{
  "type": "Feature",
  "properties": {
    "iso:country":"GB",
    "sg:address":"3 Linenhall Place",
    "sg:city":"Chester",
    "sg:classifiers":[
        {
            "category":"Professional",
            "subcategory":"Engineering",
            "type":"Services"
        }
    ],
    "sg:phone":"+44 1244 313486",
    "sg:postcode":"CH1 2LP",
    "sg:province":"Cheshire",
    "sg:tags":[
        "consulting",
        "engineer"
    ],
    "wof:name":"R P S Consultants Ltd.",
    "wof:placetype":"venue"
},
  "geometry": {"coordinates":[-2.895498991,53.1898345947],"type":"Point"}
}