{
  "type": "Feature",
  "properties": {
    "addr:full":"11 Barry Rd Kirkcaldy Fife KY2 6HY",
    "addr:housenumber":"11",
    "addr:postcode":"ky2 6hy",
    "addr:street":"Barry Rd",
    "iso:country":"GB",
    "sg:address":"11 Barry Rd",
    "sg:city":"Kirkcaldy",
    "sg:classifiers":[
        {
            "category":"Professional",
            "type":"Services"
        }
    ],
    "sg:phone":"+44 1592 261706",
    "sg:postcode":"KY2 6HY",
    "sg:province":"Fife",
    "sg:tags":[
        "entertainer"
    ],
    "wof:name":"Craig,Jimmy,",
    "wof:placetype":"venue"
},
  "geometry": {"coordinates":[-3.1788508892,56.1372947693],"type":"Point"}
}