{
  "type": "Feature",
  "properties": {
    "addr:full":"5 St John Precinct Hebburn Tyne and Wear NE31 1LG",
    "addr:housenumber":"5",
    "addr:postcode":"ne31 1lg",
    "addr:street":"St John Precinct",
    "iso:country":"GB",
    "sg:address":"5 St John Precinct",
    "sg:city":"Hebburn",
    "sg:classifiers":[
        {
            "category":"Health Services",
            "subcategory":"Optometrist",
            "type":"Services"
        }
    ],
    "sg:phone":"+44 191 483 2388",
    "sg:postcode":"NE31 1LG",
    "sg:province":"Tyne and Wear",
    "sg:tags":[
        "optician"
    ],
    "wof:name":"M Redican",
    "wof:placetype":"venue"
},
  "geometry": {"coordinates":[-1.518727,54.971348],"type":"Point"}
}