{
  "type": "Feature",
  "properties": {
    "addr:full":"45 Church Street, Padiham Burnley Lancashire BB12 8HF",
    "addr:housenumber":"45",
    "addr:postcode":"bb12 8hf",
    "addr:street":"Church Street",
    "iso:country":"GB",
    "sg:address":"45 Church Street, Padiham",
    "sg:city":"Burnley",
    "sg:classifiers":[
        {
            "category":"Health Services",
            "subcategory":"Podiatrist",
            "type":"Services"
        },
        {
            "category":"Health Services",
            "subcategory":"Chiropractor",
            "type":"Services"
        }
    ],
    "sg:phone":"+44 1282 775716",
    "sg:postcode":"BB12 8HF",
    "sg:province":"Lancashire",
    "sg:tags":[
        "podiatrists",
        "chiropodist"
    ],
    "wof:name":"A P Clark & Associates",
    "wof:placetype":"venue"
},
  "geometry": {"coordinates":[-2.318132,53.801586],"type":"Point"}
}