{
  "type": "Feature",
  "properties": {
    "iso:country":"GB",
    "sg:address":"Aultmore",
    "sg:city":"Keith",
    "sg:classifiers":[
        {
            "category":"Shopping",
            "type":"Retail Goods"
        },
        {
            "category":"Community Center",
            "type":"Public Place"
        }
    ],
    "sg:phone":"+44 1542 888001",
    "sg:postcode":"AB55 6QX",
    "sg:province":"Moray",
    "sg:tags":[
        "merchant",
        "nursery",
        "centre"
    ],
    "wof:name":"Abercairn Nurseries",
    "wof:placetype":"venue"
},
  "geometry": {"coordinates":[-2.9519190788,57.558631897],"type":"Point"}
}