{
  "type": "Feature",
  "properties": {
    "iso:country":"GB",
    "sg:address":"5 Little Essex Street",
    "sg:city":"London",
    "sg:classifiers":[
        {
            "category":"Bars & Pubs",
            "type":"Food & Drink"
        }
    ],
    "sg:phone":"+44 20 7836 2347",
    "sg:postcode":"WC2R 3LD",
    "sg:province":"Greater London",
    "sg:tags":[
        "pubs",
        "inn"
    ],
    "wof:name":"Cheshire Cheese",
    "wof:placetype":"venue"
},
  "geometry": {"coordinates":[-0.112978,51.512413],"type":"Point"}
}