{
  "type": "Feature",
  "properties": {
    "addr:full":"53a Abbotswell Road Aberdeen Aberdeen City AB12 3AD",
    "addr:housenumber":"53a",
    "addr:postcode":"ab12 3ad",
    "addr:street":"Abbotswell Road",
    "iso:country":"GB",
    "sg:address":"53a Abbotswell Road",
    "sg:city":"Aberdeen",
    "sg:classifiers":[
        {
            "category":"Building & Trades",
            "subcategory":"Pest Control",
            "type":"Services"
        }
    ],
    "sg:phone":"+44 1224 899223",
    "sg:postcode":"AB12 3AD",
    "sg:province":"Aberdeen City",
    "sg:tags":[
        "corrosion",
        "prevention"
    ],
    "wof:name":"N E C E Group Ltd.",
    "wof:placetype":"venue"
},
  "geometry": {"coordinates":[-2.096914053,57.1260910034],"type":"Point"}
}