{
  "type": "Feature",
  "properties": {
    "iso:country":"GB",
    "sg:address":"Flat 4, 32 High Pk Ho, Alexandra Rd, Elmfield",
    "sg:city":"Ryde",
    "sg:classifiers":[
        {
            "category":"Retail",
            "subcategory":"Storage",
            "type":"Services"
        }
    ],
    "sg:postcode":"PO33 1DT",
    "sg:province":"Isle of Wight",
    "sg:tags":[
        "household",
        "removal"
    ],
    "wof:name":"Blake,Graham,",
    "wof:placetype":"venue"
},
  "geometry": {"coordinates":[-1.15198,50.72134],"type":"Point"}
}