{
  "type": "Feature",
  "properties": {
    "addr:full":"768 Bristol Road South Birmingham West Midlands B31 2NN",
    "addr:housenumber":"768",
    "addr:postcode":"b31 2nn",
    "addr:street":"Bristol Road South",
    "iso:country":"GB",
    "sg:address":"768 Bristol Road South",
    "sg:city":"Birmingham",
    "sg:classifiers":[
        {
            "category":"Communications",
            "subcategory":"Film & Video Production",
            "type":"Services"
        }
    ],
    "sg:phone":"+44 121 475 5318",
    "sg:postcode":"B31 2NN",
    "sg:province":"West Midlands",
    "sg:tags":[
        "tv"
    ],
    "wof:name":"Sound & Vision",
    "wof:placetype":"venue"
},
  "geometry": {"coordinates":[-1.9703569412,52.4155693054],"type":"Point"}
}