{
  "type": "Feature",
  "properties": {
    "iso:country":"GB",
    "sg:address":"14 Town Hall Street",
    "sg:city":"Grimsby",
    "sg:classifiers":[
        {
            "category":"Organizations",
            "subcategory":"Non-profit Organization",
            "type":"Services"
        }
    ],
    "sg:phone":"+44 1472 268505",
    "sg:postcode":"DN31 1HN",
    "sg:province":"Lincolnshire",
    "sg:tags":[
        "charitable",
        "organisation",
        "voluntary",
        "charity"
    ],
    "wof:name":"COMMUNITY CHEST FURNITURE RECYCLING PROJECT",
    "wof:placetype":"venue"
},
  "geometry": {"coordinates":[-0.082479,53.565311],"type":"Point"}
}