{
  "type": "Feature",
  "properties": {
    "addr:full":"10 Halimote Road Aldershot Hampshire GU11 1NJ",
    "addr:housenumber":"10",
    "addr:postcode":"gu11 1nj",
    "addr:street":"Halimote Road",
    "iso:country":"GB",
    "sg:address":"10 Halimote Road",
    "sg:city":"Aldershot",
    "sg:classifiers":[
        {
            "category":"Retail",
            "subcategory":"Auto Rental",
            "type":"Services"
        }
    ],
    "sg:phone":"+44 1252 334633",
    "sg:postcode":"GU11 1NJ",
    "sg:province":"Hampshire",
    "sg:tags":[
        "car"
    ],
    "wof:name":"Budget Rent A Car",
    "wof:placetype":"venue"
},
  "geometry": {"coordinates":[-0.7639920115,51.2455291748],"type":"Point"}
}