{
  "type": "Feature",
  "properties": {
    "iso:country":"GB",
    "sg:address":"58 High Street",
    "sg:city":"Thornton Heath",
    "sg:classifiers":[
        {
            "category":"Health Services",
            "subcategory":"Optometrist",
            "type":"Services"
        }
    ],
    "sg:phone":"+44 20 8684 3521",
    "sg:postcode":"CR7 8LF",
    "sg:province":"Surrey",
    "sg:tags":[
        "optician"
    ],
    "wof:name":"Arthur Hayes Opticians Ltd.",
    "wof:placetype":"venue"
},
  "geometry": {"coordinates":[-0.096441,51.3988],"type":"Point"}
}