{
  "type": "Feature",
  "properties": {
    "addr:full":"2-4 Brook Street, Syston Leicester Leicestershire LE7 1GD",
    "addr:housenumber":"2-4",
    "addr:postcode":"le7 1gd",
    "addr:street":"Brook Street",
    "iso:country":"GB",
    "sg:address":"2-4 Brook Street, Syston",
    "sg:city":"Leicester",
    "sg:classifiers":[
        {
            "category":"Manufacturing",
            "subcategory":"Printing",
            "type":"Manufacturing & Wholesale Goods"
        }
    ],
    "sg:postcode":"LE7 1GD",
    "sg:province":"Leicestershire",
    "sg:tags":[
        "bookbinder"
    ],
    "wof:name":"Badminton Press",
    "wof:placetype":"venue"
},
  "geometry": {"coordinates":[-1.0778419971,52.7001571655],"type":"Point"}
}