{
  "type": "Feature",
  "properties": {
    "addr:full":"6 The Mount, Thornes Wakefield West Yorkshire WF2 8QP",
    "addr:housenumber":"6",
    "addr:postcode":"wf2 8qp",
    "addr:street":"The Mount Thornes",
    "iso:country":"GB",
    "sg:address":"6 The Mount, Thornes",
    "sg:city":"Wakefield",
    "sg:classifiers":[
        {
            "category":"Professional",
            "subcategory":"Engineering",
            "type":"Services"
        },
        {
            "category":"Professional",
            "subcategory":"Printing & Photocopies",
            "type":"Services"
        }
    ],
    "sg:phone":"+44 1924 387024",
    "sg:postcode":"WF2 8QP",
    "sg:province":"West Yorkshire",
    "sg:tags":[
        "engineeering"
    ],
    "wof:name":"Wooton Printing Services",
    "wof:placetype":"venue"
},
  "geometry": {"coordinates":[-1.5196540356,53.6692199707],"type":"Point"}
}