{
  "type": "Feature",
  "properties": {
    "addr:full":"25 Tewkesbury Avenue Pinner Greater London HA5 5LQ",
    "addr:housenumber":"25",
    "addr:postcode":"ha5 5lq",
    "addr:street":"Tewkesbury Avenue",
    "iso:country":"GB",
    "sg:address":"25 Tewkesbury Avenue",
    "sg:city":"Pinner",
    "sg:classifiers":[
        {
            "category":"Professional",
            "subcategory":"Business Services",
            "type":"Services"
        }
    ],
    "sg:phone":"+44 20 8866 1815",
    "sg:postcode":"HA5 5LQ",
    "sg:province":"Greater London",
    "sg:tags":[
        "import",
        "export",
        "agent"
    ],
    "wof:name":"G T International",
    "wof:placetype":"venue"
},
  "geometry": {"coordinates":[-0.37878,51.584206],"type":"Point"}
}