{
  "type": "Feature",
  "properties": {
    "addr:full":"18 Station Approach Virginia Water Surrey GU25 4DW",
    "addr:housenumber":"18",
    "addr:postcode":"gu25 4dw",
    "addr:street":"Station Approach;Water",
    "iso:country":"GB",
    "sg:address":"18 Station Approach",
    "sg:city":"Virginia Water",
    "sg:classifiers":[
        {
            "category":"Professional",
            "subcategory":"Lawyer & Legal Services",
            "type":"Services"
        }
    ],
    "sg:phone":"+44 1344 845969",
    "sg:postcode":"GU25 4DW",
    "sg:province":"Surrey",
    "wof:name":"Templars",
    "wof:placetype":"venue"
},
  "geometry": {"coordinates":[-0.5674020052,51.4033546448],"type":"Point"}
}