{
  "type": "Feature",
  "properties": {
    "iso:country":"GB",
    "sg:address":"Bryn Mawr Farm, Sarn",
    "sg:city":"Pwllheli",
    "sg:classifiers":[
        {
            "category":"Banks & Credit Unions",
            "subcategory":"Investment Brokerage",
            "type":"Services"
        }
    ],
    "sg:phone":"+44 1758 730642",
    "sg:postcode":"LL53 8RP",
    "sg:province":"Gwynedd",
    "sg:tags":[
        "contractor"
    ],
    "wof:name":"G Hughes",
    "wof:placetype":"venue"
},
  "geometry": {"coordinates":[-4.607307,52.872631],"type":"Point"}
}