{
  "type": "Feature",
  "properties": {
    "iso:country":"GB",
    "sg:address":"11 Belle Vue",
    "sg:city":"Whitchurch",
    "sg:classifiers":[
        {
            "category":"Building & Trades",
            "subcategory":"Construction",
            "type":"Services"
        }
    ],
    "sg:phone":"+44 1256 895868",
    "sg:postcode":"RG28 7DA",
    "sg:province":"Hampshire",
    "sg:tags":[
        "builder"
    ],
    "wof:name":"Kingston Construction",
    "wof:placetype":"venue"
},
  "geometry": {"coordinates":[-1.34012,51.231888],"type":"Point"}
}