{
  "type": "Feature",
  "properties": {
    "iso:country":"GB",
    "sg:address":"Unit 13, Winston Business Centre Chartwel",
    "sg:city":"Lancing",
    "sg:classifiers":[
        {
            "category":"Retail",
            "subcategory":"Storage",
            "type":"Services"
        }
    ],
    "sg:phone":"+44 1903 851290",
    "sg:postcode":"BN15 8TU",
    "sg:province":"West Sussex",
    "sg:tags":[
        "household",
        "removal"
    ],
    "wof:name":"Abbey Removals & Storage",
    "wof:placetype":"venue"
},
  "geometry": {"coordinates":[-0.3329629898,50.819732666],"type":"Point"}
}