{
  "type": "Feature",
  "properties": {
    "addr:full":"38 East Street Wimborne Dorset BH21 1DX",
    "addr:housenumber":"38",
    "addr:postcode":"bh21 1dx",
    "addr:street":"East Street",
    "iso:country":"GB",
    "sg:address":"38 East Street",
    "sg:city":"Wimborne",
    "sg:classifiers":[
        {
            "category":"Bars & Pubs",
            "type":"Food & Drink"
        }
    ],
    "sg:phone":"+44 1202 883464",
    "sg:postcode":"BH21 1DX",
    "sg:province":"Dorset",
    "sg:tags":[
        "pubs",
        "inn"
    ],
    "wof:name":"The Rising Sun",
    "wof:placetype":"venue"
},
  "geometry": {"coordinates":[-1.9858649969,50.7982711792],"type":"Point"}
}