{
  "type": "Feature",
  "properties": {
    "addr:full":"Oddfellows House, Shaftesbury Road Gosport Hampshire PO12 1RU",
    "addr:postcode":"po12 1ru",
    "addr:street":"Shaftesbury Road",
    "iso:country":"GB",
    "sg:address":"Oddfellows House, Shaftesbury Road",
    "sg:city":"Gosport",
    "sg:classifiers":[
        {
            "category":"Manufacturing",
            "subcategory":"Tools & Machinery",
            "type":"Manufacturing & Wholesale Goods"
        }
    ],
    "sg:phone":"+44 23 9242 2382",
    "sg:postcode":"PO12 1RU",
    "sg:province":"Hampshire",
    "sg:tags":[
        "society",
        "friendly"
    ],
    "wof:name":"Lord Nelson Lodge",
    "wof:placetype":"venue"
},
  "geometry": {"coordinates":[-1.134569,50.79303],"type":"Point"}
}