{
  "type": "Feature",
  "properties": {
    "addr:full":"88 Caldbeck Av Worcester Park Surrey KT4 8BH",
    "addr:housenumber":"88",
    "addr:postcode":"kt4 8bh",
    "addr:street":"Caldbeck Av Worcester Park",
    "iso:country":"GB",
    "sg:address":"88 Caldbeck Av",
    "sg:city":"Worcester Park",
    "sg:classifiers":[
        {
            "category":"Bakery",
            "type":"Food & Drink"
        }
    ],
    "sg:phone":"+44 20 8330 6619",
    "sg:postcode":"KT4 8BH",
    "sg:province":"Surrey",
    "sg:tags":[
        "cake",
        "maker"
    ],
    "wof:name":"Ann's Celebration Cakes",
    "wof:placetype":"venue"
},
  "geometry": {"coordinates":[-0.2392529994,51.381111145],"type":"Point"}
}