{
  "type": "Feature",
  "properties": {
    "iso:country":"GB",
    "sg:address":"27 High Street",
    "sg:city":"Lingfield",
    "sg:classifiers":[
        {
            "category":"Real Estate",
            "subcategory":"Surveying",
            "type":"Services"
        },
        {
            "category":"Real Estate",
            "subcategory":"Real Estate Agent",
            "type":"Services"
        }
    ],
    "sg:phone":"+44 1342 836166",
    "sg:postcode":"RH7 6AA",
    "sg:province":"Surrey",
    "sg:tags":[
        "surveyor",
        "valuer"
    ],
    "wof:name":"Haven Management Ltd.",
    "wof:placetype":"venue"
},
  "geometry": {"coordinates":[-0.0172719993,51.1745491028],"type":"Point"}
}