{
  "type": "Feature",
  "properties": {
    "addr:full":"54 Kneller Gardens Isleworth Greater London TW7 7NW",
    "addr:housenumber":"54",
    "addr:postcode":"tw7 7nw",
    "addr:street":"Kneller Gardens",
    "iso:country":"GB",
    "sg:address":"54 Kneller Gardens",
    "sg:city":"Isleworth",
    "sg:classifiers":[
        {
            "category":"Building & Trades",
            "subcategory":"Construction",
            "type":"Services"
        }
    ],
    "sg:postcode":"TW7 7NW",
    "sg:province":"Greater London",
    "sg:tags":[
        "builder"
    ],
    "wof:name":"V P Hearn Builders",
    "wof:placetype":"venue"
},
  "geometry": {"coordinates":[-0.351935,51.456993],"type":"Point"}
}