{
  "type": "Feature",
  "properties": {
    "iso:country":"GB",
    "sg:address":"6 Jordanthorpe Centre",
    "sg:city":"Sheffield",
    "sg:classifiers":[
        {
            "category":"Food & Beverages",
            "subcategory":"Bakery",
            "type":"Retail Goods"
        }
    ],
    "sg:phone":"+44 114 237 8507",
    "sg:postcode":"S8 8DX",
    "sg:province":"Derbyshire",
    "sg:tags":[
        "baker"
    ],
    "wof:name":"Woodthorpe Bakery",
    "wof:placetype":"venue"
},
  "geometry": {"coordinates":[-1.458536,53.322041],"type":"Point"}
}