{
  "type": "Feature",
  "properties": {
    "addr:full":"54 Ballingdon Street Sudbury Essex CO10 2BZ",
    "addr:housenumber":"54",
    "addr:postcode":"co10 2bz",
    "addr:street":"Ballingdon Street",
    "iso:country":"GB",
    "sg:address":"54 Ballingdon Street",
    "sg:city":"Sudbury",
    "sg:classifiers":[
        {
            "category":"Shopping",
            "subcategory":"Antiques",
            "type":"Retail Goods"
        }
    ],
    "sg:phone":"+44 1787 373800",
    "sg:postcode":"CO10 2BZ",
    "sg:province":"Essex",
    "wof:name":"E G & M F ANTIQUES",
    "wof:placetype":"venue"
},
  "geometry": {"coordinates":[0.7163019776,52.033782959],"type":"Point"}
}