{
  "type": "Feature",
  "properties": {
    "addr:full":"6 Thurlow Street Salford Greater Manchester M5 2UX",
    "addr:housenumber":"6",
    "addr:postcode":"m5 2ux",
    "addr:street":"Thurlow Street",
    "iso:country":"GB",
    "sg:address":"6 Thurlow Street",
    "sg:city":"Salford",
    "sg:classifiers":[
        {
            "category":"Manufacturing",
            "subcategory":"Metals",
            "type":"Manufacturing & Wholesale Goods"
        }
    ],
    "sg:phone":"+44 161 736 0526",
    "sg:postcode":"M5 2UX",
    "sg:province":"Greater Manchester",
    "sg:tags":[
        "die-casting"
    ],
    "wof:name":"Goliath Threading Tools",
    "wof:placetype":"venue"
},
  "geometry": {"coordinates":[-2.2890570164,53.4793891907],"type":"Point"}
}