{
  "type": "Feature",
  "properties": {
    "iso:country":"GB",
    "sg:address":"90 Richmond Road, Hackney",
    "sg:city":"London",
    "sg:classifiers":[
        {
            "category":"Government",
            "subcategory":"Customs House",
            "type":"Public Place"
        }
    ],
    "sg:postcode":"E8 3HW",
    "sg:province":"Greater London",
    "sg:tags":[
        "clearance"
    ],
    "wof:name":"A Better Clearance",
    "wof:placetype":"venue"
},
  "geometry": {"coordinates":[-0.069706,51.542931],"type":"Point"}
}