{
  "type": "Feature",
  "properties": {
    "addr:full":"41 Grosvenor Drive Hornchurch Essex RM11 1PH",
    "addr:housenumber":"41",
    "addr:postcode":"rm11 1ph",
    "addr:street":"Grosvenor Drive",
    "iso:country":"GB",
    "sg:address":"41 Grosvenor Drive",
    "sg:city":"Hornchurch",
    "sg:classifiers":[
        {
            "category":"Building & Trades",
            "subcategory":"Construction",
            "type":"Services"
        }
    ],
    "sg:phone":"+44 1708 443873",
    "sg:postcode":"RM11 1PH",
    "sg:province":"Essex",
    "sg:tags":[
        "builder"
    ],
    "wof:name":"Havering Building & Joinery Co.",
    "wof:placetype":"venue"
},
  "geometry": {"coordinates":[0.208746,51.565468],"type":"Point"}
}