{
  "type": "Feature",
  "properties": {
    "iso:country":"GB",
    "sg:address":"245 Glasgow Road, Rutherglen",
    "sg:city":"Glasgow",
    "sg:classifiers":[
        {
            "category":"Retail",
            "subcategory":"Auto Rental",
            "type":"Services"
        }
    ],
    "sg:phone":"+44 141 613 0044",
    "sg:postcode":"G73 1SU",
    "sg:province":"Glasgow City",
    "sg:tags":[
        "car",
        "vehicle"
    ],
    "wof:name":"Enterprise Rent A Car",
    "wof:placetype":"venue"
},
  "geometry": {"coordinates":[-4.227869,55.838997],"type":"Point"}
}