{
  "type": "Feature",
  "properties": {
    "addr:full":"York Clinic Crofton House Woking Surrey GU22 0ES",
    "addr:postcode":"gu22 0es",
    "iso:country":"GB",
    "sg:address":"York Clinic Crofton House",
    "sg:city":"Woking",
    "sg:classifiers":[
        {
            "category":"Shopping",
            "subcategory":"Pharmacy",
            "type":"Retail Goods"
        }
    ],
    "sg:phone":"+44 1483 720464",
    "sg:postcode":"GU22 0ES",
    "sg:province":"Surrey",
    "sg:tags":[
        "medicine",
        "therapy"
    ],
    "wof:name":"The Natural Health York Clinic",
    "wof:placetype":"venue"
},
  "geometry": {"coordinates":[-0.5725589991,51.2967567444],"type":"Point"}
}