{
  "type": "Feature",
  "properties": {
    "addr:full":"Meikleholmside Cottage, Annan Water Moffat Dumfries and Galloway DG10 9LS",
    "addr:postcode":"dg10 9ls",
    "addr:street":"Annan;Moffat",
    "iso:country":"GB",
    "sg:address":"Meikleholmside Cottage, Annan Water",
    "sg:city":"Moffat",
    "sg:classifiers":[
        {
            "category":"Personal",
            "subcategory":"Beauty Salon",
            "type":"Services"
        },
        {
            "category":"Personal",
            "subcategory":"Barber",
            "type":"Services"
        },
        {
            "category":"Real Estate",
            "subcategory":"Architect",
            "type":"Services"
        }
    ],
    "sg:phone":"+44 1683 221898",
    "sg:postcode":"DG10 9LS",
    "sg:province":"Dumfries and Galloway",
    "sg:tags":[
        "unisex",
        "hairdresser"
    ],
    "wof:name":"WHITE HILL DESIGN STUDIO LLP",
    "wof:placetype":"venue"
},
  "geometry": {"coordinates":[-3.4455990791,55.335193634],"type":"Point"}
}