{
  "type": "Feature",
  "properties": {
    "iso:country":"GB",
    "sg:address":"Cranford, Church End, Albury",
    "sg:city":"Much Hadham",
    "sg:classifiers":[
        {
            "category":"Professional",
            "subcategory":"Engineering",
            "type":"Services"
        },
        {
            "category":"Building & Trades",
            "subcategory":"Electrical",
            "type":"Services"
        }
    ],
    "sg:postcode":"SG11 2JG",
    "sg:province":"Hertfordshire",
    "sg:tags":[
        "engineer",
        "electrician",
        "contractor"
    ],
    "wof:name":"S J & A D Brace",
    "wof:placetype":"venue"
},
  "geometry": {"coordinates":[0.0835980028,51.9023017883],"type":"Point"}
}