{
  "type": "Feature",
  "properties": {
    "iso:country":"GB",
    "sg:address":"87 Regent Street",
    "sg:city":"London",
    "sg:classifiers":[
        {
            "category":"Arts & Performance",
            "subcategory":"Theater",
            "type":"Entertainment"
        }
    ],
    "sg:phone":"+44 20 7734 7505",
    "sg:postcode":"W1B 4EH",
    "sg:province":"Greater London",
    "sg:tags":[
        "theatrical",
        "agency"
    ],
    "wof:name":"Elena Gilbert",
    "wof:placetype":"venue"
},
  "geometry": {"coordinates":[-0.137427,51.509846],"type":"Point"}
}