{
  "type": "Feature",
  "properties": {
    "iso:country":"GB",
    "sg:address":"Stream Close, High Road, Byfleet",
    "sg:city":"West Byfleet",
    "sg:classifiers":[
        {
            "category":"Social Services",
            "subcategory":"Adult Care",
            "type":"Services"
        },
        {
            "category":"Government",
            "subcategory":"Office",
            "type":"Public Place"
        }
    ],
    "sg:phone":"+44 1932 353575",
    "sg:postcode":"KT14 7LZ",
    "sg:province":"Surrey",
    "sg:tags":[
        "local",
        "day",
        "centre"
    ],
    "wof:name":"St. Marys Day Centre",
    "wof:placetype":"venue"
},
  "geometry": {"coordinates":[-0.479817,51.338749],"type":"Point"}
}