{
  "type": "Feature",
  "properties": {
    "iso:country":"GB",
    "sg:address":"483 Bramford Lane",
    "sg:city":"Ipswich",
    "sg:classifiers":[
        {
            "category":"Food & Beverages",
            "subcategory":"Meat & Fish",
            "type":"Retail Goods"
        }
    ],
    "sg:postcode":"IP1 5JQ",
    "sg:province":"Suffolk",
    "sg:tags":[
        "chip"
    ],
    "wof:name":"Jumbo Fish Bar",
    "wof:placetype":"venue"
},
  "geometry": {"coordinates":[1.122365,52.071484],"type":"Point"}
}