{
  "type": "Feature",
  "properties": {
    "addr:full":"Ryton Grange, Ryton Malton North Yorkshire YO17 0RY",
    "addr:postcode":"yo17 0ry",
    "iso:country":"GB",
    "sg:address":"Ryton Grange, Ryton",
    "sg:city":"Malton",
    "sg:classifiers":[
        {
            "category":"Shopping",
            "subcategory":"Antiques",
            "type":"Retail Goods"
        }
    ],
    "sg:postcode":"YO17 0RY",
    "sg:province":"North Yorkshire",
    "wof:name":"Nicholas Brooksbank",
    "wof:placetype":"venue"
},
  "geometry": {"coordinates":[-0.800224,54.137825],"type":"Point"}
}