{
  "type": "Feature",
  "properties": {
    "addr:full":"Colebrook Court, Sloane Avenue London Greater London SW3 3DJ",
    "addr:postcode":"sw3 3dj",
    "addr:street":"Colebrook Court Sloane Avenue",
    "iso:country":"GB",
    "sg:address":"Colebrook Court, Sloane Avenue",
    "sg:city":"London",
    "sg:classifiers":[
        {
            "category":"Autos & Motor Vehicles",
            "subcategory":"Automobile Sales",
            "type":"Retail Goods"
        }
    ],
    "sg:phone":"+44 20 7581 3427",
    "sg:postcode":"SW3 3DJ",
    "sg:province":"Greater London",
    "sg:tags":[
        "car"
    ],
    "wof:name":"Roundabout Chelsea",
    "wof:placetype":"venue"
},
  "geometry": {"coordinates":[-0.1665640026,51.4921836853],"type":"Point"}
}