{
  "type": "Feature",
  "properties": {
    "addr:full":"High Fernley Farm, Wyke Bradford West Yorkshire BD12 8EX",
    "addr:housenumber":"wyke bradford",
    "addr:postcode":"bd12 8ex",
    "addr:street":"West Yorkshire",
    "iso:country":"GB",
    "sg:address":"High Fernley Farm, Wyke",
    "sg:city":"Bradford",
    "sg:classifiers":[
        {
            "category":"Farming",
            "subcategory":"Livestock Farm",
            "type":"Manufacturing & Wholesale Goods"
        }
    ],
    "sg:phone":"+44 1274 679242",
    "sg:postcode":"BD12 8EX",
    "sg:province":"West Yorkshire",
    "sg:tags":[
        "others"
    ],
    "wof:name":"E Safianyk",
    "wof:placetype":"venue"
},
  "geometry": {"coordinates":[-1.758306,53.795738],"type":"Point"}
}