{
  "type": "Feature",
  "properties": {
    "iso:country":"GB",
    "sg:address":"Victoria Drive",
    "sg:city":"Llandudno Junction",
    "sg:classifiers":[
        {
            "category":"Organizations",
            "subcategory":"Membership Organization",
            "type":"Services"
        }
    ],
    "sg:phone":"+44 1492 581314",
    "sg:postcode":"LL31 9PG",
    "sg:province":"Conwy",
    "sg:tags":[
        "club"
    ],
    "wof:name":"Hotpoint Social Club",
    "wof:placetype":"venue"
},
  "geometry": {"coordinates":[-3.811144,53.293365],"type":"Point"}
}