{
  "type": "Feature",
  "properties": {
    "iso:country":"GB",
    "sg:address":"Building 521, Heathrow Airport London",
    "sg:city":"Hounslow",
    "sg:classifiers":[
        {
            "category":"Freight",
            "type":"Transportation"
        }
    ],
    "sg:phone":"+44 20 8759 4439",
    "sg:postcode":"TW6 2JH",
    "sg:province":"Greater London",
    "sg:tags":[
        "forwarders"
    ],
    "wof:name":"Patel Air Services",
    "wof:placetype":"venue"
},
  "geometry": {"coordinates":[-0.4288400114,51.4738082886],"type":"Point"}
}