{
  "type": "Feature",
  "properties": {
    "iso:country":"GB",
    "sg:address":"Office, Mays Av",
    "sg:city":"Cambridge",
    "sg:classifiers":[
        {
            "category":"Social Services",
            "subcategory":"Adult Care",
            "type":"Services"
        }
    ],
    "sg:phone":"+44 1223 891842",
    "sg:postcode":"CB1 6ER",
    "sg:province":"Cambridgeshire",
    "sg:tags":[
        "housing",
        "sheltered"
    ],
    "wof:name":"Mays Avenue Sheltered Housing",
    "wof:placetype":"venue"
},
  "geometry": {"coordinates":[0.31352,52.132702],"type":"Point"}
}