{
  "type": "Feature",
  "properties": {
    "iso:country":"GB",
    "sg:address":"St Johns Court, St Johns Street",
    "sg:city":"Lichfield",
    "sg:classifiers":[
        {
            "category":"Professional",
            "type":"Services"
        }
    ],
    "sg:phone":"+44 1543 256700",
    "sg:postcode":"WS14 9DS",
    "sg:province":"Staffordshire",
    "sg:tags":[
        "repair",
        "tech",
        "maintenance"
    ],
    "wof:name":"Discus Systems Plc",
    "wof:placetype":"venue"
},
  "geometry": {"coordinates":[-1.825809,52.678425],"type":"Point"}
}