{
  "type": "Feature",
  "properties": {
    "iso:country":"GB",
    "sg:address":"Old School Ho, Front St",
    "sg:city":"Rotherham",
    "sg:classifiers":[
        {
            "category":"Community Center",
            "subcategory":"Youth",
            "type":"Public Place"
        }
    ],
    "sg:phone":"+44 114 269 5053",
    "sg:postcode":"S60 5QP",
    "sg:province":"South Yorkshire",
    "sg:tags":[
        "organisation",
        "centre"
    ],
    "wof:name":"Treeton Youth Enterprise Centre",
    "wof:placetype":"venue"
},
  "geometry": {"coordinates":[-1.360005,53.393051],"type":"Point"}
}