{
  "type": "Feature",
  "properties": {
    "iso:country":"GB",
    "sg:address":"33 Ainsdale Dr",
    "sg:city":"Peterborough",
    "sg:classifiers":[
        {
            "category":"Education",
            "subcategory":"Special Training",
            "type":"Public Place"
        }
    ],
    "sg:phone":"+44 70 5060 7608",
    "sg:postcode":"PE4 6RL",
    "sg:province":"Cambridgeshire",
    "sg:tags":[
        "product",
        "centre"
    ],
    "wof:name":"Professional Software Training",
    "wof:placetype":"venue"
},
  "geometry": {"coordinates":[-0.2734340131,52.6169548035],"type":"Point"}
}