{
  "type": "Feature",
  "properties": {
    "iso:country":"GB",
    "sg:address":"21 Bedford Sq",
    "sg:city":"Brighton",
    "sg:classifiers":[
        {
            "category":"Professional",
            "subcategory":"Computer Services",
            "type":"Services"
        }
    ],
    "sg:phone":"+44 1273 821084",
    "sg:postcode":"BN1 2PL",
    "sg:province":"East Sussex",
    "sg:tags":[
        "consultant"
    ],
    "wof:name":"Caunce,Graham N,",
    "wof:placetype":"venue"
},
  "geometry": {"coordinates":[-0.1539790034,50.8232345581],"type":"Point"}
}