{
  "type": "Feature",
  "properties": {
    "addr:full":"26 Moor Lane, Amington Tamworth Staffordshire B77 3AU",
    "addr:housenumber":"26",
    "addr:postcode":"b77 3au",
    "addr:street":"Moor Lane",
    "iso:country":"GB",
    "sg:address":"26 Moor Lane, Amington",
    "sg:city":"Tamworth",
    "sg:classifiers":[
        {
            "category":"Farming",
            "subcategory":"Nursery",
            "type":"Manufacturing & Wholesale Goods"
        },
        {
            "category":"Education",
            "subcategory":"Preschool",
            "type":"Public Place"
        },
        {
            "category":"Government",
            "subcategory":"Office",
            "type":"Public Place"
        }
    ],
    "sg:phone":"+44 1827 64925",
    "sg:postcode":"B77 3AU",
    "sg:province":"Staffordshire",
    "sg:tags":[
        "school",
        "agency",
        "creche",
        "authority"
    ],
    "wof:name":"Amington Green Nursery School",
    "wof:placetype":"venue"
},
  "geometry": {"coordinates":[-1.660024,52.639912],"type":"Point"}
}