{
  "type": "Feature",
  "properties": {
    "addr:full":"5 Cromwell Place London Greater London SW7 2JE",
    "addr:housenumber":"5",
    "addr:postcode":"sw7 2je",
    "addr:street":"Cromwell Place",
    "iso:country":"GB",
    "sg:address":"5 Cromwell Place",
    "sg:city":"London",
    "sg:classifiers":[
        {
            "category":"Banks & Credit Unions",
            "subcategory":"Investment Brokerage",
            "type":"Services"
        }
    ],
    "sg:phone":"+44 20 7584 4996",
    "sg:postcode":"SW7 2JE",
    "sg:province":"Greater London",
    "wof:name":"Shamrock Partners",
    "wof:placetype":"venue"
},
  "geometry": {"coordinates":[-0.174789,51.495438],"type":"Point"}
}