{
  "type": "Feature",
  "properties": {
    "addr:full":"327 Babbacombe Road Torquay Devon TQ1 3TB",
    "addr:housenumber":"327",
    "addr:postcode":"tq1 3tb",
    "addr:street":"Babbacombe Road",
    "iso:country":"GB",
    "sg:address":"327 Babbacombe Road",
    "sg:city":"Torquay",
    "sg:classifiers":[
        {
            "category":"Travel",
            "subcategory":"Hotels & Motels",
            "type":"Entertainment"
        }
    ],
    "sg:phone":"+44 1803 293674",
    "sg:postcode":"TQ1 3TB",
    "sg:province":"Devon",
    "wof:name":"Anstey's Cove",
    "wof:placetype":"venue"
},
  "geometry": {"coordinates":[-3.506849,50.473278],"type":"Point"}
}