{
  "type": "Feature",
  "properties": {
    "addr:full":"80 Wellington Road, Bollington Macclesfield Cheshire SK10 5HT",
    "addr:housenumber":"80",
    "addr:postcode":"sk10 5ht",
    "addr:street":"Wellington Road",
    "iso:country":"GB",
    "sg:address":"80 Wellington Road, Bollington",
    "sg:city":"Macclesfield",
    "sg:classifiers":[
        {
            "category":"Manufacturing",
            "subcategory":"Signs",
            "type":"Manufacturing & Wholesale Goods"
        }
    ],
    "sg:phone":"+44 1625 573820",
    "sg:postcode":"SK10 5HT",
    "sg:province":"Cheshire",
    "sg:tags":[
        "supplier",
        "maker",
        "nameplate"
    ],
    "wof:name":"B & B Signs",
    "wof:placetype":"venue"
},
  "geometry": {"coordinates":[-2.1087200642,53.2955856323],"type":"Point"}
}