{
  "type": "Feature",
  "properties": {
    "iso:country":"GB",
    "sg:address":"177 Tuckton Road",
    "sg:city":"Bournemouth",
    "sg:classifiers":[
        {
            "category":"Retail",
            "subcategory":"Repair Shop",
            "type":"Services"
        }
    ],
    "sg:phone":"+44 1202 429077",
    "sg:postcode":"BH6 3LA",
    "sg:province":"Dorset",
    "sg:tags":[
        "radio",
        "television",
        "video"
    ],
    "wof:name":"Jarvis Radio",
    "wof:placetype":"venue"
},
  "geometry": {"coordinates":[-1.7922229767,50.7285766602],"type":"Point"}
}