{
  "type": "Feature",
  "properties": {
    "iso:country":"GB",
    "sg:address":"Kilve, Viewdales Close, Hulland Ward",
    "sg:city":"Ashbourne",
    "sg:classifiers":[
        {
            "category":"Professional",
            "subcategory":"Art Services",
            "type":"Services"
        }
    ],
    "sg:postcode":"DE6 3EB",
    "sg:province":"Derbyshire",
    "sg:tags":[
        "photographer"
    ],
    "wof:name":"David John Holbur",
    "wof:placetype":"venue"
},
  "geometry": {"coordinates":[-1.620424,53.02042],"type":"Point"}
}