{
  "type": "Feature",
  "properties": {
    "iso:country":"GB",
    "sg:address":"10 Mutton La",
    "sg:city":"Potters Bar",
    "sg:classifiers":[
        {
            "category":"Shopping",
            "type":"Retail Goods"
        }
    ],
    "sg:phone":"+44 1707 650351",
    "sg:postcode":"EN6 2PA",
    "sg:province":"Greater London",
    "sg:tags":[
        "part",
        "accessory"
    ],
    "wof:name":"Potters Bar Motor Accessories",
    "wof:placetype":"venue"
},
  "geometry": {"coordinates":[-0.179703,51.692249],"type":"Point"}
}