{
  "type": "Feature",
  "properties": {
    "iso:country":"GB",
    "sg:address":"164 Wilmslow Road, Handforth",
    "sg:city":"Wilmslow",
    "sg:classifiers":[
        {
            "category":"Health Services",
            "subcategory":"Dentist",
            "type":"Services"
        }
    ],
    "sg:postcode":"SK9 3LF",
    "sg:province":"Cheshire",
    "wof:name":"Laburnum Dental Practice",
    "wof:placetype":"venue"
},
  "geometry": {"coordinates":[-2.215279,53.347279],"type":"Point"}
}