{
  "type": "Feature",
  "properties": {
    "addr:full":"151 Osborne Road North Southampton Hampshire SO17 2FH",
    "addr:housenumber":"151",
    "addr:postcode":"so17 2fh",
    "addr:street":"Osborne Road North",
    "iso:country":"GB",
    "sg:address":"151 Osborne Road North",
    "sg:city":"Southampton",
    "sg:classifiers":[
        {
            "category":"Professional",
            "subcategory":"Engineering",
            "type":"Services"
        }
    ],
    "sg:phone":"+44 23 8058 5338",
    "sg:postcode":"SO17 2FH",
    "sg:province":"Hampshire",
    "sg:tags":[
        "contractor",
        "electrical",
        "engineer"
    ],
    "wof:name":"P Stickland",
    "wof:placetype":"venue"
},
  "geometry": {"coordinates":[-1.386895,50.926365],"type":"Point"}
}