{
  "type": "Feature",
  "properties": {
    "iso:country":"GB",
    "sg:address":"Chagford",
    "sg:city":"Newton Abbot",
    "sg:classifiers":[
        {
            "category":"Travel",
            "subcategory":"Hotels & Motels",
            "type":"Entertainment"
        }
    ],
    "sg:phone":"+44 1647 433297",
    "sg:postcode":"TQ13 8EY",
    "sg:province":"Devon",
    "wof:name":"Thornworthy House",
    "wof:placetype":"venue"
},
  "geometry": {"coordinates":[-3.88154,50.650391],"type":"Point"}
}