{
  "type": "Feature",
  "properties": {
    "iso:country":"GB",
    "sg:address":"Stepside Manor, Gwbert Road",
    "sg:city":"Cardigan",
    "sg:classifiers":[
        {
            "category":"Farming",
            "subcategory":"Livestock Farm",
            "type":"Manufacturing & Wholesale Goods"
        }
    ],
    "sg:phone":"+44 1239 613741",
    "sg:postcode":"SA43 1PH",
    "sg:province":"Ceredigion",
    "sg:tags":[
        "others"
    ],
    "wof:name":"G R James & Sons",
    "wof:placetype":"venue"
},
  "geometry": {"coordinates":[-4.655044,52.086868],"type":"Point"}
}