{
  "type": "Feature",
  "properties": {
    "iso:country":"GB",
    "sg:address":"47-49 Cardiff Road",
    "sg:city":"Dinas Powys",
    "sg:classifiers":[
        {
            "category":"Shopping",
            "subcategory":"News",
            "type":"Retail Goods"
        }
    ],
    "sg:phone":"+44 29 2051 5967",
    "sg:postcode":"CF64 4JS",
    "sg:province":"The Vale of Glamorgan",
    "sg:tags":[
        "newsagent"
    ],
    "wof:name":"Dillons Newsagents Ltd.",
    "wof:placetype":"venue"
},
  "geometry": {"coordinates":[-3.215452,51.433842],"type":"Point"}
}