{
  "type": "Feature",
  "properties": {
    "addr:full":"Over Holme, Main Road, Cutthorpe Chesterfield Derbyshire S42 7AG",
    "addr:postcode":"s42 7ag",
    "addr:street":"Over Holme Main Road Cutthorpe",
    "iso:country":"GB",
    "sg:address":"Over Holme, Main Road, Cutthorpe",
    "sg:city":"Chesterfield",
    "sg:classifiers":[
        {
            "category":"Professional",
            "subcategory":"Management & Consulting",
            "type":"Services"
        }
    ],
    "sg:postcode":"S42 7AG",
    "sg:province":"Derbyshire",
    "sg:tags":[
        "consultant",
        "business"
    ],
    "wof:name":"Applewoods",
    "wof:placetype":"venue"
},
  "geometry": {"coordinates":[-1.4859440327,53.2572402954],"type":"Point"}
}