{
  "type": "Feature",
  "properties": {
    "addr:full":"St Thomas's Church Hall, Hotham Rd Hull East Riding of Yorkshire HU5 5LG",
    "addr:postcode":"hu5 5lg",
    "addr:street":"St;Hotham Rd",
    "iso:country":"GB",
    "sg:address":"St Thomas's Church Hall, Hotham Rd",
    "sg:city":"Hull",
    "sg:classifiers":[
        {
            "category":"Personal",
            "type":"Services"
        }
    ],
    "sg:phone":"+44 1482 823032",
    "sg:postcode":"HU5 5LG",
    "sg:province":"East Riding of Yorkshire",
    "sg:tags":[
        "slimming",
        "product"
    ],
    "wof:name":"Slimming World",
    "wof:placetype":"venue"
},
  "geometry": {"coordinates":[-0.4155400097,53.7540397644],"type":"Point"}
}