{
  "type": "Feature",
  "properties": {
    "iso:country":"GB",
    "sg:address":"97 High Street, Biddulph",
    "sg:city":"Stoke-on-trent",
    "sg:classifiers":[
        {
            "category":"Real Estate",
            "subcategory":"Real Estate Agent",
            "type":"Services"
        }
    ],
    "sg:phone":"+44 1782 510374",
    "sg:postcode":"ST8 6AA",
    "sg:province":"Staffordshire",
    "wof:name":"Britannia Estate Agents",
    "wof:placetype":"venue"
},
  "geometry": {"coordinates":[-2.176179,53.115231],"type":"Point"}
}