{
  "type": "Feature",
  "properties": {
    "addr:full":"Sunley Tower, Picaddiliy Plaza 28th Floor Manchester Greater Manchester M1 4BW",
    "addr:housenumber":"28th floor",
    "addr:postcode":"m1 4bw",
    "addr:street":"Manchester",
    "iso:country":"GB",
    "sg:address":"Sunley Tower, Picaddiliy Plaza 28th Floor",
    "sg:city":"Manchester",
    "sg:classifiers":[
        {
            "category":"Education",
            "subcategory":"Special Training",
            "type":"Public Place"
        }
    ],
    "sg:phone":"+44 161 228 3607",
    "sg:postcode":"M1 4BW",
    "sg:province":"Greater Manchester",
    "sg:tags":[
        "school",
        "language"
    ],
    "wof:name":"Orient Direct Ltd.",
    "wof:placetype":"venue"
},
  "geometry": {"coordinates":[-2.2402501106,53.4784011841],"type":"Point"}
}