{
  "type": "Feature",
  "properties": {
    "addr:full":"Ferry Lane, North Kyme Lincoln Lincolnshire LN4 4DQ",
    "addr:postcode":"ln4 4dq",
    "addr:street":"Ferry Lane",
    "iso:country":"GB",
    "sg:address":"Ferry Lane, North Kyme",
    "sg:city":"Lincoln",
    "sg:classifiers":[
        {
            "category":"Building & Trades",
            "subcategory":"Construction",
            "type":"Services"
        }
    ],
    "sg:phone":"+44 1526 860785",
    "sg:postcode":"LN4 4DQ",
    "sg:province":"Lincolnshire",
    "sg:tags":[
        "builder"
    ],
    "wof:name":"A Twigg",
    "wof:placetype":"venue"
},
  "geometry": {"coordinates":[-0.278542012,53.0466957092],"type":"Point"}
}