{
  "type": "Feature",
  "properties": {
    "addr:full":"Unit 2/4 Westfield Close, Rawreth Industrial Estat Rayleigh Essex SS6 9RL",
    "addr:housenumber":"unit 2 / 4",
    "addr:postcode":"ss6 9rl",
    "addr:street":"Westfield Close;Estat Rayleigh",
    "iso:country":"GB",
    "sg:address":"Unit 2/4 Westfield Close, Rawreth Industrial Estat",
    "sg:city":"Rayleigh",
    "sg:classifiers":[
        {
            "category":"Building & Trades",
            "subcategory":"Construction",
            "type":"Services"
        }
    ],
    "sg:phone":"+44 1268 782817",
    "sg:postcode":"SS6 9RL",
    "sg:province":"Essex",
    "sg:tags":[
        "joiner",
        "carpenter"
    ],
    "wof:name":"Parkrose Builders Ltd.",
    "wof:placetype":"venue"
},
  "geometry": {"coordinates":[0.591778,51.60281],"type":"Point"}
}