{
  "type": "Feature",
  "properties": {
    "iso:country":"GB",
    "sg:address":"Clachan",
    "sg:city":"Cairndow",
    "sg:classifiers":[
        {
            "category":"Home & Garden",
            "subcategory":"Carpets & Floor Coverings",
            "type":"Retail Goods"
        }
    ],
    "sg:phone":"+44 1499 600233",
    "sg:postcode":"PA26 8BL",
    "sg:province":"Argyll and Bute",
    "sg:tags":[
        "carpets",
        "rug",
        "matting"
    ],
    "wof:name":"Gordon's Carpet Centre",
    "wof:placetype":"venue"
},
  "geometry": {"coordinates":[-4.939461,56.25383],"type":"Point"}
}