{
  "type": "Feature",
  "properties": {
    "addr:full":"235 Kent House Road Beckenham Kent BR3 1JQ",
    "addr:housenumber":"235",
    "addr:postcode":"br3 1jq",
    "addr:street":"Kent House Road",
    "iso:country":"GB",
    "sg:address":"235 Kent House Road",
    "sg:city":"Beckenham",
    "sg:classifiers":[
        {
            "category":"Building & Trades",
            "subcategory":"Construction",
            "type":"Services"
        }
    ],
    "sg:phone":"+44 20 8659 6474",
    "sg:postcode":"BR3 1JQ",
    "sg:province":"Kent",
    "sg:tags":[
        "decorator",
        "painter"
    ],
    "wof:name":"Kent Industrial Decorating Services",
    "wof:placetype":"venue"
},
  "geometry": {"coordinates":[-0.0441740006,51.4172019958],"type":"Point"}
}