{
  "type": "Feature",
  "properties": {
    "iso:country":"GB",
    "sg:address":"52 Frimley Drive",
    "sg:city":"Bradford",
    "sg:classifiers":[
        {
            "category":"Building & Trades",
            "subcategory":"Construction",
            "type":"Services"
        }
    ],
    "sg:phone":"+44 1274 579147",
    "sg:postcode":"BD5 9EP",
    "sg:province":"West Yorkshire",
    "sg:tags":[
        "builder"
    ],
    "wof:name":"Home Extensions & Property Repairs",
    "wof:placetype":"venue"
},
  "geometry": {"coordinates":[-1.77302,53.774632],"type":"Point"}
}