{
  "type": "Feature",
  "properties": {
    "iso:country":"GB",
    "sg:address":"36 Franklin Rd",
    "sg:city":"Birmingham",
    "sg:classifiers":[
        {
            "category":"Professional",
            "subcategory":"Accounting & Tax Preparation",
            "type":"Services"
        }
    ],
    "sg:phone":"+44 121 459 4646",
    "sg:postcode":"B30 2HG",
    "sg:province":"West Midlands",
    "sg:tags":[
        "accountant"
    ],
    "wof:name":"Price Bradshaw Whitehouse & Co",
    "wof:placetype":"venue"
},
  "geometry": {"coordinates":[-1.9291199446,52.4244308472],"type":"Point"}
}