{
  "type": "Feature",
  "properties": {
    "iso:country":"GB",
    "sg:address":"1 Lower Hardwick Street",
    "sg:city":"Buxton",
    "sg:classifiers":[
        {
            "category":"Restaurant",
            "type":"Food & Drink"
        }
    ],
    "sg:phone":"+44 1298 77822",
    "sg:postcode":"SK17 6DQ",
    "sg:province":"Derbyshire",
    "sg:tags":[
        "chinese"
    ],
    "wof:name":"Kwei Lin",
    "wof:placetype":"venue"
},
  "geometry": {"coordinates":[-1.9118349552,53.2586135864],"type":"Point"}
}