{
  "type": "Feature",
  "properties": {
    "addr:full":"17 Mill St Bridgnorth Shropshire WV15 5AF",
    "addr:housenumber":"17",
    "addr:postcode":"wv15 5af",
    "addr:street":"Mill St",
    "iso:country":"GB",
    "sg:address":"17 Mill St",
    "sg:city":"Bridgnorth",
    "sg:classifiers":[
        {
            "category":"Building & Trades",
            "subcategory":"Plumbing",
            "type":"Services"
        }
    ],
    "sg:phone":"+44 1746 763070",
    "sg:postcode":"WV15 5AF",
    "sg:province":"Shropshire",
    "sg:tags":[
        "heating"
    ],
    "wof:name":"D J Smallman",
    "wof:placetype":"venue"
},
  "geometry": {"coordinates":[-2.412162,52.535999],"type":"Point"}
}