{
  "type": "Feature",
  "properties": {
    "addr:full":"24 Lowther St Carlisle Cumbria CA3 8DA",
    "addr:housenumber":"24",
    "addr:postcode":"ca3 8da",
    "addr:street":"Lowther St",
    "iso:country":"GB",
    "sg:address":"24 Lowther St",
    "sg:city":"Carlisle",
    "sg:classifiers":[
        {
            "category":"Restaurant",
            "type":"Food & Drink"
        }
    ],
    "sg:postcode":"CA3 8DA",
    "sg:province":"Cumbria",
    "wof:name":"Nelson,John,",
    "wof:placetype":"venue"
},
  "geometry": {"coordinates":[-2.9330730438,54.893737793],"type":"Point"}
}