{
  "type": "Feature",
  "properties": {
    "iso:country":"GB",
    "sg:address":"Trehill Farm",
    "sg:city":"Torpoint",
    "sg:classifiers":[
        {
            "category":"Transit Center",
            "subcategory":"Passenger",
            "type":"Transportation"
        }
    ],
    "sg:phone":"+44 1752 822511",
    "sg:postcode":"PL10 1LF",
    "sg:province":"Cornwall",
    "sg:tags":[
        "boarding",
        "kennel",
        "catteries"
    ],
    "wof:name":"Trehill Boarding Kennels & Cattery",
    "wof:placetype":"venue"
},
  "geometry": {"coordinates":[-4.212720871,50.3406677246],"type":"Point"}
}