{
  "type": "Feature",
  "properties": {
    "iso:country":"GB",
    "sg:address":"Flat 18 Summersdale Court, The Drive",
    "sg:city":"Chichester",
    "sg:classifiers":[
        {
            "category":"Utilities",
            "subcategory":"Water",
            "type":"Services"
        },
        {
            "category":"Military Area",
            "subcategory":"Air Force Base",
            "type":"Public Place"
        }
    ],
    "sg:phone":"+44 1243 774383",
    "sg:postcode":"PO19 5RF",
    "sg:province":"West Sussex",
    "sg:tags":[
        "treatment"
    ],
    "wof:name":"Homedawn Ltd.",
    "wof:placetype":"venue"
},
  "geometry": {"coordinates":[-0.78264,50.85828],"type":"Point"}
}