{
  "type": "Feature",
  "properties": {
    "addr:full":"29 Dean Road Scarborough North Yorkshire YO12 7SN",
    "addr:housenumber":"29",
    "addr:postcode":"yo12 7sn",
    "addr:street":"Dean Road",
    "iso:country":"GB",
    "sg:address":"29 Dean Road",
    "sg:city":"Scarborough",
    "sg:classifiers":[
        {
            "category":"Food & Beverages",
            "subcategory":"Meat & Fish",
            "type":"Retail Goods"
        }
    ],
    "sg:phone":"+44 1723 364052",
    "sg:postcode":"YO12 7SN",
    "sg:province":"North Yorkshire",
    "sg:tags":[
        "butcher"
    ],
    "wof:name":"DOUGLAS LEONARD SPENCE",
    "wof:placetype":"venue"
},
  "geometry": {"coordinates":[-0.4046370089,54.2848587036],"type":"Point"}
}