{
  "type": "Feature",
  "properties": {
    "addr:full":"25 Normandy St Alton Hampshire GU34 1DQ",
    "addr:housenumber":"25",
    "addr:postcode":"gu34 1dq",
    "addr:street":"Normandy St",
    "iso:country":"GB",
    "sg:address":"25 Normandy St",
    "sg:city":"Alton",
    "sg:classifiers":[
        {
            "category":"Government",
            "subcategory":"Court House",
            "type":"Public Place"
        }
    ],
    "sg:phone":"+44 1420 84155",
    "sg:postcode":"GU34 1DQ",
    "sg:province":"Hampshire",
    "wof:name":"Hampshire Probation Service",
    "wof:placetype":"venue"
},
  "geometry": {"coordinates":[-0.9720550179,51.1510162354],"type":"Point"}
}