{
  "type": "Feature",
  "properties": {
    "iso:country":"GB",
    "sg:address":"Blakenhale Road",
    "sg:city":"Birmingham",
    "sg:classifiers":[
        {
            "category":"Education",
            "subcategory":"School",
            "type":"Public Place"
        },
        {
            "category":"Government",
            "subcategory":"Office",
            "type":"Public Place"
        }
    ],
    "sg:phone":"+44 121 675 4259",
    "sg:postcode":"B33 0XD",
    "sg:province":"West Midlands",
    "sg:tags":[
        "local",
        "authority"
    ],
    "wof:name":"Blakenhale Infant School",
    "wof:placetype":"venue"
},
  "geometry": {"coordinates":[-1.7835079432,52.4742774963],"type":"Point"}
}