{
  "type": "Feature",
  "properties": {
    "iso:country":"GB",
    "sg:address":"203 Freemasons Rd",
    "sg:city":"Canning Town",
    "sg:classifiers":[
        {
            "category":"Building & Trades",
            "subcategory":"Construction",
            "type":"Services"
        }
    ],
    "sg:phone":"+44 20 7476 0130",
    "sg:postcode":"E16 3PG",
    "sg:province":"Greater London",
    "sg:tags":[
        "joiner",
        "carpenter"
    ],
    "wof:name":"B.D Holmes",
    "wof:placetype":"venue"
},
  "geometry": {"coordinates":[0.024914,51.515965],"type":"Point"}
}