{
  "type": "Feature",
  "properties": {
    "iso:country":"GB",
    "sg:address":"Unit 2 Diamond Units, Mochdre Industrial Estate, Conway Road",
    "sg:city":"Colwyn Bay",
    "sg:classifiers":[
        {
            "category":"Professional",
            "subcategory":"Management & Consulting",
            "type":"Services"
        }
    ],
    "sg:phone":"+44 1492 541222",
    "sg:postcode":"LL28 5HA",
    "sg:province":"Conwy",
    "sg:tags":[
        "fire",
        "consultant",
        "protection"
    ],
    "wof:name":"P S A Systems",
    "wof:placetype":"venue"
},
  "geometry": {"coordinates":[-3.7663700581,53.2907218933],"type":"Point"}
}