{
  "type": "Feature",
  "properties": {
    "iso:country":"GB",
    "sg:address":"Wakefield Road, Kinsley",
    "sg:city":"Pontefract",
    "sg:classifiers":[
        {
            "category":"Health Services",
            "subcategory":"Nursing And Care Facility",
            "type":"Services"
        }
    ],
    "sg:phone":"+44 1977 617374",
    "sg:postcode":"WF8 4HA",
    "sg:province":"North Yorkshire",
    "sg:tags":[
        "home"
    ],
    "wof:name":"Hemsworth Park",
    "wof:placetype":"venue"
},
  "geometry": {"coordinates":[-1.3316600323,53.6825294495],"type":"Point"}
}