{
  "type": "Feature",
  "properties": {
    "addr:full":"14-15 High Street Exeter Devon EX4 3LH",
    "addr:housenumber":"14-15",
    "addr:postcode":"ex4 3lh",
    "addr:street":"High Street",
    "iso:country":"GB",
    "sg:address":"14-15 High Street",
    "sg:city":"Exeter",
    "sg:classifiers":[
        {
            "category":"Shopping",
            "subcategory":"Clothing, Apparel, & Fashions",
            "type":"Retail Goods"
        }
    ],
    "sg:phone":"+44 1392 427322",
    "sg:postcode":"EX4 3LH",
    "sg:province":"Devon",
    "sg:tags":[
        "accessory"
    ],
    "wof:name":"Monsoon Accessorize",
    "wof:placetype":"venue"
},
  "geometry": {"coordinates":[-3.5280370712,50.724937439],"type":"Point"}
}