{
  "type": "Feature",
  "properties": {
    "iso:country":"GB",
    "sg:address":"Back Browning Street",
    "sg:city":"Stafford",
    "sg:classifiers":[
        {
            "category":"Autos & Motor Vehicles",
            "subcategory":"Automobile Sales",
            "type":"Retail Goods"
        }
    ],
    "sg:phone":"+44 1785 243470",
    "sg:postcode":"ST16 3AU",
    "sg:province":"Staffordshire",
    "sg:tags":[
        "auction",
        "car"
    ],
    "wof:name":"Stafford Motor Auctions",
    "wof:placetype":"venue"
},
  "geometry": {"coordinates":[-2.120159,52.812798],"type":"Point"}
}