{
  "type": "Feature",
  "properties": {
    "addr:full":"171 Brandling Street Sunderland Tyne and Wear SR6 0LN",
    "addr:housenumber":"171",
    "addr:postcode":"sr6 0ln",
    "addr:street":"Brandling Street",
    "iso:country":"GB",
    "sg:address":"171 Brandling Street",
    "sg:city":"Sunderland",
    "sg:classifiers":[
        {
            "category":"Shopping",
            "subcategory":"News",
            "type":"Retail Goods"
        }
    ],
    "sg:phone":"+44 191 510 0560",
    "sg:postcode":"SR6 0LN",
    "sg:province":"Tyne and Wear",
    "sg:tags":[
        "newsagent"
    ],
    "wof:name":"Roker Park Newsagency",
    "wof:placetype":"venue"
},
  "geometry": {"coordinates":[-1.372942,54.921322],"type":"Point"}
}