{
  "type": "Feature",
  "properties": {
    "iso:country":"GB",
    "sg:address":"1st Floor Fretherne Chambers",
    "sg:city":"Welwyn Garden City",
    "sg:classifiers":[
        {
            "category":"Professional",
            "subcategory":"Advertising",
            "type":"Services"
        }
    ],
    "sg:phone":"+44 1707 396300",
    "sg:postcode":"AL8 6NY",
    "sg:province":"Hertfordshire",
    "wof:name":"A R T Creative Partnership",
    "wof:placetype":"venue"
},
  "geometry": {"coordinates":[-0.2061139941,51.8006782532],"type":"Point"}
}