{
  "type": "Feature",
  "properties": {
    "iso:country":"GB",
    "sg:address":"4 Daimonds La",
    "sg:city":"Teignmouth",
    "sg:classifiers":[
        {
            "category":"Retail",
            "subcategory":"Auto Repair",
            "type":"Services"
        }
    ],
    "sg:phone":"+44 1626 778135",
    "sg:postcode":"TQ14 9HZ",
    "sg:province":"Devon",
    "sg:tags":[
        "modification",
        "garage"
    ],
    "wof:name":"Ellis Autos Mobile",
    "wof:placetype":"venue"
},
  "geometry": {"coordinates":[-3.499411,50.548363],"type":"Point"}
}