{
  "type": "Feature",
  "properties": {
    "iso:country":"GB",
    "sg:address":"Captured House, Chertsey Road, Byfleet",
    "sg:city":"West Byfleet",
    "sg:classifiers":[
        {
            "category":"Professional",
            "subcategory":"Art Services",
            "type":"Services"
        }
    ],
    "sg:phone":"+44 1932 354417",
    "sg:postcode":"KT14 7AP",
    "sg:province":"Surrey",
    "sg:tags":[
        "photographer"
    ],
    "wof:name":"Claire Louise Adams",
    "wof:placetype":"venue"
},
  "geometry": {"coordinates":[-0.481388,51.344158],"type":"Point"}
}