{
  "type": "Feature",
  "properties": {
    "addr:full":"17-19 Cookridge Lane Leeds West Yorkshire LS16 7LQ",
    "addr:housenumber":"17-19",
    "addr:postcode":"ls16 7lq",
    "addr:street":"Cookridge Lane",
    "iso:country":"GB",
    "sg:address":"17-19 Cookridge Lane",
    "sg:city":"Leeds",
    "sg:classifiers":[
        {
            "category":"Shopping",
            "subcategory":"News",
            "type":"Retail Goods"
        }
    ],
    "sg:phone":"+44 113 294 1999",
    "sg:postcode":"LS16 7LQ",
    "sg:province":"West Yorkshire",
    "sg:tags":[
        "newsagent"
    ],
    "wof:name":"N K & S N Patel",
    "wof:placetype":"venue"
},
  "geometry": {"coordinates":[-1.615462,53.861515],"type":"Point"}
}