{
  "type": "Feature",
  "properties": {
    "iso:country":"GB",
    "sg:address":"Main Street, Long Riston",
    "sg:city":"Hull",
    "sg:classifiers":[
        {
            "category":"Building & Trades",
            "subcategory":"Construction",
            "type":"Services"
        }
    ],
    "sg:phone":"+44 1964 563175",
    "sg:postcode":"HU11 5JF",
    "sg:province":"East Riding of Yorkshire",
    "sg:tags":[
        "builder"
    ],
    "wof:name":"Leonard F Taylor Builders",
    "wof:placetype":"venue"
},
  "geometry": {"coordinates":[-0.2877689898,53.8636894226],"type":"Point"}
}