{
  "type": "Feature",
  "properties": {
    "addr:full":"28 Dahlia Gardens Mitcham Greater London CR4 1LA",
    "addr:housenumber":"28",
    "addr:postcode":"cr4 1la",
    "addr:street":"Dahlia Gardens",
    "iso:country":"GB",
    "sg:address":"28 Dahlia Gardens",
    "sg:city":"Mitcham",
    "sg:classifiers":[
        {
            "category":"Retail",
            "subcategory":"Auto Repair",
            "type":"Services"
        }
    ],
    "sg:phone":"+44 20 8679 5223",
    "sg:postcode":"CR4 1LA",
    "sg:province":"Greater London",
    "sg:tags":[
        "modification",
        "garage"
    ],
    "wof:name":"Randall Car Services",
    "wof:placetype":"venue"
},
  "geometry": {"coordinates":[-0.136457,51.39875],"type":"Point"}
}