{
  "type": "Feature",
  "properties": {
    "addr:full":"Eastcombe Farm, Batcombe Shepton Mallet Somerset BA4 6AL",
    "addr:postcode":"ba4 6al",
    "iso:country":"GB",
    "sg:address":"Eastcombe Farm, Batcombe",
    "sg:city":"Shepton Mallet",
    "sg:classifiers":[
        {
            "category":"Farming",
            "subcategory":"Livestock Farm",
            "type":"Manufacturing & Wholesale Goods"
        }
    ],
    "sg:phone":"+44 1749 850298",
    "sg:postcode":"BA4 6AL",
    "sg:province":"Somerset",
    "sg:tags":[
        "others"
    ],
    "wof:name":"Gordon M Shears",
    "wof:placetype":"venue"
},
  "geometry": {"coordinates":[-2.4462080002,51.1501159668],"type":"Point"}
}