{
  "type": "Feature",
  "properties": {
    "iso:country":"GB",
    "sg:address":"Ling Cotts, Threshfield",
    "sg:city":"Skipton",
    "sg:classifiers":[
        {
            "category":"Freight",
            "type":"Transportation"
        }
    ],
    "sg:phone":"+44 1756 752341",
    "sg:postcode":"BD23 5HB",
    "sg:province":"Lancashire",
    "sg:tags":[
        "haulage",
        "transport",
        "road"
    ],
    "wof:name":"Ellis Dean",
    "wof:placetype":"venue"
},
  "geometry": {"coordinates":[-2.017219,54.069374],"type":"Point"}
}