{
  "type": "Feature",
  "properties": {
    "addr:full":"Station House, Cooksbridge Lewes East Sussex BN8 4SW",
    "addr:postcode":"bn8 4sw",
    "addr:street":"Cooksbridge",
    "iso:country":"GB",
    "sg:address":"Station House, Cooksbridge",
    "sg:city":"Lewes",
    "sg:classifiers":[
        {
            "category":"Professional",
            "type":"Services"
        },
        {
            "category":"Deli",
            "type":"Food & Drink"
        }
    ],
    "sg:postcode":"BN8 4SW",
    "sg:province":"East Sussex",
    "sg:tags":[
        "delicatessen",
        "caterer"
    ],
    "wof:name":"The Deli At Cooksbridge",
    "wof:placetype":"venue"
},
  "geometry": {"coordinates":[-0.0082040001,50.9044265747],"type":"Point"}
}