{
  "type": "Feature",
  "properties": {
    "iso:country":"GB",
    "sg:address":"Hurley Common, Hurley",
    "sg:city":"Atherstone",
    "sg:classifiers":[
        {
            "category":"Sports & Exercise",
            "subcategory":"Stables",
            "type":"Entertainment"
        }
    ],
    "sg:phone":"+44 1827 872205",
    "sg:postcode":"CV9 2LR",
    "sg:province":"Leicestershire",
    "sg:tags":[
        "education",
        "equestrian"
    ],
    "wof:name":"Holly Riding School",
    "wof:placetype":"venue"
},
  "geometry": {"coordinates":[-1.6446080208,52.5611190796],"type":"Point"}
}