{
  "type": "Feature",
  "properties": {
    "addr:full":"116 Wood Vale London Greater London SE23 3EB",
    "addr:housenumber":"116",
    "addr:postcode":"se23 3eb",
    "addr:street":"Wood",
    "iso:country":"GB",
    "sg:address":"116 Wood Vale",
    "sg:city":"London",
    "sg:classifiers":[
        {
            "category":"Personal",
            "subcategory":"Beauty Salon",
            "type":"Services"
        }
    ],
    "sg:phone":"+44 20 8299 0243",
    "sg:postcode":"SE23 3EB",
    "sg:province":"Greater London",
    "sg:tags":[
        "unisex",
        "hairdresser"
    ],
    "wof:name":"Boston Ladies & Gents Hairdressing",
    "wof:placetype":"venue"
},
  "geometry": {"coordinates":[-0.0618130006,51.4475326538],"type":"Point"}
}