{
  "type": "Feature",
  "properties": {
    "iso:country":"GB",
    "sg:address":"304 Perth Road",
    "sg:city":"Dundee",
    "sg:classifiers":[
        {
            "category":"Restaurant",
            "type":"Food & Drink"
        }
    ],
    "sg:phone":"+44 1382 646281",
    "sg:postcode":"DD2 1AU",
    "sg:province":"Dundee City",
    "wof:name":"Beiderbecke",
    "wof:placetype":"venue"
},
  "geometry": {"coordinates":[-2.994243,56.456306],"type":"Point"}
}