{
  "type": "Feature",
  "properties": {
    "iso:country":"GB",
    "sg:address":"12 Westby Road",
    "sg:city":"Bournemouth",
    "sg:classifiers":[
        {
            "category":"Travel",
            "subcategory":"Hotels & Motels",
            "type":"Entertainment"
        }
    ],
    "sg:phone":"+44 1202 303650",
    "sg:postcode":"BH5 1HD",
    "sg:province":"Dorset",
    "wof:name":"Carlton Lodge Hotel",
    "wof:placetype":"venue"
},
  "geometry": {"coordinates":[-1.839365,50.725105],"type":"Point"}
}