{
  "type": "Feature",
  "properties": {
    "iso:country":"GB",
    "sg:address":"24 Queens Road",
    "sg:city":"Buckhurst Hill",
    "sg:classifiers":[
        {
            "category":"Cafe",
            "type":"Food & Drink"
        }
    ],
    "sg:phone":"+44 20 8504 0913",
    "sg:postcode":"IG9 5BY",
    "sg:province":"Essex",
    "sg:tags":[
        "tea",
        "snack",
        "bar",
        "room"
    ],
    "wof:name":"Legends",
    "wof:placetype":"venue"
},
  "geometry": {"coordinates":[0.044849,51.625084],"type":"Point"}
}