{
  "type": "Feature",
  "properties": {
    "addr:full":"6 High St Wakefield West Yorkshire WF4 2JZ",
    "addr:housenumber":"6",
    "addr:postcode":"wf4 2jz",
    "addr:street":"High St",
    "iso:country":"GB",
    "sg:address":"6 High St",
    "sg:city":"Wakefield",
    "sg:classifiers":[
        {
            "category":"Wholesale",
            "subcategory":"Machinery & Supplies",
            "type":"Manufacturing & Wholesale Goods"
        }
    ],
    "sg:phone":"+44 161 745 9777",
    "sg:postcode":"WF4 2JZ",
    "sg:province":"West Yorkshire",
    "sg:tags":[
        "industrial",
        "commercial"
    ],
    "wof:name":"Care Graphics Ltd",
    "wof:placetype":"venue"
},
  "geometry": {"coordinates":[-1.5173979998,53.6137886047],"type":"Point"}
}