{
  "type": "Feature",
  "properties": {
    "iso:country":"GB",
    "sg:address":"168 Constitution Hill",
    "sg:city":"Norwich",
    "sg:classifiers":[
        {
            "category":"Building & Trades",
            "subcategory":"Plumbing",
            "type":"Services"
        }
    ],
    "sg:phone":"+44 1603 425936",
    "sg:postcode":"NR3 4HB",
    "sg:province":"Norfolk",
    "sg:tags":[
        "central",
        "heating"
    ],
    "wof:name":"Catton Gas Plumbing & Heating",
    "wof:placetype":"venue"
},
  "geometry": {"coordinates":[1.301435,52.650978],"type":"Point"}
}