{
  "type": "Feature",
  "properties": {
    "addr:full":"P O Box 835 Slough Berkshire SL3 8XU",
    "addr:housenumber":"835",
    "addr:postcode":"sl3 8xu",
    "addr:street":"P O Box",
    "iso:country":"GB",
    "sg:address":"P O Box 835",
    "sg:city":"Slough",
    "sg:classifiers":[
        {
            "category":"Shopping",
            "subcategory":"Hobbies, Toys, & Games",
            "type":"Retail Goods"
        },
        {
            "category":"Professional",
            "subcategory":"Computer Services",
            "type":"Services"
        }
    ],
    "sg:phone":"+44 1753 546465",
    "sg:postcode":"SL3 8XU",
    "sg:province":"Berkshire",
    "sg:tags":[
        "system",
        "software"
    ],
    "wof:name":"Electronic Arts Ltd.",
    "wof:placetype":"venue"
},
  "geometry": {"coordinates":[-0.5423290133,51.4999694824],"type":"Point"}
}