{
  "type": "Feature",
  "properties": {
    "iso:country":"GB",
    "sg:address":"496 Ridgeway Road",
    "sg:city":"Sheffield",
    "sg:classifiers":[
        {
            "category":"Cinema",
            "subcategory":"Movie Rental",
            "type":"Entertainment"
        }
    ],
    "sg:phone":"+44 114 239 3622",
    "sg:postcode":"S12 2JW",
    "sg:province":"Derbyshire",
    "sg:tags":[
        "video",
        "library"
    ],
    "wof:name":"Blockbuster Video",
    "wof:placetype":"venue"
},
  "geometry": {"coordinates":[-1.426817,53.345528],"type":"Point"}
}