{
  "type": "Feature",
  "properties": {
    "iso:country":"GB",
    "sg:address":"10 Warwick On Eden",
    "sg:city":"Carlisle",
    "sg:classifiers":[
        {
            "category":"Real Estate",
            "subcategory":"Real Estate Operator",
            "type":"Services"
        },
        {
            "category":"Real Estate",
            "subcategory":"Real Estate Agent",
            "type":"Services"
        }
    ],
    "sg:postcode":"CA4 8PA",
    "sg:province":"Cumbria",
    "sg:tags":[
        "letting"
    ],
    "wof:name":"Warburton,Tony,",
    "wof:placetype":"venue"
},
  "geometry": {"coordinates":[-2.83629,54.899502],"type":"Point"}
}