{
  "type": "Feature",
  "properties": {
    "addr:full":"Westfield House, Easingwold Road, Haxby York North Yorkshire YO61 1HN",
    "addr:postcode":"yo61 1hn",
    "addr:street":"Easingwold Road",
    "iso:country":"GB",
    "sg:address":"Westfield House, Easingwold Road, Haxby",
    "sg:city":"York",
    "sg:classifiers":[
        {
            "category":"Communications",
            "type":"Services"
        }
    ],
    "sg:postcode":"YO61 1HN",
    "sg:province":"North Yorkshire",
    "sg:tags":[
        "audio-visual"
    ],
    "wof:name":"Northern Televison",
    "wof:placetype":"venue"
},
  "geometry": {"coordinates":[-1.1382730007,54.0921401978],"type":"Point"}
}