{
  "type": "Feature",
  "properties": {
    "iso:country":"GB",
    "sg:address":"1 Grosvenor Pl",
    "sg:city":"London",
    "sg:classifiers":[
        {
            "category":"Banks & Credit Unions",
            "subcategory":"Investment Brokerage",
            "type":"Services"
        }
    ],
    "sg:postcode":"SW1X 7JH",
    "sg:province":"Greater London",
    "wof:name":"Hanson General Partner Ltd",
    "wof:placetype":"venue"
},
  "geometry": {"coordinates":[-0.151528,51.501644],"type":"Point"}
}