{
  "type": "Feature",
  "properties": {
    "addr:full":"Island House, Nacton Road Ipswich Suffolk IP3 9RR",
    "addr:postcode":"ip3 9rr",
    "addr:street":"Nacton Road",
    "iso:country":"GB",
    "sg:address":"Island House, Nacton Road",
    "sg:city":"Ipswich",
    "sg:classifiers":[
        {
            "category":"Shopping",
            "subcategory":"Stationery & Office Supplies",
            "type":"Retail Goods"
        }
    ],
    "sg:phone":"+44 1473 711112",
    "sg:postcode":"IP3 9RR",
    "sg:province":"Suffolk",
    "sg:tags":[
        "merchant",
        "paper"
    ],
    "wof:name":"The Masons Paper Co. Ltd.",
    "wof:placetype":"venue"
},
  "geometry": {"coordinates":[1.1805100441,52.0446548462],"type":"Point"}
}