{
  "type": "Feature",
  "properties": {
    "addr:full":"33 Fizroy Street London Greater London W1T 6DU",
    "addr:housenumber":"33",
    "addr:postcode":"w1t 6du",
    "addr:street":"Fizroy Street",
    "iso:country":"GB",
    "sg:address":"33 Fizroy Street",
    "sg:city":"London",
    "sg:classifiers":[
        {
            "category":"Professional",
            "subcategory":"Art Services",
            "type":"Services"
        }
    ],
    "sg:phone":"+44 20 7636 7736",
    "sg:postcode":"W1T 6DU",
    "sg:province":"Greater London",
    "sg:tags":[
        "graphic",
        "designer"
    ],
    "wof:name":"Type Technique",
    "wof:placetype":"venue"
},
  "geometry": {"coordinates":[-0.138596,51.522026],"type":"Point"}
}