{
  "type": "Feature",
  "properties": {
    "iso:country":"GB",
    "sg:address":"5 Markhams Chase, Lee Chapel North",
    "sg:city":"Basildon",
    "sg:classifiers":[
        {
            "category":"Building & Trades",
            "subcategory":"Construction",
            "type":"Services"
        }
    ],
    "sg:phone":"+44 1268 414413",
    "sg:postcode":"SS15 5JX",
    "sg:province":"Essex",
    "sg:tags":[
        "dry",
        "lining",
        "plasterers",
        "screeders"
    ],
    "wof:name":"Patrick Byrne",
    "wof:placetype":"venue"
},
  "geometry": {"coordinates":[0.438287,51.577145],"type":"Point"}
}