{
  "type": "Feature",
  "properties": {
    "addr:full":"Wembley Stadium Wembley Greater London HA9 0DW",
    "addr:postcode":"ha9 0dw",
    "iso:country":"GB",
    "sg:address":"Wembley Stadium",
    "sg:city":"Wembley",
    "sg:classifiers":[
        {
            "category":"Recreation",
            "subcategory":"Go Karts",
            "type":"Entertainment"
        }
    ],
    "sg:phone":"+44 20 8795 4159",
    "sg:postcode":"HA9 0DW",
    "sg:province":"Greater London",
    "sg:tags":[
        "karting"
    ],
    "wof:name":"Wembley Kart Circuit",
    "wof:placetype":"venue"
},
  "geometry": {"coordinates":[-0.2796800137,51.5555610657],"type":"Point"}
}