{
  "type": "Feature",
  "properties": {
    "iso:country":"GB",
    "sg:address":"64 Lemon Street",
    "sg:city":"Truro",
    "sg:classifiers":[
        {
            "category":"Health Services",
            "subcategory":"Doctor",
            "type":"Services"
        }
    ],
    "sg:phone":"+44 1872 276160",
    "sg:postcode":"TR1 2PN",
    "sg:province":"Cornwall",
    "sg:tags":[
        "practitioners"
    ],
    "wof:name":"Fozzard, C E",
    "wof:placetype":"venue"
},
  "geometry": {"coordinates":[-5.052613,50.26157],"type":"Point"}
}