{
  "type": "Feature",
  "properties": {
    "addr:full":"96-98 Market St, Shirebrook Mansfield Derbyshire NG20 8AD",
    "addr:housenumber":"96-98",
    "addr:postcode":"ng20 8ad",
    "addr:street":"Market St",
    "iso:country":"GB",
    "sg:address":"96-98 Market St, Shirebrook",
    "sg:city":"Mansfield",
    "sg:classifiers":[
        {
            "category":"Shopping",
            "subcategory":"Florist",
            "type":"Retail Goods"
        }
    ],
    "sg:phone":"+44 1623 744019",
    "sg:postcode":"NG20 8AD",
    "sg:province":"Derbyshire",
    "wof:name":"Flowertalk",
    "wof:placetype":"venue"
},
  "geometry": {"coordinates":[-1.2118229866,53.20337677],"type":"Point"}
}