{
  "type": "Feature",
  "properties": {
    "addr:full":"104 Churchill Road Bicester Oxfordshire OX26 4XD",
    "addr:housenumber":"104",
    "addr:postcode":"ox26 4xd",
    "addr:street":"Churchill Road",
    "iso:country":"GB",
    "sg:address":"104 Churchill Road",
    "sg:city":"Bicester",
    "sg:classifiers":[
        {
            "category":"Sports & Exercise",
            "subcategory":"Gym",
            "type":"Entertainment"
        }
    ],
    "sg:phone":"+44 1869 321171",
    "sg:postcode":"OX26 4XD",
    "sg:province":"Oxfordshire",
    "sg:tags":[
        "fitness",
        "health",
        "centre"
    ],
    "wof:name":"Clearwater Fitness",
    "wof:placetype":"venue"
},
  "geometry": {"coordinates":[-1.1413069963,51.9045944214],"type":"Point"}
}