{
  "type": "Feature",
  "properties": {
    "addr:full":"16a St Anthony's Road Bournemouth Dorset BH2 6PD",
    "addr:housenumber":"16a",
    "addr:postcode":"bh2 6pd",
    "addr:street":"St Anthony'S Road",
    "iso:country":"GB",
    "sg:address":"16a St Anthony's Road",
    "sg:city":"Bournemouth",
    "sg:classifiers":[
        {
            "category":"Social Services",
            "subcategory":"Retirement Home",
            "type":"Services"
        }
    ],
    "sg:phone":"+44 1202 551208",
    "sg:postcode":"BH2 6PD",
    "sg:province":"Dorset",
    "sg:tags":[
        "rest"
    ],
    "wof:name":"St Annes Court",
    "wof:placetype":"venue"
},
  "geometry": {"coordinates":[-1.8439689875,50.7312164307],"type":"Point"}
}