{
  "type": "Feature",
  "properties": {
    "addr:full":"38 Thornhill Road, Rastrick Brighouse West Yorkshire HD6 3AH",
    "addr:housenumber":"38",
    "addr:postcode":"hd6 3ah",
    "addr:street":"Thornhill Road Rastrick Brighouse West",
    "iso:country":"GB",
    "sg:address":"38 Thornhill Road, Rastrick",
    "sg:city":"Brighouse",
    "sg:classifiers":[
        {
            "category":"Home & Garden",
            "subcategory":"Building Materials",
            "type":"Retail Goods"
        }
    ],
    "sg:phone":"+44 1484 715002",
    "sg:postcode":"HD6 3AH",
    "sg:province":"West Yorkshire",
    "sg:tags":[
        "polythene",
        "plastic"
    ],
    "wof:name":"Richard Neil",
    "wof:placetype":"venue"
},
  "geometry": {"coordinates":[-1.7877850533,53.697013855],"type":"Point"}
}