{
  "type": "Feature",
  "properties": {
    "iso:country":"GB",
    "sg:address":"89 Victoria Rd, South Ascot",
    "sg:city":"Ascot",
    "sg:classifiers":[
        {
            "category":"Professional",
            "subcategory":"Secretarial Services",
            "type":"Services"
        }
    ],
    "sg:postcode":"SL5 9DR",
    "sg:province":"Berkshire",
    "wof:name":"Bolton,Stephanie,",
    "wof:placetype":"venue"
},
  "geometry": {"coordinates":[-0.672528,51.402981],"type":"Point"}
}