{
  "type": "Feature",
  "properties": {
    "iso:country":"GB",
    "sg:address":"3 Limetree Gro",
    "sg:city":"Braunton",
    "sg:classifiers":[
        {
            "category":"Home & Garden",
            "subcategory":"Building Materials",
            "type":"Retail Goods"
        }
    ],
    "sg:postcode":"EX33 1HE",
    "sg:province":"Devon",
    "sg:tags":[
        "garage",
        "door"
    ],
    "wof:name":"D R Jarvis Garage Door Specialist",
    "wof:placetype":"venue"
},
  "geometry": {"coordinates":[-4.1705560684,51.1088676453],"type":"Point"}
}