{
  "type": "Feature",
  "properties": {
    "addr:full":"20 Moss Lane, Hightown Liverpool Merseyside L38 3RA",
    "addr:housenumber":"20",
    "addr:postcode":"l38 3ra",
    "addr:street":"Moss Lane",
    "iso:country":"GB",
    "sg:address":"20 Moss Lane, Hightown",
    "sg:city":"Liverpool",
    "sg:classifiers":[
        {
            "category":"Bars & Pubs",
            "type":"Food & Drink"
        },
        {
            "category":"Community Center",
            "subcategory":"Social",
            "type":"Public Place"
        }
    ],
    "sg:phone":"+44 151 929 2106",
    "sg:postcode":"L38 3RA",
    "sg:province":"Merseyside",
    "sg:tags":[
        "pubs",
        "house",
        "inn",
        "activity"
    ],
    "wof:name":"The Pheasant Inn",
    "wof:placetype":"venue"
},
  "geometry": {"coordinates":[-3.047702,53.527565],"type":"Point"}
}