{
  "type": "Feature",
  "properties": {
    "iso:country":"GB",
    "sg:address":"111 Castle Road",
    "sg:city":"Salisbury",
    "sg:classifiers":[
        {
            "category":"Education",
            "subcategory":"Special Training",
            "type":"Public Place"
        }
    ],
    "sg:postcode":"SP1 3RP",
    "sg:province":"Wiltshire",
    "sg:tags":[
        "school",
        "language"
    ],
    "wof:name":"Premier English Language Centre",
    "wof:placetype":"venue"
},
  "geometry": {"coordinates":[-1.796831,51.081673],"type":"Point"}
}