{
  "type": "Feature",
  "properties": {
    "addr:full":"Unit 2a, Greensfield Park Industrial Estate Alnwick Northumberland NE66 2DD",
    "addr:housenumber":"unit 2a",
    "addr:postcode":"ne66 2dd",
    "addr:street":"Greensfield Park Industrial Estate",
    "iso:country":"GB",
    "sg:address":"Unit 2a, Greensfield Park Industrial Estate",
    "sg:city":"Alnwick",
    "sg:classifiers":[
        {
            "category":"Professional",
            "subcategory":"Employment Agencies",
            "type":"Services"
        }
    ],
    "sg:phone":"+44 1757 289191",
    "sg:postcode":"NE66 2DD",
    "sg:province":"Northumberland",
    "sg:tags":[
        "agricultural",
        "advice"
    ],
    "wof:name":"Cropwise (North) Ltd.",
    "wof:placetype":"venue"
},
  "geometry": {"coordinates":[-1.697919,55.401905],"type":"Point"}
}