{
  "type": "Feature",
  "properties": {
    "addr:full":"42 Sandstone Avenue, Rubery Birmingham West Midlands B45 9YF",
    "addr:housenumber":"42",
    "addr:postcode":"b45 9yf",
    "addr:street":"Sandstone Avenue",
    "iso:country":"GB",
    "sg:address":"42 Sandstone Avenue, Rubery",
    "sg:city":"Birmingham",
    "sg:classifiers":[
        {
            "category":"Food & Beverages",
            "subcategory":"Specialty",
            "type":"Retail Goods"
        }
    ],
    "sg:phone":"+44 121 628 3027",
    "sg:postcode":"B45 9YF",
    "sg:province":"West Midlands",
    "sg:tags":[
        "dietetic",
        "homogenised"
    ],
    "wof:name":"Nature's Way",
    "wof:placetype":"venue"
},
  "geometry": {"coordinates":[-2.0147631168,52.3966751099],"type":"Point"}
}