{
  "type": "Feature",
  "properties": {
    "iso:country":"GB",
    "sg:address":"Yew Tree Farm, Mugginton Lane End, Weston Underwood",
    "sg:city":"Ashbourne",
    "sg:classifiers":[
        {
            "category":"Building & Trades",
            "subcategory":"Construction",
            "type":"Services"
        }
    ],
    "sg:phone":"+44 1773 550758",
    "sg:postcode":"DE6 4PP",
    "sg:province":"Derbyshire",
    "sg:tags":[
        "builder"
    ],
    "wof:name":"Swain Building Contractors",
    "wof:placetype":"venue"
},
  "geometry": {"coordinates":[-1.5666940212,52.9798965454],"type":"Point"}
}