{
  "type": "Feature",
  "properties": {
    "addr:full":"7 Melton Road, Whissendine Oakham Leicestershire LE15 7EU",
    "addr:housenumber":"7",
    "addr:postcode":"le15 7eu",
    "addr:street":"Melton Road",
    "iso:country":"GB",
    "sg:address":"7 Melton Road, Whissendine",
    "sg:city":"Oakham",
    "sg:classifiers":[
        {
            "category":"Building & Trades",
            "subcategory":"Landscaping Services",
            "type":"Services"
        }
    ],
    "sg:phone":"+44 1664 474667",
    "sg:postcode":"LE15 7EU",
    "sg:province":"Leicestershire",
    "sg:tags":[
        "contractor",
        "drainage"
    ],
    "wof:name":"Clarks Drainage Ltd",
    "wof:placetype":"venue"
},
  "geometry": {"coordinates":[-0.754661,52.689575],"type":"Point"}
}