{
  "type": "Feature",
  "properties": {
    "addr:full":"31 Titchfield Road, Stubbington Fareham Hampshire PO14 2JH",
    "addr:housenumber":"31",
    "addr:postcode":"po14 2jh",
    "addr:street":"Titchfield Road",
    "iso:country":"GB",
    "sg:address":"31 Titchfield Road, Stubbington",
    "sg:city":"Fareham",
    "sg:classifiers":[
        {
            "category":"Organizations",
            "subcategory":"Membership Organization",
            "type":"Services"
        }
    ],
    "sg:phone":"+44 1329 662161",
    "sg:postcode":"PO14 2JH",
    "sg:province":"Hampshire",
    "sg:tags":[
        "club",
        "social"
    ],
    "wof:name":"The Crofton Club",
    "wof:placetype":"venue"
},
  "geometry": {"coordinates":[-1.2162129879,50.8275299072],"type":"Point"}
}