{
  "type": "Feature",
  "properties": {
    "iso:country":"GB",
    "sg:address":"Knolton, Overton On Dee",
    "sg:city":"Wrexham",
    "sg:classifiers":[
        {
            "category":"Bars & Pubs",
            "type":"Food & Drink"
        }
    ],
    "sg:phone":"+44 1978 710743",
    "sg:postcode":"LL13 0LE",
    "sg:province":"Wrexham",
    "sg:tags":[
        "pubs",
        "inn"
    ],
    "wof:name":"The Trotting Mare",
    "wof:placetype":"venue"
},
  "geometry": {"coordinates":[-2.934289,52.968571],"type":"Point"}
}