{
  "type": "Feature",
  "properties": {
    "addr:full":"26 Almonds Grn Liverpool Merseyside L12 5HS",
    "addr:housenumber":"26",
    "addr:postcode":"l12 5hs",
    "addr:street":"Almonds Grn",
    "iso:country":"GB",
    "sg:address":"26 Almonds Grn",
    "sg:city":"Liverpool",
    "sg:classifiers":[
        {
            "category":"Personal",
            "subcategory":"Beauty Salon",
            "type":"Services"
        }
    ],
    "sg:postcode":"L12 5HS",
    "sg:province":"Merseyside",
    "sg:tags":[
        "unisex",
        "hairdresser"
    ],
    "wof:name":"Empire Hair",
    "wof:placetype":"venue"
},
  "geometry": {"coordinates":[-2.911370039,53.4332771301],"type":"Point"}
}