{
  "type": "Feature",
  "properties": {
    "iso:country":"GB",
    "sg:address":"Rear Of 28 Church Street",
    "sg:city":"Dagenham",
    "sg:classifiers":[
        {
            "category":"Retail",
            "subcategory":"Repair Shop",
            "type":"Services"
        }
    ],
    "sg:phone":"+44 20 8984 8664",
    "sg:postcode":"RM10 9UR",
    "sg:province":"Essex",
    "sg:tags":[
        "radio",
        "television",
        "video"
    ],
    "wof:name":"Teletec",
    "wof:placetype":"venue"
},
  "geometry": {"coordinates":[0.147961,51.541618],"type":"Point"}
}