{
  "type": "Feature",
  "properties": {
    "addr:full":"Unit 1, Catherine Street West, Denton Manchester Greater Manchester M34 3SB",
    "addr:housenumber":"unit 1",
    "addr:postcode":"m34 3sb",
    "addr:street":"Catherine Street West",
    "iso:country":"GB",
    "sg:address":"Unit 1, Catherine Street West, Denton",
    "sg:city":"Manchester",
    "sg:classifiers":[
        {
            "category":"Professional",
            "type":"Services"
        }
    ],
    "sg:postcode":"M34 3SB",
    "sg:province":"Greater Manchester",
    "sg:tags":[
        "exhibition"
    ],
    "wof:name":"Benyon,Mark,",
    "wof:placetype":"venue"
},
  "geometry": {"coordinates":[-2.127274,53.455727],"type":"Point"}
}