{
  "type": "Feature",
  "properties": {
    "addr:full":"3 North St Hornchurch Essex RM11 1RL",
    "addr:housenumber":"3",
    "addr:postcode":"rm11 1rl",
    "addr:street":"North St",
    "iso:country":"GB",
    "sg:address":"3 North St",
    "sg:city":"Hornchurch",
    "sg:classifiers":[
        {
            "category":"Cafe",
            "type":"Food & Drink"
        }
    ],
    "sg:phone":"+44 1708 451450",
    "sg:postcode":"RM11 1RL",
    "sg:province":"Essex",
    "sg:tags":[
        "tea",
        "room"
    ],
    "wof:name":"Frenchs Cafe & Catering",
    "wof:placetype":"venue"
},
  "geometry": {"coordinates":[0.219929,51.562607],"type":"Point"}
}