{
  "type": "Feature",
  "properties": {
    "addr:full":"Salem Street Amlwch Isle of Anglesey LL68 9DD",
    "addr:postcode":"ll68 9dd",
    "addr:street":"Salem Street",
    "iso:country":"GB",
    "sg:address":"Salem Street",
    "sg:city":"Amlwch",
    "sg:classifiers":[
        {
            "category":"Travel",
            "subcategory":"Hotels & Motels",
            "type":"Entertainment"
        },
        {
            "category":"Taxi",
            "type":"Transportation"
        }
    ],
    "sg:phone":"+44 1407 832122",
    "sg:postcode":"LL68 9DD",
    "sg:province":"Isle of Anglesey",
    "sg:tags":[
        "mini",
        "guest",
        "cab",
        "house"
    ],
    "wof:name":"Penycefn Guest House",
    "wof:placetype":"venue"
},
  "geometry": {"coordinates":[-4.3442111015,53.4080505371],"type":"Point"}
}