{
  "type": "Feature",
  "properties": {
    "addr:full":"2 Cross Hill, Hemsworth Pontefract West Yorkshire WF9 4LQ",
    "addr:housenumber":"2",
    "addr:postcode":"wf9 4lq",
    "addr:street":"Cross Hill",
    "iso:country":"GB",
    "sg:address":"2 Cross Hill, Hemsworth",
    "sg:city":"Pontefract",
    "sg:classifiers":[
        {
            "category":"Bars & Pubs",
            "type":"Food & Drink"
        }
    ],
    "sg:phone":"+44 1977 616788",
    "sg:postcode":"WF9 4LQ",
    "sg:province":"West Yorkshire",
    "sg:tags":[
        "pubs",
        "inn"
    ],
    "wof:name":"Abdul Aziz",
    "wof:placetype":"venue"
},
  "geometry": {"coordinates":[-1.3536490202,53.6136894226],"type":"Point"}
}