{
  "type": "Feature",
  "properties": {
    "iso:country":"GB",
    "sg:address":"77-79 Main Street, Cardenden",
    "sg:city":"Lochgelly",
    "sg:classifiers":[
        {
            "category":"Bars & Pubs",
            "type":"Food & Drink"
        }
    ],
    "sg:phone":"+44 1592 720396",
    "sg:postcode":"KY5 0NA",
    "sg:province":"Fife",
    "sg:tags":[
        "pubs",
        "inn"
    ],
    "wof:name":"The Auld Hoose",
    "wof:placetype":"venue"
},
  "geometry": {"coordinates":[-3.23904,56.175129],"type":"Point"}
}