{
  "type": "Feature",
  "properties": {
    "iso:country":"GB",
    "sg:address":"Level 16 City Tower, 40 Basinghall Street",
    "sg:city":"London",
    "sg:classifiers":[
        {
            "category":"Professional",
            "subcategory":"Lawyer & Legal Services",
            "type":"Services"
        }
    ],
    "sg:phone":"+44 20 7382 0550",
    "sg:postcode":"EC2V 5DE",
    "sg:province":"Greater London",
    "wof:name":"Andrews & Kurth",
    "wof:placetype":"venue"
},
  "geometry": {"coordinates":[-0.09145,51.51693],"type":"Point"}
}