{
  "type": "Feature",
  "properties": {
    "addr:full":"Unit 4 3 Wembley Commercial Cent, Re Wembley Greater London HA9 7UR",
    "addr:housenumber":"unit;3",
    "addr:postcode":"ha9 7ur",
    "addr:street":"Wembley",
    "iso:country":"GB",
    "sg:address":"Unit 4 3 Wembley Commercial Cent, Re",
    "sg:city":"Wembley",
    "sg:classifiers":[
        {
            "category":"Shopping",
            "subcategory":"Clothing, Apparel, & Fashions",
            "type":"Retail Goods"
        }
    ],
    "sg:phone":"+44 20 8908 6278",
    "sg:postcode":"HA9 7UR",
    "sg:province":"Greater London",
    "sg:tags":[
        "lingerie"
    ],
    "wof:name":"Benmark Foundations Ltd.",
    "wof:placetype":"venue"
},
  "geometry": {"coordinates":[-0.295539,51.552963],"type":"Point"}
}