{
  "type": "Feature",
  "properties": {
    "iso:country":"GB",
    "sg:address":"22 Forest Walk",
    "sg:city":"Watford",
    "sg:classifiers":[
        {
            "category":"Arts & Performance",
            "subcategory":"Music",
            "type":"Entertainment"
        }
    ],
    "sg:phone":"+44 1923 801836",
    "sg:postcode":"WD2 2BX",
    "sg:province":"Hertfordshire",
    "sg:tags":[
        "mobile",
        "disco"
    ],
    "wof:name":"A New Decade",
    "wof:placetype":"venue"
},
  "geometry": {"coordinates":[-0.401656,51.693039],"type":"Point"}
}