{
  "type": "Feature",
  "properties": {
    "iso:country":"GB",
    "sg:address":"15 Greenway Drive",
    "sg:city":"Ashton-under-lyne",
    "sg:classifiers":[
        {
            "category":"Building & Trades",
            "subcategory":"Construction",
            "type":"Services"
        }
    ],
    "sg:phone":"+44 1457 832000",
    "sg:postcode":"OL5 0QE",
    "sg:province":"Greater Manchester",
    "sg:tags":[
        "builder"
    ],
    "wof:name":"Ricbrad Roofing",
    "wof:placetype":"venue"
},
  "geometry": {"coordinates":[-2.046286,53.522255],"type":"Point"}
}