{
  "type": "Feature",
  "properties": {
    "addr:full":"21b High St Saffron Walden Cambridgeshire CB10 1AT",
    "addr:housenumber":"21b",
    "addr:postcode":"cb10 1at",
    "addr:street":"High St",
    "iso:country":"GB",
    "sg:address":"21b High St",
    "sg:city":"Saffron Walden",
    "sg:classifiers":[
        {
            "category":"Professional",
            "subcategory":"Management & Consulting",
            "type":"Services"
        }
    ],
    "sg:postcode":"CB10 1AT",
    "sg:province":"Cambridgeshire",
    "sg:tags":[
        "consultant",
        "business"
    ],
    "wof:name":"J S D Lazco Management",
    "wof:placetype":"venue"
},
  "geometry": {"coordinates":[0.2384629995,52.0233192444],"type":"Point"}
}