{
  "type": "Feature",
  "properties": {
    "iso:country":"GB",
    "sg:address":"90 Cravells Rd",
    "sg:city":"Harpenden",
    "sg:classifiers":[
        {
            "category":"Real Estate",
            "subcategory":"Real Estate Services",
            "type":"Services"
        }
    ],
    "sg:phone":"+44 1582 767795",
    "sg:postcode":"AL5 1BG",
    "sg:province":"Hertfordshire",
    "sg:tags":[
        "management",
        "facility"
    ],
    "wof:name":"Stuart Evans Consultancy",
    "wof:placetype":"venue"
},
  "geometry": {"coordinates":[-0.345131,51.804798],"type":"Point"}
}