{
  "type": "Feature",
  "properties": {
    "addr:full":"21 Riverside Crescent, Catrine Mauchline East Ayrshire KA5 6SJ",
    "addr:housenumber":"21",
    "addr:postcode":"ka5 6sj",
    "addr:street":"Riverside Crescent Catrine Mauchline East",
    "iso:country":"GB",
    "sg:address":"21 Riverside Crescent, Catrine",
    "sg:city":"Mauchline",
    "sg:classifiers":[
        {
            "category":"Professional",
            "subcategory":"Business Services",
            "type":"Services"
        }
    ],
    "sg:postcode":"KA5 6SJ",
    "sg:province":"East Ayrshire",
    "sg:tags":[
        "shop",
        "cleaning"
    ],
    "wof:name":"H B Services",
    "wof:placetype":"venue"
},
  "geometry": {"coordinates":[-4.325664,55.504803],"type":"Point"}
}