{
  "type": "Feature",
  "properties": {
    "addr:full":"11 Leeds Road Nelson Lancashire BB9 9SZ",
    "addr:housenumber":"11",
    "addr:postcode":"bb9 9sz",
    "addr:street":"Leeds Road",
    "iso:country":"GB",
    "sg:address":"11 Leeds Road",
    "sg:city":"Nelson",
    "sg:classifiers":[
        {
            "category":"Food & Beverages",
            "subcategory":"Meat & Fish",
            "type":"Retail Goods"
        }
    ],
    "sg:phone":"+44 1282 614762",
    "sg:postcode":"BB9 9SZ",
    "sg:province":"Lancashire",
    "sg:tags":[
        "butcher"
    ],
    "wof:name":"HANSONS BUTCHERS",
    "wof:placetype":"venue"
},
  "geometry": {"coordinates":[-2.21312,53.837193],"type":"Point"}
}