{
  "type": "Feature",
  "properties": {
    "addr:full":"Dovers Farm, 21 Dovers Green Road Reigate Surrey RH2 8BU",
    "addr:housenumber":"21",
    "addr:postcode":"rh2 8bu",
    "addr:street":"Dovers Green Road",
    "iso:country":"GB",
    "sg:address":"Dovers Farm, 21 Dovers Green Road",
    "sg:city":"Reigate",
    "sg:classifiers":[
        {
            "category":"Professional",
            "subcategory":"Art Services",
            "type":"Services"
        }
    ],
    "sg:phone":"+44 1737 223242",
    "sg:postcode":"RH2 8BU",
    "sg:province":"Surrey",
    "sg:tags":[
        "graphic",
        "designer"
    ],
    "wof:name":"Graphic Art",
    "wof:placetype":"venue"
},
  "geometry": {"coordinates":[-0.204779,51.235744],"type":"Point"}
}