{
  "type": "Feature",
  "properties": {
    "iso:country":"GB",
    "sg:address":"78 York Road",
    "sg:city":"London",
    "sg:classifiers":[
        {
            "category":"Military Area",
            "subcategory":"Air Force Base",
            "type":"Public Place"
        }
    ],
    "sg:phone":"+44 20 7223 3086",
    "sg:postcode":"SW11 3QD",
    "sg:province":"Greater London",
    "sg:tags":[
        "decorative",
        "glass",
        "mirror",
        "mnfr"
    ],
    "wof:name":"The Bevelled Edge",
    "wof:placetype":"venue"
},
  "geometry": {"coordinates":[-0.176779002,51.4692001343],"type":"Point"}
}