{
  "type": "Feature",
  "properties": {
    "addr:full":"Bromage Avenue, Kingsbury Tamworth Staffordshire B78 2HN",
    "addr:postcode":"b78 2hn",
    "addr:street":"Bromage Avenue",
    "iso:country":"GB",
    "sg:address":"Bromage Avenue, Kingsbury",
    "sg:city":"Tamworth",
    "sg:classifiers":[
        {
            "category":"Education",
            "subcategory":"Library",
            "type":"Public Place"
        }
    ],
    "sg:phone":"+44 1827 872333",
    "sg:postcode":"B78 2HN",
    "sg:province":"Staffordshire",
    "sg:tags":[
        "book"
    ],
    "wof:name":"Kingsbury Library",
    "wof:placetype":"venue"
},
  "geometry": {"coordinates":[-1.684604,52.568169],"type":"Point"}
}