{
  "type": "Feature",
  "properties": {
    "iso:country":"GB",
    "sg:address":"38 Tilworth Road",
    "sg:city":"Hull",
    "sg:classifiers":[
        {
            "category":"Building & Trades",
            "subcategory":"Construction",
            "type":"Services"
        }
    ],
    "sg:postcode":"HU8 9BN",
    "sg:province":"East Riding of Yorkshire",
    "sg:tags":[
        "roofing"
    ],
    "wof:name":"D S Felters",
    "wof:placetype":"venue"
},
  "geometry": {"coordinates":[-0.2906759977,53.7694816589],"type":"Point"}
}