{
  "type": "Feature",
  "properties": {
    "addr:full":"Helmsley, Hawnby York North Yorkshire YO62 5QU",
    "addr:postcode":"yo62 5qu",
    "iso:country":"GB",
    "sg:address":"Helmsley, Hawnby",
    "sg:city":"York",
    "sg:classifiers":[
        {
            "category":"Transit Center",
            "subcategory":"Passenger",
            "type":"Transportation"
        }
    ],
    "sg:postcode":"YO62 5QU",
    "sg:province":"North Yorkshire",
    "sg:tags":[
        "boarding",
        "kennel",
        "catteries"
    ],
    "wof:name":"Rye Boarding Kennels",
    "wof:placetype":"venue"
},
  "geometry": {"coordinates":[-1.1671060324,54.2991752625],"type":"Point"}
}