{
  "type": "Feature",
  "properties": {
    "addr:full":"The Bungalow, Birchall Lane, Cole Green Hertford Hertfordshire SG14 2NR",
    "addr:postcode":"sg14 2nr",
    "addr:street":"Birchall Lane",
    "iso:country":"GB",
    "sg:address":"The Bungalow, Birchall Lane, Cole Green",
    "sg:city":"Hertford",
    "sg:classifiers":[
        {
            "category":"Transit Center",
            "subcategory":"Passenger",
            "type":"Transportation"
        },
        {
            "category":"Retail",
            "subcategory":"Pet Boarding",
            "type":"Services"
        }
    ],
    "sg:phone":"+44 1707 325337",
    "sg:postcode":"SG14 2NR",
    "sg:province":"Hertfordshire",
    "sg:tags":[
        "kennel",
        "catteries"
    ],
    "wof:name":"The Mews Cattery",
    "wof:placetype":"venue"
},
  "geometry": {"coordinates":[-0.141909,51.786388],"type":"Point"}
}