{
  "type": "Feature",
  "properties": {
    "addr:full":"The Malthouse, Springhill Lane Wolverhampton Staffordshire WV4 4UF",
    "addr:postcode":"wv4 4uf",
    "addr:street":"Springhill Lane",
    "iso:country":"GB",
    "sg:address":"The Malthouse, Springhill Lane",
    "sg:city":"Wolverhampton",
    "sg:classifiers":[
        {
            "category":"Banks & Credit Unions",
            "subcategory":"Investment Brokerage",
            "type":"Services"
        }
    ],
    "sg:phone":"+44 1902 332618",
    "sg:postcode":"WV4 4UF",
    "sg:province":"Staffordshire",
    "sg:tags":[
        "agent"
    ],
    "wof:name":"Lees Agencies",
    "wof:placetype":"venue"
},
  "geometry": {"coordinates":[-2.19446,52.562641],"type":"Point"}
}