{
  "type": "Feature",
  "properties": {
    "addr:full":"29 Chapel Market London Greater London N1 9EN",
    "addr:housenumber":"29",
    "addr:postcode":"n1 9en",
    "addr:street":"Chapel Market",
    "iso:country":"GB",
    "sg:address":"29 Chapel Market",
    "sg:city":"London",
    "sg:classifiers":[
        {
            "category":"Shopping",
            "subcategory":"Bicycles & Sporting Goods",
            "type":"Retail Goods"
        }
    ],
    "sg:phone":"+44 20 7278 1631",
    "sg:postcode":"N1 9EN",
    "sg:province":"Greater London",
    "sg:tags":[
        "shop",
        "cycle",
        "accessory"
    ],
    "wof:name":"S & S Cycles",
    "wof:placetype":"venue"
},
  "geometry": {"coordinates":[-0.108442001,51.5336685181],"type":"Point"}
}