{
  "type": "Feature",
  "properties": {
    "addr:full":"Flat 4,127 Durham Rd, Wimbledon London Greater London SW20 0DF",
    "addr:housenumber":"flat 4,127",
    "addr:postcode":"sw20 0df",
    "addr:street":"Durham Rd",
    "iso:country":"GB",
    "sg:address":"Flat 4,127 Durham Rd, Wimbledon",
    "sg:city":"London",
    "sg:classifiers":[
        {
            "category":"Professional",
            "subcategory":"Art Services",
            "type":"Services"
        }
    ],
    "sg:postcode":"SW20 0DF",
    "sg:province":"Greater London",
    "sg:tags":[
        "photographer"
    ],
    "wof:name":"Wainscot,Belinda,",
    "wof:placetype":"venue"
},
  "geometry": {"coordinates":[-0.23404,51.413761],"type":"Point"}
}