{
  "type": "Feature",
  "properties": {
    "addr:full":"52 Kingsway, Dymchurch Romney Marsh Kent TN29 0LZ",
    "addr:housenumber":"52;dymchurch",
    "addr:postcode":"tn29 0lz",
    "addr:street":"Kingsway",
    "iso:country":"GB",
    "sg:address":"52 Kingsway, Dymchurch",
    "sg:city":"Romney Marsh",
    "sg:classifiers":[
        {
            "category":"Building & Trades",
            "subcategory":"Construction",
            "type":"Services"
        }
    ],
    "sg:phone":"+44 1303 872343",
    "sg:postcode":"TN29 0LZ",
    "sg:province":"Kent",
    "sg:tags":[
        "builder"
    ],
    "wof:name":"J C Building Contractors",
    "wof:placetype":"venue"
},
  "geometry": {"coordinates":[0.9226999879,51.0038833618],"type":"Point"}
}