{
  "type": "Feature",
  "properties": {
    "addr:full":"The Causeway Colchester Essex CO4 4DJ",
    "addr:postcode":"co4 4dj",
    "addr:street":"The Causeway Colchester",
    "iso:country":"GB",
    "sg:address":"The Causeway",
    "sg:city":"Colchester",
    "sg:classifiers":[
        {
            "category":"Community Center",
            "subcategory":"Youth",
            "type":"Public Place"
        }
    ],
    "sg:phone":"+44 1206 500185",
    "sg:postcode":"CO4 4DJ",
    "sg:province":"Essex",
    "sg:tags":[
        "children's",
        "activity"
    ],
    "wof:name":"St Annes Adventure Playground",
    "wof:placetype":"venue"
},
  "geometry": {"coordinates":[0.927273,51.898632],"type":"Point"}
}