{
  "type": "Feature",
  "properties": {
    "iso:country":"GB",
    "sg:address":"25 Church St, Werrington",
    "sg:city":"Peterborough",
    "sg:classifiers":[
        {
            "category":"Building & Trades",
            "subcategory":"Construction",
            "type":"Services"
        }
    ],
    "sg:phone":"+44 1733 571600",
    "sg:postcode":"PE4 6QB",
    "sg:province":"Cambridgeshire",
    "sg:tags":[
        "joiner",
        "carpenter"
    ],
    "wof:name":"Ladds",
    "wof:placetype":"venue"
},
  "geometry": {"coordinates":[-0.276088,52.612827],"type":"Point"}
}