{
  "type": "Feature",
  "properties": {
    "addr:full":"3 Park Gate Umberleigh Devon EX37 9DA",
    "addr:housenumber":"3",
    "addr:postcode":"ex37 9da",
    "addr:street":"Park Gate Umberleigh",
    "iso:country":"GB",
    "sg:address":"3 Park Gate",
    "sg:city":"Umberleigh",
    "sg:classifiers":[
        {
            "category":"Food & Beverages",
            "subcategory":"Candy",
            "type":"Retail Goods"
        }
    ],
    "sg:postcode":"EX37 9DA",
    "sg:province":"Devon",
    "sg:tags":[
        "confectionery"
    ],
    "wof:name":"Cake Creations",
    "wof:placetype":"venue"
},
  "geometry": {"coordinates":[-3.9853448868,50.9958152771],"type":"Point"}
}