{
  "type": "Feature",
  "properties": {
    "addr:full":"324 Darwen Road, Bromley Cross Bolton Lancashire BL7 9BZ",
    "addr:housenumber":"324",
    "addr:postcode":"bl7 9bz",
    "addr:street":"Darwen Road",
    "iso:country":"GB",
    "sg:address":"324 Darwen Road, Bromley Cross",
    "sg:city":"Bolton",
    "sg:classifiers":[
        {
            "category":"Social Services",
            "subcategory":"Retirement Home",
            "type":"Services"
        }
    ],
    "sg:phone":"+44 1204 301214",
    "sg:postcode":"BL7 9BZ",
    "sg:province":"Lancashire",
    "sg:tags":[
        "rest"
    ],
    "wof:name":"St Martha's Rest Home",
    "wof:placetype":"venue"
},
  "geometry": {"coordinates":[-2.423671,53.617424],"type":"Point"}
}