{
  "type": "Feature",
  "properties": {
    "iso:country":"GB",
    "sg:address":"402 St. John St",
    "sg:city":"Clerkenwell",
    "sg:classifiers":[
        {
            "category":"Deli",
            "type":"Food & Drink"
        }
    ],
    "sg:phone":"+44 20 7713 1678",
    "sg:postcode":"EC1V 4NJ",
    "sg:province":"Greater London",
    "sg:tags":[
        "delicatessen"
    ],
    "wof:name":"Limoncello",
    "wof:placetype":"venue"
},
  "geometry": {"coordinates":[-0.10628,51.531422],"type":"Point"}
}