{
  "type": "Feature",
  "properties": {
    "addr:full":"Rose Cottage, Blackdown Beaminster Dorset DT8 3LE",
    "addr:housenumber":"beaminster",
    "addr:postcode":"dt8 3le",
    "iso:country":"GB",
    "sg:address":"Rose Cottage, Blackdown",
    "sg:city":"Beaminster",
    "sg:classifiers":[
        {
            "category":"Professional",
            "subcategory":"Detective & Security Services",
            "type":"Services"
        }
    ],
    "sg:phone":"+44 1308 868979",
    "sg:postcode":"DT8 3LE",
    "sg:province":"Dorset",
    "sg:tags":[
        "agency"
    ],
    "wof:name":"Square Deal Services",
    "wof:placetype":"venue"
},
  "geometry": {"coordinates":[-2.7388939857,50.8090057373],"type":"Point"}
}