{
  "type": "Feature",
  "properties": {
    "iso:country":"GB",
    "sg:address":"1 Main Street, Copmanthorpe",
    "sg:city":"York",
    "sg:classifiers":[
        {
            "category":"Personal",
            "subcategory":"Beauty Salon",
            "type":"Services"
        },
        {
            "category":"Personal",
            "subcategory":"Barber",
            "type":"Services"
        }
    ],
    "sg:phone":"+44 1904 708850",
    "sg:postcode":"YO23 3ST",
    "sg:province":"North Yorkshire",
    "sg:tags":[
        "unisex",
        "hairdresser"
    ],
    "wof:name":"New Image Hair Salon",
    "wof:placetype":"venue"
},
  "geometry": {"coordinates":[-1.1554330587,53.9301223755],"type":"Point"}
}