{
  "type": "Feature",
  "properties": {
    "addr:full":"Boon Hills Farm, Nether Langwith Mansfield Derbyshire NG20 9JQ",
    "addr:housenumber":"langwith",
    "addr:postcode":"ng20 9jq",
    "iso:country":"GB",
    "sg:address":"Boon Hills Farm, Nether Langwith",
    "sg:city":"Mansfield",
    "sg:classifiers":[
        {
            "category":"Travel",
            "subcategory":"Hotels & Motels",
            "type":"Entertainment"
        }
    ],
    "sg:phone":"+44 1623 743862",
    "sg:postcode":"NG20 9JQ",
    "sg:province":"Derbyshire",
    "sg:tags":[
        "house",
        "guest"
    ],
    "wof:name":"Palmers Of Boon Hills",
    "wof:placetype":"venue"
},
  "geometry": {"coordinates":[-1.208172,53.227638],"type":"Point"}
}