{
  "type": "Feature",
  "properties": {
    "iso:country":"GB",
    "sg:address":"23 Saxon Ct",
    "sg:city":"Telford",
    "sg:classifiers":[
        {
            "category":"Organizations",
            "subcategory":"Political Organization",
            "type":"Services"
        }
    ],
    "sg:phone":"+44 1952 253705",
    "sg:postcode":"TF1 4YN",
    "sg:province":"Shropshire",
    "sg:tags":[
        "party"
    ],
    "wof:name":"Green Party The",
    "wof:placetype":"venue"
},
  "geometry": {"coordinates":[-2.498797,52.714176],"type":"Point"}
}