{
  "type": "Feature",
  "properties": {
    "iso:country":"GB",
    "sg:address":"9 Winnats Close, Shirebrook",
    "sg:city":"Glossop",
    "sg:classifiers":[
        {
            "category":"Professional",
            "subcategory":"Accounting & Tax Preparation",
            "type":"Services"
        }
    ],
    "sg:postcode":"SK13 8RR",
    "sg:province":"Derbyshire",
    "sg:tags":[
        "accountant"
    ],
    "wof:name":"M A S Associates",
    "wof:placetype":"venue"
},
  "geometry": {"coordinates":[-1.929464,53.441521],"type":"Point"}
}