{
  "type": "Feature",
  "properties": {
    "addr:full":"Cotswold Avenue, Chadderton Oldham Lancashire OL9 8PJ",
    "addr:postcode":"ol9 8pj",
    "addr:street":"Cotswold Avenue",
    "iso:country":"GB",
    "sg:address":"Cotswold Avenue, Chadderton",
    "sg:city":"Oldham",
    "sg:classifiers":[
        {
            "category":"Freight",
            "type":"Transportation"
        }
    ],
    "sg:phone":"+44 161 628 2222",
    "sg:postcode":"OL9 8PJ",
    "sg:province":"Lancashire",
    "sg:tags":[
        "haulage",
        "road"
    ],
    "wof:name":"T Greenwood & Sons",
    "wof:placetype":"venue"
},
  "geometry": {"coordinates":[-2.1482839584,53.5347061157],"type":"Point"}
}