{
  "type": "Feature",
  "properties": {
    "iso:country":"GB",
    "sg:address":"437 Alfreton Road",
    "sg:city":"Nottingham",
    "sg:classifiers":[
        {
            "category":"Shopping",
            "subcategory":"Stationery & Office Supplies",
            "type":"Retail Goods"
        },
        {
            "category":"Professional",
            "subcategory":"Printing & Photocopies",
            "type":"Services"
        }
    ],
    "sg:phone":"+44 115 978 2343",
    "sg:postcode":"NG7 5LX",
    "sg:province":"Nottinghamshire",
    "sg:tags":[
        "equipment",
        "duplicating",
        "copying"
    ],
    "wof:name":"Copydoc",
    "wof:placetype":"venue"
},
  "geometry": {"coordinates":[-1.175628,52.963364],"type":"Point"}
}