{
  "type": "Feature",
  "properties": {
    "iso:country":"GB",
    "sg:address":"Landrine Farm, Mitchell",
    "sg:city":"Newquay",
    "sg:classifiers":[
        {
            "category":"Farming",
            "subcategory":"Livestock Farm",
            "type":"Manufacturing & Wholesale Goods"
        }
    ],
    "sg:phone":"+44 1872 510261",
    "sg:postcode":"TR8 5BB",
    "sg:province":"Cornwall",
    "sg:tags":[
        "others"
    ],
    "wof:name":"Brian J Townsend",
    "wof:placetype":"venue"
},
  "geometry": {"coordinates":[-5.006909,50.353168],"type":"Point"}
}