{
  "type": "Feature",
  "properties": {
    "addr:full":"The Workshop, Billets Farm Industrial Park Colchester Essex CO5 7RW",
    "addr:postcode":"co5 7rw",
    "addr:street":"Industrial Park",
    "iso:country":"GB",
    "sg:address":"The Workshop, Billets Farm Industrial Park",
    "sg:city":"Colchester",
    "sg:classifiers":[
        {
            "category":"Manufacturing",
            "subcategory":"Metals",
            "type":"Manufacturing & Wholesale Goods"
        }
    ],
    "sg:postcode":"CO5 7RW",
    "sg:province":"Essex",
    "sg:tags":[
        "steel",
        "fabricator",
        "erectors"
    ],
    "wof:name":"Popper & Carter",
    "wof:placetype":"venue"
},
  "geometry": {"coordinates":[0.8484899998,51.8152008057],"type":"Point"}
}