{
  "type": "Feature",
  "properties": {
    "addr:full":"85 Wilkins Road, Cowley Oxford Oxfordshire OX4 2JB",
    "addr:housenumber":"85",
    "addr:postcode":"ox4 2jb",
    "addr:street":"Wilkins Road",
    "iso:country":"GB",
    "sg:address":"85 Wilkins Road, Cowley",
    "sg:city":"Oxford",
    "sg:classifiers":[
        {
            "category":"Home & Garden",
            "subcategory":"Household Appliances",
            "type":"Retail Goods"
        },
        {
            "category":"Building & Trades",
            "subcategory":"Cleaning & Sanitation",
            "type":"Services"
        }
    ],
    "sg:phone":"+44 1865 747527",
    "sg:postcode":"OX4 2JB",
    "sg:province":"Oxfordshire",
    "sg:tags":[
        "cleaner",
        "repairer",
        "domestic",
        "sale",
        "vacuum"
    ],
    "wof:name":"Smith & Osman Services",
    "wof:placetype":"venue"
},
  "geometry": {"coordinates":[-1.2055900097,51.7353858948],"type":"Point"}
}