{
  "type": "Feature",
  "properties": {
    "addr:full":"Birch Park Ind Est, Huntington Rd York North Yorkshire YO31 9XX",
    "addr:postcode":"yo31 9xx",
    "addr:street":"Park;Huntington Rd",
    "iso:country":"GB",
    "sg:address":"Birch Park Ind Est, Huntington Rd",
    "sg:city":"York",
    "sg:classifiers":[
        {
            "category":"Freight",
            "type":"Transportation"
        }
    ],
    "sg:phone":"+44 1904 619105",
    "sg:postcode":"YO31 9XX",
    "sg:province":"North Yorkshire",
    "sg:tags":[
        "haulage",
        "road"
    ],
    "wof:name":"Royal Mail",
    "wof:placetype":"venue"
},
  "geometry": {"coordinates":[-1.06506,53.981209],"type":"Point"}
}