{
  "type": "Feature",
  "properties": {
    "iso:country":"GB",
    "sg:address":"Unit 15, 98 Victoria Rd",
    "sg:city":"Willesden",
    "sg:classifiers":[
        {
            "category":"Arts & Performance",
            "subcategory":"Theater",
            "type":"Entertainment"
        }
    ],
    "sg:phone":"+44 20 8961 9540",
    "sg:postcode":"NW10 6NB",
    "sg:province":"Greater London",
    "sg:tags":[
        "rehearsal",
        "studio",
        "facility"
    ],
    "wof:name":"Panic Rehearsal Studios",
    "wof:placetype":"venue"
},
  "geometry": {"coordinates":[-0.2554909885,51.5254478455],"type":"Point"}
}