{
  "type": "Feature",
  "properties": {
    "addr:full":"Manor Farm, Knights In The Bottom, Chickerell Weymouth Dorset DT3 4EA",
    "addr:housenumber":"knights",
    "addr:postcode":"dt3 4ea",
    "addr:street":"Manor",
    "iso:country":"GB",
    "sg:address":"Manor Farm, Knights In The Bottom, Chickerell",
    "sg:city":"Weymouth",
    "sg:classifiers":[
        {
            "category":"Farming",
            "subcategory":"Crops",
            "type":"Manufacturing & Wholesale Goods"
        },
        {
            "category":"Farming",
            "subcategory":"Livestock Farm",
            "type":"Manufacturing & Wholesale Goods"
        }
    ],
    "sg:phone":"+44 1305 770088",
    "sg:postcode":"DT3 4EA",
    "sg:province":"Dorset",
    "sg:tags":[
        "arable",
        "others"
    ],
    "wof:name":"L C Wheadon & Sons",
    "wof:placetype":"venue"
},
  "geometry": {"coordinates":[-2.505325079,50.6227722168],"type":"Point"}
}