{
  "type": "Feature",
  "properties": {
    "addr:full":"9 Cross Lane, Coal Aston Dronfield Derbyshire S18 3AL",
    "addr:housenumber":"9",
    "addr:postcode":"s18 3al",
    "addr:street":"Cross Lane",
    "iso:country":"GB",
    "sg:address":"9 Cross Lane, Coal Aston",
    "sg:city":"Dronfield",
    "sg:classifiers":[
        {
            "category":"Shopping",
            "subcategory":"News",
            "type":"Retail Goods"
        }
    ],
    "sg:phone":"+44 1246 412519",
    "sg:postcode":"S18 3AL",
    "sg:province":"Derbyshire",
    "sg:tags":[
        "newsagent"
    ],
    "wof:name":"W G & E Hallatt",
    "wof:placetype":"venue"
},
  "geometry": {"coordinates":[-1.4586490393,53.3105201721],"type":"Point"}
}