{
  "type": "Feature",
  "properties": {
    "iso:country":"GB",
    "sg:address":"Hoskyns Technology Park, 1 Avenue Rd, Aston",
    "sg:city":"Birmingham",
    "sg:classifiers":[
        {
            "category":"Professional",
            "subcategory":"Computer Services",
            "type":"Services"
        }
    ],
    "sg:phone":"+44 121 333 3536",
    "sg:postcode":"B6 4DU",
    "sg:province":"West Midlands",
    "sg:tags":[
        "bureau",
        "facility"
    ],
    "wof:name":"Cap Gemini UK plc",
    "wof:placetype":"venue"
},
  "geometry": {"coordinates":[-1.88409,52.496052],"type":"Point"}
}