{
  "type": "Feature",
  "properties": {
    "addr:full":"141 Otley Rd Harrogate North Yorkshire HG2 0AG",
    "addr:housenumber":"141",
    "addr:postcode":"hg2 0ag",
    "addr:street":"Otley Rd",
    "iso:country":"GB",
    "sg:address":"141 Otley Rd",
    "sg:city":"Harrogate",
    "sg:classifiers":[
        {
            "category":"Bars & Pubs",
            "type":"Food & Drink"
        }
    ],
    "sg:phone":"+44 1423 533031",
    "sg:postcode":"HG2 0AG",
    "sg:province":"North Yorkshire",
    "sg:tags":[
        "pubs",
        "inn"
    ],
    "wof:name":"Shepherd's Dog The",
    "wof:placetype":"venue"
},
  "geometry": {"coordinates":[-1.559540987,53.9813117981],"type":"Point"}
}