{
  "type": "Feature",
  "properties": {
    "iso:country":"GB",
    "sg:address":"Fox & Pheasant Center",
    "sg:city":"Colchester",
    "sg:classifiers":[
        {
            "category":"Home & Garden",
            "subcategory":"Furniture",
            "type":"Retail Goods"
        }
    ],
    "sg:phone":"+44 1787 223297",
    "sg:postcode":"CO6 2PS",
    "sg:province":"Essex",
    "wof:name":"Fox & Pheasant Ltd.",
    "wof:placetype":"venue"
},
  "geometry": {"coordinates":[0.73443,51.927219],"type":"Point"}
}