{
  "type": "Feature",
  "properties": {
    "iso:country":"GB",
    "sg:address":"1 Buxton Road",
    "sg:city":"Ashbourne",
    "sg:classifiers":[
        {
            "category":"Personal",
            "subcategory":"Beauty Salon",
            "type":"Services"
        }
    ],
    "sg:phone":"+44 1335 344588",
    "sg:postcode":"DE6 1EX",
    "sg:province":"Derbyshire",
    "sg:tags":[
        "unisex",
        "hairdresser"
    ],
    "wof:name":"Visage Beauty Salon",
    "wof:placetype":"venue"
},
  "geometry": {"coordinates":[-1.7328380346,53.0189704895],"type":"Point"}
}