{
  "type": "Feature",
  "properties": {
    "addr:full":"3 Wayside, Fieldway, New Addington Croydon Surrey CR0 9DX",
    "addr:housenumber":"3",
    "addr:postcode":"cr0 9dx",
    "addr:street":"Wayside Fieldway",
    "iso:country":"GB",
    "sg:address":"3 Wayside, Fieldway, New Addington",
    "sg:city":"Croydon",
    "sg:classifiers":[
        {
            "category":"Shopping",
            "subcategory":"News",
            "type":"Retail Goods"
        }
    ],
    "sg:phone":"+44 1689 843465",
    "sg:postcode":"CR0 9DX",
    "sg:province":"Surrey",
    "sg:tags":[
        "newsagent"
    ],
    "wof:name":"Forbuoys Ltd.",
    "wof:placetype":"venue"
},
  "geometry": {"coordinates":[-0.0215990003,51.3563270569],"type":"Point"}
}