{
  "type": "Feature",
  "properties": {
    "addr:full":"14 Shaw Bridge Street Clitheroe Lancashire BB7 1LZ",
    "addr:housenumber":"14",
    "addr:postcode":"bb7 1lz",
    "addr:street":"Shaw Bridge Street",
    "iso:country":"GB",
    "sg:address":"14 Shaw Bridge Street",
    "sg:city":"Clitheroe",
    "sg:classifiers":[
        {
            "category":"Food & Beverages",
            "subcategory":"Meat & Fish",
            "type":"Retail Goods"
        }
    ],
    "sg:phone":"+44 1200 424519",
    "sg:postcode":"BB7 1LZ",
    "sg:province":"Lancashire",
    "sg:tags":[
        "butcher"
    ],
    "wof:name":"Alpe's the Butchers",
    "wof:placetype":"venue"
},
  "geometry": {"coordinates":[-2.3869431019,53.8708953857],"type":"Point"}
}