{
  "type": "Feature",
  "properties": {
    "iso:country":"GB",
    "sg:address":"3b Windus Rd",
    "sg:city":"London",
    "sg:classifiers":[
        {
            "category":"Shopping",
            "subcategory":"Clothing, Apparel, & Fashions",
            "type":"Retail Goods"
        }
    ],
    "sg:postcode":"N16 6UP",
    "sg:province":"Greater London",
    "sg:tags":[
        "clothing",
        "fabric"
    ],
    "wof:name":"Panyiotou,E,",
    "wof:placetype":"venue"
},
  "geometry": {"coordinates":[-0.068957001,51.5666809082],"type":"Point"}
}