{
  "type": "Feature",
  "properties": {
    "iso:country":"GB",
    "sg:address":"2 Keirby Walk",
    "sg:city":"Burnley",
    "sg:classifiers":[
        {
            "category":"Shopping",
            "subcategory":"Shoes",
            "type":"Retail Goods"
        }
    ],
    "sg:phone":"+44 1282 424944",
    "sg:postcode":"BB11 2DE",
    "sg:province":"Lancashire",
    "sg:tags":[
        "shop"
    ],
    "wof:name":"Alec W Holt Ltd.",
    "wof:placetype":"venue"
},
  "geometry": {"coordinates":[-2.24008,53.789482],"type":"Point"}
}