{
  "type": "Feature",
  "properties": {
    "addr:full":"Lock Lane Castleford West Yorkshire WF10 2LA",
    "addr:postcode":"wf10 2la",
    "addr:street":"Lock Lane",
    "iso:country":"GB",
    "sg:address":"Lock Lane",
    "sg:city":"Castleford",
    "sg:classifiers":[
        {
            "category":"Home & Garden",
            "subcategory":"Building Materials",
            "type":"Retail Goods"
        }
    ],
    "sg:phone":"+44 1977 554162",
    "sg:postcode":"WF10 2LA",
    "sg:province":"West Yorkshire",
    "sg:tags":[
        "ready",
        "mixed",
        "concrete"
    ],
    "wof:name":"R M C Ready Mixed",
    "wof:placetype":"venue"
},
  "geometry": {"coordinates":[-1.351854,53.730743],"type":"Point"}
}