{
  "type": "Feature",
  "properties": {
    "iso:country":"GB",
    "sg:address":"Coolair House, Broadway, Dukinfield",
    "sg:city":"Stockport",
    "sg:classifiers":[
        {
            "category":"Manufacturing",
            "subcategory":"Buildings",
            "type":"Manufacturing & Wholesale Goods"
        }
    ],
    "sg:phone":"+44 161 343 6000",
    "sg:postcode":"SK16 4UR",
    "sg:province":"Greater Manchester",
    "sg:tags":[
        "system",
        "air conditioning"
    ],
    "wof:name":"Coolair Equipment Ltd.",
    "wof:placetype":"venue"
},
  "geometry": {"coordinates":[-2.0922238827,53.4761390686],"type":"Point"}
}