{
  "type": "Feature",
  "properties": {
    "addr:full":"Hanger G 2, Kemble Cirencester Gloucestershire GL7 6FD",
    "addr:housenumber":"2",
    "addr:postcode":"gl7 6fd",
    "addr:street":"Hanger G",
    "iso:country":"GB",
    "sg:address":"Hanger G 2, Kemble",
    "sg:city":"Cirencester",
    "sg:classifiers":[
        {
            "category":"Airport",
            "subcategory":"General Aviation",
            "type":"Transportation"
        }
    ],
    "sg:phone":"+44 1285 770917",
    "sg:postcode":"GL7 6FD",
    "sg:province":"Gloucestershire",
    "wof:name":"Delta Engineering Aviation Ltd.",
    "wof:placetype":"venue"
},
  "geometry": {"coordinates":[-1.9989819527,51.6832618713],"type":"Point"}
}