{
  "type": "Feature",
  "properties": {
    "iso:country":"GB",
    "sg:address":"Butterwick Road, Fishburn",
    "sg:city":"Stockton-on-tees",
    "sg:classifiers":[
        {
            "category":"Community Center",
            "subcategory":"Youth",
            "type":"Public Place"
        }
    ],
    "sg:phone":"+44 1740 620861",
    "sg:postcode":"TS21 4ED",
    "sg:province":"Durham",
    "sg:tags":[
        "organisation",
        "centre"
    ],
    "wof:name":"Fishburn Youth & Community Centre",
    "wof:placetype":"venue"
},
  "geometry": {"coordinates":[-1.4348289967,54.6827545166],"type":"Point"}
}