{
  "type": "Feature",
  "properties": {
    "addr:full":"11a Albany Road, Ansdell Lytham St Annes Lancashire FY8 4AT",
    "addr:housenumber":"11a",
    "addr:postcode":"fy8 4at",
    "addr:street":"Albany Road;St Annes",
    "iso:country":"GB",
    "sg:address":"11a Albany Road, Ansdell",
    "sg:city":"Lytham St Annes",
    "sg:classifiers":[
        {
            "category":"Building & Trades",
            "subcategory":"Landscaping Services",
            "type":"Services"
        }
    ],
    "sg:postcode":"FY8 4AT",
    "sg:province":"Lancashire",
    "sg:tags":[
        "gardening"
    ],
    "wof:name":"Gardens by Design",
    "wof:placetype":"venue"
},
  "geometry": {"coordinates":[-2.9915349483,53.7465629578],"type":"Point"}
}