{
  "type": "Feature",
  "properties": {
    "addr:full":"Liscorvah Sawmills, Penstraze, Chacewater Truro Cornwall TR4 8PF",
    "addr:postcode":"tr4 8pf",
    "addr:street":"Chacewater",
    "iso:country":"GB",
    "sg:address":"Liscorvah Sawmills, Penstraze, Chacewater",
    "sg:city":"Truro",
    "sg:classifiers":[
        {
            "category":"Manufacturing",
            "subcategory":"Buildings",
            "type":"Manufacturing & Wholesale Goods"
        }
    ],
    "sg:postcode":"TR4 8PF",
    "sg:province":"Cornwall",
    "sg:tags":[
        "portable"
    ],
    "wof:name":"Sale,Kevin,",
    "wof:placetype":"venue"
},
  "geometry": {"coordinates":[-5.160164,50.25626],"type":"Point"}
}