{
  "type": "Feature",
  "properties": {
    "iso:country":"GB",
    "sg:address":"11 Red Bank Road",
    "sg:city":"Blackpool",
    "sg:classifiers":[
        {
            "category":"Restaurant",
            "type":"Food & Drink"
        }
    ],
    "sg:phone":"+44 1253 351808",
    "sg:postcode":"FY2 9HN",
    "sg:province":"Lancashire",
    "wof:name":"Beavers Licensed Restaurant",
    "wof:placetype":"venue"
},
  "geometry": {"coordinates":[-3.0524349213,53.8498420715],"type":"Point"}
}