{
  "type": "Feature",
  "properties": {
    "iso:country":"GB",
    "sg:address":"Wesley House, Bull Hill",
    "sg:city":"Leatherhead",
    "sg:classifiers":[
        {
            "category":"Building & Trades",
            "subcategory":"Construction",
            "type":"Services"
        }
    ],
    "sg:phone":"+44 1372 386600",
    "sg:postcode":"KT22 7AH",
    "sg:province":"Surrey",
    "sg:tags":[
        "builder"
    ],
    "wof:name":"Castleoak Construction Care Homes Ltd",
    "wof:placetype":"venue"
},
  "geometry": {"coordinates":[-0.33136,51.297325],"type":"Point"}
}