{
  "type": "Feature",
  "properties": {
    "addr:full":"101 Broad St Reading Berkshire RG1 7QA",
    "addr:housenumber":"101",
    "addr:postcode":"rg1 7qa",
    "addr:street":"Broad St",
    "iso:country":"GB",
    "sg:address":"101 Broad St",
    "sg:city":"Reading",
    "sg:classifiers":[
        {
            "category":"Shopping",
            "subcategory":"Pets & Pet Supplies",
            "type":"Retail Goods"
        }
    ],
    "sg:phone":"+44 118 956 0656",
    "sg:postcode":"RG1 7QA",
    "sg:province":"Berkshire",
    "wof:name":"Petside",
    "wof:placetype":"venue"
},
  "geometry": {"coordinates":[-0.972717,51.455513],"type":"Point"}
}