{
  "type": "Feature",
  "properties": {
    "iso:country":"GB",
    "sg:address":"Elm Farm, Cambridge",
    "sg:city":"Gloucester",
    "sg:classifiers":[
        {
            "category":"Farming",
            "subcategory":"Livestock Farm",
            "type":"Manufacturing & Wholesale Goods"
        }
    ],
    "sg:postcode":"GL2 7AN",
    "sg:province":"Gloucestershire",
    "sg:tags":[
        "others"
    ],
    "wof:name":"Fowler,L G,",
    "wof:placetype":"venue"
},
  "geometry": {"coordinates":[-2.364144,51.73254],"type":"Point"}
}