{
  "type": "Feature",
  "properties": {
    "iso:country":"GB",
    "sg:address":"The Wharf, Bullocks Lane, Sutton",
    "sg:city":"Macclesfield",
    "sg:classifiers":[
        {
            "category":"Building & Trades",
            "subcategory":"Construction",
            "type":"Services"
        }
    ],
    "sg:phone":"+44 1260 253249",
    "sg:postcode":"SK11 0HE",
    "sg:province":"Cheshire",
    "sg:tags":[
        "roofing"
    ],
    "wof:name":"Hulley Roofing",
    "wof:placetype":"venue"
},
  "geometry": {"coordinates":[-2.11792,53.238701],"type":"Point"}
}