{
  "type": "Feature",
  "properties": {
    "iso:country":"GB",
    "sg:address":"6 New Street",
    "sg:city":"Warwick",
    "sg:classifiers":[
        {
            "category":"Shopping",
            "subcategory":"Shoes",
            "type":"Retail Goods"
        }
    ],
    "sg:phone":"+44 1926 493994",
    "sg:postcode":"CV34 4RX",
    "sg:province":"Warwickshire",
    "wof:name":"Cobbler Bob",
    "wof:placetype":"venue"
},
  "geometry": {"coordinates":[-1.590163,52.281784],"type":"Point"}
}