{
  "type": "Feature",
  "properties": {
    "iso:country":"GB",
    "sg:address":"26 Morford Street",
    "sg:city":"Bath",
    "sg:classifiers":[
        {
            "category":"Retail",
            "subcategory":"Auto Rental",
            "type":"Services"
        },
        {
            "category":"Wholesale",
            "subcategory":"Vending Machines",
            "type":"Manufacturing & Wholesale Goods"
        }
    ],
    "sg:postcode":"BA1 2RT",
    "sg:province":"Bath and North East Somerset",
    "sg:tags":[
        "sale",
        "supply"
    ],
    "wof:name":"Braddicks Vending",
    "wof:placetype":"venue"
},
  "geometry": {"coordinates":[-2.362313,51.388645],"type":"Point"}
}