{
  "type": "Feature",
  "properties": {
    "iso:country":"GB",
    "sg:address":"29 Parkway, Edgcombe Park",
    "sg:city":"Crowthorne",
    "sg:classifiers":[
        {
            "category":"Building & Trades",
            "subcategory":"Construction",
            "type":"Services"
        }
    ],
    "sg:postcode":"RG45 6EP",
    "sg:province":"Berkshire",
    "sg:tags":[
        "joiner",
        "carpenter"
    ],
    "wof:name":"Crowthorne Carpentry Services",
    "wof:placetype":"venue"
},
  "geometry": {"coordinates":[-0.8066980243,51.37342453],"type":"Point"}
}