{
  "type": "Feature",
  "properties": {
    "addr:full":"2 Nicholas Gardens London Greater London W5 5HY",
    "addr:housenumber":"2",
    "addr:postcode":"w5 5hy",
    "addr:street":"Nicholas Gardens",
    "iso:country":"GB",
    "sg:address":"2 Nicholas Gardens",
    "sg:city":"London",
    "sg:classifiers":[
        {
            "category":"Professional",
            "subcategory":"Computer Services",
            "type":"Services"
        }
    ],
    "sg:phone":"+44 20 8567 6941",
    "sg:postcode":"W5 5HY",
    "sg:province":"Greater London",
    "sg:tags":[
        "system",
        "software"
    ],
    "wof:name":"Wida Software Ltd.",
    "wof:placetype":"venue"
},
  "geometry": {"coordinates":[-0.3065789938,51.5067558289],"type":"Point"}
}