{
  "type": "Feature",
  "properties": {
    "iso:country":"GB",
    "sg:address":"23 North Wharf Road",
    "sg:city":"London",
    "sg:classifiers":[
        {
            "category":"Wholesale",
            "subcategory":"Books, Periodicals, & Newspapers",
            "type":"Manufacturing & Wholesale Goods"
        }
    ],
    "sg:postcode":"W2 1LA",
    "sg:province":"Greater London",
    "sg:tags":[
        "publishing"
    ],
    "wof:name":"Sussex Publications",
    "wof:placetype":"venue"
},
  "geometry": {"coordinates":[-0.173339,51.51907],"type":"Point"}
}