{
  "type": "Feature",
  "properties": {
    "iso:country":"GB",
    "sg:address":"Dunkeswell Airport",
    "sg:city":"Honiton",
    "sg:classifiers":[
        {
            "category":"Organizations",
            "subcategory":"Membership Organization",
            "type":"Services"
        }
    ],
    "sg:phone":"+44 1404 891226",
    "sg:postcode":"EX14 4RA",
    "sg:province":"Devon",
    "sg:tags":[
        "club"
    ],
    "wof:name":"Dunkeswell Air Centre",
    "wof:placetype":"venue"
},
  "geometry": {"coordinates":[-3.2374300957,50.8558998108],"type":"Point"}
}