{
  "type": "Feature",
  "properties": {
    "addr:full":"3 High Park, Hawarden Deeside Flintshire CH5 3EF",
    "addr:housenumber":"3",
    "addr:postcode":"ch5 3ef",
    "addr:street":"High",
    "iso:country":"GB",
    "sg:address":"3 High Park, Hawarden",
    "sg:city":"Deeside",
    "sg:classifiers":[
        {
            "category":"Retail",
            "subcategory":"Driving School",
            "type":"Services"
        }
    ],
    "sg:postcode":"CH5 3EF",
    "sg:province":"Flintshire",
    "wof:name":"Direct School of Motoring",
    "wof:placetype":"venue"
},
  "geometry": {"coordinates":[-3.033714,53.186661],"type":"Point"}
}