{
  "type": "Feature",
  "properties": {
    "addr:full":"21 Daws La London Greater London NW7 4SD",
    "addr:housenumber":"21",
    "addr:postcode":"nw7 4sd",
    "addr:street":"Daws La",
    "iso:country":"GB",
    "sg:address":"21 Daws La",
    "sg:city":"London",
    "sg:classifiers":[
        {
            "category":"Food & Beverages",
            "subcategory":"Liquor & Beverages",
            "type":"Retail Goods"
        }
    ],
    "sg:postcode":"NW7 4SD",
    "sg:province":"Greater London",
    "sg:tags":[
        "beer",
        "spirit",
        "wines"
    ],
    "wof:name":"Baker,Catherine,",
    "wof:placetype":"venue"
},
  "geometry": {"coordinates":[-0.24224,51.616024],"type":"Point"}
}