{
  "type": "Feature",
  "properties": {
    "addr:full":"8 Glasgow Road, Kirkintilloch Glasgow East Dunbartonshire G66 1SH",
    "addr:housenumber":"8",
    "addr:postcode":"g66 1sh",
    "addr:street":"Glasgow Road",
    "iso:country":"GB",
    "sg:address":"8 Glasgow Road, Kirkintilloch",
    "sg:city":"Glasgow",
    "sg:classifiers":[
        {
            "category":"Home & Garden",
            "subcategory":"Carpets & Floor Coverings",
            "type":"Retail Goods"
        }
    ],
    "sg:phone":"+44 141 777 9008",
    "sg:postcode":"G66 1SH",
    "sg:province":"East Dunbartonshire",
    "sg:tags":[
        "carpets",
        "rug",
        "matting"
    ],
    "wof:name":"Saltire Carpets",
    "wof:placetype":"venue"
},
  "geometry": {"coordinates":[-4.1635580063,55.9409675598],"type":"Point"}
}