{
  "type": "Feature",
  "properties": {
    "addr:full":"William Lilley Infant & Nursery, School, Halls Road Stapleford Nottingham Nottinghamshire NG9 7FS",
    "addr:postcode":"ng9 7fs",
    "addr:street":"Halls Road",
    "iso:country":"GB",
    "sg:address":"William Lilley Infant & Nursery, School, Halls Road Stapleford",
    "sg:city":"Nottingham",
    "sg:classifiers":[
        {
            "category":"Education",
            "subcategory":"School",
            "type":"Public Place"
        }
    ],
    "sg:phone":"+44 115 917 9277",
    "sg:postcode":"NG9 7FS",
    "sg:province":"Nottinghamshire",
    "sg:tags":[
        "local",
        "authority"
    ],
    "wof:name":"William Lilley Infant & Nursery School",
    "wof:placetype":"venue"
},
  "geometry": {"coordinates":[-1.27757,52.925152],"type":"Point"}
}