{
  "type": "Feature",
  "properties": {
    "addr:full":"Corbetts Mill, Bedford Square Leigh Lancashire WN7 2AA",
    "addr:postcode":"wn7 2aa",
    "addr:street":"Corbetts Mill Bedford Square Leigh",
    "iso:country":"GB",
    "sg:address":"Corbetts Mill, Bedford Square",
    "sg:city":"Leigh",
    "sg:classifiers":[
        {
            "category":"Shopping",
            "subcategory":"Stationery & Office Supplies",
            "type":"Retail Goods"
        }
    ],
    "sg:phone":"+44 1942 263400",
    "sg:postcode":"WN7 2AA",
    "sg:province":"Lancashire",
    "sg:tags":[
        "box",
        "carton"
    ],
    "wof:name":"Corbett Packaging Ltd.",
    "wof:placetype":"venue"
},
  "geometry": {"coordinates":[-2.5189940929,53.4969711304],"type":"Point"}
}