{
  "type": "Feature",
  "properties": {
    "addr:full":"Dene Park Hexham Northumberland NE46 1HN",
    "addr:postcode":"ne46 1hn",
    "addr:street":"Dene Park",
    "iso:country":"GB",
    "sg:address":"Dene Park",
    "sg:city":"Hexham",
    "sg:classifiers":[
        {
            "category":"Health Services",
            "subcategory":"Nursing And Care Facility",
            "type":"Services"
        },
        {
            "category":"Social Services",
            "subcategory":"Retirement Home",
            "type":"Services"
        }
    ],
    "sg:phone":"+44 1434 604520",
    "sg:postcode":"NE46 1HN",
    "sg:province":"Northumberland",
    "sg:tags":[
        "residential"
    ],
    "wof:name":"Dene Park House",
    "wof:placetype":"venue"
},
  "geometry": {"coordinates":[-2.087935,54.970367],"type":"Point"}
}