{
  "type": "Feature",
  "properties": {
    "addr:full":"Wheatley Hill Surgery, Thornley Rd Durham Durham DH6 3NR",
    "addr:postcode":"dh6 3nr",
    "addr:street":"Thornley Rd",
    "iso:country":"GB",
    "sg:address":"Wheatley Hill Surgery, Thornley Rd",
    "sg:city":"Durham",
    "sg:classifiers":[
        {
            "category":"Health Services",
            "subcategory":"Doctor",
            "type":"Services"
        }
    ],
    "sg:phone":"+44 1429 820233",
    "sg:postcode":"DH6 3NR",
    "sg:province":"Durham",
    "sg:tags":[
        "practitioners"
    ],
    "wof:name":"Patel Dr K",
    "wof:placetype":"venue"
},
  "geometry": {"coordinates":[-1.4212839603,54.7426490784],"type":"Point"}
}