{
  "type": "Feature",
  "properties": {
    "addr:full":"Roche Grange Farm Leek Staffordshire ST13 8TA",
    "addr:postcode":"st13 8ta",
    "iso:country":"GB",
    "sg:address":"Roche Grange Farm",
    "sg:city":"Leek",
    "sg:classifiers":[
        {
            "category":"Building & Trades",
            "subcategory":"Equipment Rental",
            "type":"Services"
        }
    ],
    "sg:phone":"+44 1538 300511",
    "sg:postcode":"ST13 8TA",
    "sg:province":"Staffordshire",
    "sg:tags":[
        "plant",
        "machinery"
    ],
    "wof:name":"P H Highton",
    "wof:placetype":"venue"
},
  "geometry": {"coordinates":[-2.020884,53.106476],"type":"Point"}
}