{
  "type": "Feature",
  "properties": {
    "iso:country":"GB",
    "sg:address":"Druids Heath Farm, Stonnall Road, Aldridge",
    "sg:city":"Walsall",
    "sg:classifiers":[
        {
            "category":"Food & Beverages",
            "subcategory":"Farmers Market",
            "type":"Retail Goods"
        }
    ],
    "sg:postcode":"WS9 0NQ",
    "sg:province":"Staffordshire",
    "sg:tags":[
        "farm",
        "shop",
        "pyo"
    ],
    "wof:name":"Samuel Ikin",
    "wof:placetype":"venue"
},
  "geometry": {"coordinates":[-1.9003399611,52.6164016724],"type":"Point"}
}