{
  "type": "Feature",
  "properties": {
    "addr:full":"Cowling Mill, Cowling Brow Chorley Lancashire PR6 0QG",
    "addr:postcode":"pr6 0qg",
    "addr:street":"Cowling",
    "iso:country":"GB",
    "sg:address":"Cowling Mill, Cowling Brow",
    "sg:city":"Chorley",
    "sg:classifiers":[
        {
            "category":"Community Center",
            "type":"Public Place"
        }
    ],
    "sg:phone":"+44 1257 265496",
    "sg:postcode":"PR6 0QG",
    "sg:province":"Lancashire",
    "sg:tags":[
        "recreation",
        "leisure",
        "centre"
    ],
    "wof:name":"Old Mill Leisure",
    "wof:placetype":"venue"
},
  "geometry": {"coordinates":[-2.616847,53.649628],"type":"Point"}
}