{
  "type": "Feature",
  "properties": {
    "iso:country":"GB",
    "sg:address":"Winchester Crescent, Chaddesden",
    "sg:city":"Derby",
    "sg:classifiers":[
        {
            "category":"Health Services",
            "subcategory":"Clinic",
            "type":"Services"
        }
    ],
    "sg:phone":"+44 1332 349312",
    "sg:postcode":"DE21 4EN",
    "sg:province":"Derbyshire",
    "sg:tags":[
        "nh"
    ],
    "wof:name":"Southern Derbyshire (N H S) Mental Health Trust",
    "wof:placetype":"venue"
},
  "geometry": {"coordinates":[-1.451938,52.935673],"type":"Point"}
}