{
  "type": "Feature",
  "properties": {
    "addr:full":"Unit 46 Martlands Indust Est Woking Surrey GU22 9EU",
    "addr:housenumber":"unit 46",
    "addr:postcode":"gu22 9eu",
    "addr:street":"Indust",
    "iso:country":"GB",
    "sg:address":"Unit 46 Martlands Indust Est",
    "sg:city":"Woking",
    "sg:classifiers":[
        {
            "category":"Building & Trades",
            "subcategory":"Landscaping Services",
            "type":"Services"
        }
    ],
    "sg:phone":"+44 1483 236615",
    "sg:postcode":"GU22 9EU",
    "sg:province":"Surrey",
    "sg:tags":[
        "gardening"
    ],
    "wof:name":"Skip Master",
    "wof:placetype":"venue"
},
  "geometry": {"coordinates":[-0.539729,51.301659],"type":"Point"}
}