{
  "type": "Feature",
  "properties": {
    "iso:country":"GB",
    "sg:address":"73 Adelaide Street",
    "sg:city":"Blackpool",
    "sg:classifiers":[
        {
            "category":"Travel",
            "subcategory":"Hotels & Motels",
            "type":"Entertainment"
        }
    ],
    "sg:phone":"+44 1253 628650",
    "sg:postcode":"FY1 4LN",
    "sg:province":"Lancashire",
    "sg:tags":[
        "house",
        "guest"
    ],
    "wof:name":"Shirley House",
    "wof:placetype":"venue"
},
  "geometry": {"coordinates":[-3.0487790108,53.8171005249],"type":"Point"}
}