{
  "type": "Feature",
  "properties": {
    "addr:full":"15 Bell St Reigate Surrey RH2 7AD",
    "addr:housenumber":"15",
    "addr:postcode":"rh2 7ad",
    "addr:street":"Bell St",
    "iso:country":"GB",
    "sg:address":"15 Bell St",
    "sg:city":"Reigate",
    "sg:classifiers":[
        {
            "category":"Banks & Credit Unions",
            "subcategory":"Financial Services",
            "type":"Services"
        }
    ],
    "sg:postcode":"RH2 7AD",
    "sg:province":"Surrey",
    "sg:tags":[
        "consultant"
    ],
    "wof:name":"Copperfield Business Finance Ltd",
    "wof:placetype":"venue"
},
  "geometry": {"coordinates":[-0.205019,51.236099],"type":"Point"}
}