{
  "type": "Feature",
  "properties": {
    "iso:country":"GB",
    "sg:address":"10 Ryebank, Bilsham Rd, Yapton",
    "sg:city":"Arundel",
    "sg:classifiers":[
        {
            "category":"Building & Trades",
            "subcategory":"Construction",
            "type":"Services"
        }
    ],
    "sg:postcode":"BN18 0JZ",
    "sg:province":"West Sussex",
    "sg:tags":[
        "builder"
    ],
    "wof:name":"A1 Mr Plastics",
    "wof:placetype":"venue"
},
  "geometry": {"coordinates":[-0.610515,50.819695],"type":"Point"}
}