{
  "type": "Feature",
  "properties": {
    "iso:country":"GB",
    "sg:address":"10-11 Bull St, Darlaston",
    "sg:city":"Wednesbury",
    "sg:classifiers":[
        {
            "category":"Shopping",
            "subcategory":"Clothing, Apparel, & Fashions",
            "type":"Retail Goods"
        }
    ],
    "sg:phone":"+44 121 526 3748",
    "sg:postcode":"WS10 8AX",
    "sg:province":"West Midlands",
    "sg:tags":[
        "clothing",
        "fabric"
    ],
    "wof:name":"Kelay's Sport & Leisure Ltd",
    "wof:placetype":"venue"
},
  "geometry": {"coordinates":[-2.0286369324,52.5689430237],"type":"Point"}
}