{
  "type": "Feature",
  "properties": {
    "addr:full":"Earlham Grove Wood Green Greater London N22 5HJ",
    "addr:postcode":"n22 5hj",
    "addr:street":"Earlham Grove",
    "iso:country":"GB",
    "sg:address":"Earlham Grove",
    "sg:city":"Wood Green",
    "sg:classifiers":[
        {
            "category":"Community Center",
            "type":"Public Place"
        }
    ],
    "sg:phone":"+44 20 8881 2329",
    "sg:postcode":"N22 5HJ",
    "sg:province":"Greater London",
    "sg:tags":[
        "centre"
    ],
    "wof:name":"Cypriot Community Centre",
    "wof:placetype":"venue"
},
  "geometry": {"coordinates":[-0.110654,51.603096],"type":"Point"}
}