{
  "type": "Feature",
  "properties": {
    "iso:country":"GB",
    "sg:address":"Martin Avenue",
    "sg:city":"March",
    "sg:classifiers":[
        {
            "category":"Sports & Exercise",
            "subcategory":"Gym",
            "type":"Entertainment"
        }
    ],
    "sg:phone":"+44 1354 661001",
    "sg:postcode":"PE15 0AY",
    "sg:province":"Cambridgeshire",
    "sg:tags":[
        "fitness",
        "health",
        "centre"
    ],
    "wof:name":"Alpine Health & Fitness Centre",
    "wof:placetype":"venue"
},
  "geometry": {"coordinates":[0.067535,52.562984],"type":"Point"}
}