{
  "type": "Feature",
  "properties": {
    "addr:full":"26 High Street Leiston Suffolk IP16 4EW",
    "addr:housenumber":"26",
    "addr:postcode":"ip16 4ew",
    "addr:street":"High Street",
    "iso:country":"GB",
    "sg:address":"26 High Street",
    "sg:city":"Leiston",
    "sg:classifiers":[
        {
            "category":"Health Services",
            "subcategory":"Optometrist",
            "type":"Services"
        },
        {
            "category":"Shopping",
            "subcategory":"Optician",
            "type":"Retail Goods"
        }
    ],
    "sg:phone":"+44 1728 833114",
    "sg:postcode":"IP16 4EW",
    "sg:province":"Suffolk",
    "sg:tags":[
        "ophthalmic"
    ],
    "wof:name":"Marshall & Lilley",
    "wof:placetype":"venue"
},
  "geometry": {"coordinates":[1.576899,52.207134],"type":"Point"}
}