{
  "type": "Feature",
  "properties": {
    "addr:full":"56 Newgate Avenue, Appley Bridge Wigan Lancashire WN6 9JJ",
    "addr:housenumber":"56",
    "addr:postcode":"wn6 9jj",
    "addr:street":"Newgate Avenue",
    "iso:country":"GB",
    "sg:address":"56 Newgate Avenue, Appley Bridge",
    "sg:city":"Wigan",
    "sg:classifiers":[
        {
            "category":"Retail",
            "subcategory":"Auto Repair",
            "type":"Services"
        }
    ],
    "sg:phone":"+44 1257 253304",
    "sg:postcode":"WN6 9JJ",
    "sg:province":"Lancashire",
    "sg:tags":[
        "engine",
        "car",
        "specialist"
    ],
    "wof:name":"Mobile Auto Doctors",
    "wof:placetype":"venue"
},
  "geometry": {"coordinates":[-2.7033450603,53.5809516907],"type":"Point"}
}