{
  "type": "Feature",
  "properties": {
    "addr:full":"Doris Road, Bordesley Green Birmingham West Midlands B9 4SJ",
    "addr:postcode":"b9 4sj",
    "addr:street":"Doris Road",
    "iso:country":"GB",
    "sg:address":"Doris Road, Bordesley Green",
    "sg:city":"Birmingham",
    "sg:classifiers":[
        {
            "category":"Manufacturing",
            "subcategory":"Food",
            "type":"Manufacturing & Wholesale Goods"
        },
        {
            "category":"Food & Beverages",
            "subcategory":"Supermarket",
            "type":"Retail Goods"
        }
    ],
    "sg:phone":"+44 121 771 0039",
    "sg:postcode":"B9 4SJ",
    "sg:province":"West Midlands",
    "sg:tags":[
        "frozen",
        "product",
        "manufacturer"
    ],
    "wof:name":"Raja Frozen Foods",
    "wof:placetype":"venue"
},
  "geometry": {"coordinates":[-1.8800840378,52.4777832031],"type":"Point"}
}