{
  "type": "Feature",
  "properties": {
    "addr:full":"9 Mountjoy Road Newport Newport NP20 2FB",
    "addr:housenumber":"9",
    "addr:postcode":"np20 2fb",
    "addr:street":"Mountjoy Road",
    "iso:country":"GB",
    "sg:address":"9 Mountjoy Road",
    "sg:city":"Newport",
    "sg:classifiers":[
        {
            "category":"Retail",
            "subcategory":"Auto Repair",
            "type":"Services"
        }
    ],
    "sg:phone":"+44 1633 266477",
    "sg:postcode":"NP20 2FB",
    "sg:province":"Newport",
    "sg:tags":[
        "modification",
        "garage"
    ],
    "wof:name":"Mountjoy Garage",
    "wof:placetype":"venue"
},
  "geometry": {"coordinates":[-2.99171,51.58075],"type":"Point"}
}