{
  "type": "Feature",
  "properties": {
    "iso:country":"GB",
    "sg:address":"Hardy House, The Street, Bethersden",
    "sg:city":"Ashford",
    "sg:classifiers":[
        {
            "category":"Organizations",
            "subcategory":"Political Organization",
            "type":"Services"
        }
    ],
    "sg:phone":"+44 1233 820454",
    "sg:postcode":"TN26 3AG",
    "sg:province":"Kent",
    "sg:tags":[
        "party"
    ],
    "wof:name":"Conservative Association",
    "wof:placetype":"venue"
},
  "geometry": {"coordinates":[0.756475,51.129272],"type":"Point"}
}