{
  "type": "Feature",
  "properties": {
    "iso:country":"GB",
    "sg:address":"82-86 North Road",
    "sg:city":"Darlington",
    "sg:classifiers":[
        {
            "category":"Shopping",
            "subcategory":"Catalog Store",
            "type":"Retail Goods"
        },
        {
            "category":"Shopping",
            "subcategory":"Luggage & Leather Goods",
            "type":"Retail Goods"
        }
    ],
    "sg:postcode":"DL1 2EQ",
    "sg:province":"Durham",
    "sg:tags":[
        "shop",
        "mail",
        "order",
        "leathergoods"
    ],
    "wof:name":"Y G Ltd.",
    "wof:placetype":"venue"
},
  "geometry": {"coordinates":[-1.552404,54.537399],"type":"Point"}
}