{
  "type": "Feature",
  "properties": {
    "addr:full":"124 Goodmayes Lane Ilford Essex IG3 9FX",
    "addr:housenumber":"124",
    "addr:postcode":"ig3 9fx",
    "addr:street":"Goodmayes Lane",
    "iso:country":"GB",
    "sg:address":"124 Goodmayes Lane",
    "sg:city":"Ilford",
    "sg:classifiers":[
        {
            "category":"Health Services",
            "subcategory":"Nursing And Care Facility",
            "type":"Services"
        }
    ],
    "sg:phone":"+44 20 8590 6604",
    "sg:postcode":"IG3 9FX",
    "sg:province":"Essex",
    "sg:tags":[
        "home"
    ],
    "wof:name":"Anchor Care Alternatives",
    "wof:placetype":"venue"
},
  "geometry": {"coordinates":[0.1076190025,51.5562057495],"type":"Point"}
}