{
  "type": "Feature",
  "properties": {
    "iso:country":"GB",
    "sg:address":"30 Arbroath Rd",
    "sg:city":"Dundee",
    "sg:classifiers":[
        {
            "category":"Building & Trades",
            "subcategory":"Cleaning & Sanitation",
            "type":"Services"
        }
    ],
    "sg:phone":"+44 1382 450795",
    "sg:postcode":"DD4 6EP",
    "sg:province":"Dundee City",
    "sg:tags":[
        "dry",
        "control",
        "damp",
        "rot"
    ],
    "wof:name":"Longs Of Dundee",
    "wof:placetype":"venue"
},
  "geometry": {"coordinates":[-2.9560399055,56.4684906006],"type":"Point"}
}