{
  "type": "Feature",
  "properties": {
    "addr:full":"52 High Street Lowestoft Suffolk NR32 1JA",
    "addr:housenumber":"52",
    "addr:postcode":"nr32 1ja",
    "addr:street":"High Street",
    "iso:country":"GB",
    "sg:address":"52 High Street",
    "sg:city":"Lowestoft",
    "sg:classifiers":[
        {
            "category":"Personal",
            "subcategory":"Beauty Salon",
            "type":"Services"
        }
    ],
    "sg:phone":"+44 1502 574379",
    "sg:postcode":"NR32 1JA",
    "sg:province":"Suffolk",
    "sg:tags":[
        "unisex",
        "hairdresser"
    ],
    "wof:name":"Heiner of Switzerland",
    "wof:placetype":"venue"
},
  "geometry": {"coordinates":[1.7561899424,52.4825668335],"type":"Point"}
}