{
  "type": "Feature",
  "properties": {
    "addr:full":"63-69 Eltham Road London Greater London SE12 8UF",
    "addr:housenumber":"63-69",
    "addr:postcode":"se12 8uf",
    "addr:street":"Eltham Road",
    "iso:country":"GB",
    "sg:address":"63-69 Eltham Road",
    "sg:city":"London",
    "sg:classifiers":[
        {
            "category":"Professional",
            "subcategory":"Management & Consulting",
            "type":"Services"
        }
    ],
    "sg:phone":"+44 20 8852 1261",
    "sg:postcode":"SE12 8UF",
    "sg:province":"Greater London",
    "sg:tags":[
        "consultant",
        "business"
    ],
    "wof:name":"Management International Ltd.",
    "wof:placetype":"venue"
},
  "geometry": {"coordinates":[0.0204579998,51.4544563293],"type":"Point"}
}