{
  "type": "Feature",
  "properties": {
    "addr:full":"176 Charlton Rd, Charlton London Greater London SE7 7DW",
    "addr:housenumber":"176",
    "addr:postcode":"se7 7dw",
    "addr:street":"Charlton Rd",
    "iso:country":"GB",
    "sg:address":"176 Charlton Rd, Charlton",
    "sg:city":"London",
    "sg:classifiers":[
        {
            "category":"Building & Trades",
            "subcategory":"Construction",
            "type":"Services"
        }
    ],
    "sg:phone":"+44 20 8856 0565",
    "sg:postcode":"SE7 7DW",
    "sg:province":"Greater London",
    "sg:tags":[
        "builder"
    ],
    "wof:name":"Foley's Builders & Decorators Ltd",
    "wof:placetype":"venue"
},
  "geometry": {"coordinates":[0.032786,51.479607],"type":"Point"}
}