{
  "type": "Feature",
  "properties": {
    "addr:full":"12a Hursley Road, Chandlers Ford Eastleigh Hampshire SO53 2FU",
    "addr:housenumber":"12a",
    "addr:postcode":"so53 2fu",
    "addr:street":"Hursley Road",
    "iso:country":"GB",
    "sg:address":"12a Hursley Road, Chandlers Ford",
    "sg:city":"Eastleigh",
    "sg:classifiers":[
        {
            "category":"Professional",
            "subcategory":"Computer Services",
            "type":"Services"
        }
    ],
    "sg:phone":"+44 1202 890244",
    "sg:postcode":"SO53 2FU",
    "sg:province":"Hampshire",
    "sg:tags":[
        "system",
        "software"
    ],
    "wof:name":"W A Computing",
    "wof:placetype":"venue"
},
  "geometry": {"coordinates":[-1.385046,50.984337],"type":"Point"}
}