{
  "type": "Feature",
  "properties": {
    "addr:full":"6 Broad Street Llandovery Carmarthenshire SA20 0AR",
    "addr:housenumber":"6",
    "addr:postcode":"sa20 0ar",
    "addr:street":"Broad Street",
    "iso:country":"GB",
    "sg:address":"6 Broad Street",
    "sg:city":"Llandovery",
    "sg:classifiers":[
        {
            "category":"Building & Trades",
            "subcategory":"Plumbing",
            "type":"Services"
        }
    ],
    "sg:phone":"+44 1550 720478",
    "sg:postcode":"SA20 0AR",
    "sg:province":"Carmarthenshire",
    "sg:tags":[
        "heating"
    ],
    "wof:name":"Des Clarke & Son",
    "wof:placetype":"venue"
},
  "geometry": {"coordinates":[-3.797836,51.99345],"type":"Point"}
}