{
  "type": "Feature",
  "properties": {
    "iso:country":"GB",
    "sg:address":"Betchworth House, 57-65 Station Road",
    "sg:city":"Redhill",
    "sg:classifiers":[
        {
            "category":"Government",
            "subcategory":"Office",
            "type":"Public Place"
        }
    ],
    "sg:phone":"+44 1737 854200",
    "sg:postcode":"RH1 1QB",
    "sg:province":"Surrey",
    "sg:tags":[
        "inland",
        "revenue"
    ],
    "wof:name":"Board of Inland Revenue",
    "wof:placetype":"venue"
},
  "geometry": {"coordinates":[-0.1693120003,51.2403106689],"type":"Point"}
}