{
  "type": "Feature",
  "properties": {
    "iso:country":"GB",
    "sg:address":"20 Belvoir Road, Bottesford",
    "sg:city":"Nottingham",
    "sg:classifiers":[
        {
            "category":"Professional",
            "subcategory":"Art Services",
            "type":"Services"
        },
        {
            "category":"Building & Trades",
            "subcategory":"Construction",
            "type":"Services"
        }
    ],
    "sg:phone":"+44 1949 842614",
    "sg:postcode":"NG13 0BG",
    "sg:province":"Leicestershire",
    "sg:tags":[
        "decorator",
        "painter"
    ],
    "wof:name":"Corbyn W George",
    "wof:placetype":"venue"
},
  "geometry": {"coordinates":[-0.804348,52.93784],"type":"Point"}
}