{
  "type": "Feature",
  "properties": {
    "iso:country":"GB",
    "sg:address":"20 Bellevue Road",
    "sg:city":"Southampton",
    "sg:classifiers":[
        {
            "category":"Health Services",
            "subcategory":"Doctor",
            "type":"Services"
        },
        {
            "category":"Professional",
            "subcategory":"Management & Consulting",
            "type":"Services"
        }
    ],
    "sg:phone":"+44 23 8022 1771",
    "sg:postcode":"SO15 2AY",
    "sg:province":"Hampshire",
    "sg:tags":[
        "specialist",
        "practitioners",
        "consultant"
    ],
    "wof:name":"Cameleon",
    "wof:placetype":"venue"
},
  "geometry": {"coordinates":[-1.401564002,50.9123573303],"type":"Point"}
}