{
  "type": "Feature",
  "properties": {
    "addr:full":"5 Pine Court, Loggerheads Market Drayton Shropshire TF9 4QS",
    "addr:housenumber":"5",
    "addr:postcode":"tf9 4qs",
    "addr:street":"Pine Court;Market",
    "iso:country":"GB",
    "sg:address":"5 Pine Court, Loggerheads",
    "sg:city":"Market Drayton",
    "sg:classifiers":[
        {
            "category":"Food & Beverages",
            "subcategory":"Fruits & Vegetables",
            "type":"Retail Goods"
        },
        {
            "category":"Organizations",
            "subcategory":"Membership Organization",
            "type":"Services"
        }
    ],
    "sg:phone":"+44 1630 672705",
    "sg:postcode":"TF9 4QS",
    "sg:province":"Shropshire",
    "sg:tags":[
        "greengrocer"
    ],
    "wof:name":"Pine Court (Loggerheads) Ltd",
    "wof:placetype":"venue"
},
  "geometry": {"coordinates":[-2.389102,52.920174],"type":"Point"}
}