{
  "type": "Feature",
  "properties": {
    "addr:full":"Duke Street Huntly Aberdeenshire AB54 8DL",
    "addr:postcode":"ab54 8dl",
    "addr:street":"Duke Street",
    "iso:country":"GB",
    "sg:address":"Duke Street",
    "sg:city":"Huntly",
    "sg:classifiers":[
        {
            "category":"Bars & Pubs",
            "type":"Food & Drink"
        },
        {
            "category":"Community Center",
            "subcategory":"Social",
            "type":"Public Place"
        }
    ],
    "sg:phone":"+44 1466 792579",
    "sg:postcode":"AB54 8DL",
    "sg:province":"Aberdeenshire",
    "sg:tags":[
        "pubs",
        "house",
        "inn",
        "activity"
    ],
    "wof:name":"THE ROYAL OAK BAR",
    "wof:placetype":"venue"
},
  "geometry": {"coordinates":[-2.7853488922,57.4472732544],"type":"Point"}
}