{
  "type": "Feature",
  "properties": {
    "iso:country":"GB",
    "sg:address":"Hartsdown Park, Hartsdown Road",
    "sg:city":"Margate",
    "sg:classifiers":[
        {
            "category":"Government",
            "subcategory":"Office",
            "type":"Public Place"
        }
    ],
    "sg:phone":"+44 1843 226221",
    "sg:postcode":"CT9 5QX",
    "sg:province":"Kent",
    "sg:tags":[
        "local"
    ],
    "wof:name":"Hartsdown Sports & Leisure Centre",
    "wof:placetype":"venue"
},
  "geometry": {"coordinates":[1.3758679628,51.3786048889],"type":"Point"}
}