{
  "type": "Feature",
  "properties": {
    "addr:full":"Mountfield House, Mountfield Industrial Estate New Romney Kent TN28 8LH",
    "addr:postcode":"tn28 8lh",
    "addr:street":"Industrial Estate",
    "iso:country":"GB",
    "sg:address":"Mountfield House, Mountfield Industrial Estate",
    "sg:city":"New Romney",
    "sg:classifiers":[
        {
            "category":"Shopping",
            "subcategory":"Pharmacy",
            "type":"Retail Goods"
        }
    ],
    "sg:postcode":"TN28 8LH",
    "sg:province":"Kent",
    "sg:tags":[
        "toiletry"
    ],
    "wof:name":"Hotel Complimentary Products Ltd.",
    "wof:placetype":"venue"
},
  "geometry": {"coordinates":[0.94648,50.986767],"type":"Point"}
}