{
  "type": "Feature",
  "properties": {
    "addr:full":"Unit 12 Burghmuir Industrial Estate Stirling Falkirk FK7 7PY",
    "addr:housenumber":"unit 12",
    "addr:postcode":"fk7 7py",
    "addr:street":"Burghmuir Industrial Estate",
    "iso:country":"GB",
    "sg:address":"Unit 12 Burghmuir Industrial Estate",
    "sg:city":"Stirling",
    "sg:classifiers":[
        {
            "category":"Professional",
            "subcategory":"Engineering",
            "type":"Services"
        }
    ],
    "sg:phone":"+44 1786 470699",
    "sg:postcode":"FK7 7PY",
    "sg:province":"Falkirk",
    "sg:tags":[
        "contractor",
        "electrical",
        "engineer"
    ],
    "wof:name":"Bruce Electrical Services Ltd.",
    "wof:placetype":"venue"
},
  "geometry": {"coordinates":[-3.93368,56.11364],"type":"Point"}
}