{
  "type": "Feature",
  "properties": {
    "addr:full":"16 Netheravon Road London Greater London W7 1DN",
    "addr:housenumber":"16",
    "addr:postcode":"w7 1dn",
    "addr:street":"Netheravon Road",
    "iso:country":"GB",
    "sg:address":"16 Netheravon Road",
    "sg:city":"London",
    "sg:classifiers":[
        {
            "category":"Building & Trades",
            "subcategory":"Landscaping Services",
            "type":"Services"
        }
    ],
    "sg:phone":"+44 20 8579 6143",
    "sg:postcode":"W7 1DN",
    "sg:province":"Greater London",
    "sg:tags":[
        "landscape",
        "contractor"
    ],
    "wof:name":"J B Butcher",
    "wof:placetype":"venue"
},
  "geometry": {"coordinates":[-0.333799988,51.5105018616],"type":"Point"}
}