{
  "type": "Feature",
  "properties": {
    "iso:country":"GB",
    "sg:address":"406a High Street",
    "sg:city":"Lincoln",
    "sg:classifiers":[
        {
            "category":"Communications",
            "type":"Services"
        }
    ],
    "sg:phone":"+44 1522 522478",
    "sg:postcode":"LN5 7TE",
    "sg:province":"Lincolnshire",
    "sg:tags":[
        "tv",
        "video",
        "radio"
    ],
    "wof:name":"David Marriott",
    "wof:placetype":"venue"
},
  "geometry": {"coordinates":[-0.544562,53.220333],"type":"Point"}
}