{
  "type": "Feature",
  "properties": {
    "addr:full":"35 East Street Bridport Dorset DT6 3JX",
    "addr:housenumber":"35",
    "addr:postcode":"dt6 3jx",
    "addr:street":"East Street",
    "iso:country":"GB",
    "sg:address":"35 East Street",
    "sg:city":"Bridport",
    "sg:classifiers":[
        {
            "category":"Cinema",
            "subcategory":"Movie Rental",
            "type":"Entertainment"
        }
    ],
    "sg:phone":"+44 1308 421424",
    "sg:postcode":"DT6 3JX",
    "sg:province":"Dorset",
    "sg:tags":[
        "video",
        "library"
    ],
    "wof:name":"Choices Video",
    "wof:placetype":"venue"
},
  "geometry": {"coordinates":[-2.7563939095,50.7334899902],"type":"Point"}
}