{
  "type": "Feature",
  "properties": {
    "iso:country":"GB",
    "sg:address":"94 High St, Shirley",
    "sg:city":"Solihull",
    "sg:classifiers":[
        {
            "category":"Autos & Motor Vehicles",
            "subcategory":"Fuel & Gas Station",
            "type":"Retail Goods"
        }
    ],
    "sg:phone":"+44 121 436 6886",
    "sg:postcode":"B90 1JS",
    "sg:province":"West Midlands",
    "sg:tags":[
        "petrol",
        "filling"
    ],
    "wof:name":"SOLIHULL LODGE PETROL STATION",
    "wof:placetype":"venue"
},
  "geometry": {"coordinates":[-1.859279,52.405972],"type":"Point"}
}