{
  "type": "Feature",
  "properties": {
    "iso:country":"GB",
    "sg:address":"Bridge House, Portsmouth Road, Thames Ditton",
    "sg:city":"Kingston-upon-thames",
    "sg:classifiers":[
        {
            "category":"Professional",
            "subcategory":"Lawyer & Legal Services",
            "type":"Services"
        }
    ],
    "sg:phone":"+44 20 8398 9966",
    "sg:postcode":"KT7 0SZ",
    "sg:province":"Surrey",
    "sg:tags":[
        "solicitor"
    ],
    "wof:name":"Sherwood Wheatley",
    "wof:placetype":"venue"
},
  "geometry": {"coordinates":[-0.325802,51.389183],"type":"Point"}
}