{
  "type": "Feature",
  "properties": {
    "addr:full":"Westview House, 72 Craighead Rd, Milton Of Campsie Glasgow Glasgow East Dunbartonshire G66 8DL",
    "addr:housenumber":"72",
    "addr:postcode":"g66 8dl",
    "addr:street":"Craighead Rd",
    "iso:country":"GB",
    "sg:address":"Westview House, 72 Craighead Rd, Milton Of Campsie Glasgow",
    "sg:city":"Glasgow",
    "sg:classifiers":[
        {
            "category":"Professional",
            "subcategory":"Secretarial Services",
            "type":"Services"
        }
    ],
    "sg:phone":"+44 1360 310352",
    "sg:postcode":"G66 8DL",
    "sg:province":"East Dunbartonshire",
    "wof:name":"All Yours",
    "wof:placetype":"venue"
},
  "geometry": {"coordinates":[-4.1609721184,55.966545105],"type":"Point"}
}