{
  "type": "Feature",
  "properties": {
    "iso:country":"GB",
    "sg:address":"Unit D5 Acorn Business Park, Moss Rd",
    "sg:city":"Grimsby",
    "sg:classifiers":[
        {
            "category":"Government",
            "subcategory":"Post Office",
            "type":"Public Place"
        }
    ],
    "sg:phone":"+44 1472 269888",
    "sg:postcode":"DN32 0LT",
    "sg:province":"Lincolnshire",
    "sg:tags":[
        "messenger",
        "courier"
    ],
    "wof:name":"Wine Express",
    "wof:placetype":"venue"
},
  "geometry": {"coordinates":[-0.08173,53.562859],"type":"Point"}
}