{
  "type": "Feature",
  "properties": {
    "addr:full":"The Barn, Manor Farm Baldock Bedfordshire SG7 5EE",
    "addr:postcode":"sg7 5ee",
    "addr:street":"Manor",
    "iso:country":"GB",
    "sg:address":"The Barn, Manor Farm",
    "sg:city":"Baldock",
    "sg:classifiers":[
        {
            "category":"Food & Beverages",
            "subcategory":"Liquor & Beverages",
            "type":"Retail Goods"
        }
    ],
    "sg:phone":"+44 1462 894094",
    "sg:postcode":"SG7 5EE",
    "sg:province":"Bedfordshire",
    "sg:tags":[
        "beer",
        "spirit",
        "wines"
    ],
    "wof:name":"Beer Connoisseur",
    "wof:placetype":"venue"
},
  "geometry": {"coordinates":[-0.159094,52.040161],"type":"Point"}
}