{
  "type": "Feature",
  "properties": {
    "iso:country":"GB",
    "sg:address":"127a & 127b Old Street",
    "sg:city":"Clevedon",
    "sg:classifiers":[
        {
            "category":"Building & Trades",
            "subcategory":"Cleaning & Sanitation",
            "type":"Services"
        }
    ],
    "sg:phone":"+44 1275 877045",
    "sg:postcode":"BS21 6BW",
    "sg:province":"Somerset",
    "sg:tags":[
        "repair",
        "lift",
        "-"
    ],
    "wof:name":"Abbey Lifts Ltd.",
    "wof:placetype":"venue"
},
  "geometry": {"coordinates":[-2.845227,51.437847],"type":"Point"}
}