{
  "type": "Feature",
  "properties": {
    "iso:country":"GB",
    "sg:address":"50a High St",
    "sg:city":"Wick",
    "sg:classifiers":[
        {
            "category":"Government",
            "subcategory":"Office",
            "type":"Public Place"
        }
    ],
    "sg:phone":"+44 1955 606925",
    "sg:postcode":"KW1 4BS",
    "sg:province":"Highland",
    "sg:tags":[
        "local"
    ],
    "wof:name":"Jet 2000",
    "wof:placetype":"venue"
},
  "geometry": {"coordinates":[-3.09244,58.443104],"type":"Point"}
}