{
  "type": "Feature",
  "properties": {
    "addr:full":"34 Rhode Lane Bridgwater Somerset TA6 6HU",
    "addr:housenumber":"34",
    "addr:postcode":"ta6 6hu",
    "addr:street":"Rhode Lane",
    "iso:country":"GB",
    "sg:address":"34 Rhode Lane",
    "sg:city":"Bridgwater",
    "sg:classifiers":[
        {
            "category":"Health Services",
            "subcategory":"Health Practitioner",
            "type":"Services"
        }
    ],
    "sg:phone":"+44 1278 459648",
    "sg:postcode":"TA6 6HU",
    "sg:province":"Somerset",
    "sg:tags":[
        "hypnotherapists"
    ],
    "wof:name":"S.D Gardiner",
    "wof:placetype":"venue"
},
  "geometry": {"coordinates":[-3.000044,51.11953],"type":"Point"}
}