{
  "type": "Feature",
  "properties": {
    "addr:full":"Ordsall Ho, London Rd Retford Nottinghamshire DN22 7JG",
    "addr:postcode":"dn22 7jg",
    "addr:street":"Ordsall;London Rd",
    "iso:country":"GB",
    "sg:address":"Ordsall Ho, London Rd",
    "sg:city":"Retford",
    "sg:classifiers":[
        {
            "category":"Education",
            "subcategory":"Dance Studio",
            "type":"Public Place"
        }
    ],
    "sg:phone":"+44 1777 706292",
    "sg:postcode":"DN22 7JG",
    "sg:province":"Nottinghamshire",
    "sg:tags":[
        "school",
        "dancing"
    ],
    "wof:name":"Cumberland Windsor School",
    "wof:placetype":"venue"
},
  "geometry": {"coordinates":[-0.945728004,53.3251838684],"type":"Point"}
}