{
  "type": "Feature",
  "properties": {
    "addr:full":"The Stable Block, Pen Tre Soelas Betws-y-coed Conwy LL24 0HY",
    "addr:postcode":"ll24 0hy",
    "iso:country":"GB",
    "sg:address":"The Stable Block, Pen Tre Soelas",
    "sg:city":"Betws-y-coed",
    "sg:classifiers":[
        {
            "category":"Professional",
            "subcategory":"Printing & Photocopies",
            "type":"Services"
        }
    ],
    "sg:phone":"+44 1690 770393",
    "sg:postcode":"LL24 0HY",
    "sg:province":"Conwy",
    "sg:tags":[
        "embroiderer"
    ],
    "wof:name":"Brodwaith Cletwr Embroidery",
    "wof:placetype":"venue"
},
  "geometry": {"coordinates":[-3.8023290634,53.0918197632],"type":"Point"}
}