{
  "type": "Feature",
  "properties": {
    "iso:country":"GB",
    "sg:address":"Grenville Way, Eaton Socon",
    "sg:city":"Huntingdon",
    "sg:classifiers":[
        {
            "category":"Social Services",
            "subcategory":"Retirement Home",
            "type":"Services"
        }
    ],
    "sg:phone":"+44 1480 214020",
    "sg:postcode":"PE19 8HZ",
    "sg:province":"Bedfordshire",
    "sg:tags":[
        "residential",
        "care"
    ],
    "wof:name":"Abbott Healthcare Ltd.",
    "wof:placetype":"venue"
},
  "geometry": {"coordinates":[-0.2893750072,52.2174720764],"type":"Point"}
}