{
  "type": "Feature",
  "properties": {
    "addr:full":"621a Greenland Rd Sheffield South Yorkshire S9 5HH",
    "addr:housenumber":"621a",
    "addr:postcode":"s9 5hh",
    "addr:street":"Greenland Rd",
    "iso:country":"GB",
    "sg:address":"621a Greenland Rd",
    "sg:city":"Sheffield",
    "sg:classifiers":[
        {
            "category":"Health Services",
            "subcategory":"Podiatrist",
            "type":"Services"
        },
        {
            "category":"Health Services",
            "subcategory":"Chiropractor",
            "type":"Services"
        }
    ],
    "sg:phone":"+44 114 243 6081",
    "sg:postcode":"S9 5HH",
    "sg:province":"South Yorkshire",
    "sg:tags":[
        "podiatrists",
        "chiropodist"
    ],
    "wof:name":"Ann Bluff",
    "wof:placetype":"venue"
},
  "geometry": {"coordinates":[-1.4101190567,53.3930397034],"type":"Point"}
}