{
  "type": "Feature",
  "properties": {
    "iso:country":"GB",
    "sg:address":"Dunsburgh, Roborough",
    "sg:city":"Plymouth",
    "sg:classifiers":[
        {
            "category":"Farming",
            "subcategory":"Farm",
            "type":"Manufacturing & Wholesale Goods"
        }
    ],
    "sg:phone":"+44 1752 733432",
    "sg:postcode":"PL6 7BU",
    "sg:province":"Devon",
    "sg:tags":[
        "mixed",
        "crop"
    ],
    "wof:name":"J C Horton",
    "wof:placetype":"venue"
},
  "geometry": {"coordinates":[-4.105214119,50.438785553],"type":"Point"}
}