{
  "type": "Feature",
  "properties": {
    "addr:full":"71 Blackness Road Dundee Dundee City DD1 5PD",
    "addr:housenumber":"71",
    "addr:postcode":"dd1 5pd",
    "addr:street":"Blackness Road",
    "iso:country":"GB",
    "sg:address":"71 Blackness Road",
    "sg:city":"Dundee",
    "sg:classifiers":[
        {
            "category":"Real Estate",
            "subcategory":"Developer",
            "type":"Services"
        }
    ],
    "sg:phone":"+44 1382 224141",
    "sg:postcode":"DD1 5PD",
    "sg:province":"Dundee City",
    "sg:tags":[
        "property"
    ],
    "wof:name":"H & J Property Co.",
    "wof:placetype":"venue"
},
  "geometry": {"coordinates":[-2.9926691055,56.4602508545],"type":"Point"}
}