{
  "type": "Feature",
  "properties": {
    "iso:country":"GB",
    "sg:address":"110 Shenley Road",
    "sg:city":"Borehamwood",
    "sg:classifiers":[
        {
            "category":"Professional",
            "subcategory":"Employment Agencies",
            "type":"Services"
        }
    ],
    "sg:postcode":"WD6 1EB",
    "sg:province":"Hertfordshire",
    "sg:tags":[
        "consultant"
    ],
    "wof:name":"First Appointment Ltd.",
    "wof:placetype":"venue"
},
  "geometry": {"coordinates":[-0.2743110061,51.6562423706],"type":"Point"}
}