{
  "type": "Feature",
  "properties": {
    "iso:country":"GB",
    "sg:address":"Westfield Farm, Balmedie",
    "sg:city":"Aberdeen",
    "sg:classifiers":[
        {
            "category":"Home & Garden",
            "subcategory":"Garden Supply",
            "type":"Retail Goods"
        }
    ],
    "sg:postcode":"AB23 8YL",
    "sg:province":"Aberdeen City",
    "sg:tags":[
        "bulb",
        "grower"
    ],
    "wof:name":"Robertson,Gwladys,",
    "wof:placetype":"venue"
},
  "geometry": {"coordinates":[-2.056249,57.249691],"type":"Point"}
}