{
  "type": "Feature",
  "properties": {
    "addr:full":"Elm Farm, Atherstone Road Swadlincote Derbyshire DE12 7AP",
    "addr:postcode":"de12 7ap",
    "addr:street":"Atherstone Road",
    "iso:country":"GB",
    "sg:address":"Elm Farm, Atherstone Road",
    "sg:city":"Swadlincote",
    "sg:classifiers":[
        {
            "category":"Home & Garden",
            "subcategory":"Furniture",
            "type":"Retail Goods"
        }
    ],
    "sg:postcode":"DE12 7AP",
    "sg:province":"Derbyshire",
    "wof:name":"Furniture Express",
    "wof:placetype":"venue"
},
  "geometry": {"coordinates":[-1.5467139482,52.6883125305],"type":"Point"}
}