{
  "type": "Feature",
  "properties": {
    "iso:country":"GB",
    "sg:address":"Unit 4 Arbirlot Road",
    "sg:city":"Arbroath",
    "sg:classifiers":[
        {
            "category":"Fast Food",
            "type":"Food & Drink"
        }
    ],
    "sg:phone":"+44 1241 870823",
    "sg:postcode":"DD11 2EW",
    "sg:province":"Angus",
    "sg:tags":[
        "away",
        "meal",
        "outlet",
        "take"
    ],
    "wof:name":"Great Wall Chinese Takeaway",
    "wof:placetype":"venue"
},
  "geometry": {"coordinates":[-2.6020829678,56.5593452454],"type":"Point"}
}