{
  "type": "Feature",
  "properties": {
    "iso:country":"GB",
    "sg:address":"7a Commercial Road",
    "sg:city":"Grantham",
    "sg:classifiers":[
        {
            "category":"Personal",
            "subcategory":"Beauty Salon",
            "type":"Services"
        }
    ],
    "sg:phone":"+44 1476 563566",
    "sg:postcode":"NG31 6DB",
    "sg:province":"Lincolnshire",
    "sg:tags":[
        "unisex",
        "hairdresser"
    ],
    "wof:name":"Haynes on Hair",
    "wof:placetype":"venue"
},
  "geometry": {"coordinates":[-0.640881,52.908024],"type":"Point"}
}