{
  "type": "Feature",
  "properties": {
    "addr:full":"107 Newgate Lane Fareham Hampshire PO14 1BA",
    "addr:housenumber":"107",
    "addr:postcode":"po14 1ba",
    "addr:street":"Newgate Lane",
    "iso:country":"GB",
    "sg:address":"107 Newgate Lane",
    "sg:city":"Fareham",
    "sg:classifiers":[
        {
            "category":"Military Area",
            "subcategory":"Air Force Base",
            "type":"Public Place"
        }
    ],
    "sg:postcode":"PO14 1BA",
    "sg:province":"Hampshire",
    "sg:tags":[
        "taxi",
        "hire",
        "private"
    ],
    "wof:name":"Ace Taxis",
    "wof:placetype":"venue"
},
  "geometry": {"coordinates":[-1.192296,50.826134],"type":"Point"}
}