{
  "type": "Feature",
  "properties": {
    "addr:full":"15 Glamis Road Kirriemuir Angus DD8 5BN",
    "addr:housenumber":"15",
    "addr:postcode":"dd8 5bn",
    "addr:street":"Glamis Road",
    "iso:country":"GB",
    "sg:address":"15 Glamis Road",
    "sg:city":"Kirriemuir",
    "sg:classifiers":[
        {
            "category":"Farming",
            "subcategory":"Nursery",
            "type":"Manufacturing & Wholesale Goods"
        }
    ],
    "sg:phone":"+44 1575 575993",
    "sg:postcode":"DD8 5BN",
    "sg:province":"Angus",
    "sg:tags":[
        "creche"
    ],
    "wof:name":"Tick Tock's Nursery",
    "wof:placetype":"venue"
},
  "geometry": {"coordinates":[-3.003743,56.669514],"type":"Point"}
}