{
  "type": "Feature",
  "properties": {
    "addr:full":"25 Summer Lane, Wombwell Barnsley South Yorkshire S73 8HD",
    "addr:housenumber":"25",
    "addr:postcode":"s73 8hd",
    "addr:street":"Summer Lane;Yorkshire",
    "iso:country":"GB",
    "sg:address":"25 Summer Lane, Wombwell",
    "sg:city":"Barnsley",
    "sg:classifiers":[
        {
            "category":"Fast Food",
            "type":"Food & Drink"
        },
        {
            "category":"Food & Beverages",
            "subcategory":"Meat & Fish",
            "type":"Retail Goods"
        }
    ],
    "sg:phone":"+44 1226 750652",
    "sg:postcode":"S73 8HD",
    "sg:province":"South Yorkshire",
    "sg:tags":[
        "shop",
        "chip"
    ],
    "wof:name":"Summer Lane Fish Bar Ltd",
    "wof:placetype":"venue"
},
  "geometry": {"coordinates":[-1.400018,53.52158],"type":"Point"}
}