{
  "type": "Feature",
  "properties": {
    "iso:country":"GB",
    "sg:address":"99 High St",
    "sg:city":"Winchester",
    "sg:classifiers":[
        {
            "category":"Shopping",
            "subcategory":"Gifts & Souvenirs",
            "type":"Retail Goods"
        }
    ],
    "sg:phone":"+44 1962 861917",
    "sg:postcode":"SO23 9AH",
    "sg:province":"Hampshire",
    "sg:tags":[
        "shop"
    ],
    "wof:name":"&  Albert Ltd",
    "wof:placetype":"venue"
},
  "geometry": {"coordinates":[-1.316396,51.063034],"type":"Point"}
}