{
  "type": "Feature",
  "properties": {
    "addr:full":"11 Nicholson Way Cambridge Cambridgeshire CB4 2RP",
    "addr:housenumber":"11",
    "addr:postcode":"cb4 2rp",
    "addr:street":"Nicholson Way",
    "iso:country":"GB",
    "sg:address":"11 Nicholson Way",
    "sg:city":"Cambridge",
    "sg:classifiers":[
        {
            "category":"Social Services",
            "subcategory":"Adult Care",
            "type":"Services"
        }
    ],
    "sg:phone":"+44 1223 507383",
    "sg:postcode":"CB4 2RP",
    "sg:province":"Cambridgeshire",
    "sg:tags":[
        "domestic",
        "cleaning"
    ],
    "wof:name":"Enterprise Cleaning Services",
    "wof:placetype":"venue"
},
  "geometry": {"coordinates":[0.124087,52.22826],"type":"Point"}
}