{
  "type": "Feature",
  "properties": {
    "iso:country":"GB",
    "sg:address":"750 Hertford Road, Freezywater",
    "sg:city":"Enfield",
    "sg:classifiers":[
        {
            "category":"Home & Garden",
            "subcategory":"Furniture",
            "type":"Retail Goods"
        }
    ],
    "sg:phone":"+44 1992 764659",
    "sg:postcode":"EN3 6PR",
    "sg:province":"Greater London",
    "wof:name":"Knaggs Furniture Fittings",
    "wof:placetype":"venue"
},
  "geometry": {"coordinates":[-0.0371580012,51.6750068665],"type":"Point"}
}