{
  "type": "Feature",
  "properties": {
    "addr:full":"Rearsby Road, Thrussington Leicester Leicestershire LE7 4UD",
    "addr:postcode":"le7 4ud",
    "addr:street":"Rearsby Road",
    "iso:country":"GB",
    "sg:address":"Rearsby Road, Thrussington",
    "sg:city":"Leicester",
    "sg:classifiers":[
        {
            "category":"Manufacturing",
            "subcategory":"Wood Products",
            "type":"Manufacturing & Wholesale Goods"
        }
    ],
    "sg:phone":"+44 1664 424380",
    "sg:postcode":"LE7 4UD",
    "sg:province":"Leicestershire",
    "sg:tags":[
        "maker",
        "cabinet"
    ],
    "wof:name":"Wreake Valley Craftsman Ltd.",
    "wof:placetype":"venue"
},
  "geometry": {"coordinates":[-1.038009,52.722694],"type":"Point"}
}