{
  "type": "Feature",
  "properties": {
    "addr:full":"353 Baring Road, Grove Park London Greater London SE12 0EE",
    "addr:housenumber":"353",
    "addr:postcode":"se12 0ee",
    "addr:street":"Baring Road",
    "iso:country":"GB",
    "sg:address":"353 Baring Road, Grove Park",
    "sg:city":"London",
    "sg:classifiers":[
        {
            "category":"Farming",
            "subcategory":"Nursery",
            "type":"Manufacturing & Wholesale Goods"
        }
    ],
    "sg:phone":"+44 20 8857 8258",
    "sg:postcode":"SE12 0EE",
    "sg:province":"Greater London",
    "sg:tags":[
        "creche"
    ],
    "wof:name":"Grove Park Pre-School",
    "wof:placetype":"venue"
},
  "geometry": {"coordinates":[0.021506,51.42865],"type":"Point"}
}