{
  "type": "Feature",
  "properties": {
    "iso:country":"GB",
    "sg:address":"Masonic Centre, Northwick Circle",
    "sg:city":"Harrow",
    "sg:classifiers":[
        {
            "category":"Professional",
            "type":"Services"
        }
    ],
    "sg:phone":"+44 20 8907 1763",
    "sg:postcode":"HA3 0EL",
    "sg:province":"Greater London",
    "sg:tags":[
        "caterer"
    ],
    "wof:name":"Brook,T J,",
    "wof:placetype":"venue"
},
  "geometry": {"coordinates":[-0.31032,51.581921],"type":"Point"}
}