{
  "type": "Feature",
  "properties": {
    "iso:country":"GB",
    "sg:address":"5 Clipstone Street",
    "sg:city":"London",
    "sg:classifiers":[
        {
            "category":"Bars & Pubs",
            "subcategory":"Wine Bar",
            "type":"Food & Drink"
        }
    ],
    "sg:phone":"+44 20 7436 0035",
    "sg:postcode":"W1W 6BB",
    "sg:province":"Greater London",
    "wof:name":"Ahmed Eldawlty",
    "wof:placetype":"venue"
},
  "geometry": {"coordinates":[-0.141993,51.520824],"type":"Point"}
}