{
  "type": "Feature",
  "properties": {
    "addr:full":"152-152a Lady Margaret Rd Southall Greater London UB1 2RW",
    "addr:housenumber":"152-152a",
    "addr:postcode":"ub1 2rw",
    "addr:street":"Lady Margaret Rd",
    "iso:country":"GB",
    "sg:address":"152-152a Lady Margaret Rd",
    "sg:city":"Southall",
    "sg:classifiers":[
        {
            "category":"Health Services",
            "subcategory":"Dentist",
            "type":"Services"
        }
    ],
    "sg:phone":"+44 20 8574 4666",
    "sg:postcode":"UB1 2RW",
    "sg:province":"Greater London",
    "wof:name":"Dr N Tavakoli",
    "wof:placetype":"venue"
},
  "geometry": {"coordinates":[-0.3751600087,51.5185089111],"type":"Point"}
}