{
  "type": "Feature",
  "properties": {
    "iso:country":"GB",
    "sg:address":"204 Stoke Rd",
    "sg:city":"Slough",
    "sg:classifiers":[
        {
            "category":"Social Services",
            "subcategory":"Adult Care",
            "type":"Services"
        },
        {
            "category":"Social Services",
            "subcategory":"Retirement Home",
            "type":"Services"
        }
    ],
    "sg:phone":"+44 1753 536842",
    "sg:postcode":"SL2 5AY",
    "sg:province":"Berkshire",
    "sg:tags":[
        "provider"
    ],
    "wof:name":"Oxford House",
    "wof:placetype":"venue"
},
  "geometry": {"coordinates":[-0.589558,51.52021],"type":"Point"}
}