{
  "type": "Feature",
  "properties": {
    "addr:full":"22 Burrows Vale, Brixworth Northampton Northamptonshire NN6 9US",
    "addr:housenumber":"22",
    "addr:postcode":"nn6 9us",
    "addr:street":"Burrows Vale",
    "iso:country":"GB",
    "sg:address":"22 Burrows Vale, Brixworth",
    "sg:city":"Northampton",
    "sg:classifiers":[
        {
            "category":"Professional",
            "subcategory":"Engineering",
            "type":"Services"
        }
    ],
    "sg:phone":"+44 1604 889313",
    "sg:postcode":"NN6 9US",
    "sg:province":"Northamptonshire",
    "wof:name":"Renmar Ltd.",
    "wof:placetype":"venue"
},
  "geometry": {"coordinates":[-0.896448,52.330006],"type":"Point"}
}