{
  "type": "Feature",
  "properties": {
    "addr:full":"Findon Road Worthing West Sussex BN14 0AB",
    "addr:postcode":"bn14 0ab",
    "addr:street":"Findon Road",
    "iso:country":"GB",
    "sg:address":"Findon Road",
    "sg:city":"Worthing",
    "sg:classifiers":[
        {
            "category":"Autos & Motor Vehicles",
            "subcategory":"Fuel & Gas Station",
            "type":"Retail Goods"
        }
    ],
    "sg:phone":"+44 1903 262265",
    "sg:postcode":"BN14 0AB",
    "sg:province":"West Sussex",
    "sg:tags":[
        "petrol",
        "filling"
    ],
    "wof:name":"Q8 Findon Road",
    "wof:placetype":"venue"
},
  "geometry": {"coordinates":[-0.402034,50.856525],"type":"Point"}
}