{
  "type": "Feature",
  "properties": {
    "iso:country":"GB",
    "sg:address":"Castle Place Surgery, 9 Park Hill",
    "sg:city":"Tiverton",
    "sg:classifiers":[
        {
            "category":"Health Services",
            "subcategory":"Doctor",
            "type":"Services"
        }
    ],
    "sg:phone":"+44 1884 252333",
    "sg:postcode":"EX16 6RR",
    "sg:province":"Devon",
    "sg:tags":[
        "practitioners"
    ],
    "wof:name":"Monahan, P B",
    "wof:placetype":"venue"
},
  "geometry": {"coordinates":[-3.493149,50.905025],"type":"Point"}
}