{
  "type": "Feature",
  "properties": {
    "addr:full":"Ewyn-y-don, Manes Alaw Holyhead Isle of Anglesey LL65 3BA",
    "addr:postcode":"ll65 3ba",
    "addr:street":"Holyhead",
    "iso:country":"GB",
    "sg:address":"Ewyn-y-don, Manes Alaw",
    "sg:city":"Holyhead",
    "sg:classifiers":[
        {
            "category":"Building & Trades",
            "subcategory":"Plumbing",
            "type":"Services"
        }
    ],
    "sg:phone":"+44 1407 740831",
    "sg:postcode":"LL65 3BA",
    "sg:province":"Isle of Anglesey",
    "sg:tags":[
        "plumber",
        "heating"
    ],
    "wof:name":"David Shorney",
    "wof:placetype":"venue"
},
  "geometry": {"coordinates":[-4.56931,53.290298],"type":"Point"}
}