{
  "type": "Feature",
  "properties": {
    "iso:country":"GB",
    "sg:address":"Ladye Place, Boat House, Mill Lane",
    "sg:city":"Maidenhead",
    "sg:classifiers":[
        {
            "category":"Professional",
            "subcategory":"Engineering",
            "type":"Services"
        }
    ],
    "sg:phone":"+44 1628 822200",
    "sg:postcode":"SL6 5ND",
    "sg:province":"Berkshire",
    "sg:tags":[
        "civil",
        "engineer"
    ],
    "wof:name":"Cook (River) Piling",
    "wof:placetype":"venue"
},
  "geometry": {"coordinates":[-0.8066099882,51.5493888855],"type":"Point"}
}