{
  "type": "Feature",
  "properties": {
    "iso:country":"GB",
    "sg:address":"12 East Grinstead Road",
    "sg:city":"Lingfield",
    "sg:classifiers":[
        {
            "category":"Retail",
            "subcategory":"Laundry & Dry Cleaning",
            "type":"Services"
        }
    ],
    "sg:phone":"+44 1342 834153",
    "sg:postcode":"RH7 6EP",
    "sg:province":"Surrey",
    "sg:tags":[
        "alteration"
    ],
    "wof:name":"Anthony Moore",
    "wof:placetype":"venue"
},
  "geometry": {"coordinates":[-0.018487,51.173882],"type":"Point"}
}