{
  "type": "Feature",
  "properties": {
    "iso:country":"GB",
    "sg:address":"Unit 4 St Johns Centre",
    "sg:city":"Perth",
    "sg:classifiers":[
        {
            "category":"Shopping",
            "subcategory":"Clothing, Apparel, & Fashions",
            "type":"Retail Goods"
        }
    ],
    "sg:phone":"+44 1738 639642",
    "sg:postcode":"PH1 5UX",
    "sg:province":"Perth and Kinross",
    "sg:tags":[
        "shop"
    ],
    "wof:name":"Internacionale Ltd.",
    "wof:placetype":"venue"
},
  "geometry": {"coordinates":[-3.4277439117,56.3960952759],"type":"Point"}
}