{
  "type": "Feature",
  "properties": {
    "iso:country":"GB",
    "sg:address":"Wester Greenskares, Gardenstown",
    "sg:city":"Banff",
    "sg:classifiers":[
        {
            "category":"Freight",
            "type":"Transportation"
        }
    ],
    "sg:phone":"+44 1261 851592",
    "sg:postcode":"AB45 3ER",
    "sg:province":"Aberdeenshire",
    "sg:tags":[
        "haulage",
        "road"
    ],
    "wof:name":"R G & I Chapman",
    "wof:placetype":"venue"
},
  "geometry": {"coordinates":[-2.338337,57.671852],"type":"Point"}
}