{
  "type": "Feature",
  "properties": {
    "addr:full":"4 Hillcrest Lane, Husbands Bosworth Lutterworth Leicestershire LE17 6LB",
    "addr:housenumber":"4",
    "addr:postcode":"le17 6lb",
    "addr:street":"Hillcrest Lane",
    "iso:country":"GB",
    "sg:address":"4 Hillcrest Lane, Husbands Bosworth",
    "sg:city":"Lutterworth",
    "sg:classifiers":[
        {
            "category":"Professional",
            "type":"Services"
        }
    ],
    "sg:phone":"+44 1858 880332",
    "sg:postcode":"LE17 6LB",
    "sg:province":"Leicestershire",
    "sg:tags":[
        "exhibition"
    ],
    "wof:name":"C H Towing Services",
    "wof:placetype":"venue"
},
  "geometry": {"coordinates":[-1.057553,52.454048],"type":"Point"}
}