{
  "type": "Feature",
  "properties": {
    "addr:full":"2nd Floor, 243 High Street Guildford Surrey GU1 3BJ",
    "addr:housenumber":"2nd floor 243",
    "addr:postcode":"gu1 3bj",
    "addr:street":"High Street",
    "iso:country":"GB",
    "sg:address":"2nd Floor, 243 High Street",
    "sg:city":"Guildford",
    "sg:classifiers":[
        {
            "category":"Building & Trades",
            "subcategory":"Equipment Rental",
            "type":"Services"
        }
    ],
    "sg:postcode":"GU1 3BJ",
    "sg:province":"Surrey",
    "sg:tags":[
        "hotel",
        "restaurant"
    ],
    "wof:name":"Eurojace Limited",
    "wof:placetype":"venue"
},
  "geometry": {"coordinates":[-0.5671349764,51.2376060486],"type":"Point"}
}