{
  "type": "Feature",
  "properties": {
    "addr:full":"26 Penfield Road, Drighlington Bradford West Yorkshire BD11 1ES",
    "addr:housenumber":"26",
    "addr:postcode":"bd11 1es",
    "addr:street":"Penfield Road",
    "iso:country":"GB",
    "sg:address":"26 Penfield Road, Drighlington",
    "sg:city":"Bradford",
    "sg:classifiers":[
        {
            "category":"Building & Trades",
            "subcategory":"Construction",
            "type":"Services"
        }
    ],
    "sg:postcode":"BD11 1ES",
    "sg:province":"West Yorkshire",
    "sg:tags":[
        "roofing"
    ],
    "wof:name":"L S R Roofing Services",
    "wof:placetype":"venue"
},
  "geometry": {"coordinates":[-1.656828,53.75312],"type":"Point"}
}