{
  "type": "Feature",
  "properties": {
    "addr:full":"Social Services, Ladywood Area Office, 23 All Saints Rd Birmingham West Midlands B18 5QB",
    "addr:housenumber":"23",
    "addr:postcode":"b18 5qb",
    "addr:street":"All Saints Rd",
    "iso:country":"GB",
    "sg:address":"Social Services, Ladywood Area Office, 23 All Saints Rd",
    "sg:city":"Birmingham",
    "sg:classifiers":[
        {
            "category":"Government",
            "subcategory":"Office",
            "type":"Public Place"
        }
    ],
    "sg:phone":"+44 121 303 4362",
    "sg:postcode":"B18 5QB",
    "sg:province":"West Midlands",
    "sg:tags":[
        "local"
    ],
    "wof:name":"Birmingham City Council",
    "wof:placetype":"venue"
},
  "geometry": {"coordinates":[-1.9086040258,52.4785957336],"type":"Point"}
}