{
  "type": "Feature",
  "properties": {
    "addr:full":"14 Stramongate Kendal Cumbria LA9 4BN",
    "addr:housenumber":"14",
    "addr:postcode":"la9 4bn",
    "addr:street":"Stramongate Kendal",
    "iso:country":"GB",
    "sg:address":"14 Stramongate",
    "sg:city":"Kendal",
    "sg:classifiers":[
        {
            "category":"Personal",
            "subcategory":"Beauty Salon",
            "type":"Services"
        },
        {
            "category":"Personal",
            "subcategory":"Barber",
            "type":"Services"
        }
    ],
    "sg:phone":"+44 1539 723026",
    "sg:postcode":"LA9 4BN",
    "sg:province":"Cumbria",
    "sg:tags":[
        "unisex",
        "hairdresser"
    ],
    "wof:name":"A B C Lloyd",
    "wof:placetype":"venue"
},
  "geometry": {"coordinates":[-2.7448790073,54.3284072876],"type":"Point"}
}