{
  "type": "Feature",
  "properties": {
    "addr:full":"Enquiries, 91 Station Rd Cheadle Cheshire SK8 7BG",
    "addr:housenumber":"91",
    "addr:postcode":"sk8 7bg",
    "addr:street":"Enquiries;Station Rd Cheadle",
    "iso:country":"GB",
    "sg:address":"Enquiries, 91 Station Rd",
    "sg:city":"Cheadle",
    "sg:classifiers":[
        {
            "category":"Place Of Worship",
            "type":"Public Place"
        }
    ],
    "sg:phone":"+44 161 439 6088",
    "sg:postcode":"SK8 7BG",
    "sg:province":"Cheshire",
    "wof:name":"Cheadle Hulme Quaker Meeting",
    "wof:placetype":"venue"
},
  "geometry": {"coordinates":[-2.2122719288,53.3952484131],"type":"Point"}
}