{
  "type": "Feature",
  "properties": {
    "iso:country":"GB",
    "sg:address":"Broad Flood House, Bentley",
    "sg:city":"Farnham",
    "sg:classifiers":[
        {
            "category":"Building & Trades",
            "subcategory":"Construction",
            "type":"Services"
        }
    ],
    "sg:phone":"+44 1420 23293",
    "sg:postcode":"GU10 5HU",
    "sg:province":"Hampshire",
    "sg:tags":[
        "builder"
    ],
    "wof:name":"D J Trimming Ltd.",
    "wof:placetype":"venue"
},
  "geometry": {"coordinates":[-0.8753089905,51.1901931763],"type":"Point"}
}