{
  "type": "Feature",
  "properties": {
    "iso:country":"GB",
    "sg:address":"23 Horse Street, Chipping Sodbury",
    "sg:city":"Bristol",
    "sg:classifiers":[
        {
            "category":"Utilities",
            "type":"Services"
        }
    ],
    "sg:phone":"+44 1454 880002",
    "sg:postcode":"BS37 6DA",
    "sg:province":"Gloucestershire",
    "sg:tags":[
        "internet"
    ],
    "wof:name":"Travel Uk",
    "wof:placetype":"venue"
},
  "geometry": {"coordinates":[-2.391308,51.537594],"type":"Point"}
}