{
  "type": "Feature",
  "properties": {
    "iso:country":"GB",
    "sg:address":"Corn Exchange Street",
    "sg:city":"Cambridge",
    "sg:classifiers":[
        {
            "category":"Bars & Pubs",
            "type":"Food & Drink"
        }
    ],
    "sg:phone":"+44 1223 360021",
    "sg:postcode":"CB2 3QF",
    "sg:province":"Cambridgeshire",
    "sg:tags":[
        "pubs",
        "inn"
    ],
    "wof:name":"Punch Leisure Ltd.",
    "wof:placetype":"venue"
},
  "geometry": {"coordinates":[0.121408,52.20332],"type":"Point"}
}