{
  "type": "Feature",
  "properties": {
    "addr:full":"Brunswick Chambers, 4 Paton Street Manchester Greater Manchester M1 2BA",
    "addr:housenumber":"4",
    "addr:postcode":"m1 2ba",
    "addr:street":"Paton Street",
    "iso:country":"GB",
    "sg:address":"Brunswick Chambers, 4 Paton Street",
    "sg:city":"Manchester",
    "sg:classifiers":[
        {
            "category":"Shopping",
            "subcategory":"Gifts & Souvenirs",
            "type":"Retail Goods"
        }
    ],
    "sg:postcode":"M1 2BA",
    "sg:province":"Greater Manchester",
    "sg:tags":[
        "giftware"
    ],
    "wof:name":"Sheridan Studios",
    "wof:placetype":"venue"
},
  "geometry": {"coordinates":[-2.2333199978,53.4801597595],"type":"Point"}
}