{
  "type": "Feature",
  "properties": {
    "iso:country":"GB",
    "sg:address":"23-25 Bridge Street, Bailey Gate Industrial Estate, Sturminster Marshall",
    "sg:city":"Wimborne",
    "sg:classifiers":[
        {
            "category":"Building & Trades",
            "subcategory":"Plumbing",
            "type":"Services"
        }
    ],
    "sg:phone":"+44 1258 858700",
    "sg:postcode":"BH21 4DB",
    "sg:province":"Dorset",
    "sg:tags":[
        "heating"
    ],
    "wof:name":"Mainflow Plumbing & Heating Ltd.",
    "wof:placetype":"venue"
},
  "geometry": {"coordinates":[-2.0700058937,50.7937965393],"type":"Point"}
}