{
  "type": "Feature",
  "properties": {
    "iso:country":"GB",
    "sg:address":"Langdale, Rectory Hill, Wivenhoe",
    "sg:city":"Colchester",
    "sg:classifiers":[
        {
            "category":"Building & Trades",
            "subcategory":"Landscaping Services",
            "type":"Services"
        }
    ],
    "sg:phone":"+44 1206 823898",
    "sg:postcode":"CO7 9LB",
    "sg:province":"Essex",
    "sg:tags":[
        "landscape",
        "contractor"
    ],
    "wof:name":"Wivenhoe Landscape Contracts",
    "wof:placetype":"venue"
},
  "geometry": {"coordinates":[0.959469974,51.8568382263],"type":"Point"}
}