{
  "type": "Feature",
  "properties": {
    "addr:full":"1 Blackshaw Lane, Royton Oldham Lancashire OL2 6NT",
    "addr:housenumber":"1",
    "addr:postcode":"ol2 6nt",
    "addr:street":"Blackshaw Lane",
    "iso:country":"GB",
    "sg:address":"1 Blackshaw Lane, Royton",
    "sg:city":"Oldham",
    "sg:classifiers":[
        {
            "category":"Social Services",
            "subcategory":"Child Care",
            "type":"Services"
        },
        {
            "category":"Government",
            "subcategory":"Office",
            "type":"Public Place"
        }
    ],
    "sg:phone":"+44 161 620 1210",
    "sg:postcode":"OL2 6NT",
    "sg:province":"Lancashire",
    "sg:tags":[
        "home",
        "local",
        "children's"
    ],
    "wof:name":"Blackshaw Lane Childrens Home",
    "wof:placetype":"venue"
},
  "geometry": {"coordinates":[-2.109063,53.567455],"type":"Point"}
}