{
  "type": "Feature",
  "properties": {
    "addr:full":"Po Box 36, Retford Road Worksop Nottinghamshire S81 7YU",
    "addr:housenumber":"po box 36",
    "addr:postcode":"s81 7yu",
    "addr:street":"Retford Road",
    "iso:country":"GB",
    "sg:address":"Po Box 36, Retford Road",
    "sg:city":"Worksop",
    "sg:classifiers":[
        {
            "category":"Home & Garden",
            "subcategory":"Building Materials",
            "type":"Retail Goods"
        }
    ],
    "sg:phone":"+44 1909 537800",
    "sg:postcode":"S81 7YU",
    "sg:province":"Nottinghamshire",
    "sg:tags":[
        "ready",
        "mixed",
        "concrete"
    ],
    "wof:name":"Redland",
    "wof:placetype":"venue"
},
  "geometry": {"coordinates":[-1.1269099712,53.3247718811],"type":"Point"}
}