{
  "type": "Feature",
  "properties": {
    "addr:full":"134 Manor Rd New Milton Hampshire BH25 5ED",
    "addr:housenumber":"134",
    "addr:postcode":"bh25 5ed",
    "addr:street":"Manor Rd",
    "iso:country":"GB",
    "sg:address":"134 Manor Rd",
    "sg:city":"New Milton",
    "sg:classifiers":[
        {
            "category":"Shopping",
            "subcategory":"Department Store",
            "type":"Retail Goods"
        }
    ],
    "sg:phone":"+44 1425 611151",
    "sg:postcode":"BH25 5ED",
    "sg:province":"Hampshire",
    "wof:name":"Manor Road Stores & Post Office",
    "wof:placetype":"venue"
},
  "geometry": {"coordinates":[-1.644991,50.760887],"type":"Point"}
}