{
  "type": "Feature",
  "properties": {
    "iso:country":"GB",
    "sg:address":"12 Coalbrook Road, Pontyberem",
    "sg:city":"Llanelli",
    "sg:classifiers":[
        {
            "category":"Government",
            "subcategory":"Post Office",
            "type":"Public Place"
        }
    ],
    "sg:phone":"+44 1269 870307",
    "sg:postcode":"SA15 5HU",
    "sg:province":"Carmarthenshire",
    "wof:name":"Pontyberem Post Office",
    "wof:placetype":"venue"
},
  "geometry": {"coordinates":[-4.169301033,51.7781829834],"type":"Point"}
}