{
  "type": "Feature",
  "properties": {
    "iso:country":"GB",
    "sg:address":"16 Firs Rd",
    "sg:city":"Nottingham",
    "sg:classifiers":[
        {
            "category":"Education",
            "subcategory":"Music School",
            "type":"Public Place"
        }
    ],
    "sg:phone":"+44 115 923 3849",
    "sg:postcode":"NG12 4BX",
    "sg:province":"Nottinghamshire",
    "sg:tags":[
        "teacher"
    ],
    "wof:name":"H Caswell",
    "wof:placetype":"venue"
},
  "geometry": {"coordinates":[-1.116368,52.915604],"type":"Point"}
}