{
  "type": "Feature",
  "properties": {
    "iso:country":"GB",
    "sg:address":"108 Devonshire Street",
    "sg:city":"Sheffield",
    "sg:classifiers":[
        {
            "category":"Shopping",
            "subcategory":"Clothing, Apparel, & Fashions",
            "type":"Retail Goods"
        }
    ],
    "sg:phone":"+44 114 279 6145",
    "sg:postcode":"S3 7SF",
    "sg:province":"South Yorkshire",
    "sg:tags":[
        "menswear",
        "ladieswear"
    ],
    "wof:name":"Versa Woman Ltd.",
    "wof:placetype":"venue"
},
  "geometry": {"coordinates":[-1.478006,53.379559],"type":"Point"}
}