{
  "type": "Feature",
  "properties": {
    "iso:country":"GB",
    "sg:address":"Windsor Ho, 37 Windsor St",
    "sg:city":"Chertsey",
    "sg:classifiers":[
        {
            "category":"Coffee & Tea",
            "type":"Food & Drink"
        }
    ],
    "sg:phone":"+44 1932 575600",
    "sg:postcode":"KT16 8AT",
    "sg:province":"Surrey",
    "wof:name":"Paulig U K Ltd",
    "wof:placetype":"venue"
},
  "geometry": {"coordinates":[-0.5082539916,51.3881988525],"type":"Point"}
}