{
  "type": "Feature",
  "properties": {
    "iso:country":"GB",
    "sg:address":"5 Dartford Avenue, Winton, Eccles",
    "sg:city":"Manchester",
    "sg:classifiers":[
        {
            "category":"Building & Trades",
            "subcategory":"Construction",
            "type":"Services"
        }
    ],
    "sg:phone":"+44 161 788 0630",
    "sg:postcode":"M30 8NF",
    "sg:province":"Greater Manchester",
    "sg:tags":[
        "joiner",
        "carpenter"
    ],
    "wof:name":"N P Joinery",
    "wof:placetype":"venue"
},
  "geometry": {"coordinates":[-2.365079,53.486626],"type":"Point"}
}