{
  "type": "Feature",
  "properties": {
    "addr:full":"Hobbans Farm Ongar Essex CM5 0LY",
    "addr:postcode":"cm5 0ly",
    "iso:country":"GB",
    "sg:address":"Hobbans Farm",
    "sg:city":"Ongar",
    "sg:classifiers":[
        {
            "category":"Food & Beverages",
            "subcategory":"Liquor & Beverages",
            "type":"Retail Goods"
        }
    ],
    "sg:phone":"+44 1277 890245",
    "sg:postcode":"CM5 0LY",
    "sg:province":"Essex",
    "sg:tags":[
        "beer",
        "spirit",
        "wines"
    ],
    "wof:name":"Tremaine & Webbs",
    "wof:placetype":"venue"
},
  "geometry": {"coordinates":[0.24517,51.706131],"type":"Point"}
}