{
  "type": "Feature",
  "properties": {
    "addr:full":"2 Coalpit Lane, Brereton Rugeley Staffordshire WS15 1EN",
    "addr:housenumber":"2",
    "addr:postcode":"ws15 1en",
    "addr:street":"Coalpit Lane",
    "iso:country":"GB",
    "sg:address":"2 Coalpit Lane, Brereton",
    "sg:city":"Rugeley",
    "sg:classifiers":[
        {
            "category":"Building & Trades",
            "subcategory":"Construction",
            "type":"Services"
        }
    ],
    "sg:phone":"+44 1889 584057",
    "sg:postcode":"WS15 1EN",
    "sg:province":"Staffordshire",
    "sg:tags":[
        "heating",
        "contractor"
    ],
    "wof:name":"Springfield Heating & Mechanical Services Ltd.",
    "wof:placetype":"venue"
},
  "geometry": {"coordinates":[-1.9264210463,52.7422485352],"type":"Point"}
}