{
  "type": "Feature",
  "properties": {
    "addr:full":"4 Park Gate Glasgow Glasgow City G3 6DL",
    "addr:housenumber":"4",
    "addr:postcode":"g3 6dl",
    "addr:street":"Park Gate",
    "iso:country":"GB",
    "sg:address":"4 Park Gate",
    "sg:city":"Glasgow",
    "sg:classifiers":[
        {
            "category":"Real Estate",
            "subcategory":"Architect",
            "type":"Services"
        }
    ],
    "sg:phone":"+44 141 353 2241",
    "sg:postcode":"G3 6DL",
    "sg:province":"Glasgow City",
    "wof:name":"Urquhart Partnership",
    "wof:placetype":"venue"
},
  "geometry": {"coordinates":[-4.2801151276,55.8697052002],"type":"Point"}
}