{
  "type": "Feature",
  "properties": {
    "addr:full":"155-157 Railway Terrace Rugby Warwickshire CV21 3HQ",
    "addr:housenumber":"155-157",
    "addr:postcode":"cv21 3hq",
    "addr:street":"Railway Terrace",
    "iso:country":"GB",
    "sg:address":"155-157 Railway Terrace",
    "sg:city":"Rugby",
    "sg:classifiers":[
        {
            "category":"Restaurant",
            "type":"Food & Drink"
        }
    ],
    "sg:phone":"+44 1788 542262",
    "sg:postcode":"CV21 3HQ",
    "sg:province":"Warwickshire",
    "sg:tags":[
        "indian",
        "-"
    ],
    "wof:name":"Dilruba Tandoori Restaurant",
    "wof:placetype":"venue"
},
  "geometry": {"coordinates":[-1.2557369471,52.3761787415],"type":"Point"}
}