{
  "type": "Feature",
  "properties": {
    "addr:full":"5 Harbour St Ardrossan North Ayrshire KA22 8BS",
    "addr:housenumber":"5",
    "addr:postcode":"ka22 8bs",
    "addr:street":"Harbour St",
    "iso:country":"GB",
    "sg:address":"5 Harbour St",
    "sg:city":"Ardrossan",
    "sg:classifiers":[
        {
            "category":"Professional",
            "subcategory":"Engineering",
            "type":"Services"
        }
    ],
    "sg:phone":"+44 1294 602602",
    "sg:postcode":"KA22 8BS",
    "sg:province":"North Ayrshire",
    "sg:tags":[
        "contractor",
        "electrical",
        "engineer"
    ],
    "wof:name":"A C Electrical",
    "wof:placetype":"venue"
},
  "geometry": {"coordinates":[-4.8165988922,55.6393013],"type":"Point"}
}