{
  "type": "Feature",
  "properties": {
    "addr:full":"9 Lullington Garth Borehamwood Hertfordshire WD6 2HD",
    "addr:housenumber":"9",
    "addr:postcode":"wd6 2hd",
    "addr:street":"Lullington Garth",
    "iso:country":"GB",
    "sg:address":"9 Lullington Garth",
    "sg:city":"Borehamwood",
    "sg:classifiers":[
        {
            "category":"Health Services",
            "subcategory":"Health Practitioner",
            "type":"Services"
        }
    ],
    "sg:phone":"+44 20 8207 3578",
    "sg:postcode":"WD6 2HD",
    "sg:province":"Hertfordshire",
    "sg:tags":[
        "homoeopathic"
    ],
    "wof:name":"Yasmin Steenvoorden",
    "wof:placetype":"venue"
},
  "geometry": {"coordinates":[-0.2669590116,51.6479988098],"type":"Point"}
}