{
  "type": "Feature",
  "properties": {
    "addr:full":"104 High Street Dunfermline Fife KY12 7DP",
    "addr:housenumber":"104",
    "addr:postcode":"ky12 7dp",
    "addr:street":"High Street",
    "iso:country":"GB",
    "sg:address":"104 High Street",
    "sg:city":"Dunfermline",
    "sg:classifiers":[
        {
            "category":"Fast Food",
            "type":"Food & Drink"
        }
    ],
    "sg:phone":"+44 1383 621074",
    "sg:postcode":"KY12 7DP",
    "sg:province":"Fife",
    "sg:tags":[
        "away",
        "take"
    ],
    "wof:name":"McDonalds Restaurant",
    "wof:placetype":"venue"
},
  "geometry": {"coordinates":[-3.459851,56.071709],"type":"Point"}
}