{
  "type": "Feature",
  "properties": {
    "addr:full":"Unit 6, Dragonville Industrial Durham Durham DH1 2XJ",
    "addr:housenumber":"unit 6",
    "addr:postcode":"dh1 2xj",
    "addr:street":"Dragonville Industrial",
    "iso:country":"GB",
    "sg:address":"Unit 6, Dragonville Industrial",
    "sg:city":"Durham",
    "sg:classifiers":[
        {
            "category":"Home & Garden",
            "subcategory":"Home Furnishings",
            "type":"Retail Goods"
        }
    ],
    "sg:postcode":"DH1 2XJ",
    "sg:province":"Durham",
    "sg:tags":[
        "furnishers",
        "planner",
        "kitchen"
    ],
    "wof:name":"T Q K  Ltd.",
    "wof:placetype":"venue"
},
  "geometry": {"coordinates":[-1.5342340469,54.7749404907],"type":"Point"}
}