{
  "type": "Feature",
  "properties": {
    "addr:full":"14/15 Cornhill Bury St Edmunds Suffolk IP33 1DY",
    "addr:housenumber":"14 / 15",
    "addr:postcode":"ip33 1dy",
    "addr:street":"Cornhill",
    "iso:country":"GB",
    "sg:address":"14/15 Cornhill",
    "sg:city":"Bury St Edmunds",
    "sg:classifiers":[
        {
            "category":"Shopping",
            "subcategory":"Clothing, Apparel, & Fashions",
            "type":"Retail Goods"
        }
    ],
    "sg:phone":"+44 1284 754219",
    "sg:postcode":"IP33 1DY",
    "sg:province":"Suffolk",
    "sg:tags":[
        "menswear"
    ],
    "sg:website":"http://www.burton.co.uk",
    "wof:name":"Burton Menswear Ltd",
    "wof:placetype":"venue"
},
  "geometry": {"coordinates":[0.711905,52.24472],"type":"Point"}
}