{
  "type": "Feature",
  "properties": {
    "addr:full":"16 Glovers Field, Shipham Winscombe Somerset BS25 1SU",
    "addr:housenumber":"16",
    "addr:postcode":"bs25 1su",
    "addr:street":"Glovers Field",
    "iso:country":"GB",
    "sg:address":"16 Glovers Field, Shipham",
    "sg:city":"Winscombe",
    "sg:classifiers":[
        {
            "category":"Professional",
            "subcategory":"Accounting & Tax Preparation",
            "type":"Services"
        }
    ],
    "sg:phone":"+44 1934 843681",
    "sg:postcode":"BS25 1SU",
    "sg:province":"Somerset",
    "sg:tags":[
        "accountant"
    ],
    "wof:name":"Glen Ruhe Accountancy Services",
    "wof:placetype":"venue"
},
  "geometry": {"coordinates":[-2.7944219112,51.3133163452],"type":"Point"}
}