{
  "type": "Feature",
  "properties": {
    "iso:country":"GB",
    "sg:address":"P O Box 26",
    "sg:city":"Pickering",
    "sg:classifiers":[
        {
            "category":"Wholesale",
            "subcategory":"Vending Machines",
            "type":"Manufacturing & Wholesale Goods"
        }
    ],
    "sg:phone":"+44 1751 432444",
    "sg:postcode":"YO18 8YR",
    "sg:province":"North Yorkshire",
    "sg:tags":[
        "generator"
    ],
    "wof:name":"Endcape Ltd.",
    "wof:placetype":"venue"
},
  "geometry": {"coordinates":[-0.817669,54.295132],"type":"Point"}
}