{
  "type": "Feature",
  "properties": {
    "addr:full":"10 Horse Fair Banbury Oxfordshire OX16 0AH",
    "addr:housenumber":"10",
    "addr:postcode":"ox16 0ah",
    "addr:street":"Horse Fair",
    "iso:country":"GB",
    "sg:address":"10 Horse Fair",
    "sg:city":"Banbury",
    "sg:classifiers":[
        {
            "category":"Shopping",
            "subcategory":"Pharmacy",
            "type":"Retail Goods"
        }
    ],
    "sg:phone":"+44 1295 262039",
    "sg:postcode":"OX16 0AH",
    "sg:province":"Oxfordshire",
    "sg:tags":[
        "pharmacist",
        "chemist"
    ],
    "wof:name":"Cox & Robinson (Chemist)",
    "wof:placetype":"venue"
},
  "geometry": {"coordinates":[-1.340234,52.061169],"type":"Point"}
}