{
  "type": "Feature",
  "properties": {
    "addr:full":"21/25 Viceroy Parade, High Road London Greater London N2 8AQ",
    "addr:housenumber":"21 / 25",
    "addr:postcode":"n2 8aq",
    "addr:street":"Viceroy Parade High Road",
    "iso:country":"GB",
    "sg:address":"21/25 Viceroy Parade, High Road",
    "sg:city":"London",
    "sg:classifiers":[
        {
            "category":"Community Center",
            "subcategory":"Social",
            "type":"Public Place"
        }
    ],
    "sg:phone":"+44 20 8883 0277",
    "sg:postcode":"N2 8AQ",
    "sg:province":"Greater London",
    "sg:tags":[
        "frozen",
        "food",
        "freezer",
        "centre"
    ],
    "wof:name":"Iceland Foods Plc",
    "wof:placetype":"venue"
},
  "geometry": {"coordinates":[-0.16441,51.59013],"type":"Point"}
}