{
  "type": "Feature",
  "properties": {
    "iso:country":"GB",
    "sg:address":"195 Bexhill Road",
    "sg:city":"St Leonards-on-sea",
    "sg:classifiers":[
        {
            "category":"Retail",
            "subcategory":"Auto Repair",
            "type":"Services"
        }
    ],
    "sg:postcode":"TN38 8BG",
    "sg:province":"East Sussex",
    "sg:tags":[
        "modification",
        "garage"
    ],
    "wof:name":"Bexhill Gearboxes",
    "wof:placetype":"venue"
},
  "geometry": {"coordinates":[0.5285739899,50.8515739441],"type":"Point"}
}