{
  "type": "Feature",
  "properties": {
    "addr:full":"Market Pl Didcot Oxfordshire OX11 7LE",
    "addr:postcode":"ox11 7le",
    "addr:street":"Market Pl",
    "iso:country":"GB",
    "sg:address":"Market Pl",
    "sg:city":"Didcot",
    "sg:classifiers":[
        {
            "category":"Food & Beverages",
            "subcategory":"Supermarket",
            "type":"Retail Goods"
        }
    ],
    "sg:phone":"+44 1235 818711",
    "sg:postcode":"OX11 7LE",
    "sg:province":"Oxfordshire",
    "wof:name":"Oxford Swindon & Gloucester Co-Operative",
    "wof:placetype":"venue"
},
  "geometry": {"coordinates":[-1.241869,51.606709],"type":"Point"}
}