{
  "type": "Feature",
  "properties": {
    "iso:country":"GB",
    "sg:address":"Darland House, 44 Winnington Hill",
    "sg:city":"Northwich",
    "sg:classifiers":[
        {
            "category":"Professional",
            "subcategory":"Computer Services",
            "type":"Services"
        }
    ],
    "sg:postcode":"CW8 1AU",
    "sg:province":"Cheshire",
    "sg:tags":[
        "system",
        "software"
    ],
    "wof:name":"Finecourse Limited",
    "wof:placetype":"venue"
},
  "geometry": {"coordinates":[-2.518715,53.262341],"type":"Point"}
}