{
  "type": "Feature",
  "properties": {
    "iso:country":"GB",
    "sg:address":"The Midway",
    "sg:city":"Newcastle",
    "sg:classifiers":[
        {
            "category":"Bars & Pubs",
            "subcategory":"Nightclub",
            "type":"Food & Drink"
        }
    ],
    "sg:phone":"+44 1782 717711",
    "sg:postcode":"ST5 1QG",
    "sg:province":"Staffordshire",
    "sg:tags":[
        "club",
        "night"
    ],
    "wof:name":"Time & Space Nightclub",
    "wof:placetype":"venue"
},
  "geometry": {"coordinates":[-2.2277588844,53.0100402832],"type":"Point"}
}