{
  "type": "Feature",
  "properties": {
    "addr:full":"47 Llangyfelach St Swansea Neath Port Talbot SA1 2BQ",
    "addr:housenumber":"47",
    "addr:postcode":"sa1 2bq",
    "addr:street":"Llangyfelach St",
    "iso:country":"GB",
    "sg:address":"47 Llangyfelach St",
    "sg:city":"Swansea",
    "sg:classifiers":[
        {
            "category":"Building & Trades",
            "subcategory":"Construction",
            "type":"Services"
        }
    ],
    "sg:postcode":"SA1 2BQ",
    "sg:province":"Neath Port Talbot",
    "sg:tags":[
        "roofing"
    ],
    "wof:name":"R & L Johnston",
    "wof:placetype":"venue"
},
  "geometry": {"coordinates":[-3.942887,51.631939],"type":"Point"}
}