{
  "type": "Feature",
  "properties": {
    "addr:full":"Unit 14-15, Gatehouse Centre, Albert Street Huddersfield West Yorkshire HD1 3QD",
    "addr:housenumber":"unit 14-15 gatehouse centre",
    "addr:postcode":"hd1 3qd",
    "addr:street":"Albert Street",
    "iso:country":"GB",
    "sg:address":"Unit 14-15, Gatehouse Centre, Albert Street",
    "sg:city":"Huddersfield",
    "sg:classifiers":[
        {
            "category":"Shopping",
            "subcategory":"Clothing, Apparel, & Fashions",
            "type":"Retail Goods"
        }
    ],
    "sg:phone":"+44 1484 455105",
    "sg:postcode":"HD1 3QD",
    "sg:province":"West Yorkshire",
    "sg:tags":[
        "clothing",
        "fabric"
    ],
    "wof:name":"A J Benson Ltd.",
    "wof:placetype":"venue"
},
  "geometry": {"coordinates":[-1.7826839685,53.6469535828],"type":"Point"}
}