{
  "type": "Feature",
  "properties": {
    "addr:full":"Clifton House Newmarket Cambridgeshire CB8 8QE",
    "addr:postcode":"cb8 8qe",
    "addr:street":"Newmarket",
    "iso:country":"GB",
    "sg:address":"Clifton House",
    "sg:city":"Newmarket",
    "sg:classifiers":[
        {
            "category":"Professional",
            "subcategory":"Accounting & Tax Preparation",
            "type":"Services"
        }
    ],
    "sg:phone":"+44 1638 661313",
    "sg:postcode":"CB8 8QE",
    "sg:province":"Cambridgeshire",
    "sg:tags":[
        "accountant"
    ],
    "wof:name":"Stephenson Davies",
    "wof:placetype":"venue"
},
  "geometry": {"coordinates":[0.5159,52.211559],"type":"Point"}
}