{
  "type": "Feature",
  "properties": {
    "iso:country":"GB",
    "sg:address":"Christchurch Rd",
    "sg:city":"Ringwood",
    "sg:classifiers":[
        {
            "category":"Professional",
            "subcategory":"Engineering",
            "type":"Services"
        }
    ],
    "sg:phone":"+44 1425 462400",
    "sg:postcode":"BH24 3AJ",
    "sg:province":"Dorset",
    "sg:tags":[
        "precision",
        "engineer"
    ],
    "wof:name":"A E Goetze Special Products Ltd",
    "wof:placetype":"venue"
},
  "geometry": {"coordinates":[-1.787422,50.841763],"type":"Point"}
}