{
  "type": "Feature",
  "properties": {
    "iso:country":"GB",
    "sg:address":"Aberdon Resource Centre, Coningham Rd",
    "sg:city":"Aberdeen",
    "sg:classifiers":[
        {
            "category":"Organizations",
            "subcategory":"Non-profit Organization",
            "type":"Services"
        }
    ],
    "sg:phone":"+44 1224 276505",
    "sg:postcode":"AB24 2TW",
    "sg:province":"Aberdeen City",
    "sg:tags":[
        "organisation",
        "voluntary",
        "charity"
    ],
    "wof:name":"Alzheimer Scotland - Action on Dementia",
    "wof:placetype":"venue"
},
  "geometry": {"coordinates":[-2.10873,57.170238],"type":"Point"}
}