{
  "type": "Feature",
  "properties": {
    "addr:full":"19 Compstall Road, Romiley Stockport Cheshire SK6 4BT",
    "addr:housenumber":"19",
    "addr:postcode":"sk6 4bt",
    "addr:street":"Compstall Road",
    "iso:country":"GB",
    "sg:address":"19 Compstall Road, Romiley",
    "sg:city":"Stockport",
    "sg:classifiers":[
        {
            "category":"Shopping",
            "subcategory":"Party Supplies",
            "type":"Retail Goods"
        }
    ],
    "sg:postcode":"SK6 4BT",
    "sg:province":"Cheshire",
    "sg:tags":[
        "novelty"
    ],
    "wof:name":"Jayes Party Shop",
    "wof:placetype":"venue"
},
  "geometry": {"coordinates":[-2.08752,53.413967],"type":"Point"}
}