{
  "type": "Feature",
  "properties": {
    "addr:full":"13a Brownhill Cres Pontefract West Yorkshire WF9 5LD",
    "addr:housenumber":"13a",
    "addr:postcode":"wf9 5ld",
    "addr:street":"Brownhill Cres Pontefract West",
    "iso:country":"GB",
    "sg:address":"13a Brownhill Cres",
    "sg:city":"Pontefract",
    "sg:classifiers":[
        {
            "category":"Food & Beverages",
            "subcategory":"Supermarket",
            "type":"Retail Goods"
        }
    ],
    "sg:postcode":"WF9 5LD",
    "sg:province":"West Yorkshire",
    "wof:name":"N S Gill",
    "wof:placetype":"venue"
},
  "geometry": {"coordinates":[-1.3731050491,53.6252174377],"type":"Point"}
}