{
  "type": "Feature",
  "properties": {
    "iso:country":"GB",
    "sg:address":"Raglan Road",
    "sg:city":"Hengoed",
    "sg:classifiers":[
        {
            "category":"Manufacturing",
            "subcategory":"Metals",
            "type":"Manufacturing & Wholesale Goods"
        },
        {
            "category":"Professional",
            "subcategory":"Engineering",
            "type":"Services"
        }
    ],
    "sg:phone":"+44 1443 813229",
    "sg:postcode":"CF82 7LY",
    "sg:province":"Caerphilly",
    "sg:tags":[
        "steel",
        "fabricator",
        "engineer"
    ],
    "wof:name":"Gittens & Hayter Ltd.",
    "wof:placetype":"venue"
},
  "geometry": {"coordinates":[-3.231799,51.648319],"type":"Point"}
}