{
  "type": "Feature",
  "properties": {
    "iso:country":"GB",
    "sg:address":"Merivale Farm, Selden La, Patching",
    "sg:city":"Worthing",
    "sg:classifiers":[
        {
            "category":"Professional",
            "subcategory":"Employment Agencies",
            "type":"Services"
        }
    ],
    "sg:postcode":"BN13 3UL",
    "sg:province":"West Sussex",
    "sg:tags":[
        "agricultural",
        "advice"
    ],
    "wof:name":"Groundcare Irrigation Ltd",
    "wof:placetype":"venue"
},
  "geometry": {"coordinates":[-0.453659,50.847015],"type":"Point"}
}