{
  "type": "Feature",
  "properties": {
    "addr:full":"Quay Street, Mousehole Penzance Cornwall TR19 6PL",
    "addr:postcode":"tr19 6pl",
    "addr:street":"Quay Street",
    "iso:country":"GB",
    "sg:address":"Quay Street, Mousehole",
    "sg:city":"Penzance",
    "sg:classifiers":[
        {
            "category":"Shopping",
            "subcategory":"Department Store",
            "type":"Retail Goods"
        },
        {
            "category":"Transit Center",
            "subcategory":"Freight",
            "type":"Transportation"
        }
    ],
    "sg:phone":"+44 1736 731893",
    "sg:postcode":"TR19 6PL",
    "sg:province":"Cornwall",
    "sg:tags":[
        "shop",
        "craft",
        "centre"
    ],
    "wof:name":"T & E Winters",
    "wof:placetype":"venue"
},
  "geometry": {"coordinates":[-5.538329,50.08392],"type":"Point"}
}