{
  "type": "Feature",
  "properties": {
    "addr:full":"Room C1, 15 School Of Education, University Of Manchester Manchester Greater Manchester M13 9PL",
    "addr:housenumber":"15",
    "addr:postcode":"m13 9pl",
    "addr:street":"C1",
    "iso:country":"GB",
    "sg:address":"Room C1, 15 School Of Education, University Of Manchester",
    "sg:city":"Manchester",
    "sg:classifiers":[
        {
            "category":"Education",
            "subcategory":"Special Training",
            "type":"Public Place"
        }
    ],
    "sg:phone":"+44 161 275 3482",
    "sg:postcode":"M13 9PL",
    "sg:province":"Greater Manchester",
    "sg:tags":[
        "school",
        "language"
    ],
    "wof:name":"University Of Manchester E F L Section",
    "wof:placetype":"venue"
},
  "geometry": {"coordinates":[-2.2488100529,53.4796218872],"type":"Point"}
}