{
  "type": "Feature",
  "properties": {
    "addr:full":"2 St Georges Road, Wimbledon London Greater London SW19 4UZ",
    "addr:housenumber":"2",
    "addr:postcode":"sw19 4uz",
    "addr:street":"St Georges Road",
    "iso:country":"GB",
    "sg:address":"2 St Georges Road, Wimbledon",
    "sg:city":"London",
    "sg:classifiers":[
        {
            "category":"Community Center",
            "type":"Public Place"
        }
    ],
    "sg:postcode":"SW19 4UZ",
    "sg:province":"Greater London",
    "sg:tags":[
        "centre",
        "entertainment"
    ],
    "wof:name":"Vardon Ltd.",
    "wof:placetype":"venue"
},
  "geometry": {"coordinates":[-0.2084970027,51.4209747314],"type":"Point"}
}