{
  "type": "Feature",
  "properties": {
    "iso:country":"GB",
    "sg:address":"144 Ardath Road",
    "sg:city":"Birmingham",
    "sg:classifiers":[
        {
            "category":"Building & Trades",
            "subcategory":"Construction",
            "type":"Services"
        }
    ],
    "sg:phone":"+44 121 628 3292",
    "sg:postcode":"B38 9PE",
    "sg:province":"West Midlands",
    "sg:tags":[
        "decorator",
        "painter"
    ],
    "wof:name":"Smiths Decorating & Maintenance Contractors",
    "wof:placetype":"venue"
},
  "geometry": {"coordinates":[-1.920725,52.404243],"type":"Point"}
}