{
  "type": "Feature",
  "properties": {
    "addr:full":"2338 Dumbarton Road Glasgow Glasgow City G14 0JX",
    "addr:housenumber":"2338",
    "addr:postcode":"g14 0jx",
    "addr:street":"Dumbarton Road",
    "iso:country":"GB",
    "sg:address":"2338 Dumbarton Road",
    "sg:city":"Glasgow",
    "sg:classifiers":[
        {
            "category":"Food & Beverages",
            "subcategory":"Meat & Fish",
            "type":"Retail Goods"
        }
    ],
    "sg:phone":"+44 141 959 0015",
    "sg:postcode":"G14 0JX",
    "sg:province":"Glasgow City",
    "sg:tags":[
        "chip"
    ],
    "wof:name":"Ferry Fryer",
    "wof:placetype":"venue"
},
  "geometry": {"coordinates":[-4.3773908615,55.8878936768],"type":"Point"}
}