{
  "type": "Feature",
  "properties": {
    "addr:full":"34 Cardiff Road Newport Newport NP20 2ED",
    "addr:housenumber":"34",
    "addr:postcode":"np20 2ed",
    "addr:street":"Cardiff Road",
    "iso:country":"GB",
    "sg:address":"34 Cardiff Road",
    "sg:city":"Newport",
    "sg:classifiers":[
        {
            "category":"Fast Food",
            "type":"Food & Drink"
        }
    ],
    "sg:phone":"+44 1633 243198",
    "sg:postcode":"NP20 2ED",
    "sg:province":"Newport",
    "sg:tags":[
        "away",
        "meal",
        "outlet",
        "take"
    ],
    "wof:name":"Indian Ocean Tandoori Take Away",
    "wof:placetype":"venue"
},
  "geometry": {"coordinates":[-2.993546,51.581608],"type":"Point"}
}