{
  "type": "Feature",
  "properties": {
    "iso:country":"GB",
    "sg:address":"122 Main Street, Horsley Woodhouse",
    "sg:city":"Ilkeston",
    "sg:classifiers":[
        {
            "category":"Shopping",
            "subcategory":"Florist",
            "type":"Retail Goods"
        }
    ],
    "sg:postcode":"DE7 6AW",
    "sg:province":"Derbyshire",
    "wof:name":"The Flower Shop",
    "wof:placetype":"venue"
},
  "geometry": {"coordinates":[-1.394865,52.993343],"type":"Point"}
}