{
  "type": "Feature",
  "properties": {
    "addr:full":"Oakbank Road Perth Perth and Kinross PH1 1HB",
    "addr:postcode":"ph1 1hb",
    "addr:street":"Oakbank Road",
    "iso:country":"GB",
    "sg:address":"Oakbank Road",
    "sg:city":"Perth",
    "sg:classifiers":[
        {
            "category":"Education",
            "subcategory":"School",
            "type":"Public Place"
        }
    ],
    "sg:postcode":"PH1 1HB",
    "sg:province":"Perth and Kinross",
    "sg:tags":[
        "local",
        "authority"
    ],
    "wof:name":"Perth High School",
    "wof:placetype":"venue"
},
  "geometry": {"coordinates":[-3.480644,56.395],"type":"Point"}
}