{
  "type": "Feature",
  "properties": {
    "addr:full":"28 York St Bedford Bedfordshire MK40 3RJ",
    "addr:housenumber":"28",
    "addr:postcode":"mk40 3rj",
    "addr:street":"York St",
    "iso:country":"GB",
    "sg:address":"28 York St",
    "sg:city":"Bedford",
    "sg:classifiers":[
        {
            "category":"Shopping",
            "subcategory":"Pharmacy",
            "type":"Retail Goods"
        }
    ],
    "sg:phone":"+44 1234 346744",
    "sg:postcode":"MK40 3RJ",
    "sg:province":"Bedfordshire",
    "sg:tags":[
        "medicine",
        "therapy"
    ],
    "wof:name":"Body Balance Holistic Health",
    "wof:placetype":"venue"
},
  "geometry": {"coordinates":[-0.4518620074,52.1364021301],"type":"Point"}
}