{
  "type": "Feature",
  "properties": {
    "addr:full":"45 Hollybush Lane Welwyn Garden City Hertfordshire AL7 4JH",
    "addr:housenumber":"45",
    "addr:postcode":"al7 4jh",
    "addr:street":"Hollybush Lane",
    "iso:country":"GB",
    "sg:address":"45 Hollybush Lane",
    "sg:city":"Welwyn Garden City",
    "sg:classifiers":[
        {
            "category":"Building & Trades",
            "subcategory":"Construction",
            "type":"Services"
        }
    ],
    "sg:phone":"+44 1707 334145",
    "sg:postcode":"AL7 4JH",
    "sg:province":"Hertfordshire",
    "sg:tags":[
        "roofing"
    ],
    "wof:name":"Boniface Property Maintenance",
    "wof:placetype":"venue"
},
  "geometry": {"coordinates":[-0.1973219961,51.7887573242],"type":"Point"}
}