{
  "type": "Feature",
  "properties": {
    "addr:full":"161 Orchard Croft Harlow Essex CM20 3BH",
    "addr:housenumber":"161",
    "addr:postcode":"cm20 3bh",
    "addr:street":"Orchard Croft",
    "iso:country":"GB",
    "sg:address":"161 Orchard Croft",
    "sg:city":"Harlow",
    "sg:classifiers":[
        {
            "category":"Retail",
            "subcategory":"Animal Services",
            "type":"Services"
        }
    ],
    "sg:phone":"+44 1279 411216",
    "sg:postcode":"CM20 3BH",
    "sg:province":"Essex",
    "sg:tags":[
        "pet"
    ],
    "wof:name":"Happypets",
    "wof:placetype":"venue"
},
  "geometry": {"coordinates":[0.11707,51.775211],"type":"Point"}
}