{
  "type": "Feature",
  "properties": {
    "addr:full":"284 Union Road, Oswaldtwistle Accrington Lancashire BB5 3JD",
    "addr:housenumber":"284",
    "addr:postcode":"bb5 3jd",
    "addr:street":"Union Road;Accrington",
    "iso:country":"GB",
    "sg:address":"284 Union Road, Oswaldtwistle",
    "sg:city":"Accrington",
    "sg:classifiers":[
        {
            "category":"Shopping",
            "subcategory":"Crafts & Fabrics",
            "type":"Retail Goods"
        }
    ],
    "sg:phone":"+44 1254 875525",
    "sg:postcode":"BB5 3JD",
    "sg:province":"Lancashire",
    "sg:tags":[
        "shop",
        "needlecraft",
        "wool",
        "retailer"
    ],
    "wof:name":"Sheila's Wool Shop",
    "wof:placetype":"venue"
},
  "geometry": {"coordinates":[-2.398306,53.742577],"type":"Point"}
}