{
  "type": "Feature",
  "properties": {
    "addr:full":"Bury Close, Higham Business Park, Higham Ferrers Rushden Bedfordshire NN10 8HQ",
    "addr:postcode":"nn10 8hq",
    "addr:street":"Bury Close",
    "iso:country":"GB",
    "sg:address":"Bury Close, Higham Business Park, Higham Ferrers",
    "sg:city":"Rushden",
    "sg:classifiers":[
        {
            "category":"Manufacturing",
            "subcategory":"Rubber & Plastics",
            "type":"Manufacturing & Wholesale Goods"
        }
    ],
    "sg:phone":"+44 1933 353875",
    "sg:postcode":"NN10 8HQ",
    "sg:province":"Bedfordshire",
    "sg:tags":[
        "supplier",
        "stockist"
    ],
    "wof:name":"Chamberlain Plastics Ltd.",
    "wof:placetype":"venue"
},
  "geometry": {"coordinates":[-0.5934690237,52.309589386],"type":"Point"}
}