{
  "type": "Feature",
  "properties": {
    "iso:country":"GB",
    "sg:address":"Annesdale",
    "sg:city":"Ely",
    "sg:classifiers":[
        {
            "category":"Bars & Pubs",
            "type":"Food & Drink"
        }
    ],
    "sg:phone":"+44 1353 662713",
    "sg:postcode":"CB7 4BN",
    "sg:province":"Cambridgeshire",
    "sg:tags":[
        "pubs",
        "inn"
    ],
    "wof:name":"The Cutter Inn",
    "wof:placetype":"venue"
},
  "geometry": {"coordinates":[0.2668350041,52.3937263489],"type":"Point"}
}