{
  "type": "Feature",
  "properties": {
    "iso:country":"GB",
    "sg:address":"Earlsway",
    "sg:city":"Gateshead",
    "sg:classifiers":[
        {
            "category":"Wholesale",
            "subcategory":"Non-durable Goods",
            "type":"Manufacturing & Wholesale Goods"
        }
    ],
    "sg:phone":"+44 191 482 5542",
    "sg:postcode":"NE11 0RQ",
    "sg:province":"Tyne and Wear",
    "sg:tags":[
        "carry",
        "cash"
    ],
    "wof:name":"Tyne Tees Cash & Carry Ltd.",
    "wof:placetype":"venue"
},
  "geometry": {"coordinates":[-1.6227289438,54.9453735352],"type":"Point"}
}