{
  "type": "Feature",
  "properties": {
    "addr:full":"598 Green Lanes London Greater London N13 5RY",
    "addr:housenumber":"598",
    "addr:postcode":"n13 5ry",
    "addr:street":"Green Lanes",
    "iso:country":"GB",
    "sg:address":"598 Green Lanes",
    "sg:city":"London",
    "sg:classifiers":[
        {
            "category":"Travel",
            "subcategory":"Travel Agent",
            "type":"Entertainment"
        }
    ],
    "sg:phone":"+44 20 8886 8880",
    "sg:postcode":"N13 5RY",
    "sg:province":"Greater London",
    "wof:name":"American Travel Ltd.",
    "wof:placetype":"venue"
},
  "geometry": {"coordinates":[-0.098719,51.626598],"type":"Point"}
}