{
  "type": "Feature",
  "properties": {
    "iso:country":"GB",
    "sg:address":"Oak Lodge Farm, Broughton Road, Stoney Stanton",
    "sg:city":"Leicester",
    "sg:classifiers":[
        {
            "category":"Food & Beverages",
            "subcategory":"Farmers Market",
            "type":"Retail Goods"
        }
    ],
    "sg:postcode":"LE9 6JA",
    "sg:province":"Leicestershire",
    "sg:tags":[
        "farm",
        "shop",
        "pyo"
    ],
    "wof:name":"E A Lovatt",
    "wof:placetype":"venue"
},
  "geometry": {"coordinates":[-1.2797,52.548222],"type":"Point"}
}