{
  "type": "Feature",
  "properties": {
    "iso:country":"GB",
    "sg:address":"Pease Hill Road",
    "sg:city":"Ripley",
    "sg:classifiers":[
        {
            "category":"Bars & Pubs",
            "type":"Food & Drink"
        }
    ],
    "sg:postcode":"DE5 3JH",
    "sg:province":"Derbyshire",
    "sg:tags":[
        "pubs",
        "inn"
    ],
    "wof:name":"Railway Inn",
    "wof:placetype":"venue"
},
  "geometry": {"coordinates":[-1.404107,53.0438],"type":"Point"}
}