{
  "type": "Feature",
  "properties": {
    "addr:full":"4 Bridge Street Stafford Staffordshire ST16 2HJ",
    "addr:housenumber":"4",
    "addr:postcode":"st16 2hj",
    "addr:street":"Bridge Street",
    "iso:country":"GB",
    "sg:address":"4 Bridge Street",
    "sg:city":"Stafford",
    "sg:classifiers":[
        {
            "category":"Shopping",
            "subcategory":"Florist",
            "type":"Retail Goods"
        }
    ],
    "sg:postcode":"ST16 2HJ",
    "sg:province":"Staffordshire",
    "wof:name":"Heathers of Stafford",
    "wof:placetype":"venue"
},
  "geometry": {"coordinates":[-2.1153430939,52.8041801453],"type":"Point"}
}