{
  "type": "Feature",
  "properties": {
    "iso:country":"GB",
    "sg:address":"105 Alexandra Road",
    "sg:city":"Newport",
    "sg:classifiers":[
        {
            "category":"Structure",
            "subcategory":"Warehouse",
            "type":"Public Place"
        },
        {
            "category":"Manufacturing",
            "subcategory":"Retail Goods",
            "type":"Manufacturing & Wholesale Goods"
        }
    ],
    "sg:phone":"+44 1633 264929",
    "sg:postcode":"NP20 2JG",
    "sg:province":"Newport",
    "sg:tags":[
        "chandler"
    ],
    "wof:name":"G W Elliott & Son",
    "wof:placetype":"venue"
},
  "geometry": {"coordinates":[-2.9892520905,51.5711212158],"type":"Point"}
}