{
  "type": "Feature",
  "properties": {
    "iso:country":"GB",
    "sg:address":"St. Barnabas Ho, Duncan Rd",
    "sg:city":"Gillingham",
    "sg:classifiers":[
        {
            "category":"Health Services",
            "subcategory":"Doctor",
            "type":"Services"
        }
    ],
    "sg:phone":"+44 1634 850067",
    "sg:postcode":"ME7 4LD",
    "sg:province":"Kent",
    "sg:tags":[
        "practitioners"
    ],
    "wof:name":"Ahamed, S O S",
    "wof:placetype":"venue"
},
  "geometry": {"coordinates":[0.553869,51.378281],"type":"Point"}
}