{
  "type": "Feature",
  "properties": {
    "addr:full":"4 Bishops Park Road London Greater London SW16 5TT",
    "addr:housenumber":"4",
    "addr:postcode":"sw16 5tt",
    "addr:street":"Bishops Park Road",
    "iso:country":"GB",
    "sg:address":"4 Bishops Park Road",
    "sg:city":"London",
    "sg:classifiers":[
        {
            "category":"Education",
            "subcategory":"School",
            "type":"Public Place"
        }
    ],
    "sg:phone":"+44 20 8679 5215",
    "sg:postcode":"SW16 5TT",
    "sg:province":"Greater London",
    "sg:tags":[
        "private",
        "tuition"
    ],
    "wof:name":"William Rose",
    "wof:placetype":"venue"
},
  "geometry": {"coordinates":[-0.124724,51.410503],"type":"Point"}
}