{
  "type": "Feature",
  "properties": {
    "addr:full":"20 Clifford St Tamworth Staffordshire B77 2BU",
    "addr:housenumber":"20",
    "addr:postcode":"b77 2bu",
    "addr:street":"Clifford St",
    "iso:country":"GB",
    "sg:address":"20 Clifford St",
    "sg:city":"Tamworth",
    "sg:classifiers":[
        {
            "category":"Food & Beverages",
            "subcategory":"Meat & Fish",
            "type":"Retail Goods"
        }
    ],
    "sg:phone":"+44 1827 56536",
    "sg:postcode":"B77 2BU",
    "sg:province":"Staffordshire",
    "sg:tags":[
        "merchant"
    ],
    "wof:name":"Sharpfish",
    "wof:placetype":"venue"
},
  "geometry": {"coordinates":[-1.6693240404,52.6288909912],"type":"Point"}
}