{
  "type": "Feature",
  "properties": {
    "iso:country":"GB",
    "sg:address":"171 Terminus Road",
    "sg:city":"Eastbourne",
    "sg:classifiers":[
        {
            "category":"Home & Garden",
            "subcategory":"Kitchen Supply",
            "type":"Retail Goods"
        }
    ],
    "sg:postcode":"BN21 3NX",
    "sg:province":"East Sussex",
    "sg:tags":[
        "ware"
    ],
    "wof:name":"Supercook Wholesale Supply",
    "wof:placetype":"venue"
},
  "geometry": {"coordinates":[0.288651,50.767921],"type":"Point"}
}