{
  "type": "Feature",
  "properties": {
    "iso:country":"GB",
    "sg:address":"77 Perth Road",
    "sg:city":"Dundee",
    "sg:classifiers":[
        {
            "category":"Home & Garden",
            "subcategory":"Home Furnishings",
            "type":"Retail Goods"
        }
    ],
    "sg:phone":"+44 1382 201100",
    "sg:postcode":"DD1 4HY",
    "sg:province":"Dundee City",
    "sg:tags":[
        "mantelpiece",
        "fireplace"
    ],
    "wof:name":"Ron Watson Fireplaces",
    "wof:placetype":"venue"
},
  "geometry": {"coordinates":[-2.9878599644,56.4562072754],"type":"Point"}
}