{
  "type": "Feature",
  "properties": {
    "iso:country":"GB",
    "sg:address":"12 Waterloo Street",
    "sg:city":"Oldham",
    "sg:classifiers":[
        {
            "category":"Insurance",
            "subcategory":"Insurance Agent",
            "type":"Services"
        }
    ],
    "sg:phone":"+44 161 785 0388",
    "sg:postcode":"OL1 1SQ",
    "sg:province":"Lancashire",
    "wof:name":"M A Insurance & Communications",
    "wof:placetype":"venue"
},
  "geometry": {"coordinates":[-2.108539,53.541412],"type":"Point"}
}