{
  "type": "Feature",
  "properties": {
    "addr:full":"Castle Lane West Bournemouth Dorset BH8 9UQ",
    "addr:postcode":"bh8 9uq",
    "addr:street":"Castle Lane West",
    "iso:country":"GB",
    "sg:address":"Castle Lane West",
    "sg:city":"Bournemouth",
    "sg:classifiers":[
        {
            "category":"Personal",
            "subcategory":"Beauty Salon",
            "type":"Services"
        }
    ],
    "sg:phone":"+44 1202 304341",
    "sg:postcode":"BH8 9UQ",
    "sg:province":"Dorset",
    "sg:tags":[
        "unisex",
        "hairdresser"
    ],
    "wof:name":"Heatwave",
    "wof:placetype":"venue"
},
  "geometry": {"coordinates":[-1.8566520214,50.7539978027],"type":"Point"}
}