{
  "type": "Feature",
  "properties": {
    "addr:full":"88 High Street, Wrestlingworth Sandy Bedfordshire SG19 2EJ",
    "addr:housenumber":"88",
    "addr:postcode":"sg19 2ej",
    "addr:street":"High Street",
    "iso:country":"GB",
    "sg:address":"88 High Street, Wrestlingworth",
    "sg:city":"Sandy",
    "sg:classifiers":[
        {
            "category":"Shopping",
            "subcategory":"Comic Books",
            "type":"Retail Goods"
        }
    ],
    "sg:phone":"+44 1767 631384",
    "sg:postcode":"SG19 2EJ",
    "sg:province":"Bedfordshire",
    "sg:tags":[
        "magazine"
    ],
    "wof:name":"Peachy-Keen Mail Order",
    "wof:placetype":"venue"
},
  "geometry": {"coordinates":[-0.1621659994,52.1135559082],"type":"Point"}
}