{
  "type": "Feature",
  "properties": {
    "iso:country":"GB",
    "sg:address":"6 Hardwick Drive",
    "sg:city":"Loughborough",
    "sg:classifiers":[
        {
            "category":"Personal",
            "type":"Services"
        },
        {
            "category":"Retail",
            "subcategory":"Repair Shop",
            "type":"Services"
        }
    ],
    "sg:postcode":"LE11 4TJ",
    "sg:province":"Leicestershire",
    "sg:tags":[
        "maintenance",
        "wedding"
    ],
    "wof:name":"Memory Lane Vintage Car Hire",
    "wof:placetype":"venue"
},
  "geometry": {"coordinates":[-1.237994,52.774494],"type":"Point"}
}