{
  "type": "Feature",
  "properties": {
    "addr:full":"48 Belvedere Avenue, Reddish Stockport Cheshire SK5 6QJ",
    "addr:housenumber":"48",
    "addr:postcode":"sk5 6qj",
    "addr:street":"Belvedere Avenue",
    "iso:country":"GB",
    "sg:address":"48 Belvedere Avenue, Reddish",
    "sg:city":"Stockport",
    "sg:classifiers":[
        {
            "category":"Building & Trades",
            "subcategory":"Plumbing",
            "type":"Services"
        }
    ],
    "sg:phone":"+44 161 320 7385",
    "sg:postcode":"SK5 6QJ",
    "sg:province":"Cheshire",
    "sg:tags":[
        "heating"
    ],
    "wof:name":"Robinson Eric Plumbing Services",
    "wof:placetype":"venue"
},
  "geometry": {"coordinates":[-2.1526999474,53.449546814],"type":"Point"}
}