{
  "type": "Feature",
  "properties": {
    "addr:full":"Paygrove Farm, Longlevens Gloucester Gloucestershire GL2 0BN",
    "addr:housenumber":"longlevens",
    "addr:postcode":"gl2 0bn",
    "iso:country":"GB",
    "sg:address":"Paygrove Farm, Longlevens",
    "sg:city":"Gloucester",
    "sg:classifiers":[
        {
            "category":"Shopping",
            "subcategory":"Pets & Pet Supplies",
            "type":"Retail Goods"
        }
    ],
    "sg:phone":"+44 1452 524655",
    "sg:postcode":"GL2 0BN",
    "sg:province":"Gloucestershire",
    "sg:tags":[
        "food"
    ],
    "wof:name":"B E Eeles & Sons",
    "wof:placetype":"venue"
},
  "geometry": {"coordinates":[-2.2085850239,51.8822174072],"type":"Point"}
}