{
  "type": "Feature",
  "properties": {
    "iso:country":"GB",
    "sg:address":"11 Duckmoor Road",
    "sg:city":"Bristol",
    "sg:classifiers":[
        {
            "category":"Personal",
            "subcategory":"Beauty Salon",
            "type":"Services"
        }
    ],
    "sg:postcode":"BS3 2DD",
    "sg:province":"City of Bristol",
    "sg:tags":[
        "unisex",
        "hairdresser"
    ],
    "wof:name":"Hair by Rachael",
    "wof:placetype":"venue"
},
  "geometry": {"coordinates":[-2.614284,51.437286],"type":"Point"}
}