{
  "type": "Feature",
  "properties": {
    "iso:country":"GB",
    "sg:address":"Unit E",
    "sg:city":"Romford",
    "sg:classifiers":[
        {
            "category":"Shopping",
            "subcategory":"Comic Books",
            "type":"Retail Goods"
        }
    ],
    "sg:phone":"+44 1708 372727",
    "sg:postcode":"RM3 8EN",
    "sg:province":"Essex",
    "sg:tags":[
        "magazine"
    ],
    "wof:name":"Forbidden Planet (Scotland) Ltd.",
    "wof:placetype":"venue"
},
  "geometry": {"coordinates":[0.21746,51.59803],"type":"Point"}
}