{
  "type": "Feature",
  "properties": {
    "addr:full":"Adolescent Support Team, Bedford Villa, Amity Pl Plymouth Devon PL4 8EY",
    "addr:postcode":"pl4 8ey",
    "addr:street":"Amity Pl",
    "iso:country":"GB",
    "sg:address":"Adolescent Support Team, Bedford Villa, Amity Pl",
    "sg:city":"Plymouth",
    "sg:classifiers":[
        {
            "category":"Organizations",
            "subcategory":"Non-profit Organization",
            "type":"Services"
        }
    ],
    "sg:postcode":"PL4 8EY",
    "sg:province":"Devon",
    "sg:tags":[
        "organisation",
        "voluntary",
        "charity"
    ],
    "wof:name":"Nch Children's Services Ltd",
    "wof:placetype":"venue"
},
  "geometry": {"coordinates":[-4.136894,50.375805],"type":"Point"}
}