{
  "type": "Feature",
  "properties": {
    "addr:full":"101 Church Street Croydon Surrey CR0 1RN",
    "addr:housenumber":"101",
    "addr:postcode":"cr0 1rn",
    "addr:street":"Church Street",
    "iso:country":"GB",
    "sg:address":"101 Church Street",
    "sg:city":"Croydon",
    "sg:classifiers":[
        {
            "category":"Recreation",
            "subcategory":"Gun Range",
            "type":"Entertainment"
        },
        {
            "category":"Shopping",
            "subcategory":"Comic Books",
            "type":"Retail Goods"
        }
    ],
    "sg:phone":"+44 20 8686 2400",
    "sg:postcode":"CR0 1RN",
    "sg:province":"Surrey",
    "sg:tags":[
        "magazine",
        "publishing"
    ],
    "wof:name":"A Place in Space Ltd.",
    "wof:placetype":"venue"
},
  "geometry": {"coordinates":[-0.1047779992,51.3736801147],"type":"Point"}
}