{
  "type": "Feature",
  "properties": {
    "addr:full":"127 Kennington Road London Greater London SE11 6SF",
    "addr:housenumber":"127",
    "addr:postcode":"se11 6sf",
    "addr:street":"Kennington Road",
    "iso:country":"GB",
    "sg:address":"127 Kennington Road",
    "sg:city":"London",
    "sg:classifiers":[
        {
            "category":"Organizations",
            "subcategory":"Non-profit Organization",
            "type":"Services"
        }
    ],
    "sg:phone":"+44 20 7735 1925",
    "sg:postcode":"SE11 6SF",
    "sg:province":"Greater London",
    "sg:tags":[
        "organisation",
        "voluntary",
        "charity"
    ],
    "wof:name":"Lambeth Endowed Charities",
    "wof:placetype":"venue"
},
  "geometry": {"coordinates":[-0.1106470004,51.4947776794],"type":"Point"}
}