{
  "type": "Feature",
  "properties": {
    "addr:full":"8 Knightsbridge Grn London Greater London SW1X 7QL",
    "addr:housenumber":"8",
    "addr:postcode":"sw1x 7ql",
    "addr:street":"Knightsbridge Grn",
    "iso:country":"GB",
    "sg:address":"8 Knightsbridge Grn",
    "sg:city":"London",
    "sg:classifiers":[
        {
            "category":"Food & Beverages",
            "subcategory":"Fruits & Vegetables",
            "type":"Retail Goods"
        }
    ],
    "sg:phone":"+44 20 7589 7534",
    "sg:postcode":"SW1X 7QL",
    "sg:province":"Greater London",
    "sg:tags":[
        "greengrocer"
    ],
    "wof:name":"Albert Gate Fruit Stores Ltd",
    "wof:placetype":"venue"
},
  "geometry": {"coordinates":[-0.161649,51.501129],"type":"Point"}
}