{
  "type": "Feature",
  "properties": {
    "addr:full":"7 Cragside Avenue Belford Northumberland NE70 7NA",
    "addr:housenumber":"7",
    "addr:postcode":"ne70 7na",
    "addr:street":"Cragside Avenue",
    "iso:country":"GB",
    "sg:address":"7 Cragside Avenue",
    "sg:city":"Belford",
    "sg:classifiers":[
        {
            "category":"Freight",
            "type":"Transportation"
        }
    ],
    "sg:postcode":"NE70 7NA",
    "sg:province":"Northumberland",
    "sg:tags":[
        "haulage",
        "road"
    ],
    "wof:name":"David H Bryden",
    "wof:placetype":"venue"
},
  "geometry": {"coordinates":[-1.8304330111,55.6018066406],"type":"Point"}
}