{
  "type": "Feature",
  "properties": {
    "iso:country":"GB",
    "sg:address":"Rosewood, Simonburn Avenue",
    "sg:city":"Stoke-on-trent",
    "sg:classifiers":[
        {
            "category":"Building & Trades",
            "subcategory":"Plumbing",
            "type":"Services"
        }
    ],
    "sg:postcode":"ST4 5JR",
    "sg:province":"Staffordshire",
    "sg:tags":[
        "central",
        "heating"
    ],
    "wof:name":"G Mifflin",
    "wof:placetype":"venue"
},
  "geometry": {"coordinates":[-2.205154,53.001686],"type":"Point"}
}