{
  "type": "Feature",
  "properties": {
    "iso:country":"GB",
    "sg:address":"Unit 11/15, Red Doles Lane",
    "sg:city":"Huddersfield",
    "sg:classifiers":[
        {
            "category":"Food & Beverages",
            "subcategory":"Meat & Fish",
            "type":"Retail Goods"
        }
    ],
    "sg:phone":"+44 1484 548975",
    "sg:postcode":"HD2 1YF",
    "sg:province":"West Yorkshire",
    "sg:tags":[
        "merchant"
    ],
    "wof:name":"Sailbrand Ltd.",
    "wof:placetype":"venue"
},
  "geometry": {"coordinates":[-1.773766,53.663616],"type":"Point"}
}