{
  "type": "Feature",
  "properties": {
    "addr:full":"Tregenna, Ware Road Hoddesdon Essex EN11 9AF",
    "addr:postcode":"en11 9af",
    "addr:street":"Ware Road",
    "iso:country":"GB",
    "sg:address":"Tregenna, Ware Road",
    "sg:city":"Hoddesdon",
    "sg:classifiers":[
        {
            "category":"Military Area",
            "subcategory":"Air Force Base",
            "type":"Public Place"
        }
    ],
    "sg:phone":"+44 1992 442581",
    "sg:postcode":"EN11 9AF",
    "sg:province":"Essex",
    "sg:tags":[
        "taxi",
        "hire",
        "private"
    ],
    "wof:name":"Phoenix Car Service",
    "wof:placetype":"venue"
},
  "geometry": {"coordinates":[-0.013255,51.767841],"type":"Point"}
}