{
  "type": "Feature",
  "properties": {
    "addr:full":"Dibden Cottage, Pickburn Lane, Pickburn Doncaster South Yorkshire DN5 7XF",
    "addr:postcode":"dn5 7xf",
    "addr:street":"Pickburn Lane",
    "iso:country":"GB",
    "sg:address":"Dibden Cottage, Pickburn Lane, Pickburn",
    "sg:city":"Doncaster",
    "sg:classifiers":[
        {
            "category":"Building & Trades",
            "subcategory":"Construction",
            "type":"Services"
        }
    ],
    "sg:phone":"+44 1302 330193",
    "sg:postcode":"DN5 7XF",
    "sg:province":"South Yorkshire",
    "sg:tags":[
        "roofing",
        "contracting"
    ],
    "wof:name":"H D T Roofing Specialist",
    "wof:placetype":"venue"
},
  "geometry": {"coordinates":[-1.2224700451,53.5608596802],"type":"Point"}
}