{
  "type": "Feature",
  "properties": {
    "addr:full":"1 Hollie Lucas Rd, Kings Heath Birmingham West Midlands B13 0QJ",
    "addr:housenumber":"1",
    "addr:postcode":"b13 0qj",
    "addr:street":"Hollie Lucas Rd",
    "iso:country":"GB",
    "sg:address":"1 Hollie Lucas Rd, Kings Heath",
    "sg:city":"Birmingham",
    "sg:classifiers":[
        {
            "category":"Retail",
            "subcategory":"Driving School",
            "type":"Services"
        }
    ],
    "sg:phone":"+44 121 444 1670",
    "sg:postcode":"B13 0QJ",
    "sg:province":"West Midlands",
    "wof:name":"The Charwell Driving School",
    "wof:placetype":"venue"
},
  "geometry": {"coordinates":[-1.8859200478,52.4276237488],"type":"Point"}
}