{
  "type": "Feature",
  "properties": {
    "iso:country":"GB",
    "sg:address":"55 Cross Bank Road",
    "sg:city":"Batley",
    "sg:classifiers":[
        {
            "category":"Government",
            "subcategory":"Post Office",
            "type":"Public Place"
        }
    ],
    "sg:phone":"+44 1924 472171",
    "sg:postcode":"WF17 8PN",
    "sg:province":"West Yorkshire",
    "wof:name":"Carlinghow Post Office",
    "wof:placetype":"venue"
},
  "geometry": {"coordinates":[-1.6421660185,53.7176856995],"type":"Point"}
}