{
  "type": "Feature",
  "properties": {
    "addr:full":"63 Station Road London Greater London NW10 4UX",
    "addr:housenumber":"63",
    "addr:postcode":"nw10 4ux",
    "addr:street":"Station Road",
    "iso:country":"GB",
    "sg:address":"63 Station Road",
    "sg:city":"London",
    "sg:classifiers":[
        {
            "category":"Home & Garden",
            "subcategory":"Household Appliances",
            "type":"Retail Goods"
        }
    ],
    "sg:phone":"+44 20 8961 8878",
    "sg:postcode":"NW10 4UX",
    "sg:province":"Greater London",
    "sg:tags":[
        "domestic",
        "centre"
    ],
    "wof:name":"A1 Domestic Appliances",
    "wof:placetype":"venue"
},
  "geometry": {"coordinates":[-0.24651,51.533169],"type":"Point"}
}