{
  "type": "Feature",
  "properties": {
    "addr:full":"5 Ashling Court Nottingham Nottinghamshire NG2 3JA",
    "addr:housenumber":"5",
    "addr:postcode":"ng2 3ja",
    "addr:street":"Ashling Court",
    "iso:country":"GB",
    "sg:address":"5 Ashling Court",
    "sg:city":"Nottingham",
    "sg:classifiers":[
        {
            "category":"Retail",
            "subcategory":"Photofinishing",
            "type":"Services"
        }
    ],
    "sg:phone":"+44 115 986 5436",
    "sg:postcode":"NG2 3JA",
    "sg:province":"Nottinghamshire",
    "sg:tags":[
        "photographic",
        "processor"
    ],
    "wof:name":"Silver Graphics Ltd.",
    "wof:placetype":"venue"
},
  "geometry": {"coordinates":[-1.136382,52.941853],"type":"Point"}
}