{
  "type": "Feature",
  "properties": {
    "iso:country":"GB",
    "sg:address":"8 Leigh Road",
    "sg:city":"Havant",
    "sg:classifiers":[
        {
            "category":"Social Services",
            "subcategory":"Child Care",
            "type":"Services"
        }
    ],
    "sg:phone":"+44 23 9247 2300",
    "sg:postcode":"PO9 2ET",
    "sg:province":"Hampshire",
    "sg:tags":[
        "children's",
        "home"
    ],
    "wof:name":"Stonecroft",
    "wof:placetype":"venue"
},
  "geometry": {"coordinates":[-0.979892,50.856232],"type":"Point"}
}