{
  "type": "Feature",
  "properties": {
    "addr:full":"90 Sydney St, Chelsea Chelsea Greater London SW3 6NJ",
    "addr:housenumber":"90",
    "addr:postcode":"sw3 6nj",
    "addr:street":"Sydney St",
    "iso:country":"GB",
    "sg:address":"90 Sydney St, Chelsea",
    "sg:city":"Chelsea",
    "sg:classifiers":[
        {
            "category":"Shopping",
            "subcategory":"Books",
            "type":"Retail Goods"
        }
    ],
    "sg:phone":"+44 20 7873 9689",
    "sg:postcode":"SW3 6NJ",
    "sg:province":"Greater London",
    "wof:name":"ISH Legal & Business Publications",
    "wof:placetype":"venue"
},
  "geometry": {"coordinates":[-0.168917,51.487938],"type":"Point"}
}