{
  "type": "Feature",
  "properties": {
    "addr:full":"1a Broughton St, Beeston Nottingham Nottinghamshire NG9 1BD",
    "addr:housenumber":"1a",
    "addr:postcode":"ng9 1bd",
    "addr:street":"Broughton St",
    "iso:country":"GB",
    "sg:address":"1a Broughton St, Beeston",
    "sg:city":"Nottingham",
    "sg:classifiers":[
        {
            "category":"Professional",
            "type":"Services"
        }
    ],
    "sg:phone":"+44 115 925 9530",
    "sg:postcode":"NG9 1BD",
    "sg:province":"Nottinghamshire",
    "sg:tags":[
        "shopfitters"
    ],
    "wof:name":"Bridgeman Brothers",
    "wof:placetype":"venue"
},
  "geometry": {"coordinates":[-1.2187889814,52.9294395447],"type":"Point"}
}