{
  "type": "Feature",
  "properties": {
    "iso:country":"GB",
    "sg:address":"7 Perrior Road",
    "sg:city":"Godalming",
    "sg:classifiers":[
        {
            "category":"Freight",
            "type":"Transportation"
        },
        {
            "category":"Government",
            "subcategory":"Post Office",
            "type":"Public Place"
        }
    ],
    "sg:phone":"+44 1483 422222",
    "sg:postcode":"GU7 3PY",
    "sg:province":"Surrey",
    "sg:tags":[
        "haulage",
        "messenger",
        "courier",
        "road"
    ],
    "wof:name":"1ST Choice G T N Couriers",
    "wof:placetype":"venue"
},
  "geometry": {"coordinates":[-0.607369,51.199009],"type":"Point"}
}