{
  "type": "Feature",
  "properties": {
    "addr:full":"Plymouth Gro Manchester Greater Manchester M13 9LL",
    "addr:postcode":"m13 9ll",
    "addr:street":"Gro",
    "iso:country":"GB",
    "sg:address":"Plymouth Gro",
    "sg:city":"Manchester",
    "sg:classifiers":[
        {
            "category":"Social Services",
            "subcategory":"Child Care",
            "type":"Services"
        }
    ],
    "sg:phone":"+44 161 251 4200",
    "sg:postcode":"M13 9LL",
    "sg:province":"Greater Manchester",
    "sg:tags":[
        "donor",
        "blood"
    ],
    "wof:name":"Manchester Blood Centre",
    "wof:placetype":"venue"
},
  "geometry": {"coordinates":[-2.2257490158,53.4650802612],"type":"Point"}
}