{
  "type": "Feature",
  "properties": {
    "addr:full":"Main Rd Maryport Cumbria CA15 8PB",
    "addr:postcode":"ca15 8pb",
    "addr:street":"Main Rd",
    "iso:country":"GB",
    "sg:address":"Main Rd",
    "sg:city":"Maryport",
    "sg:classifiers":[
        {
            "category":"Bars & Pubs",
            "type":"Food & Drink"
        }
    ],
    "sg:phone":"+44 1900 812720",
    "sg:postcode":"CA15 8PB",
    "sg:province":"Cumbria",
    "sg:tags":[
        "pubs",
        "inn"
    ],
    "wof:name":"Miners Arms",
    "wof:placetype":"venue"
},
  "geometry": {"coordinates":[-3.499809,54.708397],"type":"Point"}
}