{
  "type": "Feature",
  "properties": {
    "addr:full":"Dava, St Cleers Somerton Somerset TA11 6HL",
    "addr:postcode":"ta11 6hl",
    "addr:street":"Dava",
    "iso:country":"GB",
    "sg:address":"Dava, St Cleers",
    "sg:city":"Somerton",
    "sg:classifiers":[
        {
            "category":"Building & Trades",
            "subcategory":"Plumbing",
            "type":"Services"
        }
    ],
    "sg:phone":"+44 1458 272560",
    "sg:postcode":"TA11 6HL",
    "sg:province":"Somerset",
    "sg:tags":[
        "central",
        "installation",
        "heating",
        "servicing",
        "system"
    ],
    "wof:name":"D J Summerhayes",
    "wof:placetype":"venue"
},
  "geometry": {"coordinates":[-2.743304,51.053329],"type":"Point"}
}