{
  "type": "Feature",
  "properties": {
    "addr:full":"56 Wellington Road, Wilsden Bradford West Yorkshire BD15 0LX",
    "addr:housenumber":"56",
    "addr:postcode":"bd15 0lx",
    "addr:street":"Wellington Road",
    "iso:country":"GB",
    "sg:address":"56 Wellington Road, Wilsden",
    "sg:city":"Bradford",
    "sg:classifiers":[
        {
            "category":"Professional",
            "subcategory":"Engineering",
            "type":"Services"
        },
        {
            "category":"Building & Trades",
            "subcategory":"Electrical",
            "type":"Services"
        }
    ],
    "sg:phone":"+44 1535 272964",
    "sg:postcode":"BD15 0LX",
    "sg:province":"West Yorkshire",
    "sg:tags":[
        "engineer",
        "electrician",
        "contractor"
    ],
    "wof:name":"JOHN RICHARDS",
    "wof:placetype":"venue"
},
  "geometry": {"coordinates":[-1.86282897,53.8188400269],"type":"Point"}
}