{
  "type": "Feature",
  "properties": {
    "addr:full":"8 Undercliff Road West Felixstowe Suffolk IP11 2AW",
    "addr:housenumber":"8",
    "addr:postcode":"ip11 2aw",
    "addr:street":"Undercliff Road West",
    "iso:country":"GB",
    "sg:address":"8 Undercliff Road West",
    "sg:city":"Felixstowe",
    "sg:classifiers":[
        {
            "category":"Home & Garden",
            "subcategory":"Hardware",
            "type":"Retail Goods"
        }
    ],
    "sg:phone":"+44 1394 271370",
    "sg:postcode":"IP11 2AW",
    "sg:province":"Suffolk",
    "sg:tags":[
        "retailer",
        "diy"
    ],
    "wof:name":"Bills D I Y Centre",
    "wof:placetype":"venue"
},
  "geometry": {"coordinates":[1.3410320282,51.958065033],"type":"Point"}
}