{
  "type": "Feature",
  "properties": {
    "iso:country":"GB",
    "sg:address":"9 Adderwell",
    "sg:city":"Frome",
    "sg:classifiers":[
        {
            "category":"Building & Trades",
            "subcategory":"Construction",
            "type":"Services"
        },
        {
            "category":"Home & Garden",
            "subcategory":"Carpets & Floor Coverings",
            "type":"Retail Goods"
        }
    ],
    "sg:phone":"+44 1373 466512",
    "sg:postcode":"BA11 1NP",
    "sg:province":"Somerset",
    "sg:tags":[
        "welder",
        "rug",
        "carpets",
        "matting"
    ],
    "wof:name":"Liz Boss",
    "wof:placetype":"venue"
},
  "geometry": {"coordinates":[-2.314915,51.223759],"type":"Point"}
}