{
  "type": "Feature",
  "properties": {
    "addr:full":"16 Mercer Pl Dunfermline Fife KY11 4UG",
    "addr:housenumber":"16",
    "addr:postcode":"ky11 4ug",
    "addr:street":"Mercer Pl",
    "iso:country":"GB",
    "sg:address":"16 Mercer Pl",
    "sg:city":"Dunfermline",
    "sg:classifiers":[
        {
            "category":"Education",
            "subcategory":"Dance Studio",
            "type":"Public Place"
        }
    ],
    "sg:phone":"+44 1383 624497",
    "sg:postcode":"KY11 4UG",
    "sg:province":"Fife",
    "sg:tags":[
        "school",
        "dancing"
    ],
    "wof:name":"Steppin Out Dance Studio",
    "wof:placetype":"venue"
},
  "geometry": {"coordinates":[-3.4253630638,56.0747718811],"type":"Point"}
}