{
  "type": "Feature",
  "properties": {
    "iso:country":"GB",
    "sg:address":"Bailey Barracks, Greenhill Park, Greenhill Way",
    "sg:city":"Sheffield",
    "sg:classifiers":[
        {
            "category":"Government",
            "subcategory":"Office",
            "type":"Public Place"
        }
    ],
    "sg:phone":"+44 114 237 8607",
    "sg:postcode":"S8 7JQ",
    "sg:province":"Derbyshire",
    "sg:tags":[
        "armed",
        "reserve"
    ],
    "wof:name":"Territorial Army",
    "wof:placetype":"venue"
},
  "geometry": {"coordinates":[-1.47482,53.328892],"type":"Point"}
}