{
  "type": "Feature",
  "properties": {
    "addr:full":"High Street, Tean Stoke-on-trent Staffordshire ST10 4DY",
    "addr:postcode":"st10 4dy",
    "addr:street":"High Street",
    "iso:country":"GB",
    "sg:address":"High Street, Tean",
    "sg:city":"Stoke-on-trent",
    "sg:classifiers":[
        {
            "category":"Bars & Pubs",
            "type":"Food & Drink"
        }
    ],
    "sg:postcode":"ST10 4DY",
    "sg:province":"Staffordshire",
    "sg:tags":[
        "pubs",
        "inn"
    ],
    "wof:name":"The Blacks Head",
    "wof:placetype":"venue"
},
  "geometry": {"coordinates":[-1.9866349697,52.9535293579],"type":"Point"}
}