{
  "type": "Feature",
  "properties": {
    "iso:country":"GB",
    "sg:address":"Low Longthwaite Farm, Watermillock",
    "sg:city":"Penrith",
    "sg:classifiers":[
        {
            "category":"Farming",
            "subcategory":"Dairy Farm",
            "type":"Manufacturing & Wholesale Goods"
        }
    ],
    "sg:phone":"+44 17684 86292",
    "sg:postcode":"CA11 0LR",
    "sg:province":"Cumbria",
    "sg:tags":[
        "farmer"
    ],
    "wof:name":"FRANK LITTLE",
    "wof:placetype":"venue"
},
  "geometry": {"coordinates":[-2.858688,54.593777],"type":"Point"}
}