{
  "type": "Feature",
  "properties": {
    "iso:country":"GB",
    "sg:address":"45 Links Road",
    "sg:city":"Ashtead",
    "sg:classifiers":[
        {
            "category":"Shopping",
            "subcategory":"Department Store",
            "type":"Retail Goods"
        },
        {
            "category":"Home & Garden",
            "subcategory":"Carpets & Floor Coverings",
            "type":"Retail Goods"
        }
    ],
    "sg:phone":"+44 1372 276028",
    "sg:postcode":"KT21 2HL",
    "sg:province":"Surrey",
    "sg:tags":[
        "retailer",
        "rug"
    ],
    "wof:name":"Derek J Webb",
    "wof:placetype":"venue"
},
  "geometry": {"coordinates":[-0.318175,51.314526],"type":"Point"}
}