{
  "type": "Feature",
  "properties": {
    "addr:full":"Bodrigan Farm, Tresarrett Bodmin Cornwall PL30 4QQ",
    "addr:postcode":"pl30 4qq",
    "addr:street":"Tresarrett",
    "iso:country":"GB",
    "sg:address":"Bodrigan Farm, Tresarrett",
    "sg:city":"Bodmin",
    "sg:classifiers":[
        {
            "category":"Home & Garden",
            "subcategory":"Building Materials",
            "type":"Retail Goods"
        }
    ],
    "sg:postcode":"PL30 4QQ",
    "sg:province":"Cornwall",
    "sg:tags":[
        "fencing"
    ],
    "wof:name":"Field Guard Elctric Fencing",
    "wof:placetype":"venue"
},
  "geometry": {"coordinates":[-4.6968741417,50.5266838074],"type":"Point"}
}