{
  "type": "Feature",
  "properties": {
    "iso:country":"GB",
    "sg:address":"South Terminal, London Gatwick Airport",
    "sg:city":"Gatwick",
    "sg:classifiers":[
        {
            "category":"Fast Food",
            "type":"Food & Drink"
        }
    ],
    "sg:phone":"+44 1293 502085",
    "sg:postcode":"RH6 0QY",
    "sg:province":"Surrey",
    "sg:tags":[
        "away",
        "take"
    ],
    "wof:name":"KFC",
    "wof:placetype":"venue"
},
  "geometry": {"coordinates":[-0.1723539978,51.1617736816],"type":"Point"}
}