{
  "type": "Feature",
  "properties": {
    "addr:full":"Quay Street Haverfordwest Pembrokeshire SA61 1BE",
    "addr:postcode":"sa61 1be",
    "addr:street":"Quay Street",
    "iso:country":"GB",
    "sg:address":"Quay Street",
    "sg:city":"Haverfordwest",
    "sg:classifiers":[
        {
            "category":"Bars & Pubs",
            "type":"Food & Drink"
        }
    ],
    "sg:phone":"+44 1437 762122",
    "sg:postcode":"SA61 1BE",
    "sg:province":"Pembrokeshire",
    "sg:tags":[
        "pubs",
        "inn"
    ],
    "wof:name":"Bristol Trader",
    "wof:placetype":"venue"
},
  "geometry": {"coordinates":[-4.967051,51.800194],"type":"Point"}
}