{
  "type": "Feature",
  "properties": {
    "iso:country":"GB",
    "sg:address":"Rock Hill House",
    "sg:city":"Chulmleigh",
    "sg:classifiers":[
        {
            "category":"Professional",
            "subcategory":"Accounting & Tax Preparation",
            "type":"Services"
        }
    ],
    "sg:phone":"+44 1769 580025",
    "sg:postcode":"EX18 7BX",
    "sg:province":"Devon",
    "sg:tags":[
        "accountant"
    ],
    "wof:name":"N R Blackmore & Co",
    "wof:placetype":"venue"
},
  "geometry": {"coordinates":[-3.868804,50.912495],"type":"Point"}
}