{
  "type": "Feature",
  "properties": {
    "addr:full":"27a Sloane Square London Greater London SW1W 8AB",
    "addr:housenumber":"27a",
    "addr:postcode":"sw1w 8ab",
    "iso:country":"GB",
    "sg:address":"27a Sloane Square",
    "sg:city":"London",
    "sg:classifiers":[
        {
            "category":"Manufacturing",
            "subcategory":"Buildings",
            "type":"Manufacturing & Wholesale Goods"
        }
    ],
    "sg:postcode":"SW1W 8AB",
    "sg:province":"Greater London",
    "sg:tags":[
        "portable"
    ],
    "wof:name":"Conport Structures Ltd.",
    "wof:placetype":"venue"
},
  "geometry": {"coordinates":[-0.1579809934,51.4922370911],"type":"Point"}
}