{
  "type": "Feature",
  "properties": {
    "iso:country":"GB",
    "sg:address":"1 Fish Row",
    "sg:city":"Salisbury",
    "sg:classifiers":[
        {
            "category":"Social Services",
            "subcategory":"Adult Care",
            "type":"Services"
        }
    ],
    "sg:phone":"+44 1722 421745",
    "sg:postcode":"SP1 1EX",
    "sg:province":"Wiltshire",
    "sg:tags":[
        "day",
        "centre"
    ],
    "wof:name":"The Greencroft New Alliance",
    "wof:placetype":"venue"
},
  "geometry": {"coordinates":[-1.794419,51.068905],"type":"Point"}
}