{
  "type": "Feature",
  "properties": {
    "iso:country":"GB",
    "sg:address":"Caledonian Ho, Tatton St",
    "sg:city":"Knutsford",
    "sg:classifiers":[
        {
            "category":"Real Estate",
            "subcategory":"Surveying",
            "type":"Services"
        }
    ],
    "sg:phone":"+44 1565 650058",
    "sg:postcode":"WA16 6AG",
    "sg:province":"Cheshire",
    "sg:tags":[
        "surveyor",
        "valuer"
    ],
    "wof:name":"Knutsford & Cheshire",
    "wof:placetype":"venue"
},
  "geometry": {"coordinates":[-2.37624,53.304203],"type":"Point"}
}