{
  "type": "Feature",
  "properties": {
    "iso:country":"GB",
    "sg:address":"93 Coalway Road, Penn",
    "sg:city":"Wolverhampton",
    "sg:classifiers":[
        {
            "category":"Home & Garden",
            "subcategory":"Carpets & Floor Coverings",
            "type":"Retail Goods"
        }
    ],
    "sg:postcode":"WV3 7LY",
    "sg:province":"Staffordshire",
    "sg:tags":[
        "cleaner",
        "upholstery"
    ],
    "wof:name":"Quick Dry Carpet Cleaning",
    "wof:placetype":"venue"
},
  "geometry": {"coordinates":[-2.152539,52.568989],"type":"Point"}
}