{
  "type": "Feature",
  "properties": {
    "addr:full":"9 Market Place Forfar Angus DD8 3BQ",
    "addr:housenumber":"9",
    "addr:postcode":"dd8 3bq",
    "addr:street":"Market Place",
    "iso:country":"GB",
    "sg:address":"9 Market Place",
    "sg:city":"Forfar",
    "sg:classifiers":[
        {
            "category":"Retail",
            "subcategory":"Auto Repair",
            "type":"Services"
        }
    ],
    "sg:postcode":"DD8 3BQ",
    "sg:province":"Angus",
    "sg:tags":[
        "garage"
    ],
    "wof:name":"Angus Car Electrics",
    "wof:placetype":"venue"
},
  "geometry": {"coordinates":[-2.8870279789,56.6496200562],"type":"Point"}
}