{
  "type": "Feature",
  "properties": {
    "addr:full":"Trinity Centre, St Pauls Hill Winchester Hampshire SO22 5AE",
    "addr:postcode":"so22 5ae",
    "addr:street":"St Pauls Hill",
    "iso:country":"GB",
    "sg:address":"Trinity Centre, St Pauls Hill",
    "sg:city":"Winchester",
    "sg:classifiers":[
        {
            "category":"Organizations",
            "subcategory":"Non-profit Organization",
            "type":"Services"
        }
    ],
    "sg:phone":"+44 1962 855562",
    "sg:postcode":"SO22 5AE",
    "sg:province":"Hampshire",
    "sg:tags":[
        "organisation",
        "voluntary",
        "charity"
    ],
    "wof:name":"Trinity Furniture Recycling Project",
    "wof:placetype":"venue"
},
  "geometry": {"coordinates":[-1.32278,51.066971],"type":"Point"}
}