{
  "type": "Feature",
  "properties": {
    "iso:country":"GB",
    "sg:address":"94 Holloway Rd",
    "sg:city":"Holloway",
    "sg:classifiers":[
        {
            "category":"Health Services",
            "subcategory":"Doctor",
            "type":"Services"
        }
    ],
    "sg:phone":"+44 20 7607 2323",
    "sg:postcode":"N7 8JG",
    "sg:province":"Greater London",
    "sg:tags":[
        "practitioners"
    ],
    "wof:name":"Morris-Davies, F N",
    "wof:placetype":"venue"
},
  "geometry": {"coordinates":[-0.1082639992,51.5497741699],"type":"Point"}
}