{
  "type": "Feature",
  "properties": {
    "addr:full":"Unit D3, Seedbed Centre Romford Essex RM7 0AZ",
    "addr:postcode":"rm7 0az",
    "iso:country":"GB",
    "sg:address":"Unit D3, Seedbed Centre",
    "sg:city":"Romford",
    "sg:classifiers":[
        {
            "category":"Shopping",
            "subcategory":"Clothing, Apparel, & Fashions",
            "type":"Retail Goods"
        }
    ],
    "sg:phone":"+44 1708 768869",
    "sg:postcode":"RM7 0AZ",
    "sg:province":"Essex",
    "sg:tags":[
        "clothing",
        "fabric"
    ],
    "wof:name":"Galaford Ltd.",
    "wof:placetype":"venue"
},
  "geometry": {"coordinates":[0.16928,51.562889],"type":"Point"}
}