{
  "type": "Feature",
  "properties": {
    "iso:country":"GB",
    "sg:address":"168 Birchfield Road East",
    "sg:city":"Northampton",
    "sg:classifiers":[
        {
            "category":"Retail",
            "subcategory":"Laundry & Dry Cleaning",
            "type":"Services"
        }
    ],
    "sg:phone":"+44 1604 713598",
    "sg:postcode":"NN3 2HF",
    "sg:province":"Northamptonshire",
    "sg:tags":[
        "launderette"
    ],
    "wof:name":"The One Stop Laundry Shop",
    "wof:placetype":"venue"
},
  "geometry": {"coordinates":[-0.865931,52.252022],"type":"Point"}
}