{
  "type": "Feature",
  "properties": {
    "iso:country":"GB",
    "sg:address":"18 Old Mill Road",
    "sg:city":"Torquay",
    "sg:classifiers":[
        {
            "category":"Professional",
            "subcategory":"Printing & Photocopies",
            "type":"Services"
        }
    ],
    "sg:postcode":"TQ2 6AU",
    "sg:province":"Devon",
    "sg:tags":[
        "printer"
    ],
    "wof:name":"1st Impression",
    "wof:placetype":"venue"
},
  "geometry": {"coordinates":[-3.546323061,50.4663047791],"type":"Point"}
}