{
  "type": "Feature",
  "properties": {
    "addr:full":"2a Ten Valley Crescent Liverpool Merseyside L6 3BY",
    "addr:housenumber":"2a",
    "addr:postcode":"l6 3by",
    "addr:street":"Ten Valley Crescent",
    "iso:country":"GB",
    "sg:address":"2a Ten Valley Crescent",
    "sg:city":"Liverpool",
    "sg:classifiers":[
        {
            "category":"Health Services",
            "subcategory":"Clinic",
            "type":"Services"
        }
    ],
    "sg:phone":"+44 151 285 4400",
    "sg:postcode":"L6 3BY",
    "sg:province":"Merseyside",
    "sg:tags":[
        "nh"
    ],
    "wof:name":"Sheil Park Family Health Clinic",
    "wof:placetype":"venue"
},
  "geometry": {"coordinates":[-2.9475400448,53.4181213379],"type":"Point"}
}