{
  "type": "Feature",
  "properties": {
    "addr:full":"39 High Street, Wath Upon Dearne Rotherham South Yorkshire S63 7QB",
    "addr:housenumber":"39",
    "addr:postcode":"s63 7qb",
    "addr:street":"High Street",
    "iso:country":"GB",
    "sg:address":"39 High Street, Wath Upon Dearne",
    "sg:city":"Rotherham",
    "sg:classifiers":[
        {
            "category":"Food & Beverages",
            "subcategory":"Bakery",
            "type":"Retail Goods"
        }
    ],
    "sg:postcode":"S63 7QB",
    "sg:province":"South Yorkshire",
    "sg:tags":[
        "baker"
    ],
    "wof:name":"Cooplands (Doncaster) Ltd.",
    "wof:placetype":"venue"
},
  "geometry": {"coordinates":[-1.343086,53.502831],"type":"Point"}
}