{
  "type": "Feature",
  "properties": {
    "addr:full":"120 Bedford Avenue Barnet Hertfordshire EN5 2ET",
    "addr:housenumber":"120",
    "addr:postcode":"en5 2et",
    "addr:street":"Bedford Avenue",
    "iso:country":"GB",
    "sg:address":"120 Bedford Avenue",
    "sg:city":"Barnet",
    "sg:classifiers":[
        {
            "category":"Health Services",
            "subcategory":"Nursing And Care Facility",
            "type":"Services"
        }
    ],
    "sg:phone":"+44 20 8449 1526",
    "sg:postcode":"EN5 2ET",
    "sg:province":"Hertfordshire",
    "sg:tags":[
        "home"
    ],
    "wof:name":"Caring Carers Agency",
    "wof:placetype":"venue"
},
  "geometry": {"coordinates":[-0.200049,51.646496],"type":"Point"}
}