{
  "type": "Feature",
  "properties": {
    "iso:country":"GB",
    "sg:address":"59 Westlands Rd",
    "sg:city":"Uttoxeter",
    "sg:classifiers":[
        {
            "category":"Government",
            "subcategory":"Post Office",
            "type":"Public Place"
        }
    ],
    "sg:phone":"+44 1889 566668",
    "sg:postcode":"ST14 8DJ",
    "sg:province":"Derbyshire",
    "sg:tags":[
        "messenger",
        "courier"
    ],
    "wof:name":"Mercury Express UK",
    "wof:placetype":"venue"
},
  "geometry": {"coordinates":[-1.874378,52.891247],"type":"Point"}
}