{
  "type": "Feature",
  "properties": {
    "addr:full":"9 Burnwood Dr Airdrie North Lanarkshire ML6 8NQ",
    "addr:housenumber":"9",
    "addr:postcode":"ml6 8nq",
    "addr:street":"Burnwood Dr",
    "iso:country":"GB",
    "sg:address":"9 Burnwood Dr",
    "sg:city":"Airdrie",
    "sg:classifiers":[
        {
            "category":"Wholesale",
            "subcategory":"Medical Equipment & Supplies",
            "type":"Manufacturing & Wholesale Goods"
        }
    ],
    "sg:postcode":"ML6 8NQ",
    "sg:province":"North Lanarkshire",
    "sg:tags":[
        "hospital"
    ],
    "wof:name":"Rentens Obstetric Tens Rental",
    "wof:placetype":"venue"
},
  "geometry": {"coordinates":[-3.9348490238,55.862537384],"type":"Point"}
}