{
  "type": "Feature",
  "properties": {
    "iso:country":"GB",
    "sg:address":"15 Bulstrode Rd",
    "sg:city":"Hounslow",
    "sg:classifiers":[
        {
            "category":"Professional",
            "subcategory":"Lawyer & Legal Services",
            "type":"Services"
        }
    ],
    "sg:phone":"+44 20 8570 3594",
    "sg:postcode":"TW3 3AN",
    "sg:province":"Greater London",
    "sg:tags":[
        "advice",
        "counselling"
    ],
    "wof:name":"Swan Project The",
    "wof:placetype":"venue"
},
  "geometry": {"coordinates":[-0.368124,51.469872],"type":"Point"}
}