{
  "type": "Feature",
  "properties": {
    "addr:full":"7 Holman Street Aylesbury Buckinghamshire HP19 9LJ",
    "addr:housenumber":"7",
    "addr:postcode":"hp19 9lj",
    "addr:street":"Holman Street",
    "iso:country":"GB",
    "sg:address":"7 Holman Street",
    "sg:city":"Aylesbury",
    "sg:classifiers":[
        {
            "category":"Organizations",
            "subcategory":"Non-profit Organization",
            "type":"Services"
        }
    ],
    "sg:phone":"+44 1296 392498",
    "sg:postcode":"HP19 9LJ",
    "sg:province":"Buckinghamshire",
    "sg:tags":[
        "organisation",
        "voluntary",
        "charity"
    ],
    "wof:name":"Community Matters Bucks",
    "wof:placetype":"venue"
},
  "geometry": {"coordinates":[-0.8216739893,51.8264389038],"type":"Point"}
}