{
  "type": "Feature",
  "properties": {
    "addr:full":"2 Sandown Clo Eastbourne East Sussex BN23 8EF",
    "addr:housenumber":"2",
    "addr:postcode":"bn23 8ef",
    "iso:country":"GB",
    "sg:address":"2 Sandown Clo",
    "sg:city":"Eastbourne",
    "sg:classifiers":[
        {
            "category":"Education",
            "subcategory":"Dance Studio",
            "type":"Public Place"
        }
    ],
    "sg:phone":"+44 1323 767796",
    "sg:postcode":"BN23 8EF",
    "sg:province":"East Sussex",
    "sg:tags":[
        "school",
        "dancing"
    ],
    "wof:name":"Willingdon School of Dancing",
    "wof:placetype":"venue"
},
  "geometry": {"coordinates":[0.290623,50.809406],"type":"Point"}
}