{
  "type": "Feature",
  "properties": {
    "iso:country":"GB",
    "sg:address":"115 Rye Road",
    "sg:city":"Hoddesdon",
    "sg:classifiers":[
        {
            "category":"Professional",
            "subcategory":"Business Services",
            "type":"Services"
        }
    ],
    "sg:phone":"+44 1992 442618",
    "sg:postcode":"EN11 0JP",
    "sg:province":"Essex",
    "sg:tags":[
        "bookmaker"
    ],
    "wof:name":"Sports",
    "wof:placetype":"venue"
},
  "geometry": {"coordinates":[-0.00392,51.767033],"type":"Point"}
}