{
  "type": "Feature",
  "properties": {
    "addr:full":"Quality House, Quality Court Holborn Greater London WC2A 1HP",
    "addr:postcode":"wc2a 1hp",
    "addr:street":"Quality Court",
    "iso:country":"GB",
    "sg:address":"Quality House, Quality Court",
    "sg:city":"Holborn",
    "sg:classifiers":[
        {
            "category":"Professional",
            "subcategory":"Lawyer & Legal Services",
            "type":"Services"
        }
    ],
    "sg:phone":"+44 20 7404 3561",
    "sg:postcode":"WC2A 1HP",
    "sg:province":"Greater London",
    "wof:name":"National Law Tutors",
    "wof:placetype":"venue"
},
  "geometry": {"coordinates":[-0.1122239977,51.5163803101],"type":"Point"}
}