{
  "type": "Feature",
  "properties": {
    "addr:full":"Mayflower Close, Chandlers Ford Industrial Estate Eastleigh Hampshire SO53 4ZJ",
    "addr:postcode":"so53 4zj",
    "addr:street":"Mayflower Close Chandlers Ford Industrial Estate",
    "iso:country":"GB",
    "sg:address":"Mayflower Close, Chandlers Ford Industrial Estate",
    "sg:city":"Eastleigh",
    "sg:classifiers":[
        {
            "category":"Shopping",
            "subcategory":"Computers & Home Electronics",
            "type":"Retail Goods"
        }
    ],
    "sg:phone":"+44 23 8026 7411",
    "sg:postcode":"SO53 4ZJ",
    "sg:province":"Hampshire",
    "sg:tags":[
        "electrical"
    ],
    "wof:name":"Wades Electrical",
    "wof:placetype":"venue"
},
  "geometry": {"coordinates":[-1.395442009,50.982219696],"type":"Point"}
}