{
  "type": "Feature",
  "properties": {
    "addr:full":"The Old Post Office, Grassington Skipton Lancashire BD23 5AA",
    "addr:postcode":"bd23 5aa",
    "addr:street":"Grassington",
    "iso:country":"GB",
    "sg:address":"The Old Post Office, Grassington",
    "sg:city":"Skipton",
    "sg:classifiers":[
        {
            "category":"Professional",
            "subcategory":"Business Services",
            "type":"Services"
        },
        {
            "category":"Recreation",
            "subcategory":"Playground",
            "type":"Entertainment"
        }
    ],
    "sg:phone":"+44 1756 752757",
    "sg:postcode":"BD23 5AA",
    "sg:province":"Lancashire",
    "sg:tags":[
        "hospitality",
        "corporate"
    ],
    "wof:name":"Group North Ltd",
    "wof:placetype":"venue"
},
  "geometry": {"coordinates":[-1.9978630543,54.0710220337],"type":"Point"}
}