{
  "type": "Feature",
  "properties": {
    "addr:full":"1 Teal Close Blackburn Lancashire BB1 8JY",
    "addr:housenumber":"1",
    "addr:postcode":"bb1 8jy",
    "addr:street":"Teal Close",
    "iso:country":"GB",
    "sg:address":"1 Teal Close",
    "sg:city":"Blackburn",
    "sg:classifiers":[
        {
            "category":"Building & Trades",
            "subcategory":"Construction",
            "type":"Services"
        }
    ],
    "sg:phone":"+44 1254 675849",
    "sg:postcode":"BB1 8JY",
    "sg:province":"Lancashire",
    "sg:tags":[
        "roofing",
        "contracting"
    ],
    "wof:name":"Aspect Roofing Ltd",
    "wof:placetype":"venue"
},
  "geometry": {"coordinates":[-2.4934110641,53.7621612549],"type":"Point"}
}