{
  "type": "Feature",
  "properties": {
    "iso:country":"GB",
    "sg:address":"122 Aldsworth Avenue, Goring-by-sea",
    "sg:city":"Worthing",
    "sg:classifiers":[
        {
            "category":"Personal",
            "subcategory":"Beauty Salon",
            "type":"Services"
        }
    ],
    "sg:phone":"+44 1903 247592",
    "sg:postcode":"BN12 4UU",
    "sg:province":"West Sussex",
    "sg:tags":[
        "lady",
        "hairdresser"
    ],
    "wof:name":"Teresa's Hair Salon",
    "wof:placetype":"venue"
},
  "geometry": {"coordinates":[-0.431045,50.814705],"type":"Point"}
}