{
  "type": "Feature",
  "properties": {
    "addr:full":"34 Albion Road North Shields Tyne and Wear NE30 2RQ",
    "addr:housenumber":"34",
    "addr:postcode":"ne30 2rq",
    "addr:street":"Albion Road",
    "iso:country":"GB",
    "sg:address":"34 Albion Road",
    "sg:city":"North Shields",
    "sg:classifiers":[
        {
            "category":"Community Center",
            "subcategory":"Youth",
            "type":"Public Place"
        }
    ],
    "sg:phone":"+44 191 259 6766",
    "sg:postcode":"NE30 2RQ",
    "sg:province":"Tyne and Wear",
    "sg:tags":[
        "children's",
        "activity"
    ],
    "wof:name":"Kokos (North Shields) Ltd.",
    "wof:placetype":"venue"
},
  "geometry": {"coordinates":[-1.445554,55.011765],"type":"Point"}
}