{
  "type": "Feature",
  "properties": {
    "iso:country":"GB",
    "sg:address":"63 Church Street",
    "sg:city":"St Albans",
    "sg:classifiers":[
        {
            "category":"Professional",
            "subcategory":"Art Services",
            "type":"Services"
        }
    ],
    "sg:postcode":"AL3 5NG",
    "sg:province":"Hertfordshire",
    "sg:tags":[
        "photographer"
    ],
    "wof:name":"Dale Cherry Photography",
    "wof:placetype":"venue"
},
  "geometry": {"coordinates":[-0.336754,51.756981],"type":"Point"}
}