{
  "type": "Feature",
  "properties": {
    "iso:country":"GB",
    "sg:address":"14 Walker Gro",
    "sg:city":"Nottingham",
    "sg:classifiers":[
        {
            "category":"Building & Trades",
            "subcategory":"Construction",
            "type":"Services"
        }
    ],
    "sg:phone":"+44 115 949 9914",
    "sg:postcode":"NG9 7GY",
    "sg:province":"Nottinghamshire",
    "sg:tags":[
        "builder"
    ],
    "wof:name":"G W Mason Property Services",
    "wof:placetype":"venue"
},
  "geometry": {"coordinates":[-1.26728,52.9244],"type":"Point"}
}