{
  "type": "Feature",
  "properties": {
    "iso:country":"GB",
    "sg:address":"2 Riverside, Stansted Abbots",
    "sg:city":"Ware",
    "sg:classifiers":[
        {
            "category":"Professional",
            "subcategory":"Engineering",
            "type":"Services"
        }
    ],
    "sg:phone":"+44 1920 871061",
    "sg:postcode":"SG12 8AP",
    "sg:province":"Hertfordshire",
    "sg:tags":[
        "electronic",
        "engineer"
    ],
    "wof:name":"Electrotest Ltd.",
    "wof:placetype":"venue"
},
  "geometry": {"coordinates":[0.003689,51.787693],"type":"Point"}
}