{
  "type": "Feature",
  "properties": {
    "iso:country":"GB",
    "sg:address":"20 Watford Rd",
    "sg:city":"Kings Langley",
    "sg:classifiers":[
        {
            "category":"Health Services",
            "subcategory":"Dentist",
            "type":"Services"
        }
    ],
    "sg:phone":"+44 1923 267192",
    "sg:postcode":"WD4 8EA",
    "sg:province":"Hertfordshire",
    "wof:name":"R E Turner",
    "wof:placetype":"venue"
},
  "geometry": {"coordinates":[-0.448306,51.709599],"type":"Point"}
}