{
  "type": "Feature",
  "properties": {
    "addr:full":"254 High Street Perth Perth and Kinross PH1 5QJ",
    "addr:housenumber":"254",
    "addr:postcode":"ph1 5qj",
    "addr:street":"High Street",
    "iso:country":"GB",
    "sg:address":"254 High Street",
    "sg:city":"Perth",
    "sg:classifiers":[
        {
            "category":"Restaurant",
            "type":"Food & Drink"
        }
    ],
    "sg:phone":"+44 1738 639680",
    "sg:postcode":"PH1 5QJ",
    "sg:province":"Perth and Kinross",
    "sg:tags":[
        "mexican"
    ],
    "wof:name":"la Bamba Ltd.",
    "wof:placetype":"venue"
},
  "geometry": {"coordinates":[-3.435808,56.39679],"type":"Point"}
}