{
  "type": "Feature",
  "properties": {
    "iso:country":"GB",
    "sg:address":"15 Market Place",
    "sg:city":"Blandford Forum",
    "sg:classifiers":[
        {
            "category":"Professional",
            "subcategory":"Lawyer & Legal Services",
            "type":"Services"
        }
    ],
    "sg:phone":"+44 1258 455166",
    "sg:postcode":"DT11 7AF",
    "sg:province":"Dorset",
    "sg:tags":[
        "solicitor"
    ],
    "wof:name":"PORTER BARTLETT & MAYO",
    "wof:placetype":"venue"
},
  "geometry": {"coordinates":[-2.165084,50.85598],"type":"Point"}
}