{
  "type": "Feature",
  "properties": {
    "addr:full":"1 Samman Road Beverley East Riding of Yorkshire HU17 0BS",
    "addr:housenumber":"1",
    "addr:postcode":"hu17 0bs",
    "addr:street":"Samman Road",
    "iso:country":"GB",
    "sg:address":"1 Samman Road",
    "sg:city":"Beverley",
    "sg:classifiers":[
        {
            "category":"Shopping",
            "subcategory":"Pharmacy",
            "type":"Retail Goods"
        }
    ],
    "sg:phone":"+44 1482 868317",
    "sg:postcode":"HU17 0BS",
    "sg:province":"East Riding of Yorkshire",
    "sg:tags":[
        "pharmacist",
        "chemist"
    ],
    "wof:name":"Hills Pharmacy",
    "wof:placetype":"venue"
},
  "geometry": {"coordinates":[-0.4173670113,53.8468208313],"type":"Point"}
}