{
  "type": "Feature",
  "properties": {
    "addr:full":"Old Denny Rd Larbert Falkirk FK5 4SD",
    "addr:postcode":"fk5 4sd",
    "addr:street":"Old Denny Rd",
    "iso:country":"GB",
    "sg:address":"Old Denny Rd",
    "sg:city":"Larbert",
    "sg:classifiers":[
        {
            "category":"Health Services",
            "subcategory":"Clinic",
            "type":"Services"
        }
    ],
    "sg:phone":"+44 1324 570700",
    "sg:postcode":"FK5 4SD",
    "sg:province":"Falkirk",
    "sg:tags":[
        "planning",
        "family",
        "centre"
    ],
    "wof:name":"Central Scotland Health Care",
    "wof:placetype":"venue"
},
  "geometry": {"coordinates":[-3.844119,56.028381],"type":"Point"}
}