{
  "type": "Feature",
  "properties": {
    "addr:full":"111 Sydenham Road London Greater London SE26 5UA",
    "addr:housenumber":"111",
    "addr:postcode":"se26 5ua",
    "addr:street":"Sydenham Road",
    "iso:country":"GB",
    "sg:address":"111 Sydenham Road",
    "sg:city":"London",
    "sg:classifiers":[
        {
            "category":"Food & Beverages",
            "subcategory":"Bakery",
            "type":"Retail Goods"
        }
    ],
    "sg:phone":"+44 20 8778 4705",
    "sg:postcode":"SE26 5UA",
    "sg:province":"Greater London",
    "sg:tags":[
        "baker"
    ],
    "wof:name":"Slatters Bakery Ltd.",
    "wof:placetype":"venue"
},
  "geometry": {"coordinates":[-0.0414449982,51.4268913269],"type":"Point"}
}