{
  "type": "Feature",
  "properties": {
    "iso:country":"GB",
    "sg:address":"25 Brick Row, Babraham",
    "sg:city":"Cambridge",
    "sg:classifiers":[
        {
            "category":"Professional",
            "subcategory":"Art Services",
            "type":"Services"
        }
    ],
    "sg:phone":"+44 1223 836045",
    "sg:postcode":"CB2 4AJ",
    "sg:province":"Cambridgeshire",
    "sg:tags":[
        "graphic",
        "designer"
    ],
    "wof:name":"Constructive Solutions",
    "wof:placetype":"venue"
},
  "geometry": {"coordinates":[0.211295,52.131924],"type":"Point"}
}