{
  "type": "Feature",
  "properties": {
    "addr:full":"Goldward House, Somerville Road, Willand Cullompton Devon EX15 2PP",
    "addr:postcode":"ex15 2pp",
    "addr:street":"Somerville Road",
    "iso:country":"GB",
    "sg:address":"Goldward House, Somerville Road, Willand",
    "sg:city":"Cullompton",
    "sg:classifiers":[
        {
            "category":"Wholesale",
            "subcategory":"Chemicals & Plastics",
            "type":"Manufacturing & Wholesale Goods"
        }
    ],
    "sg:phone":"+44 1884 821281",
    "sg:postcode":"EX15 2PP",
    "sg:province":"Devon",
    "sg:tags":[
        "product",
        "allied"
    ],
    "wof:name":"Devon Weed Control",
    "wof:placetype":"venue"
},
  "geometry": {"coordinates":[-3.3727660179,50.8917121887],"type":"Point"}
}