{
  "type": "Feature",
  "properties": {
    "iso:country":"GB",
    "sg:address":"66 Guernsey Gardens",
    "sg:city":"Wickford",
    "sg:classifiers":[
        {
            "category":"Manufacturing",
            "subcategory":"Signs",
            "type":"Manufacturing & Wholesale Goods"
        }
    ],
    "sg:phone":"+44 1268 734470",
    "sg:postcode":"SS11 7BB",
    "sg:province":"Essex",
    "sg:tags":[
        "maker"
    ],
    "wof:name":"Addsigns",
    "wof:placetype":"venue"
},
  "geometry": {"coordinates":[0.5195180178,51.6200637817],"type":"Point"}
}