{
  "type": "Feature",
  "properties": {
    "iso:country":"GB",
    "sg:address":"12 Monkland Road",
    "sg:city":"Bathgate",
    "sg:classifiers":[
        {
            "category":"Shopping",
            "subcategory":"Department Store",
            "type":"Retail Goods"
        }
    ],
    "sg:phone":"+44 1506 631996",
    "sg:postcode":"EH48 2BQ",
    "sg:province":"West Lothian",
    "wof:name":"Shop & Save",
    "wof:placetype":"venue"
},
  "geometry": {"coordinates":[-3.656703,55.901691],"type":"Point"}
}