{
  "type": "Feature",
  "properties": {
    "iso:country":"GB",
    "sg:address":"Nantwich Road",
    "sg:city":"Crewe",
    "sg:classifiers":[
        {
            "category":"Building & Trades",
            "subcategory":"Plumbing",
            "type":"Services"
        }
    ],
    "sg:postcode":"CW2 6AW",
    "sg:province":"Cheshire",
    "sg:tags":[
        "heating"
    ],
    "wof:name":"M Thomas",
    "wof:placetype":"venue"
},
  "geometry": {"coordinates":[-2.438764,53.088875],"type":"Point"}
}