{
  "type": "Feature",
  "properties": {
    "addr:full":"37a Thames Street Sunbury-on-thames Surrey TW16 5QF",
    "addr:housenumber":"37a",
    "addr:postcode":"tw16 5qf",
    "addr:street":"Thames Street",
    "iso:country":"GB",
    "sg:address":"37a Thames Street",
    "sg:city":"Sunbury-on-thames",
    "sg:classifiers":[
        {
            "category":"Farming",
            "subcategory":"Nursery",
            "type":"Manufacturing & Wholesale Goods"
        }
    ],
    "sg:phone":"+44 1932 779556",
    "sg:postcode":"TW16 5QF",
    "sg:province":"Surrey",
    "sg:tags":[
        "creche"
    ],
    "wof:name":"Pomfrett Cottage Nursery",
    "wof:placetype":"venue"
},
  "geometry": {"coordinates":[-0.4027610123,51.4073295593],"type":"Point"}
}