{
  "type": "Feature",
  "properties": {
    "iso:country":"GB",
    "sg:address":"39 Ladygate",
    "sg:city":"Beverley",
    "sg:classifiers":[
        {
            "category":"Shopping",
            "subcategory":"Department Store",
            "type":"Retail Goods"
        },
        {
            "category":"Shopping",
            "subcategory":"Music",
            "type":"Retail Goods"
        }
    ],
    "sg:phone":"+44 1482 868033",
    "sg:postcode":"HU17 8BH",
    "sg:province":"East Riding of Yorkshire",
    "sg:tags":[
        "record",
        "tape",
        "cd"
    ],
    "wof:name":"Musidisc",
    "wof:placetype":"venue"
},
  "geometry": {"coordinates":[-0.431078,53.842552],"type":"Point"}
}