{
  "type": "Feature",
  "properties": {
    "iso:country":"GB",
    "sg:address":"12 Fortnum Close",
    "sg:city":"Birmingham",
    "sg:classifiers":[
        {
            "category":"Shopping",
            "subcategory":"Clothing, Apparel, & Fashions",
            "type":"Retail Goods"
        },
        {
            "category":"Wholesale",
            "subcategory":"Apparel",
            "type":"Manufacturing & Wholesale Goods"
        }
    ],
    "sg:phone":"+44 121 786 2828",
    "sg:postcode":"B33 0LG",
    "sg:province":"West Midlands",
    "sg:tags":[
        "supplier",
        "clothing"
    ],
    "wof:name":"Douglas & Grahame (U K) Ltd.",
    "wof:placetype":"venue"
},
  "geometry": {"coordinates":[-1.770551,52.4767],"type":"Point"}
}