{
  "type": "Feature",
  "properties": {
    "iso:country":"GB",
    "sg:address":"21 Bdwy",
    "sg:city":"St Ives",
    "sg:classifiers":[
        {
            "category":"Fast Food",
            "type":"Food & Drink"
        }
    ],
    "sg:postcode":"PE27 5BX",
    "sg:province":"Cambridgeshire",
    "sg:tags":[
        "away",
        "take"
    ],
    "wof:name":"Po,Yin Chee,",
    "wof:placetype":"venue"
},
  "geometry": {"coordinates":[-0.0762400031,52.3247489929],"type":"Point"}
}