{
  "type": "Feature",
  "properties": {
    "addr:full":"7 Portswood Place London Greater London SW15 4ED",
    "addr:housenumber":"7",
    "addr:postcode":"sw15 4ed",
    "addr:street":"Portswood Place",
    "iso:country":"GB",
    "sg:address":"7 Portswood Place",
    "sg:city":"London",
    "sg:classifiers":[
        {
            "category":"Shopping",
            "subcategory":"Department Store",
            "type":"Retail Goods"
        }
    ],
    "sg:phone":"+44 20 8876 0968",
    "sg:postcode":"SW15 4ED",
    "sg:province":"Greater London",
    "wof:name":"Kings",
    "wof:placetype":"venue"
},
  "geometry": {"coordinates":[-0.249357,51.451965332],"type":"Point"}
}