{
  "type": "Feature",
  "properties": {
    "addr:full":"103 Upper Halliford Road Shepperton Surrey TW17 8SH",
    "addr:housenumber":"103",
    "addr:postcode":"tw17 8sh",
    "addr:street":"Upper Halliford Road",
    "iso:country":"GB",
    "sg:address":"103 Upper Halliford Road",
    "sg:city":"Shepperton",
    "sg:classifiers":[
        {
            "category":"Real Estate",
            "subcategory":"Developer",
            "type":"Services"
        }
    ],
    "sg:phone":"+44 1932 789526",
    "sg:postcode":"TW17 8SH",
    "sg:province":"Surrey",
    "sg:tags":[
        "property"
    ],
    "wof:name":"Walkthorn Ltd.",
    "wof:placetype":"venue"
},
  "geometry": {"coordinates":[-0.4321289957,51.4058609009],"type":"Point"}
}