{
  "type": "Feature",
  "properties": {
    "iso:country":"GB",
    "sg:address":"26 Hamilton Terr",
    "sg:city":"Milford Haven",
    "sg:classifiers":[
        {
            "category":"Transit Center",
            "subcategory":"Freight",
            "type":"Transportation"
        }
    ],
    "sg:phone":"+44 1646 693667",
    "sg:postcode":"SA73 3JJ",
    "sg:province":"Pembrokeshire",
    "sg:tags":[
        "shop",
        "craft",
        "centre"
    ],
    "wof:name":"Lady Hamilton",
    "wof:placetype":"venue"
},
  "geometry": {"coordinates":[-5.0346741676,51.7123680115],"type":"Point"}
}