{
  "type": "Feature",
  "properties": {
    "addr:full":"28 Longfield Road Leamington Spa Warwickshire CV31 1XB",
    "addr:housenumber":"28",
    "addr:postcode":"cv31 1xb",
    "addr:street":"Longfield Road",
    "iso:country":"GB",
    "sg:address":"28 Longfield Road",
    "sg:city":"Leamington Spa",
    "sg:classifiers":[
        {
            "category":"Professional",
            "subcategory":"Engineering",
            "type":"Services"
        }
    ],
    "sg:postcode":"CV31 1XB",
    "sg:province":"Warwickshire",
    "wof:name":"Warwickshire Machine Tools",
    "wof:placetype":"venue"
},
  "geometry": {"coordinates":[-1.5196690559,52.278968811],"type":"Point"}
}