{
  "type": "Feature",
  "properties": {
    "iso:country":"GB",
    "sg:address":"6 The Green, Idle",
    "sg:city":"Bradford",
    "sg:classifiers":[
        {
            "category":"Restaurant",
            "type":"Food & Drink"
        }
    ],
    "sg:phone":"+44 1274 613518",
    "sg:postcode":"BD10 9RP",
    "sg:province":"West Yorkshire",
    "wof:name":"Khyber Restaurant",
    "wof:placetype":"venue"
},
  "geometry": {"coordinates":[-1.721489,53.836197],"type":"Point"}
}