{
  "type": "Feature",
  "properties": {
    "addr:full":"11 Tunsgate Square Guildford Surrey GU1 3QZ",
    "addr:housenumber":"11",
    "addr:postcode":"gu1 3qz",
    "addr:street":"Tunsgate Square",
    "iso:country":"GB",
    "sg:address":"11 Tunsgate Square",
    "sg:city":"Guildford",
    "sg:classifiers":[
        {
            "category":"Shopping",
            "subcategory":"Clothing, Apparel, & Fashions",
            "type":"Retail Goods"
        }
    ],
    "sg:phone":"+44 1483 565111",
    "sg:postcode":"GU1 3QZ",
    "sg:province":"Surrey",
    "sg:tags":[
        "shop"
    ],
    "wof:name":"Gog Shop",
    "wof:placetype":"venue"
},
  "geometry": {"coordinates":[-0.5716419816,51.2352600098],"type":"Point"}
}