{
  "type": "Feature",
  "properties": {
    "iso:country":"GB",
    "sg:address":"1285 London Road",
    "sg:city":"Derby",
    "sg:classifiers":[
        {
            "category":"Fast Food",
            "type":"Food & Drink"
        }
    ],
    "sg:phone":"+44 1332 752919",
    "sg:postcode":"DE24 8QN",
    "sg:province":"Derbyshire",
    "sg:tags":[
        "away",
        "take"
    ],
    "wof:name":"Amir Kebab & Balti Takeaway",
    "wof:placetype":"venue"
},
  "geometry": {"coordinates":[-1.4298889637,52.8975219727],"type":"Point"}
}