{
  "type": "Feature",
  "properties": {
    "addr:full":"Building 650, R A F Lakenheath Brandon Norfolk IP27 9PN",
    "addr:housenumber":"650",
    "addr:postcode":"ip27 9pn",
    "addr:street":"R A F",
    "iso:country":"GB",
    "sg:address":"Building 650, R A F Lakenheath",
    "sg:city":"Brandon",
    "sg:classifiers":[
        {
            "category":"Shopping",
            "subcategory":"Florist",
            "type":"Retail Goods"
        }
    ],
    "sg:postcode":"IP27 9PN",
    "sg:province":"Norfolk",
    "wof:name":"The Flower Shop",
    "wof:placetype":"venue"
},
  "geometry": {"coordinates":[0.626205,52.442741],"type":"Point"}
}