{
  "type": "Feature",
  "properties": {
    "iso:country":"GB",
    "sg:address":"208 Kingstanding Road",
    "sg:city":"Birmingham",
    "sg:classifiers":[
        {
            "category":"Shopping",
            "subcategory":"Department Store",
            "type":"Retail Goods"
        }
    ],
    "sg:postcode":"B44 8JP",
    "sg:province":"West Midlands",
    "wof:name":"Greenholme Food Stores",
    "wof:placetype":"venue"
},
  "geometry": {"coordinates":[-1.8890670538,52.5364723206],"type":"Point"}
}