{
  "type": "Feature",
  "properties": {
    "addr:full":"57 Market Street Huddersfield West Yorkshire HD3 4HZ",
    "addr:housenumber":"57",
    "addr:postcode":"hd3 4hz",
    "addr:street":"Market Street",
    "iso:country":"GB",
    "sg:address":"57 Market Street",
    "sg:city":"Huddersfield",
    "sg:classifiers":[
        {
            "category":"Food & Beverages",
            "subcategory":"Bakery",
            "type":"Retail Goods"
        }
    ],
    "sg:postcode":"HD3 4HZ",
    "sg:province":"West Yorkshire",
    "sg:tags":[
        "baker"
    ],
    "wof:name":"Parfitt's Bakers",
    "wof:placetype":"venue"
},
  "geometry": {"coordinates":[-1.826774,53.640842],"type":"Point"}
}