{
  "type": "Feature",
  "properties": {
    "iso:country":"GB",
    "sg:address":"349 Hasland Rd, Hasland",
    "sg:city":"Chesterfield",
    "sg:classifiers":[
        {
            "category":"Autos & Motor Vehicles",
            "subcategory":"Automobile Sales",
            "type":"Retail Goods"
        }
    ],
    "sg:phone":"+44 1246 563500",
    "sg:postcode":"S41 0AQ",
    "sg:province":"Derbyshire",
    "sg:tags":[
        "car"
    ],
    "wof:name":"Hasland Road Motor Co",
    "wof:placetype":"venue"
},
  "geometry": {"coordinates":[-1.410723,53.222176],"type":"Point"}
}