{
  "type": "Feature",
  "properties": {
    "addr:full":"Barnham Broom Hotel, Honingham Road, Barnham Broom Norwich Norfolk NR9 4DD",
    "addr:postcode":"nr9 4dd",
    "addr:street":"Barnham;Honingham Road",
    "iso:country":"GB",
    "sg:address":"Barnham Broom Hotel, Honingham Road, Barnham Broom",
    "sg:city":"Norwich",
    "sg:classifiers":[
        {
            "category":"Community Center",
            "type":"Public Place"
        }
    ],
    "sg:phone":"+44 1603 759741",
    "sg:postcode":"NR9 4DD",
    "sg:province":"Norfolk",
    "sg:tags":[
        "recreation",
        "leisure",
        "centre"
    ],
    "wof:name":"The Edge Health & Fitness Club Ltd.",
    "wof:placetype":"venue"
},
  "geometry": {"coordinates":[1.08055,52.624039],"type":"Point"}
}