{
  "type": "Feature",
  "properties": {
    "iso:country":"GB",
    "sg:address":"88 Brynymor Road",
    "sg:city":"Swansea",
    "sg:classifiers":[
        {
            "category":"Food & Beverages",
            "subcategory":"Candy",
            "type":"Retail Goods"
        }
    ],
    "sg:phone":"+44 1792 461612",
    "sg:postcode":"SA1 4JE",
    "sg:province":"Neath Port Talbot",
    "sg:tags":[
        "confectioner"
    ],
    "wof:name":"Sylvia's",
    "wof:placetype":"venue"
},
  "geometry": {"coordinates":[-3.958168,51.616138],"type":"Point"}
}