{
  "type": "Feature",
  "properties": {
    "addr:full":"5-9 All Saints Square Rotherham South Yorkshire S60 1PW",
    "addr:housenumber":"5-9",
    "addr:postcode":"s60 1pw",
    "addr:street":"All Saints Square",
    "iso:country":"GB",
    "sg:address":"5-9 All Saints Square",
    "sg:city":"Rotherham",
    "sg:classifiers":[
        {
            "category":"Shopping",
            "subcategory":"Clothing, Apparel, & Fashions",
            "type":"Retail Goods"
        }
    ],
    "sg:phone":"+44 1709 368678",
    "sg:postcode":"S60 1PW",
    "sg:province":"South Yorkshire",
    "sg:tags":[
        "shop"
    ],
    "wof:name":"Top Shop Top Man",
    "wof:placetype":"venue"
},
  "geometry": {"coordinates":[-1.3542430401,53.4298744202],"type":"Point"}
}