{
  "type": "Feature",
  "properties": {
    "iso:country":"GB",
    "sg:address":"382 Tag Lane, Ingol",
    "sg:city":"Preston",
    "sg:classifiers":[
        {
            "category":"Farming",
            "subcategory":"Nursery",
            "type":"Manufacturing & Wholesale Goods"
        },
        {
            "category":"Education",
            "subcategory":"Preschool",
            "type":"Public Place"
        }
    ],
    "sg:phone":"+44 1772 722764",
    "sg:postcode":"PR2 7AA",
    "sg:province":"Lancashire",
    "sg:tags":[
        "school",
        "creche"
    ],
    "wof:name":"Daisy Chain Day Nursery",
    "wof:placetype":"venue"
},
  "geometry": {"coordinates":[-2.746156,53.786034],"type":"Point"}
}