{
  "type": "Feature",
  "properties": {
    "addr:full":"Masons Arms, Rhydypandy Road, Morriston Swansea Swansea SA6 6PB",
    "addr:postcode":"sa6 6pb",
    "addr:street":"Rhydypandy Road",
    "iso:country":"GB",
    "sg:address":"Masons Arms, Rhydypandy Road, Morriston",
    "sg:city":"Swansea",
    "sg:classifiers":[
        {
            "category":"Bars & Pubs",
            "type":"Food & Drink"
        }
    ],
    "sg:phone":"+44 1792 842535",
    "sg:postcode":"SA6 6PB",
    "sg:province":"Swansea",
    "sg:tags":[
        "pubs",
        "inn"
    ],
    "wof:name":"Masons Arms Ltd.",
    "wof:placetype":"venue"
},
  "geometry": {"coordinates":[-3.92938,51.700665],"type":"Point"}
}