{
  "type": "Feature",
  "properties": {
    "addr:full":"4 Tudor Square, West Bridgford Nottingham Nottinghamshire NG2 6BT",
    "addr:housenumber":"4",
    "addr:postcode":"ng2 6bt",
    "addr:street":"Tudor Square",
    "iso:country":"GB",
    "sg:address":"4 Tudor Square, West Bridgford",
    "sg:city":"Nottingham",
    "sg:classifiers":[
        {
            "category":"Travel",
            "subcategory":"Travel Agent",
            "type":"Entertainment"
        }
    ],
    "sg:phone":"+44 115 981 1844",
    "sg:postcode":"NG2 6BT",
    "sg:province":"Nottinghamshire",
    "wof:name":"Mainline Travel",
    "wof:placetype":"venue"
},
  "geometry": {"coordinates":[-1.1261659861,52.9312820435],"type":"Point"}
}