{
  "type": "Feature",
  "properties": {
    "iso:country":"GB",
    "sg:address":"24 Crown St",
    "sg:city":"Brentwood",
    "sg:classifiers":[
        {
            "category":"Professional",
            "subcategory":"Art Services",
            "type":"Services"
        }
    ],
    "sg:phone":"+44 1277 203070",
    "sg:postcode":"CM14 4BA",
    "sg:province":"Essex",
    "sg:tags":[
        "glass",
        "engraver"
    ],
    "wof:name":"Val Carr",
    "wof:placetype":"venue"
},
  "geometry": {"coordinates":[0.3009180129,51.6192741394],"type":"Point"}
}