{
  "type": "Feature",
  "properties": {
    "addr:full":"8 South Street, Harborne Birmingham West Midlands B17 0DB",
    "addr:housenumber":"8",
    "addr:postcode":"b17 0db",
    "addr:street":"South Street",
    "iso:country":"GB",
    "sg:address":"8 South Street, Harborne",
    "sg:city":"Birmingham",
    "sg:classifiers":[
        {
            "category":"Shopping",
            "subcategory":"Clothing, Apparel, & Fashions",
            "type":"Retail Goods"
        },
        {
            "category":"Banks & Credit Unions",
            "subcategory":"Investment Brokerage",
            "type":"Services"
        }
    ],
    "sg:phone":"+44 121 428 1163",
    "sg:postcode":"B17 0DB",
    "sg:province":"West Midlands",
    "sg:tags":[
        "hire",
        "dresswear"
    ],
    "wof:name":"The Frock Exchange",
    "wof:placetype":"venue"
},
  "geometry": {"coordinates":[-1.948356986,52.4587059021],"type":"Point"}
}