{
  "type": "Feature",
  "properties": {
    "iso:country":"GB",
    "sg:address":"102 London Road",
    "sg:city":"High Wycombe",
    "sg:classifiers":[
        {
            "category":"Shopping",
            "subcategory":"Department Store",
            "type":"Retail Goods"
        },
        {
            "category":"Food & Beverages",
            "subcategory":"Groceries & Convenience Stores",
            "type":"Retail Goods"
        }
    ],
    "sg:phone":"+44 1494 526942",
    "sg:postcode":"HP11 1DB",
    "sg:province":"Buckinghamshire",
    "wof:name":"R K Off Licence",
    "wof:placetype":"venue"
},
  "geometry": {"coordinates":[-0.736067,51.625355],"type":"Point"}
}