{
  "type": "Feature",
  "properties": {
    "iso:country":"GB",
    "sg:address":"2nd Floor 31 York Place",
    "sg:city":"Edinburgh",
    "sg:classifiers":[
        {
            "category":"Organizations",
            "subcategory":"Non-profit Organization",
            "type":"Services"
        }
    ],
    "sg:phone":"+44 131 557 3332",
    "sg:postcode":"EH1 3HP",
    "sg:province":"City of Edinburgh",
    "sg:tags":[
        "organisation",
        "voluntary",
        "charity"
    ],
    "wof:name":"The International Myeloma Foundation (Uk)",
    "wof:placetype":"venue"
},
  "geometry": {"coordinates":[-3.1899309158,55.956237793],"type":"Point"}
}