{
  "type": "Feature",
  "properties": {
    "addr:full":"Dental Surgery, 85 Parrys Lane Bristol City of Bristol BS9 1AN",
    "addr:housenumber":"85",
    "addr:postcode":"bs9 1an",
    "addr:street":"Parrys Lane",
    "iso:country":"GB",
    "sg:address":"Dental Surgery, 85 Parrys Lane",
    "sg:city":"Bristol",
    "sg:classifiers":[
        {
            "category":"Health Services",
            "subcategory":"Dentist",
            "type":"Services"
        }
    ],
    "sg:phone":"+44 117 968 5048",
    "sg:postcode":"BS9 1AN",
    "sg:province":"City of Bristol",
    "wof:name":"Parrys Lane Dental Surgery",
    "wof:placetype":"venue"
},
  "geometry": {"coordinates":[-2.629420042,51.4841918945],"type":"Point"}
}