{
  "type": "Feature",
  "properties": {
    "addr:full":"Off Duke Street Larkhall South Lanarkshire ML9 2UJ",
    "addr:postcode":"ml9 2uj",
    "addr:street":"Duke Street",
    "iso:country":"GB",
    "sg:address":"Off Duke Street",
    "sg:city":"Larkhall",
    "sg:classifiers":[
        {
            "category":"Home & Garden",
            "subcategory":"Garden Supply",
            "type":"Retail Goods"
        }
    ],
    "sg:phone":"+44 1698 884511",
    "sg:postcode":"ML9 2UJ",
    "sg:province":"South Lanarkshire",
    "sg:tags":[
        "nursery",
        "centre"
    ],
    "wof:name":"Tile Cottage Nursery",
    "wof:placetype":"venue"
},
  "geometry": {"coordinates":[-3.969734,55.746029],"type":"Point"}
}