{
  "type": "Feature",
  "properties": {
    "addr:full":"57-61 Carolgate Retford Nottinghamshire DN22 6BZ",
    "addr:housenumber":"57-61",
    "addr:postcode":"dn22 6bz",
    "addr:street":"Carolgate Retford",
    "iso:country":"GB",
    "sg:address":"57-61 Carolgate",
    "sg:city":"Retford",
    "sg:classifiers":[
        {
            "category":"Home & Garden",
            "subcategory":"Hardware",
            "type":"Retail Goods"
        }
    ],
    "sg:phone":"+44 1777 705856",
    "sg:postcode":"DN22 6BZ",
    "sg:province":"Nottinghamshire",
    "sg:tags":[
        "retailer",
        "diy"
    ],
    "wof:name":"Wilkinson Hardware Stores",
    "wof:placetype":"venue"
},
  "geometry": {"coordinates":[-0.9416850209,53.3206558228],"type":"Point"}
}