{
  "type": "Feature",
  "properties": {
    "addr:full":"Winter Park, Rykneld Road, Littleover Derby Derbyshire DE23 7RJ",
    "addr:postcode":"de23 7rj",
    "addr:street":"Rykneld Road",
    "iso:country":"GB",
    "sg:address":"Winter Park, Rykneld Road, Littleover",
    "sg:city":"Derby",
    "sg:classifiers":[
        {
            "category":"Building & Trades",
            "subcategory":"Construction",
            "type":"Services"
        }
    ],
    "sg:phone":"+44 1332 521382",
    "sg:postcode":"DE23 7RJ",
    "sg:province":"Derbyshire",
    "sg:tags":[
        "builder"
    ],
    "wof:name":"David Wilson Homes (Nottingham)",
    "wof:placetype":"venue"
},
  "geometry": {"coordinates":[-1.52224,52.9011],"type":"Point"}
}