{
  "type": "Feature",
  "properties": {
    "addr:full":"2 St James Place Ilfracombe Devon EX34 9BH",
    "addr:housenumber":"2",
    "addr:postcode":"ex34 9bh",
    "addr:street":"St James Place",
    "iso:country":"GB",
    "sg:address":"2 St James Place",
    "sg:city":"Ilfracombe",
    "sg:classifiers":[
        {
            "category":"Restaurant",
            "type":"Food & Drink"
        }
    ],
    "sg:phone":"+44 1271 862281",
    "sg:postcode":"EX34 9BH",
    "sg:province":"Devon",
    "wof:name":"Golden Bay Restaurant Holiday Flats",
    "wof:placetype":"venue"
},
  "geometry": {"coordinates":[-4.118646,51.210705],"type":"Point"}
}