{
  "type": "Feature",
  "properties": {
    "addr:full":"73-75 Cumbrian Way, Millbrook Southampton Hampshire SO16 4AT",
    "addr:housenumber":"73-75",
    "addr:postcode":"so16 4at",
    "addr:street":"Cumbrian Way",
    "iso:country":"GB",
    "sg:address":"73-75 Cumbrian Way, Millbrook",
    "sg:city":"Southampton",
    "sg:classifiers":[
        {
            "category":"Cinema",
            "subcategory":"Movie Rental",
            "type":"Entertainment"
        }
    ],
    "sg:phone":"+44 23 8078 7735",
    "sg:postcode":"SO16 4AT",
    "sg:province":"Hampshire",
    "sg:tags":[
        "video",
        "library"
    ],
    "wof:name":"Millbrook Video",
    "wof:placetype":"venue"
},
  "geometry": {"coordinates":[-1.452211,50.92173],"type":"Point"}
}