{
  "type": "Feature",
  "properties": {
    "iso:country":"GB",
    "sg:address":"Maes-y-welon",
    "sg:city":"Caersws",
    "sg:classifiers":[
        {
            "category":"Education",
            "subcategory":"School",
            "type":"Public Place"
        }
    ],
    "sg:phone":"+44 1686 688458",
    "sg:postcode":"SY17 5HG",
    "sg:province":"Powys",
    "sg:tags":[
        "local",
        "authority"
    ],
    "wof:name":"Caersws Community Primary School",
    "wof:placetype":"venue"
},
  "geometry": {"coordinates":[-3.430329,52.516735],"type":"Point"}
}