{
  "type": "Feature",
  "properties": {
    "addr:full":"112 Main Road Emsworth Hampshire PO10 8AY",
    "addr:housenumber":"112",
    "addr:postcode":"po10 8ay",
    "addr:street":"Main Road",
    "iso:country":"GB",
    "sg:address":"112 Main Road",
    "sg:city":"Emsworth",
    "sg:classifiers":[
        {
            "category":"Home & Garden",
            "subcategory":"Garden Supply",
            "type":"Retail Goods"
        }
    ],
    "sg:postcode":"PO10 8AY",
    "sg:province":"Hampshire",
    "sg:tags":[
        "nursery",
        "centre"
    ],
    "wof:name":"Barry's Blooming Baskets",
    "wof:placetype":"venue"
},
  "geometry": {"coordinates":[-0.9233360291,50.8459243774],"type":"Point"}
}