{
  "type": "Feature",
  "properties": {
    "addr:full":"Summerfield Road Bradford West Yorkshire BD10 8DT",
    "addr:postcode":"bd10 8dt",
    "addr:street":"Summerfield Road",
    "iso:country":"GB",
    "sg:address":"Summerfield Road",
    "sg:city":"Bradford",
    "sg:classifiers":[
        {
            "category":"Home & Garden",
            "subcategory":"Furniture",
            "type":"Retail Goods"
        }
    ],
    "sg:phone":"+44 1274 774977",
    "sg:postcode":"BD10 8DT",
    "sg:province":"West Yorkshire",
    "wof:name":"Thorpe Edge Furniture Service",
    "wof:placetype":"venue"
},
  "geometry": {"coordinates":[-1.7251269817,53.8276939392],"type":"Point"}
}