{
  "type": "Feature",
  "properties": {
    "iso:country":"GB",
    "sg:address":"23 Parmenter Drive, Great Cornard",
    "sg:city":"Sudbury",
    "sg:classifiers":[
        {
            "category":"Shopping",
            "subcategory":"Computers & Home Electronics",
            "type":"Retail Goods"
        }
    ],
    "sg:phone":"+44 1787 377772",
    "sg:postcode":"CO10 0YS",
    "sg:province":"Essex",
    "sg:tags":[
        "aerial",
        "television",
        "radio"
    ],
    "wof:name":"Brown Tv Aerial & Satellite Services",
    "wof:placetype":"venue"
},
  "geometry": {"coordinates":[0.759587,52.027592],"type":"Point"}
}