{
  "type": "Feature",
  "properties": {
    "addr:full":"Farleigh, Woodland Way Tadworth Surrey KT20 6NN",
    "addr:housenumber":"farleigh",
    "addr:postcode":"kt20 6nn",
    "addr:street":"Woodland Way",
    "iso:country":"GB",
    "sg:address":"Farleigh, Woodland Way",
    "sg:city":"Tadworth",
    "sg:classifiers":[
        {
            "category":"Professional",
            "type":"Services"
        }
    ],
    "sg:phone":"+44 1737 832614",
    "sg:postcode":"KT20 6NN",
    "sg:province":"Surrey",
    "sg:tags":[
        "repair",
        "tech",
        "maintenance"
    ],
    "wof:name":"Ink Jet Image Ltd.",
    "wof:placetype":"venue"
},
  "geometry": {"coordinates":[-0.2119690031,51.2937278748],"type":"Point"}
}