{
  "type": "Feature",
  "properties": {
    "addr:full":"9 Bridge Avenue Maidenhead Berkshire SL6 1RR",
    "addr:housenumber":"9",
    "addr:postcode":"sl6 1rr",
    "addr:street":"Bridge Avenue",
    "iso:country":"GB",
    "sg:address":"9 Bridge Avenue",
    "sg:city":"Maidenhead",
    "sg:classifiers":[
        {
            "category":"Professional",
            "subcategory":"Business Services",
            "type":"Services"
        }
    ],
    "sg:phone":"+44 1628 624290",
    "sg:postcode":"SL6 1RR",
    "sg:province":"Berkshire",
    "sg:tags":[
        "shop",
        "cleaning"
    ],
    "wof:name":"At Your Service Cleaning Contractors Ltd.",
    "wof:placetype":"venue"
},
  "geometry": {"coordinates":[-0.71602,51.521767],"type":"Point"}
}