{
  "type": "Feature",
  "properties": {
    "addr:full":"Phoenix Court, Bartholomew Street Newbury Berkshire RG14 5QA",
    "addr:postcode":"rg14 5qa",
    "addr:street":"Phoenix Court Bartholomew Street",
    "iso:country":"GB",
    "sg:address":"Phoenix Court, Bartholomew Street",
    "sg:city":"Newbury",
    "sg:classifiers":[
        {
            "category":"Professional",
            "subcategory":"Business Services",
            "type":"Services"
        }
    ],
    "sg:postcode":"RG14 5QA",
    "sg:province":"Berkshire",
    "sg:tags":[
        "holding"
    ],
    "wof:name":"Ilsley Holdings Ltd.",
    "wof:placetype":"venue"
},
  "geometry": {"coordinates":[-1.3256440163,51.3992881775],"type":"Point"}
}