{
  "type": "Feature",
  "properties": {
    "addr:full":"321 Bromford Lane, Ward End Birmingham West Midlands B8 2SH",
    "addr:housenumber":"321",
    "addr:postcode":"b8 2sh",
    "addr:street":"Bromford Lane",
    "iso:country":"GB",
    "sg:address":"321 Bromford Lane, Ward End",
    "sg:city":"Birmingham",
    "sg:classifiers":[
        {
            "category":"Autos & Motor Vehicles",
            "subcategory":"Motorcycle Sales",
            "type":"Retail Goods"
        }
    ],
    "sg:postcode":"B8 2SH",
    "sg:province":"West Midlands",
    "wof:name":"Ideal Garages",
    "wof:placetype":"venue"
},
  "geometry": {"coordinates":[-1.8299160004,52.5021820068],"type":"Point"}
}