{
  "type": "Feature",
  "properties": {
    "iso:country":"GB",
    "sg:address":"West St",
    "sg:city":"Beverley",
    "sg:classifiers":[
        {
            "category":"Home & Garden",
            "subcategory":"Home Furnishings",
            "type":"Retail Goods"
        }
    ],
    "sg:phone":"+44 1482 861637",
    "sg:postcode":"HU17 0JH",
    "sg:province":"East Riding of Yorkshire",
    "sg:tags":[
        "mantelpiece",
        "fireplace"
    ],
    "wof:name":"Christine Moore Ornate Castings",
    "wof:placetype":"venue"
},
  "geometry": {"coordinates":[-0.405148,53.843548],"type":"Point"}
}