{
  "type": "Feature",
  "properties": {
    "addr:full":"12 The High St Newport Pagnell Buckinghamshire MK16 8AR",
    "addr:housenumber":"12",
    "addr:postcode":"mk16 8ar",
    "addr:street":"The High St",
    "iso:country":"GB",
    "sg:address":"12 The High St",
    "sg:city":"Newport Pagnell",
    "sg:classifiers":[
        {
            "category":"Professional",
            "subcategory":"Printing & Photocopies",
            "type":"Services"
        }
    ],
    "sg:postcode":"MK16 8AR",
    "sg:province":"Buckinghamshire",
    "sg:tags":[
        "printer"
    ],
    "wof:name":"Pumpkin",
    "wof:placetype":"venue"
},
  "geometry": {"coordinates":[-0.720594,52.087582],"type":"Point"}
}