{
  "type": "Feature",
  "properties": {
    "addr:full":"39/41 Boutport Street Barnstaple Devon EX31 1SA",
    "addr:housenumber":"39 / 41",
    "addr:postcode":"ex31 1sa",
    "addr:street":"Boutport Street",
    "iso:country":"GB",
    "sg:address":"39/41 Boutport Street",
    "sg:city":"Barnstaple",
    "sg:classifiers":[
        {
            "category":"Real Estate",
            "subcategory":"Real Estate Agent",
            "type":"Services"
        }
    ],
    "sg:phone":"+44 1271 373404",
    "sg:postcode":"EX31 1SA",
    "sg:province":"Devon",
    "wof:name":"Webbers Estate Agents Ltd.",
    "wof:placetype":"venue"
},
  "geometry": {"coordinates":[-4.06106,51.082912],"type":"Point"}
}