{
  "type": "Feature",
  "properties": {
    "addr:full":"The Haven, Yew Tree Lane, Caerleon Newport Monmouthshire NP18 1LL",
    "addr:postcode":"np18 1ll",
    "addr:street":"Yew Tree Lane",
    "iso:country":"GB",
    "sg:address":"The Haven, Yew Tree Lane, Caerleon",
    "sg:city":"Newport",
    "sg:classifiers":[
        {
            "category":"Retail",
            "subcategory":"Driving School",
            "type":"Services"
        }
    ],
    "sg:postcode":"NP18 1LL",
    "sg:province":"Monmouthshire",
    "wof:name":"Martin's School of Motoring",
    "wof:placetype":"venue"
},
  "geometry": {"coordinates":[-2.9556999207,51.6150283813],"type":"Point"}
}