{
  "type": "Feature",
  "properties": {
    "addr:full":"Flat 61 Enfield Cloisters, Fanshaw Street Islington Greater London N1 6LD",
    "addr:housenumber":"flat 61",
    "addr:postcode":"n1 6ld",
    "addr:street":"Fanshaw Street",
    "iso:country":"GB",
    "sg:address":"Flat 61 Enfield Cloisters, Fanshaw Street",
    "sg:city":"Islington",
    "sg:classifiers":[
        {
            "category":"Education",
            "subcategory":"School",
            "type":"Public Place"
        }
    ],
    "sg:postcode":"N1 6LD",
    "sg:province":"Greater London",
    "sg:tags":[
        "local",
        "authority"
    ],
    "wof:name":"Eurotemp Educational Ltd",
    "wof:placetype":"venue"
},
  "geometry": {"coordinates":[-0.0807899982,51.5291290283],"type":"Point"}
}