{
  "type": "Feature",
  "properties": {
    "iso:country":"GB",
    "sg:address":"3 The Street, Little Chart",
    "sg:city":"Ashford",
    "sg:classifiers":[
        {
            "category":"Organizations",
            "subcategory":"Non-profit Organization",
            "type":"Services"
        }
    ],
    "sg:postcode":"TN27 0QD",
    "sg:province":"Kent",
    "sg:tags":[
        "organisation",
        "voluntary",
        "charity"
    ],
    "wof:name":"Crossroads Ltd",
    "wof:placetype":"venue"
},
  "geometry": {"coordinates":[0.756165,51.177116],"type":"Point"}
}