{
  "type": "Feature",
  "properties": {
    "addr:full":"St Matthews Vicarage, Stowell St Bolton Lancashire BL1 3RQ",
    "addr:postcode":"bl1 3rq",
    "addr:street":"Stowell St",
    "iso:country":"GB",
    "sg:address":"St Matthews Vicarage, Stowell St",
    "sg:city":"Bolton",
    "sg:classifiers":[
        {
            "category":"Place Of Worship",
            "type":"Public Place"
        }
    ],
    "sg:phone":"+44 1204 522810",
    "sg:postcode":"BL1 3RQ",
    "sg:province":"Lancashire",
    "wof:name":"St Matthews",
    "wof:placetype":"venue"
},
  "geometry": {"coordinates":[-2.4388790131,53.5884094238],"type":"Point"}
}