{
  "type": "Feature",
  "properties": {
    "addr:full":"35 Windermere Rd Lancaster Lancashire LA1 3EX",
    "addr:housenumber":"35",
    "addr:postcode":"la1 3ex",
    "addr:street":"Windermere Rd",
    "iso:country":"GB",
    "sg:address":"35 Windermere Rd",
    "sg:city":"Lancaster",
    "sg:classifiers":[
        {
            "category":"Professional",
            "subcategory":"Employment Agencies",
            "type":"Services"
        }
    ],
    "sg:phone":"+44 1524 841554",
    "sg:postcode":"LA1 3EX",
    "sg:province":"Lancashire",
    "sg:tags":[
        "agricultural",
        "advice"
    ],
    "wof:name":"J H Coates",
    "wof:placetype":"venue"
},
  "geometry": {"coordinates":[-2.787412,54.050117],"type":"Point"}
}