{
  "type": "Feature",
  "properties": {
    "addr:full":"Abbey Road, Whitley Coventry Warwickshire CV3 4BJ",
    "addr:postcode":"cv3 4bj",
    "addr:street":"Abbey Road",
    "iso:country":"GB",
    "sg:address":"Abbey Road, Whitley",
    "sg:city":"Coventry",
    "sg:classifiers":[
        {
            "category":"Arena",
            "subcategory":"Sports Club",
            "type":"Entertainment"
        }
    ],
    "sg:phone":"+44 24 7630 6650",
    "sg:postcode":"CV3 4BJ",
    "sg:province":"Warwickshire",
    "wof:name":"Warwickshire Racquets & Health Club Ltd.",
    "wof:placetype":"venue"
},
  "geometry": {"coordinates":[-1.4831639528,52.3870010376],"type":"Point"}
}