{
  "type": "Feature",
  "properties": {
    "addr:full":"17 Abbeygate Street Bury St Edmunds Suffolk IP33 1UN",
    "addr:housenumber":"17",
    "addr:postcode":"ip33 1un",
    "addr:street":"Abbeygate Street",
    "iso:country":"GB",
    "sg:address":"17 Abbeygate Street",
    "sg:city":"Bury St Edmunds",
    "sg:classifiers":[
        {
            "category":"Shopping",
            "subcategory":"Department Store",
            "type":"Retail Goods"
        },
        {
            "category":"Shopping",
            "subcategory":"Gifts & Souvenirs",
            "type":"Retail Goods"
        }
    ],
    "sg:phone":"+44 1284 760289",
    "sg:postcode":"IP33 1UN",
    "sg:province":"Suffolk",
    "sg:tags":[
        "shop"
    ],
    "wof:name":"The Parsley Pot",
    "wof:placetype":"venue"
},
  "geometry": {"coordinates":[0.714212,52.244881],"type":"Point"}
}