{
  "type": "Feature",
  "properties": {
    "addr:full":"Crowtree Lane Louth Lincolnshire LN11 9LL",
    "addr:postcode":"ln11 9ll",
    "addr:street":"Crowtree Lane Louth",
    "iso:country":"GB",
    "sg:address":"Crowtree Lane",
    "sg:city":"Louth",
    "sg:classifiers":[
        {
            "category":"Social Services",
            "subcategory":"Retirement Home",
            "type":"Services"
        },
        {
            "category":"Government",
            "subcategory":"Office",
            "type":"Public Place"
        }
    ],
    "sg:phone":"+44 1507 602653",
    "sg:postcode":"LN11 9LL",
    "sg:province":"Lincolnshire",
    "sg:tags":[
        "local",
        "rest"
    ],
    "wof:name":"Crowtree House Home for the Elderly",
    "wof:placetype":"venue"
},
  "geometry": {"coordinates":[-0.0107399998,53.3645896912],"type":"Point"}
}