{
  "type": "Feature",
  "properties": {
    "addr:full":"10 Grange Loan Edinburgh City of Edinburgh EH9 2NR",
    "addr:housenumber":"10",
    "addr:postcode":"eh9 2nr",
    "addr:street":"Grange Loan",
    "iso:country":"GB",
    "sg:address":"10 Grange Loan",
    "sg:city":"Edinburgh",
    "sg:classifiers":[
        {
            "category":"Cafe",
            "type":"Food & Drink"
        }
    ],
    "sg:phone":"+44 131 662 9522",
    "sg:postcode":"EH9 2NR",
    "sg:province":"City of Edinburgh",
    "sg:tags":[
        "tea",
        "room"
    ],
    "wof:name":"The Chinese Cafe",
    "wof:placetype":"venue"
},
  "geometry": {"coordinates":[-3.178927,55.934113],"type":"Point"}
}