{
  "type": "Feature",
  "properties": {
    "iso:country":"GB",
    "sg:address":"2 Walton Road",
    "sg:city":"Aylesbury",
    "sg:classifiers":[
        {
            "category":"Banks & Credit Unions",
            "subcategory":"Bank",
            "type":"Services"
        }
    ],
    "sg:phone":"+44 845 740 4404",
    "sg:postcode":"HP21 7SR",
    "sg:province":"Buckinghamshire",
    "wof:name":"H S B C Bank",
    "wof:placetype":"venue"
},
  "geometry": {"coordinates":[-0.792669,51.814888],"type":"Point"}
}