{
  "type": "Feature",
  "properties": {
    "addr:full":"3 Foxenden Rd Guildford Surrey GU1 4DL",
    "addr:housenumber":"3",
    "addr:postcode":"gu1 4dl",
    "addr:street":"Foxenden Rd",
    "iso:country":"GB",
    "sg:address":"3 Foxenden Rd",
    "sg:city":"Guildford",
    "sg:classifiers":[
        {
            "category":"Professional",
            "subcategory":"Printing & Photocopies",
            "type":"Services"
        }
    ],
    "sg:phone":"+44 1483 419359",
    "sg:postcode":"GU1 4DL",
    "sg:province":"Surrey",
    "sg:tags":[
        "top",
        "publishing",
        "desk"
    ],
    "wof:name":"Dodson Granville",
    "wof:placetype":"venue"
},
  "geometry": {"coordinates":[-0.567957,51.240063],"type":"Point"}
}