{
  "type": "Feature",
  "properties": {
    "iso:country":"GB",
    "sg:address":"Unit 6, Montford Enterprise Centre, Wynford Square",
    "sg:city":"Salford",
    "sg:classifiers":[
        {
            "category":"Building & Trades",
            "subcategory":"Cleaning & Sanitation",
            "type":"Services"
        }
    ],
    "sg:phone":"+44 161 743 9810",
    "sg:postcode":"M50 2PL",
    "sg:province":"Greater Manchester",
    "sg:tags":[
        "commercial"
    ],
    "wof:name":"Mitie Cleaning (North) Ltd.",
    "wof:placetype":"venue"
},
  "geometry": {"coordinates":[-2.29203,53.47884],"type":"Point"}
}