{
  "type": "Feature",
  "properties": {
    "addr:full":"Fordybrook Farm, Ford Lane Wantage Berkshire OX12 8JX",
    "addr:postcode":"ox12 8jx",
    "addr:street":"Ford Lane",
    "iso:country":"GB",
    "sg:address":"Fordybrook Farm, Ford Lane",
    "sg:city":"Wantage",
    "sg:classifiers":[
        {
            "category":"Farming",
            "subcategory":"Farm",
            "type":"Manufacturing & Wholesale Goods"
        }
    ],
    "sg:postcode":"OX12 8JX",
    "sg:province":"Berkshire",
    "sg:tags":[
        "egg",
        "producer"
    ],
    "wof:name":"Jm & Rj Bushnell",
    "wof:placetype":"venue"
},
  "geometry": {"coordinates":[-1.4236390591,51.5917472839],"type":"Point"}
}