{
  "type": "Feature",
  "properties": {
    "addr:full":"39 Beach Road Ilfracombe Devon EX34 9QZ",
    "addr:housenumber":"39",
    "addr:postcode":"ex34 9qz",
    "addr:street":"Beach Road",
    "iso:country":"GB",
    "sg:address":"39 Beach Road",
    "sg:city":"Ilfracombe",
    "sg:classifiers":[
        {
            "category":"Bars & Pubs",
            "type":"Food & Drink"
        }
    ],
    "sg:phone":"+44 1271 867795",
    "sg:postcode":"EX34 9QZ",
    "sg:province":"Devon",
    "sg:tags":[
        "pubs",
        "inn"
    ],
    "wof:name":"Hele Bay Hotel",
    "wof:placetype":"venue"
},
  "geometry": {"coordinates":[-4.098154068,51.2092056274],"type":"Point"}
}