{
  "type": "Feature",
  "properties": {
    "addr:full":"38 The Embankment Bedford Bedfordshire MK40 3PF",
    "addr:housenumber":"38",
    "addr:postcode":"mk40 3pf",
    "addr:street":"The Embankment",
    "iso:country":"GB",
    "sg:address":"38 The Embankment",
    "sg:city":"Bedford",
    "sg:classifiers":[
        {
            "category":"Restaurant",
            "type":"Food & Drink"
        }
    ],
    "sg:phone":"+44 1525 290622",
    "sg:postcode":"MK40 3PF",
    "sg:province":"Bedfordshire",
    "wof:name":"Nicholl's Brasseries Ltd.",
    "wof:placetype":"venue"
},
  "geometry": {"coordinates":[-0.4516519904,52.1340675354],"type":"Point"}
}