{
  "type": "Feature",
  "properties": {
    "addr:full":"38 Dock Street Dundee Dundee City DD1 3DG",
    "addr:housenumber":"38",
    "addr:postcode":"dd1 3dg",
    "addr:street":"Dock Street",
    "iso:country":"GB",
    "sg:address":"38 Dock Street",
    "sg:city":"Dundee",
    "sg:classifiers":[
        {
            "category":"Personal",
            "subcategory":"Beauty Salon",
            "type":"Services"
        }
    ],
    "sg:phone":"+44 1382 877020",
    "sg:postcode":"DD1 3DG",
    "sg:province":"Dundee City",
    "sg:tags":[
        "unisex",
        "hairdresser"
    ],
    "wof:name":"Karen Smith Hair Studio",
    "wof:placetype":"venue"
},
  "geometry": {"coordinates":[-2.966195,56.460835],"type":"Point"}
}