{
  "type": "Feature",
  "properties": {
    "addr:full":"1 Long Drive Ruislip Greater London HA4 0HG",
    "addr:housenumber":"1",
    "addr:postcode":"ha4 0hg",
    "addr:street":"Long Drive",
    "iso:country":"GB",
    "sg:address":"1 Long Drive",
    "sg:city":"Ruislip",
    "sg:classifiers":[
        {
            "category":"Banks & Credit Unions",
            "subcategory":"Financial Services",
            "type":"Services"
        }
    ],
    "sg:phone":"+44 20 8845 8025",
    "sg:postcode":"HA4 0HG",
    "sg:province":"Greater London",
    "sg:tags":[
        "cashing",
        "cheque"
    ],
    "wof:name":"Chequecashing",
    "wof:placetype":"venue"
},
  "geometry": {"coordinates":[-0.398563,51.556599],"type":"Point"}
}