{
  "type": "Feature",
  "properties": {
    "addr:full":"285 City Road London Greater London EC1V 1LA",
    "addr:housenumber":"285",
    "addr:postcode":"ec1v 1la",
    "addr:street":"City Road",
    "iso:country":"GB",
    "sg:address":"285 City Road",
    "sg:city":"London",
    "sg:classifiers":[
        {
            "category":"Fast Food",
            "type":"Food & Drink"
        }
    ],
    "sg:phone":"+44 20 7250 1600",
    "sg:postcode":"EC1V 1LA",
    "sg:province":"Greater London",
    "sg:tags":[
        "away",
        "take"
    ],
    "wof:name":"China E  Caterers Ltd.",
    "wof:placetype":"venue"
},
  "geometry": {"coordinates":[-0.088079,51.526711],"type":"Point"}
}