{
  "type": "Feature",
  "properties": {
    "addr:full":"18 High Street, Bidford-on-avon Alcester Warwickshire B50 4BU",
    "addr:housenumber":"18",
    "addr:postcode":"b50 4bu",
    "addr:street":"High Street",
    "iso:country":"GB",
    "sg:address":"18 High Street, Bidford-on-avon",
    "sg:city":"Alcester",
    "sg:classifiers":[
        {
            "category":"Professional",
            "subcategory":"Lawyer & Legal Services",
            "type":"Services"
        }
    ],
    "sg:phone":"+44 1789 772955",
    "sg:postcode":"B50 4BU",
    "sg:province":"Warwickshire",
    "sg:tags":[
        "solicitor"
    ],
    "wof:name":"HALL REYNOLDS",
    "wof:placetype":"venue"
},
  "geometry": {"coordinates":[-1.853939,52.165672],"type":"Point"}
}