{
  "type": "Feature",
  "properties": {
    "iso:country":"GB",
    "sg:address":"Constituency Of Salford, Unit 4 Albion Pl",
    "sg:city":"Salford",
    "sg:classifiers":[
        {
            "category":"Government",
            "subcategory":"Office",
            "type":"Public Place"
        }
    ],
    "sg:phone":"+44 161 925 0705",
    "sg:postcode":"M5 4NL",
    "sg:province":"Greater Manchester",
    "sg:tags":[
        "mp",
        "meps"
    ],
    "wof:name":"Hazel Blears MP (Lab)",
    "wof:placetype":"venue"
},
  "geometry": {"coordinates":[-2.2724,53.483631],"type":"Point"}
}