{
  "type": "Feature",
  "properties": {
    "addr:full":"58 Turnpike Rossendale Lancashire BB4 9DU",
    "addr:housenumber":"58",
    "addr:postcode":"bb4 9du",
    "addr:street":"Turnpike",
    "iso:country":"GB",
    "sg:address":"58 Turnpike",
    "sg:city":"Rossendale",
    "sg:classifiers":[
        {
            "category":"Building & Trades",
            "subcategory":"Construction",
            "type":"Services"
        }
    ],
    "sg:phone":"+44 1706 830518",
    "sg:postcode":"BB4 9DU",
    "sg:province":"Lancashire",
    "sg:tags":[
        "builder"
    ],
    "wof:name":"B & M Holt & Sons",
    "wof:placetype":"venue"
},
  "geometry": {"coordinates":[-2.2490820885,53.6965522766],"type":"Point"}
}