{
  "type": "Feature",
  "properties": {
    "iso:country":"GB",
    "sg:address":"31 Beechways, Appleton",
    "sg:city":"Warrington",
    "sg:classifiers":[
        {
            "category":"Shopping",
            "subcategory":"Party Supplies",
            "type":"Retail Goods"
        }
    ],
    "sg:phone":"+44 1925 861622",
    "sg:postcode":"WA4 5ER",
    "sg:province":"Cheshire",
    "sg:tags":[
        "inflatables",
        "bouncy",
        "castle"
    ],
    "wof:name":"I Clare",
    "wof:placetype":"venue"
},
  "geometry": {"coordinates":[-2.570339,53.352718],"type":"Point"}
}