{
  "type": "Feature",
  "properties": {
    "addr:full":"117-119 High Street, Hadleigh Ipswich Suffolk IP7 5EJ",
    "addr:housenumber":"117-119",
    "addr:postcode":"ip7 5ej",
    "addr:street":"High Street",
    "iso:country":"GB",
    "sg:address":"117-119 High Street, Hadleigh",
    "sg:city":"Ipswich",
    "sg:classifiers":[
        {
            "category":"Restaurant",
            "type":"Food & Drink"
        }
    ],
    "sg:postcode":"IP7 5EJ",
    "sg:province":"Suffolk",
    "wof:name":"THE SPINNING WHEEL RESTAURANT",
    "wof:placetype":"venue"
},
  "geometry": {"coordinates":[0.9517580271,52.0460777283],"type":"Point"}
}