{
  "type": "Feature",
  "properties": {
    "addr:full":"Queensland Rd Holloway Greater London N7 7AH",
    "addr:postcode":"n7 7ah",
    "addr:street":"Queensland Rd",
    "iso:country":"GB",
    "sg:address":"Queensland Rd",
    "sg:city":"Holloway",
    "sg:classifiers":[
        {
            "category":"Wholesale",
            "subcategory":"Scrap",
            "type":"Manufacturing & Wholesale Goods"
        }
    ],
    "sg:phone":"+44 20 7477 4679",
    "sg:postcode":"N7 7AH",
    "sg:province":"Greater London",
    "sg:tags":[
        "waste",
        "metal"
    ],
    "wof:name":"Islington Recycling Centre",
    "wof:placetype":"venue"
},
  "geometry": {"coordinates":[-0.109312,51.553612],"type":"Point"}
}