{
  "type": "Feature",
  "properties": {
    "addr:full":"Unit 5a, Ewenny Indstl Est Bridgend Bridgend CF31 3EX",
    "addr:housenumber":"unit 5a",
    "addr:postcode":"cf31 3ex",
    "addr:street":"Indstl Est",
    "iso:country":"GB",
    "sg:address":"Unit 5a, Ewenny Indstl Est",
    "sg:city":"Bridgend",
    "sg:classifiers":[
        {
            "category":"Professional",
            "subcategory":"Business Services",
            "type":"Services"
        }
    ],
    "sg:postcode":"CF31 3EX",
    "sg:province":"Bridgend",
    "sg:tags":[
        "import",
        "export",
        "agent"
    ],
    "wof:name":"Gap European Ltd",
    "wof:placetype":"venue"
},
  "geometry": {"coordinates":[-3.5763440132,51.5019111633],"type":"Point"}
}