{
  "type": "Feature",
  "properties": {
    "iso:country":"GB",
    "sg:address":"40c Muswell Avenue",
    "sg:city":"London",
    "sg:classifiers":[
        {
            "category":"Retail",
            "subcategory":"Driving School",
            "type":"Services"
        }
    ],
    "sg:postcode":"N10 2EG",
    "sg:province":"Greater London",
    "wof:name":"Monarch School of Motoring",
    "wof:placetype":"venue"
},
  "geometry": {"coordinates":[-0.143434003,51.5961036682],"type":"Point"}
}