{
  "type": "Feature",
  "properties": {
    "addr:full":"Boathouse Lane Stockton-on-tees Durham TS18 3AT",
    "addr:postcode":"ts18 3at",
    "addr:street":"Boathouse Lane",
    "iso:country":"GB",
    "sg:address":"Boathouse Lane",
    "sg:city":"Stockton-on-tees",
    "sg:classifiers":[
        {
            "category":"Wholesale",
            "subcategory":"Machinery & Supplies",
            "type":"Manufacturing & Wholesale Goods"
        }
    ],
    "sg:phone":"+44 1642 675696",
    "sg:postcode":"TS18 3AT",
    "sg:province":"Durham",
    "sg:tags":[
        "pump"
    ],
    "wof:name":"Tomlinson Hall & Co. Ltd.",
    "wof:placetype":"venue"
},
  "geometry": {"coordinates":[-1.31198,54.557091],"type":"Point"}
}