{
  "type": "Feature",
  "properties": {
    "addr:full":"111 Connaught Gardens London Greater London N13 5BU",
    "addr:housenumber":"111",
    "addr:postcode":"n13 5bu",
    "addr:street":"Connaught Gardens",
    "iso:country":"GB",
    "sg:address":"111 Connaught Gardens",
    "sg:city":"London",
    "sg:classifiers":[
        {
            "category":"Banks & Credit Unions",
            "subcategory":"Financial Services",
            "type":"Services"
        }
    ],
    "sg:phone":"+44 20 8886 9504",
    "sg:postcode":"N13 5BU",
    "sg:province":"Greater London",
    "sg:tags":[
        "consultant"
    ],
    "wof:name":"Havva Investments Ltd.",
    "wof:placetype":"venue"
},
  "geometry": {"coordinates":[-0.0957150012,51.6187782288],"type":"Point"}
}