{
  "type": "Feature",
  "properties": {
    "iso:country":"GB",
    "sg:address":"21 Eskdaill Ct",
    "sg:city":"Dalkeith",
    "sg:classifiers":[
        {
            "category":"Home & Garden",
            "subcategory":"Furniture",
            "type":"Retail Goods"
        }
    ],
    "sg:phone":"+44 131 660 9509",
    "sg:postcode":"EH22 1AG",
    "sg:province":"City of Edinburgh",
    "sg:tags":[
        "outlet"
    ],
    "wof:name":"Warmsleys Superstore",
    "wof:placetype":"venue"
},
  "geometry": {"coordinates":[-3.0968089104,55.9043502808],"type":"Point"}
}