{
  "type": "Feature",
  "properties": {
    "iso:country":"GB",
    "sg:address":"Kirkby Gate Service Stn, Kirkby Rd, Hemsworth",
    "sg:city":"Pontefract",
    "sg:classifiers":[
        {
            "category":"Autos & Motor Vehicles",
            "subcategory":"Automobile Sales",
            "type":"Retail Goods"
        }
    ],
    "sg:postcode":"WF9 4DE",
    "sg:province":"West Yorkshire",
    "sg:tags":[
        "car"
    ],
    "wof:name":"Castle Cars",
    "wof:placetype":"venue"
},
  "geometry": {"coordinates":[-1.3461940289,53.6056785583],"type":"Point"}
}