{
  "type": "Feature",
  "properties": {
    "iso:country":"GB",
    "sg:address":"47-49 Paradise Street",
    "sg:city":"Liverpool",
    "sg:classifiers":[
        {
            "category":"Personal",
            "subcategory":"Beauty Salon",
            "type":"Services"
        },
        {
            "category":"Education",
            "subcategory":"Vocational School",
            "type":"Public Place"
        }
    ],
    "sg:phone":"+44 151 708 5258",
    "sg:postcode":"L1 3BP",
    "sg:province":"Merseyside",
    "sg:tags":[
        "unisex",
        "hairdresser",
        "hairdressing"
    ],
    "wof:name":"Herbert of Liverpool (Training) Ltd.",
    "wof:placetype":"venue"
},
  "geometry": {"coordinates":[-2.9860188961,53.4040412903],"type":"Point"}
}