{
  "type": "Feature",
  "properties": {
    "iso:country":"GB",
    "sg:address":"46a Norman Road",
    "sg:city":"Southsea",
    "sg:classifiers":[
        {
            "category":"Real Estate",
            "subcategory":"Real Estate Services",
            "type":"Services"
        },
        {
            "category":"Real Estate",
            "subcategory":"Real Estate Agent",
            "type":"Services"
        }
    ],
    "sg:phone":"+44 23 9273 1570",
    "sg:postcode":"PO4 0LP",
    "sg:province":"Hampshire",
    "sg:tags":[
        "management"
    ],
    "wof:name":"Snook Management Co Ltd",
    "wof:placetype":"venue"
},
  "geometry": {"coordinates":[-1.074779,50.788849],"type":"Point"}
}