{
  "type": "Feature",
  "properties": {
    "addr:full":"10 Stratton Road, Hainford Norwich Norfolk NR10 3AY",
    "addr:housenumber":"10",
    "addr:postcode":"nr10 3ay",
    "addr:street":"Stratton Road;Norwich",
    "iso:country":"GB",
    "sg:address":"10 Stratton Road, Hainford",
    "sg:city":"Norwich",
    "sg:classifiers":[
        {
            "category":"Bars & Pubs",
            "type":"Food & Drink"
        },
        {
            "category":"Community Center",
            "subcategory":"Social",
            "type":"Public Place"
        }
    ],
    "sg:phone":"+44 1603 891657",
    "sg:postcode":"NR10 3AY",
    "sg:province":"Norfolk",
    "sg:tags":[
        "pubs",
        "house",
        "inn",
        "activity"
    ],
    "wof:name":"The Chequers Inn",
    "wof:placetype":"venue"
},
  "geometry": {"coordinates":[1.291537,52.727833],"type":"Point"}
}