{
  "type": "Feature",
  "properties": {
    "addr:full":"50 Park Row Bristol City of Bristol BS1 5LH",
    "addr:housenumber":"50",
    "addr:postcode":"bs1 5lh",
    "addr:street":"Park Row",
    "iso:country":"GB",
    "sg:address":"50 Park Row",
    "sg:city":"Bristol",
    "sg:classifiers":[
        {
            "category":"Personal",
            "subcategory":"Beauty Salon",
            "type":"Services"
        }
    ],
    "sg:phone":"+44 117 929 1635",
    "sg:postcode":"BS1 5LH",
    "sg:province":"City of Bristol",
    "sg:tags":[
        "unisex",
        "hairdresser"
    ],
    "wof:name":"Hobbs Ladies & Gents Hairdressing",
    "wof:placetype":"venue"
},
  "geometry": {"coordinates":[-2.60272,51.455341],"type":"Point"}
}