{
  "type": "Feature",
  "properties": {
    "addr:full":"121-135 Dalton Road Barrow-in-furness Cumbria LA14 1HZ",
    "addr:housenumber":"121-135",
    "addr:postcode":"la14 1hz",
    "addr:street":"Dalton Road",
    "iso:country":"GB",
    "sg:address":"121-135 Dalton Road",
    "sg:city":"Barrow-in-furness",
    "sg:classifiers":[
        {
            "category":"Shopping",
            "subcategory":"Catalog Store",
            "type":"Retail Goods"
        }
    ],
    "sg:phone":"+44 1229 431581",
    "sg:postcode":"LA14 1HZ",
    "sg:province":"Cumbria",
    "sg:tags":[
        "catalogue",
        "showroom"
    ],
    "wof:name":"Argos Ltd.",
    "wof:placetype":"venue"
},
  "geometry": {"coordinates":[-3.225538969,54.1129226685],"type":"Point"}
}