{
  "type": "Feature",
  "properties": {
    "addr:full":"Station St Nottingham Derbyshire NG10 1GJ",
    "addr:postcode":"ng10 1gj",
    "addr:street":"St",
    "iso:country":"GB",
    "sg:address":"Station St",
    "sg:city":"Nottingham",
    "sg:classifiers":[
        {
            "category":"Health Services",
            "subcategory":"Health Practitioner",
            "type":"Services"
        }
    ],
    "sg:phone":"+44 115 972 1319",
    "sg:postcode":"NG10 1GJ",
    "sg:province":"Derbyshire",
    "sg:tags":[
        "physiotherapist"
    ],
    "wof:name":"L Daley",
    "wof:placetype":"venue"
},
  "geometry": {"coordinates":[-1.2660080194,52.8961868286],"type":"Point"}
}