{
  "type": "Feature",
  "properties": {
    "addr:full":"7 Pumbro, Stonesfield Witney Oxfordshire OX29 8QF",
    "addr:housenumber":"7",
    "addr:postcode":"ox29 8qf",
    "addr:street":"Pumbro Stonesfield",
    "iso:country":"GB",
    "sg:address":"7 Pumbro, Stonesfield",
    "sg:city":"Witney",
    "sg:classifiers":[
        {
            "category":"Communications",
            "subcategory":"Film & Video Production",
            "type":"Services"
        },
        {
            "category":"Retail",
            "subcategory":"Repair Shop",
            "type":"Services"
        }
    ],
    "sg:phone":"+44 1993 891765",
    "sg:postcode":"OX29 8QF",
    "sg:province":"Oxfordshire",
    "sg:tags":[
        "television",
        "good",
        "recording",
        "studio",
        "servicing",
        "maintenance",
        "radio"
    ],
    "wof:name":"PRO-SERV AUDIO",
    "wof:placetype":"venue"
},
  "geometry": {"coordinates":[-1.430361,51.853741],"type":"Point"}
}