{
  "type": "Feature",
  "properties": {
    "iso:country":"GB",
    "sg:address":"Lyndhurst Building, Lyndhurst Road",
    "sg:city":"Ascot",
    "sg:classifiers":[
        {
            "category":"Utilities",
            "subcategory":"Fuel Oil & Lpg",
            "type":"Services"
        }
    ],
    "sg:phone":"+44 1344 622130",
    "sg:postcode":"SL5 9ED",
    "sg:province":"Berkshire",
    "sg:tags":[
        "merchant",
        "coal",
        "smokeless"
    ],
    "wof:name":"W Sole & Sons",
    "wof:placetype":"venue"
},
  "geometry": {"coordinates":[-0.6760389805,51.4056968689],"type":"Point"}
}