{
  "type": "Feature",
  "properties": {
    "iso:country":"GB",
    "sg:address":"Link House, 2 Norfolk Square",
    "sg:city":"Brighton",
    "sg:classifiers":[
        {
            "category":"Professional",
            "subcategory":"Art Services",
            "type":"Services"
        }
    ],
    "sg:phone":"+44 1273 771551",
    "sg:postcode":"BN1 2PB",
    "sg:province":"East Sussex",
    "sg:tags":[
        "graphic",
        "designer"
    ],
    "wof:name":"Kixis Design",
    "wof:placetype":"venue"
},
  "geometry": {"coordinates":[-0.1552889943,50.8244819641],"type":"Point"}
}