{
  "type": "Feature",
  "properties": {
    "addr:full":"29 Lanark Road Carluke South Lanarkshire ML8 4HE",
    "addr:housenumber":"29",
    "addr:postcode":"ml8 4he",
    "addr:street":"Lanark Road",
    "iso:country":"GB",
    "sg:address":"29 Lanark Road",
    "sg:city":"Carluke",
    "sg:classifiers":[
        {
            "category":"Freight",
            "type":"Transportation"
        }
    ],
    "sg:postcode":"ML8 4HE",
    "sg:province":"South Lanarkshire",
    "sg:tags":[
        "haulage",
        "road"
    ],
    "wof:name":"A T G  Haulage Ltd.",
    "wof:placetype":"venue"
},
  "geometry": {"coordinates":[-3.8355710506,55.7292289734],"type":"Point"}
}