{
  "type": "Feature",
  "properties": {
    "iso:country":"GB",
    "sg:address":"30 Churchfields Road",
    "sg:city":"Salisbury",
    "sg:classifiers":[
        {
            "category":"Bars & Pubs",
            "type":"Food & Drink"
        }
    ],
    "sg:postcode":"SP2 7NW",
    "sg:province":"Wiltshire",
    "sg:tags":[
        "pubs",
        "inn"
    ],
    "wof:name":"The Blackbird Inn",
    "wof:placetype":"venue"
},
  "geometry": {"coordinates":[-1.8088419437,51.0701789856],"type":"Point"}
}