{
  "type": "Feature",
  "properties": {
    "addr:full":"7 Hastings Court, Collingham Wetherby North Yorkshire LS22 5AW",
    "addr:housenumber":"7",
    "addr:postcode":"ls22 5aw",
    "addr:street":"Hastings Court",
    "iso:country":"GB",
    "sg:address":"7 Hastings Court, Collingham",
    "sg:city":"Wetherby",
    "sg:classifiers":[
        {
            "category":"Fast Food",
            "type":"Food & Drink"
        },
        {
            "category":"Food & Beverages",
            "subcategory":"Meat & Fish",
            "type":"Retail Goods"
        }
    ],
    "sg:phone":"+44 1937 573030",
    "sg:postcode":"LS22 5AW",
    "sg:province":"North Yorkshire",
    "sg:tags":[
        "shop",
        "chip"
    ],
    "wof:name":"Hastings Fisheries",
    "wof:placetype":"venue"
},
  "geometry": {"coordinates":[-1.425116,53.905758],"type":"Point"}
}