{
  "type": "Feature",
  "properties": {
    "addr:full":"214 Bradley Road, Bradley Huddersfield West Yorkshire HD2 1QD",
    "addr:housenumber":"214",
    "addr:postcode":"hd2 1qd",
    "addr:street":"Bradley Road;West",
    "iso:country":"GB",
    "sg:address":"214 Bradley Road, Bradley",
    "sg:city":"Huddersfield",
    "sg:classifiers":[
        {
            "category":"Building & Trades",
            "subcategory":"Construction",
            "type":"Services"
        }
    ],
    "sg:phone":"+44 1484 543713",
    "sg:postcode":"HD2 1QD",
    "sg:province":"West Yorkshire",
    "sg:tags":[
        "roofing",
        "contracting"
    ],
    "wof:name":"P STRINGER ROOFING CONTRACTOR",
    "wof:placetype":"venue"
},
  "geometry": {"coordinates":[-1.752332,53.682865],"type":"Point"}
}