{
  "type": "Feature",
  "properties": {
    "iso:country":"GB",
    "sg:address":"1/5 Alfred Street",
    "sg:city":"London",
    "sg:classifiers":[
        {
            "category":"Professional",
            "subcategory":"Accounting & Tax Preparation",
            "type":"Services"
        }
    ],
    "sg:phone":"+44 20 8980 7161",
    "sg:postcode":"E3 2BE",
    "sg:province":"Greater London",
    "sg:tags":[
        "accountant"
    ],
    "wof:name":"Martin Cordell & Co",
    "wof:placetype":"venue"
},
  "geometry": {"coordinates":[-0.026189,51.528191],"type":"Point"}
}