{
  "type": "Feature",
  "properties": {
    "iso:country":"GB",
    "sg:address":"20 Lord Mayors Walk",
    "sg:city":"York",
    "sg:classifiers":[
        {
            "category":"Professional",
            "subcategory":"Printing & Photocopies",
            "type":"Services"
        },
        {
            "category":"Real Estate",
            "subcategory":"Architect",
            "type":"Services"
        }
    ],
    "sg:phone":"+44 1904 632313",
    "sg:postcode":"YO31 7HA",
    "sg:province":"North Yorkshire",
    "sg:tags":[
        "copying"
    ],
    "wof:name":"The Architect Shop",
    "wof:placetype":"venue"
},
  "geometry": {"coordinates":[-1.0782179832,53.9632148743],"type":"Point"}
}