{
  "type": "Feature",
  "properties": {
    "addr:full":"Woodbottom Farm, Meltham Huddersfield South Yorkshire HD9 4AP",
    "addr:postcode":"hd9 4ap",
    "addr:street":"South",
    "iso:country":"GB",
    "sg:address":"Woodbottom Farm, Meltham",
    "sg:city":"Huddersfield",
    "sg:classifiers":[
        {
            "category":"Professional",
            "subcategory":"Management & Consulting",
            "type":"Services"
        }
    ],
    "sg:postcode":"HD9 4AP",
    "sg:province":"South Yorkshire",
    "sg:tags":[
        "fire",
        "consultant",
        "protection"
    ],
    "wof:name":"T A Cowap Co. Ltd.",
    "wof:placetype":"venue"
},
  "geometry": {"coordinates":[-1.8327200413,53.5986709595],"type":"Point"}
}