{
  "type": "Feature",
  "properties": {
    "iso:country":"GB",
    "sg:address":"60 Alstone Lane",
    "sg:city":"Cheltenham",
    "sg:classifiers":[
        {
            "category":"Home & Garden",
            "subcategory":"Hardware",
            "type":"Retail Goods"
        }
    ],
    "sg:phone":"+44 1242 261233",
    "sg:postcode":"GL51 8HE",
    "sg:province":"Gloucestershire",
    "sg:tags":[
        "device",
        "fixing",
        "fastener"
    ],
    "wof:name":"Torque Control Ltd",
    "wof:placetype":"venue"
},
  "geometry": {"coordinates":[-2.0970098972,51.902961731],"type":"Point"}
}