{
  "type": "Feature",
  "properties": {
    "iso:country":"GB",
    "sg:address":"Belle Isle Road",
    "sg:city":"Leeds",
    "sg:classifiers":[
        {
            "category":"Health Services",
            "subcategory":"Nursing And Care Facility",
            "type":"Services"
        },
        {
            "category":"Organizations",
            "subcategory":"Membership Organization",
            "type":"Services"
        }
    ],
    "sg:phone":"+44 113 270 8529",
    "sg:postcode":"LS10 3PE",
    "sg:province":"West Yorkshire",
    "sg:tags":[
        "club",
        "home",
        "social"
    ],
    "wof:name":"Belle Isle Working Mens Club",
    "wof:placetype":"venue"
},
  "geometry": {"coordinates":[-1.530884,53.770069],"type":"Point"}
}