{
  "type": "Feature",
  "properties": {
    "iso:country":"GB",
    "sg:address":"694-698 Attercliffe Road",
    "sg:city":"Sheffield",
    "sg:classifiers":[
        {
            "category":"Shopping",
            "subcategory":"Discount & Variety Stores",
            "type":"Retail Goods"
        },
        {
            "category":"Manufacturing",
            "subcategory":"Building Materials",
            "type":"Manufacturing & Wholesale Goods"
        }
    ],
    "sg:phone":"+44 114 244 4474",
    "sg:postcode":"S9 3RP",
    "sg:province":"South Yorkshire",
    "sg:tags":[
        "equipment",
        "cleaning",
        "supply"
    ],
    "sg:website":"http://www.acejanitorial.co.uk",
    "wof:name":"Ace Janitorial Supplies Ltd.",
    "wof:placetype":"venue"
},
  "geometry": {"coordinates":[-1.431611,53.394276],"type":"Point"}
}