{
  "type": "Feature",
  "properties": {
    "addr:full":"Vicarage, 1163 High Rd Totteridge Greater London N20 0PG",
    "addr:housenumber":"1163",
    "addr:postcode":"n20 0pg",
    "addr:street":"High Rd",
    "iso:country":"GB",
    "sg:address":"Vicarage, 1163 High Rd",
    "sg:city":"Totteridge",
    "sg:classifiers":[
        {
            "category":"Place Of Worship",
            "type":"Public Place"
        }
    ],
    "sg:phone":"+44 20 8445 4569",
    "sg:postcode":"N20 0PG",
    "sg:province":"Greater London",
    "wof:name":"St John The Apostle Church",
    "wof:placetype":"venue"
},
  "geometry": {"coordinates":[-0.17596,51.627449],"type":"Point"}
}