{
  "type": "Feature",
  "properties": {
    "addr:full":"Unit 5, Kendal Ct, Kendal Ave London Greater London W3 0RU",
    "addr:housenumber":"unit 5",
    "addr:postcode":"w3 0ru",
    "addr:street":"Kendal Ct Kendal Ave",
    "iso:country":"GB",
    "sg:address":"Unit 5, Kendal Ct, Kendal Ave",
    "sg:city":"London",
    "sg:classifiers":[
        {
            "category":"Professional",
            "subcategory":"Printing & Photocopies",
            "type":"Services"
        }
    ],
    "sg:phone":"+44 20 8993 1199",
    "sg:postcode":"W3 0RU",
    "sg:province":"Greater London",
    "sg:tags":[
        "printer"
    ],
    "wof:name":"Consul Printing & Packaging Ltd",
    "wof:placetype":"venue"
},
  "geometry": {"coordinates":[-0.2798109949,51.5235443115],"type":"Point"}
}