{
  "type": "Feature",
  "properties": {
    "addr:full":"Royal Hotel, Symonds Yat Ross-on-wye Gloucestershire HR9 6JL",
    "addr:postcode":"hr9 6jl",
    "iso:country":"GB",
    "sg:address":"Royal Hotel, Symonds Yat",
    "sg:city":"Ross-on-wye",
    "sg:classifiers":[
        {
            "category":"Travel",
            "subcategory":"Hotels & Motels",
            "type":"Entertainment"
        }
    ],
    "sg:postcode":"HR9 6JL",
    "sg:province":"Gloucestershire",
    "wof:name":"Symonds Yat Royal Hotel Resort & Conference Centre Ltd.",
    "wof:placetype":"venue"
},
  "geometry": {"coordinates":[-2.648346,51.849548],"type":"Point"}
}