{
  "type": "Feature",
  "properties": {
    "addr:full":"7 Fore Street Ivybridge Devon PL21 9AB",
    "addr:housenumber":"7",
    "addr:postcode":"pl21 9ab",
    "addr:street":"Fore Street",
    "iso:country":"GB",
    "sg:address":"7 Fore Street",
    "sg:city":"Ivybridge",
    "sg:classifiers":[
        {
            "category":"Real Estate",
            "subcategory":"Real Estate Agent",
            "type":"Services"
        }
    ],
    "sg:phone":"+44 1752 893269",
    "sg:postcode":"PL21 9AB",
    "sg:province":"Devon",
    "wof:name":"B B G Estate Agencies",
    "wof:placetype":"venue"
},
  "geometry": {"coordinates":[-3.9208869934,50.3893203735],"type":"Point"}
}