{
  "type": "Feature",
  "properties": {
    "iso:country":"GB",
    "sg:address":"Main Street",
    "sg:city":"West Linton",
    "sg:classifiers":[
        {
            "category":"Food & Beverages",
            "subcategory":"Fruits & Vegetables",
            "type":"Retail Goods"
        }
    ],
    "sg:postcode":"EH46 7EE",
    "sg:province":"Midlothian",
    "sg:tags":[
        "greengrocer"
    ],
    "wof:name":"Dorothy's",
    "wof:placetype":"venue"
},
  "geometry": {"coordinates":[-3.356539,55.753799],"type":"Point"}
}