{
  "type": "Feature",
  "properties": {
    "iso:country":"GB",
    "sg:address":"188-190 Hoe Street, Walthamstow",
    "sg:city":"London",
    "sg:classifiers":[
        {
            "category":"Professional",
            "subcategory":"Lawyer & Legal Services",
            "type":"Services"
        }
    ],
    "sg:phone":"+44 20 8520 5886",
    "sg:postcode":"E17 4QH",
    "sg:province":"Greater London",
    "sg:tags":[
        "solicitor"
    ],
    "wof:name":"Gilbert Turner & Coomber",
    "wof:placetype":"venue"
},
  "geometry": {"coordinates":[-0.0199740008,51.5860595703],"type":"Point"}
}