{
  "type": "Feature",
  "properties": {
    "iso:country":"GB",
    "sg:address":"Hill Avenue",
    "sg:city":"Dumfries",
    "sg:classifiers":[
        {
            "category":"Education",
            "subcategory":"School",
            "type":"Public Place"
        },
        {
            "category":"Government",
            "subcategory":"Office",
            "type":"Public Place"
        }
    ],
    "sg:phone":"+44 1387 252615",
    "sg:postcode":"DG2 7LR",
    "sg:province":"Dumfries and Galloway",
    "sg:tags":[
        "local",
        "authority"
    ],
    "wof:name":"Troqueer Primary School",
    "wof:placetype":"venue"
},
  "geometry": {"coordinates":[-3.6129589081,55.0586204529],"type":"Point"}
}