{
  "type": "Feature",
  "properties": {
    "iso:country":"GB",
    "sg:address":"84 Parkwood Rd",
    "sg:city":"Isleworth",
    "sg:classifiers":[
        {
            "category":"Professional",
            "subcategory":"Engineering",
            "type":"Services"
        }
    ],
    "sg:phone":"+44 20 8560 6550",
    "sg:postcode":"TW7 5HD",
    "sg:province":"Greater London",
    "sg:tags":[
        "contractor",
        "electrical",
        "engineer"
    ],
    "wof:name":"Runrite Services",
    "wof:placetype":"venue"
},
  "geometry": {"coordinates":[-0.3290300071,51.4799003601],"type":"Point"}
}