{
  "type": "Feature",
  "properties": {
    "iso:country":"GB",
    "sg:address":"693 High Road, Finchley",
    "sg:city":"London",
    "sg:classifiers":[
        {
            "category":"Real Estate",
            "subcategory":"Real Estate Agent",
            "type":"Services"
        }
    ],
    "sg:phone":"+44 20 8446 0453",
    "sg:postcode":"N12 0DA",
    "sg:province":"Greater London",
    "wof:name":"Newhope Properties Ltd.",
    "wof:placetype":"venue"
},
  "geometry": {"coordinates":[-0.175846,51.611752],"type":"Point"}
}