{
  "type": "Feature",
  "properties": {
    "addr:full":"Pencroft Road Birmingham West Midlands B34 6SS",
    "addr:postcode":"6ss",
    "addr:street":"Pencroft Road",
    "iso:country":"GB",
    "sg:address":"Pencroft Road",
    "sg:city":"Birmingham",
    "sg:classifiers":[
        {
            "category":"Education",
            "subcategory":"School",
            "type":"Public Place"
        },
        {
            "category":"Government",
            "subcategory":"Office",
            "type":"Public Place"
        }
    ],
    "sg:phone":"+44 121 747 3102",
    "sg:postcode":"B34 6SS",
    "sg:province":"West Midlands",
    "sg:tags":[
        "local",
        "authority"
    ],
    "wof:name":"Brownmead Junior & Infant School",
    "wof:placetype":"venue"
},
  "geometry": {"coordinates":[-1.782254,52.499046],"type":"Point"}
}