{
  "type": "Feature",
  "properties": {
    "addr:full":"10 Swinegate York North Yorkshire YO1 8AZ",
    "addr:housenumber":"10",
    "addr:postcode":"yo1 8az",
    "addr:street":"Swinegate York",
    "iso:country":"GB",
    "sg:address":"10 Swinegate",
    "sg:city":"York",
    "sg:classifiers":[
        {
            "category":"Shopping",
            "subcategory":"Jewelry",
            "type":"Retail Goods"
        },
        {
            "category":"Shopping",
            "subcategory":"Comic Books",
            "type":"Retail Goods"
        }
    ],
    "sg:phone":"+44 1904 679000",
    "sg:postcode":"YO1 8AZ",
    "sg:province":"North Yorkshire",
    "sg:tags":[
        "jeweller",
        "sale",
        "jewellery"
    ],
    "wof:name":"Ashberry Of York",
    "wof:placetype":"venue"
},
  "geometry": {"coordinates":[-1.081918,53.960514],"type":"Point"}
}