{
  "type": "Feature",
  "properties": {
    "addr:full":"Bassetts Mill La, Hildenborough Tonbridge Kent TN11 9LX",
    "addr:postcode":"tn11 9lx",
    "addr:street":"Bassetts;La Hildenborough",
    "iso:country":"GB",
    "sg:address":"Bassetts Mill La, Hildenborough",
    "sg:city":"Tonbridge",
    "sg:classifiers":[
        {
            "category":"Food & Beverages",
            "subcategory":"Liquor & Beverages",
            "type":"Retail Goods"
        }
    ],
    "sg:postcode":"TN11 9LX",
    "sg:province":"Kent",
    "sg:tags":[
        "beer",
        "spirit",
        "wines"
    ],
    "wof:name":"The Bothy Wine Cellars",
    "wof:placetype":"venue"
},
  "geometry": {"coordinates":[0.24739,51.214031],"type":"Point"}
}