{
  "type": "Feature",
  "properties": {
    "addr:full":"17 Aston Road Waterlooville Hampshire PO7 7XG",
    "addr:housenumber":"17",
    "addr:postcode":"po7 7xg",
    "addr:street":"Aston Road",
    "iso:country":"GB",
    "sg:address":"17 Aston Road",
    "sg:city":"Waterlooville",
    "sg:classifiers":[
        {
            "category":"Professional",
            "type":"Services"
        }
    ],
    "sg:phone":"+44 23 9225 5255",
    "sg:postcode":"PO7 7XG",
    "sg:province":"Hampshire",
    "sg:tags":[
        "aircraft",
        "-",
        "maintenance"
    ],
    "wof:name":"Deltair Airmotive Ltd.",
    "wof:placetype":"venue"
},
  "geometry": {"coordinates":[-1.035147,50.884937],"type":"Point"}
}