{
  "type": "Feature",
  "properties": {
    "addr:full":"Unit D1 Spectrum Business Centre, Anthonys Way Rochester Kent ME2 4NP",
    "addr:housenumber":"d1",
    "addr:postcode":"me2 4np",
    "addr:street":"Anthonys Way",
    "iso:country":"GB",
    "sg:address":"Unit D1 Spectrum Business Centre, Anthonys Way",
    "sg:city":"Rochester",
    "sg:classifiers":[
        {
            "category":"Building & Trades",
            "subcategory":"Construction",
            "type":"Services"
        }
    ],
    "sg:phone":"+44 1634 295621",
    "sg:postcode":"ME2 4NP",
    "sg:province":"Kent",
    "sg:tags":[
        "restoration",
        "refurbishment"
    ],
    "wof:name":"Riverside Contractors Ltd.",
    "wof:placetype":"venue"
},
  "geometry": {"coordinates":[0.4887830019,51.3963699341],"type":"Point"}
}