{
  "type": "Feature",
  "properties": {
    "iso:country":"GB",
    "sg:address":"Alder Mill Nursersies",
    "sg:city":"Atherstone",
    "sg:classifiers":[
        {
            "category":"Shopping",
            "subcategory":"Pets & Pet Supplies",
            "type":"Retail Goods"
        }
    ],
    "sg:postcode":"CV9 3AH",
    "sg:province":"Leicestershire",
    "sg:tags":[
        "equestrian"
    ],
    "wof:name":"Dobbins Diner",
    "wof:placetype":"venue"
},
  "geometry": {"coordinates":[-1.541959,52.575935],"type":"Point"}
}