{
  "type": "Feature",
  "properties": {
    "iso:country":"GB",
    "sg:address":"62 Glen Shee Av",
    "sg:city":"Glasgow",
    "sg:classifiers":[
        {
            "category":"Home & Garden",
            "subcategory":"Home Furnishings",
            "type":"Retail Goods"
        }
    ],
    "sg:phone":"+44 141 881 9380",
    "sg:postcode":"G78 3QB",
    "sg:province":"East Ayrshire",
    "sg:tags":[
        "racking",
        "shelving",
        "diy"
    ],
    "wof:name":"Neilston Storage Installations",
    "wof:placetype":"venue"
},
  "geometry": {"coordinates":[-4.435403,55.777657],"type":"Point"}
}