{
  "type": "Feature",
  "properties": {
    "addr:full":"4 Abercorn Road Edinburgh City of Edinburgh EH8 7DE",
    "addr:housenumber":"4",
    "addr:postcode":"eh8 7de",
    "addr:street":"Abercorn Road",
    "iso:country":"GB",
    "sg:address":"4 Abercorn Road",
    "sg:city":"Edinburgh",
    "sg:classifiers":[
        {
            "category":"Social Services",
            "subcategory":"Job Training",
            "type":"Services"
        }
    ],
    "sg:phone":"+44 131 652 0283",
    "sg:postcode":"EH8 7DE",
    "sg:province":"City of Edinburgh",
    "sg:tags":[
        "draughtsman",
        "drawing"
    ],
    "wof:name":"Foundations",
    "wof:placetype":"venue"
},
  "geometry": {"coordinates":[-3.148525,55.954323],"type":"Point"}
}