{
  "type": "Feature",
  "properties": {
    "addr:full":"130-132 High Street Burford Gloucestershire OX18 4QU",
    "addr:housenumber":"130-132",
    "addr:postcode":"ox18 4qu",
    "addr:street":"High Street",
    "iso:country":"GB",
    "sg:address":"130-132 High Street",
    "sg:city":"Burford",
    "sg:classifiers":[
        {
            "category":"Shopping",
            "subcategory":"Shoes",
            "type":"Retail Goods"
        }
    ],
    "sg:postcode":"OX18 4QU",
    "sg:province":"Gloucestershire",
    "sg:tags":[
        "shop"
    ],
    "wof:name":"Rose Dodd",
    "wof:placetype":"venue"
},
  "geometry": {"coordinates":[-1.637063,51.807243],"type":"Point"}
}