{
  "type": "Feature",
  "properties": {
    "addr:full":"Unit 383h Jedburgh Ct, Eleventh Av, Team Valley Trading Est Gateshead Tyne and Wear NE11 0JY",
    "addr:housenumber":"383h",
    "addr:postcode":"ne11 0jy",
    "addr:street":"Jedburgh Ct Eleventh Av;Est",
    "iso:country":"GB",
    "sg:address":"Unit 383h Jedburgh Ct, Eleventh Av, Team Valley Trading Est",
    "sg:city":"Gateshead",
    "sg:classifiers":[
        {
            "category":"Retail",
            "subcategory":"Auto Repair",
            "type":"Services"
        }
    ],
    "sg:phone":"+44 191 422 5500",
    "sg:postcode":"NE11 0JY",
    "sg:province":"Tyne and Wear",
    "sg:tags":[
        "garage"
    ],
    "wof:name":"Phoenix Services",
    "wof:placetype":"venue"
},
  "geometry": {"coordinates":[-1.6073499918,54.923500061],"type":"Point"}
}