{
  "type": "Feature",
  "properties": {
    "iso:country":"GB",
    "sg:address":"Hele Lane",
    "sg:city":"South Petherton",
    "sg:classifiers":[
        {
            "category":"Place Of Worship",
            "type":"Public Place"
        }
    ],
    "sg:phone":"+44 1460 240377",
    "sg:postcode":"TA13 5DY",
    "sg:province":"Somerset",
    "wof:name":"St Peter & St Paul C Of E Church",
    "wof:placetype":"venue"
},
  "geometry": {"coordinates":[-2.808014,50.947205],"type":"Point"}
}