{
  "type": "Feature",
  "properties": {
    "addr:full":"180 West Regent Street Glasgow Glasgow City G2 4RW",
    "addr:housenumber":"180",
    "addr:postcode":"g2 4rw",
    "addr:street":"West Regent Street",
    "iso:country":"GB",
    "sg:address":"180 West Regent Street",
    "sg:city":"Glasgow",
    "sg:classifiers":[
        {
            "category":"Professional",
            "subcategory":"Management & Consulting",
            "type":"Services"
        }
    ],
    "sg:phone":"+44 141 226 5665",
    "sg:postcode":"G2 4RW",
    "sg:province":"Glasgow City",
    "sg:tags":[
        "consultant",
        "business"
    ],
    "wof:name":"Arona",
    "wof:placetype":"venue"
},
  "geometry": {"coordinates":[-4.261743,55.863865],"type":"Point"}
}