{
  "type": "Feature",
  "properties": {
    "addr:full":"The Bourne, 4b Main Street, Frodsham Warrington Cheshire WA6 7AX",
    "addr:housenumber":"4b",
    "addr:postcode":"wa6 7ax",
    "addr:street":"Main Street",
    "iso:country":"GB",
    "sg:address":"The Bourne, 4b Main Street, Frodsham",
    "sg:city":"Warrington",
    "sg:classifiers":[
        {
            "category":"Professional",
            "subcategory":"Employment Agencies",
            "type":"Services"
        }
    ],
    "sg:phone":"+44 1928 734555",
    "sg:postcode":"WA6 7AX",
    "sg:province":"Cheshire",
    "sg:tags":[
        "consultant"
    ],
    "wof:name":"M D A Ramco",
    "wof:placetype":"venue"
},
  "geometry": {"coordinates":[-2.7251389027,53.2964401245],"type":"Point"}
}