{
  "type": "Feature",
  "properties": {
    "iso:country":"GB",
    "sg:address":"Dorchester Road, Priorswood",
    "sg:city":"Taunton",
    "sg:classifiers":[
        {
            "category":"Autos & Motor Vehicles",
            "subcategory":"Fuel & Gas Station",
            "type":"Retail Goods"
        }
    ],
    "sg:phone":"+44 1823 337038",
    "sg:postcode":"TA2 7JN",
    "sg:province":"Somerset",
    "sg:tags":[
        "petrol",
        "filling"
    ],
    "wof:name":"Murco Service Station",
    "wof:placetype":"venue"
},
  "geometry": {"coordinates":[-3.096804,51.039162],"type":"Point"}
}