{
  "type": "Feature",
  "properties": {
    "addr:full":"A14 Huntingdon Road, Lolworth Cambridge Cambridgeshire CB3 8DR",
    "addr:postcode":"cb3 8dr",
    "addr:street":"Huntingdon Road",
    "iso:country":"GB",
    "sg:address":"A14 Huntingdon Road, Lolworth",
    "sg:city":"Cambridge",
    "sg:classifiers":[
        {
            "category":"Restaurant",
            "type":"Food & Drink"
        }
    ],
    "sg:phone":"+44 1954 789811",
    "sg:postcode":"CB3 8DR",
    "sg:province":"Cambridgeshire",
    "wof:name":"Little Chef",
    "wof:placetype":"venue"
},
  "geometry": {"coordinates":[0.007688,52.26421],"type":"Point"}
}