{
  "type": "Feature",
  "properties": {
    "addr:full":"28 Market Hall, High St Newcastle Staffordshire ST5 1QB",
    "addr:housenumber":"28",
    "addr:postcode":"st5 1qb",
    "addr:street":"Market Hall High St",
    "iso:country":"GB",
    "sg:address":"28 Market Hall, High St",
    "sg:city":"Newcastle",
    "sg:classifiers":[
        {
            "category":"Shopping",
            "subcategory":"Clothing, Apparel, & Fashions",
            "type":"Retail Goods"
        }
    ],
    "sg:postcode":"ST5 1QB",
    "sg:province":"Staffordshire",
    "sg:tags":[
        "shop",
        "hat"
    ],
    "wof:name":"Hatmosphere",
    "wof:placetype":"venue"
},
  "geometry": {"coordinates":[-2.2286009789,53.0088005066],"type":"Point"}
}