{
  "type": "Feature",
  "properties": {
    "addr:full":"28 Margaret Street West End Hampshire W1N 7LB",
    "addr:housenumber":"28",
    "addr:postcode":"w1n 7lb",
    "addr:street":"Margaret Street",
    "iso:country":"GB",
    "sg:address":"28 Margaret Street",
    "sg:city":"West End",
    "sg:classifiers":[
        {
            "category":"Manufacturing",
            "subcategory":"Rubber & Plastics",
            "type":"Manufacturing & Wholesale Goods"
        }
    ],
    "sg:postcode":"W1N 7LB",
    "sg:province":"Hampshire",
    "sg:tags":[
        "product"
    ],
    "wof:name":"Panmer Ltd",
    "wof:placetype":"venue"
},
  "geometry": {"coordinates":[-0.13899,51.50758],"type":"Point"}
}