{
  "type": "Feature",
  "properties": {
    "iso:country":"GB",
    "sg:address":"457 Redditch Rd, Kings Norton",
    "sg:city":"Birmingham",
    "sg:classifiers":[
        {
            "category":"Home & Garden",
            "subcategory":"Building Materials",
            "type":"Retail Goods"
        }
    ],
    "sg:phone":"+44 121 458 6662",
    "sg:postcode":"B38 8NB",
    "sg:province":"West Midlands",
    "sg:tags":[
        "insulation",
        "installers"
    ],
    "wof:name":"Glowarm Insulations",
    "wof:placetype":"venue"
},
  "geometry": {"coordinates":[-1.9492069483,52.397064209],"type":"Point"}
}