{
  "type": "Feature",
  "properties": {
    "addr:full":"11a Coronation Road Manchester Greater Manchester M43 7RL",
    "addr:housenumber":"11a",
    "addr:postcode":"m43 7rl",
    "addr:street":"Coronation Road",
    "iso:country":"GB",
    "sg:address":"11a Coronation Road",
    "sg:city":"Manchester",
    "sg:classifiers":[
        {
            "category":"Building & Trades",
            "subcategory":"Construction",
            "type":"Services"
        }
    ],
    "sg:phone":"+44 161 370 6607",
    "sg:postcode":"M43 7RL",
    "sg:province":"Greater Manchester",
    "sg:tags":[
        "builder"
    ],
    "wof:name":"A Hearden",
    "wof:placetype":"venue"
},
  "geometry": {"coordinates":[-2.1544749737,53.4884147644],"type":"Point"}
}