{
  "type": "Feature",
  "properties": {
    "addr:full":"Elderfield Road London Greater London E5 0LE",
    "addr:postcode":"e5 0le",
    "addr:street":"Elderfield Road",
    "iso:country":"GB",
    "sg:address":"Elderfield Road",
    "sg:city":"London",
    "sg:classifiers":[
        {
            "category":"Education",
            "subcategory":"School",
            "type":"Public Place"
        },
        {
            "category":"Government",
            "subcategory":"Office",
            "type":"Public Place"
        }
    ],
    "sg:phone":"+44 20 8985 3175",
    "sg:postcode":"E5 0LE",
    "sg:province":"Greater London",
    "sg:tags":[
        "local",
        "authority"
    ],
    "wof:name":"Rushmore Primary School",
    "wof:placetype":"venue"
},
  "geometry": {"coordinates":[-0.0434690006,51.556186676],"type":"Point"}
}