{
  "type": "Feature",
  "properties": {
    "iso:country":"GB",
    "sg:address":"17 Titan Way, Britannia Enterprise Park",
    "sg:city":"Lichfield",
    "sg:classifiers":[
        {
            "category":"Shopping",
            "subcategory":"Computers & Home Electronics",
            "type":"Retail Goods"
        }
    ],
    "sg:phone":"+44 1543 410600",
    "sg:postcode":"WS14 9TT",
    "sg:province":"Staffordshire",
    "sg:tags":[
        "electrical"
    ],
    "wof:name":"Cannock Electrical Wholesalers",
    "wof:placetype":"venue"
},
  "geometry": {"coordinates":[-1.796732,52.684189],"type":"Point"}
}