{
  "type": "Feature",
  "properties": {
    "addr:full":"5 2f2 Bowhill Terrace Edinburgh City of Edinburgh EH3 5QY",
    "addr:housenumber":"5",
    "addr:postcode":"eh3 5qy",
    "addr:street":"2F2 Bowhill Terrace",
    "iso:country":"GB",
    "sg:address":"5 2f2 Bowhill Terrace",
    "sg:city":"Edinburgh",
    "sg:classifiers":[
        {
            "category":"Building & Trades",
            "subcategory":"Plumbing",
            "type":"Services"
        }
    ],
    "sg:postcode":"EH3 5QY",
    "sg:province":"City of Edinburgh",
    "sg:tags":[
        "central",
        "heating"
    ],
    "wof:name":"P B H Heating Plumbing & Gas Fitting",
    "wof:placetype":"venue"
},
  "geometry": {"coordinates":[-3.20834589,55.9710350037],"type":"Point"}
}