{
  "type": "Feature",
  "properties": {
    "addr:full":"49 Catley Road Sheffield South Yorkshire S9 5JF",
    "addr:housenumber":"49",
    "addr:postcode":"s9 5jf",
    "addr:street":"Catley Road",
    "iso:country":"GB",
    "sg:address":"49 Catley Road",
    "sg:city":"Sheffield",
    "sg:classifiers":[
        {
            "category":"Building & Trades",
            "subcategory":"Cleaning & Sanitation",
            "type":"Services"
        },
        {
            "category":"Military Area",
            "subcategory":"Naval Base",
            "type":"Public Place"
        }
    ],
    "sg:phone":"+44 114 243 0406",
    "sg:postcode":"S9 5JF",
    "sg:province":"South Yorkshire",
    "sg:tags":[
        "equipment",
        "repairs",
        "janitorial",
        "servicing"
    ],
    "wof:name":"Marson Industrial Supplies Ltd.",
    "wof:placetype":"venue"
},
  "geometry": {"coordinates":[-1.404428,53.388687],"type":"Point"}
}