{
  "type": "Feature",
  "properties": {
    "iso:country":"GB",
    "sg:address":"Stephenson Square, Beechdale",
    "sg:city":"Walsall",
    "sg:classifiers":[
        {
            "category":"Organizations",
            "subcategory":"Membership Organization",
            "type":"Services"
        }
    ],
    "sg:postcode":"WS2 7DX",
    "sg:province":"West Midlands",
    "sg:tags":[
        "club"
    ],
    "wof:name":"Beechdale Social Club",
    "wof:placetype":"venue"
},
  "geometry": {"coordinates":[-2.0086491108,52.6011581421],"type":"Point"}
}