{
  "type": "Feature",
  "properties": {
    "addr:full":"7 Market Side Scarborough North Yorkshire YO11 1EX",
    "addr:housenumber":"7",
    "addr:postcode":"yo11 1ex",
    "addr:street":"Market Side",
    "iso:country":"GB",
    "sg:address":"7 Market Side",
    "sg:city":"Scarborough",
    "sg:classifiers":[
        {
            "category":"Shopping",
            "subcategory":"Gifts & Souvenirs",
            "type":"Retail Goods"
        }
    ],
    "sg:postcode":"YO11 1EX",
    "sg:province":"North Yorkshire",
    "sg:tags":[
        "shop"
    ],
    "wof:name":"M Wright",
    "wof:placetype":"venue"
},
  "geometry": {"coordinates":[-0.3964569867,54.2841262817],"type":"Point"}
}