{
  "type": "Feature",
  "properties": {
    "addr:full":"19 High Street, Botley Southampton Hampshire SO30 2EA",
    "addr:housenumber":"19",
    "addr:postcode":"so30 2ea",
    "addr:street":"High Street",
    "iso:country":"GB",
    "sg:address":"19 High Street, Botley",
    "sg:city":"Southampton",
    "sg:classifiers":[
        {
            "category":"Building & Trades",
            "subcategory":"Construction",
            "type":"Services"
        }
    ],
    "sg:phone":"+44 1489 780780",
    "sg:postcode":"SO30 2EA",
    "sg:province":"Hampshire",
    "sg:tags":[
        "decorator",
        "painter"
    ],
    "wof:name":"D C Crabb Decorators Ltd.",
    "wof:placetype":"venue"
},
  "geometry": {"coordinates":[-1.271886,50.91415],"type":"Point"}
}