{
  "type": "Feature",
  "properties": {
    "addr:full":"9 Oldminster Road, Sharpness Gloucester Gloucestershire GL13 9NB",
    "addr:housenumber":"9",
    "addr:postcode":"gl13 9nb",
    "addr:street":"Oldminster Road",
    "iso:country":"GB",
    "sg:address":"9 Oldminster Road, Sharpness",
    "sg:city":"Gloucester",
    "sg:classifiers":[
        {
            "category":"Food & Beverages",
            "subcategory":"Meat & Fish",
            "type":"Retail Goods"
        }
    ],
    "sg:postcode":"GL13 9NB",
    "sg:province":"Gloucestershire",
    "sg:tags":[
        "butcher"
    ],
    "wof:name":"Peter Thomas (Shipping Contractors)",
    "wof:placetype":"venue"
},
  "geometry": {"coordinates":[-2.4697520733,51.7225875854],"type":"Point"}
}