{
  "type": "Feature",
  "properties": {
    "iso:country":"GB",
    "sg:address":"43-45 High Street",
    "sg:city":"Sevenoaks",
    "sg:classifiers":[
        {
            "category":"Professional",
            "subcategory":"Accounting & Tax Preparation",
            "type":"Services"
        },
        {
            "category":"Retail",
            "subcategory":"Auto Repair",
            "type":"Services"
        }
    ],
    "sg:postcode":"TN13 1JF",
    "sg:province":"Kent",
    "sg:tags":[
        "modification",
        "garage",
        "accountant",
        "chartered"
    ],
    "wof:name":"William Hunter",
    "wof:placetype":"venue"
},
  "geometry": {"coordinates":[0.1935929954,51.2686386108],"type":"Point"}
}