{
  "type": "Feature",
  "properties": {
    "iso:country":"GB",
    "sg:address":"Three Crosses, Clee Hill",
    "sg:city":"Ludlow",
    "sg:classifiers":[
        {
            "category":"Social Services",
            "subcategory":"Adult Care",
            "type":"Services"
        }
    ],
    "sg:phone":"+44 1584 890466",
    "sg:postcode":"SY8 3PA",
    "sg:province":"Herefordshire",
    "sg:tags":[
        "housing",
        "sheltered"
    ],
    "wof:name":"Three Crosses Old Peoples Sheltered Dwellings",
    "wof:placetype":"venue"
},
  "geometry": {"coordinates":[-2.6023840904,52.3751144409],"type":"Point"}
}