{
  "type": "Feature",
  "properties": {
    "addr:full":"Cavendish Road, Idle Bradford West Yorkshire BD10 9LE",
    "addr:postcode":"bd10 9le",
    "addr:street":"Cavendish Road",
    "iso:country":"GB",
    "sg:address":"Cavendish Road, Idle",
    "sg:city":"Bradford",
    "sg:classifiers":[
        {
            "category":"Social Services",
            "subcategory":"Child Care",
            "type":"Services"
        }
    ],
    "sg:phone":"+44 1274 613398",
    "sg:postcode":"BD10 9LE",
    "sg:province":"West Yorkshire",
    "sg:tags":[
        "children's",
        "home"
    ],
    "wof:name":"Cavendish House",
    "wof:placetype":"venue"
},
  "geometry": {"coordinates":[-1.729144,53.83247],"type":"Point"}
}