{
  "type": "Feature",
  "properties": {
    "addr:full":"Unit 2, Station Approach Carmarthen Carmarthenshire SA31 2BE",
    "addr:housenumber":"unit 2",
    "addr:postcode":"sa31 2be",
    "addr:street":"Station Approach",
    "iso:country":"GB",
    "sg:address":"Unit 2, Station Approach",
    "sg:city":"Carmarthen",
    "sg:classifiers":[
        {
            "category":"Manufacturing",
            "subcategory":"Building Materials",
            "type":"Manufacturing & Wholesale Goods"
        }
    ],
    "sg:phone":"+44 1267 220210",
    "sg:postcode":"SA31 2BE",
    "sg:province":"Carmarthenshire",
    "sg:tags":[
        "merchant",
        "builder"
    ],
    "wof:name":"REDI PLASTICS",
    "wof:placetype":"venue"
},
  "geometry": {"coordinates":[-4.306357,51.853249],"type":"Point"}
}