{
  "type": "Feature",
  "properties": {
    "addr:full":"38 St James's Street Brighton East Sussex BN2 1RG",
    "addr:housenumber":"38",
    "addr:postcode":"bn2 1rg",
    "addr:street":"St James'S Street",
    "iso:country":"GB",
    "sg:address":"38 St James's Street",
    "sg:city":"Brighton",
    "sg:classifiers":[
        {
            "category":"Shopping",
            "subcategory":"Clothing, Apparel, & Fashions",
            "type":"Retail Goods"
        }
    ],
    "sg:postcode":"BN2 1RG",
    "sg:province":"East Sussex",
    "sg:tags":[
        "menswear"
    ],
    "wof:name":"Grants",
    "wof:placetype":"venue"
},
  "geometry": {"coordinates":[-0.124216,50.823078],"type":"Point"}
}