{
  "type": "Feature",
  "properties": {
    "addr:full":"Ditton Place, Brantridge Lane, Balcombe Haywards Heath East Sussex RH17 6JR",
    "addr:postcode":"rh17 6jr",
    "addr:street":"Ditton Place Brantridge Lane",
    "iso:country":"GB",
    "sg:address":"Ditton Place, Brantridge Lane, Balcombe",
    "sg:city":"Haywards Heath",
    "sg:classifiers":[
        {
            "category":"Education",
            "subcategory":"Special Training",
            "type":"Public Place"
        },
        {
            "category":"Retail",
            "subcategory":"Event Space",
            "type":"Services"
        }
    ],
    "sg:phone":"+44 1444 400210",
    "sg:postcode":"RH17 6JR",
    "sg:province":"East Sussex",
    "sg:tags":[
        "school",
        "timeshare",
        "accommodation"
    ],
    "wof:name":"Brantridge School",
    "wof:placetype":"venue"
},
  "geometry": {"coordinates":[-0.1346240044,51.0590362549],"type":"Point"}
}