{
  "type": "Feature",
  "properties": {
    "iso:country":"GB",
    "sg:address":"Byron First School, Byron Street",
    "sg:city":"Bradford",
    "sg:classifiers":[
        {
            "category":"Organizations",
            "subcategory":"Non-profit Organization",
            "type":"Services"
        }
    ],
    "sg:phone":"+44 1274 739770",
    "sg:postcode":"BD3 0AD",
    "sg:province":"West Yorkshire",
    "sg:tags":[
        "organisation",
        "voluntary",
        "charity"
    ],
    "wof:name":"Volunteer Reading Help",
    "wof:placetype":"venue"
},
  "geometry": {"coordinates":[-1.7320100069,53.7992782593],"type":"Point"}
}