{
  "type": "Feature",
  "properties": {
    "iso:country":"GB",
    "sg:address":"College Keep, 4-12 Terminus Terr",
    "sg:city":"Southampton",
    "sg:classifiers":[
        {
            "category":"Freight",
            "type":"Transportation"
        }
    ],
    "sg:phone":"+44 23 8023 7711",
    "sg:postcode":"SO14 3QD",
    "sg:province":"Hampshire",
    "sg:tags":[
        "overseas",
        "shipping",
        "removal"
    ],
    "wof:name":"Wallenius Lines U K Ltd",
    "wof:placetype":"venue"
},
  "geometry": {"coordinates":[-1.3971799612,50.8977012634],"type":"Point"}
}