{
  "type": "Feature",
  "properties": {
    "iso:country":"GB",
    "sg:address":"Workshop 1 Bristol Craft Centre, 6 Leonard Lane",
    "sg:city":"Bristol",
    "sg:classifiers":[
        {
            "category":"Real Estate",
            "subcategory":"Architect",
            "type":"Services"
        }
    ],
    "sg:phone":"+44 117 927 2854",
    "sg:postcode":"BS1 1EA",
    "sg:province":"City of Bristol",
    "sg:tags":[
        "technologist",
        "architectural"
    ],
    "wof:name":"John Wright Setbuilding Ltd.",
    "wof:placetype":"venue"
},
  "geometry": {"coordinates":[-2.591429,51.453667],"type":"Point"}
}