{
  "type": "Feature",
  "properties": {
    "iso:country":"GB",
    "sg:address":"Le Bistro, Main Street",
    "sg:city":"Rotherham",
    "sg:classifiers":[
        {
            "category":"Restaurant",
            "type":"Food & Drink"
        }
    ],
    "sg:phone":"+44 1226 746162",
    "sg:postcode":"S62 7TL",
    "sg:province":"South Yorkshire",
    "sg:tags":[
        "french"
    ],
    "wof:name":"Finemill Restaurants Ltd",
    "wof:placetype":"venue"
},
  "geometry": {"coordinates":[-1.4160399437,53.4779701233],"type":"Point"}
}