{
  "type": "Feature",
  "properties": {
    "addr:full":"44 South Rd Erith Kent DA8 3RA",
    "addr:housenumber":"44",
    "addr:postcode":"da8 3ra",
    "addr:street":"South Rd",
    "iso:country":"GB",
    "sg:address":"44 South Rd",
    "sg:city":"Erith",
    "sg:classifiers":[
        {
            "category":"Professional",
            "subcategory":"Engineering",
            "type":"Services"
        }
    ],
    "sg:phone":"+44 1322 338388",
    "sg:postcode":"DA8 3RA",
    "sg:province":"Kent",
    "sg:tags":[
        "contractor",
        "electrical",
        "engineer"
    ],
    "wof:name":"Woodland Site Electrical Services",
    "wof:placetype":"venue"
},
  "geometry": {"coordinates":[0.1812040061,51.4753112793],"type":"Point"}
}