{
  "type": "Feature",
  "properties": {
    "addr:full":"186 Hammersmith Rd London Greater London W6 7DJ",
    "addr:housenumber":"186",
    "addr:postcode":"w6 7dj",
    "addr:street":"Hammersmith Rd",
    "iso:country":"GB",
    "sg:address":"186 Hammersmith Rd",
    "sg:city":"London",
    "sg:classifiers":[
        {
            "category":"Shopping",
            "subcategory":"Computers & Home Electronics",
            "type":"Retail Goods"
        }
    ],
    "sg:postcode":"W6 7DJ",
    "sg:province":"Greater London",
    "sg:tags":[
        "aerial",
        "television",
        "radio"
    ],
    "wof:name":"Image Television Ltd",
    "wof:placetype":"venue"
},
  "geometry": {"coordinates":[-0.2204740047,51.493270874],"type":"Point"}
}