{
  "type": "Feature",
  "properties": {
    "addr:full":"Unit 3 Shaftmoore Lane Industrial Estate, Shaftmoore Birmingham West Midlands B28 8SP",
    "addr:housenumber":"unit 3",
    "addr:postcode":"b28 8sp",
    "addr:street":"Shaftmoore Lane Industrial Estate",
    "iso:country":"GB",
    "sg:address":"Unit 3 Shaftmoore Lane Industrial Estate, Shaftmoore",
    "sg:city":"Birmingham",
    "sg:classifiers":[
        {
            "category":"Professional",
            "subcategory":"Engineering",
            "type":"Services"
        }
    ],
    "sg:postcode":"B28 8SP",
    "sg:province":"West Midlands",
    "sg:tags":[
        "engineer",
        "mechanical"
    ],
    "wof:name":"Shaftmoore Industrial Services",
    "wof:placetype":"venue"
},
  "geometry": {"coordinates":[-1.851947,52.443649],"type":"Point"}
}