{
  "type": "Feature",
  "properties": {
    "iso:country":"GB",
    "sg:address":"Norton Cuckney",
    "sg:city":"Mansfield",
    "sg:classifiers":[
        {
            "category":"Travel",
            "subcategory":"Hotels & Motels",
            "type":"Entertainment"
        }
    ],
    "sg:phone":"+44 1623 842666",
    "sg:postcode":"NG20 9LP",
    "sg:province":"Derbyshire",
    "sg:tags":[
        "house",
        "guest"
    ],
    "wof:name":"Norton Grange Farm",
    "wof:placetype":"venue"
},
  "geometry": {"coordinates":[-1.1446499825,53.2414398193],"type":"Point"}
}