{
  "type": "Feature",
  "properties": {
    "addr:full":"Community Hospital, Woodland Mews, Sedgefield Stockton-on-tees Durham TS21 3EH",
    "addr:postcode":"ts21 3eh",
    "addr:street":"Woodland Mews",
    "iso:country":"GB",
    "sg:address":"Community Hospital, Woodland Mews, Sedgefield",
    "sg:city":"Stockton-on-tees",
    "sg:classifiers":[
        {
            "category":"Health Services",
            "subcategory":"Hospital",
            "type":"Services"
        }
    ],
    "sg:postcode":"TS21 3EH",
    "sg:province":"Durham",
    "wof:name":"National Health Service Executive Headqu",
    "wof:placetype":"venue"
},
  "geometry": {"coordinates":[-1.4500739574,54.6536064148],"type":"Point"}
}