{
  "type": "Feature",
  "properties": {
    "iso:country":"GB",
    "sg:address":"Manor Farm, Carlton Road, Barton In The Beans",
    "sg:city":"Nuneaton",
    "sg:classifiers":[
        {
            "category":"Cafe",
            "type":"Food & Drink"
        },
        {
            "category":"Farming",
            "subcategory":"Farm",
            "type":"Manufacturing & Wholesale Goods"
        }
    ],
    "sg:phone":"+44 1455 290362",
    "sg:postcode":"CV13 0DE",
    "sg:province":"Leicestershire",
    "sg:tags":[
        "mixed",
        "tea",
        "room"
    ],
    "wof:name":"S W Jackson",
    "wof:placetype":"venue"
},
  "geometry": {"coordinates":[-1.409657,52.643009],"type":"Point"}
}