{
  "type": "Feature",
  "properties": {
    "addr:full":"16 Llandybie Road, Tirydail Ammanford Carmarthenshire SA18 2DW",
    "addr:housenumber":"16",
    "addr:postcode":"sa18 2dw",
    "addr:street":"Llandybie Road Tirydail",
    "iso:country":"GB",
    "sg:address":"16 Llandybie Road, Tirydail",
    "sg:city":"Ammanford",
    "sg:classifiers":[
        {
            "category":"Building & Trades",
            "subcategory":"Construction",
            "type":"Services"
        }
    ],
    "sg:postcode":"SA18 2DW",
    "sg:province":"Carmarthenshire",
    "sg:tags":[
        "roofing"
    ],
    "wof:name":"Nigel Williams",
    "wof:placetype":"venue"
},
  "geometry": {"coordinates":[-3.994459,51.797813],"type":"Point"}
}