{
  "type": "Feature",
  "properties": {
    "addr:full":"Acorn Business Centre, 30 Lawrence St York North Yorkshire YO1 3BN",
    "addr:housenumber":"30",
    "addr:postcode":"yo1 3bn",
    "addr:street":"Lawrence St York",
    "iso:country":"GB",
    "sg:address":"Acorn Business Centre, 30 Lawrence St",
    "sg:city":"York",
    "sg:classifiers":[
        {
            "category":"Professional",
            "subcategory":"Lawyer & Legal Services",
            "type":"Services"
        }
    ],
    "sg:phone":"+44 1904 673922",
    "sg:postcode":"YO1 3BN",
    "sg:province":"North Yorkshire",
    "sg:tags":[
        "advice",
        "counselling"
    ],
    "wof:name":"Davidoff-Imago",
    "wof:placetype":"venue"
},
  "geometry": {"coordinates":[-1.0813499689,53.958770752],"type":"Point"}
}