{
  "type": "Feature",
  "properties": {
    "addr:full":"501 Lees Road Oldham Lancashire OL4 3AF",
    "addr:housenumber":"501",
    "addr:postcode":"ol4 3af",
    "addr:street":"Lees Road",
    "iso:country":"GB",
    "sg:address":"501 Lees Road",
    "sg:city":"Oldham",
    "sg:classifiers":[
        {
            "category":"Food & Beverages",
            "subcategory":"Meat & Fish",
            "type":"Retail Goods"
        },
        {
            "category":"Food & Beverages",
            "subcategory":"Groceries & Convenience Stores",
            "type":"Retail Goods"
        }
    ],
    "sg:postcode":"OL4 3AF",
    "sg:province":"Lancashire",
    "sg:tags":[
        "shop",
        "chip"
    ],
    "wof:name":"The Cod Father",
    "wof:placetype":"venue"
},
  "geometry": {"coordinates":[-2.081428051,53.5379142761],"type":"Point"}
}