{
  "type": "Feature",
  "properties": {
    "addr:full":"Catherine Street, New Road, East Huntspill Highbridge Somerset TA9 3PX",
    "addr:postcode":"road;ta9 3px",
    "addr:street":"Catherine Street New",
    "iso:country":"GB",
    "sg:address":"Catherine Street, New Road, East Huntspill",
    "sg:city":"Highbridge",
    "sg:classifiers":[
        {
            "category":"Recreation",
            "subcategory":"Campground",
            "type":"Entertainment"
        }
    ],
    "sg:postcode":"TA9 3PX",
    "sg:province":"Somerset",
    "sg:tags":[
        "caravan",
        "park"
    ],
    "wof:name":"Westhill Farm Caravan Park",
    "wof:placetype":"venue"
},
  "geometry": {"coordinates":[-2.9564650059,51.2089233398],"type":"Point"}
}