{
  "type": "Feature",
  "properties": {
    "iso:country":"GB",
    "sg:address":"56 Academy Street",
    "sg:city":"Dumfries",
    "sg:classifiers":[
        {
            "category":"Real Estate",
            "subcategory":"Surveying",
            "type":"Services"
        },
        {
            "category":"Real Estate",
            "subcategory":"Architect",
            "type":"Services"
        }
    ],
    "sg:postcode":"DG1 1BZ",
    "sg:province":"Dumfries and Galloway",
    "sg:tags":[
        "surveyor",
        "quantity"
    ],
    "wof:name":"A A DUNCAN",
    "wof:placetype":"venue"
},
  "geometry": {"coordinates":[-3.610265,55.071777],"type":"Point"}
}