{
  "type": "Feature",
  "properties": {
    "addr:full":"34 Green Park Av Halifax West Yorkshire HX3 0SR",
    "addr:housenumber":"34",
    "addr:postcode":"hx3 0sr",
    "addr:street":"Green Park Av Halifax West",
    "iso:country":"GB",
    "sg:address":"34 Green Park Av",
    "sg:city":"Halifax",
    "sg:classifiers":[
        {
            "category":"Retail",
            "subcategory":"Driving School",
            "type":"Services"
        }
    ],
    "sg:phone":"+44 1422 358104",
    "sg:postcode":"HX3 0SR",
    "sg:province":"West Yorkshire",
    "wof:name":"Traffic Tuition Driving School",
    "wof:placetype":"venue"
},
  "geometry": {"coordinates":[-1.8594310284,53.702041626],"type":"Point"}
}