{
  "type": "Feature",
  "properties": {
    "iso:country":"GB",
    "sg:address":"25 Carnsmerry, Bugle",
    "sg:city":"St Austell",
    "sg:classifiers":[
        {
            "category":"Building & Trades",
            "subcategory":"Construction",
            "type":"Services"
        }
    ],
    "sg:phone":"+44 1726 851111",
    "sg:postcode":"PL26 8PX",
    "sg:province":"Cornwall",
    "sg:tags":[
        "flooring"
    ],
    "wof:name":"Charlestown Flooring Service",
    "wof:placetype":"venue"
},
  "geometry": {"coordinates":[-4.794892,50.393002],"type":"Point"}
}