{
  "type": "Feature",
  "properties": {
    "iso:country":"GB",
    "sg:address":"Estates Office, Dunecht",
    "sg:city":"Westhill",
    "sg:classifiers":[
        {
            "category":"Farming",
            "subcategory":"Farm",
            "type":"Manufacturing & Wholesale Goods"
        }
    ],
    "sg:postcode":"AB32 7AW",
    "sg:province":"Aberdeen City",
    "sg:tags":[
        "mixed",
        "crop"
    ],
    "wof:name":"Dunecht Estates",
    "wof:placetype":"venue"
},
  "geometry": {"coordinates":[-2.408744,57.171856],"type":"Point"}
}