{
  "type": "Feature",
  "properties": {
    "addr:full":"Whitley Farm, Thurlestone Kingsbridge Devon TQ7 3LW",
    "addr:housenumber":"thurlestone",
    "addr:postcode":"tq7 3lw",
    "addr:street":"Whitley;Kingsbridge Devon",
    "iso:country":"GB",
    "sg:address":"Whitley Farm, Thurlestone",
    "sg:city":"Kingsbridge",
    "sg:classifiers":[
        {
            "category":"Farming",
            "subcategory":"Livestock Farm",
            "type":"Manufacturing & Wholesale Goods"
        }
    ],
    "sg:phone":"+44 1548 560476",
    "sg:postcode":"TQ7 3LW",
    "sg:province":"Devon",
    "sg:tags":[
        "others"
    ],
    "wof:name":"W & H M Palmer Son",
    "wof:placetype":"venue"
},
  "geometry": {"coordinates":[-3.8570590019,50.2737884521],"type":"Point"}
}