{
  "type": "Feature",
  "properties": {
    "iso:country":"GB",
    "sg:address":"107 Devonshire Street",
    "sg:city":"Sheffield",
    "sg:classifiers":[
        {
            "category":"Real Estate",
            "subcategory":"Surveying",
            "type":"Services"
        }
    ],
    "sg:postcode":"S3 7SB",
    "sg:province":"South Yorkshire",
    "sg:tags":[
        "surveyor",
        "valuer"
    ],
    "wof:name":"J K Lewis",
    "wof:placetype":"venue"
},
  "geometry": {"coordinates":[-1.476643,53.37944],"type":"Point"}
}