{
  "type": "Feature",
  "properties": {
    "iso:country":"GB",
    "sg:address":"The Greys, Erriot Wood, Lynsted",
    "sg:city":"Sittingbourne",
    "sg:classifiers":[
        {
            "category":"Recreation",
            "subcategory":"Gun Range",
            "type":"Entertainment"
        }
    ],
    "sg:phone":"+44 1795 886146",
    "sg:postcode":"ME9 0JW",
    "sg:province":"Kent",
    "sg:tags":[
        "operator",
        "tour"
    ],
    "wof:name":"THEOBALD BARBER LTD",
    "wof:placetype":"venue"
},
  "geometry": {"coordinates":[0.78677,51.315521],"type":"Point"}
}