{
  "type": "Feature",
  "properties": {
    "addr:full":"372 Wigan Road, Atherton Manchester Greater Manchester M46 0QD",
    "addr:housenumber":"372",
    "addr:postcode":"m46 0qd",
    "addr:street":"Wigan Road",
    "iso:country":"GB",
    "sg:address":"372 Wigan Road, Atherton",
    "sg:city":"Manchester",
    "sg:classifiers":[
        {
            "category":"Professional",
            "subcategory":"Engineering",
            "type":"Services"
        },
        {
            "category":"Building & Trades",
            "subcategory":"Electrical",
            "type":"Services"
        }
    ],
    "sg:phone":"+44 1942 896482",
    "sg:postcode":"M46 0QD",
    "sg:province":"Greater Manchester",
    "sg:tags":[
        "engineer",
        "electrician",
        "contractor"
    ],
    "wof:name":"John Chadwick",
    "wof:placetype":"venue"
},
  "geometry": {"coordinates":[-2.5128090382,53.5222816467],"type":"Point"}
}