{
  "type": "Feature",
  "properties": {
    "addr:full":"37 Bridge Road Coalville Leicestershire LE67 3PW",
    "addr:housenumber":"37",
    "addr:postcode":"le67 3pw",
    "addr:street":"Bridge Road",
    "iso:country":"GB",
    "sg:address":"37 Bridge Road",
    "sg:city":"Coalville",
    "sg:classifiers":[
        {
            "category":"Shopping",
            "subcategory":"Bicycles & Sporting Goods",
            "type":"Retail Goods"
        },
        {
            "category":"Recreation",
            "subcategory":"Fishing",
            "type":"Entertainment"
        }
    ],
    "sg:phone":"+44 1530 815730",
    "sg:postcode":"LE67 3PW",
    "sg:province":"Leicestershire",
    "sg:tags":[
        "equipment",
        "angling"
    ],
    "wof:name":"Richards Field & Sport",
    "wof:placetype":"venue"
},
  "geometry": {"coordinates":[-1.369974,52.722233],"type":"Point"}
}