{
  "type": "Feature",
  "properties": {
    "addr:full":"56 High Street Wick Highland KW1 4BP",
    "addr:housenumber":"56",
    "addr:postcode":"kw1 4bp",
    "addr:street":"High Street",
    "iso:country":"GB",
    "sg:address":"56 High Street",
    "sg:city":"Wick",
    "sg:classifiers":[
        {
            "category":"Recreation",
            "subcategory":"Fishing",
            "type":"Entertainment"
        }
    ],
    "sg:phone":"+44 1955 604200",
    "sg:postcode":"KW1 4BP",
    "sg:province":"Highland",
    "sg:tags":[
        "angling"
    ],
    "wof:name":"Hugo Ross",
    "wof:placetype":"venue"
},
  "geometry": {"coordinates":[-3.092293,58.443031],"type":"Point"}
}