{
  "type": "Feature",
  "properties": {
    "addr:full":"Burmoor Farm, Burnmoor Lane, Egmanton Newark Nottinghamshire NG22 0HE",
    "addr:postcode":"ng22 0he",
    "addr:street":"Burnmoor Lane",
    "iso:country":"GB",
    "sg:address":"Burmoor Farm, Burnmoor Lane, Egmanton",
    "sg:city":"Newark",
    "sg:classifiers":[
        {
            "category":"Farming",
            "subcategory":"Livestock Farm",
            "type":"Manufacturing & Wholesale Goods"
        }
    ],
    "sg:postcode":"NG22 0HE",
    "sg:province":"Nottinghamshire",
    "sg:tags":[
        "others"
    ],
    "wof:name":"G Bartle",
    "wof:placetype":"venue"
},
  "geometry": {"coordinates":[-0.902663,53.211414],"type":"Point"}
}