{
  "type": "Feature",
  "properties": {
    "iso:country":"GB",
    "sg:address":"School Ho, Burnley Rd",
    "sg:city":"Accrington",
    "sg:classifiers":[
        {
            "category":"Building & Trades",
            "subcategory":"Construction",
            "type":"Services"
        }
    ],
    "sg:phone":"+44 1282 773994",
    "sg:postcode":"BB5 5UH",
    "sg:province":"Lancashire",
    "sg:tags":[
        "roofing",
        "contracting"
    ],
    "wof:name":"Bates",
    "wof:placetype":"venue"
},
  "geometry": {"coordinates":[-2.370644,53.755329],"type":"Point"}
}