{
  "type": "Feature",
  "properties": {
    "iso:country":"GB",
    "sg:address":"25 Cumberland Road",
    "sg:city":"Harrow",
    "sg:classifiers":[
        {
            "category":"Professional",
            "subcategory":"Accounting & Tax Preparation",
            "type":"Services"
        }
    ],
    "sg:postcode":"HA1 4PJ",
    "sg:province":"Greater London",
    "sg:tags":[
        "accountant"
    ],
    "wof:name":"Lakhani & Co",
    "wof:placetype":"venue"
},
  "geometry": {"coordinates":[-0.358316,51.586773],"type":"Point"}
}