{
  "type": "Feature",
  "properties": {
    "iso:country":"GB",
    "sg:address":"Unit 7-9 Portland Walk",
    "sg:city":"Barrow In Furness",
    "sg:classifiers":[
        {
            "category":"Shopping",
            "subcategory":"Department Store",
            "type":"Retail Goods"
        }
    ],
    "sg:phone":"+44 1229 871525",
    "sg:postcode":"LA14 1DB",
    "sg:province":"Cumbria",
    "wof:name":"Littlewoods",
    "wof:placetype":"venue"
},
  "geometry": {"coordinates":[-3.216602087,54.1357536316],"type":"Point"}
}