{
  "type": "Feature",
  "properties": {
    "addr:full":"39 Lancaster Grove Hampstead Greater London NW3 4HB",
    "addr:housenumber":"39",
    "addr:postcode":"nw3 4hb",
    "addr:street":"Lancaster Grove",
    "iso:country":"GB",
    "sg:address":"39 Lancaster Grove",
    "sg:city":"Hampstead",
    "sg:classifiers":[
        {
            "category":"Education",
            "subcategory":"Music School",
            "type":"Public Place"
        }
    ],
    "sg:phone":"+44 20 7431 1299",
    "sg:postcode":"NW3 4HB",
    "sg:province":"Greater London",
    "wof:name":"International Guitar",
    "wof:placetype":"venue"
},
  "geometry": {"coordinates":[-0.168572,51.546005],"type":"Point"}
}