{
  "type": "Feature",
  "properties": {
    "addr:full":"Market Street, Chapel-en-le-frith High Peak Cheshire SK23 0NT",
    "addr:postcode":"sk23 0nt",
    "addr:street":"Market Street",
    "iso:country":"GB",
    "sg:address":"Market Street, Chapel-en-le-frith",
    "sg:city":"High Peak",
    "sg:classifiers":[
        {
            "category":"Retail",
            "subcategory":"Auto Repair",
            "type":"Services"
        }
    ],
    "sg:postcode":"SK23 0NT",
    "sg:province":"Cheshire",
    "sg:tags":[
        "modification",
        "garage"
    ],
    "wof:name":"Town End Motors",
    "wof:placetype":"venue"
},
  "geometry": {"coordinates":[-1.9080690145,53.324886322],"type":"Point"}
}