{
  "type": "Feature",
  "properties": {
    "iso:country":"GB",
    "sg:address":"415 West Princes St",
    "sg:city":"Glasgow",
    "sg:classifiers":[
        {
            "category":"Retail",
            "subcategory":"Storage",
            "type":"Services"
        }
    ],
    "sg:phone":"+44 141 339 7197",
    "sg:postcode":"G4 9HF",
    "sg:province":"Glasgow City",
    "sg:tags":[
        "household",
        "removal"
    ],
    "wof:name":"Stevens Antique & Office Removals",
    "wof:placetype":"venue"
},
  "geometry": {"coordinates":[-4.2788200378,55.87317276],"type":"Point"}
}