{
  "type": "Feature",
  "properties": {
    "iso:country":"GB",
    "sg:address":"50 Hastings St",
    "sg:city":"Luton",
    "sg:classifiers":[
        {
            "category":"Real Estate",
            "subcategory":"Real Estate Agent",
            "type":"Services"
        }
    ],
    "sg:postcode":"LU1 5BE",
    "sg:province":"Bedfordshire",
    "wof:name":"Elkington,Phillip,",
    "wof:placetype":"venue"
},
  "geometry": {"coordinates":[-0.41956,51.876534],"type":"Point"}
}