{
  "type": "Feature",
  "properties": {
    "addr:full":"69 West Dyke Road Redcar North Yorkshire TS10 2AA",
    "addr:housenumber":"69",
    "addr:postcode":"ts10 2aa",
    "addr:street":"West Dyke Road",
    "iso:country":"GB",
    "sg:address":"69 West Dyke Road",
    "sg:city":"Redcar",
    "sg:classifiers":[
        {
            "category":"Food & Beverages",
            "subcategory":"Meat & Fish",
            "type":"Retail Goods"
        }
    ],
    "sg:postcode":"TS10 2AA",
    "sg:province":"North Yorkshire",
    "sg:tags":[
        "chip"
    ],
    "wof:name":"West Dyke Fisheries",
    "wof:placetype":"venue"
},
  "geometry": {"coordinates":[-1.067727,54.614353],"type":"Point"}
}