{
  "type": "Feature",
  "properties": {
    "iso:country":"GB",
    "sg:address":"69 West Dyke Road",
    "sg:city":"Redcar",
    "sg:classifiers":[
        {
            "category":"Food & Beverages",
            "subcategory":"Meat & Fish",
            "type":"Retail Goods"
        }
    ],
    "sg:postcode":"TS10 2AA",
    "sg:province":"North Yorkshire",
    "sg:tags":[
        "chip"
    ],
    "wof:name":"West Dyke Fisheries",
    "wof:placetype":"venue"
},
  "geometry": {"coordinates":[-1.067727,54.614353],"type":"Point"}
}