{
  "type": "Feature",
  "properties": {
    "addr:full":"The White House, Chantry Lane, Bishopthorpe York North Yorkshire YO23 2GF",
    "addr:postcode":"yo23 2gf",
    "addr:street":"Chantry Lane",
    "iso:country":"GB",
    "sg:address":"The White House, Chantry Lane, Bishopthorpe",
    "sg:city":"York",
    "sg:classifiers":[
        {
            "category":"Real Estate",
            "subcategory":"Surveying",
            "type":"Services"
        }
    ],
    "sg:phone":"+44 1904 700188",
    "sg:postcode":"YO23 2GF",
    "sg:province":"North Yorkshire",
    "sg:tags":[
        "surveyor",
        "quantity"
    ],
    "wof:name":"Peter G Thompson Arics",
    "wof:placetype":"venue"
},
  "geometry": {"coordinates":[-1.100947,53.920746],"type":"Point"}
}