{
  "type": "Feature",
  "properties": {
    "addr:full":"2 Barlow Close Stonehouse Gloucestershire GL10 3QP",
    "addr:housenumber":"2",
    "addr:postcode":"gl10 3qp",
    "addr:street":"Barlow Close",
    "iso:country":"GB",
    "sg:address":"2 Barlow Close",
    "sg:city":"Stonehouse",
    "sg:classifiers":[
        {
            "category":"Home & Garden",
            "subcategory":"Home Furnishings",
            "type":"Retail Goods"
        },
        {
            "category":"Home & Garden",
            "subcategory":"Carpets & Floor Coverings",
            "type":"Retail Goods"
        }
    ],
    "sg:phone":"+44 1453 825556",
    "sg:postcode":"GL10 3QP",
    "sg:province":"Gloucestershire",
    "sg:tags":[
        "fitting",
        "rug",
        "matting",
        "carpets"
    ],
    "wof:name":"Mark Hegenbarth Carpet Fitter",
    "wof:placetype":"venue"
},
  "geometry": {"coordinates":[-2.2894160748,51.7437705994],"type":"Point"}
}