{
  "type": "Feature",
  "properties": {
    "addr:full":"Summit Ho, 12 Red Lion Sq Bloomsbury Greater London WC1R 4QD",
    "addr:housenumber":"12",
    "addr:postcode":"wc1r 4qd",
    "addr:street":"Red Lion Sq",
    "iso:country":"GB",
    "sg:address":"Summit Ho, 12 Red Lion Sq",
    "sg:city":"Bloomsbury",
    "sg:classifiers":[
        {
            "category":"Social Services",
            "type":"Services"
        }
    ],
    "sg:phone":"+44 808 224 2000",
    "sg:postcode":"WC1R 4QD",
    "sg:province":"Greater London",
    "sg:tags":[
        "helplines"
    ],
    "wof:name":"National Code Change",
    "wof:placetype":"venue"
},
  "geometry": {"coordinates":[-0.119099997,51.5187797546],"type":"Point"}
}