{
  "type": "Feature",
  "properties": {
    "addr:full":"Garners House, Main St Great Bourton Banbury Northamptonshire OX17 1QU",
    "addr:postcode":"ox17 1qu",
    "addr:street":"Main St",
    "iso:country":"GB",
    "sg:address":"Garners House, Main St Great Bourton",
    "sg:city":"Banbury",
    "sg:classifiers":[
        {
            "category":"Social Services",
            "subcategory":"Job Training",
            "type":"Services"
        }
    ],
    "sg:postcode":"OX17 1QU",
    "sg:province":"Northamptonshire",
    "sg:tags":[
        "translator",
        "interpreter"
    ],
    "wof:name":"Avondale 2000 Ltd",
    "wof:placetype":"venue"
},
  "geometry": {"coordinates":[-1.3617149591,52.0915641785],"type":"Point"}
}