{
  "type": "Feature",
  "properties": {
    "iso:country":"GB",
    "sg:address":"Hallmark House, Conway Road, Mochdre",
    "sg:city":"Colwyn Bay",
    "sg:classifiers":[
        {
            "category":"Home & Garden",
            "subcategory":"Household Appliances",
            "type":"Retail Goods"
        },
        {
            "category":"Retail",
            "subcategory":"Repair Shop",
            "type":"Services"
        }
    ],
    "sg:phone":"+44 1492 544396",
    "sg:postcode":"LL28 5HN",
    "sg:province":"Conwy",
    "sg:tags":[
        "refrigerator",
        "electrical",
        "servicing",
        "freezer"
    ],
    "wof:name":"J D Refrigeration",
    "wof:placetype":"venue"
},
  "geometry": {"coordinates":[-3.7515940666,53.2988967896],"type":"Point"}
}