{
  "type": "Feature",
  "properties": {
    "iso:country":"GB",
    "sg:address":"Main St, Helperby",
    "sg:city":"York",
    "sg:classifiers":[
        {
            "category":"Food & Beverages",
            "subcategory":"Fruits & Vegetables",
            "type":"Retail Goods"
        }
    ],
    "sg:phone":"+44 1423 360685",
    "sg:postcode":"YO61 2NT",
    "sg:province":"North Yorkshire",
    "sg:tags":[
        "greengrocer"
    ],
    "wof:name":"C.W Plowman-render & Son",
    "wof:placetype":"venue"
},
  "geometry": {"coordinates":[-1.329149,54.122784],"type":"Point"}
}