{
  "type": "Feature",
  "properties": {
    "addr:full":"31 Regent Grove, Holly Walk Leamington Spa Warwickshire CV32 4NN",
    "addr:housenumber":"31",
    "addr:postcode":"cv32 4nn",
    "addr:street":"Regent Grove Holly Walk",
    "iso:country":"GB",
    "sg:address":"31 Regent Grove, Holly Walk",
    "sg:city":"Leamington Spa",
    "sg:classifiers":[
        {
            "category":"Professional",
            "subcategory":"Art Services",
            "type":"Services"
        }
    ],
    "sg:phone":"+44 1926 420220",
    "sg:postcode":"CV32 4NN",
    "sg:province":"Warwickshire",
    "sg:tags":[
        "graphic",
        "designer"
    ],
    "wof:name":"Aurora Design Associates",
    "wof:placetype":"venue"
},
  "geometry": {"coordinates":[-1.535324,52.289139],"type":"Point"}
}