{
  "type": "Feature",
  "properties": {
    "addr:full":"P O Box 68, Beeston Nottingham Nottinghamshire NG9 3NN",
    "addr:housenumber":"box 68",
    "addr:postcode":"ng9 3nn",
    "addr:street":"P O",
    "iso:country":"GB",
    "sg:address":"P O Box 68, Beeston",
    "sg:city":"Nottingham",
    "sg:classifiers":[
        {
            "category":"Education",
            "subcategory":"Special Training",
            "type":"Public Place"
        }
    ],
    "sg:phone":"+44 115 922 1198",
    "sg:postcode":"NG9 3NN",
    "sg:province":"Nottinghamshire",
    "sg:tags":[
        "product",
        "centre"
    ],
    "wof:name":"A P L D",
    "wof:placetype":"venue"
},
  "geometry": {"coordinates":[-1.25725,52.94746],"type":"Point"}
}