{
  "type": "Feature",
  "properties": {
    "addr:full":"Market Hall, 65 South Pde Sutton Coldfield West Midlands B72 1QU",
    "addr:housenumber":"65",
    "addr:postcode":"b72 1qu",
    "addr:street":"South Pde",
    "iso:country":"GB",
    "sg:address":"Market Hall, 65 South Pde",
    "sg:city":"Sutton Coldfield",
    "sg:classifiers":[
        {
            "category":"Food & Beverages",
            "subcategory":"Meat & Fish",
            "type":"Retail Goods"
        }
    ],
    "sg:phone":"+44 121 355 3187",
    "sg:postcode":"B72 1QU",
    "sg:province":"West Midlands",
    "sg:tags":[
        "butcher"
    ],
    "wof:name":"Sutton Quality Meats",
    "wof:placetype":"venue"
},
  "geometry": {"coordinates":[-1.82318,52.562199],"type":"Point"}
}