{
  "type": "Feature",
  "properties": {
    "addr:full":"Unit 7a-7c Stockton Close, Minworth Industrial Park Sutton Coldfield Warwickshire B76 1DH",
    "addr:housenumber":"7a-7c",
    "addr:postcode":"b76 1dh",
    "addr:street":"Stockton Close;Industrial Park",
    "iso:country":"GB",
    "sg:address":"Unit 7a-7c Stockton Close, Minworth Industrial Park",
    "sg:city":"Sutton Coldfield",
    "sg:classifiers":[
        {
            "category":"Organizations",
            "subcategory":"Community Association",
            "type":"Services"
        }
    ],
    "sg:phone":"+44 121 313 5421",
    "sg:postcode":"B76 1DH",
    "sg:province":"Warwickshire",
    "sg:tags":[
        "emblem",
        "badge"
    ],
    "wof:name":"3M Minworth",
    "wof:placetype":"venue"
},
  "geometry": {"coordinates":[-1.7789520025,52.5308570862],"type":"Point"}
}