{
  "type": "Feature",
  "properties": {
    "addr:full":"7 Beeches Close Brierley Hill Staffordshire DY6 8ES",
    "addr:housenumber":"7",
    "addr:postcode":"dy6 8es",
    "addr:street":"Beeches Close Brierley Hill",
    "iso:country":"GB",
    "sg:address":"7 Beeches Close",
    "sg:city":"Brierley Hill",
    "sg:classifiers":[
        {
            "category":"Professional",
            "subcategory":"Management & Consulting",
            "type":"Services"
        }
    ],
    "sg:phone":"+44 1384 74624",
    "sg:postcode":"DY6 8ES",
    "sg:province":"Staffordshire",
    "sg:tags":[
        "fire",
        "consultant",
        "protection"
    ],
    "wof:name":"Hazard Design Ltd.",
    "wof:placetype":"venue"
},
  "geometry": {"coordinates":[-2.16509,52.492619],"type":"Point"}
}