{
  "type": "Feature",
  "properties": {
    "addr:full":"Wellington Rd Macclesfield Cheshire SK10 5JR",
    "addr:postcode":"sk10 5jr",
    "addr:street":"Wellington Rd",
    "iso:country":"GB",
    "sg:address":"Wellington Rd",
    "sg:city":"Macclesfield",
    "sg:classifiers":[
        {
            "category":"Place Of Worship",
            "type":"Public Place"
        }
    ],
    "sg:phone":"+44 1625 572259",
    "sg:postcode":"SK10 5JR",
    "sg:province":"Cheshire",
    "wof:name":"Bollington Methodist Church",
    "wof:placetype":"venue"
},
  "geometry": {"coordinates":[-2.1042890549,53.2981452942],"type":"Point"}
}