{
  "type": "Feature",
  "properties": {
    "addr:full":"College Avenue, Staveley Chesterfield Derbyshire S43 3JJ",
    "addr:postcode":"s43 3jj",
    "addr:street":"College Avenue",
    "iso:country":"GB",
    "sg:address":"College Avenue, Staveley",
    "sg:city":"Chesterfield",
    "sg:classifiers":[
        {
            "category":"Education",
            "subcategory":"School",
            "type":"Public Place"
        }
    ],
    "sg:phone":"+44 1246 472336",
    "sg:postcode":"S43 3JJ",
    "sg:province":"Derbyshire",
    "sg:tags":[
        "local",
        "authority"
    ],
    "wof:name":"Speedwell Infants School",
    "wof:placetype":"venue"
},
  "geometry": {"coordinates":[-1.357264,53.264664],"type":"Point"}
}