{
  "type": "Feature",
  "properties": {
    "iso:country":"GB",
    "sg:address":"13 Headlands",
    "sg:city":"Kettering",
    "sg:classifiers":[
        {
            "category":"Professional",
            "subcategory":"Computer Services",
            "type":"Services"
        }
    ],
    "sg:phone":"+44 1536 512526",
    "sg:postcode":"NN15 7ER",
    "sg:province":"Northamptonshire",
    "sg:tags":[
        "system",
        "software"
    ],
    "wof:name":"SOFTWARE TRAINING & SUPPORT",
    "wof:placetype":"venue"
},
  "geometry": {"coordinates":[-0.727571,52.394371],"type":"Point"}
}