{
  "type": "Feature",
  "properties": {
    "addr:full":"10 Jackson Avenue Ilkeston Derbyshire DE7 8AD",
    "addr:housenumber":"10",
    "addr:postcode":"de7 8ad",
    "addr:street":"Jackson Avenue",
    "iso:country":"GB",
    "sg:address":"10 Jackson Avenue",
    "sg:city":"Ilkeston",
    "sg:classifiers":[
        {
            "category":"Building & Trades",
            "subcategory":"Construction",
            "type":"Services"
        }
    ],
    "sg:phone":"+44 115 944 4282",
    "sg:postcode":"DE7 8AD",
    "sg:province":"Derbyshire",
    "sg:tags":[
        "builder"
    ],
    "wof:name":"Raeside Building & Joinery",
    "wof:placetype":"venue"
},
  "geometry": {"coordinates":[-1.311218,52.972694],"type":"Point"}
}