{
  "type": "Feature",
  "properties": {
    "addr:full":"30 Alamein Avenue Chatham Kent ME5 0HZ",
    "addr:housenumber":"30",
    "addr:postcode":"me5 0hz",
    "addr:street":"Alamein Avenue",
    "iso:country":"GB",
    "sg:address":"30 Alamein Avenue",
    "sg:city":"Chatham",
    "sg:classifiers":[
        {
            "category":"Military Area",
            "subcategory":"Air Force Base",
            "type":"Public Place"
        }
    ],
    "sg:phone":"+44 1634 848820",
    "sg:postcode":"ME5 0HZ",
    "sg:province":"Kent",
    "sg:tags":[
        "water",
        "treatment"
    ],
    "wof:name":"Cascade Water Softners",
    "wof:placetype":"venue"
},
  "geometry": {"coordinates":[0.521924,51.357582],"type":"Point"}
}