{
  "type": "Feature",
  "properties": {
    "iso:country":"GB",
    "sg:address":"53 London Road",
    "sg:city":"Liverpool",
    "sg:classifiers":[
        {
            "category":"Shopping",
            "subcategory":"Bicycles & Sporting Goods",
            "type":"Retail Goods"
        },
        {
            "category":"Arts & Performance",
            "subcategory":"Theater",
            "type":"Entertainment"
        }
    ],
    "sg:phone":"+44 151 298 1905",
    "sg:postcode":"L3 8HY",
    "sg:province":"Merseyside",
    "sg:tags":[
        "dance",
        "dancewear",
        "ballet",
        "balletwear"
    ],
    "wof:name":"That's Entertainment Dancewear",
    "wof:placetype":"venue"
},
  "geometry": {"coordinates":[-2.976349,53.409309],"type":"Point"}
}