{
  "type": "Feature",
  "properties": {
    "addr:full":"Brownsover Community First School, Webb Drive Rugby Northamptonshire CV23 0UP",
    "addr:postcode":"cv23 0up",
    "addr:street":"Webb Drive",
    "iso:country":"GB",
    "sg:address":"Brownsover Community First School, Webb Drive",
    "sg:city":"Rugby",
    "sg:classifiers":[
        {
            "category":"Education",
            "subcategory":"School",
            "type":"Public Place"
        }
    ],
    "sg:phone":"+44 1788 547660",
    "sg:postcode":"CV23 0UP",
    "sg:province":"Northamptonshire",
    "sg:tags":[
        "local",
        "authority"
    ],
    "sg:website":"http://www.2616.wgfl.net",
    "wof:name":"Brownsover Community School",
    "wof:placetype":"venue"
},
  "geometry": {"coordinates":[-1.2413779497,52.3948898315],"type":"Point"}
}