{
  "type": "Feature",
  "properties": {
    "iso:country":"GB",
    "sg:address":"Minster Rd",
    "sg:city":"Stourport On Severn",
    "sg:classifiers":[
        {
            "category":"Utilities",
            "subcategory":"Refuse",
            "type":"Services"
        }
    ],
    "sg:phone":"+44 1299 826736",
    "sg:postcode":"DY13 8AB",
    "sg:province":"Worcestershire",
    "sg:tags":[
        "disposal",
        "waste"
    ],
    "wof:name":"Waste Disposal Services",
    "wof:placetype":"venue"
},
  "geometry": {"coordinates":[-2.275364,52.346519],"type":"Point"}
}