{
  "type": "Feature",
  "properties": {
    "iso:country":"GB",
    "sg:address":"21a Forrester Park Drive",
    "sg:city":"Edinburgh",
    "sg:classifiers":[
        {
            "category":"Health Services",
            "subcategory":"Health Practitioner",
            "type":"Services"
        }
    ],
    "sg:phone":"+44 131 334 9784",
    "sg:postcode":"EH12 9AT",
    "sg:province":"City of Edinburgh",
    "sg:tags":[
        "hypnotherapists"
    ],
    "wof:name":"Wyn-Davies G Consultant Hypnotherapist Anylist",
    "wof:placetype":"venue"
},
  "geometry": {"coordinates":[-3.280408,55.931938],"type":"Point"}
}