{
  "type": "Feature",
  "properties": {
    "iso:country":"GB",
    "sg:address":"Horizon Poultry Farm, Tremar",
    "sg:city":"Liskeard",
    "sg:classifiers":[
        {
            "category":"Farming",
            "subcategory":"Poultry Farm",
            "type":"Manufacturing & Wholesale Goods"
        }
    ],
    "sg:phone":"+44 1579 345938",
    "sg:postcode":"PL14 6EA",
    "sg:province":"Cornwall",
    "sg:tags":[
        "game",
        "farmer"
    ],
    "wof:name":"Clifford Kent Holdings Ltd",
    "wof:placetype":"venue"
},
  "geometry": {"coordinates":[-4.465834,50.453796],"type":"Point"}
}