{
  "type": "Feature",
  "properties": {
    "addr:full":"21 Bracken Road, North Baddesley Southampton Hampshire SO52 9FP",
    "addr:housenumber":"21",
    "addr:postcode":"so52 9fp",
    "addr:street":"Bracken Road",
    "iso:country":"GB",
    "sg:address":"21 Bracken Road, North Baddesley",
    "sg:city":"Southampton",
    "sg:classifiers":[
        {
            "category":"Retail",
            "subcategory":"Auto Rental",
            "type":"Services"
        }
    ],
    "sg:phone":"+44 23 8066 6556",
    "sg:postcode":"SO52 9FP",
    "sg:province":"Hampshire",
    "sg:tags":[
        "car"
    ],
    "wof:name":"J E E Self Drive",
    "wof:placetype":"venue"
},
  "geometry": {"coordinates":[-1.4426239729,50.9715080261],"type":"Point"}
}