{
  "type": "Feature",
  "properties": {
    "addr:full":"Hillidge Road Leeds West Yorkshire LS10 1BP",
    "addr:postcode":"ls10 1bp",
    "addr:street":"Hillidge Road",
    "iso:country":"GB",
    "sg:address":"Hillidge Road",
    "sg:city":"Leeds",
    "sg:classifiers":[
        {
            "category":"Community Center",
            "subcategory":"Youth",
            "type":"Public Place"
        }
    ],
    "sg:phone":"+44 113 276 5720",
    "sg:postcode":"LS10 1BP",
    "sg:province":"West Yorkshire",
    "sg:tags":[
        "organisation",
        "centre"
    ],
    "wof:name":"Hunslet Boys Club",
    "wof:placetype":"venue"
},
  "geometry": {"coordinates":[-1.5346640348,53.7821807861],"type":"Point"}
}