{
  "type": "Feature",
  "properties": {
    "addr:full":"1a The Old Grammar, Old Grammar Lane Bungay Norfolk NR35 1PU",
    "addr:housenumber":"1a",
    "addr:postcode":"nr35 1pu",
    "addr:street":"The;Grammar Lane",
    "iso:country":"GB",
    "sg:address":"1a The Old Grammar, Old Grammar Lane",
    "sg:city":"Bungay",
    "sg:classifiers":[
        {
            "category":"Social Services",
            "subcategory":"Adult Care",
            "type":"Services"
        }
    ],
    "sg:phone":"+44 1986 892873",
    "sg:postcode":"NR35 1PU",
    "sg:province":"Norfolk",
    "sg:tags":[
        "housing",
        "sheltered"
    ],
    "wof:name":"H A & G W Read",
    "wof:placetype":"venue"
},
  "geometry": {"coordinates":[1.4437090158,52.4499702454],"type":"Point"}
}