{
  "type": "Feature",
  "properties": {
    "addr:full":"Fferm Pwll Iwrch, Darowen Machynlleth Ceredigion SY20 8NS",
    "addr:postcode":"sy20 8ns",
    "iso:country":"GB",
    "sg:address":"Fferm Pwll Iwrch, Darowen",
    "sg:city":"Machynlleth",
    "sg:classifiers":[
        {
            "category":"Farming",
            "subcategory":"Livestock Farm",
            "type":"Manufacturing & Wholesale Goods"
        }
    ],
    "sg:phone":"+44 1650 511379",
    "sg:postcode":"SY20 8NS",
    "sg:province":"Ceredigion",
    "sg:tags":[
        "others"
    ],
    "wof:name":"J A Jones",
    "wof:placetype":"venue"
},
  "geometry": {"coordinates":[-3.8467230797,52.5909614563],"type":"Point"}
}