{
  "type": "Feature",
  "properties": {
    "addr:full":"Hick Lane, Mills Bradford Road Batley West Yorkshire WF17 5LY",
    "addr:postcode":"wf17 5ly",
    "addr:street":"Hick Lane;Bradford Road",
    "iso:country":"GB",
    "sg:address":"Hick Lane, Mills Bradford Road",
    "sg:city":"Batley",
    "sg:classifiers":[
        {
            "category":"Museum",
            "subcategory":"Art Museum",
            "type":"Entertainment"
        }
    ],
    "sg:postcode":"WF17 5LY",
    "sg:province":"West Yorkshire",
    "sg:tags":[
        "gallery"
    ],
    "wof:name":"B J R Framing",
    "wof:placetype":"venue"
},
  "geometry": {"coordinates":[-1.627886,53.712318],"type":"Point"}
}