{
  "type": "Feature",
  "properties": {
    "iso:country":"GB",
    "sg:address":"Unit 6 Fourth Ct, Bridge Rd",
    "sg:city":"Leeds",
    "sg:classifiers":[
        {
            "category":"Building & Trades",
            "subcategory":"Plumbing",
            "type":"Services"
        }
    ],
    "sg:phone":"+44 113 243 6555",
    "sg:postcode":"LS11 9UG",
    "sg:province":"West Yorkshire",
    "sg:tags":[
        "central",
        "heating"
    ],
    "wof:name":"A & M Harland Plumbing & Heating",
    "wof:placetype":"venue"
},
  "geometry": {"coordinates":[-1.559169054,53.7888412476],"type":"Point"}
}