{
  "type": "Feature",
  "properties": {
    "iso:country":"GB",
    "sg:address":"171 Rochdale Rd",
    "sg:city":"Bury",
    "sg:classifiers":[
        {
            "category":"Fast Food",
            "type":"Food & Drink"
        }
    ],
    "sg:postcode":"BL9 7BB",
    "sg:province":"Lancashire",
    "sg:tags":[
        "away",
        "take"
    ],
    "wof:name":"Ilyas,K,",
    "wof:placetype":"venue"
},
  "geometry": {"coordinates":[-2.283675909,53.5929489136],"type":"Point"}
}