{
  "type": "Feature",
  "properties": {
    "iso:country":"GB",
    "sg:address":"Blackburn Technology Management Centre, Challenge Way",
    "sg:city":"Blackburn",
    "sg:classifiers":[
        {
            "category":"Manufacturing",
            "subcategory":"Wood Products",
            "type":"Manufacturing & Wholesale Goods"
        }
    ],
    "sg:phone":"+44 1254 279992",
    "sg:postcode":"BB1 5QB",
    "sg:province":"Lancashire",
    "sg:tags":[
        "packaging",
        "crate",
        "pallets"
    ],
    "wof:name":"M B Aseptic Technology Ltd",
    "wof:placetype":"venue"
},
  "geometry": {"coordinates":[-2.480399,53.748516],"type":"Point"}
}