{
  "type": "Feature",
  "properties": {
    "addr:full":"Bryant House, Manchester Rd Exmouth Devon EX8 1DE",
    "addr:postcode":"ex8 1de",
    "addr:street":"Manchester Rd",
    "iso:country":"GB",
    "sg:address":"Bryant House, Manchester Rd",
    "sg:city":"Exmouth",
    "sg:classifiers":[
        {
            "category":"Professional",
            "subcategory":"Detective & Security Services",
            "type":"Services"
        }
    ],
    "sg:phone":"+44 1395 275318",
    "sg:postcode":"EX8 1DE",
    "sg:province":"Devon",
    "wof:name":"Exe-sec International Ltd",
    "wof:placetype":"venue"
},
  "geometry": {"coordinates":[-3.4157431126,50.6200447083],"type":"Point"}
}