{
  "type": "Feature",
  "properties": {
    "addr:full":"137 Cavendish Road Blackpool Lancashire FY2 9EG",
    "addr:housenumber":"137",
    "addr:postcode":"fy2 9eg",
    "addr:street":"Cavendish Road",
    "iso:country":"GB",
    "sg:address":"137 Cavendish Road",
    "sg:city":"Blackpool",
    "sg:classifiers":[
        {
            "category":"Building & Trades",
            "subcategory":"Plumbing",
            "type":"Services"
        }
    ],
    "sg:phone":"+44 1253 829753",
    "sg:postcode":"FY2 9EG",
    "sg:province":"Lancashire",
    "sg:tags":[
        "heating"
    ],
    "wof:name":"Stuart Hinchcliffe",
    "wof:placetype":"venue"
},
  "geometry": {"coordinates":[-3.0461850166,53.8500785828],"type":"Point"}
}