{
  "type": "Feature",
  "properties": {
    "addr:full":"57 Victoria Rd Aberdeen Aberdeen City AB11 9LT",
    "addr:housenumber":"57",
    "addr:postcode":"ab11 9lt",
    "addr:street":"Victoria Rd",
    "iso:country":"GB",
    "sg:address":"57 Victoria Rd",
    "sg:city":"Aberdeen",
    "sg:classifiers":[
        {
            "category":"Health Services",
            "subcategory":"Dentist",
            "type":"Services"
        }
    ],
    "sg:phone":"+44 1224 879043",
    "sg:postcode":"AB11 9LT",
    "sg:province":"Aberdeen City",
    "wof:name":"A.C Adam",
    "wof:placetype":"venue"
},
  "geometry": {"coordinates":[-2.0882771015,57.1382026672],"type":"Point"}
}