{
  "type": "Feature",
  "properties": {
    "iso:country":"GB",
    "sg:address":"13 Shearwater Road, Offerton",
    "sg:city":"Stockport",
    "sg:classifiers":[
        {
            "category":"Professional",
            "subcategory":"Engineering",
            "type":"Services"
        },
        {
            "category":"Real Estate",
            "subcategory":"Architect",
            "type":"Services"
        }
    ],
    "sg:phone":"+44 161 456 9807",
    "sg:postcode":"SK2 5UY",
    "sg:province":"Cheshire",
    "sg:tags":[
        "consulting",
        "engineer"
    ],
    "wof:name":"Starkie Engineering Services Ltd.",
    "wof:placetype":"venue"
},
  "geometry": {"coordinates":[-2.1007730961,53.3935966492],"type":"Point"}
}