{
  "type": "Feature",
  "properties": {
    "addr:full":"14 West St Tavistock Devon PL19 8AD",
    "addr:housenumber":"14",
    "addr:postcode":"pl19 8ad",
    "addr:street":"West St",
    "iso:country":"GB",
    "sg:address":"14 West St",
    "sg:city":"Tavistock",
    "sg:classifiers":[
        {
            "category":"Home & Garden",
            "subcategory":"Furniture",
            "type":"Retail Goods"
        }
    ],
    "sg:phone":"+44 1822 618840",
    "sg:postcode":"PL19 8AD",
    "sg:province":"Devon",
    "wof:name":"Michael Antonoucci",
    "wof:placetype":"venue"
},
  "geometry": {"coordinates":[-4.147103,50.549423],"type":"Point"}
}