{
  "type": "Feature",
  "properties": {
    "iso:country":"GB",
    "sg:address":"121 Nuxley Rd",
    "sg:city":"Belvedere",
    "sg:classifiers":[
        {
            "category":"Professional",
            "type":"Services"
        }
    ],
    "sg:postcode":"DA17 5JX",
    "sg:province":"Kent",
    "sg:tags":[
        "directory",
        "pub"
    ],
    "wof:name":"Wells,John,",
    "wof:placetype":"venue"
},
  "geometry": {"coordinates":[0.143739,51.4800071716],"type":"Point"}
}