{
  "type": "Feature",
  "properties": {
    "iso:country":"GB",
    "sg:address":"Unit 1 & 2 Q M Indstl Est, The Drift, Nacton Rd",
    "sg:city":"Ipswich",
    "sg:classifiers":[
        {
            "category":"Building & Trades",
            "subcategory":"Construction",
            "type":"Services"
        }
    ],
    "sg:phone":"+44 1473 729920",
    "sg:postcode":"IP3 9QR",
    "sg:province":"Suffolk",
    "sg:tags":[
        "joinery"
    ],
    "wof:name":"Anglia Timber Trades Ltd",
    "wof:placetype":"venue"
},
  "geometry": {"coordinates":[1.1978299618,52.034740448],"type":"Point"}
}