{
  "type": "Feature",
  "properties": {
    "iso:country":"GB",
    "sg:address":"49 Thingwall Park",
    "sg:city":"Bristol",
    "sg:classifiers":[
        {
            "category":"Communications",
            "subcategory":"Film & Video Production",
            "type":"Services"
        },
        {
            "category":"Communications",
            "type":"Services"
        }
    ],
    "sg:phone":"+44 117 958 3112",
    "sg:postcode":"BS16 2AJ",
    "sg:province":"City of Bristol",
    "sg:tags":[
        "tv",
        "broadcasting",
        "studio"
    ],
    "wof:name":"B J Associates",
    "wof:placetype":"venue"
},
  "geometry": {"coordinates":[-2.546119,51.475571],"type":"Point"}
}