{
  "type": "Feature",
  "properties": {
    "addr:full":"44 Wythburn Crescent St Helens Lancashire WA11 7HF",
    "addr:housenumber":"44",
    "addr:postcode":"wa11 7hf",
    "addr:street":"Wythburn Crescent",
    "iso:country":"GB",
    "sg:address":"44 Wythburn Crescent",
    "sg:city":"St Helens",
    "sg:classifiers":[
        {
            "category":"Shopping",
            "subcategory":"News",
            "type":"Retail Goods"
        }
    ],
    "sg:phone":"+44 1744 758184",
    "sg:postcode":"WA11 7HF",
    "sg:province":"Lancashire",
    "sg:tags":[
        "newsagent"
    ],
    "wof:name":"Bob's News",
    "wof:placetype":"venue"
},
  "geometry": {"coordinates":[-2.7227010727,53.475063324],"type":"Point"}
}