{
  "type": "Feature",
  "properties": {
    "iso:country":"GB",
    "sg:address":"40 Briton Ferry Rd",
    "sg:city":"Neath",
    "sg:classifiers":[
        {
            "category":"Food & Beverages",
            "subcategory":"Groceries & Convenience Stores",
            "type":"Retail Goods"
        }
    ],
    "sg:phone":"+44 1639 633366",
    "sg:postcode":"SA11 1AA",
    "sg:province":"Neath Port Talbot",
    "sg:tags":[
        "merchant",
        "potato"
    ],
    "wof:name":"John Bater",
    "wof:placetype":"venue"
},
  "geometry": {"coordinates":[-3.806715,51.656204],"type":"Point"}
}