{
  "type": "Feature",
  "properties": {
    "addr:full":"Rushey Cottage, Back Bury Road South Breighmet Bolton Lancashire BL2 6JE",
    "addr:postcode":"bl2 6je",
    "addr:street":"Back Bury Road South",
    "iso:country":"GB",
    "sg:address":"Rushey Cottage, Back Bury Road South Breighmet",
    "sg:city":"Bolton",
    "sg:classifiers":[
        {
            "category":"Military Area",
            "subcategory":"Army Base",
            "type":"Public Place"
        }
    ],
    "sg:postcode":"BL2 6JE",
    "sg:province":"Lancashire",
    "sg:tags":[
        "mnfr",
        "printed",
        "circuit"
    ],
    "wof:name":"R. F. Machinery Ltd",
    "wof:placetype":"venue"
},
  "geometry": {"coordinates":[-2.397344,53.580479],"type":"Point"}
}