{
  "type": "Feature",
  "properties": {
    "iso:country":"GB",
    "sg:address":"45 North Hill",
    "sg:city":"Plymouth",
    "sg:classifiers":[
        {
            "category":"Education",
            "subcategory":"Special Training",
            "type":"Public Place"
        }
    ],
    "sg:phone":"+44 1752 255054",
    "sg:postcode":"PL4 8EZ",
    "sg:province":"Devon",
    "sg:tags":[
        "product",
        "centre"
    ],
    "wof:name":"Future Training (Secretarial Computer) Centre",
    "wof:placetype":"venue"
},
  "geometry": {"coordinates":[-4.136326,50.376842],"type":"Point"}
}