{
  "type": "Feature",
  "properties": {
    "addr:full":"87 Queens Way, Petts Wood Orpington Kent BR5 1DQ",
    "addr:housenumber":"87",
    "addr:postcode":"br5 1dq",
    "addr:street":"Queens Way",
    "iso:country":"GB",
    "sg:address":"87 Queens Way, Petts Wood",
    "sg:city":"Orpington",
    "sg:classifiers":[
        {
            "category":"Building & Trades",
            "subcategory":"Construction",
            "type":"Services"
        }
    ],
    "sg:phone":"+44 1689 860921",
    "sg:postcode":"BR5 1DQ",
    "sg:province":"Kent",
    "sg:tags":[
        "builder"
    ],
    "wof:name":"M Denbigh",
    "wof:placetype":"venue"
},
  "geometry": {"coordinates":[0.072637,51.388775],"type":"Point"}
}