{
  "type": "Feature",
  "properties": {
    "iso:country":"GB",
    "sg:address":"42 Bluebell Road, Walsall Wood",
    "sg:city":"Walsall",
    "sg:classifiers":[
        {
            "category":"Professional",
            "subcategory":"Computer Services",
            "type":"Services"
        }
    ],
    "sg:phone":"+44 1543 454111",
    "sg:postcode":"WS9 9EU",
    "sg:province":"Staffordshire",
    "sg:tags":[
        "system",
        "software"
    ],
    "wof:name":"Image Forms Ltd.",
    "wof:placetype":"venue"
},
  "geometry": {"coordinates":[-1.915948,52.626606],"type":"Point"}
}