{
  "type": "Feature",
  "properties": {
    "addr:full":"26 Spring Gardens Buxton Derbyshire SK17 6DE",
    "addr:housenumber":"26",
    "addr:postcode":"sk17 6de",
    "addr:street":"Spring Gardens",
    "iso:country":"GB",
    "sg:address":"26 Spring Gardens",
    "sg:city":"Buxton",
    "sg:classifiers":[
        {
            "category":"Shopping",
            "subcategory":"Thrift Store",
            "type":"Retail Goods"
        }
    ],
    "sg:phone":"+44 1298 27085",
    "sg:postcode":"SK17 6DE",
    "sg:province":"Derbyshire",
    "sg:tags":[
        "shop",
        "charity"
    ],
    "wof:name":"Imperial Cancer Research Fund",
    "wof:placetype":"venue"
},
  "geometry": {"coordinates":[-1.9123100042,53.2588920593],"type":"Point"}
}