{
  "type": "Feature",
  "properties": {
    "iso:country":"GB",
    "sg:address":"Main Rd",
    "sg:city":"Salisbury",
    "sg:classifiers":[
        {
            "category":"Place Of Worship",
            "type":"Public Place"
        }
    ],
    "sg:phone":"+44 1980 611274",
    "sg:postcode":"SP4 6EW",
    "sg:province":"Hampshire",
    "wof:name":"Bourne Valley Methodist Church",
    "wof:placetype":"venue"
},
  "geometry": {"coordinates":[-1.758464,51.167068],"type":"Point"}
}