{
  "type": "Feature",
  "properties": {
    "addr:full":"2 Firfield Road, Addlestone Weybridge Surrey KT15 1QU",
    "addr:housenumber":"2",
    "addr:postcode":"kt15 1qu",
    "addr:street":"Firfield Road;Weybridge",
    "iso:country":"GB",
    "sg:address":"2 Firfield Road, Addlestone",
    "sg:city":"Weybridge",
    "sg:classifiers":[
        {
            "category":"Building & Trades",
            "subcategory":"Construction",
            "type":"Services"
        }
    ],
    "sg:postcode":"KT15 1QU",
    "sg:province":"Surrey",
    "sg:tags":[
        "builder"
    ],
    "wof:name":"Gillian & Malcolm Coker",
    "wof:placetype":"venue"
},
  "geometry": {"coordinates":[-0.500874,51.372124],"type":"Point"}
}