{
  "type": "Feature",
  "properties": {
    "addr:full":"132 High Street Tillicoultry Clackmannanshire FK13 6DU",
    "addr:housenumber":"132",
    "addr:postcode":"fk13 6du",
    "addr:street":"High Street",
    "iso:country":"GB",
    "sg:address":"132 High Street",
    "sg:city":"Tillicoultry",
    "sg:classifiers":[
        {
            "category":"Bars & Pubs",
            "type":"Food & Drink"
        },
        {
            "category":"Community Center",
            "subcategory":"Social",
            "type":"Public Place"
        }
    ],
    "sg:phone":"+44 1259 750368",
    "sg:postcode":"FK13 6DU",
    "sg:province":"Clackmannanshire",
    "sg:tags":[
        "pubs",
        "house",
        "inn",
        "activity"
    ],
    "wof:name":"The Volunteer Arms",
    "wof:placetype":"venue"
},
  "geometry": {"coordinates":[-3.741157,56.153305],"type":"Point"}
}