{
  "type": "Feature",
  "properties": {
    "addr:full":"Regents House, Queen Street Amlwch Isle of Anglesey LL68 9AE",
    "addr:postcode":"ll68 9ae",
    "addr:street":"Queen Street",
    "iso:country":"GB",
    "sg:address":"Regents House, Queen Street",
    "sg:city":"Amlwch",
    "sg:classifiers":[
        {
            "category":"Food & Beverages",
            "subcategory":"Meat & Fish",
            "type":"Retail Goods"
        }
    ],
    "sg:phone":"+44 1407 830622",
    "sg:postcode":"LL68 9AE",
    "sg:province":"Isle of Anglesey",
    "sg:tags":[
        "butcher"
    ],
    "wof:name":"E Roberts & Son",
    "wof:placetype":"venue"
},
  "geometry": {"coordinates":[-4.3451538086,53.409488678],"type":"Point"}
}