{
  "type": "Feature",
  "properties": {
    "addr:full":"Mill Lane, Wyre Piddle Pershore Worcestershire WR10 2JF",
    "addr:postcode":"wr10 2jf",
    "addr:street":"Mill Lane",
    "iso:country":"GB",
    "sg:address":"Mill Lane, Wyre Piddle",
    "sg:city":"Pershore",
    "sg:classifiers":[
        {
            "category":"Arena",
            "subcategory":"Sports Club",
            "type":"Entertainment"
        }
    ],
    "sg:phone":"+44 1386 554105",
    "sg:postcode":"WR10 2JF",
    "sg:province":"Worcestershire",
    "wof:name":"Pershore Rugby Football Club",
    "wof:placetype":"venue"
},
  "geometry": {"coordinates":[-2.1154239178,52.1350898743],"type":"Point"}
}