{
  "type": "Feature",
  "properties": {
    "addr:full":"Broadway West York North Yorkshire YO10 4JJ",
    "addr:postcode":"yo10 4jj",
    "addr:street":"Broadway West",
    "iso:country":"GB",
    "sg:address":"Broadway West",
    "sg:city":"York",
    "sg:classifiers":[
        {
            "category":"Health Services",
            "subcategory":"Health Practitioner",
            "type":"Services"
        }
    ],
    "sg:phone":"+44 1904 621866",
    "sg:postcode":"YO10 4JJ",
    "sg:province":"North Yorkshire",
    "sg:tags":[
        "hypnotherapists"
    ],
    "wof:name":"York Counselling & Hypnotherapy Clinic For Women",
    "wof:placetype":"venue"
},
  "geometry": {"coordinates":[-1.0697239637,53.9411849976],"type":"Point"}
}