{
  "type": "Feature",
  "properties": {
    "addr:full":"Newgate Farm, Newgate Lane, Whitestake Preston Lancashire PR4 4JU",
    "addr:postcode":"pr4 4ju",
    "addr:street":"Newgate;Newgate Lane",
    "iso:country":"GB",
    "sg:address":"Newgate Farm, Newgate Lane, Whitestake",
    "sg:city":"Preston",
    "sg:classifiers":[
        {
            "category":"Food & Beverages",
            "subcategory":"Farmers Market",
            "type":"Retail Goods"
        }
    ],
    "sg:postcode":"PR4 4JU",
    "sg:province":"Lancashire",
    "sg:tags":[
        "gardener"
    ],
    "wof:name":"Frank Cookson",
    "wof:placetype":"venue"
},
  "geometry": {"coordinates":[-2.7270100117,53.7248191833],"type":"Point"}
}