{
  "type": "Feature",
  "properties": {
    "iso:country":"GB",
    "sg:address":"51 Enfield Industrial Estate",
    "sg:city":"Redditch",
    "sg:classifiers":[
        {
            "category":"Building & Trades",
            "subcategory":"Electrical",
            "type":"Services"
        }
    ],
    "sg:phone":"+44 1527 63771",
    "sg:postcode":"B97 6DR",
    "sg:province":"Warwickshire",
    "sg:tags":[
        "lighting"
    ],
    "wof:name":"Anglepoise Holdings Ltd.",
    "wof:placetype":"venue"
},
  "geometry": {"coordinates":[-1.941267,52.30727],"type":"Point"}
}