{
  "type": "Feature",
  "properties": {
    "iso:country":"GB",
    "sg:address":"13d Old Bridge Way",
    "sg:city":"Shefford",
    "sg:classifiers":[
        {
            "category":"Professional",
            "type":"Services"
        }
    ],
    "sg:phone":"+44 1462 815452",
    "sg:postcode":"SG17 5HQ",
    "sg:province":"Bedfordshire",
    "sg:tags":[
        "repair",
        "tech",
        "maintenance"
    ],
    "wof:name":"Netlogic Ltd.",
    "wof:placetype":"venue"
},
  "geometry": {"coordinates":[-0.335555,52.036549],"type":"Point"}
}