{
  "type": "Feature",
  "properties": {
    "addr:full":"16 The Lee Fleet Hampshire GU14 9RE",
    "addr:housenumber":"16",
    "addr:postcode":"gu14 9re",
    "addr:street":"The Lee",
    "iso:country":"GB",
    "sg:address":"16 The Lee",
    "sg:city":"Fleet",
    "sg:classifiers":[
        {
            "category":"Building & Trades",
            "subcategory":"Equipment Rental",
            "type":"Services"
        }
    ],
    "sg:postcode":"GU14 9RE",
    "sg:province":"Hampshire",
    "sg:tags":[
        "drain",
        "clearance"
    ],
    "wof:name":"Peter Everest",
    "wof:placetype":"venue"
},
  "geometry": {"coordinates":[-0.851859,51.273212],"type":"Point"}
}