{
  "type": "Feature",
  "properties": {
    "iso:country":"GB",
    "sg:address":"30a The Haymarket",
    "sg:city":"Bury",
    "sg:classifiers":[
        {
            "category":"Shopping",
            "subcategory":"Shoes",
            "type":"Retail Goods"
        }
    ],
    "sg:postcode":"BL9 0BX",
    "sg:province":"Lancashire",
    "sg:tags":[
        "shop"
    ],
    "wof:name":"Rafiq,Mohammed,",
    "wof:placetype":"venue"
},
  "geometry": {"coordinates":[-2.2974789143,53.5923347473],"type":"Point"}
}