{
  "type": "Feature",
  "properties": {
    "addr:full":"6 Telford Court, Streatham Hill London Greater London SW2 4RH",
    "addr:housenumber":"6",
    "addr:postcode":"sw2 4rh",
    "addr:street":"Telford Court",
    "iso:country":"GB",
    "sg:address":"6 Telford Court, Streatham Hill",
    "sg:city":"London",
    "sg:classifiers":[
        {
            "category":"Professional",
            "subcategory":"Accounting & Tax Preparation",
            "type":"Services"
        }
    ],
    "sg:postcode":"SW2 4RH",
    "sg:province":"Greater London",
    "sg:tags":[
        "accountant"
    ],
    "wof:name":"Heavystart Ltd",
    "wof:placetype":"venue"
},
  "geometry": {"coordinates":[-0.125313,51.442039],"type":"Point"}
}