{
  "type": "Feature",
  "properties": {
    "addr:full":"The Grove Rowlands Gill Durham NE39 1PN",
    "addr:postcode":"ne39 1pn",
    "addr:street":"Gill",
    "iso:country":"GB",
    "sg:address":"The Grove",
    "sg:city":"Rowlands Gill",
    "sg:classifiers":[
        {
            "category":"Government",
            "subcategory":"Post Office",
            "type":"Public Place"
        }
    ],
    "sg:phone":"+44 1207 542361",
    "sg:postcode":"NE39 1PN",
    "sg:province":"Durham",
    "wof:name":"Rowlands Gill Post Office",
    "wof:placetype":"venue"
},
  "geometry": {"coordinates":[-1.7428350449,54.9191322327],"type":"Point"}
}