{
  "type": "Feature",
  "properties": {
    "addr:full":"Unit 8 The Maltings, East Tyndall Street Cardiff Cardiff CF24 5EA",
    "addr:housenumber":"unit 8",
    "addr:postcode":"cf24 5ea",
    "addr:street":"The Maltings East Tyndall Street",
    "iso:country":"GB",
    "sg:address":"Unit 8 The Maltings, East Tyndall Street",
    "sg:city":"Cardiff",
    "sg:classifiers":[
        {
            "category":"Professional",
            "subcategory":"Advertising",
            "type":"Services"
        }
    ],
    "sg:phone":"+44 29 2049 9948",
    "sg:postcode":"CF24 5EA",
    "sg:province":"Cardiff",
    "sg:tags":[
        "agency"
    ],
    "wof:name":"Airtime Associates",
    "wof:placetype":"venue"
},
  "geometry": {"coordinates":[-3.1553859711,51.4796676636],"type":"Point"}
}