{
  "type": "Feature",
  "properties": {
    "iso:country":"GB",
    "sg:address":"8 Searle Road",
    "sg:city":"Farnham",
    "sg:classifiers":[
        {
            "category":"Social Services",
            "subcategory":"Retirement Home",
            "type":"Services"
        }
    ],
    "sg:phone":"+44 1252 727378",
    "sg:postcode":"GU9 8LJ",
    "sg:province":"Surrey",
    "sg:tags":[
        "rest"
    ],
    "wof:name":"Anchor Stone Residential Home",
    "wof:placetype":"venue"
},
  "geometry": {"coordinates":[-0.796582,51.206608],"type":"Point"}
}