{
  "type": "Feature",
  "properties": {
    "iso:country":"GB",
    "sg:address":"Hill Dene House, Main Street, Staxton",
    "sg:city":"Scarborough",
    "sg:classifiers":[
        {
            "category":"Professional",
            "subcategory":"Accounting & Tax Preparation",
            "type":"Services"
        }
    ],
    "sg:phone":"+44 1944 710880",
    "sg:postcode":"YO12 4SE",
    "sg:province":"North Yorkshire",
    "sg:tags":[
        "accountant",
        "activity"
    ],
    "wof:name":"Stephen John Marshall",
    "wof:placetype":"venue"
},
  "geometry": {"coordinates":[-0.443338,54.196819],"type":"Point"}
}