{
  "type": "Feature",
  "properties": {
    "addr:full":"1 King William Street London Greater London EC4N 7AR",
    "addr:housenumber":"1",
    "addr:postcode":"ec4n 7ar",
    "addr:street":"King William Street",
    "iso:country":"GB",
    "sg:address":"1 King William Street",
    "sg:city":"London",
    "sg:classifiers":[
        {
            "category":"Banks & Credit Unions",
            "subcategory":"Investment Brokerage",
            "type":"Services"
        }
    ],
    "sg:postcode":"EC4N 7AR",
    "sg:province":"Greater London",
    "wof:name":"Insight Investment Management (Global) Ltd.",
    "wof:placetype":"venue"
},
  "geometry": {"coordinates":[-0.087824,51.51207],"type":"Point"}
}