{
  "type": "Feature",
  "properties": {
    "iso:country":"GB",
    "sg:address":"105 Mungo Park Rd",
    "sg:city":"Rainham",
    "sg:classifiers":[
        {
            "category":"Food & Beverages",
            "subcategory":"Bakery",
            "type":"Retail Goods"
        }
    ],
    "sg:postcode":"RM13 7PP",
    "sg:province":"Essex",
    "sg:tags":[
        "baker"
    ],
    "wof:name":"Moore,Richard,",
    "wof:placetype":"venue"
},
  "geometry": {"coordinates":[0.192499,51.540161],"type":"Point"}
}