{
  "type": "Feature",
  "properties": {
    "addr:full":"12 Richmond Road, New Barnet Barnet Hertfordshire EN5 1SB",
    "addr:housenumber":"12",
    "addr:postcode":"en5 1sb",
    "addr:street":"Richmond Road",
    "iso:country":"GB",
    "sg:address":"12 Richmond Road, New Barnet",
    "sg:city":"Barnet",
    "sg:classifiers":[
        {
            "category":"Health Services",
            "subcategory":"Nursing And Care Facility",
            "type":"Services"
        }
    ],
    "sg:phone":"+44 20 8449 9252",
    "sg:postcode":"EN5 1SB",
    "sg:province":"Hertfordshire",
    "sg:tags":[
        "home"
    ],
    "wof:name":"Cedars Nursing Home",
    "wof:placetype":"venue"
},
  "geometry": {"coordinates":[-0.178658,51.646469],"type":"Point"}
}