{
  "type": "Feature",
  "properties": {
    "addr:full":"On The Foreshore, Beach Road St Bees Cumbria CA27 0ES",
    "addr:postcode":"ca27 0es",
    "addr:street":"Beach Road",
    "iso:country":"GB",
    "sg:address":"On The Foreshore, Beach Road",
    "sg:city":"St Bees",
    "sg:classifiers":[
        {
            "category":"Cafe",
            "type":"Food & Drink"
        }
    ],
    "sg:phone":"+44 1946 820175",
    "sg:postcode":"CA27 0ES",
    "sg:province":"Cumbria",
    "sg:tags":[
        "tea",
        "room"
    ],
    "wof:name":"W Hartley Icecream",
    "wof:placetype":"venue"
},
  "geometry": {"coordinates":[-3.589702,54.490822],"type":"Point"}
}