{
  "type": "Feature",
  "properties": {
    "addr:full":"Green Lane Bolton Lancashire BL3 2LY",
    "addr:postcode":"bl3 2ly",
    "addr:street":"Green Lane",
    "iso:country":"GB",
    "sg:address":"Green Lane",
    "sg:city":"Bolton",
    "sg:classifiers":[
        {
            "category":"Organizations",
            "subcategory":"Membership Organization",
            "type":"Services"
        }
    ],
    "sg:phone":"+44 1204 528123",
    "sg:postcode":"BL3 2LY",
    "sg:province":"Lancashire",
    "sg:tags":[
        "club"
    ],
    "wof:name":"London Midland Railway Clubs Association",
    "wof:placetype":"venue"
},
  "geometry": {"coordinates":[-2.4272990227,53.5599899292],"type":"Point"}
}