{
  "type": "Feature",
  "properties": {
    "addr:full":"14 Christchurch Road Ringwood Dorset BH24 1DN",
    "addr:housenumber":"14",
    "addr:postcode":"bh24 1dn",
    "addr:street":"Christchurch Road",
    "iso:country":"GB",
    "sg:address":"14 Christchurch Road",
    "sg:city":"Ringwood",
    "sg:classifiers":[
        {
            "category":"Shopping",
            "subcategory":"Florist",
            "type":"Retail Goods"
        }
    ],
    "sg:phone":"+44 1425 477313",
    "sg:postcode":"BH24 1DN",
    "sg:province":"Dorset",
    "wof:name":"Flowertalk",
    "wof:placetype":"venue"
},
  "geometry": {"coordinates":[-1.7903590202,50.8454627991],"type":"Point"}
}