{
  "type": "Feature",
  "properties": {
    "iso:country":"GB",
    "sg:address":"Frigate Rd, Roath Basin, Cardiff Docks",
    "sg:city":"Cardiff",
    "sg:classifiers":[
        {
            "category":"Manufacturing",
            "subcategory":"Lumber",
            "type":"Manufacturing & Wholesale Goods"
        }
    ],
    "sg:phone":"+44 29 2048 7738",
    "sg:postcode":"CF10 4LP",
    "sg:province":"Cardiff",
    "sg:tags":[
        "importer",
        "merchants",
        "agent",
        "timber"
    ],
    "wof:name":"Shapland,W,& Sons Ltd",
    "wof:placetype":"venue"
},
  "geometry": {"coordinates":[-3.154391,51.463921],"type":"Point"}
}