{
  "type": "Feature",
  "properties": {
    "addr:full":"7 Cherry Gardens Cotts, Royal Oak Lane Uckfield East Sussex TN22 4AL",
    "addr:housenumber":"7",
    "addr:postcode":"tn22 4al",
    "addr:street":"Cherry Gardens;Royal Oak Lane",
    "iso:country":"GB",
    "sg:address":"7 Cherry Gardens Cotts, Royal Oak Lane",
    "sg:city":"Uckfield",
    "sg:classifiers":[
        {
            "category":"Professional",
            "type":"Services"
        }
    ],
    "sg:phone":"+44 1825 733401",
    "sg:postcode":"TN22 4AL",
    "sg:province":"East Sussex",
    "sg:tags":[
        "caterer"
    ],
    "wof:name":"M & S Caterers",
    "wof:placetype":"venue"
},
  "geometry": {"coordinates":[0.09665,50.971813],"type":"Point"}
}