{
  "type": "Feature",
  "properties": {
    "addr:full":"Town Foot Farm, Shilbottle Alnwick Northumberland NE66 2HG",
    "addr:postcode":"ne66 2hg",
    "iso:country":"GB",
    "sg:address":"Town Foot Farm, Shilbottle",
    "sg:city":"Alnwick",
    "sg:classifiers":[
        {
            "category":"Sports & Exercise",
            "subcategory":"Stables",
            "type":"Entertainment"
        },
        {
            "category":"Farming",
            "subcategory":"Livestock Farm",
            "type":"Manufacturing & Wholesale Goods"
        }
    ],
    "sg:postcode":"NE66 2HG",
    "sg:province":"Northumberland",
    "sg:tags":[
        "education",
        "equestrian",
        "others"
    ],
    "wof:name":"A C & C M Stoker",
    "wof:placetype":"venue"
},
  "geometry": {"coordinates":[-1.6859580278,55.3708763123],"type":"Point"}
}