{
  "type": "Feature",
  "properties": {
    "addr:full":"Bettws Hall Farm, Bettws Cedewen Newtown Powys SY16 3DS",
    "addr:housenumber":"bettws",
    "addr:postcode":"sy16 3ds",
    "addr:street":"Hall;Bettws Cedewen",
    "iso:country":"GB",
    "sg:address":"Bettws Hall Farm, Bettws Cedewen",
    "sg:city":"Newtown",
    "sg:classifiers":[
        {
            "category":"Farming",
            "subcategory":"Livestock Farm",
            "type":"Manufacturing & Wholesale Goods"
        }
    ],
    "sg:phone":"+44 1686 650628",
    "sg:postcode":"SY16 3DS",
    "sg:province":"Powys",
    "sg:tags":[
        "others"
    ],
    "wof:name":"Bettws Hall",
    "wof:placetype":"venue"
},
  "geometry": {"coordinates":[-3.3568150997,52.5433921814],"type":"Point"}
}