{
  "type": "Feature",
  "properties": {
    "iso:country":"GB",
    "sg:address":"87 Broad Street",
    "sg:city":"Blaenavon",
    "sg:classifiers":[
        {
            "category":"Retail",
            "subcategory":"Funeral Services",
            "type":"Services"
        }
    ],
    "sg:postcode":"NP4 9NE",
    "sg:province":"Monmouthshire",
    "wof:name":"Phillip Tom",
    "wof:placetype":"venue"
},
  "geometry": {"coordinates":[-3.084106,51.773167],"type":"Point"}
}