{
  "type": "Feature",
  "properties": {
    "addr:full":"First Floor, 87 High Road, South Woodford South Woodford Greater London E18 2QP",
    "addr:housenumber":"87",
    "addr:postcode":"e18 2qp",
    "addr:street":"High Road",
    "iso:country":"GB",
    "sg:address":"First Floor, 87 High Road, South Woodford",
    "sg:city":"South Woodford",
    "sg:classifiers":[
        {
            "category":"Professional",
            "subcategory":"Management & Consulting",
            "type":"Services"
        }
    ],
    "sg:phone":"+44 20 8491 1400",
    "sg:postcode":"E18 2QP",
    "sg:province":"Greater London",
    "sg:tags":[
        "consultant",
        "business"
    ],
    "wof:name":"Johnathan Mcgovern",
    "wof:placetype":"venue"
},
  "geometry": {"coordinates":[0.0221030004,51.5942192078],"type":"Point"}
}