{
  "type": "Feature",
  "properties": {
    "addr:full":"59 Holly Court, St Modwen Road Plymouth Devon PL6 8LG",
    "addr:housenumber":"59",
    "addr:postcode":"pl6 8lg",
    "addr:street":"Holly Court;Modwen Road",
    "iso:country":"GB",
    "sg:address":"59 Holly Court, St Modwen Road",
    "sg:city":"Plymouth",
    "sg:classifiers":[
        {
            "category":"Wholesale",
            "subcategory":"Machinery & Supplies",
            "type":"Manufacturing & Wholesale Goods"
        }
    ],
    "sg:phone":"+44 1752 664796",
    "sg:postcode":"PL6 8LG",
    "sg:province":"Devon",
    "sg:tags":[
        "hydraulic"
    ],
    "wof:name":"Dunlop Hi-Flex South West",
    "wof:placetype":"venue"
},
  "geometry": {"coordinates":[-4.09269,50.396461],"type":"Point"}
}