{
  "type": "Feature",
  "properties": {
    "addr:full":"20 Exchange Street Driffield East Riding of Yorkshire YO25 6LD",
    "addr:housenumber":"20",
    "addr:postcode":"yo25 6ld",
    "addr:street":"Exchange Street",
    "iso:country":"GB",
    "sg:address":"20 Exchange Street",
    "sg:city":"Driffield",
    "sg:classifiers":[
        {
            "category":"Real Estate",
            "subcategory":"Surveying",
            "type":"Services"
        },
        {
            "category":"Real Estate",
            "subcategory":"Real Estate Agent",
            "type":"Services"
        }
    ],
    "sg:phone":"+44 1377 253151",
    "sg:postcode":"YO25 6LD",
    "sg:province":"East Riding of Yorkshire",
    "sg:tags":[
        "surveyor",
        "valuer"
    ],
    "wof:name":"Dee Atkinson & Harrison",
    "wof:placetype":"venue"
},
  "geometry": {"coordinates":[-0.438698,54.005684],"type":"Point"}
}