{
  "type": "Feature",
  "properties": {
    "addr:full":"56 St Georges Road Great Yarmouth Norfolk NR30 2JT",
    "addr:housenumber":"56",
    "addr:postcode":"nr30 2jt",
    "addr:street":"St Georges Road",
    "iso:country":"GB",
    "sg:address":"56 St Georges Road",
    "sg:city":"Great Yarmouth",
    "sg:classifiers":[
        {
            "category":"Bars & Pubs",
            "type":"Food & Drink"
        }
    ],
    "sg:phone":"+44 1493 851610",
    "sg:postcode":"NR30 2JT",
    "sg:province":"Norfolk",
    "sg:tags":[
        "pubs",
        "inn"
    ],
    "wof:name":"St Georges Tavern",
    "wof:placetype":"venue"
},
  "geometry": {"coordinates":[1.7337880135,52.6039619446],"type":"Point"}
}