{
  "type": "Feature",
  "properties": {
    "iso:country":"GB",
    "sg:address":"Blaenau, Nantglyn",
    "sg:city":"Denbigh",
    "sg:classifiers":[
        {
            "category":"Farming",
            "subcategory":"Livestock Farm",
            "type":"Manufacturing & Wholesale Goods"
        }
    ],
    "sg:phone":"+44 1745 550329",
    "sg:postcode":"LL16 5RH",
    "sg:province":"Conwy",
    "sg:tags":[
        "others"
    ],
    "wof:name":"W E & A Edwards",
    "wof:placetype":"venue"
},
  "geometry": {"coordinates":[-3.4903590679,53.1462287903],"type":"Point"}
}