{
  "type": "Feature",
  "properties": {
    "addr:full":"2 Coombe House Tenterden Kent TN30 6HD",
    "addr:housenumber":"2",
    "addr:postcode":"tn30 6hd",
    "addr:street":"Coombe",
    "iso:country":"GB",
    "sg:address":"2 Coombe House",
    "sg:city":"Tenterden",
    "sg:classifiers":[
        {
            "category":"Cafe",
            "type":"Food & Drink"
        }
    ],
    "sg:postcode":"TN30 6HD",
    "sg:province":"Kent",
    "sg:tags":[
        "tea",
        "room"
    ],
    "wof:name":"Whistle Stop Cafe",
    "wof:placetype":"venue"
},
  "geometry": {"coordinates":[0.685751,51.068371],"type":"Point"}
}