{
  "type": "Feature",
  "properties": {
    "iso:country":"GB",
    "sg:address":"52 Albert Rd",
    "sg:city":"Glasgow",
    "sg:classifiers":[
        {
            "category":"Travel",
            "subcategory":"Travel Agent",
            "type":"Entertainment"
        }
    ],
    "sg:phone":"+44 141 424 0424",
    "sg:postcode":"G42 8DN",
    "sg:province":"Glasgow City",
    "wof:name":"Adair Travel Agency Ltd",
    "wof:placetype":"venue"
},
  "geometry": {"coordinates":[-4.263899,55.83427],"type":"Point"}
}