{
  "type": "Feature",
  "properties": {
    "addr:full":"9 Sunnyside Park, Wimborne Road Poole Dorset BH16 6HQ",
    "addr:housenumber":"9",
    "addr:postcode":"bh16 6hq",
    "addr:street":"Sunnyside Park Wimborne Road",
    "iso:country":"GB",
    "sg:address":"9 Sunnyside Park, Wimborne Road",
    "sg:city":"Poole",
    "sg:classifiers":[
        {
            "category":"Sports & Exercise",
            "subcategory":"Tennis Court",
            "type":"Entertainment"
        }
    ],
    "sg:phone":"+44 1202 625100",
    "sg:postcode":"BH16 6HQ",
    "sg:province":"Dorset",
    "sg:tags":[
        "breakdown",
        "recovery"
    ],
    "wof:name":"Lytchett Minster Garage",
    "wof:placetype":"venue"
},
  "geometry": {"coordinates":[-2.0661699772,50.7618103027],"type":"Point"}
}