{
  "type": "Feature",
  "properties": {
    "addr:full":"16 Station App Virginia Water Surrey GU25 4DW",
    "addr:housenumber":"16;app",
    "addr:postcode":"gu25 4dw",
    "addr:street":"Station",
    "iso:country":"GB",
    "sg:address":"16 Station App",
    "sg:city":"Virginia Water",
    "sg:classifiers":[
        {
            "category":"Restaurant",
            "type":"Food & Drink"
        }
    ],
    "sg:phone":"+44 1344 845292",
    "sg:postcode":"GU25 4DW",
    "sg:province":"Surrey",
    "wof:name":"Lux Ii Restaurant",
    "wof:placetype":"venue"
},
  "geometry": {"coordinates":[-0.5672299862,51.4033432007],"type":"Point"}
}