{
  "type": "Feature",
  "properties": {
    "iso:country":"GB",
    "sg:address":"74-76 Glamis Road",
    "sg:city":"Kirriemuir",
    "sg:classifiers":[
        {
            "category":"Food & Beverages",
            "subcategory":"Supermarket",
            "type":"Retail Goods"
        }
    ],
    "sg:phone":"+44 1575 573862",
    "sg:postcode":"DD8 5DD",
    "sg:province":"Angus",
    "wof:name":"East Angus Co-Operative Society Ltd.",
    "wof:placetype":"venue"
},
  "geometry": {"coordinates":[-3.00431,56.667992],"type":"Point"}
}