{
  "type": "Feature",
  "properties": {
    "addr:full":"191 West George Street Glasgow G2 2LB",
    "addr:housenumber":"191",
    "addr:postcode":"g2 2lb",
    "addr:street":"West George Street",
    "iso:country":"GB",
    "sg:address":"191 West George Street",
    "sg:city":"Glasgow",
    "sg:classifiers":[
        {
            "category":"Professional",
            "subcategory":"Computer Services",
            "type":"Services"
        }
    ],
    "sg:postcode":"G2 2LB",
    "sg:website":"http://www.itiscotland.com",
    "wof:name":"ITI Scotland",
    "wof:placetype":"venue"
},
  "geometry": {"coordinates":[-4.259505,55.8627073],"type":"Point"}
}