{
  "type": "Feature",
  "properties": {
    "addr:full":"Dental Surgery, 6 Dolphin Sq Tring Buckinghamshire HP23 5BN",
    "addr:housenumber":"6",
    "addr:postcode":"hp23 5bn",
    "addr:street":"Dolphin Sq",
    "iso:country":"GB",
    "sg:address":"Dental Surgery, 6 Dolphin Sq",
    "sg:city":"Tring",
    "sg:classifiers":[
        {
            "category":"Health Services",
            "subcategory":"Dentist",
            "type":"Services"
        }
    ],
    "sg:phone":"+44 1442 823081",
    "sg:postcode":"HP23 5BN",
    "sg:province":"Buckinghamshire",
    "wof:name":"M Kaplan & Associates",
    "wof:placetype":"venue"
},
  "geometry": {"coordinates":[-0.66398,51.79327],"type":"Point"}
}