{
  "type": "Feature",
  "properties": {
    "addr:full":"32 King Street Dudley West Midlands DY2 8NY",
    "addr:housenumber":"32",
    "addr:postcode":"dy2 8ny",
    "addr:street":"King Street",
    "iso:country":"GB",
    "sg:address":"32 King Street",
    "sg:city":"Dudley",
    "sg:classifiers":[
        {
            "category":"Manufacturing",
            "subcategory":"Tools & Machinery",
            "type":"Manufacturing & Wholesale Goods"
        }
    ],
    "sg:phone":"+44 1384 232426",
    "sg:postcode":"DY2 8NY",
    "sg:province":"West Midlands",
    "sg:tags":[
        "society",
        "friendly"
    ],
    "wof:name":"Obc Insurance Consultants",
    "wof:placetype":"venue"
},
  "geometry": {"coordinates":[-2.0885350704,52.507434845],"type":"Point"}
}