{
  "type": "Feature",
  "properties": {
    "addr:full":"Perne House, Grange Road Tenterden Kent TN30 6DT",
    "addr:postcode":"tn30 6dt",
    "addr:street":"Grange Road",
    "iso:country":"GB",
    "sg:address":"Perne House, Grange Road",
    "sg:city":"Tenterden",
    "sg:classifiers":[
        {
            "category":"Retail",
            "subcategory":"Repair Shop",
            "type":"Services"
        }
    ],
    "sg:postcode":"TN30 6DT",
    "sg:province":"Kent",
    "sg:tags":[
        "maintenance"
    ],
    "wof:name":"M Button",
    "wof:placetype":"venue"
},
  "geometry": {"coordinates":[0.677246,51.084156],"type":"Point"}
}