{
  "type": "Feature",
  "properties": {
    "addr:full":"16-20 Thornton Lodge Road Huddersfield West Yorkshire HD1 3JQ",
    "addr:housenumber":"16-20",
    "addr:postcode":"hd1 3jq",
    "addr:street":"Thornton Lodge Road",
    "iso:country":"GB",
    "sg:address":"16-20 Thornton Lodge Road",
    "sg:city":"Huddersfield",
    "sg:classifiers":[
        {
            "category":"Shopping",
            "subcategory":"Department Store",
            "type":"Retail Goods"
        },
        {
            "category":"Food & Beverages",
            "subcategory":"Supermarket",
            "type":"Retail Goods"
        },
        {
            "category":"Food & Beverages",
            "subcategory":"Groceries & Convenience Stores",
            "type":"Retail Goods"
        }
    ],
    "sg:phone":"+44 1484 549956",
    "sg:postcode":"HD1 3JQ",
    "sg:province":"West Yorkshire",
    "wof:name":"Kashmir Stores",
    "wof:placetype":"venue"
},
  "geometry": {"coordinates":[-1.7976679802,53.6395339966],"type":"Point"}
}