{
  "type": "Feature",
  "properties": {
    "addr:full":"Church Street Yeovil Somerset BA20 1HE",
    "addr:postcode":"ba20 1he",
    "addr:street":"Church Street",
    "iso:country":"GB",
    "sg:address":"Church Street",
    "sg:city":"Yeovil",
    "sg:classifiers":[
        {
            "category":"Banks & Credit Unions",
            "subcategory":"Bank",
            "type":"Services"
        }
    ],
    "sg:phone":"+44 1935 411666",
    "sg:postcode":"BA20 1HE",
    "sg:province":"Somerset",
    "sg:tags":[
        "broker",
        "mortgage"
    ],
    "wof:name":"Mortgage Centre",
    "wof:placetype":"venue"
},
  "geometry": {"coordinates":[-2.633379,50.942085],"type":"Point"}
}