{
  "type": "Feature",
  "properties": {
    "addr:full":"Hallsford Bridge Industrial Esta Ongar Essex CM5 9RB",
    "addr:postcode":"cm5 9rb",
    "addr:street":"Ongar",
    "iso:country":"GB",
    "sg:address":"Hallsford Bridge Industrial Esta",
    "sg:city":"Ongar",
    "sg:classifiers":[
        {
            "category":"Social Services",
            "type":"Services"
        }
    ],
    "sg:phone":"+44 1277 364449",
    "sg:postcode":"CM5 9RB",
    "sg:province":"Essex",
    "sg:tags":[
        "disability"
    ],
    "wof:name":"Medeci Rehab Ltd.",
    "wof:placetype":"venue"
},
  "geometry": {"coordinates":[0.24517,51.706131],"type":"Point"}
}