{
  "type": "Feature",
  "properties": {
    "iso:country":"GB",
    "sg:address":"16 Techno Trading Estate, Off Kembrey Street",
    "sg:city":"Swindon",
    "sg:classifiers":[
        {
            "category":"Professional",
            "subcategory":"Art Services",
            "type":"Services"
        }
    ],
    "sg:phone":"+44 1793 541033",
    "sg:postcode":"SN2 8HB",
    "sg:province":"Wiltshire",
    "sg:tags":[
        "decorating",
        "painting"
    ],
    "wof:name":"Leyland Paint Co",
    "wof:placetype":"venue"
},
  "geometry": {"coordinates":[-1.76266,51.576626],"type":"Point"}
}