{
  "type": "Feature",
  "properties": {
    "addr:full":"Lanteglos Road Camelford Cornwall PL32 9RF",
    "addr:postcode":"pl32 9rf",
    "addr:street":"Lanteglos Road",
    "iso:country":"GB",
    "sg:address":"Lanteglos Road",
    "sg:city":"Camelford",
    "sg:classifiers":[
        {
            "category":"Arena",
            "subcategory":"Sports Club",
            "type":"Entertainment"
        }
    ],
    "sg:phone":"+44 1840 212445",
    "sg:postcode":"PL32 9RF",
    "sg:province":"Cornwall",
    "wof:name":"Camelford Bowling Club",
    "wof:placetype":"venue"
},
  "geometry": {"coordinates":[-4.678636,50.623116],"type":"Point"}
}