{
  "type": "Feature",
  "properties": {
    "addr:full":"5-11 Mono Lane Feltham Greater London TW13 7LR",
    "addr:housenumber":"5-11",
    "addr:postcode":"tw13 7lr",
    "addr:street":"Mono Lane",
    "iso:country":"GB",
    "sg:address":"5-11 Mono Lane",
    "sg:city":"Feltham",
    "sg:classifiers":[
        {
            "category":"Personal",
            "subcategory":"Skin Care",
            "type":"Services"
        }
    ],
    "sg:phone":"+44 20 8844 1433",
    "sg:postcode":"TW13 7LR",
    "sg:province":"Greater London",
    "sg:tags":[
        "razor",
        "blade"
    ],
    "wof:name":"Super-Max Ltd.",
    "wof:placetype":"venue"
},
  "geometry": {"coordinates":[-0.4073899984,51.4444618225],"type":"Point"}
}