{
  "type": "Feature",
  "properties": {
    "iso:country":"GB",
    "sg:address":"5 Edale Green",
    "sg:city":"Hinckley",
    "sg:classifiers":[
        {
            "category":"Home & Garden",
            "subcategory":"Garden Supply",
            "type":"Retail Goods"
        }
    ],
    "sg:phone":"+44 1455 271366",
    "sg:postcode":"LE10 2RP",
    "sg:province":"Leicestershire",
    "sg:tags":[
        "equipment",
        "playground"
    ],
    "wof:name":"P H Leisure Services Ltd.",
    "wof:placetype":"venue"
},
  "geometry": {"coordinates":[-1.3600540161,52.5296096802],"type":"Point"}
}