{
  "type": "Feature",
  "properties": {
    "addr:full":"The High Street, Hartley Wintney Hook Berkshire RG27 8NY",
    "addr:postcode":"rg27 8ny",
    "addr:street":"Street",
    "iso:country":"GB",
    "sg:address":"The High Street, Hartley Wintney",
    "sg:city":"Hook",
    "sg:classifiers":[
        {
            "category":"Personal",
            "subcategory":"Beauty Salon",
            "type":"Services"
        }
    ],
    "sg:phone":"+44 1252 845326",
    "sg:postcode":"RG27 8NY",
    "sg:province":"Berkshire",
    "sg:tags":[
        "unisex",
        "hairdresser"
    ],
    "wof:name":"Village Gossip (Beauty) Ltd.",
    "wof:placetype":"venue"
},
  "geometry": {"coordinates":[-0.900754,51.305828],"type":"Point"}
}