{
  "type": "Feature",
  "properties": {
    "addr:full":"High Street, Yardley Hastings Northampton Buckinghamshire NN7 1ER",
    "addr:postcode":"nn7 1er",
    "addr:street":"High Street",
    "iso:country":"GB",
    "sg:address":"High Street, Yardley Hastings",
    "sg:city":"Northampton",
    "sg:classifiers":[
        {
            "category":"Shopping",
            "subcategory":"Department Store",
            "type":"Retail Goods"
        }
    ],
    "sg:postcode":"NN7 1ER",
    "sg:province":"Buckinghamshire",
    "wof:name":"Yardley Hastings Stores",
    "wof:placetype":"venue"
},
  "geometry": {"coordinates":[-0.734026,52.20377],"type":"Point"}
}