{
  "type": "Feature",
  "properties": {
    "iso:country":"GB",
    "sg:address":"Cotteswold Road",
    "sg:city":"Gloucester",
    "sg:classifiers":[
        {
            "category":"Education",
            "subcategory":"School",
            "type":"Public Place"
        }
    ],
    "sg:phone":"+44 1452 526131",
    "sg:postcode":"GL4 6RN",
    "sg:province":"Gloucestershire",
    "sg:tags":[
        "local",
        "authority"
    ],
    "wof:name":"Centre Technology College",
    "wof:placetype":"venue"
},
  "geometry": {"coordinates":[-2.226514,51.847076],"type":"Point"}
}