{
  "type": "Feature",
  "properties": {
    "iso:country":"GB",
    "sg:address":"Station Road",
    "sg:city":"Heathfield",
    "sg:classifiers":[
        {
            "category":"Home & Garden",
            "subcategory":"Hardware",
            "type":"Retail Goods"
        },
        {
            "category":"Home & Garden",
            "subcategory":"Carpets & Floor Coverings",
            "type":"Retail Goods"
        }
    ],
    "sg:phone":"+44 1435 862235",
    "sg:postcode":"TN21 8DH",
    "sg:province":"East Sussex",
    "sg:tags":[
        "lawnmowers",
        "sales",
        "machinery"
    ],
    "sg:website":"http://www.hughpage.co.uk",
    "wof:name":"Hugh Page Sussex Ltd",
    "wof:placetype":"venue"
},
  "geometry": {"coordinates":[0.2506000102,50.9707641602],"type":"Point"}
}