{
  "type": "Feature",
  "properties": {
    "iso:country":"GB",
    "sg:address":"Newfield Green Post Office, 521 Gleadless Road",
    "sg:city":"Sheffield",
    "sg:classifiers":[
        {
            "category":"Government",
            "subcategory":"Post Office",
            "type":"Public Place"
        }
    ],
    "sg:phone":"+44 114 239 0104",
    "sg:postcode":"S2 2BS",
    "sg:province":"South Yorkshire",
    "wof:name":"Newfield Green Post Office",
    "wof:placetype":"venue"
},
  "geometry": {"coordinates":[-1.451404,53.35696],"type":"Point"}
}