{
  "type": "Feature",
  "properties": {
    "iso:country":"GB",
    "sg:address":"284 Old Christchurch Road",
    "sg:city":"Bournemouth",
    "sg:classifiers":[
        {
            "category":"Restaurant",
            "type":"Food & Drink"
        }
    ],
    "sg:phone":"+44 1202 291191",
    "sg:postcode":"BH1 1PH",
    "sg:province":"Dorset",
    "wof:name":"Rosso Two",
    "wof:placetype":"venue"
},
  "geometry": {"coordinates":[-1.867529,50.721939],"type":"Point"}
}