{
  "type": "Feature",
  "properties": {
    "iso:country":"GB",
    "sg:address":"46-50 Dean Rd",
    "sg:city":"Southampton",
    "sg:classifiers":[
        {
            "category":"Autos & Motor Vehicles",
            "subcategory":"Motorcycle Sales",
            "type":"Retail Goods"
        }
    ],
    "sg:phone":"+44 23 8044 0595",
    "sg:postcode":"SO18 6AP",
    "sg:province":"Hampshire",
    "wof:name":"Pro-Sport Motorcycles",
    "wof:placetype":"venue"
},
  "geometry": {"coordinates":[-1.3553470373,50.9165420532],"type":"Point"}
}