{
  "type": "Feature",
  "properties": {
    "addr:full":"31 The Willows Sittingbourne Kent ME10 4QS",
    "addr:housenumber":"31",
    "addr:postcode":"me10 4qs",
    "addr:street":"The Willows",
    "iso:country":"GB",
    "sg:address":"31 The Willows",
    "sg:city":"Sittingbourne",
    "sg:classifiers":[
        {
            "category":"Shopping",
            "subcategory":"Gifts & Souvenirs",
            "type":"Retail Goods"
        }
    ],
    "sg:phone":"+44 1795 843198",
    "sg:postcode":"ME10 4QS",
    "sg:province":"Kent",
    "sg:tags":[
        "diy"
    ],
    "wof:name":"F G  Stokes",
    "wof:placetype":"venue"
},
  "geometry": {"coordinates":[0.7375779748,51.3619651794],"type":"Point"}
}