{
  "type": "Feature",
  "properties": {
    "addr:full":"8 Acre Lane London Greater London SW2 5SG",
    "addr:housenumber":"8",
    "addr:postcode":"sw2 5sg",
    "addr:street":"Acre Lane",
    "iso:country":"GB",
    "sg:address":"8 Acre Lane",
    "sg:city":"London",
    "sg:classifiers":[
        {
            "category":"Health Services",
            "subcategory":"Optometrist",
            "type":"Services"
        }
    ],
    "sg:phone":"+44 20 7274 4414",
    "sg:postcode":"SW2 5SG",
    "sg:province":"Greater London",
    "sg:tags":[
        "optician"
    ],
    "wof:name":"Banks Optometrists",
    "wof:placetype":"venue"
},
  "geometry": {"coordinates":[-0.117589,51.460594],"type":"Point"}
}