{
  "type": "Feature",
  "properties": {
    "iso:country":"GB",
    "sg:address":"Moorgate Mill, Moorgate Street",
    "sg:city":"Blackburn",
    "sg:classifiers":[
        {
            "category":"Shopping",
            "subcategory":"Crafts & Fabrics",
            "type":"Retail Goods"
        }
    ],
    "sg:phone":"+44 1254 51361",
    "sg:postcode":"BB2 4NZ",
    "sg:province":"Lancashire",
    "sg:tags":[
        "yarn",
        "supply"
    ],
    "wof:name":"Tranmere Textiles Ltd.",
    "wof:placetype":"venue"
},
  "geometry": {"coordinates":[-2.499574,53.730129],"type":"Point"}
}