{
  "type": "Feature",
  "properties": {
    "addr:full":"14 Maiden Street Bude Cornwall EX23 9DQ",
    "addr:housenumber":"14",
    "addr:postcode":"ex23 9dq",
    "addr:street":"Maiden Street",
    "iso:country":"GB",
    "sg:address":"14 Maiden Street",
    "sg:city":"Bude",
    "sg:classifiers":[
        {
            "category":"Building & Trades",
            "subcategory":"Plumbing",
            "type":"Services"
        }
    ],
    "sg:postcode":"EX23 9DQ",
    "sg:province":"Cornwall",
    "sg:tags":[
        "heating"
    ],
    "wof:name":"S Curtis & Son",
    "wof:placetype":"venue"
},
  "geometry": {"coordinates":[-4.514117,50.831345],"type":"Point"}
}