{
  "type": "Feature",
  "properties": {
    "iso:country":"GB",
    "sg:address":"82 Kirby Drive",
    "sg:city":"Luton",
    "sg:classifiers":[
        {
            "category":"Shopping",
            "subcategory":"News",
            "type":"Retail Goods"
        }
    ],
    "sg:phone":"+44 1582 599992",
    "sg:postcode":"LU3 4AW",
    "sg:province":"Bedfordshire",
    "sg:tags":[
        "newsagent"
    ],
    "wof:name":"7-10 Newsagents",
    "wof:placetype":"venue"
},
  "geometry": {"coordinates":[-0.446531,51.924355],"type":"Point"}
}