{
  "type": "Feature",
  "properties": {
    "addr:full":"1-3 Greenwood Avenue, Worsbrough Dale Barnsley South Yorkshire S70 4BH",
    "addr:housenumber":"1-3",
    "addr:postcode":"s70 4bh",
    "addr:street":"Greenwood Avenue Worsbrough Dale;Yorkshire",
    "iso:country":"GB",
    "sg:address":"1-3 Greenwood Avenue, Worsbrough Dale",
    "sg:city":"Barnsley",
    "sg:classifiers":[
        {
            "category":"Shopping",
            "subcategory":"News",
            "type":"Retail Goods"
        }
    ],
    "sg:phone":"+44 1226 285476",
    "sg:postcode":"S70 4BH",
    "sg:province":"South Yorkshire",
    "sg:tags":[
        "newsagent"
    ],
    "wof:name":"S & G Senior",
    "wof:placetype":"venue"
},
  "geometry": {"coordinates":[-1.45969,53.535416],"type":"Point"}
}