{
  "type": "Feature",
  "properties": {
    "addr:full":"Marsh Lane Nantwich Cheshire CW5 5HP",
    "addr:postcode":"cw5 5hp",
    "addr:street":"Marsh Lane",
    "iso:country":"GB",
    "sg:address":"Marsh Lane",
    "sg:city":"Nantwich",
    "sg:classifiers":[
        {
            "category":"Education",
            "subcategory":"School",
            "type":"Public Place"
        },
        {
            "category":"Government",
            "subcategory":"Office",
            "type":"Public Place"
        }
    ],
    "sg:phone":"+44 1270 625587",
    "sg:postcode":"CW5 5HP",
    "sg:province":"Cheshire",
    "sg:tags":[
        "local",
        "authority"
    ],
    "wof:name":"Cheshire County Council",
    "wof:placetype":"venue"
},
  "geometry": {"coordinates":[-2.531017,53.066357],"type":"Point"}
}