{
  "type": "Feature",
  "properties": {
    "iso:country":"GB",
    "sg:address":"Unit 3 Bonville Trading Est, Bonville Rd",
    "sg:city":"Bristol",
    "sg:classifiers":[
        {
            "category":"Farming",
            "subcategory":"Dairy Farm",
            "type":"Manufacturing & Wholesale Goods"
        }
    ],
    "sg:postcode":"BS4 5QU",
    "sg:province":"City of Bristol",
    "wof:name":"Wessex Dairies Ltd",
    "wof:placetype":"venue"
},
  "geometry": {"coordinates":[-2.5352230072,51.4361381531],"type":"Point"}
}