{
  "type": "Feature",
  "properties": {
    "iso:country":"GB",
    "sg:address":"101 St Peters Street",
    "sg:city":"St Albans",
    "sg:classifiers":[
        {
            "category":"Home & Garden",
            "subcategory":"Furniture",
            "type":"Retail Goods"
        }
    ],
    "sg:phone":"+44 1727 856969",
    "sg:postcode":"AL1 3EN",
    "sg:province":"Hertfordshire",
    "wof:name":"Sofability Ltd.",
    "wof:placetype":"venue"
},
  "geometry": {"coordinates":[-0.335919,51.75523],"type":"Point"}
}