{
  "type": "Feature",
  "properties": {
    "addr:full":"Helston Delivery Office, 28-30 Coinagehall Street Helston Cornwall TR13 8EE",
    "addr:housenumber":"28-30",
    "addr:postcode":"tr13 8ee",
    "addr:street":"Coinagehall Street",
    "iso:country":"GB",
    "sg:address":"Helston Delivery Office, 28-30 Coinagehall Street",
    "sg:city":"Helston",
    "sg:classifiers":[
        {
            "category":"Personal",
            "type":"Services"
        }
    ],
    "sg:phone":"+44 1326 572413",
    "sg:postcode":"TR13 8EE",
    "sg:province":"Cornwall",
    "sg:tags":[
        "delivery"
    ],
    "wof:name":"Royal Mail",
    "wof:placetype":"venue"
},
  "geometry": {"coordinates":[-5.2669591904,50.1058197021],"type":"Point"}
}