{
  "type": "Feature",
  "properties": {
    "iso:country":"GB",
    "sg:address":"Clifton Hotel, Queens Parade",
    "sg:city":"Scarborough",
    "sg:classifiers":[
        {
            "category":"Travel",
            "subcategory":"Hotels & Motels",
            "type":"Entertainment"
        }
    ],
    "sg:phone":"+44 1723 375691",
    "sg:postcode":"YO12 7HX",
    "sg:province":"North Yorkshire",
    "wof:name":"ENGLISH ROSE HOTELS PLC",
    "wof:placetype":"venue"
},
  "geometry": {"coordinates":[-0.4275299907,54.280506134],"type":"Point"}
}