{
  "type": "Feature",
  "properties": {
    "addr:full":"421 Beulah Hill London Greater London SE19 3HB",
    "addr:housenumber":"421",
    "addr:postcode":"se19 3hb",
    "addr:street":"Beulah Hill",
    "iso:country":"GB",
    "sg:address":"421 Beulah Hill",
    "sg:city":"London",
    "sg:classifiers":[
        {
            "category":"Real Estate",
            "subcategory":"Real Estate Agent",
            "type":"Services"
        }
    ],
    "sg:phone":"+44 20 8761 2828",
    "sg:postcode":"SE19 3HB",
    "sg:province":"Greater London",
    "wof:name":"Gales",
    "wof:placetype":"venue"
},
  "geometry": {"coordinates":[-0.1065789983,51.4200401306],"type":"Point"}
}