{
  "type": "Feature",
  "properties": {
    "addr:full":"86 High Street Cowdenbeath Fife KY4 9NG",
    "addr:housenumber":"86",
    "addr:postcode":"ky4 9ng",
    "addr:street":"High Street",
    "iso:country":"GB",
    "sg:address":"86 High Street",
    "sg:city":"Cowdenbeath",
    "sg:classifiers":[
        {
            "category":"Education",
            "subcategory":"Special Training",
            "type":"Public Place"
        }
    ],
    "sg:phone":"+44 1383 418130",
    "sg:postcode":"KY4 9NG",
    "sg:province":"Fife",
    "sg:tags":[
        "product",
        "centre"
    ],
    "wof:name":"Microcom Training",
    "wof:placetype":"venue"
},
  "geometry": {"coordinates":[-3.344632,56.112804],"type":"Point"}
}