{
  "type": "Feature",
  "properties": {
    "addr:full":"7 Heron Quays, Docklands London Greater London E14 4JB",
    "addr:housenumber":"7",
    "addr:postcode":"e14 4jb",
    "addr:street":"Heron Quays",
    "iso:country":"GB",
    "sg:address":"7 Heron Quays, Docklands",
    "sg:city":"London",
    "sg:classifiers":[
        {
            "category":"Professional",
            "subcategory":"Employment Agencies",
            "type":"Services"
        }
    ],
    "sg:phone":"+44 20 7536 7950",
    "sg:postcode":"E14 4JB",
    "sg:province":"Greater London",
    "sg:tags":[
        "consultant"
    ],
    "wof:name":"Euromedica Ltd.",
    "wof:placetype":"venue"
},
  "geometry": {"coordinates":[-0.024616,51.503937],"type":"Point"}
}