{
  "type": "Feature",
  "properties": {
    "iso:country":"GB",
    "sg:address":"Lea Grn, Main Road, Lea",
    "sg:city":"Matlock",
    "sg:classifiers":[
        {
            "category":"Government",
            "subcategory":"Office",
            "type":"Public Place"
        }
    ],
    "sg:phone":"+44 1629 534561",
    "sg:postcode":"DE4 5GJ",
    "sg:province":"Derbyshire",
    "sg:tags":[
        "local"
    ],
    "wof:name":"Lea Green Centre",
    "wof:placetype":"venue"
},
  "geometry": {"coordinates":[-1.540171,53.104446],"type":"Point"}
}