{
  "type": "Feature",
  "properties": {
    "addr:full":"169 Norwood High St, West Norwwod London Greater London SE27 9TB",
    "addr:housenumber":"169",
    "addr:postcode":"london se27 9tb",
    "addr:street":"Norwood High St",
    "iso:country":"GB",
    "sg:address":"169 Norwood High St, West Norwwod",
    "sg:city":"London",
    "sg:classifiers":[
        {
            "category":"Travel",
            "subcategory":"Travel Agent",
            "type":"Entertainment"
        }
    ],
    "sg:phone":"+44 20 7766 7818",
    "sg:postcode":"SE27 9TB",
    "sg:province":"Greater London",
    "wof:name":"A Mercury Travel & Tours Ltd",
    "wof:placetype":"venue"
},
  "geometry": {"coordinates":[-0.1001930013,51.4281616211],"type":"Point"}
}