{
  "type": "Feature",
  "properties": {
    "iso:country":"GB",
    "sg:address":"1 Cobbswood Industrial Estate, Brunswick Road",
    "sg:city":"Ashford",
    "sg:classifiers":[
        {
            "category":"Wholesale",
            "subcategory":"Electrical",
            "type":"Manufacturing & Wholesale Goods"
        },
        {
            "category":"Shopping",
            "subcategory":"Computers & Home Electronics",
            "type":"Retail Goods"
        }
    ],
    "sg:phone":"+44 1233 635462",
    "sg:postcode":"TN23 1EL",
    "sg:province":"Kent",
    "sg:tags":[
        "wholesaler"
    ],
    "sg:website":"http://www.neweyandeyre.co.uk",
    "wof:name":"Newey & Eyre Ltd",
    "wof:placetype":"venue"
},
  "geometry": {"coordinates":[0.8760370016,51.1466331482],"type":"Point"}
}