{
  "type": "Feature",
  "properties": {
    "addr:full":"109 Seymour Buildings, Seymour Place London Greater London W1H 4PS",
    "addr:housenumber":"109",
    "addr:postcode":"w1h 4ps",
    "addr:street":"Seymour Buildings Seymour Place",
    "iso:country":"GB",
    "sg:address":"109 Seymour Buildings, Seymour Place",
    "sg:city":"London",
    "sg:classifiers":[
        {
            "category":"Building & Trades",
            "subcategory":"Construction",
            "type":"Services"
        }
    ],
    "sg:postcode":"W1H 4PS",
    "sg:province":"Greater London",
    "sg:tags":[
        "tiling",
        "contractor"
    ],
    "wof:name":"Seymour Ceramics",
    "wof:placetype":"venue"
},
  "geometry": {"coordinates":[-0.16336,51.519329],"type":"Point"}
}