{
  "type": "Feature",
  "properties": {
    "addr:full":"Glan Yr Afon Industrial Estate, Llanbadarn Fawr Aberystwyth Ceredigion SY23 3JQ",
    "addr:postcode":"sy23 3jq",
    "addr:street":"Yr Afon Industrial Estate",
    "iso:country":"GB",
    "sg:address":"Glan Yr Afon Industrial Estate, Llanbadarn Fawr",
    "sg:city":"Aberystwyth",
    "sg:classifiers":[
        {
            "category":"Banks & Credit Unions",
            "subcategory":"Investment Brokerage",
            "type":"Services"
        },
        {
            "category":"Train Station",
            "subcategory":"Rail",
            "type":"Transportation"
        }
    ],
    "sg:phone":"+44 1970 626920",
    "sg:postcode":"SY23 3JQ",
    "sg:province":"Ceredigion",
    "sg:tags":[
        "caravan",
        "hire"
    ],
    "wof:name":"Golden Sands Caravans",
    "wof:placetype":"venue"
},
  "geometry": {"coordinates":[-4.077869,52.41605],"type":"Point"}
}