{
  "type": "Feature",
  "properties": {
    "addr:full":"Holbrook Road, Alvaston Derby Derbyshire DE24 0DD",
    "addr:postcode":"de24 0dd",
    "addr:street":"Holbrook Road",
    "iso:country":"GB",
    "sg:address":"Holbrook Road, Alvaston",
    "sg:city":"Derby",
    "sg:classifiers":[
        {
            "category":"Education",
            "subcategory":"School",
            "type":"Public Place"
        }
    ],
    "sg:phone":"+44 1332 571231",
    "sg:postcode":"DE24 0DD",
    "sg:province":"Derbyshire",
    "sg:tags":[
        "local",
        "authority"
    ],
    "wof:name":"Oakwood Junior School",
    "wof:placetype":"venue"
},
  "geometry": {"coordinates":[-1.4264450073,52.898651123],"type":"Point"}
}