{
  "type": "Feature",
  "properties": {
    "iso:country":"GB",
    "sg:address":"Unit A22 Tonteg Rd, Treforest Indust Est",
    "sg:city":"Pontypridd",
    "sg:classifiers":[
        {
            "category":"Shopping",
            "subcategory":"Clothing, Apparel, & Fashions",
            "type":"Retail Goods"
        }
    ],
    "sg:phone":"+44 1443 843717",
    "sg:postcode":"CF37 5UA",
    "sg:province":"Caerphilly",
    "sg:tags":[
        "clothing",
        "fabric"
    ],
    "wof:name":"Flectalon Ltd",
    "wof:placetype":"venue"
},
  "geometry": {"coordinates":[-3.300638,51.574623],"type":"Point"}
}