{
  "type": "Feature",
  "properties": {
    "addr:full":"49 Charles Street Porth Bridgend CF39 9YD",
    "addr:housenumber":"49",
    "addr:postcode":"cf39 9yd",
    "addr:street":"Charles Street",
    "iso:country":"GB",
    "sg:address":"49 Charles Street",
    "sg:city":"Porth",
    "sg:classifiers":[
        {
            "category":"Building & Trades",
            "subcategory":"Construction",
            "type":"Services"
        }
    ],
    "sg:phone":"+44 1443 685310",
    "sg:postcode":"CF39 9YD",
    "sg:province":"Bridgend",
    "sg:tags":[
        "builder"
    ],
    "sg:website":"http://www.evergray.co.uk",
    "wof:name":"Evergray Ltd",
    "wof:placetype":"venue"
},
  "geometry": {"coordinates":[-3.4069969654,51.6153106689],"type":"Point"}
}