{
  "type": "Feature",
  "properties": {
    "addr:full":"9 Feasegate York North Yorkshire YO1 8SH",
    "addr:housenumber":"9",
    "addr:postcode":"yo1 8sh",
    "addr:street":"Feasegate York",
    "iso:country":"GB",
    "sg:address":"9 Feasegate",
    "sg:city":"York",
    "sg:classifiers":[
        {
            "category":"Shopping",
            "type":"Retail Goods"
        }
    ],
    "sg:phone":"+44 1904 622632",
    "sg:postcode":"YO1 8SH",
    "sg:province":"North Yorkshire",
    "sg:tags":[
        "part",
        "accessory"
    ],
    "wof:name":"Halfords",
    "wof:placetype":"venue"
},
  "geometry": {"coordinates":[-1.082424,53.959206],"type":"Point"}
}