{
  "type": "Feature",
  "properties": {
    "iso:country":"GB",
    "sg:address":"41 Princess Alexandra Walk",
    "sg:city":"Huddersfield",
    "sg:classifiers":[
        {
            "category":"Shopping",
            "subcategory":"Beauty & Cosmetics",
            "type":"Retail Goods"
        }
    ],
    "sg:phone":"+44 1484 432382",
    "sg:postcode":"HD1 2RS",
    "sg:province":"West Yorkshire",
    "sg:tags":[
        "product"
    ],
    "wof:name":"The Body Shop International plc",
    "wof:placetype":"venue"
},
  "geometry": {"coordinates":[-1.7832520008,53.6437072754],"type":"Point"}
}