{
  "type": "Feature",
  "properties": {
    "iso:country":"GB",
    "sg:address":"Kendal House, Towngate, Heptonstall",
    "sg:city":"Hebden Bridge",
    "sg:classifiers":[
        {
            "category":"Building & Trades",
            "subcategory":"Construction",
            "type":"Services"
        }
    ],
    "sg:phone":"+44 1422 842665",
    "sg:postcode":"HX7 7LW",
    "sg:province":"West Yorkshire",
    "sg:tags":[
        "dry",
        "lining",
        "plasterers",
        "screeders"
    ],
    "wof:name":"Norman Bailey",
    "wof:placetype":"venue"
},
  "geometry": {"coordinates":[-2.0206460953,53.7489852905],"type":"Point"}
}