{
  "type": "Feature",
  "properties": {
    "addr:full":"Ty Coch Industrial Estate, Ty Coch Way Cwmbran Monmouthshire NP44 7XX",
    "addr:postcode":"np44 7xx",
    "addr:street":"Industrial Estate Ty Coch Way",
    "iso:country":"GB",
    "sg:address":"Ty Coch Industrial Estate, Ty Coch Way",
    "sg:city":"Cwmbran",
    "sg:classifiers":[
        {
            "category":"Professional",
            "subcategory":"Computer Services",
            "type":"Services"
        }
    ],
    "sg:phone":"+44 1633 871111",
    "sg:postcode":"NP44 7XX",
    "sg:province":"Monmouthshire",
    "sg:tags":[
        "system",
        "software"
    ],
    "wof:name":"Gec Marconi S3i Ltd",
    "wof:placetype":"venue"
},
  "geometry": {"coordinates":[-3.024229,51.644211],"type":"Point"}
}