{
  "type": "Feature",
  "properties": {
    "addr:full":"Ury Home Farm Stonehaven Aberdeenshire AB39 3ST",
    "addr:postcode":"ab39 3st",
    "addr:street":"Stonehaven",
    "iso:country":"GB",
    "sg:address":"Ury Home Farm",
    "sg:city":"Stonehaven",
    "sg:classifiers":[
        {
            "category":"Farming",
            "subcategory":"Farm",
            "type":"Manufacturing & Wholesale Goods"
        }
    ],
    "sg:phone":"+44 1569 762714",
    "sg:postcode":"AB39 3ST",
    "sg:province":"Aberdeenshire",
    "sg:tags":[
        "mixed",
        "crop"
    ],
    "wof:name":"Ury Estate Ltd.",
    "wof:placetype":"venue"
},
  "geometry": {"coordinates":[-2.2087590694,56.9637413025],"type":"Point"}
}