{
  "type": "Feature",
  "properties": {
    "addr:full":"Higham House, New Bridge Streetwest Newcastle-upon-tyne Tyne and Wear NE1 8AH",
    "addr:postcode":"ne1 8ah",
    "addr:street":"New",
    "iso:country":"GB",
    "sg:address":"Higham House, New Bridge Streetwest",
    "sg:city":"Newcastle-upon-tyne",
    "sg:classifiers":[
        {
            "category":"Insurance",
            "subcategory":"Insurance Agent",
            "type":"Services"
        }
    ],
    "sg:phone":"+44 191 261 1211",
    "sg:postcode":"NE1 8AH",
    "sg:province":"Tyne and Wear",
    "wof:name":"Guardian Insurance",
    "wof:placetype":"venue"
},
  "geometry": {"coordinates":[-1.608274,54.97459],"type":"Point"}
}