{
  "type": "Feature",
  "properties": {
    "iso:country":"GB",
    "sg:address":"227 London Road",
    "sg:city":"Portsmouth",
    "sg:classifiers":[
        {
            "category":"Retail",
            "subcategory":"Auto Repair",
            "type":"Services"
        }
    ],
    "sg:postcode":"PO2 9AJ",
    "sg:province":"Hampshire",
    "sg:tags":[
        "car",
        "upholsterer"
    ],
    "wof:name":"Pompey Valeting Ltd",
    "wof:placetype":"venue"
},
  "geometry": {"coordinates":[-1.0770740509,50.820438385],"type":"Point"}
}