{
  "type": "Feature",
  "properties": {
    "addr:full":"70 Gowthorpe Selby East Riding of Yorkshire YO8 4ET",
    "addr:housenumber":"70",
    "addr:postcode":"yo8 4et",
    "addr:street":"Gowthorpe",
    "iso:country":"GB",
    "sg:address":"70 Gowthorpe",
    "sg:city":"Selby",
    "sg:classifiers":[
        {
            "category":"Personal",
            "subcategory":"Beauty Salon",
            "type":"Services"
        }
    ],
    "sg:phone":"+44 1757 709461",
    "sg:postcode":"YO8 4ET",
    "sg:province":"East Riding of Yorkshire",
    "sg:tags":[
        "unisex",
        "hairdresser"
    ],
    "wof:name":"Patricia & John York",
    "wof:placetype":"venue"
},
  "geometry": {"coordinates":[-1.073306,53.783459],"type":"Point"}
}