{
  "type": "Feature",
  "properties": {
    "iso:country":"GB",
    "sg:address":"87a John Finnie Street",
    "sg:city":"Kilmarnock",
    "sg:classifiers":[
        {
            "category":"Government",
            "subcategory":"Customs House",
            "type":"Public Place"
        }
    ],
    "sg:phone":"+44 1563 572422",
    "sg:postcode":"KA1 1BG",
    "sg:province":"East Ayrshire",
    "sg:tags":[
        "clearance"
    ],
    "wof:name":"Furniture Mart",
    "wof:placetype":"venue"
},
  "geometry": {"coordinates":[-4.5000309944,55.6084327698],"type":"Point"}
}