{
  "type": "Feature",
  "properties": {
    "addr:full":"Unit 6b, Old Seager Distillery, Brookmill Road London Greater London SE8 4HH",
    "addr:housenumber":"unit 6b",
    "addr:postcode":"se8 4hh",
    "addr:street":"Old Seager;Brookmill Road",
    "iso:country":"GB",
    "sg:address":"Unit 6b, Old Seager Distillery, Brookmill Road",
    "sg:city":"London",
    "sg:classifiers":[
        {
            "category":"Professional",
            "subcategory":"Business Services",
            "type":"Services"
        }
    ],
    "sg:phone":"+44 20 8469 3331",
    "sg:postcode":"SE8 4HH",
    "sg:province":"Greater London",
    "sg:tags":[
        "house",
        "mailing"
    ],
    "wof:name":"Reader Mailing Ltd.",
    "wof:placetype":"venue"
},
  "geometry": {"coordinates":[-0.0232599992,51.4743614197],"type":"Point"}
}