{
  "type": "Feature",
  "properties": {
    "iso:country":"GB",
    "sg:address":"71 Evington Road",
    "sg:city":"Leicester",
    "sg:classifiers":[
        {
            "category":"Health Services",
            "subcategory":"Doctor",
            "type":"Services"
        }
    ],
    "sg:phone":"+44 116 212 0212",
    "sg:postcode":"LE2 1QH",
    "sg:province":"Leicestershire",
    "sg:tags":[
        "practitioners"
    ],
    "wof:name":"The Maples Surgery",
    "wof:placetype":"venue"
},
  "geometry": {"coordinates":[-1.113423,52.626465],"type":"Point"}
}