{
  "type": "Feature",
  "properties": {
    "addr:full":"53 Moorland Road St Austell Cornwall PL25 5BS",
    "addr:housenumber":"53",
    "addr:postcode":"pl25 5bs",
    "addr:street":"Moorland Road",
    "iso:country":"GB",
    "sg:address":"53 Moorland Road",
    "sg:city":"St Austell",
    "sg:classifiers":[
        {
            "category":"Building & Trades",
            "subcategory":"Construction",
            "type":"Services"
        }
    ],
    "sg:phone":"+44 1726 65687",
    "sg:postcode":"PL25 5BS",
    "sg:province":"Cornwall",
    "sg:tags":[
        "builder"
    ],
    "wof:name":"Geoff Varker Building Contractor",
    "wof:placetype":"venue"
},
  "geometry": {"coordinates":[-4.796777,50.336666],"type":"Point"}
}