{
  "type": "Feature",
  "properties": {
    "addr:full":"Cos Lane Glenrothes Fife KY7 4AQ",
    "addr:postcode":"ky7 4aq",
    "addr:street":"Cos Lane",
    "iso:country":"GB",
    "sg:address":"Cos Lane",
    "sg:city":"Glenrothes",
    "sg:classifiers":[
        {
            "category":"Retail",
            "subcategory":"Veterinary Services",
            "type":"Services"
        }
    ],
    "sg:phone":"+44 1592 757373",
    "sg:postcode":"KY7 4AQ",
    "sg:province":"Fife",
    "sg:tags":[
        "surgeon"
    ],
    "wof:name":"The Howe Veterinary Centre",
    "wof:placetype":"venue"
},
  "geometry": {"coordinates":[-3.1575109959,56.190738678],"type":"Point"}
}