{
  "type": "Feature",
  "properties": {
    "addr:full":"124 High Street, Hadleigh Benfleet Essex SS7 2PB",
    "addr:housenumber":"124",
    "addr:postcode":"ss7 2pb",
    "addr:street":"High Street",
    "iso:country":"GB",
    "sg:address":"124 High Street, Hadleigh",
    "sg:city":"Benfleet",
    "sg:classifiers":[
        {
            "category":"Autos & Motor Vehicles",
            "subcategory":"Automobile Sales",
            "type":"Retail Goods"
        }
    ],
    "sg:phone":"+44 1702 555590",
    "sg:postcode":"SS7 2PB",
    "sg:province":"Essex",
    "sg:tags":[
        "car"
    ],
    "wof:name":"Esso Garage",
    "wof:placetype":"venue"
},
  "geometry": {"coordinates":[0.6086810231,51.5527572632],"type":"Point"}
}