{
  "type": "Feature",
  "properties": {
    "iso:country":"GB",
    "sg:address":"Shalford Ho, Ricksons La",
    "sg:city":"Leatherhead",
    "sg:classifiers":[
        {
            "category":"Professional",
            "subcategory":"Art Services",
            "type":"Services"
        }
    ],
    "sg:phone":"+44 1483 284409",
    "sg:postcode":"KT24 6HU",
    "sg:province":"Surrey",
    "sg:tags":[
        "picture",
        "restoration",
        "cleaning"
    ],
    "wof:name":"Memory Lane Productions",
    "wof:placetype":"venue"
},
  "geometry": {"coordinates":[-0.45478,51.271141],"type":"Point"}
}