{
  "type": "Feature",
  "properties": {
    "addr:full":"1 Jubilee Road Burgess Hill East Sussex RH15 9TL",
    "addr:housenumber":"1",
    "addr:postcode":"rh15 9tl",
    "addr:street":"Jubilee Road",
    "iso:country":"GB",
    "sg:address":"1 Jubilee Road",
    "sg:city":"Burgess Hill",
    "sg:classifiers":[
        {
            "category":"Professional",
            "subcategory":"Printing & Photocopies",
            "type":"Services"
        }
    ],
    "sg:phone":"+44 1444 480700",
    "sg:postcode":"RH15 9TL",
    "sg:province":"East Sussex",
    "sg:tags":[
        "printer"
    ],
    "sg:website":"http://www.newmanthomson.co.uk",
    "wof:name":"Newman Thomson Ltd.",
    "wof:placetype":"venue"
},
  "geometry": {"coordinates":[-0.1484010071,50.9532470703],"type":"Point"}
}