{
  "type": "Feature",
  "properties": {
    "addr:full":"20/22 Laithes Crescent Barnsley South Yorkshire S71 3AE",
    "addr:housenumber":"20 / 22",
    "addr:postcode":"s71 3ae",
    "addr:street":"Laithes Crescent;Yorkshire",
    "iso:country":"GB",
    "sg:address":"20/22 Laithes Crescent",
    "sg:city":"Barnsley",
    "sg:classifiers":[
        {
            "category":"Food & Beverages",
            "subcategory":"Meat & Fish",
            "type":"Retail Goods"
        }
    ],
    "sg:phone":"+44 1226 205672",
    "sg:postcode":"S71 3AE",
    "sg:province":"South Yorkshire",
    "sg:tags":[
        "butcher"
    ],
    "wof:name":"Hopkinsons",
    "wof:placetype":"venue"
},
  "geometry": {"coordinates":[-1.4633849859,53.5793190002],"type":"Point"}
}