{
  "type": "Feature",
  "properties": {
    "addr:full":"5 Aigburth Hall Avenue Liverpool Merseyside L19 9EA",
    "addr:housenumber":"5",
    "addr:postcode":"l19 9ea",
    "addr:street":"Aigburth Hall Avenue",
    "iso:country":"GB",
    "sg:address":"5 Aigburth Hall Avenue",
    "sg:city":"Liverpool",
    "sg:classifiers":[
        {
            "category":"Home & Garden",
            "subcategory":"Garden Supply",
            "type":"Retail Goods"
        }
    ],
    "sg:phone":"+44 151 427 3120",
    "sg:postcode":"L19 9EA",
    "sg:province":"Merseyside",
    "sg:tags":[
        "nursery",
        "centre"
    ],
    "wof:name":"Aigburth Hall Nurseries",
    "wof:placetype":"venue"
},
  "geometry": {"coordinates":[-2.917933,53.365253],"type":"Point"}
}