{
  "type": "Feature",
  "properties": {
    "iso:country":"GB",
    "sg:address":"59 Victoria Road",
    "sg:city":"Surbiton",
    "sg:classifiers":[
        {
            "category":"Professional",
            "subcategory":"Lawyer & Legal Services",
            "type":"Services"
        }
    ],
    "sg:phone":"+44 20 8390 0185",
    "sg:postcode":"KT6 4NQ",
    "sg:province":"Surrey",
    "sg:tags":[
        "solicitor"
    ],
    "wof:name":"Hill Johnson",
    "wof:placetype":"venue"
},
  "geometry": {"coordinates":[-0.3072830141,51.391834259],"type":"Point"}
}