{
  "type": "Feature",
  "properties": {
    "iso:country":"GB",
    "sg:address":"83 Owen Street",
    "sg:city":"Tipton",
    "sg:classifiers":[
        {
            "category":"Food & Beverages",
            "subcategory":"Supermarket",
            "type":"Retail Goods"
        }
    ],
    "sg:phone":"+44 121 557 8741",
    "sg:postcode":"DY4 8EX",
    "sg:province":"West Midlands",
    "wof:name":"Bains Supasave",
    "wof:placetype":"venue"
},
  "geometry": {"coordinates":[-2.068283,52.5294],"type":"Point"}
}