{
  "type": "Feature",
  "properties": {
    "iso:country":"GB",
    "sg:address":"Almeria, Thorpe Lea Rd",
    "sg:city":"Egham",
    "sg:classifiers":[
        {
            "category":"Wholesale",
            "subcategory":"Fruits & Vegetables",
            "type":"Manufacturing & Wholesale Goods"
        }
    ],
    "sg:phone":"+44 1784 433635",
    "sg:postcode":"TW20 8JL",
    "sg:province":"Surrey",
    "wof:name":"C.R Mewes Ltd",
    "wof:placetype":"venue"
},
  "geometry": {"coordinates":[-0.536077,51.406357],"type":"Point"}
}