{
  "type": "Feature",
  "properties": {
    "addr:full":"2 Lower Rd Loughton Essex IG10 2RS",
    "addr:housenumber":"2",
    "addr:postcode":"ig10 2rs",
    "addr:street":"Lower Rd",
    "iso:country":"GB",
    "sg:address":"2 Lower Rd",
    "sg:city":"Loughton",
    "sg:classifiers":[
        {
            "category":"Retail",
            "subcategory":"Repair Shop",
            "type":"Services"
        }
    ],
    "sg:phone":"+44 20 8532 0332",
    "sg:postcode":"IG10 2RS",
    "sg:province":"Essex",
    "sg:tags":[
        "clocks",
        "watch"
    ],
    "wof:name":"Craig Midgley Antique Clocks",
    "wof:placetype":"venue"
},
  "geometry": {"coordinates":[0.067521,51.656788],"type":"Point"}
}