{
  "type": "Feature",
  "properties": {
    "addr:full":"179 Portland Road Hove East Sussex BN3 5QJ",
    "addr:housenumber":"179",
    "addr:postcode":"bn3 5qj",
    "addr:street":"Portland Road",
    "iso:country":"GB",
    "sg:address":"179 Portland Road",
    "sg:city":"Hove",
    "sg:classifiers":[
        {
            "category":"Building & Trades",
            "subcategory":"Plumbing",
            "type":"Services"
        }
    ],
    "sg:postcode":"BN3 5QJ",
    "sg:province":"East Sussex",
    "sg:tags":[
        "heating"
    ],
    "wof:name":"A R Evans Plumbing & Heating",
    "wof:placetype":"venue"
},
  "geometry": {"coordinates":[-0.1886260062,50.8338279724],"type":"Point"}
}