{
  "type": "Feature",
  "properties": {
    "addr:full":"165 St. Clair St Kirkcaldy Fife KY1 2BX",
    "addr:housenumber":"165",
    "addr:postcode":"ky1 2bx",
    "addr:street":"St. Clair St",
    "iso:country":"GB",
    "sg:address":"165 St. Clair St",
    "sg:city":"Kirkcaldy",
    "sg:classifiers":[
        {
            "category":"Shopping",
            "subcategory":"Florist",
            "type":"Retail Goods"
        }
    ],
    "sg:phone":"+44 1592 590777",
    "sg:postcode":"KY1 2BX",
    "sg:province":"Fife",
    "wof:name":"The Flower Arranger",
    "wof:placetype":"venue"
},
  "geometry": {"coordinates":[-3.1393589973,56.1270599365],"type":"Point"}
}