{
  "type": "Feature",
  "properties": {
    "iso:country":"GB",
    "sg:address":"50 Hawes Side La",
    "sg:city":"Blackpool",
    "sg:classifiers":[
        {
            "category":"Personal",
            "type":"Services"
        }
    ],
    "sg:phone":"+44 1253 693874",
    "sg:postcode":"FY4 4AS",
    "sg:province":"Lancashire",
    "sg:tags":[
        "wedding"
    ],
    "wof:name":"Berry,James Anthony,",
    "wof:placetype":"venue"
},
  "geometry": {"coordinates":[-3.032182,53.798798],"type":"Point"}
}