{
  "type": "Feature",
  "properties": {
    "iso:country":"GB",
    "sg:address":"42 Munro Place",
    "sg:city":"Glasgow",
    "sg:classifiers":[
        {
            "category":"Restaurant",
            "type":"Food & Drink"
        }
    ],
    "sg:phone":"+44 141 959 2722",
    "sg:postcode":"G13 2UW",
    "sg:province":"Glasgow City",
    "wof:name":"Mulberrys Restaurant",
    "wof:placetype":"venue"
},
  "geometry": {"coordinates":[-4.3328490257,55.8919868469],"type":"Point"}
}