{
  "type": "Feature",
  "properties": {
    "addr:full":"2 Kings Way, South Woodham Ferrers Chelmsford Essex CM3 5QH",
    "addr:housenumber":"2",
    "addr:postcode":"cm3 5qh",
    "addr:street":"Kings Way",
    "iso:country":"GB",
    "sg:address":"2 Kings Way, South Woodham Ferrers",
    "sg:city":"Chelmsford",
    "sg:classifiers":[
        {
            "category":"Home & Garden",
            "subcategory":"Household Appliances",
            "type":"Retail Goods"
        }
    ],
    "sg:phone":"+44 1245 323000",
    "sg:postcode":"CM3 5QH",
    "sg:province":"Essex",
    "sg:tags":[
        "electrical"
    ],
    "wof:name":"Chambers Domestic Repairs",
    "wof:placetype":"venue"
},
  "geometry": {"coordinates":[0.603572,51.651634],"type":"Point"}
}