{
  "type": "Feature",
  "properties": {
    "iso:country":"GB",
    "sg:address":"81 Lightburn Road",
    "sg:city":"Glasgow",
    "sg:classifiers":[
        {
            "category":"Retail",
            "subcategory":"Auto Repair",
            "type":"Services"
        }
    ],
    "sg:phone":"+44 141 646 1677",
    "sg:postcode":"G72 8UD",
    "sg:province":"South Lanarkshire",
    "sg:tags":[
        "modification",
        "garage",
        "related"
    ],
    "wof:name":"Lightburn Motors",
    "wof:placetype":"venue"
},
  "geometry": {"coordinates":[-4.1388,55.80986],"type":"Point"}
}