{
  "type": "Feature",
  "properties": {
    "iso:country":"GB",
    "sg:address":"60-61 Nile Road, Gorleston",
    "sg:city":"Great Yarmouth",
    "sg:classifiers":[
        {
            "category":"Building & Trades",
            "subcategory":"Landscaping Services",
            "type":"Services"
        }
    ],
    "sg:phone":"+44 1493 442703",
    "sg:postcode":"NR31 6AS",
    "sg:province":"Norfolk",
    "sg:tags":[
        "pond",
        "aquarium"
    ],
    "wof:name":"Koi-Joy",
    "wof:placetype":"venue"
},
  "geometry": {"coordinates":[1.7276829481,52.5722961426],"type":"Point"}
}