{
  "type": "Feature",
  "properties": {
    "iso:country":"GB",
    "sg:address":"1 Manor Cottage, Kilham Lane",
    "sg:city":"Cheltenham",
    "sg:classifiers":[
        {
            "category":"Building & Trades",
            "subcategory":"Plumbing",
            "type":"Services"
        }
    ],
    "sg:postcode":"GL54 4HX",
    "sg:province":"Gloucestershire",
    "sg:tags":[
        "heating"
    ],
    "wof:name":"Fraser Morphew Plumbing",
    "wof:placetype":"venue"
},
  "geometry": {"coordinates":[-1.94901,51.863602],"type":"Point"}
}