{
  "type": "Feature",
  "properties": {
    "iso:country":"GB",
    "sg:address":"23 Dorset Street",
    "sg:city":"London",
    "sg:classifiers":[
        {
            "category":"Professional",
            "subcategory":"Accounting & Tax Preparation",
            "type":"Services"
        }
    ],
    "sg:phone":"+44 20 7935 0163",
    "sg:postcode":"W1U 6EL",
    "sg:province":"Greater London",
    "sg:tags":[
        "accountant"
    ],
    "wof:name":"Scodie Deyong",
    "wof:placetype":"venue"
},
  "geometry": {"coordinates":[-0.158289,51.519222],"type":"Point"}
}