{
  "type": "Feature",
  "properties": {
    "iso:country":"GB",
    "sg:address":"854 Osmaston Road",
    "sg:city":"Derby",
    "sg:classifiers":[
        {
            "category":"Shopping",
            "subcategory":"News",
            "type":"Retail Goods"
        }
    ],
    "sg:phone":"+44 1332 368299",
    "sg:postcode":"DE24 9AB",
    "sg:province":"Derbyshire",
    "sg:tags":[
        "newsagent"
    ],
    "wof:name":"Arcade News",
    "wof:placetype":"venue"
},
  "geometry": {"coordinates":[-1.451644,52.889965],"type":"Point"}
}