{
  "type": "Feature",
  "properties": {
    "addr:full":"91 Corbets Tey Rd Upminster Essex RM14 2AH",
    "addr:housenumber":"91",
    "addr:postcode":"rm14 2ah",
    "addr:street":"Corbets Tey Rd",
    "iso:country":"GB",
    "sg:address":"91 Corbets Tey Rd",
    "sg:city":"Upminster",
    "sg:classifiers":[
        {
            "category":"Personal",
            "subcategory":"Beauty Salon",
            "type":"Services"
        }
    ],
    "sg:phone":"+44 1708 222511",
    "sg:postcode":"RM14 2AH",
    "sg:province":"Essex",
    "sg:tags":[
        "unisex",
        "hairdresser"
    ],
    "wof:name":"Headjogs",
    "wof:placetype":"venue"
},
  "geometry": {"coordinates":[0.2478850037,51.5533943176],"type":"Point"}
}