{
  "type": "Feature",
  "properties": {
    "addr:full":"7-7a Feasegate York North Yorkshire YO1 8SH",
    "addr:housenumber":"7-7a",
    "addr:postcode":"yo1 8sh",
    "addr:street":"Feasegate York",
    "iso:country":"GB",
    "sg:address":"7-7a Feasegate",
    "sg:city":"York",
    "sg:classifiers":[
        {
            "category":"Banks & Credit Unions",
            "subcategory":"Financial Services",
            "type":"Services"
        }
    ],
    "sg:phone":"+44 1904 638771",
    "sg:postcode":"YO1 8SH",
    "sg:province":"North Yorkshire",
    "sg:tags":[
        "building",
        "society"
    ],
    "wof:name":"Yorkshire Building Society",
    "wof:placetype":"venue"
},
  "geometry": {"coordinates":[-1.082405,53.959248],"type":"Point"}
}