{
  "type": "Feature",
  "properties": {
    "addr:full":"Kilkenny Cotts, Andoversford Cheltenham Gloucestershire GL54 4LN",
    "addr:postcode":"gl54 4ln",
    "iso:country":"GB",
    "sg:address":"Kilkenny Cotts, Andoversford",
    "sg:city":"Cheltenham",
    "sg:classifiers":[
        {
            "category":"Professional",
            "subcategory":"Business Services",
            "type":"Services"
        }
    ],
    "sg:postcode":"GL54 4LN",
    "sg:province":"Gloucestershire",
    "sg:tags":[
        "import",
        "export",
        "agent"
    ],
    "wof:name":"Boardman Match",
    "wof:placetype":"venue"
},
  "geometry": {"coordinates":[-1.969802,51.872612],"type":"Point"}
}