{
  "type": "Feature",
  "properties": {
    "addr:full":"4 Pinfold, South Cave Brough East Riding of Yorkshire HU15 2EZ",
    "addr:housenumber":"4",
    "addr:postcode":"hu15 2ez",
    "addr:street":"Pinfold",
    "iso:country":"GB",
    "sg:address":"4 Pinfold, South Cave",
    "sg:city":"Brough",
    "sg:classifiers":[
        {
            "category":"Food & Beverages",
            "subcategory":"Supermarket",
            "type":"Retail Goods"
        }
    ],
    "sg:phone":"+44 1430 423160",
    "sg:postcode":"HU15 2EZ",
    "sg:province":"East Riding of Yorkshire",
    "wof:name":"Costcutter",
    "wof:placetype":"venue"
},
  "geometry": {"coordinates":[-0.6189290285,53.7648696899],"type":"Point"}
}