{
  "type": "Feature",
  "properties": {
    "iso:country":"GB",
    "sg:address":"17 Park Hill Road",
    "sg:city":"Torquay",
    "sg:classifiers":[
        {
            "category":"Community Center",
            "type":"Public Place"
        }
    ],
    "sg:phone":"+44 1803 293741",
    "sg:postcode":"TQ1 2AL",
    "sg:province":"Devon",
    "sg:tags":[
        "centre"
    ],
    "wof:name":"Memorial Hall",
    "wof:placetype":"venue"
},
  "geometry": {"coordinates":[-3.521365881,50.461063385],"type":"Point"}
}