{
  "type": "Feature",
  "properties": {
    "iso:country":"GB",
    "sg:address":"The Infant School Hall, St Edwards School, Ashley Rd",
    "sg:city":"Cheltenham",
    "sg:classifiers":[
        {
            "category":"Personal",
            "type":"Services"
        }
    ],
    "sg:phone":"+44 1242 234154",
    "sg:postcode":"GL52 6NS",
    "sg:province":"Gloucestershire",
    "sg:tags":[
        "slimming",
        "product"
    ],
    "wof:name":"Slimming World",
    "wof:placetype":"venue"
},
  "geometry": {"coordinates":[-2.04964,51.892479],"type":"Point"}
}