{
  "type": "Feature",
  "properties": {
    "addr:full":"Unit 3, 2 Willis Way, Fleet Lane Industrial Estate Poole Dorset BH15 3SS",
    "addr:housenumber":"unit;2",
    "addr:postcode":"bh15 3ss",
    "addr:street":"Willis Way Fleet Lane Industrial Estate",
    "iso:country":"GB",
    "sg:address":"Unit 3, 2 Willis Way, Fleet Lane Industrial Estate",
    "sg:city":"Poole",
    "sg:classifiers":[
        {
            "category":"Retail",
            "subcategory":"Laundry & Dry Cleaning",
            "type":"Services"
        }
    ],
    "sg:phone":"+44 1202 679299",
    "sg:postcode":"BH15 3SS",
    "sg:province":"Dorset",
    "sg:tags":[
        "launderette"
    ],
    "wof:name":"Premier Laundry Services",
    "wof:placetype":"venue"
},
  "geometry": {"coordinates":[-1.988545,50.729275],"type":"Point"}
}