{
  "type": "Feature",
  "properties": {
    "addr:full":"42 Fore Street, Shaldon Teignmouth Devon TQ14 0EA",
    "addr:housenumber":"42",
    "addr:postcode":"tq14 0ea",
    "addr:street":"Fore Street",
    "iso:country":"GB",
    "sg:address":"42 Fore Street, Shaldon",
    "sg:city":"Teignmouth",
    "sg:classifiers":[
        {
            "category":"Place Of Worship",
            "type":"Public Place"
        }
    ],
    "sg:phone":"+44 1626 873410",
    "sg:postcode":"TQ14 0EA",
    "sg:province":"Devon",
    "wof:name":"St.Ignatius of Loyola R C Church",
    "wof:placetype":"venue"
},
  "geometry": {"coordinates":[-3.507263,50.540607],"type":"Point"}
}