{
  "type": "Feature",
  "properties": {
    "addr:full":"Dean Court, Dean Crescent, Orrell Wigan Lancashire WN5 0HY",
    "addr:postcode":"wn5 0hy",
    "addr:street":"Dean Court Dean Crescent Orrell",
    "iso:country":"GB",
    "sg:address":"Dean Court, Dean Crescent, Orrell",
    "sg:city":"Wigan",
    "sg:classifiers":[
        {
            "category":"Organizations",
            "subcategory":"Community Association",
            "type":"Services"
        }
    ],
    "sg:phone":"+44 1942 215084",
    "sg:postcode":"WN5 0HY",
    "sg:province":"Lancashire",
    "sg:tags":[
        "society",
        "housing"
    ],
    "wof:name":"Anchor Trust",
    "wof:placetype":"venue"
},
  "geometry": {"coordinates":[-2.685845,53.547329],"type":"Point"}
}