{
  "type": "Feature",
  "properties": {
    "iso:country":"GB",
    "sg:address":"A-1 32 St. Vincent Terrace",
    "sg:city":"Glasgow",
    "sg:classifiers":[
        {
            "category":"Professional",
            "type":"Services"
        }
    ],
    "sg:phone":"+44 141 572 0866",
    "sg:postcode":"G3 8UU",
    "sg:province":"Glasgow City",
    "sg:tags":[
        "entertainer"
    ],
    "wof:name":"Bees Wax Entertainment Agency Ltd",
    "wof:placetype":"venue"
},
  "geometry": {"coordinates":[-4.27401,55.862709],"type":"Point"}
}