{
  "type": "Feature",
  "properties": {
    "addr:full":"Fairview, Nantucket Avenue Milford Haven Pembrokeshire SA73 2BG",
    "addr:postcode":"sa73 2bg",
    "addr:street":"Nantucket Avenue",
    "iso:country":"GB",
    "sg:address":"Fairview, Nantucket Avenue",
    "sg:city":"Milford Haven",
    "sg:classifiers":[
        {
            "category":"Food & Beverages",
            "subcategory":"Meat & Fish",
            "type":"Retail Goods"
        }
    ],
    "sg:postcode":"SA73 2BG",
    "sg:province":"Pembrokeshire",
    "sg:tags":[
        "chip"
    ],
    "wof:name":"Haven Fish Cafe",
    "wof:placetype":"venue"
},
  "geometry": {"coordinates":[-5.027044,51.716808],"type":"Point"}
}