{
  "type": "Feature",
  "properties": {
    "addr:full":"17 Central Square Cardiff Cardiff CF10 1EP",
    "addr:housenumber":"17",
    "addr:postcode":"cf10 1ep",
    "addr:street":"Central Square",
    "iso:country":"GB",
    "sg:address":"17 Central Square",
    "sg:city":"Cardiff",
    "sg:classifiers":[
        {
            "category":"Fast Food",
            "type":"Food & Drink"
        },
        {
            "category":"Restaurant",
            "type":"Food & Drink"
        }
    ],
    "sg:phone":"+44 29 2022 6200",
    "sg:postcode":"CF10 1EP",
    "sg:province":"Cardiff",
    "sg:tags":[
        "away",
        "take"
    ],
    "wof:name":"Burger King",
    "wof:placetype":"venue"
},
  "geometry": {"coordinates":[-3.1807150841,51.4766998291],"type":"Point"}
}