{
  "type": "Feature",
  "properties": {
    "addr:full":"54 Old Christchurch Road Bournemouth Dorset BH1 1LL",
    "addr:housenumber":"54",
    "addr:postcode":"bh1 1ll",
    "addr:street":"Old Christchurch Road",
    "iso:country":"GB",
    "sg:address":"54 Old Christchurch Road",
    "sg:city":"Bournemouth",
    "sg:classifiers":[
        {
            "category":"Shopping",
            "subcategory":"Mobile Phones",
            "type":"Retail Goods"
        }
    ],
    "sg:phone":"+44 1202 552588",
    "sg:postcode":"BH1 1LL",
    "sg:province":"Dorset",
    "wof:name":"K J C Mobile Phones",
    "wof:placetype":"venue"
},
  "geometry": {"coordinates":[-1.8766440153,50.7210388184],"type":"Point"}
}