{
  "type": "Feature",
  "properties": {
    "addr:full":"4 Marshall Rd Eastbourne East Sussex BN22 9AT",
    "addr:housenumber":"4",
    "addr:postcode":"bn22 9at",
    "addr:street":"Marshall Rd",
    "iso:country":"GB",
    "sg:address":"4 Marshall Rd",
    "sg:city":"Eastbourne",
    "sg:classifiers":[
        {
            "category":"Manufacturing",
            "subcategory":"Wood Products",
            "type":"Manufacturing & Wholesale Goods"
        },
        {
            "category":"Home & Garden",
            "subcategory":"Furniture",
            "type":"Retail Goods"
        }
    ],
    "sg:phone":"+44 1323 507377",
    "sg:postcode":"BN22 9AT",
    "sg:province":"East Sussex",
    "sg:tags":[
        "maker",
        "cabinet"
    ],
    "wof:name":"Work Top Worlds",
    "wof:placetype":"venue"
},
  "geometry": {"coordinates":[0.2840999961,50.7943954468],"type":"Point"}
}