{
  "type": "Feature",
  "properties": {
    "iso:country":"GB",
    "sg:address":"75-80 High Street",
    "sg:city":"Birmingham",
    "sg:classifiers":[
        {
            "category":"Autos & Motor Vehicles",
            "subcategory":"Automobile Sales",
            "type":"Retail Goods"
        }
    ],
    "sg:phone":"+44 121 252 7000",
    "sg:postcode":"B12 0LL",
    "sg:province":"West Midlands",
    "sg:tags":[
        "car"
    ],
    "wof:name":"Renault Birmingham",
    "wof:placetype":"venue"
},
  "geometry": {"coordinates":[-1.895139,52.479019],"type":"Point"}
}