{
  "type": "Feature",
  "properties": {
    "addr:full":"1 Hatcham Park Road London Greater London SE14 5QE",
    "addr:housenumber":"1",
    "addr:postcode":"se14 5qe",
    "addr:street":"Hatcham Park Road",
    "iso:country":"GB",
    "sg:address":"1 Hatcham Park Road",
    "sg:city":"London",
    "sg:classifiers":[
        {
            "category":"Retail",
            "subcategory":"Auto Repair",
            "type":"Services"
        }
    ],
    "sg:phone":"+44 20 7732 5251",
    "sg:postcode":"SE14 5QE",
    "sg:province":"Greater London",
    "sg:tags":[
        "modification",
        "garage"
    ],
    "wof:name":"Hatcham Motor Services",
    "wof:placetype":"venue"
},
  "geometry": {"coordinates":[-0.0466770008,51.4754524231],"type":"Point"}
}