{
  "type": "Feature",
  "properties": {
    "addr:full":"Well House, Copgrove Harrogate North Yorkshire HG3 3SS",
    "addr:postcode":"hg3 3ss",
    "iso:country":"GB",
    "sg:address":"Well House, Copgrove",
    "sg:city":"Harrogate",
    "sg:classifiers":[
        {
            "category":"Farming",
            "subcategory":"Farm",
            "type":"Manufacturing & Wholesale Goods"
        }
    ],
    "sg:phone":"+44 1423 340514",
    "sg:postcode":"HG3 3SS",
    "sg:province":"North Yorkshire",
    "sg:tags":[
        "mixed",
        "crop"
    ],
    "wof:name":"K & E A Hogg",
    "wof:placetype":"venue"
},
  "geometry": {"coordinates":[-1.5011390448,54.0690917969],"type":"Point"}
}