{
  "type": "Feature",
  "properties": {
    "addr:full":"Old Stables, Rear Of Chorley Lancashire PR7 2SJ",
    "addr:postcode":"pr7 2sj",
    "iso:country":"GB",
    "sg:address":"Old Stables, Rear Of",
    "sg:city":"Chorley",
    "sg:classifiers":[
        {
            "category":"Shopping",
            "subcategory":"Stationery & Office Supplies",
            "type":"Retail Goods"
        }
    ],
    "sg:phone":"+44 1257 269293",
    "sg:postcode":"PR7 2SJ",
    "sg:province":"Lancashire",
    "sg:tags":[
        "item",
        "promotional"
    ],
    "wof:name":"Pictureman Rock & Promotional Items",
    "wof:placetype":"venue"
},
  "geometry": {"coordinates":[-2.6321339607,53.6520881653],"type":"Point"}
}