{
  "type": "Feature",
  "properties": {
    "iso:country":"GB",
    "sg:address":"Northwick Close",
    "sg:city":"Worcester",
    "sg:classifiers":[
        {
            "category":"Arena",
            "subcategory":"Sports Club",
            "type":"Entertainment"
        }
    ],
    "sg:phone":"+44 1905 451092",
    "sg:postcode":"WR3 7EF",
    "sg:province":"Worcestershire",
    "wof:name":"Worcester Lawn Tennis Club",
    "wof:placetype":"venue"
},
  "geometry": {"coordinates":[-2.2336258888,52.2152023315],"type":"Point"}
}