{
  "type": "Feature",
  "properties": {
    "addr:full":"Rose Cottage, Chapel Lane, Spalford Newark Lincolnshire NG23 7HD",
    "addr:postcode":"ng23 7hd",
    "addr:street":"Chapel Lane",
    "iso:country":"GB",
    "sg:address":"Rose Cottage, Chapel Lane, Spalford",
    "sg:city":"Newark",
    "sg:classifiers":[
        {
            "category":"Professional",
            "type":"Services"
        },
        {
            "category":"Banks & Credit Unions",
            "subcategory":"Investment Brokerage",
            "type":"Services"
        }
    ],
    "sg:phone":"+44 1522 778256",
    "sg:postcode":"NG23 7HD",
    "sg:province":"Lincolnshire",
    "sg:tags":[
        "farm",
        "agricultural",
        "contractor"
    ],
    "wof:name":"R J B Contracting",
    "wof:placetype":"venue"
},
  "geometry": {"coordinates":[-0.7484580278,53.2127571106],"type":"Point"}
}