{
  "type": "Feature",
  "properties": {
    "addr:full":"133 Loughborough Rd Leicester Leicestershire LE4 5LQ",
    "addr:housenumber":"133",
    "addr:postcode":"le4 5lq",
    "addr:street":"Loughborough Rd",
    "iso:country":"GB",
    "sg:address":"133 Loughborough Rd",
    "sg:city":"Leicester",
    "sg:classifiers":[
        {
            "category":"Organizations",
            "subcategory":"Membership Organization",
            "type":"Services"
        }
    ],
    "sg:phone":"+44 116 266 4064",
    "sg:postcode":"LE4 5LQ",
    "sg:province":"Leicestershire",
    "sg:tags":[
        "club"
    ],
    "wof:name":"National Cricket Association",
    "wof:placetype":"venue"
},
  "geometry": {"coordinates":[-1.1221619844,52.656703949],"type":"Point"}
}