{
  "type": "Feature",
  "properties": {
    "addr:full":"3 Hill Street Haverfordwest Pembrokeshire SA61 1QQ",
    "addr:housenumber":"3",
    "addr:postcode":"sa61 1qq",
    "addr:street":"Hill Street",
    "iso:country":"GB",
    "sg:address":"3 Hill Street",
    "sg:city":"Haverfordwest",
    "sg:classifiers":[
        {
            "category":"Organizations",
            "subcategory":"Non-profit Organization",
            "type":"Services"
        }
    ],
    "sg:phone":"+44 1437 769972",
    "sg:postcode":"SA61 1QQ",
    "sg:province":"Pembrokeshire",
    "sg:tags":[
        "organisation",
        "voluntary",
        "charity"
    ],
    "wof:name":"Age Concern Pembrokeshire",
    "wof:placetype":"venue"
},
  "geometry": {"coordinates":[-4.9709610939,51.8001403809],"type":"Point"}
}