{
  "type": "Feature",
  "properties": {
    "iso:country":"GB",
    "sg:address":"Woodville, Main Road, Shurdington",
    "sg:city":"Cheltenham",
    "sg:classifiers":[
        {
            "category":"Building & Trades",
            "subcategory":"Landscaping Services",
            "type":"Services"
        }
    ],
    "sg:phone":"+44 1242 863249",
    "sg:postcode":"GL51 4XJ",
    "sg:province":"Gloucestershire",
    "sg:tags":[
        "landscape",
        "contractor"
    ],
    "wof:name":"C S Landscaping",
    "wof:placetype":"venue"
},
  "geometry": {"coordinates":[-2.112755,51.867001],"type":"Point"}
}