{
  "type": "Feature",
  "properties": {
    "iso:country":"GB",
    "sg:address":"17 Norris Way Industrial Estate, Norris Way",
    "sg:city":"Rushden",
    "sg:classifiers":[
        {
            "category":"Professional",
            "subcategory":"Engineering",
            "type":"Services"
        }
    ],
    "sg:phone":"+44 1933 355648",
    "sg:postcode":"NN10 6BP",
    "sg:province":"Bedfordshire",
    "wof:name":"Brian Harbour Precision Engineers",
    "wof:placetype":"venue"
},
  "geometry": {"coordinates":[-0.620637,52.298176],"type":"Point"}
}