{
  "type": "Feature",
  "properties": {
    "addr:full":"Beachley Road, Sedbury Chepstow Gloucestershire NP16 7AA",
    "addr:postcode":"np16 7aa",
    "addr:street":"Beachley Road Sedbury",
    "iso:country":"GB",
    "sg:address":"Beachley Road, Sedbury",
    "sg:city":"Chepstow",
    "sg:classifiers":[
        {
            "category":"Food & Beverages",
            "subcategory":"Groceries & Convenience Stores",
            "type":"Retail Goods"
        }
    ],
    "sg:phone":"+44 1291 624311",
    "sg:postcode":"NP16 7AA",
    "sg:province":"Gloucestershire",
    "wof:name":"Spar",
    "wof:placetype":"venue"
},
  "geometry": {"coordinates":[-2.6520290375,51.6237220764],"type":"Point"}
}