{
  "type": "Feature",
  "properties": {
    "iso:country":"GB",
    "sg:address":"33b Bank Street",
    "sg:city":"Newquay",
    "sg:classifiers":[
        {
            "category":"Fast Food",
            "type":"Food & Drink"
        }
    ],
    "sg:phone":"+44 1637 871717",
    "sg:postcode":"TR7 1DJ",
    "sg:province":"Cornwall",
    "sg:tags":[
        "away",
        "take"
    ],
    "wof:name":"M Foster",
    "wof:placetype":"venue"
},
  "geometry": {"coordinates":[-5.084134,50.41375],"type":"Point"}
}