{
  "type": "Feature",
  "properties": {
    "addr:full":"1 Belgrave Road Margate Kent CT9 1XG",
    "addr:housenumber":"1",
    "addr:postcode":"ct9 1xg",
    "addr:street":"Belgrave Road",
    "iso:country":"GB",
    "sg:address":"1 Belgrave Road",
    "sg:city":"Margate",
    "sg:classifiers":[
        {
            "category":"Retail",
            "subcategory":"Auto Repair",
            "type":"Services"
        }
    ],
    "sg:postcode":"CT9 1XG",
    "sg:province":"Kent",
    "sg:tags":[
        "modification",
        "garage",
        "related"
    ],
    "wof:name":"1ST Call",
    "wof:placetype":"venue"
},
  "geometry": {"coordinates":[1.3792630434,51.3861808777],"type":"Point"}
}