{
  "type": "Feature",
  "properties": {
    "addr:full":"10 Well Street Newcastle Staffordshire ST5 1BP",
    "addr:housenumber":"10",
    "addr:postcode":"st5 1bp",
    "addr:street":"Well Street",
    "iso:country":"GB",
    "sg:address":"10 Well Street",
    "sg:city":"Newcastle",
    "sg:classifiers":[
        {
            "category":"Sports & Exercise",
            "subcategory":"Gym",
            "type":"Entertainment"
        }
    ],
    "sg:postcode":"ST5 1BP",
    "sg:province":"Staffordshire",
    "sg:tags":[
        "fitness",
        "health",
        "centre"
    ],
    "wof:name":"Spatan",
    "wof:placetype":"venue"
},
  "geometry": {"coordinates":[-2.2239539623,53.0091056824],"type":"Point"}
}