{
  "type": "Feature",
  "properties": {
    "iso:country":"GB",
    "sg:address":"Park House Farm, Hordley",
    "sg:city":"Ellesmere",
    "sg:classifiers":[
        {
            "category":"Farming",
            "subcategory":"Livestock Farm",
            "type":"Manufacturing & Wholesale Goods"
        }
    ],
    "sg:postcode":"SY12 9BL",
    "sg:province":"Shropshire",
    "sg:tags":[
        "others"
    ],
    "wof:name":"W D Maddocks",
    "wof:placetype":"venue"
},
  "geometry": {"coordinates":[-2.9211940765,52.8711891174],"type":"Point"}
}