{
  "type": "Feature",
  "properties": {
    "addr:full":"Kempley Road Okehampton Devon EX20 1DS",
    "addr:postcode":"ex20 1ds",
    "addr:street":"Kempley Road",
    "iso:country":"GB",
    "sg:address":"Kempley Road",
    "sg:city":"Okehampton",
    "sg:classifiers":[
        {
            "category":"Autos & Motor Vehicles",
            "subcategory":"Auto Supplies",
            "type":"Retail Goods"
        }
    ],
    "sg:phone":"+44 1837 54496",
    "sg:postcode":"EX20 1DS",
    "sg:province":"Devon",
    "sg:tags":[
        "tyre"
    ],
    "wof:name":"Bob's Exhaust & Tyre Centre",
    "wof:placetype":"venue"
},
  "geometry": {"coordinates":[-4.0009288788,50.7372894287],"type":"Point"}
}