{
  "type": "Feature",
  "properties": {
    "iso:country":"GB",
    "sg:address":"2 Park Nook, Doncaster Road",
    "sg:city":"Rotherham",
    "sg:classifiers":[
        {
            "category":"Military Area",
            "subcategory":"Air Force Base",
            "type":"Public Place"
        }
    ],
    "sg:phone":"+44 1709 852897",
    "sg:postcode":"S65 4AE",
    "sg:province":"South Yorkshire",
    "sg:tags":[
        "taxi",
        "hire",
        "private"
    ],
    "wof:name":"Ace Taxis",
    "wof:placetype":"venue"
},
  "geometry": {"coordinates":[-1.306109,53.448757],"type":"Point"}
}