{
  "type": "Feature",
  "properties": {
    "iso:country":"GB",
    "sg:address":"Blackburn Technology Management Centre, Challenge Way",
    "sg:city":"Blackburn",
    "sg:classifiers":[
        {
            "category":"Professional",
            "subcategory":"Business Services",
            "type":"Services"
        }
    ],
    "sg:phone":"+44 1254 677433",
    "sg:postcode":"BB1 5QB",
    "sg:province":"Lancashire",
    "sg:tags":[
        "information"
    ],
    "wof:name":"Applied Knowledge Research Institute",
    "wof:placetype":"venue"
},
  "geometry": {"coordinates":[-2.480399,53.748516],"type":"Point"}
}