{
  "type": "Feature",
  "properties": {
    "addr:full":"Unit 4, Lanrick Rd Poplar Greater London E14 0JF",
    "addr:housenumber":"unit 4",
    "addr:postcode":"e14 0jf",
    "addr:street":"Lanrick Rd",
    "iso:country":"GB",
    "sg:address":"Unit 4, Lanrick Rd",
    "sg:city":"Poplar",
    "sg:classifiers":[
        {
            "category":"Building & Trades",
            "subcategory":"Locksmith",
            "type":"Services"
        }
    ],
    "sg:phone":"+44 20 8525 5555",
    "sg:postcode":"E14 0JF",
    "sg:province":"Greater London",
    "wof:name":"2 Cousins Access Platforms",
    "wof:placetype":"venue"
},
  "geometry": {"coordinates":[0.001962,51.514828],"type":"Point"}
}