{
  "type": "Feature",
  "properties": {
    "addr:full":"14 Warren Road Liverpool Merseyside L23 6UB",
    "addr:housenumber":"14",
    "addr:postcode":"l23 6ub",
    "addr:street":"Warren Road",
    "iso:country":"GB",
    "sg:address":"14 Warren Road",
    "sg:city":"Liverpool",
    "sg:classifiers":[
        {
            "category":"Health Services",
            "subcategory":"Nursing And Care Facility",
            "type":"Services"
        }
    ],
    "sg:phone":"+44 151 931 5007",
    "sg:postcode":"L23 6UB",
    "sg:province":"Merseyside",
    "sg:tags":[
        "home"
    ],
    "wof:name":"Warren Grange Nursing Home Ltd.",
    "wof:placetype":"venue"
},
  "geometry": {"coordinates":[-3.0416929722,53.4856758118],"type":"Point"}
}