{
  "type": "Feature",
  "properties": {
    "addr:full":"26 Prince Road, Kenfig Hill Bridgend Bridgend CF33 6ED",
    "addr:housenumber":"26",
    "addr:postcode":"cf33 6ed",
    "addr:street":"Prince Road",
    "iso:country":"GB",
    "sg:address":"26 Prince Road, Kenfig Hill",
    "sg:city":"Bridgend",
    "sg:classifiers":[
        {
            "category":"Bars & Pubs",
            "type":"Food & Drink"
        }
    ],
    "sg:postcode":"CF33 6ED",
    "sg:province":"Bridgend",
    "sg:tags":[
        "pubs",
        "inn"
    ],
    "wof:name":"Brynddy",
    "wof:placetype":"venue"
},
  "geometry": {"coordinates":[-3.677556,51.534466],"type":"Point"}
}