{
  "type": "Feature",
  "properties": {
    "addr:full":"734 Great Horton Road Bradford West Yorkshire BD7 4EY",
    "addr:housenumber":"734",
    "addr:postcode":"bd7 4ey",
    "addr:street":"Great Horton Road",
    "iso:country":"GB",
    "sg:address":"734 Great Horton Road",
    "sg:city":"Bradford",
    "sg:classifiers":[
        {
            "category":"Bars & Pubs",
            "type":"Food & Drink"
        },
        {
            "category":"Community Center",
            "subcategory":"Social",
            "type":"Public Place"
        }
    ],
    "sg:phone":"+44 1274 770069",
    "sg:postcode":"BD7 4EY",
    "sg:province":"West Yorkshire",
    "sg:tags":[
        "pubs",
        "house",
        "inn",
        "activity"
    ],
    "wof:name":"George & Dragon",
    "wof:placetype":"venue"
},
  "geometry": {"coordinates":[-1.788479,53.778942],"type":"Point"}
}