{
  "type": "Feature",
  "properties": {
    "addr:full":"Drummond Rd Skegness Lincolnshire PE25 3EB",
    "addr:postcode":"pe25 3eb",
    "addr:street":"Drummond Rd",
    "iso:country":"GB",
    "sg:address":"Drummond Rd",
    "sg:city":"Skegness",
    "sg:classifiers":[
        {
            "category":"Autos & Motor Vehicles",
            "subcategory":"Automobile Sales",
            "type":"Retail Goods"
        }
    ],
    "sg:phone":"+44 1754 612357",
    "sg:postcode":"PE25 3EB",
    "sg:province":"Lincolnshire",
    "sg:tags":[
        "car"
    ],
    "wof:name":"Tamley Autos",
    "wof:placetype":"venue"
},
  "geometry": {"coordinates":[0.3430149853,53.1418113708],"type":"Point"}
}