{
  "type": "Feature",
  "properties": {
    "addr:full":"Po Box 47 Worcester Worcestershire WR5 2YN",
    "addr:housenumber":"po box 47",
    "addr:postcode":"wr5 2yn",
    "iso:country":"GB",
    "sg:address":"Po Box 47",
    "sg:city":"Worcester",
    "sg:classifiers":[
        {
            "category":"Freight",
            "type":"Transportation"
        }
    ],
    "sg:phone":"+44 1905 353969",
    "sg:postcode":"WR5 2YN",
    "sg:province":"Worcestershire",
    "sg:tags":[
        "overseas",
        "shipping",
        "removal"
    ],
    "wof:name":"Shipco Transport Ltd",
    "wof:placetype":"venue"
},
  "geometry": {"coordinates":[-2.167304039,52.1448860168],"type":"Point"}
}