{
  "type": "Feature",
  "properties": {
    "addr:full":"16-18 Lower Oakfield Pitlochry Perth and Kinross PH16 5DS",
    "addr:housenumber":"16-18",
    "addr:postcode":"ph16 5ds",
    "addr:street":"Lower Oakfield",
    "iso:country":"GB",
    "sg:address":"16-18 Lower Oakfield",
    "sg:city":"Pitlochry",
    "sg:classifiers":[
        {
            "category":"Travel",
            "subcategory":"Hotels & Motels",
            "type":"Entertainment"
        }
    ],
    "sg:phone":"+44 1796 472070",
    "sg:postcode":"PH16 5DS",
    "sg:province":"Perth and Kinross",
    "sg:tags":[
        "house",
        "guest"
    ],
    "wof:name":"DERRYBEG GUEST HOUSE",
    "wof:placetype":"venue"
},
  "geometry": {"coordinates":[-3.7277259827,56.7025794983],"type":"Point"}
}