{
  "type": "Feature",
  "properties": {
    "addr:full":"1 Piece Hall Yard Bradford West Yorkshire BD1 1PJ",
    "addr:housenumber":"1",
    "addr:postcode":"bd1 1pj",
    "addr:street":"Piece Hall Yard Bradford West",
    "iso:country":"GB",
    "sg:address":"1 Piece Hall Yard",
    "sg:city":"Bradford",
    "sg:classifiers":[
        {
            "category":"Organizations",
            "subcategory":"Membership Organization",
            "type":"Services"
        }
    ],
    "sg:phone":"+44 1274 727036",
    "sg:postcode":"BD1 1PJ",
    "sg:province":"West Yorkshire",
    "sg:tags":[
        "club"
    ],
    "wof:name":"Bradford Club",
    "wof:placetype":"venue"
},
  "geometry": {"coordinates":[-1.752624,53.79472],"type":"Point"}
}