{
  "type": "Feature",
  "properties": {
    "addr:full":"35 High Street Narberth Carmarthenshire SA67 7AS",
    "addr:housenumber":"35",
    "addr:postcode":"sa67 7as",
    "addr:street":"High Street",
    "iso:country":"GB",
    "sg:address":"35 High Street",
    "sg:city":"Narberth",
    "sg:classifiers":[
        {
            "category":"Shopping",
            "subcategory":"Clothing, Apparel, & Fashions",
            "type":"Retail Goods"
        }
    ],
    "sg:postcode":"SA67 7AS",
    "sg:province":"Carmarthenshire",
    "sg:tags":[
        "shop"
    ],
    "wof:name":"Marys Pop-in",
    "wof:placetype":"venue"
},
  "geometry": {"coordinates":[-4.7440838814,51.7987174988],"type":"Point"}
}