{
  "type": "Feature",
  "properties": {
    "iso:country":"GB",
    "sg:address":"116 London Road, Headington",
    "sg:city":"Oxford",
    "sg:classifiers":[
        {
            "category":"Banks & Credit Unions",
            "subcategory":"Bank",
            "type":"Services"
        }
    ],
    "sg:phone":"+44 845 765 4321",
    "sg:postcode":"OX3 9AS",
    "sg:province":"Oxfordshire",
    "sg:tags":[
        "financial",
        "institution"
    ],
    "wof:name":"Abbey National plc",
    "wof:placetype":"venue"
},
  "geometry": {"coordinates":[-1.211322,51.759937],"type":"Point"}
}