{
  "type": "Feature",
  "properties": {
    "iso:country":"GB",
    "sg:address":"120 Main Street, Barrhead",
    "sg:city":"Glasgow",
    "sg:classifiers":[
        {
            "category":"Farming",
            "subcategory":"Livestock Farm",
            "type":"Manufacturing & Wholesale Goods"
        }
    ],
    "sg:phone":"+44 141 881 3841",
    "sg:postcode":"G78 1SG",
    "sg:province":"East Ayrshire",
    "sg:tags":[
        "breeder"
    ],
    "wof:name":"Lesley Janieson",
    "wof:placetype":"venue"
},
  "geometry": {"coordinates":[-4.391112,55.80014],"type":"Point"}
}