{
  "type": "Feature",
  "properties": {
    "iso:country":"GB",
    "sg:address":"2 Bedford Place",
    "sg:city":"Maidstone",
    "sg:classifiers":[
        {
            "category":"Banks & Credit Unions",
            "subcategory":"Financial Services",
            "type":"Services"
        }
    ],
    "sg:phone":"+44 1622 762288",
    "sg:postcode":"ME16 8JB",
    "sg:province":"Kent",
    "sg:tags":[
        "consultant"
    ],
    "wof:name":"McF Financial Services",
    "wof:placetype":"venue"
},
  "geometry": {"coordinates":[0.511173,51.272324],"type":"Point"}
}