{
  "type": "Feature",
  "properties": {
    "addr:full":"95 Manchester Rd Sheffield South Yorkshire S36 9QR",
    "addr:housenumber":"95",
    "addr:postcode":"s36 9qr",
    "addr:street":"Manchester Rd",
    "iso:country":"GB",
    "sg:address":"95 Manchester Rd",
    "sg:city":"Sheffield",
    "sg:classifiers":[
        {
            "category":"Fast Food",
            "type":"Food & Drink"
        }
    ],
    "sg:phone":"+44 1226 763948",
    "sg:postcode":"S36 9QR",
    "sg:province":"South Yorkshire",
    "sg:tags":[
        "away",
        "take"
    ],
    "wof:name":"Thurlstone Take Away",
    "wof:placetype":"venue"
},
  "geometry": {"coordinates":[-1.65223,53.527126],"type":"Point"}
}