{
  "type": "Feature",
  "properties": {
    "addr:full":"37 Quat Goose Lane, Swindon Village Cheltenham Gloucestershire GL51 9RP",
    "addr:housenumber":"37",
    "addr:postcode":"gl51 9rp",
    "addr:street":"Quat Goose Lane",
    "iso:country":"GB",
    "sg:address":"37 Quat Goose Lane, Swindon Village",
    "sg:city":"Cheltenham",
    "sg:classifiers":[
        {
            "category":"Building & Trades",
            "subcategory":"Landscaping Services",
            "type":"Services"
        }
    ],
    "sg:phone":"+44 1242 579508",
    "sg:postcode":"GL51 9RP",
    "sg:province":"Gloucestershire",
    "sg:tags":[
        "landscape",
        "contractor"
    ],
    "wof:name":"All Seasons",
    "wof:placetype":"venue"
},
  "geometry": {"coordinates":[-2.0962300301,51.9257965088],"type":"Point"}
}