{
  "type": "Feature",
  "properties": {
    "iso:country":"GB",
    "sg:address":"Unit 4 Brookfield Industrial Estate",
    "sg:city":"Cheadle",
    "sg:classifiers":[
        {
            "category":"Shopping",
            "subcategory":"Discount & Variety Stores",
            "type":"Retail Goods"
        }
    ],
    "sg:phone":"+44 161 428 0717",
    "sg:postcode":"SK8 2PN",
    "sg:province":"Cheshire",
    "sg:tags":[
        "cleaning",
        "supply"
    ],
    "wof:name":"Imperial Cleaning Co",
    "wof:placetype":"venue"
},
  "geometry": {"coordinates":[-2.212272,53.395248],"type":"Point"}
}