{
  "type": "Feature",
  "properties": {
    "iso:country":"GB",
    "sg:address":"Ardsley Mills, Common Lane, East Ardsley",
    "sg:city":"Wakefield",
    "sg:classifiers":[
        {
            "category":"Shopping",
            "subcategory":"Florist",
            "type":"Retail Goods"
        }
    ],
    "sg:phone":"+44 113 218 9090",
    "sg:postcode":"WF3 2DW",
    "sg:province":"West Yorkshire",
    "sg:tags":[
        "wholesale"
    ],
    "wof:name":"Country Baskets Plc",
    "wof:placetype":"venue"
},
  "geometry": {"coordinates":[-1.538376,53.719967],"type":"Point"}
}