{
  "type": "Feature",
  "properties": {
    "addr:full":"Fox Crescent Chelmsford Essex CM1 2BL",
    "addr:postcode":"cm1 2bl",
    "addr:street":"Fox Crescent",
    "iso:country":"GB",
    "sg:address":"Fox Crescent",
    "sg:city":"Chelmsford",
    "sg:classifiers":[
        {
            "category":"Education",
            "subcategory":"School",
            "type":"Public Place"
        },
        {
            "category":"Organizations",
            "subcategory":"Non-profit Organization",
            "type":"Services"
        }
    ],
    "sg:phone":"+44 1245 265511",
    "sg:postcode":"CM1 2BL",
    "sg:province":"Essex",
    "sg:tags":[
        "organisation",
        "college",
        "voluntary",
        "charity"
    ],
    "wof:name":"Rainsford High School",
    "wof:placetype":"venue"
},
  "geometry": {"coordinates":[0.4541270137,51.7448425293],"type":"Point"}
}