{
  "type": "Feature",
  "properties": {
    "addr:full":"Alphin House, Mill Lane, Alphington Exeter Devon EX2 8SG",
    "addr:postcode":"ex2 8sg",
    "addr:street":"Mill Lane",
    "iso:country":"GB",
    "sg:address":"Alphin House, Mill Lane, Alphington",
    "sg:city":"Exeter",
    "sg:classifiers":[
        {
            "category":"Health Services",
            "subcategory":"Nursing And Care Facility",
            "type":"Services"
        },
        {
            "category":"Social Services",
            "subcategory":"Retirement Home",
            "type":"Services"
        }
    ],
    "sg:phone":"+44 1392 251728",
    "sg:postcode":"EX2 8SG",
    "sg:province":"Devon",
    "sg:tags":[
        "residential"
    ],
    "wof:name":"ALPHIN HOUSE",
    "wof:placetype":"venue"
},
  "geometry": {"coordinates":[-3.5380489826,50.7007637024],"type":"Point"}
}