{
  "type": "Feature",
  "properties": {
    "iso:country":"GB",
    "sg:address":"Bayton Road, Exhall",
    "sg:city":"Coventry",
    "sg:classifiers":[
        {
            "category":"Manufacturing",
            "subcategory":"Metals",
            "type":"Manufacturing & Wholesale Goods"
        }
    ],
    "sg:phone":"+44 24 7664 4999",
    "sg:postcode":"CV7 9DX",
    "sg:province":"Warwickshire",
    "sg:tags":[
        "work",
        "sheet"
    ],
    "wof:name":"Abbey Panels Ltd.",
    "wof:placetype":"venue"
},
  "geometry": {"coordinates":[-1.482574,52.465111],"type":"Point"}
}