{
  "type": "Feature",
  "properties": {
    "addr:full":"19 High Street Marlborough Berkshire SN8 1AA",
    "addr:housenumber":"19",
    "addr:postcode":"sn8 1aa",
    "addr:street":"High Street",
    "iso:country":"GB",
    "sg:address":"19 High Street",
    "sg:city":"Marlborough",
    "sg:classifiers":[
        {
            "category":"Shopping",
            "subcategory":"Comic Books",
            "type":"Retail Goods"
        }
    ],
    "sg:phone":"+44 1672 512229",
    "sg:postcode":"SN8 1AA",
    "sg:province":"Berkshire",
    "sg:tags":[
        "jeweller"
    ],
    "wof:name":"Marlborough Jewellers",
    "wof:placetype":"venue"
},
  "geometry": {"coordinates":[-1.7315529585,51.4201965332],"type":"Point"}
}