{
  "type": "Feature",
  "properties": {
    "iso:country":"GB",
    "sg:address":"6 Bury Water Lane, Newport",
    "sg:city":"Saffron Walden",
    "sg:classifiers":[
        {
            "category":"Professional",
            "subcategory":"Accounting & Tax Preparation",
            "type":"Services"
        }
    ],
    "sg:phone":"+44 1799 540617",
    "sg:postcode":"CB11 3TZ",
    "sg:province":"Essex",
    "sg:tags":[
        "accountant"
    ],
    "wof:name":"Newport Accounting Services Ltd.",
    "wof:placetype":"venue"
},
  "geometry": {"coordinates":[0.20639,51.986832],"type":"Point"}
}