{
  "type": "Feature",
  "properties": {
    "iso:country":"GB",
    "sg:address":"14 Radwinter Road",
    "sg:city":"Saffron Walden",
    "sg:classifiers":[
        {
            "category":"Retail",
            "subcategory":"Veterinary Services",
            "type":"Services"
        }
    ],
    "sg:phone":"+44 1799 522082",
    "sg:postcode":"CB11 3JB",
    "sg:province":"Essex",
    "sg:tags":[
        "surgeon",
        "activity"
    ],
    "wof:name":"Mercer & Hughes",
    "wof:placetype":"venue"
},
  "geometry": {"coordinates":[0.250604,52.023197],"type":"Point"}
}