{
  "type": "Feature",
  "properties": {
    "iso:country":"GB",
    "sg:address":"139a Beckfield La",
    "sg:city":"York",
    "sg:classifiers":[
        {
            "category":"Professional",
            "subcategory":"Business Services",
            "type":"Services"
        }
    ],
    "sg:phone":"+44 1904 788666",
    "sg:postcode":"YO2 5PW",
    "sg:province":"East Riding of Yorkshire",
    "sg:tags":[
        "bookmaker"
    ],
    "wof:name":"York Racing",
    "wof:placetype":"venue"
},
  "geometry": {"coordinates":[-1.0834200382,53.9533309937],"type":"Point"}
}