{
  "type": "Feature",
  "properties": {
    "iso:country":"GB",
    "sg:address":"Unit 25 Lordswood Industrial Estate, Revenge Road",
    "sg:city":"Chatham",
    "sg:classifiers":[
        {
            "category":"Home & Garden",
            "subcategory":"Home Furnishings",
            "type":"Retail Goods"
        }
    ],
    "sg:phone":"+44 1634 668900",
    "sg:postcode":"ME5 8UD",
    "sg:province":"Kent",
    "sg:tags":[
        "awning",
        "canopy",
        "blinds"
    ],
    "wof:name":"Blinds Galore",
    "wof:placetype":"venue"
},
  "geometry": {"coordinates":[0.54138,51.33091],"type":"Point"}
}