{
  "type": "Feature",
  "properties": {
    "iso:country":"GB",
    "sg:address":"69 Wavertree Road",
    "sg:city":"Liverpool",
    "sg:classifiers":[
        {
            "category":"Food & Beverages",
            "subcategory":"Candy",
            "type":"Retail Goods"
        },
        {
            "category":"Food & Beverages",
            "subcategory":"Bakery",
            "type":"Retail Goods"
        }
    ],
    "sg:phone":"+44 151 281 7474",
    "sg:postcode":"L7 1PF",
    "sg:province":"Merseyside",
    "sg:tags":[
        "shop",
        "confectioner",
        "baker"
    ],
    "wof:name":"Sayers Confectioners Ltd.",
    "wof:placetype":"venue"
},
  "geometry": {"coordinates":[-2.951507,53.404831],"type":"Point"}
}