{
  "type": "Feature",
  "properties": {
    "iso:country":"GB",
    "sg:address":"27 Romilly Street",
    "sg:city":"London",
    "sg:classifiers":[
        {
            "category":"Restaurant",
            "type":"Food & Drink"
        }
    ],
    "sg:phone":"+44 20 7437 2262",
    "sg:postcode":"W1D 5AL",
    "sg:province":"Greater London",
    "sg:tags":[
        "oriental"
    ],
    "wof:name":"Cho Won Korean Restaurant",
    "wof:placetype":"venue"
},
  "geometry": {"coordinates":[-0.130818,51.513081],"type":"Point"}
}