{
  "type": "Feature",
  "properties": {
    "addr:full":"Hope Farm, Halegate Rd Widnes Cheshire WA8 8LZ",
    "addr:postcode":"wa8 8lz",
    "addr:street":"Hope;Halegate Rd",
    "iso:country":"GB",
    "sg:address":"Hope Farm, Halegate Rd",
    "sg:city":"Widnes",
    "sg:classifiers":[
        {
            "category":"Wholesale",
            "subcategory":"Machinery & Supplies",
            "type":"Manufacturing & Wholesale Goods"
        }
    ],
    "sg:phone":"+44 151 425 2500",
    "sg:postcode":"WA8 8LZ",
    "sg:province":"Cheshire",
    "sg:tags":[
        "theatrical"
    ],
    "wof:name":"Completely Costume Co",
    "wof:placetype":"venue"
},
  "geometry": {"coordinates":[-2.7332439423,53.3740310669],"type":"Point"}
}