{
  "type": "Feature",
  "properties": {
    "addr:full":"The Craft Workshop, Wilton Ross-on-wye Gloucestershire HR9 6AA",
    "addr:postcode":"hr9 6aa",
    "iso:country":"GB",
    "sg:address":"The Craft Workshop, Wilton",
    "sg:city":"Ross-on-wye",
    "sg:classifiers":[
        {
            "category":"Building & Trades",
            "subcategory":"Construction",
            "type":"Services"
        }
    ],
    "sg:phone":"+44 1989 566882",
    "sg:postcode":"HR9 6AA",
    "sg:province":"Gloucestershire",
    "sg:tags":[
        "builder"
    ],
    "wof:name":"Napolitano Developments",
    "wof:placetype":"venue"
},
  "geometry": {"coordinates":[-2.6063790321,51.9152946472],"type":"Point"}
}