{
  "type": "Feature",
  "properties": {
    "addr:full":"2 Sadlers Court, The Broadway Newbury Berkshire RG14 1BA",
    "addr:housenumber":"2",
    "addr:postcode":"rg14 1ba",
    "addr:street":"Sadlers Court The Broadway",
    "iso:country":"GB",
    "sg:address":"2 Sadlers Court, The Broadway",
    "sg:city":"Newbury",
    "sg:classifiers":[
        {
            "category":"Personal",
            "subcategory":"Beauty Salon",
            "type":"Services"
        }
    ],
    "sg:phone":"+44 1635 38478",
    "sg:postcode":"RG14 1BA",
    "sg:province":"Berkshire",
    "sg:tags":[
        "unisex",
        "hairdresser"
    ],
    "wof:name":"Fringe Hair Design Studio",
    "wof:placetype":"venue"
},
  "geometry": {"coordinates":[-1.3258719444,51.405872345],"type":"Point"}
}