{
  "type": "Feature",
  "properties": {
    "addr:full":"Station Street Tipton West Midlands DY4 8UG",
    "addr:postcode":"dy4 8ug",
    "addr:street":"Station Street",
    "iso:country":"GB",
    "sg:address":"Station Street",
    "sg:city":"Tipton",
    "sg:classifiers":[
        {
            "category":"Home & Garden",
            "subcategory":"Building Materials",
            "type":"Retail Goods"
        }
    ],
    "sg:phone":"+44 121 557 4101",
    "sg:postcode":"DY4 8UG",
    "sg:province":"West Midlands",
    "sg:tags":[
        "ventilator",
        "ventilation",
        "system"
    ],
    "wof:name":"Truflo Air Movement Ltd.",
    "wof:placetype":"venue"
},
  "geometry": {"coordinates":[-2.0501348972,52.5259552002],"type":"Point"}
}