{
  "type": "Feature",
  "properties": {
    "iso:country":"GB",
    "sg:address":"8a Union Street",
    "sg:city":"Bacup",
    "sg:classifiers":[
        {
            "category":"Shopping",
            "subcategory":"Clothing, Apparel, & Fashions",
            "type":"Retail Goods"
        },
        {
            "category":"Shopping",
            "subcategory":"Baby Store",
            "type":"Retail Goods"
        }
    ],
    "sg:phone":"+44 1706 877415",
    "sg:postcode":"OL13 0AA",
    "sg:province":"Lancashire",
    "sg:tags":[
        "child",
        "childrens",
        "babywear"
    ],
    "wof:name":"Ann's Childrens Ware",
    "wof:placetype":"venue"
},
  "geometry": {"coordinates":[-2.200189,53.702335],"type":"Point"}
}