{
  "type": "Feature",
  "properties": {
    "addr:full":"Mount Pleasant Farm House, Broadwoodkelly Winkleigh Devon EX19 8AU",
    "addr:housenumber":"winkleigh",
    "addr:postcode":"ex19 8au",
    "iso:country":"GB",
    "sg:address":"Mount Pleasant Farm House, Broadwoodkelly",
    "sg:city":"Winkleigh",
    "sg:classifiers":[
        {
            "category":"Farming",
            "subcategory":"Farm",
            "type":"Manufacturing & Wholesale Goods"
        }
    ],
    "sg:phone":"+44 1837 83786",
    "sg:postcode":"EX19 8AU",
    "sg:province":"Devon",
    "sg:tags":[
        "mixed",
        "crop"
    ],
    "wof:name":"G.J Brook",
    "wof:placetype":"venue"
},
  "geometry": {"coordinates":[-3.9423849583,50.8555793762],"type":"Point"}
}