{
  "type": "Feature",
  "properties": {
    "iso:country":"GB",
    "sg:address":"21-23 Clay Lane",
    "sg:city":"Beaminster",
    "sg:classifiers":[
        {
            "category":"Bars & Pubs",
            "type":"Food & Drink"
        }
    ],
    "sg:phone":"+44 1308 862408",
    "sg:postcode":"DT8 3BU",
    "sg:province":"Dorset",
    "sg:tags":[
        "pubs",
        "inn"
    ],
    "wof:name":"The Knapp Inn",
    "wof:placetype":"venue"
},
  "geometry": {"coordinates":[-2.7460110188,50.8099746704],"type":"Point"}
}