{
  "type": "Feature",
  "properties": {
    "addr:full":"40 Beverley Rd Worcester Park Surrey KT4 8LX",
    "addr:housenumber":"40",
    "addr:postcode":"kt4 8lx",
    "addr:street":"Beverley Rd",
    "iso:country":"GB",
    "sg:address":"40 Beverley Rd",
    "sg:city":"Worcester Park",
    "sg:classifiers":[
        {
            "category":"Professional",
            "subcategory":"Detective & Security Services",
            "type":"Services"
        },
        {
            "category":"Building & Trades",
            "subcategory":"Construction",
            "type":"Services"
        }
    ],
    "sg:phone":"+44 20 8337 8710",
    "sg:postcode":"KT4 8LX",
    "sg:province":"Surrey",
    "sg:tags":[
        "equipment",
        "builder",
        "installers"
    ],
    "wof:name":"Berrick & Co",
    "wof:placetype":"venue"
},
  "geometry": {"coordinates":[-0.232742995,51.3776626587],"type":"Point"}
}