{
  "type": "Feature",
  "properties": {
    "iso:country":"GB",
    "sg:address":"89 Calder Street, Whifflet",
    "sg:city":"Coatbridge",
    "sg:classifiers":[
        {
            "category":"Building & Trades",
            "subcategory":"Construction",
            "type":"Services"
        }
    ],
    "sg:phone":"+44 1236 421476",
    "sg:postcode":"ML5 4EY",
    "sg:province":"North Lanarkshire",
    "sg:tags":[
        "joinery"
    ],
    "wof:name":"Ace Fencing",
    "wof:placetype":"venue"
},
  "geometry": {"coordinates":[-4.012959,55.853718],"type":"Point"}
}