{
  "type": "Feature",
  "properties": {
    "iso:country":"GB",
    "sg:address":"61b Station Road",
    "sg:city":"Harrow",
    "sg:classifiers":[
        {
            "category":"Wholesale",
            "subcategory":"Machinery & Supplies",
            "type":"Manufacturing & Wholesale Goods"
        }
    ],
    "sg:phone":"+44 20 8427 1355",
    "sg:postcode":"HA1 2TZ",
    "sg:province":"Greater London",
    "sg:tags":[
        "pump"
    ],
    "wof:name":"Turney Turbines (Pumps) Ltd.",
    "wof:placetype":"venue"
},
  "geometry": {"coordinates":[-0.332267,51.587154],"type":"Point"}
}