{
  "type": "Feature",
  "properties": {
    "iso:country":"GB",
    "sg:address":"43 The Glen, Yate",
    "sg:city":"Bristol",
    "sg:classifiers":[
        {
            "category":"Retail",
            "subcategory":"Driving School",
            "type":"Services"
        }
    ],
    "sg:phone":"+44 1454 310150",
    "sg:postcode":"BS37 5PJ",
    "sg:province":"Gloucestershire",
    "wof:name":"Yate Driving School",
    "wof:placetype":"venue"
},
  "geometry": {"coordinates":[-2.4162299633,51.5427894592],"type":"Point"}
}