{
  "type": "Feature",
  "properties": {
    "iso:country":"GB",
    "sg:address":"204 High Street",
    "sg:city":"Lewes",
    "sg:classifiers":[
        {
            "category":"Organizations",
            "subcategory":"Political Organization",
            "type":"Services"
        }
    ],
    "sg:postcode":"BN7 2NS",
    "sg:province":"East Sussex",
    "sg:tags":[
        "party"
    ],
    "wof:name":"Liberal Democrats",
    "wof:placetype":"venue"
},
  "geometry": {"coordinates":[0.0124319997,50.8737678528],"type":"Point"}
}