{
  "type": "Feature",
  "properties": {
    "iso:country":"GB",
    "sg:address":"Rear Of 11 Barmoor Terr",
    "sg:city":"Ryton",
    "sg:classifiers":[
        {
            "category":"Retail",
            "subcategory":"Repair Shop",
            "type":"Services"
        }
    ],
    "sg:postcode":"NE40 3BB",
    "sg:province":"Tyne and Wear",
    "sg:tags":[
        "upholsterer"
    ],
    "wof:name":"Tynedale Upholstery",
    "wof:placetype":"venue"
},
  "geometry": {"coordinates":[-1.761564,54.972916],"type":"Point"}
}