{
  "type": "Feature",
  "properties": {
    "addr:full":"130 High Street Elgin Moray IV30 1BW",
    "addr:housenumber":"130",
    "addr:postcode":"iv30 1bw",
    "addr:street":"High Street",
    "iso:country":"GB",
    "sg:address":"130 High Street",
    "sg:city":"Elgin",
    "sg:classifiers":[
        {
            "category":"Bars & Pubs",
            "type":"Food & Drink"
        }
    ],
    "sg:phone":"+44 1343 548733",
    "sg:postcode":"IV30 1BW",
    "sg:province":"Moray",
    "sg:tags":[
        "pubs",
        "inn"
    ],
    "wof:name":"Newmarket Bar",
    "wof:placetype":"venue"
},
  "geometry": {"coordinates":[-3.316481,57.648384],"type":"Point"}
}