{
  "type": "Feature",
  "properties": {
    "iso:country":"GB",
    "sg:address":"133 Durham Road",
    "sg:city":"Consett",
    "sg:classifiers":[
        {
            "category":"Farming",
            "subcategory":"Fish & Marine Products",
            "type":"Manufacturing & Wholesale Goods"
        },
        {
            "category":"Food & Beverages",
            "subcategory":"Meat & Fish",
            "type":"Retail Goods"
        }
    ],
    "sg:phone":"+44 1207 502222",
    "sg:postcode":"DH8 7QY",
    "sg:province":"Durham",
    "sg:tags":[
        "fishmonger",
        "butcher"
    ],
    "wof:name":"Michael Brent Dyer",
    "wof:placetype":"venue"
},
  "geometry": {"coordinates":[-1.801011,54.856346],"type":"Point"}
}