{
  "type": "Feature",
  "properties": {
    "iso:country":"GB",
    "sg:address":"33 High Street",
    "sg:city":"Dingwall",
    "sg:classifiers":[
        {
            "category":"Sports & Exercise",
            "subcategory":"Sports Center",
            "type":"Entertainment"
        }
    ],
    "sg:phone":"+44 1349 862233",
    "sg:postcode":"IV15 9SN",
    "sg:province":"Highland",
    "sg:tags":[
        "shop",
        "good"
    ],
    "wof:name":"Macleans                            Primo",
    "wof:placetype":"venue"
},
  "geometry": {"coordinates":[-4.4262719154,57.5951957703],"type":"Point"}
}