{
  "type": "Feature",
  "properties": {
    "addr:full":"109 Upshire Road Waltham Abbey Essex EN9 3PE",
    "addr:housenumber":"109",
    "addr:postcode":"en9 3pe",
    "addr:street":"Upshire Road",
    "iso:country":"GB",
    "sg:address":"109 Upshire Road",
    "sg:city":"Waltham Abbey",
    "sg:classifiers":[
        {
            "category":"Building & Trades",
            "subcategory":"Construction",
            "type":"Services"
        }
    ],
    "sg:phone":"+44 1992 713011",
    "sg:postcode":"EN9 3PE",
    "sg:province":"Essex",
    "sg:tags":[
        "decorator",
        "painter"
    ],
    "wof:name":"E B S Property Care",
    "wof:placetype":"venue"
},
  "geometry": {"coordinates":[0.030305,51.689091],"type":"Point"}
}