{
  "type": "Feature",
  "properties": {
    "addr:full":"8 Bridge Road, West Cornforth Ferryhill Durham DL17 9JL",
    "addr:housenumber":"8",
    "addr:postcode":"dl17 9jl",
    "addr:street":"Bridge Road",
    "iso:country":"GB",
    "sg:address":"8 Bridge Road, West Cornforth",
    "sg:city":"Ferryhill",
    "sg:classifiers":[
        {
            "category":"Bars & Pubs",
            "type":"Food & Drink"
        }
    ],
    "sg:phone":"+44 1740 654618",
    "sg:postcode":"DL17 9JL",
    "sg:province":"Durham",
    "sg:tags":[
        "pubs",
        "inn"
    ],
    "wof:name":"Carrs Hotel",
    "wof:placetype":"venue"
},
  "geometry": {"coordinates":[-1.513771,54.705788],"type":"Point"}
}