{
  "type": "Feature",
  "properties": {
    "addr:full":"25 Denton Street Leicester Leicestershire LE3 6DD",
    "addr:housenumber":"25",
    "addr:postcode":"le3 6dd",
    "addr:street":"Denton Street",
    "iso:country":"GB",
    "sg:address":"25 Denton Street",
    "sg:city":"Leicester",
    "sg:classifiers":[
        {
            "category":"Banks & Credit Unions",
            "subcategory":"Financial Services",
            "type":"Services"
        }
    ],
    "sg:phone":"+44 116 254 6726",
    "sg:postcode":"LE3 6DD",
    "sg:province":"Leicestershire",
    "sg:tags":[
        "adviser",
        "independent"
    ],
    "wof:name":"Bradshaw & Co",
    "wof:placetype":"venue"
},
  "geometry": {"coordinates":[-1.1606309414,52.6344070435],"type":"Point"}
}