{
  "type": "Feature",
  "properties": {
    "addr:full":"The Dry Dock, 17a Waldron Rd Broadstairs Kent CT10 1TB",
    "addr:housenumber":"17a",
    "addr:postcode":"ct10 1tb",
    "addr:street":"Dock;Waldron Rd",
    "iso:country":"GB",
    "sg:address":"The Dry Dock, 17a Waldron Rd",
    "sg:city":"Broadstairs",
    "sg:classifiers":[
        {
            "category":"Building & Trades",
            "subcategory":"Plumbing",
            "type":"Services"
        }
    ],
    "sg:phone":"+44 1843 603385",
    "sg:postcode":"CT10 1TB",
    "sg:province":"Kent",
    "sg:tags":[
        "central",
        "heating"
    ],
    "wof:name":"F R Thompson",
    "wof:placetype":"venue"
},
  "geometry": {"coordinates":[1.441059947,51.3586044312],"type":"Point"}
}