{
  "type": "Feature",
  "properties": {
    "addr:full":"135 Canterbury Road, Hawkinge Folkestone Kent CT18 7BS",
    "addr:housenumber":"135",
    "addr:postcode":"ct18 7bs",
    "addr:street":"Canterbury Road",
    "iso:country":"GB",
    "sg:address":"135 Canterbury Road, Hawkinge",
    "sg:city":"Folkestone",
    "sg:classifiers":[
        {
            "category":"Professional",
            "subcategory":"Lawyer & Legal Services",
            "type":"Services"
        }
    ],
    "sg:postcode":"CT18 7BS",
    "sg:province":"Kent",
    "sg:tags":[
        "solicitor"
    ],
    "wof:name":"A P Radcliffe Solicitors",
    "wof:placetype":"venue"
},
  "geometry": {"coordinates":[1.163615,51.11676],"type":"Point"}
}