{
  "type": "Feature",
  "properties": {
    "iso:country":"GB",
    "sg:address":"135 Canterbury Road, Hawkinge",
    "sg:city":"Folkestone",
    "sg:classifiers":[
        {
            "category":"Professional",
            "subcategory":"Lawyer & Legal Services",
            "type":"Services"
        }
    ],
    "sg:postcode":"CT18 7BS",
    "sg:province":"Kent",
    "sg:tags":[
        "solicitor"
    ],
    "wof:name":"A P Radcliffe Solicitors",
    "wof:placetype":"venue"
},
  "geometry": {"coordinates":[1.163615,51.11676],"type":"Point"}
}