{
  "type": "Feature",
  "properties": {
    "iso:country":"GB",
    "sg:address":"1 West Dyke Road",
    "sg:city":"Redcar",
    "sg:classifiers":[
        {
            "category":"Food & Beverages",
            "subcategory":"Meat & Fish",
            "type":"Retail Goods"
        }
    ],
    "sg:postcode":"TS10 3EA",
    "sg:province":"North Yorkshire",
    "sg:tags":[
        "butcher"
    ],
    "wof:name":"Ellison's",
    "wof:placetype":"venue"
},
  "geometry": {"coordinates":[-1.068539,54.617989],"type":"Point"}
}