{
  "type": "Feature",
  "properties": {
    "addr:full":"Unit 12 Barnsdale Drive, Westcroft Milton Keynes Buckinghamshire MK4 4DD",
    "addr:housenumber":"unit 12",
    "addr:postcode":"mk4 4dd",
    "addr:street":"Barnsdale Drive",
    "iso:country":"GB",
    "sg:address":"Unit 12 Barnsdale Drive, Westcroft",
    "sg:city":"Milton Keynes",
    "sg:classifiers":[
        {
            "category":"Shopping",
            "subcategory":"Baby Store",
            "type":"Retail Goods"
        }
    ],
    "sg:postcode":"MK4 4DD",
    "sg:province":"Buckinghamshire",
    "sg:tags":[
        "babywear",
        "childrens"
    ],
    "wof:name":"Clothes for Real Kids",
    "wof:placetype":"venue"
},
  "geometry": {"coordinates":[-0.7918469906,52.0049209595],"type":"Point"}
}