{
  "type": "Feature",
  "properties": {
    "addr:full":"10 Hall Road Rotherham South Yorkshire S60 2BP",
    "addr:housenumber":"10",
    "addr:postcode":"s60 2bp",
    "addr:street":"Hall Road",
    "iso:country":"GB",
    "sg:address":"10 Hall Road",
    "sg:city":"Rotherham",
    "sg:classifiers":[
        {
            "category":"Building & Trades",
            "subcategory":"Cleaning & Sanitation",
            "type":"Services"
        }
    ],
    "sg:postcode":"S60 2BP",
    "sg:province":"South Yorkshire",
    "sg:tags":[
        "blast"
    ],
    "wof:name":"Haulage Contractors",
    "wof:placetype":"venue"
},
  "geometry": {"coordinates":[-1.3517,53.424084],"type":"Point"}
}