{
  "type": "Feature",
  "properties": {
    "iso:country":"GB",
    "sg:address":"176 Drury Lane",
    "sg:city":"London",
    "sg:classifiers":[
        {
            "category":"Restaurant",
            "type":"Food & Drink"
        }
    ],
    "sg:phone":"+44 20 7405 2911",
    "sg:postcode":"WC2B 5QF",
    "sg:province":"Greater London",
    "sg:tags":[
        "chinese"
    ],
    "wof:name":"Drury Lane Diner",
    "wof:placetype":"venue"
},
  "geometry": {"coordinates":[-0.123422,51.515591],"type":"Point"}
}