{
  "type": "Feature",
  "properties": {
    "iso:country":"GB",
    "sg:address":"24 Laburnum Close",
    "sg:city":"Congleton",
    "sg:classifiers":[
        {
            "category":"Building & Trades",
            "subcategory":"Construction",
            "type":"Services"
        }
    ],
    "sg:postcode":"CW12 4TX",
    "sg:province":"Cheshire",
    "sg:tags":[
        "builder"
    ],
    "wof:name":"Anthony J Walton",
    "wof:placetype":"venue"
},
  "geometry": {"coordinates":[-2.240657,53.16964],"type":"Point"}
}