{
  "type": "Feature",
  "properties": {
    "addr:full":"Oaklands Rd Oldham Lancashire OL2 6AS",
    "addr:postcode":"ol2 6as",
    "addr:street":"Oaklands Rd",
    "iso:country":"GB",
    "sg:address":"Oaklands Rd",
    "sg:city":"Oldham",
    "sg:classifiers":[
        {
            "category":"Community Center",
            "type":"Public Place"
        }
    ],
    "sg:phone":"+44 1457 874491",
    "sg:postcode":"OL2 6AS",
    "sg:province":"Lancashire",
    "sg:tags":[
        "centre"
    ],
    "wof:name":"Friezland Church Hall",
    "wof:placetype":"venue"
},
  "geometry": {"coordinates":[-2.1167991161,53.5583496094],"type":"Point"}
}