{
  "type": "Feature",
  "properties": {
    "iso:country":"GB",
    "sg:address":"3rd Flr, Upper Borough Court, Upper Borough Walls",
    "sg:city":"Bath",
    "sg:classifiers":[
        {
            "category":"Shopping",
            "subcategory":"Books",
            "type":"Retail Goods"
        }
    ],
    "sg:phone":"+44 1225 737300",
    "sg:postcode":"BA1 1RG",
    "sg:province":"Bath and North East Somerset",
    "wof:name":"Box Office Publications Ltd.",
    "wof:placetype":"venue"
},
  "geometry": {"coordinates":[-2.3599200249,51.3828201294],"type":"Point"}
}