{
  "type": "Feature",
  "properties": {
    "iso:country":"GB",
    "sg:address":"27 Montpelier Rise",
    "sg:city":"Wembley",
    "sg:classifiers":[
        {
            "category":"Retail",
            "subcategory":"Repair Shop",
            "type":"Services"
        }
    ],
    "sg:postcode":"HA9 8RG",
    "sg:province":"Greater London",
    "sg:tags":[
        "maintenance"
    ],
    "wof:name":"Fisher Painting",
    "wof:placetype":"venue"
},
  "geometry": {"coordinates":[-0.3050779998,51.5697593689],"type":"Point"}
}