{
  "type": "Feature",
  "properties": {
    "iso:country":"GB",
    "sg:address":"45 Wheeler Street",
    "sg:city":"Maidstone",
    "sg:classifiers":[
        {
            "category":"Professional",
            "subcategory":"Art Services",
            "type":"Services"
        },
        {
            "category":"Building & Trades",
            "subcategory":"Construction",
            "type":"Services"
        }
    ],
    "sg:phone":"+44 1622 756204",
    "sg:postcode":"ME14 1UA",
    "sg:province":"Kent",
    "sg:tags":[
        "decorator",
        "painter"
    ],
    "wof:name":"Michael J Mallion",
    "wof:placetype":"venue"
},
  "geometry": {"coordinates":[0.525797,51.277687],"type":"Point"}
}