{
  "type": "Feature",
  "properties": {
    "addr:full":"4 Monten St London Greater London N4 3BE",
    "addr:housenumber":"4",
    "addr:postcode":"n4 3be",
    "addr:street":"Monten St",
    "iso:country":"GB",
    "sg:address":"4 Monten St",
    "sg:city":"London",
    "sg:classifiers":[
        {
            "category":"Professional",
            "subcategory":"Computer Services",
            "type":"Services"
        }
    ],
    "sg:postcode":"N4 3BE",
    "sg:province":"Greater London",
    "sg:tags":[
        "consultant"
    ],
    "wof:name":"Information Link Ltd",
    "wof:placetype":"venue"
},
  "geometry": {"coordinates":[-0.1166789979,51.5680503845],"type":"Point"}
}