{
  "type": "Feature",
  "properties": {
    "addr:full":"Yeo Barton, Hewish Weston Super Mare Somerset BS24 6RS",
    "addr:housenumber":"yeo;hewish",
    "addr:postcode":"bs24 6rs",
    "addr:street":"Weston",
    "iso:country":"GB",
    "sg:address":"Yeo Barton, Hewish",
    "sg:city":"Weston Super Mare",
    "sg:classifiers":[
        {
            "category":"Manufacturing",
            "subcategory":"Lumber",
            "type":"Manufacturing & Wholesale Goods"
        }
    ],
    "sg:phone":"+44 1934 833201",
    "sg:postcode":"BS24 6RS",
    "sg:province":"Somerset",
    "sg:tags":[
        "importer",
        "merchants",
        "agent",
        "timber"
    ],
    "wof:name":"Scotts",
    "wof:placetype":"venue"
},
  "geometry": {"coordinates":[-2.8689699173,51.3719711304],"type":"Point"}
}