{
  "type": "Feature",
  "properties": {
    "addr:full":"Falcon One, 2 Stonefield Way Ruislip Greater London HA4 0JS",
    "addr:housenumber":"2",
    "addr:postcode":"ha4 0js",
    "addr:street":"Stonefield Way",
    "iso:country":"GB",
    "sg:address":"Falcon One, 2 Stonefield Way",
    "sg:city":"Ruislip",
    "sg:classifiers":[
        {
            "category":"Recreation",
            "subcategory":"Arcade",
            "type":"Entertainment"
        }
    ],
    "sg:phone":"+44 20 8426 5822",
    "sg:postcode":"HA4 0JS",
    "sg:province":"Greater London",
    "sg:tags":[
        "machine",
        "amusement"
    ],
    "wof:name":"Aristocrat Technologies Europe Ltd.",
    "wof:placetype":"venue"
},
  "geometry": {"coordinates":[-0.426279,51.575886],"type":"Point"}
}