{
  "type": "Feature",
  "properties": {
    "addr:full":"Unit 3, Thames Street Louth Lincolnshire LN11 7AD",
    "addr:housenumber":"unit 3",
    "addr:postcode":"ln11 7ad",
    "addr:street":"Thames Street Louth",
    "iso:country":"GB",
    "sg:address":"Unit 3, Thames Street",
    "sg:city":"Louth",
    "sg:classifiers":[
        {
            "category":"Professional",
            "subcategory":"Accounting & Tax Preparation",
            "type":"Services"
        },
        {
            "category":"Wholesale",
            "subcategory":"Construction Materials",
            "type":"Manufacturing & Wholesale Goods"
        }
    ],
    "sg:phone":"+44 1507 609400",
    "sg:postcode":"LN11 7AD",
    "sg:province":"Lincolnshire",
    "sg:tags":[
        "specialist",
        "coating",
        "powder"
    ],
    "wof:name":"Plastic Powder Coatings",
    "wof:placetype":"venue"
},
  "geometry": {"coordinates":[0.009943,53.3714294434],"type":"Point"}
}