{
  "type": "Feature",
  "properties": {
    "addr:full":"143 Shaw Heath Stockport Cheshire SK2 6QZ",
    "addr:housenumber":"143",
    "addr:postcode":"sk2 6qz",
    "addr:street":"Shaw Heath",
    "iso:country":"GB",
    "sg:address":"143 Shaw Heath",
    "sg:city":"Stockport",
    "sg:classifiers":[
        {
            "category":"Home & Garden",
            "subcategory":"Hardware",
            "type":"Retail Goods"
        }
    ],
    "sg:phone":"+44 161 480 4543",
    "sg:postcode":"SK2 6QZ",
    "sg:province":"Cheshire",
    "sg:tags":[
        "merchant",
        "ironmonger"
    ],
    "wof:name":"Handy Hardware",
    "wof:placetype":"venue"
},
  "geometry": {"coordinates":[-2.157214,53.397923],"type":"Point"}
}