{
  "type": "Feature",
  "properties": {
    "addr:full":"Unit 3 Bury Lancashire BL8 1PL",
    "addr:housenumber":"unit 3",
    "addr:postcode":"bl8 1pl",
    "iso:country":"GB",
    "sg:address":"Unit 3",
    "sg:city":"Bury",
    "sg:classifiers":[
        {
            "category":"Utilities",
            "subcategory":"Mobile Phone",
            "type":"Services"
        }
    ],
    "sg:postcode":"BL8 1PL",
    "sg:province":"Lancashire",
    "sg:tags":[
        "battery",
        "supplier"
    ],
    "wof:name":"Delta Batteries (of Bury) Ltd.",
    "wof:placetype":"venue"
},
  "geometry": {"coordinates":[-2.32454,53.60083],"type":"Point"}
}