{
  "type": "Feature",
  "properties": {
    "addr:full":"Sales Office 4 Dudley Street Grimsby Lincolnshire DN31 2AB",
    "addr:housenumber":"4",
    "addr:postcode":"dn31 2ab",
    "addr:street":"Dudley Street",
    "iso:country":"GB",
    "sg:address":"Sales Office 4 Dudley Street",
    "sg:city":"Grimsby",
    "sg:classifiers":[
        {
            "category":"Building & Trades",
            "subcategory":"Construction",
            "type":"Services"
        }
    ],
    "sg:phone":"+44 1472 352101",
    "sg:postcode":"DN31 2AB",
    "sg:province":"Lincolnshire",
    "sg:tags":[
        "builder"
    ],
    "wof:name":"Chartdale Homes Ltd.",
    "wof:placetype":"venue"
},
  "geometry": {"coordinates":[-0.09397,53.563278],"type":"Point"}
}