{
  "type": "Feature",
  "properties": {
    "addr:full":"4 Eden Rd Durham Durham DH1 5LF",
    "addr:housenumber":"4",
    "addr:postcode":"dh1 5lf",
    "addr:street":"Eden Rd",
    "iso:country":"GB",
    "sg:address":"4 Eden Rd",
    "sg:city":"Durham",
    "sg:classifiers":[
        {
            "category":"Community Center",
            "type":"Public Place"
        }
    ],
    "sg:phone":"+44 191 383 0286",
    "sg:postcode":"DH1 5LF",
    "sg:province":"Durham",
    "sg:tags":[
        "centre",
        "entertainment"
    ],
    "wof:name":"Regal Entertainments (UK)",
    "wof:placetype":"venue"
},
  "geometry": {"coordinates":[-1.5767730474,54.7967758179],"type":"Point"}
}