{
  "type": "Feature",
  "properties": {
    "addr:full":"2 Chandos Place, Bletchley Milton Keynes Buckinghamshire MK2 2SQ",
    "addr:housenumber":"2",
    "addr:postcode":"mk2 2sq",
    "addr:street":"Chandos Place",
    "iso:country":"GB",
    "sg:address":"2 Chandos Place, Bletchley",
    "sg:city":"Milton Keynes",
    "sg:classifiers":[
        {
            "category":"Professional",
            "subcategory":"Computer Services",
            "type":"Services"
        }
    ],
    "sg:phone":"+44 1908 371086",
    "sg:postcode":"MK2 2SQ",
    "sg:province":"Buckinghamshire",
    "sg:tags":[
        "consultant"
    ],
    "wof:name":"Ram Computer Systems Ltd.",
    "wof:placetype":"venue"
},
  "geometry": {"coordinates":[-0.7348369956,51.9939308167],"type":"Point"}
}