{
  "type": "Feature",
  "properties": {
    "addr:full":"89 Myddleton Road, Wood Green London Greater London N22 4NE",
    "addr:housenumber":"89",
    "addr:postcode":"n22 4ne",
    "addr:street":"Myddleton Road",
    "iso:country":"GB",
    "sg:address":"89 Myddleton Road, Wood Green",
    "sg:city":"London",
    "sg:classifiers":[
        {
            "category":"Travel",
            "subcategory":"Travel Agent",
            "type":"Entertainment"
        }
    ],
    "sg:phone":"+44 20 8881 3036",
    "sg:postcode":"N22 4NE",
    "sg:province":"Greater London",
    "wof:name":"Imperial Airtours Ltd.",
    "wof:placetype":"venue"
},
  "geometry": {"coordinates":[-0.1155600026,51.6014595032],"type":"Point"}
}