{
  "type": "Feature",
  "properties": {
    "iso:country":"GB",
    "sg:address":"Victoria House, Radford Way",
    "sg:city":"Billericay",
    "sg:classifiers":[
        {
            "category":"Wholesale",
            "subcategory":"Construction Materials",
            "type":"Manufacturing & Wholesale Goods"
        }
    ],
    "sg:phone":"+44 1268 594400",
    "sg:postcode":"CM12 0DE",
    "sg:province":"Essex",
    "sg:tags":[
        "supplier",
        "colour"
    ],
    "wof:name":"Univar Ltd.",
    "wof:placetype":"venue"
},
  "geometry": {"coordinates":[0.416556,51.629608],"type":"Point"}
}