{
  "type": "Feature",
  "properties": {
    "iso:country":"GB",
    "sg:address":"Cross Keys, Lower Bristol Road",
    "sg:city":"Bristol",
    "sg:classifiers":[
        {
            "category":"Travel",
            "subcategory":"Hotels & Motels",
            "type":"Entertainment"
        }
    ],
    "sg:postcode":"BS39 5PB",
    "sg:province":"Somerset",
    "wof:name":"Blue Lion Inns Ltd.",
    "wof:placetype":"venue"
},
  "geometry": {"coordinates":[-2.5396499634,51.3315505981],"type":"Point"}
}