{
  "type": "Feature",
  "properties": {
    "addr:full":"351-351a Hanworth Road Hounslow Greater London TW3 3SE",
    "addr:housenumber":"351-351a",
    "addr:postcode":"tw3 3se",
    "addr:street":"Hanworth Road",
    "iso:country":"GB",
    "sg:address":"351-351a Hanworth Road",
    "sg:city":"Hounslow",
    "sg:classifiers":[
        {
            "category":"Shopping",
            "subcategory":"Crafts & Fabrics",
            "type":"Retail Goods"
        }
    ],
    "sg:phone":"+44 20 8572 9838",
    "sg:postcode":"TW3 3SE",
    "sg:province":"Greater London",
    "sg:tags":[
        "shop"
    ],
    "wof:name":"Mackenzies Textile",
    "wof:placetype":"venue"
},
  "geometry": {"coordinates":[-0.369952,51.459816],"type":"Point"}
}