{
  "type": "Feature",
  "properties": {
    "addr:full":"The Portrait Studio, Jewry Street Winchester Hampshire SO23 8SA",
    "addr:postcode":"so23 8sa",
    "addr:street":"Jewry Street",
    "iso:country":"GB",
    "sg:address":"The Portrait Studio, Jewry Street",
    "sg:city":"Winchester",
    "sg:classifiers":[
        {
            "category":"Professional",
            "subcategory":"Art Services",
            "type":"Services"
        }
    ],
    "sg:postcode":"SO23 8SA",
    "sg:province":"Hampshire",
    "sg:tags":[
        "photographer"
    ],
    "wof:name":"Maddie Attenborough",
    "wof:placetype":"venue"
},
  "geometry": {"coordinates":[-1.3168090582,51.0630683899],"type":"Point"}
}