{
  "type": "Feature",
  "properties": {
    "addr:full":"39 Lilyhill Terrace Edinburgh City of Edinburgh EH8 7DR",
    "addr:housenumber":"39",
    "addr:postcode":"eh8 7dr",
    "addr:street":"Lilyhill Terrace",
    "iso:country":"GB",
    "sg:address":"39 Lilyhill Terrace",
    "sg:city":"Edinburgh",
    "sg:classifiers":[
        {
            "category":"Professional",
            "subcategory":"Management & Consulting",
            "type":"Services"
        }
    ],
    "sg:phone":"+44 131 652 0205",
    "sg:postcode":"EH8 7DR",
    "sg:province":"City of Edinburgh",
    "sg:tags":[
        "marketing",
        "consultant"
    ],
    "wof:name":"Saltire Communications",
    "wof:placetype":"venue"
},
  "geometry": {"coordinates":[-3.1518630981,55.9531898499],"type":"Point"}
}