{
  "type": "Feature",
  "properties": {
    "iso:country":"GB",
    "sg:address":"2-6 King St",
    "sg:city":"Maidstone",
    "sg:classifiers":[
        {
            "category":"Shopping",
            "subcategory":"Clothing, Apparel, & Fashions",
            "type":"Retail Goods"
        }
    ],
    "sg:phone":"+44 1622 755444",
    "sg:postcode":"ME14 1DE",
    "sg:province":"Kent",
    "sg:tags":[
        "accessory"
    ],
    "wof:name":"Miss Attitude (Trading) Ltd",
    "wof:placetype":"venue"
},
  "geometry": {"coordinates":[0.524194,51.273762],"type":"Point"}
}