{
  "type": "Feature",
  "properties": {
    "addr:full":"Wester Hailes Centre Edinburgh City of Edinburgh EH14 2SW",
    "addr:postcode":"eh14 2sw",
    "iso:country":"GB",
    "sg:address":"Wester Hailes Centre",
    "sg:city":"Edinburgh",
    "sg:classifiers":[
        {
            "category":"Community Center",
            "subcategory":"Social",
            "type":"Public Place"
        }
    ],
    "sg:phone":"+44 131 442 3795",
    "sg:postcode":"EH14 2SW",
    "sg:province":"City of Edinburgh",
    "sg:tags":[
        "frozen",
        "food",
        "freezer",
        "centre"
    ],
    "wof:name":"Farmfoods Freezer Centre",
    "wof:placetype":"venue"
},
  "geometry": {"coordinates":[-3.2857789993,55.9166603088],"type":"Point"}
}