{
  "type": "Feature",
  "properties": {
    "addr:full":"16 South St, Hythe Southampton Hampshire SO45 6EB",
    "addr:housenumber":"16",
    "addr:postcode":"so45 6eb",
    "addr:street":"South St",
    "iso:country":"GB",
    "sg:address":"16 South St, Hythe",
    "sg:city":"Southampton",
    "sg:classifiers":[
        {
            "category":"Shopping",
            "subcategory":"Bicycles & Sporting Goods",
            "type":"Retail Goods"
        }
    ],
    "sg:phone":"+44 23 8084 3396",
    "sg:postcode":"SO45 6EB",
    "sg:province":"Hampshire",
    "sg:tags":[
        "cycle",
        "accessory"
    ],
    "wof:name":"SOLENT CYCLES",
    "wof:placetype":"venue"
},
  "geometry": {"coordinates":[-1.3976089954,50.8674621582],"type":"Point"}
}