{
  "type": "Feature",
  "properties": {
    "addr:full":"15 Queen Street, Lochmaben Lockerbie Dumfries and Galloway DG11 1PP",
    "addr:housenumber":"15",
    "addr:postcode":"dg11 1pp",
    "addr:street":"Queen Street",
    "iso:country":"GB",
    "sg:address":"15 Queen Street, Lochmaben",
    "sg:city":"Lockerbie",
    "sg:classifiers":[
        {
            "category":"Real Estate",
            "subcategory":"Developer",
            "type":"Services"
        }
    ],
    "sg:phone":"+44 1387 810316",
    "sg:postcode":"DG11 1PP",
    "sg:province":"Dumfries and Galloway",
    "sg:tags":[
        "property"
    ],
    "wof:name":"W & J Hunter",
    "wof:placetype":"venue"
},
  "geometry": {"coordinates":[-3.4417390823,55.1299819946],"type":"Point"}
}