{
  "type": "Feature",
  "properties": {
    "iso:country":"GB",
    "sg:address":"11 Beckenham Av",
    "sg:city":"Liverpool",
    "sg:classifiers":[
        {
            "category":"Building & Trades",
            "subcategory":"Construction",
            "type":"Services"
        }
    ],
    "sg:phone":"+44 151 734 2715",
    "sg:postcode":"L18 1JH",
    "sg:province":"Merseyside",
    "sg:tags":[
        "builder"
    ],
    "wof:name":"Unibuild",
    "wof:placetype":"venue"
},
  "geometry": {"coordinates":[-2.9224760532,53.3862495422],"type":"Point"}
}