{
  "type": "Feature",
  "properties": {
    "iso:country":"GB",
    "sg:address":"219 Quarmby Road",
    "sg:city":"Huddersfield",
    "sg:classifiers":[
        {
            "category":"Bars & Pubs",
            "type":"Food & Drink"
        },
        {
            "category":"Community Center",
            "subcategory":"Social",
            "type":"Public Place"
        }
    ],
    "sg:phone":"+44 1484 654581",
    "sg:postcode":"HD3 4FB",
    "sg:province":"West Yorkshire",
    "sg:tags":[
        "pubs",
        "house",
        "inn",
        "activity"
    ],
    "wof:name":"The Fieldhead",
    "wof:placetype":"venue"
},
  "geometry": {"coordinates":[-1.8262460232,53.6483879089],"type":"Point"}
}