{
  "type": "Feature",
  "properties": {
    "addr:full":"Shell Bp House Leeds West Yorkshire LS2 7LY",
    "addr:postcode":"ls2 7ly",
    "addr:street":"Leeds West",
    "iso:country":"GB",
    "sg:address":"Shell Bp House",
    "sg:city":"Leeds",
    "sg:classifiers":[
        {
            "category":"Professional",
            "subcategory":"Advertising",
            "type":"Services"
        }
    ],
    "sg:phone":"+44 113 243 4646",
    "sg:postcode":"LS2 7LY",
    "sg:province":"West Yorkshire",
    "sg:tags":[
        "agency"
    ],
    "wof:name":"Stuart Hirst Ltd.",
    "wof:placetype":"venue"
},
  "geometry": {"coordinates":[-1.53783,53.798901],"type":"Point"}
}