{
  "type": "Feature",
  "properties": {
    "addr:full":"Udiam Farm Oast, Junction Road, Bodiam Robertsbridge East Sussex TN32 5XD",
    "addr:postcode":"tn32 5xd",
    "addr:street":"Junction Road;Robertsbridge",
    "iso:country":"GB",
    "sg:address":"Udiam Farm Oast, Junction Road, Bodiam",
    "sg:city":"Robertsbridge",
    "sg:classifiers":[
        {
            "category":"Professional",
            "subcategory":"Engineering",
            "type":"Services"
        }
    ],
    "sg:phone":"+44 1580 830680",
    "sg:postcode":"TN32 5XD",
    "sg:province":"East Sussex",
    "wof:name":"S J Playfoot Engineering",
    "wof:placetype":"venue"
},
  "geometry": {"coordinates":[0.4744699895,50.9856491089],"type":"Point"}
}