{
  "type": "Feature",
  "properties": {
    "iso:country":"GB",
    "sg:address":"St Marys Lane",
    "sg:city":"Upminster",
    "sg:classifiers":[
        {
            "category":"Education",
            "subcategory":"School",
            "type":"Public Place"
        }
    ],
    "sg:phone":"+44 1708 220453",
    "sg:postcode":"RM14 3BS",
    "sg:province":"Essex",
    "sg:tags":[
        "local",
        "authority"
    ],
    "wof:name":"Upminster Junior School",
    "wof:placetype":"venue"
},
  "geometry": {"coordinates":[0.267033,51.557312],"type":"Point"}
}