{
  "type": "Feature",
  "properties": {
    "addr:full":"48 Tonehill, Tonedale Wellington Devon TA21 0AX",
    "addr:housenumber":"48",
    "addr:postcode":"ta21 0ax",
    "addr:street":"Tonehill Tonedale",
    "iso:country":"GB",
    "sg:address":"48 Tonehill, Tonedale",
    "sg:city":"Wellington",
    "sg:classifiers":[
        {
            "category":"Retail",
            "subcategory":"Driving School",
            "type":"Services"
        }
    ],
    "sg:postcode":"TA21 0AX",
    "sg:province":"Devon",
    "wof:name":"Roger Nunn Driving Services",
    "wof:placetype":"venue"
},
  "geometry": {"coordinates":[-3.299949,50.984489],"type":"Point"}
}