{
  "type": "Feature",
  "properties": {
    "addr:full":"Dorset House, Blackfriars Avenue Droitwich Worcestershire WR9 8DR",
    "addr:postcode":"wr9 8dr",
    "addr:street":"Blackfriars Avenue",
    "iso:country":"GB",
    "sg:address":"Dorset House, Blackfriars Avenue",
    "sg:city":"Droitwich",
    "sg:classifiers":[
        {
            "category":"Social Services",
            "subcategory":"Retirement Home",
            "type":"Services"
        }
    ],
    "sg:phone":"+44 1905 772710",
    "sg:postcode":"WR9 8DR",
    "sg:province":"Worcestershire",
    "sg:tags":[
        "rest"
    ],
    "wof:name":"Dorset House Residential Home",
    "wof:placetype":"venue"
},
  "geometry": {"coordinates":[-2.152878,52.264946],"type":"Point"}
}