{
  "type": "Feature",
  "properties": {
    "addr:full":"The Rectory, Stackpole Pembroke Pembrokeshire SA71 5BZ",
    "addr:postcode":"sa71 5bz",
    "addr:street":"Pembroke",
    "iso:country":"GB",
    "sg:address":"The Rectory, Stackpole",
    "sg:city":"Pembroke",
    "sg:classifiers":[
        {
            "category":"Place Of Worship",
            "type":"Public Place"
        }
    ],
    "sg:postcode":"SA71 5BZ",
    "sg:province":"Pembrokeshire",
    "wof:name":"St.Twynnells",
    "wof:placetype":"venue"
},
  "geometry": {"coordinates":[-4.9141669273,51.6307754517],"type":"Point"}
}