{
  "type": "Feature",
  "properties": {
    "addr:full":"Unit 401 Berrows Business Centre, Bath Street Hereford Herefordshire HR1 2HE",
    "addr:housenumber":"401",
    "addr:postcode":"hr1 2he",
    "addr:street":"Berrows Business Centre Bath Street",
    "iso:country":"GB",
    "sg:address":"Unit 401 Berrows Business Centre, Bath Street",
    "sg:city":"Hereford",
    "sg:classifiers":[
        {
            "category":"Professional",
            "subcategory":"Detective & Security Services",
            "type":"Services"
        }
    ],
    "sg:phone":"+44 1432 278111",
    "sg:postcode":"HR1 2HE",
    "sg:province":"Herefordshire",
    "wof:name":"Night Watch Security Services",
    "wof:placetype":"venue"
},
  "geometry": {"coordinates":[-2.7110199928,52.0570411682],"type":"Point"}
}