{
  "type": "Feature",
  "properties": {
    "addr:full":"Archers Fields Close, Burnt Mills Industrial Estate Basildon Essex SS13 1DN",
    "addr:postcode":"ss13 1dn",
    "addr:street":"Archers Fields Close;Estate",
    "iso:country":"GB",
    "sg:address":"Archers Fields Close, Burnt Mills Industrial Estate",
    "sg:city":"Basildon",
    "sg:classifiers":[
        {
            "category":"Wholesale",
            "subcategory":"Scrap",
            "type":"Manufacturing & Wholesale Goods"
        }
    ],
    "sg:phone":"+44 1268 727681",
    "sg:postcode":"SS13 1DN",
    "sg:province":"Essex",
    "sg:tags":[
        "breaker",
        "dismantlers"
    ],
    "wof:name":"Basildon Volvo Parts",
    "wof:placetype":"venue"
},
  "geometry": {"coordinates":[0.502577,51.585571],"type":"Point"}
}