{
  "type": "Feature",
  "properties": {
    "addr:full":"Criminal Work Team, Court Centre, Bethesda St Stoke On Trent Staffordshire ST1 3BP",
    "addr:postcode":"st1 3bp",
    "addr:street":"Bethesda St",
    "iso:country":"GB",
    "sg:address":"Criminal Work Team, Court Centre, Bethesda St",
    "sg:city":"Stoke On Trent",
    "sg:classifiers":[
        {
            "category":"Government",
            "subcategory":"Office",
            "type":"Public Place"
        }
    ],
    "sg:phone":"+44 1782 286831",
    "sg:postcode":"ST1 3BP",
    "sg:province":"Staffordshire",
    "sg:tags":[
        "central"
    ],
    "wof:name":"Probation Service",
    "wof:placetype":"venue"
},
  "geometry": {"coordinates":[-2.175074,53.020279],"type":"Point"}
}