{
  "type": "Feature",
  "properties": {
    "iso:country":"GB",
    "sg:address":"Care Of 10 South Pde",
    "sg:city":"Northallerton",
    "sg:classifiers":[
        {
            "category":"Professional",
            "subcategory":"Lawyer & Legal Services",
            "type":"Services"
        }
    ],
    "sg:postcode":"DL7 8SE",
    "sg:province":"North Yorkshire",
    "sg:tags":[
        "advice",
        "counselling"
    ],
    "wof:name":"Bereavement Care Northallerton & Distric",
    "wof:placetype":"venue"
},
  "geometry": {"coordinates":[-1.43532,54.336189],"type":"Point"}
}