{
  "type": "Feature",
  "properties": {
    "addr:full":"The Hills Road Cambridge Cambridgeshire CB2 2QF",
    "addr:postcode":"cb2 2qf",
    "addr:street":"The Hills Road",
    "iso:country":"GB",
    "sg:address":"The Hills Road",
    "sg:city":"Cambridge",
    "sg:classifiers":[
        {
            "category":"Education",
            "subcategory":"School",
            "type":"Public Place"
        }
    ],
    "sg:postcode":"CB2 2QF",
    "sg:province":"Cambridgeshire",
    "sg:tags":[
        "independent",
        "preparatory"
    ],
    "wof:name":"The Perse School",
    "wof:placetype":"venue"
},
  "geometry": {"coordinates":[0.1359750032,52.1891517639],"type":"Point"}
}