{
  "type": "Feature",
  "properties": {
    "addr:full":"52 Kirton Road, Scawby Brigg Lincolnshire DN20 9NF",
    "addr:housenumber":"52",
    "addr:postcode":"dn20 9nf",
    "addr:street":"Kirton Road;Brigg",
    "iso:country":"GB",
    "sg:address":"52 Kirton Road, Scawby",
    "sg:city":"Brigg",
    "sg:classifiers":[
        {
            "category":"Autos & Motor Vehicles",
            "subcategory":"Automobile Sales",
            "type":"Retail Goods"
        }
    ],
    "sg:phone":"+44 1652 650291",
    "sg:postcode":"DN20 9NF",
    "sg:province":"Lincolnshire",
    "sg:tags":[
        "car",
        "used"
    ],
    "wof:name":"P A Autos",
    "wof:placetype":"venue"
},
  "geometry": {"coordinates":[-0.5769010186,53.5413093567],"type":"Point"}
}