{
  "type": "Feature",
  "properties": {
    "addr:full":"277 Whalley Road, Clayton Le Moors Accrington Lancashire BB5 5QU",
    "addr:housenumber":"277",
    "addr:postcode":"bb5 5qu",
    "addr:street":"Whalley Road",
    "iso:country":"GB",
    "sg:address":"277 Whalley Road, Clayton Le Moors",
    "sg:city":"Accrington",
    "sg:classifiers":[
        {
            "category":"Fast Food",
            "type":"Food & Drink"
        }
    ],
    "sg:phone":"+44 1254 398888",
    "sg:postcode":"BB5 5QU",
    "sg:province":"Lancashire",
    "sg:tags":[
        "away",
        "take"
    ],
    "wof:name":"Pizza Time",
    "wof:placetype":"venue"
},
  "geometry": {"coordinates":[-2.3722629547,53.7647781372],"type":"Point"}
}