{
  "type": "Feature",
  "properties": {
    "iso:country":"GB",
    "sg:address":"No 6 Lomond Industrial Estate",
    "sg:city":"Alexandria",
    "sg:classifiers":[
        {
            "category":"Shopping",
            "subcategory":"Clothing, Apparel, & Fashions",
            "type":"Retail Goods"
        }
    ],
    "sg:phone":"+44 1389 756161",
    "sg:postcode":"G83 0TL",
    "sg:province":"Argyll and Bute",
    "sg:tags":[
        "ladieswear"
    ],
    "wof:name":"Beeline",
    "wof:placetype":"venue"
},
  "geometry": {"coordinates":[-4.582669,55.988441],"type":"Point"}
}