{
  "type": "Feature",
  "properties": {
    "addr:full":"100 Brook St Glasgow Glasgow City G40 3AP",
    "addr:housenumber":"100",
    "addr:postcode":"g40 3ap",
    "addr:street":"Brook St",
    "iso:country":"GB",
    "sg:address":"100 Brook St",
    "sg:city":"Glasgow",
    "sg:classifiers":[
        {
            "category":"Building & Trades",
            "subcategory":"Equipment Rental",
            "type":"Services"
        }
    ],
    "sg:phone":"+44 141 554 6477",
    "sg:postcode":"G40 3AP",
    "sg:province":"Glasgow City",
    "sg:tags":[
        "plant",
        "machinery"
    ],
    "wof:name":"Nim Hire",
    "wof:placetype":"venue"
},
  "geometry": {"coordinates":[-4.2224750519,55.8500137329],"type":"Point"}
}