{
  "type": "Feature",
  "properties": {
    "addr:full":"Mosley Road North, Trafford Park Manchester Cheshire M17 1TU",
    "addr:postcode":"m17 1tu",
    "addr:street":"Mosley Road North Trafford Park",
    "iso:country":"GB",
    "sg:address":"Mosley Road North, Trafford Park",
    "sg:city":"Manchester",
    "sg:classifiers":[
        {
            "category":"Landmark",
            "subcategory":"Tourist Attraction",
            "type":"Public Place"
        }
    ],
    "sg:phone":"+44 161 873 7182",
    "sg:postcode":"M17 1TU",
    "sg:province":"Cheshire",
    "sg:tags":[
        "interest"
    ],
    "wof:name":"Trafford Ecology Park",
    "wof:placetype":"venue"
},
  "geometry": {"coordinates":[-2.317219,53.467426],"type":"Point"}
}