{
  "type": "Feature",
  "properties": {
    "addr:full":"Braintree Enterprise Centre Braintree Essex CM7 2YN",
    "addr:postcode":"cm7 2yn",
    "iso:country":"GB",
    "sg:address":"Braintree Enterprise Centre",
    "sg:city":"Braintree",
    "sg:classifiers":[
        {
            "category":"Home & Garden",
            "subcategory":"Household Appliances",
            "type":"Retail Goods"
        }
    ],
    "sg:postcode":"CM7 2YN",
    "sg:province":"Essex",
    "sg:tags":[
        "electrical"
    ],
    "wof:name":"J W Microwave Oven Services",
    "wof:placetype":"venue"
},
  "geometry": {"coordinates":[0.5532420278,51.8777580261],"type":"Point"}
}