{
  "type": "Feature",
  "properties": {
    "addr:full":"Peelings Lane, Westham Pevensey East Sussex BN24 5HE",
    "addr:postcode":"bn24 5he",
    "addr:street":"Peelings Lane",
    "iso:country":"GB",
    "sg:address":"Peelings Lane, Westham",
    "sg:city":"Pevensey",
    "sg:classifiers":[
        {
            "category":"Building & Trades",
            "subcategory":"Construction",
            "type":"Services"
        }
    ],
    "sg:postcode":"BN24 5HE",
    "sg:province":"East Sussex",
    "sg:tags":[
        "worker",
        "metal"
    ],
    "wof:name":"The Glynleigh Studio",
    "wof:placetype":"venue"
},
  "geometry": {"coordinates":[0.3407459855,50.8211021423],"type":"Point"}
}