{
  "type": "Feature",
  "properties": {
    "iso:country":"GB",
    "sg:address":"71 Dalling Rd",
    "sg:city":"Bathgate",
    "sg:classifiers":[
        {
            "category":"Building & Trades",
            "subcategory":"Construction",
            "type":"Services"
        }
    ],
    "sg:phone":"+44 1506 655048",
    "sg:postcode":"EH48 2RQ",
    "sg:province":"West Lothian",
    "sg:tags":[
        "dry",
        "lining",
        "plasterers",
        "screeders"
    ],
    "wof:name":"J P Brady",
    "wof:placetype":"venue"
},
  "geometry": {"coordinates":[-3.653287,55.896137],"type":"Point"}
}