{
  "type": "Feature",
  "properties": {
    "addr:full":"Moreton Hampstead, 2 Fore Street Newton Abbot Devon TQ13 8LL",
    "addr:housenumber":"2",
    "addr:postcode":"tq13 8ll",
    "addr:street":"Fore Street",
    "iso:country":"GB",
    "sg:address":"Moreton Hampstead, 2 Fore Street",
    "sg:city":"Newton Abbot",
    "sg:classifiers":[
        {
            "category":"Community Center",
            "subcategory":"Youth",
            "type":"Public Place"
        }
    ],
    "sg:phone":"+44 1392 250976",
    "sg:postcode":"TQ13 8LL",
    "sg:province":"Devon",
    "sg:tags":[
        "organisation",
        "centre"
    ],
    "wof:name":"Youth Services (Devon) Voluntary",
    "wof:placetype":"venue"
},
  "geometry": {"coordinates":[-3.7641499043,50.660949707],"type":"Point"}
}