{
  "type": "Feature",
  "properties": {
    "iso:country":"GB",
    "sg:address":"934 Christchurch Road",
    "sg:city":"Bournemouth",
    "sg:classifiers":[
        {
            "category":"Shopping",
            "subcategory":"Department Store",
            "type":"Retail Goods"
        }
    ],
    "sg:phone":"+44 1202 430000",
    "sg:postcode":"BH7 6DL",
    "sg:province":"Dorset",
    "wof:name":"Backtrack Records Secondhand",
    "wof:placetype":"venue"
},
  "geometry": {"coordinates":[-1.8252220154,50.7309684753],"type":"Point"}
}