{
  "type": "Feature",
  "properties": {
    "iso:country":"GB",
    "sg:address":"Crow House, Crow Arch Lane Industrial Estate",
    "sg:city":"Ringwood",
    "sg:classifiers":[
        {
            "category":"Manufacturing",
            "subcategory":"Building Materials",
            "type":"Manufacturing & Wholesale Goods"
        }
    ],
    "sg:phone":"+44 1425 462020",
    "sg:postcode":"BH24 1PD",
    "sg:province":"Dorset",
    "sg:tags":[
        "shutter",
        "supp",
        "door"
    ],
    "wof:name":"Kaba Door Systems Ltd.",
    "wof:placetype":"venue"
},
  "geometry": {"coordinates":[-1.779474,50.842972],"type":"Point"}
}