{
  "type": "Feature",
  "properties": {
    "addr:full":"196 New Church Road Hove East Sussex BN3 4EA",
    "addr:housenumber":"196",
    "addr:postcode":"bn3 4ea",
    "addr:street":"New Church Road",
    "iso:country":"GB",
    "sg:address":"196 New Church Road",
    "sg:city":"Hove",
    "sg:classifiers":[
        {
            "category":"Banks & Credit Unions",
            "subcategory":"Financial Services",
            "type":"Services"
        }
    ],
    "sg:phone":"+44 1273 881343",
    "sg:postcode":"BN3 4EA",
    "sg:province":"East Sussex",
    "sg:tags":[
        "adviser"
    ],
    "wof:name":"Complete Financial Services",
    "wof:placetype":"venue"
},
  "geometry": {"coordinates":[-0.201356,50.831989],"type":"Point"}
}