{
  "type": "Feature",
  "properties": {
    "iso:country":"GB",
    "sg:address":"Gatehead",
    "sg:city":"Kilmarnock",
    "sg:classifiers":[
        {
            "category":"Restaurant",
            "type":"Food & Drink"
        }
    ],
    "sg:phone":"+44 1563 850265",
    "sg:postcode":"KA2 9AJ",
    "sg:province":"East Ayrshire",
    "wof:name":"Old Rome Farmhouse Hotel",
    "wof:placetype":"venue"
},
  "geometry": {"coordinates":[-4.55434,55.589359],"type":"Point"}
}