{
  "type": "Feature",
  "properties": {
    "addr:full":"Blackburn House, 22-26 Eastern Road Romford Essex RM1 3PJ",
    "addr:housenumber":"22-26",
    "addr:postcode":"rm1 3pj",
    "addr:street":"Eastern Road",
    "iso:country":"GB",
    "sg:address":"Blackburn House, 22-26 Eastern Road",
    "sg:city":"Romford",
    "sg:classifiers":[
        {
            "category":"Freight",
            "type":"Transportation"
        }
    ],
    "sg:phone":"+44 1708 737333",
    "sg:postcode":"RM1 3PJ",
    "sg:province":"Essex",
    "sg:tags":[
        "shipping",
        "forwarders"
    ],
    "wof:name":"Anatolia Shipping & Transport Ltd.",
    "wof:placetype":"venue"
},
  "geometry": {"coordinates":[0.185384,51.57579],"type":"Point"}
}