{
  "type": "Feature",
  "properties": {
    "addr:full":"66 Bourne Rd Bexley Kent DA5 1LU",
    "addr:housenumber":"66",
    "addr:postcode":"da5 1lu",
    "addr:street":"Bourne Rd",
    "iso:country":"GB",
    "sg:address":"66 Bourne Rd",
    "sg:city":"Bexley",
    "sg:classifiers":[
        {
            "category":"Professional",
            "subcategory":"Engineering",
            "type":"Services"
        }
    ],
    "sg:phone":"+44 1322 525657",
    "sg:postcode":"DA5 1LU",
    "sg:province":"Kent",
    "sg:tags":[
        "contractor",
        "electrical",
        "engineer"
    ],
    "wof:name":"TCM Engineering",
    "wof:placetype":"venue"
},
  "geometry": {"coordinates":[0.1514479965,51.444026947],"type":"Point"}
}