{
  "type": "Feature",
  "properties": {
    "addr:full":"3 Broom Hall Road Sheffield South Yorkshire S10 2DN",
    "addr:housenumber":"3",
    "addr:postcode":"s10 2dn",
    "addr:street":"Broom Hall Road",
    "iso:country":"GB",
    "sg:address":"3 Broom Hall Road",
    "sg:city":"Sheffield",
    "sg:classifiers":[
        {
            "category":"Health Services",
            "subcategory":"Nursing And Care Facility",
            "type":"Services"
        }
    ],
    "sg:phone":"+44 114 266 9669",
    "sg:postcode":"S10 2DN",
    "sg:province":"South Yorkshire",
    "sg:tags":[
        "home"
    ],
    "wof:name":"Hallamshire Old People's Residential Home Ltd.",
    "wof:placetype":"venue"
},
  "geometry": {"coordinates":[-1.486997,53.374504],"type":"Point"}
}