{
  "type": "Feature",
  "properties": {
    "iso:country":"GB",
    "sg:address":"Unit 21 Craycombe Farm, Fladbury",
    "sg:city":"Pershore",
    "sg:classifiers":[
        {
            "category":"Building & Trades",
            "subcategory":"Cleaning & Sanitation",
            "type":"Services"
        }
    ],
    "sg:phone":"+44 1386 860032",
    "sg:postcode":"WR10 2QS",
    "sg:province":"Worcestershire",
    "sg:tags":[
        "steam"
    ],
    "wof:name":"Pressure Washer Sales & Service",
    "wof:placetype":"venue"
},
  "geometry": {"coordinates":[-2.007159,52.114006],"type":"Point"}
}