{
  "type": "Feature",
  "properties": {
    "addr:full":"Unit 8, Woodfieldside Business Park, Penmaen Road Pontllanfraith Blackwood Caerphilly NP12 2DG",
    "addr:housenumber":"unit 8",
    "addr:postcode":"np12 2dg",
    "addr:street":"Woodfieldside Business Park Penmaen Road",
    "iso:country":"GB",
    "sg:address":"Unit 8, Woodfieldside Business Park, Penmaen Road Pontllanfraith",
    "sg:city":"Blackwood",
    "sg:classifiers":[
        {
            "category":"Home & Garden",
            "subcategory":"Household Appliances",
            "type":"Retail Goods"
        }
    ],
    "sg:postcode":"NP12 2DG",
    "sg:province":"Caerphilly",
    "sg:tags":[
        "electrical"
    ],
    "wof:name":"Intertek Testing & Certification Ltd.",
    "wof:placetype":"venue"
},
  "geometry": {"coordinates":[-3.1838779449,51.6597595215],"type":"Point"}
}