{
  "type": "Feature",
  "properties": {
    "iso:country":"GB",
    "sg:address":"32 Knowler Hill",
    "sg:city":"Liversedge",
    "sg:classifiers":[
        {
            "category":"Manufacturing",
            "subcategory":"Wood Products",
            "type":"Manufacturing & Wholesale Goods"
        }
    ],
    "sg:phone":"+44 1924 511200",
    "sg:postcode":"WF15 6DT",
    "sg:province":"West Yorkshire",
    "sg:tags":[
        "maker",
        "cabinet"
    ],
    "wof:name":"Kitchen Fitting Specialists",
    "wof:placetype":"venue"
},
  "geometry": {"coordinates":[-1.6950680017,53.7126922607],"type":"Point"}
}