{
  "type": "Feature",
  "properties": {
    "addr:full":"17 Van Mildert Close Peterlee Durham SR8 2NJ",
    "addr:housenumber":"17",
    "addr:postcode":"sr8 2nj",
    "addr:street":"Van Mildert Close",
    "iso:country":"GB",
    "sg:address":"17 Van Mildert Close",
    "sg:city":"Peterlee",
    "sg:classifiers":[
        {
            "category":"Food & Beverages",
            "subcategory":"Specialty",
            "type":"Retail Goods"
        }
    ],
    "sg:phone":"+44 191 586 2634",
    "sg:postcode":"SR8 2NJ",
    "sg:province":"Durham",
    "sg:tags":[
        "product",
        "health"
    ],
    "wof:name":"Vital Spark Nutrition",
    "wof:placetype":"venue"
},
  "geometry": {"coordinates":[-1.3505979776,54.7528152466],"type":"Point"}
}