{
  "type": "Feature",
  "properties": {
    "iso:country":"GB",
    "sg:address":"The Old School House, 2 Frogge Street",
    "sg:city":"Saffron Walden",
    "sg:classifiers":[
        {
            "category":"Professional",
            "subcategory":"Engineering",
            "type":"Services"
        }
    ],
    "sg:postcode":"CB10 1SH",
    "sg:province":"Cambridgeshire",
    "sg:tags":[
        "contractor",
        "electrical",
        "engineer"
    ],
    "wof:name":"Contract Electrical Services",
    "wof:placetype":"venue"
},
  "geometry": {"coordinates":[0.1776620001,52.0719795227],"type":"Point"}
}