{
  "type": "Feature",
  "properties": {
    "addr:full":"46 Wymondley Rd Hitchin Hertfordshire SG4 9PT",
    "addr:housenumber":"46",
    "addr:postcode":"sg4 9pt",
    "addr:street":"Wymondley Rd",
    "iso:country":"GB",
    "sg:address":"46 Wymondley Rd",
    "sg:city":"Hitchin",
    "sg:classifiers":[
        {
            "category":"Personal",
            "subcategory":"Skin Care",
            "type":"Services"
        }
    ],
    "sg:phone":"+44 1462 434665",
    "sg:postcode":"SG4 9PT",
    "sg:province":"Hertfordshire",
    "sg:tags":[
        "leather",
        "merchant"
    ],
    "wof:name":"Omersa & Co",
    "wof:placetype":"venue"
},
  "geometry": {"coordinates":[-0.2630000114,51.9459037781],"type":"Point"}
}