{
  "type": "Feature",
  "properties": {
    "addr:full":"Mayfair Industrial Estate, Maldon Road, Latchingdon Chelmsford Essex CM3 6LF",
    "addr:postcode":"cm3 6lf",
    "addr:street":"Estate Maldon Road",
    "iso:country":"GB",
    "sg:address":"Mayfair Industrial Estate, Maldon Road, Latchingdon",
    "sg:city":"Chelmsford",
    "sg:classifiers":[
        {
            "category":"Manufacturing",
            "subcategory":"Electronics",
            "type":"Manufacturing & Wholesale Goods"
        }
    ],
    "sg:phone":"+44 1621 742992",
    "sg:postcode":"CM3 6LF",
    "sg:province":"Essex",
    "sg:tags":[
        "printed",
        "circuit"
    ],
    "wof:name":"Circuit Board Assembly",
    "wof:placetype":"venue"
},
  "geometry": {"coordinates":[0.7268109918,51.6717147827],"type":"Point"}
}