{
  "type": "Feature",
  "properties": {
    "addr:full":"8 Mautland Street Houghton-le-spring Durham DH4 4BH",
    "addr:housenumber":"8",
    "addr:postcode":"dh4 4bh",
    "addr:street":"Mautland Street",
    "iso:country":"GB",
    "sg:address":"8 Mautland Street",
    "sg:city":"Houghton-le-spring",
    "sg:classifiers":[
        {
            "category":"Travel",
            "subcategory":"Travel Agent",
            "type":"Entertainment"
        }
    ],
    "sg:phone":"+44 191 512 0090",
    "sg:postcode":"DH4 4BH",
    "sg:province":"Durham",
    "wof:name":"Hays Travel",
    "wof:placetype":"venue"
},
  "geometry": {"coordinates":[-1.47152,54.844181],"type":"Point"}
}