{
  "type": "Feature",
  "properties": {
    "addr:full":"The Club House, West Hill, Aspley Guise Milton Keynes Bedfordshire MK17 8DX",
    "addr:postcode":"mk17 8dx",
    "addr:street":"West Hill;Guise",
    "iso:country":"GB",
    "sg:address":"The Club House, West Hill, Aspley Guise",
    "sg:city":"Milton Keynes",
    "sg:classifiers":[
        {
            "category":"Sports & Exercise",
            "subcategory":"Golf",
            "type":"Entertainment"
        }
    ],
    "sg:phone":"+44 1908 583596",
    "sg:postcode":"MK17 8DX",
    "sg:province":"Bedfordshire",
    "sg:tags":[
        "equipment"
    ],
    "wof:name":"Aspley Guise & Woburn Sands Golf Club Ltd",
    "wof:placetype":"venue"
},
  "geometry": {"coordinates":[-0.6454610229,52.0093955994],"type":"Point"}
}