{
  "type": "Feature",
  "properties": {
    "iso:country":"GB",
    "sg:address":"173 High Street",
    "sg:city":"Birmingham",
    "sg:classifiers":[
        {
            "category":"Parking",
            "type":"Transportation"
        },
        {
            "category":"Autos & Motor Vehicles",
            "subcategory":"Auto Supplies",
            "type":"Retail Goods"
        }
    ],
    "sg:phone":"+44 121 773 9800",
    "sg:postcode":"B12 0LD",
    "sg:province":"West Midlands",
    "sg:tags":[
        "car",
        "tyre",
        "valet"
    ],
    "wof:name":"New Digbeth Tyre Services",
    "wof:placetype":"venue"
},
  "geometry": {"coordinates":[-1.949729,52.458694],"type":"Point"}
}