{
  "type": "Feature",
  "properties": {
    "iso:country":"GB",
    "sg:address":"8 High Street, Strood",
    "sg:city":"Rochester",
    "sg:classifiers":[
        {
            "category":"Home & Garden",
            "subcategory":"Home Furnishings",
            "type":"Retail Goods"
        }
    ],
    "sg:phone":"+44 1634 713090",
    "sg:postcode":"ME2 4AP",
    "sg:province":"Kent",
    "sg:tags":[
        "mantelpiece",
        "fireplace"
    ],
    "wof:name":"Premier Plaster Crafts",
    "wof:placetype":"venue"
},
  "geometry": {"coordinates":[0.498714,51.3938903809],"type":"Point"}
}