{
  "type": "Feature",
  "properties": {
    "iso:country":"GB",
    "sg:address":"2a Somerton Road",
    "sg:city":"Newport",
    "sg:classifiers":[
        {
            "category":"Fast Food",
            "type":"Food & Drink"
        }
    ],
    "sg:phone":"+44 1633 270170",
    "sg:postcode":"NP19 8LE",
    "sg:province":"Newport",
    "sg:tags":[
        "away",
        "take"
    ],
    "wof:name":"Beechwood Tandoori",
    "wof:placetype":"venue"
},
  "geometry": {"coordinates":[-2.96285,51.587021],"type":"Point"}
}