{
  "type": "Feature",
  "properties": {
    "addr:full":"82 High Street, Bentley Doncaster South Yorkshire DN5 0AT",
    "addr:housenumber":"82",
    "addr:postcode":"dn5 0at",
    "addr:street":"High Street",
    "iso:country":"GB",
    "sg:address":"82 High Street, Bentley",
    "sg:city":"Doncaster",
    "sg:classifiers":[
        {
            "category":"Fast Food",
            "type":"Food & Drink"
        }
    ],
    "sg:phone":"+44 1302 874994",
    "sg:postcode":"DN5 0AT",
    "sg:province":"South Yorkshire",
    "sg:tags":[
        "away",
        "meal",
        "outlet",
        "take"
    ],
    "wof:name":"Jumbo Chinese Take Away",
    "wof:placetype":"venue"
},
  "geometry": {"coordinates":[-1.14733,53.545219],"type":"Point"}
}