{
  "type": "Feature",
  "properties": {
    "iso:country":"GB",
    "sg:address":"54 Station Road, Law",
    "sg:city":"Carluke",
    "sg:classifiers":[
        {
            "category":"Farming",
            "subcategory":"Dairy Farm",
            "type":"Manufacturing & Wholesale Goods"
        }
    ],
    "sg:postcode":"ML8 5LW",
    "sg:province":"South Lanarkshire",
    "wof:name":"R J Wishart & Son",
    "wof:placetype":"venue"
},
  "geometry": {"coordinates":[-3.8471870422,55.7322158813],"type":"Point"}
}