{
  "type": "Feature",
  "properties": {
    "iso:country":"GB",
    "sg:address":"51a Kenninghall Road",
    "sg:city":"London",
    "sg:classifiers":[
        {
            "category":"Professional",
            "subcategory":"Testing Lab",
            "type":"Services"
        }
    ],
    "sg:phone":"+44 20 8985 0015",
    "sg:postcode":"E5 8BS",
    "sg:province":"Greater London",
    "sg:tags":[
        "mot"
    ],
    "wof:name":"Brooke Motors",
    "wof:placetype":"venue"
},
  "geometry": {"coordinates":[-0.059435,51.558537],"type":"Point"}
}