{
  "type": "Feature",
  "properties": {
    "addr:full":"2a Silvertonhill Avenue Hamilton South Lanarkshire ML3 7ND",
    "addr:housenumber":"2a",
    "addr:postcode":"ml3 7nd",
    "addr:street":"Silvertonhill Avenue",
    "iso:country":"GB",
    "sg:address":"2a Silvertonhill Avenue",
    "sg:city":"Hamilton",
    "sg:classifiers":[
        {
            "category":"Building & Trades",
            "subcategory":"Construction",
            "type":"Services"
        }
    ],
    "sg:postcode":"ML3 7ND",
    "sg:province":"South Lanarkshire",
    "sg:tags":[
        "builder"
    ],
    "wof:name":"Parkland Homes Ltd",
    "wof:placetype":"venue"
},
  "geometry": {"coordinates":[-4.035082,55.769974],"type":"Point"}
}