{
  "type": "Feature",
  "properties": {
    "addr:full":"348 Barking Road London Greater London E13 8HL",
    "addr:housenumber":"348",
    "addr:postcode":"e13 8hl",
    "addr:street":"Barking Road",
    "iso:country":"GB",
    "sg:address":"348 Barking Road",
    "sg:city":"London",
    "sg:classifiers":[
        {
            "category":"Personal",
            "type":"Services"
        }
    ],
    "sg:phone":"+44 20 7476 5956",
    "sg:postcode":"E13 8HL",
    "sg:province":"Greater London",
    "sg:tags":[
        "tailor"
    ],
    "wof:name":"Luke's Bespoke Tailors",
    "wof:placetype":"venue"
},
  "geometry": {"coordinates":[0.021133,51.5214881897],"type":"Point"}
}