{
  "type": "Feature",
  "properties": {
    "iso:country":"GB",
    "sg:address":"3 Birmingham Street",
    "sg:city":"Smethwick",
    "sg:classifiers":[
        {
            "category":"Shopping",
            "subcategory":"Pharmacy",
            "type":"Retail Goods"
        }
    ],
    "sg:phone":"+44 121 552 1047",
    "sg:postcode":"B69 4DT",
    "sg:province":"West Midlands",
    "sg:tags":[
        "pharmacist",
        "chemist"
    ],
    "wof:name":"C H White (Chemists) Ltd.",
    "wof:placetype":"venue"
},
  "geometry": {"coordinates":[-2.01568,52.503651],"type":"Point"}
}