{
  "type": "Feature",
  "properties": {
    "iso:country":"GB",
    "sg:address":"1 Bridge St, Lockwood",
    "sg:city":"Huddersfield",
    "sg:classifiers":[
        {
            "category":"Personal",
            "subcategory":"Beauty Salon",
            "type":"Services"
        }
    ],
    "sg:postcode":"HD4 6EL",
    "sg:province":"West Yorkshire",
    "sg:tags":[
        "unisex",
        "lady",
        "hairdresser"
    ],
    "wof:name":"Bull,Ann,",
    "wof:placetype":"venue"
},
  "geometry": {"coordinates":[-1.794651,53.632317],"type":"Point"}
}