{
  "type": "Feature",
  "properties": {
    "addr:full":"Liverpool Rd Warrington Cheshire WA5 1AF",
    "addr:postcode":"wa5 1af",
    "addr:street":"Liverpool Rd",
    "iso:country":"GB",
    "sg:address":"Liverpool Rd",
    "sg:city":"Warrington",
    "sg:classifiers":[
        {
            "category":"Organizations",
            "subcategory":"Membership Organization",
            "type":"Services"
        }
    ],
    "sg:phone":"+44 1925 651607",
    "sg:postcode":"WA5 1AF",
    "sg:province":"Cheshire",
    "sg:tags":[
        "club"
    ],
    "wof:name":"Barlow,T & H,Ltd",
    "wof:placetype":"venue"
},
  "geometry": {"coordinates":[-2.6074640751,53.3887367249],"type":"Point"}
}