{
  "type": "Feature",
  "properties": {
    "addr:full":"13 Hilltop Llanelli Carmarthenshire SA14 8DF",
    "addr:housenumber":"13",
    "addr:postcode":"sa14 8df",
    "addr:street":"Hilltop Llanelli",
    "iso:country":"GB",
    "sg:address":"13 Hilltop",
    "sg:city":"Llanelli",
    "sg:classifiers":[
        {
            "category":"Retail",
            "subcategory":"Driving School",
            "type":"Services"
        }
    ],
    "sg:phone":"+44 1554 749777",
    "sg:postcode":"SA14 8DF",
    "sg:province":"Carmarthenshire",
    "wof:name":"Acorn School of Motoring",
    "wof:placetype":"venue"
},
  "geometry": {"coordinates":[-4.1381349564,51.7077674866],"type":"Point"}
}