{
  "type": "Feature",
  "properties": {
    "iso:country":"GB",
    "sg:address":"184 Ealing Road",
    "sg:city":"Wembley",
    "sg:classifiers":[
        {
            "category":"Food & Beverages",
            "subcategory":"Fruits & Vegetables",
            "type":"Retail Goods"
        }
    ],
    "sg:phone":"+44 20 8902 4820",
    "sg:postcode":"HA0 4QD",
    "sg:province":"Greater London",
    "sg:tags":[
        "greengrocer"
    ],
    "wof:name":"Fudco",
    "wof:placetype":"venue"
},
  "geometry": {"coordinates":[-0.297096014,51.5450668335],"type":"Point"}
}