{
  "type": "Feature",
  "properties": {
    "iso:country":"GB",
    "sg:address":"55 High Street, Pelsall",
    "sg:city":"Walsall",
    "sg:classifiers":[
        {
            "category":"Food & Beverages",
            "subcategory":"Bakery",
            "type":"Retail Goods"
        }
    ],
    "sg:phone":"+44 1922 684822",
    "sg:postcode":"WS3 4LU",
    "sg:province":"Staffordshire",
    "sg:tags":[
        "baker"
    ],
    "wof:name":"The Village Bakery",
    "wof:placetype":"venue"
},
  "geometry": {"coordinates":[-1.967409,52.629047],"type":"Point"}
}