{
  "type": "Feature",
  "properties": {
    "addr:full":"2nd Floor Crusader House, 145-157 St.john Street Clerkenwell Greater London EC1V 4PY",
    "addr:housenumber":"2nd floor crusader;145-157",
    "addr:postcode":"ec1v 4py",
    "addr:street":"St.John Street",
    "iso:country":"GB",
    "sg:address":"2nd Floor Crusader House, 145-157 St.john Street",
    "sg:city":"Clerkenwell",
    "sg:classifiers":[
        {
            "category":"Professional",
            "subcategory":"Engineering",
            "type":"Services"
        }
    ],
    "sg:postcode":"EC1V 4PY",
    "sg:province":"Greater London",
    "sg:tags":[
        "precision",
        "engineer"
    ],
    "wof:name":"Frisby Engineering Ltd",
    "wof:placetype":"venue"
},
  "geometry": {"coordinates":[-0.1026090011,51.5233688354],"type":"Point"}
}