{
  "type": "Feature",
  "properties": {
    "iso:country":"GB",
    "sg:address":"32 High Street, Portishead",
    "sg:city":"Bristol",
    "sg:classifiers":[
        {
            "category":"Travel",
            "subcategory":"Travel Agent",
            "type":"Entertainment"
        }
    ],
    "sg:phone":"+44 1275 845660",
    "sg:postcode":"BS20 6EN",
    "sg:province":"Somerset",
    "wof:name":"Travel House",
    "wof:placetype":"venue"
},
  "geometry": {"coordinates":[-2.768758,51.484646],"type":"Point"}
}