{
  "type": "Feature",
  "properties": {
    "iso:country":"GB",
    "sg:address":"20 Thornleigh Road, Horfield",
    "sg:city":"Bristol",
    "sg:classifiers":[
        {
            "category":"Real Estate",
            "subcategory":"Architect",
            "type":"Services"
        }
    ],
    "sg:phone":"+44 117 924 0591",
    "sg:postcode":"BS7 8PH",
    "sg:province":"City of Bristol",
    "wof:name":"Speedtest Limited",
    "wof:placetype":"venue"
},
  "geometry": {"coordinates":[-2.5890789032,51.4822349548],"type":"Point"}
}