{
  "type": "Feature",
  "properties": {
    "addr:full":", Kirkoswald Penrith Penrith Cumbria CA10 1DQ",
    "addr:postcode":"ca10 1dq",
    "iso:country":"GB",
    "sg:address":", Kirkoswald Penrith",
    "sg:city":"Penrith",
    "sg:classifiers":[
        {
            "category":"Bars & Pubs",
            "type":"Food & Drink"
        }
    ],
    "sg:phone":"+44 1768 898284",
    "sg:postcode":"CA10 1DQ",
    "sg:province":"Cumbria",
    "sg:tags":[
        "pubs",
        "inn"
    ],
    "wof:name":"Fetherston Arms Hotel",
    "wof:placetype":"venue"
},
  "geometry": {"coordinates":[-2.693748951,54.7646484375],"type":"Point"}
}