{
  "type": "Feature",
  "properties": {
    "addr:full":"792 Govan Road Glasgow Glasgow City G51 2YL",
    "addr:housenumber":"792",
    "addr:postcode":"g51 2yl",
    "addr:street":"Govan Road",
    "iso:country":"GB",
    "sg:address":"792 Govan Road",
    "sg:city":"Glasgow",
    "sg:classifiers":[
        {
            "category":"Travel",
            "subcategory":"Travel Agent",
            "type":"Entertainment"
        }
    ],
    "sg:postcode":"G51 2YL",
    "sg:province":"Glasgow City",
    "wof:name":"Worldchoice Telesales",
    "wof:placetype":"venue"
},
  "geometry": {"coordinates":[-4.3110208511,55.8630218506],"type":"Point"}
}