{
  "type": "Feature",
  "properties": {
    "addr:full":"27 Windsor St Stratford Upon Avon Warwickshire CV37 6NL",
    "addr:housenumber":"27",
    "addr:postcode":"cv37 6nl",
    "addr:street":"Windsor St",
    "iso:country":"GB",
    "sg:address":"27 Windsor St",
    "sg:city":"Stratford Upon Avon",
    "sg:classifiers":[
        {
            "category":"Shopping",
            "subcategory":"Bicycles & Sporting Goods",
            "type":"Retail Goods"
        }
    ],
    "sg:phone":"+44 1789 263900",
    "sg:postcode":"CV37 6NL",
    "sg:province":"Warwickshire",
    "sg:tags":[
        "dance",
        "balletwear"
    ],
    "wof:name":"Gamba",
    "wof:placetype":"venue"
},
  "geometry": {"coordinates":[-1.7092590332,52.1944503784],"type":"Point"}
}