{
  "type": "Feature",
  "properties": {
    "addr:full":"28 Eastcott Hill Swindon Wiltshire SN1 3JG",
    "addr:housenumber":"28",
    "addr:postcode":"sn1 3jg",
    "addr:street":"Eastcott Hill",
    "iso:country":"GB",
    "sg:address":"28 Eastcott Hill",
    "sg:city":"Swindon",
    "sg:classifiers":[
        {
            "category":"Bars & Pubs",
            "type":"Food & Drink"
        }
    ],
    "sg:phone":"+44 1793 536535",
    "sg:postcode":"SN1 3JG",
    "sg:province":"Wiltshire",
    "sg:tags":[
        "pubs",
        "inn"
    ],
    "wof:name":"Oak Tree Inns Ltd.",
    "wof:placetype":"venue"
},
  "geometry": {"coordinates":[-1.7823410034,51.5548286438],"type":"Point"}
}