{
  "type": "Feature",
  "properties": {
    "addr:full":"33 The Business Centre, Bow Bridge Close, Templeborough Enterprise Park Rotherham South Yorkshire S60 1BY",
    "addr:housenumber":"33",
    "addr:postcode":"s60 1by",
    "addr:street":"The;Bow Bridge Close;Enterprise Park",
    "iso:country":"GB",
    "sg:address":"33 The Business Centre, Bow Bridge Close, Templeborough Enterprise Park",
    "sg:city":"Rotherham",
    "sg:classifiers":[
        {
            "category":"Manufacturing",
            "subcategory":"Tools & Machinery",
            "type":"Manufacturing & Wholesale Goods"
        }
    ],
    "sg:postcode":"S60 1BY",
    "sg:province":"South Yorkshire",
    "sg:tags":[
        "machine",
        "cutting"
    ],
    "wof:name":"Perfor Tools Ltd.",
    "wof:placetype":"venue"
},
  "geometry": {"coordinates":[-1.354243,53.429874],"type":"Point"}
}