{
  "type": "Feature",
  "properties": {
    "addr:full":"17 St Albans Rd Blackburn Lancashire BB1 4HA",
    "addr:housenumber":"17",
    "addr:postcode":"bb1 4ha",
    "addr:street":"St Albans Rd",
    "iso:country":"GB",
    "sg:address":"17 St Albans Rd",
    "sg:city":"Blackburn",
    "sg:classifiers":[
        {
            "category":"Home & Garden",
            "subcategory":"Home Furnishings",
            "type":"Retail Goods"
        }
    ],
    "sg:phone":"+44 1254 882300",
    "sg:postcode":"BB1 4HA",
    "sg:province":"Lancashire",
    "sg:tags":[
        "tube",
        "fitting",
        "stockist"
    ],
    "wof:name":"Sandton Steel Tube Ltd",
    "wof:placetype":"venue"
},
  "geometry": {"coordinates":[-2.421856,53.765209],"type":"Point"}
}