{
  "type": "Feature",
  "properties": {
    "addr:full":"Diglake Farm, Southport Rd Ormskirk Lancashire L40 8HF",
    "addr:postcode":"l40 8hf",
    "addr:street":"Southport Rd",
    "iso:country":"GB",
    "sg:address":"Diglake Farm, Southport Rd",
    "sg:city":"Ormskirk",
    "sg:classifiers":[
        {
            "category":"Food & Beverages",
            "subcategory":"Farmers Market",
            "type":"Retail Goods"
        }
    ],
    "sg:phone":"+44 1704 840457",
    "sg:postcode":"L40 8HF",
    "sg:province":"Lancashire",
    "sg:tags":[
        "farm",
        "shop",
        "pyo"
    ],
    "wof:name":"Diglake Farm Shop",
    "wof:placetype":"venue"
},
  "geometry": {"coordinates":[-2.9159600735,53.5885696411],"type":"Point"}
}