{
  "type": "Feature",
  "properties": {
    "iso:country":"GB",
    "sg:address":"76a High Street",
    "sg:city":"Alton",
    "sg:classifiers":[
        {
            "category":"Shopping",
            "subcategory":"Clothing, Apparel, & Fashions",
            "type":"Retail Goods"
        }
    ],
    "sg:phone":"+44 1420 87587",
    "sg:postcode":"GU34 1EN",
    "sg:province":"Hampshire",
    "sg:tags":[
        "ladieswear"
    ],
    "wof:name":"M R Clothing",
    "wof:placetype":"venue"
},
  "geometry": {"coordinates":[-0.9773629904,51.1476898193],"type":"Point"}
}