{
  "type": "Feature",
  "properties": {
    "addr:full":"Provincial House, 7 Cambridge Road Harrogate North Yorkshire HG1 1PB",
    "addr:housenumber":"7",
    "addr:postcode":"hg1 1pb",
    "addr:street":"Cambridge Road",
    "iso:country":"GB",
    "sg:address":"Provincial House, 7 Cambridge Road",
    "sg:city":"Harrogate",
    "sg:classifiers":[
        {
            "category":"Insurance",
            "subcategory":"Insurance Agent",
            "type":"Services"
        }
    ],
    "sg:phone":"+44 1423 524221",
    "sg:postcode":"HG1 1PB",
    "sg:province":"North Yorkshire",
    "wof:name":"ECCLESIASTICAL INSURANCE GROUP PLC",
    "wof:placetype":"venue"
},
  "geometry": {"coordinates":[-1.541522,53.993519],"type":"Point"}
}