{
  "type": "Feature",
  "properties": {
    "iso:country":"GB",
    "sg:address":"Westfield House, Bratton Rd",
    "sg:city":"Westbury",
    "sg:classifiers":[
        {
            "category":"Personal",
            "type":"Services"
        }
    ],
    "sg:phone":"+44 1373 865821",
    "sg:postcode":"BA13 3EP",
    "sg:province":"Wiltshire",
    "sg:tags":[
        "stress",
        "management"
    ],
    "wof:name":"Haydn Thomas",
    "wof:placetype":"venue"
},
  "geometry": {"coordinates":[-2.1795079708,51.2602653503],"type":"Point"}
}