{
  "type": "Feature",
  "properties": {
    "addr:full":"Ddol Helyg Farm, Cwmyglo Caernarfon Gwynedd LL55 4DA",
    "addr:postcode":"ll55 4da",
    "addr:street":"Cwmyglo",
    "iso:country":"GB",
    "sg:address":"Ddol Helyg Farm, Cwmyglo",
    "sg:city":"Caernarfon",
    "sg:classifiers":[
        {
            "category":"Sports & Exercise",
            "subcategory":"Stables",
            "type":"Entertainment"
        }
    ],
    "sg:phone":"+44 1286 871931",
    "sg:postcode":"LL55 4DA",
    "sg:province":"Gwynedd",
    "sg:tags":[
        "education",
        "equestrian"
    ],
    "wof:name":"Rhosyn Gwyn Equestrian Centre",
    "wof:placetype":"venue"
},
  "geometry": {"coordinates":[-4.2718091011,53.1425933838],"type":"Point"}
}