{
  "type": "Feature",
  "properties": {
    "addr:full":"4a Prout Bridge Beaminster Dorset DT8 3AY",
    "addr:housenumber":"4a;beaminster",
    "addr:postcode":"dt8 3ay",
    "addr:street":"Prout Bridge",
    "iso:country":"GB",
    "sg:address":"4a Prout Bridge",
    "sg:city":"Beaminster",
    "sg:classifiers":[
        {
            "category":"Professional",
            "subcategory":"Engineering",
            "type":"Services"
        },
        {
            "category":"Building & Trades",
            "subcategory":"Electrical",
            "type":"Services"
        }
    ],
    "sg:phone":"+44 1308 862640",
    "sg:postcode":"DT8 3AY",
    "sg:province":"Dorset",
    "sg:tags":[
        "engineer",
        "electrician",
        "contractor"
    ],
    "wof:name":"M G Electrics",
    "wof:placetype":"venue"
},
  "geometry": {"coordinates":[-2.7377250195,50.8082008362],"type":"Point"}
}