{
  "type": "Feature",
  "properties": {
    "addr:full":"431 Blackburn Road Bolton Lancashire BL1 8NJ",
    "addr:housenumber":"431",
    "addr:postcode":"bl1 8nj",
    "addr:street":"Blackburn Road",
    "iso:country":"GB",
    "sg:address":"431 Blackburn Road",
    "sg:city":"Bolton",
    "sg:classifiers":[
        {
            "category":"Retail",
            "subcategory":"Driving School",
            "type":"Services"
        }
    ],
    "sg:phone":"+44 1204 593719",
    "sg:postcode":"BL1 8NJ",
    "sg:province":"Lancashire",
    "wof:name":"Driver Training U K",
    "wof:placetype":"venue"
},
  "geometry": {"coordinates":[-2.432868,53.59753],"type":"Point"}
}