{
  "type": "Feature",
  "properties": {
    "addr:full":"Lower Street A34 Newcastle Staffordshire ST5 2RH",
    "addr:housenumber":"a34",
    "addr:postcode":"st5 2rh",
    "addr:street":"Lower Street",
    "iso:country":"GB",
    "sg:address":"Lower Street A34",
    "sg:city":"Newcastle",
    "sg:classifiers":[
        {
            "category":"Autos & Motor Vehicles",
            "subcategory":"Motorcycle Sales",
            "type":"Retail Goods"
        }
    ],
    "sg:phone":"+44 1782 713100",
    "sg:postcode":"ST5 2RH",
    "sg:province":"Staffordshire",
    "sg:tags":[
        "chauffeur",
        "driven",
        "car"
    ],
    "wof:name":"Knightsbridge Of Newcastle",
    "wof:placetype":"venue"
},
  "geometry": {"coordinates":[-2.238139,53.007549],"type":"Point"}
}