{
  "type": "Feature",
  "properties": {
    "iso:country":"GB",
    "sg:address":"23 Normand Rd, Dysart",
    "sg:city":"Kirkcaldy",
    "sg:classifiers":[
        {
            "category":"Home & Garden",
            "subcategory":"Home Furnishings",
            "type":"Retail Goods"
        }
    ],
    "sg:phone":"+44 1592 591587",
    "sg:postcode":"KY1 2XN",
    "sg:province":"Fife",
    "sg:tags":[
        "homefurnishings"
    ],
    "wof:name":"Alastair Forbes Furniture",
    "wof:placetype":"venue"
},
  "geometry": {"coordinates":[-3.123,56.127907],"type":"Point"}
}