{
  "type": "Feature",
  "properties": {
    "iso:country":"GB",
    "sg:address":"Church Lane, Whittington",
    "sg:city":"King's Lynn",
    "sg:classifiers":[
        {
            "category":"Retail",
            "subcategory":"Repair Shop",
            "type":"Services"
        },
        {
            "category":"Manufacturing",
            "subcategory":"Retail Goods",
            "type":"Manufacturing & Wholesale Goods"
        }
    ],
    "sg:phone":"+44 1366 500737",
    "sg:postcode":"PE33 9TG",
    "sg:province":"Norfolk",
    "sg:tags":[
        "ship",
        "chandler"
    ],
    "wof:name":"Downham Components",
    "wof:placetype":"venue"
},
  "geometry": {"coordinates":[0.532130003,52.5647315979],"type":"Point"}
}