{
  "type": "Feature",
  "properties": {
    "addr:full":"7 Baker St Stirling Stirling FK8 1BJ",
    "addr:housenumber":"7",
    "addr:postcode":"fk8 1bj",
    "addr:street":"Baker St",
    "iso:country":"GB",
    "sg:address":"7 Baker St",
    "sg:city":"Stirling",
    "sg:classifiers":[
        {
            "category":"Cafe",
            "type":"Food & Drink"
        }
    ],
    "sg:phone":"+44 1786 450858",
    "sg:postcode":"FK8 1BJ",
    "sg:province":"Stirling",
    "sg:tags":[
        "tea",
        "room"
    ],
    "wof:name":"Drouthy Neebors",
    "wof:placetype":"venue"
},
  "geometry": {"coordinates":[-3.9390718937,56.1189117432],"type":"Point"}
}