{
  "type": "Feature",
  "properties": {
    "addr:full":"7 East Street Huntingdon Cambridgeshire PE29 1WZ",
    "addr:housenumber":"7",
    "addr:postcode":"pe29 1wz",
    "addr:street":"East Street",
    "iso:country":"GB",
    "sg:address":"7 East Street",
    "sg:city":"Huntingdon",
    "sg:classifiers":[
        {
            "category":"Shopping",
            "subcategory":"Books",
            "type":"Retail Goods"
        }
    ],
    "sg:phone":"+44 1480 353710",
    "sg:postcode":"PE29 1WZ",
    "sg:province":"Cambridgeshire",
    "wof:name":"Melvyn King",
    "wof:placetype":"venue"
},
  "geometry": {"coordinates":[-0.173003,52.332893],"type":"Point"}
}