{
  "type": "Feature",
  "properties": {
    "addr:full":"78 Gatwick Road Crawley Surrey RH10 9YB",
    "addr:housenumber":"78",
    "addr:postcode":"rh10 9yb",
    "addr:street":"Gatwick Road",
    "iso:country":"GB",
    "sg:address":"78 Gatwick Road",
    "sg:city":"Crawley",
    "sg:classifiers":[
        {
            "category":"Shopping",
            "subcategory":"Florist",
            "type":"Retail Goods"
        }
    ],
    "sg:phone":"+44 1293 562068",
    "sg:postcode":"RH10 9YB",
    "sg:province":"Surrey",
    "wof:name":"Throwers Ltd.",
    "wof:placetype":"venue"
},
  "geometry": {"coordinates":[-0.170084998,51.1278762817],"type":"Point"}
}