{
  "type": "Feature",
  "properties": {
    "iso:country":"GB",
    "sg:address":"100 Brook Street",
    "sg:city":"Chester",
    "sg:classifiers":[
        {
            "category":"Insurance",
            "subcategory":"Insurance Agent",
            "type":"Services"
        }
    ],
    "sg:phone":"+44 1244 345076",
    "sg:postcode":"CH1 3DU",
    "sg:province":"Cheshire",
    "sg:tags":[
        "broker"
    ],
    "wof:name":"V A Powell & Co.",
    "wof:placetype":"venue"
},
  "geometry": {"coordinates":[-2.884783,53.195972],"type":"Point"}
}