{
  "type": "Feature",
  "properties": {
    "addr:full":"Unit 7 St Clements Road, Chalwyn Industrial Estate Poole Dorset BH12 4PE",
    "addr:housenumber":"unit 7",
    "addr:postcode":"bh12 4pe",
    "addr:street":"St Clements Road Chalwyn Industrial Estate",
    "iso:country":"GB",
    "sg:address":"Unit 7 St Clements Road, Chalwyn Industrial Estate",
    "sg:city":"Poole",
    "sg:classifiers":[
        {
            "category":"Retail",
            "subcategory":"Auto Repair",
            "type":"Services"
        }
    ],
    "sg:phone":"+44 1202 747777",
    "sg:postcode":"BH12 4PE",
    "sg:province":"Dorset",
    "sg:tags":[
        "modification",
        "garage"
    ],
    "wof:name":"Mr Motors",
    "wof:placetype":"venue"
},
  "geometry": {"coordinates":[-1.9518300295,50.7366104126],"type":"Point"}
}