{
  "type": "Feature",
  "properties": {
    "addr:full":"102 Norwich Road, Wroxham Norwich Norfolk NR12 8RY",
    "addr:housenumber":"102",
    "addr:postcode":"nr12 8ry",
    "addr:street":"Norwich Road;Norwich",
    "iso:country":"GB",
    "sg:address":"102 Norwich Road, Wroxham",
    "sg:city":"Norwich",
    "sg:classifiers":[
        {
            "category":"Retail",
            "subcategory":"Funeral Services",
            "type":"Services"
        }
    ],
    "sg:phone":"+44 1603 737729",
    "sg:postcode":"NR12 8RY",
    "sg:province":"Norfolk",
    "wof:name":"Norgate Funeral Services",
    "wof:placetype":"venue"
},
  "geometry": {"coordinates":[1.402012,52.70739],"type":"Point"}
}