{
  "type": "Feature",
  "properties": {
    "iso:country":"GB",
    "sg:address":"82 South Rd, Sully",
    "sg:city":"Penarth",
    "sg:classifiers":[
        {
            "category":"Real Estate",
            "subcategory":"Real Estate Agent",
            "type":"Services"
        }
    ],
    "sg:postcode":"CF64 5SL",
    "sg:province":"The Vale of Glamorgan",
    "wof:name":"Woodfield,S,",
    "wof:placetype":"venue"
},
  "geometry": {"coordinates":[-3.213938,51.405342],"type":"Point"}
}