{
  "type": "Feature",
  "properties": {
    "iso:country":"GB",
    "sg:address":"16 Morris Road",
    "sg:city":"Leicester",
    "sg:classifiers":[
        {
            "category":"Manufacturing",
            "subcategory":"Textiles",
            "type":"Manufacturing & Wholesale Goods"
        }
    ],
    "sg:phone":"+44 116 270 6288",
    "sg:postcode":"LE2 6BR",
    "sg:province":"Leicestershire",
    "sg:tags":[
        "designer"
    ],
    "wof:name":"Cookson Hair Ltd.",
    "wof:placetype":"venue"
},
  "geometry": {"coordinates":[-1.129342,52.613873],"type":"Point"}
}