{
  "type": "Feature",
  "properties": {
    "iso:country":"GB",
    "sg:address":"1 Quayhead Street, Millport",
    "sg:city":"Millport",
    "sg:classifiers":[
        {
            "category":"Travel",
            "subcategory":"Hotels & Motels",
            "type":"Entertainment"
        }
    ],
    "sg:phone":"+44 1475 530301",
    "sg:postcode":"KA28 0AP",
    "sg:province":"North Ayrshire",
    "wof:name":"The Royal George Hotel",
    "wof:placetype":"venue"
},
  "geometry": {"coordinates":[-4.9326171875,55.7510414124],"type":"Point"}
}