{
  "type": "Feature",
  "properties": {
    "iso:country":"GB",
    "sg:address":"142 Tiverton Rd",
    "sg:city":"Basingstoke",
    "sg:classifiers":[
        {
            "category":"Professional",
            "subcategory":"Engineering",
            "type":"Services"
        }
    ],
    "sg:phone":"+44 1256 323012",
    "sg:postcode":"RG23 8EH",
    "sg:province":"Hampshire",
    "sg:tags":[
        "contractor",
        "electrical",
        "engineer"
    ],
    "wof:name":"B & J Electrical Engineering Contractors",
    "wof:placetype":"venue"
},
  "geometry": {"coordinates":[-1.1243779659,51.2661781311],"type":"Point"}
}