{
  "type": "Feature",
  "properties": {
    "iso:country":"GB",
    "sg:address":"Russell Street",
    "sg:city":"Darlington",
    "sg:classifiers":[
        {
            "category":"Home & Garden",
            "subcategory":"Carpets & Floor Coverings",
            "type":"Retail Goods"
        }
    ],
    "sg:phone":"+44 1325 467778",
    "sg:postcode":"DL1 1PT",
    "sg:province":"Durham",
    "sg:tags":[
        "carpets",
        "rug",
        "matting"
    ],
    "wof:name":"Allied Carpet Stores",
    "wof:placetype":"venue"
},
  "geometry": {"coordinates":[-1.548444,54.527817],"type":"Point"}
}