{
  "type": "Feature",
  "properties": {
    "addr:full":"21 Chalybeate Street Aberystwyth Ceredigion SY23 1HS",
    "addr:housenumber":"21",
    "addr:postcode":"sy23 1hs",
    "addr:street":"Chalybeate Street",
    "iso:country":"GB",
    "sg:address":"21 Chalybeate Street",
    "sg:city":"Aberystwyth",
    "sg:classifiers":[
        {
            "category":"Restaurant",
            "type":"Food & Drink"
        }
    ],
    "sg:phone":"+44 1970 611024",
    "sg:postcode":"SY23 1HS",
    "sg:province":"Ceredigion",
    "wof:name":"Corners",
    "wof:placetype":"venue"
},
  "geometry": {"coordinates":[-4.0836420059,52.4143676758],"type":"Point"}
}