{
  "type": "Feature",
  "properties": {
    "addr:full":"23 Lincoln Park Amersham Buckinghamshire HP7 9EZ",
    "addr:housenumber":"23",
    "addr:postcode":"hp7 9ez",
    "addr:street":"Lincoln Park",
    "iso:country":"GB",
    "sg:address":"23 Lincoln Park",
    "sg:city":"Amersham",
    "sg:classifiers":[
        {
            "category":"Professional",
            "subcategory":"Management & Consulting",
            "type":"Services"
        }
    ],
    "sg:phone":"+44 1494 583833",
    "sg:postcode":"HP7 9EZ",
    "sg:province":"Buckinghamshire",
    "sg:tags":[
        "consultant",
        "training"
    ],
    "wof:name":"The Sales Training Co. Ltd.",
    "wof:placetype":"venue"
},
  "geometry": {"coordinates":[-0.592486,51.67091],"type":"Point"}
}