{
  "type": "Feature",
  "properties": {
    "iso:country":"GB",
    "sg:address":"15 Freshfield Street",
    "sg:city":"Brighton",
    "sg:classifiers":[
        {
            "category":"Professional",
            "subcategory":"Management & Consulting",
            "type":"Services"
        }
    ],
    "sg:postcode":"BN2 9ZG",
    "sg:province":"East Sussex",
    "sg:tags":[
        "consultant",
        "business"
    ],
    "wof:name":"Equinox Consultants Ltd.",
    "wof:placetype":"venue"
},
  "geometry": {"coordinates":[-0.121586,50.828159],"type":"Point"}
}