{
  "type": "Feature",
  "properties": {
    "iso:country":"GB",
    "sg:address":"Haye La",
    "sg:city":"Colchester",
    "sg:classifiers":[
        {
            "category":"Building & Trades",
            "subcategory":"Construction",
            "type":"Services"
        }
    ],
    "sg:phone":"+44 1206 735287",
    "sg:postcode":"CO5 7AE",
    "sg:province":"Essex",
    "sg:tags":[
        "joinery"
    ],
    "wof:name":"R E Hall (Builders) Ltd",
    "wof:placetype":"venue"
},
  "geometry": {"coordinates":[0.923954,51.839439],"type":"Point"}
}