{
  "type": "Feature",
  "properties": {
    "addr:full":"The Kitchens, Heightington Bewdley Shropshire DY12 2YB",
    "addr:postcode":"dy12 2yb",
    "addr:street":"Heightington",
    "iso:country":"GB",
    "sg:address":"The Kitchens, Heightington",
    "sg:city":"Bewdley",
    "sg:classifiers":[
        {
            "category":"Building & Trades",
            "subcategory":"Plumbing",
            "type":"Services"
        }
    ],
    "sg:phone":"+44 1222 223223",
    "sg:postcode":"DY12 2YB",
    "sg:province":"Shropshire",
    "sg:tags":[
        "heating"
    ],
    "wof:name":"R A Farley",
    "wof:placetype":"venue"
},
  "geometry": {"coordinates":[-2.3147790432,52.3760185242],"type":"Point"}
}