{
  "type": "Feature",
  "properties": {
    "iso:country":"GB",
    "sg:address":"2 Greedon Rise",
    "sg:city":"Loughborough",
    "sg:classifiers":[
        {
            "category":"Shopping",
            "subcategory":"Department Store",
            "type":"Retail Goods"
        }
    ],
    "sg:phone":"+44 1509 813993",
    "sg:postcode":"LE12 7TF",
    "sg:province":"Leicestershire",
    "wof:name":"Sileby Superstore",
    "wof:placetype":"venue"
},
  "geometry": {"coordinates":[-1.105842,52.735638],"type":"Point"}
}