{
  "type": "Feature",
  "properties": {
    "addr:full":"15 High St, Lewknor Watlington Buckinghamshire OX9 5TH",
    "addr:housenumber":"15",
    "addr:postcode":"ox9 5th",
    "addr:street":"High St",
    "iso:country":"GB",
    "sg:address":"15 High St, Lewknor",
    "sg:city":"Watlington",
    "sg:classifiers":[
        {
            "category":"Utilities",
            "type":"Services"
        }
    ],
    "sg:phone":"+44 1844 352053",
    "sg:postcode":"OX9 5TH",
    "sg:province":"Buckinghamshire",
    "sg:tags":[
        "internet"
    ],
    "wof:name":"Bear & Squirrell",
    "wof:placetype":"venue"
},
  "geometry": {"coordinates":[-1.005679965,51.6440811157],"type":"Point"}
}