{
  "type": "Feature",
  "properties": {
    "addr:full":"1 Bridge Street, Park Village Wolverhampton Staffordshire WV10 9DX",
    "addr:housenumber":"1",
    "addr:postcode":"wv10 9dx",
    "addr:street":"Bridge Street",
    "iso:country":"GB",
    "sg:address":"1 Bridge Street, Park Village",
    "sg:city":"Wolverhampton",
    "sg:classifiers":[
        {
            "category":"Manufacturing",
            "subcategory":"Building Materials",
            "type":"Manufacturing & Wholesale Goods"
        }
    ],
    "sg:phone":"+44 1902 736000",
    "sg:postcode":"WV10 9DX",
    "sg:province":"Staffordshire",
    "sg:tags":[
        "merchant",
        "builder"
    ],
    "wof:name":"J Thomas Edwards & Sons Plc",
    "wof:placetype":"venue"
},
  "geometry": {"coordinates":[-2.1117839813,52.5999145508],"type":"Point"}
}