{
  "type": "Feature",
  "properties": {
    "iso:country":"GB",
    "sg:address":"3rd Floor Aidan House, Sunderland Road",
    "sg:city":"Gateshead",
    "sg:classifiers":[
        {
            "category":"Transit Center",
            "subcategory":"Passenger",
            "type":"Transportation"
        },
        {
            "category":"Conference Center",
            "type":"Public Place"
        }
    ],
    "sg:phone":"+44 191 478 8300",
    "sg:postcode":"NE8 3HU",
    "sg:province":"Tyne and Wear",
    "sg:tags":[
        "commerce",
        "business",
        "centre"
    ],
    "wof:name":"Tynegate Serviced Business Centre",
    "wof:placetype":"venue"
},
  "geometry": {"coordinates":[-1.59792,54.9589],"type":"Point"}
}