{
  "type": "Feature",
  "properties": {
    "addr:full":"9 Shorewell Ingleside, Netley Abbey Southampton Hampshire SO31 5GE",
    "addr:housenumber":"9",
    "addr:postcode":"so31 5ge",
    "addr:street":"Shorewell Ingleside Netley Abbey",
    "iso:country":"GB",
    "sg:address":"9 Shorewell Ingleside, Netley Abbey",
    "sg:city":"Southampton",
    "sg:classifiers":[
        {
            "category":"Home & Garden",
            "subcategory":"Building Materials",
            "type":"Retail Goods"
        }
    ],
    "sg:phone":"+44 1489 893850",
    "sg:postcode":"SO31 5GE",
    "sg:province":"Hampshire",
    "sg:tags":[
        "fencing"
    ],
    "wof:name":"Bound Fencing",
    "wof:placetype":"venue"
},
  "geometry": {"coordinates":[-1.345804,50.881657],"type":"Point"}
}