{
  "type": "Feature",
  "properties": {
    "addr:full":"Four Pool Estate Evesham Gloucestershire WR11 2UT",
    "addr:postcode":"wr11 2ut",
    "addr:street":"Evesham",
    "iso:country":"GB",
    "sg:address":"Four Pool Estate",
    "sg:city":"Evesham",
    "sg:classifiers":[
        {
            "category":"Food & Beverages",
            "subcategory":"Supermarket",
            "type":"Retail Goods"
        }
    ],
    "sg:phone":"+44 1386 49351",
    "sg:postcode":"WR11 2UT",
    "sg:province":"Gloucestershire",
    "wof:name":"Safeway Stores Ltd.",
    "wof:placetype":"venue"
},
  "geometry": {"coordinates":[-1.939021,52.083351],"type":"Point"}
}