{
  "type": "Feature",
  "properties": {
    "iso:country":"GB",
    "sg:address":"91 Agbrigg Rd",
    "sg:city":"Wakefield",
    "sg:classifiers":[
        {
            "category":"Farming",
            "subcategory":"Dairy Farm",
            "type":"Manufacturing & Wholesale Goods"
        }
    ],
    "sg:phone":"+44 1924 255396",
    "sg:postcode":"WF1 5AB",
    "sg:province":"West Yorkshire",
    "wof:name":"Sandal Model Dairies",
    "wof:placetype":"venue"
},
  "geometry": {"coordinates":[-1.480954051,53.6653442383],"type":"Point"}
}