{
  "type": "Feature",
  "properties": {
    "addr:full":"Pantyrofn, Brynafan, Llanafan Aberystwyth Ceredigion SY23 4BG",
    "addr:postcode":"sy23 4bg",
    "iso:country":"GB",
    "sg:address":"Pantyrofn, Brynafan, Llanafan",
    "sg:city":"Aberystwyth",
    "sg:classifiers":[
        {
            "category":"Farming",
            "subcategory":"Livestock Farm",
            "type":"Manufacturing & Wholesale Goods"
        },
        {
            "category":"Farming",
            "subcategory":"Farm",
            "type":"Manufacturing & Wholesale Goods"
        }
    ],
    "sg:phone":"+44 1974 282287",
    "sg:postcode":"SY23 4BG",
    "sg:province":"Ceredigion",
    "sg:tags":[
        "mixed",
        "others"
    ],
    "wof:name":"M E Davies",
    "wof:placetype":"venue"
},
  "geometry": {"coordinates":[-3.9302589893,52.3292770386],"type":"Point"}
}