{
  "type": "Feature",
  "properties": {
    "iso:country":"GB",
    "sg:address":"Stainland Rd",
    "sg:city":"Halifax",
    "sg:classifiers":[
        {
            "category":"Place Of Worship",
            "type":"Public Place"
        }
    ],
    "sg:phone":"+44 1422 374767",
    "sg:postcode":"HX4 9EH",
    "sg:province":"West Yorkshire",
    "wof:name":"St Andrew C Of E Church",
    "wof:placetype":"venue"
},
  "geometry": {"coordinates":[-1.8835890293,53.671295166],"type":"Point"}
}