{
  "type": "Feature",
  "properties": {
    "addr:full":"70 Market Street, Shipdham Thetford Norfolk IP25 7LZ",
    "addr:housenumber":"70",
    "addr:postcode":"ip25 7lz",
    "addr:street":"Market Street",
    "iso:country":"GB",
    "sg:address":"70 Market Street, Shipdham",
    "sg:city":"Thetford",
    "sg:classifiers":[
        {
            "category":"Real Estate",
            "subcategory":"Surveying",
            "type":"Services"
        },
        {
            "category":"Real Estate",
            "subcategory":"Architect",
            "type":"Services"
        }
    ],
    "sg:phone":"+44 1362 821308",
    "sg:postcode":"IP25 7LZ",
    "sg:province":"Norfolk",
    "sg:tags":[
        "building",
        "surveyor"
    ],
    "wof:name":"DAVID A. CUTTING BUILDING SURVEYORS LTD",
    "wof:placetype":"venue"
},
  "geometry": {"coordinates":[0.9020540118,52.6312408447],"type":"Point"}
}