{
  "type": "Feature",
  "properties": {
    "iso:country":"GB",
    "sg:address":"32 The Ridings",
    "sg:city":"Eastleigh",
    "sg:classifiers":[
        {
            "category":"Military Area",
            "subcategory":"Air Force Base",
            "type":"Public Place"
        }
    ],
    "sg:postcode":"SO50 8PR",
    "sg:province":"Hampshire",
    "sg:tags":[
        "taxi",
        "hire",
        "private"
    ],
    "wof:name":"Knights Taxis",
    "wof:placetype":"venue"
},
  "geometry": {"coordinates":[-1.3119920492,50.967376709],"type":"Point"}
}