{
  "type": "Feature",
  "properties": {
    "iso:country":"GB",
    "sg:address":"Unit 5 & 6 Titford Lane, J A S Industrial Estate",
    "sg:city":"Rowley Regis",
    "sg:classifiers":[
        {
            "category":"Professional",
            "type":"Services"
        }
    ],
    "sg:phone":"+44 121 559 7766",
    "sg:postcode":"B65 0PY",
    "sg:province":"West Midlands",
    "sg:tags":[
        "pattern",
        "industrial",
        "maker"
    ],
    "wof:name":"T T Patterns",
    "wof:placetype":"venue"
},
  "geometry": {"coordinates":[-2.026647,52.487225],"type":"Point"}
}