{
  "type": "Feature",
  "properties": {
    "iso:country":"GB",
    "sg:address":"48 Fore Street",
    "sg:city":"Totnes",
    "sg:classifiers":[
        {
            "category":"Food & Beverages",
            "subcategory":"Meat & Fish",
            "type":"Retail Goods"
        }
    ],
    "sg:phone":"+44 1803 862119",
    "sg:postcode":"TQ9 5RP",
    "sg:province":"Devon",
    "sg:tags":[
        "butcher"
    ],
    "wof:name":"A W Luscombe's",
    "wof:placetype":"venue"
},
  "geometry": {"coordinates":[-3.68521,50.431004],"type":"Point"}
}