{
  "type": "Feature",
  "properties": {
    "addr:full":"4 Shepherds Bush Road London Greater London W6 7PJ",
    "addr:housenumber":"4",
    "addr:postcode":"w6 7pj",
    "addr:street":"Shepherds Bush Road",
    "iso:country":"GB",
    "sg:address":"4 Shepherds Bush Road",
    "sg:city":"London",
    "sg:classifiers":[
        {
            "category":"Professional",
            "subcategory":"Employment Agencies",
            "type":"Services"
        }
    ],
    "sg:phone":"+44 20 8743 8843",
    "sg:postcode":"W6 7PJ",
    "sg:province":"Greater London",
    "sg:tags":[
        "consultant"
    ],
    "wof:name":"C L S Services",
    "wof:placetype":"venue"
},
  "geometry": {"coordinates":[-0.2230059952,51.5025978088],"type":"Point"}
}