{
  "type": "Feature",
  "properties": {
    "addr:full":"336 Wargrave Road Newton-le-willows Cheshire WA12 8EP",
    "addr:housenumber":"336",
    "addr:postcode":"wa12 8ep",
    "addr:street":"Wargrave Road",
    "iso:country":"GB",
    "sg:address":"336 Wargrave Road",
    "sg:city":"Newton-le-willows",
    "sg:classifiers":[
        {
            "category":"Home & Garden",
            "subcategory":"Hardware",
            "type":"Retail Goods"
        }
    ],
    "sg:postcode":"WA12 8EP",
    "sg:province":"Cheshire",
    "sg:tags":[
        "retailer",
        "diy"
    ],
    "wof:name":"Wargrave Diy",
    "wof:placetype":"venue"
},
  "geometry": {"coordinates":[-2.6296830177,53.4470787048],"type":"Point"}
}