{
  "type": "Feature",
  "properties": {
    "iso:country":"GB",
    "sg:address":"Manor Farm, Court-at-street",
    "sg:city":"Hythe",
    "sg:classifiers":[
        {
            "category":"Farming",
            "subcategory":"Livestock Farm",
            "type":"Manufacturing & Wholesale Goods"
        }
    ],
    "sg:phone":"+44 1233 720256",
    "sg:postcode":"CT21 4PH",
    "sg:province":"Kent",
    "sg:tags":[
        "others"
    ],
    "wof:name":"John A Duthoit & Son",
    "wof:placetype":"venue"
},
  "geometry": {"coordinates":[1.0317829847,51.0694618225],"type":"Point"}
}