{
  "type": "Feature",
  "properties": {
    "addr:full":"19 Foundry Street Dewsbury West Yorkshire WF13 1QW",
    "addr:housenumber":"19",
    "addr:postcode":"wf13 1qw",
    "addr:street":"Foundry Street",
    "iso:country":"GB",
    "sg:address":"19 Foundry Street",
    "sg:city":"Dewsbury",
    "sg:classifiers":[
        {
            "category":"Personal",
            "subcategory":"Beauty Salon",
            "type":"Services"
        },
        {
            "category":"Personal",
            "subcategory":"Barber",
            "type":"Services"
        }
    ],
    "sg:phone":"+44 1924 462438",
    "sg:postcode":"WF13 1QW",
    "sg:province":"West Yorkshire",
    "sg:tags":[
        "unisex",
        "hairdresser"
    ],
    "wof:name":"Shapes",
    "wof:placetype":"venue"
},
  "geometry": {"coordinates":[-1.6290229559,53.6929588318],"type":"Point"}
}