{
  "type": "Feature",
  "properties": {
    "addr:full":"78 Westminster Way, Botley Oxford Oxfordshire OX2 0LW",
    "addr:housenumber":"78",
    "addr:postcode":"ox2 0lw",
    "addr:street":"Westminster Way",
    "iso:country":"GB",
    "sg:address":"78 Westminster Way, Botley",
    "sg:city":"Oxford",
    "sg:classifiers":[
        {
            "category":"Building & Trades",
            "subcategory":"Construction",
            "type":"Services"
        }
    ],
    "sg:postcode":"OX2 0LW",
    "sg:province":"Oxfordshire",
    "sg:tags":[
        "builder"
    ],
    "wof:name":"Montagu Builders",
    "wof:placetype":"venue"
},
  "geometry": {"coordinates":[-1.294153,51.749065],"type":"Point"}
}