{
  "type": "Feature",
  "properties": {
    "iso:country":"GB",
    "sg:address":"Unit 40 Van Alloys Indust Est, Busgrove La",
    "sg:city":"Henley On Thames",
    "sg:classifiers":[
        {
            "category":"Retail",
            "subcategory":"Auto Repair",
            "type":"Services"
        }
    ],
    "sg:phone":"+44 1491 682007",
    "sg:postcode":"RG9 5QW",
    "sg:province":"Berkshire",
    "sg:tags":[
        "body",
        "car"
    ],
    "wof:name":"S & B",
    "wof:placetype":"venue"
},
  "geometry": {"coordinates":[-0.903189,51.535297],"type":"Point"}
}