{
  "type": "Feature",
  "properties": {
    "iso:country":"GB",
    "sg:address":"Unit 10 Enterprise Trading Estate, Pedmore Road",
    "sg:city":"Brierley Hill",
    "sg:classifiers":[
        {
            "category":"Manufacturing",
            "subcategory":"Signs",
            "type":"Manufacturing & Wholesale Goods"
        }
    ],
    "sg:phone":"+44 1384 484631",
    "sg:postcode":"DY5 1TX",
    "sg:province":"West Midlands",
    "sg:tags":[
        "nameplate"
    ],
    "wof:name":"Beta Signs",
    "wof:placetype":"venue"
},
  "geometry": {"coordinates":[-2.105249,52.484463],"type":"Point"}
}