{
  "type": "Feature",
  "properties": {
    "iso:country":"GB",
    "sg:address":"365 Limpsfield Road",
    "sg:city":"Warlingham",
    "sg:classifiers":[
        {
            "category":"Building & Trades",
            "subcategory":"Landscaping Services",
            "type":"Services"
        }
    ],
    "sg:phone":"+44 1883 626824",
    "sg:postcode":"CR6 9HA",
    "sg:province":"Kent",
    "sg:tags":[
        "contractor",
        "drainage"
    ],
    "wof:name":"Scanseal Techniques",
    "wof:placetype":"venue"
},
  "geometry": {"coordinates":[-0.056492,51.310112],"type":"Point"}
}