{
  "type": "Feature",
  "properties": {
    "iso:country":"GB",
    "sg:address":"7 Winslow Drive",
    "sg:city":"Wigston",
    "sg:classifiers":[
        {
            "category":"Education",
            "subcategory":"Music School",
            "type":"Public Place"
        },
        {
            "category":"Shopping",
            "subcategory":"Pharmacy",
            "type":"Retail Goods"
        }
    ],
    "sg:postcode":"LE18 3QG",
    "sg:province":"Leicestershire",
    "sg:tags":[
        "medicine",
        "therapy",
        "teacher"
    ],
    "wof:name":"David Rose",
    "wof:placetype":"venue"
},
  "geometry": {"coordinates":[-1.09847,52.591743],"type":"Point"}
}