{
  "type": "Feature",
  "properties": {
    "iso:country":"GB",
    "sg:address":"Haig House, 48 Pall Mall",
    "sg:city":"London",
    "sg:classifiers":[
        {
            "category":"Organizations",
            "subcategory":"Non-profit Organization",
            "type":"Services"
        }
    ],
    "sg:phone":"+44 20 7973 7200",
    "sg:postcode":"SW1Y 5JY",
    "sg:province":"Greater London",
    "sg:tags":[
        "organisation",
        "voluntary",
        "charity"
    ],
    "wof:name":"The Royal British Legion",
    "wof:placetype":"venue"
},
  "geometry": {"coordinates":[-0.136442,51.50592],"type":"Point"}
}