{
  "type": "Feature",
  "properties": {
    "iso:country":"GB",
    "sg:address":"66 Briar Drive",
    "sg:city":"Buckley",
    "sg:classifiers":[
        {
            "category":"Shopping",
            "subcategory":"Computers & Home Electronics",
            "type":"Retail Goods"
        }
    ],
    "sg:phone":"+44 1244 543978",
    "sg:postcode":"CH7 2AS",
    "sg:province":"Denbighshire",
    "sg:tags":[
        "aerial",
        "television",
        "radio"
    ],
    "wof:name":"Flintshire Aerials",
    "wof:placetype":"venue"
},
  "geometry": {"coordinates":[-3.0740818977,53.1640777588],"type":"Point"}
}