{
  "type": "Feature",
  "properties": {
    "iso:country":"GB",
    "sg:address":"Friary House, Beaumont Road",
    "sg:city":"Plymouth",
    "sg:classifiers":[
        {
            "category":"Health Services",
            "subcategory":"Doctor",
            "type":"Services"
        }
    ],
    "sg:phone":"+44 1752 663138",
    "sg:postcode":"PL4 9BH",
    "sg:province":"Devon",
    "sg:tags":[
        "practitioners"
    ],
    "wof:name":"Friary House Surgery",
    "wof:placetype":"venue"
},
  "geometry": {"coordinates":[-4.111834,50.377571],"type":"Point"}
}