{
  "type": "Feature",
  "properties": {
    "iso:country":"GB",
    "sg:address":"Stone Croft, Church Lane",
    "sg:city":"Bristol",
    "sg:classifiers":[
        {
            "category":"Banks & Credit Unions",
            "subcategory":"Financial Services",
            "type":"Services"
        }
    ],
    "sg:phone":"+44 1275 542233",
    "sg:postcode":"BS39 6TY",
    "sg:province":"Somerset",
    "sg:tags":[
        "consultant"
    ],
    "wof:name":"James & Co. Home Buyer Services",
    "wof:placetype":"venue"
},
  "geometry": {"coordinates":[-2.5305700302,51.2984809875],"type":"Point"}
}