{
  "type": "Feature",
  "properties": {
    "addr:full":"23 Stanley Road Herne Bay Kent CT6 5SJ",
    "addr:housenumber":"23",
    "addr:postcode":"ct6 5sj",
    "addr:street":"Stanley Road",
    "iso:country":"GB",
    "sg:address":"23 Stanley Road",
    "sg:city":"Herne Bay",
    "sg:classifiers":[
        {
            "category":"Building & Trades",
            "subcategory":"Construction",
            "type":"Services"
        }
    ],
    "sg:phone":"+44 1227 363332",
    "sg:postcode":"CT6 5SJ",
    "sg:province":"Kent",
    "sg:tags":[
        "builder"
    ],
    "wof:name":"Perma Build",
    "wof:placetype":"venue"
},
  "geometry": {"coordinates":[1.128801,51.36713],"type":"Point"}
}