{
  "type": "Feature",
  "properties": {
    "addr:full":"4 Bath Street Lytham St Annes Lancashire FY8 5ES",
    "addr:housenumber":"4",
    "addr:postcode":"fy8 5es",
    "addr:street":"Bath Street",
    "iso:country":"GB",
    "sg:address":"4 Bath Street",
    "sg:city":"Lytham St Annes",
    "sg:classifiers":[
        {
            "category":"Fast Food",
            "type":"Food & Drink"
        }
    ],
    "sg:phone":"+44 1253 738390",
    "sg:postcode":"FY8 5ES",
    "sg:province":"Lancashire",
    "sg:tags":[
        "away",
        "meal",
        "outlet",
        "take"
    ],
    "wof:name":"THE SANDWICH SHOP",
    "wof:placetype":"venue"
},
  "geometry": {"coordinates":[-2.9602301121,53.7363166809],"type":"Point"}
}