{
  "type": "Feature",
  "properties": {
    "addr:full":"The Dower House, Dower Mews, 108 High Street Berkhamsted Bedfordshire HP4 2BL",
    "addr:housenumber":"108",
    "addr:postcode":"hp4 2bl",
    "addr:street":"Dower;High Street",
    "iso:country":"GB",
    "sg:address":"The Dower House, Dower Mews, 108 High Street",
    "sg:city":"Berkhamsted",
    "sg:classifiers":[
        {
            "category":"Professional",
            "subcategory":"Art Services",
            "type":"Services"
        }
    ],
    "sg:phone":"+44 1442 875431",
    "sg:postcode":"HP4 2BL",
    "sg:province":"Bedfordshire",
    "sg:tags":[
        "graphic",
        "designer"
    ],
    "wof:name":"Dennis Fairey & Associates Ltd.",
    "wof:placetype":"venue"
},
  "geometry": {"coordinates":[-0.5645589828,51.7604141235],"type":"Point"}
}