{
  "type": "Feature",
  "properties": {
    "addr:full":"45a Brighton Road Surbiton Surrey KT6 5LR",
    "addr:housenumber":"45a",
    "addr:postcode":"kt6 5lr",
    "addr:street":"Brighton Road",
    "iso:country":"GB",
    "sg:address":"45a Brighton Road",
    "sg:city":"Surbiton",
    "sg:classifiers":[
        {
            "category":"Professional",
            "subcategory":"Accounting & Tax Preparation",
            "type":"Services"
        }
    ],
    "sg:phone":"+44 20 8390 5858",
    "sg:postcode":"KT6 5LR",
    "sg:province":"Surrey",
    "sg:tags":[
        "accountant"
    ],
    "wof:name":"Coverley Gower",
    "wof:placetype":"venue"
},
  "geometry": {"coordinates":[-0.310422,51.391598],"type":"Point"}
}