{
  "type": "Feature",
  "properties": {
    "addr:full":"20-21 Widegate St London Greater London E1 7HP",
    "addr:housenumber":"20-21",
    "addr:postcode":"e1 7hp",
    "addr:street":"Widegate St",
    "iso:country":"GB",
    "sg:address":"20-21 Widegate St",
    "sg:city":"London",
    "sg:classifiers":[
        {
            "category":"Professional",
            "subcategory":"Management & Consulting",
            "type":"Services"
        }
    ],
    "sg:phone":"+44 171 377 5253",
    "sg:postcode":"E1 7HP",
    "sg:province":"Greater London",
    "sg:tags":[
        "consultant",
        "business"
    ],
    "wof:name":"Trs Consultants Plc",
    "wof:placetype":"venue"
},
  "geometry": {"coordinates":[-0.078224,51.518253],"type":"Point"}
}