{
  "type": "Feature",
  "properties": {
    "iso:country":"GB",
    "sg:address":"10 Camden Clo, Ainsworth",
    "sg:city":"Bolton",
    "sg:classifiers":[
        {
            "category":"Manufacturing",
            "subcategory":"Electronics",
            "type":"Manufacturing & Wholesale Goods"
        }
    ],
    "sg:postcode":"BL2 5RH",
    "sg:province":"Lancashire",
    "sg:tags":[
        "printed",
        "circuit"
    ],
    "wof:name":"Pennine Electronics Design & Draughting",
    "wof:placetype":"venue"
},
  "geometry": {"coordinates":[-2.356893,53.58857],"type":"Point"}
}