{
  "type": "Feature",
  "properties": {
    "iso:country":"GB",
    "sg:address":"Busby House, Stokesley",
    "sg:city":"Middlesbrough",
    "sg:classifiers":[
        {
            "category":"Farming",
            "subcategory":"Livestock Farm",
            "type":"Manufacturing & Wholesale Goods"
        },
        {
            "category":"Farming",
            "subcategory":"Farm",
            "type":"Manufacturing & Wholesale Goods"
        }
    ],
    "sg:phone":"+44 1642 710426",
    "sg:postcode":"TS9 5LB",
    "sg:province":"North Yorkshire",
    "sg:tags":[
        "mixed",
        "others"
    ],
    "wof:name":"Gloag & Sons Ltd",
    "wof:placetype":"venue"
},
  "geometry": {"coordinates":[-1.18879,54.470703],"type":"Point"}
}