{
  "type": "Feature",
  "properties": {
    "addr:full":"47 Baulk Lane, Harworth Doncaster South Yorkshire DN11 8PF",
    "addr:housenumber":"47",
    "addr:postcode":"dn11 8pf",
    "addr:street":"Baulk Lane",
    "iso:country":"GB",
    "sg:address":"47 Baulk Lane, Harworth",
    "sg:city":"Doncaster",
    "sg:classifiers":[
        {
            "category":"Building & Trades",
            "subcategory":"Construction",
            "type":"Services"
        }
    ],
    "sg:postcode":"DN11 8PF",
    "sg:province":"South Yorkshire",
    "sg:tags":[
        "platform",
        "work",
        "scaffolding"
    ],
    "wof:name":"Retford Scaffolding",
    "wof:placetype":"venue"
},
  "geometry": {"coordinates":[-1.0749959946,53.4221839905],"type":"Point"}
}