{
  "type": "Feature",
  "properties": {
    "addr:full":"Glynn Lodge, Glynn Bodmin Cornwall PL30 4AU",
    "addr:housenumber":"bodmin",
    "addr:postcode":"pl30 4au",
    "addr:street":"Glynn",
    "iso:country":"GB",
    "sg:address":"Glynn Lodge, Glynn",
    "sg:city":"Bodmin",
    "sg:classifiers":[
        {
            "category":"Professional",
            "subcategory":"Business Services",
            "type":"Services"
        },
        {
            "category":"Real Estate",
            "subcategory":"Architect",
            "type":"Services"
        }
    ],
    "sg:postcode":"PL30 4AU",
    "sg:province":"Cornwall",
    "wof:name":"HAMMOND ADMINISTRATIVE SERVICES",
    "wof:placetype":"venue"
},
  "geometry": {"coordinates":[-4.667827,50.452038],"type":"Point"}
}