{
  "type": "Feature",
  "properties": {
    "iso:country":"GB",
    "sg:address":"Luther King House, Brighton Gro",
    "sg:city":"Manchester",
    "sg:classifiers":[
        {
            "category":"Education",
            "subcategory":"Special Training",
            "type":"Public Place"
        }
    ],
    "sg:phone":"+44 161 224 2849",
    "sg:postcode":"M14 5JP",
    "sg:province":"Greater Manchester",
    "sg:tags":[
        "product",
        "centre"
    ],
    "wof:name":"Unitarian College Manchester",
    "wof:placetype":"venue"
},
  "geometry": {"coordinates":[-2.222544,53.452286],"type":"Point"}
}