{
  "type": "Feature",
  "properties": {
    "iso:country":"GB",
    "sg:address":"227 Ashley Road, Hale",
    "sg:city":"Altrincham",
    "sg:classifiers":[
        {
            "category":"Shopping",
            "subcategory":"Pets & Pet Supplies",
            "type":"Retail Goods"
        }
    ],
    "sg:phone":"+44 161 928 8085",
    "sg:postcode":"WA15 9SZ",
    "sg:province":"Cheshire",
    "wof:name":"Pets Pantry",
    "wof:placetype":"venue"
},
  "geometry": {"coordinates":[-2.343743,53.375996],"type":"Point"}
}