{
  "type": "Feature",
  "properties": {
    "addr:full":"Windlebrook House, Guildford Road Bagshot Berkshire GU19 5NG",
    "addr:postcode":"gu19 5ng",
    "addr:street":"Guildford Road",
    "iso:country":"GB",
    "sg:address":"Windlebrook House, Guildford Road",
    "sg:city":"Bagshot",
    "sg:classifiers":[
        {
            "category":"Professional",
            "subcategory":"Business Services",
            "type":"Services"
        }
    ],
    "sg:postcode":"GU19 5NG",
    "sg:province":"Berkshire",
    "sg:tags":[
        "holding"
    ],
    "wof:name":"M Y Holdings Plc",
    "wof:placetype":"venue"
},
  "geometry": {"coordinates":[-0.69092,51.361549],"type":"Point"}
}