{
  "type": "Feature",
  "properties": {
    "addr:full":"Units 20-21 Rumer Hill Business, Estate Cannock Staffordshire WS11 3ET",
    "addr:housenumber":"units 20-21",
    "addr:postcode":"ws11 3et",
    "addr:street":"Rumer Hill Business Estate",
    "iso:country":"GB",
    "sg:address":"Units 20-21 Rumer Hill Business, Estate",
    "sg:city":"Cannock",
    "sg:classifiers":[
        {
            "category":"Building & Trades",
            "subcategory":"Plumbing",
            "type":"Services"
        }
    ],
    "sg:phone":"+44 1543 573007",
    "sg:postcode":"WS11 3ET",
    "sg:province":"Staffordshire",
    "sg:tags":[
        "merchant",
        "plumbers'"
    ],
    "wof:name":"Instox Ltd.",
    "wof:placetype":"venue"
},
  "geometry": {"coordinates":[-2.033145,52.690952],"type":"Point"}
}