{
  "type": "Feature",
  "properties": {
    "iso:country":"GB",
    "sg:address":"21 Meergreen Road",
    "sg:city":"Sutton Coldfield",
    "sg:classifiers":[
        {
            "category":"Food & Beverages",
            "subcategory":"Liquor & Beverages",
            "type":"Retail Goods"
        }
    ],
    "sg:phone":"+44 121 355 4539",
    "sg:postcode":"B75 5BL",
    "sg:province":"Staffordshire",
    "sg:tags":[
        "beer",
        "spirit",
        "wines"
    ],
    "wof:name":"Majestic Wine Warehouses Ltd.",
    "wof:placetype":"venue"
},
  "geometry": {"coordinates":[-1.82870996,52.5876083374],"type":"Point"}
}