{
  "type": "Feature",
  "properties": {
    "addr:full":"C/o The Methodist Church, Rivercourt Road London Greater London W6 9JT",
    "addr:housenumber":"/ o the",
    "addr:postcode":"w6 9jt",
    "addr:street":"C;Rivercourt Road",
    "iso:country":"GB",
    "sg:address":"C/o The Methodist Church, Rivercourt Road",
    "sg:city":"London",
    "sg:classifiers":[
        {
            "category":"Farming",
            "subcategory":"Nursery",
            "type":"Manufacturing & Wholesale Goods"
        },
        {
            "category":"Education",
            "subcategory":"Preschool",
            "type":"Public Place"
        }
    ],
    "sg:phone":"+44 20 8563 7664",
    "sg:postcode":"W6 9JT",
    "sg:province":"Greater London",
    "sg:tags":[
        "school",
        "creche"
    ],
    "wof:name":"le Herisson School Ltd.",
    "wof:placetype":"venue"
},
  "geometry": {"coordinates":[-0.2333600074,51.4928398132],"type":"Point"}
}