{
  "type": "Feature",
  "properties": {
    "iso:country":"GB",
    "sg:address":"59 - 61 Sterte Avenue",
    "sg:city":"Poole",
    "sg:classifiers":[
        {
            "category":"Professional",
            "subcategory":"Engineering",
            "type":"Services"
        }
    ],
    "sg:phone":"+44 1202 672007",
    "sg:postcode":"BH15 2AN",
    "sg:province":"Dorset",
    "wof:name":"F Wykes Engineering Ltd.",
    "wof:placetype":"venue"
},
  "geometry": {"coordinates":[-1.9839,50.72245],"type":"Point"}
}