{
  "type": "Feature",
  "properties": {
    "iso:country":"GB",
    "sg:address":"13 Heath Rise",
    "sg:city":"Fakenham",
    "sg:classifiers":[
        {
            "category":"Building & Trades",
            "subcategory":"Plumbing",
            "type":"Services"
        }
    ],
    "sg:phone":"+44 1328 863228",
    "sg:postcode":"NR21 8HT",
    "sg:province":"Norfolk",
    "sg:tags":[
        "heating"
    ],
    "wof:name":"C Ledbury",
    "wof:placetype":"venue"
},
  "geometry": {"coordinates":[0.864312,52.8321],"type":"Point"}
}