{
  "type": "Feature",
  "properties": {
    "addr:full":"Aldgate Barrs, Whitechapel High St Whitechapel Greater London E1 7PJ",
    "addr:postcode":"e1 7pj",
    "addr:street":"Aldgate Barrs Whitechapel High St",
    "iso:country":"GB",
    "sg:address":"Aldgate Barrs, Whitechapel High St",
    "sg:city":"Whitechapel",
    "sg:classifiers":[
        {
            "category":"Cafe",
            "type":"Food & Drink"
        }
    ],
    "sg:phone":"+44 20 7488 0187",
    "sg:postcode":"E1 7PJ",
    "sg:province":"Greater London",
    "sg:tags":[
        "tea",
        "room"
    ],
    "wof:name":"Seattle Coffee Co Ltd",
    "wof:placetype":"venue"
},
  "geometry": {"coordinates":[-0.0726239979,51.5149497986],"type":"Point"}
}