{
  "type": "Feature",
  "properties": {
    "iso:country":"GB",
    "sg:address":"18 Arcade Chambers, High St",
    "sg:city":"Brentwood",
    "sg:classifiers":[
        {
            "category":"Organizations",
            "subcategory":"Non-profit Organization",
            "type":"Services"
        }
    ],
    "sg:phone":"+44 1277 202460",
    "sg:postcode":"CM14 4AH",
    "sg:province":"Essex",
    "sg:tags":[
        "organisation",
        "voluntary",
        "charity"
    ],
    "wof:name":"MacMillan Cancer Relief",
    "wof:placetype":"venue"
},
  "geometry": {"coordinates":[0.302834,51.620445],"type":"Point"}
}