{
  "type": "Feature",
  "properties": {
    "addr:full":"26 Lemsford Road St Albans Hertfordshire AL1 3PB",
    "addr:housenumber":"26",
    "addr:postcode":"al1 3pb",
    "addr:street":"Lemsford Road",
    "iso:country":"GB",
    "sg:address":"26 Lemsford Road",
    "sg:city":"St Albans",
    "sg:classifiers":[
        {
            "category":"Arts & Performance",
            "subcategory":"Music",
            "type":"Entertainment"
        }
    ],
    "sg:phone":"+44 1727 857384",
    "sg:postcode":"AL1 3PB",
    "sg:province":"Hertfordshire",
    "sg:tags":[
        "musician",
        "composer"
    ],
    "wof:name":"Merle F Scott Violin Piano & Teaching",
    "wof:placetype":"venue"
},
  "geometry": {"coordinates":[-0.327167,51.75425],"type":"Point"}
}