{
  "type": "Feature",
  "properties": {
    "addr:full":"91 Every St Nelson Lancashire BB9 7LS",
    "addr:housenumber":"91",
    "addr:postcode":"bb9 7ls",
    "addr:street":"Every St",
    "iso:country":"GB",
    "sg:address":"91 Every St",
    "sg:city":"Nelson",
    "sg:classifiers":[
        {
            "category":"Real Estate",
            "subcategory":"Real Estate Operator",
            "type":"Services"
        }
    ],
    "sg:postcode":"BB9 7LS",
    "sg:province":"Lancashire",
    "sg:tags":[
        "letting",
        "agent"
    ],
    "wof:name":"Pendle Properties",
    "wof:placetype":"venue"
},
  "geometry": {"coordinates":[-2.2171459198,53.8373641968],"type":"Point"}
}