{
  "type": "Feature",
  "properties": {
    "addr:full":"106 Church Street Whitby North Yorkshire YO22 4DE",
    "addr:housenumber":"106",
    "addr:postcode":"yo22 4de",
    "addr:street":"Church Street",
    "iso:country":"GB",
    "sg:address":"106 Church Street",
    "sg:city":"Whitby",
    "sg:classifiers":[
        {
            "category":"Shopping",
            "subcategory":"Gifts & Souvenirs",
            "type":"Retail Goods"
        }
    ],
    "sg:postcode":"YO22 4DE",
    "sg:province":"North Yorkshire",
    "sg:tags":[
        "shop"
    ],
    "wof:name":"White Rose Gift Shop",
    "wof:placetype":"venue"
},
  "geometry": {"coordinates":[-0.6119639874,54.488697052],"type":"Point"}
}