{
  "type": "Feature",
  "properties": {
    "iso:country":"GB",
    "sg:address":"5 Camelot Close",
    "sg:city":"Newton-le-willows",
    "sg:classifiers":[
        {
            "category":"Building & Trades",
            "subcategory":"Plumbing",
            "type":"Services"
        }
    ],
    "sg:postcode":"WA12 9HA",
    "sg:province":"Cheshire",
    "sg:tags":[
        "heating"
    ],
    "wof:name":"Wilson Plumbing & Heating",
    "wof:placetype":"venue"
},
  "geometry": {"coordinates":[-2.655604,53.455326],"type":"Point"}
}