{
  "type": "Feature",
  "properties": {
    "iso:country":"GB",
    "sg:address":"1 Grange Gardens",
    "sg:city":"Aberdare",
    "sg:classifiers":[
        {
            "category":"Education",
            "subcategory":"Music School",
            "type":"Public Place"
        }
    ],
    "sg:postcode":"CF44 6RA",
    "sg:province":"Neath Port Talbot",
    "sg:tags":[
        "teacher"
    ],
    "wof:name":"Jeremy Ryan Piano Teacher",
    "wof:placetype":"venue"
},
  "geometry": {"coordinates":[-3.445954,51.71246],"type":"Point"}
}