{
  "type": "Feature",
  "properties": {
    "iso:country":"GB",
    "sg:address":"9 Hamilton Close, Hollycroft",
    "sg:city":"Hinckley",
    "sg:classifiers":[
        {
            "category":"Home & Garden",
            "subcategory":"Hardware",
            "type":"Retail Goods"
        }
    ],
    "sg:postcode":"LE10 0TS",
    "sg:province":"Leicestershire",
    "sg:tags":[
        "retailer",
        "diy"
    ],
    "wof:name":"A & P J Gillanders",
    "wof:placetype":"venue"
},
  "geometry": {"coordinates":[-1.390716,52.547119],"type":"Point"}
}