{
  "type": "Feature",
  "properties": {
    "addr:full":"22 Hayes Street Bromley Kent BR2 7LD",
    "addr:housenumber":"22",
    "addr:postcode":"br2 7ld",
    "addr:street":"Hayes Street",
    "iso:country":"GB",
    "sg:address":"22 Hayes Street",
    "sg:city":"Bromley",
    "sg:classifiers":[
        {
            "category":"Building & Trades",
            "subcategory":"Construction",
            "type":"Services"
        }
    ],
    "sg:phone":"+44 20 8462 4671",
    "sg:postcode":"BR2 7LD",
    "sg:province":"Kent",
    "sg:tags":[
        "flooring"
    ],
    "wof:name":"Ammonite Flooring",
    "wof:placetype":"venue"
},
  "geometry": {"coordinates":[0.012918,51.376385],"type":"Point"}
}