{
  "type": "Feature",
  "properties": {
    "addr:full":"66 Main Street Kilwinning East Ayrshire KA13 6AQ",
    "addr:housenumber":"66",
    "addr:postcode":"ka13 6aq",
    "addr:street":"Main Street",
    "iso:country":"GB",
    "sg:address":"66 Main Street",
    "sg:city":"Kilwinning",
    "sg:classifiers":[
        {
            "category":"Autos & Motor Vehicles",
            "subcategory":"Auto Supplies",
            "type":"Retail Goods"
        },
        {
            "category":"Shopping",
            "type":"Retail Goods"
        }
    ],
    "sg:phone":"+44 1294 557258",
    "sg:postcode":"KA13 6AQ",
    "sg:province":"East Ayrshire",
    "sg:tags":[
        "car",
        "part",
        "accessory"
    ],
    "wof:name":"Tam's Car & Cycle",
    "wof:placetype":"venue"
},
  "geometry": {"coordinates":[-4.6980919838,55.6541557312],"type":"Point"}
}