{
  "type": "Feature",
  "properties": {
    "addr:full":"Bar End Winchester Hampshire SO23 9NT",
    "addr:postcode":"so23 9nt",
    "iso:country":"GB",
    "sg:address":"Bar End",
    "sg:city":"Winchester",
    "sg:classifiers":[
        {
            "category":"Utilities",
            "subcategory":"Refuse",
            "type":"Services"
        }
    ],
    "sg:phone":"+44 1962 848279",
    "sg:postcode":"SO23 9NT",
    "sg:province":"Hampshire",
    "sg:tags":[
        "disposal",
        "waste",
        "retail"
    ],
    "wof:name":"Winchester City Services",
    "wof:placetype":"venue"
},
  "geometry": {"coordinates":[-1.3064490557,51.0568885803],"type":"Point"}
}