{
  "type": "Feature",
  "properties": {
    "addr:full":"Newdowns St Agnes Cornwall TR5 0ST",
    "addr:postcode":"tr5 0st",
    "iso:country":"GB",
    "sg:address":"Newdowns",
    "sg:city":"St Agnes",
    "sg:classifiers":[
        {
            "category":"Professional",
            "type":"Services"
        }
    ],
    "sg:phone":"+44 1872 553344",
    "sg:postcode":"TR5 0ST",
    "sg:province":"Cornwall",
    "sg:tags":[
        "caterer"
    ],
    "wof:name":"Network Contract Services",
    "wof:placetype":"venue"
},
  "geometry": {"coordinates":[-5.1991991997,50.3120994568],"type":"Point"}
}