{
  "type": "Feature",
  "properties": {
    "iso:country":"GB",
    "sg:address":", Balquhidder Station",
    "sg:city":"Lochearnhead",
    "sg:classifiers":[
        {
            "category":"Recreation",
            "subcategory":"Campground",
            "type":"Entertainment"
        }
    ],
    "sg:phone":"+44 1567 830293",
    "sg:postcode":"FK19 8NX",
    "sg:province":"Stirling",
    "sg:tags":[
        "caravan",
        "park"
    ],
    "wof:name":"Balquhidder Braes Caravan Park",
    "wof:placetype":"venue"
},
  "geometry": {"coordinates":[-4.287324,56.385239],"type":"Point"}
}