{
  "type": "Feature",
  "properties": {
    "addr:full":"20b Westlands Gro, Portchester Fareham Hampshire PO16 9AE",
    "addr:housenumber":"20b",
    "addr:postcode":"po16 9ae",
    "addr:street":"Westlands Gro",
    "iso:country":"GB",
    "sg:address":"20b Westlands Gro, Portchester",
    "sg:city":"Fareham",
    "sg:classifiers":[
        {
            "category":"Health Services",
            "subcategory":"Doctor",
            "type":"Services"
        }
    ],
    "sg:phone":"+44 23 9237 7514",
    "sg:postcode":"PO16 9AE",
    "sg:province":"Hampshire",
    "sg:tags":[
        "practitioners"
    ],
    "wof:name":"Westlands Medical Centre",
    "wof:placetype":"venue"
},
  "geometry": {"coordinates":[-1.1338449717,50.8448219299],"type":"Point"}
}