{
  "type": "Feature",
  "properties": {
    "iso:country":"GB",
    "sg:address":"129 Strathmartine Road",
    "sg:city":"Dundee",
    "sg:classifiers":[
        {
            "category":"Health Services",
            "subcategory":"Doctor",
            "type":"Services"
        }
    ],
    "sg:phone":"+44 1382 826724",
    "sg:postcode":"DD3 8DB",
    "sg:province":"Dundee City",
    "sg:tags":[
        "practitioners"
    ],
    "wof:name":"Coldside Medical Practice",
    "wof:placetype":"venue"
},
  "geometry": {"coordinates":[-2.980889,56.475628],"type":"Point"}
}