{
  "type": "Feature",
  "properties": {
    "iso:country":"GB",
    "sg:address":"Lower Waye Alston Cross, Ashburton",
    "sg:city":"Newton Abbot",
    "sg:classifiers":[
        {
            "category":"Building & Trades",
            "subcategory":"Landscaping Services",
            "type":"Services"
        }
    ],
    "sg:phone":"+44 1364 652538",
    "sg:postcode":"TQ13 7ET",
    "sg:province":"Devon",
    "sg:tags":[
        "horticultural",
        "consultant"
    ],
    "wof:name":"Fine Turf (Devon) Ltd.",
    "wof:placetype":"venue"
},
  "geometry": {"coordinates":[-3.747107,50.520042],"type":"Point"}
}