{
  "type": "Feature",
  "properties": {
    "addr:full":"St Annes Road Lincoln Lincolnshire LN2 5RF",
    "addr:postcode":"ln2 5rf",
    "addr:street":"St Annes Road",
    "iso:country":"GB",
    "sg:address":"St Annes Road",
    "sg:city":"Lincoln",
    "sg:classifiers":[
        {
            "category":"Professional",
            "subcategory":"Testing Lab",
            "type":"Services"
        }
    ],
    "sg:phone":"+44 1522 528607",
    "sg:postcode":"LN2 5RF",
    "sg:province":"Lincolnshire",
    "sg:tags":[
        "laboratory"
    ],
    "wof:name":"Laboratory",
    "wof:placetype":"venue"
},
  "geometry": {"coordinates":[-0.524189,53.234634],"type":"Point"}
}