{
  "type": "Feature",
  "properties": {
    "addr:full":"Dean Crossing, Whitwell Road Ventnor Isle of Wight PO38 2AB",
    "addr:postcode":"po38 2ab",
    "addr:street":"Dean Crossing Whitwell Road",
    "iso:country":"GB",
    "sg:address":"Dean Crossing, Whitwell Road",
    "sg:city":"Ventnor",
    "sg:classifiers":[
        {
            "category":"Sports & Exercise",
            "subcategory":"Skate Park",
            "type":"Entertainment"
        }
    ],
    "sg:postcode":"PO38 2AB",
    "sg:province":"Isle of Wight",
    "sg:tags":[
        "mushroom"
    ],
    "wof:name":"Whitwell Mushroom Farm",
    "wof:placetype":"venue"
},
  "geometry": {"coordinates":[-1.2636829615,50.5971412659],"type":"Point"}
}