{
  "type": "Feature",
  "properties": {
    "iso:country":"GB",
    "sg:address":"Port Hamble, Satchell Lane, Hamble",
    "sg:city":"Southampton",
    "sg:classifiers":[
        {
            "category":"Bars & Pubs",
            "type":"Food & Drink"
        }
    ],
    "sg:postcode":"SO31 4QD",
    "sg:province":"Hampshire",
    "sg:tags":[
        "pubs",
        "inn"
    ],
    "wof:name":"The Square Rigger Pub",
    "wof:placetype":"venue"
},
  "geometry": {"coordinates":[-1.3287940025,50.8631248474],"type":"Point"}
}