{
  "type": "Feature",
  "properties": {
    "addr:full":"91 Abury Street London Greater London W1F 0NE",
    "addr:housenumber":"91",
    "addr:postcode":"w1f 0ne",
    "addr:street":"Abury Street",
    "iso:country":"GB",
    "sg:address":"91 Abury Street",
    "sg:city":"London",
    "sg:classifiers":[
        {
            "category":"Organizations",
            "subcategory":"Non-profit Organization",
            "type":"Services"
        }
    ],
    "sg:phone":"+44 20 7299 2888",
    "sg:postcode":"W1F 0NE",
    "sg:province":"Greater London",
    "sg:tags":[
        "organisation",
        "voluntary",
        "charity"
    ],
    "wof:name":"N A B S",
    "wof:placetype":"venue"
},
  "geometry": {"coordinates":[-0.1341499984,51.5131988525],"type":"Point"}
}