{
  "type": "Feature",
  "properties": {
    "addr:full":"20 Station Rd Preston Lancashire PR4 6SN",
    "addr:housenumber":"20",
    "addr:postcode":"pr4 6sn",
    "addr:street":"Station Rd",
    "iso:country":"GB",
    "sg:address":"20 Station Rd",
    "sg:city":"Preston",
    "sg:classifiers":[
        {
            "category":"Shopping",
            "subcategory":"Clothing, Apparel, & Fashions",
            "type":"Retail Goods"
        }
    ],
    "sg:phone":"+44 1772 814844",
    "sg:postcode":"PR4 6SN",
    "sg:province":"Lancashire",
    "sg:tags":[
        "wear",
        "leisure"
    ],
    "wof:name":"A & L'S",
    "wof:placetype":"venue"
},
  "geometry": {"coordinates":[-2.838542,53.698895],"type":"Point"}
}