{
  "type": "Feature",
  "properties": {
    "iso:country":"GB",
    "sg:address":"Steele Road",
    "sg:city":"London",
    "sg:classifiers":[
        {
            "category":"Home & Garden",
            "subcategory":"Household Appliances",
            "type":"Retail Goods"
        }
    ],
    "sg:phone":"+44 20 8993 7206",
    "sg:postcode":"NW10 7AR",
    "sg:province":"Greater London",
    "sg:tags":[
        "electrical"
    ],
    "wof:name":"Adverst Appliances",
    "wof:placetype":"venue"
},
  "geometry": {"coordinates":[-0.264544,51.534103],"type":"Point"}
}