{
  "type": "Feature",
  "properties": {
    "iso:country":"GB",
    "sg:address":"The Vicarage, Sandlebridge La",
    "sg:city":"Knutsford",
    "sg:classifiers":[
        {
            "category":"Place Of Worship",
            "type":"Public Place"
        }
    ],
    "sg:phone":"+44 1625 860981",
    "sg:postcode":"WA16 7SB",
    "sg:province":"Cheshire",
    "wof:name":"All Saints C of E Church Marthall",
    "wof:placetype":"venue"
},
  "geometry": {"coordinates":[-2.299636,53.280308],"type":"Point"}
}