{
  "type": "Feature",
  "properties": {
    "addr:full":"Lane End Farm, Shinfield Reading Berkshire RG2 9BE",
    "addr:postcode":"rg2 9be",
    "iso:country":"GB",
    "sg:address":"Lane End Farm, Shinfield",
    "sg:city":"Reading",
    "sg:classifiers":[
        {
            "category":"Shopping",
            "subcategory":"Books",
            "type":"Retail Goods"
        }
    ],
    "sg:postcode":"RG2 9BE",
    "sg:province":"Berkshire",
    "sg:tags":[
        "second-hand"
    ],
    "wof:name":"Books & Bygones",
    "wof:placetype":"venue"
},
  "geometry": {"coordinates":[-0.947666,51.411556],"type":"Point"}
}