{
  "type": "Feature",
  "properties": {
    "addr:full":"Avenue Garage, The Avenue, Comber Bach Northwich Cheshire CW9 6HT",
    "addr:postcode":"cw9 6ht",
    "addr:street":"The Avenue Comber Bach",
    "iso:country":"GB",
    "sg:address":"Avenue Garage, The Avenue, Comber Bach",
    "sg:city":"Northwich",
    "sg:classifiers":[
        {
            "category":"Retail",
            "subcategory":"Auto Repair",
            "type":"Services"
        }
    ],
    "sg:postcode":"CW9 6HT",
    "sg:province":"Cheshire",
    "sg:tags":[
        "modification",
        "garage"
    ],
    "wof:name":"J H & O Percival",
    "wof:placetype":"venue"
},
  "geometry": {"coordinates":[-2.5119988918,53.260471344],"type":"Point"}
}