{
  "type": "Feature",
  "properties": {
    "addr:full":"2 Fore Street St Ives Cornwall TR26 1AB",
    "addr:housenumber":"2",
    "addr:postcode":"tr26 1ab",
    "addr:street":"Fore Street",
    "iso:country":"GB",
    "sg:address":"2 Fore Street",
    "sg:city":"St Ives",
    "sg:classifiers":[
        {
            "category":"Shopping",
            "subcategory":"Books",
            "type":"Retail Goods"
        }
    ],
    "sg:postcode":"TR26 1AB",
    "sg:province":"Cornwall",
    "sg:tags":[
        "bookseller"
    ],
    "wof:name":"Book Centre",
    "wof:placetype":"venue"
},
  "geometry": {"coordinates":[-5.480513,50.212822],"type":"Point"}
}