{
  "type": "Feature",
  "properties": {
    "addr:full":"Scamps Hill, Scaynes Hill Road Haywards Heath East Sussex RH16 2QQ",
    "addr:postcode":"rh16 2qq",
    "addr:street":"Scamps Hill Scaynes Hill Road",
    "iso:country":"GB",
    "sg:address":"Scamps Hill, Scaynes Hill Road",
    "sg:city":"Haywards Heath",
    "sg:classifiers":[
        {
            "category":"Building & Trades",
            "subcategory":"Construction",
            "type":"Services"
        }
    ],
    "sg:postcode":"RH16 2QQ",
    "sg:province":"East Sussex",
    "sg:tags":[
        "decorator",
        "painter"
    ],
    "wof:name":"Gasson & Watson",
    "wof:placetype":"venue"
},
  "geometry": {"coordinates":[-0.076834,51.007801],"type":"Point"}
}