{
  "type": "Feature",
  "properties": {
    "addr:full":"31 Burton Road, Withington Manchester Greater Manchester M20 9FA",
    "addr:housenumber":"31",
    "addr:postcode":"m20 9fa",
    "addr:street":"Burton Road",
    "iso:country":"GB",
    "sg:address":"31 Burton Road, Withington",
    "sg:city":"Manchester",
    "sg:classifiers":[
        {
            "category":"Social Services",
            "type":"Services"
        }
    ],
    "sg:phone":"+44 161 445 5712",
    "sg:postcode":"M20 9FA",
    "sg:province":"Greater Manchester",
    "wof:name":"Burton Road Family Unit",
    "wof:placetype":"venue"
},
  "geometry": {"coordinates":[-2.22787,53.434608],"type":"Point"}
}