{
  "type": "Feature",
  "properties": {
    "addr:full":"Hulley Road Macclesfield Cheshire SK10 2ND",
    "addr:postcode":"sk10 2nd",
    "addr:street":"Hulley Road",
    "iso:country":"GB",
    "sg:address":"Hulley Road",
    "sg:city":"Macclesfield",
    "sg:classifiers":[
        {
            "category":"Shopping",
            "subcategory":"Computers & Home Electronics",
            "type":"Retail Goods"
        }
    ],
    "sg:phone":"+44 1625 426295",
    "sg:postcode":"SK10 2ND",
    "sg:province":"Cheshire",
    "sg:tags":[
        "electrical"
    ],
    "wof:name":"City Electrical Factors Ltd.",
    "wof:placetype":"venue"
},
  "geometry": {"coordinates":[-2.111404,53.269844],"type":"Point"}
}