{
  "type": "Feature",
  "properties": {
    "addr:full":"Bull Lane Works, Brandon Way West Bromwich West Midlands B70 9PQ",
    "addr:postcode":"b70 9pq",
    "addr:street":"Bull Lane;Brandon Way",
    "iso:country":"GB",
    "sg:address":"Bull Lane Works, Brandon Way",
    "sg:city":"West Bromwich",
    "sg:classifiers":[
        {
            "category":"Manufacturing",
            "subcategory":"Metals",
            "type":"Manufacturing & Wholesale Goods"
        }
    ],
    "sg:phone":"+44 121 553 0728",
    "sg:postcode":"B70 9PQ",
    "sg:province":"West Midlands",
    "sg:tags":[
        "heat",
        "-",
        "treatment"
    ],
    "wof:name":"Electro Heat Treatments Ltd.",
    "wof:placetype":"venue"
},
  "geometry": {"coordinates":[-2.0150239468,52.5183334351],"type":"Point"}
}