{
  "type": "Feature",
  "properties": {
    "addr:full":"Common Road Industrial Estate, Verulam Road Stafford Staffordshire ST16 3EA",
    "addr:postcode":"st16 3ea",
    "addr:street":"Common Road Industrial Estate Verulam Road",
    "iso:country":"GB",
    "sg:address":"Common Road Industrial Estate, Verulam Road",
    "sg:city":"Stafford",
    "sg:classifiers":[
        {
            "category":"Building & Trades",
            "subcategory":"Cleaning & Sanitation",
            "type":"Services"
        },
        {
            "category":"Home & Garden",
            "subcategory":"Hardware",
            "type":"Retail Goods"
        },
        {
            "category":"Building & Trades",
            "subcategory":"Construction",
            "type":"Services"
        }
    ],
    "sg:phone":"+44 1785 254554",
    "sg:postcode":"ST16 3EA",
    "sg:province":"Staffordshire",
    "sg:tags":[
        "heat",
        "mech",
        "commercial",
        "exchanger"
    ],
    "wof:name":"Spiro-Gills Ltd.",
    "wof:placetype":"venue"
},
  "geometry": {"coordinates":[-2.118199,52.819981],"type":"Point"}
}