{
  "type": "Feature",
  "properties": {
    "addr:full":"Rosebury Farm, Harling Road, Eaton Bray Dunstable Bedfordshire LU6 1QZ",
    "addr:housenumber":"rosebury",
    "addr:postcode":"lu6 1qz",
    "addr:street":"Harling Road",
    "iso:country":"GB",
    "sg:address":"Rosebury Farm, Harling Road, Eaton Bray",
    "sg:city":"Dunstable",
    "sg:classifiers":[
        {
            "category":"Farming",
            "subcategory":"Livestock Farm",
            "type":"Manufacturing & Wholesale Goods"
        },
        {
            "category":"Farming",
            "subcategory":"Farm",
            "type":"Manufacturing & Wholesale Goods"
        }
    ],
    "sg:phone":"+44 1525 220424",
    "sg:postcode":"LU6 1QZ",
    "sg:province":"Bedfordshire",
    "sg:tags":[
        "mixed",
        "crop",
        "others"
    ],
    "wof:name":"T H & S A Thorne",
    "wof:placetype":"venue"
},
  "geometry": {"coordinates":[-0.5760499835,51.8676300049],"type":"Point"}
}