{
  "type": "Feature",
  "properties": {
    "addr:full":"6 Byfield Avenue Thornton-cleveleys Lancashire FY5 3HW",
    "addr:housenumber":"6",
    "addr:postcode":"fy5 3hw",
    "addr:street":"Byfield Avenue",
    "iso:country":"GB",
    "sg:address":"6 Byfield Avenue",
    "sg:city":"Thornton-cleveleys",
    "sg:classifiers":[
        {
            "category":"Home & Garden",
            "subcategory":"Kitchen Supply",
            "type":"Retail Goods"
        }
    ],
    "sg:phone":"+44 1253 856898",
    "sg:postcode":"FY5 3HW",
    "sg:province":"Lancashire",
    "sg:tags":[
        "equipment",
        "catering"
    ],
    "wof:name":"Arnold Clarke",
    "wof:placetype":"venue"
},
  "geometry": {"coordinates":[-3.0295948982,53.8636932373],"type":"Point"}
}