{
  "type": "Feature",
  "properties": {
    "addr:full":"60 Hoe Street London Greater London E17 4PG",
    "addr:housenumber":"60",
    "addr:postcode":"e17 4pg",
    "addr:street":"Hoe Street",
    "iso:country":"GB",
    "sg:address":"60 Hoe Street",
    "sg:city":"London",
    "sg:classifiers":[
        {
            "category":"Banks & Credit Unions",
            "subcategory":"Financial Services",
            "type":"Services"
        }
    ],
    "sg:phone":"+44 20 8925 4433",
    "sg:postcode":"E17 4PG",
    "sg:province":"Greater London",
    "sg:tags":[
        "adviser"
    ],
    "wof:name":"East City Finance",
    "wof:placetype":"venue"
},
  "geometry": {"coordinates":[-0.019271,51.589268],"type":"Point"}
}