{
  "type": "Feature",
  "properties": {
    "iso:country":"GB",
    "sg:address":"Smith Road",
    "sg:city":"Wednesbury",
    "sg:classifiers":[
        {
            "category":"Shopping",
            "subcategory":"Books",
            "type":"Retail Goods"
        }
    ],
    "sg:phone":"+44 121 556 2666",
    "sg:postcode":"WS10 0PB",
    "sg:province":"West Midlands",
    "wof:name":"Context Ltd.",
    "wof:placetype":"venue"
},
  "geometry": {"coordinates":[-2.021904,52.546387],"type":"Point"}
}