{
  "type": "Feature",
  "properties": {
    "addr:full":"23 Spinney Road, Chawston Bedford Bedfordshire MK44 3BW",
    "addr:housenumber":"23",
    "addr:postcode":"mk44 3bw",
    "addr:street":"Spinney Road Chawston",
    "iso:country":"GB",
    "sg:address":"23 Spinney Road, Chawston",
    "sg:city":"Bedford",
    "sg:classifiers":[
        {
            "category":"Manufacturing",
            "subcategory":"Buildings",
            "type":"Manufacturing & Wholesale Goods"
        }
    ],
    "sg:phone":"+44 1480 212336",
    "sg:postcode":"MK44 3BW",
    "sg:province":"Bedfordshire",
    "sg:tags":[
        "shed",
        "greenhouse"
    ],
    "wof:name":"Beaver Sheds",
    "wof:placetype":"venue"
},
  "geometry": {"coordinates":[-0.3183679879,52.1883773804],"type":"Point"}
}