{
  "type": "Feature",
  "properties": {
    "addr:full":"77 Torphin Cres Glasgow Glasgow City G32 6NN",
    "addr:housenumber":"77",
    "addr:postcode":"g32 6nn",
    "addr:street":"Torphin Cres",
    "iso:country":"GB",
    "sg:address":"77 Torphin Cres",
    "sg:city":"Glasgow",
    "sg:classifiers":[
        {
            "category":"Home & Garden",
            "subcategory":"Carpets & Floor Coverings",
            "type":"Retail Goods"
        }
    ],
    "sg:postcode":"G32 6NN",
    "sg:province":"Glasgow City",
    "sg:tags":[
        "textile",
        "floorcoverings"
    ],
    "wof:name":"Wallace,Andrew Flooring",
    "wof:placetype":"venue"
},
  "geometry": {"coordinates":[-4.1658577919,55.8598098755],"type":"Point"}
}