{
  "type": "Feature",
  "properties": {
    "iso:country":"GB",
    "sg:address":"269 Lichfield Rd",
    "sg:city":"Walsall",
    "sg:classifiers":[
        {
            "category":"Education",
            "subcategory":"Music School",
            "type":"Public Place"
        }
    ],
    "sg:phone":"+44 1922 685885",
    "sg:postcode":"WS4 1PJ",
    "sg:province":"West Midlands",
    "sg:tags":[
        "conservatory"
    ],
    "wof:name":"Norman Such Conservatories",
    "wof:placetype":"venue"
},
  "geometry": {"coordinates":[-1.966891,52.600914],"type":"Point"}
}