{
  "type": "Feature",
  "properties": {
    "addr:full":"7 Pitsford Street, Hockley Birmingham West Midlands B18 6LJ",
    "addr:housenumber":"7",
    "addr:postcode":"b18 6lj",
    "addr:street":"Pitsford Street",
    "iso:country":"GB",
    "sg:address":"7 Pitsford Street, Hockley",
    "sg:city":"Birmingham",
    "sg:classifiers":[
        {
            "category":"Professional",
            "subcategory":"Printing & Photocopies",
            "type":"Services"
        }
    ],
    "sg:phone":"+44 121 554 5951",
    "sg:postcode":"B18 6LJ",
    "sg:province":"West Midlands",
    "sg:tags":[
        "printer"
    ],
    "wof:name":"Goldprint",
    "wof:placetype":"venue"
},
  "geometry": {"coordinates":[-1.913094,52.488815],"type":"Point"}
}