{
  "type": "Feature",
  "properties": {
    "iso:country":"GB",
    "sg:address":"16 Snowgatehead, New Mill",
    "sg:city":"Huddersfield",
    "sg:classifiers":[
        {
            "category":"Health Services",
            "subcategory":"Health Practitioner",
            "type":"Services"
        }
    ],
    "sg:phone":"+44 1484 682196",
    "sg:postcode":"HD9 7DH",
    "sg:province":"South Yorkshire",
    "sg:tags":[
        "herbalist"
    ],
    "wof:name":"Jones P Bsc M N I M H",
    "wof:placetype":"venue"
},
  "geometry": {"coordinates":[-1.755943,53.576122],"type":"Point"}
}