{
  "type": "Feature",
  "properties": {
    "iso:country":"GB",
    "sg:address":"Holyoake Avenue",
    "sg:city":"Blackpool",
    "sg:classifiers":[
        {
            "category":"Home & Garden",
            "subcategory":"Furniture",
            "type":"Retail Goods"
        }
    ],
    "sg:postcode":"FY2 0QT",
    "sg:province":"Lancashire",
    "wof:name":"The Sofa Co",
    "wof:placetype":"venue"
},
  "geometry": {"coordinates":[-3.026894,53.838547],"type":"Point"}
}