{
  "type": "Feature",
  "properties": {
    "iso:country":"GB",
    "sg:address":"Home Farm, Quidenham",
    "sg:city":"Norwich",
    "sg:classifiers":[
        {
            "category":"Farming",
            "subcategory":"Livestock Farm",
            "type":"Manufacturing & Wholesale Goods"
        }
    ],
    "sg:phone":"+44 1953 887349",
    "sg:postcode":"NR16 2PJ",
    "sg:province":"Norfolk",
    "sg:tags":[
        "others"
    ],
    "wof:name":"Seago & Lee",
    "wof:placetype":"venue"
},
  "geometry": {"coordinates":[0.98338,52.448261],"type":"Point"}
}