{
  "type": "Feature",
  "properties": {
    "addr:full":"Unit 4 North Road Okehampton Devon EX20 1BE",
    "addr:housenumber":"unit 4",
    "addr:postcode":"ex20 1be",
    "addr:street":"North Road",
    "iso:country":"GB",
    "sg:address":"Unit 4 North Road",
    "sg:city":"Okehampton",
    "sg:classifiers":[
        {
            "category":"Freight",
            "type":"Transportation"
        }
    ],
    "sg:phone":"+44 1837 54485",
    "sg:postcode":"EX20 1BE",
    "sg:province":"Devon",
    "sg:tags":[
        "haulage",
        "road"
    ],
    "wof:name":"Devon & Cornwall Distribution",
    "wof:placetype":"venue"
},
  "geometry": {"coordinates":[-4.0006837845,50.7428016663],"type":"Point"}
}