{
  "type": "Feature",
  "properties": {
    "iso:country":"GB",
    "sg:address":"5 George Street",
    "sg:city":"Brighton",
    "sg:classifiers":[
        {
            "category":"Shopping",
            "subcategory":"Shoes",
            "type":"Retail Goods"
        }
    ],
    "sg:postcode":"BN2 1RH",
    "sg:province":"East Sussex",
    "wof:name":"Pullingers",
    "wof:placetype":"venue"
},
  "geometry": {"coordinates":[-0.13496,50.821178],"type":"Point"}
}