{
  "type": "Feature",
  "properties": {
    "addr:full":"The Grn, Waddingham Gainsborough Lincolnshire DN21 4SX",
    "addr:postcode":"dn21 4sx",
    "iso:country":"GB",
    "sg:address":"The Grn, Waddingham",
    "sg:city":"Gainsborough",
    "sg:classifiers":[
        {
            "category":"Education",
            "subcategory":"School",
            "type":"Public Place"
        },
        {
            "category":"Government",
            "subcategory":"Office",
            "type":"Public Place"
        }
    ],
    "sg:phone":"+44 1673 818239",
    "sg:postcode":"DN21 4SX",
    "sg:province":"Lincolnshire",
    "sg:tags":[
        "local",
        "authority"
    ],
    "wof:name":"Waddingham County Primary School",
    "wof:placetype":"venue"
},
  "geometry": {"coordinates":[-0.51924,53.453232],"type":"Point"}
}