{
  "type": "Feature",
  "properties": {
    "addr:full":"14 Beatrice Terrace, Shiney Row Houghton-le-spring Durham DH4 4QW",
    "addr:housenumber":"14",
    "addr:postcode":"dh4 4qw",
    "addr:street":"Beatrice Terrace",
    "iso:country":"GB",
    "sg:address":"14 Beatrice Terrace, Shiney Row",
    "sg:city":"Houghton-le-spring",
    "sg:classifiers":[
        {
            "category":"Professional",
            "subcategory":"Lawyer & Legal Services",
            "type":"Services"
        }
    ],
    "sg:phone":"+44 191 385 6687",
    "sg:postcode":"DH4 4QW",
    "sg:province":"Durham",
    "sg:tags":[
        "advice",
        "counselling"
    ],
    "wof:name":"S H A R P",
    "wof:placetype":"venue"
},
  "geometry": {"coordinates":[-1.493369,54.867531],"type":"Point"}
}