{
  "type": "Feature",
  "properties": {
    "addr:full":"Underly Hall Kendal Cumbria LA9 4HE",
    "addr:postcode":"la9 4he",
    "addr:street":"Kendal",
    "iso:country":"GB",
    "sg:address":"Underly Hall",
    "sg:city":"Kendal",
    "sg:classifiers":[
        {
            "category":"Education",
            "subcategory":"Special Training",
            "type":"Public Place"
        }
    ],
    "sg:phone":"+44 15242 71206",
    "sg:postcode":"LA9 4HE",
    "sg:province":"Cumbria",
    "sg:tags":[
        "school"
    ],
    "wof:name":"Underley Hall School",
    "wof:placetype":"venue"
},
  "geometry": {"coordinates":[-2.7480840683,54.3240013123],"type":"Point"}
}