{
  "type": "Feature",
  "properties": {
    "iso:country":"GB",
    "sg:address":"1 Driberg Way",
    "sg:city":"Braintree",
    "sg:classifiers":[
        {
            "category":"Wholesale",
            "subcategory":"Furniture",
            "type":"Manufacturing & Wholesale Goods"
        }
    ],
    "sg:phone":"+44 1376 554949",
    "sg:postcode":"CM7 1NB",
    "sg:province":"Essex",
    "sg:tags":[
        "shop",
        "fitting"
    ],
    "wof:name":"Bursell Ltd.",
    "wof:placetype":"venue"
},
  "geometry": {"coordinates":[0.56129,51.869865],"type":"Point"}
}