{
  "type": "Feature",
  "properties": {
    "addr:full":"52 Madingley, St Peters Road Kingston-upon-thames Greater London KT1 3JG",
    "addr:housenumber":"52",
    "addr:postcode":"kt1 3jg",
    "addr:street":"Madingley St Peters Road",
    "iso:country":"GB",
    "sg:address":"52 Madingley, St Peters Road",
    "sg:city":"Kingston-upon-thames",
    "sg:classifiers":[
        {
            "category":"Professional",
            "subcategory":"Art Services",
            "type":"Services"
        }
    ],
    "sg:phone":"+44 20 8547 2660",
    "sg:postcode":"KT1 3JG",
    "sg:province":"Greater London",
    "sg:tags":[
        "photographer"
    ],
    "wof:name":"Artisticat",
    "wof:placetype":"venue"
},
  "geometry": {"coordinates":[-0.288183,51.409321],"type":"Point"}
}