{
  "type": "Feature",
  "properties": {
    "addr:full":"Creffield House, Oxford Rd Colchester Essex CO3 3HW",
    "addr:postcode":"co3 3hw",
    "addr:street":"Oxford Rd",
    "iso:country":"GB",
    "sg:address":"Creffield House, Oxford Rd",
    "sg:city":"Colchester",
    "sg:classifiers":[
        {
            "category":"Real Estate",
            "subcategory":"Surveying",
            "type":"Services"
        }
    ],
    "sg:phone":"+44 1206 563212",
    "sg:postcode":"CO3 3HW",
    "sg:province":"Essex",
    "sg:tags":[
        "surveyor",
        "quantity"
    ],
    "wof:name":"Potter Raper Partnership",
    "wof:placetype":"venue"
},
  "geometry": {"coordinates":[0.888135016,51.8869857788],"type":"Point"}
}