{
  "type": "Feature",
  "properties": {
    "addr:full":"Adwick Road Mexborough South Yorkshire S64 0BP",
    "addr:postcode":"s64 0bp",
    "addr:street":"Adwick Road",
    "iso:country":"GB",
    "sg:address":"Adwick Road",
    "sg:city":"Mexborough",
    "sg:classifiers":[
        {
            "category":"Shopping",
            "subcategory":"Florist",
            "type":"Retail Goods"
        }
    ],
    "sg:phone":"+44 1709 580110",
    "sg:postcode":"S64 0BP",
    "sg:province":"South Yorkshire",
    "wof:name":"Posies",
    "wof:placetype":"venue"
},
  "geometry": {"coordinates":[-1.288951993,53.5039634705],"type":"Point"}
}