{
  "type": "Feature",
  "properties": {
    "iso:country":"GB",
    "sg:address":"Room 3 Arcade Chambers, 86 High St",
    "sg:city":"Littlehampton",
    "sg:classifiers":[
        {
            "category":"Organizations",
            "subcategory":"Non-profit Organization",
            "type":"Services"
        }
    ],
    "sg:phone":"+44 1903 739669",
    "sg:postcode":"BN17 5DX",
    "sg:province":"West Sussex",
    "sg:tags":[
        "organisation",
        "voluntary",
        "charity"
    ],
    "wof:name":"Littlehampton Churches Together Homelink",
    "wof:placetype":"venue"
},
  "geometry": {"coordinates":[-0.5389590263,50.8210296631],"type":"Point"}
}