{
  "type": "Feature",
  "properties": {
    "addr:full":"414 Old London Rd, Ore Hastings East Sussex TN35 5BB",
    "addr:housenumber":"414",
    "addr:postcode":"tn35 5bb",
    "addr:street":"Old London Rd;Hastings",
    "iso:country":"GB",
    "sg:address":"414 Old London Rd, Ore",
    "sg:city":"Hastings",
    "sg:classifiers":[
        {
            "category":"Home & Garden",
            "subcategory":"Household Appliances",
            "type":"Retail Goods"
        }
    ],
    "sg:postcode":"TN35 5BB",
    "sg:province":"East Sussex",
    "sg:tags":[
        "electrical"
    ],
    "wof:name":"Dann & Weeks",
    "wof:placetype":"venue"
},
  "geometry": {"coordinates":[0.6069149971,50.8711471558],"type":"Point"}
}