{
  "type": "Feature",
  "properties": {
    "iso:country":"GB",
    "sg:address":"43 Brookside Crescent, Fenham",
    "sg:city":"Newcastle-upon-tyne",
    "sg:classifiers":[
        {
            "category":"Professional",
            "subcategory":"Detective & Security Services",
            "type":"Services"
        }
    ],
    "sg:postcode":"NE5 3LY",
    "sg:province":"Tyne and Wear",
    "sg:tags":[
        "alarm",
        "burglar",
        "system"
    ],
    "wof:name":"Feelsafe Alarms",
    "wof:placetype":"venue"
},
  "geometry": {"coordinates":[-1.6642589569,54.9913101196],"type":"Point"}
}