{
  "type": "Feature",
  "properties": {
    "addr:full":"8 Hockley Court, 2401 Stratford Road, Hockley Heath Solihull Warwickshire B94 6NW",
    "addr:housenumber":"8;2401",
    "addr:postcode":"b94 6nw",
    "addr:street":"Hockley Court;Stratford Road",
    "iso:country":"GB",
    "sg:address":"8 Hockley Court, 2401 Stratford Road, Hockley Heath",
    "sg:city":"Solihull",
    "sg:classifiers":[
        {
            "category":"Real Estate",
            "subcategory":"Real Estate Agent",
            "type":"Services"
        }
    ],
    "sg:phone":"+44 1564 785052",
    "sg:postcode":"B94 6NW",
    "sg:province":"Warwickshire",
    "wof:name":"P R Gilmore Holdings Ltd.",
    "wof:placetype":"venue"
},
  "geometry": {"coordinates":[-1.7774740458,52.3529167175],"type":"Point"}
}