{
  "type": "Feature",
  "properties": {
    "iso:country":"GB",
    "sg:address":"11 Kings Road",
    "sg:city":"Fleet",
    "sg:classifiers":[
        {
            "category":"Real Estate",
            "subcategory":"Real Estate Agent",
            "type":"Services"
        }
    ],
    "sg:postcode":"GU51 3AA",
    "sg:province":"Hampshire",
    "wof:name":"Atkinson Richards Ltd.",
    "wof:placetype":"venue"
},
  "geometry": {"coordinates":[-0.836265,51.284473],"type":"Point"}
}