{
  "type": "Feature",
  "properties": {
    "addr:full":"14 Warwick Street Daventry Northamptonshire NN11 4AL",
    "addr:housenumber":"14",
    "addr:postcode":"nn11 4al",
    "addr:street":"Warwick Street",
    "iso:country":"GB",
    "sg:address":"14 Warwick Street",
    "sg:city":"Daventry",
    "sg:classifiers":[
        {
            "category":"Retail",
            "subcategory":"Auto Repair",
            "type":"Services"
        }
    ],
    "sg:phone":"+44 1327 871612",
    "sg:postcode":"NN11 4AL",
    "sg:province":"Northamptonshire",
    "sg:tags":[
        "modification",
        "garage"
    ],
    "wof:name":"Icebroom Motors Ltd.",
    "wof:placetype":"venue"
},
  "geometry": {"coordinates":[-1.1668770313,52.2566947937],"type":"Point"}
}