{
  "type": "Feature",
  "properties": {
    "addr:full":"Tripod Crest House, Weadon Road Industrial Estate, Ross Road Northampton Northamptonshire NN5 5AX",
    "addr:postcode":"nn5 5ax",
    "addr:street":"Tripod;Weadon Road Industrial Estate Ross Road",
    "iso:country":"GB",
    "sg:address":"Tripod Crest House, Weadon Road Industrial Estate, Ross Road",
    "sg:city":"Northampton",
    "sg:classifiers":[
        {
            "category":"Building & Trades",
            "subcategory":"Equipment Rental",
            "type":"Services"
        }
    ],
    "sg:phone":"+44 1604 591177",
    "sg:postcode":"NN5 5AX",
    "sg:province":"Northamptonshire",
    "sg:tags":[
        "plant",
        "machinery"
    ],
    "wof:name":"Tripod Crest Haulage Ltd.",
    "wof:placetype":"venue"
},
  "geometry": {"coordinates":[-0.920679,52.240883],"type":"Point"}
}