{
  "type": "Feature",
  "properties": {
    "addr:full":"Unit 60 Spindus Rd, Speke Hall Indust Est Liverpool Merseyside L24 1YA",
    "addr:housenumber":"unit 60",
    "addr:postcode":"l24 1ya",
    "addr:street":"Spindus Rd",
    "iso:country":"GB",
    "sg:address":"Unit 60 Spindus Rd, Speke Hall Indust Est",
    "sg:city":"Liverpool",
    "sg:classifiers":[
        {
            "category":"Wholesale",
            "subcategory":"Machinery & Supplies",
            "type":"Manufacturing & Wholesale Goods"
        }
    ],
    "sg:phone":"+44 151 448 1711",
    "sg:postcode":"L24 1YA",
    "sg:province":"Merseyside",
    "sg:tags":[
        "theatrical"
    ],
    "wof:name":"Mr Phantasy Lighting Co",
    "wof:placetype":"venue"
},
  "geometry": {"coordinates":[-2.866644,53.343681],"type":"Point"}
}