{
  "type": "Feature",
  "properties": {
    "addr:full":"Park Way Havant Hampshire PO9 1HH",
    "addr:postcode":"po9 1hh",
    "addr:street":"Park Way",
    "iso:country":"GB",
    "sg:address":"Park Way",
    "sg:city":"Havant",
    "sg:classifiers":[
        {
            "category":"Health Services",
            "subcategory":"Hospital",
            "type":"Services"
        }
    ],
    "sg:phone":"+44 23 9247 1661",
    "sg:postcode":"PO9 1HH",
    "sg:province":"Hampshire",
    "wof:name":"Park Way Centre",
    "wof:placetype":"venue"
},
  "geometry": {"coordinates":[-0.9853240252,50.8531761169],"type":"Point"}
}