{
  "type": "Feature",
  "properties": {
    "addr:full":"41 Cornwall Dr Chesterfield Derbyshire S42 5DX",
    "addr:housenumber":"41",
    "addr:postcode":"s42 5dx",
    "addr:street":"Cornwall Dr",
    "iso:country":"GB",
    "sg:address":"41 Cornwall Dr",
    "sg:city":"Chesterfield",
    "sg:classifiers":[
        {
            "category":"Building & Trades",
            "subcategory":"Construction",
            "type":"Services"
        }
    ],
    "sg:phone":"+44 1246 270510",
    "sg:postcode":"S42 5DX",
    "sg:province":"Derbyshire",
    "sg:tags":[
        "builder"
    ],
    "wof:name":"Thackray Construction Ltd",
    "wof:placetype":"venue"
},
  "geometry": {"coordinates":[-1.3938839436,53.1987953186],"type":"Point"}
}