{
  "type": "Feature",
  "properties": {
    "iso:country":"GB",
    "sg:address":"55-59 Bensham Gro",
    "sg:city":"Thornton Heath",
    "sg:classifiers":[
        {
            "category":"Manufacturing",
            "subcategory":"Rubber & Plastics",
            "type":"Manufacturing & Wholesale Goods"
        }
    ],
    "sg:postcode":"CR7 8DD",
    "sg:province":"Surrey",
    "sg:tags":[
        "forming",
        "vacuum"
    ],
    "wof:name":"Holders Ltd.",
    "wof:placetype":"venue"
},
  "geometry": {"coordinates":[-0.101542,51.40593],"type":"Point"}
}