{
  "type": "Feature",
  "properties": {
    "addr:full":"201 Silbury Boulevard, Central Milton Keynes Milton Keynes Buckinghamshire MK9 1LZ",
    "addr:housenumber":"201",
    "addr:postcode":"mk9 1lz",
    "addr:street":"Silbury Boulevard",
    "iso:country":"GB",
    "sg:address":"201 Silbury Boulevard, Central Milton Keynes",
    "sg:city":"Milton Keynes",
    "sg:classifiers":[
        {
            "category":"Insurance",
            "subcategory":"Health Insurance",
            "type":"Services"
        }
    ],
    "sg:phone":"+44 1908 544500",
    "sg:postcode":"MK9 1LZ",
    "sg:province":"Buckinghamshire",
    "wof:name":"Medical Claims Handling Ltd",
    "wof:placetype":"venue"
},
  "geometry": {"coordinates":[-0.769052,52.03923],"type":"Point"}
}