{
  "type": "Feature",
  "properties": {
    "iso:country":"GB",
    "sg:address":"Medlock Street",
    "sg:city":"Manchester",
    "sg:classifiers":[
        {
            "category":"Government",
            "subcategory":"Department Of Motor Vehicles",
            "type":"Public Place"
        }
    ],
    "sg:postcode":"M43 7AG",
    "sg:province":"Greater Manchester",
    "sg:tags":[
        "inspection"
    ],
    "wof:name":"Medlock Street Service Station",
    "wof:placetype":"venue"
},
  "geometry": {"coordinates":[-2.1437680721,53.4843063354],"type":"Point"}
}