{
  "type": "Feature",
  "properties": {
    "addr:full":"16 Sitzhardinge St West End Greater London W1H 9PL",
    "addr:housenumber":"16",
    "addr:postcode":"w1h 9pl",
    "addr:street":"Sitzhardinge St",
    "iso:country":"GB",
    "sg:address":"16 Sitzhardinge St",
    "sg:city":"West End",
    "sg:classifiers":[
        {
            "category":"Organizations",
            "subcategory":"Non-profit Organization",
            "type":"Services"
        }
    ],
    "sg:phone":"+44 20 7224 0743",
    "sg:postcode":"W1H 9PL",
    "sg:province":"Greater London",
    "sg:tags":[
        "organisation",
        "voluntary",
        "charity"
    ],
    "wof:name":"Ash Action On Smoking & Health",
    "wof:placetype":"venue"
},
  "geometry": {"coordinates":[-0.1596100032,51.5161781311],"type":"Point"}
}