{
  "type": "Feature",
  "properties": {
    "iso:country":"GB",
    "sg:address":"4 Cofferidge Close, Stony Stratford",
    "sg:city":"Milton Keynes",
    "sg:classifiers":[
        {
            "category":"Real Estate",
            "subcategory":"Surveying",
            "type":"Services"
        }
    ],
    "sg:phone":"+44 1908 565561",
    "sg:postcode":"MK11 1BY",
    "sg:province":"Buckinghamshire",
    "sg:tags":[
        "surveyor",
        "land"
    ],
    "wof:name":"Milton Keynes Surveys",
    "wof:placetype":"venue"
},
  "geometry": {"coordinates":[-0.8523610234,52.0552597046],"type":"Point"}
}