{
  "type": "Feature",
  "properties": {
    "iso:country":"GB",
    "sg:address":"Duke Street",
    "sg:city":"Kingussie",
    "sg:classifiers":[
        {
            "category":"Landmark",
            "subcategory":"Tourist Information",
            "type":"Public Place"
        }
    ],
    "sg:phone":"+44 1540 661297",
    "sg:postcode":"PH21 1JG",
    "sg:province":"Highland",
    "wof:name":"The Highlands of Scotland Tourist Board",
    "wof:placetype":"venue"
},
  "geometry": {"coordinates":[-4.047679,57.080444],"type":"Point"}
}