{
  "type": "Feature",
  "properties": {
    "iso:country":"GB",
    "sg:address":"Unit C4 Sampson Business Park, Bridge Road",
    "sg:city":"Camberley",
    "sg:classifiers":[
        {
            "category":"Professional",
            "type":"Services"
        }
    ],
    "sg:phone":"+44 1276 676717",
    "sg:postcode":"GU15 2QR",
    "sg:province":"Berkshire",
    "sg:tags":[
        "control",
        "system"
    ],
    "wof:name":"A D G Systems Plc",
    "wof:placetype":"venue"
},
  "geometry": {"coordinates":[-0.73423,51.336216],"type":"Point"}
}