{
  "type": "Feature",
  "properties": {
    "addr:full":"Parkwood Farm, Upper Dicker Hailsham East Sussex BN27 3QL",
    "addr:postcode":"bn27 3ql",
    "addr:street":"Upper Dicker Hailsham",
    "iso:country":"GB",
    "sg:address":"Parkwood Farm, Upper Dicker",
    "sg:city":"Hailsham",
    "sg:classifiers":[
        {
            "category":"Farming",
            "subcategory":"Dairy Farm",
            "type":"Manufacturing & Wholesale Goods"
        }
    ],
    "sg:phone":"+44 1323 845871",
    "sg:postcode":"BN27 3QL",
    "sg:province":"East Sussex",
    "wof:name":"W & A Appleton (Arlington) Ltd.",
    "wof:placetype":"venue"
},
  "geometry": {"coordinates":[0.2134799957,50.8719444275],"type":"Point"}
}