{
  "type": "Feature",
  "properties": {
    "addr:full":"14 Corstorphine Road Edinburgh City of Edinburgh EH12 6HN",
    "addr:housenumber":"14",
    "addr:postcode":"eh12 6hn",
    "addr:street":"Corstorphine Road",
    "iso:country":"GB",
    "sg:address":"14 Corstorphine Road",
    "sg:city":"Edinburgh",
    "sg:classifiers":[
        {
            "category":"Travel",
            "subcategory":"Hotels & Motels",
            "type":"Entertainment"
        }
    ],
    "sg:phone":"+44 131 337 1130",
    "sg:postcode":"EH12 6HN",
    "sg:province":"City of Edinburgh",
    "wof:name":"Hampton Hotel",
    "wof:placetype":"venue"
},
  "geometry": {"coordinates":[-3.2778549194,55.9463157654],"type":"Point"}
}