{
  "type": "Feature",
  "properties": {
    "iso:country":"GB",
    "sg:address":"224 Frimley Green Road, Frimley Grn",
    "sg:city":"Camberley",
    "sg:classifiers":[
        {
            "category":"Fast Food",
            "type":"Food & Drink"
        }
    ],
    "sg:phone":"+44 1252 834500",
    "sg:postcode":"GU16 6LL",
    "sg:province":"Hampshire",
    "sg:tags":[
        "away",
        "take"
    ],
    "wof:name":"Polash",
    "wof:placetype":"venue"
},
  "geometry": {"coordinates":[-0.728579998,51.3031349182],"type":"Point"}
}