{
  "type": "Feature",
  "properties": {
    "addr:full":"Summerdown Farm, Everleigh Marlborough Berkshire SN8 3EX",
    "addr:housenumber":"everleigh",
    "addr:postcode":"sn8 3ex",
    "iso:country":"GB",
    "sg:address":"Summerdown Farm, Everleigh",
    "sg:city":"Marlborough",
    "sg:classifiers":[
        {
            "category":"Farming",
            "subcategory":"Crops",
            "type":"Manufacturing & Wholesale Goods"
        },
        {
            "category":"Farming",
            "subcategory":"Livestock Farm",
            "type":"Manufacturing & Wholesale Goods"
        }
    ],
    "sg:phone":"+44 1264 850505",
    "sg:postcode":"SN8 3EX",
    "sg:province":"Berkshire",
    "sg:tags":[
        "arable",
        "others"
    ],
    "wof:name":"R G May & Sons",
    "wof:placetype":"venue"
},
  "geometry": {"coordinates":[-1.7116830349,51.2826271057],"type":"Point"}
}