{
  "type": "Feature",
  "properties": {
    "addr:full":"239 Douglas Rd, Accocks Green Birmingham West Midlands B27 6EX",
    "addr:housenumber":"239",
    "addr:postcode":"b27 6ex",
    "addr:street":"Douglas Rd Accocks Green",
    "iso:country":"GB",
    "sg:address":"239 Douglas Rd, Accocks Green",
    "sg:city":"Birmingham",
    "sg:classifiers":[
        {
            "category":"Professional",
            "subcategory":"Art Services",
            "type":"Services"
        },
        {
            "category":"Wholesale",
            "subcategory":"Books, Periodicals, & Newspapers",
            "type":"Manufacturing & Wholesale Goods"
        }
    ],
    "sg:postcode":"B27 6EX",
    "sg:province":"West Midlands",
    "sg:tags":[
        "photographer",
        "publishing"
    ],
    "wof:name":"Corporate & Broadcast Communications Ltd",
    "wof:placetype":"venue"
},
  "geometry": {"coordinates":[-1.8284059763,52.4536247253],"type":"Point"}
}