{
  "type": "Feature",
  "properties": {
    "iso:country":"GB",
    "sg:address":"72 Higher Croft Rd, Lwr Darwen",
    "sg:city":"Darwen",
    "sg:classifiers":[
        {
            "category":"Social Services",
            "subcategory":"Retirement Home",
            "type":"Services"
        }
    ],
    "sg:phone":"+44 1254 56315",
    "sg:postcode":"BB3 0QR",
    "sg:province":"Lancashire",
    "sg:tags":[
        "residential",
        "care"
    ],
    "wof:name":"Douglas,Doreen,",
    "wof:placetype":"venue"
},
  "geometry": {"coordinates":[-2.472739,53.726299],"type":"Point"}
}