{
  "type": "Feature",
  "properties": {
    "iso:country":"GB",
    "sg:address":"5 Durness Street",
    "sg:city":"Thurso",
    "sg:classifiers":[
        {
            "category":"Professional",
            "subcategory":"Art Services",
            "type":"Services"
        },
        {
            "category":"Building & Trades",
            "subcategory":"Construction",
            "type":"Services"
        }
    ],
    "sg:phone":"+44 1847 895110",
    "sg:postcode":"KW14 8BD",
    "sg:province":"Highland",
    "sg:tags":[
        "decorator",
        "painter"
    ],
    "wof:name":"Donald Mowat",
    "wof:placetype":"venue"
},
  "geometry": {"coordinates":[-3.520305,58.596325],"type":"Point"}
}