{
  "type": "Feature",
  "properties": {
    "iso:country":"GB",
    "sg:address":"56 Grosvenor Street",
    "sg:city":"London",
    "sg:classifiers":[
        {
            "category":"Real Estate",
            "subcategory":"Surveying",
            "type":"Services"
        }
    ],
    "sg:phone":"+44 20 7491 7820",
    "sg:postcode":"W1K 3HZ",
    "sg:province":"Greater London",
    "sg:tags":[
        "surveyor",
        "quantity"
    ],
    "wof:name":"Burnham Stevens Associates",
    "wof:placetype":"venue"
},
  "geometry": {"coordinates":[-0.145009,51.511467],"type":"Point"}
}