{
  "type": "Feature",
  "properties": {
    "addr:full":"Bank Farm, Stokeham Retford Nottinghamshire DN22 0JZ",
    "addr:postcode":"dn22 0jz",
    "iso:country":"GB",
    "sg:address":"Bank Farm, Stokeham",
    "sg:city":"Retford",
    "sg:classifiers":[
        {
            "category":"Farming",
            "subcategory":"Farm",
            "type":"Manufacturing & Wholesale Goods"
        }
    ],
    "sg:phone":"+44 1777 248247",
    "sg:postcode":"DN22 0JZ",
    "sg:province":"Nottinghamshire",
    "sg:tags":[
        "mixed",
        "crop"
    ],
    "wof:name":"Highfield Farms (Stokeham) Ltd.",
    "wof:placetype":"venue"
},
  "geometry": {"coordinates":[-0.825222,53.283192],"type":"Point"}
}