{
  "type": "Feature",
  "properties": {
    "addr:full":"10 Calcot Coln Street, Dennis Cheltenham Gloucestershire GL54 3JZ",
    "addr:housenumber":"10",
    "addr:postcode":"cheltenham;gl54 3jz",
    "addr:street":"Calcot Coln Street",
    "iso:country":"GB",
    "sg:address":"10 Calcot Coln Street, Dennis",
    "sg:city":"Cheltenham",
    "sg:classifiers":[
        {
            "category":"Health Services",
            "subcategory":"Clinic",
            "type":"Services"
        }
    ],
    "sg:postcode":"GL54 3JZ",
    "sg:province":"Gloucestershire",
    "sg:tags":[
        "private"
    ],
    "wof:name":"Cotswold Allergy Clinic",
    "wof:placetype":"venue"
},
  "geometry": {"coordinates":[-1.8723499775,51.7894706726],"type":"Point"}
}