{
  "type": "Feature",
  "properties": {
    "iso:country":"GB",
    "sg:address":"25 Villa Rd",
    "sg:city":"Bingley",
    "sg:classifiers":[
        {
            "category":"Building & Trades",
            "subcategory":"Construction",
            "type":"Services"
        }
    ],
    "sg:phone":"+44 1274 562536",
    "sg:postcode":"BD16 4ER",
    "sg:province":"West Yorkshire",
    "sg:tags":[
        "builder"
    ],
    "wof:name":"Kevin Green",
    "wof:placetype":"venue"
},
  "geometry": {"coordinates":[-1.828661,53.854275],"type":"Point"}
}