{
  "type": "Feature",
  "properties": {
    "addr:full":"164 Plato Road, Brixton London Greater London SW2 5RU",
    "addr:housenumber":"164",
    "addr:postcode":"sw2 5ru",
    "addr:street":"Plato Road",
    "iso:country":"GB",
    "sg:address":"164 Plato Road, Brixton",
    "sg:city":"London",
    "sg:classifiers":[
        {
            "category":"Retail",
            "subcategory":"Auto Repair",
            "type":"Services"
        }
    ],
    "sg:phone":"+44 20 7924 0201",
    "sg:postcode":"SW2 5RU",
    "sg:province":"Greater London",
    "sg:tags":[
        "modification",
        "garage"
    ],
    "wof:name":"Clifton's Auto Repairs",
    "wof:placetype":"venue"
},
  "geometry": {"coordinates":[-0.126239,51.4613],"type":"Point"}
}