{
  "type": "Feature",
  "properties": {
    "iso:country":"GB",
    "sg:address":"126 Princes Street",
    "sg:city":"Edinburgh",
    "sg:classifiers":[
        {
            "category":"Shopping",
            "subcategory":"Clothing, Apparel, & Fashions",
            "type":"Retail Goods"
        }
    ],
    "sg:phone":"+44 131 225 1218",
    "sg:postcode":"EH2 4AH",
    "sg:province":"City of Edinburgh",
    "sg:tags":[
        "shop"
    ],
    "wof:name":"Laura Ashley",
    "wof:placetype":"venue"
},
  "geometry": {"coordinates":[-3.20443,55.950863],"type":"Point"}
}