{
  "type": "Feature",
  "properties": {
    "addr:full":"Valley House, St Anns Well Road Nottingham Nottinghamshire NG3 3HR",
    "addr:postcode":"ng3 3hr",
    "addr:street":"St;Well Road",
    "iso:country":"GB",
    "sg:address":"Valley House, St Anns Well Road",
    "sg:city":"Nottingham",
    "sg:classifiers":[
        {
            "category":"Health Services",
            "subcategory":"Clinic",
            "type":"Services"
        }
    ],
    "sg:phone":"+44 115 950 2703",
    "sg:postcode":"NG3 3HR",
    "sg:province":"Nottinghamshire",
    "sg:tags":[
        "nh"
    ],
    "wof:name":"The Medical Centre",
    "wof:placetype":"venue"
},
  "geometry": {"coordinates":[-1.1332139969,52.9635238647],"type":"Point"}
}