{
  "type": "Feature",
  "properties": {
    "iso:country":"GB",
    "sg:address":"128 Station Rd",
    "sg:city":"Sidcup",
    "sg:classifiers":[
        {
            "category":"Retail",
            "subcategory":"Repair Shop",
            "type":"Services"
        }
    ],
    "sg:phone":"+44 20 8309 5159",
    "sg:postcode":"DA15 7AF",
    "sg:province":"Kent",
    "sg:tags":[
        "maintenance"
    ],
    "wof:name":"Drewery Property Sevices",
    "wof:placetype":"venue"
},
  "geometry": {"coordinates":[0.10263,51.434387],"type":"Point"}
}