{
  "type": "Feature",
  "properties": {
    "iso:country":"GB",
    "sg:address":"66 Abbots Road",
    "sg:city":"Colchester",
    "sg:classifiers":[
        {
            "category":"Autos & Motor Vehicles",
            "subcategory":"Auto Supplies",
            "type":"Retail Goods"
        },
        {
            "category":"Retail",
            "subcategory":"Auto Repair",
            "type":"Services"
        }
    ],
    "sg:phone":"+44 1206 510800",
    "sg:postcode":"CO2 8BG",
    "sg:province":"Essex",
    "sg:tags":[
        "windscreen",
        "replacement"
    ],
    "wof:name":"A 1 2 Autoscreens",
    "wof:placetype":"venue"
},
  "geometry": {"coordinates":[0.921833992,51.8708686829],"type":"Point"}
}