{
  "type": "Feature",
  "properties": {
    "addr:full":"185a Reepham Road, Hellesdon Norwich Norfolk NR6 5NZ",
    "addr:housenumber":"185a",
    "addr:postcode":"nr6 5nz",
    "addr:street":"Reepham Road",
    "iso:country":"GB",
    "sg:address":"185a Reepham Road, Hellesdon",
    "sg:city":"Norwich",
    "sg:classifiers":[
        {
            "category":"Food & Beverages",
            "subcategory":"Fruits & Vegetables",
            "type":"Retail Goods"
        }
    ],
    "sg:phone":"+44 1603 426503",
    "sg:postcode":"NR6 5NZ",
    "sg:province":"Norfolk",
    "sg:tags":[
        "greengrocer"
    ],
    "wof:name":"The Fruit Man",
    "wof:placetype":"venue"
},
  "geometry": {"coordinates":[1.2641099691,52.6640815735],"type":"Point"}
}