{
  "type": "Feature",
  "properties": {
    "addr:full":"11-12 Gun Street Reading Berkshire RG1 2JR",
    "addr:housenumber":"11-12",
    "addr:postcode":"rg1 2jr",
    "addr:street":"Gun Street",
    "iso:country":"GB",
    "sg:address":"11-12 Gun Street",
    "sg:city":"Reading",
    "sg:classifiers":[
        {
            "category":"Banks & Credit Unions",
            "subcategory":"Financial Services",
            "type":"Services"
        }
    ],
    "sg:phone":"+44 118 958 9747",
    "sg:postcode":"RG1 2JR",
    "sg:province":"Berkshire",
    "sg:tags":[
        "cashing",
        "cheque"
    ],
    "wof:name":"The Money Shop",
    "wof:placetype":"venue"
},
  "geometry": {"coordinates":[-0.9728879929,51.4539451599],"type":"Point"}
}