{
  "type": "Feature",
  "properties": {
    "addr:full":"10 Victoria Avenue Prestatyn Denbighshire LL19 9DF",
    "addr:housenumber":"10",
    "addr:postcode":"ll19 9df",
    "addr:street":"Victoria Avenue",
    "iso:country":"GB",
    "sg:address":"10 Victoria Avenue",
    "sg:city":"Prestatyn",
    "sg:classifiers":[
        {
            "category":"Retail",
            "subcategory":"Repair Shop",
            "type":"Services"
        }
    ],
    "sg:phone":"+44 1745 853340",
    "sg:postcode":"LL19 9DF",
    "sg:province":"Denbighshire",
    "sg:tags":[
        "radio",
        "television",
        "video"
    ],
    "wof:name":"Ready Vision",
    "wof:placetype":"venue"
},
  "geometry": {"coordinates":[-3.4042639732,53.3332748413],"type":"Point"}
}