{
  "type": "Feature",
  "properties": {
    "iso:country":"GB",
    "sg:address":"11 Market Street",
    "sg:city":"Birkenhead",
    "sg:classifiers":[
        {
            "category":"Wholesale",
            "subcategory":"Home Furnishings",
            "type":"Manufacturing & Wholesale Goods"
        }
    ],
    "sg:phone":"+44 151 647 6375",
    "sg:postcode":"CH41 5ER",
    "sg:province":"Merseyside",
    "sg:tags":[
        "merchant",
        "decorators'"
    ],
    "wof:name":"Robinson & Neal Ltd.",
    "wof:placetype":"venue"
},
  "geometry": {"coordinates":[-3.014556,53.391666],"type":"Point"}
}