{
  "type": "Feature",
  "properties": {
    "iso:country":"GB",
    "sg:address":"37 Conval Street",
    "sg:city":"Keith",
    "sg:classifiers":[
        {
            "category":"Building & Trades",
            "subcategory":"Construction",
            "type":"Services"
        }
    ],
    "sg:phone":"+44 1340 820372",
    "sg:postcode":"AB55 4AH",
    "sg:province":"Moray",
    "sg:tags":[
        "builder"
    ],
    "wof:name":"A McCormack & Sons",
    "wof:placetype":"venue"
},
  "geometry": {"coordinates":[-3.131895,57.444611],"type":"Point"}
}