{
  "type": "Feature",
  "properties": {
    "iso:country":"GB",
    "sg:address":"346a York Road",
    "sg:city":"Leeds",
    "sg:classifiers":[
        {
            "category":"Personal",
            "subcategory":"Barber",
            "type":"Services"
        }
    ],
    "sg:postcode":"LS9 9DN",
    "sg:province":"West Yorkshire",
    "sg:tags":[
        "men's",
        "hairdresser"
    ],
    "wof:name":"R Cambridge",
    "wof:placetype":"venue"
},
  "geometry": {"coordinates":[-1.50321,53.800308],"type":"Point"}
}