{
  "type": "Feature",
  "properties": {
    "iso:country":"GB",
    "sg:address":"50 Ashburton Rd",
    "sg:city":"Newton Abbot",
    "sg:classifiers":[
        {
            "category":"Shopping",
            "subcategory":"News",
            "type":"Retail Goods"
        }
    ],
    "sg:phone":"+44 1626 365954",
    "sg:postcode":"TQ12 1NN",
    "sg:province":"Devon",
    "sg:tags":[
        "newsagent"
    ],
    "wof:name":"Dillons One-Stop",
    "wof:placetype":"venue"
},
  "geometry": {"coordinates":[-3.6235,50.532639],"type":"Point"}
}