{
  "type": "Feature",
  "properties": {
    "addr:full":"84/86 High Road Ilford Essex IG1 1BU",
    "addr:housenumber":"84 / 86",
    "addr:postcode":"ig1 1bu",
    "addr:street":"High Road",
    "iso:country":"GB",
    "sg:address":"84/86 High Road",
    "sg:city":"Ilford",
    "sg:classifiers":[
        {
            "category":"Banks & Credit Unions",
            "subcategory":"Bank",
            "type":"Services"
        }
    ],
    "sg:phone":"+44 845 607 0810",
    "sg:postcode":"IG1 1BU",
    "sg:province":"Essex",
    "wof:name":"Halifax Plc",
    "wof:placetype":"venue"
},
  "geometry": {"coordinates":[0.0709830001,51.5583686829],"type":"Point"}
}