{
  "type": "Feature",
  "properties": {
    "addr:full":"Mosterton Road, Misterton Crewkerne Dorset TA18 8NT",
    "addr:postcode":"ta18 8nt",
    "addr:street":"Mosterton Road",
    "iso:country":"GB",
    "sg:address":"Mosterton Road, Misterton",
    "sg:city":"Crewkerne",
    "sg:classifiers":[
        {
            "category":"Retail",
            "subcategory":"Auto Repair",
            "type":"Services"
        }
    ],
    "sg:phone":"+44 1460 73363",
    "sg:postcode":"TA18 8NT",
    "sg:province":"Dorset",
    "sg:tags":[
        "body",
        "car",
        "repairer"
    ],
    "wof:name":"Mosterton Road Body Repairs",
    "wof:placetype":"venue"
},
  "geometry": {"coordinates":[-2.7738559246,50.8702125549],"type":"Point"}
}