{
  "type": "Feature",
  "properties": {
    "iso:country":"GB",
    "sg:address":"17 St Marys Street",
    "sg:city":"Stamford",
    "sg:classifiers":[
        {
            "category":"Personal",
            "subcategory":"Beauty Salon",
            "type":"Services"
        }
    ],
    "sg:phone":"+44 1780 762323",
    "sg:postcode":"PE9 2DG",
    "sg:province":"Cambridgeshire",
    "sg:tags":[
        "unisex",
        "hairdresser"
    ],
    "wof:name":"Ivor & Pat Lewis International Hair Stylists",
    "wof:placetype":"venue"
},
  "geometry": {"coordinates":[-0.4778839946,52.6517601013],"type":"Point"}
}