{
  "type": "Feature",
  "properties": {
    "iso:country":"GB",
    "sg:address":"380 London Rd",
    "sg:city":"Westcliff On Sea",
    "sg:classifiers":[
        {
            "category":"Home & Garden",
            "subcategory":"Home Furnishings",
            "type":"Retail Goods"
        }
    ],
    "sg:phone":"+44 1702 349138",
    "sg:postcode":"SS0 7HZ",
    "sg:province":"Essex",
    "sg:tags":[
        "furnishers",
        "planner",
        "bedroom"
    ],
    "wof:name":"Essex Illuminated Ceilings & Partitions Ltd",
    "wof:placetype":"venue"
},
  "geometry": {"coordinates":[0.695251,51.5424],"type":"Point"}
}