{
  "type": "Feature",
  "properties": {
    "addr:full":"Wessex Way, Wincanton Business Park Wincanton Somerset BA9 9RR",
    "addr:postcode":"ba9 9rr",
    "addr:street":"Wessex Way;Business Park",
    "iso:country":"GB",
    "sg:address":"Wessex Way, Wincanton Business Park",
    "sg:city":"Wincanton",
    "sg:classifiers":[
        {
            "category":"Building & Trades",
            "subcategory":"Construction",
            "type":"Services"
        }
    ],
    "sg:phone":"+44 1963 34077",
    "sg:postcode":"BA9 9RR",
    "sg:province":"Somerset",
    "sg:tags":[
        "excavation",
        "groundwork",
        "contractor"
    ],
    "wof:name":"A J Davis",
    "wof:placetype":"venue"
},
  "geometry": {"coordinates":[-2.418368,51.051945],"type":"Point"}
}