{
  "type": "Feature",
  "properties": {
    "addr:full":"5 Worcester Street Oxford Oxfordshire OX1 2BX",
    "addr:housenumber":"5",
    "addr:postcode":"ox1 2bx",
    "addr:street":"Worcester Street",
    "iso:country":"GB",
    "sg:address":"5 Worcester Street",
    "sg:city":"Oxford",
    "sg:classifiers":[
        {
            "category":"Banks & Credit Unions",
            "subcategory":"Bank",
            "type":"Services"
        },
        {
            "category":"Professional",
            "subcategory":"Computer Services",
            "type":"Services"
        }
    ],
    "sg:phone":"+44 1865 200202",
    "sg:postcode":"OX1 2BX",
    "sg:province":"Oxfordshire",
    "sg:tags":[
        "information",
        "institution",
        "related"
    ],
    "wof:name":"M R C Business Information Group Ltd.",
    "wof:placetype":"venue"
},
  "geometry": {"coordinates":[-1.2631549835,51.7540473938],"type":"Point"}
}