{
  "type": "Feature",
  "properties": {
    "iso:country":"GB",
    "sg:address":"Davy Avenue",
    "sg:city":"Milton Keynes",
    "sg:classifiers":[
        {
            "category":"Professional",
            "subcategory":"Computer Services",
            "type":"Services"
        }
    ],
    "sg:phone":"+44 1908 234990",
    "sg:postcode":"MK5 8HJ",
    "sg:province":"Buckinghamshire",
    "sg:tags":[
        "system",
        "software"
    ],
    "wof:name":"Informix Software Ltd",
    "wof:placetype":"venue"
},
  "geometry": {"coordinates":[-0.766839,52.022137],"type":"Point"}
}