{
  "type": "Feature",
  "properties": {
    "addr:full":"273 Marine Road Central Morecambe Lancashire LA4 5BY",
    "addr:housenumber":"273",
    "addr:postcode":"la4 5by",
    "addr:street":"Marine Road Central Morecambe",
    "iso:country":"GB",
    "sg:address":"273 Marine Road Central",
    "sg:city":"Morecambe",
    "sg:classifiers":[
        {
            "category":"Bars & Pubs",
            "subcategory":"Nightclub",
            "type":"Food & Drink"
        }
    ],
    "sg:postcode":"LA4 5BY",
    "sg:province":"Lancashire",
    "sg:tags":[
        "club",
        "night"
    ],
    "wof:name":"Darenam,Colin,",
    "wof:placetype":"venue"
},
  "geometry": {"coordinates":[-2.849963,54.076885],"type":"Point"}
}