{
  "type": "Feature",
  "properties": {
    "iso:country":"GB",
    "sg:address":"Capstan House, Dock Tavern Lane, Gorleston",
    "sg:city":"Great Yarmouth",
    "sg:classifiers":[
        {
            "category":"Building & Trades",
            "subcategory":"Cleaning & Sanitation",
            "type":"Services"
        },
        {
            "category":"Building & Trades",
            "subcategory":"Plumbing",
            "type":"Services"
        }
    ],
    "sg:phone":"+44 1493 441004",
    "sg:postcode":"NR31 6PY",
    "sg:province":"Norfolk",
    "sg:tags":[
        "clearance",
        "drain",
        "commercial",
        "sewer"
    ],
    "wof:name":"Superclean Services",
    "wof:placetype":"venue"
},
  "geometry": {"coordinates":[1.73,52.578964],"type":"Point"}
}