{
  "type": "Feature",
  "properties": {
    "iso:country":"GB",
    "sg:address":"New Haven, Wilsill",
    "sg:city":"Harrogate",
    "sg:classifiers":[
        {
            "category":"Building & Trades",
            "subcategory":"Plumbing",
            "type":"Services"
        }
    ],
    "sg:phone":"+44 1423 712821",
    "sg:postcode":"HG3 5EB",
    "sg:province":"North Yorkshire",
    "sg:tags":[
        "plumber",
        "heating"
    ],
    "wof:name":"Slinger & Nelson",
    "wof:placetype":"venue"
},
  "geometry": {"coordinates":[-1.722761,54.076721],"type":"Point"}
}