{
  "type": "Feature",
  "properties": {
    "iso:country":"GB",
    "sg:address":"76 London Road",
    "sg:city":"Morden",
    "sg:classifiers":[
        {
            "category":"Shopping",
            "subcategory":"News",
            "type":"Retail Goods"
        }
    ],
    "sg:phone":"+44 20 8540 8511",
    "sg:postcode":"SM4 5AZ",
    "sg:province":"Surrey",
    "sg:tags":[
        "newsagent"
    ],
    "wof:name":"Bumbles Newsagent",
    "wof:placetype":"venue"
},
  "geometry": {"coordinates":[-0.1943480074,51.4020690918],"type":"Point"}
}