{
  "type": "Feature",
  "properties": {
    "addr:full":"Monoka Lower, Bankend Dumfries Dumfries and Galloway DG1 4RP",
    "addr:postcode":"dg1 4rp",
    "addr:street":"Bankend",
    "iso:country":"GB",
    "sg:address":"Monoka Lower, Bankend",
    "sg:city":"Dumfries",
    "sg:classifiers":[
        {
            "category":"Building & Trades",
            "subcategory":"Construction",
            "type":"Services"
        }
    ],
    "sg:postcode":"DG1 4RP",
    "sg:province":"Dumfries and Galloway",
    "sg:tags":[
        "builder"
    ],
    "wof:name":"Norman Brown Builders",
    "wof:placetype":"venue"
},
  "geometry": {"coordinates":[-3.522354,55.001419],"type":"Point"}
}