{
  "type": "Feature",
  "properties": {
    "iso:country":"GB",
    "sg:address":"Police Station, Morton Terr",
    "sg:city":"Gainsborough",
    "sg:classifiers":[
        {
            "category":"Government",
            "subcategory":"Police Station",
            "type":"Public Place"
        }
    ],
    "sg:phone":"+44 1427 810910",
    "sg:postcode":"DN21 2SY",
    "sg:province":"Lincolnshire",
    "sg:tags":[
        "support"
    ],
    "wof:name":"Lincolnshire Constabularly",
    "wof:placetype":"venue"
},
  "geometry": {"coordinates":[-0.7727680206,53.3956947327],"type":"Point"}
}