{
  "type": "Feature",
  "properties": {
    "iso:country":"GB",
    "sg:address":"10 Castlegate, Helmsley",
    "sg:city":"York",
    "sg:classifiers":[
        {
            "category":"Arts & Performance",
            "subcategory":"Art Gallery",
            "type":"Entertainment"
        },
        {
            "category":"Museum",
            "subcategory":"Art Museum",
            "type":"Entertainment"
        }
    ],
    "sg:phone":"+44 1439 771950",
    "sg:postcode":"YO62 5AB",
    "sg:province":"North Yorkshire",
    "wof:name":"E Stace-Marks",
    "wof:placetype":"venue"
},
  "geometry": {"coordinates":[-1.062294,54.24353],"type":"Point"}
}