{
  "type": "Feature",
  "properties": {
    "addr:full":"135 Cheam Road Sutton Surrey SM1 2BN",
    "addr:housenumber":"135",
    "addr:postcode":"sm1 2bn",
    "addr:street":"Cheam Road",
    "iso:country":"GB",
    "sg:address":"135 Cheam Road",
    "sg:city":"Sutton",
    "sg:classifiers":[
        {
            "category":"Travel",
            "subcategory":"Hotels & Motels",
            "type":"Entertainment"
        }
    ],
    "sg:phone":"+44 20 8642 3131",
    "sg:postcode":"SM1 2BN",
    "sg:province":"Surrey",
    "wof:name":"The Thatched House Hotel",
    "wof:placetype":"venue"
},
  "geometry": {"coordinates":[-0.2076700032,51.359500885],"type":"Point"}
}