{
  "type": "Feature",
  "properties": {
    "addr:full":"22 Broad Street Stirling Stirling FK8 1EF",
    "addr:housenumber":"22",
    "addr:postcode":"fk8 1ef",
    "addr:street":"Broad Street",
    "iso:country":"GB",
    "sg:address":"22 Broad Street",
    "sg:city":"Stirling",
    "sg:classifiers":[
        {
            "category":"Shopping",
            "subcategory":"Stationery & Office Supplies",
            "type":"Retail Goods"
        },
        {
            "category":"Real Estate",
            "subcategory":"Real Estate Services",
            "type":"Services"
        }
    ],
    "sg:postcode":"FK8 1EF",
    "sg:province":"Stirling",
    "sg:tags":[
        "equipment",
        "plant",
        "leasing",
        "hire"
    ],
    "wof:name":"STIRLING BUSINESS MACHINES",
    "wof:placetype":"venue"
},
  "geometry": {"coordinates":[-3.9429969788,56.121055603],"type":"Point"}
}