{
  "type": "Feature",
  "properties": {
    "addr:full":"Rowley Av Stafford Staffordshire ST17 9AA",
    "addr:postcode":"st17 9aa",
    "addr:street":"Rowley Av",
    "iso:country":"GB",
    "sg:address":"Rowley Av",
    "sg:city":"Stafford",
    "sg:classifiers":[
        {
            "category":"Place Of Worship",
            "type":"Public Place"
        }
    ],
    "sg:phone":"+44 1785 258511",
    "sg:postcode":"ST17 9AA",
    "sg:province":"Staffordshire",
    "wof:name":"St. Mary's",
    "wof:placetype":"venue"
},
  "geometry": {"coordinates":[-2.1250989437,52.8002052307],"type":"Point"}
}