{
  "type": "Feature",
  "properties": {
    "addr:full":"106 Bradshawgate Leigh Lancashire WN7 4NP",
    "addr:housenumber":"106",
    "addr:postcode":"wn7 4np",
    "addr:street":"Bradshawgate Leigh",
    "iso:country":"GB",
    "sg:address":"106 Bradshawgate",
    "sg:city":"Leigh",
    "sg:classifiers":[
        {
            "category":"Personal",
            "subcategory":"Beauty Salon",
            "type":"Services"
        }
    ],
    "sg:phone":"+44 1942 603129",
    "sg:postcode":"WN7 4NP",
    "sg:province":"Lancashire",
    "sg:tags":[
        "unisex",
        "hairdresser"
    ],
    "wof:name":"The Big Scissor Co",
    "wof:placetype":"venue"
},
  "geometry": {"coordinates":[-2.5141649246,53.4959487915],"type":"Point"}
}