{
  "type": "Feature",
  "properties": {
    "addr:full":"Units 3-4, Morley Market, Queen St, Morley Leeds West Yorkshire LS27 8EG",
    "addr:housenumber":"units 3-4",
    "addr:postcode":"ls27 8eg",
    "addr:street":"Morley;Queen St",
    "iso:country":"GB",
    "sg:address":"Units 3-4, Morley Market, Queen St, Morley",
    "sg:city":"Leeds",
    "sg:classifiers":[
        {
            "category":"Communications",
            "type":"Services"
        }
    ],
    "sg:phone":"+44 113 289 7775",
    "sg:postcode":"LS27 8EG",
    "sg:province":"West Yorkshire",
    "sg:tags":[
        "telecommunication"
    ],
    "wof:name":"Phone-acc",
    "wof:placetype":"venue"
},
  "geometry": {"coordinates":[-1.60242,53.746868],"type":"Point"}
}