{
  "type": "Feature",
  "properties": {
    "addr:full":"East Lodge House, 116 High Street Cranleigh Surrey GU6 8AJ",
    "addr:housenumber":"116",
    "addr:postcode":"gu6 8aj",
    "addr:street":"High Street",
    "iso:country":"GB",
    "sg:address":"East Lodge House, 116 High Street",
    "sg:city":"Cranleigh",
    "sg:classifiers":[
        {
            "category":"Professional",
            "subcategory":"Computer Services",
            "type":"Services"
        }
    ],
    "sg:phone":"+44 1483 273838",
    "sg:postcode":"GU6 8AJ",
    "sg:province":"Surrey",
    "sg:tags":[
        "system",
        "software"
    ],
    "wof:name":"Sweet Valley Solutions Ltd.",
    "wof:placetype":"venue"
},
  "geometry": {"coordinates":[-0.489334,51.141262],"type":"Point"}
}