{
  "type": "Feature",
  "properties": {
    "iso:country":"GB",
    "sg:address":"2 Brandwood Cotts, Brandwood",
    "sg:city":"Shrewsbury",
    "sg:classifiers":[
        {
            "category":"Building & Trades",
            "subcategory":"Cleaning & Sanitation",
            "type":"Services"
        }
    ],
    "sg:postcode":"SY4 3RF",
    "sg:province":"Shropshire",
    "sg:tags":[
        "sweep",
        "chimney"
    ],
    "wof:name":"A B Chimney Sweeps",
    "wof:placetype":"venue"
},
  "geometry": {"coordinates":[-2.7852199078,52.8325386047],"type":"Point"}
}