{
  "type": "Feature",
  "properties": {
    "addr:full":"Hillcrest Fraserburgh Aberdeenshire AB43 9NB",
    "addr:postcode":"ab43 9nb",
    "iso:country":"GB",
    "sg:address":"Hillcrest",
    "sg:city":"Fraserburgh",
    "sg:classifiers":[
        {
            "category":"Health Services",
            "subcategory":"Clinic",
            "type":"Services"
        }
    ],
    "sg:phone":"+44 1346 513151",
    "sg:postcode":"AB43 9NB",
    "sg:province":"Aberdeenshire",
    "sg:tags":[
        "nh"
    ],
    "wof:name":"Fraserburgh Clinic",
    "wof:placetype":"venue"
},
  "geometry": {"coordinates":[-2.015844,57.69442],"type":"Point"}
}