{
  "type": "Feature",
  "properties": {
    "addr:full":"Cobden House, 231 Roehampton Lane London Greater London SW15 4LB",
    "addr:housenumber":"231",
    "addr:postcode":"sw15 4lb",
    "addr:street":"Roehampton Lane",
    "iso:country":"GB",
    "sg:address":"Cobden House, 231 Roehampton Lane",
    "sg:city":"London",
    "sg:classifiers":[
        {
            "category":"Organizations",
            "subcategory":"Non-profit Organization",
            "type":"Services"
        }
    ],
    "sg:postcode":"SW15 4LB",
    "sg:province":"Greater London",
    "sg:tags":[
        "organisation",
        "voluntary",
        "charity"
    ],
    "wof:name":"The Cancer Prevention Research Trust",
    "wof:placetype":"venue"
},
  "geometry": {"coordinates":[-0.238815,51.449402],"type":"Point"}
}