{
  "type": "Feature",
  "properties": {
    "iso:country":"GB",
    "sg:address":"150 Meadfoot Road",
    "sg:city":"Coventry",
    "sg:classifiers":[
        {
            "category":"Manufacturing",
            "subcategory":"Wood Products",
            "type":"Manufacturing & Wholesale Goods"
        },
        {
            "category":"Building & Trades",
            "subcategory":"Construction",
            "type":"Services"
        }
    ],
    "sg:phone":"+44 24 7630 1342",
    "sg:postcode":"CV3 3DS",
    "sg:province":"Warwickshire",
    "sg:tags":[
        "cabinet",
        "joiner",
        "carpenter",
        "maker"
    ],
    "sg:website":"http://www.treasureshowcases.com",
    "wof:name":"Treasure Showcases",
    "wof:placetype":"venue"
},
  "geometry": {"coordinates":[-1.459283,52.389225],"type":"Point"}
}