{
  "type": "Feature",
  "properties": {
    "iso:country":"GB",
    "sg:address":"Market Place Farm, South Cave",
    "sg:city":"Brough",
    "sg:classifiers":[
        {
            "category":"Banks & Credit Unions",
            "subcategory":"Investment Brokerage",
            "type":"Services"
        }
    ],
    "sg:phone":"+44 1430 422216",
    "sg:postcode":"HU15 2AS",
    "sg:province":"East Riding of Yorkshire",
    "sg:tags":[
        "contractor"
    ],
    "wof:name":"Henry B Wilson",
    "wof:placetype":"venue"
},
  "geometry": {"coordinates":[-0.600922,53.770111],"type":"Point"}
}