{
  "type": "Feature",
  "properties": {
    "addr:full":"Shewalton Road, Riverside Business Park Irvine East Ayrshire KA11 5AJ",
    "addr:postcode":"ka11 5aj",
    "addr:street":"Shewalton Road",
    "iso:country":"GB",
    "sg:address":"Shewalton Road, Riverside Business Park",
    "sg:city":"Irvine",
    "sg:classifiers":[
        {
            "category":"Professional",
            "subcategory":"Business Services",
            "type":"Services"
        },
        {
            "category":"Train Station",
            "subcategory":"Rail",
            "type":"Transportation"
        }
    ],
    "sg:phone":"+44 1294 311002",
    "sg:postcode":"KA11 5AJ",
    "sg:province":"East Ayrshire",
    "sg:tags":[
        "caravan"
    ],
    "wof:name":"Eglinton Caravans",
    "wof:placetype":"venue"
},
  "geometry": {"coordinates":[-4.6557087898,55.5974731445],"type":"Point"}
}