{
  "type": "Feature",
  "properties": {
    "addr:full":"164 Cardigan Rd Leeds West Yorkshire LS6 1LL",
    "addr:housenumber":"164",
    "addr:postcode":"ls6 1ll",
    "addr:street":"Cardigan Rd",
    "iso:country":"GB",
    "sg:address":"164 Cardigan Rd",
    "sg:city":"Leeds",
    "sg:classifiers":[
        {
            "category":"Retail",
            "subcategory":"Repair Shop",
            "type":"Services"
        }
    ],
    "sg:phone":"+44 113 230 7277",
    "sg:postcode":"LS6 1LL",
    "sg:province":"West Yorkshire",
    "sg:tags":[
        "maintenance"
    ],
    "wof:name":"Protek Building & MaintenanceServices Ltd",
    "wof:placetype":"venue"
},
  "geometry": {"coordinates":[-1.575157,53.810307],"type":"Point"}
}