{
  "type": "Feature",
  "properties": {
    "addr:full":"23 Bridge Street Fakenham Norfolk NR21 9AG",
    "addr:housenumber":"23",
    "addr:postcode":"nr21 9ag",
    "addr:street":"Bridge Street",
    "iso:country":"GB",
    "sg:address":"23 Bridge Street",
    "sg:city":"Fakenham",
    "sg:classifiers":[
        {
            "category":"Home & Garden",
            "subcategory":"Carpets & Floor Coverings",
            "type":"Retail Goods"
        }
    ],
    "sg:postcode":"NR21 9AG",
    "sg:province":"Norfolk",
    "sg:tags":[
        "carpets",
        "rug",
        "matting"
    ],
    "wof:name":"Fakenham Carpet Centre",
    "wof:placetype":"venue"
},
  "geometry": {"coordinates":[0.8486940265,52.8294525146],"type":"Point"}
}