{
  "type": "Feature",
  "properties": {
    "iso:country":"GB",
    "sg:address":"71 Cavendish Rd",
    "sg:city":"Stockport",
    "sg:classifiers":[
        {
            "category":"Education",
            "subcategory":"Music School",
            "type":"Public Place"
        }
    ],
    "sg:postcode":"SK7 6HU",
    "sg:province":"Cheshire",
    "sg:tags":[
        "conservatory"
    ],
    "wof:name":"Avanti Uk",
    "wof:placetype":"venue"
},
  "geometry": {"coordinates":[-2.118729,53.370193],"type":"Point"}
}