{
  "type": "Feature",
  "properties": {
    "iso:country":"GB",
    "sg:address":"129-133 Green Lane",
    "sg:city":"Ilford",
    "sg:classifiers":[
        {
            "category":"Wholesale",
            "subcategory":"Scrap",
            "type":"Manufacturing & Wholesale Goods"
        }
    ],
    "sg:postcode":"IG1 1XN",
    "sg:province":"Essex",
    "sg:tags":[
        "breaker",
        "dismantlers"
    ],
    "wof:name":"South Park Motors Car Spares",
    "wof:placetype":"venue"
},
  "geometry": {"coordinates":[0.088838,51.559052],"type":"Point"}
}