{
  "type": "Feature",
  "properties": {
    "iso:country":"GB",
    "sg:address":"23 Long Street",
    "sg:city":"Dursley",
    "sg:classifiers":[
        {
            "category":"Personal",
            "subcategory":"Beauty Salon",
            "type":"Services"
        },
        {
            "category":"Personal",
            "subcategory":"Barber",
            "type":"Services"
        }
    ],
    "sg:phone":"+44 1453 542177",
    "sg:postcode":"GL11 4HL",
    "sg:province":"Gloucestershire",
    "sg:tags":[
        "unisex",
        "hairdresser"
    ],
    "wof:name":"Kingham & Spencer",
    "wof:placetype":"venue"
},
  "geometry": {"coordinates":[-2.352686,51.68206],"type":"Point"}
}