{
  "type": "Feature",
  "properties": {
    "addr:full":"P O Box 469 Addlestone Surrey KT15 3YB",
    "addr:housenumber":"469",
    "addr:postcode":"kt15 3yb",
    "addr:street":"P O Box",
    "iso:country":"GB",
    "sg:address":"P O Box 469",
    "sg:city":"Addlestone",
    "sg:classifiers":[
        {
            "category":"Professional",
            "type":"Services"
        }
    ],
    "sg:phone":"+44 1932 343604",
    "sg:postcode":"KT15 3YB",
    "sg:province":"Surrey",
    "sg:tags":[
        "entertainer"
    ],
    "wof:name":"Sticky Fingers Arts & Craft",
    "wof:placetype":"venue"
},
  "geometry": {"coordinates":[-0.5027490258,51.3477210999],"type":"Point"}
}