{
  "type": "Feature",
  "properties": {
    "iso:country":"GB",
    "sg:address":"Unit B Oakwood, Oakfield Industrial Estate",
    "sg:city":"Witney",
    "sg:classifiers":[
        {
            "category":"Professional",
            "subcategory":"Engineering",
            "type":"Services"
        }
    ],
    "sg:phone":"+44 1908 615232",
    "sg:postcode":"OX29 4TH",
    "sg:province":"Oxfordshire",
    "sg:tags":[
        "design",
        "engineer"
    ],
    "wof:name":"Newport Power Components Oxford Design",
    "wof:placetype":"venue"
},
  "geometry": {"coordinates":[-1.3778389692,51.7730979919],"type":"Point"}
}