{
  "type": "Feature",
  "properties": {
    "iso:country":"GB",
    "sg:address":"Riviera Ho, Marks View Business Centre, Pen Mill Trading Est",
    "sg:city":"Yeovil",
    "sg:classifiers":[
        {
            "category":"Shopping",
            "subcategory":"Beauty & Cosmetics",
            "type":"Retail Goods"
        }
    ],
    "sg:phone":"+44 1935 432330",
    "sg:postcode":"BA21 5HR",
    "sg:province":"Somerset",
    "sg:tags":[
        "equipment",
        "supply",
        "hairdressing"
    ],
    "wof:name":"Torbay Hairdressing Supplies (Yeovil) Ltd",
    "wof:placetype":"venue"
},
  "geometry": {"coordinates":[-2.6392920017,50.9484405518],"type":"Point"}
}