{
  "type": "Feature",
  "properties": {
    "iso:country":"GB",
    "sg:address":"Llandyfan",
    "sg:city":"Ammanford",
    "sg:classifiers":[
        {
            "category":"Bars & Pubs",
            "type":"Food & Drink"
        }
    ],
    "sg:postcode":"SA18 2UD",
    "sg:province":"Carmarthenshire",
    "sg:tags":[
        "pubs",
        "inn"
    ],
    "wof:name":"Thomas,Mary Annette,",
    "wof:placetype":"venue"
},
  "geometry": {"coordinates":[-3.95945,51.827179],"type":"Point"}
}