{
  "type": "Feature",
  "properties": {
    "addr:full":"The Court Yard, 76 Broad Street Bristol Gloucestershire BS37 6AG",
    "addr:housenumber":"76",
    "addr:postcode":"bs37 6ag",
    "addr:street":"Broad Street",
    "iso:country":"GB",
    "sg:address":"The Court Yard, 76 Broad Street",
    "sg:city":"Bristol",
    "sg:classifiers":[
        {
            "category":"Utilities",
            "type":"Services"
        }
    ],
    "sg:postcode":"BS37 6AG",
    "sg:province":"Gloucestershire",
    "sg:tags":[
        "internet"
    ],
    "wof:name":"At Info Ltd.",
    "wof:placetype":"venue"
},
  "geometry": {"coordinates":[-2.3922100067,51.5382194519],"type":"Point"}
}