{
  "type": "Feature",
  "properties": {
    "iso:country":"GB",
    "sg:address":"Denbigh House, Denbigh Rd, Bletchley",
    "sg:city":"Milton Keynes",
    "sg:classifiers":[
        {
            "category":"Professional",
            "subcategory":"Management & Consulting",
            "type":"Services"
        }
    ],
    "sg:phone":"+44 1908 371000",
    "sg:postcode":"MK1 1YP",
    "sg:province":"Buckinghamshire",
    "sg:tags":[
        "marketing",
        "consultant"
    ],
    "wof:name":"Workline",
    "wof:placetype":"venue"
},
  "geometry": {"coordinates":[-0.732679,52.00491],"type":"Point"}
}