{
  "type": "Feature",
  "properties": {
    "addr:full":"54 Mid Street Fraserburgh Aberdeenshire AB43 9EP",
    "addr:housenumber":"54",
    "addr:postcode":"ab43 9ep",
    "addr:street":"Mid Street",
    "iso:country":"GB",
    "sg:address":"54 Mid Street",
    "sg:city":"Fraserburgh",
    "sg:classifiers":[
        {
            "category":"Personal",
            "subcategory":"Beauty Salon",
            "type":"Services"
        }
    ],
    "sg:phone":"+44 1346 518569",
    "sg:postcode":"AB43 9EP",
    "sg:province":"Aberdeenshire",
    "sg:tags":[
        "unisex",
        "hairdresser"
    ],
    "wof:name":"The Kat's Whiskers",
    "wof:placetype":"venue"
},
  "geometry": {"coordinates":[-2.008177,57.692684],"type":"Point"}
}