{
  "type": "Feature",
  "properties": {
    "iso:country":"GB",
    "sg:address":"6 Crown Passage",
    "sg:city":"Westminster",
    "sg:classifiers":[
        {
            "category":"Home & Garden",
            "subcategory":"Building Materials",
            "type":"Retail Goods"
        }
    ],
    "sg:phone":"+44 20 7839 3253",
    "sg:postcode":"SW1Y 6PP",
    "sg:province":"Greater London",
    "sg:tags":[
        "hinge"
    ],
    "wof:name":"Crown Security Centres",
    "wof:placetype":"venue"
},
  "geometry": {"coordinates":[-0.1376039982,51.505897522],"type":"Point"}
}