{
  "type": "Feature",
  "properties": {
    "addr:full":"1a Winterton House, High Street Westerham Kent TN16 1AJ",
    "addr:housenumber":"1a;house",
    "addr:postcode":"tn16 1aj",
    "addr:street":"Winterton;High Street",
    "iso:country":"GB",
    "sg:address":"1a Winterton House, High Street",
    "sg:city":"Westerham",
    "sg:classifiers":[
        {
            "category":"Shopping",
            "subcategory":"Comic Books",
            "type":"Retail Goods"
        }
    ],
    "sg:postcode":"TN16 1AJ",
    "sg:province":"Kent",
    "sg:tags":[
        "jeweller"
    ],
    "wof:name":"Facets Jewellers",
    "wof:placetype":"venue"
},
  "geometry": {"coordinates":[0.071265,51.267075],"type":"Point"}
}