{
  "type": "Feature",
  "properties": {
    "addr:full":"43 Hands Walk London Greater London E16 3RA",
    "addr:housenumber":"43",
    "addr:postcode":"e16 3ra",
    "addr:street":"Hands Walk",
    "iso:country":"GB",
    "sg:address":"43 Hands Walk",
    "sg:city":"London",
    "sg:classifiers":[
        {
            "category":"Education",
            "subcategory":"School",
            "type":"Public Place"
        }
    ],
    "sg:postcode":"E16 3RA",
    "sg:province":"Greater London",
    "sg:tags":[
        "local",
        "authority"
    ],
    "wof:name":"Little Saints Nursery School Ltd.",
    "wof:placetype":"venue"
},
  "geometry": {"coordinates":[0.0217,51.513611],"type":"Point"}
}