{
  "type": "Feature",
  "properties": {
    "addr:full":"13 New Road Hebden Bridge West Yorkshire HX7 8AD",
    "addr:housenumber":"13",
    "addr:postcode":"hx7 8ad",
    "addr:street":"New Road",
    "iso:country":"GB",
    "sg:address":"13 New Road",
    "sg:city":"Hebden Bridge",
    "sg:classifiers":[
        {
            "category":"Professional",
            "subcategory":"Accounting & Tax Preparation",
            "type":"Services"
        }
    ],
    "sg:postcode":"HX7 8AD",
    "sg:province":"West Yorkshire",
    "sg:tags":[
        "accountant"
    ],
    "wof:name":"Mitaz Ltd.",
    "wof:placetype":"venue"
},
  "geometry": {"coordinates":[-2.010969,53.740265],"type":"Point"}
}