{
  "type": "Feature",
  "properties": {
    "iso:country":"GB",
    "sg:address":"2-12 Ruby Street",
    "sg:city":"London",
    "sg:classifiers":[
        {
            "category":"Retail",
            "subcategory":"Auto Repair",
            "type":"Services"
        }
    ],
    "sg:phone":"+44 20 7732 8884",
    "sg:postcode":"SE15 1LL",
    "sg:province":"Greater London",
    "sg:tags":[
        "modification",
        "garage"
    ],
    "wof:name":"Friendly Service Centre",
    "wof:placetype":"venue"
},
  "geometry": {"coordinates":[-0.061991,51.482147],"type":"Point"}
}