{
  "type": "Feature",
  "properties": {
    "addr:full":"Alma Road, Newhall Swadlincote Derbyshire DE11 0SD",
    "addr:postcode":"de11 0sd",
    "addr:street":"Alma Road",
    "iso:country":"GB",
    "sg:address":"Alma Road, Newhall",
    "sg:city":"Swadlincote",
    "sg:classifiers":[
        {
            "category":"Retail",
            "subcategory":"Auto Repair",
            "type":"Services"
        }
    ],
    "sg:phone":"+44 1283 552029",
    "sg:postcode":"DE11 0SD",
    "sg:province":"Derbyshire",
    "sg:tags":[
        "modification",
        "garage"
    ],
    "wof:name":"Hawkins Motors",
    "wof:placetype":"venue"
},
  "geometry": {"coordinates":[-1.5739979744,52.7852592468],"type":"Point"}
}