{
  "type": "Feature",
  "properties": {
    "addr:full":"Bradley Grange, Bradley Lane, Rufforth York North Yorkshire YO23 3QW",
    "addr:postcode":"yo23 3qw",
    "addr:street":"Bradley Lane",
    "iso:country":"GB",
    "sg:address":"Bradley Grange, Bradley Lane, Rufforth",
    "sg:city":"York",
    "sg:classifiers":[
        {
            "category":"Shopping",
            "subcategory":"Musical Instruments",
            "type":"Retail Goods"
        },
        {
            "category":"Professional",
            "subcategory":"Employment Agencies",
            "type":"Services"
        }
    ],
    "sg:phone":"+44 1904 738309",
    "sg:postcode":"YO23 3QW",
    "sg:province":"North Yorkshire",
    "sg:tags":[
        "sale",
        "organ",
        "accessory"
    ],
    "wof:name":"A C Pilmer Automatic Music Leasing Ltd",
    "wof:placetype":"venue"
},
  "geometry": {"coordinates":[-1.19284,53.954292],"type":"Point"}
}