{
  "type": "Feature",
  "properties": {
    "addr:full":"31 Castlegate York North Yorkshire YO1 9RN",
    "addr:housenumber":"31",
    "addr:postcode":"yo1 9rn",
    "addr:street":"Castlegate",
    "iso:country":"GB",
    "sg:address":"31 Castlegate",
    "sg:city":"York",
    "sg:classifiers":[
        {
            "category":"Restaurant",
            "type":"Food & Drink"
        },
        {
            "category":"Cafe",
            "type":"Food & Drink"
        }
    ],
    "sg:phone":"+44 1904 655716",
    "sg:postcode":"YO1 9RN",
    "sg:province":"North Yorkshire",
    "sg:tags":[
        "tea",
        "room"
    ],
    "wof:name":"Andros Coffee Lounge Ltd.",
    "wof:placetype":"venue"
},
  "geometry": {"coordinates":[-1.0799150467,53.9566421509],"type":"Point"}
}