{
  "type": "Feature",
  "properties": {
    "addr:full":"52 Market Place, South Cave Brough East Riding of Yorkshire HU15 2AT",
    "addr:housenumber":"52",
    "addr:postcode":"hu15 2at",
    "addr:street":"Market Place",
    "iso:country":"GB",
    "sg:address":"52 Market Place, South Cave",
    "sg:city":"Brough",
    "sg:classifiers":[
        {
            "category":"Travel",
            "subcategory":"Hotels & Motels",
            "type":"Entertainment"
        }
    ],
    "sg:phone":"+44 1430 422275",
    "sg:postcode":"HU15 2AT",
    "sg:province":"East Riding of Yorkshire",
    "wof:name":"Steve & Pauline Ellerington",
    "wof:placetype":"venue"
},
  "geometry": {"coordinates":[-0.600688,53.770126],"type":"Point"}
}