{
  "type": "Feature",
  "properties": {
    "iso:country":"GB",
    "sg:address":"65-67 East Street",
    "sg:city":"Blandford Forum",
    "sg:classifiers":[
        {
            "category":"Fast Food",
            "type":"Food & Drink"
        }
    ],
    "sg:phone":"+44 1258 454552",
    "sg:postcode":"DT11 7DX",
    "sg:province":"Dorset",
    "sg:tags":[
        "away",
        "meal",
        "outlet",
        "take"
    ],
    "wof:name":"Ottoman Kebab",
    "wof:placetype":"venue"
},
  "geometry": {"coordinates":[-2.1625750065,50.8560523987],"type":"Point"}
}