{
  "type": "Feature",
  "properties": {
    "iso:country":"GB",
    "sg:address":"Unit 6 213 Harrison Rd",
    "sg:city":"Leicester",
    "sg:classifiers":[
        {
            "category":"Manufacturing",
            "subcategory":"Rubber & Plastics",
            "type":"Manufacturing & Wholesale Goods"
        }
    ],
    "sg:phone":"+44 116 266 8121",
    "sg:postcode":"LE4 6QN",
    "sg:province":"Leicestershire",
    "sg:tags":[
        "injection",
        "moulding"
    ],
    "wof:name":"Virdee Plastics",
    "wof:placetype":"venue"
},
  "geometry": {"coordinates":[-1.113876,52.655205],"type":"Point"}
}