{
  "type": "Feature",
  "properties": {
    "iso:country":"GB",
    "sg:address":"King Street, Laugharne",
    "sg:city":"Carmarthen",
    "sg:classifiers":[
        {
            "category":"Bars & Pubs",
            "type":"Food & Drink"
        }
    ],
    "sg:phone":"+44 1994 427320",
    "sg:postcode":"SA33 4RY",
    "sg:province":"Carmarthenshire",
    "sg:tags":[
        "pubs",
        "inn"
    ],
    "wof:name":"Browns Hotel",
    "wof:placetype":"venue"
},
  "geometry": {"coordinates":[-4.462729,51.771809],"type":"Point"}
}