{
  "type": "Feature",
  "properties": {
    "iso:country":"GB",
    "sg:address":"Unit 2b Meteor Centre, Sir Frank Whittle Road",
    "sg:city":"Derby",
    "sg:classifiers":[
        {
            "category":"Home & Garden",
            "subcategory":"Home Furnishings",
            "type":"Retail Goods"
        }
    ],
    "sg:phone":"+44 1332 835286",
    "sg:postcode":"DE21 4SY",
    "sg:province":"Derbyshire",
    "sg:tags":[
        "furnishers",
        "planner",
        "kitchen"
    ],
    "wof:name":"Moben Kitchens",
    "wof:placetype":"venue"
},
  "geometry": {"coordinates":[-1.459504,52.947895],"type":"Point"}
}