{
  "type": "Feature",
  "properties": {
    "addr:full":"140 High Street, Wivenhoe Colchester Essex CO7 9AF",
    "addr:housenumber":"140",
    "addr:postcode":"co7 9af",
    "addr:street":"High Street",
    "iso:country":"GB",
    "sg:address":"140 High Street, Wivenhoe",
    "sg:city":"Colchester",
    "sg:classifiers":[
        {
            "category":"Travel",
            "subcategory":"Hotels & Motels",
            "type":"Entertainment"
        }
    ],
    "sg:phone":"+44 1206 822424",
    "sg:postcode":"CO7 9AF",
    "sg:province":"Essex",
    "wof:name":"The Park Hotel",
    "wof:placetype":"venue"
},
  "geometry": {"coordinates":[0.959938,51.859081],"type":"Point"}
}