{
  "type": "Feature",
  "properties": {
    "addr:full":"1 Clifton Lane Rotherham South Yorkshire S65 2AA",
    "addr:housenumber":"1",
    "addr:postcode":"s65 2aa",
    "addr:street":"Clifton Lane",
    "iso:country":"GB",
    "sg:address":"1 Clifton Lane",
    "sg:city":"Rotherham",
    "sg:classifiers":[
        {
            "category":"Organizations",
            "subcategory":"Membership Organization",
            "type":"Services"
        }
    ],
    "sg:phone":"+44 1709 370763",
    "sg:postcode":"S65 2AA",
    "sg:province":"South Yorkshire",
    "sg:tags":[
        "club",
        "social"
    ],
    "wof:name":"Rotherham Rugby Club",
    "wof:placetype":"venue"
},
  "geometry": {"coordinates":[-1.350034,53.430939],"type":"Point"}
}