{
  "type": "Feature",
  "properties": {
    "addr:full":"111 Frithville Gdns London Greater London W12 7JG",
    "addr:housenumber":"111",
    "addr:postcode":"w12 7jg",
    "addr:street":"Frithville Gdns",
    "iso:country":"GB",
    "sg:address":"111 Frithville Gdns",
    "sg:city":"London",
    "sg:classifiers":[
        {
            "category":"Wholesale",
            "subcategory":"Music Publishers",
            "type":"Manufacturing & Wholesale Goods"
        }
    ],
    "sg:phone":"+44 20 8600 3400",
    "sg:postcode":"W12 7JG",
    "sg:province":"Greater London",
    "sg:tags":[
        "record"
    ],
    "wof:name":"China Records Ltd",
    "wof:placetype":"venue"
},
  "geometry": {"coordinates":[-0.227487,51.508511],"type":"Point"}
}