{
  "type": "Feature",
  "properties": {
    "addr:full":"37 Seymour Terr, Seymour St Liverpool Merseyside L3 5PE",
    "addr:housenumber":"37",
    "addr:postcode":"l3 5pe",
    "addr:street":"Seymour Terr Seymour St",
    "iso:country":"GB",
    "sg:address":"37 Seymour Terr, Seymour St",
    "sg:city":"Liverpool",
    "sg:classifiers":[
        {
            "category":"Professional",
            "subcategory":"Accounting & Tax Preparation",
            "type":"Services"
        }
    ],
    "sg:phone":"+44 151 709 5056",
    "sg:postcode":"L3 5PE",
    "sg:province":"Merseyside",
    "sg:tags":[
        "accountant"
    ],
    "wof:name":"Hill & Harrison",
    "wof:placetype":"venue"
},
  "geometry": {"coordinates":[-2.9743280411,53.4088363647],"type":"Point"}
}