{
  "type": "Feature",
  "properties": {
    "addr:full":"3 Chestnut Gro London Greater London SW12 8JA",
    "addr:housenumber":"3",
    "addr:postcode":"sw12 8ja",
    "addr:street":"Chestnut Gro",
    "iso:country":"GB",
    "sg:address":"3 Chestnut Gro",
    "sg:city":"London",
    "sg:classifiers":[
        {
            "category":"Retail",
            "subcategory":"Laundry & Dry Cleaning",
            "type":"Services"
        }
    ],
    "sg:phone":"+44 20 8673 7407",
    "sg:postcode":"SW12 8JA",
    "sg:province":"Greater London",
    "sg:tags":[
        "launderette"
    ],
    "wof:name":"Curtneal Launderettes",
    "wof:placetype":"venue"
},
  "geometry": {"coordinates":[-0.153874,51.44408],"type":"Point"}
}