{
  "type": "Feature",
  "properties": {
    "addr:full":"37 Merrial Street Newcastle Staffordshire ST5 2AE",
    "addr:housenumber":"37",
    "addr:postcode":"st5 2ae",
    "addr:street":"Merrial Street",
    "iso:country":"GB",
    "sg:address":"37 Merrial Street",
    "sg:city":"Newcastle",
    "sg:classifiers":[
        {
            "category":"Home & Garden",
            "subcategory":"Furniture",
            "type":"Retail Goods"
        }
    ],
    "sg:phone":"+44 1782 610123",
    "sg:postcode":"ST5 2AE",
    "sg:province":"Staffordshire",
    "wof:name":"Curtains Plus",
    "wof:placetype":"venue"
},
  "geometry": {"coordinates":[-2.2275168896,53.0122566223],"type":"Point"}
}