{
  "type": "Feature",
  "properties": {
    "iso:country":"GB",
    "sg:address":"Stephens Way, Pensarn",
    "sg:city":"Carmarthen",
    "sg:classifiers":[
        {
            "category":"Autos & Motor Vehicles",
            "subcategory":"Auto Supplies",
            "type":"Retail Goods"
        }
    ],
    "sg:phone":"+44 1267 237977",
    "sg:postcode":"SA31 2BT",
    "sg:province":"Carmarthenshire",
    "sg:tags":[
        "component"
    ],
    "wof:name":"Brown Bros",
    "wof:placetype":"venue"
},
  "geometry": {"coordinates":[-4.30468,51.852463],"type":"Point"}
}