{
  "type": "Feature",
  "properties": {
    "addr:full":"Bevois Valley Road Southampton Hampshire SO14 0LA",
    "addr:postcode":"so14 0la",
    "addr:street":"Bevois Valley Road",
    "iso:country":"GB",
    "sg:address":"Bevois Valley Road",
    "sg:city":"Southampton",
    "sg:classifiers":[
        {
            "category":"Retail",
            "subcategory":"Auto Repair",
            "type":"Services"
        }
    ],
    "sg:phone":"+44 23 8090 4477",
    "sg:postcode":"SO14 0LA",
    "sg:province":"Hampshire",
    "sg:tags":[
        "body",
        "car"
    ],
    "wof:name":"Bevois Valley Autos",
    "wof:placetype":"venue"
},
  "geometry": {"coordinates":[-1.395482,50.918091],"type":"Point"}
}