{
  "type": "Feature",
  "properties": {
    "iso:country":"GB",
    "sg:address":"West Hoathly Rd",
    "sg:city":"East Grinstead",
    "sg:classifiers":[
        {
            "category":"Restaurant",
            "type":"Food & Drink"
        }
    ],
    "sg:phone":"+44 1342 317990",
    "sg:postcode":"RH19 4NE",
    "sg:province":"East Sussex",
    "wof:name":"National Trust (The)",
    "wof:placetype":"venue"
},
  "geometry": {"coordinates":[-0.0120789995,51.113735199],"type":"Point"}
}