{
  "type": "Feature",
  "properties": {
    "addr:full":"Apple Motors, Churnetside Garage, Broads Bridge Leek Staffordshire ST13 8SA",
    "addr:postcode":"st13 8sa",
    "addr:street":"Bridge",
    "iso:country":"GB",
    "sg:address":"Apple Motors, Churnetside Garage, Broads Bridge",
    "sg:city":"Leek",
    "sg:classifiers":[
        {
            "category":"Wholesale",
            "subcategory":"Scrap",
            "type":"Manufacturing & Wholesale Goods"
        }
    ],
    "sg:postcode":"ST13 8SA",
    "sg:province":"Staffordshire",
    "sg:tags":[
        "breaker",
        "dismantlers"
    ],
    "wof:name":"Ford Granada Specialists",
    "wof:placetype":"venue"
},
  "geometry": {"coordinates":[-2.020884,53.106476],"type":"Point"}
}