{
  "type": "Feature",
  "properties": {
    "addr:full":"The Vach Farm Oswestry Shropshire SY11 3ET",
    "addr:postcode":"sy11 3et",
    "iso:country":"GB",
    "sg:address":"The Vach Farm",
    "sg:city":"Oswestry",
    "sg:classifiers":[
        {
            "category":"Farming",
            "subcategory":"Dairy Farm",
            "type":"Manufacturing & Wholesale Goods"
        }
    ],
    "sg:phone":"+44 1691 774362",
    "sg:postcode":"SY11 3ET",
    "sg:province":"Shropshire",
    "wof:name":"D Lloyd",
    "wof:placetype":"venue"
},
  "geometry": {"coordinates":[-3.037184,52.894131],"type":"Point"}
}