{
  "type": "Feature",
  "properties": {
    "addr:full":"Unit 14b St Nicholas Arc Lancaster Lancashire LA1 1ND",
    "addr:housenumber":"unit 14b",
    "addr:postcode":"la1 1nd",
    "addr:street":"St;Arc",
    "iso:country":"GB",
    "sg:address":"Unit 14b St Nicholas Arc",
    "sg:city":"Lancaster",
    "sg:classifiers":[
        {
            "category":"Shopping",
            "subcategory":"Bicycles & Sporting Goods",
            "type":"Retail Goods"
        }
    ],
    "sg:phone":"+44 1524 841043",
    "sg:postcode":"LA1 1ND",
    "sg:province":"Lancashire",
    "sg:tags":[
        "equipment",
        "camping"
    ],
    "wof:name":"Millets Leisure",
    "wof:placetype":"venue"
},
  "geometry": {"coordinates":[-2.799029,54.044537],"type":"Point"}
}