{
  "type": "Feature",
  "properties": {
    "addr:full":"9 Turnpin Lane, Greenwich London Greater London SE10 9JA",
    "addr:housenumber":"9",
    "addr:postcode":"se10 9ja",
    "addr:street":"Turnpin Lane",
    "iso:country":"GB",
    "sg:address":"9 Turnpin Lane, Greenwich",
    "sg:city":"London",
    "sg:classifiers":[
        {
            "category":"Food & Beverages",
            "subcategory":"Bakery",
            "type":"Retail Goods"
        }
    ],
    "sg:phone":"+44 20 8853 2018",
    "sg:postcode":"SE10 9JA",
    "sg:province":"Greater London",
    "sg:tags":[
        "baker"
    ],
    "wof:name":"Melissa's",
    "wof:placetype":"venue"
},
  "geometry": {"coordinates":[-0.009083,51.481281],"type":"Point"}
}