{
  "type": "Feature",
  "properties": {
    "addr:full":"The Bryans Corner Dalkeith City of Edinburgh EH22 4PT",
    "addr:postcode":"eh22 4pt",
    "iso:country":"GB",
    "sg:address":"The Bryans Corner",
    "sg:city":"Dalkeith",
    "sg:classifiers":[
        {
            "category":"Fast Food",
            "type":"Food & Drink"
        }
    ],
    "sg:phone":"+44 131 663 6267",
    "sg:postcode":"EH22 4PT",
    "sg:province":"City of Edinburgh",
    "sg:tags":[
        "away",
        "take"
    ],
    "wof:name":"Mighty Bite The",
    "wof:placetype":"venue"
},
  "geometry": {"coordinates":[-3.065169,55.871269],"type":"Point"}
}