{
  "type": "Feature",
  "properties": {
    "iso:country":"GB",
    "sg:address":"Grand Floor Unit B, 443-449 Holloway Road",
    "sg:city":"London",
    "sg:classifiers":[
        {
            "category":"Manufacturing",
            "subcategory":"Metals",
            "type":"Manufacturing & Wholesale Goods"
        },
        {
            "category":"Professional",
            "subcategory":"Engineering",
            "type":"Services"
        }
    ],
    "sg:phone":"+44 20 7263 7017",
    "sg:postcode":"N7 6LJ",
    "sg:province":"Greater London",
    "sg:tags":[
        "work",
        "sheet",
        "engineer"
    ],
    "wof:name":"Dar-Val Engineering Ltd.",
    "wof:placetype":"venue"
},
  "geometry": {"coordinates":[-0.1145339981,51.5543899536],"type":"Point"}
}