{
  "type": "Feature",
  "properties": {
    "iso:country":"GB",
    "sg:address":"3 Saxon Close",
    "sg:city":"Waterlooville",
    "sg:classifiers":[
        {
            "category":"Arts & Performance",
            "subcategory":"Music",
            "type":"Entertainment"
        }
    ],
    "sg:phone":"+44 23 9235 9612",
    "sg:postcode":"PO8 0JT",
    "sg:province":"Hampshire",
    "sg:tags":[
        "mobile",
        "disco"
    ],
    "wof:name":"P.S Discos",
    "wof:placetype":"venue"
},
  "geometry": {"coordinates":[-0.999727,50.933811],"type":"Point"}
}