{
  "type": "Feature",
  "properties": {
    "addr:full":"4b Humphrey Street Swansea Neath Port Talbot SA1 6BG",
    "addr:housenumber":"4b",
    "addr:postcode":"sa1 6bg",
    "addr:street":"Humphrey Street",
    "iso:country":"GB",
    "sg:address":"4b Humphrey Street",
    "sg:city":"Swansea",
    "sg:classifiers":[
        {
            "category":"Shopping",
            "subcategory":"Florist",
            "type":"Retail Goods"
        }
    ],
    "sg:phone":"+44 1792 464202",
    "sg:postcode":"SA1 6BG",
    "sg:province":"Neath Port Talbot",
    "wof:name":"Patrica Jaynes Florists",
    "wof:placetype":"venue"
},
  "geometry": {"coordinates":[-3.955159,51.620632],"type":"Point"}
}