{
  "type": "Feature",
  "properties": {
    "iso:country":"GB",
    "sg:address":"104-106 Queens Promenade",
    "sg:city":"Blackpool",
    "sg:classifiers":[
        {
            "category":"Travel",
            "subcategory":"Hotels & Motels",
            "type":"Entertainment"
        }
    ],
    "sg:phone":"+44 1253 351396",
    "sg:postcode":"FY2 9NX",
    "sg:province":"Lancashire",
    "wof:name":"Bona Vista Hotel",
    "wof:placetype":"venue"
},
  "geometry": {"coordinates":[-3.054027,53.841663],"type":"Point"}
}