{
  "type": "Feature",
  "properties": {
    "iso:country":"GB",
    "sg:address":"69 Station Road, Cheadle Hulme",
    "sg:city":"Cheadle",
    "sg:classifiers":[
        {
            "category":"Shopping",
            "subcategory":"Florist",
            "type":"Retail Goods"
        }
    ],
    "sg:phone":"+44 161 485 8713",
    "sg:postcode":"SK8 7AA",
    "sg:province":"Cheshire",
    "wof:name":"Daisies",
    "wof:placetype":"venue"
},
  "geometry": {"coordinates":[-2.185287,53.373886],"type":"Point"}
}