{
  "type": "Feature",
  "properties": {
    "addr:full":"425 Manchester Road, Paddington Warrington Cheshire WA1 3LR",
    "addr:housenumber":"425",
    "addr:postcode":"wa1 3lr",
    "addr:street":"Manchester Road",
    "iso:country":"GB",
    "sg:address":"425 Manchester Road, Paddington",
    "sg:city":"Warrington",
    "sg:classifiers":[
        {
            "category":"Retail",
            "subcategory":"Auto Repair",
            "type":"Services"
        }
    ],
    "sg:phone":"+44 1925 815004",
    "sg:postcode":"WA1 3LR",
    "sg:province":"Cheshire",
    "sg:tags":[
        "body",
        "car",
        "repairer"
    ],
    "wof:name":"Mainland Bodycare Centre",
    "wof:placetype":"venue"
},
  "geometry": {"coordinates":[-2.55624,53.397457],"type":"Point"}
}