{
  "type": "Feature",
  "properties": {
    "iso:country":"GB",
    "sg:address":"West Hamsteels Farm, Hamsteels Lane, Quebec",
    "sg:city":"Durham",
    "sg:classifiers":[
        {
            "category":"Recreation",
            "subcategory":"Dog Park",
            "type":"Entertainment"
        }
    ],
    "sg:phone":"+44 1207 520224",
    "sg:postcode":"DH7 9RS",
    "sg:province":"Durham",
    "wof:name":"Pets Parlour",
    "wof:placetype":"venue"
},
  "geometry": {"coordinates":[-1.720379,54.787754],"type":"Point"}
}