{
  "type": "Feature",
  "properties": {
    "addr:full":"27 Kingsley Park Avenue, Millhouses Sheffield South Yorkshire S7 2HG",
    "addr:housenumber":"27",
    "addr:postcode":"s7 2hg",
    "addr:street":"Kingsley Park Avenue Millhouses",
    "iso:country":"GB",
    "sg:address":"27 Kingsley Park Avenue, Millhouses",
    "sg:city":"Sheffield",
    "sg:classifiers":[
        {
            "category":"Professional",
            "subcategory":"Computer Services",
            "type":"Services"
        }
    ],
    "sg:postcode":"S7 2HG",
    "sg:province":"South Yorkshire",
    "sg:tags":[
        "system",
        "software"
    ],
    "wof:name":"Sheffield City Opera Ltd.",
    "wof:placetype":"venue"
},
  "geometry": {"coordinates":[-1.505159,53.348534],"type":"Point"}
}