{
  "type": "Feature",
  "properties": {
    "iso:country":"GB",
    "sg:address":"Rhiw-bridwell Farm, Cross Inn",
    "sg:city":"Pontyclun",
    "sg:classifiers":[
        {
            "category":"Utilities",
            "subcategory":"Refuse",
            "type":"Services"
        }
    ],
    "sg:postcode":"CF72 8LU",
    "sg:province":"Bridgend",
    "sg:tags":[
        "disposal",
        "waste"
    ],
    "wof:name":"Total Growth Plant",
    "wof:placetype":"venue"
},
  "geometry": {"coordinates":[-3.365799,51.536343],"type":"Point"}
}