{
  "type": "Feature",
  "properties": {
    "iso:country":"GB",
    "sg:address":"81 Hamilton Road",
    "sg:city":"Motherwell",
    "sg:classifiers":[
        {
            "category":"Autos & Motor Vehicles",
            "subcategory":"Auto Supplies",
            "type":"Retail Goods"
        }
    ],
    "sg:phone":"+44 1698 230302",
    "sg:postcode":"ML1 3DQ",
    "sg:province":"North Lanarkshire",
    "sg:tags":[
        "gearbox"
    ],
    "wof:name":"David Brown Radicon",
    "wof:placetype":"venue"
},
  "geometry": {"coordinates":[-3.995446,55.789379],"type":"Point"}
}