{
  "type": "Feature",
  "properties": {
    "iso:country":"GB",
    "sg:address":"Hodder Avenue",
    "sg:city":"Chorley",
    "sg:classifiers":[
        {
            "category":"Social Services",
            "subcategory":"Adult Care",
            "type":"Services"
        },
        {
            "category":"Government",
            "subcategory":"Office",
            "type":"Public Place"
        }
    ],
    "sg:phone":"+44 1257 264018",
    "sg:postcode":"PR7 3PH",
    "sg:province":"Lancashire",
    "sg:tags":[
        "housing",
        "local",
        "sheltered"
    ],
    "wof:name":"Douglas House Sheltered Housing",
    "wof:placetype":"venue"
},
  "geometry": {"coordinates":[-2.6427791119,53.6398735046],"type":"Point"}
}