{
  "type": "Feature",
  "properties": {
    "addr:full":"10 St Wilfreds Gro, Harehills Leeds West Yorkshire LS8 3JP",
    "addr:housenumber":"10",
    "addr:postcode":"ls8 3jp",
    "addr:street":"St Wilfreds Gro",
    "iso:country":"GB",
    "sg:address":"10 St Wilfreds Gro, Harehills",
    "sg:city":"Leeds",
    "sg:classifiers":[
        {
            "category":"Building & Trades",
            "subcategory":"Landscaping Services",
            "type":"Services"
        }
    ],
    "sg:phone":"+44 113 228 1563",
    "sg:postcode":"LS8 3JP",
    "sg:province":"West Yorkshire",
    "sg:tags":[
        "forestry",
        "tree"
    ],
    "wof:name":"North Tree Services",
    "wof:placetype":"venue"
},
  "geometry": {"coordinates":[-1.508655,53.815357],"type":"Point"}
}