{
  "type": "Feature",
  "properties": {
    "addr:full":"229 Strathmore Avenue Dundee Dundee City DD3 6SN",
    "addr:housenumber":"229",
    "addr:postcode":"dd3 6sn",
    "addr:street":"Strathmore Avenue",
    "iso:country":"GB",
    "sg:address":"229 Strathmore Avenue",
    "sg:city":"Dundee",
    "sg:classifiers":[
        {
            "category":"Shopping",
            "subcategory":"Used Merchandise",
            "type":"Retail Goods"
        }
    ],
    "sg:postcode":"DD3 6SN",
    "sg:province":"Dundee City",
    "sg:tags":[
        "shop",
        "second-hand"
    ],
    "wof:name":"A B S",
    "wof:placetype":"venue"
},
  "geometry": {"coordinates":[-2.9943079948,56.4745063782],"type":"Point"}
}