{
  "type": "Feature",
  "properties": {
    "addr:full":"52 Seafield Road, Longman Industrial Estate Inverness Highland IV1 1SG",
    "addr:housenumber":"52",
    "addr:postcode":"iv1 1sg",
    "addr:street":"Seafield Road;Industrial Estate",
    "iso:country":"GB",
    "sg:address":"52 Seafield Road, Longman Industrial Estate",
    "sg:city":"Inverness",
    "sg:classifiers":[
        {
            "category":"Building & Trades",
            "subcategory":"Cleaning & Sanitation",
            "type":"Services"
        }
    ],
    "sg:phone":"+44 1463 715087",
    "sg:postcode":"IV1 1SG",
    "sg:province":"Highland",
    "sg:tags":[
        "commercial"
    ],
    "wof:name":"Highland Contract Services",
    "wof:placetype":"venue"
},
  "geometry": {"coordinates":[-4.216668,57.487297],"type":"Point"}
}