{
  "type": "Feature",
  "properties": {
    "iso:country":"GB",
    "sg:address":"11a High Street, Totton",
    "sg:city":"Southampton",
    "sg:classifiers":[
        {
            "category":"Professional",
            "subcategory":"Computer Services",
            "type":"Services"
        }
    ],
    "sg:phone":"+44 23 8084 1123",
    "sg:postcode":"SO40 9HL",
    "sg:province":"Hampshire",
    "sg:tags":[
        "system",
        "software"
    ],
    "wof:name":"C I M Services Ltd.",
    "wof:placetype":"venue"
},
  "geometry": {"coordinates":[-1.484371,50.916508],"type":"Point"}
}