{
  "type": "Feature",
  "properties": {
    "addr:full":"920 Shettleston Rd Glasgow Glasgow City G32 7XW",
    "addr:housenumber":"920",
    "addr:postcode":"g32 7xw",
    "addr:street":"Shettleston Rd",
    "iso:country":"GB",
    "sg:address":"920 Shettleston Rd",
    "sg:city":"Glasgow",
    "sg:classifiers":[
        {
            "category":"Retail",
            "subcategory":"Laundry & Dry Cleaning",
            "type":"Services"
        }
    ],
    "sg:phone":"+44 141 778 4584",
    "sg:postcode":"G32 7XW",
    "sg:province":"Glasgow City",
    "sg:tags":[
        "alteration"
    ],
    "wof:name":"Johnson Cleaners UK Ltd",
    "wof:placetype":"venue"
},
  "geometry": {"coordinates":[-4.173455,55.851833],"type":"Point"}
}