{
  "type": "Feature",
  "properties": {
    "addr:full":"Unit 5 Station Estate, Off Whitley Road Leeds West Yorkshire LS12 3HQ",
    "addr:housenumber":"unit 5;estate",
    "addr:postcode":"ls12 3hq",
    "addr:street":"Off Whitley Road",
    "iso:country":"GB",
    "sg:address":"Unit 5 Station Estate, Off Whitley Road",
    "sg:city":"Leeds",
    "sg:classifiers":[
        {
            "category":"Professional",
            "subcategory":"Printing & Photocopies",
            "type":"Services"
        }
    ],
    "sg:postcode":"LS12 3HQ",
    "sg:province":"West Yorkshire",
    "sg:tags":[
        "plate",
        "lithographic",
        "maker"
    ],
    "wof:name":"Light on Film Ltd.",
    "wof:placetype":"venue"
},
  "geometry": {"coordinates":[-1.5955660343,53.7959365845],"type":"Point"}
}