{
  "type": "Feature",
  "properties": {
    "addr:full":"Parkside House, Old Stafford Road, Coven Wolverhampton Staffordshire WV10 7PH",
    "addr:postcode":"wv10 7ph",
    "addr:street":"Old Stafford Road Coven",
    "iso:country":"GB",
    "sg:address":"Parkside House, Old Stafford Road, Coven",
    "sg:city":"Wolverhampton",
    "sg:classifiers":[
        {
            "category":"Manufacturing",
            "subcategory":"Tools & Machinery",
            "type":"Manufacturing & Wholesale Goods"
        }
    ],
    "sg:phone":"+44 1902 791289",
    "sg:postcode":"WV10 7PH",
    "sg:province":"Staffordshire",
    "sg:tags":[
        "society",
        "friendly"
    ],
    "wof:name":"Giles Lovell Ltd.",
    "wof:placetype":"venue"
},
  "geometry": {"coordinates":[-2.1266639233,52.6516609192],"type":"Point"}
}