{
  "type": "Feature",
  "properties": {
    "addr:full":"46-48 London Rd Carlisle Cumbria CA1 2EL",
    "addr:housenumber":"46-48",
    "addr:postcode":"ca1 2el",
    "addr:street":"London Rd",
    "iso:country":"GB",
    "sg:address":"46-48 London Rd",
    "sg:city":"Carlisle",
    "sg:classifiers":[
        {
            "category":"Health Services",
            "subcategory":"Doctor",
            "type":"Services"
        }
    ],
    "sg:phone":"+44 1228 527559",
    "sg:postcode":"CA1 2EL",
    "sg:province":"Cumbria",
    "sg:tags":[
        "practitioners"
    ],
    "wof:name":"Horne, A R",
    "wof:placetype":"venue"
},
  "geometry": {"coordinates":[-2.9249489307,54.8880500793],"type":"Point"}
}