{
  "type": "Feature",
  "properties": {
    "addr:full":"Sagar House, Eccleston Chorley Lancashire PR7 5PH",
    "addr:postcode":"pr7 5ph",
    "iso:country":"GB",
    "sg:address":"Sagar House, Eccleston",
    "sg:city":"Chorley",
    "sg:classifiers":[
        {
            "category":"Recreation",
            "subcategory":"Campground",
            "type":"Entertainment"
        }
    ],
    "sg:phone":"+44 1257 452452",
    "sg:postcode":"PR7 5PH",
    "sg:province":"Lancashire",
    "sg:tags":[
        "holiday",
        "centre",
        "camp"
    ],
    "wof:name":"Pontin's Ltd.",
    "wof:placetype":"venue"
},
  "geometry": {"coordinates":[-2.7317950726,53.6502914429],"type":"Point"}
}