{
  "type": "Feature",
  "properties": {
    "addr:full":"Frank St Colne Lancashire BB8 5AE",
    "addr:postcode":"bb8 5ae",
    "addr:street":"Frank St",
    "iso:country":"GB",
    "sg:address":"Frank St",
    "sg:city":"Colne",
    "sg:classifiers":[
        {
            "category":"Shopping",
            "subcategory":"Comic Books",
            "type":"Retail Goods"
        }
    ],
    "sg:phone":"+44 1282 813558",
    "sg:postcode":"BB8 5AE",
    "sg:province":"Lancashire",
    "sg:tags":[
        "jeweller"
    ],
    "wof:name":"C & N Bardwell",
    "wof:placetype":"venue"
},
  "geometry": {"coordinates":[-2.1866769791,53.9158630371],"type":"Point"}
}