{
  "type": "Feature",
  "properties": {
    "iso:country":"GB",
    "sg:address":"Marine Walk",
    "sg:city":"Sunderland",
    "sg:classifiers":[
        {
            "category":"Government",
            "subcategory":"Office",
            "type":"Public Place"
        }
    ],
    "sg:phone":"+44 191 553 2828",
    "sg:postcode":"SR6 0PL",
    "sg:province":"Tyne and Wear",
    "sg:tags":[
        "local"
    ],
    "wof:name":"Resorts Office",
    "wof:placetype":"venue"
},
  "geometry": {"coordinates":[-1.3645800352,54.9225311279],"type":"Point"}
}