{
  "type": "Feature",
  "properties": {
    "addr:full":"1 Sunnyhill Rd London Greater London SW16 2UG",
    "addr:housenumber":"1",
    "addr:postcode":"sw16 2ug",
    "addr:street":"Sunnyhill Rd",
    "iso:country":"GB",
    "sg:address":"1 Sunnyhill Rd",
    "sg:city":"London",
    "sg:classifiers":[
        {
            "category":"Shopping",
            "subcategory":"Pets & Pet Supplies",
            "type":"Retail Goods"
        }
    ],
    "sg:postcode":"SW16 2UG",
    "sg:province":"Greater London",
    "wof:name":"Biggin,Michael James,",
    "wof:placetype":"venue"
},
  "geometry": {"coordinates":[-0.1291600019,51.4308128357],"type":"Point"}
}