{
  "type": "Feature",
  "properties": {
    "iso:country":"GB",
    "sg:address":"314 Northolt Road",
    "sg:city":"Harrow",
    "sg:classifiers":[
        {
            "category":"Personal",
            "type":"Services"
        },
        {
            "category":"Shopping",
            "subcategory":"Gifts & Souvenirs",
            "type":"Retail Goods"
        },
        {
            "category":"Government",
            "subcategory":"Customs House",
            "type":"Public Place"
        },
        {
            "category":"Shopping",
            "subcategory":"Used Merchandise",
            "type":"Retail Goods"
        }
    ],
    "sg:phone":"+44 20 8423 6383",
    "sg:postcode":"HA2 8EE",
    "sg:province":"Greater London",
    "sg:tags":[
        "shop",
        "clearance",
        "furniture"
    ],
    "wof:name":"Ideal Gifts",
    "wof:placetype":"venue"
},
  "geometry": {"coordinates":[-0.356035,51.56295],"type":"Point"}
}