{
  "type": "Feature",
  "properties": {
    "addr:full":"11 College Street Leigh Lancashire WN7 2RF",
    "addr:housenumber":"11",
    "addr:postcode":"wn7 2rf",
    "addr:street":"College Street Leigh",
    "iso:country":"GB",
    "sg:address":"11 College Street",
    "sg:city":"Leigh",
    "sg:classifiers":[
        {
            "category":"Health Services",
            "subcategory":"Doctor",
            "type":"Services"
        },
        {
            "category":"Retail",
            "subcategory":"Auto Repair",
            "type":"Services"
        }
    ],
    "sg:phone":"+44 1942 674343",
    "sg:postcode":"WN7 2RF",
    "sg:province":"Lancashire",
    "sg:tags":[
        "modification",
        "garage",
        "practitioners"
    ],
    "wof:name":"K B Bent",
    "wof:placetype":"venue"
},
  "geometry": {"coordinates":[-2.5092549324,53.4960861206],"type":"Point"}
}