{
  "type": "Feature",
  "properties": {
    "addr:full":"Liverpool Road, Irlam Manchester Greater Manchester M44 5AD",
    "addr:postcode":"m44 5ad",
    "addr:street":"Liverpool Road",
    "iso:country":"GB",
    "sg:address":"Liverpool Road, Irlam",
    "sg:city":"Manchester",
    "sg:classifiers":[
        {
            "category":"Recreation",
            "type":"Entertainment"
        }
    ],
    "sg:phone":"+44 161 775 2109",
    "sg:postcode":"M44 5AD",
    "sg:province":"Greater Manchester",
    "sg:tags":[
        "snooker",
        "billiards",
        "hall",
        "pool"
    ],
    "wof:name":"Rialto Pyramid Club",
    "wof:placetype":"venue"
},
  "geometry": {"coordinates":[-2.428204,53.438095],"type":"Point"}
}