{
  "type": "Feature",
  "properties": {
    "addr:full":"The Library, New Greenham Park, Greenham Common Newbury Berkshire RG19 6HW",
    "addr:postcode":"rg19 6hw",
    "addr:street":"New Greenham Park",
    "iso:country":"GB",
    "sg:address":"The Library, New Greenham Park, Greenham Common",
    "sg:city":"Newbury",
    "sg:classifiers":[
        {
            "category":"Wholesale",
            "subcategory":"Medical Equipment & Supplies",
            "type":"Manufacturing & Wholesale Goods"
        }
    ],
    "sg:phone":"+44 1635 552539",
    "sg:postcode":"RG19 6HW",
    "sg:province":"Berkshire",
    "sg:tags":[
        "dental"
    ],
    "wof:name":"Crown Dental",
    "wof:placetype":"venue"
},
  "geometry": {"coordinates":[-1.2789599895,51.3743286133],"type":"Point"}
}