{
  "type": "Feature",
  "properties": {
    "addr:full":"Goodlife Park, Stansted Road, Birchanger Bishops Stortford Essex CM23 5PP",
    "addr:postcode":"cm23 5pp",
    "addr:street":"Stansted Road",
    "iso:country":"GB",
    "sg:address":"Goodlife Park, Stansted Road, Birchanger",
    "sg:city":"Bishops Stortford",
    "sg:classifiers":[
        {
            "category":"Home & Garden",
            "subcategory":"Hardware",
            "type":"Retail Goods"
        }
    ],
    "sg:phone":"+44 1279 653232",
    "sg:postcode":"CM23 5PP",
    "sg:province":"Essex",
    "sg:tags":[
        "retailer",
        "diy"
    ],
    "wof:name":"Focus",
    "wof:placetype":"venue"
},
  "geometry": {"coordinates":[0.190068,51.883896],"type":"Point"}
}