{
  "type": "Feature",
  "properties": {
    "addr:full":"1d Rheidol Terrace London Greater London N1 8NT",
    "addr:housenumber":"1d",
    "addr:postcode":"n1 8nt",
    "addr:street":"Rheidol Terrace",
    "iso:country":"GB",
    "sg:address":"1d Rheidol Terrace",
    "sg:city":"London",
    "sg:classifiers":[
        {
            "category":"Professional",
            "subcategory":"Management & Consulting",
            "type":"Services"
        }
    ],
    "sg:postcode":"N1 8NT",
    "sg:province":"Greater London",
    "sg:tags":[
        "consultant",
        "business"
    ],
    "wof:name":"Coolbanana Ltd",
    "wof:placetype":"venue"
},
  "geometry": {"coordinates":[-0.097537,51.535328],"type":"Point"}
}