{
  "type": "Feature",
  "properties": {
    "addr:full":"203 Priory Road Dudley West Midlands DY1 4EE",
    "addr:housenumber":"203",
    "addr:postcode":"dy1 4ee",
    "addr:street":"Priory Road",
    "iso:country":"GB",
    "sg:address":"203 Priory Road",
    "sg:city":"Dudley",
    "sg:classifiers":[
        {
            "category":"Fast Food",
            "type":"Food & Drink"
        }
    ],
    "sg:phone":"+44 1384 212480",
    "sg:postcode":"DY1 4EE",
    "sg:province":"West Midlands",
    "sg:tags":[
        "away",
        "meal",
        "outlet",
        "take"
    ],
    "wof:name":"Sunrise Chinese Takeaway",
    "wof:placetype":"venue"
},
  "geometry": {"coordinates":[-2.087884903,52.525100708],"type":"Point"}
}