{
  "type": "Feature",
  "properties": {
    "iso:country":"GB",
    "sg:address":"13 Goodwood Crescent, Timperley",
    "sg:city":"Altrincham",
    "sg:classifiers":[
        {
            "category":"Home & Garden",
            "subcategory":"Kitchen Supply",
            "type":"Retail Goods"
        }
    ],
    "sg:postcode":"WA15 7BD",
    "sg:province":"Cheshire",
    "sg:tags":[
        "measuring",
        "scale"
    ],
    "wof:name":"B & M Scientific",
    "wof:placetype":"venue"
},
  "geometry": {"coordinates":[-2.315539,53.393494],"type":"Point"}
}