{
  "type": "Feature",
  "properties": {
    "addr:full":"Low Fold Farm, Back Heights Road, Thornton Bradford West Yorkshire BD13 3RP",
    "addr:postcode":"bd13 3rp",
    "addr:street":"Back Heights Road",
    "iso:country":"GB",
    "sg:address":"Low Fold Farm, Back Heights Road, Thornton",
    "sg:city":"Bradford",
    "sg:classifiers":[
        {
            "category":"Freight",
            "type":"Transportation"
        }
    ],
    "sg:phone":"+44 1274 835232",
    "sg:postcode":"BD13 3RP",
    "sg:province":"West Yorkshire",
    "sg:tags":[
        "haulage",
        "road"
    ],
    "wof:name":"Marcus (Bradford) Ltd.",
    "wof:placetype":"venue"
},
  "geometry": {"coordinates":[-1.8494340181,53.7902336121],"type":"Point"}
}