{
  "type": "Feature",
  "properties": {
    "addr:full":"23 Harrington Avenue Lowestoft Suffolk NR32 4JU",
    "addr:housenumber":"23",
    "addr:postcode":"nr32 4ju",
    "addr:street":"Harrington Avenue",
    "iso:country":"GB",
    "sg:address":"23 Harrington Avenue",
    "sg:city":"Lowestoft",
    "sg:classifiers":[
        {
            "category":"Building & Trades",
            "subcategory":"Construction",
            "type":"Services"
        }
    ],
    "sg:postcode":"NR32 4JU",
    "sg:province":"Suffolk",
    "sg:tags":[
        "roofing"
    ],
    "wof:name":"Fibrewise Building Contractors",
    "wof:placetype":"venue"
},
  "geometry": {"coordinates":[1.747803,52.497719],"type":"Point"}
}