{
  "type": "Feature",
  "properties": {
    "addr:full":"212 Walworth Road London Greater London SE17 1JE",
    "addr:housenumber":"212",
    "addr:postcode":"se17 1je",
    "addr:street":"Walworth Road",
    "iso:country":"GB",
    "sg:address":"212 Walworth Road",
    "sg:city":"London",
    "sg:classifiers":[
        {
            "category":"Food & Beverages",
            "subcategory":"Bakery",
            "type":"Retail Goods"
        }
    ],
    "sg:phone":"+44 20 7708 2540",
    "sg:postcode":"SE17 1JE",
    "sg:province":"Greater London",
    "sg:tags":[
        "baker"
    ],
    "wof:name":"Arif Bakery",
    "wof:placetype":"venue"
},
  "geometry": {"coordinates":[-0.09648,51.48914],"type":"Point"}
}