{
  "type": "Feature",
  "properties": {
    "iso:country":"GB",
    "sg:address":"Remeha House, Molly Millars Lane",
    "sg:city":"Wokingham",
    "sg:classifiers":[
        {
            "category":"Home & Garden",
            "subcategory":"Hardware",
            "type":"Retail Goods"
        }
    ],
    "sg:phone":"+44 118 978 3434",
    "sg:postcode":"RG41 2QP",
    "sg:province":"Berkshire",
    "sg:tags":[
        "equipment",
        "heating"
    ],
    "wof:name":"Broag Ltd.",
    "wof:placetype":"venue"
},
  "geometry": {"coordinates":[-0.847958982,51.4071044922],"type":"Point"}
}