{
  "type": "Feature",
  "properties": {
    "addr:full":"The Drive Hailsham East Sussex BN27 4EP",
    "addr:postcode":"bn27 4ep",
    "addr:street":"The Drive",
    "iso:country":"GB",
    "sg:address":"The Drive",
    "sg:city":"Hailsham",
    "sg:classifiers":[
        {
            "category":"Farming",
            "subcategory":"Nursery",
            "type":"Manufacturing & Wholesale Goods"
        }
    ],
    "sg:phone":"+44 1323 848490",
    "sg:postcode":"BN27 4EP",
    "sg:province":"East Sussex",
    "sg:tags":[
        "creche"
    ],
    "wof:name":"Bunny Nursery School",
    "wof:placetype":"venue"
},
  "geometry": {"coordinates":[0.2567549944,50.8577804565],"type":"Point"}
}