{
  "type": "Feature",
  "properties": {
    "iso:country":"GB",
    "sg:address":"11 Butchers Row, Kirkgate Market",
    "sg:city":"Leeds",
    "sg:classifiers":[
        {
            "category":"Food & Beverages",
            "subcategory":"Meat & Fish",
            "type":"Retail Goods"
        }
    ],
    "sg:phone":"+44 113 243 2135",
    "sg:postcode":"LS2 7HL",
    "sg:province":"West Yorkshire",
    "sg:tags":[
        "butcher"
    ],
    "wof:name":"Johnston'S Butchers",
    "wof:placetype":"venue"
},
  "geometry": {"coordinates":[-1.53903,53.79755],"type":"Point"}
}