{
  "type": "Feature",
  "properties": {
    "addr:full":"Unit 4/9, Guy Motors Industrial Park, Park Lane Wolverhampton Staffordshire WV10 9QF",
    "addr:housenumber":"unit 4 / 9",
    "addr:postcode":"wv10 9qf",
    "addr:street":"Industrial Park Park Lane",
    "iso:country":"GB",
    "sg:address":"Unit 4/9, Guy Motors Industrial Park, Park Lane",
    "sg:city":"Wolverhampton",
    "sg:classifiers":[
        {
            "category":"Home & Garden",
            "subcategory":"Hardware",
            "type":"Retail Goods"
        }
    ],
    "sg:phone":"+44 1902 307121",
    "sg:postcode":"WV10 9QF",
    "sg:province":"Staffordshire",
    "sg:tags":[
        "device",
        "fixing",
        "fastener"
    ],
    "wof:name":"The Crown Washer Co. Ltd.",
    "wof:placetype":"venue"
},
  "geometry": {"coordinates":[-2.121669054,52.5886497498],"type":"Point"}
}