{
  "type": "Feature",
  "properties": {
    "iso:country":"GB",
    "sg:address":"362 Uxbridge Road",
    "sg:city":"Hayes",
    "sg:classifiers":[
        {
            "category":"Restaurant",
            "type":"Food & Drink"
        }
    ],
    "sg:phone":"+44 20 8573 7479",
    "sg:postcode":"UB4 0HF",
    "sg:province":"Greater London",
    "wof:name":"Beefeater Restaurant",
    "wof:placetype":"venue"
},
  "geometry": {"coordinates":[-0.40615201,51.5179519653],"type":"Point"}
}