{
  "type": "Feature",
  "properties": {
    "iso:country":"GB",
    "sg:address":"96 Town Lane, Denton",
    "sg:city":"Manchester",
    "sg:classifiers":[
        {
            "category":"Professional",
            "subcategory":"Engineering",
            "type":"Services"
        }
    ],
    "sg:phone":"+44 161 320 5477",
    "sg:postcode":"M34 2DD",
    "sg:province":"Greater Manchester",
    "sg:tags":[
        "precision",
        "engineer"
    ],
    "wof:name":"S G Turret Ltd",
    "wof:placetype":"venue"
},
  "geometry": {"coordinates":[-2.117904,53.45031],"type":"Point"}
}