{
  "type": "Feature",
  "properties": {
    "addr:full":"Unit K Calne Wiltshire SN11 9PX",
    "addr:postcode":"sn11 9px",
    "iso:country":"GB",
    "sg:address":"Unit K",
    "sg:city":"Calne",
    "sg:classifiers":[
        {
            "category":"Ice Cream",
            "type":"Food & Drink"
        }
    ],
    "sg:phone":"+44 1249 816596",
    "sg:postcode":"SN11 9PX",
    "sg:province":"Wiltshire",
    "sg:tags":[
        "mnfr"
    ],
    "wof:name":"Hill Station Ice Cream Ltd.",
    "wof:placetype":"venue"
},
  "geometry": {"coordinates":[-2.004912,51.437672],"type":"Point"}
}