{
  "type": "Feature",
  "properties": {
    "addr:full":"Riseley Gorse Farm, Part Lane, Riseley Reading Berkshire RG7 1RU",
    "addr:postcode":"rg7 1ru",
    "addr:street":"Part Lane",
    "iso:country":"GB",
    "sg:address":"Riseley Gorse Farm, Part Lane, Riseley",
    "sg:city":"Reading",
    "sg:classifiers":[
        {
            "category":"Farming",
            "subcategory":"Livestock Farm",
            "type":"Manufacturing & Wholesale Goods"
        }
    ],
    "sg:postcode":"RG7 1RU",
    "sg:province":"Berkshire",
    "sg:tags":[
        "others"
    ],
    "wof:name":"G L F Crocker",
    "wof:placetype":"venue"
},
  "geometry": {"coordinates":[-0.96568,51.361984],"type":"Point"}
}