{
  "type": "Feature",
  "properties": {
    "addr:full":"65-67 Nottingham Road, Stapleford Nottingham Nottinghamshire NG9 8AD",
    "addr:housenumber":"65-67",
    "addr:postcode":"ng9 8ad",
    "addr:street":"Nottingham Road",
    "iso:country":"GB",
    "sg:address":"65-67 Nottingham Road, Stapleford",
    "sg:city":"Nottingham",
    "sg:classifiers":[
        {
            "category":"Personal",
            "subcategory":"Beauty Salon",
            "type":"Services"
        }
    ],
    "sg:postcode":"NG9 8AD",
    "sg:province":"Nottinghamshire",
    "sg:tags":[
        "lady",
        "hairdresser"
    ],
    "wof:name":"Margaret's",
    "wof:placetype":"venue"
},
  "geometry": {"coordinates":[-1.2700740099,52.9317131042],"type":"Point"}
}