{
  "type": "Feature",
  "properties": {
    "addr:full":"Falsgrave Avenue Bradford West Yorkshire BD2 3PU",
    "addr:postcode":"bd2 3pu",
    "addr:street":"Avenue Bradford West",
    "iso:country":"GB",
    "sg:address":"Falsgrave Avenue",
    "sg:city":"Bradford",
    "sg:classifiers":[
        {
            "category":"Education",
            "subcategory":"School",
            "type":"Public Place"
        },
        {
            "category":"Government",
            "subcategory":"Office",
            "type":"Public Place"
        }
    ],
    "sg:phone":"+44 1274 771124",
    "sg:postcode":"BD2 3PU",
    "sg:province":"West Yorkshire",
    "sg:tags":[
        "local",
        "authority"
    ],
    "wof:name":"Fagley First School",
    "wof:placetype":"venue"
},
  "geometry": {"coordinates":[-1.717177,53.810478],"type":"Point"}
}