{
  "type": "Feature",
  "properties": {
    "addr:full":"24 Pinstone Street Sheffield South Yorkshire S1 2HN",
    "addr:housenumber":"24",
    "addr:postcode":"s1 2hn",
    "addr:street":"Pinstone Street",
    "iso:country":"GB",
    "sg:address":"24 Pinstone Street",
    "sg:city":"Sheffield",
    "sg:classifiers":[
        {
            "category":"Fast Food",
            "type":"Food & Drink"
        }
    ],
    "sg:phone":"+44 114 249 3340",
    "sg:postcode":"S1 2HN",
    "sg:province":"South Yorkshire",
    "sg:tags":[
        "away",
        "meal",
        "outlet",
        "take"
    ],
    "wof:name":"Fox's Sandwich Specialists",
    "wof:placetype":"venue"
},
  "geometry": {"coordinates":[-1.470606,53.379917],"type":"Point"}
}