{
  "type": "Feature",
  "properties": {
    "iso:country":"GB",
    "sg:address":"Parsonage Farm, The Street, Preston St Mary",
    "sg:city":"Sudbury",
    "sg:classifiers":[
        {
            "category":"Freight",
            "type":"Transportation"
        }
    ],
    "sg:phone":"+44 1787 247696",
    "sg:postcode":"CO10 9NQ",
    "sg:province":"Essex",
    "sg:tags":[
        "haulage",
        "road"
    ],
    "wof:name":"Pryke Bros",
    "wof:placetype":"venue"
},
  "geometry": {"coordinates":[0.84029,52.11665],"type":"Point"}
}