{
  "type": "Feature",
  "properties": {
    "addr:full":"64 Newland Witney Oxfordshire OX8 6JG",
    "addr:housenumber":"64",
    "addr:postcode":"ox8 6jg",
    "addr:street":"Newland",
    "iso:country":"GB",
    "sg:address":"64 Newland",
    "sg:city":"Witney",
    "sg:classifiers":[
        {
            "category":"Recreation",
            "subcategory":"Sailing Club",
            "type":"Entertainment"
        }
    ],
    "sg:phone":"+44 1993 771313",
    "sg:postcode":"OX8 6JG",
    "sg:province":"Oxfordshire",
    "wof:name":"Stardust Marine",
    "wof:placetype":"venue"
},
  "geometry": {"coordinates":[-1.4763059616,51.7890014648],"type":"Point"}
}