{
  "type": "Feature",
  "properties": {
    "iso:country":"GB",
    "sg:address":"5 Byker Bridge",
    "sg:city":"Newcastle-upon-tyne",
    "sg:classifiers":[
        {
            "category":"Shopping",
            "subcategory":"Clothing, Apparel, & Fashions",
            "type":"Retail Goods"
        }
    ],
    "sg:phone":"+44 191 230 2010",
    "sg:postcode":"NE1 2NS",
    "sg:province":"Tyne and Wear",
    "sg:tags":[
        "shop",
        "dress",
        "fancy"
    ],
    "wof:name":"Fancy Pants",
    "wof:placetype":"venue"
},
  "geometry": {"coordinates":[-1.5946290493,54.9752540588],"type":"Point"}
}