{
  "type": "Feature",
  "properties": {
    "iso:country":"GB",
    "sg:address":"102 High Street",
    "sg:city":"Thornton Heath",
    "sg:classifiers":[
        {
            "category":"Shopping",
            "subcategory":"Beauty & Cosmetics",
            "type":"Retail Goods"
        }
    ],
    "sg:postcode":"CR7 8LF",
    "sg:province":"Surrey",
    "sg:tags":[
        "product"
    ],
    "wof:name":"Jacif Cosmetics",
    "wof:placetype":"venue"
},
  "geometry": {"coordinates":[-0.09704,51.398888],"type":"Point"}
}