{
  "type": "Feature",
  "properties": {
    "addr:full":"The Hilton Grove, 33-37 Hatherley Mews, Walthamstow Walthamstow Greater London E17 4QP",
    "addr:housenumber":"33-37",
    "addr:postcode":"e17 4qp",
    "addr:street":"Hatherley Mews",
    "iso:country":"GB",
    "sg:address":"The Hilton Grove, 33-37 Hatherley Mews, Walthamstow",
    "sg:city":"Walthamstow",
    "sg:classifiers":[
        {
            "category":"Communications",
            "subcategory":"Film & Video Production",
            "type":"Services"
        }
    ],
    "sg:phone":"+44 20 8520 5553",
    "sg:postcode":"E17 4QP",
    "sg:province":"Greater London",
    "sg:tags":[
        "recording",
        "studio"
    ],
    "wof:name":"Cache 22",
    "wof:placetype":"venue"
},
  "geometry": {"coordinates":[-0.0205199998,51.5862998962],"type":"Point"}
}