{
  "type": "Feature",
  "properties": {
    "iso:country":"GB",
    "sg:address":"219 Bradford Road",
    "sg:city":"Bradford",
    "sg:classifiers":[
        {
            "category":"Retail",
            "subcategory":"Driving School",
            "type":"Services"
        }
    ],
    "sg:postcode":"BD14 6DA",
    "sg:province":"West Yorkshire",
    "wof:name":"Jane Summerscales",
    "wof:placetype":"venue"
},
  "geometry": {"coordinates":[-1.816883,53.784794],"type":"Point"}
}