{
  "type": "Feature",
  "properties": {
    "addr:full":"Aster Road Ipswich Suffolk IP2 0NR",
    "addr:postcode":"ip2 0nr",
    "addr:street":"Aster Road",
    "iso:country":"GB",
    "sg:address":"Aster Road",
    "sg:city":"Ipswich",
    "sg:classifiers":[
        {
            "category":"Education",
            "subcategory":"School",
            "type":"Public Place"
        }
    ],
    "sg:phone":"+44 1473 684994",
    "sg:postcode":"IP2 0NR",
    "sg:province":"Suffolk",
    "sg:tags":[
        "local",
        "authority"
    ],
    "wof:name":"Chantry Infant School",
    "wof:placetype":"venue"
},
  "geometry": {"coordinates":[1.1265499592,52.0510940552],"type":"Point"}
}