{
  "type": "Feature",
  "properties": {
    "addr:full":"Naylors Farm, Campney Lane, Bucknall Woodhall Spa Lincolnshire LN10 5DX",
    "addr:postcode":"ln10 5dx",
    "addr:street":"Campney Lane;Spa",
    "iso:country":"GB",
    "sg:address":"Naylors Farm, Campney Lane, Bucknall",
    "sg:city":"Woodhall Spa",
    "sg:classifiers":[
        {
            "category":"Farming",
            "subcategory":"Farm",
            "type":"Manufacturing & Wholesale Goods"
        }
    ],
    "sg:postcode":"LN10 5DX",
    "sg:province":"Lincolnshire",
    "sg:tags":[
        "mixed",
        "crop"
    ],
    "wof:name":"D J Steadman",
    "wof:placetype":"venue"
},
  "geometry": {"coordinates":[-0.240218,53.203648],"type":"Point"}
}