{
  "type": "Feature",
  "properties": {
    "addr:full":"38 Dolphin Lane Boston Lincolnshire PE21 6EU",
    "addr:housenumber":"38",
    "addr:postcode":"pe21 6eu",
    "addr:street":"Dolphin Lane",
    "iso:country":"GB",
    "sg:address":"38 Dolphin Lane",
    "sg:city":"Boston",
    "sg:classifiers":[
        {
            "category":"Shopping",
            "subcategory":"Clothing, Apparel, & Fashions",
            "type":"Retail Goods"
        }
    ],
    "sg:postcode":"PE21 6EU",
    "sg:province":"Lincolnshire",
    "sg:tags":[
        "shop"
    ],
    "wof:name":"Inspirations",
    "wof:placetype":"venue"
},
  "geometry": {"coordinates":[-0.0231539998,52.9777755737],"type":"Point"}
}