{
  "type": "Feature",
  "properties": {
    "iso:country":"GB",
    "sg:address":"88 Pantbach Road, Rhiwbina",
    "sg:city":"Cardiff",
    "sg:classifiers":[
        {
            "category":"Health Services",
            "subcategory":"Health Practitioner",
            "type":"Services"
        }
    ],
    "sg:phone":"+44 29 2062 4114",
    "sg:postcode":"CF4 1UD",
    "sg:province":"Cardiff",
    "sg:tags":[
        "homoeopathic"
    ],
    "wof:name":"A G Davies",
    "wof:placetype":"venue"
},
  "geometry": {"coordinates":[-3.21106,51.52914],"type":"Point"}
}