{
  "type": "Feature",
  "properties": {
    "iso:country":"GB",
    "sg:address":"259 Ewell Road",
    "sg:city":"Surbiton",
    "sg:classifiers":[
        {
            "category":"Home & Garden",
            "subcategory":"Home Furnishings",
            "type":"Retail Goods"
        }
    ],
    "sg:postcode":"KT6 7AA",
    "sg:province":"Surrey",
    "sg:tags":[
        "blind",
        "curtain",
        "fitting"
    ],
    "wof:name":"Traditions Upholsterers & Curtain Makers",
    "wof:placetype":"venue"
},
  "geometry": {"coordinates":[-0.295059,51.38512],"type":"Point"}
}