{
  "type": "Feature",
  "properties": {
    "addr:full":"1-3 Cyprus Road Burgess Hill East Sussex RH15 8DX",
    "addr:housenumber":"1-3",
    "addr:postcode":"rh15 8dx",
    "addr:street":"Cyprus Road",
    "iso:country":"GB",
    "sg:address":"1-3 Cyprus Road",
    "sg:city":"Burgess Hill",
    "sg:classifiers":[
        {
            "category":"Organizations",
            "subcategory":"Membership Organization",
            "type":"Services"
        }
    ],
    "sg:phone":"+44 1444 241992",
    "sg:postcode":"RH15 8DX",
    "sg:province":"East Sussex",
    "sg:tags":[
        "club",
        "social"
    ],
    "wof:name":"Mid Sussex Conservative Club Ltd.",
    "wof:placetype":"venue"
},
  "geometry": {"coordinates":[-0.1290400028,50.9563446045],"type":"Point"}
}