{
  "type": "Feature",
  "properties": {
    "addr:full":"20 Broadstone Avenue Halesowen West Midlands B63 2JL",
    "addr:housenumber":"20",
    "addr:postcode":"b63 2jl",
    "addr:street":"Broadstone Avenue",
    "iso:country":"GB",
    "sg:address":"20 Broadstone Avenue",
    "sg:city":"Halesowen",
    "sg:classifiers":[
        {
            "category":"Professional",
            "subcategory":"Printing & Photocopies",
            "type":"Services"
        },
        {
            "category":"Manufacturing",
            "subcategory":"Signs",
            "type":"Manufacturing & Wholesale Goods"
        }
    ],
    "sg:phone":"+44 1384 564546",
    "sg:postcode":"B63 2JL",
    "sg:province":"West Midlands",
    "sg:tags":[
        "process",
        "screen",
        "writer",
        "printer"
    ],
    "wof:name":"Graham Chance",
    "wof:placetype":"venue"
},
  "geometry": {"coordinates":[-2.0909249783,52.4530296326],"type":"Point"}
}