{
  "type": "Feature",
  "properties": {
    "addr:full":"6 Lion Close, Ramsey St. Marys Huntingdon Cambridgeshire PE17 1SP",
    "addr:housenumber":"6",
    "addr:postcode":"pe17 1sp",
    "addr:street":"Lion Close",
    "iso:country":"GB",
    "sg:address":"6 Lion Close, Ramsey St. Marys",
    "sg:city":"Huntingdon",
    "sg:classifiers":[
        {
            "category":"Wholesale",
            "subcategory":"Medical Equipment & Supplies",
            "type":"Manufacturing & Wholesale Goods"
        }
    ],
    "sg:phone":"+44 1733 844032",
    "sg:postcode":"PE17 1SP",
    "sg:province":"Cambridgeshire",
    "sg:tags":[
        "hospital"
    ],
    "wof:name":"Xomed Ltd",
    "wof:placetype":"venue"
},
  "geometry": {"coordinates":[-0.1511300057,52.479850769],"type":"Point"}
}