{
  "type": "Feature",
  "properties": {
    "addr:full":"156-158 Charminster Road Bournemouth Dorset BH8 8UU",
    "addr:housenumber":"156-158",
    "addr:postcode":"bh8 8uu",
    "addr:street":"Charminster Road",
    "iso:country":"GB",
    "sg:address":"156-158 Charminster Road",
    "sg:city":"Bournemouth",
    "sg:classifiers":[
        {
            "category":"Real Estate",
            "subcategory":"Real Estate Agent",
            "type":"Services"
        }
    ],
    "sg:phone":"+44 1202 510286",
    "sg:postcode":"BH8 8UU",
    "sg:province":"Dorset",
    "wof:name":"Roberts",
    "wof:placetype":"venue"
},
  "geometry": {"coordinates":[-1.86532,50.736324],"type":"Point"}
}