{
  "type": "Feature",
  "properties": {
    "iso:country":"GB",
    "sg:address":"Church Farm",
    "sg:city":"Royston",
    "sg:classifiers":[
        {
            "category":"Retail",
            "subcategory":"Storage",
            "type":"Services"
        }
    ],
    "sg:postcode":"SG8 0HL",
    "sg:province":"Bedfordshire",
    "sg:tags":[
        "household",
        "removal"
    ],
    "wof:name":"Ellis & Bradley Removers",
    "wof:placetype":"venue"
},
  "geometry": {"coordinates":[-0.124479,52.064423],"type":"Point"}
}