{
  "type": "Feature",
  "properties": {
    "addr:full":"181 Darkes La Potters Bar Greater London EN6 1DL",
    "addr:housenumber":"181",
    "addr:postcode":"en6 1dl",
    "addr:street":"Darkes La Potters",
    "iso:country":"GB",
    "sg:address":"181 Darkes La",
    "sg:city":"Potters Bar",
    "sg:classifiers":[
        {
            "category":"Banks & Credit Unions",
            "subcategory":"Bank",
            "type":"Services"
        }
    ],
    "sg:phone":"+44 20 8805 7000",
    "sg:postcode":"EN6 1DL",
    "sg:province":"Greater London",
    "wof:name":"NatWest",
    "wof:placetype":"venue"
},
  "geometry": {"coordinates":[-0.190222,51.698986],"type":"Point"}
}