{
  "type": "Feature",
  "properties": {
    "iso:country":"GB",
    "sg:address":"48 Tedder Close, Watton",
    "sg:city":"Thetford",
    "sg:classifiers":[
        {
            "category":"Professional",
            "subcategory":"Management & Consulting",
            "type":"Services"
        }
    ],
    "sg:phone":"+44 1953 885370",
    "sg:postcode":"IP25 6HX",
    "sg:province":"Norfolk",
    "sg:tags":[
        "environmental",
        "consultant"
    ],
    "wof:name":"Griffin Accident Investigations",
    "wof:placetype":"venue"
},
  "geometry": {"coordinates":[0.843376,52.567127],"type":"Point"}
}