{
  "type": "Feature",
  "properties": {
    "addr:full":"Higher Tregadra, Cury Cross Lanes Helston Cornwall TR12 7BB",
    "addr:postcode":"tr12 7bb",
    "addr:street":"Cury Cross Lanes",
    "iso:country":"GB",
    "sg:address":"Higher Tregadra, Cury Cross Lanes",
    "sg:city":"Helston",
    "sg:classifiers":[
        {
            "category":"Health Services",
            "subcategory":"Podiatrist",
            "type":"Services"
        }
    ],
    "sg:phone":"+44 1326 240225",
    "sg:postcode":"TR12 7BB",
    "sg:province":"Cornwall",
    "sg:tags":[
        "podiatrists",
        "chiropodist"
    ],
    "wof:name":"Pamela Mary Carpenter",
    "wof:placetype":"venue"
},
  "geometry": {"coordinates":[-5.2243990898,50.048248291],"type":"Point"}
}