{
  "type": "Feature",
  "properties": {
    "addr:full":"26 Boothferry Road Goole East Riding of Yorkshire DN14 5DN",
    "addr:housenumber":"26",
    "addr:postcode":"dn14 5dn",
    "addr:street":"Boothferry Road",
    "iso:country":"GB",
    "sg:address":"26 Boothferry Road",
    "sg:city":"Goole",
    "sg:classifiers":[
        {
            "category":"Banks & Credit Unions",
            "subcategory":"Financial Services",
            "type":"Services"
        }
    ],
    "sg:phone":"+44 1405 660000",
    "sg:postcode":"DN14 5DN",
    "sg:province":"East Riding of Yorkshire",
    "sg:tags":[
        "building",
        "society"
    ],
    "wof:name":"Nationwide Building Society",
    "wof:placetype":"venue"
},
  "geometry": {"coordinates":[-0.872754,53.703838],"type":"Point"}
}