{
  "type": "Feature",
  "properties": {
    "iso:country":"GB",
    "sg:address":"215 Brook Street, Broughty Ferry",
    "sg:city":"Dundee",
    "sg:classifiers":[
        {
            "category":"Organizations",
            "subcategory":"Non-profit Organization",
            "type":"Services"
        }
    ],
    "sg:phone":"+44 1382 732562",
    "sg:postcode":"DD5 2AG",
    "sg:province":"Angus",
    "sg:tags":[
        "organisation",
        "voluntary",
        "charity"
    ],
    "wof:name":"Peoples Dispensary for Sick Animals",
    "wof:placetype":"venue"
},
  "geometry": {"coordinates":[-2.874532,56.467384],"type":"Point"}
}