{
  "type": "Feature",
  "properties": {
    "addr:full":"The Dairy House, London Street Fairford Gloucestershire GL7 4AH",
    "addr:postcode":"gl7 4ah",
    "addr:street":"London Street",
    "iso:country":"GB",
    "sg:address":"The Dairy House, London Street",
    "sg:city":"Fairford",
    "sg:classifiers":[
        {
            "category":"Communications",
            "subcategory":"Film & Video Production",
            "type":"Services"
        }
    ],
    "sg:phone":"+44 1285 713597",
    "sg:postcode":"GL7 4AH",
    "sg:province":"Gloucestershire",
    "sg:tags":[
        "illustrator",
        "artist"
    ],
    "wof:name":"The Art Market",
    "wof:placetype":"venue"
},
  "geometry": {"coordinates":[-1.76782,51.709686],"type":"Point"}
}