{
  "type": "Feature",
  "properties": {
    "iso:country":"GB",
    "sg:address":"Manor Farm, West Harting",
    "sg:city":"Petersfield",
    "sg:classifiers":[
        {
            "category":"Farming",
            "subcategory":"Farm",
            "type":"Manufacturing & Wholesale Goods"
        }
    ],
    "sg:phone":"+44 1730 825626",
    "sg:postcode":"GU31 5PA",
    "sg:province":"Hampshire",
    "sg:tags":[
        "mixed",
        "crop"
    ],
    "wof:name":"D Bate",
    "wof:placetype":"venue"
},
  "geometry": {"coordinates":[-0.884745,50.983074],"type":"Point"}
}