{
  "type": "Feature",
  "properties": {
    "addr:full":"Gatwick Airport Railway Station, Gatwick Airport Gatwick Surrey RH6 0RD",
    "addr:postcode":"rh6 0rd",
    "addr:street":"Gatwick Airport Railway Station Gatwick Airport",
    "iso:country":"GB",
    "sg:address":"Gatwick Airport Railway Station, Gatwick Airport",
    "sg:city":"Gatwick",
    "sg:classifiers":[
        {
            "category":"Banks & Credit Unions",
            "subcategory":"Bureau De Change",
            "type":"Services"
        }
    ],
    "sg:phone":"+44 1293 530321",
    "sg:postcode":"RH6 0RD",
    "sg:province":"Surrey",
    "wof:name":"Exchange International",
    "wof:placetype":"venue"
},
  "geometry": {"coordinates":[-0.1612900048,51.1568489075],"type":"Point"}
}