{
  "type": "Feature",
  "properties": {
    "iso:country":"GB",
    "sg:address":"Weaste Lane Farm, Weaste Lane, Thelwall",
    "sg:city":"Warrington",
    "sg:classifiers":[
        {
            "category":"Farming",
            "subcategory":"Farm",
            "type":"Manufacturing & Wholesale Goods"
        }
    ],
    "sg:phone":"+44 1925 262146",
    "sg:postcode":"WA4 3JW",
    "sg:province":"Cheshire",
    "sg:tags":[
        "mixed",
        "crop"
    ],
    "wof:name":"T Cooke & Sons",
    "wof:placetype":"venue"
},
  "geometry": {"coordinates":[-2.529819,53.374626],"type":"Point"}
}