{
  "type": "Feature",
  "properties": {
    "iso:country":"GB",
    "sg:address":"17 Netheroyd Hill Road",
    "sg:city":"Huddersfield",
    "sg:classifiers":[
        {
            "category":"Professional",
            "subcategory":"Management & Consulting",
            "type":"Services"
        }
    ],
    "sg:postcode":"HD2 2LW",
    "sg:province":"West Yorkshire",
    "sg:tags":[
        "consultant",
        "specialist"
    ],
    "wof:name":"Myfanwys for Beauty",
    "wof:placetype":"venue"
},
  "geometry": {"coordinates":[-1.782845,53.670956],"type":"Point"}
}