{
  "type": "Feature",
  "properties": {
    "iso:country":"GB",
    "sg:address":"Leestone Road",
    "sg:city":"Manchester",
    "sg:classifiers":[
        {
            "category":"Professional",
            "subcategory":"Printing & Photocopies",
            "type":"Services"
        }
    ],
    "sg:phone":"+44 161 998 3441",
    "sg:postcode":"M22 4RF",
    "sg:province":"Greater Manchester",
    "sg:tags":[
        "printer"
    ],
    "wof:name":"Remploy Print",
    "wof:placetype":"venue"
},
  "geometry": {"coordinates":[-2.249901,53.397495],"type":"Point"}
}