{
  "type": "Feature",
  "properties": {
    "iso:country":"GB",
    "sg:address":"Belle Vue Lane, Blidworth",
    "sg:city":"Mansfield",
    "sg:classifiers":[
        {
            "category":"Education",
            "subcategory":"School",
            "type":"Public Place"
        }
    ],
    "sg:phone":"+44 1623 793675",
    "sg:postcode":"NG21 0RD",
    "sg:province":"Nottinghamshire",
    "sg:tags":[
        "local",
        "authority"
    ],
    "wof:name":"Robert Jones Infant & Nursery School",
    "wof:placetype":"venue"
},
  "geometry": {"coordinates":[-1.117464,53.099079],"type":"Point"}
}