{
  "type": "Feature",
  "properties": {
    "addr:full":"North Road, West Bridgford Nottingham Nottinghamshire NG2 7NH",
    "addr:postcode":"ng2 7nh",
    "addr:street":"North Road",
    "iso:country":"GB",
    "sg:address":"North Road, West Bridgford",
    "sg:city":"Nottingham",
    "sg:classifiers":[
        {
            "category":"Professional",
            "subcategory":"Management & Consulting",
            "type":"Services"
        }
    ],
    "sg:postcode":"NG2 7NH",
    "sg:province":"Nottinghamshire",
    "sg:tags":[
        "marketing",
        "consultant"
    ],
    "wof:name":"Beesley Tom Associates Media Consultants",
    "wof:placetype":"venue"
},
  "geometry": {"coordinates":[-1.1364740133,52.927116394],"type":"Point"}
}