{
  "type": "Feature",
  "properties": {
    "addr:full":"77 High Street, Lakenheath Brandon Norfolk IP27 9EW",
    "addr:housenumber":"77",
    "addr:postcode":"ip27 9ew",
    "addr:street":"High Street",
    "iso:country":"GB",
    "sg:address":"77 High Street, Lakenheath",
    "sg:city":"Brandon",
    "sg:classifiers":[
        {
            "category":"Fast Food",
            "type":"Food & Drink"
        }
    ],
    "sg:phone":"+44 1842 861234",
    "sg:postcode":"IP27 9EW",
    "sg:province":"Norfolk",
    "sg:tags":[
        "away",
        "meal",
        "outlet",
        "take"
    ],
    "wof:name":"Rising Star Take Away",
    "wof:placetype":"venue"
},
  "geometry": {"coordinates":[0.521158,52.414272],"type":"Point"}
}