{
  "type": "Feature",
  "properties": {
    "iso:country":"GB",
    "sg:address":"The Avenue, Wroxham",
    "sg:city":"Norwich",
    "sg:classifiers":[
        {
            "category":"Organizations",
            "subcategory":"Community Association",
            "type":"Services"
        },
        {
            "category":"Organizations",
            "subcategory":"Membership Organization",
            "type":"Services"
        }
    ],
    "sg:phone":"+44 1603 782808",
    "sg:postcode":"NR12 8TS",
    "sg:province":"Norfolk",
    "sg:tags":[
        "club",
        "social"
    ],
    "wof:name":"Norfolk Broads Yacht Club",
    "wof:placetype":"venue"
},
  "geometry": {"coordinates":[1.4686800241,52.7045097351],"type":"Point"}
}