{
  "type": "Feature",
  "properties": {
    "iso:country":"GB",
    "sg:address":"4 Craigluscar Road",
    "sg:city":"Dunfermline",
    "sg:classifiers":[
        {
            "category":"Shopping",
            "subcategory":"Stationery & Office Supplies",
            "type":"Retail Goods"
        },
        {
            "category":"Manufacturing",
            "subcategory":"Wood Products",
            "type":"Manufacturing & Wholesale Goods"
        }
    ],
    "sg:phone":"+44 1383 732296",
    "sg:postcode":"KY12 9JA",
    "sg:province":"Fife",
    "sg:tags":[
        "packaging",
        "equipment",
        "crate",
        "pallets"
    ],
    "sg:website":"http://www.polyscot.co.uk",
    "wof:name":"Polyscot Polystyrene",
    "wof:placetype":"venue"
},
  "geometry": {"coordinates":[-3.4990229607,56.0863685608],"type":"Point"}
}