{
  "type": "Feature",
  "properties": {
    "addr:full":"Keller & Co 367b Church Road, Frampton Cotterell Bristol Gloucestershire BS36 2AQ",
    "addr:housenumber":"367b",
    "addr:postcode":"bs36 2aq",
    "addr:street":"Church Road",
    "iso:country":"GB",
    "sg:address":"Keller & Co 367b Church Road, Frampton Cotterell",
    "sg:city":"Bristol",
    "sg:classifiers":[
        {
            "category":"Manufacturing",
            "subcategory":"Aerospace",
            "type":"Manufacturing & Wholesale Goods"
        }
    ],
    "sg:postcode":"BS36 2AQ",
    "sg:province":"Gloucestershire",
    "sg:tags":[
        "aircraft",
        "furnishing",
        "fitting"
    ],
    "wof:name":"Sinklair Ltd",
    "wof:placetype":"venue"
},
  "geometry": {"coordinates":[-2.486522913,51.5361747742],"type":"Point"}
}