{
  "type": "Feature",
  "properties": {
    "addr:full":"3 Cornish Way, Barbot Hall Estate Rotherham South Yorkshire S62 6EG",
    "addr:housenumber":"3",
    "addr:postcode":"s62 6eg",
    "addr:street":"Cornish Way Barbot Hall Estate",
    "iso:country":"GB",
    "sg:address":"3 Cornish Way, Barbot Hall Estate",
    "sg:city":"Rotherham",
    "sg:classifiers":[
        {
            "category":"Shopping",
            "subcategory":"Stationery & Office Supplies",
            "type":"Retail Goods"
        }
    ],
    "sg:phone":"+44 1709 524999",
    "sg:postcode":"S62 6EG",
    "sg:province":"South Yorkshire",
    "sg:tags":[
        "printers'"
    ],
    "wof:name":"Y B E Business Forms Ltd.",
    "wof:placetype":"venue"
},
  "geometry": {"coordinates":[-1.3495010138,53.4492835999],"type":"Point"}
}