{
  "type": "Feature",
  "properties": {
    "addr:full":"5 Potters La Milton Keynes Buckinghamshire MK11 3HE",
    "addr:housenumber":"5",
    "addr:postcode":"mk11 3he",
    "addr:street":"Potters La",
    "iso:country":"GB",
    "sg:address":"5 Potters La",
    "sg:city":"Milton Keynes",
    "sg:classifiers":[
        {
            "category":"Personal",
            "type":"Services"
        }
    ],
    "sg:phone":"+44 1908 260165",
    "sg:postcode":"MK11 3HE",
    "sg:province":"Buckinghamshire",
    "sg:tags":[
        "gift"
    ],
    "wof:name":"Fingers & Toes",
    "wof:placetype":"venue"
},
  "geometry": {"coordinates":[-0.820237,52.048496],"type":"Point"}
}