{
  "type": "Feature",
  "properties": {
    "iso:country":"GB",
    "sg:address":"Unit 2d Sandall Ho, Sandall La, Kirk Sandall",
    "sg:city":"Doncaster",
    "sg:classifiers":[
        {
            "category":"Communications",
            "subcategory":"Film & Video Production",
            "type":"Services"
        }
    ],
    "sg:postcode":"DN3 1RA",
    "sg:province":"South Yorkshire",
    "sg:tags":[
        "recording",
        "studio"
    ],
    "wof:name":"Elliss,Matthew,",
    "wof:placetype":"venue"
},
  "geometry": {"coordinates":[-1.072788,53.562778],"type":"Point"}
}