{
  "type": "Feature",
  "properties": {
    "addr:full":"16 Meeting House Lane Brighton East Sussex BN1 1HB",
    "addr:housenumber":"16",
    "addr:postcode":"bn1 1hb",
    "addr:street":"Meeting House Lane",
    "iso:country":"GB",
    "sg:address":"16 Meeting House Lane",
    "sg:city":"Brighton",
    "sg:classifiers":[
        {
            "category":"Shopping",
            "subcategory":"News",
            "type":"Retail Goods"
        }
    ],
    "sg:phone":"+44 1273 727189",
    "sg:postcode":"BN1 1HB",
    "sg:province":"East Sussex",
    "sg:tags":[
        "newsagent"
    ],
    "wof:name":"City News",
    "wof:placetype":"venue"
},
  "geometry": {"coordinates":[-0.1403039992,50.8225021362],"type":"Point"}
}