{
  "type": "Feature",
  "properties": {
    "addr:full":"26 Lowther Road London Greater London SW13 9ND",
    "addr:housenumber":"26",
    "addr:postcode":"sw13 9nd",
    "addr:street":"Lowther Road",
    "iso:country":"GB",
    "sg:address":"26 Lowther Road",
    "sg:city":"London",
    "sg:classifiers":[
        {
            "category":"Professional",
            "subcategory":"Employment Agencies",
            "type":"Services"
        }
    ],
    "sg:phone":"+44 20 8748 7482",
    "sg:postcode":"SW13 9ND",
    "sg:province":"Greater London",
    "sg:tags":[
        "consultant"
    ],
    "wof:name":"John Cockerill & Associates",
    "wof:placetype":"venue"
},
  "geometry": {"coordinates":[-0.246095,51.476967],"type":"Point"}
}