{
  "type": "Feature",
  "properties": {
    "addr:full":"12a New Lane, Feering Colchester Essex CO5 9EJ",
    "addr:housenumber":"12a",
    "addr:postcode":"co5 9ej",
    "addr:street":"New Lane",
    "iso:country":"GB",
    "sg:address":"12a New Lane, Feering",
    "sg:city":"Colchester",
    "sg:classifiers":[
        {
            "category":"Building & Trades",
            "subcategory":"Plumbing",
            "type":"Services"
        }
    ],
    "sg:postcode":"CO5 9EJ",
    "sg:province":"Essex",
    "sg:tags":[
        "heating"
    ],
    "wof:name":"Colin L Gray",
    "wof:placetype":"venue"
},
  "geometry": {"coordinates":[0.724071,51.850296],"type":"Point"}
}