{
  "type": "Feature",
  "properties": {
    "addr:full":"Room 10, Volunteer Centre Chester Le Street Durham DH3 3DQ",
    "addr:housenumber":"10",
    "addr:postcode":"dh3 3dq",
    "addr:street":"Volunteer Centre Chester Le Street",
    "iso:country":"GB",
    "sg:address":"Room 10, Volunteer Centre",
    "sg:city":"Chester Le Street",
    "sg:classifiers":[
        {
            "category":"Organizations",
            "subcategory":"Non-profit Organization",
            "type":"Services"
        }
    ],
    "sg:phone":"+44 191 389 0595",
    "sg:postcode":"DH3 3DQ",
    "sg:province":"Durham",
    "sg:tags":[
        "organisation",
        "voluntary",
        "charity"
    ],
    "wof:name":"Multiple Sclerosis Society",
    "wof:placetype":"venue"
},
  "geometry": {"coordinates":[-1.5749640465,54.8591346741],"type":"Point"}
}