{
  "type": "Feature",
  "properties": {
    "iso:country":"GB",
    "sg:address":"Stables End Court, Main Street, Market Bosworth",
    "sg:city":"Nuneaton",
    "sg:classifiers":[
        {
            "category":"Professional",
            "subcategory":"Accounting & Tax Preparation",
            "type":"Services"
        }
    ],
    "sg:postcode":"CV13 0JN",
    "sg:province":"Leicestershire",
    "sg:tags":[
        "accountant"
    ],
    "wof:name":"The Hames Partnership",
    "wof:placetype":"venue"
},
  "geometry": {"coordinates":[-1.3686790466,52.6476860046],"type":"Point"}
}