{
  "type": "Feature",
  "properties": {
    "iso:country":"GB",
    "sg:address":"Acorn House, Shab Hill, Birdlip",
    "sg:city":"Gloucester",
    "sg:classifiers":[
        {
            "category":"Professional",
            "subcategory":"Detective & Security Services",
            "type":"Services"
        }
    ],
    "sg:postcode":"GL4 8JX",
    "sg:province":"Gloucestershire",
    "sg:tags":[
        "alarm",
        "burglar",
        "system"
    ],
    "wof:name":"Gardner Security",
    "wof:placetype":"venue"
},
  "geometry": {"coordinates":[-2.1097540855,51.8279495239],"type":"Point"}
}