{
  "type": "Feature",
  "properties": {
    "addr:full":"Ware Road Hertford Hertfordshire SG14 1QA",
    "addr:postcode":"sg14 1qa",
    "addr:street":"Ware Road",
    "iso:country":"GB",
    "sg:address":"Ware Road",
    "sg:city":"Hertford",
    "sg:classifiers":[
        {
            "category":"Food & Beverages",
            "subcategory":"Supermarket",
            "type":"Retail Goods"
        },
        {
            "category":"Community Center",
            "type":"Public Place"
        }
    ],
    "sg:phone":"+44 1992 581344",
    "sg:postcode":"SG14 1QA",
    "sg:province":"Hertfordshire",
    "sg:tags":[
        "conference",
        "room",
        "centre"
    ],
    "wof:name":"Tesco Stores Ltd.",
    "wof:placetype":"venue"
},
  "geometry": {"coordinates":[-0.072234,51.79744],"type":"Point"}
}