{
  "type": "Feature",
  "properties": {
    "iso:country":"GB",
    "sg:address":"33 Stonehill St, Anfield",
    "sg:city":"Liverpool",
    "sg:classifiers":[
        {
            "category":"Retail",
            "subcategory":"Auto Repair",
            "type":"Services"
        }
    ],
    "sg:postcode":"L4 2QA",
    "sg:province":"Merseyside",
    "sg:tags":[
        "engine",
        "car",
        "specialist"
    ],
    "wof:name":"Cortman,A,& Evans,A,",
    "wof:placetype":"venue"
},
  "geometry": {"coordinates":[-2.955229,53.426071],"type":"Point"}
}