{
  "type": "Feature",
  "properties": {
    "iso:country":"GB",
    "sg:address":"Carlton Chambers, Queen Street, Wellington",
    "sg:city":"Telford",
    "sg:classifiers":[
        {
            "category":"Professional",
            "subcategory":"Management & Consulting",
            "type":"Services"
        },
        {
            "category":"Personal",
            "type":"Services"
        }
    ],
    "sg:phone":"+44 1952 255381",
    "sg:postcode":"TF1 1EW",
    "sg:province":"Shropshire",
    "sg:tags":[
        "consultant",
        "beauty",
        "specialist"
    ],
    "wof:name":"Wellington Electrolysis & Beauty Clinic",
    "wof:placetype":"venue"
},
  "geometry": {"coordinates":[-2.520539999,52.7024002075],"type":"Point"}
}