{
  "type": "Feature",
  "properties": {
    "addr:full":"95 Whitechapel High Street London Greater London E1 7RA",
    "addr:housenumber":"95",
    "addr:postcode":"e1 7ra",
    "addr:street":"Whitechapel High Street",
    "iso:country":"GB",
    "sg:address":"95 Whitechapel High Street",
    "sg:city":"London",
    "sg:classifiers":[
        {
            "category":"Shopping",
            "subcategory":"Clothing, Apparel, & Fashions",
            "type":"Retail Goods"
        },
        {
            "category":"Wholesale",
            "subcategory":"Apparel",
            "type":"Manufacturing & Wholesale Goods"
        }
    ],
    "sg:phone":"+44 20 7247 9858",
    "sg:postcode":"E1 7RA",
    "sg:province":"Greater London",
    "sg:tags":[
        "shop",
        "supplier",
        "clothing"
    ],
    "wof:name":"Pop Soda",
    "wof:placetype":"venue"
},
  "geometry": {"coordinates":[-0.0712269992,51.5156097412],"type":"Point"}
}