{
  "type": "Feature",
  "properties": {
    "addr:full":"Low Farm, Carlton, Helmsley York North Yorkshire YO62 5HQ",
    "addr:postcode":"yo62 5hq",
    "addr:street":"Carlton",
    "iso:country":"GB",
    "sg:address":"Low Farm, Carlton, Helmsley",
    "sg:city":"York",
    "sg:classifiers":[
        {
            "category":"Farming",
            "subcategory":"Farm",
            "type":"Manufacturing & Wholesale Goods"
        }
    ],
    "sg:postcode":"YO62 5HQ",
    "sg:province":"North Yorkshire",
    "sg:tags":[
        "mixed",
        "crop"
    ],
    "wof:name":"Timothy A Otterburn",
    "wof:placetype":"venue"
},
  "geometry": {"coordinates":[-1.0606889725,54.2458686829],"type":"Point"}
}