{
  "type": "Feature",
  "properties": {
    "addr:full":"Appointments, 145 George V Av Worthing West Sussex BN11 5RZ",
    "addr:housenumber":"145",
    "addr:postcode":"bn11 5rz",
    "addr:street":"Appointments;George V Av Worthing",
    "iso:country":"GB",
    "sg:address":"Appointments, 145 George V Av",
    "sg:city":"Worthing",
    "sg:classifiers":[
        {
            "category":"Health Services",
            "subcategory":"Doctor",
            "type":"Services"
        }
    ],
    "sg:phone":"+44 1903 241997",
    "sg:postcode":"BN11 5RZ",
    "sg:province":"West Sussex",
    "sg:tags":[
        "practitioners"
    ],
    "wof:name":"Sayers, R D",
    "wof:placetype":"venue"
},
  "geometry": {"coordinates":[-0.3754239976,50.8136253357],"type":"Point"}
}