{
  "type": "Feature",
  "properties": {
    "iso:country":"GB",
    "sg:address":"East Pastures Farm, Skelton In Cleveland",
    "sg:city":"Saltburn-by-the-sea",
    "sg:classifiers":[
        {
            "category":"Manufacturing",
            "subcategory":"Wood Products",
            "type":"Manufacturing & Wholesale Goods"
        }
    ],
    "sg:postcode":"TS12 2AZ",
    "sg:province":"North Yorkshire",
    "sg:tags":[
        "maker",
        "cabinet"
    ],
    "wof:name":"Krown Kitchens & Bedrooms Ltd",
    "wof:placetype":"venue"
},
  "geometry": {"coordinates":[-0.976239,54.561779],"type":"Point"}
}