{
  "type": "Feature",
  "properties": {
    "addr:full":"116 Brompton Rd London Greater London SW3 1JJ",
    "addr:housenumber":"116",
    "addr:postcode":"sw3 1jj",
    "addr:street":"Brompton Rd",
    "iso:country":"GB",
    "sg:address":"116 Brompton Rd",
    "sg:city":"London",
    "sg:classifiers":[
        {
            "category":"Freight",
            "type":"Transportation"
        }
    ],
    "sg:postcode":"SW3 1JJ",
    "sg:province":"Greater London",
    "sg:tags":[
        "overseas",
        "shipping",
        "removal"
    ],
    "wof:name":"Euronav (Uk) Agencies Ltd",
    "wof:placetype":"venue"
},
  "geometry": {"coordinates":[-0.164479,51.499161],"type":"Point"}
}