{
  "type": "Feature",
  "properties": {
    "addr:full":"5 East St Faversham Kent ME13 8AD",
    "addr:housenumber":"5",
    "addr:postcode":"me13 8ad",
    "addr:street":"East St",
    "iso:country":"GB",
    "sg:address":"5 East St",
    "sg:city":"Faversham",
    "sg:classifiers":[
        {
            "category":"Shopping",
            "type":"Retail Goods"
        }
    ],
    "sg:phone":"+44 1795 534948",
    "sg:postcode":"ME13 8AD",
    "sg:province":"Kent",
    "sg:tags":[
        "part",
        "accessory"
    ],
    "wof:name":"Carspot Ltd",
    "wof:placetype":"venue"
},
  "geometry": {"coordinates":[0.892611,51.315266],"type":"Point"}
}