{
  "type": "Feature",
  "properties": {
    "iso:country":"GB",
    "sg:address":"41 Mesnes Street",
    "sg:city":"Wigan",
    "sg:classifiers":[
        {
            "category":"Shopping",
            "subcategory":"Books",
            "type":"Retail Goods"
        }
    ],
    "sg:phone":"+44 1942 242810",
    "sg:postcode":"WN1 1QY",
    "sg:province":"Lancashire",
    "sg:tags":[
        "bookseller"
    ],
    "wof:name":"Smiths of Wigan",
    "wof:placetype":"venue"
},
  "geometry": {"coordinates":[-2.631874,53.549244],"type":"Point"}
}