{
  "type": "Feature",
  "properties": {
    "iso:country":"GB",
    "sg:address":"21 Beach Road",
    "sg:city":"Southsea",
    "sg:classifiers":[
        {
            "category":"Travel",
            "subcategory":"Hotels & Motels",
            "type":"Entertainment"
        }
    ],
    "sg:phone":"+44 23 9273 4108",
    "sg:postcode":"PO5 2JH",
    "sg:province":"Hampshire",
    "sg:tags":[
        "house",
        "guest"
    ],
    "wof:name":"Sherwood Guest House",
    "wof:placetype":"venue"
},
  "geometry": {"coordinates":[-1.082019,50.78051],"type":"Point"}
}