{
  "type": "Feature",
  "properties": {
    "addr:full":"7 Farndale Gardens Shildon Durham DL4 2LZ",
    "addr:housenumber":"7",
    "addr:postcode":"dl4 2lz",
    "addr:street":"Farndale Gardens",
    "iso:country":"GB",
    "sg:address":"7 Farndale Gardens",
    "sg:city":"Shildon",
    "sg:classifiers":[
        {
            "category":"Shopping",
            "subcategory":"Pharmacy",
            "type":"Retail Goods"
        }
    ],
    "sg:phone":"+44 1388 773063",
    "sg:postcode":"DL4 2LZ",
    "sg:province":"Durham",
    "sg:tags":[
        "medicine",
        "therapy"
    ],
    "wof:name":"Harvest Grain Co Ltd The",
    "wof:placetype":"venue"
},
  "geometry": {"coordinates":[-1.629506,54.631233],"type":"Point"}
}