{
  "type": "Feature",
  "properties": {
    "iso:country":"GB",
    "sg:address":"94-96 High Street",
    "sg:city":"Canvey Island",
    "sg:classifiers":[
        {
            "category":"Professional",
            "subcategory":"Lawyer & Legal Services",
            "type":"Services"
        }
    ],
    "sg:phone":"+44 1268 692255",
    "sg:postcode":"SS8 7SU",
    "sg:province":"Essex",
    "sg:tags":[
        "solicitor"
    ],
    "wof:name":"Hook & Partners",
    "wof:placetype":"venue"
},
  "geometry": {"coordinates":[0.597916,51.522621],"type":"Point"}
}