{
  "type": "Feature",
  "properties": {
    "addr:full":"228 Station Road, Bamber Bridge Preston Lancashire PR5 6TQ",
    "addr:housenumber":"228",
    "addr:postcode":"pr5 6tq",
    "addr:street":"Station Road",
    "iso:country":"GB",
    "sg:address":"228 Station Road, Bamber Bridge",
    "sg:city":"Preston",
    "sg:classifiers":[
        {
            "category":"Shopping",
            "subcategory":"Gifts & Souvenirs",
            "type":"Retail Goods"
        }
    ],
    "sg:postcode":"PR5 6TQ",
    "sg:province":"Lancashire",
    "sg:tags":[
        "poster",
        "card"
    ],
    "wof:name":"Cameo Cards",
    "wof:placetype":"venue"
},
  "geometry": {"coordinates":[-2.660654,53.727592],"type":"Point"}
}