{
  "type": "Feature",
  "properties": {
    "addr:full":"34 Bruton Place London Greater London W1J 6LD",
    "addr:housenumber":"34",
    "addr:postcode":"w1j 6ld",
    "addr:street":"Bruton Place",
    "iso:country":"GB",
    "sg:address":"34 Bruton Place",
    "sg:city":"London",
    "sg:classifiers":[
        {
            "category":"Retail",
            "subcategory":"Laundry & Dry Cleaning",
            "type":"Services"
        }
    ],
    "sg:phone":"+44 20 8802 4836",
    "sg:postcode":"W1J 6LD",
    "sg:province":"Greater London",
    "sg:tags":[
        "alteration"
    ],
    "wof:name":"Lilliman & Cox Ltd.",
    "wof:placetype":"venue"
},
  "geometry": {"coordinates":[-0.1454170048,51.5109786987],"type":"Point"}
}