{
  "type": "Feature",
  "properties": {
    "addr:full":"The Thorley Centre Bishops Stortford Essex CM23 4EG",
    "addr:postcode":"cm23 4eg",
    "iso:country":"GB",
    "sg:address":"The Thorley Centre",
    "sg:city":"Bishops Stortford",
    "sg:classifiers":[
        {
            "category":"Bars & Pubs",
            "type":"Food & Drink"
        }
    ],
    "sg:phone":"+44 1279 652101",
    "sg:postcode":"CM23 4EG",
    "sg:province":"Essex",
    "sg:tags":[
        "pubs",
        "inn"
    ],
    "wof:name":"Marne Inn",
    "wof:placetype":"venue"
},
  "geometry": {"coordinates":[0.161956,51.872356],"type":"Point"}
}