{
  "type": "Feature",
  "properties": {
    "iso:country":"GB",
    "sg:address":"Unit 68-70 Aflex Palace, 52 Church St",
    "sg:city":"Manchester",
    "sg:classifiers":[
        {
            "category":"Shopping",
            "subcategory":"Gifts & Souvenirs",
            "type":"Retail Goods"
        }
    ],
    "sg:postcode":"M4 1PW",
    "sg:province":"Greater Manchester",
    "sg:tags":[
        "shop"
    ],
    "wof:name":"Raaj,C,",
    "wof:placetype":"venue"
},
  "geometry": {"coordinates":[-2.23763,53.482979],"type":"Point"}
}