{
  "type": "Feature",
  "properties": {
    "iso:country":"GB",
    "sg:address":"20 South St Andrews Street",
    "sg:city":"Edinburgh",
    "sg:classifiers":[
        {
            "category":"Professional",
            "subcategory":"Management & Consulting",
            "type":"Services"
        }
    ],
    "sg:phone":"+44 131 557 0123",
    "sg:postcode":"EH2 2AZ",
    "sg:province":"City of Edinburgh",
    "sg:tags":[
        "marketing",
        "consultant"
    ],
    "wof:name":"Caci (U K) Ltd.",
    "wof:placetype":"venue"
},
  "geometry": {"coordinates":[-3.1918990612,55.9534873962],"type":"Point"}
}