{
  "type": "Feature",
  "properties": {
    "iso:country":"GB",
    "sg:address":"Caenby Corner",
    "sg:city":"Market Rasen",
    "sg:classifiers":[
        {
            "category":"Home & Garden",
            "subcategory":"Home Furnishings",
            "type":"Retail Goods"
        }
    ],
    "sg:phone":"+44 1673 878500",
    "sg:postcode":"LN8 2BU",
    "sg:province":"Lincolnshire",
    "sg:tags":[
        "homefurnishings"
    ],
    "wof:name":"Benwood Pine",
    "wof:placetype":"venue"
},
  "geometry": {"coordinates":[-0.4997679889,53.3876914978],"type":"Point"}
}