{
  "type": "Feature",
  "properties": {
    "iso:country":"GB",
    "sg:address":"The Gables Clinic 108 High St",
    "sg:city":"Uckfield",
    "sg:classifiers":[
        {
            "category":"Health Services",
            "subcategory":"Health Practitioner",
            "type":"Services"
        }
    ],
    "sg:phone":"+44 1825 766529",
    "sg:postcode":"TN22 1PX",
    "sg:province":"East Sussex",
    "sg:tags":[
        "osteopath"
    ],
    "wof:name":"L Oakenfold DO",
    "wof:placetype":"venue"
},
  "geometry": {"coordinates":[0.0966499969,50.9718132019],"type":"Point"}
}