{
  "type": "Feature",
  "properties": {
    "iso:country":"GB",
    "sg:address":"25 Angus Drive",
    "sg:city":"Ruislip",
    "sg:classifiers":[
        {
            "category":"Retail",
            "subcategory":"Driving School",
            "type":"Services"
        }
    ],
    "sg:phone":"+44 20 8841 4037",
    "sg:postcode":"HA4 0RZ",
    "sg:province":"Greater London",
    "wof:name":"Adrian School of Motoring",
    "wof:placetype":"venue"
},
  "geometry": {"coordinates":[-0.3957020044,51.5601997375],"type":"Point"}
}