{
  "type": "Feature",
  "properties": {
    "iso:country":"GB",
    "sg:address":"The Hermitage, Main St",
    "sg:city":"Buckingham",
    "sg:classifiers":[
        {
            "category":"Social Services",
            "subcategory":"Child Care",
            "type":"Services"
        }
    ],
    "sg:phone":"+44 1280 822669",
    "sg:postcode":"MK18 2AP",
    "sg:province":"Buckinghamshire",
    "sg:tags":[
        "agency",
        "nanny"
    ],
    "wof:name":"Buckingham Nannies",
    "wof:placetype":"venue"
},
  "geometry": {"coordinates":[-0.986479,52.000751],"type":"Point"}
}