{
  "type": "Feature",
  "properties": {
    "addr:full":"Woodlands, Hollins Hill Shipley West Yorkshire BD17 7QN",
    "addr:postcode":"bd17 7qn",
    "addr:street":"Hollins Hill",
    "iso:country":"GB",
    "sg:address":"Woodlands, Hollins Hill",
    "sg:city":"Shipley",
    "sg:classifiers":[
        {
            "category":"Utilities",
            "subcategory":"Electric",
            "type":"Services"
        }
    ],
    "sg:phone":"+44 1274 591482",
    "sg:postcode":"BD17 7QN",
    "sg:province":"West Yorkshire",
    "sg:tags":[
        "electrical",
        "contractor"
    ],
    "wof:name":"S and J Beaumont",
    "wof:placetype":"venue"
},
  "geometry": {"coordinates":[-1.772899,53.837975],"type":"Point"}
}