{
  "type": "Feature",
  "properties": {
    "addr:full":"204b The Business Village London Greater London SW18 4JQ",
    "addr:housenumber":"204b",
    "addr:postcode":"sw18 4jq",
    "addr:street":"The Business Village",
    "iso:country":"GB",
    "sg:address":"204b The Business Village",
    "sg:city":"London",
    "sg:classifiers":[
        {
            "category":"Shopping",
            "subcategory":"Mobile Phones",
            "type":"Retail Goods"
        }
    ],
    "sg:postcode":"SW18 4JQ",
    "sg:province":"Greater London",
    "wof:name":"Network Cellular Communications Ltd.",
    "wof:placetype":"venue"
},
  "geometry": {"coordinates":[-0.19831,51.45686],"type":"Point"}
}