{
  "type": "Feature",
  "properties": {
    "iso:country":"GB",
    "sg:address":"Rowley Park Farm, Worfield",
    "sg:city":"Bridgnorth",
    "sg:classifiers":[
        {
            "category":"Farming",
            "subcategory":"Livestock Farm",
            "type":"Manufacturing & Wholesale Goods"
        }
    ],
    "sg:postcode":"WV15 5NT",
    "sg:province":"Shropshire",
    "sg:tags":[
        "others"
    ],
    "wof:name":"J H Chester",
    "wof:placetype":"venue"
},
  "geometry": {"coordinates":[-2.358624,52.556946],"type":"Point"}
}