{
  "type": "Feature",
  "properties": {
    "addr:full":"Bell Court Stratford-upon-avon Warwickshire CV37 6JP",
    "addr:postcode":"cv37 6jp",
    "addr:street":"Bell Court",
    "iso:country":"GB",
    "sg:address":"Bell Court",
    "sg:city":"Stratford-upon-avon",
    "sg:classifiers":[
        {
            "category":"Shopping",
            "subcategory":"Comic Books",
            "type":"Retail Goods"
        }
    ],
    "sg:phone":"+44 1789 267276",
    "sg:postcode":"CV37 6JP",
    "sg:province":"Warwickshire",
    "sg:tags":[
        "jeweller"
    ],
    "wof:name":"Dynasty",
    "wof:placetype":"venue"
},
  "geometry": {"coordinates":[-1.7072689533,52.1941337585],"type":"Point"}
}