{
  "type": "Feature",
  "properties": {
    "iso:country":"GB",
    "sg:address":"1 Harley St",
    "sg:city":"West End",
    "sg:classifiers":[
        {
            "category":"Health Services",
            "subcategory":"Health Practitioner",
            "type":"Services"
        }
    ],
    "sg:phone":"+44 20 7636 5681",
    "sg:postcode":"W1N 1DA",
    "sg:province":"Hampshire",
    "sg:tags":[
        "osteopath"
    ],
    "wof:name":"Stephen J Lusty",
    "wof:placetype":"venue"
},
  "geometry": {"coordinates":[-0.14623,51.516972],"type":"Point"}
}