{
  "type": "Feature",
  "properties": {
    "addr:full":"70 Craddock Street Wolverhampton Shropshire WV6 0QJ",
    "addr:housenumber":"70",
    "addr:postcode":"wv6 0qj",
    "addr:street":"Craddock Street",
    "iso:country":"GB",
    "sg:address":"70 Craddock Street",
    "sg:city":"Wolverhampton",
    "sg:classifiers":[
        {
            "category":"Recreation",
            "subcategory":"Dog Park",
            "type":"Entertainment"
        }
    ],
    "sg:phone":"+44 1902 688838",
    "sg:postcode":"WV6 0QJ",
    "sg:province":"Shropshire",
    "wof:name":"Heads & Tails",
    "wof:placetype":"venue"
},
  "geometry": {"coordinates":[-2.140654,52.597206],"type":"Point"}
}