{
  "type": "Feature",
  "properties": {
    "iso:country":"GB",
    "sg:address":"3 Newport Crescent",
    "sg:city":"Middlesbrough",
    "sg:classifiers":[
        {
            "category":"Personal",
            "subcategory":"Beauty Salon",
            "type":"Services"
        }
    ],
    "sg:phone":"+44 1642 242892",
    "sg:postcode":"TS1 5EP",
    "sg:province":"North Yorkshire",
    "sg:tags":[
        "unisex",
        "hairdresser"
    ],
    "wof:name":"Zed Hair Co.",
    "wof:placetype":"venue"
},
  "geometry": {"coordinates":[-1.237712,54.575939],"type":"Point"}
}