{
  "type": "Feature",
  "properties": {
    "iso:country":"GB",
    "sg:address":"17 Southport Road",
    "sg:city":"Chorley",
    "sg:classifiers":[
        {
            "category":"Health Services",
            "subcategory":"Nursing And Care Facility",
            "type":"Services"
        }
    ],
    "sg:phone":"+44 1257 260474",
    "sg:postcode":"PR7 1LB",
    "sg:province":"Lancashire",
    "sg:tags":[
        "home"
    ],
    "wof:name":"Lynden Villa",
    "wof:placetype":"venue"
},
  "geometry": {"coordinates":[-2.639219,53.653362],"type":"Point"}
}