{
  "type": "Feature",
  "properties": {
    "iso:country":"GB",
    "sg:address":"The Square, Stow On The Wold",
    "sg:city":"Cheltenham",
    "sg:classifiers":[
        {
            "category":"Shopping",
            "subcategory":"Antiques",
            "type":"Retail Goods"
        }
    ],
    "sg:postcode":"GL54 1AB",
    "sg:province":"Gloucestershire",
    "wof:name":"Changelike Ltd.",
    "wof:placetype":"venue"
},
  "geometry": {"coordinates":[-1.7235239744,51.9291343689],"type":"Point"}
}