{
  "type": "Feature",
  "properties": {
    "addr:full":"22 York Street Colne Lancashire BB8 0ND",
    "addr:housenumber":"22",
    "addr:postcode":"bb8 0nd",
    "addr:street":"York Street",
    "iso:country":"GB",
    "sg:address":"22 York Street",
    "sg:city":"Colne",
    "sg:classifiers":[
        {
            "category":"Building & Trades",
            "subcategory":"Plumbing",
            "type":"Services"
        }
    ],
    "sg:phone":"+44 1282 861070",
    "sg:postcode":"BB8 0ND",
    "sg:province":"Lancashire",
    "sg:tags":[
        "plumber",
        "heating"
    ],
    "wof:name":"Geoff Ellis Plumbing & Heating",
    "wof:placetype":"venue"
},
  "geometry": {"coordinates":[-2.1609990597,53.8590660095],"type":"Point"}
}