{
  "type": "Feature",
  "properties": {
    "addr:full":"Foster Ave Bilston West Midlands WV14 9PT",
    "addr:postcode":"wv14 9pt",
    "addr:street":"Foster Ave",
    "iso:country":"GB",
    "sg:address":"Foster Ave",
    "sg:city":"Bilston",
    "sg:classifiers":[
        {
            "category":"Farming",
            "subcategory":"Nursery",
            "type":"Manufacturing & Wholesale Goods"
        },
        {
            "category":"Government",
            "subcategory":"Office",
            "type":"Public Place"
        }
    ],
    "sg:postcode":"WV14 9PT",
    "sg:province":"West Midlands",
    "sg:tags":[
        "local",
        "creche"
    ],
    "wof:name":"Wolverhampton Borough Council",
    "wof:placetype":"venue"
},
  "geometry": {"coordinates":[-2.0963480473,52.5480194092],"type":"Point"}
}