{
  "type": "Feature",
  "properties": {
    "iso:country":"GB",
    "sg:address":"26 Church Road, Great Glen",
    "sg:city":"Leicester",
    "sg:classifiers":[
        {
            "category":"Professional",
            "subcategory":"Employment Agencies",
            "type":"Services"
        }
    ],
    "sg:postcode":"LE8 9FE",
    "sg:province":"Leicestershire",
    "sg:tags":[
        "consultant"
    ],
    "wof:name":"Falcon Industrial Services",
    "wof:placetype":"venue"
},
  "geometry": {"coordinates":[-1.0349440575,52.5744972229],"type":"Point"}
}