{
  "type": "Feature",
  "properties": {
    "iso:country":"GB",
    "sg:address":"Street Farm, High St",
    "sg:city":"Chippenham",
    "sg:classifiers":[
        {
            "category":"Banks & Credit Unions",
            "subcategory":"Investment Brokerage",
            "type":"Services"
        }
    ],
    "sg:phone":"+44 1249 782976",
    "sg:postcode":"SN14 7BG",
    "sg:province":"Gloucestershire",
    "sg:tags":[
        "contractor"
    ],
    "wof:name":"C K Read",
    "wof:placetype":"venue"
},
  "geometry": {"coordinates":[-2.19287,51.487259],"type":"Point"}
}