{
  "type": "Feature",
  "properties": {
    "addr:full":"140 Edgely Rd London Greater London SW4 6HB",
    "addr:housenumber":"140",
    "addr:postcode":"sw4 6hb",
    "addr:street":"Edgely Rd",
    "iso:country":"GB",
    "sg:address":"140 Edgely Rd",
    "sg:city":"London",
    "sg:classifiers":[
        {
            "category":"Banks & Credit Unions",
            "subcategory":"Financial Services",
            "type":"Services"
        }
    ],
    "sg:phone":"+44 20 7630 0582",
    "sg:postcode":"SW4 6HB",
    "sg:province":"Greater London",
    "sg:tags":[
        "adviser"
    ],
    "wof:name":"C4 Consulting Ltd",
    "wof:placetype":"venue"
},
  "geometry": {"coordinates":[-0.1366569996,51.4681549072],"type":"Point"}
}