{
  "type": "Feature",
  "properties": {
    "iso:country":"GB",
    "sg:address":"Unit D, Burnham Road",
    "sg:city":"Dartford",
    "sg:classifiers":[
        {
            "category":"Professional",
            "subcategory":"Engineering",
            "type":"Services"
        },
        {
            "category":"Shopping",
            "subcategory":"Computers & Home Electronics",
            "type":"Retail Goods"
        }
    ],
    "sg:phone":"+44 1322 288698",
    "sg:postcode":"DA1 5BN",
    "sg:province":"Kent",
    "sg:tags":[
        "equipment",
        "assembly",
        "electronic",
        "engineer"
    ],
    "wof:name":"Electro Avionics",
    "wof:placetype":"venue"
},
  "geometry": {"coordinates":[0.2082249969,51.4541473389],"type":"Point"}
}