{
  "type": "Feature",
  "properties": {
    "iso:country":"GB",
    "sg:address":"Sedgley Rd West",
    "sg:city":"Tipton",
    "sg:classifiers":[
        {
            "category":"Autos & Motor Vehicles",
            "subcategory":"Automobile Sales",
            "type":"Retail Goods"
        }
    ],
    "sg:postcode":"DY4 8AP",
    "sg:province":"West Midlands",
    "sg:tags":[
        "car"
    ],
    "wof:name":"Dale,Bill,",
    "wof:placetype":"venue"
},
  "geometry": {"coordinates":[-2.083269,52.530853],"type":"Point"}
}