{
  "type": "Feature",
  "properties": {
    "addr:full":"Unit 23, Trent Lane Industrial Estate, Willow Road Derby Leicestershire DE74 2NP",
    "addr:housenumber":"unit 23",
    "addr:postcode":"de74 2np",
    "addr:street":"Trent Lane Industrial Estate Willow Road",
    "iso:country":"GB",
    "sg:address":"Unit 23, Trent Lane Industrial Estate, Willow Road",
    "sg:city":"Derby",
    "sg:classifiers":[
        {
            "category":"Building & Trades",
            "subcategory":"Equipment Rental",
            "type":"Services"
        }
    ],
    "sg:phone":"+44 1332 853888",
    "sg:postcode":"DE74 2NP",
    "sg:province":"Leicestershire",
    "sg:tags":[
        "horticultural"
    ],
    "wof:name":"Growing Technologies Ltd.",
    "wof:placetype":"venue"
},
  "geometry": {"coordinates":[-1.3376749754,52.8490219116],"type":"Point"}
}