{
  "type": "Feature",
  "properties": {
    "iso:country":"GB",
    "sg:address":"200 Nottingham Road, Borrowash",
    "sg:city":"Derby",
    "sg:classifiers":[
        {
            "category":"Building & Trades",
            "subcategory":"Construction",
            "type":"Services"
        }
    ],
    "sg:phone":"+44 1332 662914",
    "sg:postcode":"DE72 3FR",
    "sg:province":"Derbyshire",
    "sg:tags":[
        "builder"
    ],
    "wof:name":"John R Kingham Upholstery",
    "wof:placetype":"venue"
},
  "geometry": {"coordinates":[-1.3688789606,52.9054336548],"type":"Point"}
}