{
  "type": "Feature",
  "properties": {
    "iso:country":"GB",
    "sg:address":"22 Grange Road",
    "sg:city":"Newark",
    "sg:classifiers":[
        {
            "category":"Building & Trades",
            "subcategory":"Plumbing",
            "type":"Services"
        }
    ],
    "sg:postcode":"NG24 4LE",
    "sg:province":"Nottinghamshire",
    "sg:tags":[
        "heating"
    ],
    "wof:name":"Paul Derry",
    "wof:placetype":"venue"
},
  "geometry": {"coordinates":[-0.809345,53.057533],"type":"Point"}
}