{
  "type": "Feature",
  "properties": {
    "addr:full":"22 Grange Road Newark Nottinghamshire NG24 4LE",
    "addr:housenumber":"22",
    "addr:postcode":"ng24 4le",
    "addr:street":"Grange Road",
    "iso:country":"GB",
    "sg:address":"22 Grange Road",
    "sg:city":"Newark",
    "sg:classifiers":[
        {
            "category":"Building & Trades",
            "subcategory":"Plumbing",
            "type":"Services"
        }
    ],
    "sg:postcode":"NG24 4LE",
    "sg:province":"Nottinghamshire",
    "sg:tags":[
        "heating"
    ],
    "wof:name":"Paul Derry",
    "wof:placetype":"venue"
},
  "geometry": {"coordinates":[-0.809345,53.057533],"type":"Point"}
}