{
  "type": "Feature",
  "properties": {
    "addr:full":"Weoley Avenue Birmingham West Midlands B29 6PU",
    "addr:postcode":"b29 6pu",
    "addr:street":"Weoley Avenue",
    "iso:country":"GB",
    "sg:address":"Weoley Avenue",
    "sg:city":"Birmingham",
    "sg:classifiers":[
        {
            "category":"Organizations",
            "subcategory":"Community Association",
            "type":"Services"
        },
        {
            "category":"Organizations",
            "subcategory":"Membership Organization",
            "type":"Services"
        }
    ],
    "sg:phone":"+44 121 472 2910",
    "sg:postcode":"B29 6PU",
    "sg:province":"West Midlands",
    "sg:tags":[
        "club",
        "social"
    ],
    "wof:name":"AVENUE SOCIAL CLUB",
    "wof:placetype":"venue"
},
  "geometry": {"coordinates":[-1.9578540325,52.44348526],"type":"Point"}
}