{
  "type": "Feature",
  "properties": {
    "addr:full":"4 Bay Terrace Pevensey East Sussex BN24 6EE",
    "addr:housenumber":"4",
    "addr:postcode":"bn24 6ee",
    "addr:street":"Bay",
    "iso:country":"GB",
    "sg:address":"4 Bay Terrace",
    "sg:city":"Pevensey",
    "sg:classifiers":[
        {
            "category":"Professional",
            "subcategory":"Management & Consulting",
            "type":"Services"
        }
    ],
    "sg:postcode":"BN24 6EE",
    "sg:province":"East Sussex",
    "sg:tags":[
        "marketing",
        "consultant"
    ],
    "wof:name":"Channel 2000 Ltd.",
    "wof:placetype":"venue"
},
  "geometry": {"coordinates":[0.3503710032,50.8115844727],"type":"Point"}
}