{
  "type": "Feature",
  "properties": {
    "iso:country":"GB",
    "sg:address":"3 Colescroft Hill",
    "sg:city":"Purley",
    "sg:classifiers":[
        {
            "category":"Building & Trades",
            "subcategory":"Plumbing",
            "type":"Services"
        }
    ],
    "sg:phone":"+44 20 8660 3687",
    "sg:postcode":"CR8 4BB",
    "sg:province":"Surrey",
    "sg:tags":[
        "plumber",
        "heating"
    ],
    "wof:name":"MARTIN BENHAM",
    "wof:placetype":"venue"
},
  "geometry": {"coordinates":[-0.115701,51.319263],"type":"Point"}
}