{
  "type": "Feature",
  "properties": {
    "iso:country":"GB",
    "sg:address":"Liverpool Airport, Speke",
    "sg:city":"Liverpool",
    "sg:classifiers":[
        {
            "category":"Parking",
            "type":"Transportation"
        }
    ],
    "sg:phone":"+44 20 7499 7050",
    "sg:postcode":"L24 8QD",
    "sg:province":"Merseyside",
    "sg:tags":[
        "car",
        "park"
    ],
    "wof:name":"Ncp",
    "wof:placetype":"venue"
},
  "geometry": {"coordinates":[-2.88255,53.34798],"type":"Point"}
}