{
  "type": "Feature",
  "properties": {
    "addr:full":"Tryfan, Caerhun Bangor Gwynedd LL57 4DT",
    "addr:postcode":"ll57 4dt",
    "iso:country":"GB",
    "sg:address":"Tryfan, Caerhun",
    "sg:city":"Bangor",
    "sg:classifiers":[
        {
            "category":"Social Services",
            "subcategory":"Retirement Home",
            "type":"Services"
        }
    ],
    "sg:phone":"+44 1248 361092",
    "sg:postcode":"LL57 4DT",
    "sg:province":"Gwynedd",
    "sg:tags":[
        "residential",
        "care"
    ],
    "wof:name":"Oakdale Residential Home",
    "wof:placetype":"venue"
},
  "geometry": {"coordinates":[-4.137094,53.199203],"type":"Point"}
}