{
  "type": "Feature",
  "properties": {
    "addr:full":"71 Slade Road, Roughley Sutton Coldfield Staffordshire B75 5PB",
    "addr:housenumber":"71",
    "addr:postcode":"b75 5pb",
    "addr:street":"Slade Road",
    "iso:country":"GB",
    "sg:address":"71 Slade Road, Roughley",
    "sg:city":"Sutton Coldfield",
    "sg:classifiers":[
        {
            "category":"Building & Trades",
            "subcategory":"Construction",
            "type":"Services"
        }
    ],
    "sg:postcode":"B75 5PB",
    "sg:province":"Staffordshire",
    "sg:tags":[
        "resurfacing",
        "laying",
        "floor"
    ],
    "wof:name":"P G A Morgan",
    "wof:placetype":"venue"
},
  "geometry": {"coordinates":[-1.8086839914,52.5896186829],"type":"Point"}
}