{
  "type": "Feature",
  "properties": {
    "iso:country":"GB",
    "sg:address":"80 Kingsland Crescent",
    "sg:city":"Barry",
    "sg:classifiers":[
        {
            "category":"Building & Trades",
            "subcategory":"Construction",
            "type":"Services"
        }
    ],
    "sg:phone":"+44 1446 420308",
    "sg:postcode":"CF63 4JS",
    "sg:province":"The Vale of Glamorgan",
    "sg:tags":[
        "glazier"
    ],
    "wof:name":"Mark James",
    "wof:placetype":"venue"
},
  "geometry": {"coordinates":[-3.264995,51.404854],"type":"Point"}
}