{
  "type": "Feature",
  "properties": {
    "iso:country":"GB",
    "sg:address":"Front Street, Sherburn",
    "sg:city":"Durham",
    "sg:classifiers":[
        {
            "category":"Bars & Pubs",
            "type":"Food & Drink"
        }
    ],
    "sg:phone":"+44 191 372 2632",
    "sg:postcode":"DH6 2NB",
    "sg:province":"Durham",
    "sg:tags":[
        "pubs",
        "inn"
    ],
    "wof:name":"Cross Keys Inn",
    "wof:placetype":"venue"
},
  "geometry": {"coordinates":[-1.4177039862,54.7848548889],"type":"Point"}
}