{
  "type": "Feature",
  "properties": {
    "addr:full":"Unit 2 Anglia Trading Estate, Clarendon Way Colchester Essex CO1 1XF",
    "addr:housenumber":"unit 2 anglia",
    "addr:postcode":"co1 1xf",
    "addr:street":"Trading Estate Clarendon Way",
    "iso:country":"GB",
    "sg:address":"Unit 2 Anglia Trading Estate, Clarendon Way",
    "sg:city":"Colchester",
    "sg:classifiers":[
        {
            "category":"Shopping",
            "subcategory":"Discount & Variety Stores",
            "type":"Retail Goods"
        }
    ],
    "sg:phone":"+44 1206 544877",
    "sg:postcode":"CO1 1XF",
    "sg:province":"Essex",
    "sg:tags":[
        "centre"
    ],
    "wof:name":"C R Supplies Ltd.",
    "wof:placetype":"venue"
},
  "geometry": {"coordinates":[0.89805,51.89872],"type":"Point"}
}