{
  "type": "Feature",
  "properties": {
    "iso:country":"GB",
    "sg:address":"41 Villiers Road",
    "sg:city":"Southall",
    "sg:classifiers":[
        {
            "category":"Organizations",
            "subcategory":"Non-profit Organization",
            "type":"Services"
        }
    ],
    "sg:phone":"+44 20 8574 1892",
    "sg:postcode":"UB1 3BS",
    "sg:province":"Greater London",
    "sg:tags":[
        "charitable",
        "organisation",
        "voluntary",
        "charity"
    ],
    "wof:name":"Missionaries Of Charity",
    "wof:placetype":"venue"
},
  "geometry": {"coordinates":[-0.375124,51.507851],"type":"Point"}
}