{
  "type": "Feature",
  "properties": {
    "addr:full":"42 Maida Vale London Greater London W9 1RP",
    "addr:housenumber":"42",
    "addr:postcode":"w9 1rp",
    "addr:street":"Maida Vale",
    "iso:country":"GB",
    "sg:address":"42 Maida Vale",
    "sg:city":"London",
    "sg:classifiers":[
        {
            "category":"Government",
            "subcategory":"Embassy",
            "type":"Public Place"
        }
    ],
    "sg:phone":"+44 20 7286 1297",
    "sg:postcode":"W9 1RP",
    "sg:province":"Greater London",
    "sg:tags":[
        "consulate"
    ],
    "wof:name":"Embassy of the People's Republic of China",
    "wof:placetype":"venue"
},
  "geometry": {"coordinates":[-0.183221,51.530022],"type":"Point"}
}