{
  "type": "Feature",
  "properties": {
    "addr:full":"Robsack Commuinty Centre, Odeam Drive St Leonards-on-sea East Sussex TN38 9TW",
    "addr:postcode":"tn38 9tw",
    "addr:street":"Odeam Drive St Leonards-On-Sea",
    "iso:country":"GB",
    "sg:address":"Robsack Commuinty Centre, Odeam Drive",
    "sg:city":"St Leonards-on-sea",
    "sg:classifiers":[
        {
            "category":"Education",
            "subcategory":"Preschool",
            "type":"Public Place"
        }
    ],
    "sg:phone":"+44 1424 853334",
    "sg:postcode":"TN38 9TW",
    "sg:province":"East Sussex",
    "sg:tags":[
        "pre-school",
        "playgroups"
    ],
    "wof:name":"Robsack Playlink",
    "wof:placetype":"venue"
},
  "geometry": {"coordinates":[0.552515,50.855743],"type":"Point"}
}