{
  "type": "Feature",
  "properties": {
    "iso:country":"GB",
    "sg:address":"74 Cedar Avenue",
    "sg:city":"Wickford",
    "sg:classifiers":[
        {
            "category":"Professional",
            "type":"Services"
        }
    ],
    "sg:phone":"+44 1268 763753",
    "sg:postcode":"SS12 9DX",
    "sg:province":"Essex",
    "sg:tags":[
        "entertainer"
    ],
    "wof:name":"E B A",
    "wof:placetype":"venue"
},
  "geometry": {"coordinates":[0.516336,51.602093],"type":"Point"}
}