{
  "type": "Feature",
  "properties": {
    "addr:full":"118 Stanley Street Accrington Lancashire BB5 6QG",
    "addr:housenumber":"118",
    "addr:postcode":"bb5 6qg",
    "addr:street":"Stanley Street",
    "iso:country":"GB",
    "sg:address":"118 Stanley Street",
    "sg:city":"Accrington",
    "sg:classifiers":[
        {
            "category":"Shopping",
            "subcategory":"News",
            "type":"Retail Goods"
        }
    ],
    "sg:phone":"+44 1254 232280",
    "sg:postcode":"BB5 6QG",
    "sg:province":"Lancashire",
    "sg:tags":[
        "newsagent"
    ],
    "wof:name":"Geoffrey J Cronshaw",
    "wof:placetype":"venue"
},
  "geometry": {"coordinates":[-2.3564209938,53.7553710938],"type":"Point"}
}