{
  "type": "Feature",
  "properties": {
    "iso:country":"GB",
    "sg:address":"34-40 Kirkgate",
    "sg:city":"Otley",
    "sg:classifiers":[
        {
            "category":"Shopping",
            "subcategory":"Department Store",
            "type":"Retail Goods"
        }
    ],
    "sg:phone":"+44 1943 462098",
    "sg:postcode":"LS21 3HL",
    "sg:province":"North Yorkshire",
    "sg:tags":[
        "departmental"
    ],
    "wof:name":"Woolworths Plc",
    "wof:placetype":"venue"
},
  "geometry": {"coordinates":[-1.693947,53.904808],"type":"Point"}
}