{
  "type": "Feature",
  "properties": {
    "iso:country":"GB",
    "sg:address":"15 Llanrumney Avenue, Rumney",
    "sg:city":"Cardiff",
    "sg:classifiers":[
        {
            "category":"Professional",
            "subcategory":"Art Services",
            "type":"Services"
        }
    ],
    "sg:phone":"+44 29 2079 1631",
    "sg:postcode":"CF3 4BP",
    "sg:province":"Caerphilly",
    "sg:tags":[
        "photographer"
    ],
    "wof:name":"Anthony Howell Studio",
    "wof:placetype":"venue"
},
  "geometry": {"coordinates":[-3.131483,51.511009],"type":"Point"}
}