{
  "type": "Feature",
  "properties": {
    "addr:full":"1 Rochester Street, Medway Chatham Kent ME4 6RT",
    "addr:housenumber":"1",
    "addr:postcode":"me4 6rt",
    "addr:street":"Rochester Street",
    "iso:country":"GB",
    "sg:address":"1 Rochester Street, Medway",
    "sg:city":"Chatham",
    "sg:classifiers":[
        {
            "category":"Shopping",
            "subcategory":"Department Store",
            "type":"Retail Goods"
        }
    ],
    "sg:phone":"+44 1634 401686",
    "sg:postcode":"ME4 6RT",
    "sg:province":"Kent",
    "wof:name":"Kanabar Groceries",
    "wof:placetype":"venue"
},
  "geometry": {"coordinates":[0.520508,51.377357],"type":"Point"}
}