{
  "type": "Feature",
  "properties": {
    "addr:full":"52 Eagle Street Stoke-on-trent Staffordshire ST1 3PE",
    "addr:housenumber":"52",
    "addr:postcode":"st1 3pe",
    "addr:street":"Eagle Street",
    "iso:country":"GB",
    "sg:address":"52 Eagle Street",
    "sg:city":"Stoke-on-trent",
    "sg:classifiers":[
        {
            "category":"Utilities",
            "subcategory":"Refuse",
            "type":"Services"
        },
        {
            "category":"Professional",
            "subcategory":"Business Services",
            "type":"Services"
        }
    ],
    "sg:postcode":"ST1 3PE",
    "sg:province":"Staffordshire",
    "sg:tags":[
        "skip",
        "hire",
        "answering"
    ],
    "wof:name":"The Message Centre",
    "wof:placetype":"venue"
},
  "geometry": {"coordinates":[-2.1640620232,53.0238838196],"type":"Point"}
}