{
  "type": "Feature",
  "properties": {
    "addr:full":"23a Gold Street Northampton Northamptonshire NN1 1RA",
    "addr:housenumber":"23a",
    "addr:postcode":"nn1 1ra",
    "addr:street":"Gold Street",
    "iso:country":"GB",
    "sg:address":"23a Gold Street",
    "sg:city":"Northampton",
    "sg:classifiers":[
        {
            "category":"Restaurant",
            "type":"Food & Drink"
        }
    ],
    "sg:postcode":"NN1 1RA",
    "sg:province":"Northamptonshire",
    "wof:name":"Fontana,Tomata,",
    "wof:placetype":"venue"
},
  "geometry": {"coordinates":[-0.899749,52.236649],"type":"Point"}
}