{
  "type": "Feature",
  "properties": {
    "iso:country":"GB",
    "sg:address":"17 Clasketgate",
    "sg:city":"Lincoln",
    "sg:classifiers":[
        {
            "category":"Fast Food",
            "type":"Food & Drink"
        }
    ],
    "sg:postcode":"LN2 1JJ",
    "sg:province":"Lincolnshire",
    "sg:tags":[
        "away",
        "take"
    ],
    "wof:name":"La Scala",
    "wof:placetype":"venue"
},
  "geometry": {"coordinates":[-0.538867,53.230576],"type":"Point"}
}