{
  "type": "Feature",
  "properties": {
    "addr:full":"17 Devonshire Cres, Mill Hill Mill Hill Greater London NW7 1DW",
    "addr:housenumber":"17",
    "addr:postcode":"nw7 1dw",
    "addr:street":"Devonshire Cres Mill Hill;Hill",
    "iso:country":"GB",
    "sg:address":"17 Devonshire Cres, Mill Hill",
    "sg:city":"Mill Hill",
    "sg:classifiers":[
        {
            "category":"Health Services",
            "subcategory":"Podiatrist",
            "type":"Services"
        }
    ],
    "sg:phone":"+44 20 8349 3039",
    "sg:postcode":"NW7 1DW",
    "sg:province":"Greater London",
    "sg:tags":[
        "podiatrists",
        "chiropodist"
    ],
    "wof:name":"Annette Danemann",
    "wof:placetype":"venue"
},
  "geometry": {"coordinates":[-0.213676,51.606571],"type":"Point"}
}