{
  "type": "Feature",
  "properties": {
    "addr:full":"1 Souters Lane Chester Cheshire CH1 1SH",
    "addr:housenumber":"1",
    "addr:postcode":"ch1 1sh",
    "addr:street":"Souters Lane",
    "iso:country":"GB",
    "sg:address":"1 Souters Lane",
    "sg:city":"Chester",
    "sg:classifiers":[
        {
            "category":"Restaurant",
            "type":"Food & Drink"
        }
    ],
    "sg:phone":"+44 1244 311518",
    "sg:postcode":"CH1 1SH",
    "sg:province":"Cheshire",
    "wof:name":"Old Orleans",
    "wof:placetype":"venue"
},
  "geometry": {"coordinates":[-2.887453,53.188396],"type":"Point"}
}