{
  "type": "Feature",
  "properties": {
    "iso:country":"GB",
    "sg:address":"4 Wentloog Rd",
    "sg:city":"Cardiff",
    "sg:classifiers":[
        {
            "category":"Shopping",
            "subcategory":"Used Merchandise",
            "type":"Retail Goods"
        }
    ],
    "sg:phone":"+44 29 2077 8735",
    "sg:postcode":"CF3 8LP",
    "sg:province":"Caerphilly",
    "sg:tags":[
        "shop",
        "second-hand"
    ],
    "wof:name":"Nearly New Shop The",
    "wof:placetype":"venue"
},
  "geometry": {"coordinates":[-3.098289,51.506672],"type":"Point"}
}