{
  "type": "Feature",
  "properties": {
    "iso:country":"GB",
    "sg:address":"106 Warton Street",
    "sg:city":"Lytham St Annes",
    "sg:classifiers":[
        {
            "category":"Professional",
            "subcategory":"Computer Services",
            "type":"Services"
        }
    ],
    "sg:postcode":"FY8 5HA",
    "sg:province":"Lancashire",
    "sg:tags":[
        "system",
        "software"
    ],
    "wof:name":"Wildon Ltd",
    "wof:placetype":"venue"
},
  "geometry": {"coordinates":[-2.950378,53.737724],"type":"Point"}
}