{
  "type": "Feature",
  "properties": {
    "iso:country":"GB",
    "sg:address":"Winter Gardens, Church Street",
    "sg:city":"Blackpool",
    "sg:classifiers":[
        {
            "category":"Arts & Performance",
            "subcategory":"Theater",
            "type":"Entertainment"
        }
    ],
    "sg:phone":"+44 1253 292029",
    "sg:postcode":"FY1 1HW",
    "sg:province":"Lancashire",
    "sg:tags":[
        "hall",
        "theatre",
        "concert"
    ],
    "wof:name":"Blackpool Direct",
    "wof:placetype":"venue"
},
  "geometry": {"coordinates":[-3.050718,53.809101],"type":"Point"}
}