{
  "type": "Feature",
  "properties": {
    "addr:full":"8 Lawrence Way Cambridge Cambridgeshire CB4 2PR",
    "addr:housenumber":"8",
    "addr:postcode":"cb4 2pr",
    "addr:street":"Lawrence Way",
    "iso:country":"GB",
    "sg:address":"8 Lawrence Way",
    "sg:city":"Cambridge",
    "sg:classifiers":[
        {
            "category":"Professional",
            "subcategory":"Employment Agencies",
            "type":"Services"
        }
    ],
    "sg:phone":"+44 1223 426871",
    "sg:postcode":"CB4 2PR",
    "sg:province":"Cambridgeshire",
    "sg:tags":[
        "consultant"
    ],
    "wof:name":"Oxbridge Graduate Recruitment Ltd.",
    "wof:placetype":"venue"
},
  "geometry": {"coordinates":[0.1355749965,52.2307472229],"type":"Point"}
}