{
  "type": "Feature",
  "properties": {
    "iso:country":"GB",
    "sg:address":"72 Victoria Rd",
    "sg:city":"Runcorn",
    "sg:classifiers":[
        {
            "category":"Retail",
            "subcategory":"Funeral Services",
            "type":"Services"
        }
    ],
    "sg:phone":"+44 1928 572098",
    "sg:postcode":"WA7 5SR",
    "sg:province":"Cheshire",
    "wof:name":"S Rigby",
    "wof:placetype":"venue"
},
  "geometry": {"coordinates":[-2.728717,53.337971],"type":"Point"}
}