{
  "type": "Feature",
  "properties": {
    "addr:full":"Clavering Place Farm, Stickling Grn, Clavering Saffron Walden Essex CB11 4RN",
    "addr:postcode":"cb11 4rn",
    "addr:street":"Clavering Place Farm Stickling Grn",
    "iso:country":"GB",
    "sg:address":"Clavering Place Farm, Stickling Grn, Clavering",
    "sg:city":"Saffron Walden",
    "sg:classifiers":[
        {
            "category":"Banks & Credit Unions",
            "subcategory":"Investment Brokerage",
            "type":"Services"
        }
    ],
    "sg:postcode":"CB11 4RN",
    "sg:province":"Essex",
    "sg:tags":[
        "contractor"
    ],
    "wof:name":"G W Balaam & Son",
    "wof:placetype":"venue"
},
  "geometry": {"coordinates":[0.144457,51.965839],"type":"Point"}
}