{
  "type": "Feature",
  "properties": {
    "iso:country":"GB",
    "sg:address":"21 Stonerwood Ave, Hall Green",
    "sg:city":"Birmingham",
    "sg:classifiers":[
        {
            "category":"Building & Trades",
            "subcategory":"Construction",
            "type":"Services"
        }
    ],
    "sg:phone":"+44 7974 662983",
    "sg:postcode":"B28 0AX",
    "sg:province":"West Midlands",
    "sg:tags":[
        "roofing"
    ],
    "wof:name":"Walker Electrical Ltd",
    "wof:placetype":"venue"
},
  "geometry": {"coordinates":[-1.8512400389,52.4305610657],"type":"Point"}
}