{
  "type": "Feature",
  "properties": {
    "iso:country":"GB",
    "sg:address":"Dene Road, Castletown",
    "sg:city":"Sunderland",
    "sg:classifiers":[
        {
            "category":"Home & Garden",
            "subcategory":"Furniture",
            "type":"Retail Goods"
        }
    ],
    "sg:phone":"+44 191 516 8100",
    "sg:postcode":"SR5 3AH",
    "sg:province":"Tyne and Wear",
    "wof:name":"Kingsbury Interiors",
    "wof:placetype":"venue"
},
  "geometry": {"coordinates":[-1.435459,54.919231],"type":"Point"}
}