{
  "type": "Feature",
  "properties": {
    "iso:country":"GB",
    "sg:address":"31 North Road East",
    "sg:city":"Plymouth",
    "sg:classifiers":[
        {
            "category":"Health Services",
            "subcategory":"Dentist",
            "type":"Services"
        }
    ],
    "sg:phone":"+44 1752 664506",
    "sg:postcode":"PL4 6AY",
    "sg:province":"Devon",
    "wof:name":"T J Brown",
    "wof:placetype":"venue"
},
  "geometry": {"coordinates":[-4.1373958588,50.377620697],"type":"Point"}
}