{
  "type": "Feature",
  "properties": {
    "addr:full":"47 Angus Close Chessington Surrey KT9 2BN",
    "addr:housenumber":"47",
    "addr:postcode":"kt9 2bn",
    "addr:street":"Angus Close",
    "iso:country":"GB",
    "sg:address":"47 Angus Close",
    "sg:city":"Chessington",
    "sg:classifiers":[
        {
            "category":"Freight",
            "type":"Transportation"
        }
    ],
    "sg:postcode":"KT9 2BN",
    "sg:province":"Surrey",
    "sg:tags":[
        "haulage",
        "road"
    ],
    "wof:name":"Mariel Distribution Services Ltd",
    "wof:placetype":"venue"
},
  "geometry": {"coordinates":[-0.287562,51.364346],"type":"Point"}
}