{
  "type": "Feature",
  "properties": {
    "iso:country":"GB",
    "sg:address":"Brokenford Lane, Totton",
    "sg:city":"Southampton",
    "sg:classifiers":[
        {
            "category":"Retail",
            "subcategory":"Auto Repair",
            "type":"Services"
        }
    ],
    "sg:phone":"+44 23 8042 8400",
    "sg:postcode":"SO40 9DY",
    "sg:province":"Hampshire",
    "sg:tags":[
        "modification",
        "garage"
    ],
    "wof:name":"Barr-Weld",
    "wof:placetype":"venue"
},
  "geometry": {"coordinates":[-1.490807,50.916416],"type":"Point"}
}