{
  "type": "Feature",
  "properties": {
    "addr:full":"28 New Bdwy, Uxbridge Road Uxbridge Greater London UB10 0LL",
    "addr:housenumber":"28",
    "addr:postcode":"ub10 0ll",
    "addr:street":"New Bdwy Uxbridge Road",
    "iso:country":"GB",
    "sg:address":"28 New Bdwy, Uxbridge Road",
    "sg:city":"Uxbridge",
    "sg:classifiers":[
        {
            "category":"Professional",
            "subcategory":"Printing & Photocopies",
            "type":"Services"
        }
    ],
    "sg:phone":"+44 1895 235640",
    "sg:postcode":"UB10 0LL",
    "sg:province":"Greater London",
    "sg:tags":[
        "printer"
    ],
    "wof:name":"The Woodcroft Press",
    "wof:placetype":"venue"
},
  "geometry": {"coordinates":[-0.446966,51.529747],"type":"Point"}
}