{
  "type": "Feature",
  "properties": {
    "iso:country":"GB",
    "sg:address":"24 St Helens Road",
    "sg:city":"Bolton",
    "sg:classifiers":[
        {
            "category":"Fast Food",
            "type":"Food & Drink"
        }
    ],
    "sg:postcode":"BL3 3NH",
    "sg:province":"Lancashire",
    "sg:tags":[
        "away",
        "take"
    ],
    "wof:name":"Abu Takeaway",
    "wof:placetype":"venue"
},
  "geometry": {"coordinates":[-2.4459900856,53.5660133362],"type":"Point"}
}