{
  "type": "Feature",
  "properties": {
    "iso:country":"GB",
    "sg:address":"Warden, High Street, Sawtry",
    "sg:city":"Huntingdon",
    "sg:classifiers":[
        {
            "category":"Social Services",
            "subcategory":"Adult Care",
            "type":"Services"
        },
        {
            "category":"Government",
            "subcategory":"Office",
            "type":"Public Place"
        }
    ],
    "sg:postcode":"PE28 5SP",
    "sg:province":"Bedfordshire",
    "sg:tags":[
        "housing",
        "local",
        "sheltered"
    ],
    "wof:name":"Mellors Court Sheltered Housing",
    "wof:placetype":"venue"
},
  "geometry": {"coordinates":[-0.275309,52.436729],"type":"Point"}
}