{
  "type": "Feature",
  "properties": {
    "addr:full":"Angel Rd Thames Ditton Surrey KT7 0AU",
    "addr:postcode":"kt7 0au",
    "addr:street":"Angel Rd",
    "iso:country":"GB",
    "sg:address":"Angel Rd",
    "sg:city":"Thames Ditton",
    "sg:classifiers":[
        {
            "category":"Bars & Pubs",
            "type":"Food & Drink"
        }
    ],
    "sg:phone":"+44 20 8398 2005",
    "sg:postcode":"KT7 0AU",
    "sg:province":"Surrey",
    "sg:tags":[
        "pubs",
        "inn"
    ],
    "wof:name":"Angel Public House",
    "wof:placetype":"venue"
},
  "geometry": {"coordinates":[-0.3286060095,51.3834075928],"type":"Point"}
}