{
  "type": "Feature",
  "properties": {
    "iso:country":"GB",
    "sg:address":"Arndale House, Station Road, Crossgates",
    "sg:city":"Leeds",
    "sg:classifiers":[
        {
            "category":"Professional",
            "subcategory":"Business Services",
            "type":"Services"
        },
        {
            "category":"Arena",
            "subcategory":"Sports Club",
            "type":"Entertainment"
        }
    ],
    "sg:phone":"+44 113 264 4242",
    "sg:postcode":"LS15 8EU",
    "sg:province":"West Yorkshire",
    "sg:tags":[
        "trade"
    ],
    "wof:name":"Confederation Of British Industry",
    "wof:placetype":"venue"
},
  "geometry": {"coordinates":[-1.452182,53.807186],"type":"Point"}
}