{
  "type": "Feature",
  "properties": {
    "addr:full":"Plas Glyn Afon, Waunfawr Caernarfon Gwynedd LL55 4YY",
    "addr:postcode":"ll55 4yy",
    "addr:street":"Plas Glyn",
    "iso:country":"GB",
    "sg:address":"Plas Glyn Afon, Waunfawr",
    "sg:city":"Caernarfon",
    "sg:classifiers":[
        {
            "category":"Professional",
            "subcategory":"Printing & Photocopies",
            "type":"Services"
        }
    ],
    "sg:postcode":"LL55 4YY",
    "sg:province":"Gwynedd",
    "sg:tags":[
        "embroiderer"
    ],
    "wof:name":"Stitch Ltd.",
    "wof:placetype":"venue"
},
  "geometry": {"coordinates":[-4.2053809166,53.1105690002],"type":"Point"}
}