{
  "type": "Feature",
  "properties": {
    "addr:full":"Griffin House, 32 The Ropewalk Nottingham Nottinghamshire NG1 5DW",
    "addr:housenumber":"32",
    "addr:postcode":"ng1 5dw",
    "addr:street":"The Ropewalk",
    "iso:country":"GB",
    "sg:address":"Griffin House, 32 The Ropewalk",
    "sg:city":"Nottingham",
    "sg:classifiers":[
        {
            "category":"Banks & Credit Unions",
            "subcategory":"Financial Services",
            "type":"Services"
        }
    ],
    "sg:phone":"+44 115 958 6333",
    "sg:postcode":"NG1 5DW",
    "sg:province":"Nottinghamshire",
    "sg:tags":[
        "adviser"
    ],
    "wof:name":"Blythens Financial Services Ltd.",
    "wof:placetype":"venue"
},
  "geometry": {"coordinates":[-1.1587690115,52.9533729553],"type":"Point"}
}