{
  "type": "Feature",
  "properties": {
    "addr:full":"Unit 3 James Ct, Viking Way, Winch Wen Indstl Est, Winch Wen Swansea Neath Port Talbot SA1 7DA",
    "addr:housenumber":"unit 3",
    "addr:postcode":"sa1 7da",
    "addr:street":"James Ct Viking Way",
    "iso:country":"GB",
    "sg:address":"Unit 3 James Ct, Viking Way, Winch Wen Indstl Est, Winch Wen",
    "sg:city":"Swansea",
    "sg:classifiers":[
        {
            "category":"Retail",
            "subcategory":"Auto Repair",
            "type":"Services"
        }
    ],
    "sg:postcode":"SA1 7DA",
    "sg:province":"Neath Port Talbot",
    "sg:tags":[
        "bodybuilder",
        "repairer"
    ],
    "wof:name":"Davies,Eric Vaughan,",
    "wof:placetype":"venue"
},
  "geometry": {"coordinates":[-3.899319,51.655308],"type":"Point"}
}