{
  "type": "Feature",
  "properties": {
    "iso:country":"GB",
    "sg:address":"Health Centre",
    "sg:city":"Llanfairpwllgwyngyll",
    "sg:classifiers":[
        {
            "category":"Health Services",
            "subcategory":"Doctor",
            "type":"Services"
        }
    ],
    "sg:phone":"+44 1248 714388",
    "sg:postcode":"LL61 5YZ",
    "sg:province":"Isle of Anglesey",
    "sg:tags":[
        "practitioners"
    ],
    "wof:name":"Roberts, G R",
    "wof:placetype":"venue"
},
  "geometry": {"coordinates":[-4.209749,53.221443],"type":"Point"}
}