{
  "type": "Feature",
  "properties": {
    "iso:country":"GB",
    "sg:address":"79 Beauchamp Avenue, Handsworth Wood",
    "sg:city":"Birmingham",
    "sg:classifiers":[
        {
            "category":"Building & Trades",
            "subcategory":"Plumbing",
            "type":"Services"
        }
    ],
    "sg:phone":"+44 121 358 4382",
    "sg:postcode":"B20 1DS",
    "sg:province":"West Midlands",
    "sg:tags":[
        "drain",
        "clearance",
        "sewer"
    ],
    "wof:name":"Drainservices Birmingham",
    "wof:placetype":"venue"
},
  "geometry": {"coordinates":[-1.932491,52.528389],"type":"Point"}
}