{
  "type": "Feature",
  "properties": {
    "addr:full":"79 Cornwallis Ct, Lansdowne Green South Lambeth Greater London SW8 2NX",
    "addr:housenumber":"79",
    "addr:postcode":"sw8 2nx",
    "addr:street":"Cornwallis Ct Lansdowne Green",
    "iso:country":"GB",
    "sg:address":"79 Cornwallis Ct, Lansdowne Green",
    "sg:city":"South Lambeth",
    "sg:classifiers":[
        {
            "category":"Education",
            "subcategory":"Special Training",
            "type":"Public Place"
        }
    ],
    "sg:phone":"+44 20 7622 6796",
    "sg:postcode":"SW8 2NX",
    "sg:province":"Greater London",
    "sg:tags":[
        "product",
        "centre"
    ],
    "wof:name":"Youthspace",
    "wof:placetype":"venue"
},
  "geometry": {"coordinates":[-0.1284500062,51.4751205444],"type":"Point"}
}