{
  "type": "Feature",
  "properties": {
    "addr:full":"1 Faraday House, Brightlingsea Place London Greater London E14 8DA",
    "addr:housenumber":"1",
    "addr:postcode":"e14 8da",
    "addr:street":"Brightlingsea Place",
    "iso:country":"GB",
    "sg:address":"1 Faraday House, Brightlingsea Place",
    "sg:city":"London",
    "sg:classifiers":[
        {
            "category":"Building & Trades",
            "subcategory":"Plumbing",
            "type":"Services"
        }
    ],
    "sg:phone":"+44 20 7515 7710",
    "sg:postcode":"E14 8DA",
    "sg:province":"Greater London",
    "sg:tags":[
        "heating"
    ],
    "wof:name":"Paul Maxwell Registered Plumber",
    "wof:placetype":"venue"
},
  "geometry": {"coordinates":[-0.0340600014,51.509021759],"type":"Point"}
}