{
  "type": "Feature",
  "properties": {
    "addr:full":"3 The Mall, Charlton Centre High Street Dover Kent CT16 1TS",
    "addr:housenumber":"3",
    "addr:postcode":"ct16 1ts",
    "addr:street":"The Mall Charlton;High Street",
    "iso:country":"GB",
    "sg:address":"3 The Mall, Charlton Centre High Street",
    "sg:city":"Dover",
    "sg:classifiers":[
        {
            "category":"Food & Beverages",
            "subcategory":"Fruits & Vegetables",
            "type":"Retail Goods"
        }
    ],
    "sg:postcode":"CT16 1TS",
    "sg:province":"Kent",
    "sg:tags":[
        "greengrocer"
    ],
    "wof:name":"Crisp & Fresh",
    "wof:placetype":"venue"
},
  "geometry": {"coordinates":[1.328761,51.126846],"type":"Point"}
}