{
  "type": "Feature",
  "properties": {
    "addr:full":"Factory 3 Digby Street Ilkeston Derbyshire DE7 5TJ",
    "addr:housenumber":"3",
    "addr:postcode":"de7 5tj",
    "addr:street":"Digby Street",
    "iso:country":"GB",
    "sg:address":"Factory 3 Digby Street",
    "sg:city":"Ilkeston",
    "sg:classifiers":[
        {
            "category":"Home & Garden",
            "subcategory":"Building Materials",
            "type":"Retail Goods"
        }
    ],
    "sg:postcode":"DE7 5TJ",
    "sg:province":"Derbyshire",
    "sg:tags":[
        "polythene",
        "plastic"
    ],
    "wof:name":"Narrow Polythene Films",
    "wof:placetype":"venue"
},
  "geometry": {"coordinates":[-1.3101890087,52.9786109924],"type":"Point"}
}