{
  "type": "Feature",
  "properties": {
    "iso:country":"GB",
    "sg:address":"7 Shearwater Lane",
    "sg:city":"Stockton-on-tees",
    "sg:classifiers":[
        {
            "category":"Bars & Pubs",
            "subcategory":"Nightclub",
            "type":"Food & Drink"
        }
    ],
    "sg:postcode":"TS20 1SH",
    "sg:province":"Durham",
    "sg:tags":[
        "karaoke"
    ],
    "wof:name":"Starmakers Karaoke",
    "wof:placetype":"venue"
},
  "geometry": {"coordinates":[-1.313631,54.597626],"type":"Point"}
}