{
  "type": "Feature",
  "properties": {
    "addr:full":"57 Cumberland Road Middlesbrough North Yorkshire TS5 6PN",
    "addr:housenumber":"57",
    "addr:postcode":"ts5 6pn",
    "addr:street":"Cumberland Road",
    "iso:country":"GB",
    "sg:address":"57 Cumberland Road",
    "sg:city":"Middlesbrough",
    "sg:classifiers":[
        {
            "category":"Shopping",
            "subcategory":"News",
            "type":"Retail Goods"
        }
    ],
    "sg:postcode":"TS5 6PN",
    "sg:province":"North Yorkshire",
    "sg:tags":[
        "newsagent"
    ],
    "wof:name":"Cumberland Road Newsagents",
    "wof:placetype":"venue"
},
  "geometry": {"coordinates":[-1.23771,54.560024],"type":"Point"}
}