{
  "type": "Feature",
  "properties": {
    "iso:country":"GB",
    "sg:address":"Fox Hill Rd",
    "sg:city":"Sheffield",
    "sg:classifiers":[
        {
            "category":"Place Of Worship",
            "type":"Public Place"
        }
    ],
    "sg:phone":"+44 114 231 3518",
    "sg:postcode":"S6 1BP",
    "sg:province":"South Yorkshire",
    "wof:name":"Birley Carr Methodist Church",
    "wof:placetype":"venue"
},
  "geometry": {"coordinates":[-1.497568965,53.4335517883],"type":"Point"}
}