{
  "type": "Feature",
  "properties": {
    "iso:country":"GB",
    "sg:address":"53 Northward Rd",
    "sg:city":"Wilmslow",
    "sg:classifiers":[
        {
            "category":"Building & Trades",
            "subcategory":"Construction",
            "type":"Services"
        }
    ],
    "sg:phone":"+44 1625 531921",
    "sg:postcode":"SK9 6AB",
    "sg:province":"Cheshire",
    "sg:tags":[
        "decorator",
        "painter"
    ],
    "wof:name":"Gordon R Frost",
    "wof:placetype":"venue"
},
  "geometry": {"coordinates":[-2.246889,53.324581],"type":"Point"}
}