{
  "type": "Feature",
  "properties": {
    "iso:country":"GB",
    "sg:address":"Newspaper House, Yeoman Industrial Park, Test Lane",
    "sg:city":"Southampton",
    "sg:classifiers":[
        {
            "category":"Communications",
            "subcategory":"Newspaper",
            "type":"Services"
        }
    ],
    "sg:phone":"+44 23 8042 4777",
    "sg:postcode":"SO16 9JX",
    "sg:province":"Hampshire",
    "sg:tags":[
        "magazine"
    ],
    "wof:name":"The Southern Daily Echo Ltd.",
    "wof:placetype":"venue"
},
  "geometry": {"coordinates":[-1.47415,50.929272],"type":"Point"}
}