{
  "type": "Feature",
  "properties": {
    "iso:country":"GB",
    "sg:address":"Willow Lane, Wargrave",
    "sg:city":"Reading",
    "sg:classifiers":[
        {
            "category":"Social Services",
            "subcategory":"Job Training",
            "type":"Services"
        }
    ],
    "sg:phone":"+44 118 940 1422",
    "sg:postcode":"RG10 8LH",
    "sg:province":"Berkshire",
    "sg:tags":[
        "engineering",
        "marine"
    ],
    "wof:name":"Aquatec Marine",
    "wof:placetype":"venue"
},
  "geometry": {"coordinates":[-0.8727520108,51.5097541809],"type":"Point"}
}