{
  "type": "Feature",
  "properties": {
    "addr:full":"Special Effects, Pinewood Studios, Pinewood Rd Iver Berkshire SL0 0NH",
    "addr:postcode":"sl0 0nh",
    "addr:street":"Pinewood Rd",
    "iso:country":"GB",
    "sg:address":"Special Effects, Pinewood Studios, Pinewood Rd",
    "sg:city":"Iver",
    "sg:classifiers":[
        {
            "category":"Communications",
            "subcategory":"Film & Video Production",
            "type":"Services"
        }
    ],
    "sg:phone":"+44 1753 656962",
    "sg:postcode":"SL0 0NH",
    "sg:province":"Berkshire",
    "sg:tags":[
        "tv",
        "studio"
    ],
    "wof:name":"Image Animation",
    "wof:placetype":"venue"
},
  "geometry": {"coordinates":[-0.5206189752,51.5365447998],"type":"Point"}
}