{
  "type": "Feature",
  "properties": {
    "addr:full":"37 Hesleden Tamworth Staffordshire B77 4HR",
    "addr:housenumber":"37",
    "addr:postcode":"b77 4hr",
    "addr:street":"Hesleden",
    "iso:country":"GB",
    "sg:address":"37 Hesleden",
    "sg:city":"Tamworth",
    "sg:classifiers":[
        {
            "category":"Professional",
            "subcategory":"Art Services",
            "type":"Services"
        }
    ],
    "sg:phone":"+44 1827 331646",
    "sg:postcode":"B77 4HR",
    "sg:province":"Staffordshire",
    "sg:tags":[
        "graphic",
        "designer"
    ],
    "wof:name":"Raphael Creative Design",
    "wof:placetype":"venue"
},
  "geometry": {"coordinates":[-1.6533939838,52.6140594482],"type":"Point"}
}