{
  "type": "Feature",
  "properties": {
    "iso:country":"GB",
    "sg:address":"Middle Lane",
    "sg:city":"Chester",
    "sg:classifiers":[
        {
            "category":"Shopping",
            "subcategory":"Department Store",
            "type":"Retail Goods"
        }
    ],
    "sg:postcode":"CH3 6JA",
    "sg:province":"Cheshire",
    "wof:name":"Aldford Post Office",
    "wof:placetype":"venue"
},
  "geometry": {"coordinates":[-2.86977,53.12719],"type":"Point"}
}