{
  "type": "Feature",
  "properties": {
    "iso:country":"GB",
    "sg:address":"Unit 5",
    "sg:city":"Keswick",
    "sg:classifiers":[
        {
            "category":"Manufacturing",
            "subcategory":"Building Materials",
            "type":"Manufacturing & Wholesale Goods"
        }
    ],
    "sg:phone":"+44 17687 74695",
    "sg:postcode":"CA12 5LU",
    "sg:province":"Cumbria",
    "sg:tags":[
        "stonemason"
    ],
    "wof:name":"John Gaskell",
    "wof:placetype":"venue"
},
  "geometry": {"coordinates":[-3.1649899483,54.5909614563],"type":"Point"}
}