{
  "type": "Feature",
  "properties": {
    "addr:full":"155 South Street Perth Perth and Kinross PH2 8NY",
    "addr:housenumber":"155",
    "addr:postcode":"ph2 8ny",
    "addr:street":"South Street",
    "iso:country":"GB",
    "sg:address":"155 South Street",
    "sg:city":"Perth",
    "sg:classifiers":[
        {
            "category":"Home & Garden",
            "subcategory":"Hardware",
            "type":"Retail Goods"
        }
    ],
    "sg:postcode":"PH2 8NY",
    "sg:province":"Perth and Kinross",
    "sg:tags":[
        "retailer",
        "lighting"
    ],
    "wof:name":"John T Young & Son",
    "wof:placetype":"venue"
},
  "geometry": {"coordinates":[-3.4328451157,56.3955001831],"type":"Point"}
}