{
  "type": "Feature",
  "properties": {
    "addr:full":"26 F5 Kyle Industrial Estate Kyle Highland IV40 8AX",
    "addr:housenumber":"f5",
    "addr:postcode":"iv40 8ax",
    "addr:street":"26;Kyle Industrial Estate",
    "iso:country":"GB",
    "sg:address":"26 F5 Kyle Industrial Estate",
    "sg:city":"Kyle",
    "sg:classifiers":[
        {
            "category":"Building & Trades",
            "subcategory":"Construction",
            "type":"Services"
        }
    ],
    "sg:phone":"+44 1599 534782",
    "sg:postcode":"IV40 8AX",
    "sg:province":"Highland",
    "sg:tags":[
        "joiner",
        "carpenter"
    ],
    "wof:name":"John Macrae Joinery Contractors",
    "wof:placetype":"venue"
},
  "geometry": {"coordinates":[-5.714052,57.280945],"type":"Point"}
}