{
  "type": "Feature",
  "properties": {
    "iso:country":"GB",
    "sg:address":"Prospero Barn, The Green",
    "sg:city":"Stratford-upon-avon",
    "sg:classifiers":[
        {
            "category":"Professional",
            "subcategory":"Management & Consulting",
            "type":"Services"
        }
    ],
    "sg:phone":"+44 1789 734300",
    "sg:postcode":"CV37 0TR",
    "sg:province":"Warwickshire",
    "sg:tags":[
        "consultant",
        "business"
    ],
    "wof:name":"Sales Pathways Ltd.",
    "wof:placetype":"venue"
},
  "geometry": {"coordinates":[-1.707269,52.194134],"type":"Point"}
}