{
  "type": "Feature",
  "properties": {
    "iso:country":"GB",
    "sg:address":"24 Merrivale Road",
    "sg:city":"Stafford",
    "sg:classifiers":[
        {
            "category":"Arts & Performance",
            "subcategory":"Music",
            "type":"Entertainment"
        }
    ],
    "sg:phone":"+44 1785 226359",
    "sg:postcode":"ST17 9EB",
    "sg:province":"Staffordshire",
    "sg:tags":[
        "mobile",
        "disco"
    ],
    "wof:name":"Midnite Rider Roadshow",
    "wof:placetype":"venue"
},
  "geometry": {"coordinates":[-2.112883,52.785748],"type":"Point"}
}