{
  "type": "Feature",
  "properties": {
    "iso:country":"GB",
    "sg:address":"Gold Street",
    "sg:city":"Wellingborough",
    "sg:classifiers":[
        {
            "category":"Place Of Worship",
            "type":"Public Place"
        }
    ],
    "sg:phone":"+44 1933 223101",
    "sg:postcode":"NN8 4EQ",
    "sg:province":"Northamptonshire",
    "wof:name":"H & B Howes (Wellingborough) Ltd.",
    "wof:placetype":"venue"
},
  "geometry": {"coordinates":[-0.6911389828,52.3088340759],"type":"Point"}
}