{
  "type": "Feature",
  "properties": {
    "addr:full":"33 Wood Rd, Chaddesden Derby Derbyshire DE21 4LX",
    "addr:housenumber":"33",
    "addr:postcode":"de21 4lx",
    "addr:street":"Wood Rd",
    "iso:country":"GB",
    "sg:address":"33 Wood Rd, Chaddesden",
    "sg:city":"Derby",
    "sg:classifiers":[
        {
            "category":"Personal",
            "subcategory":"Beauty Salon",
            "type":"Services"
        }
    ],
    "sg:phone":"+44 1332 673540",
    "sg:postcode":"DE21 4LX",
    "sg:province":"Derbyshire",
    "sg:tags":[
        "unisex",
        "hairdresser"
    ],
    "wof:name":"Mrs E.M Bevan",
    "wof:placetype":"venue"
},
  "geometry": {"coordinates":[-1.4319339991,52.9326972961],"type":"Point"}
}