{
  "type": "Feature",
  "properties": {
    "iso:country":"GB",
    "sg:address":"Delamare Road",
    "sg:city":"Waltham Cross",
    "sg:classifiers":[
        {
            "category":"Professional",
            "subcategory":"Printing & Photocopies",
            "type":"Services"
        }
    ],
    "sg:phone":"+44 1992 642261",
    "sg:postcode":"EN8 9SH",
    "sg:province":"Essex",
    "sg:tags":[
        "process",
        "screen",
        "printer"
    ],
    "wof:name":"L & J Carnell Screen Printers",
    "wof:placetype":"venue"
},
  "geometry": {"coordinates":[-0.025693,51.704903],"type":"Point"}
}