{
  "type": "Feature",
  "properties": {
    "addr:full":"Maidstone Industrial Centre, St. Peter St Maidstone Kent ME16 0ST",
    "addr:postcode":"me16 0st",
    "addr:street":"Maidstone;Centre;St",
    "iso:country":"GB",
    "sg:address":"Maidstone Industrial Centre, St. Peter St",
    "sg:city":"Maidstone",
    "sg:classifiers":[
        {
            "category":"Wholesale",
            "subcategory":"Metals & Minerals",
            "type":"Manufacturing & Wholesale Goods"
        }
    ],
    "sg:phone":"+44 1622 685230",
    "sg:postcode":"ME16 0ST",
    "sg:province":"Kent",
    "sg:tags":[
        "aluminium",
        "stockholder"
    ],
    "wof:name":"Cladlite Engineering",
    "wof:placetype":"venue"
},
  "geometry": {"coordinates":[0.5161899924,51.2769889832],"type":"Point"}
}