{
  "type": "Feature",
  "properties": {
    "iso:country":"GB",
    "sg:address":"20 Barrow Street",
    "sg:city":"St Helens",
    "sg:classifiers":[
        {
            "category":"Shopping",
            "subcategory":"Optician",
            "type":"Retail Goods"
        }
    ],
    "sg:postcode":"WA10 1RX",
    "sg:province":"Merseyside",
    "wof:name":"Rayner",
    "wof:placetype":"venue"
},
  "geometry": {"coordinates":[-2.735925,53.453831],"type":"Point"}
}