{
  "type": "Feature",
  "properties": {
    "iso:country":"GB",
    "sg:address":"Fieldhouse School, Greenbank Road",
    "sg:city":"Rochdale",
    "sg:classifiers":[
        {
            "category":"Government",
            "subcategory":"Office",
            "type":"Public Place"
        }
    ],
    "sg:phone":"+44 1706 647078",
    "sg:postcode":"OL12 0HZ",
    "sg:province":"Lancashire",
    "sg:tags":[
        "education",
        "agency",
        "authority"
    ],
    "wof:name":"Rochdale Educational Music Service",
    "wof:placetype":"venue"
},
  "geometry": {"coordinates":[-2.1557660103,53.6276359558],"type":"Point"}
}