{
  "type": "Feature",
  "properties": {
    "iso:country":"GB",
    "sg:address":"13 Dinsdale Road",
    "sg:city":"London",
    "sg:classifiers":[
        {
            "category":"Professional",
            "subcategory":"Secretarial Services",
            "type":"Services"
        }
    ],
    "sg:postcode":"SE3 7RJ",
    "sg:province":"Greater London",
    "sg:tags":[
        "processing",
        "word"
    ],
    "wof:name":"Jet Typewriter Repair Service",
    "wof:placetype":"venue"
},
  "geometry": {"coordinates":[0.009225,51.483051],"type":"Point"}
}