{
  "type": "Feature",
  "properties": {
    "addr:full":"Brambleside, Bellbrook Indust Est Uckfield East Sussex TN22 1XX",
    "addr:postcode":"tn22 1xx",
    "addr:street":"Indust",
    "iso:country":"GB",
    "sg:address":"Brambleside, Bellbrook Indust Est",
    "sg:city":"Uckfield",
    "sg:classifiers":[
        {
            "category":"Home & Garden",
            "subcategory":"Home Furnishings",
            "type":"Retail Goods"
        }
    ],
    "sg:phone":"+44 1825 769616",
    "sg:postcode":"TN22 1XX",
    "sg:province":"East Sussex",
    "sg:tags":[
        "furnishers",
        "planner",
        "kitchen"
    ],
    "wof:name":"Contract Kitchens",
    "wof:placetype":"venue"
},
  "geometry": {"coordinates":[0.09665,50.971813],"type":"Point"}
}