{
  "type": "Feature",
  "properties": {
    "addr:full":"275a Old Kent Road London Greater London SE1 5LU",
    "addr:housenumber":"275a",
    "addr:postcode":"se1 5lu",
    "addr:street":"Old;Road",
    "iso:country":"GB",
    "sg:address":"275a Old Kent Road",
    "sg:city":"London",
    "sg:classifiers":[
        {
            "category":"Food & Beverages",
            "subcategory":"Bakery",
            "type":"Retail Goods"
        }
    ],
    "sg:phone":"+44 20 7232 2031",
    "sg:postcode":"SE1 5LU",
    "sg:province":"Greater London",
    "sg:tags":[
        "shop",
        "baker"
    ],
    "wof:name":"Hazel's Bakery",
    "wof:placetype":"venue"
},
  "geometry": {"coordinates":[-0.079684,51.490002],"type":"Point"}
}