{
  "type": "Feature",
  "properties": {
    "addr:full":"11 Copse Wood Way Northwood Greater London HA6 2GQ",
    "addr:housenumber":"11",
    "addr:postcode":"ha6 2gq",
    "addr:street":"Copse Wood Way",
    "iso:country":"GB",
    "sg:address":"11 Copse Wood Way",
    "sg:city":"Northwood",
    "sg:classifiers":[
        {
            "category":"Professional",
            "subcategory":"Management & Consulting",
            "type":"Services"
        }
    ],
    "sg:phone":"+44 1923 840040",
    "sg:postcode":"HA6 2GQ",
    "sg:province":"Greater London",
    "sg:tags":[
        "consultant",
        "business"
    ],
    "wof:name":"Silver & Co",
    "wof:placetype":"venue"
},
  "geometry": {"coordinates":[-0.437148,51.607925],"type":"Point"}
}