{
  "type": "Feature",
  "properties": {
    "iso:country":"GB",
    "sg:address":"122 Goldcroft",
    "sg:city":"Yeovil",
    "sg:classifiers":[
        {
            "category":"Organizations",
            "subcategory":"Religious Organization",
            "type":"Services"
        }
    ],
    "sg:phone":"+44 1935 421056",
    "sg:postcode":"BA21 4DE",
    "sg:province":"Somerset",
    "sg:tags":[
        "organisation"
    ],
    "wof:name":"Quakers Religious Society Of Friends",
    "wof:placetype":"venue"
},
  "geometry": {"coordinates":[-2.630371,50.947197],"type":"Point"}
}