{
  "type": "Feature",
  "properties": {
    "addr:full":"8 Little Austins Road Farnham Surrey GU9 8JR",
    "addr:housenumber":"8",
    "addr:postcode":"gu9 8jr",
    "addr:street":"Little Austins Road",
    "iso:country":"GB",
    "sg:address":"8 Little Austins Road",
    "sg:city":"Farnham",
    "sg:classifiers":[
        {
            "category":"Real Estate",
            "subcategory":"Real Estate Services",
            "type":"Services"
        },
        {
            "category":"Real Estate",
            "subcategory":"Developer",
            "type":"Services"
        }
    ],
    "sg:phone":"+44 1252 716411",
    "sg:postcode":"GU9 8JR",
    "sg:province":"Surrey",
    "sg:tags":[
        "property",
        "management"
    ],
    "wof:name":"C W Developments Ltd",
    "wof:placetype":"venue"
},
  "geometry": {"coordinates":[-0.786432,51.205288],"type":"Point"}
}