{
  "type": "Feature",
  "properties": {
    "addr:full":"13a Weston Rd Southend-on-sea Essex SS1 1AS",
    "addr:housenumber":"13a",
    "addr:postcode":"ss1 1as",
    "addr:street":"Weston Rd",
    "iso:country":"GB",
    "sg:address":"13a Weston Rd",
    "sg:city":"Southend-on-sea",
    "sg:classifiers":[
        {
            "category":"Real Estate",
            "subcategory":"Developer",
            "type":"Services"
        }
    ],
    "sg:postcode":"SS1 1AS",
    "sg:province":"Essex",
    "sg:tags":[
        "property"
    ],
    "wof:name":"Lodwick Homes Ltd",
    "wof:placetype":"venue"
},
  "geometry": {"coordinates":[0.712647,51.53624],"type":"Point"}
}