{
  "type": "Feature",
  "properties": {
    "addr:full":"93 High Street, New Pitsligo Fraserburgh Aberdeenshire AB43 6NH",
    "addr:housenumber":"93",
    "addr:postcode":"ab43 6nh",
    "addr:street":"High Street",
    "iso:country":"GB",
    "sg:address":"93 High Street, New Pitsligo",
    "sg:city":"Fraserburgh",
    "sg:classifiers":[
        {
            "category":"Farming",
            "subcategory":"Fish & Marine Products",
            "type":"Manufacturing & Wholesale Goods"
        }
    ],
    "sg:phone":"+44 1771 653243",
    "sg:postcode":"AB43 6NH",
    "sg:province":"Aberdeenshire",
    "sg:tags":[
        "fishmonger"
    ],
    "wof:name":"John A Hogg",
    "wof:placetype":"venue"
},
  "geometry": {"coordinates":[-2.1949419975,57.6596908569],"type":"Point"}
}