{
  "type": "Feature",
  "properties": {
    "addr:full":"Green Street Hartlepool Durham TS24 7QY",
    "addr:postcode":"ts24 7qy",
    "addr:street":"Green Street",
    "iso:country":"GB",
    "sg:address":"Green Street",
    "sg:city":"Hartlepool",
    "sg:classifiers":[
        {
            "category":"Building & Trades",
            "subcategory":"Construction",
            "type":"Services"
        }
    ],
    "sg:phone":"+44 1429 272084",
    "sg:postcode":"TS24 7QY",
    "sg:province":"Durham",
    "sg:tags":[
        "joiner",
        "carpenter"
    ],
    "wof:name":"Phillips of Hartlepool",
    "wof:placetype":"venue"
},
  "geometry": {"coordinates":[-1.2105909586,54.6798362732],"type":"Point"}
}