{
  "type": "Feature",
  "properties": {
    "addr:full":"Moor La Industrial Est, Perrywell Rd Birmingham West Midlands B6 7AT",
    "addr:postcode":"b6 7at",
    "addr:street":"Moor La Industrial Est Perrywell Rd",
    "iso:country":"GB",
    "sg:address":"Moor La Industrial Est, Perrywell Rd",
    "sg:city":"Birmingham",
    "sg:classifiers":[
        {
            "category":"Retail",
            "subcategory":"Auto Rental",
            "type":"Services"
        }
    ],
    "sg:phone":"+44 121 356 2080",
    "sg:postcode":"B6 7AT",
    "sg:province":"West Midlands",
    "sg:tags":[
        "truck",
        "hire",
        "van"
    ],
    "wof:name":"Via Truck Rental Ltd",
    "wof:placetype":"venue"
},
  "geometry": {"coordinates":[-1.884173,52.530067],"type":"Point"}
}