{
  "type": "Feature",
  "properties": {
    "addr:full":"16 Harrow Close, Caerleon Newport Monmouthshire NP18 3EF",
    "addr:housenumber":"16",
    "addr:postcode":"np18 3ef",
    "addr:street":"Harrow Close",
    "iso:country":"GB",
    "sg:address":"16 Harrow Close, Caerleon",
    "sg:city":"Newport",
    "sg:classifiers":[
        {
            "category":"Building & Trades",
            "subcategory":"Plumbing",
            "type":"Services"
        }
    ],
    "sg:phone":"+44 1633 420010",
    "sg:postcode":"NP18 3EF",
    "sg:province":"Monmouthshire",
    "sg:tags":[
        "central",
        "installation",
        "system",
        "servicing",
        "heating"
    ],
    "wof:name":"Nelson & Miggins",
    "wof:placetype":"venue"
},
  "geometry": {"coordinates":[-2.9743249416,51.619140625],"type":"Point"}
}