{
  "type": "Feature",
  "properties": {
    "addr:full":"15 Woodcross Avenue, Cantley Doncaster South Yorkshire DN4 6RU",
    "addr:housenumber":"15",
    "addr:postcode":"dn4 6ru",
    "addr:street":"Woodcross Avenue",
    "iso:country":"GB",
    "sg:address":"15 Woodcross Avenue, Cantley",
    "sg:city":"Doncaster",
    "sg:classifiers":[
        {
            "category":"Professional",
            "subcategory":"Computer Services",
            "type":"Services"
        }
    ],
    "sg:postcode":"DN4 6RU",
    "sg:province":"South Yorkshire",
    "sg:tags":[
        "system",
        "software"
    ],
    "wof:name":"Lester Quilter & Co. Ltd.",
    "wof:placetype":"venue"
},
  "geometry": {"coordinates":[-1.061769,53.503956],"type":"Point"}
}