{
  "type": "Feature",
  "properties": {
    "iso:country":"GB",
    "sg:address":"Cornermount, Mount Pk Rd",
    "sg:city":"Harrow",
    "sg:classifiers":[
        {
            "category":"Manufacturing",
            "subcategory":"Textiles",
            "type":"Manufacturing & Wholesale Goods"
        }
    ],
    "sg:postcode":"HA1 3LB",
    "sg:province":"Greater London",
    "wof:name":"Tollydon Ltd",
    "wof:placetype":"venue"
},
  "geometry": {"coordinates":[-0.336082,51.578785],"type":"Point"}
}