{
  "type": "Feature",
  "properties": {
    "addr:full":"41 West Street Marlow Berkshire SL7 2LS",
    "addr:housenumber":"41",
    "addr:postcode":"sl7 2ls",
    "addr:street":"West Street",
    "iso:country":"GB",
    "sg:address":"41 West Street",
    "sg:city":"Marlow",
    "sg:classifiers":[
        {
            "category":"Restaurant",
            "type":"Food & Drink"
        }
    ],
    "sg:phone":"+44 1628 482211",
    "sg:postcode":"SL7 2LS",
    "sg:province":"Berkshire",
    "sg:tags":[
        "indian",
        "-"
    ],
    "wof:name":"Thiger Garden",
    "wof:placetype":"venue"
},
  "geometry": {"coordinates":[-0.7782700062,51.5708770752],"type":"Point"}
}