{
  "type": "Feature",
  "properties": {
    "iso:country":"GB",
    "sg:address":"9-11 Inverurie Road, Bucksburn",
    "sg:city":"Aberdeen",
    "sg:classifiers":[
        {
            "category":"Shopping",
            "subcategory":"Pharmacy",
            "type":"Retail Goods"
        }
    ],
    "sg:phone":"+44 1224 714476",
    "sg:postcode":"AB21 9LJ",
    "sg:province":"Aberdeen City",
    "sg:tags":[
        "dispensing",
        "store",
        "pharmacist",
        "chemist",
        "drug"
    ],
    "wof:name":"David M Wood",
    "wof:placetype":"venue"
},
  "geometry": {"coordinates":[-2.171239,57.17701],"type":"Point"}
}