{
  "type": "Feature",
  "properties": {
    "addr:full":"16 Crown La, Theale Reading Berkshire RG7 5BQ",
    "addr:housenumber":"16",
    "addr:postcode":"rg7 5bq",
    "addr:street":"Crown La Theale",
    "iso:country":"GB",
    "sg:address":"16 Crown La, Theale",
    "sg:city":"Reading",
    "sg:classifiers":[
        {
            "category":"Building & Trades",
            "subcategory":"Construction",
            "type":"Services"
        }
    ],
    "sg:postcode":"RG7 5BQ",
    "sg:province":"Berkshire",
    "sg:tags":[
        "builder"
    ],
    "wof:name":"B P C Services",
    "wof:placetype":"venue"
},
  "geometry": {"coordinates":[-1.077403,51.437855],"type":"Point"}
}