{
  "type": "Feature",
  "properties": {
    "iso:country":"GB",
    "sg:address":"44 Churchill Clo, Flackwell Heath",
    "sg:city":"High Wycombe",
    "sg:classifiers":[
        {
            "category":"Professional",
            "subcategory":"Secretarial Services",
            "type":"Services"
        }
    ],
    "sg:postcode":"HP10 9LB",
    "sg:province":"Buckinghamshire",
    "wof:name":"Taylor,Anne,",
    "wof:placetype":"venue"
},
  "geometry": {"coordinates":[-0.701022,51.595722],"type":"Point"}
}