{
  "type": "Feature",
  "properties": {
    "iso:country":"GB",
    "sg:address":"54 Station Road",
    "sg:city":"Sudbury",
    "sg:classifiers":[
        {
            "category":"Professional",
            "subcategory":"Printing & Photocopies",
            "type":"Services"
        }
    ],
    "sg:postcode":"CO10 2SP",
    "sg:province":"Essex",
    "sg:tags":[
        "duplicating",
        "copying"
    ],
    "wof:name":"Sudbury Duplicating Service",
    "wof:placetype":"venue"
},
  "geometry": {"coordinates":[0.729756,52.037518],"type":"Point"}
}