{
  "type": "Feature",
  "properties": {
    "iso:country":"GB",
    "sg:address":"King James Road",
    "sg:city":"Knaresborough",
    "sg:classifiers":[
        {
            "category":"Place Of Worship",
            "type":"Public Place"
        }
    ],
    "sg:postcode":"HG5 8EB",
    "sg:province":"North Yorkshire",
    "wof:name":"Knaresborough Community Church",
    "wof:placetype":"venue"
},
  "geometry": {"coordinates":[-1.4621239901,54.0052642822],"type":"Point"}
}