{
  "type": "Feature",
  "properties": {
    "addr:full":"1 Shrewsbury Court, Old Trafford Manchester Cheshire M16 7NR",
    "addr:housenumber":"1",
    "addr:postcode":"m16 7nr",
    "addr:street":"Shrewsbury Court",
    "iso:country":"GB",
    "sg:address":"1 Shrewsbury Court, Old Trafford",
    "sg:city":"Manchester",
    "sg:classifiers":[
        {
            "category":"Social Services",
            "subcategory":"Adult Care",
            "type":"Services"
        }
    ],
    "sg:phone":"+44 161 227 9275",
    "sg:postcode":"M16 7NR",
    "sg:province":"Cheshire",
    "sg:tags":[
        "day",
        "centre"
    ],
    "wof:name":"Age Concern",
    "wof:placetype":"venue"
},
  "geometry": {"coordinates":[-2.2589590549,53.4612083435],"type":"Point"}
}