{
  "type": "Feature",
  "properties": {
    "addr:full":"9 Chalfield Close, Keynsham Bristol City of Bristol BS31 1JZ",
    "addr:housenumber":"9",
    "addr:postcode":"bs31 1jz",
    "addr:street":"Chalfield Close",
    "iso:country":"GB",
    "sg:address":"9 Chalfield Close, Keynsham",
    "sg:city":"Bristol",
    "sg:classifiers":[
        {
            "category":"Building & Trades",
            "subcategory":"Construction",
            "type":"Services"
        }
    ],
    "sg:postcode":"BS31 1JZ",
    "sg:province":"City of Bristol",
    "sg:tags":[
        "builder"
    ],
    "wof:name":"Kaseda Ltd",
    "wof:placetype":"venue"
},
  "geometry": {"coordinates":[-2.487182,51.398621],"type":"Point"}
}