{
  "type": "Feature",
  "properties": {
    "addr:full":"71 Biggin St Dover Kent CT16 1BB",
    "addr:housenumber":"71",
    "addr:postcode":"ct16 1bb",
    "addr:street":"Biggin St",
    "iso:country":"GB",
    "sg:address":"71 Biggin St",
    "sg:city":"Dover",
    "sg:classifiers":[
        {
            "category":"Retail",
            "subcategory":"Laundry & Dry Cleaning",
            "type":"Services"
        }
    ],
    "sg:phone":"+44 1304 204399",
    "sg:postcode":"CT16 1BB",
    "sg:province":"Kent",
    "sg:tags":[
        "alteration"
    ],
    "wof:name":"Johnsons The Cleaners",
    "wof:placetype":"venue"
},
  "geometry": {"coordinates":[1.310109,51.127075],"type":"Point"}
}