{
  "type": "Feature",
  "properties": {
    "addr:full":"54-56 Dalton Road Barrow-in-furness Cumbria LA14 1JB",
    "addr:housenumber":"54-56",
    "addr:postcode":"la14 1jb",
    "addr:street":"Dalton Road",
    "iso:country":"GB",
    "sg:address":"54-56 Dalton Road",
    "sg:city":"Barrow-in-furness",
    "sg:classifiers":[
        {
            "category":"Shopping",
            "subcategory":"Pharmacy",
            "type":"Retail Goods"
        }
    ],
    "sg:phone":"+44 1229 835398",
    "sg:postcode":"LA14 1JB",
    "sg:province":"Cumbria",
    "sg:tags":[
        "pharmacist",
        "store",
        "drug",
        "chemist"
    ],
    "wof:name":"Tattersall Chemist",
    "wof:placetype":"venue"
},
  "geometry": {"coordinates":[-3.2254159451,54.111415863],"type":"Point"}
}