{
  "type": "Feature",
  "properties": {
    "iso:country":"GB",
    "sg:address":"50a Wheeler Street",
    "sg:city":"Stourbridge",
    "sg:classifiers":[
        {
            "category":"Building & Trades",
            "subcategory":"Plumbing",
            "type":"Services"
        }
    ],
    "sg:phone":"+44 1384 372241",
    "sg:postcode":"DY8 1XJ",
    "sg:province":"Staffordshire",
    "sg:tags":[
        "heating"
    ],
    "wof:name":"Shilvock & Harris Ltd.",
    "wof:placetype":"venue"
},
  "geometry": {"coordinates":[-2.153564,52.457905],"type":"Point"}
}