{
  "type": "Feature",
  "properties": {
    "addr:full":"16 Thorpe Field Drive Leicester Leicestershire LE4 8GU",
    "addr:housenumber":"16",
    "addr:postcode":"le4 8gu",
    "addr:street":"Thorpe Field Drive",
    "iso:country":"GB",
    "sg:address":"16 Thorpe Field Drive",
    "sg:city":"Leicester",
    "sg:classifiers":[
        {
            "category":"Shopping",
            "subcategory":"Musical Instruments",
            "type":"Retail Goods"
        },
        {
            "category":"Transit Center",
            "subcategory":"Freight",
            "type":"Transportation"
        }
    ],
    "sg:phone":"+44 116 269 4405",
    "sg:postcode":"LE4 8GU",
    "sg:province":"Leicestershire",
    "sg:tags":[
        "piano",
        "accessory"
    ],
    "wof:name":"Clive G Carlin",
    "wof:placetype":"venue"
},
  "geometry": {"coordinates":[-1.085833,52.682953],"type":"Point"}
}