{
  "type": "Feature",
  "properties": {
    "addr:full":"5 Market Sq, Winslow Buckingham Buckinghamshire MK18 3AB",
    "addr:housenumber":"5",
    "addr:postcode":"mk18 3ab",
    "addr:street":"Market Sq",
    "iso:country":"GB",
    "sg:address":"5 Market Sq, Winslow",
    "sg:city":"Buckingham",
    "sg:classifiers":[
        {
            "category":"Professional",
            "type":"Services"
        }
    ],
    "sg:phone":"+44 1296 715555",
    "sg:postcode":"MK18 3AB",
    "sg:province":"Buckinghamshire",
    "sg:tags":[
        "leasing"
    ],
    "wof:name":"Protech Rentals Ltd",
    "wof:placetype":"venue"
},
  "geometry": {"coordinates":[-0.881326,51.943504],"type":"Point"}
}