{
  "type": "Feature",
  "properties": {
    "addr:full":"2 South, Crosshill Road, Bishopbriggs Glasgow East Dunbartonshire G64 2LZ",
    "addr:housenumber":"2",
    "addr:postcode":"g64 2lz",
    "addr:street":"South Crosshill Road",
    "iso:country":"GB",
    "sg:address":"2 South, Crosshill Road, Bishopbriggs",
    "sg:city":"Glasgow",
    "sg:classifiers":[
        {
            "category":"Place Of Worship",
            "type":"Public Place"
        }
    ],
    "sg:phone":"+44 141 772 1619",
    "sg:postcode":"G64 2LZ",
    "sg:province":"East Dunbartonshire",
    "wof:name":"St.Matthew S Catholic Church",
    "wof:placetype":"venue"
},
  "geometry": {"coordinates":[-4.2238688469,55.9066543579],"type":"Point"}
}