{
  "type": "Feature",
  "properties": {
    "iso:country":"GB",
    "sg:address":"Vicarage Field, Rear Of Grange Drive Community C",
    "sg:city":"Swindon",
    "sg:classifiers":[
        {
            "category":"Sports & Exercise",
            "subcategory":"Bowling",
            "type":"Entertainment"
        }
    ],
    "sg:phone":"+44 1793 822886",
    "sg:postcode":"SN1 3HJ",
    "sg:province":"Wiltshire",
    "wof:name":"Stratton Churchway Bowls Club",
    "wof:placetype":"venue"
},
  "geometry": {"coordinates":[-1.7764300108,51.5530509949],"type":"Point"}
}