{
  "type": "Feature",
  "properties": {
    "iso:country":"GB",
    "sg:address":"Garretts Farm, Plough Road, Eastchurch",
    "sg:city":"Sheerness",
    "sg:classifiers":[
        {
            "category":"Farming",
            "subcategory":"Livestock Farm",
            "type":"Manufacturing & Wholesale Goods"
        }
    ],
    "sg:phone":"+44 1795 880404",
    "sg:postcode":"ME12 4JL",
    "sg:province":"Kent",
    "sg:tags":[
        "others"
    ],
    "wof:name":"W G Frostick",
    "wof:placetype":"venue"
},
  "geometry": {"coordinates":[0.8604419827,51.4039115906],"type":"Point"}
}