{
  "type": "Feature",
  "properties": {
    "addr:full":"South Street, West Rainton Houghton-le-spring Durham DH4 6PA",
    "addr:postcode":"dh4 6pa",
    "addr:street":"South Street West",
    "iso:country":"GB",
    "sg:address":"South Street, West Rainton",
    "sg:city":"Houghton-le-spring",
    "sg:classifiers":[
        {
            "category":"Bars & Pubs",
            "type":"Food & Drink"
        }
    ],
    "sg:phone":"+44 191 584 1022",
    "sg:postcode":"DH4 6PA",
    "sg:province":"Durham",
    "sg:tags":[
        "pubs",
        "inn"
    ],
    "wof:name":"Whitbread Hotel Co. Ltd.",
    "wof:placetype":"venue"
},
  "geometry": {"coordinates":[-1.511014,54.847691],"type":"Point"}
}