{
  "type": "Feature",
  "properties": {
    "addr:full":"Yoxall Health Centre, Savey La Burton On Trent Derbyshire DE13 8PD",
    "addr:postcode":"de13 8pd",
    "addr:street":"La Burton On",
    "iso:country":"GB",
    "sg:address":"Yoxall Health Centre, Savey La",
    "sg:city":"Burton On Trent",
    "sg:classifiers":[
        {
            "category":"Health Services",
            "subcategory":"Doctor",
            "type":"Services"
        }
    ],
    "sg:phone":"+44 1543 472202",
    "sg:postcode":"DE13 8PD",
    "sg:province":"Derbyshire",
    "sg:tags":[
        "practitioners"
    ],
    "wof:name":"Atkinson, M G W",
    "wof:placetype":"venue"
},
  "geometry": {"coordinates":[-1.790862,52.768578],"type":"Point"}
}