{
  "type": "Feature",
  "properties": {
    "addr:full":"Y Traeth Porthmadog Gwynedd LL49 9DF",
    "addr:postcode":"ll49 9df",
    "addr:street":"Porthmadog",
    "iso:country":"GB",
    "sg:address":"Y Traeth",
    "sg:city":"Porthmadog",
    "sg:classifiers":[
        {
            "category":"Utilities",
            "subcategory":"Refuse",
            "type":"Services"
        }
    ],
    "sg:phone":"+44 1766 513152",
    "sg:postcode":"LL49 9DF",
    "sg:province":"Gwynedd",
    "sg:tags":[
        "disposal",
        "waste"
    ],
    "wof:name":"Wrights Waste Services",
    "wof:placetype":"venue"
},
  "geometry": {"coordinates":[-4.132989,52.927738],"type":"Point"}
}