{
  "type": "Feature",
  "properties": {
    "iso:country":"GB",
    "sg:address":"Unit 19 Robert Leonard Centre, Howemoss",
    "sg:city":"Aberdeen",
    "sg:classifiers":[
        {
            "category":"Government",
            "subcategory":"Post Office",
            "type":"Public Place"
        }
    ],
    "sg:phone":"+44 1224 771207",
    "sg:postcode":"AB21 0GL",
    "sg:province":"Aberdeen City",
    "sg:tags":[
        "messenger",
        "courier"
    ],
    "wof:name":"T N T Express Worldwide Ltd.",
    "wof:placetype":"venue"
},
  "geometry": {"coordinates":[-2.21805,57.20364],"type":"Point"}
}