{
  "type": "Feature",
  "properties": {
    "iso:country":"GB",
    "sg:address":"47 Woodland Rise",
    "sg:city":"Welwyn Garden City",
    "sg:classifiers":[
        {
            "category":"Professional",
            "subcategory":"Lawyer & Legal Services",
            "type":"Services"
        }
    ],
    "sg:postcode":"AL8 7LJ",
    "sg:province":"Hertfordshire",
    "sg:tags":[
        "advice",
        "counselling"
    ],
    "wof:name":"Marcia Agnew Counsellor",
    "wof:placetype":"venue"
},
  "geometry": {"coordinates":[-0.210075,51.809349],"type":"Point"}
}