{
  "type": "Feature",
  "properties": {
    "iso:country":"GB",
    "sg:address":"107 West Dock Street",
    "sg:city":"Hull",
    "sg:classifiers":[
        {
            "category":"Food & Beverages",
            "subcategory":"Meat & Fish",
            "type":"Retail Goods"
        }
    ],
    "sg:phone":"+44 1482 326705",
    "sg:postcode":"HU3 4TR",
    "sg:province":"East Riding of Yorkshire",
    "sg:tags":[
        "merchant"
    ],
    "wof:name":"St.Dunstan's Fishing Co. Ltd.",
    "wof:placetype":"venue"
},
  "geometry": {"coordinates":[-0.3720369935,53.7301025391],"type":"Point"}
}