{
  "type": "Feature",
  "properties": {
    "addr:full":"41 Clapham Terr Leamington Spa Warwickshire CV31 1HZ",
    "addr:housenumber":"41",
    "addr:postcode":"cv31 1hz",
    "addr:street":"Clapham Terr",
    "iso:country":"GB",
    "sg:address":"41 Clapham Terr",
    "sg:city":"Leamington Spa",
    "sg:classifiers":[
        {
            "category":"Shopping",
            "subcategory":"Department Store",
            "type":"Retail Goods"
        }
    ],
    "sg:phone":"+44 1926 428919",
    "sg:postcode":"CV31 1HZ",
    "sg:province":"Warwickshire",
    "wof:name":"Bains Stores",
    "wof:placetype":"venue"
},
  "geometry": {"coordinates":[-1.524151,52.282883],"type":"Point"}
}