{
  "type": "Feature",
  "properties": {
    "addr:full":"Flat 503 Mayflower House, Manhattan Drive Cambridge Cambridgeshire CB4 1TR",
    "addr:housenumber":"flat 503;house",
    "addr:postcode":"cb4 1tr",
    "addr:street":"Manhattan Drive",
    "iso:country":"GB",
    "sg:address":"Flat 503 Mayflower House, Manhattan Drive",
    "sg:city":"Cambridge",
    "sg:classifiers":[
        {
            "category":"Recreation",
            "subcategory":"Boat Charter",
            "type":"Entertainment"
        }
    ],
    "sg:postcode":"CB4 1TR",
    "sg:province":"Cambridgeshire",
    "sg:tags":[
        "excursion"
    ],
    "wof:name":"Cambridge Chauffeur Punts",
    "wof:placetype":"venue"
},
  "geometry": {"coordinates":[0.1354199946,52.2126998901],"type":"Point"}
}