{
  "type": "Feature",
  "properties": {
    "addr:full":"27 Scotland Street Ellesmere Shropshire SY12 0DG",
    "addr:housenumber":"27",
    "addr:postcode":"sy12 0dg",
    "addr:street":"Scotland Street",
    "iso:country":"GB",
    "sg:address":"27 Scotland Street",
    "sg:city":"Ellesmere",
    "sg:classifiers":[
        {
            "category":"Retail",
            "subcategory":"Repair Shop",
            "type":"Services"
        }
    ],
    "sg:postcode":"SY12 0DG",
    "sg:province":"Shropshire",
    "sg:tags":[
        "furniture"
    ],
    "wof:name":"Timothy John Butler",
    "wof:placetype":"venue"
},
  "geometry": {"coordinates":[-2.895746,52.906441],"type":"Point"}
}