{
  "type": "Feature",
  "properties": {
    "iso:country":"GB",
    "sg:address":"Kingsbridge House, 17-23 Rectory Gro",
    "sg:city":"Leigh-on-sea",
    "sg:classifiers":[
        {
            "category":"Building & Trades",
            "subcategory":"Cleaning & Sanitation",
            "type":"Services"
        }
    ],
    "sg:phone":"+44 1702 204424",
    "sg:postcode":"SS9 2HA",
    "sg:province":"Essex",
    "sg:tags":[
        "commercial"
    ],
    "wof:name":"R C S Cleaning Services Ltd.",
    "wof:placetype":"venue"
},
  "geometry": {"coordinates":[0.653816,51.542496],"type":"Point"}
}