{
  "type": "Feature",
  "properties": {
    "iso:country":"GB",
    "sg:address":"Mermaid Boatyard, Riverside, Brundall",
    "sg:city":"Norwich",
    "sg:classifiers":[
        {
            "category":"Real Estate",
            "subcategory":"Architect",
            "type":"Services"
        }
    ],
    "sg:postcode":"NR13 5PS",
    "sg:province":"Norfolk",
    "wof:name":"Unicorn Marine",
    "wof:placetype":"venue"
},
  "geometry": {"coordinates":[1.2948999405,52.6224937439],"type":"Point"}
}