{
  "type": "Feature",
  "properties": {
    "iso:country":"GB",
    "sg:address":"3 Market Street",
    "sg:city":"Alnwick",
    "sg:classifiers":[
        {
            "category":"Shopping",
            "subcategory":"Clothing, Apparel, & Fashions",
            "type":"Retail Goods"
        }
    ],
    "sg:phone":"+44 1665 510560",
    "sg:postcode":"NE66 1SS",
    "sg:province":"Northumberland",
    "sg:tags":[
        "lady",
        "fashionwear",
        "ladieswear"
    ],
    "wof:name":"Raggy Dolls",
    "wof:placetype":"venue"
},
  "geometry": {"coordinates":[-1.705776,55.413174],"type":"Point"}
}