{
  "type": "Feature",
  "properties": {
    "iso:country":"GB",
    "sg:address":"Woking Library, Gloucester Walk",
    "sg:city":"Woking",
    "sg:classifiers":[
        {
            "category":"Education",
            "subcategory":"Library",
            "type":"Public Place"
        }
    ],
    "sg:phone":"+44 1483 770591",
    "sg:postcode":"GU21 6HL",
    "sg:province":"Surrey",
    "sg:tags":[
        "book"
    ],
    "wof:name":"Woking Library",
    "wof:placetype":"venue"
},
  "geometry": {"coordinates":[-0.55855,51.322075],"type":"Point"}
}