{
  "type": "Feature",
  "properties": {
    "addr:full":"30 Meadow Lane, North Hykeham Lincoln Lincolnshire LN6 9RE",
    "addr:housenumber":"30",
    "addr:postcode":"ln6 9re",
    "addr:street":"Meadow Lane",
    "iso:country":"GB",
    "sg:address":"30 Meadow Lane, North Hykeham",
    "sg:city":"Lincoln",
    "sg:classifiers":[
        {
            "category":"Building & Trades",
            "subcategory":"Landscaping Services",
            "type":"Services"
        }
    ],
    "sg:phone":"+44 1522 500464",
    "sg:postcode":"LN6 9RE",
    "sg:province":"Lincolnshire",
    "sg:tags":[
        "landscape",
        "contractor"
    ],
    "wof:name":"Cedar Landscaping",
    "wof:placetype":"venue"
},
  "geometry": {"coordinates":[-0.5851169825,53.1795883179],"type":"Point"}
}