{
  "type": "Feature",
  "properties": {
    "addr:full":"14 Derllwyn Rd Bridgend Bridgend CF32 9DG",
    "addr:housenumber":"14",
    "addr:postcode":"cf32 9dg",
    "addr:street":"Derllwyn Rd",
    "iso:country":"GB",
    "sg:address":"14 Derllwyn Rd",
    "sg:city":"Bridgend",
    "sg:classifiers":[
        {
            "category":"Retail",
            "subcategory":"Driving School",
            "type":"Services"
        }
    ],
    "sg:phone":"+44 1656 725778",
    "sg:postcode":"CF32 9DG",
    "sg:province":"Bridgend",
    "wof:name":"John Essaye School Of Motoring",
    "wof:placetype":"venue"
},
  "geometry": {"coordinates":[-3.5984590054,51.5506439209],"type":"Point"}
}