{
  "type": "Feature",
  "properties": {
    "addr:full":"86 Market Street Hyde Cheshire SK14 1ES",
    "addr:housenumber":"86",
    "addr:postcode":"sk14 1es",
    "addr:street":"Market Street",
    "iso:country":"GB",
    "sg:address":"86 Market Street",
    "sg:city":"Hyde",
    "sg:classifiers":[
        {
            "category":"Home & Garden",
            "subcategory":"Carpets & Floor Coverings",
            "type":"Retail Goods"
        }
    ],
    "sg:phone":"+44 161 368 4660",
    "sg:postcode":"SK14 1ES",
    "sg:province":"Cheshire",
    "sg:tags":[
        "carpets",
        "rug",
        "matting"
    ],
    "wof:name":"Market Place Carpet Centre",
    "wof:placetype":"venue"
},
  "geometry": {"coordinates":[-2.078707,53.450031],"type":"Point"}
}