{
  "type": "Feature",
  "properties": {
    "iso:country":"GB",
    "sg:address":"288 Aldridge Road, Streetly",
    "sg:city":"Sutton Coldfield",
    "sg:classifiers":[
        {
            "category":"Professional",
            "type":"Services"
        }
    ],
    "sg:postcode":"B74 2DU",
    "sg:province":"Staffordshire",
    "sg:tags":[
        "entertainer"
    ],
    "wof:name":"Platinum Entertaintments",
    "wof:placetype":"venue"
},
  "geometry": {"coordinates":[-1.8921610117,52.5705299377],"type":"Point"}
}