{
  "type": "Feature",
  "properties": {
    "addr:full":"2 Willowbrook, Stanton Harcourt Witney Oxfordshire OX29 5SN",
    "addr:housenumber":"2",
    "addr:postcode":"ox29 5sn",
    "addr:street":"Willowbrook Stanton",
    "iso:country":"GB",
    "sg:address":"2 Willowbrook, Stanton Harcourt",
    "sg:city":"Witney",
    "sg:classifiers":[
        {
            "category":"Building & Trades",
            "subcategory":"Construction",
            "type":"Services"
        }
    ],
    "sg:phone":"+44 1865 883435",
    "sg:postcode":"OX29 5SN",
    "sg:province":"Oxfordshire",
    "sg:tags":[
        "specialised",
        "work",
        "platform",
        "scaffolding",
        "contractor"
    ],
    "wof:name":"S A S Scaffolding Services",
    "wof:placetype":"venue"
},
  "geometry": {"coordinates":[-1.408325,51.74807],"type":"Point"}
}