{
  "type": "Feature",
  "properties": {
    "addr:full":"Norman Rd Belvedere Kent DA17 6LD",
    "addr:postcode":"da17 6ld",
    "addr:street":"Norman Rd",
    "iso:country":"GB",
    "sg:address":"Norman Rd",
    "sg:city":"Belvedere",
    "sg:classifiers":[
        {
            "category":"Retail",
            "subcategory":"Repair Shop",
            "type":"Services"
        }
    ],
    "sg:postcode":"DA17 6LD",
    "sg:province":"Kent",
    "sg:tags":[
        "equipment",
        "catering"
    ],
    "wof:name":"Marigold Industrial Catering Services Lt",
    "wof:placetype":"venue"
},
  "geometry": {"coordinates":[0.15278,51.494236],"type":"Point"}
}