{
  "type": "Feature",
  "properties": {
    "iso:country":"GB",
    "sg:address":"Unit 6 Station Road, Wetheringsett",
    "sg:city":"Stowmarket",
    "sg:classifiers":[
        {
            "category":"Professional",
            "type":"Services"
        },
        {
            "category":"Manufacturing",
            "subcategory":"Electronics",
            "type":"Manufacturing & Wholesale Goods"
        }
    ],
    "sg:phone":"+44 1449 766711",
    "sg:postcode":"IP14 5QJ",
    "sg:province":"Suffolk",
    "sg:tags":[
        "control",
        "manufacture",
        "system",
        "panel"
    ],
    "wof:name":"I C S",
    "wof:placetype":"venue"
},
  "geometry": {"coordinates":[1.119843,52.244213],"type":"Point"}
}