{
  "type": "Feature",
  "properties": {
    "iso:country":"GB",
    "sg:address":"Cairnorrie",
    "sg:city":"Ellon",
    "sg:classifiers":[
        {
            "category":"Education",
            "subcategory":"School",
            "type":"Public Place"
        },
        {
            "category":"Government",
            "subcategory":"Office",
            "type":"Public Place"
        }
    ],
    "sg:phone":"+44 1651 806262",
    "sg:postcode":"AB41 7BX",
    "sg:province":"Aberdeenshire",
    "sg:tags":[
        "local",
        "authority"
    ],
    "wof:name":"Cairnorrie School",
    "wof:placetype":"venue"
},
  "geometry": {"coordinates":[-2.2092790604,57.3821907043],"type":"Point"}
}