{
  "type": "Feature",
  "properties": {
    "addr:full":"138 Listerhills Road Bradford West Yorkshire BD7 1JR",
    "addr:housenumber":"138",
    "addr:postcode":"bd7 1jr",
    "addr:street":"Listerhills Road",
    "iso:country":"GB",
    "sg:address":"138 Listerhills Road",
    "sg:city":"Bradford",
    "sg:classifiers":[
        {
            "category":"Bars & Pubs",
            "type":"Food & Drink"
        },
        {
            "category":"Community Center",
            "subcategory":"Social",
            "type":"Public Place"
        },
        {
            "category":"Travel",
            "subcategory":"Hotels & Motels",
            "type":"Entertainment"
        }
    ],
    "sg:postcode":"BD7 1JR",
    "sg:province":"West Yorkshire",
    "sg:tags":[
        "pubs",
        "house",
        "inn",
        "activity"
    ],
    "wof:name":"E Fernie",
    "wof:placetype":"venue"
},
  "geometry": {"coordinates":[-1.769877,53.793793],"type":"Point"}
}