{
  "type": "Feature",
  "properties": {
    "addr:full":"1 Georges Wood Road, Brookmans Park Hatfield Hertfordshire AL9 7BY",
    "addr:housenumber":"1",
    "addr:postcode":"al9 7by",
    "addr:street":"Georges Wood Road",
    "iso:country":"GB",
    "sg:address":"1 Georges Wood Road, Brookmans Park",
    "sg:city":"Hatfield",
    "sg:classifiers":[
        {
            "category":"Real Estate",
            "subcategory":"Architect",
            "type":"Services"
        }
    ],
    "sg:postcode":"AL9 7BY",
    "sg:province":"Hertfordshire",
    "wof:name":"David Carr & Associates",
    "wof:placetype":"venue"
},
  "geometry": {"coordinates":[-0.177789,51.722935],"type":"Point"}
}