{
  "type": "Feature",
  "properties": {
    "addr:full":"Crief Farm, Wass York North Yorkshire YO61 4AY",
    "addr:postcode":"yo61 4ay",
    "addr:street":"Crief;Wass",
    "iso:country":"GB",
    "sg:address":"Crief Farm, Wass",
    "sg:city":"York",
    "sg:classifiers":[
        {
            "category":"Travel",
            "subcategory":"Hotels & Motels",
            "type":"Entertainment"
        }
    ],
    "sg:phone":"+44 1347 868207",
    "sg:postcode":"YO61 4AY",
    "sg:province":"North Yorkshire",
    "sg:tags":[
        "self",
        "catering"
    ],
    "wof:name":"Crief Lodge Holiday Homes",
    "wof:placetype":"venue"
},
  "geometry": {"coordinates":[-1.1510210037,54.2063446045],"type":"Point"}
}