{
  "type": "Feature",
  "properties": {
    "addr:full":"Kings Down Tail Caravan Park Sidmouth Devon EX10 0PD",
    "addr:postcode":"ex10 0pd",
    "addr:street":"Down;Sidmouth",
    "iso:country":"GB",
    "sg:address":"Kings Down Tail Caravan Park",
    "sg:city":"Sidmouth",
    "sg:classifiers":[
        {
            "category":"Recreation",
            "subcategory":"Campground",
            "type":"Entertainment"
        }
    ],
    "sg:phone":"+44 1297 680313",
    "sg:postcode":"EX10 0PD",
    "sg:province":"Devon",
    "sg:tags":[
        "caravan",
        "park"
    ],
    "wof:name":"Ian McKenzie-Edwards",
    "wof:placetype":"venue"
},
  "geometry": {"coordinates":[-3.237619,50.68745],"type":"Point"}
}