{
  "type": "Feature",
  "properties": {
    "addr:full":"Hangar, 1a Wrights Lane, Burtonwood Warrington Cheshire WA5 4DB",
    "addr:postcode":"wa5 4db",
    "addr:street":"Wrights Lane",
    "iso:country":"GB",
    "sg:address":"Hangar, 1a Wrights Lane, Burtonwood",
    "sg:city":"Warrington",
    "sg:classifiers":[
        {
            "category":"Retail",
            "subcategory":"Storage",
            "type":"Services"
        }
    ],
    "sg:phone":"+44 1925 711157",
    "sg:postcode":"WA5 4DB",
    "sg:province":"Cheshire",
    "sg:tags":[
        "cold"
    ],
    "wof:name":"Advanced Thermal Composites Ltd.",
    "wof:placetype":"venue"
},
  "geometry": {"coordinates":[-2.659374,53.431076],"type":"Point"}
}