{
  "type": "Feature",
  "properties": {
    "iso:country":"GB",
    "sg:address":"24 Blackhorse Road",
    "sg:city":"Bristol",
    "sg:classifiers":[
        {
            "category":"Building & Trades",
            "subcategory":"Construction",
            "type":"Services"
        }
    ],
    "sg:phone":"+44 117 960 9891",
    "sg:postcode":"BS15 8EF",
    "sg:province":"City of Bristol",
    "sg:tags":[
        "builder"
    ],
    "wof:name":"M & J Building Contractors",
    "wof:placetype":"venue"
},
  "geometry": {"coordinates":[-2.512207,51.460152],"type":"Point"}
}