{
  "type": "Feature",
  "properties": {
    "addr:full":"424 Stradbroke Road Sheffield South Yorkshire S13 7GA",
    "addr:housenumber":"424",
    "addr:postcode":"s13 7ga",
    "addr:street":"Stradbroke Road",
    "iso:country":"GB",
    "sg:address":"424 Stradbroke Road",
    "sg:city":"Sheffield",
    "sg:classifiers":[
        {
            "category":"Building & Trades",
            "subcategory":"Construction",
            "type":"Services"
        }
    ],
    "sg:phone":"+44 114 269 1098",
    "sg:postcode":"S13 7GA",
    "sg:province":"South Yorkshire",
    "sg:tags":[
        "decorator",
        "painter"
    ],
    "wof:name":"Billy Lax",
    "wof:placetype":"venue"
},
  "geometry": {"coordinates":[-1.382676959,53.3592338562],"type":"Point"}
}