{
  "type": "Feature",
  "properties": {
    "iso:country":"GB",
    "sg:address":"24 High St",
    "sg:city":"Scunthorpe",
    "sg:classifiers":[
        {
            "category":"Shopping",
            "subcategory":"Computers & Home Electronics",
            "type":"Retail Goods"
        }
    ],
    "sg:phone":"+44 1724 764948",
    "sg:postcode":"DN17 3RS",
    "sg:province":"Lincolnshire",
    "sg:tags":[
        "aerial",
        "television",
        "radio"
    ],
    "wof:name":"Aerial Contractors",
    "wof:placetype":"venue"
},
  "geometry": {"coordinates":[-0.736453,53.576115],"type":"Point"}
}