{
  "type": "Feature",
  "properties": {
    "addr:full":"86 The Thoroughfare Woodbridge Suffolk IP12 1AH",
    "addr:housenumber":"86",
    "addr:postcode":"ip12 1ah",
    "addr:street":"The Thoroughfare",
    "iso:country":"GB",
    "sg:address":"86 The Thoroughfare",
    "sg:city":"Woodbridge",
    "sg:classifiers":[
        {
            "category":"Personal",
            "subcategory":"Beauty Salon",
            "type":"Services"
        }
    ],
    "sg:phone":"+44 1394 387436",
    "sg:postcode":"IP12 1AH",
    "sg:province":"Suffolk",
    "sg:tags":[
        "unisex",
        "hairdresser"
    ],
    "wof:name":"The Hair Workshop by Robert Douglas",
    "wof:placetype":"venue"
},
  "geometry": {"coordinates":[1.3316,52.106167],"type":"Point"}
}