{
  "type": "Feature",
  "properties": {
    "addr:full":"5 Windsor Place Bridge Of Weir Inverclyde PA11 3AF",
    "addr:housenumber":"5",
    "addr:postcode":"pa11 3af",
    "addr:street":"Windsor Place Bridge",
    "iso:country":"GB",
    "sg:address":"5 Windsor Place",
    "sg:city":"Bridge Of Weir",
    "sg:classifiers":[
        {
            "category":"Home & Garden",
            "subcategory":"Building Materials",
            "type":"Retail Goods"
        },
        {
            "category":"Home & Garden",
            "subcategory":"Furniture",
            "type":"Retail Goods"
        }
    ],
    "sg:postcode":"PA11 3AF",
    "sg:province":"Inverclyde",
    "sg:tags":[
        "furnishers",
        "bathroom",
        "planner"
    ],
    "wof:name":"Aqua Style",
    "wof:placetype":"venue"
},
  "geometry": {"coordinates":[-4.582529068,55.8567199707],"type":"Point"}
}