{
  "type": "Feature",
  "properties": {
    "addr:full":"Treoak Housey Farm Liskeard Cornwall PL14 4JX",
    "addr:postcode":"pl14 4jx",
    "iso:country":"GB",
    "sg:address":"Treoak Housey Farm",
    "sg:city":"Liskeard",
    "sg:classifiers":[
        {
            "category":"Farming",
            "subcategory":"Farm",
            "type":"Manufacturing & Wholesale Goods"
        }
    ],
    "sg:phone":"+44 1579 343008",
    "sg:postcode":"PL14 4JX",
    "sg:province":"Cornwall",
    "sg:tags":[
        "mixed",
        "crop"
    ],
    "wof:name":"D G & B M Coumbe",
    "wof:placetype":"venue"
},
  "geometry": {"coordinates":[-4.465834,50.453796],"type":"Point"}
}