{
  "type": "Feature",
  "properties": {
    "addr:full":"37c Seaford Road Enfield Greater London EN1 1NS",
    "addr:housenumber":"37c",
    "addr:postcode":"en1 1ns",
    "addr:street":"Seaford Road",
    "iso:country":"GB",
    "sg:address":"37c Seaford Road",
    "sg:city":"Enfield",
    "sg:classifiers":[
        {
            "category":"Building & Trades",
            "subcategory":"Construction",
            "type":"Services"
        }
    ],
    "sg:phone":"+44 20 8364 4097",
    "sg:postcode":"EN1 1NS",
    "sg:province":"Greater London",
    "sg:tags":[
        "builder"
    ],
    "wof:name":"Oakland Building Services Ltd.",
    "wof:placetype":"venue"
},
  "geometry": {"coordinates":[-0.072718,51.650482],"type":"Point"}
}