{
  "type": "Feature",
  "properties": {
    "addr:full":"18-20 Leslie Street Blairgowrie Perth and Kinross PH10 6AH",
    "addr:housenumber":"18-20",
    "addr:postcode":"ph10 6ah",
    "addr:street":"Leslie Street",
    "iso:country":"GB",
    "sg:address":"18-20 Leslie Street",
    "sg:city":"Blairgowrie",
    "sg:classifiers":[
        {
            "category":"Restaurant",
            "type":"Food & Drink"
        }
    ],
    "sg:phone":"+44 1250 874888",
    "sg:postcode":"PH10 6AH",
    "sg:province":"Perth and Kinross",
    "wof:name":"The Dome Restaurant",
    "wof:placetype":"venue"
},
  "geometry": {"coordinates":[-3.338181,56.59193],"type":"Point"}
}