{
  "type": "Feature",
  "properties": {
    "iso:country":"GB",
    "sg:address":"Station Rd",
    "sg:city":"Holywell",
    "sg:classifiers":[
        {
            "category":"Wholesale",
            "subcategory":"Scrap",
            "type":"Manufacturing & Wholesale Goods"
        }
    ],
    "sg:postcode":"CH8 7EL",
    "sg:province":"Denbighshire",
    "sg:tags":[
        "breaker",
        "dismantlers"
    ],
    "wof:name":"M & M Motor Salvage",
    "wof:placetype":"venue"
},
  "geometry": {"coordinates":[-3.206049,53.291161],"type":"Point"}
}