{
  "type": "Feature",
  "properties": {
    "addr:full":"Waterloo Road Wolverhampton West Midlands WV1 4RB",
    "addr:postcode":"wv1 4rb",
    "addr:street":"Waterloo Road",
    "iso:country":"GB",
    "sg:address":"Waterloo Road",
    "sg:city":"Wolverhampton",
    "sg:classifiers":[
        {
            "category":"Bars & Pubs",
            "type":"Food & Drink"
        }
    ],
    "sg:phone":"+44 1902 421833",
    "sg:postcode":"WV1 4RB",
    "sg:province":"West Midlands",
    "sg:tags":[
        "pubs",
        "inn"
    ],
    "wof:name":"The Goalpost",
    "wof:placetype":"venue"
},
  "geometry": {"coordinates":[-2.1308839321,52.5933494568],"type":"Point"}
}