{
  "type": "Feature",
  "properties": {
    "iso:country":"GB",
    "sg:address":"22 St Lawrence Road, North Wingfield",
    "sg:city":"Chesterfield",
    "sg:classifiers":[
        {
            "category":"Bars & Pubs",
            "type":"Food & Drink"
        }
    ],
    "sg:phone":"+44 1246 851021",
    "sg:postcode":"S42 5LH",
    "sg:province":"Derbyshire",
    "sg:tags":[
        "pubs",
        "inn"
    ],
    "wof:name":"White Hart Inn",
    "wof:placetype":"venue"
},
  "geometry": {"coordinates":[-1.388553,53.180233],"type":"Point"}
}