{
  "type": "Feature",
  "properties": {
    "addr:full":"22 Cheriton Gardens, Godington Way Industrial Estate Folkestone Kent TN23 1JB",
    "addr:housenumber":"22;estate",
    "addr:postcode":"tn23 1jb",
    "addr:street":"Cheriton Gardens Godington Way Industrial",
    "iso:country":"GB",
    "sg:address":"22 Cheriton Gardens, Godington Way Industrial Estate",
    "sg:city":"Folkestone",
    "sg:classifiers":[
        {
            "category":"Home & Garden",
            "subcategory":"Household Appliances",
            "type":"Retail Goods"
        }
    ],
    "sg:phone":"+44 1622 861411",
    "sg:postcode":"TN23 1JB",
    "sg:province":"Kent",
    "sg:tags":[
        "refrigeration",
        "air conditioning"
    ],
    "wof:name":"Airite (Southern) Ltd.",
    "wof:placetype":"venue"
},
  "geometry": {"coordinates":[0.86593,51.14806],"type":"Point"}
}