{
  "type": "Feature",
  "properties": {
    "iso:country":"GB",
    "sg:address":"66 Bold St",
    "sg:city":"Liverpool",
    "sg:classifiers":[
        {
            "category":"Bars & Pubs",
            "subcategory":"Wine Bar",
            "type":"Food & Drink"
        }
    ],
    "sg:postcode":"L1 4HR",
    "sg:province":"Merseyside",
    "wof:name":"Thomas,Lola,",
    "wof:placetype":"venue"
},
  "geometry": {"coordinates":[-2.978655,53.403202],"type":"Point"}
}