{
  "type": "Feature",
  "properties": {
    "addr:full":"Office 17, Castle Park Frodsham Cheshire WA6 6UJ",
    "addr:housenumber":"17",
    "addr:postcode":"wa6 6uj",
    "addr:street":"Castle Park",
    "iso:country":"GB",
    "sg:address":"Office 17, Castle Park",
    "sg:city":"Frodsham",
    "sg:classifiers":[
        {
            "category":"Government",
            "subcategory":"Office",
            "type":"Public Place"
        }
    ],
    "sg:postcode":"WA6 6UJ",
    "sg:province":"Cheshire",
    "sg:tags":[
        "mp",
        "meps"
    ],
    "wof:name":"Mike Hall",
    "wof:placetype":"venue"
},
  "geometry": {"coordinates":[-2.70773,53.263512],"type":"Point"}
}