{
  "type": "Feature",
  "properties": {
    "iso:country":"GB",
    "sg:address":"72 Aston Abbotts Road, Weedon",
    "sg:city":"Aylesbury",
    "sg:classifiers":[
        {
            "category":"Building & Trades",
            "subcategory":"Landscaping Services",
            "type":"Services"
        }
    ],
    "sg:postcode":"HP22 4NH",
    "sg:province":"Buckinghamshire",
    "sg:tags":[
        "irrigation",
        "system"
    ],
    "wof:name":"Oasis Irrigation Systems",
    "wof:placetype":"venue"
},
  "geometry": {"coordinates":[-0.813518,51.856411],"type":"Point"}
}