{
  "type": "Feature",
  "properties": {
    "addr:full":"1 Abbeygate Grimsby Lincolnshire DN31 1JY",
    "addr:housenumber":"1",
    "addr:postcode":"dn31 1jy",
    "addr:street":"Abbeygate",
    "iso:country":"GB",
    "sg:address":"1 Abbeygate",
    "sg:city":"Grimsby",
    "sg:classifiers":[
        {
            "category":"Travel",
            "subcategory":"Travel Agent",
            "type":"Entertainment"
        }
    ],
    "sg:phone":"+44 1472 352137",
    "sg:postcode":"DN31 1JY",
    "sg:province":"Lincolnshire",
    "wof:name":"Inter-Continental Travel Ltd.",
    "wof:placetype":"venue"
},
  "geometry": {"coordinates":[-0.086364001,53.5644111633],"type":"Point"}
}