{
  "type": "Feature",
  "properties": {
    "addr:full":"263 Kingsland Rd Bethnal Green Greater London E2 8AS",
    "addr:housenumber":"263",
    "addr:postcode":"e2 8as",
    "addr:street":"Kingsland Rd",
    "iso:country":"GB",
    "sg:address":"263 Kingsland Rd",
    "sg:city":"Bethnal Green",
    "sg:classifiers":[
        {
            "category":"Personal",
            "subcategory":"Beauty Salon",
            "type":"Services"
        }
    ],
    "sg:phone":"+44 20 7613 2050",
    "sg:postcode":"E2 8AS",
    "sg:province":"Greater London",
    "sg:tags":[
        "unisex",
        "hairdresser"
    ],
    "wof:name":"Images",
    "wof:placetype":"venue"
},
  "geometry": {"coordinates":[-0.077139,51.535561],"type":"Point"}
}