{
  "type": "Feature",
  "properties": {
    "addr:full":"87 Cricklewood Broadway London Greater London NW2 3JG",
    "addr:housenumber":"87",
    "addr:postcode":"nw2 3jg",
    "addr:street":"Cricklewood Broadway",
    "iso:country":"GB",
    "sg:address":"87 Cricklewood Broadway",
    "sg:city":"London",
    "sg:classifiers":[
        {
            "category":"Professional",
            "subcategory":"Lawyer & Legal Services",
            "type":"Services"
        }
    ],
    "sg:phone":"+44 20 8450 1832",
    "sg:postcode":"NW2 3JG",
    "sg:province":"Greater London",
    "sg:tags":[
        "solicitor"
    ],
    "wof:name":"Straiton & Co.",
    "wof:placetype":"venue"
},
  "geometry": {"coordinates":[-0.213039,51.554562],"type":"Point"}
}