{
  "type": "Feature",
  "properties": {
    "addr:full":"21 Gladstone Rd, Willesborough Ashford Kent TN24 0BY",
    "addr:housenumber":"21",
    "addr:postcode":"tn24 0by",
    "addr:street":"Gladstone Rd",
    "iso:country":"GB",
    "sg:address":"21 Gladstone Rd, Willesborough",
    "sg:city":"Ashford",
    "sg:classifiers":[
        {
            "category":"Autos & Motor Vehicles",
            "subcategory":"Automobile Sales",
            "type":"Retail Goods"
        }
    ],
    "sg:phone":"+44 1233 664418",
    "sg:postcode":"TN24 0BY",
    "sg:province":"Kent",
    "sg:tags":[
        "commercial"
    ],
    "wof:name":"Motor Match",
    "wof:placetype":"venue"
},
  "geometry": {"coordinates":[0.8913319707,51.1344947815],"type":"Point"}
}