{
  "type": "Feature",
  "properties": {
    "addr:full":"25 Queen Street Scarborough North Yorkshire YO11 1HA",
    "addr:housenumber":"25",
    "addr:postcode":"yo11 1ha",
    "addr:street":"Queen Street",
    "iso:country":"GB",
    "sg:address":"25 Queen Street",
    "sg:city":"Scarborough",
    "sg:classifiers":[
        {
            "category":"Bars & Pubs",
            "type":"Food & Drink"
        },
        {
            "category":"Community Center",
            "subcategory":"Social",
            "type":"Public Place"
        }
    ],
    "sg:phone":"+44 1723 373074",
    "sg:postcode":"YO11 1HA",
    "sg:province":"North Yorkshire",
    "sg:tags":[
        "pubs",
        "house",
        "inn",
        "activity"
    ],
    "wof:name":"Black Swan Hotel",
    "wof:placetype":"venue"
},
  "geometry": {"coordinates":[-0.3992390037,54.2845611572],"type":"Point"}
}