{
  "type": "Feature",
  "properties": {
    "iso:country":"GB",
    "sg:address":"19 Govan Cross Shopping Centre, Govan Road",
    "sg:city":"Glasgow",
    "sg:classifiers":[
        {
            "category":"Home & Garden",
            "subcategory":"Carpets & Floor Coverings",
            "type":"Retail Goods"
        }
    ],
    "sg:postcode":"G51 3JW",
    "sg:province":"Glasgow City",
    "sg:tags":[
        "carpets",
        "rug",
        "matting"
    ],
    "wof:name":"Premier Carpets",
    "wof:placetype":"venue"
},
  "geometry": {"coordinates":[-4.31279,55.862598],"type":"Point"}
}