{
  "type": "Feature",
  "properties": {
    "iso:country":"GB",
    "sg:address":"348 West Barnes Lane",
    "sg:city":"New Malden",
    "sg:classifiers":[
        {
            "category":"Utilities",
            "subcategory":"Telephone",
            "type":"Services"
        },
        {
            "category":"Shopping",
            "subcategory":"Computers & Home Electronics",
            "type":"Retail Goods"
        }
    ],
    "sg:phone":"+44 20 8336 1150",
    "sg:postcode":"KT3 6NB",
    "sg:province":"Surrey",
    "sg:tags":[
        "telecom",
        "equipment",
        "system",
        "telecommunication"
    ],
    "wof:name":"Telecoms U K",
    "wof:placetype":"venue"
},
  "geometry": {"coordinates":[-0.2391490042,51.3941001892],"type":"Point"}
}