{
  "type": "Feature",
  "properties": {
    "addr:full":"Measham House Farm, Gallows Lane, Measham Swadlincote Derbyshire DE12 7HD",
    "addr:postcode":"de12 7hd",
    "addr:street":"Gallows Lane",
    "iso:country":"GB",
    "sg:address":"Measham House Farm, Gallows Lane, Measham",
    "sg:city":"Swadlincote",
    "sg:classifiers":[
        {
            "category":"Travel",
            "subcategory":"Hotels & Motels",
            "type":"Entertainment"
        },
        {
            "category":"Farming",
            "subcategory":"Livestock Farm",
            "type":"Manufacturing & Wholesale Goods"
        },
        {
            "category":"Farming",
            "subcategory":"Farm",
            "type":"Manufacturing & Wholesale Goods"
        }
    ],
    "sg:phone":"+44 1530 270465",
    "sg:postcode":"DE12 7HD",
    "sg:province":"Derbyshire",
    "sg:tags":[
        "mixed",
        "house",
        "guest",
        "crop",
        "others"
    ],
    "wof:name":"J J LOVETT",
    "wof:placetype":"venue"
},
  "geometry": {"coordinates":[-1.5119240284,52.7032585144],"type":"Point"}
}