{
  "type": "Feature",
  "properties": {
    "addr:full":"539 Maidstone Road, Wigmore Gillingham Kent ME8 0JY",
    "addr:housenumber":"539",
    "addr:postcode":"me8 0jy",
    "addr:street":"Maidstone Road",
    "iso:country":"GB",
    "sg:address":"539 Maidstone Road, Wigmore",
    "sg:city":"Gillingham",
    "sg:classifiers":[
        {
            "category":"Professional",
            "subcategory":"Engineering",
            "type":"Services"
        }
    ],
    "sg:postcode":"ME8 0JY",
    "sg:province":"Kent",
    "sg:tags":[
        "precision",
        "engineer"
    ],
    "wof:name":"Trimec Services Engineering",
    "wof:placetype":"venue"
},
  "geometry": {"coordinates":[0.589114,51.343311],"type":"Point"}
}