{
  "type": "Feature",
  "properties": {
    "addr:full":"2 Church Terrace Holyhead Isle of Anglesey LL65 2HP",
    "addr:housenumber":"2",
    "addr:postcode":"ll65 2hp",
    "addr:street":"Church Terrace",
    "iso:country":"GB",
    "sg:address":"2 Church Terrace",
    "sg:city":"Holyhead",
    "sg:classifiers":[
        {
            "category":"Manufacturing",
            "subcategory":"Tools & Machinery",
            "type":"Manufacturing & Wholesale Goods"
        }
    ],
    "sg:phone":"+44 1407 760914",
    "sg:postcode":"LL65 2HP",
    "sg:province":"Isle of Anglesey",
    "sg:tags":[
        "society",
        "friendly"
    ],
    "wof:name":"John Lyon Insurance Services",
    "wof:placetype":"venue"
},
  "geometry": {"coordinates":[-4.630714,53.30637],"type":"Point"}
}