{
  "type": "Feature",
  "properties": {
    "addr:full":"58 Pasley Street Plymouth Devon PL2 1DR",
    "addr:housenumber":"58",
    "addr:postcode":"pl2 1dr",
    "addr:street":"Pasley Street",
    "iso:country":"GB",
    "sg:address":"58 Pasley Street",
    "sg:city":"Plymouth",
    "sg:classifiers":[
        {
            "category":"Fast Food",
            "type":"Food & Drink"
        },
        {
            "category":"Restaurant",
            "type":"Food & Drink"
        }
    ],
    "sg:phone":"+44 1752 607330",
    "sg:postcode":"PL2 1DR",
    "sg:province":"Devon",
    "sg:tags":[
        "away",
        "take"
    ],
    "wof:name":"Pasley Chinese Take Away",
    "wof:placetype":"venue"
},
  "geometry": {"coordinates":[-4.171645,50.38245],"type":"Point"}
}