{
  "type": "Feature",
  "properties": {
    "addr:full":"Hall Rd Leamington Spa Warwickshire CV32 5RA",
    "addr:postcode":"cv32 5ra",
    "addr:street":"Hall Rd",
    "iso:country":"GB",
    "sg:address":"Hall Rd",
    "sg:city":"Leamington Spa",
    "sg:classifiers":[
        {
            "category":"Retail",
            "subcategory":"Auto Repair",
            "type":"Services"
        }
    ],
    "sg:phone":"+44 1926 426409",
    "sg:postcode":"CV32 5RA",
    "sg:province":"Warwickshire",
    "sg:tags":[
        "car",
        "specialist",
        "customizing"
    ],
    "wof:name":"Just Tyres",
    "wof:placetype":"venue"
},
  "geometry": {"coordinates":[-1.538214,52.294144],"type":"Point"}
}