{
  "type": "Feature",
  "properties": {
    "addr:full":"151a Cowley Road Oxford Oxfordshire OX4 1UT",
    "addr:housenumber":"151a",
    "addr:postcode":"ox4 1ut",
    "addr:street":"Cowley Road",
    "iso:country":"GB",
    "sg:address":"151a Cowley Road",
    "sg:city":"Oxford",
    "sg:classifiers":[
        {
            "category":"Shopping",
            "subcategory":"Pharmacy",
            "type":"Retail Goods"
        }
    ],
    "sg:phone":"+44 1865 243633",
    "sg:postcode":"OX4 1UT",
    "sg:province":"Oxfordshire",
    "sg:tags":[
        "pharmacist",
        "chemist"
    ],
    "wof:name":"Boots the Chemists",
    "wof:placetype":"venue"
},
  "geometry": {"coordinates":[-1.2361730337,51.7476234436],"type":"Point"}
}