{
  "type": "Feature",
  "properties": {
    "addr:full":"90 Archel Road, West Kensington London Greater London W14 9QP",
    "addr:housenumber":"90",
    "addr:postcode":"w14 9qp",
    "addr:street":"Archel Road",
    "iso:country":"GB",
    "sg:address":"90 Archel Road, West Kensington",
    "sg:city":"London",
    "sg:classifiers":[
        {
            "category":"Professional",
            "subcategory":"Business Services",
            "type":"Services"
        }
    ],
    "sg:phone":"+44 20 7864 8370",
    "sg:postcode":"W14 9QP",
    "sg:province":"Greater London",
    "sg:tags":[
        "accomodation"
    ],
    "wof:name":"Charm Valley Ltd.",
    "wof:placetype":"venue"
},
  "geometry": {"coordinates":[-0.2071069926,51.4862785339],"type":"Point"}
}