{
  "type": "Feature",
  "properties": {
    "addr:full":"136-140 Bedford Road, Kempston Bedford Bedfordshire MK42 8BH",
    "addr:housenumber":"136-140",
    "addr:postcode":"mk42 8bh",
    "addr:street":"Bedford Road",
    "iso:country":"GB",
    "sg:address":"136-140 Bedford Road, Kempston",
    "sg:city":"Bedford",
    "sg:classifiers":[
        {
            "category":"Airport",
            "subcategory":"General Aviation",
            "type":"Transportation"
        }
    ],
    "sg:postcode":"MK42 8BH",
    "sg:province":"Bedfordshire",
    "wof:name":"Anthony Kinns Aviation (Services) Limite",
    "wof:placetype":"venue"
},
  "geometry": {"coordinates":[-0.4915530086,52.1202278137],"type":"Point"}
}