{
  "type": "Feature",
  "properties": {
    "addr:full":"11 Chapelmere Close Sandbach Cheshire CW11 1TB",
    "addr:housenumber":"11",
    "addr:postcode":"cw11 1tb",
    "addr:street":"Chapelmere Close",
    "iso:country":"GB",
    "sg:address":"11 Chapelmere Close",
    "sg:city":"Sandbach",
    "sg:classifiers":[
        {
            "category":"Health Services",
            "subcategory":"Health Practitioner",
            "type":"Services"
        }
    ],
    "sg:postcode":"CW11 1TB",
    "sg:province":"Cheshire",
    "sg:tags":[
        "hypnotherapists"
    ],
    "wof:name":"Hypnotherapy & Counselling",
    "wof:placetype":"venue"
},
  "geometry": {"coordinates":[-2.383399,53.14687],"type":"Point"}
}