{
  "type": "Feature",
  "properties": {
    "addr:full":"40-42 Church Street Grimsby Lincolnshire DN32 7DD",
    "addr:housenumber":"40-42",
    "addr:postcode":"dn32 7dd",
    "addr:street":"Church Street",
    "iso:country":"GB",
    "sg:address":"40-42 Church Street",
    "sg:city":"Grimsby",
    "sg:classifiers":[
        {
            "category":"Autos & Motor Vehicles",
            "subcategory":"Auto Supplies",
            "type":"Retail Goods"
        }
    ],
    "sg:phone":"+44 1472 241242",
    "sg:postcode":"DN32 7DD",
    "sg:province":"Lincolnshire",
    "sg:tags":[
        "tyre"
    ],
    "wof:name":"Grimsby Tyrefit",
    "wof:placetype":"venue"
},
  "geometry": {"coordinates":[-0.073946,53.573509],"type":"Point"}
}