{
  "type": "Feature",
  "properties": {
    "addr:full":"1 Evelyn Rd Wimbledon Greater London SW19 8NU",
    "addr:housenumber":"1",
    "addr:postcode":"sw19 8nu",
    "addr:street":"Evelyn Rd",
    "iso:country":"GB",
    "sg:address":"1 Evelyn Rd",
    "sg:city":"Wimbledon",
    "sg:classifiers":[
        {
            "category":"Health Services",
            "subcategory":"Health Practitioner",
            "type":"Services"
        }
    ],
    "sg:phone":"+44 20 8540 3389",
    "sg:postcode":"SW19 8NU",
    "sg:province":"Greater London",
    "sg:tags":[
        "homoeopathic"
    ],
    "wof:name":"T Marshall-manifold D.sc M.b.ac.a",
    "wof:placetype":"venue"
},
  "geometry": {"coordinates":[-0.193547,51.422649],"type":"Point"}
}