{
  "type": "Feature",
  "properties": {
    "addr:full":"Oldington Lane Kidderminster Staffordshire DY11 7PY",
    "addr:postcode":"dy11 7py",
    "addr:street":"Oldington Lane",
    "iso:country":"GB",
    "sg:address":"Oldington Lane",
    "sg:city":"Kidderminster",
    "sg:classifiers":[
        {
            "category":"Building & Trades",
            "subcategory":"Construction",
            "type":"Services"
        }
    ],
    "sg:phone":"+44 1562 825511",
    "sg:postcode":"DY11 7PY",
    "sg:province":"Staffordshire",
    "sg:tags":[
        "equipment"
    ],
    "wof:name":"W H Price",
    "wof:placetype":"venue"
},
  "geometry": {"coordinates":[-2.2683739662,52.3600845337],"type":"Point"}
}