{
  "type": "Feature",
  "properties": {
    "iso:country":"GB",
    "sg:address":"Crest Road, Handy Cross",
    "sg:city":"High Wycombe",
    "sg:classifiers":[
        {
            "category":"Restaurant",
            "type":"Food & Drink"
        }
    ],
    "sg:phone":"+44 1494 442073",
    "sg:postcode":"HP11 1TL",
    "sg:province":"Buckinghamshire",
    "sg:tags":[
        "oriental"
    ],
    "wof:name":"The Mongolian Barbecue",
    "wof:placetype":"venue"
},
  "geometry": {"coordinates":[-0.7729,51.612518],"type":"Point"}
}