{
  "type": "Feature",
  "properties": {
    "addr:full":"Fairway Garage, Bedwas Rd Caerphilly Caerphilly CF83 3AU",
    "addr:postcode":"cf83 3au",
    "addr:street":"Bedwas Rd",
    "iso:country":"GB",
    "sg:address":"Fairway Garage, Bedwas Rd",
    "sg:city":"Caerphilly",
    "sg:classifiers":[
        {
            "category":"Sports & Exercise",
            "subcategory":"Tennis Court",
            "type":"Entertainment"
        }
    ],
    "sg:phone":"+44 29 2088 2932",
    "sg:postcode":"CF83 3AU",
    "sg:province":"Caerphilly",
    "sg:tags":[
        "breakdown",
        "recovery"
    ],
    "wof:name":"Auto Rescue & Recovery Service",
    "wof:placetype":"venue"
},
  "geometry": {"coordinates":[-3.2177278996,51.576587677],"type":"Point"}
}