{
  "type": "Feature",
  "properties": {
    "iso:country":"GB",
    "sg:address":"20 Shaw Road",
    "sg:city":"Oldham",
    "sg:classifiers":[
        {
            "category":"Building & Trades",
            "subcategory":"Equipment Rental",
            "type":"Services"
        }
    ],
    "sg:phone":"+44 161 626 3554",
    "sg:postcode":"OL1 3LS",
    "sg:province":"Lancashire",
    "sg:tags":[
        "plant",
        "tool",
        "hire",
        "centre"
    ],
    "wof:name":"Banson Tool Hire Ltd",
    "wof:placetype":"venue"
},
  "geometry": {"coordinates":[-2.1035890579,53.5511245728],"type":"Point"}
}