{
  "type": "Feature",
  "properties": {
    "addr:full":"Grains Road, Shaw Oldham Lancashire OL2 8JB",
    "addr:postcode":"ol2 8jb",
    "addr:street":"Grains Road",
    "iso:country":"GB",
    "sg:address":"Grains Road, Shaw",
    "sg:city":"Oldham",
    "sg:classifiers":[
        {
            "category":"Shopping",
            "subcategory":"Computers & Home Electronics",
            "type":"Retail Goods"
        },
        {
            "category":"Professional",
            "subcategory":"Computer Services",
            "type":"Services"
        }
    ],
    "sg:phone":"+44 1706 299902",
    "sg:postcode":"OL2 8JB",
    "sg:province":"Lancashire",
    "sg:tags":[
        "software",
        "sales",
        "system"
    ],
    "wof:name":"Northern Computer Markets",
    "wof:placetype":"venue"
},
  "geometry": {"coordinates":[-2.0935099125,53.5795593262],"type":"Point"}
}