{
  "type": "Feature",
  "properties": {
    "iso:country":"GB",
    "sg:address":"Flat 1 70 Station Road",
    "sg:city":"Petersfield",
    "sg:classifiers":[
        {
            "category":"Organizations",
            "subcategory":"Membership Organization",
            "type":"Services"
        }
    ],
    "sg:phone":"+44 1256 753526",
    "sg:postcode":"GU32 3ET",
    "sg:province":"Hampshire",
    "sg:tags":[
        "club"
    ],
    "wof:name":"70 Station Road Management Ltd.",
    "wof:placetype":"venue"
},
  "geometry": {"coordinates":[-0.935826,51.003796],"type":"Point"}
}