{
  "type": "Feature",
  "properties": {
    "addr:full":"38 Kepwell Road Prudhoe Northumberland NE42 6PD",
    "addr:housenumber":"38",
    "addr:postcode":"ne42 6pd",
    "addr:street":"Kepwell Road",
    "iso:country":"GB",
    "sg:address":"38 Kepwell Road",
    "sg:city":"Prudhoe",
    "sg:classifiers":[
        {
            "category":"Professional",
            "subcategory":"Accounting & Tax Preparation",
            "type":"Services"
        }
    ],
    "sg:postcode":"NE42 6PD",
    "sg:province":"Northumberland",
    "sg:tags":[
        "accountant"
    ],
    "wof:name":"Prudhoe Business Services",
    "wof:placetype":"venue"
},
  "geometry": {"coordinates":[-1.85507,54.962292],"type":"Point"}
}