{
  "type": "Feature",
  "properties": {
    "iso:country":"GB",
    "sg:address":"Town Quay",
    "sg:city":"Southampton",
    "sg:classifiers":[
        {
            "category":"Bars & Pubs",
            "type":"Food & Drink"
        }
    ],
    "sg:postcode":"SO14 2NY",
    "sg:province":"Hampshire",
    "sg:tags":[
        "pubs",
        "inn"
    ],
    "wof:name":"The Platform Tavern",
    "wof:placetype":"venue"
},
  "geometry": {"coordinates":[-1.40616,50.897167],"type":"Point"}
}