{
  "type": "Feature",
  "properties": {
    "addr:full":"3 Kirkland Kendal Cumbria LA9 5AF",
    "addr:housenumber":"3",
    "addr:postcode":"la9 5af",
    "addr:street":"Kirkland Kendal",
    "iso:country":"GB",
    "sg:address":"3 Kirkland",
    "sg:city":"Kendal",
    "sg:classifiers":[
        {
            "category":"Cinema",
            "subcategory":"Movie Rental",
            "type":"Entertainment"
        }
    ],
    "sg:phone":"+44 1539 728356",
    "sg:postcode":"LA9 5AF",
    "sg:province":"Cumbria",
    "sg:tags":[
        "video",
        "library"
    ],
    "wof:name":"KIRKLAND VIDEOS",
    "wof:placetype":"venue"
},
  "geometry": {"coordinates":[-2.746546,54.323177],"type":"Point"}
}