{
  "type": "Feature",
  "properties": {
    "iso:country":"GB",
    "sg:address":"608 Chepstow Rd",
    "sg:city":"Newport",
    "sg:classifiers":[
        {
            "category":"Place Of Worship",
            "type":"Public Place"
        }
    ],
    "sg:phone":"+44 1633 272066",
    "sg:postcode":"NP9 9BZ",
    "sg:province":"East Riding of Yorkshire",
    "wof:name":"Bishpool Methodist Church",
    "wof:placetype":"venue"
},
  "geometry": {"coordinates":[-2.9484739304,51.5922775269],"type":"Point"}
}