{
  "type": "Feature",
  "properties": {
    "iso:country":"GB",
    "sg:address":"52 Frances Road",
    "sg:city":"Bournemouth",
    "sg:classifiers":[
        {
            "category":"Travel",
            "subcategory":"Hotels & Motels",
            "type":"Entertainment"
        }
    ],
    "sg:phone":"+44 1202 553884",
    "sg:postcode":"BH1 3SA",
    "sg:province":"Dorset",
    "wof:name":"Amarillo Hotel",
    "wof:placetype":"venue"
},
  "geometry": {"coordinates":[-1.857506,50.725388],"type":"Point"}
}