{
  "type": "Feature",
  "properties": {
    "iso:country":"GB",
    "sg:address":"1 Church Lane",
    "sg:city":"Wallingford",
    "sg:classifiers":[
        {
            "category":"Building & Trades",
            "subcategory":"Construction",
            "type":"Services"
        }
    ],
    "sg:phone":"+44 1491 834975",
    "sg:postcode":"OX10 0DX",
    "sg:province":"Oxfordshire",
    "sg:tags":[
        "builder"
    ],
    "wof:name":"Beechcroft Construction Ltd.",
    "wof:placetype":"venue"
},
  "geometry": {"coordinates":[-1.125403,51.599537],"type":"Point"}
}