{
  "type": "Feature",
  "properties": {
    "addr:full":"35 Wood Street Ashby-de-la-zouch Derbyshire LE65 1EL",
    "addr:housenumber":"35",
    "addr:postcode":"le65 1el",
    "addr:street":"Wood Street",
    "iso:country":"GB",
    "sg:address":"35 Wood Street",
    "sg:city":"Ashby-de-la-zouch",
    "sg:classifiers":[
        {
            "category":"Travel",
            "subcategory":"Hotels & Motels",
            "type":"Entertainment"
        }
    ],
    "sg:phone":"+44 1530 415176",
    "sg:postcode":"LE65 1EL",
    "sg:province":"Derbyshire",
    "wof:name":"Ashby Court Hotel",
    "wof:placetype":"venue"
},
  "geometry": {"coordinates":[-1.465446949,52.7489128113],"type":"Point"}
}