{
  "type": "Feature",
  "properties": {
    "iso:country":"GB",
    "sg:address":", Mordiford",
    "sg:city":"Hereford",
    "sg:classifiers":[
        {
            "category":"Government",
            "subcategory":"Post Office",
            "type":"Public Place"
        }
    ],
    "sg:phone":"+44 1432 870235",
    "sg:postcode":"HR1 4LN",
    "sg:province":"Herefordshire",
    "wof:name":"Mordiford P.O & Stores",
    "wof:placetype":"venue"
},
  "geometry": {"coordinates":[-2.626074,52.033054],"type":"Point"}
}