{
  "type": "Feature",
  "properties": {
    "addr:full":"Brae Shetland Shetland Islands ZE2 9QP",
    "addr:postcode":"ze2 9qp",
    "addr:street":"Brae Shetland Shetland",
    "iso:country":"GB",
    "sg:address":"Brae",
    "sg:city":"Shetland",
    "sg:classifiers":[
        {
            "category":"Utilities",
            "subcategory":"Fuel Oil & Lpg",
            "type":"Services"
        }
    ],
    "sg:phone":"+44 1806 242208",
    "sg:postcode":"ZE2 9QP",
    "sg:province":"Shetland Islands",
    "sg:tags":[
        "distributor"
    ],
    "wof:name":"Air B P Ltd.",
    "wof:placetype":"venue"
},
  "geometry": {"coordinates":[-1.3174799681,60.4206199646],"type":"Point"}
}