{
  "type": "Feature",
  "properties": {
    "addr:full":"Waterloo Square, Alfriston Polegate East Sussex BN26 5UE",
    "addr:postcode":"bn26 5ue",
    "addr:street":"Waterloo Square",
    "iso:country":"GB",
    "sg:address":"Waterloo Square, Alfriston",
    "sg:city":"Polegate",
    "sg:classifiers":[
        {
            "category":"Bars & Pubs",
            "type":"Food & Drink"
        }
    ],
    "sg:phone":"+44 1323 870241",
    "sg:postcode":"BN26 5UE",
    "sg:province":"East Sussex",
    "sg:tags":[
        "pubs",
        "inn"
    ],
    "wof:name":"Ye Olde Smugglers Inn",
    "wof:placetype":"venue"
},
  "geometry": {"coordinates":[0.15672,50.808384],"type":"Point"}
}