{
  "type": "Feature",
  "properties": {
    "iso:country":"GB",
    "sg:address":"469 Blackburn Road",
    "sg:city":"Bolton",
    "sg:classifiers":[
        {
            "category":"Shopping",
            "subcategory":"Thrift Store",
            "type":"Retail Goods"
        }
    ],
    "sg:phone":"+44 1204 303219",
    "sg:postcode":"BL1 8NN",
    "sg:province":"Lancashire",
    "sg:tags":[
        "shop",
        "charity"
    ],
    "sg:website":"http://www.oxfam.org.uk",
    "wof:name":"Oxfam",
    "wof:placetype":"venue"
},
  "geometry": {"coordinates":[-2.433074,53.599178],"type":"Point"}
}