{
  "type": "Feature",
  "properties": {
    "iso:country":"GB",
    "sg:address":"180-182 Rush Green Road",
    "sg:city":"Romford",
    "sg:classifiers":[
        {
            "category":"Home & Garden",
            "subcategory":"Building Materials",
            "type":"Retail Goods"
        }
    ],
    "sg:postcode":"RM7 0JU",
    "sg:province":"Essex",
    "sg:tags":[
        "plaster",
        "ware"
    ],
    "wof:name":"Newtons Unique Plastercraft",
    "wof:placetype":"venue"
},
  "geometry": {"coordinates":[0.159864,51.562752],"type":"Point"}
}