{
  "type": "Feature",
  "properties": {
    "addr:full":"The Maltings, Charlton Road Shepton Mallet Somerset BA4 5QE",
    "addr:postcode":"ba4 5qe",
    "addr:street":"The;Charlton Road",
    "iso:country":"GB",
    "sg:address":"The Maltings, Charlton Road",
    "sg:city":"Shepton Mallet",
    "sg:classifiers":[
        {
            "category":"Professional",
            "subcategory":"Computer Services",
            "type":"Services"
        }
    ],
    "sg:phone":"+44 1749 333300",
    "sg:postcode":"BA4 5QE",
    "sg:province":"Somerset",
    "sg:tags":[
        "information"
    ],
    "wof:name":"U K Online Ltd.",
    "wof:placetype":"venue"
},
  "geometry": {"coordinates":[-2.546778,51.189732],"type":"Point"}
}