{
  "type": "Feature",
  "properties": {
    "addr:full":"Gate House, 5 Chapel Place, Rivington Street London Greater London EC2A 3DQ",
    "addr:housenumber":"5",
    "addr:postcode":"ec2a 3dq",
    "addr:street":"Gate;Chapel Place Rivington Street",
    "iso:country":"GB",
    "sg:address":"Gate House, 5 Chapel Place, Rivington Street",
    "sg:city":"London",
    "sg:classifiers":[
        {
            "category":"Shopping",
            "subcategory":"Stationery & Office Supplies",
            "type":"Retail Goods"
        }
    ],
    "sg:phone":"+44 20 7613 7400",
    "sg:postcode":"EC2A 3DQ",
    "sg:province":"Greater London",
    "sg:tags":[
        "equipment"
    ],
    "wof:name":"Charterhouse Voice & Data Plc",
    "wof:placetype":"venue"
},
  "geometry": {"coordinates":[-0.08221,51.52631],"type":"Point"}
}