{
  "type": "Feature",
  "properties": {
    "addr:full":"The Arndale Centre, Wandsworth London Greater London SW18 4TF",
    "addr:postcode":"sw18 4tf",
    "iso:country":"GB",
    "sg:address":"The Arndale Centre, Wandsworth",
    "sg:city":"London",
    "sg:classifiers":[
        {
            "category":"Shopping",
            "subcategory":"Clothing, Apparel, & Fashions",
            "type":"Retail Goods"
        }
    ],
    "sg:phone":"+44 20 8874 1375",
    "sg:postcode":"SW18 4TF",
    "sg:province":"Greater London",
    "sg:tags":[
        "shop"
    ],
    "wof:name":"Mark One",
    "wof:placetype":"venue"
},
  "geometry": {"coordinates":[-0.1944790035,51.4568710327],"type":"Point"}
}