{
  "type": "Feature",
  "properties": {
    "iso:country":"GB",
    "sg:address":"Sutton Lodge, Main St, Wick",
    "sg:city":"Pershore",
    "sg:classifiers":[
        {
            "category":"Building & Trades",
            "subcategory":"Landscaping Services",
            "type":"Services"
        }
    ],
    "sg:phone":"+44 1386 561174",
    "sg:postcode":"WR10 3NU",
    "sg:province":"Worcestershire",
    "sg:tags":[
        "landscape",
        "contractor"
    ],
    "wof:name":"Mark Dowdeswell Landscapes",
    "wof:placetype":"venue"
},
  "geometry": {"coordinates":[-2.0581989288,52.1040000916],"type":"Point"}
}