{
  "type": "Feature",
  "properties": {
    "addr:full":"4 Church Street Barnoldswick Lancashire BB18 5UT",
    "addr:housenumber":"4",
    "addr:postcode":"bb18 5ut",
    "addr:street":"Church Street",
    "iso:country":"GB",
    "sg:address":"4 Church Street",
    "sg:city":"Barnoldswick",
    "sg:classifiers":[
        {
            "category":"Shopping",
            "subcategory":"Department Store",
            "type":"Retail Goods"
        },
        {
            "category":"Shopping",
            "subcategory":"Music",
            "type":"Retail Goods"
        }
    ],
    "sg:postcode":"BB18 5UT",
    "sg:province":"Lancashire",
    "sg:tags":[
        "dvd",
        "tape",
        "vinyl",
        "cd"
    ],
    "wof:name":"CLARE BROWN",
    "wof:placetype":"venue"
},
  "geometry": {"coordinates":[-2.1887719631,53.9160461426],"type":"Point"}
}