{
  "type": "Feature",
  "properties": {
    "addr:full":"Suite 202 Bradford Court, Bradford Street Birmingham West Midlands B12 0NF",
    "addr:housenumber":"suite 202",
    "addr:postcode":"b12 0nf",
    "addr:street":"Bradford Court Bradford Street",
    "iso:country":"GB",
    "sg:address":"Suite 202 Bradford Court, Bradford Street",
    "sg:city":"Birmingham",
    "sg:classifiers":[
        {
            "category":"Professional",
            "subcategory":"Advertising",
            "type":"Services"
        }
    ],
    "sg:phone":"+44 121 244 2420",
    "sg:postcode":"B12 0NF",
    "sg:province":"West Midlands",
    "sg:tags":[
        "agency"
    ],
    "wof:name":"Jewel Communications Ltd.",
    "wof:placetype":"venue"
},
  "geometry": {"coordinates":[-1.880164,52.471184],"type":"Point"}
}