{
  "type": "Feature",
  "properties": {
    "addr:full":"11 Bincote Rd Enfield Greater London EN2 7RD",
    "addr:housenumber":"11",
    "addr:postcode":"en2 7rd",
    "addr:street":"Bincote Rd",
    "iso:country":"GB",
    "sg:address":"11 Bincote Rd",
    "sg:city":"Enfield",
    "sg:classifiers":[
        {
            "category":"Health Services",
            "subcategory":"Doctor",
            "type":"Services"
        }
    ],
    "sg:phone":"+44 20 8363 0585",
    "sg:postcode":"EN2 7RD",
    "sg:province":"Greater London",
    "sg:tags":[
        "practitioners"
    ],
    "wof:name":"Dissanayake, H R M",
    "wof:placetype":"venue"
},
  "geometry": {"coordinates":[-0.1102970019,51.6539230347],"type":"Point"}
}