{
  "type": "Feature",
  "properties": {
    "addr:full":"Netherley Road, Tarbock Grn Prescot Cheshire L35 6QE",
    "addr:postcode":"l35 6qe",
    "addr:street":"Netherley Road",
    "iso:country":"GB",
    "sg:address":"Netherley Road, Tarbock Grn",
    "sg:city":"Prescot",
    "sg:classifiers":[
        {
            "category":"Home & Garden",
            "subcategory":"Garden Supply",
            "type":"Retail Goods"
        }
    ],
    "sg:phone":"+44 151 487 8147",
    "sg:postcode":"L35 6QE",
    "sg:province":"Cheshire",
    "sg:tags":[
        "nursery",
        "centre"
    ],
    "wof:name":"Martin's Garden Centre",
    "wof:placetype":"venue"
},
  "geometry": {"coordinates":[-2.75855,53.405918],"type":"Point"}
}