{
  "type": "Feature",
  "properties": {
    "addr:full":"60 Quarry Street Guildford Surrey GU1 3UB",
    "addr:housenumber":"60",
    "addr:postcode":"gu1 3ub",
    "addr:street":"Quarry Street",
    "iso:country":"GB",
    "sg:address":"60 Quarry Street",
    "sg:city":"Guildford",
    "sg:classifiers":[
        {
            "category":"Professional",
            "subcategory":"Lawyer & Legal Services",
            "type":"Services"
        }
    ],
    "sg:phone":"+44 1483 576507",
    "sg:postcode":"GU1 3UB",
    "sg:province":"Surrey",
    "sg:tags":[
        "solicitor"
    ],
    "wof:name":"Perkins & Harris",
    "wof:placetype":"venue"
},
  "geometry": {"coordinates":[-0.574061,51.234634],"type":"Point"}
}