{
  "type": "Feature",
  "properties": {
    "addr:full":"128 Trimdon Avenue Middlesbrough North Yorkshire TS5 8SB",
    "addr:housenumber":"128",
    "addr:postcode":"ts5 8sb",
    "addr:street":"Trimdon Avenue",
    "iso:country":"GB",
    "sg:address":"128 Trimdon Avenue",
    "sg:city":"Middlesbrough",
    "sg:classifiers":[
        {
            "category":"Food & Beverages",
            "subcategory":"Supermarket",
            "type":"Retail Goods"
        }
    ],
    "sg:phone":"+44 1642 850107",
    "sg:postcode":"TS5 8SB",
    "sg:province":"North Yorkshire",
    "wof:name":"Spar",
    "wof:placetype":"venue"
},
  "geometry": {"coordinates":[-1.2622499466,54.5378303528],"type":"Point"}
}