{
  "type": "Feature",
  "properties": {
    "addr:full":"20 Church Hill Loughton Essex IG10 1LA",
    "addr:housenumber":"20",
    "addr:postcode":"ig10 1la",
    "addr:street":"Church Hill",
    "iso:country":"GB",
    "sg:address":"20 Church Hill",
    "sg:city":"Loughton",
    "sg:classifiers":[
        {
            "category":"Retail",
            "subcategory":"Photofinishing",
            "type":"Services"
        }
    ],
    "sg:phone":"+44 20 8508 8585",
    "sg:postcode":"IG10 1LA",
    "sg:province":"Essex",
    "sg:tags":[
        "photographic",
        "processor"
    ],
    "wof:name":"Lindrum Photography",
    "wof:placetype":"venue"
},
  "geometry": {"coordinates":[0.0593350008,51.651424408],"type":"Point"}
}