{
  "type": "Feature",
  "properties": {
    "addr:full":"Furness House, 71-73 Hoghton Street Southport Lancashire PR9 0PR",
    "addr:housenumber":"71-73",
    "addr:postcode":"pr9 0pr",
    "addr:street":"Hoghton Street",
    "iso:country":"GB",
    "sg:address":"Furness House, 71-73 Hoghton Street",
    "sg:city":"Southport",
    "sg:classifiers":[
        {
            "category":"Professional",
            "subcategory":"Accounting & Tax Preparation",
            "type":"Services"
        }
    ],
    "sg:phone":"+44 1704 535687",
    "sg:postcode":"PR9 0PR",
    "sg:province":"Lancashire",
    "sg:tags":[
        "accountant"
    ],
    "wof:name":"Jones Harris",
    "wof:placetype":"venue"
},
  "geometry": {"coordinates":[-2.998467,53.650105],"type":"Point"}
}