{
  "type": "Feature",
  "properties": {
    "addr:full":"12 The Grange London Greater London SE1 3AG",
    "addr:housenumber":"12",
    "addr:postcode":"se1 3ag",
    "addr:street":"The Grange",
    "iso:country":"GB",
    "sg:address":"12 The Grange",
    "sg:city":"London",
    "sg:classifiers":[
        {
            "category":"Social Services",
            "subcategory":"Retirement Home",
            "type":"Services"
        },
        {
            "category":"Government",
            "subcategory":"Office",
            "type":"Public Place"
        }
    ],
    "sg:phone":"+44 20 7252 3762",
    "sg:postcode":"SE1 3AG",
    "sg:province":"Greater London",
    "sg:tags":[
        "residential",
        "local",
        "care"
    ],
    "wof:name":"Gibson House Residential Care Home",
    "wof:placetype":"venue"
},
  "geometry": {"coordinates":[-0.0767930001,51.4962081909],"type":"Point"}
}