{
  "type": "Feature",
  "properties": {
    "addr:full":"30 Hunters Chase, Throapham, Dinnington Sheffield South Yorkshire S25 2TQ",
    "addr:housenumber":"30",
    "addr:postcode":"s25 2tq",
    "addr:street":"Hunters Chase Throapham Dinnington",
    "iso:country":"GB",
    "sg:address":"30 Hunters Chase, Throapham, Dinnington",
    "sg:city":"Sheffield",
    "sg:classifiers":[
        {
            "category":"Professional",
            "subcategory":"Detective & Security Services",
            "type":"Services"
        }
    ],
    "sg:phone":"+44 1909 560044",
    "sg:postcode":"S25 2TQ",
    "sg:province":"South Yorkshire",
    "sg:tags":[
        "agency"
    ],
    "wof:name":"Pace",
    "wof:placetype":"venue"
},
  "geometry": {"coordinates":[-1.205813,53.377834],"type":"Point"}
}