{
  "type": "Feature",
  "properties": {
    "iso:country":"GB",
    "sg:address":"131 Blackburn Street, Radcliffe",
    "sg:city":"Manchester",
    "sg:classifiers":[
        {
            "category":"Banks & Credit Unions",
            "subcategory":"Bank",
            "type":"Services"
        }
    ],
    "sg:phone":"+44 161 723 2980",
    "sg:postcode":"M26 9WQ",
    "sg:province":"Greater Manchester",
    "wof:name":"The Royal Bank of Scotland Plc",
    "wof:placetype":"venue"
},
  "geometry": {"coordinates":[-2.3396100998,53.5605392456],"type":"Point"}
}