{
  "type": "Feature",
  "properties": {
    "addr:full":"Unit 38 Viking Precinct Jarrow Tyne and Wear NE32 3LH",
    "addr:housenumber":"unit 38",
    "addr:postcode":"ne32 3lh",
    "addr:street":"Viking Precinct",
    "iso:country":"GB",
    "sg:address":"Unit 38 Viking Precinct",
    "sg:city":"Jarrow",
    "sg:classifiers":[
        {
            "category":"Shopping",
            "subcategory":"Shoes",
            "type":"Retail Goods"
        }
    ],
    "sg:phone":"+44 191 483 3919",
    "sg:postcode":"NE32 3LH",
    "sg:province":"Tyne and Wear",
    "sg:tags":[
        "shop"
    ],
    "wof:name":"Davids Shoes",
    "wof:placetype":"venue"
},
  "geometry": {"coordinates":[-1.46885,54.97662],"type":"Point"}
}