{
  "type": "Feature",
  "properties": {
    "iso:country":"GB",
    "sg:address":"Church Street",
    "sg:city":"Hinckley",
    "sg:classifiers":[
        {
            "category":"Professional",
            "subcategory":"Lawyer & Legal Services",
            "type":"Services"
        }
    ],
    "sg:phone":"+44 1455 610747",
    "sg:postcode":"LE10 1DN",
    "sg:province":"Leicestershire",
    "sg:tags":[
        "solicitor"
    ],
    "wof:name":"Thomas Flavell & Sons",
    "wof:placetype":"venue"
},
  "geometry": {"coordinates":[-1.372754,52.542439],"type":"Point"}
}