{
  "type": "Feature",
  "properties": {
    "iso:country":"GB",
    "sg:address":"Springboard Centre",
    "sg:city":"Coalville",
    "sg:classifiers":[
        {
            "category":"Home & Garden",
            "subcategory":"Home Furnishings",
            "type":"Retail Goods"
        }
    ],
    "sg:phone":"+44 1530 813662",
    "sg:postcode":"LE67 3DW",
    "sg:province":"Leicestershire",
    "sg:tags":[
        "mantelpiece",
        "fireplace"
    ],
    "wof:name":"Charnwood Fireplaces",
    "wof:placetype":"venue"
},
  "geometry": {"coordinates":[-1.3723059893,52.7187843323],"type":"Point"}
}