{
  "type": "Feature",
  "properties": {
    "addr:full":"20 Breck Road, Anfield Liverpool Merseyside L4 2RB",
    "addr:housenumber":"20",
    "addr:postcode":"l4 2rb",
    "addr:street":"Breck Road Anfield",
    "iso:country":"GB",
    "sg:address":"20 Breck Road, Anfield",
    "sg:city":"Liverpool",
    "sg:classifiers":[
        {
            "category":"Bars & Pubs",
            "type":"Food & Drink"
        },
        {
            "category":"Community Center",
            "subcategory":"Social",
            "type":"Public Place"
        }
    ],
    "sg:phone":"+44 151 263 2418",
    "sg:postcode":"L4 2RB",
    "sg:province":"Merseyside",
    "sg:tags":[
        "pubs",
        "house",
        "inn",
        "activity"
    ],
    "wof:name":"The Cabbage Hall",
    "wof:placetype":"venue"
},
  "geometry": {"coordinates":[-2.953179,53.425434],"type":"Point"}
}