{
  "type": "Feature",
  "properties": {
    "addr:full":"Loraine Street Liverpool Merseyside L5 4RX",
    "addr:postcode":"l5 4rx",
    "addr:street":"Loraine Street",
    "iso:country":"GB",
    "sg:address":"Loraine Street",
    "sg:city":"Liverpool",
    "sg:classifiers":[
        {
            "category":"Education",
            "subcategory":"University",
            "type":"Public Place"
        }
    ],
    "sg:postcode":"L5 4RX",
    "sg:province":"Merseyside",
    "sg:tags":[
        "adult"
    ],
    "wof:name":"Liverpool City Council",
    "wof:placetype":"venue"
},
  "geometry": {"coordinates":[-2.965229,53.425652],"type":"Point"}
}