{
  "type": "Feature",
  "properties": {
    "addr:full":"Newchurch, Kinnersley Hereford Herefordshire HR3 6QQ",
    "addr:postcode":"hr3 6qq",
    "iso:country":"GB",
    "sg:address":"Newchurch, Kinnersley",
    "sg:city":"Hereford",
    "sg:classifiers":[
        {
            "category":"Farming",
            "subcategory":"Livestock Farm",
            "type":"Manufacturing & Wholesale Goods"
        }
    ],
    "sg:phone":"+44 1544 327788",
    "sg:postcode":"HR3 6QQ",
    "sg:province":"Herefordshire",
    "sg:tags":[
        "others"
    ],
    "wof:name":"Newchurch Properties Ltd.",
    "wof:placetype":"venue"
},
  "geometry": {"coordinates":[-2.961525,52.139057],"type":"Point"}
}