{
  "type": "Feature",
  "properties": {
    "addr:full":"19 Balliol Rd Ladbroke Grove Greater London W10 6LX",
    "addr:housenumber":"19",
    "addr:postcode":"w10 6lx",
    "addr:street":"Balliol Rd",
    "iso:country":"GB",
    "sg:address":"19 Balliol Rd",
    "sg:city":"Ladbroke Grove",
    "sg:classifiers":[
        {
            "category":"Shopping",
            "subcategory":"Books",
            "type":"Retail Goods"
        },
        {
            "category":"Wholesale",
            "subcategory":"Books, Periodicals, & Newspapers",
            "type":"Manufacturing & Wholesale Goods"
        }
    ],
    "sg:phone":"+44 20 8968 9274",
    "sg:postcode":"W10 6LX",
    "sg:province":"Greater London",
    "sg:tags":[
        "publisher"
    ],
    "wof:name":"Otterquill Books",
    "wof:placetype":"venue"
},
  "geometry": {"coordinates":[-0.220963,51.517044],"type":"Point"}
}