{
  "type": "Feature",
  "properties": {
    "addr:full":"24 Cleveland Street Wolverhampton West Midlands WV1 3HT",
    "addr:housenumber":"24",
    "addr:postcode":"wv1 3ht",
    "addr:street":"Cleveland Street",
    "iso:country":"GB",
    "sg:address":"24 Cleveland Street",
    "sg:city":"Wolverhampton",
    "sg:classifiers":[
        {
            "category":"Shopping",
            "subcategory":"Crafts & Fabrics",
            "type":"Retail Goods"
        }
    ],
    "sg:phone":"+44 1902 420380",
    "sg:postcode":"WV1 3HT",
    "sg:province":"West Midlands",
    "sg:tags":[
        "shop"
    ],
    "wof:name":"A H Stores",
    "wof:placetype":"venue"
},
  "geometry": {"coordinates":[-2.1269240379,52.5828781128],"type":"Point"}
}