{
  "type": "Feature",
  "properties": {
    "iso:country":"GB",
    "sg:address":"1 Gladstone Terr",
    "sg:city":"Ripon",
    "sg:classifiers":[
        {
            "category":"Home & Garden",
            "subcategory":"Household Appliances",
            "type":"Retail Goods"
        }
    ],
    "sg:phone":"+44 1765 603936",
    "sg:postcode":"HG4 1PR",
    "sg:province":"North Yorkshire",
    "sg:tags":[
        "electrical"
    ],
    "wof:name":"T J Brockwell",
    "wof:placetype":"venue"
},
  "geometry": {"coordinates":[-1.5227110386,54.1322593689],"type":"Point"}
}