{
  "type": "Feature",
  "properties": {
    "addr:full":"87 Brackens La, Alvaston Derby Derbyshire DE240AN",
    "addr:housenumber":"87",
    "addr:postcode":"de240an",
    "addr:street":"Brackens La Alvaston",
    "iso:country":"GB",
    "sg:address":"87 Brackens La, Alvaston",
    "sg:city":"Derby",
    "sg:classifiers":[
        {
            "category":"Farming",
            "subcategory":"Fish & Marine Products",
            "type":"Manufacturing & Wholesale Goods"
        }
    ],
    "sg:postcode":"DE240AN",
    "sg:province":"Derbyshire",
    "sg:tags":[
        "fishmonger"
    ],
    "wof:name":"Coates,Maurice,",
    "wof:placetype":"venue"
},
  "geometry": {"coordinates":[-1.4421750307,52.8899497986],"type":"Point"}
}