{
  "type": "Feature",
  "properties": {
    "addr:full":"87 Telegraph Road, Heswall Wirral Merseyside CH60 0AU",
    "addr:housenumber":"87",
    "addr:postcode":"ch60 0au",
    "addr:street":"Telegraph Road",
    "iso:country":"GB",
    "sg:address":"87 Telegraph Road, Heswall",
    "sg:city":"Wirral",
    "sg:classifiers":[
        {
            "category":"Professional",
            "subcategory":"Lawyer & Legal Services",
            "type":"Services"
        }
    ],
    "sg:phone":"+44 151 342 1831",
    "sg:postcode":"CH60 0AU",
    "sg:province":"Merseyside",
    "sg:tags":[
        "solicitor"
    ],
    "wof:name":"Guy Williams Quiggin",
    "wof:placetype":"venue"
},
  "geometry": {"coordinates":[-3.0955040455,53.3267860413],"type":"Point"}
}