{
  "type": "Feature",
  "properties": {
    "iso:country":"GB",
    "sg:address":"Unit 8 Willoughby Place, Millfield",
    "sg:city":"Chard",
    "sg:classifiers":[
        {
            "category":"Building & Trades",
            "subcategory":"Construction",
            "type":"Services"
        }
    ],
    "sg:phone":"+44 1460 61666",
    "sg:postcode":"TA20 2BB",
    "sg:province":"Devon",
    "sg:tags":[
        "glazier"
    ],
    "wof:name":"Adams Glass",
    "wof:placetype":"venue"
},
  "geometry": {"coordinates":[-2.9550440311,50.8406715393],"type":"Point"}
}