{
  "type": "Feature",
  "properties": {
    "addr:full":", Belmont Hereford Herefordshire HR2 9RY",
    "addr:postcode":"hr2 9ry",
    "iso:country":"GB",
    "sg:address":", Belmont",
    "sg:city":"Hereford",
    "sg:classifiers":[
        {
            "category":"Travel",
            "subcategory":"Hotels & Motels",
            "type":"Entertainment"
        }
    ],
    "sg:phone":"+44 1432 277475",
    "sg:postcode":"HR2 9RY",
    "sg:province":"Herefordshire",
    "sg:tags":[
        "house",
        "guest"
    ],
    "wof:name":"Hedley Lodge",
    "wof:placetype":"venue"
},
  "geometry": {"coordinates":[-2.754524,52.037254],"type":"Point"}
}