{
  "type": "Feature",
  "properties": {
    "addr:full":"19 Common Rd Bristol City of Bristol BS15 3LL",
    "addr:housenumber":"19",
    "addr:postcode":"bs15 3ll",
    "addr:street":"Common Rd",
    "iso:country":"GB",
    "sg:address":"19 Common Rd",
    "sg:city":"Bristol",
    "sg:classifiers":[
        {
            "category":"Professional",
            "type":"Services"
        }
    ],
    "sg:postcode":"BS15 3LL",
    "sg:province":"City of Bristol",
    "sg:tags":[
        "exhibition"
    ],
    "wof:name":"Harvey Exhibitions & Scenery Contractors",
    "wof:placetype":"venue"
},
  "geometry": {"coordinates":[-2.5211908817,51.4382133484],"type":"Point"}
}