{
  "type": "Feature",
  "properties": {
    "addr:full":"Bridge Street, Troedyrhiw Merthyr Tydfil Caerphilly CF48 4JU",
    "addr:postcode":"cf48 4ju",
    "addr:street":"Bridge Street",
    "iso:country":"GB",
    "sg:address":"Bridge Street, Troedyrhiw",
    "sg:city":"Merthyr Tydfil",
    "sg:classifiers":[
        {
            "category":"Organizations",
            "subcategory":"Community Association",
            "type":"Services"
        },
        {
            "category":"Organizations",
            "subcategory":"Membership Organization",
            "type":"Services"
        }
    ],
    "sg:phone":"+44 1443 690205",
    "sg:postcode":"CF48 4JU",
    "sg:province":"Caerphilly",
    "sg:tags":[
        "club",
        "social"
    ],
    "wof:name":"Ex Servicemen's Club",
    "wof:placetype":"venue"
},
  "geometry": {"coordinates":[-3.345201,51.712646],"type":"Point"}
}