{
  "type": "Feature",
  "properties": {
    "addr:full":"283 Coatsworth Road, Shipcote Gateshead Tyne and Wear NE8 4LJ",
    "addr:housenumber":"283",
    "addr:postcode":"ne8 4lj",
    "addr:street":"Coatsworth Road",
    "iso:country":"GB",
    "sg:address":"283 Coatsworth Road, Shipcote",
    "sg:city":"Gateshead",
    "sg:classifiers":[
        {
            "category":"Shopping",
            "subcategory":"News",
            "type":"Retail Goods"
        }
    ],
    "sg:phone":"+44 191 420 0284",
    "sg:postcode":"NE8 4LJ",
    "sg:province":"Tyne and Wear",
    "sg:tags":[
        "newsagent"
    ],
    "wof:name":"M W Newsagents",
    "wof:placetype":"venue"
},
  "geometry": {"coordinates":[-1.6053140163,54.9509391785],"type":"Point"}
}