{
  "type": "Feature",
  "properties": {
    "addr:full":"Leicesters Lane, Higher Kinnerton Chester Cheshire CH4 9BQ",
    "addr:postcode":"ch4 9bq",
    "addr:street":"Leicesters Lane",
    "iso:country":"GB",
    "sg:address":"Leicesters Lane, Higher Kinnerton",
    "sg:city":"Chester",
    "sg:classifiers":[
        {
            "category":"Farming",
            "subcategory":"Livestock Farm",
            "type":"Manufacturing & Wholesale Goods"
        },
        {
            "category":"Farming",
            "subcategory":"Farm",
            "type":"Manufacturing & Wholesale Goods"
        }
    ],
    "sg:postcode":"CH4 9BQ",
    "sg:province":"Cheshire",
    "sg:tags":[
        "mixed",
        "crop",
        "others"
    ],
    "wof:name":"Peter Curtis",
    "wof:placetype":"venue"
},
  "geometry": {"coordinates":[-3.0059270859,53.1551589966],"type":"Point"}
}