{
  "type": "Feature",
  "properties": {
    "iso:country":"GB",
    "sg:address":"Floor 2 Boscobel House, Welsh Street",
    "sg:city":"Chepstow",
    "sg:classifiers":[
        {
            "category":"Banks & Credit Unions",
            "subcategory":"Bank",
            "type":"Services"
        }
    ],
    "sg:phone":"+44 1291 626226",
    "sg:postcode":"NP16 5JB",
    "sg:province":"Gloucestershire",
    "sg:tags":[
        "broker",
        "mortgage"
    ],
    "wof:name":"J F S Home Loans",
    "wof:placetype":"venue"
},
  "geometry": {"coordinates":[-2.677194,51.641113],"type":"Point"}
}