{
  "type": "Feature",
  "properties": {
    "iso:country":"GB",
    "sg:address":"47 Stamford Rd",
    "sg:city":"Southport",
    "sg:classifiers":[
        {
            "category":"Manufacturing",
            "subcategory":"Metals",
            "type":"Manufacturing & Wholesale Goods"
        }
    ],
    "sg:phone":"+44 1704 563100",
    "sg:postcode":"PR8 4ET",
    "sg:province":"Lancashire",
    "sg:tags":[
        "work",
        "sheet"
    ],
    "wof:name":"Ryan Sheet Metal Fabrication & Welding",
    "wof:placetype":"venue"
},
  "geometry": {"coordinates":[-3.004891,53.627926],"type":"Point"}
}