{
  "type": "Feature",
  "properties": {
    "addr:full":"379 Hessle Rd Hull East Riding of Yorkshire HU3 4EJ",
    "addr:housenumber":"379",
    "addr:postcode":"hu3 4ej",
    "addr:street":"Hessle Rd",
    "iso:country":"GB",
    "sg:address":"379 Hessle Rd",
    "sg:city":"Hull",
    "sg:classifiers":[
        {
            "category":"Home & Garden",
            "subcategory":"Home Furnishings",
            "type":"Retail Goods"
        }
    ],
    "sg:postcode":"HU3 4EJ",
    "sg:province":"East Riding of Yorkshire",
    "sg:tags":[
        "furnishers",
        "planner",
        "kitchen"
    ],
    "wof:name":"Collins,Steven,",
    "wof:placetype":"venue"
},
  "geometry": {"coordinates":[-0.369486,53.734276],"type":"Point"}
}