{
  "type": "Feature",
  "properties": {
    "addr:full":"25a Downs Side, Cheam Sutton Surrey SM2 7EH",
    "addr:housenumber":"25a",
    "addr:postcode":"sm2 7eh",
    "addr:street":"Downs Side",
    "iso:country":"GB",
    "sg:address":"25a Downs Side, Cheam",
    "sg:city":"Sutton",
    "sg:classifiers":[
        {
            "category":"Building & Trades",
            "subcategory":"Construction",
            "type":"Services"
        }
    ],
    "sg:postcode":"SM2 7EH",
    "sg:province":"Surrey",
    "sg:tags":[
        "joiner",
        "carpenter"
    ],
    "wof:name":"D J Murton & Associates",
    "wof:placetype":"venue"
},
  "geometry": {"coordinates":[-0.2087959945,51.3396377563],"type":"Point"}
}