{
  "type": "Feature",
  "properties": {
    "addr:full":"Unit 1 Portrack Grange Close, Portrack Industrial Estate Stockton-on-tees Durham TS18 2PU",
    "addr:housenumber":"unit 1",
    "addr:postcode":"ts18 2pu",
    "addr:street":"Portrack Grange Close;Industrial Estate",
    "iso:country":"GB",
    "sg:address":"Unit 1 Portrack Grange Close, Portrack Industrial Estate",
    "sg:city":"Stockton-on-tees",
    "sg:classifiers":[
        {
            "category":"Home & Garden",
            "subcategory":"Household Appliances",
            "type":"Retail Goods"
        }
    ],
    "sg:phone":"+44 1642 615515",
    "sg:postcode":"TS18 2PU",
    "sg:province":"Durham",
    "sg:tags":[
        "spare",
        "heating"
    ],
    "wof:name":"Controls Center",
    "wof:placetype":"venue"
},
  "geometry": {"coordinates":[-1.2796260118,54.5713806152],"type":"Point"}
}