{
  "type": "Feature",
  "properties": {
    "addr:full":"84 Cadewell Lane Torquay Devon TQ2 7HP",
    "addr:housenumber":"84",
    "addr:postcode":"tq2 7hp",
    "addr:street":"Cadewell Lane",
    "iso:country":"GB",
    "sg:address":"84 Cadewell Lane",
    "sg:city":"Torquay",
    "sg:classifiers":[
        {
            "category":"Shopping",
            "subcategory":"Clothing, Apparel, & Fashions",
            "type":"Retail Goods"
        }
    ],
    "sg:postcode":"TQ2 7HP",
    "sg:province":"Devon",
    "sg:tags":[
        "dresswear"
    ],
    "wof:name":"M Davies",
    "wof:placetype":"venue"
},
  "geometry": {"coordinates":[-3.5618209839,50.4800338745],"type":"Point"}
}