{
  "type": "Feature",
  "properties": {
    "addr:full":"Calder House, Deep Lane Brighouse West Yorkshire HD6 4HF",
    "addr:postcode":"hd6 4hf",
    "addr:street":"Deep Lane",
    "iso:country":"GB",
    "sg:address":"Calder House, Deep Lane",
    "sg:city":"Brighouse",
    "sg:classifiers":[
        {
            "category":"Professional",
            "subcategory":"Management & Consulting",
            "type":"Services"
        }
    ],
    "sg:phone":"+44 1484 401739",
    "sg:postcode":"HD6 4HF",
    "sg:province":"West Yorkshire",
    "sg:tags":[
        "consultant",
        "business"
    ],
    "wof:name":"Birkby Lancaster Consulting",
    "wof:placetype":"venue"
},
  "geometry": {"coordinates":[-1.752439,53.699242],"type":"Point"}
}