{
  "type": "Feature",
  "properties": {
    "iso:country":"GB",
    "sg:address":"63 St Johns",
    "sg:city":"Worcester",
    "sg:classifiers":[
        {
            "category":"Professional",
            "subcategory":"Accounting & Tax Preparation",
            "type":"Services"
        }
    ],
    "sg:phone":"+44 1905 420808",
    "sg:postcode":"WR2 5AG",
    "sg:province":"Worcestershire",
    "sg:tags":[
        "consultant"
    ],
    "wof:name":"Tax Relief Ltd.",
    "wof:placetype":"venue"
},
  "geometry": {"coordinates":[-2.235047,52.18737],"type":"Point"}
}