{
  "type": "Feature",
  "properties": {
    "iso:country":"GB",
    "sg:address":"93-95 Soho Road, Handsworth",
    "sg:city":"Birmingham",
    "sg:classifiers":[
        {
            "category":"Home & Garden",
            "subcategory":"Furniture",
            "type":"Retail Goods"
        }
    ],
    "sg:phone":"+44 121 554 3694",
    "sg:postcode":"B21 9SP",
    "sg:province":"West Midlands",
    "sg:tags":[
        "outlet"
    ],
    "wof:name":"M K Bros",
    "wof:placetype":"venue"
},
  "geometry": {"coordinates":[-1.928691,52.502056],"type":"Point"}
}