{
  "type": "Feature",
  "properties": {
    "addr:full":"21 Earlham West Centre Norwich Norfolk NR5 8AD",
    "addr:housenumber":"21",
    "addr:postcode":"nr5 8ad",
    "addr:street":"Earlham West Centre Norwich Norfolk",
    "iso:country":"GB",
    "sg:address":"21 Earlham West Centre",
    "sg:city":"Norwich",
    "sg:classifiers":[
        {
            "category":"Professional",
            "subcategory":"Business Services",
            "type":"Services"
        }
    ],
    "sg:phone":"+44 1603 454473",
    "sg:postcode":"NR5 8AD",
    "sg:province":"Norfolk",
    "sg:tags":[
        "bookmaker"
    ],
    "wof:name":"Alan J Bunney",
    "wof:placetype":"venue"
},
  "geometry": {"coordinates":[1.2408989668,52.6317634583],"type":"Point"}
}