{
  "type": "Feature",
  "properties": {
    "iso:country":"GB",
    "sg:address":"79-81 City Road",
    "sg:city":"Cardiff",
    "sg:classifiers":[
        {
            "category":"Shopping",
            "subcategory":"Department Store",
            "type":"Retail Goods"
        },
        {
            "category":"Shopping",
            "subcategory":"Crafts & Fabrics",
            "type":"Retail Goods"
        }
    ],
    "sg:phone":"+44 29 2048 1168",
    "sg:postcode":"CF24 3BL",
    "sg:province":"Cardiff",
    "sg:tags":[
        "retailer"
    ],
    "wof:name":"City Fabrics",
    "wof:placetype":"venue"
},
  "geometry": {"coordinates":[-3.1673579216,51.4878921509],"type":"Point"}
}