{
  "type": "Feature",
  "properties": {
    "iso:country":"GB",
    "sg:address":"Farm Office, Feadon Farm",
    "sg:city":"Redruth",
    "sg:classifiers":[
        {
            "category":"Farming",
            "subcategory":"Livestock Farm",
            "type":"Manufacturing & Wholesale Goods"
        }
    ],
    "sg:phone":"+44 1209 843494",
    "sg:postcode":"TR16 4PF",
    "sg:province":"Cornwall",
    "sg:tags":[
        "others"
    ],
    "wof:name":"Duchy College",
    "wof:placetype":"venue"
},
  "geometry": {"coordinates":[-5.28722,50.255138],"type":"Point"}
}