{
  "type": "Feature",
  "properties": {
    "addr:full":"43 Woodlands Road, Amsdell Lytham St. Annes Lancashire FY8 1DA",
    "addr:housenumber":"43",
    "addr:postcode":"fy8 1da",
    "addr:street":"Woodlands Road Amsdell Lytham St. Annes",
    "iso:country":"GB",
    "sg:address":"43 Woodlands Road, Amsdell",
    "sg:city":"Lytham St. Annes",
    "sg:classifiers":[
        {
            "category":"Real Estate",
            "subcategory":"Architect",
            "type":"Services"
        }
    ],
    "sg:phone":"+44 1253 738080",
    "sg:postcode":"FY8 1DA",
    "sg:province":"Lancashire",
    "wof:name":"V C S Associates",
    "wof:placetype":"venue"
},
  "geometry": {"coordinates":[-2.992877,53.741413],"type":"Point"}
}