{
  "type": "Feature",
  "properties": {
    "iso:country":"GB",
    "sg:address":"Unit C1-c2, Enterprise Park, Beck View Road",
    "sg:city":"Beverley",
    "sg:classifiers":[
        {
            "category":"Manufacturing",
            "subcategory":"Wood Products",
            "type":"Manufacturing & Wholesale Goods"
        }
    ],
    "sg:phone":"+44 1482 881255",
    "sg:postcode":"HU17 0JT",
    "sg:province":"East Riding of Yorkshire",
    "sg:tags":[
        "packaging",
        "crate",
        "pallets"
    ],
    "wof:name":"Allpac Packing Co",
    "wof:placetype":"venue"
},
  "geometry": {"coordinates":[-0.432449,53.842812],"type":"Point"}
}