{
  "type": "Feature",
  "properties": {
    "addr:full":"Oxford St Bilston West Midlands WV14 7DE",
    "addr:postcode":"wv14 7de",
    "addr:street":"Oxford St",
    "iso:country":"GB",
    "sg:address":"Oxford St",
    "sg:city":"Bilston",
    "sg:classifiers":[
        {
            "category":"Bars & Pubs",
            "type":"Food & Drink"
        }
    ],
    "sg:postcode":"WV14 7DE",
    "sg:province":"West Midlands",
    "sg:tags":[
        "pubs",
        "inn"
    ],
    "wof:name":"Mason,Edward,",
    "wof:placetype":"venue"
},
  "geometry": {"coordinates":[-2.071945,52.565674],"type":"Point"}
}