{
  "type": "Feature",
  "properties": {
    "addr:full":"Sherwood Ho, Severn Dr Walton On Thames Surrey KT12 3BQ",
    "addr:postcode":"kt12 3bq",
    "addr:street":"Severn Dr",
    "iso:country":"GB",
    "sg:address":"Sherwood Ho, Severn Dr",
    "sg:city":"Walton On Thames",
    "sg:classifiers":[
        {
            "category":"Social Services",
            "subcategory":"Retirement Home",
            "type":"Services"
        }
    ],
    "sg:phone":"+44 1932 221170",
    "sg:postcode":"KT12 3BQ",
    "sg:province":"Surrey",
    "sg:tags":[
        "residential",
        "care"
    ],
    "wof:name":"Walton-On-Thames Charity",
    "wof:placetype":"venue"
},
  "geometry": {"coordinates":[-0.4207040071,51.3843460083],"type":"Point"}
}