{
  "type": "Feature",
  "properties": {
    "addr:full":"512 Liverpool Street Salford Greater Manchester M6 5QZ",
    "addr:housenumber":"512",
    "addr:postcode":"m6 5qz",
    "addr:street":"Liverpool Street",
    "iso:country":"GB",
    "sg:address":"512 Liverpool Street",
    "sg:city":"Salford",
    "sg:classifiers":[
        {
            "category":"Retail",
            "subcategory":"Laundry & Dry Cleaning",
            "type":"Services"
        }
    ],
    "sg:phone":"+44 161 745 8735",
    "sg:postcode":"M6 5QZ",
    "sg:province":"Greater Manchester",
    "sg:tags":[
        "launderette"
    ],
    "wof:name":"Soap Opera Laundry Co",
    "wof:placetype":"venue"
},
  "geometry": {"coordinates":[-2.2996931076,53.4841384888],"type":"Point"}
}