{
  "type": "Feature",
  "properties": {
    "addr:full":"2 Park Lane, Cowplain Waterlooville Hampshire PO8 8AB",
    "addr:housenumber":"2",
    "addr:postcode":"po8 8ab",
    "addr:street":"Park Lane",
    "iso:country":"GB",
    "sg:address":"2 Park Lane, Cowplain",
    "sg:city":"Waterlooville",
    "sg:classifiers":[
        {
            "category":"Professional",
            "subcategory":"Engineering",
            "type":"Services"
        },
        {
            "category":"Building & Trades",
            "subcategory":"Electrical",
            "type":"Services"
        }
    ],
    "sg:phone":"+44 23 9226 9258",
    "sg:postcode":"PO8 8AB",
    "sg:province":"Hampshire",
    "sg:tags":[
        "engineer",
        "electrician",
        "contractor"
    ],
    "wof:name":"R D Collins Electrical Contractors",
    "wof:placetype":"venue"
},
  "geometry": {"coordinates":[-1.0186040401,50.8931770325],"type":"Point"}
}