{
  "type": "Feature",
  "properties": {
    "addr:full":"30 St Owen Street Hereford Herefordshire HR1 2PR",
    "addr:housenumber":"30",
    "addr:postcode":"hr1 2pr",
    "addr:street":"St Owen Street",
    "iso:country":"GB",
    "sg:address":"30 St Owen Street",
    "sg:city":"Hereford",
    "sg:classifiers":[
        {
            "category":"Professional",
            "subcategory":"Accounting & Tax Preparation",
            "type":"Services"
        }
    ],
    "sg:phone":"+44 1981 250800",
    "sg:postcode":"HR1 2PR",
    "sg:province":"Herefordshire",
    "sg:tags":[
        "accountant"
    ],
    "wof:name":"Manmani Deen Assoicates",
    "wof:placetype":"venue"
},
  "geometry": {"coordinates":[-2.713359,52.055851],"type":"Point"}
}