{
  "type": "Feature",
  "properties": {
    "addr:full":"47a High Rd, Bushey Heath Watford Hertfordshire WD2 1EE",
    "addr:housenumber":"47a",
    "addr:postcode":"wd2 1ee",
    "addr:street":"High Rd",
    "iso:country":"GB",
    "sg:address":"47a High Rd, Bushey Heath",
    "sg:city":"Watford",
    "sg:classifiers":[
        {
            "category":"Taxi",
            "type":"Transportation"
        }
    ],
    "sg:phone":"+44 20 8950 9545",
    "sg:postcode":"WD2 1EE",
    "sg:province":"Hertfordshire",
    "sg:tags":[
        "mini",
        "cab"
    ],
    "wof:name":"Bushey & District Cars",
    "wof:placetype":"venue"
},
  "geometry": {"coordinates":[-0.3403199911,51.6333885193],"type":"Point"}
}