{
  "type": "Feature",
  "properties": {
    "addr:full":"Unit 2 Eastern Avenue Gloucester Gloucestershire GL4 7BY",
    "addr:housenumber":"unit 2",
    "addr:postcode":"gl4 7by",
    "addr:street":"Eastern Avenue",
    "iso:country":"GB",
    "sg:address":"Unit 2 Eastern Avenue",
    "sg:city":"Gloucester",
    "sg:classifiers":[
        {
            "category":"Home & Garden",
            "subcategory":"Furniture",
            "type":"Retail Goods"
        }
    ],
    "sg:phone":"+44 1452 311300",
    "sg:postcode":"GL4 7BY",
    "sg:province":"Gloucestershire",
    "wof:name":"M F I Furniture Centres Ltd.",
    "wof:placetype":"venue"
},
  "geometry": {"coordinates":[-2.213558,51.86356],"type":"Point"}
}