{
  "type": "Feature",
  "properties": {
    "addr:full":"The Farmhouse, Bonneyhale Road, Ealand Warpings Scunthorpe Lincolnshire DN17 4DG",
    "addr:postcode":"dn17 4dg",
    "addr:street":"Bonneyhale Road Ealand Warpings",
    "iso:country":"GB",
    "sg:address":"The Farmhouse, Bonneyhale Road, Ealand Warpings",
    "sg:city":"Scunthorpe",
    "sg:classifiers":[
        {
            "category":"Sports & Exercise",
            "subcategory":"Skate Park",
            "type":"Entertainment"
        }
    ],
    "sg:postcode":"DN17 4DG",
    "sg:province":"Lincolnshire",
    "sg:tags":[
        "mushroom"
    ],
    "wof:name":"Bonneyhale Mushrooms",
    "wof:placetype":"venue"
},
  "geometry": {"coordinates":[-0.818964,53.592403],"type":"Point"}
}