{
  "type": "Feature",
  "properties": {
    "addr:full":"The Broadway, Joel St Northwood Greater London HA6 1PF",
    "addr:postcode":"ha6 1pf",
    "addr:street":"The Broadway Joel St",
    "iso:country":"GB",
    "sg:address":"The Broadway, Joel St",
    "sg:city":"Northwood",
    "sg:classifiers":[
        {
            "category":"Home & Garden",
            "subcategory":"Furniture",
            "type":"Retail Goods"
        }
    ],
    "sg:phone":"+44 1923 842000",
    "sg:postcode":"HA6 1PF",
    "sg:province":"Greater London",
    "wof:name":"Life Style Fitted Bedrooms",
    "wof:placetype":"venue"
},
  "geometry": {"coordinates":[-0.4094699919,51.6019897461],"type":"Point"}
}