{
  "type": "Feature",
  "properties": {
    "addr:full":"12 Beechwood Drive Birkenhead Merseyside L43 7ZU",
    "addr:housenumber":"12",
    "addr:postcode":"l43 7zu",
    "addr:street":"Beechwood Drive",
    "iso:country":"GB",
    "sg:address":"12 Beechwood Drive",
    "sg:city":"Birkenhead",
    "sg:classifiers":[
        {
            "category":"Fast Food",
            "type":"Food & Drink"
        }
    ],
    "sg:phone":"+44 151 604 1236",
    "sg:postcode":"L43 7ZU",
    "sg:province":"Merseyside",
    "sg:tags":[
        "away",
        "take"
    ],
    "wof:name":"Beechwood Fast Food Takeaway",
    "wof:placetype":"venue"
},
  "geometry": {"coordinates":[-3.0831949711,53.3957023621],"type":"Point"}
}