{
  "type": "Feature",
  "properties": {
    "addr:full":"Bridge End House, Bacup Road Rossendale Lancashire BB4 7AW",
    "addr:postcode":"bb4 7aw",
    "addr:street":"End;Bacup Road",
    "iso:country":"GB",
    "sg:address":"Bridge End House, Bacup Road",
    "sg:city":"Rossendale",
    "sg:classifiers":[
        {
            "category":"Education",
            "subcategory":"Library",
            "type":"Public Place"
        }
    ],
    "sg:phone":"+44 1706 227693",
    "sg:postcode":"BB4 7AW",
    "sg:province":"Lancashire",
    "sg:tags":[
        "book"
    ],
    "wof:name":"Waterfoot Library",
    "wof:placetype":"venue"
},
  "geometry": {"coordinates":[-2.273389101,53.700088501],"type":"Point"}
}