{
  "type": "Feature",
  "properties": {
    "addr:full":"24 Rainhall Road, Barnoldswick Colne Lancashire BB18 5AF",
    "addr:housenumber":"24",
    "addr:postcode":"bb18 5af",
    "addr:street":"Rainhall Road;Colne",
    "iso:country":"GB",
    "sg:address":"24 Rainhall Road, Barnoldswick",
    "sg:city":"Colne",
    "sg:classifiers":[
        {
            "category":"Shopping",
            "subcategory":"News",
            "type":"Retail Goods"
        }
    ],
    "sg:phone":"+44 1282 813381",
    "sg:postcode":"BB18 5AF",
    "sg:province":"Lancashire",
    "sg:tags":[
        "newsagent"
    ],
    "wof:name":"B & P Edmondson",
    "wof:placetype":"venue"
},
  "geometry": {"coordinates":[-2.1866500378,53.9157066345],"type":"Point"}
}