{
  "type": "Feature",
  "properties": {
    "addr:full":"229b Lower Hillmorton Road Rugby Warwickshire CV21 4AA",
    "addr:housenumber":"229b",
    "addr:postcode":"cv21 4aa",
    "addr:street":"Lower Hillmorton Road",
    "iso:country":"GB",
    "sg:address":"229b Lower Hillmorton Road",
    "sg:city":"Rugby",
    "sg:classifiers":[
        {
            "category":"Fast Food",
            "type":"Food & Drink"
        }
    ],
    "sg:phone":"+44 1788 550532",
    "sg:postcode":"CV21 4AA",
    "sg:province":"Warwickshire",
    "sg:tags":[
        "away",
        "meal",
        "outlet",
        "take"
    ],
    "wof:name":"Four Seasons Chinese Take Away",
    "wof:placetype":"venue"
},
  "geometry": {"coordinates":[-1.232669,52.366116],"type":"Point"}
}