{
  "type": "Feature",
  "properties": {
    "iso:country":"GB",
    "sg:address":"63 Cromwell St",
    "sg:city":"Stornoway",
    "sg:classifiers":[
        {
            "category":"Shopping",
            "subcategory":"Books",
            "type":"Retail Goods"
        }
    ],
    "sg:phone":"+44 1851 702372",
    "sg:postcode":"HS1 2DD",
    "sg:province":"Eilean Siar",
    "sg:tags":[
        "bookseller"
    ],
    "wof:name":"Loch Erisort Ltd",
    "wof:placetype":"venue"
},
  "geometry": {"coordinates":[-6.380339,58.213451],"type":"Point"}
}