{
  "type": "Feature",
  "properties": {
    "iso:country":"GB",
    "sg:address":"19 Riding Barns Way, Sunniside",
    "sg:city":"Newcastle-upon-tyne",
    "sg:classifiers":[
        {
            "category":"Retail",
            "subcategory":"Driving School",
            "type":"Services"
        }
    ],
    "sg:phone":"+44 191 488 0101",
    "sg:postcode":"NE16 5QA",
    "sg:province":"Durham",
    "wof:name":"Glen School of Motoring",
    "wof:placetype":"venue"
},
  "geometry": {"coordinates":[-1.6818339825,54.9231147766],"type":"Point"}
}