{
  "type": "Feature",
  "properties": {
    "addr:full":"Stonehenge Park, Orcheston Salisbury Wiltshire SP3 4SH",
    "addr:postcode":"sp3 4sh",
    "iso:country":"GB",
    "sg:address":"Stonehenge Park, Orcheston",
    "sg:city":"Salisbury",
    "sg:classifiers":[
        {
            "category":"Recreation",
            "subcategory":"Campground",
            "type":"Entertainment"
        }
    ],
    "sg:postcode":"SP3 4SH",
    "sg:province":"Wiltshire",
    "sg:tags":[
        "site",
        "camping"
    ],
    "wof:name":"Stonehenge Touring Park",
    "wof:placetype":"venue"
},
  "geometry": {"coordinates":[-1.917856,51.20681],"type":"Point"}
}