{
  "type": "Feature",
  "properties": {
    "iso:country":"GB",
    "sg:address":"7 Nunhold Business Centre, Dark La, Hatton",
    "sg:city":"Warwick",
    "sg:classifiers":[
        {
            "category":"Retail",
            "subcategory":"Repair Shop",
            "type":"Services"
        }
    ],
    "sg:postcode":"CV35 8XB",
    "sg:province":"Warwickshire",
    "sg:tags":[
        "clocks",
        "watch"
    ],
    "wof:name":"Summersons Restorations",
    "wof:placetype":"venue"
},
  "geometry": {"coordinates":[-1.662364,52.290173],"type":"Point"}
}