{
  "type": "Feature",
  "properties": {
    "addr:full":"Newsham House, Winston Darlington Durham DL2 3QN",
    "addr:postcode":"dl2 3qn",
    "addr:street":"Winston Darlington",
    "iso:country":"GB",
    "sg:address":"Newsham House, Winston",
    "sg:city":"Darlington",
    "sg:classifiers":[
        {
            "category":"Building & Trades",
            "subcategory":"Construction",
            "type":"Services"
        }
    ],
    "sg:phone":"+44 1833 660663",
    "sg:postcode":"DL2 3QN",
    "sg:province":"Durham",
    "sg:tags":[
        "builder"
    ],
    "wof:name":"John Malcolm Ltd.",
    "wof:placetype":"venue"
},
  "geometry": {"coordinates":[-1.781284,54.548134],"type":"Point"}
}