{
  "type": "Feature",
  "properties": {
    "addr:full":"Hareslade Farm, Brandicup, Bishopston Swansea Swansea SA3 3DT",
    "addr:postcode":"sa3 3dt",
    "addr:street":"Brandicup",
    "iso:country":"GB",
    "sg:address":"Hareslade Farm, Brandicup, Bishopston",
    "sg:city":"Swansea",
    "sg:classifiers":[
        {
            "category":"Real Estate",
            "subcategory":"Architect",
            "type":"Services"
        }
    ],
    "sg:postcode":"SA3 3DT",
    "sg:province":"Swansea",
    "wof:name":"John Noel Architect",
    "wof:placetype":"venue"
},
  "geometry": {"coordinates":[-4.047634,51.576405],"type":"Point"}
}