{
  "type": "Feature",
  "properties": {
    "addr:full":"Main Road, Maltby Le Marsh Alford Lincolnshire LN13 0JP",
    "addr:postcode":"ln13 0jp",
    "addr:street":"Main Road",
    "iso:country":"GB",
    "sg:address":"Main Road, Maltby Le Marsh",
    "sg:city":"Alford",
    "sg:classifiers":[
        {
            "category":"Recreation",
            "subcategory":"Fishing",
            "type":"Entertainment"
        }
    ],
    "sg:phone":"+44 1507 450623",
    "sg:postcode":"LN13 0JP",
    "sg:province":"Lincolnshire",
    "sg:tags":[
        "equipment",
        "angling"
    ],
    "wof:name":"Oham Lakes",
    "wof:placetype":"venue"
},
  "geometry": {"coordinates":[0.200244993,53.3102760315],"type":"Point"}
}