{
  "type": "Feature",
  "properties": {
    "addr:full":"108 Station Road, Bamber Bridge Preston Lancashire PR5 6QP",
    "addr:housenumber":"108",
    "addr:postcode":"pr5 6qp",
    "addr:street":"Station Road",
    "iso:country":"GB",
    "sg:address":"108 Station Road, Bamber Bridge",
    "sg:city":"Preston",
    "sg:classifiers":[
        {
            "category":"Insurance",
            "subcategory":"Insurance Agent",
            "type":"Services"
        }
    ],
    "sg:phone":"+44 1772 697777",
    "sg:postcode":"PR5 6QP",
    "sg:province":"Lancashire",
    "sg:tags":[
        "broker"
    ],
    "wof:name":"Insurance Broking Partnership",
    "wof:placetype":"venue"
},
  "geometry": {"coordinates":[-2.6624569893,53.7319107056],"type":"Point"}
}