{
  "type": "Feature",
  "properties": {
    "addr:full":"8 Milton Road, College Milton North, East Kilbride Glasgow South Lanarkshire G74 5BU",
    "addr:housenumber":"8",
    "addr:postcode":"g74 5bu",
    "addr:street":"Milton Road;East",
    "iso:country":"GB",
    "sg:address":"8 Milton Road, College Milton North, East Kilbride",
    "sg:city":"Glasgow",
    "sg:classifiers":[
        {
            "category":"Distillery",
            "subcategory":"None",
            "type":"Food & Drink"
        }
    ],
    "sg:phone":"+44 1355 260999",
    "sg:postcode":"G74 5BU",
    "sg:province":"South Lanarkshire",
    "wof:name":"Burn Stewart Distillers Ltd.",
    "wof:placetype":"venue"
},
  "geometry": {"coordinates":[-4.2112021446,55.7672538757],"type":"Point"}
}