{
  "type": "Feature",
  "properties": {
    "addr:full":"27 Carlyon Road Hayes Greater London UB4 0NR",
    "addr:housenumber":"27",
    "addr:postcode":"ub4 0nr",
    "addr:street":"Carlyon Road",
    "iso:country":"GB",
    "sg:address":"27 Carlyon Road",
    "sg:city":"Hayes",
    "sg:classifiers":[
        {
            "category":"Retail",
            "subcategory":"Repair Shop",
            "type":"Services"
        }
    ],
    "sg:postcode":"UB4 0NR",
    "sg:province":"Greater London",
    "sg:tags":[
        "maintenance"
    ],
    "wof:name":"Professional Property Maintenance",
    "wof:placetype":"venue"
},
  "geometry": {"coordinates":[-0.398923,51.522545],"type":"Point"}
}