{
  "type": "Feature",
  "properties": {
    "addr:full":"1 Syddall St Hyde Cheshire SK14 1JH",
    "addr:housenumber":"1",
    "addr:postcode":"sk14 1jh",
    "addr:street":"Syddall St",
    "iso:country":"GB",
    "sg:address":"1 Syddall St",
    "sg:city":"Hyde",
    "sg:classifiers":[
        {
            "category":"Food & Beverages",
            "subcategory":"Fruits & Vegetables",
            "type":"Retail Goods"
        }
    ],
    "sg:phone":"+44 161 366 8357",
    "sg:postcode":"SK14 1JH",
    "sg:province":"Cheshire",
    "sg:tags":[
        "greengrocer"
    ],
    "wof:name":"Quality Food",
    "wof:placetype":"venue"
},
  "geometry": {"coordinates":[-2.0781490803,53.447719574],"type":"Point"}
}