{
  "type": "Feature",
  "properties": {
    "addr:full":"Oldfield Farm, Marshfield Chippenham Gloucestershire SN14 8LE",
    "addr:postcode":"sn14 8le",
    "addr:street":"Marshfield",
    "iso:country":"GB",
    "sg:address":"Oldfield Farm, Marshfield",
    "sg:city":"Chippenham",
    "sg:classifiers":[
        {
            "category":"Ice Cream",
            "type":"Food & Drink"
        }
    ],
    "sg:phone":"+44 1225 891221",
    "sg:postcode":"SN14 8LE",
    "sg:province":"Gloucestershire",
    "sg:tags":[
        "mnfr"
    ],
    "wof:name":"Marshfield Farm Foods",
    "wof:placetype":"venue"
},
  "geometry": {"coordinates":[-2.3187100887,51.4641952515],"type":"Point"}
}