{
  "type": "Feature",
  "properties": {
    "iso:country":"GB",
    "sg:address":"The Coach House, Upper York Street",
    "sg:city":"Bristol",
    "sg:classifiers":[
        {
            "category":"Community Center",
            "subcategory":"Youth",
            "type":"Public Place"
        },
        {
            "category":"Organizations",
            "subcategory":"Non-profit Organization",
            "type":"Services"
        }
    ],
    "sg:phone":"+44 117 942 5362",
    "sg:postcode":"BS2 8QN",
    "sg:province":"City of Bristol",
    "sg:tags":[
        "organisation",
        "charity",
        "voluntary",
        "centre"
    ],
    "wof:name":"Fairbridge Avon",
    "wof:placetype":"venue"
},
  "geometry": {"coordinates":[-2.590254,51.462051],"type":"Point"}
}