{
  "type": "Feature",
  "properties": {
    "addr:full":"John Ryder Training Centre, St Anns Road Chertsey Surrey KT16 9EH",
    "addr:postcode":"kt16 9eh",
    "addr:street":"St Anns Road",
    "iso:country":"GB",
    "sg:address":"John Ryder Training Centre, St Anns Road",
    "sg:city":"Chertsey",
    "sg:classifiers":[
        {
            "category":"Education",
            "subcategory":"Special Training",
            "type":"Public Place"
        }
    ],
    "sg:phone":"+44 1932 561871",
    "sg:postcode":"KT16 9EH",
    "sg:province":"Surrey",
    "sg:tags":[
        "product",
        "centre"
    ],
    "wof:name":"Construction Health & Safety Group",
    "wof:placetype":"venue"
},
  "geometry": {"coordinates":[-0.508254,51.388199],"type":"Point"}
}