{
  "type": "Feature",
  "properties": {
    "iso:country":"GB",
    "sg:address":"139 Kirkby Rd, Hemsworth",
    "sg:city":"Pontefract",
    "sg:classifiers":[
        {
            "category":"Building & Trades",
            "subcategory":"Construction",
            "type":"Services"
        }
    ],
    "sg:postcode":"WF9 4DE",
    "sg:province":"West Yorkshire",
    "sg:tags":[
        "tiling",
        "contractor"
    ],
    "wof:name":"Rowley,Dave,",
    "wof:placetype":"venue"
},
  "geometry": {"coordinates":[-1.3461010456,53.6069564819],"type":"Point"}
}