{
  "type": "Feature",
  "properties": {
    "iso:country":"GB",
    "sg:address":"Unit 9, Crayside Industrial Estate",
    "sg:city":"Dartford",
    "sg:classifiers":[
        {
            "category":"Shopping",
            "subcategory":"Stationery & Office Supplies",
            "type":"Retail Goods"
        },
        {
            "category":"Professional",
            "subcategory":"Engineering",
            "type":"Services"
        }
    ],
    "sg:phone":"+44 1322 550055",
    "sg:postcode":"DA1 4RF",
    "sg:province":"Kent",
    "sg:tags":[
        "printers'",
        "printing",
        "finishing"
    ],
    "wof:name":"Exel Graphic Services Ltd.",
    "wof:placetype":"venue"
},
  "geometry": {"coordinates":[0.220555,51.444633],"type":"Point"}
}