{
  "type": "Feature",
  "properties": {
    "addr:full":"94-96 Shields Road Newcastle-upon-tyne Tyne and Wear NE6 1DS",
    "addr:housenumber":"94-96",
    "addr:postcode":"ne6 1ds",
    "addr:street":"Shields Road",
    "iso:country":"GB",
    "sg:address":"94-96 Shields Road",
    "sg:city":"Newcastle-upon-tyne",
    "sg:classifiers":[
        {
            "category":"Home & Garden",
            "subcategory":"Hardware",
            "type":"Retail Goods"
        }
    ],
    "sg:phone":"+44 191 265 2228",
    "sg:postcode":"NE6 1DS",
    "sg:province":"Tyne and Wear",
    "sg:tags":[
        "retailer",
        "lighting"
    ],
    "wof:name":"S A Lighting Centre",
    "wof:placetype":"venue"
},
  "geometry": {"coordinates":[-1.582888,54.976711],"type":"Point"}
}