{
  "type": "Feature",
  "properties": {
    "iso:country":"GB",
    "sg:address":"31 Elizabeth Street",
    "sg:city":"Nelson",
    "sg:classifiers":[
        {
            "category":"Manufacturing",
            "subcategory":"Textiles",
            "type":"Manufacturing & Wholesale Goods"
        },
        {
            "category":"Shopping",
            "subcategory":"Crafts & Fabrics",
            "type":"Retail Goods"
        }
    ],
    "sg:phone":"+44 1282 612234",
    "sg:postcode":"BB9 7YA",
    "sg:province":"Lancashire",
    "sg:tags":[
        "merchant",
        "knitwear",
        "agent",
        "producer"
    ],
    "wof:name":"Nelson Textiles",
    "wof:placetype":"venue"
},
  "geometry": {"coordinates":[-2.21331,53.841827],"type":"Point"}
}