{
  "type": "Feature",
  "properties": {
    "addr:full":"244a Chase Side Southgate Greater London N14 4PL",
    "addr:housenumber":"244a",
    "addr:postcode":"n14 4pl",
    "addr:street":"Chase Side",
    "iso:country":"GB",
    "sg:address":"244a Chase Side",
    "sg:city":"Southgate",
    "sg:classifiers":[
        {
            "category":"Health Services",
            "subcategory":"Dentist",
            "type":"Services"
        }
    ],
    "sg:phone":"+44 20 8449 5643",
    "sg:postcode":"N14 4PL",
    "sg:province":"Greater London",
    "wof:name":"A Adams",
    "wof:placetype":"venue"
},
  "geometry": {"coordinates":[-0.1408659965,51.6384124756],"type":"Point"}
}