{
  "type": "Feature",
  "properties": {
    "addr:full":"153 Finstall Road, Finstall Bromsgrove Worcestershire B60 3DD",
    "addr:housenumber":"153",
    "addr:postcode":"b60 3dd",
    "addr:street":"Finstall Road",
    "iso:country":"GB",
    "sg:address":"153 Finstall Road, Finstall",
    "sg:city":"Bromsgrove",
    "sg:classifiers":[
        {
            "category":"Professional",
            "subcategory":"Management & Consulting",
            "type":"Services"
        }
    ],
    "sg:phone":"+44 1527 835685",
    "sg:postcode":"B60 3DD",
    "sg:province":"Worcestershire",
    "sg:tags":[
        "consultant",
        "training"
    ],
    "wof:name":"Sellsem",
    "wof:placetype":"venue"
},
  "geometry": {"coordinates":[-2.032554,52.329082],"type":"Point"}
}