{
  "type": "Feature",
  "properties": {
    "addr:full":"Kings Road Bury St Edmunds Suffolk IP33 3DE",
    "addr:postcode":"ip33 3de",
    "addr:street":"Kings Road",
    "iso:country":"GB",
    "sg:address":"Kings Road",
    "sg:city":"Bury St Edmunds",
    "sg:classifiers":[
        {
            "category":"Shopping",
            "subcategory":"Florist",
            "type":"Retail Goods"
        }
    ],
    "sg:postcode":"IP33 3DE",
    "sg:province":"Suffolk",
    "wof:name":"The Flower House",
    "wof:placetype":"venue"
},
  "geometry": {"coordinates":[0.7079049945,52.2446136475],"type":"Point"}
}