{
  "type": "Feature",
  "properties": {
    "addr:full":"Woodlands, Cholderton Salisbury Hampshire SP4 0EQ",
    "addr:postcode":"sp4 0eq",
    "iso:country":"GB",
    "sg:address":"Woodlands, Cholderton",
    "sg:city":"Salisbury",
    "sg:classifiers":[
        {
            "category":"Professional",
            "type":"Services"
        }
    ],
    "sg:phone":"+44 1980 629889",
    "sg:postcode":"SP4 0EQ",
    "sg:province":"Hampshire",
    "sg:tags":[
        "caterer"
    ],
    "wof:name":"Charlton's Catering Co Ltd",
    "wof:placetype":"venue"
},
  "geometry": {"coordinates":[-1.6797720194,51.1788864136],"type":"Point"}
}