{
  "type": "Feature",
  "properties": {
    "iso:country":"GB",
    "sg:address":"53 Upper Tichborne Street",
    "sg:city":"Leicester",
    "sg:classifiers":[
        {
            "category":"Personal",
            "type":"Services"
        },
        {
            "category":"Professional",
            "subcategory":"Lawyer & Legal Services",
            "type":"Services"
        }
    ],
    "sg:phone":"+44 116 255 8670",
    "sg:postcode":"LE2 1GL",
    "sg:province":"Leicestershire",
    "sg:tags":[
        "advice",
        "counselling"
    ],
    "wof:name":"Insight",
    "wof:placetype":"venue"
},
  "geometry": {"coordinates":[-1.117583,52.628338],"type":"Point"}
}