{
  "type": "Feature",
  "properties": {
    "iso:country":"GB",
    "sg:address":"Chalford Hill, Middle Hill",
    "sg:city":"Stroud",
    "sg:classifiers":[
        {
            "category":"Farming",
            "subcategory":"Dairy Farm",
            "type":"Manufacturing & Wholesale Goods"
        }
    ],
    "sg:postcode":"GL6 8BE",
    "sg:province":"Gloucestershire",
    "wof:name":"Hania Cheeses",
    "wof:placetype":"venue"
},
  "geometry": {"coordinates":[-2.15188,51.729439],"type":"Point"}
}