{
  "type": "Feature",
  "properties": {
    "iso:country":"GB",
    "sg:address":"Ellerthwaite Depot, Broad St",
    "sg:city":"Windermere",
    "sg:classifiers":[
        {
            "category":"Building & Trades",
            "subcategory":"Landscaping Services",
            "type":"Services"
        }
    ],
    "sg:phone":"+44 15394 88746",
    "sg:postcode":"LA23 2AB",
    "sg:province":"Cumbria",
    "sg:tags":[
        "gardening"
    ],
    "wof:name":"Continental Landscapes Ltd",
    "wof:placetype":"venue"
},
  "geometry": {"coordinates":[-2.9063060284,54.3760986328],"type":"Point"}
}