{
  "type": "Feature",
  "properties": {
    "iso:country":"GB",
    "sg:address":"Glasgow Ho, High St",
    "sg:city":"Lampeter",
    "sg:classifiers":[
        {
            "category":"Home & Garden",
            "subcategory":"Hardware",
            "type":"Retail Goods"
        }
    ],
    "sg:phone":"+44 1570 422522",
    "sg:postcode":"SA48 7BB",
    "sg:province":"Carmarthenshire",
    "wof:name":"J W Davies",
    "wof:placetype":"venue"
},
  "geometry": {"coordinates":[-4.0774650574,52.1142616272],"type":"Point"}
}