{
  "type": "Feature",
  "properties": {
    "addr:full":"Cross Street Ellesmere Shropshire SY12 0AW",
    "addr:postcode":"sy12 0aw",
    "addr:street":"Cross Street",
    "iso:country":"GB",
    "sg:address":"Cross Street",
    "sg:city":"Ellesmere",
    "sg:classifiers":[
        {
            "category":"Bars & Pubs",
            "type":"Food & Drink"
        }
    ],
    "sg:phone":"+44 1691 622596",
    "sg:postcode":"SY12 0AW",
    "sg:province":"Shropshire",
    "sg:tags":[
        "pubs",
        "inn"
    ],
    "wof:name":"Swan Inn",
    "wof:placetype":"venue"
},
  "geometry": {"coordinates":[-2.893132,52.908237],"type":"Point"}
}