{
  "type": "Feature",
  "properties": {
    "iso:country":"GB",
    "sg:address":"22 High Street, Wing",
    "sg:city":"Leighton Buzzard",
    "sg:classifiers":[
        {
            "category":"Bus Charters",
            "type":"Transportation"
        }
    ],
    "sg:phone":"+44 1296 688739",
    "sg:postcode":"LU7 0NR",
    "sg:province":"Bedfordshire",
    "sg:tags":[
        "mini",
        "hire",
        "leasing"
    ],
    "wof:name":"Wing Cabs",
    "wof:placetype":"venue"
},
  "geometry": {"coordinates":[-0.7241880298,51.9049682617],"type":"Point"}
}