{
  "type": "Feature",
  "properties": {
    "addr:full":"Unit 2 Peterborough Cambridgeshire PE4 5EG",
    "addr:housenumber":"unit 2",
    "addr:postcode":"pe4 5eg",
    "addr:street":"Peterborough",
    "iso:country":"GB",
    "sg:address":"Unit 2",
    "sg:city":"Peterborough",
    "sg:classifiers":[
        {
            "category":"Fast Food",
            "type":"Food & Drink"
        }
    ],
    "sg:phone":"+44 1733 708888",
    "sg:postcode":"PE4 5EG",
    "sg:province":"Cambridgeshire",
    "sg:tags":[
        "away",
        "take"
    ],
    "wof:name":"Peking Supreme",
    "wof:placetype":"venue"
},
  "geometry": {"coordinates":[-0.27933,52.628479],"type":"Point"}
}