{
  "type": "Feature",
  "properties": {
    "iso:country":"GB",
    "sg:address":"Unit 9 Dorrington Business Park",
    "sg:city":"Shrewsbury",
    "sg:classifiers":[
        {
            "category":"Professional",
            "subcategory":"Management & Consulting",
            "type":"Services"
        }
    ],
    "sg:phone":"+44 1743 718299",
    "sg:postcode":"SY5 7JP",
    "sg:province":"Shropshire",
    "sg:tags":[
        "consultant",
        "business"
    ],
    "wof:name":"Hamilton Roberts",
    "wof:placetype":"venue"
},
  "geometry": {"coordinates":[-2.773744,52.622826],"type":"Point"}
}