{
  "type": "Feature",
  "properties": {
    "addr:full":"Freeman Road Newcastle-upon-tyne Tyne and Wear NE7 7AF",
    "addr:postcode":"ne7 7af",
    "addr:street":"Freeman Road",
    "iso:country":"GB",
    "sg:address":"Freeman Road",
    "sg:city":"Newcastle-upon-tyne",
    "sg:classifiers":[
        {
            "category":"Social Services",
            "type":"Services"
        },
        {
            "category":"Health Services",
            "subcategory":"Hospital",
            "type":"Services"
        }
    ],
    "sg:phone":"+44 191 285 8659",
    "sg:postcode":"NE7 7AF",
    "sg:province":"Tyne and Wear",
    "sg:tags":[
        "surgical",
        "disability"
    ],
    "wof:name":"C A Blatchford & Sons Ltd",
    "wof:placetype":"venue"
},
  "geometry": {"coordinates":[-1.594634,54.999725],"type":"Point"}
}