{
  "type": "Feature",
  "properties": {
    "iso:country":"GB",
    "sg:address":"Belle Vue Way, Longhill Industrial Estate",
    "sg:city":"Hartlepool",
    "sg:classifiers":[
        {
            "category":"Building & Trades",
            "subcategory":"Construction",
            "type":"Services"
        }
    ],
    "sg:postcode":"TS25 1NU",
    "sg:province":"Durham",
    "sg:tags":[
        "joinery"
    ],
    "wof:name":"J D A Joinery",
    "wof:placetype":"venue"
},
  "geometry": {"coordinates":[-1.217739,54.66568],"type":"Point"}
}