{
  "type": "Feature",
  "properties": {
    "iso:country":"GB",
    "sg:address":"24 Sherrard St",
    "sg:city":"Melton Mowbray",
    "sg:classifiers":[
        {
            "category":"Shopping",
            "subcategory":"Clothing, Apparel, & Fashions",
            "type":"Retail Goods"
        }
    ],
    "sg:postcode":"LE13 1XJ",
    "sg:province":"Leicestershire",
    "sg:tags":[
        "lingerie",
        "hosiery"
    ],
    "wof:name":"Harwayes Ltd",
    "wof:placetype":"venue"
},
  "geometry": {"coordinates":[-0.884552002,52.764415741],"type":"Point"}
}