{
  "type": "Feature",
  "properties": {
    "iso:country":"GB",
    "sg:address":"Little Wakering Rd",
    "sg:city":"Southend On Sea",
    "sg:classifiers":[
        {
            "category":"Place Of Worship",
            "type":"Public Place"
        }
    ],
    "sg:phone":"+44 1702 219200",
    "sg:postcode":"SS3 0JN",
    "sg:province":"Essex",
    "wof:name":"All Saints C of E Church",
    "wof:placetype":"venue"
},
  "geometry": {"coordinates":[0.783912,51.567963],"type":"Point"}
}