{
  "type": "Feature",
  "properties": {
    "addr:full":"16 Station Approach, Coulsdon North Coulsdon Surrey CR5 2NR",
    "addr:housenumber":"16",
    "addr:postcode":"cr5 2nr",
    "addr:street":"Station Approach",
    "iso:country":"GB",
    "sg:address":"16 Station Approach, Coulsdon North",
    "sg:city":"Coulsdon",
    "sg:classifiers":[
        {
            "category":"Shopping",
            "subcategory":"Florist",
            "type":"Retail Goods"
        }
    ],
    "sg:phone":"+44 1737 551119",
    "sg:postcode":"CR5 2NR",
    "sg:province":"Surrey",
    "wof:name":"Flower Ranger",
    "wof:placetype":"venue"
},
  "geometry": {"coordinates":[-0.1391790062,51.3189239502],"type":"Point"}
}