{
  "type": "Feature",
  "properties": {
    "addr:full":"25 Boroughbridge Road York North Yorkshire YO26 5RT",
    "addr:housenumber":"25",
    "addr:postcode":"yo26 5rt",
    "addr:street":"Boroughbridge Road",
    "iso:country":"GB",
    "sg:address":"25 Boroughbridge Road",
    "sg:city":"York",
    "sg:classifiers":[
        {
            "category":"Professional",
            "subcategory":"Lawyer & Legal Services",
            "type":"Services"
        }
    ],
    "sg:phone":"+44 1904 632244",
    "sg:postcode":"YO26 5RT",
    "sg:province":"North Yorkshire",
    "sg:tags":[
        "solicitor"
    ],
    "wof:name":"P Crowe Solicitors",
    "wof:placetype":"venue"
},
  "geometry": {"coordinates":[-1.1178250313,53.9635505676],"type":"Point"}
}