{
  "type": "Feature",
  "properties": {
    "iso:country":"GB",
    "sg:address":"48 Shirley St, Sawley",
    "sg:city":"Nottingham",
    "sg:classifiers":[
        {
            "category":"Wholesale",
            "subcategory":"Construction Materials",
            "type":"Manufacturing & Wholesale Goods"
        }
    ],
    "sg:phone":"+44 115 946 0404",
    "sg:postcode":"NG10 3BN",
    "sg:province":"Derbyshire",
    "sg:tags":[
        "lift"
    ],
    "wof:name":"Lift Logic",
    "wof:placetype":"venue"
},
  "geometry": {"coordinates":[-1.300856,52.880543],"type":"Point"}
}