{
  "type": "Feature",
  "properties": {
    "iso:country":"GB",
    "sg:address":"32 Estoril Rd",
    "sg:city":"Darlington",
    "sg:classifiers":[
        {
            "category":"Building & Trades",
            "subcategory":"Cleaning & Sanitation",
            "type":"Services"
        }
    ],
    "sg:phone":"+44 1325 283788",
    "sg:postcode":"DL1 4ND",
    "sg:province":"Durham",
    "sg:tags":[
        "cleaner",
        "window"
    ],
    "wof:name":"K & M.V Taylor",
    "wof:placetype":"venue"
},
  "geometry": {"coordinates":[-1.521754,54.520638],"type":"Point"}
}