{
  "type": "Feature",
  "properties": {
    "addr:full":"17 Harwood Close, Tewin Welwyn Hertfordshire AL6 0LF",
    "addr:housenumber":"17",
    "addr:postcode":"al6 0lf",
    "addr:street":"Harwood Close",
    "iso:country":"GB",
    "sg:address":"17 Harwood Close, Tewin",
    "sg:city":"Welwyn",
    "sg:classifiers":[
        {
            "category":"Retail",
            "subcategory":"Portrait Studio",
            "type":"Services"
        },
        {
            "category":"Professional",
            "subcategory":"Art Services",
            "type":"Services"
        }
    ],
    "sg:phone":"+44 1438 717841",
    "sg:postcode":"AL6 0LF",
    "sg:province":"Hertfordshire",
    "sg:tags":[
        "photographer",
        "commercial"
    ],
    "wof:name":"LES BORG",
    "wof:placetype":"venue"
},
  "geometry": {"coordinates":[-0.1545210034,51.818572998],"type":"Point"}
}