{
  "type": "Feature",
  "properties": {
    "addr:full":"Mill House, Ilkeston Road Nottingham Nottinghamshire NG7 3EP",
    "addr:postcode":"ng7 3ep",
    "addr:street":"Ilkeston Road",
    "iso:country":"GB",
    "sg:address":"Mill House, Ilkeston Road",
    "sg:city":"Nottingham",
    "sg:classifiers":[
        {
            "category":"Home & Garden",
            "subcategory":"Hardware",
            "type":"Retail Goods"
        }
    ],
    "sg:phone":"+44 115 978 1717",
    "sg:postcode":"NG7 3EP",
    "sg:province":"Nottinghamshire",
    "sg:tags":[
        "centre",
        "improvement"
    ],
    "wof:name":"Magnet Kitchens",
    "wof:placetype":"venue"
},
  "geometry": {"coordinates":[-1.166839,52.956139],"type":"Point"}
}