{
  "type": "Feature",
  "properties": {
    "iso:country":"GB",
    "sg:address":"163 Selby Road",
    "sg:city":"Leeds",
    "sg:classifiers":[
        {
            "category":"Building & Trades",
            "subcategory":"Cleaning & Sanitation",
            "type":"Services"
        }
    ],
    "sg:postcode":"LS15 7HT",
    "sg:province":"West Yorkshire",
    "sg:tags":[
        "contracting",
        "commercial"
    ],
    "wof:name":"Anthony Nicholas Cronian",
    "wof:placetype":"venue"
},
  "geometry": {"coordinates":[-1.474306,53.797142],"type":"Point"}
}