{
  "type": "Feature",
  "properties": {
    "iso:country":"GB",
    "sg:address":"Lodge Farm, Fenny Drayton",
    "sg:city":"Nuneaton",
    "sg:classifiers":[
        {
            "category":"Manufacturing",
            "subcategory":"Metals",
            "type":"Manufacturing & Wholesale Goods"
        }
    ],
    "sg:phone":"+44 1827 714535",
    "sg:postcode":"CV13 6BH",
    "sg:province":"Leicestershire",
    "sg:tags":[
        "steel",
        "fabricator",
        "erectors"
    ],
    "wof:name":"Art Fabrication",
    "wof:placetype":"venue"
},
  "geometry": {"coordinates":[-1.482594,52.566109],"type":"Point"}
}