{
  "type": "Feature",
  "properties": {
    "addr:full":"Old Barn, Penniment Farm, Penniment Lane Mansfield Derbyshire NG19 6PJ",
    "addr:housenumber":"penniment",
    "addr:postcode":"ng19 6pj",
    "addr:street":"Old;Penniment Lane",
    "iso:country":"GB",
    "sg:address":"Old Barn, Penniment Farm, Penniment Lane",
    "sg:city":"Mansfield",
    "sg:classifiers":[
        {
            "category":"Bars & Pubs",
            "subcategory":"Wine Bar",
            "type":"Food & Drink"
        }
    ],
    "sg:phone":"+44 1623 652458",
    "sg:postcode":"NG19 6PJ",
    "sg:province":"Derbyshire",
    "sg:tags":[
        "fitter"
    ],
    "wof:name":"Concept Interiors",
    "wof:placetype":"venue"
},
  "geometry": {"coordinates":[-1.227572,53.155804],"type":"Point"}
}