{
  "type": "Feature",
  "properties": {
    "iso:country":"GB",
    "sg:address":"1452 High Road",
    "sg:city":"London",
    "sg:classifiers":[
        {
            "category":"Shopping",
            "subcategory":"News",
            "type":"Retail Goods"
        }
    ],
    "sg:phone":"+44 20 8445 3518",
    "sg:postcode":"N20 9BS",
    "sg:province":"Greater London",
    "sg:tags":[
        "newsagent"
    ],
    "wof:name":"News Fare",
    "wof:placetype":"venue"
},
  "geometry": {"coordinates":[-0.176197,51.635502],"type":"Point"}
}