{
  "type": "Feature",
  "properties": {
    "iso:country":"GB",
    "sg:address":"Unit 2 Glendale Park, Fernbank Road",
    "sg:city":"Ascot",
    "sg:classifiers":[
        {
            "category":"Wholesale",
            "subcategory":"Medical Equipment & Supplies",
            "type":"Manufacturing & Wholesale Goods"
        }
    ],
    "sg:phone":"+44 1344 890916",
    "sg:postcode":"SL5 8JB",
    "sg:province":"Berkshire",
    "sg:tags":[
        "hospital"
    ],
    "wof:name":"Baxa Ltd.",
    "wof:placetype":"venue"
},
  "geometry": {"coordinates":[-0.686438,51.428268],"type":"Point"}
}