{
  "type": "Feature",
  "properties": {
    "iso:country":"GB",
    "sg:address":"53 Fosse Clo, London Rd",
    "sg:city":"Cirencester",
    "sg:classifiers":[
        {
            "category":"Professional",
            "subcategory":"Detective & Security Services",
            "type":"Services"
        }
    ],
    "sg:postcode":"GL7 1TB",
    "sg:province":"Gloucestershire",
    "sg:tags":[
        "agency"
    ],
    "wof:name":"Allen,Adrian,",
    "wof:placetype":"venue"
},
  "geometry": {"coordinates":[-1.9521080256,51.7201881409],"type":"Point"}
}