{
  "type": "Feature",
  "properties": {
    "addr:full":"23 Stringhams Copse, Sendmarsh, Ripley Woking Surrey GU23 6JE",
    "addr:housenumber":"23",
    "addr:postcode":"gu23 6je",
    "addr:street":"Stringhams Copse",
    "iso:country":"GB",
    "sg:address":"23 Stringhams Copse, Sendmarsh, Ripley",
    "sg:city":"Woking",
    "sg:classifiers":[
        {
            "category":"Professional",
            "type":"Services"
        },
        {
            "category":"Retail",
            "subcategory":"Laundry & Dry Cleaning",
            "type":"Services"
        }
    ],
    "sg:phone":"+44 1483 225385",
    "sg:postcode":"GU23 6JE",
    "sg:province":"Surrey",
    "sg:tags":[
        "ironing",
        "reflexologists",
        "home"
    ],
    "wof:name":"Reflexology by Suzanne",
    "wof:placetype":"venue"
},
  "geometry": {"coordinates":[-0.5099149942,51.2881584167],"type":"Point"}
}