{
  "type": "Feature",
  "properties": {
    "addr:full":"21 Station Road Woodhall Spa Lincolnshire LN10 6QL",
    "addr:housenumber":"21",
    "addr:postcode":"ln10 6ql",
    "addr:street":"Station Road",
    "iso:country":"GB",
    "sg:address":"21 Station Road",
    "sg:city":"Woodhall Spa",
    "sg:classifiers":[
        {
            "category":"Shopping",
            "subcategory":"Florist",
            "type":"Retail Goods"
        }
    ],
    "sg:phone":"+44 1526 354423",
    "sg:postcode":"LN10 6QL",
    "sg:province":"Lincolnshire",
    "wof:name":"Fleur' de' Lys",
    "wof:placetype":"venue"
},
  "geometry": {"coordinates":[-0.2181289941,53.1516532898],"type":"Point"}
}