{
  "type": "Feature",
  "properties": {
    "addr:full":"150 Mottram Road Stalybridge Greater Manchester SK15 2RF",
    "addr:housenumber":"150",
    "addr:postcode":"sk15 2rf",
    "addr:street":"Mottram Road",
    "iso:country":"GB",
    "sg:address":"150 Mottram Road",
    "sg:city":"Stalybridge",
    "sg:classifiers":[
        {
            "category":"Health Services",
            "subcategory":"Health Practitioner",
            "type":"Services"
        }
    ],
    "sg:postcode":"SK15 2RF",
    "sg:province":"Greater Manchester",
    "sg:tags":[
        "physiotherapist"
    ],
    "wof:name":"Brown Lawrie",
    "wof:placetype":"venue"
},
  "geometry": {"coordinates":[-2.043367,53.476845],"type":"Point"}
}