{
  "type": "Feature",
  "properties": {
    "addr:full":"4-6 Victoria Road Teddington Greater London TW11 0AZ",
    "addr:housenumber":"4-6",
    "addr:postcode":"tw11 0az",
    "addr:street":"Victoria Road",
    "iso:country":"GB",
    "sg:address":"4-6 Victoria Road",
    "sg:city":"Teddington",
    "sg:classifiers":[
        {
            "category":"Shopping",
            "subcategory":"News",
            "type":"Retail Goods"
        }
    ],
    "sg:postcode":"TW11 0AZ",
    "sg:province":"Greater London",
    "sg:tags":[
        "newsagent"
    ],
    "wof:name":"S & R TRADERS",
    "wof:placetype":"venue"
},
  "geometry": {"coordinates":[-0.333031,51.424213],"type":"Point"}
}