{
  "type": "Feature",
  "properties": {
    "addr:full":"18 Station Road, Manor Park London Greater London E12 5BT",
    "addr:housenumber":"18",
    "addr:postcode":"e12 5bt",
    "addr:street":"Station Road Manor",
    "iso:country":"GB",
    "sg:address":"18 Station Road, Manor Park",
    "sg:city":"London",
    "sg:classifiers":[
        {
            "category":"Manufacturing",
            "subcategory":"Tools & Machinery",
            "type":"Manufacturing & Wholesale Goods"
        }
    ],
    "sg:phone":"+44 20 8478 8203",
    "sg:postcode":"E12 5BT",
    "sg:province":"Greater London",
    "sg:tags":[
        "society",
        "friendly"
    ],
    "wof:name":"Brokerhouse Financial Services Ltd.",
    "wof:placetype":"venue"
},
  "geometry": {"coordinates":[0.0473419987,51.5515289307],"type":"Point"}
}