{
  "type": "Feature",
  "properties": {
    "addr:full":"45 Fifth Avenue Bolton Lancashire BL1 4LX",
    "addr:housenumber":"45",
    "addr:postcode":"bl1 4lx",
    "addr:street":"Fifth Avenue",
    "iso:country":"GB",
    "sg:address":"45 Fifth Avenue",
    "sg:city":"Bolton",
    "sg:classifiers":[
        {
            "category":"Education",
            "subcategory":"Special Training",
            "type":"Public Place"
        },
        {
            "category":"Professional",
            "subcategory":"Lawyer & Legal Services",
            "type":"Services"
        }
    ],
    "sg:phone":"+44 1204 845875",
    "sg:postcode":"BL1 4LX",
    "sg:province":"Lancashire",
    "sg:tags":[
        "product",
        "centre",
        "patent",
        "agent",
        "aid",
        "first"
    ],
    "wof:name":"I N F A C T First Aid Training",
    "wof:placetype":"venue"
},
  "geometry": {"coordinates":[-2.45927,53.57785],"type":"Point"}
}