{
  "type": "Feature",
  "properties": {
    "addr:full":"Unit 15b Challenge House, Sherwood Dr Milton Keynes Buckinghamshire MK3 6DP",
    "addr:housenumber":"unit 15b challenge house",
    "addr:postcode":"mk3 6dp",
    "addr:street":"Sherwood Dr",
    "iso:country":"GB",
    "sg:address":"Unit 15b Challenge House, Sherwood Dr",
    "sg:city":"Milton Keynes",
    "sg:classifiers":[
        {
            "category":"Travel",
            "subcategory":"Travel Agent",
            "type":"Entertainment"
        }
    ],
    "sg:phone":"+44 1908 631533",
    "sg:postcode":"MK3 6DP",
    "sg:province":"Buckinghamshire",
    "wof:name":"Lifestyle Promotions",
    "wof:placetype":"venue"
},
  "geometry": {"coordinates":[-0.7381759882,51.9985198975],"type":"Point"}
}