{
  "type": "Feature",
  "properties": {
    "addr:full":"Berkeley Ho, Victoria Av Harrogate North Yorkshire HG1 5PZ",
    "addr:postcode":"hg1 5pz",
    "addr:street":"Victoria Av",
    "iso:country":"GB",
    "sg:address":"Berkeley Ho, Victoria Av",
    "sg:city":"Harrogate",
    "sg:classifiers":[
        {
            "category":"Social Services",
            "type":"Services"
        }
    ],
    "sg:phone":"+44 1423 832800",
    "sg:postcode":"HG1 5PZ",
    "sg:province":"North Yorkshire",
    "sg:tags":[
        "benefit",
        "agency"
    ],
    "wof:name":"Benefits & Contributions",
    "wof:placetype":"venue"
},
  "geometry": {"coordinates":[-1.544524,53.99469],"type":"Point"}
}