{
  "type": "Feature",
  "properties": {
    "addr:full":"Southall Street Manchester Greater Manchester M3 1LG",
    "addr:postcode":"m3 1lg",
    "addr:street":"Southall Street",
    "iso:country":"GB",
    "sg:address":"Southall Street",
    "sg:city":"Manchester",
    "sg:classifiers":[
        {
            "category":"Wholesale",
            "subcategory":"Machinery & Supplies",
            "type":"Manufacturing & Wholesale Goods"
        }
    ],
    "sg:phone":"+44 161 832 0077",
    "sg:postcode":"M3 1LG",
    "sg:province":"Greater Manchester",
    "sg:tags":[
        "hydraulic"
    ],
    "wof:name":"M S C Platforms",
    "wof:placetype":"venue"
},
  "geometry": {"coordinates":[-2.245169,53.492367],"type":"Point"}
}