{
  "type": "Feature",
  "properties": {
    "addr:full":"Carlton Ho, 27a Carlton Dr London Greater London SW15 2BS",
    "addr:housenumber":"27a",
    "addr:postcode":"sw15 2bs",
    "addr:street":"Carlton Dr",
    "iso:country":"GB",
    "sg:address":"Carlton Ho, 27a Carlton Dr",
    "sg:city":"London",
    "sg:classifiers":[
        {
            "category":"Organizations",
            "subcategory":"Non-profit Organization",
            "type":"Services"
        }
    ],
    "sg:phone":"+44 20 8780 2841",
    "sg:postcode":"SW15 2BS",
    "sg:province":"Greater London",
    "sg:tags":[
        "organisation",
        "voluntary",
        "charity"
    ],
    "wof:name":"East European Partnership",
    "wof:placetype":"venue"
},
  "geometry": {"coordinates":[-0.21232,51.459309],"type":"Point"}
}