{
  "type": "Feature",
  "properties": {
    "addr:full":"15 Courtenay Street Newton Abbot Devon TQ12 2QH",
    "addr:housenumber":"15",
    "addr:postcode":"tq12 2qh",
    "addr:street":"Courtenay Street",
    "iso:country":"GB",
    "sg:address":"15 Courtenay Street",
    "sg:city":"Newton Abbot",
    "sg:classifiers":[
        {
            "category":"Communications",
            "subcategory":"Film & Video Production",
            "type":"Services"
        }
    ],
    "sg:phone":"+44 1626 366618",
    "sg:postcode":"TQ12 2QH",
    "sg:province":"Devon",
    "sg:tags":[
        "tv"
    ],
    "wof:name":"Granada U K Rental & Retail Ltd.",
    "wof:placetype":"venue"
},
  "geometry": {"coordinates":[-3.609759,50.530682],"type":"Point"}
}