{
  "type": "Feature",
  "properties": {
    "iso:country":"GB",
    "sg:address":"Stonebroom Industrial Estate, Stonebroom",
    "sg:city":"Derby",
    "sg:classifiers":[
        {
            "category":"Manufacturing",
            "subcategory":"Electronics",
            "type":"Manufacturing & Wholesale Goods"
        }
    ],
    "sg:phone":"+44 1773 875544",
    "sg:postcode":"DE55 6LQ",
    "sg:province":"Derbyshire",
    "sg:tags":[
        "control",
        "component",
        "-",
        "electronic"
    ],
    "wof:name":"Bluebell Industries Ltd.",
    "wof:placetype":"venue"
},
  "geometry": {"coordinates":[-1.389769,53.130531],"type":"Point"}
}