{
  "type": "Feature",
  "properties": {
    "addr:full":"Adelaide Dock, Endsleigh Road Southall Greater London UB2 5QR",
    "addr:postcode":"ub2 5qr",
    "addr:street":"Endsleigh Road",
    "iso:country":"GB",
    "sg:address":"Adelaide Dock, Endsleigh Road",
    "sg:city":"Southall",
    "sg:classifiers":[
        {
            "category":"Recreation",
            "subcategory":"Boat Charter",
            "type":"Entertainment"
        }
    ],
    "sg:phone":"+44 20 8571 5678",
    "sg:postcode":"UB2 5QR",
    "sg:province":"Greater London",
    "sg:tags":[
        "excursion"
    ],
    "wof:name":"Adelaide Marine Ltd.",
    "wof:placetype":"venue"
},
  "geometry": {"coordinates":[-0.383329004,51.4990997314],"type":"Point"}
}