{
  "type": "Feature",
  "properties": {
    "addr:full":"17 St Mary Street Chepstow Gloucestershire NP16 5EW",
    "addr:housenumber":"17",
    "addr:postcode":"np16 5ew",
    "addr:street":"St Mary Street",
    "iso:country":"GB",
    "sg:address":"17 St Mary Street",
    "sg:city":"Chepstow",
    "sg:classifiers":[
        {
            "category":"Restaurant",
            "type":"Food & Drink"
        }
    ],
    "sg:phone":"+44 1291 622959",
    "sg:postcode":"NP16 5EW",
    "sg:province":"Gloucestershire",
    "sg:tags":[
        "chinese"
    ],
    "wof:name":"Jade Restaurant",
    "wof:placetype":"venue"
},
  "geometry": {"coordinates":[-2.6743519306,51.642490387],"type":"Point"}
}