{
  "type": "Feature",
  "properties": {
    "iso:country":"GB",
    "sg:address":"Vulcan Close",
    "sg:city":"Whitstable",
    "sg:classifiers":[
        {
            "category":"Farming",
            "subcategory":"Nursery",
            "type":"Manufacturing & Wholesale Goods"
        },
        {
            "category":"Government",
            "subcategory":"Office",
            "type":"Public Place"
        }
    ],
    "sg:phone":"+44 1227 274435",
    "sg:postcode":"CT5 4LZ",
    "sg:province":"Kent",
    "sg:tags":[
        "creche",
        "agency",
        "education",
        "authority"
    ],
    "wof:name":"The Whitstable Nursery",
    "wof:placetype":"venue"
},
  "geometry": {"coordinates":[1.02054,51.349232],"type":"Point"}
}