{
  "type": "Feature",
  "properties": {
    "addr:full":"49 Piercefield Road, Freshfield Liverpool Lancashire L37 7DG",
    "addr:housenumber":"49",
    "addr:postcode":"l37 7dg",
    "addr:street":"Piercefield Road",
    "iso:country":"GB",
    "sg:address":"49 Piercefield Road, Freshfield",
    "sg:city":"Liverpool",
    "sg:classifiers":[
        {
            "category":"Personal",
            "subcategory":"Beauty Salon",
            "type":"Services"
        }
    ],
    "sg:phone":"+44 1704 872504",
    "sg:postcode":"L37 7DG",
    "sg:province":"Lancashire",
    "sg:tags":[
        "ladies",
        "lady",
        "hairdresser"
    ],
    "wof:name":"Hair Line",
    "wof:placetype":"venue"
},
  "geometry": {"coordinates":[-3.0592720509,53.5646324158],"type":"Point"}
}