{
  "type": "Feature",
  "properties": {
    "iso:country":"GB",
    "sg:address":"2 Devonshire Place",
    "sg:city":"London",
    "sg:classifiers":[
        {
            "category":"Health Services",
            "subcategory":"Dentist",
            "type":"Services"
        }
    ],
    "sg:phone":"+44 20 7224 7004",
    "sg:postcode":"W1G 6HJ",
    "sg:province":"Greater London",
    "wof:name":"Neil Kramer",
    "wof:placetype":"venue"
},
  "geometry": {"coordinates":[-0.1495960057,51.5217208862],"type":"Point"}
}