{
  "type": "Feature",
  "properties": {
    "iso:country":"GB",
    "sg:address":"1a Meadowbrook Road",
    "sg:city":"Dorking",
    "sg:classifiers":[
        {
            "category":"Personal",
            "subcategory":"Beauty Salon",
            "type":"Services"
        },
        {
            "category":"Personal",
            "subcategory":"Barber",
            "type":"Services"
        }
    ],
    "sg:phone":"+44 1306 882400",
    "sg:postcode":"RH4 1DH",
    "sg:province":"Surrey",
    "sg:tags":[
        "unisex",
        "hairdresser"
    ],
    "sg:website":"http://www.goldenscissors.co.uk",
    "wof:name":"The Golden Scissors",
    "wof:placetype":"venue"
},
  "geometry": {"coordinates":[-0.335072,51.232555],"type":"Point"}
}