{
  "type": "Feature",
  "properties": {
    "iso:country":"GB",
    "sg:address":"687 London Rd",
    "sg:city":"Westcliff-on-sea",
    "sg:classifiers":[
        {
            "category":"Real Estate",
            "subcategory":"Real Estate Agent",
            "type":"Services"
        }
    ],
    "sg:postcode":"SS0 9PA",
    "sg:province":"Essex",
    "wof:name":"Threshold",
    "wof:placetype":"venue"
},
  "geometry": {"coordinates":[0.682039,51.545742],"type":"Point"}
}