{
  "type": "Feature",
  "properties": {
    "addr:full":"Nottingham Road, Somercotes Alfreton Derbyshire DE55 4HQ",
    "addr:postcode":"de55 4hq",
    "addr:street":"Nottingham Road",
    "iso:country":"GB",
    "sg:address":"Nottingham Road, Somercotes",
    "sg:city":"Alfreton",
    "sg:classifiers":[
        {
            "category":"Bars & Pubs",
            "type":"Food & Drink"
        }
    ],
    "sg:phone":"+44 1773 602611",
    "sg:postcode":"DE55 4HQ",
    "sg:province":"Derbyshire",
    "sg:tags":[
        "pubs",
        "inn"
    ],
    "wof:name":"Cotes Park Inn",
    "wof:placetype":"venue"
},
  "geometry": {"coordinates":[-1.3710689545,53.0807609558],"type":"Point"}
}