{
  "type": "Feature",
  "properties": {
    "iso:country":"GB",
    "sg:address":"Lynnfield House, Church Street",
    "sg:city":"Altrincham",
    "sg:classifiers":[
        {
            "category":"Insurance",
            "subcategory":"Insurance Agent",
            "type":"Services"
        }
    ],
    "sg:phone":"+44 870 513 3218",
    "sg:postcode":"WA14 4DZ",
    "sg:province":"Cheshire",
    "sg:tags":[
        "broker"
    ],
    "wof:name":"Acumus Insurance Solutions Ltd.",
    "wof:placetype":"venue"
},
  "geometry": {"coordinates":[-2.35019207,53.3899917603],"type":"Point"}
}