{
  "type": "Feature",
  "properties": {
    "iso:country":"GB",
    "sg:address":"13 St Catherines Avenue, Catfield",
    "sg:city":"Great Yarmouth",
    "sg:classifiers":[
        {
            "category":"Military Area",
            "subcategory":"Air Force Base",
            "type":"Public Place"
        }
    ],
    "sg:postcode":"NR29 5AP",
    "sg:province":"Norfolk",
    "sg:tags":[
        "taxi",
        "hire",
        "private"
    ],
    "wof:name":"C A B",
    "wof:placetype":"venue"
},
  "geometry": {"coordinates":[1.536487,52.73774],"type":"Point"}
}