{
  "type": "Feature",
  "properties": {
    "addr:full":"Redberth Farm, Tiers Cross Haverfordwest Pembrokeshire SA62 3BZ",
    "addr:postcode":"sa62 3bz",
    "addr:street":"Cross",
    "iso:country":"GB",
    "sg:address":"Redberth Farm, Tiers Cross",
    "sg:city":"Haverfordwest",
    "sg:classifiers":[
        {
            "category":"Farming",
            "subcategory":"Livestock Farm",
            "type":"Manufacturing & Wholesale Goods"
        }
    ],
    "sg:phone":"+44 1437 890289",
    "sg:postcode":"SA62 3BZ",
    "sg:province":"Pembrokeshire",
    "sg:tags":[
        "others"
    ],
    "wof:name":"David W Jones",
    "wof:placetype":"venue"
},
  "geometry": {"coordinates":[-5.036426,51.755154],"type":"Point"}
}