{
  "type": "Feature",
  "properties": {
    "addr:full":"32 St James Street, New Bradwell Milton Keynes Buckinghamshire MK13 0BH",
    "addr:housenumber":"32",
    "addr:postcode":"mk13 0bh",
    "addr:street":"St James Street",
    "iso:country":"GB",
    "sg:address":"32 St James Street, New Bradwell",
    "sg:city":"Milton Keynes",
    "sg:classifiers":[
        {
            "category":"Shopping",
            "subcategory":"Pharmacy",
            "type":"Retail Goods"
        }
    ],
    "sg:phone":"+44 1908 313389",
    "sg:postcode":"MK13 0BH",
    "sg:province":"Buckinghamshire",
    "sg:tags":[
        "pharmacist",
        "chemist"
    ],
    "wof:name":"McLaren Chemists",
    "wof:placetype":"venue"
},
  "geometry": {"coordinates":[-0.793101,52.064533],"type":"Point"}
}