{
  "type": "Feature",
  "properties": {
    "addr:full":"Wyndineuk House, Salters Lane Tamworth Staffordshire B79 8BH",
    "addr:postcode":"b79 8bh",
    "addr:street":"Salters Lane",
    "iso:country":"GB",
    "sg:address":"Wyndineuk House, Salters Lane",
    "sg:city":"Tamworth",
    "sg:classifiers":[
        {
            "category":"Home & Garden",
            "subcategory":"Building Materials",
            "type":"Retail Goods"
        }
    ],
    "sg:phone":"+44 800 387877",
    "sg:postcode":"B79 8BH",
    "sg:province":"Staffordshire",
    "sg:tags":[
        "insulation",
        "installers"
    ],
    "wof:name":"Eco Roof",
    "wof:placetype":"venue"
},
  "geometry": {"coordinates":[-1.6980479956,52.6399154663],"type":"Point"}
}