{
  "type": "Feature",
  "properties": {
    "addr:full":"4 Chapel Hill, Tilehurst Reading Berkshire RG31 5DG",
    "addr:housenumber":"4",
    "addr:postcode":"rg31 5dg",
    "addr:street":"Chapel Hill",
    "iso:country":"GB",
    "sg:address":"4 Chapel Hill, Tilehurst",
    "sg:city":"Reading",
    "sg:classifiers":[
        {
            "category":"Health Services",
            "subcategory":"Doctor",
            "type":"Services"
        }
    ],
    "sg:phone":"+44 118 942 7177",
    "sg:postcode":"RG31 5DG",
    "sg:province":"Berkshire",
    "sg:tags":[
        "practitioners"
    ],
    "wof:name":"Chapel Hill Surgery",
    "wof:placetype":"venue"
},
  "geometry": {"coordinates":[-1.0439800024,51.457157135],"type":"Point"}
}