{
  "type": "Feature",
  "properties": {
    "iso:country":"GB",
    "sg:address":"3 Binchester Street, Simonside",
    "sg:city":"South Shields",
    "sg:classifiers":[
        {
            "category":"Shopping",
            "subcategory":"Crafts & Fabrics",
            "type":"Retail Goods"
        }
    ],
    "sg:phone":"+44 191 424 0112",
    "sg:postcode":"NE34 9AR",
    "sg:province":"Tyne and Wear",
    "sg:tags":[
        "shop",
        "needlecraft",
        "wool"
    ],
    "wof:name":"The Wool Shop",
    "wof:placetype":"venue"
},
  "geometry": {"coordinates":[-1.452644,54.969505],"type":"Point"}
}