{
  "type": "Feature",
  "properties": {
    "iso:country":"GB",
    "sg:address":"10 Moores Place",
    "sg:city":"Hungerford",
    "sg:classifiers":[
        {
            "category":"Professional",
            "subcategory":"Art Services",
            "type":"Services"
        },
        {
            "category":"Building & Trades",
            "subcategory":"Construction",
            "type":"Services"
        }
    ],
    "sg:postcode":"RG17 0JS",
    "sg:province":"Berkshire",
    "sg:tags":[
        "decorator",
        "painter"
    ],
    "wof:name":"Michael Richard Lambourn",
    "wof:placetype":"venue"
},
  "geometry": {"coordinates":[-1.520545,51.412785],"type":"Point"}
}