{
  "type": "Feature",
  "properties": {
    "addr:full":"Headley Mill Bordon Hampshire GU35 8RJ",
    "addr:postcode":"gu35 8rj",
    "addr:street":"Headley Mill",
    "iso:country":"GB",
    "sg:address":"Headley Mill",
    "sg:city":"Bordon",
    "sg:classifiers":[
        {
            "category":"Shopping",
            "subcategory":"Pets & Pet Supplies",
            "type":"Retail Goods"
        }
    ],
    "sg:phone":"+44 1420 472031",
    "sg:postcode":"GU35 8RJ",
    "sg:province":"Hampshire",
    "sg:tags":[
        "food"
    ],
    "wof:name":"J Ellis & Sons (Bordon) Ltd.",
    "wof:placetype":"venue"
},
  "geometry": {"coordinates":[-0.8207899928,51.1196250916],"type":"Point"}
}