{
  "type": "Feature",
  "properties": {
    "addr:full":"34 Orange Row Road, Terrington St Clement King's Lynn Lincolnshire PE34 4PD",
    "addr:housenumber":"34",
    "addr:postcode":"pe34 4pd",
    "addr:street":"Orange Row Road",
    "iso:country":"GB",
    "sg:address":"34 Orange Row Road, Terrington St Clement",
    "sg:city":"King's Lynn",
    "sg:classifiers":[
        {
            "category":"Freight",
            "type":"Transportation"
        }
    ],
    "sg:postcode":"PE34 4PD",
    "sg:province":"Lincolnshire",
    "sg:tags":[
        "haulage",
        "road"
    ],
    "wof:name":"Raymond W Howling",
    "wof:placetype":"venue"
},
  "geometry": {"coordinates":[0.2862100005,52.7623596191],"type":"Point"}
}