{
  "type": "Feature",
  "properties": {
    "addr:full":"P O Box 182 High Wycombe Buckinghamshire HP10 8RH",
    "addr:housenumber":"182",
    "addr:postcode":"hp10 8rh",
    "addr:street":"P O Box",
    "iso:country":"GB",
    "sg:address":"P O Box 182",
    "sg:city":"High Wycombe",
    "sg:classifiers":[
        {
            "category":"Professional",
            "subcategory":"Employment Agencies",
            "type":"Services"
        }
    ],
    "sg:phone":"+44 1494 816746",
    "sg:postcode":"HP10 8RH",
    "sg:province":"Buckinghamshire",
    "sg:tags":[
        "modelling"
    ],
    "wof:name":"Models Advance",
    "wof:placetype":"venue"
},
  "geometry": {"coordinates":[-0.6763579845,51.6313056946],"type":"Point"}
}