{
  "type": "Feature",
  "properties": {
    "addr:full":"48 Weston Road Doncaster South Yorkshire DN4 8NF",
    "addr:housenumber":"48",
    "addr:postcode":"dn4 8nf",
    "addr:street":"Weston Road",
    "iso:country":"GB",
    "sg:address":"48 Weston Road",
    "sg:city":"Doncaster",
    "sg:classifiers":[
        {
            "category":"Personal",
            "subcategory":"Beauty Salon",
            "type":"Services"
        }
    ],
    "sg:phone":"+44 1302 852116",
    "sg:postcode":"DN4 8NF",
    "sg:province":"South Yorkshire",
    "sg:tags":[
        "unisex",
        "hairdresser"
    ],
    "wof:name":"Weston Road Hair Studios",
    "wof:placetype":"venue"
},
  "geometry": {"coordinates":[-1.1444250345,53.4998321533],"type":"Point"}
}