{
  "type": "Feature",
  "properties": {
    "iso:country":"GB",
    "sg:address":"110 Wellingborough Rd",
    "sg:city":"Northampton",
    "sg:classifiers":[
        {
            "category":"Professional",
            "subcategory":"Business Services",
            "type":"Services"
        }
    ],
    "sg:postcode":"NN1 4DR",
    "sg:province":"Northamptonshire",
    "sg:tags":[
        "import",
        "export",
        "agent"
    ],
    "wof:name":"Dearden Trophies",
    "wof:placetype":"venue"
},
  "geometry": {"coordinates":[-0.883676,52.240971],"type":"Point"}
}