{
  "type": "Feature",
  "properties": {
    "iso:country":"GB",
    "sg:address":"Poundsbridge, Penshurst",
    "sg:city":"Tonbridge",
    "sg:classifiers":[
        {
            "category":"Retail",
            "subcategory":"Storage",
            "type":"Services"
        }
    ],
    "sg:phone":"+44 1892 861099",
    "sg:postcode":"TN11 8AP",
    "sg:province":"Kent",
    "sg:tags":[
        "recording",
        "equipment"
    ],
    "wof:name":"Sounds Incorporated",
    "wof:placetype":"venue"
},
  "geometry": {"coordinates":[0.183378,51.172852],"type":"Point"}
}