{
  "type": "Feature",
  "properties": {
    "iso:country":"GB",
    "sg:address":"51a North Down Road, Beacon Park",
    "sg:city":"Plymouth",
    "sg:classifiers":[
        {
            "category":"Shopping",
            "subcategory":"Computers & Home Electronics",
            "type":"Retail Goods"
        }
    ],
    "sg:phone":"+44 1752 564174",
    "sg:postcode":"PL2 3HL",
    "sg:province":"Devon",
    "sg:tags":[
        "electrical"
    ],
    "wof:name":"The Tradesman",
    "wof:placetype":"venue"
},
  "geometry": {"coordinates":[-4.156622,50.392082],"type":"Point"}
}