{
  "type": "Feature",
  "properties": {
    "addr:full":"Huntingdon Road Cambridge Cambridgeshire CB3 0JJ",
    "addr:postcode":"cb3 0jj",
    "addr:street":"Huntingdon Road",
    "iso:country":"GB",
    "sg:address":"Huntingdon Road",
    "sg:city":"Cambridge",
    "sg:classifiers":[
        {
            "category":"Retail",
            "subcategory":"Funeral Services",
            "type":"Services"
        },
        {
            "category":"Government",
            "subcategory":"Office",
            "type":"Public Place"
        }
    ],
    "sg:phone":"+44 1954 780681",
    "sg:postcode":"CB3 0JJ",
    "sg:province":"Cambridgeshire",
    "sg:tags":[
        "cemetery",
        "local",
        "crematorium"
    ],
    "wof:name":"Cambridge City Crematorium",
    "wof:placetype":"venue"
},
  "geometry": {"coordinates":[0.0949449986,52.221950531],"type":"Point"}
}