{
  "type": "Feature",
  "properties": {
    "addr:full":"Derby Sq Liverpool Merseyside L2 7SD",
    "addr:postcode":"l2 7sd",
    "addr:street":"Derby Sq",
    "iso:country":"GB",
    "sg:address":"Derby Sq",
    "sg:city":"Liverpool",
    "sg:classifiers":[
        {
            "category":"Government",
            "subcategory":"Office",
            "type":"Public Place"
        }
    ],
    "sg:phone":"+44 151 236 6363",
    "sg:postcode":"L2 7SD",
    "sg:province":"Merseyside",
    "sg:tags":[
        "armed",
        "reserve"
    ],
    "wof:name":"RHQ The Kings Regiment",
    "wof:placetype":"venue"
},
  "geometry": {"coordinates":[-2.9900341034,53.4051895142],"type":"Point"}
}