{
  "type": "Feature",
  "properties": {
    "addr:full":"72 Pennine La, Golborne Warrington Cheshire WA3 3HF",
    "addr:housenumber":"72",
    "addr:postcode":"wa3 3hf",
    "addr:street":"Pennine La Golborne",
    "iso:country":"GB",
    "sg:address":"72 Pennine La, Golborne",
    "sg:city":"Warrington",
    "sg:classifiers":[
        {
            "category":"Building & Trades",
            "subcategory":"Construction",
            "type":"Services"
        }
    ],
    "sg:postcode":"WA3 3HF",
    "sg:province":"Cheshire",
    "sg:tags":[
        "contractor",
        "paving",
        "driveway"
    ],
    "wof:name":"Evans,David,",
    "wof:placetype":"venue"
},
  "geometry": {"coordinates":[-2.582189,53.480255],"type":"Point"}
}