{
  "type": "Feature",
  "properties": {
    "addr:full":"Lewis Road, Selsey Chichester West Sussex PO20 0RG",
    "addr:postcode":"po20 0rg",
    "addr:street":"Lewis Road",
    "iso:country":"GB",
    "sg:address":"Lewis Road, Selsey",
    "sg:city":"Chichester",
    "sg:classifiers":[
        {
            "category":"Autos & Motor Vehicles",
            "subcategory":"Automobile Sales",
            "type":"Retail Goods"
        }
    ],
    "sg:phone":"+44 1243 607607",
    "sg:postcode":"PO20 0RG",
    "sg:province":"West Sussex",
    "sg:tags":[
        "car"
    ],
    "wof:name":"The Selsey Motor Co",
    "wof:placetype":"venue"
},
  "geometry": {"coordinates":[-0.7829189897,50.7417106628],"type":"Point"}
}