{
  "type": "Feature",
  "properties": {
    "addr:full":"Trafford Bank House, 32 Brindley Road Manchester Cheshire M16 9SD",
    "addr:housenumber":"32",
    "addr:postcode":"m16 9sd",
    "addr:street":"Brindley Road",
    "iso:country":"GB",
    "sg:address":"Trafford Bank House, 32 Brindley Road",
    "sg:city":"Manchester",
    "sg:classifiers":[
        {
            "category":"Home & Garden",
            "subcategory":"Hardware",
            "type":"Retail Goods"
        },
        {
            "category":"Building & Trades",
            "subcategory":"Electrical",
            "type":"Services"
        }
    ],
    "sg:phone":"+44 161 876 9141",
    "sg:postcode":"M16 9SD",
    "sg:province":"Cheshire",
    "sg:tags":[
        "retailer",
        "lighting",
        "consultant"
    ],
    "wof:name":"THE LIGHTING MAINTENANCE CO",
    "wof:placetype":"venue"
},
  "geometry": {"coordinates":[-2.275069,53.465019],"type":"Point"}
}