{
  "type": "Feature",
  "properties": {
    "addr:full":"11 Raleigh Road London Greater London SE20 7JE",
    "addr:housenumber":"11",
    "addr:postcode":"se20 7je",
    "addr:street":"Raleigh Road",
    "iso:country":"GB",
    "sg:address":"11 Raleigh Road",
    "sg:city":"London",
    "sg:classifiers":[
        {
            "category":"Building & Trades",
            "subcategory":"Construction",
            "type":"Services"
        }
    ],
    "sg:phone":"+44 20 8776 8278",
    "sg:postcode":"SE20 7JE",
    "sg:province":"Greater London",
    "sg:tags":[
        "roofing"
    ],
    "wof:name":"Claret Roofing",
    "wof:placetype":"venue"
},
  "geometry": {"coordinates":[-0.051066,51.414791],"type":"Point"}
}