{
  "type": "Feature",
  "properties": {
    "addr:full":"Unit 14 Western Industrial Estate, Honeybourne Evesham Gloucestershire WR11 7QB",
    "addr:housenumber":"unit 14",
    "addr:postcode":"wr11 7qb",
    "addr:street":"Western Industrial Estate",
    "iso:country":"GB",
    "sg:address":"Unit 14 Western Industrial Estate, Honeybourne",
    "sg:city":"Evesham",
    "sg:classifiers":[
        {
            "category":"Building & Trades",
            "subcategory":"Electrical",
            "type":"Services"
        }
    ],
    "sg:phone":"+44 1386 849010",
    "sg:postcode":"WR11 7QB",
    "sg:province":"Gloucestershire",
    "sg:tags":[
        "lighting"
    ],
    "wof:name":"David Barton International Ltd.",
    "wof:placetype":"venue"
},
  "geometry": {"coordinates":[-1.830432,52.093491],"type":"Point"}
}