{
  "type": "Feature",
  "properties": {
    "iso:country":"GB",
    "sg:address":"Masonic Lodge, 41 Bo'ness Road",
    "sg:city":"Grangemouth",
    "sg:classifiers":[
        {
            "category":"Government",
            "subcategory":"Police Station",
            "type":"Public Place"
        },
        {
            "category":"Organizations",
            "subcategory":"Non-profit Organization",
            "type":"Services"
        }
    ],
    "sg:phone":"+44 1324 877777",
    "sg:postcode":"FK3 8AN",
    "sg:province":"Falkirk",
    "sg:tags":[
        "organisation",
        "force",
        "voluntary",
        "charity"
    ],
    "wof:name":"Great Priory of Scotland",
    "wof:placetype":"venue"
},
  "geometry": {"coordinates":[-3.723894,56.009331],"type":"Point"}
}