{
  "type": "Feature",
  "properties": {
    "iso:country":"GB",
    "sg:address":"66 Church Road",
    "sg:city":"Manchester",
    "sg:classifiers":[
        {
            "category":"Shopping",
            "subcategory":"News",
            "type":"Retail Goods"
        }
    ],
    "sg:postcode":"M22 4NW",
    "sg:province":"Greater Manchester",
    "sg:tags":[
        "newsagent"
    ],
    "wof:name":"K's News",
    "wof:placetype":"venue"
},
  "geometry": {"coordinates":[-2.256008,53.407261],"type":"Point"}
}