{
  "type": "Feature",
  "properties": {
    "addr:full":"5 Tregarrick Looe Cornwall PL13 2SD",
    "addr:housenumber":"5",
    "addr:postcode":"pl13 2sd",
    "addr:street":"Tregarrick",
    "iso:country":"GB",
    "sg:address":"5 Tregarrick",
    "sg:city":"Looe",
    "sg:classifiers":[
        {
            "category":"Arts & Performance",
            "subcategory":"Music",
            "type":"Entertainment"
        }
    ],
    "sg:postcode":"PL13 2SD",
    "sg:province":"Cornwall",
    "sg:tags":[
        "mobile",
        "disco"
    ],
    "wof:name":"Faulkners Flight Mobile",
    "wof:placetype":"venue"
},
  "geometry": {"coordinates":[-4.464207,50.35463],"type":"Point"}
}