{
  "type": "Feature",
  "properties": {
    "iso:country":"GB",
    "sg:address":"15 Sunningdale Close, Swinton",
    "sg:city":"Mexborough",
    "sg:classifiers":[
        {
            "category":"Health Services",
            "subcategory":"Podiatrist",
            "type":"Services"
        }
    ],
    "sg:postcode":"S64 8SS",
    "sg:province":"South Yorkshire",
    "sg:tags":[
        "podiatrists",
        "chiropodist"
    ],
    "wof:name":"Stephen Willey",
    "wof:placetype":"venue"
},
  "geometry": {"coordinates":[-1.308751,53.480907],"type":"Point"}
}