{
  "type": "Feature",
  "properties": {
    "iso:country":"GB",
    "sg:address":"Unit 2 Air Ministry Site, Caistor Road, Holton Le Moor",
    "sg:city":"Market Rasen",
    "sg:classifiers":[
        {
            "category":"Retail",
            "subcategory":"Repair Shop",
            "type":"Services"
        },
        {
            "category":"Farming",
            "subcategory":"Farm",
            "type":"Manufacturing & Wholesale Goods"
        }
    ],
    "sg:phone":"+44 1673 828883",
    "sg:postcode":"LN7 6AH",
    "sg:province":"Lincolnshire",
    "sg:tags":[
        "agricultural",
        "sale",
        "machinery"
    ],
    "sg:website":"http://www.nytractorparts.co.uk",
    "wof:name":"Nick Young",
    "wof:placetype":"venue"
},
  "geometry": {"coordinates":[-0.374074012,53.4672546387],"type":"Point"}
}