{
  "type": "Feature",
  "properties": {
    "addr:full":"170 Lanark Road West Currie City of Edinburgh EH14 5NY",
    "addr:housenumber":"170",
    "addr:postcode":"eh14 5ny",
    "addr:street":"Lanark Road West",
    "iso:country":"GB",
    "sg:address":"170 Lanark Road West",
    "sg:city":"Currie",
    "sg:classifiers":[
        {
            "category":"Retail",
            "subcategory":"Auto Repair",
            "type":"Services"
        }
    ],
    "sg:phone":"+44 131 449 5751",
    "sg:postcode":"EH14 5NY",
    "sg:province":"City of Edinburgh",
    "sg:tags":[
        "modification",
        "garage",
        "related"
    ],
    "wof:name":"Hope Scott Garage",
    "wof:placetype":"venue"
},
  "geometry": {"coordinates":[-3.307101965,55.8968391418],"type":"Point"}
}