{
  "type": "Feature",
  "properties": {
    "addr:full":"312 Norwich Road Ipswich Suffolk IP1 4HD",
    "addr:housenumber":"312",
    "addr:postcode":"ip1 4hd",
    "addr:street":"Norwich Road",
    "iso:country":"GB",
    "sg:address":"312 Norwich Road",
    "sg:city":"Ipswich",
    "sg:classifiers":[
        {
            "category":"Travel",
            "subcategory":"Hotels & Motels",
            "type":"Entertainment"
        }
    ],
    "sg:phone":"+44 1473 464796",
    "sg:postcode":"IP1 4HD",
    "sg:province":"Suffolk",
    "sg:tags":[
        "house",
        "guest"
    ],
    "wof:name":"Bosmere Hotel",
    "wof:placetype":"venue"
},
  "geometry": {"coordinates":[1.137263,52.067711],"type":"Point"}
}