{
  "type": "Feature",
  "properties": {
    "addr:full":"196 Northgate Darlington Durham DL1 1QU",
    "addr:housenumber":"196",
    "addr:postcode":"dl1 1qu",
    "addr:street":"Northgate",
    "iso:country":"GB",
    "sg:address":"196 Northgate",
    "sg:city":"Darlington",
    "sg:classifiers":[
        {
            "category":"Restaurant",
            "type":"Food & Drink"
        }
    ],
    "sg:phone":"+44 1325 461222",
    "sg:postcode":"DL1 1QU",
    "sg:province":"Durham",
    "wof:name":"Sardis",
    "wof:placetype":"venue"
},
  "geometry": {"coordinates":[-1.552456975,54.5305671692],"type":"Point"}
}