{
  "type": "Feature",
  "properties": {
    "addr:full":"29a Macleod St Nelson Lancashire BB9 7HE",
    "addr:housenumber":"29a",
    "addr:postcode":"bb9 7he",
    "addr:street":"Macleod St",
    "iso:country":"GB",
    "sg:address":"29a Macleod St",
    "sg:city":"Nelson",
    "sg:classifiers":[
        {
            "category":"Banks & Credit Unions",
            "subcategory":"Financial Services",
            "type":"Services"
        }
    ],
    "sg:phone":"+44 1282 699899",
    "sg:postcode":"BB9 7HE",
    "sg:province":"Lancashire",
    "sg:tags":[
        "consultant"
    ],
    "wof:name":"City Mortgage & Finance Mortgage",
    "wof:placetype":"venue"
},
  "geometry": {"coordinates":[-2.2202620506,53.8360824585],"type":"Point"}
}