{
  "type": "Feature",
  "properties": {
    "addr:full":"2 Stainbeck Avenue Leeds West Yorkshire LS7 2PA",
    "addr:housenumber":"2",
    "addr:postcode":"ls7 2pa",
    "addr:street":"Stainbeck Avenue",
    "iso:country":"GB",
    "sg:address":"2 Stainbeck Avenue",
    "sg:city":"Leeds",
    "sg:classifiers":[
        {
            "category":"Retail",
            "subcategory":"Repair Shop",
            "type":"Services"
        },
        {
            "category":"Manufacturing",
            "subcategory":"Furniture",
            "type":"Manufacturing & Wholesale Goods"
        }
    ],
    "sg:postcode":"LS7 2PA",
    "sg:province":"West Yorkshire",
    "sg:tags":[
        "mnfr",
        "upholstering",
        "upholsterer"
    ],
    "wof:name":"R H Dickinson",
    "wof:placetype":"venue"
},
  "geometry": {"coordinates":[-1.565841,53.828472],"type":"Point"}
}