{
  "type": "Feature",
  "properties": {
    "addr:full":"24 Yeomans Close Bishops Stortford Essex CM23 4EU",
    "addr:housenumber":"24",
    "addr:postcode":"cm23 4eu",
    "addr:street":"Yeomans Close",
    "iso:country":"GB",
    "sg:address":"24 Yeomans Close",
    "sg:city":"Bishops Stortford",
    "sg:classifiers":[
        {
            "category":"Organizations",
            "subcategory":"Non-profit Organization",
            "type":"Services"
        }
    ],
    "sg:phone":"+44 1279 461841",
    "sg:postcode":"CM23 4EU",
    "sg:province":"Essex",
    "sg:tags":[
        "alarm",
        "system"
    ],
    "wof:name":"Gold Seal Security Installations",
    "wof:placetype":"venue"
},
  "geometry": {"coordinates":[0.145665,51.863804],"type":"Point"}
}