{
  "type": "Feature",
  "properties": {
    "iso:country":"GB",
    "sg:address":"73 Newington Road",
    "sg:city":"Ramsgate",
    "sg:classifiers":[
        {
            "category":"Shopping",
            "subcategory":"News",
            "type":"Retail Goods"
        }
    ],
    "sg:phone":"+44 1843 591915",
    "sg:postcode":"CT12 6PP",
    "sg:province":"Kent",
    "sg:tags":[
        "newsagent"
    ],
    "wof:name":"Surykant C Patel",
    "wof:placetype":"venue"
},
  "geometry": {"coordinates":[1.398925,51.344444],"type":"Point"}
}