{
  "type": "Feature",
  "properties": {
    "addr:full":"566 Queensferry Rd Edinburgh City of Edinburgh EH4 6AT",
    "addr:housenumber":"566",
    "addr:postcode":"eh4 6at",
    "addr:street":"Queensferry Rd",
    "iso:country":"GB",
    "sg:address":"566 Queensferry Rd",
    "sg:city":"Edinburgh",
    "sg:classifiers":[
        {
            "category":"Building & Trades",
            "subcategory":"Construction",
            "type":"Services"
        }
    ],
    "sg:phone":"+44 131 339 4417",
    "sg:postcode":"EH4 6AT",
    "sg:province":"City of Edinburgh",
    "sg:tags":[
        "demolition",
        "contractor"
    ],
    "wof:name":"C M I Contractors Ltd",
    "wof:placetype":"venue"
},
  "geometry": {"coordinates":[-3.2987520695,55.9751777649],"type":"Point"}
}