{
  "type": "Feature",
  "properties": {
    "addr:full":"34 Glynwood Gardens Gateshead Tyne and Wear NE9 5RS",
    "addr:housenumber":"34",
    "addr:postcode":"ne9 5rs",
    "addr:street":"Glynwood Gardens",
    "iso:country":"GB",
    "sg:address":"34 Glynwood Gardens",
    "sg:city":"Gateshead",
    "sg:classifiers":[
        {
            "category":"Building & Trades",
            "subcategory":"Plumbing",
            "type":"Services"
        }
    ],
    "sg:phone":"+44 191 482 0912",
    "sg:postcode":"NE9 5RS",
    "sg:province":"Tyne and Wear",
    "sg:tags":[
        "heating"
    ],
    "wof:name":"Longbank Plumbing & Heating Services",
    "wof:placetype":"venue"
},
  "geometry": {"coordinates":[-1.588443,54.936783],"type":"Point"}
}