{
  "type": "Feature",
  "properties": {
    "iso:country":"GB",
    "sg:address":"St Johns Hill",
    "sg:city":"Wareham",
    "sg:classifiers":[
        {
            "category":"Bars & Pubs",
            "type":"Food & Drink"
        }
    ],
    "sg:phone":"+44 1929 552995",
    "sg:postcode":"BH20 4LZ",
    "sg:province":"Dorset",
    "sg:tags":[
        "pubs",
        "inn"
    ],
    "wof:name":"Horse & Groom Inn",
    "wof:placetype":"venue"
},
  "geometry": {"coordinates":[-2.108365,50.685326],"type":"Point"}
}