{
  "type": "Feature",
  "properties": {
    "addr:full":"64 Tanylan Terr Swansea Swansea SA6 7DU",
    "addr:housenumber":"64",
    "addr:postcode":"sa6 7du",
    "addr:street":"Tanylan Terr",
    "iso:country":"GB",
    "sg:address":"64 Tanylan Terr",
    "sg:city":"Swansea",
    "sg:classifiers":[
        {
            "category":"Food & Beverages",
            "subcategory":"Supermarket",
            "type":"Retail Goods"
        }
    ],
    "sg:phone":"+44 1792 790999",
    "sg:postcode":"SA6 7DU",
    "sg:province":"Swansea",
    "sg:tags":[
        "frozen"
    ],
    "wof:name":"Spicey Bite",
    "wof:placetype":"venue"
},
  "geometry": {"coordinates":[-3.932051,51.664581],"type":"Point"}
}