{
  "type": "Feature",
  "properties": {
    "addr:full":"127-129 Portland Street Manchester Greater Manchester M1 4PZ",
    "addr:housenumber":"127-129",
    "addr:postcode":"m1 4pz",
    "addr:street":"Portland Street",
    "iso:country":"GB",
    "sg:address":"127-129 Portland Street",
    "sg:city":"Manchester",
    "sg:classifiers":[
        {
            "category":"Professional",
            "subcategory":"Management & Consulting",
            "type":"Services"
        }
    ],
    "sg:postcode":"M1 4PZ",
    "sg:province":"Greater Manchester",
    "sg:tags":[
        "consultant",
        "business"
    ],
    "wof:name":"Whitmuir Ltd",
    "wof:placetype":"venue"
},
  "geometry": {"coordinates":[-2.241687,53.476437],"type":"Point"}
}