{
  "type": "Feature",
  "properties": {
    "iso:country":"GB",
    "sg:address":"47-49 Howard Street",
    "sg:city":"Birmingham",
    "sg:classifiers":[
        {
            "category":"Manufacturing",
            "subcategory":"Wood Products",
            "type":"Manufacturing & Wholesale Goods"
        }
    ],
    "sg:phone":"+44 121 236 5937",
    "sg:postcode":"B19 3HL",
    "sg:province":"West Midlands",
    "sg:tags":[
        "packaging",
        "crate",
        "pallets"
    ],
    "wof:name":"J Walters & Co. Ltd.",
    "wof:placetype":"venue"
},
  "geometry": {"coordinates":[-1.904466,52.488262],"type":"Point"}
}