{
  "type": "Feature",
  "properties": {
    "iso:country":"GB",
    "sg:address":"Redburn Rd, Westerhope",
    "sg:city":"Newcastle Upon Tyne",
    "sg:classifiers":[
        {
            "category":"Home & Garden",
            "subcategory":"Hardware",
            "type":"Retail Goods"
        }
    ],
    "sg:phone":"+44 191 214 6009",
    "sg:postcode":"NE5 1NB",
    "sg:province":"Tyne and Wear",
    "sg:tags":[
        "part",
        "accessory"
    ],
    "wof:name":"C F Motor Cycles",
    "wof:placetype":"venue"
},
  "geometry": {"coordinates":[-1.69357,55.003262],"type":"Point"}
}