{
  "type": "Feature",
  "properties": {
    "iso:country":"GB",
    "sg:address":"Ruishton Primary School, Newlands Road, Ruishton",
    "sg:city":"Taunton",
    "sg:classifiers":[
        {
            "category":"Social Services",
            "subcategory":"Child Care",
            "type":"Services"
        }
    ],
    "sg:phone":"+44 1823 444248",
    "sg:postcode":"TA3 5JZ",
    "sg:province":"Devon",
    "sg:tags":[
        "childminders"
    ],
    "wof:name":"Ruishton Rascals Out of School Club",
    "wof:placetype":"venue"
},
  "geometry": {"coordinates":[-3.051654,51.019932],"type":"Point"}
}