{
  "type": "Feature",
  "properties": {
    "addr:full":"12 Lonsdale Gardens Tunbridge Wells Kent TN1 1PA",
    "addr:housenumber":"12",
    "addr:postcode":"tn1 1pa",
    "addr:street":"Lonsdale Gardens;Wells",
    "iso:country":"GB",
    "sg:address":"12 Lonsdale Gardens",
    "sg:city":"Tunbridge Wells",
    "sg:classifiers":[
        {
            "category":"Professional",
            "subcategory":"Management & Consulting",
            "type":"Services"
        }
    ],
    "sg:postcode":"TN1 1PA",
    "sg:province":"Kent",
    "sg:tags":[
        "consultant",
        "business"
    ],
    "wof:name":"Kingsbridge Consultancy (Kent) Ltd",
    "wof:placetype":"venue"
},
  "geometry": {"coordinates":[0.2616809905,51.1311569214],"type":"Point"}
}