{
  "type": "Feature",
  "properties": {
    "addr:full":"17 Hever Close Maidstone Kent ME15 8SR",
    "addr:housenumber":"17",
    "addr:postcode":"me15 8sr",
    "addr:street":"Hever Close",
    "iso:country":"GB",
    "sg:address":"17 Hever Close",
    "sg:city":"Maidstone",
    "sg:classifiers":[
        {
            "category":"Home & Garden",
            "subcategory":"Building Materials",
            "type":"Retail Goods"
        }
    ],
    "sg:phone":"+44 1622 677170",
    "sg:postcode":"ME15 8SR",
    "sg:province":"Kent",
    "sg:tags":[
        "furnishers",
        "bathroom",
        "planner"
    ],
    "wof:name":"Bathrooms Complete",
    "wof:placetype":"venue"
},
  "geometry": {"coordinates":[0.55819,51.247044],"type":"Point"}
}