{
  "type": "Feature",
  "properties": {
    "addr:full":"Unit 27, Riverside Quay Haverfordwest Pembrokeshire SA61 2LJ",
    "addr:housenumber":"unit 27",
    "addr:postcode":"sa61 2lj",
    "addr:street":"Riverside Quay",
    "iso:country":"GB",
    "sg:address":"Unit 27, Riverside Quay",
    "sg:city":"Haverfordwest",
    "sg:classifiers":[
        {
            "category":"Travel",
            "subcategory":"Travel Agent",
            "type":"Entertainment"
        }
    ],
    "sg:phone":"+44 1437 766887",
    "sg:postcode":"SA61 2LJ",
    "sg:province":"Pembrokeshire",
    "wof:name":"Lunn Poly Ltd.",
    "wof:placetype":"venue"
},
  "geometry": {"coordinates":[-4.977350235,51.7987632751],"type":"Point"}
}