{
  "type": "Feature",
  "properties": {
    "iso:country":"GB",
    "sg:address":"9 Darell Croft",
    "sg:city":"Sutton Coldfield",
    "sg:classifiers":[
        {
            "category":"Manufacturing",
            "subcategory":"Buildings",
            "type":"Manufacturing & Wholesale Goods"
        }
    ],
    "sg:postcode":"B76 1HU",
    "sg:province":"Warwickshire",
    "sg:tags":[
        "shed",
        "greenhouse"
    ],
    "wof:name":"Dovetail Building Developments Ltd.",
    "wof:placetype":"venue"
},
  "geometry": {"coordinates":[-1.80606,52.556107],"type":"Point"}
}