{
  "type": "Feature",
  "properties": {
    "addr:full":"Thorpe Farm, Wretham Thetford Norfolk IP24 1RG",
    "addr:housenumber":"wretham",
    "addr:postcode":"ip24 1rg",
    "iso:country":"GB",
    "sg:address":"Thorpe Farm, Wretham",
    "sg:city":"Thetford",
    "sg:classifiers":[
        {
            "category":"Farming",
            "subcategory":"Livestock Farm",
            "type":"Manufacturing & Wholesale Goods"
        }
    ],
    "sg:postcode":"IP24 1RG",
    "sg:province":"Norfolk",
    "sg:tags":[
        "others"
    ],
    "wof:name":"R G Abrey",
    "wof:placetype":"venue"
},
  "geometry": {"coordinates":[0.8308249712,52.4743232727],"type":"Point"}
}