{
  "type": "Feature",
  "properties": {
    "addr:full":"Priory Aveune High Wycombe Buckinghamshire HP13 6SG",
    "addr:postcode":"hp13 6sg",
    "addr:street":"Priory",
    "iso:country":"GB",
    "sg:address":"Priory Aveune",
    "sg:city":"High Wycombe",
    "sg:classifiers":[
        {
            "category":"Education",
            "subcategory":"School",
            "type":"Public Place"
        }
    ],
    "sg:phone":"+44 1494 522231",
    "sg:postcode":"HP13 6SG",
    "sg:province":"Buckinghamshire",
    "sg:tags":[
        "college",
        "local",
        "authority"
    ],
    "wof:name":"Hamilton Primary School",
    "wof:placetype":"venue"
},
  "geometry": {"coordinates":[-0.7477890253,51.628944397],"type":"Point"}
}