{
  "type": "Feature",
  "properties": {
    "iso:country":"GB",
    "sg:address":"The Street, Oaksey",
    "sg:city":"Malmesbury",
    "sg:classifiers":[
        {
            "category":"Community Center",
            "subcategory":"Youth",
            "type":"Public Place"
        }
    ],
    "sg:phone":"+44 1666 577737",
    "sg:postcode":"SN16 9TG",
    "sg:province":"Wiltshire",
    "sg:tags":[
        "organisation",
        "centre"
    ],
    "wof:name":"Oaksey Youth Centre",
    "wof:placetype":"venue"
},
  "geometry": {"coordinates":[-2.054764,51.599155],"type":"Point"}
}