{
  "type": "Feature",
  "properties": {
    "addr:full":"7a Oliver Place Hawick Cumbria TD9 9BG",
    "addr:housenumber":"7a",
    "addr:postcode":"td9 9bg",
    "addr:street":"Oliver Place Hawick",
    "iso:country":"GB",
    "sg:address":"7a Oliver Place",
    "sg:city":"Hawick",
    "sg:classifiers":[
        {
            "category":"Shopping",
            "subcategory":"Clothing, Apparel, & Fashions",
            "type":"Retail Goods"
        }
    ],
    "sg:phone":"+44 1450 370103",
    "sg:postcode":"TD9 9BG",
    "sg:province":"Cumbria",
    "sg:tags":[
        "haberdasher"
    ],
    "wof:name":"Fun 2 Do",
    "wof:placetype":"venue"
},
  "geometry": {"coordinates":[-2.774515,55.428593],"type":"Point"}
}