{
  "type": "Feature",
  "properties": {
    "iso:country":"GB",
    "sg:address":"4 Dorset Clo",
    "sg:city":"Chesterfield",
    "sg:classifiers":[
        {
            "category":"Building & Trades",
            "subcategory":"Construction",
            "type":"Services"
        }
    ],
    "sg:phone":"+44 1246 221704",
    "sg:postcode":"S43 1DW",
    "sg:province":"Derbyshire",
    "sg:tags":[
        "roofing"
    ],
    "wof:name":"K S Mason",
    "wof:placetype":"venue"
},
  "geometry": {"coordinates":[-1.38897,53.259907],"type":"Point"}
}