{
  "type": "Feature",
  "properties": {
    "iso:country":"GB",
    "sg:address":"21 Eaglesham Road, Clarkston",
    "sg:city":"Glasgow",
    "sg:classifiers":[
        {
            "category":"Shopping",
            "subcategory":"Clothing, Apparel, & Fashions",
            "type":"Retail Goods"
        }
    ],
    "sg:postcode":"G76 7DH",
    "sg:province":"East Renfrewshire",
    "sg:tags":[
        "shop"
    ],
    "wof:name":"Extra Elegance Ltd.",
    "wof:placetype":"venue"
},
  "geometry": {"coordinates":[-4.275041,55.784466],"type":"Point"}
}