{
  "type": "Feature",
  "properties": {
    "iso:country":"GB",
    "sg:address":"8 Four Crosses Rd, Shelfield",
    "sg:city":"Walsall",
    "sg:classifiers":[
        {
            "category":"Health Services",
            "subcategory":"Doctor",
            "type":"Services"
        }
    ],
    "sg:phone":"+44 1922 682232",
    "sg:postcode":"WS4 1PR",
    "sg:province":"West Midlands",
    "sg:tags":[
        "practitioners"
    ],
    "wof:name":"Drs Green Peters Edwards & Askey",
    "wof:placetype":"venue"
},
  "geometry": {"coordinates":[-1.9517320395,52.617729187],"type":"Point"}
}