{
  "type": "Feature",
  "properties": {
    "addr:full":"11 Nugent Terrace London Greater London NW8 9QB",
    "addr:housenumber":"11",
    "addr:postcode":"nw8 9qb",
    "addr:street":"Nugent Terrace",
    "iso:country":"GB",
    "sg:address":"11 Nugent Terrace",
    "sg:city":"London",
    "sg:classifiers":[
        {
            "category":"Shopping",
            "subcategory":"Department Store",
            "type":"Retail Goods"
        }
    ],
    "sg:phone":"+44 20 7286 1684",
    "sg:postcode":"NW8 9QB",
    "sg:province":"Greater London",
    "wof:name":"Corner Shop",
    "wof:placetype":"venue"
},
  "geometry": {"coordinates":[-0.180439,51.531658],"type":"Point"}
}