{
  "type": "Feature",
  "properties": {
    "iso:country":"GB",
    "sg:address":"58 High Street",
    "sg:city":"Broadstairs",
    "sg:classifiers":[
        {
            "category":"Shopping",
            "subcategory":"Hobbies, Toys, & Games",
            "type":"Retail Goods"
        }
    ],
    "sg:postcode":"CT10 1JT",
    "sg:province":"Kent",
    "sg:tags":[
        "shop",
        "toy"
    ],
    "wof:name":"Bazaar 58",
    "wof:placetype":"venue"
},
  "geometry": {"coordinates":[1.4389350414,51.3592567444],"type":"Point"}
}