{
  "type": "Feature",
  "properties": {
    "iso:country":"GB",
    "sg:address":"10 Brinkburn Dr",
    "sg:city":"Darlington",
    "sg:classifiers":[
        {
            "category":"Building & Trades",
            "subcategory":"Plumbing",
            "type":"Services"
        }
    ],
    "sg:postcode":"DL3 0LB",
    "sg:province":"Durham",
    "sg:tags":[
        "heating"
    ],
    "wof:name":"Scott,Paul,",
    "wof:placetype":"venue"
},
  "geometry": {"coordinates":[-1.571787,54.536522],"type":"Point"}
}