{
  "type": "Feature",
  "properties": {
    "addr:full":"10 Brinkburn Dr Darlington Durham DL3 0LB",
    "addr:housenumber":"10",
    "addr:postcode":"dl3 0lb",
    "addr:street":"Brinkburn Dr",
    "iso:country":"GB",
    "sg:address":"10 Brinkburn Dr",
    "sg:city":"Darlington",
    "sg:classifiers":[
        {
            "category":"Building & Trades",
            "subcategory":"Plumbing",
            "type":"Services"
        }
    ],
    "sg:postcode":"DL3 0LB",
    "sg:province":"Durham",
    "sg:tags":[
        "heating"
    ],
    "wof:name":"Scott,Paul,",
    "wof:placetype":"venue"
},
  "geometry": {"coordinates":[-1.571787,54.536522],"type":"Point"}
}