{
  "type": "Feature",
  "properties": {
    "addr:full":"Unit 16 Crown Walk Bicester Oxfordshire OX26 6HY",
    "addr:housenumber":"unit 16",
    "addr:postcode":"ox26 6hy",
    "addr:street":"Crown Walk",
    "iso:country":"GB",
    "sg:address":"Unit 16 Crown Walk",
    "sg:city":"Bicester",
    "sg:classifiers":[
        {
            "category":"Retail",
            "subcategory":"Photofinishing",
            "type":"Services"
        }
    ],
    "sg:phone":"+44 1869 320534",
    "sg:postcode":"OX26 6HY",
    "sg:province":"Oxfordshire",
    "sg:tags":[
        "photographic",
        "processor"
    ],
    "wof:name":"Bonusprint",
    "wof:placetype":"venue"
},
  "geometry": {"coordinates":[-1.1535400152,51.8980255127],"type":"Point"}
}