{
  "type": "Feature",
  "properties": {
    "addr:full":"Bonar Hall, University Of Dundee Dundee Dundee City DD1 4HN",
    "addr:postcode":"dd1 4hn",
    "addr:street":"Dundee",
    "iso:country":"GB",
    "sg:address":"Bonar Hall, University Of Dundee",
    "sg:city":"Dundee",
    "sg:classifiers":[
        {
            "category":"Arena",
            "subcategory":"Sports Club",
            "type":"Entertainment"
        }
    ],
    "sg:phone":"+44 1382 201262",
    "sg:postcode":"DD1 4HN",
    "sg:province":"Dundee City",
    "wof:name":"Dorothy Dobson's Over 60'S Exercise",
    "wof:placetype":"venue"
},
  "geometry": {"coordinates":[-2.9676089287,56.4613761902],"type":"Point"}
}