{
  "type": "Feature",
  "properties": {
    "iso:country":"GB",
    "sg:address":"45 Barnard Street",
    "sg:city":"Shrewsbury",
    "sg:classifiers":[
        {
            "category":"Home & Garden",
            "subcategory":"Household Appliances",
            "type":"Retail Goods"
        }
    ],
    "sg:phone":"+44 1939 232999",
    "sg:postcode":"SY4 5EF",
    "sg:province":"Shropshire",
    "sg:tags":[
        "electrical"
    ],
    "wof:name":"A S Paul",
    "wof:placetype":"venue"
},
  "geometry": {"coordinates":[-2.729158,52.853989],"type":"Point"}
}