{
  "type": "Feature",
  "properties": {
    "iso:country":"GB",
    "sg:address":"Unit 41 North Farm Road",
    "sg:city":"Scunthorpe",
    "sg:classifiers":[
        {
            "category":"Utilities",
            "subcategory":"Refuse",
            "type":"Services"
        }
    ],
    "sg:phone":"+44 1724 849200",
    "sg:postcode":"DN17 2DS",
    "sg:province":"Lincolnshire",
    "sg:tags":[
        "disposal",
        "waste"
    ],
    "wof:name":"Cleanaway Ltd.",
    "wof:placetype":"venue"
},
  "geometry": {"coordinates":[-0.675757,53.552734],"type":"Point"}
}