{
  "type": "Feature",
  "properties": {
    "addr:full":"45 Fusehill Street Carlisle Cumbria CA1 2HL",
    "addr:housenumber":"45",
    "addr:postcode":"ca1 2hl",
    "addr:street":"Fusehill Street",
    "iso:country":"GB",
    "sg:address":"45 Fusehill Street",
    "sg:city":"Carlisle",
    "sg:classifiers":[
        {
            "category":"Shopping",
            "subcategory":"News",
            "type":"Retail Goods"
        }
    ],
    "sg:phone":"+44 1228 535279",
    "sg:postcode":"CA1 2HL",
    "sg:province":"Cumbria",
    "sg:tags":[
        "newsagent"
    ],
    "wof:name":"Penningtons",
    "wof:placetype":"venue"
},
  "geometry": {"coordinates":[-2.920429,54.889965],"type":"Point"}
}