{
  "type": "Feature",
  "properties": {
    "addr:full":"27 Stirling Street Tillicoultry Clackmannanshire FK13 6EA",
    "addr:housenumber":"27",
    "addr:postcode":"fk13 6ea",
    "addr:street":"Stirling Street",
    "iso:country":"GB",
    "sg:address":"27 Stirling Street",
    "sg:city":"Tillicoultry",
    "sg:classifiers":[
        {
            "category":"Real Estate",
            "subcategory":"Architect",
            "type":"Services"
        }
    ],
    "sg:phone":"+44 1259 750440",
    "sg:postcode":"FK13 6EA",
    "sg:province":"Clackmannanshire",
    "sg:tags":[
        "kilt",
        "accessory"
    ],
    "wof:name":"Daiglen of Scotland",
    "wof:placetype":"venue"
},
  "geometry": {"coordinates":[-3.7467460632,56.1555938721],"type":"Point"}
}