{
  "type": "Feature",
  "properties": {
    "addr:full":"6 Church Walk Richmond Greater London TW9 1SN",
    "addr:housenumber":"6",
    "addr:postcode":"tw9 1sn",
    "addr:street":"Church Walk",
    "iso:country":"GB",
    "sg:address":"6 Church Walk",
    "sg:city":"Richmond",
    "sg:classifiers":[
        {
            "category":"Restaurant",
            "type":"Food & Drink"
        }
    ],
    "sg:postcode":"TW9 1SN",
    "sg:province":"Greater London",
    "wof:name":"The Refectory",
    "wof:placetype":"venue"
},
  "geometry": {"coordinates":[-0.304013,51.46014],"type":"Point"}
}