{
  "type": "Feature",
  "properties": {
    "iso:country":"GB",
    "sg:address":"238 Brick Lane, Shoreditch",
    "sg:city":"London",
    "sg:classifiers":[
        {
            "category":"Real Estate",
            "subcategory":"Architect",
            "type":"Services"
        }
    ],
    "sg:phone":"+44 20 7739 2710",
    "sg:postcode":"E2 7EB",
    "sg:province":"Greater London",
    "wof:name":"Phillip Michael Roys",
    "wof:placetype":"venue"
},
  "geometry": {"coordinates":[-0.071807,51.525749],"type":"Point"}
}