{
  "type": "Feature",
  "properties": {
    "addr:full":"Warwick Road, Whetstone Leicester Leicestershire LE8 6LW",
    "addr:postcode":"le8 6lw",
    "addr:street":"Warwick Road",
    "iso:country":"GB",
    "sg:address":"Warwick Road, Whetstone",
    "sg:city":"Leicester",
    "sg:classifiers":[
        {
            "category":"Organizations",
            "subcategory":"Membership Organization",
            "type":"Services"
        }
    ],
    "sg:phone":"+44 116 286 4852",
    "sg:postcode":"LE8 6LW",
    "sg:province":"Leicestershire",
    "sg:tags":[
        "club"
    ],
    "wof:name":"Blaby & Whetstone Boys Club",
    "wof:placetype":"venue"
},
  "geometry": {"coordinates":[-1.1804939508,52.5642852783],"type":"Point"}
}