{
  "type": "Feature",
  "properties": {
    "addr:full":"The Old Rectory, St Marys Hill Chester Cheshire CH1 2DW",
    "addr:postcode":"ch1 2dw",
    "addr:street":"St Marys Hill",
    "iso:country":"GB",
    "sg:address":"The Old Rectory, St Marys Hill",
    "sg:city":"Chester",
    "sg:classifiers":[
        {
            "category":"Health Services",
            "subcategory":"Nursing And Care Facility",
            "type":"Services"
        }
    ],
    "sg:phone":"+44 1244 344100",
    "sg:postcode":"CH1 2DW",
    "sg:province":"Cheshire",
    "sg:tags":[
        "home"
    ],
    "wof:name":"Care Management Technologies Ltd.",
    "wof:placetype":"venue"
},
  "geometry": {"coordinates":[-2.894369,53.188129],"type":"Point"}
}