{
  "type": "Feature",
  "properties": {
    "addr:full":"Redcourt, Beaconsfield Road, Farnham Royal Slough Berkshire SL2 3BY",
    "addr:postcode":"sl2 3by",
    "addr:street":"Redcourt Beaconsfield Road",
    "iso:country":"GB",
    "sg:address":"Redcourt, Beaconsfield Road, Farnham Royal",
    "sg:city":"Slough",
    "sg:classifiers":[
        {
            "category":"Insurance",
            "subcategory":"Insurance Agent",
            "type":"Services"
        }
    ],
    "sg:postcode":"SL2 3BY",
    "sg:province":"Berkshire",
    "wof:name":"Goldline Claims Ltd.",
    "wof:placetype":"venue"
},
  "geometry": {"coordinates":[-0.616684,51.539555],"type":"Point"}
}