{
  "type": "Feature",
  "properties": {
    "addr:full":"Unit 9 Tudor Enterprise Park, Tudor Road Harrow Greater London HA3 5PH",
    "addr:housenumber":"unit 9",
    "addr:postcode":"ha3 5ph",
    "addr:street":"Tudor Enterprise Park Tudor Road",
    "iso:country":"GB",
    "sg:address":"Unit 9 Tudor Enterprise Park, Tudor Road",
    "sg:city":"Harrow",
    "sg:classifiers":[
        {
            "category":"Professional",
            "subcategory":"Printing & Photocopies",
            "type":"Services"
        }
    ],
    "sg:postcode":"HA3 5PH",
    "sg:province":"Greater London",
    "sg:tags":[
        "photocopier"
    ],
    "wof:name":"Copylogic Ltd.",
    "wof:placetype":"venue"
},
  "geometry": {"coordinates":[-0.3454700112,51.5991096497],"type":"Point"}
}