{
  "type": "Feature",
  "properties": {
    "addr:full":"23 Abbotsbury Road Morden Surrey SM4 5LJ",
    "addr:housenumber":"23",
    "addr:postcode":"sm4 5lj",
    "addr:street":"Abbotsbury Road",
    "iso:country":"GB",
    "sg:address":"23 Abbotsbury Road",
    "sg:city":"Morden",
    "sg:classifiers":[
        {
            "category":"Bus Charters",
            "type":"Transportation"
        }
    ],
    "sg:postcode":"SM4 5LJ",
    "sg:province":"Surrey",
    "sg:tags":[
        "coach"
    ],
    "wof:name":"Superdirect Ltd.",
    "wof:placetype":"venue"
},
  "geometry": {"coordinates":[-0.1921170056,51.4023246765],"type":"Point"}
}