{
  "type": "Feature",
  "properties": {
    "addr:full":"Poole Railway Station, Serpentine Road Poole Dorset BH15 2BQ",
    "addr:postcode":"bh15 2bq",
    "addr:street":"Serpentine Road",
    "iso:country":"GB",
    "sg:address":"Poole Railway Station, Serpentine Road",
    "sg:city":"Poole",
    "sg:classifiers":[
        {
            "category":"Shopping",
            "subcategory":"News",
            "type":"Retail Goods"
        }
    ],
    "sg:phone":"+44 1202 684918",
    "sg:postcode":"BH15 2BQ",
    "sg:province":"Dorset",
    "sg:tags":[
        "newsagent"
    ],
    "wof:name":"Buffers",
    "wof:placetype":"venue"
},
  "geometry": {"coordinates":[-1.980845,50.720688],"type":"Point"}
}