{
  "type": "Feature",
  "properties": {
    "addr:full":"Liverpool Rd Whitchurch Cheshire SY13 1SW",
    "addr:postcode":"sy13 1sw",
    "addr:street":"Liverpool Rd",
    "iso:country":"GB",
    "sg:address":"Liverpool Rd",
    "sg:city":"Whitchurch",
    "sg:classifiers":[
        {
            "category":"Shopping",
            "type":"Retail Goods"
        }
    ],
    "sg:phone":"+44 1948 662869",
    "sg:postcode":"SY13 1SW",
    "sg:province":"Cheshire",
    "sg:tags":[
        "merchant"
    ],
    "wof:name":"F S L Bells",
    "wof:placetype":"venue"
},
  "geometry": {"coordinates":[-2.686639,52.9655],"type":"Point"}
}