{
  "type": "Feature",
  "properties": {
    "iso:country":"GB",
    "sg:address":"29 Easterly Rd",
    "sg:city":"Leeds",
    "sg:classifiers":[
        {
            "category":"Manufacturing",
            "subcategory":"Signs",
            "type":"Manufacturing & Wholesale Goods"
        }
    ],
    "sg:phone":"+44 113 240 3105",
    "sg:postcode":"LS8 2TN",
    "sg:province":"West Yorkshire",
    "sg:tags":[
        "writer"
    ],
    "wof:name":"William E Daniell",
    "wof:placetype":"venue"
},
  "geometry": {"coordinates":[-1.510912,53.817574],"type":"Point"}
}