{
  "type": "Feature",
  "properties": {
    "iso:country":"GB",
    "sg:address":"18 Carmelite Street",
    "sg:city":"Banff",
    "sg:classifiers":[
        {
            "category":"Professional",
            "subcategory":"Management & Consulting",
            "type":"Services"
        }
    ],
    "sg:phone":"+44 1261 818774",
    "sg:postcode":"AB45 1AF",
    "sg:province":"Aberdeenshire",
    "sg:tags":[
        "consultant",
        "business"
    ],
    "wof:name":"Mackie-Allen Consultancy",
    "wof:placetype":"venue"
},
  "geometry": {"coordinates":[-2.520507,57.664772],"type":"Point"}
}