{
  "type": "Feature",
  "properties": {
    "iso:country":"GB",
    "sg:address":"4 Mansel Close, Cosgrove",
    "sg:city":"Milton Keynes",
    "sg:classifiers":[
        {
            "category":"Professional",
            "subcategory":"Lawyer & Legal Services",
            "type":"Services"
        }
    ],
    "sg:postcode":"MK19 7JQ",
    "sg:province":"Buckinghamshire",
    "sg:tags":[
        "conveyancing"
    ],
    "wof:name":"John Francis & Co",
    "wof:placetype":"venue"
},
  "geometry": {"coordinates":[-0.848834,52.076672],"type":"Point"}
}