{
  "type": "Feature",
  "properties": {
    "addr:full":"58 Manor Road Rugby Warwickshire CV21 2TG",
    "addr:housenumber":"58",
    "addr:postcode":"cv21 2tg",
    "addr:street":"Manor Road",
    "iso:country":"GB",
    "sg:address":"58 Manor Road",
    "sg:city":"Rugby",
    "sg:classifiers":[
        {
            "category":"Autos & Motor Vehicles",
            "subcategory":"Motorcycle Sales",
            "type":"Retail Goods"
        },
        {
            "category":"Retail",
            "subcategory":"Auto Repair",
            "type":"Services"
        }
    ],
    "sg:phone":"+44 1788 570105",
    "sg:postcode":"CV21 2TG",
    "sg:province":"Warwickshire",
    "sg:tags":[
        "modification",
        "garage",
        "scooter",
        "cycle"
    ],
    "wof:name":"R & J Motorcycles",
    "wof:placetype":"venue"
},
  "geometry": {"coordinates":[-1.25981,52.377502],"type":"Point"}
}