{
  "type": "Feature",
  "properties": {
    "addr:full":"The Meadows, Cannock Road Wolverhampton Staffordshire WV10 0RD",
    "addr:postcode":"wv10 0rd",
    "addr:street":"Cannock Road",
    "iso:country":"GB",
    "sg:address":"The Meadows, Cannock Road",
    "sg:city":"Wolverhampton",
    "sg:classifiers":[
        {
            "category":"Shopping",
            "subcategory":"Discount & Variety Stores",
            "type":"Retail Goods"
        }
    ],
    "sg:phone":"+44 1902 306306",
    "sg:postcode":"WV10 0RD",
    "sg:province":"Staffordshire",
    "sg:tags":[
        "centre"
    ],
    "wof:name":"The Pound Land Group Plc",
    "wof:placetype":"venue"
},
  "geometry": {"coordinates":[-2.121669,52.58865],"type":"Point"}
}