{
  "type": "Feature",
  "properties": {
    "iso:country":"GB",
    "sg:address":"105 Sycamore Road",
    "sg:city":"Amersham",
    "sg:classifiers":[
        {
            "category":"Personal",
            "subcategory":"Beauty Salon",
            "type":"Services"
        },
        {
            "category":"Personal",
            "subcategory":"Barber",
            "type":"Services"
        }
    ],
    "sg:phone":"+44 1494 434016",
    "sg:postcode":"HP6 5EJ",
    "sg:province":"Buckinghamshire",
    "sg:tags":[
        "unisex",
        "hairdresser"
    ],
    "wof:name":"Jonathan Walker",
    "wof:placetype":"venue"
},
  "geometry": {"coordinates":[-0.6052200198,51.6787986755],"type":"Point"}
}