{
  "type": "Feature",
  "properties": {
    "addr:full":"14a Wellesley Mansions, Edith Villas London Greater London W14 9AH",
    "addr:housenumber":"14a",
    "addr:postcode":"w14 9ah",
    "iso:country":"GB",
    "sg:address":"14a Wellesley Mansions, Edith Villas",
    "sg:city":"London",
    "sg:classifiers":[
        {
            "category":"Real Estate",
            "subcategory":"Real Estate Agent",
            "type":"Services"
        }
    ],
    "sg:phone":"+44 870 870 8889",
    "sg:postcode":"W14 9AH",
    "sg:province":"Greater London",
    "wof:name":"Robert Bruenell",
    "wof:placetype":"venue"
},
  "geometry": {"coordinates":[-0.20706,51.49157],"type":"Point"}
}