{
  "type": "Feature",
  "properties": {
    "iso:country":"GB",
    "sg:address":"40 Montagu Gardens",
    "sg:city":"Leeds",
    "sg:classifiers":[
        {
            "category":"Building & Trades",
            "subcategory":"Construction",
            "type":"Services"
        }
    ],
    "sg:phone":"+44 113 248 2408",
    "sg:postcode":"LS8 2RW",
    "sg:province":"West Yorkshire",
    "sg:tags":[
        "builder"
    ],
    "wof:name":"Tommy Noone",
    "wof:placetype":"venue"
},
  "geometry": {"coordinates":[-1.5008,53.8204],"type":"Point"}
}