{
  "type": "Feature",
  "properties": {
    "iso:country":"GB",
    "sg:address":"10 Dalry Road",
    "sg:city":"Kilbirnie",
    "sg:classifiers":[
        {
            "category":"Food & Beverages",
            "subcategory":"Liquor & Beverages",
            "type":"Retail Goods"
        }
    ],
    "sg:phone":"+44 1505 684413",
    "sg:postcode":"KA25 6HY",
    "sg:province":"North Ayrshire",
    "sg:tags":[
        "beer",
        "spirit",
        "wines"
    ],
    "wof:name":"Julie Shields",
    "wof:placetype":"venue"
},
  "geometry": {"coordinates":[-4.687924,55.746574],"type":"Point"}
}