{
  "type": "Feature",
  "properties": {
    "addr:full":"Chestnut House, Muston Lane, Easthorpe Nottingham Leicestershire NG13 0DY",
    "addr:postcode":"ng13 0dy",
    "addr:street":"Muston Lane",
    "iso:country":"GB",
    "sg:address":"Chestnut House, Muston Lane, Easthorpe",
    "sg:city":"Nottingham",
    "sg:classifiers":[
        {
            "category":"Real Estate",
            "subcategory":"Surveying",
            "type":"Services"
        }
    ],
    "sg:phone":"+44 1949 842750",
    "sg:postcode":"NG13 0DY",
    "sg:province":"Leicestershire",
    "sg:tags":[
        "surveyor",
        "valuer"
    ],
    "wof:name":"Martyn Stubbs Chartered Surveyors",
    "wof:placetype":"venue"
},
  "geometry": {"coordinates":[-0.7877839804,52.9365959167],"type":"Point"}
}