{
  "type": "Feature",
  "properties": {
    "iso:country":"GB",
    "sg:address":"568 Rayleigh Road",
    "sg:city":"Leigh-on-sea",
    "sg:classifiers":[
        {
            "category":"Shopping",
            "subcategory":"Bicycles & Sporting Goods",
            "type":"Retail Goods"
        },
        {
            "category":"Education",
            "subcategory":"Dance Studio",
            "type":"Public Place"
        }
    ],
    "sg:phone":"+44 1702 511950",
    "sg:postcode":"SS9 5HX",
    "sg:province":"Essex",
    "sg:tags":[
        "school",
        "dancing",
        "balletwear"
    ],
    "wof:name":"Studio 1 Dancewear",
    "wof:placetype":"venue"
},
  "geometry": {"coordinates":[0.639201,51.572994],"type":"Point"}
}