{
  "type": "Feature",
  "properties": {
    "addr:full":"148 Main St Millom Cumbria LA18 4EZ",
    "addr:housenumber":"148",
    "addr:postcode":"la18 4ez",
    "addr:street":"Main St",
    "iso:country":"GB",
    "sg:address":"148 Main St",
    "sg:city":"Millom",
    "sg:classifiers":[
        {
            "category":"Food & Beverages",
            "subcategory":"Meat & Fish",
            "type":"Retail Goods"
        }
    ],
    "sg:postcode":"LA18 4EZ",
    "sg:province":"Cumbria",
    "sg:tags":[
        "butcher"
    ],
    "wof:name":"Clark,J B, & Son",
    "wof:placetype":"venue"
},
  "geometry": {"coordinates":[-3.294118,54.198589],"type":"Point"}
}