{
  "type": "Feature",
  "properties": {
    "iso:country":"GB",
    "sg:address":"Pepys Ct, 84 The Chase",
    "sg:city":"Clapham",
    "sg:classifiers":[
        {
            "category":"Wholesale",
            "subcategory":"Music Publishers",
            "type":"Manufacturing & Wholesale Goods"
        }
    ],
    "sg:phone":"+44 20 7627 8777",
    "sg:postcode":"SW4 0NF",
    "sg:province":"Greater London",
    "sg:tags":[
        "record"
    ],
    "wof:name":"Bespoke Audio Ltd",
    "wof:placetype":"venue"
},
  "geometry": {"coordinates":[-0.147330001,51.4659118652],"type":"Point"}
}