{
  "type": "Feature",
  "properties": {
    "addr:full":"Lower Sigford Farm, Bickington Newton Abbot Devon TQ12 6LD",
    "addr:housenumber":"bickington newton",
    "addr:postcode":"tq12 6ld",
    "iso:country":"GB",
    "sg:address":"Lower Sigford Farm, Bickington",
    "sg:city":"Newton Abbot",
    "sg:classifiers":[
        {
            "category":"Farming",
            "subcategory":"Livestock Farm",
            "type":"Manufacturing & Wholesale Goods"
        }
    ],
    "sg:phone":"+44 1626 821204",
    "sg:postcode":"TQ12 6LD",
    "sg:province":"Devon",
    "sg:tags":[
        "others"
    ],
    "wof:name":"David W  Coysh",
    "wof:placetype":"venue"
},
  "geometry": {"coordinates":[-3.695219,50.541859],"type":"Point"}
}