{
  "type": "Feature",
  "properties": {
    "iso:country":"GB",
    "sg:address":"Unit 26, Number One Industrial Estate",
    "sg:city":"Consett",
    "sg:classifiers":[
        {
            "category":"Professional",
            "subcategory":"Business Services",
            "type":"Services"
        }
    ],
    "sg:phone":"+44 1207 583562",
    "sg:postcode":"DH8 6TJ",
    "sg:province":"Durham",
    "sg:tags":[
        "code",
        "bar"
    ],
    "wof:name":"Briarsoft",
    "wof:placetype":"venue"
},
  "geometry": {"coordinates":[-1.8359140158,54.8609886169],"type":"Point"}
}