{
  "type": "Feature",
  "properties": {
    "addr:full":"100 Grange Rd, Blunham Bedford Bedfordshire MK44 3NT",
    "addr:housenumber":"100",
    "addr:postcode":"mk44 3nt",
    "addr:street":"Grange Rd",
    "iso:country":"GB",
    "sg:address":"100 Grange Rd, Blunham",
    "sg:city":"Bedford",
    "sg:classifiers":[
        {
            "category":"Professional",
            "subcategory":"Computer Services",
            "type":"Services"
        }
    ],
    "sg:phone":"+44 1767 640134",
    "sg:postcode":"MK44 3NT",
    "sg:province":"Bedfordshire",
    "sg:tags":[
        "consultant"
    ],
    "wof:name":"Bedford Computer Consultants",
    "wof:placetype":"venue"
},
  "geometry": {"coordinates":[-0.3164289892,52.1541404724],"type":"Point"}
}