{
  "type": "Feature",
  "properties": {
    "addr:full":"402 Commercial Road, Stepney London Greater London E1 0LG",
    "addr:housenumber":"402",
    "addr:postcode":"e1 0lg",
    "addr:street":"Commercial Road",
    "iso:country":"GB",
    "sg:address":"402 Commercial Road, Stepney",
    "sg:city":"London",
    "sg:classifiers":[
        {
            "category":"Professional",
            "subcategory":"Lawyer & Legal Services",
            "type":"Services"
        }
    ],
    "sg:postcode":"E1 0LG",
    "sg:province":"Greater London",
    "sg:tags":[
        "solicitor"
    ],
    "wof:name":"Edward Fail Bradshaw & Waterson",
    "wof:placetype":"venue"
},
  "geometry": {"coordinates":[-0.049773,51.513554],"type":"Point"}
}