{
  "type": "Feature",
  "properties": {
    "iso:country":"GB",
    "sg:address":"High Street, Porlock",
    "sg:city":"Minehead",
    "sg:classifiers":[
        {
            "category":"Travel",
            "subcategory":"Hotels & Motels",
            "type":"Entertainment"
        }
    ],
    "sg:phone":"+44 1643 862504",
    "sg:postcode":"TA24 8PY",
    "sg:province":"Somerset",
    "wof:name":"Seabrook Investments Ltd.",
    "wof:placetype":"venue"
},
  "geometry": {"coordinates":[-3.5929949284,51.2094116211],"type":"Point"}
}