{
  "type": "Feature",
  "properties": {
    "iso:country":"GB",
    "sg:address":"Scouts Headquarters, Carver Rd",
    "sg:city":"Burton On Trent",
    "sg:classifiers":[
        {
            "category":"Community Center",
            "subcategory":"Youth",
            "type":"Public Place"
        }
    ],
    "sg:phone":"+44 1283 532194",
    "sg:postcode":"DE13 0GQ",
    "sg:province":"Derbyshire",
    "sg:tags":[
        "organisation",
        "centre"
    ],
    "wof:name":"13th Burton Scout Group",
    "wof:placetype":"venue"
},
  "geometry": {"coordinates":[-1.64487,52.81826],"type":"Point"}
}