{
  "type": "Feature",
  "properties": {
    "iso:country":"GB",
    "sg:address":"66 St Georges Road",
    "sg:city":"Brighton",
    "sg:classifiers":[
        {
            "category":"Government",
            "subcategory":"Post Office",
            "type":"Public Place"
        }
    ],
    "sg:phone":"+44 1273 607746",
    "sg:postcode":"BN2 1EF",
    "sg:province":"East Sussex",
    "wof:name":"St George's Road Post Office",
    "wof:placetype":"venue"
},
  "geometry": {"coordinates":[-0.1174509972,50.8173446655],"type":"Point"}
}