{
  "type": "Feature",
  "properties": {
    "addr:full":"23 Lysias Road, Balham London Greater London SW12 8BW",
    "addr:housenumber":"23",
    "addr:postcode":"sw12 8bw",
    "addr:street":"Lysias Road",
    "iso:country":"GB",
    "sg:address":"23 Lysias Road, Balham",
    "sg:city":"London",
    "sg:classifiers":[
        {
            "category":"Professional",
            "subcategory":"Accounting & Tax Preparation",
            "type":"Services"
        }
    ],
    "sg:postcode":"SW12 8BW",
    "sg:province":"Greater London",
    "sg:tags":[
        "accountant"
    ],
    "wof:name":"Stenbuild Ltd",
    "wof:placetype":"venue"
},
  "geometry": {"coordinates":[-0.151792,51.450897],"type":"Point"}
}