{
  "type": "Feature",
  "properties": {
    "addr:full":"Unit 2 Northside Industrial Estate, Whitley Bridge Goole East Riding of Yorkshire DN14 0GH",
    "addr:housenumber":"unit 2",
    "addr:postcode":"dn14 0gh",
    "addr:street":"Industrial Estate Whitley Bridge",
    "iso:country":"GB",
    "sg:address":"Unit 2 Northside Industrial Estate, Whitley Bridge",
    "sg:city":"Goole",
    "sg:classifiers":[
        {
            "category":"Home & Garden",
            "subcategory":"Home Furnishings",
            "type":"Retail Goods"
        }
    ],
    "sg:phone":"+44 1977 662277",
    "sg:postcode":"DN14 0GH",
    "sg:province":"East Riding of Yorkshire",
    "sg:tags":[
        "racking",
        "shelving",
        "diy"
    ],
    "wof:name":"J & M Storage Systems Ltd.",
    "wof:placetype":"venue"
},
  "geometry": {"coordinates":[-1.156908989,53.6980056763],"type":"Point"}
}