{
  "type": "Feature",
  "properties": {
    "iso:country":"GB",
    "sg:address":"Kimberley Merrylands, Corscombe",
    "sg:city":"Dorchester",
    "sg:classifiers":[
        {
            "category":"Building & Trades",
            "subcategory":"Construction",
            "type":"Services"
        }
    ],
    "sg:postcode":"DT2 0PD",
    "sg:province":"Dorset",
    "sg:tags":[
        "builder"
    ],
    "wof:name":"Kimberly Construction",
    "wof:placetype":"venue"
},
  "geometry": {"coordinates":[-2.6844139099,50.8459663391],"type":"Point"}
}