{
  "type": "Feature",
  "properties": {
    "addr:full":"120-121 London Road Marlborough Berkshire SN8 1LH",
    "addr:housenumber":"120-121",
    "addr:postcode":"sn8 1lh",
    "addr:street":"London Road",
    "iso:country":"GB",
    "sg:address":"120-121 London Road",
    "sg:city":"Marlborough",
    "sg:classifiers":[
        {
            "category":"Autos & Motor Vehicles",
            "subcategory":"Auto Supplies",
            "type":"Retail Goods"
        }
    ],
    "sg:phone":"+44 1672 512274",
    "sg:postcode":"SN8 1LH",
    "sg:province":"Berkshire",
    "sg:tags":[
        "tyre"
    ],
    "wof:name":"Ats",
    "wof:placetype":"venue"
},
  "geometry": {"coordinates":[-1.7258980274,51.4202957153],"type":"Point"}
}