{
  "type": "Feature",
  "properties": {
    "addr:full":"29 High Street Welwyn Hertfordshire AL6 9EE",
    "addr:housenumber":"29",
    "addr:postcode":"al6 9ee",
    "addr:street":"High Street",
    "iso:country":"GB",
    "sg:address":"29 High Street",
    "sg:city":"Welwyn",
    "sg:classifiers":[
        {
            "category":"Professional",
            "subcategory":"Management & Consulting",
            "type":"Services"
        }
    ],
    "sg:phone":"+44 1438 840984",
    "sg:postcode":"AL6 9EE",
    "sg:province":"Hertfordshire",
    "sg:tags":[
        "consultant",
        "business"
    ],
    "sg:website":"http://www.ejjh.co.uk",
    "wof:name":"Eames Jones Judge Hawkings",
    "wof:placetype":"venue"
},
  "geometry": {"coordinates":[-0.215423,51.830326],"type":"Point"}
}