{
  "type": "Feature",
  "properties": {
    "addr:full":"Morelock House, Strawberry Lane Willenhall West Midlands WV13 3RS",
    "addr:postcode":"wv13 3rs",
    "addr:street":"Strawberry Lane",
    "iso:country":"GB",
    "sg:address":"Morelock House, Strawberry Lane",
    "sg:city":"Willenhall",
    "sg:classifiers":[
        {
            "category":"Manufacturing",
            "subcategory":"Signs",
            "type":"Manufacturing & Wholesale Goods"
        }
    ],
    "sg:phone":"+44 1902 637575",
    "sg:postcode":"WV13 3RS",
    "sg:province":"West Midlands",
    "sg:tags":[
        "nameplate"
    ],
    "wof:name":"Morelock Signs Ltd.",
    "wof:placetype":"venue"
},
  "geometry": {"coordinates":[-2.085889,52.589176],"type":"Point"}
}