{
  "type": "Feature",
  "properties": {
    "iso:country":"GB",
    "sg:address":"The Dolls Ho, Gladstone Building, Hope St",
    "sg:city":"Hebden Bridge",
    "sg:classifiers":[
        {
            "category":"Wholesale",
            "subcategory":"Toys & Hobbies",
            "type":"Manufacturing & Wholesale Goods"
        }
    ],
    "sg:phone":"+44 1422 845606",
    "sg:postcode":"HX7 8AG",
    "sg:province":"West Yorkshire",
    "sg:tags":[
        "hospital",
        "doll"
    ],
    "wof:name":"S Rouse",
    "wof:placetype":"venue"
},
  "geometry": {"coordinates":[-2.014491,53.741226],"type":"Point"}
}