{
  "type": "Feature",
  "properties": {
    "iso:country":"GB",
    "sg:address":"4 Tombland",
    "sg:city":"Norwich",
    "sg:classifiers":[
        {
            "category":"Real Estate",
            "subcategory":"Architect",
            "type":"Services"
        }
    ],
    "sg:phone":"+44 1603 623166",
    "sg:postcode":"NR3 1HE",
    "sg:province":"Norfolk",
    "wof:name":"Gibbs Bonner Minns Partnership",
    "wof:placetype":"venue"
},
  "geometry": {"coordinates":[1.298621,52.630829],"type":"Point"}
}