{
  "type": "Feature",
  "properties": {
    "iso:country":"GB",
    "sg:address":"1 Bow Court, Fletchworth Gate Industrial Estate, Fletchworth Gate",
    "sg:city":"Coventry",
    "sg:classifiers":[
        {
            "category":"Professional",
            "subcategory":"Management & Consulting",
            "type":"Services"
        }
    ],
    "sg:phone":"+44 24 7671 8200",
    "sg:postcode":"CV5 6SP",
    "sg:province":"West Midlands",
    "sg:tags":[
        "consultant",
        "business"
    ],
    "wof:name":"Savant Group Ltd.",
    "wof:placetype":"venue"
},
  "geometry": {"coordinates":[-1.551972,52.39642],"type":"Point"}
}