{
  "type": "Feature",
  "properties": {
    "addr:full":"Lytton Street Middlesbrough North Yorkshire TS4 2BZ",
    "addr:postcode":"ts4 2bz",
    "addr:street":"Lytton Street",
    "iso:country":"GB",
    "sg:address":"Lytton Street",
    "sg:city":"Middlesbrough",
    "sg:classifiers":[
        {
            "category":"Retail",
            "subcategory":"Auto Repair",
            "type":"Services"
        }
    ],
    "sg:phone":"+44 1642 245375",
    "sg:postcode":"TS4 2BZ",
    "sg:province":"North Yorkshire",
    "sg:tags":[
        "modification",
        "garage",
        "related"
    ],
    "wof:name":"Saltwells Garage",
    "wof:placetype":"venue"
},
  "geometry": {"coordinates":[-1.219819,54.571098],"type":"Point"}
}