{
  "type": "Feature",
  "properties": {
    "addr:full":"94 Bedford Road Rushden Bedfordshire NN10 0NE",
    "addr:housenumber":"94",
    "addr:postcode":"nn10 0ne",
    "addr:street":"Bedford Road",
    "iso:country":"GB",
    "sg:address":"94 Bedford Road",
    "sg:city":"Rushden",
    "sg:classifiers":[
        {
            "category":"Manufacturing",
            "subcategory":"Paper Products",
            "type":"Manufacturing & Wholesale Goods"
        }
    ],
    "sg:phone":"+44 1933 356434",
    "sg:postcode":"NN10 0NE",
    "sg:province":"Bedfordshire",
    "sg:tags":[
        "cardboard"
    ],
    "wof:name":"Betts & Brittin",
    "wof:placetype":"venue"
},
  "geometry": {"coordinates":[-0.5876269937,52.2743759155],"type":"Point"}
}