{
  "type": "Feature",
  "properties": {
    "iso:country":"GB",
    "sg:address":"2 Freelands Place, Old Kilpatrick",
    "sg:city":"Glasgow",
    "sg:classifiers":[
        {
            "category":"Food & Beverages",
            "subcategory":"Groceries & Convenience Stores",
            "type":"Retail Goods"
        }
    ],
    "sg:phone":"+44 1389 891200",
    "sg:postcode":"G60 5ED",
    "sg:province":"West Dunbartonshire",
    "wof:name":"Spar Store",
    "wof:placetype":"venue"
},
  "geometry": {"coordinates":[-4.4483718872,55.9177017212],"type":"Point"}
}