{
  "type": "Feature",
  "properties": {
    "addr:full":"St Guthlacs Lodge, Crowland Peterborough Cambridgeshire PE6 0JP",
    "addr:postcode":"pe6 0jp",
    "addr:street":"Crowland Peterborough",
    "iso:country":"GB",
    "sg:address":"St Guthlacs Lodge, Crowland",
    "sg:city":"Peterborough",
    "sg:classifiers":[
        {
            "category":"Farming",
            "subcategory":"Livestock Farm",
            "type":"Manufacturing & Wholesale Goods"
        }
    ],
    "sg:phone":"+44 1733 210316",
    "sg:postcode":"PE6 0JP",
    "sg:province":"Cambridgeshire",
    "sg:tags":[
        "others"
    ],
    "wof:name":"J W E Banks Ltd.",
    "wof:placetype":"venue"
},
  "geometry": {"coordinates":[-0.1645040065,52.6779212952],"type":"Point"}
}