{
  "type": "Feature",
  "properties": {
    "iso:country":"GB",
    "sg:address":"1a Humber Rd",
    "sg:city":"Cricklewood",
    "sg:classifiers":[
        {
            "category":"Shopping",
            "subcategory":"News",
            "type":"Retail Goods"
        }
    ],
    "sg:phone":"+44 181 452 6950",
    "sg:postcode":"NW2 6EG",
    "sg:province":"Greater London",
    "sg:tags":[
        "newsagent"
    ],
    "wof:name":"Mahesh News & Macs Off Licence",
    "wof:placetype":"venue"
},
  "geometry": {"coordinates":[-0.2310799956,51.5648193359],"type":"Point"}
}