{
  "type": "Feature",
  "properties": {
    "addr:full":"163 Wood Street London Greater London E17 3LX",
    "addr:housenumber":"163",
    "addr:postcode":"e17 3lx",
    "addr:street":"Wood Street",
    "iso:country":"GB",
    "sg:address":"163 Wood Street",
    "sg:city":"London",
    "sg:classifiers":[
        {
            "category":"Home & Garden",
            "subcategory":"Furniture",
            "type":"Retail Goods"
        }
    ],
    "sg:phone":"+44 20 8521 9133",
    "sg:postcode":"E17 3LX",
    "sg:province":"Greater London",
    "wof:name":"Discount Furniture",
    "wof:placetype":"venue"
},
  "geometry": {"coordinates":[-0.003065,51.58688],"type":"Point"}
}