{
  "type": "Feature",
  "properties": {
    "addr:full":"Elm Grove Rd Ealing Greater London W5 3JH",
    "addr:postcode":"w5 3jh",
    "addr:street":"Elm Grove Rd",
    "iso:country":"GB",
    "sg:address":"Elm Grove Rd",
    "sg:city":"Ealing",
    "sg:classifiers":[
        {
            "category":"Place Of Worship",
            "type":"Public Place"
        }
    ],
    "sg:phone":"+44 20 8567 8166",
    "sg:postcode":"W5 3JH",
    "sg:province":"Greater London",
    "wof:name":"All Saints C Of E Church",
    "wof:placetype":"venue"
},
  "geometry": {"coordinates":[-0.2999309897,51.5140228271],"type":"Point"}
}