{
  "type": "Feature",
  "properties": {
    "addr:full":"6 Larkspur Drive, Marchwood Southampton Hampshire SO40 4JX",
    "addr:housenumber":"6",
    "addr:postcode":"so40 4jx",
    "addr:street":"Larkspur Drive",
    "iso:country":"GB",
    "sg:address":"6 Larkspur Drive, Marchwood",
    "sg:city":"Southampton",
    "sg:classifiers":[
        {
            "category":"Real Estate",
            "subcategory":"Surveying",
            "type":"Services"
        }
    ],
    "sg:phone":"+44 23 8086 7030",
    "sg:postcode":"SO40 4JX",
    "sg:province":"Hampshire",
    "sg:tags":[
        "building",
        "surveyor"
    ],
    "wof:name":"Nicholas Ireland ARICS. MBEng",
    "wof:placetype":"venue"
},
  "geometry": {"coordinates":[-1.4533400536,50.8866233826],"type":"Point"}
}