{
  "type": "Feature",
  "properties": {
    "addr:full":"Bentley Road, Little Bromley Manningtree Essex CO11 2PL",
    "addr:postcode":"co11 2pl",
    "addr:street":"Bentley Road",
    "iso:country":"GB",
    "sg:address":"Bentley Road, Little Bromley",
    "sg:city":"Manningtree",
    "sg:classifiers":[
        {
            "category":"Bars & Pubs",
            "type":"Food & Drink"
        }
    ],
    "sg:phone":"+44 1206 397415",
    "sg:postcode":"CO11 2PL",
    "sg:province":"Essex",
    "sg:tags":[
        "pubs",
        "inn"
    ],
    "wof:name":"John Kemp",
    "wof:placetype":"venue"
},
  "geometry": {"coordinates":[1.0458250046,51.9175643921],"type":"Point"}
}