{
  "type": "Feature",
  "properties": {
    "iso:country":"GB",
    "sg:address":"High Street",
    "sg:city":"Narberth",
    "sg:classifiers":[
        {
            "category":"Retail",
            "subcategory":"Auto Repair",
            "type":"Services"
        }
    ],
    "sg:phone":"+44 1834 831485",
    "sg:postcode":"SA67 8PU",
    "sg:province":"Carmarthenshire",
    "sg:tags":[
        "modification",
        "garage"
    ],
    "wof:name":"Alan Mason",
    "wof:placetype":"venue"
},
  "geometry": {"coordinates":[-4.742659,51.797733],"type":"Point"}
}