{
  "type": "Feature",
  "properties": {
    "iso:country":"GB",
    "sg:address":"Bell Walk House, Bell Walk",
    "sg:city":"Uckfield",
    "sg:classifiers":[
        {
            "category":"Professional",
            "subcategory":"Engineering",
            "type":"Services"
        },
        {
            "category":"Home & Garden",
            "subcategory":"Household Appliances",
            "type":"Retail Goods"
        }
    ],
    "sg:phone":"+44 1825 765077",
    "sg:postcode":"TN22 5DQ",
    "sg:province":"East Sussex",
    "sg:tags":[
        "electrical",
        "domestic",
        "engineer"
    ],
    "wof:name":"Ramac Engineering Ltd",
    "wof:placetype":"venue"
},
  "geometry": {"coordinates":[0.095427,50.968945],"type":"Point"}
}