{
  "type": "Feature",
  "properties": {
    "iso:country":"GB",
    "sg:address":"Old Exchange",
    "sg:city":"Ipswich",
    "sg:classifiers":[
        {
            "category":"Building & Trades",
            "subcategory":"Construction",
            "type":"Services"
        }
    ],
    "sg:phone":"+44 1473 830866",
    "sg:postcode":"IP6 0DQ",
    "sg:province":"Suffolk",
    "sg:tags":[
        "builder"
    ],
    "wof:name":"Claydon Services",
    "wof:placetype":"venue"
},
  "geometry": {"coordinates":[1.152724,52.117374],"type":"Point"}
}