{
  "type": "Feature",
  "properties": {
    "iso:country":"GB",
    "sg:address":"4 South Rd",
    "sg:city":"Skegness",
    "sg:classifiers":[
        {
            "category":"Professional",
            "subcategory":"Lawyer & Legal Services",
            "type":"Services"
        }
    ],
    "sg:phone":"+44 1754 871746",
    "sg:postcode":"PE24 5TS",
    "sg:province":"Lincolnshire",
    "sg:tags":[
        "solicitor"
    ],
    "wof:name":"Walkers Owen & Craig",
    "wof:placetype":"venue"
},
  "geometry": {"coordinates":[0.298638,53.223988],"type":"Point"}
}