{
  "type": "Feature",
  "properties": {
    "addr:full":"51 High Street, Tarvin Chester Cheshire CH3 8EE",
    "addr:housenumber":"51",
    "addr:postcode":"ch3 8ee",
    "addr:street":"High Street",
    "iso:country":"GB",
    "sg:address":"51 High Street, Tarvin",
    "sg:city":"Chester",
    "sg:classifiers":[
        {
            "category":"Wholesale",
            "subcategory":"Fruits & Vegetables",
            "type":"Manufacturing & Wholesale Goods"
        },
        {
            "category":"Food & Beverages",
            "subcategory":"Groceries & Convenience Stores",
            "type":"Retail Goods"
        }
    ],
    "sg:phone":"+44 1829 741219",
    "sg:postcode":"CH3 8EE",
    "sg:province":"Cheshire",
    "sg:tags":[
        "merchant",
        "potato"
    ],
    "wof:name":"Potato Supplies Ltd.",
    "wof:placetype":"venue"
},
  "geometry": {"coordinates":[-2.764899,53.197529],"type":"Point"}
}