{
  "type": "Feature",
  "properties": {
    "iso:country":"GB",
    "sg:address":"Norman House, 105-109 Strand",
    "sg:city":"London",
    "sg:classifiers":[
        {
            "category":"Organizations",
            "subcategory":"Community Association",
            "type":"Services"
        }
    ],
    "sg:phone":"+44 20 7836 3630",
    "sg:postcode":"WC2R 0AA",
    "sg:province":"Greater London",
    "sg:tags":[
        "society",
        "housing"
    ],
    "wof:name":"Independent Housing Ombudsman Ltd.",
    "wof:placetype":"venue"
},
  "geometry": {"coordinates":[-0.12032,51.510761],"type":"Point"}
}