{
  "type": "Feature",
  "properties": {
    "addr:full":"Unit 1020, 30 Lawrence Street York North Yorkshire YO10 3BN",
    "addr:housenumber":"unit 1020 30",
    "addr:postcode":"yo10 3bn",
    "addr:street":"Lawrence Street",
    "iso:country":"GB",
    "sg:address":"Unit 1020, 30 Lawrence Street",
    "sg:city":"York",
    "sg:classifiers":[
        {
            "category":"Social Services",
            "subcategory":"Adult Care",
            "type":"Services"
        }
    ],
    "sg:phone":"+44 1904 489218",
    "sg:postcode":"YO10 3BN",
    "sg:province":"North Yorkshire",
    "sg:tags":[
        "domestic",
        "cleaning"
    ],
    "wof:name":"Merrymaids of York & Harrogate",
    "wof:placetype":"venue"
},
  "geometry": {"coordinates":[-1.070894,53.954384],"type":"Point"}
}