{
  "type": "Feature",
  "properties": {
    "addr:full":"Abbey Drive Ashby-de-la-zouch Derbyshire LE65 2LX",
    "addr:postcode":"le65 2lx",
    "addr:street":"Abbey Drive",
    "iso:country":"GB",
    "sg:address":"Abbey Drive",
    "sg:city":"Ashby-de-la-zouch",
    "sg:classifiers":[
        {
            "category":"Shopping",
            "subcategory":"Department Store",
            "type":"Retail Goods"
        },
        {
            "category":"Food & Beverages",
            "subcategory":"Groceries & Convenience Stores",
            "type":"Retail Goods"
        }
    ],
    "sg:phone":"+44 1530 411318",
    "sg:postcode":"LE65 2LX",
    "sg:province":"Derbyshire",
    "wof:name":"Abbey Stores",
    "wof:placetype":"venue"
},
  "geometry": {"coordinates":[-1.485344,52.749088],"type":"Point"}
}