{
  "type": "Feature",
  "properties": {
    "addr:full":"Kingswood House, 41 Kingswood Way South Croydon Surrey CR2 8QL",
    "addr:housenumber":"41",
    "addr:postcode":"cr2 8ql",
    "addr:street":"Kingswood Way",
    "iso:country":"GB",
    "sg:address":"Kingswood House, 41 Kingswood Way",
    "sg:city":"South Croydon",
    "sg:classifiers":[
        {
            "category":"Real Estate",
            "subcategory":"Surveying",
            "type":"Services"
        }
    ],
    "sg:phone":"+44 20 8657 9299",
    "sg:postcode":"CR2 8QL",
    "sg:province":"Surrey",
    "sg:tags":[
        "building",
        "surveyor"
    ],
    "wof:name":"Kingswood Associates M & E",
    "wof:placetype":"venue"
},
  "geometry": {"coordinates":[-0.058609,51.33086],"type":"Point"}
}