{
  "type": "Feature",
  "properties": {
    "iso:country":"GB",
    "sg:address":"120 Highlands Rd",
    "sg:city":"Solihull",
    "sg:classifiers":[
        {
            "category":"Cinema",
            "subcategory":"Movie Theater",
            "type":"Entertainment"
        }
    ],
    "sg:phone":"+44 870 588 8990",
    "sg:postcode":"B90 4BW",
    "sg:province":"West Midlands",
    "wof:name":"UCI 8 Cinemas",
    "wof:placetype":"venue"
},
  "geometry": {"coordinates":[-1.808209,52.39896],"type":"Point"}
}