{
  "type": "Feature",
  "properties": {
    "addr:full":"Po Box, 140 4 St. Dunstan's Hill Monument Greater London EC3R 5HB",
    "addr:housenumber":"po;4",
    "addr:postcode":"ec3r 5hb",
    "addr:street":"Box 140",
    "iso:country":"GB",
    "sg:address":"Po Box, 140 4 St. Dunstan's Hill",
    "sg:city":"Monument",
    "sg:classifiers":[
        {
            "category":"Organizations",
            "subcategory":"Non-profit Organization",
            "type":"Services"
        }
    ],
    "sg:phone":"+44 20 7204 5003",
    "sg:postcode":"EC3R 5HB",
    "sg:province":"Greater London",
    "sg:tags":[
        "organisation",
        "voluntary",
        "charity"
    ],
    "wof:name":"Gifts In Kind UK",
    "wof:placetype":"venue"
},
  "geometry": {"coordinates":[-0.08053,51.50935],"type":"Point"}
}