{
  "type": "Feature",
  "properties": {
    "addr:full":"Stoke House, Church Road Ashford Kent TN23 1RD",
    "addr:postcode":"tn23 1rd",
    "addr:street":"Church Road",
    "iso:country":"GB",
    "sg:address":"Stoke House, Church Road",
    "sg:city":"Ashford",
    "sg:classifiers":[
        {
            "category":"Professional",
            "subcategory":"Lawyer & Legal Services",
            "type":"Services"
        }
    ],
    "sg:phone":"+44 1233 624551",
    "sg:postcode":"TN23 1RD",
    "sg:province":"Kent",
    "sg:tags":[
        "solicitor"
    ],
    "wof:name":"Bradleys",
    "wof:placetype":"venue"
},
  "geometry": {"coordinates":[0.87248,51.146191],"type":"Point"}
}