{
  "type": "Feature",
  "properties": {
    "iso:country":"GB",
    "sg:address":"12 Beaumont Pl",
    "sg:city":"Barnet",
    "sg:classifiers":[
        {
            "category":"Wholesale",
            "subcategory":"Toys & Hobbies",
            "type":"Manufacturing & Wholesale Goods"
        }
    ],
    "sg:postcode":"EN5 4PR",
    "sg:province":"Hertfordshire",
    "sg:tags":[
        "game"
    ],
    "wof:name":"Landers,Michelle,",
    "wof:placetype":"venue"
},
  "geometry": {"coordinates":[-0.196345,51.666561],"type":"Point"}
}