{
  "type": "Feature",
  "properties": {
    "addr:full":"Oak Road, Bebington Wirral Merseyside CH63 8PQ",
    "addr:postcode":"ch63 8pq",
    "addr:street":"Oak Road",
    "iso:country":"GB",
    "sg:address":"Oak Road, Bebington",
    "sg:city":"Wirral",
    "sg:classifiers":[
        {
            "category":"Autos & Motor Vehicles",
            "subcategory":"Automobile Sales",
            "type":"Retail Goods"
        }
    ],
    "sg:postcode":"CH63 8PQ",
    "sg:province":"Merseyside",
    "sg:tags":[
        "car"
    ],
    "wof:name":"Oak Road Car Sales",
    "wof:placetype":"venue"
},
  "geometry": {"coordinates":[-3.010909,53.361355],"type":"Point"}
}