{
  "type": "Feature",
  "properties": {
    "addr:full":"Unit 7 Silver End Indstl Est, Brettell La Brierley Hill West Midlands DY5 3LA",
    "addr:housenumber":"unit 7",
    "addr:postcode":"dy5 3la",
    "addr:street":"Silver End Indstl Est;La Brierley Hill",
    "iso:country":"GB",
    "sg:address":"Unit 7 Silver End Indstl Est, Brettell La",
    "sg:city":"Brierley Hill",
    "sg:classifiers":[
        {
            "category":"Retail",
            "subcategory":"Auto Repair",
            "type":"Services"
        }
    ],
    "sg:postcode":"DY5 3LA",
    "sg:province":"West Midlands",
    "sg:tags":[
        "body",
        "car"
    ],
    "wof:name":"Suell,R,",
    "wof:placetype":"venue"
},
  "geometry": {"coordinates":[-2.133754015,52.4757003784],"type":"Point"}
}