{
  "type": "Feature",
  "properties": {
    "iso:country":"GB",
    "sg:address":"Nether Grn Farm, Moorwood Moor Lane, Wessington",
    "sg:city":"Alfreton",
    "sg:classifiers":[
        {
            "category":"Farming",
            "subcategory":"Dairy Farm",
            "type":"Manufacturing & Wholesale Goods"
        }
    ],
    "sg:phone":"+44 1773 832902",
    "sg:postcode":"DE55 6DU",
    "sg:province":"Derbyshire",
    "sg:tags":[
        "farmer"
    ],
    "wof:name":"Easom & Sons",
    "wof:placetype":"venue"
},
  "geometry": {"coordinates":[-1.447124,53.115608],"type":"Point"}
}