{
  "type": "Feature",
  "properties": {
    "iso:country":"GB",
    "sg:address":"9a Bold Street",
    "sg:city":"Liverpool",
    "sg:classifiers":[
        {
            "category":"Shopping",
            "subcategory":"Gifts & Souvenirs",
            "type":"Retail Goods"
        }
    ],
    "sg:phone":"+44 151 707 0894",
    "sg:postcode":"L1 4DN",
    "sg:province":"Merseyside",
    "sg:tags":[
        "poster",
        "card"
    ],
    "wof:name":"Springfield Trading",
    "wof:placetype":"venue"
},
  "geometry": {"coordinates":[-2.980768919,53.4044761658],"type":"Point"}
}