{
  "type": "Feature",
  "properties": {
    "addr:full":"Unit 114 Victoria Centre, Glasshouse Street Nottingham Nottinghamshire NG1 3QD",
    "addr:housenumber":"114",
    "addr:postcode":"ng1 3qd",
    "addr:street":"Victoria Centre Glasshouse Street",
    "iso:country":"GB",
    "sg:address":"Unit 114 Victoria Centre, Glasshouse Street",
    "sg:city":"Nottingham",
    "sg:classifiers":[
        {
            "category":"Cafe",
            "type":"Food & Drink"
        }
    ],
    "sg:phone":"+44 115 948 0330",
    "sg:postcode":"NG1 3QD",
    "sg:province":"Nottinghamshire",
    "sg:tags":[
        "tea",
        "room"
    ],
    "wof:name":"Druckers Vienna Patisserie",
    "wof:placetype":"venue"
},
  "geometry": {"coordinates":[-1.1467789412,52.9552192688],"type":"Point"}
}