{
  "type": "Feature",
  "properties": {
    "iso:country":"GB",
    "sg:address":"159-173 St John Street",
    "sg:city":"London",
    "sg:classifiers":[
        {
            "category":"Communications",
            "type":"Services"
        }
    ],
    "sg:postcode":"EC1V 4QJ",
    "sg:province":"Greater London",
    "sg:tags":[
        "broadcasting"
    ],
    "wof:name":"Casetv Com Ltd.",
    "wof:placetype":"venue"
},
  "geometry": {"coordinates":[-0.10308,51.523472],"type":"Point"}
}