{
  "type": "Feature",
  "properties": {
    "addr:full":"16 The Maltings Uttoxeter Derbyshire ST14 7LN",
    "addr:housenumber":"16",
    "addr:postcode":"st14 7ln",
    "addr:street":"The Maltings Uttoxeter",
    "iso:country":"GB",
    "sg:address":"16 The Maltings",
    "sg:city":"Uttoxeter",
    "sg:classifiers":[
        {
            "category":"Shopping",
            "subcategory":"Gifts & Souvenirs",
            "type":"Retail Goods"
        }
    ],
    "sg:phone":"+44 1889 565528",
    "sg:postcode":"ST14 7LN",
    "sg:province":"Derbyshire",
    "sg:tags":[
        "poster",
        "card"
    ],
    "wof:name":"Pamela Joan Cards & Gifts",
    "wof:placetype":"venue"
},
  "geometry": {"coordinates":[-1.865519,52.899891],"type":"Point"}
}