{
  "type": "Feature",
  "properties": {
    "addr:full":"36 Brownfield Welwyn Garden City Hertfordshire AL7 1AN",
    "addr:housenumber":"36",
    "addr:postcode":"al7 1an",
    "addr:street":"Brownfield Welwyn",
    "iso:country":"GB",
    "sg:address":"36 Brownfield",
    "sg:city":"Welwyn Garden City",
    "sg:classifiers":[
        {
            "category":"Retail",
            "subcategory":"Auto Repair",
            "type":"Services"
        }
    ],
    "sg:phone":"+44 1707 371549",
    "sg:postcode":"AL7 1AN",
    "sg:province":"Hertfordshire",
    "sg:tags":[
        "body",
        "car"
    ],
    "wof:name":"R G F Ltd.",
    "wof:placetype":"venue"
},
  "geometry": {"coordinates":[-0.190019995,51.8041038513],"type":"Point"}
}