{
  "type": "Feature",
  "properties": {
    "addr:full":"Sunny View, 113 Monks Dyke Rd Louth Lincolnshire LN11 8DN",
    "addr:housenumber":"113",
    "addr:postcode":"ln11 8dn",
    "addr:street":"Monks Dyke Rd Louth",
    "iso:country":"GB",
    "sg:address":"Sunny View, 113 Monks Dyke Rd",
    "sg:city":"Louth",
    "sg:classifiers":[
        {
            "category":"Professional",
            "subcategory":"Engineering",
            "type":"Services"
        }
    ],
    "sg:phone":"+44 1507 603833",
    "sg:postcode":"LN11 8DN",
    "sg:province":"Lincolnshire",
    "sg:tags":[
        "contractor",
        "electrical",
        "engineer"
    ],
    "wof:name":"John Winter",
    "wof:placetype":"venue"
},
  "geometry": {"coordinates":[-0.007391,53.366497],"type":"Point"}
}