{
  "type": "Feature",
  "properties": {
    "iso:country":"GB",
    "sg:address":"31 Morrell Rd",
    "sg:city":"Manchester",
    "sg:classifiers":[
        {
            "category":"Building & Trades",
            "subcategory":"Plumbing",
            "type":"Services"
        }
    ],
    "sg:phone":"+44 161 998 4531",
    "sg:postcode":"M22 4WJ",
    "sg:province":"Greater Manchester",
    "sg:tags":[
        "heating"
    ],
    "wof:name":"G Holmes",
    "wof:placetype":"venue"
},
  "geometry": {"coordinates":[-2.2559111118,53.4058151245],"type":"Point"}
}