{
  "type": "Feature",
  "properties": {
    "addr:full":"2 Carr Street Blyth Northumberland NE24 4NG",
    "addr:housenumber":"2",
    "addr:postcode":"ne24 4ng",
    "addr:street":"Carr Street;Northumberland",
    "iso:country":"GB",
    "sg:address":"2 Carr Street",
    "sg:city":"Blyth",
    "sg:classifiers":[
        {
            "category":"Personal",
            "subcategory":"Beauty Salon",
            "type":"Services"
        },
        {
            "category":"Personal",
            "subcategory":"Barber",
            "type":"Services"
        }
    ],
    "sg:phone":"+44 1670 353779",
    "sg:postcode":"NE24 4NG",
    "sg:province":"Northumberland",
    "sg:tags":[
        "unisex",
        "hairdresser"
    ],
    "wof:name":"Susan's",
    "wof:placetype":"venue"
},
  "geometry": {"coordinates":[-1.529533,55.112324],"type":"Point"}
}