{
  "type": "Feature",
  "properties": {
    "addr:full":"Holburn St Aberdeen Aberdeen City AB10 6BS",
    "addr:postcode":"ab10 6bs",
    "addr:street":"Holburn St",
    "iso:country":"GB",
    "sg:address":"Holburn St",
    "sg:city":"Aberdeen",
    "sg:classifiers":[
        {
            "category":"Place Of Worship",
            "type":"Public Place"
        }
    ],
    "sg:phone":"+44 1224 322631",
    "sg:postcode":"AB10 6BS",
    "sg:province":"Aberdeen City",
    "wof:name":"St James' Episcopal Church",
    "wof:placetype":"venue"
},
  "geometry": {"coordinates":[-2.112289,57.142319],"type":"Point"}
}