{
  "type": "Feature",
  "properties": {
    "addr:full":"24 Castle Street East Cowes Isle of Wight PO32 6RD",
    "addr:housenumber":"24",
    "addr:postcode":"po32 6rd",
    "addr:street":"Castle Street",
    "iso:country":"GB",
    "sg:address":"24 Castle Street",
    "sg:city":"East Cowes",
    "sg:classifiers":[
        {
            "category":"Shopping",
            "subcategory":"News",
            "type":"Retail Goods"
        }
    ],
    "sg:postcode":"PO32 6RD",
    "sg:province":"Isle of Wight",
    "sg:tags":[
        "newsagent"
    ],
    "wof:name":"The News Shop",
    "wof:placetype":"venue"
},
  "geometry": {"coordinates":[-1.28958,50.758247],"type":"Point"}
}