{
  "type": "Feature",
  "properties": {
    "addr:full":"25 Fitzwilliam Street, Park Gate Rotherham South Yorkshire S62 6EP",
    "addr:housenumber":"25",
    "addr:postcode":"s62 6ep",
    "addr:street":"Fitzwilliam Street Park",
    "iso:country":"GB",
    "sg:address":"25 Fitzwilliam Street, Park Gate",
    "sg:city":"Rotherham",
    "sg:classifiers":[
        {
            "category":"Retail",
            "subcategory":"Repair Shop",
            "type":"Services"
        },
        {
            "category":"Building & Trades",
            "subcategory":"Construction",
            "type":"Services"
        }
    ],
    "sg:phone":"+44 1709 522413",
    "sg:postcode":"S62 6EP",
    "sg:province":"South Yorkshire",
    "sg:tags":[
        "builder",
        "upholsterer"
    ],
    "wof:name":"B T P Upholstery",
    "wof:placetype":"venue"
},
  "geometry": {"coordinates":[-1.345851,53.45171],"type":"Point"}
}