{
  "type": "Feature",
  "properties": {
    "iso:country":"GB",
    "sg:address":"14 Black Jack Street",
    "sg:city":"Cirencester",
    "sg:classifiers":[
        {
            "category":"Food & Beverages",
            "subcategory":"Meat & Fish",
            "type":"Retail Goods"
        }
    ],
    "sg:phone":"+44 1285 653387",
    "sg:postcode":"GL7 2AA",
    "sg:province":"Gloucestershire",
    "sg:tags":[
        "butcher"
    ],
    "wof:name":"Jesse Smith",
    "wof:placetype":"venue"
},
  "geometry": {"coordinates":[-1.969597,51.71748],"type":"Point"}
}