{
  "type": "Feature",
  "properties": {
    "addr:full":"Westlake Domgay Road, Four Crosses Llanymynech Shropshire SY22 6SJ",
    "addr:postcode":"sy22 6sj",
    "addr:street":"Domgay Road Four",
    "iso:country":"GB",
    "sg:address":"Westlake Domgay Road, Four Crosses",
    "sg:city":"Llanymynech",
    "sg:classifiers":[
        {
            "category":"Recreation",
            "subcategory":"Fishing",
            "type":"Entertainment"
        }
    ],
    "sg:phone":"+44 1691 831475",
    "sg:postcode":"SY22 6SJ",
    "sg:province":"Shropshire",
    "sg:tags":[
        "angling"
    ],
    "wof:name":"West Lake Fishery",
    "wof:placetype":"venue"
},
  "geometry": {"coordinates":[-3.089354,52.780853],"type":"Point"}
}