{
  "type": "Feature",
  "properties": {
    "iso:country":"GB",
    "sg:address":"6 Poole Road, West Ewell",
    "sg:city":"Epsom",
    "sg:classifiers":[
        {
            "category":"Communications",
            "type":"Services"
        }
    ],
    "sg:postcode":"KT19 9RY",
    "sg:province":"Surrey",
    "sg:tags":[
        "telecommunication"
    ],
    "wof:name":"Communications Mix Ltd",
    "wof:placetype":"venue"
},
  "geometry": {"coordinates":[-0.266962,51.357281],"type":"Point"}
}