{
  "type": "Feature",
  "properties": {
    "iso:country":"GB",
    "sg:address":"16 St Clements St",
    "sg:city":"Oxford",
    "sg:classifiers":[
        {
            "category":"Restaurant",
            "type":"Food & Drink"
        }
    ],
    "sg:phone":"+44 1865 792727",
    "sg:postcode":"OX4 1AB",
    "sg:province":"Oxfordshire",
    "sg:tags":[
        "mexican"
    ],
    "wof:name":"El Meson Castellano",
    "wof:placetype":"venue"
},
  "geometry": {"coordinates":[-1.24361,51.750275],"type":"Point"}
}