{
  "type": "Feature",
  "properties": {
    "addr:full":"A45 London Road, Ryton On Dunsmore Coventry Warwickshire CV8 3DY",
    "addr:postcode":"cv8 3dy",
    "addr:street":"London Road",
    "iso:country":"GB",
    "sg:address":"A45 London Road, Ryton On Dunsmore",
    "sg:city":"Coventry",
    "sg:classifiers":[
        {
            "category":"Travel",
            "subcategory":"Hotels & Motels",
            "type":"Entertainment"
        }
    ],
    "sg:phone":"+44 24 7630 1585",
    "sg:postcode":"CV8 3DY",
    "sg:province":"Warwickshire",
    "wof:name":"Courtyard Coventry",
    "wof:placetype":"venue"
},
  "geometry": {"coordinates":[-1.4459500313,52.3701896667],"type":"Point"}
}