{
  "type": "Feature",
  "properties": {
    "iso:country":"GB",
    "sg:address":"Unit 13 Mulberry Business Centre, Quebec Way",
    "sg:city":"Sth Bermondsey",
    "sg:classifiers":[
        {
            "category":"Shopping",
            "subcategory":"Stationery & Office Supplies",
            "type":"Retail Goods"
        }
    ],
    "sg:phone":"+44 20 7237 5251",
    "sg:postcode":"SE16 1LB",
    "sg:province":"Greater London",
    "sg:tags":[
        "printers'"
    ],
    "wof:name":"Alan K Carter Litho Supplies Ltd",
    "wof:placetype":"venue"
},
  "geometry": {"coordinates":[-0.0532,51.496029],"type":"Point"}
}