{
  "type": "Feature",
  "properties": {
    "addr:full":"Unit 1 Stoke Mill, Mill Rd Bedford Bedfordshire MK44 1NN",
    "addr:housenumber":"unit 1",
    "addr:postcode":"mk44 1nn",
    "addr:street":"Stoke Mill Mill Rd",
    "iso:country":"GB",
    "sg:address":"Unit 1 Stoke Mill, Mill Rd",
    "sg:city":"Bedford",
    "sg:classifiers":[
        {
            "category":"Wholesale",
            "subcategory":"Machinery & Supplies",
            "type":"Manufacturing & Wholesale Goods"
        }
    ],
    "sg:phone":"+44 1234 782882",
    "sg:postcode":"MK44 1NN",
    "sg:province":"Bedfordshire",
    "sg:tags":[
        "industrial",
        "commercial"
    ],
    "wof:name":"Ultrapost",
    "wof:placetype":"venue"
},
  "geometry": {"coordinates":[-0.52132,52.220852],"type":"Point"}
}