{
  "type": "Feature",
  "properties": {
    "iso:country":"GB",
    "sg:address":"Unit 3 Station Road Indstl Est",
    "sg:city":"Hailsham",
    "sg:classifiers":[
        {
            "category":"Professional",
            "subcategory":"Printing & Photocopies",
            "type":"Services"
        }
    ],
    "sg:phone":"+44 1323 849149",
    "sg:postcode":"BN27 2EH",
    "sg:province":"East Sussex",
    "sg:tags":[
        "plate",
        "printer",
        "lithographic",
        "maker"
    ],
    "wof:name":"Prime Press Ltd",
    "wof:placetype":"venue"
},
  "geometry": {"coordinates":[0.25755,50.861504],"type":"Point"}
}