{
  "type": "Feature",
  "properties": {
    "addr:full":"Unit 1 Cambridge Close Retail Park, Cambridge Clo Aylesbury Buckinghamshire HP20 1DF",
    "addr:housenumber":"unit 1",
    "addr:postcode":"hp20 1df",
    "addr:street":"Cambridge Close Retail Park;Clo",
    "iso:country":"GB",
    "sg:address":"Unit 1 Cambridge Close Retail Park, Cambridge Clo",
    "sg:city":"Aylesbury",
    "sg:classifiers":[
        {
            "category":"Home & Garden",
            "subcategory":"Carpets & Floor Coverings",
            "type":"Retail Goods"
        }
    ],
    "sg:phone":"+44 1296 427227",
    "sg:postcode":"HP20 1DF",
    "sg:province":"Buckinghamshire",
    "sg:tags":[
        "carpets",
        "rug",
        "matting"
    ],
    "wof:name":"Allied Carpet Stores",
    "wof:placetype":"venue"
},
  "geometry": {"coordinates":[-0.8093929887,51.8203163147],"type":"Point"}
}