{
  "type": "Feature",
  "properties": {
    "iso:country":"GB",
    "sg:address":"Cygnus Way, Black Country New Road",
    "sg:city":"West Bromwich",
    "sg:classifiers":[
        {
            "category":"Building & Trades",
            "subcategory":"Construction",
            "type":"Services"
        }
    ],
    "sg:phone":"+44 121 521 2500",
    "sg:postcode":"B70 0XB",
    "sg:province":"West Midlands",
    "sg:tags":[
        "fork",
        "lift",
        "truck"
    ],
    "wof:name":"Barloworld Handling Ltd",
    "wof:placetype":"venue"
},
  "geometry": {"coordinates":[-2.026343,52.530884],"type":"Point"}
}