{
  "type": "Feature",
  "properties": {
    "iso:country":"GB",
    "sg:address":"8-10 Portland Street",
    "sg:city":"Kilmarnock",
    "sg:classifiers":[
        {
            "category":"Shopping",
            "subcategory":"Shoes",
            "type":"Retail Goods"
        }
    ],
    "sg:phone":"+44 1563 524340",
    "sg:postcode":"KA1 2BS",
    "sg:province":"East Ayrshire",
    "sg:tags":[
        "shop"
    ],
    "wof:name":"Clarks",
    "wof:placetype":"venue"
},
  "geometry": {"coordinates":[-4.500569,55.607704],"type":"Point"}
}