{
  "type": "Feature",
  "properties": {
    "iso:country":"GB",
    "sg:address":"The Greenway",
    "sg:city":"Middlesbrough",
    "sg:classifiers":[
        {
            "category":"Arena",
            "subcategory":"Sports Club",
            "type":"Entertainment"
        }
    ],
    "sg:phone":"+44 1642 250174",
    "sg:postcode":"TS3 9PA",
    "sg:province":"North Yorkshire",
    "sg:tags":[
        "ground"
    ],
    "wof:name":"Thorntree Park Pavilion",
    "wof:placetype":"venue"
},
  "geometry": {"coordinates":[-1.184429,54.566265],"type":"Point"}
}