{
  "type": "Feature",
  "properties": {
    "addr:full":"Unit 6l Caxton Trading Estate, Printing House Lane Hayes Greater London UB3 1BE",
    "addr:housenumber":"6l",
    "addr:postcode":"ub3 1be",
    "addr:street":"Trading;House Lane",
    "iso:country":"GB",
    "sg:address":"Unit 6l Caxton Trading Estate, Printing House Lane",
    "sg:city":"Hayes",
    "sg:classifiers":[
        {
            "category":"Wholesale",
            "subcategory":"Construction Materials",
            "type":"Manufacturing & Wholesale Goods"
        }
    ],
    "sg:phone":"+44 20 8561 1423",
    "sg:postcode":"UB3 1BE",
    "sg:province":"Greater London",
    "sg:tags":[
        "coating",
        "powder"
    ],
    "wof:name":"G R Engineering Co. Ltd.",
    "wof:placetype":"venue"
},
  "geometry": {"coordinates":[-0.424756,51.501553],"type":"Point"}
}