{
  "type": "Feature",
  "properties": {
    "addr:full":"Lower Stockton Farm, Lower Stockton Marton Welshpool Shropshire SY21 8JL",
    "addr:postcode":"sy21 8jl",
    "addr:street":"Lower Stockton;Lower",
    "iso:country":"GB",
    "sg:address":"Lower Stockton Farm, Lower Stockton Marton",
    "sg:city":"Welshpool",
    "sg:classifiers":[
        {
            "category":"Farming",
            "subcategory":"Farm",
            "type":"Manufacturing & Wholesale Goods"
        }
    ],
    "sg:phone":"+44 1938 561221",
    "sg:postcode":"SY21 8JL",
    "sg:province":"Shropshire",
    "sg:tags":[
        "mixed",
        "crop"
    ],
    "wof:name":"D S Clare",
    "wof:placetype":"venue"
},
  "geometry": {"coordinates":[-3.145203,52.66119],"type":"Point"}
}