{
  "type": "Feature",
  "properties": {
    "addr:full":"24 West Fryerne Reading Berkshire RG30 2BY",
    "addr:housenumber":"24",
    "addr:postcode":"rg30 2by",
    "addr:street":"West Fryerne",
    "iso:country":"GB",
    "sg:address":"24 West Fryerne",
    "sg:city":"Reading",
    "sg:classifiers":[
        {
            "category":"Retail",
            "subcategory":"Driving School",
            "type":"Services"
        }
    ],
    "sg:postcode":"RG30 2BY",
    "sg:province":"Berkshire",
    "wof:name":"Colin School of Motoring",
    "wof:placetype":"venue"
},
  "geometry": {"coordinates":[-1.0004520416,51.4512901306],"type":"Point"}
}