{
  "type": "Feature",
  "properties": {
    "addr:full":"Main St, Cambuslang Glasgow South Lanarkshire G72 7EX",
    "addr:postcode":"g72 7ex",
    "addr:street":"Main St",
    "iso:country":"GB",
    "sg:address":"Main St, Cambuslang",
    "sg:city":"Glasgow",
    "sg:classifiers":[
        {
            "category":"Home & Garden",
            "subcategory":"Furniture",
            "type":"Retail Goods"
        }
    ],
    "sg:postcode":"G72 7EX",
    "sg:province":"South Lanarkshire",
    "wof:name":"Sweeney,Patrick,",
    "wof:placetype":"venue"
},
  "geometry": {"coordinates":[-4.172374,55.819805],"type":"Point"}
}