{
  "type": "Feature",
  "properties": {
    "addr:full":"180 Tulketh Brow, Ashton On Ribble Preston Lancashire PR2 2JJ",
    "addr:housenumber":"180",
    "addr:postcode":"pr2 2jj",
    "addr:street":"Tulketh Brow",
    "iso:country":"GB",
    "sg:address":"180 Tulketh Brow, Ashton On Ribble",
    "sg:city":"Preston",
    "sg:classifiers":[
        {
            "category":"Cinema",
            "subcategory":"Movie Rental",
            "type":"Entertainment"
        }
    ],
    "sg:phone":"+44 1772 726911",
    "sg:postcode":"PR2 2JJ",
    "sg:province":"Lancashire",
    "sg:tags":[
        "video",
        "library"
    ],
    "wof:name":"Jack Beanstalk Video",
    "wof:placetype":"venue"
},
  "geometry": {"coordinates":[-2.7259190083,53.7678718567],"type":"Point"}
}