{
  "type": "Feature",
  "properties": {
    "addr:full":"Chapel St, Goslawdales, Hillside Terr Selkirk Scottish Borders TD7 4EP",
    "addr:postcode":"td7 4ep",
    "addr:street":"Chapel St Goslawdales",
    "iso:country":"GB",
    "sg:address":"Chapel St, Goslawdales, Hillside Terr",
    "sg:city":"Selkirk",
    "sg:classifiers":[
        {
            "category":"Community Center",
            "type":"Public Place"
        }
    ],
    "sg:phone":"+44 1750 721591",
    "sg:postcode":"TD7 4EP",
    "sg:province":"Scottish Borders",
    "sg:tags":[
        "centre"
    ],
    "wof:name":"Argus Community Centre",
    "wof:placetype":"venue"
},
  "geometry": {"coordinates":[-2.8394839764,55.5493354797],"type":"Point"}
}