{
  "type": "Feature",
  "properties": {
    "iso:country":"GB",
    "sg:address":"298a Chiswick High Road",
    "sg:city":"London",
    "sg:classifiers":[
        {
            "category":"Shopping",
            "subcategory":"Tobacco",
            "type":"Retail Goods"
        }
    ],
    "sg:phone":"+44 20 8994 4820",
    "sg:postcode":"W4 1PA",
    "sg:province":"Greater London",
    "sg:tags":[
        "tobacconist"
    ],
    "wof:name":"Shears",
    "wof:placetype":"venue"
},
  "geometry": {"coordinates":[-0.260475,51.492588],"type":"Point"}
}