{
  "type": "Feature",
  "properties": {
    "iso:country":"GB",
    "sg:address":"New Yard, Mill St East",
    "sg:city":"Dewsbury",
    "sg:classifiers":[
        {
            "category":"Freight",
            "type":"Transportation"
        }
    ],
    "sg:phone":"+44 1924 462401",
    "sg:postcode":"WF12 9BQ",
    "sg:province":"West Yorkshire",
    "sg:tags":[
        "haulage",
        "road"
    ],
    "wof:name":"K D Wrigglesworth Ltd.",
    "wof:placetype":"venue"
},
  "geometry": {"coordinates":[-1.62476,53.68288],"type":"Point"}
}