{
  "type": "Feature",
  "properties": {
    "addr:full":"Windmill Avenue, Kilburn Belper Derbyshire DE56 0PQ",
    "addr:postcode":"de56 0pq",
    "addr:street":"Windmill Avenue",
    "iso:country":"GB",
    "sg:address":"Windmill Avenue, Kilburn",
    "sg:city":"Belper",
    "sg:classifiers":[
        {
            "category":"Food & Beverages",
            "subcategory":"Supermarket",
            "type":"Retail Goods"
        },
        {
            "category":"Food & Beverages",
            "subcategory":"Groceries & Convenience Stores",
            "type":"Retail Goods"
        }
    ],
    "sg:phone":"+44 1332 880453",
    "sg:postcode":"DE56 0PQ",
    "sg:province":"Derbyshire",
    "wof:name":"Spar",
    "wof:placetype":"venue"
},
  "geometry": {"coordinates":[-1.4373650551,53.0078353882],"type":"Point"}
}