{
  "type": "Feature",
  "properties": {
    "addr:full":"388 Holdenhurst Road Bournemouth Dorset BH8 8BL",
    "addr:housenumber":"388",
    "addr:postcode":"bh8 8bl",
    "addr:street":"Holdenhurst Road",
    "iso:country":"GB",
    "sg:address":"388 Holdenhurst Road",
    "sg:city":"Bournemouth",
    "sg:classifiers":[
        {
            "category":"Shopping",
            "subcategory":"News",
            "type":"Retail Goods"
        }
    ],
    "sg:phone":"+44 1202 391394",
    "sg:postcode":"BH8 8BL",
    "sg:province":"Dorset",
    "sg:tags":[
        "newsagent"
    ],
    "wof:name":"Springbourne News",
    "wof:placetype":"venue"
},
  "geometry": {"coordinates":[-1.850202,50.732754],"type":"Point"}
}