{
  "type": "Feature",
  "properties": {
    "addr:full":"106 London Rd Liverpool Merseyside L3 5JY",
    "addr:housenumber":"106",
    "addr:postcode":"l3 5jy",
    "addr:street":"London Rd",
    "iso:country":"GB",
    "sg:address":"106 London Rd",
    "sg:city":"Liverpool",
    "sg:classifiers":[
        {
            "category":"Education",
            "subcategory":"Special Training",
            "type":"Public Place"
        }
    ],
    "sg:phone":"+44 151 281 6647",
    "sg:postcode":"L3 5JY",
    "sg:province":"Merseyside",
    "sg:tags":[
        "product",
        "centre"
    ],
    "wof:name":"Kinetic Computer Systems",
    "wof:placetype":"venue"
},
  "geometry": {"coordinates":[-2.9721679688,53.409324646],"type":"Point"}
}