{
  "type": "Feature",
  "properties": {
    "addr:full":"Unit 1b Greenhill Industrial Estate, Birmingham Road Kidderminster Staffordshire DY10 2RN",
    "addr:housenumber":"unit 1b",
    "addr:postcode":"dy10 2rn",
    "addr:street":"Greenhill Industrial Estate Birmingham Road",
    "iso:country":"GB",
    "sg:address":"Unit 1b Greenhill Industrial Estate, Birmingham Road",
    "sg:city":"Kidderminster",
    "sg:classifiers":[
        {
            "category":"Shopping",
            "type":"Retail Goods"
        }
    ],
    "sg:phone":"+44 1562 824545",
    "sg:postcode":"DY10 2RN",
    "sg:province":"Staffordshire",
    "sg:tags":[
        "part",
        "accessory"
    ],
    "wof:name":"Partco",
    "wof:placetype":"venue"
},
  "geometry": {"coordinates":[-2.2490839958,52.3881111145],"type":"Point"}
}