{
  "type": "Feature",
  "properties": {
    "addr:full":"148 Alcester Road, Moseley Birmingham West Midlands B13 8HS",
    "addr:housenumber":"148",
    "addr:postcode":"b13 8hs",
    "addr:street":"Alcester Road",
    "iso:country":"GB",
    "sg:address":"148 Alcester Road, Moseley",
    "sg:city":"Birmingham",
    "sg:classifiers":[
        {
            "category":"Food & Beverages",
            "subcategory":"Specialty",
            "type":"Retail Goods"
        }
    ],
    "sg:phone":"+44 121 449 6909",
    "sg:postcode":"B13 8HS",
    "sg:province":"West Midlands",
    "sg:tags":[
        "product",
        "health"
    ],
    "wof:name":"Sage Wholefoods (Moseley) Ltd.",
    "wof:placetype":"venue"
},
  "geometry": {"coordinates":[-1.8877979517,52.4478492737],"type":"Point"}
}