{
  "type": "Feature",
  "properties": {
    "addr:full":"77-79 Rushey Green Catford Greater London SE6 4AF",
    "addr:housenumber":"77-79",
    "addr:postcode":"se6 4af",
    "addr:street":"Rushey Green",
    "iso:country":"GB",
    "sg:address":"77-79 Rushey Green",
    "sg:city":"Catford",
    "sg:classifiers":[
        {
            "category":"Organizations",
            "subcategory":"Membership Organization",
            "type":"Services"
        }
    ],
    "sg:postcode":"SE6 4AF",
    "sg:province":"Greater London",
    "sg:tags":[
        "club"
    ],
    "wof:name":"Kennard Street Community Centre",
    "wof:placetype":"venue"
},
  "geometry": {"coordinates":[-0.017574,51.448139],"type":"Point"}
}