{
  "type": "Feature",
  "properties": {
    "addr:full":"26 Knowsley Street Manchester Greater Manchester M8 8HQ",
    "addr:housenumber":"26",
    "addr:postcode":"m8 8hq",
    "addr:street":"Knowsley Street",
    "iso:country":"GB",
    "sg:address":"26 Knowsley Street",
    "sg:city":"Manchester",
    "sg:classifiers":[
        {
            "category":"Manufacturing",
            "subcategory":"Rubber & Plastics",
            "type":"Manufacturing & Wholesale Goods"
        }
    ],
    "sg:phone":"+44 161 832 7361",
    "sg:postcode":"M8 8HQ",
    "sg:province":"Greater Manchester",
    "sg:tags":[
        "product",
        "foam"
    ],
    "wof:name":"Rather Bros",
    "wof:placetype":"venue"
},
  "geometry": {"coordinates":[-2.2417640686,53.4939842224],"type":"Point"}
}