{
  "type": "Feature",
  "properties": {
    "addr:full":"Blackdyke Industrial Estate, Silloth Wigton Cumbria CA7 4PD",
    "addr:postcode":"ca7 4pd",
    "iso:country":"GB",
    "sg:address":"Blackdyke Industrial Estate, Silloth",
    "sg:city":"Wigton",
    "sg:classifiers":[
        {
            "category":"Manufacturing",
            "subcategory":"Building Materials",
            "type":"Manufacturing & Wholesale Goods"
        }
    ],
    "sg:phone":"+44 16973 31324",
    "sg:postcode":"CA7 4PD",
    "sg:province":"Cumbria",
    "sg:tags":[
        "concrete",
        "product"
    ],
    "wof:name":"Coulthards Concrete Products (1980) Ltd.",
    "wof:placetype":"venue"
},
  "geometry": {"coordinates":[-3.3869590759,54.8679962158],"type":"Point"}
}