{
  "type": "Feature",
  "properties": {
    "addr:full":"210a Hoe Street London Greater London E17 4QH",
    "addr:housenumber":"210a",
    "addr:postcode":"e17 4qh",
    "addr:street":"Hoe Street",
    "iso:country":"GB",
    "sg:address":"210a Hoe Street",
    "sg:city":"London",
    "sg:classifiers":[
        {
            "category":"Professional",
            "subcategory":"Computer Services",
            "type":"Services"
        }
    ],
    "sg:phone":"+44 20 8509 1029",
    "sg:postcode":"E17 4QH",
    "sg:province":"Greater London",
    "sg:tags":[
        "consultant"
    ],
    "wof:name":"The Learning Shop",
    "wof:placetype":"venue"
},
  "geometry": {"coordinates":[-0.0197519995,51.5856628418],"type":"Point"}
}