{
  "type": "Feature",
  "properties": {
    "iso:country":"GB",
    "sg:address":"Manor Farm, Mill Road",
    "sg:city":"Brackley",
    "sg:classifiers":[
        {
            "category":"Farming",
            "subcategory":"Farm",
            "type":"Manufacturing & Wholesale Goods"
        }
    ],
    "sg:phone":"+44 1280 850253",
    "sg:postcode":"NN13 5TQ",
    "sg:province":"Buckinghamshire",
    "sg:tags":[
        "mixed",
        "crop"
    ],
    "wof:name":"S V Clarke & Co.",
    "wof:placetype":"venue"
},
  "geometry": {"coordinates":[-1.069209,52.067169],"type":"Point"}
}