{
  "type": "Feature",
  "properties": {
    "addr:full":"Ravensworth Hill Richmond Durham DL11 7ET",
    "addr:postcode":"dl11 7et",
    "addr:street":"Ravensworth Hill",
    "iso:country":"GB",
    "sg:address":"Ravensworth Hill",
    "sg:city":"Richmond",
    "sg:classifiers":[
        {
            "category":"Bars & Pubs",
            "type":"Food & Drink"
        }
    ],
    "sg:phone":"+44 1325 718328",
    "sg:postcode":"DL11 7ET",
    "sg:province":"Durham",
    "sg:tags":[
        "pubs",
        "inn"
    ],
    "wof:name":"Bayhorse Inn",
    "wof:placetype":"venue"
},
  "geometry": {"coordinates":[-1.7851879597,54.4670906067],"type":"Point"}
}