{
  "type": "Feature",
  "properties": {
    "iso:country":"GB",
    "sg:address":"3 Hill View",
    "sg:city":"Pontypridd",
    "sg:classifiers":[
        {
            "category":"Recreation",
            "type":"Entertainment"
        }
    ],
    "sg:phone":"+44 1443 201230",
    "sg:postcode":"CF38 2DS",
    "sg:province":"Rhondda, Cynon, Taff",
    "sg:tags":[
        "snooker",
        "billiards",
        "pool"
    ],
    "wof:name":"Pool Table Services",
    "wof:placetype":"venue"
},
  "geometry": {"coordinates":[-3.3528530598,51.5545959473],"type":"Point"}
}