{
  "type": "Feature",
  "properties": {
    "addr:full":"St Marys Road, Manningham Bradford West Yorkshire BD8 7QN",
    "addr:postcode":"bd8 7qn",
    "addr:street":"St Marys Road",
    "iso:country":"GB",
    "sg:address":"St Marys Road, Manningham",
    "sg:city":"Bradford",
    "sg:classifiers":[
        {
            "category":"Social Services",
            "subcategory":"Retirement Home",
            "type":"Services"
        }
    ],
    "sg:phone":"+44 1274 547984",
    "sg:postcode":"BD8 7QN",
    "sg:province":"West Yorkshire",
    "sg:tags":[
        "residential",
        "care"
    ],
    "wof:name":"Nightingale Rest Home",
    "wof:placetype":"venue"
},
  "geometry": {"coordinates":[-1.771699,53.808399],"type":"Point"}
}