{
  "type": "Feature",
  "properties": {
    "addr:full":"2a Southam Street London Greater London W10 5PH",
    "addr:housenumber":"2a",
    "addr:postcode":"w10 5ph",
    "addr:street":"Southam Street",
    "iso:country":"GB",
    "sg:address":"2a Southam Street",
    "sg:city":"London",
    "sg:classifiers":[
        {
            "category":"Wholesale",
            "subcategory":"Music Publishers",
            "type":"Manufacturing & Wholesale Goods"
        }
    ],
    "sg:phone":"+44 20 8960 3253",
    "sg:postcode":"W10 5PH",
    "sg:province":"Greater London",
    "sg:tags":[
        "record"
    ],
    "wof:name":"Mumbo Jumbo",
    "wof:placetype":"venue"
},
  "geometry": {"coordinates":[-0.2070319951,51.5232009888],"type":"Point"}
}