{
  "type": "Feature",
  "properties": {
    "iso:country":"GB",
    "sg:address":"36 Wivelsfield, Eaton Bray",
    "sg:city":"Dunstable",
    "sg:classifiers":[
        {
            "category":"Taxi",
            "type":"Transportation"
        },
        {
            "category":"Military Area",
            "subcategory":"Air Force Base",
            "type":"Public Place"
        }
    ],
    "sg:phone":"+44 1525 220321",
    "sg:postcode":"LU6 2JQ",
    "sg:province":"Bedfordshire",
    "sg:tags":[
        "mini",
        "hire",
        "private",
        "cab"
    ],
    "wof:name":"First Quality Cars",
    "wof:placetype":"venue"
},
  "geometry": {"coordinates":[-0.5871409774,51.8767585754],"type":"Point"}
}