{
  "type": "Feature",
  "properties": {
    "iso:country":"GB",
    "sg:address":"Esk Suite, Gallery House, Tannery Road",
    "sg:city":"Carlisle",
    "sg:classifiers":[
        {
            "category":"Professional",
            "subcategory":"Management & Consulting",
            "type":"Services"
        }
    ],
    "sg:postcode":"CA1 2SS",
    "sg:province":"Cumbria",
    "sg:tags":[
        "consultant",
        "training"
    ],
    "wof:name":"Woodward Ltd.",
    "wof:placetype":"venue"
},
  "geometry": {"coordinates":[-2.9155499935,54.8823013306],"type":"Point"}
}