{
  "type": "Feature",
  "properties": {
    "iso:country":"GB",
    "sg:address":"Union Road",
    "sg:city":"Kingsbridge",
    "sg:classifiers":[
        {
            "category":"Wholesale",
            "subcategory":"Fruits & Vegetables",
            "type":"Manufacturing & Wholesale Goods"
        }
    ],
    "sg:phone":"+44 1548 856064",
    "sg:postcode":"TQ7 1EF",
    "sg:province":"Devon",
    "wof:name":"M W Barrett",
    "wof:placetype":"venue"
},
  "geometry": {"coordinates":[-3.780045,50.284119],"type":"Point"}
}