{
  "type": "Feature",
  "properties": {
    "iso:country":"GB",
    "sg:address":"14 Clover Park",
    "sg:city":"Swindon",
    "sg:classifiers":[
        {
            "category":"Shopping",
            "subcategory":"Computers & Home Electronics",
            "type":"Retail Goods"
        }
    ],
    "sg:postcode":"SN25 3JJ",
    "sg:province":"Wiltshire",
    "sg:tags":[
        "aerial",
        "television",
        "radio"
    ],
    "wof:name":"Abbey Ariel Services",
    "wof:placetype":"venue"
},
  "geometry": {"coordinates":[-1.813389,51.586872],"type":"Point"}
}