{
  "type": "Feature",
  "properties": {
    "addr:full":"122 Busby Road, Clarkston Glasgow East Renfrewshire G76 8BG",
    "addr:housenumber":"122",
    "addr:postcode":"g76 8bg",
    "addr:street":"Busby Road",
    "iso:country":"GB",
    "sg:address":"122 Busby Road, Clarkston",
    "sg:city":"Glasgow",
    "sg:classifiers":[
        {
            "category":"Banks & Credit Unions",
            "subcategory":"Bank",
            "type":"Services"
        }
    ],
    "sg:phone":"+44 141 951 7107",
    "sg:postcode":"G76 8BG",
    "sg:province":"East Renfrewshire",
    "wof:name":"Clydesdale Bank Plc",
    "wof:placetype":"venue"
},
  "geometry": {"coordinates":[-4.27443,55.785885],"type":"Point"}
}