{
  "type": "Feature",
  "properties": {
    "addr:full":"63 Onslow Road Southampton Hampshire SO14 0JL",
    "addr:housenumber":"63",
    "addr:postcode":"so14 0jl",
    "addr:street":"Onslow Road",
    "iso:country":"GB",
    "sg:address":"63 Onslow Road",
    "sg:city":"Southampton",
    "sg:classifiers":[
        {
            "category":"Bars & Pubs",
            "type":"Food & Drink"
        }
    ],
    "sg:phone":"+44 23 8033 0350",
    "sg:postcode":"SO14 0JL",
    "sg:province":"Hampshire",
    "sg:tags":[
        "pubs",
        "inn"
    ],
    "wof:name":"The Bevois Castle",
    "wof:placetype":"venue"
},
  "geometry": {"coordinates":[-1.3976969719,50.9151420593],"type":"Point"}
}