{
  "type": "Feature",
  "properties": {
    "iso:country":"GB",
    "sg:address":"The Holder Station, Bittacy Hill",
    "sg:city":"London",
    "sg:classifiers":[
        {
            "category":"Utilities",
            "subcategory":"Natural Gas",
            "type":"Services"
        }
    ],
    "sg:phone":"+44 20 8371 7500",
    "sg:postcode":"NW7 1HU",
    "sg:province":"Greater London",
    "wof:name":"Transco",
    "wof:placetype":"venue"
},
  "geometry": {"coordinates":[-0.2086,51.606899],"type":"Point"}
}