{
  "type": "Feature",
  "properties": {
    "iso:country":"GB",
    "sg:address":"4 Nelson Street",
    "sg:city":"Southend-on-sea",
    "sg:classifiers":[
        {
            "category":"Professional",
            "subcategory":"Lawyer & Legal Services",
            "type":"Services"
        }
    ],
    "sg:phone":"+44 1702 463466",
    "sg:postcode":"SS1 1EF",
    "sg:province":"Essex",
    "sg:tags":[
        "solicitor"
    ],
    "wof:name":"Barnes & Taylor",
    "wof:placetype":"venue"
},
  "geometry": {"coordinates":[0.710365,51.536167],"type":"Point"}
}