{
  "type": "Feature",
  "properties": {
    "iso:country":"GB",
    "sg:address":"Othona, Sunningdale Road",
    "sg:city":"Chelmsford",
    "sg:classifiers":[
        {
            "category":"Social Services",
            "subcategory":"Job Training",
            "type":"Services"
        }
    ],
    "sg:phone":"+44 1621 742415",
    "sg:postcode":"CM3 6DB",
    "sg:province":"Essex",
    "sg:tags":[
        "engineering",
        "marine"
    ],
    "wof:name":"Althorne Autos",
    "wof:placetype":"venue"
},
  "geometry": {"coordinates":[0.748556,51.655602],"type":"Point"}
}