{
  "type": "Feature",
  "properties": {
    "addr:full":"6 Bradstocks Way Abingdon Oxfordshire OX14 4BY",
    "addr:housenumber":"6",
    "addr:postcode":"ox14 4by",
    "addr:street":"Bradstocks Way",
    "iso:country":"GB",
    "sg:address":"6 Bradstocks Way",
    "sg:city":"Abingdon",
    "sg:classifiers":[
        {
            "category":"Food & Beverages",
            "subcategory":"Groceries & Convenience Stores",
            "type":"Retail Goods"
        }
    ],
    "sg:postcode":"OX14 4BY",
    "sg:province":"Oxfordshire",
    "wof:name":"Evergreen Stores & Post Office",
    "wof:placetype":"venue"
},
  "geometry": {"coordinates":[-1.285102,51.632019],"type":"Point"}
}