{
  "type": "Feature",
  "properties": {
    "iso:country":"GB",
    "sg:address":"Rectory Meadow",
    "sg:city":"Ipswich",
    "sg:classifiers":[
        {
            "category":"Government",
            "subcategory":"City Hall",
            "type":"Public Place"
        }
    ],
    "sg:phone":"+44 1473 658611",
    "sg:postcode":"IP7 6PA",
    "sg:province":"Suffolk",
    "wof:name":"Elmsett & Aldham Village Hall",
    "wof:placetype":"venue"
},
  "geometry": {"coordinates":[1.00067,52.08025],"type":"Point"}
}