{
  "type": "Feature",
  "properties": {
    "addr:full":"Stables Cottage, Forwood, Minchinhampton Stroud Gloucestershire GL6 9AB",
    "addr:postcode":"gl6 9ab",
    "addr:street":"Forwood",
    "iso:country":"GB",
    "sg:address":"Stables Cottage, Forwood, Minchinhampton",
    "sg:city":"Stroud",
    "sg:classifiers":[
        {
            "category":"Military Area",
            "subcategory":"Air Force Base",
            "type":"Public Place"
        }
    ],
    "sg:phone":"+44 1453 883719",
    "sg:postcode":"GL6 9AB",
    "sg:province":"Gloucestershire",
    "sg:tags":[
        "decorative",
        "glass",
        "mirror",
        "mnfr"
    ],
    "wof:name":"Mike Taffinder",
    "wof:placetype":"venue"
},
  "geometry": {"coordinates":[-2.1888189316,51.7051315308],"type":"Point"}
}