{
  "type": "Feature",
  "properties": {
    "addr:full":"Unit 11, Enterprise Park, Moorhouse Avenue Leeds West Yorkshire LS11 8HA",
    "addr:housenumber":"unit 11",
    "addr:postcode":"ls11 8ha",
    "addr:street":"Enterprise Park Moorhouse Avenue",
    "iso:country":"GB",
    "sg:address":"Unit 11, Enterprise Park, Moorhouse Avenue",
    "sg:city":"Leeds",
    "sg:classifiers":[
        {
            "category":"Shopping",
            "subcategory":"Mobile Phones",
            "type":"Retail Goods"
        }
    ],
    "sg:phone":"+44 113 270 3911",
    "sg:postcode":"LS11 8HA",
    "sg:province":"West Yorkshire",
    "wof:name":"Radiophone Services (U K) Ltd.",
    "wof:placetype":"venue"
},
  "geometry": {"coordinates":[-1.56639,53.768864],"type":"Point"}
}