{
  "type": "Feature",
  "properties": {
    "addr:full":"Veldon, Shepherds La Shrewsbury Shropshire SY3 8BT",
    "addr:postcode":"sy3 8bt",
    "addr:street":"La Shrewsbury",
    "iso:country":"GB",
    "sg:address":"Veldon, Shepherds La",
    "sg:city":"Shrewsbury",
    "sg:classifiers":[
        {
            "category":"Building & Trades",
            "subcategory":"Construction",
            "type":"Services"
        }
    ],
    "sg:phone":"+44 1743 850999",
    "sg:postcode":"SY3 8BT",
    "sg:province":"Shropshire",
    "sg:tags":[
        "ceiling",
        "contractor"
    ],
    "wof:name":"Shropshire Ceilings",
    "wof:placetype":"venue"
},
  "geometry": {"coordinates":[-2.8095700741,52.7221908569],"type":"Point"}
}