{
  "type": "Feature",
  "properties": {
    "iso:country":"GB",
    "sg:address":"Bulkington La",
    "sg:city":"Nuneaton",
    "sg:classifiers":[
        {
            "category":"Professional",
            "subcategory":"Lawyer & Legal Services",
            "type":"Services"
        }
    ],
    "sg:phone":"+44 24 7638 8308",
    "sg:postcode":"CV11 4SA",
    "sg:province":"Leicestershire",
    "sg:tags":[
        "advice",
        "counselling"
    ],
    "wof:name":"Nuneaton Counselling Service",
    "wof:placetype":"venue"
},
  "geometry": {"coordinates":[-1.437289,52.502644],"type":"Point"}
}