{
  "type": "Feature",
  "properties": {
    "addr:full":"56 Henry Street Liverpool Merseyside L1 5BU",
    "addr:housenumber":"56",
    "addr:postcode":"l1 5bu",
    "addr:street":"Henry Street",
    "iso:country":"GB",
    "sg:address":"56 Henry Street",
    "sg:city":"Liverpool",
    "sg:classifiers":[
        {
            "category":"Autos & Motor Vehicles",
            "subcategory":"Auto Supplies",
            "type":"Retail Goods"
        }
    ],
    "sg:phone":"+44 151 708 9035",
    "sg:postcode":"L1 5BU",
    "sg:province":"Merseyside",
    "sg:tags":[
        "tyre"
    ],
    "wof:name":"Town Tyres",
    "wof:placetype":"venue"
},
  "geometry": {"coordinates":[-2.980891,53.40089],"type":"Point"}
}