{
  "type": "Feature",
  "properties": {
    "iso:country":"GB",
    "sg:address":"Units B3 & B7, Marabout Industrial Estate",
    "sg:city":"Dorchester",
    "sg:classifiers":[
        {
            "category":"Wholesale",
            "subcategory":"Fruits & Vegetables",
            "type":"Manufacturing & Wholesale Goods"
        }
    ],
    "sg:phone":"+44 1305 264752",
    "sg:postcode":"DT1 1YA",
    "sg:province":"Dorset",
    "wof:name":"Graingers of Dorchester",
    "wof:placetype":"venue"
},
  "geometry": {"coordinates":[-2.44482,50.717548],"type":"Point"}
}