{
  "type": "Feature",
  "properties": {
    "addr:full":"Chatham Road, Sandling Maidstone Kent ME14 3AG",
    "addr:postcode":"me14 3ag",
    "addr:street":"Chatham Road",
    "iso:country":"GB",
    "sg:address":"Chatham Road, Sandling",
    "sg:city":"Maidstone",
    "sg:classifiers":[
        {
            "category":"Restaurant",
            "type":"Food & Drink"
        }
    ],
    "sg:phone":"+44 1622 752975",
    "sg:postcode":"ME14 3AG",
    "sg:province":"Kent",
    "wof:name":"Running Horse",
    "wof:placetype":"venue"
},
  "geometry": {"coordinates":[0.516965,51.294189],"type":"Point"}
}