{
  "type": "Feature",
  "properties": {
    "addr:full":"Bruce House, Elgin Street Dunfermline Fife KY12 7SA",
    "addr:postcode":"ky12 7sa",
    "addr:street":"Elgin Street",
    "iso:country":"GB",
    "sg:address":"Bruce House, Elgin Street",
    "sg:city":"Dunfermline",
    "sg:classifiers":[
        {
            "category":"Military Area",
            "subcategory":"Coast Guard Base",
            "type":"Public Place"
        },
        {
            "category":"Government",
            "subcategory":"Office",
            "type":"Public Place"
        }
    ],
    "sg:phone":"+44 1383 723615",
    "sg:postcode":"KY12 7SA",
    "sg:province":"Fife",
    "sg:tags":[
        "force",
        "armed",
        "reserve"
    ],
    "wof:name":"Territorial Auxiliary & Volunteer Reserve Association",
    "wof:placetype":"venue"
},
  "geometry": {"coordinates":[-3.459199,56.065289],"type":"Point"}
}