{
  "type": "Feature",
  "properties": {
    "iso:country":"GB",
    "sg:address":"304 Windmill Trading Est, Common Side East",
    "sg:city":"Mitcham",
    "sg:classifiers":[
        {
            "category":"Professional",
            "subcategory":"Engineering",
            "type":"Services"
        }
    ],
    "sg:phone":"+44 20 8640 2149",
    "sg:postcode":"CR4 1HY",
    "sg:province":"Greater London",
    "sg:tags":[
        "precision",
        "engineer"
    ],
    "wof:name":"J G Tools",
    "wof:placetype":"venue"
},
  "geometry": {"coordinates":[-0.1642549932,51.4071502686],"type":"Point"}
}