{
  "type": "Feature",
  "properties": {
    "addr:full":"Thomas Duggan House, Manor Lane Shipley West Yorkshire BD18 3RB",
    "addr:postcode":"bd18 3rb",
    "addr:street":"Thomas;Manor Lane",
    "iso:country":"GB",
    "sg:address":"Thomas Duggan House, Manor Lane",
    "sg:city":"Shipley",
    "sg:classifiers":[
        {
            "category":"Organizations",
            "subcategory":"Community Association",
            "type":"Services"
        }
    ],
    "sg:phone":"+44 1274 599686",
    "sg:postcode":"BD18 3RB",
    "sg:province":"West Yorkshire",
    "sg:tags":[
        "society",
        "housing"
    ],
    "wof:name":"Hanover Housing Association",
    "wof:placetype":"venue"
},
  "geometry": {"coordinates":[-1.779029,53.833405],"type":"Point"}
}