{
  "type": "Feature",
  "properties": {
    "iso:country":"GB",
    "sg:address":"61 Avondale Road",
    "sg:city":"Rayleigh",
    "sg:classifiers":[
        {
            "category":"Retail",
            "subcategory":"Auto Repair",
            "type":"Services"
        }
    ],
    "sg:postcode":"SS6 8NJ",
    "sg:province":"Essex",
    "sg:tags":[
        "modification",
        "garage"
    ],
    "wof:name":"Chapman Mobile Repairs",
    "wof:placetype":"venue"
},
  "geometry": {"coordinates":[0.621783,51.587143],"type":"Point"}
}