{
  "type": "Feature",
  "properties": {
    "addr:full":"Fish Farm Indstl Est, Tut Hill, Fornham All Saints Bury St Edmunds Cambridgeshire IP28 6LE",
    "addr:postcode":"ip28 6le",
    "addr:street":"Indstl;Tut Hill;St",
    "iso:country":"GB",
    "sg:address":"Fish Farm Indstl Est, Tut Hill, Fornham All Saints",
    "sg:city":"Bury St Edmunds",
    "sg:classifiers":[
        {
            "category":"Professional",
            "subcategory":"Business Services",
            "type":"Services"
        },
        {
            "category":"Shopping",
            "subcategory":"Pets & Pet Supplies",
            "type":"Retail Goods"
        }
    ],
    "sg:postcode":"IP28 6LE",
    "sg:province":"Cambridgeshire",
    "sg:tags":[
        "import",
        "export",
        "agent"
    ],
    "wof:name":"Hurrell,John Brian,",
    "wof:placetype":"venue"
},
  "geometry": {"coordinates":[0.688767,52.273968],"type":"Point"}
}