{
  "type": "Feature",
  "properties": {
    "addr:full":"24 Freshwater Close Luton Bedfordshire LU3 3TA",
    "addr:housenumber":"24",
    "addr:postcode":"lu3 3ta",
    "addr:street":"Freshwater Close",
    "iso:country":"GB",
    "sg:address":"24 Freshwater Close",
    "sg:city":"Luton",
    "sg:classifiers":[
        {
            "category":"Place Of Worship",
            "type":"Public Place"
        }
    ],
    "sg:phone":"+44 1582 502400",
    "sg:postcode":"LU3 3TA",
    "sg:province":"Bedfordshire",
    "wof:name":"Church Of The Holy Family",
    "wof:placetype":"venue"
},
  "geometry": {"coordinates":[-0.4476589859,51.9141693115],"type":"Point"}
}