{
  "type": "Feature",
  "properties": {
    "iso:country":"GB",
    "sg:address":"79 Gray St",
    "sg:city":"Dundee",
    "sg:classifiers":[
        {
            "category":"Food & Beverages",
            "subcategory":"Meat & Fish",
            "type":"Retail Goods"
        }
    ],
    "sg:postcode":"DD5 2BP",
    "sg:province":"Angus",
    "sg:tags":[
        "butcher"
    ],
    "wof:name":"Burnett,J B,",
    "wof:placetype":"venue"
},
  "geometry": {"coordinates":[-2.8735229969,56.4668045044],"type":"Point"}
}