{
  "type": "Feature",
  "properties": {
    "addr:full":"9 Kingsland House, 512 Wimborne Road East Ferndown Dorset BH22 9NG",
    "addr:housenumber":"9;512",
    "addr:postcode":"bh22 9ng",
    "addr:street":"Kingsland;Wimborne Road East",
    "iso:country":"GB",
    "sg:address":"9 Kingsland House, 512 Wimborne Road East",
    "sg:city":"Ferndown",
    "sg:classifiers":[
        {
            "category":"Professional",
            "subcategory":"Management & Consulting",
            "type":"Services"
        }
    ],
    "sg:postcode":"BH22 9NG",
    "sg:province":"Dorset",
    "sg:tags":[
        "consultant",
        "business"
    ],
    "wof:name":"B L Solutions Ltd.",
    "wof:placetype":"venue"
},
  "geometry": {"coordinates":[-1.8893890381,50.8018302917],"type":"Point"}
}