{
  "type": "Feature",
  "properties": {
    "addr:full":"Unit 1a, Dewhurst Row, Bamber Bridge Preston Lancashire PR5 6BB",
    "addr:housenumber":"unit 1a",
    "addr:postcode":"pr5 6bb",
    "addr:street":"Dewhurst Row",
    "iso:country":"GB",
    "sg:address":"Unit 1a, Dewhurst Row, Bamber Bridge",
    "sg:city":"Preston",
    "sg:classifiers":[
        {
            "category":"Autos & Motor Vehicles",
            "subcategory":"Auto Supplies",
            "type":"Retail Goods"
        }
    ],
    "sg:phone":"+44 1772 336139",
    "sg:postcode":"PR5 6BB",
    "sg:province":"Lancashire",
    "sg:tags":[
        "car",
        "accessory"
    ],
    "wof:name":"Bamber Bridge Auto Electrics",
    "wof:placetype":"venue"
},
  "geometry": {"coordinates":[-2.671749,53.722801],"type":"Point"}
}