{
  "type": "Feature",
  "properties": {
    "addr:full":"9 Third Avenue Wetherby North Yorkshire LS22 6JR",
    "addr:housenumber":"9",
    "addr:postcode":"ls22 6jr",
    "addr:street":"Third Avenue",
    "iso:country":"GB",
    "sg:address":"9 Third Avenue",
    "sg:city":"Wetherby",
    "sg:classifiers":[
        {
            "category":"Manufacturing",
            "subcategory":"Building Materials",
            "type":"Manufacturing & Wholesale Goods"
        }
    ],
    "sg:phone":"+44 1937 586474",
    "sg:postcode":"LS22 6JR",
    "sg:province":"North Yorkshire",
    "sg:tags":[
        "tile",
        "mnfrs"
    ],
    "wof:name":"AA Ceramic Tiling",
    "wof:placetype":"venue"
},
  "geometry": {"coordinates":[-1.378911,53.928165],"type":"Point"}
}