{
  "type": "Feature",
  "properties": {
    "iso:country":"GB",
    "sg:address":"24 Dane Heath Business Park, Wentworth Road Heathfiled",
    "sg:city":"Newton Abbot",
    "sg:classifiers":[
        {
            "category":"Shopping",
            "subcategory":"Stationery & Office Supplies",
            "type":"Retail Goods"
        }
    ],
    "sg:phone":"+44 1626 835050",
    "sg:postcode":"TQ12 6TL",
    "sg:province":"Devon",
    "wof:name":"S W Office Consultants Ltd.",
    "wof:placetype":"venue"
},
  "geometry": {"coordinates":[-3.659250021,50.5722999573],"type":"Point"}
}