{
  "type": "Feature",
  "properties": {
    "addr:full":"1 Oakwood Avenue Newbiggin By The Sea Northumberland NE64 6HD",
    "addr:housenumber":"1",
    "addr:postcode":"ne64 6hd",
    "addr:street":"Oakwood Avenue",
    "iso:country":"GB",
    "sg:address":"1 Oakwood Avenue",
    "sg:city":"Newbiggin By The Sea",
    "sg:classifiers":[
        {
            "category":"Building & Trades",
            "subcategory":"Construction",
            "type":"Services"
        }
    ],
    "sg:phone":"+44 1670 521600",
    "sg:postcode":"NE64 6HD",
    "sg:province":"Northumberland",
    "sg:tags":[
        "builder"
    ],
    "wof:name":"Lockcover Ltd",
    "wof:placetype":"venue"
},
  "geometry": {"coordinates":[-1.5176379681,55.1880493164],"type":"Point"}
}