{
  "type": "Feature",
  "properties": {
    "iso:country":"GB",
    "sg:address":"4 West Regent Street",
    "sg:city":"Glasgow",
    "sg:classifiers":[
        {
            "category":"Professional",
            "subcategory":"Lawyer & Legal Services",
            "type":"Services"
        }
    ],
    "sg:postcode":"G2 1RW",
    "sg:province":"Glasgow City",
    "sg:tags":[
        "solicitor"
    ],
    "wof:name":"Alexander Stone & Co.",
    "wof:placetype":"venue"
},
  "geometry": {"coordinates":[-4.2556,55.863136],"type":"Point"}
}