{
  "type": "Feature",
  "properties": {
    "iso:country":"GB",
    "sg:address":"26 Ridley Place",
    "sg:city":"Newcastle-upon-tyne",
    "sg:classifiers":[
        {
            "category":"Travel",
            "subcategory":"Travel Agent",
            "type":"Entertainment"
        }
    ],
    "sg:phone":"+44 191 261 4888",
    "sg:postcode":"NE1 8JW",
    "sg:province":"Tyne and Wear",
    "sg:tags":[
        "agency",
        "activity"
    ],
    "wof:name":"Dawson & Sanderson Ltd.",
    "wof:placetype":"venue"
},
  "geometry": {"coordinates":[-1.61138,54.977268],"type":"Point"}
}