{
  "type": "Feature",
  "properties": {
    "addr:full":"128 Christchurch Rd Brixton Greater London SW2 3DF",
    "addr:housenumber":"128",
    "addr:postcode":"sw2 3df",
    "addr:street":"Christchurch Rd",
    "iso:country":"GB",
    "sg:address":"128 Christchurch Rd",
    "sg:city":"Brixton",
    "sg:classifiers":[
        {
            "category":"Health Services",
            "subcategory":"Health Practitioner",
            "type":"Services"
        }
    ],
    "sg:phone":"+44 20 8671 5583",
    "sg:postcode":"SW2 3DF",
    "sg:province":"Greater London",
    "sg:tags":[
        "acupuncture"
    ],
    "wof:name":"Physiotherapy Acupuncture Clinic",
    "wof:placetype":"venue"
},
  "geometry": {"coordinates":[-0.108189,51.440327],"type":"Point"}
}