{
  "type": "Feature",
  "properties": {
    "iso:country":"GB",
    "sg:address":"430 Crownhill Road, West Park",
    "sg:city":"Plymouth",
    "sg:classifiers":[
        {
            "category":"Personal",
            "subcategory":"Beauty Salon",
            "type":"Services"
        },
        {
            "category":"Personal",
            "subcategory":"Barber",
            "type":"Services"
        }
    ],
    "sg:phone":"+44 1752 367775",
    "sg:postcode":"PL5 2QS",
    "sg:province":"Devon",
    "sg:tags":[
        "unisex",
        "hairdresser"
    ],
    "wof:name":"Y PARTRIDGE & N TULL",
    "wof:placetype":"venue"
},
  "geometry": {"coordinates":[-4.16497612,50.4129219055],"type":"Point"}
}