{
  "type": "Feature",
  "properties": {
    "iso:country":"GB",
    "sg:address":"Netherfield House, 1 Salisbury Road, Low Moor",
    "sg:city":"Bradford",
    "sg:classifiers":[
        {
            "category":"Retail",
            "subcategory":"Veterinary Services",
            "type":"Services"
        }
    ],
    "sg:phone":"+44 1274 679192",
    "sg:postcode":"BD12 0AA",
    "sg:province":"West Yorkshire",
    "sg:tags":[
        "surgeon",
        "activity"
    ],
    "wof:name":"Sage Veterinary Group",
    "wof:placetype":"venue"
},
  "geometry": {"coordinates":[-1.766435,53.756508],"type":"Point"}
}