{
  "type": "Feature",
  "properties": {
    "addr:full":"49 Havelock Road Bexhill-on-sea East Sussex TN40 2BY",
    "addr:housenumber":"49",
    "addr:postcode":"tn40 2by",
    "addr:street":"Havelock Road",
    "iso:country":"GB",
    "sg:address":"49 Havelock Road",
    "sg:city":"Bexhill-on-sea",
    "sg:classifiers":[
        {
            "category":"Building & Trades",
            "subcategory":"Construction",
            "type":"Services"
        }
    ],
    "sg:phone":"+44 1424 210652",
    "sg:postcode":"TN40 2BY",
    "sg:province":"East Sussex",
    "sg:tags":[
        "decorator",
        "painter"
    ],
    "wof:name":"P R & E M Bird",
    "wof:placetype":"venue"
},
  "geometry": {"coordinates":[0.4727669954,50.8517494202],"type":"Point"}
}