{
  "type": "Feature",
  "properties": {
    "iso:country":"GB",
    "sg:address":"John Gilbert Way, Wharfside",
    "sg:city":"Manchester",
    "sg:classifiers":[
        {
            "category":"Manufacturing",
            "subcategory":"Lumber",
            "type":"Manufacturing & Wholesale Goods"
        }
    ],
    "sg:phone":"+44 161 848 0167",
    "sg:postcode":"M17 1HL",
    "sg:province":"Cheshire",
    "sg:tags":[
        "importer",
        "merchants",
        "agent",
        "timber"
    ],
    "wof:name":"H L H Timber & Plywood Ltd.",
    "wof:placetype":"venue"
},
  "geometry": {"coordinates":[-2.3040781021,53.4639396667],"type":"Point"}
}