{
  "type": "Feature",
  "properties": {
    "iso:country":"GB",
    "sg:address":"46 The Churchills",
    "sg:city":"Newton Abbot",
    "sg:classifiers":[
        {
            "category":"Taxi",
            "type":"Transportation"
        }
    ],
    "sg:phone":"+44 1626 353656",
    "sg:postcode":"TQ12 1QN",
    "sg:province":"Devon",
    "sg:tags":[
        "mini",
        "cab"
    ],
    "wof:name":"Churchill Taxis",
    "wof:placetype":"venue"
},
  "geometry": {"coordinates":[-3.6208379269,50.5354728699],"type":"Point"}
}