{
  "type": "Feature",
  "properties": {
    "addr:full":"43 Harlington Road Mexborough South Yorkshire S64 0DF",
    "addr:housenumber":"43",
    "addr:postcode":"s64 0df",
    "addr:street":"Harlington Road",
    "iso:country":"GB",
    "sg:address":"43 Harlington Road",
    "sg:city":"Mexborough",
    "sg:classifiers":[
        {
            "category":"Banks & Credit Unions",
            "subcategory":"Bureau De Change",
            "type":"Services"
        },
        {
            "category":"Food & Beverages",
            "subcategory":"Liquor & Beverages",
            "type":"Retail Goods"
        }
    ],
    "sg:phone":"+44 1709 583509",
    "sg:postcode":"S64 0DF",
    "sg:province":"South Yorkshire",
    "sg:tags":[
        "beer",
        "wine",
        "spirit",
        "wines"
    ],
    "wof:name":"Harlington Road Off Licence",
    "wof:placetype":"venue"
},
  "geometry": {"coordinates":[-1.2796000242,53.4975662231],"type":"Point"}
}