{
  "type": "Feature",
  "properties": {
    "iso:country":"GB",
    "sg:address":"Unit 2, Seafield Way, Seafield Road East",
    "sg:city":"Edinburgh",
    "sg:classifiers":[
        {
            "category":"Wholesale",
            "subcategory":"Construction Materials",
            "type":"Manufacturing & Wholesale Goods"
        }
    ],
    "sg:phone":"+44 131 554 0298",
    "sg:postcode":"EH6 7LD",
    "sg:province":"City of Edinburgh",
    "sg:tags":[
        "lift"
    ],
    "wof:name":"Hss Lift & Shift",
    "wof:placetype":"venue"
},
  "geometry": {"coordinates":[-3.136734,55.967972],"type":"Point"}
}