{
  "type": "Feature",
  "properties": {
    "addr:full":"14 Cranbourne Close, Rubery, Rednal Birmingham West Midlands B45 0DN",
    "addr:housenumber":"14",
    "addr:postcode":"b45 0dn",
    "addr:street":"Cranbourne Close;Rednal",
    "iso:country":"GB",
    "sg:address":"14 Cranbourne Close, Rubery, Rednal",
    "sg:city":"Birmingham",
    "sg:classifiers":[
        {
            "category":"Building & Trades",
            "subcategory":"Cleaning & Sanitation",
            "type":"Services"
        },
        {
            "category":"Social Services",
            "subcategory":"Adult Care",
            "type":"Services"
        }
    ],
    "sg:phone":"+44 121 680 6304",
    "sg:postcode":"B45 0DN",
    "sg:province":"West Midlands",
    "sg:tags":[
        "contracting",
        "domestic"
    ],
    "wof:name":"L A Domestics",
    "wof:placetype":"venue"
},
  "geometry": {"coordinates":[-2.0083270073,52.4062805176],"type":"Point"}
}