{
  "type": "Feature",
  "properties": {
    "iso:country":"GB",
    "sg:address":"253 Boldmere Road",
    "sg:city":"Sutton Coldfield",
    "sg:classifiers":[
        {
            "category":"Social Services",
            "subcategory":"Retirement Home",
            "type":"Services"
        }
    ],
    "sg:phone":"+44 121 373 6562",
    "sg:postcode":"B73 5LL",
    "sg:province":"West Midlands",
    "sg:tags":[
        "rest"
    ],
    "wof:name":"Bretby House",
    "wof:placetype":"venue"
},
  "geometry": {"coordinates":[-1.8377920389,52.5417175293],"type":"Point"}
}