{
  "type": "Feature",
  "properties": {
    "iso:country":"GB",
    "sg:address":"Kingseat Road, Halbeath",
    "sg:city":"Dunfermline",
    "sg:classifiers":[
        {
            "category":"Professional",
            "subcategory":"Engineering",
            "type":"Services"
        }
    ],
    "sg:phone":"+44 1383 731651",
    "sg:postcode":"KY12 0UA",
    "sg:province":"Fife",
    "sg:tags":[
        "engineer"
    ],
    "wof:name":"Enco Engineering Supplies Ltd.",
    "wof:placetype":"venue"
},
  "geometry": {"coordinates":[-3.405519,56.08704],"type":"Point"}
}