{
  "type": "Feature",
  "properties": {
    "iso:country":"GB",
    "sg:address":"3 Chapel St, Oakthorpe",
    "sg:city":"Swadlincote",
    "sg:classifiers":[
        {
            "category":"Professional",
            "subcategory":"Engineering",
            "type":"Services"
        }
    ],
    "sg:postcode":"DE12 7QT",
    "sg:province":"Derbyshire",
    "sg:tags":[
        "contractor",
        "electrical",
        "engineer"
    ],
    "wof:name":"Robinson,Stephen John,",
    "wof:placetype":"venue"
},
  "geometry": {"coordinates":[-1.539662,52.723698],"type":"Point"}
}