{
  "type": "Feature",
  "properties": {
    "iso:country":"GB",
    "sg:address":"Unit 211, Oxo Tower Wharf, Barge House St, South Bank",
    "sg:city":"Southwark",
    "sg:classifiers":[
        {
            "category":"Professional",
            "subcategory":"Art Services",
            "type":"Services"
        }
    ],
    "sg:phone":"+44 20 7620 0330",
    "sg:postcode":"SE1 9PH",
    "sg:province":"Greater London",
    "sg:tags":[
        "consultant",
        "design"
    ],
    "wof:name":"Mak Design",
    "wof:placetype":"venue"
},
  "geometry": {"coordinates":[-0.088969,51.505634],"type":"Point"}
}