{
  "type": "Feature",
  "properties": {
    "addr:full":"Lower Cliffs Farm Rugeley Staffordshire WS15 2UY",
    "addr:housenumber":"rugeley",
    "addr:postcode":"ws15 2uy",
    "addr:street":"Lower Cliffs Farm",
    "iso:country":"GB",
    "sg:address":"Lower Cliffs Farm",
    "sg:city":"Rugeley",
    "sg:classifiers":[
        {
            "category":"Farming",
            "subcategory":"Farm",
            "type":"Manufacturing & Wholesale Goods"
        }
    ],
    "sg:postcode":"WS15 2UY",
    "sg:province":"Staffordshire",
    "sg:tags":[
        "mixed",
        "crop"
    ],
    "wof:name":"David J Woodcock",
    "wof:placetype":"venue"
},
  "geometry": {"coordinates":[-1.935352,52.757557],"type":"Point"}
}