{
  "type": "Feature",
  "properties": {
    "iso:country":"GB",
    "sg:address":"34 Ladies Drive",
    "sg:city":"Shetland",
    "sg:classifiers":[
        {
            "category":"Travel",
            "subcategory":"Hostel",
            "type":"Entertainment"
        },
        {
            "category":"Government",
            "subcategory":"Office",
            "type":"Public Place"
        }
    ],
    "sg:phone":"+44 1595 694712",
    "sg:postcode":"ZE1 0HH",
    "sg:province":"Shetland Islands",
    "sg:tags":[
        "local"
    ],
    "wof:name":"Hostel Administration Building",
    "wof:placetype":"venue"
},
  "geometry": {"coordinates":[-1.1702890396,60.1448287964],"type":"Point"}
}