{
  "type": "Feature",
  "properties": {
    "addr:full":"20 Cleaves Avenue, Colerne Chippenham Gloucestershire SN14 8BX",
    "addr:housenumber":"20",
    "addr:postcode":"sn14 8bx",
    "addr:street":"Cleaves Avenue",
    "iso:country":"GB",
    "sg:address":"20 Cleaves Avenue, Colerne",
    "sg:city":"Chippenham",
    "sg:classifiers":[
        {
            "category":"Professional",
            "subcategory":"Accounting & Tax Preparation",
            "type":"Services"
        }
    ],
    "sg:phone":"+44 1225 744544",
    "sg:postcode":"SN14 8BX",
    "sg:province":"Gloucestershire",
    "sg:tags":[
        "payroll"
    ],
    "wof:name":"A & S Payroll Management Ltd.",
    "wof:placetype":"venue"
},
  "geometry": {"coordinates":[-2.2667269707,51.4377593994],"type":"Point"}
}