{
  "type": "Feature",
  "properties": {
    "iso:country":"GB",
    "sg:address":"25a Lowndes Street",
    "sg:city":"London",
    "sg:classifiers":[
        {
            "category":"Personal",
            "subcategory":"Beauty Salon",
            "type":"Services"
        }
    ],
    "sg:phone":"+44 20 7235 3154",
    "sg:postcode":"SW1X 9JF",
    "sg:province":"Greater London",
    "wof:name":"Steiner Salon",
    "wof:placetype":"venue"
},
  "geometry": {"coordinates":[-0.157853,51.498787],"type":"Point"}
}