{
  "type": "Feature",
  "properties": {
    "addr:full":"Dennis Lane Stanmore Greater London HA7 4LA",
    "addr:postcode":"ha7 4la",
    "addr:street":"Dennis Lane",
    "iso:country":"GB",
    "sg:address":"Dennis Lane",
    "sg:city":"Stanmore",
    "sg:classifiers":[
        {
            "category":"Arena",
            "subcategory":"Sports Club",
            "type":"Entertainment"
        }
    ],
    "sg:postcode":"HA7 4LA",
    "sg:province":"Greater London",
    "wof:name":"Stanmore Bowls Club",
    "wof:placetype":"venue"
},
  "geometry": {"coordinates":[-0.317602,51.625519],"type":"Point"}
}