{
  "type": "Feature",
  "properties": {
    "iso:country":"GB",
    "sg:address":"55 Northey Avenue",
    "sg:city":"Sutton",
    "sg:classifiers":[
        {
            "category":"Utilities",
            "subcategory":"Mobile Phone",
            "type":"Services"
        },
        {
            "category":"Shopping",
            "subcategory":"Computers & Home Electronics",
            "type":"Retail Goods"
        }
    ],
    "sg:phone":"+44 20 8770 2173",
    "sg:postcode":"SM2 7HU",
    "sg:province":"Surrey",
    "sg:tags":[
        "sound",
        "equipment",
        "rental",
        "installation"
    ],
    "wof:name":"Auditronics Services",
    "wof:placetype":"venue"
},
  "geometry": {"coordinates":[-0.221642,51.345909],"type":"Point"}
}