{
  "type": "Feature",
  "properties": {
    "addr:full":"Unit 3, Rose Kiln Lane, Brunel Park Reading Berkshire RG2 0JZ",
    "addr:housenumber":"unit 3",
    "addr:postcode":"rg2 0jz",
    "addr:street":"Rose Kiln Lane Brunel Park",
    "iso:country":"GB",
    "sg:address":"Unit 3, Rose Kiln Lane, Brunel Park",
    "sg:city":"Reading",
    "sg:classifiers":[
        {
            "category":"Shopping",
            "subcategory":"Bicycles & Sporting Goods",
            "type":"Retail Goods"
        },
        {
            "category":"Sports & Exercise",
            "subcategory":"Sports Center",
            "type":"Entertainment"
        },
        {
            "category":"Home & Garden",
            "subcategory":"Carpets & Floor Coverings",
            "type":"Retail Goods"
        }
    ],
    "sg:phone":"+44 118 931 1798",
    "sg:postcode":"RG2 0JZ",
    "sg:province":"Berkshire",
    "sg:tags":[
        "shop",
        "carpets",
        "rug",
        "matting",
        "sale"
    ],
    "wof:name":"J J B Sports Plc",
    "wof:placetype":"venue"
},
  "geometry": {"coordinates":[-0.974606,51.436199],"type":"Point"}
}