{
  "type": "Feature",
  "properties": {
    "iso:country":"GB",
    "sg:address":"2 Westmead Close",
    "sg:city":"Hayling Island",
    "sg:classifiers":[
        {
            "category":"Shopping",
            "subcategory":"Crafts & Fabrics",
            "type":"Retail Goods"
        }
    ],
    "sg:postcode":"PO11 0DS",
    "sg:province":"Hampshire",
    "sg:tags":[
        "machine",
        "sewing",
        "knitting"
    ],
    "wof:name":"Read Sewing Machines",
    "wof:placetype":"venue"
},
  "geometry": {"coordinates":[-0.993692,50.787376],"type":"Point"}
}