{
  "type": "Feature",
  "properties": {
    "iso:country":"GB",
    "sg:address":"Georgian House, 24 Bird St",
    "sg:city":"Lichfield",
    "sg:classifiers":[
        {
            "category":"Real Estate",
            "subcategory":"Architect",
            "type":"Services"
        }
    ],
    "sg:phone":"+44 1543 254357",
    "sg:postcode":"WS13 6PT",
    "sg:province":"Staffordshire",
    "wof:name":"Brownhill, Hayward Brown",
    "wof:placetype":"venue"
},
  "geometry": {"coordinates":[-1.830450058,52.6832275391],"type":"Point"}
}