{
  "type": "Feature",
  "properties": {
    "addr:full":"18 City Business Centre, Basin Road Chichester West Sussex PO19 8DU",
    "addr:housenumber":"18",
    "addr:postcode":"po19 8du",
    "addr:street":"City Business Centre Basin Road",
    "iso:country":"GB",
    "sg:address":"18 City Business Centre, Basin Road",
    "sg:city":"Chichester",
    "sg:classifiers":[
        {
            "category":"Real Estate",
            "subcategory":"Surveying",
            "type":"Services"
        }
    ],
    "sg:phone":"+44 1243 783592",
    "sg:postcode":"PO19 8DU",
    "sg:province":"West Sussex",
    "sg:tags":[
        "surveyor",
        "valuer"
    ],
    "wof:name":"Cranes",
    "wof:placetype":"venue"
},
  "geometry": {"coordinates":[-0.7754290104,50.8361663818],"type":"Point"}
}