{
  "type": "Feature",
  "properties": {
    "addr:full":"28 St Johns, Puckeridge Ware Hertfordshire SG11 1SY",
    "addr:housenumber":"28",
    "addr:postcode":"sg11 1sy",
    "addr:street":"St Johns Puckeridge Ware",
    "iso:country":"GB",
    "sg:address":"28 St Johns, Puckeridge",
    "sg:city":"Ware",
    "sg:classifiers":[
        {
            "category":"Professional",
            "subcategory":"Accounting & Tax Preparation",
            "type":"Services"
        }
    ],
    "sg:postcode":"SG11 1SY",
    "sg:province":"Hertfordshire",
    "sg:tags":[
        "accountant"
    ],
    "wof:name":"Loroco",
    "wof:placetype":"venue"
},
  "geometry": {"coordinates":[0.02072,51.88908],"type":"Point"}
}