{
  "type": "Feature",
  "properties": {
    "iso:country":"GB",
    "sg:address":"31a King Street",
    "sg:city":"Belper",
    "sg:classifiers":[
        {
            "category":"Shopping",
            "subcategory":"News",
            "type":"Retail Goods"
        }
    ],
    "sg:phone":"+44 1773 826256",
    "sg:postcode":"DE56 1PX",
    "sg:province":"Derbyshire",
    "sg:tags":[
        "newsagent"
    ],
    "wof:name":"JOHN POYNTON",
    "wof:placetype":"venue"
},
  "geometry": {"coordinates":[-1.4820530415,53.0233802795],"type":"Point"}
}