{
  "type": "Feature",
  "properties": {
    "iso:country":"GB",
    "sg:address":"Rivendell, Sheethanger Lane, Felden",
    "sg:city":"Hemel Hempstead",
    "sg:classifiers":[
        {
            "category":"Professional",
            "subcategory":"Management & Consulting",
            "type":"Services"
        }
    ],
    "sg:phone":"+44 7976 739566",
    "sg:postcode":"HP3 0BQ",
    "sg:province":"Hertfordshire",
    "sg:tags":[
        "consultant",
        "business"
    ],
    "wof:name":"Received Wisdom Ltd.",
    "wof:placetype":"venue"
},
  "geometry": {"coordinates":[-0.495514,51.742466],"type":"Point"}
}