{
  "type": "Feature",
  "properties": {
    "iso:country":"GB",
    "sg:address":"Clitheroe Road, Stonyhurst, Great Mitton",
    "sg:city":"Clitheroe",
    "sg:classifiers":[
        {
            "category":"Farming",
            "subcategory":"Livestock Farm",
            "type":"Manufacturing & Wholesale Goods"
        }
    ],
    "sg:postcode":"BB7 9PH",
    "sg:province":"Lancashire",
    "sg:tags":[
        "others"
    ],
    "wof:name":"S Ainsworth",
    "wof:placetype":"venue"
},
  "geometry": {"coordinates":[-2.340724,53.836731],"type":"Point"}
}