{
  "type": "Feature",
  "properties": {
    "addr:full":"Clitheroe Road, Stonyhurst, Great Mitton Clitheroe Lancashire BB7 9PH",
    "addr:housenumber":"mitton",
    "addr:postcode":"bb7 9ph",
    "addr:street":"Clitheroe Road Stonyhurst",
    "iso:country":"GB",
    "sg:address":"Clitheroe Road, Stonyhurst, Great Mitton",
    "sg:city":"Clitheroe",
    "sg:classifiers":[
        {
            "category":"Farming",
            "subcategory":"Livestock Farm",
            "type":"Manufacturing & Wholesale Goods"
        }
    ],
    "sg:postcode":"BB7 9PH",
    "sg:province":"Lancashire",
    "sg:tags":[
        "others"
    ],
    "wof:name":"S Ainsworth",
    "wof:placetype":"venue"
},
  "geometry": {"coordinates":[-2.340724,53.836731],"type":"Point"}
}