{
  "type": "Feature",
  "properties": {
    "addr:full":"Revelstone, Idless Truro Cornwall TR4 9QS",
    "addr:postcode":"tr4 9qs",
    "iso:country":"GB",
    "sg:address":"Revelstone, Idless",
    "sg:city":"Truro",
    "sg:classifiers":[
        {
            "category":"Health Services",
            "subcategory":"Health Practitioner",
            "type":"Services"
        }
    ],
    "sg:phone":"+44 1872 242363",
    "sg:postcode":"TR4 9QS",
    "sg:province":"Cornwall",
    "sg:tags":[
        "therapist",
        "speech"
    ],
    "wof:name":"Paull Nutritional Therapist",
    "wof:placetype":"venue"
},
  "geometry": {"coordinates":[-5.0601449013,50.2860832214],"type":"Point"}
}