{
  "type": "Feature",
  "properties": {
    "iso:country":"GB",
    "sg:address":"Squids Gate, Challock",
    "sg:city":"Ashford",
    "sg:classifiers":[
        {
            "category":"Education",
            "subcategory":"Special Training",
            "type":"Public Place"
        }
    ],
    "sg:postcode":"TN25 4DR",
    "sg:province":"Kent",
    "sg:tags":[
        "school",
        "flying"
    ],
    "wof:name":"Kent Gliding Club Ltd.",
    "wof:placetype":"venue"
},
  "geometry": {"coordinates":[0.8771569729,51.2208061218],"type":"Point"}
}