{
  "type": "Feature",
  "properties": {
    "addr:full":"52-54 Canal Street Perth Perth and Kinross PH2 8LF",
    "addr:housenumber":"52-54",
    "addr:postcode":"ph2 8lf",
    "addr:street":"Canal Street",
    "iso:country":"GB",
    "sg:address":"52-54 Canal Street",
    "sg:city":"Perth",
    "sg:classifiers":[
        {
            "category":"Professional",
            "type":"Services"
        }
    ],
    "sg:phone":"+44 1738 633337",
    "sg:postcode":"PH2 8LF",
    "sg:province":"Perth and Kinross",
    "sg:tags":[
        "auctioneer"
    ],
    "wof:name":"Loves Auction Rooms",
    "wof:placetype":"venue"
},
  "geometry": {"coordinates":[-3.429959,56.394146],"type":"Point"}
}