{
  "type": "Feature",
  "properties": {
    "addr:full":"Acorn Farm Business Centre, Cublington Rd, Wing Leighton Buzzard Bedfordshire LU7 0LB",
    "addr:housenumber":"acorn;business",
    "addr:postcode":"lu7 0lb",
    "addr:street":"Cublington Rd",
    "iso:country":"GB",
    "sg:address":"Acorn Farm Business Centre, Cublington Rd, Wing",
    "sg:city":"Leighton Buzzard",
    "sg:classifiers":[
        {
            "category":"Professional",
            "subcategory":"Advertising",
            "type":"Services"
        },
        {
            "category":"Professional",
            "subcategory":"Printing & Photocopies",
            "type":"Services"
        }
    ],
    "sg:phone":"+44 70 0078 1690",
    "sg:postcode":"LU7 0LB",
    "sg:province":"Bedfordshire",
    "sg:tags":[
        "mail",
        "printer",
        "direct"
    ],
    "wof:name":"C P M Corporate Print Management Ltd",
    "wof:placetype":"venue"
},
  "geometry": {"coordinates":[-0.714999,51.897835],"type":"Point"}
}