{
  "type": "Feature",
  "properties": {
    "addr:full":"20 St Davids Close, Pen Y Garn Pontypool Monmouthshire NP4 8BA",
    "addr:housenumber":"20",
    "addr:postcode":"np4 8ba",
    "addr:street":"St Davids Close Pen Y Garn Pontypool",
    "iso:country":"GB",
    "sg:address":"20 St Davids Close, Pen Y Garn",
    "sg:city":"Pontypool",
    "sg:classifiers":[
        {
            "category":"Retail",
            "subcategory":"Driving School",
            "type":"Services"
        }
    ],
    "sg:phone":"+44 1495 762287",
    "sg:postcode":"NP4 8BA",
    "sg:province":"Monmouthshire",
    "wof:name":"Elite School of Motoring",
    "wof:placetype":"venue"
},
  "geometry": {"coordinates":[-3.0368850231,51.7046813965],"type":"Point"}
}