{
  "type": "Feature",
  "properties": {
    "iso:country":"GB",
    "sg:address":"46 Minehead Road",
    "sg:city":"Harrow",
    "sg:classifiers":[
        {
            "category":"Professional",
            "subcategory":"Secretarial Services",
            "type":"Services"
        }
    ],
    "sg:postcode":"HA2 9DS",
    "sg:province":"Greater London",
    "wof:name":"C & G Secretarial Services",
    "wof:placetype":"venue"
},
  "geometry": {"coordinates":[-0.369981,51.565205],"type":"Point"}
}