{
  "type": "Feature",
  "properties": {
    "addr:full":"Unit 8 Homefield Rd Haverhill Essex CB9 8QU",
    "addr:housenumber":"unit 8",
    "addr:postcode":"cb9 8qu",
    "addr:street":"Homefield Rd",
    "iso:country":"GB",
    "sg:address":"Unit 8 Homefield Rd",
    "sg:city":"Haverhill",
    "sg:classifiers":[
        {
            "category":"Retail",
            "subcategory":"Auto Repair",
            "type":"Services"
        }
    ],
    "sg:phone":"+44 1440 714903",
    "sg:postcode":"CB9 8QU",
    "sg:province":"Essex",
    "sg:tags":[
        "modification",
        "garage"
    ],
    "wof:name":"Mitchells Motor & Plant Repairs",
    "wof:placetype":"venue"
},
  "geometry": {"coordinates":[0.428866,52.073559],"type":"Point"}
}