{
  "type": "Feature",
  "properties": {
    "iso:country":"GB",
    "sg:address":"1 Post Office Cotts",
    "sg:city":"Muir Of Ord",
    "sg:classifiers":[
        {
            "category":"Building & Trades",
            "subcategory":"Plumbing",
            "type":"Services"
        }
    ],
    "sg:postcode":"IV6 7SU",
    "sg:province":"Highland",
    "sg:tags":[
        "heating"
    ],
    "wof:name":"Chas Munro",
    "wof:placetype":"venue"
},
  "geometry": {"coordinates":[-4.4585990906,57.5176887512],"type":"Point"}
}