{
  "type": "Feature",
  "properties": {
    "addr:full":"10 Station Rd, Whittington Moor Chesterfield Derbyshire S41 9AQ",
    "addr:housenumber":"10",
    "addr:postcode":"s41 9aq",
    "addr:street":"Station Rd",
    "iso:country":"GB",
    "sg:address":"10 Station Rd, Whittington Moor",
    "sg:city":"Chesterfield",
    "sg:classifiers":[
        {
            "category":"Manufacturing",
            "subcategory":"Rubber & Plastics",
            "type":"Manufacturing & Wholesale Goods"
        }
    ],
    "sg:phone":"+44 1246 456100",
    "sg:postcode":"S41 9AQ",
    "sg:province":"Derbyshire",
    "sg:tags":[
        "product"
    ],
    "wof:name":"Stone Bank",
    "wof:placetype":"venue"
},
  "geometry": {"coordinates":[-1.4283269644,53.2594566345],"type":"Point"}
}