{
  "type": "Feature",
  "properties": {
    "addr:full":"49 Market Place Inverurie Aberdeenshire AB51 3PY",
    "addr:housenumber":"49",
    "addr:postcode":"ab51 3py",
    "addr:street":"Market Place",
    "iso:country":"GB",
    "sg:address":"49 Market Place",
    "sg:city":"Inverurie",
    "sg:classifiers":[
        {
            "category":"Home & Garden",
            "subcategory":"Household Appliances",
            "type":"Retail Goods"
        },
        {
            "category":"Home & Garden",
            "subcategory":"Hardware",
            "type":"Retail Goods"
        }
    ],
    "sg:phone":"+44 1467 621363",
    "sg:postcode":"AB51 3PY",
    "sg:province":"Aberdeenshire",
    "sg:tags":[
        "kitchenware"
    ],
    "wof:name":"PAUL MCPHERSON & SON",
    "wof:placetype":"venue"
},
  "geometry": {"coordinates":[-2.3743190765,57.2837295532],"type":"Point"}
}