{
  "type": "Feature",
  "properties": {
    "addr:full":"Holker Business Centre, Burnley Road Colne Lancashire BB8 8EG",
    "addr:postcode":"bb8 8eg",
    "addr:street":"Burnley Road",
    "iso:country":"GB",
    "sg:address":"Holker Business Centre, Burnley Road",
    "sg:city":"Colne",
    "sg:classifiers":[
        {
            "category":"Recreation",
            "subcategory":"Go Karts",
            "type":"Entertainment"
        }
    ],
    "sg:phone":"+44 1282 865675",
    "sg:postcode":"BB8 8EG",
    "sg:province":"Lancashire",
    "sg:tags":[
        "karting"
    ],
    "wof:name":"Prestige Indoor Karting",
    "wof:placetype":"venue"
},
  "geometry": {"coordinates":[-2.2012150288,53.84923172],"type":"Point"}
}