{
  "type": "Feature",
  "properties": {
    "addr:full":"459 Grn Lanes London Greater London N4 1HE",
    "addr:housenumber":"459",
    "addr:postcode":"n4 1he",
    "addr:street":"Grn Lanes",
    "iso:country":"GB",
    "sg:address":"459 Grn Lanes",
    "sg:city":"London",
    "sg:classifiers":[
        {
            "category":"Shopping",
            "subcategory":"Pharmacy",
            "type":"Retail Goods"
        }
    ],
    "sg:postcode":"N4 1HE",
    "sg:province":"Greater London",
    "sg:tags":[
        "store",
        "drug"
    ],
    "wof:name":"Kabra's Universal Drug Store",
    "wof:placetype":"venue"
},
  "geometry": {"coordinates":[-0.099469997,51.5797615051],"type":"Point"}
}