{
  "type": "Feature",
  "properties": {
    "iso:country":"GB",
    "sg:address":"Screentec House",
    "sg:city":"Wakefield",
    "sg:classifiers":[
        {
            "category":"Shopping",
            "subcategory":"Gifts & Souvenirs",
            "type":"Retail Goods"
        },
        {
            "category":"Professional",
            "subcategory":"Printing & Photocopies",
            "type":"Services"
        }
    ],
    "sg:phone":"+44 1924 291222",
    "sg:postcode":"WF1 3NS",
    "sg:province":"West Yorkshire",
    "sg:tags":[
        "process",
        "giftware",
        "screen",
        "printer"
    ],
    "wof:name":"Screentec Print Ltd.",
    "wof:placetype":"venue"
},
  "geometry": {"coordinates":[-1.4928799868,53.6866607666],"type":"Point"}
}