{
  "type": "Feature",
  "properties": {
    "iso:country":"GB",
    "sg:address":"1 Central House, The Square Moreton Hampstead",
    "sg:city":"Newton Abbot",
    "sg:classifiers":[
        {
            "category":"Home & Garden",
            "subcategory":"Hardware",
            "type":"Retail Goods"
        }
    ],
    "sg:phone":"+44 1647 440141",
    "sg:postcode":"TQ13 8NF",
    "sg:province":"Devon",
    "wof:name":"Arnolds",
    "wof:placetype":"venue"
},
  "geometry": {"coordinates":[-3.7651600838,50.6607284546],"type":"Point"}
}