{
  "type": "Feature",
  "properties": {
    "addr:full":"Wilcote Grange Farm, Wilcote Chipping Norton Gloucestershire OX7 3EA",
    "addr:housenumber":"norton",
    "addr:postcode":"ox7 3ea",
    "addr:street":"Wilcote",
    "iso:country":"GB",
    "sg:address":"Wilcote Grange Farm, Wilcote",
    "sg:city":"Chipping Norton",
    "sg:classifiers":[
        {
            "category":"Farming",
            "subcategory":"Livestock Farm",
            "type":"Manufacturing & Wholesale Goods"
        }
    ],
    "sg:phone":"+44 1993 868277",
    "sg:postcode":"OX7 3EA",
    "sg:province":"Gloucestershire",
    "sg:tags":[
        "others"
    ],
    "wof:name":"Lucy N R Ford",
    "wof:placetype":"venue"
},
  "geometry": {"coordinates":[-1.4602440596,51.8368263245],"type":"Point"}
}