{
  "type": "Feature",
  "properties": {
    "addr:full":"Great Warley Forge, Great Warley Brentwood Essex CM13 3JF",
    "addr:postcode":"cm13 3jf",
    "addr:street":"Forge Great",
    "iso:country":"GB",
    "sg:address":"Great Warley Forge, Great Warley",
    "sg:city":"Brentwood",
    "sg:classifiers":[
        {
            "category":"Utilities",
            "subcategory":"Natural Gas",
            "type":"Services"
        }
    ],
    "sg:phone":"+44 1277 226547",
    "sg:postcode":"CM13 3JF",
    "sg:province":"Essex",
    "sg:tags":[
        "blacksmith"
    ],
    "wof:name":"Great Warley-Fabrications",
    "wof:placetype":"venue"
},
  "geometry": {"coordinates":[0.286459,51.594494],"type":"Point"}
}