{
  "type": "Feature",
  "properties": {
    "addr:full":"Shrubbery Hall, Vian St Lewisham Greater London SE13 7DJ",
    "addr:postcode":"se13 7dj",
    "addr:street":"Vian St",
    "iso:country":"GB",
    "sg:address":"Shrubbery Hall, Vian St",
    "sg:city":"Lewisham",
    "sg:classifiers":[
        {
            "category":"Organizations",
            "subcategory":"Non-profit Organization",
            "type":"Services"
        }
    ],
    "sg:phone":"+44 20 8318 1334",
    "sg:postcode":"SE13 7DJ",
    "sg:province":"Greater London",
    "sg:tags":[
        "organisation",
        "voluntary",
        "charity"
    ],
    "wof:name":"London City Mission",
    "wof:placetype":"venue"
},
  "geometry": {"coordinates":[-0.012449,51.4588356018],"type":"Point"}
}