{
  "type": "Feature",
  "properties": {
    "iso:country":"GB",
    "sg:address":"23 West View",
    "sg:city":"Newent",
    "sg:classifiers":[
        {
            "category":"Taxi",
            "type":"Transportation"
        }
    ],
    "sg:phone":"+44 1531 822248",
    "sg:postcode":"GL18 1TE",
    "sg:province":"Gloucestershire",
    "sg:tags":[
        "mini",
        "cab"
    ],
    "wof:name":"Newent Taxis",
    "wof:placetype":"venue"
},
  "geometry": {"coordinates":[-2.414552,51.930965],"type":"Point"}
}