{
  "type": "Feature",
  "properties": {
    "iso:country":"GB",
    "sg:address":"95 Fairfax Road",
    "sg:city":"London",
    "sg:classifiers":[
        {
            "category":"Food & Beverages",
            "subcategory":"Supermarket",
            "type":"Retail Goods"
        }
    ],
    "sg:phone":"+44 20 7328 2751",
    "sg:postcode":"NW6 4DY",
    "sg:province":"Greater London",
    "wof:name":"Savemore Supermarket & Off Licence",
    "wof:placetype":"venue"
},
  "geometry": {"coordinates":[-0.1797849983,51.5421409607],"type":"Point"}
}