{
  "type": "Feature",
  "properties": {
    "addr:full":"Unit 2 St Davids Road Valley Way, Swansea Enterprise Park Swansea Swansea SA6 8QL",
    "addr:housenumber":"unit 2;enterprise",
    "addr:postcode":"sa6 8ql",
    "addr:street":"St Davids Road Valley Way;Park",
    "iso:country":"GB",
    "sg:address":"Unit 2 St Davids Road Valley Way, Swansea Enterprise Park",
    "sg:city":"Swansea",
    "sg:classifiers":[
        {
            "category":"Professional",
            "subcategory":"Computer Services",
            "type":"Services"
        }
    ],
    "sg:phone":"+44 1792 700033",
    "sg:postcode":"SA6 8QL",
    "sg:province":"Swansea",
    "sg:tags":[
        "system",
        "software"
    ],
    "wof:name":"P C World",
    "wof:placetype":"venue"
},
  "geometry": {"coordinates":[-3.9167430401,51.6607551575],"type":"Point"}
}