{
  "type": "Feature",
  "properties": {
    "addr:full":"68 Duxmere Drive Ross-on-wye Gloucestershire HR9 5UP",
    "addr:housenumber":"68",
    "addr:postcode":"hr9 5up",
    "addr:street":"Duxmere Drive",
    "iso:country":"GB",
    "sg:address":"68 Duxmere Drive",
    "sg:city":"Ross-on-wye",
    "sg:classifiers":[
        {
            "category":"Food & Beverages",
            "subcategory":"Supermarket",
            "type":"Retail Goods"
        }
    ],
    "sg:phone":"+44 1989 768761",
    "sg:postcode":"HR9 5UP",
    "sg:province":"Gloucestershire",
    "wof:name":"Wye Dean Shopping Service",
    "wof:placetype":"venue"
},
  "geometry": {"coordinates":[-2.5879170895,51.9061965942],"type":"Point"}
}