{
  "type": "Feature",
  "properties": {
    "addr:full":"7 Upper Garth Rd Bangor Gwynedd LL57 2SR",
    "addr:housenumber":"7",
    "addr:postcode":"ll57 2sr",
    "addr:street":"Upper Garth Rd",
    "iso:country":"GB",
    "sg:address":"7 Upper Garth Rd",
    "sg:city":"Bangor",
    "sg:classifiers":[
        {
            "category":"Communications",
            "subcategory":"Film & Video Production",
            "type":"Services"
        }
    ],
    "sg:phone":"+44 1248 351747",
    "sg:postcode":"LL57 2SR",
    "sg:province":"Gwynedd",
    "sg:tags":[
        "tv",
        "studio"
    ],
    "wof:name":"Griffilms",
    "wof:placetype":"venue"
},
  "geometry": {"coordinates":[-4.122636795,53.2356948853],"type":"Point"}
}