{
  "type": "Feature",
  "properties": {
    "addr:full":"38 Bexley High Street Bexley Kent DA5 1AH",
    "addr:housenumber":"38",
    "addr:postcode":"da5 1ah",
    "addr:street":"Bexley High Street",
    "iso:country":"GB",
    "sg:address":"38 Bexley High Street",
    "sg:city":"Bexley",
    "sg:classifiers":[
        {
            "category":"Bars & Pubs",
            "type":"Food & Drink"
        },
        {
            "category":"Community Center",
            "subcategory":"Social",
            "type":"Public Place"
        }
    ],
    "sg:phone":"+44 1322 522779",
    "sg:postcode":"DA5 1AH",
    "sg:province":"Kent",
    "sg:tags":[
        "pubs",
        "house",
        "inn",
        "activity"
    ],
    "wof:name":"The Railway Tavern",
    "wof:placetype":"venue"
},
  "geometry": {"coordinates":[0.1489679962,51.4412689209],"type":"Point"}
}