{
  "type": "Feature",
  "properties": {
    "addr:full":"Common Lane Beccles Norfolk NR34 9RH",
    "addr:postcode":"nr34 9rh",
    "addr:street":"Common Lane",
    "iso:country":"GB",
    "sg:address":"Common Lane",
    "sg:city":"Beccles",
    "sg:classifiers":[
        {
            "category":"Organizations",
            "subcategory":"Community Association",
            "type":"Services"
        },
        {
            "category":"Organizations",
            "subcategory":"Membership Organization",
            "type":"Services"
        }
    ],
    "sg:phone":"+44 1502 713549",
    "sg:postcode":"NR34 9RH",
    "sg:province":"Norfolk",
    "sg:tags":[
        "club",
        "social"
    ],
    "wof:name":"Beccles Indoor Bowls Club",
    "wof:placetype":"venue"
},
  "geometry": {"coordinates":[1.5727000237,52.4565162659],"type":"Point"}
}