{
  "type": "Feature",
  "properties": {
    "iso:country":"GB",
    "sg:address":"13 Cripsey Avenue",
    "sg:city":"Ongar",
    "sg:classifiers":[
        {
            "category":"Utilities",
            "subcategory":"Natural Gas",
            "type":"Services"
        }
    ],
    "sg:phone":"+44 1277 364161",
    "sg:postcode":"CM5 0AT",
    "sg:province":"Essex",
    "sg:tags":[
        "control",
        "energy",
        "management",
        "system"
    ],
    "wof:name":"Fewells Plumbing & Heating Services",
    "wof:placetype":"venue"
},
  "geometry": {"coordinates":[0.2382210046,51.7177772522],"type":"Point"}
}