{
  "type": "Feature",
  "properties": {
    "addr:full":"79 Church Street Leigh Lancashire WN7 1AZ",
    "addr:housenumber":"79",
    "addr:postcode":"wn7 1az",
    "addr:street":"Church Street Leigh",
    "iso:country":"GB",
    "sg:address":"79 Church Street",
    "sg:city":"Leigh",
    "sg:classifiers":[
        {
            "category":"Health Services",
            "subcategory":"Doctor",
            "type":"Services"
        }
    ],
    "sg:phone":"+44 1942 680909",
    "sg:postcode":"WN7 1AZ",
    "sg:province":"Lancashire",
    "sg:tags":[
        "practitioners"
    ],
    "wof:name":"Dr D N Das",
    "wof:placetype":"venue"
},
  "geometry": {"coordinates":[-2.514316082,53.4977607727],"type":"Point"}
}