{
  "type": "Feature",
  "properties": {
    "iso:country":"GB",
    "sg:address":"Granville Chambers, 2a Radford Street",
    "sg:city":"Stone",
    "sg:classifiers":[
        {
            "category":"Manufacturing",
            "subcategory":"Pottery",
            "type":"Manufacturing & Wholesale Goods"
        }
    ],
    "sg:phone":"+44 1785 812426",
    "sg:postcode":"ST15 8DA",
    "sg:province":"Staffordshire",
    "sg:tags":[
        "supplier"
    ],
    "wof:name":"Ambassador Pottery Holdings 1982",
    "wof:placetype":"venue"
},
  "geometry": {"coordinates":[-2.143473,52.900826],"type":"Point"}
}