{
  "type": "Feature",
  "properties": {
    "iso:country":"GB",
    "sg:address":"Howards Lane",
    "sg:city":"Wareham",
    "sg:classifiers":[
        {
            "category":"Organizations",
            "subcategory":"Membership Organization",
            "type":"Services"
        }
    ],
    "sg:phone":"+44 1929 556896",
    "sg:postcode":"BH20 4HU",
    "sg:province":"Dorset",
    "sg:tags":[
        "club"
    ],
    "wof:name":"Masonic Hall",
    "wof:placetype":"venue"
},
  "geometry": {"coordinates":[-2.109994,50.686596],"type":"Point"}
}