{
  "type": "Feature",
  "properties": {
    "addr:full":"9 Beaumont Rd Windsor Berkshire SL4 1HY",
    "addr:housenumber":"9",
    "addr:postcode":"sl4 1hy",
    "addr:street":"Beaumont Rd",
    "iso:country":"GB",
    "sg:address":"9 Beaumont Rd",
    "sg:city":"Windsor",
    "sg:classifiers":[
        {
            "category":"Health Services",
            "subcategory":"Doctor",
            "type":"Services"
        }
    ],
    "sg:phone":"+44 1753 865200",
    "sg:postcode":"SL4 1HY",
    "sg:province":"Berkshire",
    "sg:tags":[
        "practitioners"
    ],
    "wof:name":"R.K Dega",
    "wof:placetype":"venue"
},
  "geometry": {"coordinates":[-0.612574,51.475666],"type":"Point"}
}