{
  "type": "Feature",
  "properties": {
    "iso:country":"GB",
    "sg:address":"11 Norfolk Street",
    "sg:city":"London",
    "sg:classifiers":[
        {
            "category":"Building & Trades",
            "subcategory":"Construction",
            "type":"Services"
        }
    ],
    "sg:phone":"+44 20 8519 8445",
    "sg:postcode":"E7 0HN",
    "sg:province":"Greater London",
    "sg:tags":[
        "builder"
    ],
    "wof:name":"J J Laffey",
    "wof:placetype":"venue"
},
  "geometry": {"coordinates":[0.021207,51.550732],"type":"Point"}
}