{
  "type": "Feature",
  "properties": {
    "iso:country":"GB",
    "sg:address":"100 Mildenhall Road, Fordham",
    "sg:city":"Ely",
    "sg:classifiers":[
        {
            "category":"Building & Trades",
            "subcategory":"Equipment Rental",
            "type":"Services"
        }
    ],
    "sg:phone":"+44 1638 720781",
    "sg:postcode":"CB7 5NR",
    "sg:province":"Cambridgeshire",
    "sg:tags":[
        "plant",
        "machinery"
    ],
    "wof:name":"L O C Plant Hire & Haulage",
    "wof:placetype":"venue"
},
  "geometry": {"coordinates":[0.403003,52.310822],"type":"Point"}
}