{
  "type": "Feature",
  "properties": {
    "addr:full":"290 - 294 Hackney Rd London Greater London E2 7SJ",
    "addr:housenumber":"294",
    "addr:postcode":"e2 7sj",
    "addr:street":"Hackney Rd",
    "iso:country":"GB",
    "sg:address":"290 - 294 Hackney Rd",
    "sg:city":"London",
    "sg:classifiers":[
        {
            "category":"Personal",
            "subcategory":"Skin Care",
            "type":"Services"
        }
    ],
    "sg:postcode":"E2 7SJ",
    "sg:province":"Greater London",
    "sg:tags":[
        "leather",
        "merchant"
    ],
    "wof:name":"Asara Handbag Co",
    "wof:placetype":"venue"
},
  "geometry": {"coordinates":[-0.068209,51.531059],"type":"Point"}
}