{
  "type": "Feature",
  "properties": {
    "addr:full":"23 Stoneyholm Road Kilbirnie North Ayrshire KA25 7DT",
    "addr:housenumber":"23",
    "addr:postcode":"ka25 7dt",
    "addr:street":"Stoneyholm Road",
    "iso:country":"GB",
    "sg:address":"23 Stoneyholm Road",
    "sg:city":"Kilbirnie",
    "sg:classifiers":[
        {
            "category":"Bakery",
            "type":"Food & Drink"
        },
        {
            "category":"Home & Garden",
            "subcategory":"Building Materials",
            "type":"Retail Goods"
        }
    ],
    "sg:postcode":"KA25 7DT",
    "sg:province":"North Ayrshire",
    "sg:tags":[
        "cake",
        "plastic",
        "maker",
        "polythene"
    ],
    "wof:name":"Vee Bee Sugar Art",
    "wof:placetype":"venue"
},
  "geometry": {"coordinates":[-4.6810998917,55.7574043274],"type":"Point"}
}