{
  "type": "Feature",
  "properties": {
    "iso:country":"GB",
    "sg:address":"Westwey House, Westwey Road",
    "sg:city":"Weymouth",
    "sg:classifiers":[
        {
            "category":"Social Services",
            "type":"Services"
        },
        {
            "category":"Professional",
            "subcategory":"Employment Agencies",
            "type":"Services"
        }
    ],
    "sg:phone":"+44 1305 328000",
    "sg:postcode":"DT4 8TG",
    "sg:province":"Dorset",
    "sg:tags":[
        "consultant",
        "benefit",
        "recruitment"
    ],
    "wof:name":"Jobcentre Plus",
    "wof:placetype":"venue"
},
  "geometry": {"coordinates":[-2.459206,50.609901],"type":"Point"}
}