{
  "type": "Feature",
  "properties": {
    "iso:country":"GB",
    "sg:address":"31-37 Spring Street",
    "sg:city":"Oldham",
    "sg:classifiers":[
        {
            "category":"Travel",
            "subcategory":"Hostel",
            "type":"Entertainment"
        }
    ],
    "sg:phone":"+44 161 624 2934",
    "sg:postcode":"OL4 2BD",
    "sg:province":"Lancashire",
    "wof:name":"Threshold Housing Project Ltd.",
    "wof:placetype":"venue"
},
  "geometry": {"coordinates":[-2.085281,53.547153],"type":"Point"}
}