{
  "type": "Feature",
  "properties": {
    "addr:full":"Old Glasshouse Farm, Lowfield Lane St Helens Cheshire WA9 5AZ",
    "addr:postcode":"wa9 5az",
    "addr:street":"Lowfield Lane",
    "iso:country":"GB",
    "sg:address":"Old Glasshouse Farm, Lowfield Lane",
    "sg:city":"St Helens",
    "sg:classifiers":[
        {
            "category":"Retail",
            "subcategory":"Auto Repair",
            "type":"Services"
        }
    ],
    "sg:phone":"+44 1744 851259",
    "sg:postcode":"WA9 5AZ",
    "sg:province":"Cheshire",
    "sg:tags":[
        "modification",
        "garage"
    ],
    "wof:name":"D F H Motors",
    "wof:placetype":"venue"
},
  "geometry": {"coordinates":[-2.74055,53.423031],"type":"Point"}
}