{
  "type": "Feature",
  "properties": {
    "addr:full":"5a-9 Beech Street Leicester Leicestershire LE5 0DF",
    "addr:housenumber":"5a-9",
    "addr:postcode":"le5 0df",
    "addr:street":"Beech Street",
    "iso:country":"GB",
    "sg:address":"5a-9 Beech Street",
    "sg:city":"Leicester",
    "sg:classifiers":[
        {
            "category":"Shopping",
            "subcategory":"Clothing, Apparel, & Fashions",
            "type":"Retail Goods"
        }
    ],
    "sg:phone":"+44 116 251 5156",
    "sg:postcode":"LE5 0DF",
    "sg:province":"Leicestershire",
    "sg:tags":[
        "clothing",
        "accessory"
    ],
    "wof:name":"Genel 86 Ltd.",
    "wof:placetype":"venue"
},
  "geometry": {"coordinates":[-1.109009,52.643585],"type":"Point"}
}