{
  "type": "Feature",
  "properties": {
    "addr:full":"119 Winterstoke Road Bristol City of Bristol BS3 2NS",
    "addr:housenumber":"119",
    "addr:postcode":"bs3 2ns",
    "addr:street":"Winterstoke Road",
    "iso:country":"GB",
    "sg:address":"119 Winterstoke Road",
    "sg:city":"Bristol",
    "sg:classifiers":[
        {
            "category":"Shopping",
            "subcategory":"Mobile Phones",
            "type":"Retail Goods"
        },
        {
            "category":"Communications",
            "type":"Services"
        }
    ],
    "sg:phone":"+44 117 963 2033",
    "sg:postcode":"BS3 2NS",
    "sg:province":"City of Bristol",
    "sg:tags":[
        "telecommunication"
    ],
    "wof:name":"The Carphone Warehouse Ltd.",
    "wof:placetype":"venue"
},
  "geometry": {"coordinates":[-2.610640049,51.4329528809],"type":"Point"}
}