{
  "type": "Feature",
  "properties": {
    "iso:country":"GB",
    "sg:address":"2 Grant Street",
    "sg:city":"Wick",
    "sg:classifiers":[
        {
            "category":"Shopping",
            "subcategory":"Department Store",
            "type":"Retail Goods"
        },
        {
            "category":"Home & Garden",
            "subcategory":"Carpets & Floor Coverings",
            "type":"Retail Goods"
        }
    ],
    "sg:phone":"+44 1955 602024",
    "sg:postcode":"KW1 5AY",
    "sg:province":"Highland",
    "sg:tags":[
        "carpets",
        "rug",
        "matting"
    ],
    "wof:name":"R J McDonald",
    "wof:placetype":"venue"
},
  "geometry": {"coordinates":[-3.086849,58.437428],"type":"Point"}
}