{
  "type": "Feature",
  "properties": {
    "iso:country":"GB",
    "sg:address":"Station Road",
    "sg:city":"Mirfield",
    "sg:classifiers":[
        {
            "category":"Manufacturing",
            "subcategory":"Building Materials",
            "type":"Manufacturing & Wholesale Goods"
        }
    ],
    "sg:phone":"+44 1924 490584",
    "sg:postcode":"WF14 8NL",
    "sg:province":"West Yorkshire",
    "sg:tags":[
        "merchant",
        "builder"
    ],
    "wof:name":"Healey Ward",
    "wof:placetype":"venue"
},
  "geometry": {"coordinates":[-1.6928030252,53.6733093262],"type":"Point"}
}