{
  "type": "Feature",
  "properties": {
    "iso:country":"GB",
    "sg:address":"4 Victoria Place",
    "sg:city":"St Austell",
    "sg:classifiers":[
        {
            "category":"Food & Beverages",
            "subcategory":"Meat & Fish",
            "type":"Retail Goods"
        }
    ],
    "sg:postcode":"PL25 5PE",
    "sg:province":"Cornwall",
    "sg:tags":[
        "chip"
    ],
    "wof:name":"F Pascoe",
    "wof:placetype":"venue"
},
  "geometry": {"coordinates":[-4.792431,50.3382],"type":"Point"}
}