{
  "type": "Feature",
  "properties": {
    "addr:full":"18 Trident Centre Dudley West Midlands DY1 1QJ",
    "addr:housenumber":"18",
    "addr:postcode":"dy1 1qj",
    "addr:street":"Trident Centre",
    "iso:country":"GB",
    "sg:address":"18 Trident Centre",
    "sg:city":"Dudley",
    "sg:classifiers":[
        {
            "category":"Shopping",
            "subcategory":"Crafts & Fabrics",
            "type":"Retail Goods"
        }
    ],
    "sg:postcode":"DY1 1QJ",
    "sg:province":"West Midlands",
    "sg:tags":[
        "shop",
        "needlecraft",
        "wool"
    ],
    "wof:name":"John B Smith",
    "wof:placetype":"venue"
},
  "geometry": {"coordinates":[-2.0850598812,52.50963974],"type":"Point"}
}