{
  "type": "Feature",
  "properties": {
    "iso:country":"GB",
    "sg:address":"10 Lenton Boulevard",
    "sg:city":"Nottingham",
    "sg:classifiers":[
        {
            "category":"Fast Food",
            "type":"Food & Drink"
        }
    ],
    "sg:phone":"+44 115 947 4008",
    "sg:postcode":"NG7 2ES",
    "sg:province":"Nottinghamshire",
    "sg:tags":[
        "away",
        "take"
    ],
    "wof:name":"New Lenton Tandoori",
    "wof:placetype":"venue"
},
  "geometry": {"coordinates":[-1.1738009453,52.9476928711],"type":"Point"}
}