{
  "type": "Feature",
  "properties": {
    "addr:full":"3 Katherine Villas, Mill Hill Eastbridef Edenbridge East Sussex TN8 5BT",
    "addr:housenumber":"3",
    "addr:postcode":"tn8 5bt",
    "addr:street":"Katherine Villas",
    "iso:country":"GB",
    "sg:address":"3 Katherine Villas, Mill Hill Eastbridef",
    "sg:city":"Edenbridge",
    "sg:classifiers":[
        {
            "category":"Building & Trades",
            "subcategory":"Landscaping Services",
            "type":"Services"
        }
    ],
    "sg:phone":"+44 1732 862989",
    "sg:postcode":"TN8 5BT",
    "sg:province":"East Sussex",
    "sg:tags":[
        "forestry",
        "tree"
    ],
    "wof:name":"Dalrymple Ltd.",
    "wof:placetype":"venue"
},
  "geometry": {"coordinates":[0.065714,51.193012],"type":"Point"}
}