{
  "type": "Feature",
  "properties": {
    "addr:full":"107 Newport Street Leicester Leicestershire LE3 9FU",
    "addr:housenumber":"107",
    "addr:postcode":"le3 9fu",
    "addr:street":"Newport Street",
    "iso:country":"GB",
    "sg:address":"107 Newport Street",
    "sg:city":"Leicester",
    "sg:classifiers":[
        {
            "category":"Shopping",
            "subcategory":"Clothing, Apparel, & Fashions",
            "type":"Retail Goods"
        }
    ],
    "sg:postcode":"LE3 9FU",
    "sg:province":"Leicestershire",
    "sg:tags":[
        "clothing",
        "fabric"
    ],
    "wof:name":"C B M Clothing Ltd.",
    "wof:placetype":"venue"
},
  "geometry": {"coordinates":[-1.153739,52.638939],"type":"Point"}
}