{
  "type": "Feature",
  "properties": {
    "addr:full":"5 York Street Stourport-on-severn Worcestershire DY13 9EQ",
    "addr:housenumber":"5",
    "addr:postcode":"dy13 9eq",
    "addr:street":"York Street",
    "iso:country":"GB",
    "sg:address":"5 York Street",
    "sg:city":"Stourport-on-severn",
    "sg:classifiers":[
        {
            "category":"Fast Food",
            "type":"Food & Drink"
        }
    ],
    "sg:phone":"+44 1299 879278",
    "sg:postcode":"DY13 9EQ",
    "sg:province":"Worcestershire",
    "sg:tags":[
        "away",
        "meal",
        "outlet",
        "take"
    ],
    "wof:name":"Stourport Tandoori",
    "wof:placetype":"venue"
},
  "geometry": {"coordinates":[-2.278639,52.338791],"type":"Point"}
}