{
  "type": "Feature",
  "properties": {
    "iso:country":"GB",
    "sg:address":"138 Harley Street",
    "sg:city":"London",
    "sg:classifiers":[
        {
            "category":"Health Services",
            "subcategory":"Doctor",
            "type":"Services"
        }
    ],
    "sg:phone":"+44 20 7935 1963",
    "sg:postcode":"W1G 7LA",
    "sg:province":"Greater London",
    "sg:tags":[
        "practitioners"
    ],
    "wof:name":"A D Isaacs",
    "wof:placetype":"venue"
},
  "geometry": {"coordinates":[-0.1484369934,51.5227546692],"type":"Point"}
}