{
  "type": "Feature",
  "properties": {
    "addr:full":"25 Islington Liverpool Merseyside L3 8PP",
    "addr:housenumber":"25",
    "addr:postcode":"l3 8pp",
    "addr:street":"Islington",
    "iso:country":"GB",
    "sg:address":"25 Islington",
    "sg:city":"Liverpool",
    "sg:classifiers":[
        {
            "category":"Autos & Motor Vehicles",
            "subcategory":"Fuel & Gas Station",
            "type":"Retail Goods"
        }
    ],
    "sg:phone":"+44 151 298 2354",
    "sg:postcode":"L3 8PP",
    "sg:province":"Merseyside",
    "sg:tags":[
        "hr",
        "petrol"
    ],
    "wof:name":"Snax 24 Ltd",
    "wof:placetype":"venue"
},
  "geometry": {"coordinates":[-2.9684491158,53.412021637],"type":"Point"}
}