{
  "type": "Feature",
  "properties": {
    "iso:country":"GB",
    "sg:address":"Exeter Place, Kettering Road",
    "sg:city":"Northampton",
    "sg:classifiers":[
        {
            "category":"Professional",
            "type":"Services"
        }
    ],
    "sg:postcode":"NN1 4DQ",
    "sg:province":"Northamptonshire",
    "sg:tags":[
        "caterer"
    ],
    "wof:name":"The Exeter Rooms Catering",
    "wof:placetype":"venue"
},
  "geometry": {"coordinates":[-0.882492,52.242947],"type":"Point"}
}