{
  "type": "Feature",
  "properties": {
    "addr:full":"118 Mill Street Macclesfield Cheshire SK11 6NR",
    "addr:housenumber":"118",
    "addr:postcode":"sk11 6nr",
    "addr:street":"Mill Street",
    "iso:country":"GB",
    "sg:address":"118 Mill Street",
    "sg:city":"Macclesfield",
    "sg:classifiers":[
        {
            "category":"Shopping",
            "subcategory":"News",
            "type":"Retail Goods"
        }
    ],
    "sg:phone":"+44 1625 427468",
    "sg:postcode":"SK11 6NR",
    "sg:province":"Cheshire",
    "sg:tags":[
        "newsagent"
    ],
    "wof:name":"Mnm News Ltd.",
    "wof:placetype":"venue"
},
  "geometry": {"coordinates":[-2.125155,53.257328],"type":"Point"}
}