{
  "type": "Feature",
  "properties": {
    "iso:country":"GB",
    "sg:address":"Claremont Court, 31 Ezra Street",
    "sg:city":"London",
    "sg:classifiers":[
        {
            "category":"Building & Trades",
            "subcategory":"Construction",
            "type":"Services"
        }
    ],
    "sg:postcode":"W2 5HX",
    "sg:province":"Greater London",
    "sg:tags":[
        "heating",
        "contractor"
    ],
    "wof:name":"Abbercorn Services Ltd.",
    "wof:placetype":"venue"
},
  "geometry": {"coordinates":[-0.18844,51.516109],"type":"Point"}
}