{
  "type": "Feature",
  "properties": {
    "addr:full":"Great North Road Newcastle-upon-tyne Tyne and Wear NE2 3BB",
    "addr:postcode":"ne2 3bb",
    "addr:street":"Great North Road",
    "iso:country":"GB",
    "sg:address":"Great North Road",
    "sg:city":"Newcastle-upon-tyne",
    "sg:classifiers":[
        {
            "category":"Education",
            "subcategory":"Special Training",
            "type":"Public Place"
        }
    ],
    "sg:postcode":"NE2 3BB",
    "sg:province":"Tyne and Wear",
    "sg:tags":[
        "school"
    ],
    "wof:name":"Northern Counties School",
    "wof:placetype":"venue"
},
  "geometry": {"coordinates":[-1.6151889563,54.9917068481],"type":"Point"}
}