{
  "type": "Feature",
  "properties": {
    "iso:country":"GB",
    "sg:address":"Main Road, Abercynon",
    "sg:city":"Mountain Ash",
    "sg:classifiers":[
        {
            "category":"Education",
            "subcategory":"School",
            "type":"Public Place"
        },
        {
            "category":"Government",
            "subcategory":"Office",
            "type":"Public Place"
        }
    ],
    "sg:phone":"+44 1443 742327",
    "sg:postcode":"CF45 4LJ",
    "sg:province":"Rhondda, Cynon, Taff",
    "sg:tags":[
        "local",
        "authority"
    ],
    "wof:name":"Ynysboeth Junior School",
    "wof:placetype":"venue"
},
  "geometry": {"coordinates":[-3.3506290913,51.6613998413],"type":"Point"}
}