{
  "type": "Feature",
  "properties": {
    "iso:country":"GB",
    "sg:address":"3 Hanover Bldgs",
    "sg:city":"Southampton",
    "sg:classifiers":[
        {
            "category":"Banks & Credit Unions",
            "subcategory":"Financial Services",
            "type":"Services"
        }
    ],
    "sg:phone":"+44 23 8063 0748",
    "sg:postcode":"SO14 1JW",
    "sg:province":"Hampshire",
    "sg:tags":[
        "building",
        "society"
    ],
    "wof:name":"Birmingham Midshires Building Society",
    "wof:placetype":"venue"
},
  "geometry": {"coordinates":[-1.403933,50.903194],"type":"Point"}
}