{
  "type": "Feature",
  "properties": {
    "addr:full":"Unit 138 Lydney Trading Estate, Harbour Road Lydney Gloucestershire GL15 4EJ",
    "addr:housenumber":"138",
    "addr:postcode":"gl15 4ej",
    "addr:street":"Lydney Trading Estate Harbour Road",
    "iso:country":"GB",
    "sg:address":"Unit 138 Lydney Trading Estate, Harbour Road",
    "sg:city":"Lydney",
    "sg:classifiers":[
        {
            "category":"Manufacturing",
            "subcategory":"Rubber & Plastics",
            "type":"Manufacturing & Wholesale Goods"
        }
    ],
    "sg:phone":"+44 1594 843000",
    "sg:postcode":"GL15 4EJ",
    "sg:province":"Gloucestershire",
    "sg:tags":[
        "product",
        "manufacturer"
    ],
    "wof:name":"A & S Plastics",
    "wof:placetype":"venue"
},
  "geometry": {"coordinates":[-2.535819,51.724491],"type":"Point"}
}