{
  "type": "Feature",
  "properties": {
    "addr:full":"King Edwards Road Chatteris Cambridgeshire PE16 6NG",
    "addr:postcode":"pe16 6ng",
    "addr:street":"King Edwards Road",
    "iso:country":"GB",
    "sg:address":"King Edwards Road",
    "sg:city":"Chatteris",
    "sg:classifiers":[
        {
            "category":"Food & Beverages",
            "subcategory":"Groceries & Convenience Stores",
            "type":"Retail Goods"
        }
    ],
    "sg:postcode":"PE16 6NG",
    "sg:province":"Cambridgeshire",
    "sg:tags":[
        "merchant",
        "potato"
    ],
    "wof:name":"David George Collett",
    "wof:placetype":"venue"
},
  "geometry": {"coordinates":[0.048457,52.455173],"type":"Point"}
}