{
  "type": "Feature",
  "properties": {
    "iso:country":"GB",
    "sg:address":"Birch House Lane, Cotes, Swynnerton",
    "sg:city":"Stone",
    "sg:classifiers":[
        {
            "category":"Manufacturing",
            "subcategory":"Metals",
            "type":"Manufacturing & Wholesale Goods"
        }
    ],
    "sg:phone":"+44 1782 791677",
    "sg:postcode":"ST15 0QQ",
    "sg:province":"Staffordshire",
    "sg:tags":[
        "work",
        "sheet"
    ],
    "wof:name":"Ken V Farrington",
    "wof:placetype":"venue"
},
  "geometry": {"coordinates":[-2.139495,52.885529],"type":"Point"}
}