{
  "type": "Feature",
  "properties": {
    "iso:country":"GB",
    "sg:address":"17 Staples Hill",
    "sg:city":"Bath",
    "sg:classifiers":[
        {
            "category":"Wholesale",
            "subcategory":"Chemicals & Plastics",
            "type":"Manufacturing & Wholesale Goods"
        }
    ],
    "sg:postcode":"BA2 7WL",
    "sg:province":"Somerset",
    "sg:tags":[
        "retail",
        "freezer",
        "refrigerator"
    ],
    "wof:name":"Longacre",
    "wof:placetype":"venue"
},
  "geometry": {"coordinates":[-2.299949,51.334042],"type":"Point"}
}