{
  "type": "Feature",
  "properties": {
    "addr:full":"266 Catherine St Leicester Leicestershire LE4 6GD",
    "addr:housenumber":"266",
    "addr:postcode":"le4 6gd",
    "addr:street":"Catherine St",
    "iso:country":"GB",
    "sg:address":"266 Catherine St",
    "sg:city":"Leicester",
    "sg:classifiers":[
        {
            "category":"Shopping",
            "type":"Retail Goods"
        }
    ],
    "sg:phone":"+44 116 266 8282",
    "sg:postcode":"LE4 6GD",
    "sg:province":"Leicestershire",
    "sg:tags":[
        "part",
        "accessory"
    ],
    "wof:name":"LAKHANI MOTORS",
    "wof:placetype":"venue"
},
  "geometry": {"coordinates":[-1.1090910435,52.6514472961],"type":"Point"}
}