{
  "type": "Feature",
  "properties": {
    "addr:full":"Wellington Studio, 23 Wellington Mews London Greater London SE7 7TF",
    "addr:housenumber":"23",
    "addr:postcode":"se7 7tf",
    "addr:street":"Wellington Mews",
    "iso:country":"GB",
    "sg:address":"Wellington Studio, 23 Wellington Mews",
    "sg:city":"London",
    "sg:classifiers":[
        {
            "category":"Professional",
            "subcategory":"Engineering",
            "type":"Services"
        }
    ],
    "sg:phone":"+44 20 8293 3119",
    "sg:postcode":"SE7 7TF",
    "sg:province":"Greater London",
    "sg:tags":[
        "consultant",
        "structural"
    ],
    "sg:website":"http://www.structuralengineer.btinternet.co.uk",
    "wof:name":"David Powell Edmondson & Partners",
    "wof:placetype":"venue"
},
  "geometry": {"coordinates":[0.03066,51.483452],"type":"Point"}
}