{
  "type": "Feature",
  "properties": {
    "addr:full":"2 Brickyard Bungalow, Tonbridge Rd Edenbridge East Sussex TN8 7AU",
    "addr:housenumber":"2",
    "addr:postcode":"tn8 7au",
    "addr:street":"Brickyard;Tonbridge Rd",
    "iso:country":"GB",
    "sg:address":"2 Brickyard Bungalow, Tonbridge Rd",
    "sg:city":"Edenbridge",
    "sg:classifiers":[
        {
            "category":"Building & Trades",
            "subcategory":"Landscaping Services",
            "type":"Services"
        }
    ],
    "sg:phone":"+44 1892 870929",
    "sg:postcode":"TN8 7AU",
    "sg:province":"East Sussex",
    "sg:tags":[
        "landscape",
        "contractor"
    ],
    "wof:name":"T Harbert",
    "wof:placetype":"venue"
},
  "geometry": {"coordinates":[0.0647469983,51.1973876953],"type":"Point"}
}