{
  "type": "Feature",
  "properties": {
    "addr:full":"Unit 5 Heol Ty Gwyn Indust Est Maesteg Bridgend CF34 0BQ",
    "addr:housenumber":"unit 5",
    "addr:postcode":"cf34 0bq",
    "addr:street":"Heol Ty Gwyn Indust Est",
    "iso:country":"GB",
    "sg:address":"Unit 5 Heol Ty Gwyn Indust Est",
    "sg:city":"Maesteg",
    "sg:classifiers":[
        {
            "category":"Freight",
            "type":"Transportation"
        }
    ],
    "sg:phone":"+44 1656 737127",
    "sg:postcode":"CF34 0BQ",
    "sg:province":"Bridgend",
    "sg:tags":[
        "haulage",
        "road"
    ],
    "wof:name":"G & H Ames Ltd",
    "wof:placetype":"venue"
},
  "geometry": {"coordinates":[-3.665857,51.614807],"type":"Point"}
}