{
  "type": "Feature",
  "properties": {
    "addr:full":"Sweet Briar Retail Park, Sweet Briar Road Norwich Norfolk NR6 5AL",
    "addr:postcode":"nr6 5al",
    "addr:street":"Sweet Briar Retail Park Sweet Briar Road Norwich Norfolk",
    "iso:country":"GB",
    "sg:address":"Sweet Briar Retail Park, Sweet Briar Road",
    "sg:city":"Norwich",
    "sg:classifiers":[
        {
            "category":"Professional",
            "subcategory":"Computer Services",
            "type":"Services"
        }
    ],
    "sg:phone":"+44 1603 406777",
    "sg:postcode":"NR6 5AL",
    "sg:province":"Norfolk",
    "sg:tags":[
        "system",
        "software"
    ],
    "wof:name":"D S G Retail Ltd.",
    "wof:placetype":"venue"
},
  "geometry": {"coordinates":[1.26123,52.64986],"type":"Point"}
}