{
  "type": "Feature",
  "properties": {
    "addr:full":"6 Old Bury Hill House, Old Bury Hill, Westcott Dorking Surrey RH4 3JU",
    "addr:housenumber":"6",
    "addr:postcode":"rh4 3ju",
    "addr:street":"Old Bury Hill;Old Bury Hill",
    "iso:country":"GB",
    "sg:address":"6 Old Bury Hill House, Old Bury Hill, Westcott",
    "sg:city":"Dorking",
    "sg:classifiers":[
        {
            "category":"Building & Trades",
            "subcategory":"Construction",
            "type":"Services"
        }
    ],
    "sg:postcode":"RH4 3JU",
    "sg:province":"Surrey",
    "sg:tags":[
        "decorator",
        "painter"
    ],
    "wof:name":"First Impressions",
    "wof:placetype":"venue"
},
  "geometry": {"coordinates":[-0.366299,51.225433],"type":"Point"}
}