{
  "type": "Feature",
  "properties": {
    "addr:full":"226 Union Road, Oswaldtwistle Accrington Lancashire BB5 3JB",
    "addr:housenumber":"226",
    "addr:postcode":"bb5 3jb",
    "addr:street":"Union Road;Accrington",
    "iso:country":"GB",
    "sg:address":"226 Union Road, Oswaldtwistle",
    "sg:city":"Accrington",
    "sg:classifiers":[
        {
            "category":"Bars & Pubs",
            "type":"Food & Drink"
        }
    ],
    "sg:phone":"+44 1254 234689",
    "sg:postcode":"BB5 3JB",
    "sg:province":"Lancashire",
    "sg:tags":[
        "pubs",
        "inn"
    ],
    "wof:name":"Pubmaster Ltd.",
    "wof:placetype":"venue"
},
  "geometry": {"coordinates":[-2.395989,53.743511],"type":"Point"}
}