{
  "type": "Feature",
  "properties": {
    "addr:full":"14 Ivy House Road Uxbridge Greater London UB10 8NE",
    "addr:housenumber":"14",
    "addr:postcode":"ub10 8ne",
    "addr:street":"Ivy House Road",
    "iso:country":"GB",
    "sg:address":"14 Ivy House Road",
    "sg:city":"Uxbridge",
    "sg:classifiers":[
        {
            "category":"Building & Trades",
            "subcategory":"Plumbing",
            "type":"Services"
        }
    ],
    "sg:postcode":"UB10 8NE",
    "sg:province":"Greater London",
    "sg:tags":[
        "heating"
    ],
    "wof:name":"Anthony M McLennan",
    "wof:placetype":"venue"
},
  "geometry": {"coordinates":[-0.447358,51.564705],"type":"Point"}
}