{
  "type": "Feature",
  "properties": {
    "iso:country":"GB",
    "sg:address":"1 Wharfedale Place",
    "sg:city":"Harrogate",
    "sg:classifiers":[
        {
            "category":"Personal",
            "type":"Services"
        }
    ],
    "sg:postcode":"HG2 0AY",
    "sg:province":"North Yorkshire",
    "sg:tags":[
        "dressmaker"
    ],
    "wof:name":"C Crossley",
    "wof:placetype":"venue"
},
  "geometry": {"coordinates":[-1.560286,53.981071],"type":"Point"}
}