{
  "type": "Feature",
  "properties": {
    "iso:country":"GB",
    "sg:address":"4-6 Wharf Street",
    "sg:city":"Leeds",
    "sg:classifiers":[
        {
            "category":"Real Estate",
            "subcategory":"Surveying",
            "type":"Services"
        }
    ],
    "sg:phone":"+44 113 244 5713",
    "sg:postcode":"LS2 7EQ",
    "sg:province":"West Yorkshire",
    "sg:tags":[
        "surveyor",
        "quantity"
    ],
    "wof:name":"Speight Simpson Partnership",
    "wof:placetype":"venue"
},
  "geometry": {"coordinates":[-1.5375189781,53.7955627441],"type":"Point"}
}