{
  "type": "Feature",
  "properties": {
    "addr:full":"292 High Rd, Leyton Leyton Greater London E10 5PW",
    "addr:housenumber":"292",
    "addr:postcode":"e10 5pw",
    "addr:street":"High Rd",
    "iso:country":"GB",
    "sg:address":"292 High Rd, Leyton",
    "sg:city":"Leyton",
    "sg:classifiers":[
        {
            "category":"Taxi",
            "type":"Transportation"
        }
    ],
    "sg:phone":"+44 20 8923 8885",
    "sg:postcode":"E10 5PW",
    "sg:province":"Greater London",
    "sg:tags":[
        "mini",
        "cab"
    ],
    "wof:name":"Vehicular Reality-glam Cars",
    "wof:placetype":"venue"
},
  "geometry": {"coordinates":[-0.009118,51.5600471497],"type":"Point"}
}