{
  "type": "Feature",
  "properties": {
    "addr:full":"6a Locarno Road Tipton West Midlands DY4 9SH",
    "addr:housenumber":"6a",
    "addr:postcode":"dy4 9sh",
    "addr:street":"Locarno Road",
    "iso:country":"GB",
    "sg:address":"6a Locarno Road",
    "sg:city":"Tipton",
    "sg:classifiers":[
        {
            "category":"Government",
            "subcategory":"Post Office",
            "type":"Public Place"
        }
    ],
    "sg:phone":"+44 121 557 1468",
    "sg:postcode":"DY4 9SH",
    "sg:province":"West Midlands",
    "wof:name":"Locarno Road Post Office",
    "wof:placetype":"venue"
},
  "geometry": {"coordinates":[-2.057467,52.533569],"type":"Point"}
}