{
  "type": "Feature",
  "properties": {
    "addr:full":"12 St. Peters Way Derby Derbyshire DE1 2NR",
    "addr:housenumber":"12",
    "addr:postcode":"de1 2nr",
    "addr:street":"St. Peters Way",
    "iso:country":"GB",
    "sg:address":"12 St. Peters Way",
    "sg:city":"Derby",
    "sg:classifiers":[
        {
            "category":"Shopping",
            "subcategory":"Clothing, Apparel, & Fashions",
            "type":"Retail Goods"
        }
    ],
    "sg:phone":"+44 1332 361008",
    "sg:postcode":"DE1 2NR",
    "sg:province":"Derbyshire",
    "sg:tags":[
        "shop"
    ],
    "wof:name":"Cuba",
    "wof:placetype":"venue"
},
  "geometry": {"coordinates":[-1.4774440527,52.9204483032],"type":"Point"}
}