{
  "type": "Feature",
  "properties": {
    "iso:country":"GB",
    "sg:address":"Friday Hill House, 7 Simmons Lane",
    "sg:city":"Chingford",
    "sg:classifiers":[
        {
            "category":"Education",
            "subcategory":"University",
            "type":"Public Place"
        },
        {
            "category":"Education",
            "subcategory":"School",
            "type":"Public Place"
        }
    ],
    "sg:phone":"+44 20 8529 3380",
    "sg:postcode":"E4 6JH",
    "sg:province":"Greater London",
    "sg:tags":[
        "local",
        "adult",
        "authority"
    ],
    "wof:name":"Chingford Adult & Community Education Centre",
    "wof:placetype":"venue"
},
  "geometry": {"coordinates":[0.00199,51.623916626],"type":"Point"}
}