{
  "type": "Feature",
  "properties": {
    "iso:country":"GB",
    "sg:address":"9 St Norbert Grn",
    "sg:city":"London",
    "sg:classifiers":[
        {
            "category":"Building & Trades",
            "subcategory":"Construction",
            "type":"Services"
        }
    ],
    "sg:phone":"+44 20 7732 3125",
    "sg:postcode":"SE4 2HD",
    "sg:province":"Greater London",
    "sg:tags":[
        "tiling",
        "contractor"
    ],
    "wof:name":"Beta Tiling",
    "wof:placetype":"venue"
},
  "geometry": {"coordinates":[-0.0393790007,51.4614181519],"type":"Point"}
}