{
  "type": "Feature",
  "properties": {
    "iso:country":"GB",
    "sg:address":"87 Trinity Square",
    "sg:city":"Margate",
    "sg:classifiers":[
        {
            "category":"Personal",
            "subcategory":"Beauty Salon",
            "type":"Services"
        }
    ],
    "sg:phone":"+44 1843 221040",
    "sg:postcode":"CT9 1QD",
    "sg:province":"Kent",
    "sg:tags":[
        "lady",
        "hairdresser"
    ],
    "wof:name":"G Herms",
    "wof:placetype":"venue"
},
  "geometry": {"coordinates":[1.387595,51.391235],"type":"Point"}
}