{
  "type": "Feature",
  "properties": {
    "addr:full":"2 Chapel Street, Mow Cop Stoke-on-trent Cheshire ST7 4NT",
    "addr:housenumber":"2",
    "addr:postcode":"st7 4nt",
    "addr:street":"Chapel Street",
    "iso:country":"GB",
    "sg:address":"2 Chapel Street, Mow Cop",
    "sg:city":"Stoke-on-trent",
    "sg:classifiers":[
        {
            "category":"Shopping",
            "subcategory":"News",
            "type":"Retail Goods"
        }
    ],
    "sg:phone":"+44 1782 513261",
    "sg:postcode":"ST7 4NT",
    "sg:province":"Cheshire",
    "sg:tags":[
        "newsagent"
    ],
    "wof:name":"J & J Heath",
    "wof:placetype":"venue"
},
  "geometry": {"coordinates":[-2.2265789509,53.1067123413],"type":"Point"}
}