{
  "type": "Feature",
  "properties": {
    "iso:country":"GB",
    "sg:address":"Corse Croft, Kinnoir",
    "sg:city":"Huntly",
    "sg:classifiers":[
        {
            "category":"Transit Center",
            "subcategory":"Passenger",
            "type":"Transportation"
        }
    ],
    "sg:phone":"+44 1466 711404",
    "sg:postcode":"AB54 7YS",
    "sg:province":"Aberdeenshire",
    "sg:tags":[
        "boarding",
        "kennel",
        "catteries"
    ],
    "wof:name":"Corse Croft Cattery",
    "wof:placetype":"venue"
},
  "geometry": {"coordinates":[-2.736554,57.478146],"type":"Point"}
}