{
  "type": "Feature",
  "properties": {
    "addr:full":"3 Rochford Dr Luton Bedfordshire LU2 8SP",
    "addr:housenumber":"3",
    "addr:postcode":"lu2 8sp",
    "addr:street":"Rochford Dr",
    "iso:country":"GB",
    "sg:address":"3 Rochford Dr",
    "sg:city":"Luton",
    "sg:classifiers":[
        {
            "category":"Shopping",
            "subcategory":"Mobile Phones",
            "type":"Retail Goods"
        }
    ],
    "sg:phone":"+44 1582 480339",
    "sg:postcode":"LU2 8SP",
    "sg:province":"Bedfordshire",
    "wof:name":"Ace Communications",
    "wof:placetype":"venue"
},
  "geometry": {"coordinates":[-0.3726600111,51.8921165466],"type":"Point"}
}