{
  "type": "Feature",
  "properties": {
    "iso:country":"GB",
    "sg:address":"6 Highland Rd",
    "sg:city":"Southsea",
    "sg:classifiers":[
        {
            "category":"Shopping",
            "subcategory":"Used Merchandise",
            "type":"Retail Goods"
        }
    ],
    "sg:phone":"+44 23 9278 9189",
    "sg:postcode":"PO4 9AH",
    "sg:province":"Hampshire",
    "sg:tags":[
        "shop",
        "second-hand"
    ],
    "wof:name":"Austin Furnitures",
    "wof:placetype":"venue"
},
  "geometry": {"coordinates":[-1.069729,50.786079],"type":"Point"}
}