{
  "type": "Feature",
  "properties": {
    "iso:country":"GB",
    "sg:address":"6 Kingshill View, Law",
    "sg:city":"Carluke",
    "sg:classifiers":[
        {
            "category":"Home & Garden",
            "subcategory":"Hardware",
            "type":"Retail Goods"
        }
    ],
    "sg:phone":"+44 1698 375063",
    "sg:postcode":"ML8 5LA",
    "sg:province":"South Lanarkshire",
    "sg:tags":[
        "equipment",
        "wire",
        "cable"
    ],
    "wof:name":"H M Cabling Systems Ltd.",
    "wof:placetype":"venue"
},
  "geometry": {"coordinates":[-3.879112,55.744564],"type":"Point"}
}