{
  "type": "Feature",
  "properties": {
    "iso:country":"GB",
    "sg:address":"626 Bradford Rd",
    "sg:city":"Batley",
    "sg:classifiers":[
        {
            "category":"Manufacturing",
            "subcategory":"Building Materials",
            "type":"Manufacturing & Wholesale Goods"
        }
    ],
    "sg:postcode":"WF17 8HF",
    "sg:province":"West Yorkshire",
    "sg:tags":[
        "shutter",
        "supp",
        "door"
    ],
    "wof:name":"Hardacre,Darren,",
    "wof:placetype":"venue"
},
  "geometry": {"coordinates":[-1.645511,53.721767],"type":"Point"}
}