{
  "type": "Feature",
  "properties": {
    "iso:country":"GB",
    "sg:address":"Stn Rd West, Ash Vale",
    "sg:city":"Aldershot",
    "sg:classifiers":[
        {
            "category":"Retail",
            "subcategory":"Auto Repair",
            "type":"Services"
        }
    ],
    "sg:postcode":"GU12 5QD",
    "sg:province":"Hampshire",
    "sg:tags":[
        "modification",
        "garage"
    ],
    "wof:name":"Adamson, D",
    "wof:placetype":"venue"
},
  "geometry": {"coordinates":[-0.720989,51.266731],"type":"Point"}
}