{
  "type": "Feature",
  "properties": {
    "addr:full":"Cavendish House, Cavendish Rise Dronfield Derbyshire S18 1QZ",
    "addr:postcode":"s18 1qz",
    "addr:street":"Cavendish Rise",
    "iso:country":"GB",
    "sg:address":"Cavendish House, Cavendish Rise",
    "sg:city":"Dronfield",
    "sg:classifiers":[
        {
            "category":"Real Estate",
            "subcategory":"Real Estate Agent",
            "type":"Services"
        }
    ],
    "sg:phone":"+44 1246 291330",
    "sg:postcode":"S18 1QZ",
    "sg:province":"Derbyshire",
    "wof:name":"Castle Estates",
    "wof:placetype":"venue"
},
  "geometry": {"coordinates":[-1.477064,53.297401],"type":"Point"}
}