{
  "type": "Feature",
  "properties": {
    "iso:country":"GB",
    "sg:address":"81 Leadside Rd",
    "sg:city":"Aberdeen",
    "sg:classifiers":[
        {
            "category":"Farming",
            "subcategory":"Livestock Farm",
            "type":"Manufacturing & Wholesale Goods"
        },
        {
            "category":"Shopping",
            "subcategory":"Florist",
            "type":"Retail Goods"
        }
    ],
    "sg:postcode":"AB25 1RX",
    "sg:province":"Aberdeen City",
    "sg:tags":[
        "breeder"
    ],
    "wof:name":"Bradley,Phil,",
    "wof:placetype":"venue"
},
  "geometry": {"coordinates":[-2.111068964,57.1486053467],"type":"Point"}
}