{
  "type": "Feature",
  "properties": {
    "iso:country":"GB",
    "sg:address":"41 Edgehill Drive",
    "sg:city":"Daventry",
    "sg:classifiers":[
        {
            "category":"Health Services",
            "subcategory":"Clinic",
            "type":"Services"
        }
    ],
    "sg:postcode":"NN11 5GR",
    "sg:province":"Northamptonshire",
    "sg:tags":[
        "medical"
    ],
    "wof:name":"Churchill Medical Ltd.",
    "wof:placetype":"venue"
},
  "geometry": {"coordinates":[-1.158184,52.277206],"type":"Point"}
}