{
  "type": "Feature",
  "properties": {
    "iso:country":"GB",
    "sg:address":"Meadowbank, Croft Road",
    "sg:city":"Crowborough",
    "sg:classifiers":[
        {
            "category":"Organizations",
            "subcategory":"Non-profit Organization",
            "type":"Services"
        }
    ],
    "sg:phone":"+44 1892 668151",
    "sg:postcode":"TN6 1DL",
    "sg:province":"East Sussex",
    "sg:tags":[
        "organisation",
        "voluntary",
        "charity"
    ],
    "wof:name":"Crowborough & District Volunteer Bureau",
    "wof:placetype":"venue"
},
  "geometry": {"coordinates":[0.1718930006,51.0531959534],"type":"Point"}
}