{
  "type": "Feature",
  "properties": {
    "iso:country":"GB",
    "sg:address":"Lowcroft House, Church Road",
    "sg:city":"Wolverhampton",
    "sg:classifiers":[
        {
            "category":"Health Services",
            "subcategory":"Health Practitioner",
            "type":"Services"
        }
    ],
    "sg:phone":"+44 1902 898256",
    "sg:postcode":"WV5 9EZ",
    "sg:province":"Shropshire",
    "sg:tags":[
        "physiotherapist"
    ],
    "wof:name":"Derek Potter",
    "wof:placetype":"venue"
},
  "geometry": {"coordinates":[-2.184359,52.535923],"type":"Point"}
}