{
  "type": "Feature",
  "properties": {
    "addr:full":"Unit 1a Rectory Business Centre, Rectory La Sidcup Kent DA14 4QQ",
    "addr:housenumber":"unit 1a rectory business centre",
    "addr:postcode":"da14 4qq",
    "addr:street":"Rectory La Sidcup",
    "iso:country":"GB",
    "sg:address":"Unit 1a Rectory Business Centre, Rectory La",
    "sg:city":"Sidcup",
    "sg:classifiers":[
        {
            "category":"Professional",
            "subcategory":"Engineering",
            "type":"Services"
        }
    ],
    "sg:phone":"+44 20 8308 9274",
    "sg:postcode":"DA14 4QQ",
    "sg:province":"Kent",
    "sg:tags":[
        "contractor",
        "electrical",
        "engineer"
    ],
    "wof:name":"Cobra Electrical Services Ltd",
    "wof:placetype":"venue"
},
  "geometry": {"coordinates":[0.103945002,51.4259185791],"type":"Point"}
}