{
  "type": "Feature",
  "properties": {
    "addr:full":"Old Park Rd Bradford West Yorkshire BD10 9QZ",
    "addr:postcode":"bd10 9qz",
    "addr:street":"Old Park Rd",
    "iso:country":"GB",
    "sg:address":"Old Park Rd",
    "sg:city":"Bradford",
    "sg:classifiers":[
        {
            "category":"Social Services",
            "subcategory":"Retirement Home",
            "type":"Services"
        }
    ],
    "sg:phone":"+44 1274 616850",
    "sg:postcode":"BD10 9QZ",
    "sg:province":"West Yorkshire",
    "sg:tags":[
        "residential",
        "care"
    ],
    "wof:name":"Coburg Residential Care Home",
    "wof:placetype":"venue"
},
  "geometry": {"coordinates":[-1.722034,53.83387],"type":"Point"}
}