{
  "type": "Feature",
  "properties": {
    "addr:full":"Hill Top Ho, Holywell Rd, Clipsham Oakham Leicestershire LE15 7SG",
    "addr:postcode":"le15 7sg",
    "addr:street":"Holywell Rd",
    "iso:country":"GB",
    "sg:address":"Hill Top Ho, Holywell Rd, Clipsham",
    "sg:city":"Oakham",
    "sg:classifiers":[
        {
            "category":"Farming",
            "subcategory":"Livestock Farm",
            "type":"Manufacturing & Wholesale Goods"
        }
    ],
    "sg:postcode":"LE15 7SG",
    "sg:province":"Leicestershire",
    "sg:tags":[
        "others"
    ],
    "wof:name":"Feathersone,Peter R,",
    "wof:placetype":"venue"
},
  "geometry": {"coordinates":[-0.5648130178,52.7338829041],"type":"Point"}
}