{
  "type": "Feature",
  "properties": {
    "iso:country":"GB",
    "sg:address":"Mid Yell",
    "sg:city":"Shetland",
    "sg:classifiers":[
        {
            "category":"Farming",
            "subcategory":"Fish & Marine Products",
            "type":"Manufacturing & Wholesale Goods"
        }
    ],
    "sg:phone":"+44 1957 702112",
    "sg:postcode":"ZE2 9BN",
    "sg:province":"Shetland Islands",
    "sg:tags":[
        "fishmonger"
    ],
    "wof:name":"Shetland-Norse Preserving Co. Ltd.",
    "wof:placetype":"venue"
},
  "geometry": {"coordinates":[-1.06832,60.601501],"type":"Point"}
}