{
  "type": "Feature",
  "properties": {
    "addr:full":"High Street, St Clears Carmarthen Carmarthenshire SA33 4EE",
    "addr:postcode":"sa33 4ee",
    "addr:street":"High Street",
    "iso:country":"GB",
    "sg:address":"High Street, St Clears",
    "sg:city":"Carmarthen",
    "sg:classifiers":[
        {
            "category":"Bars & Pubs",
            "type":"Food & Drink"
        }
    ],
    "sg:phone":"+44 1994 231251",
    "sg:postcode":"SA33 4EE",
    "sg:province":"Carmarthenshire",
    "sg:tags":[
        "pubs",
        "inn"
    ],
    "wof:name":"Santa Clara Inn",
    "wof:placetype":"venue"
},
  "geometry": {"coordinates":[-4.4984908104,51.8188171387],"type":"Point"}
}