{
  "type": "Feature",
  "properties": {
    "iso:country":"GB",
    "sg:address":"4 Firs Road, Tullibody",
    "sg:city":"Alloa",
    "sg:classifiers":[
        {
            "category":"Building & Trades",
            "subcategory":"Plumbing",
            "type":"Services"
        }
    ],
    "sg:phone":"+44 1259 722837",
    "sg:postcode":"FK10 2TH",
    "sg:province":"Clackmannanshire",
    "sg:tags":[
        "heating"
    ],
    "wof:name":"A I Hendry Plumbers",
    "wof:placetype":"venue"
},
  "geometry": {"coordinates":[-3.827002,56.134052],"type":"Point"}
}