{
  "type": "Feature",
  "properties": {
    "addr:full":"3 Somerby Close Broxbourne Essex EN10 7AE",
    "addr:housenumber":"3",
    "addr:postcode":"en10 7ae",
    "addr:street":"Somerby Close",
    "iso:country":"GB",
    "sg:address":"3 Somerby Close",
    "sg:city":"Broxbourne",
    "sg:classifiers":[
        {
            "category":"Building & Trades",
            "subcategory":"Construction",
            "type":"Services"
        }
    ],
    "sg:postcode":"EN10 7AE",
    "sg:province":"Essex",
    "sg:tags":[
        "joiner",
        "carpenter"
    ],
    "wof:name":"K & S Partners",
    "wof:placetype":"venue"
},
  "geometry": {"coordinates":[-0.014252,51.744099],"type":"Point"}
}