{
  "type": "Feature",
  "properties": {
    "addr:full":"Heronbank, 99a Tay Street Newport-on-tay Fife DD6 8AR",
    "addr:housenumber":"99a",
    "addr:postcode":"dd6 8ar",
    "addr:street":"Heronbank;Tay Street",
    "iso:country":"GB",
    "sg:address":"Heronbank, 99a Tay Street",
    "sg:city":"Newport-on-tay",
    "sg:classifiers":[
        {
            "category":"Professional",
            "subcategory":"Management & Consulting",
            "type":"Services"
        }
    ],
    "sg:phone":"+44 1382 541777",
    "sg:postcode":"DD6 8AR",
    "sg:province":"Fife",
    "sg:tags":[
        "marketing",
        "consultant"
    ],
    "wof:name":"Heron Communications",
    "wof:placetype":"venue"
},
  "geometry": {"coordinates":[-2.9417309761,56.4398117065],"type":"Point"}
}