{
  "type": "Feature",
  "properties": {
    "addr:full":"175 Kenn Road Clevedon Somerset BS21 6LH",
    "addr:housenumber":"175",
    "addr:postcode":"bs21 6lh",
    "addr:street":"Kenn Road",
    "iso:country":"GB",
    "sg:address":"175 Kenn Road",
    "sg:city":"Clevedon",
    "sg:classifiers":[
        {
            "category":"Professional",
            "subcategory":"Testing Lab",
            "type":"Services"
        }
    ],
    "sg:phone":"+44 1275 793000",
    "sg:postcode":"BS21 6LH",
    "sg:province":"Somerset",
    "sg:tags":[
        "laboratory"
    ],
    "wof:name":"Labcaire Systems Ltd.",
    "wof:placetype":"venue"
},
  "geometry": {"coordinates":[-2.852793,51.429344],"type":"Point"}
}