{
  "type": "Feature",
  "properties": {
    "iso:country":"GB",
    "sg:address":"1a Shenley Road",
    "sg:city":"Dartford",
    "sg:classifiers":[
        {
            "category":"Home & Garden",
            "subcategory":"Hardware",
            "type":"Retail Goods"
        }
    ],
    "sg:postcode":"DA1 1YF",
    "sg:province":"Kent",
    "sg:tags":[
        "equipment",
        "welding"
    ],
    "wof:name":"Martin Welding Equipment Co. Limited",
    "wof:placetype":"venue"
},
  "geometry": {"coordinates":[0.2322520018,51.4422416687],"type":"Point"}
}