{
  "type": "Feature",
  "properties": {
    "addr:full":"Earls Croome Nursery, Worcester Rd Worcester Gloucestershire WR8 9DA",
    "addr:postcode":"wr8 9da",
    "addr:street":"Worcester Rd",
    "iso:country":"GB",
    "sg:address":"Earls Croome Nursery, Worcester Rd",
    "sg:city":"Worcester",
    "sg:classifiers":[
        {
            "category":"Restaurant",
            "type":"Food & Drink"
        }
    ],
    "sg:phone":"+44 1684 594475",
    "sg:postcode":"WR8 9DA",
    "sg:province":"Gloucestershire",
    "wof:name":"Robins Restaurant",
    "wof:placetype":"venue"
},
  "geometry": {"coordinates":[-2.192059,52.07851],"type":"Point"}
}