{
  "type": "Feature",
  "properties": {
    "iso:country":"GB",
    "sg:address":"3 Winchester Street, Overton",
    "sg:city":"Basingstoke",
    "sg:classifiers":[
        {
            "category":"Personal",
            "subcategory":"Beauty Salon",
            "type":"Services"
        },
        {
            "category":"Personal",
            "subcategory":"Barber",
            "type":"Services"
        },
        {
            "category":"Retail",
            "subcategory":"Repair Shop",
            "type":"Services"
        }
    ],
    "sg:phone":"+44 1256 771180",
    "sg:postcode":"RG25 3HR",
    "sg:province":"Hampshire",
    "sg:tags":[
        "unisex",
        "maintenance",
        "hairdresser"
    ],
    "wof:name":"Checkmate",
    "wof:placetype":"venue"
},
  "geometry": {"coordinates":[-1.2628760338,51.2437820435],"type":"Point"}
}