{
  "type": "Feature",
  "properties": {
    "addr:full":"Bryant House, 21 Silverdale Road, Wolstanton Newcastle Staffordshire ST5 8BQ",
    "addr:housenumber":"21",
    "addr:postcode":"st5 8bq",
    "addr:street":"Silverdale Road",
    "iso:country":"GB",
    "sg:address":"Bryant House, 21 Silverdale Road, Wolstanton",
    "sg:city":"Newcastle",
    "sg:classifiers":[
        {
            "category":"Banks & Credit Unions",
            "subcategory":"Financial Services",
            "type":"Services"
        }
    ],
    "sg:phone":"+44 1782 712233",
    "sg:postcode":"ST5 8BQ",
    "sg:province":"Staffordshire",
    "sg:tags":[
        "adviser"
    ],
    "wof:name":"S D B Strategic Planners Ltd.",
    "wof:placetype":"venue"
},
  "geometry": {"coordinates":[-2.220108,53.030796],"type":"Point"}
}