{
  "type": "Feature",
  "properties": {
    "iso:country":"GB",
    "sg:address":"1 Moorfields, Moorhaven",
    "sg:city":"Ivybridge",
    "sg:classifiers":[
        {
            "category":"Professional",
            "subcategory":"Management & Consulting",
            "type":"Services"
        }
    ],
    "sg:postcode":"PL21 0XQ",
    "sg:province":"Devon",
    "sg:tags":[
        "consultant",
        "business"
    ],
    "wof:name":"Collage Consulting Ltd",
    "wof:placetype":"venue"
},
  "geometry": {"coordinates":[-3.8964109421,50.3773269653],"type":"Point"}
}