{
  "type": "Feature",
  "properties": {
    "addr:full":"28 Lower Market Street Penryn Cornwall TR10 8BG",
    "addr:housenumber":"28",
    "addr:postcode":"tr10 8bg",
    "addr:street":"Lower Market Street",
    "iso:country":"GB",
    "sg:address":"28 Lower Market Street",
    "sg:city":"Penryn",
    "sg:classifiers":[
        {
            "category":"Personal",
            "subcategory":"Beauty Salon",
            "type":"Services"
        }
    ],
    "sg:postcode":"TR10 8BG",
    "sg:province":"Cornwall",
    "sg:tags":[
        "unisex",
        "hairdresser"
    ],
    "wof:name":"Hair by Jeanette",
    "wof:placetype":"venue"
},
  "geometry": {"coordinates":[-5.104809,50.168575],"type":"Point"}
}