{
  "type": "Feature",
  "properties": {
    "addr:full":"319 Romford Road Forest Gate Greater London E7 9HA",
    "addr:housenumber":"319",
    "addr:postcode":"e7 9ha",
    "addr:street":"Romford Road;Gate",
    "iso:country":"GB",
    "sg:address":"319 Romford Road",
    "sg:city":"Forest Gate",
    "sg:classifiers":[
        {
            "category":"Real Estate",
            "subcategory":"Real Estate Agent",
            "type":"Services"
        }
    ],
    "sg:phone":"+44 20 8519 9887",
    "sg:postcode":"E7 9HA",
    "sg:province":"Greater London",
    "wof:name":"United Enterprises",
    "wof:placetype":"venue"
},
  "geometry": {"coordinates":[0.0236900002,51.5463104248],"type":"Point"}
}