{
  "type": "Feature",
  "properties": {
    "addr:full":"St Martins, Chequers Lane Basingstoke Berkshire RG27 0NY",
    "addr:postcode":"rg27 0ny",
    "addr:street":"Chequers Lane",
    "iso:country":"GB",
    "sg:address":"St Martins, Chequers Lane",
    "sg:city":"Basingstoke",
    "sg:classifiers":[
        {
            "category":"Retail",
            "subcategory":"Auto Repair",
            "type":"Services"
        }
    ],
    "sg:phone":"+44 1252 870221",
    "sg:postcode":"RG27 0NY",
    "sg:province":"Berkshire",
    "sg:tags":[
        "modification",
        "car",
        "vehicle",
        "commercial",
        "garage"
    ],
    "wof:name":"Orlando Engineering Ltd",
    "wof:placetype":"venue"
},
  "geometry": {"coordinates":[-0.8609700203,51.3433494568],"type":"Point"}
}