{
  "type": "Feature",
  "properties": {
    "addr:full":"218 Manor Oaks Road Sheffield South Yorkshire S2 5EE",
    "addr:housenumber":"218",
    "addr:postcode":"s2 5ee",
    "addr:street":"Manor Oaks Road",
    "iso:country":"GB",
    "sg:address":"218 Manor Oaks Road",
    "sg:city":"Sheffield",
    "sg:classifiers":[
        {
            "category":"Personal",
            "subcategory":"Beauty Salon",
            "type":"Services"
        }
    ],
    "sg:phone":"+44 114 249 0440",
    "sg:postcode":"S2 5EE",
    "sg:province":"South Yorkshire",
    "sg:tags":[
        "unisex",
        "hairdresser"
    ],
    "wof:name":"Just Cutz",
    "wof:placetype":"venue"
},
  "geometry": {"coordinates":[-1.4422819614,53.3786239624],"type":"Point"}
}