{
  "type": "Feature",
  "properties": {
    "iso:country":"GB",
    "sg:address":"Frome House, Lower Bristol Road",
    "sg:city":"Bath",
    "sg:classifiers":[
        {
            "category":"Insurance",
            "subcategory":"Insurance Agent",
            "type":"Services"
        }
    ],
    "sg:phone":"+44 1225 444553",
    "sg:postcode":"BA2 1EY",
    "sg:province":"Somerset",
    "sg:tags":[
        "broker"
    ],
    "wof:name":"Kallender Jeffries Insurance Brokers Ltd.",
    "wof:placetype":"venue"
},
  "geometry": {"coordinates":[-2.388463,51.380451],"type":"Point"}
}