{
  "type": "Feature",
  "properties": {
    "iso:country":"GB",
    "sg:address":"Unit, 121, , 30 Great Guildford St",
    "sg:city":"Southwark",
    "sg:classifiers":[
        {
            "category":"Shopping",
            "subcategory":"Photographic Equipment",
            "type":"Retail Goods"
        }
    ],
    "sg:phone":"+44 20 7928 9343",
    "sg:postcode":"SE1 0HS",
    "sg:province":"Greater London",
    "wof:name":"P Tuke",
    "wof:placetype":"venue"
},
  "geometry": {"coordinates":[-0.0973000005,51.5049934387],"type":"Point"}
}