{
  "type": "Feature",
  "properties": {
    "iso:country":"GB",
    "sg:address":"14 Upr Frog St",
    "sg:city":"Tenby",
    "sg:classifiers":[
        {
            "category":"Manufacturing",
            "subcategory":"Pottery",
            "type":"Manufacturing & Wholesale Goods"
        }
    ],
    "sg:postcode":"SA70 7JD",
    "sg:province":"Pembrokeshire",
    "wof:name":"Tenby Pottery Studio",
    "wof:placetype":"venue"
},
  "geometry": {"coordinates":[-4.6991028786,51.6702880859],"type":"Point"}
}