{
  "type": "Feature",
  "properties": {
    "addr:full":"Lodge Road Maldon Essex CM9 6HW",
    "addr:postcode":"cm9 6hw",
    "addr:street":"Lodge Road",
    "iso:country":"GB",
    "sg:address":"Lodge Road",
    "sg:city":"Maldon",
    "sg:classifiers":[
        {
            "category":"Social Services",
            "subcategory":"Retirement Home",
            "type":"Services"
        }
    ],
    "sg:phone":"+44 1621 858286",
    "sg:postcode":"CM9 6HW",
    "sg:province":"Essex",
    "sg:tags":[
        "residential",
        "care"
    ],
    "wof:name":"The Lodge Residential Retirement Home",
    "wof:placetype":"venue"
},
  "geometry": {"coordinates":[0.646699,51.71217],"type":"Point"}
}