{
  "type": "Feature",
  "properties": {
    "addr:full":"St Osburghs Priory, Barras Lane Coventry West Midlands CV1 4AQ",
    "addr:postcode":"cv1 4aq",
    "addr:street":"Priory Barras Lane",
    "iso:country":"GB",
    "sg:address":"St Osburghs Priory, Barras Lane",
    "sg:city":"Coventry",
    "sg:classifiers":[
        {
            "category":"Place Of Worship",
            "type":"Public Place"
        }
    ],
    "sg:phone":"+44 24 7622 0402",
    "sg:postcode":"CV1 4AQ",
    "sg:province":"West Midlands",
    "wof:name":"St Osburghs R C Church",
    "wof:placetype":"venue"
},
  "geometry": {"coordinates":[-1.5077680349,52.4069862366],"type":"Point"}
}