{
  "type": "Feature",
  "properties": {
    "iso:country":"GB",
    "sg:address":"148 Winchester Rd",
    "sg:city":"Alton",
    "sg:classifiers":[
        {
            "category":"Autos & Motor Vehicles",
            "subcategory":"Fuel & Gas Station",
            "type":"Retail Goods"
        }
    ],
    "sg:phone":"+44 1420 562025",
    "sg:postcode":"GU34 5HZ",
    "sg:province":"Hampshire",
    "sg:tags":[
        "petrol",
        "filling"
    ],
    "wof:name":"Elf Service Station",
    "wof:placetype":"venue"
},
  "geometry": {"coordinates":[-1.061688,51.105961],"type":"Point"}
}