{
  "type": "Feature",
  "properties": {
    "iso:country":"GB",
    "sg:address":"3 Harrold Road, Lavendon",
    "sg:city":"Olney",
    "sg:classifiers":[
        {
            "category":"Freight",
            "type":"Transportation"
        }
    ],
    "sg:postcode":"MK46 4HU",
    "sg:province":"Buckinghamshire",
    "sg:tags":[
        "haulage",
        "road"
    ],
    "wof:name":"Norman Kitchener Transport",
    "wof:placetype":"venue"
},
  "geometry": {"coordinates":[-0.656802,52.172279],"type":"Point"}
}