{
  "type": "Feature",
  "properties": {
    "addr:full":"Yarwell Drive, Maltby Rotherham South Yorkshire S66 8HZ",
    "addr:postcode":"s66 8hz",
    "addr:street":"Yarwell Drive",
    "iso:country":"GB",
    "sg:address":"Yarwell Drive, Maltby",
    "sg:city":"Rotherham",
    "sg:classifiers":[
        {
            "category":"Bars & Pubs",
            "type":"Food & Drink"
        }
    ],
    "sg:phone":"+44 1709 817660",
    "sg:postcode":"S66 8HZ",
    "sg:province":"South Yorkshire",
    "sg:tags":[
        "pubs",
        "house",
        "inn",
        "public",
        "activity"
    ],
    "wof:name":"The Haynook",
    "wof:placetype":"venue"
},
  "geometry": {"coordinates":[-1.211874,53.429852],"type":"Point"}
}