{
  "type": "Feature",
  "properties": {
    "iso:country":"GB",
    "sg:address":"234 London Road",
    "sg:city":"Benfleet",
    "sg:classifiers":[
        {
            "category":"Building & Trades",
            "subcategory":"Electrical",
            "type":"Services"
        }
    ],
    "sg:phone":"+44 1268 792125",
    "sg:postcode":"SS7 5UP",
    "sg:province":"Essex",
    "sg:tags":[
        "galvanising"
    ],
    "wof:name":"Industrial Platers Ltd.",
    "wof:placetype":"venue"
},
  "geometry": {"coordinates":[0.558153,51.566685],"type":"Point"}
}