{
  "type": "Feature",
  "properties": {
    "iso:country":"GB",
    "sg:address":"Newbridge Industrial Estate",
    "sg:city":"Newbridge",
    "sg:classifiers":[
        {
            "category":"Manufacturing",
            "subcategory":"Metals",
            "type":"Manufacturing & Wholesale Goods"
        }
    ],
    "sg:phone":"+44 131 333 3310",
    "sg:postcode":"EH28 8PJ",
    "sg:province":"City of Edinburgh",
    "sg:tags":[
        "steel",
        "stockholder"
    ],
    "wof:name":"Austin Trumanns Steel Ltd.",
    "wof:placetype":"venue"
},
  "geometry": {"coordinates":[-3.409335,55.940845],"type":"Point"}
}