{
  "type": "Feature",
  "properties": {
    "addr:full":"3 Charlotte St Cheadle Cheshire SK8 1DT",
    "addr:housenumber":"3",
    "addr:postcode":"sk8 1dt",
    "addr:street":"Charlotte St Cheadle",
    "iso:country":"GB",
    "sg:address":"3 Charlotte St",
    "sg:city":"Cheadle",
    "sg:classifiers":[
        {
            "category":"Building & Trades",
            "subcategory":"Construction",
            "type":"Services"
        }
    ],
    "sg:phone":"+44 161 491 3805",
    "sg:postcode":"SK8 1DT",
    "sg:province":"Cheshire",
    "sg:tags":[
        "builder"
    ],
    "wof:name":"The Alan Franks Group",
    "wof:placetype":"venue"
},
  "geometry": {"coordinates":[-2.215872,53.392204],"type":"Point"}
}