{
  "type": "Feature",
  "properties": {
    "addr:full":"Dotland Farm Hexham Northumberland NE46 2JY",
    "addr:housenumber":"hexham",
    "addr:postcode":"ne46 2jy",
    "addr:street":"Northumberland",
    "iso:country":"GB",
    "sg:address":"Dotland Farm",
    "sg:city":"Hexham",
    "sg:classifiers":[
        {
            "category":"Farming",
            "subcategory":"Livestock Farm",
            "type":"Manufacturing & Wholesale Goods"
        }
    ],
    "sg:postcode":"NE46 2JY",
    "sg:province":"Northumberland",
    "sg:tags":[
        "others"
    ],
    "wof:name":"T R Simpson",
    "wof:placetype":"venue"
},
  "geometry": {"coordinates":[-2.1012940407,54.970035553],"type":"Point"}
}