{
  "type": "Feature",
  "properties": {
    "addr:full":"8 Sycamore Road Amersham Buckinghamshire HP6 5DU",
    "addr:housenumber":"8",
    "addr:postcode":"hp6 5du",
    "addr:street":"Sycamore Road",
    "iso:country":"GB",
    "sg:address":"8 Sycamore Road",
    "sg:city":"Amersham",
    "sg:classifiers":[
        {
            "category":"Banks & Credit Unions",
            "subcategory":"Bank",
            "type":"Services"
        }
    ],
    "sg:phone":"+44 845 072 3333",
    "sg:postcode":"HP6 5DU",
    "sg:province":"Buckinghamshire",
    "sg:tags":[
        "financial",
        "institution"
    ],
    "sg:website":"http://www.lloydstsb.com",
    "wof:name":"Lloyds Tsb Bank Plc",
    "wof:placetype":"venue"
},
  "geometry": {"coordinates":[-0.6064479947,51.6774978638],"type":"Point"}
}