{
  "type": "Feature",
  "properties": {
    "iso:country":"GB",
    "sg:address":"6 Chartridge, Branston",
    "sg:city":"Lincoln",
    "sg:classifiers":[
        {
            "category":"Professional",
            "subcategory":"Management & Consulting",
            "type":"Services"
        },
        {
            "category":"Military Area",
            "subcategory":"Air Force Base",
            "type":"Public Place"
        }
    ],
    "sg:phone":"+44 1522 820022",
    "sg:postcode":"LN4 1UE",
    "sg:province":"Lincolnshire",
    "sg:tags":[
        "technician",
        "adviser",
        "safety",
        "consultant"
    ],
    "wof:name":"S A T Safety Ltd",
    "wof:placetype":"venue"
},
  "geometry": {"coordinates":[-0.456289,53.212509],"type":"Point"}
}