{
  "type": "Feature",
  "properties": {
    "iso:country":"GB",
    "sg:address":"45 Warham Road, Haringey",
    "sg:city":"London",
    "sg:classifiers":[
        {
            "category":"Professional",
            "type":"Services"
        }
    ],
    "sg:phone":"+44 20 8292 6592",
    "sg:postcode":"N4 1AR",
    "sg:province":"Greater London",
    "sg:tags":[
        "repair",
        "tech",
        "maintenance"
    ],
    "wof:name":"P C Focus Support Services",
    "wof:placetype":"venue"
},
  "geometry": {"coordinates":[-0.103609,51.580982],"type":"Point"}
}