{
  "type": "Feature",
  "properties": {
    "addr:full":"127 Groveley Rd Sunbury-on-thames Surrey TW16 7JZ",
    "addr:housenumber":"127",
    "addr:postcode":"tw16 7jz",
    "addr:street":"Groveley Rd",
    "iso:country":"GB",
    "sg:address":"127 Groveley Rd",
    "sg:city":"Sunbury-on-thames",
    "sg:classifiers":[
        {
            "category":"Communications",
            "type":"Services"
        }
    ],
    "sg:postcode":"TW16 7JZ",
    "sg:province":"Surrey",
    "sg:tags":[
        "telecommunication"
    ],
    "wof:name":"O'Malley,Dean,",
    "wof:placetype":"venue"
},
  "geometry": {"coordinates":[-0.421212,51.429359],"type":"Point"}
}