{
  "type": "Feature",
  "properties": {
    "addr:full":"23 Abbey Parade London Greater London SW19 1DG",
    "addr:housenumber":"23",
    "addr:postcode":"sw19 1dg",
    "addr:street":"Abbey Parade",
    "iso:country":"GB",
    "sg:address":"23 Abbey Parade",
    "sg:city":"London",
    "sg:classifiers":[
        {
            "category":"Shopping",
            "subcategory":"Bicycles & Sporting Goods",
            "type":"Retail Goods"
        }
    ],
    "sg:phone":"+44 20 8542 2534",
    "sg:postcode":"SW19 1DG",
    "sg:province":"Greater London",
    "sg:tags":[
        "cycle",
        "accessory"
    ],
    "wof:name":"A W Cycles",
    "wof:placetype":"venue"
},
  "geometry": {"coordinates":[-0.156153,51.426003],"type":"Point"}
}