{
  "type": "Feature",
  "properties": {
    "iso:country":"GB",
    "sg:address":"Stall 15 Crown Centre",
    "sg:city":"Stourbridge",
    "sg:classifiers":[
        {
            "category":"Food & Beverages",
            "subcategory":"Liquor & Beverages",
            "type":"Retail Goods"
        }
    ],
    "sg:postcode":"DY8 1YD",
    "sg:province":"Staffordshire",
    "sg:tags":[
        "beer",
        "spirit",
        "wines"
    ],
    "wof:name":"Brenda's Home Brew",
    "wof:placetype":"venue"
},
  "geometry": {"coordinates":[-2.1478540897,52.4539489746],"type":"Point"}
}