{
  "type": "Feature",
  "properties": {
    "addr:full":"Carwedd Fynydd, Llannefydd Denbigh Conwy LL16 5EH",
    "addr:postcode":"ll16 5eh",
    "addr:street":"Llannefydd",
    "iso:country":"GB",
    "sg:address":"Carwedd Fynydd, Llannefydd",
    "sg:city":"Denbigh",
    "sg:classifiers":[
        {
            "category":"Farming",
            "subcategory":"Farm",
            "type":"Manufacturing & Wholesale Goods"
        }
    ],
    "sg:phone":"+44 1745 540257",
    "sg:postcode":"LL16 5EH",
    "sg:province":"Conwy",
    "sg:tags":[
        "mixed",
        "crop"
    ],
    "wof:name":"D C Evans & Co.",
    "wof:placetype":"venue"
},
  "geometry": {"coordinates":[-3.526304,53.222984],"type":"Point"}
}