{
  "type": "Feature",
  "properties": {
    "addr:full":"Roydon Road Launceston Cornwall PL15 8HL",
    "addr:postcode":"pl15 8hl",
    "addr:street":"Roydon Road",
    "iso:country":"GB",
    "sg:address":"Roydon Road",
    "sg:city":"Launceston",
    "sg:classifiers":[
        {
            "category":"Education",
            "subcategory":"School",
            "type":"Public Place"
        }
    ],
    "sg:phone":"+44 1566 772170",
    "sg:postcode":"PL15 8HL",
    "sg:province":"Cornwall",
    "sg:tags":[
        "local",
        "authority"
    ],
    "wof:name":"St Stephens C P School",
    "wof:placetype":"venue"
},
  "geometry": {"coordinates":[-4.3654918671,50.6433067322],"type":"Point"}
}