{
  "type": "Feature",
  "properties": {
    "addr:full":"299 Muswell Hill Bdwy London Greater London N10 1DH",
    "addr:housenumber":"299",
    "addr:postcode":"n10 1dh",
    "addr:street":"Muswell Hill",
    "iso:country":"GB",
    "sg:address":"299 Muswell Hill Bdwy",
    "sg:city":"London",
    "sg:classifiers":[
        {
            "category":"Building & Trades",
            "subcategory":"Locksmith",
            "type":"Services"
        }
    ],
    "sg:phone":"+44 20 8444 7300",
    "sg:postcode":"N10 1DH",
    "sg:province":"Greater London",
    "sg:tags":[
        "cutting",
        "key"
    ],
    "wof:name":"Tony Andrews",
    "wof:placetype":"venue"
},
  "geometry": {"coordinates":[-0.1432269961,51.5920066833],"type":"Point"}
}