{
  "type": "Feature",
  "properties": {
    "iso:country":"GB",
    "sg:address":"352 Cricklewood Lane",
    "sg:city":"London",
    "sg:classifiers":[
        {
            "category":"Building & Trades",
            "subcategory":"Construction",
            "type":"Services"
        }
    ],
    "sg:phone":"+44 20 8949 2553",
    "sg:postcode":"NW2 2QH",
    "sg:province":"Greater London",
    "sg:tags":[
        "decorator",
        "painter"
    ],
    "wof:name":"M J Kloss",
    "wof:placetype":"venue"
},
  "geometry": {"coordinates":[-0.198706,51.562901],"type":"Point"}
}