{
  "type": "Feature",
  "properties": {
    "addr:full":"52 Virginia Street Glasgow Glasgow City G1 1TY",
    "addr:housenumber":"52",
    "addr:postcode":"g1 1ty",
    "addr:street":"Virginia Street",
    "iso:country":"GB",
    "sg:address":"52 Virginia Street",
    "sg:city":"Glasgow",
    "sg:classifiers":[
        {
            "category":"Travel",
            "subcategory":"Hotels & Motels",
            "type":"Entertainment"
        }
    ],
    "sg:phone":"+44 141 552 2424",
    "sg:postcode":"G1 1TY",
    "sg:province":"Glasgow City",
    "wof:name":"The Merchant Lodge",
    "wof:placetype":"venue"
},
  "geometry": {"coordinates":[-4.2498159409,55.8587799072],"type":"Point"}
}