{
  "type": "Feature",
  "properties": {
    "addr:full":"6a St Andrews Parade Weston-super-mare Somerset BS23 3SS",
    "addr:housenumber":"6a",
    "addr:postcode":"bs23 3ss",
    "addr:street":"St Andrews Parade",
    "iso:country":"GB",
    "sg:address":"6a St Andrews Parade",
    "sg:city":"Weston-super-mare",
    "sg:classifiers":[
        {
            "category":"Government",
            "subcategory":"Post Office",
            "type":"Public Place"
        }
    ],
    "sg:phone":"+44 1934 623428",
    "sg:postcode":"BS23 3SS",
    "sg:province":"Somerset",
    "wof:name":"Bournville Post Office",
    "wof:placetype":"venue"
},
  "geometry": {"coordinates":[-2.9656889439,51.3324508667],"type":"Point"}
}