{
  "type": "Feature",
  "properties": {
    "addr:full":"40 Northumberland Street Morecambe Lancashire LA4 4BA",
    "addr:housenumber":"40",
    "addr:postcode":"la4 4ba",
    "addr:street":"Northumberland Street",
    "iso:country":"GB",
    "sg:address":"40 Northumberland Street",
    "sg:city":"Morecambe",
    "sg:classifiers":[
        {
            "category":"Travel",
            "subcategory":"Hotels & Motels",
            "type":"Entertainment"
        }
    ],
    "sg:phone":"+44 1524 424623",
    "sg:postcode":"LA4 4BA",
    "sg:province":"Lancashire",
    "sg:tags":[
        "house",
        "guest"
    ],
    "wof:name":"Star Well Guest House",
    "wof:placetype":"venue"
},
  "geometry": {"coordinates":[-2.8697888851,54.0713615417],"type":"Point"}
}