{
  "type": "Feature",
  "properties": {
    "addr:full":"150b Falcon Rd Battersea Greater London SW11 2LW",
    "addr:housenumber":"150b",
    "addr:postcode":"sw11 2lw",
    "addr:street":"Falcon Rd",
    "iso:country":"GB",
    "sg:address":"150b Falcon Rd",
    "sg:city":"Battersea",
    "sg:classifiers":[
        {
            "category":"Building & Trades",
            "subcategory":"Cleaning & Sanitation",
            "type":"Services"
        }
    ],
    "sg:phone":"+44 20 7924 5330",
    "sg:postcode":"SW11 2LW",
    "sg:province":"Greater London",
    "sg:tags":[
        "asbestos",
        "removal"
    ],
    "wof:name":"Envirobond UK Ltd",
    "wof:placetype":"venue"
},
  "geometry": {"coordinates":[-0.168109,51.464138],"type":"Point"}
}