{
  "type": "Feature",
  "properties": {
    "addr:full":"3 Church Rd, Steep Petersfield Hampshire GU32 3DW",
    "addr:housenumber":"3",
    "addr:postcode":"gu32 3dw",
    "addr:street":"Church Rd",
    "iso:country":"GB",
    "sg:address":"3 Church Rd, Steep",
    "sg:city":"Petersfield",
    "sg:classifiers":[
        {
            "category":"Government",
            "subcategory":"Office",
            "type":"Public Place"
        }
    ],
    "sg:postcode":"GU32 3DW",
    "sg:province":"Hampshire",
    "sg:tags":[
        "central"
    ],
    "wof:name":"Malva",
    "wof:placetype":"venue"
},
  "geometry": {"coordinates":[-0.9358260036,51.0037956238],"type":"Point"}
}