{
  "type": "Feature",
  "properties": {
    "addr:full":"1 Crown Point Close Ossett West Yorkshire WF5 8RH",
    "addr:housenumber":"1",
    "addr:postcode":"wf5 8rh",
    "addr:street":"Crown Point Close",
    "iso:country":"GB",
    "sg:address":"1 Crown Point Close",
    "sg:city":"Ossett",
    "sg:classifiers":[
        {
            "category":"Professional",
            "type":"Services"
        }
    ],
    "sg:postcode":"WF5 8RH",
    "sg:province":"West Yorkshire",
    "sg:tags":[
        "caterer"
    ],
    "wof:name":"R & C Ltd.",
    "wof:placetype":"venue"
},
  "geometry": {"coordinates":[-1.589317,53.684563],"type":"Point"}
}