{
  "type": "Feature",
  "properties": {
    "addr:full":"Voluntary Forum Tweed St Berwick Upon Tweed Northumberland TD15 1NG",
    "addr:postcode":"td15 1ng",
    "addr:street":"Tweed St",
    "iso:country":"GB",
    "sg:address":"Voluntary Forum Tweed St",
    "sg:city":"Berwick Upon Tweed",
    "sg:classifiers":[
        {
            "category":"Organizations",
            "subcategory":"Non-profit Organization",
            "type":"Services"
        }
    ],
    "sg:phone":"+44 1289 306040",
    "sg:postcode":"TD15 1NG",
    "sg:province":"Northumberland",
    "sg:tags":[
        "organisation",
        "voluntary",
        "charity"
    ],
    "wof:name":"Alzheimers Disease Society",
    "wof:placetype":"venue"
},
  "geometry": {"coordinates":[-2.0070240498,55.7714347839],"type":"Point"}
}