{
  "type": "Feature",
  "properties": {
    "iso:country":"GB",
    "sg:address":"9 Geneva Road",
    "sg:city":"Darlington",
    "sg:classifiers":[
        {
            "category":"Shopping",
            "subcategory":"Pharmacy",
            "type":"Retail Goods"
        }
    ],
    "sg:phone":"+44 1325 250030",
    "sg:postcode":"DL1 4NE",
    "sg:province":"Durham",
    "sg:tags":[
        "pharmacist",
        "chemist"
    ],
    "wof:name":"Clarks Chemist",
    "wof:placetype":"venue"
},
  "geometry": {"coordinates":[-1.528376,54.522675],"type":"Point"}
}