{
  "type": "Feature",
  "properties": {
    "addr:full":"36 Earls Court Gardens London Greater London SW5 0TR",
    "addr:housenumber":"36",
    "addr:postcode":"sw5 0tr",
    "addr:street":"Earls Court Gardens",
    "iso:country":"GB",
    "sg:address":"36 Earls Court Gardens",
    "sg:city":"London",
    "sg:classifiers":[
        {
            "category":"Travel",
            "subcategory":"Hotels & Motels",
            "type":"Entertainment"
        }
    ],
    "sg:phone":"+44 20 7370 0798",
    "sg:postcode":"SW5 0TR",
    "sg:province":"Greater London",
    "wof:name":"Earls Court Gardens Hotel",
    "wof:placetype":"venue"
},
  "geometry": {"coordinates":[-0.191121,51.493351],"type":"Point"}
}