{
  "type": "Feature",
  "properties": {
    "addr:full":"22 Connaught Street London Greater London W2 2AF",
    "addr:housenumber":"22",
    "addr:postcode":"w2 2af",
    "addr:street":"Connaught Street",
    "iso:country":"GB",
    "sg:address":"22 Connaught Street",
    "sg:city":"London",
    "sg:classifiers":[
        {
            "category":"Building & Trades",
            "subcategory":"Construction",
            "type":"Services"
        }
    ],
    "sg:phone":"+44 20 7258 0433",
    "sg:postcode":"W2 2AF",
    "sg:province":"Greater London",
    "sg:tags":[
        "builder"
    ],
    "wof:name":"Hazletts",
    "wof:placetype":"venue"
},
  "geometry": {"coordinates":[-0.165633,51.51469],"type":"Point"}
}