{
  "type": "Feature",
  "properties": {
    "iso:country":"GB",
    "sg:address":"90 Oxford Street",
    "sg:city":"Wednesbury",
    "sg:classifiers":[
        {
            "category":"Shopping",
            "subcategory":"News",
            "type":"Retail Goods"
        }
    ],
    "sg:phone":"+44 121 556 8151",
    "sg:postcode":"WS10 0PY",
    "sg:province":"West Midlands",
    "sg:tags":[
        "newsagent"
    ],
    "wof:name":"Johal Supersave",
    "wof:placetype":"venue"
},
  "geometry": {"coordinates":[-2.005062,52.553139],"type":"Point"}
}