{
  "type": "Feature",
  "properties": {
    "iso:country":"GB",
    "sg:address":"Boundary House, 91-93 Charterhouse Street",
    "sg:city":"London",
    "sg:classifiers":[
        {
            "category":"Real Estate",
            "subcategory":"Real Estate Agent",
            "type":"Services"
        }
    ],
    "sg:phone":"+44 1621 893454",
    "sg:postcode":"EC1M 6PN",
    "sg:province":"Greater London",
    "wof:name":"Routebuy Ltd.",
    "wof:placetype":"venue"
},
  "geometry": {"coordinates":[-0.1014129966,51.5199394226],"type":"Point"}
}