{
  "type": "Feature",
  "properties": {
    "addr:full":"44 Meadowcroft Gdns, Westfield Sheffield South Yorkshire S20 8EL",
    "addr:housenumber":"44",
    "addr:postcode":"s20 8el",
    "addr:street":"Meadowcroft Gdns",
    "iso:country":"GB",
    "sg:address":"44 Meadowcroft Gdns, Westfield",
    "sg:city":"Sheffield",
    "sg:classifiers":[
        {
            "category":"Building & Trades",
            "subcategory":"Construction",
            "type":"Services"
        }
    ],
    "sg:postcode":"S20 8EL",
    "sg:province":"South Yorkshire",
    "sg:tags":[
        "dry",
        "lining",
        "plasterers",
        "screeders"
    ],
    "wof:name":"Havenhand,Richard,",
    "wof:placetype":"venue"
},
  "geometry": {"coordinates":[-1.3533129692,53.3319854736],"type":"Point"}
}