{
  "type": "Feature",
  "properties": {
    "addr:full":"354 Uxbridge Road Southall Greater London UB1 3DD",
    "addr:housenumber":"354",
    "addr:postcode":"ub1 3dd",
    "addr:street":"Uxbridge Road",
    "iso:country":"GB",
    "sg:address":"354 Uxbridge Road",
    "sg:city":"Southall",
    "sg:classifiers":[
        {
            "category":"Autos & Motor Vehicles",
            "subcategory":"Fuel & Gas Station",
            "type":"Retail Goods"
        }
    ],
    "sg:postcode":"UB1 3DD",
    "sg:province":"Greater London",
    "sg:tags":[
        "hr",
        "petrol"
    ],
    "wof:name":"Viaduct Self Service Station",
    "wof:placetype":"venue"
},
  "geometry": {"coordinates":[-0.346899,51.508919],"type":"Point"}
}