{
  "type": "Feature",
  "properties": {
    "iso:country":"GB",
    "sg:address":"Boundary Way, Lufton Trading Estate, Lufton",
    "sg:city":"Yeovil",
    "sg:classifiers":[
        {
            "category":"Building & Trades",
            "subcategory":"Construction",
            "type":"Services"
        }
    ],
    "sg:phone":"+44 1935 425232",
    "sg:postcode":"BA22 8HZ",
    "sg:province":"Dorset",
    "sg:tags":[
        "joinery"
    ],
    "wof:name":"Monk Woodworking Ltd.",
    "wof:placetype":"venue"
},
  "geometry": {"coordinates":[-2.676344,50.944393],"type":"Point"}
}