{
  "type": "Feature",
  "properties": {
    "addr:full":"163 Macaulay Rd Hartlepool Durham TS25 4NE",
    "addr:housenumber":"163",
    "addr:postcode":"ts25 4ne",
    "addr:street":"Macaulay Rd",
    "iso:country":"GB",
    "sg:address":"163 Macaulay Rd",
    "sg:city":"Hartlepool",
    "sg:classifiers":[
        {
            "category":"Professional",
            "subcategory":"Engineering",
            "type":"Services"
        }
    ],
    "sg:phone":"+44 1429 275473",
    "sg:postcode":"TS25 4NE",
    "sg:province":"Durham",
    "sg:tags":[
        "contractor",
        "electrical",
        "engineer"
    ],
    "wof:name":"Sunshine Electrical",
    "wof:placetype":"venue"
},
  "geometry": {"coordinates":[-1.2416549921,54.6690940857],"type":"Point"}
}