{
  "type": "Feature",
  "properties": {
    "addr:full":"78 High Street, Uppermill Oldham Lancashire OL3 6AW",
    "addr:housenumber":"78",
    "addr:postcode":"ol3 6aw",
    "addr:street":"High Street",
    "iso:country":"GB",
    "sg:address":"78 High Street, Uppermill",
    "sg:city":"Oldham",
    "sg:classifiers":[
        {
            "category":"Arts & Performance",
            "subcategory":"Art Gallery",
            "type":"Entertainment"
        },
        {
            "category":"Shopping",
            "subcategory":"Crafts & Fabrics",
            "type":"Retail Goods"
        }
    ],
    "sg:phone":"+44 1457 876923",
    "sg:postcode":"OL3 6AW",
    "sg:province":"Lancashire",
    "sg:tags":[
        "material",
        "sale",
        "supply"
    ],
    "wof:name":"Copy Right",
    "wof:placetype":"venue"
},
  "geometry": {"coordinates":[-2.005374,53.548485],"type":"Point"}
}