{
  "type": "Feature",
  "properties": {
    "iso:country":"GB",
    "sg:address":"57 Harlestones Road, Cottenham",
    "sg:city":"Cambridge",
    "sg:classifiers":[
        {
            "category":"Building & Trades",
            "subcategory":"Plumbing",
            "type":"Services"
        }
    ],
    "sg:phone":"+44 1954 251001",
    "sg:postcode":"CB4 8TR",
    "sg:province":"Cambridgeshire",
    "sg:tags":[
        "central",
        "heating"
    ],
    "wof:name":"City Heating Engineers",
    "wof:placetype":"venue"
},
  "geometry": {"coordinates":[0.1223,52.285221],"type":"Point"}
}