{
  "type": "Feature",
  "properties": {
    "iso:country":"GB",
    "sg:address":"Paignton Rd, Stoke Gabriel",
    "sg:city":"Totnes",
    "sg:classifiers":[
        {
            "category":"Manufacturing",
            "subcategory":"Pottery",
            "type":"Manufacturing & Wholesale Goods"
        }
    ],
    "sg:postcode":"TQ9 6SL",
    "sg:province":"Devon",
    "sg:tags":[
        "furnaces"
    ],
    "wof:name":"Skipwith,Michael Charles,",
    "wof:placetype":"venue"
},
  "geometry": {"coordinates":[-3.622959,50.407505],"type":"Point"}
}