{
  "type": "Feature",
  "properties": {
    "iso:country":"GB",
    "sg:address":"15 Kennoway Drive",
    "sg:city":"Glasgow",
    "sg:classifiers":[
        {
            "category":"Building & Trades",
            "subcategory":"Construction",
            "type":"Services"
        }
    ],
    "sg:postcode":"G11 7TU",
    "sg:province":"Glasgow City",
    "sg:tags":[
        "builder"
    ],
    "wof:name":"Machaffie Builders",
    "wof:placetype":"venue"
},
  "geometry": {"coordinates":[-4.319969,55.871441],"type":"Point"}
}