{
  "type": "Feature",
  "properties": {
    "addr:full":"89 Howletts Lane Ruislip Greater London HA4 7YG",
    "addr:housenumber":"89",
    "addr:postcode":"ha4 7yg",
    "addr:street":"Howletts Lane",
    "iso:country":"GB",
    "sg:address":"89 Howletts Lane",
    "sg:city":"Ruislip",
    "sg:classifiers":[
        {
            "category":"Food & Beverages",
            "subcategory":"Fruits & Vegetables",
            "type":"Retail Goods"
        }
    ],
    "sg:phone":"+44 1895 635535",
    "sg:postcode":"HA4 7YG",
    "sg:province":"Greater London",
    "sg:tags":[
        "greengrocer"
    ],
    "wof:name":"First Choice",
    "wof:placetype":"venue"
},
  "geometry": {"coordinates":[-0.440118,51.585037],"type":"Point"}
}