{
  "type": "Feature",
  "properties": {
    "addr:full":"Front Street Stanley Durham DH9 0NB",
    "addr:postcode":"dh9 0nb",
    "addr:street":"Front Street",
    "iso:country":"GB",
    "sg:address":"Front Street",
    "sg:city":"Stanley",
    "sg:classifiers":[
        {
            "category":"Food & Beverages",
            "subcategory":"Supermarket",
            "type":"Retail Goods"
        }
    ],
    "sg:phone":"+44 1207 235721",
    "sg:postcode":"DH9 0NB",
    "sg:province":"Durham",
    "wof:name":"Asda Stores Ltd.",
    "wof:placetype":"venue"
},
  "geometry": {"coordinates":[-1.696739,54.87207],"type":"Point"}
}