{
  "type": "Feature",
  "properties": {
    "addr:full":"Trews Field Industrial Estate, Tondu Road Bridgend Bridgend CF31 4JH",
    "addr:postcode":"cf31 4jh",
    "addr:street":"Estate Tondu Road",
    "iso:country":"GB",
    "sg:address":"Trews Field Industrial Estate, Tondu Road",
    "sg:city":"Bridgend",
    "sg:classifiers":[
        {
            "category":"Autos & Motor Vehicles",
            "subcategory":"Automobile Sales",
            "type":"Retail Goods"
        }
    ],
    "sg:phone":"+44 1656 659141",
    "sg:postcode":"CF31 4JH",
    "sg:province":"Bridgend",
    "sg:tags":[
        "car"
    ],
    "wof:name":"Tondu Road Motors Ltd.",
    "wof:placetype":"venue"
},
  "geometry": {"coordinates":[-3.578263,51.508835],"type":"Point"}
}