{
  "type": "Feature",
  "properties": {
    "addr:full":"12 Old Town Street Dawlish Devon EX7 9AW",
    "addr:housenumber":"12",
    "addr:postcode":"ex7 9aw",
    "addr:street":"Old Town Street",
    "iso:country":"GB",
    "sg:address":"12 Old Town Street",
    "sg:city":"Dawlish",
    "sg:classifiers":[
        {
            "category":"Food & Beverages",
            "subcategory":"Meat & Fish",
            "type":"Retail Goods"
        }
    ],
    "sg:phone":"+44 1626 863293",
    "sg:postcode":"EX7 9AW",
    "sg:province":"Devon",
    "sg:tags":[
        "butcher"
    ],
    "wof:name":"H G Thorp & Son",
    "wof:placetype":"venue"
},
  "geometry": {"coordinates":[-3.4751980305,50.5819778442],"type":"Point"}
}