{
  "type": "Feature",
  "properties": {
    "addr:full":"76 Fieldway Dagenham Essex RM8 2BD",
    "addr:housenumber":"76",
    "addr:postcode":"rm8 2bd",
    "addr:street":"Fieldway Dagenham",
    "iso:country":"GB",
    "sg:address":"76 Fieldway",
    "sg:city":"Dagenham",
    "sg:classifiers":[
        {
            "category":"Building & Trades",
            "subcategory":"Plumbing",
            "type":"Services"
        }
    ],
    "sg:phone":"+44 20 8597 6737",
    "sg:postcode":"RM8 2BD",
    "sg:province":"Essex",
    "sg:tags":[
        "central",
        "heating"
    ],
    "wof:name":"Avenue Plumbing & Heating",
    "wof:placetype":"venue"
},
  "geometry": {"coordinates":[0.1219210029,51.5531044006],"type":"Point"}
}