{
  "type": "Feature",
  "properties": {
    "iso:country":"GB",
    "sg:address":"121a Barnsley Road, Wombwell",
    "sg:city":"Barnsley",
    "sg:classifiers":[
        {
            "category":"Professional",
            "subcategory":"Business Services",
            "type":"Services"
        }
    ],
    "sg:phone":"+44 1226 754559",
    "sg:postcode":"S73 8HH",
    "sg:province":"South Yorkshire",
    "sg:tags":[
        "tile",
        "stockist"
    ],
    "wof:name":"Modern Ceramics",
    "wof:placetype":"venue"
},
  "geometry": {"coordinates":[-1.407862,53.527092],"type":"Point"}
}