{
  "type": "Feature",
  "properties": {
    "addr:full":"Greenbank Melton Mowbray Leicestershire LE13 1BB",
    "addr:postcode":"le13 1bb",
    "iso:country":"GB",
    "sg:address":"Greenbank",
    "sg:city":"Melton Mowbray",
    "sg:classifiers":[
        {
            "category":"Professional",
            "subcategory":"Business Services",
            "type":"Services"
        },
        {
            "category":"Retail",
            "subcategory":"Storage",
            "type":"Services"
        }
    ],
    "sg:phone":"+44 1664 410132",
    "sg:postcode":"LE13 1BB",
    "sg:province":"Leicestershire",
    "sg:tags":[
        "distribution",
        "activity",
        "domestic",
        "removal"
    ],
    "wof:name":"EXEL INVESTMENTS LTD",
    "wof:placetype":"venue"
},
  "geometry": {"coordinates":[-0.8895549774,52.7658691406],"type":"Point"}
}