{
  "type": "Feature",
  "properties": {
    "addr:full":"436 Foleshill Rd Coventry Warwickshire CV6 5JX",
    "addr:housenumber":"436",
    "addr:postcode":"cv6 5jx",
    "addr:street":"Foleshill Rd",
    "iso:country":"GB",
    "sg:address":"436 Foleshill Rd",
    "sg:city":"Coventry",
    "sg:classifiers":[
        {
            "category":"Autos & Motor Vehicles",
            "subcategory":"Automobile Sales",
            "type":"Retail Goods"
        }
    ],
    "sg:postcode":"CV6 5JX",
    "sg:province":"Warwickshire",
    "sg:tags":[
        "car"
    ],
    "wof:name":"Vehicle Wholesale Coventry",
    "wof:placetype":"venue"
},
  "geometry": {"coordinates":[-1.498034,52.429909],"type":"Point"}
}