{
  "type": "Feature",
  "properties": {
    "addr:full":"Gore Lane Farm Marlborough Berkshire SN8 2JX",
    "addr:postcode":"sn8 2jx",
    "addr:street":"Gore Lane",
    "iso:country":"GB",
    "sg:address":"Gore Lane Farm",
    "sg:city":"Marlborough",
    "sg:classifiers":[
        {
            "category":"Farming",
            "subcategory":"Dairy Farm",
            "type":"Manufacturing & Wholesale Goods"
        }
    ],
    "sg:postcode":"SN8 2JX",
    "sg:province":"Berkshire",
    "wof:name":"J D Wright & Son",
    "wof:placetype":"venue"
},
  "geometry": {"coordinates":[-1.6131379604,51.5171432495],"type":"Point"}
}