{
  "type": "Feature",
  "properties": {
    "iso:country":"GB",
    "sg:address":"7 Beauty Bank",
    "sg:city":"Cradley Heath",
    "sg:classifiers":[
        {
            "category":"Building & Trades",
            "subcategory":"Construction",
            "type":"Services"
        }
    ],
    "sg:phone":"+44 1384 567198",
    "sg:postcode":"B64 7HY",
    "sg:province":"West Midlands",
    "sg:tags":[
        "builder"
    ],
    "wof:name":"Arthur Williams & Son",
    "wof:placetype":"venue"
},
  "geometry": {"coordinates":[-2.058299,52.471203],"type":"Point"}
}