{
  "type": "Feature",
  "properties": {
    "iso:country":"GB",
    "sg:address":"36 Chapel Street, Cawston",
    "sg:city":"Norwich",
    "sg:classifiers":[
        {
            "category":"Food & Beverages",
            "subcategory":"Liquor & Beverages",
            "type":"Retail Goods"
        }
    ],
    "sg:phone":"+44 1603 871444",
    "sg:postcode":"NR10 4BQ",
    "sg:province":"Norfolk",
    "sg:tags":[
        "beer",
        "spirit",
        "wines"
    ],
    "wof:name":"Continental Wine Experts Ltd.",
    "wof:placetype":"venue"
},
  "geometry": {"coordinates":[1.1658689976,52.7736587524],"type":"Point"}
}