{
  "type": "Feature",
  "properties": {
    "addr:full":"23 Southfield Road Huddersfield West Yorkshire HD5 8RY",
    "addr:housenumber":"23",
    "addr:postcode":"hd5 8ry",
    "addr:street":"Southfield Road",
    "iso:country":"GB",
    "sg:address":"23 Southfield Road",
    "sg:city":"Huddersfield",
    "sg:classifiers":[
        {
            "category":"Shopping",
            "subcategory":"News",
            "type":"Retail Goods"
        },
        {
            "category":"Food & Beverages",
            "subcategory":"Groceries & Convenience Stores",
            "type":"Retail Goods"
        }
    ],
    "sg:phone":"+44 1484 421349",
    "sg:postcode":"HD5 8RY",
    "sg:province":"West Yorkshire",
    "sg:tags":[
        "newsagent"
    ],
    "wof:name":"Aujla's Minimarket",
    "wof:placetype":"venue"
},
  "geometry": {"coordinates":[-1.7480089664,53.6356391907],"type":"Point"}
}