{
  "type": "Feature",
  "properties": {
    "iso:country":"GB",
    "sg:address":"27 Hall Lane, Baguley",
    "sg:city":"Manchester",
    "sg:classifiers":[
        {
            "category":"Food & Beverages",
            "subcategory":"Bakery",
            "type":"Retail Goods"
        }
    ],
    "sg:phone":"+44 161 946 1171",
    "sg:postcode":"M23 1AQ",
    "sg:province":"Cheshire",
    "sg:tags":[
        "baker"
    ],
    "wof:name":"Alexander Allison",
    "wof:placetype":"venue"
},
  "geometry": {"coordinates":[-2.2771298885,53.399055481],"type":"Point"}
}