{
  "type": "Feature",
  "properties": {
    "addr:full":"Wickhurst Studios, Wickhurst Lane, Broadbridge Heath Horsham West Sussex RH12 3LA",
    "addr:postcode":"rh12 3la",
    "addr:street":"Wickhurst Lane",
    "iso:country":"GB",
    "sg:address":"Wickhurst Studios, Wickhurst Lane, Broadbridge Heath",
    "sg:city":"Horsham",
    "sg:classifiers":[
        {
            "category":"Professional",
            "type":"Services"
        },
        {
            "category":"Communications",
            "type":"Services"
        }
    ],
    "sg:phone":"+44 1403 211110",
    "sg:postcode":"RH12 3LA",
    "sg:province":"West Sussex",
    "sg:tags":[
        "exhibition",
        "audio-visual"
    ],
    "sg:website":"http://www.imageprojections.co.uk",
    "wof:name":"The Image Projections Co Ltd",
    "wof:placetype":"venue"
},
  "geometry": {"coordinates":[-0.36154899,51.0721244812],"type":"Point"}
}