{
  "type": "Feature",
  "properties": {
    "iso:country":"GB",
    "sg:address":"129 Bede Burn Road",
    "sg:city":"Jarrow",
    "sg:classifiers":[
        {
            "category":"Autos & Motor Vehicles",
            "subcategory":"Automobile Sales",
            "type":"Retail Goods"
        }
    ],
    "sg:phone":"+44 191 489 9100",
    "sg:postcode":"NE32 5AZ",
    "sg:province":"Tyne and Wear",
    "sg:tags":[
        "car"
    ],
    "wof:name":"Fleetstave Ltd.",
    "wof:placetype":"venue"
},
  "geometry": {"coordinates":[-1.4929280281,54.9731864929],"type":"Point"}
}