{
  "type": "Feature",
  "properties": {
    "iso:country":"GB",
    "sg:address":"173 Albert Road, Farnworth",
    "sg:city":"Bolton",
    "sg:classifiers":[
        {
            "category":"Building & Trades",
            "subcategory":"Construction",
            "type":"Services"
        }
    ],
    "sg:phone":"+44 1204 572136",
    "sg:postcode":"BL4 9HP",
    "sg:province":"Lancashire",
    "sg:tags":[
        "builder"
    ],
    "wof:name":"Mike Medcalf & Son Builders",
    "wof:placetype":"venue"
},
  "geometry": {"coordinates":[-2.399420023,53.5450019836],"type":"Point"}
}