{
  "type": "Feature",
  "properties": {
    "addr:full":"34 Cartmel Gardens Morden Surrey SM4 6QN",
    "addr:housenumber":"34",
    "addr:postcode":"sm4 6qn",
    "addr:street":"Cartmel Gardens",
    "iso:country":"GB",
    "sg:address":"34 Cartmel Gardens",
    "sg:city":"Morden",
    "sg:classifiers":[
        {
            "category":"Building & Trades",
            "subcategory":"Construction",
            "type":"Services"
        }
    ],
    "sg:phone":"+44 20 8255 1979",
    "sg:postcode":"SM4 6QN",
    "sg:province":"Surrey",
    "sg:tags":[
        "platform",
        "work",
        "scaffolding"
    ],
    "wof:name":"All Tight Scaffolding",
    "wof:placetype":"venue"
},
  "geometry": {"coordinates":[-0.188907,51.393505],"type":"Point"}
}