{
  "type": "Feature",
  "properties": {
    "addr:full":"20 Aylmer Parade, Aylmer Rd, East Finchley East Finchley Greater London N2 0PE",
    "addr:housenumber":"20",
    "addr:postcode":"n2 0pe",
    "addr:street":"Aylmer Parade Aylmer Rd",
    "iso:country":"GB",
    "sg:address":"20 Aylmer Parade, Aylmer Rd, East Finchley",
    "sg:city":"East Finchley",
    "sg:classifiers":[
        {
            "category":"Taxi",
            "type":"Transportation"
        }
    ],
    "sg:phone":"+44 20 8340 1616",
    "sg:postcode":"N2 0PE",
    "sg:province":"Greater London",
    "sg:tags":[
        "mini",
        "cab"
    ],
    "wof:name":"Muswell Hill Cars",
    "wof:placetype":"venue"
},
  "geometry": {"coordinates":[-0.1641799957,51.5827484131],"type":"Point"}
}