{
  "type": "Feature",
  "properties": {
    "addr:full":"27 Queen Street Neath Neath Port Talbot SA11 1DN",
    "addr:housenumber":"27",
    "addr:postcode":"sa11 1dn",
    "addr:street":"Queen Street",
    "iso:country":"GB",
    "sg:address":"27 Queen Street",
    "sg:city":"Neath",
    "sg:classifiers":[
        {
            "category":"Food & Beverages",
            "subcategory":"Bakery",
            "type":"Retail Goods"
        }
    ],
    "sg:phone":"+44 1639 643483",
    "sg:postcode":"SA11 1DN",
    "sg:province":"Neath Port Talbot",
    "sg:tags":[
        "baker"
    ],
    "wof:name":"Jenkins Bakery",
    "wof:placetype":"venue"
},
  "geometry": {"coordinates":[-3.804095,51.661953],"type":"Point"}
}