{
  "type": "Feature",
  "properties": {
    "addr:full":"5 Park Road Ramsgate Kent CT11 7QN",
    "addr:housenumber":"5",
    "addr:postcode":"ct11 7qn",
    "addr:street":"Park Road Ramsgate",
    "iso:country":"GB",
    "sg:address":"5 Park Road",
    "sg:city":"Ramsgate",
    "sg:classifiers":[
        {
            "category":"Building & Trades",
            "subcategory":"Landscaping Services",
            "type":"Services"
        }
    ],
    "sg:phone":"+44 1843 592458",
    "sg:postcode":"CT11 7QN",
    "sg:province":"Kent",
    "sg:tags":[
        "forestry",
        "surgeon",
        "tree"
    ],
    "wof:name":"Frank Hall",
    "wof:placetype":"venue"
},
  "geometry": {"coordinates":[1.4124610424,51.3385505676],"type":"Point"}
}