{
  "type": "Feature",
  "properties": {
    "iso:country":"GB",
    "sg:address":"Linnet Way",
    "sg:city":"Bedford",
    "sg:classifiers":[
        {
            "category":"Personal",
            "type":"Services"
        }
    ],
    "sg:phone":"+44 1234 261739",
    "sg:postcode":"MK41 7HN",
    "sg:province":"Bedfordshire",
    "sg:tags":[
        "wedding"
    ],
    "wof:name":"Classic Video Productions",
    "wof:placetype":"venue"
},
  "geometry": {"coordinates":[-0.463013,52.155094],"type":"Point"}
}