{
  "type": "Feature",
  "properties": {
    "iso:country":"GB",
    "sg:address":"Lisle Lane",
    "sg:city":"Ely",
    "sg:classifiers":[
        {
            "category":"Social Services",
            "subcategory":"Adult Care",
            "type":"Services"
        }
    ],
    "sg:phone":"+44 1353 669349",
    "sg:postcode":"CB7 4AS",
    "sg:province":"Cambridgeshire",
    "sg:tags":[
        "industrial"
    ],
    "wof:name":"Glowbug",
    "wof:placetype":"venue"
},
  "geometry": {"coordinates":[0.269571,52.397835],"type":"Point"}
}