{
  "type": "Feature",
  "properties": {
    "addr:full":"11 Whitfield Drive Ayr South Ayrshire KA8 9RX",
    "addr:housenumber":"11",
    "addr:postcode":"ka8 9rx",
    "addr:street":"Whitfield Drive",
    "iso:country":"GB",
    "sg:address":"11 Whitfield Drive",
    "sg:city":"Ayr",
    "sg:classifiers":[
        {
            "category":"Recreation",
            "subcategory":"Fishing",
            "type":"Entertainment"
        }
    ],
    "sg:phone":"+44 1292 611161",
    "sg:postcode":"KA8 9RX",
    "sg:province":"South Ayrshire",
    "sg:tags":[
        "angling"
    ],
    "wof:name":"Shetland Seafoods Ltd.",
    "wof:placetype":"venue"
},
  "geometry": {"coordinates":[-4.596645,55.47575],"type":"Point"}
}