{
  "type": "Feature",
  "properties": {
    "iso:country":"GB",
    "sg:address":"P O Box 86",
    "sg:city":"Romsey",
    "sg:classifiers":[
        {
            "category":"Organizations",
            "subcategory":"Non-profit Organization",
            "type":"Services"
        }
    ],
    "sg:phone":"+44 1794 515004",
    "sg:postcode":"SO51 8YD",
    "sg:province":"Hampshire",
    "sg:tags":[
        "organisation",
        "voluntary",
        "charity"
    ],
    "wof:name":"Oxford Mission",
    "wof:placetype":"venue"
},
  "geometry": {"coordinates":[-1.493759,50.990849],"type":"Point"}
}