{
  "type": "Feature",
  "properties": {
    "iso:country":"GB",
    "sg:address":"61 Oxford Road",
    "sg:city":"Abingdon",
    "sg:classifiers":[
        {
            "category":"Building & Trades",
            "subcategory":"Landscaping Services",
            "type":"Services"
        }
    ],
    "sg:phone":"+44 1235 520596",
    "sg:postcode":"OX14 2AA",
    "sg:province":"Oxfordshire",
    "sg:tags":[
        "gardening"
    ],
    "wof:name":"Lawn Wise",
    "wof:placetype":"venue"
},
  "geometry": {"coordinates":[-1.273728013,51.6809997559],"type":"Point"}
}