{
  "type": "Feature",
  "properties": {
    "addr:full":"The Maltings, Southmill Road Bishops Stortford Essex CM23 3DH",
    "addr:postcode":"cm23 3dh",
    "addr:street":"The;Southmill Road",
    "iso:country":"GB",
    "sg:address":"The Maltings, Southmill Road",
    "sg:city":"Bishops Stortford",
    "sg:classifiers":[
        {
            "category":"Airline",
            "type":"Transportation"
        },
        {
            "category":"Professional",
            "subcategory":"Employment Agencies",
            "type":"Services"
        }
    ],
    "sg:phone":"+44 1279 508644",
    "sg:postcode":"CM23 3DH",
    "sg:province":"Essex",
    "sg:tags":[
        "consultant",
        "airport"
    ],
    "wof:name":"I A P Aircraft Maintenance Ltd.",
    "wof:placetype":"venue"
},
  "geometry": {"coordinates":[0.161956,51.872356],"type":"Point"}
}