{
  "type": "Feature",
  "properties": {
    "iso:country":"GB",
    "sg:address":"47 Swanpool Street",
    "sg:city":"Falmouth",
    "sg:classifiers":[
        {
            "category":"Social Services",
            "subcategory":"Retirement Home",
            "type":"Services"
        }
    ],
    "sg:phone":"+44 1326 316055",
    "sg:postcode":"TR11 3HT",
    "sg:province":"Cornwall",
    "sg:tags":[
        "residential",
        "care"
    ],
    "wof:name":"Cherrybabes",
    "wof:placetype":"venue"
},
  "geometry": {"coordinates":[-5.066568,50.151131],"type":"Point"}
}