{
  "type": "Feature",
  "properties": {
    "addr:full":"Croxtons Mill, Blasford Hill Chelmsford Essex CM3 3PJ",
    "addr:postcode":"cm3 3pj",
    "addr:street":"Blasford Hill",
    "iso:country":"GB",
    "sg:address":"Croxtons Mill, Blasford Hill",
    "sg:city":"Chelmsford",
    "sg:classifiers":[
        {
            "category":"Banks & Credit Unions",
            "subcategory":"Bureau De Change",
            "type":"Services"
        }
    ],
    "sg:phone":"+44 1245 361611",
    "sg:postcode":"CM3 3PJ",
    "sg:province":"Essex",
    "sg:tags":[
        "town",
        "consultant",
        "planning"
    ],
    "wof:name":"Andrew Martin Associates",
    "wof:placetype":"venue"
},
  "geometry": {"coordinates":[0.4787999988,51.7766685486],"type":"Point"}
}