{
  "type": "Feature",
  "properties": {
    "addr:full":"8 Stanford Av Brighton East Sussex BN1 6AA",
    "addr:housenumber":"8",
    "addr:postcode":"bn1 6aa",
    "addr:street":"Stanford Av",
    "iso:country":"GB",
    "sg:address":"8 Stanford Av",
    "sg:city":"Brighton",
    "sg:classifiers":[
        {
            "category":"Professional",
            "subcategory":"Computer Services",
            "type":"Services"
        }
    ],
    "sg:phone":"+44 1273 331033",
    "sg:postcode":"BN1 6AA",
    "sg:province":"East Sussex",
    "sg:tags":[
        "system",
        "software"
    ],
    "wof:name":"Bright Solutions",
    "wof:placetype":"venue"
},
  "geometry": {"coordinates":[-0.1419949979,50.836894989],"type":"Point"}
}