{
  "type": "Feature",
  "properties": {
    "iso:country":"GB",
    "sg:address":"130a-130b High Street",
    "sg:city":"London",
    "sg:classifiers":[
        {
            "category":"Home & Garden",
            "subcategory":"Home Furnishings",
            "type":"Retail Goods"
        }
    ],
    "sg:postcode":"SE20 7EZ",
    "sg:province":"Greater London",
    "sg:tags":[
        "blind",
        "curtain",
        "fitting"
    ],
    "wof:name":"Bestwear Drapers",
    "wof:placetype":"venue"
},
  "geometry": {"coordinates":[-0.052715,51.414837],"type":"Point"}
}