{
  "type": "Feature",
  "properties": {
    "addr:full":"Repton Rd, Willington Derby Derbyshire DE65 6BX",
    "addr:postcode":"de65 6bx",
    "addr:street":"Repton Rd",
    "iso:country":"GB",
    "sg:address":"Repton Rd, Willington",
    "sg:city":"Derby",
    "sg:classifiers":[
        {
            "category":"Farming",
            "subcategory":"Farm",
            "type":"Manufacturing & Wholesale Goods"
        }
    ],
    "sg:postcode":"DE65 6BX",
    "sg:province":"Derbyshire",
    "sg:tags":[
        "mixed",
        "crop"
    ],
    "wof:name":"Wooddisse,R E,",
    "wof:placetype":"venue"
},
  "geometry": {"coordinates":[-1.552106,52.838692],"type":"Point"}
}