{
  "type": "Feature",
  "properties": {
    "addr:full":"39 Littlestone Rd, Littlestone New Romney Kent TN28 8LN",
    "addr:housenumber":"39",
    "addr:postcode":"tn28 8ln",
    "addr:street":"Littlestone Rd",
    "iso:country":"GB",
    "sg:address":"39 Littlestone Rd, Littlestone",
    "sg:city":"New Romney",
    "sg:classifiers":[
        {
            "category":"Personal",
            "subcategory":"Beauty Salon",
            "type":"Services"
        }
    ],
    "sg:postcode":"TN28 8LN",
    "sg:province":"Kent",
    "sg:tags":[
        "unisex",
        "hairdresser"
    ],
    "wof:name":"Lay,Vicki,",
    "wof:placetype":"venue"
},
  "geometry": {"coordinates":[0.956697,50.984329],"type":"Point"}
}