{
  "type": "Feature",
  "properties": {
    "addr:full":"57 Ullet Road Liverpool Merseyside L17 2AA",
    "addr:housenumber":"57",
    "addr:postcode":"l17 2aa",
    "addr:street":"Ullet Road",
    "iso:country":"GB",
    "sg:address":"57 Ullet Road",
    "sg:city":"Liverpool",
    "sg:classifiers":[
        {
            "category":"Place Of Worship",
            "type":"Public Place"
        },
        {
            "category":"Organizations",
            "subcategory":"Non-profit Organization",
            "type":"Services"
        }
    ],
    "sg:phone":"+44 151 733 1927",
    "sg:postcode":"L17 2AA",
    "sg:province":"Merseyside",
    "sg:tags":[
        "charitable",
        "organisation",
        "charity"
    ],
    "wof:name":"ULLET ROAD UNITARIAN CHURCH",
    "wof:placetype":"venue"
},
  "geometry": {"coordinates":[-2.937913,53.389664],"type":"Point"}
}