{
  "type": "Feature",
  "properties": {
    "addr:full":"Endeavour House London Greater London WC2H 8JG",
    "addr:postcode":"wc2h 8jg",
    "iso:country":"GB",
    "sg:address":"Endeavour House",
    "sg:city":"London",
    "sg:classifiers":[
        {
            "category":"Communications",
            "subcategory":"Newspaper",
            "type":"Services"
        }
    ],
    "sg:phone":"+44 20 7295 5000",
    "sg:postcode":"WC2H 8JG",
    "sg:province":"Greater London",
    "sg:tags":[
        "magazine"
    ],
    "wof:name":"E M A P London Lifestyle Ltd.",
    "wof:placetype":"venue"
},
  "geometry": {"coordinates":[-0.1269440055,51.5153198242],"type":"Point"}
}