{
  "type": "Feature",
  "properties": {
    "iso:country":"GB",
    "sg:address":"67-71 Castle Street",
    "sg:city":"Cirencester",
    "sg:classifiers":[
        {
            "category":"Real Estate",
            "subcategory":"Real Estate Agent",
            "type":"Services"
        }
    ],
    "sg:phone":"+44 1285 654535",
    "sg:postcode":"GL7 1QD",
    "sg:province":"Gloucestershire",
    "wof:name":"Hamptons International",
    "wof:placetype":"venue"
},
  "geometry": {"coordinates":[-1.971256,51.716015],"type":"Point"}
}