{
  "type": "Feature",
  "properties": {
    "addr:full":"Whitehill Lane, Oxford Road Aylesbury Buckinghamshire HP19 3EN",
    "addr:postcode":"hp19 3en",
    "addr:street":"Whitehill Lane Oxford Road",
    "iso:country":"GB",
    "sg:address":"Whitehill Lane, Oxford Road",
    "sg:city":"Aylesbury",
    "sg:classifiers":[
        {
            "category":"Health Services",
            "subcategory":"Doctor",
            "type":"Services"
        }
    ],
    "sg:phone":"+44 1296 432742",
    "sg:postcode":"HP19 3EN",
    "sg:province":"Buckinghamshire",
    "sg:tags":[
        "practitioners"
    ],
    "wof:name":"Whitehill Surgery",
    "wof:placetype":"venue"
},
  "geometry": {"coordinates":[-0.83167,51.826302],"type":"Point"}
}