{
  "type": "Feature",
  "properties": {
    "iso:country":"GB",
    "sg:address":"250 Whetley Lane",
    "sg:city":"Bradford",
    "sg:classifiers":[
        {
            "category":"Professional",
            "subcategory":"Business Services",
            "type":"Services"
        }
    ],
    "sg:phone":"+44 1274 482100",
    "sg:postcode":"BD8 9DJ",
    "sg:province":"West Yorkshire",
    "sg:tags":[
        "answering"
    ],
    "wof:name":"International Call Centre",
    "wof:placetype":"venue"
},
  "geometry": {"coordinates":[-1.776021,53.803505],"type":"Point"}
}