{
  "type": "Feature",
  "properties": {
    "addr:full":"Bruce Allen, 1st Floor, Chichester House, 45 Chichester Road Southend-on-sea Essex SS1 2JU",
    "addr:housenumber":"1st floor chichester;45",
    "addr:postcode":"ss1 2ju",
    "addr:street":"Bruce;Chichester Road",
    "iso:country":"GB",
    "sg:address":"Bruce Allen, 1st Floor, Chichester House, 45 Chichester Road",
    "sg:city":"Southend-on-sea",
    "sg:classifiers":[
        {
            "category":"Professional",
            "subcategory":"Computer Services",
            "type":"Services"
        }
    ],
    "sg:postcode":"SS1 2JU",
    "sg:province":"Essex",
    "sg:tags":[
        "system",
        "software"
    ],
    "wof:name":"Amershall Ltd",
    "wof:placetype":"venue"
},
  "geometry": {"coordinates":[0.70516,51.540386],"type":"Point"}
}