{
  "type": "Feature",
  "properties": {
    "addr:full":"Abbotsfield Road, Reginald Road Industrial Estate St Helens Cheshire WA9 4HU",
    "addr:postcode":"wa9 4hu",
    "addr:street":"Abbotsfield Road Reginald Road Industrial Estate",
    "iso:country":"GB",
    "sg:address":"Abbotsfield Road, Reginald Road Industrial Estate",
    "sg:city":"St Helens",
    "sg:classifiers":[
        {
            "category":"Manufacturing",
            "subcategory":"Metals",
            "type":"Manufacturing & Wholesale Goods"
        }
    ],
    "sg:phone":"+44 1744 810052",
    "sg:postcode":"WA9 4HU",
    "sg:province":"Cheshire",
    "sg:tags":[
        "steel",
        "stockholder"
    ],
    "wof:name":"West Lancashire Steel Services",
    "wof:placetype":"venue"
},
  "geometry": {"coordinates":[-2.7035529613,53.4272918701],"type":"Point"}
}