{
  "type": "Feature",
  "properties": {
    "iso:country":"GB",
    "sg:address":"Barclays Bank Chambers",
    "sg:city":"Birmingham",
    "sg:classifiers":[
        {
            "category":"Professional",
            "subcategory":"Accounting & Tax Preparation",
            "type":"Services"
        }
    ],
    "sg:phone":"+44 121 772 4040",
    "sg:postcode":"B11 4LD",
    "sg:province":"West Midlands",
    "sg:tags":[
        "accountant",
        "chartered"
    ],
    "wof:name":"C D G Computerised Accounts Ltd.",
    "wof:placetype":"venue"
},
  "geometry": {"coordinates":[-1.9086040258,52.4785957336],"type":"Point"}
}