{
  "type": "Feature",
  "properties": {
    "addr:full":"69 High Street, Westbury On Trym Bristol City of Bristol BS9 3ED",
    "addr:housenumber":"69",
    "addr:postcode":"bs9 3ed",
    "addr:street":"High Street",
    "iso:country":"GB",
    "sg:address":"69 High Street, Westbury On Trym",
    "sg:city":"Bristol",
    "sg:classifiers":[
        {
            "category":"Fast Food",
            "type":"Food & Drink"
        }
    ],
    "sg:phone":"+44 117 950 7007",
    "sg:postcode":"BS9 3ED",
    "sg:province":"City of Bristol",
    "sg:tags":[
        "away",
        "take"
    ],
    "wof:name":"Bamboo House",
    "wof:placetype":"venue"
},
  "geometry": {"coordinates":[-2.6181750298,51.4946937561],"type":"Point"}
}