{
  "type": "Feature",
  "properties": {
    "iso:country":"GB",
    "sg:address":"Dutch House, 307-308 High Holborn",
    "sg:city":"London",
    "sg:classifiers":[
        {
            "category":"Banks & Credit Unions",
            "subcategory":"Financial Services",
            "type":"Services"
        }
    ],
    "sg:postcode":"WC1V 7LL",
    "sg:province":"Greater London",
    "sg:tags":[
        "consultant"
    ],
    "wof:name":"Napier Blakeley Winter",
    "wof:placetype":"venue"
},
  "geometry": {"coordinates":[-0.239846,51.548859],"type":"Point"}
}