{
  "type": "Feature",
  "properties": {
    "addr:full":"St. Matthews Ho, Shepherdess Walk Islington Greater London N1 7BP",
    "addr:postcode":"n1 7bp",
    "addr:street":"Shepherdess Walk",
    "iso:country":"GB",
    "sg:address":"St. Matthews Ho, Shepherdess Walk",
    "sg:city":"Islington",
    "sg:classifiers":[
        {
            "category":"Utilities",
            "subcategory":"Telephone",
            "type":"Services"
        }
    ],
    "sg:phone":"+44 20 7320 3220",
    "sg:postcode":"N1 7BP",
    "sg:province":"Greater London",
    "sg:tags":[
        "telecommunication"
    ],
    "wof:name":"Connect Voice Messaging",
    "wof:placetype":"venue"
},
  "geometry": {"coordinates":[-0.0923700035,51.5294189453],"type":"Point"}
}