{
  "type": "Feature",
  "properties": {
    "iso:country":"GB",
    "sg:address":"9-11 Gladstone Road",
    "sg:city":"Scarborough",
    "sg:classifiers":[
        {
            "category":"Shopping",
            "subcategory":"Pharmacy",
            "type":"Retail Goods"
        }
    ],
    "sg:postcode":"YO12 7BQ",
    "sg:province":"North Yorkshire",
    "sg:tags":[
        "pharmacist",
        "chemist"
    ],
    "wof:name":"Thomas Graham Pharmacy",
    "wof:placetype":"venue"
},
  "geometry": {"coordinates":[-0.41053,54.28249],"type":"Point"}
}