{
  "type": "Feature",
  "properties": {
    "addr:full":"108 Boston Road London Greater London W7 2EP",
    "addr:housenumber":"108",
    "addr:postcode":"w7 2ep",
    "addr:street":"Boston Road",
    "iso:country":"GB",
    "sg:address":"108 Boston Road",
    "sg:city":"London",
    "sg:classifiers":[
        {
            "category":"Building & Trades",
            "subcategory":"Construction",
            "type":"Services"
        }
    ],
    "sg:phone":"+44 20 8567 6441",
    "sg:postcode":"W7 2EP",
    "sg:province":"Greater London",
    "sg:tags":[
        "roofing"
    ],
    "wof:name":"M & M Cuddihy Ltd.",
    "wof:placetype":"venue"
},
  "geometry": {"coordinates":[-0.334927,51.504749],"type":"Point"}
}