{
  "type": "Feature",
  "properties": {
    "iso:country":"GB",
    "sg:address":"35 The Cleaves, Cambuspark",
    "sg:city":"Alloa",
    "sg:classifiers":[
        {
            "category":"Building & Trades",
            "subcategory":"Construction",
            "type":"Services"
        }
    ],
    "sg:phone":"+44 1259 724555",
    "sg:postcode":"FK10 2XD",
    "sg:province":"Clackmannanshire",
    "sg:tags":[
        "tiling",
        "contractor"
    ],
    "wof:name":"Abg Ceramic Tiling",
    "wof:placetype":"venue"
},
  "geometry": {"coordinates":[-3.8388519287,56.1296882629],"type":"Point"}
}