{
  "type": "Feature",
  "properties": {
    "iso:country":"GB",
    "sg:address":"Unit 20 Rigby Close",
    "sg:city":"Warwick",
    "sg:classifiers":[
        {
            "category":"Professional",
            "type":"Services"
        }
    ],
    "sg:phone":"+44 1926 316718",
    "sg:postcode":"CV34 6TH",
    "sg:province":"Warwickshire",
    "sg:tags":[
        "caterer"
    ],
    "wof:name":"Cindy's Caterers",
    "wof:placetype":"venue"
},
  "geometry": {"coordinates":[-1.552013,52.272732],"type":"Point"}
}