{
  "type": "Feature",
  "properties": {
    "addr:full":"44 Grasmere Road Blackpool Lancashire FY1 5HT",
    "addr:housenumber":"44",
    "addr:postcode":"fy1 5ht",
    "addr:street":"Grasmere Road",
    "iso:country":"GB",
    "sg:address":"44 Grasmere Road",
    "sg:city":"Blackpool",
    "sg:classifiers":[
        {
            "category":"Shopping",
            "subcategory":"Computers & Home Electronics",
            "type":"Retail Goods"
        }
    ],
    "sg:postcode":"FY1 5HT",
    "sg:province":"Lancashire",
    "sg:tags":[
        "aerial",
        "television",
        "radio"
    ],
    "wof:name":"A Baird Aerials",
    "wof:placetype":"venue"
},
  "geometry": {"coordinates":[-3.0439479351,53.8085746765],"type":"Point"}
}