{
  "type": "Feature",
  "properties": {
    "iso:country":"GB",
    "sg:address":"Whitethorn Dr",
    "sg:city":"Bridgend",
    "sg:classifiers":[
        {
            "category":"Community Center",
            "type":"Public Place"
        }
    ],
    "sg:phone":"+44 1656 663400",
    "sg:postcode":"CF31 1NP",
    "sg:province":"Bridgend",
    "sg:tags":[
        "centre"
    ],
    "wof:name":"Brackla Community Centre",
    "wof:placetype":"venue"
},
  "geometry": {"coordinates":[-3.578263,51.508835],"type":"Point"}
}