{
  "type": "Feature",
  "properties": {
    "addr:full":"2 Bleeding Heart Yard London Greater London EC1N 8SJ",
    "addr:housenumber":"2",
    "addr:postcode":"ec1n 8sj",
    "addr:street":"Bleeding Heart Yard",
    "iso:country":"GB",
    "sg:address":"2 Bleeding Heart Yard",
    "sg:city":"London",
    "sg:classifiers":[
        {
            "category":"Professional",
            "subcategory":"Art Services",
            "type":"Services"
        }
    ],
    "sg:postcode":"EC1N 8SJ",
    "sg:province":"Greater London",
    "sg:tags":[
        "graphic",
        "designer"
    ],
    "wof:name":"Felton Communication Ltd.",
    "wof:placetype":"venue"
},
  "geometry": {"coordinates":[-0.106986,51.519238],"type":"Point"}
}