{
  "type": "Feature",
  "properties": {
    "iso:country":"GB",
    "sg:address":"Unit 16, Trident Industrial Estate, Blackthorne Road",
    "sg:city":"Slough",
    "sg:classifiers":[
        {
            "category":"Freight",
            "type":"Transportation"
        }
    ],
    "sg:phone":"+44 1753 680680",
    "sg:postcode":"SL3 0AX",
    "sg:province":"Berkshire",
    "sg:tags":[
        "forwarders"
    ],
    "wof:name":"Fred Olsen Airfreight Ltd.",
    "wof:placetype":"venue"
},
  "geometry": {"coordinates":[-0.5128600001,51.4740104675],"type":"Point"}
}