{
  "type": "Feature",
  "properties": {
    "addr:full":"Gilbert House, Foundry Lane Newcastle-upon-tyne Tyne and Wear NE6 1LH",
    "addr:postcode":"ne6 1lh",
    "addr:street":"Foundry Lane",
    "iso:country":"GB",
    "sg:address":"Gilbert House, Foundry Lane",
    "sg:city":"Newcastle-upon-tyne",
    "sg:classifiers":[
        {
            "category":"Professional",
            "subcategory":"Printing & Photocopies",
            "type":"Services"
        }
    ],
    "sg:phone":"+44 191 276 5027",
    "sg:postcode":"NE6 1LH",
    "sg:province":"Tyne and Wear",
    "sg:tags":[
        "printer"
    ],
    "wof:name":"Gilbert Print & Design Ltd.",
    "wof:placetype":"venue"
},
  "geometry": {"coordinates":[-1.5908030272,54.9755554199],"type":"Point"}
}