{
  "type": "Feature",
  "properties": {
    "iso:country":"GB",
    "sg:address":"6 Prentice Place",
    "sg:city":"Harlow",
    "sg:classifiers":[
        {
            "category":"Fast Food",
            "type":"Food & Drink"
        }
    ],
    "sg:phone":"+44 1279 866246",
    "sg:postcode":"CM17 9BQ",
    "sg:province":"Essex",
    "sg:tags":[
        "away",
        "take"
    ],
    "wof:name":"Fish'n Chick'n Ltd.",
    "wof:placetype":"venue"
},
  "geometry": {"coordinates":[0.132645,51.758015],"type":"Point"}
}