{
  "type": "Feature",
  "properties": {
    "addr:full":"Victoria Pk Selkirk Scottish Borders TD7 5DN",
    "addr:postcode":"td7 5dn",
    "addr:street":"Victoria Pk Selkirk",
    "iso:country":"GB",
    "sg:address":"Victoria Pk",
    "sg:city":"Selkirk",
    "sg:classifiers":[
        {
            "category":"Community Center",
            "type":"Public Place"
        },
        {
            "category":"Government",
            "subcategory":"Office",
            "type":"Public Place"
        }
    ],
    "sg:phone":"+44 1750 20897",
    "sg:postcode":"TD7 5DN",
    "sg:province":"Scottish Borders",
    "sg:tags":[
        "recreation",
        "local",
        "leisure",
        "centre"
    ],
    "wof:name":"Borders Regional Council",
    "wof:placetype":"venue"
},
  "geometry": {"coordinates":[-2.8431639671,55.549495697],"type":"Point"}
}