{
  "type": "Feature",
  "properties": {
    "iso:country":"GB",
    "sg:address":"Bottoms Fold, Mossley",
    "sg:city":"Ashton-under-lyne",
    "sg:classifiers":[
        {
            "category":"Banks & Credit Unions",
            "subcategory":"Bank",
            "type":"Services"
        },
        {
            "category":"Professional",
            "subcategory":"Business Services",
            "type":"Services"
        }
    ],
    "sg:phone":"+44 1457 837747",
    "sg:postcode":"OL5 9NH",
    "sg:province":"Greater Manchester",
    "sg:tags":[
        "stocktaking",
        "inventory"
    ],
    "wof:name":"D J Dormer & Son",
    "wof:placetype":"venue"
},
  "geometry": {"coordinates":[-2.04125,53.517082],"type":"Point"}
}