{
  "type": "Feature",
  "properties": {
    "iso:country":"GB",
    "sg:address":"Ashton",
    "sg:city":"Wedmore",
    "sg:classifiers":[
        {
            "category":"Community Center",
            "type":"Public Place"
        }
    ],
    "sg:postcode":"BS28 4QF",
    "sg:province":"Somerset",
    "sg:tags":[
        "recreation",
        "leisure",
        "centre"
    ],
    "wof:name":"Monkeys Childrens Adventure Play Centre",
    "wof:placetype":"venue"
},
  "geometry": {"coordinates":[-2.81016,51.227631],"type":"Point"}
}