{
  "type": "Feature",
  "properties": {
    "addr:full":"25 Eastcheap Letchworth Hertfordshire SG6 3DA",
    "addr:housenumber":"25",
    "addr:postcode":"sg6 3da",
    "addr:street":"Eastcheap Letchworth",
    "iso:country":"GB",
    "sg:address":"25 Eastcheap",
    "sg:city":"Letchworth",
    "sg:classifiers":[
        {
            "category":"Retail",
            "subcategory":"Laundry & Dry Cleaning",
            "type":"Services"
        }
    ],
    "sg:phone":"+44 1462 682571",
    "sg:postcode":"SG6 3DA",
    "sg:province":"Hertfordshire",
    "sg:tags":[
        "alteration"
    ],
    "wof:name":"Professional Dry Cleaners",
    "wof:placetype":"venue"
},
  "geometry": {"coordinates":[-0.2287410051,51.9780921936],"type":"Point"}
}