{
  "type": "Feature",
  "properties": {
    "iso:country":"GB",
    "sg:address":"62 Ham Road",
    "sg:city":"Worthing",
    "sg:classifiers":[
        {
            "category":"Food & Beverages",
            "subcategory":"Meat & Fish",
            "type":"Retail Goods"
        }
    ],
    "sg:phone":"+44 1903 201350",
    "sg:postcode":"BN11 2QY",
    "sg:province":"West Sussex",
    "sg:tags":[
        "chip"
    ],
    "wof:name":"Christoforos Fish Bar",
    "wof:placetype":"venue"
},
  "geometry": {"coordinates":[-0.351494,50.815666],"type":"Point"}
}