{
  "type": "Feature",
  "properties": {
    "iso:country":"GB",
    "sg:address":"Hawksclough Garage, Mytholmroyd",
    "sg:city":"Hebden Bridge",
    "sg:classifiers":[
        {
            "category":"Retail",
            "subcategory":"Auto Repair",
            "type":"Services"
        }
    ],
    "sg:postcode":"HX7 5AD",
    "sg:province":"West Yorkshire",
    "sg:tags":[
        "body",
        "car"
    ],
    "wof:name":"Paul Libotte",
    "wof:placetype":"venue"
},
  "geometry": {"coordinates":[-1.981635,53.730579],"type":"Point"}
}