{
  "type": "Feature",
  "properties": {
    "addr:full":"9-11 Central Drive, Rawmarsh Rotherham South Yorkshire S62 7NG",
    "addr:housenumber":"9-11",
    "addr:postcode":"s62 7ng",
    "addr:street":"Central Drive",
    "iso:country":"GB",
    "sg:address":"9-11 Central Drive, Rawmarsh",
    "sg:city":"Rotherham",
    "sg:classifiers":[
        {
            "category":"Shopping",
            "subcategory":"Department Store",
            "type":"Retail Goods"
        }
    ],
    "sg:postcode":"S62 7NG",
    "sg:province":"South Yorkshire",
    "wof:name":"Manor Farm Stores",
    "wof:placetype":"venue"
},
  "geometry": {"coordinates":[-1.3619459867,53.4731788635],"type":"Point"}
}