{
  "type": "Feature",
  "properties": {
    "addr:full":"Telegraph Hill Exeter Devon EX6 7XP",
    "addr:postcode":"ex6 7xp",
    "addr:street":"Telegraph Hill",
    "iso:country":"GB",
    "sg:address":"Telegraph Hill",
    "sg:city":"Exeter",
    "sg:classifiers":[
        {
            "category":"Autos & Motor Vehicles",
            "subcategory":"Fuel & Gas Station",
            "type":"Retail Goods"
        }
    ],
    "sg:phone":"+44 1392 832894",
    "sg:postcode":"EX6 7XP",
    "sg:province":"Devon",
    "sg:tags":[
        "petrol",
        "filling"
    ],
    "wof:name":"Telgraph Hill Service Station",
    "wof:placetype":"venue"
},
  "geometry": {"coordinates":[-3.540753,50.643215],"type":"Point"}
}