{
  "type": "Feature",
  "properties": {
    "addr:full":"65 Fillebrook Road, Leytonstone London Greater London E11 4AU",
    "addr:housenumber":"65",
    "addr:postcode":"e11 4au",
    "addr:street":"Fillebrook Road",
    "iso:country":"GB",
    "sg:address":"65 Fillebrook Road, Leytonstone",
    "sg:city":"London",
    "sg:classifiers":[
        {
            "category":"Personal",
            "subcategory":"Shoe Repair & Shine",
            "type":"Services"
        }
    ],
    "sg:phone":"+44 1992 572252",
    "sg:postcode":"E11 4AU",
    "sg:province":"Greater London",
    "sg:tags":[
        "chandelier"
    ],
    "wof:name":"Lyndon's Chandelier Services Ltd.",
    "wof:placetype":"venue"
},
  "geometry": {"coordinates":[0.0061420002,51.5676345825],"type":"Point"}
}