{
  "type": "Feature",
  "properties": {
    "addr:full":"Ground Floor Gordon House, Leicester Street Southport Lancashire PR9 0ER",
    "addr:housenumber":"ground floor gordon house",
    "addr:postcode":"pr9 0er",
    "addr:street":"Leicester Street",
    "iso:country":"GB",
    "sg:address":"Ground Floor Gordon House, Leicester Street",
    "sg:city":"Southport",
    "sg:classifiers":[
        {
            "category":"Banks & Credit Unions",
            "subcategory":"Financial Services",
            "type":"Services"
        }
    ],
    "sg:phone":"+44 1704 543913",
    "sg:postcode":"PR9 0ER",
    "sg:province":"Lancashire",
    "sg:tags":[
        "consultant"
    ],
    "wof:name":"Allied Dunbar Assurance Plc",
    "wof:placetype":"venue"
},
  "geometry": {"coordinates":[-3.002249,53.654606],"type":"Point"}
}