{
  "type": "Feature",
  "properties": {
    "addr:full":"10 Gurney Street, New Marske Redcar North Yorkshire TS11 8EG",
    "addr:housenumber":"10",
    "addr:postcode":"ts11 8eg",
    "addr:street":"Gurney Street",
    "iso:country":"GB",
    "sg:address":"10 Gurney Street, New Marske",
    "sg:city":"Redcar",
    "sg:classifiers":[
        {
            "category":"Food & Beverages",
            "subcategory":"Groceries & Convenience Stores",
            "type":"Retail Goods"
        }
    ],
    "sg:phone":"+44 1642 484720",
    "sg:postcode":"TS11 8EG",
    "sg:province":"North Yorkshire",
    "wof:name":"Bells Stores",
    "wof:placetype":"venue"
},
  "geometry": {"coordinates":[-1.0390930176,54.5824928284],"type":"Point"}
}