{
  "type": "Feature",
  "properties": {
    "iso:country":"GB",
    "sg:address":"Marchants Bambles Grn, Terling",
    "sg:city":"Chelmsford",
    "sg:classifiers":[
        {
            "category":"Real Estate",
            "subcategory":"Architect",
            "type":"Services"
        }
    ],
    "sg:postcode":"CM3 2QP",
    "sg:province":"Essex",
    "sg:tags":[
        "architectural"
    ],
    "wof:name":"Roger Ludlow",
    "wof:placetype":"venue"
},
  "geometry": {"coordinates":[0.5670899749,51.806137085],"type":"Point"}
}