{
  "type": "Feature",
  "properties": {
    "iso:country":"GB",
    "sg:address":"Cattermole Buildings, Market Place, Codnor",
    "sg:city":"Ripley",
    "sg:classifiers":[
        {
            "category":"Mining & Drilling",
            "type":"Manufacturing & Wholesale Goods"
        }
    ],
    "sg:phone":"+44 1773 570596",
    "sg:postcode":"DE5 9QA",
    "sg:province":"Derbyshire",
    "sg:tags":[
        "coal"
    ],
    "wof:name":"H C M Electrical Ltd.",
    "wof:placetype":"venue"
},
  "geometry": {"coordinates":[-1.375829,53.044216],"type":"Point"}
}