{
  "type": "Feature",
  "properties": {
    "iso:country":"GB",
    "sg:address":"Taylor House, Brandlesholme Road",
    "sg:city":"Bury",
    "sg:classifiers":[
        {
            "category":"Government",
            "subcategory":"Office",
            "type":"Public Place"
        }
    ],
    "sg:postcode":"BL8 1HS",
    "sg:province":"Lancashire",
    "sg:tags":[
        "local"
    ],
    "wof:name":"Care-Link Community Alarm Service",
    "wof:placetype":"venue"
},
  "geometry": {"coordinates":[-2.318917,53.612999],"type":"Point"}
}