{
  "type": "Feature",
  "properties": {
    "iso:country":"GB",
    "sg:address":"4 Station Road, Ushaw Moor",
    "sg:city":"Durham",
    "sg:classifiers":[
        {
            "category":"Food & Beverages",
            "subcategory":"Fruits & Vegetables",
            "type":"Retail Goods"
        }
    ],
    "sg:postcode":"DH7 7PX",
    "sg:province":"Durham",
    "sg:tags":[
        "greengrocer"
    ],
    "wof:name":"Robert Bodinner",
    "wof:placetype":"venue"
},
  "geometry": {"coordinates":[-1.645812,54.777779],"type":"Point"}
}