{
  "type": "Feature",
  "properties": {
    "addr:full":"North Road Cardiff Cardiff CF14 3AE",
    "addr:postcode":"cf14 3ae",
    "addr:street":"North Road",
    "iso:country":"GB",
    "sg:address":"North Road",
    "sg:city":"Cardiff",
    "sg:classifiers":[
        {
            "category":"Autos & Motor Vehicles",
            "subcategory":"Fuel & Gas Station",
            "type":"Retail Goods"
        }
    ],
    "sg:phone":"+44 29 2061 8875",
    "sg:postcode":"CF14 3AE",
    "sg:province":"Cardiff",
    "sg:tags":[
        "petrol",
        "filling"
    ],
    "wof:name":"WEIGHBRIDGE GENERAL SERVICE STATION",
    "wof:placetype":"venue"
},
  "geometry": {"coordinates":[-3.199379,51.506142],"type":"Point"}
}