{
  "type": "Feature",
  "properties": {
    "iso:country":"GB",
    "sg:address":"114 Islingword Road",
    "sg:city":"Brighton",
    "sg:classifiers":[
        {
            "category":"Manufacturing",
            "subcategory":"Motor Vehicles & Parts",
            "type":"Manufacturing & Wholesale Goods"
        },
        {
            "category":"Autos & Motor Vehicles",
            "subcategory":"Auto Supplies",
            "type":"Retail Goods"
        }
    ],
    "sg:phone":"+44 1273 685925",
    "sg:postcode":"BN2 9SG",
    "sg:province":"East Sussex",
    "sg:tags":[
        "electric",
        "servicing",
        "sales"
    ],
    "sg:website":"http://www.electricmotorrewinds.co.uk",
    "wof:name":"Electric Motor Rewinds",
    "wof:placetype":"venue"
},
  "geometry": {"coordinates":[-0.126713,50.830326],"type":"Point"}
}