{
  "type": "Feature",
  "properties": {
    "addr:full":"21-23 Murray Rd Northwood Greater London HA6 2YP",
    "addr:housenumber":"21-23",
    "addr:postcode":"ha6 2yp",
    "addr:street":"Murray Rd",
    "iso:country":"GB",
    "sg:address":"21-23 Murray Rd",
    "sg:city":"Northwood",
    "sg:classifiers":[
        {
            "category":"Place Of Worship",
            "type":"Public Place"
        }
    ],
    "sg:phone":"+44 1923 820004",
    "sg:postcode":"HA6 2YP",
    "sg:province":"Greater London",
    "wof:name":"Northwood United Synagogue",
    "wof:placetype":"venue"
},
  "geometry": {"coordinates":[-0.4246740043,51.610042572],"type":"Point"}
}