{
  "type": "Feature",
  "properties": {
    "iso:country":"GB",
    "sg:address":"43 Grylls Park",
    "sg:city":"Looe",
    "sg:classifiers":[
        {
            "category":"Home & Garden",
            "subcategory":"Kitchen Supply",
            "type":"Retail Goods"
        }
    ],
    "sg:phone":"+44 1983 884455",
    "sg:postcode":"PL13 2NG",
    "sg:province":"Cornwall",
    "sg:tags":[
        "equipment",
        "catering"
    ],
    "wof:name":"Oyster Catering Equipment Ltd.",
    "wof:placetype":"venue"
},
  "geometry": {"coordinates":[-4.562642,50.38369],"type":"Point"}
}