{
  "type": "Feature",
  "properties": {
    "addr:full":"37 Barkston Close Billingham Durham TS22 5EY",
    "addr:housenumber":"37",
    "addr:postcode":"ts22 5ey",
    "addr:street":"Barkston Close",
    "iso:country":"GB",
    "sg:address":"37 Barkston Close",
    "sg:city":"Billingham",
    "sg:classifiers":[
        {
            "category":"Home & Garden",
            "subcategory":"Carpets & Floor Coverings",
            "type":"Retail Goods"
        }
    ],
    "sg:phone":"+44 1642 872078",
    "sg:postcode":"TS22 5EY",
    "sg:province":"Durham",
    "sg:tags":[
        "carpets",
        "rug",
        "matting"
    ],
    "wof:name":"Steve's Carpet Fitting",
    "wof:placetype":"venue"
},
  "geometry": {"coordinates":[-1.304947,54.616562],"type":"Point"}
}