{
  "type": "Feature",
  "properties": {
    "addr:full":"Abbey House 51 High Street Saffron Walden Cambridgeshire CB10 1AR",
    "addr:housenumber":"51",
    "addr:postcode":"cb10 1ar",
    "addr:street":"High Street",
    "iso:country":"GB",
    "sg:address":"Abbey House 51 High Street",
    "sg:city":"Saffron Walden",
    "sg:classifiers":[
        {
            "category":"Building & Trades",
            "subcategory":"Electrical",
            "type":"Services"
        }
    ],
    "sg:postcode":"CB10 1AR",
    "sg:province":"Cambridgeshire",
    "sg:tags":[
        "consultant",
        "lighting"
    ],
    "wof:name":"Country Lights",
    "wof:placetype":"venue"
},
  "geometry": {"coordinates":[0.2389670014,52.0223388672],"type":"Point"}
}