{
  "type": "Feature",
  "properties": {
    "addr:full":"11 Bramble Way Rugeley Staffordshire WS15 2SP",
    "addr:housenumber":"11",
    "addr:postcode":"ws15 2sp",
    "addr:street":"Bramble Way",
    "iso:country":"GB",
    "sg:address":"11 Bramble Way",
    "sg:city":"Rugeley",
    "sg:classifiers":[
        {
            "category":"Retail",
            "subcategory":"Driving School",
            "type":"Services"
        }
    ],
    "sg:postcode":"WS15 2SP",
    "sg:province":"Staffordshire",
    "wof:name":"Driveway School of Motoring",
    "wof:placetype":"venue"
},
  "geometry": {"coordinates":[-1.9515160322,52.7607688904],"type":"Point"}
}