{
  "type": "Feature",
  "properties": {
    "iso:country":"GB",
    "sg:address":"Unit 7, 82-86 Cambridge Road",
    "sg:city":"Stansted",
    "sg:classifiers":[
        {
            "category":"Government",
            "subcategory":"Fire Station",
            "type":"Public Place"
        }
    ],
    "sg:phone":"+44 1279 816780",
    "sg:postcode":"CM24 8DB",
    "sg:province":"Essex",
    "sg:tags":[
        "security"
    ],
    "wof:name":"Home & Office Fire Extinguishers Ltd.",
    "wof:placetype":"venue"
},
  "geometry": {"coordinates":[0.197869,51.90799],"type":"Point"}
}