{
  "type": "Feature",
  "properties": {
    "iso:country":"GB",
    "sg:address":"Filliams Farm, Plaistow Rd",
    "sg:city":"Billingshurst",
    "sg:classifiers":[
        {
            "category":"Home & Garden",
            "subcategory":"Garden Supply",
            "type":"Retail Goods"
        }
    ],
    "sg:phone":"+44 1403 820237",
    "sg:postcode":"RH14 0JR",
    "sg:province":"West Sussex",
    "sg:tags":[
        "nursery",
        "centre"
    ],
    "wof:name":"R E Vallens",
    "wof:placetype":"venue"
},
  "geometry": {"coordinates":[-0.5633980036,51.0682945251],"type":"Point"}
}