{
  "type": "Feature",
  "properties": {
    "iso:country":"GB",
    "sg:address":"29 Lockway",
    "sg:city":"Abingdon",
    "sg:classifiers":[
        {
            "category":"Building & Trades",
            "subcategory":"Construction",
            "type":"Services"
        }
    ],
    "sg:phone":"+44 1235 531354",
    "sg:postcode":"OX14 4LF",
    "sg:province":"Oxfordshire",
    "sg:tags":[
        "decorator",
        "painter"
    ],
    "wof:name":"D & D J Fincham",
    "wof:placetype":"venue"
},
  "geometry": {"coordinates":[-1.315625,51.641953],"type":"Point"}
}