{
  "type": "Feature",
  "properties": {
    "iso:country":"GB",
    "sg:address":"Leicester Road, Billesdon",
    "sg:city":"Leicester",
    "sg:classifiers":[
        {
            "category":"Farming",
            "subcategory":"Livestock Farm",
            "type":"Manufacturing & Wholesale Goods"
        }
    ],
    "sg:phone":"+44 116 259 6320",
    "sg:postcode":"LE7 9FD",
    "sg:province":"Leicestershire",
    "sg:tags":[
        "others"
    ],
    "wof:name":"Fiona D Miles",
    "wof:placetype":"venue"
},
  "geometry": {"coordinates":[-0.911449,52.642647],"type":"Point"}
}