{
  "type": "Feature",
  "properties": {
    "addr:full":"339 Oxford Street London Greater London W1C 2JE",
    "addr:housenumber":"339",
    "addr:postcode":"w1c 2je",
    "addr:street":"Oxford Street",
    "iso:country":"GB",
    "sg:address":"339 Oxford Street",
    "sg:city":"London",
    "sg:classifiers":[
        {
            "category":"Banks & Credit Unions",
            "subcategory":"Bureau De Change",
            "type":"Services"
        }
    ],
    "sg:phone":"+44 20 7491 7226",
    "sg:postcode":"W1C 2JE",
    "sg:province":"Greater London",
    "wof:name":"Exchange International",
    "wof:placetype":"venue"
},
  "geometry": {"coordinates":[-0.147517994,51.5144844055],"type":"Point"}
}