{
  "type": "Feature",
  "properties": {
    "iso:country":"GB",
    "sg:address":"23 Harbour Quay",
    "sg:city":"Wick",
    "sg:classifiers":[
        {
            "category":"Organizations",
            "subcategory":"Non-profit Organization",
            "type":"Services"
        }
    ],
    "sg:phone":"+44 1955 606682",
    "sg:postcode":"KW1 5EP",
    "sg:province":"Highland",
    "sg:tags":[
        "organisation",
        "voluntary",
        "charity"
    ],
    "wof:name":"Volunteer Link Caithness",
    "wof:placetype":"venue"
},
  "geometry": {"coordinates":[-3.086996,58.440132],"type":"Point"}
}