{
  "type": "Feature",
  "properties": {
    "addr:full":", Talybont Near Barmouth Talybont Gwynedd LL43 2AN",
    "addr:postcode":"ll43 2an",
    "addr:street":"Near Barmouth Talybont",
    "iso:country":"GB",
    "sg:address":", Talybont Near Barmouth",
    "sg:city":"Talybont",
    "sg:classifiers":[
        {
            "category":"Bars & Pubs",
            "type":"Food & Drink"
        }
    ],
    "sg:phone":"+44 1341 247578",
    "sg:postcode":"LL43 2AN",
    "sg:province":"Gwynedd",
    "sg:tags":[
        "pubs",
        "inn"
    ],
    "wof:name":"Ysgethin Inn",
    "wof:placetype":"venue"
},
  "geometry": {"coordinates":[-4.092428,52.774815],"type":"Point"}
}