{
  "type": "Feature",
  "properties": {
    "iso:country":"GB",
    "sg:address":"Suite 8a Alberton House, 30 St Marys Parsonage",
    "sg:city":"Manchester",
    "sg:classifiers":[
        {
            "category":"Banks & Credit Unions",
            "subcategory":"Financial Services",
            "type":"Services"
        }
    ],
    "sg:phone":"+44 161 834 8899",
    "sg:postcode":"M60 9FH",
    "sg:province":"Greater Manchester",
    "sg:tags":[
        "adviser"
    ],
    "wof:name":"Barclay Brown Financial Services Ltd.",
    "wof:placetype":"venue"
},
  "geometry": {"coordinates":[-2.2499969006,53.4823722839],"type":"Point"}
}