{
  "type": "Feature",
  "properties": {
    "addr:full":"16 Bosville Road Sevenoaks Kent TN13 3JD",
    "addr:housenumber":"16",
    "addr:postcode":"tn13 3jd",
    "addr:street":"Bosville Road",
    "iso:country":"GB",
    "sg:address":"16 Bosville Road",
    "sg:city":"Sevenoaks",
    "sg:classifiers":[
        {
            "category":"Shopping",
            "subcategory":"Department Store",
            "type":"Retail Goods"
        }
    ],
    "sg:phone":"+44 7970 646545",
    "sg:postcode":"TN13 3JD",
    "sg:province":"Kent",
    "wof:name":"Sound Asylum Music Ltd.",
    "wof:placetype":"venue"
},
  "geometry": {"coordinates":[0.180354,51.280533],"type":"Point"}
}