{
  "type": "Feature",
  "properties": {
    "addr:full":"64 Springbank Rd Lewisham Greater London SE13 6SN",
    "addr:housenumber":"64",
    "addr:postcode":"se13 6sn",
    "addr:street":"Springbank Rd",
    "iso:country":"GB",
    "sg:address":"64 Springbank Rd",
    "sg:city":"Lewisham",
    "sg:classifiers":[
        {
            "category":"Utilities",
            "type":"Services"
        }
    ],
    "sg:phone":"+44 20 8333 2555",
    "sg:postcode":"SE13 6SN",
    "sg:province":"Greater London",
    "sg:tags":[
        "internet"
    ],
    "wof:name":"Global Internet Consultants",
    "wof:placetype":"venue"
},
  "geometry": {"coordinates":[-0.000277,51.450085],"type":"Point"}
}