{
  "type": "Feature",
  "properties": {
    "iso:country":"GB",
    "sg:address":"74 Brodrick Road",
    "sg:city":"Eastbourne",
    "sg:classifiers":[
        {
            "category":"Communications",
            "type":"Services"
        }
    ],
    "sg:postcode":"BN22 9NS",
    "sg:province":"East Sussex",
    "sg:tags":[
        "telecommunication"
    ],
    "wof:name":"Clearwater Communications International",
    "wof:placetype":"venue"
},
  "geometry": {"coordinates":[0.2769500017,50.799697876],"type":"Point"}
}