{
  "type": "Feature",
  "properties": {
    "addr:full":"39 Jamaica Street Edinburgh City of Edinburgh EH3 6HF",
    "addr:housenumber":"39",
    "addr:postcode":"eh3 6hf",
    "addr:street":"Jamaica Street",
    "iso:country":"GB",
    "sg:address":"39 Jamaica Street",
    "sg:city":"Edinburgh",
    "sg:classifiers":[
        {
            "category":"Bars & Pubs",
            "type":"Food & Drink"
        },
        {
            "category":"Food & Beverages",
            "subcategory":"Liquor & Beverages",
            "type":"Retail Goods"
        }
    ],
    "sg:phone":"+44 131 225 1858",
    "sg:postcode":"EH3 6HF",
    "sg:province":"City of Edinburgh",
    "sg:tags":[
        "pubs",
        "beer",
        "wine",
        "inn",
        "spirit"
    ],
    "wof:name":"Kay's Bar",
    "wof:placetype":"venue"
},
  "geometry": {"coordinates":[-3.2029440403,55.9559745789],"type":"Point"}
}