{
  "type": "Feature",
  "properties": {
    "iso:country":"GB",
    "sg:address":"Berkshire House, Queen Street",
    "sg:city":"Maidenhead",
    "sg:classifiers":[
        {
            "category":"Professional",
            "subcategory":"Employment Agencies",
            "type":"Services"
        }
    ],
    "sg:phone":"+44 1628 675551",
    "sg:postcode":"SL6 1NF",
    "sg:province":"Berkshire",
    "sg:tags":[
        "consultant"
    ],
    "wof:name":"Hunterskil Howard Consulting Ltd.",
    "wof:placetype":"venue"
},
  "geometry": {"coordinates":[-0.7202060223,51.522518158],"type":"Point"}
}