{
  "type": "Feature",
  "properties": {
    "addr:full":"8 Aspen Lane, Oswaldtwistle Accrington Lancashire BB5 4QA",
    "addr:housenumber":"8",
    "addr:postcode":"bb5 4qa",
    "addr:street":"Aspen Lane;Accrington",
    "iso:country":"GB",
    "sg:address":"8 Aspen Lane, Oswaldtwistle",
    "sg:city":"Accrington",
    "sg:classifiers":[
        {
            "category":"Building & Trades",
            "subcategory":"Plumbing",
            "type":"Services"
        }
    ],
    "sg:phone":"+44 1254 391727",
    "sg:postcode":"BB5 4QA",
    "sg:province":"Lancashire",
    "sg:tags":[
        "plumber",
        "heating"
    ],
    "wof:name":"Bewarm Heating Co",
    "wof:placetype":"venue"
},
  "geometry": {"coordinates":[-2.4120519161,53.7466049194],"type":"Point"}
}