{
  "type": "Feature",
  "properties": {
    "addr:full":"Woodside House, Main Street Newark Lincolnshire NG23 6JN",
    "addr:postcode":"ng23 6jn",
    "addr:street":"Main Street",
    "iso:country":"GB",
    "sg:address":"Woodside House, Main Street",
    "sg:city":"Newark",
    "sg:classifiers":[
        {
            "category":"Professional",
            "subcategory":"Art Services",
            "type":"Services"
        }
    ],
    "sg:phone":"+44 1636 636377",
    "sg:postcode":"NG23 6JN",
    "sg:province":"Lincolnshire",
    "sg:tags":[
        "consultant",
        "design"
    ],
    "wof:name":"Heritage Concern Ltd.",
    "wof:placetype":"venue"
},
  "geometry": {"coordinates":[-0.83973,53.123386],"type":"Point"}
}