{
  "type": "Feature",
  "properties": {
    "addr:full":"Osprey House, Archer Close Studley Warwickshire B80 7HX",
    "addr:postcode":"b80 7hx",
    "addr:street":"Archer Close",
    "iso:country":"GB",
    "sg:address":"Osprey House, Archer Close",
    "sg:city":"Studley",
    "sg:classifiers":[
        {
            "category":"Social Services",
            "subcategory":"Adult Care",
            "type":"Services"
        }
    ],
    "sg:phone":"+44 1527 853153",
    "sg:postcode":"B80 7HX",
    "sg:province":"Warwickshire",
    "sg:tags":[
        "housing",
        "sheltered"
    ],
    "wof:name":"Osprey Ho",
    "wof:placetype":"venue"
},
  "geometry": {"coordinates":[-1.9010390043,52.2728347778],"type":"Point"}
}