{
  "type": "Feature",
  "properties": {
    "addr:full":"308 High Road, Wood Grn London Greater London N22 8JR",
    "addr:housenumber":"308",
    "addr:postcode":"n22 8jr",
    "addr:street":"High Road Wood",
    "iso:country":"GB",
    "sg:address":"308 High Road, Wood Grn",
    "sg:city":"London",
    "sg:classifiers":[
        {
            "category":"Home & Garden",
            "subcategory":"Household Appliances",
            "type":"Retail Goods"
        }
    ],
    "sg:phone":"+44 20 8881 1488",
    "sg:postcode":"N22 8JR",
    "sg:province":"Greater London",
    "sg:tags":[
        "electrical"
    ],
    "wof:name":"Trade Domestics",
    "wof:placetype":"venue"
},
  "geometry": {"coordinates":[-0.111279,51.605972],"type":"Point"}
}