{
  "type": "Feature",
  "properties": {
    "addr:full":"Morbrow, Western Rd Crowborough East Sussex TN6 3EN",
    "addr:postcode":"tn6 3en",
    "addr:street":"Western Rd",
    "iso:country":"GB",
    "sg:address":"Morbrow, Western Rd",
    "sg:city":"Crowborough",
    "sg:classifiers":[
        {
            "category":"Education",
            "subcategory":"Special Training",
            "type":"Public Place"
        },
        {
            "category":"Education",
            "subcategory":"School",
            "type":"Public Place"
        }
    ],
    "sg:phone":"+44 1892 652683",
    "sg:postcode":"TN6 3EN",
    "sg:province":"East Sussex",
    "sg:tags":[
        "centre",
        "private",
        "tuition"
    ],
    "wof:name":"Crowborough Learning Centre",
    "wof:placetype":"venue"
},
  "geometry": {"coordinates":[0.18517,51.043365],"type":"Point"}
}