{
  "type": "Feature",
  "properties": {
    "iso:country":"GB",
    "sg:address":"26 Grange Ave",
    "sg:city":"London",
    "sg:classifiers":[
        {
            "category":"Professional",
            "subcategory":"Management & Consulting",
            "type":"Services"
        }
    ],
    "sg:postcode":"N20 8AD",
    "sg:province":"Greater London",
    "sg:tags":[
        "consultant",
        "promotion",
        "direct",
        "sale"
    ],
    "wof:name":"First Concept (U K)",
    "wof:placetype":"venue"
},
  "geometry": {"coordinates":[-0.2094369978,51.6367912292],"type":"Point"}
}