{
  "type": "Feature",
  "properties": {
    "addr:full":"Chalkstone Way Haverhill Essex CB9 0LD",
    "addr:postcode":"cb9 0ld",
    "addr:street":"Chalkstone Way",
    "iso:country":"GB",
    "sg:address":"Chalkstone Way",
    "sg:city":"Haverhill",
    "sg:classifiers":[
        {
            "category":"Education",
            "subcategory":"School",
            "type":"Public Place"
        },
        {
            "category":"Government",
            "subcategory":"Office",
            "type":"Public Place"
        }
    ],
    "sg:phone":"+44 1440 761511",
    "sg:postcode":"CB9 0LD",
    "sg:province":"Essex",
    "sg:tags":[
        "local",
        "authority"
    ],
    "wof:name":"Samuel Ward Upper School",
    "wof:placetype":"venue"
},
  "geometry": {"coordinates":[0.4570150077,52.0789108276],"type":"Point"}
}