{
  "type": "Feature",
  "properties": {
    "iso:country":"GB",
    "sg:address":"274-276 Queenstown Road",
    "sg:city":"London",
    "sg:classifiers":[
        {
            "category":"Utilities",
            "subcategory":"Telephone",
            "type":"Services"
        }
    ],
    "sg:phone":"+44 20 7498 0374",
    "sg:postcode":"SW8 4LP",
    "sg:province":"Greater London",
    "sg:tags":[
        "telecommunication"
    ],
    "wof:name":"Dialogue",
    "wof:placetype":"venue"
},
  "geometry": {"coordinates":[-0.148259,51.476379],"type":"Point"}
}