{
  "type": "Feature",
  "properties": {
    "addr:full":"Savoy Centre, 140 Sauchiehall Street Glasgow Glasgow City G2 3DH",
    "addr:housenumber":"140",
    "addr:postcode":"g2 3dh",
    "addr:street":"Sauchiehall Street",
    "iso:country":"GB",
    "sg:address":"Savoy Centre, 140 Sauchiehall Street",
    "sg:city":"Glasgow",
    "sg:classifiers":[
        {
            "category":"Restaurant",
            "type":"Food & Drink"
        }
    ],
    "sg:phone":"+44 141 332 7028",
    "sg:postcode":"G2 3DH",
    "sg:province":"Glasgow City",
    "wof:name":"Windows Restaurant",
    "wof:placetype":"venue"
},
  "geometry": {"coordinates":[-4.26242,55.865349],"type":"Point"}
}