{
  "type": "Feature",
  "properties": {
    "iso:country":"GB",
    "sg:address":"489 Pitsmoor Road",
    "sg:city":"Sheffield",
    "sg:classifiers":[
        {
            "category":"Food & Beverages",
            "subcategory":"Supermarket",
            "type":"Retail Goods"
        }
    ],
    "sg:postcode":"S3 9AT",
    "sg:province":"South Yorkshire",
    "wof:name":"Tollbar Minimarket",
    "wof:placetype":"venue"
},
  "geometry": {"coordinates":[-1.4651360512,53.4008865356],"type":"Point"}
}