{
  "type": "Feature",
  "properties": {
    "addr:full":"61 Shrubbery Road London Greater London SW16 2AS",
    "addr:housenumber":"61",
    "addr:postcode":"sw16 2as",
    "addr:street":"Shrubbery Road",
    "iso:country":"GB",
    "sg:address":"61 Shrubbery Road",
    "sg:city":"London",
    "sg:classifiers":[
        {
            "category":"Food & Beverages",
            "subcategory":"Liquor & Beverages",
            "type":"Retail Goods"
        }
    ],
    "sg:phone":"+44 20 8677 1197",
    "sg:postcode":"SW16 2AS",
    "sg:province":"Greater London",
    "sg:tags":[
        "beer",
        "spirit",
        "wines"
    ],
    "wof:name":"Taliana Trading Co",
    "wof:placetype":"venue"
},
  "geometry": {"coordinates":[-0.1277350038,51.4293174744],"type":"Point"}
}