{
  "type": "Feature",
  "properties": {
    "addr:full":"201 The Broadway Southall Greater London UB1 1LZ",
    "addr:housenumber":"201",
    "addr:postcode":"ub1 1lz",
    "addr:street":"The Broadway",
    "iso:country":"GB",
    "sg:address":"201 The Broadway",
    "sg:city":"Southall",
    "sg:classifiers":[
        {
            "category":"Retail",
            "subcategory":"Auto Repair",
            "type":"Services"
        }
    ],
    "sg:phone":"+44 20 8574 3582",
    "sg:postcode":"UB1 1LZ",
    "sg:province":"Greater London",
    "sg:tags":[
        "modification",
        "garage"
    ],
    "wof:name":"Broadway Auto Service Centre",
    "wof:placetype":"venue"
},
  "geometry": {"coordinates":[-0.390344,51.51318],"type":"Point"}
}