{
  "type": "Feature",
  "properties": {
    "addr:full":"Longlands Mill, Castle St Stalybridge Greater Manchester SK15 1NX",
    "addr:postcode":"sk15 1nx",
    "addr:street":"Longlands Mill Castle St",
    "iso:country":"GB",
    "sg:address":"Longlands Mill, Castle St",
    "sg:city":"Stalybridge",
    "sg:classifiers":[
        {
            "category":"Professional",
            "subcategory":"Engineering",
            "type":"Services"
        }
    ],
    "sg:postcode":"SK15 1NX",
    "sg:province":"Greater Manchester",
    "wof:name":"Rodgers,M J,& Sons",
    "wof:placetype":"venue"
},
  "geometry": {"coordinates":[-2.0575690269,53.483543396],"type":"Point"}
}