{
  "type": "Feature",
  "properties": {
    "iso:country":"GB",
    "sg:address":"10a Church Street",
    "sg:city":"Atherstone",
    "sg:classifiers":[
        {
            "category":"Home & Garden",
            "subcategory":"Building Materials",
            "type":"Retail Goods"
        }
    ],
    "sg:phone":"+44 1827 720700",
    "sg:postcode":"CV9 1HA",
    "sg:province":"Leicestershire",
    "sg:tags":[
        "ventilator",
        "ventilation",
        "system"
    ],
    "wof:name":"Maintenance & Contracting Specialists Ltd.",
    "wof:placetype":"venue"
},
  "geometry": {"coordinates":[-1.547328,52.577709],"type":"Point"}
}