{
  "type": "Feature",
  "properties": {
    "iso:country":"GB",
    "sg:address":"Relief Road, Broughton Astley",
    "sg:city":"Leicester",
    "sg:classifiers":[
        {
            "category":"Freight",
            "type":"Transportation"
        }
    ],
    "sg:phone":"+44 1455 282293",
    "sg:postcode":"LE9 6SN",
    "sg:province":"Leicestershire",
    "sg:tags":[
        "haulage",
        "road"
    ],
    "wof:name":"G T N & J M Ratcliffe",
    "wof:placetype":"venue"
},
  "geometry": {"coordinates":[-1.225593,52.531677],"type":"Point"}
}