{
  "type": "Feature",
  "properties": {
    "addr:full":"4 Albion Quay, Lombard Road London Greater London SW11 3RQ",
    "addr:housenumber":"4",
    "addr:postcode":"sw11 3rq",
    "addr:street":"Albion Quay Lombard Road",
    "iso:country":"GB",
    "sg:address":"4 Albion Quay, Lombard Road",
    "sg:city":"London",
    "sg:classifiers":[
        {
            "category":"Building & Trades",
            "subcategory":"Construction",
            "type":"Services"
        }
    ],
    "sg:postcode":"SW11 3RQ",
    "sg:province":"Greater London",
    "sg:tags":[
        "builder"
    ],
    "wof:name":"Holt Nicholas Construction",
    "wof:placetype":"venue"
},
  "geometry": {"coordinates":[-0.17727,51.472961],"type":"Point"}
}