{
  "type": "Feature",
  "properties": {
    "iso:country":"GB",
    "sg:address":"4 Albion Quay, Lombard Road",
    "sg:city":"London",
    "sg:classifiers":[
        {
            "category":"Building & Trades",
            "subcategory":"Construction",
            "type":"Services"
        }
    ],
    "sg:postcode":"SW11 3RQ",
    "sg:province":"Greater London",
    "sg:tags":[
        "builder"
    ],
    "wof:name":"Holt Nicholas Construction",
    "wof:placetype":"venue"
},
  "geometry": {"coordinates":[-0.17727,51.472961],"type":"Point"}
}