{
  "type": "Feature",
  "properties": {
    "addr:full":"10 Main Street, Sprotbrough Doncaster South Yorkshire DN5 7RF",
    "addr:housenumber":"10",
    "addr:postcode":"dn5 7rf",
    "addr:street":"Main Street",
    "iso:country":"GB",
    "sg:address":"10 Main Street, Sprotbrough",
    "sg:city":"Doncaster",
    "sg:classifiers":[
        {
            "category":"Shopping",
            "subcategory":"Florist",
            "type":"Retail Goods"
        }
    ],
    "sg:phone":"+44 1302 311555",
    "sg:postcode":"DN5 7RF",
    "sg:province":"South Yorkshire",
    "wof:name":"The House of Flowers",
    "wof:placetype":"venue"
},
  "geometry": {"coordinates":[-1.1883670092,53.5124511719],"type":"Point"}
}