{
  "type": "Feature",
  "properties": {
    "iso:country":"GB",
    "sg:address":"The Warehouse, 23 Victoria Road",
    "sg:city":"Richmond",
    "sg:classifiers":[
        {
            "category":"Retail",
            "subcategory":"Storage",
            "type":"Services"
        }
    ],
    "sg:postcode":"DL10 4AE",
    "sg:province":"North Yorkshire",
    "sg:tags":[
        "household",
        "removal"
    ],
    "wof:name":"Brian Anderson Removals",
    "wof:placetype":"venue"
},
  "geometry": {"coordinates":[-1.738664031,54.4043388367],"type":"Point"}
}