{
  "type": "Feature",
  "properties": {
    "addr:full":"Wellington Row Whitehaven Cumbria CA28 7HG",
    "addr:postcode":"ca28 7hg",
    "addr:street":"Wellington Row",
    "iso:country":"GB",
    "sg:address":"Wellington Row",
    "sg:city":"Whitehaven",
    "sg:classifiers":[
        {
            "category":"Education",
            "subcategory":"School",
            "type":"Public Place"
        }
    ],
    "sg:phone":"+44 1946 852660",
    "sg:postcode":"CA28 7HG",
    "sg:province":"Cumbria",
    "sg:tags":[
        "local",
        "authority"
    ],
    "wof:name":"St James C Of E Junior School",
    "wof:placetype":"venue"
},
  "geometry": {"coordinates":[-3.5839509964,54.5514297485],"type":"Point"}
}