{
  "type": "Feature",
  "properties": {
    "addr:full":"Garden Cottage, Ockham Lane Cobham Surrey KT11 1LP",
    "addr:postcode":"kt11 1lp",
    "addr:street":"Ockham Lane",
    "iso:country":"GB",
    "sg:address":"Garden Cottage, Ockham Lane",
    "sg:city":"Cobham",
    "sg:classifiers":[
        {
            "category":"Professional",
            "subcategory":"Accounting & Tax Preparation",
            "type":"Services"
        }
    ],
    "sg:postcode":"KT11 1LP",
    "sg:province":"Surrey",
    "sg:tags":[
        "accountant"
    ],
    "wof:name":"Timothy William Drake",
    "wof:placetype":"venue"
},
  "geometry": {"coordinates":[-0.410454005,51.3281173706],"type":"Point"}
}