{
  "type": "Feature",
  "properties": {
    "iso:country":"GB",
    "sg:address":"High Heworth",
    "sg:city":"Gateshead",
    "sg:classifiers":[
        {
            "category":"Bars & Pubs",
            "type":"Food & Drink"
        }
    ],
    "sg:phone":"+44 191 469 2664",
    "sg:postcode":"NE10 9BB",
    "sg:province":"Tyne and Wear",
    "sg:tags":[
        "pubs",
        "inn"
    ],
    "wof:name":"Fiddlers Three",
    "wof:placetype":"venue"
},
  "geometry": {"coordinates":[-1.56276,54.94202],"type":"Point"}
}