{
  "type": "Feature",
  "properties": {
    "addr:full":"17 Westpark, Eaton Rise London Greater London W5 2HH",
    "addr:housenumber":"17",
    "addr:postcode":"w5 2hh",
    "addr:street":"Westpark Eaton Rise",
    "iso:country":"GB",
    "sg:address":"17 Westpark, Eaton Rise",
    "sg:city":"London",
    "sg:classifiers":[
        {
            "category":"Juice Bar",
            "subcategory":"None",
            "type":"Food & Drink"
        }
    ],
    "sg:phone":"+44 20 8723 7000",
    "sg:postcode":"W5 2HH",
    "sg:province":"Greater London",
    "sg:tags":[
        "fruit"
    ],
    "wof:name":"Exotic Planet Juices Ltd.",
    "wof:placetype":"venue"
},
  "geometry": {"coordinates":[-0.3062300086,51.5174217224],"type":"Point"}
}