{
  "type": "Feature",
  "properties": {
    "addr:full":"20 Batchelor Street Chatham Kent ME4 4BJ",
    "addr:housenumber":"20",
    "addr:postcode":"me4 4bj",
    "addr:street":"Batchelor Street",
    "iso:country":"GB",
    "sg:address":"20 Batchelor Street",
    "sg:city":"Chatham",
    "sg:classifiers":[
        {
            "category":"Professional",
            "subcategory":"Accounting & Tax Preparation",
            "type":"Services"
        }
    ],
    "sg:phone":"+44 1634 407365",
    "sg:postcode":"ME4 4BJ",
    "sg:province":"Kent",
    "sg:tags":[
        "accountant"
    ],
    "wof:name":"Accountancy & Administration Systems Ltd.",
    "wof:placetype":"venue"
},
  "geometry": {"coordinates":[0.5284669995,51.3815383911],"type":"Point"}
}