{
  "type": "Feature",
  "properties": {
    "addr:full":"Inside Court - Unit 1, Cairngorm Gate Milton Keynes Buckinghamshire MK6 1AG",
    "addr:housenumber":"unit 1",
    "addr:postcode":"mk6 1ag",
    "addr:street":"Inside;Cairngorm Gate",
    "iso:country":"GB",
    "sg:address":"Inside Court - Unit 1, Cairngorm Gate",
    "sg:city":"Milton Keynes",
    "sg:classifiers":[
        {
            "category":"Education",
            "subcategory":"Music School",
            "type":"Public Place"
        }
    ],
    "sg:phone":"+44 1908 233433",
    "sg:postcode":"MK6 1AG",
    "sg:province":"Buckinghamshire",
    "sg:tags":[
        "conservatory"
    ],
    "wof:name":"Win-Dor Ltd.",
    "wof:placetype":"venue"
},
  "geometry": {"coordinates":[-0.764069,52.030193],"type":"Point"}
}