{
  "type": "Feature",
  "properties": {
    "addr:full":"1a The Green, Hardingstone Northampton Northamptonshire NN4 7BU",
    "addr:housenumber":"1a",
    "addr:postcode":"nn4 7bu",
    "addr:street":"The Green",
    "iso:country":"GB",
    "sg:address":"1a The Green, Hardingstone",
    "sg:city":"Northampton",
    "sg:classifiers":[
        {
            "category":"Farming",
            "subcategory":"Farm",
            "type":"Manufacturing & Wholesale Goods"
        }
    ],
    "sg:phone":"+44 1604 766123",
    "sg:postcode":"NN4 7BU",
    "sg:province":"Northamptonshire",
    "sg:tags":[
        "mixed",
        "crop"
    ],
    "wof:name":"D & R Pittams",
    "wof:placetype":"venue"
},
  "geometry": {"coordinates":[-0.8386639953,52.2200965881],"type":"Point"}
}