{
  "type": "Feature",
  "properties": {
    "addr:full":"3 Theberton Street, Islington London Greater London N1 0QY",
    "addr:housenumber":"3",
    "addr:postcode":"n1 0qy",
    "addr:street":"Theberton Street",
    "iso:country":"GB",
    "sg:address":"3 Theberton Street, Islington",
    "sg:city":"London",
    "sg:classifiers":[
        {
            "category":"Travel",
            "subcategory":"Hotels & Motels",
            "type":"Entertainment"
        },
        {
            "category":"Personal",
            "subcategory":"Barber",
            "type":"Services"
        }
    ],
    "sg:phone":"+44 20 7359 4997",
    "sg:postcode":"N1 0QY",
    "sg:province":"Greater London",
    "sg:tags":[
        "men's",
        "hairdresser"
    ],
    "wof:name":"Huckers",
    "wof:placetype":"venue"
},
  "geometry": {"coordinates":[-0.1030659974,51.5374412537],"type":"Point"}
}