{
  "type": "Feature",
  "properties": {
    "addr:full":"284 Fort Austin Avenue Plymouth Devon PL6 5SR",
    "addr:housenumber":"284",
    "addr:postcode":"pl6 5sr",
    "addr:street":"Fort Austin Avenue",
    "iso:country":"GB",
    "sg:address":"284 Fort Austin Avenue",
    "sg:city":"Plymouth",
    "sg:classifiers":[
        {
            "category":"Autos & Motor Vehicles",
            "subcategory":"Automobile Sales",
            "type":"Retail Goods"
        },
        {
            "category":"Food & Beverages",
            "subcategory":"Meat & Fish",
            "type":"Retail Goods"
        }
    ],
    "sg:phone":"+44 1752 771529",
    "sg:postcode":"PL6 5SR",
    "sg:province":"Devon",
    "sg:tags":[
        "car",
        "chip"
    ],
    "wof:name":"TOP CAR MOTORS",
    "wof:placetype":"venue"
},
  "geometry": {"coordinates":[-4.1059060097,50.4002037048],"type":"Point"}
}