{
  "type": "Feature",
  "properties": {
    "iso:country":"GB",
    "sg:address":"Arran Avenue",
    "sg:city":"Blackburn",
    "sg:classifiers":[
        {
            "category":"Education",
            "subcategory":"School",
            "type":"Public Place"
        }
    ],
    "sg:phone":"+44 1254 698016",
    "sg:postcode":"BB1 2ET",
    "sg:province":"Lancashire",
    "sg:tags":[
        "local",
        "authority"
    ],
    "wof:name":"Shadsworth County Junior School",
    "wof:placetype":"venue"
},
  "geometry": {"coordinates":[-2.441849,53.739243],"type":"Point"}
}