{
  "type": "Feature",
  "properties": {
    "iso:country":"GB",
    "sg:address":"Maple Grove",
    "sg:city":"March",
    "sg:classifiers":[
        {
            "category":"Education",
            "subcategory":"School",
            "type":"Public Place"
        },
        {
            "category":"Government",
            "subcategory":"Office",
            "type":"Public Place"
        }
    ],
    "sg:phone":"+44 1354 653033",
    "sg:postcode":"PE15 8JT",
    "sg:province":"Cambridgeshire",
    "sg:tags":[
        "local",
        "authority"
    ],
    "wof:name":"Westwood Junior School",
    "wof:placetype":"venue"
},
  "geometry": {"coordinates":[0.0889049992,52.5512542725],"type":"Point"}
}