{
  "type": "Feature",
  "properties": {
    "iso:country":"GB",
    "sg:address":"5 Warham Road",
    "sg:city":"Croydon",
    "sg:classifiers":[
        {
            "category":"Social Services",
            "subcategory":"Retirement Home",
            "type":"Services"
        }
    ],
    "sg:phone":"+44 20 8686 8801",
    "sg:postcode":"CR2 6LE",
    "sg:province":"Surrey",
    "sg:tags":[
        "residential",
        "care"
    ],
    "wof:name":"Laurel Residential Homes Ltd.",
    "wof:placetype":"venue"
},
  "geometry": {"coordinates":[-0.098776,51.363575],"type":"Point"}
}