{
  "type": "Feature",
  "properties": {
    "iso:country":"GB",
    "sg:address":"16 Fothringham Drive",
    "sg:city":"Dundee",
    "sg:classifiers":[
        {
            "category":"Building & Trades",
            "subcategory":"Landscaping Services",
            "type":"Services"
        },
        {
            "category":"Autos & Motor Vehicles",
            "subcategory":"Auto Supplies",
            "type":"Retail Goods"
        }
    ],
    "sg:phone":"+44 1382 534652",
    "sg:postcode":"DD5 4SN",
    "sg:province":"Angus",
    "sg:tags":[
        "horticultural",
        "towing",
        "eqpt",
        "trailer"
    ],
    "wof:name":"Monifieth Trailers",
    "wof:placetype":"venue"
},
  "geometry": {"coordinates":[-2.8247790337,56.4884147644],"type":"Point"}
}