{
  "type": "Feature",
  "properties": {
    "addr:full":"Sandford Crediton Devon EX17 4LN",
    "addr:postcode":"ex17 4ln",
    "iso:country":"GB",
    "sg:address":"Sandford",
    "sg:city":"Crediton",
    "sg:classifiers":[
        {
            "category":"Government",
            "subcategory":"Post Office",
            "type":"Public Place"
        }
    ],
    "sg:phone":"+44 1363 772053",
    "sg:postcode":"EX17 4LN",
    "sg:province":"Devon",
    "wof:name":"J E M Newstead",
    "wof:placetype":"venue"
},
  "geometry": {"coordinates":[-3.663394,50.810249],"type":"Point"}
}