{
  "type": "Feature",
  "properties": {
    "addr:full":"32 Cambrian View, Whipcord Lane Chester Cheshire CH1 4DE",
    "addr:housenumber":"32",
    "addr:postcode":"ch1 4de",
    "addr:street":"Cambrian View Whipcord Lane",
    "iso:country":"GB",
    "sg:address":"32 Cambrian View, Whipcord Lane",
    "sg:city":"Chester",
    "sg:classifiers":[
        {
            "category":"Personal",
            "type":"Services"
        },
        {
            "category":"Government",
            "subcategory":"Customs House",
            "type":"Public Place"
        }
    ],
    "sg:phone":"+44 1244 371306",
    "sg:postcode":"CH1 4DE",
    "sg:province":"Cheshire",
    "sg:tags":[
        "clearance"
    ],
    "wof:name":"Taylors",
    "wof:placetype":"venue"
},
  "geometry": {"coordinates":[-2.903291,53.198277],"type":"Point"}
}