{
  "type": "Feature",
  "properties": {
    "iso:country":"GB",
    "sg:address":"Coombeshead Road",
    "sg:city":"Newton Abbot",
    "sg:classifiers":[
        {
            "category":"Education",
            "subcategory":"School",
            "type":"Public Place"
        }
    ],
    "sg:phone":"+44 1626 352559",
    "sg:postcode":"TQ12 1PT",
    "sg:province":"Devon",
    "sg:tags":[
        "local",
        "authority"
    ],
    "wof:name":"St Joseph's R C Primary School",
    "wof:placetype":"venue"
},
  "geometry": {"coordinates":[-3.6279909611,50.5358772278],"type":"Point"}
}