{
  "type": "Feature",
  "properties": {
    "iso:country":"GB",
    "sg:address":"94 High Street",
    "sg:city":"Shepperton",
    "sg:classifiers":[
        {
            "category":"Home & Garden",
            "subcategory":"Hardware",
            "type":"Retail Goods"
        }
    ],
    "sg:phone":"+44 1932 240557",
    "sg:postcode":"TW17 9AU",
    "sg:province":"Surrey",
    "sg:tags":[
        "shop",
        "retailer",
        "diy"
    ],
    "wof:name":"Shepperton Homecare",
    "wof:placetype":"venue"
},
  "geometry": {"coordinates":[-0.449061,51.392418],"type":"Point"}
}