{
  "type": "Feature",
  "properties": {
    "addr:full":"15 The High St Sittingbourne Kent ME10 4AY",
    "addr:housenumber":"15",
    "addr:postcode":"me10 4ay",
    "addr:street":"The High St",
    "iso:country":"GB",
    "sg:address":"15 The High St",
    "sg:city":"Sittingbourne",
    "sg:classifiers":[
        {
            "category":"Building & Trades",
            "subcategory":"Landscaping Services",
            "type":"Services"
        }
    ],
    "sg:postcode":"ME10 4AY",
    "sg:province":"Kent",
    "sg:tags":[
        "pond",
        "aquarium"
    ],
    "wof:name":"Aldred,Martin,",
    "wof:placetype":"venue"
},
  "geometry": {"coordinates":[0.73961,51.339245],"type":"Point"}
}