{
  "type": "Feature",
  "properties": {
    "iso:country":"GB",
    "sg:address":"3a Crown Buildings, 15 High Street",
    "sg:city":"Portsmouth",
    "sg:classifiers":[
        {
            "category":"Food & Beverages",
            "subcategory":"Fruits & Vegetables",
            "type":"Retail Goods"
        }
    ],
    "sg:postcode":"PO6 3BU",
    "sg:province":"Hampshire",
    "sg:tags":[
        "greengrocer"
    ],
    "wof:name":"Little Gems",
    "wof:placetype":"venue"
},
  "geometry": {"coordinates":[-1.0664099455,50.8464012146],"type":"Point"}
}