{
  "type": "Feature",
  "properties": {
    "addr:full":"12 Fratton Road Portsmouth Hampshire PO1 5BX",
    "addr:housenumber":"12",
    "addr:postcode":"hampshire po1 5bx",
    "addr:street":"Fratton Road",
    "iso:country":"GB",
    "sg:address":"12 Fratton Road",
    "sg:city":"Portsmouth",
    "sg:classifiers":[
        {
            "category":"Professional",
            "subcategory":"Accounting & Tax Preparation",
            "type":"Services"
        }
    ],
    "sg:postcode":"PO1 5BX",
    "sg:province":"Hampshire",
    "sg:tags":[
        "accountant"
    ],
    "wof:name":"Geoffrey N Barnes",
    "wof:placetype":"venue"
},
  "geometry": {"coordinates":[-1.0767760277,50.7968902588],"type":"Point"}
}