{
  "type": "Feature",
  "properties": {
    "iso:country":"GB",
    "sg:address":"259 Kilmarnock Road",
    "sg:city":"Glasgow",
    "sg:classifiers":[
        {
            "category":"Shopping",
            "subcategory":"News",
            "type":"Retail Goods"
        }
    ],
    "sg:phone":"+44 141 632 4368",
    "sg:postcode":"G41 3JF",
    "sg:province":"Glasgow City",
    "sg:tags":[
        "newsagent"
    ],
    "wof:name":"Khar General Stores",
    "wof:placetype":"venue"
},
  "geometry": {"coordinates":[-4.2850289345,55.8269996643],"type":"Point"}
}