{
  "type": "Feature",
  "properties": {
    "iso:country":"GB",
    "sg:address":"The Ark School, School Road, Padworth",
    "sg:city":"Reading",
    "sg:classifiers":[
        {
            "category":"Farming",
            "subcategory":"Nursery",
            "type":"Manufacturing & Wholesale Goods"
        }
    ],
    "sg:phone":"+44 118 983 4802",
    "sg:postcode":"RG7 4JA",
    "sg:province":"Berkshire",
    "sg:tags":[
        "creche"
    ],
    "wof:name":"J & W Hartley Ltd.",
    "wof:placetype":"venue"
},
  "geometry": {"coordinates":[-1.136184,51.400814],"type":"Point"}
}