{
  "type": "Feature",
  "properties": {
    "iso:country":"GB",
    "sg:address":", Otterton Budleigh Salterton",
    "sg:city":"Budleigh Salterton",
    "sg:classifiers":[
        {
            "category":"Recreation",
            "subcategory":"Campground",
            "type":"Entertainment"
        }
    ],
    "sg:phone":"+44 1395 568398",
    "sg:postcode":"EX9 7BX",
    "sg:province":"Devon",
    "sg:tags":[
        "holiday",
        "centre",
        "camp"
    ],
    "wof:name":"Ladram Bay Holiday Centre",
    "wof:placetype":"venue"
},
  "geometry": {"coordinates":[-3.3303,50.629742],"type":"Point"}
}