{
  "type": "Feature",
  "properties": {
    "addr:full":"295 A & B Vicarage Road, Kings Heath Birmingham West Midlands B14 7NE",
    "addr:housenumber":"295 a & b",
    "addr:postcode":"b14 7ne",
    "addr:street":"Vicarage Road",
    "iso:country":"GB",
    "sg:address":"295 A & B Vicarage Road, Kings Heath",
    "sg:city":"Birmingham",
    "sg:classifiers":[
        {
            "category":"Retail",
            "subcategory":"Repair Shop",
            "type":"Services"
        }
    ],
    "sg:phone":"+44 121 443 4452",
    "sg:postcode":"B14 7NE",
    "sg:province":"West Midlands",
    "sg:tags":[
        "upholsterer"
    ],
    "wof:name":"K H U Ltd.",
    "wof:placetype":"venue"
},
  "geometry": {"coordinates":[-1.9069199562,52.4271888733],"type":"Point"}
}