{
  "type": "Feature",
  "properties": {
    "addr:full":"Honeywell Nursery Close, Bradley Stafford Staffordshire ST18 9EN",
    "addr:postcode":"st18 9en",
    "addr:street":"Nursery Close",
    "iso:country":"GB",
    "sg:address":"Honeywell Nursery Close, Bradley",
    "sg:city":"Stafford",
    "sg:classifiers":[
        {
            "category":"Building & Trades",
            "subcategory":"Construction",
            "type":"Services"
        }
    ],
    "sg:phone":"+44 1785 780200",
    "sg:postcode":"ST18 9EN",
    "sg:province":"Staffordshire",
    "sg:tags":[
        "contractor",
        "paving",
        "driveway"
    ],
    "wof:name":"Hartshorne Landscapes",
    "wof:placetype":"venue"
},
  "geometry": {"coordinates":[-2.17981,52.757969],"type":"Point"}
}