{
  "type": "Feature",
  "properties": {
    "addr:full":"111 Sandigate Road Folkestone Kent CT20 2BL",
    "addr:housenumber":"111",
    "addr:postcode":"ct20 2bl",
    "addr:street":"Sandigate Road",
    "iso:country":"GB",
    "sg:address":"111 Sandigate Road",
    "sg:city":"Folkestone",
    "sg:classifiers":[
        {
            "category":"Travel",
            "subcategory":"Travel Agent",
            "type":"Entertainment"
        },
        {
            "category":"Shopping",
            "subcategory":"Bicycles & Sporting Goods",
            "type":"Retail Goods"
        },
        {
            "category":"Sports & Exercise",
            "subcategory":"Sports Center",
            "type":"Entertainment"
        }
    ],
    "sg:phone":"+44 1303 257511",
    "sg:postcode":"CT20 2BL",
    "sg:province":"Kent",
    "sg:tags":[
        "shop",
        "sale"
    ],
    "wof:name":"Landau Travel Ltd.",
    "wof:placetype":"venue"
},
  "geometry": {"coordinates":[1.176222,51.077763],"type":"Point"}
}