{
  "type": "Feature",
  "properties": {
    "addr:full":"The Wood Yard, New Inn Lane Stoke-on-trent Staffordshire ST4 8EX",
    "addr:postcode":"st4 8ex",
    "addr:street":"New Inn Lane",
    "iso:country":"GB",
    "sg:address":"The Wood Yard, New Inn Lane",
    "sg:city":"Stoke-on-trent",
    "sg:classifiers":[
        {
            "category":"Home & Garden",
            "subcategory":"Building Materials",
            "type":"Retail Goods"
        }
    ],
    "sg:phone":"+44 1782 658669",
    "sg:postcode":"ST4 8EX",
    "sg:province":"Staffordshire",
    "sg:tags":[
        "fencing"
    ],
    "wof:name":"A & D Sanders Bros",
    "wof:placetype":"venue"
},
  "geometry": {"coordinates":[-2.19421,52.973961],"type":"Point"}
}