{
  "type": "Feature",
  "properties": {
    "addr:full":"12 Calverley Grove Leeds West Yorkshire LS13 3LH",
    "addr:housenumber":"12",
    "addr:postcode":"ls13 3lh",
    "addr:street":"Calverley Grove",
    "iso:country":"GB",
    "sg:address":"12 Calverley Grove",
    "sg:city":"Leeds",
    "sg:classifiers":[
        {
            "category":"Banks & Credit Unions",
            "subcategory":"Financial Services",
            "type":"Services"
        }
    ],
    "sg:phone":"+44 113 257 5949",
    "sg:postcode":"LS13 3LH",
    "sg:province":"West Yorkshire",
    "sg:tags":[
        "adviser"
    ],
    "wof:name":"Personal & Corporate Planning",
    "wof:placetype":"venue"
},
  "geometry": {"coordinates":[-1.6431200504,53.8135719299],"type":"Point"}
}