{
  "type": "Feature",
  "properties": {
    "addr:full":"Wilton Road, Humberstone Grimsby Lincolnshire DN36 4AW",
    "addr:postcode":"dn36 4aw",
    "addr:street":"Wilton Road",
    "iso:country":"GB",
    "sg:address":"Wilton Road, Humberstone",
    "sg:city":"Grimsby",
    "sg:classifiers":[
        {
            "category":"Shopping",
            "subcategory":"Gifts & Souvenirs",
            "type":"Retail Goods"
        }
    ],
    "sg:phone":"+44 1472 811123",
    "sg:postcode":"DN36 4AW",
    "sg:province":"Lincolnshire",
    "sg:tags":[
        "window",
        "leaded"
    ],
    "wof:name":"Duralead",
    "wof:placetype":"venue"
},
  "geometry": {"coordinates":[-0.0466170013,53.5354614258],"type":"Point"}
}