{
  "type": "Feature",
  "properties": {
    "iso:country":"GB",
    "sg:address":"164 St Ediths Marsh, Bromham",
    "sg:city":"Chippenham",
    "sg:classifiers":[
        {
            "category":"Government",
            "subcategory":"Fire Station",
            "type":"Public Place"
        }
    ],
    "sg:postcode":"SN15 2DG",
    "sg:province":"Wiltshire",
    "sg:tags":[
        "security"
    ],
    "wof:name":"Moonraker Fire Protection",
    "wof:placetype":"venue"
},
  "geometry": {"coordinates":[-2.055822,51.385551],"type":"Point"}
}