{
  "type": "Feature",
  "properties": {
    "iso:country":"GB",
    "sg:address":"23 Pond Street",
    "sg:city":"London",
    "sg:classifiers":[
        {
            "category":"Shopping",
            "subcategory":"Books",
            "type":"Retail Goods"
        }
    ],
    "sg:phone":"+44 20 7431 4422",
    "sg:postcode":"NW3 2PN",
    "sg:province":"Greater London",
    "wof:name":"Yale University Press London",
    "wof:placetype":"venue"
},
  "geometry": {"coordinates":[-0.1668680012,51.5539588928],"type":"Point"}
}