{
  "type": "Feature",
  "properties": {
    "addr:full":"149 High St, Barking Side Ilford Essex IG6 2AJ",
    "addr:housenumber":"149",
    "addr:postcode":"ig6 2aj",
    "addr:street":"High St",
    "iso:country":"GB",
    "sg:address":"149 High St, Barking Side",
    "sg:city":"Ilford",
    "sg:classifiers":[
        {
            "category":"Shopping",
            "subcategory":"Thrift Store",
            "type":"Retail Goods"
        }
    ],
    "sg:phone":"+44 20 8551 2049",
    "sg:postcode":"IG6 2AJ",
    "sg:province":"Essex",
    "sg:tags":[
        "shop",
        "charity"
    ],
    "wof:name":"Norwood Ravenswood Charity Shop",
    "wof:placetype":"venue"
},
  "geometry": {"coordinates":[0.083877,51.59264],"type":"Point"}
}