{
  "type": "Feature",
  "properties": {
    "addr:full":"177 Drury Lane London Greater London WC2B 5QF",
    "addr:housenumber":"177",
    "addr:postcode":"wc2b 5qf",
    "addr:street":"Drury Lane",
    "iso:country":"GB",
    "sg:address":"177 Drury Lane",
    "sg:city":"London",
    "sg:classifiers":[
        {
            "category":"Personal",
            "subcategory":"Barber",
            "type":"Services"
        }
    ],
    "sg:phone":"+44 20 7831 6116",
    "sg:postcode":"WC2B 5QF",
    "sg:province":"Greater London",
    "sg:tags":[
        "men's",
        "hairdresser"
    ],
    "wof:name":"Super Cuts",
    "wof:placetype":"venue"
},
  "geometry": {"coordinates":[-0.123539,51.515598],"type":"Point"}
}