{
  "type": "Feature",
  "properties": {
    "iso:country":"GB",
    "sg:address":"34 Harbour Street",
    "sg:city":"Ramsgate",
    "sg:classifiers":[
        {
            "category":"Shopping",
            "type":"Retail Goods"
        }
    ],
    "sg:phone":"+44 1843 852752",
    "sg:postcode":"CT11 8HA",
    "sg:province":"Kent",
    "sg:tags":[
        "shop",
        "new age"
    ],
    "wof:name":"Eastern Clothing Co",
    "wof:placetype":"venue"
},
  "geometry": {"coordinates":[1.4206559658,51.3327713013],"type":"Point"}
}