{
  "type": "Feature",
  "properties": {
    "addr:full":"Gillingham Dam Beccles Norfolk NR34 0EB",
    "addr:postcode":"nr34 0eb",
    "iso:country":"GB",
    "sg:address":"Gillingham Dam",
    "sg:city":"Beccles",
    "sg:classifiers":[
        {
            "category":"Recreation",
            "subcategory":"Boat Charter",
            "type":"Entertainment"
        }
    ],
    "sg:phone":"+44 1502 712166",
    "sg:postcode":"NR34 0EB",
    "sg:province":"Norfolk",
    "sg:tags":[
        "excursion"
    ],
    "wof:name":"H E Hipperson Ltd.",
    "wof:placetype":"venue"
},
  "geometry": {"coordinates":[1.561573,52.46386],"type":"Point"}
}