{
  "type": "Feature",
  "properties": {
    "iso:country":"GB",
    "sg:address":"Kuoni House, Deepdene Avenue",
    "sg:city":"Dorking",
    "sg:classifiers":[
        {
            "category":"Recreation",
            "subcategory":"Gun Range",
            "type":"Entertainment"
        }
    ],
    "sg:phone":"+44 1306 740888",
    "sg:postcode":"RH5 4AZ",
    "sg:province":"Surrey",
    "sg:tags":[
        "operator",
        "tour"
    ],
    "wof:name":"Kuoni (U K) Ltd.",
    "wof:placetype":"venue"
},
  "geometry": {"coordinates":[-0.322214,51.234825],"type":"Point"}
}