{
  "type": "Feature",
  "properties": {
    "iso:country":"GB",
    "sg:address":"Longbrook Lane, Lympstone",
    "sg:city":"Exmouth",
    "sg:classifiers":[
        {
            "category":"Farming",
            "subcategory":"Poultry Farm",
            "type":"Manufacturing & Wholesale Goods"
        }
    ],
    "sg:postcode":"EX8 5BE",
    "sg:province":"Devon",
    "wof:name":"Bond Lane Farm Ltd.",
    "wof:placetype":"venue"
},
  "geometry": {"coordinates":[-3.417639,50.649639],"type":"Point"}
}