{
  "type": "Feature",
  "properties": {
    "iso:country":"GB",
    "sg:address":"8 Lidgett Lane, Garforth",
    "sg:city":"Leeds",
    "sg:classifiers":[
        {
            "category":"Health Services",
            "subcategory":"Health Practitioner",
            "type":"Services"
        }
    ],
    "sg:phone":"+44 113 286 8999",
    "sg:postcode":"LS25 1EQ",
    "sg:province":"North Yorkshire",
    "sg:tags":[
        "hypnotherapists"
    ],
    "wof:name":"Hypnotherapy Centre Leeds",
    "wof:placetype":"venue"
},
  "geometry": {"coordinates":[-1.388736,53.791653],"type":"Point"}
}