{
  "type": "Feature",
  "properties": {
    "addr:full":"Vicount Court, Station Road, Brize-norton Carterton Gloucestershire OX18 3PR",
    "addr:postcode":"ox18 3pr",
    "addr:street":"Station Road",
    "iso:country":"GB",
    "sg:address":"Vicount Court, Station Road, Brize-norton",
    "sg:city":"Carterton",
    "sg:classifiers":[
        {
            "category":"Wholesale",
            "subcategory":"Construction Materials",
            "type":"Manufacturing & Wholesale Goods"
        }
    ],
    "sg:phone":"+44 1993 851433",
    "sg:postcode":"OX18 3PR",
    "sg:province":"Gloucestershire",
    "sg:tags":[
        "merchant",
        "stone"
    ],
    "wof:name":"Conlon J & P Ltd.",
    "wof:placetype":"venue"
},
  "geometry": {"coordinates":[-1.5660640001,51.7650985718],"type":"Point"}
}