{
  "type": "Feature",
  "properties": {
    "addr:full":"7 Market Street Stafford Staffordshire ST16 2JZ",
    "addr:housenumber":"7",
    "addr:postcode":"st16 2jz",
    "addr:street":"Market Street",
    "iso:country":"GB",
    "sg:address":"7 Market Street",
    "sg:city":"Stafford",
    "sg:classifiers":[
        {
            "category":"Banks & Credit Unions",
            "subcategory":"Financial Services",
            "type":"Services"
        }
    ],
    "sg:phone":"+44 1784 257857",
    "sg:postcode":"ST16 2JZ",
    "sg:province":"Staffordshire",
    "sg:tags":[
        "agent",
        "tied"
    ],
    "wof:name":"Nicolsons Financial Management Ltd.",
    "wof:placetype":"venue"
},
  "geometry": {"coordinates":[-2.1160600185,52.8075637817],"type":"Point"}
}