{
  "type": "Feature",
  "properties": {
    "addr:full":"123 Netherton Road Worksop Nottinghamshire S80 2SA",
    "addr:housenumber":"123",
    "addr:postcode":"s80 2sa",
    "addr:street":"Netherton Road",
    "iso:country":"GB",
    "sg:address":"123 Netherton Road",
    "sg:city":"Worksop",
    "sg:classifiers":[
        {
            "category":"Shopping",
            "subcategory":"Antiques",
            "type":"Retail Goods"
        }
    ],
    "sg:postcode":"S80 2SA",
    "sg:province":"Nottinghamshire",
    "wof:name":"John Sanderson Antiques",
    "wof:placetype":"venue"
},
  "geometry": {"coordinates":[-1.114838,53.297806],"type":"Point"}
}