{
  "type": "Feature",
  "properties": {
    "iso:country":"GB",
    "sg:address":"70 High St",
    "sg:city":"Alfreton",
    "sg:classifiers":[
        {
            "category":"Shopping",
            "subcategory":"Shoes",
            "type":"Retail Goods"
        }
    ],
    "sg:postcode":"DE55 7BE",
    "sg:province":"Derbyshire",
    "sg:tags":[
        "shop"
    ],
    "wof:name":"Sugg,Gordon,",
    "wof:placetype":"venue"
},
  "geometry": {"coordinates":[-1.387133956,53.0974617004],"type":"Point"}
}