{
  "type": "Feature",
  "properties": {
    "iso:country":"GB",
    "sg:address":"91a Bale Road",
    "sg:city":"London",
    "sg:classifiers":[
        {
            "category":"Shopping",
            "subcategory":"Clothing, Apparel, & Fashions",
            "type":"Retail Goods"
        }
    ],
    "sg:phone":"+44 20 8802 1188",
    "sg:postcode":"N4 1TG",
    "sg:province":"Greater London",
    "sg:tags":[
        "clothing",
        "fabric"
    ],
    "wof:name":"Abbey Designs Ltd.",
    "wof:placetype":"venue"
},
  "geometry": {"coordinates":[-0.09216,51.57481],"type":"Point"}
}