{
  "type": "Feature",
  "properties": {
    "addr:full":"Antron Hill Farm, Antron Hill Penryn Cornwall TR10 9HH",
    "addr:postcode":"tr10 9hh",
    "addr:street":"Antron Hill;Antron Hill",
    "iso:country":"GB",
    "sg:address":"Antron Hill Farm, Antron Hill",
    "sg:city":"Penryn",
    "sg:classifiers":[
        {
            "category":"Freight",
            "type":"Transportation"
        }
    ],
    "sg:phone":"+44 1326 373565",
    "sg:postcode":"TR10 9HH",
    "sg:province":"Cornwall",
    "sg:tags":[
        "haulage",
        "road"
    ],
    "wof:name":"Sid Knowles Ltd.",
    "wof:placetype":"venue"
},
  "geometry": {"coordinates":[-5.1357140541,50.1642532349],"type":"Point"}
}