{
  "type": "Feature",
  "properties": {
    "iso:country":"GB",
    "sg:address":"Market Square",
    "sg:city":"London",
    "sg:classifiers":[
        {
            "category":"Shopping",
            "subcategory":"Shoes",
            "type":"Retail Goods"
        }
    ],
    "sg:phone":"+44 20 7538 2930",
    "sg:postcode":"E14 6AQ",
    "sg:province":"Greater London",
    "wof:name":"Well Heeled",
    "wof:placetype":"venue"
},
  "geometry": {"coordinates":[-0.0144990003,51.5126266479],"type":"Point"}
}