{
  "type": "Feature",
  "properties": {
    "addr:full":"27a High Street Thames Ditton Surrey KT7 0SD",
    "addr:housenumber":"27a",
    "addr:postcode":"kt7 0sd",
    "addr:street":"High Street",
    "iso:country":"GB",
    "sg:address":"27a High Street",
    "sg:city":"Thames Ditton",
    "sg:classifiers":[
        {
            "category":"Professional",
            "subcategory":"Computer Services",
            "type":"Services"
        }
    ],
    "sg:phone":"+44 20 8224 6444",
    "sg:postcode":"KT7 0SD",
    "sg:province":"Surrey",
    "sg:tags":[
        "consultant"
    ],
    "wof:name":"Computer Gym (Uk) Ltd.",
    "wof:placetype":"venue"
},
  "geometry": {"coordinates":[-0.3337849975,51.3903465271],"type":"Point"}
}