{
  "type": "Feature",
  "properties": {
    "addr:full":"5 Frimley Road Camberley Berkshire GU15 3EN",
    "addr:housenumber":"5",
    "addr:postcode":"gu15 3en",
    "addr:street":"Frimley Road",
    "iso:country":"GB",
    "sg:address":"5 Frimley Road",
    "sg:city":"Camberley",
    "sg:classifiers":[
        {
            "category":"Shopping",
            "subcategory":"News",
            "type":"Retail Goods"
        },
        {
            "category":"Food & Beverages",
            "subcategory":"Groceries & Convenience Stores",
            "type":"Retail Goods"
        }
    ],
    "sg:phone":"+44 1276 21915",
    "sg:postcode":"GU15 3EN",
    "sg:province":"Berkshire",
    "sg:tags":[
        "newsagent"
    ],
    "wof:name":"SIOBHAN MCILFATRICK",
    "wof:placetype":"venue"
},
  "geometry": {"coordinates":[-0.760446012,51.3357543945],"type":"Point"}
}