{
  "type": "Feature",
  "properties": {
    "addr:full":"4 Old Cross Hertford Hertfordshire SG14 1RB",
    "addr:housenumber":"4",
    "addr:postcode":"sg14 1rb",
    "addr:street":"Old Cross",
    "iso:country":"GB",
    "sg:address":"4 Old Cross",
    "sg:city":"Hertford",
    "sg:classifiers":[
        {
            "category":"Professional",
            "subcategory":"Lawyer & Legal Services",
            "type":"Services"
        }
    ],
    "sg:phone":"+44 1992 589439",
    "sg:postcode":"SG14 1RB",
    "sg:province":"Hertfordshire",
    "sg:tags":[
        "advice",
        "counselling"
    ],
    "wof:name":"Hertford Natural Therapy Centre",
    "wof:placetype":"venue"
},
  "geometry": {"coordinates":[-0.0803759992,51.7970657349],"type":"Point"}
}