{
  "type": "Feature",
  "properties": {
    "addr:full":"Kingsley Road Peterborough Cambridgeshire PE1 5JS",
    "addr:postcode":"pe1 5js",
    "addr:street":"Kingsley Road",
    "iso:country":"GB",
    "sg:address":"Kingsley Road",
    "sg:city":"Peterborough",
    "sg:classifiers":[
        {
            "category":"Education",
            "subcategory":"School",
            "type":"Public Place"
        }
    ],
    "sg:phone":"+44 1733 566847",
    "sg:postcode":"PE1 5JS",
    "sg:province":"Cambridgeshire",
    "sg:tags":[
        "local",
        "authority"
    ],
    "wof:name":"Abbotsmede Primary & Nursery School",
    "wof:placetype":"venue"
},
  "geometry": {"coordinates":[-0.227474004,52.5807991028],"type":"Point"}
}