{
  "type": "Feature",
  "properties": {
    "iso:country":"GB",
    "sg:address":"Buxton Road",
    "sg:city":"Macclesfield",
    "sg:classifiers":[
        {
            "category":"Bars & Pubs",
            "type":"Food & Drink"
        }
    ],
    "sg:postcode":"SK10 1NG",
    "sg:province":"Cheshire",
    "sg:tags":[
        "pubs",
        "inn"
    ],
    "wof:name":"The Bridgewater Arms",
    "wof:placetype":"venue"
},
  "geometry": {"coordinates":[-2.118974,53.259666],"type":"Point"}
}