{
  "type": "Feature",
  "properties": {
    "iso:country":"GB",
    "sg:address":"Perranwell Station",
    "sg:city":"Truro",
    "sg:classifiers":[
        {
            "category":"Building & Trades",
            "subcategory":"Construction",
            "type":"Services"
        }
    ],
    "sg:phone":"+44 1872 863501",
    "sg:postcode":"TR3 7LG",
    "sg:province":"Cornwall",
    "sg:tags":[
        "platform",
        "work",
        "scaffolding"
    ],
    "wof:name":"Initial Deborah Services",
    "wof:placetype":"venue"
},
  "geometry": {"coordinates":[-5.1189599037,50.2128295898],"type":"Point"}
}