{
  "type": "Feature",
  "properties": {
    "addr:full":"3 Haven Rd Canvey Island Essex SS8 0LU",
    "addr:housenumber":"3",
    "addr:postcode":"ss8 0lu",
    "addr:street":"Haven Rd",
    "iso:country":"GB",
    "sg:address":"3 Haven Rd",
    "sg:city":"Canvey Island",
    "sg:classifiers":[
        {
            "category":"Professional",
            "subcategory":"Management & Consulting",
            "type":"Services"
        }
    ],
    "sg:phone":"+44 1268 697555",
    "sg:postcode":"SS8 0LU",
    "sg:province":"Essex",
    "sg:tags":[
        "sport"
    ],
    "wof:name":"P.R.G Golf Promotions",
    "wof:placetype":"venue"
},
  "geometry": {"coordinates":[0.5643919706,51.5196342468],"type":"Point"}
}