{
  "type": "Feature",
  "properties": {
    "addr:full":"17 Lillie Rd Fulham Greater London SW6 1UE",
    "addr:housenumber":"17",
    "addr:postcode":"sw6 1ue",
    "addr:street":"Lillie Rd",
    "iso:country":"GB",
    "sg:address":"17 Lillie Rd",
    "sg:city":"Fulham",
    "sg:classifiers":[
        {
            "category":"Retail",
            "subcategory":"Auto Repair",
            "type":"Services"
        }
    ],
    "sg:phone":"+44 20 7381 1500",
    "sg:postcode":"SW6 1UE",
    "sg:province":"Greater London",
    "sg:tags":[
        "car",
        "specialist",
        "customizing"
    ],
    "wof:name":"Hamann Motor Sport UK Ltd",
    "wof:placetype":"venue"
},
  "geometry": {"coordinates":[-0.197268,51.486786],"type":"Point"}
}