{
  "type": "Feature",
  "properties": {
    "iso:country":"GB",
    "sg:address":"195 Errwood Rd",
    "sg:city":"Manchester",
    "sg:classifiers":[
        {
            "category":"Food & Beverages",
            "subcategory":"Supermarket",
            "type":"Retail Goods"
        }
    ],
    "sg:phone":"+44 161 443 2777",
    "sg:postcode":"M19 1JB",
    "sg:province":"Greater Manchester",
    "wof:name":"Cellar One",
    "wof:placetype":"venue"
},
  "geometry": {"coordinates":[-2.1966710091,53.4287719727],"type":"Point"}
}