{
  "type": "Feature",
  "properties": {
    "addr:full":"Municipal Building, Boscawen Street Truro Cornwall TR1 2NE",
    "addr:postcode":"tr1 2ne",
    "addr:street":"Boscawen Street",
    "iso:country":"GB",
    "sg:address":"Municipal Building, Boscawen Street",
    "sg:city":"Truro",
    "sg:classifiers":[
        {
            "category":"Government",
            "subcategory":"Office",
            "type":"Public Place"
        }
    ],
    "sg:phone":"+44 1872 274766",
    "sg:postcode":"TR1 2NE",
    "sg:province":"Cornwall",
    "sg:tags":[
        "local"
    ],
    "wof:name":"Truro City Council",
    "wof:placetype":"venue"
},
  "geometry": {"coordinates":[-5.053631,50.26524],"type":"Point"}
}