{
  "type": "Feature",
  "properties": {
    "iso:country":"GB",
    "sg:address":"261 Broadwater Crescent",
    "sg:city":"Stevenage",
    "sg:classifiers":[
        {
            "category":"Fast Food",
            "type":"Food & Drink"
        }
    ],
    "sg:phone":"+44 1438 311226",
    "sg:postcode":"SG2 8ET",
    "sg:province":"Hertfordshire",
    "sg:tags":[
        "away",
        "take"
    ],
    "wof:name":"Dilraj Tandoori",
    "wof:placetype":"venue"
},
  "geometry": {"coordinates":[-0.1785269976,51.881603241],"type":"Point"}
}