{
  "type": "Feature",
  "properties": {
    "addr:full":"103 Hednesford Road, Heath Hayes Cannock Staffordshire WS12 3HL",
    "addr:housenumber":"103",
    "addr:postcode":"ws12 3hl",
    "addr:street":"Hednesford Road",
    "iso:country":"GB",
    "sg:address":"103 Hednesford Road, Heath Hayes",
    "sg:city":"Cannock",
    "sg:classifiers":[
        {
            "category":"Shopping",
            "subcategory":"Pets & Pet Supplies",
            "type":"Retail Goods"
        }
    ],
    "sg:phone":"+44 1543 279147",
    "sg:postcode":"WS12 3HL",
    "sg:province":"Staffordshire",
    "sg:tags":[
        "food"
    ],
    "wof:name":"Paws & Claws",
    "wof:placetype":"venue"
},
  "geometry": {"coordinates":[-1.9802399874,52.6884307861],"type":"Point"}
}