{
  "type": "Feature",
  "properties": {
    "addr:full":"Unit 1, Ainscough Business Park Wigan Lancashire WN6 9RS",
    "addr:housenumber":"unit 1",
    "addr:postcode":"wn6 9rs",
    "addr:street":"Ainscough Business Park",
    "iso:country":"GB",
    "sg:address":"Unit 1, Ainscough Business Park",
    "sg:city":"Wigan",
    "sg:classifiers":[
        {
            "category":"Building & Trades",
            "subcategory":"Equipment Rental",
            "type":"Services"
        }
    ],
    "sg:phone":"+44 1257 425718",
    "sg:postcode":"WN6 9RS",
    "sg:province":"Lancashire",
    "sg:tags":[
        "hire",
        "centre"
    ],
    "wof:name":"S J S Hire Tools Ltd.",
    "wof:placetype":"venue"
},
  "geometry": {"coordinates":[-2.69585,53.591019],"type":"Point"}
}