{
  "type": "Feature",
  "properties": {
    "addr:full":"Tindle Enterprise Centre, 37a West St Farnham Surrey GU9 7DR",
    "addr:housenumber":"37a",
    "addr:postcode":"gu9 7dr",
    "addr:street":"West St",
    "iso:country":"GB",
    "sg:address":"Tindle Enterprise Centre, 37a West St",
    "sg:city":"Farnham",
    "sg:classifiers":[
        {
            "category":"Professional",
            "type":"Services"
        }
    ],
    "sg:phone":"+44 1252 723052",
    "sg:postcode":"GU9 7DR",
    "sg:province":"Surrey",
    "sg:tags":[
        "interior",
        "furnishers",
        "designer"
    ],
    "wof:name":"Spatial Design Studio The",
    "wof:placetype":"venue"
},
  "geometry": {"coordinates":[-0.8008369803,51.2143211365],"type":"Point"}
}