{
  "type": "Feature",
  "properties": {
    "addr:full":"118 High St Stockton On Tees Durham TS18 1AY",
    "addr:housenumber":"118",
    "addr:postcode":"ts18 1ay",
    "addr:street":"High St",
    "iso:country":"GB",
    "sg:address":"118 High St",
    "sg:city":"Stockton On Tees",
    "sg:classifiers":[
        {
            "category":"Shopping",
            "subcategory":"Music",
            "type":"Retail Goods"
        }
    ],
    "sg:phone":"+44 1642 608147",
    "sg:postcode":"TS18 1AY",
    "sg:province":"Durham",
    "sg:tags":[
        "shop"
    ],
    "wof:name":"Music Box",
    "wof:placetype":"venue"
},
  "geometry": {"coordinates":[-1.313271,54.564674],"type":"Point"}
}