{
  "type": "Feature",
  "properties": {
    "addr:full":"12 Adelaide Street Coventry West Midlands CV1 5GT",
    "addr:housenumber":"12",
    "addr:postcode":"cv1 5gt",
    "addr:street":"Adelaide Street",
    "iso:country":"GB",
    "sg:address":"12 Adelaide Street",
    "sg:city":"Coventry",
    "sg:classifiers":[
        {
            "category":"Organizations",
            "subcategory":"Non-profit Organization",
            "type":"Services"
        }
    ],
    "sg:postcode":"CV1 5GT",
    "sg:province":"West Midlands",
    "sg:tags":[
        "organisation",
        "voluntary",
        "charity"
    ],
    "wof:name":"Coventry & Warwickshire Community Safety Scheme",
    "wof:placetype":"venue"
},
  "geometry": {"coordinates":[-1.5004689693,52.4148788452],"type":"Point"}
}