{
  "type": "Feature",
  "properties": {
    "iso:country":"GB",
    "sg:address":"Town Hill",
    "sg:city":"Warrington",
    "sg:classifiers":[
        {
            "category":"Banks & Credit Unions",
            "subcategory":"Bank",
            "type":"Services"
        }
    ],
    "sg:phone":"+44 845 300 0000",
    "sg:postcode":"WA1 2LP",
    "sg:province":"Cheshire",
    "sg:tags":[
        "financial",
        "institution"
    ],
    "wof:name":"Lloyds T S B Bank Plc",
    "wof:placetype":"venue"
},
  "geometry": {"coordinates":[-2.593259,53.390125],"type":"Point"}
}