{
  "type": "Feature",
  "properties": {
    "iso:country":"GB",
    "sg:address":"14 The Swan Centre, Rosemary Road",
    "sg:city":"London",
    "sg:classifiers":[
        {
            "category":"Building & Trades",
            "subcategory":"Equipment Rental",
            "type":"Services"
        }
    ],
    "sg:phone":"+44 20 8944 7222",
    "sg:postcode":"SW17 0AR",
    "sg:province":"Greater London",
    "sg:tags":[
        "hire",
        "centre"
    ],
    "wof:name":"Tool Services Ltd.",
    "wof:placetype":"venue"
},
  "geometry": {"coordinates":[-0.1884,51.433651],"type":"Point"}
}