{
  "type": "Feature",
  "properties": {
    "iso:country":"GB",
    "sg:address":"Headland Farm, Amblestone",
    "sg:city":"Haverfordwest",
    "sg:classifiers":[
        {
            "category":"Building & Trades",
            "subcategory":"Equipment Rental",
            "type":"Services"
        },
        {
            "category":"Farming",
            "subcategory":"Farm",
            "type":"Manufacturing & Wholesale Goods"
        }
    ],
    "sg:postcode":"SA62 5QX",
    "sg:province":"Pembrokeshire",
    "sg:tags":[
        "mixed",
        "plant",
        "machinery",
        "crop"
    ],
    "wof:name":"Belton,J M,",
    "wof:placetype":"venue"
},
  "geometry": {"coordinates":[-4.9065737724,51.8950386047],"type":"Point"}
}