{
  "type": "Feature",
  "properties": {
    "iso:country":"GB",
    "sg:address":"36 Ombersley Close, Woodrow South",
    "sg:city":"Redditch",
    "sg:classifiers":[
        {
            "category":"Retail",
            "subcategory":"Driving School",
            "type":"Services"
        },
        {
            "category":"Education",
            "subcategory":"School",
            "type":"Public Place"
        }
    ],
    "sg:phone":"+44 1527 527923",
    "sg:postcode":"B98 7UU",
    "sg:province":"Warwickshire",
    "sg:tags":[
        "local",
        "authority"
    ],
    "wof:name":"J W A School Of Motoring",
    "wof:placetype":"venue"
},
  "geometry": {"coordinates":[-1.9133169651,52.2855262756],"type":"Point"}
}