{
  "type": "Feature",
  "properties": {
    "addr:full":"1 Scheregate Colchester Essex CO2 7AS",
    "addr:housenumber":"1",
    "addr:postcode":"co2 7as",
    "addr:street":"Scheregate Colchester",
    "iso:country":"GB",
    "sg:address":"1 Scheregate",
    "sg:city":"Colchester",
    "sg:classifiers":[
        {
            "category":"Organizations",
            "subcategory":"Non-profit Organization",
            "type":"Services"
        }
    ],
    "sg:phone":"+44 1206 768341",
    "sg:postcode":"CO2 7AS",
    "sg:province":"Essex",
    "sg:tags":[
        "organisation",
        "voluntary",
        "charity"
    ],
    "wof:name":"British Heart Foundation",
    "wof:placetype":"venue"
},
  "geometry": {"coordinates":[0.908010006,51.8775482178],"type":"Point"}
}