{
  "type": "Feature",
  "properties": {
    "iso:country":"GB",
    "sg:address":"The Manor Drive",
    "sg:city":"Worcester Park",
    "sg:classifiers":[
        {
            "category":"Education",
            "subcategory":"School",
            "type":"Public Place"
        }
    ],
    "sg:phone":"+44 20 8337 4804",
    "sg:postcode":"KT4 7LW",
    "sg:province":"Surrey",
    "sg:tags":[
        "local",
        "authority"
    ],
    "wof:name":"Malden Parochial Primary School",
    "wof:placetype":"venue"
},
  "geometry": {"coordinates":[-0.252559,51.381073],"type":"Point"}
}