{
  "type": "Feature",
  "properties": {
    "addr:full":"10 Buckingham Place London Greater London SW1E 6HX",
    "addr:housenumber":"10",
    "addr:postcode":"sw1e 6hx",
    "addr:street":"Buckingham Place",
    "iso:country":"GB",
    "sg:address":"10 Buckingham Place",
    "sg:city":"London",
    "sg:classifiers":[
        {
            "category":"Organizations",
            "subcategory":"Non-profit Organization",
            "type":"Services"
        }
    ],
    "sg:phone":"+44 20 7821 2828",
    "sg:postcode":"SW1E 6HX",
    "sg:province":"Greater London",
    "sg:tags":[
        "organisation",
        "voluntary",
        "charity"
    ],
    "wof:name":"The Lord's Taverners Ltd.",
    "wof:placetype":"venue"
},
  "geometry": {"coordinates":[-0.14061,51.498917],"type":"Point"}
}