{
  "type": "Feature",
  "properties": {
    "addr:full":"Holly Lodge Southampton Hampshire SO32 3NB",
    "addr:postcode":"hampshire so32 3nb",
    "iso:country":"GB",
    "sg:address":"Holly Lodge",
    "sg:city":"Southampton",
    "sg:classifiers":[
        {
            "category":"Professional",
            "type":"Services"
        }
    ],
    "sg:phone":"+44 1489 877156",
    "sg:postcode":"SO32 3NB",
    "sg:province":"Hampshire",
    "sg:tags":[
        "marine"
    ],
    "wof:name":"European Marine Consultants",
    "wof:placetype":"venue"
},
  "geometry": {"coordinates":[-1.1369290352,50.9613189697],"type":"Point"}
}