{
  "type": "Feature",
  "properties": {
    "addr:full":"12 Cedar Avenue Rhyl Conwy LL18 4JS",
    "addr:housenumber":"12",
    "addr:postcode":"ll18 4js",
    "addr:street":"Cedar Avenue",
    "iso:country":"GB",
    "sg:address":"12 Cedar Avenue",
    "sg:city":"Rhyl",
    "sg:classifiers":[
        {
            "category":"Manufacturing",
            "subcategory":"Petroleum Products",
            "type":"Manufacturing & Wholesale Goods"
        }
    ],
    "sg:postcode":"LL18 4JS",
    "sg:province":"Conwy",
    "sg:tags":[
        "double",
        "glazing"
    ],
    "wof:name":"Sunray Doors & Windows",
    "wof:placetype":"venue"
},
  "geometry": {"coordinates":[-3.4670689106,53.3194503784],"type":"Point"}
}