{
  "type": "Feature",
  "properties": {
    "addr:full":"Ayres Road, Off Warwick Road South, Old Trafford Manchester Cheshire M16 0WU",
    "addr:postcode":"m16 0wu",
    "addr:street":"Ayres Road Off Warwick Road South",
    "iso:country":"GB",
    "sg:address":"Ayres Road, Off Warwick Road South, Old Trafford",
    "sg:city":"Manchester",
    "sg:classifiers":[
        {
            "category":"Professional",
            "subcategory":"Engineering",
            "type":"Services"
        }
    ],
    "sg:phone":"+44 161 848 7777",
    "sg:postcode":"M16 0WU",
    "sg:province":"Cheshire",
    "wof:name":"Phillips & Sons (Manchester) Ltd.",
    "wof:placetype":"venue"
},
  "geometry": {"coordinates":[-2.2756540775,53.457244873],"type":"Point"}
}