{
  "type": "Feature",
  "properties": {
    "addr:full":"103 Howbury Street Bedford Bedfordshire MK40 3QT",
    "addr:housenumber":"103",
    "addr:postcode":"mk40 3qt",
    "addr:street":"Howbury Street",
    "iso:country":"GB",
    "sg:address":"103 Howbury Street",
    "sg:city":"Bedford",
    "sg:classifiers":[
        {
            "category":"Retail",
            "subcategory":"Repair Shop",
            "type":"Services"
        }
    ],
    "sg:postcode":"MK40 3QT",
    "sg:province":"Bedfordshire",
    "sg:tags":[
        "maintenance"
    ],
    "wof:name":"R T Darlow",
    "wof:placetype":"venue"
},
  "geometry": {"coordinates":[-0.454774,52.138031],"type":"Point"}
}