{
  "type": "Feature",
  "properties": {
    "iso:country":"GB",
    "sg:address":"68 Austin Street",
    "sg:city":"Ipswich",
    "sg:classifiers":[
        {
            "category":"Organizations",
            "subcategory":"Membership Organization",
            "type":"Services"
        }
    ],
    "sg:phone":"+44 1473 688847",
    "sg:postcode":"IP2 8DF",
    "sg:province":"Suffolk",
    "sg:tags":[
        "club"
    ],
    "wof:name":"Bridge Ward Conservative Club",
    "wof:placetype":"venue"
},
  "geometry": {"coordinates":[1.154542,52.049229],"type":"Point"}
}