{
  "type": "Feature",
  "properties": {
    "addr:full":"4 Sandy Close, Bollington Macclesfield Cheshire SK11 8BY",
    "addr:housenumber":"4",
    "addr:postcode":"sk11 8by",
    "addr:street":"Sandy Close",
    "iso:country":"GB",
    "sg:address":"4 Sandy Close, Bollington",
    "sg:city":"Macclesfield",
    "sg:classifiers":[
        {
            "category":"Building & Trades",
            "subcategory":"Construction",
            "type":"Services"
        }
    ],
    "sg:postcode":"SK11 8BY",
    "sg:province":"Cheshire",
    "sg:tags":[
        "dry",
        "lining",
        "plasterers",
        "screeders"
    ],
    "wof:name":"Cleaver & Holmers",
    "wof:placetype":"venue"
},
  "geometry": {"coordinates":[-2.125756,53.255669],"type":"Point"}
}