{
  "type": "Feature",
  "properties": {
    "addr:full":"Unit 7 Moorland Trading Estate, Metheringham Lincoln Lincolnshire LN4 3HX",
    "addr:housenumber":"unit 7;trading estate",
    "addr:postcode":"ln4 3hx",
    "iso:country":"GB",
    "sg:address":"Unit 7 Moorland Trading Estate, Metheringham",
    "sg:city":"Lincoln",
    "sg:classifiers":[
        {
            "category":"Home & Garden",
            "subcategory":"Hardware",
            "type":"Retail Goods"
        }
    ],
    "sg:phone":"+44 1526 323630",
    "sg:postcode":"LN4 3HX",
    "sg:province":"Lincolnshire",
    "sg:tags":[
        "generator"
    ],
    "wof:name":"Tru-Gen Ltd.",
    "wof:placetype":"venue"
},
  "geometry": {"coordinates":[-0.4050700068,53.1418952942],"type":"Point"}
}