{
  "type": "Feature",
  "properties": {
    "addr:full":"Tegryn Garage, Tegryn Llanfyrnach Carmarthenshire SA35 0BL",
    "addr:postcode":"sa35 0bl",
    "iso:country":"GB",
    "sg:address":"Tegryn Garage, Tegryn",
    "sg:city":"Llanfyrnach",
    "sg:classifiers":[
        {
            "category":"Retail",
            "subcategory":"Auto Repair",
            "type":"Services"
        }
    ],
    "sg:phone":"+44 1239 698202",
    "sg:postcode":"SA35 0BL",
    "sg:province":"Carmarthenshire",
    "sg:tags":[
        "modification",
        "garage"
    ],
    "wof:name":"T J Morgan & Son",
    "wof:placetype":"venue"
},
  "geometry": {"coordinates":[-4.589888,51.951145],"type":"Point"}
}