{
  "type": "Feature",
  "properties": {
    "addr:full":"4 Boar Lane Stockton-on-tees Durham TS17 0RX",
    "addr:housenumber":"4",
    "addr:postcode":"ts17 0rx",
    "addr:street":"Boar Lane",
    "iso:country":"GB",
    "sg:address":"4 Boar Lane",
    "sg:city":"Stockton-on-tees",
    "sg:classifiers":[
        {
            "category":"Building & Trades",
            "subcategory":"Landscaping Services",
            "type":"Services"
        }
    ],
    "sg:phone":"+44 1642 769833",
    "sg:postcode":"TS17 0RX",
    "sg:province":"Durham",
    "sg:tags":[
        "gardening"
    ],
    "wof:name":"E J Garden Services",
    "wof:placetype":"venue"
},
  "geometry": {"coordinates":[-1.3041100502,54.5234298706],"type":"Point"}
}