{
  "type": "Feature",
  "properties": {
    "iso:country":"GB",
    "sg:address":"20 Cross Street, Enderby",
    "sg:city":"Leicester",
    "sg:classifiers":[
        {
            "category":"Shopping",
            "subcategory":"Crafts & Fabrics",
            "type":"Retail Goods"
        }
    ],
    "sg:postcode":"LE19 4NJ",
    "sg:province":"Leicestershire",
    "sg:tags":[
        "brush"
    ],
    "wof:name":"W S Brookes & Co. Ltd.",
    "wof:placetype":"venue"
},
  "geometry": {"coordinates":[-1.2098749876,52.588924408],"type":"Point"}
}