{
  "type": "Feature",
  "properties": {
    "addr:full":"23 Christchurch Drive, Blackwater Camberley Hampshire GU17 0HG",
    "addr:housenumber":"23",
    "addr:postcode":"gu17 0hg",
    "addr:street":"Christchurch Drive",
    "iso:country":"GB",
    "sg:address":"23 Christchurch Drive, Blackwater",
    "sg:city":"Camberley",
    "sg:classifiers":[
        {
            "category":"Building & Trades",
            "subcategory":"Construction",
            "type":"Services"
        },
        {
            "category":"Military Area",
            "subcategory":"Air Force Base",
            "type":"Public Place"
        }
    ],
    "sg:phone":"+44 1252 654427",
    "sg:postcode":"GU17 0HG",
    "sg:province":"Hampshire",
    "sg:tags":[
        "groundwork",
        "excavation",
        "contractor"
    ],
    "wof:name":"V Cumber",
    "wof:placetype":"venue"
},
  "geometry": {"coordinates":[-0.7891280055,51.337436676],"type":"Point"}
}