{
  "type": "Feature",
  "properties": {
    "iso:country":"GB",
    "sg:address":"A458, Trewern",
    "sg:city":"Welshpool",
    "sg:classifiers":[
        {
            "category":"Restaurant",
            "type":"Food & Drink"
        }
    ],
    "sg:phone":"+44 1938 570344",
    "sg:postcode":"SY21 8SZ",
    "sg:province":"Shropshire",
    "wof:name":"Little Chef",
    "wof:placetype":"venue"
},
  "geometry": {"coordinates":[-3.148608,52.649891],"type":"Point"}
}