{
  "type": "Feature",
  "properties": {
    "addr:full":"3 Hall Lane Prescot Merseyside L34 5UN",
    "addr:housenumber":"3",
    "addr:postcode":"l34 5un",
    "addr:street":"Hall Lane",
    "iso:country":"GB",
    "sg:address":"3 Hall Lane",
    "sg:city":"Prescot",
    "sg:classifiers":[
        {
            "category":"Shopping",
            "type":"Retail Goods"
        }
    ],
    "sg:phone":"+44 151 430 0088",
    "sg:postcode":"L34 5UN",
    "sg:province":"Merseyside",
    "sg:tags":[
        "part",
        "accessory"
    ],
    "wof:name":"K L S",
    "wof:placetype":"venue"
},
  "geometry": {"coordinates":[-2.8025679588,53.4227752686],"type":"Point"}
}