{
  "type": "Feature",
  "properties": {
    "iso:country":"GB",
    "sg:address":"7 Castle Parade",
    "sg:city":"Bournemouth",
    "sg:classifiers":[
        {
            "category":"Recreation",
            "subcategory":"Fishing",
            "type":"Entertainment"
        }
    ],
    "sg:phone":"+44 1202 480520",
    "sg:postcode":"BH7 6SH",
    "sg:province":"Dorset",
    "sg:tags":[
        "equipment",
        "angling"
    ],
    "wof:name":"Christchurch Angling Centre",
    "wof:placetype":"venue"
},
  "geometry": {"coordinates":[-1.809234,50.740444],"type":"Point"}
}