{
  "type": "Feature",
  "properties": {
    "iso:country":"GB",
    "sg:address":"Unit B 5 Seedbed Centre, Davidson Way",
    "sg:city":"Romford",
    "sg:classifiers":[
        {
            "category":"Professional",
            "subcategory":"Employment Agencies",
            "type":"Services"
        }
    ],
    "sg:phone":"+44 1708 728653",
    "sg:postcode":"RM7 0AZ",
    "sg:province":"Essex",
    "sg:tags":[
        "consultant"
    ],
    "wof:name":"Securicor Recruitment Services",
    "wof:placetype":"venue"
},
  "geometry": {"coordinates":[0.18427,51.570179],"type":"Point"}
}