{
  "type": "Feature",
  "properties": {
    "iso:country":"GB",
    "sg:address":"Grafton Lodge Lane, Grafton",
    "sg:city":"York",
    "sg:classifiers":[
        {
            "category":"Farming",
            "subcategory":"Farm",
            "type":"Manufacturing & Wholesale Goods"
        }
    ],
    "sg:phone":"+44 1423 322100",
    "sg:postcode":"YO51 9QS",
    "sg:province":"North Yorkshire",
    "sg:tags":[
        "mixed",
        "crop"
    ],
    "wof:name":"R K Hird",
    "wof:placetype":"venue"
},
  "geometry": {"coordinates":[-1.382321,54.078217],"type":"Point"}
}