{
  "type": "Feature",
  "properties": {
    "addr:full":"1 Marine Parade Great Yarmouth Norfolk NR30 3AG",
    "addr:housenumber":"1",
    "addr:postcode":"nr30 3ag",
    "addr:street":"Marine Parade",
    "iso:country":"GB",
    "sg:address":"1 Marine Parade",
    "sg:city":"Great Yarmouth",
    "sg:classifiers":[
        {
            "category":"Travel",
            "subcategory":"Hotels & Motels",
            "type":"Entertainment"
        }
    ],
    "sg:phone":"+44 1493 855551",
    "sg:postcode":"NR30 3AG",
    "sg:province":"Norfolk",
    "wof:name":"The Hotel Elizabeth",
    "wof:placetype":"venue"
},
  "geometry": {"coordinates":[1.735978,52.600704],"type":"Point"}
}