{
  "type": "Feature",
  "properties": {
    "addr:full":"Gateside Works, Barrhead Glasgow East Ayrshire G78 1TP",
    "addr:postcode":"g78 1tp",
    "iso:country":"GB",
    "sg:address":"Gateside Works, Barrhead",
    "sg:city":"Glasgow",
    "sg:classifiers":[
        {
            "category":"Retail",
            "subcategory":"Auto Repair",
            "type":"Services"
        }
    ],
    "sg:phone":"+44 141 881 5559",
    "sg:postcode":"G78 1TP",
    "sg:province":"East Ayrshire",
    "sg:tags":[
        "modification",
        "garage"
    ],
    "wof:name":"Eagle Motor Services",
    "wof:placetype":"venue"
},
  "geometry": {"coordinates":[-4.404498,55.795315],"type":"Point"}
}