{
  "type": "Feature",
  "properties": {
    "iso:country":"GB",
    "sg:address":"38 Moulton Street",
    "sg:city":"Manchester",
    "sg:classifiers":[
        {
            "category":"Manufacturing",
            "subcategory":"Jewelry",
            "type":"Manufacturing & Wholesale Goods"
        },
        {
            "category":"Shopping",
            "subcategory":"Comic Books",
            "type":"Retail Goods"
        }
    ],
    "sg:phone":"+44 161 832 7363",
    "sg:postcode":"M8 8FQ",
    "sg:province":"Greater Manchester",
    "sg:tags":[
        "manufacture",
        "repair",
        "jeweller",
        "jewellery"
    ],
    "wof:name":"Seven Sisters",
    "wof:placetype":"venue"
},
  "geometry": {"coordinates":[-2.2508289814,53.4943313599],"type":"Point"}
}