{
  "type": "Feature",
  "properties": {
    "iso:country":"GB",
    "sg:address":"John St Industrial Estate, Blantyre",
    "sg:city":"Glasgow",
    "sg:classifiers":[
        {
            "category":"Building & Trades",
            "subcategory":"Landscaping Services",
            "type":"Services"
        }
    ],
    "sg:phone":"+44 1698 829950",
    "sg:postcode":"G72 0JG",
    "sg:province":"South Lanarkshire",
    "sg:tags":[
        "gardening",
        "landscape",
        "contractor"
    ],
    "wof:name":"GARDEN SERVICES BLANTYRE",
    "wof:placetype":"venue"
},
  "geometry": {"coordinates":[-4.0849728584,55.7935752869],"type":"Point"}
}