{
  "type": "Feature",
  "properties": {
    "iso:country":"GB",
    "sg:address":"Vere Rd",
    "sg:city":"Lanark",
    "sg:classifiers":[
        {
            "category":"Government",
            "subcategory":"Police Station",
            "type":"Public Place"
        }
    ],
    "sg:phone":"+44 1555 662455",
    "sg:postcode":"ML11 9RP",
    "sg:province":"South Lanarkshire",
    "sg:tags":[
        "support"
    ],
    "wof:name":"Strathclyde Police",
    "wof:placetype":"venue"
},
  "geometry": {"coordinates":[-3.781384,55.673866],"type":"Point"}
}