{
  "type": "Feature",
  "properties": {
    "iso:country":"GB",
    "sg:address":"129b Mary Street",
    "sg:city":"Scunthorpe",
    "sg:classifiers":[
        {
            "category":"Banks & Credit Unions",
            "subcategory":"Financial Services",
            "type":"Services"
        }
    ],
    "sg:postcode":"DN15 7PX",
    "sg:province":"Lincolnshire",
    "sg:tags":[
        "adviser"
    ],
    "wof:name":"Chapterhouse",
    "wof:placetype":"venue"
},
  "geometry": {"coordinates":[-0.655638,53.589935],"type":"Point"}
}