{
  "type": "Feature",
  "properties": {
    "addr:full":"14 Berkswell Close, Clee View Dudley West Midlands DY1 2GH",
    "addr:housenumber":"14",
    "addr:postcode":"dy1 2gh",
    "addr:street":"Berkswell Close Clee View",
    "iso:country":"GB",
    "sg:address":"14 Berkswell Close, Clee View",
    "sg:city":"Dudley",
    "sg:classifiers":[
        {
            "category":"Building & Trades",
            "subcategory":"Construction",
            "type":"Services"
        }
    ],
    "sg:phone":"+44 1384 234917",
    "sg:postcode":"DY1 2GH",
    "sg:province":"West Midlands",
    "sg:tags":[
        "roofing"
    ],
    "wof:name":"W M Builders",
    "wof:placetype":"venue"
},
  "geometry": {"coordinates":[-2.115617,52.520248],"type":"Point"}
}