{
  "type": "Feature",
  "properties": {
    "addr:full":"Pyleigh House Farm, Lydeard St Lawrence Taunton Devon TA4 3QZ",
    "addr:postcode":"ta4 3qz",
    "addr:street":"Lydeard St",
    "iso:country":"GB",
    "sg:address":"Pyleigh House Farm, Lydeard St Lawrence",
    "sg:city":"Taunton",
    "sg:classifiers":[
        {
            "category":"Farming",
            "subcategory":"Dairy Farm",
            "type":"Manufacturing & Wholesale Goods"
        }
    ],
    "sg:phone":"+44 1984 667223",
    "sg:postcode":"TA4 3QZ",
    "sg:province":"Devon",
    "wof:name":"William Henry Blake",
    "wof:placetype":"venue"
},
  "geometry": {"coordinates":[-3.241672039,51.0799598694],"type":"Point"}
}