{
  "type": "Feature",
  "properties": {
    "iso:country":"GB",
    "sg:address":"Sand Street",
    "sg:city":"Pwllheli",
    "sg:classifiers":[
        {
            "category":"Manufacturing",
            "subcategory":"Glass & Minerals",
            "type":"Manufacturing & Wholesale Goods"
        }
    ],
    "sg:postcode":"LL53 5ES",
    "sg:province":"Gwynedd",
    "sg:tags":[
        "chalk",
        "stone",
        "slate"
    ],
    "wof:name":"John Williams & Co.",
    "wof:placetype":"venue"
},
  "geometry": {"coordinates":[-4.413864,52.891045],"type":"Point"}
}