{
  "type": "Feature",
  "properties": {
    "iso:country":"GB",
    "sg:address":"94 Riversdale Road",
    "sg:city":"London",
    "sg:classifiers":[
        {
            "category":"Retail",
            "subcategory":"Laundry & Dry Cleaning",
            "type":"Services"
        }
    ],
    "sg:postcode":"N5 2JZ",
    "sg:province":"Greater London",
    "sg:tags":[
        "launderette"
    ],
    "wof:name":"Riversdale Launderette",
    "wof:placetype":"venue"
},
  "geometry": {"coordinates":[-0.09303,51.560612],"type":"Point"}
}