{
  "type": "Feature",
  "properties": {
    "addr:full":"107 Kensington Church Street London Greater London W8 7LN",
    "addr:housenumber":"107",
    "addr:postcode":"w8 7ln",
    "addr:street":"Kensington Church Street",
    "iso:country":"GB",
    "sg:address":"107 Kensington Church Street",
    "sg:city":"London",
    "sg:classifiers":[
        {
            "category":"Shopping",
            "subcategory":"Antiques",
            "type":"Retail Goods"
        }
    ],
    "sg:phone":"+44 20 7727 8737",
    "sg:postcode":"W8 7LN",
    "sg:province":"Greater London",
    "wof:name":"Gary Atkins",
    "wof:placetype":"venue"
},
  "geometry": {"coordinates":[-0.1949889958,51.5080490112],"type":"Point"}
}