{
  "type": "Feature",
  "properties": {
    "iso:country":"GB",
    "sg:address":"Margaret St",
    "sg:city":"Dunmow",
    "sg:classifiers":[
        {
            "category":"Health Services",
            "subcategory":"Doctor",
            "type":"Services"
        }
    ],
    "sg:phone":"+44 1371 830213",
    "sg:postcode":"CM6 2QN",
    "sg:province":"Essex",
    "sg:tags":[
        "practitioners"
    ],
    "wof:name":"Surgery The",
    "wof:placetype":"venue"
},
  "geometry": {"coordinates":[0.34212,51.95504],"type":"Point"}
}