{
  "type": "Feature",
  "properties": {
    "iso:country":"GB",
    "sg:address":"38 Southfield Road",
    "sg:city":"High Wycombe",
    "sg:classifiers":[
        {
            "category":"Shopping",
            "subcategory":"Pharmacy",
            "type":"Retail Goods"
        }
    ],
    "sg:postcode":"HP13 5LA",
    "sg:province":"Buckinghamshire",
    "sg:tags":[
        "medicine",
        "therapy"
    ],
    "wof:name":"Karen Orchard",
    "wof:placetype":"venue"
},
  "geometry": {"coordinates":[-0.77676,51.639938],"type":"Point"}
}