{
  "type": "Feature",
  "properties": {
    "iso:country":"GB",
    "sg:address":"Unity Chambers, 34 High East Street",
    "sg:city":"Dorchester",
    "sg:classifiers":[
        {
            "category":"Autos & Motor Vehicles",
            "subcategory":"Automobile Sales",
            "type":"Retail Goods"
        }
    ],
    "sg:postcode":"DT1 1HA",
    "sg:province":"Dorset",
    "sg:tags":[
        "commercial"
    ],
    "wof:name":"Vincent,David,Ltd",
    "wof:placetype":"venue"
},
  "geometry": {"coordinates":[-2.441564,50.711906],"type":"Point"}
}