{
  "type": "Feature",
  "properties": {
    "addr:full":"23 Fore Street, Kingskerswell Newton Abbot Devon TQ12 5HT",
    "addr:housenumber":"23",
    "addr:postcode":"tq12 5ht",
    "addr:street":"Fore Street",
    "iso:country":"GB",
    "sg:address":"23 Fore Street, Kingskerswell",
    "sg:city":"Newton Abbot",
    "sg:classifiers":[
        {
            "category":"Shopping",
            "subcategory":"Pharmacy",
            "type":"Retail Goods"
        }
    ],
    "sg:postcode":"TQ12 5HT",
    "sg:province":"Devon",
    "sg:tags":[
        "pharmacist",
        "chemist"
    ],
    "wof:name":"Manor Pharmacy",
    "wof:placetype":"venue"
},
  "geometry": {"coordinates":[-3.5809700489,50.4990005493],"type":"Point"}
}