{
  "type": "Feature",
  "properties": {
    "iso:country":"GB",
    "sg:address":"Rectory Rd",
    "sg:city":"Manor Park",
    "sg:classifiers":[
        {
            "category":"Education",
            "subcategory":"School",
            "type":"Public Place"
        }
    ],
    "sg:phone":"+44 20 8514 7180",
    "sg:postcode":"E12 6JB",
    "sg:province":"Greater London",
    "sg:tags":[
        "local",
        "authority"
    ],
    "wof:name":"Little Ilford Community Education Centre",
    "wof:placetype":"venue"
},
  "geometry": {"coordinates":[0.05258,51.55241],"type":"Point"}
}