{
  "type": "Feature",
  "properties": {
    "iso:country":"GB",
    "sg:address":"Gylven Garage, Top Road",
    "sg:city":"Salisbury",
    "sg:classifiers":[
        {
            "category":"Retail",
            "subcategory":"Auto Repair",
            "type":"Services"
        }
    ],
    "sg:phone":"+44 1722 780241",
    "sg:postcode":"SP5 5JP",
    "sg:province":"Dorset",
    "sg:tags":[
        "modification",
        "garage"
    ],
    "wof:name":"A M Booth",
    "wof:placetype":"venue"
},
  "geometry": {"coordinates":[-2.01417,51.018871],"type":"Point"}
}