{
  "type": "Feature",
  "properties": {
    "addr:full":"Salmon Fields, Royton Oldham Lancashire OL2 6JG",
    "addr:postcode":"ol2 6jg",
    "addr:street":"Salmon Fields",
    "iso:country":"GB",
    "sg:address":"Salmon Fields, Royton",
    "sg:city":"Oldham",
    "sg:classifiers":[
        {
            "category":"Banks & Credit Unions",
            "subcategory":"Investment Brokerage",
            "type":"Services"
        },
        {
            "category":"Manufacturing",
            "subcategory":"Building Materials",
            "type":"Manufacturing & Wholesale Goods"
        }
    ],
    "sg:phone":"+44 161 627 4222",
    "sg:postcode":"OL2 6JG",
    "sg:province":"Lancashire",
    "sg:tags":[
        "extruders",
        "extrusion",
        "plastic"
    ],
    "wof:name":"Quantum Profile Systems Ltd.",
    "wof:placetype":"venue"
},
  "geometry": {"coordinates":[-2.118579,53.561794],"type":"Point"}
}