{
  "type": "Feature",
  "properties": {
    "iso:country":"GB",
    "sg:address":"Unit 3, Claylands Road, Bishops Waltham",
    "sg:city":"Southampton",
    "sg:classifiers":[
        {
            "category":"Retail",
            "subcategory":"Repair Shop",
            "type":"Services"
        }
    ],
    "sg:phone":"+44 1489 896836",
    "sg:postcode":"SO32 1BH",
    "sg:province":"Hampshire",
    "sg:tags":[
        "upholsterer"
    ],
    "wof:name":"Newveck Upholstery",
    "wof:placetype":"venue"
},
  "geometry": {"coordinates":[-1.2214750051,50.9577522278],"type":"Point"}
}