{
  "type": "Feature",
  "properties": {
    "addr:full":"Manor Street Falkirk Falkirk FK1 1NH",
    "addr:postcode":"fk1 1nh",
    "addr:street":"Manor Street",
    "iso:country":"GB",
    "sg:address":"Manor Street",
    "sg:city":"Falkirk",
    "sg:classifiers":[
        {
            "category":"Bars & Pubs",
            "type":"Food & Drink"
        }
    ],
    "sg:phone":"+44 1324 612282",
    "sg:postcode":"FK1 1NH",
    "sg:province":"Falkirk",
    "sg:tags":[
        "pubs",
        "inn"
    ],
    "wof:name":"Aitkens Bar",
    "wof:placetype":"venue"
},
  "geometry": {"coordinates":[-3.784096,55.99979],"type":"Point"}
}