{
  "type": "Feature",
  "properties": {
    "iso:country":"GB",
    "sg:address":"39 London Rd",
    "sg:city":"Reading",
    "sg:classifiers":[
        {
            "category":"Health Services",
            "subcategory":"Dentist",
            "type":"Services"
        }
    ],
    "sg:phone":"+44 118 950 9977",
    "sg:postcode":"RG1 5BL",
    "sg:province":"Berkshire",
    "sg:tags":[
        "technician",
        "instrument",
        "dental"
    ],
    "wof:name":"Heald Prosthetics",
    "wof:placetype":"venue"
},
  "geometry": {"coordinates":[-0.964957,51.450855],"type":"Point"}
}