{
  "type": "Feature",
  "properties": {
    "addr:full":"6 The Link Mall Nottingham Nottinghamshire NG1 3PR",
    "addr:housenumber":"6",
    "addr:postcode":"ng1 3pr",
    "addr:street":"The Link Mall",
    "iso:country":"GB",
    "sg:address":"6 The Link Mall",
    "sg:city":"Nottingham",
    "sg:classifiers":[
        {
            "category":"Shopping",
            "subcategory":"Department Store",
            "type":"Retail Goods"
        }
    ],
    "sg:phone":"+44 115 941 8487",
    "sg:postcode":"NG1 3PR",
    "sg:province":"Nottinghamshire",
    "wof:name":"Gemini Jewellers",
    "wof:placetype":"venue"
},
  "geometry": {"coordinates":[-1.14647,52.956451],"type":"Point"}
}