{
  "type": "Feature",
  "properties": {
    "iso:country":"GB",
    "sg:address":"341 Regents Park Road",
    "sg:city":"London",
    "sg:classifiers":[
        {
            "category":"Real Estate",
            "subcategory":"Real Estate Agent",
            "type":"Services"
        }
    ],
    "sg:phone":"+44 20 8349 3131",
    "sg:postcode":"N3 1DP",
    "sg:province":"Greater London",
    "wof:name":"Legal & General Estate Agency",
    "wof:placetype":"venue"
},
  "geometry": {"coordinates":[-0.195727,51.599873],"type":"Point"}
}