{
  "type": "Feature",
  "properties": {
    "iso:country":"GB",
    "sg:address":"406 Clayhall Avenue",
    "sg:city":"Ilford",
    "sg:classifiers":[
        {
            "category":"Organizations",
            "subcategory":"Community Association",
            "type":"Services"
        }
    ],
    "sg:phone":"+44 20 8551 2400",
    "sg:postcode":"IG5 0TA",
    "sg:province":"Essex",
    "sg:tags":[
        "society",
        "housing"
    ],
    "wof:name":"Birchwood Home for the Elderly",
    "wof:placetype":"venue"
},
  "geometry": {"coordinates":[0.069885,51.591133],"type":"Point"}
}