{
  "type": "Feature",
  "properties": {
    "addr:full":"Hastingwood Trading Est, Harbet Rd Upper Edmonton Greater London N18 3LP",
    "addr:postcode":"n18 3lp",
    "addr:street":"Harbet Rd",
    "iso:country":"GB",
    "sg:address":"Hastingwood Trading Est, Harbet Rd",
    "sg:city":"Upper Edmonton",
    "sg:classifiers":[
        {
            "category":"Shopping",
            "type":"Retail Goods"
        }
    ],
    "sg:phone":"+44 20 8887 0011",
    "sg:postcode":"N18 3LP",
    "sg:province":"Greater London",
    "sg:tags":[
        "part",
        "accessory"
    ],
    "wof:name":"Japeuro Car Parts Ltd",
    "wof:placetype":"venue"
},
  "geometry": {"coordinates":[-0.0423,51.61327],"type":"Point"}
}