{
  "type": "Feature",
  "properties": {
    "addr:full":"Edithfield Yard, Newmill Road, Newmill Industrial Estate Keith Moray AB55 5BT",
    "addr:postcode":"ab55 5bt",
    "addr:street":"Newmill Road Newmill Industrial Estate",
    "iso:country":"GB",
    "sg:address":"Edithfield Yard, Newmill Road, Newmill Industrial Estate",
    "sg:city":"Keith",
    "sg:classifiers":[
        {
            "category":"Manufacturing",
            "subcategory":"Building Materials",
            "type":"Manufacturing & Wholesale Goods"
        }
    ],
    "sg:phone":"+44 1542 886222",
    "sg:postcode":"AB55 5BT",
    "sg:province":"Moray",
    "sg:tags":[
        "merchant",
        "builder"
    ],
    "wof:name":"Kbm (1988) Ltd.",
    "wof:placetype":"venue"
},
  "geometry": {"coordinates":[-2.9504199028,57.5432357788],"type":"Point"}
}