{
  "type": "Feature",
  "properties": {
    "addr:full":"32 Waterside Street Strathaven South Lanarkshire ML10 6AW",
    "addr:housenumber":"32",
    "addr:postcode":"ml10 6aw",
    "addr:street":"Waterside Street",
    "iso:country":"GB",
    "sg:address":"32 Waterside Street",
    "sg:city":"Strathaven",
    "sg:classifiers":[
        {
            "category":"Shopping",
            "subcategory":"Crafts & Fabrics",
            "type":"Retail Goods"
        }
    ],
    "sg:postcode":"ML10 6AW",
    "sg:province":"South Lanarkshire",
    "sg:tags":[
        "material",
        "art"
    ],
    "wof:name":"The Craft Bench",
    "wof:placetype":"venue"
},
  "geometry": {"coordinates":[-4.0646238327,55.6772918701],"type":"Point"}
}