{
  "type": "Feature",
  "properties": {
    "iso:country":"GB",
    "sg:address":"48 High Street",
    "sg:city":"Lymington",
    "sg:classifiers":[
        {
            "category":"Professional",
            "subcategory":"Lawyer & Legal Services",
            "type":"Services"
        }
    ],
    "sg:postcode":"SO41 9ZQ",
    "sg:province":"Hampshire",
    "sg:tags":[
        "solicitor"
    ],
    "wof:name":"Moore & Blatch",
    "wof:placetype":"venue"
},
  "geometry": {"coordinates":[-1.544869,50.757393],"type":"Point"}
}