{
  "type": "Feature",
  "properties": {
    "addr:full":"Ochil House, Springkerse Business Park Stirling Falkirk FK7 7XE",
    "addr:postcode":"fk7 7xe",
    "addr:street":"Springkerse Business Park",
    "iso:country":"GB",
    "sg:address":"Ochil House, Springkerse Business Park",
    "sg:city":"Stirling",
    "sg:classifiers":[
        {
            "category":"Wholesale",
            "subcategory":"Books, Periodicals, & Newspapers",
            "type":"Manufacturing & Wholesale Goods"
        }
    ],
    "sg:phone":"+44 1786 407000",
    "sg:postcode":"FK7 7XE",
    "sg:province":"Falkirk",
    "sg:tags":[
        "publishing"
    ],
    "wof:name":"The Endat Group Ltd.",
    "wof:placetype":"venue"
},
  "geometry": {"coordinates":[-3.9105439186,56.1175804138],"type":"Point"}
}