{
  "type": "Feature",
  "properties": {
    "addr:full":"Lakewood Ho, Horndon Business Pk, West Horndon Brentwood Essex CM13 3XL",
    "addr:postcode":"cm13 3xl",
    "addr:street":"Business Pk West Horndon",
    "iso:country":"GB",
    "sg:address":"Lakewood Ho, Horndon Business Pk, West Horndon",
    "sg:city":"Brentwood",
    "sg:classifiers":[
        {
            "category":"Retail",
            "subcategory":"Laundry & Dry Cleaning",
            "type":"Services"
        }
    ],
    "sg:postcode":"CM13 3XL",
    "sg:province":"Essex",
    "sg:tags":[
        "alteration"
    ],
    "wof:name":"Brummer,Christine,",
    "wof:placetype":"venue"
},
  "geometry": {"coordinates":[0.3428199887,51.5689239502],"type":"Point"}
}