{
  "type": "Feature",
  "properties": {
    "addr:full":"268 Bradford Road Batley West Yorkshire WF17 6JD",
    "addr:housenumber":"268",
    "addr:postcode":"wf17 6jd",
    "addr:street":"Bradford Road",
    "iso:country":"GB",
    "sg:address":"268 Bradford Road",
    "sg:city":"Batley",
    "sg:classifiers":[
        {
            "category":"Restaurant",
            "type":"Food & Drink"
        }
    ],
    "sg:phone":"+44 1924 422202",
    "sg:postcode":"WF17 6JD",
    "sg:province":"West Yorkshire",
    "sg:tags":[
        "indian",
        "-"
    ],
    "sg:website":"http://www.oasisrestaurant.co.uk",
    "wof:name":"Oasis Indian Restaurant",
    "wof:placetype":"venue"
},
  "geometry": {"coordinates":[-1.6266800165,53.7068901062],"type":"Point"}
}