{
  "type": "Feature",
  "properties": {
    "addr:full":"The Rhiw, The Mkt Bridgend Bridgend CF31 1DL",
    "addr:postcode":"cf31 1dl",
    "iso:country":"GB",
    "sg:address":"The Rhiw, The Mkt",
    "sg:city":"Bridgend",
    "sg:classifiers":[
        {
            "category":"Farming",
            "subcategory":"Fish & Marine Products",
            "type":"Manufacturing & Wholesale Goods"
        }
    ],
    "sg:postcode":"CF31 1DL",
    "sg:province":"Bridgend",
    "sg:tags":[
        "fishmonger"
    ],
    "wof:name":"Huw's Plaice",
    "wof:placetype":"venue"
},
  "geometry": {"coordinates":[-3.5782630444,51.5088348389],"type":"Point"}
}