{
  "type": "Feature",
  "properties": {
    "addr:full":"31 Queen Street Horsham West Sussex RH13 5AA",
    "addr:housenumber":"31",
    "addr:postcode":"rh13 5aa",
    "addr:street":"Queen Street",
    "iso:country":"GB",
    "sg:address":"31 Queen Street",
    "sg:city":"Horsham",
    "sg:classifiers":[
        {
            "category":"Professional",
            "subcategory":"Computer Services",
            "type":"Services"
        }
    ],
    "sg:postcode":"RH13 5AA",
    "sg:province":"West Sussex",
    "sg:tags":[
        "system",
        "software"
    ],
    "wof:name":"L-Tech Computer Services Ltd",
    "wof:placetype":"venue"
},
  "geometry": {"coordinates":[-0.3223640025,51.0604438782],"type":"Point"}
}