{
  "type": "Feature",
  "properties": {
    "addr:full":"The Gables  Banwell Rd, Hutton Weston-super-mare Somerset BS24 9TZ",
    "addr:postcode":"bs24 9tz",
    "addr:street":"Banwell Rd",
    "iso:country":"GB",
    "sg:address":"The Gables  Banwell Rd, Hutton",
    "sg:city":"Weston-super-mare",
    "sg:classifiers":[
        {
            "category":"Professional",
            "subcategory":"Management & Consulting",
            "type":"Services"
        }
    ],
    "sg:postcode":"BS24 9TZ",
    "sg:province":"Somerset",
    "sg:tags":[
        "consultant",
        "business"
    ],
    "wof:name":"Mainhood,David,",
    "wof:placetype":"venue"
},
  "geometry": {"coordinates":[-2.9285049438,51.3247108459],"type":"Point"}
}