{
  "type": "Feature",
  "properties": {
    "addr:full":"Blithbury Rugeley Staffordshire WS15 3JQ",
    "addr:postcode":"ws15 3jq",
    "iso:country":"GB",
    "sg:address":"Blithbury",
    "sg:city":"Rugeley",
    "sg:classifiers":[
        {
            "category":"Education",
            "subcategory":"Special Training",
            "type":"Public Place"
        }
    ],
    "sg:phone":"+44 1332 510951",
    "sg:postcode":"WS15 3JQ",
    "sg:province":"Staffordshire",
    "sg:tags":[
        "school"
    ],
    "wof:name":"Westwood School",
    "wof:placetype":"venue"
},
  "geometry": {"coordinates":[-1.87381,52.776691],"type":"Point"}
}