{
  "type": "Feature",
  "properties": {
    "addr:full":"1 Skyrmans Fee, Kirby Cross Frinton-on-sea Essex CO13 0RN",
    "addr:housenumber":"1",
    "addr:postcode":"co13 0rn",
    "addr:street":"Skyrmans Fee",
    "iso:country":"GB",
    "sg:address":"1 Skyrmans Fee, Kirby Cross",
    "sg:city":"Frinton-on-sea",
    "sg:classifiers":[
        {
            "category":"Organizations",
            "subcategory":"Non-profit Organization",
            "type":"Services"
        }
    ],
    "sg:postcode":"CO13 0RN",
    "sg:province":"Essex",
    "sg:tags":[
        "organisation",
        "voluntary",
        "charity"
    ],
    "wof:name":"Micro & Anophthalmic Childrens Society",
    "wof:placetype":"venue"
},
  "geometry": {"coordinates":[1.241114,51.840324],"type":"Point"}
}