{
  "type": "Feature",
  "properties": {
    "iso:country":"GB",
    "sg:address":"Victoria Road",
    "sg:city":"Mablethorpe",
    "sg:classifiers":[
        {
            "category":"Travel",
            "subcategory":"Hotels & Motels",
            "type":"Entertainment"
        }
    ],
    "sg:phone":"+44 1507 473611",
    "sg:postcode":"LN12 2AJ",
    "sg:province":"Lincolnshire",
    "wof:name":"Eagle Hotel",
    "wof:placetype":"venue"
},
  "geometry": {"coordinates":[0.264135,53.339127],"type":"Point"}
}