{
  "type": "Feature",
  "properties": {
    "iso:country":"GB",
    "sg:address":"Pleasant St",
    "sg:city":"Liverpool",
    "sg:classifiers":[
        {
            "category":"Education",
            "subcategory":"School",
            "type":"Public Place"
        }
    ],
    "sg:phone":"+44 151 709 3802",
    "sg:postcode":"L3 5TS",
    "sg:province":"Merseyside",
    "sg:tags":[
        "local",
        "authority"
    ],
    "wof:name":"Pleasant St J.M.I & Nursery",
    "wof:placetype":"venue"
},
  "geometry": {"coordinates":[-2.972563982,53.4047355652],"type":"Point"}
}