{
  "type": "Feature",
  "properties": {
    "iso:country":"GB",
    "sg:address":"Trowswell, Lovers Lane, Goudhurst",
    "sg:city":"Cranbrook",
    "sg:classifiers":[
        {
            "category":"Health Services",
            "subcategory":"Clinic",
            "type":"Services"
        }
    ],
    "sg:phone":"+44 1580 212340",
    "sg:postcode":"TN17 1JE",
    "sg:province":"Kent",
    "sg:tags":[
        "private"
    ],
    "wof:name":"Amanda Reuter",
    "wof:placetype":"venue"
},
  "geometry": {"coordinates":[0.458639,51.112839],"type":"Point"}
}