{
  "type": "Feature",
  "properties": {
    "addr:full":"Higher East Leigh, Modbury Ivybridge Devon PL21 0SH",
    "addr:postcode":"pl21 0sh",
    "addr:street":"East Leigh",
    "iso:country":"GB",
    "sg:address":"Higher East Leigh, Modbury",
    "sg:city":"Ivybridge",
    "sg:classifiers":[
        {
            "category":"Recreation",
            "subcategory":"Campground",
            "type":"Entertainment"
        }
    ],
    "sg:phone":"+44 1548 830714",
    "sg:postcode":"PL21 0SH",
    "sg:province":"Devon",
    "sg:tags":[
        "caravan",
        "park"
    ],
    "wof:name":"Broad Park Caravan Club Site",
    "wof:placetype":"venue"
},
  "geometry": {"coordinates":[-3.8878660202,50.3491783142],"type":"Point"}
}