{
  "type": "Feature",
  "properties": {
    "addr:full":"17 St Ebba Road Eyemouth Scottish Borders TD14 5AE",
    "addr:housenumber":"17",
    "addr:postcode":"td14 5ae",
    "addr:street":"St Ebba Road",
    "iso:country":"GB",
    "sg:address":"17 St Ebba Road",
    "sg:city":"Eyemouth",
    "sg:classifiers":[
        {
            "category":"Professional",
            "subcategory":"Engineering",
            "type":"Services"
        },
        {
            "category":"Building & Trades",
            "subcategory":"Electrical",
            "type":"Services"
        }
    ],
    "sg:phone":"+44 1890 750288",
    "sg:postcode":"TD14 5AE",
    "sg:province":"Scottish Borders",
    "sg:tags":[
        "engineer",
        "electrician",
        "contractor"
    ],
    "wof:name":"Stewart & Young",
    "wof:placetype":"venue"
},
  "geometry": {"coordinates":[-2.093603,55.871841],"type":"Point"}
}