{
  "type": "Feature",
  "properties": {
    "addr:full":"Heene Rd Worthing West Sussex BN11 4PL",
    "addr:postcode":"bn11 4pl",
    "addr:street":"Heene Rd",
    "iso:country":"GB",
    "sg:address":"Heene Rd",
    "sg:city":"Worthing",
    "sg:classifiers":[
        {
            "category":"Community Center",
            "type":"Public Place"
        }
    ],
    "sg:phone":"+44 1903 209997",
    "sg:postcode":"BN11 4PL",
    "sg:province":"West Sussex",
    "sg:tags":[
        "centre"
    ],
    "wof:name":"Heene Community Centre",
    "wof:placetype":"venue"
},
  "geometry": {"coordinates":[-0.386519,50.817936],"type":"Point"}
}