{
  "type": "Feature",
  "properties": {
    "iso:country":"GB",
    "sg:address":"Marsham St",
    "sg:city":"Maidstone",
    "sg:classifiers":[
        {
            "category":"Education",
            "subcategory":"Special Training",
            "type":"Public Place"
        }
    ],
    "sg:phone":"+44 1622 686428",
    "sg:postcode":"ME14 1HH",
    "sg:province":"Kent",
    "sg:tags":[
        "product",
        "centre"
    ],
    "wof:name":"Head Start",
    "wof:placetype":"venue"
},
  "geometry": {"coordinates":[0.5280900002,51.2743110657],"type":"Point"}
}