{
  "type": "Feature",
  "properties": {
    "addr:full":"Red Lion House, 229 Barton Street Gloucester Gloucestershire GL1 4JE",
    "addr:housenumber":"229",
    "addr:postcode":"gl1 4je",
    "addr:street":"Barton Street",
    "iso:country":"GB",
    "sg:address":"Red Lion House, 229 Barton Street",
    "sg:city":"Gloucester",
    "sg:classifiers":[
        {
            "category":"Building & Trades",
            "subcategory":"Construction",
            "type":"Services"
        }
    ],
    "sg:postcode":"GL1 4JE",
    "sg:province":"Gloucestershire",
    "sg:tags":[
        "builder"
    ],
    "wof:name":"Fine Homes Gloucester",
    "wof:placetype":"venue"
},
  "geometry": {"coordinates":[-2.2324309349,51.8580703735],"type":"Point"}
}