{
  "type": "Feature",
  "properties": {
    "iso:country":"GB",
    "sg:address":"21 Roundel Way, Marden",
    "sg:city":"Tonbridge",
    "sg:classifiers":[
        {
            "category":"Professional",
            "subcategory":"Employment Agencies",
            "type":"Services"
        }
    ],
    "sg:postcode":"TN12 9TW",
    "sg:province":"Kent",
    "sg:tags":[
        "consultant"
    ],
    "wof:name":"Timmax Recruitment Ltd",
    "wof:placetype":"venue"
},
  "geometry": {"coordinates":[0.496943,51.172009],"type":"Point"}
}