{
  "type": "Feature",
  "properties": {
    "iso:country":"GB",
    "sg:address":"Dowlais Court, 1a Vale Road, Splott",
    "sg:city":"Cardiff",
    "sg:classifiers":[
        {
            "category":"Building & Trades",
            "subcategory":"Construction",
            "type":"Services"
        }
    ],
    "sg:postcode":"CF24 2LS",
    "sg:province":"Cardiff",
    "sg:tags":[
        "builder"
    ],
    "wof:name":"Dineen Bros Ltd.",
    "wof:placetype":"venue"
},
  "geometry": {"coordinates":[-3.14741,51.48769],"type":"Point"}
}