{
  "type": "Feature",
  "properties": {
    "iso:country":"GB",
    "sg:address":"107 Manningham Lane",
    "sg:city":"Bradford",
    "sg:classifiers":[
        {
            "category":"Shopping",
            "subcategory":"Books",
            "type":"Retail Goods"
        }
    ],
    "sg:phone":"+44 1274 721871",
    "sg:postcode":"BD1 3BN",
    "sg:province":"West Yorkshire",
    "sg:tags":[
        "bookseller"
    ],
    "wof:name":"Books Asia",
    "wof:placetype":"venue"
},
  "geometry": {"coordinates":[-1.760382,53.801456],"type":"Point"}
}