{
  "type": "Feature",
  "properties": {
    "iso:country":"GB",
    "sg:address":"Waltons Garage, Walton-on-the-hill",
    "sg:city":"Stafford",
    "sg:classifiers":[
        {
            "category":"Retail",
            "subcategory":"Auto Rental",
            "type":"Services"
        }
    ],
    "sg:phone":"+44 1785 661293",
    "sg:postcode":"ST17 0JX",
    "sg:province":"Staffordshire",
    "sg:tags":[
        "car",
        "hire",
        "truck"
    ],
    "wof:name":"B C L Ltd",
    "wof:placetype":"venue"
},
  "geometry": {"coordinates":[-2.063894,52.788574],"type":"Point"}
}