{
  "type": "Feature",
  "properties": {
    "iso:country":"GB",
    "sg:address":"The Studio, Elmbank Shore Rd, Clynder",
    "sg:city":"Helensburgh",
    "sg:classifiers":[
        {
            "category":"Utilities",
            "type":"Services"
        }
    ],
    "sg:phone":"+44 1436 831633",
    "sg:postcode":"G84 0QD",
    "sg:province":"Argyll and Bute",
    "sg:tags":[
        "internet"
    ],
    "wof:name":"D.F.C Design",
    "wof:placetype":"venue"
},
  "geometry": {"coordinates":[-4.819619,56.02536],"type":"Point"}
}