{
  "type": "Feature",
  "properties": {
    "addr:full":"Unit 2 Northway House The Forum Cirencester Gloucestershire GL7 2QY",
    "addr:housenumber":"unit 2;the",
    "addr:postcode":"gl7 2qy",
    "addr:street":"Northway",
    "iso:country":"GB",
    "sg:address":"Unit 2 Northway House The Forum",
    "sg:city":"Cirencester",
    "sg:classifiers":[
        {
            "category":"Cinema",
            "subcategory":"Movie Rental",
            "type":"Entertainment"
        }
    ],
    "sg:phone":"+44 1285 655863",
    "sg:postcode":"GL7 2QY",
    "sg:province":"Gloucestershire",
    "sg:tags":[
        "video",
        "library"
    ],
    "wof:name":"Choices Video",
    "wof:placetype":"venue"
},
  "geometry": {"coordinates":[-1.953541,51.718548],"type":"Point"}
}