{
  "type": "Feature",
  "properties": {
    "iso:country":"GB",
    "sg:address":"14 Lawn Lane",
    "sg:city":"Hemel Hempstead",
    "sg:classifiers":[
        {
            "category":"Real Estate",
            "subcategory":"Real Estate Operator",
            "type":"Services"
        }
    ],
    "sg:postcode":"HP3 9HL",
    "sg:province":"Hertfordshire",
    "sg:tags":[
        "letting",
        "agent"
    ],
    "wof:name":"E C S Property Services",
    "wof:placetype":"venue"
},
  "geometry": {"coordinates":[-0.472295,51.745056],"type":"Point"}
}