{
  "type": "Feature",
  "properties": {
    "addr:full":"2 Llanwenarth Road, Govilon Abergavenny Herefordshire NP7 9PN",
    "addr:housenumber":"2",
    "addr:postcode":"np7 9pn",
    "addr:street":"Llanwenarth Road",
    "iso:country":"GB",
    "sg:address":"2 Llanwenarth Road, Govilon",
    "sg:city":"Abergavenny",
    "sg:classifiers":[
        {
            "category":"Home & Garden",
            "subcategory":"Home Furnishings",
            "type":"Retail Goods"
        },
        {
            "category":"Building & Trades",
            "subcategory":"Landfill",
            "type":"Services"
        }
    ],
    "sg:phone":"+44 1873 830112",
    "sg:postcode":"NP7 9PN",
    "sg:province":"Herefordshire",
    "sg:tags":[
        "blind",
        "awning",
        "canopy",
        "blinds"
    ],
    "wof:name":"EVERGREEN BLINDS",
    "wof:placetype":"venue"
},
  "geometry": {"coordinates":[-3.0622119904,51.818195343],"type":"Point"}
}