{
  "type": "Feature",
  "properties": {
    "iso:country":"GB",
    "sg:address":"6 Mill St, Aston",
    "sg:city":"Birmingham",
    "sg:classifiers":[
        {
            "category":"Professional",
            "subcategory":"Accounting & Tax Preparation",
            "type":"Services"
        }
    ],
    "sg:phone":"+44 121 359 5212",
    "sg:postcode":"B6 4BS",
    "sg:province":"West Midlands",
    "sg:tags":[
        "accountant"
    ],
    "wof:name":"Abacus Accountancy Services",
    "wof:placetype":"venue"
},
  "geometry": {"coordinates":[-1.891145,52.493481],"type":"Point"}
}