{
  "type": "Feature",
  "properties": {
    "iso:country":"GB",
    "sg:address":"Upper Deck Gore Lane",
    "sg:city":"Exmouth",
    "sg:classifiers":[
        {
            "category":"Shopping",
            "subcategory":"Computers & Home Electronics",
            "type":"Retail Goods"
        }
    ],
    "sg:phone":"+44 1395 222675",
    "sg:postcode":"EX8 5BZ",
    "sg:province":"Devon",
    "sg:tags":[
        "aerial",
        "television",
        "radio"
    ],
    "wof:name":"Apollo Aerials",
    "wof:placetype":"venue"
},
  "geometry": {"coordinates":[-3.413289,50.619415],"type":"Point"}
}