{
  "type": "Feature",
  "properties": {
    "addr:full":"225 Hagley Road Birmingham West Midlands B16 9RY",
    "addr:housenumber":"225",
    "addr:postcode":"b16 9ry",
    "addr:street":"Hagley Road",
    "iso:country":"GB",
    "sg:address":"225 Hagley Road",
    "sg:city":"Birmingham",
    "sg:classifiers":[
        {
            "category":"Travel",
            "subcategory":"Hotels & Motels",
            "type":"Entertainment"
        }
    ],
    "sg:phone":"+44 121 455 9777",
    "sg:postcode":"B16 9RY",
    "sg:province":"West Midlands",
    "wof:name":"Strathallan Thistle Hotel",
    "wof:placetype":"venue"
},
  "geometry": {"coordinates":[-1.9379980564,52.4721260071],"type":"Point"}
}