{
  "type": "Feature",
  "properties": {
    "iso:country":"GB",
    "sg:address":"12 Peterborough Rd, Rydes Hill",
    "sg:city":"Guildford",
    "sg:classifiers":[
        {
            "category":"Shopping",
            "subcategory":"Stationery & Office Supplies",
            "type":"Retail Goods"
        }
    ],
    "sg:phone":"+44 1483 560767",
    "sg:postcode":"GU2 9SY",
    "sg:province":"Surrey",
    "sg:tags":[
        "recording",
        "machine",
        "time"
    ],
    "wof:name":"James Fitzgerald C.M.B.H.I",
    "wof:placetype":"venue"
},
  "geometry": {"coordinates":[-0.600915,51.253235],"type":"Point"}
}