{
  "type": "Feature",
  "properties": {
    "addr:full":"71 High Street Ruislip Greater London HA4 8JB",
    "addr:housenumber":"71",
    "addr:postcode":"ha4 8jb",
    "addr:street":"High Street",
    "iso:country":"GB",
    "sg:address":"71 High Street",
    "sg:city":"Ruislip",
    "sg:classifiers":[
        {
            "category":"Organizations",
            "subcategory":"Non-profit Organization",
            "type":"Services"
        }
    ],
    "sg:phone":"+44 1895 623359",
    "sg:postcode":"HA4 8JB",
    "sg:province":"Greater London",
    "sg:tags":[
        "organisation",
        "voluntary",
        "charity"
    ],
    "wof:name":"Scope Trading Department Area Office",
    "wof:placetype":"venue"
},
  "geometry": {"coordinates":[-0.4244500101,51.5743484497],"type":"Point"}
}