{
  "type": "Feature",
  "properties": {
    "addr:full":"37 Lisle Close Gravesend Kent DA12 4XH",
    "addr:housenumber":"37",
    "addr:postcode":"da12 4xh",
    "addr:street":"Lisle Close",
    "iso:country":"GB",
    "sg:address":"37 Lisle Close",
    "sg:city":"Gravesend",
    "sg:classifiers":[
        {
            "category":"Professional",
            "subcategory":"Engineering",
            "type":"Services"
        },
        {
            "category":"Home & Garden",
            "subcategory":"Building Materials",
            "type":"Retail Goods"
        }
    ],
    "sg:postcode":"DA12 4XH",
    "sg:province":"Kent",
    "sg:tags":[
        "civil",
        "furnishers",
        "bathroom",
        "planner",
        "engineer"
    ],
    "wof:name":"Tile in Style",
    "wof:placetype":"venue"
},
  "geometry": {"coordinates":[0.4104300141,51.4303398132],"type":"Point"}
}