{
  "type": "Feature",
  "properties": {
    "addr:full":"60 St Peters Avenue Cleethorpes Lincolnshire DN35 8HP",
    "addr:housenumber":"60",
    "addr:postcode":"dn35 8hp",
    "addr:street":"St Peters Avenue",
    "iso:country":"GB",
    "sg:address":"60 St Peters Avenue",
    "sg:city":"Cleethorpes",
    "sg:classifiers":[
        {
            "category":"Personal",
            "subcategory":"Beauty Salon",
            "type":"Services"
        }
    ],
    "sg:phone":"+44 1472 691299",
    "sg:postcode":"DN35 8HP",
    "sg:province":"Lincolnshire",
    "sg:tags":[
        "unisex",
        "hairdresser"
    ],
    "wof:name":"Kimbles",
    "wof:placetype":"venue"
},
  "geometry": {"coordinates":[-0.030572,53.558338],"type":"Point"}
}