{
  "type": "Feature",
  "properties": {
    "addr:full":"Conifers, Church Road, Farley Hill Reading Berkshire RG7 1TU",
    "addr:postcode":"rg7 1tu",
    "addr:street":"Church Road Farley Hill",
    "iso:country":"GB",
    "sg:address":"Conifers, Church Road, Farley Hill",
    "sg:city":"Reading",
    "sg:classifiers":[
        {
            "category":"Building & Trades",
            "subcategory":"Construction",
            "type":"Services"
        },
        {
            "category":"Sports & Exercise",
            "subcategory":"Playing Field",
            "type":"Entertainment"
        }
    ],
    "sg:phone":"+44 118 973 2805",
    "sg:postcode":"RG7 1TU",
    "sg:province":"Berkshire",
    "sg:tags":[
        "conservation",
        "craft",
        "thatching",
        "related"
    ],
    "wof:name":"E E Sharp & Son",
    "wof:placetype":"venue"
},
  "geometry": {"coordinates":[-0.91561,51.373131],"type":"Point"}
}