{
  "type": "Feature",
  "properties": {
    "addr:full":"9-10 Redan Hill Estate, Redan Road Aldershot Hampshire GU12 4SJ",
    "addr:housenumber":"9-10",
    "addr:postcode":"gu12 4sj",
    "addr:street":"Redan Hill Estate Redan Road",
    "iso:country":"GB",
    "sg:address":"9-10 Redan Hill Estate, Redan Road",
    "sg:city":"Aldershot",
    "sg:classifiers":[
        {
            "category":"Wholesale",
            "subcategory":"Machinery & Supplies",
            "type":"Manufacturing & Wholesale Goods"
        }
    ],
    "sg:phone":"+44 1252 333883",
    "sg:postcode":"GU12 4SJ",
    "sg:province":"Hampshire",
    "sg:tags":[
        "equipment",
        "-",
        "sale",
        "hydraulic",
        "accessory"
    ],
    "sg:website":"http://www.mhs.co.uk",
    "wof:name":"Modular Hydraulic Systems Ltd",
    "wof:placetype":"venue"
},
  "geometry": {"coordinates":[-0.7441859841,51.251285553],"type":"Point"}
}