{
  "type": "Feature",
  "properties": {
    "addr:full":"Ferry Farm Abattoir Ferry Lane, Skellingthorpe Lincoln Lincolnshire LN6 5TX",
    "addr:postcode":"ln6 5tx",
    "addr:street":"Ferry;Abattoir Ferry Lane",
    "iso:country":"GB",
    "sg:address":"Ferry Farm Abattoir Ferry Lane, Skellingthorpe",
    "sg:city":"Lincoln",
    "sg:classifiers":[
        {
            "category":"Wholesale",
            "subcategory":"Meat",
            "type":"Manufacturing & Wholesale Goods"
        }
    ],
    "sg:phone":"+44 1522 682023",
    "sg:postcode":"LN6 5TX",
    "sg:province":"Lincolnshire",
    "sg:tags":[
        "abattoir"
    ],
    "wof:name":"St.Merryn Meat Ltd.",
    "wof:placetype":"venue"
},
  "geometry": {"coordinates":[-0.6165289879,53.2364273071],"type":"Point"}
}