{
  "type": "Feature",
  "properties": {
    "iso:country":"GB",
    "sg:address":"29 Back Canning St",
    "sg:city":"Liverpool",
    "sg:classifiers":[
        {
            "category":"Retail",
            "subcategory":"Auto Repair",
            "type":"Services"
        }
    ],
    "sg:phone":"+44 151 709 5457",
    "sg:postcode":"L8 7PB",
    "sg:province":"Merseyside",
    "sg:tags":[
        "modification",
        "garage"
    ],
    "wof:name":"F B Motors",
    "wof:placetype":"venue"
},
  "geometry": {"coordinates":[-2.968945,53.398933],"type":"Point"}
}