{
  "type": "Feature",
  "properties": {
    "addr:full":"25 Craigowan Road Dundee Dundee City DD2 4NN",
    "addr:housenumber":"25",
    "addr:postcode":"dd2 4nn",
    "addr:street":"Craigowan Road",
    "iso:country":"GB",
    "sg:address":"25 Craigowan Road",
    "sg:city":"Dundee",
    "sg:classifiers":[
        {
            "category":"Food & Beverages",
            "subcategory":"Fruits & Vegetables",
            "type":"Retail Goods"
        }
    ],
    "sg:phone":"+44 1382 622141",
    "sg:postcode":"DD2 4NN",
    "sg:province":"Dundee City",
    "sg:tags":[
        "greengrocer"
    ],
    "wof:name":"Charleston Super Savers",
    "wof:placetype":"venue"
},
  "geometry": {"coordinates":[-3.0374751091,56.47315979],"type":"Point"}
}