{
  "type": "Feature",
  "properties": {
    "addr:full":"4 Lowther Street Carlisle Cumbria CA3 8DA",
    "addr:housenumber":"4",
    "addr:postcode":"ca3 8da",
    "addr:street":"Lowther Street",
    "iso:country":"GB",
    "sg:address":"4 Lowther Street",
    "sg:city":"Carlisle",
    "sg:classifiers":[
        {
            "category":"Food & Beverages",
            "subcategory":"Bakery",
            "type":"Retail Goods"
        }
    ],
    "sg:phone":"+44 1228 511918",
    "sg:postcode":"CA3 8DA",
    "sg:province":"Cumbria",
    "sg:tags":[
        "baker"
    ],
    "wof:name":"W Sproat & Son",
    "wof:placetype":"venue"
},
  "geometry": {"coordinates":[-2.9329340458,54.8929977417],"type":"Point"}
}