{
  "type": "Feature",
  "properties": {
    "addr:full":"11a St Marys Road Market Harborough Leicestershire LE16 7DS",
    "addr:housenumber":"11a",
    "addr:postcode":"le16 7ds",
    "addr:street":"St Marys Road",
    "iso:country":"GB",
    "sg:address":"11a St Marys Road",
    "sg:city":"Market Harborough",
    "sg:classifiers":[
        {
            "category":"Professional",
            "subcategory":"Lawyer & Legal Services",
            "type":"Services"
        }
    ],
    "sg:phone":"+44 1858 466850",
    "sg:postcode":"LE16 7DS",
    "sg:province":"Leicestershire",
    "sg:tags":[
        "advice",
        "counselling"
    ],
    "wof:name":"Harborough District Citizens Advice Bureau",
    "wof:placetype":"venue"
},
  "geometry": {"coordinates":[-0.9192609787,52.4781837463],"type":"Point"}
}