{
  "type": "Feature",
  "properties": {
    "iso:country":"GB",
    "sg:address":"Swallow Nest, Woodgate",
    "sg:city":"Dereham",
    "sg:classifiers":[
        {
            "category":"Sports & Exercise",
            "subcategory":"Sports Center",
            "type":"Entertainment"
        }
    ],
    "sg:phone":"+44 1362 637030",
    "sg:postcode":"NR20 4NU",
    "sg:province":"Norfolk",
    "sg:tags":[
        "coaching"
    ],
    "wof:name":"Anglia Academy Tae-Kwon-Do",
    "wof:placetype":"venue"
},
  "geometry": {"coordinates":[0.98905,52.704399],"type":"Point"}
}