{
  "type": "Feature",
  "properties": {
    "iso:country":"GB",
    "sg:address":"27 Roman Road",
    "sg:city":"Middlesbrough",
    "sg:classifiers":[
        {
            "category":"Shopping",
            "subcategory":"Gifts & Souvenirs",
            "type":"Retail Goods"
        },
        {
            "category":"Professional",
            "subcategory":"Printing & Photocopies",
            "type":"Services"
        }
    ],
    "sg:phone":"+44 1642 881040",
    "sg:postcode":"TS5 6EA",
    "sg:province":"North Yorkshire",
    "sg:tags":[
        "trophy",
        "supplier",
        "medal"
    ],
    "wof:name":"Classic Trophies U K",
    "wof:placetype":"venue"
},
  "geometry": {"coordinates":[-1.247709,54.557819],"type":"Point"}
}