{
  "type": "Feature",
  "properties": {
    "iso:country":"GB",
    "sg:address":"40 Priors Road",
    "sg:city":"Cheltenham",
    "sg:classifiers":[
        {
            "category":"Building & Trades",
            "subcategory":"Plumbing",
            "type":"Services"
        }
    ],
    "sg:phone":"+44 1242 677111",
    "sg:postcode":"GL52 5AA",
    "sg:province":"Gloucestershire",
    "sg:tags":[
        "central",
        "heating"
    ],
    "wof:name":"Inta-Heat",
    "wof:placetype":"venue"
},
  "geometry": {"coordinates":[-2.051802,51.902],"type":"Point"}
}