{
  "type": "Feature",
  "properties": {
    "addr:full":"42 St Marys Street Wallingford Oxfordshire OX10 0EU",
    "addr:housenumber":"42",
    "addr:postcode":"ox10 0eu",
    "addr:street":"St Marys Street",
    "iso:country":"GB",
    "sg:address":"42 St Marys Street",
    "sg:city":"Wallingford",
    "sg:classifiers":[
        {
            "category":"Shopping",
            "subcategory":"Books",
            "type":"Retail Goods"
        }
    ],
    "sg:phone":"+44 1491 836510",
    "sg:postcode":"OX10 0EU",
    "sg:province":"Oxfordshire",
    "sg:tags":[
        "bookseller"
    ],
    "wof:name":"The Colophon Bookshop",
    "wof:placetype":"venue"
},
  "geometry": {"coordinates":[-1.125246,51.598011],"type":"Point"}
}