{
  "type": "Feature",
  "properties": {
    "iso:country":"GB",
    "sg:address":"79 Hillhead Road, Kirkintilloch",
    "sg:city":"Glasgow",
    "sg:classifiers":[
        {
            "category":"Place Of Worship",
            "type":"Public Place"
        }
    ],
    "sg:phone":"+44 141 776 2310",
    "sg:postcode":"G66 2HY",
    "sg:province":"East Dunbartonshire",
    "wof:name":"St.Flannans Catholic Church",
    "wof:placetype":"venue"
},
  "geometry": {"coordinates":[-4.14458,55.94265],"type":"Point"}
}