{
  "type": "Feature",
  "properties": {
    "addr:full":"216 Boultham Park Road Lincoln Lincolnshire LN6 7TE",
    "addr:housenumber":"216",
    "addr:postcode":"ln6 7te",
    "addr:street":"Boultham Park Road",
    "iso:country":"GB",
    "sg:address":"216 Boultham Park Road",
    "sg:city":"Lincoln",
    "sg:classifiers":[
        {
            "category":"Professional",
            "subcategory":"Computer Services",
            "type":"Services"
        }
    ],
    "sg:phone":"+44 1522 589855",
    "sg:postcode":"LN6 7TE",
    "sg:province":"Lincolnshire",
    "sg:tags":[
        "consultant"
    ],
    "wof:name":"Integral Systems & Support (East Midlands)",
    "wof:placetype":"venue"
},
  "geometry": {"coordinates":[-0.5610730052,53.2120819092],"type":"Point"}
}