{
  "type": "Feature",
  "properties": {
    "iso:country":"GB",
    "sg:address":"159 Leigh Road",
    "sg:city":"Leigh-on-sea",
    "sg:classifiers":[
        {
            "category":"Shopping",
            "subcategory":"Baby Store",
            "type":"Retail Goods"
        }
    ],
    "sg:phone":"+44 1702 475789",
    "sg:postcode":"SS9 1JF",
    "sg:province":"Essex",
    "sg:tags":[
        "nursery",
        "accessory"
    ],
    "wof:name":"Sunshine Stores Ltd.",
    "wof:placetype":"venue"
},
  "geometry": {"coordinates":[0.6645500064,51.5431861877],"type":"Point"}
}