{
  "type": "Feature",
  "properties": {
    "addr:full":"51-53 Glancynon Terrace, Abercynon Mountain Ash Rhondda, Cynon, Taff CF45 4TF",
    "addr:housenumber":"51-53",
    "addr:postcode":"cf45 4tf",
    "addr:street":"Glancynon Terrace Abercynon;Ash;Cynon Taff",
    "iso:country":"GB",
    "sg:address":"51-53 Glancynon Terrace, Abercynon",
    "sg:city":"Mountain Ash",
    "sg:classifiers":[
        {
            "category":"Shopping",
            "subcategory":"Department Store",
            "type":"Retail Goods"
        }
    ],
    "sg:phone":"+44 1443 740230",
    "sg:postcode":"CF45 4TF",
    "sg:province":"Rhondda, Cynon, Taff",
    "wof:name":"Glancynon Food Discount Store",
    "wof:placetype":"venue"
},
  "geometry": {"coordinates":[-3.3248689175,51.6470031738],"type":"Point"}
}