{
  "type": "Feature",
  "properties": {
    "addr:full":"8a West St Morecambe Lancashire LA3 1RB",
    "addr:housenumber":"8a",
    "addr:postcode":"la3 1rb",
    "addr:street":"West St",
    "iso:country":"GB",
    "sg:address":"8a West St",
    "sg:city":"Morecambe",
    "sg:classifiers":[
        {
            "category":"Shopping",
            "subcategory":"Used Merchandise",
            "type":"Retail Goods"
        }
    ],
    "sg:phone":"+44 1524 411816",
    "sg:postcode":"LA3 1RB",
    "sg:province":"Lancashire",
    "sg:tags":[
        "furniture"
    ],
    "wof:name":"West End",
    "wof:placetype":"venue"
},
  "geometry": {"coordinates":[-2.882034,54.064503],"type":"Point"}
}