{
  "type": "Feature",
  "properties": {
    "addr:full":"G E C Estate, 14 Osram Rd East Lane Wembley Greater London HA9 7NG",
    "addr:housenumber":"14",
    "addr:postcode":"ha9 7ng",
    "addr:street":"Osram Rd East Lane",
    "iso:country":"GB",
    "sg:address":"G E C Estate, 14 Osram Rd East Lane",
    "sg:city":"Wembley",
    "sg:classifiers":[
        {
            "category":"Professional",
            "type":"Services"
        }
    ],
    "sg:phone":"+44 20 8904 7225",
    "sg:postcode":"HA9 7NG",
    "sg:province":"Greater London",
    "sg:tags":[
        "repair",
        "tech",
        "maintenance"
    ],
    "wof:name":"B B L Services",
    "wof:placetype":"venue"
},
  "geometry": {"coordinates":[-0.295539,51.552963],"type":"Point"}
}