{
  "type": "Feature",
  "properties": {
    "iso:country":"GB",
    "sg:address":"Hollin Gate",
    "sg:city":"Otley",
    "sg:classifiers":[
        {
            "category":"Organizations",
            "subcategory":"Membership Organization",
            "type":"Services"
        }
    ],
    "sg:phone":"+44 1943 464139",
    "sg:postcode":"LS21 2DP",
    "sg:province":"North Yorkshire",
    "sg:tags":[
        "club",
        "social"
    ],
    "wof:name":"Otley Working Mens' Social Club",
    "wof:placetype":"venue"
},
  "geometry": {"coordinates":[-1.7126990557,53.9153137207],"type":"Point"}
}