{
  "type": "Feature",
  "properties": {
    "addr:full":"67 Dimsdale View East Newcastle Staffordshire ST5 8HN",
    "addr:housenumber":"67",
    "addr:postcode":"st5 8hn",
    "addr:street":"Dimsdale View East",
    "iso:country":"GB",
    "sg:address":"67 Dimsdale View East",
    "sg:city":"Newcastle",
    "sg:classifiers":[
        {
            "category":"Building & Trades",
            "subcategory":"Construction",
            "type":"Services"
        }
    ],
    "sg:phone":"+44 1782 632845",
    "sg:postcode":"ST5 8HN",
    "sg:province":"Staffordshire",
    "sg:tags":[
        "decorator",
        "painter"
    ],
    "wof:name":"D J Heath",
    "wof:placetype":"venue"
},
  "geometry": {"coordinates":[-2.227686882,53.0355567932],"type":"Point"}
}