{
  "type": "Feature",
  "properties": {
    "addr:full":"9 Cokeham Road Lancing West Sussex BN15 0AA",
    "addr:housenumber":"9",
    "addr:postcode":"bn15 0aa",
    "addr:street":"Cokeham Road",
    "iso:country":"GB",
    "sg:address":"9 Cokeham Road",
    "sg:city":"Lancing",
    "sg:classifiers":[
        {
            "category":"Retail",
            "subcategory":"Auto Repair",
            "type":"Services"
        }
    ],
    "sg:phone":"+44 1903 752231",
    "sg:postcode":"BN15 0AA",
    "sg:province":"West Sussex",
    "sg:tags":[
        "modification",
        "garage"
    ],
    "wof:name":"M C B Services",
    "wof:placetype":"venue"
},
  "geometry": {"coordinates":[-0.332893014,50.8318367004],"type":"Point"}
}