{
  "type": "Feature",
  "properties": {
    "iso:country":"GB",
    "sg:address":"34 Queens Street, Madeley",
    "sg:city":"Telford",
    "sg:classifiers":[
        {
            "category":"Professional",
            "subcategory":"Engineering",
            "type":"Services"
        }
    ],
    "sg:postcode":"TF7 4BL",
    "sg:province":"Shropshire",
    "sg:tags":[
        "contractor",
        "electrical",
        "engineer"
    ],
    "wof:name":"S S Electronics",
    "wof:placetype":"venue"
},
  "geometry": {"coordinates":[-2.439546,52.636944],"type":"Point"}
}