{
  "type": "Feature",
  "properties": {
    "addr:full":"22 Woodfield Road Dursley Gloucestershire GL11 6HE",
    "addr:housenumber":"22",
    "addr:postcode":"gl11 6he",
    "addr:street":"Woodfield Road",
    "iso:country":"GB",
    "sg:address":"22 Woodfield Road",
    "sg:city":"Dursley",
    "sg:classifiers":[
        {
            "category":"Farming",
            "subcategory":"Nursery",
            "type":"Manufacturing & Wholesale Goods"
        }
    ],
    "sg:phone":"+44 1453 544111",
    "sg:postcode":"GL11 6HE",
    "sg:province":"Gloucestershire",
    "sg:tags":[
        "creche"
    ],
    "wof:name":"Imagine Co-Operative Child Care",
    "wof:placetype":"venue"
},
  "geometry": {"coordinates":[-2.370812,51.69611],"type":"Point"}
}