{
  "type": "Feature",
  "properties": {
    "addr:full":"19 Howard Court, Nerston Industrial Estate, East Kilbride Glasgow South Lanarkshire G74 4QZ",
    "addr:housenumber":"19",
    "addr:postcode":"g74 4qz",
    "addr:street":"Howard Court Nerston Industrial Estate East",
    "iso:country":"GB",
    "sg:address":"19 Howard Court, Nerston Industrial Estate, East Kilbride",
    "sg:city":"Glasgow",
    "sg:classifiers":[
        {
            "category":"Mining & Drilling",
            "type":"Manufacturing & Wholesale Goods"
        }
    ],
    "sg:phone":"+44 1355 244212",
    "sg:postcode":"G74 4QZ",
    "sg:province":"South Lanarkshire",
    "sg:tags":[
        "oil",
        "petroleum"
    ],
    "wof:name":"Specialist Lubrication Systems Co Ltd",
    "wof:placetype":"venue"
},
  "geometry": {"coordinates":[-4.165652,55.779247],"type":"Point"}
}