{
  "type": "Feature",
  "properties": {
    "iso:country":"GB",
    "sg:address":"34 Southbourne Avenue, Holbury",
    "sg:city":"Southampton",
    "sg:classifiers":[
        {
            "category":"Building & Trades",
            "subcategory":"Construction",
            "type":"Services"
        }
    ],
    "sg:phone":"+44 23 8089 4150",
    "sg:postcode":"SO45 2NT",
    "sg:province":"Hampshire",
    "sg:tags":[
        "heating",
        "contractor"
    ],
    "wof:name":"E H King & Sons",
    "wof:placetype":"venue"
},
  "geometry": {"coordinates":[-1.388402,50.832832],"type":"Point"}
}