{
  "type": "Feature",
  "properties": {
    "addr:full":"Laigh Court Beith North Ayrshire KA15 2DQ",
    "addr:postcode":"ka15 2dq",
    "iso:country":"GB",
    "sg:address":"Laigh Court",
    "sg:city":"Beith",
    "sg:classifiers":[
        {
            "category":"Social Services",
            "subcategory":"Adult Care",
            "type":"Services"
        },
        {
            "category":"Social Services",
            "subcategory":"Retirement Home",
            "type":"Services"
        }
    ],
    "sg:phone":"+44 1505 504434",
    "sg:postcode":"KA15 2DQ",
    "sg:province":"North Ayrshire",
    "sg:tags":[
        "housing",
        "sheltered",
        "accommodation"
    ],
    "wof:name":"Laigh Court Sheltered Housing",
    "wof:placetype":"venue"
},
  "geometry": {"coordinates":[-4.632584,55.753601],"type":"Point"}
}