{
  "type": "Feature",
  "properties": {
    "addr:full":"4 Akroyd Place, North Parade Halifax West Yorkshire HX1 1YH",
    "addr:housenumber":"4",
    "addr:postcode":"hx1 1yh",
    "addr:street":"Akroyd Place North Parade",
    "iso:country":"GB",
    "sg:address":"4 Akroyd Place, North Parade",
    "sg:city":"Halifax",
    "sg:classifiers":[
        {
            "category":"Community Center",
            "type":"Public Place"
        }
    ],
    "sg:phone":"+44 1422 341488",
    "sg:postcode":"HX1 1YH",
    "sg:province":"West Yorkshire",
    "sg:tags":[
        "recreation",
        "leisure",
        "centre"
    ],
    "wof:name":"The Halifax Body Station",
    "wof:placetype":"venue"
},
  "geometry": {"coordinates":[-1.862224,53.721233],"type":"Point"}
}