{
  "type": "Feature",
  "properties": {
    "addr:full":"2 Lock Street Sheffield South Yorkshire S6 3BJ",
    "addr:housenumber":"2",
    "addr:postcode":"s6 3bj",
    "addr:street":"Lock Street",
    "iso:country":"GB",
    "sg:address":"2 Lock Street",
    "sg:city":"Sheffield",
    "sg:classifiers":[
        {
            "category":"Manufacturing",
            "subcategory":"Metals",
            "type":"Manufacturing & Wholesale Goods"
        }
    ],
    "sg:phone":"+44 114 232 3272",
    "sg:postcode":"S6 3BJ",
    "sg:province":"South Yorkshire",
    "wof:name":"W H Greaves & Son (Electro-Platers) Ltd.",
    "wof:placetype":"venue"
},
  "geometry": {"coordinates":[-1.484967947,53.392742157],"type":"Point"}
}