{
  "type": "Feature",
  "properties": {
    "addr:full":"37 Stepney Street Llanelli Carmarthenshire SA15 3YB",
    "addr:housenumber":"37",
    "addr:postcode":"sa15 3yb",
    "addr:street":"Stepney Street",
    "iso:country":"GB",
    "sg:address":"37 Stepney Street",
    "sg:city":"Llanelli",
    "sg:classifiers":[
        {
            "category":"Travel",
            "subcategory":"Travel Agent",
            "type":"Entertainment"
        }
    ],
    "sg:phone":"+44 1554 772634",
    "sg:postcode":"SA15 3YB",
    "sg:province":"Carmarthenshire",
    "wof:name":"Going Places Leisure Travel",
    "wof:placetype":"venue"
},
  "geometry": {"coordinates":[-4.163073,51.681194],"type":"Point"}
}