{
  "type": "Feature",
  "properties": {
    "addr:full":"9 Crwys Road, Cathays Cardiff Cardiff CF24 4NA",
    "addr:housenumber":"9",
    "addr:postcode":"cf24 4na",
    "addr:street":"Crwys Road",
    "iso:country":"GB",
    "sg:address":"9 Crwys Road, Cathays",
    "sg:city":"Cardiff",
    "sg:classifiers":[
        {
            "category":"Communications",
            "type":"Services"
        }
    ],
    "sg:postcode":"CF24 4NA",
    "sg:province":"Cardiff",
    "sg:tags":[
        "tv",
        "video",
        "radio"
    ],
    "wof:name":"Reliable Satellite Services",
    "wof:placetype":"venue"
},
  "geometry": {"coordinates":[-3.1727230549,51.492805481],"type":"Point"}
}