{
  "type": "Feature",
  "properties": {
    "addr:full":"Tooting Leisure Centre, Greaves Pl Tooting Greater London SW17 0NE",
    "addr:postcode":"sw17 0ne",
    "addr:street":"Greaves Pl",
    "iso:country":"GB",
    "sg:address":"Tooting Leisure Centre, Greaves Pl",
    "sg:city":"Tooting",
    "sg:classifiers":[
        {
            "category":"Professional",
            "type":"Services"
        }
    ],
    "sg:phone":"+44 20 8333 7555",
    "sg:postcode":"SW17 0NE",
    "sg:province":"Greater London",
    "sg:tags":[
        "caterer"
    ],
    "wof:name":"2 A'S Catering",
    "wof:placetype":"venue"
},
  "geometry": {"coordinates":[-0.166554004,51.4293746948],"type":"Point"}
}