{
  "type": "Feature",
  "properties": {
    "addr:full":"22 Cromwell Way Witham Essex CM8 2ES",
    "addr:housenumber":"22",
    "addr:postcode":"cm8 2es",
    "addr:street":"Cromwell Way",
    "iso:country":"GB",
    "sg:address":"22 Cromwell Way",
    "sg:city":"Witham",
    "sg:classifiers":[
        {
            "category":"Real Estate",
            "subcategory":"Surveying",
            "type":"Services"
        }
    ],
    "sg:postcode":"CM8 2ES",
    "sg:province":"Essex",
    "sg:tags":[
        "surveyor",
        "quantity"
    ],
    "wof:name":"Philip F Helps",
    "wof:placetype":"venue"
},
  "geometry": {"coordinates":[0.63159,51.803833],"type":"Point"}
}