{
  "type": "Feature",
  "properties": {
    "addr:full":"Wisteria Studio, Wharf Road Wallingford Oxfordshire OX10 7EW",
    "addr:postcode":"ox10 7ew",
    "addr:street":"Wharf Road",
    "iso:country":"GB",
    "sg:address":"Wisteria Studio, Wharf Road",
    "sg:city":"Wallingford",
    "sg:classifiers":[
        {
            "category":"Retail",
            "subcategory":"Repair Shop",
            "type":"Services"
        }
    ],
    "sg:phone":"+44 1865 858650",
    "sg:postcode":"OX10 7EW",
    "sg:province":"Oxfordshire",
    "sg:tags":[
        "furniture"
    ],
    "wof:name":"James Smith",
    "wof:placetype":"venue"
},
  "geometry": {"coordinates":[-1.1256229877,51.6009101868],"type":"Point"}
}