{
  "type": "Feature",
  "properties": {
    "addr:full":"296 Kitts Green Road Birmingham West Midlands B33 9SB",
    "addr:housenumber":"296",
    "addr:postcode":"b33 9sb",
    "addr:street":"Kitts Green Road",
    "iso:country":"GB",
    "sg:address":"296 Kitts Green Road",
    "sg:city":"Birmingham",
    "sg:classifiers":[
        {
            "category":"Shopping",
            "subcategory":"Used Merchandise",
            "type":"Retail Goods"
        }
    ],
    "sg:phone":"+44 121 683 8308",
    "sg:postcode":"B33 9SB",
    "sg:province":"West Midlands",
    "sg:tags":[
        "shop",
        "second-hand"
    ],
    "wof:name":"Penelope's",
    "wof:placetype":"venue"
},
  "geometry": {"coordinates":[-1.7806940079,52.4831848145],"type":"Point"}
}