{
  "type": "Feature",
  "properties": {
    "addr:full":"19/21 Connaught Road Littlehampton West Sussex BN17 6ER",
    "addr:housenumber":"19 / 21",
    "addr:postcode":"bn17 6er",
    "addr:street":"Connaught Road",
    "iso:country":"GB",
    "sg:address":"19/21 Connaught Road",
    "sg:city":"Littlehampton",
    "sg:classifiers":[
        {
            "category":"Communications",
            "type":"Services"
        }
    ],
    "sg:phone":"+44 1903 717135",
    "sg:postcode":"BN17 6ER",
    "sg:province":"West Sussex",
    "sg:tags":[
        "data",
        "network"
    ],
    "wof:name":"Netcomm Systems Integration Ltd.",
    "wof:placetype":"venue"
},
  "geometry": {"coordinates":[-0.542317,50.811531],"type":"Point"}
}