{
  "type": "Feature",
  "properties": {
    "addr:full":"21 South Molton Street London Greater London W1K 5QZ",
    "addr:housenumber":"21",
    "addr:postcode":"w1k 5qz",
    "addr:street":"South Molton Street",
    "iso:country":"GB",
    "sg:address":"21 South Molton Street",
    "sg:city":"London",
    "sg:classifiers":[
        {
            "category":"Arts & Performance",
            "subcategory":"Art Gallery",
            "type":"Entertainment"
        }
    ],
    "sg:postcode":"W1K 5QZ",
    "sg:province":"Greater London",
    "wof:name":"Electrum Gallery Ltd.",
    "wof:placetype":"venue"
},
  "geometry": {"coordinates":[-0.148536,51.51387],"type":"Point"}
}