{
  "type": "Feature",
  "properties": {
    "iso:country":"GB",
    "sg:address":"11 Clyde Terrace",
    "sg:city":"Spennymoor",
    "sg:classifiers":[
        {
            "category":"Taxi",
            "type":"Transportation"
        }
    ],
    "sg:phone":"+44 1388 811379",
    "sg:postcode":"DL16 7SE",
    "sg:province":"Durham",
    "sg:tags":[
        "mini",
        "cab"
    ],
    "wof:name":"Margaret Turnbull",
    "wof:placetype":"venue"
},
  "geometry": {"coordinates":[-1.605439,54.697086],"type":"Point"}
}