{
  "type": "Feature",
  "properties": {
    "iso:country":"GB",
    "sg:address":"47 High Street, Milford On Sea",
    "sg:city":"Lymington",
    "sg:classifiers":[
        {
            "category":"Personal",
            "subcategory":"Beauty Salon",
            "type":"Services"
        },
        {
            "category":"Personal",
            "subcategory":"Barber",
            "type":"Services"
        }
    ],
    "sg:phone":"+44 1590 642144",
    "sg:postcode":"SO41 0QG",
    "sg:province":"Hampshire",
    "sg:tags":[
        "unisex",
        "hairdresser"
    ],
    "wof:name":"Ellis Hairdressing",
    "wof:placetype":"venue"
},
  "geometry": {"coordinates":[-1.588145,50.725449],"type":"Point"}
}