{
  "type": "Feature",
  "properties": {
    "addr:full":"10a Boston Rd Sleaford Lincolnshire NG34 7ET",
    "addr:housenumber":"10a",
    "addr:postcode":"ng34 7et",
    "addr:street":"Boston Rd",
    "iso:country":"GB",
    "sg:address":"10a Boston Rd",
    "sg:city":"Sleaford",
    "sg:classifiers":[
        {
            "category":"Professional",
            "subcategory":"Printing & Photocopies",
            "type":"Services"
        }
    ],
    "sg:postcode":"NG34 7ET",
    "sg:province":"Lincolnshire",
    "sg:tags":[
        "printer"
    ],
    "wof:name":"Universal Printers",
    "wof:placetype":"venue"
},
  "geometry": {"coordinates":[-0.40854,52.996502],"type":"Point"}
}