{
  "type": "Feature",
  "properties": {
    "iso:country":"GB",
    "sg:address":"364 Horbury Road",
    "sg:city":"Wakefield",
    "sg:classifiers":[
        {
            "category":"Building & Trades",
            "subcategory":"Construction",
            "type":"Services"
        }
    ],
    "sg:phone":"+44 1924 374231",
    "sg:postcode":"WF2 8JH",
    "sg:province":"West Yorkshire",
    "sg:tags":[
        "joiner",
        "carpenter"
    ],
    "wof:name":"J Foley",
    "wof:placetype":"venue"
},
  "geometry": {"coordinates":[-1.536955,53.66713],"type":"Point"}
}