{
  "type": "Feature",
  "properties": {
    "addr:full":"7 The Triangle, Willingdon Eastbourne East Sussex BN20 9PJ",
    "addr:housenumber":"7;willingdon",
    "addr:postcode":"bn20 9pj",
    "addr:street":"The Triangle",
    "iso:country":"GB",
    "sg:address":"7 The Triangle, Willingdon",
    "sg:city":"Eastbourne",
    "sg:classifiers":[
        {
            "category":"Health Services",
            "subcategory":"Podiatrist",
            "type":"Services"
        }
    ],
    "sg:phone":"+44 1323 484455",
    "sg:postcode":"BN20 9PJ",
    "sg:province":"East Sussex",
    "sg:tags":[
        "podiatrists",
        "chiropodist"
    ],
    "wof:name":"Sharon Jones",
    "wof:placetype":"venue"
},
  "geometry": {"coordinates":[0.2491499931,50.8087692261],"type":"Point"}
}