{
  "type": "Feature",
  "properties": {
    "addr:full":"122-126 Sauchiehall Street Glasgow Glasgow City G2 3AH",
    "addr:housenumber":"122-126",
    "addr:postcode":"g2 3ah",
    "addr:street":"Sauchiehall Street",
    "iso:country":"GB",
    "sg:address":"122-126 Sauchiehall Street",
    "sg:city":"Glasgow",
    "sg:classifiers":[
        {
            "category":"Shopping",
            "subcategory":"Clothing, Apparel, & Fashions",
            "type":"Retail Goods"
        }
    ],
    "sg:phone":"+44 141 332 2091",
    "sg:postcode":"G2 3AH",
    "sg:province":"Glasgow City",
    "sg:tags":[
        "shop"
    ],
    "wof:name":"River Island Clothing Co. Ltd.",
    "wof:placetype":"venue"
},
  "geometry": {"coordinates":[-4.26664,55.865929],"type":"Point"}
}