{
  "type": "Feature",
  "properties": {
    "iso:country":"GB",
    "sg:address":"Monks Barn, The Village, Dale Abbey",
    "sg:city":"Ilkeston",
    "sg:classifiers":[
        {
            "category":"Building & Trades",
            "subcategory":"Construction",
            "type":"Services"
        }
    ],
    "sg:phone":"+44 115 932 2059",
    "sg:postcode":"DE7 4PN",
    "sg:province":"Derbyshire",
    "sg:tags":[
        "roofing"
    ],
    "wof:name":"Roland M Wheatley",
    "wof:placetype":"venue"
},
  "geometry": {"coordinates":[-1.3526409864,52.9454612732],"type":"Point"}
}