{
  "type": "Feature",
  "properties": {
    "iso:country":"GB",
    "sg:address":"34 Cheney Road",
    "sg:city":"Faversham",
    "sg:classifiers":[
        {
            "category":"Professional",
            "subcategory":"Computer Services",
            "type":"Services"
        }
    ],
    "sg:postcode":"ME13 8DG",
    "sg:province":"Kent",
    "sg:tags":[
        "system",
        "software"
    ],
    "wof:name":"H J B Logic Ltd",
    "wof:placetype":"venue"
},
  "geometry": {"coordinates":[0.906932,51.314053],"type":"Point"}
}