{
  "type": "Feature",
  "properties": {
    "iso:country":"GB",
    "sg:address":"37 Hutchinson Road, Norden",
    "sg:city":"Rochdale",
    "sg:classifiers":[
        {
            "category":"Home & Garden",
            "subcategory":"Garden Supply",
            "type":"Retail Goods"
        }
    ],
    "sg:phone":"+44 1706 649619",
    "sg:postcode":"OL11 5TX",
    "sg:province":"Lancashire",
    "sg:tags":[
        "turfing"
    ],
    "wof:name":"Christopher Cedric Jones",
    "wof:placetype":"venue"
},
  "geometry": {"coordinates":[-2.2180709839,53.6266555786],"type":"Point"}
}