{
  "type": "Feature",
  "properties": {
    "addr:full":"1 Mabledon Place London Greater London WC1H 9AJ",
    "addr:housenumber":"1",
    "addr:postcode":"wc1h 9aj",
    "addr:street":"Mabledon Place",
    "iso:country":"GB",
    "sg:address":"1 Mabledon Place",
    "sg:city":"London",
    "sg:classifiers":[
        {
            "category":"Organizations",
            "subcategory":"Professional Association",
            "type":"Services"
        }
    ],
    "sg:phone":"+44 845 355 0845",
    "sg:postcode":"WC1H 9AJ",
    "sg:province":"Greater London",
    "sg:tags":[
        "union",
        "trade"
    ],
    "wof:name":"Unison",
    "wof:placetype":"venue"
},
  "geometry": {"coordinates":[-0.127479,51.527962],"type":"Point"}
}