{
  "type": "Feature",
  "properties": {
    "iso:country":"GB",
    "sg:address":"New House, Coronation Road",
    "sg:city":"Ascot",
    "sg:classifiers":[
        {
            "category":"Professional",
            "subcategory":"Business Services",
            "type":"Services"
        }
    ],
    "sg:postcode":"SL5 9LP",
    "sg:province":"Berkshire",
    "sg:tags":[
        "hospitality",
        "corporate"
    ],
    "wof:name":"Maximum Style",
    "wof:placetype":"venue"
},
  "geometry": {"coordinates":[-0.6710060239,51.3997764587],"type":"Point"}
}