{
  "type": "Feature",
  "properties": {
    "iso:country":"GB",
    "sg:address":"19 Clarence Street",
    "sg:city":"Newcastle",
    "sg:classifiers":[
        {
            "category":"Building & Trades",
            "subcategory":"Construction",
            "type":"Services"
        }
    ],
    "sg:phone":"+44 1782 631287",
    "sg:postcode":"ST5 1DF",
    "sg:province":"Staffordshire",
    "sg:tags":[
        "dry",
        "lining",
        "plasterers",
        "screeders"
    ],
    "wof:name":"Sandsite Ltd.",
    "wof:placetype":"venue"
},
  "geometry": {"coordinates":[-2.2171,53.011215],"type":"Point"}
}