{
  "type": "Feature",
  "properties": {
    "iso:country":"GB",
    "sg:address":"Raffety House, 2-4 Sutton Court Road",
    "sg:city":"Sutton",
    "sg:classifiers":[
        {
            "category":"Organizations",
            "subcategory":"Non-profit Organization",
            "type":"Services"
        }
    ],
    "sg:postcode":"SM1 4TN",
    "sg:province":"Surrey",
    "sg:tags":[
        "organisation",
        "voluntary",
        "charity"
    ],
    "wof:name":"Christian Mission To The Communist World",
    "wof:placetype":"venue"
},
  "geometry": {"coordinates":[-0.18799,51.360744],"type":"Point"}
}