{
  "type": "Feature",
  "properties": {
    "iso:country":"GB",
    "sg:address":"John Street",
    "sg:city":"Dalbeattie",
    "sg:classifiers":[
        {
            "category":"Travel",
            "subcategory":"Hotels & Motels",
            "type":"Entertainment"
        }
    ],
    "sg:phone":"+44 1556 610219",
    "sg:postcode":"DG5 4JJ",
    "sg:province":"Dumfries and Galloway",
    "wof:name":"Burnside Hotel",
    "wof:placetype":"venue"
},
  "geometry": {"coordinates":[-3.821162,54.936329],"type":"Point"}
}