{
  "type": "Feature",
  "properties": {
    "addr:full":"158-162 Grange Road, Kings Heath Birmingham West Midlands B14 7RR",
    "addr:housenumber":"158-162",
    "addr:postcode":"b14 7rr",
    "addr:street":"Grange Road",
    "iso:country":"GB",
    "sg:address":"158-162 Grange Road, Kings Heath",
    "sg:city":"Birmingham",
    "sg:classifiers":[
        {
            "category":"Building & Trades",
            "subcategory":"Construction",
            "type":"Services"
        }
    ],
    "sg:postcode":"B14 7RR",
    "sg:province":"West Midlands",
    "sg:tags":[
        "joiner",
        "carpenter"
    ],
    "wof:name":"Assured Carpentry Joinery & Lock Fittings",
    "wof:placetype":"venue"
},
  "geometry": {"coordinates":[-1.897459,52.435085],"type":"Point"}
}