{
  "type": "Feature",
  "properties": {
    "addr:full":"28 Scotland St Ellesmere Shropshire SY12 0EG",
    "addr:housenumber":"28",
    "addr:postcode":"sy12 0eg",
    "addr:street":"Scotland St",
    "iso:country":"GB",
    "sg:address":"28 Scotland St",
    "sg:city":"Ellesmere",
    "sg:classifiers":[
        {
            "category":"Travel",
            "subcategory":"Travel Agent",
            "type":"Entertainment"
        }
    ],
    "sg:phone":"+44 1691 624363",
    "sg:postcode":"SY12 0EG",
    "sg:province":"Shropshire",
    "wof:name":"Mere Travel",
    "wof:placetype":"venue"
},
  "geometry": {"coordinates":[-2.895608,52.90678],"type":"Point"}
}