{
  "type": "Feature",
  "properties": {
    "addr:full":"Steyning Grammar School, Horsham Road Steyning West Sussex BN44 3AA",
    "addr:postcode":"bn44 3aa",
    "addr:street":"Horsham Road",
    "iso:country":"GB",
    "sg:address":"Steyning Grammar School, Horsham Road",
    "sg:city":"Steyning",
    "sg:classifiers":[
        {
            "category":"Community Center",
            "type":"Public Place"
        }
    ],
    "sg:phone":"+44 1903 879666",
    "sg:postcode":"BN44 3AA",
    "sg:province":"West Sussex",
    "sg:tags":[
        "recreation",
        "leisure",
        "centre"
    ],
    "wof:name":"Steyning Sports Centre",
    "wof:placetype":"venue"
},
  "geometry": {"coordinates":[-0.3177250028,50.8827972412],"type":"Point"}
}