{
  "type": "Feature",
  "properties": {
    "addr:full":"59 Eastgate Louth Lincolnshire LN11 9PL",
    "addr:housenumber":"59",
    "addr:postcode":"ln11 9pl",
    "addr:street":"Eastgate Louth",
    "iso:country":"GB",
    "sg:address":"59 Eastgate",
    "sg:city":"Louth",
    "sg:classifiers":[
        {
            "category":"Home & Garden",
            "subcategory":"Furniture",
            "type":"Retail Goods"
        }
    ],
    "sg:phone":"+44 1507 610438",
    "sg:postcode":"LN11 9PL",
    "sg:province":"Lincolnshire",
    "wof:name":"Woodlanders",
    "wof:placetype":"venue"
},
  "geometry": {"coordinates":[-0.003407,53.367268],"type":"Point"}
}