{
  "type": "Feature",
  "properties": {
    "iso:country":"GB",
    "sg:address":"354 St Anns Road",
    "sg:city":"London",
    "sg:classifiers":[
        {
            "category":"Shopping",
            "subcategory":"News",
            "type":"Retail Goods"
        }
    ],
    "sg:postcode":"N15 3TA",
    "sg:province":"Greater London",
    "sg:tags":[
        "newsagent"
    ],
    "wof:name":"St Anns News",
    "wof:placetype":"venue"
},
  "geometry": {"coordinates":[-0.094492,51.58131],"type":"Point"}
}