{
  "type": "Feature",
  "properties": {
    "addr:full":"Thornhill Road Turriff Aberdeenshire AB53 5WH",
    "addr:postcode":"ab53 5wh",
    "addr:street":"Thornhill Road",
    "iso:country":"GB",
    "sg:address":"Thornhill Road",
    "sg:city":"Turriff",
    "sg:classifiers":[
        {
            "category":"Utilities",
            "subcategory":"Natural Gas",
            "type":"Services"
        }
    ],
    "sg:postcode":"AB53 5WH",
    "sg:province":"Aberdeenshire",
    "sg:tags":[
        "blacksmith"
    ],
    "wof:name":"S J Morrison",
    "wof:placetype":"venue"
},
  "geometry": {"coordinates":[-2.328575,57.54192],"type":"Point"}
}