{
  "type": "Feature",
  "properties": {
    "addr:full":"Hurlingham Studios, Ranelagh Gardens London Greater London SW6 3PA",
    "addr:postcode":"sw6 3pa",
    "addr:street":"Ranelagh Gardens",
    "iso:country":"GB",
    "sg:address":"Hurlingham Studios, Ranelagh Gardens",
    "sg:city":"London",
    "sg:classifiers":[
        {
            "category":"Social Services",
            "subcategory":"Job Training",
            "type":"Services"
        }
    ],
    "sg:postcode":"SW6 3PA",
    "sg:province":"Greater London",
    "sg:tags":[
        "translator",
        "interpreter"
    ],
    "wof:name":"Inter-Com Translations",
    "wof:placetype":"venue"
},
  "geometry": {"coordinates":[-0.20858,51.467751],"type":"Point"}
}