{
  "type": "Feature",
  "properties": {
    "iso:country":"GB",
    "sg:address":"10 Greenacres, South Cornelly",
    "sg:city":"Bridgend",
    "sg:classifiers":[
        {
            "category":"Professional",
            "subcategory":"Engineering",
            "type":"Services"
        },
        {
            "category":"Building & Trades",
            "subcategory":"Cleaning & Sanitation",
            "type":"Services"
        }
    ],
    "sg:phone":"+44 1656 745511",
    "sg:postcode":"CF33 4SE",
    "sg:province":"Bridgend",
    "sg:tags":[
        "contracting",
        "design",
        "commercial",
        "engineer"
    ],
    "wof:name":"Childsplay Industrial Control Ltd",
    "wof:placetype":"venue"
},
  "geometry": {"coordinates":[-3.7031428814,51.5103340149],"type":"Point"}
}