{
  "type": "Feature",
  "properties": {
    "iso:country":"GB",
    "sg:address":"Express House, 464 Berkshire Avenue",
    "sg:city":"Slough",
    "sg:classifiers":[
        {
            "category":"Professional",
            "type":"Services"
        },
        {
            "category":"Personal",
            "type":"Services"
        }
    ],
    "sg:phone":"+44 1753 706000",
    "sg:postcode":"SL1 4PL",
    "sg:province":"Berkshire",
    "sg:tags":[
        "delivery",
        "good"
    ],
    "wof:name":"Business Post Ltd",
    "wof:placetype":"venue"
},
  "geometry": {"coordinates":[-0.618497,51.521519],"type":"Point"}
}