{
  "type": "Feature",
  "properties": {
    "addr:full":"29 Maidstone Drive, Wollaton Nottingham Nottinghamshire NG8 2RF",
    "addr:housenumber":"29",
    "addr:postcode":"ng8 2rf",
    "addr:street":"Maidstone Drive",
    "iso:country":"GB",
    "sg:address":"29 Maidstone Drive, Wollaton",
    "sg:city":"Nottingham",
    "sg:classifiers":[
        {
            "category":"Professional",
            "subcategory":"Accounting & Tax Preparation",
            "type":"Services"
        }
    ],
    "sg:phone":"+44 115 928 8444",
    "sg:postcode":"NG8 2RF",
    "sg:province":"Nottinghamshire",
    "sg:tags":[
        "accountant"
    ],
    "wof:name":"P K Consulting",
    "wof:placetype":"venue"
},
  "geometry": {"coordinates":[-1.2332570553,52.9437980652],"type":"Point"}
}