{
  "type": "Feature",
  "properties": {
    "addr:full":"Unit 8 20 Haslett Avenue Crawley Surrey RH10 1FL",
    "addr:housenumber":"unit;20",
    "addr:postcode":"rh10 1fl",
    "addr:street":"Haslett Avenue",
    "iso:country":"GB",
    "sg:address":"Unit 8 20 Haslett Avenue",
    "sg:city":"Crawley",
    "sg:classifiers":[
        {
            "category":"Shopping",
            "subcategory":"Baby Store",
            "type":"Retail Goods"
        }
    ],
    "sg:phone":"+44 1293 544900",
    "sg:postcode":"RH10 1FL",
    "sg:province":"Surrey",
    "sg:tags":[
        "nursery",
        "accessory"
    ],
    "wof:name":"Mothercare (U K) Ltd.",
    "wof:placetype":"venue"
},
  "geometry": {"coordinates":[-0.1763139963,51.1141967773],"type":"Point"}
}