{
  "type": "Feature",
  "properties": {
    "iso:country":"GB",
    "sg:address":"Glendale, Clapper Lane, Staplehurst",
    "sg:city":"Tonbridge",
    "sg:classifiers":[
        {
            "category":"Health Services",
            "subcategory":"Medical Lab",
            "type":"Services"
        }
    ],
    "sg:phone":"+44 1580 893977",
    "sg:postcode":"TN12 0JS",
    "sg:province":"Kent",
    "sg:tags":[
        "dental"
    ],
    "wof:name":"Ceratech Dental Services",
    "wof:placetype":"venue"
},
  "geometry": {"coordinates":[0.5525919795,51.167049408],"type":"Point"}
}