{
  "type": "Feature",
  "properties": {
    "addr:full":"1 Hermitage Court, Wapping High Street Whitechapel Devon E1W2PL",
    "addr:housenumber":"1",
    "addr:postcode":"e1w2pl",
    "addr:street":"Hermitage Court Wapping High Street",
    "iso:country":"GB",
    "sg:address":"1 Hermitage Court, Wapping High Street",
    "sg:city":"Whitechapel",
    "sg:classifiers":[
        {
            "category":"Banks & Credit Unions",
            "subcategory":"Financial Services",
            "type":"Services"
        }
    ],
    "sg:phone":"+44 20 7702 2320",
    "sg:postcode":"E1W2PL",
    "sg:province":"Devon",
    "sg:tags":[
        "adviser"
    ],
    "wof:name":"Agency Financial Services",
    "wof:placetype":"venue"
},
  "geometry": {"coordinates":[-0.063397,51.503876],"type":"Point"}
}