{
  "type": "Feature",
  "properties": {
    "addr:full":"80 Lambeth Rd Southwark Greater London SE1 7PW",
    "addr:housenumber":"80",
    "addr:postcode":"se1 7pw",
    "addr:street":"Lambeth Rd",
    "iso:country":"GB",
    "sg:address":"80 Lambeth Rd",
    "sg:city":"Southwark",
    "sg:classifiers":[
        {
            "category":"Health Services",
            "subcategory":"Hospital",
            "type":"Services"
        }
    ],
    "sg:phone":"+44 20 7928 5633",
    "sg:postcode":"SE1 7PW",
    "sg:province":"Greater London",
    "wof:name":"Churchill Clinic",
    "wof:placetype":"venue"
},
  "geometry": {"coordinates":[-0.109603,51.497059],"type":"Point"}
}