{
  "type": "Feature",
  "properties": {
    "iso:country":"GB",
    "sg:address":"Thynne Street",
    "sg:city":"Bolton",
    "sg:classifiers":[
        {
            "category":"Autos & Motor Vehicles",
            "subcategory":"Auto Supplies",
            "type":"Retail Goods"
        }
    ],
    "sg:postcode":"BL3 6BD",
    "sg:province":"Lancashire",
    "sg:tags":[
        "part",
        "motorcycle",
        "accessory"
    ],
    "wof:name":"Sharples Tyres",
    "wof:placetype":"venue"
},
  "geometry": {"coordinates":[-2.427504,53.573921],"type":"Point"}
}