{
  "type": "Feature",
  "properties": {
    "iso:country":"GB",
    "sg:address":"Unit 6 Fenchurch Court",
    "sg:city":"Oxford",
    "sg:classifiers":[
        {
            "category":"Home & Garden",
            "subcategory":"Hardware",
            "type":"Retail Goods"
        }
    ],
    "sg:phone":"+44 1865 395292",
    "sg:postcode":"OX4 6ZN",
    "sg:province":"Oxfordshire",
    "wof:name":"Newman",
    "wof:placetype":"venue"
},
  "geometry": {"coordinates":[-1.1996799707,51.7289085388],"type":"Point"}
}