{
  "type": "Feature",
  "properties": {
    "iso:country":"GB",
    "sg:address":"57 Orsett Road",
    "sg:city":"Grays",
    "sg:classifiers":[
        {
            "category":"Restaurant",
            "type":"Food & Drink"
        }
    ],
    "sg:phone":"+44 1375 393071",
    "sg:postcode":"RM17 5HJ",
    "sg:province":"Essex",
    "sg:tags":[
        "indian"
    ],
    "wof:name":"New Delhi Balti House",
    "wof:placetype":"venue"
},
  "geometry": {"coordinates":[0.325794,51.479366],"type":"Point"}
}