{
  "type": "Feature",
  "properties": {
    "iso:country":"GB",
    "sg:address":"Holywell Spring Farm, Burton Road",
    "sg:city":"Ashby-de-la-zouch",
    "sg:classifiers":[
        {
            "category":"Farming",
            "subcategory":"Livestock Farm",
            "type":"Manufacturing & Wholesale Goods"
        }
    ],
    "sg:postcode":"LE65 2LP",
    "sg:province":"Derbyshire",
    "sg:tags":[
        "others"
    ],
    "wof:name":"P T Betts",
    "wof:placetype":"venue"
},
  "geometry": {"coordinates":[-1.474861,52.748093],"type":"Point"}
}