{
  "type": "Feature",
  "properties": {
    "addr:full":"116 Eliotts Drive Yeovil Somerset BA21 3NR",
    "addr:housenumber":"116",
    "addr:postcode":"ba21 3nr",
    "addr:street":"Eliotts Drive",
    "iso:country":"GB",
    "sg:address":"116 Eliotts Drive",
    "sg:city":"Yeovil",
    "sg:classifiers":[
        {
            "category":"Building & Trades",
            "subcategory":"Construction",
            "type":"Services"
        }
    ],
    "sg:phone":"+44 1935 474778",
    "sg:postcode":"BA21 3NR",
    "sg:province":"Somerset",
    "sg:tags":[
        "decorator",
        "painter"
    ],
    "wof:name":"T B Montacute",
    "wof:placetype":"venue"
},
  "geometry": {"coordinates":[-2.653803,50.953117],"type":"Point"}
}