{
  "type": "Feature",
  "properties": {
    "addr:full":"53 Ormskirk Street St Helens Merseyside WA10 2SY",
    "addr:housenumber":"53",
    "addr:postcode":"wa10 2sy",
    "addr:street":"Ormskirk Street",
    "iso:country":"GB",
    "sg:address":"53 Ormskirk Street",
    "sg:city":"St Helens",
    "sg:classifiers":[
        {
            "category":"Shopping",
            "subcategory":"Photographic Equipment",
            "type":"Retail Goods"
        }
    ],
    "sg:postcode":"WA10 2SY",
    "sg:province":"Merseyside",
    "sg:tags":[
        "supply"
    ],
    "wof:name":"Keyfoto",
    "wof:placetype":"venue"
},
  "geometry": {"coordinates":[-2.739377,53.454418],"type":"Point"}
}