{
  "type": "Feature",
  "properties": {
    "addr:full":"44 Main Road, Whitletes Ayr South Ayrshire KA8 0LQ",
    "addr:housenumber":"44",
    "addr:postcode":"ka8 0lq",
    "addr:street":"Main Road Whitletes",
    "iso:country":"GB",
    "sg:address":"44 Main Road, Whitletes",
    "sg:city":"Ayr",
    "sg:classifiers":[
        {
            "category":"Food & Beverages",
            "subcategory":"Bakery",
            "type":"Retail Goods"
        }
    ],
    "sg:phone":"+44 1292 267514",
    "sg:postcode":"KA8 0LQ",
    "sg:province":"South Ayrshire",
    "sg:tags":[
        "shop",
        "baker"
    ],
    "wof:name":"Stobbs Bakers",
    "wof:placetype":"venue"
},
  "geometry": {"coordinates":[-4.595580101,55.4721603394],"type":"Point"}
}