{
  "type": "Feature",
  "properties": {
    "iso:country":"GB",
    "sg:address":"2 Leather Lane",
    "sg:city":"Braintree",
    "sg:classifiers":[
        {
            "category":"Home & Garden",
            "subcategory":"Furniture",
            "type":"Retail Goods"
        }
    ],
    "sg:phone":"+44 1376 321009",
    "sg:postcode":"CM7 1UZ",
    "sg:province":"Essex",
    "wof:name":"The Linen Post",
    "wof:placetype":"venue"
},
  "geometry": {"coordinates":[0.5532420278,51.8777580261],"type":"Point"}
}