{
  "type": "Feature",
  "properties": {
    "iso:country":"GB",
    "sg:address":"36 Cartwright Gardens",
    "sg:city":"London",
    "sg:classifiers":[
        {
            "category":"Travel",
            "subcategory":"Hostel",
            "type":"Entertainment"
        }
    ],
    "sg:postcode":"WC1H 9BZ",
    "sg:province":"Greater London",
    "wof:name":"Cartwright University Hall",
    "wof:placetype":"venue"
},
  "geometry": {"coordinates":[-0.127287,51.527515],"type":"Point"}
}