{
  "type": "Feature",
  "properties": {
    "addr:full":"83 London Road Northwich Cheshire CW9 5HQ",
    "addr:housenumber":"83",
    "addr:postcode":"cw9 5hq",
    "addr:street":"London Road",
    "iso:country":"GB",
    "sg:address":"83 London Road",
    "sg:city":"Northwich",
    "sg:classifiers":[
        {
            "category":"Banks & Credit Unions",
            "subcategory":"Bank",
            "type":"Services"
        },
        {
            "category":"Banks & Credit Unions",
            "subcategory":"Financial Services",
            "type":"Services"
        }
    ],
    "sg:phone":"+44 1606 49121",
    "sg:postcode":"CW9 5HQ",
    "sg:province":"Cheshire",
    "sg:tags":[
        "adviser",
        "broker",
        "mortgage",
        "independent"
    ],
    "wof:name":"Delamere Financial Services",
    "wof:placetype":"venue"
},
  "geometry": {"coordinates":[-2.512718,53.256199],"type":"Point"}
}