{
  "type": "Feature",
  "properties": {
    "iso:country":"GB",
    "sg:address":"Station Road, Alne",
    "sg:city":"York",
    "sg:classifiers":[
        {
            "category":"Bars & Pubs",
            "type":"Food & Drink"
        }
    ],
    "sg:phone":"+44 1904 625228",
    "sg:postcode":"YO61 1TP",
    "sg:province":"North Yorkshire",
    "sg:tags":[
        "pubs",
        "inn"
    ],
    "wof:name":"The Winning Post Inn",
    "wof:placetype":"venue"
},
  "geometry": {"coordinates":[-1.239288,54.083958],"type":"Point"}
}