{
  "type": "Feature",
  "properties": {
    "addr:full":"3 Commercial St Newport East Riding of Yorkshire NP1 6AW",
    "addr:housenumber":"3",
    "addr:postcode":"np1 6aw",
    "addr:street":"Commercial St",
    "iso:country":"GB",
    "sg:address":"3 Commercial St",
    "sg:city":"Newport",
    "sg:classifiers":[
        {
            "category":"Health Services",
            "subcategory":"Dentist",
            "type":"Services"
        }
    ],
    "sg:phone":"+44 1633 612265",
    "sg:postcode":"NP1 6AW",
    "sg:province":"East Riding of Yorkshire",
    "wof:name":"P M Price",
    "wof:placetype":"venue"
},
  "geometry": {"coordinates":[-2.9962170124,51.5876998901],"type":"Point"}
}