{
  "type": "Feature",
  "properties": {
    "addr:full":"Flamstone Cottage, Flamstone Street, Bishopstone Salisbury Dorset SP5 4BZ",
    "addr:postcode":"sp5 4bz",
    "addr:street":"Flamstone Street",
    "iso:country":"GB",
    "sg:address":"Flamstone Cottage, Flamstone Street, Bishopstone",
    "sg:city":"Salisbury",
    "sg:classifiers":[
        {
            "category":"Professional",
            "type":"Services"
        }
    ],
    "sg:phone":"+44 1722 780194",
    "sg:postcode":"SP5 4BZ",
    "sg:province":"Dorset",
    "sg:tags":[
        "caterer"
    ],
    "wof:name":"Devils on Horseback",
    "wof:placetype":"venue"
},
  "geometry": {"coordinates":[-1.909174,51.030914],"type":"Point"}
}