{
  "type": "Feature",
  "properties": {
    "addr:full":"31 Carroll Av Hereford Herefordshire HR4 0QW",
    "addr:housenumber":"31",
    "addr:postcode":"hr4 0qw",
    "addr:street":"Carroll Av",
    "iso:country":"GB",
    "sg:address":"31 Carroll Av",
    "sg:city":"Hereford",
    "sg:classifiers":[
        {
            "category":"Farming",
            "subcategory":"Fish & Marine Products",
            "type":"Manufacturing & Wholesale Goods"
        }
    ],
    "sg:phone":"+44 1432 356842",
    "sg:postcode":"HR4 0QW",
    "sg:province":"Herefordshire",
    "sg:tags":[
        "fishmonger"
    ],
    "wof:name":"Finny's Of Hereford",
    "wof:placetype":"venue"
},
  "geometry": {"coordinates":[-2.748918,52.061905],"type":"Point"}
}