{
  "type": "Feature",
  "properties": {
    "iso:country":"GB",
    "sg:address":"88 Salford Clo",
    "sg:city":"Redditch",
    "sg:classifiers":[
        {
            "category":"Autos & Motor Vehicles",
            "subcategory":"Motorcycle Sales",
            "type":"Retail Goods"
        }
    ],
    "sg:phone":"+44 1527 500230",
    "sg:postcode":"B98 7UN",
    "sg:province":"Warwickshire",
    "sg:tags":[
        "chauffeur",
        "driven",
        "car"
    ],
    "wof:name":"Kane,John,",
    "wof:placetype":"venue"
},
  "geometry": {"coordinates":[-1.9171630144,52.2831039429],"type":"Point"}
}