{
  "type": "Feature",
  "properties": {
    "iso:country":"GB",
    "sg:address":"14 Manor Rd, Wickhamford",
    "sg:city":"Evesham",
    "sg:classifiers":[
        {
            "category":"Professional",
            "subcategory":"Engineering",
            "type":"Services"
        }
    ],
    "sg:phone":"+44 1386 832556",
    "sg:postcode":"WR11 6SA",
    "sg:province":"Gloucestershire",
    "sg:tags":[
        "merchant",
        "engineers'"
    ],
    "wof:name":"European Oils",
    "wof:placetype":"venue"
},
  "geometry": {"coordinates":[-1.943969,52.106392],"type":"Point"}
}