{
  "type": "Feature",
  "properties": {
    "addr:full":"28 King Street Maidenhead Berkshire SL6 1EF",
    "addr:housenumber":"28",
    "addr:postcode":"sl6 1ef",
    "addr:street":"King Street",
    "iso:country":"GB",
    "sg:address":"28 King Street",
    "sg:city":"Maidenhead",
    "sg:classifiers":[
        {
            "category":"Shopping",
            "subcategory":"Florist",
            "type":"Retail Goods"
        }
    ],
    "sg:postcode":"SL6 1EF",
    "sg:province":"Berkshire",
    "wof:name":"Sweet Williams Florist",
    "wof:placetype":"venue"
},
  "geometry": {"coordinates":[-0.722943,51.52121],"type":"Point"}
}