{
  "type": "Feature",
  "properties": {
    "addr:full":"Burngreave Sheffield South Yorkshire S3 7ES",
    "addr:postcode":"s3 7es",
    "addr:street":"South",
    "iso:country":"GB",
    "sg:address":"Burngreave",
    "sg:city":"Sheffield",
    "sg:classifiers":[
        {
            "category":"Landmark",
            "subcategory":"Tourist Attraction",
            "type":"Public Place"
        }
    ],
    "sg:phone":"+44 114 276 6492",
    "sg:postcode":"S3 7ES",
    "sg:province":"South Yorkshire",
    "sg:tags":[
        "interest"
    ],
    "wof:name":"Pitsmoor Adventure Playground",
    "wof:placetype":"venue"
},
  "geometry": {"coordinates":[-1.465128,53.40041],"type":"Point"}
}