{
  "type": "Feature",
  "properties": {
    "addr:full":"Care Of Keynsham Leisure Centre, Temple Street, Keynsham Bristol City of Bristol BS31 1EF",
    "addr:postcode":"bs31 1ef",
    "addr:street":"Temple Street",
    "iso:country":"GB",
    "sg:address":"Care Of Keynsham Leisure Centre, Temple Street, Keynsham",
    "sg:city":"Bristol",
    "sg:classifiers":[
        {
            "category":"Professional",
            "type":"Services"
        }
    ],
    "sg:phone":"+44 117 986 1081",
    "sg:postcode":"BS31 1EF",
    "sg:province":"City of Bristol",
    "sg:tags":[
        "caterer"
    ],
    "wof:name":"Caterleisure Ltd.",
    "wof:placetype":"venue"
},
  "geometry": {"coordinates":[-2.496429,51.414471],"type":"Point"}
}