{
  "type": "Feature",
  "properties": {
    "iso:country":"GB",
    "sg:address":"2 Westbourne Street",
    "sg:city":"Walsall",
    "sg:classifiers":[
        {
            "category":"Shopping",
            "subcategory":"Department Store",
            "type":"Retail Goods"
        },
        {
            "category":"Food & Beverages",
            "subcategory":"Supermarket",
            "type":"Retail Goods"
        }
    ],
    "sg:phone":"+44 1922 623740",
    "sg:postcode":"WS4 2JB",
    "sg:province":"West Midlands",
    "wof:name":"Westbourne Street Post Office",
    "wof:placetype":"venue"
},
  "geometry": {"coordinates":[-1.973102,52.592514],"type":"Point"}
}