{
  "type": "Feature",
  "properties": {
    "addr:full":"3 Hoodhill Road Rotherham South Yorkshire S62 7UN",
    "addr:housenumber":"3",
    "addr:postcode":"s62 7un",
    "addr:street":"Hoodhill Road",
    "iso:country":"GB",
    "sg:address":"3 Hoodhill Road",
    "sg:city":"Rotherham",
    "sg:classifiers":[
        {
            "category":"Building & Trades",
            "subcategory":"Construction",
            "type":"Services"
        }
    ],
    "sg:phone":"+44 1923 266605",
    "sg:postcode":"S62 7UN",
    "sg:province":"South Yorkshire",
    "sg:tags":[
        "paint",
        "household",
        "spraying"
    ],
    "wof:name":"Sagola Ltd.",
    "wof:placetype":"venue"
},
  "geometry": {"coordinates":[-1.450269,53.477901],"type":"Point"}
}