{
  "type": "Feature",
  "properties": {
    "addr:full":"Rothienorman Inverurie Aberdeenshire AB51 8YD",
    "addr:postcode":"ab51 8yd",
    "iso:country":"GB",
    "sg:address":"Rothienorman",
    "sg:city":"Inverurie",
    "sg:classifiers":[
        {
            "category":"Manufacturing",
            "subcategory":"Metals",
            "type":"Manufacturing & Wholesale Goods"
        },
        {
            "category":"Wholesale",
            "subcategory":"Machinery & Supplies",
            "type":"Manufacturing & Wholesale Goods"
        }
    ],
    "sg:phone":"+44 1651 821331",
    "sg:postcode":"AB51 8YD",
    "sg:province":"Aberdeenshire",
    "sg:tags":[
        "steel",
        "fabricator",
        "erectors"
    ],
    "wof:name":"Fraser Manufacturing Ltd.",
    "wof:placetype":"venue"
},
  "geometry": {"coordinates":[-2.4659490585,57.4112052917],"type":"Point"}
}