{
  "type": "Feature",
  "properties": {
    "addr:full":"330 Regents Park Rd Finchley Central Greater London N3 2LN",
    "addr:housenumber":"330",
    "addr:postcode":"n3 2ln",
    "addr:street":"Regents Park Rd",
    "iso:country":"GB",
    "sg:address":"330 Regents Park Rd",
    "sg:city":"Finchley Central",
    "sg:classifiers":[
        {
            "category":"Retail",
            "subcategory":"Laundry & Dry Cleaning",
            "type":"Services"
        }
    ],
    "sg:phone":"+44 20 8349 4900",
    "sg:postcode":"N3 2LN",
    "sg:province":"Greater London",
    "sg:tags":[
        "alteration"
    ],
    "wof:name":"Cleansleeve",
    "wof:placetype":"venue"
},
  "geometry": {"coordinates":[-0.194843,51.600147],"type":"Point"}
}