{
  "type": "Feature",
  "properties": {
    "addr:full":"106-107 High St Stourbridge Staffordshire DY8 5RT",
    "addr:housenumber":"106-107",
    "addr:postcode":"dy8 5rt",
    "addr:street":"High St",
    "iso:country":"GB",
    "sg:address":"106-107 High St",
    "sg:city":"Stourbridge",
    "sg:classifiers":[
        {
            "category":"Fast Food",
            "type":"Food & Drink"
        },
        {
            "category":"Food & Beverages",
            "subcategory":"Meat & Fish",
            "type":"Retail Goods"
        }
    ],
    "sg:phone":"+44 1384 295169",
    "sg:postcode":"DY8 5RT",
    "sg:province":"Staffordshire",
    "sg:tags":[
        "shop",
        "chip"
    ],
    "wof:name":"Wordsley Fish Bar",
    "wof:placetype":"venue"
},
  "geometry": {"coordinates":[-2.161787,52.480633],"type":"Point"}
}