{
  "type": "Feature",
  "properties": {
    "addr:full":"Brooklands, Halesworth Road, Redisham Beccles Norfolk NR34 8NF",
    "addr:postcode":"nr34 8nf",
    "addr:street":"Halesworth Road",
    "iso:country":"GB",
    "sg:address":"Brooklands, Halesworth Road, Redisham",
    "sg:city":"Beccles",
    "sg:classifiers":[
        {
            "category":"Recreation",
            "subcategory":"Amusement Park",
            "type":"Entertainment"
        },
        {
            "category":"Recreation",
            "subcategory":"Water Park",
            "type":"Entertainment"
        },
        {
            "category":"Autos & Motor Vehicles",
            "subcategory":"Boat Sales",
            "type":"Retail Goods"
        }
    ],
    "sg:phone":"+44 1986 781316",
    "sg:postcode":"NR34 8NF",
    "sg:province":"Norfolk",
    "sg:tags":[
        "machine",
        "gaming",
        "theme",
        "arcade"
    ],
    "wof:name":"B E Lee Amusements",
    "wof:placetype":"venue"
},
  "geometry": {"coordinates":[1.541075,52.404442],"type":"Point"}
}