{
  "type": "Feature",
  "properties": {
    "addr:full":"60 Penshurst Gardens Edgware Greater London HA8 9TU",
    "addr:housenumber":"60",
    "addr:postcode":"ha8 9tu",
    "addr:street":"Penshurst Gardens",
    "iso:country":"GB",
    "sg:address":"60 Penshurst Gardens",
    "sg:city":"Edgware",
    "sg:classifiers":[
        {
            "category":"Professional",
            "subcategory":"Accounting & Tax Preparation",
            "type":"Services"
        }
    ],
    "sg:phone":"+44 20 8958 8819",
    "sg:postcode":"HA8 9TU",
    "sg:province":"Greater London",
    "sg:tags":[
        "accountant"
    ],
    "wof:name":"Jessa & Co Chartered Accountants",
    "wof:placetype":"venue"
},
  "geometry": {"coordinates":[-0.2693789899,51.6168746948],"type":"Point"}
}