{
  "type": "Feature",
  "properties": {
    "addr:full":"39-40 Catherine St Frome Somerset BA11 1DB",
    "addr:housenumber":"39-40",
    "addr:postcode":"ba11 1db",
    "addr:street":"Catherine St",
    "iso:country":"GB",
    "sg:address":"39-40 Catherine St",
    "sg:city":"Frome",
    "sg:classifiers":[
        {
            "category":"Shopping",
            "subcategory":"Used Merchandise",
            "type":"Retail Goods"
        }
    ],
    "sg:postcode":"BA11 1DB",
    "sg:province":"Somerset",
    "sg:tags":[
        "shop",
        "second-hand",
        "furniture"
    ],
    "wof:name":"Fryer,Bernard David,",
    "wof:placetype":"venue"
},
  "geometry": {"coordinates":[-2.3260500431,51.2311668396],"type":"Point"}
}