{
  "type": "Feature",
  "properties": {
    "addr:full":"366 Rochester Way, Eltham London Greater London SE9 6LH",
    "addr:housenumber":"366",
    "addr:postcode":"se9 6lh",
    "addr:street":"Rochester Way",
    "iso:country":"GB",
    "sg:address":"366 Rochester Way, Eltham",
    "sg:city":"London",
    "sg:classifiers":[
        {
            "category":"Organizations",
            "subcategory":"Membership Organization",
            "type":"Services"
        }
    ],
    "sg:phone":"+44 20 8850 2032",
    "sg:postcode":"SE9 6LH",
    "sg:province":"Greater London",
    "sg:tags":[
        "club",
        "social"
    ],
    "wof:name":"The Rochester Club",
    "wof:placetype":"venue"
},
  "geometry": {"coordinates":[0.0394550003,51.4618797302],"type":"Point"}
}