{
  "type": "Feature",
  "properties": {
    "addr:full":"Whitbread Cottage, Green Street Green Road, Lane End Dartford Kent DA2 7JR",
    "addr:postcode":"da2 7jr",
    "addr:street":"Green Street Green Road",
    "iso:country":"GB",
    "sg:address":"Whitbread Cottage, Green Street Green Road, Lane End",
    "sg:city":"Dartford",
    "sg:classifiers":[
        {
            "category":"Shopping",
            "subcategory":"News",
            "type":"Retail Goods"
        }
    ],
    "sg:phone":"+44 1322 224588",
    "sg:postcode":"DA2 7JR",
    "sg:province":"Kent",
    "sg:tags":[
        "newsagent"
    ],
    "wof:name":"Lane End Newsagents",
    "wof:placetype":"venue"
},
  "geometry": {"coordinates":[0.24848,51.427341],"type":"Point"}
}