{
  "type": "Feature",
  "properties": {
    "addr:full":"15 Ermine Rise, Great Casterton Stamford Cambridgeshire PE9 4AJ",
    "addr:housenumber":"15",
    "addr:postcode":"pe9 4aj",
    "addr:street":"Ermine Rise",
    "iso:country":"GB",
    "sg:address":"15 Ermine Rise, Great Casterton",
    "sg:city":"Stamford",
    "sg:classifiers":[
        {
            "category":"Professional",
            "subcategory":"Engineering",
            "type":"Services"
        },
        {
            "category":"Building & Trades",
            "subcategory":"Electrical",
            "type":"Services"
        }
    ],
    "sg:phone":"+44 1780 765524",
    "sg:postcode":"PE9 4AJ",
    "sg:province":"Cambridgeshire",
    "sg:tags":[
        "engineer",
        "electrician",
        "contractor"
    ],
    "wof:name":"POLLARD ELECTRICAL (STAMFORD) LTD",
    "wof:placetype":"venue"
},
  "geometry": {"coordinates":[-0.524233,52.672207],"type":"Point"}
}