{
  "type": "Feature",
  "properties": {
    "iso:country":"GB",
    "sg:address":"Estate Office, Station Road, Staplehurst",
    "sg:city":"Tonbridge",
    "sg:classifiers":[
        {
            "category":"Manufacturing",
            "subcategory":"Petroleum Products",
            "type":"Manufacturing & Wholesale Goods"
        }
    ],
    "sg:postcode":"TN12 0QQ",
    "sg:province":"Kent",
    "sg:tags":[
        "double",
        "glazing"
    ],
    "wof:name":"Allclad P V C",
    "wof:placetype":"venue"
},
  "geometry": {"coordinates":[0.5525919795,51.167049408],"type":"Point"}
}