{
  "type": "Feature",
  "properties": {
    "iso:country":"GB",
    "sg:address":"85 Little Oaks",
    "sg:city":"Penryn",
    "sg:classifiers":[
        {
            "category":"Freight",
            "type":"Transportation"
        }
    ],
    "sg:postcode":"TR10 8RX",
    "sg:province":"Cornwall",
    "sg:tags":[
        "haulage",
        "road"
    ],
    "wof:name":"G E Trevor",
    "wof:placetype":"venue"
},
  "geometry": {"coordinates":[-5.11546278,50.1641654968],"type":"Point"}
}