{
  "type": "Feature",
  "properties": {
    "addr:full":"60 Homewood Road Sutton Surrey SM2 7JS",
    "addr:housenumber":"60",
    "addr:postcode":"sm2 7js",
    "addr:street":"Homewood Road",
    "iso:country":"GB",
    "sg:address":"60 Homewood Road",
    "sg:city":"Sutton",
    "sg:classifiers":[
        {
            "category":"Shopping",
            "subcategory":"Shoes",
            "type":"Retail Goods"
        }
    ],
    "sg:postcode":"SM2 7JS",
    "sg:province":"Surrey",
    "sg:tags":[
        "footwear"
    ],
    "wof:name":"Nicole Shoes Ltd.",
    "wof:placetype":"venue"
},
  "geometry": {"coordinates":[-0.225975,51.351135],"type":"Point"}
}