{
  "type": "Feature",
  "properties": {
    "iso:country":"GB",
    "sg:address":"55 Bishopsgate",
    "sg:city":"Moorgate",
    "sg:classifiers":[
        {
            "category":"Insurance",
            "subcategory":"Insurance Agent",
            "type":"Services"
        }
    ],
    "sg:phone":"+44 20 7578 7000",
    "sg:postcode":"EC2N 3AS",
    "sg:province":"Greater London",
    "sg:tags":[
        "broker"
    ],
    "wof:name":"Bonfield Group Ltd",
    "wof:placetype":"venue"
},
  "geometry": {"coordinates":[-0.084237,51.513721],"type":"Point"}
}