{
  "type": "Feature",
  "properties": {
    "addr:full":"Walton Street Oxford Oxfordshire OX2 6AW",
    "addr:postcode":"ox2 6aw",
    "addr:street":"Walton Street",
    "iso:country":"GB",
    "sg:address":"Walton Street",
    "sg:city":"Oxford",
    "sg:classifiers":[
        {
            "category":"Professional",
            "subcategory":"Testing Lab",
            "type":"Services"
        }
    ],
    "sg:phone":"+44 1865 248996",
    "sg:postcode":"OX2 6AW",
    "sg:province":"Oxfordshire",
    "sg:tags":[
        "laboratory"
    ],
    "wof:name":"Nuffield Laboratory of Ophthalmology",
    "wof:placetype":"venue"
},
  "geometry": {"coordinates":[-1.2667939663,51.760559082],"type":"Point"}
}