{
  "type": "Feature",
  "properties": {
    "iso:country":"GB",
    "sg:address":"85 Medway Drive",
    "sg:city":"Greenford",
    "sg:classifiers":[
        {
            "category":"Manufacturing",
            "subcategory":"Rubber & Plastics",
            "type":"Manufacturing & Wholesale Goods"
        }
    ],
    "sg:postcode":"UB6 8LW",
    "sg:province":"Greater London",
    "sg:tags":[
        "mould"
    ],
    "wof:name":"Maggie Moulds",
    "wof:placetype":"venue"
},
  "geometry": {"coordinates":[-0.332841,51.53746],"type":"Point"}
}