{
  "type": "Feature",
  "properties": {
    "iso:country":"GB",
    "sg:address":"38 Moorburn Road",
    "sg:city":"Largs",
    "sg:classifiers":[
        {
            "category":"Personal",
            "type":"Services"
        }
    ],
    "sg:postcode":"KA30 9HX",
    "sg:province":"North Ayrshire",
    "sg:tags":[
        "wedding"
    ],
    "wof:name":"Ekim Enterprises",
    "wof:placetype":"venue"
},
  "geometry": {"coordinates":[-4.860769,55.79718],"type":"Point"}
}