{
  "type": "Feature",
  "properties": {
    "addr:full":"Swallowfield Way Hayes Greater London UB3 1DQ",
    "addr:postcode":"ub3 1dq",
    "addr:street":"Swallowfield Way",
    "iso:country":"GB",
    "sg:address":"Swallowfield Way",
    "sg:city":"Hayes",
    "sg:classifiers":[
        {
            "category":"Shopping",
            "subcategory":"Clothing, Apparel, & Fashions",
            "type":"Retail Goods"
        }
    ],
    "sg:phone":"+44 20 8569 0006",
    "sg:postcode":"UB3 1DQ",
    "sg:province":"Greater London",
    "sg:tags":[
        "lingerie",
        "hosiery",
        "accessory"
    ],
    "wof:name":"CONTESSA (LADIESWEAR) LTD",
    "wof:placetype":"venue"
},
  "geometry": {"coordinates":[-0.435947,51.505993],"type":"Point"}
}