{
  "type": "Feature",
  "properties": {
    "iso:country":"GB",
    "sg:address":"Acre Lane, Spring Park",
    "sg:city":"Northampton",
    "sg:classifiers":[
        {
            "category":"Education",
            "subcategory":"School",
            "type":"Public Place"
        }
    ],
    "sg:phone":"+44 1604 843780",
    "sg:postcode":"NN2 8DF",
    "sg:province":"Northamptonshire",
    "sg:tags":[
        "local",
        "authority"
    ],
    "wof:name":"Whitehills Primary School",
    "wof:placetype":"venue"
},
  "geometry": {"coordinates":[-0.913963,52.275478],"type":"Point"}
}