{
  "type": "Feature",
  "properties": {
    "iso:country":"GB",
    "sg:address":"Cromwell Rd",
    "sg:city":"Inverness",
    "sg:classifiers":[
        {
            "category":"Community Center",
            "subcategory":"Youth",
            "type":"Public Place"
        }
    ],
    "sg:phone":"+44 1463 234734",
    "sg:postcode":"IV1 1SX",
    "sg:province":"Highland",
    "sg:tags":[
        "forestry",
        "consultant"
    ],
    "wof:name":"Forest Enterprise",
    "wof:placetype":"venue"
},
  "geometry": {"coordinates":[-4.229646,57.487938],"type":"Point"}
}