{
  "type": "Feature",
  "properties": {
    "iso:country":"GB",
    "sg:address":"77/79 Main Street, Crosshill",
    "sg:city":"Lochgelly",
    "sg:classifiers":[
        {
            "category":"Professional",
            "subcategory":"Engineering",
            "type":"Services"
        }
    ],
    "sg:postcode":"KY5 8AT",
    "sg:province":"Fife",
    "sg:tags":[
        "design",
        "engineer"
    ],
    "wof:name":"Cardsafe Ltd.",
    "wof:placetype":"venue"
},
  "geometry": {"coordinates":[-3.323877,56.150326],"type":"Point"}
}