{
  "type": "Feature",
  "properties": {
    "addr:full":"Adelaide Place Canterbury Kent CT1 2QA",
    "addr:postcode":"ct1 2qa",
    "addr:street":"Adelaide Place",
    "iso:country":"GB",
    "sg:address":"Adelaide Place",
    "sg:city":"Canterbury",
    "sg:classifiers":[
        {
            "category":"Fast Food",
            "type":"Food & Drink"
        }
    ],
    "sg:postcode":"CT1 2QA",
    "sg:province":"Kent",
    "sg:tags":[
        "away",
        "take"
    ],
    "wof:name":"The Hermitage French Restaurant & Coffee",
    "wof:placetype":"venue"
},
  "geometry": {"coordinates":[1.077265,51.27734],"type":"Point"}
}