{
  "type": "Feature",
  "properties": {
    "addr:full":"65 Clifton Street London Greater London EC2A 4JE",
    "addr:housenumber":"65",
    "addr:postcode":"ec2a 4je",
    "addr:street":"Clifton Street",
    "iso:country":"GB",
    "sg:address":"65 Clifton Street",
    "sg:city":"London",
    "sg:classifiers":[
        {
            "category":"Communications",
            "type":"Services"
        }
    ],
    "sg:phone":"+44 20 7426 7330",
    "sg:postcode":"EC2A 4JE",
    "sg:province":"Greater London",
    "sg:tags":[
        "broadcasting"
    ],
    "wof:name":"Japan Satellite T V (Europe) Ltd.",
    "wof:placetype":"venue"
},
  "geometry": {"coordinates":[-0.1767040044,51.5248641968],"type":"Point"}
}