{
  "type": "Feature",
  "properties": {
    "addr:full":"24 Heath Road Petersfield Hampshire GU31 4EA",
    "addr:housenumber":"24",
    "addr:postcode":"gu31 4ea",
    "addr:street":"Heath Road",
    "iso:country":"GB",
    "sg:address":"24 Heath Road",
    "sg:city":"Petersfield",
    "sg:classifiers":[
        {
            "category":"Government",
            "subcategory":"Office",
            "type":"Public Place"
        }
    ],
    "sg:phone":"+44 1730 263365",
    "sg:postcode":"GU31 4EA",
    "sg:province":"Hampshire",
    "sg:tags":[
        "local"
    ],
    "wof:name":"Petersfield Town Council",
    "wof:placetype":"venue"
},
  "geometry": {"coordinates":[-0.932395,51.003448],"type":"Point"}
}