{
  "type": "Feature",
  "properties": {
    "addr:full":"Great Western Way, Great Bridge Tipton West Midlands DY4 7AH",
    "addr:postcode":"dy4 7ah",
    "addr:street":"Great Western Way",
    "iso:country":"GB",
    "sg:address":"Great Western Way, Great Bridge",
    "sg:city":"Tipton",
    "sg:classifiers":[
        {
            "category":"Building & Trades",
            "subcategory":"Construction",
            "type":"Services"
        }
    ],
    "sg:phone":"+44 121 557 6242",
    "sg:postcode":"DY4 7AH",
    "sg:province":"West Midlands",
    "sg:tags":[
        "fork",
        "lift",
        "truck"
    ],
    "wof:name":"Narrow Aisle Ltd.",
    "wof:placetype":"venue"
},
  "geometry": {"coordinates":[-2.031117,52.531612],"type":"Point"}
}