{
  "type": "Feature",
  "properties": {
    "iso:country":"GB",
    "sg:address":"7 Greenford Close, Cheadle Hulme",
    "sg:city":"Cheadle",
    "sg:classifiers":[
        {
            "category":"Retail",
            "subcategory":"Driving School",
            "type":"Services"
        }
    ],
    "sg:postcode":"SK8 5RN",
    "sg:province":"Cheshire",
    "wof:name":"Pete Tansley Driving School",
    "wof:placetype":"venue"
},
  "geometry": {"coordinates":[-2.185921,53.384525],"type":"Point"}
}