{
  "type": "Feature",
  "properties": {
    "iso:country":"GB",
    "sg:address":"32 Russet Drive, Little Billing",
    "sg:city":"Northampton",
    "sg:classifiers":[
        {
            "category":"Building & Trades",
            "subcategory":"Construction",
            "type":"Services"
        }
    ],
    "sg:phone":"+44 1604 414646",
    "sg:postcode":"NN3 9TF",
    "sg:province":"Northamptonshire",
    "sg:tags":[
        "builder"
    ],
    "wof:name":"Letts Builders",
    "wof:placetype":"venue"
},
  "geometry": {"coordinates":[-0.822716,52.254875],"type":"Point"}
}