{
  "type": "Feature",
  "properties": {
    "iso:country":"GB",
    "sg:address":"Unit 9 New St",
    "sg:city":"Wednesbury",
    "sg:classifiers":[
        {
            "category":"Shopping",
            "type":"Retail Goods"
        }
    ],
    "sg:phone":"+44 121 556 4925",
    "sg:postcode":"WS10 0AA",
    "sg:province":"West Midlands",
    "sg:tags":[
        "bag"
    ],
    "wof:name":"Allpak",
    "wof:placetype":"venue"
},
  "geometry": {"coordinates":[-2.019766,52.548187],"type":"Point"}
}