{
  "type": "Feature",
  "properties": {
    "addr:full":"The Business Academy, 43 Watson Road Worksop Nottinghamshire S80 2BA",
    "addr:housenumber":"43",
    "addr:postcode":"s80 2ba",
    "addr:street":"Watson Road",
    "iso:country":"GB",
    "sg:address":"The Business Academy, 43 Watson Road",
    "sg:city":"Worksop",
    "sg:classifiers":[
        {
            "category":"Professional",
            "subcategory":"Employment Agencies",
            "type":"Services"
        }
    ],
    "sg:phone":"+44 1909 477669",
    "sg:postcode":"S80 2BA",
    "sg:province":"Nottinghamshire",
    "sg:tags":[
        "career",
        "guidance"
    ],
    "wof:name":"Bassetlaw Training Agency",
    "wof:placetype":"venue"
},
  "geometry": {"coordinates":[-1.123189,53.30661],"type":"Point"}
}