{
  "type": "Feature",
  "properties": {
    "addr:full":"3rd Floor, 45/47 Cornhill London Greater London EC3V 3PD",
    "addr:housenumber":"3rd floor 45 / 47",
    "addr:postcode":"ec3v 3pd",
    "addr:street":"Cornhill",
    "iso:country":"GB",
    "sg:address":"3rd Floor, 45/47 Cornhill",
    "sg:city":"London",
    "sg:classifiers":[
        {
            "category":"Banks & Credit Unions",
            "subcategory":"Financial Services",
            "type":"Services"
        }
    ],
    "sg:postcode":"EC3V 3PD",
    "sg:province":"Greater London",
    "sg:tags":[
        "consultant"
    ],
    "wof:name":"Ripley Investments Ltd",
    "wof:placetype":"venue"
},
  "geometry": {"coordinates":[-0.085373,51.51326],"type":"Point"}
}