{
  "type": "Feature",
  "properties": {
    "addr:full":"3 Bailey Street, Cwm Ebbw Vale Blaenau Gwent NP23 7RT",
    "addr:housenumber":"3",
    "addr:postcode":"np23 7rt",
    "addr:street":"Bailey Street",
    "iso:country":"GB",
    "sg:address":"3 Bailey Street, Cwm",
    "sg:city":"Ebbw Vale",
    "sg:classifiers":[
        {
            "category":"Retail",
            "subcategory":"Repair Shop",
            "type":"Services"
        },
        {
            "category":"Manufacturing",
            "subcategory":"Furniture",
            "type":"Manufacturing & Wholesale Goods"
        }
    ],
    "sg:phone":"+44 1495 370558",
    "sg:postcode":"NP23 7RT",
    "sg:province":"Blaenau Gwent",
    "sg:tags":[
        "mnfr",
        "upholstering",
        "upholsterer"
    ],
    "wof:name":"Evans Upholstery Repairs",
    "wof:placetype":"venue"
},
  "geometry": {"coordinates":[-3.1814320087,51.7427368164],"type":"Point"}
}