{
  "type": "Feature",
  "properties": {
    "addr:full":"Elm End, Hare Lane Chard Devon TA20 3JT",
    "addr:postcode":"ta20 3jt",
    "addr:street":"Elm;Hare Lane",
    "iso:country":"GB",
    "sg:address":"Elm End, Hare Lane",
    "sg:city":"Chard",
    "sg:classifiers":[
        {
            "category":"Shopping",
            "type":"Retail Goods"
        }
    ],
    "sg:phone":"+44 1460 234375",
    "sg:postcode":"TA20 3JT",
    "sg:province":"Devon",
    "sg:tags":[
        "merchant"
    ],
    "wof:name":"R H Criddle",
    "wof:placetype":"venue"
},
  "geometry": {"coordinates":[-2.960474,50.873524],"type":"Point"}
}