{
  "type": "Feature",
  "properties": {
    "addr:full":"Unit 5, Wentworth Industrial Court, Goodwin Road Slough Berkshire SL2 2ER",
    "addr:housenumber":"unit 5",
    "addr:postcode":"sl2 2er",
    "addr:street":"Wentworth Industrial Court Goodwin Road",
    "iso:country":"GB",
    "sg:address":"Unit 5, Wentworth Industrial Court, Goodwin Road",
    "sg:city":"Slough",
    "sg:classifiers":[
        {
            "category":"Professional",
            "subcategory":"Engineering",
            "type":"Services"
        }
    ],
    "sg:phone":"+44 1753 516608",
    "sg:postcode":"SL2 2ER",
    "sg:province":"Berkshire",
    "sg:tags":[
        "precision",
        "engineer"
    ],
    "wof:name":"Midas Tool Co",
    "wof:placetype":"venue"
},
  "geometry": {"coordinates":[-0.6343489885,51.5339317322],"type":"Point"}
}