{
  "type": "Feature",
  "properties": {
    "iso:country":"GB",
    "sg:address":"21 Highfield Drive, Monton",
    "sg:city":"Manchester",
    "sg:classifiers":[
        {
            "category":"Building & Trades",
            "subcategory":"Construction",
            "type":"Services"
        }
    ],
    "sg:postcode":"M30 9PZ",
    "sg:province":"Greater Manchester",
    "sg:tags":[
        "decorator",
        "painter"
    ],
    "wof:name":"A Whitefoot Painting & Decorating",
    "wof:placetype":"venue"
},
  "geometry": {"coordinates":[-2.351448,53.492004],"type":"Point"}
}