{
  "type": "Feature",
  "properties": {
    "addr:full":"8 Baltic Street 3rd Floor London EC1Y 0UP",
    "addr:housenumber":"8;3rd floor",
    "addr:postcode":"ec1y 0up",
    "addr:street":"Baltic Street",
    "iso:country":"GB",
    "sg:address":"8 Baltic Street 3rd Floor",
    "sg:city":"London",
    "sg:classifiers":[
        {
            "category":"Professional",
            "subcategory":"Computer Services",
            "type":"Services"
        }
    ],
    "sg:postcode":"EC1Y 0UP",
    "sg:website":"http://www.whathouse.co.uk",
    "wof:name":"Whathouse",
    "wof:placetype":"venue"
},
  "geometry": {"coordinates":[-0.132918,51.515301],"type":"Point"}
}