{
  "type": "Feature",
  "properties": {
    "iso:country":"GB",
    "sg:address":"Rose Nursery, Halliford Road",
    "sg:city":"Shepperton",
    "sg:classifiers":[
        {
            "category":"Farming",
            "subcategory":"Nursery",
            "type":"Manufacturing & Wholesale Goods"
        },
        {
            "category":"Community Center",
            "type":"Public Place"
        }
    ],
    "sg:phone":"+44 1932 783219",
    "sg:postcode":"TW17 8RU",
    "sg:province":"Surrey",
    "sg:tags":[
        "centre"
    ],
    "wof:name":"Squire's Roses",
    "wof:placetype":"venue"
},
  "geometry": {"coordinates":[-0.431634,51.411076],"type":"Point"}
}