{
  "type": "Feature",
  "properties": {
    "addr:full":"6 South Field, Heptonstall Hebden Bridge West Yorkshire HX7 7LS",
    "addr:housenumber":"6",
    "addr:postcode":"hx7 7ls",
    "addr:street":"South Field;West",
    "iso:country":"GB",
    "sg:address":"6 South Field, Heptonstall",
    "sg:city":"Hebden Bridge",
    "sg:classifiers":[
        {
            "category":"Arts & Performance",
            "subcategory":"Music",
            "type":"Entertainment"
        }
    ],
    "sg:postcode":"HX7 7LS",
    "sg:province":"West Yorkshire",
    "sg:tags":[
        "mobile",
        "disco"
    ],
    "wof:name":"Astro Mobile Disco",
    "wof:placetype":"venue"
},
  "geometry": {"coordinates":[-2.0170209408,53.745174408],"type":"Point"}
}