{
  "type": "Feature",
  "properties": {
    "addr:full":"16 High St, Cheddington Leighton Buzzard Bedfordshire LU7 0RQ",
    "addr:housenumber":"16",
    "addr:postcode":"lu7 0rq",
    "addr:street":"High St",
    "iso:country":"GB",
    "sg:address":"16 High St, Cheddington",
    "sg:city":"Leighton Buzzard",
    "sg:classifiers":[
        {
            "category":"Autos & Motor Vehicles",
            "subcategory":"Automobile Sales",
            "type":"Retail Goods"
        }
    ],
    "sg:postcode":"LU7 0RQ",
    "sg:province":"Bedfordshire",
    "sg:tags":[
        "car"
    ],
    "wof:name":"Marzex,Martin,",
    "wof:placetype":"venue"
},
  "geometry": {"coordinates":[-0.7240179777,51.904586792],"type":"Point"}
}