{
  "type": "Feature",
  "properties": {
    "iso:country":"GB",
    "sg:address":"New Court, St Swithin's Lane",
    "sg:city":"London",
    "sg:classifiers":[
        {
            "category":"Banks & Credit Unions",
            "subcategory":"Bank",
            "type":"Services"
        }
    ],
    "sg:phone":"+44 20 7280 5000",
    "sg:postcode":"EC4P 4DU",
    "sg:province":"Greater London",
    "wof:name":"Rothschild Nominees Ltd.",
    "wof:placetype":"venue"
},
  "geometry": {"coordinates":[-0.1059200019,51.5139389038],"type":"Point"}
}