{
  "type": "Feature",
  "properties": {
    "iso:country":"GB",
    "sg:address":"Landford Common Farm, New Rd",
    "sg:city":"Salisbury",
    "sg:classifiers":[
        {
            "category":"Shopping",
            "subcategory":"Pets & Pet Supplies",
            "type":"Retail Goods"
        }
    ],
    "sg:phone":"+44 1794 323305",
    "sg:postcode":"SP5 2AZ",
    "sg:province":"Dorset",
    "sg:tags":[
        "food"
    ],
    "wof:name":"Johnston Horse Feeds",
    "wof:placetype":"venue"
},
  "geometry": {"coordinates":[-1.7176309824,50.9928588867],"type":"Point"}
}