{
  "type": "Feature",
  "properties": {
    "addr:full":"79 King Street Castle Douglas Dumfries and Galloway DG7 1AH",
    "addr:housenumber":"79",
    "addr:postcode":"dg7 1ah",
    "addr:street":"King Street",
    "iso:country":"GB",
    "sg:address":"79 King Street",
    "sg:city":"Castle Douglas",
    "sg:classifiers":[
        {
            "category":"Shopping",
            "subcategory":"Pharmacy",
            "type":"Retail Goods"
        }
    ],
    "sg:phone":"+44 1556 502026",
    "sg:postcode":"DG7 1AH",
    "sg:province":"Dumfries and Galloway",
    "sg:tags":[
        "pharmacist",
        "chemist"
    ],
    "wof:name":"Moss Chemists",
    "wof:placetype":"venue"
},
  "geometry": {"coordinates":[-3.9287788868,54.9413375854],"type":"Point"}
}