{
  "type": "Feature",
  "properties": {
    "addr:full":"Queensgate Centre, Edinburgh Way Harlow Essex CM20 2AG",
    "addr:postcode":"cm20 2ag",
    "addr:street":"Queensgate;Edinburgh Way",
    "iso:country":"GB",
    "sg:address":"Queensgate Centre, Edinburgh Way",
    "sg:city":"Harlow",
    "sg:classifiers":[
        {
            "category":"Cinema",
            "subcategory":"Movie Theater",
            "type":"Entertainment"
        }
    ],
    "sg:phone":"+44 1279 436014",
    "sg:postcode":"CM20 2AG",
    "sg:province":"Essex",
    "wof:name":"UGC Cinemas",
    "wof:placetype":"venue"
},
  "geometry": {"coordinates":[0.0975060016,51.7731513977],"type":"Point"}
}