{
  "type": "Feature",
  "properties": {
    "addr:full":"New House, Fen End Farm King's Lynn Norfolk PE32 1DA",
    "addr:postcode":"pe32 1da",
    "addr:street":"Fen End",
    "iso:country":"GB",
    "sg:address":"New House, Fen End Farm",
    "sg:city":"King's Lynn",
    "sg:classifiers":[
        {
            "category":"Building & Trades",
            "subcategory":"Construction",
            "type":"Services"
        }
    ],
    "sg:postcode":"PE32 1DA",
    "sg:province":"Norfolk",
    "sg:tags":[
        "builder"
    ],
    "wof:name":"Ray Rudd Builders",
    "wof:placetype":"venue"
},
  "geometry": {"coordinates":[0.5261700153,52.7651596069],"type":"Point"}
}