{
  "type": "Feature",
  "properties": {
    "addr:full":"Unit 1, 75 Raleigh St Nottingham Nottinghamshire NG7 4DL",
    "addr:housenumber":"unit;75",
    "addr:postcode":"ng7 4dl",
    "addr:street":"Raleigh St",
    "iso:country":"GB",
    "sg:address":"Unit 1, 75 Raleigh St",
    "sg:city":"Nottingham",
    "sg:classifiers":[
        {
            "category":"Professional",
            "type":"Services"
        }
    ],
    "sg:phone":"+44 115 950 3208",
    "sg:postcode":"NG7 4DL",
    "sg:province":"Nottinghamshire",
    "sg:tags":[
        "interior",
        "furnishers",
        "designer"
    ],
    "wof:name":"Demaine",
    "wof:placetype":"venue"
},
  "geometry": {"coordinates":[-1.1609790325,52.9601783752],"type":"Point"}
}