{
  "type": "Feature",
  "properties": {
    "iso:country":"GB",
    "sg:address":"34 Potters Lane",
    "sg:city":"Barnet",
    "sg:classifiers":[
        {
            "category":"Home & Garden",
            "subcategory":"Garden Supply",
            "type":"Retail Goods"
        }
    ],
    "sg:postcode":"EN5 5BE",
    "sg:province":"Hertfordshire",
    "sg:tags":[
        "turfing"
    ],
    "wof:name":"J D Gardening Services",
    "wof:placetype":"venue"
},
  "geometry": {"coordinates":[-0.188477,51.651173],"type":"Point"}
}