{
  "type": "Feature",
  "properties": {
    "iso:country":"GB",
    "sg:address":"Old Market House, The Quay",
    "sg:city":"Brixham",
    "sg:classifiers":[
        {
            "category":"Landmark",
            "subcategory":"Tourist Attraction",
            "type":"Public Place"
        }
    ],
    "sg:phone":"+44 1803 858444",
    "sg:postcode":"TQ5 8AW",
    "sg:province":"Devon",
    "sg:tags":[
        "interest"
    ],
    "wof:name":"The Deep",
    "wof:placetype":"venue"
},
  "geometry": {"coordinates":[-3.513034,50.397018],"type":"Point"}
}