{
  "type": "Feature",
  "properties": {
    "addr:full":"G Block, Brecklands, Lingord Wood Milton Keynes Buckinghamshire MK14 6NB",
    "addr:postcode":"mk14 6nb",
    "addr:street":"Wood",
    "iso:country":"GB",
    "sg:address":"G Block, Brecklands, Lingord Wood",
    "sg:city":"Milton Keynes",
    "sg:classifiers":[
        {
            "category":"Professional",
            "subcategory":"Business Services",
            "type":"Services"
        }
    ],
    "sg:phone":"+44 1908 220908",
    "sg:postcode":"MK14 6NB",
    "sg:province":"Buckinghamshire",
    "sg:tags":[
        "trade"
    ],
    "wof:name":"B.S.I",
    "wof:placetype":"venue"
},
  "geometry": {"coordinates":[-0.74982,52.060501],"type":"Point"}
}