{
  "type": "Feature",
  "properties": {
    "addr:full":"42 Abbotts Rd Southall Greater London UB1 1HT",
    "addr:housenumber":"42",
    "addr:postcode":"ub1 1ht",
    "addr:street":"Abbotts Rd",
    "iso:country":"GB",
    "sg:address":"42 Abbotts Rd",
    "sg:city":"Southall",
    "sg:classifiers":[
        {
            "category":"Health Services",
            "subcategory":"Doctor",
            "type":"Services"
        }
    ],
    "sg:phone":"+44 20 8574 7746",
    "sg:postcode":"UB1 1HT",
    "sg:province":"Greater London",
    "sg:tags":[
        "practitioners"
    ],
    "wof:name":"K.T Maw",
    "wof:placetype":"venue"
},
  "geometry": {"coordinates":[-0.3827329874,51.5106201172],"type":"Point"}
}