{
  "type": "Feature",
  "properties": {
    "iso:country":"GB",
    "sg:address":"Camp Road",
    "sg:city":"St Albans",
    "sg:classifiers":[
        {
            "category":"Education",
            "subcategory":"School",
            "type":"Public Place"
        }
    ],
    "sg:phone":"+44 1727 851056",
    "sg:postcode":"AL1 5PG",
    "sg:province":"Hertfordshire",
    "sg:tags":[
        "local",
        "authority"
    ],
    "wof:name":"Camp Infant School",
    "wof:placetype":"venue"
},
  "geometry": {"coordinates":[-0.322651,51.750702],"type":"Point"}
}