{
  "type": "Feature",
  "properties": {
    "addr:full":"Brunel Drive Newark Nottinghamshire NG24 2DE",
    "addr:postcode":"ng24 2de",
    "addr:street":"Brunel Drive",
    "iso:country":"GB",
    "sg:address":"Brunel Drive",
    "sg:city":"Newark",
    "sg:classifiers":[
        {
            "category":"Bakery",
            "type":"Food & Drink"
        }
    ],
    "sg:phone":"+44 1636 680123",
    "sg:postcode":"NG24 2DE",
    "sg:province":"Nottinghamshire",
    "sg:tags":[
        "cake",
        "maker"
    ],
    "wof:name":"The Dessert Co",
    "wof:placetype":"venue"
},
  "geometry": {"coordinates":[-0.7868390083,53.0882263184],"type":"Point"}
}