{
  "type": "Feature",
  "properties": {
    "iso:country":"GB",
    "sg:address":"90-92 Manchester Road",
    "sg:city":"Leigh",
    "sg:classifiers":[
        {
            "category":"Shopping",
            "subcategory":"Pharmacy",
            "type":"Retail Goods"
        }
    ],
    "sg:phone":"+44 1942 674283",
    "sg:postcode":"WN7 2LD",
    "sg:province":"Lancashire",
    "sg:tags":[
        "pharmacist",
        "chemist"
    ],
    "wof:name":"Showman's Chemist",
    "wof:placetype":"venue"
},
  "geometry": {"coordinates":[-2.4955120087,53.4944229126],"type":"Point"}
}