{
  "type": "Feature",
  "properties": {
    "addr:full":"Old London Road Hastings East Sussex TN35 5BH",
    "addr:postcode":"tn35 5bh",
    "addr:street":"Old London Road",
    "iso:country":"GB",
    "sg:address":"Old London Road",
    "sg:city":"Hastings",
    "sg:classifiers":[
        {
            "category":"Health Services",
            "subcategory":"Clinic",
            "type":"Services"
        }
    ],
    "sg:phone":"+44 1424 448400",
    "sg:postcode":"TN35 5BH",
    "sg:province":"East Sussex",
    "sg:tags":[
        "nh"
    ],
    "wof:name":"Ore Clinic",
    "wof:placetype":"venue"
},
  "geometry": {"coordinates":[0.6072030067,50.8746147156],"type":"Point"}
}