{
  "type": "Feature",
  "properties": {
    "addr:full":"28 Connaught Street London Greater London W2 2AF",
    "addr:housenumber":"28",
    "addr:postcode":"w2 2af",
    "addr:street":"Connaught Street",
    "iso:country":"GB",
    "sg:address":"28 Connaught Street",
    "sg:city":"London",
    "sg:classifiers":[
        {
            "category":"Personal",
            "type":"Services"
        }
    ],
    "sg:phone":"+44 20 7706 0708",
    "sg:postcode":"W2 2AF",
    "sg:province":"Greater London",
    "sg:tags":[
        "wedding"
    ],
    "wof:name":"Ritva Westerius",
    "wof:placetype":"venue"
},
  "geometry": {"coordinates":[-0.165871,51.514648],"type":"Point"}
}