{
  "type": "Feature",
  "properties": {
    "addr:full":"Roxeth Hill Harrow Greater London HA2 0JX",
    "addr:postcode":"ha2 0jx",
    "addr:street":"Roxeth Hill",
    "iso:country":"GB",
    "sg:address":"Roxeth Hill",
    "sg:city":"Harrow",
    "sg:classifiers":[
        {
            "category":"Health Services",
            "subcategory":"Hospital",
            "type":"Services"
        }
    ],
    "sg:phone":"+44 20 8956 3200",
    "sg:postcode":"HA2 0JX",
    "sg:province":"Greater London",
    "wof:name":"Harrow And Elendon Nhs Trust",
    "wof:placetype":"venue"
},
  "geometry": {"coordinates":[-0.34381,51.568745],"type":"Point"}
}