{
  "type": "Feature",
  "properties": {
    "addr:full":"Commerce House Whitbrook Way, Stakehill Industrial Estate Manchester Greater Manchester M24 2SS",
    "addr:postcode":"m24 2ss",
    "addr:street":"Whitbrook Way Stakehill Industrial Estate",
    "iso:country":"GB",
    "sg:address":"Commerce House Whitbrook Way, Stakehill Industrial Estate",
    "sg:city":"Manchester",
    "sg:classifiers":[
        {
            "category":"Professional",
            "subcategory":"Detective & Security Services",
            "type":"Services"
        }
    ],
    "sg:postcode":"M24 2SS",
    "sg:province":"Greater Manchester",
    "sg:tags":[
        "equipment"
    ],
    "wof:name":"Gardiner Technology Ltd.",
    "wof:placetype":"venue"
},
  "geometry": {"coordinates":[-2.1741020679,53.5709381104],"type":"Point"}
}