{
  "type": "Feature",
  "properties": {
    "iso:country":"GB",
    "sg:address":"1 Westfield Terrace, Hartley",
    "sg:city":"Cranbrook",
    "sg:classifiers":[
        {
            "category":"Wholesale",
            "subcategory":"Groceries",
            "type":"Manufacturing & Wholesale Goods"
        },
        {
            "category":"Food & Beverages",
            "subcategory":"Ethnic Foods",
            "type":"Retail Goods"
        }
    ],
    "sg:phone":"+44 1580 713581",
    "sg:postcode":"TN17 3PX",
    "sg:province":"Kent",
    "sg:tags":[
        "supplier",
        "drink",
        "catering"
    ],
    "wof:name":"C W Parker & Son",
    "wof:placetype":"venue"
},
  "geometry": {"coordinates":[0.510253,51.082272],"type":"Point"}
}