{
  "type": "Feature",
  "properties": {
    "addr:full":"P O Box 12, West Corby Wirral Merseyside CH48 8AT",
    "addr:housenumber":"box 12",
    "addr:postcode":"ch48 8at",
    "addr:street":"P O;West Corby",
    "iso:country":"GB",
    "sg:address":"P O Box 12, West Corby",
    "sg:city":"Wirral",
    "sg:classifiers":[
        {
            "category":"Building & Trades",
            "subcategory":"Construction",
            "type":"Services"
        }
    ],
    "sg:phone":"+44 151 625 5479",
    "sg:postcode":"CH48 8AT",
    "sg:province":"Merseyside",
    "sg:tags":[
        "builder"
    ],
    "wof:name":"Caldy Construction Co. Ltd.",
    "wof:placetype":"venue"
},
  "geometry": {"coordinates":[-3.1604299545,53.3671302795],"type":"Point"}
}