{
  "type": "Feature",
  "properties": {
    "addr:full":"38 York Avenue, Moorside Consett Durham DH8 8DS",
    "addr:housenumber":"38",
    "addr:postcode":"dh8 8ds",
    "addr:street":"York Avenue",
    "iso:country":"GB",
    "sg:address":"38 York Avenue, Moorside",
    "sg:city":"Consett",
    "sg:classifiers":[
        {
            "category":"Personal",
            "subcategory":"Beauty Salon",
            "type":"Services"
        }
    ],
    "sg:phone":"+44 1207 508002",
    "sg:postcode":"DH8 8DS",
    "sg:province":"Durham",
    "sg:tags":[
        "unisex",
        "hairdresser"
    ],
    "wof:name":"Castleside Hair Fashions",
    "wof:placetype":"venue"
},
  "geometry": {"coordinates":[-1.8712869883,54.8377571106],"type":"Point"}
}