{
  "type": "Feature",
  "properties": {
    "addr:full":"Unit 9, Eastwood Road Peterborough Cambridgeshire PE8 4DF",
    "addr:housenumber":"unit 9",
    "addr:postcode":"pe8 4df",
    "addr:street":"Eastwood Road",
    "iso:country":"GB",
    "sg:address":"Unit 9, Eastwood Road",
    "sg:city":"Peterborough",
    "sg:classifiers":[
        {
            "category":"Shopping",
            "subcategory":"Florist",
            "type":"Retail Goods"
        }
    ],
    "sg:phone":"+44 1832 273255",
    "sg:postcode":"PE8 4DF",
    "sg:province":"Cambridgeshire",
    "wof:name":"Hillyards of Oundle",
    "wof:placetype":"venue"
},
  "geometry": {"coordinates":[-0.4644269943,52.4834747314],"type":"Point"}
}