{
  "type": "Feature",
  "properties": {
    "iso:country":"GB",
    "sg:address":"1 Prince Of Wales Drive",
    "sg:city":"Neath",
    "sg:classifiers":[
        {
            "category":"Shopping",
            "subcategory":"Pharmacy",
            "type":"Retail Goods"
        }
    ],
    "sg:phone":"+44 1639 635654",
    "sg:postcode":"SA11 3EW",
    "sg:province":"Neath Port Talbot",
    "sg:tags":[
        "pharmacist",
        "dispensing",
        "chemist"
    ],
    "wof:name":"Versesure Ltd",
    "wof:placetype":"venue"
},
  "geometry": {"coordinates":[-3.802289,51.66515],"type":"Point"}
}