{
  "type": "Feature",
  "properties": {
    "addr:full":"Battersea Rise London Greater London SW11 1HS",
    "addr:postcode":"sw11 1hs",
    "addr:street":"Battersea Rise",
    "iso:country":"GB",
    "sg:address":"Battersea Rise",
    "sg:city":"London",
    "sg:classifiers":[
        {
            "category":"Education",
            "subcategory":"School",
            "type":"Public Place"
        }
    ],
    "sg:phone":"+44 20 8870 4171",
    "sg:postcode":"SW11 1HS",
    "sg:province":"Greater London",
    "sg:tags":[
        "independent",
        "preparatory"
    ],
    "sg:website":"http://www.emanuel.org.uk",
    "wof:name":"Emanuel School",
    "wof:placetype":"venue"
},
  "geometry": {"coordinates":[-0.164579,51.460911],"type":"Point"}
}