{
  "type": "Feature",
  "properties": {
    "addr:full":"78 Albert Road Colne Lancashire BB8 0AG",
    "addr:housenumber":"78",
    "addr:postcode":"bb8 0ag",
    "addr:street":"Albert Road",
    "iso:country":"GB",
    "sg:address":"78 Albert Road",
    "sg:city":"Colne",
    "sg:classifiers":[
        {
            "category":"Travel",
            "subcategory":"Hotels & Motels",
            "type":"Entertainment"
        },
        {
            "category":"Food & Beverages",
            "subcategory":"Supermarket",
            "type":"Retail Goods"
        }
    ],
    "sg:phone":"+44 1282 864072",
    "sg:postcode":"BB8 0AG",
    "sg:province":"Lancashire",
    "sg:tags":[
        "frozen",
        "house",
        "guest"
    ],
    "wof:name":"Napolina",
    "wof:placetype":"venue"
},
  "geometry": {"coordinates":[-2.1783399582,53.855430603],"type":"Point"}
}