{
  "type": "Feature",
  "properties": {
    "addr:full":"559 Loxley Road, Loxley Sheffield South Yorkshire S6 6RR",
    "addr:housenumber":"559",
    "addr:postcode":"s6 6rr",
    "addr:street":"Loxley Road",
    "iso:country":"GB",
    "sg:address":"559 Loxley Road, Loxley",
    "sg:city":"Sheffield",
    "sg:classifiers":[
        {
            "category":"Building & Trades",
            "subcategory":"Construction",
            "type":"Services"
        }
    ],
    "sg:phone":"+44 114 232 0128",
    "sg:postcode":"S6 6RR",
    "sg:province":"South Yorkshire",
    "sg:tags":[
        "roofing"
    ],
    "wof:name":"A J  Electrical Ltd.",
    "wof:placetype":"venue"
},
  "geometry": {"coordinates":[-1.534925,53.40424],"type":"Point"}
}