{
  "type": "Feature",
  "properties": {
    "addr:full":"75 Lincoln Crescent Enfield Greater London EN1 1JZ",
    "addr:housenumber":"75",
    "addr:postcode":"en1 1jz",
    "addr:street":"Lincoln Crescent",
    "iso:country":"GB",
    "sg:address":"75 Lincoln Crescent",
    "sg:city":"Enfield",
    "sg:classifiers":[
        {
            "category":"Building & Trades",
            "subcategory":"Construction",
            "type":"Services"
        }
    ],
    "sg:postcode":"EN1 1JZ",
    "sg:province":"Greater London",
    "sg:tags":[
        "decorator",
        "painter"
    ],
    "wof:name":"R & K Builders",
    "wof:placetype":"venue"
},
  "geometry": {"coordinates":[-0.0705370009,51.6461639404],"type":"Point"}
}