{
  "type": "Feature",
  "properties": {
    "addr:full":"1 King Road, Warsop Mansfield Derbyshire NG20 0BQ",
    "addr:housenumber":"1",
    "addr:postcode":"ng20 0bq",
    "addr:street":"King Road",
    "iso:country":"GB",
    "sg:address":"1 King Road, Warsop",
    "sg:city":"Mansfield",
    "sg:classifiers":[
        {
            "category":"Shopping",
            "subcategory":"Department Store",
            "type":"Retail Goods"
        }
    ],
    "sg:phone":"+44 1623 842261",
    "sg:postcode":"NG20 0BQ",
    "sg:province":"Derbyshire",
    "wof:name":"Wine Bibber",
    "wof:placetype":"venue"
},
  "geometry": {"coordinates":[-1.156707,53.205421],"type":"Point"}
}