{
  "type": "Feature",
  "properties": {
    "addr:full":"The Vicarage, The Plestor Alton Hampshire GU34 3JQ",
    "addr:housenumber":"the",
    "addr:postcode":"gu34 3jq",
    "addr:street":"Alton",
    "iso:country":"GB",
    "sg:address":"The Vicarage, The Plestor",
    "sg:city":"Alton",
    "sg:classifiers":[
        {
            "category":"Place Of Worship",
            "type":"Public Place"
        }
    ],
    "sg:phone":"+44 1420 511242",
    "sg:postcode":"GU34 3JQ",
    "sg:province":"Hampshire",
    "wof:name":"Selborne Parish Church",
    "wof:placetype":"venue"
},
  "geometry": {"coordinates":[-0.985304,51.110645],"type":"Point"}
}