{
  "type": "Feature",
  "properties": {
    "iso:country":"GB",
    "sg:address":"8 Lyndhurst Road",
    "sg:city":"Exeter",
    "sg:classifiers":[
        {
            "category":"Health Services",
            "subcategory":"Doctor",
            "type":"Services"
        }
    ],
    "sg:phone":"+44 1392 439551",
    "sg:postcode":"EX2 4PA",
    "sg:province":"Devon",
    "sg:tags":[
        "surgeon"
    ],
    "wof:name":"V S Devaraj",
    "wof:placetype":"venue"
},
  "geometry": {"coordinates":[-3.516645,50.718777],"type":"Point"}
}