{
  "type": "Feature",
  "properties": {
    "iso:country":"GB",
    "sg:address":"1-7 Old Irvine Road",
    "sg:city":"Kilmarnock",
    "sg:classifiers":[
        {
            "category":"Autos & Motor Vehicles",
            "subcategory":"Auto Supplies",
            "type":"Retail Goods"
        },
        {
            "category":"Retail",
            "subcategory":"Auto Repair",
            "type":"Services"
        }
    ],
    "sg:phone":"+44 1563 522819",
    "sg:postcode":"KA1 2BD",
    "sg:province":"East Ayrshire",
    "sg:tags":[
        "car",
        "specialist",
        "tyre",
        "customizing"
    ],
    "wof:name":"City Tyres & Exhausts Ltd.",
    "wof:placetype":"venue"
},
  "geometry": {"coordinates":[-4.5040688515,55.6088485718],"type":"Point"}
}