{
  "type": "Feature",
  "properties": {
    "iso:country":"GB",
    "sg:address":"Victoria Drive, Old Town",
    "sg:city":"Eastbourne",
    "sg:classifiers":[
        {
            "category":"Education",
            "subcategory":"Library",
            "type":"Public Place"
        },
        {
            "category":"Government",
            "subcategory":"Office",
            "type":"Public Place"
        }
    ],
    "sg:phone":"+44 1323 732516",
    "sg:postcode":"BN20 8QJ",
    "sg:province":"East Sussex",
    "sg:tags":[
        "book",
        "local"
    ],
    "wof:name":"Old Town Library",
    "wof:placetype":"venue"
},
  "geometry": {"coordinates":[0.255712,50.787689],"type":"Point"}
}