{
  "type": "Feature",
  "properties": {
    "addr:full":"22 Carlooe Crescent, Alloway Ayr South Ayrshire KA7 4SS",
    "addr:housenumber":"22",
    "addr:postcode":"ka7 4ss",
    "addr:street":"Carlooe Crescent Alloway",
    "iso:country":"GB",
    "sg:address":"22 Carlooe Crescent, Alloway",
    "sg:city":"Ayr",
    "sg:classifiers":[
        {
            "category":"Home & Garden",
            "subcategory":"Household Appliances",
            "type":"Retail Goods"
        }
    ],
    "sg:phone":"+44 1292 441679",
    "sg:postcode":"KA7 4SS",
    "sg:province":"South Ayrshire",
    "sg:tags":[
        "electrical",
        "domestic"
    ],
    "wof:name":"Resource Technology",
    "wof:placetype":"venue"
},
  "geometry": {"coordinates":[-4.6356210709,55.4315605164],"type":"Point"}
}