{
  "type": "Feature",
  "properties": {
    "addr:full":"403 London Road (opp Rising Sun), Hazel Gro Stockport Cheshire SK7 6AA",
    "addr:housenumber":"403;rising sun",
    "addr:postcode":"sk7 6aa",
    "addr:street":"London Road",
    "iso:country":"GB",
    "sg:address":"403 London Road (opp Rising Sun), Hazel Gro",
    "sg:city":"Stockport",
    "sg:classifiers":[
        {
            "category":"Restaurant",
            "type":"Food & Drink"
        }
    ],
    "sg:phone":"+44 161 487 4490",
    "sg:postcode":"SK7 6AA",
    "sg:province":"Cheshire",
    "sg:tags":[
        "indian"
    ],
    "wof:name":"Balti Massala",
    "wof:placetype":"venue"
},
  "geometry": {"coordinates":[-2.11399,53.375839],"type":"Point"}
}