{
  "type": "Feature",
  "properties": {
    "addr:full":"19 Horndon Industrial Park Brentwood Essex CM13 3XD",
    "addr:housenumber":"19",
    "addr:postcode":"cm13 3xd",
    "addr:street":"Horndon Industrial Park",
    "iso:country":"GB",
    "sg:address":"19 Horndon Industrial Park",
    "sg:city":"Brentwood",
    "sg:classifiers":[
        {
            "category":"Professional",
            "subcategory":"Engineering",
            "type":"Services"
        }
    ],
    "sg:phone":"+44 1277 811251",
    "sg:postcode":"CM13 3XD",
    "sg:province":"Essex",
    "wof:name":"Special Metals Fabrication Ltd",
    "wof:placetype":"venue"
},
  "geometry": {"coordinates":[0.3207539916,51.599899292],"type":"Point"}
}