{
  "type": "Feature",
  "properties": {
    "addr:full":"158 Mid Summer Arcade, Milton Keynes Shopping Centre Milton Keynes Buckinghamshire MK9 3BA",
    "addr:housenumber":"158",
    "addr:postcode":"mk9 3ba",
    "addr:street":"Mid Summer",
    "iso:country":"GB",
    "sg:address":"158 Mid Summer Arcade, Milton Keynes Shopping Centre",
    "sg:city":"Milton Keynes",
    "sg:classifiers":[
        {
            "category":"Coffee & Tea",
            "type":"Food & Drink"
        },
        {
            "category":"Cafe",
            "type":"Food & Drink"
        }
    ],
    "sg:phone":"+44 1908 394266",
    "sg:postcode":"MK9 3BA",
    "sg:province":"Buckinghamshire",
    "sg:tags":[
        "shop",
        "room"
    ],
    "sg:website":"http://www.costa.co.uk",
    "wof:name":"Costa Coffee Ltd",
    "wof:placetype":"venue"
},
  "geometry": {"coordinates":[-0.7538689971,52.042930603],"type":"Point"}
}