{
  "type": "Feature",
  "properties": {
    "iso:country":"GB",
    "sg:address":"Leicester Square, Penshurst",
    "sg:city":"Tonbridge",
    "sg:classifiers":[
        {
            "category":"Building & Trades",
            "subcategory":"Pest Control",
            "type":"Services"
        }
    ],
    "sg:phone":"+44 1892 870164",
    "sg:postcode":"TN11 8BJ",
    "sg:province":"Kent",
    "sg:tags":[
        "vermin"
    ],
    "wof:name":"Enviroguard (U K) Ltd.",
    "wof:placetype":"venue"
},
  "geometry": {"coordinates":[0.1833779961,51.1728515625],"type":"Point"}
}