{
  "type": "Feature",
  "properties": {
    "addr:full":"2 Carnforth Parade Grimsby Lincolnshire DN34 5LA",
    "addr:housenumber":"2",
    "addr:postcode":"dn34 5la",
    "addr:street":"Carnforth Parade",
    "iso:country":"GB",
    "sg:address":"2 Carnforth Parade",
    "sg:city":"Grimsby",
    "sg:classifiers":[
        {
            "category":"Fast Food",
            "type":"Food & Drink"
        }
    ],
    "sg:phone":"+44 1472 877355",
    "sg:postcode":"DN34 5LA",
    "sg:province":"Lincolnshire",
    "sg:tags":[
        "away",
        "meal",
        "outlet",
        "take"
    ],
    "wof:name":"Nick's Takeaway",
    "wof:placetype":"venue"
},
  "geometry": {"coordinates":[-0.1125700027,53.5520248413],"type":"Point"}
}