{
  "type": "Feature",
  "properties": {
    "addr:full":"Beeleigh, Langford Maldon Essex CM9 6LL",
    "addr:postcode":"cm9 6ll",
    "addr:street":"Beeleigh Langford",
    "iso:country":"GB",
    "sg:address":"Beeleigh, Langford",
    "sg:city":"Maldon",
    "sg:classifiers":[
        {
            "category":"Sports & Exercise",
            "subcategory":"Golf",
            "type":"Entertainment"
        }
    ],
    "sg:phone":"+44 1621 853212",
    "sg:postcode":"CM9 6LL",
    "sg:province":"Essex",
    "sg:tags":[
        "club",
        "course"
    ],
    "wof:name":"Maldon Golf Club",
    "wof:placetype":"venue"
},
  "geometry": {"coordinates":[0.6631330252,51.7400627136],"type":"Point"}
}