{
  "type": "Feature",
  "properties": {
    "addr:full":"Longwater Industrial Estate Norwich Norfolk NR5 0TX",
    "addr:postcode":"nr5 0tx",
    "addr:street":"Longwater Industrial Estate Norwich Norfolk",
    "iso:country":"GB",
    "sg:address":"Longwater Industrial Estate",
    "sg:city":"Norwich",
    "sg:classifiers":[
        {
            "category":"Home & Garden",
            "subcategory":"Garden Supply",
            "type":"Retail Goods"
        }
    ],
    "sg:phone":"+44 1603 743767",
    "sg:postcode":"NR5 0TX",
    "sg:province":"Norfolk",
    "sg:tags":[
        "sand",
        "gravel"
    ],
    "wof:name":"Longwater (Gravel) Co. Ltd.",
    "wof:placetype":"venue"
},
  "geometry": {"coordinates":[1.17562,52.651402],"type":"Point"}
}