{
  "type": "Feature",
  "properties": {
    "addr:full":"Unit 1 Mill Lane Pitlochry Perth and Kinross PH16 5BH",
    "addr:housenumber":"unit 1",
    "addr:postcode":"ph16 5bh",
    "addr:street":"Mill Lane",
    "iso:country":"GB",
    "sg:address":"Unit 1 Mill Lane",
    "sg:city":"Pitlochry",
    "sg:classifiers":[
        {
            "category":"Cinema",
            "subcategory":"Movie Rental",
            "type":"Entertainment"
        }
    ],
    "sg:phone":"+44 1796 473074",
    "sg:postcode":"PH16 5BH",
    "sg:province":"Perth and Kinross",
    "sg:tags":[
        "video",
        "library"
    ],
    "wof:name":"Treasure Island",
    "wof:placetype":"venue"
},
  "geometry": {"coordinates":[-3.7342190742,56.7033157349],"type":"Point"}
}