{
  "type": "Feature",
  "properties": {
    "addr:full":"88 Templedene Avenue Staines Berkshire TW18 1LN",
    "addr:housenumber":"88",
    "addr:postcode":"tw18 1ln",
    "addr:street":"Templedene Avenue",
    "iso:country":"GB",
    "sg:address":"88 Templedene Avenue",
    "sg:city":"Staines",
    "sg:classifiers":[
        {
            "category":"Professional",
            "subcategory":"Accounting & Tax Preparation",
            "type":"Services"
        }
    ],
    "sg:phone":"+44 1784 462767",
    "sg:postcode":"TW18 1LN",
    "sg:province":"Berkshire",
    "sg:tags":[
        "accountant"
    ],
    "wof:name":"Robert Reid",
    "wof:placetype":"venue"
},
  "geometry": {"coordinates":[-0.489196986,51.4228134155],"type":"Point"}
}