{
  "type": "Feature",
  "properties": {
    "iso:country":"GB",
    "sg:address":"High Street, Scalby",
    "sg:city":"Scarborough",
    "sg:classifiers":[
        {
            "category":"Government",
            "subcategory":"Post Office",
            "type":"Public Place"
        }
    ],
    "sg:phone":"+44 1723 362710",
    "sg:postcode":"YO13 0PT",
    "sg:province":"North Yorkshire",
    "wof:name":"SCALBY POST OFFICE",
    "wof:placetype":"venue"
},
  "geometry": {"coordinates":[-0.447163,54.300362],"type":"Point"}
}