{
  "type": "Feature",
  "properties": {
    "iso:country":"GB",
    "sg:address":"2 Bray Road, Saltney",
    "sg:city":"Chester",
    "sg:classifiers":[
        {
            "category":"Autos & Motor Vehicles",
            "subcategory":"Motorcycle Sales",
            "type":"Retail Goods"
        }
    ],
    "sg:postcode":"CH4 8DL",
    "sg:province":"Cheshire",
    "sg:tags":[
        "chauffeur",
        "driven",
        "car"
    ],
    "wof:name":"David John Holland",
    "wof:placetype":"venue"
},
  "geometry": {"coordinates":[-2.9172039032,53.1772155762],"type":"Point"}
}