{
  "type": "Feature",
  "properties": {
    "addr:full":"Roundabout House, Lower Tockington Road, Tockington Bristol Gloucestershire BS32 4LE",
    "addr:postcode":"bs32 4le",
    "addr:street":"Lower Tockington Road",
    "iso:country":"GB",
    "sg:address":"Roundabout House, Lower Tockington Road, Tockington",
    "sg:city":"Bristol",
    "sg:classifiers":[
        {
            "category":"Freight",
            "type":"Transportation"
        }
    ],
    "sg:phone":"+44 1454 613335",
    "sg:postcode":"BS32 4LE",
    "sg:province":"Gloucestershire",
    "sg:tags":[
        "haulage",
        "transport",
        "road"
    ],
    "wof:name":"M K Grosvenor",
    "wof:placetype":"venue"
},
  "geometry": {"coordinates":[-2.5650498867,51.5766410828],"type":"Point"}
}