{
  "type": "Feature",
  "properties": {
    "addr:full":"8 Dunure Road, Doonfoot Ayr South Ayrshire KA7 4HR",
    "addr:housenumber":"8",
    "addr:postcode":"ka7 4hr",
    "addr:street":"Dunure Road Doonfoot",
    "iso:country":"GB",
    "sg:address":"8 Dunure Road, Doonfoot",
    "sg:city":"Ayr",
    "sg:classifiers":[
        {
            "category":"Bars & Pubs",
            "type":"Food & Drink"
        }
    ],
    "sg:phone":"+44 1292 442441",
    "sg:postcode":"KA7 4HR",
    "sg:province":"South Ayrshire",
    "sg:tags":[
        "pubs",
        "inn"
    ],
    "wof:name":"The Balgarth Brewers Fayre",
    "wof:placetype":"venue"
},
  "geometry": {"coordinates":[-4.654119,55.436604],"type":"Point"}
}