{
  "type": "Feature",
  "properties": {
    "iso:country":"GB",
    "sg:address":"Unit C7, Brookside Business Park, Greengate",
    "sg:city":"Manchester",
    "sg:classifiers":[
        {
            "category":"Shopping",
            "subcategory":"Clothing, Apparel, & Fashions",
            "type":"Retail Goods"
        }
    ],
    "sg:postcode":"M24 1GS",
    "sg:province":"Greater Manchester",
    "sg:tags":[
        "lingerie"
    ],
    "wof:name":"Impressions",
    "wof:placetype":"venue"
},
  "geometry": {"coordinates":[-2.177864,53.537895],"type":"Point"}
}