{
  "type": "Feature",
  "properties": {
    "iso:country":"GB",
    "sg:address":"Market House",
    "sg:city":"Wokingham",
    "sg:classifiers":[
        {
            "category":"Communications",
            "subcategory":"Film & Video Production",
            "type":"Services"
        }
    ],
    "sg:postcode":"RG40 1AP",
    "sg:province":"Berkshire",
    "sg:tags":[
        "pr",
        "telemarketing"
    ],
    "wof:name":"Pathfinder Property Marketing Services",
    "wof:placetype":"venue"
},
  "geometry": {"coordinates":[-0.834594,51.410801],"type":"Point"}
}