{
  "type": "Feature",
  "properties": {
    "iso:country":"GB",
    "sg:address":"34 Norwood Road",
    "sg:city":"Southall",
    "sg:classifiers":[
        {
            "category":"Personal",
            "subcategory":"Beauty Salon",
            "type":"Services"
        }
    ],
    "sg:phone":"+44 20 8574 7784",
    "sg:postcode":"UB2 4DL",
    "sg:province":"Greater London",
    "wof:name":"The Beauty Garden",
    "wof:placetype":"venue"
},
  "geometry": {"coordinates":[-0.381267,51.499176],"type":"Point"}
}