{
  "type": "Feature",
  "properties": {
    "iso:country":"GB",
    "sg:address":"58 Plymouth Road",
    "sg:city":"Tavistock",
    "sg:classifiers":[
        {
            "category":"Health Services",
            "subcategory":"Nursing And Care Facility",
            "type":"Services"
        },
        {
            "category":"Social Services",
            "subcategory":"Retirement Home",
            "type":"Services"
        }
    ],
    "sg:postcode":"PL19 8BU",
    "sg:province":"Devon",
    "sg:tags":[
        "residential"
    ],
    "wof:name":"BRENCHLEY RESIDENTIAL HOME",
    "wof:placetype":"venue"
},
  "geometry": {"coordinates":[-4.151524,50.546089],"type":"Point"}
}