{
  "type": "Feature",
  "properties": {
    "addr:full":"110 Micklegate York North Yorkshire YO1 6LW",
    "addr:housenumber":"110",
    "addr:postcode":"yo1 6lw",
    "addr:street":"Micklegate",
    "iso:country":"GB",
    "sg:address":"110 Micklegate",
    "sg:city":"York",
    "sg:classifiers":[
        {
            "category":"Manufacturing",
            "subcategory":"Tools & Machinery",
            "type":"Manufacturing & Wholesale Goods"
        }
    ],
    "sg:phone":"+44 1904 622248",
    "sg:postcode":"YO1 6LW",
    "sg:province":"North Yorkshire",
    "sg:tags":[
        "society",
        "friendly"
    ],
    "wof:name":"National Deposit Friendly Society",
    "wof:placetype":"venue"
},
  "geometry": {"coordinates":[-1.089867,53.956791],"type":"Point"}
}