{
  "type": "Feature",
  "properties": {
    "addr:full":"Unit 8 Pennywell Business Centre, Portsmouth Road Sunderland Tyne and Wear SR4 9AR",
    "addr:housenumber":"unit 8",
    "addr:postcode":"sr4 9ar",
    "addr:street":"Pennywell Business Centre Portsmouth Road",
    "iso:country":"GB",
    "sg:address":"Unit 8 Pennywell Business Centre, Portsmouth Road",
    "sg:city":"Sunderland",
    "sg:classifiers":[
        {
            "category":"Home & Garden",
            "subcategory":"Building Materials",
            "type":"Retail Goods"
        }
    ],
    "sg:postcode":"SR4 9AR",
    "sg:province":"Tyne and Wear",
    "sg:tags":[
        "ironwork",
        "wrought"
    ],
    "wof:name":"Vulcan Traditional Iron Works",
    "wof:placetype":"venue"
},
  "geometry": {"coordinates":[-1.4388289452,54.8953018188],"type":"Point"}
}