{
  "type": "Feature",
  "properties": {
    "addr:full":"Chester Brook House, Portside North Ellesmere Port Cheshire CH65 2HQ",
    "addr:postcode":"ch65 2hq",
    "addr:street":"Chester;Portside North",
    "iso:country":"GB",
    "sg:address":"Chester Brook House, Portside North",
    "sg:city":"Ellesmere Port",
    "sg:classifiers":[
        {
            "category":"Professional",
            "subcategory":"Computer Services",
            "type":"Services"
        }
    ],
    "sg:phone":"+44 151 355 4555",
    "sg:postcode":"CH65 2HQ",
    "sg:province":"Cheshire",
    "sg:tags":[
        "system",
        "software"
    ],
    "wof:name":"Chesterbrook Computer Systems Ltd.",
    "wof:placetype":"venue"
},
  "geometry": {"coordinates":[-2.8978,53.289261],"type":"Point"}
}