{
  "type": "Feature",
  "properties": {
    "addr:full":"Lime Grove Works London Greater London W12 8EE",
    "addr:postcode":"w12 8ee",
    "addr:street":"Lime Grove",
    "iso:country":"GB",
    "sg:address":"Lime Grove Works",
    "sg:city":"London",
    "sg:classifiers":[
        {
            "category":"Real Estate",
            "subcategory":"Architect",
            "type":"Services"
        }
    ],
    "sg:phone":"+44 20 8762 0880",
    "sg:postcode":"W12 8EE",
    "sg:province":"Greater London",
    "wof:name":"Dominic Warren Architects",
    "wof:placetype":"venue"
},
  "geometry": {"coordinates":[-0.2274499983,51.5040092468],"type":"Point"}
}