{
  "type": "Feature",
  "properties": {
    "addr:full":"Club House, Cilsanws Merthyr Tydfil Caerphilly CF48 2NU",
    "addr:postcode":"cf48 2nu",
    "addr:street":"Club;Cilsanws",
    "iso:country":"GB",
    "sg:address":"Club House, Cilsanws",
    "sg:city":"Merthyr Tydfil",
    "sg:classifiers":[
        {
            "category":"Sports & Exercise",
            "subcategory":"Golf",
            "type":"Entertainment"
        }
    ],
    "sg:phone":"+44 1685 723308",
    "sg:postcode":"CF48 2NU",
    "sg:province":"Caerphilly",
    "sg:tags":[
        "club",
        "course"
    ],
    "wof:name":"Merthyr Cilsanws Golf Club",
    "wof:placetype":"venue"
},
  "geometry": {"coordinates":[-3.405214,51.762943],"type":"Point"}
}