{
  "type": "Feature",
  "properties": {
    "addr:full":"54 London Road Leicester Leicestershire LE2 0QD",
    "addr:housenumber":"54",
    "addr:postcode":"le2 0qd",
    "addr:street":"London Road",
    "iso:country":"GB",
    "sg:address":"54 London Road",
    "sg:city":"Leicester",
    "sg:classifiers":[
        {
            "category":"Shopping",
            "subcategory":"Hobbies, Toys, & Games",
            "type":"Retail Goods"
        }
    ],
    "sg:phone":"+44 116 254 3110",
    "sg:postcode":"LE2 0QD",
    "sg:province":"Leicestershire",
    "sg:tags":[
        "stamp"
    ],
    "wof:name":"London Road Stamp Centre",
    "wof:placetype":"venue"
},
  "geometry": {"coordinates":[-1.124258,52.630241],"type":"Point"}
}