{
  "type": "Feature",
  "properties": {
    "addr:full":"17 Melbourne Road, Balby Doncaster South Yorkshire DN4 0UN",
    "addr:housenumber":"17",
    "addr:postcode":"dn4 0un",
    "addr:street":"Melbourne Road",
    "iso:country":"GB",
    "sg:address":"17 Melbourne Road, Balby",
    "sg:city":"Doncaster",
    "sg:classifiers":[
        {
            "category":"Building & Trades",
            "subcategory":"Construction",
            "type":"Services"
        }
    ],
    "sg:phone":"+44 1302 340999",
    "sg:postcode":"DN4 0UN",
    "sg:province":"South Yorkshire",
    "sg:tags":[
        "joinery"
    ],
    "wof:name":"David Wilkinson Ltd.",
    "wof:placetype":"venue"
},
  "geometry": {"coordinates":[-1.1707880497,53.5015258789],"type":"Point"}
}