{
  "type": "Feature",
  "properties": {
    "addr:full":"Provost Robson Drive Laurencekirk Aberdeenshire AB30 1FT",
    "addr:postcode":"ab30 1ft",
    "addr:street":"Robson Drive",
    "iso:country":"GB",
    "sg:address":"Provost Robson Drive",
    "sg:city":"Laurencekirk",
    "sg:classifiers":[
        {
            "category":"Social Services",
            "subcategory":"Adult Care",
            "type":"Services"
        },
        {
            "category":"Government",
            "subcategory":"Office",
            "type":"Public Place"
        }
    ],
    "sg:phone":"+44 1561 377612",
    "sg:postcode":"AB30 1FT",
    "sg:province":"Aberdeenshire",
    "sg:tags":[
        "housing",
        "local",
        "sheltered"
    ],
    "wof:name":"Mearns Court",
    "wof:placetype":"venue"
},
  "geometry": {"coordinates":[-2.475489,56.830406],"type":"Point"}
}