{
  "type": "Feature",
  "properties": {
    "addr:full":"13 The Ridings, Bramber Steyning West Sussex BN44 3PX",
    "addr:housenumber":"13",
    "addr:postcode":"bn44 3px",
    "addr:street":"The Ridings",
    "iso:country":"GB",
    "sg:address":"13 The Ridings, Bramber",
    "sg:city":"Steyning",
    "sg:classifiers":[
        {
            "category":"Health Services",
            "subcategory":"Podiatrist",
            "type":"Services"
        }
    ],
    "sg:phone":"+44 1903 814200",
    "sg:postcode":"BN44 3PX",
    "sg:province":"West Sussex",
    "sg:tags":[
        "podiatrists",
        "chiropodist"
    ],
    "wof:name":"Mrs S J Colbert",
    "wof:placetype":"venue"
},
  "geometry": {"coordinates":[-0.32714,50.88063],"type":"Point"}
}