{
  "type": "Feature",
  "properties": {
    "addr:full":"2nd Floor 2 Dale Rd Matlock Derbyshire DE4 3LT",
    "addr:housenumber":"2nd floor 2",
    "addr:postcode":"de4 3lt",
    "addr:street":"Dale Rd",
    "iso:country":"GB",
    "sg:address":"2nd Floor 2 Dale Rd",
    "sg:city":"Matlock",
    "sg:classifiers":[
        {
            "category":"Government",
            "subcategory":"Office",
            "type":"Public Place"
        }
    ],
    "sg:phone":"+44 1629 56563",
    "sg:postcode":"DE4 3LT",
    "sg:province":"Derbyshire",
    "sg:tags":[
        "education",
        "agency",
        "authority"
    ],
    "wof:name":"Christians Involved In Derbyshire Schools",
    "wof:placetype":"venue"
},
  "geometry": {"coordinates":[-1.556684,53.137585],"type":"Point"}
}