{
  "type": "Feature",
  "properties": {
    "iso:country":"GB",
    "sg:address":"Pound Lane",
    "sg:city":"Norwich",
    "sg:classifiers":[
        {
            "category":"Community Center",
            "type":"Public Place"
        }
    ],
    "sg:phone":"+44 1603 701680",
    "sg:postcode":"NR7 0UW",
    "sg:province":"Norfolk",
    "sg:tags":[
        "recreation",
        "leisure",
        "centre"
    ],
    "wof:name":"Thorpe St Andrew Parish Council",
    "wof:placetype":"venue"
},
  "geometry": {"coordinates":[1.3590370417,52.6340637207],"type":"Point"}
}