{
  "type": "Feature",
  "properties": {
    "addr:full":"Meadowview Park, St Osyth Road, Little Clacton Clacton-on-sea Essex CO16 9NT",
    "addr:postcode":"co16 9nt",
    "addr:street":"St Osyth Road",
    "iso:country":"GB",
    "sg:address":"Meadowview Park, St Osyth Road, Little Clacton",
    "sg:city":"Clacton-on-sea",
    "sg:classifiers":[
        {
            "category":"Manufacturing",
            "subcategory":"Buildings",
            "type":"Manufacturing & Wholesale Goods"
        }
    ],
    "sg:phone":"+44 1255 861859",
    "sg:postcode":"CO16 9NT",
    "sg:province":"Essex",
    "sg:tags":[
        "mobile",
        "home"
    ],
    "wof:name":"Wickland (Holdings) Ltd.",
    "wof:placetype":"venue"
},
  "geometry": {"coordinates":[1.1418700218,51.827331543],"type":"Point"}
}