{
  "type": "Feature",
  "properties": {
    "addr:full":"Worsley Road, Worsley Manchester Greater Manchester M28 2WQ",
    "addr:postcode":"m28 2wq",
    "addr:street":"Worsley Road",
    "iso:country":"GB",
    "sg:address":"Worsley Road, Worsley",
    "sg:city":"Manchester",
    "sg:classifiers":[
        {
            "category":"Education",
            "subcategory":"School",
            "type":"Public Place"
        }
    ],
    "sg:phone":"+44 161 794 1463",
    "sg:postcode":"M28 2WQ",
    "sg:province":"Greater Manchester",
    "sg:tags":[
        "independent",
        "preparatory"
    ],
    "wof:name":"Bridgewater School",
    "wof:placetype":"venue"
},
  "geometry": {"coordinates":[-2.364454031,53.504234314],"type":"Point"}
}