{
  "type": "Feature",
  "properties": {
    "addr:full":"9 Ffrydan Road Bala Gwynedd LL23 7RU",
    "addr:housenumber":"9",
    "addr:postcode":"ll23 7ru",
    "addr:street":"Ffrydan Road",
    "iso:country":"GB",
    "sg:address":"9 Ffrydan Road",
    "sg:city":"Bala",
    "sg:classifiers":[
        {
            "category":"Retail",
            "subcategory":"Veterinary Services",
            "type":"Services"
        }
    ],
    "sg:phone":"+44 1678 521466",
    "sg:postcode":"LL23 7RU",
    "sg:province":"Gwynedd",
    "sg:tags":[
        "surgeon"
    ],
    "wof:name":"Wern Tegid Surgery",
    "wof:placetype":"venue"
},
  "geometry": {"coordinates":[-3.603459,52.916168],"type":"Point"}
}