{
  "type": "Feature",
  "properties": {
    "addr:full":"16 Steel Close Honiton Devon EX14 1UY",
    "addr:housenumber":"16",
    "addr:postcode":"ex14 1uy",
    "addr:street":"Steel Close",
    "iso:country":"GB",
    "sg:address":"16 Steel Close",
    "sg:city":"Honiton",
    "sg:classifiers":[
        {
            "category":"Building & Trades",
            "subcategory":"Construction",
            "type":"Services"
        }
    ],
    "sg:phone":"+44 1404 41967",
    "sg:postcode":"EX14 1UY",
    "sg:province":"Devon",
    "sg:tags":[
        "joinery",
        "joiner",
        "carpenter",
        "carpentry"
    ],
    "wof:name":"D Lane",
    "wof:placetype":"venue"
},
  "geometry": {"coordinates":[-3.1802148819,50.8011856079],"type":"Point"}
}