{
  "type": "Feature",
  "properties": {
    "addr:full":"Greenways, Middletown Welshpool Shropshire SY21 8DF",
    "addr:postcode":"sy21 8df",
    "addr:street":"Greenways",
    "iso:country":"GB",
    "sg:address":"Greenways, Middletown",
    "sg:city":"Welshpool",
    "sg:classifiers":[
        {
            "category":"Shopping",
            "subcategory":"Computers & Home Electronics",
            "type":"Retail Goods"
        }
    ],
    "sg:phone":"+44 1938 570337",
    "sg:postcode":"SY21 8DF",
    "sg:province":"Shropshire",
    "wof:name":"Creative Music Systems",
    "wof:placetype":"venue"
},
  "geometry": {"coordinates":[-3.031929,52.706459],"type":"Point"}
}