{
  "type": "Feature",
  "properties": {
    "iso:country":"GB",
    "sg:address":"Unit 4a Victoria Business Park",
    "sg:city":"St Austell",
    "sg:classifiers":[
        {
            "category":"Wholesale",
            "subcategory":"Sporting Goods",
            "type":"Manufacturing & Wholesale Goods"
        }
    ],
    "sg:phone":"+44 1726 891118",
    "sg:postcode":"PL26 8LX",
    "sg:province":"Cornwall",
    "sg:tags":[
        "mnfr",
        "sport",
        "equipment"
    ],
    "wof:name":"Highflyers The Kite Site Ltd",
    "wof:placetype":"venue"
},
  "geometry": {"coordinates":[-4.83029,50.419979],"type":"Point"}
}