{
  "type": "Feature",
  "properties": {
    "iso:country":"GB",
    "sg:address":"7 All Hallows Road, Bispham",
    "sg:city":"Blackpool",
    "sg:classifiers":[
        {
            "category":"Education",
            "subcategory":"College",
            "type":"Public Place"
        }
    ],
    "sg:phone":"+44 1253 353701",
    "sg:postcode":"FY2 0AS",
    "sg:province":"Lancashire",
    "sg:tags":[
        "school"
    ],
    "wof:name":"Bispham Clothing Co",
    "wof:placetype":"venue"
},
  "geometry": {"coordinates":[-3.039063,53.852947],"type":"Point"}
}