{
  "type": "Feature",
  "properties": {
    "addr:full":"10 Broadmeadow La Walsall Staffordshire WS6 6EJ",
    "addr:housenumber":"10",
    "addr:postcode":"ws6 6ej",
    "addr:street":"Broadmeadow La",
    "iso:country":"GB",
    "sg:address":"10 Broadmeadow La",
    "sg:city":"Walsall",
    "sg:classifiers":[
        {
            "category":"Building & Trades",
            "subcategory":"Construction",
            "type":"Services"
        }
    ],
    "sg:phone":"+44 1922 412070",
    "sg:postcode":"WS6 6EJ",
    "sg:province":"Staffordshire",
    "sg:tags":[
        "builder"
    ],
    "wof:name":"Albany Property Services",
    "wof:placetype":"venue"
},
  "geometry": {"coordinates":[-2.0116701126,52.6609191895],"type":"Point"}
}