{
  "type": "Feature",
  "properties": {
    "addr:full":"South Gro, Highgate Highgate Greater London N6 6LB",
    "addr:postcode":"n6 6lb",
    "addr:street":"South Gro Highgate Highgate",
    "iso:country":"GB",
    "sg:address":"South Gro, Highgate",
    "sg:city":"Highgate",
    "sg:classifiers":[
        {
            "category":"Place Of Worship",
            "type":"Public Place"
        }
    ],
    "sg:phone":"+44 20 8340 7279",
    "sg:postcode":"N6 6LB",
    "sg:province":"Greater London",
    "wof:name":"St Michael C Of E Church",
    "wof:placetype":"venue"
},
  "geometry": {"coordinates":[-0.149844,51.571449],"type":"Point"}
}