{
  "type": "Feature",
  "properties": {
    "addr:full":"Old Buildings, Sandleford Farm Newbury Berkshire RG20 9BB",
    "addr:housenumber":"newbury",
    "addr:postcode":"rg20 9bb",
    "addr:street":"Old;Sandleford;Berkshire",
    "iso:country":"GB",
    "sg:address":"Old Buildings, Sandleford Farm",
    "sg:city":"Newbury",
    "sg:classifiers":[
        {
            "category":"Professional",
            "subcategory":"Engineering",
            "type":"Services"
        }
    ],
    "sg:phone":"+44 1635 37936",
    "sg:postcode":"RG20 9BB",
    "sg:province":"Berkshire",
    "wof:name":"Alder Engineering",
    "wof:placetype":"venue"
},
  "geometry": {"coordinates":[-1.31851,51.37841],"type":"Point"}
}