{
  "type": "Feature",
  "properties": {
    "iso:country":"GB",
    "sg:address":"62-70 Tettenhall Rd",
    "sg:city":"Wolverhampton",
    "sg:classifiers":[
        {
            "category":"Farming",
            "subcategory":"Nursery",
            "type":"Manufacturing & Wholesale Goods"
        }
    ],
    "sg:phone":"+44 1902 424355",
    "sg:postcode":"WV1 4TZ",
    "sg:province":"West Midlands",
    "sg:tags":[
        "creche"
    ],
    "wof:name":"Childcare Enterprise Ltd",
    "wof:placetype":"venue"
},
  "geometry": {"coordinates":[-2.141145,52.586143],"type":"Point"}
}