{
  "type": "Feature",
  "properties": {
    "addr:full":"8 Polwarth Crescent Edinburgh City of Edinburgh EH11 1HW",
    "addr:housenumber":"8",
    "addr:postcode":"eh11 1hw",
    "addr:street":"Polwarth Crescent",
    "iso:country":"GB",
    "sg:address":"8 Polwarth Crescent",
    "sg:city":"Edinburgh",
    "sg:classifiers":[
        {
            "category":"Food & Beverages",
            "subcategory":"Supermarket",
            "type":"Retail Goods"
        }
    ],
    "sg:postcode":"EH11 1HW",
    "sg:province":"City of Edinburgh",
    "wof:name":"Polwarth Superstore",
    "wof:placetype":"venue"
},
  "geometry": {"coordinates":[-3.216667,55.937763],"type":"Point"}
}