{
  "type": "Feature",
  "properties": {
    "iso:country":"GB",
    "sg:address":"Bristol Road South, Northfield",
    "sg:city":"Birmingham",
    "sg:classifiers":[
        {
            "category":"Professional",
            "subcategory":"Employment Agencies",
            "type":"Services"
        },
        {
            "category":"Education",
            "subcategory":"University",
            "type":"Public Place"
        },
        {
            "category":"Education",
            "subcategory":"School",
            "type":"Public Place"
        }
    ],
    "sg:phone":"+44 121 483 1111",
    "sg:postcode":"B31 2AJ",
    "sg:province":"West Midlands",
    "sg:tags":[
        "career",
        "guidance",
        "college"
    ],
    "wof:name":"Bournville College of Further Education",
    "wof:placetype":"venue"
},
  "geometry": {"coordinates":[-1.983169,52.400993],"type":"Point"}
}