{
  "type": "Feature",
  "properties": {
    "addr:full":"906 New Chester Road Wirral Cheshire CH62 6AU",
    "addr:housenumber":"906",
    "addr:postcode":"ch62 6au",
    "addr:street":"New Chester Road",
    "iso:country":"GB",
    "sg:address":"906 New Chester Road",
    "sg:city":"Wirral",
    "sg:classifiers":[
        {
            "category":"Retail",
            "subcategory":"Veterinary Services",
            "type":"Services"
        }
    ],
    "sg:phone":"+44 151 334 1355",
    "sg:postcode":"CH62 6AU",
    "sg:province":"Cheshire",
    "sg:tags":[
        "surgeon",
        "activity"
    ],
    "wof:name":"Allport Veterinary Surgery",
    "wof:placetype":"venue"
},
  "geometry": {"coordinates":[-2.97159,53.324986],"type":"Point"}
}