{
  "type": "Feature",
  "properties": {
    "addr:full":"232 Eltham High Street, Eltham London Greater London SE9 1BA",
    "addr:housenumber":"232",
    "addr:postcode":"se9 1ba",
    "addr:street":"Eltham High Street",
    "iso:country":"GB",
    "sg:address":"232 Eltham High Street, Eltham",
    "sg:city":"London",
    "sg:classifiers":[
        {
            "category":"Shopping",
            "subcategory":"Gifts & Souvenirs",
            "type":"Retail Goods"
        }
    ],
    "sg:phone":"+44 20 8850 0894",
    "sg:postcode":"SE9 1BA",
    "sg:province":"Greater London",
    "sg:tags":[
        "shop"
    ],
    "wof:name":"Kenny'S Pop In",
    "wof:placetype":"venue"
},
  "geometry": {"coordinates":[0.059652,51.450691],"type":"Point"}
}