{
  "type": "Feature",
  "properties": {
    "addr:full":"58 Broughton La Crewe Cheshire CW2 8JR",
    "addr:housenumber":"58",
    "addr:postcode":"cw2 8jr",
    "addr:street":"Broughton La Crewe",
    "iso:country":"GB",
    "sg:address":"58 Broughton La",
    "sg:city":"Crewe",
    "sg:classifiers":[
        {
            "category":"Professional",
            "subcategory":"Engineering",
            "type":"Services"
        }
    ],
    "sg:postcode":"CW2 8JR",
    "sg:province":"Cheshire",
    "sg:tags":[
        "contractor",
        "electrical",
        "engineer"
    ],
    "wof:name":"John Tuffy",
    "wof:placetype":"venue"
},
  "geometry": {"coordinates":[-2.463311,53.084042],"type":"Point"}
}