{
  "type": "Feature",
  "properties": {
    "iso:country":"GB",
    "sg:address":"63 Fir La",
    "sg:city":"Lowestoft",
    "sg:classifiers":[
        {
            "category":"Professional",
            "type":"Services"
        }
    ],
    "sg:phone":"+44 1502 508724",
    "sg:postcode":"NR32 2RD",
    "sg:province":"Suffolk",
    "sg:tags":[
        "repair",
        "tech",
        "maintenance"
    ],
    "wof:name":"Dolphins Multimedia Systems",
    "wof:placetype":"venue"
},
  "geometry": {"coordinates":[1.732355,52.485657],"type":"Point"}
}