{
  "type": "Feature",
  "properties": {
    "addr:full":"Ty Hen, Rhostrehwfa Llangefni Gwynedd LL77 7YP",
    "addr:postcode":"ll77 7yp",
    "addr:street":"Llangefni",
    "iso:country":"GB",
    "sg:address":"Ty Hen, Rhostrehwfa",
    "sg:city":"Llangefni",
    "sg:classifiers":[
        {
            "category":"Farming",
            "subcategory":"Livestock Farm",
            "type":"Manufacturing & Wholesale Goods"
        }
    ],
    "sg:postcode":"LL77 7YP",
    "sg:province":"Gwynedd",
    "sg:tags":[
        "others"
    ],
    "wof:name":"Roberts,Owen,",
    "wof:placetype":"venue"
},
  "geometry": {"coordinates":[-4.3084640503,53.2556037903],"type":"Point"}
}