{
  "type": "Feature",
  "properties": {
    "addr:full":"4 Doxford Drive, South West Industrial Estate Peterlee Durham SR8 2RL",
    "addr:housenumber":"4",
    "addr:postcode":"sr8 2rl",
    "addr:street":"Doxford Drive South;Industrial Estate",
    "iso:country":"GB",
    "sg:address":"4 Doxford Drive, South West Industrial Estate",
    "sg:city":"Peterlee",
    "sg:classifiers":[
        {
            "category":"Home & Garden",
            "subcategory":"Hardware",
            "type":"Retail Goods"
        }
    ],
    "sg:phone":"+44 191 587 2787",
    "sg:postcode":"SR8 2RL",
    "sg:province":"Durham",
    "sg:tags":[
        "battery"
    ],
    "wof:name":"Alexander Technologies Europe Ltd.",
    "wof:placetype":"venue"
},
  "geometry": {"coordinates":[-1.36490798,54.7611122131],"type":"Point"}
}