{
  "type": "Feature",
  "properties": {
    "iso:country":"GB",
    "sg:address":"107 Brierley Rd, Grimethorpe",
    "sg:city":"Barnsley",
    "sg:classifiers":[
        {
            "category":"Government",
            "subcategory":"Post Office",
            "type":"Public Place"
        }
    ],
    "sg:phone":"+44 1226 711262",
    "sg:postcode":"S72 7AD",
    "sg:province":"South Yorkshire",
    "wof:name":"C.W.S Jenner",
    "wof:placetype":"venue"
},
  "geometry": {"coordinates":[-1.38105,53.58186],"type":"Point"}
}