{
  "type": "Feature",
  "properties": {
    "addr:full":"28-30 South Street Worthing West Sussex BN11 3AA",
    "addr:housenumber":"28-30",
    "addr:postcode":"bn11 3aa",
    "addr:street":"South Street",
    "iso:country":"GB",
    "sg:address":"28-30 South Street",
    "sg:city":"Worthing",
    "sg:classifiers":[
        {
            "category":"Home & Garden",
            "subcategory":"Hardware",
            "type":"Retail Goods"
        }
    ],
    "sg:phone":"+44 1903 200282",
    "sg:postcode":"BN11 3AA",
    "sg:province":"West Sussex",
    "wof:name":"Robert Dyas Holdings Ltd.",
    "wof:placetype":"venue"
},
  "geometry": {"coordinates":[-0.3697830141,50.8108406067],"type":"Point"}
}