{
  "type": "Feature",
  "properties": {
    "addr:full":"82 Main Street Callander Stirling FK17 8BD",
    "addr:housenumber":"82",
    "addr:postcode":"fk17 8bd",
    "addr:street":"Main Street",
    "iso:country":"GB",
    "sg:address":"82 Main Street",
    "sg:city":"Callander",
    "sg:classifiers":[
        {
            "category":"Real Estate",
            "subcategory":"Architect",
            "type":"Services"
        }
    ],
    "sg:phone":"+44 1877 331477",
    "sg:postcode":"FK17 8BD",
    "sg:province":"Stirling",
    "sg:tags":[
        "kilt",
        "accessory"
    ],
    "wof:name":"Russell Hector",
    "wof:placetype":"venue"
},
  "geometry": {"coordinates":[-4.21392,56.24337],"type":"Point"}
}