{
  "type": "Feature",
  "properties": {
    "addr:full":"1b Grace Reynolds Walk, Main Square Camberley Berkshire GU15 3SN",
    "addr:housenumber":"1b",
    "addr:postcode":"gu15 3sn",
    "addr:street":"Grace Reynolds Walk",
    "iso:country":"GB",
    "sg:address":"1b Grace Reynolds Walk, Main Square",
    "sg:city":"Camberley",
    "sg:classifiers":[
        {
            "category":"Shopping",
            "subcategory":"Optician",
            "type":"Retail Goods"
        }
    ],
    "sg:phone":"+44 1276 25880",
    "sg:postcode":"GU15 3SN",
    "sg:province":"Berkshire",
    "sg:tags":[
        "opthalmic"
    ],
    "sg:website":"http://www.danda.co.uk",
    "wof:name":"Dollond & Aitchison",
    "wof:placetype":"venue"
},
  "geometry": {"coordinates":[-0.7342299819,51.3362159729],"type":"Point"}
}