{
  "type": "Feature",
  "properties": {
    "addr:full":"14 Betts Avenue, Martlesham Heath Ipswich Suffolk IP5 3RH",
    "addr:housenumber":"14",
    "addr:postcode":"ip5 3rh",
    "addr:street":"Betts Avenue",
    "iso:country":"GB",
    "sg:address":"14 Betts Avenue, Martlesham Heath",
    "sg:city":"Ipswich",
    "sg:classifiers":[
        {
            "category":"Communications",
            "subcategory":"Newspaper",
            "type":"Services"
        }
    ],
    "sg:phone":"+44 1473 611363",
    "sg:postcode":"IP5 3RH",
    "sg:province":"Suffolk",
    "sg:tags":[
        "magazine"
    ],
    "wof:name":"The Ipswich Advertiser",
    "wof:placetype":"venue"
},
  "geometry": {"coordinates":[1.281082,52.061451],"type":"Point"}
}