{
  "type": "Feature",
  "properties": {
    "addr:full":"3 Woodland Parade Hove East Sussex BN3 6DR",
    "addr:housenumber":"3",
    "addr:postcode":"bn3 6dr",
    "addr:street":"Woodland Parade Hove",
    "iso:country":"GB",
    "sg:address":"3 Woodland Parade",
    "sg:city":"Hove",
    "sg:classifiers":[
        {
            "category":"Home & Garden",
            "subcategory":"Hardware",
            "type":"Retail Goods"
        }
    ],
    "sg:phone":"+44 1273 882787",
    "sg:postcode":"BN3 6DR",
    "sg:province":"East Sussex",
    "wof:name":"Benhams Hardware",
    "wof:placetype":"venue"
},
  "geometry": {"coordinates":[-0.1742220074,50.8466567993],"type":"Point"}
}