{
  "type": "Feature",
  "properties": {
    "addr:full":"1901 Maryhill Road Glasgow Glasgow City G20 0BY",
    "addr:housenumber":"1901",
    "addr:postcode":"g20 0by",
    "addr:street":"Maryhill Road",
    "iso:country":"GB",
    "sg:address":"1901 Maryhill Road",
    "sg:city":"Glasgow",
    "sg:classifiers":[
        {
            "category":"Food & Beverages",
            "subcategory":"Meat & Fish",
            "type":"Retail Goods"
        }
    ],
    "sg:phone":"+44 141 946 2077",
    "sg:postcode":"G20 0BY",
    "sg:province":"Glasgow City",
    "sg:tags":[
        "butcher"
    ],
    "wof:name":"G C Blackadder & Son",
    "wof:placetype":"venue"
},
  "geometry": {"coordinates":[-4.2989649773,55.8960647583],"type":"Point"}
}