{
  "type": "Feature",
  "properties": {
    "iso:country":"GB",
    "sg:address":"148 Chatham Street",
    "sg:city":"Reading",
    "sg:classifiers":[
        {
            "category":"Bars & Pubs",
            "type":"Food & Drink"
        }
    ],
    "sg:postcode":"RG1 7HT",
    "sg:province":"Berkshire",
    "sg:tags":[
        "pubs",
        "inn"
    ],
    "wof:name":"The Alfreds Head",
    "wof:placetype":"venue"
},
  "geometry": {"coordinates":[-0.98338902,51.4559783936],"type":"Point"}
}