{
  "type": "Feature",
  "properties": {
    "addr:full":"Outerthwaite Farm, Allithwaite Road, Flookburgh Grange-over-sands Cumbria LA11 7JP",
    "addr:postcode":"la11 7jp",
    "addr:street":"Allithwaite Road",
    "iso:country":"GB",
    "sg:address":"Outerthwaite Farm, Allithwaite Road, Flookburgh",
    "sg:city":"Grange-over-sands",
    "sg:classifiers":[
        {
            "category":"Farming",
            "subcategory":"Farm",
            "type":"Manufacturing & Wholesale Goods"
        }
    ],
    "sg:postcode":"LA11 7JP",
    "sg:province":"Cumbria",
    "sg:tags":[
        "mixed",
        "crop"
    ],
    "wof:name":"J B Moore",
    "wof:placetype":"venue"
},
  "geometry": {"coordinates":[-2.92164,54.184158],"type":"Point"}
}