{
  "type": "Feature",
  "properties": {
    "addr:full":"Unit 22a Deeside Industrial Estate, Marsh Lane Deeside Flintshire CH5 2AR",
    "addr:housenumber":"unit 22a",
    "addr:postcode":"ch5 2ar",
    "addr:street":"Industrial Estate Marsh Lane",
    "iso:country":"GB",
    "sg:address":"Unit 22a Deeside Industrial Estate, Marsh Lane",
    "sg:city":"Deeside",
    "sg:classifiers":[
        {
            "category":"Autos & Motor Vehicles",
            "subcategory":"Auto Supplies",
            "type":"Retail Goods"
        }
    ],
    "sg:phone":"+44 1244 288596",
    "sg:postcode":"CH5 2AR",
    "sg:province":"Flintshire",
    "sg:tags":[
        "tyre"
    ],
    "wof:name":"Mobile Tyre Services",
    "wof:placetype":"venue"
},
  "geometry": {"coordinates":[-3.00083,53.224918],"type":"Point"}
}