{
  "type": "Feature",
  "properties": {
    "iso:country":"GB",
    "sg:address":"Southbank House, Victoria Rd, Southborough",
    "sg:city":"Tunbridge Wells",
    "sg:classifiers":[
        {
            "category":"Professional",
            "subcategory":"Business Services",
            "type":"Services"
        }
    ],
    "sg:phone":"+44 1892 526584",
    "sg:postcode":"TN4 0LT",
    "sg:province":"Kent",
    "sg:tags":[
        "food",
        "import",
        "export",
        "agent"
    ],
    "wof:name":"Perin's Ltd",
    "wof:placetype":"venue"
},
  "geometry": {"coordinates":[0.2599489987,51.1558914185],"type":"Point"}
}