{
  "type": "Feature",
  "properties": {
    "iso:country":"GB",
    "sg:address":"101-108 Britannia Walk",
    "sg:city":"London",
    "sg:classifiers":[
        {
            "category":"Wholesale",
            "subcategory":"Scrap",
            "type":"Manufacturing & Wholesale Goods"
        }
    ],
    "sg:phone":"+44 20 7490 1000",
    "sg:postcode":"N1 7LU",
    "sg:province":"Greater London",
    "sg:tags":[
        "salvage"
    ],
    "wof:name":"Lassco Trade Warehouse",
    "wof:placetype":"venue"
},
  "geometry": {"coordinates":[-0.0898,51.528927],"type":"Point"}
}