{
  "type": "Feature",
  "properties": {
    "addr:full":"Warehouse, Ainsworth Ho, Bury Rd Rossendale Lancashire BB4 5PG",
    "addr:postcode":"bb4 5pg",
    "addr:street":"Bury Rd",
    "iso:country":"GB",
    "sg:address":"Warehouse, Ainsworth Ho, Bury Rd",
    "sg:city":"Rossendale",
    "sg:classifiers":[
        {
            "category":"Shopping",
            "subcategory":"Crafts & Fabrics",
            "type":"Retail Goods"
        }
    ],
    "sg:phone":"+44 1706 221278",
    "sg:postcode":"BB4 5PG",
    "sg:province":"Lancashire",
    "sg:tags":[
        "shop"
    ],
    "wof:name":"Lodge Fabrics",
    "wof:placetype":"venue"
},
  "geometry": {"coordinates":[-2.274824,53.708961],"type":"Point"}
}