{
  "type": "Feature",
  "properties": {
    "addr:full":"34 Beech Rd Reigate Surrey RH2 9ND",
    "addr:housenumber":"34",
    "addr:postcode":"rh2 9nd",
    "addr:street":"Beech Rd",
    "iso:country":"GB",
    "sg:address":"34 Beech Rd",
    "sg:city":"Reigate",
    "sg:classifiers":[
        {
            "category":"Education",
            "subcategory":"Dance Studio",
            "type":"Public Place"
        }
    ],
    "sg:phone":"+44 1737 246404",
    "sg:postcode":"RH2 9ND",
    "sg:province":"Surrey",
    "sg:tags":[
        "ballet",
        "school"
    ],
    "wof:name":"Valentine Walker School Of Dance",
    "wof:placetype":"venue"
},
  "geometry": {"coordinates":[-0.203851,51.250504],"type":"Point"}
}