{
  "type": "Feature",
  "properties": {
    "addr:full":"4-5 South Parade Pier Southsea Hampshire PO4 0SW",
    "addr:housenumber":"4-5",
    "addr:postcode":"po4 0sw",
    "addr:street":"South Parade Pier Southsea",
    "iso:country":"GB",
    "sg:address":"4-5 South Parade Pier",
    "sg:city":"Southsea",
    "sg:classifiers":[
        {
            "category":"Shopping",
            "subcategory":"News",
            "type":"Retail Goods"
        }
    ],
    "sg:postcode":"PO4 0SW",
    "sg:province":"Hampshire",
    "sg:tags":[
        "newsagent"
    ],
    "wof:name":"Keene,George,",
    "wof:placetype":"venue"
},
  "geometry": {"coordinates":[-1.078589,50.77906],"type":"Point"}
}