{
  "type": "Feature",
  "properties": {
    "addr:full":"23 Hilary Close, Crow Wood Widnes Cheshire WA8 3HT",
    "addr:housenumber":"23",
    "addr:postcode":"wa8 3ht",
    "addr:street":"Hilary Close Crow Wood",
    "iso:country":"GB",
    "sg:address":"23 Hilary Close, Crow Wood",
    "sg:city":"Widnes",
    "sg:classifiers":[
        {
            "category":"Utilities",
            "subcategory":"Telephone",
            "type":"Services"
        }
    ],
    "sg:phone":"+44 151 420 2712",
    "sg:postcode":"WA8 3HT",
    "sg:province":"Cheshire",
    "sg:tags":[
        "telecommunication"
    ],
    "wof:name":"Hermes Telecom",
    "wof:placetype":"venue"
},
  "geometry": {"coordinates":[-2.707124,53.379463],"type":"Point"}
}