{
  "type": "Feature",
  "properties": {
    "addr:full":"396 Lea Bridge Road London Greater London E10 7DY",
    "addr:housenumber":"396",
    "addr:postcode":"e10 7dy",
    "addr:street":"Lea Bridge Road",
    "iso:country":"GB",
    "sg:address":"396 Lea Bridge Road",
    "sg:city":"London",
    "sg:classifiers":[
        {
            "category":"Professional",
            "subcategory":"Art Services",
            "type":"Services"
        }
    ],
    "sg:phone":"+44 20 8539 9266",
    "sg:postcode":"E10 7DY",
    "sg:province":"Greater London",
    "sg:tags":[
        "framing"
    ],
    "wof:name":"Forest Frames",
    "wof:placetype":"venue"
},
  "geometry": {"coordinates":[-0.0228359997,51.5710334778],"type":"Point"}
}