{
  "type": "Feature",
  "properties": {
    "iso:country":"GB",
    "sg:address":"6 Willesden Lane",
    "sg:city":"London",
    "sg:classifiers":[
        {
            "category":"Retail",
            "subcategory":"Laundry & Dry Cleaning",
            "type":"Services"
        }
    ],
    "sg:phone":"+44 20 7328 5630",
    "sg:postcode":"NW6 7SR",
    "sg:province":"Greater London",
    "sg:tags":[
        "alteration"
    ],
    "wof:name":"P M Dry Cleaners",
    "wof:placetype":"venue"
},
  "geometry": {"coordinates":[-0.198909,51.541611],"type":"Point"}
}