{
  "type": "Feature",
  "properties": {
    "iso:country":"GB",
    "sg:address":"Parc Y Prysau, Brynford",
    "sg:city":"Holywell",
    "sg:classifiers":[
        {
            "category":"Building & Trades",
            "subcategory":"Construction",
            "type":"Services"
        }
    ],
    "sg:postcode":"CH8 8LS",
    "sg:province":"Denbighshire",
    "sg:tags":[
        "platform",
        "work",
        "scaffolding"
    ],
    "wof:name":"K Birch & Son",
    "wof:placetype":"venue"
},
  "geometry": {"coordinates":[-3.234544,53.25861],"type":"Point"}
}