{
  "type": "Feature",
  "properties": {
    "addr:full":"505 Hawthorne Road Unit 4 Liverpool Merseyside L20 6JJ",
    "addr:housenumber":"505;4",
    "addr:postcode":"l20 6jj",
    "addr:street":"Hawthorne Road Unit",
    "iso:country":"GB",
    "sg:address":"505 Hawthorne Road Unit 4",
    "sg:city":"Liverpool",
    "sg:classifiers":[
        {
            "category":"Freight",
            "type":"Transportation"
        }
    ],
    "sg:postcode":"L20 6JJ",
    "sg:province":"Merseyside",
    "sg:tags":[
        "forwarders"
    ],
    "wof:name":"Awards Shipping Ltd.",
    "wof:placetype":"venue"
},
  "geometry": {"coordinates":[-2.9972560406,53.4696121216],"type":"Point"}
}