{
  "type": "Feature",
  "properties": {
    "iso:country":"GB",
    "sg:address":"26a Lever St",
    "sg:city":"Manchester",
    "sg:classifiers":[
        {
            "category":"Wholesale",
            "subcategory":"Non-durable Goods",
            "type":"Manufacturing & Wholesale Goods"
        }
    ],
    "sg:phone":"+44 161 236 1021",
    "sg:postcode":"M1 1DW",
    "sg:province":"Greater Manchester",
    "sg:tags":[
        "carry",
        "cash"
    ],
    "wof:name":"Hamburgers (G & M) Ltd",
    "wof:placetype":"venue"
},
  "geometry": {"coordinates":[-2.2339100838,53.4823875427],"type":"Point"}
}