{
  "type": "Feature",
  "properties": {
    "iso:country":"GB",
    "sg:address":"7 Hornleigh Gro",
    "sg:city":"Redcar",
    "sg:classifiers":[
        {
            "category":"Education",
            "subcategory":"Music School",
            "type":"Public Place"
        }
    ],
    "sg:postcode":"TS10 1QS",
    "sg:province":"North Yorkshire",
    "sg:tags":[
        "teacher"
    ],
    "wof:name":"Angela Mathieson",
    "wof:placetype":"venue"
},
  "geometry": {"coordinates":[-1.0812840462,54.6158485413],"type":"Point"}
}