{
  "type": "Feature",
  "properties": {
    "addr:full":"5 Chapel Street Peterhead Aberdeenshire AB42 1TH",
    "addr:housenumber":"5",
    "addr:postcode":"ab42 1th",
    "addr:street":"Chapel Street",
    "iso:country":"GB",
    "sg:address":"5 Chapel Street",
    "sg:city":"Peterhead",
    "sg:classifiers":[
        {
            "category":"Shopping",
            "subcategory":"Clothing, Apparel, & Fashions",
            "type":"Retail Goods"
        }
    ],
    "sg:phone":"+44 1779 490200",
    "sg:postcode":"AB42 1TH",
    "sg:province":"Aberdeenshire",
    "sg:tags":[
        "lady",
        "fashionwear",
        "ladieswear"
    ],
    "wof:name":"Dressage",
    "wof:placetype":"venue"
},
  "geometry": {"coordinates":[-1.778732,57.505344],"type":"Point"}
}