{
  "type": "Feature",
  "properties": {
    "addr:full":"Lillisford Farm, Littlehempston Totnes Devon TQ9 6NG",
    "addr:postcode":"tq9 6ng",
    "iso:country":"GB",
    "sg:address":"Lillisford Farm, Littlehempston",
    "sg:city":"Totnes",
    "sg:classifiers":[
        {
            "category":"Farming",
            "subcategory":"Livestock Farm",
            "type":"Manufacturing & Wholesale Goods"
        }
    ],
    "sg:postcode":"TQ9 6NG",
    "sg:province":"Devon",
    "sg:tags":[
        "others"
    ],
    "wof:name":"B T Shilston",
    "wof:placetype":"venue"
},
  "geometry": {"coordinates":[-3.6667239666,50.4508705139],"type":"Point"}
}