{
  "type": "Feature",
  "properties": {
    "iso:country":"GB",
    "sg:address":"8 Station Yard",
    "sg:city":"Abingdon",
    "sg:classifiers":[
        {
            "category":"Shopping",
            "subcategory":"Books",
            "type":"Retail Goods"
        }
    ],
    "sg:phone":"+44 1235 861234",
    "sg:postcode":"OX13 6RX",
    "sg:province":"Oxfordshire",
    "sg:tags":[
        "second-hand"
    ],
    "wof:name":"Professional Book Supplies Ltd.",
    "wof:placetype":"venue"
},
  "geometry": {"coordinates":[-1.3200399876,51.6215934753],"type":"Point"}
}