{
  "type": "Feature",
  "properties": {
    "iso:country":"GB",
    "sg:address":"Bath Road, Padworth",
    "sg:city":"Reading",
    "sg:classifiers":[
        {
            "category":"Travel",
            "subcategory":"Hotels & Motels",
            "type":"Entertainment"
        }
    ],
    "sg:phone":"+44 118 971 3282",
    "sg:postcode":"RG7 5HT",
    "sg:province":"Berkshire",
    "wof:name":"Confort Inn Reading South",
    "wof:placetype":"venue"
},
  "geometry": {"coordinates":[-1.112002,51.419907],"type":"Point"}
}