{
  "type": "Feature",
  "properties": {
    "iso:country":"GB",
    "sg:address":"The Coach House, Victoria Road",
    "sg:city":"Lydney",
    "sg:classifiers":[
        {
            "category":"Health Services",
            "subcategory":"Dentist",
            "type":"Services"
        }
    ],
    "sg:phone":"+44 1594 842715",
    "sg:postcode":"GL15 5DG",
    "sg:province":"Gloucestershire",
    "wof:name":"IAN D STORRAR",
    "wof:placetype":"venue"
},
  "geometry": {"coordinates":[-2.533547,51.724701],"type":"Point"}
}