{
  "type": "Feature",
  "properties": {
    "addr:full":"High Catton, Stamford Bridge York East Riding of Yorkshire YO41 1HY",
    "addr:postcode":"yo41 1hy",
    "addr:street":"Stamford",
    "iso:country":"GB",
    "sg:address":"High Catton, Stamford Bridge",
    "sg:city":"York",
    "sg:classifiers":[
        {
            "category":"Farming",
            "subcategory":"Farm",
            "type":"Manufacturing & Wholesale Goods"
        }
    ],
    "sg:postcode":"YO41 1HY",
    "sg:province":"East Riding of Yorkshire",
    "sg:tags":[
        "mixed",
        "crop"
    ],
    "wof:name":"P W Triffitt",
    "wof:placetype":"venue"
},
  "geometry": {"coordinates":[-0.90798,53.975327],"type":"Point"}
}