{
  "type": "Feature",
  "properties": {
    "addr:full":"24 The Oval Oxford Oxfordshire OX4 4SE",
    "addr:housenumber":"24",
    "addr:postcode":"ox4 4se",
    "addr:street":"The Oval",
    "iso:country":"GB",
    "sg:address":"24 The Oval",
    "sg:city":"Oxford",
    "sg:classifiers":[
        {
            "category":"Food & Beverages",
            "subcategory":"Supermarket",
            "type":"Retail Goods"
        }
    ],
    "sg:phone":"+44 1865 778135",
    "sg:postcode":"OX4 4SE",
    "sg:province":"Oxfordshire",
    "wof:name":"Oxford Swindon & Gloucester Co-Operative",
    "wof:placetype":"venue"
},
  "geometry": {"coordinates":[-1.232102,51.725052],"type":"Point"}
}