{
  "type": "Feature",
  "properties": {
    "addr:full":"Montan House, 36 Calthorpe Road Birmingham West Midlands B15 1TS",
    "addr:housenumber":"36",
    "addr:postcode":"b15 1ts",
    "addr:street":"Calthorpe Road",
    "iso:country":"GB",
    "sg:address":"Montan House, 36 Calthorpe Road",
    "sg:city":"Birmingham",
    "sg:classifiers":[
        {
            "category":"Banks & Credit Unions",
            "subcategory":"Financial Services",
            "type":"Services"
        }
    ],
    "sg:postcode":"B15 1TS",
    "sg:province":"West Midlands",
    "sg:tags":[
        "consultant"
    ],
    "wof:name":"Saga Management & Investment Limited",
    "wof:placetype":"venue"
},
  "geometry": {"coordinates":[-1.921579957,52.4681739807],"type":"Point"}
}