{
  "type": "Feature",
  "properties": {
    "addr:full":"Gloucester Rd Bristol City of Bristol BS7 8NY",
    "addr:postcode":"bs7 8ny",
    "addr:street":"Gloucester Rd",
    "iso:country":"GB",
    "sg:address":"Gloucester Rd",
    "sg:city":"Bristol",
    "sg:classifiers":[
        {
            "category":"Professional",
            "subcategory":"Business Services",
            "type":"Services"
        }
    ],
    "sg:phone":"+44 117 924 0294",
    "sg:postcode":"BS7 8NY",
    "sg:province":"City of Bristol",
    "sg:tags":[
        "distribution"
    ],
    "wof:name":"Cotswold Country Foods",
    "wof:placetype":"venue"
},
  "geometry": {"coordinates":[-2.587938,51.481564],"type":"Point"}
}