{
  "type": "Feature",
  "properties": {
    "addr:full":"Lodge Lane Cannock Staffordshire WS11 3LT",
    "addr:postcode":"ws11 3lt",
    "addr:street":"Lodge Lane",
    "iso:country":"GB",
    "sg:address":"Lodge Lane",
    "sg:city":"Cannock",
    "sg:classifiers":[
        {
            "category":"Home & Garden",
            "subcategory":"Building Materials",
            "type":"Retail Goods"
        }
    ],
    "sg:phone":"+44 1922 708000",
    "sg:postcode":"WS11 3LT",
    "sg:province":"Staffordshire",
    "sg:tags":[
        "brick"
    ],
    "wof:name":"Ibstock Brick",
    "wof:placetype":"venue"
},
  "geometry": {"coordinates":[-2.0331449509,52.690952301],"type":"Point"}
}