{
  "type": "Feature",
  "properties": {
    "iso:country":"GB",
    "sg:address":"6 Broadmead Green, Thorpe End",
    "sg:city":"Norwich",
    "sg:classifiers":[
        {
            "category":"Professional",
            "subcategory":"Management & Consulting",
            "type":"Services"
        },
        {
            "category":"Professional",
            "subcategory":"Computer Services",
            "type":"Services"
        }
    ],
    "sg:phone":"+44 1603 735660",
    "sg:postcode":"NR13 5DE",
    "sg:province":"Norfolk",
    "sg:tags":[
        "consultant",
        "business",
        "information"
    ],
    "wof:name":"Sealines Logic Ltd",
    "wof:placetype":"venue"
},
  "geometry": {"coordinates":[1.2949,52.622494],"type":"Point"}
}