{
  "type": "Feature",
  "properties": {
    "addr:full":"512a Normanby Road Middlesbrough North Yorkshire TS6 9BZ",
    "addr:housenumber":"512a",
    "addr:postcode":"ts6 9bz",
    "addr:street":"Normanby Road",
    "iso:country":"GB",
    "sg:address":"512a Normanby Road",
    "sg:city":"Middlesbrough",
    "sg:classifiers":[
        {
            "category":"Food & Beverages",
            "subcategory":"Meat & Fish",
            "type":"Retail Goods"
        }
    ],
    "sg:phone":"+44 1642 452452",
    "sg:postcode":"TS6 9BZ",
    "sg:province":"North Yorkshire",
    "sg:tags":[
        "butcher"
    ],
    "wof:name":"Normanby Butchers",
    "wof:placetype":"venue"
},
  "geometry": {"coordinates":[-1.159299016,54.5623588562],"type":"Point"}
}