{
  "type": "Feature",
  "properties": {
    "addr:full":"Hardwick Rd Stockton On Tees Durham TS19 8PE",
    "addr:postcode":"ts19 8pe",
    "addr:street":"Hardwick Rd",
    "iso:country":"GB",
    "sg:address":"Hardwick Rd",
    "sg:city":"Stockton On Tees",
    "sg:classifiers":[
        {
            "category":"Professional",
            "subcategory":"Computer Services",
            "type":"Services"
        }
    ],
    "sg:phone":"+44 1642 624655",
    "sg:postcode":"TS19 8PE",
    "sg:province":"Durham",
    "sg:tags":[
        "information"
    ],
    "wof:name":"Stroke Association The",
    "wof:placetype":"venue"
},
  "geometry": {"coordinates":[-1.344819,54.586151],"type":"Point"}
}