{
  "type": "Feature",
  "properties": {
    "addr:full":"24 The Pavement London Greater London SW4 0JA",
    "addr:housenumber":"24",
    "addr:postcode":"sw4 0ja",
    "addr:street":"The Pavement",
    "iso:country":"GB",
    "sg:address":"24 The Pavement",
    "sg:city":"London",
    "sg:classifiers":[
        {
            "category":"Food & Beverages",
            "subcategory":"Meat & Fish",
            "type":"Retail Goods"
        }
    ],
    "sg:phone":"+44 20 7622 1624",
    "sg:postcode":"SW4 0JA",
    "sg:province":"Greater London",
    "sg:tags":[
        "butcher"
    ],
    "wof:name":"M Moen & Son",
    "wof:placetype":"venue"
},
  "geometry": {"coordinates":[-0.1401579976,51.4623985291],"type":"Point"}
}