{
  "type": "Feature",
  "properties": {
    "addr:full":"243 Clepington Road Dundee Dundee City DD3 7UE",
    "addr:housenumber":"243",
    "addr:postcode":"dd3 7ue",
    "addr:street":"Clepington Road",
    "iso:country":"GB",
    "sg:address":"243 Clepington Road",
    "sg:city":"Dundee",
    "sg:classifiers":[
        {
            "category":"Fast Food",
            "type":"Food & Drink"
        }
    ],
    "sg:phone":"+44 1382 819400",
    "sg:postcode":"DD3 7UE",
    "sg:province":"Dundee City",
    "sg:tags":[
        "away",
        "take"
    ],
    "wof:name":"Tak Awa",
    "wof:placetype":"venue"
},
  "geometry": {"coordinates":[-2.973726,56.477871],"type":"Point"}
}