{
  "type": "Feature",
  "properties": {
    "addr:full":"24 White Oak Dr Beckenham Kent BR3 6QE",
    "addr:housenumber":"24",
    "addr:postcode":"br3 6qe",
    "addr:street":"White Oak Dr",
    "iso:country":"GB",
    "sg:address":"24 White Oak Dr",
    "sg:city":"Beckenham",
    "sg:classifiers":[
        {
            "category":"Professional",
            "subcategory":"Engineering",
            "type":"Services"
        }
    ],
    "sg:postcode":"BR3 6QE",
    "sg:province":"Kent",
    "sg:tags":[
        "engineer",
        "structural"
    ],
    "wof:name":"Steele,Peter,",
    "wof:placetype":"venue"
},
  "geometry": {"coordinates":[-0.0098999999,51.4058303833],"type":"Point"}
}