{
  "type": "Feature",
  "properties": {
    "addr:full":"Normanston Drive Lowestoft Suffolk NR32 2PY",
    "addr:postcode":"nr32 2py",
    "addr:street":"Normanston Drive",
    "iso:country":"GB",
    "sg:address":"Normanston Drive",
    "sg:city":"Lowestoft",
    "sg:classifiers":[
        {
            "category":"Autos & Motor Vehicles",
            "subcategory":"Fuel & Gas Station",
            "type":"Retail Goods"
        }
    ],
    "sg:phone":"+44 1502 509000",
    "sg:postcode":"NR32 2PY",
    "sg:province":"Suffolk",
    "sg:tags":[
        "hr",
        "petrol"
    ],
    "wof:name":"Shell Oulton Broad",
    "wof:placetype":"venue"
},
  "geometry": {"coordinates":[1.7346,52.483135],"type":"Point"}
}