{
  "type": "Feature",
  "properties": {
    "addr:full":"12 Mill Lane, Ackworth Pontefract West Yorkshire WF7 7NE",
    "addr:housenumber":"12",
    "addr:postcode":"wf7 7ne",
    "addr:street":"Mill Lane;Pontefract West",
    "iso:country":"GB",
    "sg:address":"12 Mill Lane, Ackworth",
    "sg:city":"Pontefract",
    "sg:classifiers":[
        {
            "category":"Professional",
            "subcategory":"Engineering",
            "type":"Services"
        }
    ],
    "sg:phone":"+44 1977 610110",
    "sg:postcode":"WF7 7NE",
    "sg:province":"West Yorkshire",
    "sg:tags":[
        "contractor",
        "electrical",
        "engineer"
    ],
    "wof:name":"Anchor Alarm & Electrical Contractors",
    "wof:placetype":"venue"
},
  "geometry": {"coordinates":[-1.331916,53.645985],"type":"Point"}
}