{
  "type": "Feature",
  "properties": {
    "addr:full":"2 Monkton Street Ryde Isle of Wight PO33 1JN",
    "addr:housenumber":"2",
    "addr:postcode":"po33 1jn",
    "addr:street":"Monkton Street",
    "iso:country":"GB",
    "sg:address":"2 Monkton Street",
    "sg:city":"Ryde",
    "sg:classifiers":[
        {
            "category":"Fast Food",
            "type":"Food & Drink"
        },
        {
            "category":"Food & Beverages",
            "subcategory":"Meat & Fish",
            "type":"Retail Goods"
        }
    ],
    "sg:phone":"+44 1983 562679",
    "sg:postcode":"PO33 1JN",
    "sg:province":"Isle of Wight",
    "sg:tags":[
        "shop",
        "chip"
    ],
    "wof:name":"Chipmunks",
    "wof:placetype":"venue"
},
  "geometry": {"coordinates":[-1.1540410519,50.730091095],"type":"Point"}
}