{
  "type": "Feature",
  "properties": {
    "addr:full":"Station Rd Gloucester Gloucestershire GL1 1EW",
    "addr:postcode":"gl1 1ew",
    "addr:street":"Station Rd",
    "iso:country":"GB",
    "sg:address":"Station Rd",
    "sg:city":"Gloucester",
    "sg:classifiers":[
        {
            "category":"Bars & Pubs",
            "type":"Food & Drink"
        }
    ],
    "sg:postcode":"GL1 1EW",
    "sg:province":"Gloucestershire",
    "sg:tags":[
        "pubs",
        "inn"
    ],
    "wof:name":"Prince of Wales",
    "wof:placetype":"venue"
},
  "geometry": {"coordinates":[-2.241349,51.865044],"type":"Point"}
}