{
  "type": "Feature",
  "properties": {
    "addr:full":"31 Bold Street Liverpool Merseyside L1 4DN",
    "addr:housenumber":"31",
    "addr:postcode":"l1 4dn",
    "addr:street":"Bold Street",
    "iso:country":"GB",
    "sg:address":"31 Bold Street",
    "sg:city":"Liverpool",
    "sg:classifiers":[
        {
            "category":"Home & Garden",
            "subcategory":"Home Furnishings",
            "type":"Retail Goods"
        }
    ],
    "sg:phone":"+44 151 708 9806",
    "sg:postcode":"L1 4DN",
    "sg:province":"Merseyside",
    "sg:tags":[
        "beds",
        "bedding",
        "blanket",
        "bed"
    ],
    "wof:name":"HOME & BARGAIN LINEN",
    "wof:placetype":"venue"
},
  "geometry": {"coordinates":[-2.979279995,53.4037475586],"type":"Point"}
}