{
  "type": "Feature",
  "properties": {
    "addr:full":"Unit 31 Site 6a Rushock Trading Est Droitwich Worcestershire WR9 0NR",
    "addr:housenumber":"unit 31;6a",
    "addr:postcode":"wr9 0nr",
    "addr:street":"Site",
    "iso:country":"GB",
    "sg:address":"Unit 31 Site 6a Rushock Trading Est",
    "sg:city":"Droitwich",
    "sg:classifiers":[
        {
            "category":"Professional",
            "subcategory":"Engineering",
            "type":"Services"
        }
    ],
    "sg:phone":"+44 1299 251031",
    "sg:postcode":"WR9 0NR",
    "sg:province":"Worcestershire",
    "sg:tags":[
        "precision",
        "engineer"
    ],
    "wof:name":"Rushock Precision Engineering Ltd",
    "wof:placetype":"venue"
},
  "geometry": {"coordinates":[-2.172187,52.338905],"type":"Point"}
}