{
  "type": "Feature",
  "properties": {
    "iso:country":"GB",
    "sg:address":"24 Church Road, Aston",
    "sg:city":"Birmingham",
    "sg:classifiers":[
        {
            "category":"Shopping",
            "subcategory":"Pharmacy",
            "type":"Retail Goods"
        }
    ],
    "sg:phone":"+44 121 326 7159",
    "sg:postcode":"B6 5UP",
    "sg:province":"West Midlands",
    "sg:tags":[
        "pharmacist",
        "chemist"
    ],
    "wof:name":"Vantage Chemist",
    "wof:placetype":"venue"
},
  "geometry": {"coordinates":[-1.875726,52.503628],"type":"Point"}
}