{
  "type": "Feature",
  "properties": {
    "addr:full":"239a Footscray Road London Greater London SE9 2EL",
    "addr:housenumber":"239a",
    "addr:postcode":"se9 2el",
    "addr:street":"Footscray Road",
    "iso:country":"GB",
    "sg:address":"239a Footscray Road",
    "sg:city":"London",
    "sg:classifiers":[
        {
            "category":"Arena",
            "subcategory":"Sports Club",
            "type":"Entertainment"
        }
    ],
    "sg:phone":"+44 20 8850 4698",
    "sg:postcode":"SE9 2EL",
    "sg:province":"Greater London",
    "wof:name":"Footscray Rugby Sports & Social Club",
    "wof:placetype":"venue"
},
  "geometry": {"coordinates":[0.0696899965,51.4405593872],"type":"Point"}
}