{
  "type": "Feature",
  "properties": {
    "addr:full":"6 Glan-y-llyn, North Cornelly Bridgend Bridgend CF33 4EF",
    "addr:housenumber":"6",
    "addr:postcode":"cf33 4ef",
    "addr:street":"Glan-Y-Llyn North;Bridgend",
    "iso:country":"GB",
    "sg:address":"6 Glan-y-llyn, North Cornelly",
    "sg:city":"Bridgend",
    "sg:classifiers":[
        {
            "category":"Health Services",
            "subcategory":"Health Practitioner",
            "type":"Services"
        }
    ],
    "sg:phone":"+44 1656 740200",
    "sg:postcode":"CF33 4EF",
    "sg:province":"Bridgend",
    "sg:tags":[
        "therapist",
        "speech"
    ],
    "wof:name":"Mid Glamorgan Hypnotherapy",
    "wof:placetype":"venue"
},
  "geometry": {"coordinates":[-3.6967229843,51.519329071],"type":"Point"}
}