{
  "type": "Feature",
  "properties": {
    "iso:country":"GB",
    "sg:address":"175 Commercial Street",
    "sg:city":"Edinburgh",
    "sg:classifiers":[
        {
            "category":"Community Center",
            "subcategory":"Youth",
            "type":"Public Place"
        }
    ],
    "sg:phone":"+44 131 554 0510",
    "sg:postcode":"EH6 6JE",
    "sg:province":"City of Edinburgh",
    "sg:tags":[
        "organisation",
        "centre"
    ],
    "wof:name":"Citadel Youth Centre",
    "wof:placetype":"venue"
},
  "geometry": {"coordinates":[-3.176146,55.977428],"type":"Point"}
}