{
  "type": "Feature",
  "properties": {
    "iso:country":"GB",
    "sg:address":"367 Wokingham Road, Earley",
    "sg:city":"Reading",
    "sg:classifiers":[
        {
            "category":"Sports & Exercise",
            "subcategory":"Golf",
            "type":"Entertainment"
        }
    ],
    "sg:postcode":"RG6 7EH",
    "sg:province":"Berkshire",
    "sg:tags":[
        "equipment"
    ],
    "wof:name":"Cml Golf",
    "wof:placetype":"venue"
},
  "geometry": {"coordinates":[-0.912136,51.438782],"type":"Point"}
}