{
  "type": "Feature",
  "properties": {
    "addr:full":"23 Queen Annes Gro London Greater London W4 1HW",
    "addr:housenumber":"23",
    "addr:postcode":"w4 1hw",
    "addr:street":"Queen Annes",
    "iso:country":"GB",
    "sg:address":"23 Queen Annes Gro",
    "sg:city":"London",
    "sg:classifiers":[
        {
            "category":"Building & Trades",
            "subcategory":"Construction",
            "type":"Services"
        }
    ],
    "sg:postcode":"W4 1HW",
    "sg:province":"Greater London",
    "sg:tags":[
        "restoration",
        "refurbishment"
    ],
    "wof:name":"J H A Build & Design",
    "wof:placetype":"venue"
},
  "geometry": {"coordinates":[-0.1335999966,51.5003585815],"type":"Point"}
}