{
  "type": "Feature",
  "properties": {
    "iso:country":"GB",
    "sg:address":"3 Collins Avenue",
    "sg:city":"Blackpool",
    "sg:classifiers":[
        {
            "category":"Food & Beverages",
            "subcategory":"Meat & Fish",
            "type":"Retail Goods"
        },
        {
            "category":"Food & Beverages",
            "subcategory":"Groceries & Convenience Stores",
            "type":"Retail Goods"
        }
    ],
    "sg:phone":"+44 1253 358926",
    "sg:postcode":"FY2 0NS",
    "sg:province":"Lancashire",
    "sg:tags":[
        "shop",
        "chip"
    ],
    "wof:name":"Squirrel Chippy",
    "wof:placetype":"venue"
},
  "geometry": {"coordinates":[-3.0328669548,53.8438720703],"type":"Point"}
}