{
  "type": "Feature",
  "properties": {
    "iso:country":"GB",
    "sg:address":"Station Street",
    "sg:city":"Saltburn-by-the-sea",
    "sg:classifiers":[
        {
            "category":"Travel",
            "subcategory":"Hotels & Motels",
            "type":"Entertainment"
        }
    ],
    "sg:phone":"+44 1287 625820",
    "sg:postcode":"TS12 1AE",
    "sg:province":"North Yorkshire",
    "wof:name":"The Queen Hotel",
    "wof:placetype":"venue"
},
  "geometry": {"coordinates":[-0.973706,54.582943],"type":"Point"}
}