{
  "type": "Feature",
  "properties": {
    "iso:country":"GB",
    "sg:address":"Unit 2 Blackhouse Quay, Little London",
    "sg:city":"Newport",
    "sg:classifiers":[
        {
            "category":"Building & Trades",
            "subcategory":"Construction",
            "type":"Services"
        }
    ],
    "sg:phone":"+44 1983 520750",
    "sg:postcode":"PO30 5YH",
    "sg:province":"Isle of Wight",
    "sg:tags":[
        "fork",
        "lift",
        "truck"
    ],
    "wof:name":"Transportatruck",
    "wof:placetype":"venue"
},
  "geometry": {"coordinates":[-1.302009,50.705818],"type":"Point"}
}