{
  "type": "Feature",
  "properties": {
    "iso:country":"GB",
    "sg:address":"Unit 17 Enterprise Trading Estate, Pedmore Road",
    "sg:city":"Brierley Hill",
    "sg:classifiers":[
        {
            "category":"Home & Garden",
            "subcategory":"Building Materials",
            "type":"Retail Goods"
        }
    ],
    "sg:phone":"+44 1384 482492",
    "sg:postcode":"DY5 1HG",
    "sg:province":"West Midlands",
    "sg:tags":[
        "access",
        "equipment"
    ],
    "wof:name":"Russon Access Platforms",
    "wof:placetype":"venue"
},
  "geometry": {"coordinates":[-2.105249,52.484463],"type":"Point"}
}