{
  "type": "Feature",
  "properties": {
    "addr:full":"340 Station Road Harrow Greater London HA1 2DR",
    "addr:housenumber":"340",
    "addr:postcode":"ha1 2dr",
    "addr:street":"Station Road",
    "iso:country":"GB",
    "sg:address":"340 Station Road",
    "sg:city":"Harrow",
    "sg:classifiers":[
        {
            "category":"Retail",
            "subcategory":"Laundry & Dry Cleaning",
            "type":"Services"
        },
        {
            "category":"Shopping",
            "subcategory":"Shoes",
            "type":"Retail Goods"
        }
    ],
    "sg:phone":"+44 20 8861 0446",
    "sg:postcode":"HA1 2DR",
    "sg:province":"Greater London",
    "sg:tags":[
        "alteration"
    ],
    "wof:name":"Sketchley Dry Cleaners",
    "wof:placetype":"venue"
},
  "geometry": {"coordinates":[-0.333829999,51.5803947449],"type":"Point"}
}