{
  "type": "Feature",
  "properties": {
    "iso:country":"GB",
    "sg:address":"252 Jamaica Rd",
    "sg:city":"Sth Bermondsey",
    "sg:classifiers":[
        {
            "category":"Community Center",
            "subcategory":"Youth",
            "type":"Public Place"
        }
    ],
    "sg:phone":"+44 20 7237 2333",
    "sg:postcode":"SE16 4BD",
    "sg:province":"Greater London",
    "sg:tags":[
        "organisation",
        "centre"
    ],
    "wof:name":"Bermonsey & Southwark District Scout Council",
    "wof:placetype":"venue"
},
  "geometry": {"coordinates":[-0.0585110001,51.4987220764],"type":"Point"}
}