{
  "type": "Feature",
  "properties": {
    "addr:full":"14 John Street Sunderland Tyne and Wear SR1 1HZ",
    "addr:housenumber":"14",
    "addr:postcode":"sr1 1hz",
    "addr:street":"John Street",
    "iso:country":"GB",
    "sg:address":"14 John Street",
    "sg:city":"Sunderland",
    "sg:classifiers":[
        {
            "category":"Professional",
            "subcategory":"Lawyer & Legal Services",
            "type":"Services"
        }
    ],
    "sg:phone":"+44 191 567 7024",
    "sg:postcode":"SR1 1HZ",
    "sg:province":"Tyne and Wear",
    "sg:tags":[
        "solicitor"
    ],
    "wof:name":"Longdon Walker & Renny",
    "wof:placetype":"venue"
},
  "geometry": {"coordinates":[-1.3801590204,54.9061355591],"type":"Point"}
}