{
  "type": "Feature",
  "properties": {
    "addr:full":"17-19 Bishopthorpe Road York North Yorkshire YO23 1NA",
    "addr:housenumber":"17-19",
    "addr:postcode":"yo23 1na",
    "addr:street":"Bishopthorpe Road",
    "iso:country":"GB",
    "sg:address":"17-19 Bishopthorpe Road",
    "sg:city":"York",
    "sg:classifiers":[
        {
            "category":"Restaurant",
            "type":"Food & Drink"
        }
    ],
    "sg:phone":"+44 1904 670684",
    "sg:postcode":"YO23 1NA",
    "sg:province":"North Yorkshire",
    "sg:tags":[
        "indian"
    ],
    "wof:name":"Lal Quila Restaurant",
    "wof:placetype":"venue"
},
  "geometry": {"coordinates":[-1.084913,53.951756],"type":"Point"}
}