{
  "type": "Feature",
  "properties": {
    "addr:full":"1 Meadows Rd Cheadle Cheshire SK8 6EJ",
    "addr:housenumber":"1",
    "addr:postcode":"sk8 6ej",
    "addr:street":"Meadows Rd Cheadle",
    "iso:country":"GB",
    "sg:address":"1 Meadows Rd",
    "sg:city":"Cheadle",
    "sg:classifiers":[
        {
            "category":"Building & Trades",
            "subcategory":"Construction",
            "type":"Services"
        }
    ],
    "sg:phone":"+44 161 477 4443",
    "sg:postcode":"SK8 6EJ",
    "sg:province":"Cheshire",
    "sg:tags":[
        "decorator",
        "painter"
    ],
    "wof:name":"Philip Marsden Decorators",
    "wof:placetype":"venue"
},
  "geometry": {"coordinates":[-2.198657,53.370609],"type":"Point"}
}