{
  "type": "Feature",
  "properties": {
    "addr:full":"843 Shettleston Road Glasgow Glasgow City G32 7NR",
    "addr:housenumber":"843",
    "addr:postcode":"g32 7nr",
    "addr:street":"Shettleston Road",
    "iso:country":"GB",
    "sg:address":"843 Shettleston Road",
    "sg:city":"Glasgow",
    "sg:classifiers":[
        {
            "category":"Bars & Pubs",
            "type":"Food & Drink"
        }
    ],
    "sg:phone":"+44 141 778 3601",
    "sg:postcode":"G32 7NR",
    "sg:province":"Glasgow City",
    "sg:tags":[
        "pubs",
        "inn"
    ],
    "wof:name":"The Town Tavern",
    "wof:placetype":"venue"
},
  "geometry": {"coordinates":[-4.175297,55.852249],"type":"Point"}
}