{
  "type": "Feature",
  "properties": {
    "addr:full":"77 Elm Rd New Malden Surrey KT3 3HH",
    "addr:housenumber":"77",
    "addr:postcode":"kt3 3hh",
    "addr:street":"Elm Rd",
    "iso:country":"GB",
    "sg:address":"77 Elm Rd",
    "sg:city":"New Malden",
    "sg:classifiers":[
        {
            "category":"Home & Garden",
            "subcategory":"Hardware",
            "type":"Retail Goods"
        }
    ],
    "sg:phone":"+44 20 8942 2722",
    "sg:postcode":"KT3 3HH",
    "sg:province":"Surrey",
    "sg:tags":[
        "lawnmowers",
        "machinery"
    ],
    "wof:name":"Rexvale Mowers Ltd",
    "wof:placetype":"venue"
},
  "geometry": {"coordinates":[-0.265278995,51.4036140442],"type":"Point"}
}