{
  "type": "Feature",
  "properties": {
    "addr:full":"John M Castro & Co, 76 High Street Brierley Hill West Midlands DY5 3AW",
    "addr:housenumber":"76",
    "addr:postcode":"dy5 3aw",
    "addr:street":"John;High Street",
    "iso:country":"GB",
    "sg:address":"John M Castro & Co, 76 High Street",
    "sg:city":"Brierley Hill",
    "sg:classifiers":[
        {
            "category":"Building & Trades",
            "subcategory":"Construction",
            "type":"Services"
        }
    ],
    "sg:phone":"+44 1384 262601",
    "sg:postcode":"DY5 3AW",
    "sg:province":"West Midlands",
    "sg:tags":[
        "concrete"
    ],
    "wof:name":"R M Reinforcements Ltd.",
    "wof:placetype":"venue"
},
  "geometry": {"coordinates":[-2.1214680672,52.4806022644],"type":"Point"}
}