{
  "type": "Feature",
  "properties": {
    "addr:full":"56a High St Camberley Berkshire GU15 3RS",
    "addr:housenumber":"56a",
    "addr:postcode":"gu15 3rs",
    "addr:street":"High St",
    "iso:country":"GB",
    "sg:address":"56a High St",
    "sg:city":"Camberley",
    "sg:classifiers":[
        {
            "category":"Professional",
            "subcategory":"Employment Agencies",
            "type":"Services"
        }
    ],
    "sg:phone":"+44 1276 691895",
    "sg:postcode":"GU15 3RS",
    "sg:province":"Berkshire",
    "sg:tags":[
        "consultant"
    ],
    "wof:name":"Banking Personnel",
    "wof:placetype":"venue"
},
  "geometry": {"coordinates":[-0.7446619868,51.3381385803],"type":"Point"}
}