{
  "type": "Feature",
  "properties": {
    "iso:country":"GB",
    "sg:address":"26 Hornby Road",
    "sg:city":"Blackpool",
    "sg:classifiers":[
        {
            "category":"Travel",
            "subcategory":"Hotels & Motels",
            "type":"Entertainment"
        }
    ],
    "sg:phone":"+44 1253 624377",
    "sg:postcode":"FY1 4QG",
    "sg:province":"Lancashire",
    "wof:name":"Newholme",
    "wof:placetype":"venue"
},
  "geometry": {"coordinates":[-3.05108,53.813938],"type":"Point"}
}