{
  "type": "Feature",
  "properties": {
    "addr:full":"53 Woolpack St Wolverhampton West Midlands WV1 3NA",
    "addr:housenumber":"53",
    "addr:postcode":"wv1 3na",
    "addr:street":"Woolpack St",
    "iso:country":"GB",
    "sg:address":"53 Woolpack St",
    "sg:city":"Wolverhampton",
    "sg:classifiers":[
        {
            "category":"Professional",
            "subcategory":"Employment Agencies",
            "type":"Services"
        }
    ],
    "sg:phone":"+44 1902 714122",
    "sg:postcode":"WV1 3NA",
    "sg:province":"West Midlands",
    "sg:tags":[
        "consultant"
    ],
    "wof:name":"Temps Select",
    "wof:placetype":"venue"
},
  "geometry": {"coordinates":[-2.127834,52.585419],"type":"Point"}
}