{
  "type": "Feature",
  "properties": {
    "addr:full":"6 Bennett Street, Sandiacre Nottingham Derbyshire NG10 5JF",
    "addr:housenumber":"6",
    "addr:postcode":"ng10 5jf",
    "addr:street":"Bennett Street",
    "iso:country":"GB",
    "sg:address":"6 Bennett Street, Sandiacre",
    "sg:city":"Nottingham",
    "sg:classifiers":[
        {
            "category":"Building & Trades",
            "subcategory":"Landscaping Services",
            "type":"Services"
        }
    ],
    "sg:postcode":"NG10 5JF",
    "sg:province":"Derbyshire",
    "sg:tags":[
        "gardening"
    ],
    "wof:name":"John Cresswell",
    "wof:placetype":"venue"
},
  "geometry": {"coordinates":[-1.291445,52.923782],"type":"Point"}
}