{
  "type": "Feature",
  "properties": {
    "addr:full":"Unit 2 Culme Way, Dunkeswell Honiton Devon EX14 4JP",
    "addr:housenumber":"unit 2",
    "addr:postcode":"ex14 4jp",
    "addr:street":"Culme Way",
    "iso:country":"GB",
    "sg:address":"Unit 2 Culme Way, Dunkeswell",
    "sg:city":"Honiton",
    "sg:classifiers":[
        {
            "category":"Fast Food",
            "type":"Food & Drink"
        },
        {
            "category":"Organizations",
            "subcategory":"Membership Organization",
            "type":"Services"
        }
    ],
    "sg:phone":"+44 1404 891714",
    "sg:postcode":"EX14 4JP",
    "sg:province":"Devon",
    "sg:tags":[
        "club",
        "away",
        "take",
        "outlet",
        "meal"
    ],
    "wof:name":"Highfield Sports & Social Club",
    "wof:placetype":"venue"
},
  "geometry": {"coordinates":[-3.2217390537,50.854095459],"type":"Point"}
}