{
  "type": "Feature",
  "properties": {
    "addr:full":"Rivers Corner, Glue Hill Sturminster Newton Dorset DT10 2AB",
    "addr:postcode":"dt10 2ab",
    "addr:street":"Glue Hill",
    "iso:country":"GB",
    "sg:address":"Rivers Corner, Glue Hill",
    "sg:city":"Sturminster Newton",
    "sg:classifiers":[
        {
            "category":"Building & Trades",
            "subcategory":"Construction",
            "type":"Services"
        },
        {
            "category":"Utilities",
            "subcategory":"Natural Gas",
            "type":"Services"
        }
    ],
    "sg:phone":"+44 1258 472213",
    "sg:postcode":"DT10 2AB",
    "sg:province":"Dorset",
    "sg:tags":[
        "control",
        "management",
        "system",
        "energy",
        "heating",
        "contractor"
    ],
    "wof:name":"A K H Heating Ltd.",
    "wof:placetype":"venue"
},
  "geometry": {"coordinates":[-2.3128418922,50.9198112488],"type":"Point"}
}