{
  "type": "Feature",
  "properties": {
    "addr:full":"165 Sydenham Road London Greater London SE26 5HB",
    "addr:housenumber":"165",
    "addr:postcode":"se26 5hb",
    "addr:street":"Sydenham Road",
    "iso:country":"GB",
    "sg:address":"165 Sydenham Road",
    "sg:city":"London",
    "sg:classifiers":[
        {
            "category":"Shopping",
            "subcategory":"News",
            "type":"Retail Goods"
        }
    ],
    "sg:postcode":"SE26 5HB",
    "sg:province":"Greater London",
    "sg:tags":[
        "newsagent"
    ],
    "wof:name":"B K Patel",
    "wof:placetype":"venue"
},
  "geometry": {"coordinates":[-0.046441,51.4258422852],"type":"Point"}
}