{
  "type": "Feature",
  "properties": {
    "iso:country":"GB",
    "sg:address":"89 Western Road",
    "sg:city":"Hove",
    "sg:classifiers":[
        {
            "category":"Shopping",
            "subcategory":"Clothing, Apparel, & Fashions",
            "type":"Retail Goods"
        }
    ],
    "sg:phone":"+44 1273 775583",
    "sg:postcode":"BN3 1JB",
    "sg:province":"East Sussex",
    "sg:tags":[
        "dresswear"
    ],
    "wof:name":"The Walk in Wardrobe",
    "wof:placetype":"venue"
},
  "geometry": {"coordinates":[-0.160592,50.826038],"type":"Point"}
}