{
  "type": "Feature",
  "properties": {
    "iso:country":"GB",
    "sg:address":"168 Crook Street",
    "sg:city":"Bolton",
    "sg:classifiers":[
        {
            "category":"Professional",
            "subcategory":"Printing & Photocopies",
            "type":"Services"
        }
    ],
    "sg:phone":"+44 1204 525300",
    "sg:postcode":"BL3 6AS",
    "sg:province":"Lancashire",
    "sg:tags":[
        "printer"
    ],
    "wof:name":"Hardman & Co.",
    "wof:placetype":"venue"
},
  "geometry": {"coordinates":[-2.426156,53.573357],"type":"Point"}
}