{
  "type": "Feature",
  "properties": {
    "addr:full":"Atlas House, Bell St West Bromwich West Midlands B70 7BT",
    "addr:postcode":"b70 7bt",
    "addr:street":"Bell St West",
    "iso:country":"GB",
    "sg:address":"Atlas House, Bell St",
    "sg:city":"West Bromwich",
    "sg:classifiers":[
        {
            "category":"Building & Trades",
            "subcategory":"Construction",
            "type":"Services"
        }
    ],
    "sg:phone":"+44 121 500 5791",
    "sg:postcode":"B70 7BT",
    "sg:province":"West Midlands",
    "sg:tags":[
        "fork",
        "lift",
        "truck"
    ],
    "wof:name":"Lift Truck Repair Service",
    "wof:placetype":"venue"
},
  "geometry": {"coordinates":[-1.9929089546,52.5135955811],"type":"Point"}
}