{
  "type": "Feature",
  "properties": {
    "addr:full":"601 Woodborough Rd, Mapperley Nottingham Nottinghamshire NG3 5RA",
    "addr:housenumber":"601",
    "addr:postcode":"ng3 5ra",
    "addr:street":"Woodborough Rd",
    "iso:country":"GB",
    "sg:address":"601 Woodborough Rd, Mapperley",
    "sg:city":"Nottingham",
    "sg:classifiers":[
        {
            "category":"Autos & Motor Vehicles",
            "subcategory":"Fuel & Gas Station",
            "type":"Retail Goods"
        }
    ],
    "sg:postcode":"NG3 5RA",
    "sg:province":"Nottinghamshire",
    "sg:tags":[
        "petrol",
        "filling"
    ],
    "wof:name":"Mapperley Service Station",
    "wof:placetype":"venue"
},
  "geometry": {"coordinates":[-1.1273620129,52.9815788269],"type":"Point"}
}