{
  "type": "Feature",
  "properties": {
    "addr:full":"South Bank Road East Middlesbrough North Yorkshire TS3 8AX",
    "addr:postcode":"ts3 8ax",
    "addr:street":"South Bank Road East",
    "iso:country":"GB",
    "sg:address":"South Bank Road East",
    "sg:city":"Middlesbrough",
    "sg:classifiers":[
        {
            "category":"Autos & Motor Vehicles",
            "subcategory":"Automobile Sales",
            "type":"Retail Goods"
        }
    ],
    "sg:postcode":"TS3 8AX",
    "sg:province":"North Yorkshire",
    "sg:tags":[
        "car"
    ],
    "wof:name":"Eric Carter Car Sales",
    "wof:placetype":"venue"
},
  "geometry": {"coordinates":[-1.2035690546,54.5740089417],"type":"Point"}
}