{
  "type": "Feature",
  "properties": {
    "iso:country":"GB",
    "sg:address":"Warminister Road, Littledown",
    "sg:city":"Shaftesbury",
    "sg:classifiers":[
        {
            "category":"Manufacturing",
            "subcategory":"Building Materials",
            "type":"Manufacturing & Wholesale Goods"
        }
    ],
    "sg:phone":"+44 1747 852772",
    "sg:postcode":"SP7 9HD",
    "sg:province":"Dorset",
    "sg:tags":[
        "merchant",
        "builder"
    ],
    "wof:name":"Travis Perkins",
    "wof:placetype":"venue"
},
  "geometry": {"coordinates":[-2.1886599064,51.0177612305],"type":"Point"}
}