{
  "type": "Feature",
  "properties": {
    "iso:country":"GB",
    "sg:address":"32 Scrutton Street",
    "sg:city":"London",
    "sg:classifiers":[
        {
            "category":"Insurance",
            "subcategory":"Insurance Agent",
            "type":"Services"
        },
        {
            "category":"Insurance",
            "subcategory":"Life Insurance",
            "type":"Services"
        }
    ],
    "sg:phone":"+44 20 8850 3288",
    "sg:postcode":"EC2A 4RQ",
    "sg:province":"Greater London",
    "sg:tags":[
        "broker",
        "assurance"
    ],
    "wof:name":"Directly Financial Ltd.",
    "wof:placetype":"venue"
},
  "geometry": {"coordinates":[-0.0819170028,51.52318573],"type":"Point"}
}