{
  "type": "Feature",
  "properties": {
    "iso:country":"GB",
    "sg:address":"Park View, Swynnerton",
    "sg:city":"Stone",
    "sg:classifiers":[
        {
            "category":"Education",
            "subcategory":"School",
            "type":"Public Place"
        }
    ],
    "sg:phone":"+44 1782 796214",
    "sg:postcode":"ST15 0QG",
    "sg:province":"Staffordshire",
    "sg:tags":[
        "local",
        "authority"
    ],
    "wof:name":"Swynnerton R C Primary School",
    "wof:placetype":"venue"
},
  "geometry": {"coordinates":[-2.222924,52.916553],"type":"Point"}
}