{
  "type": "Feature",
  "properties": {
    "addr:full":"170-172 Merton Road London Greater London SW19 1EG",
    "addr:housenumber":"170-172",
    "addr:postcode":"sw19 1eg",
    "addr:street":"Merton Road",
    "iso:country":"GB",
    "sg:address":"170-172 Merton Road",
    "sg:city":"London",
    "sg:classifiers":[
        {
            "category":"Retail",
            "subcategory":"Veterinary Services",
            "type":"Services"
        }
    ],
    "sg:postcode":"SW19 1EG",
    "sg:province":"Greater London",
    "sg:tags":[
        "surgeon"
    ],
    "wof:name":"Park Veterinary Practice",
    "wof:placetype":"venue"
},
  "geometry": {"coordinates":[-0.192787,51.418236],"type":"Point"}
}