{
  "type": "Feature",
  "properties": {
    "iso:country":"GB",
    "sg:address":"24 Putnoe Lane",
    "sg:city":"Bedford",
    "sg:classifiers":[
        {
            "category":"Manufacturing",
            "subcategory":"Furniture",
            "type":"Manufacturing & Wholesale Goods"
        }
    ],
    "sg:phone":"+44 1234 266238",
    "sg:postcode":"MK41 9AB",
    "sg:province":"Bedfordshire",
    "sg:tags":[
        "polishing",
        "french"
    ],
    "wof:name":"E C Garratt",
    "wof:placetype":"venue"
},
  "geometry": {"coordinates":[-0.4518530071,52.1503181458],"type":"Point"}
}