{
  "type": "Feature",
  "properties": {
    "addr:full":"Unit 12, Lyon Road Industrial Estate, Kearsley Bolton Lancashire BL4 8NB",
    "addr:housenumber":"unit 12",
    "addr:postcode":"bl4 8nb",
    "addr:street":"Lyon Road Industrial Estate",
    "iso:country":"GB",
    "sg:address":"Unit 12, Lyon Road Industrial Estate, Kearsley",
    "sg:city":"Bolton",
    "sg:classifiers":[
        {
            "category":"Home & Garden",
            "subcategory":"Hardware",
            "type":"Retail Goods"
        }
    ],
    "sg:phone":"+44 1204 706666",
    "sg:postcode":"BL4 8NB",
    "sg:province":"Lancashire",
    "sg:tags":[
        "device",
        "fixing",
        "fastener"
    ],
    "wof:name":"Pembury Super Pack",
    "wof:placetype":"venue"
},
  "geometry": {"coordinates":[-2.3874740601,53.5373153687],"type":"Point"}
}