{
  "type": "Feature",
  "properties": {
    "iso:country":"GB",
    "sg:address":"27 Station Road",
    "sg:city":"Horsham",
    "sg:classifiers":[
        {
            "category":"Home & Garden",
            "subcategory":"Garden Supply",
            "type":"Retail Goods"
        }
    ],
    "sg:phone":"+44 1403 730505",
    "sg:postcode":"RH13 5EZ",
    "sg:province":"West Sussex",
    "sg:tags":[
        "pool",
        "swimming"
    ],
    "wof:name":"Alligator Pools Ltd.",
    "wof:placetype":"venue"
},
  "geometry": {"coordinates":[-0.3179840147,51.0658760071],"type":"Point"}
}