{
  "type": "Feature",
  "properties": {
    "addr:full":"Glebe Farm, Bozeat Wellingborough Bedfordshire NN29 7LB",
    "addr:postcode":"nn29 7lb",
    "iso:country":"GB",
    "sg:address":"Glebe Farm, Bozeat",
    "sg:city":"Wellingborough",
    "sg:classifiers":[
        {
            "category":"Sports & Exercise",
            "subcategory":"Stables",
            "type":"Entertainment"
        }
    ],
    "sg:phone":"+44 1933 665083",
    "sg:postcode":"NN29 7LB",
    "sg:province":"Bedfordshire",
    "sg:tags":[
        "education",
        "equestrian"
    ],
    "wof:name":"Glebe Farm Equestrian Centre",
    "wof:placetype":"venue"
},
  "geometry": {"coordinates":[-0.6760280132,52.2217483521],"type":"Point"}
}