{
  "type": "Feature",
  "properties": {
    "addr:full":"Fys Cross Farm, Knightons Lane Godalming Surrey GU8 4NY",
    "addr:postcode":"gu8 4ny",
    "addr:street":"Fys;Knightons Lane",
    "iso:country":"GB",
    "sg:address":"Fys Cross Farm, Knightons Lane",
    "sg:city":"Godalming",
    "sg:classifiers":[
        {
            "category":"Shopping",
            "subcategory":"Clothing, Apparel, & Fashions",
            "type":"Retail Goods"
        }
    ],
    "sg:phone":"+44 1483 200777",
    "sg:postcode":"GU8 4NY",
    "sg:province":"Surrey",
    "sg:tags":[
        "wear",
        "leisure"
    ],
    "wof:name":"Magnum Enterprises",
    "wof:placetype":"venue"
},
  "geometry": {"coordinates":[-0.5591199994,51.1086196899],"type":"Point"}
}