{
  "type": "Feature",
  "properties": {
    "addr:full":"6 Dingwall Drive, Greasby Wirral Merseyside CH49 1SG",
    "addr:housenumber":"6",
    "addr:postcode":"ch49 1sg",
    "addr:street":"Dingwall Drive",
    "iso:country":"GB",
    "sg:address":"6 Dingwall Drive, Greasby",
    "sg:city":"Wirral",
    "sg:classifiers":[
        {
            "category":"Retail",
            "subcategory":"Auto Repair",
            "type":"Services"
        }
    ],
    "sg:postcode":"CH49 1SG",
    "sg:province":"Merseyside",
    "sg:tags":[
        "engine",
        "specialist",
        "garage",
        "modification",
        "car"
    ],
    "wof:name":"Mobile Mechanic",
    "wof:placetype":"venue"
},
  "geometry": {"coordinates":[-3.114044,53.376514],"type":"Point"}
}