{
  "type": "Feature",
  "properties": {
    "iso:country":"GB",
    "sg:address":"6 Volpe Clo",
    "sg:city":"Swindon",
    "sg:classifiers":[
        {
            "category":"Professional",
            "type":"Services"
        }
    ],
    "sg:phone":"+44 1793 881488",
    "sg:postcode":"SN5 6BS",
    "sg:province":"Wiltshire",
    "sg:tags":[
        "repair",
        "tech",
        "maintenance"
    ],
    "wof:name":"Finesse Systems",
    "wof:placetype":"venue"
},
  "geometry": {"coordinates":[-1.847530961,51.5532417297],"type":"Point"}
}