{
  "type": "Feature",
  "properties": {
    "addr:full":"Hallam Mill, Hallam St Stockport Cheshire SK2 6PT",
    "addr:postcode":"sk2 6pt",
    "addr:street":"Hallam;Hallam St",
    "iso:country":"GB",
    "sg:address":"Hallam Mill, Hallam St",
    "sg:city":"Stockport",
    "sg:classifiers":[
        {
            "category":"Shopping",
            "subcategory":"Jewelry",
            "type":"Retail Goods"
        }
    ],
    "sg:phone":"+44 161 477 1411",
    "sg:postcode":"SK2 6PT",
    "sg:province":"Cheshire",
    "sg:tags":[
        "gold",
        "silversmith"
    ],
    "wof:name":"Ben Woodcock Jewellery",
    "wof:placetype":"venue"
},
  "geometry": {"coordinates":[-2.1513400078,53.3955993652],"type":"Point"}
}