{
  "type": "Feature",
  "properties": {
    "addr:full":"8 Kirton Crescent Lytham St. Annes Lancashire FY8 4BJ",
    "addr:housenumber":"8",
    "addr:postcode":"fy8 4bj",
    "addr:street":"Kirton Crescent",
    "iso:country":"GB",
    "sg:address":"8 Kirton Crescent",
    "sg:city":"Lytham St. Annes",
    "sg:classifiers":[
        {
            "category":"Building & Trades",
            "subcategory":"Construction",
            "type":"Services"
        }
    ],
    "sg:phone":"+44 1253 737836",
    "sg:postcode":"FY8 4BJ",
    "sg:province":"Lancashire",
    "sg:tags":[
        "builder"
    ],
    "wof:name":"Arnold Mason & Son",
    "wof:placetype":"venue"
},
  "geometry": {"coordinates":[-2.994673,53.751236],"type":"Point"}
}