{
  "type": "Feature",
  "properties": {
    "addr:full":"Austin Drive Coventry Warwickshire CV6 7NS",
    "addr:postcode":"cv6 7ns",
    "addr:street":"Austin Drive",
    "iso:country":"GB",
    "sg:address":"Austin Drive",
    "sg:city":"Coventry",
    "sg:classifiers":[
        {
            "category":"Shopping",
            "subcategory":"Clothing, Apparel, & Fashions",
            "type":"Retail Goods"
        }
    ],
    "sg:phone":"+44 24 7668 1520",
    "sg:postcode":"CV6 7NS",
    "sg:province":"Warwickshire",
    "sg:tags":[
        "shop"
    ],
    "wof:name":"Stage 2",
    "wof:placetype":"venue"
},
  "geometry": {"coordinates":[-1.4849480391,52.4300727844],"type":"Point"}
}