{
  "type": "Feature",
  "properties": {
    "iso:country":"GB",
    "sg:address":"George Inn La",
    "sg:city":"Perth",
    "sg:classifiers":[
        {
            "category":"Organizations",
            "subcategory":"Professional Association",
            "type":"Services"
        }
    ],
    "sg:phone":"+44 1738 475098",
    "sg:postcode":"PH1 5LH",
    "sg:province":"Perth and Kinross",
    "sg:tags":[
        "union",
        "trade"
    ],
    "wof:name":"Unison Branch Office",
    "wof:placetype":"venue"
},
  "geometry": {"coordinates":[-3.4268140793,56.3979034424],"type":"Point"}
}