{
  "type": "Feature",
  "properties": {
    "addr:full":"49 King Street Manchester Greater Manchester M2 7AY",
    "addr:housenumber":"49",
    "addr:postcode":"m2 7ay",
    "addr:street":"King Street",
    "iso:country":"GB",
    "sg:address":"49 King Street",
    "sg:city":"Manchester",
    "sg:classifiers":[
        {
            "category":"Real Estate",
            "subcategory":"Surveying",
            "type":"Services"
        }
    ],
    "sg:phone":"+44 161 834 4066",
    "sg:postcode":"M2 7AY",
    "sg:province":"Greater Manchester",
    "sg:tags":[
        "surveyor",
        "valuer"
    ],
    "wof:name":"Skelhorn Walker",
    "wof:placetype":"venue"
},
  "geometry": {"coordinates":[-2.2450499535,53.4812088013],"type":"Point"}
}