{
  "type": "Feature",
  "properties": {
    "iso:country":"GB",
    "sg:address":"202 Bell Lane",
    "sg:city":"Bury",
    "sg:classifiers":[
        {
            "category":"Personal",
            "type":"Services"
        }
    ],
    "sg:postcode":"BL9 6HS",
    "sg:province":"Lancashire",
    "sg:tags":[
        "wedding"
    ],
    "wof:name":"Aristocrat Wedding Cars",
    "wof:placetype":"venue"
},
  "geometry": {"coordinates":[-2.277344,53.597645],"type":"Point"}
}