{
  "type": "Feature",
  "properties": {
    "addr:full":"44 Abbey Street Leicester Leicestershire LE1 3TG",
    "addr:housenumber":"44",
    "addr:postcode":"le1 3tg",
    "addr:street":"Abbey Street",
    "iso:country":"GB",
    "sg:address":"44 Abbey Street",
    "sg:city":"Leicester",
    "sg:classifiers":[
        {
            "category":"Professional",
            "subcategory":"Business Services",
            "type":"Services"
        }
    ],
    "sg:phone":"+44 116 251 8282",
    "sg:postcode":"LE1 3TG",
    "sg:province":"Leicestershire",
    "sg:tags":[
        "import",
        "export",
        "agent"
    ],
    "wof:name":"Lee Tai Trading Ltd.",
    "wof:placetype":"venue"
},
  "geometry": {"coordinates":[-1.132605,52.639839],"type":"Point"}
}