{
  "type": "Feature",
  "properties": {
    "addr:full":"34 Birchdale Rd Liverpool Merseyside L22 9QX",
    "addr:housenumber":"34",
    "addr:postcode":"l22 9qx",
    "addr:street":"Birchdale Rd",
    "iso:country":"GB",
    "sg:address":"34 Birchdale Rd",
    "sg:city":"Liverpool",
    "sg:classifiers":[
        {
            "category":"Education",
            "subcategory":"Music School",
            "type":"Public Place"
        }
    ],
    "sg:phone":"+44 151 474 3651",
    "sg:postcode":"L22 9QX",
    "sg:province":"Merseyside",
    "sg:tags":[
        "teacher"
    ],
    "wof:name":"Guitar Tuition",
    "wof:placetype":"venue"
},
  "geometry": {"coordinates":[-3.0288960934,53.4790611267],"type":"Point"}
}