{
  "type": "Feature",
  "properties": {
    "iso:country":"GB",
    "sg:address":"66 East Street",
    "sg:city":"London",
    "sg:classifiers":[
        {
            "category":"Shopping",
            "subcategory":"Shoes",
            "type":"Retail Goods"
        }
    ],
    "sg:phone":"+44 20 7703 8073",
    "sg:postcode":"SE17 2DQ",
    "sg:province":"Greater London",
    "sg:tags":[
        "shop"
    ],
    "wof:name":"Ravel Shoes",
    "wof:placetype":"venue"
},
  "geometry": {"coordinates":[-0.092606,51.488548],"type":"Point"}
}