{
  "type": "Feature",
  "properties": {
    "iso:country":"GB",
    "sg:address":"Church Rd",
    "sg:city":"Ely",
    "sg:classifiers":[
        {
            "category":"Place Of Worship",
            "type":"Public Place"
        }
    ],
    "sg:phone":"+44 1353 720243",
    "sg:postcode":"CB7 5XT",
    "sg:province":"Cambridgeshire",
    "wof:name":"St Laurence Church",
    "wof:placetype":"venue"
},
  "geometry": {"coordinates":[0.311515,52.310863],"type":"Point"}
}