{
  "type": "Feature",
  "properties": {
    "iso:country":"GB",
    "sg:address":"98 Sheffield Rd",
    "sg:city":"Sutton Coldfield",
    "sg:classifiers":[
        {
            "category":"Professional",
            "subcategory":"Engineering",
            "type":"Services"
        }
    ],
    "sg:phone":"+44 121 384 1133",
    "sg:postcode":"B73 5HW",
    "sg:province":"West Midlands",
    "sg:tags":[
        "ge",
        "engineer",
        "mechanical"
    ],
    "wof:name":"Prime Mechanical Services Ltd",
    "wof:placetype":"venue"
},
  "geometry": {"coordinates":[-1.832444,52.537544],"type":"Point"}
}