{
  "type": "Feature",
  "properties": {
    "addr:full":"44 Acton Rd Whitstable Kent CT5 1JJ",
    "addr:housenumber":"44",
    "addr:postcode":"ct5 1jj",
    "addr:street":"Acton Rd Whitstable",
    "iso:country":"GB",
    "sg:address":"44 Acton Rd",
    "sg:city":"Whitstable",
    "sg:classifiers":[
        {
            "category":"Building & Trades",
            "subcategory":"Construction",
            "type":"Services"
        }
    ],
    "sg:postcode":"CT5 1JJ",
    "sg:province":"Kent",
    "sg:tags":[
        "roofing"
    ],
    "wof:name":"Robinson,Danny,",
    "wof:placetype":"venue"
},
  "geometry": {"coordinates":[1.029214,51.359032],"type":"Point"}
}