{
  "type": "Feature",
  "properties": {
    "iso:country":"GB",
    "sg:address":"Barcaldine",
    "sg:city":"Oban",
    "sg:classifiers":[
        {
            "category":"Farming",
            "subcategory":"Nursery",
            "type":"Manufacturing & Wholesale Goods"
        }
    ],
    "sg:phone":"+44 1631 720605",
    "sg:postcode":"PA37 1SE",
    "sg:province":"Argyll and Bute",
    "sg:tags":[
        "creche"
    ],
    "wof:name":"Early Birds Nursery",
    "wof:placetype":"venue"
},
  "geometry": {"coordinates":[-5.381229,56.475048],"type":"Point"}
}