{
  "type": "Feature",
  "properties": {
    "addr:full":"76 Princes St Perth Perth and Kinross PH2 8LH",
    "addr:housenumber":"76",
    "addr:postcode":"ph2 8lh",
    "addr:street":"Princes St",
    "iso:country":"GB",
    "sg:address":"76 Princes St",
    "sg:city":"Perth",
    "sg:classifiers":[
        {
            "category":"Autos & Motor Vehicles",
            "subcategory":"Auto Supplies",
            "type":"Retail Goods"
        }
    ],
    "sg:phone":"+44 1738 630260",
    "sg:postcode":"PH2 8LH",
    "sg:province":"Perth and Kinross",
    "sg:tags":[
        "tyre"
    ],
    "wof:name":"Smiley",
    "wof:placetype":"venue"
},
  "geometry": {"coordinates":[-3.428236,56.39275],"type":"Point"}
}