{
  "type": "Feature",
  "properties": {
    "addr:full":"9 Royal Park Gro Leeds West Yorkshire LS6 1HF",
    "addr:housenumber":"9",
    "addr:postcode":"ls6 1hf",
    "addr:street":"Park Gro Leeds West",
    "iso:country":"GB",
    "sg:address":"9 Royal Park Gro",
    "sg:city":"Leeds",
    "sg:classifiers":[
        {
            "category":"Real Estate",
            "subcategory":"Real Estate Agent",
            "type":"Services"
        }
    ],
    "sg:postcode":"LS6 1HF",
    "sg:province":"West Yorkshire",
    "wof:name":"Woodhouse Estates",
    "wof:placetype":"venue"
},
  "geometry": {"coordinates":[-1.5667979717,53.8105354309],"type":"Point"}
}