{
  "type": "Feature",
  "properties": {
    "addr:full":"Church La Halstead Essex CO9 4DR",
    "addr:postcode":"co9 4dr",
    "addr:street":"La Halstead",
    "iso:country":"GB",
    "sg:address":"Church La",
    "sg:city":"Halstead",
    "sg:classifiers":[
        {
            "category":"Place Of Worship",
            "type":"Public Place"
        }
    ],
    "sg:phone":"+44 1787 237358",
    "sg:postcode":"CO9 4DR",
    "sg:province":"Essex",
    "wof:name":"St Margaret Of Antioch",
    "wof:placetype":"venue"
},
  "geometry": {"coordinates":[0.533758,52.0392],"type":"Point"}
}