{
  "type": "Feature",
  "properties": {
    "addr:full":"82 Middlewood Rd Sheffield South Yorkshire S6 4HA",
    "addr:housenumber":"82",
    "addr:postcode":"s6 4ha",
    "addr:street":"Middlewood Rd",
    "iso:country":"GB",
    "sg:address":"82 Middlewood Rd",
    "sg:city":"Sheffield",
    "sg:classifiers":[
        {
            "category":"Professional",
            "subcategory":"Art Services",
            "type":"Services"
        }
    ],
    "sg:postcode":"S6 4HA",
    "sg:province":"South Yorkshire",
    "sg:tags":[
        "framing"
    ],
    "wof:name":"Goodyear,Carole,",
    "wof:placetype":"venue"
},
  "geometry": {"coordinates":[-1.503401041,53.4044418335],"type":"Point"}
}