{
  "type": "Feature",
  "properties": {
    "addr:full":"Penkenna, Kanes Hill Southampton Hampshire SO19 6AJ",
    "addr:postcode":"so19 6aj",
    "addr:street":"Kanes Hill",
    "iso:country":"GB",
    "sg:address":"Penkenna, Kanes Hill",
    "sg:city":"Southampton",
    "sg:classifiers":[
        {
            "category":"Autos & Motor Vehicles",
            "subcategory":"Motorcycle Sales",
            "type":"Retail Goods"
        }
    ],
    "sg:phone":"+44 23 8047 1312",
    "sg:postcode":"SO19 6AJ",
    "sg:province":"Hampshire",
    "sg:tags":[
        "chauffeur",
        "driven",
        "car"
    ],
    "wof:name":"Adams Chauffeurs",
    "wof:placetype":"venue"
},
  "geometry": {"coordinates":[-1.32433,50.91061],"type":"Point"}
}