{
  "type": "Feature",
  "properties": {
    "addr:full":"Stane Street, Five Oaks Billingshurst West Sussex RH14 9AZ",
    "addr:housenumber":"billingshurst",
    "addr:postcode":"rh14 9az",
    "addr:street":"Stane Street;West",
    "iso:country":"GB",
    "sg:address":"Stane Street, Five Oaks",
    "sg:city":"Billingshurst",
    "sg:classifiers":[
        {
            "category":"Home & Garden",
            "subcategory":"Building Materials",
            "type":"Retail Goods"
        },
        {
            "category":"Farming",
            "subcategory":"Livestock Farm",
            "type":"Manufacturing & Wholesale Goods"
        }
    ],
    "sg:phone":"+44 1403 783290",
    "sg:postcode":"RH14 9AZ",
    "sg:province":"West Sussex",
    "sg:tags":[
        "fencing",
        "others"
    ],
    "wof:name":"Five Oaks Farm Sawmills",
    "wof:placetype":"venue"
},
  "geometry": {"coordinates":[-0.462937,51.007576],"type":"Point"}
}