{
  "type": "Feature",
  "properties": {
    "addr:full":"Unit 4, Docks Way Newport Newport NP20 2NS",
    "addr:housenumber":"unit 4",
    "addr:postcode":"np20 2ns",
    "addr:street":"Docks Way",
    "iso:country":"GB",
    "sg:address":"Unit 4, Docks Way",
    "sg:city":"Newport",
    "sg:classifiers":[
        {
            "category":"Shopping",
            "type":"Retail Goods"
        },
        {
            "category":"Retail",
            "subcategory":"Auto Repair",
            "type":"Services"
        }
    ],
    "sg:phone":"+44 1633 244776",
    "sg:postcode":"NP20 2NS",
    "sg:province":"Newport",
    "sg:tags":[
        "modification",
        "garage",
        "part",
        "accessory"
    ],
    "wof:name":"Halfords Superstore",
    "wof:placetype":"venue"
},
  "geometry": {"coordinates":[-2.9985339642,51.5705299377],"type":"Point"}
}