{
  "type": "Feature",
  "properties": {
    "iso:country":"GB",
    "sg:address":"Alexandra Road",
    "sg:city":"Lowestoft",
    "sg:classifiers":[
        {
            "category":"Building & Trades",
            "subcategory":"Equipment Rental",
            "type":"Services"
        },
        {
            "category":"Building & Trades",
            "subcategory":"Construction",
            "type":"Services"
        }
    ],
    "sg:phone":"+44 1502 589291",
    "sg:postcode":"NR32 1PL",
    "sg:province":"Suffolk",
    "sg:tags":[
        "tool",
        "hire"
    ],
    "wof:name":"Lowestoft Tool Hire",
    "wof:placetype":"venue"
},
  "geometry": {"coordinates":[1.752783,52.481068],"type":"Point"}
}