{
  "type": "Feature",
  "properties": {
    "iso:country":"GB",
    "sg:address":"Chalk Pit Stables, Headley Road",
    "sg:city":"Epsom",
    "sg:classifiers":[
        {
            "category":"Personal",
            "subcategory":"Adult",
            "type":"Services"
        }
    ],
    "sg:phone":"+44 1372 278453",
    "sg:postcode":"KT18 6BW",
    "sg:province":"Surrey",
    "sg:tags":[
        "equestrian"
    ],
    "wof:name":"Brooke Sanders",
    "wof:placetype":"venue"
},
  "geometry": {"coordinates":[-0.27897,51.275646],"type":"Point"}
}