{
  "type": "Feature",
  "properties": {
    "addr:full":"Furnival Street Sheffield South Yorkshire S1 1DG",
    "addr:postcode":"s1 1dg",
    "addr:street":"Furnival Street",
    "iso:country":"GB",
    "sg:address":"Furnival Street",
    "sg:city":"Sheffield",
    "sg:classifiers":[
        {
            "category":"Manufacturing",
            "subcategory":"Building Materials",
            "type":"Manufacturing & Wholesale Goods"
        }
    ],
    "sg:phone":"+44 114 273 1191",
    "sg:postcode":"S1 1DG",
    "sg:province":"South Yorkshire",
    "sg:tags":[
        "merchant",
        "builder"
    ],
    "wof:name":"Jewson Ltd.",
    "wof:placetype":"venue"
},
  "geometry": {"coordinates":[-1.4681140184,53.3766212463],"type":"Point"}
}