{
  "type": "Feature",
  "properties": {
    "iso:country":"GB",
    "sg:address":"Top Street, Wing",
    "sg:city":"Oakham",
    "sg:classifiers":[
        {
            "category":"Bars & Pubs",
            "type":"Food & Drink"
        },
        {
            "category":"Community Center",
            "subcategory":"Social",
            "type":"Public Place"
        }
    ],
    "sg:phone":"+44 1572 737634",
    "sg:postcode":"LE15 8SE",
    "sg:province":"Leicestershire",
    "sg:tags":[
        "pubs",
        "house",
        "inn",
        "activity"
    ],
    "wof:name":"NEIL & KAREN HORNSBY",
    "wof:placetype":"venue"
},
  "geometry": {"coordinates":[-0.6850540042,52.6172065735],"type":"Point"}
}