{
  "type": "Feature",
  "properties": {
    "iso:country":"GB",
    "sg:address":"110 Great Brays",
    "sg:city":"Harlow",
    "sg:classifiers":[
        {
            "category":"Farming",
            "subcategory":"Farm",
            "type":"Manufacturing & Wholesale Goods"
        }
    ],
    "sg:phone":"+44 1279 305458",
    "sg:postcode":"CM18 6DP",
    "sg:province":"Essex",
    "sg:tags":[
        "agricultural"
    ],
    "wof:name":"Linda Snell",
    "wof:placetype":"venue"
},
  "geometry": {"coordinates":[0.11508,51.764439],"type":"Point"}
}