{
  "type": "Feature",
  "properties": {
    "addr:full":"140 Broad Hinton Swindon Wiltshire SN4 9PQ",
    "addr:housenumber":"140",
    "addr:postcode":"sn4 9pq",
    "addr:street":"Broad",
    "iso:country":"GB",
    "sg:address":"140 Broad Hinton",
    "sg:city":"Swindon",
    "sg:classifiers":[
        {
            "category":"Autos & Motor Vehicles",
            "subcategory":"Auto Supplies",
            "type":"Retail Goods"
        }
    ],
    "sg:phone":"+44 1793 731173",
    "sg:postcode":"SN4 9PQ",
    "sg:province":"Wiltshire",
    "sg:tags":[
        "electric"
    ],
    "wof:name":"Shaver Kudell Manufacturing Ltd.",
    "wof:placetype":"venue"
},
  "geometry": {"coordinates":[-1.8519500494,51.4890213013],"type":"Point"}
}