{
  "type": "Feature",
  "properties": {
    "addr:full":"Glendale Avenue Newbury Berkshire RG14 6TL",
    "addr:postcode":"rg14 6tl",
    "addr:street":"Glendale Avenue",
    "iso:country":"GB",
    "sg:address":"Glendale Avenue",
    "sg:city":"Newbury",
    "sg:classifiers":[
        {
            "category":"Community Center",
            "type":"Public Place"
        },
        {
            "category":"Organizations",
            "subcategory":"Community Association",
            "type":"Services"
        }
    ],
    "sg:phone":"+44 1635 40376",
    "sg:postcode":"RG14 6TL",
    "sg:province":"Berkshire",
    "sg:tags":[
        "associations",
        "centre",
        "housing",
        "co-operatives",
        "trust",
        "societies"
    ],
    "wof:name":"WASH COMMON COMMUNITY CENTRE",
    "wof:placetype":"venue"
},
  "geometry": {"coordinates":[-1.3490610123,51.3790359497],"type":"Point"}
}