{
  "type": "Feature",
  "properties": {
    "addr:full":"1 Bank Street Worcester Worcestershire WR1 2EP",
    "addr:housenumber":"1",
    "addr:postcode":"wr1 2ep",
    "addr:street":"Bank Street",
    "iso:country":"GB",
    "sg:address":"1 Bank Street",
    "sg:city":"Worcester",
    "sg:classifiers":[
        {
            "category":"Real Estate",
            "subcategory":"Developer",
            "type":"Services"
        }
    ],
    "sg:phone":"+44 1905 610562",
    "sg:postcode":"WR1 2EP",
    "sg:province":"Worcestershire",
    "sg:tags":[
        "property"
    ],
    "wof:name":"Prime Plc",
    "wof:placetype":"venue"
},
  "geometry": {"coordinates":[-2.222274,52.191067],"type":"Point"}
}