{
  "type": "Feature",
  "properties": {
    "addr:full":"98 High Street Galashiels Scottish Borders TD1 1SQ",
    "addr:housenumber":"98",
    "addr:postcode":"td1 1sq",
    "addr:street":"High Street",
    "iso:country":"GB",
    "sg:address":"98 High Street",
    "sg:city":"Galashiels",
    "sg:classifiers":[
        {
            "category":"Taxi",
            "type":"Transportation"
        },
        {
            "category":"Military Area",
            "subcategory":"Air Force Base",
            "type":"Public Place"
        }
    ],
    "sg:phone":"+44 1896 756789",
    "sg:postcode":"TD1 1SQ",
    "sg:province":"Scottish Borders",
    "sg:tags":[
        "mini",
        "hire",
        "private",
        "cab"
    ],
    "wof:name":"Five Star Taxis",
    "wof:placetype":"venue"
},
  "geometry": {"coordinates":[-2.8116528988,55.6186637878],"type":"Point"}
}