{
  "type": "Feature",
  "properties": {
    "iso:country":"GB",
    "sg:address":"Pembroke Ho, Wilson Rd, Longstanton",
    "sg:city":"Cambridge",
    "sg:classifiers":[
        {
            "category":"Bus Charters",
            "type":"Transportation"
        }
    ],
    "sg:phone":"+44 1954 201350",
    "sg:postcode":"CB4 5DA",
    "sg:province":"Cambridgeshire",
    "sg:tags":[
        "coach"
    ],
    "wof:name":"Airport Lynx",
    "wof:placetype":"venue"
},
  "geometry": {"coordinates":[0.04433,52.282825],"type":"Point"}
}