{
  "type": "Feature",
  "properties": {
    "addr:full":"9 Church Street Stourbridge Staffordshire DY8 1LT",
    "addr:housenumber":"9",
    "addr:postcode":"dy8 1lt",
    "addr:street":"Church Street",
    "iso:country":"GB",
    "sg:address":"9 Church Street",
    "sg:city":"Stourbridge",
    "sg:classifiers":[
        {
            "category":"Professional",
            "subcategory":"Art Services",
            "type":"Services"
        }
    ],
    "sg:postcode":"DY8 1LT",
    "sg:province":"Staffordshire",
    "sg:tags":[
        "graphic",
        "designer"
    ],
    "wof:name":"Swinford Graphics Ltd.",
    "wof:placetype":"venue"
},
  "geometry": {"coordinates":[-2.1427400112,52.4545135498],"type":"Point"}
}