{
  "type": "Feature",
  "properties": {
    "iso:country":"GB",
    "sg:address":"High Street, Harston",
    "sg:city":"Cambridge",
    "sg:classifiers":[
        {
            "category":"Autos & Motor Vehicles",
            "subcategory":"Automobile Sales",
            "type":"Retail Goods"
        }
    ],
    "sg:phone":"+44 1223 872872",
    "sg:postcode":"CB2 5QE",
    "sg:province":"Cambridgeshire",
    "sg:tags":[
        "car"
    ],
    "wof:name":"Lancaster Cambridge",
    "wof:placetype":"venue"
},
  "geometry": {"coordinates":[0.0805469975,52.1375236511],"type":"Point"}
}