{
  "type": "Feature",
  "properties": {
    "iso:country":"GB",
    "sg:address":"66 Grosvenor Road",
    "sg:city":"Tunbridge Wells",
    "sg:classifiers":[
        {
            "category":"Food & Beverages",
            "subcategory":"Specialty",
            "type":"Retail Goods"
        }
    ],
    "sg:phone":"+44 1892 543834",
    "sg:postcode":"TN1 2AS",
    "sg:province":"Kent",
    "sg:tags":[
        "product",
        "health"
    ],
    "wof:name":"Natural Life",
    "wof:placetype":"venue"
},
  "geometry": {"coordinates":[0.26244,51.136604],"type":"Point"}
}