{
  "type": "Feature",
  "properties": {
    "iso:country":"GB",
    "sg:address":"38 Kingsgate",
    "sg:city":"Doncaster",
    "sg:classifiers":[
        {
            "category":"Organizations",
            "subcategory":"Non-profit Organization",
            "type":"Services"
        }
    ],
    "sg:phone":"+44 1302 329931",
    "sg:postcode":"DN1 3JU",
    "sg:province":"South Yorkshire",
    "sg:tags":[
        "organisation",
        "voluntary",
        "charity"
    ],
    "wof:name":"N C H Action for Children",
    "wof:placetype":"venue"
},
  "geometry": {"coordinates":[-1.133494,53.521358],"type":"Point"}
}