{
  "type": "Feature",
  "properties": {
    "iso:country":"GB",
    "sg:address":"7 Shibdon Rd",
    "sg:city":"Blaydon On Tyne",
    "sg:classifiers":[
        {
            "category":"Personal",
            "subcategory":"Barber",
            "type":"Services"
        }
    ],
    "sg:phone":"+44 191 440 0339",
    "sg:postcode":"NE21 5AF",
    "sg:province":"Tyne and Wear",
    "sg:tags":[
        "men's",
        "hairdresser"
    ],
    "wof:name":"Darrens Barber Shop",
    "wof:placetype":"venue"
},
  "geometry": {"coordinates":[-1.711951,54.963627],"type":"Point"}
}