{
  "type": "Feature",
  "properties": {
    "iso:country":"GB",
    "sg:address":"93 Kirkstall Road",
    "sg:city":"Leeds",
    "sg:classifiers":[
        {
            "category":"Autos & Motor Vehicles",
            "subcategory":"Auto Supplies",
            "type":"Retail Goods"
        }
    ],
    "sg:phone":"+44 113 242 0059",
    "sg:postcode":"LS3 1JJ",
    "sg:province":"West Yorkshire",
    "sg:tags":[
        "exhaust",
        "absorber",
        "shock"
    ],
    "wof:name":"Kwik-Fit Tyre & Exhaust Centre",
    "wof:placetype":"venue"
},
  "geometry": {"coordinates":[-1.571469,53.802399],"type":"Point"}
}