{
  "type": "Feature",
  "properties": {
    "iso:country":"GB",
    "sg:address":"14 Cathedral Rd",
    "sg:city":"Cardiff",
    "sg:classifiers":[
        {
            "category":"Government",
            "subcategory":"Office",
            "type":"Public Place"
        }
    ],
    "sg:phone":"+44 29 2037 3500",
    "sg:postcode":"CF11 9LJ",
    "sg:province":"Cardiff",
    "sg:tags":[
        "project",
        "gov",
        "community"
    ],
    "wof:name":"Welsh Cancer Intelligence & Surveillance",
    "wof:placetype":"venue"
},
  "geometry": {"coordinates":[-3.189844,51.482563],"type":"Point"}
}