{
  "type": "Feature",
  "properties": {
    "addr:full":"Milton Heights, Milton Abingdon Oxfordshire OX14 4EH",
    "addr:postcode":"ox14 4eh",
    "iso:country":"GB",
    "sg:address":"Milton Heights, Milton",
    "sg:city":"Abingdon",
    "sg:classifiers":[
        {
            "category":"Organizations",
            "subcategory":"Non-profit Organization",
            "type":"Services"
        }
    ],
    "sg:phone":"+44 1235 831686",
    "sg:postcode":"OX14 4EH",
    "sg:province":"Oxfordshire",
    "sg:tags":[
        "organisation",
        "voluntary",
        "charity"
    ],
    "wof:name":"The Home Farm Trust Ltd.",
    "wof:placetype":"venue"
},
  "geometry": {"coordinates":[-1.3002140522,51.6265563965],"type":"Point"}
}