{
  "type": "Feature",
  "properties": {
    "addr:full":"90 Richmond Road Kingston-upon-thames Greater London KT2 5EN",
    "addr:housenumber":"90",
    "addr:postcode":"kt2 5en",
    "addr:street":"Richmond Road",
    "iso:country":"GB",
    "sg:address":"90 Richmond Road",
    "sg:city":"Kingston-upon-thames",
    "sg:classifiers":[
        {
            "category":"Real Estate",
            "subcategory":"Architect",
            "type":"Services"
        }
    ],
    "sg:postcode":"KT2 5EN",
    "sg:province":"Greater London",
    "wof:name":"The R M A Partnership",
    "wof:placetype":"venue"
},
  "geometry": {"coordinates":[-0.301041,51.416012],"type":"Point"}
}