{
  "type": "Feature",
  "properties": {
    "iso:country":"GB",
    "sg:address":"37 St Thomas's Road",
    "sg:city":"Chorley",
    "sg:classifiers":[
        {
            "category":"Professional",
            "subcategory":"Computer Services",
            "type":"Services"
        }
    ],
    "sg:phone":"+44 1257 232719",
    "sg:postcode":"PR7 1HP",
    "sg:province":"Lancashire",
    "sg:tags":[
        "system",
        "software"
    ],
    "wof:name":"Mjh Data Systems Ltd.",
    "wof:placetype":"venue"
},
  "geometry": {"coordinates":[-2.635023,53.653557],"type":"Point"}
}