{
  "type": "Feature",
  "properties": {
    "iso:country":"GB",
    "sg:address":"Acol Farm House, The Street, Acol",
    "sg:city":"Birchington",
    "sg:classifiers":[
        {
            "category":"Farming",
            "subcategory":"Livestock Farm",
            "type":"Manufacturing & Wholesale Goods"
        }
    ],
    "sg:postcode":"CT7 0JA",
    "sg:province":"Kent",
    "sg:tags":[
        "others"
    ],
    "wof:name":"C S Willett & Co. Ltd.",
    "wof:placetype":"venue"
},
  "geometry": {"coordinates":[1.3134319782,51.3587684631],"type":"Point"}
}