{
  "type": "Feature",
  "properties": {
    "iso:country":"GB",
    "sg:address":"Unit 3, 60 Well Street",
    "sg:city":"Paisley",
    "sg:classifiers":[
        {
            "category":"Autos & Motor Vehicles",
            "subcategory":"Automobile Sales",
            "type":"Retail Goods"
        },
        {
            "category":"Professional",
            "subcategory":"Testing Lab",
            "type":"Services"
        }
    ],
    "sg:postcode":"PA1 2QE",
    "sg:province":"Renfrewshire",
    "sg:tags":[
        "car",
        "mot"
    ],
    "wof:name":"Autotech Motor Engineers Ltd.",
    "wof:placetype":"venue"
},
  "geometry": {"coordinates":[-4.4388790131,55.8470497131],"type":"Point"}
}