{
  "type": "Feature",
  "properties": {
    "addr:full":"3 Milton Avenue Blackpool Lancashire FY3 8LY",
    "addr:housenumber":"3",
    "addr:postcode":"fy3 8ly",
    "addr:street":"Milton Avenue",
    "iso:country":"GB",
    "sg:address":"3 Milton Avenue",
    "sg:city":"Blackpool",
    "sg:classifiers":[
        {
            "category":"Shopping",
            "type":"Retail Goods"
        }
    ],
    "sg:phone":"+44 1253 394377",
    "sg:postcode":"FY3 8LY",
    "sg:province":"Lancashire",
    "sg:tags":[
        "merchant"
    ],
    "wof:name":"Milton Seeds",
    "wof:placetype":"venue"
},
  "geometry": {"coordinates":[-3.026751,53.819904],"type":"Point"}
}