{
  "type": "Feature",
  "properties": {
    "iso:country":"GB",
    "sg:address":"2 Ulstan Close, Woldingham",
    "sg:city":"Caterham",
    "sg:classifiers":[
        {
            "category":"Building & Trades",
            "subcategory":"Plumbing",
            "type":"Services"
        }
    ],
    "sg:postcode":"CR3 7EH",
    "sg:province":"Surrey",
    "sg:tags":[
        "central",
        "heating"
    ],
    "wof:name":"K A B",
    "wof:placetype":"venue"
},
  "geometry": {"coordinates":[-0.032654,51.285522],"type":"Point"}
}