{
  "type": "Feature",
  "properties": {
    "iso:country":"GB",
    "sg:address":"Owenford Road",
    "sg:city":"Coventry",
    "sg:classifiers":[
        {
            "category":"Education",
            "subcategory":"School",
            "type":"Public Place"
        },
        {
            "category":"Government",
            "subcategory":"Office",
            "type":"Public Place"
        }
    ],
    "sg:phone":"+44 24 7659 4851",
    "sg:postcode":"CV6 3FS",
    "sg:province":"Warwickshire",
    "sg:tags":[
        "local",
        "authority"
    ],
    "wof:name":"Joseph Cash Primary School",
    "wof:placetype":"venue"
},
  "geometry": {"coordinates":[-1.516084,52.430679],"type":"Point"}
}