{
  "type": "Feature",
  "properties": {
    "addr:full":"South Steading, Sunnyside, Merrycoulter Aboyne Aberdeen City AB12 5GT",
    "addr:postcode":"ab12 5gt",
    "addr:street":"South Steading",
    "iso:country":"GB",
    "sg:address":"South Steading, Sunnyside, Merrycoulter",
    "sg:city":"Aboyne",
    "sg:classifiers":[
        {
            "category":"Real Estate",
            "subcategory":"Architect",
            "type":"Services"
        }
    ],
    "sg:postcode":"AB12 5GT",
    "sg:province":"Aberdeen City",
    "wof:name":"Intergrity Engineering Ltd",
    "wof:placetype":"venue"
},
  "geometry": {"coordinates":[-2.25003,57.057159],"type":"Point"}
}