{
  "type": "Feature",
  "properties": {
    "iso:country":"GB",
    "sg:address":"136 Walsall Road",
    "sg:city":"Willenhall",
    "sg:classifiers":[
        {
            "category":"Autos & Motor Vehicles",
            "subcategory":"Auto Supplies",
            "type":"Retail Goods"
        },
        {
            "category":"Government",
            "subcategory":"Customs House",
            "type":"Public Place"
        }
    ],
    "sg:phone":"+44 1902 635152",
    "sg:postcode":"WV13 2ED",
    "sg:province":"West Midlands",
    "sg:tags":[
        "clearance",
        "component"
    ],
    "wof:name":"R W Bennett Motors",
    "wof:placetype":"venue"
},
  "geometry": {"coordinates":[-2.042684,52.585976],"type":"Point"}
}