{
  "type": "Feature",
  "properties": {
    "addr:full":"46 Spittal Derby Leicestershire DE74 2NQ",
    "addr:housenumber":"46",
    "addr:postcode":"de74 2nq",
    "addr:street":"Spittal",
    "iso:country":"GB",
    "sg:address":"46 Spittal",
    "sg:city":"Derby",
    "sg:classifiers":[
        {
            "category":"Manufacturing",
            "subcategory":"Petroleum Products",
            "type":"Manufacturing & Wholesale Goods"
        }
    ],
    "sg:phone":"+44 1332 812136",
    "sg:postcode":"DE74 2NQ",
    "sg:province":"Leicestershire",
    "sg:tags":[
        "double",
        "glazing"
    ],
    "wof:name":"Melvin J Reid Ltd",
    "wof:placetype":"venue"
},
  "geometry": {"coordinates":[-1.3402620554,52.8457145691],"type":"Point"}
}