{
  "type": "Feature",
  "properties": {
    "addr:full":"Station Road, Langley Slough Berkshire SL3 8BY",
    "addr:postcode":"sl3 8by",
    "addr:street":"Station Road",
    "iso:country":"GB",
    "sg:address":"Station Road, Langley",
    "sg:city":"Slough",
    "sg:classifiers":[
        {
            "category":"Education",
            "subcategory":"University",
            "type":"Public Place"
        },
        {
            "category":"Conference Center",
            "type":"Public Place"
        }
    ],
    "sg:phone":"+44 1753 793285",
    "sg:postcode":"SL3 8BY",
    "sg:province":"Berkshire",
    "sg:tags":[
        "higher"
    ],
    "wof:name":"Langley Hall Conference Centre",
    "wof:placetype":"venue"
},
  "geometry": {"coordinates":[-0.5427939892,51.5074653625],"type":"Point"}
}