{
  "type": "Feature",
  "properties": {
    "iso:country":"GB",
    "sg:address":"33 Newmarket Street",
    "sg:city":"Ayr",
    "sg:classifiers":[
        {
            "category":"Professional",
            "subcategory":"Lawyer & Legal Services",
            "type":"Services"
        }
    ],
    "sg:phone":"+44 1292 265073",
    "sg:postcode":"KA7 1LL",
    "sg:province":"South Ayrshire",
    "sg:tags":[
        "solicitor"
    ],
    "wof:name":"J & A B BOYD",
    "wof:placetype":"venue"
},
  "geometry": {"coordinates":[-4.630361,55.463402],"type":"Point"}
}