{
  "type": "Feature",
  "properties": {
    "addr:full":"2 Well Lane, Chapel Allerton Leeds West Yorkshire LS7 4PQ",
    "addr:housenumber":"2",
    "addr:postcode":"ls7 4pq",
    "addr:street":"Well Lane",
    "iso:country":"GB",
    "sg:address":"2 Well Lane, Chapel Allerton",
    "sg:city":"Leeds",
    "sg:classifiers":[
        {
            "category":"Professional",
            "subcategory":"Advertising",
            "type":"Services"
        }
    ],
    "sg:postcode":"LS7 4PQ",
    "sg:province":"West Yorkshire",
    "sg:tags":[
        "agency"
    ],
    "wof:name":"Paul Whittaker & Associates",
    "wof:placetype":"venue"
},
  "geometry": {"coordinates":[-1.536936,53.829311],"type":"Point"}
}