{
  "type": "Feature",
  "properties": {
    "iso:country":"GB",
    "sg:address":"278 New Rd, Croxley Green",
    "sg:city":"Rickmansworth",
    "sg:classifiers":[
        {
            "category":"Utilities",
            "type":"Services"
        }
    ],
    "sg:phone":"+44 1923 774300",
    "sg:postcode":"WD3 3HH",
    "sg:province":"Hertfordshire",
    "sg:tags":[
        "internet"
    ],
    "wof:name":"C M A Holdings Ltd",
    "wof:placetype":"venue"
},
  "geometry": {"coordinates":[-0.443114996,51.6473312378],"type":"Point"}
}