{
  "type": "Feature",
  "properties": {
    "addr:full":"27 King Street Southall Greater London UB2 4DG",
    "addr:housenumber":"27",
    "addr:postcode":"ub2 4dg",
    "addr:street":"King Street",
    "iso:country":"GB",
    "sg:address":"27 King Street",
    "sg:city":"Southall",
    "sg:classifiers":[
        {
            "category":"Food & Beverages",
            "subcategory":"Meat & Fish",
            "type":"Retail Goods"
        }
    ],
    "sg:phone":"+44 20 8571 7292",
    "sg:postcode":"UB2 4DG",
    "sg:province":"Greater London",
    "sg:tags":[
        "butcher"
    ],
    "wof:name":"Western Meat Shop",
    "wof:placetype":"venue"
},
  "geometry": {"coordinates":[-0.382457,51.501167],"type":"Point"}
}