{
  "type": "Feature",
  "properties": {
    "iso:country":"GB",
    "sg:address":"Worcester Road, Upton Warren",
    "sg:city":"Bromsgrove",
    "sg:classifiers":[
        {
            "category":"Freight",
            "type":"Transportation"
        }
    ],
    "sg:postcode":"B61 7ER",
    "sg:province":"Worcestershire",
    "sg:tags":[
        "haulage",
        "road"
    ],
    "wof:name":"Power Plant Hire Ltd.",
    "wof:placetype":"venue"
},
  "geometry": {"coordinates":[-2.098396,52.305485],"type":"Point"}
}