{
  "type": "Feature",
  "properties": {
    "iso:country":"GB",
    "sg:address":"Dental Laboratory, Rear 44 Beverley Road",
    "sg:city":"Hull",
    "sg:classifiers":[
        {
            "category":"Health Services",
            "subcategory":"Medical Lab",
            "type":"Services"
        }
    ],
    "sg:phone":"+44 1482 217308",
    "sg:postcode":"HU3 1YE",
    "sg:province":"East Riding of Yorkshire",
    "sg:tags":[
        "dental"
    ],
    "wof:name":"Eric W Fisher",
    "wof:placetype":"venue"
},
  "geometry": {"coordinates":[-0.347299993,53.750831604],"type":"Point"}
}