{
  "type": "Feature",
  "properties": {
    "addr:full":"188 Dukes Ride Crowthorne Berkshire RG45 6DS",
    "addr:housenumber":"188",
    "addr:postcode":"rg45 6ds",
    "addr:street":"Dukes Ride",
    "iso:country":"GB",
    "sg:address":"188 Dukes Ride",
    "sg:city":"Crowthorne",
    "sg:classifiers":[
        {
            "category":"Shopping",
            "subcategory":"News",
            "type":"Retail Goods"
        }
    ],
    "sg:phone":"+44 1344 772221",
    "sg:postcode":"RG45 6DS",
    "sg:province":"Berkshire",
    "sg:tags":[
        "newsagent"
    ],
    "wof:name":"Crowthorne Station Post Office",
    "wof:placetype":"venue"
},
  "geometry": {"coordinates":[-0.816956,51.367519],"type":"Point"}
}