{
  "type": "Feature",
  "properties": {
    "iso:country":"GB",
    "sg:address":"50 High Street",
    "sg:city":"Bracknell",
    "sg:classifiers":[
        {
            "category":"Shopping",
            "subcategory":"Baby Store",
            "type":"Retail Goods"
        }
    ],
    "sg:phone":"+44 1344 868776",
    "sg:postcode":"RG12 1LL",
    "sg:province":"Berkshire",
    "sg:tags":[
        "babywear",
        "childrens"
    ],
    "wof:name":"Childrens Stop",
    "wof:placetype":"venue"
},
  "geometry": {"coordinates":[-0.752452,51.41703],"type":"Point"}
}