{
  "type": "Feature",
  "properties": {
    "iso:country":"GB",
    "sg:address":"Flat 2 Dudley House, North Wharf Road",
    "sg:city":"London",
    "sg:classifiers":[
        {
            "category":"Real Estate",
            "subcategory":"Real Estate Agent",
            "type":"Services"
        }
    ],
    "sg:postcode":"W2 1LE",
    "sg:province":"Greater London",
    "wof:name":"Swissdeal Co.",
    "wof:placetype":"venue"
},
  "geometry": {"coordinates":[-0.1768,51.51881],"type":"Point"}
}