{
  "type": "Feature",
  "properties": {
    "addr:full":"22 Alfreda Avenue, Hullbridge Hockley Essex SS5 6LT",
    "addr:housenumber":"22",
    "addr:postcode":"ss5 6lt",
    "addr:street":"Alfreda Avenue;Hockley",
    "iso:country":"GB",
    "sg:address":"22 Alfreda Avenue, Hullbridge",
    "sg:city":"Hockley",
    "sg:classifiers":[
        {
            "category":"Banks & Credit Unions",
            "subcategory":"Financial Services",
            "type":"Services"
        }
    ],
    "sg:phone":"+44 1702 230240",
    "sg:postcode":"SS5 6LT",
    "sg:province":"Essex",
    "sg:tags":[
        "consultant"
    ],
    "wof:name":"Renown Financial Services",
    "wof:placetype":"venue"
},
  "geometry": {"coordinates":[0.6076939702,51.6278114319],"type":"Point"}
}