{
  "type": "Feature",
  "properties": {
    "addr:full":"5 Ashpole Road Braintree Essex CM7 5LW",
    "addr:housenumber":"5",
    "addr:postcode":"cm7 5lw",
    "addr:street":"Ashpole Road",
    "iso:country":"GB",
    "sg:address":"5 Ashpole Road",
    "sg:city":"Braintree",
    "sg:classifiers":[
        {
            "category":"Home & Garden",
            "subcategory":"Furniture",
            "type":"Retail Goods"
        }
    ],
    "sg:phone":"+44 1376 324729",
    "sg:postcode":"CM7 5LW",
    "sg:province":"Essex",
    "wof:name":"Ann Arnold",
    "wof:placetype":"venue"
},
  "geometry": {"coordinates":[0.5673000216,51.9059448242],"type":"Point"}
}