{
  "type": "Feature",
  "properties": {
    "addr:full":"Charlcombe Lodge, Park Lane, Brook Godalming Surrey GU8 5LA",
    "addr:housenumber":"charlcombe",
    "addr:postcode":"gu8 5la",
    "addr:street":"Park Lane",
    "iso:country":"GB",
    "sg:address":"Charlcombe Lodge, Park Lane, Brook",
    "sg:city":"Godalming",
    "sg:classifiers":[
        {
            "category":"Professional",
            "type":"Services"
        },
        {
            "category":"Professional",
            "subcategory":"Employment Agencies",
            "type":"Services"
        }
    ],
    "sg:phone":"+44 1428 685660",
    "sg:postcode":"GU8 5LA",
    "sg:province":"Surrey",
    "sg:tags":[
        "entertainer",
        "entertainment"
    ],
    "sg:website":"http://www.veqtor.co.uk",
    "wof:name":"Quantum Pursuits",
    "wof:placetype":"venue"
},
  "geometry": {"coordinates":[-0.6765499711,51.1315116882],"type":"Point"}
}