{
  "type": "Feature",
  "properties": {
    "addr:full":"23 Stonly Butts Blackburn Lancashire BB1 7JD",
    "addr:housenumber":"23",
    "addr:postcode":"bb1 7jd",
    "addr:street":"Stonly Butts",
    "iso:country":"GB",
    "sg:address":"23 Stonly Butts",
    "sg:city":"Blackburn",
    "sg:classifiers":[
        {
            "category":"Health Services",
            "subcategory":"Clinic",
            "type":"Services"
        }
    ],
    "sg:phone":"+44 1254 278220",
    "sg:postcode":"BB1 7JD",
    "sg:province":"Lancashire",
    "sg:tags":[
        "aromatherapy"
    ],
    "wof:name":"Zodiac",
    "wof:placetype":"venue"
},
  "geometry": {"coordinates":[-2.480399,53.748516],"type":"Point"}
}