{
  "type": "Feature",
  "properties": {
    "addr:full":"Tilsbrook, Duck End Dunmow Essex CM6 3BS",
    "addr:postcode":"cm6 3bs",
    "addr:street":"End Dunmow",
    "iso:country":"GB",
    "sg:address":"Tilsbrook, Duck End",
    "sg:city":"Dunmow",
    "sg:classifiers":[
        {
            "category":"Real Estate",
            "subcategory":"Real Estate Agent",
            "type":"Services"
        }
    ],
    "sg:postcode":"CM6 3BS",
    "sg:province":"Essex",
    "wof:name":"Bran End Properties Limited",
    "wof:placetype":"venue"
},
  "geometry": {"coordinates":[0.4044800103,51.8683891296],"type":"Point"}
}