{
  "type": "Feature",
  "properties": {
    "addr:full":"40 Old Shoreham Road Hove East Sussex BN3 6GA",
    "addr:housenumber":"40",
    "addr:postcode":"bn3 6ga",
    "addr:street":"Old Shoreham Road",
    "iso:country":"GB",
    "sg:address":"40 Old Shoreham Road",
    "sg:city":"Hove",
    "sg:classifiers":[
        {
            "category":"Health Services",
            "subcategory":"Nursing And Care Facility",
            "type":"Services"
        }
    ],
    "sg:phone":"+44 1273 739739",
    "sg:postcode":"BN3 6GA",
    "sg:province":"East Sussex",
    "sg:tags":[
        "home"
    ],
    "wof:name":"Grosvenor Lodge",
    "wof:placetype":"venue"
},
  "geometry": {"coordinates":[-0.161245,50.835773],"type":"Point"}
}