{
  "type": "Feature",
  "properties": {
    "iso:country":"GB",
    "sg:address":"Crowhurst",
    "sg:city":"Battle",
    "sg:classifiers":[
        {
            "category":"Government",
            "subcategory":"Post Office",
            "type":"Public Place"
        }
    ],
    "sg:phone":"+44 1424 830242",
    "sg:postcode":"TN33 9AL",
    "sg:province":"East Sussex",
    "wof:name":"Crowhurst Post Office Stores",
    "wof:placetype":"venue"
},
  "geometry": {"coordinates":[0.499597013,50.8900718689],"type":"Point"}
}