{
  "type": "Feature",
  "properties": {
    "addr:full":"321 Dudley Rd Birmingham West Midlands B18 4HB",
    "addr:housenumber":"321",
    "addr:postcode":"b18 4hb",
    "addr:street":"Dudley Rd",
    "iso:country":"GB",
    "sg:address":"321 Dudley Rd",
    "sg:city":"Birmingham",
    "sg:classifiers":[
        {
            "category":"Fast Food",
            "type":"Food & Drink"
        }
    ],
    "sg:postcode":"B18 4HB",
    "sg:province":"West Midlands",
    "sg:tags":[
        "away",
        "take"
    ],
    "wof:name":"Sun House",
    "wof:placetype":"venue"
},
  "geometry": {"coordinates":[-1.9423840046,52.4866294861],"type":"Point"}
}