{
  "type": "Feature",
  "properties": {
    "addr:full":"Waungoch Farm, Cray Brecon Powys LD3 8TL",
    "addr:housenumber":"cray",
    "addr:postcode":"ld3 8tl",
    "iso:country":"GB",
    "sg:address":"Waungoch Farm, Cray",
    "sg:city":"Brecon",
    "sg:classifiers":[
        {
            "category":"Farming",
            "subcategory":"Livestock Farm",
            "type":"Manufacturing & Wholesale Goods"
        }
    ],
    "sg:postcode":"LD3 8TL",
    "sg:province":"Powys",
    "sg:tags":[
        "others"
    ],
    "wof:name":"M G Stanesby",
    "wof:placetype":"venue"
},
  "geometry": {"coordinates":[-3.6058940887,51.9062767029],"type":"Point"}
}