{
  "type": "Feature",
  "properties": {
    "addr:full":"1194 Neath Road, Neath Swansea Swansea SA6 8JT",
    "addr:housenumber":"1194",
    "addr:postcode":"sa6 8jt",
    "addr:street":"Neath Road",
    "iso:country":"GB",
    "sg:address":"1194 Neath Road, Neath",
    "sg:city":"Swansea",
    "sg:classifiers":[
        {
            "category":"Retail",
            "subcategory":"Auto Repair",
            "type":"Services"
        }
    ],
    "sg:phone":"+44 1792 773636",
    "sg:postcode":"SA6 8JT",
    "sg:province":"Swansea",
    "sg:tags":[
        "body",
        "car"
    ],
    "wof:name":"Autopaints (South Wales) Ltd.",
    "wof:placetype":"venue"
},
  "geometry": {"coordinates":[-3.934838,51.647812],"type":"Point"}
}