{
  "type": "Feature",
  "properties": {
    "addr:full":"8-10 Compton Road Leeds West Yorkshire LS9 6DF",
    "addr:housenumber":"8-10",
    "addr:postcode":"ls9 6df",
    "addr:street":"Compton Road",
    "iso:country":"GB",
    "sg:address":"8-10 Compton Road",
    "sg:city":"Leeds",
    "sg:classifiers":[
        {
            "category":"Home & Garden",
            "subcategory":"Furniture",
            "type":"Retail Goods"
        }
    ],
    "sg:phone":"+44 113 248 4114",
    "sg:postcode":"LS9 6DF",
    "sg:province":"West Yorkshire",
    "sg:tags":[
        "outlet"
    ],
    "wof:name":"Compton Household Furniture",
    "wof:placetype":"venue"
},
  "geometry": {"coordinates":[-1.511914,53.80724],"type":"Point"}
}