{
  "type": "Feature",
  "properties": {
    "iso:country":"GB",
    "sg:address":"2 Bright Street",
    "sg:city":"Blackpool",
    "sg:classifiers":[
        {
            "category":"Travel",
            "subcategory":"Hotels & Motels",
            "type":"Entertainment"
        }
    ],
    "sg:phone":"+44 1253 345828",
    "sg:postcode":"FY4 1BS",
    "sg:province":"Lancashire",
    "sg:tags":[
        "house",
        "guest"
    ],
    "wof:name":"Homely Guest House",
    "wof:placetype":"venue"
},
  "geometry": {"coordinates":[-3.052839,53.797569],"type":"Point"}
}