{
  "type": "Feature",
  "properties": {
    "addr:full":"176-178 Mansell Road Greenford Greater London UB6 9EH",
    "addr:housenumber":"176-178",
    "addr:postcode":"ub6 9eh",
    "addr:street":"Mansell Road",
    "iso:country":"GB",
    "sg:address":"176-178 Mansell Road",
    "sg:city":"Greenford",
    "sg:classifiers":[
        {
            "category":"Retail",
            "subcategory":"Auto Repair",
            "type":"Services"
        }
    ],
    "sg:postcode":"UB6 9EH",
    "sg:province":"Greater London",
    "sg:tags":[
        "modification",
        "garage"
    ],
    "wof:name":"Diagnostic Techniques",
    "wof:placetype":"venue"
},
  "geometry": {"coordinates":[-0.3568829894,51.5281677246],"type":"Point"}
}