{
  "type": "Feature",
  "properties": {
    "iso:country":"GB",
    "sg:address":"University Of Dundee, Perth Road",
    "sg:city":"Dundee",
    "sg:classifiers":[
        {
            "category":"Landmark",
            "subcategory":"Tourist Attraction",
            "type":"Public Place"
        }
    ],
    "sg:phone":"+44 1382 566939",
    "sg:postcode":"DD1 4HN",
    "sg:province":"Dundee City",
    "sg:tags":[
        "interest"
    ],
    "wof:name":"University of Dundee",
    "wof:placetype":"venue"
},
  "geometry": {"coordinates":[-2.9676089287,56.4613761902],"type":"Point"}
}