{
  "type": "Feature",
  "properties": {
    "addr:full":"842 Yeovil Road Slough Berkshire SL1 4JG",
    "addr:housenumber":"842",
    "addr:postcode":"sl1 4jg",
    "addr:street":"Yeovil Road",
    "iso:country":"GB",
    "sg:address":"842 Yeovil Road",
    "sg:city":"Slough",
    "sg:classifiers":[
        {
            "category":"Autos & Motor Vehicles",
            "subcategory":"Auto Supplies",
            "type":"Retail Goods"
        }
    ],
    "sg:postcode":"SL1 4JG",
    "sg:province":"Berkshire",
    "sg:tags":[
        "electronics"
    ],
    "wof:name":"Vehicle Electrical Services",
    "wof:placetype":"venue"
},
  "geometry": {"coordinates":[-0.6399620175,51.5258674622],"type":"Point"}
}