{
  "type": "Feature",
  "properties": {
    "addr:full":"Lothian Road Edinburgh City of Edinburgh EH1 2EA",
    "addr:postcode":"eh1 2ea",
    "addr:street":"Lothian Road",
    "iso:country":"GB",
    "sg:address":"Lothian Road",
    "sg:city":"Edinburgh",
    "sg:classifiers":[
        {
            "category":"Government",
            "subcategory":"Office",
            "type":"Public Place"
        },
        {
            "category":"Arts & Performance",
            "subcategory":"Theater",
            "type":"Entertainment"
        }
    ],
    "sg:phone":"+44 131 228 8616",
    "sg:postcode":"EH1 2EA",
    "sg:province":"City of Edinburgh",
    "sg:tags":[
        "local",
        "concert",
        "theatre",
        "hall"
    ],
    "wof:name":"Usher Hall",
    "wof:placetype":"venue"
},
  "geometry": {"coordinates":[-3.206159,55.947666],"type":"Point"}
}