{
  "type": "Feature",
  "properties": {
    "addr:full":"Blashy Nook Main St, Stainforth Settle North Yorkshire BD24 9PE",
    "addr:postcode":"bd24 9pe",
    "addr:street":"Main St",
    "iso:country":"GB",
    "sg:address":"Blashy Nook Main St, Stainforth",
    "sg:city":"Settle",
    "sg:classifiers":[
        {
            "category":"Building & Trades",
            "subcategory":"Construction",
            "type":"Services"
        }
    ],
    "sg:phone":"+44 1729 825259",
    "sg:postcode":"BD24 9PE",
    "sg:province":"North Yorkshire",
    "sg:tags":[
        "decorator",
        "painter"
    ],
    "wof:name":"Andrew Sharp Decorating & Paint Effects Specialists",
    "wof:placetype":"venue"
},
  "geometry": {"coordinates":[-2.277606,54.069759],"type":"Point"}
}