{
  "type": "Feature",
  "properties": {
    "iso:country":"GB",
    "sg:address":"Ketley Farm, Ketley Road",
    "sg:city":"Brierley Hill",
    "sg:classifiers":[
        {
            "category":"Farming",
            "subcategory":"Dairy Farm",
            "type":"Manufacturing & Wholesale Goods"
        },
        {
            "category":"Farming",
            "subcategory":"Livestock Farm",
            "type":"Manufacturing & Wholesale Goods"
        }
    ],
    "sg:phone":"+44 1384 295248",
    "sg:postcode":"DY6 8DD",
    "sg:province":"Staffordshire",
    "sg:tags":[
        "others"
    ],
    "wof:name":"Norman Lester",
    "wof:placetype":"venue"
},
  "geometry": {"coordinates":[-2.15377,52.498638],"type":"Point"}
}