{
  "type": "Feature",
  "properties": {
    "iso:country":"GB",
    "sg:address":"13 Market Place",
    "sg:city":"Devizes",
    "sg:classifiers":[
        {
            "category":"Organizations",
            "subcategory":"Non-profit Organization",
            "type":"Services"
        }
    ],
    "sg:phone":"+44 1380 727767",
    "sg:postcode":"SN10 1HT",
    "sg:province":"Wiltshire",
    "sg:tags":[
        "organisation",
        "voluntary",
        "charity"
    ],
    "wof:name":"Age Concern Wiltshire",
    "wof:placetype":"venue"
},
  "geometry": {"coordinates":[-1.996638,51.352818],"type":"Point"}
}