{
  "type": "Feature",
  "properties": {
    "iso:country":"GB",
    "sg:address":"2a Amy Road",
    "sg:city":"Oxted",
    "sg:classifiers":[
        {
            "category":"Building & Trades",
            "subcategory":"Plumbing",
            "type":"Services"
        }
    ],
    "sg:phone":"+44 1883 713378",
    "sg:postcode":"RH8 0PX",
    "sg:province":"Surrey",
    "sg:tags":[
        "central",
        "heating"
    ],
    "wof:name":"Blades Heating Ltd.",
    "wof:placetype":"venue"
},
  "geometry": {"coordinates":[-0.003371,51.258041],"type":"Point"}
}