{
  "type": "Feature",
  "properties": {
    "addr:full":"50 Medina Road, Coshay Portsmouth Hampshire PO6 3HD",
    "addr:housenumber":"50",
    "addr:postcode":"hampshire po6 3hd",
    "addr:street":"Medina Road Coshay",
    "iso:country":"GB",
    "sg:address":"50 Medina Road, Coshay",
    "sg:city":"Portsmouth",
    "sg:classifiers":[
        {
            "category":"Food & Beverages",
            "subcategory":"Fruits & Vegetables",
            "type":"Retail Goods"
        }
    ],
    "sg:phone":"+44 23 9238 3195",
    "sg:postcode":"PO6 3HD",
    "sg:province":"Hampshire",
    "sg:tags":[
        "greengrocer"
    ],
    "wof:name":"Jds Ltd.",
    "wof:placetype":"venue"
},
  "geometry": {"coordinates":[-1.07103,50.845455],"type":"Point"}
}