{
  "type": "Feature",
  "properties": {
    "iso:country":"GB",
    "sg:address":"41 Dyke Rd",
    "sg:city":"Brighton",
    "sg:classifiers":[
        {
            "category":"Professional",
            "subcategory":"Employment Agencies",
            "type":"Services"
        }
    ],
    "sg:phone":"+44 1273 748880",
    "sg:postcode":"BN1 3JA",
    "sg:province":"East Sussex",
    "sg:tags":[
        "career",
        "guidance"
    ],
    "wof:name":"New Horizons",
    "wof:placetype":"venue"
},
  "geometry": {"coordinates":[-0.145803,50.825184],"type":"Point"}
}