{
  "type": "Feature",
  "properties": {
    "addr:full":"Front Street, Pelton Fell Chester-le-street Durham DH2 1DB",
    "addr:postcode":"dh2 1db",
    "addr:street":"Front Street;Fell",
    "iso:country":"GB",
    "sg:address":"Front Street, Pelton Fell",
    "sg:city":"Chester-le-street",
    "sg:classifiers":[
        {
            "category":"Bars & Pubs",
            "type":"Food & Drink"
        }
    ],
    "sg:postcode":"DH2 1DB",
    "sg:province":"Durham",
    "sg:tags":[
        "pubs",
        "inn"
    ],
    "wof:name":"J M Pallister",
    "wof:placetype":"venue"
},
  "geometry": {"coordinates":[-1.6087089777,54.872844696],"type":"Point"}
}