{
  "type": "Feature",
  "properties": {
    "addr:full":"2 Fawn Court, The Ryde Hatfield Hertfordshire AL9 5DJ",
    "addr:housenumber":"2",
    "addr:postcode":"al9 5dj",
    "addr:street":"Fawn Court",
    "iso:country":"GB",
    "sg:address":"2 Fawn Court, The Ryde",
    "sg:city":"Hatfield",
    "sg:classifiers":[
        {
            "category":"Manufacturing",
            "subcategory":"Rubber & Plastics",
            "type":"Manufacturing & Wholesale Goods"
        }
    ],
    "sg:postcode":"AL9 5DJ",
    "sg:province":"Hertfordshire",
    "sg:tags":[
        "injection",
        "moulding"
    ],
    "wof:name":"Ten Cate Mouldings (U K) Ltd",
    "wof:placetype":"venue"
},
  "geometry": {"coordinates":[-0.2139260024,51.7699890137],"type":"Point"}
}