{
  "type": "Feature",
  "properties": {
    "addr:full":"4 Dol-y-pentre, Ruabon Wrexham Wrexham LL14 6TF",
    "addr:housenumber":"4",
    "addr:postcode":"ll14 6tf",
    "addr:street":"Dol-Y-Pentre Ruabon",
    "iso:country":"GB",
    "sg:address":"4 Dol-y-pentre, Ruabon",
    "sg:city":"Wrexham",
    "sg:classifiers":[
        {
            "category":"Professional",
            "type":"Services"
        }
    ],
    "sg:phone":"+44 1978 810839",
    "sg:postcode":"LL14 6TF",
    "sg:province":"Wrexham",
    "sg:tags":[
        "entertainer"
    ],
    "wof:name":"Partyfaces",
    "wof:placetype":"venue"
},
  "geometry": {"coordinates":[-3.039114,52.987438],"type":"Point"}
}