{
  "type": "Feature",
  "properties": {
    "addr:full":"6 Bond St Aberdare Neath Port Talbot CF44 7HA",
    "addr:housenumber":"6",
    "addr:postcode":"cf44 7ha",
    "addr:street":"Bond St",
    "iso:country":"GB",
    "sg:address":"6 Bond St",
    "sg:city":"Aberdare",
    "sg:classifiers":[
        {
            "category":"Building & Trades",
            "subcategory":"Construction",
            "type":"Services"
        }
    ],
    "sg:phone":"+44 1685 878894",
    "sg:postcode":"CF44 7HA",
    "sg:province":"Neath Port Talbot",
    "sg:tags":[
        "roofing"
    ],
    "wof:name":"R A Davies",
    "wof:placetype":"venue"
},
  "geometry": {"coordinates":[-3.44256,51.709995],"type":"Point"}
}