{
  "type": "Feature",
  "properties": {
    "addr:full":"Conitor Ho, Denbury Rd Newton Abbot Devon TQ12 6AD",
    "addr:postcode":"tq12 6ad",
    "addr:street":"Denbury Rd",
    "iso:country":"GB",
    "sg:address":"Conitor Ho, Denbury Rd",
    "sg:city":"Newton Abbot",
    "sg:classifiers":[
        {
            "category":"Building & Trades",
            "subcategory":"Construction",
            "type":"Services"
        }
    ],
    "sg:phone":"+44 1626 363535",
    "sg:postcode":"TQ12 6AD",
    "sg:province":"Devon",
    "sg:tags":[
        "builder"
    ],
    "wof:name":"Coteford Construction Ltd",
    "wof:placetype":"venue"
},
  "geometry": {"coordinates":[-3.6076591015,50.5288696289],"type":"Point"}
}