{
  "type": "Feature",
  "properties": {
    "addr:full":"84 Werneth Road Stockport Cheshire SK6 1HR",
    "addr:housenumber":"84",
    "addr:postcode":"sk6 1hr",
    "addr:street":"Werneth Road",
    "iso:country":"GB",
    "sg:address":"84 Werneth Road",
    "sg:city":"Stockport",
    "sg:classifiers":[
        {
            "category":"Home & Garden",
            "subcategory":"Building Materials",
            "type":"Retail Goods"
        }
    ],
    "sg:phone":"+44 161 406 7667",
    "sg:postcode":"SK6 1HR",
    "sg:province":"Cheshire",
    "sg:tags":[
        "garage",
        "door"
    ],
    "wof:name":"G E Doors",
    "wof:placetype":"venue"
},
  "geometry": {"coordinates":[-2.0823829174,53.4233551025],"type":"Point"}
}