{
  "type": "Feature",
  "properties": {
    "addr:full":"Sandall Road Wisbech Cambridgeshire PE13 2PS",
    "addr:postcode":"pe13 2ps",
    "addr:street":"Sandall Road",
    "iso:country":"GB",
    "sg:address":"Sandall Road",
    "sg:city":"Wisbech",
    "sg:classifiers":[
        {
            "category":"Professional",
            "subcategory":"Detective & Security Services",
            "type":"Services"
        }
    ],
    "sg:postcode":"PE13 2PS",
    "sg:province":"Cambridgeshire",
    "wof:name":"Atech Security Services Ltd.",
    "wof:placetype":"venue"
},
  "geometry": {"coordinates":[0.1593009979,52.6557579041],"type":"Point"}
}