{
  "type": "Feature",
  "properties": {
    "iso:country":"GB",
    "sg:address":"187a Altway",
    "sg:city":"Liverpool",
    "sg:classifiers":[
        {
            "category":"Wholesale",
            "subcategory":"Books, Periodicals, & Newspapers",
            "type":"Manufacturing & Wholesale Goods"
        }
    ],
    "sg:postcode":"L10 6LA",
    "sg:province":"Merseyside",
    "sg:tags":[
        "newsagent"
    ],
    "wof:name":"Aintree News",
    "wof:placetype":"venue"
},
  "geometry": {"coordinates":[-2.9360170364,53.4830436707],"type":"Point"}
}