{
  "type": "Feature",
  "properties": {
    "iso:country":"GB",
    "sg:address":"21 Cornwall Rd",
    "sg:city":"Bedford",
    "sg:classifiers":[
        {
            "category":"Manufacturing",
            "subcategory":"Petroleum Products",
            "type":"Manufacturing & Wholesale Goods"
        }
    ],
    "sg:postcode":"MK40 3DH",
    "sg:province":"Bedfordshire",
    "sg:tags":[
        "double",
        "glazing"
    ],
    "wof:name":"M & H Windows",
    "wof:placetype":"venue"
},
  "geometry": {"coordinates":[-0.454697,52.143967],"type":"Point"}
}