{
  "type": "Feature",
  "properties": {
    "iso:country":"GB",
    "sg:address":"Conheath House, Glencaple Road",
    "sg:city":"Dumfries",
    "sg:classifiers":[
        {
            "category":"Farming",
            "subcategory":"Nursery",
            "type":"Manufacturing & Wholesale Goods"
        },
        {
            "category":"Community Center",
            "type":"Public Place"
        }
    ],
    "sg:phone":"+44 1387 770411",
    "sg:postcode":"DG1 4UB",
    "sg:province":"Dumfries and Galloway",
    "sg:tags":[
        "centre"
    ],
    "wof:name":"Conheath Nurseries",
    "wof:placetype":"venue"
},
  "geometry": {"coordinates":[-3.602313,55.058136],"type":"Point"}
}