{
  "type": "Feature",
  "properties": {
    "iso:country":"GB",
    "sg:address":"Unit 3",
    "sg:city":"Ruthin",
    "sg:classifiers":[
        {
            "category":"Personal",
            "subcategory":"Beauty Salon",
            "type":"Services"
        }
    ],
    "sg:phone":"+44 1824 705681",
    "sg:postcode":"LL15 1AF",
    "sg:province":"Denbighshire",
    "sg:tags":[
        "ladies",
        "lady",
        "hairdresser"
    ],
    "wof:name":"Hairs & Graces",
    "wof:placetype":"venue"
},
  "geometry": {"coordinates":[-3.302149,53.119289],"type":"Point"}
}