{
  "type": "Feature",
  "properties": {
    "addr:full":"Telephone House, 21 Ward Road Dundee Dundee City DD1 1ND",
    "addr:housenumber":"21",
    "addr:postcode":"dd1 1nd",
    "addr:street":"Ward Road",
    "iso:country":"GB",
    "sg:address":"Telephone House, 21 Ward Road",
    "sg:city":"Dundee",
    "sg:classifiers":[
        {
            "category":"Organizations",
            "subcategory":"Membership Organization",
            "type":"Services"
        }
    ],
    "sg:postcode":"DD1 1ND",
    "sg:province":"Dundee City",
    "sg:tags":[
        "club"
    ],
    "wof:name":"Disabled  &  Carers Information Centre A",
    "wof:placetype":"venue"
},
  "geometry": {"coordinates":[-2.9765539169,56.4616851807],"type":"Point"}
}