{
  "type": "Feature",
  "properties": {
    "addr:full":"Unit 6 Keirnar Ho, Tut Hill Bury St Edmunds Cambridgeshire IP28 6LF",
    "addr:housenumber":"unit 6",
    "addr:postcode":"ip28 6lf",
    "addr:street":"Keirnar Ho Tut Hill",
    "iso:country":"GB",
    "sg:address":"Unit 6 Keirnar Ho, Tut Hill",
    "sg:city":"Bury St Edmunds",
    "sg:classifiers":[
        {
            "category":"Retail",
            "subcategory":"Auto Repair",
            "type":"Services"
        }
    ],
    "sg:phone":"+44 1284 760779",
    "sg:postcode":"IP28 6LF",
    "sg:province":"Cambridgeshire",
    "sg:tags":[
        "modification",
        "garage"
    ],
    "wof:name":"C C Garage Services",
    "wof:placetype":"venue"
},
  "geometry": {"coordinates":[0.68644,52.270168],"type":"Point"}
}