{
  "type": "Feature",
  "properties": {
    "addr:full":"Unit 8 Ryedale Court, The Village, Haxby York North Yorkshire YO32 3SA",
    "addr:housenumber":"unit 8",
    "addr:postcode":"yo32 3sa",
    "addr:street":"Ryedale Court The Village",
    "iso:country":"GB",
    "sg:address":"Unit 8 Ryedale Court, The Village, Haxby",
    "sg:city":"York",
    "sg:classifiers":[
        {
            "category":"Cinema",
            "subcategory":"Movie Rental",
            "type":"Entertainment"
        }
    ],
    "sg:phone":"+44 1904 750268",
    "sg:postcode":"YO32 3SA",
    "sg:province":"North Yorkshire",
    "sg:tags":[
        "video",
        "library"
    ],
    "wof:name":"Choices Video",
    "wof:placetype":"venue"
},
  "geometry": {"coordinates":[-1.0740089417,54.0157546997],"type":"Point"}
}