{
  "type": "Feature",
  "properties": {
    "iso:country":"GB",
    "sg:address":"70 Kingslea Park",
    "sg:city":"East Cowes",
    "sg:classifiers":[
        {
            "category":"Shopping",
            "subcategory":"Photographic Equipment",
            "type":"Retail Goods"
        }
    ],
    "sg:phone":"+44 1983 299031",
    "sg:postcode":"PO32 6JN",
    "sg:province":"Isle of Wight",
    "wof:name":"Fabulous Wedding Photography",
    "wof:placetype":"venue"
},
  "geometry": {"coordinates":[-1.283811,50.747356],"type":"Point"}
}