{
  "type": "Feature",
  "properties": {
    "addr:full":"31a Hill Avenue Amersham Buckinghamshire HP6 5BX",
    "addr:housenumber":"31a",
    "addr:postcode":"hp6 5bx",
    "addr:street":"Hill Avenue Amersham",
    "iso:country":"GB",
    "sg:address":"31a Hill Avenue",
    "sg:city":"Amersham",
    "sg:classifiers":[
        {
            "category":"Communications",
            "type":"Services"
        }
    ],
    "sg:phone":"+44 1494 729777",
    "sg:postcode":"HP6 5BX",
    "sg:province":"Buckinghamshire",
    "sg:tags":[
        "broadcasting",
        "audio-visual"
    ],
    "wof:name":"Goldhawk Media Ltd.",
    "wof:placetype":"venue"
},
  "geometry": {"coordinates":[-0.6074,51.675655],"type":"Point"}
}