{
  "type": "Feature",
  "properties": {
    "addr:full":"Hanning Rd, Higher Horton Ilminster Somerset TA19 9QH",
    "addr:postcode":"ta19 9qh",
    "addr:street":"Hanning Rd",
    "iso:country":"GB",
    "sg:address":"Hanning Rd, Higher Horton",
    "sg:city":"Ilminster",
    "sg:classifiers":[
        {
            "category":"Autos & Motor Vehicles",
            "subcategory":"Fuel & Gas Station",
            "type":"Retail Goods"
        }
    ],
    "sg:postcode":"TA19 9QH",
    "sg:province":"Somerset",
    "sg:tags":[
        "petrol",
        "filling"
    ],
    "wof:name":"Bushby,E J,",
    "wof:placetype":"venue"
},
  "geometry": {"coordinates":[-2.9647939205,50.9292640686],"type":"Point"}
}