{
  "type": "Feature",
  "properties": {
    "addr:full":"Rydal Villa, High Street, Uppermill Oldham Lancashire OL3 6BT",
    "addr:postcode":"ol3 6bt",
    "addr:street":"High Street",
    "iso:country":"GB",
    "sg:address":"Rydal Villa, High Street, Uppermill",
    "sg:city":"Oldham",
    "sg:classifiers":[
        {
            "category":"Professional",
            "subcategory":"Management & Consulting",
            "type":"Services"
        }
    ],
    "sg:postcode":"OL3 6BT",
    "sg:province":"Lancashire",
    "sg:tags":[
        "marketing",
        "consultant"
    ],
    "wof:name":"Sanderson Associates Ltd.",
    "wof:placetype":"venue"
},
  "geometry": {"coordinates":[-2.006526,53.547478],"type":"Point"}
}