{
  "type": "Feature",
  "properties": {
    "iso:country":"GB",
    "sg:address":"4 Snaresbrook, Station App",
    "sg:city":"London",
    "sg:classifiers":[
        {
            "category":"Taxi",
            "type":"Transportation"
        }
    ],
    "sg:phone":"+44 20 8989 5151",
    "sg:postcode":"E11 2QE",
    "sg:province":"Greater London",
    "sg:tags":[
        "mini",
        "cab"
    ],
    "wof:name":"Snaresbrook Cars",
    "wof:placetype":"venue"
},
  "geometry": {"coordinates":[0.02879,51.576031],"type":"Point"}
}