{
  "type": "Feature",
  "properties": {
    "iso:country":"GB",
    "sg:address":"Unit 15 Crofts Ct, Butts Clo",
    "sg:city":"Thornton-cleveleys",
    "sg:classifiers":[
        {
            "category":"Bakery",
            "type":"Food & Drink"
        }
    ],
    "sg:postcode":"FY5 4JX",
    "sg:province":"Lancashire",
    "sg:tags":[
        "cake",
        "maker"
    ],
    "wof:name":"Bradshaw,Celia,",
    "wof:placetype":"venue"
},
  "geometry": {"coordinates":[-3.001364,53.870968],"type":"Point"}
}