{
  "type": "Feature",
  "properties": {
    "iso:country":"GB",
    "sg:address":"Pexhill Road, Siddington",
    "sg:city":"Macclesfield",
    "sg:classifiers":[
        {
            "category":"Community Center",
            "type":"Public Place"
        },
        {
            "category":"Organizations",
            "subcategory":"Non-profit Organization",
            "type":"Services"
        }
    ],
    "sg:phone":"+44 1260 224518",
    "sg:postcode":"SK11 9JN",
    "sg:province":"Cheshire",
    "sg:tags":[
        "conference",
        "room",
        "centre",
        "organisation",
        "charitable",
        "charity"
    ],
    "wof:name":"Thorneycroft Hall",
    "wof:placetype":"venue"
},
  "geometry": {"coordinates":[-2.168595,53.253811],"type":"Point"}
}