{
  "type": "Feature",
  "properties": {
    "iso:country":"GB",
    "sg:address":"23 Ellis Close, Cottenham",
    "sg:city":"Cambridge",
    "sg:classifiers":[
        {
            "category":"Professional",
            "subcategory":"Management & Consulting",
            "type":"Services"
        },
        {
            "category":"Social Services",
            "subcategory":"Job Training",
            "type":"Services"
        }
    ],
    "sg:phone":"+44 1954 252382",
    "sg:postcode":"CB4 8UN",
    "sg:province":"Cambridgeshire",
    "sg:tags":[
        "consultant",
        "drawing",
        "business",
        "draughtsman"
    ],
    "wof:name":"Synergy Draughting Services",
    "wof:placetype":"venue"
},
  "geometry": {"coordinates":[0.119002,52.282497],"type":"Point"}
}