{
  "type": "Feature",
  "properties": {
    "addr:full":"Field Lane Batley West Yorkshire WF17 5AG",
    "addr:postcode":"wf17 5ag",
    "addr:street":"Field Lane",
    "iso:country":"GB",
    "sg:address":"Field Lane",
    "sg:city":"Batley",
    "sg:classifiers":[
        {
            "category":"Communications",
            "subcategory":"Television Station",
            "type":"Services"
        }
    ],
    "sg:phone":"+44 1924 444489",
    "sg:postcode":"WF17 5AG",
    "sg:province":"West Yorkshire",
    "sg:tags":[
        "tv",
        "mnfr",
        "cable"
    ],
    "wof:name":"D C E Telecom",
    "wof:placetype":"venue"
},
  "geometry": {"coordinates":[-1.6288189888,53.7112922668],"type":"Point"}
}