{
  "type": "Feature",
  "properties": {
    "addr:full":"53 Lockesfield Place London Greater London E14 3AJ",
    "addr:housenumber":"53",
    "addr:postcode":"e14 3aj",
    "addr:street":"Lockesfield Place",
    "iso:country":"GB",
    "sg:address":"53 Lockesfield Place",
    "sg:city":"London",
    "sg:classifiers":[
        {
            "category":"Professional",
            "subcategory":"Computer Services",
            "type":"Services"
        }
    ],
    "sg:phone":"+44 20 7538 0863",
    "sg:postcode":"E14 3AJ",
    "sg:province":"Greater London",
    "sg:tags":[
        "system",
        "software"
    ],
    "wof:name":"Another Corporation Ltd.",
    "wof:placetype":"venue"
},
  "geometry": {"coordinates":[-0.0142390002,51.487739563],"type":"Point"}
}