{
  "type": "Feature",
  "properties": {
    "addr:full":"Milton Lane Dartmouth Devon TQ6 9HW",
    "addr:postcode":"tq6 9hw",
    "addr:street":"Milton Lane",
    "iso:country":"GB",
    "sg:address":"Milton Lane",
    "sg:city":"Dartmouth",
    "sg:classifiers":[
        {
            "category":"Education",
            "subcategory":"School",
            "type":"Public Place"
        },
        {
            "category":"Government",
            "subcategory":"Office",
            "type":"Public Place"
        }
    ],
    "sg:phone":"+44 1803 832495",
    "sg:postcode":"TQ6 9HW",
    "sg:province":"Devon",
    "sg:tags":[
        "local",
        "authority"
    ],
    "wof:name":"St John the Baptist R C Primary School",
    "wof:placetype":"venue"
},
  "geometry": {"coordinates":[-3.596154,50.347191],"type":"Point"}
}