{
  "type": "Feature",
  "properties": {
    "addr:full":"28 Shortwood Av Staines Berkshire TW18 4JL",
    "addr:housenumber":"28",
    "addr:postcode":"tw18 4jl",
    "addr:street":"Shortwood Av Staines",
    "iso:country":"GB",
    "sg:address":"28 Shortwood Av",
    "sg:city":"Staines",
    "sg:classifiers":[
        {
            "category":"Building & Trades",
            "subcategory":"Construction",
            "type":"Services"
        }
    ],
    "sg:phone":"+44 1784 458501",
    "sg:postcode":"TW18 4JL",
    "sg:province":"Berkshire",
    "sg:tags":[
        "decorator",
        "painter"
    ],
    "wof:name":"David Germany",
    "wof:placetype":"venue"
},
  "geometry": {"coordinates":[-0.49195,51.437214],"type":"Point"}
}