{
  "type": "Feature",
  "properties": {
    "addr:full":"9 Royal Crescent Mews Brighton East Sussex BN2 1AW",
    "addr:housenumber":"9",
    "addr:postcode":"bn2 1aw",
    "addr:street":"Royal Crescent Mews",
    "iso:country":"GB",
    "sg:address":"9 Royal Crescent Mews",
    "sg:city":"Brighton",
    "sg:classifiers":[
        {
            "category":"Professional",
            "subcategory":"Computer Services",
            "type":"Services"
        }
    ],
    "sg:phone":"+44 1273 602610",
    "sg:postcode":"BN2 1AW",
    "sg:province":"East Sussex",
    "sg:tags":[
        "system",
        "software"
    ],
    "wof:name":"1st Language Translation & Interpreting Ltd.",
    "wof:placetype":"venue"
},
  "geometry": {"coordinates":[-0.124424,50.818554],"type":"Point"}
}