{
  "type": "Feature",
  "properties": {
    "addr:full":"Chelsea Harbour Design Centre, Chelsea Harbour London Greater London SW10 0XE",
    "addr:postcode":"sw10 0xe",
    "iso:country":"GB",
    "sg:address":"Chelsea Harbour Design Centre, Chelsea Harbour",
    "sg:city":"London",
    "sg:classifiers":[
        {
            "category":"Professional",
            "subcategory":"Management & Consulting",
            "type":"Services"
        }
    ],
    "sg:phone":"+44 20 7823 3502",
    "sg:postcode":"SW10 0XE",
    "sg:province":"Greater London",
    "sg:tags":[
        "marketing",
        "consultant"
    ],
    "wof:name":"Preuss Bros Ltd.",
    "wof:placetype":"venue"
},
  "geometry": {"coordinates":[-0.1829299927,51.4760093689],"type":"Point"}
}