{
  "type": "Feature",
  "properties": {
    "addr:full":"1-2 Wellesley Parade, Wellesley Road Twickenham Greater London TW2 5SQ",
    "addr:housenumber":"1-2",
    "addr:postcode":"tw2 5sq",
    "addr:street":"Wellesley Parade Wellesley Road",
    "iso:country":"GB",
    "sg:address":"1-2 Wellesley Parade, Wellesley Road",
    "sg:city":"Twickenham",
    "sg:classifiers":[
        {
            "category":"Shopping",
            "subcategory":"News",
            "type":"Retail Goods"
        },
        {
            "category":"Food & Beverages",
            "subcategory":"Groceries & Convenience Stores",
            "type":"Retail Goods"
        }
    ],
    "sg:phone":"+44 20 8894 5762",
    "sg:postcode":"TW2 5SQ",
    "sg:province":"Greater London",
    "sg:tags":[
        "newsagent"
    ],
    "wof:name":"T & M Smith",
    "wof:placetype":"venue"
},
  "geometry": {"coordinates":[-0.348272,51.439064],"type":"Point"}
}