{
  "type": "Feature",
  "properties": {
    "iso:country":"GB",
    "sg:address":"Eileen Anderson Court, Johnson's Place",
    "sg:city":"Westminster",
    "sg:classifiers":[
        {
            "category":"Health Services",
            "subcategory":"Nursing And Care Facility",
            "type":"Services"
        }
    ],
    "sg:phone":"+44 20 7821 5307",
    "sg:postcode":"SW1V 3EZ",
    "sg:province":"Greater London",
    "sg:tags":[
        "home"
    ],
    "wof:name":"The Bethnal Green & East London Housing Association Ltd",
    "wof:placetype":"venue"
},
  "geometry": {"coordinates":[-0.13947,51.486752],"type":"Point"}
}