{
  "type": "Feature",
  "properties": {
    "addr:full":"38 Broad Street Teddington Greater London TW11 8QY",
    "addr:housenumber":"38",
    "addr:postcode":"tw11 8qy",
    "addr:street":"Broad Street",
    "iso:country":"GB",
    "sg:address":"38 Broad Street",
    "sg:city":"Teddington",
    "sg:classifiers":[
        {
            "category":"Fast Food",
            "type":"Food & Drink"
        }
    ],
    "sg:phone":"+44 20 8977 0928",
    "sg:postcode":"TW11 8QY",
    "sg:province":"Greater London",
    "sg:tags":[
        "away",
        "meal",
        "outlet",
        "take"
    ],
    "wof:name":"New China Express",
    "wof:placetype":"venue"
},
  "geometry": {"coordinates":[-0.3378069997,51.4259681702],"type":"Point"}
}