{
  "type": "Feature",
  "properties": {
    "iso:country":"GB",
    "sg:address":"Marshalls Court, Marshalls Road",
    "sg:city":"Sutton",
    "sg:classifiers":[
        {
            "category":"Manufacturing",
            "subcategory":"Tools & Machinery",
            "type":"Manufacturing & Wholesale Goods"
        },
        {
            "category":"Insurance",
            "subcategory":"Insurance Agent",
            "type":"Services"
        }
    ],
    "sg:phone":"+44 20 8652 1313",
    "sg:postcode":"SM1 4DU",
    "sg:province":"Surrey",
    "sg:tags":[
        "society",
        "friendly"
    ],
    "wof:name":"Firstassist Services Ltd.",
    "wof:placetype":"venue"
},
  "geometry": {"coordinates":[-0.194278,51.367695],"type":"Point"}
}