{
  "type": "Feature",
  "properties": {
    "addr:full":"68 Greenwood, Clayton Grn Preston Lancashire PR5 8JU",
    "addr:housenumber":"68",
    "addr:postcode":"pr5 8ju",
    "addr:street":"Greenwood Clayton Grn",
    "iso:country":"GB",
    "sg:address":"68 Greenwood, Clayton Grn",
    "sg:city":"Preston",
    "sg:classifiers":[
        {
            "category":"Home & Garden",
            "subcategory":"Household Appliances",
            "type":"Retail Goods"
        }
    ],
    "sg:postcode":"PR5 8JU",
    "sg:province":"Lancashire",
    "sg:tags":[
        "gas"
    ],
    "wof:name":"G  A  S",
    "wof:placetype":"venue"
},
  "geometry": {"coordinates":[-2.6447839737,53.711063385],"type":"Point"}
}