{
  "type": "Feature",
  "properties": {
    "iso:country":"GB",
    "sg:address":"26 East Park",
    "sg:city":"Sawbridgeworth",
    "sg:classifiers":[
        {
            "category":"Retail",
            "subcategory":"Repair Shop",
            "type":"Services"
        }
    ],
    "sg:phone":"+44 1279 722416",
    "sg:postcode":"CM21 9EX",
    "sg:province":"Essex",
    "sg:tags":[
        "clocks",
        "watch"
    ],
    "wof:name":"Church & Turret Clocks",
    "wof:placetype":"venue"
},
  "geometry": {"coordinates":[0.147652,51.806774],"type":"Point"}
}