{
  "type": "Feature",
  "properties": {
    "addr:full":"82 Woodchurch Lane Birkenhead Merseyside CH42 9PD",
    "addr:housenumber":"82",
    "addr:postcode":"ch42 9pd",
    "addr:street":"Woodchurch Lane",
    "iso:country":"GB",
    "sg:address":"82 Woodchurch Lane",
    "sg:city":"Birkenhead",
    "sg:classifiers":[
        {
            "category":"Home & Garden",
            "subcategory":"Household Appliances",
            "type":"Retail Goods"
        }
    ],
    "sg:phone":"+44 151 608 0189",
    "sg:postcode":"CH42 9PD",
    "sg:province":"Merseyside",
    "sg:tags":[
        "domestic",
        "centre"
    ],
    "wof:name":"N H M Ood",
    "wof:placetype":"venue"
},
  "geometry": {"coordinates":[-3.038233,53.374084],"type":"Point"}
}