{
  "type": "Feature",
  "properties": {
    "iso:country":"GB",
    "sg:address":"24 Mill Street",
    "sg:city":"Bedford",
    "sg:classifiers":[
        {
            "category":"Home & Garden",
            "subcategory":"Furniture",
            "type":"Retail Goods"
        }
    ],
    "sg:phone":"+44 1234 365048",
    "sg:postcode":"MK40 3HD",
    "sg:province":"Bedfordshire",
    "wof:name":"Amaroso Sarro",
    "wof:placetype":"venue"
},
  "geometry": {"coordinates":[-0.465229,52.137089],"type":"Point"}
}