{
  "type": "Feature",
  "properties": {
    "iso:country":"GB",
    "sg:address":"Jamage Indust Est, Pit La",
    "sg:city":"Stoke On Trent",
    "sg:classifiers":[
        {
            "category":"Utilities",
            "subcategory":"Fuel Oil & Lpg",
            "type":"Services"
        }
    ],
    "sg:phone":"+44 1782 783750",
    "sg:postcode":"ST7 1UH",
    "sg:province":"Cheshire",
    "sg:tags":[
        "coal",
        "smokeless"
    ],
    "wof:name":"CPL British Fuels",
    "wof:placetype":"venue"
},
  "geometry": {"coordinates":[-2.2616300583,53.0722007751],"type":"Point"}
}