{
  "type": "Feature",
  "properties": {
    "iso:country":"GB",
    "sg:address":"3 Fishmarket Quay, Swansea Marina",
    "sg:city":"Swansea",
    "sg:classifiers":[
        {
            "category":"Fast Food",
            "type":"Food & Drink"
        },
        {
            "category":"Restaurant",
            "type":"Food & Drink"
        }
    ],
    "sg:phone":"+44 1792 456285",
    "sg:postcode":"SA1 1UN",
    "sg:province":"Neath Port Talbot",
    "sg:tags":[
        "away",
        "take"
    ],
    "wof:name":"Gallini's",
    "wof:placetype":"venue"
},
  "geometry": {"coordinates":[-3.940929,51.623154],"type":"Point"}
}