{
  "type": "Feature",
  "properties": {
    "addr:full":"120 High Street Cowes Isle of Wight PO31 7AX",
    "addr:housenumber":"120",
    "addr:postcode":"po31 7ax",
    "addr:street":"High Street",
    "iso:country":"GB",
    "sg:address":"120 High Street",
    "sg:city":"Cowes",
    "sg:classifiers":[
        {
            "category":"Arena",
            "subcategory":"Stadium",
            "type":"Entertainment"
        },
        {
            "category":"Arena",
            "subcategory":"Sports Club",
            "type":"Entertainment"
        }
    ],
    "sg:phone":"+44 1983 296060",
    "sg:postcode":"PO31 7AX",
    "sg:province":"Isle of Wight",
    "sg:tags":[
        "ground"
    ],
    "wof:name":"World Cruising Club",
    "wof:placetype":"venue"
},
  "geometry": {"coordinates":[-1.297801,50.761639],"type":"Point"}
}