{
  "type": "Feature",
  "properties": {
    "addr:full":"187 Rookery Rd, Handsworth Birmingham West Midlands B21 9QZ",
    "addr:housenumber":"187",
    "addr:postcode":"b21 9qz",
    "addr:street":"Rookery Rd",
    "iso:country":"GB",
    "sg:address":"187 Rookery Rd, Handsworth",
    "sg:city":"Birmingham",
    "sg:classifiers":[
        {
            "category":"Manufacturing",
            "subcategory":"Metals",
            "type":"Manufacturing & Wholesale Goods"
        }
    ],
    "sg:phone":"+44 121 554 1703",
    "sg:postcode":"B21 9QZ",
    "sg:province":"West Midlands",
    "sg:tags":[
        "steel",
        "fabricator",
        "erectors"
    ],
    "wof:name":"Fab Gates & Grills",
    "wof:placetype":"venue"
},
  "geometry": {"coordinates":[-1.9400160313,52.5106697083],"type":"Point"}
}