{
  "type": "Feature",
  "properties": {
    "iso:country":"GB",
    "sg:address":"11 Thistle Place",
    "sg:city":"Aberdeen",
    "sg:classifiers":[
        {
            "category":"Professional",
            "subcategory":"Accounting & Tax Preparation",
            "type":"Services"
        }
    ],
    "sg:phone":"+44 1224 634111",
    "sg:postcode":"AB10 1UZ",
    "sg:province":"Aberdeen City",
    "sg:tags":[
        "accountant"
    ],
    "wof:name":"Miller McWilliam",
    "wof:placetype":"venue"
},
  "geometry": {"coordinates":[-2.112517,57.143223],"type":"Point"}
}