{
  "type": "Feature",
  "properties": {
    "addr:full":"344 Cricklewood La, Childs Hill London Greater London NW2 2QH",
    "addr:housenumber":"344",
    "addr:postcode":"nw2 2qh",
    "addr:street":"Cricklewood La Childs",
    "iso:country":"GB",
    "sg:address":"344 Cricklewood La, Childs Hill",
    "sg:city":"London",
    "sg:classifiers":[
        {
            "category":"Real Estate",
            "subcategory":"Architect",
            "type":"Services"
        }
    ],
    "sg:postcode":"NW2 2QH",
    "sg:province":"Greater London",
    "wof:name":"Onyxgold Ltd",
    "wof:placetype":"venue"
},
  "geometry": {"coordinates":[-0.199064,51.562859],"type":"Point"}
}