{
  "type": "Feature",
  "properties": {
    "iso:country":"GB",
    "sg:address":"Clwyd Avenue",
    "sg:city":"Denbigh",
    "sg:classifiers":[
        {
            "category":"Community Center",
            "type":"Public Place"
        },
        {
            "category":"Government",
            "subcategory":"Office",
            "type":"Public Place"
        }
    ],
    "sg:phone":"+44 1745 816311",
    "sg:postcode":"LL16 3HB",
    "sg:province":"Conwy",
    "sg:tags":[
        "recreation",
        "local",
        "leisure",
        "centre"
    ],
    "wof:name":"Denbigh Leisure Centre",
    "wof:placetype":"venue"
},
  "geometry": {"coordinates":[-3.407608,53.184891],"type":"Point"}
}