{
  "type": "Feature",
  "properties": {
    "addr:full":"18-20 Ash Lane, Rustington Littlehampton West Sussex BN16 3BZ",
    "addr:housenumber":"18-20",
    "addr:postcode":"bn16 3bz",
    "addr:street":"Ash Lane",
    "iso:country":"GB",
    "sg:address":"18-20 Ash Lane, Rustington",
    "sg:city":"Littlehampton",
    "sg:classifiers":[
        {
            "category":"Banks & Credit Unions",
            "subcategory":"Financial Services",
            "type":"Services"
        }
    ],
    "sg:postcode":"BN16 3BZ",
    "sg:province":"West Sussex",
    "sg:tags":[
        "consultant"
    ],
    "wof:name":"Richard Hobden",
    "wof:placetype":"venue"
},
  "geometry": {"coordinates":[-0.5046849847,50.8109741211],"type":"Point"}
}