{
  "type": "Feature",
  "properties": {
    "iso:country":"GB",
    "sg:address":"4 Majestic Parade, Sandgate Rd",
    "sg:city":"Folkestone",
    "sg:classifiers":[
        {
            "category":"Insurance",
            "subcategory":"Insurance Agent",
            "type":"Services"
        }
    ],
    "sg:phone":"+44 1303 850706",
    "sg:postcode":"CT20 2BZ",
    "sg:province":"Kent",
    "wof:name":"Hill House Hammond Ltd",
    "wof:placetype":"venue"
},
  "geometry": {"coordinates":[1.177945,51.084431],"type":"Point"}
}