{
  "type": "Feature",
  "properties": {
    "addr:full":"27 North Bridge Edinburgh City of Edinburgh EH1 1SB",
    "addr:housenumber":"27",
    "addr:postcode":"eh1 1sb",
    "addr:street":"North Bridge Edinburgh",
    "iso:country":"GB",
    "sg:address":"27 North Bridge",
    "sg:city":"Edinburgh",
    "sg:classifiers":[
        {
            "category":"Home & Garden",
            "subcategory":"Household Appliances",
            "type":"Retail Goods"
        }
    ],
    "sg:phone":"+44 131 556 0301",
    "sg:postcode":"EH1 1SB",
    "sg:province":"City of Edinburgh",
    "sg:tags":[
        "electrical",
        "domestic"
    ],
    "wof:name":"Tandy",
    "wof:placetype":"venue"
},
  "geometry": {"coordinates":[-3.187514,55.950542],"type":"Point"}
}