{
  "type": "Feature",
  "properties": {
    "addr:full":"Grange Farm, Main Street, Thistleton Oakham Leicestershire LE15 7RE",
    "addr:postcode":"le15 7re",
    "addr:street":"Main Street",
    "iso:country":"GB",
    "sg:address":"Grange Farm, Main Street, Thistleton",
    "sg:city":"Oakham",
    "sg:classifiers":[
        {
            "category":"Home & Garden",
            "subcategory":"Garden Supply",
            "type":"Retail Goods"
        }
    ],
    "sg:phone":"+44 1572 767658",
    "sg:postcode":"LE15 7RE",
    "sg:province":"Leicestershire",
    "sg:tags":[
        "nursery",
        "centre"
    ],
    "wof:name":"The Herb Nursery",
    "wof:placetype":"venue"
},
  "geometry": {"coordinates":[-0.649846,52.751144],"type":"Point"}
}