{
  "type": "Feature",
  "properties": {
    "iso:country":"GB",
    "sg:address":"Westergate House, Denmans Lane, Fontwell",
    "sg:city":"Arundel",
    "sg:classifiers":[
        {
            "category":"Health Services",
            "subcategory":"Nursing And Care Facility",
            "type":"Services"
        }
    ],
    "sg:phone":"+44 1243 544055",
    "sg:postcode":"BN18 0SU",
    "sg:province":"West Sussex",
    "sg:tags":[
        "home"
    ],
    "wof:name":"Westergate Nursing Home",
    "wof:placetype":"venue"
},
  "geometry": {"coordinates":[-0.648239,50.854923],"type":"Point"}
}