{
  "type": "Feature",
  "properties": {
    "addr:full":"Morian House, Bridgend Business Centre, Bennett St Bridgend Bridgend CF31 3SH",
    "addr:postcode":"cf31 3sh",
    "addr:street":"Bridgend;Bennett St",
    "iso:country":"GB",
    "sg:address":"Morian House, Bridgend Business Centre, Bennett St",
    "sg:city":"Bridgend",
    "sg:classifiers":[
        {
            "category":"Manufacturing",
            "subcategory":"Tools & Machinery",
            "type":"Manufacturing & Wholesale Goods"
        }
    ],
    "sg:phone":"+44 1656 646655",
    "sg:postcode":"CF31 3SH",
    "sg:province":"Bridgend",
    "sg:tags":[
        "society",
        "friendly"
    ],
    "wof:name":"Friends Provident",
    "wof:placetype":"venue"
},
  "geometry": {"coordinates":[-3.5399138927,51.5031890869],"type":"Point"}
}