{
  "type": "Feature",
  "properties": {
    "addr:full":"Marchmont Court Addison Gardens London Greater London W14 0EU",
    "addr:postcode":"w14 0eu",
    "addr:street":"Marchmont Court Addison Gardens",
    "iso:country":"GB",
    "sg:address":"Marchmont Court Addison Gardens",
    "sg:city":"London",
    "sg:classifiers":[
        {
            "category":"Organizations",
            "subcategory":"Membership Organization",
            "type":"Services"
        }
    ],
    "sg:postcode":"W14 0EU",
    "sg:province":"Greater London",
    "sg:tags":[
        "club"
    ],
    "wof:name":"Marchmont Court Ltd",
    "wof:placetype":"venue"
},
  "geometry": {"coordinates":[-0.216744,51.50135],"type":"Point"}
}