{
  "type": "Feature",
  "properties": {
    "iso:country":"GB",
    "sg:address":"Market House, 12 Market House",
    "sg:city":"Harlow",
    "sg:classifiers":[
        {
            "category":"Banks & Credit Unions",
            "subcategory":"Bank",
            "type":"Services"
        }
    ],
    "sg:phone":"+44 1279 423006",
    "sg:postcode":"CM20 1BL",
    "sg:province":"Essex",
    "sg:tags":[
        "broker",
        "mortgage"
    ],
    "wof:name":"Broker Mortgage Services",
    "wof:placetype":"venue"
},
  "geometry": {"coordinates":[0.093615,51.771534],"type":"Point"}
}