{
  "type": "Feature",
  "properties": {
    "addr:full":"54-55 Ship Street Brighton East Sussex BN1 1AF",
    "addr:housenumber":"54-55",
    "addr:postcode":"bn1 1af",
    "addr:street":"Ship Street",
    "iso:country":"GB",
    "sg:address":"54-55 Ship Street",
    "sg:city":"Brighton",
    "sg:classifiers":[
        {
            "category":"Banks & Credit Unions",
            "subcategory":"Financial Services",
            "type":"Services"
        }
    ],
    "sg:phone":"+44 1273 326334",
    "sg:postcode":"BN1 1AF",
    "sg:province":"East Sussex",
    "sg:tags":[
        "building",
        "society"
    ],
    "wof:name":"Bristol & West Plc",
    "wof:placetype":"venue"
},
  "geometry": {"coordinates":[-0.141497,50.822502],"type":"Point"}
}