{
  "type": "Feature",
  "properties": {
    "iso:country":"GB",
    "sg:address":"50 Brocksparkwood, Hutton",
    "sg:city":"Brentwood",
    "sg:classifiers":[
        {
            "category":"Retail",
            "subcategory":"Auto Repair",
            "type":"Services"
        }
    ],
    "sg:phone":"+44 1277 229921",
    "sg:postcode":"CM13 2TJ",
    "sg:province":"Essex",
    "sg:tags":[
        "body",
        "car"
    ],
    "wof:name":"Chips Away",
    "wof:placetype":"venue"
},
  "geometry": {"coordinates":[0.332133,51.615971],"type":"Point"}
}