{
  "type": "Feature",
  "properties": {
    "iso:country":"GB",
    "sg:address":"St Helens Convent, 5 Kingsborough Gardens",
    "sg:city":"Glasgow",
    "sg:classifiers":[
        {
            "category":"Organizations",
            "subcategory":"Religious Organization",
            "type":"Services"
        }
    ],
    "sg:phone":"+44 141 339 6789",
    "sg:postcode":"G12 9NH",
    "sg:province":"Glasgow City",
    "sg:tags":[
        "organisation"
    ],
    "wof:name":"Franciscan Missionaries Of Mary",
    "wof:placetype":"venue"
},
  "geometry": {"coordinates":[-4.30516,55.878319],"type":"Point"}
}