{
  "type": "Feature",
  "properties": {
    "iso:country":"GB",
    "sg:address":"Didcot Delivery Office, 130 Broadway",
    "sg:city":"Didcot",
    "sg:classifiers":[
        {
            "category":"Personal",
            "type":"Services"
        }
    ],
    "sg:phone":"+44 1235 813298",
    "sg:postcode":"OX11 8ZZ",
    "sg:province":"Oxfordshire",
    "sg:tags":[
        "delivery"
    ],
    "wof:name":"Royal Mail Group Plc",
    "wof:placetype":"venue"
},
  "geometry": {"coordinates":[-1.2321150303,51.6023826599],"type":"Point"}
}