{
  "type": "Feature",
  "properties": {
    "addr:full":"Station Garage, St Margarets Street Bradford-on-avon Wiltshire BA15 1DL",
    "addr:postcode":"ba15 1dl",
    "addr:street":"St Margarets Street",
    "iso:country":"GB",
    "sg:address":"Station Garage, St Margarets Street",
    "sg:city":"Bradford-on-avon",
    "sg:classifiers":[
        {
            "category":"Autos & Motor Vehicles",
            "subcategory":"Automobile Sales",
            "type":"Retail Goods"
        }
    ],
    "sg:phone":"+44 1225 863215",
    "sg:postcode":"BA15 1DL",
    "sg:province":"Wiltshire",
    "sg:tags":[
        "car"
    ],
    "wof:name":"E W Stone Ltd.",
    "wof:placetype":"venue"
},
  "geometry": {"coordinates":[-2.2521140575,51.3462028503],"type":"Point"}
}