{
  "type": "Feature",
  "properties": {
    "addr:full":"Robert Frew Medical Centre, Salcott Crescent Wickford Essex SS12 9NR",
    "addr:postcode":"ss12 9nr",
    "addr:street":"Salcott Crescent",
    "iso:country":"GB",
    "sg:address":"Robert Frew Medical Centre, Salcott Crescent",
    "sg:city":"Wickford",
    "sg:classifiers":[
        {
            "category":"Health Services",
            "subcategory":"Doctor",
            "type":"Services"
        }
    ],
    "sg:phone":"+44 1268 578800",
    "sg:postcode":"SS12 9NR",
    "sg:province":"Essex",
    "sg:tags":[
        "practitioners"
    ],
    "wof:name":"Agbaje Harriott Ogunsanya Wissa & Brown",
    "wof:placetype":"venue"
},
  "geometry": {"coordinates":[0.5189149976,51.6114349365],"type":"Point"}
}