{
  "type": "Feature",
  "properties": {
    "addr:full":"Unit 5 Ashdown Farm, Badsey Road Evesham Gloucestershire WR11 7PA",
    "addr:housenumber":"unit 5 ashdown farm",
    "addr:postcode":"wr11 7pa",
    "addr:street":"Badsey Road",
    "iso:country":"GB",
    "sg:address":"Unit 5 Ashdown Farm, Badsey Road",
    "sg:city":"Evesham",
    "sg:classifiers":[
        {
            "category":"Manufacturing",
            "subcategory":"Metals",
            "type":"Manufacturing & Wholesale Goods"
        }
    ],
    "sg:phone":"+44 1386 48206",
    "sg:postcode":"WR11 7PA",
    "sg:province":"Gloucestershire",
    "sg:tags":[
        "work",
        "sheet"
    ],
    "wof:name":"Jeebra Metalwork",
    "wof:placetype":"venue"
},
  "geometry": {"coordinates":[-1.9439690113,52.1063919067],"type":"Point"}
}