{
  "type": "Feature",
  "properties": {
    "iso:country":"GB",
    "sg:address":", Rhydlewis",
    "sg:city":"Llandysul",
    "sg:classifiers":[
        {
            "category":"Education",
            "subcategory":"School",
            "type":"Public Place"
        }
    ],
    "sg:phone":"+44 1239 851416",
    "sg:postcode":"SA44 5PQ",
    "sg:province":"Carmarthenshire",
    "sg:tags":[
        "local",
        "authority"
    ],
    "wof:name":"Rhydlewis County Primary School",
    "wof:placetype":"venue"
},
  "geometry": {"coordinates":[-4.4141321182,52.0991439819],"type":"Point"}
}