{
  "type": "Feature",
  "properties": {
    "iso:country":"GB",
    "sg:address":"7 South Parade, Totten",
    "sg:city":"Southampton",
    "sg:classifiers":[
        {
            "category":"Professional",
            "subcategory":"Accounting & Tax Preparation",
            "type":"Services"
        }
    ],
    "sg:phone":"+44 23 8087 0385",
    "sg:postcode":"SO40 3PY",
    "sg:province":"Hampshire",
    "sg:tags":[
        "accountant"
    ],
    "wof:name":"Martin Young",
    "wof:placetype":"venue"
},
  "geometry": {"coordinates":[-1.48977,50.918892],"type":"Point"}
}