{
  "type": "Feature",
  "properties": {
    "iso:country":"GB",
    "sg:address":"Tyn Twll Farm, Old Bagillt Rd",
    "sg:city":"Bagillt",
    "sg:classifiers":[
        {
            "category":"Farming",
            "subcategory":"Farm",
            "type":"Manufacturing & Wholesale Goods"
        }
    ],
    "sg:phone":"+44 1352 710943",
    "sg:postcode":"CH6 6ER",
    "sg:province":"Flintshire",
    "sg:tags":[
        "mixed",
        "crop"
    ],
    "wof:name":"B F Carr",
    "wof:placetype":"venue"
},
  "geometry": {"coordinates":[-3.171054,53.268921],"type":"Point"}
}