{
  "type": "Feature",
  "properties": {
    "addr:full":"Unit 1 Matilda Close, Gillingham Business Park Gillingham Kent ME8 0PP",
    "addr:housenumber":"unit 1",
    "addr:postcode":"me8 0pp",
    "addr:street":"Matilda Close",
    "iso:country":"GB",
    "sg:address":"Unit 1 Matilda Close, Gillingham Business Park",
    "sg:city":"Gillingham",
    "sg:classifiers":[
        {
            "category":"Home & Garden",
            "subcategory":"Hardware",
            "type":"Retail Goods"
        },
        {
            "category":"Building & Trades",
            "subcategory":"Pest Control",
            "type":"Services"
        }
    ],
    "sg:phone":"+44 1634 233110",
    "sg:postcode":"ME8 0PP",
    "sg:province":"Kent",
    "sg:tags":[
        "device",
        "fixing",
        "fastener"
    ],
    "wof:name":"Jubilee Clips Ltd.",
    "wof:placetype":"venue"
},
  "geometry": {"coordinates":[0.578734,51.364502],"type":"Point"}
}