{
  "type": "Feature",
  "properties": {
    "addr:full":"Unit K, Floors Street Industrial Estate Johnstone Renfrewshire PA5 8PE",
    "addr:housenumber":"estate",
    "addr:postcode":"pa5 8pe",
    "addr:street":"Street Industrial",
    "iso:country":"GB",
    "sg:address":"Unit K, Floors Street Industrial Estate",
    "sg:city":"Johnstone",
    "sg:classifiers":[
        {
            "category":"Shopping",
            "subcategory":"Clothing, Apparel, & Fashions",
            "type":"Retail Goods"
        }
    ],
    "sg:phone":"+44 1505 321688",
    "sg:postcode":"PA5 8PE",
    "sg:province":"Renfrewshire",
    "sg:tags":[
        "workwear",
        "protective"
    ],
    "wof:name":"Peter Renton Industrial Supplies",
    "wof:placetype":"venue"
},
  "geometry": {"coordinates":[-4.5083441734,55.8361091614],"type":"Point"}
}