{
  "type": "Feature",
  "properties": {
    "addr:full":"3 St. Helens Place Monument Greater London EC3A 6AU",
    "addr:housenumber":"3",
    "addr:postcode":"ec3a 6au",
    "addr:street":"St. Helens Place",
    "iso:country":"GB",
    "sg:address":"3 St. Helens Place",
    "sg:city":"Monument",
    "sg:classifiers":[
        {
            "category":"Banks & Credit Unions",
            "subcategory":"Bank",
            "type":"Services"
        }
    ],
    "sg:phone":"+44 20 7256 6655",
    "sg:postcode":"EC3A 6AU",
    "sg:province":"Greater London",
    "wof:name":"Banco Boavista S.A",
    "wof:placetype":"venue"
},
  "geometry": {"coordinates":[-0.0824289992,51.5151939392],"type":"Point"}
}