{
  "type": "Feature",
  "properties": {
    "addr:full":"Dolycoed Terrace Ferndale Rhondda, Cynon, Taff CF43 3BW",
    "addr:postcode":"cf43 3bw",
    "addr:street":"Dolycoed Terrace",
    "iso:country":"GB",
    "sg:address":"Dolycoed Terrace",
    "sg:city":"Ferndale",
    "sg:classifiers":[
        {
            "category":"Autos & Motor Vehicles",
            "subcategory":"Fuel & Gas Station",
            "type":"Retail Goods"
        }
    ],
    "sg:phone":"+44 1443 755015",
    "sg:postcode":"CF43 3BW",
    "sg:province":"Rhondda, Cynon, Taff",
    "sg:tags":[
        "petrol",
        "filling"
    ],
    "wof:name":"Griffiths Service Station",
    "wof:placetype":"venue"
},
  "geometry": {"coordinates":[-3.4478089809,51.661113739],"type":"Point"}
}