{
  "type": "Feature",
  "properties": {
    "addr:full":"Hilton Of Duncrievie, Glenfarg Perth Perth and Kinross PH2 9PD",
    "addr:postcode":"ph2 9pd",
    "iso:country":"GB",
    "sg:address":"Hilton Of Duncrievie, Glenfarg",
    "sg:city":"Perth",
    "sg:classifiers":[
        {
            "category":"Farming",
            "subcategory":"Farm",
            "type":"Manufacturing & Wholesale Goods"
        }
    ],
    "sg:postcode":"PH2 9PD",
    "sg:province":"Perth and Kinross",
    "sg:tags":[
        "mixed",
        "crop"
    ],
    "wof:name":"C L Stewart",
    "wof:placetype":"venue"
},
  "geometry": {"coordinates":[-3.398643,56.278355],"type":"Point"}
}