{
  "type": "Feature",
  "properties": {
    "addr:full":"764a Fulham Road London Greater London SW6 5SJ",
    "addr:housenumber":"764a",
    "addr:postcode":"sw6 5sj",
    "addr:street":"Fulham Road",
    "iso:country":"GB",
    "sg:address":"764a Fulham Road",
    "sg:city":"London",
    "sg:classifiers":[
        {
            "category":"Personal",
            "subcategory":"Beauty Salon",
            "type":"Services"
        }
    ],
    "sg:postcode":"SW6 5SJ",
    "sg:province":"Greater London",
    "sg:tags":[
        "unisex",
        "hairdresser"
    ],
    "wof:name":"The Strand",
    "wof:placetype":"venue"
},
  "geometry": {"coordinates":[-0.2099819928,51.4723510742],"type":"Point"}
}