{
  "type": "Feature",
  "properties": {
    "addr:full":"Lake House, 7 Parkfield Road, Coleshill Birmingham Warwickshire B46 3LD",
    "addr:housenumber":"7",
    "addr:postcode":"b46 3ld",
    "addr:street":"Parkfield Road",
    "iso:country":"GB",
    "sg:address":"Lake House, 7 Parkfield Road, Coleshill",
    "sg:city":"Birmingham",
    "sg:classifiers":[
        {
            "category":"Freight",
            "type":"Transportation"
        }
    ],
    "sg:phone":"+44 121 784 5101",
    "sg:postcode":"B46 3LD",
    "sg:province":"Warwickshire",
    "sg:tags":[
        "forwarders"
    ],
    "wof:name":"Andersen Harvey Lake & Co Ltd",
    "wof:placetype":"venue"
},
  "geometry": {"coordinates":[-1.7065830231,52.4965591431],"type":"Point"}
}