{
  "type": "Feature",
  "properties": {
    "addr:full":"29 Clarkenwell Road London Greater London EC1M 5TA",
    "addr:housenumber":"29",
    "addr:postcode":"ec1m 5ta",
    "addr:street":"Clarkenwell Road",
    "iso:country":"GB",
    "sg:address":"29 Clarkenwell Road",
    "sg:city":"London",
    "sg:classifiers":[
        {
            "category":"Professional",
            "subcategory":"Advertising",
            "type":"Services"
        }
    ],
    "sg:phone":"+44 20 7287 4877",
    "sg:postcode":"EC1M 5TA",
    "sg:province":"Greater London",
    "sg:tags":[
        "agency"
    ],
    "wof:name":"World Writers Ltd.",
    "wof:placetype":"venue"
},
  "geometry": {"coordinates":[-0.102615,51.522388],"type":"Point"}
}