{
  "type": "Feature",
  "properties": {
    "addr:full":"High Street, Newton Poppleford Sidmouth Devon EX10 0DW",
    "addr:postcode":"ex10 0dw",
    "addr:street":"High Street",
    "iso:country":"GB",
    "sg:address":"High Street, Newton Poppleford",
    "sg:city":"Sidmouth",
    "sg:classifiers":[
        {
            "category":"Restaurant",
            "type":"Food & Drink"
        }
    ],
    "sg:phone":"+44 1395 568136",
    "sg:postcode":"EX10 0DW",
    "sg:province":"Devon",
    "wof:name":"la Rosina Trattoria",
    "wof:placetype":"venue"
},
  "geometry": {"coordinates":[-3.298363924,50.699798584],"type":"Point"}
}