{
  "type": "Feature",
  "properties": {
    "addr:full":"8 Bombay Street London Greater London SE16 3UX",
    "addr:housenumber":"8",
    "addr:postcode":"se16 3ux",
    "addr:street":"Bombay Street",
    "iso:country":"GB",
    "sg:address":"8 Bombay Street",
    "sg:city":"London",
    "sg:classifiers":[
        {
            "category":"Professional",
            "subcategory":"Management & Consulting",
            "type":"Services"
        }
    ],
    "sg:phone":"+44 20 7237 6707",
    "sg:postcode":"SE16 3UX",
    "sg:province":"Greater London",
    "sg:tags":[
        "fire",
        "consultant",
        "protection"
    ],
    "wof:name":"Gordonson Fire Protection Ltd.",
    "wof:placetype":"venue"
},
  "geometry": {"coordinates":[-0.062662,51.492832],"type":"Point"}
}