{
  "type": "Feature",
  "properties": {
    "iso:country":"GB",
    "sg:address":"Fairfield Lane",
    "sg:city":"Barrow In Furness",
    "sg:classifiers":[
        {
            "category":"Health Services",
            "subcategory":"Clinic",
            "type":"Services"
        }
    ],
    "sg:phone":"+44 1229 836422",
    "sg:postcode":"LA13 9AH",
    "sg:province":"Cumbria",
    "sg:tags":[
        "private"
    ],
    "wof:name":"Fairfield Clinic",
    "wof:placetype":"venue"
},
  "geometry": {"coordinates":[-3.2140870094,54.1239891052],"type":"Point"}
}