{
  "type": "Feature",
  "properties": {
    "iso:country":"GB",
    "sg:address":"116 Wallasey Village",
    "sg:city":"Wallasey",
    "sg:classifiers":[
        {
            "category":"Fast Food",
            "type":"Food & Drink"
        }
    ],
    "sg:phone":"+44 151 638 5060",
    "sg:postcode":"L45 3LN",
    "sg:province":"Merseyside",
    "sg:tags":[
        "away",
        "take"
    ],
    "wof:name":"Greedys",
    "wof:placetype":"venue"
},
  "geometry": {"coordinates":[-3.0649809837,53.4238967896],"type":"Point"}
}