{
  "type": "Feature",
  "properties": {
    "addr:full":"11 Market Place, Pocklington York East Riding of Yorkshire YO42 2AS",
    "addr:housenumber":"11",
    "addr:postcode":"yo42 2as",
    "addr:street":"Market Place",
    "iso:country":"GB",
    "sg:address":"11 Market Place, Pocklington",
    "sg:city":"York",
    "sg:classifiers":[
        {
            "category":"Shopping",
            "subcategory":"News",
            "type":"Retail Goods"
        }
    ],
    "sg:phone":"+44 1759 306689",
    "sg:postcode":"YO42 2AS",
    "sg:province":"East Riding of Yorkshire",
    "sg:tags":[
        "newsagent"
    ],
    "wof:name":"Maynews Ltd.",
    "wof:placetype":"venue"
},
  "geometry": {"coordinates":[-0.7791640162,53.9304122925],"type":"Point"}
}