{
  "type": "Feature",
  "properties": {
    "addr:full":"Old Station Yd (the), Kirkby Lonsdale Carnforth Cumbria LA6 2HP",
    "addr:housenumber":"kirkby",
    "addr:postcode":"la6 2hp",
    "addr:street":"Yd The",
    "iso:country":"GB",
    "sg:address":"Old Station Yd (the), Kirkby Lonsdale",
    "sg:city":"Carnforth",
    "sg:classifiers":[
        {
            "category":"Real Estate",
            "subcategory":"Developer",
            "type":"Services"
        },
        {
            "category":"Building & Trades",
            "subcategory":"Construction",
            "type":"Services"
        }
    ],
    "sg:phone":"+44 15242 72743",
    "sg:postcode":"LA6 2HP",
    "sg:province":"Cumbria",
    "sg:tags":[
        "property",
        "contractor"
    ],
    "wof:name":"W B Build Ltd",
    "wof:placetype":"venue"
},
  "geometry": {"coordinates":[-2.5982739925,54.2020187378],"type":"Point"}
}