{
  "type": "Feature",
  "properties": {
    "addr:full":"59b Thorntree Road Stockton-on-tees Durham TS17 8LU",
    "addr:housenumber":"59b",
    "addr:postcode":"ts17 8lu",
    "addr:street":"Thorntree Road",
    "iso:country":"GB",
    "sg:address":"59b Thorntree Road",
    "sg:city":"Stockton-on-tees",
    "sg:classifiers":[
        {
            "category":"Personal",
            "subcategory":"Barber",
            "type":"Services"
        }
    ],
    "sg:postcode":"TS17 8LU",
    "sg:province":"Durham",
    "sg:tags":[
        "men's",
        "hairdresser"
    ],
    "wof:name":"Jim's Gents Hairdressing",
    "wof:placetype":"venue"
},
  "geometry": {"coordinates":[-1.29861,54.545361],"type":"Point"}
}