{
  "type": "Feature",
  "properties": {
    "addr:full":"320 Lincoln Road Enfield Greater London EN3 4AA",
    "addr:housenumber":"320",
    "addr:postcode":"en3 4aa",
    "addr:street":"Lincoln Road",
    "iso:country":"GB",
    "sg:address":"320 Lincoln Road",
    "sg:city":"Enfield",
    "sg:classifiers":[
        {
            "category":"Personal",
            "subcategory":"Skin Care",
            "type":"Services"
        }
    ],
    "sg:phone":"+44 20 8366 2123",
    "sg:postcode":"EN3 4AA",
    "sg:province":"Greater London",
    "sg:tags":[
        "leather",
        "merchant"
    ],
    "wof:name":"Cadore Ltd.",
    "wof:placetype":"venue"
},
  "geometry": {"coordinates":[-0.0531760007,51.6442718506],"type":"Point"}
}