{
  "type": "Feature",
  "properties": {
    "iso:country":"GB",
    "sg:address":"62 Outram Street",
    "sg:city":"Sutton-in-ashfield",
    "sg:classifiers":[
        {
            "category":"Personal",
            "subcategory":"Beauty Salon",
            "type":"Services"
        }
    ],
    "sg:phone":"+44 1623 554480",
    "sg:postcode":"NG17 4FF",
    "sg:province":"Nottinghamshire",
    "sg:tags":[
        "unisex",
        "hairdresser"
    ],
    "wof:name":"Clippers Hair Design",
    "wof:placetype":"venue"
},
  "geometry": {"coordinates":[-1.256314,53.128304],"type":"Point"}
}