{
  "type": "Feature",
  "properties": {
    "iso:country":"GB",
    "sg:address":"4 Hope Street, Stocksbridge",
    "sg:city":"Sheffield",
    "sg:classifiers":[
        {
            "category":"Personal",
            "subcategory":"Beauty Salon",
            "type":"Services"
        }
    ],
    "sg:postcode":"S36 1BR",
    "sg:province":"South Yorkshire",
    "sg:tags":[
        "unisex",
        "hairdresser"
    ],
    "wof:name":"Seonaids Hair Salon",
    "wof:placetype":"venue"
},
  "geometry": {"coordinates":[-1.5930609703,53.4817199707],"type":"Point"}
}