{
  "type": "Feature",
  "properties": {
    "addr:full":"4 Hope Street, Stocksbridge Sheffield South Yorkshire S36 1BR",
    "addr:housenumber":"4",
    "addr:postcode":"s36 1br",
    "addr:street":"Hope Street",
    "iso:country":"GB",
    "sg:address":"4 Hope Street, Stocksbridge",
    "sg:city":"Sheffield",
    "sg:classifiers":[
        {
            "category":"Personal",
            "subcategory":"Beauty Salon",
            "type":"Services"
        }
    ],
    "sg:postcode":"S36 1BR",
    "sg:province":"South Yorkshire",
    "sg:tags":[
        "unisex",
        "hairdresser"
    ],
    "wof:name":"Seonaids Hair Salon",
    "wof:placetype":"venue"
},
  "geometry": {"coordinates":[-1.5930609703,53.4817199707],"type":"Point"}
}