{
  "type": "Feature",
  "properties": {
    "iso:country":"GB",
    "sg:address":"36 Phillips Ct",
    "sg:city":"Stamford",
    "sg:classifiers":[
        {
            "category":"Professional",
            "subcategory":"Accounting & Tax Preparation",
            "type":"Services"
        }
    ],
    "sg:phone":"+44 1780 754889",
    "sg:postcode":"PE9 2EE",
    "sg:province":"Cambridgeshire",
    "sg:tags":[
        "accountant"
    ],
    "wof:name":"A & R International Consultants",
    "wof:placetype":"venue"
},
  "geometry": {"coordinates":[-0.4737719893,52.6497688293],"type":"Point"}
}