{
  "type": "Feature",
  "properties": {
    "iso:country":"GB",
    "sg:address":"16 Vincent Avenue",
    "sg:city":"Stratford-upon-avon",
    "sg:classifiers":[
        {
            "category":"Real Estate",
            "subcategory":"Surveying",
            "type":"Services"
        }
    ],
    "sg:phone":"+44 1789 205697",
    "sg:postcode":"CV37 6SR",
    "sg:province":"Warwickshire",
    "sg:tags":[
        "building",
        "surveyor"
    ],
    "wof:name":"Michael Smith Associates",
    "wof:placetype":"venue"
},
  "geometry": {"coordinates":[-1.7083,52.19968],"type":"Point"}
}