{
  "type": "Feature",
  "properties": {
    "addr:full":"11 London Road Wickford Essex SS12 0AW",
    "addr:housenumber":"11",
    "addr:postcode":"ss12 0aw",
    "addr:street":"London Road",
    "iso:country":"GB",
    "sg:address":"11 London Road",
    "sg:city":"Wickford",
    "sg:classifiers":[
        {
            "category":"Real Estate",
            "subcategory":"Real Estate Agent",
            "type":"Services"
        }
    ],
    "sg:phone":"+44 1268 766477",
    "sg:postcode":"SS12 0AW",
    "sg:province":"Essex",
    "wof:name":"Barrett Property Management",
    "wof:placetype":"venue"
},
  "geometry": {"coordinates":[0.518689,51.61132],"type":"Point"}
}