{
  "type": "Feature",
  "properties": {
    "addr:full":"Penle House, Webb Street Bury Lancashire BL8 1AF",
    "addr:postcode":"bl8 1af",
    "addr:street":"Webb Street",
    "iso:country":"GB",
    "sg:address":"Penle House, Webb Street",
    "sg:city":"Bury",
    "sg:classifiers":[
        {
            "category":"Professional",
            "subcategory":"Management & Consulting",
            "type":"Services"
        }
    ],
    "sg:phone":"+44 161 764 2252",
    "sg:postcode":"BL8 1AF",
    "sg:province":"Lancashire",
    "sg:tags":[
        "fire",
        "consultant",
        "protection"
    ],
    "wof:name":"Pendle Design Ltd.",
    "wof:placetype":"venue"
},
  "geometry": {"coordinates":[-2.308546,53.59737],"type":"Point"}
}