{
  "type": "Feature",
  "properties": {
    "iso:country":"GB",
    "sg:address":"23 Hough Lane",
    "sg:city":"Preston",
    "sg:classifiers":[
        {
            "category":"Real Estate",
            "subcategory":"Real Estate Agent",
            "type":"Services"
        }
    ],
    "sg:phone":"+44 1772 622614",
    "sg:postcode":"PR25 2SU",
    "sg:province":"Lancashire",
    "wof:name":"Ann Douglas Estate Agents",
    "wof:placetype":"venue"
},
  "geometry": {"coordinates":[-2.693489,53.695347],"type":"Point"}
}