{
  "type": "Feature",
  "properties": {
    "addr:full":"34 Worrall Rd Sheffield South Yorkshire S6 4BA",
    "addr:housenumber":"34",
    "addr:postcode":"s6 4ba",
    "addr:street":"Worrall Rd",
    "iso:country":"GB",
    "sg:address":"34 Worrall Rd",
    "sg:city":"Sheffield",
    "sg:classifiers":[
        {
            "category":"Professional",
            "subcategory":"Engineering",
            "type":"Services"
        }
    ],
    "sg:phone":"+44 114 234 4736",
    "sg:postcode":"S6 4BA",
    "sg:province":"South Yorkshire",
    "sg:tags":[
        "contractor",
        "electrical",
        "engineer"
    ],
    "wof:name":"H Greaves",
    "wof:placetype":"venue"
},
  "geometry": {"coordinates":[-1.5169190168,53.4112014771],"type":"Point"}
}