{
  "type": "Feature",
  "properties": {
    "addr:full":"6-8 North Street Leighton Buzzard Bedfordshire LU7 1EN",
    "addr:housenumber":"6-8",
    "addr:postcode":"lu7 1en",
    "addr:street":"North Street",
    "iso:country":"GB",
    "sg:address":"6-8 North Street",
    "sg:city":"Leighton Buzzard",
    "sg:classifiers":[
        {
            "category":"Manufacturing",
            "subcategory":"Tools & Machinery",
            "type":"Manufacturing & Wholesale Goods"
        }
    ],
    "sg:phone":"+44 1525 851529",
    "sg:postcode":"LU7 1EN",
    "sg:province":"Bedfordshire",
    "sg:tags":[
        "society",
        "friendly"
    ],
    "wof:name":"Ryder Insurance Consultants",
    "wof:placetype":"venue"
},
  "geometry": {"coordinates":[-0.6607469916,51.917011261],"type":"Point"}
}