{
  "type": "Feature",
  "properties": {
    "iso:country":"GB",
    "sg:address":"252 Dickson Road",
    "sg:city":"Blackpool",
    "sg:classifiers":[
        {
            "category":"Cafe",
            "type":"Food & Drink"
        }
    ],
    "sg:postcode":"FY1 2JS",
    "sg:province":"Lancashire",
    "sg:tags":[
        "tea",
        "snack",
        "bar",
        "room"
    ],
    "wof:name":"THE LANTERN",
    "wof:placetype":"venue"
},
  "geometry": {"coordinates":[-3.053901,53.83197],"type":"Point"}
}