{
  "type": "Feature",
  "properties": {
    "addr:full":"11 Adcroft Street Stockport Cheshire SK1 3HZ",
    "addr:housenumber":"11",
    "addr:postcode":"sk1 3hz",
    "addr:street":"Adcroft Street",
    "iso:country":"GB",
    "sg:address":"11 Adcroft Street",
    "sg:city":"Stockport",
    "sg:classifiers":[
        {
            "category":"Building & Trades",
            "subcategory":"Construction",
            "type":"Services"
        }
    ],
    "sg:postcode":"SK1 3HZ",
    "sg:province":"Cheshire",
    "sg:tags":[
        "builder"
    ],
    "wof:name":"Cobell Construction Co. Ltd.",
    "wof:placetype":"venue"
},
  "geometry": {"coordinates":[-2.1524989605,53.4009437561],"type":"Point"}
}