{
  "type": "Feature",
  "properties": {
    "addr:full":"11 Hillcrest Avenue Bexhill-on-sea East Sussex TN39 4DA",
    "addr:housenumber":"11",
    "addr:postcode":"tn39 4da",
    "addr:street":"Hillcrest Avenue",
    "iso:country":"GB",
    "sg:address":"11 Hillcrest Avenue",
    "sg:city":"Bexhill-on-sea",
    "sg:classifiers":[
        {
            "category":"Retail",
            "subcategory":"Repair Shop",
            "type":"Services"
        }
    ],
    "sg:phone":"+44 1424 212697",
    "sg:postcode":"TN39 4DA",
    "sg:province":"East Sussex",
    "sg:tags":[
        "radio",
        "television",
        "video"
    ],
    "wof:name":"R C Potter",
    "wof:placetype":"venue"
},
  "geometry": {"coordinates":[0.4615530074,50.8534202576],"type":"Point"}
}