{
  "type": "Feature",
  "properties": {
    "addr:full":"54 Greenford Road Greenford Greater London UB6 9AT",
    "addr:housenumber":"54",
    "addr:postcode":"ub6 9at",
    "addr:street":"Greenford Road",
    "iso:country":"GB",
    "sg:address":"54 Greenford Road",
    "sg:city":"Greenford",
    "sg:classifiers":[
        {
            "category":"Retail",
            "subcategory":"Laundry & Dry Cleaning",
            "type":"Services"
        }
    ],
    "sg:phone":"+44 20 8813 1758",
    "sg:postcode":"UB6 9AT",
    "sg:province":"Greater London",
    "sg:tags":[
        "launderette"
    ],
    "wof:name":"Posh Wash",
    "wof:placetype":"venue"
},
  "geometry": {"coordinates":[-0.354359,51.519081],"type":"Point"}
}