{
  "type": "Feature",
  "properties": {
    "addr:full":"Berry Way Skegness Lincolnshire PE25 3QS",
    "addr:postcode":"pe25 3qs",
    "addr:street":"Berry Way",
    "iso:country":"GB",
    "sg:address":"Berry Way",
    "sg:city":"Skegness",
    "sg:classifiers":[
        {
            "category":"Home & Garden",
            "subcategory":"Furniture",
            "type":"Retail Goods"
        }
    ],
    "sg:phone":"+44 1754 761574",
    "sg:postcode":"PE25 3QS",
    "sg:province":"Lincolnshire",
    "wof:name":"Charles Lane & Fraser",
    "wof:placetype":"venue"
},
  "geometry": {"coordinates":[0.334615,53.14423],"type":"Point"}
}