{
  "type": "Feature",
  "properties": {
    "addr:full":"Marble Lane Health Centre, 37 Marble La Grove Park Greater London SE12 8PN",
    "addr:housenumber":"37",
    "addr:postcode":"se12 8pn",
    "addr:street":"Marble;Marble La Grove Park",
    "iso:country":"GB",
    "sg:address":"Marble Lane Health Centre, 37 Marble La",
    "sg:city":"Grove Park",
    "sg:classifiers":[
        {
            "category":"Health Services",
            "subcategory":"Doctor",
            "type":"Services"
        }
    ],
    "sg:phone":"+44 20 8857 4145",
    "sg:postcode":"SE12 8PN",
    "sg:province":"Greater London",
    "sg:tags":[
        "practitioners"
    ],
    "wof:name":"Lingarajah, S",
    "wof:placetype":"venue"
},
  "geometry": {"coordinates":[0.01641,51.45406],"type":"Point"}
}