{
  "type": "Feature",
  "properties": {
    "addr:full":"2 Coldicotts Close, Bretforton Evesham Gloucestershire WR11 7HT",
    "addr:housenumber":"2",
    "addr:postcode":"wr11 7ht",
    "addr:street":"Coldicotts Close",
    "iso:country":"GB",
    "sg:address":"2 Coldicotts Close, Bretforton",
    "sg:city":"Evesham",
    "sg:classifiers":[
        {
            "category":"Food & Beverages",
            "subcategory":"Farmers Market",
            "type":"Retail Goods"
        }
    ],
    "sg:postcode":"WR11 7HT",
    "sg:province":"Gloucestershire",
    "sg:tags":[
        "gardener"
    ],
    "wof:name":"F H Byrd & Sons",
    "wof:placetype":"venue"
},
  "geometry": {"coordinates":[-1.8713719845,52.0957641602],"type":"Point"}
}