{
  "type": "Feature",
  "properties": {
    "addr:full":"89 Chesham Fold Road Bury Lancashire BL9 6JZ",
    "addr:housenumber":"89",
    "addr:postcode":"bl9 6jz",
    "addr:street":"Chesham Fold Road",
    "iso:country":"GB",
    "sg:address":"89 Chesham Fold Road",
    "sg:city":"Bury",
    "sg:classifiers":[
        {
            "category":"Organizations",
            "subcategory":"Non-profit Organization",
            "type":"Services"
        }
    ],
    "sg:postcode":"BL9 6JZ",
    "sg:province":"Lancashire",
    "sg:tags":[
        "organisation",
        "voluntary",
        "charity"
    ],
    "wof:name":"The Chesham Fold Community Project",
    "wof:placetype":"venue"
},
  "geometry": {"coordinates":[-2.2752048969,53.6008262634],"type":"Point"}
}