{
  "type": "Feature",
  "properties": {
    "iso:country":"GB",
    "sg:address":"54-56 Victoria St",
    "sg:city":"Newton Stewart",
    "sg:classifiers":[
        {
            "category":"Travel",
            "subcategory":"Hotels & Motels",
            "type":"Entertainment"
        }
    ],
    "sg:phone":"+44 1671 402653",
    "sg:postcode":"DG8 6DB",
    "sg:province":"Dumfries and Galloway",
    "wof:name":"Galloway Arms Hotel",
    "wof:placetype":"venue"
},
  "geometry": {"coordinates":[-4.483333,54.959412],"type":"Point"}
}