{
  "type": "Feature",
  "properties": {
    "addr:full":"71 Market Street, Hollingworth Hyde Cheshire SK14 8HR",
    "addr:housenumber":"71",
    "addr:postcode":"sk14 8hr",
    "addr:street":"Market Street",
    "iso:country":"GB",
    "sg:address":"71 Market Street, Hollingworth",
    "sg:city":"Hyde",
    "sg:classifiers":[
        {
            "category":"Wholesale",
            "subcategory":"Furniture",
            "type":"Manufacturing & Wholesale Goods"
        }
    ],
    "sg:phone":"+44 1457 766747",
    "sg:postcode":"SK14 8HR",
    "sg:province":"Cheshire",
    "sg:tags":[
        "shop",
        "fitting"
    ],
    "wof:name":"Dove House Forge",
    "wof:placetype":"venue"
},
  "geometry": {"coordinates":[-1.9913159609,53.4630393982],"type":"Point"}
}