{
  "type": "Feature",
  "properties": {
    "addr:full":"Bankhead Farm, Cairnryan Stranraer Dumfries and Galloway DG9 8QX",
    "addr:postcode":"dg9 8qx",
    "addr:street":"Bankhead",
    "iso:country":"GB",
    "sg:address":"Bankhead Farm, Cairnryan",
    "sg:city":"Stranraer",
    "sg:classifiers":[
        {
            "category":"Farming",
            "subcategory":"Dairy Farm",
            "type":"Manufacturing & Wholesale Goods"
        }
    ],
    "sg:postcode":"DG9 8QX",
    "sg:province":"Dumfries and Galloway",
    "wof:name":"Ian McGhgie",
    "wof:placetype":"venue"
},
  "geometry": {"coordinates":[-5.0164442062,54.9056358337],"type":"Point"}
}