{
  "type": "Feature",
  "properties": {
    "addr:full":"Aventis House 50 Kings Hill Avenue, Kings Hill West Malling Kent ME19 4AH",
    "addr:housenumber":"50",
    "addr:postcode":"me19 4ah",
    "addr:street":"Kings Hill Avenue",
    "iso:country":"GB",
    "sg:address":"Aventis House 50 Kings Hill Avenue, Kings Hill",
    "sg:city":"West Malling",
    "sg:classifiers":[
        {
            "category":"Shopping",
            "subcategory":"Pharmacy",
            "type":"Retail Goods"
        }
    ],
    "sg:phone":"+44 1732 584000",
    "sg:postcode":"ME19 4AH",
    "sg:province":"Kent",
    "sg:tags":[
        "pharmaceutical"
    ],
    "wof:name":"May & Baker Ltd.",
    "wof:placetype":"venue"
},
  "geometry": {"coordinates":[0.4129399955,51.2937088013],"type":"Point"}
}