{
  "type": "Feature",
  "properties": {
    "addr:full":"44 Lock Lane, Long Eaton Nottingham Derbyshire NG10 3DD",
    "addr:housenumber":"44",
    "addr:postcode":"ng10 3dd",
    "addr:street":"Lock Lane",
    "iso:country":"GB",
    "sg:address":"44 Lock Lane, Long Eaton",
    "sg:city":"Nottingham",
    "sg:classifiers":[
        {
            "category":"Real Estate",
            "subcategory":"Real Estate Services",
            "type":"Services"
        },
        {
            "category":"Organizations",
            "subcategory":"Membership Organization",
            "type":"Services"
        }
    ],
    "sg:phone":"+44 115 973 3668",
    "sg:postcode":"NG10 3DD",
    "sg:province":"Derbyshire",
    "sg:tags":[
        "club",
        "management"
    ],
    "wof:name":"OVERDALE (LONG EATON) MANAGEMENT CO LTD",
    "wof:placetype":"venue"
},
  "geometry": {"coordinates":[-1.290643,52.879623],"type":"Point"}
}