{
  "type": "Feature",
  "properties": {
    "iso:country":"GB",
    "sg:address":"1 Wharf Road",
    "sg:city":"St Ives",
    "sg:classifiers":[
        {
            "category":"Shopping",
            "subcategory":"Gifts & Souvenirs",
            "type":"Retail Goods"
        }
    ],
    "sg:phone":"+44 1736 797260",
    "sg:postcode":"TR26 1LG",
    "sg:province":"Cornwall",
    "sg:tags":[
        "shop"
    ],
    "wof:name":"The Golden Galleon",
    "wof:placetype":"venue"
},
  "geometry": {"coordinates":[-5.4798760414,50.2138710022],"type":"Point"}
}