{
  "type": "Feature",
  "properties": {
    "addr:full":"Unit 2 Wem Business Park, Wem Shrewsbury Shropshire SY4 5BF",
    "addr:housenumber":"unit 2",
    "addr:postcode":"sy4 5bf",
    "addr:street":"Wem Business Park Wem",
    "iso:country":"GB",
    "sg:address":"Unit 2 Wem Business Park, Wem",
    "sg:city":"Shrewsbury",
    "sg:classifiers":[
        {
            "category":"Shopping",
            "subcategory":"Catalog Store",
            "type":"Retail Goods"
        }
    ],
    "sg:postcode":"SY4 5BF",
    "sg:province":"Shropshire",
    "sg:tags":[
        "mail",
        "order"
    ],
    "wof:name":"Gardens Bird Supplies Ltd.",
    "wof:placetype":"venue"
},
  "geometry": {"coordinates":[-2.7113699913,52.8572387695],"type":"Point"}
}