{
  "type": "Feature",
  "properties": {
    "addr:full":"1st Floor, 40 Lowther Street Carlisle Cumbria CA3 8DH",
    "addr:housenumber":"40",
    "addr:postcode":"ca3 8dh",
    "addr:street":"Lowther Street",
    "iso:country":"GB",
    "sg:address":"1st Floor, 40 Lowther Street",
    "sg:city":"Carlisle",
    "sg:classifiers":[
        {
            "category":"Transit Center",
            "subcategory":"Freight",
            "type":"Transportation"
        },
        {
            "category":"Banks & Credit Unions",
            "subcategory":"Bank",
            "type":"Services"
        },
        {
            "category":"Commercial Area",
            "type":"Public Place"
        },
        {
            "category":"Real Estate",
            "subcategory":"Real Estate Agent",
            "type":"Services"
        }
    ],
    "sg:phone":"+44 1228 515515",
    "sg:postcode":"CA3 8DH",
    "sg:province":"Cumbria",
    "sg:tags":[
        "shop",
        "property",
        "broker",
        "mortgage",
        "centre"
    ],
    "wof:name":"Homesearch Direct Ltd.",
    "wof:placetype":"venue"
},
  "geometry": {"coordinates":[-2.9332358837,54.894493103],"type":"Point"}
}