{
  "type": "Feature",
  "properties": {
    "addr:full":"Mullett Road Wolverhampton Staffordshire WV11 1DD",
    "addr:postcode":"wv11 1dd",
    "addr:street":"Mullett Road",
    "iso:country":"GB",
    "sg:address":"Mullett Road",
    "sg:city":"Wolverhampton",
    "sg:classifiers":[
        {
            "category":"Education",
            "subcategory":"School",
            "type":"Public Place"
        },
        {
            "category":"Government",
            "subcategory":"Office",
            "type":"Public Place"
        }
    ],
    "sg:phone":"+44 1902 558778",
    "sg:postcode":"WV11 1DD",
    "sg:province":"Staffordshire",
    "sg:tags":[
        "local",
        "authority"
    ],
    "wof:name":"D'Eyncourt Primary School",
    "wof:placetype":"venue"
},
  "geometry": {"coordinates":[-2.096159,52.609928],"type":"Point"}
}