{
  "type": "Feature",
  "properties": {
    "addr:full":"181 London Rd Waterlooville Hampshire PO8 8ER",
    "addr:housenumber":"181",
    "addr:postcode":"po8 8er",
    "addr:street":"London Rd",
    "iso:country":"GB",
    "sg:address":"181 London Rd",
    "sg:city":"Waterlooville",
    "sg:classifiers":[
        {
            "category":"Retail",
            "subcategory":"Storage",
            "type":"Services"
        }
    ],
    "sg:phone":"+44 23 9225 8555",
    "sg:postcode":"PO8 8ER",
    "sg:province":"Hampshire",
    "sg:tags":[
        "household",
        "removal"
    ],
    "wof:name":"Chapman Transport Services",
    "wof:placetype":"venue"
},
  "geometry": {"coordinates":[-1.0241190195,50.8889007568],"type":"Point"}
}