{
  "type": "Feature",
  "properties": {
    "iso:country":"GB",
    "sg:address":"10 Bolton St",
    "sg:city":"Bury",
    "sg:classifiers":[
        {
            "category":"Banks & Credit Unions",
            "subcategory":"Bank",
            "type":"Services"
        }
    ],
    "sg:phone":"+44 161 797 3200",
    "sg:postcode":"BL9 0LQ",
    "sg:province":"Lancashire",
    "sg:tags":[
        "broker",
        "mortgage"
    ],
    "wof:name":"S & R Associates",
    "wof:placetype":"venue"
},
  "geometry": {"coordinates":[-2.298659,53.593643],"type":"Point"}
}