{
  "type": "Feature",
  "properties": {
    "iso:country":"GB",
    "sg:address":"Unit 6, Beddington Cross, Beddington Lane",
    "sg:city":"Croydon",
    "sg:classifiers":[
        {
            "category":"Manufacturing",
            "subcategory":"Buildings",
            "type":"Manufacturing & Wholesale Goods"
        }
    ],
    "sg:phone":"+44 20 8665 1200",
    "sg:postcode":"CR0 4XN",
    "sg:province":"Surrey",
    "sg:tags":[
        "system",
        "air conditioning"
    ],
    "wof:name":"Controls Center",
    "wof:placetype":"venue"
},
  "geometry": {"coordinates":[-0.125764,51.367664],"type":"Point"}
}