{
  "type": "Feature",
  "properties": {
    "iso:country":"GB",
    "sg:address":"22 Woodborough Rd",
    "sg:city":"Winscombe",
    "sg:classifiers":[
        {
            "category":"Cinema",
            "subcategory":"Movie Rental",
            "type":"Entertainment"
        }
    ],
    "sg:phone":"+44 1934 844588",
    "sg:postcode":"BS25 1AD",
    "sg:province":"Somerset",
    "sg:tags":[
        "video",
        "library"
    ],
    "wof:name":"Top 10 Videos",
    "wof:placetype":"venue"
},
  "geometry": {"coordinates":[-2.832515955,51.3144035339],"type":"Point"}
}