{
  "type": "Feature",
  "properties": {
    "iso:country":"GB",
    "sg:address":"27 Mill Lane, Kingsthorpe",
    "sg:city":"Northampton",
    "sg:classifiers":[
        {
            "category":"Recreation",
            "subcategory":"Water Park",
            "type":"Entertainment"
        }
    ],
    "sg:postcode":"NN2 6RQ",
    "sg:province":"Northamptonshire",
    "sg:tags":[
        "merchant",
        "hide",
        "skin"
    ],
    "wof:name":"Anglia Shoes Ltd",
    "wof:placetype":"venue"
},
  "geometry": {"coordinates":[-0.903733,52.259514],"type":"Point"}
}