{
  "type": "Feature",
  "properties": {
    "addr:full":"Constarry Rd, Croy Kilsyth Glasgow East Dunbartonshire G65 9HY",
    "addr:postcode":"g65 9hy",
    "addr:street":"Constarry Rd",
    "iso:country":"GB",
    "sg:address":"Constarry Rd, Croy Kilsyth",
    "sg:city":"Glasgow",
    "sg:classifiers":[
        {
            "category":"Wholesale",
            "subcategory":"Construction Materials",
            "type":"Manufacturing & Wholesale Goods"
        },
        {
            "category":"Home & Garden",
            "subcategory":"Building Materials",
            "type":"Retail Goods"
        }
    ],
    "sg:phone":"+44 1236 821500",
    "sg:postcode":"G65 9HY",
    "sg:province":"East Dunbartonshire",
    "sg:tags":[
        "ready",
        "mixed",
        "mortar",
        "concrete"
    ],
    "wof:name":"Tarmac Topmix Ltd",
    "wof:placetype":"venue"
},
  "geometry": {"coordinates":[-4.0465288162,55.9610328674],"type":"Point"}
}