{
  "type": "Feature",
  "properties": {
    "addr:full":"Primrose Hill, Doddington March Cambridgeshire PE15 0SU",
    "addr:postcode":"pe15 0su",
    "addr:street":"March",
    "iso:country":"GB",
    "sg:address":"Primrose Hill, Doddington",
    "sg:city":"March",
    "sg:classifiers":[
        {
            "category":"Retail",
            "subcategory":"Auto Repair",
            "type":"Services"
        }
    ],
    "sg:phone":"+44 1354 741641",
    "sg:postcode":"PE15 0SU",
    "sg:province":"Cambridgeshire",
    "sg:tags":[
        "modification",
        "garage"
    ],
    "wof:name":"Richard Moore Engineering",
    "wof:placetype":"venue"
},
  "geometry": {"coordinates":[0.0620899983,52.4968109131],"type":"Point"}
}