{
  "type": "Feature",
  "properties": {
    "addr:full":"32 Enborne Rd Newbury Berkshire RG14 6AH",
    "addr:housenumber":"32",
    "addr:postcode":"rg14 6ah",
    "addr:street":"Enborne Rd",
    "iso:country":"GB",
    "sg:address":"32 Enborne Rd",
    "sg:city":"Newbury",
    "sg:classifiers":[
        {
            "category":"Military Area",
            "subcategory":"Air Force Base",
            "type":"Public Place"
        }
    ],
    "sg:phone":"+44 1635 30272",
    "sg:postcode":"RG14 6AH",
    "sg:province":"Berkshire",
    "sg:tags":[
        "taxi",
        "hire",
        "private"
    ],
    "wof:name":"Meridian Cars Newbury",
    "wof:placetype":"venue"
},
  "geometry": {"coordinates":[-1.3318480253,51.3957977295],"type":"Point"}
}