{
  "type": "Feature",
  "properties": {
    "addr:full":"Fabian Way, Port Tennant Swansea Neath Port Talbot SA1 8PA",
    "addr:postcode":"sa1 8pa",
    "addr:street":"Fabian Way",
    "iso:country":"GB",
    "sg:address":"Fabian Way, Port Tennant",
    "sg:city":"Swansea",
    "sg:classifiers":[
        {
            "category":"Bars & Pubs",
            "type":"Food & Drink"
        }
    ],
    "sg:phone":"+44 1792 654327",
    "sg:postcode":"SA1 8PA",
    "sg:province":"Neath Port Talbot",
    "sg:tags":[
        "pubs",
        "inn"
    ],
    "wof:name":"Daniel J Williams",
    "wof:placetype":"venue"
},
  "geometry": {"coordinates":[-3.914299,51.623692],"type":"Point"}
}