{
  "type": "Feature",
  "properties": {
    "addr:full":"Unit 16 Red House Yard, Gislingham Road Eye Suffolk IP23 8HH",
    "addr:housenumber":"unit 16",
    "addr:postcode":"ip23 8hh",
    "addr:street":"Red;Yard Gislingham Road",
    "iso:country":"GB",
    "sg:address":"Unit 16 Red House Yard, Gislingham Road",
    "sg:city":"Eye",
    "sg:classifiers":[
        {
            "category":"Shopping",
            "subcategory":"Stationery & Office Supplies",
            "type":"Retail Goods"
        },
        {
            "category":"Shopping",
            "subcategory":"Hobbies, Toys, & Games",
            "type":"Retail Goods"
        }
    ],
    "sg:phone":"+44 1379 788154",
    "sg:postcode":"IP23 8HH",
    "sg:province":"Suffolk",
    "sg:tags":[
        "equipment",
        "educational",
        "toy"
    ],
    "wof:name":"Suffolk Playworks",
    "wof:placetype":"venue"
},
  "geometry": {"coordinates":[1.14587605,52.3220710754],"type":"Point"}
}