{
  "type": "Feature",
  "properties": {
    "addr:full":"High Threave, Kirkcowan Newton Stewart Dumfries and Galloway DG8 0BU",
    "addr:postcode":"dg8 0bu",
    "addr:street":"Stewart",
    "iso:country":"GB",
    "sg:address":"High Threave, Kirkcowan",
    "sg:city":"Newton Stewart",
    "sg:classifiers":[
        {
            "category":"Farming",
            "subcategory":"Farm",
            "type":"Manufacturing & Wholesale Goods"
        }
    ],
    "sg:phone":"+44 1671 830272",
    "sg:postcode":"DG8 0BU",
    "sg:province":"Dumfries and Galloway",
    "sg:tags":[
        "mixed",
        "crop"
    ],
    "wof:name":"H & W McKie",
    "wof:placetype":"venue"
},
  "geometry": {"coordinates":[-4.6083607674,54.9165992737],"type":"Point"}
}