{
  "type": "Feature",
  "properties": {
    "iso:country":"GB",
    "sg:address":"Melbourne Road, Staunton Harold",
    "sg:city":"Ashby-de-la-zouch",
    "sg:classifiers":[
        {
            "category":"Manufacturing",
            "subcategory":"Signs",
            "type":"Manufacturing & Wholesale Goods"
        }
    ],
    "sg:postcode":"LE65 1RU",
    "sg:province":"Derbyshire",
    "sg:tags":[
        "writer"
    ],
    "wof:name":"The Sign Studio",
    "wof:placetype":"venue"
},
  "geometry": {"coordinates":[-1.4419100285,52.7855186462],"type":"Point"}
}