{
  "type": "Feature",
  "properties": {
    "addr:full":"71 New Road Gravesend Kent DA11 0AE",
    "addr:housenumber":"71",
    "addr:postcode":"da11 0ae",
    "addr:street":"New Road",
    "iso:country":"GB",
    "sg:address":"71 New Road",
    "sg:city":"Gravesend",
    "sg:classifiers":[
        {
            "category":"Food & Beverages",
            "subcategory":"Fruits & Vegetables",
            "type":"Retail Goods"
        }
    ],
    "sg:phone":"+44 1474 560650",
    "sg:postcode":"DA11 0AE",
    "sg:province":"Kent",
    "sg:tags":[
        "greengrocer"
    ],
    "wof:name":"Pick N Choose",
    "wof:placetype":"venue"
},
  "geometry": {"coordinates":[0.366216,51.442375],"type":"Point"}
}