{
  "type": "Feature",
  "properties": {
    "addr:full":"3 St John Street Chester Cheshire CH1 1DA",
    "addr:housenumber":"3",
    "addr:postcode":"ch1 1da",
    "addr:street":"St John Street",
    "iso:country":"GB",
    "sg:address":"3 St John Street",
    "sg:city":"Chester",
    "sg:classifiers":[
        {
            "category":"Bars & Pubs",
            "type":"Food & Drink"
        }
    ],
    "sg:phone":"+44 1244 323543",
    "sg:postcode":"CH1 1DA",
    "sg:province":"Cheshire",
    "sg:tags":[
        "pubs",
        "inn"
    ],
    "wof:name":"The Marlborough Arms",
    "wof:placetype":"venue"
},
  "geometry": {"coordinates":[-2.889835,53.187538],"type":"Point"}
}