{
  "type": "Feature",
  "properties": {
    "iso:country":"GB",
    "sg:address":"1 Worcester Road",
    "sg:city":"Bromsgrove",
    "sg:classifiers":[
        {
            "category":"Restaurant",
            "type":"Food & Drink"
        }
    ],
    "sg:phone":"+44 1527 875891",
    "sg:postcode":"B61 7DL",
    "sg:province":"Worcestershire",
    "sg:tags":[
        "indian"
    ],
    "wof:name":"Balti Garden",
    "wof:placetype":"venue"
},
  "geometry": {"coordinates":[-2.062419,52.333359],"type":"Point"}
}