{
  "type": "Feature",
  "properties": {
    "addr:full":"38 Cavendish Rd, Elston Pk Leicester Leicestershire LE2 7PH",
    "addr:housenumber":"38",
    "addr:postcode":"le2 7ph",
    "addr:street":"Cavendish Rd Elston Pk",
    "iso:country":"GB",
    "sg:address":"38 Cavendish Rd, Elston Pk",
    "sg:city":"Leicester",
    "sg:classifiers":[
        {
            "category":"Shopping",
            "subcategory":"News",
            "type":"Retail Goods"
        }
    ],
    "sg:postcode":"LE2 7PH",
    "sg:province":"Leicestershire",
    "sg:tags":[
        "newsagent"
    ],
    "wof:name":"Kumar,Ravinder",
    "wof:placetype":"venue"
},
  "geometry": {"coordinates":[-1.140778,52.613029],"type":"Point"}
}