{
  "type": "Feature",
  "properties": {
    "addr:full":"208 St Annes Road East Lytham St Annes Lancashire FY8 3HT",
    "addr:housenumber":"208",
    "addr:postcode":"fy8 3ht",
    "addr:street":"St Annes Road East;St",
    "iso:country":"GB",
    "sg:address":"208 St Annes Road East",
    "sg:city":"Lytham St Annes",
    "sg:classifiers":[
        {
            "category":"Building & Trades",
            "subcategory":"Construction",
            "type":"Services"
        }
    ],
    "sg:phone":"+44 1253 714907",
    "sg:postcode":"FY8 3HT",
    "sg:province":"Lancashire",
    "sg:tags":[
        "flooring"
    ],
    "wof:name":"Scandafloor Ltd.",
    "wof:placetype":"venue"
},
  "geometry": {"coordinates":[-3.009987,53.761726],"type":"Point"}
}