{
  "type": "Feature",
  "properties": {
    "iso:country":"GB",
    "sg:address":"Coley Avenue",
    "sg:city":"Woking",
    "sg:classifiers":[
        {
            "category":"Social Services",
            "subcategory":"Retirement Home",
            "type":"Services"
        }
    ],
    "sg:postcode":"GU22 7BT",
    "sg:province":"Surrey",
    "sg:tags":[
        "residential",
        "care"
    ],
    "wof:name":"The Shanty Rest Home",
    "wof:placetype":"venue"
},
  "geometry": {"coordinates":[-0.550738,51.317131],"type":"Point"}
}