{
  "type": "Feature",
  "properties": {
    "addr:full":"29 Hersham Rd Walton On Thames Surrey KT12 1LF",
    "addr:housenumber":"29",
    "addr:postcode":"kt12 1lf",
    "addr:street":"Hersham Rd",
    "iso:country":"GB",
    "sg:address":"29 Hersham Rd",
    "sg:city":"Walton On Thames",
    "sg:classifiers":[
        {
            "category":"Health Services",
            "subcategory":"Health Practitioner",
            "type":"Services"
        }
    ],
    "sg:phone":"+44 1932 252425",
    "sg:postcode":"KT12 1LF",
    "sg:province":"Surrey",
    "sg:tags":[
        "homoeopathic"
    ],
    "wof:name":"Dr A Econs",
    "wof:placetype":"venue"
},
  "geometry": {"coordinates":[-0.413382,51.380394],"type":"Point"}
}