{
  "type": "Feature",
  "properties": {
    "iso:country":"GB",
    "sg:address":"203 Springvale Road, Crookes",
    "sg:city":"Sheffield",
    "sg:classifiers":[
        {
            "category":"Building & Trades",
            "subcategory":"Construction",
            "type":"Services"
        }
    ],
    "sg:phone":"+44 114 266 5050",
    "sg:postcode":"S10 1LG",
    "sg:province":"South Yorkshire",
    "sg:tags":[
        "glass",
        "replacement"
    ],
    "wof:name":"South Yorkshire Glass Ltd.",
    "wof:placetype":"venue"
},
  "geometry": {"coordinates":[-1.497839,53.387711],"type":"Point"}
}