{
  "type": "Feature",
  "properties": {
    "addr:full":"20 Market Square Northampton Northamptonshire NN1 2DL",
    "addr:housenumber":"20",
    "addr:postcode":"nn1 2dl",
    "addr:street":"Market Square",
    "iso:country":"GB",
    "sg:address":"20 Market Square",
    "sg:city":"Northampton",
    "sg:classifiers":[
        {
            "category":"Professional",
            "subcategory":"Management & Consulting",
            "type":"Services"
        }
    ],
    "sg:phone":"+44 1604 602001",
    "sg:postcode":"NN1 2DL",
    "sg:province":"Northamptonshire",
    "sg:tags":[
        "marketing",
        "consultant"
    ],
    "wof:name":"Cedar Marketing Services Ltd.",
    "wof:placetype":"venue"
},
  "geometry": {"coordinates":[-0.896347,52.23822],"type":"Point"}
}