{
  "type": "Feature",
  "properties": {
    "iso:country":"GB",
    "sg:address":"23 Wood Pack Av, Fellside Park, Wickham",
    "sg:city":"Newcastle-upon-tyne",
    "sg:classifiers":[
        {
            "category":"Shopping",
            "subcategory":"Clothing, Apparel, & Fashions",
            "type":"Retail Goods"
        }
    ],
    "sg:phone":"+44 191 488 5499",
    "sg:postcode":"NE16 5YY",
    "sg:province":"Durham",
    "sg:tags":[
        "t-shirt"
    ],
    "wof:name":"Zicos the Magic Touch",
    "wof:placetype":"venue"
},
  "geometry": {"coordinates":[-1.6976649761,54.9393234253],"type":"Point"}
}