{
  "type": "Feature",
  "properties": {
    "addr:full":"12 Southland Close Colchester Essex CO4 0QH",
    "addr:housenumber":"12",
    "addr:postcode":"co4 0qh",
    "addr:street":"Southland Close",
    "iso:country":"GB",
    "sg:address":"12 Southland Close",
    "sg:city":"Colchester",
    "sg:classifiers":[
        {
            "category":"Home & Garden",
            "subcategory":"Carpets & Floor Coverings",
            "type":"Retail Goods"
        }
    ],
    "sg:postcode":"CO4 0QH",
    "sg:province":"Essex",
    "sg:tags":[
        "carpets",
        "rug",
        "matting"
    ],
    "wof:name":"Alan James",
    "wof:placetype":"venue"
},
  "geometry": {"coordinates":[0.924925,51.900341],"type":"Point"}
}