{
  "type": "Feature",
  "properties": {
    "addr:full":"72 Whitworth Road Northampton Northamptonshire NN1 4HJ",
    "addr:housenumber":"72",
    "addr:postcode":"nn1 4hj",
    "addr:street":"Whitworth Road",
    "iso:country":"GB",
    "sg:address":"72 Whitworth Road",
    "sg:city":"Northampton",
    "sg:classifiers":[
        {
            "category":"Professional",
            "subcategory":"Art Services",
            "type":"Services"
        },
        {
            "category":"Building & Trades",
            "subcategory":"Construction",
            "type":"Services"
        }
    ],
    "sg:phone":"+44 1604 630724",
    "sg:postcode":"NN1 4HJ",
    "sg:province":"Northamptonshire",
    "sg:tags":[
        "decorator",
        "painter"
    ],
    "wof:name":"ANTHONY MARIS",
    "wof:placetype":"venue"
},
  "geometry": {"coordinates":[-0.879281,52.243923],"type":"Point"}
}