{
  "type": "Feature",
  "properties": {
    "addr:full":"4 London Rd Morden Surrey SM4 5BQ",
    "addr:housenumber":"4",
    "addr:postcode":"sm4 5bq",
    "addr:street":"London Rd",
    "iso:country":"GB",
    "sg:address":"4 London Rd",
    "sg:city":"Morden",
    "sg:classifiers":[
        {
            "category":"Personal",
            "subcategory":"Beauty Salon",
            "type":"Services"
        }
    ],
    "sg:phone":"+44 20 8648 0891",
    "sg:postcode":"SM4 5BQ",
    "sg:province":"Surrey",
    "sg:tags":[
        "unisex",
        "hairdresser"
    ],
    "wof:name":"Changes 2",
    "wof:placetype":"venue"
},
  "geometry": {"coordinates":[-0.192259,51.403175],"type":"Point"}
}