{
  "type": "Feature",
  "properties": {
    "addr:full":"Fanshaws, Brickendon Hertford Hertfordshire SG13 8PQ",
    "addr:postcode":"sg13 8pq",
    "addr:street":"Hertford",
    "iso:country":"GB",
    "sg:address":"Fanshaws, Brickendon",
    "sg:city":"Hertford",
    "sg:classifiers":[
        {
            "category":"Wholesale",
            "subcategory":"Books, Periodicals, & Newspapers",
            "type":"Manufacturing & Wholesale Goods"
        },
        {
            "category":"Organizations",
            "subcategory":"Professional Association",
            "type":"Services"
        }
    ],
    "sg:phone":"+44 1992 511521",
    "sg:postcode":"SG13 8PQ",
    "sg:province":"Hertfordshire",
    "sg:tags":[
        "institute",
        "publishing"
    ],
    "wof:name":"Motor Industry Management Ltd",
    "wof:placetype":"venue"
},
  "geometry": {"coordinates":[-0.0842360035,51.7551956177],"type":"Point"}
}