{
  "type": "Feature",
  "properties": {
    "addr:full":"141 Hands Road Heanor Derbyshire DE75 7HD",
    "addr:housenumber":"141",
    "addr:postcode":"de75 7hd",
    "addr:street":"Hands Road",
    "iso:country":"GB",
    "sg:address":"141 Hands Road",
    "sg:city":"Heanor",
    "sg:classifiers":[
        {
            "category":"Military Area",
            "subcategory":"Air Force Base",
            "type":"Public Place"
        }
    ],
    "sg:phone":"+44 1773 716000",
    "sg:postcode":"DE75 7HD",
    "sg:province":"Derbyshire",
    "sg:tags":[
        "taxi",
        "hire",
        "private"
    ],
    "wof:name":"Premier Taxis",
    "wof:placetype":"venue"
},
  "geometry": {"coordinates":[-1.3414510489,53.0127601624],"type":"Point"}
}