{
  "type": "Feature",
  "properties": {
    "addr:full":"Saddlers Cottage, High Street, Fenny Compton Southam Warwickshire CV47 2YG",
    "addr:postcode":"cv47 2yg",
    "addr:street":"High Street",
    "iso:country":"GB",
    "sg:address":"Saddlers Cottage, High Street, Fenny Compton",
    "sg:city":"Southam",
    "sg:classifiers":[
        {
            "category":"Farming",
            "subcategory":"Livestock Farm",
            "type":"Manufacturing & Wholesale Goods"
        }
    ],
    "sg:phone":"+44 1295 770641",
    "sg:postcode":"CV47 2YG",
    "sg:province":"Warwickshire",
    "sg:tags":[
        "breeder"
    ],
    "wof:name":"Cottage Flowers",
    "wof:placetype":"venue"
},
  "geometry": {"coordinates":[-1.391019,52.16758],"type":"Point"}
}