{
  "type": "Feature",
  "properties": {
    "iso:country":"GB",
    "sg:address":"1 Waterhouse Square, 138 Holborn",
    "sg:city":"London",
    "sg:classifiers":[
        {
            "category":"Professional",
            "subcategory":"Lawyer & Legal Services",
            "type":"Services"
        }
    ],
    "sg:phone":"+44 20 7583 5522",
    "sg:postcode":"EC1N 2ST",
    "sg:province":"Greater London",
    "sg:tags":[
        "solicitor"
    ],
    "wof:name":"Jennings Son & Ash",
    "wof:placetype":"venue"
},
  "geometry": {"coordinates":[-0.10952,51.518108],"type":"Point"}
}