{
  "type": "Feature",
  "properties": {
    "iso:country":"GB",
    "sg:address":"62 Windsor Crescent, Ovingham",
    "sg:city":"Prudhoe",
    "sg:classifiers":[
        {
            "category":"Professional",
            "subcategory":"Engineering",
            "type":"Services"
        }
    ],
    "sg:postcode":"NE42 6AS",
    "sg:province":"Northumberland",
    "sg:tags":[
        "design",
        "engineer"
    ],
    "wof:name":"de-Mining Systems U K Ltd.",
    "wof:placetype":"venue"
},
  "geometry": {"coordinates":[-1.865131,54.971527],"type":"Point"}
}