{
  "type": "Feature",
  "properties": {
    "addr:full":"2 Park Mall Ashford Kent TN24 8RY",
    "addr:housenumber":"2",
    "addr:postcode":"tn24 8ry",
    "addr:street":"Park Mall",
    "iso:country":"GB",
    "sg:address":"2 Park Mall",
    "sg:city":"Ashford",
    "sg:classifiers":[
        {
            "category":"Shopping",
            "subcategory":"Clothing, Apparel, & Fashions",
            "type":"Retail Goods"
        }
    ],
    "sg:phone":"+44 1233 642626",
    "sg:postcode":"TN24 8RY",
    "sg:province":"Kent",
    "sg:tags":[
        "shop"
    ],
    "wof:name":"Next Retail",
    "wof:placetype":"venue"
},
  "geometry": {"coordinates":[0.8838989735,51.1505126953],"type":"Point"}
}