{
  "type": "Feature",
  "properties": {
    "iso:country":"GB",
    "sg:address":"2 Summit Road",
    "sg:city":"Northolt",
    "sg:classifiers":[
        {
            "category":"Travel",
            "subcategory":"Travel Agent",
            "type":"Entertainment"
        }
    ],
    "sg:phone":"+44 20 8845 7266",
    "sg:postcode":"UB5 5HJ",
    "sg:province":"Greater London",
    "wof:name":"East Africa Travels",
    "wof:placetype":"venue"
},
  "geometry": {"coordinates":[-0.364796,51.546204],"type":"Point"}
}