{
  "type": "Feature",
  "properties": {
    "addr:full":"Garth Wks, Pwllygath St, Kenfig Hill Bridgend Bridgend CF33 6ES",
    "addr:postcode":"cf33 6es",
    "addr:street":"Garth;Pwllygath St",
    "iso:country":"GB",
    "sg:address":"Garth Wks, Pwllygath St, Kenfig Hill",
    "sg:city":"Bridgend",
    "sg:classifiers":[
        {
            "category":"Professional",
            "type":"Services"
        }
    ],
    "sg:postcode":"CF33 6ES",
    "sg:province":"Bridgend",
    "sg:tags":[
        "interior",
        "furnishers",
        "designer"
    ],
    "wof:name":"Chameleon Decorative Furniture",
    "wof:placetype":"venue"
},
  "geometry": {"coordinates":[-3.6759090424,51.5333786011],"type":"Point"}
}