{
  "type": "Feature",
  "properties": {
    "iso:country":"GB",
    "sg:address":"453-454 Strand",
    "sg:city":"Holborn",
    "sg:classifiers":[
        {
            "category":"Professional",
            "subcategory":"Employment Agencies",
            "type":"Services"
        }
    ],
    "sg:phone":"+44 20 7414 4057",
    "sg:postcode":"WC2R 0RG",
    "sg:province":"Greater London",
    "sg:tags":[
        "career",
        "guidance"
    ],
    "wof:name":"Royal Navy & Royal Marines Careers Office",
    "wof:placetype":"venue"
},
  "geometry": {"coordinates":[-0.119189,51.51128],"type":"Point"}
}