{
  "type": "Feature",
  "properties": {
    "addr:full":"3 Masters Lodge, Johnson Street London Greater London E1 0BE",
    "addr:housenumber":"3",
    "addr:postcode":"e1 0be",
    "addr:street":"Masters Lodge Johnson Street",
    "iso:country":"GB",
    "sg:address":"3 Masters Lodge, Johnson Street",
    "sg:city":"London",
    "sg:classifiers":[
        {
            "category":"Professional",
            "type":"Services"
        }
    ],
    "sg:phone":"+44 20 7790 5330",
    "sg:postcode":"E1 0BE",
    "sg:province":"Greater London",
    "sg:tags":[
        "interior",
        "furnishers",
        "designer"
    ],
    "wof:name":"Interior Aspects",
    "wof:placetype":"venue"
},
  "geometry": {"coordinates":[-0.0512599982,51.511680603],"type":"Point"}
}