{
  "type": "Feature",
  "properties": {
    "iso:country":"GB",
    "sg:address":"Wimbourne Quay",
    "sg:city":"Blyth",
    "sg:classifiers":[
        {
            "category":"Freight",
            "type":"Transportation"
        }
    ],
    "sg:phone":"+44 1670 351666",
    "sg:postcode":"NE24 1PX",
    "sg:province":"Northumberland",
    "sg:tags":[
        "forwarders"
    ],
    "wof:name":"U P M-Kymmene Distribution Ltd.",
    "wof:placetype":"venue"
},
  "geometry": {"coordinates":[-1.515669,55.123665],"type":"Point"}
}