{
  "type": "Feature",
  "properties": {
    "iso:country":"GB",
    "sg:address":"211 Rayleigh Road, Hutton",
    "sg:city":"Brentwood",
    "sg:classifiers":[
        {
            "category":"Wholesale",
            "subcategory":"Electrical",
            "type":"Manufacturing & Wholesale Goods"
        },
        {
            "category":"Shopping",
            "subcategory":"Computers & Home Electronics",
            "type":"Retail Goods"
        }
    ],
    "sg:phone":"+44 1277 222372",
    "sg:postcode":"CM13 1LZ",
    "sg:province":"Essex",
    "sg:tags":[
        "wholesaler"
    ],
    "wof:name":"L C A Wholesale",
    "wof:placetype":"venue"
},
  "geometry": {"coordinates":[0.3514750004,51.6331634521],"type":"Point"}
}