{
  "type": "Feature",
  "properties": {
    "iso:country":"GB",
    "sg:address":"Marbury Works, Clarence Drive",
    "sg:city":"Filey",
    "sg:classifiers":[
        {
            "category":"Shopping",
            "subcategory":"Stationery & Office Supplies",
            "type":"Retail Goods"
        }
    ],
    "sg:phone":"+44 1723 513346",
    "sg:postcode":"YO14 0AB",
    "sg:province":"North Yorkshire",
    "sg:tags":[
        "item",
        "promotional"
    ],
    "wof:name":"Marshall Bros Ltd.",
    "wof:placetype":"venue"
},
  "geometry": {"coordinates":[-0.290749,54.211845],"type":"Point"}
}