{
  "type": "Feature",
  "properties": {
    "iso:country":"GB",
    "sg:address":"Denman Street",
    "sg:city":"Nottingham",
    "sg:classifiers":[
        {
            "category":"Education",
            "subcategory":"School",
            "type":"Public Place"
        }
    ],
    "sg:phone":"+44 115 915 5810",
    "sg:postcode":"NG7 3FL",
    "sg:province":"Nottinghamshire",
    "sg:tags":[
        "local",
        "authority"
    ],
    "wof:name":"Radford Primary School",
    "wof:placetype":"venue"
},
  "geometry": {"coordinates":[-1.168144,52.957481],"type":"Point"}
}