{
  "type": "Feature",
  "properties": {
    "iso:country":"GB",
    "sg:address":"5 Market Dew Street",
    "sg:city":"Penzance",
    "sg:classifiers":[
        {
            "category":"Travel",
            "subcategory":"Travel Agent",
            "type":"Entertainment"
        }
    ],
    "sg:phone":"+44 1736 365521",
    "sg:postcode":"TR18 2HN",
    "sg:province":"Cornwall",
    "wof:name":"Lets Go Crusing",
    "wof:placetype":"venue"
},
  "geometry": {"coordinates":[-5.5362501144,50.1190834045],"type":"Point"}
}