{
  "type": "Feature",
  "properties": {
    "addr:full":"5 Peartree Close, West Wellow Romsey Hampshire SO51 6GY",
    "addr:housenumber":"5",
    "addr:postcode":"so51 6gy",
    "addr:street":"Peartree Close West",
    "iso:country":"GB",
    "sg:address":"5 Peartree Close, West Wellow",
    "sg:city":"Romsey",
    "sg:classifiers":[
        {
            "category":"Professional",
            "subcategory":"Management & Consulting",
            "type":"Services"
        }
    ],
    "sg:phone":"+44 1794 324312",
    "sg:postcode":"SO51 6GY",
    "sg:province":"Hampshire",
    "sg:tags":[
        "consultant",
        "business"
    ],
    "wof:name":"Littleton Shaw Ltd.",
    "wof:placetype":"venue"
},
  "geometry": {"coordinates":[-1.595345,50.971745],"type":"Point"}
}