{
  "type": "Feature",
  "properties": {
    "iso:country":"GB",
    "sg:address":"Albion Ho, 25 Bridge St",
    "sg:city":"Macclesfield",
    "sg:postcode":"SK11 6EG",
    "sg:province":"Cheshire",
    "wof:name":"Southgate Thermoplastics Ltd",
    "wof:placetype":"venue"
},
  "geometry": {"coordinates":[-2.1257560253,53.2556686401],"type":"Point"}
}