{
  "type": "Feature",
  "properties": {
    "iso:country":"GB",
    "sg:address":"Holmesdale Street",
    "sg:city":"Cardiff",
    "sg:classifiers":[
        {
            "category":"Education",
            "subcategory":"School",
            "type":"Public Place"
        }
    ],
    "sg:phone":"+44 29 2022 7998",
    "sg:postcode":"CF11 7XS",
    "sg:province":"Cardiff",
    "sg:tags":[
        "local",
        "authority"
    ],
    "wof:name":"Grangetown County Junior School",
    "wof:placetype":"venue"
},
  "geometry": {"coordinates":[-3.181684,51.466942],"type":"Point"}
}