{
  "type": "Feature",
  "properties": {
    "addr:full":"St Andrews Road, C/o S O Petrolleum, Holesmouth Bristol City of Bristol BS11 9BN",
    "addr:postcode":"bs11 9bn",
    "addr:street":"St Andrews Road C;O",
    "iso:country":"GB",
    "sg:address":"St Andrews Road, C/o S O Petrolleum, Holesmouth",
    "sg:city":"Bristol",
    "sg:classifiers":[
        {
            "category":"Mining & Drilling",
            "type":"Manufacturing & Wholesale Goods"
        }
    ],
    "sg:phone":"+44 117 982 4671",
    "sg:postcode":"BS11 9BN",
    "sg:province":"City of Bristol",
    "sg:tags":[
        "oil",
        "petroleum"
    ],
    "wof:name":"P&O Trans Euro",
    "wof:placetype":"venue"
},
  "geometry": {"coordinates":[-2.698054,51.502869],"type":"Point"}
}