{
  "type": "Feature",
  "properties": {
    "addr:full":"13 King Street West Stockport Cheshire SK3 0DT",
    "addr:housenumber":"13",
    "addr:postcode":"sk3 0dt",
    "addr:street":"King Street West",
    "iso:country":"GB",
    "sg:address":"13 King Street West",
    "sg:city":"Stockport",
    "sg:classifiers":[
        {
            "category":"Home & Garden",
            "subcategory":"Home Furnishings",
            "type":"Retail Goods"
        }
    ],
    "sg:phone":"+44 161 477 4747",
    "sg:postcode":"SK3 0DT",
    "sg:province":"Cheshire",
    "sg:tags":[
        "tubing",
        "fitting"
    ],
    "wof:name":"Iddon Hydraulics Ltd.",
    "wof:placetype":"venue"
},
  "geometry": {"coordinates":[-2.1657679081,53.4061889648],"type":"Point"}
}