{
  "type": "Feature",
  "properties": {
    "addr:full":"Unit 8 Northwest Business Park, Servia Hill Leeds West Yorkshire LS6 2QH",
    "addr:housenumber":"unit 8",
    "addr:postcode":"ls6 2qh",
    "addr:street":"Northwest Business Park Servia Hill",
    "iso:country":"GB",
    "sg:address":"Unit 8 Northwest Business Park, Servia Hill",
    "sg:city":"Leeds",
    "sg:classifiers":[
        {
            "category":"Home & Garden",
            "subcategory":"Home Furnishings",
            "type":"Retail Goods"
        }
    ],
    "sg:phone":"+44 113 242 9797",
    "sg:postcode":"LS6 2QH",
    "sg:province":"West Yorkshire",
    "sg:tags":[
        "furnishers",
        "planner",
        "kitchen"
    ],
    "wof:name":"Living Design",
    "wof:placetype":"venue"
},
  "geometry": {"coordinates":[-1.54782,53.811031],"type":"Point"}
}