{
  "type": "Feature",
  "properties": {
    "addr:full":"76 Daisy Bank Road Manchester Greater Manchester M14 5GL",
    "addr:housenumber":"76",
    "addr:postcode":"m14 5gl",
    "addr:street":"Daisy Bank Road",
    "iso:country":"GB",
    "sg:address":"76 Daisy Bank Road",
    "sg:city":"Manchester",
    "sg:classifiers":[
        {
            "category":"Travel",
            "subcategory":"Hostel",
            "type":"Entertainment"
        },
        {
            "category":"Organizations",
            "subcategory":"Community Association",
            "type":"Services"
        }
    ],
    "sg:phone":"+44 161 224 5883",
    "sg:postcode":"M14 5GL",
    "sg:province":"Greater Manchester",
    "sg:tags":[
        "co-operatives",
        "housing",
        "trust",
        "society"
    ],
    "wof:name":"Christian Alliance Housing Association Ltd",
    "wof:placetype":"venue"
},
  "geometry": {"coordinates":[-2.222544,53.452286],"type":"Point"}
}