{
  "type": "Feature",
  "properties": {
    "iso:country":"GB",
    "sg:address":"20 Gathurst Lane, Shevington",
    "sg:city":"Wigan",
    "sg:classifiers":[
        {
            "category":"Food & Beverages",
            "subcategory":"Bakery",
            "type":"Retail Goods"
        }
    ],
    "sg:phone":"+44 1257 252625",
    "sg:postcode":"WN6 8HA",
    "sg:province":"Lancashire",
    "sg:tags":[
        "baker"
    ],
    "wof:name":"Greenhalgh's Craft Bakery Ltd.",
    "wof:placetype":"venue"
},
  "geometry": {"coordinates":[-2.694793,53.570282],"type":"Point"}
}