{
  "type": "Feature",
  "properties": {
    "addr:full":"Hospital Road Sevenoaks Kent TN13 3PG",
    "addr:postcode":"tn13 3pg",
    "addr:street":"Hospital Road",
    "iso:country":"GB",
    "sg:address":"Hospital Road",
    "sg:city":"Sevenoaks",
    "sg:classifiers":[
        {
            "category":"Organizations",
            "subcategory":"Non-profit Organization",
            "type":"Services"
        }
    ],
    "sg:phone":"+44 1732 465539",
    "sg:postcode":"TN13 3PG",
    "sg:province":"Kent",
    "sg:tags":[
        "organisation",
        "voluntary",
        "charity"
    ],
    "wof:name":"Spring House Family Centre",
    "wof:placetype":"venue"
},
  "geometry": {"coordinates":[0.1954970062,51.2874755859],"type":"Point"}
}