{
  "type": "Feature",
  "properties": {
    "addr:full":"Spa Rd Hockley Essex SS5 4AR",
    "addr:postcode":"ss5 4ar",
    "addr:street":"Spa Rd",
    "iso:country":"GB",
    "sg:address":"Spa Rd",
    "sg:city":"Hockley",
    "sg:classifiers":[
        {
            "category":"Health Services",
            "subcategory":"Clinic",
            "type":"Services"
        }
    ],
    "sg:phone":"+44 1702 578700",
    "sg:postcode":"SS5 4AR",
    "sg:province":"Essex",
    "sg:tags":[
        "nh"
    ],
    "wof:name":"Hockley Clinic",
    "wof:placetype":"venue"
},
  "geometry": {"coordinates":[0.658,51.602314],"type":"Point"}
}