{
  "type": "Feature",
  "properties": {
    "addr:full":"49 Fore Street Salcombe Devon TQ8 8JE",
    "addr:housenumber":"49",
    "addr:postcode":"tq8 8je",
    "addr:street":"Fore Street",
    "iso:country":"GB",
    "sg:address":"49 Fore Street",
    "sg:city":"Salcombe",
    "sg:classifiers":[
        {
            "category":"Health Services",
            "subcategory":"Dentist",
            "type":"Services"
        }
    ],
    "sg:phone":"+44 1548 842886",
    "sg:postcode":"TQ8 8JE",
    "sg:province":"Devon",
    "wof:name":"Jones & Higgs",
    "wof:placetype":"venue"
},
  "geometry": {"coordinates":[-3.76697,50.236351],"type":"Point"}
}