{
  "type": "Feature",
  "properties": {
    "iso:country":"GB",
    "sg:address":"4 Mona Terrace, Llangoed",
    "sg:city":"Beaumaris",
    "sg:classifiers":[
        {
            "category":"Home & Garden",
            "subcategory":"Building Materials",
            "type":"Retail Goods"
        },
        {
            "category":"Building & Trades",
            "subcategory":"Construction",
            "type":"Services"
        }
    ],
    "sg:phone":"+44 1248 490434",
    "sg:postcode":"LL58 8NN",
    "sg:province":"Isle of Anglesey",
    "sg:tags":[
        "dry",
        "plasterers",
        "installers",
        "builder",
        "lining",
        "insulation",
        "screeders"
    ],
    "wof:name":"Lewis Christopher Pritchard",
    "wof:placetype":"venue"
},
  "geometry": {"coordinates":[-4.0872659683,53.2949676514],"type":"Point"}
}