{
  "type": "Feature",
  "properties": {
    "iso:country":"GB",
    "sg:address":"2 Vulcan Place",
    "sg:city":"Bedlington",
    "sg:classifiers":[
        {
            "category":"Restaurant",
            "type":"Food & Drink"
        }
    ],
    "sg:phone":"+44 1670 825262",
    "sg:postcode":"NE22 5DN",
    "sg:province":"Northumberland",
    "sg:tags":[
        "-",
        "italian"
    ],
    "wof:name":"Verdi Restaurant",
    "wof:placetype":"venue"
},
  "geometry": {"coordinates":[-1.592949,55.130611],"type":"Point"}
}