{
  "type": "Feature",
  "properties": {
    "addr:full":"71 The Lynch Winscombe Somerset BS25 1AR",
    "addr:housenumber":"71",
    "addr:postcode":"bs25 1ar",
    "addr:street":"The Lynch",
    "iso:country":"GB",
    "sg:address":"71 The Lynch",
    "sg:city":"Winscombe",
    "sg:classifiers":[
        {
            "category":"Social Services",
            "subcategory":"Retirement Home",
            "type":"Services"
        },
        {
            "category":"Government",
            "subcategory":"Office",
            "type":"Public Place"
        }
    ],
    "sg:phone":"+44 1934 842068",
    "sg:postcode":"BS25 1AR",
    "sg:province":"Somerset",
    "sg:tags":[
        "central",
        "rest"
    ],
    "wof:name":"Strathmore House",
    "wof:placetype":"venue"
},
  "geometry": {"coordinates":[-2.837489,51.311611],"type":"Point"}
}