{
  "type": "Feature",
  "properties": {
    "addr:full":"Oldtown Of Kincraigie, Tarland Aboyne Aberdeenshire AB34 4SY",
    "addr:postcode":"ab34 4sy",
    "iso:country":"GB",
    "sg:address":"Oldtown Of Kincraigie, Tarland",
    "sg:city":"Aboyne",
    "sg:classifiers":[
        {
            "category":"Farming",
            "subcategory":"Livestock Farm",
            "type":"Manufacturing & Wholesale Goods"
        }
    ],
    "sg:postcode":"AB34 4SY",
    "sg:province":"Aberdeenshire",
    "sg:tags":[
        "others"
    ],
    "wof:name":"Ian Charles Anderson",
    "wof:placetype":"venue"
},
  "geometry": {"coordinates":[-2.854389,57.131126],"type":"Point"}
}