{
  "type": "Feature",
  "properties": {
    "iso:country":"GB",
    "sg:address":"Ynysybwl Road",
    "sg:city":"Pontypridd",
    "sg:classifiers":[
        {
            "category":"Retail",
            "subcategory":"Auto Repair",
            "type":"Services"
        }
    ],
    "sg:postcode":"CF37 3BL",
    "sg:province":"Caerphilly",
    "sg:tags":[
        "modification",
        "garage"
    ],
    "wof:name":"Diamond Auto Repairs",
    "wof:placetype":"venue"
},
  "geometry": {"coordinates":[-3.328398,51.623222],"type":"Point"}
}