{
  "type": "Feature",
  "properties": {
    "iso:country":"GB",
    "sg:address":"119 High St",
    "sg:city":"Stourbridge",
    "sg:classifiers":[
        {
            "category":"Personal",
            "subcategory":"Beauty Salon",
            "type":"Services"
        }
    ],
    "sg:postcode":"DY8 1EE",
    "sg:province":"Staffordshire",
    "sg:tags":[
        "lady",
        "hairdresser"
    ],
    "wof:name":"Martanne Salons Ltd",
    "wof:placetype":"venue"
},
  "geometry": {"coordinates":[-2.145478,52.456532],"type":"Point"}
}