{
  "type": "Feature",
  "properties": {
    "addr:full":"Merrielands Crescent, Ripley Road Dagenham Essex RM9 6SJ",
    "addr:postcode":"rm9 6sj",
    "addr:street":"Merrielands Crescent Ripley Road",
    "iso:country":"GB",
    "sg:address":"Merrielands Crescent, Ripley Road",
    "sg:city":"Dagenham",
    "sg:classifiers":[
        {
            "category":"Food & Beverages",
            "subcategory":"Supermarket",
            "type":"Retail Goods"
        }
    ],
    "sg:phone":"+44 20 8984 7633",
    "sg:postcode":"RM9 6SJ",
    "sg:province":"Essex",
    "wof:name":"Asda Stores Ltd.",
    "wof:placetype":"venue"
},
  "geometry": {"coordinates":[0.1461769938,51.5303001404],"type":"Point"}
}