{
  "type": "Feature",
  "properties": {
    "addr:full":"3 Lainson Street London Greater London SW18 5RS",
    "addr:housenumber":"3",
    "addr:postcode":"sw18 5rs",
    "addr:street":"Lainson Street",
    "iso:country":"GB",
    "sg:address":"3 Lainson Street",
    "sg:city":"London",
    "sg:classifiers":[
        {
            "category":"Professional",
            "type":"Services"
        }
    ],
    "sg:phone":"+44 20 8788 4004",
    "sg:postcode":"SW18 5RS",
    "sg:province":"Greater London",
    "sg:tags":[
        "writer"
    ],
    "wof:name":"Max Findlay Associates",
    "wof:placetype":"venue"
},
  "geometry": {"coordinates":[-0.2008250058,51.4486808777],"type":"Point"}
}