{
  "type": "Feature",
  "properties": {
    "addr:full":"2nd Floor, 159-163 Great Portland Street London Greater London W1W 5PA",
    "addr:housenumber":"2nd floor 159-163",
    "addr:postcode":"w1w 5pa",
    "addr:street":"Great Portland Street",
    "iso:country":"GB",
    "sg:address":"2nd Floor, 159-163 Great Portland Street",
    "sg:city":"London",
    "sg:classifiers":[
        {
            "category":"Professional",
            "subcategory":"Computer Services",
            "type":"Services"
        }
    ],
    "sg:phone":"+44 20 7637 1010",
    "sg:postcode":"W1W 5PA",
    "sg:province":"Greater London",
    "sg:tags":[
        "system",
        "software"
    ],
    "wof:name":"Primal Pictures Ltd.",
    "wof:placetype":"venue"
},
  "geometry": {"coordinates":[-0.143409,51.521389],"type":"Point"}
}