{
  "type": "Feature",
  "properties": {
    "addr:full":"Whitebirk Road Blackburn Lancashire BB1 3HY",
    "addr:postcode":"bb1 3hy",
    "addr:street":"Whitebirk Road",
    "iso:country":"GB",
    "sg:address":"Whitebirk Road",
    "sg:city":"Blackburn",
    "sg:classifiers":[
        {
            "category":"Retail",
            "subcategory":"Auto Repair",
            "type":"Services"
        }
    ],
    "sg:postcode":"BB1 3HY",
    "sg:province":"Lancashire",
    "sg:tags":[
        "car",
        "sprayer",
        "painter"
    ],
    "wof:name":"I & S Motors",
    "wof:placetype":"venue"
},
  "geometry": {"coordinates":[-2.446137,53.753288],"type":"Point"}
}