{
  "type": "Feature",
  "properties": {
    "iso:country":"GB",
    "sg:address":"6-7 Wellfield Court, Wellfield Shopping Centre",
    "sg:city":"Bangor",
    "sg:classifiers":[
        {
            "category":"Shopping",
            "subcategory":"Antiques",
            "type":"Retail Goods"
        }
    ],
    "sg:postcode":"LL57 1EL",
    "sg:province":"Gwynedd",
    "wof:name":"Wellfield Antique Centre",
    "wof:placetype":"venue"
},
  "geometry": {"coordinates":[-4.1260638237,53.2295951843],"type":"Point"}
}