{
  "type": "Feature",
  "properties": {
    "iso:country":"GB",
    "sg:address":"43 Church Street",
    "sg:city":"Berwick-upon-tweed",
    "sg:classifiers":[
        {
            "category":"Travel",
            "subcategory":"Hotels & Motels",
            "type":"Entertainment"
        }
    ],
    "sg:phone":"+44 1289 306483",
    "sg:postcode":"TD15 1EE",
    "sg:province":"Northumberland",
    "sg:tags":[
        "house",
        "guest"
    ],
    "wof:name":"Miranda Guest House",
    "wof:placetype":"venue"
},
  "geometry": {"coordinates":[-2.002334,55.77063],"type":"Point"}
}