{
  "type": "Feature",
  "properties": {
    "addr:full":"Care Of The Clinic Centre, Sandbach Road South Stoke On Trent Cheshire ST7 2LU",
    "addr:postcode":"st7 2lu",
    "addr:street":"Sandbach Road South Stoke On Trent",
    "iso:country":"GB",
    "sg:address":"Care Of The Clinic Centre, Sandbach Road South",
    "sg:city":"Stoke On Trent",
    "sg:classifiers":[
        {
            "category":"Health Services",
            "subcategory":"Clinic",
            "type":"Services"
        }
    ],
    "sg:phone":"+44 1270 873215",
    "sg:postcode":"ST7 2LU",
    "sg:province":"Cheshire",
    "sg:tags":[
        "planning",
        "family",
        "centre"
    ],
    "wof:name":"Family Planning Clinic",
    "wof:placetype":"venue"
},
  "geometry": {"coordinates":[-2.3002998829,53.093460083],"type":"Point"}
}