{
  "type": "Feature",
  "properties": {
    "iso:country":"GB",
    "sg:address":"Bentley House, The Green, Great Bentley",
    "sg:city":"Colchester",
    "sg:classifiers":[
        {
            "category":"Professional",
            "subcategory":"Art Services",
            "type":"Services"
        },
        {
            "category":"Building & Trades",
            "subcategory":"Electrical",
            "type":"Services"
        }
    ],
    "sg:phone":"+44 845 170 0017",
    "sg:postcode":"CO7 8PJ",
    "sg:province":"Essex",
    "sg:tags":[
        "consultant",
        "design",
        "lighting"
    ],
    "wof:name":"Technovations Ltd",
    "wof:placetype":"venue"
},
  "geometry": {"coordinates":[1.0649499893,51.8555107117],"type":"Point"}
}