{
  "type": "Feature",
  "properties": {
    "iso:country":"GB",
    "sg:address":"3b Woodlands Road",
    "sg:city":"Harrow",
    "sg:classifiers":[
        {
            "category":"Building & Trades",
            "subcategory":"Cleaning & Sanitation",
            "type":"Services"
        }
    ],
    "sg:phone":"+44 20 8861 6668",
    "sg:postcode":"HA1 2RT",
    "sg:province":"Greater London",
    "sg:tags":[
        "cleaner",
        "window"
    ],
    "wof:name":"Leonard Gateshill",
    "wof:placetype":"venue"
},
  "geometry": {"coordinates":[-0.331705,51.586094],"type":"Point"}
}