{
  "type": "Feature",
  "properties": {
    "addr:full":"66 Moss La Liverpool Merseyside L9 8AN",
    "addr:housenumber":"66",
    "addr:postcode":"l9 8an",
    "addr:street":"Moss La",
    "iso:country":"GB",
    "sg:address":"66 Moss La",
    "sg:city":"Liverpool",
    "sg:classifiers":[
        {
            "category":"Home & Garden",
            "subcategory":"Household Appliances",
            "type":"Retail Goods"
        }
    ],
    "sg:phone":"+44 151 521 1101",
    "sg:postcode":"L9 8AN",
    "sg:province":"Merseyside",
    "sg:tags":[
        "domestic",
        "centre"
    ],
    "wof:name":"Moss Lane Appliances",
    "wof:placetype":"venue"
},
  "geometry": {"coordinates":[-2.9689249992,53.4629707336],"type":"Point"}
}