{
  "type": "Feature",
  "properties": {
    "iso:country":"GB",
    "sg:address":"133 Newmarket",
    "sg:city":"Louth",
    "sg:classifiers":[
        {
            "category":"Bars & Pubs",
            "type":"Food & Drink"
        }
    ],
    "sg:phone":"+44 1507 605146",
    "sg:postcode":"LN11 9EG",
    "sg:province":"Lincolnshire",
    "sg:tags":[
        "pubs",
        "inn"
    ],
    "wof:name":"The Newmarket Inn",
    "wof:placetype":"venue"
},
  "geometry": {"coordinates":[0.001049,53.362614],"type":"Point"}
}