{
  "type": "Feature",
  "properties": {
    "addr:full":"61 Redbrae Road Glasgow East Dunbartonshire G66 2DE",
    "addr:housenumber":"61",
    "addr:postcode":"g66 2de",
    "addr:street":"Redbrae Road",
    "iso:country":"GB",
    "sg:address":"61 Redbrae Road",
    "sg:city":"Glasgow",
    "sg:classifiers":[
        {
            "category":"Building & Trades",
            "subcategory":"Plumbing",
            "type":"Services"
        }
    ],
    "sg:postcode":"G66 2DE",
    "sg:province":"East Dunbartonshire",
    "sg:tags":[
        "heating"
    ],
    "wof:name":"James Christie & Co",
    "wof:placetype":"venue"
},
  "geometry": {"coordinates":[-4.1438708305,55.9384155273],"type":"Point"}
}