{
  "type": "Feature",
  "properties": {
    "addr:full":"45 Wilbraham Road, Walkden Manchester Greater Manchester M28 3LJ",
    "addr:housenumber":"45",
    "addr:postcode":"m28 3lj",
    "addr:street":"Wilbraham Road",
    "iso:country":"GB",
    "sg:address":"45 Wilbraham Road, Walkden",
    "sg:city":"Manchester",
    "sg:classifiers":[
        {
            "category":"Building & Trades",
            "subcategory":"Landscaping Services",
            "type":"Services"
        }
    ],
    "sg:phone":"+44 161 702 6808",
    "sg:postcode":"M28 3LJ",
    "sg:province":"Greater Manchester",
    "sg:tags":[
        "gardening"
    ],
    "wof:name":"J & K Gardens",
    "wof:placetype":"venue"
},
  "geometry": {"coordinates":[-2.3931069374,53.524936676],"type":"Point"}
}