{
  "type": "Feature",
  "properties": {
    "addr:full":"10 Clarendon Rd Watford Hertfordshire WD17 1DY",
    "addr:housenumber":"10",
    "addr:postcode":"wd17 1dy",
    "addr:street":"Clarendon Rd",
    "iso:country":"GB",
    "sg:address":"10 Clarendon Rd",
    "sg:city":"Watford",
    "sg:classifiers":[
        {
            "category":"Retail",
            "subcategory":"Laundry & Dry Cleaning",
            "type":"Services"
        }
    ],
    "sg:phone":"+44 1923 224917",
    "sg:postcode":"WD17 1DY",
    "sg:province":"Hertfordshire",
    "sg:tags":[
        "alteration"
    ],
    "wof:name":"Deans,David A,Ltd",
    "wof:placetype":"venue"
},
  "geometry": {"coordinates":[-0.3976640105,51.6568641663],"type":"Point"}
}