{
  "type": "Feature",
  "properties": {
    "addr:full":"Summer Time, Rose Valley, Pendeen Penzance Cornwall TR19 7TS",
    "addr:postcode":"tr19 7ts",
    "iso:country":"GB",
    "sg:address":"Summer Time, Rose Valley, Pendeen",
    "sg:city":"Penzance",
    "sg:classifiers":[
        {
            "category":"Home & Garden",
            "subcategory":"Carpets & Floor Coverings",
            "type":"Retail Goods"
        }
    ],
    "sg:phone":"+44 1736 788438",
    "sg:postcode":"TR19 7TS",
    "sg:province":"Cornwall",
    "sg:tags":[
        "cleaner",
        "upholstery"
    ],
    "wof:name":"M & M Carpetcare",
    "wof:placetype":"venue"
},
  "geometry": {"coordinates":[-5.666738987,50.1510391235],"type":"Point"}
}