{
  "type": "Feature",
  "properties": {
    "addr:full":"Unit 13, Acorn Park Ind Est Castleford West Yorkshire WF10 1QX",
    "addr:housenumber":"unit 13",
    "addr:postcode":"wf10 1qx",
    "addr:street":"Acorn Park;West Yorkshire",
    "iso:country":"GB",
    "sg:address":"Unit 13, Acorn Park Ind Est",
    "sg:city":"Castleford",
    "sg:classifiers":[
        {
            "category":"Building & Trades",
            "subcategory":"Cleaning & Sanitation",
            "type":"Services"
        }
    ],
    "sg:phone":"+44 1977 603652",
    "sg:postcode":"WF10 1QX",
    "sg:province":"West Yorkshire",
    "sg:tags":[
        "blast"
    ],
    "wof:name":"Acorn Shot Blasting",
    "wof:placetype":"venue"
},
  "geometry": {"coordinates":[-1.3442080021,53.721698761],"type":"Point"}
}