{
  "type": "Feature",
  "properties": {
    "addr:full":"94 St Georges Crescent Slough Berkshire SL1 5PA",
    "addr:housenumber":"94",
    "addr:postcode":"sl1 5pa",
    "addr:street":"St Georges Crescent",
    "iso:country":"GB",
    "sg:address":"94 St Georges Crescent",
    "sg:city":"Slough",
    "sg:classifiers":[
        {
            "category":"Retail",
            "subcategory":"Driving School",
            "type":"Services"
        }
    ],
    "sg:phone":"+44 1628 661986",
    "sg:postcode":"SL1 5PA",
    "sg:province":"Berkshire",
    "wof:name":"Keith Scaife",
    "wof:placetype":"venue"
},
  "geometry": {"coordinates":[-0.653557,51.51796],"type":"Point"}
}