{
  "type": "Feature",
  "properties": {
    "addr:full":"2 Crookes Road Sheffield South Yorkshire S10 5BB",
    "addr:housenumber":"2",
    "addr:postcode":"s10 5bb",
    "addr:street":"Crookes Road",
    "iso:country":"GB",
    "sg:address":"2 Crookes Road",
    "sg:city":"Sheffield",
    "sg:classifiers":[
        {
            "category":"Retail",
            "subcategory":"Auto Repair",
            "type":"Services"
        }
    ],
    "sg:phone":"+44 114 266 5854",
    "sg:postcode":"S10 5BB",
    "sg:province":"South Yorkshire",
    "sg:tags":[
        "modification",
        "garage"
    ],
    "wof:name":"Tarrants Car Accessories",
    "wof:placetype":"venue"
},
  "geometry": {"coordinates":[-1.500518,53.377762],"type":"Point"}
}