{
  "type": "Feature",
  "properties": {
    "addr:full":"Palladium House, 139-141 Worcester Road Stourbridge West Midlands DY9 0NW",
    "addr:housenumber":"139-141",
    "addr:postcode":"dy9 0nw",
    "addr:street":"Worcester Road",
    "iso:country":"GB",
    "sg:address":"Palladium House, 139-141 Worcester Road",
    "sg:city":"Stourbridge",
    "sg:classifiers":[
        {
            "category":"Professional",
            "subcategory":"Accounting & Tax Preparation",
            "type":"Services"
        }
    ],
    "sg:phone":"+44 1562 886532",
    "sg:postcode":"DY9 0NW",
    "sg:province":"West Midlands",
    "sg:tags":[
        "accountant"
    ],
    "wof:name":"Greenfield & Co",
    "wof:placetype":"venue"
},
  "geometry": {"coordinates":[-2.1433060169,52.4209632874],"type":"Point"}
}