{
  "type": "Feature",
  "properties": {
    "iso:country":"GB",
    "sg:address":"Birmingham Business Centre, 272 Montgomery Street",
    "sg:city":"Birmingham",
    "sg:classifiers":[
        {
            "category":"Arts & Performance",
            "subcategory":"Theater",
            "type":"Entertainment"
        },
        {
            "category":"Professional",
            "subcategory":"Computer Services",
            "type":"Services"
        }
    ],
    "sg:postcode":"B11 1DS",
    "sg:province":"West Midlands",
    "sg:tags":[
        "theatrical",
        "agency",
        "system",
        "software"
    ],
    "wof:name":"Slapdash Systems Solutions",
    "wof:placetype":"venue"
},
  "geometry": {"coordinates":[-1.9086040258,52.4785957336],"type":"Point"}
}