{
  "type": "Feature",
  "properties": {
    "iso:country":"GB",
    "sg:address":"The Barracks, White Cross Ind Est",
    "sg:city":"Lancaster",
    "sg:classifiers":[
        {
            "category":"Manufacturing",
            "subcategory":"Rubber & Plastics",
            "type":"Manufacturing & Wholesale Goods"
        }
    ],
    "sg:phone":"+44 1524 36425",
    "sg:postcode":"LA1 4XQ",
    "sg:province":"Lancashire",
    "sg:tags":[
        "product"
    ],
    "wof:name":"Tarkett Folien GMBH",
    "wof:placetype":"venue"
},
  "geometry": {"coordinates":[-2.799029,54.044537],"type":"Point"}
}