{
  "type": "Feature",
  "properties": {
    "addr:full":"Close Farm, Shipton Moyne Tetbury Gloucestershire GL8 8PH",
    "addr:housenumber":"moyne",
    "addr:postcode":"gl8 8ph",
    "iso:country":"GB",
    "sg:address":"Close Farm, Shipton Moyne",
    "sg:city":"Tetbury",
    "sg:classifiers":[
        {
            "category":"Farming",
            "subcategory":"Livestock Farm",
            "type":"Manufacturing & Wholesale Goods"
        }
    ],
    "sg:phone":"+44 1666 502452",
    "sg:postcode":"GL8 8PH",
    "sg:province":"Gloucestershire",
    "sg:tags":[
        "others"
    ],
    "wof:name":"John Hodges Transport",
    "wof:placetype":"venue"
},
  "geometry": {"coordinates":[-2.1609759331,51.6378593445],"type":"Point"}
}