{
  "type": "Feature",
  "properties": {
    "iso:country":"GB",
    "sg:address":"31 Market Hall",
    "sg:city":"Chesterfield",
    "sg:classifiers":[
        {
            "category":"Food & Beverages",
            "subcategory":"Dairy",
            "type":"Retail Goods"
        }
    ],
    "sg:postcode":"S40 1AR",
    "sg:province":"Derbyshire",
    "sg:tags":[
        "produce"
    ],
    "wof:name":"R P Davidson Cheese Factors",
    "wof:placetype":"venue"
},
  "geometry": {"coordinates":[-1.429579,53.235661],"type":"Point"}
}