{
  "type": "Feature",
  "properties": {
    "addr:full":"30 Crescent Road Fareham Hampshire PO16 0HG",
    "addr:housenumber":"30",
    "addr:postcode":"po16 0hg",
    "addr:street":"Crescent Road",
    "iso:country":"GB",
    "sg:address":"30 Crescent Road",
    "sg:city":"Fareham",
    "sg:classifiers":[
        {
            "category":"Building & Trades",
            "subcategory":"Construction",
            "type":"Services"
        }
    ],
    "sg:phone":"+44 1329 230317",
    "sg:postcode":"PO16 0HG",
    "sg:province":"Hampshire",
    "sg:tags":[
        "builder"
    ],
    "wof:name":"Smith Brothers",
    "wof:placetype":"venue"
},
  "geometry": {"coordinates":[-1.186103,50.851871],"type":"Point"}
}