{
  "type": "Feature",
  "properties": {
    "iso:country":"GB",
    "sg:address":"Waterloo Road, Penygroes",
    "sg:city":"Llanelli",
    "sg:classifiers":[
        {
            "category":"Arena",
            "subcategory":"Sports Club",
            "type":"Entertainment"
        }
    ],
    "sg:phone":"+44 1269 842575",
    "sg:postcode":"SA14 7NP",
    "sg:province":"Carmarthenshire",
    "wof:name":"Penygroes Rugby Football Club",
    "wof:placetype":"venue"
},
  "geometry": {"coordinates":[-4.049074,51.79657],"type":"Point"}
}