{
  "type": "Feature",
  "properties": {
    "iso:country":"GB",
    "sg:address":"22 Dewyk Road",
    "sg:city":"Canvey Island",
    "sg:classifiers":[
        {
            "category":"Professional",
            "type":"Services"
        }
    ],
    "sg:phone":"+44 1268 680988",
    "sg:postcode":"SS8 8BD",
    "sg:province":"Essex",
    "sg:tags":[
        "entertainer"
    ],
    "wof:name":"Professor Rainbow",
    "wof:placetype":"venue"
},
  "geometry": {"coordinates":[0.596523,51.527283],"type":"Point"}
}