{
  "type": "Feature",
  "properties": {
    "addr:full":"1034a Coventry Rd Birmingham West Midlands B25 8DP",
    "addr:housenumber":"1034a",
    "addr:postcode":"b25 8dp",
    "addr:street":"Coventry Rd",
    "iso:country":"GB",
    "sg:address":"1034a Coventry Rd",
    "sg:city":"Birmingham",
    "sg:classifiers":[
        {
            "category":"Professional",
            "subcategory":"Engineering",
            "type":"Services"
        }
    ],
    "sg:postcode":"B25 8DP",
    "sg:province":"West Midlands",
    "sg:tags":[
        "precision",
        "engineer"
    ],
    "wof:name":"J & E Engineering",
    "wof:placetype":"venue"
},
  "geometry": {"coordinates":[-1.8362569809,52.4638214111],"type":"Point"}
}