{
  "type": "Feature",
  "properties": {
    "iso:country":"GB",
    "sg:address":"Unit 5, Maplehurst Close, Hot Lane Industrial Estate",
    "sg:city":"Stoke-on-trent",
    "sg:classifiers":[
        {
            "category":"Professional",
            "subcategory":"Engineering",
            "type":"Services"
        }
    ],
    "sg:postcode":"ST6 2EJ",
    "sg:province":"Staffordshire",
    "sg:tags":[
        "contractor",
        "electrical",
        "engineer"
    ],
    "wof:name":"Engineering Services (Stoke-on-Trent) Ltd.",
    "wof:placetype":"venue"
},
  "geometry": {"coordinates":[-2.1835091114,53.0440216064],"type":"Point"}
}