{
  "type": "Feature",
  "properties": {
    "iso:country":"GB",
    "sg:address":"Unit30 Neath Abbey Business Park, Neath Abbey",
    "sg:city":"Neath",
    "sg:classifiers":[
        {
            "category":"Organizations",
            "subcategory":"Professional Association",
            "type":"Services"
        }
    ],
    "sg:postcode":"SA10 7DR",
    "sg:province":"Neath Port Talbot",
    "sg:tags":[
        "tech",
        "system",
        "automation"
    ],
    "wof:name":"R + R Automation Ltd",
    "wof:placetype":"venue"
},
  "geometry": {"coordinates":[-3.827755,51.66708],"type":"Point"}
}