{
  "type": "Feature",
  "properties": {
    "addr:full":"7 Sipson Lane Hayes Greater London UB3 5EH",
    "addr:housenumber":"7",
    "addr:postcode":"ub3 5eh",
    "addr:street":"Sipson Lane",
    "iso:country":"GB",
    "sg:address":"7 Sipson Lane",
    "sg:city":"Hayes",
    "sg:classifiers":[
        {
            "category":"Shopping",
            "subcategory":"Stationery & Office Supplies",
            "type":"Retail Goods"
        }
    ],
    "sg:phone":"+44 20 8897 0414",
    "sg:postcode":"UB3 5EH",
    "sg:province":"Greater London",
    "sg:tags":[
        "box",
        "carton"
    ],
    "wof:name":"Komfort Office Crate Hire",
    "wof:placetype":"venue"
},
  "geometry": {"coordinates":[-0.436409,51.487782],"type":"Point"}
}