{
  "type": "Feature",
  "properties": {
    "iso:country":"GB",
    "sg:address":"Lime Cottage",
    "sg:city":"Barnstaple",
    "sg:classifiers":[
        {
            "category":"Manufacturing",
            "subcategory":"Rubber & Plastics",
            "type":"Manufacturing & Wholesale Goods"
        },
        {
            "category":"Shopping",
            "subcategory":"Discount & Variety Stores",
            "type":"Retail Goods"
        }
    ],
    "sg:phone":"+44 1271 858732",
    "sg:postcode":"EX31 3JS",
    "sg:province":"Devon",
    "sg:tags":[
        "supplier",
        "cleaning",
        "stockist",
        "supply"
    ],
    "wof:name":"South West Rubber & Plastics",
    "wof:placetype":"venue"
},
  "geometry": {"coordinates":[-4.07275,51.01638],"type":"Point"}
}