{
  "type": "Feature",
  "properties": {
    "iso:country":"GB",
    "sg:address":"Unit 4 Gravelly Drive",
    "sg:city":"Newport",
    "sg:classifiers":[
        {
            "category":"Retail",
            "subcategory":"Laundry & Dry Cleaning",
            "type":"Services"
        }
    ],
    "sg:phone":"+44 1952 810479",
    "sg:postcode":"TF10 7QN",
    "sg:province":"Shropshire",
    "sg:tags":[
        "launderette"
    ],
    "wof:name":"Morgan Building Co",
    "wof:placetype":"venue"
},
  "geometry": {"coordinates":[-2.381085,52.767673],"type":"Point"}
}