{
  "type": "Feature",
  "properties": {
    "addr:full":"Digital, President Park Sheffield South Yorkshire S4 7UR",
    "addr:postcode":"s4 7ur",
    "addr:street":"President Park",
    "iso:country":"GB",
    "sg:address":"Digital, President Park",
    "sg:city":"Sheffield",
    "sg:classifiers":[
        {
            "category":"Utilities",
            "subcategory":"Telephone",
            "type":"Services"
        },
        {
            "category":"Shopping",
            "subcategory":"Computers & Home Electronics",
            "type":"Retail Goods"
        }
    ],
    "sg:phone":"+44 114 221 2000",
    "sg:postcode":"S4 7UR",
    "sg:province":"South Yorkshire",
    "sg:tags":[
        "consumables",
        "telecommunication"
    ],
    "wof:name":"Digital Exchange (Yorkshire) Ltd.",
    "wof:placetype":"venue"
},
  "geometry": {"coordinates":[-1.447539,53.393848],"type":"Point"}
}