{
  "type": "Feature",
  "properties": {
    "iso:country":"GB",
    "sg:address":"543 Lion Works, Wallisdown Rd, Parkstone",
    "sg:city":"Poole",
    "sg:classifiers":[
        {
            "category":"Professional",
            "subcategory":"Management & Consulting",
            "type":"Services"
        }
    ],
    "sg:phone":"+44 1202 537373",
    "sg:postcode":"BH12 5AD",
    "sg:province":"Dorset",
    "sg:tags":[
        "consultant"
    ],
    "wof:name":"Prepay Telephone Co",
    "wof:placetype":"venue"
},
  "geometry": {"coordinates":[-1.9279299974,50.7518997192],"type":"Point"}
}