{
  "type": "Feature",
  "properties": {
    "iso:country":"GB",
    "sg:address":"Walton Grounds",
    "sg:city":"Banbury",
    "sg:classifiers":[
        {
            "category":"Farming",
            "subcategory":"Livestock Farm",
            "type":"Manufacturing & Wholesale Goods"
        }
    ],
    "sg:phone":"+44 1295 811210",
    "sg:postcode":"OX17 3QW",
    "sg:province":"Northamptonshire",
    "sg:tags":[
        "others"
    ],
    "wof:name":"Twyford Farms Ltd.",
    "wof:placetype":"venue"
},
  "geometry": {"coordinates":[-1.307292,52.02243],"type":"Point"}
}