{
  "type": "Feature",
  "properties": {
    "addr:full":"7a Hartington Rd Aberdeen Aberdeen City AB10 6XT",
    "addr:housenumber":"7a",
    "addr:postcode":"ab10 6xt",
    "addr:street":"Hartington Rd",
    "iso:country":"GB",
    "sg:address":"7a Hartington Rd",
    "sg:city":"Aberdeen",
    "sg:classifiers":[
        {
            "category":"Professional",
            "subcategory":"Printing & Photocopies",
            "type":"Services"
        }
    ],
    "sg:phone":"+44 1224 590502",
    "sg:postcode":"AB10 6XT",
    "sg:province":"Aberdeen City",
    "sg:tags":[
        "process",
        "screen",
        "printer"
    ],
    "wof:name":"Clarke Graphics",
    "wof:placetype":"venue"
},
  "geometry": {"coordinates":[-2.122079,57.14119],"type":"Point"}
}