{
  "type": "Feature",
  "properties": {
    "addr:full":"84b Berners St Leicester Leicestershire LE2 0FS",
    "addr:housenumber":"84b",
    "addr:postcode":"le2 0fs",
    "addr:street":"Berners St",
    "iso:country":"GB",
    "sg:address":"84b Berners St",
    "sg:city":"Leicester",
    "sg:classifiers":[
        {
            "category":"Food & Beverages",
            "subcategory":"Groceries & Convenience Stores",
            "type":"Retail Goods"
        }
    ],
    "sg:phone":"+44 116 212 4025",
    "sg:postcode":"LE2 0FS",
    "sg:province":"Leicestershire",
    "wof:name":"Hafsa Grocers",
    "wof:placetype":"venue"
},
  "geometry": {"coordinates":[-1.113402009,52.6344604492],"type":"Point"}
}