{
  "type": "Feature",
  "properties": {
    "addr:full":"Meehanite Business Park, 38 Albert Road North Reigate Surrey RH2 9EG",
    "addr:housenumber":"38",
    "addr:postcode":"rh2 9eg",
    "addr:street":"Albert Road North Reigate",
    "iso:country":"GB",
    "sg:address":"Meehanite Business Park, 38 Albert Road North",
    "sg:city":"Reigate",
    "sg:classifiers":[
        {
            "category":"Professional",
            "subcategory":"Business Services",
            "type":"Services"
        }
    ],
    "sg:phone":"+44 1737 223030",
    "sg:postcode":"RH2 9EG",
    "sg:province":"Surrey",
    "sg:tags":[
        "tile",
        "stockist"
    ],
    "wof:name":"The Extra Special Tile Co",
    "wof:placetype":"venue"
},
  "geometry": {"coordinates":[-0.2047789991,51.2357444763],"type":"Point"}
}