{
  "type": "Feature",
  "properties": {
    "iso:country":"GB",
    "sg:address":"85 Gunnersbury Lane, Acton",
    "sg:city":"London",
    "sg:classifiers":[
        {
            "category":"Retail",
            "subcategory":"Auto Repair",
            "type":"Services"
        }
    ],
    "sg:postcode":"W3 8HH",
    "sg:province":"Greater London",
    "sg:tags":[
        "modification",
        "garage"
    ],
    "wof:name":"Acton Town Garage Ltd.",
    "wof:placetype":"venue"
},
  "geometry": {"coordinates":[-0.2794179916,51.5042533875],"type":"Point"}
}