{
  "type": "Feature",
  "properties": {
    "iso:country":"GB",
    "sg:address":"57 Anmore Rd",
    "sg:city":"Waterlooville",
    "sg:classifiers":[
        {
            "category":"Social Services",
            "subcategory":"Retirement Home",
            "type":"Services"
        }
    ],
    "sg:phone":"+44 23 9225 0766",
    "sg:postcode":"PO7 6NT",
    "sg:province":"Hampshire",
    "sg:tags":[
        "residential",
        "care"
    ],
    "wof:name":"Ashburton Cottage",
    "wof:placetype":"venue"
},
  "geometry": {"coordinates":[-1.0596050024,50.9030799866],"type":"Point"}
}