{
  "type": "Feature",
  "properties": {
    "iso:country":"GB",
    "sg:address":"Suite 7 Vincent Ho, 136 Westgate",
    "sg:city":"Wakefield",
    "sg:classifiers":[
        {
            "category":"Professional",
            "subcategory":"Lawyer & Legal Services",
            "type":"Services"
        }
    ],
    "sg:phone":"+44 1924 360880",
    "sg:postcode":"WF2 9SR",
    "sg:province":"West Yorkshire",
    "sg:tags":[
        "advice",
        "counselling"
    ],
    "wof:name":"Mind Matters",
    "wof:placetype":"venue"
},
  "geometry": {"coordinates":[-1.5212470293,53.6819534302],"type":"Point"}
}