{
  "type": "Feature",
  "properties": {
    "iso:country":"GB",
    "sg:address":"Inwood Avenue",
    "sg:city":"Hounslow",
    "sg:classifiers":[
        {
            "category":"Social Services",
            "subcategory":"Adult Care",
            "type":"Services"
        }
    ],
    "sg:phone":"+44 20 8570 0347",
    "sg:postcode":"TW3 1XF",
    "sg:province":"Greater London",
    "sg:tags":[
        "housing",
        "sheltered"
    ],
    "wof:name":"The Everglades",
    "wof:placetype":"venue"
},
  "geometry": {"coordinates":[-0.356248,51.468201],"type":"Point"}
}