{
  "type": "Feature",
  "properties": {
    "addr:full":"Environment Centre, Market Place, Somercotes Alfreton Derbyshire DE55 4HT",
    "addr:postcode":"de55 4ht",
    "addr:street":"Market Place",
    "iso:country":"GB",
    "sg:address":"Environment Centre, Market Place, Somercotes",
    "sg:city":"Alfreton",
    "sg:classifiers":[
        {
            "category":"Arts & Performance",
            "subcategory":"Theater",
            "type":"Entertainment"
        }
    ],
    "sg:phone":"+44 1773 540962",
    "sg:postcode":"DE55 4HT",
    "sg:province":"Derbyshire",
    "sg:tags":[
        "theatrical",
        "presentation",
        "theatre"
    ],
    "wof:name":"Oddsocks Production",
    "wof:placetype":"venue"
},
  "geometry": {"coordinates":[-1.371069,53.080761],"type":"Point"}
}