{
  "type": "Feature",
  "properties": {
    "iso:country":"GB",
    "sg:address":"Hudson Street",
    "sg:city":"Leeds",
    "sg:classifiers":[
        {
            "category":"Building & Trades",
            "subcategory":"Construction",
            "type":"Services"
        }
    ],
    "sg:phone":"+44 113 248 7238",
    "sg:postcode":"LS9 6EL",
    "sg:province":"West Yorkshire",
    "sg:tags":[
        "roofing"
    ],
    "wof:name":"Lionsden Ltd.",
    "wof:placetype":"venue"
},
  "geometry": {"coordinates":[-1.5084340572,53.8046684265],"type":"Point"}
}