{
  "type": "Feature",
  "properties": {
    "addr:full":"38-40 Stonehills House Welwyn Garden City Hertfordshire AL8 6NH",
    "addr:housenumber":"38-40",
    "addr:postcode":"al8 6nh",
    "addr:street":"Stonehills House Welwyn",
    "iso:country":"GB",
    "sg:address":"38-40 Stonehills House",
    "sg:city":"Welwyn Garden City",
    "sg:classifiers":[
        {
            "category":"Banks & Credit Unions",
            "subcategory":"Financial Services",
            "type":"Services"
        }
    ],
    "sg:postcode":"AL8 6NH",
    "sg:province":"Hertfordshire",
    "sg:tags":[
        "adviser"
    ],
    "wof:name":"Chiltern Financial Consultants",
    "wof:placetype":"venue"
},
  "geometry": {"coordinates":[-0.2057480067,51.8018035889],"type":"Point"}
}