{
  "type": "Feature",
  "properties": {
    "addr:full":"Fair Close, Copyhold Lane, Cuckfield Haywards Heath East Sussex RH17 5EB",
    "addr:postcode":"rh17 5eb",
    "addr:street":"Fair Close Copyhold Lane",
    "iso:country":"GB",
    "sg:address":"Fair Close, Copyhold Lane, Cuckfield",
    "sg:city":"Haywards Heath",
    "sg:classifiers":[
        {
            "category":"Professional",
            "subcategory":"Management & Consulting",
            "type":"Services"
        }
    ],
    "sg:postcode":"RH17 5EB",
    "sg:province":"East Sussex",
    "sg:tags":[
        "consultant",
        "business"
    ],
    "wof:name":"Optimum Consultants Ltd.",
    "wof:placetype":"venue"
},
  "geometry": {"coordinates":[-0.1406289935,51.0108146667],"type":"Point"}
}