{
  "type": "Feature",
  "properties": {
    "iso:country":"GB",
    "sg:address":"97 Findowrie Street",
    "sg:city":"Dundee",
    "sg:classifiers":[
        {
            "category":"Building & Trades",
            "subcategory":"Construction",
            "type":"Services"
        }
    ],
    "sg:phone":"+44 1382 501440",
    "sg:postcode":"DD4 9NJ",
    "sg:province":"Dundee City",
    "sg:tags":[
        "builder",
        "contractor"
    ],
    "wof:name":"Blair Construction Services Ltd.",
    "wof:placetype":"venue"
},
  "geometry": {"coordinates":[-2.9331760406,56.4925727844],"type":"Point"}
}