{
  "type": "Feature",
  "properties": {
    "iso:country":"GB",
    "sg:address":"54-56 Rawmarsh Hill, Parkgate",
    "sg:city":"Rotherham",
    "sg:classifiers":[
        {
            "category":"Professional",
            "subcategory":"Art Services",
            "type":"Services"
        }
    ],
    "sg:phone":"+44 1709 522070",
    "sg:postcode":"S62 6EU",
    "sg:province":"South Yorkshire",
    "sg:tags":[
        "photographer"
    ],
    "wof:name":"Westfield Photography",
    "wof:placetype":"venue"
},
  "geometry": {"coordinates":[-1.3440339565,53.4552192688],"type":"Point"}
}