{
  "type": "Feature",
  "properties": {
    "addr:full":"37 Howland Peterborough Cambridgeshire PE2 5QY",
    "addr:housenumber":"37",
    "addr:postcode":"pe2 5qy",
    "addr:street":"Howland Peterborough",
    "iso:country":"GB",
    "sg:address":"37 Howland",
    "sg:city":"Peterborough",
    "sg:classifiers":[
        {
            "category":"Home & Garden",
            "subcategory":"Household Appliances",
            "type":"Retail Goods"
        },
        {
            "category":"Building & Trades",
            "subcategory":"Plumbing",
            "type":"Services"
        }
    ],
    "sg:phone":"+44 1733 238195",
    "sg:postcode":"PE2 5QY",
    "sg:province":"Cambridgeshire",
    "sg:tags":[
        "central",
        "gas",
        "heating"
    ],
    "wof:name":"Dial A Plumber",
    "wof:placetype":"venue"
},
  "geometry": {"coordinates":[-0.287258,52.543121],"type":"Point"}
}