{
  "type": "Feature",
  "properties": {
    "addr:full":"Suite F, 4 Golden Sq Aberdeen Aberdeen City AB10 1RD",
    "addr:housenumber":"4",
    "addr:postcode":"ab10 1rd",
    "addr:street":"Golden Sq",
    "iso:country":"GB",
    "sg:address":"Suite F, 4 Golden Sq",
    "sg:city":"Aberdeen",
    "sg:classifiers":[
        {
            "category":"Professional",
            "subcategory":"Employment Agencies",
            "type":"Services"
        }
    ],
    "sg:postcode":"AB10 1RD",
    "sg:province":"Aberdeen City",
    "sg:tags":[
        "modelling"
    ],
    "wof:name":"Dual Productions",
    "wof:placetype":"venue"
},
  "geometry": {"coordinates":[-2.10416,57.145962],"type":"Point"}
}