{
  "type": "Feature",
  "properties": {
    "addr:full":"Tall Ash Farm, Buxton Road Congleton Cheshire CW12 2DY",
    "addr:postcode":"cw12 2dy",
    "addr:street":"Tall Ash;Buxton Road",
    "iso:country":"GB",
    "sg:address":"Tall Ash Farm, Buxton Road",
    "sg:city":"Congleton",
    "sg:classifiers":[
        {
            "category":"Farming",
            "subcategory":"Livestock Farm",
            "type":"Manufacturing & Wholesale Goods"
        }
    ],
    "sg:phone":"+44 1260 273168",
    "sg:postcode":"CW12 2DY",
    "sg:province":"Cheshire",
    "sg:tags":[
        "others"
    ],
    "wof:name":"J A & P A Hudson",
    "wof:placetype":"venue"
},
  "geometry": {"coordinates":[-2.1899631023,53.1711387634],"type":"Point"}
}