{
  "type": "Feature",
  "properties": {
    "addr:full":"46 Broom Street, Great Cornard Sudbury Essex CO10 0JT",
    "addr:housenumber":"46",
    "addr:postcode":"co10 0jt",
    "addr:street":"Broom Street",
    "iso:country":"GB",
    "sg:address":"46 Broom Street, Great Cornard",
    "sg:city":"Sudbury",
    "sg:classifiers":[
        {
            "category":"Retail",
            "subcategory":"Driving School",
            "type":"Services"
        }
    ],
    "sg:phone":"+44 1787 371873",
    "sg:postcode":"CO10 0JT",
    "sg:province":"Essex",
    "wof:name":"Cornard School Of Motoring",
    "wof:placetype":"venue"
},
  "geometry": {"coordinates":[0.749114,52.02821],"type":"Point"}
}