{
  "type": "Feature",
  "properties": {
    "iso:country":"GB",
    "sg:address":"29 Cochran Street",
    "sg:city":"Paisley",
    "sg:classifiers":[
        {
            "category":"Shopping",
            "subcategory":"Crafts & Fabrics",
            "type":"Retail Goods"
        },
        {
            "category":"Building & Trades",
            "subcategory":"Construction",
            "type":"Services"
        }
    ],
    "sg:phone":"+44 141 889 6087",
    "sg:postcode":"PA1 1JY",
    "sg:province":"Renfrewshire",
    "sg:tags":[
        "paint",
        "household",
        "outlet",
        "spraying",
        "centre"
    ],
    "wof:name":"Pots Of Fun Hobby Ceramics Workshop",
    "wof:placetype":"venue"
},
  "geometry": {"coordinates":[-4.414782,55.845013],"type":"Point"}
}