{
  "type": "Feature",
  "properties": {
    "addr:full":"10 Chatsworth Place, Longthorpe Peterborough Cambridgeshire PE3 9NP",
    "addr:housenumber":"10",
    "addr:postcode":"pe3 9np",
    "addr:street":"Chatsworth Place",
    "iso:country":"GB",
    "sg:address":"10 Chatsworth Place, Longthorpe",
    "sg:city":"Peterborough",
    "sg:classifiers":[
        {
            "category":"Professional",
            "subcategory":"Management & Consulting",
            "type":"Services"
        }
    ],
    "sg:phone":"+44 1733 331341",
    "sg:postcode":"PE3 9NP",
    "sg:province":"Cambridgeshire",
    "sg:tags":[
        "project"
    ],
    "wof:name":"PLANACTIV (PROJECTS) LTD",
    "wof:placetype":"venue"
},
  "geometry": {"coordinates":[-0.279087,52.575417],"type":"Point"}
}