{
  "type": "Feature",
  "properties": {
    "iso:country":"GB",
    "sg:address":"57 Chorley New Rd",
    "sg:city":"Bolton",
    "sg:classifiers":[
        {
            "category":"Health Services",
            "subcategory":"Doctor",
            "type":"Services"
        }
    ],
    "sg:phone":"+44 1204 523270",
    "sg:postcode":"BL1 4QR",
    "sg:province":"Lancashire",
    "sg:tags":[
        "practitioners"
    ],
    "wof:name":"Lane, P J",
    "wof:placetype":"venue"
},
  "geometry": {"coordinates":[-2.443631,53.581776],"type":"Point"}
}