{
  "type": "Feature",
  "properties": {
    "iso:country":"GB",
    "sg:address":"16 Holderness Road",
    "sg:city":"Hull",
    "sg:classifiers":[
        {
            "category":"Professional",
            "subcategory":"Business Services",
            "type":"Services"
        },
        {
            "category":"Professional",
            "subcategory":"Printing & Photocopies",
            "type":"Services"
        }
    ],
    "sg:phone":"+44 1482 212138",
    "sg:postcode":"HU9 1EG",
    "sg:province":"East Riding of Yorkshire",
    "sg:tags":[
        "trophy",
        "import",
        "export",
        "agent"
    ],
    "wof:name":"Sports Trophies K & E K",
    "wof:placetype":"venue"
},
  "geometry": {"coordinates":[-0.321299,53.748901],"type":"Point"}
}