{
  "type": "Feature",
  "properties": {
    "iso:country":"GB",
    "sg:address":"Grenadier House, Eagle Court, Preston Farm",
    "sg:city":"Stockton-on-tees",
    "sg:classifiers":[
        {
            "category":"Communications",
            "type":"Services"
        },
        {
            "category":"Shopping",
            "subcategory":"Discount & Variety Stores",
            "type":"Retail Goods"
        }
    ],
    "sg:phone":"+44 1642 608608",
    "sg:postcode":"TS18 3TB",
    "sg:province":"Durham",
    "sg:tags":[
        "supply",
        "cleaning",
        "audio-visual"
    ],
    "wof:name":"Greenham Video",
    "wof:placetype":"venue"
},
  "geometry": {"coordinates":[-1.3294240236,54.5436058044],"type":"Point"}
}