{
  "type": "Feature",
  "properties": {
    "addr:full":"36 Station Road Shotts North Lanarkshire ML7 5DS",
    "addr:housenumber":"36",
    "addr:postcode":"ml7 5ds",
    "addr:street":"Station Road",
    "iso:country":"GB",
    "sg:address":"36 Station Road",
    "sg:city":"Shotts",
    "sg:classifiers":[
        {
            "category":"Health Services",
            "subcategory":"Doctor",
            "type":"Services"
        }
    ],
    "sg:phone":"+44 1501 823001",
    "sg:postcode":"ML7 5DS",
    "sg:province":"North Lanarkshire",
    "sg:tags":[
        "practitioners"
    ],
    "wof:name":"M A Muqit Surgery",
    "wof:placetype":"venue"
},
  "geometry": {"coordinates":[-3.790999,55.81797],"type":"Point"}
}