{
  "type": "Feature",
  "properties": {
    "addr:full":"46 Lammermoor Terrace Tranent East Lothian EH33 1NJ",
    "addr:housenumber":"46",
    "addr:postcode":"eh33 1nj",
    "addr:street":"Lammermoor Terrace",
    "iso:country":"GB",
    "sg:address":"46 Lammermoor Terrace",
    "sg:city":"Tranent",
    "sg:classifiers":[
        {
            "category":"Education",
            "subcategory":"School",
            "type":"Public Place"
        }
    ],
    "sg:postcode":"EH33 1NJ",
    "sg:province":"East Lothian",
    "sg:tags":[
        "local",
        "authority"
    ],
    "wof:name":"Gap Training Ltd",
    "wof:placetype":"venue"
},
  "geometry": {"coordinates":[-2.9651660919,55.9442558289],"type":"Point"}
}