{
  "type": "Feature",
  "properties": {
    "addr:full":"6 Chudleigh Road London Greater London SE4 1JW",
    "addr:housenumber":"6",
    "addr:postcode":"se4 1jw",
    "addr:street":"Chudleigh Road",
    "iso:country":"GB",
    "sg:address":"6 Chudleigh Road",
    "sg:city":"London",
    "sg:classifiers":[
        {
            "category":"Arts & Performance",
            "subcategory":"Music",
            "type":"Entertainment"
        }
    ],
    "sg:postcode":"SE4 1JW",
    "sg:province":"Greater London",
    "sg:tags":[
        "mobile",
        "disco"
    ],
    "wof:name":"Britannia Discotheque",
    "wof:placetype":"venue"
},
  "geometry": {"coordinates":[-0.0227480009,51.4562683105],"type":"Point"}
}