{
  "type": "Feature",
  "properties": {
    "addr:full":"Chestnut Cottage, Pond Close, Loxwood Billingshurst West Sussex RH14 0SH",
    "addr:postcode":"loxwood;rh14 0sh",
    "addr:street":"Pond Close",
    "iso:country":"GB",
    "sg:address":"Chestnut Cottage, Pond Close, Loxwood",
    "sg:city":"Billingshurst",
    "sg:classifiers":[
        {
            "category":"Retail",
            "subcategory":"Driving School",
            "type":"Services"
        }
    ],
    "sg:phone":"+44 1403 753183",
    "sg:postcode":"RH14 0SH",
    "sg:province":"West Sussex",
    "wof:name":"Group One L G V Training",
    "wof:placetype":"venue"
},
  "geometry": {"coordinates":[-0.5195659995,51.0755805969],"type":"Point"}
}