{
  "type": "Feature",
  "properties": {
    "addr:full":"Green Lane End, Lupton Carnforth Cumbria LA6 2PP",
    "addr:postcode":"la6 2pp",
    "addr:street":"Green Lane End",
    "iso:country":"GB",
    "sg:address":"Green Lane End, Lupton",
    "sg:city":"Carnforth",
    "sg:classifiers":[
        {
            "category":"Manufacturing",
            "subcategory":"Wood Products",
            "type":"Manufacturing & Wholesale Goods"
        },
        {
            "category":"Home & Garden",
            "subcategory":"Building Materials",
            "type":"Retail Goods"
        }
    ],
    "sg:phone":"+44 15395 67155",
    "sg:postcode":"LA6 2PP",
    "sg:province":"Cumbria",
    "sg:tags":[
        "pallet",
        "crate",
        "packaging",
        "packing",
        "pallets",
        "supplier"
    ],
    "wof:name":"D.L.S Packaging",
    "wof:placetype":"venue"
},
  "geometry": {"coordinates":[-2.6502509117,54.250087738],"type":"Point"}
}