{
  "type": "Feature",
  "properties": {
    "iso:country":"GB",
    "sg:address":"79c Sitwell Street, Spondon",
    "sg:city":"Derby",
    "sg:classifiers":[
        {
            "category":"Retail",
            "subcategory":"Laundry & Dry Cleaning",
            "type":"Services"
        }
    ],
    "sg:phone":"+44 1332 664797",
    "sg:postcode":"DE21 7FH",
    "sg:province":"Derbyshire",
    "sg:tags":[
        "cleaner",
        "alteration"
    ],
    "wof:name":"Spondon Dry Cleaning Co",
    "wof:placetype":"venue"
},
  "geometry": {"coordinates":[-1.404163,52.920269],"type":"Point"}
}