{
  "type": "Feature",
  "properties": {
    "addr:full":"Harrison House Farm, Roots Lane, Catforth Preston Lancashire PR4 0JB",
    "addr:postcode":"pr4 0jb",
    "addr:street":"Roots Lane",
    "iso:country":"GB",
    "sg:address":"Harrison House Farm, Roots Lane, Catforth",
    "sg:city":"Preston",
    "sg:classifiers":[
        {
            "category":"Recreation",
            "subcategory":"Dog Park",
            "type":"Entertainment"
        }
    ],
    "sg:postcode":"PR4 0JB",
    "sg:province":"Lancashire",
    "wof:name":"Raggamuffin's Dog Grooming Boarding Kennel & Catte",
    "wof:placetype":"venue"
},
  "geometry": {"coordinates":[-2.79188,53.813087],"type":"Point"}
}