{
  "type": "Feature",
  "properties": {
    "addr:full":"Kent Rd Wolverhampton West Midlands WV2 2AY",
    "addr:postcode":"wv2 2ay",
    "addr:street":"Kent Rd",
    "iso:country":"GB",
    "sg:address":"Kent Rd",
    "sg:city":"Wolverhampton",
    "sg:classifiers":[
        {
            "category":"Bars & Pubs",
            "type":"Food & Drink"
        }
    ],
    "sg:postcode":"WV2 2AY",
    "sg:province":"West Midlands",
    "sg:tags":[
        "pubs",
        "inn"
    ],
    "wof:name":"Moulders Arms (The)",
    "wof:placetype":"venue"
},
  "geometry": {"coordinates":[-2.114046,52.574642],"type":"Point"}
}