{
  "type": "Feature",
  "properties": {
    "iso:country":"GB",
    "sg:address":"Brown Street",
    "sg:city":"Dundee",
    "sg:classifiers":[
        {
            "category":"Building & Trades",
            "subcategory":"Construction",
            "type":"Services"
        },
        {
            "category":"Retail",
            "subcategory":"Auto Repair",
            "type":"Services"
        }
    ],
    "sg:phone":"+44 1382 224671",
    "sg:postcode":"DD1 5ED",
    "sg:province":"Dundee City",
    "sg:tags":[
        "body",
        "car",
        "builder"
    ],
    "wof:name":"Arnots Garage",
    "wof:placetype":"venue"
},
  "geometry": {"coordinates":[-2.980624,56.462818],"type":"Point"}
}