{
  "type": "Feature",
  "properties": {
    "addr:full":"Great Universal Buildings, 35-37 London Road Preston Lancashire PR1 4BZ",
    "addr:housenumber":"35-37",
    "addr:postcode":"pr1 4bz",
    "addr:street":"London Road",
    "iso:country":"GB",
    "sg:address":"Great Universal Buildings, 35-37 London Road",
    "sg:city":"Preston",
    "sg:classifiers":[
        {
            "category":"Professional",
            "subcategory":"Engineering",
            "type":"Services"
        }
    ],
    "sg:phone":"+44 1772 259933",
    "sg:postcode":"PR1 4BZ",
    "sg:province":"Lancashire",
    "sg:tags":[
        "consulting",
        "engineer"
    ],
    "wof:name":"Jacobs U K  Ltd.",
    "wof:placetype":"venue"
},
  "geometry": {"coordinates":[-2.7057290077,53.7579612732],"type":"Point"}
}