{
  "type": "Feature",
  "properties": {
    "iso:country":"GB",
    "sg:address":"25 Lusher Rise",
    "sg:city":"Norwich",
    "sg:classifiers":[
        {
            "category":"Building & Trades",
            "subcategory":"Plumbing",
            "type":"Services"
        }
    ],
    "sg:postcode":"NR6 5ED",
    "sg:province":"Norfolk",
    "sg:tags":[
        "central",
        "heating"
    ],
    "wof:name":"Wensum Heating & Combustion Servies",
    "wof:placetype":"venue"
},
  "geometry": {"coordinates":[1.249104023,52.6385993958],"type":"Point"}
}