{
  "type": "Feature",
  "properties": {
    "addr:full":"9 Seaview Terrace, Beer Seaton Devon EX12 3EX",
    "addr:housenumber":"9",
    "addr:postcode":"ex12 3ex",
    "addr:street":"Seaview Terrace",
    "iso:country":"GB",
    "sg:address":"9 Seaview Terrace, Beer",
    "sg:city":"Seaton",
    "sg:classifiers":[
        {
            "category":"Real Estate",
            "subcategory":"Real Estate Agent",
            "type":"Services"
        },
        {
            "category":"Farming",
            "subcategory":"Farm",
            "type":"Manufacturing & Wholesale Goods"
        }
    ],
    "sg:phone":"+44 1297 21106",
    "sg:postcode":"EX12 3EX",
    "sg:province":"Devon",
    "sg:tags":[
        "mixed",
        "crop"
    ],
    "wof:name":"THE CLINTON DEVON ESTATES",
    "wof:placetype":"venue"
},
  "geometry": {"coordinates":[-3.089331,50.699326],"type":"Point"}
}