{
  "type": "Feature",
  "properties": {
    "iso:country":"GB",
    "sg:address":"172 Ashley Road, Hale",
    "sg:city":"Altrincham",
    "sg:classifiers":[
        {
            "category":"Real Estate",
            "subcategory":"Real Estate Operator",
            "type":"Services"
        }
    ],
    "sg:phone":"+44 161 929 9898",
    "sg:postcode":"WA15 9SF",
    "sg:province":"Cheshire",
    "sg:tags":[
        "letting",
        "agent"
    ],
    "wof:name":"Jordan Fishwick Murray & Co.",
    "wof:placetype":"venue"
},
  "geometry": {"coordinates":[-2.346476,53.377296],"type":"Point"}
}