{
  "type": "Feature",
  "properties": {
    "iso:country":"GB",
    "sg:address":"Seafield Rd East",
    "sg:city":"Edinburgh",
    "sg:classifiers":[
        {
            "category":"Retail",
            "subcategory":"Auto Repair",
            "type":"Services"
        }
    ],
    "sg:phone":"+44 131 468 7300",
    "sg:postcode":"EH15 1ED",
    "sg:province":"City of Edinburgh",
    "sg:tags":[
        "body",
        "car"
    ],
    "wof:name":"Jm Accident Repair Centre",
    "wof:placetype":"venue"
},
  "geometry": {"coordinates":[-3.130579,55.964306],"type":"Point"}
}