{
  "type": "Feature",
  "properties": {
    "addr:full":"52 Appleby Gardens Dunstable Bedfordshire LU6 3DB",
    "addr:housenumber":"52",
    "addr:postcode":"lu6 3db",
    "addr:street":"Appleby Gardens",
    "iso:country":"GB",
    "sg:address":"52 Appleby Gardens",
    "sg:city":"Dunstable",
    "sg:classifiers":[
        {
            "category":"Professional",
            "subcategory":"Printing & Photocopies",
            "type":"Services"
        }
    ],
    "sg:postcode":"LU6 3DB",
    "sg:province":"Bedfordshire",
    "sg:tags":[
        "printer"
    ],
    "wof:name":"Algek Print",
    "wof:placetype":"venue"
},
  "geometry": {"coordinates":[-0.522187,51.878559],"type":"Point"}
}