{
  "type": "Feature",
  "properties": {
    "iso:country":"GB",
    "sg:address":"Rockly Court, Rock Road Finedon",
    "sg:city":"Kettering",
    "sg:classifiers":[
        {
            "category":"Professional",
            "subcategory":"Engineering",
            "type":"Services"
        }
    ],
    "sg:postcode":"NN9 5EL",
    "sg:province":"Northamptonshire",
    "sg:tags":[
        "consulting",
        "engineer"
    ],
    "wof:name":"L M P Technical Services Ltd.",
    "wof:placetype":"venue"
},
  "geometry": {"coordinates":[-0.64716,52.340118],"type":"Point"}
}