{
  "type": "Feature",
  "properties": {
    "addr:full":"4 Spa La Wigston Leicestershire LE18 3QD",
    "addr:housenumber":"4",
    "addr:postcode":"le18 3qd",
    "addr:street":"Spa La Wigston",
    "iso:country":"GB",
    "sg:address":"4 Spa La",
    "sg:city":"Wigston",
    "sg:classifiers":[
        {
            "category":"Social Services",
            "subcategory":"Retirement Home",
            "type":"Services"
        }
    ],
    "sg:phone":"+44 116 257 0262",
    "sg:postcode":"LE18 3QD",
    "sg:province":"Leicestershire",
    "sg:tags":[
        "residential",
        "care"
    ],
    "wof:name":"Stoneygate",
    "wof:placetype":"venue"
},
  "geometry": {"coordinates":[-1.102748,52.584221],"type":"Point"}
}