{
  "type": "Feature",
  "properties": {
    "addr:full":"80-84 Bridge Street, Ramsbottom Bury Lancashire BL0 9AG",
    "addr:housenumber":"80-84",
    "addr:postcode":"bl0 9ag",
    "addr:street":"Bridge Street",
    "iso:country":"GB",
    "sg:address":"80-84 Bridge Street, Ramsbottom",
    "sg:city":"Bury",
    "sg:classifiers":[
        {
            "category":"Shopping",
            "subcategory":"Luggage & Leather Goods",
            "type":"Retail Goods"
        }
    ],
    "sg:phone":"+44 1706 825751",
    "sg:postcode":"BL0 9AG",
    "sg:province":"Lancashire",
    "sg:tags":[
        "shop",
        "leathergoods"
    ],
    "wof:name":"Bill Allpress Leathergoods",
    "wof:placetype":"venue"
},
  "geometry": {"coordinates":[-2.3183701038,53.6486244202],"type":"Point"}
}