{
  "type": "Feature",
  "properties": {
    "addr:full":"9 Glendale Gro Wirral Merseyside CH63 9FP",
    "addr:housenumber":"9",
    "addr:postcode":"ch63 9fp",
    "addr:street":"Glendale Gro",
    "iso:country":"GB",
    "sg:address":"9 Glendale Gro",
    "sg:city":"Wirral",
    "sg:classifiers":[
        {
            "category":"Farming",
            "subcategory":"Dairy Farm",
            "type":"Manufacturing & Wholesale Goods"
        }
    ],
    "sg:phone":"+44 151 334 9520",
    "sg:postcode":"CH63 9FP",
    "sg:province":"Merseyside",
    "wof:name":"Simon's Dairy",
    "wof:placetype":"venue"
},
  "geometry": {"coordinates":[-2.9961760044,53.3381156921],"type":"Point"}
}