{
  "type": "Feature",
  "properties": {
    "addr:full":"24-26 Merchant Street Bristol City of Bristol BS1 3EP",
    "addr:housenumber":"24-26",
    "addr:postcode":"bs1 3ep",
    "addr:street":"Merchant Street",
    "iso:country":"GB",
    "sg:address":"24-26 Merchant Street",
    "sg:city":"Bristol",
    "sg:classifiers":[
        {
            "category":"Fast Food",
            "type":"Food & Drink"
        }
    ],
    "sg:phone":"+44 117 927 2417",
    "sg:postcode":"BS1 3EP",
    "sg:province":"City of Bristol",
    "sg:tags":[
        "away",
        "take"
    ],
    "wof:name":"McDonald's",
    "wof:placetype":"venue"
},
  "geometry": {"coordinates":[-2.588504,51.457218],"type":"Point"}
}