{
  "type": "Feature",
  "properties": {
    "iso:country":"GB",
    "sg:address":"Water Lane",
    "sg:city":"Towcester",
    "sg:classifiers":[
        {
            "category":"Manufacturing",
            "subcategory":"Electronics",
            "type":"Manufacturing & Wholesale Goods"
        }
    ],
    "sg:phone":"+44 1327 359922",
    "sg:postcode":"NN12 6JN",
    "sg:province":"Buckinghamshire",
    "sg:tags":[
        "computer",
        "-",
        "printed",
        "circuit"
    ],
    "wof:name":"Foundation Technology Ltd.",
    "wof:placetype":"venue"
},
  "geometry": {"coordinates":[-0.991328,52.130116],"type":"Point"}
}