{
  "type": "Feature",
  "properties": {
    "iso:country":"GB",
    "sg:address":"19-21 New Street",
    "sg:city":"Andover",
    "sg:classifiers":[
        {
            "category":"Autos & Motor Vehicles",
            "subcategory":"Automobile Sales",
            "type":"Retail Goods"
        }
    ],
    "sg:postcode":"SP10 1EL",
    "sg:province":"Hampshire",
    "sg:tags":[
        "car"
    ],
    "wof:name":"Reeves & Gates Automart",
    "wof:placetype":"venue"
},
  "geometry": {"coordinates":[-1.4770959616,51.2105484009],"type":"Point"}
}