{
  "type": "Feature",
  "properties": {
    "iso:country":"GB",
    "sg:address":"246a High Street",
    "sg:city":"Guildford",
    "sg:classifiers":[
        {
            "category":"Professional",
            "subcategory":"Art Services",
            "type":"Services"
        }
    ],
    "sg:phone":"+44 1483 533448",
    "sg:postcode":"GU1 3JF",
    "sg:province":"Surrey",
    "sg:tags":[
        "photographer"
    ],
    "wof:name":"Payday Secretarial",
    "wof:placetype":"venue"
},
  "geometry": {"coordinates":[-0.567711,51.23711],"type":"Point"}
}