{
  "type": "Feature",
  "properties": {
    "iso:country":"GB",
    "sg:address":"10 Scar Bank",
    "sg:city":"Warwick",
    "sg:classifiers":[
        {
            "category":"Professional",
            "subcategory":"Engineering",
            "type":"Services"
        }
    ],
    "sg:phone":"+44 1926 498117",
    "sg:postcode":"CV34 5DB",
    "sg:province":"Warwickshire",
    "sg:tags":[
        "engineer"
    ],
    "wof:name":"Avenue Pattern Co Ltd",
    "wof:placetype":"venue"
},
  "geometry": {"coordinates":[-1.5877439976,52.2916984558],"type":"Point"}
}