{
  "type": "Feature",
  "properties": {
    "iso:country":"GB",
    "sg:address":"14 Springvale Industrial Estate",
    "sg:city":"Cwmbran",
    "sg:classifiers":[
        {
            "category":"Building & Trades",
            "subcategory":"Equipment Rental",
            "type":"Services"
        }
    ],
    "sg:phone":"+44 1633 867867",
    "sg:postcode":"NP44 5BR",
    "sg:province":"Monmouthshire",
    "sg:tags":[
        "hire",
        "centre"
    ],
    "wof:name":"Gater Tool Hire & Sales Ltd.",
    "wof:placetype":"venue"
},
  "geometry": {"coordinates":[-3.0367639065,51.656703949],"type":"Point"}
}