{
  "type": "Feature",
  "properties": {
    "iso:country":"GB",
    "sg:address":"Sunnybank Terrace, Cwmparc",
    "sg:city":"Treorchy",
    "sg:classifiers":[
        {
            "category":"Organizations",
            "subcategory":"Community Association",
            "type":"Services"
        },
        {
            "category":"Organizations",
            "subcategory":"Membership Organization",
            "type":"Services"
        }
    ],
    "sg:phone":"+44 1443 773131",
    "sg:postcode":"CF42 6ND",
    "sg:province":"Rhondda, Cynon, Taff",
    "sg:tags":[
        "club",
        "social"
    ],
    "wof:name":"Parc & Dare Ex Servicemens Club",
    "wof:placetype":"venue"
},
  "geometry": {"coordinates":[-3.505229,51.659664],"type":"Point"}
}