{
  "type": "Feature",
  "properties": {
    "iso:country":"GB",
    "sg:address":"Unit 6 The Science Village, Claro Road",
    "sg:city":"Harrogate",
    "sg:classifiers":[
        {
            "category":"Professional",
            "subcategory":"Engineering",
            "type":"Services"
        }
    ],
    "sg:phone":"+44 1423 523633",
    "sg:postcode":"HG1 4AG",
    "sg:province":"North Yorkshire",
    "sg:tags":[
        "precision",
        "engineer"
    ],
    "wof:name":"Harrogate Precision Engineering",
    "wof:placetype":"venue"
},
  "geometry": {"coordinates":[-1.544524,53.99469],"type":"Point"}
}