{
  "type": "Feature",
  "properties": {
    "addr:full":"Wixford Road, Bidford On Avon Alcester Warwickshire B50 4LG",
    "addr:postcode":"avon;b50 4lg",
    "addr:street":"Wixford Road",
    "iso:country":"GB",
    "sg:address":"Wixford Road, Bidford On Avon",
    "sg:city":"Alcester",
    "sg:classifiers":[
        {
            "category":"Bars & Pubs",
            "type":"Food & Drink"
        },
        {
            "category":"Community Center",
            "subcategory":"Social",
            "type":"Public Place"
        }
    ],
    "sg:phone":"+44 1789 772420",
    "sg:postcode":"B50 4LG",
    "sg:province":"Warwickshire",
    "sg:tags":[
        "pubs",
        "house",
        "inn",
        "activity"
    ],
    "wof:name":"Golden Cross Inn",
    "wof:placetype":"venue"
},
  "geometry": {"coordinates":[-1.860054,52.164616],"type":"Point"}
}