{
  "type": "Feature",
  "properties": {
    "addr:full":"Stalls 15-16, New Market Warrington Cheshire WA1 2EN",
    "addr:housenumber":"15-16",
    "addr:postcode":"wa1 2en",
    "addr:street":"Stalls;Market",
    "iso:country":"GB",
    "sg:address":"Stalls 15-16, New Market",
    "sg:city":"Warrington",
    "sg:classifiers":[
        {
            "category":"Food & Beverages",
            "subcategory":"Meat & Fish",
            "type":"Retail Goods"
        }
    ],
    "sg:phone":"+44 1925 637624",
    "sg:postcode":"WA1 2EN",
    "sg:province":"Cheshire",
    "sg:tags":[
        "butcher"
    ],
    "wof:name":"Yates Greer & Co.",
    "wof:placetype":"venue"
},
  "geometry": {"coordinates":[-2.59178,53.38802],"type":"Point"}
}