{
  "type": "Feature",
  "properties": {
    "addr:full":"132 Swan Street, Sible Hedingham Halstead Essex CO9 3PP",
    "addr:housenumber":"132",
    "addr:postcode":"co9 3pp",
    "addr:street":"Swan Street",
    "iso:country":"GB",
    "sg:address":"132 Swan Street, Sible Hedingham",
    "sg:city":"Halstead",
    "sg:classifiers":[
        {
            "category":"Personal",
            "subcategory":"Beauty Salon",
            "type":"Services"
        }
    ],
    "sg:phone":"+44 1787 460085",
    "sg:postcode":"CO9 3PP",
    "sg:province":"Essex",
    "wof:name":"Skin Deep Beauty Salon",
    "wof:placetype":"venue"
},
  "geometry": {"coordinates":[0.593049,51.977272],"type":"Point"}
}