{
  "type": "Feature",
  "properties": {
    "addr:full":"2 Holland Clo Barnstaple Devon EX31 2LQ",
    "addr:housenumber":"2",
    "addr:postcode":"ex31 2lq",
    "addr:street":"Holland Clo",
    "iso:country":"GB",
    "sg:address":"2 Holland Clo",
    "sg:city":"Barnstaple",
    "sg:classifiers":[
        {
            "category":"Building & Trades",
            "subcategory":"Construction",
            "type":"Services"
        }
    ],
    "sg:postcode":"EX31 2LQ",
    "sg:province":"Devon",
    "sg:tags":[
        "joiner",
        "carpenter"
    ],
    "wof:name":"Fox,David,",
    "wof:placetype":"venue"
},
  "geometry": {"coordinates":[-4.098004818,51.0734138489],"type":"Point"}
}