{
  "type": "Feature",
  "properties": {
    "addr:full":"Bugler House Rickmansworth Hertfordshire WD3 1JY",
    "addr:postcode":"wd3 1jy",
    "addr:street":"Rickmansworth",
    "iso:country":"GB",
    "sg:address":"Bugler House",
    "sg:city":"Rickmansworth",
    "sg:classifiers":[
        {
            "category":"Building & Trades",
            "subcategory":"Construction",
            "type":"Services"
        }
    ],
    "sg:phone":"+44 1923 777988",
    "sg:postcode":"WD3 1JY",
    "sg:province":"Hertfordshire",
    "sg:tags":[
        "builder"
    ],
    "wof:name":"Bugler Developments Ltd.",
    "wof:placetype":"venue"
},
  "geometry": {"coordinates":[-0.4682750106,51.6414375305],"type":"Point"}
}