{
  "type": "Feature",
  "properties": {
    "addr:full":"353 Hitchin Road Luton Bedfordshire LU2 7SW",
    "addr:housenumber":"353",
    "addr:postcode":"lu2 7sw",
    "addr:street":"Hitchin Road",
    "iso:country":"GB",
    "sg:address":"353 Hitchin Road",
    "sg:city":"Luton",
    "sg:classifiers":[
        {
            "category":"Personal",
            "subcategory":"Beauty Salon",
            "type":"Services"
        }
    ],
    "sg:postcode":"LU2 7SW",
    "sg:province":"Bedfordshire",
    "sg:tags":[
        "lady",
        "hairdresser"
    ],
    "wof:name":"Cameo Hair Fashions",
    "wof:placetype":"venue"
},
  "geometry": {"coordinates":[-0.401906,51.891659],"type":"Point"}
}