{
  "type": "Feature",
  "properties": {
    "iso:country":"GB",
    "sg:address":"460 Killinghall Road",
    "sg:city":"Bradford",
    "sg:classifiers":[
        {
            "category":"Food & Beverages",
            "subcategory":"Meat & Fish",
            "type":"Retail Goods"
        }
    ],
    "sg:postcode":"BD2 4SL",
    "sg:province":"West Yorkshire",
    "sg:tags":[
        "butcher"
    ],
    "wof:name":"Duncans Butchers",
    "wof:placetype":"venue"
},
  "geometry": {"coordinates":[-1.729368,53.808868],"type":"Point"}
}