{
  "type": "Feature",
  "properties": {
    "addr:full":"Bolton General Hospital, Minerva Road, Farnworth Bolton Lancashire BL3 1AZ",
    "addr:postcode":"bl3 1az",
    "addr:street":"Minerva Road",
    "iso:country":"GB",
    "sg:address":"Bolton General Hospital, Minerva Road, Farnworth",
    "sg:city":"Bolton",
    "sg:classifiers":[
        {
            "category":"Farming",
            "subcategory":"Nursery",
            "type":"Manufacturing & Wholesale Goods"
        }
    ],
    "sg:phone":"+44 1204 390581",
    "sg:postcode":"BL3 1AZ",
    "sg:province":"Lancashire",
    "sg:tags":[
        "creche"
    ],
    "wof:name":"High Meadows Day Nursery",
    "wof:placetype":"venue"
},
  "geometry": {"coordinates":[-2.36868,53.554932],"type":"Point"}
}