{
  "type": "Feature",
  "properties": {
    "addr:full":"18 George Street St Albans Hertfordshire AL3 4ES",
    "addr:housenumber":"18",
    "addr:postcode":"al3 4es",
    "addr:street":"George Street",
    "iso:country":"GB",
    "sg:address":"18 George Street",
    "sg:city":"St Albans",
    "sg:classifiers":[
        {
            "category":"Shopping",
            "subcategory":"Clothing, Apparel, & Fashions",
            "type":"Retail Goods"
        }
    ],
    "sg:postcode":"AL3 4ES",
    "sg:province":"Hertfordshire",
    "sg:tags":[
        "shop"
    ],
    "wof:name":"Tabard Fashions",
    "wof:placetype":"venue"
},
  "geometry": {"coordinates":[-0.3425790071,51.751739502],"type":"Point"}
}