{
  "type": "Feature",
  "properties": {
    "iso:country":"GB",
    "sg:address":"Unit 30 Birchbrook Indust Park, Birchbrook La",
    "sg:city":"Lichfield",
    "sg:classifiers":[
        {
            "category":"Shopping",
            "subcategory":"Bicycles & Sporting Goods",
            "type":"Retail Goods"
        }
    ],
    "sg:phone":"+44 1543 481666",
    "sg:postcode":"WS14 0DT",
    "sg:province":"Staffordshire",
    "sg:tags":[
        "riding",
        "saddlery",
        "wear"
    ],
    "wof:name":"Miller Crosby Ltd",
    "wof:placetype":"venue"
},
  "geometry": {"coordinates":[-1.848729,52.639656],"type":"Point"}
}