{
  "type": "Feature",
  "properties": {
    "addr:full":"Castlegate Centre, Spencer Hall, High Street Stockton-on-tees Durham TS18 1BW",
    "addr:postcode":"ts18 1bw",
    "addr:street":"Castlegate;High Street",
    "iso:country":"GB",
    "sg:address":"Castlegate Centre, Spencer Hall, High Street",
    "sg:city":"Stockton-on-tees",
    "sg:classifiers":[
        {
            "category":"Food & Beverages",
            "subcategory":"Bakery",
            "type":"Retail Goods"
        }
    ],
    "sg:phone":"+44 1642 612195",
    "sg:postcode":"TS18 1BW",
    "sg:province":"Durham",
    "sg:tags":[
        "baker"
    ],
    "wof:name":"Morgan's Bakery",
    "wof:placetype":"venue"
},
  "geometry": {"coordinates":[-1.3120499849,54.5627098083],"type":"Point"}
}