{
  "type": "Feature",
  "properties": {
    "iso:country":"GB",
    "sg:address":"4 Hornbury Crescent, Clockface",
    "sg:city":"St Helens",
    "sg:classifiers":[
        {
            "category":"Arts & Performance",
            "subcategory":"Music",
            "type":"Entertainment"
        }
    ],
    "sg:postcode":"WA9 4RY",
    "sg:province":"Cheshire",
    "sg:tags":[
        "mobile",
        "disco"
    ],
    "wof:name":"M K A Disco & Karaoke",
    "wof:placetype":"venue"
},
  "geometry": {"coordinates":[-2.71561,53.419231],"type":"Point"}
}