{
  "type": "Feature",
  "properties": {
    "iso:country":"GB",
    "sg:address":"78 Argyll Street",
    "sg:city":"Dunoon",
    "sg:classifiers":[
        {
            "category":"Banks & Credit Unions",
            "subcategory":"Bank",
            "type":"Services"
        }
    ],
    "sg:phone":"+44 1369 762000",
    "sg:postcode":"PA23 7NH",
    "sg:province":"Argyll and Bute",
    "sg:tags":[
        "financial",
        "institution"
    ],
    "wof:name":"Bank of Scotland",
    "wof:placetype":"venue"
},
  "geometry": {"coordinates":[-4.92536,55.948956],"type":"Point"}
}