{
  "type": "Feature",
  "properties": {
    "iso:country":"GB",
    "sg:address":"38 Looe Street",
    "sg:city":"Plymouth",
    "sg:classifiers":[
        {
            "category":"Real Estate",
            "subcategory":"Architect",
            "type":"Services"
        }
    ],
    "sg:postcode":"PL4 0EB",
    "sg:province":"Devon",
    "wof:name":"Pearson Lubbock Architects",
    "wof:placetype":"venue"
},
  "geometry": {"coordinates":[-4.1371831894,50.3694992065],"type":"Point"}
}