{
  "type": "Feature",
  "properties": {
    "addr:full":"Warwick Road Carlisle Cumbria CA1 1DN",
    "addr:postcode":"ca1 1dn",
    "addr:street":"Warwick Road",
    "iso:country":"GB",
    "sg:address":"Warwick Road",
    "sg:city":"Carlisle",
    "sg:classifiers":[
        {
            "category":"Cinema",
            "subcategory":"Movie Theater",
            "type":"Entertainment"
        }
    ],
    "sg:phone":"+44 1228 525586",
    "sg:postcode":"CA1 1DN",
    "sg:province":"Cumbria",
    "wof:name":"Lonsdale Cinemas",
    "wof:placetype":"venue"
},
  "geometry": {"coordinates":[-2.924789,54.894386],"type":"Point"}
}