{
  "type": "Feature",
  "properties": {
    "addr:full":"67 Station Road, Ampthill Bedford Bedfordshire MK45 2QU",
    "addr:housenumber":"67",
    "addr:postcode":"mk45 2qu",
    "addr:street":"Station Road",
    "iso:country":"GB",
    "sg:address":"67 Station Road, Ampthill",
    "sg:city":"Bedford",
    "sg:classifiers":[
        {
            "category":"Building & Trades",
            "subcategory":"Landscaping Services",
            "type":"Services"
        }
    ],
    "sg:phone":"+44 1525 406018",
    "sg:postcode":"MK45 2QU",
    "sg:province":"Bedfordshire",
    "sg:tags":[
        "landscape",
        "contractor"
    ],
    "wof:name":"Warners Landscaping & Garden Services",
    "wof:placetype":"venue"
},
  "geometry": {"coordinates":[-0.502211988,52.0255050659],"type":"Point"}
}