{
  "type": "Feature",
  "properties": {
    "iso:country":"GB",
    "sg:address":"Church Hill, Gwersyllt",
    "sg:city":"Wrexham",
    "sg:classifiers":[
        {
            "category":"Education",
            "subcategory":"School",
            "type":"Public Place"
        },
        {
            "category":"Education",
            "subcategory":"University",
            "type":"Public Place"
        }
    ],
    "sg:phone":"+44 1978 750618",
    "sg:postcode":"LL11 4HB",
    "sg:province":"Wrexham",
    "sg:tags":[
        "adult",
        "location"
    ],
    "wof:name":"Ysgol Bryn Alyn",
    "wof:placetype":"venue"
},
  "geometry": {"coordinates":[-3.019284,53.072384],"type":"Point"}
}