{
  "type": "Feature",
  "properties": {
    "addr:full":"Staffordshire House, 28 New Road Dudley West Midlands DY2 8TA",
    "addr:housenumber":"28",
    "addr:postcode":"dy2 8ta",
    "addr:street":"New Road",
    "iso:country":"GB",
    "sg:address":"Staffordshire House, 28 New Road",
    "sg:city":"Dudley",
    "sg:classifiers":[
        {
            "category":"Building & Trades",
            "subcategory":"Cleaning & Sanitation",
            "type":"Services"
        }
    ],
    "sg:postcode":"DY2 8TA",
    "sg:province":"West Midlands",
    "sg:tags":[
        "commercial"
    ],
    "wof:name":"Castle Cleaning Service",
    "wof:placetype":"venue"
},
  "geometry": {"coordinates":[-2.084808,52.504284],"type":"Point"}
}