{
  "type": "Feature",
  "properties": {
    "addr:full":"Bromborough Pool Primary School, Kitchen, York St Wirral Cheshire CH62 4TZ",
    "addr:postcode":"ch62 4tz",
    "addr:street":"York St",
    "iso:country":"GB",
    "sg:address":"Bromborough Pool Primary School, Kitchen, York St",
    "sg:city":"Wirral",
    "sg:classifiers":[
        {
            "category":"Government",
            "subcategory":"Office",
            "type":"Public Place"
        }
    ],
    "sg:phone":"+44 151 645 8910",
    "sg:postcode":"CH62 4TZ",
    "sg:province":"Cheshire",
    "sg:tags":[
        "local"
    ],
    "wof:name":"Metropolitan Borough of Wirral",
    "wof:placetype":"venue"
},
  "geometry": {"coordinates":[-2.9783000946,53.3505210876],"type":"Point"}
}