{
  "type": "Feature",
  "properties": {
    "addr:full":"Unit 208 The Commercial Centre, Picket Piece Andover Hampshire SP11 6LU",
    "addr:housenumber":"208",
    "addr:postcode":"sp11 6lu",
    "addr:street":"The",
    "iso:country":"GB",
    "sg:address":"Unit 208 The Commercial Centre, Picket Piece",
    "sg:city":"Andover",
    "sg:classifiers":[
        {
            "category":"Building & Trades",
            "subcategory":"Plumbing",
            "type":"Services"
        },
        {
            "category":"Home & Garden",
            "subcategory":"Building Materials",
            "type":"Retail Goods"
        }
    ],
    "sg:phone":"+44 1264 334108",
    "sg:postcode":"SP11 6LU",
    "sg:province":"Hampshire",
    "sg:tags":[
        "merchant",
        "ventilator",
        "ventilation",
        "system",
        "plumbers'"
    ],
    "wof:name":"Trade Supplies",
    "wof:placetype":"venue"
},
  "geometry": {"coordinates":[-1.430295,51.208237],"type":"Point"}
}