{
  "type": "Feature",
  "properties": {
    "addr:full":"12 Euston Place Leamington Spa Warwickshire CV32 4LR",
    "addr:housenumber":"12",
    "addr:postcode":"cv32 4lr",
    "addr:street":"Euston Place",
    "iso:country":"GB",
    "sg:address":"12 Euston Place",
    "sg:city":"Leamington Spa",
    "sg:classifiers":[
        {
            "category":"Real Estate",
            "subcategory":"Real Estate Agent",
            "type":"Services"
        }
    ],
    "sg:phone":"+44 1926 429268",
    "sg:postcode":"CV32 4LR",
    "sg:province":"Warwickshire",
    "wof:name":"Loveitts",
    "wof:placetype":"venue"
},
  "geometry": {"coordinates":[-1.534516,52.288471],"type":"Point"}
}