{
  "type": "Feature",
  "properties": {
    "addr:full":"3rd Floor, Commodity Quay, East Smithfield London Greater London E1W 1AZ",
    "addr:housenumber":"3rd floor",
    "addr:postcode":"e1w 1az",
    "addr:street":"Commodity Quay East",
    "iso:country":"GB",
    "sg:address":"3rd Floor, Commodity Quay, East Smithfield",
    "sg:city":"London",
    "sg:classifiers":[
        {
            "category":"Banks & Credit Unions",
            "subcategory":"Investment Brokerage",
            "type":"Services"
        }
    ],
    "sg:phone":"+44 20 7702 4040",
    "sg:postcode":"E1W 1AZ",
    "sg:province":"Greater London",
    "sg:tags":[
        "stockbroker"
    ],
    "wof:name":"Instinet Global Services Ltd.",
    "wof:placetype":"venue"
},
  "geometry": {"coordinates":[-0.071114,51.508125],"type":"Point"}
}