{
  "type": "Feature",
  "properties": {
    "addr:full":"Unit 8, Brassmill Enterprise Centre Bath Bath and North East Somerset BA1 3JN",
    "addr:housenumber":"unit 8 brassmill;centre",
    "addr:postcode":"ba1 3jn",
    "addr:street":"Bath",
    "iso:country":"GB",
    "sg:address":"Unit 8, Brassmill Enterprise Centre",
    "sg:city":"Bath",
    "sg:classifiers":[
        {
            "category":"Professional",
            "subcategory":"Art Services",
            "type":"Services"
        }
    ],
    "sg:phone":"+44 1225 444809",
    "sg:postcode":"BA1 3JN",
    "sg:province":"Bath and North East Somerset",
    "sg:tags":[
        "consultant",
        "design"
    ],
    "wof:name":"Milsom Industrial Designs Ltd.",
    "wof:placetype":"venue"
},
  "geometry": {"coordinates":[-2.402769,51.38649],"type":"Point"}
}