{
  "type": "Feature",
  "properties": {
    "addr:full":"21 The Parade, Claygate Esher Surrey KT10 0PD",
    "addr:housenumber":"21",
    "addr:postcode":"kt10 0pd",
    "addr:street":"The Parade",
    "iso:country":"GB",
    "sg:address":"21 The Parade, Claygate",
    "sg:city":"Esher",
    "sg:classifiers":[
        {
            "category":"Food & Beverages",
            "subcategory":"Meat & Fish",
            "type":"Retail Goods"
        }
    ],
    "sg:phone":"+44 1372 462901",
    "sg:postcode":"KT10 0PD",
    "sg:province":"Surrey",
    "sg:tags":[
        "butcher"
    ],
    "wof:name":"J. WILLIAMS (SOUTHDOWN HOUSE) LTD",
    "wof:placetype":"venue"
},
  "geometry": {"coordinates":[-0.3468259871,51.3610076904],"type":"Point"}
}