{
  "type": "Feature",
  "properties": {
    "iso:country":"GB",
    "sg:address":"14 Reed Square, Castle Vale",
    "sg:city":"Birmingham",
    "sg:classifiers":[
        {
            "category":"Food & Beverages",
            "subcategory":"Meat & Fish",
            "type":"Retail Goods"
        }
    ],
    "sg:phone":"+44 121 747 6123",
    "sg:postcode":"B35 7PS",
    "sg:province":"West Midlands",
    "sg:tags":[
        "chip"
    ],
    "wof:name":"Reed Square Fish Bar",
    "wof:placetype":"venue"
},
  "geometry": {"coordinates":[-1.7847499847,52.5213088989],"type":"Point"}
}