{
  "type": "Feature",
  "properties": {
    "addr:full":"8 Albert Indstl Est Bolton House Rd, Bickershaw Wigan Lancashire WN2 4XU",
    "addr:housenumber":"8",
    "addr:postcode":"wn2 4xu",
    "addr:street":"Albert Indstl Est;House Rd",
    "iso:country":"GB",
    "sg:address":"8 Albert Indstl Est Bolton House Rd, Bickershaw",
    "sg:city":"Wigan",
    "sg:classifiers":[
        {
            "category":"Home & Garden",
            "subcategory":"Building Materials",
            "type":"Retail Goods"
        }
    ],
    "sg:postcode":"WN2 4XU",
    "sg:province":"Lancashire",
    "sg:tags":[
        "gate",
        "door",
        "barrier"
    ],
    "wof:name":"Multicast Fencing & Flags Ltd",
    "wof:placetype":"venue"
},
  "geometry": {"coordinates":[-2.56129,53.512009],"type":"Point"}
}