{
  "type": "Feature",
  "properties": {
    "addr:full":"2 Harcourt Road Harrogate North Yorkshire HG1 5NL",
    "addr:housenumber":"2",
    "addr:postcode":"hg1 5nl",
    "addr:street":"Harcourt Road",
    "iso:country":"GB",
    "sg:address":"2 Harcourt Road",
    "sg:city":"Harrogate",
    "sg:classifiers":[
        {
            "category":"Farming",
            "subcategory":"Nursery",
            "type":"Manufacturing & Wholesale Goods"
        },
        {
            "category":"Education",
            "subcategory":"Preschool",
            "type":"Public Place"
        }
    ],
    "sg:phone":"+44 1423 563969",
    "sg:postcode":"HG1 5NL",
    "sg:province":"North Yorkshire",
    "sg:tags":[
        "school",
        "creche"
    ],
    "wof:name":"Harcourt Pre School Nursery",
    "wof:placetype":"venue"
},
  "geometry": {"coordinates":[-1.5307879448,53.9950866699],"type":"Point"}
}