{
  "type": "Feature",
  "properties": {
    "iso:country":"GB",
    "sg:address":"83 St Johns Road",
    "sg:city":"Liverpool",
    "sg:classifiers":[
        {
            "category":"Shopping",
            "subcategory":"Department Store",
            "type":"Retail Goods"
        }
    ],
    "sg:phone":"+44 151 928 1883",
    "sg:postcode":"L22 9QD",
    "sg:province":"Merseyside",
    "wof:name":"Clarkson's",
    "wof:placetype":"venue"
},
  "geometry": {"coordinates":[-3.027042,53.478382],"type":"Point"}
}