{
  "type": "Feature",
  "properties": {
    "addr:full":"8 Gainsborough Rd Felixstowe Suffolk IP11 7HT",
    "addr:housenumber":"8",
    "addr:postcode":"ip11 7ht",
    "addr:street":"Gainsborough Rd",
    "iso:country":"GB",
    "sg:address":"8 Gainsborough Rd",
    "sg:city":"Felixstowe",
    "sg:classifiers":[
        {
            "category":"Place Of Worship",
            "type":"Public Place"
        }
    ],
    "sg:phone":"+44 1394 282561",
    "sg:postcode":"IP11 7HT",
    "sg:province":"Suffolk",
    "wof:name":"St Felix R C Church",
    "wof:placetype":"venue"
},
  "geometry": {"coordinates":[1.3530859947,51.9652557373],"type":"Point"}
}