{
  "type": "Feature",
  "properties": {
    "iso:country":"GB",
    "sg:address":"88 Nantwich Road",
    "sg:city":"Crewe",
    "sg:classifiers":[
        {
            "category":"Fast Food",
            "type":"Food & Drink"
        }
    ],
    "sg:postcode":"CW2 6AT",
    "sg:province":"Cheshire",
    "sg:tags":[
        "away",
        "take"
    ],
    "wof:name":"The Pizza Place",
    "wof:placetype":"venue"
},
  "geometry": {"coordinates":[-2.440158,53.088482],"type":"Point"}
}