{
  "type": "Feature",
  "properties": {
    "addr:full":"11-13 Breams Buildings St Paul's Greater London EC4A 1HB",
    "addr:housenumber":"11-13",
    "addr:postcode":"ec4a 1hb",
    "addr:street":"Breams Buildings St",
    "iso:country":"GB",
    "sg:address":"11-13 Breams Buildings",
    "sg:city":"St Paul's",
    "sg:classifiers":[
        {
            "category":"Professional",
            "subcategory":"Lawyer & Legal Services",
            "type":"Services"
        }
    ],
    "sg:phone":"+44 171 405 7554",
    "sg:postcode":"EC4A 1HB",
    "sg:province":"Greater London",
    "sg:tags":[
        "solicitor"
    ],
    "wof:name":"Carter Lemon",
    "wof:placetype":"venue"
},
  "geometry": {"coordinates":[-0.111197,51.516129],"type":"Point"}
}