{
  "type": "Feature",
  "properties": {
    "iso:country":"GB",
    "sg:address":"891 Aikenhead Road",
    "sg:city":"Glasgow",
    "sg:classifiers":[
        {
            "category":"Food & Beverages",
            "subcategory":"Meat & Fish",
            "type":"Retail Goods"
        },
        {
            "category":"Food & Beverages",
            "subcategory":"Groceries & Convenience Stores",
            "type":"Retail Goods"
        }
    ],
    "sg:phone":"+44 141 632 5585",
    "sg:postcode":"G42 0NT",
    "sg:province":"Glasgow City",
    "sg:tags":[
        "shop",
        "chip"
    ],
    "wof:name":"Michael's Superchippy",
    "wof:placetype":"venue"
},
  "geometry": {"coordinates":[-4.247739,55.829189],"type":"Point"}
}