{
  "type": "Feature",
  "properties": {
    "addr:full":"7 Vicarage Road Wednesbury West Midlands WS10 9DW",
    "addr:housenumber":"7",
    "addr:postcode":"ws10 9dw",
    "addr:street":"Vicarage Road",
    "iso:country":"GB",
    "sg:address":"7 Vicarage Road",
    "sg:city":"Wednesbury",
    "sg:classifiers":[
        {
            "category":"Manufacturing",
            "subcategory":"Metals",
            "type":"Manufacturing & Wholesale Goods"
        }
    ],
    "sg:phone":"+44 121 556 8978",
    "sg:postcode":"WS10 9DW",
    "sg:province":"West Midlands",
    "sg:tags":[
        "steel",
        "stockholder"
    ],
    "wof:name":"Linton Steel Supplies Ltd.",
    "wof:placetype":"venue"
},
  "geometry": {"coordinates":[-2.011707,52.55756],"type":"Point"}
}