{
  "type": "Feature",
  "properties": {
    "addr:full":"103 Princess Victoria Street Bristol City of Bristol BS8 4DD",
    "addr:housenumber":"103",
    "addr:postcode":"bs8 4dd",
    "addr:street":"Princess Victoria Street",
    "iso:country":"GB",
    "sg:address":"103 Princess Victoria Street",
    "sg:city":"Bristol",
    "sg:classifiers":[
        {
            "category":"Real Estate",
            "subcategory":"Architect",
            "type":"Services"
        }
    ],
    "sg:postcode":"BS8 4DD",
    "sg:province":"City of Bristol",
    "wof:name":"Falconer Falconer & Falconer",
    "wof:placetype":"venue"
},
  "geometry": {"coordinates":[-2.6235949993,51.4535102844],"type":"Point"}
}