{
  "type": "Feature",
  "properties": {
    "addr:full":"17-18 Shelvers Hill Tadworth Surrey KT20 5PU",
    "addr:housenumber":"17-18",
    "addr:postcode":"kt20 5pu",
    "addr:street":"Shelvers Hill",
    "iso:country":"GB",
    "sg:address":"17-18 Shelvers Hill",
    "sg:city":"Tadworth",
    "sg:classifiers":[
        {
            "category":"Professional",
            "subcategory":"Detective & Security Services",
            "type":"Services"
        }
    ],
    "sg:phone":"+44 1737 812265",
    "sg:postcode":"KT20 5PU",
    "sg:province":"Surrey",
    "sg:tags":[
        "agency"
    ],
    "wof:name":"F C Parkin Investigation & Research",
    "wof:placetype":"venue"
},
  "geometry": {"coordinates":[-0.2369890064,51.2967643738],"type":"Point"}
}