{
  "type": "Feature",
  "properties": {
    "addr:full":"Higher Hurston Farm, Chagford Newton Abbot Devon TQ13 8EF",
    "addr:postcode":"tq13 8ef",
    "iso:country":"GB",
    "sg:address":"Higher Hurston Farm, Chagford",
    "sg:city":"Newton Abbot",
    "sg:classifiers":[
        {
            "category":"Farming",
            "subcategory":"Livestock Farm",
            "type":"Manufacturing & Wholesale Goods"
        },
        {
            "category":"Farming",
            "subcategory":"Farm",
            "type":"Manufacturing & Wholesale Goods"
        }
    ],
    "sg:phone":"+44 1647 433390",
    "sg:postcode":"TQ13 8EF",
    "sg:province":"Devon",
    "sg:tags":[
        "mixed",
        "crop",
        "others"
    ],
    "wof:name":"Carl P Allerfeldt",
    "wof:placetype":"venue"
},
  "geometry": {"coordinates":[-3.834256,50.677418],"type":"Point"}
}