{
  "type": "Feature",
  "properties": {
    "iso:country":"GB",
    "sg:address":"Grove House, Waltham Road, White Waltham",
    "sg:city":"Maidenhead",
    "sg:classifiers":[
        {
            "category":"Communications",
            "type":"Services"
        }
    ],
    "sg:postcode":"SL6 3TN",
    "sg:province":"Berkshire",
    "sg:tags":[
        "data",
        "network"
    ],
    "wof:name":"Crosskeys Networks Ltd.",
    "wof:placetype":"venue"
},
  "geometry": {"coordinates":[-0.763574,51.502243],"type":"Point"}
}