{
  "type": "Feature",
  "properties": {
    "iso:country":"GB",
    "sg:address":"10 Stewart Street",
    "sg:city":"Wolverhampton",
    "sg:classifiers":[
        {
            "category":"Sports & Exercise",
            "subcategory":"Athletic Track",
            "type":"Entertainment"
        }
    ],
    "sg:phone":"+44 1902 717733",
    "sg:postcode":"WV2 4JW",
    "sg:province":"West Midlands",
    "sg:tags":[
        "bags",
        "accessory",
        "belt"
    ],
    "wof:name":"Travel Protection Bag",
    "wof:placetype":"venue"
},
  "geometry": {"coordinates":[-2.1302690506,52.5781097412],"type":"Point"}
}