{
  "type": "Feature",
  "properties": {
    "addr:full":"207 Holton Road Barry The Vale of Glamorgan CF63 4HR",
    "addr:housenumber":"207",
    "addr:postcode":"cf63 4hr",
    "addr:street":"Holton Road;Vale",
    "iso:country":"GB",
    "sg:address":"207 Holton Road",
    "sg:city":"Barry",
    "sg:classifiers":[
        {
            "category":"Cafe",
            "type":"Food & Drink"
        }
    ],
    "sg:phone":"+44 1446 700665",
    "sg:postcode":"CF63 4HR",
    "sg:province":"The Vale of Glamorgan",
    "sg:tags":[
        "tea",
        "room"
    ],
    "wof:name":"Lisa's Cafe",
    "wof:placetype":"venue"
},
  "geometry": {"coordinates":[-3.2614340782,51.4072799683],"type":"Point"}
}