{
  "type": "Feature",
  "properties": {
    "addr:full":"60 High Street, Whitton Twickenham Greater London TW2 7LS",
    "addr:housenumber":"60",
    "addr:postcode":"tw2 7ls",
    "addr:street":"High Street",
    "iso:country":"GB",
    "sg:address":"60 High Street, Whitton",
    "sg:city":"Twickenham",
    "sg:classifiers":[
        {
            "category":"Home & Garden",
            "subcategory":"Household Appliances",
            "type":"Retail Goods"
        },
        {
            "category":"Retail",
            "subcategory":"Repair Shop",
            "type":"Services"
        }
    ],
    "sg:phone":"+44 20 8894 9889",
    "sg:postcode":"TW2 7LS",
    "sg:province":"Greater London",
    "sg:tags":[
        "machine",
        "electrical",
        "washing"
    ],
    "wof:name":"R Jones Ltd",
    "wof:placetype":"venue"
},
  "geometry": {"coordinates":[-0.3581990004,51.4515686035],"type":"Point"}
}