{
  "type": "Feature",
  "properties": {
    "addr:full":"35-37 Lord Street Fleetwood Lancashire FY7 6DU",
    "addr:housenumber":"35-37",
    "addr:postcode":"fy7 6du",
    "addr:street":"Lord Street",
    "iso:country":"GB",
    "sg:address":"35-37 Lord Street",
    "sg:city":"Fleetwood",
    "sg:classifiers":[
        {
            "category":"Shopping",
            "subcategory":"Thrift Store",
            "type":"Retail Goods"
        }
    ],
    "sg:phone":"+44 1253 770860",
    "sg:postcode":"FY7 6DU",
    "sg:province":"Lancashire",
    "sg:tags":[
        "shop",
        "charity"
    ],
    "sg:website":"http://www.oxfam.org.uk",
    "wof:name":"Oxfam",
    "wof:placetype":"venue"
},
  "geometry": {"coordinates":[-3.00981,53.923252],"type":"Point"}
}