{
  "type": "Feature",
  "properties": {
    "addr:full":"Office, 1 Cowdray Centre House, Cowdray Avenue Colchester Essex CO1 1GE",
    "addr:housenumber":"1",
    "addr:postcode":"co1 1ge",
    "addr:street":"Cowdray Centre House Cowdray Avenue",
    "iso:country":"GB",
    "sg:address":"Office, 1 Cowdray Centre House, Cowdray Avenue",
    "sg:city":"Colchester",
    "sg:classifiers":[
        {
            "category":"Professional",
            "subcategory":"Accounting & Tax Preparation",
            "type":"Services"
        }
    ],
    "sg:phone":"+44 1206 575041",
    "sg:postcode":"CO1 1GE",
    "sg:province":"Essex",
    "sg:tags":[
        "accountant"
    ],
    "wof:name":"Peters & Co",
    "wof:placetype":"venue"
},
  "geometry": {"coordinates":[0.9086300135,51.8978500366],"type":"Point"}
}