{
  "type": "Feature",
  "properties": {
    "iso:country":"GB",
    "sg:address":"Duncan Ho, Dolphin Sq",
    "sg:city":"London",
    "sg:classifiers":[
        {
            "category":"Professional",
            "subcategory":"Engineering",
            "type":"Services"
        }
    ],
    "sg:postcode":"SW1V 3PS",
    "sg:province":"Greater London",
    "sg:tags":[
        "design",
        "engineer"
    ],
    "wof:name":"Waterfield Odan & Associates",
    "wof:placetype":"venue"
},
  "geometry": {"coordinates":[-0.131204,51.487896],"type":"Point"}
}