{
  "type": "Feature",
  "properties": {
    "addr:full":"100 Townfield Lane, Barnton Northwich Cheshire CW8 4QL",
    "addr:housenumber":"100",
    "addr:postcode":"cw8 4ql",
    "addr:street":"Townfield Lane",
    "iso:country":"GB",
    "sg:address":"100 Townfield Lane, Barnton",
    "sg:city":"Northwich",
    "sg:classifiers":[
        {
            "category":"Professional",
            "subcategory":"Engineering",
            "type":"Services"
        }
    ],
    "sg:phone":"+44 1606 74323",
    "sg:postcode":"CW8 4QL",
    "sg:province":"Cheshire",
    "sg:tags":[
        "contractor",
        "electrical",
        "engineer"
    ],
    "wof:name":"A & A Electrical Services",
    "wof:placetype":"venue"
},
  "geometry": {"coordinates":[-2.5509469509,53.2758674622],"type":"Point"}
}