{
  "type": "Feature",
  "properties": {
    "iso:country":"GB",
    "sg:address":"190 St. Vincent St",
    "sg:city":"Glasgow",
    "sg:classifiers":[
        {
            "category":"Professional",
            "subcategory":"Lawyer & Legal Services",
            "type":"Services"
        }
    ],
    "sg:phone":"+44 141 221 4495",
    "sg:postcode":"G2 5SP",
    "sg:province":"Glasgow City",
    "sg:tags":[
        "solicitor"
    ],
    "wof:name":"Towers-clark Steven & Lyle",
    "wof:placetype":"venue"
},
  "geometry": {"coordinates":[-4.2603340149,55.8620643616],"type":"Point"}
}