{
  "type": "Feature",
  "properties": {
    "addr:full":"454-468 Eastern Avenue, Gants Hill Ilford Essex IG2 6EQ",
    "addr:housenumber":"454-468",
    "addr:postcode":"ig2 6eq",
    "addr:street":"Eastern Avenue",
    "iso:country":"GB",
    "sg:address":"454-468 Eastern Avenue, Gants Hill",
    "sg:city":"Ilford",
    "sg:classifiers":[
        {
            "category":"Manufacturing",
            "subcategory":"Furniture",
            "type":"Manufacturing & Wholesale Goods"
        }
    ],
    "sg:phone":"+44 20 8518 1234",
    "sg:postcode":"IG2 6EQ",
    "sg:province":"Essex",
    "sg:tags":[
        "mnfr",
        "garden",
        "patio"
    ],
    "wof:name":"Leisure Furniture Ltd.",
    "wof:placetype":"venue"
},
  "geometry": {"coordinates":[0.0684750006,51.576007843],"type":"Point"}
}