{
  "type": "Feature",
  "properties": {
    "addr:full":"62-64 Kensington High Street London Greater London W8 4PE",
    "addr:housenumber":"62-64",
    "addr:postcode":"w8 4pe",
    "addr:street":"Kensington High Street",
    "iso:country":"GB",
    "sg:address":"62-64 Kensington High Street",
    "sg:city":"London",
    "sg:classifiers":[
        {
            "category":"Shopping",
            "subcategory":"Music",
            "type":"Retail Goods"
        }
    ],
    "sg:phone":"+44 20 7361 6611",
    "sg:postcode":"W8 4PE",
    "sg:province":"Greater London",
    "sg:tags":[
        "record",
        "tape",
        "cd"
    ],
    "wof:name":"M T S Inc",
    "wof:placetype":"venue"
},
  "geometry": {"coordinates":[-0.1908890009,51.5019989014],"type":"Point"}
}