{
  "type": "Feature",
  "properties": {
    "iso:country":"GB",
    "sg:address":"3 Tower Place",
    "sg:city":"King's Lynn",
    "sg:classifiers":[
        {
            "category":"Retail",
            "subcategory":"Auto Repair",
            "type":"Services"
        }
    ],
    "sg:phone":"+44 1553 773308",
    "sg:postcode":"PE30 5DF",
    "sg:province":"Norfolk",
    "sg:tags":[
        "body",
        "car",
        "repairer"
    ],
    "wof:name":"Mick Culey",
    "wof:placetype":"venue"
},
  "geometry": {"coordinates":[0.39814,52.75169],"type":"Point"}
}