{
  "type": "Feature",
  "properties": {
    "addr:full":"29 Almondvale South Livingston West Lothian EH54 6NB",
    "addr:housenumber":"29",
    "addr:postcode":"eh54 6nb",
    "addr:street":"Almondvale South",
    "iso:country":"GB",
    "sg:address":"29 Almondvale South",
    "sg:city":"Livingston",
    "sg:classifiers":[
        {
            "category":"Travel",
            "subcategory":"Travel Agent",
            "type":"Entertainment"
        }
    ],
    "sg:phone":"+44 1506 430101",
    "sg:postcode":"EH54 6NB",
    "sg:province":"West Lothian",
    "wof:name":"Lunn Poly Ltd.",
    "wof:placetype":"venue"
},
  "geometry": {"coordinates":[-3.5088050365,55.8842964172],"type":"Point"}
}