{
  "type": "Feature",
  "properties": {
    "iso:country":"GB",
    "sg:address":"Croxton Road",
    "sg:city":"Thetford",
    "sg:classifiers":[
        {
            "category":"Bus Charters",
            "type":"Transportation"
        }
    ],
    "sg:phone":"+44 1842 752226",
    "sg:postcode":"IP24 1AG",
    "sg:province":"Norfolk",
    "sg:tags":[
        "hire",
        "coach"
    ],
    "wof:name":"Coach Services Ltd.",
    "wof:placetype":"venue"
},
  "geometry": {"coordinates":[0.755699,52.42765],"type":"Point"}
}