{
  "type": "Feature",
  "properties": {
    "addr:full":"Teesside White Water Course Stockton-on-tees Durham TS18 2QW",
    "addr:postcode":"ts18 2qw",
    "addr:street":"Teesside",
    "iso:country":"GB",
    "sg:address":"Teesside White Water Course",
    "sg:city":"Stockton-on-tees",
    "sg:classifiers":[
        {
            "category":"Recreation",
            "subcategory":"Water Park",
            "type":"Entertainment"
        }
    ],
    "sg:phone":"+44 1642 678000",
    "sg:postcode":"TS18 2QW",
    "sg:province":"Durham",
    "sg:tags":[
        "sport"
    ],
    "wof:name":"Four Seasons",
    "wof:placetype":"venue"
},
  "geometry": {"coordinates":[-1.289139986,54.5653190613],"type":"Point"}
}