{
  "type": "Feature",
  "properties": {
    "addr:full":"Islawrdref Dolgellau Gwynedd LL40 1TS",
    "addr:postcode":"ll40 1ts",
    "addr:street":"Islawrdref",
    "iso:country":"GB",
    "sg:address":"Islawrdref",
    "sg:city":"Dolgellau",
    "sg:classifiers":[
        {
            "category":"Travel",
            "subcategory":"Hostel",
            "type":"Entertainment"
        }
    ],
    "sg:phone":"+44 1341 423178",
    "sg:postcode":"LL40 1TS",
    "sg:province":"Gwynedd",
    "wof:name":"Caban Cader Idris",
    "wof:placetype":"venue"
},
  "geometry": {"coordinates":[-3.953989,52.723011],"type":"Point"}
}