{
  "type": "Feature",
  "properties": {
    "addr:full":"Unit 14 Fountain Business Centre, Ellis Street Coatbridge North Lanarkshire ML5 3AA",
    "addr:housenumber":"unit 14",
    "addr:postcode":"ml5 3aa",
    "addr:street":"Fountain Business Centre Ellis Street",
    "iso:country":"GB",
    "sg:address":"Unit 14 Fountain Business Centre, Ellis Street",
    "sg:city":"Coatbridge",
    "sg:classifiers":[
        {
            "category":"Real Estate",
            "subcategory":"Architect",
            "type":"Services"
        }
    ],
    "sg:phone":"+44 1236 421659",
    "sg:postcode":"ML5 3AA",
    "sg:province":"North Lanarkshire",
    "wof:name":"Ian F Thomson",
    "wof:placetype":"venue"
},
  "geometry": {"coordinates":[-4.035839,55.858753],"type":"Point"}
}