{
  "type": "Feature",
  "properties": {
    "addr:full":"126 South Lambeth Road London Greater London SW8 1RB",
    "addr:housenumber":"126",
    "addr:postcode":"sw8 1rb",
    "addr:street":"South Lambeth Road",
    "iso:country":"GB",
    "sg:address":"126 South Lambeth Road",
    "sg:city":"London",
    "sg:classifiers":[
        {
            "category":"Bars & Pubs",
            "type":"Food & Drink"
        }
    ],
    "sg:phone":"+44 20 7622 3602",
    "sg:postcode":"SW8 1RB",
    "sg:province":"Greater London",
    "sg:tags":[
        "pubs",
        "house",
        "inn",
        "public",
        "activity"
    ],
    "wof:name":"The Wheatsheaf",
    "wof:placetype":"venue"
},
  "geometry": {"coordinates":[-0.124813,51.480915],"type":"Point"}
}