{
  "type": "Feature",
  "properties": {
    "iso:country":"GB",
    "sg:address":"119 Bridgend Road, Aberkenfig",
    "sg:city":"Bridgend",
    "sg:classifiers":[
        {
            "category":"Retail",
            "subcategory":"Event Space",
            "type":"Services"
        },
        {
            "category":"Shopping",
            "subcategory":"Bicycles & Sporting Goods",
            "type":"Retail Goods"
        },
        {
            "category":"Recreation",
            "subcategory":"Fishing",
            "type":"Entertainment"
        },
        {
            "category":"Shopping",
            "subcategory":"Hobbies, Toys, & Games",
            "type":"Retail Goods"
        }
    ],
    "sg:phone":"+44 1656 722448",
    "sg:postcode":"CF32 9AP",
    "sg:province":"Bridgend",
    "sg:tags":[
        "equipment",
        "angling",
        "sale",
        "boat",
        "gunsmith"
    ],
    "wof:name":"Bridgend Trailercraft Ltd.",
    "wof:placetype":"venue"
},
  "geometry": {"coordinates":[-3.596282,51.539474],"type":"Point"}
}