{
  "type": "Feature",
  "properties": {
    "addr:full":"Bryn Farm, Plas Yw Farm Rd Mold Denbighshire CH7 5QS",
    "addr:postcode":"ch7 5qs",
    "addr:street":"Bryn;Plas;Farm Rd",
    "iso:country":"GB",
    "sg:address":"Bryn Farm, Plas Yw Farm Rd",
    "sg:city":"Mold",
    "sg:classifiers":[
        {
            "category":"Farming",
            "subcategory":"Livestock Farm",
            "type":"Manufacturing & Wholesale Goods"
        }
    ],
    "sg:phone":"+44 1352 740097",
    "sg:postcode":"CH7 5QS",
    "sg:province":"Denbighshire",
    "sg:tags":[
        "others"
    ],
    "wof:name":"J J Platt",
    "wof:placetype":"venue"
},
  "geometry": {"coordinates":[-3.3042280674,53.2466659546],"type":"Point"}
}