{
  "type": "Feature",
  "properties": {
    "iso:country":"GB",
    "sg:address":"Manor Farm, Hockering",
    "sg:city":"Dereham",
    "sg:classifiers":[
        {
            "category":"Farming",
            "subcategory":"Livestock Farm",
            "type":"Manufacturing & Wholesale Goods"
        }
    ],
    "sg:phone":"+44 1603 880330",
    "sg:postcode":"NR20 3AJ",
    "sg:province":"Norfolk",
    "sg:tags":[
        "others"
    ],
    "wof:name":"E G Fish",
    "wof:placetype":"venue"
},
  "geometry": {"coordinates":[1.068213,52.674046],"type":"Point"}
}