{
  "type": "Feature",
  "properties": {
    "iso:country":"GB",
    "sg:address":"Woodall, Redburn Industrial Estate",
    "sg:city":"Enfield",
    "sg:classifiers":[
        {
            "category":"Building & Trades",
            "subcategory":"Cleaning & Sanitation",
            "type":"Services"
        }
    ],
    "sg:phone":"+44 20 8805 8586",
    "sg:postcode":"EN3 4LQ",
    "sg:province":"Greater London",
    "sg:tags":[
        "contracting",
        "commercial"
    ],
    "wof:name":"Courtesy Cleaning Services Ltd",
    "wof:placetype":"venue"
},
  "geometry": {"coordinates":[-0.03793,51.63961],"type":"Point"}
}