{
  "type": "Feature",
  "properties": {
    "addr:full":"2 Copson St Manchester Greater Manchester M20 3HE",
    "addr:housenumber":"2",
    "addr:postcode":"m20 3he",
    "addr:street":"Copson St",
    "iso:country":"GB",
    "sg:address":"2 Copson St",
    "sg:city":"Manchester",
    "sg:classifiers":[
        {
            "category":"Shopping",
            "subcategory":"Thrift Store",
            "type":"Retail Goods"
        }
    ],
    "sg:phone":"+44 161 434 9853",
    "sg:postcode":"M20 3HE",
    "sg:province":"Greater Manchester",
    "sg:tags":[
        "shop",
        "charity"
    ],
    "wof:name":"Age Concern",
    "wof:placetype":"venue"
},
  "geometry": {"coordinates":[-2.2287859917,53.4337348938],"type":"Point"}
}