{
  "type": "Feature",
  "properties": {
    "addr:full":"48 Broadoak Rd, Langford Bristol Somerset BS40 5HB",
    "addr:housenumber":"48",
    "addr:postcode":"bs40 5hb",
    "addr:street":"Broadoak Rd",
    "iso:country":"GB",
    "sg:address":"48 Broadoak Rd, Langford",
    "sg:city":"Bristol",
    "sg:classifiers":[
        {
            "category":"Professional",
            "subcategory":"Printing & Photocopies",
            "type":"Services"
        }
    ],
    "sg:phone":"+44 1934 853232",
    "sg:postcode":"BS40 5HB",
    "sg:province":"Somerset",
    "sg:tags":[
        "plate",
        "lithographic",
        "maker"
    ],
    "wof:name":"The Print & Promotion Company",
    "wof:placetype":"venue"
},
  "geometry": {"coordinates":[-2.790414,51.34021],"type":"Point"}
}