{
  "type": "Feature",
  "properties": {
    "addr:full":"5 Hancock Road London Greater London E3 3DA",
    "addr:housenumber":"5",
    "addr:postcode":"e3 3da",
    "addr:street":"Hancock Road",
    "iso:country":"GB",
    "sg:address":"5 Hancock Road",
    "sg:city":"London",
    "sg:classifiers":[
        {
            "category":"Professional",
            "subcategory":"Printing & Photocopies",
            "type":"Services"
        }
    ],
    "sg:phone":"+44 20 8981 6100",
    "sg:postcode":"E3 3DA",
    "sg:province":"Greater London",
    "sg:tags":[
        "printer"
    ],
    "wof:name":"The Rivington Press Ltd.",
    "wof:placetype":"venue"
},
  "geometry": {"coordinates":[-0.011465,51.527897],"type":"Point"}
}