{
  "type": "Feature",
  "properties": {
    "iso:country":"GB",
    "sg:address":"26 Cromwell Rd",
    "sg:city":"Rugby",
    "sg:classifiers":[
        {
            "category":"Food & Beverages",
            "subcategory":"Groceries & Convenience Stores",
            "type":"Retail Goods"
        }
    ],
    "sg:phone":"+44 1788 330279",
    "sg:postcode":"CV22 5LP",
    "sg:province":"Warwickshire",
    "wof:name":"Cromwell Stores",
    "wof:placetype":"venue"
},
  "geometry": {"coordinates":[-1.250245,52.366951],"type":"Point"}
}