{
  "type": "Feature",
  "properties": {
    "iso:country":"GB",
    "sg:address":"50 St Marychurch Road",
    "sg:city":"Torquay",
    "sg:classifiers":[
        {
            "category":"Travel",
            "subcategory":"Hotels & Motels",
            "type":"Entertainment"
        }
    ],
    "sg:postcode":"TQ1 3JE",
    "sg:province":"Devon",
    "wof:name":"Hotel Fiesta",
    "wof:placetype":"venue"
},
  "geometry": {"coordinates":[-3.531063,50.472637],"type":"Point"}
}