{
  "type": "Feature",
  "properties": {
    "addr:full":"88 Burlington Rd New Malden Surrey KT3 4NT",
    "addr:housenumber":"88",
    "addr:postcode":"kt3 4nt",
    "addr:street":"Burlington Rd",
    "iso:country":"GB",
    "sg:address":"88 Burlington Rd",
    "sg:city":"New Malden",
    "sg:classifiers":[
        {
            "category":"Insurance",
            "subcategory":"Insurance Agent",
            "type":"Services"
        }
    ],
    "sg:phone":"+44 20 8942 7861",
    "sg:postcode":"KT3 4NT",
    "sg:province":"Surrey",
    "wof:name":"Swinton",
    "wof:placetype":"venue"
},
  "geometry": {"coordinates":[-0.24974,51.398903],"type":"Point"}
}