{
  "type": "Feature",
  "properties": {
    "iso:country":"GB",
    "sg:address":"88 Burlington Rd",
    "sg:city":"New Malden",
    "sg:classifiers":[
        {
            "category":"Insurance",
            "subcategory":"Insurance Agent",
            "type":"Services"
        }
    ],
    "sg:phone":"+44 20 8942 7861",
    "sg:postcode":"KT3 4NT",
    "sg:province":"Surrey",
    "wof:name":"Swinton",
    "wof:placetype":"venue"
},
  "geometry": {"coordinates":[-0.24974,51.398903],"type":"Point"}
}