{
  "type": "Feature",
  "properties": {
    "addr:full":"London Underwriting Centre, 3 Minster Court, Mincing Lane Monument Greater London EC3R 7DD",
    "addr:housenumber":"3",
    "addr:postcode":"ec3r 7dd",
    "addr:street":"Minster Court Mincing Lane",
    "iso:country":"GB",
    "sg:address":"London Underwriting Centre, 3 Minster Court, Mincing Lane",
    "sg:city":"Monument",
    "sg:classifiers":[
        {
            "category":"Manufacturing",
            "subcategory":"Tools & Machinery",
            "type":"Manufacturing & Wholesale Goods"
        }
    ],
    "sg:phone":"+44 20 7617 4444",
    "sg:postcode":"EC3R 7DD",
    "sg:province":"Greater London",
    "sg:tags":[
        "society",
        "friendly"
    ],
    "wof:name":"London Insurance & Reinsurance Market Associati",
    "wof:placetype":"venue"
},
  "geometry": {"coordinates":[-0.08105,51.510269],"type":"Point"}
}