{
  "type": "Feature",
  "properties": {
    "iso:country":"GB",
    "sg:address":"2 Washburn Court",
    "sg:city":"Wetherby",
    "sg:classifiers":[
        {
            "category":"Building & Trades",
            "subcategory":"Construction",
            "type":"Services"
        }
    ],
    "sg:postcode":"LS22 7GF",
    "sg:province":"North Yorkshire",
    "sg:tags":[
        "glazier"
    ],
    "wof:name":"M C Hewison",
    "wof:placetype":"venue"
},
  "geometry": {"coordinates":[-1.397443,53.940289],"type":"Point"}
}