{
  "type": "Feature",
  "properties": {
    "iso:country":"GB",
    "sg:address":"Macklington Way, Warrencliff Street, Off Summer Lane",
    "sg:city":"Barnsley",
    "sg:classifiers":[
        {
            "category":"Government",
            "subcategory":"Department Of Motor Vehicles",
            "type":"Public Place"
        }
    ],
    "sg:phone":"+44 1226 203794",
    "sg:postcode":"S70 6DZ",
    "sg:province":"South Yorkshire",
    "sg:tags":[
        "engine",
        "component"
    ],
    "wof:name":"Fairclough Radiators",
    "wof:placetype":"venue"
},
  "geometry": {"coordinates":[-1.4889149666,53.552482605],"type":"Point"}
}