{
  "type": "Feature",
  "properties": {
    "addr:full":"140 Westfield Drive Workington Cumbria CA14 3RW",
    "addr:housenumber":"140",
    "addr:postcode":"ca14 3rw",
    "addr:street":"Westfield Drive",
    "iso:country":"GB",
    "sg:address":"140 Westfield Drive",
    "sg:city":"Workington",
    "sg:classifiers":[
        {
            "category":"Food & Beverages",
            "subcategory":"Meat & Fish",
            "type":"Retail Goods"
        }
    ],
    "sg:phone":"+44 1900 66658",
    "sg:postcode":"CA14 3RW",
    "sg:province":"Cumbria",
    "sg:tags":[
        "chip"
    ],
    "wof:name":"Moorclose Fisheries",
    "wof:placetype":"venue"
},
  "geometry": {"coordinates":[-3.5516610146,54.6298980713],"type":"Point"}
}