{
  "type": "Feature",
  "properties": {
    "addr:full":"9-10 South Promenade Thornton-cleveleys Lancashire FY5 1BZ",
    "addr:housenumber":"9-10",
    "addr:postcode":"fy5 1bz",
    "addr:street":"South Promenade Thornton-Cleveleys",
    "iso:country":"GB",
    "sg:address":"9-10 South Promenade",
    "sg:city":"Thornton-cleveleys",
    "sg:classifiers":[
        {
            "category":"Travel",
            "subcategory":"Hotels & Motels",
            "type":"Entertainment"
        },
        {
            "category":"Bars & Pubs",
            "subcategory":"Hookah Bar",
            "type":"Food & Drink"
        }
    ],
    "sg:phone":"+44 1253 858347",
    "sg:postcode":"FY5 1BZ",
    "sg:province":"Lancashire",
    "sg:tags":[
        "self",
        "holiday",
        "catering"
    ],
    "wof:name":"Cleveleys Holiday Appartments",
    "wof:placetype":"venue"
},
  "geometry": {"coordinates":[-3.046986,53.877487],"type":"Point"}
}