{
  "type": "Feature",
  "properties": {
    "addr:full":"45 Windmill Hill Enfield Greater London EN2 7AE",
    "addr:housenumber":"45",
    "addr:postcode":"en2 7ae",
    "addr:street":"Windmill Hill",
    "iso:country":"GB",
    "sg:address":"45 Windmill Hill",
    "sg:city":"Enfield",
    "sg:classifiers":[
        {
            "category":"Personal",
            "subcategory":"Beauty Salon",
            "type":"Services"
        }
    ],
    "sg:phone":"+44 20 8363 2236",
    "sg:postcode":"EN2 7AE",
    "sg:province":"Greater London",
    "sg:tags":[
        "unisex",
        "hairdresser"
    ],
    "wof:name":"Rosalie Gibbs Hair Salon",
    "wof:placetype":"venue"
},
  "geometry": {"coordinates":[-0.09217,51.653492],"type":"Point"}
}