{
  "type": "Feature",
  "properties": {
    "iso:country":"GB",
    "sg:address":"74 Brick Lane",
    "sg:city":"London",
    "sg:classifiers":[
        {
            "category":"Cinema",
            "subcategory":"Movie Rental",
            "type":"Entertainment"
        }
    ],
    "sg:phone":"+44 20 7247 2547",
    "sg:postcode":"E1 6RL",
    "sg:province":"Greater London",
    "sg:tags":[
        "video",
        "library"
    ],
    "wof:name":"Brick Lane Music House Ltd.",
    "wof:placetype":"venue"
},
  "geometry": {"coordinates":[-0.0720760003,51.5201835632],"type":"Point"}
}