{
  "type": "Feature",
  "properties": {
    "addr:full":"70-72 Liverpool Road Manchester Greater Manchester M30 0WA",
    "addr:housenumber":"70-72",
    "addr:postcode":"m30 0wa",
    "addr:street":"Liverpool Road",
    "iso:country":"GB",
    "sg:address":"70-72 Liverpool Road",
    "sg:city":"Manchester",
    "sg:classifiers":[
        {
            "category":"Shopping",
            "subcategory":"Department Store",
            "type":"Retail Goods"
        }
    ],
    "sg:postcode":"M30 0WA",
    "sg:province":"Greater Manchester",
    "wof:name":"Davray Carpets",
    "wof:placetype":"venue"
},
  "geometry": {"coordinates":[-2.3444368839,53.4828720093],"type":"Point"}
}