{
  "type": "Feature",
  "properties": {
    "iso:country":"GB",
    "sg:address":"Bath Road, Colerne",
    "sg:city":"Chippenham",
    "sg:classifiers":[
        {
            "category":"Shopping",
            "subcategory":"Florist",
            "type":"Retail Goods"
        }
    ],
    "sg:phone":"+44 1225 742985",
    "sg:postcode":"SN14 8EQ",
    "sg:province":"Gloucestershire",
    "wof:name":"Eileens Flower Shop",
    "wof:placetype":"venue"
},
  "geometry": {"coordinates":[-2.260508,51.439911],"type":"Point"}
}