{
  "type": "Feature",
  "properties": {
    "addr:full":"21 The Hopmarket Worcester Worcestershire WR1 1DL",
    "addr:housenumber":"21",
    "addr:postcode":"wr1 1dl",
    "addr:street":"The Hopmarket",
    "iso:country":"GB",
    "sg:address":"21 The Hopmarket",
    "sg:city":"Worcester",
    "sg:classifiers":[
        {
            "category":"Shopping",
            "subcategory":"Computers & Home Electronics",
            "type":"Retail Goods"
        }
    ],
    "sg:phone":"+44 1905 731178",
    "sg:postcode":"WR1 1DL",
    "sg:province":"Worcestershire",
    "sg:tags":[
        "candle",
        "household"
    ],
    "wof:name":"C L Candelcraft",
    "wof:placetype":"venue"
},
  "geometry": {"coordinates":[-2.2215139866,52.1940002441],"type":"Point"}
}