{
  "type": "Feature",
  "properties": {
    "iso:country":"GB",
    "sg:address":"10a Atcost Rd",
    "sg:city":"Barking",
    "sg:classifiers":[
        {
            "category":"Shopping",
            "type":"Retail Goods"
        }
    ],
    "sg:phone":"+44 20 8507 3545",
    "sg:postcode":"IG11 0EQ",
    "sg:province":"Essex",
    "sg:tags":[
        "bag"
    ],
    "wof:name":"Superfastenings Ltd",
    "wof:placetype":"venue"
},
  "geometry": {"coordinates":[0.1042049974,51.5168190002],"type":"Point"}
}