{
  "type": "Feature",
  "properties": {
    "addr:full":"Unit 2 Kings Business Pk, Kings Rd Birmingham West Midlands B44 9HP",
    "addr:housenumber":"unit 2",
    "addr:postcode":"b44 9hp",
    "addr:street":"Kings Business Pk Kings Rd",
    "iso:country":"GB",
    "sg:address":"Unit 2 Kings Business Pk, Kings Rd",
    "sg:city":"Birmingham",
    "sg:classifiers":[
        {
            "category":"Professional",
            "type":"Services"
        },
        {
            "category":"Professional",
            "subcategory":"Printing & Photocopies",
            "type":"Services"
        }
    ],
    "sg:postcode":"B44 9HP",
    "sg:province":"West Midlands",
    "sg:tags":[
        "directory",
        "plate",
        "lithographic",
        "maker",
        "pub"
    ],
    "wof:name":"Howson,Anthony,",
    "wof:placetype":"venue"
},
  "geometry": {"coordinates":[-1.8972899914,52.5545654297],"type":"Point"}
}