{
  "type": "Feature",
  "properties": {
    "addr:full":"54 Butts Road, Raunds Wellingborough Northamptonshire NN9 6JG",
    "addr:housenumber":"54",
    "addr:postcode":"nn9 6jg",
    "addr:street":"Butts Road",
    "iso:country":"GB",
    "sg:address":"54 Butts Road, Raunds",
    "sg:city":"Wellingborough",
    "sg:classifiers":[
        {
            "category":"Wholesale",
            "subcategory":"Machinery & Supplies",
            "type":"Manufacturing & Wholesale Goods"
        }
    ],
    "sg:phone":"+44 1933 622307",
    "sg:postcode":"NN9 6JG",
    "sg:province":"Northamptonshire",
    "sg:tags":[
        "industrial",
        "commercial"
    ],
    "wof:name":"Metafix (U K) Ltd.",
    "wof:placetype":"venue"
},
  "geometry": {"coordinates":[-0.528435,52.346249],"type":"Point"}
}