{
  "type": "Feature",
  "properties": {
    "addr:full":"15-16 Aston Road, Waterlooville Portsmouth Hampshire PO7 7XG",
    "addr:housenumber":"15-16",
    "addr:postcode":"hampshire po7 7xg",
    "addr:street":"Aston Road",
    "iso:country":"GB",
    "sg:address":"15-16 Aston Road, Waterlooville",
    "sg:city":"Portsmouth",
    "sg:classifiers":[
        {
            "category":"Manufacturing",
            "subcategory":"Rubber & Plastics",
            "type":"Manufacturing & Wholesale Goods"
        },
        {
            "category":"Manufacturing",
            "subcategory":"Tobacco Products",
            "type":"Manufacturing & Wholesale Goods"
        }
    ],
    "sg:phone":"+44 23 9225 9500",
    "sg:postcode":"PO7 7XG",
    "sg:province":"Hampshire",
    "sg:tags":[
        "ind",
        "manufacturer"
    ],
    "wof:name":"Sunlight Plastics Ltd",
    "wof:placetype":"venue"
},
  "geometry": {"coordinates":[-1.03483,50.885353],"type":"Point"}
}