{
  "type": "Feature",
  "properties": {
    "iso:country":"GB",
    "sg:address":"21 New Street",
    "sg:city":"Dudley",
    "sg:classifiers":[
        {
            "category":"Shopping",
            "subcategory":"Discount & Variety Stores",
            "type":"Retail Goods"
        }
    ],
    "sg:postcode":"DY1 1LT",
    "sg:province":"West Midlands",
    "sg:tags":[
        "shop",
        "model"
    ],
    "wof:name":"The Model Shop",
    "wof:placetype":"venue"
},
  "geometry": {"coordinates":[-2.082411,52.51115],"type":"Point"}
}