{
  "type": "Feature",
  "properties": {
    "addr:full":"316 Hindley Rd, Westhoughton Bolton Lancashire BL5 2DT",
    "addr:housenumber":"316",
    "addr:postcode":"bl5 2dt",
    "addr:street":"Hindley Rd",
    "iso:country":"GB",
    "sg:address":"316 Hindley Rd, Westhoughton",
    "sg:city":"Bolton",
    "sg:classifiers":[
        {
            "category":"Professional",
            "subcategory":"Detective & Security Services",
            "type":"Services"
        }
    ],
    "sg:phone":"+44 1942 819520",
    "sg:postcode":"BL5 2DT",
    "sg:province":"Lancashire",
    "sg:tags":[
        "alarm",
        "burglar",
        "system"
    ],
    "wof:name":"Witt,David,",
    "wof:placetype":"venue"
},
  "geometry": {"coordinates":[-2.531201,53.533398],"type":"Point"}
}