{
  "type": "Feature",
  "properties": {
    "iso:country":"GB",
    "sg:address":"65 Wellington Road North",
    "sg:city":"Stockport",
    "sg:classifiers":[
        {
            "category":"Cafe",
            "type":"Food & Drink"
        }
    ],
    "sg:phone":"+44 161 477 2421",
    "sg:postcode":"SK4 2LP",
    "sg:province":"Cheshire",
    "sg:tags":[
        "tea",
        "snack",
        "bar",
        "room"
    ],
    "wof:name":"RASHID MAHMOOD",
    "wof:placetype":"venue"
},
  "geometry": {"coordinates":[-2.169203,53.41552],"type":"Point"}
}