{
  "type": "Feature",
  "properties": {
    "iso:country":"GB",
    "sg:address":"Parkhead Road, New Coundon",
    "sg:city":"Bishop Auckland",
    "sg:classifiers":[
        {
            "category":"Autos & Motor Vehicles",
            "subcategory":"Automobile Sales",
            "type":"Retail Goods"
        }
    ],
    "sg:phone":"+44 1388 605861",
    "sg:postcode":"DL14 8QE",
    "sg:province":"Durham",
    "sg:tags":[
        "commercial"
    ],
    "wof:name":"Weir Valley Commercials",
    "wof:placetype":"venue"
},
  "geometry": {"coordinates":[-1.656159,54.656841],"type":"Point"}
}