{
  "type": "Feature",
  "properties": {
    "iso:country":"GB",
    "sg:address":"60 Greenfield Av",
    "sg:city":"Dinas Powys",
    "sg:classifiers":[
        {
            "category":"Health Services",
            "subcategory":"Dentist",
            "type":"Services"
        }
    ],
    "sg:phone":"+44 29 2051 5151",
    "sg:postcode":"CF64 4BX",
    "sg:province":"The Vale of Glamorgan",
    "wof:name":"B Webber",
    "wof:placetype":"venue"
},
  "geometry": {"coordinates":[-3.219819,51.433029],"type":"Point"}
}