{
  "type": "Feature",
  "properties": {
    "addr:full":"Cilmery Farm, Cilmery Builth Wells Powys LD2 3LG",
    "addr:postcode":"ld2 3lg",
    "addr:street":"Builth Wells",
    "iso:country":"GB",
    "sg:address":"Cilmery Farm, Cilmery",
    "sg:city":"Builth Wells",
    "sg:classifiers":[
        {
            "category":"Farming",
            "subcategory":"Livestock Farm",
            "type":"Manufacturing & Wholesale Goods"
        }
    ],
    "sg:phone":"+44 1982 552680",
    "sg:postcode":"LD2 3LG",
    "sg:province":"Powys",
    "sg:tags":[
        "others"
    ],
    "wof:name":"S & G L JONES",
    "wof:placetype":"venue"
},
  "geometry": {"coordinates":[-3.4030599594,52.148273468],"type":"Point"}
}