{
  "type": "Feature",
  "properties": {
    "addr:full":"1 Bromley Lane Chislehurst Kent BR7 6LH",
    "addr:housenumber":"1",
    "addr:postcode":"br7 6lh",
    "addr:street":"Bromley Lane",
    "iso:country":"GB",
    "sg:address":"1 Bromley Lane",
    "sg:city":"Chislehurst",
    "sg:classifiers":[
        {
            "category":"Building & Trades",
            "subcategory":"Construction",
            "type":"Services"
        }
    ],
    "sg:phone":"+44 1732 220327",
    "sg:postcode":"BR7 6LH",
    "sg:province":"Kent",
    "sg:tags":[
        "builder"
    ],
    "wof:name":"Elite Interiors Ltd.",
    "wof:placetype":"venue"
},
  "geometry": {"coordinates":[0.075718,51.412788],"type":"Point"}
}