{
  "type": "Feature",
  "properties": {
    "addr:full":"79 St John Street Lichfield Staffordshire WS14 9DT",
    "addr:housenumber":"79",
    "addr:postcode":"ws14 9dt",
    "addr:street":"St John Street",
    "iso:country":"GB",
    "sg:address":"79 St John Street",
    "sg:city":"Lichfield",
    "sg:classifiers":[
        {
            "category":"Retail",
            "subcategory":"Auto Repair",
            "type":"Services"
        }
    ],
    "sg:phone":"+44 1543 262379",
    "sg:postcode":"WS14 9DT",
    "sg:province":"Staffordshire",
    "sg:tags":[
        "modification",
        "garage"
    ],
    "wof:name":"The Midland Auto-Electrical Co. (Lichfield) Ltd.",
    "wof:placetype":"venue"
},
  "geometry": {"coordinates":[-1.825446,52.678299],"type":"Point"}
}