{
  "type": "Feature",
  "properties": {
    "iso:country":"GB",
    "sg:address":"34 Anglesey Street",
    "sg:city":"Cannock",
    "sg:classifiers":[
        {
            "category":"Travel",
            "subcategory":"Hotels & Motels",
            "type":"Entertainment"
        }
    ],
    "sg:phone":"+44 1543 422502",
    "sg:postcode":"WS12 5AA",
    "sg:province":"Staffordshire",
    "sg:tags":[
        "house",
        "guest"
    ],
    "wof:name":"York House",
    "wof:placetype":"venue"
},
  "geometry": {"coordinates":[-2.001495,52.709076],"type":"Point"}
}