{
  "type": "Feature",
  "properties": {
    "addr:full":"9 The Crescent, Barham Ipswich Suffolk IP6 0PE",
    "addr:housenumber":"9",
    "addr:postcode":"ip6 0pe",
    "addr:street":"The Crescent",
    "iso:country":"GB",
    "sg:address":"9 The Crescent, Barham",
    "sg:city":"Ipswich",
    "sg:classifiers":[
        {
            "category":"Military Area",
            "subcategory":"Naval Base",
            "type":"Public Place"
        },
        {
            "category":"Retail",
            "subcategory":"Auto Repair",
            "type":"Services"
        }
    ],
    "sg:phone":"+44 1473 830666",
    "sg:postcode":"IP6 0PE",
    "sg:province":"Suffolk",
    "sg:tags":[
        "truck",
        "electrical",
        "van",
        "car",
        "centre"
    ],
    "wof:name":"Paul Fenn",
    "wof:placetype":"venue"
},
  "geometry": {"coordinates":[1.102239,52.118927],"type":"Point"}
}