{
  "type": "Feature",
  "properties": {
    "addr:full":"Holly Hill Garage, Sunderland Rd, Felling Gateshead Tyne and Wear NE10 9NQ",
    "addr:postcode":"ne10 9nq",
    "addr:street":"Sunderland Rd",
    "iso:country":"GB",
    "sg:address":"Holly Hill Garage, Sunderland Rd, Felling",
    "sg:city":"Gateshead",
    "sg:classifiers":[
        {
            "category":"Retail",
            "subcategory":"Auto Repair",
            "type":"Services"
        }
    ],
    "sg:postcode":"NE10 9NQ",
    "sg:province":"Tyne and Wear",
    "sg:tags":[
        "modification",
        "garage"
    ],
    "wof:name":"W N M Commercials",
    "wof:placetype":"venue"
},
  "geometry": {"coordinates":[-1.5694500208,54.9502182007],"type":"Point"}
}