{
  "type": "Feature",
  "properties": {
    "iso:country":"GB",
    "sg:address":"258 Stockport Road, Cheadle Heath",
    "sg:city":"Stockport",
    "sg:classifiers":[
        {
            "category":"Real Estate",
            "subcategory":"Real Estate Agent",
            "type":"Services"
        }
    ],
    "sg:phone":"+44 161 428 4653",
    "sg:postcode":"SK3 0RG",
    "sg:province":"Cheshire",
    "wof:name":"Strepton Ltd.",
    "wof:placetype":"venue"
},
  "geometry": {"coordinates":[-2.194214,53.400421],"type":"Point"}
}