{
  "type": "Feature",
  "properties": {
    "addr:full":"14 Crummock Drive Kendal Cumbria LA9 7PQ",
    "addr:housenumber":"14",
    "addr:postcode":"la9 7pq",
    "addr:street":"Crummock Drive",
    "iso:country":"GB",
    "sg:address":"14 Crummock Drive",
    "sg:city":"Kendal",
    "sg:classifiers":[
        {
            "category":"Shopping",
            "subcategory":"Computers & Home Electronics",
            "type":"Retail Goods"
        }
    ],
    "sg:phone":"+44 1539 721439",
    "sg:postcode":"LA9 7PQ",
    "sg:province":"Cumbria",
    "sg:tags":[
        "aerial",
        "television",
        "radio"
    ],
    "wof:name":"J B Aerial Services",
    "wof:placetype":"venue"
},
  "geometry": {"coordinates":[-2.7296309471,54.3160972595],"type":"Point"}
}