{
  "type": "Feature",
  "properties": {
    "addr:full":"185 Poverest Road Orpington Kent BR5 2DY",
    "addr:housenumber":"185",
    "addr:postcode":"br5 2dy",
    "addr:street":"Poverest Road",
    "iso:country":"GB",
    "sg:address":"185 Poverest Road",
    "sg:city":"Orpington",
    "sg:classifiers":[
        {
            "category":"Building & Trades",
            "subcategory":"Landscaping Services",
            "type":"Services"
        }
    ],
    "sg:postcode":"BR5 2DY",
    "sg:province":"Kent",
    "sg:tags":[
        "gardening"
    ],
    "wof:name":"R & P Squires",
    "wof:placetype":"venue"
},
  "geometry": {"coordinates":[0.0983150005,51.390171051],"type":"Point"}
}