{
  "type": "Feature",
  "properties": {
    "addr:full":"Church Street, Great Harwood Blackburn Lancashire BB6 7NF",
    "addr:postcode":"bb6 7nf",
    "addr:street":"Church Street",
    "iso:country":"GB",
    "sg:address":"Church Street, Great Harwood",
    "sg:city":"Blackburn",
    "sg:classifiers":[
        {
            "category":"Social Services",
            "subcategory":"Child Care",
            "type":"Services"
        },
        {
            "category":"Social Services",
            "subcategory":"Adult Care",
            "type":"Services"
        }
    ],
    "sg:phone":"+44 1254 884065",
    "sg:postcode":"BB6 7NF",
    "sg:province":"Lancashire",
    "sg:tags":[
        "day",
        "centre"
    ],
    "wof:name":"Bank Mill House Centre",
    "wof:placetype":"venue"
},
  "geometry": {"coordinates":[-2.4076440334,53.7870140076],"type":"Point"}
}