{
  "type": "Feature",
  "properties": {
    "iso:country":"GB",
    "sg:address":"Units U-v West Haul Park, Par Moor Rd",
    "sg:city":"St Austell",
    "sg:classifiers":[
        {
            "category":"Manufacturing",
            "subcategory":"Metals",
            "type":"Manufacturing & Wholesale Goods"
        }
    ],
    "sg:phone":"+44 1726 817099",
    "sg:postcode":"PL25 3RF",
    "sg:province":"Cornwall",
    "sg:tags":[
        "steel",
        "fabricator",
        "erectors"
    ],
    "wof:name":"Perry Enterprises",
    "wof:placetype":"venue"
},
  "geometry": {"coordinates":[-4.792324,50.337421],"type":"Point"}
}