{
  "type": "Feature",
  "properties": {
    "addr:full":"Business Station, 19 Goosecroft Road Stirling Stirling FK8 1PF",
    "addr:postcode":"fk8 1pf",
    "addr:street":"Goosecroft Road",
    "iso:country":"GB",
    "sg:address":"Business Station, 19 Goosecroft Road",
    "sg:city":"Stirling",
    "sg:classifiers":[
        {
            "category":"Social Services",
            "type":"Services"
        }
    ],
    "sg:phone":"+44 1786 449606",
    "sg:postcode":"FK8 1PF",
    "sg:province":"Stirling",
    "sg:tags":[
        "disability"
    ],
    "wof:name":"Shopmobility",
    "wof:placetype":"venue"
},
  "geometry": {"coordinates":[-3.9395198822,56.1173591614],"type":"Point"}
}