{
  "type": "Feature",
  "properties": {
    "iso:country":"GB",
    "sg:address":"13 Swan Business Centre, Old Swan La",
    "sg:city":"Hailsham",
    "sg:classifiers":[
        {
            "category":"Professional",
            "subcategory":"Printing & Photocopies",
            "type":"Services"
        }
    ],
    "sg:postcode":"BN27 2BY",
    "sg:province":"East Sussex",
    "sg:tags":[
        "printer"
    ],
    "wof:name":"Fisher,Maurice,",
    "wof:placetype":"venue"
},
  "geometry": {"coordinates":[0.25652,50.865383],"type":"Point"}
}