{
  "type": "Feature",
  "properties": {
    "iso:country":"GB",
    "sg:address":"Unit 1 Oban Livestock Centre, Upper Soroba",
    "sg:city":"Oban",
    "sg:classifiers":[
        {
            "category":"Insurance",
            "subcategory":"Insurance Agent",
            "type":"Services"
        }
    ],
    "sg:phone":"+44 1631 567036",
    "sg:postcode":"PA34 4SD",
    "sg:province":"Argyll and Bute",
    "wof:name":"National Farmers Union",
    "wof:placetype":"venue"
},
  "geometry": {"coordinates":[-5.469119,56.407982],"type":"Point"}
}