{
  "type": "Feature",
  "properties": {
    "addr:full":"Florence St Swindon Wiltshire SN2 1BA",
    "addr:postcode":"sn2 1ba",
    "addr:street":"Florence St",
    "iso:country":"GB",
    "sg:address":"Florence St",
    "sg:city":"Swindon",
    "sg:classifiers":[
        {
            "category":"Place Of Worship",
            "type":"Public Place"
        }
    ],
    "sg:phone":"+44 1793 522273",
    "sg:postcode":"SN2 1BA",
    "sg:province":"Wiltshire",
    "wof:name":"Christian Brethren Mission Hall",
    "wof:placetype":"venue"
},
  "geometry": {"coordinates":[-1.780674,51.571369],"type":"Point"}
}