{
  "type": "Feature",
  "properties": {
    "iso:country":"GB",
    "sg:address":"59 Harrowside",
    "sg:city":"Blackpool",
    "sg:classifiers":[
        {
            "category":"Retail",
            "subcategory":"Auto Repair",
            "type":"Services"
        }
    ],
    "sg:phone":"+44 1253 347596",
    "sg:postcode":"FY4 1QH",
    "sg:province":"Lancashire",
    "sg:tags":[
        "modification",
        "garage"
    ],
    "wof:name":"Harrowside Garage",
    "wof:placetype":"venue"
},
  "geometry": {"coordinates":[-3.052163,53.784222],"type":"Point"}
}