{
  "type": "Feature",
  "properties": {
    "iso:country":"GB",
    "sg:address":"Bede Island Campus, Narborough Road",
    "sg:city":"Leicester",
    "sg:classifiers":[
        {
            "category":"Education",
            "subcategory":"University",
            "type":"Public Place"
        },
        {
            "category":"Education",
            "subcategory":"School",
            "type":"Public Place"
        }
    ],
    "sg:phone":"+44 116 224 2103",
    "sg:postcode":"LE3 0BT",
    "sg:province":"Leicestershire",
    "sg:tags":[
        "local",
        "authority",
        "higher"
    ],
    "wof:name":"LEICESTER COLLEGE",
    "wof:placetype":"venue"
},
  "geometry": {"coordinates":[-1.1506299973,52.6264610291],"type":"Point"}
}