{
  "type": "Feature",
  "properties": {
    "addr:full":"Ashley Ho 250-252 Ashley Rd Poole Dorset BH14 9BZ",
    "addr:housenumber":"250-252",
    "addr:postcode":"bh14 9bz",
    "addr:street":"Ashley;Ashley Rd",
    "iso:country":"GB",
    "sg:address":"Ashley Ho 250-252 Ashley Rd",
    "sg:city":"Poole",
    "sg:classifiers":[
        {
            "category":"Personal",
            "subcategory":"Beauty Salon",
            "type":"Services"
        }
    ],
    "sg:postcode":"BH14 9BZ",
    "sg:province":"Dorset",
    "sg:tags":[
        "unisex",
        "hairdresser"
    ],
    "wof:name":"Headweys Hair Academy",
    "wof:placetype":"venue"
},
  "geometry": {"coordinates":[-1.9324200153,50.7284202576],"type":"Point"}
}