{
  "type": "Feature",
  "properties": {
    "addr:full":"Bryngwyn Road Newport Newport NP20 4JQ",
    "addr:postcode":"np20 4jq",
    "addr:street":"Bryngwyn Road",
    "iso:country":"GB",
    "sg:address":"Bryngwyn Road",
    "sg:city":"Newport",
    "sg:classifiers":[
        {
            "category":"Social Services",
            "subcategory":"Retirement Home",
            "type":"Services"
        },
        {
            "category":"Organizations",
            "subcategory":"Community Association",
            "type":"Services"
        }
    ],
    "sg:phone":"+44 1633 264038",
    "sg:postcode":"NP20 4JQ",
    "sg:province":"Newport",
    "sg:tags":[
        "society",
        "housing",
        "rest"
    ],
    "wof:name":"Home Valley House Warden",
    "wof:placetype":"venue"
},
  "geometry": {"coordinates":[-3.006757,51.586239],"type":"Point"}
}