{
  "type": "Feature",
  "properties": {
    "addr:full":"6 Lochaline Avenue Paisley East Renfrewshire PA2 9ET",
    "addr:housenumber":"6",
    "addr:postcode":"pa2 9et",
    "addr:street":"Lochaline Avenue",
    "iso:country":"GB",
    "sg:address":"6 Lochaline Avenue",
    "sg:city":"Paisley",
    "sg:classifiers":[
        {
            "category":"Government",
            "subcategory":"Post Office",
            "type":"Public Place"
        }
    ],
    "sg:phone":"+44 1505 812524",
    "sg:postcode":"PA2 9ET",
    "sg:province":"East Renfrewshire",
    "wof:name":"Lochaline Avenue Post Office",
    "wof:placetype":"venue"
},
  "geometry": {"coordinates":[-4.453083,55.833237],"type":"Point"}
}