{
  "type": "Feature",
  "properties": {
    "addr:full":"2 Humbledon Park Sunderland Tyne and Wear SR3 4AA",
    "addr:housenumber":"2",
    "addr:postcode":"sr3 4aa",
    "addr:street":"Humbledon Park",
    "iso:country":"GB",
    "sg:address":"2 Humbledon Park",
    "sg:city":"Sunderland",
    "sg:classifiers":[
        {
            "category":"Personal",
            "subcategory":"Beauty Salon",
            "type":"Services"
        }
    ],
    "sg:phone":"+44 191 528 9123",
    "sg:postcode":"SR3 4AA",
    "sg:province":"Tyne and Wear",
    "sg:tags":[
        "unisex",
        "hairdresser"
    ],
    "wof:name":"Jojo's Hair Salon",
    "wof:placetype":"venue"
},
  "geometry": {"coordinates":[-1.404648,54.89259],"type":"Point"}
}