{
  "type": "Feature",
  "properties": {
    "iso:country":"GB",
    "sg:address":"15 St Aubyns Rd",
    "sg:city":"Eastbourne",
    "sg:classifiers":[
        {
            "category":"Travel",
            "subcategory":"Hotels & Motels",
            "type":"Entertainment"
        }
    ],
    "sg:phone":"+44 1323 730000",
    "sg:postcode":"BN22 7AS",
    "sg:province":"East Sussex",
    "sg:tags":[
        "house",
        "guest"
    ],
    "wof:name":"Mona Lisa Guest House",
    "wof:placetype":"venue"
},
  "geometry": {"coordinates":[0.296112,50.77195],"type":"Point"}
}