{
  "type": "Feature",
  "properties": {
    "iso:country":"GB",
    "sg:address":"201a Mayfield Road",
    "sg:city":"Farnborough",
    "sg:classifiers":[
        {
            "category":"Community Center",
            "type":"Public Place"
        }
    ],
    "sg:phone":"+44 1252 398398",
    "sg:postcode":"GU14 8UB",
    "sg:province":"Hampshire",
    "sg:tags":[
        "centre"
    ],
    "wof:name":"Prospect Community Centre",
    "wof:placetype":"venue"
},
  "geometry": {"coordinates":[-0.762849,51.304279],"type":"Point"}
}