{
  "type": "Feature",
  "properties": {
    "addr:full":"755 Old Lode Lane Solihull West Midlands B92 8JE",
    "addr:housenumber":"755",
    "addr:postcode":"b92 8je",
    "addr:street":"Old Lode Lane",
    "iso:country":"GB",
    "sg:address":"755 Old Lode Lane",
    "sg:city":"Solihull",
    "sg:classifiers":[
        {
            "category":"Food & Beverages",
            "subcategory":"Liquor & Beverages",
            "type":"Retail Goods"
        }
    ],
    "sg:phone":"+44 121 722 3700",
    "sg:postcode":"B92 8JE",
    "sg:province":"West Midlands",
    "sg:tags":[
        "beer",
        "spirit",
        "wines"
    ],
    "wof:name":"The Liquor Celler",
    "wof:placetype":"venue"
},
  "geometry": {"coordinates":[-1.778265,52.448147],"type":"Point"}
}