{
  "type": "Feature",
  "properties": {
    "addr:full":"48 Palmerston Street, Bollington Macclesfield Cheshire SK10 5PX",
    "addr:housenumber":"48",
    "addr:postcode":"sk10 5px",
    "addr:street":"Palmerston Street",
    "iso:country":"GB",
    "sg:address":"48 Palmerston Street, Bollington",
    "sg:city":"Macclesfield",
    "sg:classifiers":[
        {
            "category":"Bars & Pubs",
            "type":"Food & Drink"
        }
    ],
    "sg:phone":"+44 1625 573883",
    "sg:postcode":"SK10 5PX",
    "sg:province":"Cheshire",
    "sg:tags":[
        "pubs",
        "house",
        "inn",
        "public",
        "activity"
    ],
    "wof:name":"The Meridian Inn",
    "wof:placetype":"venue"
},
  "geometry": {"coordinates":[-2.0947089195,53.2979888916],"type":"Point"}
}