{
  "type": "Feature",
  "properties": {
    "addr:full":"148 Busby Road Glasgow East Renfrewshire G76 8BH",
    "addr:housenumber":"148",
    "addr:postcode":"g76 8bh",
    "addr:street":"Busby Road",
    "iso:country":"GB",
    "sg:address":"148 Busby Road",
    "sg:city":"Glasgow",
    "sg:classifiers":[
        {
            "category":"Food & Beverages",
            "subcategory":"Meat & Fish",
            "type":"Retail Goods"
        }
    ],
    "sg:phone":"+44 141 644 1326",
    "sg:postcode":"G76 8BH",
    "sg:province":"East Renfrewshire",
    "sg:tags":[
        "butcher"
    ],
    "wof:name":"A Shaw Butchers",
    "wof:placetype":"venue"
},
  "geometry": {"coordinates":[-4.273153,55.785297],"type":"Point"}
}