{
  "type": "Feature",
  "properties": {
    "iso:country":"GB",
    "sg:address":"1382 - 1386 Leeds Road",
    "sg:city":"Bradford",
    "sg:classifiers":[
        {
            "category":"Food & Beverages",
            "subcategory":"Fruits & Vegetables",
            "type":"Retail Goods"
        },
        {
            "category":"Food & Beverages",
            "subcategory":"Groceries & Convenience Stores",
            "type":"Retail Goods"
        }
    ],
    "sg:phone":"+44 1274 665239",
    "sg:postcode":"BD3 7AE",
    "sg:province":"West Yorkshire",
    "sg:tags":[
        "grocer",
        "greengrocer"
    ],
    "wof:name":"Ahmed Foods",
    "wof:placetype":"venue"
},
  "geometry": {"coordinates":[-1.711321,53.797745],"type":"Point"}
}