{
  "type": "Feature",
  "properties": {
    "addr:full":"Elmfield Lodge, 2 Bennetthorpe Doncaster South Yorkshire DN2 6AD",
    "addr:housenumber":"2",
    "addr:postcode":"dn2 6ad",
    "addr:street":"Bennetthorpe Doncaster South",
    "iso:country":"GB",
    "sg:address":"Elmfield Lodge, 2 Bennetthorpe",
    "sg:city":"Doncaster",
    "sg:classifiers":[
        {
            "category":"Organizations",
            "subcategory":"Community Association",
            "type":"Services"
        },
        {
            "category":"Organizations",
            "subcategory":"Membership Organization",
            "type":"Services"
        }
    ],
    "sg:phone":"+44 1302 364397",
    "sg:postcode":"DN2 6AD",
    "sg:province":"South Yorkshire",
    "sg:tags":[
        "club",
        "social"
    ],
    "wof:name":"Doncaster Comrades Of The Great War Social Club",
    "wof:placetype":"venue"
},
  "geometry": {"coordinates":[-1.1157000065,53.5192298889],"type":"Point"}
}