{
  "type": "Feature",
  "properties": {
    "addr:full":"The Boat Yard, Balmaha Glasgow Argyll and Bute G63 0JG",
    "addr:postcode":"g63 0jg",
    "iso:country":"GB",
    "sg:address":"The Boat Yard, Balmaha",
    "sg:city":"Glasgow",
    "sg:classifiers":[
        {
            "category":"Recreation",
            "subcategory":"Boat Charter",
            "type":"Entertainment"
        }
    ],
    "sg:phone":"+44 1360 870214",
    "sg:postcode":"G63 0JG",
    "sg:province":"Argyll and Bute",
    "sg:tags":[
        "excursion"
    ],
    "wof:name":"Macfarlane & Son",
    "wof:placetype":"venue"
},
  "geometry": {"coordinates":[-4.5432319641,56.0849380493],"type":"Point"}
}