{
  "type": "Feature",
  "properties": {
    "addr:full":"46-48 Bradford Road Brighouse West Yorkshire HD6 1RY",
    "addr:housenumber":"46-48",
    "addr:postcode":"hd6 1ry",
    "addr:street":"Bradford Road",
    "iso:country":"GB",
    "sg:address":"46-48 Bradford Road",
    "sg:city":"Brighouse",
    "sg:classifiers":[
        {
            "category":"Health Services",
            "subcategory":"Dentist",
            "type":"Services"
        }
    ],
    "sg:phone":"+44 1484 716246",
    "sg:postcode":"HD6 1RY",
    "sg:province":"West Yorkshire",
    "wof:name":"A D Hewitt & Associates",
    "wof:placetype":"venue"
},
  "geometry": {"coordinates":[-1.778386,53.703526],"type":"Point"}
}