{
  "type": "Feature",
  "properties": {
    "iso:country":"GB",
    "sg:address":"3 The Pound, Holnest",
    "sg:city":"Sherborne",
    "sg:classifiers":[
        {
            "category":"Building & Trades",
            "subcategory":"Landscaping Services",
            "type":"Services"
        }
    ],
    "sg:phone":"+44 1963 210336",
    "sg:postcode":"DT9 5PT",
    "sg:province":"Dorset",
    "sg:tags":[
        "gardening"
    ],
    "wof:name":"Nipper Roberts",
    "wof:placetype":"venue"
},
  "geometry": {"coordinates":[-2.470294,50.935192],"type":"Point"}
}