{
  "type": "Feature",
  "properties": {
    "iso:country":"GB",
    "sg:address":"Duffins Farm, Lotts Bridge, Threeholes",
    "sg:city":"Wisbech",
    "sg:classifiers":[
        {
            "category":"Travel",
            "subcategory":"Travel Agent",
            "type":"Entertainment"
        }
    ],
    "sg:phone":"+44 1354 638315",
    "sg:postcode":"PE14 9JG",
    "sg:province":"Cambridgeshire",
    "wof:name":"Big Sky U K Safaris Ltd",
    "wof:placetype":"venue"
},
  "geometry": {"coordinates":[0.2190500051,52.5815162659],"type":"Point"}
}