{
  "type": "Feature",
  "properties": {
    "iso:country":"GB",
    "sg:address":"Unit F8, The Mayford Centre, Mayford Grn",
    "sg:city":"Woking",
    "sg:classifiers":[
        {
            "category":"Professional",
            "subcategory":"Printing & Photocopies",
            "type":"Services"
        }
    ],
    "sg:phone":"+44 1483 728323",
    "sg:postcode":"GU22 0PP",
    "sg:province":"Surrey",
    "sg:tags":[
        "printer"
    ],
    "wof:name":"Impress Graphics",
    "wof:placetype":"venue"
},
  "geometry": {"coordinates":[-0.572559,51.296757],"type":"Point"}
}