{
  "type": "Feature",
  "properties": {
    "addr:full":"20 Abbey Close, Ampthill Bedford Bedfordshire MK45 2SH",
    "addr:housenumber":"20",
    "addr:postcode":"mk45 2sh",
    "addr:street":"Abbey Close",
    "iso:country":"GB",
    "sg:address":"20 Abbey Close, Ampthill",
    "sg:city":"Bedford",
    "sg:classifiers":[
        {
            "category":"Health Services",
            "subcategory":"Health Practitioner",
            "type":"Services"
        }
    ],
    "sg:postcode":"MK45 2SH",
    "sg:province":"Bedfordshire",
    "sg:tags":[
        "physiotherapist"
    ],
    "wof:name":"Bodytune Sports Remedial Massage",
    "wof:placetype":"venue"
},
  "geometry": {"coordinates":[-0.4887880087,52.023651123],"type":"Point"}
}