{
  "type": "Feature",
  "properties": {
    "addr:full":"Thorney Mill Road Iver Berkshire SL0 9AL",
    "addr:postcode":"sl0 9al",
    "addr:street":"Thorney Mill Road",
    "iso:country":"GB",
    "sg:address":"Thorney Mill Road",
    "sg:city":"Iver",
    "sg:classifiers":[
        {
            "category":"Sports & Exercise",
            "subcategory":"Golf",
            "type":"Entertainment"
        }
    ],
    "sg:phone":"+44 1895 422095",
    "sg:postcode":"SL0 9AL",
    "sg:province":"Berkshire",
    "sg:tags":[
        "club",
        "course"
    ],
    "wof:name":"Thorney Park Golf Course",
    "wof:placetype":"venue"
},
  "geometry": {"coordinates":[-0.489864,51.50346],"type":"Point"}
}