{
  "type": "Feature",
  "properties": {
    "addr:full":"Conway Road Llandudno Conwy LL30 1GA",
    "addr:postcode":"ll30 1ga",
    "addr:street":"Conway Road",
    "iso:country":"GB",
    "sg:address":"Conway Road",
    "sg:city":"Llandudno",
    "sg:classifiers":[
        {
            "category":"Government",
            "subcategory":"Court House",
            "type":"Public Place"
        }
    ],
    "sg:phone":"+44 1492 871333",
    "sg:postcode":"LL30 1GA",
    "sg:province":"Conwy",
    "wof:name":"Conwy Magistrates Court",
    "wof:placetype":"venue"
},
  "geometry": {"coordinates":[-3.8206241131,53.3183517456],"type":"Point"}
}