{
  "type": "Feature",
  "properties": {
    "iso:country":"GB",
    "sg:address":"133-135 St James Street",
    "sg:city":"Burnley",
    "sg:classifiers":[
        {
            "category":"Bars & Pubs",
            "type":"Food & Drink"
        }
    ],
    "sg:phone":"+44 1282 414895",
    "sg:postcode":"BB11 1PD",
    "sg:province":"Lancashire",
    "sg:tags":[
        "pubs",
        "inn"
    ],
    "wof:name":"The Garden Bar",
    "wof:placetype":"venue"
},
  "geometry": {"coordinates":[-2.2464339733,53.789768219],"type":"Point"}
}