{
  "type": "Feature",
  "properties": {
    "iso:country":"GB",
    "sg:address":"21 New Jubilee Mkt The Piazza",
    "sg:city":"London",
    "sg:classifiers":[
        {
            "category":"Shopping",
            "subcategory":"Department Store",
            "type":"Retail Goods"
        }
    ],
    "sg:postcode":"WC2E 8HB",
    "sg:province":"Greater London",
    "wof:name":"Peters Discount Cards",
    "wof:placetype":"venue"
},
  "geometry": {"coordinates":[-0.12294,51.512009],"type":"Point"}
}