{
  "type": "Feature",
  "properties": {
    "iso:country":"GB",
    "sg:address":"Railway Approach, St John Street",
    "sg:city":"Bridgwater",
    "sg:classifiers":[
        {
            "category":"Taxi",
            "type":"Transportation"
        },
        {
            "category":"Military Area",
            "subcategory":"Air Force Base",
            "type":"Public Place"
        }
    ],
    "sg:phone":"+44 1278 444334",
    "sg:postcode":"TA6 5HB",
    "sg:province":"Somerset",
    "sg:tags":[
        "mini",
        "hire",
        "private",
        "cab"
    ],
    "wof:name":"Bee-Line Cabs",
    "wof:placetype":"venue"
},
  "geometry": {"coordinates":[-3.0138239861,51.1275558472],"type":"Point"}
}