{
  "type": "Feature",
  "properties": {
    "addr:full":"Unit7, 2a Western Approach South Shields Tyne and Wear NE33 5QU",
    "addr:housenumber":"2a",
    "addr:postcode":"ne33 5qu",
    "addr:street":"Unit7;Western Approach",
    "iso:country":"GB",
    "sg:address":"Unit7, 2a Western Approach",
    "sg:city":"South Shields",
    "sg:classifiers":[
        {
            "category":"Food & Beverages",
            "subcategory":"Bakery",
            "type":"Retail Goods"
        },
        {
            "category":"Home & Garden",
            "subcategory":"Kitchen Supply",
            "type":"Retail Goods"
        }
    ],
    "sg:phone":"+44 191 456 2189",
    "sg:postcode":"NE33 5QU",
    "sg:province":"Tyne and Wear",
    "sg:tags":[
        "confectioner",
        "baker",
        "confectionery"
    ],
    "wof:name":"J W Rae",
    "wof:placetype":"venue"
},
  "geometry": {"coordinates":[-1.4353239536,54.9910736084],"type":"Point"}
}