{
  "type": "Feature",
  "properties": {
    "addr:full":"Unit 4 Wimbledon Bridge, Wimbledon London Greater London SW19 3RU",
    "addr:housenumber":"unit 4",
    "addr:postcode":"sw19 3ru",
    "addr:street":"Wimbledon Bridge",
    "iso:country":"GB",
    "sg:address":"Unit 4 Wimbledon Bridge, Wimbledon",
    "sg:city":"London",
    "sg:classifiers":[
        {
            "category":"Shopping",
            "subcategory":"Clothing, Apparel, & Fashions",
            "type":"Retail Goods"
        }
    ],
    "sg:phone":"+44 20 8545 0544",
    "sg:postcode":"SW19 3RU",
    "sg:province":"Greater London",
    "sg:tags":[
        "shop"
    ],
    "wof:name":"Next Retail Ltd.",
    "wof:placetype":"venue"
},
  "geometry": {"coordinates":[-0.20665,51.420471],"type":"Point"}
}