{
  "type": "Feature",
  "properties": {
    "addr:full":"Nottingham Rd Derby Derbyshire DE21 6LZ",
    "addr:postcode":"de21 6lz",
    "addr:street":"Nottingham Rd",
    "iso:country":"GB",
    "sg:address":"Nottingham Rd",
    "sg:city":"Derby",
    "sg:classifiers":[
        {
            "category":"Organizations",
            "subcategory":"Membership Organization",
            "type":"Services"
        }
    ],
    "sg:phone":"+44 1332 676780",
    "sg:postcode":"DE21 6LZ",
    "sg:province":"Derbyshire",
    "sg:tags":[
        "club"
    ],
    "wof:name":"Cascade Bingo Club",
    "wof:placetype":"venue"
},
  "geometry": {"coordinates":[-1.4461740255,52.9267539978],"type":"Point"}
}