{
  "type": "Feature",
  "properties": {
    "addr:full":"Unit 17 Martello Enterprise Court Littlehampton West Sussex BN17 7PA",
    "addr:housenumber":"unit 17 martello",
    "addr:postcode":"bn17 7pa",
    "addr:street":"Enterprise Court",
    "iso:country":"GB",
    "sg:address":"Unit 17 Martello Enterprise Court",
    "sg:city":"Littlehampton",
    "sg:classifiers":[
        {
            "category":"Utilities",
            "subcategory":"Telephone",
            "type":"Services"
        }
    ],
    "sg:phone":"+44 1903 722222",
    "sg:postcode":"BN17 7PA",
    "sg:province":"West Sussex",
    "sg:tags":[
        "telecommunication"
    ],
    "wof:name":"Communication Systems",
    "wof:placetype":"venue"
},
  "geometry": {"coordinates":[-0.5452960134,50.8312606812],"type":"Point"}
}