{
  "type": "Feature",
  "properties": {
    "iso:country":"GB",
    "sg:address":"24 Eltham Avenue",
    "sg:city":"Slough",
    "sg:classifiers":[
        {
            "category":"Professional",
            "subcategory":"Detective & Security Services",
            "type":"Services"
        }
    ],
    "sg:postcode":"SL1 5TH",
    "sg:province":"Berkshire",
    "sg:tags":[
        "equipment",
        "installers"
    ],
    "wof:name":"S A1 Howes Electrical Contractors",
    "wof:placetype":"venue"
},
  "geometry": {"coordinates":[-0.642256,51.51112],"type":"Point"}
}