{
  "type": "Feature",
  "properties": {
    "addr:full":"Plaxdale Green Road, Stansted Sevenoaks Kent TN15 7PB",
    "addr:postcode":"tn15 7pb",
    "addr:street":"Green Road",
    "iso:country":"GB",
    "sg:address":"Plaxdale Green Road, Stansted",
    "sg:city":"Sevenoaks",
    "sg:classifiers":[
        {
            "category":"Recreation",
            "subcategory":"Campground",
            "type":"Entertainment"
        }
    ],
    "sg:phone":"+44 1732 822261",
    "sg:postcode":"TN15 7PB",
    "sg:province":"Kent",
    "sg:tags":[
        "site",
        "camping"
    ],
    "wof:name":"Thriftwood Camping & Caravan Park",
    "wof:placetype":"venue"
},
  "geometry": {"coordinates":[0.291726,51.328369],"type":"Point"}
}