{
  "type": "Feature",
  "properties": {
    "addr:full":"Godwell Lane Ivybridge Devon PL21 0LE",
    "addr:postcode":"pl21 0le",
    "addr:street":"Godwell Lane",
    "iso:country":"GB",
    "sg:address":"Godwell Lane",
    "sg:city":"Ivybridge",
    "sg:classifiers":[
        {
            "category":"Building & Trades",
            "subcategory":"Construction",
            "type":"Services"
        }
    ],
    "sg:postcode":"PL21 0LE",
    "sg:province":"Devon",
    "sg:tags":[
        "roofing"
    ],
    "wof:name":"F Nurse",
    "wof:placetype":"venue"
},
  "geometry": {"coordinates":[-3.9041340351,50.3897781372],"type":"Point"}
}