{
  "type": "Feature",
  "properties": {
    "addr:full":"80 Tatum St Elephant And Castle Greater London SE17 1QR",
    "addr:housenumber":"80",
    "addr:postcode":"se17 1qr",
    "addr:street":"Tatum St",
    "iso:country":"GB",
    "sg:address":"80 Tatum St",
    "sg:city":"Elephant And Castle",
    "sg:classifiers":[
        {
            "category":"Place Of Worship",
            "type":"Public Place"
        }
    ],
    "sg:phone":"+44 20 7703 3803",
    "sg:postcode":"SE17 1QR",
    "sg:province":"Greater London",
    "wof:name":"St Christophers C Of E Church",
    "wof:placetype":"venue"
},
  "geometry": {"coordinates":[-0.085397,51.490601],"type":"Point"}
}