{
  "type": "Feature",
  "properties": {
    "addr:full":"Pre-school, The Vine Community School, Vine Road Basingstoke Hampshire RG21 5PB",
    "addr:postcode":"rg21 5pb",
    "addr:street":"Vine Road",
    "iso:country":"GB",
    "sg:address":"Pre-school, The Vine Community School, Vine Road",
    "sg:city":"Basingstoke",
    "sg:classifiers":[
        {
            "category":"Farming",
            "subcategory":"Nursery",
            "type":"Manufacturing & Wholesale Goods"
        }
    ],
    "sg:postcode":"RG21 5PB",
    "sg:province":"Hampshire",
    "sg:tags":[
        "creche"
    ],
    "wof:name":"The Vine Centre",
    "wof:placetype":"venue"
},
  "geometry": {"coordinates":[-1.083088994,51.2624435425],"type":"Point"}
}