{
  "type": "Feature",
  "properties": {
    "addr:full":"Pressen Farm Cornhill-on-tweed Northumberland TD12 4RS",
    "addr:postcode":"td12 4rs",
    "addr:street":"Northumberland",
    "iso:country":"GB",
    "sg:address":"Pressen Farm",
    "sg:city":"Cornhill-on-tweed",
    "sg:classifiers":[
        {
            "category":"Farming",
            "subcategory":"Farm",
            "type":"Manufacturing & Wholesale Goods"
        }
    ],
    "sg:phone":"+44 1890 850247",
    "sg:postcode":"TD12 4RS",
    "sg:province":"Northumberland",
    "sg:tags":[
        "mixed",
        "crop"
    ],
    "wof:name":"J B Barr",
    "wof:placetype":"venue"
},
  "geometry": {"coordinates":[-2.220848,55.648235],"type":"Point"}
}