{
  "type": "Feature",
  "properties": {
    "iso:country":"GB",
    "sg:address":"Brewers Loft, Dorchester Rd, Maiden Newton",
    "sg:city":"Dorchester",
    "sg:classifiers":[
        {
            "category":"Home & Garden",
            "subcategory":"Furniture",
            "type":"Retail Goods"
        }
    ],
    "sg:postcode":"DT2 0BD",
    "sg:province":"Dorset",
    "wof:name":"Massey,J,",
    "wof:placetype":"venue"
},
  "geometry": {"coordinates":[-2.5713291168,50.7769088745],"type":"Point"}
}