{
  "type": "Feature",
  "properties": {
    "addr:full":"Health Vistors, 2 St Leonards Road Bournemouth Dorset BH8 8QN",
    "addr:housenumber":"2",
    "addr:postcode":"bh8 8qn",
    "addr:street":"St Leonards Road",
    "iso:country":"GB",
    "sg:address":"Health Vistors, 2 St Leonards Road",
    "sg:city":"Bournemouth",
    "sg:classifiers":[
        {
            "category":"Health Services",
            "subcategory":"Clinic",
            "type":"Services"
        }
    ],
    "sg:phone":"+44 1202 517443",
    "sg:postcode":"BH8 8QN",
    "sg:province":"Dorset",
    "sg:tags":[
        "nh"
    ],
    "wof:name":"Dorset Healthcare N H S Trust",
    "wof:placetype":"venue"
},
  "geometry": {"coordinates":[-1.8617399931,50.7354507446],"type":"Point"}
}