{
  "type": "Feature",
  "properties": {
    "addr:full":"Pantiles Chambers, 85 High St Tunbridge Wells Kent TN1 1YG",
    "addr:housenumber":"85",
    "addr:postcode":"tn1 1yg",
    "addr:street":"High St",
    "iso:country":"GB",
    "sg:address":"Pantiles Chambers, 85 High St",
    "sg:city":"Tunbridge Wells",
    "sg:classifiers":[
        {
            "category":"Organizations",
            "subcategory":"Non-profit Organization",
            "type":"Services"
        }
    ],
    "sg:postcode":"TN1 1YG",
    "sg:province":"Kent",
    "sg:tags":[
        "organisation",
        "voluntary",
        "charity"
    ],
    "wof:name":"Tiger Trust",
    "wof:placetype":"venue"
},
  "geometry": {"coordinates":[0.2635500133,51.1333732605],"type":"Point"}
}