{
  "type": "Feature",
  "properties": {
    "iso:country":"GB",
    "sg:address":"5th Floor, 8 Elliot Place, Clydeway Centre",
    "sg:city":"Glasgow",
    "sg:classifiers":[
        {
            "category":"Professional",
            "subcategory":"Engineering",
            "type":"Services"
        }
    ],
    "sg:postcode":"G3 8EP",
    "sg:province":"Glasgow City",
    "sg:tags":[
        "precision",
        "engineer"
    ],
    "wof:name":"Bar Knight Precision Engineers Ltd.",
    "wof:placetype":"venue"
},
  "geometry": {"coordinates":[-4.2795472145,55.8607978821],"type":"Point"}
}