{
  "type": "Feature",
  "properties": {
    "iso:country":"GB",
    "sg:address":"170 New Street",
    "sg:city":"Torrington",
    "sg:classifiers":[
        {
            "category":"Bars & Pubs",
            "type":"Food & Drink"
        }
    ],
    "sg:postcode":"EX38 8BX",
    "sg:province":"Devon",
    "sg:tags":[
        "pubs",
        "inn"
    ],
    "wof:name":"Torrington Arms",
    "wof:placetype":"venue"
},
  "geometry": {"coordinates":[-4.1504898071,50.9528923035],"type":"Point"}
}