{
  "type": "Feature",
  "properties": {
    "addr:full":"6 The Square, Harmans Water Bracknell Berkshire RG12 9LP",
    "addr:housenumber":"6",
    "addr:postcode":"rg12 9lp",
    "addr:street":"The Square Harmans Water",
    "iso:country":"GB",
    "sg:address":"6 The Square, Harmans Water",
    "sg:city":"Bracknell",
    "sg:classifiers":[
        {
            "category":"Shopping",
            "subcategory":"News",
            "type":"Retail Goods"
        }
    ],
    "sg:phone":"+44 1344 307116",
    "sg:postcode":"RG12 9LP",
    "sg:province":"Berkshire",
    "sg:tags":[
        "newsagent"
    ],
    "wof:name":"Martin The Newsagent",
    "wof:placetype":"venue"
},
  "geometry": {"coordinates":[-0.7339220047,51.4047088623],"type":"Point"}
}