{
  "type": "Feature",
  "properties": {
    "iso:country":"GB",
    "sg:address":"744 Oxford Road",
    "sg:city":"Reading",
    "sg:classifiers":[
        {
            "category":"Insurance",
            "subcategory":"Insurance Agent",
            "type":"Services"
        }
    ],
    "sg:phone":"+44 118 950 8833",
    "sg:postcode":"RG30 1EJ",
    "sg:province":"Berkshire",
    "sg:tags":[
        "broker"
    ],
    "wof:name":"INGOT INSURANCE SERVICES",
    "wof:placetype":"venue"
},
  "geometry": {"coordinates":[-1.0088000298,51.4601745605],"type":"Point"}
}