{
  "type": "Feature",
  "properties": {
    "iso:country":"GB",
    "sg:address":"1st Floor Suite, Trinity Court, Trinity St",
    "sg:city":"Peterborough",
    "sg:classifiers":[
        {
            "category":"Professional",
            "subcategory":"Employment Agencies",
            "type":"Services"
        }
    ],
    "sg:phone":"+44 1733 565488",
    "sg:postcode":"PE1 1DA",
    "sg:province":"Cambridgeshire",
    "sg:tags":[
        "consultant"
    ],
    "wof:name":"Nicholas Andrews & Temps Financial",
    "wof:placetype":"venue"
},
  "geometry": {"coordinates":[-0.245594,52.571526],"type":"Point"}
}