{
  "type": "Feature",
  "properties": {
    "addr:full":"34 & 38 North Street Bridgwater Somerset TA6 3YD",
    "addr:housenumber":"34 & 38",
    "addr:postcode":"ta6 3yd",
    "addr:street":"North Street",
    "iso:country":"GB",
    "sg:address":"34 & 38 North Street",
    "sg:city":"Bridgwater",
    "sg:classifiers":[
        {
            "category":"Professional",
            "subcategory":"Accounting & Tax Preparation",
            "type":"Services"
        }
    ],
    "sg:postcode":"TA6 3YD",
    "sg:province":"Somerset",
    "sg:tags":[
        "accountant"
    ],
    "wof:name":"Michael J Dodden & Co.",
    "wof:placetype":"venue"
},
  "geometry": {"coordinates":[-3.0102961063,51.128074646],"type":"Point"}
}