{
  "type": "Feature",
  "properties": {
    "addr:full":"116 High Street Street Somerset BA16 0EW",
    "addr:housenumber":"116",
    "addr:postcode":"ba16 0ew",
    "addr:street":"High Street Street",
    "iso:country":"GB",
    "sg:address":"116 High Street",
    "sg:city":"Street",
    "sg:classifiers":[
        {
            "category":"Shopping",
            "subcategory":"Florist",
            "type":"Retail Goods"
        }
    ],
    "sg:phone":"+44 1458 442845",
    "sg:postcode":"BA16 0EW",
    "sg:province":"Somerset",
    "wof:name":"Mundy's Of Street",
    "wof:placetype":"venue"
},
  "geometry": {"coordinates":[-2.741861,51.1259],"type":"Point"}
}