{
  "type": "Feature",
  "properties": {
    "iso:country":"GB",
    "sg:address":"Whitelands Indust Est, Clarence St",
    "sg:city":"Stalybridge",
    "sg:classifiers":[
        {
            "category":"Shopping",
            "subcategory":"Clothing, Apparel, & Fashions",
            "type":"Retail Goods"
        }
    ],
    "sg:phone":"+44 161 339 5923",
    "sg:postcode":"SK15 1QL",
    "sg:province":"Greater Manchester",
    "sg:tags":[
        "sportswear"
    ],
    "wof:name":"Alpha Sportswear",
    "wof:placetype":"venue"
},
  "geometry": {"coordinates":[-2.057569,53.483543],"type":"Point"}
}