{
  "type": "Feature",
  "properties": {
    "addr:full":"North Road, Wellington Telford Shropshire TF1 3ES",
    "addr:postcode":"tf1 3es",
    "addr:street":"North Road",
    "iso:country":"GB",
    "sg:address":"North Road, Wellington",
    "sg:city":"Telford",
    "sg:classifiers":[
        {
            "category":"Education",
            "subcategory":"School",
            "type":"Public Place"
        }
    ],
    "sg:phone":"+44 1952 242783",
    "sg:postcode":"TF1 3ES",
    "sg:province":"Shropshire",
    "sg:tags":[
        "local",
        "authority"
    ],
    "wof:name":"Park Junior School",
    "wof:placetype":"venue"
},
  "geometry": {"coordinates":[-2.524685,52.706196],"type":"Point"}
}