{
  "type": "Feature",
  "properties": {
    "addr:full":"314 Hook Road Chessington Surrey KT9 1NY",
    "addr:housenumber":"314",
    "addr:postcode":"kt9 1ny",
    "addr:street":"Hook Road",
    "iso:country":"GB",
    "sg:address":"314 Hook Road",
    "sg:city":"Chessington",
    "sg:classifiers":[
        {
            "category":"Retail",
            "subcategory":"Repair Shop",
            "type":"Services"
        },
        {
            "category":"Shopping",
            "subcategory":"Computers & Home Electronics",
            "type":"Retail Goods"
        }
    ],
    "sg:postcode":"KT9 1NY",
    "sg:province":"Surrey",
    "sg:tags":[
        "video",
        "television",
        "aerial",
        "radio"
    ],
    "wof:name":"T V Audio Video Microwave Repair Centre",
    "wof:placetype":"venue"
},
  "geometry": {"coordinates":[-0.3067399859,51.3678436279],"type":"Point"}
}