{
  "type": "Feature",
  "properties": {
    "iso:country":"GB",
    "sg:address":"5 Firwood Park, Chadderton",
    "sg:city":"Oldham",
    "sg:classifiers":[
        {
            "category":"Retail",
            "subcategory":"Driving School",
            "type":"Services"
        }
    ],
    "sg:phone":"+44 7721 384811",
    "sg:postcode":"OL9 9SE",
    "sg:province":"Lancashire",
    "wof:name":"Ladybyrds Driving Academy",
    "wof:placetype":"venue"
},
  "geometry": {"coordinates":[-2.1619501114,53.5488891602],"type":"Point"}
}