{
  "type": "Feature",
  "properties": {
    "iso:country":"GB",
    "sg:address":"249 Torquay Road, Preston",
    "sg:city":"Paignton",
    "sg:classifiers":[
        {
            "category":"Personal",
            "type":"Services"
        }
    ],
    "sg:phone":"+44 1803 523737",
    "sg:postcode":"TQ3 2HL",
    "sg:province":"Devon",
    "sg:tags":[
        "dressmaker"
    ],
    "wof:name":"Modella",
    "wof:placetype":"venue"
},
  "geometry": {"coordinates":[-3.5627601147,50.444770813],"type":"Point"}
}