{
  "type": "Feature",
  "properties": {
    "addr:full":"Doo'cot Cottage, Braehead, Finavon Forfar Angus DD8 3PX",
    "addr:housenumber":"braehead",
    "addr:postcode":"dd8 3px",
    "addr:street":"Finavon",
    "iso:country":"GB",
    "sg:address":"Doo'cot Cottage, Braehead, Finavon",
    "sg:city":"Forfar",
    "sg:classifiers":[
        {
            "category":"Shopping",
            "subcategory":"Crafts & Fabrics",
            "type":"Retail Goods"
        }
    ],
    "sg:postcode":"DD8 3PX",
    "sg:province":"Angus",
    "sg:tags":[
        "shop"
    ],
    "wof:name":"Finavon Fabrics",
    "wof:placetype":"venue"
},
  "geometry": {"coordinates":[-2.8278000355,56.6976890564],"type":"Point"}
}