{
  "type": "Feature",
  "properties": {
    "iso:country":"GB",
    "sg:address":"159a Godstone Road, Whyteleafe",
    "sg:city":"Croydon",
    "sg:classifiers":[
        {
            "category":"Manufacturing",
            "subcategory":"Petroleum Products",
            "type":"Manufacturing & Wholesale Goods"
        },
        {
            "category":"Building & Trades",
            "subcategory":"Construction",
            "type":"Services"
        }
    ],
    "sg:phone":"+44 20 8660 8888",
    "sg:postcode":"CR3 0EH",
    "sg:province":"Surrey",
    "sg:tags":[
        "repair",
        "window",
        "glazing",
        "replacement",
        "double"
    ],
    "wof:name":"Coltlight Ltd.",
    "wof:placetype":"venue"
},
  "geometry": {"coordinates":[-0.079753,51.310913],"type":"Point"}
}