{
  "type": "Feature",
  "properties": {
    "addr:full":"4 Cleave Avenue Orpington Kent BR6 7HB",
    "addr:housenumber":"4",
    "addr:postcode":"br6 7hb",
    "addr:street":"Cleave Avenue",
    "iso:country":"GB",
    "sg:address":"4 Cleave Avenue",
    "sg:city":"Orpington",
    "sg:classifiers":[
        {
            "category":"Home & Garden",
            "subcategory":"Kitchen Supply",
            "type":"Retail Goods"
        }
    ],
    "sg:phone":"+44 1689 889990",
    "sg:postcode":"BR6 7HB",
    "sg:province":"Kent",
    "sg:tags":[
        "measuring",
        "scale"
    ],
    "wof:name":"Metax Ltd.",
    "wof:placetype":"venue"
},
  "geometry": {"coordinates":[0.085825,51.356697],"type":"Point"}
}