{
  "type": "Feature",
  "properties": {
    "addr:full":"12 Aketon Road Castleford West Yorkshire WF10 5DJ",
    "addr:housenumber":"12",
    "addr:postcode":"wf10 5dj",
    "addr:street":"Aketon Road",
    "iso:country":"GB",
    "sg:address":"12 Aketon Road",
    "sg:city":"Castleford",
    "sg:classifiers":[
        {
            "category":"Shopping",
            "type":"Retail Goods"
        }
    ],
    "sg:phone":"+44 1977 550524",
    "sg:postcode":"WF10 5DJ",
    "sg:province":"West Yorkshire",
    "sg:tags":[
        "part",
        "accessory"
    ],
    "wof:name":"The Car Shop",
    "wof:placetype":"venue"
},
  "geometry": {"coordinates":[-1.3625910282,53.7163352966],"type":"Point"}
}