{
  "type": "Feature",
  "properties": {
    "iso:country":"GB",
    "sg:address":"Stanwell New Road",
    "sg:city":"Staines",
    "sg:classifiers":[
        {
            "category":"Military Area",
            "subcategory":"Naval Base",
            "type":"Public Place"
        },
        {
            "category":"Retail",
            "subcategory":"Animal Services",
            "type":"Services"
        }
    ],
    "sg:phone":"+44 1784 453148",
    "sg:postcode":"TW18 4HZ",
    "sg:province":"Berkshire",
    "sg:tags":[
        "box",
        "horse",
        "transportation",
        "equine",
        "transporting"
    ],
    "wof:name":"B H C Coach Builders",
    "wof:placetype":"venue"
},
  "geometry": {"coordinates":[-0.4977740049,51.4383201599],"type":"Point"}
}