{
  "type": "Feature",
  "properties": {
    "iso:country":"GB",
    "sg:address":"16 Fisher Street",
    "sg:city":"Workington",
    "sg:classifiers":[
        {
            "category":"Home & Garden",
            "subcategory":"Garden Supply",
            "type":"Retail Goods"
        }
    ],
    "sg:phone":"+44 1900 602219",
    "sg:postcode":"CA14 2EP",
    "sg:province":"Cumbria",
    "sg:tags":[
        "nursery",
        "centre"
    ],
    "wof:name":"Solway Supplies",
    "wof:placetype":"venue"
},
  "geometry": {"coordinates":[-3.552085,54.645191],"type":"Point"}
}