{
  "type": "Feature",
  "properties": {
    "addr:full":"Victoria Chambers, 142 West Nile Street Glasgow Glasgow City G1 2RQ",
    "addr:housenumber":"142",
    "addr:postcode":"g1 2rq",
    "addr:street":"West Nile Street",
    "iso:country":"GB",
    "sg:address":"Victoria Chambers, 142 West Nile Street",
    "sg:city":"Glasgow",
    "sg:classifiers":[
        {
            "category":"Professional",
            "subcategory":"Engineering",
            "type":"Services"
        }
    ],
    "sg:phone":"+44 141 331 2280",
    "sg:postcode":"G1 2RQ",
    "sg:province":"Glasgow City",
    "sg:tags":[
        "consultant",
        "structural"
    ],
    "wof:name":"Structural Partnership Ltd",
    "wof:placetype":"venue"
},
  "geometry": {"coordinates":[-4.2425107956,55.8578071594],"type":"Point"}
}