{
  "type": "Feature",
  "properties": {
    "iso:country":"GB",
    "sg:address":"1st Floor Suite 39a Leicester, Road,",
    "sg:city":"Salford",
    "sg:classifiers":[
        {
            "category":"Professional",
            "subcategory":"Engineering",
            "type":"Services"
        }
    ],
    "sg:postcode":"M7 4AS",
    "sg:province":"Greater Manchester",
    "sg:tags":[
        "contractor",
        "electrical",
        "engineer"
    ],
    "wof:name":"A R Electric (U.K.) Ltd",
    "wof:placetype":"venue"
},
  "geometry": {"coordinates":[-2.249989,53.514374],"type":"Point"}
}