{
  "type": "Feature",
  "properties": {
    "iso:country":"GB",
    "sg:address":"Stows Manor Farm",
    "sg:city":"Skegness",
    "sg:classifiers":[
        {
            "category":"Shopping",
            "subcategory":"Department Store",
            "type":"Retail Goods"
        }
    ],
    "sg:postcode":"PE25 1HY",
    "sg:province":"Lincolnshire",
    "wof:name":"Bobs Camp Shop",
    "wof:placetype":"venue"
},
  "geometry": {"coordinates":[0.337,53.145271],"type":"Point"}
}