{
  "type": "Feature",
  "properties": {
    "addr:full":"42-43 Grainger Market Newcastle-upon-tyne Tyne and Wear NE1 5QG",
    "addr:housenumber":"42-43",
    "addr:postcode":"ne1 5qg",
    "addr:street":"Grainger",
    "iso:country":"GB",
    "sg:address":"42-43 Grainger Market",
    "sg:city":"Newcastle-upon-tyne",
    "sg:classifiers":[
        {
            "category":"Shopping",
            "subcategory":"Florist",
            "type":"Retail Goods"
        }
    ],
    "sg:phone":"+44 191 232 2232",
    "sg:postcode":"NE1 5QG",
    "sg:province":"Tyne and Wear",
    "wof:name":"Mauds Florists",
    "wof:placetype":"venue"
},
  "geometry": {"coordinates":[-1.6148,54.972244],"type":"Point"}
}