{
  "type": "Feature",
  "properties": {
    "addr:full":"Unit 5 1 Petersfield Road, Whitehill Bordon Hampshire GU35 9AR",
    "addr:housenumber":"unit;1",
    "addr:postcode":"gu35 9ar",
    "addr:street":"Petersfield Road",
    "iso:country":"GB",
    "sg:address":"Unit 5 1 Petersfield Road, Whitehill",
    "sg:city":"Bordon",
    "sg:classifiers":[
        {
            "category":"Recreation",
            "subcategory":"Fishing",
            "type":"Entertainment"
        }
    ],
    "sg:phone":"+44 1420 477090",
    "sg:postcode":"GU35 9AR",
    "sg:province":"Hampshire",
    "sg:tags":[
        "equipment",
        "angling"
    ],
    "wof:name":"Nicolette Carter",
    "wof:placetype":"venue"
},
  "geometry": {"coordinates":[-0.8651139736,51.1088562012],"type":"Point"}
}