{
  "type": "Feature",
  "properties": {
    "addr:full":"Able House, Billingham Reach Industrial Estate, Haverton Hill Road Billingham Durham TS23 1PX",
    "addr:postcode":"ts23 1px",
    "addr:street":"Billingham Reach Industrial Estate Haverton Hill Road",
    "iso:country":"GB",
    "sg:address":"Able House, Billingham Reach Industrial Estate, Haverton Hill Road",
    "sg:city":"Billingham",
    "sg:classifiers":[
        {
            "category":"Freight",
            "type":"Transportation"
        }
    ],
    "sg:phone":"+44 1642 560057",
    "sg:postcode":"TS23 1PX",
    "sg:province":"Durham",
    "sg:tags":[
        "overseas",
        "shipping",
        "removal"
    ],
    "wof:name":"Graypen Ltd.",
    "wof:placetype":"venue"
},
  "geometry": {"coordinates":[-1.2630389929,54.5867881775],"type":"Point"}
}