{
  "type": "Feature",
  "properties": {
    "addr:full":"25 Falcon Wood Road Croydon Surrey CR0 9BE",
    "addr:housenumber":"25",
    "addr:postcode":"cr0 9be",
    "addr:street":"Falcon Wood Road",
    "iso:country":"GB",
    "sg:address":"25 Falcon Wood Road",
    "sg:city":"Croydon",
    "sg:classifiers":[
        {
            "category":"Social Services",
            "subcategory":"Job Training",
            "type":"Services"
        }
    ],
    "sg:phone":"+44 1689 842827",
    "sg:postcode":"CR0 9BE",
    "sg:province":"Surrey",
    "sg:tags":[
        "translator",
        "interpreter"
    ],
    "wof:name":"Translations (Croydon) Ltd.",
    "wof:placetype":"venue"
},
  "geometry": {"coordinates":[-0.033148,51.351383],"type":"Point"}
}