{
  "type": "Feature",
  "properties": {
    "iso:country":"GB",
    "sg:address":"4 Causewayhead",
    "sg:city":"Penzance",
    "sg:classifiers":[
        {
            "category":"Home & Garden",
            "subcategory":"Furniture",
            "type":"Retail Goods"
        }
    ],
    "sg:postcode":"TR18 2SN",
    "sg:province":"Cornwall",
    "wof:name":"Discount Furniture",
    "wof:placetype":"venue"
},
  "geometry": {"coordinates":[-5.538366,50.119064],"type":"Point"}
}