{
  "type": "Feature",
  "properties": {
    "addr:full":"Bolham Road Tiverton Devon EX16 6SG",
    "addr:postcode":"ex16 6sg",
    "addr:street":"Bolham Road",
    "iso:country":"GB",
    "sg:address":"Bolham Road",
    "sg:city":"Tiverton",
    "sg:classifiers":[
        {
            "category":"Food & Beverages",
            "subcategory":"Farmers Market",
            "type":"Retail Goods"
        }
    ],
    "sg:phone":"+44 1884 257706",
    "sg:postcode":"EX16 6SG",
    "sg:province":"Devon",
    "sg:tags":[
        "farm",
        "shop",
        "pyo"
    ],
    "wof:name":"Martyn Tapp",
    "wof:placetype":"venue"
},
  "geometry": {"coordinates":[-3.492299,50.913834],"type":"Point"}
}