{
  "type": "Feature",
  "properties": {
    "addr:full":"11 Pickford Lane Bexleyheath Kent DA7 4RD",
    "addr:housenumber":"11",
    "addr:postcode":"da7 4rd",
    "addr:street":"Pickford Lane",
    "iso:country":"GB",
    "sg:address":"11 Pickford Lane",
    "sg:city":"Bexleyheath",
    "sg:classifiers":[
        {
            "category":"Wholesale",
            "subcategory":"Office Equipment",
            "type":"Manufacturing & Wholesale Goods"
        },
        {
            "category":"Autos & Motor Vehicles",
            "subcategory":"Auto Supplies",
            "type":"Retail Goods"
        }
    ],
    "sg:phone":"+44 20 8301 1643",
    "sg:postcode":"DA7 4RD",
    "sg:province":"Kent",
    "sg:tags":[
        "taxi",
        "supplier",
        "taximeter"
    ],
    "wof:name":"Pickford Taxi Garage",
    "wof:placetype":"venue"
},
  "geometry": {"coordinates":[0.132612,51.464134],"type":"Point"}
}