{
  "type": "Feature",
  "properties": {
    "addr:full":"27 Low Farm Place Northampton Northamptonshire NN3 6HY",
    "addr:housenumber":"27",
    "addr:postcode":"nn3 6hy",
    "addr:street":"Low Farm Place",
    "iso:country":"GB",
    "sg:address":"27 Low Farm Place",
    "sg:city":"Northampton",
    "sg:classifiers":[
        {
            "category":"Professional",
            "subcategory":"Art Services",
            "type":"Services"
        }
    ],
    "sg:postcode":"NN3 6HY",
    "sg:province":"Northamptonshire",
    "sg:tags":[
        "consultant",
        "design"
    ],
    "wof:name":"3 D Design Studios Ltd.",
    "wof:placetype":"venue"
},
  "geometry": {"coordinates":[-0.877390027,52.2799377441],"type":"Point"}
}