{
  "type": "Feature",
  "properties": {
    "addr:full":"40 Bridge Street Glasgow South Lanarkshire G72 7EA",
    "addr:housenumber":"40",
    "addr:postcode":"g72 7ea",
    "addr:street":"Bridge Street",
    "iso:country":"GB",
    "sg:address":"40 Bridge Street",
    "sg:city":"Glasgow",
    "sg:classifiers":[
        {
            "category":"Manufacturing",
            "subcategory":"Wood Products",
            "type":"Manufacturing & Wholesale Goods"
        }
    ],
    "sg:phone":"+44 141 641 7577",
    "sg:postcode":"G72 7EA",
    "sg:province":"South Lanarkshire",
    "sg:tags":[
        "packaging",
        "crate",
        "pallets"
    ],
    "wof:name":"T & L Pallets Supplies",
    "wof:placetype":"venue"
},
  "geometry": {"coordinates":[-4.171319,55.820671],"type":"Point"}
}