{
  "type": "Feature",
  "properties": {
    "addr:full":"12 Church Farm Close, Marksbury Bath Somerset BA2 9JG",
    "addr:housenumber":"12",
    "addr:postcode":"ba2 9jg",
    "addr:street":"Church Farm Close",
    "iso:country":"GB",
    "sg:address":"12 Church Farm Close, Marksbury",
    "sg:city":"Bath",
    "sg:classifiers":[
        {
            "category":"Farming",
            "subcategory":"Livestock Farm",
            "type":"Manufacturing & Wholesale Goods"
        }
    ],
    "sg:phone":"+44 1761 470387",
    "sg:postcode":"BA2 9JG",
    "sg:province":"Somerset",
    "sg:tags":[
        "others"
    ],
    "wof:name":"Sidney J Collins",
    "wof:placetype":"venue"
},
  "geometry": {"coordinates":[-2.4820671082,51.3584442139],"type":"Point"}
}