{
  "type": "Feature",
  "properties": {
    "addr:full":"3 Marylands Avenue Hockley Essex SS5 5AQ",
    "addr:housenumber":"3",
    "addr:postcode":"ss5 5aq",
    "addr:street":"Marylands Avenue",
    "iso:country":"GB",
    "sg:address":"3 Marylands Avenue",
    "sg:city":"Hockley",
    "sg:classifiers":[
        {
            "category":"Building & Trades",
            "subcategory":"Construction",
            "type":"Services"
        }
    ],
    "sg:phone":"+44 1702 204250",
    "sg:postcode":"SS5 5AQ",
    "sg:province":"Essex",
    "sg:tags":[
        "joiner",
        "carpenter"
    ],
    "wof:name":"Doors Galore",
    "wof:placetype":"venue"
},
  "geometry": {"coordinates":[0.656554997,51.6060791016],"type":"Point"}
}