{
  "type": "Feature",
  "properties": {
    "addr:full":"91 Bates Avenue Darlington Durham DL3 0TS",
    "addr:housenumber":"91",
    "addr:postcode":"dl3 0ts",
    "addr:street":"Bates Avenue",
    "iso:country":"GB",
    "sg:address":"91 Bates Avenue",
    "sg:city":"Darlington",
    "sg:classifiers":[
        {
            "category":"Personal",
            "subcategory":"Beauty Salon",
            "type":"Services"
        }
    ],
    "sg:postcode":"DL3 0TS",
    "sg:province":"Durham",
    "sg:tags":[
        "lady",
        "hairdresser"
    ],
    "wof:name":"Peter Allen",
    "wof:placetype":"venue"
},
  "geometry": {"coordinates":[-1.5830390453,54.5391807556],"type":"Point"}
}