{
  "type": "Feature",
  "properties": {
    "iso:country":"GB",
    "sg:address":"7 Grove Promenade",
    "sg:city":"Ilkley",
    "sg:classifiers":[
        {
            "category":"Restaurant",
            "type":"Food & Drink"
        }
    ],
    "sg:phone":"+44 1943 601908",
    "sg:postcode":"LS29 8AF",
    "sg:province":"North Yorkshire",
    "sg:tags":[
        "-",
        "italian"
    ],
    "wof:name":"La Sila",
    "wof:placetype":"venue"
},
  "geometry": {"coordinates":[-1.82919,53.924126],"type":"Point"}
}