{
  "type": "Feature",
  "properties": {
    "addr:full":"30 Bewicke Road Wallsend Tyne and Wear NE28 6SH",
    "addr:housenumber":"30",
    "addr:postcode":"ne28 6sh",
    "addr:street":"Bewicke Road",
    "iso:country":"GB",
    "sg:address":"30 Bewicke Road",
    "sg:city":"Wallsend",
    "sg:classifiers":[
        {
            "category":"Shopping",
            "subcategory":"News",
            "type":"Retail Goods"
        }
    ],
    "sg:phone":"+44 191 289 1692",
    "sg:postcode":"NE28 6SH",
    "sg:province":"Tyne and Wear",
    "sg:tags":[
        "newsagent"
    ],
    "wof:name":"Bewicke Stores",
    "wof:placetype":"venue"
},
  "geometry": {"coordinates":[-1.4914250374,54.9915084839],"type":"Point"}
}