{
  "type": "Feature",
  "properties": {
    "iso:country":"GB",
    "sg:address":"Station Road",
    "sg:city":"Looe",
    "sg:classifiers":[
        {
            "category":"Travel",
            "subcategory":"Hotels & Motels",
            "type":"Entertainment"
        }
    ],
    "sg:postcode":"PL13 1HL",
    "sg:province":"Cornwall",
    "wof:name":"Rivercroft Hotel",
    "wof:placetype":"venue"
},
  "geometry": {"coordinates":[-4.4551510811,50.3570518494],"type":"Point"}
}