{
  "type": "Feature",
  "properties": {
    "addr:full":"236 London Rd Stoke On Trent Staffordshire ST4 5RH",
    "addr:housenumber":"236",
    "addr:postcode":"st4 5rh",
    "addr:street":"London Rd",
    "iso:country":"GB",
    "sg:address":"236 London Rd",
    "sg:city":"Stoke On Trent",
    "sg:classifiers":[
        {
            "category":"Home & Garden",
            "subcategory":"Household Appliances",
            "type":"Retail Goods"
        }
    ],
    "sg:phone":"+44 1782 747945",
    "sg:postcode":"ST4 5RH",
    "sg:province":"Staffordshire",
    "sg:tags":[
        "electrical"
    ],
    "wof:name":"B.C Refrigeration",
    "wof:placetype":"venue"
},
  "geometry": {"coordinates":[-2.1886599064,52.9993476868],"type":"Point"}
}