{
  "type": "Feature",
  "properties": {
    "addr:full":"Granada House, 6 Gabriel's Hill Maidstone Kent ME15 6JJ",
    "addr:housenumber":"6",
    "addr:postcode":"me15 6jj",
    "addr:street":"Gabriel'S Hill",
    "iso:country":"GB",
    "sg:address":"Granada House, 6 Gabriel's Hill",
    "sg:city":"Maidstone",
    "sg:classifiers":[
        {
            "category":"Fast Food",
            "type":"Food & Drink"
        }
    ],
    "sg:phone":"+44 1622 751931",
    "sg:postcode":"ME15 6JJ",
    "sg:province":"Kent",
    "sg:tags":[
        "away",
        "take"
    ],
    "wof:name":"Bosphorus Restaurant",
    "wof:placetype":"venue"
},
  "geometry": {"coordinates":[0.470236,51.260792],"type":"Point"}
}