{
  "type": "Feature",
  "properties": {
    "addr:full":"1a Glastonbury Street London Greater London NW6 1QJ",
    "addr:housenumber":"1a",
    "addr:postcode":"nw6 1qj",
    "addr:street":"Glastonbury Street",
    "iso:country":"GB",
    "sg:address":"1a Glastonbury Street",
    "sg:city":"London",
    "sg:classifiers":[
        {
            "category":"Retail",
            "subcategory":"Auto Repair",
            "type":"Services"
        }
    ],
    "sg:phone":"+44 20 7433 1911",
    "sg:postcode":"NW6 1QJ",
    "sg:province":"Greater London",
    "sg:tags":[
        "modification",
        "garage"
    ],
    "wof:name":"Motor Works",
    "wof:placetype":"venue"
},
  "geometry": {"coordinates":[-0.19982,51.550167],"type":"Point"}
}