{
  "type": "Feature",
  "properties": {
    "iso:country":"GB",
    "sg:address":"61 New Peachey La",
    "sg:city":"Uxbridge",
    "sg:classifiers":[
        {
            "category":"Building & Trades",
            "subcategory":"Construction",
            "type":"Services"
        }
    ],
    "sg:phone":"+44 1895 234869",
    "sg:postcode":"UB8 3SY",
    "sg:province":"Buckinghamshire",
    "sg:tags":[
        "bricklaying"
    ],
    "wof:name":"N Bridge",
    "wof:placetype":"venue"
},
  "geometry": {"coordinates":[-0.477636,51.523323],"type":"Point"}
}