{
  "type": "Feature",
  "properties": {
    "addr:full":"Warrington Street Ashton-under-lyne Greater Manchester OL6 7JE",
    "addr:postcode":"ol6 7je",
    "addr:street":"Warrington Street",
    "iso:country":"GB",
    "sg:address":"Warrington Street",
    "sg:city":"Ashton-under-lyne",
    "sg:classifiers":[
        {
            "category":"Commercial Area",
            "type":"Public Place"
        }
    ],
    "sg:phone":"+44 161 339 6228",
    "sg:postcode":"OL6 7JE",
    "sg:province":"Greater Manchester",
    "sg:tags":[
        "shop",
        "centre"
    ],
    "wof:name":"Arcades Shopping Centre",
    "wof:placetype":"venue"
},
  "geometry": {"coordinates":[-2.093774,53.488369],"type":"Point"}
}