{
  "type": "Feature",
  "properties": {
    "addr:full":"3a Hornington Road Burton-on-trent Derbyshire DE14 2PR",
    "addr:housenumber":"3a",
    "addr:postcode":"de14 2pr",
    "addr:street":"Hornington Road",
    "iso:country":"GB",
    "sg:address":"3a Hornington Road",
    "sg:city":"Burton-on-trent",
    "sg:classifiers":[
        {
            "category":"Recreation",
            "subcategory":"Go Karts",
            "type":"Entertainment"
        }
    ],
    "sg:postcode":"DE14 2PR",
    "sg:province":"Derbyshire",
    "sg:tags":[
        "karting"
    ],
    "wof:name":"Dma Leisure Ltd.",
    "wof:placetype":"venue"
},
  "geometry": {"coordinates":[-1.647701,52.804352],"type":"Point"}
}