{
  "type": "Feature",
  "properties": {
    "iso:country":"GB",
    "sg:address":"8 High Street",
    "sg:city":"Cullompton",
    "sg:classifiers":[
        {
            "category":"Shopping",
            "subcategory":"Hobbies, Toys, & Games",
            "type":"Retail Goods"
        }
    ],
    "sg:phone":"+44 1884 32219",
    "sg:postcode":"EX15 1AA",
    "sg:province":"Devon",
    "sg:tags":[
        "shop",
        "toy"
    ],
    "wof:name":"Denners",
    "wof:placetype":"venue"
},
  "geometry": {"coordinates":[-3.3930649757,50.8576316833],"type":"Point"}
}