{
  "type": "Feature",
  "properties": {
    "addr:full":"Blackhall R Kendal Cumbria LA9 4BT",
    "addr:postcode":"la9 4bt",
    "addr:street":"R",
    "iso:country":"GB",
    "sg:address":"Blackhall R",
    "sg:city":"Kendal",
    "sg:classifiers":[
        {
            "category":"Building & Trades",
            "subcategory":"Construction",
            "type":"Services"
        }
    ],
    "sg:phone":"+44 1539 732224",
    "sg:postcode":"LA9 4BT",
    "sg:province":"Cumbria",
    "sg:tags":[
        "platform",
        "work",
        "scaffolding"
    ],
    "wof:name":"Rhino Scaffolding",
    "wof:placetype":"venue"
},
  "geometry": {"coordinates":[-2.748084,54.324001],"type":"Point"}
}