{
  "type": "Feature",
  "properties": {
    "addr:full":"3 Central Avenue Carlisle Cumbria CA1 3QB",
    "addr:housenumber":"3",
    "addr:postcode":"ca1 3qb",
    "addr:street":"Central Avenue",
    "iso:country":"GB",
    "sg:address":"3 Central Avenue",
    "sg:city":"Carlisle",
    "sg:classifiers":[
        {
            "category":"Fast Food",
            "type":"Food & Drink"
        },
        {
            "category":"Food & Beverages",
            "subcategory":"Meat & Fish",
            "type":"Retail Goods"
        }
    ],
    "sg:phone":"+44 1228 526098",
    "sg:postcode":"CA1 3QB",
    "sg:province":"Cumbria",
    "sg:tags":[
        "outlet",
        "chip",
        "meal",
        "away",
        "take"
    ],
    "wof:name":"J Morrison",
    "wof:placetype":"venue"
},
  "geometry": {"coordinates":[-2.9023029804,54.8817863464],"type":"Point"}
}