{
  "type": "Feature",
  "properties": {
    "iso:country":"GB",
    "sg:address":"Rheola Works, Rheola",
    "sg:city":"Neath",
    "sg:classifiers":[
        {
            "category":"Mining & Drilling",
            "type":"Manufacturing & Wholesale Goods"
        }
    ],
    "sg:phone":"+44 1639 711190",
    "sg:postcode":"SA11 4DT",
    "sg:province":"Neath Port Talbot",
    "sg:tags":[
        "coal"
    ],
    "wof:name":"Signal Fern Ltd",
    "wof:placetype":"venue"
},
  "geometry": {"coordinates":[-3.6982591152,51.7096214294],"type":"Point"}
}