{
  "type": "Feature",
  "properties": {
    "iso:country":"GB",
    "sg:address":"191 Skellow Road, Skellow",
    "sg:city":"Doncaster",
    "sg:classifiers":[
        {
            "category":"Fast Food",
            "type":"Food & Drink"
        }
    ],
    "sg:phone":"+44 1302 721456",
    "sg:postcode":"DN6 8HP",
    "sg:province":"North Yorkshire",
    "sg:tags":[
        "away",
        "take"
    ],
    "wof:name":"The Curry House",
    "wof:placetype":"venue"
},
  "geometry": {"coordinates":[-1.192889,53.585449],"type":"Point"}
}