{
  "type": "Feature",
  "properties": {
    "addr:full":"241a Ashley Road Poole Dorset BH14 9DS",
    "addr:housenumber":"241a",
    "addr:postcode":"bh14 9ds",
    "addr:street":"Ashley Road",
    "iso:country":"GB",
    "sg:address":"241a Ashley Road",
    "sg:city":"Poole",
    "sg:classifiers":[
        {
            "category":"Real Estate",
            "subcategory":"Real Estate Agent",
            "type":"Services"
        }
    ],
    "sg:phone":"+44 1202 735413",
    "sg:postcode":"BH14 9DS",
    "sg:province":"Dorset",
    "wof:name":"Mann & Co",
    "wof:placetype":"venue"
},
  "geometry": {"coordinates":[-1.9363119602,50.7285270691],"type":"Point"}
}