{
  "type": "Feature",
  "properties": {
    "addr:full":"11 Kings Street, Bedworth Nuneaton Warwickshire CV12 8HS",
    "addr:housenumber":"11",
    "addr:postcode":"cv12 8hs",
    "addr:street":"Kings Street",
    "iso:country":"GB",
    "sg:address":"11 Kings Street, Bedworth",
    "sg:city":"Nuneaton",
    "sg:classifiers":[
        {
            "category":"Shopping",
            "subcategory":"Discount & Variety Stores",
            "type":"Retail Goods"
        }
    ],
    "sg:phone":"+44 24 7631 5675",
    "sg:postcode":"CV12 8HS",
    "sg:province":"Warwickshire",
    "sg:tags":[
        "surplus"
    ],
    "wof:name":"Next Best Continental Wear",
    "wof:placetype":"venue"
},
  "geometry": {"coordinates":[-1.472127,52.479359],"type":"Point"}
}