{
  "type": "Feature",
  "properties": {
    "addr:full":"14a Barton Business Pk, New Dover Rd Canterbury Kent CT1 3AA",
    "addr:housenumber":"14a",
    "addr:postcode":"ct1 3aa",
    "addr:street":"Business Pk New Dover Rd",
    "iso:country":"GB",
    "sg:address":"14a Barton Business Pk, New Dover Rd",
    "sg:city":"Canterbury",
    "sg:classifiers":[
        {
            "category":"Autos & Motor Vehicles",
            "subcategory":"Automobile Sales",
            "type":"Retail Goods"
        }
    ],
    "sg:postcode":"CT1 3AA",
    "sg:province":"Kent",
    "sg:tags":[
        "car"
    ],
    "wof:name":"Foreman,Peter,",
    "wof:placetype":"venue"
},
  "geometry": {"coordinates":[1.07561,51.27597],"type":"Point"}
}