{
  "type": "Feature",
  "properties": {
    "addr:full":"9 Wallace Way Hitchin Hertfordshire SG4 0SE",
    "addr:housenumber":"9",
    "addr:postcode":"sg4 0se",
    "addr:street":"Wallace Way",
    "iso:country":"GB",
    "sg:address":"9 Wallace Way",
    "sg:city":"Hitchin",
    "sg:classifiers":[
        {
            "category":"Professional",
            "subcategory":"Testing Lab",
            "type":"Services"
        },
        {
            "category":"Retail",
            "subcategory":"Auto Repair",
            "type":"Services"
        }
    ],
    "sg:phone":"+44 1462 455595",
    "sg:postcode":"SG4 0SE",
    "sg:province":"Hertfordshire",
    "sg:tags":[
        "modification",
        "garage",
        "mot"
    ],
    "wof:name":"Autopoint Services",
    "wof:placetype":"venue"
},
  "geometry": {"coordinates":[-0.2681390047,51.9637260437],"type":"Point"}
}