{
  "type": "Feature",
  "properties": {
    "iso:country":"GB",
    "sg:address":"27 Belmont Close",
    "sg:city":"London",
    "sg:classifiers":[
        {
            "category":"Shopping",
            "subcategory":"Pharmacy",
            "type":"Retail Goods"
        }
    ],
    "sg:phone":"+44 20 7720 3207",
    "sg:postcode":"SW4 6AY",
    "sg:province":"Greater London",
    "sg:tags":[
        "medicine",
        "therapy"
    ],
    "wof:name":"The London Shambhala Meditation Centre",
    "wof:placetype":"venue"
},
  "geometry": {"coordinates":[-0.137282,51.465103],"type":"Point"}
}