{
  "type": "Feature",
  "properties": {
    "iso:country":"GB",
    "sg:address":"156 Pickersleigh Rd",
    "sg:city":"Malvern",
    "sg:classifiers":[
        {
            "category":"Building & Trades",
            "subcategory":"Cleaning & Sanitation",
            "type":"Services"
        }
    ],
    "sg:postcode":"WR14 2RX",
    "sg:province":"Herefordshire",
    "sg:tags":[
        "dry",
        "control",
        "damp",
        "rot"
    ],
    "wof:name":"Jones,Trevor,",
    "wof:placetype":"venue"
},
  "geometry": {"coordinates":[-2.3121869564,52.1203651428],"type":"Point"}
}