{
  "type": "Feature",
  "properties": {
    "iso:country":"GB",
    "sg:address":"Milton Road, Drayton",
    "sg:city":"Abingdon",
    "sg:classifiers":[
        {
            "category":"Professional",
            "subcategory":"Engineering",
            "type":"Services"
        }
    ],
    "sg:phone":"+44 1235 531272",
    "sg:postcode":"OX14 4EZ",
    "sg:province":"Oxfordshire",
    "sg:tags":[
        "engineer"
    ],
    "wof:name":"Pipaway Engineering Ltd",
    "wof:placetype":"venue"
},
  "geometry": {"coordinates":[-1.3125040531,51.6438903809],"type":"Point"}
}