{
  "type": "Feature",
  "properties": {
    "addr:full":"Staithe Cottage, Horsey Road, West Somerton Great Yarmouth Norfolk NR29 4EB",
    "addr:postcode":"nr29 4eb",
    "addr:street":"Horsey Road West;Yarmouth",
    "iso:country":"GB",
    "sg:address":"Staithe Cottage, Horsey Road, West Somerton",
    "sg:city":"Great Yarmouth",
    "sg:classifiers":[
        {
            "category":"Professional",
            "subcategory":"Business Services",
            "type":"Services"
        }
    ],
    "sg:phone":"+44 1493 393214",
    "sg:postcode":"NR29 4EB",
    "sg:province":"Norfolk",
    "sg:tags":[
        "planning",
        "supervisor"
    ],
    "wof:name":"N W Grayling",
    "wof:placetype":"venue"
},
  "geometry": {"coordinates":[1.65602,52.719608],"type":"Point"}
}