{
  "type": "Feature",
  "properties": {
    "addr:full":"Fullers Hill Chesham Buckinghamshire HP5 1LR",
    "addr:postcode":"hp5 1lr",
    "addr:street":"Hill",
    "iso:country":"GB",
    "sg:address":"Fullers Hill",
    "sg:city":"Chesham",
    "sg:classifiers":[
        {
            "category":"Building & Trades",
            "subcategory":"Construction",
            "type":"Services"
        }
    ],
    "sg:postcode":"HP5 1LR",
    "sg:province":"Buckinghamshire",
    "sg:tags":[
        "builder"
    ],
    "wof:name":"Amersham Amalgamated Builders Ltd.",
    "wof:placetype":"venue"
},
  "geometry": {"coordinates":[-0.6161649823,51.7011032104],"type":"Point"}
}