{
  "type": "Feature",
  "properties": {
    "addr:full":"11a Goose Green Altrincham Cheshire WA14 1DW",
    "addr:housenumber":"11a",
    "addr:postcode":"wa14 1dw",
    "addr:street":"Goose",
    "iso:country":"GB",
    "sg:address":"11a Goose Green",
    "sg:city":"Altrincham",
    "sg:classifiers":[
        {
            "category":"Professional",
            "subcategory":"Art Services",
            "type":"Services"
        }
    ],
    "sg:phone":"+44 161 926 8444",
    "sg:postcode":"WA14 1DW",
    "sg:province":"Cheshire",
    "sg:tags":[
        "consultant",
        "design"
    ],
    "wof:name":"The Foundry",
    "wof:placetype":"venue"
},
  "geometry": {"coordinates":[-2.3497641087,53.3854484558],"type":"Point"}
}