{
  "type": "Feature",
  "properties": {
    "iso:country":"GB",
    "sg:address":"5 Captains Close",
    "sg:city":"Chesham",
    "sg:classifiers":[
        {
            "category":"Military Area",
            "subcategory":"Air Force Base",
            "type":"Public Place"
        }
    ],
    "sg:phone":"+44 1494 782259",
    "sg:postcode":"HP5 2PP",
    "sg:province":"Buckinghamshire",
    "sg:tags":[
        "taxi",
        "hire",
        "private"
    ],
    "wof:name":"Courtesy Cars",
    "wof:placetype":"venue"
},
  "geometry": {"coordinates":[-0.620694,51.722565],"type":"Point"}
}