{
  "type": "Feature",
  "properties": {
    "iso:country":"GB",
    "sg:address":"81-83 Stokes Croft",
    "sg:city":"Bristol",
    "sg:classifiers":[
        {
            "category":"Bars & Pubs",
            "subcategory":"Nightclub",
            "type":"Food & Drink"
        }
    ],
    "sg:postcode":"BS1 3RD",
    "sg:province":"City of Bristol",
    "sg:tags":[
        "club",
        "night"
    ],
    "wof:name":"Lakota Ltd.",
    "wof:placetype":"venue"
},
  "geometry": {"coordinates":[-2.5901319981,51.462928772],"type":"Point"}
}