{
  "type": "Feature",
  "properties": {
    "addr:full":"Station Garage, 186 High Street North London Greater London E6 2JA",
    "addr:housenumber":"186",
    "addr:postcode":"e6 2ja",
    "addr:street":"High Street North",
    "iso:country":"GB",
    "sg:address":"Station Garage, 186 High Street North",
    "sg:city":"London",
    "sg:classifiers":[
        {
            "category":"Taxi",
            "type":"Transportation"
        }
    ],
    "sg:phone":"+44 20 8552 5555",
    "sg:postcode":"E6 2JA",
    "sg:province":"Greater London",
    "sg:tags":[
        "mini",
        "hire",
        "cab",
        "private",
        "vehicle"
    ],
    "wof:name":"Petchey's Car Hire",
    "wof:placetype":"venue"
},
  "geometry": {"coordinates":[0.0515840016,51.5382499695],"type":"Point"}
}