{
  "type": "Feature",
  "properties": {
    "iso:country":"GB",
    "sg:address":"58a Main Road, Westwood",
    "sg:city":"Oldham",
    "sg:classifiers":[
        {
            "category":"Community Center",
            "subcategory":"Youth",
            "type":"Public Place"
        }
    ],
    "sg:phone":"+44 161 628 7088",
    "sg:postcode":"OL9 6LR",
    "sg:province":"Lancashire",
    "sg:tags":[
        "organisation",
        "centre"
    ],
    "wof:name":"Oldham Bangladeshi Youth Association",
    "wof:placetype":"venue"
},
  "geometry": {"coordinates":[-2.1293981075,53.5456314087],"type":"Point"}
}