{
  "type": "Feature",
  "properties": {
    "addr:full":"18 Watford Road Radlett Hertfordshire WD7 8LE",
    "addr:housenumber":"18",
    "addr:postcode":"wd7 8le",
    "addr:street":"Watford Road",
    "iso:country":"GB",
    "sg:address":"18 Watford Road",
    "sg:city":"Radlett",
    "sg:classifiers":[
        {
            "category":"Professional",
            "subcategory":"Business Services",
            "type":"Services"
        }
    ],
    "sg:phone":"+44 1923 858306",
    "sg:postcode":"WD7 8LE",
    "sg:province":"Hertfordshire",
    "sg:tags":[
        "distributor",
        "film"
    ],
    "wof:name":"Arrow Film Distributors Ltd.",
    "wof:placetype":"venue"
},
  "geometry": {"coordinates":[-0.3261519969,51.6853065491],"type":"Point"}
}