{
  "type": "Feature",
  "properties": {
    "iso:country":"GB",
    "sg:address":"5 Durning Road",
    "sg:city":"Liverpool",
    "sg:classifiers":[
        {
            "category":"Shopping",
            "subcategory":"Department Store",
            "type":"Retail Goods"
        }
    ],
    "sg:phone":"+44 151 263 4176",
    "sg:postcode":"L7 5NB",
    "sg:province":"Merseyside",
    "wof:name":"Sammys Store",
    "wof:placetype":"venue"
},
  "geometry": {"coordinates":[-2.948363,53.40464],"type":"Point"}
}