{
  "type": "Feature",
  "properties": {
    "iso:country":"GB",
    "sg:address":"39 High Street",
    "sg:city":"Horley",
    "sg:classifiers":[
        {
            "category":"Professional",
            "subcategory":"Employment Agencies",
            "type":"Services"
        }
    ],
    "sg:postcode":"RH6 7BN",
    "sg:province":"Surrey",
    "sg:tags":[
        "airline"
    ],
    "wof:name":"Skyplan Services (uk) Ltd",
    "wof:placetype":"venue"
},
  "geometry": {"coordinates":[-0.1617570072,51.1728782654],"type":"Point"}
}