{
  "type": "Feature",
  "properties": {
    "iso:country":"GB",
    "sg:address":"15 Bridge Street",
    "sg:city":"Aberystwyth",
    "sg:classifiers":[
        {
            "category":"Home & Garden",
            "subcategory":"Furniture",
            "type":"Retail Goods"
        }
    ],
    "sg:postcode":"SY23 1PZ",
    "sg:province":"Ceredigion",
    "wof:name":"R Benjamin & Son",
    "wof:placetype":"venue"
},
  "geometry": {"coordinates":[-4.085878849,52.4139137268],"type":"Point"}
}