{
  "type": "Feature",
  "properties": {
    "addr:full":"289 Maxwell Road Glasgow Glasgow City G41 1TD",
    "addr:housenumber":"289",
    "addr:postcode":"g41 1td",
    "addr:street":"Maxwell Road",
    "iso:country":"GB",
    "sg:address":"289 Maxwell Road",
    "sg:city":"Glasgow",
    "sg:classifiers":[
        {
            "category":"Travel",
            "subcategory":"Travel Agent",
            "type":"Entertainment"
        }
    ],
    "sg:postcode":"G41 1TD",
    "sg:province":"Glasgow City",
    "wof:name":"Madina Travel & Freight",
    "wof:placetype":"venue"
},
  "geometry": {"coordinates":[-4.273437,55.844254],"type":"Point"}
}