{
  "type": "Feature",
  "properties": {
    "iso:country":"GB",
    "sg:address":"20 Melton Street",
    "sg:city":"Mexborough",
    "sg:classifiers":[
        {
            "category":"Bus Charters",
            "type":"Transportation"
        }
    ],
    "sg:phone":"+44 1709 585359",
    "sg:postcode":"S64 0EZ",
    "sg:province":"South Yorkshire",
    "sg:tags":[
        "hire",
        "coach"
    ],
    "wof:name":"L L Travel",
    "wof:placetype":"venue"
},
  "geometry": {"coordinates":[-1.2752029896,53.4927444458],"type":"Point"}
}