{
  "type": "Feature",
  "properties": {
    "addr:full":"30 Ridge Road Sutton Surrey SM3 9LJ",
    "addr:housenumber":"30",
    "addr:postcode":"sm3 9lj",
    "addr:street":"Ridge Road",
    "iso:country":"GB",
    "sg:address":"30 Ridge Road",
    "sg:city":"Sutton",
    "sg:classifiers":[
        {
            "category":"Building & Trades",
            "subcategory":"Construction",
            "type":"Services"
        }
    ],
    "sg:phone":"+44 20 8644 1175",
    "sg:postcode":"SM3 9LJ",
    "sg:province":"Surrey",
    "sg:tags":[
        "roofing"
    ],
    "wof:name":"K W Porter Roofing Ltd.",
    "wof:placetype":"venue"
},
  "geometry": {"coordinates":[-0.2058590055,51.3820533752],"type":"Point"}
}