{
  "type": "Feature",
  "properties": {
    "iso:country":"GB",
    "sg:address":"58 Station Road, Marston Grn",
    "sg:city":"Birmingham",
    "sg:classifiers":[
        {
            "category":"Shopping",
            "subcategory":"Florist",
            "type":"Retail Goods"
        }
    ],
    "sg:phone":"+44 121 779 5526",
    "sg:postcode":"B37 7BA",
    "sg:province":"West Midlands",
    "wof:name":"Handful of Flowers",
    "wof:placetype":"venue"
},
  "geometry": {"coordinates":[-1.749827981,52.467590332],"type":"Point"}
}