{
  "type": "Feature",
  "properties": {
    "addr:full":"White Horse Hill Chislehurst Kent BR7 6DG",
    "addr:postcode":"br7 6dg",
    "addr:street":"Hill",
    "iso:country":"GB",
    "sg:address":"White Horse Hill",
    "sg:city":"Chislehurst",
    "sg:classifiers":[
        {
            "category":"Bars & Pubs",
            "type":"Food & Drink"
        }
    ],
    "sg:postcode":"BR7 6DG",
    "sg:province":"Kent",
    "sg:tags":[
        "pubs",
        "inn"
    ],
    "wof:name":"Penny Farthing",
    "wof:placetype":"venue"
},
  "geometry": {"coordinates":[0.0584699996,51.424659729],"type":"Point"}
}