{
  "type": "Feature",
  "properties": {
    "addr:full":"41 Sea Grove Avenue Hayling Island Hampshire PO11 9EP",
    "addr:housenumber":"41",
    "addr:postcode":"po11 9ep",
    "addr:street":"Sea Grove Avenue",
    "iso:country":"GB",
    "sg:address":"41 Sea Grove Avenue",
    "sg:city":"Hayling Island",
    "sg:classifiers":[
        {
            "category":"Building & Trades",
            "subcategory":"Landscaping Services",
            "type":"Services"
        }
    ],
    "sg:phone":"+44 23 9246 3057",
    "sg:postcode":"PO11 9EP",
    "sg:province":"Hampshire",
    "sg:tags":[
        "landscape",
        "contractor"
    ],
    "wof:name":"Hayling Landscapes",
    "wof:placetype":"venue"
},
  "geometry": {"coordinates":[-0.9783459902,50.7843856812],"type":"Point"}
}