{
  "type": "Feature",
  "properties": {
    "addr:full":"Main Terminal Building, London City Airport Canning Town Greater London E16 2PX",
    "addr:postcode":"e16 2px",
    "iso:country":"GB",
    "sg:address":"Main Terminal Building, London City Airport",
    "sg:city":"Canning Town",
    "sg:classifiers":[
        {
            "category":"Airline",
            "type":"Transportation"
        }
    ],
    "sg:phone":"+44 20 7474 8888",
    "sg:postcode":"E16 2PX",
    "sg:province":"Greater London",
    "wof:name":"Cityjet",
    "wof:placetype":"venue"
},
  "geometry": {"coordinates":[0.048,51.504051],"type":"Point"}
}