{
  "type": "Feature",
  "properties": {
    "addr:full":"Karyon House, Pontyfelin Road, New Inn Pontypool Monmouthshire NP4 0DQ",
    "addr:postcode":"np4 0dq",
    "addr:street":"Pontyfelin Road",
    "iso:country":"GB",
    "sg:address":"Karyon House, Pontyfelin Road, New Inn",
    "sg:city":"Pontypool",
    "sg:classifiers":[
        {
            "category":"Retail",
            "subcategory":"Auto Repair",
            "type":"Services"
        }
    ],
    "sg:phone":"+44 1495 763435",
    "sg:postcode":"NP4 0DQ",
    "sg:province":"Monmouthshire",
    "sg:tags":[
        "modification",
        "garage"
    ],
    "wof:name":"Polo Grounds Motor Services",
    "wof:placetype":"venue"
},
  "geometry": {"coordinates":[-3.0139191151,51.68542099],"type":"Point"}
}