{
  "type": "Feature",
  "properties": {
    "addr:full":"Lilac Dene Belper Derbyshire DE56 2DB",
    "addr:postcode":"de56 2db",
    "addr:street":"Dene Belper",
    "iso:country":"GB",
    "sg:address":"Lilac Dene",
    "sg:city":"Belper",
    "sg:classifiers":[
        {
            "category":"Building & Trades",
            "subcategory":"Equipment Rental",
            "type":"Services"
        }
    ],
    "sg:phone":"+44 1773 880547",
    "sg:postcode":"DE56 2DB",
    "sg:province":"Derbyshire",
    "sg:tags":[
        "plant",
        "machinery"
    ],
    "wof:name":"S J Smalley",
    "wof:placetype":"venue"
},
  "geometry": {"coordinates":[-1.475982,53.02861],"type":"Point"}
}