{
  "type": "Feature",
  "properties": {
    "iso:country":"GB",
    "sg:address":"5 Morris St",
    "sg:city":"Hook",
    "sg:classifiers":[
        {
            "category":"Communications",
            "type":"Services"
        }
    ],
    "sg:phone":"+44 1256 767611",
    "sg:postcode":"RG27 9NT",
    "sg:province":"Berkshire",
    "sg:tags":[
        "data",
        "network"
    ],
    "wof:name":"Greenshoots Communications",
    "wof:placetype":"venue"
},
  "geometry": {"coordinates":[-0.976458,51.27795],"type":"Point"}
}