{
  "type": "Feature",
  "properties": {
    "iso:country":"GB",
    "sg:address":"Belasis Business Centre, Coxwold Way",
    "sg:city":"Billingham",
    "sg:classifiers":[
        {
            "category":"Professional",
            "subcategory":"Detective & Security Services",
            "type":"Services"
        }
    ],
    "sg:phone":"+44 1642 343422",
    "sg:postcode":"TS23 4EA",
    "sg:province":"Durham",
    "sg:tags":[
        "agency"
    ],
    "wof:name":"Douglas Associates",
    "wof:placetype":"venue"
},
  "geometry": {"coordinates":[-1.2936450243,54.6068572998],"type":"Point"}
}