{
  "type": "Feature",
  "properties": {
    "iso:country":"GB",
    "sg:address":"50 Bexley Street",
    "sg:city":"Windsor",
    "sg:classifiers":[
        {
            "category":"Bars & Pubs",
            "type":"Food & Drink"
        }
    ],
    "sg:phone":"+44 1753 865552",
    "sg:postcode":"SL4 5BX",
    "sg:province":"Berkshire",
    "sg:tags":[
        "pubs",
        "inn"
    ],
    "wof:name":"The Bexley Arms",
    "wof:placetype":"venue"
},
  "geometry": {"coordinates":[-0.619023,51.481274],"type":"Point"}
}