{
  "type": "Feature",
  "properties": {
    "iso:country":"GB",
    "sg:address":"P O Box 5 Station Rd",
    "sg:city":"Derby",
    "sg:classifiers":[
        {
            "category":"Manufacturing",
            "subcategory":"Chemicals & Compounds",
            "type":"Manufacturing & Wholesale Goods"
        }
    ],
    "sg:phone":"+44 1332 661422",
    "sg:postcode":"DE21 7BP",
    "sg:province":"Derbyshire",
    "sg:tags":[
        "pesticide"
    ],
    "wof:name":"Courtaulds Chemicals",
    "wof:placetype":"venue"
},
  "geometry": {"coordinates":[-1.38138,52.906448],"type":"Point"}
}