{
  "type": "Feature",
  "properties": {
    "addr:full":"3 Station Approach, Hoe Street, Walthamstow London Greater London E17 9QF",
    "addr:housenumber":"3",
    "addr:postcode":"e17 9qf",
    "addr:street":"Station Approach Hoe Street",
    "iso:country":"GB",
    "sg:address":"3 Station Approach, Hoe Street, Walthamstow",
    "sg:city":"London",
    "sg:classifiers":[
        {
            "category":"Retail",
            "subcategory":"Auto Rental",
            "type":"Services"
        }
    ],
    "sg:phone":"+44 20 8350 8350",
    "sg:postcode":"E17 9QF",
    "sg:province":"Greater London",
    "sg:tags":[
        "car",
        "hire",
        "truck"
    ],
    "wof:name":"Complete Auto Rental Services Ltd.",
    "wof:placetype":"venue"
},
  "geometry": {"coordinates":[-0.0190500002,51.5827407837],"type":"Point"}
}