{
  "type": "Feature",
  "properties": {
    "iso:country":"GB",
    "sg:address":"5 Richmond Road",
    "sg:city":"Ramsgate",
    "sg:classifiers":[
        {
            "category":"Personal",
            "subcategory":"Beauty Salon",
            "type":"Services"
        }
    ],
    "sg:phone":"+44 1843 592495",
    "sg:postcode":"CT11 9QP",
    "sg:province":"Kent",
    "sg:tags":[
        "lady",
        "hairdresser"
    ],
    "wof:name":"Shirley`S Hair Studio",
    "wof:placetype":"venue"
},
  "geometry": {"coordinates":[1.410675,51.333103],"type":"Point"}
}