{
  "type": "Feature",
  "properties": {
    "addr:full":"35a Church Street, Church Gresley Swadlincote Derbyshire DE11 9NP",
    "addr:housenumber":"35a",
    "addr:postcode":"de11 9np",
    "addr:street":"Church Street",
    "iso:country":"GB",
    "sg:address":"35a Church Street, Church Gresley",
    "sg:city":"Swadlincote",
    "sg:classifiers":[
        {
            "category":"Personal",
            "subcategory":"Barber",
            "type":"Services"
        }
    ],
    "sg:phone":"+44 1283 217100",
    "sg:postcode":"DE11 9NP",
    "sg:province":"Derbyshire",
    "sg:tags":[
        "men's",
        "gents",
        "hairdresser"
    ],
    "wof:name":"Terrence Leslie",
    "wof:placetype":"venue"
},
  "geometry": {"coordinates":[-1.562324,52.76144],"type":"Point"}
}