{
  "type": "Feature",
  "properties": {
    "addr:full":"Unit 1, Clackmannan Road Alloa Clackmannanshire FK10 4DA",
    "addr:housenumber":"unit 1",
    "addr:postcode":"fk10 4da",
    "addr:street":"Clackmannan Road",
    "iso:country":"GB",
    "sg:address":"Unit 1, Clackmannan Road",
    "sg:city":"Alloa",
    "sg:classifiers":[
        {
            "category":"Retail",
            "subcategory":"Auto Repair",
            "type":"Services"
        }
    ],
    "sg:phone":"+44 1259 216063",
    "sg:postcode":"FK10 4DA",
    "sg:province":"Clackmannanshire",
    "sg:tags":[
        "modification",
        "garage",
        "related"
    ],
    "wof:name":"Central Auto Services",
    "wof:placetype":"venue"
},
  "geometry": {"coordinates":[-3.7818889618,56.1162414551],"type":"Point"}
}