{
  "type": "Feature",
  "properties": {
    "iso:country":"GB",
    "sg:address":"27 Watergate Row South",
    "sg:city":"Chester",
    "sg:classifiers":[
        {
            "category":"Shopping",
            "subcategory":"Antiques",
            "type":"Retail Goods"
        }
    ],
    "sg:phone":"+44 1244 340095",
    "sg:postcode":"CH1 2LE",
    "sg:province":"Cheshire",
    "wof:name":"Moor Hall Antiques",
    "wof:placetype":"venue"
},
  "geometry": {"coordinates":[-2.8927490711,53.1899986267],"type":"Point"}
}