{
  "type": "Feature",
  "properties": {
    "addr:full":"9 Pine Close, Newton Porthcawl Bridgend CF36 5NX",
    "addr:housenumber":"9",
    "addr:postcode":"cf36 5nx",
    "addr:street":"Pine Close",
    "iso:country":"GB",
    "sg:address":"9 Pine Close, Newton",
    "sg:city":"Porthcawl",
    "sg:classifiers":[
        {
            "category":"Autos & Motor Vehicles",
            "subcategory":"Recreational Vehicle Sales",
            "type":"Retail Goods"
        }
    ],
    "sg:phone":"+44 1656 773774",
    "sg:postcode":"CF36 5NX",
    "sg:province":"Bridgend",
    "sg:tags":[
        "caravan"
    ],
    "wof:name":"Pleasure Caravans Ltd",
    "wof:placetype":"venue"
},
  "geometry": {"coordinates":[-3.690919,51.48761],"type":"Point"}
}