{
  "type": "Feature",
  "properties": {
    "iso:country":"GB",
    "sg:address":"28 Station Road, Brompton On Swale",
    "sg:city":"Richmond",
    "sg:classifiers":[
        {
            "category":"Shopping",
            "subcategory":"Clothing, Apparel, & Fashions",
            "type":"Retail Goods"
        },
        {
            "category":"Home & Garden",
            "subcategory":"Building Materials",
            "type":"Retail Goods"
        }
    ],
    "sg:phone":"+44 1748 811220",
    "sg:postcode":"DL10 7HN",
    "sg:province":"North Yorkshire",
    "sg:tags":[
        "furnishers",
        "bathroom",
        "planner",
        "clothing",
        "fabric"
    ],
    "wof:name":"D M & D A Cockerill",
    "wof:placetype":"venue"
},
  "geometry": {"coordinates":[-1.661021,54.392994],"type":"Point"}
}