{
  "type": "Feature",
  "properties": {
    "iso:country":"GB",
    "sg:address":"Church Path, High St",
    "sg:city":"Chelmsford",
    "sg:classifiers":[
        {
            "category":"Place Of Worship",
            "type":"Public Place"
        }
    ],
    "sg:phone":"+44 1245 477501",
    "sg:postcode":"CM2 7HN",
    "sg:province":"Essex",
    "wof:name":"St Marys C Of E Church",
    "wof:placetype":"venue"
},
  "geometry": {"coordinates":[0.477891,51.731918],"type":"Point"}
}