{
  "type": "Feature",
  "properties": {
    "iso:country":"GB",
    "sg:address":"Royal Street, Smallbridge",
    "sg:city":"Rochdale",
    "sg:classifiers":[
        {
            "category":"Shopping",
            "subcategory":"Discount & Variety Stores",
            "type":"Retail Goods"
        }
    ],
    "sg:phone":"+44 1706 644940",
    "sg:postcode":"OL16 2QA",
    "sg:province":"Lancashire",
    "sg:tags":[
        "cleaning",
        "supply"
    ],
    "wof:name":"James Law (Chemicals) Ltd.",
    "wof:placetype":"venue"
},
  "geometry": {"coordinates":[-2.1355009079,53.6316413879],"type":"Point"}
}