{
  "type": "Feature",
  "properties": {
    "addr:full":"Suite F Carina House, Linford Wood Business Centre Milton Keynes Buckinghamshire MK14 6PA",
    "addr:postcode":"mk14 6pa",
    "addr:street":"Linford Wood",
    "iso:country":"GB",
    "sg:address":"Suite F Carina House, Linford Wood Business Centre",
    "sg:city":"Milton Keynes",
    "sg:classifiers":[
        {
            "category":"Professional",
            "subcategory":"Computer Services",
            "type":"Services"
        }
    ],
    "sg:phone":"+44 1908 325200",
    "sg:postcode":"MK14 6PA",
    "sg:province":"Buckinghamshire",
    "sg:tags":[
        "system",
        "software"
    ],
    "wof:name":"Ge Fanuc International Ltd.",
    "wof:placetype":"venue"
},
  "geometry": {"coordinates":[-0.768181026,52.057384491],"type":"Point"}
}