{
  "type": "Feature",
  "properties": {
    "iso:country":"GB",
    "sg:address":"405 Eastcote Lane, South Harrow",
    "sg:city":"Harrow",
    "sg:classifiers":[
        {
            "category":"Shopping",
            "subcategory":"News",
            "type":"Retail Goods"
        }
    ],
    "sg:phone":"+44 20 8422 1612",
    "sg:postcode":"HA2 8SE",
    "sg:province":"Greater London",
    "sg:tags":[
        "newsagent"
    ],
    "wof:name":"J S & D S Patel",
    "wof:placetype":"venue"
},
  "geometry": {"coordinates":[-0.357739,51.56773],"type":"Point"}
}