{
  "type": "Feature",
  "properties": {
    "addr:full":"Duchess Nina House, 17 Cadzow Crescent Bo'ness Falkirk EH51 9AY",
    "addr:housenumber":"17",
    "addr:postcode":"eh51 9ay",
    "addr:street":"Cadzow Crescent",
    "iso:country":"GB",
    "sg:address":"Duchess Nina House, 17 Cadzow Crescent",
    "sg:city":"Bo'ness",
    "sg:classifiers":[
        {
            "category":"Organizations",
            "subcategory":"Non-profit Organization",
            "type":"Services"
        }
    ],
    "sg:phone":"+44 1506 823118",
    "sg:postcode":"EH51 9AY",
    "sg:province":"Falkirk",
    "sg:tags":[
        "organisation",
        "voluntary",
        "charity"
    ],
    "wof:name":"Bo'ness Family Centre",
    "wof:placetype":"venue"
},
  "geometry": {"coordinates":[-3.6060600281,56.0130081177],"type":"Point"}
}