{
  "type": "Feature",
  "properties": {
    "addr:full":"Unit 4-5 Ashley Industrial Estate, Sackville St Leeds West Yorkshire LS7 2BS",
    "addr:housenumber":"unit 4-5",
    "addr:postcode":"ls7 2bs",
    "addr:street":"Ashley Industrial Estate Sackville St",
    "iso:country":"GB",
    "sg:address":"Unit 4-5 Ashley Industrial Estate, Sackville St",
    "sg:city":"Leeds",
    "sg:classifiers":[
        {
            "category":"Shopping",
            "subcategory":"Stationery & Office Supplies",
            "type":"Retail Goods"
        }
    ],
    "sg:phone":"+44 113 288 6111",
    "sg:postcode":"LS7 2BS",
    "sg:province":"West Yorkshire",
    "sg:tags":[
        "equipment"
    ],
    "wof:name":"Work Inc",
    "wof:placetype":"venue"
},
  "geometry": {"coordinates":[-1.5393500328,53.8109817505],"type":"Point"}
}