{
  "type": "Feature",
  "properties": {
    "addr:full":"Chapel Gate House, Ullenhall Solihull Warwickshire B95 5RT",
    "addr:postcode":"b95 5rt",
    "addr:street":"Gate",
    "iso:country":"GB",
    "sg:address":"Chapel Gate House, Ullenhall",
    "sg:city":"Solihull",
    "sg:classifiers":[
        {
            "category":"Real Estate",
            "subcategory":"Developer",
            "type":"Services"
        }
    ],
    "sg:phone":"+44 1564 792382",
    "sg:postcode":"B95 5RT",
    "sg:province":"Warwickshire",
    "sg:tags":[
        "property"
    ],
    "wof:name":"Arden Vale Homes Ltd.",
    "wof:placetype":"venue"
},
  "geometry": {"coordinates":[-1.8445290327,52.3132896423],"type":"Point"}
}