{
  "type": "Feature",
  "properties": {
    "addr:full":"9 Lundin Road, Crossford Dunfermline Fife KY12 8PL",
    "addr:housenumber":"9",
    "addr:postcode":"ky12 8pl",
    "addr:street":"Lundin Road",
    "iso:country":"GB",
    "sg:address":"9 Lundin Road, Crossford",
    "sg:city":"Dunfermline",
    "sg:classifiers":[
        {
            "category":"Retail",
            "subcategory":"Driving School",
            "type":"Services"
        }
    ],
    "sg:postcode":"KY12 8PL",
    "sg:province":"Fife",
    "wof:name":"Annand School of Motoring",
    "wof:placetype":"venue"
},
  "geometry": {"coordinates":[-3.5009460449,56.0643959045],"type":"Point"}
}