{
  "type": "Feature",
  "properties": {
    "addr:full":"Dealer Enquiries, Albion Tower Leeds West Yorkshire LS1 5ES",
    "addr:postcode":"ls1 5es",
    "addr:street":"West",
    "iso:country":"GB",
    "sg:address":"Dealer Enquiries, Albion Tower",
    "sg:city":"Leeds",
    "sg:classifiers":[
        {
            "category":"Banks & Credit Unions",
            "subcategory":"Financial Services",
            "type":"Services"
        }
    ],
    "sg:phone":"+44 113 244 4881",
    "sg:postcode":"LS1 5ES",
    "sg:province":"West Yorkshire",
    "sg:tags":[
        "consultant"
    ],
    "wof:name":"Nova Retail Finance",
    "wof:placetype":"venue"
},
  "geometry": {"coordinates":[-1.5465869904,53.7944946289],"type":"Point"}
}