{
  "type": "Feature",
  "properties": {
    "iso:country":"GB",
    "sg:address":"Unit 6/7, Brookfield Road, Demmings Industrial Estate",
    "sg:city":"Cheadle",
    "sg:classifiers":[
        {
            "category":"Personal",
            "type":"Services"
        }
    ],
    "sg:phone":"+44 161 428 8383",
    "sg:postcode":"SK8 2PN",
    "sg:province":"Cheshire",
    "sg:tags":[
        "gift"
    ],
    "wof:name":"Elms & Elms Ltd.",
    "wof:placetype":"venue"
},
  "geometry": {"coordinates":[-2.212272,53.395248],"type":"Point"}
}