{
  "type": "Feature",
  "properties": {
    "iso:country":"GB",
    "sg:address":"6-24 Southgate Road",
    "sg:city":"London",
    "sg:classifiers":[
        {
            "category":"Professional",
            "subcategory":"Printing & Photocopies",
            "type":"Services"
        }
    ],
    "sg:postcode":"N1 3JJ",
    "sg:province":"Greater London",
    "sg:tags":[
        "printer"
    ],
    "wof:name":"Nice & Easy Printing Ltd.",
    "wof:placetype":"venue"
},
  "geometry": {"coordinates":[-0.086198,51.537632],"type":"Point"}
}