{
  "type": "Feature",
  "properties": {
    "iso:country":"GB",
    "sg:address":"Eldon Ct, Eldon Sq",
    "sg:city":"Newcastle-upon-tyne",
    "sg:classifiers":[
        {
            "category":"Farming",
            "subcategory":"Aquatic Farm",
            "type":"Manufacturing & Wholesale Goods"
        }
    ],
    "sg:phone":"+44 191 230 1830",
    "sg:postcode":"NE1 7HA",
    "sg:province":"Tyne and Wear",
    "sg:tags":[
        "installers",
        "draughtproofing"
    ],
    "wof:name":"Eaga Ltd",
    "wof:placetype":"venue"
},
  "geometry": {"coordinates":[-1.61673,54.974499],"type":"Point"}
}