{
  "type": "Feature",
  "properties": {
    "addr:full":"58 Merthyr Road Pontypridd Caerphilly CF37 4DD",
    "addr:housenumber":"58",
    "addr:postcode":"cf37 4dd",
    "addr:street":"Merthyr Road",
    "iso:country":"GB",
    "sg:address":"58 Merthyr Road",
    "sg:city":"Pontypridd",
    "sg:classifiers":[
        {
            "category":"Sports & Exercise",
            "subcategory":"Ice Rink",
            "type":"Entertainment"
        },
        {
            "category":"Home & Garden",
            "subcategory":"Kitchen Supply",
            "type":"Retail Goods"
        }
    ],
    "sg:phone":"+44 1443 402947",
    "sg:postcode":"CF37 4DD",
    "sg:province":"Caerphilly",
    "sg:tags":[
        "shop",
        "glass",
        "glassware",
        "china",
        "crystalware"
    ],
    "wof:name":"E Roberts & Sons",
    "wof:placetype":"venue"
},
  "geometry": {"coordinates":[-3.3323938847,51.6057510376],"type":"Point"}
}