{
  "type": "Feature",
  "properties": {
    "iso:country":"GB",
    "sg:address":"4 Thompson Street",
    "sg:city":"Barry",
    "sg:classifiers":[
        {
            "category":"Shopping",
            "subcategory":"Shoes",
            "type":"Retail Goods"
        }
    ],
    "sg:phone":"+44 1446 739823",
    "sg:postcode":"CF63 4JL",
    "sg:province":"The Vale of Glamorgan",
    "wof:name":"N & M Frangoulis",
    "wof:placetype":"venue"
},
  "geometry": {"coordinates":[-3.2700750828,51.4048118591],"type":"Point"}
}