{
  "type": "Feature",
  "properties": {
    "iso:country":"GB",
    "sg:address":"Hill Top Farm",
    "sg:city":"Skipton",
    "sg:classifiers":[
        {
            "category":"Building & Trades",
            "subcategory":"Construction",
            "type":"Services"
        }
    ],
    "sg:postcode":"BD23 4EA",
    "sg:province":"Lancashire",
    "sg:tags":[
        "builder"
    ],
    "wof:name":"Dyson Structural Services",
    "wof:placetype":"venue"
},
  "geometry": {"coordinates":[-2.238194,54.050323],"type":"Point"}
}