{
  "type": "Feature",
  "properties": {
    "iso:country":"GB",
    "sg:address":"Braxtonhill",
    "sg:city":"Cornhill-on-tweed",
    "sg:classifiers":[
        {
            "category":"Farming",
            "subcategory":"Farm",
            "type":"Manufacturing & Wholesale Goods"
        }
    ],
    "sg:phone":"+44 1890 820283",
    "sg:postcode":"TD12 4QS",
    "sg:province":"Northumberland",
    "sg:tags":[
        "mixed",
        "crop"
    ],
    "wof:name":"R & M Neill Ltd.",
    "wof:placetype":"venue"
},
  "geometry": {"coordinates":[-2.220848,55.648235],"type":"Point"}
}