{
  "type": "Feature",
  "properties": {
    "addr:full":"Moat Farm, Peasenhall Saxmundham Suffolk IP17 2JR",
    "addr:housenumber":"saxmundham",
    "addr:postcode":"ip17 2jr",
    "addr:street":"Moat",
    "iso:country":"GB",
    "sg:address":"Moat Farm, Peasenhall",
    "sg:city":"Saxmundham",
    "sg:classifiers":[
        {
            "category":"Farming",
            "subcategory":"Crops",
            "type":"Manufacturing & Wholesale Goods"
        },
        {
            "category":"Farming",
            "subcategory":"Livestock Farm",
            "type":"Manufacturing & Wholesale Goods"
        }
    ],
    "sg:phone":"+44 1728 660456",
    "sg:postcode":"IP17 2JR",
    "sg:province":"Suffolk",
    "sg:tags":[
        "arable",
        "others"
    ],
    "wof:name":"John S Clark",
    "wof:placetype":"venue"
},
  "geometry": {"coordinates":[1.4506440163,52.2711982727],"type":"Point"}
}