{
  "type": "Feature",
  "properties": {
    "iso:country":"GB",
    "sg:address":"Ruthven Road",
    "sg:city":"Bristol",
    "sg:classifiers":[
        {
            "category":"Farming",
            "subcategory":"Nursery",
            "type":"Manufacturing & Wholesale Goods"
        },
        {
            "category":"Government",
            "subcategory":"Office",
            "type":"Public Place"
        }
    ],
    "sg:phone":"+44 117 966 2969",
    "sg:postcode":"BS4 1ST",
    "sg:province":"City of Bristol",
    "sg:tags":[
        "local",
        "creche"
    ],
    "wof:name":"Knowle Day Nursery",
    "wof:placetype":"venue"
},
  "geometry": {"coordinates":[-2.5899739265,51.4235801697],"type":"Point"}
}