{
  "type": "Feature",
  "properties": {
    "addr:full":"27 Adam And Eve Mews London Greater London W8 6UG",
    "addr:housenumber":"27",
    "addr:postcode":"w8 6ug",
    "addr:street":"Adam And Eve Mews",
    "iso:country":"GB",
    "sg:address":"27 Adam And Eve Mews",
    "sg:city":"London",
    "sg:classifiers":[
        {
            "category":"Insurance",
            "subcategory":"Insurance Agent",
            "type":"Services"
        }
    ],
    "sg:phone":"+44 20 7938 3033",
    "sg:postcode":"W8 6UG",
    "sg:province":"Greater London",
    "wof:name":"Bloodlines Ltd.",
    "wof:placetype":"venue"
},
  "geometry": {"coordinates":[-0.1941539943,51.4991226196],"type":"Point"}
}