{
  "type": "Feature",
  "properties": {
    "iso:country":"GB",
    "sg:address":"Unit 6 Russell Rd",
    "sg:city":"Birkenhead",
    "sg:classifiers":[
        {
            "category":"Retail",
            "subcategory":"Auto Rental",
            "type":"Services"
        }
    ],
    "sg:phone":"+44 151 608 1568",
    "sg:postcode":"L42 1RP",
    "sg:province":"Merseyside",
    "sg:tags":[
        "car"
    ],
    "wof:name":"Oxton Autos",
    "wof:placetype":"venue"
},
  "geometry": {"coordinates":[-3.008084,53.375389],"type":"Point"}
}