{
  "type": "Feature",
  "properties": {
    "addr:full":"Womensline, P O Box 3 Portsmouth Hampshire PO1 1AA",
    "addr:housenumber":"3",
    "addr:postcode":"hampshire po1 1aa",
    "addr:street":"P O Box",
    "iso:country":"GB",
    "sg:address":"Womensline, P O Box 3",
    "sg:city":"Portsmouth",
    "sg:classifiers":[
        {
            "category":"Professional",
            "subcategory":"Lawyer & Legal Services",
            "type":"Services"
        }
    ],
    "sg:phone":"+44 23 9266 9511",
    "sg:postcode":"PO1 1AA",
    "sg:province":"Hampshire",
    "sg:tags":[
        "advice",
        "counselling"
    ],
    "wof:name":"Portsmouth Rape Area Crisis Services",
    "wof:placetype":"venue"
},
  "geometry": {"coordinates":[-1.0872839689,50.8040084839],"type":"Point"}
}