{
  "type": "Feature",
  "properties": {
    "iso:country":"GB",
    "sg:address":"Greenhedges, London Road",
    "sg:city":"Westerham",
    "sg:classifiers":[
        {
            "category":"Building & Trades",
            "subcategory":"Equipment Rental",
            "type":"Services"
        }
    ],
    "sg:phone":"+44 1959 562300",
    "sg:postcode":"TN16 1BB",
    "sg:province":"Kent",
    "sg:tags":[
        "hire",
        "catering"
    ],
    "wof:name":"Classic Touch",
    "wof:placetype":"venue"
},
  "geometry": {"coordinates":[0.071265,51.267075],"type":"Point"}
}