{
  "type": "Feature",
  "properties": {
    "addr:full":"226 Barr Street Birmingham West Midlands B19 3AG",
    "addr:housenumber":"226",
    "addr:postcode":"b19 3ag",
    "addr:street":"Barr Street",
    "iso:country":"GB",
    "sg:address":"226 Barr Street",
    "sg:city":"Birmingham",
    "sg:classifiers":[
        {
            "category":"Manufacturing",
            "subcategory":"Tools & Machinery",
            "type":"Manufacturing & Wholesale Goods"
        }
    ],
    "sg:postcode":"B19 3AG",
    "sg:province":"West Midlands",
    "sg:tags":[
        "design",
        "maker",
        "manufacturer"
    ],
    "wof:name":"G E Winfield",
    "wof:placetype":"venue"
},
  "geometry": {"coordinates":[-1.912233,52.493858],"type":"Point"}
}