{
  "type": "Feature",
  "properties": {
    "addr:full":"19 Bridge Street, Loddon Norwich Norfolk NR14 6NA",
    "addr:housenumber":"19",
    "addr:postcode":"nr14 6na",
    "addr:street":"Bridge Street;Norwich",
    "iso:country":"GB",
    "sg:address":"19 Bridge Street, Loddon",
    "sg:city":"Norwich",
    "sg:classifiers":[
        {
            "category":"Retail",
            "subcategory":"Funeral Services",
            "type":"Services"
        }
    ],
    "sg:phone":"+44 1508 528274",
    "sg:postcode":"NR14 6NA",
    "sg:province":"Norfolk",
    "wof:name":"Youngs Funeral Directors",
    "wof:placetype":"venue"
},
  "geometry": {"coordinates":[1.4804129601,52.5367355347],"type":"Point"}
}