{
  "type": "Feature",
  "properties": {
    "iso:country":"GB",
    "sg:address":"Windsor Road, Water Oakley",
    "sg:city":"Windsor",
    "sg:classifiers":[
        {
            "category":"Travel",
            "subcategory":"Hotels & Motels",
            "type":"Entertainment"
        }
    ],
    "sg:phone":"+44 1753 609988",
    "sg:postcode":"SL4 5UR",
    "sg:province":"Berkshire",
    "wof:name":"Oakley Court Hotel",
    "wof:placetype":"venue"
},
  "geometry": {"coordinates":[-0.655724,51.483994],"type":"Point"}
}