{
  "type": "Feature",
  "properties": {
    "addr:full":"350 Edgware Rd Bayswater Greater London W2 1EA",
    "addr:housenumber":"350",
    "addr:postcode":"w2 1ea",
    "addr:street":"Edgware Rd",
    "iso:country":"GB",
    "sg:address":"350 Edgware Rd",
    "sg:city":"Bayswater",
    "sg:classifiers":[
        {
            "category":"Shopping",
            "subcategory":"Computers & Home Electronics",
            "type":"Retail Goods"
        }
    ],
    "sg:phone":"+44 20 7224 8333",
    "sg:postcode":"W2 1EA",
    "sg:province":"Greater London",
    "sg:tags":[
        "hi-fi",
        "centre"
    ],
    "wof:name":"Linn West Two",
    "wof:placetype":"venue"
},
  "geometry": {"coordinates":[-0.1726990044,51.5218582153],"type":"Point"}
}