{
  "type": "Feature",
  "properties": {
    "addr:full":"3-5 Beastfair Pontefract North Yorkshire WF8 1AL",
    "addr:housenumber":"3-5",
    "addr:postcode":"wf8 1al",
    "addr:street":"Beastfair Pontefract",
    "iso:country":"GB",
    "sg:address":"3-5 Beastfair",
    "sg:city":"Pontefract",
    "sg:classifiers":[
        {
            "category":"Shopping",
            "subcategory":"Pharmacy",
            "type":"Retail Goods"
        }
    ],
    "sg:phone":"+44 1977 703719",
    "sg:postcode":"WF8 1AL",
    "sg:province":"North Yorkshire",
    "sg:tags":[
        "pharmacist",
        "chemist"
    ],
    "wof:name":"Boots the Chemists",
    "wof:placetype":"venue"
},
  "geometry": {"coordinates":[-1.312399,53.69138],"type":"Point"}
}