{
  "type": "Feature",
  "properties": {
    "addr:full":"68 Pipeland Road St Andrews Fife KY16 8JZ",
    "addr:housenumber":"68",
    "addr:postcode":"ky16 8jz",
    "addr:street":"Pipeland Road",
    "iso:country":"GB",
    "sg:address":"68 Pipeland Road",
    "sg:city":"St Andrews",
    "sg:classifiers":[
        {
            "category":"Health Services",
            "subcategory":"Doctor",
            "type":"Services"
        }
    ],
    "sg:phone":"+44 1334 476840",
    "sg:postcode":"KY16 8JZ",
    "sg:province":"Fife",
    "sg:tags":[
        "practitioners"
    ],
    "wof:name":"St Andrews Health Centre",
    "wof:placetype":"venue"
},
  "geometry": {"coordinates":[-2.800127,56.33194],"type":"Point"}
}