{
  "type": "Feature",
  "properties": {
    "iso:country":"GB",
    "sg:address":"45 Bersham Lane, Badgers Dene",
    "sg:city":"Grays",
    "sg:classifiers":[
        {
            "category":"Taxi",
            "type":"Transportation"
        }
    ],
    "sg:phone":"+44 1375 387653",
    "sg:postcode":"RM17 5EN",
    "sg:province":"Essex",
    "sg:tags":[
        "mini",
        "cab"
    ],
    "wof:name":"Roy's Taxis",
    "wof:placetype":"venue"
},
  "geometry": {"coordinates":[0.316597,51.483494],"type":"Point"}
}