{
  "type": "Feature",
  "properties": {
    "addr:full":"8-10 Vine Street Glasgow Glasgow City G11 6BD",
    "addr:housenumber":"8-10",
    "addr:postcode":"g11 6bd",
    "addr:street":"Vine Street",
    "iso:country":"GB",
    "sg:address":"8-10 Vine Street",
    "sg:city":"Glasgow",
    "sg:classifiers":[
        {
            "category":"Home & Garden",
            "subcategory":"Household Appliances",
            "type":"Retail Goods"
        }
    ],
    "sg:phone":"+44 141 339 4206",
    "sg:postcode":"G11 6BD",
    "sg:province":"Glasgow City",
    "sg:tags":[
        "repairs",
        "electrical",
        "domestic",
        "servicing"
    ],
    "wof:name":"C D A Services",
    "wof:placetype":"venue"
},
  "geometry": {"coordinates":[-4.308264,55.870621],"type":"Point"}
}