{
  "type": "Feature",
  "properties": {
    "addr:full":"Chailey Heritage School, Haywards Heath Road, North Chailey Lewes East Sussex BN8 4EF",
    "addr:housenumber":"chailey",
    "addr:postcode":"bn8 4ef",
    "addr:street":"Heath Road North",
    "iso:country":"GB",
    "sg:address":"Chailey Heritage School, Haywards Heath Road, North Chailey",
    "sg:city":"Lewes",
    "sg:classifiers":[
        {
            "category":"Shopping",
            "subcategory":"Clothing, Apparel, & Fashions",
            "type":"Retail Goods"
        }
    ],
    "sg:phone":"+44 1825 724376",
    "sg:postcode":"BN8 4EF",
    "sg:province":"East Sussex",
    "sg:tags":[
        "t-shirt"
    ],
    "wof:name":"Chailey Heritage Enterprise Centre",
    "wof:placetype":"venue"
},
  "geometry": {"coordinates":[-0.018703,50.972286],"type":"Point"}
}