{
  "type": "Feature",
  "properties": {
    "addr:full":"96 East Main St Bathgate North Lanarkshire EH47 0PT",
    "addr:housenumber":"96",
    "addr:postcode":"eh47 0pt",
    "addr:street":"East Main St Bathgate",
    "iso:country":"GB",
    "sg:address":"96 East Main St",
    "sg:city":"Bathgate",
    "sg:classifiers":[
        {
            "category":"Health Services",
            "subcategory":"Nursing And Care Facility",
            "type":"Services"
        }
    ],
    "sg:phone":"+44 1501 740920",
    "sg:postcode":"EH47 0PT",
    "sg:province":"North Lanarkshire",
    "sg:tags":[
        "home"
    ],
    "wof:name":"Horizon Housing Association",
    "wof:placetype":"venue"
},
  "geometry": {"coordinates":[-3.689689,55.866199],"type":"Point"}
}