{
  "type": "Feature",
  "properties": {
    "addr:full":"Pen-y-bryn, School Street Ferndale Rhondda, Cynon, Taff CF43 4DN",
    "addr:postcode":"cf43 4dn",
    "addr:street":"School Street",
    "iso:country":"GB",
    "sg:address":"Pen-y-bryn, School Street",
    "sg:city":"Ferndale",
    "sg:classifiers":[
        {
            "category":"Bus Charters",
            "type":"Transportation"
        }
    ],
    "sg:postcode":"CF43 4DN",
    "sg:province":"Rhondda, Cynon, Taff",
    "sg:tags":[
        "hire",
        "coach"
    ],
    "wof:name":"Roberts Coaches",
    "wof:placetype":"venue"
},
  "geometry": {"coordinates":[-3.4478089809,51.661113739],"type":"Point"}
}