{
  "type": "Feature",
  "properties": {
    "iso:country":"GB",
    "sg:address":"116 Westbourne Rd",
    "sg:city":"Huddersfield",
    "sg:classifiers":[
        {
            "category":"Health Services",
            "subcategory":"Dentist",
            "type":"Services"
        }
    ],
    "sg:phone":"+44 1484 516633",
    "sg:postcode":"HD1 4LF",
    "sg:province":"West Yorkshire",
    "wof:name":"Millington-Smith M J",
    "wof:placetype":"venue"
},
  "geometry": {"coordinates":[-1.807211,53.651527],"type":"Point"}
}