{
  "type": "Feature",
  "properties": {
    "iso:country":"GB",
    "sg:address":"Hill View Road, Michelmersh",
    "sg:city":"Romsey",
    "sg:classifiers":[
        {
            "category":"Building & Trades",
            "subcategory":"Construction",
            "type":"Services"
        }
    ],
    "sg:phone":"+44 1794 368275",
    "sg:postcode":"SO51 0NN",
    "sg:province":"Hampshire",
    "sg:tags":[
        "welder"
    ],
    "wof:name":"L K Ninnim",
    "wof:placetype":"venue"
},
  "geometry": {"coordinates":[-1.4671740532,51.0221862793],"type":"Point"}
}