{
  "type": "Feature",
  "properties": {
    "addr:full":"Brookley Road Brockenhurst Hampshire SO42 7RR",
    "addr:postcode":"so42 7rr",
    "addr:street":"Brookley Road",
    "iso:country":"GB",
    "sg:address":"Brookley Road",
    "sg:city":"Brockenhurst",
    "sg:classifiers":[
        {
            "category":"Bars & Pubs",
            "type":"Food & Drink"
        }
    ],
    "sg:phone":"+44 1590 623333",
    "sg:postcode":"SO42 7RR",
    "sg:province":"Hampshire",
    "sg:tags":[
        "pubs",
        "inn"
    ],
    "wof:name":"Morant Arms",
    "wof:placetype":"venue"
},
  "geometry": {"coordinates":[-1.579106,50.819351],"type":"Point"}
}