{
  "type": "Feature",
  "properties": {
    "addr:full":"St Peters, Ellachie Mews Gosport Hampshire PO12 2DR",
    "addr:postcode":"po12 2dr",
    "addr:street":"Mews",
    "iso:country":"GB",
    "sg:address":"St Peters, Ellachie Mews",
    "sg:city":"Gosport",
    "sg:classifiers":[
        {
            "category":"Professional",
            "subcategory":"Research",
            "type":"Services"
        }
    ],
    "sg:phone":"+44 23 9252 2017",
    "sg:postcode":"PO12 2DR",
    "sg:province":"Hampshire",
    "sg:tags":[
        "market"
    ],
    "wof:name":"Crombie International Research",
    "wof:placetype":"venue"
},
  "geometry": {"coordinates":[-1.1595629454,50.7930984497],"type":"Point"}
}