{
  "type": "Feature",
  "properties": {
    "addr:full":"29 Warwick Road Solihull West Midlands B92 7HS",
    "addr:housenumber":"29",
    "addr:postcode":"b92 7hs",
    "addr:street":"Warwick Road",
    "iso:country":"GB",
    "sg:address":"29 Warwick Road",
    "sg:city":"Solihull",
    "sg:classifiers":[
        {
            "category":"Home & Garden",
            "subcategory":"Furniture",
            "type":"Retail Goods"
        }
    ],
    "sg:phone":"+44 121 706 0481",
    "sg:postcode":"B92 7HS",
    "sg:province":"West Midlands",
    "wof:name":"Millhouse Pine",
    "wof:placetype":"venue"
},
  "geometry": {"coordinates":[-1.810475,52.44154],"type":"Point"}
}