{
  "type": "Feature",
  "properties": {
    "addr:full":"Ship Canal House, 98 King St Manchester Greater Manchester M2 4WU",
    "addr:housenumber":"98",
    "addr:postcode":"m2 4wu",
    "addr:street":"King St",
    "iso:country":"GB",
    "sg:address":"Ship Canal House, 98 King St",
    "sg:city":"Manchester",
    "sg:classifiers":[
        {
            "category":"Professional",
            "subcategory":"Employment Agencies",
            "type":"Services"
        }
    ],
    "sg:phone":"+44 161 830 4480",
    "sg:postcode":"M2 4WU",
    "sg:province":"Greater Manchester",
    "sg:tags":[
        "consultant"
    ],
    "wof:name":"Reynell Legal Recruitment",
    "wof:placetype":"venue"
},
  "geometry": {"coordinates":[-2.242709,53.480801],"type":"Point"}
}