{
  "type": "Feature",
  "properties": {
    "addr:full":"254 Plungington Road Preston Lancashire PR2 3PQ",
    "addr:housenumber":"254",
    "addr:postcode":"pr2 3pq",
    "addr:street":"Plungington Road",
    "iso:country":"GB",
    "sg:address":"254 Plungington Road",
    "sg:city":"Preston",
    "sg:classifiers":[
        {
            "category":"Shopping",
            "subcategory":"Hobbies, Toys, & Games",
            "type":"Retail Goods"
        }
    ],
    "sg:phone":"+44 1772 718048",
    "sg:postcode":"PR2 3PQ",
    "sg:province":"Lancashire",
    "sg:tags":[
        "gunsmith"
    ],
    "wof:name":"S Entwistle (Preston) Ltd.",
    "wof:placetype":"venue"
},
  "geometry": {"coordinates":[-2.713876,53.774437],"type":"Point"}
}