{
  "type": "Feature",
  "properties": {
    "addr:full":"Knowesouth Jedburgh Scottish Borders TD8 6ST",
    "addr:postcode":"td8 6st",
    "iso:country":"GB",
    "sg:address":"Knowesouth",
    "sg:city":"Jedburgh",
    "sg:classifiers":[
        {
            "category":"Health Services",
            "subcategory":"Nursing And Care Facility",
            "type":"Services"
        }
    ],
    "sg:phone":"+44 1835 863161",
    "sg:postcode":"TD8 6ST",
    "sg:province":"Scottish Borders",
    "sg:tags":[
        "home"
    ],
    "wof:name":"Knowesouth Nursing Home",
    "wof:placetype":"venue"
},
  "geometry": {"coordinates":[-2.554624,55.477718],"type":"Point"}
}