{
  "type": "Feature",
  "properties": {
    "addr:full":"The Maltings Surgery, 10 Victoria St St Albans Hertfordshire AL1 3JB",
    "addr:housenumber":"10",
    "addr:postcode":"al1 3jb",
    "addr:street":"The;Victoria St",
    "iso:country":"GB",
    "sg:address":"The Maltings Surgery, 10 Victoria St",
    "sg:city":"St Albans",
    "sg:classifiers":[
        {
            "category":"Health Services",
            "subcategory":"Doctor",
            "type":"Services"
        }
    ],
    "sg:phone":"+44 1727 853296",
    "sg:postcode":"AL1 3JB",
    "sg:province":"Hertfordshire",
    "sg:tags":[
        "practitioners"
    ],
    "wof:name":"Franks, D",
    "wof:placetype":"venue"
},
  "geometry": {"coordinates":[-0.3377520144,51.7531890869],"type":"Point"}
}