{
  "type": "Feature",
  "properties": {
    "iso:country":"GB",
    "sg:address":"64 Kyleakin Road, Thornliebank",
    "sg:city":"Glasgow",
    "sg:classifiers":[
        {
            "category":"Government",
            "subcategory":"Post Office",
            "type":"Public Place"
        }
    ],
    "sg:phone":"+44 141 638 3223",
    "sg:postcode":"G46 8DF",
    "sg:province":"East Renfrewshire",
    "wof:name":"Arden Sub P O",
    "wof:placetype":"venue"
},
  "geometry": {"coordinates":[-4.3315420151,55.8062934875],"type":"Point"}
}