{
  "type": "Feature",
  "properties": {
    "iso:country":"GB",
    "sg:address":"304 Whitehorse Rd",
    "sg:city":"Croydon",
    "sg:classifiers":[
        {
            "category":"Shopping",
            "type":"Retail Goods"
        }
    ],
    "sg:postcode":"CR0 2LE",
    "sg:province":"Surrey",
    "sg:tags":[
        "part",
        "accessory"
    ],
    "wof:name":"Fisher,F,",
    "wof:placetype":"venue"
},
  "geometry": {"coordinates":[-0.09384,51.392803],"type":"Point"}
}