{
  "type": "Feature",
  "properties": {
    "addr:full":"12 Limes Avenue, Euxton Chorley Lancashire PR7 6BJ",
    "addr:housenumber":"12",
    "addr:postcode":"pr7 6bj",
    "addr:street":"Limes Avenue",
    "iso:country":"GB",
    "sg:address":"12 Limes Avenue, Euxton",
    "sg:city":"Chorley",
    "sg:classifiers":[
        {
            "category":"Professional",
            "type":"Services"
        }
    ],
    "sg:postcode":"PR7 6BJ",
    "sg:province":"Lancashire",
    "sg:tags":[
        "entertainer"
    ],
    "wof:name":"Preston Ladies Barbershop Singers",
    "wof:placetype":"venue"
},
  "geometry": {"coordinates":[-2.6805980206,53.6734809875],"type":"Point"}
}