{
  "type": "Feature",
  "properties": {
    "iso:country":"GB",
    "sg:address":"227 Whittington Road",
    "sg:city":"London",
    "sg:classifiers":[
        {
            "category":"Insurance",
            "subcategory":"Insurance Agent",
            "type":"Services"
        }
    ],
    "sg:phone":"+44 20 8888 3312",
    "sg:postcode":"N22 8YW",
    "sg:province":"Greater London",
    "sg:tags":[
        "broker"
    ],
    "wof:name":"Winston Insurance Facilities",
    "wof:placetype":"venue"
},
  "geometry": {"coordinates":[-0.115505,51.609745],"type":"Point"}
}