{
  "type": "Feature",
  "properties": {
    "iso:country":"GB",
    "sg:address":"276, High Street, Erdington",
    "sg:city":"Birmingham",
    "sg:classifiers":[
        {
            "category":"Fast Food",
            "type":"Food & Drink"
        }
    ],
    "sg:phone":"+44 121 373 1091",
    "sg:postcode":"B23 6SN",
    "sg:province":"West Midlands",
    "sg:tags":[
        "away",
        "take"
    ],
    "wof:name":"Sixways Fish Bar",
    "wof:placetype":"venue"
},
  "geometry": {"coordinates":[-1.8437240124,52.521774292],"type":"Point"}
}