{
  "type": "Feature",
  "properties": {
    "iso:country":"GB",
    "sg:address":"Spring Hill School, Palace Road",
    "sg:city":"Ripon",
    "sg:classifiers":[
        {
            "category":"Organizations",
            "subcategory":"Non-profit Organization",
            "type":"Services"
        }
    ],
    "sg:phone":"+44 1765 603320",
    "sg:postcode":"HG4 3HN",
    "sg:province":"North Yorkshire",
    "sg:tags":[
        "organisation",
        "voluntary",
        "charity"
    ],
    "wof:name":"Barnardo's",
    "wof:placetype":"venue"
},
  "geometry": {"coordinates":[-1.5235790014,54.1367950439],"type":"Point"}
}