{
  "type": "Feature",
  "properties": {
    "iso:country":"GB",
    "sg:address":"1 North Street",
    "sg:city":"Bridlington",
    "sg:classifiers":[
        {
            "category":"Banks & Credit Unions",
            "subcategory":"Financial Services",
            "type":"Services"
        }
    ],
    "sg:phone":"+44 1262 606618",
    "sg:postcode":"YO15 2DZ",
    "sg:province":"East Riding of Yorkshire",
    "sg:tags":[
        "adviser",
        "independent"
    ],
    "sg:website":"http://www.mhi.co.uk",
    "wof:name":"M H I Ltd",
    "wof:placetype":"venue"
},
  "geometry": {"coordinates":[-0.192097,54.083347],"type":"Point"}
}