{
  "type": "Feature",
  "properties": {
    "addr:full":"Bypass Rd Chester Cheshire CH3 8EF",
    "addr:postcode":"ch3 8ef",
    "addr:street":"Bypass Rd",
    "iso:country":"GB",
    "sg:address":"Bypass Rd",
    "sg:city":"Chester",
    "sg:classifiers":[
        {
            "category":"Bars & Pubs",
            "type":"Food & Drink"
        }
    ],
    "sg:phone":"+44 1829 740247",
    "sg:postcode":"CH3 8EF",
    "sg:province":"Cheshire",
    "sg:tags":[
        "pubs",
        "inn"
    ],
    "wof:name":"Village Tavern The",
    "wof:placetype":"venue"
},
  "geometry": {"coordinates":[-2.7691240311,53.1970710754],"type":"Point"}
}