{
  "type": "Feature",
  "properties": {
    "iso:country":"GB",
    "sg:address":"4 Garden St",
    "sg:city":"Ayr",
    "sg:classifiers":[
        {
            "category":"Professional",
            "subcategory":"Business Services",
            "type":"Services"
        }
    ],
    "sg:postcode":"KA8 0BB",
    "sg:province":"South Ayrshire",
    "sg:tags":[
        "import",
        "export",
        "agent"
    ],
    "wof:name":"McGregor,Lynn,",
    "wof:placetype":"venue"
},
  "geometry": {"coordinates":[-4.629341,55.466022],"type":"Point"}
}