{
  "type": "Feature",
  "properties": {
    "iso:country":"GB",
    "sg:address":"Lions Road",
    "sg:city":"New Romney",
    "sg:classifiers":[
        {
            "category":"Travel",
            "subcategory":"Hotels & Motels",
            "type":"Entertainment"
        },
        {
            "category":"Building & Trades",
            "subcategory":"Construction",
            "type":"Services"
        }
    ],
    "sg:phone":"+44 1797 363830",
    "sg:postcode":"TN28 8HA",
    "sg:province":"Kent",
    "sg:tags":[
        "house",
        "decorator",
        "guest",
        "painter"
    ],
    "wof:name":"Mulberry House",
    "wof:placetype":"venue"
},
  "geometry": {"coordinates":[0.938225,50.984581],"type":"Point"}
}