{
  "type": "Feature",
  "properties": {
    "iso:country":"GB",
    "sg:address":"21-23 St Benedicts Street",
    "sg:city":"Norwich",
    "sg:classifiers":[
        {
            "category":"Shopping",
            "subcategory":"Clothing, Apparel, & Fashions",
            "type":"Retail Goods"
        }
    ],
    "sg:postcode":"NR2 4PF",
    "sg:province":"Norfolk",
    "sg:tags":[
        "shop",
        "dress",
        "fancy"
    ],
    "wof:name":"Pandoras Fancy Dress",
    "wof:placetype":"venue"
},
  "geometry": {"coordinates":[1.28995,52.631031],"type":"Point"}
}