{
  "type": "Feature",
  "properties": {
    "addr:full":"712 Southchurch Road Southend-on-sea Essex SS1 2PS",
    "addr:housenumber":"712",
    "addr:postcode":"ss1 2ps",
    "addr:street":"Southchurch Road",
    "iso:country":"GB",
    "sg:address":"712 Southchurch Road",
    "sg:city":"Southend-on-sea",
    "sg:classifiers":[
        {
            "category":"Cafe",
            "type":"Food & Drink"
        }
    ],
    "sg:phone":"+44 1702 467714",
    "sg:postcode":"SS1 2PS",
    "sg:province":"Essex",
    "sg:tags":[
        "tea",
        "room"
    ],
    "wof:name":"Take-A-Break Cafe",
    "wof:placetype":"venue"
},
  "geometry": {"coordinates":[0.736621,51.541164],"type":"Point"}
}