{
  "type": "Feature",
  "properties": {
    "addr:full":"Swaffham Car And Service Centre, The Filling Station, Castle Acre Road Swaffham Norfolk PE37 7HS",
    "addr:postcode":"pe37 7hs",
    "addr:street":"The;Castle Acre Road",
    "iso:country":"GB",
    "sg:address":"Swaffham Car And Service Centre, The Filling Station, Castle Acre Road",
    "sg:city":"Swaffham",
    "sg:classifiers":[
        {
            "category":"Retail",
            "subcategory":"Auto Repair",
            "type":"Services"
        }
    ],
    "sg:phone":"+44 1760 724282",
    "sg:postcode":"PE37 7HS",
    "sg:province":"Norfolk",
    "sg:tags":[
        "modification",
        "garage",
        "related"
    ],
    "sg:website":"http://www.tgautos.co.uk",
    "wof:name":"Trevor Greef Motor Services",
    "wof:placetype":"venue"
},
  "geometry": {"coordinates":[0.689797,52.643845],"type":"Point"}
}