{
  "type": "Feature",
  "properties": {
    "addr:full":"358 Purley Way Croydon Surrey CR0 4NY",
    "addr:housenumber":"358",
    "addr:postcode":"cr0 4ny",
    "addr:street":"Purley Way",
    "iso:country":"GB",
    "sg:address":"358 Purley Way",
    "sg:city":"Croydon",
    "sg:classifiers":[
        {
            "category":"Shopping",
            "subcategory":"News",
            "type":"Retail Goods"
        }
    ],
    "sg:phone":"+44 20 8688 7000",
    "sg:postcode":"CR0 4NY",
    "sg:province":"Surrey",
    "sg:tags":[
        "newsagent"
    ],
    "wof:name":"Pat Bros Newsagents",
    "wof:placetype":"venue"
},
  "geometry": {"coordinates":[-0.1172349975,51.3709487915],"type":"Point"}
}