{
  "type": "Feature",
  "properties": {
    "iso:country":"GB",
    "sg:address":"Business & Innovation Centre, Sunderland Enterprise Park",
    "sg:city":"Sunderland",
    "sg:classifiers":[
        {
            "category":"Professional",
            "subcategory":"Management & Consulting",
            "type":"Services"
        }
    ],
    "sg:phone":"+44 191 516 6100",
    "sg:postcode":"SR5 2TA",
    "sg:province":"Tyne and Wear",
    "sg:tags":[
        "consultant",
        "business"
    ],
    "wof:name":"Business Link Sunderland",
    "wof:placetype":"venue"
},
  "geometry": {"coordinates":[-1.41556,54.918678],"type":"Point"}
}