{
  "type": "Feature",
  "properties": {
    "addr:full":"Haverscroft Indust Est, New Rd Attleborough Norfolk NR17 1YE",
    "addr:postcode":"nr17 1ye",
    "addr:street":"New Rd",
    "iso:country":"GB",
    "sg:address":"Haverscroft Indust Est, New Rd",
    "sg:city":"Attleborough",
    "sg:classifiers":[
        {
            "category":"Professional",
            "subcategory":"Printing & Photocopies",
            "type":"Services"
        }
    ],
    "sg:phone":"+44 1953 455535",
    "sg:postcode":"NR17 1YE",
    "sg:province":"Norfolk",
    "sg:tags":[
        "computer",
        "tag",
        "label"
    ],
    "wof:name":"H V E Label & Foil Blocking Printers",
    "wof:placetype":"venue"
},
  "geometry": {"coordinates":[1.0144350529,52.5190544128],"type":"Point"}
}