{
  "type": "Feature",
  "properties": {
    "iso:country":"GB",
    "sg:address":"41 High Street",
    "sg:city":"Crediton",
    "sg:classifiers":[
        {
            "category":"Personal",
            "subcategory":"Beauty Salon",
            "type":"Services"
        }
    ],
    "sg:phone":"+44 1363 775433",
    "sg:postcode":"EX17 3JP",
    "sg:province":"Devon",
    "sg:tags":[
        "unisex",
        "hairdresser"
    ],
    "wof:name":"Kezia's",
    "wof:placetype":"venue"
},
  "geometry": {"coordinates":[-3.661432,50.790703],"type":"Point"}
}