{
  "type": "Feature",
  "properties": {
    "addr:full":"Lockside Huddersfield West Yorkshire HD1 3DH",
    "addr:postcode":"hd1 3dh",
    "addr:street":"West",
    "iso:country":"GB",
    "sg:address":"Lockside",
    "sg:city":"Huddersfield",
    "sg:classifiers":[
        {
            "category":"Education",
            "subcategory":"Special Training",
            "type":"Public Place"
        }
    ],
    "sg:postcode":"HD1 3DH",
    "sg:province":"West Yorkshire",
    "sg:tags":[
        "product",
        "centre"
    ],
    "wof:name":"School of Education",
    "wof:placetype":"venue"
},
  "geometry": {"coordinates":[-1.799085021,53.6309432983],"type":"Point"}
}