{
  "type": "Feature",
  "properties": {
    "iso:country":"GB",
    "sg:address":"9 Mansell Dr",
    "sg:city":"Rochester",
    "sg:classifiers":[
        {
            "category":"Building & Trades",
            "subcategory":"Plumbing",
            "type":"Services"
        }
    ],
    "sg:phone":"+44 1634 847751",
    "sg:postcode":"ME1 3HX",
    "sg:province":"Kent",
    "sg:tags":[
        "heating"
    ],
    "wof:name":"Glazebrook Plumbing & Heating",
    "wof:placetype":"venue"
},
  "geometry": {"coordinates":[0.485187,51.374535],"type":"Point"}
}