{
  "type": "Feature",
  "properties": {
    "addr:full":"11 Reads Avenue Blackpool Lancashire FY1 4BW",
    "addr:housenumber":"11",
    "addr:postcode":"fy1 4bw",
    "addr:street":"Reads Avenue",
    "iso:country":"GB",
    "sg:address":"11 Reads Avenue",
    "sg:city":"Blackpool",
    "sg:classifiers":[
        {
            "category":"Travel",
            "subcategory":"Hotels & Motels",
            "type":"Entertainment"
        }
    ],
    "sg:phone":"+44 1253 628210",
    "sg:postcode":"FY1 4BW",
    "sg:province":"Lancashire",
    "sg:tags":[
        "house",
        "guest"
    ],
    "wof:name":"Avondale",
    "wof:placetype":"venue"
},
  "geometry": {"coordinates":[-3.0498049259,53.8129386902],"type":"Point"}
}