{
  "type": "Feature",
  "properties": {
    "iso:country":"GB",
    "sg:address":"16 Thingwall Road",
    "sg:city":"Wirral",
    "sg:classifiers":[
        {
            "category":"Personal",
            "subcategory":"Beauty Salon",
            "type":"Services"
        },
        {
            "category":"Personal",
            "subcategory":"Barber",
            "type":"Services"
        }
    ],
    "sg:phone":"+44 151 648 1208",
    "sg:postcode":"CH61 3UE",
    "sg:province":"Merseyside",
    "sg:tags":[
        "unisex",
        "hairdresser"
    ],
    "wof:name":"Fringes",
    "wof:placetype":"venue"
},
  "geometry": {"coordinates":[-3.097769,53.355511],"type":"Point"}
}