{
  "type": "Feature",
  "properties": {
    "addr:full":"Low Farm, Starra La, Whixley York North Yorkshire YO26 8AU",
    "addr:postcode":"yo26 8au",
    "iso:country":"GB",
    "sg:address":"Low Farm, Starra La, Whixley",
    "sg:city":"York",
    "sg:classifiers":[
        {
            "category":"Farming",
            "subcategory":"Livestock Farm",
            "type":"Manufacturing & Wholesale Goods"
        }
    ],
    "sg:postcode":"YO26 8AU",
    "sg:province":"North Yorkshire",
    "sg:tags":[
        "others"
    ],
    "wof:name":"Kettlewell,I A & D,",
    "wof:placetype":"venue"
},
  "geometry": {"coordinates":[-1.327428,54.016209],"type":"Point"}
}