{
  "type": "Feature",
  "properties": {
    "addr:full":"367 London Road Croydon Surrey CR0 3PB",
    "addr:housenumber":"367",
    "addr:postcode":"cr0 3pb",
    "addr:street":"London Road",
    "iso:country":"GB",
    "sg:address":"367 London Road",
    "sg:city":"Croydon",
    "sg:classifiers":[
        {
            "category":"Retail",
            "subcategory":"Photofinishing",
            "type":"Services"
        }
    ],
    "sg:postcode":"CR0 3PB",
    "sg:province":"Surrey",
    "sg:tags":[
        "photographic",
        "processor"
    ],
    "wof:name":"Hi-Tech Photos",
    "wof:placetype":"venue"
},
  "geometry": {"coordinates":[-0.1100009978,51.3853111267],"type":"Point"}
}