{
  "type": "Feature",
  "properties": {
    "iso:country":"GB",
    "sg:address":"Wildwoods Farm, Marldon",
    "sg:city":"Paignton",
    "sg:classifiers":[
        {
            "category":"Farming",
            "subcategory":"Farm",
            "type":"Manufacturing & Wholesale Goods"
        }
    ],
    "sg:postcode":"TQ3 1RS",
    "sg:province":"Devon",
    "sg:tags":[
        "mixed",
        "crop"
    ],
    "wof:name":"D J Berlyn",
    "wof:placetype":"venue"
},
  "geometry": {"coordinates":[-3.593077,50.454876],"type":"Point"}
}