{
  "type": "Feature",
  "properties": {
    "addr:full":"139-140 Nightingale Road Hitchin Bedfordshire SG5 1RG",
    "addr:housenumber":"139-140",
    "addr:postcode":"sg5 1rg",
    "addr:street":"Nightingale Road",
    "iso:country":"GB",
    "sg:address":"139-140 Nightingale Road",
    "sg:city":"Hitchin",
    "sg:classifiers":[
        {
            "category":"Food & Beverages",
            "subcategory":"Groceries & Convenience Stores",
            "type":"Retail Goods"
        }
    ],
    "sg:phone":"+44 1462 421099",
    "sg:postcode":"SG5 1RG",
    "sg:province":"Bedfordshire",
    "wof:name":"Nightingale Supermarket",
    "wof:placetype":"venue"
},
  "geometry": {"coordinates":[-0.271234,51.953571],"type":"Point"}
}