{
  "type": "Feature",
  "properties": {
    "iso:country":"GB",
    "sg:address":"Verwig",
    "sg:city":"Cardigan",
    "sg:classifiers":[
        {
            "category":"Government",
            "subcategory":"Post Office",
            "type":"Public Place"
        }
    ],
    "sg:phone":"+44 1239 612413",
    "sg:postcode":"SA43 1PX",
    "sg:province":"Ceredigion",
    "wof:name":"Verwig Post Office",
    "wof:placetype":"venue"
},
  "geometry": {"coordinates":[-4.655044,52.086868],"type":"Point"}
}