{
  "type": "Feature",
  "properties": {
    "iso:country":"GB",
    "sg:address":"48 Springfield Park, Holyport",
    "sg:city":"Maidenhead",
    "sg:classifiers":[
        {
            "category":"Professional",
            "subcategory":"Computer Services",
            "type":"Services"
        }
    ],
    "sg:phone":"+44 1628 778487",
    "sg:postcode":"SL6 2YN",
    "sg:province":"Berkshire",
    "sg:tags":[
        "system",
        "software"
    ],
    "wof:name":"Ology Communications",
    "wof:placetype":"venue"
},
  "geometry": {"coordinates":[-0.701906,51.495403],"type":"Point"}
}