{
  "type": "Feature",
  "properties": {
    "addr:full":"70 Cheap Street Sherborne Dorset DT9 3BA",
    "addr:housenumber":"70",
    "addr:postcode":"dt9 3ba",
    "addr:street":"Cheap Street",
    "iso:country":"GB",
    "sg:address":"70 Cheap Street",
    "sg:city":"Sherborne",
    "sg:classifiers":[
        {
            "category":"Professional",
            "subcategory":"Lawyer & Legal Services",
            "type":"Services"
        }
    ],
    "sg:phone":"+44 1935 813133",
    "sg:postcode":"DT9 3BA",
    "sg:province":"Dorset",
    "sg:tags":[
        "solicitor"
    ],
    "wof:name":"Jeremy Wood & Co",
    "wof:placetype":"venue"
},
  "geometry": {"coordinates":[-2.516102,50.947979],"type":"Point"}
}