{
  "type": "Feature",
  "properties": {
    "addr:full":"3 Netherfaulds Drive Denny Falkirk FK6 5BX",
    "addr:housenumber":"3",
    "addr:postcode":"fk6 5bx",
    "addr:street":"Netherfaulds Drive",
    "iso:country":"GB",
    "sg:address":"3 Netherfaulds Drive",
    "sg:city":"Denny",
    "sg:classifiers":[
        {
            "category":"Banks & Credit Unions",
            "subcategory":"Bank",
            "type":"Services"
        },
        {
            "category":"Professional",
            "subcategory":"Business Services",
            "type":"Services"
        }
    ],
    "sg:phone":"+44 1324 823119",
    "sg:postcode":"FK6 5BX",
    "sg:province":"Falkirk",
    "sg:tags":[
        "stocktaking",
        "inventory"
    ],
    "wof:name":"DUNCAN MCLEAN STOCKTAKERS",
    "wof:placetype":"venue"
},
  "geometry": {"coordinates":[-3.921509,56.014839],"type":"Point"}
}