{
  "type": "Feature",
  "properties": {
    "iso:country":"GB",
    "sg:address":"91 Claude Road, Chorlton",
    "sg:city":"Manchester",
    "sg:classifiers":[
        {
            "category":"Professional",
            "subcategory":"Engineering",
            "type":"Services"
        }
    ],
    "sg:postcode":"M21 8DE",
    "sg:province":"Cheshire",
    "sg:tags":[
        "consulting",
        "engineer"
    ],
    "wof:name":"Energy  &  Environment Ltd",
    "wof:placetype":"venue"
},
  "geometry": {"coordinates":[-2.280775,53.435146],"type":"Point"}
}