{
  "type": "Feature",
  "properties": {
    "addr:full":"14 Cambrian Terrace Leeds West Yorkshire LS11 8JB",
    "addr:housenumber":"14",
    "addr:postcode":"ls11 8jb",
    "addr:street":"Cambrian Terrace",
    "iso:country":"GB",
    "sg:address":"14 Cambrian Terrace",
    "sg:city":"Leeds",
    "sg:classifiers":[
        {
            "category":"Retail",
            "subcategory":"Driving School",
            "type":"Services"
        }
    ],
    "sg:postcode":"LS11 8JB",
    "sg:province":"West Yorkshire",
    "wof:name":"Beeston School of Motoring",
    "wof:placetype":"venue"
},
  "geometry": {"coordinates":[-1.554263,53.782658],"type":"Point"}
}