{
  "type": "Feature",
  "properties": {
    "addr:full":"2 Gaol Street Oakham Leicestershire LE15 6AQ",
    "addr:housenumber":"2",
    "addr:postcode":"le15 6aq",
    "addr:street":"Gaol Street",
    "iso:country":"GB",
    "sg:address":"2 Gaol Street",
    "sg:city":"Oakham",
    "sg:classifiers":[
        {
            "category":"Manufacturing",
            "subcategory":"Petroleum Products",
            "type":"Manufacturing & Wholesale Goods"
        },
        {
            "category":"Building & Trades",
            "subcategory":"Construction",
            "type":"Services"
        }
    ],
    "sg:phone":"+44 1572 755933",
    "sg:postcode":"LE15 6AQ",
    "sg:province":"Leicestershire",
    "sg:tags":[
        "specialised",
        "contractor",
        "glazing",
        "double"
    ],
    "wof:name":"Oakham Home Improvements Ltd",
    "wof:placetype":"venue"
},
  "geometry": {"coordinates":[-0.7302619815,52.6697692871],"type":"Point"}
}