{
  "type": "Feature",
  "properties": {
    "addr:full":"Melbury The Green, Woolpit Bury St Edmunds Suffolk IP30 9RG",
    "addr:postcode":"ip30 9rg",
    "addr:street":"The Green",
    "iso:country":"GB",
    "sg:address":"Melbury The Green, Woolpit",
    "sg:city":"Bury St Edmunds",
    "sg:classifiers":[
        {
            "category":"Real Estate",
            "subcategory":"Real Estate Agent",
            "type":"Services"
        }
    ],
    "sg:postcode":"IP30 9RG",
    "sg:province":"Suffolk",
    "wof:name":"R.T. Properties Ltd",
    "wof:placetype":"venue"
},
  "geometry": {"coordinates":[0.893017,52.223724],"type":"Point"}
}