{
  "type": "Feature",
  "properties": {
    "addr:full":"Bemerton Lodge Old Peoples Home, Christie Miller Rd Salisbury Wiltshire SP2 7EN",
    "addr:postcode":"sp2 7en",
    "addr:street":"Old;Christie Miller Rd",
    "iso:country":"GB",
    "sg:address":"Bemerton Lodge Old Peoples Home, Christie Miller Rd",
    "sg:city":"Salisbury",
    "sg:classifiers":[
        {
            "category":"Government",
            "subcategory":"Office",
            "type":"Public Place"
        }
    ],
    "sg:phone":"+44 1722 331502",
    "sg:postcode":"SP2 7EN",
    "sg:province":"Wiltshire",
    "sg:tags":[
        "local"
    ],
    "wof:name":"Wiltshire County Council",
    "wof:placetype":"venue"
},
  "geometry": {"coordinates":[-1.8002840281,51.0695381165],"type":"Point"}
}