{
  "type": "Feature",
  "properties": {
    "addr:full":"21 Main Street, Colmonell Girvan South Ayrshire KA26 0RY",
    "addr:housenumber":"21",
    "addr:postcode":"ka26 0ry",
    "addr:street":"Main Street",
    "iso:country":"GB",
    "sg:address":"21 Main Street, Colmonell",
    "sg:city":"Girvan",
    "sg:classifiers":[
        {
            "category":"Travel",
            "subcategory":"Hotels & Motels",
            "type":"Entertainment"
        }
    ],
    "sg:phone":"+44 1465 881213",
    "sg:postcode":"KA26 0RY",
    "sg:province":"South Ayrshire",
    "wof:name":"The Queens Hotel",
    "wof:placetype":"venue"
},
  "geometry": {"coordinates":[-5.0043449402,55.1012077332],"type":"Point"}
}