{
  "type": "Feature",
  "properties": {
    "iso:country":"GB",
    "sg:address":"8 Dukes La",
    "sg:city":"Brighton",
    "sg:classifiers":[
        {
            "category":"Personal",
            "type":"Services"
        }
    ],
    "sg:postcode":"BN1 1BG",
    "sg:province":"East Sussex",
    "sg:tags":[
        "wedding"
    ],
    "wof:name":"Whitworth,Sarah,",
    "wof:placetype":"venue"
},
  "geometry": {"coordinates":[-0.142514,50.82272],"type":"Point"}
}