{
  "type": "Feature",
  "properties": {
    "addr:full":"Japonica Lane, Willen Park Milton Keynes Buckinghamshire MK15 9JY",
    "addr:postcode":"mk15 9jy",
    "addr:street":"Japonica Lane",
    "iso:country":"GB",
    "sg:address":"Japonica Lane, Willen Park",
    "sg:city":"Milton Keynes",
    "sg:classifiers":[
        {
            "category":"Social Services",
            "subcategory":"Retirement Home",
            "type":"Services"
        }
    ],
    "sg:phone":"+44 1908 235000",
    "sg:postcode":"MK15 9JY",
    "sg:province":"Buckinghamshire",
    "sg:tags":[
        "residential",
        "care"
    ],
    "wof:name":"Camphill Milton Keynes Communities Ltd.",
    "wof:placetype":"venue"
},
  "geometry": {"coordinates":[-0.729658,52.056564],"type":"Point"}
}