{
  "type": "Feature",
  "properties": {
    "addr:full":"5 Astwood Road, Feckenham Redditch Warwickshire B96 6HQ",
    "addr:housenumber":"5",
    "addr:postcode":"b96 6hq",
    "addr:street":"Astwood Road",
    "iso:country":"GB",
    "sg:address":"5 Astwood Road, Feckenham",
    "sg:city":"Redditch",
    "sg:classifiers":[
        {
            "category":"Shopping",
            "subcategory":"Bicycles & Sporting Goods",
            "type":"Retail Goods"
        }
    ],
    "sg:phone":"+44 1527 894000",
    "sg:postcode":"B96 6HQ",
    "sg:province":"Warwickshire",
    "sg:tags":[
        "equipment",
        "camping"
    ],
    "wof:name":"Wayfarer Leisure Ltd.",
    "wof:placetype":"venue"
},
  "geometry": {"coordinates":[-1.9874689579,52.2520484924],"type":"Point"}
}