{
  "type": "Feature",
  "properties": {
    "iso:country":"GB",
    "sg:address":"65 Kensington High Street",
    "sg:city":"London",
    "sg:classifiers":[
        {
            "category":"Shopping",
            "subcategory":"Clothing, Apparel, & Fashions",
            "type":"Retail Goods"
        }
    ],
    "sg:phone":"+44 20 7937 3573",
    "sg:postcode":"W8 5SE",
    "sg:province":"Greater London",
    "sg:tags":[
        "shop"
    ],
    "sg:website":"http://www.jigsaw-online.com",
    "wof:name":"Jigsaw",
    "wof:placetype":"venue"
},
  "geometry": {"coordinates":[-0.1902099997,51.50207901],"type":"Point"}
}