{
  "type": "Feature",
  "properties": {
    "addr:full":"Topeka House, The Luther Challis Business Park, Barnwood Road Gloucester Gloucestershire GL4 3HX",
    "addr:postcode":"gl4 3hx",
    "addr:street":"The;Business Park Barnwood Road",
    "iso:country":"GB",
    "sg:address":"Topeka House, The Luther Challis Business Park, Barnwood Road",
    "sg:city":"Gloucester",
    "sg:classifiers":[
        {
            "category":"Professional",
            "type":"Services"
        },
        {
            "category":"Conference Center",
            "type":"Public Place"
        }
    ],
    "sg:phone":"+44 1452 553456",
    "sg:postcode":"GL4 3HX",
    "sg:province":"Gloucestershire",
    "sg:tags":[
        "related"
    ],
    "wof:name":"Intercall Conferencing Services Ltd",
    "wof:placetype":"venue"
},
  "geometry": {"coordinates":[-2.209339,51.862801],"type":"Point"}
}