{
  "type": "Feature",
  "properties": {
    "addr:full":"18 Main Street, Pymore Ely Cambridgeshire CB6 2ED",
    "addr:housenumber":"18",
    "addr:postcode":"cb6 2ed",
    "addr:street":"Main Street Pymore Ely",
    "iso:country":"GB",
    "sg:address":"18 Main Street, Pymore",
    "sg:city":"Ely",
    "sg:classifiers":[
        {
            "category":"Home & Garden",
            "subcategory":"Garden Supply",
            "type":"Retail Goods"
        }
    ],
    "sg:phone":"+44 1353 699413",
    "sg:postcode":"CB6 2ED",
    "sg:province":"Cambridgeshire",
    "sg:tags":[
        "merchant",
        "seed"
    ],
    "wof:name":"C N Seeds",
    "wof:placetype":"venue"
},
  "geometry": {"coordinates":[0.201938,52.45332],"type":"Point"}
}