{
  "type": "Feature",
  "properties": {
    "iso:country":"GB",
    "sg:address":"18 Oldham Road, Failsworth",
    "sg:city":"Manchester",
    "sg:classifiers":[
        {
            "category":"Home & Garden",
            "subcategory":"Household Appliances",
            "type":"Retail Goods"
        },
        {
            "category":"Retail",
            "subcategory":"Repair Shop",
            "type":"Services"
        }
    ],
    "sg:phone":"+44 161 681 2815",
    "sg:postcode":"M35 0JE",
    "sg:province":"Lancashire",
    "sg:tags":[
        "machine",
        "electrical",
        "washing"
    ],
    "wof:name":"John Taylor",
    "wof:placetype":"venue"
},
  "geometry": {"coordinates":[-2.175151,53.504356],"type":"Point"}
}