{
  "type": "Feature",
  "properties": {
    "iso:country":"GB",
    "sg:address":"70 Castleham Road, Castleham Industrial",
    "sg:city":"St Leonards-on-sea",
    "sg:classifiers":[
        {
            "category":"Shopping",
            "subcategory":"Gifts & Souvenirs",
            "type":"Retail Goods"
        },
        {
            "category":"Building & Trades",
            "subcategory":"Construction",
            "type":"Services"
        }
    ],
    "sg:phone":"+44 1424 424243",
    "sg:postcode":"TN38 9NU",
    "sg:province":"East Sussex",
    "sg:tags":[
        "window",
        "leaded",
        "replacement"
    ],
    "wof:name":"Newlite Windows Ltd.",
    "wof:placetype":"venue"
},
  "geometry": {"coordinates":[0.539476,50.883003],"type":"Point"}
}