{
  "type": "Feature",
  "properties": {
    "addr:full":"Parc Hall, Park Road Treorchy Rhondda, Cynon, Taff CF42 6LD",
    "addr:postcode":"cf42 6ld",
    "addr:street":"Hall Park Road;Cynon Taff",
    "iso:country":"GB",
    "sg:address":"Parc Hall, Park Road",
    "sg:city":"Treorchy",
    "sg:classifiers":[
        {
            "category":"Community Center",
            "type":"Public Place"
        },
        {
            "category":"Organizations",
            "subcategory":"Membership Organization",
            "type":"Services"
        }
    ],
    "sg:phone":"+44 1443 778244",
    "sg:postcode":"CF42 6LD",
    "sg:province":"Rhondda, Cynon, Taff",
    "sg:tags":[
        "club",
        "centre"
    ],
    "wof:name":"THE MID GLAMORGAN SCOUTS ASSOCIATION",
    "wof:placetype":"venue"
},
  "geometry": {"coordinates":[-3.505229,51.659664],"type":"Point"}
}