{
  "type": "Feature",
  "properties": {
    "addr:full":"Desford Hall, Leicester Lane, Desford Leicester Leicestershire LE9 9JJ",
    "addr:housenumber":"desford",
    "addr:postcode":"le9 9jj",
    "addr:street":"Leicester Lane",
    "iso:country":"GB",
    "sg:address":"Desford Hall, Leicester Lane, Desford",
    "sg:city":"Leicester",
    "sg:classifiers":[
        {
            "category":"Banks & Credit Unions",
            "subcategory":"Financial Services",
            "type":"Services"
        }
    ],
    "sg:phone":"+44 1455 828882",
    "sg:postcode":"LE9 9JJ",
    "sg:province":"Leicestershire",
    "sg:tags":[
        "adviser"
    ],
    "wof:name":"Inter-Alliance plc",
    "wof:placetype":"venue"
},
  "geometry": {"coordinates":[-1.296534,52.625858],"type":"Point"}
}