{
  "type": "Feature",
  "properties": {
    "addr:full":"Windermere Ho, Middle St Lancaster Lancashire LA1 1JZ",
    "addr:postcode":"la1 1jz",
    "addr:street":"Middle St",
    "iso:country":"GB",
    "sg:address":"Windermere Ho, Middle St",
    "sg:city":"Lancaster",
    "sg:classifiers":[
        {
            "category":"Professional",
            "subcategory":"Employment Agencies",
            "type":"Services"
        }
    ],
    "sg:phone":"+44 1524 833344",
    "sg:postcode":"LA1 1JZ",
    "sg:province":"Lancashire",
    "sg:tags":[
        "consultant"
    ],
    "wof:name":"J Q Recruitment Ltd",
    "wof:placetype":"venue"
},
  "geometry": {"coordinates":[-2.799029,54.044537],"type":"Point"}
}