{
  "type": "Feature",
  "properties": {
    "addr:full":"53 Rathcoole Avenue Hornsey Greater London N8 9LY",
    "addr:housenumber":"53",
    "addr:postcode":"n8 9ly",
    "addr:street":"Rathcoole Avenue",
    "iso:country":"GB",
    "sg:address":"53 Rathcoole Avenue",
    "sg:city":"Hornsey",
    "sg:classifiers":[
        {
            "category":"Professional",
            "subcategory":"Computer Services",
            "type":"Services"
        }
    ],
    "sg:phone":"+44 20 8348 8585",
    "sg:postcode":"N8 9LY",
    "sg:province":"Greater London",
    "sg:tags":[
        "system",
        "software"
    ],
    "wof:name":"Peter Sergeant",
    "wof:placetype":"venue"
},
  "geometry": {"coordinates":[-0.1135329977,51.5840377808],"type":"Point"}
}