{
  "type": "Feature",
  "properties": {
    "addr:full":"2 Westly Wood Welwyn Garden City Hertfordshire AL7 1QL",
    "addr:housenumber":"2",
    "addr:postcode":"al7 1ql",
    "addr:street":"Westly Wood",
    "iso:country":"GB",
    "sg:address":"2 Westly Wood",
    "sg:city":"Welwyn Garden City",
    "sg:classifiers":[
        {
            "category":"Retail",
            "subcategory":"Driving School",
            "type":"Services"
        },
        {
            "category":"Professional",
            "subcategory":"Lawyer & Legal Services",
            "type":"Services"
        },
        {
            "category":"Professional",
            "subcategory":"Art Services",
            "type":"Services"
        },
        {
            "category":"Professional",
            "subcategory":"Secretarial Services",
            "type":"Services"
        }
    ],
    "sg:postcode":"AL7 1QL",
    "sg:province":"Hertfordshire",
    "sg:tags":[
        "photographer",
        "solicitor"
    ],
    "wof:name":"Ridgeway Business Services",
    "wof:placetype":"venue"
},
  "geometry": {"coordinates":[-0.183412,51.803295],"type":"Point"}
}