{
  "type": "Feature",
  "properties": {
    "addr:full":"1 Jardine Road Birmingham West Midlands B6 6HJ",
    "addr:housenumber":"1",
    "addr:postcode":"b6 6hj",
    "addr:street":"Jardine Road",
    "iso:country":"GB",
    "sg:address":"1 Jardine Road",
    "sg:city":"Birmingham",
    "sg:classifiers":[
        {
            "category":"Shopping",
            "subcategory":"News",
            "type":"Retail Goods"
        }
    ],
    "sg:phone":"+44 121 328 4755",
    "sg:postcode":"B6 6HJ",
    "sg:province":"West Midlands",
    "sg:tags":[
        "newsagent"
    ],
    "wof:name":"K C News",
    "wof:placetype":"venue"
},
  "geometry": {"coordinates":[-1.8880970478,52.5088005066],"type":"Point"}
}