{
  "type": "Feature",
  "properties": {
    "addr:full":"Unit 24, Sabre Court Business Park Gillingham Kent ME8 0RW",
    "addr:housenumber":"unit 24",
    "addr:postcode":"me8 0rw",
    "addr:street":"Sabre Court Business Park",
    "iso:country":"GB",
    "sg:address":"Unit 24, Sabre Court Business Park",
    "sg:city":"Gillingham",
    "sg:classifiers":[
        {
            "category":"Professional",
            "subcategory":"Engineering",
            "type":"Services"
        }
    ],
    "sg:phone":"+44 1634 231950",
    "sg:postcode":"ME8 0RW",
    "sg:province":"Kent",
    "sg:tags":[
        "contractor",
        "electrical",
        "engineer"
    ],
    "wof:name":"M & P Puxty Electrical Ltd.",
    "wof:placetype":"venue"
},
  "geometry": {"coordinates":[0.573576,51.366543],"type":"Point"}
}