{
  "type": "Feature",
  "properties": {
    "iso:country":"GB",
    "sg:address":"13 Fairfield Avenue",
    "sg:city":"Grays",
    "sg:classifiers":[
        {
            "category":"Shopping",
            "subcategory":"Computers & Home Electronics",
            "type":"Retail Goods"
        }
    ],
    "sg:postcode":"RM16 2LT",
    "sg:province":"Essex",
    "sg:tags":[
        "aerial",
        "television",
        "radio"
    ],
    "wof:name":"Outram Independent Aerials",
    "wof:placetype":"venue"
},
  "geometry": {"coordinates":[0.338932,51.50021],"type":"Point"}
}