{
  "type": "Feature",
  "properties": {
    "iso:country":"GB",
    "sg:address":"14 Madoc St",
    "sg:city":"Llandudno",
    "sg:classifiers":[
        {
            "category":"Real Estate",
            "subcategory":"Real Estate Agent",
            "type":"Services"
        }
    ],
    "sg:phone":"+44 1492 877418",
    "sg:postcode":"LL30 2TL",
    "sg:province":"Conwy",
    "wof:name":"John Snow",
    "wof:placetype":"venue"
},
  "geometry": {"coordinates":[-3.8312139511,53.3230400085],"type":"Point"}
}