{
  "type": "Feature",
  "properties": {
    "addr:full":"34 Mountain Street, Mossley Ashton-under-lyne Greater Manchester OL5 0EZ",
    "addr:housenumber":"34",
    "addr:postcode":"ol5 0ez",
    "addr:street":"Mountain Street",
    "iso:country":"GB",
    "sg:address":"34 Mountain Street, Mossley",
    "sg:city":"Ashton-under-lyne",
    "sg:classifiers":[
        {
            "category":"Professional",
            "subcategory":"Management & Consulting",
            "type":"Services"
        }
    ],
    "sg:phone":"+44 1457 837865",
    "sg:postcode":"OL5 0EZ",
    "sg:province":"Greater Manchester",
    "sg:tags":[
        "consultant",
        "specialist"
    ],
    "wof:name":"Julie",
    "wof:placetype":"venue"
},
  "geometry": {"coordinates":[-2.043463,53.517513],"type":"Point"}
}