{
  "type": "Feature",
  "properties": {
    "addr:full":"Forum Buildings, St James Parade Bath Bath and North East Somerset BA1 1UG",
    "addr:postcode":"ba1 1ug",
    "addr:street":"St James Parade",
    "iso:country":"GB",
    "sg:address":"Forum Buildings, St James Parade",
    "sg:city":"Bath",
    "sg:classifiers":[
        {
            "category":"Cafe",
            "type":"Food & Drink"
        }
    ],
    "sg:postcode":"BA1 1UG",
    "sg:province":"Bath and North East Somerset",
    "sg:tags":[
        "tea",
        "room"
    ],
    "wof:name":"Ricki's",
    "wof:placetype":"venue"
},
  "geometry": {"coordinates":[-2.361166954,51.3850708008],"type":"Point"}
}