{
  "type": "Feature",
  "properties": {
    "iso:country":"GB",
    "sg:address":"1 Hailesland Road",
    "sg:city":"Edinburgh",
    "sg:classifiers":[
        {
            "category":"Banks & Credit Unions",
            "subcategory":"Bank",
            "type":"Services"
        }
    ],
    "sg:phone":"+44 131 538 7364",
    "sg:postcode":"EH14 2QS",
    "sg:province":"City of Edinburgh",
    "wof:name":"Wester Hales Credit Union",
    "wof:placetype":"venue"
},
  "geometry": {"coordinates":[-3.2766799927,55.9175682068],"type":"Point"}
}