{
  "type": "Feature",
  "properties": {
    "addr:full":"The Guildhall Nottingham Nottinghamshire NG1 4BT",
    "addr:postcode":"ng1 4bt",
    "iso:country":"GB",
    "sg:address":"The Guildhall",
    "sg:city":"Nottingham",
    "sg:classifiers":[
        {
            "category":"Government",
            "subcategory":"Office",
            "type":"Public Place"
        }
    ],
    "sg:phone":"+44 115 915 5555",
    "sg:postcode":"NG1 4BT",
    "sg:province":"Nottinghamshire",
    "sg:tags":[
        "local"
    ],
    "wof:name":"Nottingham City Council",
    "wof:placetype":"venue"
},
  "geometry": {"coordinates":[-1.1439239979,52.9492263794],"type":"Point"}
}