{
  "type": "Feature",
  "properties": {
    "addr:full":"4 Manning Rd Felixstowe Suffolk IP11 2AS",
    "addr:housenumber":"4",
    "addr:postcode":"ip11 2as",
    "addr:street":"Manning Rd",
    "iso:country":"GB",
    "sg:address":"4 Manning Rd",
    "sg:city":"Felixstowe",
    "sg:classifiers":[
        {
            "category":"Personal",
            "subcategory":"Beauty Salon",
            "type":"Services"
        }
    ],
    "sg:postcode":"IP11 2AS",
    "sg:province":"Suffolk",
    "sg:tags":[
        "unisex",
        "hairdresser"
    ],
    "wof:name":"Smith,Edna,",
    "wof:placetype":"venue"
},
  "geometry": {"coordinates":[1.3424899578,51.9580039978],"type":"Point"}
}