{
  "type": "Feature",
  "properties": {
    "addr:full":"Unit D Bartley Drive, Telford Way Industrial Estate Kettering Northamptonshire NN16 8UN",
    "addr:housenumber":"unit d;estate",
    "addr:postcode":"nn16 8un",
    "addr:street":"Bartley Drive Telford Way Industrial",
    "iso:country":"GB",
    "sg:address":"Unit D Bartley Drive, Telford Way Industrial Estate",
    "sg:city":"Kettering",
    "sg:classifiers":[
        {
            "category":"Manufacturing",
            "subcategory":"Petroleum Products",
            "type":"Manufacturing & Wholesale Goods"
        }
    ],
    "sg:phone":"+44 1536 312222",
    "sg:postcode":"NN16 8UN",
    "sg:province":"Northamptonshire",
    "sg:tags":[
        "double",
        "glazing"
    ],
    "wof:name":"Coldseal",
    "wof:placetype":"venue"
},
  "geometry": {"coordinates":[-0.7439230084,52.406665802],"type":"Point"}
}