{
  "type": "Feature",
  "properties": {
    "addr:full":"Wyatts, Rickmansworth Road, Chorleywood Rickmansworth Hertfordshire WD3 5SE",
    "addr:postcode":"wd3 5se",
    "addr:street":"Rickmansworth Road",
    "iso:country":"GB",
    "sg:address":"Wyatts, Rickmansworth Road, Chorleywood",
    "sg:city":"Rickmansworth",
    "sg:classifiers":[
        {
            "category":"Real Estate",
            "subcategory":"Real Estate Agent",
            "type":"Services"
        }
    ],
    "sg:phone":"+44 1923 282244",
    "sg:postcode":"WD3 5SE",
    "sg:province":"Hertfordshire",
    "wof:name":"Peter Robson & Co.",
    "wof:placetype":"venue"
},
  "geometry": {"coordinates":[-0.521474,51.654804],"type":"Point"}
}