{
  "type": "Feature",
  "properties": {
    "iso:country":"GB",
    "sg:address":"1 Riddway, Wingerworth",
    "sg:city":"Chesterfield",
    "sg:classifiers":[
        {
            "category":"Real Estate",
            "subcategory":"Real Estate Agent",
            "type":"Services"
        }
    ],
    "sg:phone":"+44 1246 205610",
    "sg:postcode":"S42 6UX",
    "sg:province":"Derbyshire",
    "wof:name":"Assured Property Management",
    "wof:placetype":"venue"
},
  "geometry": {"coordinates":[-1.437169,53.196259],"type":"Point"}
}