{
  "type": "Feature",
  "properties": {
    "iso:country":"GB",
    "sg:address":"18 Grover Walk, Corringham",
    "sg:city":"Stanford-le-hope",
    "sg:classifiers":[
        {
            "category":"Retail",
            "subcategory":"Laundry & Dry Cleaning",
            "type":"Services"
        }
    ],
    "sg:phone":"+44 1375 675538",
    "sg:postcode":"SS17 7LY",
    "sg:province":"Essex",
    "sg:tags":[
        "alteration"
    ],
    "wof:name":"Dry Cleaning Plus",
    "wof:placetype":"venue"
},
  "geometry": {"coordinates":[0.446591,51.524548],"type":"Point"}
}