{
  "type": "Feature",
  "properties": {
    "addr:full":"216 Cheney Manor Road Swindon Wiltshire SN2 2NZ",
    "addr:housenumber":"216",
    "addr:postcode":"sn2 2nz",
    "addr:street":"Cheney Manor Road",
    "iso:country":"GB",
    "sg:address":"216 Cheney Manor Road",
    "sg:city":"Swindon",
    "sg:classifiers":[
        {
            "category":"Home & Garden",
            "subcategory":"Home Furnishings",
            "type":"Retail Goods"
        },
        {
            "category":"Home & Garden",
            "subcategory":"Building Materials",
            "type":"Retail Goods"
        }
    ],
    "sg:phone":"+44 1793 490076",
    "sg:postcode":"SN2 2NZ",
    "sg:province":"Wiltshire",
    "sg:tags":[
        "installers",
        "planner",
        "kitchen",
        "furnishers"
    ],
    "wof:name":"G I Tucker Kitchen & Bathroom Suppliers & Fitters",
    "wof:placetype":"venue"
},
  "geometry": {"coordinates":[-1.8016740084,51.5772247314],"type":"Point"}
}