{
  "type": "Feature",
  "properties": {
    "addr:full":"2a Clareville Gro London Greater London SW7 5AR",
    "addr:housenumber":"2a",
    "addr:postcode":"sw7 5ar",
    "addr:street":"Clareville Gro",
    "iso:country":"GB",
    "sg:address":"2a Clareville Gro",
    "sg:city":"London",
    "sg:classifiers":[
        {
            "category":"Professional",
            "subcategory":"Art Services",
            "type":"Services"
        }
    ],
    "sg:phone":"+44 20 7370 7560",
    "sg:postcode":"SW7 5AR",
    "sg:province":"Greater London",
    "sg:tags":[
        "graphic",
        "designer"
    ],
    "wof:name":"Engine Design Ltd.",
    "wof:placetype":"venue"
},
  "geometry": {"coordinates":[-0.179757,51.493214],"type":"Point"}
}