{
  "type": "Feature",
  "properties": {
    "addr:full":"30 High Street, Wendover Aylesbury Buckinghamshire HP22 6EA",
    "addr:housenumber":"30",
    "addr:postcode":"hp22 6ea",
    "addr:street":"High Street",
    "iso:country":"GB",
    "sg:address":"30 High Street, Wendover",
    "sg:city":"Aylesbury",
    "sg:classifiers":[
        {
            "category":"Professional",
            "subcategory":"Computer Services",
            "type":"Services"
        }
    ],
    "sg:postcode":"HP22 6EA",
    "sg:province":"Buckinghamshire",
    "sg:tags":[
        "system",
        "software"
    ],
    "wof:name":"Datek (Uk) Ltd",
    "wof:placetype":"venue"
},
  "geometry": {"coordinates":[-0.74414,51.762138],"type":"Point"}
}