{
  "type": "Feature",
  "properties": {
    "iso:country":"GB",
    "sg:address":"Alma Mill, Crompton Rd",
    "sg:city":"Macclesfield",
    "sg:classifiers":[
        {
            "category":"Professional",
            "type":"Services"
        }
    ],
    "sg:phone":"+44 1625 610618",
    "sg:postcode":"SK11 8DS",
    "sg:province":"Cheshire",
    "sg:tags":[
        "repair",
        "tech",
        "maintenance"
    ],
    "wof:name":"P C Workshop",
    "wof:placetype":"venue"
},
  "geometry": {"coordinates":[-2.1257560253,53.2556686401],"type":"Point"}
}