{
  "type": "Feature",
  "properties": {
    "addr:full":"66 Gardlea Road Airdrie North Lanarkshire ML6 9JN",
    "addr:housenumber":"66",
    "addr:postcode":"ml6 9jn",
    "addr:street":"Gardlea Road",
    "iso:country":"GB",
    "sg:address":"66 Gardlea Road",
    "sg:city":"Airdrie",
    "sg:classifiers":[
        {
            "category":"Food & Beverages",
            "subcategory":"Groceries & Convenience Stores",
            "type":"Retail Goods"
        }
    ],
    "sg:phone":"+44 1236 763905",
    "sg:postcode":"ML6 9JN",
    "sg:province":"North Lanarkshire",
    "wof:name":"Gardlea Superfayre",
    "wof:placetype":"venue"
},
  "geometry": {"coordinates":[-3.972401,55.860992],"type":"Point"}
}