{
  "type": "Feature",
  "properties": {
    "addr:full":"Church House, 22 Bolton Lane Ipswich Suffolk IP4 2BT",
    "addr:housenumber":"22",
    "addr:postcode":"ip4 2bt",
    "addr:street":"Bolton Lane",
    "iso:country":"GB",
    "sg:address":"Church House, 22 Bolton Lane",
    "sg:city":"Ipswich",
    "sg:classifiers":[
        {
            "category":"Place Of Worship",
            "type":"Public Place"
        }
    ],
    "sg:phone":"+44 1473 214798",
    "sg:postcode":"IP4 2BT",
    "sg:province":"Suffolk",
    "wof:name":"St. Margarets Church Office",
    "wof:placetype":"venue"
},
  "geometry": {"coordinates":[1.1595660448,52.0611877441],"type":"Point"}
}