{
  "type": "Feature",
  "properties": {
    "addr:full":"54 East Main Street Broxburn City of Edinburgh EH52 5AE",
    "addr:housenumber":"54",
    "addr:postcode":"eh52 5ae",
    "addr:street":"East Main Street",
    "iso:country":"GB",
    "sg:address":"54 East Main Street",
    "sg:city":"Broxburn",
    "sg:classifiers":[
        {
            "category":"Shopping",
            "subcategory":"Jewelry",
            "type":"Retail Goods"
        },
        {
            "category":"Shopping",
            "subcategory":"Comic Books",
            "type":"Retail Goods"
        }
    ],
    "sg:phone":"+44 1506 852407",
    "sg:postcode":"EH52 5AE",
    "sg:province":"City of Edinburgh",
    "sg:tags":[
        "jeweller",
        "sale",
        "jewellery"
    ],
    "wof:name":"Alan Cunningham",
    "wof:placetype":"venue"
},
  "geometry": {"coordinates":[-3.4696938992,55.9342041016],"type":"Point"}
}