{
  "type": "Feature",
  "properties": {
    "iso:country":"GB",
    "sg:address":"Business Centre, West Ave One",
    "sg:city":"Letchworth",
    "sg:classifiers":[
        {
            "category":"Real Estate",
            "subcategory":"Real Estate Agent",
            "type":"Services"
        }
    ],
    "sg:phone":"+44 1462 480088",
    "sg:postcode":"SG6 2HB",
    "sg:province":"Hertfordshire",
    "wof:name":"C G Property Services Ltd",
    "wof:placetype":"venue"
},
  "geometry": {"coordinates":[-0.222243,51.972549],"type":"Point"}
}