{
  "type": "Feature",
  "properties": {
    "iso:country":"GB",
    "sg:address":"Floor, 12 Southgate House, Wood St",
    "sg:city":"Cardiff",
    "sg:classifiers":[
        {
            "category":"Professional",
            "subcategory":"Management & Consulting",
            "type":"Services"
        }
    ],
    "sg:phone":"+44 29 2022 5746",
    "sg:postcode":"CF10 1EW",
    "sg:province":"Cardiff",
    "sg:tags":[
        "environmental",
        "consultant"
    ],
    "wof:name":"The Met. Office",
    "wof:placetype":"venue"
},
  "geometry": {"coordinates":[-3.178622961,51.4774589539],"type":"Point"}
}