{
  "type": "Feature",
  "properties": {
    "iso:country":"GB",
    "sg:address":"15 Merton Avenue, Hartley",
    "sg:city":"Longfield",
    "sg:classifiers":[
        {
            "category":"Professional",
            "subcategory":"Accounting & Tax Preparation",
            "type":"Services"
        }
    ],
    "sg:phone":"+44 1474 709210",
    "sg:postcode":"DA3 7EB",
    "sg:province":"Kent",
    "sg:tags":[
        "accountant"
    ],
    "wof:name":"Fox & Co.",
    "wof:placetype":"venue"
},
  "geometry": {"coordinates":[0.30648,51.392342],"type":"Point"}
}