{
  "type": "Feature",
  "properties": {
    "iso:country":"GB",
    "sg:address":"53 Oaklands Drive",
    "sg:city":"Batley",
    "sg:classifiers":[
        {
            "category":"Professional",
            "subcategory":"Engineering",
            "type":"Services"
        }
    ],
    "sg:phone":"+44 1924 444566",
    "sg:postcode":"WF17 6RD",
    "sg:province":"West Yorkshire",
    "sg:tags":[
        "contractor",
        "electrical",
        "engineer"
    ],
    "wof:name":"E D S Electrical Domestic Services",
    "wof:placetype":"venue"
},
  "geometry": {"coordinates":[-1.614634,53.712029],"type":"Point"}
}