{
  "type": "Feature",
  "properties": {
    "iso:country":"GB",
    "sg:address":"10 The Kestrels Grove",
    "sg:city":"Wantage",
    "sg:classifiers":[
        {
            "category":"Building & Trades",
            "subcategory":"Construction",
            "type":"Services"
        }
    ],
    "sg:postcode":"OX12 0QA",
    "sg:province":"Berkshire",
    "sg:tags":[
        "roofing"
    ],
    "wof:name":"Huggins Roofing",
    "wof:placetype":"venue"
},
  "geometry": {"coordinates":[-1.429729,51.612503],"type":"Point"}
}