{
  "type": "Feature",
  "properties": {
    "addr:full":"Barningham Rd, Newsham Richmond Durham DL11 7RA",
    "addr:postcode":"dl11 7ra",
    "addr:street":"Barningham Rd",
    "iso:country":"GB",
    "sg:address":"Barningham Rd, Newsham",
    "sg:city":"Richmond",
    "sg:classifiers":[
        {
            "category":"Government",
            "subcategory":"Post Office",
            "type":"Public Place"
        }
    ],
    "sg:postcode":"DL11 7RA",
    "sg:province":"Durham",
    "wof:name":"Village Stores (The)",
    "wof:placetype":"venue"
},
  "geometry": {"coordinates":[-1.8710340261,54.4891662598],"type":"Point"}
}