{
  "type": "Feature",
  "properties": {
    "addr:full":"26 Dawes Clo Coventry Warwickshire CV2 4LL",
    "addr:housenumber":"26",
    "addr:postcode":"cv2 4ll",
    "iso:country":"GB",
    "sg:address":"26 Dawes Clo",
    "sg:city":"Coventry",
    "sg:classifiers":[
        {
            "category":"Professional",
            "subcategory":"Accounting & Tax Preparation",
            "type":"Services"
        }
    ],
    "sg:phone":"+44 24 7644 7672",
    "sg:postcode":"CV2 4LL",
    "sg:province":"Warwickshire",
    "sg:tags":[
        "accountant"
    ],
    "wof:name":"B J Accountancy Services",
    "wof:placetype":"venue"
},
  "geometry": {"coordinates":[-1.48131001,52.4125366211],"type":"Point"}
}