{
  "type": "Feature",
  "properties": {
    "iso:country":"GB",
    "sg:address":"32 Redhouse Court, Blackburn",
    "sg:city":"Bathgate",
    "sg:classifiers":[
        {
            "category":"Professional",
            "subcategory":"Art Services",
            "type":"Services"
        },
        {
            "category":"Building & Trades",
            "subcategory":"Construction",
            "type":"Services"
        }
    ],
    "sg:phone":"+44 1506 633539",
    "sg:postcode":"EH47 7BU",
    "sg:province":"North Lanarkshire",
    "sg:tags":[
        "decorator",
        "painter"
    ],
    "wof:name":"Steven Barker",
    "wof:placetype":"venue"
},
  "geometry": {"coordinates":[-3.610179,55.871632],"type":"Point"}
}