{
  "type": "Feature",
  "properties": {
    "addr:full":"121 Liverpool Road, Upton By Chester Chester Cheshire CH2 1BB",
    "addr:housenumber":"121",
    "addr:postcode":"ch2 1bb",
    "addr:street":"Liverpool Road",
    "iso:country":"GB",
    "sg:address":"121 Liverpool Road, Upton By Chester",
    "sg:city":"Chester",
    "sg:classifiers":[
        {
            "category":"Health Services",
            "subcategory":"Health Practitioner",
            "type":"Services"
        }
    ],
    "sg:postcode":"CH2 1BB",
    "sg:province":"Cheshire",
    "sg:tags":[
        "osteopath"
    ],
    "wof:name":"Farooq Ahmed Khan",
    "wof:placetype":"venue"
},
  "geometry": {"coordinates":[-2.8958899975,53.2172851562],"type":"Point"}
}