{
  "type": "Feature",
  "properties": {
    "iso:country":"GB",
    "sg:address":"400 Gospel Lane",
    "sg:city":"Birmingham",
    "sg:classifiers":[
        {
            "category":"Banks & Credit Unions",
            "subcategory":"Investment Brokerage",
            "type":"Services"
        },
        {
            "category":"Government",
            "subcategory":"Post Office",
            "type":"Public Place"
        },
        {
            "category":"Shopping",
            "subcategory":"Pharmacy",
            "type":"Retail Goods"
        }
    ],
    "sg:phone":"+44 121 707 9108",
    "sg:postcode":"B27 7AW",
    "sg:province":"West Midlands",
    "sg:tags":[
        "pharmacist",
        "finance",
        "chemist",
        "broker"
    ],
    "wof:name":"S K & R Goel",
    "wof:placetype":"venue"
},
  "geometry": {"coordinates":[-1.818177,52.431419],"type":"Point"}
}