{
  "type": "Feature",
  "properties": {
    "iso:country":"GB",
    "sg:address":"145 Station Rd",
    "sg:city":"Addlestone",
    "sg:classifiers":[
        {
            "category":"Shopping",
            "subcategory":"Department Store",
            "type":"Retail Goods"
        },
        {
            "category":"Shopping",
            "subcategory":"Comic Books",
            "type":"Retail Goods"
        }
    ],
    "sg:postcode":"KT15 2AT",
    "sg:province":"Surrey",
    "sg:tags":[
        "jeweller"
    ],
    "wof:name":"O'Leary,Michael,",
    "wof:placetype":"venue"
},
  "geometry": {"coordinates":[-0.485847,51.372196],"type":"Point"}
}