{
  "type": "Feature",
  "properties": {
    "addr:full":"145 Station Rd Addlestone Surrey KT15 2AT",
    "addr:housenumber":"145",
    "addr:postcode":"kt15 2at",
    "addr:street":"Station Rd",
    "iso:country":"GB",
    "sg:address":"145 Station Rd",
    "sg:city":"Addlestone",
    "sg:classifiers":[
        {
            "category":"Shopping",
            "subcategory":"Department Store",
            "type":"Retail Goods"
        },
        {
            "category":"Shopping",
            "subcategory":"Comic Books",
            "type":"Retail Goods"
        }
    ],
    "sg:postcode":"KT15 2AT",
    "sg:province":"Surrey",
    "sg:tags":[
        "jeweller"
    ],
    "wof:name":"O'Leary,Michael,",
    "wof:placetype":"venue"
},
  "geometry": {"coordinates":[-0.485847,51.372196],"type":"Point"}
}