{
  "type": "Feature",
  "properties": {
    "addr:full":"1 Abbey Drive, Smithybridge Littleborough Lancashire OL15 0NA",
    "addr:housenumber":"1",
    "addr:postcode":"ol15 0na",
    "addr:street":"Abbey Drive",
    "iso:country":"GB",
    "sg:address":"1 Abbey Drive, Smithybridge",
    "sg:city":"Littleborough",
    "sg:classifiers":[
        {
            "category":"Building & Trades",
            "subcategory":"Plumbing",
            "type":"Services"
        }
    ],
    "sg:phone":"+44 1706 376273",
    "sg:postcode":"OL15 0NA",
    "sg:province":"Lancashire",
    "sg:tags":[
        "heating"
    ],
    "wof:name":"Property Services",
    "wof:placetype":"venue"
},
  "geometry": {"coordinates":[-2.1082088947,53.6352233887],"type":"Point"}
}