{
  "type": "Feature",
  "properties": {
    "iso:country":"GB",
    "sg:address":"39 High St",
    "sg:city":"Kirriemuir",
    "sg:classifiers":[
        {
            "category":"Shopping",
            "subcategory":"Books",
            "type":"Retail Goods"
        }
    ],
    "sg:postcode":"DD8 4JG",
    "sg:province":"Angus",
    "sg:tags":[
        "bookseller"
    ],
    "wof:name":"Collins,William,",
    "wof:placetype":"venue"
},
  "geometry": {"coordinates":[-3.0045089722,56.6731338501],"type":"Point"}
}