{
  "type": "Feature",
  "properties": {
    "iso:country":"GB",
    "sg:address":"The Shambles, Waterloo Street",
    "sg:city":"Market Rasen",
    "sg:classifiers":[
        {
            "category":"Shopping",
            "subcategory":"Florist",
            "type":"Retail Goods"
        }
    ],
    "sg:postcode":"LN8 3ES",
    "sg:province":"Lincolnshire",
    "wof:name":"Occasional Flowers",
    "wof:placetype":"venue"
},
  "geometry": {"coordinates":[-0.3415389955,53.3946266174],"type":"Point"}
}