{
  "type": "Feature",
  "properties": {
    "addr:full":"Conchieton Kirkcudbright Dumfries and Galloway DG6 4TA",
    "addr:postcode":"dg6 4ta",
    "iso:country":"GB",
    "sg:address":"Conchieton",
    "sg:city":"Kirkcudbright",
    "sg:classifiers":[
        {
            "category":"Professional",
            "subcategory":"Art Services",
            "type":"Services"
        },
        {
            "category":"Professional",
            "subcategory":"Computer Services",
            "type":"Services"
        }
    ],
    "sg:phone":"+44 1557 870256",
    "sg:postcode":"DG6 4TA",
    "sg:province":"Dumfries and Galloway",
    "sg:tags":[
        "consultant",
        "design",
        "system",
        "software"
    ],
    "wof:name":"CARSON MANAGEMENT SYSTEMS",
    "wof:placetype":"venue"
},
  "geometry": {"coordinates":[-4.0476388931,54.836971283],"type":"Point"}
}