{
  "type": "Feature",
  "properties": {
    "iso:country":"GB",
    "sg:address":"234 Fratton Road",
    "sg:city":"Portsmouth",
    "sg:classifiers":[
        {
            "category":"Fast Food",
            "type":"Food & Drink"
        }
    ],
    "sg:phone":"+44 23 9282 4720",
    "sg:postcode":"PO1 5HH",
    "sg:province":"Hampshire",
    "sg:tags":[
        "away",
        "take"
    ],
    "wof:name":"Indian Ocean Takeaway",
    "wof:placetype":"venue"
},
  "geometry": {"coordinates":[-1.077139,50.801979],"type":"Point"}
}