{
  "type": "Feature",
  "properties": {
    "iso:country":"GB",
    "sg:address":"53 Adams Maedows",
    "sg:city":"Ilminster",
    "sg:classifiers":[
        {
            "category":"Manufacturing",
            "subcategory":"Petroleum Products",
            "type":"Manufacturing & Wholesale Goods"
        },
        {
            "category":"Building & Trades",
            "subcategory":"Construction",
            "type":"Services"
        }
    ],
    "sg:phone":"+44 1460 52290",
    "sg:postcode":"TA19 9DB",
    "sg:province":"Somerset",
    "sg:tags":[
        "double",
        "glazing",
        "installers"
    ],
    "wof:name":"STEVE APPLETON",
    "wof:placetype":"venue"
},
  "geometry": {"coordinates":[-2.91753,50.928669],"type":"Point"}
}