{
  "type": "Feature",
  "properties": {
    "addr:full":"Cartmell Road Blackburn Lancashire BB2 2SZ",
    "addr:postcode":"bb2 2sz",
    "addr:street":"Cartmell Road",
    "iso:country":"GB",
    "sg:address":"Cartmell Road",
    "sg:city":"Blackburn",
    "sg:classifiers":[
        {
            "category":"Home & Garden",
            "subcategory":"Home Furnishings",
            "type":"Retail Goods"
        },
        {
            "category":"Manufacturing",
            "subcategory":"Textiles",
            "type":"Manufacturing & Wholesale Goods"
        }
    ],
    "sg:phone":"+44 1254 55101",
    "sg:postcode":"BB2 2SZ",
    "sg:province":"Lancashire",
    "sg:tags":[
        "made-up",
        "wallpaper"
    ],
    "wof:name":"VOITH PAPER FABRICS BLACKBURN LTD",
    "wof:placetype":"venue"
},
  "geometry": {"coordinates":[-2.5102639198,53.7389640808],"type":"Point"}
}