{
  "type": "Feature",
  "properties": {
    "addr:full":"37 The Street, Bapchild Sittingbourne Kent ME9 9AD",
    "addr:housenumber":"37",
    "addr:postcode":"me9 9ad",
    "addr:street":"The Street",
    "iso:country":"GB",
    "sg:address":"37 The Street, Bapchild",
    "sg:city":"Sittingbourne",
    "sg:classifiers":[
        {
            "category":"Sports & Exercise",
            "subcategory":"Race Track",
            "type":"Entertainment"
        }
    ],
    "sg:phone":"+44 1795 410400",
    "sg:postcode":"ME9 9AD",
    "sg:province":"Kent",
    "sg:tags":[
        "motor"
    ],
    "wof:name":"Lica Motorsport",
    "wof:placetype":"venue"
},
  "geometry": {"coordinates":[0.769396,51.334423],"type":"Point"}
}