{
  "type": "Feature",
  "properties": {
    "addr:full":"Unit 24 Crossgrange Fairfax Rd, Heathfield Indust Est Heathfield Newton Abbot Devon TQ12 6UD",
    "addr:housenumber":"unit 24",
    "addr:postcode":"tq12 6ud",
    "addr:street":"Crossgrange Fairfax Rd;Indust",
    "iso:country":"GB",
    "sg:address":"Unit 24 Crossgrange Fairfax Rd, Heathfield Indust Est Heathfield",
    "sg:city":"Newton Abbot",
    "sg:classifiers":[
        {
            "category":"Shopping",
            "subcategory":"Crafts & Fabrics",
            "type":"Retail Goods"
        }
    ],
    "sg:postcode":"TQ12 6UD",
    "sg:province":"Devon",
    "sg:tags":[
        "knitwear",
        "yarn"
    ],
    "wof:name":"Gracepoint Ltd",
    "wof:placetype":"venue"
},
  "geometry": {"coordinates":[-3.656849,50.567791],"type":"Point"}
}