{
  "type": "Feature",
  "properties": {
    "addr:full":"64 Guy Road Kenilworth Warwickshire CV8 1FX",
    "addr:housenumber":"64",
    "addr:postcode":"cv8 1fx",
    "addr:street":"Guy Road",
    "iso:country":"GB",
    "sg:address":"64 Guy Road",
    "sg:city":"Kenilworth",
    "sg:classifiers":[
        {
            "category":"Retail",
            "subcategory":"Driving School",
            "type":"Services"
        }
    ],
    "sg:phone":"+44 1926 856047",
    "sg:postcode":"CV8 1FX",
    "sg:province":"Warwickshire",
    "wof:name":"Castle Driving School",
    "wof:placetype":"venue"
},
  "geometry": {"coordinates":[-1.57759,52.335171],"type":"Point"}
}