{
  "type": "Feature",
  "properties": {
    "addr:full":"206 Bramhall Lane South, Bramhall Stockport Cheshire SK7 3AA",
    "addr:housenumber":"206",
    "addr:postcode":"sk7 3aa",
    "addr:street":"Bramhall Lane South",
    "iso:country":"GB",
    "sg:address":"206 Bramhall Lane South, Bramhall",
    "sg:city":"Stockport",
    "sg:classifiers":[
        {
            "category":"Communications",
            "subcategory":"Film & Video Production",
            "type":"Services"
        }
    ],
    "sg:phone":"+44 161 439 1117",
    "sg:postcode":"SK7 3AA",
    "sg:province":"Cheshire",
    "sg:tags":[
        "illustrator",
        "artist"
    ],
    "wof:name":"D Wilkinson",
    "wof:placetype":"venue"
},
  "geometry": {"coordinates":[-2.1613750458,53.3704490662],"type":"Point"}
}