{
  "type": "Feature",
  "properties": {
    "addr:full":"38 Oak Park Rise Barnsley South Yorkshire S70 4PB",
    "addr:housenumber":"38",
    "addr:postcode":"s70 4pb",
    "addr:street":"Oak Park Rise;Yorkshire",
    "iso:country":"GB",
    "sg:address":"38 Oak Park Rise",
    "sg:city":"Barnsley",
    "sg:classifiers":[
        {
            "category":"Retail",
            "subcategory":"Auto Repair",
            "type":"Services"
        }
    ],
    "sg:phone":"+44 1226 247761",
    "sg:postcode":"S70 4PB",
    "sg:province":"South Yorkshire",
    "sg:tags":[
        "engine",
        "car",
        "specialist"
    ],
    "wof:name":"Motax Engine Tuning",
    "wof:placetype":"venue"
},
  "geometry": {"coordinates":[-1.470719,53.543716],"type":"Point"}
}