{
  "type": "Feature",
  "properties": {
    "iso:country":"GB",
    "sg:address":"3 Wycliffe St",
    "sg:city":"Leicester",
    "sg:classifiers":[
        {
            "category":"Professional",
            "subcategory":"Lawyer & Legal Services",
            "type":"Services"
        }
    ],
    "sg:phone":"+44 116 254 6457",
    "sg:postcode":"LE1 5LR",
    "sg:province":"Leicestershire",
    "sg:tags":[
        "solicitor"
    ],
    "wof:name":"F Derek Nurse",
    "wof:placetype":"venue"
},
  "geometry": {"coordinates":[-1.136176,52.632927],"type":"Point"}
}