{
  "type": "Feature",
  "properties": {
    "addr:full":"Norwood Works, Broad Oak Road Canterbury Kent CT2 7QB",
    "addr:postcode":"ct2 7qb",
    "addr:street":"Broad Oak Road",
    "iso:country":"GB",
    "sg:address":"Norwood Works, Broad Oak Road",
    "sg:city":"Canterbury",
    "sg:classifiers":[
        {
            "category":"Shopping",
            "subcategory":"Stationery & Office Supplies",
            "type":"Retail Goods"
        },
        {
            "category":"Shopping",
            "type":"Retail Goods"
        }
    ],
    "sg:phone":"+44 1227 768747",
    "sg:postcode":"CT2 7QB",
    "sg:province":"Kent",
    "sg:tags":[
        "packaging",
        "bag",
        "material"
    ],
    "wof:name":"Robins Paper Bag Co. Ltd.",
    "wof:placetype":"venue"
},
  "geometry": {"coordinates":[1.09195,51.292599],"type":"Point"}
}