{
  "type": "Feature",
  "properties": {
    "iso:country":"GB",
    "sg:address":"86 Malvern Av",
    "sg:city":"Harrow",
    "sg:classifiers":[
        {
            "category":"Home & Garden",
            "subcategory":"Household Appliances",
            "type":"Retail Goods"
        }
    ],
    "sg:phone":"+44 20 8423 1678",
    "sg:postcode":"HA2 9EX",
    "sg:province":"Greater London",
    "sg:tags":[
        "electrical"
    ],
    "wof:name":"Laurie Johnston",
    "wof:placetype":"venue"
},
  "geometry": {"coordinates":[-0.3716959953,51.5659561157],"type":"Point"}
}