{
  "type": "Feature",
  "properties": {
    "iso:country":"GB",
    "sg:address":"96 The Ridgeway",
    "sg:city":"Westcliff-on-sea",
    "sg:classifiers":[
        {
            "category":"Restaurant",
            "type":"Food & Drink"
        }
    ],
    "sg:phone":"+44 1702 480213",
    "sg:postcode":"SS0 8NU",
    "sg:province":"Essex",
    "sg:tags":[
        "chinese"
    ],
    "wof:name":"Noble House",
    "wof:placetype":"venue"
},
  "geometry": {"coordinates":[0.6740130186,51.5389823914],"type":"Point"}
}