{
  "type": "Feature",
  "properties": {
    "addr:full":"1-2 Orchard Parade Eastbourne East Sussex BN20 9PL",
    "addr:housenumber":"1-2",
    "addr:postcode":"bn20 9pl",
    "addr:street":"Orchard Parade",
    "iso:country":"GB",
    "sg:address":"1-2 Orchard Parade",
    "sg:city":"Eastbourne",
    "sg:classifiers":[
        {
            "category":"Shopping",
            "subcategory":"Pharmacy",
            "type":"Retail Goods"
        }
    ],
    "sg:phone":"+44 1323 484448",
    "sg:postcode":"BN20 9PL",
    "sg:province":"East Sussex",
    "sg:tags":[
        "pharmacist",
        "store",
        "drug",
        "chemist"
    ],
    "wof:name":"Triangle Pharmacy",
    "wof:placetype":"venue"
},
  "geometry": {"coordinates":[0.2482250035,50.8078193665],"type":"Point"}
}