{
  "type": "Feature",
  "properties": {
    "addr:full":"99 Station Rd Cardiff Cardiff CF4 2FD",
    "addr:housenumber":"99",
    "addr:postcode":"cf4 2fd",
    "addr:street":"Station Rd",
    "iso:country":"GB",
    "sg:address":"99 Station Rd",
    "sg:city":"Cardiff",
    "sg:classifiers":[
        {
            "category":"Health Services",
            "subcategory":"Doctor",
            "type":"Services"
        }
    ],
    "sg:phone":"+44 29 2056 7822",
    "sg:postcode":"CF4 2FD",
    "sg:province":"Cardiff",
    "sg:tags":[
        "practitioners"
    ],
    "wof:name":"Llandaff North Medical Centre",
    "wof:placetype":"venue"
},
  "geometry": {"coordinates":[-3.2284870148,51.5046005249],"type":"Point"}
}