{
  "type": "Feature",
  "properties": {
    "iso:country":"GB",
    "sg:address":"26 Easter Drylaw Place",
    "sg:city":"Edinburgh",
    "sg:classifiers":[
        {
            "category":"Building & Trades",
            "subcategory":"Construction",
            "type":"Services"
        }
    ],
    "sg:phone":"+44 131 343 6642",
    "sg:postcode":"EH4 2QF",
    "sg:province":"City of Edinburgh",
    "sg:tags":[
        "glazier"
    ],
    "wof:name":"J W Glazing Ltd",
    "wof:placetype":"venue"
},
  "geometry": {"coordinates":[-3.2432770729,55.9670982361],"type":"Point"}
}