{
  "type": "Feature",
  "properties": {
    "addr:full":"6 Windmill Avenue, Raunds Wellingborough Northamptonshire NN9 6JX",
    "addr:housenumber":"6",
    "addr:postcode":"nn9 6jx",
    "addr:street":"Windmill Avenue",
    "iso:country":"GB",
    "sg:address":"6 Windmill Avenue, Raunds",
    "sg:city":"Wellingborough",
    "sg:classifiers":[
        {
            "category":"Building & Trades",
            "subcategory":"Landscaping Services",
            "type":"Services"
        },
        {
            "category":"Banks & Credit Unions",
            "subcategory":"Investment Brokerage",
            "type":"Services"
        }
    ],
    "sg:phone":"+44 1933 460071",
    "sg:postcode":"NN9 6JX",
    "sg:province":"Northamptonshire",
    "sg:tags":[
        "supplier",
        "turf",
        "landscape",
        "contractor"
    ],
    "wof:name":"P & H Landscapes",
    "wof:placetype":"venue"
},
  "geometry": {"coordinates":[-0.53787,52.345341],"type":"Point"}
}