{
  "type": "Feature",
  "properties": {
    "iso:country":"GB",
    "sg:address":"Mountview",
    "sg:city":"Cairndow",
    "sg:classifiers":[
        {
            "category":"Retail",
            "subcategory":"Repair Shop",
            "type":"Services"
        }
    ],
    "sg:phone":"+44 1301 703311",
    "sg:postcode":"PA24 8AJ",
    "sg:province":"Argyll and Bute",
    "sg:tags":[
        "sharpening",
        "tool"
    ],
    "wof:name":"Mike the Knife",
    "wof:placetype":"venue"
},
  "geometry": {"coordinates":[-4.912738,56.156952],"type":"Point"}
}