{
  "type": "Feature",
  "properties": {
    "iso:country":"GB",
    "sg:address":"17 Berriew Street",
    "sg:city":"Welshpool",
    "sg:classifiers":[
        {
            "category":"Home & Garden",
            "subcategory":"Carpets & Floor Coverings",
            "type":"Retail Goods"
        }
    ],
    "sg:phone":"+44 1938 553345",
    "sg:postcode":"SY21 7SQ",
    "sg:province":"Shropshire",
    "sg:tags":[
        "carpets",
        "rug",
        "matting"
    ],
    "wof:name":"Powys Carpets Ltd.",
    "wof:placetype":"venue"
},
  "geometry": {"coordinates":[-3.1476609707,52.6587791443],"type":"Point"}
}