{
  "type": "Feature",
  "properties": {
    "addr:full":"58 Birley Moor Road Sheffield Derbyshire S12 4WD",
    "addr:housenumber":"58",
    "addr:postcode":"s12 4wd",
    "addr:street":"Birley Moor Road",
    "iso:country":"GB",
    "sg:address":"58 Birley Moor Road",
    "sg:city":"Sheffield",
    "sg:classifiers":[
        {
            "category":"Shopping",
            "subcategory":"Florist",
            "type":"Retail Goods"
        }
    ],
    "sg:phone":"+44 114 254 4445",
    "sg:postcode":"S12 4WD",
    "sg:province":"Derbyshire",
    "wof:name":"Daisy Chain Florists",
    "wof:placetype":"venue"
},
  "geometry": {"coordinates":[-1.4018919468,53.3492851257],"type":"Point"}
}