{
  "type": "Feature",
  "properties": {
    "iso:country":"GB",
    "sg:address":"5 Canterbury Lane",
    "sg:city":"Canterbury",
    "sg:classifiers":[
        {
            "category":"Restaurant",
            "type":"Food & Drink"
        }
    ],
    "sg:phone":"+44 1227 765506",
    "sg:postcode":"CT1 2HL",
    "sg:province":"Kent",
    "wof:name":"Panteli's of Canterbury Ltd.",
    "wof:placetype":"venue"
},
  "geometry": {"coordinates":[1.08351,51.278038],"type":"Point"}
}