{
  "type": "Feature",
  "properties": {
    "addr:full":"439 West Derby Road Liverpool Merseyside L6 4BL",
    "addr:housenumber":"439",
    "addr:postcode":"l6 4bl",
    "addr:street":"West Derby Road",
    "iso:country":"GB",
    "sg:address":"439 West Derby Road",
    "sg:city":"Liverpool",
    "sg:classifiers":[
        {
            "category":"Autos & Motor Vehicles",
            "subcategory":"Automobile Sales",
            "type":"Retail Goods"
        },
        {
            "category":"Retail",
            "subcategory":"Auto Repair",
            "type":"Services"
        }
    ],
    "sg:postcode":"L6 4BL",
    "sg:province":"Merseyside",
    "sg:tags":[
        "garage",
        "related",
        "car"
    ],
    "wof:name":"BROOKFIELD MOTOR CO",
    "wof:placetype":"venue"
},
  "geometry": {"coordinates":[-2.939586,53.423027],"type":"Point"}
}