{
  "type": "Feature",
  "properties": {
    "iso:country":"GB",
    "sg:address":"The Wheelwright Shop, Webbington, Loxton",
    "sg:city":"Axbridge",
    "sg:classifiers":[
        {
            "category":"Museum",
            "subcategory":"Art Museum",
            "type":"Entertainment"
        }
    ],
    "sg:phone":"+44 1934 750841",
    "sg:postcode":"BS26 2HX",
    "sg:province":"Somerset",
    "sg:tags":[
        "gallery"
    ],
    "wof:name":"The Wheelwrights Working Museum & Gypsy Folklore Collection",
    "wof:placetype":"venue"
},
  "geometry": {"coordinates":[-2.818409,51.288391],"type":"Point"}
}