{
  "type": "Feature",
  "properties": {
    "addr:full":"23 Lucas Close Yateley Hampshire GU46 6JD",
    "addr:housenumber":"23",
    "addr:postcode":"gu46 6jd",
    "addr:street":"Lucas Close",
    "iso:country":"GB",
    "sg:address":"23 Lucas Close",
    "sg:city":"Yateley",
    "sg:classifiers":[
        {
            "category":"Shopping",
            "subcategory":"Pharmacy",
            "type":"Retail Goods"
        }
    ],
    "sg:phone":"+44 1252 671488",
    "sg:postcode":"GU46 6JD",
    "sg:province":"Hampshire",
    "sg:tags":[
        "medicine",
        "therapy"
    ],
    "wof:name":"Madeleine Cloridor-wood BA Psychol MA",
    "wof:placetype":"venue"
},
  "geometry": {"coordinates":[-0.8293390274,51.3352737427],"type":"Point"}
}