{
  "type": "Feature",
  "properties": {
    "addr:full":"7 Ullswater Drive Wetherby North Yorkshire LS22 6YF",
    "addr:housenumber":"7",
    "addr:postcode":"ls22 6yf",
    "addr:street":"Ullswater Drive",
    "iso:country":"GB",
    "sg:address":"7 Ullswater Drive",
    "sg:city":"Wetherby",
    "sg:classifiers":[
        {
            "category":"Professional",
            "subcategory":"Management & Consulting",
            "type":"Services"
        }
    ],
    "sg:postcode":"LS22 6YF",
    "sg:province":"North Yorkshire",
    "sg:tags":[
        "marketing",
        "consultant"
    ],
    "wof:name":"P H Developments",
    "wof:placetype":"venue"
},
  "geometry": {"coordinates":[-1.403216,53.932037],"type":"Point"}
}