{
  "type": "Feature",
  "properties": {
    "iso:country":"GB",
    "sg:address":"152 Hasler Rd, Candford Heath",
    "sg:city":"Poole",
    "sg:classifiers":[
        {
            "category":"Home & Garden",
            "subcategory":"Home Furnishings",
            "type":"Retail Goods"
        },
        {
            "category":"Communications",
            "type":"Services"
        }
    ],
    "sg:postcode":"BH17 9AH",
    "sg:province":"Dorset",
    "sg:tags":[
        "planner",
        "tv",
        "furnishers",
        "video",
        "radio",
        "kitchen"
    ],
    "wof:name":"Samways,Brian Robert,",
    "wof:placetype":"venue"
},
  "geometry": {"coordinates":[-1.980719,50.752083],"type":"Point"}
}