{
  "type": "Feature",
  "properties": {
    "addr:full":"32 Caspian Gro Stoke-on-trent Staffordshire ST4 8RX",
    "addr:housenumber":"32",
    "addr:postcode":"st4 8rx",
    "addr:street":"Caspian Gro",
    "iso:country":"GB",
    "sg:address":"32 Caspian Gro",
    "sg:city":"Stoke-on-trent",
    "sg:classifiers":[
        {
            "category":"Restaurant",
            "type":"Food & Drink"
        }
    ],
    "sg:phone":"+44 1782 642038",
    "sg:postcode":"ST4 8RX",
    "sg:province":"Staffordshire",
    "wof:name":"Rutherfords Canal Boat Restaurant",
    "wof:placetype":"venue"
},
  "geometry": {"coordinates":[-2.1808750629,52.9689216614],"type":"Point"}
}