{
  "type": "Feature",
  "properties": {
    "iso:country":"GB",
    "sg:address":"236 Clyde Street",
    "sg:city":"Glasgow",
    "sg:classifiers":[
        {
            "category":"Organizations",
            "subcategory":"Non-profit Organization",
            "type":"Services"
        }
    ],
    "sg:phone":"+44 141 241 6185",
    "sg:postcode":"G1 4JH",
    "sg:province":"Glasgow City",
    "sg:tags":[
        "organisation",
        "voluntary",
        "charity"
    ],
    "wof:name":"Leonard Cheshire Services",
    "wof:placetype":"venue"
},
  "geometry": {"coordinates":[-4.2548618317,55.855846405],"type":"Point"}
}