{
  "type": "Feature",
  "properties": {
    "iso:country":"GB",
    "sg:address":"21 Witney Way, Boldon Business Park",
    "sg:city":"Boldon Colliery",
    "sg:classifiers":[
        {
            "category":"Professional",
            "subcategory":"Printing & Photocopies",
            "type":"Services"
        }
    ],
    "sg:phone":"+44 191 519 0202",
    "sg:postcode":"NE35 9PE",
    "sg:province":"Tyne and Wear",
    "sg:tags":[
        "typesetter"
    ],
    "wof:name":"Keywords",
    "wof:placetype":"venue"
},
  "geometry": {"coordinates":[-1.4707100391,54.9437713623],"type":"Point"}
}