{
  "type": "Feature",
  "properties": {
    "iso:country":"GB",
    "sg:address":"East Farm, Waldridge Lane",
    "sg:city":"Chester-le-street",
    "sg:classifiers":[
        {
            "category":"Home & Garden",
            "subcategory":"Building Materials",
            "type":"Retail Goods"
        }
    ],
    "sg:phone":"+44 191 389 2817",
    "sg:postcode":"DH2 2NQ",
    "sg:province":"Durham",
    "sg:tags":[
        "fencing"
    ],
    "wof:name":"Charlton Fencing",
    "wof:placetype":"venue"
},
  "geometry": {"coordinates":[-1.598176,54.851646],"type":"Point"}
}