{
  "type": "Feature",
  "properties": {
    "addr:full":"5 Moorland Avenue, Delph Oldham Lancashire OL3 5QF",
    "addr:housenumber":"5",
    "addr:postcode":"ol3 5qf",
    "addr:street":"Moorland Avenue",
    "iso:country":"GB",
    "sg:address":"5 Moorland Avenue, Delph",
    "sg:city":"Oldham",
    "sg:classifiers":[
        {
            "category":"Communications",
            "subcategory":"Film & Video Production",
            "type":"Services"
        },
        {
            "category":"Professional",
            "subcategory":"Art Services",
            "type":"Services"
        }
    ],
    "sg:phone":"+44 1457 876938",
    "sg:postcode":"OL3 5QF",
    "sg:province":"Lancashire",
    "sg:tags":[
        "illustrator",
        "artist"
    ],
    "wof:name":"Robert Littleford",
    "wof:placetype":"venue"
},
  "geometry": {"coordinates":[-2.018848896,53.5594940186],"type":"Point"}
}