{
  "type": "Feature",
  "properties": {
    "iso:country":"GB",
    "sg:address":"Welsh Walls",
    "sg:city":"Oswestry",
    "sg:classifiers":[
        {
            "category":"Restaurant",
            "type":"Food & Drink"
        }
    ],
    "sg:phone":"+44 1691 670970",
    "sg:postcode":"SY11 1AW",
    "sg:province":"Shropshire",
    "wof:name":"The Walls Eating House & Dining Room",
    "wof:placetype":"venue"
},
  "geometry": {"coordinates":[-3.058588,52.860687],"type":"Point"}
}