{
  "type": "Feature",
  "properties": {
    "iso:country":"GB",
    "sg:address":"The Clock Tower, Lyne",
    "sg:city":"Chertsey",
    "sg:classifiers":[
        {
            "category":"Building & Trades",
            "subcategory":"Landscaping Services",
            "type":"Services"
        }
    ],
    "sg:phone":"+44 1932 571800",
    "sg:postcode":"KT16 0BH",
    "sg:province":"Surrey",
    "sg:tags":[
        "horticultural",
        "consultant"
    ],
    "wof:name":"Rotec",
    "wof:placetype":"venue"
},
  "geometry": {"coordinates":[-0.545274,51.385864],"type":"Point"}
}