{
  "type": "Feature",
  "properties": {
    "iso:country":"GB",
    "sg:address":"South Road, Chapel St Leonards",
    "sg:city":"Skegness",
    "sg:classifiers":[
        {
            "category":"Travel",
            "subcategory":"Hotels & Motels",
            "type":"Entertainment"
        }
    ],
    "sg:phone":"+44 1754 872228",
    "sg:postcode":"PE24 5TH",
    "sg:province":"Lincolnshire",
    "wof:name":"Vine Hotel",
    "wof:placetype":"venue"
},
  "geometry": {"coordinates":[0.336813,53.223297],"type":"Point"}
}