{
  "type": "Feature",
  "properties": {
    "addr:full":"West End La Esher Surrey KT10 8LB",
    "addr:postcode":"kt10 8lb",
    "addr:street":"West",
    "iso:country":"GB",
    "sg:address":"West End La",
    "sg:city":"Esher",
    "sg:classifiers":[
        {
            "category":"Community Center",
            "type":"Public Place"
        }
    ],
    "sg:phone":"+44 1372 463535",
    "sg:postcode":"KT10 8LB",
    "sg:province":"Surrey",
    "sg:tags":[
        "recreation",
        "leisure",
        "centre"
    ],
    "wof:name":"West End Recreation Ground",
    "wof:placetype":"venue"
},
  "geometry": {"coordinates":[-0.3802239895,51.3627052307],"type":"Point"}
}