{
  "type": "Feature",
  "properties": {
    "addr:full":"114a Baddeley Green Lane Stoke-on-trent Staffordshire ST2 7HA",
    "addr:housenumber":"114a",
    "addr:postcode":"st2 7ha",
    "addr:street":"Baddeley Green Lane",
    "iso:country":"GB",
    "sg:address":"114a Baddeley Green Lane",
    "sg:city":"Stoke-on-trent",
    "sg:classifiers":[
        {
            "category":"Shopping",
            "subcategory":"Department Store",
            "type":"Retail Goods"
        }
    ],
    "sg:postcode":"ST2 7HA",
    "sg:province":"Staffordshire",
    "wof:name":"Baddeley Green Stores",
    "wof:placetype":"venue"
},
  "geometry": {"coordinates":[-2.1398489475,53.0527000427],"type":"Point"}
}