{
  "type": "Feature",
  "properties": {
    "addr:full":"The Old Workhouse, Hudds Vale Road, St George Bristol City of Bristol BS5 7HY",
    "addr:postcode":"bs5 7hy",
    "addr:street":"Vale Road",
    "iso:country":"GB",
    "sg:address":"The Old Workhouse, Hudds Vale Road, St George",
    "sg:city":"Bristol",
    "sg:classifiers":[
        {
            "category":"Building & Trades",
            "subcategory":"Construction",
            "type":"Services"
        }
    ],
    "sg:phone":"+44 117 941 4222",
    "sg:postcode":"BS5 7HY",
    "sg:province":"City of Bristol",
    "sg:tags":[
        "ceiling",
        "contractor"
    ],
    "wof:name":"H & L Ceilings Ltd.",
    "wof:placetype":"venue"
},
  "geometry": {"coordinates":[-2.5444099903,51.4630317688],"type":"Point"}
}