{
  "type": "Feature",
  "properties": {
    "addr:full":"70 Ferring Street, Ferring Worthing West Sussex BN12 5JP",
    "addr:housenumber":"70",
    "addr:postcode":"bn12 5jp",
    "addr:street":"Ferring Street",
    "iso:country":"GB",
    "sg:address":"70 Ferring Street, Ferring",
    "sg:city":"Worthing",
    "sg:classifiers":[
        {
            "category":"Health Services",
            "subcategory":"Dentist",
            "type":"Services"
        }
    ],
    "sg:phone":"+44 1903 246858",
    "sg:postcode":"BN12 5JP",
    "sg:province":"West Sussex",
    "wof:name":"Dental Surgery",
    "wof:placetype":"venue"
},
  "geometry": {"coordinates":[-0.447031,50.815258],"type":"Point"}
}