{
  "type": "Feature",
  "properties": {
    "iso:country":"GB",
    "sg:address":"Hale Road Indstl Est, Halebank",
    "sg:city":"Widnes",
    "sg:classifiers":[
        {
            "category":"Building & Trades",
            "subcategory":"Equipment Rental",
            "type":"Services"
        }
    ],
    "sg:postcode":"WA8 8XW",
    "sg:province":"Cheshire",
    "sg:tags":[
        "plant",
        "machinery"
    ],
    "wof:name":"Airpac Rentals",
    "wof:placetype":"venue"
},
  "geometry": {"coordinates":[-2.756549,53.369705],"type":"Point"}
}