{
  "type": "Feature",
  "properties": {
    "addr:full":"62 Compayne Gardens London Greater London NW6 3RY",
    "addr:housenumber":"62",
    "addr:postcode":"nw6 3ry",
    "addr:street":"Compayne Gardens",
    "iso:country":"GB",
    "sg:address":"62 Compayne Gardens",
    "sg:city":"London",
    "sg:classifiers":[
        {
            "category":"Arts & Performance",
            "subcategory":"Theater",
            "type":"Entertainment"
        }
    ],
    "sg:phone":"+44 20 7372 1928",
    "sg:postcode":"NW6 3RY",
    "sg:province":"Greater London",
    "sg:tags":[
        "theatrical",
        "agency"
    ],
    "wof:name":"June Epstein Associates",
    "wof:placetype":"venue"
},
  "geometry": {"coordinates":[-0.187277,51.545212],"type":"Point"}
}