{
  "type": "Feature",
  "properties": {
    "iso:country":"GB",
    "sg:address":"6 Cookham Road",
    "sg:city":"Maidenhead",
    "sg:classifiers":[
        {
            "category":"Health Services",
            "subcategory":"Dentist",
            "type":"Services"
        }
    ],
    "sg:phone":"+44 1628 623584",
    "sg:postcode":"SL6 8AJ",
    "sg:province":"Berkshire",
    "wof:name":"D R Archer & A J Crosbie",
    "wof:placetype":"venue"
},
  "geometry": {"coordinates":[-0.7200139761,51.5250816345],"type":"Point"}
}