{
  "type": "Feature",
  "properties": {
    "addr:full":"5 Gloucester Road Cirencester Gloucestershire GL7 2LB",
    "addr:housenumber":"5",
    "addr:postcode":"gl7 2lb",
    "addr:street":"Gloucester Road",
    "iso:country":"GB",
    "sg:address":"5 Gloucester Road",
    "sg:city":"Cirencester",
    "sg:classifiers":[
        {
            "category":"Bars & Pubs",
            "type":"Food & Drink"
        }
    ],
    "sg:phone":"+44 1285 653422",
    "sg:postcode":"GL7 2LB",
    "sg:province":"Gloucestershire",
    "sg:tags":[
        "pubs",
        "inn"
    ],
    "wof:name":"Plough Inn",
    "wof:placetype":"venue"
},
  "geometry": {"coordinates":[-1.9794620275,51.728477478],"type":"Point"}
}