{
  "type": "Feature",
  "properties": {
    "addr:full":"7 Springfield Park Alnwick Northumberland NE66 2NH",
    "addr:housenumber":"7",
    "addr:postcode":"ne66 2nh",
    "addr:street":"Springfield Park",
    "iso:country":"GB",
    "sg:address":"7 Springfield Park",
    "sg:city":"Alnwick",
    "sg:classifiers":[
        {
            "category":"Freight",
            "type":"Transportation"
        }
    ],
    "sg:phone":"+44 1665 602803",
    "sg:postcode":"NE66 2NH",
    "sg:province":"Northumberland",
    "sg:tags":[
        "haulage",
        "transport",
        "road"
    ],
    "wof:name":"Richard Aynsley",
    "wof:placetype":"venue"
},
  "geometry": {"coordinates":[-1.6943509579,55.4108314514],"type":"Point"}
}