{
  "type": "Feature",
  "properties": {
    "iso:country":"GB",
    "sg:address":"15 High Street",
    "sg:city":"Burton-on-trent",
    "sg:classifiers":[
        {
            "category":"Shopping",
            "subcategory":"Comic Books",
            "type":"Retail Goods"
        }
    ],
    "sg:phone":"+44 1283 542501",
    "sg:postcode":"DE14 1HU",
    "sg:province":"Derbyshire",
    "sg:tags":[
        "jeweller"
    ],
    "wof:name":"Samuel H",
    "wof:placetype":"venue"
},
  "geometry": {"coordinates":[-1.630908,52.801823],"type":"Point"}
}