{
  "type": "Feature",
  "properties": {
    "addr:full":"The School House, Church Lane Bakewell Derbyshire DE45 1DE",
    "addr:postcode":"de45 1de",
    "addr:street":"Church Lane",
    "iso:country":"GB",
    "sg:address":"The School House, Church Lane",
    "sg:city":"Bakewell",
    "sg:classifiers":[
        {
            "category":"Professional",
            "subcategory":"Computer Services",
            "type":"Services"
        }
    ],
    "sg:phone":"+44 1629 813232",
    "sg:postcode":"DE45 1DE",
    "sg:province":"Derbyshire",
    "sg:tags":[
        "consultant"
    ],
    "wof:name":"Package Solutions Ltd.",
    "wof:placetype":"venue"
},
  "geometry": {"coordinates":[-1.6788090467,53.2141265869],"type":"Point"}
}