{
  "type": "Feature",
  "properties": {
    "iso:country":"GB",
    "sg:address":"54 Avebury, Little Foxes",
    "sg:city":"Bracknell",
    "sg:classifiers":[
        {
            "category":"Professional",
            "subcategory":"Engineering",
            "type":"Services"
        }
    ],
    "sg:phone":"+44 1344 422672",
    "sg:postcode":"RG12 8SQ",
    "sg:province":"Berkshire",
    "sg:tags":[
        "contractor",
        "electrical",
        "engineer"
    ],
    "wof:name":"R & R Electrics",
    "wof:placetype":"venue"
},
  "geometry": {"coordinates":[-0.76314,51.397667],"type":"Point"}
}