{
  "type": "Feature",
  "properties": {
    "iso:country":"GB",
    "sg:address":"Castle Works, Bolton Street",
    "sg:city":"Bury",
    "sg:classifiers":[
        {
            "category":"Shopping",
            "subcategory":"Gifts & Souvenirs",
            "type":"Retail Goods"
        }
    ],
    "sg:phone":"+44 161 797 7803",
    "sg:postcode":"BL9 0LL",
    "sg:province":"Lancashire",
    "sg:tags":[
        "ducting"
    ],
    "wof:name":"Cold Roll Rings",
    "wof:placetype":"venue"
},
  "geometry": {"coordinates":[-2.303154,53.593769],"type":"Point"}
}