{
  "type": "Feature",
  "properties": {
    "iso:country":"GB",
    "sg:address":"Healey New Mills, Healey Road",
    "sg:city":"Ossett",
    "sg:classifiers":[
        {
            "category":"Real Estate",
            "subcategory":"Real Estate Agent",
            "type":"Services"
        }
    ],
    "sg:phone":"+44 1924 273109",
    "sg:postcode":"WF5 8NF",
    "sg:province":"West Yorkshire",
    "wof:name":"Briggs Wilson & Sons Ltd.",
    "wof:placetype":"venue"
},
  "geometry": {"coordinates":[-1.586879,53.677761],"type":"Point"}
}