{
  "type": "Feature",
  "properties": {
    "addr:full":"3 The Butts, Warwick Warwick Warwickshire CV34 4SS",
    "addr:housenumber":"3",
    "addr:postcode":"cv34 4ss",
    "addr:street":"The Butts",
    "iso:country":"GB",
    "sg:address":"3 The Butts, Warwick",
    "sg:city":"Warwick",
    "sg:classifiers":[
        {
            "category":"Professional",
            "subcategory":"Management & Consulting",
            "type":"Services"
        }
    ],
    "sg:phone":"+44 1926 403040",
    "sg:postcode":"CV34 4SS",
    "sg:province":"Warwickshire",
    "sg:tags":[
        "consultant",
        "business"
    ],
    "wof:name":"J & A B Associates Ltd.",
    "wof:placetype":"venue"
},
  "geometry": {"coordinates":[-1.5880709887,52.2835083008],"type":"Point"}
}