{
  "type": "Feature",
  "properties": {
    "addr:full":"46 Western Road Bexhill-on-sea East Sussex TN40 1DY",
    "addr:housenumber":"46",
    "addr:postcode":"tn40 1dy",
    "addr:street":"Western Road",
    "iso:country":"GB",
    "sg:address":"46 Western Road",
    "sg:city":"Bexhill-on-sea",
    "sg:classifiers":[
        {
            "category":"Shopping",
            "subcategory":"Pets & Pet Supplies",
            "type":"Retail Goods"
        }
    ],
    "sg:postcode":"TN40 1DY",
    "sg:province":"East Sussex",
    "wof:name":"Bexhill Pets",
    "wof:placetype":"venue"
},
  "geometry": {"coordinates":[0.470709,50.840191],"type":"Point"}
}