{
  "type": "Feature",
  "properties": {
    "iso:country":"GB",
    "sg:address":"52a High Street, Epworth",
    "sg:city":"Doncaster",
    "sg:classifiers":[
        {
            "category":"Shopping",
            "subcategory":"Clothing, Apparel, & Fashions",
            "type":"Retail Goods"
        }
    ],
    "sg:postcode":"DN9 1EP",
    "sg:province":"Lincolnshire",
    "sg:tags":[
        "lingerie",
        "hosiery"
    ],
    "wof:name":"Freda's",
    "wof:placetype":"venue"
},
  "geometry": {"coordinates":[-0.822066009,53.5259017944],"type":"Point"}
}