{
  "type": "Feature",
  "properties": {
    "addr:full":"333 London Road Mitcham Greater London CR4 4BE",
    "addr:housenumber":"333",
    "addr:postcode":"cr4 4be",
    "addr:street":"London Road",
    "iso:country":"GB",
    "sg:address":"333 London Road",
    "sg:city":"Mitcham",
    "sg:classifiers":[
        {
            "category":"Shopping",
            "subcategory":"News",
            "type":"Retail Goods"
        }
    ],
    "sg:phone":"+44 20 8640 3193",
    "sg:postcode":"CR4 4BE",
    "sg:province":"Greater London",
    "sg:tags":[
        "newsagent"
    ],
    "wof:name":"News & Food",
    "wof:placetype":"venue"
},
  "geometry": {"coordinates":[-0.169219,51.400349],"type":"Point"}
}