{
  "type": "Feature",
  "properties": {
    "addr:full":"Park Road, Hockley Birmingham West Midlands B18 5HE",
    "addr:postcode":"b18 5he",
    "addr:street":"Park Road Hockley",
    "iso:country":"GB",
    "sg:address":"Park Road, Hockley",
    "sg:city":"Birmingham",
    "sg:classifiers":[
        {
            "category":"Building & Trades",
            "subcategory":"Construction",
            "type":"Services"
        }
    ],
    "sg:phone":"+44 121 554 4551",
    "sg:postcode":"B18 5HE",
    "sg:province":"West Midlands",
    "sg:tags":[
        "builder"
    ],
    "wof:name":"Richmond Construction",
    "wof:placetype":"venue"
},
  "geometry": {"coordinates":[-1.929579,52.498409],"type":"Point"}
}