{
  "type": "Feature",
  "properties": {
    "iso:country":"GB",
    "sg:address":"65 Main St",
    "sg:city":"Edinburgh",
    "sg:classifiers":[
        {
            "category":"Health Services",
            "subcategory":"Dentist",
            "type":"Services"
        }
    ],
    "sg:phone":"+44 131 336 3903",
    "sg:postcode":"EH4 5AD",
    "sg:province":"City of Edinburgh",
    "wof:name":"E Butler",
    "wof:placetype":"venue"
},
  "geometry": {"coordinates":[-3.268269062,55.9656982422],"type":"Point"}
}