{
  "type": "Feature",
  "properties": {
    "addr:full":"17 West Bar Street Banbury Oxfordshire OX16 9SA",
    "addr:housenumber":"17",
    "addr:postcode":"ox16 9sa",
    "addr:street":"West Bar Street",
    "iso:country":"GB",
    "sg:address":"17 West Bar Street",
    "sg:city":"Banbury",
    "sg:classifiers":[
        {
            "category":"Professional",
            "subcategory":"Lawyer & Legal Services",
            "type":"Services"
        }
    ],
    "sg:phone":"+44 1295 263556",
    "sg:postcode":"OX16 9SA",
    "sg:province":"Oxfordshire",
    "sg:tags":[
        "solicitor"
    ],
    "wof:name":"Herbert & Cholmeley",
    "wof:placetype":"venue"
},
  "geometry": {"coordinates":[-1.3434430361,52.0590705872],"type":"Point"}
}