{
  "type": "Feature",
  "properties": {
    "iso:country":"GB",
    "sg:address":"5 Baker Street",
    "sg:city":"Cheltenham",
    "sg:classifiers":[
        {
            "category":"Building & Trades",
            "subcategory":"Construction",
            "type":"Services"
        }
    ],
    "sg:phone":"+44 1242 512557",
    "sg:postcode":"GL50 9HG",
    "sg:province":"Gloucestershire",
    "sg:tags":[
        "builder"
    ],
    "wof:name":"Graham E Morris",
    "wof:placetype":"venue"
},
  "geometry": {"coordinates":[-2.0843679905,51.9071121216],"type":"Point"}
}