{
  "type": "Feature",
  "properties": {
    "addr:full":"St Johns House, St Johns Street Bury St Edmunds Suffolk IP33 1SJ",
    "addr:postcode":"ip33 1sj",
    "addr:street":"St Johns Street",
    "iso:country":"GB",
    "sg:address":"St Johns House, St Johns Street",
    "sg:city":"Bury St Edmunds",
    "sg:classifiers":[
        {
            "category":"Shopping",
            "subcategory":"Clothing, Apparel, & Fashions",
            "type":"Retail Goods"
        }
    ],
    "sg:phone":"+44 1284 765222",
    "sg:postcode":"IP33 1SJ",
    "sg:province":"Suffolk",
    "sg:tags":[
        "menswear"
    ],
    "wof:name":"Glanville",
    "wof:placetype":"venue"
},
  "geometry": {"coordinates":[0.712876,52.249874],"type":"Point"}
}