{
  "type": "Feature",
  "properties": {
    "iso:country":"GB",
    "sg:address":"Cadgers Way, The Grange, Earlsferry",
    "sg:city":"Leven",
    "sg:classifiers":[
        {
            "category":"Professional",
            "subcategory":"Management & Consulting",
            "type":"Services"
        }
    ],
    "sg:phone":"+44 1333 330578",
    "sg:postcode":"KY9 1AN",
    "sg:province":"Fife",
    "sg:tags":[
        "consultant",
        "business"
    ],
    "wof:name":"Dickson Corporate Management",
    "wof:placetype":"venue"
},
  "geometry": {"coordinates":[-2.833519,56.190006],"type":"Point"}
}