{
  "type": "Feature",
  "properties": {
    "addr:full":"Unit 3, Hanover Mills, Greg St, Reddish Stockport Cheshire SK5 7NR",
    "addr:housenumber":"unit 3",
    "addr:postcode":"sk5 7nr",
    "addr:street":"Hanover Mills Greg St",
    "iso:country":"GB",
    "sg:address":"Unit 3, Hanover Mills, Greg St, Reddish",
    "sg:city":"Stockport",
    "sg:classifiers":[
        {
            "category":"Government",
            "subcategory":"Post Office",
            "type":"Public Place"
        }
    ],
    "sg:phone":"+44 161 476 0600",
    "sg:postcode":"SK5 7NR",
    "sg:province":"Cheshire",
    "sg:tags":[
        "messenger",
        "courier"
    ],
    "wof:name":"Via-tec Services",
    "wof:placetype":"venue"
},
  "geometry": {"coordinates":[-2.1612000465,53.4289512634],"type":"Point"}
}