{
  "type": "Feature",
  "properties": {
    "addr:full":"51 Borough High Street London Greater London SE1 1NB",
    "addr:housenumber":"51",
    "addr:postcode":"se1 1nb",
    "addr:street":"Borough High Street",
    "iso:country":"GB",
    "sg:address":"51 Borough High Street",
    "sg:city":"London",
    "sg:classifiers":[
        {
            "category":"Travel",
            "subcategory":"Travel Agent",
            "type":"Entertainment"
        }
    ],
    "sg:postcode":"SE1 1NB",
    "sg:province":"Greater London",
    "wof:name":"Baxter Hoare Travel Ltd.",
    "wof:placetype":"venue"
},
  "geometry": {"coordinates":[-0.0898099989,51.5048294067],"type":"Point"}
}