{
  "type": "Feature",
  "properties": {
    "addr:full":"28 Eaton Drive, Collier Row Romford Essex RM5 2ND",
    "addr:housenumber":"28",
    "addr:postcode":"rm5 2nd",
    "addr:street":"Eaton Drive",
    "iso:country":"GB",
    "sg:address":"28 Eaton Drive, Collier Row",
    "sg:city":"Romford",
    "sg:classifiers":[
        {
            "category":"Shopping",
            "subcategory":"Clothing, Apparel, & Fashions",
            "type":"Retail Goods"
        }
    ],
    "sg:phone":"+44 1708 748170",
    "sg:postcode":"RM5 2ND",
    "sg:province":"Essex",
    "sg:tags":[
        "shop",
        "hat"
    ],
    "wof:name":"Occasional Hats Hire Service",
    "wof:placetype":"venue"
},
  "geometry": {"coordinates":[0.1587869972,51.5990371704],"type":"Point"}
}