{
  "type": "Feature",
  "properties": {
    "addr:full":"51 Barkly Road, Beeston Leeds West Yorkshire LS11 7EN",
    "addr:housenumber":"51",
    "addr:postcode":"ls11 7en",
    "addr:street":"Barkly Road",
    "iso:country":"GB",
    "sg:address":"51 Barkly Road, Beeston",
    "sg:city":"Leeds",
    "sg:classifiers":[
        {
            "category":"Manufacturing",
            "subcategory":"Wood Products",
            "type":"Manufacturing & Wholesale Goods"
        },
        {
            "category":"Building & Trades",
            "subcategory":"Construction",
            "type":"Services"
        }
    ],
    "sg:phone":"+44 113 270 1833",
    "sg:postcode":"LS11 7EN",
    "sg:province":"West Yorkshire",
    "sg:tags":[
        "joinery",
        "manufacturer"
    ],
    "wof:name":"Vickers Joinery Ltd",
    "wof:placetype":"venue"
},
  "geometry": {"coordinates":[-1.561446,53.770283],"type":"Point"}
}