{
  "type": "Feature",
  "properties": {
    "addr:full":"94 Nathans Road, North Wembley Wembley Greater London HA0 3RX",
    "addr:housenumber":"94",
    "addr:postcode":"ha0 3rx",
    "addr:street":"Nathans Road",
    "iso:country":"GB",
    "sg:address":"94 Nathans Road, North Wembley",
    "sg:city":"Wembley",
    "sg:classifiers":[
        {
            "category":"Home & Garden",
            "subcategory":"Home Furnishings",
            "type":"Retail Goods"
        },
        {
            "category":"Manufacturing",
            "subcategory":"Furniture",
            "type":"Manufacturing & Wholesale Goods"
        }
    ],
    "sg:phone":"+44 20 8908 2229",
    "sg:postcode":"HA0 3RX",
    "sg:province":"Greater London",
    "sg:tags":[
        "soft",
        "manufacturer"
    ],
    "wof:name":"Deepa Furnishings",
    "wof:placetype":"venue"
},
  "geometry": {"coordinates":[-0.309531,51.570602],"type":"Point"}
}