{
  "type": "Feature",
  "properties": {
    "addr:full":", Gladestry Kington Kington Herefordshire HR5 3NR",
    "addr:postcode":"hr5 3nr",
    "addr:street":"Gladestry",
    "iso:country":"GB",
    "sg:address":", Gladestry Kington",
    "sg:city":"Kington",
    "sg:classifiers":[
        {
            "category":"Education",
            "subcategory":"School",
            "type":"Public Place"
        }
    ],
    "sg:phone":"+44 1544 370207",
    "sg:postcode":"HR5 3NR",
    "sg:province":"Herefordshire",
    "sg:tags":[
        "local",
        "authority"
    ],
    "wof:name":"Gladestry Church in Wales Primary School",
    "wof:placetype":"venue"
},
  "geometry": {"coordinates":[-3.0294780731,52.20362854],"type":"Point"}
}