{
  "type": "Feature",
  "properties": {
    "addr:full":"Jenkins Farm Jenkins Lane, Edge Stroud Gloucestershire GL6 6NB",
    "addr:postcode":"gl6 6nb",
    "addr:street":"Jenkins Lane",
    "iso:country":"GB",
    "sg:address":"Jenkins Farm Jenkins Lane, Edge",
    "sg:city":"Stroud",
    "sg:classifiers":[
        {
            "category":"Farming",
            "subcategory":"Livestock Farm",
            "type":"Manufacturing & Wholesale Goods"
        },
        {
            "category":"Farming",
            "subcategory":"Farm",
            "type":"Manufacturing & Wholesale Goods"
        }
    ],
    "sg:phone":"+44 1452 812566",
    "sg:postcode":"GL6 6NB",
    "sg:province":"Gloucestershire",
    "sg:tags":[
        "mixed",
        "crop",
        "others"
    ],
    "wof:name":"Martin S Slinger",
    "wof:placetype":"venue"
},
  "geometry": {"coordinates":[-2.221104,51.786236],"type":"Point"}
}