{
  "type": "Feature",
  "properties": {
    "iso:country":"GB",
    "sg:address":"Ivy Cottage, Brogdale Road",
    "sg:city":"Faversham",
    "sg:classifiers":[
        {
            "category":"Building & Trades",
            "subcategory":"Construction",
            "type":"Services"
        }
    ],
    "sg:postcode":"ME13 8XU",
    "sg:province":"Kent",
    "sg:tags":[
        "builder"
    ],
    "wof:name":"Burden K Building Contractor & Brickwork Specialis",
    "wof:placetype":"venue"
},
  "geometry": {"coordinates":[0.8834400177,51.3096046448],"type":"Point"}
}