{
  "type": "Feature",
  "properties": {
    "iso:country":"GB",
    "sg:address":"266 Overndale Road, Fishponds",
    "sg:city":"Bristol",
    "sg:classifiers":[
        {
            "category":"Education",
            "subcategory":"School",
            "type":"Public Place"
        }
    ],
    "sg:phone":"+44 117 956 7977",
    "sg:postcode":"BS16 2RG",
    "sg:province":"City of Bristol",
    "sg:tags":[
        "independent",
        "preparatory"
    ],
    "wof:name":"Gracefield Preparatory School",
    "wof:placetype":"venue"
},
  "geometry": {"coordinates":[-2.518476963,51.4840660095],"type":"Point"}
}