{
  "type": "Feature",
  "properties": {
    "addr:full":"219 Rannoch Road Perth Perth and Kinross PH1 2DP",
    "addr:housenumber":"219",
    "addr:postcode":"ph1 2dp",
    "addr:street":"Rannoch Road",
    "iso:country":"GB",
    "sg:address":"219 Rannoch Road",
    "sg:city":"Perth",
    "sg:classifiers":[
        {
            "category":"Government",
            "subcategory":"Post Office",
            "type":"Public Place"
        }
    ],
    "sg:phone":"+44 1738 628095",
    "sg:postcode":"PH1 2DP",
    "sg:province":"Perth and Kinross",
    "wof:name":"Letham Sub Post Office",
    "wof:placetype":"venue"
},
  "geometry": {"coordinates":[-3.4725289345,56.4019470215],"type":"Point"}
}