{
  "type": "Feature",
  "properties": {
    "iso:country":"GB",
    "sg:address":"191 Stockwell Rd",
    "sg:city":"Brixton",
    "sg:classifiers":[
        {
            "category":"Shopping",
            "subcategory":"Pharmacy",
            "type":"Retail Goods"
        }
    ],
    "sg:phone":"+44 20 7737 0079",
    "sg:postcode":"SW9 9SJ",
    "sg:province":"Greater London",
    "sg:tags":[
        "medicine",
        "therapy"
    ],
    "wof:name":"Meridian Clinic",
    "wof:placetype":"venue"
},
  "geometry": {"coordinates":[-0.115518,51.465454],"type":"Point"}
}