{
  "type": "Feature",
  "properties": {
    "addr:full":"126 High Street, Eckington Sheffield Derbyshire S21 4DR",
    "addr:housenumber":"126",
    "addr:postcode":"s21 4dr",
    "addr:street":"High Street",
    "iso:country":"GB",
    "sg:address":"126 High Street, Eckington",
    "sg:city":"Sheffield",
    "sg:classifiers":[
        {
            "category":"Bars & Pubs",
            "type":"Food & Drink"
        },
        {
            "category":"Community Center",
            "subcategory":"Social",
            "type":"Public Place"
        }
    ],
    "sg:phone":"+44 1246 433665",
    "sg:postcode":"S21 4DR",
    "sg:province":"Derbyshire",
    "sg:tags":[
        "pubs",
        "house",
        "inn",
        "activity"
    ],
    "wof:name":"The Bird in the Hand",
    "wof:placetype":"venue"
},
  "geometry": {"coordinates":[-1.3637789488,53.3080787659],"type":"Point"}
}