{
  "type": "Feature",
  "properties": {
    "iso:country":"GB",
    "sg:address":"Staple House, Eleanors Cross",
    "sg:city":"Dunstable",
    "sg:classifiers":[
        {
            "category":"Real Estate",
            "subcategory":"Real Estate Agent",
            "type":"Services"
        }
    ],
    "sg:phone":"+44 1582 476677",
    "sg:postcode":"LU6 1SU",
    "sg:province":"Bedfordshire",
    "wof:name":"Densons Property Management",
    "wof:placetype":"venue"
},
  "geometry": {"coordinates":[-0.5231900215,51.8864479065],"type":"Point"}
}