{
  "type": "Feature",
  "properties": {
    "iso:country":"GB",
    "sg:address":"14 King Street",
    "sg:city":"Penrith",
    "sg:classifiers":[
        {
            "category":"Communications",
            "subcategory":"Newspaper",
            "type":"Services"
        }
    ],
    "sg:phone":"+44 1768 862313",
    "sg:postcode":"CA11 7AH",
    "sg:province":"Cumbria",
    "sg:tags":[
        "magazine"
    ],
    "wof:name":"Cumberland & Westmorland Herald Ltd.",
    "wof:placetype":"venue"
},
  "geometry": {"coordinates":[-2.7506809235,54.6632499695],"type":"Point"}
}