{
  "type": "Feature",
  "properties": {
    "iso:country":"GB",
    "sg:address":"Alberton House, Hogwood Lane",
    "sg:city":"Wokingham",
    "sg:classifiers":[
        {
            "category":"Transit Center",
            "subcategory":"Passenger",
            "type":"Transportation"
        }
    ],
    "sg:postcode":"RG40 4RF",
    "sg:province":"Berkshire",
    "sg:tags":[
        "airport"
    ],
    "wof:name":"& Global Aviation Ltd.",
    "wof:placetype":"venue"
},
  "geometry": {"coordinates":[-0.889501,51.37616],"type":"Point"}
}