{
  "type": "Feature",
  "properties": {
    "addr:full":"Halsey Cross Farm, Nether Stowey Bridgwater Somerset TA5 1JB",
    "addr:postcode":"ta5 1jb",
    "addr:street":"Halsey Cross Farm Nether Stowey",
    "iso:country":"GB",
    "sg:address":"Halsey Cross Farm, Nether Stowey",
    "sg:city":"Bridgwater",
    "sg:classifiers":[
        {
            "category":"Farming",
            "subcategory":"Livestock Farm",
            "type":"Manufacturing & Wholesale Goods"
        }
    ],
    "sg:phone":"+44 1278 732413",
    "sg:postcode":"TA5 1JB",
    "sg:province":"Somerset",
    "sg:tags":[
        "others"
    ],
    "wof:name":"Raymond Barrow",
    "wof:placetype":"venue"
},
  "geometry": {"coordinates":[-3.161729,51.153904],"type":"Point"}
}