{
  "type": "Feature",
  "properties": {
    "iso:country":"GB",
    "sg:address":"94 Wyngate Drive",
    "sg:city":"Leicester",
    "sg:classifiers":[
        {
            "category":"Building & Trades",
            "subcategory":"Construction",
            "type":"Services"
        }
    ],
    "sg:phone":"+44 7977 307855",
    "sg:postcode":"LE3 0UT",
    "sg:province":"Leicestershire",
    "sg:tags":[
        "flooring"
    ],
    "wof:name":"Keane Block Paving",
    "wof:placetype":"venue"
},
  "geometry": {"coordinates":[-1.161942,52.62962],"type":"Point"}
}