{
  "type": "Feature",
  "properties": {
    "addr:full":"Unit 1 Knightsbridge, The Postings Kirkcaldy Fife KY1 1HN",
    "addr:housenumber":"unit 1",
    "addr:postcode":"ky1 1hn",
    "addr:street":"Knightsbridge The Postings",
    "iso:country":"GB",
    "sg:address":"Unit 1 Knightsbridge, The Postings",
    "sg:city":"Kirkcaldy",
    "sg:classifiers":[
        {
            "category":"Shopping",
            "subcategory":"Books",
            "type":"Retail Goods"
        }
    ],
    "sg:postcode":"KY1 1HN",
    "sg:province":"Fife",
    "sg:tags":[
        "bookseller"
    ],
    "wof:name":"Readers Paradise",
    "wof:placetype":"venue"
},
  "geometry": {"coordinates":[-3.1630289555,56.1095962524],"type":"Point"}
}