{
  "type": "Feature",
  "properties": {
    "iso:country":"GB",
    "sg:address":"69 Bromfield Rd, Southcrest",
    "sg:city":"Redditch",
    "sg:classifiers":[
        {
            "category":"Professional",
            "subcategory":"Art Services",
            "type":"Services"
        }
    ],
    "sg:postcode":"B97 4PQ",
    "sg:province":"Warwickshire",
    "sg:tags":[
        "photographer"
    ],
    "wof:name":"Jones,Patricia,",
    "wof:placetype":"venue"
},
  "geometry": {"coordinates":[-1.945778966,52.2998466492],"type":"Point"}
}