{
  "type": "Feature",
  "properties": {
    "iso:country":"GB",
    "sg:address":"24 High Street, Keynsham",
    "sg:city":"Bristol",
    "sg:classifiers":[
        {
            "category":"Retail",
            "subcategory":"Funeral Services",
            "type":"Services"
        }
    ],
    "sg:phone":"+44 117 986 3233",
    "sg:postcode":"BS31 1DQ",
    "sg:province":"City of Bristol",
    "wof:name":"Co-Op Funeral Services",
    "wof:placetype":"venue"
},
  "geometry": {"coordinates":[-2.499133,51.416637],"type":"Point"}
}