{
  "type": "Feature",
  "properties": {
    "iso:country":"GB",
    "sg:address":"P.o Box 714 18 Llwyn Estyn, Aberconwy",
    "sg:city":"Conwy",
    "sg:classifiers":[
        {
            "category":"Government",
            "subcategory":"Post Office",
            "type":"Public Place"
        }
    ],
    "sg:phone":"+44 1492 573743",
    "sg:postcode":"LL31 9RA",
    "sg:province":"Conwy",
    "sg:tags":[
        "organisation",
        "soc",
        "research"
    ],
    "wof:name":"Varol Research",
    "wof:placetype":"venue"
},
  "geometry": {"coordinates":[-3.8148300648,53.2907295227],"type":"Point"}
}