{
  "type": "Feature",
  "properties": {
    "iso:country":"GB",
    "sg:address":"41a Spring Gardens",
    "sg:city":"Buxton",
    "sg:classifiers":[
        {
            "category":"Professional",
            "subcategory":"Computer Services",
            "type":"Services"
        }
    ],
    "sg:phone":"+44 1298 27460",
    "sg:postcode":"SK17 6BJ",
    "sg:province":"Derbyshire",
    "sg:tags":[
        "system",
        "software"
    ],
    "wof:name":"Sky Software",
    "wof:placetype":"venue"
},
  "geometry": {"coordinates":[-1.912232995,53.2592010498],"type":"Point"}
}