{
  "type": "Feature",
  "properties": {
    "iso:country":"GB",
    "sg:address":"63 Main Street, Torrance",
    "sg:city":"Glasgow",
    "sg:classifiers":[
        {
            "category":"Government",
            "subcategory":"Post Office",
            "type":"Public Place"
        }
    ],
    "sg:postcode":"G64 4EL",
    "sg:province":"East Dunbartonshire",
    "wof:name":"Torrance Post Office",
    "wof:placetype":"venue"
},
  "geometry": {"coordinates":[-4.212414,55.938274],"type":"Point"}
}