{
  "type": "Feature",
  "properties": {
    "addr:full":"34 Courtenay Street Newton Abbot Devon TQ12 2TA",
    "addr:housenumber":"34",
    "addr:postcode":"tq12 2ta",
    "addr:street":"Courtenay Street",
    "iso:country":"GB",
    "sg:address":"34 Courtenay Street",
    "sg:city":"Newton Abbot",
    "sg:classifiers":[
        {
            "category":"Shopping",
            "subcategory":"Gifts & Souvenirs",
            "type":"Retail Goods"
        }
    ],
    "sg:phone":"+44 1626 361283",
    "sg:postcode":"TQ12 2TA",
    "sg:province":"Devon",
    "sg:tags":[
        "poster",
        "card"
    ],
    "wof:name":"Clinton Cards Plc",
    "wof:placetype":"venue"
},
  "geometry": {"coordinates":[-3.6098370552,50.5303611755],"type":"Point"}
}