{
  "type": "Feature",
  "properties": {
    "addr:full":"89 Graham Street Airdrie North Lanarkshire ML6 6DE",
    "addr:housenumber":"89",
    "addr:postcode":"ml6 6de",
    "addr:street":"Graham Street",
    "iso:country":"GB",
    "sg:address":"89 Graham Street",
    "sg:city":"Airdrie",
    "sg:classifiers":[
        {
            "category":"Cafe",
            "type":"Food & Drink"
        }
    ],
    "sg:phone":"+44 1236 763469",
    "sg:postcode":"ML6 6DE",
    "sg:province":"North Lanarkshire",
    "sg:tags":[
        "tea",
        "room"
    ],
    "wof:name":"Cordina Ltd.",
    "wof:placetype":"venue"
},
  "geometry": {"coordinates":[-3.976556,55.866516],"type":"Point"}
}