{
  "type": "Feature",
  "properties": {
    "addr:full":"36a Woodborough Road Winscombe Somerset BS25 1AG",
    "addr:housenumber":"36a",
    "addr:postcode":"bs25 1ag",
    "addr:street":"Woodborough Road",
    "iso:country":"GB",
    "sg:address":"36a Woodborough Road",
    "sg:city":"Winscombe",
    "sg:classifiers":[
        {
            "category":"Home & Garden",
            "subcategory":"Kitchen Supply",
            "type":"Retail Goods"
        }
    ],
    "sg:phone":"+44 1934 843658",
    "sg:postcode":"BS25 1AG",
    "sg:province":"Somerset",
    "sg:tags":[
        "glassware",
        "china"
    ],
    "wof:name":"The Pippins",
    "wof:placetype":"venue"
},
  "geometry": {"coordinates":[-2.833379,51.314644],"type":"Point"}
}