{
  "type": "Feature",
  "properties": {
    "iso:country":"GB",
    "sg:address":"48 The Belfry, Station Road",
    "sg:city":"Redhill",
    "sg:classifiers":[
        {
            "category":"Home & Garden",
            "subcategory":"Household Appliances",
            "type":"Retail Goods"
        },
        {
            "category":"Home & Garden",
            "subcategory":"Kitchen Supply",
            "type":"Retail Goods"
        }
    ],
    "sg:postcode":"RH1 1SE",
    "sg:province":"Surrey",
    "sg:tags":[
        "ware",
        "kitchenware"
    ],
    "wof:name":"KITCHIN WINDOW",
    "wof:placetype":"venue"
},
  "geometry": {"coordinates":[-0.1688790023,51.2381782532],"type":"Point"}
}