{
  "type": "Feature",
  "properties": {
    "addr:full":"Courtyard Surgery, London Rd Horsham West Sussex RH12 1AT",
    "addr:postcode":"rh12 1at",
    "addr:street":"London Rd",
    "iso:country":"GB",
    "sg:address":"Courtyard Surgery, London Rd",
    "sg:city":"Horsham",
    "sg:classifiers":[
        {
            "category":"Health Services",
            "subcategory":"Doctor",
            "type":"Services"
        }
    ],
    "sg:phone":"+44 1403 253100",
    "sg:postcode":"RH12 1AT",
    "sg:province":"West Sussex",
    "sg:tags":[
        "practitioners"
    ],
    "wof:name":"Watson, R",
    "wof:placetype":"venue"
},
  "geometry": {"coordinates":[-0.3291069865,51.0651817322],"type":"Point"}
}