{
  "type": "Feature",
  "properties": {
    "addr:full":"15 Village Centre, Leverstock Green Road Hemel Hempstead Hertfordshire HP3 8QG",
    "addr:housenumber":"15",
    "addr:postcode":"hp3 8qg",
    "addr:street":"Village Centre Leverstock Green Road",
    "iso:country":"GB",
    "sg:address":"15 Village Centre, Leverstock Green Road",
    "sg:city":"Hemel Hempstead",
    "sg:classifiers":[
        {
            "category":"Personal",
            "subcategory":"Beauty Salon",
            "type":"Services"
        }
    ],
    "sg:phone":"+44 1442 213517",
    "sg:postcode":"HP3 8QG",
    "sg:province":"Hertfordshire",
    "sg:tags":[
        "unisex",
        "hairdresser"
    ],
    "wof:name":"Maureen Roberts",
    "wof:placetype":"venue"
},
  "geometry": {"coordinates":[-0.439969,51.751999],"type":"Point"}
}