{
  "type": "Feature",
  "properties": {
    "addr:full":"Trefaes Fach, Beulah Newcastle Emlyn Carmarthenshire SA38 9QT",
    "addr:postcode":"sa38 9qt",
    "addr:street":"Trefaes;Beulah",
    "iso:country":"GB",
    "sg:address":"Trefaes Fach, Beulah",
    "sg:city":"Newcastle Emlyn",
    "sg:classifiers":[
        {
            "category":"Farming",
            "subcategory":"Dairy Farm",
            "type":"Manufacturing & Wholesale Goods"
        }
    ],
    "sg:phone":"+44 1239 810758",
    "sg:postcode":"SA38 9QT",
    "sg:province":"Carmarthenshire",
    "wof:name":"M & C G & Son Stanfield",
    "wof:placetype":"venue"
},
  "geometry": {"coordinates":[-4.467984,52.035919],"type":"Point"}
}