{
  "type": "Feature",
  "properties": {
    "addr:full":"110-112 Finlay Road Gloucester Gloucestershire GL4 6TF",
    "addr:housenumber":"110-112",
    "addr:postcode":"gl4 6tf",
    "addr:street":"Finlay Road",
    "iso:country":"GB",
    "sg:address":"110-112 Finlay Road",
    "sg:city":"Gloucester",
    "sg:classifiers":[
        {
            "category":"Organizations",
            "subcategory":"Non-profit Organization",
            "type":"Services"
        }
    ],
    "sg:phone":"+44 1452 309440",
    "sg:postcode":"GL4 6TF",
    "sg:province":"Gloucestershire",
    "sg:tags":[
        "organisation",
        "voluntary",
        "charity"
    ],
    "wof:name":"White City Project",
    "wof:placetype":"venue"
},
  "geometry": {"coordinates":[-2.236897,51.843811],"type":"Point"}
}