{
  "type": "Feature",
  "properties": {
    "addr:full":"3-5 Victoria Rd Wallasey Merseyside L45 2JA",
    "addr:housenumber":"3-5",
    "addr:postcode":"l45 2ja",
    "addr:street":"Victoria Rd",
    "iso:country":"GB",
    "sg:address":"3-5 Victoria Rd",
    "sg:city":"Wallasey",
    "sg:classifiers":[
        {
            "category":"Bars & Pubs",
            "type":"Food & Drink"
        }
    ],
    "sg:phone":"+44 151 630 0103",
    "sg:postcode":"L45 2JA",
    "sg:province":"Merseyside",
    "sg:tags":[
        "pubs",
        "inn"
    ],
    "wof:name":"Old Mother Redcaps",
    "wof:placetype":"venue"
},
  "geometry": {"coordinates":[-3.040408,53.438641],"type":"Point"}
}