{
  "type": "Feature",
  "properties": {
    "iso:country":"GB",
    "sg:address":"25 Green Street",
    "sg:city":"Neath",
    "sg:classifiers":[
        {
            "category":"Shopping",
            "subcategory":"Clothing, Apparel, & Fashions",
            "type":"Retail Goods"
        }
    ],
    "sg:phone":"+44 1639 643335",
    "sg:postcode":"SA11 1DF",
    "sg:province":"Neath Port Talbot",
    "sg:tags":[
        "menswear"
    ],
    "wof:name":"Ciro Citterio",
    "wof:placetype":"venue"
},
  "geometry": {"coordinates":[-3.805493,51.662666],"type":"Point"}
}