{
  "type": "Feature",
  "properties": {
    "addr:full":"Walton Ct Community Centre,, Hannan Rd, Aylesbury Buckinghamshire HP21 8TJ",
    "addr:postcode":"hp21 8tj",
    "addr:street":"Walton Ct;Hannan Rd",
    "iso:country":"GB",
    "sg:address":"Walton Ct Community Centre,, Hannan Rd,",
    "sg:city":"Aylesbury",
    "sg:classifiers":[
        {
            "category":"Community Center",
            "type":"Public Place"
        }
    ],
    "sg:postcode":"HP21 8TJ",
    "sg:province":"Buckinghamshire",
    "sg:tags":[
        "centre"
    ],
    "wof:name":"Walton Court Social Club Ltd",
    "wof:placetype":"venue"
},
  "geometry": {"coordinates":[-0.80974,51.813881],"type":"Point"}
}