{
  "type": "Feature",
  "properties": {
    "addr:full":"41 Drymen Road, Bearsden Glasgow East Dunbartonshire G61 2RL",
    "addr:housenumber":"41",
    "addr:postcode":"g61 2rl",
    "addr:street":"Drymen Road",
    "iso:country":"GB",
    "sg:address":"41 Drymen Road, Bearsden",
    "sg:city":"Glasgow",
    "sg:classifiers":[
        {
            "category":"Social Services",
            "subcategory":"Retirement Home",
            "type":"Services"
        }
    ],
    "sg:phone":"+44 141 942 9636",
    "sg:postcode":"G61 2RL",
    "sg:province":"East Dunbartonshire",
    "sg:tags":[
        "rest"
    ],
    "wof:name":"Abbotsford House",
    "wof:placetype":"venue"
},
  "geometry": {"coordinates":[-4.326378,55.912434],"type":"Point"}
}