{
  "type": "Feature",
  "properties": {
    "addr:full":"17 North Street, Penydarren Merthyr Tydfil Merthyr Tydfil CF47 9HW",
    "addr:housenumber":"17",
    "addr:postcode":"cf47 9hw",
    "addr:street":"North Street;Tydfil",
    "iso:country":"GB",
    "sg:address":"17 North Street, Penydarren",
    "sg:city":"Merthyr Tydfil",
    "sg:classifiers":[
        {
            "category":"Taxi",
            "type":"Transportation"
        }
    ],
    "sg:phone":"+44 1685 374374",
    "sg:postcode":"CF47 9HW",
    "sg:province":"Merthyr Tydfil",
    "sg:tags":[
        "mini",
        "cab"
    ],
    "wof:name":"A B C Cars",
    "wof:placetype":"venue"
},
  "geometry": {"coordinates":[-3.3637800217,51.7583389282],"type":"Point"}
}