{
  "type": "Feature",
  "properties": {
    "iso:country":"GB",
    "sg:address":"31 Oakdene Parade",
    "sg:city":"Cobham",
    "sg:classifiers":[
        {
            "category":"Shopping",
            "subcategory":"Department Store",
            "type":"Retail Goods"
        },
        {
            "category":"Shopping",
            "subcategory":"Gifts & Souvenirs",
            "type":"Retail Goods"
        }
    ],
    "sg:phone":"+44 1932 868684",
    "sg:postcode":"KT11 2LR",
    "sg:province":"Surrey",
    "sg:tags":[
        "shop"
    ],
    "wof:name":"Harvey Weston (Gifts) Ltd.",
    "wof:placetype":"venue"
},
  "geometry": {"coordinates":[-0.411659,51.329521],"type":"Point"}
}