{
  "type": "Feature",
  "properties": {
    "addr:full":"Rear Of 104 Chamberlayne Rd Willesden Greater London NW10 3JN",
    "addr:postcode":"nw10 3jn",
    "addr:street":"Chamberlayne Rd",
    "iso:country":"GB",
    "sg:address":"Rear Of 104 Chamberlayne Rd",
    "sg:city":"Willesden",
    "sg:classifiers":[
        {
            "category":"Professional",
            "subcategory":"Art Services",
            "type":"Services"
        }
    ],
    "sg:phone":"+44 20 8960 7403",
    "sg:postcode":"NW10 3JN",
    "sg:province":"Greater London",
    "sg:tags":[
        "photographer"
    ],
    "wof:name":"The Rise Photographic Studio",
    "wof:placetype":"venue"
},
  "geometry": {"coordinates":[-0.2237389982,51.5389137268],"type":"Point"}
}