{
  "type": "Feature",
  "properties": {
    "iso:country":"GB",
    "sg:address":"96 Earlswood Road",
    "sg:city":"Redhill",
    "sg:classifiers":[
        {
            "category":"Restaurant",
            "type":"Food & Drink"
        }
    ],
    "sg:phone":"+44 1737 778121",
    "sg:postcode":"RH1 6HW",
    "sg:province":"Surrey",
    "sg:tags":[
        "indian"
    ],
    "wof:name":"Taste of India",
    "wof:placetype":"venue"
},
  "geometry": {"coordinates":[-0.171814,51.226128],"type":"Point"}
}