{
  "type": "Feature",
  "properties": {
    "addr:full":"62a Stoke Newington Church St Stoke Newington Greater London N16 0NB",
    "addr:housenumber":"62a",
    "addr:postcode":"n16 0nb",
    "addr:street":"Stoke Newington Church St",
    "iso:country":"GB",
    "sg:address":"62a Stoke Newington Church St",
    "sg:city":"Stoke Newington",
    "sg:classifiers":[
        {
            "category":"Shopping",
            "subcategory":"Crafts & Fabrics",
            "type":"Retail Goods"
        }
    ],
    "sg:phone":"+44 20 7249 2277",
    "sg:postcode":"N16 0NB",
    "sg:province":"Greater London",
    "sg:tags":[
        "knitwear",
        "yarn"
    ],
    "wof:name":"Masaha Fashion Wear",
    "wof:placetype":"venue"
},
  "geometry": {"coordinates":[-0.0764029995,51.5622329712],"type":"Point"}
}