{
  "type": "Feature",
  "properties": {
    "addr:full":"5 Blackhorse Lane Ipswich Suffolk IP1 2EF",
    "addr:housenumber":"5",
    "addr:postcode":"ip1 2ef",
    "addr:street":"Blackhorse Lane",
    "iso:country":"GB",
    "sg:address":"5 Blackhorse Lane",
    "sg:city":"Ipswich",
    "sg:classifiers":[
        {
            "category":"Real Estate",
            "subcategory":"Surveying",
            "type":"Services"
        }
    ],
    "sg:phone":"+44 1473 211651",
    "sg:postcode":"IP1 2EF",
    "sg:province":"Suffolk",
    "sg:tags":[
        "surveyor",
        "quantity"
    ],
    "wof:name":"Downey & Warren",
    "wof:placetype":"venue"
},
  "geometry": {"coordinates":[1.1497139931,52.0582504272],"type":"Point"}
}