{
  "type": "Feature",
  "properties": {
    "addr:full":"Growmore Project, Pilmer Road Crowborough East Sussex TN6 2UG",
    "addr:postcode":"tn6 2ug",
    "addr:street":"Pilmer Road",
    "iso:country":"GB",
    "sg:address":"Growmore Project, Pilmer Road",
    "sg:city":"Crowborough",
    "sg:classifiers":[
        {
            "category":"Organizations",
            "subcategory":"Non-profit Organization",
            "type":"Services"
        }
    ],
    "sg:phone":"+44 1892 667327",
    "sg:postcode":"TN6 2UG",
    "sg:province":"East Sussex",
    "sg:tags":[
        "organisation",
        "voluntary",
        "charity"
    ],
    "wof:name":"Mencap",
    "wof:placetype":"venue"
},
  "geometry": {"coordinates":[0.1718930006,51.0531959534],"type":"Point"}
}