{
  "type": "Feature",
  "properties": {
    "iso:country":"GB",
    "sg:address":"Riverside Depot, Neath Road",
    "sg:city":"Neath",
    "sg:classifiers":[
        {
            "category":"Autos & Motor Vehicles",
            "subcategory":"Automobile Sales",
            "type":"Retail Goods"
        }
    ],
    "sg:phone":"+44 1639 814899",
    "sg:postcode":"SA11 2NL",
    "sg:province":"Neath Port Talbot",
    "sg:tags":[
        "auction",
        "car"
    ],
    "wof:name":"Swansea Motor Vehicle Auction Ltd.",
    "wof:placetype":"venue"
},
  "geometry": {"coordinates":[-3.799813,51.662712],"type":"Point"}
}