{
  "type": "Feature",
  "properties": {
    "addr:full":"7 Signet Court, Swanns Road Cambridge Cambridgeshire CB5 8LA",
    "addr:housenumber":"7",
    "addr:postcode":"cb5 8la",
    "addr:street":"Signet Court Swanns Road",
    "iso:country":"GB",
    "sg:address":"7 Signet Court, Swanns Road",
    "sg:city":"Cambridge",
    "sg:classifiers":[
        {
            "category":"Autos & Motor Vehicles",
            "subcategory":"Automobile Sales",
            "type":"Retail Goods"
        }
    ],
    "sg:phone":"+44 1223 361433",
    "sg:postcode":"CB5 8LA",
    "sg:province":"Cambridgeshire",
    "sg:tags":[
        "car"
    ],
    "wof:name":"Whiteley & Creasy (Cambridge) Ltd.",
    "wof:placetype":"venue"
},
  "geometry": {"coordinates":[0.150676,52.214066],"type":"Point"}
}