{
  "type": "Feature",
  "properties": {
    "iso:country":"GB",
    "sg:address":"73 Kingsway",
    "sg:city":"London",
    "sg:classifiers":[
        {
            "category":"Professional",
            "subcategory":"Engineering",
            "type":"Services"
        }
    ],
    "sg:phone":"+44 20 7831 7483",
    "sg:postcode":"WC2B 6SR",
    "sg:province":"Greater London",
    "sg:tags":[
        "engineer",
        "structural"
    ],
    "wof:name":"Smartline",
    "wof:placetype":"venue"
},
  "geometry": {"coordinates":[-0.119472,51.515755],"type":"Point"}
}