{
  "type": "Feature",
  "properties": {
    "addr:full":"394 Perth Road Dundee Dundee City DD2 1JQ",
    "addr:housenumber":"394",
    "addr:postcode":"dd2 1jq",
    "addr:street":"Perth Road",
    "iso:country":"GB",
    "sg:address":"394 Perth Road",
    "sg:city":"Dundee",
    "sg:classifiers":[
        {
            "category":"Autos & Motor Vehicles",
            "subcategory":"Fuel & Gas Station",
            "type":"Retail Goods"
        }
    ],
    "sg:postcode":"DD2 1JQ",
    "sg:province":"Dundee City",
    "sg:tags":[
        "petrol",
        "filling"
    ],
    "wof:name":"Tayview Self Serve",
    "wof:placetype":"venue"
},
  "geometry": {"coordinates":[-2.999890089,56.4565391541],"type":"Point"}
}