{
  "type": "Feature",
  "properties": {
    "addr:full":"127 Reigate Road, Ewell Epsom Surrey KT17 3DE",
    "addr:housenumber":"127",
    "addr:postcode":"kt17 3de",
    "addr:street":"Reigate Road",
    "iso:country":"GB",
    "sg:address":"127 Reigate Road, Ewell",
    "sg:city":"Epsom",
    "sg:classifiers":[
        {
            "category":"Home & Garden",
            "subcategory":"Garden Supply",
            "type":"Retail Goods"
        }
    ],
    "sg:phone":"+44 20 8393 4265",
    "sg:postcode":"KT17 3DE",
    "sg:province":"Surrey",
    "sg:tags":[
        "nursery",
        "centre"
    ],
    "wof:name":"Beechcroft Nursery",
    "wof:placetype":"venue"
},
  "geometry": {"coordinates":[-0.2381280065,51.3324012756],"type":"Point"}
}