{
  "type": "Feature",
  "properties": {
    "iso:country":"GB",
    "sg:address":"High Street, Canewdon",
    "sg:city":"Rochford",
    "sg:classifiers":[
        {
            "category":"Shopping",
            "subcategory":"Department Store",
            "type":"Retail Goods"
        }
    ],
    "sg:phone":"+44 1702 258210",
    "sg:postcode":"SS4 3PU",
    "sg:province":"Essex",
    "wof:name":"J Moss & Son",
    "wof:placetype":"venue"
},
  "geometry": {"coordinates":[0.742484,51.617611],"type":"Point"}
}