{
  "type": "Feature",
  "properties": {
    "addr:full":"8 Priory Centre Worksop Nottinghamshire S80 1JR",
    "addr:housenumber":"8",
    "addr:postcode":"s80 1jr",
    "addr:street":"Priory Centre",
    "iso:country":"GB",
    "sg:address":"8 Priory Centre",
    "sg:city":"Worksop",
    "sg:classifiers":[
        {
            "category":"Shopping",
            "subcategory":"Shoes",
            "type":"Retail Goods"
        }
    ],
    "sg:phone":"+44 1909 473031",
    "sg:postcode":"S80 1JR",
    "sg:province":"Nottinghamshire",
    "sg:tags":[
        "shop"
    ],
    "wof:name":"Masons (Worksop) Ltd",
    "wof:placetype":"venue"
},
  "geometry": {"coordinates":[-1.126649,53.305229],"type":"Point"}
}