{
  "type": "Feature",
  "properties": {
    "addr:full":"20a Commercial Road Hereford Herefordshire HR1 2BD",
    "addr:housenumber":"20a",
    "addr:postcode":"hr1 2bd",
    "addr:street":"Commercial Road",
    "iso:country":"GB",
    "sg:address":"20a Commercial Road",
    "sg:city":"Hereford",
    "sg:classifiers":[
        {
            "category":"Fast Food",
            "type":"Food & Drink"
        }
    ],
    "sg:phone":"+44 1432 341086",
    "sg:postcode":"HR1 2BD",
    "sg:province":"Herefordshire",
    "sg:tags":[
        "away",
        "meal",
        "outlet",
        "take"
    ],
    "wof:name":"Jasmin House",
    "wof:placetype":"venue"
},
  "geometry": {"coordinates":[-2.711039,52.058414],"type":"Point"}
}