{
  "type": "Feature",
  "properties": {
    "iso:country":"GB",
    "sg:address":"8 Sandringham Road",
    "sg:city":"London",
    "sg:classifiers":[
        {
            "category":"Personal",
            "subcategory":"Barber",
            "type":"Services"
        }
    ],
    "sg:phone":"+44 20 7254 6353",
    "sg:postcode":"E8 2LP",
    "sg:province":"Greater London",
    "sg:tags":[
        "unisex",
        "men's",
        "hairdresser"
    ],
    "wof:name":"All Nations Hairdressing Salon",
    "wof:placetype":"venue"
},
  "geometry": {"coordinates":[-0.074923,51.549629],"type":"Point"}
}