{
  "type": "Feature",
  "properties": {
    "iso:country":"GB",
    "sg:address":"106 Bush Road, Cuxton",
    "sg:city":"Rochester",
    "sg:classifiers":[
        {
            "category":"Building & Trades",
            "subcategory":"Construction",
            "type":"Services"
        }
    ],
    "sg:phone":"+44 1634 711836",
    "sg:postcode":"ME2 1HA",
    "sg:province":"Kent",
    "sg:tags":[
        "roofing",
        "contracting"
    ],
    "wof:name":"Copelands Roofing",
    "wof:placetype":"venue"
},
  "geometry": {"coordinates":[0.450323,51.375519],"type":"Point"}
}