{
  "type": "Feature",
  "properties": {
    "addr:full":"Braxted Road, Little Braxted Witham Essex CM8 3ED",
    "addr:postcode":"cm8 3ed",
    "addr:street":"Braxted Road;Witham",
    "iso:country":"GB",
    "sg:address":"Braxted Road, Little Braxted",
    "sg:city":"Witham",
    "sg:classifiers":[
        {
            "category":"Social Services",
            "subcategory":"Retirement Home",
            "type":"Services"
        }
    ],
    "sg:phone":"+44 1621 891974",
    "sg:postcode":"CM8 3ED",
    "sg:province":"Essex",
    "sg:tags":[
        "rest"
    ],
    "wof:name":"Little Oaks Residential Home",
    "wof:placetype":"venue"
},
  "geometry": {"coordinates":[0.7044659853,51.7998199463],"type":"Point"}
}