{
  "type": "Feature",
  "properties": {
    "iso:country":"GB",
    "sg:address":"86 Jetson Street",
    "sg:city":"Manchester",
    "sg:classifiers":[
        {
            "category":"Shopping",
            "subcategory":"News",
            "type":"Retail Goods"
        }
    ],
    "sg:phone":"+44 161 301 2536",
    "sg:postcode":"M18 8SZ",
    "sg:province":"Greater Manchester",
    "sg:tags":[
        "newsagent"
    ],
    "wof:name":"Raja Bros",
    "wof:placetype":"venue"
},
  "geometry": {"coordinates":[-2.156129,53.468666],"type":"Point"}
}