{
  "type": "Feature",
  "properties": {
    "iso:country":"GB",
    "sg:address":"Tower Drive, Neath Hill",
    "sg:city":"Milton Keynes",
    "sg:classifiers":[
        {
            "category":"Social Services",
            "subcategory":"Adult Care",
            "type":"Services"
        }
    ],
    "sg:phone":"+44 1908 604290",
    "sg:postcode":"MK14 6HY",
    "sg:province":"Buckinghamshire",
    "sg:tags":[
        "day",
        "centre"
    ],
    "wof:name":"Tower Drive Centre",
    "wof:placetype":"venue"
},
  "geometry": {"coordinates":[-0.749156,52.063095],"type":"Point"}
}