{
  "type": "Feature",
  "properties": {
    "addr:full":"101 Meadow Lane Coalville Leicestershire LE67 4DQ",
    "addr:housenumber":"101",
    "addr:postcode":"le67 4dq",
    "addr:street":"Meadow Lane",
    "iso:country":"GB",
    "sg:address":"101 Meadow Lane",
    "sg:city":"Coalville",
    "sg:classifiers":[
        {
            "category":"Personal",
            "subcategory":"Beauty Salon",
            "type":"Services"
        }
    ],
    "sg:phone":"+44 1530 836031",
    "sg:postcode":"LE67 4DQ",
    "sg:province":"Leicestershire",
    "sg:tags":[
        "unisex",
        "hairdresser"
    ],
    "wof:name":"Capers 1 Hair Design & Barbers Shop",
    "wof:placetype":"venue"
},
  "geometry": {"coordinates":[-1.335079,52.729149],"type":"Point"}
}