{
  "type": "Feature",
  "properties": {
    "addr:full":"50 Highfield Lane Chesterfield Derbyshire S41 8AY",
    "addr:housenumber":"50",
    "addr:postcode":"s41 8ay",
    "addr:street":"Highfield Lane",
    "iso:country":"GB",
    "sg:address":"50 Highfield Lane",
    "sg:city":"Chesterfield",
    "sg:classifiers":[
        {
            "category":"Health Services",
            "subcategory":"Dentist",
            "type":"Services"
        }
    ],
    "sg:phone":"+44 1246 277339",
    "sg:postcode":"S41 8AY",
    "sg:province":"Derbyshire",
    "wof:name":"A A Surgeon-Frame",
    "wof:placetype":"venue"
},
  "geometry": {"coordinates":[-1.442797,53.250774],"type":"Point"}
}