{
  "type": "Feature",
  "properties": {
    "addr:full":"244 Andrew Street Stockport Cheshire SK6 5HW",
    "addr:housenumber":"244",
    "addr:postcode":"sk6 5hw",
    "addr:street":"Andrew Street",
    "iso:country":"GB",
    "sg:address":"244 Andrew Street",
    "sg:city":"Stockport",
    "sg:classifiers":[
        {
            "category":"Home & Garden",
            "subcategory":"Hardware",
            "type":"Retail Goods"
        }
    ],
    "sg:postcode":"SK6 5HW",
    "sg:province":"Cheshire",
    "sg:tags":[
        "retailer",
        "diy"
    ],
    "wof:name":"H & K Whitehead",
    "wof:placetype":"venue"
},
  "geometry": {"coordinates":[-2.0543889999,53.4141807556],"type":"Point"}
}