{
  "type": "Feature",
  "properties": {
    "iso:country":"GB",
    "sg:address":"Brook House, Garstang Road, Brock",
    "sg:city":"Preston",
    "sg:classifiers":[
        {
            "category":"Farming",
            "subcategory":"Livestock Farm",
            "type":"Manufacturing & Wholesale Goods"
        },
        {
            "category":"Shopping",
            "type":"Retail Goods"
        }
    ],
    "sg:phone":"+44 1995 640212",
    "sg:postcode":"PR3 0RD",
    "sg:province":"Lancashire",
    "sg:tags":[
        "merchant",
        "others"
    ],
    "wof:name":"W C Thornton & Son Ltd.",
    "wof:placetype":"venue"
},
  "geometry": {"coordinates":[-2.744929,53.854641],"type":"Point"}
}