{
  "type": "Feature",
  "properties": {
    "iso:country":"GB",
    "sg:address":"104 Westbourne Road, Marsh",
    "sg:city":"Huddersfield",
    "sg:classifiers":[
        {
            "category":"Government",
            "subcategory":"Post Office",
            "type":"Public Place"
        }
    ],
    "sg:postcode":"HD1 4LF",
    "sg:province":"West Yorkshire",
    "wof:name":"Marsh Post Office",
    "wof:placetype":"venue"
},
  "geometry": {"coordinates":[-1.806764,53.65155],"type":"Point"}
}