{
  "type": "Feature",
  "properties": {
    "addr:full":"104 Westbourne Road, Marsh Huddersfield West Yorkshire HD1 4LF",
    "addr:housenumber":"104",
    "addr:postcode":"hd1 4lf",
    "addr:street":"Westbourne Road;West",
    "iso:country":"GB",
    "sg:address":"104 Westbourne Road, Marsh",
    "sg:city":"Huddersfield",
    "sg:classifiers":[
        {
            "category":"Government",
            "subcategory":"Post Office",
            "type":"Public Place"
        }
    ],
    "sg:postcode":"HD1 4LF",
    "sg:province":"West Yorkshire",
    "wof:name":"Marsh Post Office",
    "wof:placetype":"venue"
},
  "geometry": {"coordinates":[-1.806764,53.65155],"type":"Point"}
}