{
  "type": "Feature",
  "properties": {
    "iso:country":"GB",
    "sg:address":"37 Sheepridge Rd",
    "sg:city":"Huddersfield",
    "sg:classifiers":[
        {
            "category":"Bars & Pubs",
            "type":"Food & Drink"
        }
    ],
    "sg:phone":"+44 1484 300180",
    "sg:postcode":"HD2 1HA",
    "sg:province":"West Yorkshire",
    "sg:tags":[
        "pubs",
        "inn"
    ],
    "wof:name":"The Fleece Inn",
    "wof:placetype":"venue"
},
  "geometry": {"coordinates":[-1.768638,53.668739],"type":"Point"}
}