{
  "type": "Feature",
  "properties": {
    "iso:country":"GB",
    "sg:address":"192 London Road",
    "sg:city":"Leicester",
    "sg:classifiers":[
        {
            "category":"Retail",
            "subcategory":"Veterinary Services",
            "type":"Services"
        }
    ],
    "sg:phone":"+44 116 254 3255",
    "sg:postcode":"LE2 1ND",
    "sg:province":"Leicestershire",
    "sg:tags":[
        "surgeon",
        "activity"
    ],
    "wof:name":"BROWN BELL & BENTLEY",
    "wof:placetype":"venue"
},
  "geometry": {"coordinates":[-1.115713954,52.6245956421],"type":"Point"}
}