{
  "type": "Feature",
  "properties": {
    "iso:country":"GB",
    "sg:address":"2 Coney Hall Parade, Kingsway",
    "sg:city":"West Wickham",
    "sg:classifiers":[
        {
            "category":"Professional",
            "subcategory":"Printing & Photocopies",
            "type":"Services"
        }
    ],
    "sg:phone":"+44 20 8462 6697",
    "sg:postcode":"BR4 9JB",
    "sg:province":"Kent",
    "sg:tags":[
        "printer"
    ],
    "wof:name":"Coney Services Ltd.",
    "wof:placetype":"venue"
},
  "geometry": {"coordinates":[0.0019950001,51.3739852905],"type":"Point"}
}