{
  "type": "Feature",
  "properties": {
    "addr:full":"4 Powells Place Porth Bridgend CF39 9RW",
    "addr:housenumber":"4",
    "addr:postcode":"cf39 9rw",
    "addr:street":"Powells Place Porth",
    "iso:country":"GB",
    "sg:address":"4 Powells Place",
    "sg:city":"Porth",
    "sg:classifiers":[
        {
            "category":"Health Services",
            "subcategory":"Health Practitioner",
            "type":"Services"
        }
    ],
    "sg:phone":"+44 1443 687848",
    "sg:postcode":"CF39 9RW",
    "sg:province":"Bridgend",
    "sg:tags":[
        "herbalist"
    ],
    "wof:name":"A P Morris",
    "wof:placetype":"venue"
},
  "geometry": {"coordinates":[-3.4088289738,51.6128845215],"type":"Point"}
}