{
  "type": "Feature",
  "properties": {
    "addr:full":"33b Windsor Road Blackburn Lancashire BB1 2DQ",
    "addr:housenumber":"33b",
    "addr:postcode":"bb1 2dq",
    "addr:street":"Windsor Road",
    "iso:country":"GB",
    "sg:address":"33b Windsor Road",
    "sg:city":"Blackburn",
    "sg:classifiers":[
        {
            "category":"Professional",
            "subcategory":"Computer Services",
            "type":"Services"
        }
    ],
    "sg:postcode":"BB1 2DQ",
    "sg:province":"Lancashire",
    "sg:tags":[
        "consultant"
    ],
    "wof:name":"Cyber Galaxy",
    "wof:placetype":"venue"
},
  "geometry": {"coordinates":[-2.4358808994,53.7465209961],"type":"Point"}
}