{
  "type": "Feature",
  "properties": {
    "iso:country":"GB",
    "sg:address":"16 Lake St",
    "sg:city":"Leighton Buzzard",
    "sg:classifiers":[
        {
            "category":"Health Services",
            "subcategory":"Dentist",
            "type":"Services"
        }
    ],
    "sg:phone":"+44 1525 850025",
    "sg:postcode":"LU7 8RT",
    "sg:province":"Bedfordshire",
    "sg:tags":[
        "technician",
        "dental"
    ],
    "wof:name":"Denches Ltd",
    "wof:placetype":"venue"
},
  "geometry": {"coordinates":[-0.659837,51.915733],"type":"Point"}
}