{
  "type": "Feature",
  "properties": {
    "iso:country":"GB",
    "sg:address":"121 Cherry Orchard Road",
    "sg:city":"Croydon",
    "sg:classifiers":[
        {
            "category":"Travel",
            "subcategory":"Hotels & Motels",
            "type":"Entertainment"
        }
    ],
    "sg:phone":"+44 20 8686 8068",
    "sg:postcode":"CR0 6BE",
    "sg:province":"Surrey",
    "wof:name":"Chromeace 2 Ltd.",
    "wof:placetype":"venue"
},
  "geometry": {"coordinates":[-0.089177,51.379105],"type":"Point"}
}