{
  "type": "Feature",
  "properties": {
    "addr:full":"Unit 1a Kingdon Enterprise Park, Clovelly Rd Indust Est Bideford Devon EX39 3HN",
    "addr:housenumber":"unit 1a kingdon",
    "addr:postcode":"ex39 3hn",
    "addr:street":"Enterprise Park Clovelly Rd",
    "iso:country":"GB",
    "sg:address":"Unit 1a Kingdon Enterprise Park, Clovelly Rd Indust Est",
    "sg:city":"Bideford",
    "sg:classifiers":[
        {
            "category":"Autos & Motor Vehicles",
            "subcategory":"Auto Supplies",
            "type":"Retail Goods"
        }
    ],
    "sg:phone":"+44 1237 422294",
    "sg:postcode":"EX39 3HN",
    "sg:province":"Devon",
    "sg:tags":[
        "part",
        "motorcycle",
        "accessory"
    ],
    "wof:name":"Spartan Engineering",
    "wof:placetype":"venue"
},
  "geometry": {"coordinates":[-4.204259,51.019249],"type":"Point"}
}