{
  "type": "Feature",
  "properties": {
    "addr:full":"4 Barnsdale Dr Milton Keynes Buckinghamshire MK4 4DD",
    "addr:housenumber":"4",
    "addr:postcode":"mk4 4dd",
    "addr:street":"Barnsdale Dr",
    "iso:country":"GB",
    "sg:address":"4 Barnsdale Dr",
    "sg:city":"Milton Keynes",
    "sg:classifiers":[
        {
            "category":"Farming",
            "subcategory":"Nursery",
            "type":"Manufacturing & Wholesale Goods"
        }
    ],
    "sg:phone":"+44 1908 505100",
    "sg:postcode":"MK4 4DD",
    "sg:province":"Buckinghamshire",
    "sg:tags":[
        "creche"
    ],
    "wof:name":"Safeway Creche",
    "wof:placetype":"venue"
},
  "geometry": {"coordinates":[-0.7926700115,52.0063285828],"type":"Point"}
}