{
  "type": "Feature",
  "properties": {
    "iso:country":"GB",
    "sg:address":"30 Duke Street",
    "sg:city":"Coldstream",
    "sg:classifiers":[
        {
            "category":"Retail",
            "subcategory":"Driving School",
            "type":"Services"
        }
    ],
    "sg:phone":"+44 1890 883671",
    "sg:postcode":"TD12 4BS",
    "sg:province":"Northumberland",
    "wof:name":"Sally Moffat Driving Instruction",
    "wof:placetype":"venue"
},
  "geometry": {"coordinates":[-2.255022,55.649689],"type":"Point"}
}