{
  "type": "Feature",
  "properties": {
    "iso:country":"GB",
    "sg:address":"41-43 Lower Kings Road",
    "sg:city":"Berkhamsted",
    "sg:classifiers":[
        {
            "category":"Arts & Performance",
            "subcategory":"Art Gallery",
            "type":"Entertainment"
        }
    ],
    "sg:phone":"+44 1442 878300",
    "sg:postcode":"HP4 2AB",
    "sg:province":"Bedfordshire",
    "wof:name":"Berkeley Gallery",
    "wof:placetype":"venue"
},
  "geometry": {"coordinates":[-0.5645970106,51.761806488],"type":"Point"}
}