{
  "type": "Feature",
  "properties": {
    "iso:country":"GB",
    "sg:address":"Wilscombe, Hoares Lane, Kilmersdon",
    "sg:city":"Bath",
    "sg:classifiers":[
        {
            "category":"Professional",
            "subcategory":"Management & Consulting",
            "type":"Services"
        }
    ],
    "sg:phone":"+44 1761 432332",
    "sg:postcode":"BA3 5ST",
    "sg:province":"Somerset",
    "sg:tags":[
        "consultant",
        "safety"
    ],
    "wof:name":"Ken Hutton Associates",
    "wof:placetype":"venue"
},
  "geometry": {"coordinates":[-2.437458,51.269661],"type":"Point"}
}