{
  "type": "Feature",
  "properties": {
    "addr:full":"29 Racecourse Rd Richmond North Yorkshire DL10 4SU",
    "addr:housenumber":"29",
    "addr:postcode":"dl10 4su",
    "addr:street":"Racecourse Rd",
    "iso:country":"GB",
    "sg:address":"29 Racecourse Rd",
    "sg:city":"Richmond",
    "sg:classifiers":[
        {
            "category":"Retail",
            "subcategory":"Auto Repair",
            "type":"Services"
        }
    ],
    "sg:postcode":"DL10 4SU",
    "sg:province":"North Yorkshire",
    "sg:tags":[
        "modification",
        "garage"
    ],
    "wof:name":"B P Vehicle Service & Repair",
    "wof:placetype":"venue"
},
  "geometry": {"coordinates":[-1.7447689772,54.4118614197],"type":"Point"}
}