{
  "type": "Feature",
  "properties": {
    "addr:full":"Woodside, Yester Park Chislehurst Kent BR7 5DQ",
    "addr:postcode":"br7 5dq",
    "addr:street":"Chislehurst",
    "iso:country":"GB",
    "sg:address":"Woodside, Yester Park",
    "sg:city":"Chislehurst",
    "sg:classifiers":[
        {
            "category":"Building & Trades",
            "subcategory":"Construction",
            "type":"Services"
        }
    ],
    "sg:phone":"+44 20 8467 2347",
    "sg:postcode":"BR7 5DQ",
    "sg:province":"Kent",
    "sg:tags":[
        "tiling",
        "contractor"
    ],
    "wof:name":"James Cyril Sydney Andrews",
    "wof:placetype":"venue"
},
  "geometry": {"coordinates":[0.0663900003,51.4192848206],"type":"Point"}
}