{
  "type": "Feature",
  "properties": {
    "addr:full":"38a Cross Bank Road, Ernston Manchester Cheshire M41 0TQ",
    "addr:housenumber":"38a",
    "addr:postcode":"m41 0tq",
    "addr:street":"Cross Bank Road",
    "iso:country":"GB",
    "sg:address":"38a Cross Bank Road, Ernston",
    "sg:city":"Manchester",
    "sg:classifiers":[
        {
            "category":"Organizations",
            "subcategory":"Political Organization",
            "type":"Services"
        }
    ],
    "sg:phone":"+44 161 746 8886",
    "sg:postcode":"M41 0TQ",
    "sg:province":"Cheshire",
    "sg:tags":[
        "mediation"
    ],
    "wof:name":"Pathway Mediation Services Ltd.",
    "wof:placetype":"venue"
},
  "geometry": {"coordinates":[-2.353174,53.44986],"type":"Point"}
}