{
  "type": "Feature",
  "properties": {
    "addr:full":"London Road Hook Berkshire RG27 9DZ",
    "addr:postcode":"rg27 9dz",
    "addr:street":"London Road",
    "iso:country":"GB",
    "sg:address":"London Road",
    "sg:city":"Hook",
    "sg:classifiers":[
        {
            "category":"Place Of Worship",
            "type":"Public Place"
        },
        {
            "category":"Organizations",
            "subcategory":"Non-profit Organization",
            "type":"Services"
        }
    ],
    "sg:phone":"+44 1256 760169",
    "sg:postcode":"RG27 9DZ",
    "sg:province":"Berkshire",
    "sg:tags":[
        "charitable",
        "organisation",
        "charity"
    ],
    "wof:name":"ST JOHN THE EVANGELIST CHURCH",
    "wof:placetype":"venue"
},
  "geometry": {"coordinates":[-0.9675289989,51.2805862427],"type":"Point"}
}