{
  "type": "Feature",
  "properties": {
    "iso:country":"GB",
    "sg:address":"11a North Street, Portslade",
    "sg:city":"Brighton",
    "sg:classifiers":[
        {
            "category":"Professional",
            "subcategory":"Computer Services",
            "type":"Services"
        }
    ],
    "sg:postcode":"BN41 1DH",
    "sg:province":"East Sussex",
    "sg:tags":[
        "consultant"
    ],
    "wof:name":"Betlink Ltd",
    "wof:placetype":"venue"
},
  "geometry": {"coordinates":[-0.209122,50.830452],"type":"Point"}
}