{
  "type": "Feature",
  "properties": {
    "iso:country":"GB",
    "sg:address":"282 Shuttlewood Road, Bolsover",
    "sg:city":"Chesterfield",
    "sg:classifiers":[
        {
            "category":"Farming",
            "subcategory":"Livestock Farm",
            "type":"Manufacturing & Wholesale Goods"
        }
    ],
    "sg:phone":"+44 1246 825327",
    "sg:postcode":"S44 6PB",
    "sg:province":"Derbyshire",
    "sg:tags":[
        "others"
    ],
    "wof:name":"Richard Kirk",
    "wof:placetype":"venue"
},
  "geometry": {"coordinates":[-1.293139,53.238861],"type":"Point"}
}