{
  "type": "Feature",
  "properties": {
    "addr:full":"10 Marina Way, Cippenham Slough Berkshire SL1 5NS",
    "addr:housenumber":"10",
    "addr:postcode":"sl1 5ns",
    "addr:street":"Marina Way",
    "iso:country":"GB",
    "sg:address":"10 Marina Way, Cippenham",
    "sg:city":"Slough",
    "sg:classifiers":[
        {
            "category":"Manufacturing",
            "subcategory":"Rubber & Plastics",
            "type":"Manufacturing & Wholesale Goods"
        }
    ],
    "sg:phone":"+44 1628 662318",
    "sg:postcode":"SL1 5NS",
    "sg:province":"Berkshire",
    "sg:tags":[
        "product"
    ],
    "wof:name":"Dam'nplast Ltd.",
    "wof:placetype":"venue"
},
  "geometry": {"coordinates":[-0.6508650184,51.5180511475],"type":"Point"}
}