{
  "type": "Feature",
  "properties": {
    "addr:full":"The Cross, Parliament St Stroud Gloucestershire GL5 1QQ",
    "addr:postcode":"gl5 1qq",
    "addr:street":"Cross Parliament St",
    "iso:country":"GB",
    "sg:address":"The Cross, Parliament St",
    "sg:city":"Stroud",
    "sg:classifiers":[
        {
            "category":"Government",
            "subcategory":"Police Station",
            "type":"Public Place"
        }
    ],
    "sg:phone":"+44 1453 766311",
    "sg:postcode":"GL5 1QQ",
    "sg:province":"Gloucestershire",
    "sg:tags":[
        "support"
    ],
    "wof:name":"Stroud Divisional Police Headquarters",
    "wof:placetype":"venue"
},
  "geometry": {"coordinates":[-2.2115290165,51.7453231812],"type":"Point"}
}