{
  "type": "Feature",
  "properties": {
    "iso:country":"GB",
    "sg:address":"U S Air Base, Raf Lakeheath",
    "sg:city":"Brandon",
    "sg:classifiers":[
        {
            "category":"Shopping",
            "subcategory":"Optician",
            "type":"Retail Goods"
        },
        {
            "category":"Professional",
            "subcategory":"Business Services",
            "type":"Services"
        }
    ],
    "sg:phone":"+44 1638 533622",
    "sg:postcode":"IP27 9PN",
    "sg:province":"Norfolk",
    "sg:tags":[
        "import",
        "export",
        "agent"
    ],
    "wof:name":"Army & Airforce Exchange Service",
    "wof:placetype":"venue"
},
  "geometry": {"coordinates":[0.626205,52.442741],"type":"Point"}
}