{
  "type": "Feature",
  "properties": {
    "addr:full":"Wakefield Road, Hampole Doncaster North Yorkshire DN6 7EZ",
    "addr:postcode":"dn6 7ez",
    "addr:street":"Wakefield Road",
    "iso:country":"GB",
    "sg:address":"Wakefield Road, Hampole",
    "sg:city":"Doncaster",
    "sg:classifiers":[
        {
            "category":"Farming",
            "subcategory":"Livestock Farm",
            "type":"Manufacturing & Wholesale Goods"
        }
    ],
    "sg:phone":"+44 1302 724659",
    "sg:postcode":"DN6 7EZ",
    "sg:province":"North Yorkshire",
    "sg:tags":[
        "others"
    ],
    "wof:name":"J E Sour & Sons",
    "wof:placetype":"venue"
},
  "geometry": {"coordinates":[-1.2264419794,53.589515686],"type":"Point"}
}