{
  "type": "Feature",
  "properties": {
    "addr:full":"69 Aspenlea Road London Greater London W6 8LH",
    "addr:housenumber":"69",
    "addr:postcode":"w6 8lh",
    "addr:street":"Aspenlea Road",
    "iso:country":"GB",
    "sg:address":"69 Aspenlea Road",
    "sg:city":"London",
    "sg:classifiers":[
        {
            "category":"Building & Trades",
            "subcategory":"Construction",
            "type":"Services"
        }
    ],
    "sg:phone":"+44 20 7385 8088",
    "sg:postcode":"W6 8LH",
    "sg:province":"Greater London",
    "sg:tags":[
        "builder"
    ],
    "wof:name":"Legge & Windsor",
    "wof:placetype":"venue"
},
  "geometry": {"coordinates":[-0.2182749957,51.4857673645],"type":"Point"}
}