{
  "type": "Feature",
  "properties": {
    "iso:country":"GB",
    "sg:address":"Second Avenue",
    "sg:city":"London",
    "sg:classifiers":[
        {
            "category":"Retail",
            "subcategory":"Auto Repair",
            "type":"Services"
        }
    ],
    "sg:phone":"+44 20 8345 5148",
    "sg:postcode":"N18 2PG",
    "sg:province":"Greater London",
    "sg:tags":[
        "modification",
        "garage"
    ],
    "wof:name":"Lea Valley Motors",
    "wof:placetype":"venue"
},
  "geometry": {"coordinates":[-0.050269,51.618774],"type":"Point"}
}