{
  "type": "Feature",
  "properties": {
    "iso:country":"GB",
    "sg:address":"2 York Street",
    "sg:city":"Clitheroe",
    "sg:classifiers":[
        {
            "category":"Personal",
            "subcategory":"Beauty Salon",
            "type":"Services"
        }
    ],
    "sg:phone":"+44 1200 428669",
    "sg:postcode":"BB7 2DL",
    "sg:province":"Lancashire",
    "wof:name":"la Femme",
    "wof:placetype":"venue"
},
  "geometry": {"coordinates":[-2.388812,53.873688],"type":"Point"}
}