{
  "type": "Feature",
  "properties": {
    "iso:country":"GB",
    "sg:address":"Magna Street",
    "sg:city":"Motherwell",
    "sg:classifiers":[
        {
            "category":"Education",
            "subcategory":"School",
            "type":"Public Place"
        },
        {
            "category":"Government",
            "subcategory":"Office",
            "type":"Public Place"
        }
    ],
    "sg:phone":"+44 1698 264843",
    "sg:postcode":"ML1 4QZ",
    "sg:province":"North Lanarkshire",
    "sg:tags":[
        "local",
        "authority"
    ],
    "wof:name":"Clydeview School",
    "wof:placetype":"venue"
},
  "geometry": {"coordinates":[-4.013199,55.7976],"type":"Point"}
}