{
  "type": "Feature",
  "properties": {
    "addr:full":"Bay House, Baytree Road Weston-super-mare Somerset BS22 8HG",
    "addr:postcode":"bs22 8hg",
    "addr:street":"Baytree Road",
    "iso:country":"GB",
    "sg:address":"Bay House, Baytree Road",
    "sg:city":"Weston-super-mare",
    "sg:classifiers":[
        {
            "category":"Organizations",
            "subcategory":"Non-profit Organization",
            "type":"Services"
        }
    ],
    "sg:phone":"+44 1934 628789",
    "sg:postcode":"BS22 8HG",
    "sg:province":"Somerset",
    "sg:tags":[
        "organisation",
        "voluntary",
        "charity"
    ],
    "wof:name":"Weston & District Society for the Spastic & Mentally Handicapped",
    "wof:placetype":"venue"
},
  "geometry": {"coordinates":[-2.9459290504,51.3575325012],"type":"Point"}
}