{
  "type": "Feature",
  "properties": {
    "addr:full":"The Hawthorns, Tellisford Lane Bath Somerset BA2 7LL",
    "addr:postcode":"ba2 7ll",
    "addr:street":"Tellisford Lane",
    "iso:country":"GB",
    "sg:address":"The Hawthorns, Tellisford Lane",
    "sg:city":"Bath",
    "sg:classifiers":[
        {
            "category":"Professional",
            "subcategory":"Computer Services",
            "type":"Services"
        }
    ],
    "sg:postcode":"BA2 7LL",
    "sg:province":"Somerset",
    "sg:tags":[
        "consultant"
    ],
    "wof:name":"D.J. Associates Ltd",
    "wof:placetype":"venue"
},
  "geometry": {"coordinates":[-2.3290290833,51.3024635315],"type":"Point"}
}