{
  "type": "Feature",
  "properties": {
    "addr:full":"Manor Lodge Aylesbury Buckinghamshire HP17 8SH",
    "addr:postcode":"hp17 8sh",
    "addr:street":"Aylesbury",
    "iso:country":"GB",
    "sg:address":"Manor Lodge",
    "sg:city":"Aylesbury",
    "sg:classifiers":[
        {
            "category":"Professional",
            "subcategory":"Management & Consulting",
            "type":"Services"
        }
    ],
    "sg:postcode":"HP17 8SH",
    "sg:province":"Buckinghamshire",
    "sg:tags":[
        "consultant",
        "business"
    ],
    "wof:name":"P B Communication Services",
    "wof:placetype":"venue"
},
  "geometry": {"coordinates":[-0.8970590234,51.7874717712],"type":"Point"}
}