{
  "type": "Feature",
  "properties": {
    "iso:country":"GB",
    "sg:address":"426-428 Bethnal Green Road, Bethnal Green",
    "sg:city":"London",
    "sg:classifiers":[
        {
            "category":"Shopping",
            "subcategory":"Pharmacy",
            "type":"Retail Goods"
        }
    ],
    "sg:phone":"+44 20 7729 5342",
    "sg:postcode":"E2 0DJ",
    "sg:province":"Greater London",
    "sg:tags":[
        "pharmacist",
        "dispensing",
        "chemist"
    ],
    "wof:name":"Boots The Chemists",
    "wof:placetype":"venue"
},
  "geometry": {"coordinates":[-0.0596950017,51.5269508362],"type":"Point"}
}