{
  "type": "Feature",
  "properties": {
    "addr:full":"3 Victoria Road, Netherfield Nottingham Nottinghamshire NG4 2LA",
    "addr:housenumber":"3",
    "addr:postcode":"ng4 2la",
    "addr:street":"Victoria Road",
    "iso:country":"GB",
    "sg:address":"3 Victoria Road, Netherfield",
    "sg:city":"Nottingham",
    "sg:classifiers":[
        {
            "category":"Banks & Credit Unions",
            "subcategory":"Financial Services",
            "type":"Services"
        },
        {
            "category":"Real Estate",
            "subcategory":"Real Estate Agent",
            "type":"Services"
        }
    ],
    "sg:phone":"+44 115 961 5111",
    "sg:postcode":"NG4 2LA",
    "sg:province":"Nottinghamshire",
    "sg:tags":[
        "adviser"
    ],
    "wof:name":"Bowbanks and Field",
    "wof:placetype":"venue"
},
  "geometry": {"coordinates":[-1.0785030127,52.9647216797],"type":"Point"}
}