{
  "type": "Feature",
  "properties": {
    "addr:full":"30a Wings Road Farnham Surrey GU9 0HW",
    "addr:postcode":"gu9 0hw",
    "addr:street":"Wings Road",
    "iso:country":"GB",
    "sg:address":"30a Wings Road",
    "sg:city":"Farnham",
    "sg:classifiers":[
        {
            "category":"Utilities",
            "type":"Services"
        }
    ],
    "sg:phone":"+44 1252 820863",
    "sg:postcode":"GU9 0HW",
    "sg:province":"Surrey",
    "sg:tags":[
        "internet"
    ],
    "wof:name":"Choicedomains.co.uk",
    "wof:placetype":"venue"
},
  "geometry": {"coordinates":[-0.801297,51.232704],"type":"Point"}
}