{
  "type": "Feature",
  "properties": {
    "addr:full":"50-52 Bargates Christchurch Dorset BH23 1QL",
    "addr:housenumber":"50-52",
    "addr:postcode":"bh23 1ql",
    "addr:street":"Bargates",
    "iso:country":"GB",
    "sg:address":"50-52 Bargates",
    "sg:city":"Christchurch",
    "sg:classifiers":[
        {
            "category":"Banks & Credit Unions",
            "subcategory":"Financial Services",
            "type":"Services"
        }
    ],
    "sg:phone":"+44 1202 499455",
    "sg:postcode":"BH23 1QL",
    "sg:province":"Dorset",
    "sg:tags":[
        "adviser"
    ],
    "wof:name":"Priory Financial Management Group",
    "wof:placetype":"venue"
},
  "geometry": {"coordinates":[-1.780914,50.737286],"type":"Point"}
}