{
  "type": "Feature",
  "properties": {
    "iso:country":"GB",
    "sg:address":"12 Park Street",
    "sg:city":"Worksop",
    "sg:classifiers":[
        {
            "category":"Arts & Performance",
            "subcategory":"Art Gallery",
            "type":"Entertainment"
        }
    ],
    "sg:phone":"+44 1909 489400",
    "sg:postcode":"S80 1HB",
    "sg:province":"Nottinghamshire",
    "wof:name":"Classic Framers & Gallery",
    "wof:placetype":"venue"
},
  "geometry": {"coordinates":[-1.124219,53.300873],"type":"Point"}
}