{
  "type": "Feature",
  "properties": {
    "addr:full":"Bunns La Mill Hill Greater London NW7 2DQ",
    "addr:postcode":"nw7 2dq",
    "addr:street":"La Mill Hill",
    "iso:country":"GB",
    "sg:address":"Bunns La",
    "sg:city":"Mill Hill",
    "sg:classifiers":[
        {
            "category":"Professional",
            "subcategory":"Management & Consulting",
            "type":"Services"
        }
    ],
    "sg:phone":"+44 20 8906 9888",
    "sg:postcode":"NW7 2DQ",
    "sg:province":"Greater London",
    "sg:tags":[
        "consultant",
        "business"
    ],
    "wof:name":"Creative Learning Consultants",
    "wof:placetype":"venue"
},
  "geometry": {"coordinates":[-0.2481070012,51.6107215881],"type":"Point"}
}