{
  "type": "Feature",
  "properties": {
    "addr:full":"4 Sopwith Way Daventry Northamptonshire NN11 5PB",
    "addr:housenumber":"4",
    "addr:postcode":"nn11 5pb",
    "addr:street":"Sopwith Way",
    "iso:country":"GB",
    "sg:address":"4 Sopwith Way",
    "sg:city":"Daventry",
    "sg:classifiers":[
        {
            "category":"Professional",
            "subcategory":"Engineering",
            "type":"Services"
        }
    ],
    "sg:postcode":"NN11 5PB",
    "sg:province":"Northamptonshire",
    "wof:name":"Sustaplast Ltd.",
    "wof:placetype":"venue"
},
  "geometry": {"coordinates":[-1.162239,52.260433],"type":"Point"}
}