{
  "type": "Feature",
  "properties": {
    "iso:country":"GB",
    "sg:address":"41 Harbour Street",
    "sg:city":"Whitstable",
    "sg:classifiers":[
        {
            "category":"Restaurant",
            "type":"Food & Drink"
        }
    ],
    "sg:phone":"+44 1227 265337",
    "sg:postcode":"CT5 1AH",
    "sg:province":"Kent",
    "wof:name":"Birdies",
    "wof:placetype":"venue"
},
  "geometry": {"coordinates":[1.0248080492,51.3608665466],"type":"Point"}
}