{
  "type": "Feature",
  "properties": {
    "addr:full":"Unit 10 Waverley Industrial Park, Halesham Drive Harrow Greater London HA5 4TR",
    "addr:housenumber":"unit 10",
    "addr:postcode":"ha5 4tr",
    "addr:street":"Industrial Park Halesham Drive",
    "iso:country":"GB",
    "sg:address":"Unit 10 Waverley Industrial Park, Halesham Drive",
    "sg:city":"Harrow",
    "sg:classifiers":[
        {
            "category":"Professional",
            "subcategory":"Art Services",
            "type":"Services"
        }
    ],
    "sg:postcode":"HA5 4TR",
    "sg:province":"Greater London",
    "sg:tags":[
        "graphic",
        "designer"
    ],
    "wof:name":"Rede Design Ltd.",
    "wof:placetype":"venue"
},
  "geometry": {"coordinates":[-0.3863100111,51.6057014465],"type":"Point"}
}