{
  "type": "Feature",
  "properties": {
    "addr:full":"61 Lawrence Ave New Malden Surrey KT3 5LZ",
    "addr:housenumber":"61",
    "addr:postcode":"kt3 5lz",
    "addr:street":"Lawrence Ave",
    "iso:country":"GB",
    "sg:address":"61 Lawrence Ave",
    "sg:city":"New Malden",
    "sg:classifiers":[
        {
            "category":"Professional",
            "subcategory":"Accounting & Tax Preparation",
            "type":"Services"
        }
    ],
    "sg:postcode":"KT3 5LZ",
    "sg:province":"Surrey",
    "sg:tags":[
        "accountant"
    ],
    "wof:name":"Finders Corporation (U K) Ltd",
    "wof:placetype":"venue"
},
  "geometry": {"coordinates":[-0.261096,51.388348],"type":"Point"}
}