{
  "type": "Feature",
  "properties": {
    "iso:country":"GB",
    "sg:address":"Linden Terrace",
    "sg:city":"Ferryhill",
    "sg:classifiers":[
        {
            "category":"Organizations",
            "subcategory":"Membership Organization",
            "type":"Services"
        }
    ],
    "sg:phone":"+44 1740 651731",
    "sg:postcode":"DL17 0DQ",
    "sg:province":"Durham",
    "sg:tags":[
        "club"
    ],
    "wof:name":"The Royal British Legion",
    "wof:placetype":"venue"
},
  "geometry": {"coordinates":[-1.529486,54.67345],"type":"Point"}
}