{
  "type": "Feature",
  "properties": {
    "addr:full":"Unit 23, Parkburn Court, Parkburn Industrial Estate Hamilton South Lanarkshire ML3 0QQ",
    "addr:housenumber":"unit 23",
    "addr:postcode":"ml3 0qq",
    "addr:street":"Parkburn Court Parkburn Industrial Estate",
    "iso:country":"GB",
    "sg:address":"Unit 23, Parkburn Court, Parkburn Industrial Estate",
    "sg:city":"Hamilton",
    "sg:classifiers":[
        {
            "category":"Home & Garden",
            "subcategory":"Kitchen Supply",
            "type":"Retail Goods"
        }
    ],
    "sg:postcode":"ML3 0QQ",
    "sg:province":"South Lanarkshire",
    "sg:tags":[
        "equipment",
        "brewer"
    ],
    "wof:name":"Dispense Services",
    "wof:placetype":"venue"
},
  "geometry": {"coordinates":[-4.07533,55.786991],"type":"Point"}
}