{
  "type": "Feature",
  "properties": {
    "iso:country":"GB",
    "sg:address":"4 Shropshire St",
    "sg:city":"Crewe",
    "sg:classifiers":[
        {
            "category":"Utilities",
            "subcategory":"Fuel Oil & Lpg",
            "type":"Services"
        }
    ],
    "sg:phone":"+44 1270 812882",
    "sg:postcode":"CW3 0DX",
    "sg:province":"Cheshire",
    "sg:tags":[
        "distributor"
    ],
    "wof:name":"Audlem & Woore Oils",
    "wof:placetype":"venue"
},
  "geometry": {"coordinates":[-2.508946,52.988358],"type":"Point"}
}