{
  "type": "Feature",
  "properties": {
    "iso:country":"GB",
    "sg:address":"Woodlands Drive, Heysham",
    "sg:city":"Morecambe",
    "sg:classifiers":[
        {
            "category":"Health Services",
            "subcategory":"Hospital",
            "type":"Services"
        },
        {
            "category":"Sports & Exercise",
            "subcategory":"Playing Field",
            "type":"Entertainment"
        }
    ],
    "sg:phone":"+44 1772 865965",
    "sg:postcode":"LA3 1LZ",
    "sg:province":"Lancashire",
    "sg:tags":[
        "medical",
        "transportation",
        "ambulance"
    ],
    "wof:name":"Lancashire Ambulance Service",
    "wof:placetype":"venue"
},
  "geometry": {"coordinates":[-2.884741,54.056793],"type":"Point"}
}