{
  "type": "Feature",
  "properties": {
    "iso:country":"GB",
    "sg:address":"42-44 Station Road, North Harrow",
    "sg:city":"Harrow",
    "sg:classifiers":[
        {
            "category":"Travel",
            "subcategory":"Travel Agent",
            "type":"Entertainment"
        },
        {
            "category":"Recreation",
            "subcategory":"Gun Range",
            "type":"Entertainment"
        }
    ],
    "sg:phone":"+44 20 8427 7111",
    "sg:postcode":"HA2 7SE",
    "sg:province":"Greater London",
    "sg:tags":[
        "operator",
        "tour",
        "agency",
        "activity"
    ],
    "wof:name":"Bob Mortimore Travel Ltd.",
    "wof:placetype":"venue"
},
  "geometry": {"coordinates":[-0.361204,51.585602],"type":"Point"}
}