{
  "type": "Feature",
  "properties": {
    "iso:country":"GB",
    "sg:address":"5 Raglan Rd",
    "sg:city":"Morecambe",
    "sg:classifiers":[
        {
            "category":"Building & Trades",
            "subcategory":"Construction",
            "type":"Services"
        }
    ],
    "sg:phone":"+44 1524 410778",
    "sg:postcode":"LA3 1EF",
    "sg:province":"Lancashire",
    "sg:tags":[
        "builder"
    ],
    "wof:name":"C.D Coman",
    "wof:placetype":"venue"
},
  "geometry": {"coordinates":[-2.886853,54.060532],"type":"Point"}
}