{
  "type": "Feature",
  "properties": {
    "addr:full":"Great Oak Street Llanidloes Powys SY18 6BW",
    "addr:postcode":"sy18 6bw",
    "addr:street":"Great Oak Street",
    "iso:country":"GB",
    "sg:address":"Great Oak Street",
    "sg:city":"Llanidloes",
    "sg:classifiers":[
        {
            "category":"Professional",
            "type":"Services"
        },
        {
            "category":"Real Estate",
            "subcategory":"Real Estate Agent",
            "type":"Services"
        }
    ],
    "sg:phone":"+44 1686 412567",
    "sg:postcode":"SY18 6BW",
    "sg:province":"Powys",
    "sg:tags":[
        "auctioneer"
    ],
    "wof:name":"Morris Marshall & Poole",
    "wof:placetype":"venue"
},
  "geometry": {"coordinates":[-3.539664,52.448463],"type":"Point"}
}