{
  "type": "Feature",
  "properties": {
    "iso:country":"GB",
    "sg:address":"54 St Peters Street",
    "sg:city":"Canterbury",
    "sg:classifiers":[
        {
            "category":"Sports & Exercise",
            "subcategory":"Sports Center",
            "type":"Entertainment"
        }
    ],
    "sg:postcode":"CT1 2BE",
    "sg:province":"Kent",
    "sg:tags":[
        "shop",
        "good"
    ],
    "wof:name":"All Skates",
    "wof:placetype":"venue"
},
  "geometry": {"coordinates":[1.0778880119,51.2801742554],"type":"Point"}
}