{
  "type": "Feature",
  "properties": {
    "addr:full":"7 Bank Street Annan Dumfries and Galloway DG12 6AA",
    "addr:housenumber":"7",
    "addr:postcode":"dg12 6aa",
    "addr:street":"Bank Street",
    "iso:country":"GB",
    "sg:address":"7 Bank Street",
    "sg:city":"Annan",
    "sg:classifiers":[
        {
            "category":"Professional",
            "subcategory":"Business Services",
            "type":"Services"
        },
        {
            "category":"Shopping",
            "subcategory":"Pets & Pet Supplies",
            "type":"Retail Goods"
        }
    ],
    "sg:phone":"+44 1461 205301",
    "sg:postcode":"DG12 6AA",
    "sg:province":"Dumfries and Galloway",
    "sg:tags":[
        "import",
        "export",
        "agent"
    ],
    "wof:name":"Petsaver",
    "wof:placetype":"venue"
},
  "geometry": {"coordinates":[-3.2622919083,54.9870300293],"type":"Point"}
}