{
  "type": "Feature",
  "properties": {
    "addr:full":"32 Willesden Avenue Peterborough Cambridgeshire PE4 6EA",
    "addr:housenumber":"32",
    "addr:postcode":"pe4 6ea",
    "addr:street":"Willesden Avenue",
    "iso:country":"GB",
    "sg:address":"32 Willesden Avenue",
    "sg:city":"Peterborough",
    "sg:classifiers":[
        {
            "category":"Taxi",
            "type":"Transportation"
        },
        {
            "category":"Military Area",
            "subcategory":"Air Force Base",
            "type":"Public Place"
        }
    ],
    "sg:phone":"+44 1733 321456",
    "sg:postcode":"PE4 6EA",
    "sg:province":"Cambridgeshire",
    "sg:tags":[
        "mini",
        "hire",
        "private",
        "cab"
    ],
    "wof:name":"Abba Cars",
    "wof:placetype":"venue"
},
  "geometry": {"coordinates":[-0.261673,52.600384],"type":"Point"}
}