{
  "type": "Feature",
  "properties": {
    "addr:full":"20 Market St Telford Shropshire TF1 1DT",
    "addr:housenumber":"20",
    "addr:postcode":"tf1 1dt",
    "addr:street":"Market St",
    "iso:country":"GB",
    "sg:address":"20 Market St",
    "sg:city":"Telford",
    "sg:classifiers":[
        {
            "category":"Shopping",
            "subcategory":"Clothing, Apparel, & Fashions",
            "type":"Retail Goods"
        }
    ],
    "sg:phone":"+44 1952 271600",
    "sg:postcode":"TF1 1DT",
    "sg:province":"Shropshire",
    "sg:tags":[
        "clothing"
    ],
    "wof:name":"Greater Freedom Ltd",
    "wof:placetype":"venue"
},
  "geometry": {"coordinates":[-2.5199,52.701134],"type":"Point"}
}