{
  "type": "Feature",
  "properties": {
    "iso:country":"GB",
    "sg:address":"Unit 2 Chattan Complex, Bonnylside Rd",
    "sg:city":"Bonnybridge",
    "sg:classifiers":[
        {
            "category":"Building & Trades",
            "subcategory":"Construction",
            "type":"Services"
        }
    ],
    "sg:phone":"+44 1324 815222",
    "sg:postcode":"FK4 2AD",
    "sg:province":"Falkirk",
    "sg:tags":[
        "glazier"
    ],
    "wof:name":"A.J. Glass & Glazing",
    "wof:placetype":"venue"
},
  "geometry": {"coordinates":[-3.8808801174,56.0003700256],"type":"Point"}
}