{
  "type": "Feature",
  "properties": {
    "addr:full":"34 Belvedere Bath BA1 5PA",
    "addr:housenumber":"34",
    "addr:postcode":"ba1 5pa",
    "addr:street":"Belvedere",
    "iso:country":"GB",
    "sg:address":"34 Belvedere",
    "sg:city":"Bath",
    "sg:classifiers":[
        {
            "category":"Professional",
            "subcategory":"Computer Services",
            "type":"Services"
        }
    ],
    "sg:postcode":"BA1 5PA",
    "sg:tags":[
        "weight-loss-2-0",
        "weight-loss-transformations"
    ],
    "sg:website":"http://ZodBod.com",
    "wof:name":"ZodBod",
    "wof:placetype":"venue"
},
  "geometry": {"coordinates":[-2.3626891,51.3891333],"type":"Point"}
}