{
  "type": "Feature",
  "properties": {
    "addr:full":"14 Corelli St Newport Newport NP19 7AR",
    "addr:housenumber":"14",
    "addr:postcode":"np19 7ar",
    "addr:street":"Corelli St",
    "iso:country":"GB",
    "sg:address":"14 Corelli St",
    "sg:city":"Newport",
    "sg:classifiers":[
        {
            "category":"Home & Garden",
            "subcategory":"Household Appliances",
            "type":"Retail Goods"
        }
    ],
    "sg:phone":"+44 1633 216626",
    "sg:postcode":"NP19 7AR",
    "sg:province":"Newport",
    "sg:tags":[
        "domestic",
        "centre"
    ],
    "wof:name":"Lowlake Ltd",
    "wof:placetype":"venue"
},
  "geometry": {"coordinates":[-2.9887700081,51.5931282043],"type":"Point"}
}