{
  "type": "Feature",
  "properties": {
    "addr:full":"4 King Street Melton Mowbray Leicestershire LE13 1XA",
    "addr:housenumber":"4",
    "addr:postcode":"le13 1xa",
    "addr:street":"King Street",
    "iso:country":"GB",
    "sg:address":"4 King Street",
    "sg:city":"Melton Mowbray",
    "sg:classifiers":[
        {
            "category":"Shopping",
            "subcategory":"Clothing, Apparel, & Fashions",
            "type":"Retail Goods"
        }
    ],
    "sg:phone":"+44 1664 567426",
    "sg:postcode":"LE13 1XA",
    "sg:province":"Leicestershire",
    "sg:tags":[
        "ladieswear"
    ],
    "wof:name":"J M & S Rosella Ltd.",
    "wof:placetype":"venue"
},
  "geometry": {"coordinates":[-0.886236012,52.7651290894],"type":"Point"}
}