{
  "type": "Feature",
  "properties": {
    "addr:full":"43 Chingford Avenue London Greater London E4 6RJ",
    "addr:housenumber":"43",
    "addr:postcode":"e4 6rj",
    "addr:street":"Chingford Avenue",
    "iso:country":"GB",
    "sg:address":"43 Chingford Avenue",
    "sg:city":"London",
    "sg:classifiers":[
        {
            "category":"Professional",
            "subcategory":"Management & Consulting",
            "type":"Services"
        }
    ],
    "sg:phone":"+44 20 8524 7620",
    "sg:postcode":"E4 6RJ",
    "sg:province":"Greater London",
    "sg:tags":[
        "consultant",
        "business"
    ],
    "wof:name":"G J B Ltd.",
    "wof:placetype":"venue"
},
  "geometry": {"coordinates":[-0.0096829999,51.6235084534],"type":"Point"}
}