{
  "type": "Feature",
  "properties": {
    "addr:full":"58 North Bondgate Bishop Auckland Durham DL14 7PG",
    "addr:housenumber":"58",
    "addr:postcode":"dl14 7pg",
    "addr:street":"North Bondgate;Auckland",
    "iso:country":"GB",
    "sg:address":"58 North Bondgate",
    "sg:city":"Bishop Auckland",
    "sg:classifiers":[
        {
            "category":"Building & Trades",
            "subcategory":"Construction",
            "type":"Services"
        }
    ],
    "sg:phone":"+44 1388 661113",
    "sg:postcode":"DL14 7PG",
    "sg:province":"Durham",
    "sg:tags":[
        "builder"
    ],
    "wof:name":"Redfern Building Services Ltd",
    "wof:placetype":"venue"
},
  "geometry": {"coordinates":[-1.6754469872,54.6655883789],"type":"Point"}
}