{
  "type": "Feature",
  "properties": {
    "addr:full":"Hassalls, Waldron Heathfield East Sussex TN21 0QX",
    "addr:postcode":"tn21 0qx",
    "iso:country":"GB",
    "sg:address":"Hassalls, Waldron",
    "sg:city":"Heathfield",
    "sg:classifiers":[
        {
            "category":"Organizations",
            "subcategory":"Community Association",
            "type":"Services"
        }
    ],
    "sg:phone":"+44 1435 813322",
    "sg:postcode":"TN21 0QX",
    "sg:province":"East Sussex",
    "sg:tags":[
        "relation",
        "public"
    ],
    "wof:name":"Extension One",
    "wof:placetype":"venue"
},
  "geometry": {"coordinates":[0.204425,50.951691],"type":"Point"}
}