{
  "type": "Feature",
  "properties": {
    "iso:country":"GB",
    "sg:address":"C/o Rouse & Co 55 Station Road",
    "sg:city":"Beaconsfield",
    "sg:classifiers":[
        {
            "category":"Utilities",
            "subcategory":"Refuse",
            "type":"Services"
        }
    ],
    "sg:postcode":"HP9 1QL",
    "sg:province":"Buckinghamshire",
    "sg:tags":[
        "collection"
    ],
    "wof:name":"Rje Telehoist Ltd",
    "wof:placetype":"venue"
},
  "geometry": {"coordinates":[-0.6441,51.609459],"type":"Point"}
}