{
  "type": "Feature",
  "properties": {
    "addr:full":"Meadow Cottage Farm, Churt Road Bordon Hampshire GU35 8SS",
    "addr:postcode":"gu35 8ss",
    "addr:street":"Churt Road",
    "iso:country":"GB",
    "sg:address":"Meadow Cottage Farm, Churt Road",
    "sg:city":"Bordon",
    "sg:classifiers":[
        {
            "category":"Ice Cream",
            "type":"Food & Drink"
        }
    ],
    "sg:phone":"+44 1428 712155",
    "sg:postcode":"GU35 8SS",
    "sg:province":"Hampshire",
    "sg:tags":[
        "distributor",
        "mnfr",
        "manufacturer"
    ],
    "wof:name":"Blackburne & Haynes",
    "wof:placetype":"venue"
},
  "geometry": {"coordinates":[-0.865114,51.108856],"type":"Point"}
}