{
  "type": "Feature",
  "properties": {
    "addr:full":"Birch La, Off Cobbs La Crewe Cheshire CW2 5JL",
    "addr:postcode":"cw2 5jl",
    "addr:street":"Birch La Off Cobbs La Crewe",
    "iso:country":"GB",
    "sg:address":"Birch La, Off Cobbs La",
    "sg:city":"Crewe",
    "sg:classifiers":[
        {
            "category":"Recreation",
            "subcategory":"Dog Park",
            "type":"Entertainment"
        }
    ],
    "sg:phone":"+44 1270 841553",
    "sg:postcode":"CW2 5JL",
    "sg:province":"Cheshire",
    "wof:name":"Hollies Training Centre The",
    "wof:placetype":"venue"
},
  "geometry": {"coordinates":[-2.426529,53.05167],"type":"Point"}
}