{
  "type": "Feature",
  "properties": {
    "addr:full":"Bradley Farm, Cumnor Oxford Oxfordshire OX2 9QU",
    "addr:postcode":"ox2 9qu",
    "iso:country":"GB",
    "sg:address":"Bradley Farm, Cumnor",
    "sg:city":"Oxford",
    "sg:classifiers":[
        {
            "category":"Farming",
            "subcategory":"Livestock Farm",
            "type":"Manufacturing & Wholesale Goods"
        }
    ],
    "sg:postcode":"OX2 9QU",
    "sg:province":"Oxfordshire",
    "sg:tags":[
        "others"
    ],
    "wof:name":"W L Bowden & Son",
    "wof:placetype":"venue"
},
  "geometry": {"coordinates":[-1.331009,51.732666],"type":"Point"}
}