{
  "type": "Feature",
  "properties": {
    "addr:full":"5 Eastwood Road Rayleigh Essex SS6 7JD",
    "addr:housenumber":"5",
    "addr:postcode":"ss6 7jd",
    "addr:street":"Eastwood Road Rayleigh",
    "iso:country":"GB",
    "sg:address":"5 Eastwood Road",
    "sg:city":"Rayleigh",
    "sg:classifiers":[
        {
            "category":"Shopping",
            "subcategory":"Comic Books",
            "type":"Retail Goods"
        }
    ],
    "sg:phone":"+44 1268 773461",
    "sg:postcode":"SS6 7JD",
    "sg:province":"Essex",
    "sg:tags":[
        "jeweller"
    ],
    "wof:name":"J Eden",
    "wof:placetype":"venue"
},
  "geometry": {"coordinates":[0.605898,51.584965],"type":"Point"}
}