{
  "type": "Feature",
  "properties": {
    "addr:full":"1 Coopers Rise Godalming Surrey GU7 2NH",
    "addr:housenumber":"1",
    "addr:postcode":"gu7 2nh",
    "addr:street":"Coopers Rise",
    "iso:country":"GB",
    "sg:address":"1 Coopers Rise",
    "sg:city":"Godalming",
    "sg:classifiers":[
        {
            "category":"Organizations",
            "subcategory":"Community Association",
            "type":"Services"
        },
        {
            "category":"Organizations",
            "subcategory":"Membership Organization",
            "type":"Services"
        }
    ],
    "sg:phone":"+44 1483 414539",
    "sg:postcode":"GU7 2NH",
    "sg:province":"Surrey",
    "sg:tags":[
        "club",
        "social"
    ],
    "wof:name":"OCKFORD SOCIAL CLUB",
    "wof:placetype":"venue"
},
  "geometry": {"coordinates":[-0.62799,51.179382],"type":"Point"}
}