{
  "type": "Feature",
  "properties": {
    "addr:full":"21 St Peters Avenue Cleethorpes Lincolnshire DN35 8HQ",
    "addr:housenumber":"21",
    "addr:postcode":"dn35 8hq",
    "addr:street":"St Peters Avenue",
    "iso:country":"GB",
    "sg:address":"21 St Peters Avenue",
    "sg:city":"Cleethorpes",
    "sg:classifiers":[
        {
            "category":"Food & Beverages",
            "subcategory":"Meat & Fish",
            "type":"Retail Goods"
        }
    ],
    "sg:phone":"+44 1472 200190",
    "sg:postcode":"DN35 8HQ",
    "sg:province":"Lincolnshire",
    "sg:tags":[
        "butcher"
    ],
    "wof:name":"Pat Steer Quality Butchers Ltd",
    "wof:placetype":"venue"
},
  "geometry": {"coordinates":[-0.0322580002,53.560092926],"type":"Point"}
}