{
  "type": "Feature",
  "properties": {
    "iso:country":"GB",
    "sg:address":"2 Red House Close, New Whittington",
    "sg:city":"Chesterfield",
    "sg:classifiers":[
        {
            "category":"Education",
            "subcategory":"Vocational School",
            "type":"Public Place"
        },
        {
            "category":"Education",
            "subcategory":"School",
            "type":"Public Place"
        }
    ],
    "sg:phone":"+44 1246 260998",
    "sg:postcode":"S43 2HA",
    "sg:province":"Derbyshire",
    "sg:tags":[
        "tuition",
        "private",
        "swimming"
    ],
    "wof:name":"The Swim School",
    "wof:placetype":"venue"
},
  "geometry": {"coordinates":[-1.403969,53.276154],"type":"Point"}
}