{
  "type": "Feature",
  "properties": {
    "addr:full":"7 Glebe Close, Donington-on-bain Louth Lincolnshire LN11 9TS",
    "addr:housenumber":"7",
    "addr:postcode":"ln11 9ts",
    "addr:street":"Glebe Close;Louth",
    "iso:country":"GB",
    "sg:address":"7 Glebe Close, Donington-on-bain",
    "sg:city":"Louth",
    "sg:classifiers":[
        {
            "category":"Building & Trades",
            "subcategory":"Construction",
            "type":"Services"
        }
    ],
    "sg:phone":"+44 1507 343648",
    "sg:postcode":"LN11 9TS",
    "sg:province":"Lincolnshire",
    "sg:tags":[
        "builder"
    ],
    "wof:name":"Goodwin & Tucker Ltd.",
    "wof:placetype":"venue"
},
  "geometry": {"coordinates":[-0.1455470026,53.3292388916],"type":"Point"}
}