{
  "type": "Feature",
  "properties": {
    "addr:full":"58 Stephenson Place Birmingham West Midlands B2 4DY",
    "addr:housenumber":"58",
    "addr:postcode":"b2 4dy",
    "addr:street":"Stephenson Place",
    "iso:country":"GB",
    "sg:address":"58 Stephenson Place",
    "sg:city":"Birmingham",
    "sg:classifiers":[
        {
            "category":"Bars & Pubs",
            "type":"Food & Drink"
        }
    ],
    "sg:phone":"+44 121 643 2969",
    "sg:postcode":"B2 4DY",
    "sg:province":"West Midlands",
    "sg:tags":[
        "pubs",
        "inn"
    ],
    "wof:name":"The Newt & Cucumbers",
    "wof:placetype":"venue"
},
  "geometry": {"coordinates":[-1.89976,52.478504],"type":"Point"}
}