{
  "type": "Feature",
  "properties": {
    "addr:full":"124 High St, Nailsea Bristol Somerset BS48 1AH",
    "addr:housenumber":"124",
    "addr:postcode":"bs48 1ah",
    "addr:street":"High St",
    "iso:country":"GB",
    "sg:address":"124 High St, Nailsea",
    "sg:city":"Bristol",
    "sg:classifiers":[
        {
            "category":"Personal",
            "subcategory":"Beauty Salon",
            "type":"Services"
        }
    ],
    "sg:postcode":"BS48 1AH",
    "sg:province":"Somerset",
    "sg:tags":[
        "unisex",
        "hairdresser"
    ],
    "wof:name":"Cooper,Dennis,",
    "wof:placetype":"venue"
},
  "geometry": {"coordinates":[-2.7447850704,51.4358406067],"type":"Point"}
}