{
  "type": "Feature",
  "properties": {
    "iso:country":"GB",
    "sg:address":"61 Goodison Road",
    "sg:city":"Liverpool",
    "sg:classifiers":[
        {
            "category":"Food & Beverages",
            "subcategory":"Meat & Fish",
            "type":"Retail Goods"
        }
    ],
    "sg:phone":"+44 151 525 6902",
    "sg:postcode":"L4 4EJ",
    "sg:province":"Merseyside",
    "sg:tags":[
        "chip"
    ],
    "wof:name":"K W Au",
    "wof:placetype":"venue"
},
  "geometry": {"coordinates":[-2.967765,53.439831],"type":"Point"}
}