{
  "type": "Feature",
  "properties": {
    "addr:full":"Dean Hey Farm, Mytholmroyd Hebden Bridge West Yorkshire HX7 5RU",
    "addr:postcode":"hx7 5ru",
    "addr:street":"Dean Hey;West",
    "iso:country":"GB",
    "sg:address":"Dean Hey Farm, Mytholmroyd",
    "sg:city":"Hebden Bridge",
    "sg:classifiers":[
        {
            "category":"Farming",
            "subcategory":"Poultry Farm",
            "type":"Manufacturing & Wholesale Goods"
        }
    ],
    "sg:phone":"+44 1422 882641",
    "sg:postcode":"HX7 5RU",
    "sg:province":"West Yorkshire",
    "sg:tags":[
        "game"
    ],
    "wof:name":"Thornber Chicks Ltd.",
    "wof:placetype":"venue"
},
  "geometry": {"coordinates":[-1.9816349745,53.7305793762],"type":"Point"}
}