{
  "type": "Feature",
  "properties": {
    "addr:full":"The Industrial Estate, Hatherleigh Okehampton Devon EX20 3LP",
    "addr:housenumber":"estate",
    "addr:postcode":"ex20 3lp",
    "addr:street":"Hatherleigh",
    "iso:country":"GB",
    "sg:address":"The Industrial Estate, Hatherleigh",
    "sg:city":"Okehampton",
    "sg:classifiers":[
        {
            "category":"Shopping",
            "subcategory":"Pets & Pet Supplies",
            "type":"Retail Goods"
        }
    ],
    "sg:phone":"+44 1837 810888",
    "sg:postcode":"EX20 3LP",
    "sg:province":"Devon",
    "sg:tags":[
        "food"
    ],
    "wof:name":"Bones Pet & Animal Feeds Supplies",
    "wof:placetype":"venue"
},
  "geometry": {"coordinates":[-4.072584,50.819809],"type":"Point"}
}