{
  "type": "Feature",
  "properties": {
    "addr:full":"96 Alma Rd Southampton Hampshire SO14 6UW",
    "addr:housenumber":"96",
    "addr:postcode":"so14 6uw",
    "addr:street":"Alma Rd",
    "iso:country":"GB",
    "sg:address":"96 Alma Rd",
    "sg:city":"Southampton",
    "sg:classifiers":[
        {
            "category":"Freight",
            "type":"Transportation"
        }
    ],
    "sg:phone":"+44 23 8058 1477",
    "sg:postcode":"SO14 6UW",
    "sg:province":"Hampshire",
    "sg:tags":[
        "haulage",
        "road"
    ],
    "wof:name":"Chris Nicholls",
    "wof:placetype":"venue"
},
  "geometry": {"coordinates":[-1.4030150175,50.9213905334],"type":"Point"}
}