{
  "type": "Feature",
  "properties": {
    "addr:full":"121 Sydenham Rd Sydenham Greater London SE26 5HB",
    "addr:housenumber":"121",
    "addr:postcode":"se26 5hb",
    "addr:street":"Sydenham Rd",
    "iso:country":"GB",
    "sg:address":"121 Sydenham Rd",
    "sg:city":"Sydenham",
    "sg:classifiers":[
        {
            "category":"Bars & Pubs",
            "type":"Food & Drink"
        }
    ],
    "sg:phone":"+44 20 8778 8728",
    "sg:postcode":"SE26 5HB",
    "sg:province":"Greater London",
    "sg:tags":[
        "pubs",
        "inn"
    ],
    "wof:name":"Dolphin The",
    "wof:placetype":"venue"
},
  "geometry": {"coordinates":[-0.0488479994,51.4258956909],"type":"Point"}
}