{
  "type": "Feature",
  "properties": {
    "addr:full":"120-122 High Street, Barkingside Ilford Essex IG6 2DU",
    "addr:housenumber":"120-122",
    "addr:postcode":"ig6 2du",
    "addr:street":"High Street",
    "iso:country":"GB",
    "sg:address":"120-122 High Street, Barkingside",
    "sg:city":"Ilford",
    "sg:classifiers":[
        {
            "category":"Shopping",
            "subcategory":"Clothing, Apparel, & Fashions",
            "type":"Retail Goods"
        }
    ],
    "sg:phone":"+44 20 8551 4465",
    "sg:postcode":"IG6 2DU",
    "sg:province":"Essex",
    "sg:tags":[
        "shop"
    ],
    "wof:name":"Spirit Mens & Ladies Wear Ltd.",
    "wof:placetype":"venue"
},
  "geometry": {"coordinates":[0.083616,51.591763],"type":"Point"}
}