{
  "type": "Feature",
  "properties": {
    "iso:country":"GB",
    "sg:address":"20 Fern Rise",
    "sg:city":"Leicester",
    "sg:classifiers":[
        {
            "category":"Home & Garden",
            "subcategory":"Household Appliances",
            "type":"Retail Goods"
        }
    ],
    "sg:phone":"+44 116 276 2717",
    "sg:postcode":"LE5 1FF",
    "sg:province":"Leicestershire",
    "sg:tags":[
        "electrical"
    ],
    "wof:name":"Green's",
    "wof:placetype":"venue"
},
  "geometry": {"coordinates":[-1.0642460585,52.6498565674],"type":"Point"}
}