{
  "type": "Feature",
  "properties": {
    "addr:full":"176 Bishopsgate London Greater London EC2M 4NQ",
    "addr:housenumber":"176",
    "addr:postcode":"ec2m 4nq",
    "addr:street":"Bishopsgate",
    "iso:country":"GB",
    "sg:address":"176 Bishopsgate",
    "sg:city":"London",
    "sg:classifiers":[
        {
            "category":"Professional",
            "type":"Services"
        }
    ],
    "sg:phone":"+44 20 7283 4889",
    "sg:postcode":"EC2M 4NQ",
    "sg:province":"Greater London",
    "sg:tags":[
        "caterer"
    ],
    "wof:name":"Ponti's Polo Bar",
    "wof:placetype":"venue"
},
  "geometry": {"coordinates":[-0.080322,51.517612],"type":"Point"}
}