{
  "type": "Feature",
  "properties": {
    "iso:country":"GB",
    "sg:address":"Nursery Road, Nazeing",
    "sg:city":"Waltham Abbey",
    "sg:classifiers":[
        {
            "category":"Wholesale",
            "subcategory":"Fruits & Vegetables",
            "type":"Manufacturing & Wholesale Goods"
        }
    ],
    "sg:phone":"+44 1992 466967",
    "sg:postcode":"EN9 2JF",
    "sg:province":"Essex",
    "wof:name":"Arnlands Nursery",
    "wof:placetype":"venue"
},
  "geometry": {"coordinates":[0.048448,51.738914],"type":"Point"}
}