{
  "type": "Feature",
  "properties": {
    "iso:country":"GB",
    "sg:address":"32 Coney Furlong",
    "sg:city":"Peacehaven",
    "sg:classifiers":[
        {
            "category":"Organizations",
            "subcategory":"Non-profit Organization",
            "type":"Services"
        }
    ],
    "sg:phone":"+44 1273 580135",
    "sg:postcode":"BN10 8EH",
    "sg:province":"East Sussex",
    "sg:tags":[
        "alarm",
        "system"
    ],
    "wof:name":"Meridian",
    "wof:placetype":"venue"
},
  "geometry": {"coordinates":[0.010607,50.8055],"type":"Point"}
}