{
  "type": "Feature",
  "properties": {
    "addr:full":"6 Eastern Avenue East Romford Essex RM1 4DR",
    "addr:housenumber":"6",
    "addr:postcode":"rm1 4dr",
    "addr:street":"Eastern Avenue East",
    "iso:country":"GB",
    "sg:address":"6 Eastern Avenue East",
    "sg:city":"Romford",
    "sg:classifiers":[
        {
            "category":"Autos & Motor Vehicles",
            "subcategory":"Automobile Sales",
            "type":"Retail Goods"
        }
    ],
    "sg:phone":"+44 1708 737444",
    "sg:postcode":"RM1 4DR",
    "sg:province":"Essex",
    "sg:tags":[
        "commercial"
    ],
    "wof:name":"Motorpoint Ltd",
    "wof:placetype":"venue"
},
  "geometry": {"coordinates":[0.17291,51.586449],"type":"Point"}
}