{
  "type": "Feature",
  "properties": {
    "iso:country":"GB",
    "sg:address":"8 Cumberland Walk",
    "sg:city":"Tunbridge Wells",
    "sg:classifiers":[
        {
            "category":"Banks & Credit Unions",
            "subcategory":"Financial Services",
            "type":"Services"
        }
    ],
    "sg:phone":"+44 1892 518007",
    "sg:postcode":"TN1 1UJ",
    "sg:province":"Kent",
    "sg:tags":[
        "consultant"
    ],
    "wof:name":"Net Partners",
    "wof:placetype":"venue"
},
  "geometry": {"coordinates":[0.261411,51.126305],"type":"Point"}
}