{
  "type": "Feature",
  "properties": {
    "addr:full":"Station Precinct Windermere Cumbria LA23 1AH",
    "addr:postcode":"la23 1ah",
    "iso:country":"GB",
    "sg:address":"Station Precinct",
    "sg:city":"Windermere",
    "sg:classifiers":[
        {
            "category":"Cafe",
            "type":"Food & Drink"
        }
    ],
    "sg:phone":"+44 15394 46732",
    "sg:postcode":"LA23 1AH",
    "sg:province":"Cumbria",
    "sg:tags":[
        "tea",
        "room"
    ],
    "wof:name":"Miller Howe Kaff",
    "wof:placetype":"venue"
},
  "geometry": {"coordinates":[-2.9064040184,54.3796653748],"type":"Point"}
}