{
  "type": "Feature",
  "properties": {
    "addr:full":"113 Kennington Road London Greater London SE11 6SF",
    "addr:housenumber":"113",
    "addr:postcode":"se11 6sf",
    "addr:street":"Kennington Road",
    "iso:country":"GB",
    "sg:address":"113 Kennington Road",
    "sg:city":"London",
    "sg:classifiers":[
        {
            "category":"Autos & Motor Vehicles",
            "subcategory":"Motorcycle Sales",
            "type":"Retail Goods"
        }
    ],
    "sg:phone":"+44 20 7735 5819",
    "sg:postcode":"SE11 6SF",
    "sg:province":"Greater London",
    "wof:name":"Supreme Motor Cycle",
    "wof:placetype":"venue"
},
  "geometry": {"coordinates":[-0.1106859967,51.4952964783],"type":"Point"}
}