{
  "type": "Feature",
  "properties": {
    "iso:country":"GB",
    "sg:address":"37a Waterloo Rd",
    "sg:city":"Wellington",
    "sg:classifiers":[
        {
            "category":"Retail",
            "subcategory":"Repair Shop",
            "type":"Services"
        }
    ],
    "sg:phone":"+44 1823 663666",
    "sg:postcode":"TA21 8JQ",
    "sg:province":"Devon",
    "sg:tags":[
        "radio",
        "television",
        "video"
    ],
    "wof:name":"Kapital Electronics",
    "wof:placetype":"venue"
},
  "geometry": {"coordinates":[-3.2360370159,50.980506897],"type":"Point"}
}