{
  "type": "Feature",
  "properties": {
    "iso:country":"GB",
    "sg:address":"36a Langdale Road",
    "sg:city":"Runcorn",
    "sg:classifiers":[
        {
            "category":"Food & Beverages",
            "subcategory":"Liquor & Beverages",
            "type":"Retail Goods"
        }
    ],
    "sg:phone":"+44 1928 572318",
    "sg:postcode":"WA7 5PU",
    "sg:province":"Cheshire",
    "sg:tags":[
        "beer",
        "spirit",
        "wines"
    ],
    "wof:name":"The Drinks Cabin",
    "wof:placetype":"venue"
},
  "geometry": {"coordinates":[-2.7292380333,53.3341674805],"type":"Point"}
}