{
  "type": "Feature",
  "properties": {
    "iso:country":"GB",
    "sg:address":"19 Fore Street",
    "sg:city":"St Austell",
    "sg:classifiers":[
        {
            "category":"Restaurant",
            "type":"Food & Drink"
        }
    ],
    "sg:phone":"+44 1726 65923",
    "sg:postcode":"PL25 5PX",
    "sg:province":"Cornwall",
    "wof:name":"Wimpy International Ltd.",
    "wof:placetype":"venue"
},
  "geometry": {"coordinates":[-4.793555,50.338097],"type":"Point"}
}