{
  "type": "Feature",
  "properties": {
    "iso:country":"GB",
    "sg:address":"1 South St Johns Place",
    "sg:city":"Perth",
    "sg:classifiers":[
        {
            "category":"Shopping",
            "subcategory":"Baby Store",
            "type":"Retail Goods"
        }
    ],
    "sg:postcode":"PH1 5SU",
    "sg:province":"Perth and Kinross",
    "sg:tags":[
        "babywear",
        "childrens"
    ],
    "wof:name":"Free Spirit",
    "wof:placetype":"venue"
},
  "geometry": {"coordinates":[-3.425901,56.395168],"type":"Point"}
}