{
  "type": "Feature",
  "properties": {
    "iso:country":"GB",
    "sg:address":"16 Castle Street",
    "sg:city":"Caerphilly",
    "sg:classifiers":[
        {
            "category":"Insurance",
            "subcategory":"Insurance Agent",
            "type":"Services"
        }
    ],
    "sg:phone":"+44 29 2086 1116",
    "sg:postcode":"CF83 1NY",
    "sg:province":"Caerphilly",
    "sg:tags":[
        "broker"
    ],
    "wof:name":"Gwyn Roberts (Insurance Brokers) Ltd.",
    "wof:placetype":"venue"
},
  "geometry": {"coordinates":[-3.217575,51.57732],"type":"Point"}
}