{
  "type": "Feature",
  "properties": {
    "addr:full":"Mountview, 302 Sealand Road Chester Cheshire CH1 4LQ",
    "addr:housenumber":"302",
    "addr:postcode":"ch1 4lq",
    "addr:street":"Sealand Road",
    "iso:country":"GB",
    "sg:address":"Mountview, 302 Sealand Road",
    "sg:city":"Chester",
    "sg:classifiers":[
        {
            "category":"Autos & Motor Vehicles",
            "subcategory":"Automobile Sales",
            "type":"Retail Goods"
        }
    ],
    "sg:phone":"+44 1244 390009",
    "sg:postcode":"CH1 4LQ",
    "sg:province":"Cheshire",
    "sg:tags":[
        "car"
    ],
    "wof:name":"Henlys (Chester)",
    "wof:placetype":"venue"
},
  "geometry": {"coordinates":[-2.8943688869,53.188129425],"type":"Point"}
}