{
  "type": "Feature",
  "properties": {
    "addr:full":"169 Aston Clinton Road, Weston Turville Aylesbury Buckinghamshire HP22 5AD",
    "addr:housenumber":"169",
    "addr:postcode":"hp22 5ad",
    "addr:street":"Aston Clinton Road",
    "iso:country":"GB",
    "sg:address":"169 Aston Clinton Road, Weston Turville",
    "sg:city":"Aylesbury",
    "sg:classifiers":[
        {
            "category":"Home & Garden",
            "subcategory":"Household Appliances",
            "type":"Retail Goods"
        },
        {
            "category":"Retail",
            "subcategory":"Repair Shop",
            "type":"Services"
        }
    ],
    "sg:phone":"+44 1296 632222",
    "sg:postcode":"HP22 5AD",
    "sg:province":"Buckinghamshire",
    "sg:tags":[
        "refrigerator",
        "electrical",
        "servicing",
        "freezer"
    ],
    "wof:name":"Aylesbury Refrigeration",
    "wof:placetype":"venue"
},
  "geometry": {"coordinates":[-0.759617,51.808128],"type":"Point"}
}