{
  "type": "Feature",
  "properties": {
    "addr:full":"113 High Street London Greater London E13 0AD",
    "addr:housenumber":"113",
    "addr:postcode":"e13 0ad",
    "addr:street":"High Street",
    "iso:country":"GB",
    "sg:address":"113 High Street",
    "sg:city":"London",
    "sg:classifiers":[
        {
            "category":"Food & Beverages",
            "subcategory":"Liquor & Beverages",
            "type":"Retail Goods"
        }
    ],
    "sg:phone":"+44 20 8552 4530",
    "sg:postcode":"E13 0AD",
    "sg:province":"Greater London",
    "sg:tags":[
        "beer",
        "spirit",
        "wines"
    ],
    "wof:name":"Family Choice",
    "wof:placetype":"venue"
},
  "geometry": {"coordinates":[0.0238099992,51.5298118591],"type":"Point"}
}