{
  "type": "Feature",
  "properties": {
    "addr:full":"Unit 29 Duffryn Indust Est Hengoed Caerphilly CF82 7AJ",
    "addr:housenumber":"unit 29",
    "addr:postcode":"cf82 7aj",
    "iso:country":"GB",
    "sg:address":"Unit 29 Duffryn Indust Est",
    "sg:city":"Hengoed",
    "sg:classifiers":[
        {
            "category":"Food & Beverages",
            "subcategory":"Meat & Fish",
            "type":"Retail Goods"
        }
    ],
    "sg:phone":"+44 1443 812059",
    "sg:postcode":"CF82 7AJ",
    "sg:province":"Caerphilly",
    "sg:tags":[
        "butcher"
    ],
    "wof:name":"Ace Meats Ltd",
    "wof:placetype":"venue"
},
  "geometry": {"coordinates":[-3.2317988873,51.6483192444],"type":"Point"}
}