{
  "type": "Feature",
  "properties": {
    "iso:country":"GB",
    "sg:address":"St Martins Church Centre, Church St",
    "sg:city":"Liskeard",
    "sg:classifiers":[
        {
            "category":"Place Of Worship",
            "type":"Public Place"
        }
    ],
    "sg:phone":"+44 1579 347411",
    "sg:postcode":"PL14 3AQ",
    "sg:province":"Cornwall",
    "wof:name":"St Peters C Of E Church",
    "wof:placetype":"venue"
},
  "geometry": {"coordinates":[-4.4658341408,50.4537963867],"type":"Point"}
}