{
  "type": "Feature",
  "properties": {
    "iso:country":"GB",
    "sg:address":"33-35 Bank Street",
    "sg:city":"Braintree",
    "sg:classifiers":[
        {
            "category":"Shopping",
            "subcategory":"Comic Books",
            "type":"Retail Goods"
        }
    ],
    "sg:phone":"+44 1376 322501",
    "sg:postcode":"CM7 1UG",
    "sg:province":"Essex",
    "sg:tags":[
        "jeweller"
    ],
    "wof:name":"F Hinds Ltd.",
    "wof:placetype":"venue"
},
  "geometry": {"coordinates":[0.5509390235,51.8794937134],"type":"Point"}
}