{
  "type": "Feature",
  "properties": {
    "addr:full":"37 Broomfield Road Beckenham Kent BR3 3QB",
    "addr:housenumber":"37",
    "addr:postcode":"br3 3qb",
    "addr:street":"Broomfield Road",
    "iso:country":"GB",
    "sg:address":"37 Broomfield Road",
    "sg:city":"Beckenham",
    "sg:classifiers":[
        {
            "category":"Building & Trades",
            "subcategory":"Construction",
            "type":"Services"
        }
    ],
    "sg:phone":"+44 20 8650 4996",
    "sg:postcode":"BR3 3QB",
    "sg:province":"Kent",
    "sg:tags":[
        "builder"
    ],
    "wof:name":"R P S Cherry Building",
    "wof:placetype":"venue"
},
  "geometry": {"coordinates":[-0.038272,51.39996],"type":"Point"}
}