{
  "type": "Feature",
  "properties": {
    "addr:full":"The Arch, 324-325 Blucher Road London Greater London SE5 0LH",
    "addr:postcode":"324-325;se5 0lh",
    "addr:street":"Blucher Road",
    "iso:country":"GB",
    "sg:address":"The Arch, 324-325 Blucher Road",
    "sg:city":"London",
    "sg:classifiers":[
        {
            "category":"Professional",
            "type":"Services"
        }
    ],
    "sg:postcode":"SE5 0LH",
    "sg:province":"Greater London",
    "sg:tags":[
        "caterer"
    ],
    "wof:name":"Scott Harris Ltd.",
    "wof:placetype":"venue"
},
  "geometry": {"coordinates":[-0.0948700011,51.4771385193],"type":"Point"}
}