{
  "type": "Feature",
  "properties": {
    "addr:full":"57 Sidcup High St Sidcup Kent DA14 6ED",
    "addr:housenumber":"57",
    "addr:postcode":"da14 6ed",
    "addr:street":"High St",
    "iso:country":"GB",
    "sg:address":"57 Sidcup High St",
    "sg:city":"Sidcup",
    "sg:classifiers":[
        {
            "category":"Food & Beverages",
            "subcategory":"Fruits & Vegetables",
            "type":"Retail Goods"
        }
    ],
    "sg:phone":"+44 20 8302 0152",
    "sg:postcode":"DA14 6ED",
    "sg:province":"Kent",
    "sg:tags":[
        "greengrocer"
    ],
    "wof:name":"The Market",
    "wof:placetype":"venue"
},
  "geometry": {"coordinates":[0.10278,51.426289],"type":"Point"}
}