{
  "type": "Feature",
  "properties": {
    "iso:country":"GB",
    "sg:address":"50 High Street",
    "sg:city":"Malmesbury",
    "sg:classifiers":[
        {
            "category":"Real Estate",
            "subcategory":"Real Estate Agent",
            "type":"Services"
        }
    ],
    "sg:phone":"+44 1666 825725",
    "sg:postcode":"SN16 9AT",
    "sg:province":"Wiltshire",
    "wof:name":"Christopher Blount & Co",
    "wof:placetype":"venue"
},
  "geometry": {"coordinates":[-2.097136,51.582043],"type":"Point"}
}