{
  "type": "Feature",
  "properties": {
    "iso:country":"GB",
    "sg:address":"44 Glancynon Terrace, Abercynon",
    "sg:city":"Mountain Ash",
    "sg:classifiers":[
        {
            "category":"Food & Beverages",
            "subcategory":"Meat & Fish",
            "type":"Retail Goods"
        }
    ],
    "sg:phone":"+44 1443 740236",
    "sg:postcode":"CF45 4TG",
    "sg:province":"Rhondda, Cynon, Taff",
    "sg:tags":[
        "butcher"
    ],
    "wof:name":"M S & J T Lee",
    "wof:placetype":"venue"
},
  "geometry": {"coordinates":[-3.324702,51.647202],"type":"Point"}
}