{
  "type": "Feature",
  "properties": {
    "addr:full":"211 High Road Ilford Essex IG1 1LX",
    "addr:housenumber":"211",
    "addr:postcode":"ig1 1lx",
    "addr:street":"High Road",
    "iso:country":"GB",
    "sg:address":"211 High Road",
    "sg:city":"Ilford",
    "sg:classifiers":[
        {
            "category":"Shopping",
            "subcategory":"Photographic Equipment",
            "type":"Retail Goods"
        }
    ],
    "sg:phone":"+44 20 8514 7111",
    "sg:postcode":"IG1 1LX",
    "sg:province":"Essex",
    "sg:tags":[
        "supply"
    ],
    "wof:name":"Jessop Photo Video Centre",
    "wof:placetype":"venue"
},
  "geometry": {"coordinates":[0.076171,51.559673],"type":"Point"}
}