{
  "type": "Feature",
  "properties": {
    "iso:country":"GB",
    "sg:address":"112 Fore Street",
    "sg:city":"Saltash",
    "sg:classifiers":[
        {
            "category":"Shopping",
            "subcategory":"Clothing, Apparel, & Fashions",
            "type":"Retail Goods"
        }
    ],
    "sg:phone":"+44 1752 849994",
    "sg:postcode":"PL12 6JW",
    "sg:province":"Cornwall",
    "sg:tags":[
        "shop"
    ],
    "wof:name":"Intrigue",
    "wof:placetype":"venue"
},
  "geometry": {"coordinates":[-4.213172,50.408913],"type":"Point"}
}