{
  "type": "Feature",
  "properties": {
    "iso:country":"GB",
    "sg:address":"Unit 3 Coventry Court, Coventry Road",
    "sg:city":"Nottingham",
    "sg:classifiers":[
        {
            "category":"Professional",
            "subcategory":"Printing & Photocopies",
            "type":"Services"
        }
    ],
    "sg:phone":"+44 115 975 1416",
    "sg:postcode":"NG6 8PR",
    "sg:province":"Nottinghamshire",
    "sg:tags":[
        "printer"
    ],
    "wof:name":"K C Tompkin Ltd.",
    "wof:placetype":"venue"
},
  "geometry": {"coordinates":[-1.197339,52.995411],"type":"Point"}
}