{
  "type": "Feature",
  "properties": {
    "iso:country":"GB",
    "sg:address":"Harpenden Common Golf Club, East Common",
    "sg:city":"Harpenden",
    "sg:classifiers":[
        {
            "category":"Sports & Exercise",
            "subcategory":"Golf",
            "type":"Entertainment"
        }
    ],
    "sg:phone":"+44 1582 460655",
    "sg:postcode":"AL5 1BL",
    "sg:province":"Hertfordshire",
    "sg:tags":[
        "club",
        "course"
    ],
    "wof:name":"Harpenden Common Golf Club",
    "wof:placetype":"venue"
},
  "geometry": {"coordinates":[-0.356559,51.816216],"type":"Point"}
}