{
  "type": "Feature",
  "properties": {
    "iso:country":"GB",
    "sg:address":"Worlds End Lane, Buxhall",
    "sg:city":"Stowmarket",
    "sg:classifiers":[
        {
            "category":"Transit Center",
            "subcategory":"Passenger",
            "type":"Transportation"
        }
    ],
    "sg:postcode":"IP14 3ED",
    "sg:province":"Suffolk",
    "sg:tags":[
        "boarding",
        "kennel",
        "catteries"
    ],
    "wof:name":"West End Farm Kennels & Cattery",
    "wof:placetype":"venue"
},
  "geometry": {"coordinates":[0.930659,52.181053],"type":"Point"}
}