{
  "type": "Feature",
  "properties": {
    "addr:full":"Kingsgate Workshops, Kingsgate Road London Greater London NW6 2JG",
    "addr:postcode":"nw6 2jg",
    "addr:street":"Kingsgate;Kingsgate Road",
    "iso:country":"GB",
    "sg:address":"Kingsgate Workshops, Kingsgate Road",
    "sg:city":"London",
    "sg:classifiers":[
        {
            "category":"Professional",
            "subcategory":"Art Services",
            "type":"Services"
        }
    ],
    "sg:phone":"+44 20 7328 2824",
    "sg:postcode":"NW6 2JG",
    "sg:province":"Greater London",
    "sg:tags":[
        "carver",
        "sculptor"
    ],
    "wof:name":"Tim Hine",
    "wof:placetype":"venue"
},
  "geometry": {"coordinates":[-0.19661,51.543941],"type":"Point"}
}