{
  "type": "Feature",
  "properties": {
    "addr:full":"124 Eldersley St Glasgow Glasgow City G3 7AW",
    "addr:housenumber":"124",
    "addr:postcode":"g3 7aw",
    "addr:street":"Eldersley St",
    "iso:country":"GB",
    "sg:address":"124 Eldersley St",
    "sg:city":"Glasgow",
    "sg:classifiers":[
        {
            "category":"Real Estate",
            "subcategory":"Architect",
            "type":"Services"
        }
    ],
    "sg:postcode":"G3 7AW",
    "sg:province":"Glasgow City",
    "wof:name":"Discovery Land Surveys",
    "wof:placetype":"venue"
},
  "geometry": {"coordinates":[-4.276182,55.866024],"type":"Point"}
}