{
  "type": "Feature",
  "properties": {
    "addr:full":"Newspaper House, Tannery Lane Warrington Cheshire WA5 2UD",
    "addr:postcode":"wa5 2ud",
    "addr:street":"Tannery Lane",
    "iso:country":"GB",
    "sg:address":"Newspaper House, Tannery Lane",
    "sg:city":"Warrington",
    "sg:classifiers":[
        {
            "category":"Professional",
            "subcategory":"Engineering",
            "type":"Services"
        }
    ],
    "sg:phone":"+44 1925 722003",
    "sg:postcode":"WA5 2UD",
    "sg:province":"Cheshire",
    "sg:tags":[
        "engineer",
        "structural"
    ],
    "wof:name":"Steve Hunt Partnership",
    "wof:placetype":"venue"
},
  "geometry": {"coordinates":[-2.6718459129,53.3796386719],"type":"Point"}
}