{
  "type": "Feature",
  "properties": {
    "iso:country":"GB",
    "sg:address":"34 Wellington Rd",
    "sg:city":"Birkenhead",
    "sg:classifiers":[
        {
            "category":"Government",
            "subcategory":"Post Office",
            "type":"Public Place"
        }
    ],
    "sg:phone":"+44 151 652 1427",
    "sg:postcode":"L43 2JF",
    "sg:province":"Merseyside",
    "wof:name":"Wellington Road Post Office",
    "wof:placetype":"venue"
},
  "geometry": {"coordinates":[-3.051578,53.38335],"type":"Point"}
}