{
  "type": "Feature",
  "properties": {
    "addr:full":"11a Upton Road Bexleyheath Kent DA6 8LQ",
    "addr:housenumber":"11a",
    "addr:postcode":"da6 8lq",
    "addr:street":"Upton Road",
    "iso:country":"GB",
    "sg:address":"11a Upton Road",
    "sg:city":"Bexleyheath",
    "sg:classifiers":[
        {
            "category":"Banks & Credit Unions",
            "subcategory":"Bureau De Change",
            "type":"Services"
        }
    ],
    "sg:phone":"+44 20 8301 0920",
    "sg:postcode":"DA6 8LQ",
    "sg:province":"Kent",
    "sg:tags":[
        "committee",
        "panel"
    ],
    "wof:name":"Bexley Community Health Council",
    "wof:placetype":"venue"
},
  "geometry": {"coordinates":[0.131664,51.457241],"type":"Point"}
}