{
  "type": "Feature",
  "properties": {
    "iso:country":"GB",
    "sg:address":"2b Central Avenue",
    "sg:city":"Southend-on-sea",
    "sg:classifiers":[
        {
            "category":"Retail",
            "subcategory":"Auto Repair",
            "type":"Services"
        }
    ],
    "sg:phone":"+44 1702 610591",
    "sg:postcode":"SS2 5HS",
    "sg:province":"Essex",
    "sg:tags":[
        "modification",
        "garage"
    ],
    "wof:name":"R K Auto Services",
    "wof:placetype":"venue"
},
  "geometry": {"coordinates":[0.718531,51.544395],"type":"Point"}
}