{
  "type": "Feature",
  "properties": {
    "iso:country":"GB",
    "sg:address":"7b Station Parade, Tarring Road",
    "sg:city":"Worthing",
    "sg:classifiers":[
        {
            "category":"Retail",
            "subcategory":"Repair Shop",
            "type":"Services"
        }
    ],
    "sg:postcode":"BN11 4SS",
    "sg:province":"West Sussex",
    "sg:tags":[
        "radio",
        "television",
        "video"
    ],
    "wof:name":"T McIntyre",
    "wof:placetype":"venue"
},
  "geometry": {"coordinates":[-0.375424,50.813625],"type":"Point"}
}