{
  "type": "Feature",
  "properties": {
    "addr:full":"24 Dorward Road Montrose Aberdeenshire DD10 8SB",
    "addr:housenumber":"24",
    "addr:postcode":"dd10 8sb",
    "addr:street":"Dorward Road",
    "iso:country":"GB",
    "sg:address":"24 Dorward Road",
    "sg:city":"Montrose",
    "sg:classifiers":[
        {
            "category":"Health Services",
            "subcategory":"Nursing And Care Facility",
            "type":"Services"
        },
        {
            "category":"Social Services",
            "subcategory":"Retirement Home",
            "type":"Services"
        }
    ],
    "sg:phone":"+44 1674 673871",
    "sg:postcode":"DD10 8SB",
    "sg:province":"Aberdeenshire",
    "sg:tags":[
        "residential"
    ],
    "wof:name":"Dorward House",
    "wof:placetype":"venue"
},
  "geometry": {"coordinates":[-2.4596910477,56.7163848877],"type":"Point"}
}