{
  "type": "Feature",
  "properties": {
    "iso:country":"GB",
    "sg:address":"Fidlers Well, Bamford",
    "sg:city":"Hope Valley",
    "sg:classifiers":[
        {
            "category":"Education",
            "subcategory":"School",
            "type":"Public Place"
        }
    ],
    "sg:phone":"+44 1433 651267",
    "sg:postcode":"S33 0AR",
    "sg:province":"Derbyshire",
    "sg:tags":[
        "local",
        "authority"
    ],
    "wof:name":"Bamford County Primary School",
    "wof:placetype":"venue"
},
  "geometry": {"coordinates":[-1.689613,53.349155],"type":"Point"}
}