{
  "type": "Feature",
  "properties": {
    "iso:country":"GB",
    "sg:address":"17 Derwent Way",
    "sg:city":"Braintree",
    "sg:classifiers":[
        {
            "category":"Banks & Credit Unions",
            "subcategory":"Financial Services",
            "type":"Services"
        }
    ],
    "sg:phone":"+44 1376 330249",
    "sg:postcode":"CM7 8UH",
    "sg:province":"Essex",
    "sg:tags":[
        "adviser"
    ],
    "wof:name":"Chambers & Co",
    "wof:placetype":"venue"
},
  "geometry": {"coordinates":[0.5324860215,51.8608169556],"type":"Point"}
}