{
  "type": "Feature",
  "properties": {
    "iso:country":"GB",
    "sg:address":"34 Dovedale Circle",
    "sg:city":"Ilkeston",
    "sg:classifiers":[
        {
            "category":"Professional",
            "subcategory":"Detective & Security Services",
            "type":"Services"
        }
    ],
    "sg:phone":"+44 115 932 9655",
    "sg:postcode":"DE7 8SE",
    "sg:province":"Derbyshire",
    "wof:name":"E Williams",
    "wof:placetype":"venue"
},
  "geometry": {"coordinates":[-1.311323,52.994099],"type":"Point"}
}