{
  "type": "Feature",
  "properties": {
    "addr:full":"86-88 High Street Dunblane Perth and Kinross FK15 0AY",
    "addr:housenumber":"86-88",
    "addr:postcode":"fk15 0ay",
    "addr:street":"High Street",
    "iso:country":"GB",
    "sg:address":"86-88 High Street",
    "sg:city":"Dunblane",
    "sg:classifiers":[
        {
            "category":"Restaurant",
            "type":"Food & Drink"
        }
    ],
    "sg:postcode":"FK15 0AY",
    "sg:province":"Perth and Kinross",
    "wof:name":"LOTUS CANTONESE RESTAURANT",
    "wof:placetype":"venue"
},
  "geometry": {"coordinates":[-3.963938,56.188011],"type":"Point"}
}