{
  "type": "Feature",
  "properties": {
    "iso:country":"GB",
    "sg:address":"1 Dougalston Gardens South, Milngavie",
    "sg:city":"Glasgow",
    "sg:classifiers":[
        {
            "category":"Travel",
            "subcategory":"Hotels & Motels",
            "type":"Entertainment"
        }
    ],
    "sg:phone":"+44 141 956 5973",
    "sg:postcode":"G62 6HS",
    "sg:province":"East Dunbartonshire",
    "sg:tags":[
        "house",
        "guest"
    ],
    "wof:name":"Westview",
    "wof:placetype":"venue"
},
  "geometry": {"coordinates":[-4.310959,55.939041],"type":"Point"}
}