{
  "type": "Feature",
  "properties": {
    "addr:full":"264a Plumstead High St Woolwich Greater London SE18 1JN",
    "addr:housenumber":"264a",
    "addr:postcode":"se18 1jn",
    "addr:street":"High St",
    "iso:country":"GB",
    "sg:address":"264a Plumstead High St",
    "sg:city":"Woolwich",
    "sg:classifiers":[
        {
            "category":"Shopping",
            "subcategory":"Crafts & Fabrics",
            "type":"Retail Goods"
        }
    ],
    "sg:phone":"+44 20 8317 1465",
    "sg:postcode":"SE18 1JN",
    "sg:province":"Greater London",
    "sg:tags":[
        "shop",
        "needlecraft",
        "wool"
    ],
    "wof:name":"Village Yarns",
    "wof:placetype":"venue"
},
  "geometry": {"coordinates":[0.098401,51.48595],"type":"Point"}
}