{
  "type": "Feature",
  "properties": {
    "iso:country":"GB",
    "sg:address":"54-56 West Main Street, Harthill",
    "sg:city":"Shotts",
    "sg:classifiers":[
        {
            "category":"Fast Food",
            "type":"Food & Drink"
        }
    ],
    "sg:phone":"+44 1501 751246",
    "sg:postcode":"ML7 5QD",
    "sg:province":"North Lanarkshire",
    "sg:tags":[
        "away",
        "meal",
        "outlet",
        "take"
    ],
    "wof:name":"Jasmine House",
    "wof:placetype":"venue"
},
  "geometry": {"coordinates":[-3.751482,55.860485],"type":"Point"}
}