{
  "type": "Feature",
  "properties": {
    "addr:full":"The Barclay Centre, University Of Warwick Science Park Coventry Warwickshire CV4 7EZ",
    "addr:postcode":"cv4 7ez",
    "addr:street":"Science Park",
    "iso:country":"GB",
    "sg:address":"The Barclay Centre, University Of Warwick Science Park",
    "sg:city":"Coventry",
    "sg:classifiers":[
        {
            "category":"Professional",
            "subcategory":"Engineering",
            "type":"Services"
        }
    ],
    "sg:phone":"+44 24 7669 2141",
    "sg:postcode":"CV4 7EZ",
    "sg:province":"Warwickshire",
    "sg:tags":[
        "consulting",
        "engineer"
    ],
    "wof:name":"Organics Ltd.",
    "wof:placetype":"venue"
},
  "geometry": {"coordinates":[-1.5579940081,52.3859558105],"type":"Point"}
}