{
  "type": "Feature",
  "properties": {
    "addr:full":"3a Crown Buildings, The Green London Greater London E4 7EX",
    "addr:housenumber":"3a",
    "addr:postcode":"e4 7ex",
    "addr:street":"Crown Buildings The Green",
    "iso:country":"GB",
    "sg:address":"3a Crown Buildings, The Green",
    "sg:city":"London",
    "sg:classifiers":[
        {
            "category":"Wholesale",
            "subcategory":"Computers",
            "type":"Manufacturing & Wholesale Goods"
        },
        {
            "category":"Professional",
            "subcategory":"Computer Services",
            "type":"Services"
        }
    ],
    "sg:phone":"+44 20 8524 3595",
    "sg:postcode":"E4 7EX",
    "sg:province":"Greater London",
    "sg:tags":[
        "supplier",
        "consultant",
        "consumables"
    ],
    "wof:name":"F M K Ltd.",
    "wof:placetype":"venue"
},
  "geometry": {"coordinates":[0.00056,51.6304702759],"type":"Point"}
}