{
  "type": "Feature",
  "properties": {
    "addr:full":"Crestina House, Archbold Terrace Newcastle Upon Tyne Tyne and Wear NE2 1DB",
    "addr:postcode":"ne2 1db",
    "addr:street":"Archbold Terrace",
    "iso:country":"GB",
    "sg:address":"Crestina House, Archbold Terrace",
    "sg:city":"Newcastle Upon Tyne",
    "sg:classifiers":[
        {
            "category":"Professional",
            "subcategory":"Computer Services",
            "type":"Services"
        }
    ],
    "sg:phone":"+44 191 212 1244",
    "sg:postcode":"NE2 1DB",
    "sg:province":"Tyne and Wear",
    "sg:tags":[
        "consultant"
    ],
    "wof:name":"Informatics Ctec",
    "wof:placetype":"venue"
},
  "geometry": {"coordinates":[-1.60566,54.981468],"type":"Point"}
}