{
  "type": "Feature",
  "properties": {
    "iso:country":"GB",
    "sg:address":"3 Margravine Gardens",
    "sg:city":"London",
    "sg:classifiers":[
        {
            "category":"Shopping",
            "subcategory":"Pharmacy",
            "type":"Retail Goods"
        }
    ],
    "sg:phone":"+44 20 8748 6330",
    "sg:postcode":"W6 8RL",
    "sg:province":"Greater London",
    "sg:tags":[
        "pharmacist",
        "dispensing",
        "chemist"
    ],
    "wof:name":"Barons Pharmacy",
    "wof:placetype":"venue"
},
  "geometry": {"coordinates":[-0.213829,51.489998],"type":"Point"}
}