{
  "type": "Feature",
  "properties": {
    "addr:full":"Charles And Company, 3 Murray Street Llanelli Carmarthenshire SA15 1AQ",
    "addr:housenumber":"3",
    "addr:postcode":"sa15 1aq",
    "addr:street":"Murray Street",
    "iso:country":"GB",
    "sg:address":"Charles And Company, 3 Murray Street",
    "sg:city":"Llanelli",
    "sg:classifiers":[
        {
            "category":"Travel",
            "subcategory":"Travel Agent",
            "type":"Entertainment"
        }
    ],
    "sg:postcode":"SA15 1AQ",
    "sg:province":"Carmarthenshire",
    "wof:name":"Detour Solutions Ltd",
    "wof:placetype":"venue"
},
  "geometry": {"coordinates":[-4.150349,51.679138],"type":"Point"}
}