{
  "type": "Feature",
  "properties": {
    "iso:country":"GB",
    "sg:address":"188 Merton High Street",
    "sg:city":"London",
    "sg:classifiers":[
        {
            "category":"Shopping",
            "subcategory":"Tobacco",
            "type":"Retail Goods"
        }
    ],
    "sg:phone":"+44 20 8542 6256",
    "sg:postcode":"SW19 1AY",
    "sg:province":"Greater London",
    "sg:tags":[
        "confectioner",
        "tobacconist"
    ],
    "wof:name":"Peter Kent (Tobacconists) Ltd.",
    "wof:placetype":"venue"
},
  "geometry": {"coordinates":[-0.189892,51.415825],"type":"Point"}
}