{
  "type": "Feature",
  "properties": {
    "addr:full":"11 Hewett Rd Fareham Hampshire PO14 4JQ",
    "addr:housenumber":"11",
    "addr:postcode":"po14 4jq",
    "addr:street":"Hewett Rd",
    "iso:country":"GB",
    "sg:address":"11 Hewett Rd",
    "sg:city":"Fareham",
    "sg:classifiers":[
        {
            "category":"Building & Trades",
            "subcategory":"Construction",
            "type":"Services"
        }
    ],
    "sg:phone":"+44 1329 847086",
    "sg:postcode":"PO14 4JQ",
    "sg:province":"Hampshire",
    "sg:tags":[
        "joiner",
        "carpenter"
    ],
    "wof:name":"David Purkiss & Son",
    "wof:placetype":"venue"
},
  "geometry": {"coordinates":[-1.237068,50.844524],"type":"Point"}
}