{
  "type": "Feature",
  "properties": {
    "addr:full":"Targeting House, Gadbrook Park, Rudheath Northwich Cheshire CW9 7UZ",
    "addr:postcode":"cw9 7uz",
    "addr:street":"Gadbrook Park",
    "iso:country":"GB",
    "sg:address":"Targeting House, Gadbrook Park, Rudheath",
    "sg:city":"Northwich",
    "sg:classifiers":[
        {
            "category":"Professional",
            "subcategory":"Engineering",
            "type":"Services"
        }
    ],
    "sg:phone":"+44 1606 815100",
    "sg:postcode":"CW9 7UZ",
    "sg:province":"Cheshire",
    "sg:tags":[
        "chemical",
        "engineer"
    ],
    "wof:name":"Linnhoff March Ltd",
    "wof:placetype":"venue"
},
  "geometry": {"coordinates":[-2.4851369858,53.2480392456],"type":"Point"}
}