{
  "type": "Feature",
  "properties": {
    "addr:full":"24 Mallorie Park Drive Ripon North Yorkshire HG4 2QD",
    "addr:housenumber":"24",
    "addr:postcode":"hg4 2qd",
    "addr:street":"Mallorie Park Drive",
    "iso:country":"GB",
    "sg:address":"24 Mallorie Park Drive",
    "sg:city":"Ripon",
    "sg:classifiers":[
        {
            "category":"Professional",
            "subcategory":"Engineering",
            "type":"Services"
        }
    ],
    "sg:phone":"+44 1765 602174",
    "sg:postcode":"HG4 2QD",
    "sg:province":"North Yorkshire",
    "sg:tags":[
        "agricultural",
        "engineer"
    ],
    "wof:name":"M & V Gatford",
    "wof:placetype":"venue"
},
  "geometry": {"coordinates":[-1.5338020325,54.1332855225],"type":"Point"}
}