{
  "type": "Feature",
  "properties": {
    "iso:country":"GB",
    "sg:address":"3 Sarsden Close, Chadlington",
    "sg:city":"Chipping Norton",
    "sg:classifiers":[
        {
            "category":"Retail",
            "subcategory":"Auto Repair",
            "type":"Services"
        }
    ],
    "sg:phone":"+44 1608 676869",
    "sg:postcode":"OX7 3LJ",
    "sg:province":"Gloucestershire",
    "sg:tags":[
        "body",
        "car"
    ],
    "wof:name":"Paint Technik",
    "wof:placetype":"venue"
},
  "geometry": {"coordinates":[-1.526508,51.896572],"type":"Point"}
}