{
  "type": "Feature",
  "properties": {
    "addr:full":"4th Floor, Ramillies Ho, 1-2 Ramillies S London Greater London W1F 7LN",
    "addr:housenumber":"4th floor ramillies;1-2",
    "addr:postcode":"w1f 7ln",
    "iso:country":"GB",
    "sg:address":"4th Floor, Ramillies Ho, 1-2 Ramillies S",
    "sg:city":"London",
    "sg:classifiers":[
        {
            "category":"Professional",
            "subcategory":"Management & Consulting",
            "type":"Services"
        }
    ],
    "sg:postcode":"W1F 7LN",
    "sg:province":"Greater London",
    "sg:tags":[
        "marketing",
        "consultant"
    ],
    "wof:name":"Ford Hill & Friends Ltd",
    "wof:placetype":"venue"
},
  "geometry": {"coordinates":[-0.1387699991,51.5148086548],"type":"Point"}
}