{
  "type": "Feature",
  "properties": {
    "iso:country":"GB",
    "sg:address":"80 Burnfield Road, Giffnock",
    "sg:city":"Glasgow",
    "sg:classifiers":[
        {
            "category":"Autos & Motor Vehicles",
            "subcategory":"Automobile Sales",
            "type":"Retail Goods"
        }
    ],
    "sg:phone":"+44 141 633 1134",
    "sg:postcode":"G46 7PU",
    "sg:province":"East Renfrewshire",
    "sg:tags":[
        "auction",
        "car"
    ],
    "wof:name":"Scottish Motor Auction Group",
    "wof:placetype":"venue"
},
  "geometry": {"coordinates":[-4.29874,55.809326],"type":"Point"}
}