{
  "type": "Feature",
  "properties": {
    "iso:country":"GB",
    "sg:address":"Andrea Ho, 1st Floor 109-111 Humberstone Rd",
    "sg:city":"Leicester",
    "sg:classifiers":[
        {
            "category":"Shopping",
            "subcategory":"Clothing, Apparel, & Fashions",
            "type":"Retail Goods"
        }
    ],
    "sg:phone":"+44 116 251 0031",
    "sg:postcode":"LE5 3AN",
    "sg:province":"Leicestershire",
    "sg:tags":[
        "clothing",
        "fabric"
    ],
    "wof:name":"K.H.M Fashions",
    "wof:placetype":"venue"
},
  "geometry": {"coordinates":[-1.121819973,52.6377296448],"type":"Point"}
}