{
  "type": "Feature",
  "properties": {
    "addr:full":"Well Lane, Clare Sudbury Essex CO10 8NH",
    "addr:postcode":"co10 8nh",
    "addr:street":"Well Lane",
    "iso:country":"GB",
    "sg:address":"Well Lane, Clare",
    "sg:city":"Sudbury",
    "sg:classifiers":[
        {
            "category":"Restaurant",
            "type":"Food & Drink"
        }
    ],
    "sg:phone":"+44 1787 278148",
    "sg:postcode":"CO10 8NH",
    "sg:province":"Essex",
    "wof:name":"THE PEPPERMILL RESTAURANT",
    "wof:placetype":"venue"
},
  "geometry": {"coordinates":[0.5812510252,52.080493927],"type":"Point"}
}