{
  "type": "Feature",
  "properties": {
    "addr:full":"Cilau Farm Goodwick Pembrokeshire SA64 0HF",
    "addr:postcode":"sa64 0hf",
    "iso:country":"GB",
    "sg:address":"Cilau Farm",
    "sg:city":"Goodwick",
    "sg:classifiers":[
        {
            "category":"Farming",
            "subcategory":"Dairy Farm",
            "type":"Manufacturing & Wholesale Goods"
        }
    ],
    "sg:phone":"+44 1348 872278",
    "sg:postcode":"SA64 0HF",
    "sg:province":"Pembrokeshire",
    "wof:name":"E T & W R E  Thomas",
    "wof:placetype":"venue"
},
  "geometry": {"coordinates":[-4.997849,52.000923],"type":"Point"}
}