{
  "type": "Feature",
  "properties": {
    "iso:country":"GB",
    "sg:address":"Autumn Cottage, Musket Lane, Hollingbourne",
    "sg:city":"Maidstone",
    "sg:classifiers":[
        {
            "category":"Professional",
            "subcategory":"Accounting & Tax Preparation",
            "type":"Services"
        }
    ],
    "sg:phone":"+44 1622 880580",
    "sg:postcode":"ME17 1UY",
    "sg:province":"Kent",
    "sg:tags":[
        "accountant"
    ],
    "wof:name":"Peter Lee & Co",
    "wof:placetype":"venue"
},
  "geometry": {"coordinates":[0.641254,51.266026],"type":"Point"}
}