{
  "type": "Feature",
  "properties": {
    "addr:full":"7 Arkwright Street, Wirksworth Matlock Derbyshire DE4 4EE",
    "addr:housenumber":"7",
    "addr:postcode":"de4 4ee",
    "addr:street":"Arkwright Street",
    "iso:country":"GB",
    "sg:address":"7 Arkwright Street, Wirksworth",
    "sg:city":"Matlock",
    "sg:classifiers":[
        {
            "category":"Wholesale",
            "subcategory":"Scrap",
            "type":"Manufacturing & Wholesale Goods"
        }
    ],
    "sg:postcode":"DE4 4EE",
    "sg:province":"Derbyshire",
    "sg:tags":[
        "waste",
        "metal"
    ],
    "wof:name":"C Jones",
    "wof:placetype":"venue"
},
  "geometry": {"coordinates":[-1.577256,53.078186],"type":"Point"}
}