{
  "type": "Feature",
  "properties": {
    "iso:country":"GB",
    "sg:address":"Mercury House, 15 Princewood Road",
    "sg:city":"Corby",
    "sg:classifiers":[
        {
            "category":"Wholesale",
            "subcategory":"Toys & Hobbies",
            "type":"Manufacturing & Wholesale Goods"
        }
    ],
    "sg:postcode":"NN17 4AY",
    "sg:province":"Northamptonshire",
    "sg:tags":[
        "balloon",
        "novelty"
    ],
    "wof:name":"Balloon Supply Co",
    "wof:placetype":"venue"
},
  "geometry": {"coordinates":[-0.703108,52.510693],"type":"Point"}
}