{
  "type": "Feature",
  "properties": {
    "iso:country":"GB",
    "sg:address":"1 The Broadway",
    "sg:city":"Woodford Green",
    "sg:classifiers":[
        {
            "category":"Professional",
            "subcategory":"Art Services",
            "type":"Services"
        }
    ],
    "sg:phone":"+44 20 8505 2226",
    "sg:postcode":"IG8 0HL",
    "sg:province":"Essex",
    "sg:tags":[
        "framing"
    ],
    "wof:name":"Lev, Michael,",
    "wof:placetype":"venue"
},
  "geometry": {"coordinates":[0.0334360003,51.6080932617],"type":"Point"}
}