{
  "type": "Feature",
  "properties": {
    "iso:country":"GB",
    "sg:address":"35 Froghall Road",
    "sg:city":"Aberdeen",
    "sg:classifiers":[
        {
            "category":"Autos & Motor Vehicles",
            "subcategory":"Auto Supplies",
            "type":"Retail Goods"
        }
    ],
    "sg:phone":"+44 1224 633186",
    "sg:postcode":"AB24 3JL",
    "sg:province":"Aberdeen City",
    "sg:tags":[
        "car",
        "audio"
    ],
    "wof:name":"Radio Stereo Services",
    "wof:placetype":"venue"
},
  "geometry": {"coordinates":[-2.101461,57.157227],"type":"Point"}
}