{
  "type": "Feature",
  "properties": {
    "addr:full":"29 Colonnade, Grenville Street London Greater London WC1N 1JA",
    "addr:housenumber":"29",
    "addr:postcode":"wc1n 1ja",
    "addr:street":"Colonnade Grenville Street",
    "iso:country":"GB",
    "sg:address":"29 Colonnade, Grenville Street",
    "sg:city":"London",
    "sg:classifiers":[
        {
            "category":"Building & Trades",
            "subcategory":"Construction",
            "type":"Services"
        }
    ],
    "sg:phone":"+44 20 7837 0221",
    "sg:postcode":"WC1N 1JA",
    "sg:province":"Greater London",
    "sg:tags":[
        "decorator",
        "painter"
    ],
    "wof:name":"Frederick Cope & Co. Ltd.",
    "wof:placetype":"venue"
},
  "geometry": {"coordinates":[-0.1240279973,51.5227813721],"type":"Point"}
}