{
  "type": "Feature",
  "properties": {
    "addr:full":"Queen Street Newport Newport NP20 2EB",
    "addr:postcode":"np20 2eb",
    "addr:street":"Queen Street",
    "iso:country":"GB",
    "sg:address":"Queen Street",
    "sg:city":"Newport",
    "sg:classifiers":[
        {
            "category":"Organizations",
            "subcategory":"Membership Organization",
            "type":"Services"
        }
    ],
    "sg:phone":"+44 1633 265258",
    "sg:postcode":"NP20 2EB",
    "sg:province":"Newport",
    "sg:tags":[
        "club"
    ],
    "wof:name":"The Royal British Legion",
    "wof:placetype":"venue"
},
  "geometry": {"coordinates":[-2.994249,51.581894],"type":"Point"}
}