{
  "type": "Feature",
  "properties": {
    "iso:country":"GB",
    "sg:address":"18 English Road, Freemantle",
    "sg:city":"Southampton",
    "sg:classifiers":[
        {
            "category":"Bars & Pubs",
            "type":"Food & Drink"
        },
        {
            "category":"Community Center",
            "subcategory":"Social",
            "type":"Public Place"
        }
    ],
    "sg:phone":"+44 23 8032 0620",
    "sg:postcode":"SO15 8QF",
    "sg:province":"Hampshire",
    "sg:tags":[
        "pubs",
        "house",
        "inn",
        "activity"
    ],
    "wof:name":"The Englishman Inn",
    "wof:placetype":"venue"
},
  "geometry": {"coordinates":[-1.434966,50.918373],"type":"Point"}
}