{
  "type": "Feature",
  "properties": {
    "addr:full":"7 Coltsfoot Drive Horsham West Sussex RH12 5FN",
    "addr:housenumber":"7",
    "addr:postcode":"rh12 5fn",
    "addr:street":"Coltsfoot Drive",
    "iso:country":"GB",
    "sg:address":"7 Coltsfoot Drive",
    "sg:city":"Horsham",
    "sg:classifiers":[
        {
            "category":"Personal",
            "subcategory":"Beauty Salon",
            "type":"Services"
        },
        {
            "category":"Personal",
            "subcategory":"Barber",
            "type":"Services"
        }
    ],
    "sg:phone":"+44 1403 255555",
    "sg:postcode":"RH12 5FN",
    "sg:province":"West Sussex",
    "sg:tags":[
        "unisex",
        "hairdresser"
    ],
    "wof:name":"Studio 2",
    "wof:placetype":"venue"
},
  "geometry": {"coordinates":[-0.315941,51.078838],"type":"Point"}
}