{
  "type": "Feature",
  "properties": {
    "iso:country":"GB",
    "sg:address":"15 Sydes Brae, High Blantyre",
    "sg:city":"Glasgow",
    "sg:classifiers":[
        {
            "category":"Home & Garden",
            "subcategory":"Home Furnishings",
            "type":"Retail Goods"
        }
    ],
    "sg:phone":"+44 1698 712211",
    "sg:postcode":"G72 0TL",
    "sg:province":"South Lanarkshire",
    "sg:tags":[
        "merchant",
        "diy",
        "decorators'"
    ],
    "wof:name":"I O B Decorators Ltd.",
    "wof:placetype":"venue"
},
  "geometry": {"coordinates":[-4.106512,55.781605],"type":"Point"}
}