{
  "type": "Feature",
  "properties": {
    "addr:full":"Westminster Tower, 3 Albert Embankment Southwark Greater London SE1 7SW",
    "addr:housenumber":"3",
    "addr:postcode":"se1 7sw",
    "addr:street":"Albert Embankment",
    "iso:country":"GB",
    "sg:address":"Westminster Tower, 3 Albert Embankment",
    "sg:city":"Southwark",
    "sg:classifiers":[
        {
            "category":"Professional",
            "subcategory":"Business Services",
            "type":"Services"
        }
    ],
    "sg:phone":"+44 20 7793 3050",
    "sg:postcode":"SE1 7SW",
    "sg:province":"Greater London",
    "sg:tags":[
        "trade"
    ],
    "wof:name":"Association for Instrumentation, Control, Automation (Gambica)",
    "wof:placetype":"venue"
},
  "geometry": {"coordinates":[-0.12087,51.493698],"type":"Point"}
}