{
  "type": "Feature",
  "properties": {
    "addr:full":"10 Craighill Gardens Edinburgh City of Edinburgh EH10 5PY",
    "addr:housenumber":"10",
    "addr:postcode":"eh10 5py",
    "addr:street":"Craighill Gardens",
    "iso:country":"GB",
    "sg:address":"10 Craighill Gardens",
    "sg:city":"Edinburgh",
    "sg:classifiers":[
        {
            "category":"Sports & Exercise",
            "subcategory":"Golf",
            "type":"Entertainment"
        }
    ],
    "sg:phone":"+44 131 447 1219",
    "sg:postcode":"EH10 5PY",
    "sg:province":"City of Edinburgh",
    "sg:tags":[
        "club",
        "course",
        "equipment"
    ],
    "wof:name":"Merchants of Edinburgh Golf Club",
    "wof:placetype":"venue"
},
  "geometry": {"coordinates":[-3.2226920128,55.920627594],"type":"Point"}
}