{
  "type": "Feature",
  "properties": {
    "addr:full":"Glebe Farm, Abingdon Road, Standlake Witney Oxfordshire OX29 7QH",
    "addr:postcode":"ox29 7qh",
    "addr:street":"Abingdon Road",
    "iso:country":"GB",
    "sg:address":"Glebe Farm, Abingdon Road, Standlake",
    "sg:city":"Witney",
    "sg:classifiers":[
        {
            "category":"Farming",
            "subcategory":"Farm",
            "type":"Manufacturing & Wholesale Goods"
        }
    ],
    "sg:postcode":"OX29 7QH",
    "sg:province":"Oxfordshire",
    "sg:tags":[
        "mixed",
        "crop"
    ],
    "wof:name":"Bernard E Costar",
    "wof:placetype":"venue"
},
  "geometry": {"coordinates":[-1.424509,51.728374],"type":"Point"}
}