{
  "type": "Feature",
  "properties": {
    "iso:country":"GB",
    "sg:address":"2nd Floor, Wembly Point",
    "sg:city":"Wembley",
    "sg:classifiers":[
        {
            "category":"Professional",
            "subcategory":"Accounting & Tax Preparation",
            "type":"Services"
        }
    ],
    "sg:phone":"+44 20 8900 9456",
    "sg:postcode":"HA9 6XH",
    "sg:province":"Greater London",
    "sg:tags":[
        "accountant",
        "chartered"
    ],
    "wof:name":"Andrew Sharma & Co",
    "wof:placetype":"venue"
},
  "geometry": {"coordinates":[-0.287004,51.553551],"type":"Point"}
}