{
  "type": "Feature",
  "properties": {
    "addr:full":"Chambers Manor, Epping Green Epping Essex CM16 6PR",
    "addr:postcode":"cm16 6pr",
    "iso:country":"GB",
    "sg:address":"Chambers Manor, Epping Green",
    "sg:city":"Epping",
    "sg:classifiers":[
        {
            "category":"Home & Garden",
            "subcategory":"Garden Supply",
            "type":"Retail Goods"
        }
    ],
    "sg:postcode":"CM16 6PR",
    "sg:province":"Essex",
    "sg:tags":[
        "bulb",
        "grower"
    ],
    "wof:name":"George Padfield Ltd.",
    "wof:placetype":"venue"
},
  "geometry": {"coordinates":[0.079843998,51.7198524475],"type":"Point"}
}