{
  "type": "Feature",
  "properties": {
    "iso:country":"GB",
    "sg:address":"29 Buttermarket Street",
    "sg:city":"Warrington",
    "sg:classifiers":[
        {
            "category":"Banks & Credit Unions",
            "subcategory":"Financial Services",
            "type":"Services"
        }
    ],
    "sg:phone":"+44 1925 418771",
    "sg:postcode":"WA1 2LY",
    "sg:province":"Cheshire",
    "sg:tags":[
        "building",
        "society"
    ],
    "wof:name":"Cheshire Building Society",
    "wof:placetype":"venue"
},
  "geometry": {"coordinates":[-2.592073,53.389736],"type":"Point"}
}