{
  "type": "Feature",
  "properties": {
    "addr:full":"9 Connaught Close, Connaught Gardens East Clacton On Sea Essex CO15 6HZ",
    "addr:housenumber":"9",
    "addr:postcode":"co15 6hz",
    "addr:street":"Connaught Close Connaught Gardens East Clacton",
    "iso:country":"GB",
    "sg:address":"9 Connaught Close, Connaught Gardens East",
    "sg:city":"Clacton On Sea",
    "sg:classifiers":[
        {
            "category":"Building & Trades",
            "subcategory":"Construction",
            "type":"Services"
        }
    ],
    "sg:phone":"+44 1255 428808",
    "sg:postcode":"CO15 6HZ",
    "sg:province":"Essex",
    "sg:tags":[
        "decorator",
        "painter"
    ],
    "wof:name":"Turners",
    "wof:placetype":"venue"
},
  "geometry": {"coordinates":[1.1713140011,51.7949333191],"type":"Point"}
}