{
  "type": "Feature",
  "properties": {
    "iso:country":"GB",
    "sg:address":"18 Fernhurst Road",
    "sg:city":"Ashford",
    "sg:classifiers":[
        {
            "category":"Education",
            "subcategory":"Special Training",
            "type":"Public Place"
        },
        {
            "category":"Professional",
            "subcategory":"Art Services",
            "type":"Services"
        }
    ],
    "sg:phone":"+44 1784 247951",
    "sg:postcode":"TW15 1AH",
    "sg:province":"Greater London",
    "sg:tags":[
        "martial",
        "instruction"
    ],
    "wof:name":"HAPKIDO",
    "wof:placetype":"venue"
},
  "geometry": {"coordinates":[-0.44473,51.433517],"type":"Point"}
}