{
  "type": "Feature",
  "properties": {
    "iso:country":"GB",
    "sg:address":"11 Maunsel Street",
    "sg:city":"London",
    "sg:classifiers":[
        {
            "category":"Banks & Credit Unions",
            "subcategory":"Financial Services",
            "type":"Services"
        }
    ],
    "sg:phone":"+44 20 7931 0001",
    "sg:postcode":"SW1P 2QL",
    "sg:province":"Greater London",
    "sg:tags":[
        "adviser"
    ],
    "wof:name":"Montagu-Smith & Co. Ltd.",
    "wof:placetype":"venue"
},
  "geometry": {"coordinates":[-0.133165,51.494236],"type":"Point"}
}