{
  "type": "Feature",
  "properties": {
    "iso:country":"GB",
    "sg:address":"Travellers Lane, Welham Green, North Mymms",
    "sg:city":"Hatfield",
    "sg:classifiers":[
        {
            "category":"Retail",
            "subcategory":"Auto Repair",
            "type":"Services"
        }
    ],
    "sg:phone":"+44 1707 266237",
    "sg:postcode":"AL9 7HF",
    "sg:province":"Hertfordshire",
    "sg:tags":[
        "car",
        "repairer",
        "commercial",
        "bodybuilder",
        "vehicle"
    ],
    "wof:name":"Wright Signs & Coachworks Ltd",
    "wof:placetype":"venue"
},
  "geometry": {"coordinates":[-0.213064,51.738243103],"type":"Point"}
}