{
  "type": "Feature",
  "properties": {
    "iso:country":"GB",
    "sg:address":"21 Walter Rd",
    "sg:city":"Swansea",
    "sg:classifiers":[
        {
            "category":"Real Estate",
            "subcategory":"Real Estate Agent",
            "type":"Services"
        }
    ],
    "sg:phone":"+44 1639 798200",
    "sg:postcode":"SA1 5NQ",
    "sg:province":"Neath Port Talbot",
    "wof:name":"Peter Morgan",
    "wof:placetype":"venue"
},
  "geometry": {"coordinates":[-3.954995,51.61972],"type":"Point"}
}