{
  "type": "Feature",
  "properties": {
    "iso:country":"GB",
    "sg:address":"The Lodge, Middleton Road",
    "sg:city":"Pickering",
    "sg:classifiers":[
        {
            "category":"Fast Food",
            "type":"Food & Drink"
        },
        {
            "category":"Travel",
            "subcategory":"Hotels & Motels",
            "type":"Entertainment"
        }
    ],
    "sg:postcode":"YO18 8NQ",
    "sg:province":"North Yorkshire",
    "sg:tags":[
        "away",
        "take"
    ],
    "wof:name":"The Lodge Bistro & Hotel",
    "wof:placetype":"venue"
},
  "geometry": {"coordinates":[-0.791588,54.252254],"type":"Point"}
}