{
  "type": "Feature",
  "properties": {
    "addr:full":"26 North Street Bridlington East Riding of Yorkshire YO15 2DY",
    "addr:housenumber":"26",
    "addr:postcode":"yo15 2dy",
    "addr:street":"North Street",
    "iso:country":"GB",
    "sg:address":"26 North Street",
    "sg:city":"Bridlington",
    "sg:classifiers":[
        {
            "category":"Professional",
            "subcategory":"Printing & Photocopies",
            "type":"Services"
        }
    ],
    "sg:postcode":"YO15 2DY",
    "sg:province":"East Riding of Yorkshire",
    "sg:tags":[
        "printer"
    ],
    "wof:name":"Quay Printing Press",
    "wof:placetype":"venue"
},
  "geometry": {"coordinates":[-0.19147,54.083664],"type":"Point"}
}