{
  "type": "Feature",
  "properties": {
    "iso:country":"GB",
    "sg:address":"27a London Road",
    "sg:city":"Alderley Edge",
    "sg:classifiers":[
        {
            "category":"Farming",
            "subcategory":"Fish & Marine Products",
            "type":"Manufacturing & Wholesale Goods"
        }
    ],
    "sg:phone":"+44 1625 582296",
    "sg:postcode":"SK9 7JT",
    "sg:province":"Cheshire",
    "sg:tags":[
        "fishmonger"
    ],
    "wof:name":"R Taylor",
    "wof:placetype":"venue"
},
  "geometry": {"coordinates":[-2.2360699177,53.3025474548],"type":"Point"}
}