{
  "type": "Feature",
  "properties": {
    "iso:country":"GB",
    "sg:address":"116 Brigg Road, Messingham",
    "sg:city":"Scunthorpe",
    "sg:classifiers":[
        {
            "category":"Professional",
            "type":"Services"
        },
        {
            "category":"Banks & Credit Unions",
            "subcategory":"Investment Brokerage",
            "type":"Services"
        }
    ],
    "sg:phone":"+44 1724 762747",
    "sg:postcode":"DN17 3RB",
    "sg:province":"Lincolnshire",
    "sg:tags":[
        "farm",
        "agricultural",
        "contractor"
    ],
    "wof:name":"H REG BROWN",
    "wof:placetype":"venue"
},
  "geometry": {"coordinates":[-0.643165,53.525417],"type":"Point"}
}