{
  "type": "Feature",
  "properties": {
    "addr:full":"Dental Surgery, 32 Prescott St Halifax West Yorkshire HX1 2QW",
    "addr:housenumber":"32",
    "addr:postcode":"hx1 2qw",
    "addr:street":"Prescott St",
    "iso:country":"GB",
    "sg:address":"Dental Surgery, 32 Prescott St",
    "sg:city":"Halifax",
    "sg:classifiers":[
        {
            "category":"Health Services",
            "subcategory":"Dentist",
            "type":"Services"
        }
    ],
    "sg:phone":"+44 1422 354147",
    "sg:postcode":"HX1 2QW",
    "sg:province":"West Yorkshire",
    "wof:name":"G Brooks",
    "wof:placetype":"venue"
},
  "geometry": {"coordinates":[-1.8622239828,53.7212333679],"type":"Point"}
}