{
  "type": "Feature",
  "properties": {
    "addr:full":"Little Horsted Uckfield East Sussex TN22 5TS",
    "addr:postcode":"tn22 5ts",
    "iso:country":"GB",
    "sg:address":"Little Horsted",
    "sg:city":"Uckfield",
    "sg:classifiers":[
        {
            "category":"Travel",
            "subcategory":"Hotels & Motels",
            "type":"Entertainment"
        }
    ],
    "sg:phone":"+44 1825 750581",
    "sg:postcode":"TN22 5TS",
    "sg:province":"East Sussex",
    "wof:name":"Horsted Place Ltd",
    "wof:placetype":"venue"
},
  "geometry": {"coordinates":[0.0916699991,50.9456710815],"type":"Point"}
}