{
  "type": "Feature",
  "properties": {
    "iso:country":"GB",
    "sg:address":"76 Wisbech Road",
    "sg:city":"March",
    "sg:classifiers":[
        {
            "category":"Professional",
            "subcategory":"Engineering",
            "type":"Services"
        }
    ],
    "sg:postcode":"PE15 8EF",
    "sg:province":"Cambridgeshire",
    "sg:tags":[
        "gas",
        "engineer"
    ],
    "wof:name":"P G Plumbing",
    "wof:placetype":"venue"
},
  "geometry": {"coordinates":[0.075568,52.555588],"type":"Point"}
}