{
  "type": "Feature",
  "properties": {
    "addr:full":"10 St Peters Place, Eccles Aylesford Kent ME20 7TF",
    "addr:housenumber":"10",
    "addr:postcode":"me20 7tf",
    "addr:street":"St Peters Place",
    "iso:country":"GB",
    "sg:address":"10 St Peters Place, Eccles",
    "sg:city":"Aylesford",
    "sg:classifiers":[
        {
            "category":"Wholesale",
            "subcategory":"Electrical",
            "type":"Manufacturing & Wholesale Goods"
        }
    ],
    "sg:postcode":"ME20 7TF",
    "sg:province":"Kent",
    "sg:tags":[
        "equipment",
        "refrigeration"
    ],
    "wof:name":"M D M Refridgeration",
    "wof:placetype":"venue"
},
  "geometry": {"coordinates":[0.478027,51.319798],"type":"Point"}
}