{
  "type": "Feature",
  "properties": {
    "addr:full":"14 Hugh Rd Coventry Warwickshire CV3 1AD",
    "addr:housenumber":"14",
    "addr:postcode":"cv3 1ad",
    "addr:street":"Hugh Rd",
    "iso:country":"GB",
    "sg:address":"14 Hugh Rd",
    "sg:city":"Coventry",
    "sg:classifiers":[
        {
            "category":"Building & Trades",
            "subcategory":"Construction",
            "type":"Services"
        }
    ],
    "sg:phone":"+44 24 7645 0660",
    "sg:postcode":"CV3 1AD",
    "sg:province":"Warwickshire",
    "sg:tags":[
        "builder"
    ],
    "wof:name":"Boyle,Brendan,",
    "wof:placetype":"venue"
},
  "geometry": {"coordinates":[-1.4860509634,52.4040718079],"type":"Point"}
}