{
  "type": "Feature",
  "properties": {
    "addr:full":"7 Fernlea Leicester Leicestershire LE19 3WN",
    "addr:housenumber":"7",
    "addr:postcode":"le19 3wn",
    "addr:street":"Fernlea",
    "iso:country":"GB",
    "sg:address":"7 Fernlea",
    "sg:city":"Leicester",
    "sg:classifiers":[
        {
            "category":"Shopping",
            "subcategory":"Computers & Home Electronics",
            "type":"Retail Goods"
        }
    ],
    "sg:postcode":"LE19 3WN",
    "sg:province":"Leicestershire",
    "sg:tags":[
        "aerial",
        "television",
        "radio"
    ],
    "wof:name":"Multi Aerial Services (Midlands) Ltd.",
    "wof:placetype":"venue"
},
  "geometry": {"coordinates":[-1.220636,52.578247],"type":"Point"}
}