{
  "type": "Feature",
  "properties": {
    "addr:full":"28 Hare Hill Addlestone Surrey KT15 1DT",
    "addr:housenumber":"28",
    "addr:postcode":"kt15 1dt",
    "addr:street":"Hare Hill",
    "iso:country":"GB",
    "sg:address":"28 Hare Hill",
    "sg:city":"Addlestone",
    "sg:classifiers":[
        {
            "category":"Building & Trades",
            "subcategory":"Construction",
            "type":"Services"
        }
    ],
    "sg:postcode":"KT15 1DT",
    "sg:province":"Surrey",
    "sg:tags":[
        "glazier",
        "decorator",
        "painter"
    ],
    "wof:name":"Just Decorating",
    "wof:placetype":"venue"
},
  "geometry": {"coordinates":[-0.518164,51.365734],"type":"Point"}
}