{
  "type": "Feature",
  "properties": {
    "addr:full":"The Street, Hamstreet Ashford Kent TN26 2JH",
    "addr:postcode":"tn26 2jh",
    "addr:street":"The Street",
    "iso:country":"GB",
    "sg:address":"The Street, Hamstreet",
    "sg:city":"Ashford",
    "sg:classifiers":[
        {
            "category":"Food & Beverages",
            "subcategory":"Candy",
            "type":"Retail Goods"
        }
    ],
    "sg:postcode":"TN26 2JH",
    "sg:province":"Kent",
    "sg:tags":[
        "confectioner"
    ],
    "wof:name":"The Chocolate Box (Ham Street) Ltd.",
    "wof:placetype":"venue"
},
  "geometry": {"coordinates":[0.787365,51.035706],"type":"Point"}
}