{
  "type": "Feature",
  "properties": {
    "addr:full":"301 Imex Ho 40 Princess St Manchester Greater Manchester M1 6DE",
    "addr:housenumber":"301;40",
    "addr:postcode":"m1 6de",
    "addr:street":"Imex Ho;Princess St",
    "iso:country":"GB",
    "sg:address":"301 Imex Ho 40 Princess St",
    "sg:city":"Manchester",
    "sg:classifiers":[
        {
            "category":"Shopping",
            "subcategory":"Discount & Variety Stores",
            "type":"Retail Goods"
        }
    ],
    "sg:phone":"+44 161 236 8183",
    "sg:postcode":"M1 6DE",
    "sg:province":"Greater Manchester",
    "sg:tags":[
        "centre"
    ],
    "wof:name":"A B C Card Club Ltd",
    "wof:placetype":"venue"
},
  "geometry": {"coordinates":[-2.23964,53.4772],"type":"Point"}
}