{
  "type": "Feature",
  "properties": {
    "iso:country":"GB",
    "sg:address":"P O Box 3025",
    "sg:city":"Bournemouth",
    "sg:classifiers":[
        {
            "category":"Professional",
            "type":"Services"
        }
    ],
    "sg:postcode":"BH7 6ZQ",
    "sg:province":"Dorset",
    "sg:tags":[
        "relocation"
    ],
    "wof:name":"Area Relocating Services",
    "wof:placetype":"venue"
},
  "geometry": {"coordinates":[-1.82433,50.733398],"type":"Point"}
}