{
  "type": "Feature",
  "properties": {
    "addr:full":"May View, Blythe Road Hoddesdon Essex EN11 0BB",
    "addr:postcode":"en11 0bb",
    "addr:street":"May;Blythe Road",
    "iso:country":"GB",
    "sg:address":"May View, Blythe Road",
    "sg:city":"Hoddesdon",
    "sg:classifiers":[
        {
            "category":"Retail",
            "subcategory":"Laundry & Dry Cleaning",
            "type":"Services"
        }
    ],
    "sg:phone":"+44 1992 451143",
    "sg:postcode":"EN11 0BB",
    "sg:province":"Essex",
    "sg:tags":[
        "home",
        "ironing"
    ],
    "wof:name":"Press Gang",
    "wof:placetype":"venue"
},
  "geometry": {"coordinates":[-0.0132550001,51.7678413391],"type":"Point"}
}