{
  "type": "Feature",
  "properties": {
    "addr:full":"Unit 1, Walkham Business Park Plymouth Devon PL5 3LS",
    "addr:housenumber":"unit 1",
    "addr:postcode":"pl5 3ls",
    "addr:street":"Walkham Business Park",
    "iso:country":"GB",
    "sg:address":"Unit 1, Walkham Business Park",
    "sg:city":"Plymouth",
    "sg:classifiers":[
        {
            "category":"Shopping",
            "subcategory":"Clothing, Apparel, & Fashions",
            "type":"Retail Goods"
        }
    ],
    "sg:phone":"+44 1752 201617",
    "sg:postcode":"PL5 3LS",
    "sg:province":"Devon",
    "sg:tags":[
        "wear",
        "leisure"
    ],
    "wof:name":"Viking Sport & Leisure",
    "wof:placetype":"venue"
},
  "geometry": {"coordinates":[-4.160094,50.403671],"type":"Point"}
}