{
  "type": "Feature",
  "properties": {
    "iso:country":"GB",
    "sg:address":"B1-b11 Seedbed Centre, Avenue Road, Nechells",
    "sg:city":"Birmingham",
    "sg:classifiers":[
        {
            "category":"Manufacturing",
            "subcategory":"Rubber & Plastics",
            "type":"Manufacturing & Wholesale Goods"
        },
        {
            "category":"Wholesale",
            "subcategory":"Chemicals & Plastics",
            "type":"Manufacturing & Wholesale Goods"
        }
    ],
    "sg:phone":"+44 121 359 0084",
    "sg:postcode":"B7 4NT",
    "sg:province":"West Midlands",
    "sg:tags":[
        "mould",
        "injection",
        "moulding",
        "manufacturer"
    ],
    "wof:name":"C M A Mouldform",
    "wof:placetype":"venue"
},
  "geometry": {"coordinates":[-1.8807599545,52.494808197],"type":"Point"}
}