{
  "type": "Feature",
  "properties": {
    "iso:country":"GB",
    "sg:address":"Bromford Lane",
    "sg:city":"West Bromwich",
    "sg:classifiers":[
        {
            "category":"Organizations",
            "subcategory":"Community Association",
            "type":"Services"
        },
        {
            "category":"Organizations",
            "subcategory":"Membership Organization",
            "type":"Services"
        }
    ],
    "sg:phone":"+44 121 553 0223",
    "sg:postcode":"B70 7HW",
    "sg:province":"West Midlands",
    "sg:tags":[
        "club",
        "social"
    ],
    "wof:name":"Bromford Lane Gardeners Society",
    "wof:placetype":"venue"
},
  "geometry": {"coordinates":[-2.002823,52.513885],"type":"Point"}
}