{
  "type": "Feature",
  "properties": {
    "addr:full":"37 Pytchley Road Kettering Northamptonshire NN15 6ND",
    "addr:housenumber":"37",
    "addr:postcode":"nn15 6nd",
    "addr:street":"Pytchley Road",
    "iso:country":"GB",
    "sg:address":"37 Pytchley Road",
    "sg:city":"Kettering",
    "sg:classifiers":[
        {
            "category":"Autos & Motor Vehicles",
            "subcategory":"Auto Supplies",
            "type":"Retail Goods"
        },
        {
            "category":"Shopping",
            "type":"Retail Goods"
        }
    ],
    "sg:phone":"+44 1536 514400",
    "sg:postcode":"NN15 6ND",
    "sg:province":"Northamptonshire",
    "sg:tags":[
        "car",
        "part",
        "accessory"
    ],
    "wof:name":"Ultimate Design",
    "wof:placetype":"venue"
},
  "geometry": {"coordinates":[-0.7146430016,52.3848953247],"type":"Point"}
}