{
  "type": "Feature",
  "properties": {
    "addr:full":"3 Waterloo Street West Macclesfield Cheshire SK11 6PJ",
    "addr:housenumber":"3",
    "addr:postcode":"sk11 6pj",
    "addr:street":"Waterloo Street West",
    "iso:country":"GB",
    "sg:address":"3 Waterloo Street West",
    "sg:city":"Macclesfield",
    "sg:classifiers":[
        {
            "category":"Health Services",
            "subcategory":"Dentist",
            "type":"Services"
        }
    ],
    "sg:phone":"+44 1625 511131",
    "sg:postcode":"SK11 6PJ",
    "sg:province":"Cheshire",
    "sg:tags":[
        "technician",
        "dental"
    ],
    "wof:name":"Chris Wright Denture Services",
    "wof:placetype":"venue"
},
  "geometry": {"coordinates":[-2.1296200752,53.258605957],"type":"Point"}
}