{
  "type": "Feature",
  "properties": {
    "addr:full":"Smithy Lane, Bradley Stafford Staffordshire ST18 9DZ",
    "addr:postcode":"st18 9dz",
    "addr:street":"Smithy Lane",
    "iso:country":"GB",
    "sg:address":"Smithy Lane, Bradley",
    "sg:city":"Stafford",
    "sg:classifiers":[
        {
            "category":"Restaurant",
            "type":"Food & Drink"
        }
    ],
    "sg:phone":"+44 1785 780297",
    "sg:postcode":"ST18 9DZ",
    "sg:province":"Staffordshire",
    "wof:name":"The Red Lion Inn & Restaurant",
    "wof:placetype":"venue"
},
  "geometry": {"coordinates":[-2.17981,52.757969],"type":"Point"}
}