{
  "type": "Feature",
  "properties": {
    "addr:full":"Heights Farm, High Street, Slingsby York North Yorkshire YO62 4AE",
    "addr:postcode":"yo62 4ae",
    "addr:street":"Heights;High Street",
    "iso:country":"GB",
    "sg:address":"Heights Farm, High Street, Slingsby",
    "sg:city":"York",
    "sg:classifiers":[
        {
            "category":"Banks & Credit Unions",
            "subcategory":"Investment Brokerage",
            "type":"Services"
        }
    ],
    "sg:postcode":"YO62 4AE",
    "sg:province":"North Yorkshire",
    "sg:tags":[
        "contractor"
    ],
    "wof:name":"J E Clifford & Sons",
    "wof:placetype":"venue"
},
  "geometry": {"coordinates":[-0.933258,54.162136],"type":"Point"}
}