{
  "type": "Feature",
  "properties": {
    "addr:full":"Pendugwm, Llanfihangel Llanfyllin Shropshire SY22 5JF",
    "addr:postcode":"sy22 5jf",
    "addr:street":"Llanfyllin Shropshire",
    "iso:country":"GB",
    "sg:address":"Pendugwm, Llanfihangel",
    "sg:city":"Llanfyllin",
    "sg:classifiers":[
        {
            "category":"Farming",
            "subcategory":"Dairy Farm",
            "type":"Manufacturing & Wholesale Goods"
        }
    ],
    "sg:phone":"+44 1691 648430",
    "sg:postcode":"SY22 5JF",
    "sg:province":"Shropshire",
    "wof:name":"Idris G Evans & Sons",
    "wof:placetype":"venue"
},
  "geometry": {"coordinates":[-3.269958,52.764301],"type":"Point"}
}