{
  "type": "Feature",
  "properties": {
    "addr:full":"1040 Manchester Road, Bankfoot Bradford West Yorkshire BD5 8NW",
    "addr:housenumber":"1040",
    "addr:postcode":"bd5 8nw",
    "addr:street":"Manchester Road",
    "iso:country":"GB",
    "sg:address":"1040 Manchester Road, Bankfoot",
    "sg:city":"Bradford",
    "sg:classifiers":[
        {
            "category":"Food & Beverages",
            "subcategory":"Supermarket",
            "type":"Retail Goods"
        }
    ],
    "sg:phone":"+44 1274 307381",
    "sg:postcode":"BD5 8NW",
    "sg:province":"West Yorkshire",
    "wof:name":"Kwik Save Stores Ltd.",
    "wof:placetype":"venue"
},
  "geometry": {"coordinates":[-1.762854,53.769535],"type":"Point"}
}