{
  "type": "Feature",
  "properties": {
    "iso:country":"GB",
    "sg:address":"Woolmore Farm, Bowerhill",
    "sg:city":"Melksham",
    "sg:classifiers":[
        {
            "category":"Farming",
            "subcategory":"Dairy Farm",
            "type":"Manufacturing & Wholesale Goods"
        }
    ],
    "sg:phone":"+44 1225 704456",
    "sg:postcode":"SN12 6QZ",
    "sg:province":"Wiltshire",
    "sg:tags":[
        "farmer"
    ],
    "wof:name":"J R & E A Marston",
    "wof:placetype":"venue"
},
  "geometry": {"coordinates":[-2.1221280098,51.3611679077],"type":"Point"}
}