{
  "type": "Feature",
  "properties": {
    "addr:full":"30 Ship Street Brighton East Sussex BN1 1AD",
    "addr:housenumber":"30",
    "addr:postcode":"bn1 1ad",
    "addr:street":"Ship Street",
    "iso:country":"GB",
    "sg:address":"30 Ship Street",
    "sg:city":"Brighton",
    "sg:classifiers":[
        {
            "category":"Cafe",
            "type":"Food & Drink"
        }
    ],
    "sg:phone":"+44 1273 202106",
    "sg:postcode":"BN1 1AD",
    "sg:province":"East Sussex",
    "sg:tags":[
        "tea",
        "room"
    ],
    "wof:name":"Lanes Patisserie & Cafe",
    "wof:placetype":"venue"
},
  "geometry": {"coordinates":[-0.141834,50.822403],"type":"Point"}
}