{
  "type": "Feature",
  "properties": {
    "addr:full":"3a Union St Andover Hampshire SP10 1PA",
    "addr:housenumber":"3a",
    "addr:postcode":"sp10 1pa",
    "addr:street":"Union St",
    "iso:country":"GB",
    "sg:address":"3a Union St",
    "sg:city":"Andover",
    "sg:classifiers":[
        {
            "category":"Organizations",
            "subcategory":"Non-profit Organization",
            "type":"Services"
        }
    ],
    "sg:phone":"+44 1264 362944",
    "sg:postcode":"SP10 1PA",
    "sg:province":"Hampshire",
    "sg:tags":[
        "organisation",
        "voluntary",
        "charity"
    ],
    "wof:name":"The Baguette De Moet",
    "wof:placetype":"venue"
},
  "geometry": {"coordinates":[-1.476779,51.206493],"type":"Point"}
}