{
  "type": "Feature",
  "properties": {
    "iso:country":"GB",
    "sg:address":"2 Scott Lane, Riddlesden",
    "sg:city":"Keighley",
    "sg:classifiers":[
        {
            "category":"Professional",
            "type":"Services"
        }
    ],
    "sg:phone":"+44 1282 456467",
    "sg:postcode":"BD20 5BT",
    "sg:province":"North Yorkshire",
    "sg:tags":[
        "entertainer"
    ],
    "wof:name":"Mike King Entertainments",
    "wof:placetype":"venue"
},
  "geometry": {"coordinates":[-1.885747,53.878807],"type":"Point"}
}