{
  "type": "Feature",
  "properties": {
    "iso:country":"GB",
    "sg:address":"91 Eastham Village Rd",
    "sg:city":"Wirral",
    "sg:classifiers":[
        {
            "category":"Building & Trades",
            "subcategory":"Construction",
            "type":"Services"
        }
    ],
    "sg:phone":"+44 151 328 1000",
    "sg:postcode":"CH62 0AW",
    "sg:province":"Cheshire",
    "sg:tags":[
        "demolition",
        "contractor"
    ],
    "wof:name":"Heritage",
    "wof:placetype":"venue"
},
  "geometry": {"coordinates":[-2.9615879059,53.3158988953],"type":"Point"}
}