{
  "type": "Feature",
  "properties": {
    "addr:full":"232 Southport Road Southport Lancashire PR8 5LF",
    "addr:housenumber":"232",
    "addr:postcode":"pr8 5lf",
    "addr:street":"Southport Road",
    "iso:country":"GB",
    "sg:address":"232 Southport Road",
    "sg:city":"Southport",
    "sg:classifiers":[
        {
            "category":"Professional",
            "subcategory":"Art Services",
            "type":"Services"
        }
    ],
    "sg:phone":"+44 1704 880881",
    "sg:postcode":"PR8 5LF",
    "sg:province":"Lancashire",
    "sg:tags":[
        "graphic",
        "designer"
    ],
    "wof:name":"Prescott & Co",
    "wof:placetype":"venue"
},
  "geometry": {"coordinates":[-2.9496929646,53.6185684204],"type":"Point"}
}