{
  "type": "Feature",
  "properties": {
    "addr:full":"8 Gunville Road Newport Isle of Wight PO30 5FP",
    "addr:housenumber":"8",
    "addr:postcode":"po30 5fp",
    "addr:street":"Gunville Road",
    "iso:country":"GB",
    "sg:address":"8 Gunville Road",
    "sg:city":"Newport",
    "sg:classifiers":[
        {
            "category":"Insurance",
            "subcategory":"Insurance Agent",
            "type":"Services"
        }
    ],
    "sg:phone":"+44 1983 522290",
    "sg:postcode":"PO30 5FP",
    "sg:province":"Isle of Wight",
    "wof:name":"National Farmers Union Mutual Insurance Society Ltd.",
    "wof:placetype":"venue"
},
  "geometry": {"coordinates":[-1.3179420233,50.6935653687],"type":"Point"}
}