{
  "type": "Feature",
  "properties": {
    "iso:country":"GB",
    "sg:address":"8 Heriot Road",
    "sg:city":"London",
    "sg:classifiers":[
        {
            "category":"Real Estate",
            "subcategory":"Developer",
            "type":"Services"
        }
    ],
    "sg:phone":"+44 20 8202 0030",
    "sg:postcode":"NW4 2DG",
    "sg:province":"Greater London",
    "sg:tags":[
        "property"
    ],
    "wof:name":"Palmerston Properties Ltd.",
    "wof:placetype":"venue"
},
  "geometry": {"coordinates":[-0.220829,51.585201],"type":"Point"}
}