{
  "type": "Feature",
  "properties": {
    "iso:country":"GB",
    "sg:address":"Strathard Lane",
    "sg:city":"Milford Haven",
    "sg:classifiers":[
        {
            "category":"Taxi",
            "type":"Transportation"
        },
        {
            "category":"Military Area",
            "subcategory":"Air Force Base",
            "type":"Public Place"
        }
    ],
    "sg:phone":"+44 1646 695222",
    "sg:postcode":"SA73 3QU",
    "sg:province":"Pembrokeshire",
    "sg:tags":[
        "mini",
        "hire",
        "private",
        "cab"
    ],
    "wof:name":"A K Taxis",
    "wof:placetype":"venue"
},
  "geometry": {"coordinates":[-5.0270438194,51.7168083191],"type":"Point"}
}