{
  "type": "Feature",
  "properties": {
    "iso:country":"GB",
    "sg:address":"Winchester Road",
    "sg:city":"Alresford",
    "sg:classifiers":[
        {
            "category":"Food & Beverages",
            "subcategory":"Ethnic Foods",
            "type":"Retail Goods"
        }
    ],
    "sg:phone":"+44 1962 734080",
    "sg:postcode":"SO24 9EZ",
    "sg:province":"Hampshire",
    "sg:tags":[
        "merchant",
        "oil",
        "essential"
    ],
    "wof:name":"Melaleuca Plantations of Bungawalbyn Pty Ltd.",
    "wof:placetype":"venue"
},
  "geometry": {"coordinates":[-1.1784340143,51.0872497559],"type":"Point"}
}