{
  "type": "Feature",
  "properties": {
    "addr:full":"81 Euston Road Morecambe Lancashire LA4 5JY",
    "addr:housenumber":"81",
    "addr:postcode":"la4 5jy",
    "addr:street":"Euston Road",
    "iso:country":"GB",
    "sg:address":"81 Euston Road",
    "sg:city":"Morecambe",
    "sg:classifiers":[
        {
            "category":"Personal",
            "subcategory":"Tattoo Parlor",
            "type":"Services"
        }
    ],
    "sg:phone":"+44 1524 401411",
    "sg:postcode":"LA4 5JY",
    "sg:province":"Lancashire",
    "sg:tags":[
        "tattooing",
        "piercing",
        "artist"
    ],
    "wof:name":"The Tattoo Studio",
    "wof:placetype":"venue"
},
  "geometry": {"coordinates":[-2.8639259338,54.0717697144],"type":"Point"}
}