{
  "type": "Feature",
  "properties": {
    "iso:country":"GB",
    "sg:address":"Unit 4, County Lane, Warfield",
    "sg:city":"Bracknell",
    "sg:classifiers":[
        {
            "category":"Banks & Credit Unions",
            "subcategory":"Financial Services",
            "type":"Services"
        },
        {
            "category":"Real Estate",
            "subcategory":"Real Estate Agent",
            "type":"Services"
        }
    ],
    "sg:phone":"+44 1344 425555",
    "sg:postcode":"RG42 3JP",
    "sg:province":"Berkshire",
    "wof:name":"Prospect Financial Services",
    "wof:placetype":"venue"
},
  "geometry": {"coordinates":[-0.735311,51.427792],"type":"Point"}
}