{
  "type": "Feature",
  "properties": {
    "addr:full":"55 Drury Lane London Greater London WC2B 5SQ",
    "addr:housenumber":"55",
    "addr:postcode":"wc2b 5sq",
    "addr:street":"Drury Lane",
    "iso:country":"GB",
    "sg:address":"55 Drury Lane",
    "sg:city":"London",
    "sg:classifiers":[
        {
            "category":"Banks & Credit Unions",
            "subcategory":"Financial Services",
            "type":"Services"
        }
    ],
    "sg:postcode":"WC2B 5SQ",
    "sg:province":"Greater London",
    "sg:tags":[
        "consultant"
    ],
    "wof:name":"Clive Banks Music Limited",
    "wof:placetype":"venue"
},
  "geometry": {"coordinates":[-0.120089,51.513721],"type":"Point"}
}