{
  "type": "Feature",
  "properties": {
    "addr:full":"Beckwith Ho, 4 Beckwith Dr, Harrogate Rd Bradford West Yorkshire BD10 0ES",
    "addr:housenumber":"4",
    "addr:postcode":"bd10 0es",
    "addr:street":"Beckwith Dr Harrogate Rd",
    "iso:country":"GB",
    "sg:address":"Beckwith Ho, 4 Beckwith Dr, Harrogate Rd",
    "sg:city":"Bradford",
    "sg:classifiers":[
        {
            "category":"Real Estate",
            "subcategory":"Architect",
            "type":"Services"
        }
    ],
    "sg:phone":"+44 1274 611657",
    "sg:postcode":"BD10 0ES",
    "sg:province":"West Yorkshire",
    "sg:tags":[
        "technologist",
        "architectural"
    ],
    "wof:name":"Beckwith Design & Development Co",
    "wof:placetype":"venue"
},
  "geometry": {"coordinates":[-1.7583060265,53.7957382202],"type":"Point"}
}