{
  "type": "Feature",
  "properties": {
    "iso:country":"GB",
    "sg:address":"Oxford Rd",
    "sg:city":"Uxbridge",
    "sg:classifiers":[
        {
            "category":"Organizations",
            "subcategory":"Membership Organization",
            "type":"Services"
        }
    ],
    "sg:phone":"+44 1895 238717",
    "sg:postcode":"UB9 4DA",
    "sg:province":"Buckinghamshire",
    "sg:tags":[
        "club"
    ],
    "wof:name":"Denham United Football Club",
    "wof:placetype":"venue"
},
  "geometry": {"coordinates":[-0.491938,51.55724],"type":"Point"}
}