{
  "type": "Feature",
  "properties": {
    "iso:country":"GB",
    "sg:address":"451 Newark Road",
    "sg:city":"Lincoln",
    "sg:classifiers":[
        {
            "category":"Autos & Motor Vehicles",
            "subcategory":"Automobile Sales",
            "type":"Retail Goods"
        }
    ],
    "sg:postcode":"LN6 8RT",
    "sg:province":"Lincolnshire",
    "sg:tags":[
        "car"
    ],
    "wof:name":"Martins Motor Co.",
    "wof:placetype":"venue"
},
  "geometry": {"coordinates":[-0.559951,53.201942],"type":"Point"}
}