{
  "type": "Feature",
  "properties": {
    "addr:full":"29 High Petergate York North Yorkshire YO1 2HP",
    "addr:housenumber":"29",
    "addr:postcode":"yo1 2hp",
    "addr:street":"High Petergate",
    "iso:country":"GB",
    "sg:address":"29 High Petergate",
    "sg:city":"York",
    "sg:classifiers":[
        {
            "category":"Health Services",
            "subcategory":"Dentist",
            "type":"Services"
        }
    ],
    "sg:postcode":"YO1 2HP",
    "sg:province":"North Yorkshire",
    "wof:name":"K J McDermott",
    "wof:placetype":"venue"
},
  "geometry": {"coordinates":[-1.08303,53.96159],"type":"Point"}
}