{
  "type": "Feature",
  "properties": {
    "addr:full":"45 Base Green Crescent Sheffield Derbyshire S12 3FD",
    "addr:housenumber":"45",
    "addr:postcode":"s12 3fd",
    "addr:street":"Base Green Crescent",
    "iso:country":"GB",
    "sg:address":"45 Base Green Crescent",
    "sg:city":"Sheffield",
    "sg:classifiers":[
        {
            "category":"Building & Trades",
            "subcategory":"Construction",
            "type":"Services"
        }
    ],
    "sg:postcode":"S12 3FD",
    "sg:province":"Derbyshire",
    "sg:tags":[
        "roofing"
    ],
    "wof:name":"Paul Eshelby Roofing",
    "wof:placetype":"venue"
},
  "geometry": {"coordinates":[-1.420074,53.343872],"type":"Point"}
}