{
  "type": "Feature",
  "properties": {
    "addr:full":"16 Flansham Lane, Felpham Bognor Regis West Sussex PO22 6AB",
    "addr:housenumber":"16",
    "addr:postcode":"po22 6ab",
    "addr:street":"Flansham Lane",
    "iso:country":"GB",
    "sg:address":"16 Flansham Lane, Felpham",
    "sg:city":"Bognor Regis",
    "sg:classifiers":[
        {
            "category":"Home & Garden",
            "subcategory":"Home Furnishings",
            "type":"Retail Goods"
        }
    ],
    "sg:phone":"+44 1243 582277",
    "sg:postcode":"PO22 6AB",
    "sg:province":"West Sussex",
    "sg:tags":[
        "blind",
        "curtain",
        "fitting"
    ],
    "wof:name":"Angela Fearne Interiors",
    "wof:placetype":"venue"
},
  "geometry": {"coordinates":[-0.6365479827,50.7953872681],"type":"Point"}
}