{
  "type": "Feature",
  "properties": {
    "addr:full":"61 Barton Road, Worsley Manchester Greater Manchester M28 2GX",
    "addr:housenumber":"61",
    "addr:postcode":"m28 2gx",
    "addr:street":"Barton Road",
    "iso:country":"GB",
    "sg:address":"61 Barton Road, Worsley",
    "sg:city":"Manchester",
    "sg:classifiers":[
        {
            "category":"Shopping",
            "subcategory":"Musical Instruments",
            "type":"Retail Goods"
        }
    ],
    "sg:postcode":"M28 2GX",
    "sg:province":"Greater Manchester",
    "wof:name":"Alex Temple Harpsicords",
    "wof:placetype":"venue"
},
  "geometry": {"coordinates":[-2.3772790432,53.4966773987],"type":"Point"}
}