{
  "type": "Feature",
  "properties": {
    "addr:full":"19 Adams Avenue, Tunstall Stoke-on-trent Staffordshire ST6 5PE",
    "addr:housenumber":"19",
    "addr:postcode":"staffordshire st6 5pe",
    "addr:street":"Adams Avenue",
    "iso:country":"GB",
    "sg:address":"19 Adams Avenue, Tunstall",
    "sg:city":"Stoke-on-trent",
    "sg:classifiers":[
        {
            "category":"Building & Trades",
            "subcategory":"Construction",
            "type":"Services"
        }
    ],
    "sg:phone":"+44 1782 825321",
    "sg:postcode":"ST6 5PE",
    "sg:province":"Staffordshire",
    "sg:tags":[
        "demolition",
        "contractor"
    ],
    "wof:name":"E J B Sumbland",
    "wof:placetype":"venue"
},
  "geometry": {"coordinates":[-2.213015,53.06654],"type":"Point"}
}