{
  "type": "Feature",
  "properties": {
    "addr:full":"66a West Gate Mansfield Nottinghamshire NG18 1RR",
    "addr:housenumber":"66a",
    "addr:postcode":"ng18 1rr",
    "addr:street":"West Gate",
    "iso:country":"GB",
    "sg:address":"66a West Gate",
    "sg:city":"Mansfield",
    "sg:classifiers":[
        {
            "category":"Personal",
            "subcategory":"Beauty Salon",
            "type":"Services"
        }
    ],
    "sg:postcode":"NG18 1RR",
    "sg:province":"Nottinghamshire",
    "sg:tags":[
        "unisex",
        "hairdresser"
    ],
    "wof:name":"Trzopek,Fleur,",
    "wof:placetype":"venue"
},
  "geometry": {"coordinates":[-1.1988990307,53.1464004517],"type":"Point"}
}