{
  "type": "Feature",
  "properties": {
    "iso:country":"GB",
    "sg:address":"875-877 Govan Road",
    "sg:city":"Glasgow",
    "sg:classifiers":[
        {
            "category":"Professional",
            "subcategory":"Lawyer & Legal Services",
            "type":"Services"
        }
    ],
    "sg:phone":"+44 141 445 3355",
    "sg:postcode":"G51 3DL",
    "sg:province":"Glasgow City",
    "sg:tags":[
        "solicitor"
    ],
    "wof:name":"Fitzpatrick & Co",
    "wof:placetype":"venue"
},
  "geometry": {"coordinates":[-4.315809,55.863785],"type":"Point"}
}