{
  "type": "Feature",
  "properties": {
    "addr:full":"Corvine House, Owen Road Diss Norfolk IP22 4ER",
    "addr:postcode":"ip22 4er",
    "addr:street":"Owen Road",
    "iso:country":"GB",
    "sg:address":"Corvine House, Owen Road",
    "sg:city":"Diss",
    "sg:classifiers":[
        {
            "category":"Building & Trades",
            "subcategory":"Construction",
            "type":"Services"
        }
    ],
    "sg:phone":"+44 1379 652212",
    "sg:postcode":"IP22 4ER",
    "sg:province":"Norfolk",
    "sg:tags":[
        "restoration",
        "refurbishment"
    ],
    "wof:name":"Jay Interiors Ltd.",
    "wof:placetype":"venue"
},
  "geometry": {"coordinates":[1.1224900484,52.3750762939],"type":"Point"}
}