{
  "type": "Feature",
  "properties": {
    "addr:full":"Clydeway Centre, 45 Finnieston Street Glasgow Glasgow City G3 8JU",
    "addr:housenumber":"45",
    "addr:postcode":"g3 8ju",
    "addr:street":"Finnieston Street",
    "iso:country":"GB",
    "sg:address":"Clydeway Centre, 45 Finnieston Street",
    "sg:city":"Glasgow",
    "sg:classifiers":[
        {
            "category":"Manufacturing",
            "subcategory":"Signs",
            "type":"Manufacturing & Wholesale Goods"
        }
    ],
    "sg:phone":"+44 141 221 8033",
    "sg:postcode":"G3 8JU",
    "sg:province":"Glasgow City",
    "sg:tags":[
        "nameplate"
    ],
    "wof:name":"Sign Post",
    "wof:placetype":"venue"
},
  "geometry": {"coordinates":[-4.2807,55.86253],"type":"Point"}
}