{
  "type": "Feature",
  "properties": {
    "addr:full":"Kirkby Stephen Youth Hostel, Fletcher Hill Kirkby Stephen Cumbria CA17 4QQ",
    "addr:postcode":"ca17 4qq",
    "addr:street":"Fletcher Hill",
    "iso:country":"GB",
    "sg:address":"Kirkby Stephen Youth Hostel, Fletcher Hill",
    "sg:city":"Kirkby Stephen",
    "sg:classifiers":[
        {
            "category":"Travel",
            "subcategory":"Hostel",
            "type":"Entertainment"
        }
    ],
    "sg:phone":"+44 17683 71793",
    "sg:postcode":"CA17 4QQ",
    "sg:province":"Cumbria",
    "sg:tags":[
        "youth"
    ],
    "wof:name":"Youth Hostels Association",
    "wof:placetype":"venue"
},
  "geometry": {"coordinates":[-2.348623,54.472717],"type":"Point"}
}