{
  "type": "Feature",
  "properties": {
    "addr:full":"Stonehaven, Cowbridge Boston Lincolnshire PE22 7AX",
    "addr:postcode":"pe22 7ax",
    "addr:street":"Stonehaven Cowbridge",
    "iso:country":"GB",
    "sg:address":"Stonehaven, Cowbridge",
    "sg:city":"Boston",
    "sg:classifiers":[
        {
            "category":"Retail",
            "subcategory":"Repair Shop",
            "type":"Services"
        }
    ],
    "sg:postcode":"PE22 7AX",
    "sg:province":"Lincolnshire",
    "sg:tags":[
        "radio",
        "television",
        "video"
    ],
    "wof:name":"Alpha Vision",
    "wof:placetype":"venue"
},
  "geometry": {"coordinates":[-0.0224389993,53.0057487488],"type":"Point"}
}