{
  "type": "Feature",
  "properties": {
    "addr:full":"92 Chatsworth Road Morecambe Lancashire LA3 1BL",
    "addr:housenumber":"92",
    "addr:postcode":"la3 1bl",
    "addr:street":"Chatsworth Road",
    "iso:country":"GB",
    "sg:address":"92 Chatsworth Road",
    "sg:city":"Morecambe",
    "sg:classifiers":[
        {
            "category":"Recreation",
            "subcategory":"Fishing",
            "type":"Entertainment"
        }
    ],
    "sg:phone":"+44 1524 831818",
    "sg:postcode":"LA3 1BL",
    "sg:province":"Lancashire",
    "sg:tags":[
        "angling"
    ],
    "wof:name":"Mark & Joanne Nicholls",
    "wof:placetype":"venue"
},
  "geometry": {"coordinates":[-2.878805,54.063461],"type":"Point"}
}