{
  "type": "Feature",
  "properties": {
    "addr:full":"Home Farm, Tilbury Road, East Haddon Northampton Northamptonshire NN6 8BX",
    "addr:postcode":"nn6 8bx",
    "addr:street":"Tilbury Road East",
    "iso:country":"GB",
    "sg:address":"Home Farm, Tilbury Road, East Haddon",
    "sg:city":"Northampton",
    "sg:classifiers":[
        {
            "category":"Farming",
            "subcategory":"Farm",
            "type":"Manufacturing & Wholesale Goods"
        }
    ],
    "sg:phone":"+44 1604 770208",
    "sg:postcode":"NN6 8BX",
    "sg:province":"Northamptonshire",
    "sg:tags":[
        "mixed",
        "crop"
    ],
    "wof:name":"R W Spencer",
    "wof:placetype":"venue"
},
  "geometry": {"coordinates":[-1.0232059956,52.3071937561],"type":"Point"}
}