{
  "type": "Feature",
  "properties": {
    "addr:full":"80 Wilson Road, Hanford Stoke-on-trent Staffordshire ST4 4QQ",
    "addr:housenumber":"80",
    "addr:postcode":"st4 4qq",
    "addr:street":"Wilson Road",
    "iso:country":"GB",
    "sg:address":"80 Wilson Road, Hanford",
    "sg:city":"Stoke-on-trent",
    "sg:classifiers":[
        {
            "category":"Personal",
            "subcategory":"Beauty Salon",
            "type":"Services"
        }
    ],
    "sg:postcode":"ST4 4QQ",
    "sg:province":"Staffordshire",
    "sg:tags":[
        "unisex",
        "hairdresser"
    ],
    "wof:name":"Steve Boulton Hair Specialist",
    "wof:placetype":"venue"
},
  "geometry": {"coordinates":[-2.195866,52.977715],"type":"Point"}
}