{
  "type": "Feature",
  "properties": {
    "iso:country":"GB",
    "sg:address":"112 Roxburgh Street",
    "sg:city":"Greenock",
    "sg:classifiers":[
        {
            "category":"Home & Garden",
            "subcategory":"Carpets & Floor Coverings",
            "type":"Retail Goods"
        }
    ],
    "sg:postcode":"PA15 4JT",
    "sg:province":"Inverclyde",
    "sg:tags":[
        "carpets",
        "rug",
        "matting"
    ],
    "wof:name":"Carpet & Vinyl Warehouse",
    "wof:placetype":"venue"
},
  "geometry": {"coordinates":[-4.7643260956,55.9463005066],"type":"Point"}
}