{
  "type": "Feature",
  "properties": {
    "addr:full":"Balure Of Shian, Ledaig Oban Argyll and Bute PA37 1SD",
    "addr:postcode":"pa37 1sd",
    "addr:street":"Ledaig",
    "iso:country":"GB",
    "sg:address":"Balure Of Shian, Ledaig",
    "sg:city":"Oban",
    "sg:classifiers":[
        {
            "category":"Farming",
            "subcategory":"Livestock Farm",
            "type":"Manufacturing & Wholesale Goods"
        }
    ],
    "sg:phone":"+44 1631 720243",
    "sg:postcode":"PA37 1SD",
    "sg:province":"Argyll and Bute",
    "sg:tags":[
        "others"
    ],
    "wof:name":"Ronald Hogg",
    "wof:placetype":"venue"
},
  "geometry": {"coordinates":[-5.4026989937,56.4815864563],"type":"Point"}
}