{
  "type": "Feature",
  "properties": {
    "iso:country":"GB",
    "sg:address":"Creswick Street",
    "sg:city":"Sheffield",
    "sg:classifiers":[
        {
            "category":"Education",
            "subcategory":"Preschool",
            "type":"Public Place"
        }
    ],
    "sg:phone":"+44 114 233 5197",
    "sg:postcode":"S6 2TN",
    "sg:province":"South Yorkshire",
    "sg:tags":[
        "pre-school",
        "playgroups"
    ],
    "wof:name":"Creswick Street Young Children's Centre",
    "wof:placetype":"venue"
},
  "geometry": {"coordinates":[-1.490658,53.395828],"type":"Point"}
}