{
  "type": "Feature",
  "properties": {
    "iso:country":"GB",
    "sg:address":"Widden Hill, Highfield Lane, Horton",
    "sg:city":"Bristol",
    "sg:classifiers":[
        {
            "category":"Farming",
            "subcategory":"Livestock Farm",
            "type":"Manufacturing & Wholesale Goods"
        }
    ],
    "sg:phone":"+44 1454 312096",
    "sg:postcode":"BS37 6QU",
    "sg:province":"Gloucestershire",
    "sg:tags":[
        "others"
    ],
    "wof:name":"Peter H Lippiatt",
    "wof:placetype":"venue"
},
  "geometry": {"coordinates":[-2.353535,51.559292],"type":"Point"}
}