{
  "type": "Feature",
  "properties": {
    "addr:full":"Sheriffmuir Road, Greenloaning Dunblane Perth and Kinross FK15 0ND",
    "addr:postcode":"fk15 0nd",
    "addr:street":"Sheriffmuir Road",
    "iso:country":"GB",
    "sg:address":"Sheriffmuir Road, Greenloaning",
    "sg:city":"Dunblane",
    "sg:classifiers":[
        {
            "category":"Sports & Exercise",
            "subcategory":"Stables",
            "type":"Entertainment"
        },
        {
            "category":"Organizations",
            "subcategory":"Non-profit Organization",
            "type":"Services"
        }
    ],
    "sg:postcode":"FK15 0ND",
    "sg:province":"Perth and Kinross",
    "sg:tags":[
        "charity",
        "organisation",
        "education",
        "voluntary",
        "equestrian"
    ],
    "wof:name":"Greenloaning Equine Care & Riding School",
    "wof:placetype":"venue"
},
  "geometry": {"coordinates":[-3.8828840256,56.2454147339],"type":"Point"}
}