{
  "type": "Feature",
  "properties": {
    "iso:country":"GB",
    "sg:address":"Clyde Crescent",
    "sg:city":"Cheltenham",
    "sg:classifiers":[
        {
            "category":"Social Services",
            "subcategory":"Adult Care",
            "type":"Services"
        },
        {
            "category":"Government",
            "subcategory":"Office",
            "type":"Public Place"
        }
    ],
    "sg:phone":"+44 1242 513010",
    "sg:postcode":"GL52 5QH",
    "sg:province":"Gloucestershire",
    "sg:tags":[
        "local",
        "day",
        "centre"
    ],
    "wof:name":"Whaddon Family Centre",
    "wof:placetype":"venue"
},
  "geometry": {"coordinates":[-2.051358,51.906097],"type":"Point"}
}