{
  "type": "Feature",
  "properties": {
    "iso:country":"GB",
    "sg:address":"71 Audley Road",
    "sg:city":"London",
    "sg:classifiers":[
        {
            "category":"Professional",
            "subcategory":"Business Services",
            "type":"Services"
        }
    ],
    "sg:phone":"+44 20 8202 6028",
    "sg:postcode":"NW4 3EU",
    "sg:province":"Greater London",
    "sg:tags":[
        "import",
        "export",
        "agent"
    ],
    "wof:name":"Acorn Exports Ltd.",
    "wof:placetype":"venue"
},
  "geometry": {"coordinates":[-0.233476,51.579178],"type":"Point"}
}