{
  "type": "Feature",
  "properties": {
    "iso:country":"GB",
    "sg:address":"Lensbury Way",
    "sg:city":"Abbey Wood",
    "sg:classifiers":[
        {
            "category":"Place Of Worship",
            "type":"Public Place"
        }
    ],
    "sg:phone":"+44 20 8310 2419",
    "sg:postcode":"SE2 9TA",
    "sg:province":"Greater London",
    "wof:name":"Church of the Cross",
    "wof:placetype":"venue"
},
  "geometry": {"coordinates":[0.12124,51.492447],"type":"Point"}
}