{
  "type": "Feature",
  "properties": {
    "addr:full":"26-28 Kirkgate Street, Walsoken Wisbech Cambridgeshire PE13 3QS",
    "addr:housenumber":"26-28",
    "addr:postcode":"pe13 3qs",
    "addr:street":"Kirkgate Street",
    "iso:country":"GB",
    "sg:address":"26-28 Kirkgate Street, Walsoken",
    "sg:city":"Wisbech",
    "sg:classifiers":[
        {
            "category":"Professional",
            "subcategory":"Employment Agencies",
            "type":"Services"
        }
    ],
    "sg:phone":"+44 1945 474355",
    "sg:postcode":"PE13 3QS",
    "sg:province":"Cambridgeshire",
    "sg:tags":[
        "consultant"
    ],
    "wof:name":"Rapid Employment & Recruitment",
    "wof:placetype":"venue"
},
  "geometry": {"coordinates":[0.1795530021,52.6725082397],"type":"Point"}
}