{
  "type": "Feature",
  "properties": {
    "addr:full":"10 Victoria Road Surbiton Surrey KT6 4JY",
    "addr:housenumber":"10",
    "addr:postcode":"kt6 4jy",
    "addr:street":"Victoria Road",
    "iso:country":"GB",
    "sg:address":"10 Victoria Road",
    "sg:city":"Surbiton",
    "sg:classifiers":[
        {
            "category":"Banks & Credit Unions",
            "subcategory":"Bank",
            "type":"Services"
        }
    ],
    "sg:phone":"+44 845 610 1202",
    "sg:postcode":"KT6 4JY",
    "sg:province":"Surrey",
    "sg:tags":[
        "financial",
        "institution"
    ],
    "wof:name":"NATIONAL WESTMINSTER BANK PLC",
    "wof:placetype":"venue"
},
  "geometry": {"coordinates":[-0.311835,51.390209],"type":"Point"}
}