{
  "type": "Feature",
  "properties": {
    "addr:full":"3 Newport Way Middlesbrough North Yorkshire TS1 5JW",
    "addr:housenumber":"3",
    "addr:postcode":"ts1 5jw",
    "addr:street":"Newport Way",
    "iso:country":"GB",
    "sg:address":"3 Newport Way",
    "sg:city":"Middlesbrough",
    "sg:classifiers":[
        {
            "category":"Shopping",
            "subcategory":"Beauty & Cosmetics",
            "type":"Retail Goods"
        }
    ],
    "sg:phone":"+44 1642 246666",
    "sg:postcode":"TS1 5JW",
    "sg:province":"North Yorkshire",
    "sg:tags":[
        "equipment",
        "supply",
        "hairdressing"
    ],
    "wof:name":"Ray & Co. (Hairdressers Sundries Men) Ltd.",
    "wof:placetype":"venue"
},
  "geometry": {"coordinates":[-1.251333,54.575317],"type":"Point"}
}