{
  "type": "Feature",
  "properties": {
    "iso:country":"GB",
    "sg:address":"6 Farm Rd",
    "sg:city":"Street",
    "sg:classifiers":[
        {
            "category":"Professional",
            "subcategory":"Lawyer & Legal Services",
            "type":"Services"
        }
    ],
    "sg:phone":"+44 1749 836100",
    "sg:postcode":"BA16 0EL",
    "sg:province":"Somerset",
    "sg:tags":[
        "solicitor"
    ],
    "wof:name":"Chubb Bulleid",
    "wof:placetype":"venue"
},
  "geometry": {"coordinates":[-2.74037,51.127438],"type":"Point"}
}