{
  "type": "Feature",
  "properties": {
    "iso:country":"GB",
    "sg:address":"8 Clos Dwyerw",
    "sg:city":"Caerphilly",
    "sg:classifiers":[
        {
            "category":"Banks & Credit Unions",
            "subcategory":"Financial Services",
            "type":"Services"
        }
    ],
    "sg:phone":"+44 29 2088 0445",
    "sg:postcode":"CF83 1TE",
    "sg:province":"Caerphilly",
    "sg:tags":[
        "consultant"
    ],
    "wof:name":"Agency Financial Services",
    "wof:placetype":"venue"
},
  "geometry": {"coordinates":[-3.2352120876,51.569103241],"type":"Point"}
}