{
  "type": "Feature",
  "properties": {
    "addr:full":"30 Loxford Avenue East Ham Greater London E6 3DB",
    "addr:housenumber":"30",
    "addr:postcode":"e6 3db",
    "addr:street":"Loxford Avenue",
    "iso:country":"GB",
    "sg:address":"30 Loxford Avenue",
    "sg:city":"East Ham",
    "sg:classifiers":[
        {
            "category":"Professional",
            "subcategory":"Engineering",
            "type":"Services"
        },
        {
            "category":"Building & Trades",
            "subcategory":"Electrical",
            "type":"Services"
        }
    ],
    "sg:phone":"+44 20 8552 9942",
    "sg:postcode":"E6 3DB",
    "sg:province":"Greater London",
    "sg:tags":[
        "engineer",
        "electrician",
        "contractor"
    ],
    "wof:name":"A T G Electrical Services",
    "wof:placetype":"venue"
},
  "geometry": {"coordinates":[0.042707,51.530041],"type":"Point"}
}