{
  "type": "Feature",
  "properties": {
    "iso:country":"GB",
    "sg:address":"26 Normanhurst Road",
    "sg:city":"Walton-on-thames",
    "sg:classifiers":[
        {
            "category":"Manufacturing",
            "subcategory":"Wood Products",
            "type":"Manufacturing & Wholesale Goods"
        },
        {
            "category":"Building & Trades",
            "subcategory":"Construction",
            "type":"Services"
        }
    ],
    "sg:phone":"+44 1932 244745",
    "sg:postcode":"KT12 3EQ",
    "sg:province":"Surrey",
    "sg:tags":[
        "window",
        "replacement",
        "sawmill",
        "shaving"
    ],
    "wof:name":"Hawkins Joinery",
    "wof:placetype":"venue"
},
  "geometry": {"coordinates":[-0.393305,51.38089],"type":"Point"}
}