{
  "type": "Feature",
  "properties": {
    "iso:country":"GB",
    "sg:address":"Long Marston Airfield, Long Marston",
    "sg:city":"Stratford-upon-avon",
    "sg:classifiers":[
        {
            "category":"Professional",
            "subcategory":"Business Services",
            "type":"Services"
        },
        {
            "category":"Sports & Exercise",
            "subcategory":"Race Track",
            "type":"Entertainment"
        }
    ],
    "sg:postcode":"CV37 8LL",
    "sg:province":"Warwickshire",
    "sg:tags":[
        "bookmaker",
        "motor"
    ],
    "wof:name":"Avonpark Raceway",
    "wof:placetype":"venue"
},
  "geometry": {"coordinates":[-1.7768739462,52.1350364685],"type":"Point"}
}