{
  "type": "Feature",
  "properties": {
    "iso:country":"GB",
    "sg:address":"Mill Marsh Lane, Brimsdown",
    "sg:city":"Enfield",
    "sg:classifiers":[
        {
            "category":"Manufacturing",
            "subcategory":"Metals",
            "type":"Manufacturing & Wholesale Goods"
        }
    ],
    "sg:phone":"+44 1554 750121",
    "sg:postcode":"EN3 7QD",
    "sg:province":"Greater London",
    "sg:tags":[
        "industry",
        "f-a"
    ],
    "wof:name":"Delta Enfield Metals Ltd.",
    "wof:placetype":"venue"
},
  "geometry": {"coordinates":[-0.033652,51.654732],"type":"Point"}
}