{
  "type": "Feature",
  "properties": {
    "addr:full":"C Co, T A Centre, Oakleigh Rd Barnstaple Devon EX32 8JT",
    "addr:housenumber":"c",
    "addr:postcode":"ex32 8jt",
    "addr:street":"Co T A;Oakleigh Rd",
    "iso:country":"GB",
    "sg:address":"C Co, T A Centre, Oakleigh Rd",
    "sg:city":"Barnstaple",
    "sg:classifiers":[
        {
            "category":"Government",
            "subcategory":"Office",
            "type":"Public Place"
        }
    ],
    "sg:phone":"+44 1271 342296",
    "sg:postcode":"EX32 8JT",
    "sg:province":"Devon",
    "sg:tags":[
        "armed",
        "reserve"
    ],
    "wof:name":"Devon Army Cadet Force",
    "wof:placetype":"venue"
},
  "geometry": {"coordinates":[-4.056221962,51.0783233643],"type":"Point"}
}