{
  "type": "Feature",
  "properties": {
    "addr:full":"The Studio Polventon, Ponsanooth Truro Cornwall TR3 7HU",
    "addr:postcode":"tr3 7hu",
    "iso:country":"GB",
    "sg:address":"The Studio Polventon, Ponsanooth",
    "sg:city":"Truro",
    "sg:classifiers":[
        {
            "category":"Professional",
            "type":"Services"
        }
    ],
    "sg:phone":"+44 1872 863100",
    "sg:postcode":"TR3 7HU",
    "sg:province":"Cornwall",
    "sg:tags":[
        "entertainer"
    ],
    "wof:name":"SH Concert Travel",
    "wof:placetype":"venue"
},
  "geometry": {"coordinates":[-5.1403098106,50.1958580017],"type":"Point"}
}