{
  "type": "Feature",
  "properties": {
    "addr:full":"176 Queen St Walsall West Midlands WS2 9NX",
    "addr:housenumber":"176",
    "addr:postcode":"ws2 9nx",
    "addr:street":"Queen St",
    "iso:country":"GB",
    "sg:address":"176 Queen St",
    "sg:city":"Walsall",
    "sg:classifiers":[
        {
            "category":"Autos & Motor Vehicles",
            "subcategory":"Auto Supplies",
            "type":"Retail Goods"
        }
    ],
    "sg:phone":"+44 1922 625957",
    "sg:postcode":"WS2 9NX",
    "sg:province":"West Midlands",
    "sg:tags":[
        "car",
        "audio"
    ],
    "wof:name":"J & S Lunt Radio & Stereo Centre Ltd",
    "wof:placetype":"venue"
},
  "geometry": {"coordinates":[-1.991549015,52.5814590454],"type":"Point"}
}