{
  "type": "Feature",
  "properties": {
    "iso:country":"GB",
    "sg:address":"The Kingsley Centre, Main Rd",
    "sg:city":"Bordon",
    "sg:classifiers":[
        {
            "category":"Professional",
            "subcategory":"Lawyer & Legal Services",
            "type":"Services"
        }
    ],
    "sg:phone":"+44 1420 479000",
    "sg:postcode":"GU35 9ND",
    "sg:province":"Hampshire",
    "sg:tags":[
        "advice",
        "counselling"
    ],
    "wof:name":"Gateopener",
    "wof:placetype":"venue"
},
  "geometry": {"coordinates":[-0.865114,51.108856],"type":"Point"}
}