{
  "type": "Feature",
  "properties": {
    "addr:full":"40 Harbour Rd Inverness Highland IV1 1SY",
    "addr:housenumber":"40",
    "addr:postcode":"iv1 1sy",
    "addr:street":"Harbour Rd",
    "iso:country":"GB",
    "sg:address":"40 Harbour Rd",
    "sg:city":"Inverness",
    "sg:classifiers":[
        {
            "category":"Autos & Motor Vehicles",
            "subcategory":"Automobile Sales",
            "type":"Retail Goods"
        }
    ],
    "sg:phone":"+44 7778 855501",
    "sg:postcode":"IV1 1SY",
    "sg:province":"Highland",
    "sg:tags":[
        "car"
    ],
    "wof:name":"S V L Cars",
    "wof:placetype":"venue"
},
  "geometry": {"coordinates":[-4.21479702,57.484828949],"type":"Point"}
}