{
  "type": "Feature",
  "properties": {
    "iso:country":"GB",
    "sg:address":"12 Thornton Road",
    "sg:city":"Morecambe",
    "sg:classifiers":[
        {
            "category":"Home & Garden",
            "subcategory":"Furniture",
            "type":"Retail Goods"
        }
    ],
    "sg:phone":"+44 1524 415346",
    "sg:postcode":"LA4 5PE",
    "sg:province":"Lancashire",
    "wof:name":"Multibasics Ltd.",
    "wof:placetype":"venue"
},
  "geometry": {"coordinates":[-2.85378,54.076401],"type":"Point"}
}