{
  "type": "Feature",
  "properties": {
    "addr:full":"88a Tooley Street London Greater London SE1 2TF",
    "addr:housenumber":"88a",
    "addr:postcode":"se1 2tf",
    "addr:street":"Tooley Street",
    "iso:country":"GB",
    "sg:address":"88a Tooley Street",
    "sg:city":"London",
    "sg:classifiers":[
        {
            "category":"Fast Food",
            "type":"Food & Drink"
        }
    ],
    "sg:phone":"+44 20 7357 0712",
    "sg:postcode":"SE1 2TF",
    "sg:province":"Greater London",
    "sg:tags":[
        "away",
        "take"
    ],
    "wof:name":"Dungeon Fishbar",
    "wof:placetype":"venue"
},
  "geometry": {"coordinates":[-0.0831160024,51.5044937134],"type":"Point"}
}