{
  "type": "Feature",
  "properties": {
    "iso:country":"GB",
    "sg:address":"3a Carlton Road",
    "sg:city":"Lowestoft",
    "sg:classifiers":[
        {
            "category":"Retail",
            "subcategory":"Auto Repair",
            "type":"Services"
        }
    ],
    "sg:postcode":"NR33 0RU",
    "sg:province":"Suffolk",
    "sg:tags":[
        "electrician"
    ],
    "wof:name":"Autosparks",
    "wof:placetype":"venue"
},
  "geometry": {"coordinates":[1.7413049936,52.4647827148],"type":"Point"}
}