{
  "type": "Feature",
  "properties": {
    "iso:country":"GB",
    "sg:address":"12 Gordon Street",
    "sg:city":"Southport",
    "sg:classifiers":[
        {
            "category":"Travel",
            "subcategory":"Hotels & Motels",
            "type":"Entertainment"
        }
    ],
    "sg:phone":"+44 1704 535893",
    "sg:postcode":"PR9 0BG",
    "sg:province":"Lancashire",
    "sg:tags":[
        "house",
        "guest"
    ],
    "wof:name":"Gordon Guest House",
    "wof:placetype":"venue"
},
  "geometry": {"coordinates":[-3.000596,53.651882],"type":"Point"}
}