{
  "type": "Feature",
  "properties": {
    "addr:full":"Kirkby Malham, Airton Skipton Lancashire BD23 4BJ",
    "addr:postcode":"bd23 4bj",
    "iso:country":"GB",
    "sg:address":"Kirkby Malham, Airton",
    "sg:city":"Skipton",
    "sg:classifiers":[
        {
            "category":"Food & Beverages",
            "subcategory":"Liquor & Beverages",
            "type":"Retail Goods"
        }
    ],
    "sg:postcode":"BD23 4BJ",
    "sg:province":"Lancashire",
    "sg:tags":[
        "beer",
        "spirit",
        "wines"
    ],
    "wof:name":"John Medlicot & Co",
    "wof:placetype":"venue"
},
  "geometry": {"coordinates":[-2.1512210369,54.029384613],"type":"Point"}
}