{
  "type": "Feature",
  "properties": {
    "iso:country":"GB",
    "sg:address":"30 Station Road East",
    "sg:city":"Oxted",
    "sg:classifiers":[
        {
            "category":"Restaurant",
            "type":"Food & Drink"
        }
    ],
    "sg:phone":"+44 1883 713988",
    "sg:postcode":"RH8 0PG",
    "sg:province":"Surrey",
    "sg:tags":[
        "chinese"
    ],
    "wof:name":"Rainbow Chinese Restaurant",
    "wof:placetype":"venue"
},
  "geometry": {"coordinates":[-0.001746,51.25753],"type":"Point"}
}