{
  "type": "Feature",
  "properties": {
    "addr:full":"396 Idle Road, Five Lane Ends Bradford West Yorkshire BD2 2AW",
    "addr:housenumber":"396;bradford",
    "addr:postcode":"yorkshire bd2 2aw",
    "addr:street":"Idle Road Five Lane Ends",
    "iso:country":"GB",
    "sg:address":"396 Idle Road, Five Lane Ends",
    "sg:city":"Bradford",
    "sg:classifiers":[
        {
            "category":"Building & Trades",
            "subcategory":"Construction",
            "type":"Services"
        }
    ],
    "sg:phone":"+44 1274 632009",
    "sg:postcode":"BD2 2AW",
    "sg:province":"West Yorkshire",
    "sg:tags":[
        "joinery",
        "joiner",
        "carpenter",
        "carpentry"
    ],
    "wof:name":"Undercliffe Joinery",
    "wof:placetype":"venue"
},
  "geometry": {"coordinates":[-1.73546803,53.8200492859],"type":"Point"}
}