{
  "type": "Feature",
  "properties": {
    "iso:country":"GB",
    "sg:address":"68 Main Ridgeeast",
    "sg:city":"Boston",
    "sg:classifiers":[
        {
            "category":"Personal",
            "subcategory":"Beauty Salon",
            "type":"Services"
        }
    ],
    "sg:phone":"+44 1205 362529",
    "sg:postcode":"PE21 6ST",
    "sg:province":"Lincolnshire",
    "sg:tags":[
        "unisex",
        "hairdresser"
    ],
    "wof:name":"Ridgeway Salon",
    "wof:placetype":"venue"
},
  "geometry": {"coordinates":[-0.018354,52.978394],"type":"Point"}
}