{
  "type": "Feature",
  "properties": {
    "iso:country":"GB",
    "sg:address":"Old Post Office Cottage, Killiecrankie",
    "sg:city":"Pitlochry",
    "sg:classifiers":[
        {
            "category":"Government",
            "subcategory":"Post Office",
            "type":"Public Place"
        }
    ],
    "sg:phone":"+44 1796 473228",
    "sg:postcode":"PH16 5LG",
    "sg:province":"Perth and Kinross",
    "wof:name":"Killiecrankie Post Office",
    "wof:placetype":"venue"
},
  "geometry": {"coordinates":[-3.734699,56.703335],"type":"Point"}
}