{
  "type": "Feature",
  "properties": {
    "addr:full":"35-37 East Street Newton Abbot Devon TQ12 2JP",
    "addr:housenumber":"35-37",
    "addr:postcode":"tq12 2jp",
    "addr:street":"East Street",
    "iso:country":"GB",
    "sg:address":"35-37 East Street",
    "sg:city":"Newton Abbot",
    "sg:classifiers":[
        {
            "category":"Bars & Pubs",
            "type":"Food & Drink"
        }
    ],
    "sg:phone":"+44 1626 365249",
    "sg:postcode":"TQ12 2JP",
    "sg:province":"Devon",
    "sg:tags":[
        "pubs",
        "inn"
    ],
    "wof:name":"Locomotive Inn",
    "wof:placetype":"venue"
},
  "geometry": {"coordinates":[-3.608289,50.528912],"type":"Point"}
}