{
  "type": "Feature",
  "properties": {
    "iso:country":"GB",
    "sg:address":"15a Shipbourne Road",
    "sg:city":"Tonbridge",
    "sg:classifiers":[
        {
            "category":"Home & Garden",
            "subcategory":"Home Furnishings",
            "type":"Retail Goods"
        }
    ],
    "sg:postcode":"TN10 3DN",
    "sg:province":"Kent",
    "sg:tags":[
        "patio",
        "furniture"
    ],
    "wof:name":"World of Pots",
    "wof:placetype":"venue"
},
  "geometry": {"coordinates":[0.277184,51.201496],"type":"Point"}
}