{
  "type": "Feature",
  "properties": {
    "addr:full":"5 Blenheim St West End Hampshire W1Y 9LB",
    "addr:housenumber":"5",
    "addr:postcode":"w1y 9lb",
    "addr:street":"Blenheim St",
    "iso:country":"GB",
    "sg:address":"5 Blenheim St",
    "sg:city":"West End",
    "sg:classifiers":[
        {
            "category":"Arts & Performance",
            "subcategory":"Theater",
            "type":"Entertainment"
        }
    ],
    "sg:phone":"+44 20 7499 4011",
    "sg:postcode":"W1Y 9LB",
    "sg:province":"Hampshire",
    "sg:tags":[
        "theatrical",
        "agency"
    ],
    "wof:name":"John Grantham",
    "wof:placetype":"venue"
},
  "geometry": {"coordinates":[-0.1467290074,51.5141372681],"type":"Point"}
}