{
  "type": "Feature",
  "properties": {
    "addr:full":"Millen Road Sittingbourne Kent ME10 2AA",
    "addr:postcode":"me10 2aa",
    "addr:street":"Millen Road",
    "iso:country":"GB",
    "sg:address":"Millen Road",
    "sg:city":"Sittingbourne",
    "sg:classifiers":[
        {
            "category":"Retail",
            "subcategory":"Auto Repair",
            "type":"Services"
        }
    ],
    "sg:postcode":"ME10 2AA",
    "sg:province":"Kent",
    "sg:tags":[
        "modification",
        "garage"
    ],
    "wof:name":"St Michaels Service Centre",
    "wof:placetype":"venue"
},
  "geometry": {"coordinates":[0.731407,51.346272],"type":"Point"}
}