{
  "type": "Feature",
  "properties": {
    "addr:full":"17-19 Goresbrook Rd Dagenham Essex RM9 6UX",
    "addr:housenumber":"17-19",
    "addr:postcode":"rm9 6ux",
    "addr:street":"Goresbrook Rd",
    "iso:country":"GB",
    "sg:address":"17-19 Goresbrook Rd",
    "sg:city":"Dagenham",
    "sg:classifiers":[
        {
            "category":"Shopping",
            "subcategory":"News",
            "type":"Retail Goods"
        }
    ],
    "sg:phone":"+44 20 8592 2053",
    "sg:postcode":"RM9 6UX",
    "sg:province":"Essex",
    "sg:tags":[
        "newsagent"
    ],
    "wof:name":"Gorsebrook Rd Post Office",
    "wof:placetype":"venue"
},
  "geometry": {"coordinates":[0.1458469927,51.5322036743],"type":"Point"}
}