{
  "type": "Feature",
  "properties": {
    "iso:country":"GB",
    "sg:address":"49 Wrawby Street",
    "sg:city":"Brigg",
    "sg:classifiers":[
        {
            "category":"Home & Garden",
            "subcategory":"Hardware",
            "type":"Retail Goods"
        }
    ],
    "sg:phone":"+44 1652 656415",
    "sg:postcode":"DN20 8JB",
    "sg:province":"Lincolnshire",
    "sg:tags":[
        "retailer",
        "diy"
    ],
    "wof:name":"Pennys Wallpaper Shop",
    "wof:placetype":"venue"
},
  "geometry": {"coordinates":[-0.488749,53.552238],"type":"Point"}
}