{
  "type": "Feature",
  "properties": {
    "addr:full":"1 Bridge Rd, Mossley Hill Liverpool Merseyside L18 5EQ",
    "addr:housenumber":"1",
    "addr:postcode":"l18 5eq",
    "addr:street":"Bridge Rd",
    "iso:country":"GB",
    "sg:address":"1 Bridge Rd, Mossley Hill",
    "sg:city":"Liverpool",
    "sg:classifiers":[
        {
            "category":"Professional",
            "type":"Services"
        }
    ],
    "sg:phone":"+44 151 281 3792",
    "sg:postcode":"L18 5EQ",
    "sg:province":"Merseyside",
    "sg:tags":[
        "entertainer"
    ],
    "wof:name":"Soul Conspiracy Band",
    "wof:placetype":"venue"
},
  "geometry": {"coordinates":[-2.914388895,53.3797607422],"type":"Point"}
}