{
  "type": "Feature",
  "properties": {
    "addr:full":"Town Hall, Old Bristol Road Stroud Gloucestershire GL6 0JF",
    "addr:postcode":"gl6 0jf",
    "addr:street":"Old Bristol Road",
    "iso:country":"GB",
    "sg:address":"Town Hall, Old Bristol Road",
    "sg:city":"Stroud",
    "sg:classifiers":[
        {
            "category":"Manufacturing",
            "subcategory":"Tools & Machinery",
            "type":"Manufacturing & Wholesale Goods"
        },
        {
            "category":"Professional",
            "subcategory":"Engineering",
            "type":"Services"
        }
    ],
    "sg:phone":"+44 1453 836188",
    "sg:postcode":"GL6 0JF",
    "sg:province":"Gloucestershire",
    "sg:tags":[
        "society",
        "finishing",
        "printing",
        "friendly"
    ],
    "wof:name":"A B R Insurance Services",
    "wof:placetype":"venue"
},
  "geometry": {"coordinates":[-2.2190489769,51.6928710938],"type":"Point"}
}