{
  "type": "Feature",
  "properties": {
    "iso:country":"GB",
    "sg:address":"39 Station Street",
    "sg:city":"Walsall",
    "sg:classifiers":[
        {
            "category":"Travel",
            "subcategory":"Travel Agent",
            "type":"Entertainment"
        }
    ],
    "sg:phone":"+44 1922 648888",
    "sg:postcode":"WS2 9JT",
    "sg:province":"West Midlands",
    "wof:name":"Towe Ken Travel",
    "wof:placetype":"venue"
},
  "geometry": {"coordinates":[-1.984658,52.585293],"type":"Point"}
}