{
  "type": "Feature",
  "properties": {
    "addr:full":"8 Lombard Ct Monument Greater London EC3V 9BJ",
    "addr:housenumber":"8",
    "addr:postcode":"ec3v 9bj",
    "addr:street":"Lombard Ct",
    "iso:country":"GB",
    "sg:address":"8 Lombard Ct",
    "sg:city":"Monument",
    "sg:classifiers":[
        {
            "category":"Bars & Pubs",
            "type":"Food & Drink"
        }
    ],
    "sg:phone":"+44 20 7623 3680",
    "sg:postcode":"EC3V 9BJ",
    "sg:province":"Greater London",
    "sg:tags":[
        "pubs",
        "inn"
    ],
    "wof:name":"Red Lion The",
    "wof:placetype":"venue"
},
  "geometry": {"coordinates":[-0.088059,51.512779],"type":"Point"}
}