{
  "type": "Feature",
  "properties": {
    "iso:country":"GB",
    "sg:address":"12 Minster Road",
    "sg:city":"Bolton",
    "sg:classifiers":[
        {
            "category":"Building & Trades",
            "subcategory":"Construction",
            "type":"Services"
        }
    ],
    "sg:phone":"+44 1204 419618",
    "sg:postcode":"BL2 2NH",
    "sg:province":"Lancashire",
    "sg:tags":[
        "joiner",
        "carpenter"
    ],
    "wof:name":"First Class Joinery",
    "wof:placetype":"venue"
},
  "geometry": {"coordinates":[-2.406352,53.592892],"type":"Point"}
}