{
  "type": "Feature",
  "properties": {
    "addr:full":"145 High St Dundee Dundee City DD2 3DB",
    "addr:housenumber":"145",
    "addr:postcode":"dd2 3db",
    "addr:street":"High St",
    "iso:country":"GB",
    "sg:address":"145 High St",
    "sg:city":"Dundee",
    "sg:classifiers":[
        {
            "category":"Professional",
            "subcategory":"Engineering",
            "type":"Services"
        }
    ],
    "sg:phone":"+44 1382 611426",
    "sg:postcode":"DD2 3DB",
    "sg:province":"Dundee City",
    "sg:tags":[
        "contractor",
        "electrical",
        "engineer"
    ],
    "wof:name":"J Reoch & Son",
    "wof:placetype":"venue"
},
  "geometry": {"coordinates":[-3.0102119446,56.4731864929],"type":"Point"}
}