{
  "type": "Feature",
  "properties": {
    "addr:full":"7 Princes Street Southport Lancashire PR8 1EG",
    "addr:housenumber":"7",
    "addr:postcode":"pr8 1eg",
    "addr:street":"Princes Street",
    "iso:country":"GB",
    "sg:address":"7 Princes Street",
    "sg:city":"Southport",
    "sg:classifiers":[
        {
            "category":"Shopping",
            "subcategory":"Baby Store",
            "type":"Retail Goods"
        }
    ],
    "sg:phone":"+44 1704 542085",
    "sg:postcode":"PR8 1EG",
    "sg:province":"Lancashire",
    "sg:tags":[
        "babywear",
        "childrens"
    ],
    "wof:name":"Simply Precious",
    "wof:placetype":"venue"
},
  "geometry": {"coordinates":[-3.0052320957,53.6454353333],"type":"Point"}
}