{
  "type": "Feature",
  "properties": {
    "addr:full":"Unit 7d Orme Court, Granby Road Bakewell Derbyshire DE45 1ES",
    "addr:housenumber":"unit 7d",
    "addr:postcode":"de45 1es",
    "addr:street":"Orme Court Granby Road",
    "iso:country":"GB",
    "sg:address":"Unit 7d Orme Court, Granby Road",
    "sg:city":"Bakewell",
    "sg:classifiers":[
        {
            "category":"Personal",
            "subcategory":"Beauty Salon",
            "type":"Services"
        }
    ],
    "sg:phone":"+44 1629 814016",
    "sg:postcode":"DE45 1ES",
    "sg:province":"Derbyshire",
    "sg:tags":[
        "unisex",
        "hairdresser"
    ],
    "wof:name":"Montana",
    "wof:placetype":"venue"
},
  "geometry": {"coordinates":[-1.6731040478,53.2129745483],"type":"Point"}
}