{
  "type": "Feature",
  "properties": {
    "addr:full":"Criftin Farm, Oxton Road, Epperstone Nottingham Nottinghamshire NG14 6AT",
    "addr:postcode":"ng14 6at",
    "addr:street":"Oxton Road",
    "iso:country":"GB",
    "sg:address":"Criftin Farm, Oxton Road, Epperstone",
    "sg:city":"Nottingham",
    "sg:classifiers":[
        {
            "category":"Farming",
            "subcategory":"Livestock Farm",
            "type":"Manufacturing & Wholesale Goods"
        },
        {
            "category":"Farming",
            "subcategory":"Farm",
            "type":"Manufacturing & Wholesale Goods"
        }
    ],
    "sg:phone":"+44 115 965 2039",
    "sg:postcode":"NG14 6AT",
    "sg:province":"Nottinghamshire",
    "sg:tags":[
        "mixed",
        "others"
    ],
    "wof:name":"R J & J M C ESAM",
    "wof:placetype":"venue"
},
  "geometry": {"coordinates":[-1.029269,53.029499],"type":"Point"}
}