{
  "type": "Feature",
  "properties": {
    "addr:full":"55 Dunmoor Gro, Ingleby Barwick Stockton-on-tees Durham TS17 0QW",
    "addr:housenumber":"55",
    "addr:postcode":"ts17 0qw",
    "addr:street":"Dunmoor Gro",
    "iso:country":"GB",
    "sg:address":"55 Dunmoor Gro, Ingleby Barwick",
    "sg:city":"Stockton-on-tees",
    "sg:classifiers":[
        {
            "category":"Building & Trades",
            "subcategory":"Construction",
            "type":"Services"
        }
    ],
    "sg:phone":"+44 7831 189682",
    "sg:postcode":"TS17 0QW",
    "sg:province":"Durham",
    "sg:tags":[
        "roofing"
    ],
    "wof:name":"Abbey Sales",
    "wof:placetype":"venue"
},
  "geometry": {"coordinates":[-1.31473,54.511478],"type":"Point"}
}