{
  "type": "Feature",
  "properties": {
    "iso:country":"GB",
    "sg:address":"10 Victoria Road",
    "sg:city":"Dorchester",
    "sg:classifiers":[
        {
            "category":"Real Estate",
            "subcategory":"Architect",
            "type":"Services"
        }
    ],
    "sg:postcode":"DT1 1SB",
    "sg:province":"Dorset",
    "wof:name":"Nick Harrison Engineering Services",
    "wof:placetype":"venue"
},
  "geometry": {"coordinates":[-2.442511,50.711697],"type":"Point"}
}