{
  "type": "Feature",
  "properties": {
    "iso:country":"GB",
    "sg:address":"Court Ho, Carlton Pl",
    "sg:city":"Teignmouth",
    "sg:classifiers":[
        {
            "category":"Government",
            "subcategory":"Office",
            "type":"Public Place"
        }
    ],
    "sg:phone":"+44 1626 772531",
    "sg:postcode":"TQ14 8AB",
    "sg:province":"Devon",
    "sg:tags":[
        "central"
    ],
    "wof:name":"Probation Service",
    "wof:placetype":"venue"
},
  "geometry": {"coordinates":[-3.500104,50.548344],"type":"Point"}
}