{
  "type": "Feature",
  "properties": {
    "addr:full":"Turks Boatyard, Thames Side Kingston-upon-thames Greater London KT1 1PX",
    "addr:postcode":"kt1 1px",
    "addr:street":"Thames Side Kingston-Upon-Thames",
    "iso:country":"GB",
    "sg:address":"Turks Boatyard, Thames Side",
    "sg:city":"Kingston-upon-thames",
    "sg:classifiers":[
        {
            "category":"Bars & Pubs",
            "type":"Food & Drink"
        }
    ],
    "sg:phone":"+44 20 8547 2323",
    "sg:postcode":"KT1 1PX",
    "sg:province":"Greater London",
    "sg:tags":[
        "pubs",
        "inn"
    ],
    "wof:name":"Slug & Lettuce",
    "wof:placetype":"venue"
},
  "geometry": {"coordinates":[-0.3071399927,51.4125099182],"type":"Point"}
}