{
  "type": "Feature",
  "properties": {
    "addr:full":"2 Devonport Mews London Greater London W12 8NG",
    "addr:housenumber":"2",
    "addr:postcode":"w12 8ng",
    "addr:street":"Devonport Mews",
    "iso:country":"GB",
    "sg:address":"2 Devonport Mews",
    "sg:city":"London",
    "sg:classifiers":[
        {
            "category":"Communications",
            "subcategory":"Film & Video Production",
            "type":"Services"
        }
    ],
    "sg:phone":"+44 20 8749 6133",
    "sg:postcode":"W12 8NG",
    "sg:province":"Greater London",
    "sg:tags":[
        "recording",
        "sound",
        "studio"
    ],
    "wof:name":"A Major Music Co",
    "wof:placetype":"venue"
},
  "geometry": {"coordinates":[-0.229977,51.501949],"type":"Point"}
}