{
  "type": "Feature",
  "properties": {
    "iso:country":"GB",
    "sg:address":"1b Marshside Road",
    "sg:city":"Southport",
    "sg:classifiers":[
        {
            "category":"Shopping",
            "subcategory":"Florist",
            "type":"Retail Goods"
        }
    ],
    "sg:phone":"+44 1704 212219",
    "sg:postcode":"PR9 9TL",
    "sg:province":"Lancashire",
    "wof:name":"Tom Hodge",
    "wof:placetype":"venue"
},
  "geometry": {"coordinates":[-2.9664890766,53.6627082825],"type":"Point"}
}