{
  "type": "Feature",
  "properties": {
    "addr:full":"44 Seven Oaks Cres Nottingham Nottinghamshire NG9 3FP",
    "addr:housenumber":"44",
    "addr:postcode":"ng9 3fp",
    "addr:street":"Seven Oaks Cres",
    "iso:country":"GB",
    "sg:address":"44 Seven Oaks Cres",
    "sg:city":"Nottingham",
    "sg:classifiers":[
        {
            "category":"Health Services",
            "subcategory":"Health Practitioner",
            "type":"Services"
        }
    ],
    "sg:phone":"+44 115 925 1184",
    "sg:postcode":"NG9 3FP",
    "sg:province":"Nottinghamshire",
    "sg:tags":[
        "acupuncture"
    ],
    "wof:name":"Martin Dean",
    "wof:placetype":"venue"
},
  "geometry": {"coordinates":[-1.2422330379,52.941116333],"type":"Point"}
}