{
  "type": "Feature",
  "properties": {
    "addr:full":"573 Fishponds Road, Fishponds Bristol City of Bristol BS16 3AF",
    "addr:housenumber":"573",
    "addr:postcode":"bs16 3af",
    "addr:street":"Fishponds Road",
    "iso:country":"GB",
    "sg:address":"573 Fishponds Road, Fishponds",
    "sg:city":"Bristol",
    "sg:classifiers":[
        {
            "category":"Place Of Worship",
            "subcategory":"Synagogue",
            "type":"Public Place"
        }
    ],
    "sg:phone":"+44 117 958 4995",
    "sg:postcode":"BS16 3AF",
    "sg:province":"City of Bristol",
    "sg:tags":[
        "top",
        "sunroof",
        "vinyl"
    ],
    "wof:name":"Fishponds Sunroof Centre",
    "wof:placetype":"venue"
},
  "geometry": {"coordinates":[-2.538481,51.476791],"type":"Point"}
}