{
  "type": "Feature",
  "properties": {
    "addr:full":"Unit 1 Peterborough Road, Crowland Peterborough Cambridgeshire PE6 0BA",
    "addr:housenumber":"unit 1",
    "addr:postcode":"pe6 0ba",
    "addr:street":"Peterborough Road",
    "iso:country":"GB",
    "sg:address":"Unit 1 Peterborough Road, Crowland",
    "sg:city":"Peterborough",
    "sg:classifiers":[
        {
            "category":"Personal",
            "subcategory":"Beauty Salon",
            "type":"Services"
        }
    ],
    "sg:postcode":"PE6 0BA",
    "sg:province":"Cambridgeshire",
    "sg:tags":[
        "unisex",
        "hairdresser"
    ],
    "wof:name":"Sharon Witham",
    "wof:placetype":"venue"
},
  "geometry": {"coordinates":[-0.1657070071,52.6718444824],"type":"Point"}
}