{
  "type": "Feature",
  "properties": {
    "iso:country":"GB",
    "sg:address":"Equipment Depot Midland Trading, Estate, Consul Road",
    "sg:city":"Rugby",
    "sg:classifiers":[
        {
            "category":"Building & Trades",
            "subcategory":"Construction",
            "type":"Services"
        }
    ],
    "sg:phone":"+44 1788 576072",
    "sg:postcode":"CV21 1PB",
    "sg:province":"Warwickshire",
    "sg:tags":[
        "builder"
    ],
    "wof:name":"Shepherd Construction Ltd.",
    "wof:placetype":"venue"
},
  "geometry": {"coordinates":[-1.26651,52.38763],"type":"Point"}
}