{
  "type": "Feature",
  "properties": {
    "iso:country":"GB",
    "sg:address":"11 Chapel Street",
    "sg:city":"Penzance",
    "sg:classifiers":[
        {
            "category":"Building & Trades",
            "subcategory":"Construction",
            "type":"Services"
        }
    ],
    "sg:phone":"+44 1736 360528",
    "sg:postcode":"TR18 4AW",
    "sg:province":"Cornwall",
    "sg:tags":[
        "window",
        "door"
    ],
    "wof:name":"Handles Etc",
    "wof:placetype":"venue"
},
  "geometry": {"coordinates":[-5.53667593,50.1178741455],"type":"Point"}
}