{
  "type": "Feature",
  "properties": {
    "addr:full":"3 High Street Knaresborough North Yorkshire HG5 0ET",
    "addr:housenumber":"3",
    "addr:postcode":"hg5 0et",
    "addr:street":"High Street",
    "iso:country":"GB",
    "sg:address":"3 High Street",
    "sg:city":"Knaresborough",
    "sg:classifiers":[
        {
            "category":"Bars & Pubs",
            "type":"Food & Drink"
        }
    ],
    "sg:phone":"+44 1423 863314",
    "sg:postcode":"HG5 0ET",
    "sg:province":"North Yorkshire",
    "sg:tags":[
        "pubs",
        "inn"
    ],
    "wof:name":"The Board Inn",
    "wof:placetype":"venue"
},
  "geometry": {"coordinates":[-1.4657390118,54.0079994202],"type":"Point"}
}