{
  "type": "Feature",
  "properties": {
    "addr:full":"Crosland Industrial Estate, Bredbury Stockport Cheshire SK6 2BR",
    "addr:postcode":"sk6 2br",
    "addr:street":"Crosland Industrial Estate",
    "iso:country":"GB",
    "sg:address":"Crosland Industrial Estate, Bredbury",
    "sg:city":"Stockport",
    "sg:classifiers":[
        {
            "category":"Professional",
            "subcategory":"Art Services",
            "type":"Services"
        }
    ],
    "sg:postcode":"SK6 2BR",
    "sg:province":"Cheshire",
    "sg:tags":[
        "model",
        "maker"
    ],
    "wof:name":"Technical Models Ltd.",
    "wof:placetype":"venue"
},
  "geometry": {"coordinates":[-2.122762,53.42065],"type":"Point"}
}