{
  "type": "Feature",
  "properties": {
    "iso:country":"GB",
    "sg:address":"53 Tib St",
    "sg:city":"Manchester",
    "sg:classifiers":[
        {
            "category":"Wholesale",
            "subcategory":"Machinery & Supplies",
            "type":"Manufacturing & Wholesale Goods"
        }
    ],
    "sg:postcode":"M4 1LS",
    "sg:province":"Greater Manchester",
    "sg:tags":[
        "theatrical"
    ],
    "wof:name":"Morrell,David,",
    "wof:placetype":"venue"
},
  "geometry": {"coordinates":[-2.2342739105,53.4843063354],"type":"Point"}
}