{
  "type": "Feature",
  "properties": {
    "addr:full":"16 Osborne Terrace Gateshead Tyne and Wear NE8 1UY",
    "addr:housenumber":"16",
    "addr:postcode":"ne8 1uy",
    "addr:street":"Osborne Terrace",
    "iso:country":"GB",
    "sg:address":"16 Osborne Terrace",
    "sg:city":"Gateshead",
    "sg:classifiers":[
        {
            "category":"Health Services",
            "subcategory":"Nursing And Care Facility",
            "type":"Services"
        },
        {
            "category":"Social Services",
            "subcategory":"Retirement Home",
            "type":"Services"
        }
    ],
    "sg:postcode":"NE8 1UY",
    "sg:province":"Tyne and Wear",
    "sg:tags":[
        "residential"
    ],
    "wof:name":"Osborne House-Care for the Mentally Ill",
    "wof:placetype":"venue"
},
  "geometry": {"coordinates":[-1.6020460129,54.9610404968],"type":"Point"}
}