{
  "type": "Feature",
  "properties": {
    "iso:country":"GB",
    "sg:address":"10 Lumber Lane, Worsley",
    "sg:city":"Manchester",
    "sg:classifiers":[
        {
            "category":"Building & Trades",
            "subcategory":"Plumbing",
            "type":"Services"
        },
        {
            "category":"Home & Garden",
            "subcategory":"Carpets & Floor Coverings",
            "type":"Retail Goods"
        }
    ],
    "sg:phone":"+44 161 790 8359",
    "sg:postcode":"M28 2QH",
    "sg:province":"Greater Manchester",
    "sg:tags":[
        "wall",
        "tie",
        "plumber",
        "replacement"
    ],
    "wof:name":"1st Choice Plumbing & Heating",
    "wof:placetype":"venue"
},
  "geometry": {"coordinates":[-2.3878641129,53.5112953186],"type":"Point"}
}