{
  "type": "Feature",
  "properties": {
    "addr:full":"Melbury Ho, 34 Southborough Rd, Bickley Bromley Kent BR1 2EB",
    "addr:housenumber":"34",
    "addr:postcode":"br1 2eb",
    "addr:street":"Southborough Rd",
    "iso:country":"GB",
    "sg:address":"Melbury Ho, 34 Southborough Rd, Bickley",
    "sg:city":"Bromley",
    "sg:classifiers":[
        {
            "category":"Professional",
            "subcategory":"Business Services",
            "type":"Services"
        }
    ],
    "sg:postcode":"BR1 2EB",
    "sg:province":"Kent",
    "sg:tags":[
        "holding"
    ],
    "wof:name":"South Coastal (Holdings) Ltd",
    "wof:placetype":"venue"
},
  "geometry": {"coordinates":[0.014928,51.4057006836],"type":"Point"}
}