{
  "type": "Feature",
  "properties": {
    "addr:full":"Keyes House, Dolphin Square London Greater London SW1V 3NA",
    "addr:postcode":"sw1v 3na",
    "addr:street":"Dolphin Square",
    "iso:country":"GB",
    "sg:address":"Keyes House, Dolphin Square",
    "sg:city":"London",
    "sg:classifiers":[
        {
            "category":"Professional",
            "subcategory":"Engineering",
            "type":"Services"
        }
    ],
    "sg:phone":"+44 20 7828 6894",
    "sg:postcode":"SW1V 3NA",
    "sg:province":"Greater London",
    "sg:tags":[
        "consulting",
        "engineer"
    ],
    "wof:name":"Genever & Partners",
    "wof:placetype":"venue"
},
  "geometry": {"coordinates":[-0.1354109943,51.4865684509],"type":"Point"}
}