{
  "type": "Feature",
  "properties": {
    "iso:country":"GB",
    "sg:address":"2 Bloomsbury Street",
    "sg:city":"London",
    "sg:postcode":"WC1B 3ST",
    "sg:province":"Greater London",
    "wof:name":"Robot Food Tech Ltd",
    "wof:placetype":"venue"
},
  "geometry": {"coordinates":[-0.126882,51.517002],"type":"Point"}
}