{
  "type": "Feature",
  "properties": {
    "iso:country":"GB",
    "sg:address":"Western Harbour, Leith Docks",
    "sg:city":"Edinburgh",
    "sg:classifiers":[
        {
            "category":"Building & Trades",
            "subcategory":"Construction",
            "type":"Services"
        }
    ],
    "sg:phone":"+44 131 553 2790",
    "sg:postcode":"EH6 6NU",
    "sg:province":"City of Edinburgh",
    "sg:tags":[
        "glazier"
    ],
    "wof:name":"Safety First Window Films",
    "wof:placetype":"venue"
},
  "geometry": {"coordinates":[-3.175334,55.977348],"type":"Point"}
}