{
  "type": "Feature",
  "properties": {
    "iso:country":"GB",
    "sg:address":"119 Victoria Road",
    "sg:city":"Aberdeen",
    "sg:classifiers":[
        {
            "category":"Farming",
            "subcategory":"Fish & Marine Products",
            "type":"Manufacturing & Wholesale Goods"
        }
    ],
    "sg:postcode":"AB11 9LY",
    "sg:province":"Aberdeen City",
    "sg:tags":[
        "fishmonger"
    ],
    "wof:name":"A Wiggins",
    "wof:placetype":"venue"
},
  "geometry": {"coordinates":[-2.08656,57.137135],"type":"Point"}
}