{
  "type": "Feature",
  "properties": {
    "addr:full":"Kirkshaws Road Coatbridge North Lanarkshire ML5 4SL",
    "addr:postcode":"ml5 4sl",
    "addr:street":"Kirkshaws Road",
    "iso:country":"GB",
    "sg:address":"Kirkshaws Road",
    "sg:city":"Coatbridge",
    "sg:classifiers":[
        {
            "category":"Sports & Exercise",
            "subcategory":"Golf",
            "type":"Entertainment"
        }
    ],
    "sg:phone":"+44 1236 440687",
    "sg:postcode":"ML5 4SL",
    "sg:province":"North Lanarkshire",
    "sg:tags":[
        "equipment"
    ],
    "wof:name":"Golf Usa Ltd.",
    "wof:placetype":"venue"
},
  "geometry": {"coordinates":[-4.0288391113,55.8439064026],"type":"Point"}
}