{
  "type": "Feature",
  "properties": {
    "iso:country":"GB",
    "sg:address":"Benson Close, Valley Way Enterprise Park",
    "sg:city":"Swansea",
    "sg:classifiers":[
        {
            "category":"Shopping",
            "subcategory":"Beauty & Cosmetics",
            "type":"Retail Goods"
        }
    ],
    "sg:phone":"+44 1792 700118",
    "sg:postcode":"SA6 8RG",
    "sg:province":"Swansea",
    "sg:tags":[
        "product"
    ],
    "wof:name":"Alberto-Culver Co. (U K) Ltd.",
    "wof:placetype":"venue"
},
  "geometry": {"coordinates":[-3.9193310738,51.6551475525],"type":"Point"}
}