{
  "type": "Feature",
  "properties": {
    "addr:full":"1 Whitehall Estate, Flex Meadow, Pinnacles West Harlow Essex CM19 5TJ",
    "addr:housenumber":"1",
    "addr:postcode":"cm19 5tj",
    "addr:street":"Whitehall Estate Flex Meadow Pinnacles West",
    "iso:country":"GB",
    "sg:address":"1 Whitehall Estate, Flex Meadow, Pinnacles West",
    "sg:city":"Harlow",
    "sg:classifiers":[
        {
            "category":"Professional",
            "subcategory":"Testing Lab",
            "type":"Services"
        }
    ],
    "sg:phone":"+44 1279 451774",
    "sg:postcode":"CM19 5TJ",
    "sg:province":"Essex",
    "sg:tags":[
        "laboratory"
    ],
    "wof:name":"Brookfield Viscometers Ltd.",
    "wof:placetype":"venue"
},
  "geometry": {"coordinates":[0.0654599965,51.7619400024],"type":"Point"}
}