{
  "type": "Feature",
  "properties": {
    "iso:country":"GB",
    "sg:address":"Barn Farm, Kexby",
    "sg:city":"York",
    "sg:classifiers":[
        {
            "category":"Home & Garden",
            "subcategory":"Garden Supply",
            "type":"Retail Goods"
        }
    ],
    "sg:postcode":"YO41 5LE",
    "sg:province":"East Riding of Yorkshire",
    "sg:tags":[
        "bulb",
        "grower"
    ],
    "wof:name":"Elliott,O C,",
    "wof:placetype":"venue"
},
  "geometry": {"coordinates":[-0.929258,53.950649],"type":"Point"}
}