{
  "type": "Feature",
  "properties": {
    "iso:country":"GB",
    "sg:address":"5 Ridley Mews, Norton",
    "sg:city":"Billingham",
    "sg:classifiers":[
        {
            "category":"Manufacturing",
            "subcategory":"Tools & Machinery",
            "type":"Manufacturing & Wholesale Goods"
        }
    ],
    "sg:phone":"+44 1642 535555",
    "sg:postcode":"TS20 1DW",
    "sg:province":"Durham",
    "sg:tags":[
        "society",
        "friendly"
    ],
    "wof:name":"Kingbro Insurance",
    "wof:placetype":"venue"
},
  "geometry": {"coordinates":[-1.321271,54.590015],"type":"Point"}
}