{
  "type": "Feature",
  "properties": {
    "addr:full":"Cornwall House, Mynytho Pwllheli Gwynedd LL53 7RH",
    "addr:postcode":"ll53 7rh",
    "iso:country":"GB",
    "sg:address":"Cornwall House, Mynytho",
    "sg:city":"Pwllheli",
    "sg:classifiers":[
        {
            "category":"Building & Trades",
            "subcategory":"Construction",
            "type":"Services"
        }
    ],
    "sg:phone":"+44 1758 740686",
    "sg:postcode":"LL53 7RH",
    "sg:province":"Gwynedd",
    "sg:tags":[
        "decorator",
        "painter"
    ],
    "wof:name":"Sol-Dec",
    "wof:placetype":"venue"
},
  "geometry": {"coordinates":[-4.516604,52.851551],"type":"Point"}
}