{
  "type": "Feature",
  "properties": {
    "addr:full":"3 Higgin Street Burnley Lancashire BB10 4DZ",
    "addr:housenumber":"3",
    "addr:postcode":"bb10 4dz",
    "addr:street":"Higgin Street",
    "iso:country":"GB",
    "sg:address":"3 Higgin Street",
    "sg:city":"Burnley",
    "sg:classifiers":[
        {
            "category":"Bars & Pubs",
            "type":"Food & Drink"
        }
    ],
    "sg:phone":"+44 1282 717669",
    "sg:postcode":"BB10 4DZ",
    "sg:province":"Lancashire",
    "sg:tags":[
        "pubs",
        "inn"
    ],
    "wof:name":"Park View",
    "wof:placetype":"venue"
},
  "geometry": {"coordinates":[-2.230686,53.787182],"type":"Point"}
}