{
  "type": "Feature",
  "properties": {
    "iso:country":"GB",
    "sg:address":"Cow Lane, Bushey",
    "sg:city":"Watford",
    "sg:classifiers":[
        {
            "category":"Retail",
            "subcategory":"Auto Repair",
            "type":"Services"
        }
    ],
    "sg:phone":"+44 20 8950 6838",
    "sg:postcode":"WD24 5BF",
    "sg:province":"Hertfordshire",
    "sg:tags":[
        "modification",
        "garage"
    ],
    "wof:name":"Bushey Car Care",
    "wof:placetype":"venue"
},
  "geometry": {"coordinates":[-0.4089199901,51.6762886047],"type":"Point"}
}