{
  "type": "Feature",
  "properties": {
    "addr:full":"1 Brinks Lane Bolton Lancashire BL2 6QD",
    "addr:housenumber":"1",
    "addr:postcode":"bl2 6qd",
    "addr:street":"Brinks Lane",
    "iso:country":"GB",
    "sg:address":"1 Brinks Lane",
    "sg:city":"Bolton",
    "sg:classifiers":[
        {
            "category":"Building & Trades",
            "subcategory":"Construction",
            "type":"Services"
        }
    ],
    "sg:postcode":"BL2 6QD",
    "sg:province":"Lancashire",
    "sg:tags":[
        "builder"
    ],
    "wof:name":"Williams & Rowley",
    "wof:placetype":"venue"
},
  "geometry": {"coordinates":[-2.373872,53.578529],"type":"Point"}
}