{
  "type": "Feature",
  "properties": {
    "iso:country":"GB",
    "sg:address":"Unit 1, 75 Campbell St, Farnworth",
    "sg:city":"Bolton",
    "sg:classifiers":[
        {
            "category":"Retail",
            "subcategory":"Auto Repair",
            "type":"Services"
        }
    ],
    "sg:postcode":"BL4 7NF",
    "sg:province":"Lancashire",
    "sg:tags":[
        "body",
        "car"
    ],
    "wof:name":"S A Car Sales",
    "wof:placetype":"venue"
},
  "geometry": {"coordinates":[-2.407528,53.554825],"type":"Point"}
}