{
  "type": "Feature",
  "properties": {
    "addr:full":"164 Somerset Road, Handsworth Birmingham West Midlands B20 2JG",
    "addr:housenumber":"164",
    "addr:postcode":"b20 2jg",
    "addr:street":"Somerset Road",
    "iso:country":"GB",
    "sg:address":"164 Somerset Road, Handsworth",
    "sg:city":"Birmingham",
    "sg:classifiers":[
        {
            "category":"Food & Beverages",
            "subcategory":"Meat & Fish",
            "type":"Retail Goods"
        }
    ],
    "sg:postcode":"B20 2JG",
    "sg:province":"West Midlands",
    "sg:tags":[
        "chip"
    ],
    "wof:name":"Fish & Chips",
    "wof:placetype":"venue"
},
  "geometry": {"coordinates":[-1.9341909885,52.5142936707],"type":"Point"}
}