{
  "type": "Feature",
  "properties": {
    "addr:full":"115 Westfaling St Hereford Herefordshire HR4 0JE",
    "addr:housenumber":"115",
    "addr:postcode":"hr4 0je",
    "addr:street":"Westfaling St",
    "iso:country":"GB",
    "sg:address":"115 Westfaling St",
    "sg:city":"Hereford",
    "sg:classifiers":[
        {
            "category":"Retail",
            "subcategory":"Funeral Services",
            "type":"Services"
        }
    ],
    "sg:postcode":"HR4 0JE",
    "sg:province":"Herefordshire",
    "wof:name":"Dawe,Reg,",
    "wof:placetype":"venue"
},
  "geometry": {"coordinates":[-2.7337379456,52.0558815002],"type":"Point"}
}