{
  "type": "Feature",
  "properties": {
    "addr:full":"Market Place Brackley Buckinghamshire NN13 7NN",
    "addr:postcode":"nn13 7nn",
    "addr:street":"Market Place Brackley",
    "iso:country":"GB",
    "sg:address":"Market Place",
    "sg:city":"Brackley",
    "sg:classifiers":[
        {
            "category":"Shopping",
            "subcategory":"Optical Goods",
            "type":"Retail Goods"
        }
    ],
    "sg:phone":"+44 1280 702002",
    "sg:postcode":"NN13 7NN",
    "sg:province":"Buckinghamshire",
    "wof:name":"Cantor & Nissel Ltd.",
    "wof:placetype":"venue"
},
  "geometry": {"coordinates":[-1.1488740444,52.0276031494],"type":"Point"}
}