{
  "type": "Feature",
  "properties": {
    "addr:full":"11 Shrieves Walk Stratford Upon Avon Warwickshire CV37 6GJ",
    "addr:housenumber":"11",
    "addr:postcode":"cv37 6gj",
    "addr:street":"Shrieves Walk",
    "iso:country":"GB",
    "sg:address":"11 Shrieves Walk",
    "sg:city":"Stratford Upon Avon",
    "sg:classifiers":[
        {
            "category":"Shopping",
            "subcategory":"Thrift Store",
            "type":"Retail Goods"
        }
    ],
    "sg:phone":"+44 1789 299258",
    "sg:postcode":"CV37 6GJ",
    "sg:province":"Warwickshire",
    "sg:tags":[
        "shop",
        "charity"
    ],
    "wof:name":"Shakespeare Hospice",
    "wof:placetype":"venue"
},
  "geometry": {"coordinates":[-1.7072689533,52.1941337585],"type":"Point"}
}