{
  "type": "Feature",
  "properties": {
    "iso:country":"GB",
    "sg:address":"South Bank Business Centre, Normanby Rd",
    "sg:city":"Middlesbrough",
    "sg:classifiers":[
        {
            "category":"Utilities",
            "subcategory":"Fuel Oil & Lpg",
            "type":"Services"
        }
    ],
    "sg:phone":"+44 1642 454051",
    "sg:postcode":"TS6 6RS",
    "sg:province":"North Yorkshire",
    "sg:tags":[
        "gas"
    ],
    "wof:name":"Oilfield Services International Ltd",
    "wof:placetype":"venue"
},
  "geometry": {"coordinates":[-1.173174,54.577805],"type":"Point"}
}