{
  "type": "Feature",
  "properties": {
    "addr:full":"10 Floor Southgate House, Wood Street Cardiff Cardiff CF1 1EW",
    "addr:housenumber":"10",
    "addr:postcode":"cf1 1ew",
    "addr:street":"Floor Southgate House Wood Street",
    "iso:country":"GB",
    "sg:address":"10 Floor Southgate House, Wood Street",
    "sg:city":"Cardiff",
    "sg:classifiers":[
        {
            "category":"Professional",
            "subcategory":"Management & Consulting",
            "type":"Services"
        }
    ],
    "sg:postcode":"CF1 1EW",
    "sg:province":"Cardiff",
    "sg:tags":[
        "sport"
    ],
    "wof:name":"Rugby World Cup Tournament Office",
    "wof:placetype":"venue"
},
  "geometry": {"coordinates":[-3.1827991009,51.4761009216],"type":"Point"}
}