{
  "type": "Feature",
  "properties": {
    "addr:full":"57 Sutton Rd Doncaster North Yorkshire DN6 0AQ",
    "addr:housenumber":"57",
    "addr:postcode":"dn6 0aq",
    "addr:street":"Sutton Rd",
    "iso:country":"GB",
    "sg:address":"57 Sutton Rd",
    "sg:city":"Doncaster",
    "sg:classifiers":[
        {
            "category":"Food & Beverages",
            "subcategory":"Meat & Fish",
            "type":"Retail Goods"
        }
    ],
    "sg:postcode":"DN6 0AQ",
    "sg:province":"North Yorkshire",
    "sg:tags":[
        "chip"
    ],
    "wof:name":"Askern Fish & Chips",
    "wof:placetype":"venue"
},
  "geometry": {"coordinates":[-1.157056,53.609409],"type":"Point"}
}