{
  "type": "Feature",
  "properties": {
    "iso:country":"GB",
    "sg:address":"Riverside Industrial Estate, Atherstone Street, Fazeley",
    "sg:city":"Tamworth",
    "sg:classifiers":[
        {
            "category":"Professional",
            "subcategory":"Lawyer & Legal Services",
            "type":"Services"
        }
    ],
    "sg:phone":"+44 1827 60099",
    "sg:postcode":"B78 3RW",
    "sg:province":"Staffordshire",
    "sg:tags":[
        "solicitor"
    ],
    "wof:name":"Blakemores Solicitors",
    "wof:placetype":"venue"
},
  "geometry": {"coordinates":[-1.694909,52.61454],"type":"Point"}
}