{
  "type": "Feature",
  "properties": {
    "addr:full":"Laneside House Penrith Cumbria CA10 2HX",
    "addr:postcode":"ca10 2hx",
    "addr:street":"Penrith",
    "iso:country":"GB",
    "sg:address":"Laneside House",
    "sg:city":"Penrith",
    "sg:classifiers":[
        {
            "category":"Travel",
            "subcategory":"Travel Agent",
            "type":"Entertainment"
        }
    ],
    "sg:postcode":"CA10 2HX",
    "sg:province":"Cumbria",
    "wof:name":"Global Tourism Solutions (Uk) Ltd.",
    "wof:placetype":"venue"
},
  "geometry": {"coordinates":[-2.747818,54.610561],"type":"Point"}
}