{
  "type": "Feature",
  "properties": {
    "iso:country":"GB",
    "sg:address":"296-298 High Holborn",
    "sg:city":"London",
    "sg:classifiers":[
        {
            "category":"Shopping",
            "subcategory":"Books",
            "type":"Retail Goods"
        }
    ],
    "sg:postcode":"WC1V 7JH",
    "sg:province":"Greater London",
    "sg:tags":[
        "bookseller"
    ],
    "wof:name":"Book Warehouse Ltd (The)",
    "wof:placetype":"venue"
},
  "geometry": {"coordinates":[-0.239487,51.548969],"type":"Point"}
}