{
  "type": "Feature",
  "properties": {
    "addr:full":"315 Whitehorse Road Croydon Surrey CR0 2HR",
    "addr:housenumber":"315",
    "addr:postcode":"cr0 2hr",
    "addr:street":"Whitehorse Road",
    "iso:country":"GB",
    "sg:address":"315 Whitehorse Road",
    "sg:city":"Croydon",
    "sg:classifiers":[
        {
            "category":"Home & Garden",
            "subcategory":"Hardware",
            "type":"Retail Goods"
        }
    ],
    "sg:postcode":"CR0 2HR",
    "sg:province":"Surrey",
    "wof:name":"E T Hardware",
    "wof:placetype":"venue"
},
  "geometry": {"coordinates":[-0.093931,51.393776],"type":"Point"}
}