{
  "type": "Feature",
  "properties": {
    "iso:country":"GB",
    "sg:address":"31 Mayfield Road",
    "sg:city":"Sutton",
    "sg:classifiers":[
        {
            "category":"Health Services",
            "subcategory":"Nursing And Care Facility",
            "type":"Services"
        }
    ],
    "sg:phone":"+44 20 8643 1335",
    "sg:postcode":"SM2 5DU",
    "sg:province":"Surrey",
    "sg:tags":[
        "home"
    ],
    "wof:name":"St. Judes Nursing & Residential Home",
    "wof:placetype":"venue"
},
  "geometry": {"coordinates":[-0.1811269969,51.3569602966],"type":"Point"}
}