{
  "type": "Feature",
  "properties": {
    "addr:full":"29 Aire Street Castleford West Yorkshire WF10 1JJ",
    "addr:housenumber":"29",
    "addr:postcode":"wf10 1jj",
    "addr:street":"Aire Street",
    "iso:country":"GB",
    "sg:address":"29 Aire Street",
    "sg:city":"Castleford",
    "sg:classifiers":[
        {
            "category":"Retail",
            "subcategory":"Repair Shop",
            "type":"Services"
        }
    ],
    "sg:phone":"+44 1977 559937",
    "sg:postcode":"WF10 1JJ",
    "sg:province":"West Yorkshire",
    "sg:tags":[
        "upholstering",
        "upholsterer"
    ],
    "wof:name":"Castle Upholstery",
    "wof:placetype":"venue"
},
  "geometry": {"coordinates":[-1.3520989418,53.7275505066],"type":"Point"}
}