{
  "type": "Feature",
  "properties": {
    "addr:full":"19 Lansdowne Cres Durham Durham DH6 5BL",
    "addr:housenumber":"19",
    "addr:postcode":"dh6 5bl",
    "addr:street":"Lansdowne Cres",
    "iso:country":"GB",
    "sg:address":"19 Lansdowne Cres",
    "sg:city":"Durham",
    "sg:classifiers":[
        {
            "category":"Building & Trades",
            "subcategory":"Construction",
            "type":"Services"
        }
    ],
    "sg:phone":"+44 191 377 0774",
    "sg:postcode":"DH6 5BL",
    "sg:province":"Durham",
    "sg:tags":[
        "builder"
    ],
    "wof:name":"D & D A Hindshaw",
    "wof:placetype":"venue"
},
  "geometry": {"coordinates":[-1.5186239481,54.7352104187],"type":"Point"}
}