{
  "type": "Feature",
  "properties": {
    "addr:full":"90 South Street Exeter Devon EX1 1EN",
    "addr:housenumber":"90",
    "addr:postcode":"ex1 1en",
    "addr:street":"South Street",
    "iso:country":"GB",
    "sg:address":"90 South Street",
    "sg:city":"Exeter",
    "sg:classifiers":[
        {
            "category":"Professional",
            "subcategory":"Detective & Security Services",
            "type":"Services"
        }
    ],
    "sg:phone":"+44 1392 420350",
    "sg:postcode":"EX1 1EN",
    "sg:province":"Devon",
    "sg:tags":[
        "equipment",
        "locksmith",
        "installers"
    ],
    "wof:name":"Five Star Security Services (S W) L",
    "wof:placetype":"venue"
},
  "geometry": {"coordinates":[-3.5320949554,50.7218666077],"type":"Point"}
}