{
  "type": "Feature",
  "properties": {
    "addr:full":"7 Firwood Drive Camberley Berkshire GU15 3QD",
    "addr:housenumber":"7",
    "addr:postcode":"gu15 3qd",
    "addr:street":"Firwood Drive",
    "iso:country":"GB",
    "sg:address":"7 Firwood Drive",
    "sg:city":"Camberley",
    "sg:classifiers":[
        {
            "category":"Shopping",
            "subcategory":"Computers & Home Electronics",
            "type":"Retail Goods"
        },
        {
            "category":"Professional",
            "subcategory":"Computer Services",
            "type":"Services"
        }
    ],
    "sg:phone":"+44 1276 501100",
    "sg:postcode":"GU15 3QD",
    "sg:province":"Berkshire",
    "sg:tags":[
        "software",
        "sales",
        "system"
    ],
    "sg:website":"http://www.ovidnet.com",
    "wof:name":"Ovid",
    "wof:placetype":"venue"
},
  "geometry": {"coordinates":[-0.748562,51.335648],"type":"Point"}
}