{
  "type": "Feature",
  "properties": {
    "addr:full":"Hays Way Westhill Aberdeen City AB32 6XZ",
    "addr:postcode":"ab32 6xz",
    "addr:street":"Hays Way",
    "iso:country":"GB",
    "sg:address":"Hays Way",
    "sg:city":"Westhill",
    "sg:classifiers":[
        {
            "category":"Education",
            "subcategory":"School",
            "type":"Public Place"
        },
        {
            "category":"Community Center",
            "type":"Public Place"
        },
        {
            "category":"Government",
            "subcategory":"Office",
            "type":"Public Place"
        }
    ],
    "sg:phone":"+44 1224 740111",
    "sg:postcode":"AB32 6XZ",
    "sg:province":"Aberdeen City",
    "sg:tags":[
        "local",
        "authority",
        "centre"
    ],
    "wof:name":"Westhill Academy",
    "wof:placetype":"venue"
},
  "geometry": {"coordinates":[-2.2806138992,57.1568603516],"type":"Point"}
}