{
  "type": "Feature",
  "properties": {
    "iso:country":"GB",
    "sg:address":"East Farm, East Langdon",
    "sg:city":"Dover",
    "sg:classifiers":[
        {
            "category":"Manufacturing",
            "subcategory":"Rubber & Plastics",
            "type":"Manufacturing & Wholesale Goods"
        }
    ],
    "sg:phone":"+44 1304 852832",
    "sg:postcode":"CT15 5JF",
    "sg:province":"Kent",
    "sg:tags":[
        "product"
    ],
    "wof:name":"Kent Polyurethane Mouldings Ltd",
    "wof:placetype":"venue"
},
  "geometry": {"coordinates":[1.3369129896,51.1672325134],"type":"Point"}
}