{
  "type": "Feature",
  "properties": {
    "addr:full":"Kensham House, Bradninch Exeter Devon EX5 4RD",
    "addr:postcode":"ex5 4rd",
    "iso:country":"GB",
    "sg:address":"Kensham House, Bradninch",
    "sg:city":"Exeter",
    "sg:classifiers":[
        {
            "category":"Retail",
            "subcategory":"Driving School",
            "type":"Services"
        }
    ],
    "sg:phone":"+44 1392 881460",
    "sg:postcode":"EX5 4RD",
    "sg:province":"Devon",
    "wof:name":"Iscal Driving Tuition",
    "wof:placetype":"venue"
},
  "geometry": {"coordinates":[-3.421899,50.826908],"type":"Point"}
}