{
  "type": "Feature",
  "properties": {
    "addr:full":"3a Newbold Rd Rugby Warwickshire CV21 2NU",
    "addr:housenumber":"3a",
    "addr:postcode":"cv21 2nu",
    "addr:street":"Newbold Rd",
    "iso:country":"GB",
    "sg:address":"3a Newbold Rd",
    "sg:city":"Rugby",
    "sg:classifiers":[
        {
            "category":"Manufacturing",
            "subcategory":"Tools & Machinery",
            "type":"Manufacturing & Wholesale Goods"
        }
    ],
    "sg:postcode":"CV21 2NU",
    "sg:province":"Warwickshire",
    "sg:tags":[
        "society",
        "friendly"
    ],
    "wof:name":"Regional Financial Planning",
    "wof:placetype":"venue"
},
  "geometry": {"coordinates":[-1.2647889853,52.3757019043],"type":"Point"}
}