{
  "type": "Feature",
  "properties": {
    "iso:country":"GB",
    "sg:address":"2 Nabby Nook, Charlestown",
    "sg:city":"Hebden Bridge",
    "sg:classifiers":[
        {
            "category":"Professional",
            "subcategory":"Accounting & Tax Preparation",
            "type":"Services"
        }
    ],
    "sg:phone":"+44 1422 842626",
    "sg:postcode":"HX7 6PS",
    "sg:province":"West Yorkshire",
    "sg:tags":[
        "accountant"
    ],
    "wof:name":"R. Packwood Accountants",
    "wof:placetype":"venue"
},
  "geometry": {"coordinates":[-2.014491,53.741226],"type":"Point"}
}