{
  "type": "Feature",
  "properties": {
    "iso:country":"GB",
    "sg:address":"Unit 5 Gunhill Industrial Estate, Gunhill Road",
    "sg:city":"Doncaster",
    "sg:classifiers":[
        {
            "category":"Professional",
            "subcategory":"Engineering",
            "type":"Services"
        }
    ],
    "sg:phone":"+44 1302 835416",
    "sg:postcode":"DN3 3EF",
    "sg:province":"South Yorkshire",
    "sg:tags":[
        "precision",
        "engineer"
    ],
    "wof:name":"T & M Engineering Tool Makers",
    "wof:placetype":"venue"
},
  "geometry": {"coordinates":[-1.0436120033,53.5383872986],"type":"Point"}
}