{
  "type": "Feature",
  "properties": {
    "addr:full":"5a Thurlow St Bedford Bedfordshire MK40 1LR",
    "addr:housenumber":"5a",
    "addr:postcode":"mk40 1lr",
    "addr:street":"Thurlow St",
    "iso:country":"GB",
    "sg:address":"5a Thurlow St",
    "sg:city":"Bedford",
    "sg:classifiers":[
        {
            "category":"Health Services",
            "subcategory":"Dentist",
            "type":"Services"
        }
    ],
    "sg:phone":"+44 1234 351327",
    "sg:postcode":"MK40 1LR",
    "sg:province":"Bedfordshire",
    "sg:tags":[
        "technician",
        "dental"
    ],
    "wof:name":"Castle Dental Laboratory",
    "wof:placetype":"venue"
},
  "geometry": {"coordinates":[-0.470755,52.137123],"type":"Point"}
}