{
  "type": "Feature",
  "properties": {
    "iso:country":"GB",
    "sg:address":"3 Stompits Road, Holyport",
    "sg:city":"Maidenhead",
    "sg:classifiers":[
        {
            "category":"Food & Beverages",
            "subcategory":"Fruits & Vegetables",
            "type":"Retail Goods"
        }
    ],
    "sg:phone":"+44 1628 629216",
    "sg:postcode":"SL6 2LA",
    "sg:province":"Berkshire",
    "sg:tags":[
        "greengrocer"
    ],
    "wof:name":"Chemist",
    "wof:placetype":"venue"
},
  "geometry": {"coordinates":[-0.709421,51.493347],"type":"Point"}
}