{
  "type": "Feature",
  "properties": {
    "addr:full":"83 Buckingham Palace Rd London Greater London SW1W 0QJ",
    "addr:housenumber":"83",
    "addr:postcode":"sw1w 0qj",
    "addr:street":"Buckingham Palace Rd",
    "iso:country":"GB",
    "sg:address":"83 Buckingham Palace Rd",
    "sg:city":"London",
    "sg:classifiers":[
        {
            "category":"Travel",
            "subcategory":"Travel Agent",
            "type":"Entertainment"
        }
    ],
    "sg:phone":"+44 20 7630 5188",
    "sg:postcode":"SW1W 0QJ",
    "sg:province":"Greater London",
    "wof:name":"Inter Europe Travel Ltd",
    "wof:placetype":"venue"
},
  "geometry": {"coordinates":[-0.145189,51.49617],"type":"Point"}
}