{
  "type": "Feature",
  "properties": {
    "addr:full":"14 Nightingale Road Horsham West Sussex RH12 2NW",
    "addr:housenumber":"14",
    "addr:postcode":"rh12 2nw",
    "addr:street":"Nightingale Road",
    "iso:country":"GB",
    "sg:address":"14 Nightingale Road",
    "sg:city":"Horsham",
    "sg:classifiers":[
        {
            "category":"Professional",
            "subcategory":"Detective & Security Services",
            "type":"Services"
        }
    ],
    "sg:phone":"+44 1403 264408",
    "sg:postcode":"RH12 2NW",
    "sg:province":"West Sussex",
    "sg:tags":[
        "alarm",
        "burglar",
        "system"
    ],
    "wof:name":"Tcom Group Ltd.",
    "wof:placetype":"venue"
},
  "geometry": {"coordinates":[-0.319679,51.06916],"type":"Point"}
}