{
  "type": "Feature",
  "properties": {
    "iso:country":"GB",
    "sg:address":"Northover, Ilchester",
    "sg:city":"Yeovil",
    "sg:classifiers":[
        {
            "category":"Travel",
            "subcategory":"Hotels & Motels",
            "type":"Entertainment"
        }
    ],
    "sg:phone":"+44 1935 841193",
    "sg:postcode":"BA22 8NG",
    "sg:province":"Dorset",
    "sg:tags":[
        "house",
        "guest"
    ],
    "wof:name":"Liongate House Bed & Breakfast",
    "wof:placetype":"venue"
},
  "geometry": {"coordinates":[-2.6805000305,51.010848999],"type":"Point"}
}