{
  "type": "Feature",
  "properties": {
    "addr:full":"14 Cremyll Road Reading Berkshire RG1 8NQ",
    "addr:housenumber":"14",
    "addr:postcode":"rg1 8nq",
    "addr:street":"Cremyll Road",
    "iso:country":"GB",
    "sg:address":"14 Cremyll Road",
    "sg:city":"Reading",
    "sg:classifiers":[
        {
            "category":"Professional",
            "subcategory":"Printing & Photocopies",
            "type":"Services"
        }
    ],
    "sg:phone":"+44 118 939 3838",
    "sg:postcode":"RG1 8NQ",
    "sg:province":"Berkshire",
    "sg:tags":[
        "printer"
    ],
    "wof:name":"The Riverside Printing Co. (Reading) Ltd.",
    "wof:placetype":"venue"
},
  "geometry": {"coordinates":[-0.9819560051,51.4634361267],"type":"Point"}
}