{
  "type": "Feature",
  "properties": {
    "addr:full":"2 Cross Street, Caerleon Newport Monmouthshire NP18 1AF",
    "addr:housenumber":"2",
    "addr:postcode":"np18 1af",
    "addr:street":"Cross Street",
    "iso:country":"GB",
    "sg:address":"2 Cross Street, Caerleon",
    "sg:city":"Newport",
    "sg:classifiers":[
        {
            "category":"Restaurant",
            "type":"Food & Drink"
        }
    ],
    "sg:phone":"+44 1633 422489",
    "sg:postcode":"NP18 1AF",
    "sg:province":"Monmouthshire",
    "sg:tags":[
        "indian",
        "-"
    ],
    "sg:website":"http://www.bagan.co.uk",
    "wof:name":"Bagan Tandoori Restaurant",
    "wof:placetype":"venue"
},
  "geometry": {"coordinates":[-2.9519639015,51.6107406616],"type":"Point"}
}