{
  "type": "Feature",
  "properties": {
    "addr:full":"3 Royal Terrace Southend-on-sea Essex SS1 1DY",
    "addr:housenumber":"3",
    "addr:postcode":"ss1 1dy",
    "addr:street":"Royal Terrace",
    "iso:country":"GB",
    "sg:address":"3 Royal Terrace",
    "sg:city":"Southend-on-sea",
    "sg:classifiers":[
        {
            "category":"Professional",
            "subcategory":"Accounting & Tax Preparation",
            "type":"Services"
        }
    ],
    "sg:phone":"+44 1702 434040",
    "sg:postcode":"SS1 1DY",
    "sg:province":"Essex",
    "sg:tags":[
        "accountant"
    ],
    "wof:name":"Lawfords Ltd.",
    "wof:placetype":"venue"
},
  "geometry": {"coordinates":[0.714117,51.534153],"type":"Point"}
}