{
  "type": "Feature",
  "properties": {
    "addr:full":"Biggin Hill Airport, Biggin Hill Westerham Kent TN16 3BN",
    "addr:postcode":"tn16 3bn",
    "iso:country":"GB",
    "sg:address":"Biggin Hill Airport, Biggin Hill",
    "sg:city":"Westerham",
    "sg:classifiers":[
        {
            "category":"Shopping",
            "subcategory":"Musical Instruments",
            "type":"Retail Goods"
        }
    ],
    "sg:phone":"+44 1959 572251",
    "sg:postcode":"TN16 3BN",
    "sg:province":"Kent",
    "wof:name":"Vendair (London) Ltd.",
    "wof:placetype":"venue"
},
  "geometry": {"coordinates":[0.0359760001,51.3104667664],"type":"Point"}
}