{
  "type": "Feature",
  "properties": {
    "addr:full":"138 Victoria Road West Thornton-cleveleys Lancashire FY5 3LG",
    "addr:housenumber":"138",
    "addr:postcode":"fy5 3lg",
    "addr:street":"Victoria Road West Thornton-Cleveleys",
    "iso:country":"GB",
    "sg:address":"138 Victoria Road West",
    "sg:city":"Thornton-cleveleys",
    "sg:classifiers":[
        {
            "category":"Communications",
            "subcategory":"Newspaper",
            "type":"Services"
        },
        {
            "category":"Wholesale",
            "subcategory":"Books, Periodicals, & Newspapers",
            "type":"Manufacturing & Wholesale Goods"
        }
    ],
    "sg:phone":"+44 1253 864133",
    "sg:postcode":"FY5 3LG",
    "sg:province":"Lancashire",
    "sg:tags":[
        "magazine",
        "publishing"
    ],
    "wof:name":"Evening Gazette",
    "wof:placetype":"venue"
},
  "geometry": {"coordinates":[-3.0218780041,53.8742752075],"type":"Point"}
}