{
  "type": "Feature",
  "properties": {
    "addr:full":"66 St Giles Street Northampton Northamptonshire NN1 1JW",
    "addr:housenumber":"66",
    "addr:postcode":"nn1 1jw",
    "addr:street":"St Giles Street",
    "iso:country":"GB",
    "sg:address":"66 St Giles Street",
    "sg:city":"Northampton",
    "sg:classifiers":[
        {
            "category":"Personal",
            "subcategory":"Barber",
            "type":"Services"
        }
    ],
    "sg:phone":"+44 1604 601400",
    "sg:postcode":"NN1 1JW",
    "sg:province":"Northamptonshire",
    "sg:tags":[
        "men's",
        "gents",
        "hairdresser"
    ],
    "wof:name":"Andrews Hair Salon",
    "wof:placetype":"venue"
},
  "geometry": {"coordinates":[-0.891752,52.237453],"type":"Point"}
}