{
  "type": "Feature",
  "properties": {
    "iso:country":"GB",
    "sg:address":"319 London Road, Hadleigh",
    "sg:city":"Benfleet",
    "sg:classifiers":[
        {
            "category":"Real Estate",
            "subcategory":"Surveying",
            "type":"Services"
        }
    ],
    "sg:phone":"+44 1702 559365",
    "sg:postcode":"SS7 2BN",
    "sg:province":"Essex",
    "sg:tags":[
        "surveyor",
        "valuer"
    ],
    "wof:name":"Wheeldon & Deacon",
    "wof:placetype":"venue"
},
  "geometry": {"coordinates":[0.612408,51.552246],"type":"Point"}
}