{
  "type": "Feature",
  "properties": {
    "addr:full":"105 Stoke Newington Church Stree, T London Greater London N16 0UD",
    "addr:housenumber":"105",
    "addr:postcode":"n16 0ud",
    "addr:street":"Stoke Newington;Stree T",
    "iso:country":"GB",
    "sg:address":"105 Stoke Newington Church Stree, T",
    "sg:city":"London",
    "sg:classifiers":[
        {
            "category":"Bars & Pubs",
            "type":"Food & Drink"
        }
    ],
    "sg:postcode":"N16 0UD",
    "sg:province":"Greater London",
    "sg:tags":[
        "pubs",
        "inn"
    ],
    "wof:name":"The Auld Shillelagh",
    "wof:placetype":"venue"
},
  "geometry": {"coordinates":[-0.0794,51.56205],"type":"Point"}
}