{
  "type": "Feature",
  "properties": {
    "addr:full":"Downs Way Indust Est Dumfries Dumfries and Galloway DG1 3RS",
    "addr:postcode":"dg1 3rs",
    "addr:street":"Downs Way",
    "iso:country":"GB",
    "sg:address":"Downs Way Indust Est",
    "sg:city":"Dumfries",
    "sg:classifiers":[
        {
            "category":"Manufacturing",
            "subcategory":"Metals",
            "type":"Manufacturing & Wholesale Goods"
        }
    ],
    "sg:phone":"+44 1387 261024",
    "sg:postcode":"DG1 3RS",
    "sg:province":"Dumfries and Galloway",
    "sg:tags":[
        "steel",
        "fabricator",
        "erectors"
    ],
    "wof:name":"Robert Mcturk & Co",
    "wof:placetype":"venue"
},
  "geometry": {"coordinates":[-3.581014,55.093487],"type":"Point"}
}