{
  "type": "Feature",
  "properties": {
    "addr:full":"Lin Cluden House, 112 Crescent Road Reading Berkshire RG1 5SN",
    "addr:housenumber":"112",
    "addr:postcode":"rg1 5sn",
    "addr:street":"Crescent Road",
    "iso:country":"GB",
    "sg:address":"Lin Cluden House, 112 Crescent Road",
    "sg:city":"Reading",
    "sg:classifiers":[
        {
            "category":"Professional",
            "subcategory":"Management & Consulting",
            "type":"Services"
        },
        {
            "category":"Personal",
            "type":"Services"
        }
    ],
    "sg:phone":"+44 118 926 7935",
    "sg:postcode":"RG1 5SN",
    "sg:province":"Berkshire",
    "sg:tags":[
        "environmental",
        "stress",
        "consultant"
    ],
    "wof:name":"Cheviot Artus Plc",
    "wof:placetype":"venue"
},
  "geometry": {"coordinates":[-0.943656,51.448334],"type":"Point"}
}