{
  "type": "Feature",
  "properties": {
    "addr:full":"352 Loxley Road Sheffield South Yorkshire S6 4TJ",
    "addr:housenumber":"352",
    "addr:postcode":"s6 4tj",
    "addr:street":"Loxley Road",
    "iso:country":"GB",
    "sg:address":"352 Loxley Road",
    "sg:city":"Sheffield",
    "sg:classifiers":[
        {
            "category":"Shopping",
            "subcategory":"Stationery & Office Supplies",
            "type":"Retail Goods"
        },
        {
            "category":"Communications",
            "subcategory":"News Services",
            "type":"Services"
        }
    ],
    "sg:phone":"+44 114 234 3571",
    "sg:postcode":"S6 4TJ",
    "sg:province":"South Yorkshire",
    "sg:tags":[
        "press",
        "packaging",
        "equipment"
    ],
    "wof:name":"LEONARD HALL (PATTERNS) LTD",
    "wof:placetype":"venue"
},
  "geometry": {"coordinates":[-1.521623,53.402809],"type":"Point"}
}