{
  "type": "Feature",
  "properties": {
    "addr:full":"385 Whitehall Road Leeds West Yorkshire LS12 6LB",
    "addr:housenumber":"385",
    "addr:postcode":"ls12 6lb",
    "addr:street":"Whitehall Road",
    "iso:country":"GB",
    "sg:address":"385 Whitehall Road",
    "sg:city":"Leeds",
    "sg:classifiers":[
        {
            "category":"Fast Food",
            "type":"Food & Drink"
        }
    ],
    "sg:phone":"+44 113 231 9931",
    "sg:postcode":"LS12 6LB",
    "sg:province":"West Yorkshire",
    "sg:tags":[
        "away",
        "take"
    ],
    "wof:name":"Pizza Top",
    "wof:placetype":"venue"
},
  "geometry": {"coordinates":[-1.599717,53.780964],"type":"Point"}
}