{
  "type": "Feature",
  "properties": {
    "addr:full":"South Farm, Farnham Blandford Forum Dorset DT11 8DE",
    "addr:housenumber":"farnham",
    "addr:postcode":"dt11 8de",
    "addr:street":"South",
    "iso:country":"GB",
    "sg:address":"South Farm, Farnham",
    "sg:city":"Blandford Forum",
    "sg:classifiers":[
        {
            "category":"Farming",
            "subcategory":"Livestock Farm",
            "type":"Manufacturing & Wholesale Goods"
        }
    ],
    "sg:phone":"+44 1725 516340",
    "sg:postcode":"DT11 8DE",
    "sg:province":"Dorset",
    "sg:tags":[
        "others"
    ],
    "wof:name":"Nicholas Miller",
    "wof:placetype":"venue"
},
  "geometry": {"coordinates":[-2.0587120056,50.9351196289],"type":"Point"}
}