{
  "type": "Feature",
  "properties": {
    "addr:full":"7 John St Wakefield West Yorkshire WF1 4PN",
    "addr:housenumber":"7",
    "addr:postcode":"wf1 4pn",
    "addr:street":"John St",
    "iso:country":"GB",
    "sg:address":"7 John St",
    "sg:city":"Wakefield",
    "sg:classifiers":[
        {
            "category":"Building & Trades",
            "subcategory":"Construction",
            "type":"Services"
        }
    ],
    "sg:phone":"+44 1924 371274",
    "sg:postcode":"WF1 4PN",
    "sg:province":"West Yorkshire",
    "sg:tags":[
        "joiner",
        "carpenter"
    ],
    "wof:name":"G Wilcox & Sons",
    "wof:placetype":"venue"
},
  "geometry": {"coordinates":[-1.489668,53.680683],"type":"Point"}
}