{
  "type": "Feature",
  "properties": {
    "iso:country":"GB",
    "sg:address":"43 High Street",
    "sg:city":"Kington",
    "sg:classifiers":[
        {
            "category":"Shopping",
            "subcategory":"Stationery & Office Supplies",
            "type":"Retail Goods"
        },
        {
            "category":"Shopping",
            "subcategory":"Gifts & Souvenirs",
            "type":"Retail Goods"
        }
    ],
    "sg:phone":"+44 1544 230103",
    "sg:postcode":"HR5 3BJ",
    "sg:province":"Herefordshire",
    "sg:tags":[
        "shop",
        "poster",
        "card"
    ],
    "wof:name":"Peacehaven Cards",
    "wof:placetype":"venue"
},
  "geometry": {"coordinates":[-3.029996,52.20348],"type":"Point"}
}