{
  "type": "Feature",
  "properties": {
    "addr:full":"1 Market Arcade Newport Newport NP20 1FS",
    "addr:housenumber":"1",
    "addr:postcode":"np20 1fs",
    "addr:street":"Market Arcade",
    "iso:country":"GB",
    "sg:address":"1 Market Arcade",
    "sg:city":"Newport",
    "sg:classifiers":[
        {
            "category":"Personal",
            "subcategory":"Tattoo Parlor",
            "type":"Services"
        }
    ],
    "sg:postcode":"NP20 1FS",
    "sg:province":"Newport",
    "sg:tags":[
        "tattooing",
        "piercing"
    ],
    "wof:name":"A Thompson",
    "wof:placetype":"venue"
},
  "geometry": {"coordinates":[-2.9964439869,51.5895881653],"type":"Point"}
}