{
  "type": "Feature",
  "properties": {
    "addr:full":"Halsbeer Farm Cullompton Devon EX15 2HN",
    "addr:housenumber":"cullompton",
    "addr:postcode":"ex15 2hn",
    "addr:street":"Devon",
    "iso:country":"GB",
    "sg:address":"Halsbeer Farm",
    "sg:city":"Cullompton",
    "sg:classifiers":[
        {
            "category":"Farming",
            "subcategory":"Livestock Farm",
            "type":"Manufacturing & Wholesale Goods"
        }
    ],
    "sg:phone":"+44 1884 266259",
    "sg:postcode":"EX15 2HN",
    "sg:province":"Devon",
    "sg:tags":[
        "others"
    ],
    "wof:name":"C L Snell",
    "wof:placetype":"venue"
},
  "geometry": {"coordinates":[-3.392634,50.858166],"type":"Point"}
}