{
  "type": "Feature",
  "properties": {
    "addr:full":"277 Buxton Road Macclesfield Cheshire SK11 7ET",
    "addr:housenumber":"277",
    "addr:postcode":"sk11 7et",
    "addr:street":"Buxton Road",
    "iso:country":"GB",
    "sg:address":"277 Buxton Road",
    "sg:city":"Macclesfield",
    "sg:classifiers":[
        {
            "category":"Health Services",
            "subcategory":"Health Practitioner",
            "type":"Services"
        }
    ],
    "sg:phone":"+44 1625 611183",
    "sg:postcode":"SK11 7ET",
    "sg:province":"Cheshire",
    "sg:tags":[
        "osteopath"
    ],
    "wof:name":"John Michael Gardiner",
    "wof:placetype":"venue"
},
  "geometry": {"coordinates":[-2.1099579334,53.2578048706],"type":"Point"}
}