{
  "type": "Feature",
  "properties": {
    "addr:full":"10 Binley Road Coventry Warwickshire CV3 1HZ",
    "addr:housenumber":"10",
    "addr:postcode":"cv3 1hz",
    "addr:street":"Binley Road",
    "iso:country":"GB",
    "sg:address":"10 Binley Road",
    "sg:city":"Coventry",
    "sg:classifiers":[
        {
            "category":"Personal",
            "subcategory":"Beauty Salon",
            "type":"Services"
        }
    ],
    "sg:phone":"+44 24 7622 4857",
    "sg:postcode":"CV3 1HZ",
    "sg:province":"Warwickshire",
    "sg:tags":[
        "unisex",
        "hairdresser"
    ],
    "wof:name":"Gosford Park Salon",
    "wof:placetype":"venue"
},
  "geometry": {"coordinates":[-1.491905,52.407734],"type":"Point"}
}