{
  "type": "Feature",
  "properties": {
    "addr:full":"High Street Aldershot Hampshire GU11 1DJ",
    "addr:postcode":"gu11 1dj",
    "addr:street":"High Street",
    "iso:country":"GB",
    "sg:address":"High Street",
    "sg:city":"Aldershot",
    "sg:classifiers":[
        {
            "category":"Cinema",
            "subcategory":"Movie Theater",
            "type":"Entertainment"
        }
    ],
    "sg:phone":"+44 1252 317223",
    "sg:postcode":"GU11 1DJ",
    "sg:province":"Hampshire",
    "wof:name":"A B C Cinema",
    "wof:placetype":"venue"
},
  "geometry": {"coordinates":[-0.765563,51.250134],"type":"Point"}
}