{
  "type": "Feature",
  "properties": {
    "iso:country":"GB",
    "sg:address":"6/8 Bank Villas, Jerry Lane",
    "sg:city":"Sowerby Bridge",
    "sg:classifiers":[
        {
            "category":"Organizations",
            "subcategory":"Non-profit Organization",
            "type":"Services"
        }
    ],
    "sg:phone":"+44 1422 835542",
    "sg:postcode":"HX6 3BH",
    "sg:province":"West Yorkshire",
    "sg:tags":[
        "organisation",
        "voluntary",
        "charity"
    ],
    "wof:name":"Catholic Care",
    "wof:placetype":"venue"
},
  "geometry": {"coordinates":[-1.913934,53.706539],"type":"Point"}
}