{
  "type": "Feature",
  "properties": {
    "iso:country":"GB",
    "sg:address":"11 Dagmar Road",
    "sg:city":"Dorchester",
    "sg:classifiers":[
        {
            "category":"Education",
            "subcategory":"Music School",
            "type":"Public Place"
        },
        {
            "category":"Home & Garden",
            "subcategory":"Building Materials",
            "type":"Retail Goods"
        }
    ],
    "sg:phone":"+44 1305 261539",
    "sg:postcode":"DT1 2NA",
    "sg:province":"Dorset",
    "sg:tags":[
        "garage",
        "window",
        "door",
        "frame",
        "conservatory"
    ],
    "wof:name":"Acorn Conservatories Ltd.",
    "wof:placetype":"venue"
},
  "geometry": {"coordinates":[-2.444415,50.710464],"type":"Point"}
}