{
  "type": "Feature",
  "properties": {
    "addr:full":"24 St Faiths Lane Norwich Norfolk NR1 1NN",
    "addr:housenumber":"24",
    "addr:postcode":"nr1 1nn",
    "addr:street":"St Faiths Lane",
    "iso:country":"GB",
    "sg:address":"24 St Faiths Lane",
    "sg:city":"Norwich",
    "sg:classifiers":[
        {
            "category":"Shopping",
            "subcategory":"Stationery & Office Supplies",
            "type":"Retail Goods"
        }
    ],
    "sg:phone":"+44 1603 627822",
    "sg:postcode":"NR1 1NN",
    "sg:province":"Norfolk",
    "sg:tags":[
        "equipment"
    ],
    "wof:name":"Leonards Office Equipment",
    "wof:placetype":"venue"
},
  "geometry": {"coordinates":[1.3035789728,52.6294517517],"type":"Point"}
}