{
  "type": "Feature",
  "properties": {
    "iso:country":"GB",
    "sg:address":"100 Somerville Street",
    "sg:city":"Burntisland",
    "sg:classifiers":[
        {
            "category":"Health Services",
            "subcategory":"Dentist",
            "type":"Services"
        }
    ],
    "sg:postcode":"KY3 9DH",
    "sg:province":"Fife",
    "wof:name":"Helen Macdonald",
    "wof:placetype":"venue"
},
  "geometry": {"coordinates":[-3.230374,56.059303],"type":"Point"}
}