{
  "type": "Feature",
  "properties": {
    "addr:full":"42 Clifton Street Blackpool Lancashire FY1 1JP",
    "addr:housenumber":"42",
    "addr:postcode":"fy1 1jp",
    "addr:street":"Clifton Street",
    "iso:country":"GB",
    "sg:address":"42 Clifton Street",
    "sg:city":"Blackpool",
    "sg:classifiers":[
        {
            "category":"Cafe",
            "type":"Food & Drink"
        }
    ],
    "sg:phone":"+44 1253 751927",
    "sg:postcode":"FY1 1JP",
    "sg:province":"Lancashire",
    "sg:tags":[
        "tea",
        "room"
    ],
    "wof:name":"Cromwells Coffee Lounge",
    "wof:placetype":"venue"
},
  "geometry": {"coordinates":[-3.0529739857,53.8189430237],"type":"Point"}
}