{
  "type": "Feature",
  "properties": {
    "addr:full":"3 The Oaks Taunton Somerset TA1 2QX",
    "addr:housenumber":"3",
    "addr:postcode":"ta1 2qx",
    "addr:street":"The Oaks",
    "iso:country":"GB",
    "sg:address":"3 The Oaks",
    "sg:city":"Taunton",
    "sg:classifiers":[
        {
            "category":"Professional",
            "type":"Services"
        },
        {
            "category":"Professional",
            "subcategory":"Business Services",
            "type":"Services"
        }
    ],
    "sg:phone":"+44 1823 283223",
    "sg:postcode":"TA1 2QX",
    "sg:province":"Somerset",
    "sg:tags":[
        "distribution",
        "provider"
    ],
    "wof:name":"I B F Distribution",
    "wof:placetype":"venue"
},
  "geometry": {"coordinates":[-3.083190918,51.0050964355],"type":"Point"}
}