{
  "type": "Feature",
  "properties": {
    "iso:country":"GB",
    "sg:address":"Lynn Road, Weeting",
    "sg:city":"Brandon",
    "sg:classifiers":[
        {
            "category":"Organizations",
            "subcategory":"Membership Organization",
            "type":"Services"
        }
    ],
    "sg:phone":"+44 1842 815538",
    "sg:postcode":"IP27 0QS",
    "sg:province":"Norfolk",
    "sg:tags":[
        "club"
    ],
    "wof:name":"Weeting Bowls Club",
    "wof:placetype":"venue"
},
  "geometry": {"coordinates":[0.6262050271,52.442741394],"type":"Point"}
}