{
  "type": "Feature",
  "properties": {
    "addr:full":"1 Huntingdon Rd Cambridge Cambridgeshire CB3 0DB",
    "addr:housenumber":"1",
    "addr:postcode":"cb3 0db",
    "addr:street":"Huntingdon Rd",
    "iso:country":"GB",
    "sg:address":"1 Huntingdon Rd",
    "sg:city":"Cambridge",
    "sg:classifiers":[
        {
            "category":"Health Services",
            "subcategory":"Clinic",
            "type":"Services"
        }
    ],
    "sg:phone":"+44 1223 313969",
    "sg:postcode":"CB3 0DB",
    "sg:province":"Cambridgeshire",
    "sg:tags":[
        "private"
    ],
    "wof:name":"British Airways Travel Clinics",
    "wof:placetype":"venue"
},
  "geometry": {"coordinates":[0.110227,52.213959],"type":"Point"}
}