{
  "type": "Feature",
  "properties": {
    "addr:full":"Millers Road, Byker Newcastle-upon-tyne Tyne and Wear NE6 2XP",
    "addr:postcode":"ne6 2xp",
    "addr:street":"Millers Road",
    "iso:country":"GB",
    "sg:address":"Millers Road, Byker",
    "sg:city":"Newcastle-upon-tyne",
    "sg:classifiers":[
        {
            "category":"Retail",
            "subcategory":"Auto Repair",
            "type":"Services"
        }
    ],
    "sg:phone":"+44 191 276 3724",
    "sg:postcode":"NE6 2XP",
    "sg:province":"Tyne and Wear",
    "sg:tags":[
        "modification",
        "garage"
    ],
    "wof:name":"Eric Christer Millers Rd Garage",
    "wof:placetype":"venue"
},
  "geometry": {"coordinates":[-1.573834,54.978489],"type":"Point"}
}