{
  "type": "Feature",
  "properties": {
    "addr:full":"Is Helen Farm Caernarfon Gwynedd LL54 5RN",
    "addr:postcode":"ll54 5rn",
    "addr:street":"Caernarfon",
    "iso:country":"GB",
    "sg:address":"Is Helen Farm",
    "sg:city":"Caernarfon",
    "sg:classifiers":[
        {
            "category":"Farming",
            "subcategory":"Dairy Farm",
            "type":"Manufacturing & Wholesale Goods"
        }
    ],
    "sg:phone":"+44 1286 678497",
    "sg:postcode":"LL54 5RN",
    "sg:province":"Gwynedd",
    "sg:tags":[
        "farmer"
    ],
    "wof:name":"Ifor Owen",
    "wof:placetype":"venue"
},
  "geometry": {"coordinates":[-4.29152,53.133499],"type":"Point"}
}