{
  "type": "Feature",
  "properties": {
    "addr:full":"26-30 Rainhall Road Barnoldswick Lancashire BB18 5DR",
    "addr:housenumber":"26-30",
    "addr:postcode":"bb18 5dr",
    "addr:street":"Rainhall Road",
    "iso:country":"GB",
    "sg:address":"26-30 Rainhall Road",
    "sg:city":"Barnoldswick",
    "sg:classifiers":[
        {
            "category":"Shopping",
            "subcategory":"Pharmacy",
            "type":"Retail Goods"
        }
    ],
    "sg:phone":"+44 1282 812195",
    "sg:postcode":"BB18 5DR",
    "sg:province":"Lancashire",
    "sg:tags":[
        "pharmacist",
        "chemist"
    ],
    "wof:name":"Gary Hush Pharmacy",
    "wof:placetype":"venue"
},
  "geometry": {"coordinates":[-2.186504,53.915752],"type":"Point"}
}