{
  "type": "Feature",
  "properties": {
    "addr:full":"75 Ocean Road South Shields Tyne and Wear NE33 2JJ",
    "addr:housenumber":"75",
    "addr:postcode":"ne33 2jj",
    "addr:street":"Ocean Road",
    "iso:country":"GB",
    "sg:address":"75 Ocean Road",
    "sg:city":"South Shields",
    "sg:classifiers":[
        {
            "category":"Travel",
            "subcategory":"Hotels & Motels",
            "type":"Entertainment"
        }
    ],
    "sg:phone":"+44 191 455 2361",
    "sg:postcode":"NE33 2JJ",
    "sg:province":"Tyne and Wear",
    "sg:tags":[
        "house",
        "guest"
    ],
    "wof:name":"M & R WILSON",
    "wof:placetype":"venue"
},
  "geometry": {"coordinates":[-1.4271860123,55.0000457764],"type":"Point"}
}