{
  "type": "Feature",
  "properties": {
    "iso:country":"GB",
    "sg:address":"Fron Farm, Cae Newydd Road, Gwernymynydd",
    "sg:city":"Mold",
    "sg:classifiers":[
        {
            "category":"Farming",
            "subcategory":"Livestock Farm",
            "type":"Manufacturing & Wholesale Goods"
        }
    ],
    "sg:postcode":"CH7 4AU",
    "sg:province":"Denbighshire",
    "sg:tags":[
        "others"
    ],
    "wof:name":"J T Jones",
    "wof:placetype":"venue"
},
  "geometry": {"coordinates":[-3.167568922,53.1334114075],"type":"Point"}
}