{
  "type": "Feature",
  "properties": {
    "iso:country":"GB",
    "sg:address":"1 Elven Street",
    "sg:city":"Burnley",
    "sg:classifiers":[
        {
            "category":"Travel",
            "subcategory":"Hotels & Motels",
            "type":"Entertainment"
        }
    ],
    "sg:phone":"+44 1282 422684",
    "sg:postcode":"BB11 3ET",
    "sg:province":"Lancashire",
    "wof:name":"1800ATALEXANDER HOTEL",
    "wof:placetype":"venue"
},
  "geometry": {"coordinates":[-2.243809,53.78801],"type":"Point"}
}