{
  "type": "Feature",
  "properties": {
    "addr:full":"62 Lauderdale Street Preston Lancashire PR1 8JL",
    "addr:housenumber":"62",
    "addr:postcode":"pr1 8jl",
    "addr:street":"Lauderdale Street",
    "iso:country":"GB",
    "sg:address":"62 Lauderdale Street",
    "sg:city":"Preston",
    "sg:classifiers":[
        {
            "category":"Shopping",
            "subcategory":"Department Store",
            "type":"Retail Goods"
        },
        {
            "category":"Food & Beverages",
            "subcategory":"Groceries & Convenience Stores",
            "type":"Retail Goods"
        }
    ],
    "sg:phone":"+44 1772 252671",
    "sg:postcode":"PR1 8JL",
    "sg:province":"Lancashire",
    "wof:name":"Vohra Stores",
    "wof:placetype":"venue"
},
  "geometry": {"coordinates":[-2.713299036,53.7543945312],"type":"Point"}
}