{
  "type": "Feature",
  "properties": {
    "addr:full":"Chapel Works, Bradden La Hemel Hempstead Hertfordshire HP2 6HZ",
    "addr:postcode":"hp2 6hz",
    "addr:street":"Bradden La Hemel Hempstead",
    "iso:country":"GB",
    "sg:address":"Chapel Works, Bradden La",
    "sg:city":"Hemel Hempstead",
    "sg:classifiers":[
        {
            "category":"Building & Trades",
            "subcategory":"Construction",
            "type":"Services"
        }
    ],
    "sg:phone":"+44 1582 841857",
    "sg:postcode":"HP2 6HZ",
    "sg:province":"Hertfordshire",
    "sg:tags":[
        "joinery"
    ],
    "wof:name":"R Hellard & Co",
    "wof:placetype":"venue"
},
  "geometry": {"coordinates":[-0.4942399859,51.8109588623],"type":"Point"}
}