{
  "type": "Feature",
  "properties": {
    "addr:full":"9 Criterion Buildings, Portsmouth Road Thames Ditton Surrey KT7 0SS",
    "addr:housenumber":"9",
    "addr:postcode":"kt7 0ss",
    "addr:street":"Criterion Buildings Portsmouth Road",
    "iso:country":"GB",
    "sg:address":"9 Criterion Buildings, Portsmouth Road",
    "sg:city":"Thames Ditton",
    "sg:classifiers":[
        {
            "category":"Personal",
            "subcategory":"Beauty Salon",
            "type":"Services"
        }
    ],
    "sg:phone":"+44 20 8339 0832",
    "sg:postcode":"KT7 0SS",
    "sg:province":"Surrey",
    "wof:name":"The Natural Touch",
    "wof:placetype":"venue"
},
  "geometry": {"coordinates":[-0.3333089948,51.3873443604],"type":"Point"}
}