{
  "type": "Feature",
  "properties": {
    "iso:country":"GB",
    "sg:address":"126 Hartfield Rd, Wimbledon",
    "sg:city":"London",
    "sg:classifiers":[
        {
            "category":"Retail",
            "subcategory":"Auto Repair",
            "type":"Services"
        }
    ],
    "sg:postcode":"SW19 3TG",
    "sg:province":"Greater London",
    "sg:tags":[
        "modification",
        "garage"
    ],
    "wof:name":"Swift Motor Services",
    "wof:placetype":"venue"
},
  "geometry": {"coordinates":[-0.203177,51.417332],"type":"Point"}
}