{
  "type": "Feature",
  "properties": {
    "addr:full":"51-55 Hanover Street Stranraer Dumfries and Galloway DG9 7RY",
    "addr:housenumber":"51-55",
    "addr:postcode":"dg9 7ry",
    "addr:street":"Hanover Street",
    "iso:country":"GB",
    "sg:address":"51-55 Hanover Street",
    "sg:city":"Stranraer",
    "sg:classifiers":[
        {
            "category":"Home & Garden",
            "subcategory":"Furniture",
            "type":"Retail Goods"
        }
    ],
    "sg:phone":"+44 1776 702484",
    "sg:postcode":"DG9 7RY",
    "sg:province":"Dumfries and Galloway",
    "sg:tags":[
        "outlet"
    ],
    "wof:name":"L Fidler & Sons",
    "wof:placetype":"venue"
},
  "geometry": {"coordinates":[-5.024551,54.903404],"type":"Point"}
}