{
  "type": "Feature",
  "properties": {
    "iso:country":"GB",
    "sg:address":"88 Dudley Road West, Tividale",
    "sg:city":"Birmingham",
    "sg:classifiers":[
        {
            "category":"Autos & Motor Vehicles",
            "subcategory":"Automobile Sales",
            "type":"Retail Goods"
        }
    ],
    "sg:phone":"+44 121 520 7187",
    "sg:postcode":"B69 2HX",
    "sg:province":"West Midlands",
    "sg:tags":[
        "car"
    ],
    "wof:name":"Tividale Motor Group",
    "wof:placetype":"venue"
},
  "geometry": {"coordinates":[-2.0606648922,52.5138626099],"type":"Point"}
}