{
  "type": "Feature",
  "properties": {
    "addr:full":"314 Prestbury Road Cheltenham Gloucestershire GL52 3DD",
    "addr:housenumber":"314",
    "addr:postcode":"gl52 3dd",
    "addr:street":"Prestbury Road",
    "iso:country":"GB",
    "sg:address":"314 Prestbury Road",
    "sg:city":"Cheltenham",
    "sg:classifiers":[
        {
            "category":"Building & Trades",
            "subcategory":"Construction",
            "type":"Services"
        }
    ],
    "sg:phone":"+44 1242 244235",
    "sg:postcode":"GL52 3DD",
    "sg:province":"Gloucestershire",
    "sg:tags":[
        "builder"
    ],
    "wof:name":"R Garthwaite",
    "wof:placetype":"venue"
},
  "geometry": {"coordinates":[-2.0489730835,51.9121589661],"type":"Point"}
}