{
  "type": "Feature",
  "properties": {
    "addr:full":"Blairlogie Stirling Clackmannanshire FK9 5PX",
    "addr:postcode":"fk9 5px",
    "iso:country":"GB",
    "sg:address":"Blairlogie",
    "sg:city":"Stirling",
    "sg:classifiers":[
        {
            "category":"Recreation",
            "subcategory":"Campground",
            "type":"Entertainment"
        }
    ],
    "sg:phone":"+44 1786 474947",
    "sg:postcode":"FK9 5PX",
    "sg:province":"Clackmannanshire",
    "sg:tags":[
        "caravan",
        "park"
    ],
    "wof:name":"Witches Craig Caravan Park",
    "wof:placetype":"venue"
},
  "geometry": {"coordinates":[-3.88877,56.150269],"type":"Point"}
}