{
  "type": "Feature",
  "properties": {
    "iso:country":"GB",
    "sg:address":"10 Stradling Avenue",
    "sg:city":"Weston-super-mare",
    "sg:classifiers":[
        {
            "category":"Building & Trades",
            "subcategory":"Construction",
            "type":"Services"
        }
    ],
    "sg:postcode":"BS23 3RD",
    "sg:province":"Somerset",
    "sg:tags":[
        "builder"
    ],
    "wof:name":"Somerset Container Storage",
    "wof:placetype":"venue"
},
  "geometry": {"coordinates":[-2.968913,51.336239],"type":"Point"}
}