{
  "type": "Feature",
  "properties": {
    "addr:full":"340 Duke Street Glasgow Glasgow City G31 1QZ",
    "addr:housenumber":"340",
    "addr:postcode":"g31 1qz",
    "addr:street":"Duke Street",
    "iso:country":"GB",
    "sg:address":"340 Duke Street",
    "sg:city":"Glasgow",
    "sg:classifiers":[
        {
            "category":"Shopping",
            "subcategory":"News",
            "type":"Retail Goods"
        }
    ],
    "sg:phone":"+44 141 554 6024",
    "sg:postcode":"G31 1QZ",
    "sg:province":"Glasgow City",
    "sg:tags":[
        "newsagent"
    ],
    "wof:name":"Harris Newsagents",
    "wof:placetype":"venue"
},
  "geometry": {"coordinates":[-4.221321106,55.8582420349],"type":"Point"}
}