{
  "type": "Feature",
  "properties": {
    "iso:country":"GB",
    "sg:address":"35 Querneby Road",
    "sg:city":"Nottingham",
    "sg:classifiers":[
        {
            "category":"Manufacturing",
            "subcategory":"Metals",
            "type":"Manufacturing & Wholesale Goods"
        }
    ],
    "sg:phone":"+44 115 960 4587",
    "sg:postcode":"NG3 5JB",
    "sg:province":"Nottinghamshire",
    "sg:tags":[
        "merchant"
    ],
    "wof:name":"S  Jeyes & Son (Midlands) Ltd.",
    "wof:placetype":"venue"
},
  "geometry": {"coordinates":[-1.135161,52.976967],"type":"Point"}
}