{
  "type": "Feature",
  "properties": {
    "addr:full":"105 Argyll Road Ripley Derbyshire DE5 3LH",
    "addr:housenumber":"105",
    "addr:postcode":"de5 3lh",
    "addr:street":"Argyll Road",
    "iso:country":"GB",
    "sg:address":"105 Argyll Road",
    "sg:city":"Ripley",
    "sg:classifiers":[
        {
            "category":"Real Estate",
            "subcategory":"Real Estate Services",
            "type":"Services"
        },
        {
            "category":"Retail",
            "subcategory":"Repair Shop",
            "type":"Services"
        }
    ],
    "sg:phone":"+44 1773 749221",
    "sg:postcode":"DE5 3LH",
    "sg:province":"Derbyshire",
    "sg:tags":[
        "property",
        "maintenance"
    ],
    "wof:name":"Vernon Spencer",
    "wof:placetype":"venue"
},
  "geometry": {"coordinates":[-1.400719,53.051414],"type":"Point"}
}