{
  "type": "Feature",
  "properties": {
    "addr:full":"24 King St Preston Lancashire PR3 3RQ",
    "addr:housenumber":"24",
    "addr:postcode":"pr3 3rq",
    "addr:street":"King St",
    "iso:country":"GB",
    "sg:address":"24 King St",
    "sg:city":"Preston",
    "sg:classifiers":[
        {
            "category":"Health Services",
            "subcategory":"Clinic",
            "type":"Services"
        }
    ],
    "sg:phone":"+44 1772 782831",
    "sg:postcode":"PR3 3RQ",
    "sg:province":"Lancashire",
    "sg:tags":[
        "nh"
    ],
    "wof:name":"Longridge Health Centre",
    "wof:placetype":"venue"
},
  "geometry": {"coordinates":[-2.598622,53.830181],"type":"Point"}
}