{
  "type": "Feature",
  "properties": {
    "addr:full":"Powburn Alnwick Northumberland NE66 4HR",
    "addr:postcode":"ne66 4hr",
    "addr:street":"Powburn",
    "iso:country":"GB",
    "sg:address":"Powburn",
    "sg:city":"Alnwick",
    "sg:classifiers":[
        {
            "category":"Social Services",
            "subcategory":"Retirement Home",
            "type":"Services"
        }
    ],
    "sg:postcode":"NE66 4HR",
    "sg:province":"Northumberland",
    "sg:tags":[
        "residential",
        "care"
    ],
    "wof:name":"Greenfields Residential Care Home",
    "wof:placetype":"venue"
},
  "geometry": {"coordinates":[-1.8997299671,55.4365997314],"type":"Point"}
}