{
  "type": "Feature",
  "properties": {
    "addr:full":"2 Crown Office Row, Temple St Paul's Greater London EC4Y 7HJ",
    "addr:housenumber":"2",
    "addr:postcode":"ec4y 7hj",
    "addr:street":"Office Row Temple St",
    "iso:country":"GB",
    "sg:address":"2 Crown Office Row, Temple",
    "sg:city":"St Paul's",
    "sg:classifiers":[
        {
            "category":"Professional",
            "subcategory":"Lawyer & Legal Services",
            "type":"Services"
        }
    ],
    "sg:phone":"+44 20 7797 8100",
    "sg:postcode":"EC4Y 7HJ",
    "sg:province":"Greater London",
    "sg:tags":[
        "barrister"
    ],
    "wof:name":"Roger Ter Haar",
    "wof:placetype":"venue"
},
  "geometry": {"coordinates":[-0.11059,51.51247],"type":"Point"}
}