{
  "type": "Feature",
  "properties": {
    "addr:full":"Knutsford Road, Chelford Macclesfield Cheshire SK11 9BB",
    "addr:postcode":"sk11 9bb",
    "addr:street":"Knutsford Road",
    "iso:country":"GB",
    "sg:address":"Knutsford Road, Chelford",
    "sg:city":"Macclesfield",
    "sg:classifiers":[
        {
            "category":"Bars & Pubs",
            "type":"Food & Drink"
        }
    ],
    "sg:phone":"+44 1625 861366",
    "sg:postcode":"SK11 9BB",
    "sg:province":"Cheshire",
    "sg:tags":[
        "pubs",
        "inn"
    ],
    "wof:name":"The Egerton Arms",
    "wof:placetype":"venue"
},
  "geometry": {"coordinates":[-2.2840850353,53.271270752],"type":"Point"}
}