{
  "type": "Feature",
  "properties": {
    "addr:full":"Height Top Farm, Stump Hall Rd Burnley Lancashire BB12 9BU",
    "addr:postcode":"bb12 9bu",
    "addr:street":"Hall Rd",
    "iso:country":"GB",
    "sg:address":"Height Top Farm, Stump Hall Rd",
    "sg:city":"Burnley",
    "sg:classifiers":[
        {
            "category":"Manufacturing",
            "subcategory":"Building Materials",
            "type":"Manufacturing & Wholesale Goods"
        }
    ],
    "sg:phone":"+44 1282 772009",
    "sg:postcode":"BB12 9BU",
    "sg:province":"Lancashire",
    "sg:tags":[
        "concrete",
        "product"
    ],
    "wof:name":"JKS",
    "wof:placetype":"venue"
},
  "geometry": {"coordinates":[-2.2689459324,53.8427658081],"type":"Point"}
}