{
  "type": "Feature",
  "properties": {
    "addr:full":"1b Downshire Hill Hampstead Greater London NW3 1NR",
    "addr:housenumber":"1b",
    "addr:postcode":"nw3 1nr",
    "addr:street":"Downshire Hill",
    "iso:country":"GB",
    "sg:address":"1b Downshire Hill",
    "sg:city":"Hampstead",
    "sg:classifiers":[
        {
            "category":"Health Services",
            "subcategory":"Doctor",
            "type":"Services"
        }
    ],
    "sg:phone":"+44 20 7435 1131",
    "sg:postcode":"NW3 1NR",
    "sg:province":"Greater London",
    "sg:tags":[
        "practitioners"
    ],
    "wof:name":"Sheldon, J",
    "wof:placetype":"venue"
},
  "geometry": {"coordinates":[-0.171903,51.554752],"type":"Point"}
}