{
  "type": "Feature",
  "properties": {
    "addr:full":"Tanglewood, Giles Lane Canterbury Kent CT2 7LX",
    "addr:postcode":"ct2 7lx",
    "addr:street":"Giles Lane",
    "iso:country":"GB",
    "sg:address":"Tanglewood, Giles Lane",
    "sg:city":"Canterbury",
    "sg:classifiers":[
        {
            "category":"Community Center",
            "type":"Public Place"
        }
    ],
    "sg:phone":"+44 1227 828000",
    "sg:postcode":"CT2 7LX",
    "sg:province":"Kent",
    "sg:tags":[
        "conference",
        "room",
        "centre"
    ],
    "wof:name":"U K C Hospitality",
    "wof:placetype":"venue"
},
  "geometry": {"coordinates":[1.06547,51.296131],"type":"Point"}
}