{
  "type": "Feature",
  "properties": {
    "iso:country":"GB",
    "sg:address":"Furtherfen Farm, Southery",
    "sg:city":"Downham Market",
    "sg:classifiers":[
        {
            "category":"Banks & Credit Unions",
            "subcategory":"Investment Brokerage",
            "type":"Services"
        }
    ],
    "sg:phone":"+44 1366 377677",
    "sg:postcode":"PE38 0HS",
    "sg:province":"Cambridgeshire",
    "sg:tags":[
        "contractor"
    ],
    "wof:name":"A L Legge & Son Ltd.",
    "wof:placetype":"venue"
},
  "geometry": {"coordinates":[0.39353,52.526989],"type":"Point"}
}