{
  "type": "Feature",
  "properties": {
    "iso:country":"GB",
    "sg:address":"Arham Court, Teston",
    "sg:city":"Maidstone",
    "sg:classifiers":[
        {
            "category":"Shopping",
            "subcategory":"Stationery & Office Supplies",
            "type":"Retail Goods"
        }
    ],
    "sg:phone":"+44 1622 817000",
    "sg:postcode":"ME18 5BZ",
    "sg:province":"Kent",
    "sg:tags":[
        "envelope"
    ],
    "wof:name":"Carlton Agencies",
    "wof:placetype":"venue"
},
  "geometry": {"coordinates":[0.4469960034,51.2530555725],"type":"Point"}
}