{
  "type": "Feature",
  "properties": {
    "iso:country":"GB",
    "sg:address":"31 Chorley Old Rd",
    "sg:city":"Bolton",
    "sg:classifiers":[
        {
            "category":"Professional",
            "subcategory":"Accounting & Tax Preparation",
            "type":"Services"
        }
    ],
    "sg:postcode":"BL1 3AD",
    "sg:province":"Lancashire",
    "sg:tags":[
        "accountant"
    ],
    "wof:name":"Shafiq,Shahid,",
    "wof:placetype":"venue"
},
  "geometry": {"coordinates":[-2.442723,53.582993],"type":"Point"}
}