{
  "type": "Feature",
  "properties": {
    "addr:full":"Unit 10, 53 Valley Rd Bradford West Yorkshire BD1 4RN",
    "addr:housenumber":"unit;53",
    "addr:postcode":"bd1 4rn",
    "addr:street":"Valley Rd",
    "iso:country":"GB",
    "sg:address":"Unit 10, 53 Valley Rd",
    "sg:city":"Bradford",
    "sg:classifiers":[
        {
            "category":"Shopping",
            "subcategory":"Computers & Home Electronics",
            "type":"Retail Goods"
        }
    ],
    "sg:phone":"+44 1274 304300",
    "sg:postcode":"BD1 4RN",
    "sg:province":"West Yorkshire",
    "wof:name":"P C World",
    "wof:placetype":"venue"
},
  "geometry": {"coordinates":[-1.7567290068,53.8051338196],"type":"Point"}
}