{
  "type": "Feature",
  "properties": {
    "addr:full":"Silverwood, Sheerwater Road, Woodham Addlestone Surrey KT15 3QL",
    "addr:postcode":"kt15 3ql",
    "addr:street":"Sheerwater Road",
    "iso:country":"GB",
    "sg:address":"Silverwood, Sheerwater Road, Woodham",
    "sg:city":"Addlestone",
    "sg:classifiers":[
        {
            "category":"Professional",
            "subcategory":"Art Services",
            "type":"Services"
        }
    ],
    "sg:phone":"+44 1932 354338",
    "sg:postcode":"KT15 3QL",
    "sg:province":"Surrey",
    "sg:tags":[
        "photographer",
        "graphic",
        "designer"
    ],
    "wof:name":"T K Art & Design",
    "wof:placetype":"venue"
},
  "geometry": {"coordinates":[-0.502249,51.347904],"type":"Point"}
}