{
  "type": "Feature",
  "properties": {
    "addr:full":"104 East View Road Sutton Coldfield West Midlands B72 1JA",
    "addr:housenumber":"104",
    "addr:postcode":"b72 1ja",
    "addr:street":"East View Road",
    "iso:country":"GB",
    "sg:address":"104 East View Road",
    "sg:city":"Sutton Coldfield",
    "sg:classifiers":[
        {
            "category":"Professional",
            "subcategory":"Art Services",
            "type":"Services"
        },
        {
            "category":"Building & Trades",
            "subcategory":"Construction",
            "type":"Services"
        }
    ],
    "sg:phone":"+44 121 354 4862",
    "sg:postcode":"B72 1JA",
    "sg:province":"West Midlands",
    "sg:tags":[
        "decorator",
        "painter"
    ],
    "wof:name":"RAYMOND REDDING",
    "wof:placetype":"venue"
},
  "geometry": {"coordinates":[-1.813961,52.549126],"type":"Point"}
}