{
  "type": "Feature",
  "properties": {
    "addr:full":"Unit 2-3 Stewart Centre, Brands Hatch, Fawkham Longfield Kent DA3 8NG",
    "addr:housenumber":"unit 2-3",
    "addr:postcode":"da3 8ng",
    "addr:street":"Stewart Centre Brands",
    "iso:country":"GB",
    "sg:address":"Unit 2-3 Stewart Centre, Brands Hatch, Fawkham",
    "sg:city":"Longfield",
    "sg:classifiers":[
        {
            "category":"Sports & Exercise",
            "subcategory":"Race Track",
            "type":"Entertainment"
        }
    ],
    "sg:postcode":"DA3 8NG",
    "sg:province":"Kent",
    "sg:tags":[
        "motor"
    ],
    "wof:name":"Circuitry-Formula 1 Merchandise",
    "wof:placetype":"venue"
},
  "geometry": {"coordinates":[0.2766279876,51.3669395447],"type":"Point"}
}