{
  "type": "Feature",
  "properties": {
    "iso:country":"GB",
    "sg:address":"93 Hawthorn Street",
    "sg:city":"Wilmslow",
    "sg:classifiers":[
        {
            "category":"Building & Trades",
            "subcategory":"Construction",
            "type":"Services"
        }
    ],
    "sg:phone":"+44 1625 537811",
    "sg:postcode":"SK9 5EJ",
    "sg:province":"Cheshire",
    "sg:tags":[
        "roofing"
    ],
    "wof:name":"A & A Greenslade Roofing Contractors",
    "wof:placetype":"venue"
},
  "geometry": {"coordinates":[-2.2388861179,53.3238525391],"type":"Point"}
}