{
  "type": "Feature",
  "properties": {
    "iso:country":"GB",
    "sg:address":"53 The Strand, Walmer",
    "sg:city":"Deal",
    "sg:classifiers":[
        {
            "category":"Restaurant",
            "type":"Food & Drink"
        }
    ],
    "sg:phone":"+44 1304 363939",
    "sg:postcode":"CT14 7DP",
    "sg:province":"Kent",
    "sg:tags":[
        "indian",
        "-"
    ],
    "wof:name":"Bengal Spice",
    "wof:placetype":"venue"
},
  "geometry": {"coordinates":[1.402471,51.215649],"type":"Point"}
}