{
  "type": "Feature",
  "properties": {
    "iso:country":"GB",
    "sg:address":"45 Portsdown Hill Road",
    "sg:city":"Havant",
    "sg:classifiers":[
        {
            "category":"Shopping",
            "subcategory":"Pharmacy",
            "type":"Retail Goods"
        }
    ],
    "sg:postcode":"PO9 3TU",
    "sg:province":"Hampshire",
    "sg:tags":[
        "pharmacist",
        "chemist"
    ],
    "wof:name":"K H Knight (Drayton) Ltd.",
    "wof:placetype":"venue"
},
  "geometry": {"coordinates":[-1.016764,50.852974],"type":"Point"}
}