{
  "type": "Feature",
  "properties": {
    "iso:country":"GB",
    "sg:address":"Holme Farm Produce, 19-21 Market Street, Milnsbridge",
    "sg:city":"Huddersfield",
    "sg:classifiers":[
        {
            "category":"Food & Beverages",
            "subcategory":"Fruits & Vegetables",
            "type":"Retail Goods"
        }
    ],
    "sg:phone":"+44 1484 657566",
    "sg:postcode":"HD3 4ND",
    "sg:province":"West Yorkshire",
    "sg:tags":[
        "greengrocer"
    ],
    "wof:name":"Holme Farm Produce",
    "wof:placetype":"venue"
},
  "geometry": {"coordinates":[-1.825966,53.639435],"type":"Point"}
}