{
  "type": "Feature",
  "properties": {
    "addr:full":"Rear Of Little Chef Oxford Rd Wallingford Oxfordshire OX10 7LY",
    "addr:housenumber":"rear of",
    "addr:postcode":"ox10 7ly",
    "addr:street":"Oxford Rd",
    "iso:country":"GB",
    "sg:address":"Rear Of Little Chef Oxford Rd",
    "sg:city":"Wallingford",
    "sg:classifiers":[
        {
            "category":"Utilities",
            "subcategory":"Refuse",
            "type":"Services"
        }
    ],
    "sg:phone":"+44 1865 340035",
    "sg:postcode":"OX10 7LY",
    "sg:province":"Oxfordshire",
    "sg:tags":[
        "skip",
        "hire"
    ],
    "wof:name":"Bells Mini Skips",
    "wof:placetype":"venue"
},
  "geometry": {"coordinates":[-1.1256229877,51.6009101868],"type":"Point"}
}