{
  "type": "Feature",
  "properties": {
    "addr:full":"1 Lakeside Lido Caravan Camp, Warren Road, North Somercotes Louth Lincolnshire LN11 7RB",
    "addr:housenumber":"1;camp",
    "addr:postcode":"ln11 7rb",
    "addr:street":"Lakeside;Warren Road;Louth",
    "iso:country":"GB",
    "sg:address":"1 Lakeside Lido Caravan Camp, Warren Road, North Somercotes",
    "sg:city":"Louth",
    "sg:classifiers":[
        {
            "category":"Recreation",
            "subcategory":"Campground",
            "type":"Entertainment"
        }
    ],
    "sg:phone":"+44 1507 358428",
    "sg:postcode":"LN11 7RB",
    "sg:province":"Lincolnshire",
    "sg:tags":[
        "caravan",
        "park"
    ],
    "sg:website":"http://www.donamott.com",
    "wof:name":"Lakeside Park",
    "wof:placetype":"venue"
},
  "geometry": {"coordinates":[0.1794320047,53.4267845154],"type":"Point"}
}