{
  "type": "Feature",
  "properties": {
    "addr:full":"41 Rochester Way Banbury Northamptonshire OX17 3JU",
    "addr:housenumber":"41",
    "addr:postcode":"ox17 3ju",
    "addr:street":"Rochester Way",
    "iso:country":"GB",
    "sg:address":"41 Rochester Way",
    "sg:city":"Banbury",
    "sg:classifiers":[
        {
            "category":"Food & Beverages",
            "subcategory":"Supermarket",
            "type":"Retail Goods"
        }
    ],
    "sg:postcode":"OX17 3JU",
    "sg:province":"Northamptonshire",
    "wof:name":"Rochester Way Stores",
    "wof:placetype":"venue"
},
  "geometry": {"coordinates":[-1.308112,52.021645],"type":"Point"}
}