{
  "type": "Feature",
  "properties": {
    "addr:full":"8 Ellenborough Park South Weston-super-mare Somerset BS23 1XW",
    "addr:housenumber":"8",
    "addr:postcode":"bs23 1xw",
    "addr:street":"Ellenborough Park South",
    "iso:country":"GB",
    "sg:address":"8 Ellenborough Park South",
    "sg:city":"Weston-super-mare",
    "sg:classifiers":[
        {
            "category":"Social Services",
            "subcategory":"Retirement Home",
            "type":"Services"
        }
    ],
    "sg:phone":"+44 1934 632817",
    "sg:postcode":"BS23 1XW",
    "sg:province":"Somerset",
    "sg:tags":[
        "rest"
    ],
    "wof:name":"Stella Maris",
    "wof:placetype":"venue"
},
  "geometry": {"coordinates":[-2.979424,51.341705],"type":"Point"}
}