{
  "type": "Feature",
  "properties": {
    "iso:country":"GB",
    "sg:address":"415 Manchester Rd, Paddington",
    "sg:city":"Warrington",
    "sg:classifiers":[
        {
            "category":"Autos & Motor Vehicles",
            "subcategory":"Automobile Sales",
            "type":"Retail Goods"
        }
    ],
    "sg:phone":"+44 1925 819401",
    "sg:postcode":"WA1 3LR",
    "sg:province":"Cheshire",
    "sg:tags":[
        "commercial"
    ],
    "wof:name":"Barclays Citroen Ltd",
    "wof:placetype":"venue"
},
  "geometry": {"coordinates":[-2.556808,53.397385],"type":"Point"}
}