{
  "type": "Feature",
  "properties": {
    "addr:full":"51 Shropshire Street Market Drayton Shropshire TF9 3DA",
    "addr:housenumber":"51",
    "addr:postcode":"tf9 3da",
    "addr:street":"Shropshire Street",
    "iso:country":"GB",
    "sg:address":"51 Shropshire Street",
    "sg:city":"Market Drayton",
    "sg:classifiers":[
        {
            "category":"Bars & Pubs",
            "type":"Food & Drink"
        }
    ],
    "sg:phone":"+44 1630 657834",
    "sg:postcode":"TF9 3DA",
    "sg:province":"Shropshire",
    "sg:tags":[
        "pubs",
        "inn"
    ],
    "wof:name":"Oscars Wine Bar",
    "wof:placetype":"venue"
},
  "geometry": {"coordinates":[-2.485867,52.902679],"type":"Point"}
}