{
  "type": "Feature",
  "properties": {
    "iso:country":"GB",
    "sg:address":"123 Westminster Bridge Road",
    "sg:city":"London",
    "sg:classifiers":[
        {
            "category":"Banks & Credit Unions",
            "subcategory":"Financial Services",
            "type":"Services"
        }
    ],
    "sg:phone":"+44 20 7902 0110",
    "sg:postcode":"SE1 7HR",
    "sg:province":"Greater London",
    "sg:tags":[
        "consultant"
    ],
    "wof:name":"C P de Leeuw Investments Ltd.",
    "wof:placetype":"venue"
},
  "geometry": {"coordinates":[-0.113536,51.499237],"type":"Point"}
}