{"geometry":{"type":"Point","coordinates":[-0.472539,52.030571]},"type":"Feature","id":102559957,"bbox":[-0.472539,52.030571,-0.472539,52.030571],"properties":{"sg:province":"Bedfordshire","sg:tags":["chauffeur","driven","car"],"geom:longitude":-0.472539,"wof:breaches":[],"sg:href":"http://api.simplegeo.com/1.0/features/SG_4oqqF0gqdwO9sX4XEkQ4Ko_52.030571_-0.472539@1300740015.json","sg:owner":"simplegeo","sg:postcode":"MK45 2AE","geom:latitude":52.030571,"sg:classifiers":[{"category":"Autos & Motor Vehicles","type":"Retail Goods","subcategory":"Motorcycle Sales"}],"sg:address":"Clophill Road, Maulden","sg:phone":"+44 1525 862201","wof:hierarchy":[{"venue_id":102559957,"country_id":85633159,"region_id":85684591}],"geom:area":0.000000,"sg:city":"Bedford","wof:lastmodified":1438093111,"iso:country":"GB","wof:geomhash":"443a0e8f0240975edf60a6ea293e5fda","wof:name":"Executive Travel","wof:belongsto":[85633159,85684591],"src:geom":"simplegeo","wof:placetype":"venue","wof:supersedes":[],"wof:id":102559957,"wof:superseded_by":[],"wof:concordances":{"sg:id":"SG_4oqqF0gqdwO9sX4XEkQ4Ko_52.030571_-0.472539@1300740015"},"wof:parent_id":85684591}}