{
  "type": "Feature",
  "properties": {
    "addr:full":"Clophill Road, Maulden Bedford Bedfordshire MK45 2AE",
    "addr:postcode":"mk45 2ae",
    "addr:street":"Clophill Road",
    "iso:country":"GB",
    "sg:address":"Clophill Road, Maulden",
    "sg:city":"Bedford",
    "sg:classifiers":[
        {
            "category":"Autos & Motor Vehicles",
            "subcategory":"Motorcycle Sales",
            "type":"Retail Goods"
        }
    ],
    "sg:href":"http://api.simplegeo.com/1.0/features/SG_4oqqF0gqdwO9sX4XEkQ4Ko_52.030571_-0.472539@1300740015.json",
    "sg:phone":"+44 1525 862201",
    "sg:postcode":"MK45 2AE",
    "sg:province":"Bedfordshire",
    "sg:tags":[
        "chauffeur",
        "driven",
        "car"
    ],
    "wof:name":"Executive Travel",
    "wof:placetype":"venue"
},
  "geometry": {"coordinates":[-0.472539,52.030571],"type":"Point"}
}