{
  "type": "Feature",
  "properties": {
    "addr:full":"79 Bentley Rd Ashford Kent TN24 0HR",
    "addr:housenumber":"79",
    "addr:postcode":"tn24 0hr",
    "addr:street":"Bentley Rd",
    "iso:country":"GB",
    "sg:address":"79 Bentley Rd",
    "sg:city":"Ashford",
    "sg:classifiers":[
        {
            "category":"Building & Trades",
            "subcategory":"Construction",
            "type":"Services"
        }
    ],
    "sg:phone":"+44 1233 642943",
    "sg:postcode":"TN24 0HR",
    "sg:province":"Kent",
    "sg:tags":[
        "contractor",
        "paving",
        "driveway"
    ],
    "wof:name":"Hills Contractors",
    "wof:placetype":"venue"
},
  "geometry": {"coordinates":[0.8940709829,51.1361427307],"type":"Point"}
}