{
  "type": "Feature",
  "properties": {
    "addr:full":"30 Queen Street Market Rasen Lincolnshire LN8 3EH",
    "addr:housenumber":"30",
    "addr:postcode":"ln8 3eh",
    "addr:street":"Queen Street",
    "iso:country":"GB",
    "sg:address":"30 Queen Street",
    "sg:city":"Market Rasen",
    "sg:classifiers":[
        {
            "category":"Shopping",
            "subcategory":"Thrift Store",
            "type":"Retail Goods"
        }
    ],
    "sg:phone":"+44 1673 842104",
    "sg:postcode":"LN8 3EH",
    "sg:province":"Lincolnshire",
    "sg:tags":[
        "shop",
        "charity"
    ],
    "sg:website":"http://www.oxfam.org.uk",
    "wof:name":"Oxfam",
    "wof:placetype":"venue"
},
  "geometry": {"coordinates":[-0.3361000121,53.3874168396],"type":"Point"}
}