{
  "type": "Feature",
  "properties": {
    "addr:full":"5 Hambleton Grove, Emerson Valley Milton Keynes Buckinghamshire MK4 2JS",
    "addr:housenumber":"5",
    "addr:postcode":"mk4 2js",
    "addr:street":"Hambleton Grove",
    "iso:country":"GB",
    "sg:address":"5 Hambleton Grove, Emerson Valley",
    "sg:city":"Milton Keynes",
    "sg:classifiers":[
        {
            "category":"Professional",
            "subcategory":"Computer Services",
            "type":"Services"
        }
    ],
    "sg:postcode":"MK4 2JS",
    "sg:province":"Buckinghamshire",
    "sg:tags":[
        "system",
        "software"
    ],
    "wof:name":"Alphelsi Ltd",
    "wof:placetype":"venue"
},
  "geometry": {"coordinates":[-0.7842350006,52.0057296753],"type":"Point"}
}