{
  "type": "Feature",
  "properties": {
    "addr:full":"1388 London Road London Greater London SW16 4BZ",
    "addr:housenumber":"1388",
    "addr:postcode":"sw16 4bz",
    "addr:street":"London Road",
    "iso:country":"GB",
    "sg:address":"1388 London Road",
    "sg:city":"London",
    "sg:classifiers":[
        {
            "category":"Restaurant",
            "type":"Food & Drink"
        }
    ],
    "sg:postcode":"SW16 4BZ",
    "sg:province":"Greater London",
    "wof:name":"Just Williams",
    "wof:placetype":"venue"
},
  "geometry": {"coordinates":[-0.122091,51.409672],"type":"Point"}
}