{
  "type": "Feature",
  "properties": {
    "iso:country":"GB",
    "sg:address":"266 Radford Road",
    "sg:city":"Coventry",
    "sg:classifiers":[
        {
            "category":"Professional",
            "subcategory":"Business Services",
            "type":"Services"
        }
    ],
    "sg:phone":"+44 24 7659 0595",
    "sg:postcode":"CV6 3BU",
    "sg:province":"Warwickshire",
    "sg:tags":[
        "import",
        "export",
        "agent"
    ],
    "wof:name":"Robert Ensor",
    "wof:placetype":"venue"
},
  "geometry": {"coordinates":[-1.521501,52.42297],"type":"Point"}
}