{
  "type": "Feature",
  "properties": {
    "iso:country":"GB",
    "sg:address":"Higher Moor Road",
    "sg:city":"Blackpool",
    "sg:classifiers":[
        {
            "category":"Retail",
            "subcategory":"Auto Repair",
            "type":"Services"
        }
    ],
    "sg:postcode":"FY3 7NA",
    "sg:province":"Lancashire",
    "sg:tags":[
        "body",
        "car"
    ],
    "wof:name":"I Holmes",
    "wof:placetype":"venue"
},
  "geometry": {"coordinates":[-3.018295,53.841358],"type":"Point"}
}