{
  "type": "Feature",
  "properties": {
    "iso:country":"GB",
    "sg:address":"95 Main Road",
    "sg:city":"Sidcup",
    "sg:classifiers":[
        {
            "category":"Retail",
            "subcategory":"Laundry & Dry Cleaning",
            "type":"Services"
        }
    ],
    "sg:phone":"+44 20 8309 6035",
    "sg:postcode":"DA14 6ND",
    "sg:province":"Kent",
    "sg:tags":[
        "cleaner",
        "alteration"
    ],
    "wof:name":"Sidcup Dry Cleaners",
    "wof:placetype":"venue"
},
  "geometry": {"coordinates":[0.100345999,51.426612854],"type":"Point"}
}