{
  "type": "Feature",
  "properties": {
    "iso:country":"GB",
    "sg:address":"Queensway House, 1 Queensferry Terrace",
    "sg:city":"Edinburgh",
    "sg:classifiers":[
        {
            "category":"Professional",
            "subcategory":"Computer Services",
            "type":"Services"
        }
    ],
    "sg:phone":"+44 131 332 3311",
    "sg:postcode":"EH4 3ER",
    "sg:province":"City of Edinburgh",
    "sg:tags":[
        "development",
        "system",
        "software"
    ],
    "wof:name":"Newell & Budge Ltd",
    "wof:placetype":"venue"
},
  "geometry": {"coordinates":[-3.250844,55.95805],"type":"Point"}
}