{
  "type": "Feature",
  "properties": {
    "iso:country":"GB",
    "sg:address":"20 Central Cres",
    "sg:city":"Norwich",
    "sg:classifiers":[
        {
            "category":"Landmark",
            "subcategory":"Tourist Attraction",
            "type":"Public Place"
        }
    ],
    "sg:phone":"+44 1603 811542",
    "sg:postcode":"NR9 3EP",
    "sg:province":"Norfolk",
    "sg:tags":[
        "interest"
    ],
    "wof:name":"Norfolk Church Tours",
    "wof:placetype":"venue"
},
  "geometry": {"coordinates":[1.174845,52.599697],"type":"Point"}
}