{
  "type": "Feature",
  "properties": {
    "addr:full":"24 Eastport Lane Lewes East Sussex BN7 1TL",
    "addr:housenumber":"24",
    "addr:postcode":"bn7 1tl",
    "addr:street":"Eastport Lane",
    "iso:country":"GB",
    "sg:address":"24 Eastport Lane",
    "sg:city":"Lewes",
    "sg:classifiers":[
        {
            "category":"Utilities",
            "type":"Services"
        }
    ],
    "sg:phone":"+44 1273 485940",
    "sg:postcode":"BN7 1TL",
    "sg:province":"East Sussex",
    "sg:tags":[
        "internet"
    ],
    "wof:name":"Incamedia Ltd.",
    "wof:placetype":"venue"
},
  "geometry": {"coordinates":[0.00785,50.869865],"type":"Point"}
}