{
  "type": "Feature",
  "properties": {
    "iso:country":"GB",
    "sg:address":"37 Harthall La",
    "sg:city":"Kings Langley",
    "sg:classifiers":[
        {
            "category":"Professional",
            "subcategory":"Engineering",
            "type":"Services"
        }
    ],
    "sg:phone":"+44 1923 269393",
    "sg:postcode":"WD4 8JW",
    "sg:province":"Hertfordshire",
    "sg:tags":[
        "gas",
        "engineer"
    ],
    "wof:name":"Paynter J (Plumbing & Heating)",
    "wof:placetype":"venue"
},
  "geometry": {"coordinates":[-0.429216,51.722977],"type":"Point"}
}