{
  "type": "Feature",
  "properties": {
    "addr:full":"110 Farleigh Rd Stoke Newington Greater London N16 7TF",
    "addr:housenumber":"110",
    "addr:postcode":"n16 7tf",
    "addr:street":"Farleigh Rd",
    "iso:country":"GB",
    "sg:address":"110 Farleigh Rd",
    "sg:city":"Stoke Newington",
    "sg:classifiers":[
        {
            "category":"Personal",
            "type":"Services"
        }
    ],
    "sg:phone":"+44 20 7254 8759",
    "sg:postcode":"N16 7TF",
    "sg:province":"Greater London",
    "sg:tags":[
        "tailor"
    ],
    "wof:name":"Tony Gents Taylor",
    "wof:placetype":"venue"
},
  "geometry": {"coordinates":[-0.068618,51.555363],"type":"Point"}
}