{
  "type": "Feature",
  "properties": {
    "iso:country":"GB",
    "sg:address":"42 Hastings Road",
    "sg:city":"Leicester",
    "sg:classifiers":[
        {
            "category":"Professional",
            "subcategory":"Business Services",
            "type":"Services"
        }
    ],
    "sg:phone":"+44 116 212 7500",
    "sg:postcode":"LE5 0HL",
    "sg:province":"Leicestershire",
    "sg:tags":[
        "import",
        "export",
        "agent"
    ],
    "wof:name":"Extrade (U K) Ltd.",
    "wof:placetype":"venue"
},
  "geometry": {"coordinates":[-1.1048320532,52.6461219788],"type":"Point"}
}