{
  "type": "Feature",
  "properties": {
    "addr:full":"Unit 12b Bon Accord Centre, George Street Aberdeen Aberdeen City AB1 1HZ",
    "addr:housenumber":"unit 12b",
    "addr:postcode":"ab1 1hz",
    "addr:street":"Bon Accord Centre George Street",
    "iso:country":"GB",
    "sg:address":"Unit 12b Bon Accord Centre, George Street",
    "sg:city":"Aberdeen",
    "sg:classifiers":[
        {
            "category":"Food & Beverages",
            "subcategory":"Candy",
            "type":"Retail Goods"
        }
    ],
    "sg:phone":"+44 1224 621004",
    "sg:postcode":"AB1 1HZ",
    "sg:province":"Aberdeen City",
    "sg:tags":[
        "confectioner"
    ],
    "wof:name":"Thorntons Plc",
    "wof:placetype":"venue"
},
  "geometry": {"coordinates":[-2.1067800522,57.1539306641],"type":"Point"}
}