{
  "type": "Feature",
  "properties": {
    "addr:full":"42 Mersey Rd Sale Cheshire M33 6LF",
    "addr:housenumber":"42",
    "addr:postcode":"m33 6lf",
    "addr:street":"Mersey Rd",
    "iso:country":"GB",
    "sg:address":"42 Mersey Rd",
    "sg:city":"Sale",
    "sg:classifiers":[
        {
            "category":"Retail",
            "subcategory":"Auto Repair",
            "type":"Services"
        }
    ],
    "sg:phone":"+44 161 973 3265",
    "sg:postcode":"M33 6LF",
    "sg:province":"Cheshire",
    "sg:tags":[
        "modification",
        "garage"
    ],
    "wof:name":"Diesel Technique",
    "wof:placetype":"venue"
},
  "geometry": {"coordinates":[-2.3229949474,53.4306755066],"type":"Point"}
}