{
  "type": "Feature",
  "properties": {
    "iso:country":"GB",
    "sg:address":"104 Gloucester Road, Kensington & Chelsae",
    "sg:city":"London",
    "sg:classifiers":[
        {
            "category":"Military Area",
            "subcategory":"Air Force Base",
            "type":"Public Place"
        }
    ],
    "sg:phone":"+44 20 7244 6556",
    "sg:postcode":"SW7 4RH",
    "sg:province":"Greater London",
    "sg:tags":[
        "taxi",
        "hire",
        "private"
    ],
    "wof:name":"1st airports express cars",
    "wof:placetype":"venue"
},
  "geometry": {"coordinates":[-0.18348,51.496185],"type":"Point"}
}