{
  "type": "Feature",
  "properties": {
    "addr:full":"Constantine Bay Padstow Cornwall PL28 8JB",
    "addr:postcode":"pl28 8jb",
    "addr:street":"Constantine",
    "iso:country":"GB",
    "sg:address":"Constantine Bay",
    "sg:city":"Padstow",
    "sg:classifiers":[
        {
            "category":"Sports & Exercise",
            "subcategory":"Golf",
            "type":"Entertainment"
        }
    ],
    "sg:phone":"+44 1841 520208",
    "sg:postcode":"PL28 8JB",
    "sg:province":"Cornwall",
    "sg:tags":[
        "club",
        "course"
    ],
    "wof:name":"Trevose Ltd.",
    "wof:placetype":"venue"
},
  "geometry": {"coordinates":[-4.941839,50.537365],"type":"Point"}
}