{
  "type": "Feature",
  "properties": {
    "addr:full":"39 Napiershall Street Glasgow Glasgow City G20 6EZ",
    "addr:housenumber":"39",
    "addr:postcode":"g20 6ez",
    "addr:street":"Napiershall Street",
    "iso:country":"GB",
    "sg:address":"39 Napiershall Street",
    "sg:city":"Glasgow",
    "sg:classifiers":[
        {
            "category":"Retail",
            "subcategory":"Event Space",
            "type":"Services"
        }
    ],
    "sg:phone":"+44 141 575 3001",
    "sg:postcode":"G20 6EZ",
    "sg:province":"Glasgow City",
    "sg:tags":[
        "exhibition",
        "organiser"
    ],
    "wof:name":"Impact Arts",
    "wof:placetype":"venue"
},
  "geometry": {"coordinates":[-4.2734031677,55.8746452332],"type":"Point"}
}