{
  "type": "Feature",
  "properties": {
    "addr:full":"Woodrow Centre, Woodrow Redditch Warwickshire B98 7RY",
    "addr:postcode":"b98 7ry",
    "addr:street":"Woodrow;Woodrow",
    "iso:country":"GB",
    "sg:address":"Woodrow Centre, Woodrow",
    "sg:city":"Redditch",
    "sg:classifiers":[
        {
            "category":"Food & Beverages",
            "subcategory":"Supermarket",
            "type":"Retail Goods"
        }
    ],
    "sg:phone":"+44 1527 527112",
    "sg:postcode":"B98 7RY",
    "sg:province":"Warwickshire",
    "wof:name":"Kwik Save Foodstores",
    "wof:placetype":"venue"
},
  "geometry": {"coordinates":[-1.9154189825,52.2879943848],"type":"Point"}
}