{
  "type": "Feature",
  "properties": {
    "iso:country":"GB",
    "sg:address":"2 Coningsby",
    "sg:city":"Bracknell",
    "sg:classifiers":[
        {
            "category":"Retail",
            "subcategory":"Storage",
            "type":"Services"
        }
    ],
    "sg:phone":"+44 1344 411400",
    "sg:postcode":"RG12 7BE",
    "sg:province":"Berkshire",
    "sg:tags":[
        "household",
        "removal"
    ],
    "wof:name":"A T R Removals",
    "wof:placetype":"venue"
},
  "geometry": {"coordinates":[-0.749864,51.407162],"type":"Point"}
}