{
  "type": "Feature",
  "properties": {
    "addr:full":"Town Farm, Workshops Dean Lane, Sixpenny Handley Salisbury Dorset SP5 5PA",
    "addr:postcode":"sp5 5pa",
    "addr:street":"Dean Lane",
    "iso:country":"GB",
    "sg:address":"Town Farm, Workshops Dean Lane, Sixpenny Handley",
    "sg:city":"Salisbury",
    "sg:classifiers":[
        {
            "category":"Professional",
            "type":"Services"
        }
    ],
    "sg:phone":"+44 1725 552000",
    "sg:postcode":"SP5 5PA",
    "sg:province":"Dorset",
    "sg:tags":[
        "interior",
        "furnishers",
        "designer"
    ],
    "wof:name":"Katherine Fortescue Ltd",
    "wof:placetype":"venue"
},
  "geometry": {"coordinates":[-2.0034739971,50.9532699585],"type":"Point"}
}