{
  "type": "Feature",
  "properties": {
    "addr:full":"Wesley St Nottingham Derbyshire NG16 4AL",
    "addr:postcode":"ng16 4al",
    "addr:street":"Wesley St",
    "iso:country":"GB",
    "sg:address":"Wesley St",
    "sg:city":"Nottingham",
    "sg:classifiers":[
        {
            "category":"Freight",
            "type":"Transportation"
        }
    ],
    "sg:phone":"+44 1773 530789",
    "sg:postcode":"NG16 4AL",
    "sg:province":"Derbyshire",
    "sg:tags":[
        "haulage",
        "road"
    ],
    "wof:name":"Team Heanor Heavy Lift Ltd",
    "wof:placetype":"venue"
},
  "geometry": {"coordinates":[-1.2530289888,53.0796546936],"type":"Point"}
}