{
  "type": "Feature",
  "properties": {
    "iso:country":"GB",
    "sg:address":"The Street, Charmouth",
    "sg:city":"Bridport",
    "sg:classifiers":[
        {
            "category":"Cafe",
            "type":"Food & Drink"
        }
    ],
    "sg:phone":"+44 1297 560246",
    "sg:postcode":"DT6 6PU",
    "sg:province":"Dorset",
    "sg:tags":[
        "tea",
        "room"
    ],
    "wof:name":"The Piggy Bank",
    "wof:placetype":"venue"
},
  "geometry": {"coordinates":[-2.896855,50.739422],"type":"Point"}
}