{
  "type": "Feature",
  "properties": {
    "addr:full":"10 Jaynestown Road, Camben London Greater London NW1 7BY",
    "addr:housenumber":"10",
    "addr:postcode":"nw1 7by",
    "addr:street":"Jaynestown Road",
    "iso:country":"GB",
    "sg:address":"10 Jaynestown Road, Camben",
    "sg:city":"London",
    "sg:classifiers":[
        {
            "category":"Professional",
            "subcategory":"Advertising",
            "type":"Services"
        }
    ],
    "sg:phone":"+44 20 7482 3000",
    "sg:postcode":"NW1 7BY",
    "sg:province":"Greater London",
    "sg:tags":[
        "agency"
    ],
    "wof:name":"T D I Transit Advertising Ltd.",
    "wof:placetype":"venue"
},
  "geometry": {"coordinates":[-0.1448059976,51.5407028198],"type":"Point"}
}