{
  "type": "Feature",
  "properties": {
    "addr:full":"1-3 Walton Street London Greater London SW3 2JD",
    "addr:housenumber":"1-3",
    "addr:postcode":"sw3 2jd",
    "addr:street":"Walton Street",
    "iso:country":"GB",
    "sg:address":"1-3 Walton Street",
    "sg:city":"London",
    "sg:classifiers":[
        {
            "category":"Restaurant",
            "type":"Food & Drink"
        }
    ],
    "sg:phone":"+44 20 7225 2301",
    "sg:postcode":"SW3 2JD",
    "sg:province":"Greater London",
    "sg:tags":[
        "italian"
    ],
    "wof:name":"Scalini Restaurant",
    "wof:placetype":"venue"
},
  "geometry": {"coordinates":[-0.164805,51.495983],"type":"Point"}
}