{
  "type": "Feature",
  "properties": {
    "iso:country":"GB",
    "sg:address":"Furze Lane",
    "sg:city":"Godalming",
    "sg:classifiers":[
        {
            "category":"Wholesale",
            "subcategory":"Machinery & Supplies",
            "type":"Manufacturing & Wholesale Goods"
        }
    ],
    "sg:postcode":"GU7 3NP",
    "sg:province":"Surrey",
    "wof:name":"Pond Farm Sales",
    "wof:placetype":"venue"
},
  "geometry": {"coordinates":[-0.600374,51.203751],"type":"Point"}
}