{
  "type": "Feature",
  "properties": {
    "addr:full":"Willow House, Main Street, Gilling East York North Yorkshire YO62 4JH",
    "addr:postcode":"yo62 4jh",
    "addr:street":"Main Street",
    "iso:country":"GB",
    "sg:address":"Willow House, Main Street, Gilling East",
    "sg:city":"York",
    "sg:classifiers":[
        {
            "category":"Social Services",
            "subcategory":"Job Training",
            "type":"Services"
        }
    ],
    "sg:postcode":"YO62 4JH",
    "sg:province":"North Yorkshire",
    "sg:tags":[
        "translator",
        "interpreter"
    ],
    "wof:name":"Henny Garbutt Translations",
    "wof:placetype":"venue"
},
  "geometry": {"coordinates":[-1.0588339567,54.1847686768],"type":"Point"}
}