{
  "type": "Feature",
  "properties": {
    "addr:full":"2 Queen Street Cardiff Cardiff CF10 2RJ",
    "addr:housenumber":"2",
    "addr:postcode":"cf10 2rj",
    "addr:street":"Queen Street",
    "iso:country":"GB",
    "sg:address":"2 Queen Street",
    "sg:city":"Cardiff",
    "sg:classifiers":[
        {
            "category":"Professional",
            "subcategory":"Computer Services",
            "type":"Services"
        }
    ],
    "sg:phone":"+44 29 2037 2007",
    "sg:postcode":"CF10 2RJ",
    "sg:province":"Cardiff",
    "sg:tags":[
        "aided",
        "design"
    ],
    "wof:name":"Omarco",
    "wof:placetype":"venue"
},
  "geometry": {"coordinates":[-3.178174,51.481693],"type":"Point"}
}