{
  "type": "Feature",
  "properties": {
    "iso:country":"GB",
    "sg:address":"Northlands Pavement, Pitsea Centre, Pitsea",
    "sg:city":"Basildon",
    "sg:classifiers":[
        {
            "category":"Organizations",
            "subcategory":"Non-profit Organization",
            "type":"Services"
        }
    ],
    "sg:phone":"+44 1268 583748",
    "sg:postcode":"SS13 3DU",
    "sg:province":"Essex",
    "sg:tags":[
        "organisation",
        "voluntary",
        "charity"
    ],
    "wof:name":"Bailey Housing Association",
    "wof:placetype":"venue"
},
  "geometry": {"coordinates":[0.50333,51.564758],"type":"Point"}
}