{
  "type": "Feature",
  "properties": {
    "iso:country":"GB",
    "sg:address":"123 Aldersgate Street",
    "sg:city":"London",
    "sg:classifiers":[
        {
            "category":"Real Estate",
            "subcategory":"Real Estate Agent",
            "type":"Services"
        }
    ],
    "sg:phone":"+44 20 7251 4171",
    "sg:postcode":"EC1A 4JQ",
    "sg:province":"Greater London",
    "wof:name":"Intergrate Systems Ltd.",
    "wof:placetype":"venue"
},
  "geometry": {"coordinates":[-0.0976699963,51.5209693909],"type":"Point"}
}