{
  "type": "Feature",
  "properties": {
    "addr:full":"15 Lavender Rd Middlesbrough North Yorkshire TS3 7AG",
    "addr:housenumber":"15",
    "addr:postcode":"ts3 7ag",
    "addr:street":"Lavender Rd",
    "iso:country":"GB",
    "sg:address":"15 Lavender Rd",
    "sg:city":"Middlesbrough",
    "sg:classifiers":[
        {
            "category":"Retail",
            "subcategory":"Auto Repair",
            "type":"Services"
        }
    ],
    "sg:phone":"+44 1642 247094",
    "sg:postcode":"TS3 7AG",
    "sg:province":"North Yorkshire",
    "sg:tags":[
        "engine",
        "car",
        "specialist"
    ],
    "wof:name":"A P Atkinson",
    "wof:placetype":"venue"
},
  "geometry": {"coordinates":[-1.210089,54.56551],"type":"Point"}
}