{
  "type": "Feature",
  "properties": {
    "addr:full":"71 Rugeley Road, Hazel Slade Cannock Staffordshire WS12 5PQ",
    "addr:housenumber":"71",
    "addr:postcode":"ws12 5pq",
    "addr:street":"Rugeley Road",
    "iso:country":"GB",
    "sg:address":"71 Rugeley Road, Hazel Slade",
    "sg:city":"Cannock",
    "sg:classifiers":[
        {
            "category":"Shopping",
            "subcategory":"Department Store",
            "type":"Retail Goods"
        }
    ],
    "sg:phone":"+44 1543 423519",
    "sg:postcode":"WS12 5PQ",
    "sg:province":"Staffordshire",
    "wof:name":"The Village Store",
    "wof:placetype":"venue"
},
  "geometry": {"coordinates":[-1.969884,52.713909],"type":"Point"}
}