{
  "type": "Feature",
  "properties": {
    "addr:full":"17 The Boulevard, Park Road Melton Mowbray Leicestershire LE13 1TT",
    "addr:housenumber":"17",
    "addr:postcode":"le13 1tt",
    "addr:street":"The Boulevard Park Road",
    "iso:country":"GB",
    "sg:address":"17 The Boulevard, Park Road",
    "sg:city":"Melton Mowbray",
    "sg:classifiers":[
        {
            "category":"Home & Garden",
            "subcategory":"Furniture",
            "type":"Retail Goods"
        }
    ],
    "sg:phone":"+44 1664 410427",
    "sg:postcode":"LE13 1TT",
    "sg:province":"Leicestershire",
    "wof:name":"Smith John",
    "wof:placetype":"venue"
},
  "geometry": {"coordinates":[-0.88859,52.766441],"type":"Point"}
}