{
  "type": "Feature",
  "properties": {
    "addr:full":"2 Old Market Way, High Street Moreton-in-marsh Gloucestershire GL56 0AX",
    "addr:housenumber":"2",
    "addr:postcode":"gl56 0ax",
    "addr:street":"Old Market Way High Street",
    "iso:country":"GB",
    "sg:address":"2 Old Market Way, High Street",
    "sg:city":"Moreton-in-marsh",
    "sg:classifiers":[
        {
            "category":"Shopping",
            "subcategory":"Clothing, Apparel, & Fashions",
            "type":"Retail Goods"
        }
    ],
    "sg:phone":"+44 1608 652080",
    "sg:postcode":"GL56 0AX",
    "sg:province":"Gloucestershire",
    "sg:tags":[
        "shop"
    ],
    "wof:name":"The Oxford Shirt Co",
    "wof:placetype":"venue"
},
  "geometry": {"coordinates":[-1.703281045,51.9897270203],"type":"Point"}
}