{
  "type": "Feature",
  "properties": {
    "iso:country":"GB",
    "sg:address":"51 King Edward Avenue",
    "sg:city":"Mansfield",
    "sg:classifiers":[
        {
            "category":"Building & Trades",
            "subcategory":"Landscaping Services",
            "type":"Services"
        }
    ],
    "sg:postcode":"NG18 5AE",
    "sg:province":"Nottinghamshire",
    "sg:tags":[
        "landscape",
        "contractor"
    ],
    "wof:name":"The Gardenscape Co.",
    "wof:placetype":"venue"
},
  "geometry": {"coordinates":[-1.2018100023,53.1306762695],"type":"Point"}
}