{
  "type": "Feature",
  "properties": {
    "iso:country":"GB",
    "sg:address":"The Rear Of Cecil Road, Gorseinon",
    "sg:city":"Swansea",
    "sg:classifiers":[
        {
            "category":"Retail",
            "subcategory":"Laundry & Dry Cleaning",
            "type":"Services"
        },
        {
            "category":"Building & Trades",
            "subcategory":"Cleaning & Sanitation",
            "type":"Services"
        }
    ],
    "sg:phone":"+44 1792 896077",
    "sg:postcode":"SA4 4BY",
    "sg:province":"Carmarthenshire",
    "sg:tags":[
        "launderette",
        "commercial"
    ],
    "wof:name":"Gorseinon Laundry Services",
    "wof:placetype":"venue"
},
  "geometry": {"coordinates":[-4.041219,51.666676],"type":"Point"}
}