{
  "type": "Feature",
  "properties": {
    "iso:country":"GB",
    "sg:address":"44 Chadwick Rd",
    "sg:city":"Westcliff On Sea",
    "sg:classifiers":[
        {
            "category":"Professional",
            "subcategory":"Accounting & Tax Preparation",
            "type":"Services"
        }
    ],
    "sg:phone":"+44 1702 213564",
    "sg:postcode":"SS0 8LD",
    "sg:province":"Essex",
    "sg:tags":[
        "accountant"
    ],
    "wof:name":"Accurate Accounting Bureau",
    "wof:placetype":"venue"
},
  "geometry": {"coordinates":[0.682595,51.541374],"type":"Point"}
}