{
  "type": "Feature",
  "properties": {
    "addr:full":"Foxyards Of Tipton, Sedgley Rd Tipton West Midlands DY4 8AP",
    "addr:postcode":"dy4 8ap",
    "addr:street":"Sedgley Rd",
    "iso:country":"GB",
    "sg:address":"Foxyards Of Tipton, Sedgley Rd",
    "sg:city":"Tipton",
    "sg:classifiers":[
        {
            "category":"Autos & Motor Vehicles",
            "subcategory":"Automobile Sales",
            "type":"Retail Goods"
        }
    ],
    "sg:phone":"+44 121 557 7153",
    "sg:postcode":"DY4 8AP",
    "sg:province":"West Midlands",
    "sg:tags":[
        "car"
    ],
    "wof:name":"Bloomfield Garages",
    "wof:placetype":"venue"
},
  "geometry": {"coordinates":[-2.070697,52.528137],"type":"Point"}
}