{
  "type": "Feature",
  "properties": {
    "iso:country":"GB",
    "sg:address":"68 Cannock Street",
    "sg:city":"Leicester",
    "sg:classifiers":[
        {
            "category":"Manufacturing",
            "subcategory":"Metals",
            "type":"Manufacturing & Wholesale Goods"
        }
    ],
    "sg:phone":"+44 116 276 7162",
    "sg:postcode":"LE4 9HR",
    "sg:province":"Leicestershire",
    "sg:tags":[
        "heat",
        "-",
        "treatment"
    ],
    "wof:name":"Lenton Treatments",
    "wof:placetype":"venue"
},
  "geometry": {"coordinates":[-1.0796149969,52.6619682312],"type":"Point"}
}