{
  "type": "Feature",
  "properties": {
    "iso:country":"GB",
    "sg:address":"Windle Field Farm, Mill Brow Rd",
    "sg:city":"Colne",
    "sg:classifiers":[
        {
            "category":"Farming",
            "subcategory":"Livestock Farm",
            "type":"Manufacturing & Wholesale Goods"
        }
    ],
    "sg:phone":"+44 1282 843248",
    "sg:postcode":"BB8 6JY",
    "sg:province":"Lancashire",
    "sg:tags":[
        "others"
    ],
    "wof:name":"M E Beresford",
    "wof:placetype":"venue"
},
  "geometry": {"coordinates":[-2.170365,53.856857],"type":"Point"}
}