{
  "type": "Feature",
  "properties": {
    "addr:full":"4a High Street Malpas Cheshire SY14 8NR",
    "addr:housenumber":"4a",
    "addr:postcode":"sy14 8nr",
    "addr:street":"High Street",
    "iso:country":"GB",
    "sg:address":"4a High Street",
    "sg:city":"Malpas",
    "sg:classifiers":[
        {
            "category":"Shopping",
            "subcategory":"Gifts & Souvenirs",
            "type":"Retail Goods"
        }
    ],
    "sg:phone":"+44 1948 861046",
    "sg:postcode":"SY14 8NR",
    "sg:province":"Cheshire",
    "sg:tags":[
        "shop"
    ],
    "wof:name":"The Secret Garden",
    "wof:placetype":"venue"
},
  "geometry": {"coordinates":[-2.767469,53.022041],"type":"Point"}
}