{
  "type": "Feature",
  "properties": {
    "addr:full":"203 Hills Road Cambridge Cambridgeshire CB2 2RN",
    "addr:housenumber":"203",
    "addr:postcode":"cb2 2rn",
    "addr:street":"Hills Road",
    "iso:country":"GB",
    "sg:address":"203 Hills Road",
    "sg:city":"Cambridge",
    "sg:classifiers":[
        {
            "category":"Shopping",
            "subcategory":"Pharmacy",
            "type":"Retail Goods"
        }
    ],
    "sg:phone":"+44 1223 210585",
    "sg:postcode":"CB2 2RN",
    "sg:province":"Cambridgeshire",
    "sg:tags":[
        "medicine",
        "therapy"
    ],
    "wof:name":"Celia Radha",
    "wof:placetype":"venue"
},
  "geometry": {"coordinates":[0.1381420046,52.1860961914],"type":"Point"}
}