{
  "type": "Feature",
  "properties": {
    "addr:full":"18 East Street Barking Essex IG11 8EU",
    "addr:housenumber":"18",
    "addr:postcode":"ig11 8eu",
    "addr:street":"East Street",
    "iso:country":"GB",
    "sg:address":"18 East Street",
    "sg:city":"Barking",
    "sg:classifiers":[
        {
            "category":"Food & Beverages",
            "subcategory":"Bakery",
            "type":"Retail Goods"
        }
    ],
    "sg:phone":"+44 20 8507 7889",
    "sg:postcode":"IG11 8EU",
    "sg:province":"Essex",
    "sg:tags":[
        "baker"
    ],
    "wof:name":"Cornish Pasty Bakeries",
    "wof:placetype":"venue"
},
  "geometry": {"coordinates":[0.077315,51.536331],"type":"Point"}
}