{
  "type": "Feature",
  "properties": {
    "addr:full":"Suite B4 Romany Centre, Wareham Rd, Holton Heath Poole Dorset BH16 6JL",
    "addr:housenumber":"suite b4",
    "addr:postcode":"bh16 6jl",
    "addr:street":"Wareham Rd",
    "iso:country":"GB",
    "sg:address":"Suite B4 Romany Centre, Wareham Rd, Holton Heath",
    "sg:city":"Poole",
    "sg:classifiers":[
        {
            "category":"Professional",
            "subcategory":"Computer Services",
            "type":"Services"
        }
    ],
    "sg:postcode":"BH16 6JL",
    "sg:province":"Dorset",
    "sg:tags":[
        "system",
        "software"
    ],
    "wof:name":"Razmatazz Ltd",
    "wof:placetype":"venue"
},
  "geometry": {"coordinates":[-2.0723590851,50.7173309326],"type":"Point"}
}