{
  "type": "Feature",
  "properties": {
    "iso:country":"GB",
    "sg:address":"8 Lake Industrial Way",
    "sg:city":"Sandown",
    "sg:classifiers":[
        {
            "category":"Building & Trades",
            "subcategory":"Construction",
            "type":"Services"
        }
    ],
    "sg:phone":"+44 1983 408999",
    "sg:postcode":"PO36 9PL",
    "sg:province":"Isle of Wight",
    "sg:tags":[
        "window",
        "replacement"
    ],
    "wof:name":"The Window Doctor",
    "wof:placetype":"venue"
},
  "geometry": {"coordinates":[-1.163906,50.650135],"type":"Point"}
}