{
  "type": "Feature",
  "properties": {
    "iso:country":"GB",
    "sg:address":"11 Townsend Pl",
    "sg:city":"Kingswinford",
    "sg:classifiers":[
        {
            "category":"Restaurant",
            "type":"Food & Drink"
        }
    ],
    "sg:phone":"+44 1384 291889",
    "sg:postcode":"DY6 9JL",
    "sg:province":"Staffordshire",
    "sg:tags":[
        "indian"
    ],
    "wof:name":"Kingswinford Tandoori Restaurant",
    "wof:placetype":"venue"
},
  "geometry": {"coordinates":[-2.167674,52.495804],"type":"Point"}
}