{
  "type": "Feature",
  "properties": {
    "addr:full":"7 Martletts Corner, Church Street, Rudgwick Horsham West Sussex RH12 3EX",
    "addr:housenumber":"7",
    "addr:postcode":"rh12 3ex",
    "addr:street":"Martletts Corner Church Street",
    "iso:country":"GB",
    "sg:address":"7 Martletts Corner, Church Street, Rudgwick",
    "sg:city":"Horsham",
    "sg:classifiers":[
        {
            "category":"Shopping",
            "subcategory":"Florist",
            "type":"Retail Goods"
        }
    ],
    "sg:postcode":"RH12 3EX",
    "sg:province":"West Sussex",
    "wof:name":"Mimosa",
    "wof:placetype":"venue"
},
  "geometry": {"coordinates":[-0.448429,51.090824],"type":"Point"}
}