{
  "type": "Feature",
  "properties": {
    "addr:full":"Y Grug Rhyddwen Pl, Craig Cefn Parc Swansea Swansea SA6 5RL",
    "addr:postcode":"sa6 5rl",
    "addr:street":"Pl;Cefn Parc",
    "iso:country":"GB",
    "sg:address":"Y Grug Rhyddwen Pl, Craig Cefn Parc",
    "sg:city":"Swansea",
    "sg:classifiers":[
        {
            "category":"Building & Trades",
            "subcategory":"Equipment Rental",
            "type":"Services"
        }
    ],
    "sg:postcode":"SA6 5RL",
    "sg:province":"Swansea",
    "sg:tags":[
        "plant",
        "machinery"
    ],
    "wof:name":"Mainwaring,John E,",
    "wof:placetype":"venue"
},
  "geometry": {"coordinates":[-3.908297,51.708149],"type":"Point"}
}