{
  "type": "Feature",
  "properties": {
    "addr:full":"48 Kings Road Lancing West Sussex BN15 8DY",
    "addr:housenumber":"48",
    "addr:postcode":"bn15 8dy",
    "addr:street":"Kings Road",
    "iso:country":"GB",
    "sg:address":"48 Kings Road",
    "sg:city":"Lancing",
    "sg:classifiers":[
        {
            "category":"Professional",
            "subcategory":"Art Services",
            "type":"Services"
        }
    ],
    "sg:phone":"+44 1903 753562",
    "sg:postcode":"BN15 8DY",
    "sg:province":"West Sussex",
    "sg:tags":[
        "photographer"
    ],
    "wof:name":"Andrew Mardell Photography",
    "wof:placetype":"venue"
},
  "geometry": {"coordinates":[-0.316041,50.825005],"type":"Point"}
}