{
  "type": "Feature",
  "properties": {
    "iso:country":"GB",
    "sg:address":"9 East Circus Street",
    "sg:city":"Nottingham",
    "sg:classifiers":[
        {
            "category":"Professional",
            "subcategory":"Engineering",
            "type":"Services"
        }
    ],
    "sg:phone":"+44 115 947 3115",
    "sg:postcode":"NG1 5AF",
    "sg:province":"Nottinghamshire",
    "sg:tags":[
        "engineer",
        "structural"
    ],
    "wof:name":"Keith Simpson Associates Ltd.",
    "wof:placetype":"venue"
},
  "geometry": {"coordinates":[-1.156381,52.953545],"type":"Point"}
}