{
  "type": "Feature",
  "properties": {
    "iso:country":"GB",
    "sg:address":"261 King Street, Broughty Ferry",
    "sg:city":"Dundee",
    "sg:classifiers":[
        {
            "category":"Autos & Motor Vehicles",
            "subcategory":"Automobile Sales",
            "type":"Retail Goods"
        }
    ],
    "sg:phone":"+44 1382 779708",
    "sg:postcode":"DD5 2AZ",
    "sg:province":"Angus",
    "sg:tags":[
        "car"
    ],
    "wof:name":"John McGregor Brou'ty",
    "wof:placetype":"venue"
},
  "geometry": {"coordinates":[-2.873482,56.465786],"type":"Point"}
}