{
  "type": "Feature",
  "properties": {
    "iso:country":"GB",
    "sg:address":"Knightshayes Court, Bolham",
    "sg:city":"Tiverton",
    "sg:classifiers":[
        {
            "category":"Landmark",
            "subcategory":"Tourist Attraction",
            "type":"Public Place"
        }
    ],
    "sg:phone":"+44 1884 254665",
    "sg:postcode":"EX16 7RQ",
    "sg:province":"Devon",
    "sg:tags":[
        "interest"
    ],
    "wof:name":"The National Trust",
    "wof:placetype":"venue"
},
  "geometry": {"coordinates":[-3.48115,50.925941],"type":"Point"}
}