{
  "type": "Feature",
  "properties": {
    "addr:full":"144-146 Lower Clapton Road London Greater London E5 0QN",
    "addr:housenumber":"144-146",
    "addr:postcode":"e5 0qn",
    "addr:street":"Lower Clapton Road",
    "iso:country":"GB",
    "sg:address":"144-146 Lower Clapton Road",
    "sg:city":"London",
    "sg:classifiers":[
        {
            "category":"Manufacturing",
            "subcategory":"Signs",
            "type":"Manufacturing & Wholesale Goods"
        }
    ],
    "sg:phone":"+44 20 8985 8835",
    "sg:postcode":"E5 0QN",
    "sg:province":"Greater London",
    "sg:tags":[
        "writer"
    ],
    "wof:name":"Sara Signs",
    "wof:placetype":"venue"
},
  "geometry": {"coordinates":[-0.0544200018,51.5560874939],"type":"Point"}
}