{
  "type": "Feature",
  "properties": {
    "iso:country":"GB",
    "sg:address":"79 King Lane",
    "sg:city":"Leeds",
    "sg:classifiers":[
        {
            "category":"Shopping",
            "subcategory":"Pharmacy",
            "type":"Retail Goods"
        }
    ],
    "sg:phone":"+44 113 268 7331",
    "sg:postcode":"LS17 5AX",
    "sg:province":"North Yorkshire",
    "sg:tags":[
        "pharmacist",
        "dispensing",
        "chemist"
    ],
    "sg:website":"http://www.livingcare.co.uk",
    "wof:name":"King Lane Pharmacy",
    "wof:placetype":"venue"
},
  "geometry": {"coordinates":[-1.544199,53.840832],"type":"Point"}
}