{
  "type": "Feature",
  "properties": {
    "addr:full":"113 Cowgate, Kirkintilloch Glasgow East Dunbartonshire G66 1HW",
    "addr:housenumber":"113",
    "addr:postcode":"g66 1hw",
    "addr:street":"Cowgate Kirkintilloch",
    "iso:country":"GB",
    "sg:address":"113 Cowgate, Kirkintilloch",
    "sg:city":"Glasgow",
    "sg:classifiers":[
        {
            "category":"Autos & Motor Vehicles",
            "subcategory":"Automobile Sales",
            "type":"Retail Goods"
        },
        {
            "category":"Shopping",
            "type":"Retail Goods"
        }
    ],
    "sg:postcode":"G66 1HW",
    "sg:province":"East Dunbartonshire",
    "sg:tags":[
        "car",
        "part",
        "accessory"
    ],
    "wof:name":"Taylor,Sandy,",
    "wof:placetype":"venue"
},
  "geometry": {"coordinates":[-4.1563577652,55.939617157],"type":"Point"}
}