{
  "type": "Feature",
  "properties": {
    "iso:country":"GB",
    "sg:address":"Elm Lane, Earley",
    "sg:city":"Reading",
    "sg:classifiers":[
        {
            "category":"Professional",
            "type":"Services"
        }
    ],
    "sg:phone":"+44 118 975 3653",
    "sg:postcode":"RG6 5UQ",
    "sg:province":"Berkshire",
    "sg:tags":[
        "interior",
        "furnishers",
        "designer"
    ],
    "wof:name":"Karen Taylor",
    "wof:placetype":"venue"
},
  "geometry": {"coordinates":[-0.9399160147,51.4314689636],"type":"Point"}
}