{
  "type": "Feature",
  "properties": {
    "addr:full":"1 2 & 3 Pelham Yard, High Street Seaford East Sussex BN25 1PQ",
    "addr:housenumber":"2 & 3",
    "addr:postcode":"bn25 1pq",
    "addr:street":"Pelham Yard High Street",
    "iso:country":"GB",
    "sg:address":"1 2 & 3 Pelham Yard, High Street",
    "sg:city":"Seaford",
    "sg:classifiers":[
        {
            "category":"Professional",
            "subcategory":"Management & Consulting",
            "type":"Services"
        }
    ],
    "sg:phone":"+44 1323 893770",
    "sg:postcode":"BN25 1PQ",
    "sg:province":"East Sussex",
    "sg:tags":[
        "consultant",
        "business"
    ],
    "wof:name":"B S Boyce & Co",
    "wof:placetype":"venue"
},
  "geometry": {"coordinates":[0.102289997,50.7707710266],"type":"Point"}
}