{
  "type": "Feature",
  "properties": {
    "iso:country":"GB",
    "sg:address":"195 Stoke Road",
    "sg:city":"Gosport",
    "sg:classifiers":[
        {
            "category":"Bars & Pubs",
            "type":"Food & Drink"
        }
    ],
    "sg:phone":"+44 23 9252 0031",
    "sg:postcode":"PO12 1SE",
    "sg:province":"Hampshire",
    "sg:tags":[
        "pubs",
        "inn"
    ],
    "wof:name":"The White Hart",
    "wof:placetype":"venue"
},
  "geometry": {"coordinates":[-1.136958,50.792278],"type":"Point"}
}