{
  "type": "Feature",
  "properties": {
    "addr:full":"6 South Close Alresford Hampshire SO24 9HS",
    "addr:housenumber":"6",
    "addr:postcode":"so24 9hs",
    "addr:street":"South Close",
    "iso:country":"GB",
    "sg:address":"6 South Close",
    "sg:city":"Alresford",
    "sg:classifiers":[
        {
            "category":"Professional",
            "subcategory":"Engineering",
            "type":"Services"
        }
    ],
    "sg:postcode":"SO24 9HS",
    "sg:province":"Hampshire",
    "sg:tags":[
        "engineer",
        "structural"
    ],
    "wof:name":"E T Design",
    "wof:placetype":"venue"
},
  "geometry": {"coordinates":[-1.1756819487,51.0853614807],"type":"Point"}
}