{
  "type": "Feature",
  "properties": {
    "addr:full":"12 High Road London Greater London E18 2QL",
    "addr:housenumber":"12",
    "addr:postcode":"e18 2ql",
    "addr:street":"High Road",
    "iso:country":"GB",
    "sg:address":"12 High Road",
    "sg:city":"London",
    "sg:classifiers":[
        {
            "category":"Personal",
            "subcategory":"Beauty Salon",
            "type":"Services"
        }
    ],
    "sg:phone":"+44 20 7622 2044",
    "sg:postcode":"E18 2QL",
    "sg:province":"Greater London",
    "sg:tags":[
        "ladies",
        "lady",
        "hairdresser"
    ],
    "wof:name":"CHARLES",
    "wof:placetype":"venue"
},
  "geometry": {"coordinates":[0.0226440001,51.5929603577],"type":"Point"}
}