{
  "type": "Feature",
  "properties": {
    "iso:country":"GB",
    "sg:address":"Newbury Lane, Coleford",
    "sg:city":"Bath",
    "sg:classifiers":[
        {
            "category":"Utilities",
            "subcategory":"Refuse",
            "type":"Services"
        }
    ],
    "sg:phone":"+44 1373 813515",
    "sg:postcode":"BA3 5RU",
    "sg:province":"Somerset",
    "sg:tags":[
        "disposal",
        "waste"
    ],
    "wof:name":"Wyvern Waste Services Ltd.",
    "wof:placetype":"venue"
},
  "geometry": {"coordinates":[-2.446518,51.242432],"type":"Point"}
}