{
  "type": "Feature",
  "properties": {
    "iso:country":"GB",
    "sg:address":"Forge House, The Grn, Bearsted",
    "sg:city":"Maidstone",
    "sg:classifiers":[
        {
            "category":"Banks & Credit Unions",
            "subcategory":"Financial Services",
            "type":"Services"
        }
    ],
    "sg:phone":"+44 1622 734454",
    "sg:postcode":"ME14 4DT",
    "sg:province":"Kent",
    "sg:tags":[
        "adviser",
        "independent"
    ],
    "wof:name":"Manners Horne & Co",
    "wof:placetype":"venue"
},
  "geometry": {"coordinates":[0.574084,51.267258],"type":"Point"}
}