{
  "type": "Feature",
  "properties": {
    "iso:country":"GB",
    "sg:address":"134-138 Buxton Road",
    "sg:city":"Stockport",
    "sg:classifiers":[
        {
            "category":"Home & Garden",
            "subcategory":"Hardware",
            "type":"Retail Goods"
        }
    ],
    "sg:postcode":"SK2 6PL",
    "sg:province":"Cheshire",
    "sg:tags":[
        "retailer",
        "lighting"
    ],
    "wof:name":"Cheshire Trading Co",
    "wof:placetype":"venue"
},
  "geometry": {"coordinates":[-2.148624,53.394711],"type":"Point"}
}