{
  "type": "Feature",
  "properties": {
    "addr:full":"78 Ilford Lane Ilford Essex IG1 2LA",
    "addr:housenumber":"78",
    "addr:postcode":"ig1 2la",
    "addr:street":"Ilford Lane",
    "iso:country":"GB",
    "sg:address":"78 Ilford Lane",
    "sg:city":"Ilford",
    "sg:classifiers":[
        {
            "category":"Real Estate",
            "subcategory":"Real Estate Operator",
            "type":"Services"
        }
    ],
    "sg:phone":"+44 20 8553 9933",
    "sg:postcode":"IG1 2LA",
    "sg:province":"Essex",
    "sg:tags":[
        "letting",
        "agent"
    ],
    "wof:name":"Chas Property Services",
    "wof:placetype":"venue"
},
  "geometry": {"coordinates":[0.0720510036,51.5547828674],"type":"Point"}
}