{
  "type": "Feature",
  "properties": {
    "addr:full":"33-37 Bury Old Rd Bolton Lancashire BL2 2AY",
    "addr:housenumber":"33-37",
    "addr:postcode":"bl2 2ay",
    "addr:street":"Bury Old Rd",
    "iso:country":"GB",
    "sg:address":"33-37 Bury Old Rd",
    "sg:city":"Bolton",
    "sg:classifiers":[
        {
            "category":"Shopping",
            "type":"Retail Goods"
        }
    ],
    "sg:phone":"+44 1204 385888",
    "sg:postcode":"BL2 2AY",
    "sg:province":"Lancashire",
    "sg:tags":[
        "part",
        "accessory"
    ],
    "wof:name":"Brakes International Ltd",
    "wof:placetype":"venue"
},
  "geometry": {"coordinates":[-2.4187040329,53.5798110962],"type":"Point"}
}