{
  "type": "Feature",
  "properties": {
    "iso:country":"GB",
    "sg:address":"Unit 7, Monksbridge Trading Estate, Dinnington",
    "sg:city":"Sheffield",
    "sg:classifiers":[
        {
            "category":"Retail",
            "subcategory":"Auto Repair",
            "type":"Services"
        }
    ],
    "sg:phone":"+44 1909 563348",
    "sg:postcode":"S25 3QZ",
    "sg:province":"South Yorkshire",
    "sg:tags":[
        "modification",
        "garage",
        "related"
    ],
    "wof:name":"Monksbridge Garage",
    "wof:placetype":"venue"
},
  "geometry": {"coordinates":[-1.229069,53.373051],"type":"Point"}
}