{
  "type": "Feature",
  "properties": {
    "iso:country":"GB",
    "sg:address":"35-51 Burr Road, Wandsworth",
    "sg:city":"London",
    "sg:classifiers":[
        {
            "category":"Retail",
            "subcategory":"Auto Repair",
            "type":"Services"
        }
    ],
    "sg:phone":"+44 20 8874 3635",
    "sg:postcode":"SW18 4SQ",
    "sg:province":"Greater London",
    "sg:tags":[
        "body",
        "garage",
        "modification",
        "car"
    ],
    "wof:name":"Tielynn Motors Ltd.",
    "wof:placetype":"venue"
},
  "geometry": {"coordinates":[-0.195825,51.446476],"type":"Point"}
}