{
  "type": "Feature",
  "properties": {
    "addr:full":"Bluewater Park Site Office, Bean Road Greenhithe Kent DA9 9JH",
    "addr:postcode":"da9 9jh",
    "addr:street":"Bean Road",
    "iso:country":"GB",
    "sg:address":"Bluewater Park Site Office, Bean Road",
    "sg:city":"Greenhithe",
    "sg:classifiers":[
        {
            "category":"Building & Trades",
            "subcategory":"Equipment Rental",
            "type":"Services"
        }
    ],
    "sg:postcode":"DA9 9JH",
    "sg:province":"Kent",
    "sg:tags":[
        "plant",
        "machinery"
    ],
    "wof:name":"Wyseplant Ltd.",
    "wof:placetype":"venue"
},
  "geometry": {"coordinates":[0.277498,51.440262],"type":"Point"}
}