{
  "type": "Feature",
  "properties": {
    "iso:country":"GB",
    "sg:address":"Walnut Lodge, Luton Road Wilshamstead",
    "sg:city":"Bedford",
    "sg:classifiers":[
        {
            "category":"Building & Trades",
            "subcategory":"Construction",
            "type":"Services"
        }
    ],
    "sg:postcode":"MK45 3ET",
    "sg:province":"Bedfordshire",
    "sg:tags":[
        "joiner",
        "carpenter"
    ],
    "wof:name":"Peter Mackinnon",
    "wof:placetype":"venue"
},
  "geometry": {"coordinates":[-0.44987,52.074848],"type":"Point"}
}