{
  "type": "Feature",
  "properties": {
    "addr:full":"High St Billingshurst West Sussex RH14 9QS",
    "addr:postcode":"rh14 9qs",
    "addr:street":"High St",
    "iso:country":"GB",
    "sg:address":"High St",
    "sg:city":"Billingshurst",
    "sg:classifiers":[
        {
            "category":"Place Of Worship",
            "type":"Public Place"
        }
    ],
    "sg:phone":"+44 1403 711132",
    "sg:postcode":"RH14 9QS",
    "sg:province":"West Sussex",
    "wof:name":"Free Christian Church (Unitarian)",
    "wof:placetype":"venue"
},
  "geometry": {"coordinates":[-0.449814,51.024963],"type":"Point"}
}