{
  "type": "Feature",
  "properties": {
    "addr:full":"Cliff Parade Penarth The Vale of Glamorgan CF64 5BP",
    "addr:postcode":"cf64 5bp",
    "addr:street":"Cliff Parade;Vale",
    "iso:country":"GB",
    "sg:address":"Cliff Parade",
    "sg:city":"Penarth",
    "sg:classifiers":[
        {
            "category":"Restaurant",
            "type":"Food & Drink"
        }
    ],
    "sg:phone":"+44 29 2070 2785",
    "sg:postcode":"CF64 5BP",
    "sg:province":"The Vale of Glamorgan",
    "sg:tags":[
        "-",
        "italian"
    ],
    "wof:name":"CIONI BISTRO",
    "wof:placetype":"venue"
},
  "geometry": {"coordinates":[-3.17146,51.428207],"type":"Point"}
}