{
  "type": "Feature",
  "properties": {
    "addr:full":"Commercial Barns, Helmingham Rd Ipswich Suffolk IP6 9JS",
    "addr:postcode":"ip6 9js",
    "addr:street":"Helmingham Rd",
    "iso:country":"GB",
    "sg:address":"Commercial Barns, Helmingham Rd",
    "sg:city":"Ipswich",
    "sg:classifiers":[
        {
            "category":"Building & Trades",
            "subcategory":"Construction",
            "type":"Services"
        }
    ],
    "sg:phone":"+44 1473 890018",
    "sg:postcode":"IP6 9JS",
    "sg:province":"Suffolk",
    "sg:tags":[
        "joinery"
    ],
    "wof:name":"Bloom,John,",
    "wof:placetype":"venue"
},
  "geometry": {"coordinates":[1.19606,52.150639],"type":"Point"}
}