{
  "type": "Feature",
  "properties": {
    "iso:country":"GB",
    "sg:address":"11 Saulfland Place",
    "sg:city":"Christchurch",
    "sg:classifiers":[
        {
            "category":"Food & Beverages",
            "subcategory":"Groceries & Convenience Stores",
            "type":"Retail Goods"
        }
    ],
    "sg:phone":"+44 1425 274025",
    "sg:postcode":"BH23 4QP",
    "sg:province":"Dorset",
    "wof:name":"Saulflands Post Office & Store",
    "wof:placetype":"venue"
},
  "geometry": {"coordinates":[-1.724269,50.743111],"type":"Point"}
}