{
  "type": "Feature",
  "properties": {
    "iso:country":"GB",
    "sg:address":"Greatwell Drive",
    "sg:city":"Romsey",
    "sg:classifiers":[
        {
            "category":"Social Services",
            "subcategory":"Retirement Home",
            "type":"Services"
        },
        {
            "category":"Government",
            "subcategory":"Office",
            "type":"Public Place"
        }
    ],
    "sg:phone":"+44 1794 512138",
    "sg:postcode":"SO51 7QN",
    "sg:province":"Hampshire",
    "sg:tags":[
        "residential",
        "local",
        "care"
    ],
    "wof:name":"Nightingale Lodge",
    "wof:placetype":"venue"
},
  "geometry": {"coordinates":[-1.488321,50.992657],"type":"Point"}
}