{
  "type": "Feature",
  "properties": {
    "iso:country":"GB",
    "sg:address":"1 Brodie House, Central Square",
    "sg:city":"Telford",
    "sg:classifiers":[
        {
            "category":"Professional",
            "subcategory":"Lawyer & Legal Services",
            "type":"Services"
        }
    ],
    "sg:phone":"+44 1952 291222",
    "sg:postcode":"TF3 4DR",
    "sg:province":"Shropshire",
    "sg:tags":[
        "solicitor"
    ],
    "wof:name":"Lanyon Bowdler",
    "wof:placetype":"venue"
},
  "geometry": {"coordinates":[-2.447883,52.679321],"type":"Point"}
}