{
  "type": "Feature",
  "properties": {
    "addr:full":"Park Hill, Dunmill Rd Bracknell Berkshire RG12 1QS",
    "addr:postcode":"rg12 1qs",
    "addr:street":"Dunmill Rd",
    "iso:country":"GB",
    "sg:address":"Park Hill, Dunmill Rd",
    "sg:city":"Bracknell",
    "sg:classifiers":[
        {
            "category":"Communications",
            "type":"Services"
        }
    ],
    "sg:phone":"+44 1344 381400",
    "sg:postcode":"RG12 1QS",
    "sg:province":"Berkshire",
    "sg:tags":[
        "audio-visual"
    ],
    "wof:name":"Multimedia & Teleconferencing Solutions",
    "wof:placetype":"venue"
},
  "geometry": {"coordinates":[-0.7657399774,51.4148216248],"type":"Point"}
}