{
  "type": "Feature",
  "properties": {
    "addr:full":"Unit 3 Twin Trees Business Park, Moor Lane Westfield Woking Surrey GU22 9RB",
    "addr:housenumber":"unit 3",
    "addr:postcode":"gu22 9rb",
    "addr:street":"Twin Trees Business Park Moor Lane",
    "iso:country":"GB",
    "sg:address":"Unit 3 Twin Trees Business Park, Moor Lane Westfield",
    "sg:city":"Woking",
    "sg:classifiers":[
        {
            "category":"Professional",
            "subcategory":"Advertising",
            "type":"Services"
        }
    ],
    "sg:postcode":"GU22 9RB",
    "sg:province":"Surrey",
    "sg:tags":[
        "distribution",
        "circular"
    ],
    "wof:name":"Crays Hill Holdings Ltd.",
    "wof:placetype":"venue"
},
  "geometry": {"coordinates":[-0.5558000207,51.2949905396],"type":"Point"}
}