{
  "type": "Feature",
  "properties": {
    "iso:country":"GB",
    "sg:address":"Bells Close",
    "sg:city":"Newcastle-upon-tyne",
    "sg:classifiers":[
        {
            "category":"Place Of Worship",
            "type":"Public Place"
        },
        {
            "category":"Education",
            "subcategory":"School",
            "type":"Public Place"
        }
    ],
    "sg:phone":"+44 191 267 5677",
    "sg:postcode":"NE15 6XX",
    "sg:province":"Northumberland",
    "sg:tags":[
        "local",
        "authority"
    ],
    "wof:name":"St Georges R C Primary School",
    "wof:placetype":"venue"
},
  "geometry": {"coordinates":[-1.7015420198,54.9732704163],"type":"Point"}
}