{
  "type": "Feature",
  "properties": {
    "addr:full":"125 Bridge Street Belper Derbyshire DE56 1BA",
    "addr:housenumber":"125",
    "addr:postcode":"de56 1ba",
    "addr:street":"Bridge Street",
    "iso:country":"GB",
    "sg:address":"125 Bridge Street",
    "sg:city":"Belper",
    "sg:classifiers":[
        {
            "category":"Personal",
            "type":"Services"
        },
        {
            "category":"Professional",
            "subcategory":"Business Services",
            "type":"Services"
        }
    ],
    "sg:postcode":"DE56 1BA",
    "sg:province":"Derbyshire",
    "sg:tags":[
        "import",
        "export",
        "agent",
        "wedding"
    ],
    "wof:name":"Allisons Cakes & Crafts",
    "wof:placetype":"venue"
},
  "geometry": {"coordinates":[-1.485745,53.026981],"type":"Point"}
}