{
  "type": "Feature",
  "properties": {
    "addr:full":"1106 High Road, Chadwell Heath Romford Essex RM6 4AD",
    "addr:housenumber":"1106",
    "addr:postcode":"rm6 4ad",
    "addr:street":"High Road",
    "iso:country":"GB",
    "sg:address":"1106 High Road, Chadwell Heath",
    "sg:city":"Romford",
    "sg:classifiers":[
        {
            "category":"Health Services",
            "subcategory":"Optometrist",
            "type":"Services"
        }
    ],
    "sg:phone":"+44 20 8590 1762",
    "sg:postcode":"RM6 4AD",
    "sg:province":"Essex",
    "sg:tags":[
        "optician"
    ],
    "wof:name":"J I Partridges",
    "wof:placetype":"venue"
},
  "geometry": {"coordinates":[0.12404,51.56937],"type":"Point"}
}