{
  "type": "Feature",
  "properties": {
    "addr:full":"137 High Street Dorking Surrey RH4 1AQ",
    "addr:housenumber":"137",
    "addr:postcode":"rh4 1aq",
    "addr:street":"High Street",
    "iso:country":"GB",
    "sg:address":"137 High Street",
    "sg:city":"Dorking",
    "sg:classifiers":[
        {
            "category":"Shopping",
            "subcategory":"Luggage & Leather Goods",
            "type":"Retail Goods"
        }
    ],
    "sg:phone":"+44 1306 889398",
    "sg:postcode":"RH4 1AQ",
    "sg:province":"Surrey",
    "sg:tags":[
        "shop",
        "leathergoods"
    ],
    "wof:name":"Lockey Bros",
    "wof:placetype":"venue"
},
  "geometry": {"coordinates":[-0.3301750124,51.2325553894],"type":"Point"}
}