{
  "type": "Feature",
  "properties": {
    "addr:full":"The Piggery, Laundry Lane Leominster Herefordshire HR6 8JT",
    "addr:postcode":"hr6 8jt",
    "addr:street":"Laundry Lane",
    "iso:country":"GB",
    "sg:address":"The Piggery, Laundry Lane",
    "sg:city":"Leominster",
    "sg:classifiers":[
        {
            "category":"Building & Trades",
            "subcategory":"Cleaning & Sanitation",
            "type":"Services"
        }
    ],
    "sg:postcode":"HR6 8JT",
    "sg:province":"Herefordshire",
    "sg:tags":[
        "commercial",
        "sweep",
        "chimney"
    ],
    "wof:name":"Geoffrey John Pritchard",
    "wof:placetype":"venue"
},
  "geometry": {"coordinates":[-2.7435529232,52.2270774841],"type":"Point"}
}