{
  "type": "Feature",
  "properties": {
    "iso:country":"GB",
    "sg:address":"2 Valley View Close",
    "sg:city":"Plymouth",
    "sg:classifiers":[
        {
            "category":"Banks & Credit Unions",
            "subcategory":"Bank",
            "type":"Services"
        }
    ],
    "sg:phone":"+44 1752 702749",
    "sg:postcode":"PL3 6PJ",
    "sg:province":"Devon",
    "sg:tags":[
        "stocktaking",
        "inventory"
    ],
    "wof:name":"Nicholas & Linda Bawden",
    "wof:placetype":"venue"
},
  "geometry": {"coordinates":[-4.113805,50.393173],"type":"Point"}
}