{
  "type": "Feature",
  "properties": {
    "iso:country":"GB",
    "sg:address":"11 Rectory Road, Ashton In Makerfield",
    "sg:city":"Wigan",
    "sg:classifiers":[
        {
            "category":"Bus Charters",
            "type":"Transportation"
        }
    ],
    "sg:postcode":"WN4 0QD",
    "sg:province":"Lancashire",
    "sg:tags":[
        "mini",
        "hire",
        "leasing"
    ],
    "wof:name":"Ashton Mini Travel",
    "wof:placetype":"venue"
},
  "geometry": {"coordinates":[-2.665732,53.495975],"type":"Point"}
}