{
  "type": "Feature",
  "properties": {
    "addr:full":"36 Hardwicke Road Hastings East Sussex TN34 3PF",
    "addr:housenumber":"36",
    "addr:postcode":"tn34 3pf",
    "addr:street":"Hardwicke Road",
    "iso:country":"GB",
    "sg:address":"36 Hardwicke Road",
    "sg:city":"Hastings",
    "sg:classifiers":[
        {
            "category":"Professional",
            "type":"Services"
        }
    ],
    "sg:phone":"+44 1424 426501",
    "sg:postcode":"TN34 3PF",
    "sg:province":"East Sussex",
    "sg:tags":[
        "entertainer"
    ],
    "wof:name":"Daisy Daffodil",
    "wof:placetype":"venue"
},
  "geometry": {"coordinates":[0.597335,50.86565],"type":"Point"}
}