{
  "type": "Feature",
  "properties": {
    "addr:full":"17 Macclesfield Road, Plestbury Macclesfield Cheshire SK10 4BW",
    "addr:housenumber":"17",
    "addr:postcode":"sk10 4bw",
    "addr:street":"Macclesfield Road Plestbury",
    "iso:country":"GB",
    "sg:address":"17 Macclesfield Road, Plestbury",
    "sg:city":"Macclesfield",
    "sg:classifiers":[
        {
            "category":"Retail",
            "subcategory":"Funeral Services",
            "type":"Services"
        },
        {
            "category":"Building & Trades",
            "subcategory":"Construction",
            "type":"Services"
        }
    ],
    "sg:phone":"+44 1625 829232",
    "sg:postcode":"SK10 4BW",
    "sg:province":"Cheshire",
    "sg:tags":[
        "builder"
    ],
    "wof:name":"J W Brocklehurst & Sons Ltd",
    "wof:placetype":"venue"
},
  "geometry": {"coordinates":[-2.150828,53.287529],"type":"Point"}
}