{
  "type": "Feature",
  "properties": {
    "addr:full":"40a Hampstead High Street London Greater London NW3 1QE",
    "addr:housenumber":"40a",
    "addr:postcode":"nw3 1qe",
    "addr:street":"Hampstead High Street",
    "iso:country":"GB",
    "sg:address":"40a Hampstead High Street",
    "sg:city":"London",
    "sg:classifiers":[
        {
            "category":"Banks & Credit Unions",
            "subcategory":"Investment Brokerage",
            "type":"Services"
        }
    ],
    "sg:phone":"+44 20 7433 3075",
    "sg:postcode":"NW3 1QE",
    "sg:province":"Greater London",
    "sg:tags":[
        "vehicle"
    ],
    "wof:name":"Central & Metropolitan Estates Western Ltd.",
    "wof:placetype":"venue"
},
  "geometry": {"coordinates":[-0.177484,51.556229],"type":"Point"}
}