{
  "type": "Feature",
  "properties": {
    "addr:full":"159 Abbey Foregate Shrewsbury Shropshire SY2 6AP",
    "addr:housenumber":"159",
    "addr:postcode":"sy2 6ap",
    "addr:street":"Abbey Foregate",
    "iso:country":"GB",
    "sg:address":"159 Abbey Foregate",
    "sg:city":"Shrewsbury",
    "sg:classifiers":[
        {
            "category":"Shopping",
            "subcategory":"Hobbies, Toys, & Games",
            "type":"Retail Goods"
        }
    ],
    "sg:postcode":"SY2 6AP",
    "sg:province":"Shropshire",
    "sg:tags":[
        "computer"
    ],
    "wof:name":"Brian Foster",
    "wof:placetype":"venue"
},
  "geometry": {"coordinates":[-2.7387719154,52.7062911987],"type":"Point"}
}