{
  "type": "Feature",
  "properties": {
    "addr:full":"Knapp Road Ashford Greater London TW15 2HZ",
    "addr:postcode":"tw15 2hz",
    "addr:street":"Knapp Road",
    "iso:country":"GB",
    "sg:address":"Knapp Road",
    "sg:city":"Ashford",
    "sg:classifiers":[
        {
            "category":"Education",
            "subcategory":"School",
            "type":"Public Place"
        },
        {
            "category":"Government",
            "subcategory":"Office",
            "type":"Public Place"
        }
    ],
    "sg:phone":"+44 1784 253379",
    "sg:postcode":"TW15 2HZ",
    "sg:province":"Greater London",
    "sg:tags":[
        "local",
        "authority"
    ],
    "wof:name":"Clarendon County First School",
    "wof:placetype":"venue"
},
  "geometry": {"coordinates":[-0.4657390118,51.4358863831],"type":"Point"}
}