{
  "type": "Feature",
  "properties": {
    "iso:country":"GB",
    "sg:address":"138 Nab Wood Drive",
    "sg:city":"Shipley",
    "sg:classifiers":[
        {
            "category":"Wholesale",
            "subcategory":"Medical Equipment & Supplies",
            "type":"Manufacturing & Wholesale Goods"
        }
    ],
    "sg:phone":"+44 1274 582120",
    "sg:postcode":"BD18 4EW",
    "sg:province":"West Yorkshire",
    "sg:tags":[
        "hospital",
        "optical"
    ],
    "wof:name":"RUTTERFORD DENTAL SUPPLIES LTD",
    "wof:placetype":"venue"
},
  "geometry": {"coordinates":[-1.809502,53.826889],"type":"Point"}
}