{
  "type": "Feature",
  "properties": {
    "iso:country":"GB",
    "sg:address":"2 The Green, Clifton, Swinton",
    "sg:city":"Manchester",
    "sg:classifiers":[
        {
            "category":"Government",
            "subcategory":"Post Office",
            "type":"Public Place"
        }
    ],
    "sg:phone":"+44 161 794 2973",
    "sg:postcode":"M27 8QL",
    "sg:province":"Greater Manchester",
    "wof:name":"P & D Brierley",
    "wof:placetype":"venue"
},
  "geometry": {"coordinates":[-2.322315,53.520401],"type":"Point"}
}