{
  "type": "Feature",
  "properties": {
    "addr:full":"14 Coverdale Gardens Croydon Surrey CR0 5LS",
    "addr:housenumber":"14",
    "addr:postcode":"cr0 5ls",
    "addr:street":"Coverdale Gardens",
    "iso:country":"GB",
    "sg:address":"14 Coverdale Gardens",
    "sg:city":"Croydon",
    "sg:classifiers":[
        {
            "category":"Real Estate",
            "subcategory":"Real Estate Operator",
            "type":"Services"
        }
    ],
    "sg:phone":"+44 20 8688 7086",
    "sg:postcode":"CR0 5LS",
    "sg:province":"Surrey",
    "sg:tags":[
        "letting",
        "agent"
    ],
    "wof:name":"Willow Residential Letting",
    "wof:placetype":"venue"
},
  "geometry": {"coordinates":[-0.080506,51.370667],"type":"Point"}
}