{
  "type": "Feature",
  "properties": {
    "iso:country":"GB",
    "sg:address":"Poplar Farm, Stanton Prior",
    "sg:city":"Bath",
    "sg:classifiers":[
        {
            "category":"Home & Garden",
            "subcategory":"Garden Supply",
            "type":"Retail Goods"
        },
        {
            "category":"Farming",
            "subcategory":"Livestock Farm",
            "type":"Manufacturing & Wholesale Goods"
        }
    ],
    "sg:postcode":"BA2 9HX",
    "sg:province":"Somerset",
    "sg:tags":[
        "bulb",
        "grower",
        "others"
    ],
    "wof:name":"R A & B W Hardwick",
    "wof:placetype":"venue"
},
  "geometry": {"coordinates":[-2.463439,51.365711],"type":"Point"}
}