{
  "type": "Feature",
  "properties": {
    "iso:country":"GB",
    "sg:address":"113 Cornwall St",
    "sg:city":"Plymouth",
    "sg:classifiers":[
        {
            "category":"Cafe",
            "type":"Food & Drink"
        }
    ],
    "sg:phone":"+44 1752 661105",
    "sg:postcode":"PL1 1PA",
    "sg:province":"Devon",
    "sg:tags":[
        "tea",
        "room"
    ],
    "wof:name":"Dumplins",
    "wof:placetype":"venue"
},
  "geometry": {"coordinates":[-4.146207,50.372185],"type":"Point"}
}