{
  "type": "Feature",
  "properties": {
    "addr:full":"98-100 Lea Village Birmingham West Midlands B33 9SD",
    "addr:housenumber":"98-100",
    "addr:postcode":"b33 9sd",
    "addr:street":"Lea Village",
    "iso:country":"GB",
    "sg:address":"98-100 Lea Village",
    "sg:city":"Birmingham",
    "sg:classifiers":[
        {
            "category":"Health Services",
            "subcategory":"Doctor",
            "type":"Services"
        }
    ],
    "sg:phone":"+44 121 789 9565",
    "sg:postcode":"B33 9SD",
    "sg:province":"West Midlands",
    "sg:tags":[
        "practitioners"
    ],
    "wof:name":"S K Dhamija",
    "wof:placetype":"venue"
},
  "geometry": {"coordinates":[-1.7801920176,52.4821052551],"type":"Point"}
}