{
  "type": "Feature",
  "properties": {
    "iso:country":"GB",
    "sg:address":"14 Priory Road",
    "sg:city":"Liverpool",
    "sg:classifiers":[
        {
            "category":"Food & Beverages",
            "subcategory":"Meat & Fish",
            "type":"Retail Goods"
        }
    ],
    "sg:phone":"+44 151 286 9285",
    "sg:postcode":"L4 2RY",
    "sg:province":"Merseyside",
    "sg:tags":[
        "butcher"
    ],
    "wof:name":"Bob Guy Quality Foods",
    "wof:placetype":"venue"
},
  "geometry": {"coordinates":[-2.954336,53.432613],"type":"Point"}
}