{
  "type": "Feature",
  "properties": {
    "addr:full":"25 Selby Rise Uckfield East Sussex TN22 5ED",
    "addr:housenumber":"25",
    "addr:postcode":"tn22 5ed",
    "addr:street":"Selby Rise",
    "iso:country":"GB",
    "sg:address":"25 Selby Rise",
    "sg:city":"Uckfield",
    "sg:classifiers":[
        {
            "category":"Health Services",
            "subcategory":"Nursing And Care Facility",
            "type":"Services"
        }
    ],
    "sg:phone":"+44 1825 766122",
    "sg:postcode":"TN22 5ED",
    "sg:province":"East Sussex",
    "sg:tags":[
        "home"
    ],
    "wof:name":"Elite Care",
    "wof:placetype":"venue"
},
  "geometry": {"coordinates":[0.1019980013,50.9644126892],"type":"Point"}
}