{
  "type": "Feature",
  "properties": {
    "iso:country":"GB",
    "sg:address":"Unit 2 1-5 Castle Street",
    "sg:city":"Forfar",
    "sg:classifiers":[
        {
            "category":"Organizations",
            "subcategory":"Non-profit Organization",
            "type":"Services"
        }
    ],
    "sg:phone":"+44 1307 469491",
    "sg:postcode":"DD8 3AE",
    "sg:province":"Angus",
    "sg:tags":[
        "organisation",
        "voluntary",
        "charity"
    ],
    "wof:name":"British Heart Foundation",
    "wof:placetype":"venue"
},
  "geometry": {"coordinates":[-2.888799,56.644356],"type":"Point"}
}