{
  "type": "Feature",
  "properties": {
    "addr:full":"58 Murray Place Stirling Stirling FK8 2BX",
    "addr:housenumber":"58",
    "addr:postcode":"fk8 2bx",
    "addr:street":"Murray Place",
    "iso:country":"GB",
    "sg:address":"58 Murray Place",
    "sg:city":"Stirling",
    "sg:classifiers":[
        {
            "category":"Shopping",
            "subcategory":"Clothing, Apparel, & Fashions",
            "type":"Retail Goods"
        }
    ],
    "sg:postcode":"FK8 2BX",
    "sg:province":"Stirling",
    "sg:tags":[
        "menswear"
    ],
    "wof:name":"Matt Clothing",
    "wof:placetype":"venue"
},
  "geometry": {"coordinates":[-3.9371380806,56.1196174622],"type":"Point"}
}