{
  "type": "Feature",
  "properties": {
    "iso:country":"GB",
    "sg:address":"939-953 London Road",
    "sg:city":"Leigh-on-sea",
    "sg:classifiers":[
        {
            "category":"Autos & Motor Vehicles",
            "subcategory":"Automobile Sales",
            "type":"Retail Goods"
        }
    ],
    "sg:phone":"+44 1702 472333",
    "sg:postcode":"SS9 3LQ",
    "sg:province":"Essex",
    "sg:tags":[
        "car"
    ],
    "wof:name":"Lancaster Specialist Cars",
    "wof:placetype":"venue"
},
  "geometry": {"coordinates":[0.668786,51.547009],"type":"Point"}
}