{
  "type": "Feature",
  "properties": {
    "iso:country":"GB",
    "sg:address":"Woodneuk, Station Road, Bolsover",
    "sg:city":"Chesterfield",
    "sg:classifiers":[
        {
            "category":"Bus Charters",
            "type":"Transportation"
        }
    ],
    "sg:phone":"+44 1246 822057",
    "sg:postcode":"S44 6BH",
    "sg:province":"Derbyshire",
    "sg:tags":[
        "hire",
        "coach"
    ],
    "wof:name":"Castle Coaches",
    "wof:placetype":"venue"
},
  "geometry": {"coordinates":[-1.2900710106,53.2290916443],"type":"Point"}
}