{
  "type": "Feature",
  "properties": {
    "iso:country":"GB",
    "sg:address":"111 Hertford Rd",
    "sg:city":"Lower Edmonton",
    "sg:classifiers":[
        {
            "category":"Building & Trades",
            "subcategory":"Construction",
            "type":"Services"
        }
    ],
    "sg:phone":"+44 20 8884 4868",
    "sg:postcode":"N9 7EE",
    "sg:province":"Greater London",
    "sg:tags":[
        "builder"
    ],
    "wof:name":"Crestmoor Ltd",
    "wof:placetype":"venue"
},
  "geometry": {"coordinates":[-0.056463,51.62846],"type":"Point"}
}