{
  "type": "Feature",
  "properties": {
    "iso:country":"GB",
    "sg:address":"4-5 George Row",
    "sg:city":"Northampton",
    "sg:classifiers":[
        {
            "category":"Real Estate",
            "subcategory":"Real Estate Agent",
            "type":"Services"
        }
    ],
    "sg:phone":"+44 1604 631225",
    "sg:postcode":"NN1 1DF",
    "sg:province":"Northamptonshire",
    "wof:name":"Property Management Services",
    "wof:placetype":"venue"
},
  "geometry": {"coordinates":[-0.896438,52.236752],"type":"Point"}
}