{
  "type": "Feature",
  "properties": {
    "addr:full":"7 Princes Drive Harrow Greater London HA1 1XJ",
    "addr:housenumber":"7",
    "addr:postcode":"ha1 1xj",
    "addr:street":"Princes Drive",
    "iso:country":"GB",
    "sg:address":"7 Princes Drive",
    "sg:city":"Harrow",
    "sg:classifiers":[
        {
            "category":"Wholesale",
            "subcategory":"Chemicals & Plastics",
            "type":"Manufacturing & Wholesale Goods"
        }
    ],
    "sg:postcode":"HA1 1XJ",
    "sg:province":"Greater London",
    "sg:tags":[
        "product",
        "allied"
    ],
    "wof:name":"Chemical & Industrial Supplies Ltd.",
    "wof:placetype":"venue"
},
  "geometry": {"coordinates":[-0.3378799856,51.5927238464],"type":"Point"}
}