{
  "type": "Feature",
  "properties": {
    "addr:full":"Cow Watering Lane, Writtle Chelmsford Essex CM1 3SB",
    "addr:postcode":"cm1 3sb",
    "addr:street":"Cow Watering Lane",
    "iso:country":"GB",
    "sg:address":"Cow Watering Lane, Writtle",
    "sg:city":"Chelmsford",
    "sg:classifiers":[
        {
            "category":"Home & Garden",
            "subcategory":"Furniture",
            "type":"Retail Goods"
        }
    ],
    "sg:phone":"+44 1245 422552",
    "sg:postcode":"CM1 3SB",
    "sg:province":"Essex",
    "wof:name":"Pinewood Furnishings",
    "wof:placetype":"venue"
},
  "geometry": {"coordinates":[0.4205150008,51.7397232056],"type":"Point"}
}