{
  "type": "Feature",
  "properties": {
    "addr:full":"3 Dereham Way North Shields Tyne and Wear NE29 8BU",
    "addr:housenumber":"3",
    "addr:postcode":"ne29 8bu",
    "addr:street":"Dereham Way",
    "iso:country":"GB",
    "sg:address":"3 Dereham Way",
    "sg:city":"North Shields",
    "sg:classifiers":[
        {
            "category":"Retail",
            "subcategory":"Storage",
            "type":"Services"
        }
    ],
    "sg:phone":"+44 191 258 5462",
    "sg:postcode":"NE29 8BU",
    "sg:province":"Tyne and Wear",
    "sg:tags":[
        "household",
        "removal"
    ],
    "wof:name":"Charles Wake Removals Ltd.",
    "wof:placetype":"venue"
},
  "geometry": {"coordinates":[-1.489079,55.02124],"type":"Point"}
}