{
  "type": "Feature",
  "properties": {
    "addr:full":"Unit 8 Crendon Site, A W Nielsen Rd Goole East Riding of Yorkshire DN14 6UE",
    "addr:housenumber":"unit 8 crendon site",
    "addr:postcode":"dn14 6ue",
    "addr:street":"W Nielsen Rd",
    "iso:country":"GB",
    "sg:address":"Unit 8 Crendon Site, A W Nielsen Rd",
    "sg:city":"Goole",
    "sg:classifiers":[
        {
            "category":"Manufacturing",
            "subcategory":"Wood Products",
            "type":"Manufacturing & Wholesale Goods"
        }
    ],
    "sg:postcode":"DN14 6UE",
    "sg:province":"East Riding of Yorkshire",
    "sg:tags":[
        "packaging",
        "crate",
        "pallets"
    ],
    "wof:name":"Sleightholme,R C & R A,",
    "wof:placetype":"venue"
},
  "geometry": {"coordinates":[-0.8914840221,53.7043190002],"type":"Point"}
}