{
  "type": "Feature",
  "properties": {
    "iso:country":"GB",
    "sg:address":"116 Raddlebarn Road",
    "sg:city":"Birmingham",
    "sg:classifiers":[
        {
            "category":"Autos & Motor Vehicles",
            "subcategory":"Automobile Sales",
            "type":"Retail Goods"
        }
    ],
    "sg:phone":"+44 121 472 7139",
    "sg:postcode":"B29 6HQ",
    "sg:province":"West Midlands",
    "sg:tags":[
        "car"
    ],
    "wof:name":"Smallbone & Son Service Station Ltd.",
    "wof:placetype":"venue"
},
  "geometry": {"coordinates":[-1.9277260303,52.4334106445],"type":"Point"}
}