{
  "type": "Feature",
  "properties": {
    "addr:full":"Unit 7, Shepherds Business Park Norwich Norfolk NR9 5SG",
    "addr:housenumber":"unit 7",
    "addr:postcode":"nr9 5sg",
    "addr:street":"Shepherds Business Park Norwich Norfolk",
    "iso:country":"GB",
    "sg:address":"Unit 7, Shepherds Business Park",
    "sg:city":"Norwich",
    "sg:classifiers":[
        {
            "category":"Building & Trades",
            "subcategory":"Construction",
            "type":"Services"
        }
    ],
    "sg:phone":"+44 1603 871186",
    "sg:postcode":"NR9 5SG",
    "sg:province":"Norfolk",
    "sg:tags":[
        "demolition",
        "contractor"
    ],
    "wof:name":"Shepherds Demolition Ltd.",
    "wof:placetype":"venue"
},
  "geometry": {"coordinates":[1.12565,52.718262],"type":"Point"}
}