{
  "type": "Feature",
  "properties": {
    "addr:full":"Cody Road London Greater London E16 4SR",
    "addr:postcode":"e16 4sr",
    "addr:street":"Cody Road",
    "iso:country":"GB",
    "sg:address":"Cody Road",
    "sg:city":"London",
    "sg:classifiers":[
        {
            "category":"Cafe",
            "type":"Food & Drink"
        }
    ],
    "sg:phone":"+44 20 7476 9375",
    "sg:postcode":"E16 4SR",
    "sg:province":"Greater London",
    "sg:tags":[
        "tea",
        "snack",
        "bar",
        "room"
    ],
    "wof:name":"Nibbles Sandwich Bar",
    "wof:placetype":"venue"
},
  "geometry": {"coordinates":[0.00336,51.520824],"type":"Point"}
}