{
  "type": "Feature",
  "properties": {
    "iso:country":"GB",
    "sg:address":"189 Hamilton Rd",
    "sg:city":"Felixstowe",
    "sg:classifiers":[
        {
            "category":"Food & Beverages",
            "subcategory":"Supermarket",
            "type":"Retail Goods"
        }
    ],
    "sg:phone":"+44 1394 272331",
    "sg:postcode":"IP11 7DT",
    "sg:province":"Suffolk",
    "wof:name":"Solar Discounts",
    "wof:placetype":"venue"
},
  "geometry": {"coordinates":[1.352682,51.966896],"type":"Point"}
}