{
  "type": "Feature",
  "properties": {
    "addr:full":"1 Clifton Road Runcorn Cheshire WA7 4ST",
    "addr:housenumber":"1",
    "addr:postcode":"wa7 4st",
    "addr:street":"Clifton Road",
    "iso:country":"GB",
    "sg:address":"1 Clifton Road",
    "sg:city":"Runcorn",
    "sg:classifiers":[
        {
            "category":"Social Services",
            "subcategory":"Retirement Home",
            "type":"Services"
        }
    ],
    "sg:phone":"+44 1928 572231",
    "sg:postcode":"WA7 4ST",
    "sg:province":"Cheshire",
    "sg:tags":[
        "rest"
    ],
    "wof:name":"Hillcrest Residential Home",
    "wof:placetype":"venue"
},
  "geometry": {"coordinates":[-2.731388092,53.3281822205],"type":"Point"}
}