{
  "type": "Feature",
  "properties": {
    "iso:country":"GB",
    "sg:address":"313a Roundhay Road",
    "sg:city":"Leeds",
    "sg:classifiers":[
        {
            "category":"Health Services",
            "subcategory":"Dentist",
            "type":"Services"
        }
    ],
    "sg:phone":"+44 113 249 0795",
    "sg:postcode":"LS8 4HT",
    "sg:province":"West Yorkshire",
    "wof:name":"John Johnson Dental Practice",
    "wof:placetype":"venue"
},
  "geometry": {"coordinates":[-1.515209,53.818626],"type":"Point"}
}