{
  "type": "Feature",
  "properties": {
    "addr:full":"25 Rails La Hayling Island Hampshire PO11 9LG",
    "addr:housenumber":"25",
    "addr:postcode":"po11 9lg",
    "addr:street":"Rails La Hayling",
    "iso:country":"GB",
    "sg:address":"25 Rails La",
    "sg:city":"Hayling Island",
    "sg:classifiers":[
        {
            "category":"Food & Beverages",
            "subcategory":"Fruits & Vegetables",
            "type":"Retail Goods"
        }
    ],
    "sg:phone":"+44 23 9246 4257",
    "sg:postcode":"PO11 9LG",
    "sg:province":"Hampshire",
    "sg:tags":[
        "greengrocer"
    ],
    "wof:name":"Mary's Foodstore",
    "wof:placetype":"venue"
},
  "geometry": {"coordinates":[-0.965337,50.782585],"type":"Point"}
}