{
  "type": "Feature",
  "properties": {
    "addr:full":"Optical Trade Building, 100 High St West Bromwich West Midlands B70 6NZ",
    "addr:housenumber":"100",
    "addr:postcode":"b70 6nz",
    "addr:street":"High St",
    "iso:country":"GB",
    "sg:address":"Optical Trade Building, 100 High St",
    "sg:city":"West Bromwich",
    "sg:classifiers":[
        {
            "category":"Health Services",
            "subcategory":"Optometrist",
            "type":"Services"
        }
    ],
    "sg:phone":"+44 121 500 5502",
    "sg:postcode":"B70 6NZ",
    "sg:province":"West Midlands",
    "sg:tags":[
        "optician"
    ],
    "wof:name":"Disposable Contact Lens Clinic",
    "wof:placetype":"venue"
},
  "geometry": {"coordinates":[-1.990224,52.518623],"type":"Point"}
}