{
  "type": "Feature",
  "properties": {
    "iso:country":"GB",
    "sg:address":"145 Shoreditch High St",
    "sg:city":"Whitechapel",
    "sg:classifiers":[
        {
            "category":"Shopping",
            "subcategory":"Shoes",
            "type":"Retail Goods"
        }
    ],
    "sg:phone":"+44 20 7613 0902",
    "sg:postcode":"E1 6JE",
    "sg:province":"Greater London",
    "sg:tags":[
        "footwear"
    ],
    "wof:name":"Green Apple Italian Fashion Shoes",
    "wof:placetype":"venue"
},
  "geometry": {"coordinates":[-0.078519,51.521488],"type":"Point"}
}