{
  "type": "Feature",
  "properties": {
    "addr:full":"344 Hook Road Chessington Surrey KT9 1NU",
    "addr:housenumber":"344",
    "addr:postcode":"kt9 1nu",
    "addr:street":"Hook Road",
    "iso:country":"GB",
    "sg:address":"344 Hook Road",
    "sg:city":"Chessington",
    "sg:classifiers":[
        {
            "category":"Food & Beverages",
            "subcategory":"Meat & Fish",
            "type":"Retail Goods"
        }
    ],
    "sg:phone":"+44 20 8397 1976",
    "sg:postcode":"KT9 1NU",
    "sg:province":"Surrey",
    "sg:tags":[
        "chip"
    ],
    "wof:name":"Mr. Chips",
    "wof:placetype":"venue"
},
  "geometry": {"coordinates":[-0.30721,51.366924],"type":"Point"}
}