{
  "type": "Feature",
  "properties": {
    "iso:country":"GB",
    "sg:address":"Project Building, Wall Farm",
    "sg:city":"Ipswich",
    "sg:classifiers":[
        {
            "category":"Professional",
            "subcategory":"Management & Consulting",
            "type":"Services"
        }
    ],
    "sg:postcode":"IP9 2RQ",
    "sg:province":"Suffolk",
    "sg:tags":[
        "conservation"
    ],
    "wof:name":"Suffolk Coast & Heaths Project",
    "wof:placetype":"venue"
},
  "geometry": {"coordinates":[1.16739,51.97501],"type":"Point"}
}