{
  "type": "Feature",
  "properties": {
    "iso:country":"GB",
    "sg:address":"7 Washington Lane",
    "sg:city":"Edinburgh",
    "sg:classifiers":[
        {
            "category":"Organizations",
            "subcategory":"Non-profit Organization",
            "type":"Services"
        }
    ],
    "sg:phone":"+44 131 313 3828",
    "sg:postcode":"EH11 2HA",
    "sg:province":"City of Edinburgh",
    "sg:tags":[
        "organisation",
        "voluntary",
        "charity"
    ],
    "wof:name":"Edinburgh Medical Missionary Society",
    "wof:placetype":"venue"
},
  "geometry": {"coordinates":[-3.2223279476,55.9427223206],"type":"Point"}
}