{
  "type": "Feature",
  "properties": {
    "addr:full":"1 Sidney Avenue, Palmers Green Palmers Green Greater London N13 4XA",
    "addr:housenumber":"1",
    "addr:postcode":"n13 4xa",
    "addr:street":"Sidney Avenue",
    "iso:country":"GB",
    "sg:address":"1 Sidney Avenue, Palmers Green",
    "sg:city":"Palmers Green",
    "sg:classifiers":[
        {
            "category":"Autos & Motor Vehicles",
            "subcategory":"Automobile Sales",
            "type":"Retail Goods"
        }
    ],
    "sg:phone":"+44 20 8888 0404",
    "sg:postcode":"N13 4XA",
    "sg:province":"Greater London",
    "sg:tags":[
        "commercial"
    ],
    "wof:name":"Car Zone",
    "wof:placetype":"venue"
},
  "geometry": {"coordinates":[-0.109727,51.611752],"type":"Point"}
}