{
  "type": "Feature",
  "properties": {
    "iso:country":"GB",
    "sg:address":"Unit J7, Springhead Rd, Northfleet",
    "sg:city":"Gravesend",
    "sg:classifiers":[
        {
            "category":"Professional",
            "subcategory":"Art Services",
            "type":"Services"
        }
    ],
    "sg:phone":"+44 1474 354834",
    "sg:postcode":"DA11 8HL",
    "sg:province":"Kent",
    "sg:tags":[
        "graphic",
        "designer"
    ],
    "wof:name":"Vision Design Studio",
    "wof:placetype":"venue"
},
  "geometry": {"coordinates":[0.3330470026,51.4328727722],"type":"Point"}
}