{
  "type": "Feature",
  "properties": {
    "addr:full":"18 Badgers Walk Henley-on-thames Berkshire RG9 3JQ",
    "addr:housenumber":"18",
    "addr:postcode":"rg9 3jq",
    "addr:street":"Badgers Walk",
    "iso:country":"GB",
    "sg:address":"18 Badgers Walk",
    "sg:city":"Henley-on-thames",
    "sg:classifiers":[
        {
            "category":"Building & Trades",
            "subcategory":"Construction",
            "type":"Services"
        }
    ],
    "sg:postcode":"RG9 3JQ",
    "sg:province":"Berkshire",
    "sg:tags":[
        "roofing"
    ],
    "wof:name":"Flat Roof",
    "wof:placetype":"venue"
},
  "geometry": {"coordinates":[-0.8849650025,51.5089035034],"type":"Point"}
}