{
  "type": "Feature",
  "properties": {
    "addr:full":"113 Campbell Street, Riccarton Kilmarnock East Ayrshire KA1 4HR",
    "addr:housenumber":"113",
    "addr:postcode":"ka1 4hr",
    "addr:street":"Campbell Street",
    "iso:country":"GB",
    "sg:address":"113 Campbell Street, Riccarton",
    "sg:city":"Kilmarnock",
    "sg:classifiers":[
        {
            "category":"Autos & Motor Vehicles",
            "subcategory":"Automobile Sales",
            "type":"Retail Goods"
        }
    ],
    "sg:phone":"+44 1563 572525",
    "sg:postcode":"KA1 4HR",
    "sg:province":"East Ayrshire",
    "sg:tags":[
        "car"
    ],
    "wof:name":"George Bicket & Co. Ltd.",
    "wof:placetype":"venue"
},
  "geometry": {"coordinates":[-4.4994192123,55.5930213928],"type":"Point"}
}