{
  "type": "Feature",
  "properties": {
    "iso:country":"GB",
    "sg:address":"Unit 8 Wyndham Road, Hawksworth Trading Estate",
    "sg:city":"Swindon",
    "sg:classifiers":[
        {
            "category":"Manufacturing",
            "subcategory":"Petroleum Products",
            "type":"Manufacturing & Wholesale Goods"
        }
    ],
    "sg:phone":"+44 1793 877900",
    "sg:postcode":"SN2 1EJ",
    "sg:province":"Wiltshire",
    "sg:tags":[
        "double",
        "glazing"
    ],
    "wof:name":"Regal Windows (Southern) Ltd.",
    "wof:placetype":"venue"
},
  "geometry": {"coordinates":[-1.7991119623,51.5682296753],"type":"Point"}
}