{
  "type": "Feature",
  "properties": {
    "addr:full":"13 Honiton Way, Penketh Warrington Cheshire WA5 2EY",
    "addr:housenumber":"13",
    "addr:postcode":"wa5 2ey",
    "addr:street":"Honiton Way",
    "iso:country":"GB",
    "sg:address":"13 Honiton Way, Penketh",
    "sg:city":"Warrington",
    "sg:classifiers":[
        {
            "category":"Shopping",
            "subcategory":"Party Supplies",
            "type":"Retail Goods"
        }
    ],
    "sg:phone":"+44 1925 723693",
    "sg:postcode":"WA5 2EY",
    "sg:province":"Cheshire",
    "sg:tags":[
        "inflatables",
        "bouncy",
        "castle"
    ],
    "wof:name":"Party Time Bouncy Castles",
    "wof:placetype":"venue"
},
  "geometry": {"coordinates":[-2.655219,53.386627],"type":"Point"}
}