{
  "type": "Feature",
  "properties": {
    "addr:full":"Raffety House, 2-4 Sutton Court Road Sutton Surrey SM1 4TN",
    "addr:housenumber":"2-4",
    "addr:postcode":"sm1 4tn",
    "addr:street":"Sutton Court Road",
    "iso:country":"GB",
    "sg:address":"Raffety House, 2-4 Sutton Court Road",
    "sg:city":"Sutton",
    "sg:classifiers":[
        {
            "category":"Professional",
            "subcategory":"Business Services",
            "type":"Services"
        }
    ],
    "sg:postcode":"SM1 4TN",
    "sg:province":"Surrey",
    "sg:tags":[
        "holding"
    ],
    "wof:name":"Targetcase Ltd",
    "wof:placetype":"venue"
},
  "geometry": {"coordinates":[-0.18799,51.360744],"type":"Point"}
}