{
  "type": "Feature",
  "properties": {
    "addr:full":"Westloch Farm, Coldingham Eyemouth Scottish Borders TD14 5QE",
    "addr:postcode":"td14 5qe",
    "iso:country":"GB",
    "sg:address":"Westloch Farm, Coldingham",
    "sg:city":"Eyemouth",
    "sg:classifiers":[
        {
            "category":"Farming",
            "subcategory":"Livestock Farm",
            "type":"Manufacturing & Wholesale Goods"
        }
    ],
    "sg:phone":"+44 1890 771406",
    "sg:postcode":"TD14 5QE",
    "sg:province":"Scottish Borders",
    "sg:tags":[
        "others"
    ],
    "wof:name":"I W Scott",
    "wof:placetype":"venue"
},
  "geometry": {"coordinates":[-2.0951159,55.8731422424],"type":"Point"}
}