{
  "type": "Feature",
  "properties": {
    "iso:country":"GB",
    "sg:address":"2 Katifer Lane",
    "sg:city":"Malmesbury",
    "sg:classifiers":[
        {
            "category":"Utilities",
            "subcategory":"Natural Gas",
            "type":"Services"
        }
    ],
    "sg:phone":"+44 1666 824448",
    "sg:postcode":"SN16 0AU",
    "sg:province":"Wiltshire",
    "sg:tags":[
        "blacksmith"
    ],
    "wof:name":"Street Farm Forge",
    "wof:placetype":"venue"
},
  "geometry": {"coordinates":[-2.101668,51.585583],"type":"Point"}
}