{
  "type": "Feature",
  "properties": {
    "addr:full":"29 Bridge Street Banbury Oxfordshire OX16 5PN",
    "addr:housenumber":"29",
    "addr:postcode":"ox16 5pn",
    "addr:street":"Bridge Street",
    "iso:country":"GB",
    "sg:address":"29 Bridge Street",
    "sg:city":"Banbury",
    "sg:classifiers":[
        {
            "category":"Fast Food",
            "type":"Food & Drink"
        }
    ],
    "sg:phone":"+44 1295 277977",
    "sg:postcode":"OX16 5PN",
    "sg:province":"Oxfordshire",
    "sg:tags":[
        "away",
        "take"
    ],
    "wof:name":"Sophies Sandwich Bar",
    "wof:placetype":"venue"
},
  "geometry": {"coordinates":[-1.332695961,52.0619163513],"type":"Point"}
}