{
  "type": "Feature",
  "properties": {
    "iso:country":"GB",
    "sg:address":"3 Havelin Barns, Stourpaine",
    "sg:city":"Blandford Forum",
    "sg:classifiers":[
        {
            "category":"Building & Trades",
            "subcategory":"Construction",
            "type":"Services"
        }
    ],
    "sg:postcode":"DT11 8TQ",
    "sg:province":"Dorset",
    "sg:tags":[
        "builder"
    ],
    "wof:name":"B Clement-Doble",
    "wof:placetype":"venue"
},
  "geometry": {"coordinates":[-2.1194889545,50.8693885803],"type":"Point"}
}