{
  "type": "Feature",
  "properties": {
    "iso:country":"GB",
    "sg:address":"Unit 4 Orchard Industrial Estate, Kiln Lane",
    "sg:city":"Swindon",
    "sg:classifiers":[
        {
            "category":"Professional",
            "subcategory":"Engineering",
            "type":"Services"
        }
    ],
    "sg:postcode":"SN2 2NP",
    "sg:province":"Wiltshire",
    "sg:tags":[
        "precision",
        "engineer"
    ],
    "wof:name":"Specialist Jig Co.",
    "wof:placetype":"venue"
},
  "geometry": {"coordinates":[-1.807904,51.577736],"type":"Point"}
}