{
  "type": "Feature",
  "properties": {
    "addr:full":"199 Somervell Road Harrow Greater London HA2 8UA",
    "addr:housenumber":"199",
    "addr:postcode":"ha2 8ua",
    "addr:street":"Somervell Road",
    "iso:country":"GB",
    "sg:address":"199 Somervell Road",
    "sg:city":"Harrow",
    "sg:classifiers":[
        {
            "category":"Professional",
            "subcategory":"Engineering",
            "type":"Services"
        }
    ],
    "sg:phone":"+44 20 8422 2299",
    "sg:postcode":"HA2 8UA",
    "sg:province":"Greater London",
    "sg:tags":[
        "contractor",
        "electrical",
        "engineer"
    ],
    "wof:name":"Safelectrics",
    "wof:placetype":"venue"
},
  "geometry": {"coordinates":[-0.372446,51.556255],"type":"Point"}
}