{
  "type": "Feature",
  "properties": {
    "iso:country":"GB",
    "sg:address":"2 Diamond Close, Biddulph",
    "sg:city":"Stoke-on-trent",
    "sg:classifiers":[
        {
            "category":"Professional",
            "subcategory":"Engineering",
            "type":"Services"
        }
    ],
    "sg:phone":"+44 1782 518917",
    "sg:postcode":"ST8 6JP",
    "sg:province":"Staffordshire",
    "sg:tags":[
        "contractor",
        "electrical",
        "engineer"
    ],
    "wof:name":"Charles Mann",
    "wof:placetype":"venue"
},
  "geometry": {"coordinates":[-2.1794850826,53.1151199341],"type":"Point"}
}