{
  "type": "Feature",
  "properties": {
    "addr:full":"6c Raymond Street, Old Forge House Thetford Norfolk IP24 2EA",
    "addr:housenumber":"6c",
    "addr:postcode":"ip24 2ea",
    "addr:street":"Raymond Street",
    "iso:country":"GB",
    "sg:address":"6c Raymond Street, Old Forge House",
    "sg:city":"Thetford",
    "sg:classifiers":[
        {
            "category":"Building & Trades",
            "subcategory":"Construction",
            "type":"Services"
        }
    ],
    "sg:phone":"+44 1842 753114",
    "sg:postcode":"IP24 2EA",
    "sg:province":"Norfolk",
    "sg:tags":[
        "builder"
    ],
    "wof:name":"Goddards of Thetford (1954) Ltd.",
    "wof:placetype":"venue"
},
  "geometry": {"coordinates":[0.7500399947,52.4125747681],"type":"Point"}
}