{
  "type": "Feature",
  "properties": {
    "addr:full":"176-178 Breck Road, Everton Liverpool Merseyside L5 6PX",
    "addr:housenumber":"176-178",
    "addr:postcode":"l5 6px",
    "addr:street":"Breck Road",
    "iso:country":"GB",
    "sg:address":"176-178 Breck Road, Everton",
    "sg:city":"Liverpool",
    "sg:classifiers":[
        {
            "category":"Community Center",
            "subcategory":"Social",
            "type":"Public Place"
        }
    ],
    "sg:phone":"+44 151 260 4060",
    "sg:postcode":"L5 6PX",
    "sg:province":"Merseyside",
    "sg:tags":[
        "frozen",
        "food",
        "freezer",
        "centre"
    ],
    "wof:name":"Iceland Foods Plc",
    "wof:placetype":"venue"
},
  "geometry": {"coordinates":[-2.9596140385,53.4225502014],"type":"Point"}
}