{
  "type": "Feature",
  "properties": {
    "iso:country":"GB",
    "sg:address":"21 Princess Street, Outwood",
    "sg:city":"Wakefield",
    "sg:classifiers":[
        {
            "category":"Home & Garden",
            "subcategory":"Building Materials",
            "type":"Retail Goods"
        }
    ],
    "sg:phone":"+44 1924 211530",
    "sg:postcode":"WF1 2PJ",
    "sg:province":"West Yorkshire",
    "sg:tags":[
        "plaster",
        "ware"
    ],
    "wof:name":"Dec-Ornate",
    "wof:placetype":"venue"
},
  "geometry": {"coordinates":[-1.5049409866,53.7087211609],"type":"Point"}
}