{
  "type": "Feature",
  "properties": {
    "addr:full":"Crostwick Lane Norwich Norfolk NR10 3NQ",
    "addr:postcode":"nr10 3nq",
    "addr:street":"Crostwick Lane",
    "iso:country":"GB",
    "sg:address":"Crostwick Lane",
    "sg:city":"Norwich",
    "sg:classifiers":[
        {
            "category":"Organizations",
            "subcategory":"Membership Organization",
            "type":"Services"
        }
    ],
    "sg:phone":"+44 1603 890864",
    "sg:postcode":"NR10 3NQ",
    "sg:province":"Norfolk",
    "sg:tags":[
        "club"
    ],
    "wof:name":"Spixworth Social Club",
    "wof:placetype":"venue"
},
  "geometry": {"coordinates":[1.331078,52.688],"type":"Point"}
}