{
  "type": "Feature",
  "properties": {
    "iso:country":"GB",
    "sg:address":"Victoria Mill, Trafalgar Street",
    "sg:city":"Burnley",
    "sg:classifiers":[
        {
            "category":"Shopping",
            "subcategory":"Luggage & Leather Goods",
            "type":"Retail Goods"
        }
    ],
    "sg:phone":"+44 1282 425667",
    "sg:postcode":"BB11 1RQ",
    "sg:province":"Lancashire",
    "sg:tags":[
        "shop",
        "leathergoods"
    ],
    "wof:name":"Suedewear Co.",
    "wof:placetype":"venue"
},
  "geometry": {"coordinates":[-2.2438089848,53.7880096436],"type":"Point"}
}