{
  "type": "Feature",
  "properties": {
    "iso:country":"GB",
    "sg:address":"Assay House",
    "sg:city":"London",
    "sg:classifiers":[
        {
            "category":"Shopping",
            "subcategory":"Jewelry",
            "type":"Retail Goods"
        }
    ],
    "sg:phone":"+44 20 7831 2366",
    "sg:postcode":"EC1N 8SU",
    "sg:province":"Greater London",
    "sg:tags":[
        "gold",
        "silversmith"
    ],
    "wof:name":"Hatton Metals Ltd.",
    "wof:placetype":"venue"
},
  "geometry": {"coordinates":[-0.087574,51.508404],"type":"Point"}
}