{
  "type": "Feature",
  "properties": {
    "addr:full":"Bellingham Grn London Greater London SE6 3HD",
    "addr:postcode":"se6 3hd",
    "addr:street":"Bellingham Grn",
    "iso:country":"GB",
    "sg:address":"Bellingham Grn",
    "sg:city":"London",
    "sg:classifiers":[
        {
            "category":"Organizations",
            "subcategory":"Membership Organization",
            "type":"Services"
        }
    ],
    "sg:phone":"+44 20 8698 4891",
    "sg:postcode":"SE6 3HD",
    "sg:province":"Greater London",
    "sg:tags":[
        "club"
    ],
    "wof:name":"Bellingham (North) Community Association",
    "wof:placetype":"venue"
},
  "geometry": {"coordinates":[-0.023653,51.431278],"type":"Point"}
}