{
  "type": "Feature",
  "properties": {
    "iso:country":"GB",
    "sg:address":"15 Jermyn Street",
    "sg:city":"London",
    "sg:classifiers":[
        {
            "category":"Manufacturing",
            "subcategory":"Wood Products",
            "type":"Manufacturing & Wholesale Goods"
        }
    ],
    "sg:phone":"+44 20 7734 7340",
    "sg:postcode":"SW1Y 6LT",
    "sg:province":"Greater London",
    "wof:name":"Dunkelman & Son Ltd.",
    "wof:placetype":"venue"
},
  "geometry": {"coordinates":[-0.134519,51.509243],"type":"Point"}
}