{
  "type": "Feature",
  "properties": {
    "addr:full":"613 Pollokshaws Rd Glasgow Glasgow City G41 2QG",
    "addr:housenumber":"613",
    "addr:postcode":"g41 2qg",
    "addr:street":"Pollokshaws Rd",
    "iso:country":"GB",
    "sg:address":"613 Pollokshaws Rd",
    "sg:city":"Glasgow",
    "sg:classifiers":[
        {
            "category":"Communications",
            "subcategory":"Film & Video Production",
            "type":"Services"
        }
    ],
    "sg:phone":"+44 141 423 5634",
    "sg:postcode":"G41 2QG",
    "sg:province":"Glasgow City",
    "sg:tags":[
        "tv"
    ],
    "wof:name":"Video Exchange",
    "wof:placetype":"venue"
},
  "geometry": {"coordinates":[-4.268778801,55.8373069763],"type":"Point"}
}