{
  "type": "Feature",
  "properties": {
    "iso:country":"GB",
    "sg:address":"105 Shawsdale Road",
    "sg:city":"Birmingham",
    "sg:classifiers":[
        {
            "category":"Professional",
            "subcategory":"Business Services",
            "type":"Services"
        }
    ],
    "sg:phone":"+44 121 749 6684",
    "sg:postcode":"B36 8NG",
    "sg:province":"West Midlands",
    "sg:tags":[
        "bookmaker"
    ],
    "wof:name":"5 Star Bookmakers",
    "wof:placetype":"venue"
},
  "geometry": {"coordinates":[-1.8008650541,52.5019874573],"type":"Point"}
}