{
  "type": "Feature",
  "properties": {
    "addr:full":"2a Seely Road, Tooting London Greater London SW17 9QR",
    "addr:housenumber":"2a",
    "addr:postcode":"sw17 9qr",
    "addr:street":"Seely Road",
    "iso:country":"GB",
    "sg:address":"2a Seely Road, Tooting",
    "sg:city":"London",
    "sg:classifiers":[
        {
            "category":"Retail",
            "subcategory":"Repair Shop",
            "type":"Services"
        }
    ],
    "sg:phone":"+44 20 8672 2030",
    "sg:postcode":"SW17 9QR",
    "sg:province":"Greater London",
    "sg:tags":[
        "upholsterer"
    ],
    "wof:name":"Jones Upholstery Services",
    "wof:placetype":"venue"
},
  "geometry": {"coordinates":[-0.159794,51.422001],"type":"Point"}
}