{
  "type": "Feature",
  "properties": {
    "addr:full":"7 Bryn Siriol, Benllech Tyn-y-gongl Isle of Anglesey LL74 8TF",
    "addr:housenumber":"7",
    "addr:postcode":"ll74 8tf",
    "addr:street":"Bryn Siriol Benllech Tyn-Y-Gongl",
    "iso:country":"GB",
    "sg:address":"7 Bryn Siriol, Benllech",
    "sg:city":"Tyn-y-gongl",
    "sg:classifiers":[
        {
            "category":"Shopping",
            "subcategory":"Shoes",
            "type":"Retail Goods"
        }
    ],
    "sg:postcode":"LL74 8TF",
    "sg:province":"Isle of Anglesey",
    "sg:tags":[
        "shop"
    ],
    "wof:name":"Shoetique",
    "wof:placetype":"venue"
},
  "geometry": {"coordinates":[-4.2334518433,53.3216133118],"type":"Point"}
}