{
  "type": "Feature",
  "properties": {
    "addr:full":"21 Bolton Street Brixham Devon TQ5 9BZ",
    "addr:housenumber":"21",
    "addr:postcode":"tq5 9bz",
    "addr:street":"Bolton Street",
    "iso:country":"GB",
    "sg:address":"21 Bolton Street",
    "sg:city":"Brixham",
    "sg:classifiers":[
        {
            "category":"Personal",
            "subcategory":"Beauty Salon",
            "type":"Services"
        }
    ],
    "sg:phone":"+44 1803 851808",
    "sg:postcode":"TQ5 9BZ",
    "sg:province":"Devon",
    "sg:tags":[
        "lady",
        "hairdresser"
    ],
    "wof:name":"Highlights",
    "wof:placetype":"venue"
},
  "geometry": {"coordinates":[-3.515923,50.393238],"type":"Point"}
}