{
  "type": "Feature",
  "properties": {
    "addr:full":"9 Chadleigh Lane, Godmanchester Huntingdon Cambridgeshire PE29 2AL",
    "addr:housenumber":"9",
    "addr:postcode":"pe29 2al",
    "addr:street":"Chadleigh Lane",
    "iso:country":"GB",
    "sg:address":"9 Chadleigh Lane, Godmanchester",
    "sg:city":"Huntingdon",
    "sg:classifiers":[
        {
            "category":"Shopping",
            "subcategory":"Musical Instruments",
            "type":"Retail Goods"
        }
    ],
    "sg:postcode":"PE29 2AL",
    "sg:province":"Cambridgeshire",
    "wof:name":"P Storey Piano Tuning",
    "wof:placetype":"venue"
},
  "geometry": {"coordinates":[-0.1699540019,52.3188247681],"type":"Point"}
}