{
  "type": "Feature",
  "properties": {
    "addr:full":"Harlington Rd Bedford Bedfordshire MK45 4SJ",
    "addr:postcode":"mk45 4sj",
    "addr:street":"Harlington Rd",
    "iso:country":"GB",
    "sg:address":"Harlington Rd",
    "sg:city":"Bedford",
    "sg:classifiers":[
        {
            "category":"Home & Garden",
            "subcategory":"Garden Supply",
            "type":"Retail Goods"
        }
    ],
    "sg:phone":"+44 1525 872385",
    "sg:postcode":"MK45 4SJ",
    "sg:province":"Bedfordshire",
    "sg:tags":[
        "nursery",
        "centre"
    ],
    "wof:name":"Mill End Nursery",
    "wof:placetype":"venue"
},
  "geometry": {"coordinates":[-0.455764,51.964695],"type":"Point"}
}