{
  "type": "Feature",
  "properties": {
    "addr:full":"Slade House, Kirtlington Kidlington Buckinghamshire OX5 3JA",
    "addr:postcode":"ox5 3ja",
    "addr:street":"Kirtlington",
    "iso:country":"GB",
    "sg:address":"Slade House, Kirtlington",
    "sg:city":"Kidlington",
    "sg:classifiers":[
        {
            "category":"Professional",
            "subcategory":"Management & Consulting",
            "type":"Services"
        }
    ],
    "sg:phone":"+44 1869 350272",
    "sg:postcode":"OX5 3JA",
    "sg:province":"Buckinghamshire",
    "sg:tags":[
        "consultant",
        "business"
    ],
    "wof:name":"John Hine FCA",
    "wof:placetype":"venue"
},
  "geometry": {"coordinates":[-1.2763789892,51.87292099],"type":"Point"}
}