{
  "type": "Feature",
  "properties": {
    "iso:country":"GB",
    "sg:address":"8 Canberra House, Corby Gate Business Park, Priors Haw Road",
    "sg:city":"Corby",
    "sg:classifiers":[
        {
            "category":"Professional",
            "type":"Services"
        }
    ],
    "sg:phone":"+44 1536 443444",
    "sg:postcode":"NN17 5JG",
    "sg:province":"Northamptonshire",
    "sg:tags":[
        "exhibition"
    ],
    "wof:name":"The Melrose Partnership Ltd.",
    "wof:placetype":"venue"
},
  "geometry": {"coordinates":[-0.7026000023,52.4859771729],"type":"Point"}
}