{
  "type": "Feature",
  "properties": {
    "addr:full":"12a North End, Moat View, Bassingbourn Royston Bedfordshire SG8 5NX",
    "addr:housenumber":"12a",
    "addr:postcode":"sg8 5nx",
    "addr:street":"North;Moat",
    "iso:country":"GB",
    "sg:address":"12a North End, Moat View, Bassingbourn",
    "sg:city":"Royston",
    "sg:classifiers":[
        {
            "category":"Building & Trades",
            "subcategory":"Cleaning & Sanitation",
            "type":"Services"
        }
    ],
    "sg:postcode":"SG8 5NX",
    "sg:province":"Bedfordshire",
    "sg:tags":[
        "commercial"
    ],
    "wof:name":"E & P Cleaning Contractors",
    "wof:placetype":"venue"
},
  "geometry": {"coordinates":[-0.0601929985,52.0793533325],"type":"Point"}
}