{
  "type": "Feature",
  "properties": {
    "iso:country":"GB",
    "sg:address":"Mount Pleasant Black Moor Rd, Oxenhope",
    "sg:city":"Keighley",
    "sg:classifiers":[
        {
            "category":"Shopping",
            "subcategory":"Crafts & Fabrics",
            "type":"Retail Goods"
        }
    ],
    "sg:phone":"+44 1535 642721",
    "sg:postcode":"BD22 9SS",
    "sg:province":"North Yorkshire",
    "sg:tags":[
        "merchant",
        "wool"
    ],
    "wof:name":"R.A Bateson",
    "wof:placetype":"venue"
},
  "geometry": {"coordinates":[-1.951091,53.81324],"type":"Point"}
}