{
  "type": "Feature",
  "properties": {
    "iso:country":"GB",
    "sg:address":"300 Woodhouse Lane",
    "sg:city":"Wigan",
    "sg:classifiers":[
        {
            "category":"Food & Beverages",
            "subcategory":"Meat & Fish",
            "type":"Retail Goods"
        }
    ],
    "sg:phone":"+44 1942 495722",
    "sg:postcode":"WN6 7TD",
    "sg:province":"Lancashire",
    "sg:tags":[
        "chip"
    ],
    "wof:name":"Stadium Chip Shop",
    "wof:placetype":"venue"
},
  "geometry": {"coordinates":[-2.659422,53.556129],"type":"Point"}
}