{
  "type": "Feature",
  "properties": {
    "addr:full":"302 Platt Lane Manchester Greater Manchester M14 7BZ",
    "addr:housenumber":"302",
    "addr:postcode":"m14 7bz",
    "addr:street":"Platt Lane",
    "iso:country":"GB",
    "sg:address":"302 Platt Lane",
    "sg:city":"Manchester",
    "sg:classifiers":[
        {
            "category":"Retail",
            "subcategory":"Auto Repair",
            "type":"Services"
        }
    ],
    "sg:phone":"+44 161 225 9965",
    "sg:postcode":"M14 7BZ",
    "sg:province":"Greater Manchester",
    "sg:tags":[
        "body",
        "car"
    ],
    "wof:name":"B & A Car Hire & Storage",
    "wof:placetype":"venue"
},
  "geometry": {"coordinates":[-2.237287,53.447247],"type":"Point"}
}