{
  "type": "Feature",
  "properties": {
    "addr:full":"23 Valley Park, Bamfurlong Lane Cheltenham Gloucestershire GL51 6SL",
    "addr:housenumber":"23",
    "addr:postcode":"gl51 6sl",
    "addr:street":"Valley Park Bamfurlong Lane",
    "iso:country":"GB",
    "sg:address":"23 Valley Park, Bamfurlong Lane",
    "sg:city":"Cheltenham",
    "sg:classifiers":[
        {
            "category":"Home & Garden",
            "subcategory":"Household Appliances",
            "type":"Retail Goods"
        }
    ],
    "sg:phone":"+44 1242 701182",
    "sg:postcode":"GL51 6SL",
    "sg:province":"Gloucestershire",
    "sg:tags":[
        "electrical"
    ],
    "wof:name":"B.J.M Refrigeration",
    "wof:placetype":"venue"
},
  "geometry": {"coordinates":[-2.14673,51.894268],"type":"Point"}
}