{
  "type": "Feature",
  "properties": {
    "addr:full":"30 Chapel Street Bridlington East Riding of Yorkshire YO15 2DW",
    "addr:housenumber":"30",
    "addr:postcode":"yo15 2dw",
    "addr:street":"Chapel Street",
    "iso:country":"GB",
    "sg:address":"30 Chapel Street",
    "sg:city":"Bridlington",
    "sg:classifiers":[
        {
            "category":"Shopping",
            "subcategory":"Pets & Pet Supplies",
            "type":"Retail Goods"
        }
    ],
    "sg:phone":"+44 1262 672206",
    "sg:postcode":"YO15 2DW",
    "sg:province":"East Riding of Yorkshire",
    "sg:tags":[
        "shop"
    ],
    "wof:name":"Simpsons Pet Stores",
    "wof:placetype":"venue"
},
  "geometry": {"coordinates":[-0.190103,54.082298],"type":"Point"}
}