{
  "type": "Feature",
  "properties": {
    "addr:full":"Audley Street Works, Audley Street, Mossley Ashton-under-lyne Greater Manchester OL5 9HW",
    "addr:postcode":"ol5 9hw",
    "addr:street":"Audley Street;Audley Street",
    "iso:country":"GB",
    "sg:address":"Audley Street Works, Audley Street, Mossley",
    "sg:city":"Ashton-under-lyne",
    "sg:classifiers":[
        {
            "category":"Utilities",
            "subcategory":"Recycling",
            "type":"Services"
        },
        {
            "category":"Wholesale",
            "subcategory":"Electrical",
            "type":"Manufacturing & Wholesale Goods"
        }
    ],
    "sg:phone":"+44 1457 835391",
    "sg:postcode":"OL5 9HW",
    "sg:province":"Greater Manchester",
    "sg:tags":[
        "equipment",
        "blowing",
        "fan",
        "refrigeration"
    ],
    "wof:name":"Victoria Fan & Engineering Supplies Ltd",
    "wof:placetype":"venue"
},
  "geometry": {"coordinates":[-2.0368089676,53.5136489868],"type":"Point"}
}