{
  "type": "Feature",
  "properties": {
    "iso:country":"GB",
    "sg:address":"55 Fore Street, Topsham",
    "sg:city":"Exeter",
    "sg:classifiers":[
        {
            "category":"Personal",
            "subcategory":"Beauty Salon",
            "type":"Services"
        },
        {
            "category":"Personal",
            "subcategory":"Barber",
            "type":"Services"
        }
    ],
    "sg:phone":"+44 1392 877559",
    "sg:postcode":"EX3 0HW",
    "sg:province":"Devon",
    "sg:tags":[
        "unisex",
        "hairdresser"
    ],
    "wof:name":"Ruffles Hair Design",
    "wof:placetype":"venue"
},
  "geometry": {"coordinates":[-3.465481,50.682434],"type":"Point"}
}