{
  "type": "Feature",
  "properties": {
    "addr:full":"24 Eastwood Drive, Littleover Derby Derbyshire DE23 6BN",
    "addr:housenumber":"24",
    "addr:postcode":"de23 6bn",
    "addr:street":"Eastwood Drive",
    "iso:country":"GB",
    "sg:address":"24 Eastwood Drive, Littleover",
    "sg:city":"Derby",
    "sg:classifiers":[
        {
            "category":"Real Estate",
            "subcategory":"Real Estate Services",
            "type":"Services"
        },
        {
            "category":"Retail",
            "subcategory":"Repair Shop",
            "type":"Services"
        }
    ],
    "sg:phone":"+44 1332 344555",
    "sg:postcode":"DE23 6BN",
    "sg:province":"Derbyshire",
    "sg:tags":[
        "property",
        "maintenance"
    ],
    "wof:name":"R W Woolley",
    "wof:placetype":"venue"
},
  "geometry": {"coordinates":[-1.505294,52.909363],"type":"Point"}
}