{
  "type": "Feature",
  "properties": {
    "addr:full":"44a York Road Salisbury Wiltshire SP2 7AP",
    "addr:housenumber":"44a",
    "addr:postcode":"sp2 7ap",
    "addr:street":"York Road",
    "iso:country":"GB",
    "sg:address":"44a York Road",
    "sg:city":"Salisbury",
    "sg:classifiers":[
        {
            "category":"Military Area",
            "subcategory":"Air Force Base",
            "type":"Public Place"
        }
    ],
    "sg:phone":"+44 1722 505055",
    "sg:postcode":"SP2 7AP",
    "sg:province":"Wiltshire",
    "sg:tags":[
        "taxi",
        "hire",
        "private"
    ],
    "wof:name":"Allied Taxis",
    "wof:placetype":"venue"
},
  "geometry": {"coordinates":[-1.8033020496,51.0732536316],"type":"Point"}
}