{
  "type": "Feature",
  "properties": {
    "addr:full":"200 High St Hornchurch Essex RM12 6QP",
    "addr:housenumber":"200",
    "addr:postcode":"rm12 6qp",
    "addr:street":"High St",
    "iso:country":"GB",
    "sg:address":"200 High St",
    "sg:city":"Hornchurch",
    "sg:classifiers":[
        {
            "category":"Professional",
            "subcategory":"Printing & Photocopies",
            "type":"Services"
        }
    ],
    "sg:phone":"+44 1708 458585",
    "sg:postcode":"RM12 6QP",
    "sg:province":"Essex",
    "sg:tags":[
        "duplicating",
        "copying"
    ],
    "wof:name":"Essex Office Machines Ltd",
    "wof:placetype":"venue"
},
  "geometry": {"coordinates":[0.2229419947,51.5612983704],"type":"Point"}
}