{
  "type": "Feature",
  "properties": {
    "addr:full":"75 Harewood Road, Whoberley Coventry West Midlands CV5 8BS",
    "addr:housenumber":"75",
    "addr:postcode":"cv5 8bs",
    "addr:street":"Harewood Road Whoberley",
    "iso:country":"GB",
    "sg:address":"75 Harewood Road, Whoberley",
    "sg:city":"Coventry",
    "sg:classifiers":[
        {
            "category":"Professional",
            "type":"Services"
        }
    ],
    "sg:phone":"+44 24 7667 8799",
    "sg:postcode":"CV5 8BS",
    "sg:province":"West Midlands",
    "sg:tags":[
        "caterer"
    ],
    "wof:name":"Wilda's Finest Feaster",
    "wof:placetype":"venue"
},
  "geometry": {"coordinates":[-1.5579420328,52.4089584351],"type":"Point"}
}