{
  "type": "Feature",
  "properties": {
    "iso:country":"GB",
    "sg:address":"Epsom Avenue, Stanley Green Trading Estate, Handforth",
    "sg:city":"Wilmslow",
    "sg:classifiers":[
        {
            "category":"Manufacturing",
            "subcategory":"Chemicals & Compounds",
            "type":"Manufacturing & Wholesale Goods"
        },
        {
            "category":"Manufacturing",
            "subcategory":"Wood Products",
            "type":"Manufacturing & Wholesale Goods"
        }
    ],
    "sg:phone":"+44 161 482 6000",
    "sg:postcode":"SK9 3RP",
    "sg:province":"Cheshire",
    "sg:tags":[
        "packaging",
        "crate",
        "pallets"
    ],
    "wof:name":"R W Greeff",
    "wof:placetype":"venue"
},
  "geometry": {"coordinates":[-2.206123,53.352371],"type":"Point"}
}