{
  "type": "Feature",
  "properties": {
    "iso:country":"GB",
    "sg:address":"Dental Surgery, 131 High St",
    "sg:city":"Weston Super Mare",
    "sg:classifiers":[
        {
            "category":"Health Services",
            "subcategory":"Dentist",
            "type":"Services"
        }
    ],
    "sg:phone":"+44 1934 517711",
    "sg:postcode":"BS22 6HQ",
    "sg:province":"Somerset",
    "wof:name":"D Thomas",
    "wof:placetype":"venue"
},
  "geometry": {"coordinates":[-2.92875,51.36002],"type":"Point"}
}