{
  "type": "Feature",
  "properties": {
    "iso:country":"GB",
    "sg:address":"William Hopwood Street",
    "sg:city":"Blackburn",
    "sg:classifiers":[
        {
            "category":"Health Services",
            "subcategory":"Doctor",
            "type":"Services"
        }
    ],
    "sg:phone":"+44 1254 52522",
    "sg:postcode":"BB1 1LX",
    "sg:province":"Lancashire",
    "sg:tags":[
        "practitioners"
    ],
    "wof:name":"N Nagpal",
    "wof:placetype":"venue"
},
  "geometry": {"coordinates":[-2.466304,53.746586],"type":"Point"}
}