{
  "type": "Feature",
  "properties": {
    "iso:country":"GB",
    "sg:address":"Deanery Road",
    "sg:city":"Bristol",
    "sg:classifiers":[
        {
            "category":"Autos & Motor Vehicles",
            "subcategory":"Fuel & Gas Station",
            "type":"Retail Goods"
        }
    ],
    "sg:phone":"+44 117 947 8886",
    "sg:postcode":"BS15 9JB",
    "sg:province":"City of Bristol",
    "sg:tags":[
        "petrol",
        "filling"
    ],
    "wof:name":"Warmley Service Station",
    "wof:placetype":"venue"
},
  "geometry": {"coordinates":[-2.4797840118,51.4600639343],"type":"Point"}
}