{
  "type": "Feature",
  "properties": {
    "addr:full":"21 Pinner Rd Harrow Greater London HA1 4BB",
    "addr:housenumber":"21",
    "addr:postcode":"ha1 4bb",
    "addr:street":"Pinner Rd",
    "iso:country":"GB",
    "sg:address":"21 Pinner Rd",
    "sg:city":"Harrow",
    "sg:classifiers":[
        {
            "category":"Government",
            "subcategory":"Office",
            "type":"Public Place"
        }
    ],
    "sg:phone":"+44 20 8863 3377",
    "sg:postcode":"HA1 4BB",
    "sg:province":"Greater London",
    "sg:tags":[
        "project",
        "gov",
        "community"
    ],
    "wof:name":"Brent & Harrow Health Promotion Unit",
    "wof:placetype":"venue"
},
  "geometry": {"coordinates":[-0.343362987,51.5809326172],"type":"Point"}
}