{
  "type": "Feature",
  "properties": {
    "addr:full":"Unit B, Camberley Court, Camberley Road Nottingham Nottinghamshire NG6 8GE",
    "addr:postcode":"ng6 8ge",
    "addr:street":"Camberley Court Camberley Road",
    "iso:country":"GB",
    "sg:address":"Unit B, Camberley Court, Camberley Road",
    "sg:city":"Nottingham",
    "sg:classifiers":[
        {
            "category":"Manufacturing",
            "subcategory":"Tools & Machinery",
            "type":"Manufacturing & Wholesale Goods"
        }
    ],
    "sg:phone":"+44 115 979 5000",
    "sg:postcode":"NG6 8GE",
    "sg:province":"Nottinghamshire",
    "sg:tags":[
        "design",
        "maker"
    ],
    "wof:name":"Emtec Toolmakers Ltd.",
    "wof:placetype":"venue"
},
  "geometry": {"coordinates":[-1.207954,53.007206],"type":"Point"}
}