{
  "type": "Feature",
  "properties": {
    "iso:country":"GB",
    "sg:address":"Albion Mill, Albion Trad Est, Cobden St",
    "sg:city":"Salford",
    "sg:classifiers":[
        {
            "category":"Sports & Exercise",
            "subcategory":"Athletic Track",
            "type":"Entertainment"
        }
    ],
    "sg:postcode":"M6 6LY",
    "sg:province":"Greater Manchester",
    "sg:tags":[
        "bags",
        "accessory",
        "belt"
    ],
    "wof:name":"Alphamiss Ltd",
    "wof:placetype":"venue"
},
  "geometry": {"coordinates":[-2.283879,53.493649],"type":"Point"}
}