{
  "type": "Feature",
  "properties": {
    "addr:full":"58 High Street, Staple Hill Bristol City of Bristol BS16 5HN",
    "addr:housenumber":"58",
    "addr:postcode":"bs16 5hn",
    "addr:street":"High Street",
    "iso:country":"GB",
    "sg:address":"58 High Street, Staple Hill",
    "sg:city":"Bristol",
    "sg:classifiers":[
        {
            "category":"Shopping",
            "subcategory":"Used Merchandise",
            "type":"Retail Goods"
        }
    ],
    "sg:postcode":"BS16 5HN",
    "sg:province":"City of Bristol",
    "sg:tags":[
        "shop",
        "second-hand"
    ],
    "wof:name":"Murgatroyd's",
    "wof:placetype":"venue"
},
  "geometry": {"coordinates":[-2.515334,51.481468],"type":"Point"}
}