{
  "type": "Feature",
  "properties": {
    "iso:country":"GB",
    "sg:address":"College Chambers, 3 & 4 Hampshire Terrace",
    "sg:city":"Portsmouth",
    "sg:classifiers":[
        {
            "category":"Utilities",
            "type":"Services"
        }
    ],
    "sg:phone":"+44 23 9282 1111",
    "sg:postcode":"PO1 2QF",
    "sg:province":"Hampshire",
    "sg:tags":[
        "internet"
    ],
    "wof:name":"UK Auctions.Com",
    "wof:placetype":"venue"
},
  "geometry": {"coordinates":[-1.0955599546,50.7940063477],"type":"Point"}
}