{
  "type": "Feature",
  "properties": {
    "addr:full":"147c Albert Road Southsea Hampshire PO4 0JW",
    "addr:housenumber":"147c",
    "addr:postcode":"po4 0jw",
    "addr:street":"Albert Road",
    "iso:country":"GB",
    "sg:address":"147c Albert Road",
    "sg:city":"Southsea",
    "sg:classifiers":[
        {
            "category":"Personal",
            "subcategory":"Barber",
            "type":"Services"
        }
    ],
    "sg:phone":"+44 23 9273 0674",
    "sg:postcode":"PO4 0JW",
    "sg:province":"Hampshire",
    "sg:tags":[
        "men's",
        "hairdresser"
    ],
    "wof:name":"Melmont Gents Hairdressing",
    "wof:placetype":"venue"
},
  "geometry": {"coordinates":[-1.0761090517,50.7867584229],"type":"Point"}
}