{
  "type": "Feature",
  "properties": {
    "addr:full":"210 Maidstone Road Rochester Kent ME1 3LP",
    "addr:housenumber":"210",
    "addr:postcode":"me1 3lp",
    "addr:street":"Maidstone Road Rochester",
    "iso:country":"GB",
    "sg:address":"210 Maidstone Road",
    "sg:city":"Rochester",
    "sg:classifiers":[
        {
            "category":"Shopping",
            "subcategory":"Department Store",
            "type":"Retail Goods"
        }
    ],
    "sg:phone":"+44 1634 402258",
    "sg:postcode":"ME1 3LP",
    "sg:province":"Kent",
    "wof:name":"Setterfields",
    "wof:placetype":"venue"
},
  "geometry": {"coordinates":[0.499324,51.368084],"type":"Point"}
}