{
  "type": "Feature",
  "properties": {
    "iso:country":"GB",
    "sg:address":"81 Homestead Way, New Addington",
    "sg:city":"Croydon",
    "sg:classifiers":[
        {
            "category":"Manufacturing",
            "subcategory":"Building Materials",
            "type":"Manufacturing & Wholesale Goods"
        }
    ],
    "sg:postcode":"CR0 0AW",
    "sg:province":"Surrey",
    "sg:tags":[
        "tarmac",
        "asphalt"
    ],
    "wof:name":"M & C Surfacing",
    "wof:placetype":"venue"
},
  "geometry": {"coordinates":[-0.007899,51.334858],"type":"Point"}
}