{
  "type": "Feature",
  "properties": {
    "addr:full":"13 Purbeck Business Centre, Victoria Avenue Industrial Swanage Dorset BH19 1AU",
    "addr:housenumber":"13;business centre",
    "addr:postcode":"bh19 1au",
    "addr:street":"Purbeck;Victoria Avenue Industrial",
    "iso:country":"GB",
    "sg:address":"13 Purbeck Business Centre, Victoria Avenue Industrial",
    "sg:city":"Swanage",
    "sg:classifiers":[
        {
            "category":"Wholesale",
            "subcategory":"Machinery & Supplies",
            "type":"Manufacturing & Wholesale Goods"
        },
        {
            "category":"Train Station",
            "subcategory":"Rail",
            "type":"Transportation"
        }
    ],
    "sg:phone":"+44 1929 426606",
    "sg:postcode":"BH19 1AU",
    "sg:province":"Dorset",
    "sg:tags":[
        "equipment",
        "railway"
    ],
    "wof:name":"Southern Locomotives Ltd.",
    "wof:placetype":"venue"
},
  "geometry": {"coordinates":[-1.973228,50.61285],"type":"Point"}
}