{
  "type": "Feature",
  "properties": {
    "iso:country":"GB",
    "sg:address":"Unit 1 Arch Lane, Ashton In Makerfield",
    "sg:city":"Wigan",
    "sg:classifiers":[
        {
            "category":"Professional",
            "subcategory":"Engineering",
            "type":"Services"
        }
    ],
    "sg:postcode":"WN4 0XL",
    "sg:province":"Lancashire",
    "wof:name":"International Components",
    "wof:placetype":"venue"
},
  "geometry": {"coordinates":[-2.6883189678,53.487159729],"type":"Point"}
}