{
  "type": "Feature",
  "properties": {
    "iso:country":"GB",
    "sg:address":"Roman Ho, 2 Rougier St",
    "sg:city":"York",
    "sg:classifiers":[
        {
            "category":"Insurance",
            "subcategory":"Life Insurance",
            "type":"Services"
        }
    ],
    "sg:phone":"+44 1904 634567",
    "sg:postcode":"YO1 1HR",
    "sg:province":"North Yorkshire",
    "sg:tags":[
        "assurance"
    ],
    "wof:name":"Abbey National Life",
    "wof:placetype":"venue"
},
  "geometry": {"coordinates":[-1.0813499689,53.958770752],"type":"Point"}
}