{
  "type": "Feature",
  "properties": {
    "iso:country":"GB",
    "sg:address":"Unit E10 Redford Industrial Estate, Ford",
    "sg:city":"Arundel",
    "sg:classifiers":[
        {
            "category":"Home & Garden",
            "subcategory":"Garden Supply",
            "type":"Retail Goods"
        }
    ],
    "sg:postcode":"BN18 0HY",
    "sg:province":"West Sussex",
    "sg:tags":[
        "equipment",
        "playground"
    ],
    "wof:name":"J Carroll & Associates",
    "wof:placetype":"venue"
},
  "geometry": {"coordinates":[-0.579919,50.813492],"type":"Point"}
}