{
  "type": "Feature",
  "properties": {
    "iso:country":"GB",
    "sg:address":"Unit 9 117-119 Seven Sisters Rd",
    "sg:city":"Holloway",
    "sg:classifiers":[
        {
            "category":"Travel",
            "subcategory":"Travel Agent",
            "type":"Entertainment"
        }
    ],
    "sg:phone":"+44 20 7561 1867",
    "sg:postcode":"N7 7QG",
    "sg:province":"Greater London",
    "wof:name":"Air Zone Travel Ltd",
    "wof:placetype":"venue"
},
  "geometry": {"coordinates":[-0.113576,51.561119],"type":"Point"}
}