{
  "type": "Feature",
  "properties": {
    "iso:country":"GB",
    "sg:address":"Unit 4, 11 Fieldings Road, Cheshunt",
    "sg:city":"Waltham Cross",
    "sg:classifiers":[
        {
            "category":"Manufacturing",
            "subcategory":"Signs",
            "type":"Manufacturing & Wholesale Goods"
        }
    ],
    "sg:phone":"+44 1992 636348",
    "sg:postcode":"EN8 9TL",
    "sg:province":"Essex",
    "sg:tags":[
        "nameplate"
    ],
    "wof:name":"Rye Signs Ltd.",
    "wof:placetype":"venue"
},
  "geometry": {"coordinates":[-0.024209,51.70813],"type":"Point"}
}