{
  "type": "Feature",
  "properties": {
    "addr:full":"1561 London Rd, Norbury Streatham Greater London SW16 4AD",
    "addr:housenumber":"1561",
    "addr:postcode":"sw16 4ad",
    "addr:street":"London Rd",
    "iso:country":"GB",
    "sg:address":"1561 London Rd, Norbury",
    "sg:city":"Streatham",
    "sg:classifiers":[
        {
            "category":"Building & Trades",
            "subcategory":"Cleaning & Sanitation",
            "type":"Services"
        }
    ],
    "sg:phone":"+44 20 8765 1061",
    "sg:postcode":"SW16 4AD",
    "sg:province":"Greater London",
    "sg:tags":[
        "commercial"
    ],
    "wof:name":"Ashdel Cleaning Services",
    "wof:placetype":"venue"
},
  "geometry": {"coordinates":[-0.124181,51.412533],"type":"Point"}
}