{
  "type": "Feature",
  "properties": {
    "iso:country":"GB",
    "sg:address":"80 South Road, Oundle",
    "sg:city":"Peterborough",
    "sg:classifiers":[
        {
            "category":"Real Estate",
            "subcategory":"Architect",
            "type":"Services"
        }
    ],
    "sg:phone":"+44 1832 272112",
    "sg:postcode":"PE8 4BP",
    "sg:province":"Cambridgeshire",
    "wof:name":"Paul Bancroft Architect",
    "wof:placetype":"venue"
},
  "geometry": {"coordinates":[-0.4697560072,52.4792900085],"type":"Point"}
}