{
  "type": "Feature",
  "properties": {
    "iso:country":"GB",
    "sg:address":"17 Chaplins Close, Coates",
    "sg:city":"Peterborough",
    "sg:classifiers":[
        {
            "category":"Manufacturing",
            "subcategory":"Petroleum Products",
            "type":"Manufacturing & Wholesale Goods"
        },
        {
            "category":"Building & Trades",
            "subcategory":"Construction",
            "type":"Services"
        }
    ],
    "sg:phone":"+44 1733 840665",
    "sg:postcode":"PE7 2BZ",
    "sg:province":"Cambridgeshire",
    "sg:tags":[
        "double",
        "glazier",
        "glazing"
    ],
    "wof:name":"M & B Windows Doors & Conservatories",
    "wof:placetype":"venue"
},
  "geometry": {"coordinates":[-0.0693800002,52.5620574951],"type":"Point"}
}