{
  "type": "Feature",
  "properties": {
    "addr:full":"Cemetery Gates, Townhead Rothesay Argyll and Bute PA20 9AR",
    "addr:postcode":"pa20 9ar",
    "addr:street":"Townhead",
    "iso:country":"GB",
    "sg:address":"Cemetery Gates, Townhead",
    "sg:city":"Rothesay",
    "sg:classifiers":[
        {
            "category":"Building & Trades",
            "subcategory":"Construction",
            "type":"Services"
        }
    ],
    "sg:phone":"+44 1700 503006",
    "sg:postcode":"PA20 9AR",
    "sg:province":"Argyll and Bute",
    "sg:tags":[
        "monumental",
        "mason"
    ],
    "wof:name":"W Kirkhope & Sons",
    "wof:placetype":"venue"
},
  "geometry": {"coordinates":[-5.0548348427,55.8346748352],"type":"Point"}
}