{
  "type": "Feature",
  "properties": {
    "addr:full":"4 Radcliffe Sq London Greater London SW15 6BL",
    "addr:housenumber":"4",
    "addr:postcode":"sw15 6bl",
    "addr:street":"Radcliffe Sq",
    "iso:country":"GB",
    "sg:address":"4 Radcliffe Sq",
    "sg:city":"London",
    "sg:classifiers":[
        {
            "category":"Education",
            "subcategory":"Music School",
            "type":"Public Place"
        }
    ],
    "sg:postcode":"SW15 6BL",
    "sg:province":"Greater London",
    "wof:name":"Chiswick Records Ltd",
    "wof:placetype":"venue"
},
  "geometry": {"coordinates":[-0.240214,51.536266],"type":"Point"}
}