{
  "type": "Feature",
  "properties": {
    "iso:country":"GB",
    "sg:address":"Unit 7, Fenlake Road Industrial Estate, Fenlake Road",
    "sg:city":"Bedford",
    "sg:classifiers":[
        {
            "category":"Retail",
            "subcategory":"Auto Repair",
            "type":"Services"
        }
    ],
    "sg:phone":"+44 1234 218223",
    "sg:postcode":"MK42 0HB",
    "sg:province":"Bedfordshire",
    "sg:tags":[
        "body",
        "car"
    ],
    "wof:name":"Patterson Accident Repair Centre",
    "wof:placetype":"venue"
},
  "geometry": {"coordinates":[-0.455393,52.12962],"type":"Point"}
}