{
  "type": "Feature",
  "properties": {
    "addr:full":"17-19 Clayport Street Alnwick Northumberland NE66 1LA",
    "addr:housenumber":"17-19",
    "addr:postcode":"ne66 1la",
    "addr:street":"Clayport Street",
    "iso:country":"GB",
    "sg:address":"17-19 Clayport Street",
    "sg:city":"Alnwick",
    "sg:classifiers":[
        {
            "category":"Fast Food",
            "type":"Food & Drink"
        }
    ],
    "sg:phone":"+44 1665 510772",
    "sg:postcode":"NE66 1LA",
    "sg:province":"Northumberland",
    "sg:tags":[
        "away",
        "meal",
        "outlet",
        "take"
    ],
    "wof:name":"Alnwick Tandoori Takeaway",
    "wof:placetype":"venue"
},
  "geometry": {"coordinates":[-1.709226,55.412422],"type":"Point"}
}