{
  "type": "Feature",
  "properties": {
    "iso:country":"GB",
    "sg:address":"7 The Arcade, Hoe St",
    "sg:city":"London",
    "sg:classifiers":[
        {
            "category":"Shopping",
            "subcategory":"Department Store",
            "type":"Retail Goods"
        }
    ],
    "sg:postcode":"E17 4QG",
    "sg:province":"Greater London",
    "wof:name":"Banji,Cornelia,",
    "wof:placetype":"venue"
},
  "geometry": {"coordinates":[-0.0203300007,51.5850982666],"type":"Point"}
}