{
  "type": "Feature",
  "properties": {
    "iso:country":"GB",
    "sg:address":"26 Stileham Bank, Milborne St Andrew",
    "sg:city":"Blandford Forum",
    "sg:classifiers":[
        {
            "category":"Farming",
            "subcategory":"Farm",
            "type":"Manufacturing & Wholesale Goods"
        }
    ],
    "sg:phone":"+44 1258 837403",
    "sg:postcode":"DT11 0LE",
    "sg:province":"Dorset",
    "sg:tags":[
        "agricultural"
    ],
    "wof:name":"Countrywide Security Suppliers",
    "wof:placetype":"venue"
},
  "geometry": {"coordinates":[-2.281215,50.778561],"type":"Point"}
}