{
  "type": "Feature",
  "properties": {
    "iso:country":"GB",
    "sg:address":"3 Crispin Centre",
    "sg:city":"Street",
    "sg:classifiers":[
        {
            "category":"Shopping",
            "subcategory":"Gifts & Souvenirs",
            "type":"Retail Goods"
        }
    ],
    "sg:phone":"+44 1458 445971",
    "sg:postcode":"BA16 0HP",
    "sg:province":"Somerset",
    "sg:tags":[
        "shop"
    ],
    "wof:name":"Weeping Willow",
    "wof:placetype":"venue"
},
  "geometry": {"coordinates":[-2.740859,51.126251],"type":"Point"}
}