{
  "type": "Feature",
  "properties": {
    "iso:country":"GB",
    "sg:address":"24 Marlborough Crescent",
    "sg:city":"Burton-on-trent",
    "sg:classifiers":[
        {
            "category":"Manufacturing",
            "subcategory":"Buildings",
            "type":"Manufacturing & Wholesale Goods"
        },
        {
            "category":"Parking",
            "subcategory":"Garage",
            "type":"Transportation"
        }
    ],
    "sg:phone":"+44 7713 878823",
    "sg:postcode":"DE15 9DF",
    "sg:province":"Derbyshire",
    "sg:tags":[
        "carport",
        "portable"
    ],
    "wof:name":"Midland Car Ports",
    "wof:placetype":"venue"
},
  "geometry": {"coordinates":[-1.6158280373,52.7930107117],"type":"Point"}
}