{
  "type": "Feature",
  "properties": {
    "addr:full":"58 Nuttall Street Accrington Lancashire BB5 2HN",
    "addr:housenumber":"58",
    "addr:postcode":"bb5 2hn",
    "addr:street":"Nuttall Street",
    "iso:country":"GB",
    "sg:address":"58 Nuttall Street",
    "sg:city":"Accrington",
    "sg:classifiers":[
        {
            "category":"Shopping",
            "subcategory":"News",
            "type":"Retail Goods"
        }
    ],
    "sg:phone":"+44 1254 232149",
    "sg:postcode":"BB5 2HN",
    "sg:province":"Lancashire",
    "sg:tags":[
        "newsagent"
    ],
    "wof:name":"A & W Green",
    "wof:placetype":"venue"
},
  "geometry": {"coordinates":[-2.36352,53.748489],"type":"Point"}
}