{
  "type": "Feature",
  "properties": {
    "iso:country":"GB",
    "sg:address":"39-41 New Bedford Road",
    "sg:city":"Luton",
    "sg:classifiers":[
        {
            "category":"Restaurant",
            "type":"Food & Drink"
        }
    ],
    "sg:phone":"+44 1582 457924",
    "sg:postcode":"LU1 1SE",
    "sg:province":"Bedfordshire",
    "sg:tags":[
        "greek"
    ],
    "wof:name":"To Pigathaki",
    "wof:placetype":"venue"
},
  "geometry": {"coordinates":[-0.4203369915,51.8831748962],"type":"Point"}
}