{
  "type": "Feature",
  "properties": {
    "addr:full":"Manor Primary School, Beechwood Dr Birkenhead Merseyside L43 7ZU",
    "addr:postcode":"l43 7zu",
    "addr:street":"Beechwood Dr",
    "iso:country":"GB",
    "sg:address":"Manor Primary School, Beechwood Dr",
    "sg:city":"Birkenhead",
    "sg:classifiers":[
        {
            "category":"Government",
            "subcategory":"Office",
            "type":"Public Place"
        }
    ],
    "sg:phone":"+44 151 677 3152",
    "sg:postcode":"L43 7ZU",
    "sg:province":"Merseyside",
    "sg:tags":[
        "local"
    ],
    "wof:name":"Metropolitan Borough of Wirral",
    "wof:placetype":"venue"
},
  "geometry": {"coordinates":[-3.0254900455,53.3925590515],"type":"Point"}
}