{
  "type": "Feature",
  "properties": {
    "addr:full":"Po Box 45 Hinckley Leicestershire LE10 1JY",
    "addr:housenumber":"po box 45",
    "addr:postcode":"le10 1jy",
    "iso:country":"GB",
    "sg:address":"Po Box 45",
    "sg:city":"Hinckley",
    "sg:classifiers":[
        {
            "category":"Organizations",
            "subcategory":"Non-profit Organization",
            "type":"Services"
        }
    ],
    "sg:postcode":"LE10 1JY",
    "sg:province":"Leicestershire",
    "sg:tags":[
        "organisation",
        "voluntary",
        "charity"
    ],
    "wof:name":"National Society for Research Into Allergy",
    "wof:placetype":"venue"
},
  "geometry": {"coordinates":[-1.370249033,52.5448608398],"type":"Point"}
}