{
  "type": "Feature",
  "properties": {
    "addr:full":"15 Church Way South Croydon Surrey CR2 0JT",
    "addr:housenumber":"15",
    "addr:postcode":"cr2 0jt",
    "addr:street":"Church Way",
    "iso:country":"GB",
    "sg:address":"15 Church Way",
    "sg:city":"South Croydon",
    "sg:classifiers":[
        {
            "category":"Farming",
            "subcategory":"Nursery",
            "type":"Manufacturing & Wholesale Goods"
        }
    ],
    "sg:phone":"+44 20 8651 0446",
    "sg:postcode":"CR2 0JT",
    "sg:province":"Surrey",
    "sg:tags":[
        "creche"
    ],
    "wof:name":"Beech House",
    "wof:placetype":"venue"
},
  "geometry": {"coordinates":[-0.0779350027,51.3427391052],"type":"Point"}
}