{
  "type": "Feature",
  "properties": {
    "iso:country":"GB",
    "sg:address":"24 Warwick Rd",
    "sg:city":"Redhill",
    "sg:classifiers":[
        {
            "category":"Professional",
            "subcategory":"Lawyer & Legal Services",
            "type":"Services"
        }
    ],
    "sg:phone":"+44 1737 772844",
    "sg:postcode":"RH1 1BU",
    "sg:province":"Surrey",
    "sg:tags":[
        "advice",
        "counselling"
    ],
    "wof:name":"Redhill Counselling Centre",
    "wof:placetype":"venue"
},
  "geometry": {"coordinates":[-0.1707289964,51.2419090271],"type":"Point"}
}