{
  "type": "Feature",
  "properties": {
    "addr:full":"Mold Road, Gwersylly Wrexham Wrexham LL11 4AH",
    "addr:postcode":"ll11 4ah",
    "addr:street":"Mold Road Gwersylly",
    "iso:country":"GB",
    "sg:address":"Mold Road, Gwersylly",
    "sg:city":"Wrexham",
    "sg:classifiers":[
        {
            "category":"Retail",
            "subcategory":"Auto Rental",
            "type":"Services"
        }
    ],
    "sg:phone":"+44 1978 759020",
    "sg:postcode":"LL11 4AH",
    "sg:province":"Wrexham",
    "sg:tags":[
        "truck",
        "hire",
        "van"
    ],
    "wof:name":"Parkwall Service Station Ltd.",
    "wof:placetype":"venue"
},
  "geometry": {"coordinates":[-3.0217590332,53.080696106],"type":"Point"}
}