{
  "type": "Feature",
  "properties": {
    "iso:country":"GB",
    "sg:address":"47-49 Sauchiehall St",
    "sg:city":"Glasgow",
    "sg:classifiers":[
        {
            "category":"Banks & Credit Unions",
            "subcategory":"Bank",
            "type":"Services"
        }
    ],
    "sg:phone":"+44 845 604 2310",
    "sg:postcode":"G2 3AT",
    "sg:province":"Glasgow City",
    "wof:name":"Halifax plc",
    "wof:placetype":"venue"
},
  "geometry": {"coordinates":[-4.258042,55.864914],"type":"Point"}
}