{
  "type": "Feature",
  "properties": {
    "iso:country":"GB",
    "sg:address":"Longford Road",
    "sg:city":"Holyhead",
    "sg:classifiers":[
        {
            "category":"Professional",
            "type":"Services"
        },
        {
            "category":"Real Estate",
            "subcategory":"Architect",
            "type":"Services"
        }
    ],
    "sg:phone":"+44 1407 762568",
    "sg:postcode":"LL65 1TR",
    "sg:province":"Isle of Anglesey",
    "sg:tags":[
        "marine"
    ],
    "wof:name":"Marine Advisory Service",
    "wof:placetype":"venue"
},
  "geometry": {"coordinates":[-4.635559,53.307701],"type":"Point"}
}