{
  "type": "Feature",
  "properties": {
    "addr:full":"24 Earl Street Maidstone Kent ME14 1PP",
    "addr:housenumber":"24",
    "addr:postcode":"me14 1pp",
    "addr:street":"Earl Street",
    "iso:country":"GB",
    "sg:address":"24 Earl Street",
    "sg:city":"Maidstone",
    "sg:classifiers":[
        {
            "category":"Bars & Pubs",
            "type":"Food & Drink"
        }
    ],
    "sg:phone":"+44 1622 758516",
    "sg:postcode":"ME14 1PP",
    "sg:province":"Kent",
    "sg:tags":[
        "pubs",
        "inn"
    ],
    "wof:name":"Hogs Head",
    "wof:placetype":"venue"
},
  "geometry": {"coordinates":[0.521781,51.274895],"type":"Point"}
}