{
  "type": "Feature",
  "properties": {
    "iso:country":"GB",
    "sg:address":"96 Peascod Street",
    "sg:city":"Windsor",
    "sg:classifiers":[
        {
            "category":"Food & Beverages",
            "subcategory":"Specialty",
            "type":"Retail Goods"
        }
    ],
    "sg:phone":"+44 1753 860618",
    "sg:postcode":"SL4 1DH",
    "sg:province":"Berkshire",
    "sg:tags":[
        "retailer",
        "product",
        "health"
    ],
    "wof:name":"HEALTH & DIET CENTRES LTD",
    "wof:placetype":"venue"
},
  "geometry": {"coordinates":[-0.611328,51.481148],"type":"Point"}
}