{
  "type": "Feature",
  "properties": {
    "iso:country":"GB",
    "sg:address":"177 Darkes Lane",
    "sg:city":"Potters Bar",
    "sg:classifiers":[
        {
            "category":"Health Services",
            "subcategory":"Optometrist",
            "type":"Services"
        }
    ],
    "sg:phone":"+44 1707 652322",
    "sg:postcode":"EN6 1BW",
    "sg:province":"Greater London",
    "sg:tags":[
        "optician"
    ],
    "wof:name":"Adler Cole & Dixon",
    "wof:placetype":"venue"
},
  "geometry": {"coordinates":[-0.1902450025,51.6989517212],"type":"Point"}
}