{
  "type": "Feature",
  "properties": {
    "iso:country":"GB",
    "sg:address":"53 Southend Road",
    "sg:city":"Grays",
    "sg:classifiers":[
        {
            "category":"Personal",
            "subcategory":"Beauty Salon",
            "type":"Services"
        }
    ],
    "sg:phone":"+44 1375 372170",
    "sg:postcode":"RM17 5NJ",
    "sg:province":"Essex",
    "sg:tags":[
        "unisex",
        "hairdresser"
    ],
    "wof:name":"Dezis Clipjoint",
    "wof:placetype":"venue"
},
  "geometry": {"coordinates":[0.336038,51.484417],"type":"Point"}
}