{
  "type": "Feature",
  "properties": {
    "addr:full":"109 Winchester Road Romsey Hampshire SO51 8JF",
    "addr:housenumber":"109",
    "addr:postcode":"so51 8jf",
    "addr:street":"Winchester Road",
    "iso:country":"GB",
    "sg:address":"109 Winchester Road",
    "sg:city":"Romsey",
    "sg:classifiers":[
        {
            "category":"Shopping",
            "subcategory":"Bicycles & Sporting Goods",
            "type":"Retail Goods"
        }
    ],
    "sg:phone":"+44 1794 513344",
    "sg:postcode":"SO51 8JF",
    "sg:province":"Hampshire",
    "sg:tags":[
        "cycle",
        "accessory"
    ],
    "wof:name":"Cycle World Wessex Ltd.",
    "wof:placetype":"venue"
},
  "geometry": {"coordinates":[-1.486619,50.990734],"type":"Point"}
}