{
  "type": "Feature",
  "properties": {
    "addr:full":"Anderton St Chorley Lancashire PR7 2AY",
    "addr:postcode":"pr7 2ay",
    "addr:street":"Anderton St",
    "iso:country":"GB",
    "sg:address":"Anderton St",
    "sg:city":"Chorley",
    "sg:classifiers":[
        {
            "category":"Home & Garden",
            "subcategory":"Home Furnishings",
            "type":"Retail Goods"
        }
    ],
    "sg:phone":"+44 1257 276318",
    "sg:postcode":"PR7 2AY",
    "sg:province":"Lancashire",
    "sg:tags":[
        "racking",
        "shelving",
        "diy"
    ],
    "wof:name":"Storage Equipment Services Ltd",
    "wof:placetype":"venue"
},
  "geometry": {"coordinates":[-2.6277439594,53.6514854431],"type":"Point"}
}