{
  "type": "Feature",
  "properties": {
    "addr:full":"1 Peartree Gdns, Collier Row Romford Essex RM7 8HT",
    "addr:housenumber":"1",
    "addr:postcode":"rm7 8ht",
    "addr:street":"Peartree Gdns;Row",
    "iso:country":"GB",
    "sg:address":"1 Peartree Gdns, Collier Row",
    "sg:city":"Romford",
    "sg:classifiers":[
        {
            "category":"Autos & Motor Vehicles",
            "subcategory":"Motorcycle Sales",
            "type":"Retail Goods"
        }
    ],
    "sg:postcode":"RM7 8HT",
    "sg:province":"Essex",
    "sg:tags":[
        "chauffeur",
        "driven",
        "car"
    ],
    "wof:name":"Select Chauffeur Services",
    "wof:placetype":"venue"
},
  "geometry": {"coordinates":[0.15999,51.592548],"type":"Point"}
}