{
  "type": "Feature",
  "properties": {
    "iso:country":"GB",
    "sg:address":"Fron Ucha, Glyndwr Road Gwernymynydd",
    "sg:city":"Mold",
    "sg:classifiers":[
        {
            "category":"Farming",
            "subcategory":"Livestock Farm",
            "type":"Manufacturing & Wholesale Goods"
        }
    ],
    "sg:postcode":"CH7 5LW",
    "sg:province":"Denbighshire",
    "sg:tags":[
        "others"
    ],
    "wof:name":"Jones J R & Partners",
    "wof:placetype":"venue"
},
  "geometry": {"coordinates":[-3.177687,53.152802],"type":"Point"}
}