{
  "type": "Feature",
  "properties": {
    "addr:full":"Little Cowarne Court, Little Cowarne Bromyard Herefordshire HR7 4RH",
    "addr:postcode":"hr7 4rh",
    "addr:street":"Little Cowarne Court",
    "iso:country":"GB",
    "sg:address":"Little Cowarne Court, Little Cowarne",
    "sg:city":"Bromyard",
    "sg:classifiers":[
        {
            "category":"Farming",
            "subcategory":"Farm",
            "type":"Manufacturing & Wholesale Goods"
        }
    ],
    "sg:phone":"+44 1885 400203",
    "sg:postcode":"HR7 4RH",
    "sg:province":"Herefordshire",
    "sg:tags":[
        "mixed",
        "crop"
    ],
    "wof:name":"C C Hopkinson Ltd",
    "wof:placetype":"venue"
},
  "geometry": {"coordinates":[-2.5103991032,52.1890983582],"type":"Point"}
}