{
  "type": "Feature",
  "properties": {
    "iso:country":"GB",
    "sg:address":"70 Barton Road",
    "sg:city":"Lancaster",
    "sg:classifiers":[
        {
            "category":"Building & Trades",
            "subcategory":"Construction",
            "type":"Services"
        }
    ],
    "sg:phone":"+44 1524 33365",
    "sg:postcode":"LA1 4EP",
    "sg:province":"Lancashire",
    "sg:tags":[
        "roofing"
    ],
    "wof:name":"Ian J Morrison",
    "wof:placetype":"venue"
},
  "geometry": {"coordinates":[-2.7918870449,54.0317611694],"type":"Point"}
}