{
  "type": "Feature",
  "properties": {
    "iso:country":"GB",
    "sg:address":"Rackvernal Road, Midsomer Norton",
    "sg:city":"Bath",
    "sg:classifiers":[
        {
            "category":"Community Center",
            "type":"Public Place"
        }
    ],
    "sg:phone":"+44 1761 415522",
    "sg:postcode":"BA3 2UG",
    "sg:province":"Somerset",
    "sg:tags":[
        "recreation",
        "leisure",
        "centre"
    ],
    "wof:name":"South Wansdyke Sports Centre",
    "wof:placetype":"venue"
},
  "geometry": {"coordinates":[-2.487124,51.28677],"type":"Point"}
}