{
  "type": "Feature",
  "properties": {
    "iso:country":"GB",
    "sg:address":"69-71 Back Commonside",
    "sg:city":"Lytham St Annes",
    "sg:classifiers":[
        {
            "category":"Autos & Motor Vehicles",
            "subcategory":"Automobile Sales",
            "type":"Retail Goods"
        },
        {
            "category":"Retail",
            "subcategory":"Auto Repair",
            "type":"Services"
        }
    ],
    "sg:phone":"+44 1253 732317",
    "sg:postcode":"FY8 4DJ",
    "sg:province":"Lancashire",
    "sg:tags":[
        "modification",
        "garage",
        "car"
    ],
    "wof:name":"TAYLOR AUTO'S",
    "wof:placetype":"venue"
},
  "geometry": {"coordinates":[-2.991574,53.749516],"type":"Point"}
}