{
  "type": "Feature",
  "properties": {
    "addr:full":"Link House, 35 Walmersley Road Bury Lancashire BL9 5AE",
    "addr:housenumber":"35",
    "addr:postcode":"bl9 5ae",
    "addr:street":"Walmersley Road",
    "iso:country":"GB",
    "sg:address":"Link House, 35 Walmersley Road",
    "sg:city":"Bury",
    "sg:classifiers":[
        {
            "category":"Professional",
            "subcategory":"Computer Services",
            "type":"Services"
        }
    ],
    "sg:phone":"+44 161 763 4185",
    "sg:postcode":"BL9 5AE",
    "sg:province":"Lancashire",
    "sg:tags":[
        "information"
    ],
    "wof:name":"Business Environment Association",
    "wof:placetype":"venue"
},
  "geometry": {"coordinates":[-2.289845,53.598385],"type":"Point"}
}