{
  "type": "Feature",
  "properties": {
    "addr:full":"P.o Box 3973, Chelmsford Chelmsford Essex CM2 0UW",
    "addr:housenumber":"3973",
    "addr:postcode":"cm2 0uw",
    "addr:street":"P.O Box",
    "iso:country":"GB",
    "sg:address":"P.o Box 3973, Chelmsford",
    "sg:city":"Chelmsford",
    "sg:classifiers":[
        {
            "category":"Wholesale",
            "subcategory":"Machinery & Supplies",
            "type":"Manufacturing & Wholesale Goods"
        }
    ],
    "sg:phone":"+44 1245 261070",
    "sg:postcode":"CM2 0UW",
    "sg:province":"Essex",
    "sg:tags":[
        "theatrical"
    ],
    "wof:name":"Under Wraps Dancers",
    "wof:placetype":"venue"
},
  "geometry": {"coordinates":[0.4778909981,51.731918335],"type":"Point"}
}