{
  "type": "Feature",
  "properties": {
    "iso:country":"GB",
    "sg:address":"37 Vermont Gro, Anchorsholme",
    "sg:city":"Thornton Cleveleys",
    "sg:classifiers":[
        {
            "category":"Retail",
            "subcategory":"Driving School",
            "type":"Services"
        }
    ],
    "sg:phone":"+44 1253 868275",
    "sg:postcode":"FY5 3RL",
    "sg:province":"Lancashire",
    "wof:name":"P J Wilson",
    "wof:placetype":"venue"
},
  "geometry": {"coordinates":[-3.0294370651,53.8672676086],"type":"Point"}
}