{
  "type": "Feature",
  "properties": {
    "addr:full":"Oxford Road, Berinsfield Wallingford Oxfordshire OX10 7LY",
    "addr:postcode":"ox10 7ly",
    "addr:street":"Oxford Road",
    "iso:country":"GB",
    "sg:address":"Oxford Road, Berinsfield",
    "sg:city":"Wallingford",
    "sg:classifiers":[
        {
            "category":"Wholesale",
            "subcategory":"Scrap",
            "type":"Manufacturing & Wholesale Goods"
        }
    ],
    "sg:phone":"+44 1865 340035",
    "sg:postcode":"OX10 7LY",
    "sg:province":"Oxfordshire",
    "sg:tags":[
        "breaker",
        "dismantlers"
    ],
    "wof:name":"Berinsfield Car Breakers",
    "wof:placetype":"venue"
},
  "geometry": {"coordinates":[-1.1676870584,51.6493415833],"type":"Point"}
}