{
  "type": "Feature",
  "properties": {
    "iso:country":"GB",
    "sg:address":"The Old Coalyard, Lower Station Road",
    "sg:city":"Lewes",
    "sg:classifiers":[
        {
            "category":"Building & Trades",
            "subcategory":"Construction",
            "type":"Services"
        }
    ],
    "sg:phone":"+44 1825 724290",
    "sg:postcode":"BN8 4HU",
    "sg:province":"East Sussex",
    "sg:tags":[
        "builder"
    ],
    "wof:name":"Dovetail Homes",
    "wof:placetype":"venue"
},
  "geometry": {"coordinates":[-0.0028,50.969131],"type":"Point"}
}