{
  "type": "Feature",
  "properties": {
    "iso:country":"GB",
    "sg:address":"83 Roundmoor Drive, Cheshunt",
    "sg:city":"Waltham Cross",
    "sg:classifiers":[
        {
            "category":"Food & Beverages",
            "subcategory":"Groceries & Convenience Stores",
            "type":"Retail Goods"
        }
    ],
    "sg:phone":"+44 1992 626259",
    "sg:postcode":"EN8 9HW",
    "sg:province":"Essex",
    "wof:name":"Roundmoor Stores",
    "wof:placetype":"venue"
},
  "geometry": {"coordinates":[-0.029912,51.706455],"type":"Point"}
}