{
  "type": "Feature",
  "properties": {
    "addr:full":"1 King Street, Cross Heath Newcastle Staffordshire ST5 9HQ",
    "addr:housenumber":"1",
    "addr:postcode":"st5 9hq",
    "addr:street":"King Street",
    "iso:country":"GB",
    "sg:address":"1 King Street, Cross Heath",
    "sg:city":"Newcastle",
    "sg:classifiers":[
        {
            "category":"Shopping",
            "subcategory":"Mobile Phones",
            "type":"Retail Goods"
        }
    ],
    "sg:postcode":"ST5 9HQ",
    "sg:province":"Staffordshire",
    "wof:name":"Network Orange Communications",
    "wof:placetype":"venue"
},
  "geometry": {"coordinates":[-2.2325320244,53.0231933594],"type":"Point"}
}