{
  "type": "Feature",
  "properties": {
    "addr:full":"Units 1 & 2 Brook Way, Kingston Rd Leatherhead Surrey KT22 7NA",
    "addr:housenumber":"units 1 & 2",
    "addr:postcode":"kt22 7na",
    "addr:street":"Brook Way;Rd",
    "iso:country":"GB",
    "sg:address":"Units 1 & 2 Brook Way, Kingston Rd",
    "sg:city":"Leatherhead",
    "sg:classifiers":[
        {
            "category":"Professional",
            "subcategory":"Testing Lab",
            "type":"Services"
        }
    ],
    "sg:phone":"+44 1372 377566",
    "sg:postcode":"KT22 7NA",
    "sg:province":"Surrey",
    "sg:tags":[
        "mot"
    ],
    "wof:name":"Leatherhead Motor Co",
    "wof:placetype":"venue"
},
  "geometry": {"coordinates":[-0.33539,51.311001],"type":"Point"}
}