{
  "type": "Feature",
  "properties": {
    "addr:full":"2 Parsons Mead Abingdon Oxfordshire OX14 1LS",
    "addr:housenumber":"2",
    "addr:postcode":"ox14 1ls",
    "addr:street":"Parsons Mead",
    "iso:country":"GB",
    "sg:address":"2 Parsons Mead",
    "sg:city":"Abingdon",
    "sg:classifiers":[
        {
            "category":"Military Area",
            "subcategory":"Air Force Base",
            "type":"Public Place"
        }
    ],
    "sg:phone":"+44 1235 555599",
    "sg:postcode":"OX14 1LS",
    "sg:province":"Oxfordshire",
    "sg:tags":[
        "taxi",
        "hire",
        "private"
    ],
    "wof:name":"Toots Taxis",
    "wof:placetype":"venue"
},
  "geometry": {"coordinates":[-1.2877800465,51.6844749451],"type":"Point"}
}