{
  "type": "Feature",
  "properties": {
    "iso:country":"GB",
    "sg:address":"21 Widey Lane",
    "sg:city":"Plymouth",
    "sg:classifiers":[
        {
            "category":"Health Services",
            "subcategory":"Nursing And Care Facility",
            "type":"Services"
        },
        {
            "category":"Social Services",
            "subcategory":"Retirement Home",
            "type":"Services"
        }
    ],
    "sg:postcode":"PL6 5JS",
    "sg:province":"Devon",
    "sg:tags":[
        "residential"
    ],
    "wof:name":"WIDEY GRANGE",
    "wof:placetype":"venue"
},
  "geometry": {"coordinates":[-4.126999,50.404884],"type":"Point"}
}