{
  "type": "Feature",
  "properties": {
    "iso:country":"GB",
    "sg:address":"Floor 3 38 Floral Street",
    "sg:city":"London",
    "sg:classifiers":[
        {
            "category":"Food & Beverages",
            "subcategory":"Liquor & Beverages",
            "type":"Retail Goods"
        }
    ],
    "sg:postcode":"WC2E 9DG",
    "sg:province":"Greater London",
    "sg:tags":[
        "beer",
        "spirit",
        "wines"
    ],
    "wof:name":"Premium Brand Corporation Ltd.",
    "wof:placetype":"venue"
},
  "geometry": {"coordinates":[-0.124326,51.512577],"type":"Point"}
}