{
  "type": "Feature",
  "properties": {
    "iso:country":"GB",
    "sg:address":"Anniesland Village Business Park",
    "sg:city":"Glasgow",
    "sg:classifiers":[
        {
            "category":"Retail",
            "subcategory":"Storage",
            "type":"Services"
        }
    ],
    "sg:phone":"+44 141 943 2211",
    "sg:postcode":"G61 2DG",
    "sg:province":"East Dunbartonshire",
    "sg:tags":[
        "household",
        "removal"
    ],
    "wof:name":"Bearsden & Milngavie Removal Co",
    "wof:placetype":"venue"
},
  "geometry": {"coordinates":[-4.32959,55.916351],"type":"Point"}
}