{
  "type": "Feature",
  "properties": {
    "addr:full":"76 Oban Grove, Fearnhead Warrington Cheshire WA2 0TG",
    "addr:housenumber":"76",
    "addr:postcode":"wa2 0tg",
    "addr:street":"Oban Grove Fearnhead",
    "iso:country":"GB",
    "sg:address":"76 Oban Grove, Fearnhead",
    "sg:city":"Warrington",
    "sg:classifiers":[
        {
            "category":"Professional",
            "subcategory":"Computer Services",
            "type":"Services"
        }
    ],
    "sg:postcode":"WA2 0TG",
    "sg:province":"Cheshire",
    "sg:tags":[
        "aided",
        "design"
    ],
    "wof:name":"Fabcad Ltd",
    "wof:placetype":"venue"
},
  "geometry": {"coordinates":[-2.552932024,53.4191627502],"type":"Point"}
}