{
  "type": "Feature",
  "properties": {
    "addr:full":"Grangefield Industrial Estate Pudsey West Yorkshire LS28 6JP",
    "addr:postcode":"ls28 6jp",
    "addr:street":"Estate Pudsey West",
    "iso:country":"GB",
    "sg:address":"Grangefield Industrial Estate",
    "sg:city":"Pudsey",
    "sg:classifiers":[
        {
            "category":"Train Station",
            "subcategory":"Light Rail",
            "type":"Transportation"
        }
    ],
    "sg:phone":"+44 113 236 2992",
    "sg:postcode":"LS28 6JP",
    "sg:province":"West Yorkshire",
    "sg:tags":[
        "alloy"
    ],
    "wof:name":"Rolled Alloys (Uk) Ltd.",
    "wof:placetype":"venue"
},
  "geometry": {"coordinates":[-1.655524,53.805183],"type":"Point"}
}