{
  "type": "Feature",
  "properties": {
    "addr:full":"11 Bridge Street Newhaven East Sussex BN9 9PH",
    "addr:housenumber":"11",
    "addr:postcode":"bn9 9ph",
    "addr:street":"Bridge Street",
    "iso:country":"GB",
    "sg:address":"11 Bridge Street",
    "sg:city":"Newhaven",
    "sg:classifiers":[
        {
            "category":"Professional",
            "type":"Services"
        }
    ],
    "sg:postcode":"BN9 9PH",
    "sg:province":"East Sussex",
    "sg:tags":[
        "repair",
        "tech",
        "maintenance"
    ],
    "wof:name":"Joystix",
    "wof:placetype":"venue"
},
  "geometry": {"coordinates":[0.051379,50.794472],"type":"Point"}
}