{
  "type": "Feature",
  "properties": {
    "iso:country":"GB",
    "sg:address":"9 Fairclough Road, Rainhill",
    "sg:city":"Prescot",
    "sg:classifiers":[
        {
            "category":"Professional",
            "subcategory":"Engineering",
            "type":"Services"
        },
        {
            "category":"Building & Trades",
            "subcategory":"Electrical",
            "type":"Services"
        }
    ],
    "sg:phone":"+44 151 430 6628",
    "sg:postcode":"L35 9JG",
    "sg:province":"Cheshire",
    "sg:tags":[
        "engineer",
        "electrician",
        "contractor"
    ],
    "wof:name":"Phill Lowton Portable Appliance Testing",
    "wof:placetype":"venue"
},
  "geometry": {"coordinates":[-2.772855,53.416901],"type":"Point"}
}