{
  "type": "Feature",
  "properties": {
    "addr:full":"101-103 Erith High Street Erith Kent DA8 1RD",
    "addr:housenumber":"101-103",
    "addr:postcode":"da8 1rd",
    "addr:street":"Erith High Street",
    "iso:country":"GB",
    "sg:address":"101-103 Erith High Street",
    "sg:city":"Erith",
    "sg:classifiers":[
        {
            "category":"Insurance",
            "subcategory":"Insurance Agent",
            "type":"Services"
        }
    ],
    "sg:phone":"+44 1322 349917",
    "sg:postcode":"DA8 1RD",
    "sg:province":"Kent",
    "sg:tags":[
        "broker"
    ],
    "wof:name":"Robert Nott & Partners Ltd.",
    "wof:placetype":"venue"
},
  "geometry": {"coordinates":[0.180985,51.479912],"type":"Point"}
}