{
  "type": "Feature",
  "properties": {
    "addr:full":"Lawrence James Kenworthy +1, 5 The North Colonnade London Greater London E14 4BB",
    "addr:housenumber":"5",
    "addr:postcode":"e14 4bb",
    "addr:street":"Lawrence;The North Colonnade",
    "iso:country":"GB",
    "sg:address":"Lawrence James Kenworthy +1, 5 The North Colonnade",
    "sg:city":"London",
    "sg:classifiers":[
        {
            "category":"Banks & Credit Unions",
            "subcategory":"Bank",
            "type":"Services"
        }
    ],
    "sg:postcode":"E14 4BB",
    "sg:province":"Greater London",
    "wof:name":"Barclays Libra Ltd.",
    "wof:placetype":"venue"
},
  "geometry": {"coordinates":[-0.0220899992,51.5056686401],"type":"Point"}
}