{
  "type": "Feature",
  "properties": {
    "addr:full":"533 Sauchiehall Street Glasgow Glasgow City G3 7PH",
    "addr:housenumber":"533",
    "addr:postcode":"g3 7ph",
    "addr:street":"Sauchiehall Street",
    "iso:country":"GB",
    "sg:address":"533 Sauchiehall Street",
    "sg:city":"Glasgow",
    "sg:classifiers":[
        {
            "category":"Government",
            "subcategory":"Post Office",
            "type":"Public Place"
        }
    ],
    "sg:phone":"+44 141 221 5529",
    "sg:postcode":"G3 7PH",
    "sg:province":"Glasgow City",
    "wof:name":"Charing Cross Post Office",
    "wof:placetype":"venue"
},
  "geometry": {"coordinates":[-4.2727742195,55.8662261963],"type":"Point"}
}