{
  "type": "Feature",
  "properties": {
    "addr:full":"14 Temple Road, Biggin Hill Westerham Kent TN16 3UH",
    "addr:housenumber":"14",
    "addr:postcode":"tn16 3uh",
    "addr:street":"Temple Road",
    "iso:country":"GB",
    "sg:address":"14 Temple Road, Biggin Hill",
    "sg:city":"Westerham",
    "sg:classifiers":[
        {
            "category":"Building & Trades",
            "subcategory":"Construction",
            "type":"Services"
        }
    ],
    "sg:phone":"+44 1959 571124",
    "sg:postcode":"TN16 3UH",
    "sg:province":"Kent",
    "sg:tags":[
        "decorator",
        "painter"
    ],
    "wof:name":"Temple Walls",
    "wof:placetype":"venue"
},
  "geometry": {"coordinates":[0.0333499983,51.3115844727],"type":"Point"}
}