{
  "type": "Feature",
  "properties": {
    "addr:full":"Old Railway Yard Denbigh Conwy LL16 3EA",
    "addr:postcode":"ll16 3ea",
    "addr:street":"Old Railway Yard",
    "iso:country":"GB",
    "sg:address":"Old Railway Yard",
    "sg:city":"Denbigh",
    "sg:classifiers":[
        {
            "category":"Food & Beverages",
            "subcategory":"Supermarket",
            "type":"Retail Goods"
        }
    ],
    "sg:phone":"+44 1745 813460",
    "sg:postcode":"LL16 3EA",
    "sg:province":"Conwy",
    "wof:name":"Kwik Save Foodstores",
    "wof:placetype":"venue"
},
  "geometry": {"coordinates":[-3.421149,53.183411],"type":"Point"}
}