{
  "type": "Feature",
  "properties": {
    "addr:full":"190 Borough Rd St Helens Merseyside WA10 3TD",
    "addr:housenumber":"190",
    "addr:postcode":"wa10 3td",
    "addr:street":"Borough Rd",
    "iso:country":"GB",
    "sg:address":"190 Borough Rd",
    "sg:city":"St Helens",
    "sg:classifiers":[
        {
            "category":"Communications",
            "type":"Services"
        }
    ],
    "sg:phone":"+44 1744 454600",
    "sg:postcode":"WA10 3TD",
    "sg:province":"Merseyside",
    "sg:tags":[
        "tv",
        "video",
        "radio"
    ],
    "wof:name":"Hawley Satellite",
    "wof:placetype":"venue"
},
  "geometry": {"coordinates":[-2.7515320778,53.448135376],"type":"Point"}
}