{
  "type": "Feature",
  "properties": {
    "addr:full":"Ward Clerical Office, Rhind Street Bodmin Cornwall PL31 2EN",
    "addr:postcode":"pl31 2en",
    "addr:street":"Rhind Street",
    "iso:country":"GB",
    "sg:address":"Ward Clerical Office, Rhind Street",
    "sg:city":"Bodmin",
    "sg:classifiers":[
        {
            "category":"Health Services",
            "subcategory":"Hospital",
            "type":"Services"
        }
    ],
    "sg:phone":"+44 1208 251555",
    "sg:postcode":"PL31 2EN",
    "sg:province":"Cornwall",
    "wof:name":"East Cornwall Hospital",
    "wof:placetype":"venue"
},
  "geometry": {"coordinates":[-4.7163691521,50.4710464478],"type":"Point"}
}