{
  "type": "Feature",
  "properties": {
    "addr:full":"White Hart Little St Marys, Long Melford Sudbury Essex CO10 9HX",
    "addr:housenumber":"melford",
    "addr:postcode":"co10 9hx",
    "addr:street":"Little;Sudbury",
    "iso:country":"GB",
    "sg:address":"White Hart Little St Marys, Long Melford",
    "sg:city":"Sudbury",
    "sg:classifiers":[
        {
            "category":"Shopping",
            "subcategory":"Antiques",
            "type":"Retail Goods"
        },
        {
            "category":"Shopping",
            "subcategory":"Used Merchandise",
            "type":"Retail Goods"
        }
    ],
    "sg:postcode":"CO10 9HX",
    "sg:province":"Essex",
    "sg:tags":[
        "shop",
        "second-hand"
    ],
    "wof:name":"King,J,",
    "wof:placetype":"venue"
},
  "geometry": {"coordinates":[0.71648,52.075264],"type":"Point"}
}