{
  "type": "Feature",
  "properties": {
    "addr:full":"Farm Walk London Greater London NW11 7TP",
    "addr:postcode":"nw11 7tp",
    "addr:street":"Farm Walk",
    "iso:country":"GB",
    "sg:address":"Farm Walk",
    "sg:city":"London",
    "sg:classifiers":[
        {
            "category":"Arena",
            "subcategory":"Sports Club",
            "type":"Entertainment"
        }
    ],
    "sg:postcode":"NW11 7TP",
    "sg:province":"Greater London",
    "wof:name":"Farm Walk Lawn Tennis Club",
    "wof:placetype":"venue"
},
  "geometry": {"coordinates":[-0.1977390051,51.581703186],"type":"Point"}
}