{
  "type": "Feature",
  "properties": {
    "iso:country":"GB",
    "sg:address":"2 Mill La",
    "sg:city":"Halifax",
    "sg:classifiers":[
        {
            "category":"Bars & Pubs",
            "type":"Food & Drink"
        }
    ],
    "sg:phone":"+44 1422 242059",
    "sg:postcode":"HX2 8UH",
    "sg:province":"West Yorkshire",
    "sg:tags":[
        "pubs",
        "inn"
    ],
    "wof:name":"Hebble Crossing The",
    "wof:placetype":"venue"
},
  "geometry": {"coordinates":[-1.903573,53.75771],"type":"Point"}
}