{
  "type": "Feature",
  "properties": {
    "addr:full":"4 Coniston Gro Heywood Lancashire OL10 2BW",
    "addr:housenumber":"4",
    "addr:postcode":"ol10 2bw",
    "addr:street":"Coniston Gro Heywood",
    "iso:country":"GB",
    "sg:address":"4 Coniston Gro",
    "sg:city":"Heywood",
    "sg:classifiers":[
        {
            "category":"Retail",
            "subcategory":"Storage",
            "type":"Services"
        }
    ],
    "sg:phone":"+44 1706 360200",
    "sg:postcode":"OL10 2BW",
    "sg:province":"Lancashire",
    "sg:tags":[
        "household",
        "removal"
    ],
    "wof:name":"Stan & Ollies Removals",
    "wof:placetype":"venue"
},
  "geometry": {"coordinates":[-2.2148869038,53.5864868164],"type":"Point"}
}