{
  "type": "Feature",
  "properties": {
    "iso:country":"GB",
    "sg:address":"St Johns Way, St Johns Business Estate",
    "sg:city":"Downham Market",
    "sg:classifiers":[
        {
            "category":"Home & Garden",
            "subcategory":"Kitchen Supply",
            "type":"Retail Goods"
        }
    ],
    "sg:phone":"+44 1366 386633",
    "sg:postcode":"PE38 0QQ",
    "sg:province":"Cambridgeshire",
    "sg:tags":[
        "catering"
    ],
    "wof:name":"Accent Fresh Ltd.",
    "wof:placetype":"venue"
},
  "geometry": {"coordinates":[0.3787949979,52.6022834778],"type":"Point"}
}