{
  "type": "Feature",
  "properties": {
    "addr:full":"2 Eastfield Gro Normanton West Yorkshire WF6 1QA",
    "addr:housenumber":"2",
    "addr:postcode":"wf6 1qa",
    "addr:street":"Eastfield Gro Normanton West",
    "iso:country":"GB",
    "sg:address":"2 Eastfield Gro",
    "sg:city":"Normanton",
    "sg:classifiers":[
        {
            "category":"Building & Trades",
            "subcategory":"Plumbing",
            "type":"Services"
        }
    ],
    "sg:phone":"+44 1924 892047",
    "sg:postcode":"WF6 1QA",
    "sg:province":"West Yorkshire",
    "sg:tags":[
        "heating"
    ],
    "wof:name":"Thomas Holley & Son",
    "wof:placetype":"venue"
},
  "geometry": {"coordinates":[-1.406172,53.703419],"type":"Point"}
}