{
  "type": "Feature",
  "properties": {
    "iso:country":"GB",
    "sg:address":"Unit 8, Hamilton Way, Gore Rd Ind Est",
    "sg:city":"New Milton",
    "sg:classifiers":[
        {
            "category":"Food & Beverages",
            "subcategory":"Supermarket",
            "type":"Retail Goods"
        }
    ],
    "sg:phone":"+44 1425 638084",
    "sg:postcode":"BH25 6TQ",
    "sg:province":"Hampshire",
    "sg:tags":[
        "frozen"
    ],
    "wof:name":"Taylor Made Marketing",
    "wof:placetype":"venue"
},
  "geometry": {"coordinates":[-1.66816,50.752342],"type":"Point"}
}