{
  "type": "Feature",
  "properties": {
    "addr:full":"35 Cottage Lane Glossop Derbyshire SK13 7EN",
    "addr:housenumber":"35",
    "addr:postcode":"sk13 7en",
    "addr:street":"Cottage Lane",
    "iso:country":"GB",
    "sg:address":"35 Cottage Lane",
    "sg:city":"Glossop",
    "sg:classifiers":[
        {
            "category":"Building & Trades",
            "subcategory":"Construction",
            "type":"Services"
        }
    ],
    "sg:postcode":"SK13 7EN",
    "sg:province":"Derbyshire",
    "sg:tags":[
        "joiner",
        "carpenter"
    ],
    "wof:name":"Anthony Raymond Leedham",
    "wof:placetype":"venue"
},
  "geometry": {"coordinates":[-1.9809279442,53.4468994141],"type":"Point"}
}