{
  "type": "Feature",
  "properties": {
    "addr:full":"Parc Brean Camborne Cornwall TR14 0RQ",
    "addr:postcode":"tr14 0rq",
    "iso:country":"GB",
    "sg:address":"Parc Brean",
    "sg:city":"Camborne",
    "sg:classifiers":[
        {
            "category":"Building & Trades",
            "subcategory":"Construction",
            "type":"Services"
        }
    ],
    "sg:phone":"+44 1209 715316",
    "sg:postcode":"TR14 0RQ",
    "sg:province":"Cornwall",
    "sg:tags":[
        "joinery"
    ],
    "wof:name":"Don Thomas Joinery",
    "wof:placetype":"venue"
},
  "geometry": {"coordinates":[-5.3012580872,50.2136535645],"type":"Point"}
}