{
  "type": "Feature",
  "properties": {
    "addr:full":"Courtland Emms Lane, Brooks Green Horsham West Sussex RH13 0TR",
    "addr:postcode":"rh13 0tr",
    "addr:street":"Courtland Emms Lane Brooks Green",
    "iso:country":"GB",
    "sg:address":"Courtland Emms Lane, Brooks Green",
    "sg:city":"Horsham",
    "sg:classifiers":[
        {
            "category":"Education",
            "subcategory":"Special Training",
            "type":"Public Place"
        }
    ],
    "sg:phone":"+44 1403 741880",
    "sg:postcode":"RH13 0TR",
    "sg:province":"West Sussex",
    "sg:tags":[
        "product",
        "centre"
    ],
    "wof:name":"Tutorpro Ltd.",
    "wof:placetype":"venue"
},
  "geometry": {"coordinates":[-0.391939,51.013733],"type":"Point"}
}