{
  "type": "Feature",
  "properties": {
    "addr:full":"Green Gables, Higher Lincombe Road Torquay Devon TQ1 2HD",
    "addr:housenumber":"higher",
    "addr:postcode":"tq1 2hd",
    "addr:street":"Green;Lincombe Road",
    "iso:country":"GB",
    "sg:address":"Green Gables, Higher Lincombe Road",
    "sg:city":"Torquay",
    "sg:classifiers":[
        {
            "category":"Building & Trades",
            "subcategory":"Construction",
            "type":"Services"
        }
    ],
    "sg:phone":"+44 1803 298485",
    "sg:postcode":"TQ1 2HD",
    "sg:province":"Devon",
    "sg:tags":[
        "decorator",
        "painter"
    ],
    "wof:name":"Wellswood Decorators",
    "wof:placetype":"venue"
},
  "geometry": {"coordinates":[-3.506114006,50.4626312256],"type":"Point"}
}