{
  "type": "Feature",
  "properties": {
    "addr:full":"13 Beaufort Gardens London Greater London NW4 3QN",
    "addr:housenumber":"13",
    "addr:postcode":"nw4 3qn",
    "addr:street":"Beaufort Gardens",
    "iso:country":"GB",
    "sg:address":"13 Beaufort Gardens",
    "sg:city":"London",
    "sg:classifiers":[
        {
            "category":"Professional",
            "subcategory":"Advertising",
            "type":"Services"
        }
    ],
    "sg:postcode":"NW4 3QN",
    "sg:province":"Greater London",
    "sg:tags":[
        "agency"
    ],
    "wof:name":"M.F.S.A. Ltd",
    "wof:placetype":"venue"
},
  "geometry": {"coordinates":[-0.2240550071,51.5799407959],"type":"Point"}
}