{
  "type": "Feature",
  "properties": {
    "addr:full":"Hill Top Farm, Whilton Daventry Northamptonshire NN11 5NN",
    "addr:postcode":"nn11 5nn",
    "iso:country":"GB",
    "sg:address":"Hill Top Farm, Whilton",
    "sg:city":"Daventry",
    "sg:classifiers":[
        {
            "category":"Farming",
            "subcategory":"Livestock Farm",
            "type":"Manufacturing & Wholesale Goods"
        },
        {
            "category":"Farming",
            "subcategory":"Farm",
            "type":"Manufacturing & Wholesale Goods"
        }
    ],
    "sg:postcode":"NN11 5NN",
    "sg:province":"Northamptonshire",
    "sg:tags":[
        "mixed",
        "crop",
        "others"
    ],
    "wof:name":"G W Emery",
    "wof:placetype":"venue"
},
  "geometry": {"coordinates":[-1.1622389555,52.260433197],"type":"Point"}
}