{
  "type": "Feature",
  "properties": {
    "iso:country":"GB",
    "sg:address":"Enterprise House, Meadow Drive, Hampton In Arden",
    "sg:city":"Solihull",
    "sg:classifiers":[
        {
            "category":"Professional",
            "subcategory":"Management & Consulting",
            "type":"Services"
        }
    ],
    "sg:phone":"+44 1675 443030",
    "sg:postcode":"B92 0BD",
    "sg:province":"West Midlands",
    "sg:tags":[
        "consultant",
        "training"
    ],
    "wof:name":"Garner Harris Ltd.",
    "wof:placetype":"venue"
},
  "geometry": {"coordinates":[-1.700071,52.426628],"type":"Point"}
}