{
  "type": "Feature",
  "properties": {
    "addr:full":"89 Newbold Road Chesterfield Derbyshire S41 7PS",
    "addr:housenumber":"89",
    "addr:postcode":"s41 7ps",
    "addr:street":"Newbold Road",
    "iso:country":"GB",
    "sg:address":"89 Newbold Road",
    "sg:city":"Chesterfield",
    "sg:classifiers":[
        {
            "category":"Travel",
            "subcategory":"Hotels & Motels",
            "type":"Entertainment"
        }
    ],
    "sg:postcode":"S41 7PS",
    "sg:province":"Derbyshire",
    "wof:name":"First European Hotel",
    "wof:placetype":"venue"
},
  "geometry": {"coordinates":[-1.433132,53.242008],"type":"Point"}
}