{
  "type": "Feature",
  "properties": {
    "iso:country":"GB",
    "sg:address":"Unit 2/3 Print Village, 58 Chadwick Road",
    "sg:city":"London",
    "sg:classifiers":[
        {
            "category":"Professional",
            "subcategory":"Printing & Photocopies",
            "type":"Services"
        }
    ],
    "sg:phone":"+44 20 7358 1395",
    "sg:postcode":"SE15 4PU",
    "sg:province":"Greater London",
    "sg:tags":[
        "printer"
    ],
    "wof:name":"The Tower Printing Co. Ltd.",
    "wof:placetype":"venue"
},
  "geometry": {"coordinates":[-0.07463,51.467869],"type":"Point"}
}