{
  "type": "Feature",
  "properties": {
    "addr:full":"Unit 1a, Rear Of Oak Down, Horsham Road Dorking Surrey RH5 4PF",
    "addr:housenumber":"unit 1a rear of oak",
    "addr:postcode":"rh5 4pf",
    "addr:street":"Horsham Road",
    "iso:country":"GB",
    "sg:address":"Unit 1a, Rear Of Oak Down, Horsham Road",
    "sg:city":"Dorking",
    "sg:classifiers":[
        {
            "category":"Retail",
            "subcategory":"Auto Repair",
            "type":"Services"
        }
    ],
    "sg:phone":"+44 1306 713232",
    "sg:postcode":"RH5 4PF",
    "sg:province":"Surrey",
    "sg:tags":[
        "modification",
        "garage"
    ],
    "wof:name":"M J F Engineering",
    "wof:placetype":"venue"
},
  "geometry": {"coordinates":[-0.3162400126,51.1706695557],"type":"Point"}
}