{
  "type": "Feature",
  "properties": {
    "addr:full":"14 Stockwell Road East Grinstead East Sussex RH19 4AU",
    "addr:housenumber":"14",
    "addr:postcode":"rh19 4au",
    "addr:street":"Stockwell Road",
    "iso:country":"GB",
    "sg:address":"14 Stockwell Road",
    "sg:city":"East Grinstead",
    "sg:classifiers":[
        {
            "category":"Professional",
            "type":"Services"
        }
    ],
    "sg:phone":"+44 1342 323425",
    "sg:postcode":"RH19 4AU",
    "sg:province":"East Sussex",
    "sg:tags":[
        "entertainer"
    ],
    "wof:name":"Express Yourself",
    "wof:placetype":"venue"
},
  "geometry": {"coordinates":[-0.010886,51.114056],"type":"Point"}
}