{
  "type": "Feature",
  "properties": {
    "iso:country":"GB",
    "sg:address":"9 Orchard Gardens",
    "sg:city":"Bolton",
    "sg:classifiers":[
        {
            "category":"Building & Trades",
            "subcategory":"Construction",
            "type":"Services"
        }
    ],
    "sg:phone":"+44 1204 527588",
    "sg:postcode":"BL2 3PS",
    "sg:province":"Lancashire",
    "sg:tags":[
        "glazier",
        "decorator",
        "painter"
    ],
    "wof:name":"J K Morton",
    "wof:placetype":"venue"
},
  "geometry": {"coordinates":[-2.3812398911,53.5966911316],"type":"Point"}
}