{
  "type": "Feature",
  "properties": {
    "addr:full":"25 Ardencraig Drive Glasgow Glasgow City G45 0HS",
    "addr:housenumber":"25",
    "addr:postcode":"g45 0hs",
    "addr:street":"Ardencraig Drive",
    "iso:country":"GB",
    "sg:address":"25 Ardencraig Drive",
    "sg:city":"Glasgow",
    "sg:classifiers":[
        {
            "category":"Education",
            "subcategory":"School",
            "type":"Public Place"
        }
    ],
    "sg:phone":"+44 141 634 3113",
    "sg:postcode":"G45 0HS",
    "sg:province":"Glasgow City",
    "sg:tags":[
        "local",
        "authority"
    ],
    "wof:name":"St Dominic's R C Primary School",
    "wof:placetype":"venue"
},
  "geometry": {"coordinates":[-4.2217288017,55.8022003174],"type":"Point"}
}