{
  "type": "Feature",
  "properties": {
    "addr:full":"48 Corrie Rd Cambridge Cambridgeshire CB1 3RB",
    "addr:housenumber":"48",
    "addr:postcode":"cb1 3rb",
    "addr:street":"Corrie Rd",
    "iso:country":"GB",
    "sg:address":"48 Corrie Rd",
    "sg:city":"Cambridge",
    "sg:classifiers":[
        {
            "category":"Professional",
            "subcategory":"Business Services",
            "type":"Services"
        }
    ],
    "sg:phone":"+44 1223 241959",
    "sg:postcode":"CB1 3RB",
    "sg:province":"Cambridgeshire",
    "sg:tags":[
        "shop",
        "cleaning"
    ],
    "wof:name":"Spick & Span",
    "wof:placetype":"venue"
},
  "geometry": {"coordinates":[0.1441719979,52.1945495605],"type":"Point"}
}