{
  "type": "Feature",
  "properties": {
    "iso:country":"GB",
    "sg:address":"129-131 Trafalgar Road",
    "sg:city":"London",
    "sg:classifiers":[
        {
            "category":"Shopping",
            "subcategory":"Florist",
            "type":"Retail Goods"
        }
    ],
    "sg:phone":"+44 20 8858 0859",
    "sg:postcode":"SE10 9TX",
    "sg:province":"Greater London",
    "wof:name":"The Greenwich Flower Co",
    "wof:placetype":"venue"
},
  "geometry": {"coordinates":[0.0030690001,51.484703064],"type":"Point"}
}