{
  "type": "Feature",
  "properties": {
    "iso:country":"GB",
    "sg:address":"43 Middleshot Square",
    "sg:city":"Prestonpans",
    "sg:classifiers":[
        {
            "category":"Cinema",
            "subcategory":"Movie Rental",
            "type":"Entertainment"
        }
    ],
    "sg:postcode":"EH32 9RQ",
    "sg:province":"East Lothian",
    "sg:tags":[
        "video",
        "library"
    ],
    "wof:name":"Video Select",
    "wof:placetype":"venue"
},
  "geometry": {"coordinates":[-2.967294,55.960499],"type":"Point"}
}