{
  "type": "Feature",
  "properties": {
    "addr:full":"43 Middleshot Square Prestonpans East Lothian EH32 9RQ",
    "addr:housenumber":"43",
    "addr:postcode":"eh32 9rq",
    "addr:street":"Middleshot Square",
    "iso:country":"GB",
    "sg:address":"43 Middleshot Square",
    "sg:city":"Prestonpans",
    "sg:classifiers":[
        {
            "category":"Cinema",
            "subcategory":"Movie Rental",
            "type":"Entertainment"
        }
    ],
    "sg:postcode":"EH32 9RQ",
    "sg:province":"East Lothian",
    "sg:tags":[
        "video",
        "library"
    ],
    "wof:name":"Video Select",
    "wof:placetype":"venue"
},
  "geometry": {"coordinates":[-2.967294,55.960499],"type":"Point"}
}