{
  "type": "Feature",
  "properties": {
    "addr:full":"150 High Street London Greater London SE20 7EU",
    "addr:housenumber":"150",
    "addr:postcode":"se20 7eu",
    "addr:street":"High Street",
    "iso:country":"GB",
    "sg:address":"150 High Street",
    "sg:city":"London",
    "sg:classifiers":[
        {
            "category":"Fast Food",
            "type":"Food & Drink"
        }
    ],
    "sg:postcode":"SE20 7EU",
    "sg:province":"Greater London",
    "sg:tags":[
        "away",
        "take"
    ],
    "wof:name":"Carib Vibe Cafe Ltd",
    "wof:placetype":"venue"
},
  "geometry": {"coordinates":[-0.0520940013,51.4141654968],"type":"Point"}
}