{
  "type": "Feature",
  "properties": {
    "iso:country":"GB",
    "sg:address":"164 Fair Oak Road",
    "sg:city":"Eastleigh",
    "sg:classifiers":[
        {
            "category":"Food & Beverages",
            "subcategory":"Groceries & Convenience Stores",
            "type":"Retail Goods"
        }
    ],
    "sg:phone":"+44 23 8069 2702",
    "sg:postcode":"SO50 8HA",
    "sg:province":"Hampshire",
    "wof:name":"Wellstead & Daly",
    "wof:placetype":"venue"
},
  "geometry": {"coordinates":[-1.325729,50.96627],"type":"Point"}
}