{
  "type": "Feature",
  "properties": {
    "addr:full":"246 Woodhouse Road London Greater London N12 0RU",
    "addr:housenumber":"246",
    "addr:postcode":"n12 0ru",
    "addr:street":"Woodhouse Road",
    "iso:country":"GB",
    "sg:address":"246 Woodhouse Road",
    "sg:city":"London",
    "sg:classifiers":[
        {
            "category":"Autos & Motor Vehicles",
            "subcategory":"Automobile Sales",
            "type":"Retail Goods"
        }
    ],
    "sg:phone":"+44 20 8368 1235",
    "sg:postcode":"N12 0RU",
    "sg:province":"Greater London",
    "sg:tags":[
        "car"
    ],
    "wof:name":"Rex Garages",
    "wof:placetype":"venue"
},
  "geometry": {"coordinates":[-0.1621190012,51.6117095947],"type":"Point"}
}