{
  "type": "Feature",
  "properties": {
    "addr:full":"4 St Andrews Street South Bury St Edmunds Suffolk IP33 3PH",
    "addr:housenumber":"4",
    "addr:postcode":"ip33 3ph",
    "addr:street":"St Andrews Street South",
    "iso:country":"GB",
    "sg:address":"4 St Andrews Street South",
    "sg:city":"Bury St Edmunds",
    "sg:classifiers":[
        {
            "category":"Manufacturing",
            "subcategory":"Apparel",
            "type":"Manufacturing & Wholesale Goods"
        }
    ],
    "sg:phone":"+44 1284 725699",
    "sg:postcode":"IP33 3PH",
    "sg:province":"Suffolk",
    "sg:tags":[
        "garment",
        "designer"
    ],
    "wof:name":"Wildlife Distribution",
    "wof:placetype":"venue"
},
  "geometry": {"coordinates":[0.7117689848,52.2417869568],"type":"Point"}
}