{
  "type": "Feature",
  "properties": {
    "addr:full":"14 Dixon St Nelson Lancashire BB9 8PL",
    "addr:housenumber":"14",
    "addr:postcode":"bb9 8pl",
    "addr:street":"Dixon St",
    "iso:country":"GB",
    "sg:address":"14 Dixon St",
    "sg:city":"Nelson",
    "sg:classifiers":[
        {
            "category":"Building & Trades",
            "subcategory":"Landscaping Services",
            "type":"Services"
        }
    ],
    "sg:phone":"+44 1282 699009",
    "sg:postcode":"BB9 8PL",
    "sg:province":"Lancashire",
    "sg:tags":[
        "landscape",
        "contractor"
    ],
    "wof:name":"Davies Landscaping",
    "wof:placetype":"venue"
},
  "geometry": {"coordinates":[-2.22513,53.847824],"type":"Point"}
}