{
  "type": "Feature",
  "properties": {
    "iso:country":"GB",
    "sg:address":"28 Deptford High Street",
    "sg:city":"London",
    "sg:classifiers":[
        {
            "category":"Professional",
            "subcategory":"Lawyer & Legal Services",
            "type":"Services"
        }
    ],
    "sg:phone":"+44 20 8692 5355",
    "sg:postcode":"SE8 4AF",
    "sg:province":"Greater London",
    "sg:tags":[
        "advice",
        "counselling"
    ],
    "wof:name":"Lewisham Law Centre Ltd.",
    "wof:placetype":"venue"
},
  "geometry": {"coordinates":[-0.023077,51.4743],"type":"Point"}
}