{
  "type": "Feature",
  "properties": {
    "iso:country":"GB",
    "sg:address":"Parkside House, 190-192 Wigan Road, Euxton",
    "sg:city":"Chorley",
    "sg:classifiers":[
        {
            "category":"Professional",
            "subcategory":"Art Services",
            "type":"Services"
        }
    ],
    "sg:phone":"+44 1257 263393",
    "sg:postcode":"PR7 6JW",
    "sg:province":"Lancashire",
    "sg:tags":[
        "photographer"
    ],
    "wof:name":"Raymond Thomas",
    "wof:placetype":"venue"
},
  "geometry": {"coordinates":[-2.675237,53.665257],"type":"Point"}
}