{
  "type": "Feature",
  "properties": {
    "addr:full":"1 Penn Rd Beaconsfield Buckinghamshire HP9 2PR",
    "addr:housenumber":"1",
    "addr:postcode":"hp9 2pr",
    "addr:street":"Penn Rd",
    "iso:country":"GB",
    "sg:address":"1 Penn Rd",
    "sg:city":"Beaconsfield",
    "sg:classifiers":[
        {
            "category":"Banks & Credit Unions",
            "subcategory":"Bank",
            "type":"Services"
        }
    ],
    "sg:phone":"+44 1494 442244",
    "sg:postcode":"HP9 2PR",
    "sg:province":"Buckinghamshire",
    "wof:name":"NatWest",
    "wof:placetype":"venue"
},
  "geometry": {"coordinates":[-0.647521019,51.6124343872],"type":"Point"}
}