{
  "type": "Feature",
  "properties": {
    "addr:full":"Pilot House, Unit 3 41 King Street Leicester Leicestershire LE1 6RN",
    "addr:housenumber":"unit;41",
    "addr:postcode":"le1 6rn",
    "addr:street":"Pilot;King Street",
    "iso:country":"GB",
    "sg:address":"Pilot House, Unit 3 41 King Street",
    "sg:city":"Leicester",
    "sg:classifiers":[
        {
            "category":"Organizations",
            "subcategory":"Non-profit Organization",
            "type":"Services"
        }
    ],
    "sg:postcode":"LE1 6RN",
    "sg:province":"Leicestershire",
    "sg:tags":[
        "organisation",
        "voluntary",
        "charity"
    ],
    "wof:name":"Sofa",
    "wof:placetype":"venue"
},
  "geometry": {"coordinates":[-1.1321239471,52.6304473877],"type":"Point"}
}