{
  "type": "Feature",
  "properties": {
    "addr:full":"11 Brunel Rd, Gorse Lane Industrial Estate Clacton On Sea Essex CO15 4LU",
    "addr:housenumber":"11;estate",
    "addr:postcode":"co15 4lu",
    "addr:street":"Brunel Rd Gorse Lane Industrial",
    "iso:country":"GB",
    "sg:address":"11 Brunel Rd, Gorse Lane Industrial Estate",
    "sg:city":"Clacton On Sea",
    "sg:classifiers":[
        {
            "category":"Professional",
            "subcategory":"Computer Services",
            "type":"Services"
        }
    ],
    "sg:phone":"+44 1255 221515",
    "sg:postcode":"CO15 4LU",
    "sg:province":"Essex",
    "sg:tags":[
        "aided",
        "design"
    ],
    "wof:name":"The Cad Bureau",
    "wof:placetype":"venue"
},
  "geometry": {"coordinates":[1.1695450544,51.8166389465],"type":"Point"}
}