{
  "type": "Feature",
  "properties": {
    "addr:full":"Church Lane Sale Cheshire M33 5QG",
    "addr:postcode":"m33 5qg",
    "addr:street":"Church Lane",
    "iso:country":"GB",
    "sg:address":"Church Lane",
    "sg:city":"Sale",
    "sg:classifiers":[
        {
            "category":"Education",
            "subcategory":"School",
            "type":"Public Place"
        }
    ],
    "sg:phone":"+44 161 962 1828",
    "sg:postcode":"M33 5QG",
    "sg:province":"Cheshire",
    "sg:tags":[
        "local",
        "authority"
    ],
    "wof:name":"Trafford Metropolitan Borough Council",
    "wof:placetype":"venue"
},
  "geometry": {"coordinates":[-2.3424038887,53.4319343567],"type":"Point"}
}