{
  "type": "Feature",
  "properties": {
    "iso:country":"GB",
    "sg:address":"5 Hendon St",
    "sg:city":"Sheffield",
    "sg:classifiers":[
        {
            "category":"Professional",
            "subcategory":"Accounting & Tax Preparation",
            "type":"Services"
        }
    ],
    "sg:phone":"+44 114 288 0655",
    "sg:postcode":"S13 9AX",
    "sg:province":"South Yorkshire",
    "sg:tags":[
        "accountant"
    ],
    "wof:name":"Green & Co",
    "wof:placetype":"venue"
},
  "geometry": {"coordinates":[-1.3870010376,53.3718795776],"type":"Point"}
}