{
  "type": "Feature",
  "properties": {
    "iso:country":"GB",
    "sg:address":"The Lodge, Ridley Hall, Bardon Mill",
    "sg:city":"Hexham",
    "sg:classifiers":[
        {
            "category":"Education",
            "subcategory":"Special Training",
            "type":"Public Place"
        }
    ],
    "sg:phone":"+44 1434 344933",
    "sg:postcode":"NE47 7BP",
    "sg:province":"Northumberland",
    "sg:tags":[
        "product",
        "centre"
    ],
    "wof:name":"Tynedale Horticultral Service",
    "wof:placetype":"venue"
},
  "geometry": {"coordinates":[-2.343387,54.976479],"type":"Point"}
}