{
  "type": "Feature",
  "properties": {
    "addr:full":"Jalna Culverlands Farm, Manns Hill, Burghfield Common Reading Berkshire RG7 3BD",
    "addr:postcode":"rg7 3bd",
    "addr:street":"Manns Hill Burghfield Common",
    "iso:country":"GB",
    "sg:address":"Jalna Culverlands Farm, Manns Hill, Burghfield Common",
    "sg:city":"Reading",
    "sg:classifiers":[
        {
            "category":"Retail",
            "subcategory":"Auto Repair",
            "type":"Services"
        }
    ],
    "sg:postcode":"RG7 3BD",
    "sg:province":"Berkshire",
    "sg:tags":[
        "electrician"
    ],
    "wof:name":"E M F Auto Electrics",
    "wof:placetype":"venue"
},
  "geometry": {"coordinates":[-1.06459,51.395096],"type":"Point"}
}