{
  "type": "Feature",
  "properties": {
    "addr:full":"317 Bury Road Bolton Lancashire BL2 6BB",
    "addr:housenumber":"317",
    "addr:postcode":"bl2 6bb",
    "addr:street":"Bury Road",
    "iso:country":"GB",
    "sg:address":"317 Bury Road",
    "sg:city":"Bolton",
    "sg:classifiers":[
        {
            "category":"Professional",
            "subcategory":"Printing & Photocopies",
            "type":"Services"
        }
    ],
    "sg:phone":"+44 1204 391888",
    "sg:postcode":"BL2 6BB",
    "sg:province":"Lancashire",
    "sg:tags":[
        "trophy"
    ],
    "wof:name":"Bolton Trophy Centre",
    "wof:placetype":"venue"
},
  "geometry": {"coordinates":[-2.4062519073,53.5805625916],"type":"Point"}
}