{
  "type": "Feature",
  "properties": {
    "addr:full":"19 Bargates Christchurch Dorset BH23 1QD",
    "addr:housenumber":"19",
    "addr:postcode":"bh23 1qd",
    "addr:street":"Bargates",
    "iso:country":"GB",
    "sg:address":"19 Bargates",
    "sg:city":"Christchurch",
    "sg:classifiers":[
        {
            "category":"Building & Trades",
            "subcategory":"Construction",
            "type":"Services"
        }
    ],
    "sg:phone":"+44 1202 480062",
    "sg:postcode":"BH23 1QD",
    "sg:province":"Dorset",
    "sg:tags":[
        "ceiling",
        "contractor"
    ],
    "wof:name":"Motile Projects Ltd.",
    "wof:placetype":"venue"
},
  "geometry": {"coordinates":[-1.779111,50.736118],"type":"Point"}
}