{
  "type": "Feature",
  "properties": {
    "addr:full":"30 King Street Middlewich Cheshire CW10 9EH",
    "addr:housenumber":"30",
    "addr:postcode":"cw10 9eh",
    "addr:street":"King Street",
    "iso:country":"GB",
    "sg:address":"30 King Street",
    "sg:city":"Middlewich",
    "sg:classifiers":[
        {
            "category":"Professional",
            "subcategory":"Business Services",
            "type":"Services"
        }
    ],
    "sg:phone":"+44 1606 833133",
    "sg:postcode":"CW10 9EH",
    "sg:province":"Cheshire",
    "sg:tags":[
        "agent",
        "manufacturers'"
    ],
    "wof:name":"Mark Taylor Fashion Agencies",
    "wof:placetype":"venue"
},
  "geometry": {"coordinates":[-2.444983,53.197849],"type":"Point"}
}