{
  "type": "Feature",
  "properties": {
    "iso:country":"GB",
    "sg:address":"16 Forest Drive, Theydon Bois",
    "sg:city":"Epping",
    "sg:classifiers":[
        {
            "category":"Food & Beverages",
            "subcategory":"Fruits & Vegetables",
            "type":"Retail Goods"
        }
    ],
    "sg:phone":"+44 1992 812792",
    "sg:postcode":"CM16 7EY",
    "sg:province":"Essex",
    "sg:tags":[
        "greengrocer"
    ],
    "wof:name":"The Market Garden",
    "wof:placetype":"venue"
},
  "geometry": {"coordinates":[0.101634,51.672012],"type":"Point"}
}