{
  "type": "Feature",
  "properties": {
    "addr:full":"151 South Ealing Road London Greater London W5 4QP",
    "addr:housenumber":"151",
    "addr:postcode":"w5 4qp",
    "addr:street":"South Ealing Road",
    "iso:country":"GB",
    "sg:address":"151 South Ealing Road",
    "sg:city":"London",
    "sg:classifiers":[
        {
            "category":"Health Services",
            "subcategory":"Optometrist",
            "type":"Services"
        },
        {
            "category":"Shopping",
            "subcategory":"Optician",
            "type":"Retail Goods"
        }
    ],
    "sg:phone":"+44 20 8567 7902",
    "sg:postcode":"W5 4QP",
    "sg:province":"Greater London",
    "sg:tags":[
        "ophthalmic"
    ],
    "wof:name":"J Wexler",
    "wof:placetype":"venue"
},
  "geometry": {"coordinates":[-0.3059979975,51.498210907],"type":"Point"}
}