{
  "type": "Feature",
  "properties": {
    "addr:full":"9 Endcliffe Grove Avenue Sheffield South Yorkshire S10 3EJ",
    "addr:housenumber":"9",
    "addr:postcode":"s10 3ej",
    "addr:street":"Endcliffe Grove Avenue",
    "iso:country":"GB",
    "sg:address":"9 Endcliffe Grove Avenue",
    "sg:city":"Sheffield",
    "sg:classifiers":[
        {
            "category":"Health Services",
            "subcategory":"Doctor",
            "type":"Services"
        }
    ],
    "sg:phone":"+44 114 266 6545",
    "sg:postcode":"S10 3EJ",
    "sg:province":"South Yorkshire",
    "sg:tags":[
        "practitioners"
    ],
    "wof:name":"D R Cullen",
    "wof:placetype":"venue"
},
  "geometry": {"coordinates":[-1.511855,53.370255],"type":"Point"}
}