{
  "type": "Feature",
  "properties": {
    "iso:country":"GB",
    "sg:address":"2-4 Hanford Way",
    "sg:city":"Loughborough",
    "sg:classifiers":[
        {
            "category":"Retail",
            "subcategory":"Auto Repair",
            "type":"Services"
        }
    ],
    "sg:phone":"+44 1509 234814",
    "sg:postcode":"LE11 1LS",
    "sg:province":"Leicestershire",
    "sg:tags":[
        "body",
        "car"
    ],
    "wof:name":"Pegasus Body Shop",
    "wof:placetype":"venue"
},
  "geometry": {"coordinates":[-1.2004649639,52.7773170471],"type":"Point"}
}