{
  "type": "Feature",
  "properties": {
    "iso:country":"GB",
    "sg:address":"151 Huddersfield Road, Meltham",
    "sg:city":"Huddersfield",
    "sg:classifiers":[
        {
            "category":"Building & Trades",
            "subcategory":"Construction",
            "type":"Services"
        }
    ],
    "sg:phone":"+44 1484 854129",
    "sg:postcode":"HD9 4AJ",
    "sg:province":"South Yorkshire",
    "sg:tags":[
        "demolition",
        "contractor"
    ],
    "wof:name":"Concrete Services",
    "wof:placetype":"venue"
},
  "geometry": {"coordinates":[-1.8391510248,53.5951576233],"type":"Point"}
}