{
  "type": "Feature",
  "properties": {
    "addr:full":"26b Chapel Lane, Formby Liverpool Lancashire L37 4DU",
    "addr:housenumber":"26b",
    "addr:postcode":"l37 4du",
    "addr:street":"Chapel Lane",
    "iso:country":"GB",
    "sg:address":"26b Chapel Lane, Formby",
    "sg:city":"Liverpool",
    "sg:classifiers":[
        {
            "category":"Arts & Performance",
            "subcategory":"Art Gallery",
            "type":"Entertainment"
        }
    ],
    "sg:phone":"+44 1704 831160",
    "sg:postcode":"L37 4DU",
    "sg:province":"Lancashire",
    "wof:name":"M G Fine Arts",
    "wof:placetype":"venue"
},
  "geometry": {"coordinates":[-3.06097,53.556728],"type":"Point"}
}