{
  "type": "Feature",
  "properties": {
    "addr:full":"Reclamation Yard, Upper Green Bradford West Yorkshire BD7 4EZ",
    "addr:postcode":"bd7 4ez",
    "addr:street":"Reclamation Yard",
    "iso:country":"GB",
    "sg:address":"Reclamation Yard, Upper Green",
    "sg:city":"Bradford",
    "sg:classifiers":[
        {
            "category":"Wholesale",
            "subcategory":"Construction Materials",
            "type":"Manufacturing & Wholesale Goods"
        }
    ],
    "sg:phone":"+44 1274 501270",
    "sg:postcode":"BD7 4EZ",
    "sg:province":"West Yorkshire",
    "sg:tags":[
        "merchant",
        "stone"
    ],
    "wof:name":"Spivey Demolition",
    "wof:placetype":"venue"
},
  "geometry": {"coordinates":[-1.78895998,53.7795181274],"type":"Point"}
}