{
  "type": "Feature",
  "properties": {
    "iso:country":"GB",
    "sg:address":"2 Stockerston Road, Uppingham",
    "sg:city":"Leicester",
    "sg:classifiers":[
        {
            "category":"Shopping",
            "subcategory":"Department Store",
            "type":"Retail Goods"
        },
        {
            "category":"Shopping",
            "subcategory":"Gifts & Souvenirs",
            "type":"Retail Goods"
        },
        {
            "category":"Real Estate",
            "subcategory":"Real Estate Agent",
            "type":"Services"
        }
    ],
    "sg:phone":"+44 1572 823955",
    "sg:postcode":"LE15 9UD",
    "sg:province":"Leicestershire",
    "sg:tags":[
        "shop"
    ],
    "wof:name":"Minerva",
    "wof:placetype":"venue"
},
  "geometry": {"coordinates":[-0.7275559902,52.5883026123],"type":"Point"}
}