{
  "type": "Feature",
  "properties": {
    "addr:full":"Pentwyn Farm, Llanwern Brecon Powys LD3 7UP",
    "addr:postcode":"ld3 7up",
    "iso:country":"GB",
    "sg:address":"Pentwyn Farm, Llanwern",
    "sg:city":"Brecon",
    "sg:classifiers":[
        {
            "category":"Farming",
            "subcategory":"Livestock Farm",
            "type":"Manufacturing & Wholesale Goods"
        }
    ],
    "sg:postcode":"LD3 7UP",
    "sg:province":"Powys",
    "sg:tags":[
        "others"
    ],
    "wof:name":"G M Davies",
    "wof:placetype":"venue"
},
  "geometry": {"coordinates":[-3.3911418915,51.9497413635],"type":"Point"}
}