{
  "type": "Feature",
  "properties": {
    "iso:country":"GB",
    "sg:address":"Unit C, Austin House, Wotton Road",
    "sg:city":"Ashford",
    "sg:classifiers":[
        {
            "category":"Professional",
            "subcategory":"Engineering",
            "type":"Services"
        }
    ],
    "sg:phone":"+44 1233 611069",
    "sg:postcode":"TN23 2LW",
    "sg:province":"Kent",
    "sg:tags":[
        "civil",
        "engineer"
    ],
    "wof:name":"W P Breen Ltd.",
    "wof:placetype":"venue"
},
  "geometry": {"coordinates":[0.8658499718,51.1318817139],"type":"Point"}
}