{
  "type": "Feature",
  "properties": {
    "iso:country":"GB",
    "sg:address":"Club House, Castle Road",
    "sg:city":"Invergordon",
    "sg:classifiers":[
        {
            "category":"Arena",
            "subcategory":"Sports Club",
            "type":"Entertainment"
        }
    ],
    "sg:phone":"+44 1349 852136",
    "sg:postcode":"IV18 0AZ",
    "sg:province":"Highland",
    "wof:name":"Ross Sutherland Rugby Club",
    "wof:placetype":"venue"
},
  "geometry": {"coordinates":[-4.169818,57.689682],"type":"Point"}
}