{
  "type": "Feature",
  "properties": {
    "iso:country":"GB",
    "sg:address":"53 High Street",
    "sg:city":"Laurencekirk",
    "sg:classifiers":[
        {
            "category":"Real Estate",
            "subcategory":"Architect",
            "type":"Services"
        }
    ],
    "sg:phone":"+44 1561 378882",
    "sg:postcode":"AB30 1BH",
    "sg:province":"Aberdeenshire",
    "wof:name":"Wheadon Electrical Engineering Services Ltd.",
    "wof:placetype":"venue"
},
  "geometry": {"coordinates":[-2.465553,56.833023],"type":"Point"}
}