{
  "type": "Feature",
  "properties": {
    "iso:country":"GB",
    "sg:address":"The Granary",
    "sg:city":"North Walsham",
    "sg:classifiers":[
        {
            "category":"Manufacturing",
            "subcategory":"Metals",
            "type":"Manufacturing & Wholesale Goods"
        }
    ],
    "sg:postcode":"NR28 0JY",
    "sg:province":"Norfolk",
    "sg:tags":[
        "steel",
        "fabricator",
        "erectors"
    ],
    "wof:name":"F W H Jordan Welding & Fabricating Ltd.",
    "wof:placetype":"venue"
},
  "geometry": {"coordinates":[1.38476,52.818314],"type":"Point"}
}