{
  "type": "Feature",
  "properties": {
    "iso:country":"GB",
    "sg:address":"38 Grantham Street",
    "sg:city":"Lincoln",
    "sg:classifiers":[
        {
            "category":"Shopping",
            "subcategory":"Musical Instruments",
            "type":"Retail Goods"
        }
    ],
    "sg:postcode":"LN2 1LW",
    "sg:province":"Lincolnshire",
    "sg:tags":[
        "music",
        "sheet"
    ],
    "wof:name":"Counterpoint",
    "wof:placetype":"venue"
},
  "geometry": {"coordinates":[-0.539018,53.23148],"type":"Point"}
}