{
  "type": "Feature",
  "properties": {
    "iso:country":"GB",
    "sg:address":"14 Zobel Close, Sweet Briar Rd Ind Est",
    "sg:city":"Norwich",
    "sg:classifiers":[
        {
            "category":"Shopping",
            "subcategory":"Stationery & Office Supplies",
            "type":"Retail Goods"
        }
    ],
    "sg:phone":"+44 1603 419900",
    "sg:postcode":"NR3 2BY",
    "sg:province":"Norfolk",
    "wof:name":"BOB DOBSON OFFICE SUPPLIES",
    "wof:placetype":"venue"
},
  "geometry": {"coordinates":[1.264564991,52.6473197937],"type":"Point"}
}