{
  "type": "Feature",
  "properties": {
    "iso:country":"GB",
    "sg:address":"536-538 Little Horton Lane",
    "sg:city":"Bradford",
    "sg:classifiers":[
        {
            "category":"Shopping",
            "subcategory":"Department Store",
            "type":"Retail Goods"
        }
    ],
    "sg:phone":"+44 1274 726578",
    "sg:postcode":"BD5 0PA",
    "sg:province":"West Yorkshire",
    "wof:name":"Fresh Fare Quality Foods Store",
    "wof:placetype":"venue"
},
  "geometry": {"coordinates":[-1.7656710148,53.7808265686],"type":"Point"}
}