{
  "type": "Feature",
  "properties": {
    "addr:full":"6 Barle Close, Ingleby Barwick Stockton-on-tees Durham TS17 0PL",
    "addr:housenumber":"6",
    "addr:postcode":"ts17 0pl",
    "addr:street":"Barle Close",
    "iso:country":"GB",
    "sg:address":"6 Barle Close, Ingleby Barwick",
    "sg:city":"Stockton-on-tees",
    "sg:classifiers":[
        {
            "category":"Arts & Performance",
            "subcategory":"Music",
            "type":"Entertainment"
        }
    ],
    "sg:phone":"+44 1642 769720",
    "sg:postcode":"TS17 0PL",
    "sg:province":"Durham",
    "sg:tags":[
        "mobile",
        "disco"
    ],
    "wof:name":"Yarm Mobile Disco & Karoake",
    "wof:placetype":"venue"
},
  "geometry": {"coordinates":[-1.30779,54.50816],"type":"Point"}
}