{
  "type": "Feature",
  "properties": {
    "iso:country":"GB",
    "sg:address":"Marshwood Close",
    "sg:city":"Canterbury",
    "sg:classifiers":[
        {
            "category":"Food & Beverages",
            "subcategory":"Supermarket",
            "type":"Retail Goods"
        }
    ],
    "sg:phone":"+44 1227 781310",
    "sg:postcode":"CT1 1DX",
    "sg:province":"Kent",
    "sg:tags":[
        "frozen"
    ],
    "wof:name":"Chaucer Foods",
    "wof:placetype":"venue"
},
  "geometry": {"coordinates":[1.0984239578,51.2909355164],"type":"Point"}
}