{
  "type": "Feature",
  "properties": {
    "iso:country":"GB",
    "sg:address":"Distin House, 111-117 Teignmouth Road",
    "sg:city":"Torquay",
    "sg:classifiers":[
        {
            "category":"Home & Garden",
            "subcategory":"Furniture",
            "type":"Retail Goods"
        }
    ],
    "sg:phone":"+44 1803 311470",
    "sg:postcode":"TQ1 4HA",
    "sg:province":"Devon",
    "wof:name":"Mfi Furniture Centre",
    "wof:placetype":"venue"
},
  "geometry": {"coordinates":[-3.536535,50.47961],"type":"Point"}
}