{
  "type": "Feature",
  "properties": {
    "addr:full":"Unit 2 Guardian Industrial Estate, Patterden Lane, Marden Tonbridge Kent TN12 9QJ",
    "addr:housenumber":"unit 2;estate",
    "addr:postcode":"tn12 9qj",
    "addr:street":"Guardian Industrial;Patterden Lane",
    "iso:country":"GB",
    "sg:address":"Unit 2 Guardian Industrial Estate, Patterden Lane, Marden",
    "sg:city":"Tonbridge",
    "sg:classifiers":[
        {
            "category":"Retail",
            "subcategory":"Veterinary Services",
            "type":"Services"
        }
    ],
    "sg:phone":"+44 1622 832919",
    "sg:postcode":"TN12 9QJ",
    "sg:province":"Kent",
    "sg:tags":[
        "pharmacy"
    ],
    "wof:name":"Burtons Medical Equipment Ltd.",
    "wof:placetype":"venue"
},
  "geometry": {"coordinates":[0.489726007,51.176322937],"type":"Point"}
}