{
  "type": "Feature",
  "properties": {
    "addr:full":"450 Welbeck Road, Walker Newcastle-upon-tyne Tyne and Wear NE6 2NY",
    "addr:housenumber":"450",
    "addr:postcode":"ne6 2ny",
    "addr:street":"Welbeck Road",
    "iso:country":"GB",
    "sg:address":"450 Welbeck Road, Walker",
    "sg:city":"Newcastle-upon-tyne",
    "sg:classifiers":[
        {
            "category":"Shopping",
            "subcategory":"Clothing, Apparel, & Fashions",
            "type":"Retail Goods"
        }
    ],
    "sg:postcode":"NE6 2NY",
    "sg:province":"Tyne and Wear",
    "sg:tags":[
        "shop"
    ],
    "wof:name":"Isobel A Redpath",
    "wof:placetype":"venue"
},
  "geometry": {"coordinates":[-1.5621470213,54.9738998413],"type":"Point"}
}