{
  "type": "Feature",
  "properties": {
    "addr:full":"63 Duke St West End Hampshire W1M 5DH",
    "addr:housenumber":"63",
    "addr:postcode":"w1m 5dh",
    "addr:street":"Duke St",
    "iso:country":"GB",
    "sg:address":"63 Duke St",
    "sg:city":"West End",
    "sg:classifiers":[
        {
            "category":"Utilities",
            "subcategory":"Natural Gas",
            "type":"Services"
        }
    ],
    "sg:phone":"+44 20 7495 3482",
    "sg:postcode":"W1M 5DH",
    "sg:province":"Hampshire",
    "wof:name":"Coalgas plc",
    "wof:placetype":"venue"
},
  "geometry": {"coordinates":[-0.150989,51.513893],"type":"Point"}
}