{
  "type": "Feature",
  "properties": {
    "addr:full":"156 Muller Road, Horfield Bristol City of Bristol BS7 9RE",
    "addr:housenumber":"156",
    "addr:postcode":"bs7 9re",
    "addr:street":"Muller Road",
    "iso:country":"GB",
    "sg:address":"156 Muller Road, Horfield",
    "sg:city":"Bristol",
    "sg:classifiers":[
        {
            "category":"Shopping",
            "subcategory":"News",
            "type":"Retail Goods"
        }
    ],
    "sg:phone":"+44 117 975 5305",
    "sg:postcode":"BS7 9RE",
    "sg:province":"City of Bristol",
    "sg:tags":[
        "newsagent"
    ],
    "wof:name":"S & A News",
    "wof:placetype":"venue"
},
  "geometry": {"coordinates":[-2.579668045,51.4834594727],"type":"Point"}
}