{
  "type": "Feature",
  "properties": {
    "addr:full":"120-130 Kings Road Harrogate North Yorkshire HG1 5HY",
    "addr:housenumber":"120-130",
    "addr:postcode":"hg1 5hy",
    "addr:street":"Kings Road",
    "iso:country":"GB",
    "sg:address":"120-130 Kings Road",
    "sg:city":"Harrogate",
    "sg:classifiers":[
        {
            "category":"Home & Garden",
            "subcategory":"Home Furnishings",
            "type":"Retail Goods"
        }
    ],
    "sg:phone":"+44 1423 568628",
    "sg:postcode":"HG1 5HY",
    "sg:province":"North Yorkshire",
    "sg:tags":[
        "blind",
        "curtain",
        "fitting",
        "soft",
        "sale"
    ],
    "wof:name":"Sandersons Interiors",
    "wof:placetype":"venue"
},
  "geometry": {"coordinates":[-1.5376189947,54.0021896362],"type":"Point"}
}