{
  "type": "Feature",
  "properties": {
    "addr:full":"5 Audreys Court, 153 Great North Road, Eaton Socon St Neots Bedfordshire PE19 8EQ",
    "addr:housenumber":"5;153",
    "addr:postcode":"socon;pe19 8eq",
    "addr:street":"Audreys;Great North Road",
    "iso:country":"GB",
    "sg:address":"5 Audreys Court, 153 Great North Road, Eaton Socon",
    "sg:city":"St Neots",
    "sg:classifiers":[
        {
            "category":"Real Estate",
            "subcategory":"Architect",
            "type":"Services"
        }
    ],
    "sg:postcode":"PE19 8EQ",
    "sg:province":"Bedfordshire",
    "sg:tags":[
        "technologist",
        "architectural"
    ],
    "wof:name":"Keith Hurst Design Ltd.",
    "wof:placetype":"venue"
},
  "geometry": {"coordinates":[-0.289375,52.217472],"type":"Point"}
}