{
  "type": "Feature",
  "properties": {
    "addr:full":"24 Angel Crescent Bridgwater Somerset TA6 3EW",
    "addr:housenumber":"24",
    "addr:postcode":"ta6 3ew",
    "addr:street":"Angel Crescent",
    "iso:country":"GB",
    "sg:address":"24 Angel Crescent",
    "sg:city":"Bridgwater",
    "sg:classifiers":[
        {
            "category":"Wholesale",
            "subcategory":"Machinery & Supplies",
            "type":"Manufacturing & Wholesale Goods"
        }
    ],
    "sg:phone":"+44 1278 455622",
    "sg:postcode":"TA6 3EW",
    "sg:province":"Somerset",
    "sg:tags":[
        "industrial",
        "commercial"
    ],
    "wof:name":"Technical Woodmachinery Sales (Bridgwater) Ltd.",
    "wof:placetype":"venue"
},
  "geometry": {"coordinates":[-3.00567,51.129135],"type":"Point"}
}