{
  "type": "Feature",
  "properties": {
    "addr:full":"52 Clifton Street Blackpool Lancashire FY1 1JP",
    "addr:housenumber":"52",
    "addr:postcode":"fy1 1jp",
    "addr:street":"Clifton Street",
    "iso:country":"GB",
    "sg:address":"52 Clifton Street",
    "sg:city":"Blackpool",
    "sg:classifiers":[
        {
            "category":"Social Services",
            "type":"Services"
        },
        {
            "category":"Utilities",
            "subcategory":"Mobile Phone",
            "type":"Services"
        }
    ],
    "sg:phone":"+44 1253 476451",
    "sg:postcode":"FY1 1JP",
    "sg:province":"Lancashire",
    "sg:tags":[
        "equipment",
        "disability",
        "mobility"
    ],
    "wof:name":"Shopmobility",
    "wof:placetype":"venue"
},
  "geometry": {"coordinates":[-3.0533289909,53.8188285828],"type":"Point"}
}