{
  "type": "Feature",
  "properties": {
    "addr:full":"Centre House 103-107 Irish Street, Dumfries Dumfries Dumfries and Galloway DG1 2NP",
    "addr:housenumber":"103-107",
    "addr:postcode":"dg1 2np",
    "addr:street":"Irish Street",
    "iso:country":"GB",
    "sg:address":"Centre House 103-107 Irish Street, Dumfries",
    "sg:city":"Dumfries",
    "sg:classifiers":[
        {
            "category":"Banks & Credit Unions",
            "subcategory":"Financial Services",
            "type":"Services"
        }
    ],
    "sg:postcode":"DG1 2NP",
    "sg:province":"Dumfries and Galloway",
    "sg:tags":[
        "agent",
        "tied"
    ],
    "wof:name":"Cammeray Investments Ltd.",
    "wof:placetype":"venue"
},
  "geometry": {"coordinates":[-3.6121320724,55.0682754517],"type":"Point"}
}