{
  "type": "Feature",
  "properties": {
    "iso:country":"GB",
    "sg:address":"25 Princess Dr",
    "sg:city":"Leicester",
    "sg:classifiers":[
        {
            "category":"Organizations",
            "subcategory":"Non-profit Organization",
            "type":"Services"
        }
    ],
    "sg:phone":"+44 116 239 5855",
    "sg:postcode":"LE9 2DJ",
    "sg:province":"Leicestershire",
    "sg:tags":[
        "organisation",
        "voluntary",
        "charity"
    ],
    "wof:name":"Kirby Muxloe Youth Project",
    "wof:placetype":"venue"
},
  "geometry": {"coordinates":[-1.235799,52.630692],"type":"Point"}
}