{
  "type": "Feature",
  "properties": {
    "iso:country":"GB",
    "sg:address":"49 Stoney Lane, Yardley",
    "sg:city":"Birmingham",
    "sg:classifiers":[
        {
            "category":"Home & Garden",
            "subcategory":"Home Furnishings",
            "type":"Retail Goods"
        },
        {
            "category":"Home & Garden",
            "subcategory":"Building Materials",
            "type":"Retail Goods"
        }
    ],
    "sg:phone":"+44 121 783 9966",
    "sg:postcode":"B25 8RE",
    "sg:province":"West Midlands",
    "sg:tags":[
        "furnishers",
        "bathroom",
        "planner"
    ],
    "wof:name":"Bathrooms Galore",
    "wof:placetype":"venue"
},
  "geometry": {"coordinates":[-1.8103480339,52.4681434631],"type":"Point"}
}