{
  "type": "Feature",
  "properties": {
    "addr:full":"6 Newmeadow Copse Swindon Wiltshire SN5 5AQ",
    "addr:housenumber":"6",
    "addr:postcode":"sn5 5aq",
    "addr:street":"Newmeadow Copse Swindon",
    "iso:country":"GB",
    "sg:address":"6 Newmeadow Copse",
    "sg:city":"Swindon",
    "sg:classifiers":[
        {
            "category":"Building & Trades",
            "subcategory":"Construction",
            "type":"Services"
        }
    ],
    "sg:phone":"+44 1793 887266",
    "sg:postcode":"SN5 5AQ",
    "sg:province":"Wiltshire",
    "sg:tags":[
        "builder"
    ],
    "wof:name":"Papa Creative Builders",
    "wof:placetype":"venue"
},
  "geometry": {"coordinates":[-1.839622,51.576263],"type":"Point"}
}