{
  "type": "Feature",
  "properties": {
    "addr:full":"Guildford Railway Station, Station Approach Guildford Surrey GU1 4UT",
    "addr:postcode":"gu1 4ut",
    "addr:street":"Station Approach",
    "iso:country":"GB",
    "sg:address":"Guildford Railway Station, Station Approach",
    "sg:city":"Guildford",
    "sg:classifiers":[
        {
            "category":"Retail",
            "subcategory":"Auto Rental",
            "type":"Services"
        }
    ],
    "sg:phone":"+44 1483 536677",
    "sg:postcode":"GU1 4UT",
    "sg:province":"Surrey",
    "sg:tags":[
        "car",
        "vehicle"
    ],
    "sg:website":"http://www.hertz.co.uk",
    "wof:name":"Hertz Rent A Car Ltd",
    "wof:placetype":"venue"
},
  "geometry": {"coordinates":[-0.570516,51.237087],"type":"Point"}
}