{
  "type": "Feature",
  "properties": {
    "addr:full":"126 The Avenue Sunbury-on-thames Surrey TW16 5EA",
    "addr:housenumber":"126",
    "addr:postcode":"tw16 5ea",
    "addr:street":"The Avenue",
    "iso:country":"GB",
    "sg:address":"126 The Avenue",
    "sg:city":"Sunbury-on-thames",
    "sg:classifiers":[
        {
            "category":"Banks & Credit Unions",
            "subcategory":"Financial Services",
            "type":"Services"
        }
    ],
    "sg:postcode":"TW16 5EA",
    "sg:province":"Surrey",
    "sg:tags":[
        "consultant",
        "pension"
    ],
    "wof:name":"Terence E Brand",
    "wof:placetype":"venue"
},
  "geometry": {"coordinates":[-0.409581989,51.4137573242],"type":"Point"}
}