{
  "type": "Feature",
  "properties": {
    "addr:full":"24 Copeland Drive, Standish Wigan Lancashire WN6 0XR",
    "addr:housenumber":"24",
    "addr:postcode":"wn6 0xr",
    "addr:street":"Copeland Drive",
    "iso:country":"GB",
    "sg:address":"24 Copeland Drive, Standish",
    "sg:city":"Wigan",
    "sg:classifiers":[
        {
            "category":"Banks & Credit Unions",
            "subcategory":"Financial Services",
            "type":"Services"
        }
    ],
    "sg:postcode":"WN6 0XR",
    "sg:province":"Lancashire",
    "sg:tags":[
        "consultant"
    ],
    "wof:name":"Coleclough Arkwright Ltd.",
    "wof:placetype":"venue"
},
  "geometry": {"coordinates":[-2.654106,53.589622],"type":"Point"}
}