{
  "type": "Feature",
  "properties": {
    "iso:country":"GB",
    "sg:address":"39 Pannal Ash Drive",
    "sg:city":"Harrogate",
    "sg:classifiers":[
        {
            "category":"Shopping",
            "subcategory":"Musical Instruments",
            "type":"Retail Goods"
        }
    ],
    "sg:postcode":"HG2 0HX",
    "sg:province":"North Yorkshire",
    "wof:name":"Michael S Butterworth",
    "wof:placetype":"venue"
},
  "geometry": {"coordinates":[-1.5527509451,53.9808349609],"type":"Point"}
}