{
  "type": "Feature",
  "properties": {
    "iso:country":"GB",
    "sg:address":"22 Mathew St",
    "sg:city":"Liverpool",
    "sg:classifiers":[
        {
            "category":"Shopping",
            "subcategory":"Department Store",
            "type":"Retail Goods"
        }
    ],
    "sg:postcode":"L2 6RE",
    "sg:province":"Merseyside",
    "wof:name":"Whitby,Simon,",
    "wof:placetype":"venue"
},
  "geometry": {"coordinates":[-2.987522,53.406216],"type":"Point"}
}