{
  "type": "Feature",
  "properties": {
    "addr:full":"46-62 Bank Street Alexandria Argyll and Bute G83 0LS",
    "addr:housenumber":"46-62",
    "addr:postcode":"g83 0ls",
    "addr:street":"Bank Street",
    "iso:country":"GB",
    "sg:address":"46-62 Bank Street",
    "sg:city":"Alexandria",
    "sg:classifiers":[
        {
            "category":"Health Services",
            "subcategory":"Doctor",
            "type":"Services"
        }
    ],
    "sg:phone":"+44 1389 752650",
    "sg:postcode":"G83 0LS",
    "sg:province":"Argyll and Bute",
    "sg:tags":[
        "practitioners"
    ],
    "wof:name":"Dr Gordon Stevenson & Partners",
    "wof:placetype":"venue"
},
  "geometry": {"coordinates":[-4.5799770355,55.9870529175],"type":"Point"}
}