{
  "type": "Feature",
  "properties": {
    "iso:country":"GB",
    "sg:address":"21 Astral View, Wibsey",
    "sg:city":"Bradford",
    "sg:classifiers":[
        {
            "category":"Building & Trades",
            "subcategory":"Construction",
            "type":"Services"
        }
    ],
    "sg:postcode":"BD6 3AL",
    "sg:province":"West Yorkshire",
    "sg:tags":[
        "roofing"
    ],
    "wof:name":"Kenny,Darren,",
    "wof:placetype":"venue"
},
  "geometry": {"coordinates":[-1.781908989,53.7679214478],"type":"Point"}
}