{
  "type": "Feature",
  "properties": {
    "addr:full":"15 Willowcourt Avenue Harrow Greater London HA3 8ER",
    "addr:housenumber":"15",
    "addr:postcode":"ha3 8er",
    "addr:street":"Willowcourt Avenue",
    "iso:country":"GB",
    "sg:address":"15 Willowcourt Avenue",
    "sg:city":"Harrow",
    "sg:classifiers":[
        {
            "category":"Building & Trades",
            "subcategory":"Plumbing",
            "type":"Services"
        }
    ],
    "sg:phone":"+44 20 8907 0701",
    "sg:postcode":"HA3 8ER",
    "sg:province":"Greater London",
    "sg:tags":[
        "heating"
    ],
    "wof:name":"I S Cassidy",
    "wof:placetype":"venue"
},
  "geometry": {"coordinates":[-0.314908,51.584583],"type":"Point"}
}