{
  "type": "Feature",
  "properties": {
    "iso:country":"GB",
    "sg:address":"Gravel Court Farm, Harescombe",
    "sg:city":"Gloucester",
    "sg:classifiers":[
        {
            "category":"Farming",
            "subcategory":"Livestock Farm",
            "type":"Manufacturing & Wholesale Goods"
        }
    ],
    "sg:phone":"+44 1452 813247",
    "sg:postcode":"GL4 0XD",
    "sg:province":"Gloucestershire",
    "sg:tags":[
        "others"
    ],
    "wof:name":"H J Ratcliffe & Partners",
    "wof:placetype":"venue"
},
  "geometry": {"coordinates":[-2.2230739594,51.7901611328],"type":"Point"}
}