{
  "type": "Feature",
  "properties": {
    "addr:full":"16 Killick Road, Hoo Rochester Kent ME3 9ER",
    "addr:housenumber":"16",
    "addr:postcode":"me3 9er",
    "addr:street":"Killick Road",
    "iso:country":"GB",
    "sg:address":"16 Killick Road, Hoo",
    "sg:city":"Rochester",
    "sg:classifiers":[
        {
            "category":"Professional",
            "subcategory":"Printing & Photocopies",
            "type":"Services"
        }
    ],
    "sg:phone":"+44 1634 254452",
    "sg:postcode":"ME3 9ER",
    "sg:province":"Kent",
    "sg:tags":[
        "duplicating",
        "copying"
    ],
    "wof:name":"Willow Copiers & Business Equipment",
    "wof:placetype":"venue"
},
  "geometry": {"coordinates":[0.558331,51.421997],"type":"Point"}
}