{
  "type": "Feature",
  "properties": {
    "addr:full":"29 Townhead Street Cumnock East Ayrshire KA18 1LA",
    "addr:housenumber":"29",
    "addr:postcode":"ka18 1la",
    "addr:street":"Townhead Street",
    "iso:country":"GB",
    "sg:address":"29 Townhead Street",
    "sg:city":"Cumnock",
    "sg:classifiers":[
        {
            "category":"Cinema",
            "subcategory":"Movie Rental",
            "type":"Entertainment"
        }
    ],
    "sg:phone":"+44 1290 420753",
    "sg:postcode":"KA18 1LA",
    "sg:province":"East Ayrshire",
    "sg:tags":[
        "video",
        "library"
    ],
    "wof:name":"Video West",
    "wof:placetype":"venue"
},
  "geometry": {"coordinates":[-4.2631411552,55.4544944763],"type":"Point"}
}