{
  "type": "Feature",
  "properties": {
    "addr:full":"Waveney Drive Lowestoft Suffolk NR33 0TS",
    "addr:postcode":"nr33 0ts",
    "addr:street":"Waveney Drive",
    "iso:country":"GB",
    "sg:address":"Waveney Drive",
    "sg:city":"Lowestoft",
    "sg:classifiers":[
        {
            "category":"Military Area",
            "subcategory":"Army Base",
            "type":"Public Place"
        }
    ],
    "sg:phone":"+44 1502 573461",
    "sg:postcode":"NR33 0TS",
    "sg:province":"Suffolk",
    "sg:tags":[
        "joinery",
        "centre"
    ],
    "wof:name":"Rugby Joinery",
    "wof:placetype":"venue"
},
  "geometry": {"coordinates":[1.7384660244,52.4707489014],"type":"Point"}
}