{
  "type": "Feature",
  "properties": {
    "addr:full":", Bradford Holsworthy Cornwall EX22 7AN",
    "addr:postcode":"ex22 7an",
    "iso:country":"GB",
    "sg:address":", Bradford",
    "sg:city":"Holsworthy",
    "sg:classifiers":[
        {
            "category":"Travel",
            "subcategory":"Hotels & Motels",
            "type":"Entertainment"
        }
    ],
    "sg:phone":"+44 1409 281386",
    "sg:postcode":"EX22 7AN",
    "sg:province":"Cornwall",
    "sg:tags":[
        "house",
        "guest"
    ],
    "wof:name":"Priestacott House",
    "wof:placetype":"venue"
},
  "geometry": {"coordinates":[-4.245068,50.842491],"type":"Point"}
}