{
  "type": "Feature",
  "properties": {
    "iso:country":"GB",
    "sg:address":"Victoria Road",
    "sg:city":"Bexhill-on-sea",
    "sg:classifiers":[
        {
            "category":"Home & Garden",
            "subcategory":"Home Furnishings",
            "type":"Retail Goods"
        }
    ],
    "sg:phone":"+44 1424 215015",
    "sg:postcode":"TN39 3PD",
    "sg:province":"East Sussex",
    "sg:tags":[
        "homefurnishings"
    ],
    "wof:name":"Woodstocks",
    "wof:placetype":"venue"
},
  "geometry": {"coordinates":[0.4689500034,50.8420066833],"type":"Point"}
}