{
  "type": "Feature",
  "properties": {
    "addr:full":"76 Burnbank Centre Hamilton South Lanarkshire ML3 0NA",
    "addr:housenumber":"76",
    "addr:postcode":"ml3 0na",
    "addr:street":"Burnbank Centre",
    "iso:country":"GB",
    "sg:address":"76 Burnbank Centre",
    "sg:city":"Hamilton",
    "sg:classifiers":[
        {
            "category":"Education",
            "subcategory":"Library",
            "type":"Public Place"
        },
        {
            "category":"Government",
            "subcategory":"Office",
            "type":"Public Place"
        }
    ],
    "sg:phone":"+44 1698 285730",
    "sg:postcode":"ML3 0NA",
    "sg:province":"South Lanarkshire",
    "sg:tags":[
        "book",
        "local"
    ],
    "wof:name":"Burnbank Library",
    "wof:placetype":"venue"
},
  "geometry": {"coordinates":[-4.066435,55.781086],"type":"Point"}
}