{
  "type": "Feature",
  "properties": {
    "iso:country":"GB",
    "sg:address":"29 High Road",
    "sg:city":"Broxbourne",
    "sg:classifiers":[
        {
            "category":"Fast Food",
            "type":"Food & Drink"
        }
    ],
    "sg:phone":"+44 1992 451148",
    "sg:postcode":"EN10 7HX",
    "sg:province":"Essex",
    "sg:tags":[
        "away",
        "take"
    ],
    "wof:name":"H F Chan",
    "wof:placetype":"venue"
},
  "geometry": {"coordinates":[-0.015664,51.752079],"type":"Point"}
}