{
  "type": "Feature",
  "properties": {
    "addr:full":"Church Hill, Wolvley Hinckley Leicestershire LE10 3LB",
    "addr:postcode":"le10 3lb",
    "addr:street":"Church Hill Wolvley",
    "iso:country":"GB",
    "sg:address":"Church Hill, Wolvley",
    "sg:city":"Hinckley",
    "sg:classifiers":[
        {
            "category":"Utilities",
            "subcategory":"Refuse",
            "type":"Services"
        }
    ],
    "sg:phone":"+44 1455 220672",
    "sg:postcode":"LE10 3LB",
    "sg:province":"Leicestershire",
    "sg:tags":[
        "skip",
        "hire"
    ],
    "wof:name":"Unique Industrial Cleaners",
    "wof:placetype":"venue"
},
  "geometry": {"coordinates":[-1.3678289652,52.4888687134],"type":"Point"}
}