{
  "type": "Feature",
  "properties": {
    "addr:full":"24 St Albans Road Bristol City of Bristol BS6 7SJ",
    "addr:housenumber":"24",
    "addr:postcode":"bs6 7sj",
    "addr:street":"St Albans Road",
    "iso:country":"GB",
    "sg:address":"24 St Albans Road",
    "sg:city":"Bristol",
    "sg:classifiers":[
        {
            "category":"Professional",
            "type":"Services"
        }
    ],
    "sg:phone":"+44 117 942 5331",
    "sg:postcode":"BS6 7SJ",
    "sg:province":"City of Bristol",
    "sg:tags":[
        "exhibition"
    ],
    "wof:name":"Expose",
    "wof:placetype":"venue"
},
  "geometry": {"coordinates":[-2.609207,51.47855],"type":"Point"}
}