{
  "type": "Feature",
  "properties": {
    "addr:full":"19 Radcliffe Street, Wolverton Milton Keynes Buckinghamshire MK12 5DQ",
    "addr:housenumber":"19",
    "addr:postcode":"mk12 5dq",
    "addr:street":"Radcliffe Street",
    "iso:country":"GB",
    "sg:address":"19 Radcliffe Street, Wolverton",
    "sg:city":"Milton Keynes",
    "sg:classifiers":[
        {
            "category":"Sports & Exercise",
            "subcategory":"Sports Center",
            "type":"Entertainment"
        }
    ],
    "sg:postcode":"MK12 5DQ",
    "sg:province":"Buckinghamshire",
    "sg:tags":[
        "shop",
        "good"
    ],
    "wof:name":"Protex Sports",
    "wof:placetype":"venue"
},
  "geometry": {"coordinates":[-0.8096370101,52.0610198975],"type":"Point"}
}