{
  "type": "Feature",
  "properties": {
    "addr:full":"75-79 Broadway Market, Tooting High Street London Greater London SW17 0RJ",
    "addr:housenumber":"75-79",
    "addr:postcode":"sw17 0rj",
    "addr:street":"Broadway Market Tooting High Street",
    "iso:country":"GB",
    "sg:address":"75-79 Broadway Market, Tooting High Street",
    "sg:city":"London",
    "sg:classifiers":[
        {
            "category":"Shopping",
            "subcategory":"Clothing, Apparel, & Fashions",
            "type":"Retail Goods"
        }
    ],
    "sg:phone":"+44 20 8672 9638",
    "sg:postcode":"SW17 0RJ",
    "sg:province":"Greater London",
    "sg:tags":[
        "lingerie",
        "hosiery"
    ],
    "wof:name":"J & J Clobber",
    "wof:placetype":"venue"
},
  "geometry": {"coordinates":[-0.1664600074,51.4286804199],"type":"Point"}
}