{
  "type": "Feature",
  "properties": {
    "addr:full":"160 Westminster Rd Birmingham West Midlands B20 3NA",
    "addr:housenumber":"160",
    "addr:postcode":"b20 3na",
    "addr:street":"Westminster Rd",
    "iso:country":"GB",
    "sg:address":"160 Westminster Rd",
    "sg:city":"Birmingham",
    "sg:classifiers":[
        {
            "category":"Shopping",
            "subcategory":"Pharmacy",
            "type":"Retail Goods"
        }
    ],
    "sg:phone":"+44 121 356 5588",
    "sg:postcode":"B20 3NA",
    "sg:province":"West Midlands",
    "sg:tags":[
        "medicine",
        "therapy"
    ],
    "wof:name":"Centre Of Reflexology & Aromatherapy",
    "wof:placetype":"venue"
},
  "geometry": {"coordinates":[-1.909375,52.514446],"type":"Point"}
}