{
  "type": "Feature",
  "properties": {
    "addr:full":"210 Park Road, South Moor Stanley Durham DH9 7AW",
    "addr:housenumber":"210",
    "addr:postcode":"dh9 7aw",
    "addr:street":"Park Road South Moor Stanley",
    "iso:country":"GB",
    "sg:address":"210 Park Road, South Moor",
    "sg:city":"Stanley",
    "sg:classifiers":[
        {
            "category":"Shopping",
            "subcategory":"Department Store",
            "type":"Retail Goods"
        }
    ],
    "sg:postcode":"DH9 7AW",
    "sg:province":"Durham",
    "wof:name":"Kenneth Richardson",
    "wof:placetype":"venue"
},
  "geometry": {"coordinates":[-1.7055389881,54.8611907959],"type":"Point"}
}