{
  "type": "Feature",
  "properties": {
    "iso:country":"GB",
    "sg:address":"93 Hampton Rd, Hampton Hill",
    "sg:city":"Hampton",
    "sg:classifiers":[
        {
            "category":"Professional",
            "subcategory":"Accounting & Tax Preparation",
            "type":"Services"
        }
    ],
    "sg:postcode":"TW12 1JQ",
    "sg:province":"Greater London",
    "sg:tags":[
        "accountant"
    ],
    "wof:name":"Robinson,Ian,",
    "wof:placetype":"venue"
},
  "geometry": {"coordinates":[-0.352119,51.428638],"type":"Point"}
}