{
  "type": "Feature",
  "properties": {
    "iso:country":"GB",
    "sg:address":"6 Woodside Avenue, Fulwood",
    "sg:city":"Preston",
    "sg:classifiers":[
        {
            "category":"Building & Trades",
            "subcategory":"Construction",
            "type":"Services"
        }
    ],
    "sg:phone":"+44 1772 719437",
    "sg:postcode":"PR2 8JY",
    "sg:province":"Lancashire",
    "sg:tags":[
        "joinery",
        "joiner",
        "carpenter",
        "carpentry"
    ],
    "wof:name":"G Hargreaves",
    "wof:placetype":"venue"
},
  "geometry": {"coordinates":[-2.710827,53.779423],"type":"Point"}
}