{
  "type": "Feature",
  "properties": {
    "addr:full":"13 London Road Brighton East Sussex BN1 4JA",
    "addr:housenumber":"13",
    "addr:postcode":"bn1 4ja",
    "addr:street":"London Road",
    "iso:country":"GB",
    "sg:address":"13 London Road",
    "sg:city":"Brighton",
    "sg:classifiers":[
        {
            "category":"Shopping",
            "subcategory":"Clothing, Apparel, & Fashions",
            "type":"Retail Goods"
        }
    ],
    "sg:phone":"+44 1273 682435",
    "sg:postcode":"BN1 4JA",
    "sg:province":"East Sussex",
    "sg:tags":[
        "shop"
    ],
    "wof:name":"Happit Ltd.",
    "wof:placetype":"venue"
},
  "geometry": {"coordinates":[-0.1362240016,50.8303947449],"type":"Point"}
}