{
  "type": "Feature",
  "properties": {
    "addr:full":"Stretchdown Farm, Stretchdown, Witheridge Tiverton Devon EX16 8PD",
    "addr:postcode":"ex16 8pd",
    "addr:street":"Witheridge",
    "iso:country":"GB",
    "sg:address":"Stretchdown Farm, Stretchdown, Witheridge",
    "sg:city":"Tiverton",
    "sg:classifiers":[
        {
            "category":"Autos & Motor Vehicles",
            "subcategory":"Automobile Sales",
            "type":"Retail Goods"
        }
    ],
    "sg:postcode":"EX16 8PD",
    "sg:province":"Devon",
    "sg:tags":[
        "car"
    ],
    "wof:name":"M & M Trading",
    "wof:placetype":"venue"
},
  "geometry": {"coordinates":[-3.700682,50.916611],"type":"Point"}
}