{
  "type": "Feature",
  "properties": {
    "iso:country":"GB",
    "sg:address":"Basement Office, 3 Waterloo Crescent",
    "sg:city":"Dover",
    "sg:classifiers":[
        {
            "category":"Professional",
            "type":"Services"
        }
    ],
    "sg:phone":"+44 1304 227000",
    "sg:postcode":"CT16 1LA",
    "sg:province":"Kent",
    "sg:tags":[
        "archaeologist"
    ],
    "wof:name":"Canterbury Archaeological Trust Ltd",
    "wof:placetype":"venue"
},
  "geometry": {"coordinates":[1.328761,51.126846],"type":"Point"}
}