{
  "type": "Feature",
  "properties": {
    "addr:full":"High Birch Terrace Rochdale Lancashire OL11 4RA",
    "addr:postcode":"ol11 4ra",
    "addr:street":"Birch Terrace",
    "iso:country":"GB",
    "sg:address":"High Birch Terrace",
    "sg:city":"Rochdale",
    "sg:classifiers":[
        {
            "category":"Education",
            "subcategory":"School",
            "type":"Public Place"
        },
        {
            "category":"Government",
            "subcategory":"Office",
            "type":"Public Place"
        }
    ],
    "sg:phone":"+44 1706 631752",
    "sg:postcode":"OL11 4RA",
    "sg:province":"Lancashire",
    "sg:tags":[
        "local",
        "authority"
    ],
    "wof:name":"Rochdale Metropolitan Borough Council",
    "wof:placetype":"venue"
},
  "geometry": {"coordinates":[-2.1853199005,53.6042404175],"type":"Point"}
}