{
  "type": "Feature",
  "properties": {
    "iso:country":"GB",
    "sg:address":"Alverstone Road",
    "sg:city":"East Cowes",
    "sg:classifiers":[
        {
            "category":"Manufacturing",
            "subcategory":"Metals",
            "type":"Manufacturing & Wholesale Goods"
        }
    ],
    "sg:postcode":"PO32 6NZ",
    "sg:province":"Isle of Wight",
    "sg:tags":[
        "steel",
        "fabricator",
        "erectors"
    ],
    "wof:name":"Michael Augustus",
    "wof:placetype":"venue"
},
  "geometry": {"coordinates":[-1.265277,50.736828],"type":"Point"}
}