{
  "type": "Feature",
  "properties": {
    "addr:full":"39 Burton Street, Tutbury Burton-on-trent Derbyshire DE13 9NR",
    "addr:housenumber":"39",
    "addr:postcode":"de13 9nr",
    "addr:street":"Burton Street",
    "iso:country":"GB",
    "sg:address":"39 Burton Street, Tutbury",
    "sg:city":"Burton-on-trent",
    "sg:classifiers":[
        {
            "category":"Restaurant",
            "type":"Food & Drink"
        }
    ],
    "sg:postcode":"DE13 9NR",
    "sg:province":"Derbyshire",
    "wof:name":"The Cross Keys",
    "wof:placetype":"venue"
},
  "geometry": {"coordinates":[-1.6832369566,52.8560295105],"type":"Point"}
}