{
  "type": "Feature",
  "properties": {
    "addr:full":"Hodee, Frensham Road Cranbrook Kent TN17 4NJ",
    "addr:postcode":"tn17 4nj",
    "addr:street":"Frensham Road",
    "iso:country":"GB",
    "sg:address":"Hodee, Frensham Road",
    "sg:city":"Cranbrook",
    "sg:classifiers":[
        {
            "category":"Building & Trades",
            "subcategory":"Construction",
            "type":"Services"
        }
    ],
    "sg:postcode":"TN17 4NJ",
    "sg:province":"Kent",
    "sg:tags":[
        "decorator",
        "painter"
    ],
    "wof:name":"Colour Your World Decorators",
    "wof:placetype":"venue"
},
  "geometry": {"coordinates":[0.6418579817,51.0420608521],"type":"Point"}
}