{
  "type": "Feature",
  "properties": {
    "addr:full":"Milestone Bullington, Sutton Scotney Winchester Hampshire SO21 3RB",
    "addr:postcode":"so21 3rb",
    "iso:country":"GB",
    "sg:address":"Milestone Bullington, Sutton Scotney",
    "sg:city":"Winchester",
    "sg:classifiers":[
        {
            "category":"Home & Garden",
            "subcategory":"Garden Supply",
            "type":"Retail Goods"
        }
    ],
    "sg:postcode":"SO21 3RB",
    "sg:province":"Hampshire",
    "sg:tags":[
        "bulb",
        "grower"
    ],
    "wof:name":"Bullington Manor Farms",
    "wof:placetype":"venue"
},
  "geometry": {"coordinates":[-1.3379809856,51.1522064209],"type":"Point"}
}