{
  "type": "Feature",
  "properties": {
    "addr:full":"Trench Road, Trench Telford Shropshire TF2 7DX",
    "addr:postcode":"tf2 7dx",
    "addr:street":"Trench Road",
    "iso:country":"GB",
    "sg:address":"Trench Road, Trench",
    "sg:city":"Telford",
    "sg:classifiers":[
        {
            "category":"Bars & Pubs",
            "type":"Food & Drink"
        }
    ],
    "sg:phone":"+44 1952 605711",
    "sg:postcode":"TF2 7DX",
    "sg:province":"Shropshire",
    "sg:tags":[
        "pubs",
        "inn"
    ],
    "wof:name":"Old Shawbirch Inn",
    "wof:placetype":"venue"
},
  "geometry": {"coordinates":[-2.4486138821,52.7158660889],"type":"Point"}
}