{
  "type": "Feature",
  "properties": {
    "addr:full":"Unit 1, Charles Industrial Estate, Stowupland Road Stowmarket Suffolk IP14 5AH",
    "addr:housenumber":"unit 1",
    "addr:postcode":"ip14 5ah",
    "addr:street":"Charles Industrial Estate Stowupland Road",
    "iso:country":"GB",
    "sg:address":"Unit 1, Charles Industrial Estate, Stowupland Road",
    "sg:city":"Stowmarket",
    "sg:classifiers":[
        {
            "category":"Retail",
            "subcategory":"Event Space",
            "type":"Services"
        },
        {
            "category":"Shopping",
            "subcategory":"Computers & Home Electronics",
            "type":"Retail Goods"
        }
    ],
    "sg:phone":"+44 1449 678639",
    "sg:postcode":"IP14 5AH",
    "sg:province":"Suffolk",
    "sg:tags":[
        "product",
        "electrical",
        "sales"
    ],
    "wof:name":"P M E ELECTRICAL WHOLESALE",
    "wof:placetype":"venue"
},
  "geometry": {"coordinates":[0.996769011,52.1886253357],"type":"Point"}
}