{
  "type": "Feature",
  "properties": {
    "iso:country":"GB",
    "sg:address":"Railway Goods Yard, Crosshills",
    "sg:city":"Keighley",
    "sg:classifiers":[
        {
            "category":"Retail",
            "subcategory":"Auto Repair",
            "type":"Services"
        }
    ],
    "sg:postcode":"BD20 7DA",
    "sg:province":"North Yorkshire",
    "sg:tags":[
        "bodybuilder",
        "repairer"
    ],
    "wof:name":"Aire Valley Commercials",
    "wof:placetype":"venue"
},
  "geometry": {"coordinates":[-1.9899300337,53.9019393921],"type":"Point"}
}