{
  "type": "Feature",
  "properties": {
    "addr:full":"45 Bloomfield St North Halesowen West Midlands B63 3RE",
    "addr:housenumber":"45",
    "addr:postcode":"b63 3re",
    "addr:street":"Bloomfield St",
    "iso:country":"GB",
    "sg:address":"45 Bloomfield St North",
    "sg:city":"Halesowen",
    "sg:classifiers":[
        {
            "category":"Education",
            "subcategory":"Music School",
            "type":"Public Place"
        }
    ],
    "sg:postcode":"B63 3RE",
    "sg:province":"West Midlands",
    "sg:tags":[
        "teacher"
    ],
    "wof:name":"Organ & Keyboard Tuition",
    "wof:placetype":"venue"
},
  "geometry": {"coordinates":[-2.061164,52.454685],"type":"Point"}
}