{
  "type": "Feature",
  "properties": {
    "iso:country":"GB",
    "sg:address":"Glen House, High St",
    "sg:city":"Banstead",
    "sg:classifiers":[
        {
            "category":"Social Services",
            "type":"Services"
        }
    ],
    "sg:phone":"+44 1737 379902",
    "sg:postcode":"SM7 2LH",
    "sg:province":"Surrey",
    "wof:name":"Home-start Epsom Banstead & Ewell",
    "wof:placetype":"venue"
},
  "geometry": {"coordinates":[-0.195663,51.324425],"type":"Point"}
}