{
  "type": "Feature",
  "properties": {
    "addr:full":"121 Shenley Road Borehamwood Hertfordshire WD6 1AG",
    "addr:housenumber":"121",
    "addr:postcode":"wd6 1ag",
    "addr:street":"Shenley Road",
    "iso:country":"GB",
    "sg:address":"121 Shenley Road",
    "sg:city":"Borehamwood",
    "sg:classifiers":[
        {
            "category":"Food & Beverages",
            "subcategory":"Bakery",
            "type":"Retail Goods"
        }
    ],
    "sg:phone":"+44 20 8953 5737",
    "sg:postcode":"WD6 1AG",
    "sg:province":"Hertfordshire",
    "sg:tags":[
        "baker"
    ],
    "wof:name":"G J Pearce Ltd.",
    "wof:placetype":"venue"
},
  "geometry": {"coordinates":[-0.2751590014,51.6562843323],"type":"Point"}
}