{
  "type": "Feature",
  "properties": {
    "iso:country":"GB",
    "sg:address":"7 Inveralmond Road, Inveralmond Industrial Estate",
    "sg:city":"Perth",
    "sg:classifiers":[
        {
            "category":"Food & Beverages",
            "subcategory":"Supermarket",
            "type":"Retail Goods"
        }
    ],
    "sg:phone":"+44 1738 449779",
    "sg:postcode":"PH1 3TW",
    "sg:province":"Perth and Kinross",
    "sg:tags":[
        "frozen"
    ],
    "wof:name":"Irvine Patisserie Ltd.",
    "wof:placetype":"venue"
},
  "geometry": {"coordinates":[-3.480984,56.417919],"type":"Point"}
}