{
  "type": "Feature",
  "properties": {
    "addr:full":"118 Ballards Lane London Greater London N3 2DN",
    "addr:housenumber":"118",
    "addr:postcode":"n3 2dn",
    "addr:street":"Ballards Lane",
    "iso:country":"GB",
    "sg:address":"118 Ballards Lane",
    "sg:city":"London",
    "sg:classifiers":[
        {
            "category":"Cafe",
            "type":"Food & Drink"
        }
    ],
    "sg:postcode":"N3 2DN",
    "sg:province":"Greater London",
    "sg:tags":[
        "tea",
        "room"
    ],
    "wof:name":"SHANDIZ COFFEE SHOP",
    "wof:placetype":"venue"
},
  "geometry": {"coordinates":[-0.188982,51.604408],"type":"Point"}
}