{
  "type": "Feature",
  "properties": {
    "iso:country":"GB",
    "sg:address":"2 Beachfield Court",
    "sg:city":"Penzance",
    "sg:classifiers":[
        {
            "category":"Recreation",
            "subcategory":"Dog Park",
            "type":"Entertainment"
        }
    ],
    "sg:phone":"+44 1736 364242",
    "sg:postcode":"TR18 4NQ",
    "sg:province":"Cornwall",
    "wof:name":"Head to Tail",
    "wof:placetype":"venue"
},
  "geometry": {"coordinates":[-5.5415887833,50.1122016907],"type":"Point"}
}