{
  "type": "Feature",
  "properties": {
    "addr:full":"285 London Road Sheffield South Yorkshire S2 4NF",
    "addr:housenumber":"285",
    "addr:postcode":"s2 4nf",
    "addr:street":"London Road",
    "iso:country":"GB",
    "sg:address":"285 London Road",
    "sg:city":"Sheffield",
    "sg:classifiers":[
        {
            "category":"Professional",
            "subcategory":"Lawyer & Legal Services",
            "type":"Services"
        }
    ],
    "sg:phone":"+44 114 255 8001",
    "sg:postcode":"S2 4NF",
    "sg:province":"South Yorkshire",
    "sg:tags":[
        "solicitor"
    ],
    "wof:name":"Athi Kulisra Smith",
    "wof:placetype":"venue"
},
  "geometry": {"coordinates":[-1.474704,53.366505],"type":"Point"}
}