{
  "type": "Feature",
  "properties": {
    "addr:full":"Green Lane Worcester Park Surrey KT4 8AJ",
    "addr:postcode":"kt4 8aj",
    "addr:street":"Green Lane",
    "iso:country":"GB",
    "sg:address":"Green Lane",
    "sg:city":"Worcester Park",
    "sg:classifiers":[
        {
            "category":"Arena",
            "subcategory":"Sports Club",
            "type":"Entertainment"
        }
    ],
    "sg:phone":"+44 20 8337 4995",
    "sg:postcode":"KT4 8AJ",
    "sg:province":"Surrey",
    "sg:tags":[
        "ground"
    ],
    "wof:name":"Worcester Park Athletic Club",
    "wof:placetype":"venue"
},
  "geometry": {"coordinates":[-0.2390059978,51.3851356506],"type":"Point"}
}