{
  "type": "Feature",
  "properties": {
    "addr:full":"41 Beaver Shopping Centre Coalville Leicestershire LE67 3XF",
    "addr:housenumber":"41",
    "addr:postcode":"le67 3xf",
    "addr:street":"Beaver Shopping",
    "iso:country":"GB",
    "sg:address":"41 Beaver Shopping Centre",
    "sg:city":"Coalville",
    "sg:classifiers":[
        {
            "category":"Shopping",
            "subcategory":"Shoes",
            "type":"Retail Goods"
        }
    ],
    "sg:phone":"+44 1530 813536",
    "sg:postcode":"LE67 3XF",
    "sg:province":"Leicestershire",
    "sg:tags":[
        "shop"
    ],
    "wof:name":"Oliver Timpson",
    "wof:placetype":"venue"
},
  "geometry": {"coordinates":[-1.3735389709,52.7253303528],"type":"Point"}
}