{
  "type": "Feature",
  "properties": {
    "addr:full":"157 Stoke Newington Church Stree London Greater London N16 0UH",
    "addr:housenumber":"157",
    "addr:postcode":"n16 0uh",
    "addr:street":"Stoke Newington;Stree",
    "iso:country":"GB",
    "sg:address":"157 Stoke Newington Church Stree",
    "sg:city":"London",
    "sg:classifiers":[
        {
            "category":"Shopping",
            "subcategory":"Clothing, Apparel, & Fashions",
            "type":"Retail Goods"
        }
    ],
    "sg:postcode":"N16 0UH",
    "sg:province":"Greater London",
    "sg:tags":[
        "shop"
    ],
    "wof:name":"Ribbons & Taylor Vintage Clothing",
    "wof:placetype":"venue"
},
  "geometry": {"coordinates":[-0.081901,51.561367],"type":"Point"}
}