{
  "type": "Feature",
  "properties": {
    "iso:country":"GB",
    "sg:address":"2 Camberwell Church Street, Camberwell",
    "sg:city":"London",
    "sg:classifiers":[
        {
            "category":"Professional",
            "subcategory":"Lawyer & Legal Services",
            "type":"Services"
        }
    ],
    "sg:postcode":"SE5 8QU",
    "sg:province":"Greater London",
    "sg:tags":[
        "solicitor"
    ],
    "wof:name":"Hartnells",
    "wof:placetype":"venue"
},
  "geometry": {"coordinates":[-0.092058,51.474033],"type":"Point"}
}