{
  "type": "Feature",
  "properties": {
    "addr:full":"17-19 Lever Street London Greater London EC1V 3QU",
    "addr:housenumber":"17-19",
    "addr:postcode":"ec1v 3qu",
    "addr:street":"Lever Street",
    "iso:country":"GB",
    "sg:address":"17-19 Lever Street",
    "sg:city":"London",
    "sg:classifiers":[
        {
            "category":"Manufacturing",
            "subcategory":"Jewelry",
            "type":"Manufacturing & Wholesale Goods"
        }
    ],
    "sg:phone":"+44 20 7253 8322",
    "sg:postcode":"EC1V 3QU",
    "sg:province":"Greater London",
    "sg:tags":[
        "repair",
        "jewellery"
    ],
    "wof:name":"Paul Slade & Co. Ltd.",
    "wof:placetype":"venue"
},
  "geometry": {"coordinates":[-0.099244,51.52655],"type":"Point"}
}