{
  "type": "Feature",
  "properties": {
    "addr:full":"Grafton House, Bulls Head Yard Alcester Warwickshire B49 5BX",
    "addr:postcode":"b49 5bx",
    "iso:country":"GB",
    "sg:address":"Grafton House, Bulls Head Yard",
    "sg:city":"Alcester",
    "sg:classifiers":[
        {
            "category":"Shopping",
            "subcategory":"Bicycles & Sporting Goods",
            "type":"Retail Goods"
        }
    ],
    "sg:postcode":"B49 5BX",
    "sg:province":"Warwickshire",
    "sg:tags":[
        "riding",
        "saddlery",
        "wear"
    ],
    "wof:name":"Alcester Riding Supplies",
    "wof:placetype":"venue"
},
  "geometry": {"coordinates":[-1.871267,52.215553],"type":"Point"}
}