{
  "type": "Feature",
  "properties": {
    "iso:country":"GB",
    "sg:address":"26 Carlton Mansions, Randolph Avenue",
    "sg:city":"London",
    "sg:classifiers":[
        {
            "category":"Professional",
            "subcategory":"Management & Consulting",
            "type":"Services"
        }
    ],
    "sg:postcode":"W9 1NP",
    "sg:province":"Greater London",
    "sg:tags":[
        "consultant",
        "business"
    ],
    "wof:name":"Chiswell Consultancy Services Ltd",
    "wof:placetype":"venue"
},
  "geometry": {"coordinates":[-0.18871,51.531799],"type":"Point"}
}