{
  "type": "Feature",
  "properties": {
    "addr:full":"Torcross Kingsbridge Devon TQ7 2TH",
    "addr:postcode":"tq7 2th",
    "addr:street":"Torcross",
    "iso:country":"GB",
    "sg:address":"Torcross",
    "sg:city":"Kingsbridge",
    "sg:classifiers":[
        {
            "category":"Travel",
            "subcategory":"Hotels & Motels",
            "type":"Entertainment"
        }
    ],
    "sg:phone":"+44 1548 580220",
    "sg:postcode":"TQ7 2TH",
    "sg:province":"Devon",
    "wof:name":"Greyhomes Hotel",
    "wof:placetype":"venue"
},
  "geometry": {"coordinates":[-3.655654,50.26799],"type":"Point"}
}