{
  "type": "Feature",
  "properties": {
    "addr:full":"106 High Street Invergordon Highland IV18 0DR",
    "addr:housenumber":"106",
    "addr:postcode":"iv18 0dr",
    "addr:street":"High Street",
    "iso:country":"GB",
    "sg:address":"106 High Street",
    "sg:city":"Invergordon",
    "sg:classifiers":[
        {
            "category":"Shopping",
            "subcategory":"Department Store",
            "type":"Retail Goods"
        },
        {
            "category":"Shopping",
            "subcategory":"Jewelry",
            "type":"Retail Goods"
        }
    ],
    "sg:phone":"+44 1349 852212",
    "sg:postcode":"IV18 0DR",
    "sg:province":"Highland",
    "sg:tags":[
        "sale",
        "jewellery"
    ],
    "wof:name":"M A Forbes",
    "wof:placetype":"venue"
},
  "geometry": {"coordinates":[-4.1662,57.68853],"type":"Point"}
}