{
  "type": "Feature",
  "properties": {
    "addr:full":"South Lasts Farm Milltimber Aberdeen City AB13 0ES",
    "addr:postcode":"ab13 0es",
    "addr:street":"South Lasts;Milltimber",
    "iso:country":"GB",
    "sg:address":"South Lasts Farm",
    "sg:city":"Milltimber",
    "sg:classifiers":[
        {
            "category":"Farming",
            "subcategory":"Farm",
            "type":"Manufacturing & Wholesale Goods"
        }
    ],
    "sg:phone":"+44 1224 733898",
    "sg:postcode":"AB13 0ES",
    "sg:province":"Aberdeen City",
    "sg:tags":[
        "mixed",
        "crop"
    ],
    "wof:name":"JOSEPH DOW",
    "wof:placetype":"venue"
},
  "geometry": {"coordinates":[-2.2343389988,57.1043434143],"type":"Point"}
}