{
  "type": "Feature",
  "properties": {
    "addr:full":"Whiteshill House, Whiteshill Common, Hambrook Bristol City of Bristol BS16 1SD",
    "addr:postcode":"bs16 1sd",
    "addr:street":"Whiteshill Common",
    "iso:country":"GB",
    "sg:address":"Whiteshill House, Whiteshill Common, Hambrook",
    "sg:city":"Bristol",
    "sg:classifiers":[
        {
            "category":"Health Services",
            "subcategory":"Nursing And Care Facility",
            "type":"Services"
        }
    ],
    "sg:phone":"+44 117 956 8475",
    "sg:postcode":"BS16 1SD",
    "sg:province":"City of Bristol",
    "sg:tags":[
        "home"
    ],
    "wof:name":"Community Care Concern Ltd",
    "wof:placetype":"venue"
},
  "geometry": {"coordinates":[-2.512944,51.510685],"type":"Point"}
}