{
  "type": "Feature",
  "properties": {
    "iso:country":"GB",
    "sg:address":"Coed Mawr",
    "sg:city":"Llanwrtyd Wells",
    "sg:classifiers":[
        {
            "category":"Farming",
            "subcategory":"Farm",
            "type":"Manufacturing & Wholesale Goods"
        }
    ],
    "sg:phone":"+44 1591 620244",
    "sg:postcode":"LD5 4TY",
    "sg:province":"Powys",
    "sg:tags":[
        "hatchery"
    ],
    "wof:name":"Wye Valley Fisheries",
    "wof:placetype":"venue"
},
  "geometry": {"coordinates":[-3.6251618862,52.1359786987],"type":"Point"}
}