{
  "type": "Feature",
  "properties": {
    "addr:full":"36 Biggin Street Dover Kent CT16 1BU",
    "addr:housenumber":"36",
    "addr:postcode":"ct16 1bu",
    "addr:street":"Biggin Street",
    "iso:country":"GB",
    "sg:address":"36 Biggin Street",
    "sg:city":"Dover",
    "sg:classifiers":[
        {
            "category":"Shopping",
            "subcategory":"Comic Books",
            "type":"Retail Goods"
        }
    ],
    "sg:phone":"+44 1304 206852",
    "sg:postcode":"CT16 1BU",
    "sg:province":"Kent",
    "sg:tags":[
        "jeweller"
    ],
    "wof:name":"John Angell (Dover) Ltd.",
    "wof:placetype":"venue"
},
  "geometry": {"coordinates":[1.311414957,51.1267585754],"type":"Point"}
}