{
  "type": "Feature",
  "properties": {
    "iso:country":"GB",
    "sg:address":"18 Merstow Grn",
    "sg:city":"Evesham",
    "sg:classifiers":[
        {
            "category":"Professional",
            "subcategory":"Accounting & Tax Preparation",
            "type":"Services"
        }
    ],
    "sg:phone":"+44 1386 45979",
    "sg:postcode":"WR11 4BD",
    "sg:province":"Gloucestershire",
    "sg:tags":[
        "accountant"
    ],
    "wof:name":"C M Dalby",
    "wof:placetype":"venue"
},
  "geometry": {"coordinates":[-1.950507,52.092014],"type":"Point"}
}