{
  "type": "Feature",
  "properties": {
    "iso:country":"GB",
    "sg:address":"59 Heol Fach, North Cornelly",
    "sg:city":"Bridgend",
    "sg:classifiers":[
        {
            "category":"Cinema",
            "subcategory":"Movie Rental",
            "type":"Entertainment"
        }
    ],
    "sg:phone":"+44 1656 742298",
    "sg:postcode":"CF33 4LN",
    "sg:province":"Bridgend",
    "sg:tags":[
        "video",
        "library"
    ],
    "wof:name":"Newton Video",
    "wof:placetype":"venue"
},
  "geometry": {"coordinates":[-3.701021,51.52145],"type":"Point"}
}