{
  "type": "Feature",
  "properties": {
    "iso:country":"GB",
    "sg:address":"64a Church Street",
    "sg:city":"Warrington",
    "sg:classifiers":[
        {
            "category":"Government",
            "subcategory":"Post Office",
            "type":"Public Place"
        }
    ],
    "sg:phone":"+44 1925 630981",
    "sg:postcode":"WA1 2SY",
    "sg:province":"Cheshire",
    "wof:name":"Church Street Sub Post Office",
    "wof:placetype":"venue"
},
  "geometry": {"coordinates":[-2.58454,53.390228],"type":"Point"}
}