{
  "type": "Feature",
  "properties": {
    "addr:full":"28 Elmwood Rd Croydon Surrey CR0 2SG",
    "addr:housenumber":"28",
    "addr:postcode":"cr0 2sg",
    "addr:street":"Elmwood Rd",
    "iso:country":"GB",
    "sg:address":"28 Elmwood Rd",
    "sg:city":"Croydon",
    "sg:classifiers":[
        {
            "category":"Health Services",
            "subcategory":"Nursing And Care Facility",
            "type":"Services"
        }
    ],
    "sg:phone":"+44 20 8665 0645",
    "sg:postcode":"CR0 2SG",
    "sg:province":"Surrey",
    "sg:tags":[
        "home"
    ],
    "wof:name":"Woodleigh Nursing Home",
    "wof:placetype":"venue"
},
  "geometry": {"coordinates":[-0.1059539989,51.3848762512],"type":"Point"}
}