{
  "type": "Feature",
  "properties": {
    "addr:full":"Unit F, 18 Dock St, Leith Edinburgh City of Edinburgh EH6 6EY",
    "addr:housenumber":"18",
    "addr:postcode":"eh6 6ey",
    "addr:street":"Dock St",
    "iso:country":"GB",
    "sg:address":"Unit F, 18 Dock St, Leith",
    "sg:city":"Edinburgh",
    "sg:classifiers":[
        {
            "category":"Home & Garden",
            "subcategory":"Building Materials",
            "type":"Retail Goods"
        }
    ],
    "sg:phone":"+44 131 555 1396",
    "sg:postcode":"EH6 6EY",
    "sg:province":"City of Edinburgh",
    "sg:tags":[
        "stairlifts"
    ],
    "wof:name":"Express Evans Lifts",
    "wof:placetype":"venue"
},
  "geometry": {"coordinates":[-3.17426,55.97657],"type":"Point"}
}