{
  "type": "Feature",
  "properties": {
    "addr:full":"101 Whitehouse Common Road Sutton Coldfield Staffordshire B75 6EY",
    "addr:housenumber":"101",
    "addr:postcode":"b75 6ey",
    "addr:street":"Whitehouse Common Road",
    "iso:country":"GB",
    "sg:address":"101 Whitehouse Common Road",
    "sg:city":"Sutton Coldfield",
    "sg:classifiers":[
        {
            "category":"Government",
            "subcategory":"Post Office",
            "type":"Public Place"
        }
    ],
    "sg:phone":"+44 121 311 2691",
    "sg:postcode":"B75 6EY",
    "sg:province":"Staffordshire",
    "wof:name":"Whitehouse Common Road Post Office",
    "wof:placetype":"venue"
},
  "geometry": {"coordinates":[-1.8028069735,52.5706787109],"type":"Point"}
}