{
  "type": "Feature",
  "properties": {
    "iso:country":"GB",
    "sg:address":"17 Albany Parade, High Street",
    "sg:city":"Brentford",
    "sg:classifiers":[
        {
            "category":"Health Services",
            "subcategory":"Dentist",
            "type":"Services"
        }
    ],
    "sg:phone":"+44 20 8560 5351",
    "sg:postcode":"TW8 0JW",
    "sg:province":"Greater London",
    "wof:name":"Albany Parade Dental Surgery",
    "wof:placetype":"venue"
},
  "geometry": {"coordinates":[-0.301825,51.485668],"type":"Point"}
}