{
  "type": "Feature",
  "properties": {
    "addr:full":"1 Coppice Gro Knutsford Cheshire WA16 6TN",
    "addr:housenumber":"1",
    "addr:postcode":"wa16 6tn",
    "addr:street":"Coppice Gro",
    "iso:country":"GB",
    "sg:address":"1 Coppice Gro",
    "sg:city":"Knutsford",
    "sg:classifiers":[
        {
            "category":"Professional",
            "subcategory":"Management & Consulting",
            "type":"Services"
        }
    ],
    "sg:phone":"+44 1565 654690",
    "sg:postcode":"WA16 6TN",
    "sg:province":"Cheshire",
    "sg:tags":[
        "marketing",
        "consultant"
    ],
    "wof:name":"Wine Consultancy The",
    "wof:placetype":"venue"
},
  "geometry": {"coordinates":[-2.37624,53.304203],"type":"Point"}
}