{
  "type": "Feature",
  "properties": {
    "iso:country":"GB",
    "sg:address":"Old Hatch Manor",
    "sg:city":"Ruislip",
    "sg:classifiers":[
        {
            "category":"Education",
            "subcategory":"School",
            "type":"Public Place"
        },
        {
            "category":"Government",
            "subcategory":"Office",
            "type":"Public Place"
        }
    ],
    "sg:phone":"+44 1895 675984",
    "sg:postcode":"HA4 8QG",
    "sg:province":"Greater London",
    "sg:tags":[
        "local",
        "authority"
    ],
    "wof:name":"Warrender Junior & Infant School",
    "wof:placetype":"venue"
},
  "geometry": {"coordinates":[-0.4136140049,51.57654953],"type":"Point"}
}