{
  "type": "Feature",
  "properties": {
    "addr:full":"Parc Mawr Farm, Senghenydd Caerphilly Caerphilly CF83 4HH",
    "addr:postcode":"cf83 4hh",
    "iso:country":"GB",
    "sg:address":"Parc Mawr Farm, Senghenydd",
    "sg:city":"Caerphilly",
    "sg:classifiers":[
        {
            "category":"Farming",
            "subcategory":"Livestock Farm",
            "type":"Manufacturing & Wholesale Goods"
        }
    ],
    "sg:phone":"+44 29 2083 0209",
    "sg:postcode":"CF83 4HH",
    "sg:province":"Caerphilly",
    "sg:tags":[
        "others"
    ],
    "wof:name":"B & W J M Griffiths",
    "wof:placetype":"venue"
},
  "geometry": {"coordinates":[-3.276674,51.607948],"type":"Point"}
}