{
  "type": "Feature",
  "properties": {
    "iso:country":"GB",
    "sg:address":"2 Molesey Rd",
    "sg:city":"Walton On Thames",
    "sg:classifiers":[
        {
            "category":"Food & Beverages",
            "subcategory":"Meat & Fish",
            "type":"Retail Goods"
        }
    ],
    "sg:phone":"+44 1932 252820",
    "sg:postcode":"KT12 4RQ",
    "sg:province":"Surrey",
    "sg:tags":[
        "butcher"
    ],
    "wof:name":"Quality Catering",
    "wof:placetype":"venue"
},
  "geometry": {"coordinates":[-0.392789,51.37262],"type":"Point"}
}