{
  "type": "Feature",
  "properties": {
    "iso:country":"GB",
    "sg:address":"Iron Acton By-pass, Yate",
    "sg:city":"Bristol",
    "sg:classifiers":[
        {
            "category":"Autos & Motor Vehicles",
            "subcategory":"Fuel & Gas Station",
            "type":"Retail Goods"
        }
    ],
    "sg:phone":"+44 1454 228944",
    "sg:postcode":"BS37 9XY",
    "sg:province":"Gloucestershire",
    "sg:tags":[
        "petrol",
        "filling"
    ],
    "wof:name":"Q8 Petroleum",
    "wof:placetype":"venue"
},
  "geometry": {"coordinates":[-2.460513,51.550182],"type":"Point"}
}