{
  "type": "Feature",
  "properties": {
    "iso:country":"GB",
    "sg:address":"Unit 4 Forgehammer Industrial Estate",
    "sg:city":"Cwmbran",
    "sg:classifiers":[
        {
            "category":"Retail",
            "subcategory":"Repair Shop",
            "type":"Services"
        }
    ],
    "sg:phone":"+44 1633 871867",
    "sg:postcode":"NP44 3AA",
    "sg:province":"Monmouthshire",
    "sg:tags":[
        "radio",
        "television",
        "video"
    ],
    "wof:name":"Adams Television",
    "wof:placetype":"venue"
},
  "geometry": {"coordinates":[-3.0273990631,51.6555480957],"type":"Point"}
}