{
  "type": "Feature",
  "properties": {
    "addr:full":"445 Hagley Road, Edgbaston Birmingham West Midlands B17 8BL",
    "addr:housenumber":"445",
    "addr:postcode":"b17 8bl",
    "addr:street":"Hagley Road",
    "iso:country":"GB",
    "sg:address":"445 Hagley Road, Edgbaston",
    "sg:city":"Birmingham",
    "sg:classifiers":[
        {
            "category":"Social Services",
            "subcategory":"Retirement Home",
            "type":"Services"
        }
    ],
    "sg:postcode":"B17 8BL",
    "sg:province":"West Midlands",
    "sg:tags":[
        "care"
    ],
    "wof:name":"Priory Homecare",
    "wof:placetype":"venue"
},
  "geometry": {"coordinates":[-1.964406,52.473537],"type":"Point"}
}