{
  "type": "Feature",
  "properties": {
    "addr:full":"15 Dunlin Close Southsea Hampshire PO4 8YW",
    "addr:housenumber":"15",
    "addr:postcode":"po4 8yw",
    "addr:street":"Dunlin Close",
    "iso:country":"GB",
    "sg:address":"15 Dunlin Close",
    "sg:city":"Southsea",
    "sg:classifiers":[
        {
            "category":"Retail",
            "subcategory":"Driving School",
            "type":"Services"
        },
        {
            "category":"Education",
            "subcategory":"School",
            "type":"Public Place"
        }
    ],
    "sg:phone":"+44 23 9273 2704",
    "sg:postcode":"PO4 8YW",
    "sg:province":"Hampshire",
    "sg:tags":[
        "local",
        "authority"
    ],
    "wof:name":"Coopers School of Motoring",
    "wof:placetype":"venue"
},
  "geometry": {"coordinates":[-1.042659,50.798588],"type":"Point"}
}