{
  "type": "Feature",
  "properties": {
    "iso:country":"GB",
    "sg:address":"143 Kirkby Road",
    "sg:city":"Sutton-in-ashfield",
    "sg:classifiers":[
        {
            "category":"Home & Garden",
            "subcategory":"Furniture",
            "type":"Retail Goods"
        }
    ],
    "sg:phone":"+44 1623 443661",
    "sg:postcode":"NG17 1GW",
    "sg:province":"Nottinghamshire",
    "wof:name":"Sofa Centre by G & S Sofas",
    "wof:placetype":"venue"
},
  "geometry": {"coordinates":[-1.267598033,53.1175689697],"type":"Point"}
}