{
  "type": "Feature",
  "properties": {
    "addr:full":"3 Pond Cottages Broomfield Herne Bay Kent CT6 7AF",
    "addr:housenumber":"3",
    "addr:postcode":"ct6 7af",
    "addr:street":"Pond Cottages Broomfield",
    "iso:country":"GB",
    "sg:address":"3 Pond Cottages Broomfield",
    "sg:city":"Herne Bay",
    "sg:classifiers":[
        {
            "category":"Health Services",
            "subcategory":"Podiatrist",
            "type":"Services"
        }
    ],
    "sg:phone":"+44 1227 369869",
    "sg:postcode":"CT6 7AF",
    "sg:province":"Kent",
    "sg:tags":[
        "podiatrists",
        "chiropodist"
    ],
    "wof:name":"M Hawken MSSCh MBChA",
    "wof:placetype":"venue"
},
  "geometry": {"coordinates":[1.1576449871,51.357383728],"type":"Point"}
}