{
  "type": "Feature",
  "properties": {
    "iso:country":"GB",
    "sg:address":"129 Coombs Rd",
    "sg:city":"Halesowen",
    "sg:classifiers":[
        {
            "category":"Utilities",
            "subcategory":"Natural Gas",
            "type":"Services"
        }
    ],
    "sg:phone":"+44 121 561 4777",
    "sg:postcode":"B62 8AF",
    "sg:province":"West Midlands",
    "sg:tags":[
        "injector",
        "diesel"
    ],
    "wof:name":"R G A Associates",
    "wof:placetype":"venue"
},
  "geometry": {"coordinates":[-2.047327,52.466576],"type":"Point"}
}