{
  "type": "Feature",
  "properties": {
    "iso:country":"GB",
    "sg:address":"Commercial Road",
    "sg:city":"Spalding",
    "sg:classifiers":[
        {
            "category":"Bars & Pubs",
            "type":"Food & Drink"
        }
    ],
    "sg:phone":"+44 1775 723204",
    "sg:postcode":"PE11 2HA",
    "sg:province":"Lincolnshire",
    "sg:tags":[
        "pubs",
        "inn"
    ],
    "wof:name":"Dennis Dermot Daniel Parsons",
    "wof:placetype":"venue"
},
  "geometry": {"coordinates":[-0.141823,52.792831],"type":"Point"}
}