{
  "type": "Feature",
  "properties": {
    "iso:country":"GB",
    "sg:address":"24 Kingsfield Rd, Dane End",
    "sg:city":"Ware",
    "sg:classifiers":[
        {
            "category":"Professional",
            "subcategory":"Engineering",
            "type":"Services"
        }
    ],
    "sg:postcode":"SG12 0LY",
    "sg:province":"Hertfordshire",
    "sg:tags":[
        "contractor",
        "electrical",
        "engineer"
    ],
    "wof:name":"D A McNeil Electricals",
    "wof:placetype":"venue"
},
  "geometry": {"coordinates":[-0.062867,51.876411],"type":"Point"}
}