{
  "type": "Feature",
  "properties": {
    "addr:full":"Chestnut House, Coombehurst Drive Basingstoke Hampshire RG21 3HE",
    "addr:postcode":"rg21 3he",
    "addr:street":"Coombehurst Drive",
    "iso:country":"GB",
    "sg:address":"Chestnut House, Coombehurst Drive",
    "sg:city":"Basingstoke",
    "sg:classifiers":[
        {
            "category":"Building & Trades",
            "subcategory":"Construction",
            "type":"Services"
        }
    ],
    "sg:postcode":"RG21 3HE",
    "sg:province":"Hampshire",
    "sg:tags":[
        "conversion",
        "loft"
    ],
    "wof:name":"Roger Nicholls",
    "wof:placetype":"venue"
},
  "geometry": {"coordinates":[-1.0885820389,51.2527046204],"type":"Point"}
}