{
  "type": "Feature",
  "properties": {
    "addr:full":"Harriotts Hayes Road, Albrighton Wolverhampton Shropshire WV7 3AF",
    "addr:postcode":"wv7 3af",
    "addr:street":"Hayes Road",
    "iso:country":"GB",
    "sg:address":"Harriotts Hayes Road, Albrighton",
    "sg:city":"Wolverhampton",
    "sg:classifiers":[
        {
            "category":"Education",
            "subcategory":"School",
            "type":"Public Place"
        }
    ],
    "sg:phone":"+44 1902 372534",
    "sg:postcode":"WV7 3AF",
    "sg:province":"Shropshire",
    "sg:tags":[
        "independent",
        "preparatory"
    ],
    "wof:name":"Birchfield School",
    "wof:placetype":"venue"
},
  "geometry": {"coordinates":[-2.271562,52.639477],"type":"Point"}
}