{
  "type": "Feature",
  "properties": {
    "iso:country":"GB",
    "sg:address":"34 Hebden Road, Howarth",
    "sg:city":"Keighley",
    "sg:classifiers":[
        {
            "category":"Farming",
            "subcategory":"Dairy Farm",
            "type":"Manufacturing & Wholesale Goods"
        }
    ],
    "sg:phone":"+44 1535 643391",
    "sg:postcode":"BD22 8RE",
    "sg:province":"North Yorkshire",
    "wof:name":"Stanley& Patricia Turner Dairyman",
    "wof:placetype":"venue"
},
  "geometry": {"coordinates":[-1.9405939579,53.8332481384],"type":"Point"}
}