{
  "type": "Feature",
  "properties": {
    "addr:full":"29 Bakers Lane Lichfield Staffordshire WS13 6NG",
    "addr:housenumber":"29",
    "addr:postcode":"ws13 6ng",
    "addr:street":"Bakers Lane",
    "iso:country":"GB",
    "sg:address":"29 Bakers Lane",
    "sg:city":"Lichfield",
    "sg:classifiers":[
        {
            "category":"Shopping",
            "subcategory":"Music",
            "type":"Retail Goods"
        }
    ],
    "sg:phone":"+44 1543 415656",
    "sg:postcode":"WS13 6NG",
    "sg:province":"Staffordshire",
    "sg:tags":[
        "record",
        "tape",
        "cd"
    ],
    "wof:name":"Andys Records",
    "wof:placetype":"venue"
},
  "geometry": {"coordinates":[-1.8251539469,52.6829566956],"type":"Point"}
}