{
  "type": "Feature",
  "properties": {
    "addr:full":"46 Peabody Road Farnborough Hampshire GU14 6EY",
    "addr:housenumber":"46",
    "addr:postcode":"gu14 6ey",
    "addr:street":"Peabody Road",
    "iso:country":"GB",
    "sg:address":"46 Peabody Road",
    "sg:city":"Farnborough",
    "sg:classifiers":[
        {
            "category":"Shopping",
            "subcategory":"Pets & Pet Supplies",
            "type":"Retail Goods"
        }
    ],
    "sg:phone":"+44 1252 542951",
    "sg:postcode":"GU14 6EY",
    "sg:province":"Hampshire",
    "sg:tags":[
        "supplier",
        "pond",
        "aquarium"
    ],
    "wof:name":"Lynchford Aquatics",
    "wof:placetype":"venue"
},
  "geometry": {"coordinates":[-0.745062,51.276253],"type":"Point"}
}