{
  "type": "Feature",
  "properties": {
    "addr:full":"P O Box 73 West Pdo Nottingham Nottinghamshire NG7 4DG",
    "addr:housenumber":"box 73",
    "addr:postcode":"ng7 4dg",
    "addr:street":"P O;West Pdo",
    "iso:country":"GB",
    "sg:address":"P O Box 73 West Pdo",
    "sg:city":"Nottingham",
    "sg:classifiers":[
        {
            "category":"Communications",
            "subcategory":"Newspaper",
            "type":"Services"
        }
    ],
    "sg:postcode":"NG7 4DG",
    "sg:province":"Nottinghamshire",
    "sg:tags":[
        "magazine"
    ],
    "wof:name":"Overall There Is A Smell of Fried Onion",
    "wof:placetype":"venue"
},
  "geometry": {"coordinates":[-1.1627500057,52.9588508606],"type":"Point"}
}