{
  "type": "Feature",
  "properties": {
    "iso:country":"GB",
    "sg:address":"Combe Martin Health Centre, Castle Street, Combe Martin",
    "sg:city":"Ilfracombe",
    "sg:classifiers":[
        {
            "category":"Health Services",
            "subcategory":"Doctor",
            "type":"Services"
        },
        {
            "category":"Health Services",
            "subcategory":"Clinic",
            "type":"Services"
        }
    ],
    "sg:phone":"+44 1271 882406",
    "sg:postcode":"EX34 0JA",
    "sg:province":"Devon",
    "sg:tags":[
        "nh",
        "practitioners"
    ],
    "wof:name":"Combe Martin Health Centre",
    "wof:placetype":"venue"
},
  "geometry": {"coordinates":[-4.0259652138,51.2004013062],"type":"Point"}
}