{
  "type": "Feature",
  "properties": {
    "addr:full":"Clayfield Close, Malton Park Northampton Northamptonshire NN3 6QF",
    "addr:postcode":"nn3 6qf",
    "addr:street":"Clayfield Close",
    "iso:country":"GB",
    "sg:address":"Clayfield Close, Malton Park",
    "sg:city":"Northampton",
    "sg:classifiers":[
        {
            "category":"Sports & Exercise",
            "subcategory":"Race Track",
            "type":"Entertainment"
        }
    ],
    "sg:phone":"+44 1604 499300",
    "sg:postcode":"NN3 6QF",
    "sg:province":"Northamptonshire",
    "sg:tags":[
        "motor"
    ],
    "wof:name":"Jondel Motorsport",
    "wof:placetype":"venue"
},
  "geometry": {"coordinates":[-0.860864,52.275928],"type":"Point"}
}