{
  "type": "Feature",
  "properties": {
    "iso:country":"GB",
    "sg:address":"Grange House, Grange Street",
    "sg:city":"Wakefield",
    "sg:classifiers":[
        {
            "category":"Home & Garden",
            "subcategory":"Carpets & Floor Coverings",
            "type":"Retail Goods"
        }
    ],
    "sg:postcode":"WF2 8TF",
    "sg:province":"West Yorkshire",
    "sg:tags":[
        "textile",
        "floorcoverings"
    ],
    "wof:name":"Ashwood Kitchen Floors",
    "wof:placetype":"venue"
},
  "geometry": {"coordinates":[-1.513102,53.678703],"type":"Point"}
}