{
  "type": "Feature",
  "properties": {
    "iso:country":"GB",
    "sg:address":"71 Wellington Rd",
    "sg:city":"Wallasey",
    "sg:classifiers":[
        {
            "category":"Travel",
            "subcategory":"Hotels & Motels",
            "type":"Entertainment"
        }
    ],
    "sg:phone":"+44 151 639 4727",
    "sg:postcode":"L45 2NE",
    "sg:province":"Merseyside",
    "wof:name":"Divonne Hotel The",
    "wof:placetype":"venue"
},
  "geometry": {"coordinates":[-3.049078,53.438332],"type":"Point"}
}