{
  "type": "Feature",
  "properties": {
    "addr:full":"Hazelhurst, Firgrove Rd, Yateley Camberley Hampshire GU46 6QD",
    "addr:postcode":"gu46 6qd",
    "addr:street":"Firgrove Rd",
    "iso:country":"GB",
    "sg:address":"Hazelhurst, Firgrove Rd, Yateley",
    "sg:city":"Camberley",
    "sg:classifiers":[
        {
            "category":"Building & Trades",
            "subcategory":"Construction",
            "type":"Services"
        }
    ],
    "sg:postcode":"GU46 6QD",
    "sg:province":"Hampshire",
    "sg:tags":[
        "heating",
        "contractor"
    ],
    "wof:name":"Webster,Ian,",
    "wof:placetype":"venue"
},
  "geometry": {"coordinates":[-0.8385999799,51.341178894],"type":"Point"}
}