{
  "type": "Feature",
  "properties": {
    "addr:full":"405 Lord Street Southport Lancashire PR9 0AG",
    "addr:housenumber":"405",
    "addr:postcode":"pr9 0ag",
    "addr:street":"Lord Street",
    "iso:country":"GB",
    "sg:address":"405 Lord Street",
    "sg:city":"Southport",
    "sg:classifiers":[
        {
            "category":"Food & Beverages",
            "subcategory":"Bakery",
            "type":"Retail Goods"
        }
    ],
    "sg:phone":"+44 1704 533743",
    "sg:postcode":"PR9 0AG",
    "sg:province":"Lancashire",
    "sg:tags":[
        "baker"
    ],
    "wof:name":"The Dutch Chef",
    "wof:placetype":"venue"
},
  "geometry": {"coordinates":[-3.002894,53.649944],"type":"Point"}
}