{
  "type": "Feature",
  "properties": {
    "addr:full":"79 Marle Hill Rd Cheltenham Gloucestershire GL50 4LN",
    "addr:housenumber":"79",
    "addr:postcode":"gl50 4ln",
    "addr:street":"Marle Hill Rd",
    "iso:country":"GB",
    "sg:address":"79 Marle Hill Rd",
    "sg:city":"Cheltenham",
    "sg:classifiers":[
        {
            "category":"Home & Garden",
            "subcategory":"Home Furnishings",
            "type":"Retail Goods"
        }
    ],
    "sg:phone":"+44 1242 243543",
    "sg:postcode":"GL50 4LN",
    "sg:province":"Gloucestershire",
    "sg:tags":[
        "furnishers",
        "planner",
        "kitchen"
    ],
    "wof:name":"Stroke Of Genius",
    "wof:placetype":"venue"
},
  "geometry": {"coordinates":[-2.0762379169,51.908618927],"type":"Point"}
}