{
  "type": "Feature",
  "properties": {
    "addr:full":"744 Green Lanes London Greater London N21 3RE",
    "addr:housenumber":"744",
    "addr:postcode":"n21 3re",
    "addr:street":"Green Lanes",
    "iso:country":"GB",
    "sg:address":"744 Green Lanes",
    "sg:city":"London",
    "sg:classifiers":[
        {
            "category":"Cafe",
            "type":"Food & Drink"
        }
    ],
    "sg:postcode":"N21 3RE",
    "sg:province":"Greater London",
    "sg:tags":[
        "tea",
        "room"
    ],
    "wof:name":"The Broadway Tea Room",
    "wof:placetype":"venue"
},
  "geometry": {"coordinates":[-0.0959959999,51.6315345764],"type":"Point"}
}