{
  "type": "Feature",
  "properties": {
    "addr:full":"309 Upper Elmers End Rd Beckenham Kent BR3 3QP",
    "addr:housenumber":"309",
    "addr:postcode":"br3 3qp",
    "addr:street":"Upper Elmers End Rd",
    "iso:country":"GB",
    "sg:address":"309 Upper Elmers End Rd",
    "sg:city":"Beckenham",
    "sg:classifiers":[
        {
            "category":"Personal",
            "subcategory":"Beauty Salon",
            "type":"Services"
        }
    ],
    "sg:phone":"+44 20 8650 2252",
    "sg:postcode":"BR3 3QP",
    "sg:province":"Kent",
    "sg:tags":[
        "lady",
        "hairdresser"
    ],
    "wof:name":"Angela Hair Fashions",
    "wof:placetype":"venue"
},
  "geometry": {"coordinates":[-0.0383450016,51.3919868469],"type":"Point"}
}