{
  "type": "Feature",
  "properties": {
    "addr:full":"Unit 51b Bradley Hall Trading Est, Bradl, Standish Wigan Lancashire WN6 0XQ",
    "addr:housenumber":"unit 51b",
    "addr:postcode":"wn6 0xq",
    "addr:street":"Bradley Hall Trading Est",
    "iso:country":"GB",
    "sg:address":"Unit 51b Bradley Hall Trading Est, Bradl, Standish",
    "sg:city":"Wigan",
    "sg:classifiers":[
        {
            "category":"Retail",
            "subcategory":"Auto Repair",
            "type":"Services"
        }
    ],
    "sg:postcode":"WN6 0XQ",
    "sg:province":"Lancashire",
    "sg:tags":[
        "modification",
        "garage"
    ],
    "wof:name":"D & S Motor Care",
    "wof:placetype":"venue"
},
  "geometry": {"coordinates":[-2.663401,53.586021],"type":"Point"}
}