{
  "type": "Feature",
  "properties": {
    "addr:full":"Unit 9a, Boss Hall Road Ipswich Suffolk IP1 5BN",
    "addr:housenumber":"unit 9a boss",
    "addr:postcode":"ip1 5bn",
    "addr:street":"Hall Road",
    "iso:country":"GB",
    "sg:address":"Unit 9a, Boss Hall Road",
    "sg:city":"Ipswich",
    "sg:classifiers":[
        {
            "category":"Wholesale",
            "subcategory":"Construction Materials",
            "type":"Manufacturing & Wholesale Goods"
        },
        {
            "category":"Professional",
            "subcategory":"Art Services",
            "type":"Services"
        }
    ],
    "sg:phone":"+44 1473 463333",
    "sg:postcode":"IP1 5BN",
    "sg:province":"Suffolk",
    "sg:tags":[
        "polishing",
        "metal",
        "finishing",
        "coating",
        "powder"
    ],
    "wof:name":"Industrial Powder & Paint Services Ltd.",
    "wof:placetype":"venue"
},
  "geometry": {"coordinates":[1.1248430014,52.0653305054],"type":"Point"}
}