{
  "type": "Feature",
  "properties": {
    "addr:full":"13 Fortis Green Road London Greater London N10 3HP",
    "addr:housenumber":"13",
    "addr:postcode":"n10 3hp",
    "addr:street":"Fortis Green Road",
    "iso:country":"GB",
    "sg:address":"13 Fortis Green Road",
    "sg:city":"London",
    "sg:classifiers":[
        {
            "category":"Manufacturing",
            "subcategory":"Food",
            "type":"Manufacturing & Wholesale Goods"
        }
    ],
    "sg:phone":"+44 20 8444 9141",
    "sg:postcode":"N10 3HP",
    "sg:province":"Greater London",
    "sg:tags":[
        "cheese",
        "producer"
    ],
    "wof:name":"Cheeses",
    "wof:placetype":"venue"
},
  "geometry": {"coordinates":[-0.146228,51.589851],"type":"Point"}
}