{
  "type": "Feature",
  "properties": {
    "addr:full":"Bedale Drive Bradford West Yorkshire BD6 3ST",
    "addr:postcode":"bd6 3st",
    "addr:street":"Bedale Drive",
    "iso:country":"GB",
    "sg:address":"Bedale Drive",
    "sg:city":"Bradford",
    "sg:classifiers":[
        {
            "category":"Education",
            "subcategory":"School",
            "type":"Public Place"
        },
        {
            "category":"Government",
            "subcategory":"Office",
            "type":"Public Place"
        }
    ],
    "sg:phone":"+44 1274 677549",
    "sg:postcode":"BD6 3ST",
    "sg:province":"West Yorkshire",
    "sg:tags":[
        "local",
        "authority"
    ],
    "wof:name":"Reevy Hill First School",
    "wof:placetype":"venue"
},
  "geometry": {"coordinates":[-1.7952990532,53.7677612305],"type":"Point"}
}