{
  "type": "Feature",
  "properties": {
    "addr:full":"Jobs Farm, New House Lane, Salfords Redhill Surrey RH1 5RE",
    "addr:postcode":"rh1 5re",
    "addr:street":"New House Lane;Redhill",
    "iso:country":"GB",
    "sg:address":"Jobs Farm, New House Lane, Salfords",
    "sg:city":"Redhill",
    "sg:classifiers":[
        {
            "category":"Banks & Credit Unions",
            "subcategory":"Investment Brokerage",
            "type":"Services"
        }
    ],
    "sg:phone":"+44 1293 773386",
    "sg:postcode":"RH1 5RE",
    "sg:province":"Surrey",
    "sg:tags":[
        "contractor"
    ],
    "wof:name":"N J Fuller Agricultural Contractors",
    "wof:placetype":"venue"
},
  "geometry": {"coordinates":[-0.1630689949,51.2144088745],"type":"Point"}
}