{
  "type": "Feature",
  "properties": {
    "iso:country":"GB",
    "sg:address":"Tapitlaw Farm, Comrie",
    "sg:city":"Dunfermline",
    "sg:classifiers":[
        {
            "category":"Sports & Exercise",
            "subcategory":"Stables",
            "type":"Entertainment"
        }
    ],
    "sg:phone":"+44 1383 850302",
    "sg:postcode":"KY12 9HE",
    "sg:province":"Fife",
    "sg:tags":[
        "education",
        "equestrian"
    ],
    "wof:name":"TAPITLAW RIDING SCHOOL",
    "wof:placetype":"venue"
},
  "geometry": {"coordinates":[-3.580599,56.087776],"type":"Point"}
}