{
  "type": "Feature",
  "properties": {
    "addr:full":"91 The Ridgeway Watford Hertfordshire WD17 4WJ",
    "addr:housenumber":"91",
    "addr:postcode":"wd17 4wj",
    "addr:street":"The Ridgeway",
    "iso:country":"GB",
    "sg:address":"91 The Ridgeway",
    "sg:city":"Watford",
    "sg:classifiers":[
        {
            "category":"Building & Trades",
            "subcategory":"Construction",
            "type":"Services"
        }
    ],
    "sg:phone":"+44 1923 210016",
    "sg:postcode":"WD17 4WJ",
    "sg:province":"Hertfordshire",
    "sg:tags":[
        "joiner",
        "carpenter"
    ],
    "wof:name":"Paul Holman Carpentry and Cabinets",
    "wof:placetype":"venue"
},
  "geometry": {"coordinates":[-0.4235619903,51.6786613464],"type":"Point"}
}