{
  "type": "Feature",
  "properties": {
    "iso:country":"GB",
    "sg:address":"Unit 6 Herbert Avenue, Melton Road",
    "sg:city":"Leicester",
    "sg:classifiers":[
        {
            "category":"Home & Garden",
            "subcategory":"Home Furnishings",
            "type":"Retail Goods"
        }
    ],
    "sg:phone":"+44 116 261 0740",
    "sg:postcode":"LE4 5EW",
    "sg:province":"Leicestershire",
    "sg:tags":[
        "awning",
        "canopy",
        "blinds"
    ],
    "wof:name":"Safe Glass Ltd.",
    "wof:placetype":"venue"
},
  "geometry": {"coordinates":[-1.120099,52.654919],"type":"Point"}
}