{
  "type": "Feature",
  "properties": {
    "addr:full":"3 Mill Lane, Bromley By Bow London Greater London E3 3DU",
    "addr:housenumber":"3",
    "addr:postcode":"e3 3du",
    "addr:street":"Mill Lane",
    "iso:country":"GB",
    "sg:address":"3 Mill Lane, Bromley By Bow",
    "sg:city":"London",
    "sg:classifiers":[
        {
            "category":"Landmark",
            "subcategory":"Tourist Attraction",
            "type":"Public Place"
        }
    ],
    "sg:phone":"+44 20 8980 4626",
    "sg:postcode":"E3 3DU",
    "sg:province":"Greater London",
    "sg:tags":[
        "interest"
    ],
    "wof:name":"The Millers House",
    "wof:placetype":"venue"
},
  "geometry": {"coordinates":[-0.0069900001,51.5273590088],"type":"Point"}
}