{
  "type": "Feature",
  "properties": {
    "addr:full":"East St Peterborough Cambridgeshire PE6 0EN",
    "addr:postcode":"pe6 0en",
    "addr:street":"East St",
    "iso:country":"GB",
    "sg:address":"East St",
    "sg:city":"Peterborough",
    "sg:classifiers":[
        {
            "category":"Place Of Worship",
            "type":"Public Place"
        }
    ],
    "sg:phone":"+44 1733 210499",
    "sg:postcode":"PE6 0EN",
    "sg:province":"Cambridgeshire",
    "wof:name":"Crowland Abbey",
    "wof:placetype":"venue"
},
  "geometry": {"coordinates":[-0.166491,52.676262],"type":"Point"}
}