{
  "type": "Feature",
  "properties": {
    "iso:country":"GB",
    "sg:address":"Georgian House, 67-71 London Road",
    "sg:city":"Newbury",
    "sg:classifiers":[
        {
            "category":"Professional",
            "subcategory":"Computer Services",
            "type":"Services"
        }
    ],
    "sg:phone":"+44 1635 239239",
    "sg:postcode":"RG14 1JN",
    "sg:province":"Berkshire",
    "sg:tags":[
        "consultant"
    ],
    "wof:name":"Serious Cybernetics Ltd.",
    "wof:placetype":"venue"
},
  "geometry": {"coordinates":[-1.320334,51.406284],"type":"Point"}
}