{
  "type": "Feature",
  "properties": {
    "addr:full":"Loveless Hall, Church Lane Chessington Surrey KT9 2DR",
    "addr:postcode":"kt9 2dr",
    "addr:street":"Church Lane",
    "iso:country":"GB",
    "sg:address":"Loveless Hall, Church Lane",
    "sg:city":"Chessington",
    "sg:classifiers":[
        {
            "category":"Community Center",
            "subcategory":"Youth",
            "type":"Public Place"
        }
    ],
    "sg:phone":"+44 20 8397 2495",
    "sg:postcode":"KT9 2DR",
    "sg:province":"Surrey",
    "sg:tags":[
        "organisation",
        "centre"
    ],
    "wof:name":"Chessington Youth & Community Centre",
    "wof:placetype":"venue"
},
  "geometry": {"coordinates":[-0.308645,51.361874],"type":"Point"}
}