{
  "type": "Feature",
  "properties": {
    "iso:country":"GB",
    "sg:address":"Chequers House, 77-81 Newmarket Road",
    "sg:city":"Cambridge",
    "sg:classifiers":[
        {
            "category":"Professional",
            "subcategory":"Lawyer & Legal Services",
            "type":"Services"
        }
    ],
    "sg:phone":"+44 1223 363111",
    "sg:postcode":"CB5 8EU",
    "sg:province":"Cambridgeshire",
    "sg:tags":[
        "solicitor"
    ],
    "wof:name":"Few & Kester",
    "wof:placetype":"venue"
},
  "geometry": {"coordinates":[0.1365319937,52.2085151672],"type":"Point"}
}