{
  "type": "Feature",
  "properties": {
    "addr:full":"42 Salters Rd Newcastle Upon Tyne Tyne and Wear NE3 1DX",
    "addr:housenumber":"42",
    "addr:postcode":"ne3 1dx",
    "addr:street":"Salters Rd",
    "iso:country":"GB",
    "sg:address":"42 Salters Rd",
    "sg:city":"Newcastle Upon Tyne",
    "sg:classifiers":[
        {
            "category":"Health Services",
            "subcategory":"Health Practitioner",
            "type":"Services"
        }
    ],
    "sg:phone":"+44 191 284 3558",
    "sg:postcode":"NE3 1DX",
    "sg:province":"Tyne and Wear",
    "sg:tags":[
        "psychologist"
    ],
    "wof:name":"Jane Mccarthy",
    "wof:placetype":"venue"
},
  "geometry": {"coordinates":[-1.6237850189,55.0067863464],"type":"Point"}
}