{
  "type": "Feature",
  "properties": {
    "iso:country":"GB",
    "sg:address":"193 Oldfield Lane North",
    "sg:city":"Greenford",
    "sg:classifiers":[
        {
            "category":"Manufacturing",
            "subcategory":"Signs",
            "type":"Manufacturing & Wholesale Goods"
        }
    ],
    "sg:phone":"+44 20 8578 2878",
    "sg:postcode":"UB6 8PN",
    "sg:province":"Greater London",
    "sg:tags":[
        "writer"
    ],
    "wof:name":"E G Kolman",
    "wof:placetype":"venue"
},
  "geometry": {"coordinates":[-0.348531,51.540108],"type":"Point"}
}