{
  "type": "Feature",
  "properties": {
    "addr:full":"Studio B Pembroke House, Campsbourne Rd Hornsey Greater London N8 7PE",
    "addr:postcode":"n8 7pe",
    "addr:street":"Campsbourne Rd",
    "iso:country":"GB",
    "sg:address":"Studio B Pembroke House, Campsbourne Rd",
    "sg:city":"Hornsey",
    "sg:classifiers":[
        {
            "category":"Shopping",
            "subcategory":"Clothing, Apparel, & Fashions",
            "type":"Retail Goods"
        }
    ],
    "sg:phone":"+44 20 8340 4600",
    "sg:postcode":"N8 7PE",
    "sg:province":"Greater London",
    "sg:tags":[
        "clothing"
    ],
    "wof:name":"Distribution De Artisano",
    "wof:placetype":"venue"
},
  "geometry": {"coordinates":[-0.119314,51.5882263184],"type":"Point"}
}