{
  "type": "Feature",
  "properties": {
    "iso:country":"GB",
    "sg:address":"144 Hampton Lane, Blackfield",
    "sg:city":"Southampton",
    "sg:classifiers":[
        {
            "category":"Cinema",
            "subcategory":"Movie Rental",
            "type":"Entertainment"
        }
    ],
    "sg:phone":"+44 23 8089 4752",
    "sg:postcode":"SO45 1WE",
    "sg:province":"Hampshire",
    "sg:tags":[
        "video",
        "library"
    ],
    "wof:name":"Video to Go",
    "wof:placetype":"venue"
},
  "geometry": {"coordinates":[-1.371803,50.817547],"type":"Point"}
}