{
  "type": "Feature",
  "properties": {
    "addr:full":"44-45 Chancery La Holborn Greater London WC2A 1JB",
    "addr:housenumber":"44-45",
    "addr:postcode":"wc2a 1jb",
    "addr:street":"Chancery La Holborn",
    "iso:country":"GB",
    "sg:address":"44-45 Chancery La",
    "sg:city":"Holborn",
    "sg:classifiers":[
        {
            "category":"Professional",
            "subcategory":"Lawyer & Legal Services",
            "type":"Services"
        }
    ],
    "sg:phone":"+44 20 7831 8687",
    "sg:postcode":"WC2A 1JB",
    "sg:province":"Greater London",
    "sg:tags":[
        "solicitor"
    ],
    "wof:name":"Ison Andrews",
    "wof:placetype":"venue"
},
  "geometry": {"coordinates":[-0.1122549996,51.5165939331],"type":"Point"}
}