{
  "type": "Feature",
  "properties": {
    "addr:full":"Moscar Heights, Hollow Meadows Sheffield South Yorkshire S6 6GL",
    "addr:postcode":"s6 6gl",
    "addr:street":"Heights Hollow",
    "iso:country":"GB",
    "sg:address":"Moscar Heights, Hollow Meadows",
    "sg:city":"Sheffield",
    "sg:classifiers":[
        {
            "category":"Professional",
            "subcategory":"Business Services",
            "type":"Services"
        }
    ],
    "sg:postcode":"S6 6GL",
    "sg:province":"South Yorkshire",
    "sg:tags":[
        "import",
        "export",
        "agent"
    ],
    "wof:name":"Moscar Marketing",
    "wof:placetype":"venue"
},
  "geometry": {"coordinates":[-1.639072,53.389706],"type":"Point"}
}