{
  "type": "Feature",
  "properties": {
    "iso:country":"GB",
    "sg:address":"78 Queens Way",
    "sg:city":"West Wickham",
    "sg:classifiers":[
        {
            "category":"Building & Trades",
            "subcategory":"Construction",
            "type":"Services"
        }
    ],
    "sg:phone":"+44 1689 607087",
    "sg:postcode":"BR4 9ER",
    "sg:province":"Kent",
    "sg:tags":[
        "decorator",
        "painter"
    ],
    "wof:name":"Kent Decorators",
    "wof:placetype":"venue"
},
  "geometry": {"coordinates":[0.003776,51.366352],"type":"Point"}
}