{
  "type": "Feature",
  "properties": {
    "iso:country":"GB",
    "sg:address":"155 Mander Square Mander Centre",
    "sg:city":"Wolverhampton",
    "sg:classifiers":[
        {
            "category":"Restaurant",
            "type":"Food & Drink"
        }
    ],
    "sg:phone":"+44 1902 711695",
    "sg:postcode":"WV1 3NN",
    "sg:province":"West Midlands",
    "wof:name":"Poppins Restaurant",
    "wof:placetype":"venue"
},
  "geometry": {"coordinates":[-2.129489,52.584213],"type":"Point"}
}