{
  "type": "Feature",
  "properties": {
    "iso:country":"GB",
    "sg:address":"34 Watson Road, South Shore",
    "sg:city":"Blackpool",
    "sg:classifiers":[
        {
            "category":"Retail",
            "subcategory":"Auto Repair",
            "type":"Services"
        }
    ],
    "sg:phone":"+44 1253 404677",
    "sg:postcode":"FY4 2DD",
    "sg:province":"Lancashire",
    "sg:tags":[
        "modification",
        "garage"
    ],
    "wof:name":"Farrer's Garage",
    "wof:placetype":"venue"
},
  "geometry": {"coordinates":[-3.046732,53.791965],"type":"Point"}
}