{
  "type": "Feature",
  "properties": {
    "addr:full":"Lowergate Works, Water Street, Morland Penrith Cumbria CA10 3AY",
    "addr:postcode":"ca10 3ay",
    "addr:street":"Lowergate;Water Street",
    "iso:country":"GB",
    "sg:address":"Lowergate Works, Water Street, Morland",
    "sg:city":"Penrith",
    "sg:classifiers":[
        {
            "category":"Professional",
            "subcategory":"Engineering",
            "type":"Services"
        },
        {
            "category":"Wholesale",
            "subcategory":"Machinery & Supplies",
            "type":"Manufacturing & Wholesale Goods"
        }
    ],
    "sg:phone":"+44 1931 714655",
    "sg:postcode":"CA10 3AY",
    "sg:province":"Cumbria",
    "sg:tags":[
        "supplier",
        "industrial",
        "manufacturer"
    ],
    "wof:name":"Thwaites Services Ltd",
    "wof:placetype":"venue"
},
  "geometry": {"coordinates":[-2.6209700108,54.594959259],"type":"Point"}
}