{
  "type": "Feature",
  "properties": {
    "iso:country":"GB",
    "sg:address":"Unit 5, Millie Street",
    "sg:city":"Kirkcaldy",
    "sg:classifiers":[
        {
            "category":"Organizations",
            "subcategory":"Non-profit Organization",
            "type":"Services"
        }
    ],
    "sg:postcode":"KY1 2NL",
    "sg:province":"Fife",
    "sg:tags":[
        "organisation",
        "voluntary",
        "charity"
    ],
    "wof:name":"Fife Family Support Project for Mental Health Diff",
    "wof:placetype":"venue"
},
  "geometry": {"coordinates":[-3.144407,56.122688],"type":"Point"}
}