{
  "type": "Feature",
  "properties": {
    "addr:full":"Bridge End, High St, Willington Crook Durham DL15 0PN",
    "addr:postcode":"dl15 0pn",
    "addr:street":"Bridge End High St",
    "iso:country":"GB",
    "sg:address":"Bridge End, High St, Willington",
    "sg:city":"Crook",
    "sg:classifiers":[
        {
            "category":"Retail",
            "subcategory":"Funeral Services",
            "type":"Services"
        }
    ],
    "sg:phone":"+44 1388 747747",
    "sg:postcode":"DL15 0PN",
    "sg:province":"Durham",
    "sg:tags":[
        "mnfr",
        "monumental",
        "mason"
    ],
    "wof:name":"Christopher Hardy",
    "wof:placetype":"venue"
},
  "geometry": {"coordinates":[-1.696789,54.712311],"type":"Point"}
}