{
  "type": "Feature",
  "properties": {
    "addr:full":"328 North Dee Road, The Square Aberdeen Aberdeen City AB15 9SE",
    "addr:housenumber":"328",
    "addr:postcode":"ab15 9se",
    "addr:street":"North Dee Road The Square",
    "iso:country":"GB",
    "sg:address":"328 North Dee Road, The Square",
    "sg:city":"Aberdeen",
    "sg:classifiers":[
        {
            "category":"Travel",
            "subcategory":"Hotels & Motels",
            "type":"Entertainment"
        }
    ],
    "sg:phone":"+44 1224 867632",
    "sg:postcode":"AB15 9SE",
    "sg:province":"Aberdeen City",
    "wof:name":"c/o Cults Hotel",
    "wof:placetype":"venue"
},
  "geometry": {"coordinates":[-2.189949,57.11412],"type":"Point"}
}