{
  "type": "Feature",
  "properties": {
    "addr:full":"37 Redlands Lane Fareham Hampshire PO14 1HL",
    "addr:housenumber":"37",
    "addr:postcode":"po14 1hl",
    "addr:street":"Redlands Lane",
    "iso:country":"GB",
    "sg:address":"37 Redlands Lane",
    "sg:city":"Fareham",
    "sg:classifiers":[
        {
            "category":"Retail",
            "subcategory":"Auto Repair",
            "type":"Services"
        }
    ],
    "sg:phone":"+44 1329 232269",
    "sg:postcode":"PO14 1HL",
    "sg:province":"Hampshire",
    "sg:tags":[
        "modification",
        "garage"
    ],
    "wof:name":"Dave Bushill Mobile Motor Repairs",
    "wof:placetype":"venue"
},
  "geometry": {"coordinates":[-1.1933490038,50.8498725891],"type":"Point"}
}