{
  "type": "Feature",
  "properties": {
    "addr:full":"Progress Way Enfield Greater London EN1 1UU",
    "addr:postcode":"en1 1uu",
    "addr:street":"Progress Way",
    "iso:country":"GB",
    "sg:address":"Progress Way",
    "sg:city":"Enfield",
    "sg:classifiers":[
        {
            "category":"Wholesale",
            "subcategory":"Non-durable Goods",
            "type":"Manufacturing & Wholesale Goods"
        }
    ],
    "sg:phone":"+44 20 8367 3367",
    "sg:postcode":"EN1 1UU",
    "sg:province":"Greater London",
    "sg:tags":[
        "carry",
        "cash"
    ],
    "wof:name":"W B Poultry & Meats Ltd.",
    "wof:placetype":"venue"
},
  "geometry": {"coordinates":[-0.060854,51.642544],"type":"Point"}
}