{
  "type": "Feature",
  "properties": {
    "addr:full":"72-77 Lower Tower Street, Newtown Birmingham West Midlands B19 3NF",
    "addr:housenumber":"72-77",
    "addr:postcode":"b19 3nf",
    "addr:street":"Lower Tower Street",
    "iso:country":"GB",
    "sg:address":"72-77 Lower Tower Street, Newtown",
    "sg:city":"Birmingham",
    "sg:classifiers":[
        {
            "category":"Manufacturing",
            "subcategory":"Metals",
            "type":"Manufacturing & Wholesale Goods"
        },
        {
            "category":"Building & Trades",
            "subcategory":"Construction",
            "type":"Services"
        }
    ],
    "sg:phone":"+44 121 359 3023",
    "sg:postcode":"B19 3NF",
    "sg:province":"West Midlands",
    "sg:tags":[
        "pressworkers",
        "worker"
    ],
    "wof:name":"R & E Presswork Ltd",
    "wof:placetype":"venue"
},
  "geometry": {"coordinates":[-1.8976659775,52.4903564453],"type":"Point"}
}