{
  "type": "Feature",
  "properties": {
    "iso:country":"GB",
    "sg:address":"22 Holyoake Place",
    "sg:city":"Rugeley",
    "sg:classifiers":[
        {
            "category":"Shopping",
            "subcategory":"News",
            "type":"Retail Goods"
        }
    ],
    "sg:phone":"+44 1889 583361",
    "sg:postcode":"WS15 2NP",
    "sg:province":"Staffordshire",
    "sg:tags":[
        "newsagent"
    ],
    "wof:name":"Pams News Shops",
    "wof:placetype":"venue"
},
  "geometry": {"coordinates":[-1.94898,52.769386],"type":"Point"}
}