{
  "type": "Feature",
  "properties": {
    "addr:full":"19 Spencer Bridge Road Northampton Northamptonshire NN5 5HA",
    "addr:housenumber":"19",
    "addr:postcode":"nn5 5ha",
    "addr:street":"Spencer Bridge Road",
    "iso:country":"GB",
    "sg:address":"19 Spencer Bridge Road",
    "sg:city":"Northampton",
    "sg:classifiers":[
        {
            "category":"Fast Food",
            "type":"Food & Drink"
        }
    ],
    "sg:phone":"+44 1604 751554",
    "sg:postcode":"NN5 5HA",
    "sg:province":"Northamptonshire",
    "sg:tags":[
        "away",
        "take"
    ],
    "wof:name":"Gate of India",
    "wof:placetype":"venue"
},
  "geometry": {"coordinates":[-0.915128,52.241531],"type":"Point"}
}