{
  "type": "Feature",
  "properties": {
    "addr:full":"Wholesale Fruit Centre, Bessemer Rd Cardiff Cardiff CF11 8BE",
    "addr:postcode":"cf11 8be",
    "addr:street":"Bessemer Rd",
    "iso:country":"GB",
    "sg:address":"Wholesale Fruit Centre, Bessemer Rd",
    "sg:city":"Cardiff",
    "sg:classifiers":[
        {
            "category":"Wholesale",
            "subcategory":"Fruits & Vegetables",
            "type":"Manufacturing & Wholesale Goods"
        }
    ],
    "sg:postcode":"CF11 8BE",
    "sg:province":"Cardiff",
    "wof:name":"Redbridge Produce & Flowers Ltd",
    "wof:placetype":"venue"
},
  "geometry": {"coordinates":[-3.19854,51.467411],"type":"Point"}
}