{
  "type": "Feature",
  "properties": {
    "addr:full":"Unit 5 Avon Gorge Industrial Estate, Portview Road, Avonmouth Bristol City of Bristol BS11 9LQ",
    "addr:housenumber":"unit 5",
    "addr:postcode":"bs11 9lq",
    "addr:street":"Avon Gorge Industrial;Portview Road",
    "iso:country":"GB",
    "sg:address":"Unit 5 Avon Gorge Industrial Estate, Portview Road, Avonmouth",
    "sg:city":"Bristol",
    "sg:classifiers":[
        {
            "category":"Manufacturing",
            "subcategory":"Food",
            "type":"Manufacturing & Wholesale Goods"
        }
    ],
    "sg:phone":"+44 117 982 4742",
    "sg:postcode":"BS11 9LQ",
    "sg:province":"City of Bristol",
    "sg:tags":[
        "mnfr",
        "drink",
        "soft"
    ],
    "wof:name":"Osprey Developments Ltd.",
    "wof:placetype":"venue"
},
  "geometry": {"coordinates":[-2.694124,51.498917],"type":"Point"}
}