{
  "type": "Feature",
  "properties": {
    "iso:country":"GB",
    "sg:address":"Old School Cottage, Coggeshall Road",
    "sg:city":"Colchester",
    "sg:classifiers":[
        {
            "category":"Professional",
            "subcategory":"Detective & Security Services",
            "type":"Services"
        }
    ],
    "sg:phone":"+44 1787 221810",
    "sg:postcode":"CO6 2JU",
    "sg:province":"Essex",
    "sg:tags":[
        "equipment",
        "installers"
    ],
    "wof:name":"Graham Scott Security Installations",
    "wof:placetype":"venue"
},
  "geometry": {"coordinates":[0.69699,51.910782],"type":"Point"}
}