{
  "type": "Feature",
  "properties": {
    "addr:full":"Unit 7, 5 Marsland Street Stockport Cheshire SK7 4ER",
    "addr:housenumber":"unit;5",
    "addr:postcode":"sk7 4er",
    "addr:street":"Marsland Street",
    "iso:country":"GB",
    "sg:address":"Unit 7, 5 Marsland Street",
    "sg:city":"Stockport",
    "sg:classifiers":[
        {
            "category":"Shopping",
            "subcategory":"Clothing, Apparel, & Fashions",
            "type":"Retail Goods"
        }
    ],
    "sg:postcode":"SK7 4ER",
    "sg:province":"Cheshire",
    "sg:tags":[
        "clothing"
    ],
    "wof:name":"Hopkins 95",
    "wof:placetype":"venue"
},
  "geometry": {"coordinates":[-2.121738,53.378502],"type":"Point"}
}