{
  "type": "Feature",
  "properties": {
    "addr:full":"37 Glade Close, Petit Meadow Northampton Northamptonshire NN3 9SN",
    "addr:housenumber":"37",
    "addr:postcode":"nn3 9sn",
    "addr:street":"Glade Close Petit Meadow",
    "iso:country":"GB",
    "sg:address":"37 Glade Close, Petit Meadow",
    "sg:city":"Northampton",
    "sg:classifiers":[
        {
            "category":"Building & Trades",
            "subcategory":"Landscaping Services",
            "type":"Services"
        }
    ],
    "sg:postcode":"NN3 9SN",
    "sg:province":"Northamptonshire",
    "sg:tags":[
        "landscape",
        "contractor"
    ],
    "wof:name":"Fairview Landscapes",
    "wof:placetype":"venue"
},
  "geometry": {"coordinates":[-0.8182880282,52.2526283264],"type":"Point"}
}