{
  "type": "Feature",
  "properties": {
    "iso:country":"GB",
    "sg:address":"59a High Street",
    "sg:city":"Hungerford",
    "sg:classifiers":[
        {
            "category":"Manufacturing",
            "subcategory":"Building Materials",
            "type":"Manufacturing & Wholesale Goods"
        }
    ],
    "sg:phone":"+44 1488 681818",
    "sg:postcode":"RG17 0NE",
    "sg:province":"Berkshire",
    "sg:tags":[
        "tarmac",
        "asphalt"
    ],
    "wof:name":"Alliance Surfacing Ltd.",
    "wof:placetype":"venue"
},
  "geometry": {"coordinates":[-1.51677,51.412525],"type":"Point"}
}