{
  "type": "Feature",
  "properties": {
    "addr:full":"Genners Lane, Bartley Grn Birmingham West Midlands B32 3NT",
    "addr:postcode":"b32 3nt",
    "addr:street":"Genners Lane Bartley Grn",
    "iso:country":"GB",
    "sg:address":"Genners Lane, Bartley Grn",
    "sg:city":"Birmingham",
    "sg:classifiers":[
        {
            "category":"Education",
            "subcategory":"University",
            "type":"Public Place"
        }
    ],
    "sg:phone":"+44 121 476 1181",
    "sg:postcode":"B32 3NT",
    "sg:province":"West Midlands",
    "sg:tags":[
        "higher"
    ],
    "wof:name":"Newman College",
    "wof:placetype":"venue"
},
  "geometry": {"coordinates":[-1.9927539825,52.4324607849],"type":"Point"}
}