{
  "type": "Feature",
  "properties": {
    "addr:full":"2 Friarsgate, Grosvenor Street Chester Cheshire CH1 1XG",
    "addr:housenumber":"2",
    "addr:postcode":"ch1 1xg",
    "addr:street":"Friarsgate Grosvenor Street",
    "iso:country":"GB",
    "sg:address":"2 Friarsgate, Grosvenor Street",
    "sg:city":"Chester",
    "sg:classifiers":[
        {
            "category":"Real Estate",
            "subcategory":"Real Estate Agent",
            "type":"Services"
        }
    ],
    "sg:postcode":"CH1 1XG",
    "sg:province":"Cheshire",
    "wof:name":"The Ludgate Estates Ltd.",
    "wof:placetype":"venue"
},
  "geometry": {"coordinates":[-2.887574,53.190956],"type":"Point"}
}