{
  "type": "Feature",
  "properties": {
    "addr:full":"4 Alcester Drive Leicester Leicestershire LE5 6LA",
    "addr:housenumber":"4",
    "addr:postcode":"le5 6la",
    "addr:street":"Alcester Drive",
    "iso:country":"GB",
    "sg:address":"4 Alcester Drive",
    "sg:city":"Leicester",
    "sg:classifiers":[
        {
            "category":"Personal",
            "type":"Services"
        }
    ],
    "sg:postcode":"LE5 6LA",
    "sg:province":"Leicestershire",
    "sg:tags":[
        "wedding"
    ],
    "wof:name":"Peter R Gwilt Photographer",
    "wof:placetype":"venue"
},
  "geometry": {"coordinates":[-1.061095,52.628918],"type":"Point"}
}