{
  "type": "Feature",
  "properties": {
    "addr:full":"Municipal Markets, Circus Street Brighton East Sussex BN2 9QF",
    "addr:postcode":"bn2 9qf",
    "addr:street":"Circus Street",
    "iso:country":"GB",
    "sg:address":"Municipal Markets, Circus Street",
    "sg:city":"Brighton",
    "sg:classifiers":[
        {
            "category":"Food & Beverages",
            "subcategory":"Fruits & Vegetables",
            "type":"Retail Goods"
        }
    ],
    "sg:phone":"+44 1273 602781",
    "sg:postcode":"BN2 9QF",
    "sg:province":"East Sussex",
    "sg:tags":[
        "greengrocer"
    ],
    "wof:name":"C H Mears & Sons",
    "wof:placetype":"venue"
},
  "geometry": {"coordinates":[-0.1344909966,50.8282165527],"type":"Point"}
}