{
  "type": "Feature",
  "properties": {
    "iso:country":"GB",
    "sg:address":"24 Broad Street",
    "sg:city":"Nottingham",
    "sg:classifiers":[
        {
            "category":"Bars & Pubs",
            "type":"Food & Drink"
        }
    ],
    "sg:phone":"+44 115 941 4886",
    "sg:postcode":"NG1 3AN",
    "sg:province":"Nottinghamshire",
    "sg:tags":[
        "pubs",
        "inn"
    ],
    "wof:name":"Lord Roberts",
    "wof:placetype":"venue"
},
  "geometry": {"coordinates":[-1.144265,52.954735],"type":"Point"}
}