{
  "type": "Feature",
  "properties": {
    "iso:country":"GB",
    "sg:address":"87a St Andrews Road",
    "sg:city":"Felixstowe",
    "sg:classifiers":[
        {
            "category":"Professional",
            "subcategory":"Business Services",
            "type":"Services"
        },
        {
            "category":"Manufacturing",
            "subcategory":"Signs",
            "type":"Manufacturing & Wholesale Goods"
        }
    ],
    "sg:phone":"+44 1394 271780",
    "sg:postcode":"IP11 7BW",
    "sg:province":"Suffolk",
    "sg:tags":[
        "distribution",
        "writer"
    ],
    "wof:name":"Specialist Studio Kitchen Distribution",
    "wof:placetype":"venue"
},
  "geometry": {"coordinates":[1.351718,51.966187],"type":"Point"}
}