{
  "type": "Feature",
  "properties": {
    "addr:full":"7 Tudor Close, Bromham Bedford Bedfordshire MK43 8LB",
    "addr:housenumber":"7",
    "addr:postcode":"mk43 8lb",
    "addr:street":"Tudor Close",
    "iso:country":"GB",
    "sg:address":"7 Tudor Close, Bromham",
    "sg:city":"Bedford",
    "sg:classifiers":[
        {
            "category":"Professional",
            "type":"Services"
        }
    ],
    "sg:phone":"+44 1234 824117",
    "sg:postcode":"MK43 8LB",
    "sg:province":"Bedfordshire",
    "sg:tags":[
        "entertainer"
    ],
    "wof:name":"Millstream",
    "wof:placetype":"venue"
},
  "geometry": {"coordinates":[-0.5316,52.151569],"type":"Point"}
}