{
  "type": "Feature",
  "properties": {
    "addr:full":"7-9 Handbridge Chester Cheshire CH4 7JE",
    "addr:housenumber":"7-9",
    "addr:postcode":"ch4 7je",
    "iso:country":"GB",
    "sg:address":"7-9 Handbridge",
    "sg:city":"Chester",
    "sg:classifiers":[
        {
            "category":"Shopping",
            "subcategory":"Pharmacy",
            "type":"Retail Goods"
        }
    ],
    "sg:phone":"+44 1244 683454",
    "sg:postcode":"CH4 7JE",
    "sg:province":"Cheshire",
    "sg:tags":[
        "pharmacist",
        "chemist"
    ],
    "wof:name":"Cleansharp",
    "wof:placetype":"venue"
},
  "geometry": {"coordinates":[-2.8878099918,53.1846656799],"type":"Point"}
}