{
  "type": "Feature",
  "properties": {
    "addr:full":"Gym N Slim, Rear Of 208 Stratford Rd Solihull West Midlands B90 3AG",
    "addr:housenumber":"rear;208",
    "addr:postcode":"b90 3ag",
    "addr:street":"N Slim;Stratford Rd",
    "iso:country":"GB",
    "sg:address":"Gym N Slim, Rear Of 208 Stratford Rd",
    "sg:city":"Solihull",
    "sg:classifiers":[
        {
            "category":"Health Services",
            "subcategory":"Clinic",
            "type":"Services"
        }
    ],
    "sg:phone":"+44 121 722 4003",
    "sg:postcode":"B90 3AG",
    "sg:province":"West Midlands",
    "sg:tags":[
        "aromatherapy"
    ],
    "wof:name":"Eileen Lander",
    "wof:placetype":"venue"
},
  "geometry": {"coordinates":[-1.82716,52.411732],"type":"Point"}
}