{
  "type": "Feature",
  "properties": {
    "addr:full":"Nursery Farm, Woodborough Pewsey Wiltshire SN9 5PF",
    "addr:postcode":"sn9 5pf",
    "addr:street":"Pewsey",
    "iso:country":"GB",
    "sg:address":"Nursery Farm, Woodborough",
    "sg:city":"Pewsey",
    "sg:classifiers":[
        {
            "category":"Home & Garden",
            "subcategory":"Garden Supply",
            "type":"Retail Goods"
        }
    ],
    "sg:phone":"+44 1672 851249",
    "sg:postcode":"SN9 5PF",
    "sg:province":"Wiltshire",
    "sg:tags":[
        "nursery",
        "centre"
    ],
    "wof:name":"Walter T Ware Ltd.",
    "wof:placetype":"venue"
},
  "geometry": {"coordinates":[-1.762319,51.340286],"type":"Point"}
}