{
  "type": "Feature",
  "properties": {
    "iso:country":"GB",
    "sg:address":"Scotchman Road, Manningham",
    "sg:city":"Bradford",
    "sg:classifiers":[
        {
            "category":"Education",
            "subcategory":"School",
            "type":"Public Place"
        },
        {
            "category":"Government",
            "subcategory":"Office",
            "type":"Public Place"
        }
    ],
    "sg:phone":"+44 1274 495934",
    "sg:postcode":"BD9 5AT",
    "sg:province":"West Yorkshire",
    "sg:tags":[
        "local",
        "authority"
    ],
    "wof:name":"Margaret McMillan First School & Nursery",
    "wof:placetype":"venue"
},
  "geometry": {"coordinates":[-1.788743,53.809502],"type":"Point"}
}