{
  "type": "Feature",
  "properties": {
    "iso:country":"GB",
    "sg:address":"Oldham Indoor Market",
    "sg:city":"Oldham",
    "sg:classifiers":[
        {
            "category":"Shopping",
            "subcategory":"Pets & Pet Supplies",
            "type":"Retail Goods"
        }
    ],
    "sg:phone":"+44 161 627 5668",
    "sg:postcode":"OL1 3BG",
    "sg:province":"Lancashire",
    "wof:name":"Animal Magic Pet Stores",
    "wof:placetype":"venue"
},
  "geometry": {"coordinates":[-2.112329,53.54031],"type":"Point"}
}