{
  "type": "Feature",
  "properties": {
    "iso:country":"GB",
    "sg:address":"14-16 Speke Road, Garston",
    "sg:city":"Liverpool",
    "sg:classifiers":[
        {
            "category":"Shopping",
            "subcategory":"Discount & Variety Stores",
            "type":"Retail Goods"
        }
    ],
    "sg:phone":"+44 151 280 0466",
    "sg:postcode":"L19 2PA",
    "sg:province":"Merseyside",
    "sg:tags":[
        "centre"
    ],
    "wof:name":"Edgars Discount Store",
    "wof:placetype":"venue"
},
  "geometry": {"coordinates":[-2.8959031105,53.3532028198],"type":"Point"}
}