{
  "type": "Feature",
  "properties": {
    "addr:full":"Tyddyn Mali Llanrwst Conwy LL26 0DZ",
    "addr:postcode":"ll26 0dz",
    "iso:country":"GB",
    "sg:address":"Tyddyn Mali",
    "sg:city":"Llanrwst",
    "sg:classifiers":[
        {
            "category":"Autos & Motor Vehicles",
            "subcategory":"Automobile Sales",
            "type":"Retail Goods"
        }
    ],
    "sg:phone":"+44 1492 641905",
    "sg:postcode":"LL26 0DZ",
    "sg:province":"Conwy",
    "sg:tags":[
        "car"
    ],
    "wof:name":"Burtech Specialised Trailers",
    "wof:placetype":"venue"
},
  "geometry": {"coordinates":[-3.7977,53.137661],"type":"Point"}
}