{
  "type": "Feature",
  "properties": {
    "iso:country":"GB",
    "sg:address":"23 Brunel Way",
    "sg:city":"Thetford",
    "sg:classifiers":[
        {
            "category":"Recreation",
            "subcategory":"Go Karts",
            "type":"Entertainment"
        }
    ],
    "sg:postcode":"IP24 1HP",
    "sg:province":"Norfolk",
    "sg:tags":[
        "karting"
    ],
    "wof:name":"Fullerton Racing Karts",
    "wof:placetype":"venue"
},
  "geometry": {"coordinates":[0.73968,52.426235],"type":"Point"}
}