{
  "type": "Feature",
  "properties": {
    "addr:full":"The Rear Of 28 Kent Road Orpington Kent BR5 4AD",
    "addr:housenumber":"of 28",
    "addr:postcode":"br5 4ad",
    "addr:street":"Kent Road",
    "iso:country":"GB",
    "sg:address":"The Rear Of 28 Kent Road",
    "sg:city":"Orpington",
    "sg:classifiers":[
        {
            "category":"Professional",
            "type":"Services"
        }
    ],
    "sg:phone":"+44 1689 829202",
    "sg:postcode":"BR5 4AD",
    "sg:province":"Kent",
    "sg:tags":[
        "shopfitters"
    ],
    "wof:name":"Prompt Aluminium Shopfronts",
    "wof:placetype":"venue"
},
  "geometry": {"coordinates":[0.1123600006,51.3863296509],"type":"Point"}
}