{
  "type": "Feature",
  "properties": {
    "addr:full":"37 Downsford Road Seaford East Sussex BN25 4PU",
    "addr:housenumber":"37",
    "addr:postcode":"bn25 4pu",
    "addr:street":"Downsford Road",
    "iso:country":"GB",
    "sg:address":"37 Downsford Road",
    "sg:city":"Seaford",
    "sg:classifiers":[
        {
            "category":"Real Estate",
            "subcategory":"Surveying",
            "type":"Services"
        },
        {
            "category":"Real Estate",
            "subcategory":"Real Estate Agent",
            "type":"Services"
        }
    ],
    "sg:phone":"+44 1323 892587",
    "sg:postcode":"BN25 4PU",
    "sg:province":"East Sussex",
    "sg:tags":[
        "surveyor",
        "valuer"
    ],
    "wof:name":"Roy Sharman & Co.",
    "wof:placetype":"venue"
},
  "geometry": {"coordinates":[0.1141759977,50.7730827332],"type":"Point"}
}