{
  "type": "Feature",
  "properties": {
    "addr:full":"1 Ash Gr Ripon North Yorkshire HG4 2DJ",
    "addr:housenumber":"1",
    "addr:postcode":"hg4 2dj",
    "addr:street":"Ash Gr",
    "iso:country":"GB",
    "sg:address":"1 Ash Gr",
    "sg:city":"Ripon",
    "sg:classifiers":[
        {
            "category":"Home & Garden",
            "subcategory":"Furniture",
            "type":"Retail Goods"
        }
    ],
    "sg:phone":"+44 1765 602790",
    "sg:postcode":"HG4 2DJ",
    "sg:province":"North Yorkshire",
    "wof:name":"Morgans of Ripon",
    "wof:placetype":"venue"
},
  "geometry": {"coordinates":[-1.540989995,54.1391868591],"type":"Point"}
}