{
  "type": "Feature",
  "properties": {
    "addr:full":"Unit 3, The Chase, West Thurrock Romford Essex RM16 1XT",
    "addr:housenumber":"unit 3",
    "addr:postcode":"rm16 1xt",
    "addr:street":"The Chase",
    "iso:country":"GB",
    "sg:address":"Unit 3, The Chase, West Thurrock",
    "sg:city":"Romford",
    "sg:classifiers":[
        {
            "category":"Retail",
            "subcategory":"Auto Repair",
            "type":"Services"
        }
    ],
    "sg:phone":"+44 1375 391884",
    "sg:postcode":"RM16 1XT",
    "sg:province":"Essex",
    "sg:tags":[
        "modification",
        "garage"
    ],
    "wof:name":"Super Car Garage",
    "wof:placetype":"venue"
},
  "geometry": {"coordinates":[0.3427,51.505421],"type":"Point"}
}