{
  "type": "Feature",
  "properties": {
    "addr:full":"138 Plymyard Avenue Wirral Cheshire CH62 8HF",
    "addr:housenumber":"138",
    "addr:postcode":"ch62 8hf",
    "addr:street":"Plymyard Avenue",
    "iso:country":"GB",
    "sg:address":"138 Plymyard Avenue",
    "sg:city":"Wirral",
    "sg:classifiers":[
        {
            "category":"Food & Beverages",
            "subcategory":"Fruits & Vegetables",
            "type":"Retail Goods"
        }
    ],
    "sg:postcode":"CH62 8HF",
    "sg:province":"Cheshire",
    "sg:tags":[
        "greengrocer"
    ],
    "wof:name":"A & J Grindrod",
    "wof:placetype":"venue"
},
  "geometry": {"coordinates":[-2.9782168865,53.3131752014],"type":"Point"}
}