{
  "type": "Feature",
  "properties": {
    "addr:full":"80 Oldham Rd Manchester Greater Manchester M4 5EB",
    "addr:housenumber":"80",
    "addr:postcode":"m4 5eb",
    "addr:street":"Oldham Rd",
    "iso:country":"GB",
    "sg:address":"80 Oldham Rd",
    "sg:city":"Manchester",
    "sg:classifiers":[
        {
            "category":"Recreation",
            "subcategory":"Gun Range",
            "type":"Entertainment"
        }
    ],
    "sg:phone":"+44 161 228 1270",
    "sg:postcode":"M4 5EB",
    "sg:province":"Greater Manchester",
    "sg:tags":[
        "operator",
        "tour"
    ],
    "wof:name":"Club Canaries",
    "wof:placetype":"venue"
},
  "geometry": {"coordinates":[-2.2290890217,53.4861450195],"type":"Point"}
}