{
  "type": "Feature",
  "properties": {
    "addr:full":"75 Bloomfield Rd London Greater London SE18 7JJ",
    "addr:housenumber":"75",
    "addr:postcode":"se18 7jj",
    "addr:street":"Bloomfield Rd",
    "iso:country":"GB",
    "sg:address":"75 Bloomfield Rd",
    "sg:city":"London",
    "sg:classifiers":[
        {
            "category":"Manufacturing",
            "subcategory":"Petroleum Products",
            "type":"Manufacturing & Wholesale Goods"
        }
    ],
    "sg:postcode":"SE18 7JJ",
    "sg:province":"Greater London",
    "sg:tags":[
        "double",
        "glazing"
    ],
    "wof:name":"L R Double Glazing",
    "wof:placetype":"venue"
},
  "geometry": {"coordinates":[0.071226,51.484718],"type":"Point"}
}