{
  "type": "Feature",
  "properties": {
    "addr:full":"8 Broomfield Square Aberlour Moray AB38 9QP",
    "addr:housenumber":"8",
    "addr:postcode":"ab38 9qp",
    "addr:street":"Broomfield Square Aberlour",
    "iso:country":"GB",
    "sg:address":"8 Broomfield Square",
    "sg:city":"Aberlour",
    "sg:classifiers":[
        {
            "category":"Bars & Pubs",
            "type":"Food & Drink"
        }
    ],
    "sg:phone":"+44 1340 881771",
    "sg:postcode":"AB38 9QP",
    "sg:province":"Moray",
    "sg:tags":[
        "pubs",
        "inn"
    ],
    "wof:name":"The Mash Tun",
    "wof:placetype":"venue"
},
  "geometry": {"coordinates":[-3.2241249084,57.4711647034],"type":"Point"}
}