{
  "type": "Feature",
  "properties": {
    "iso:country":"GB",
    "sg:address":"225 Springfield Road",
    "sg:city":"Sutton Coldfield",
    "sg:classifiers":[
        {
            "category":"Shopping",
            "subcategory":"News",
            "type":"Retail Goods"
        }
    ],
    "sg:phone":"+44 121 378 1174",
    "sg:postcode":"B76 2SZ",
    "sg:province":"Warwickshire",
    "sg:tags":[
        "newsagent"
    ],
    "wof:name":"Dillons Newsagents Ltd.",
    "wof:placetype":"venue"
},
  "geometry": {"coordinates":[-1.786941,52.559326],"type":"Point"}
}