{
  "type": "Feature",
  "properties": {
    "iso:country":"GB",
    "sg:address":"The Wheatsheaf, Coton, Milwich",
    "sg:city":"Stafford",
    "sg:classifiers":[
        {
            "category":"Farming",
            "subcategory":"Livestock Farm",
            "type":"Manufacturing & Wholesale Goods"
        }
    ],
    "sg:phone":"+44 1889 505200",
    "sg:postcode":"ST18 0ET",
    "sg:province":"Staffordshire",
    "sg:tags":[
        "others"
    ],
    "wof:name":"R D & I E Kite",
    "wof:placetype":"venue"
},
  "geometry": {"coordinates":[-2.0416789055,52.8883857727],"type":"Point"}
}