{
  "type": "Feature",
  "properties": {
    "iso:country":"GB",
    "sg:address":"75-76 Grand Pde",
    "sg:city":"Brighton",
    "sg:classifiers":[
        {
            "category":"Sports & Exercise",
            "subcategory":"Gym",
            "type":"Entertainment"
        }
    ],
    "sg:phone":"+44 1273 679968",
    "sg:postcode":"BN2 2JA",
    "sg:province":"East Sussex",
    "sg:tags":[
        "fitness",
        "health",
        "centre"
    ],
    "wof:name":"Lazy Days",
    "wof:placetype":"venue"
},
  "geometry": {"coordinates":[-0.135765,50.823715],"type":"Point"}
}