{
  "type": "Feature",
  "properties": {
    "addr:full":"Unit 16, Fountayne Road London Greater London N15 4QL",
    "addr:housenumber":"unit 16",
    "addr:postcode":"n15 4ql",
    "addr:street":"Fountayne Road",
    "iso:country":"GB",
    "sg:address":"Unit 16, Fountayne Road",
    "sg:city":"London",
    "sg:classifiers":[
        {
            "category":"Retail",
            "subcategory":"Event Space",
            "type":"Services"
        }
    ],
    "sg:phone":"+44 20 8808 2403",
    "sg:postcode":"N15 4QL",
    "sg:province":"Greater London",
    "sg:tags":[
        "exhibition",
        "organiser"
    ],
    "wof:name":"P A F Promotions",
    "wof:placetype":"venue"
},
  "geometry": {"coordinates":[-0.0636669993,51.584854126],"type":"Point"}
}