{
  "type": "Feature",
  "properties": {
    "addr:full":"189 Lower Clapton Road London Greater London E5 8EG",
    "addr:housenumber":"189",
    "addr:postcode":"e5 8eg",
    "addr:street":"Lower Clapton Road",
    "iso:country":"GB",
    "sg:address":"189 Lower Clapton Road",
    "sg:city":"London",
    "sg:classifiers":[
        {
            "category":"Food & Beverages",
            "subcategory":"Meat & Fish",
            "type":"Retail Goods"
        },
        {
            "category":"Food & Beverages",
            "subcategory":"Groceries & Convenience Stores",
            "type":"Retail Goods"
        }
    ],
    "sg:phone":"+44 20 8985 6880",
    "sg:postcode":"E5 8EG",
    "sg:province":"Greater London",
    "sg:tags":[
        "shop",
        "chip"
    ],
    "wof:name":"Mermaid Fish Shop",
    "wof:placetype":"venue"
},
  "geometry": {"coordinates":[-0.055564,51.556881],"type":"Point"}
}