{
  "type": "Feature",
  "properties": {
    "iso:country":"GB",
    "sg:address":"318 Dumbarton Road",
    "sg:city":"Glasgow",
    "sg:classifiers":[
        {
            "category":"Shopping",
            "subcategory":"News",
            "type":"Retail Goods"
        },
        {
            "category":"Food & Beverages",
            "subcategory":"Groceries & Convenience Stores",
            "type":"Retail Goods"
        }
    ],
    "sg:phone":"+44 141 334 0503",
    "sg:postcode":"G11 6TF",
    "sg:province":"Glasgow City",
    "sg:tags":[
        "newsagent"
    ],
    "wof:name":"Fags & Mags",
    "wof:placetype":"venue"
},
  "geometry": {"coordinates":[-4.306143,55.871021],"type":"Point"}
}