{
  "type": "Feature",
  "properties": {
    "addr:full":"65 Green Lane Edgware Greater London HA8 7PZ",
    "addr:housenumber":"65",
    "addr:postcode":"ha8 7pz",
    "addr:street":"Green Lane",
    "iso:country":"GB",
    "sg:address":"65 Green Lane",
    "sg:city":"Edgware",
    "sg:classifiers":[
        {
            "category":"Personal",
            "type":"Services"
        },
        {
            "category":"Professional",
            "subcategory":"Lawyer & Legal Services",
            "type":"Services"
        }
    ],
    "sg:phone":"+44 20 8958 9758",
    "sg:postcode":"HA8 7PZ",
    "sg:province":"Greater London",
    "sg:tags":[
        "advice",
        "counselling"
    ],
    "wof:name":"Accord Counselling Services",
    "wof:placetype":"venue"
},
  "geometry": {"coordinates":[-0.280856,51.61673],"type":"Point"}
}