{
  "type": "Feature",
  "properties": {
    "addr:full":"Glenbryde Rd West Kilbride North Ayrshire KA23 9NJ",
    "addr:postcode":"ka23 9nj",
    "addr:street":"Glenbryde Rd",
    "iso:country":"GB",
    "sg:address":"Glenbryde Rd",
    "sg:city":"West Kilbride",
    "sg:classifiers":[
        {
            "category":"Education",
            "subcategory":"Special Training",
            "type":"Public Place"
        }
    ],
    "sg:phone":"+44 1294 829303",
    "sg:postcode":"KA23 9NJ",
    "sg:province":"North Ayrshire",
    "sg:tags":[
        "product",
        "centre"
    ],
    "wof:name":"Seamill Training Centre",
    "wof:placetype":"venue"
},
  "geometry": {"coordinates":[-4.8588290215,55.6975212097],"type":"Point"}
}