{
  "type": "Feature",
  "properties": {
    "addr:full":"7 Cheviot Clo Tonbridge Kent TN9 1NH",
    "addr:housenumber":"7",
    "addr:postcode":"tn9 1nh",
    "addr:street":"Cheviot Clo Tonbridge",
    "iso:country":"GB",
    "sg:address":"7 Cheviot Clo",
    "sg:city":"Tonbridge",
    "sg:classifiers":[
        {
            "category":"Professional",
            "subcategory":"Printing & Photocopies",
            "type":"Services"
        }
    ],
    "sg:phone":"+44 1732 368843",
    "sg:postcode":"TN9 1NH",
    "sg:province":"Kent",
    "sg:tags":[
        "duplicating",
        "copying"
    ],
    "wof:name":"Instep Ltd",
    "wof:placetype":"venue"
},
  "geometry": {"coordinates":[0.280557,51.205368],"type":"Point"}
}