{
  "type": "Feature",
  "properties": {
    "addr:full":"Unit 2a, Watlington Industrial Estate, Cuxham Road Watlington Oxfordshire OX49 5LU",
    "addr:housenumber":"unit 2a",
    "addr:postcode":"ox49 5lu",
    "addr:street":"Industrial Estate Cuxham Road",
    "iso:country":"GB",
    "sg:address":"Unit 2a, Watlington Industrial Estate, Cuxham Road",
    "sg:city":"Watlington",
    "sg:classifiers":[
        {
            "category":"Professional",
            "subcategory":"Engineering",
            "type":"Services"
        }
    ],
    "sg:phone":"+44 1491 614422",
    "sg:postcode":"OX49 5LU",
    "sg:province":"Oxfordshire",
    "sg:tags":[
        "precision",
        "engineer"
    ],
    "wof:name":"Chiltern Cam Service Ltd.",
    "wof:placetype":"venue"
},
  "geometry": {"coordinates":[-1.005681,51.644085],"type":"Point"}
}