{
  "type": "Feature",
  "properties": {
    "addr:full":"31 Woodshires Rd, Longford Coventry Warwickshire CV6 6AA",
    "addr:housenumber":"31",
    "addr:postcode":"cv6 6aa",
    "addr:street":"Woodshires Rd",
    "iso:country":"GB",
    "sg:address":"31 Woodshires Rd, Longford",
    "sg:city":"Coventry",
    "sg:classifiers":[
        {
            "category":"Building & Trades",
            "subcategory":"Construction",
            "type":"Services"
        }
    ],
    "sg:phone":"+44 24 7636 6297",
    "sg:postcode":"CV6 6AA",
    "sg:province":"Warwickshire",
    "sg:tags":[
        "builder"
    ],
    "wof:name":"Yew Tree Builders",
    "wof:placetype":"venue"
},
  "geometry": {"coordinates":[-1.491135,52.454304],"type":"Point"}
}