{
  "type": "Feature",
  "properties": {
    "iso:country":"GB",
    "sg:address":"18 Sir Simons Arcade",
    "sg:city":"Lancaster",
    "sg:classifiers":[
        {
            "category":"Sports & Exercise",
            "subcategory":"Sports Center",
            "type":"Entertainment"
        }
    ],
    "sg:phone":"+44 1524 68397",
    "sg:postcode":"LA1 1JL",
    "sg:province":"Lancashire",
    "sg:tags":[
        "shop",
        "good"
    ],
    "wof:name":"Scotts Sports",
    "wof:placetype":"venue"
},
  "geometry": {"coordinates":[-2.802274,54.048115],"type":"Point"}
}