{
  "type": "Feature",
  "properties": {
    "iso:country":"GB",
    "sg:address":"Old Barn, Draughton",
    "sg:city":"Northampton",
    "sg:classifiers":[
        {
            "category":"Home & Garden",
            "subcategory":"Kitchen Supply",
            "type":"Retail Goods"
        }
    ],
    "sg:phone":"+44 1604 686599",
    "sg:postcode":"NN6 9JQ",
    "sg:province":"Northamptonshire",
    "sg:tags":[
        "table"
    ],
    "wof:name":"Walters China Trade",
    "wof:placetype":"venue"
},
  "geometry": {"coordinates":[-0.883054,52.382946],"type":"Point"}
}