{
  "type": "Feature",
  "properties": {
    "iso:country":"GB",
    "sg:address":"202 Leeds Road",
    "sg:city":"Bradford",
    "sg:classifiers":[
        {
            "category":"Train Station",
            "subcategory":"Rail",
            "type":"Transportation"
        }
    ],
    "sg:postcode":"BD3 9PS",
    "sg:province":"West Yorkshire",
    "sg:tags":[
        "caravan"
    ],
    "wof:name":"Pro-Tec Covers Ltd.",
    "wof:placetype":"venue"
},
  "geometry": {"coordinates":[-1.74215,53.793041],"type":"Point"}
}