{
  "type": "Feature",
  "properties": {
    "addr:full":"Cragg Hill Farm, Crag Lane, Killinghall Harrogate North Yorkshire HG3 2BB",
    "addr:postcode":"hg3 2bb",
    "addr:street":"Cragg Hill;Crag Lane",
    "iso:country":"GB",
    "sg:address":"Cragg Hill Farm, Crag Lane, Killinghall",
    "sg:city":"Harrogate",
    "sg:classifiers":[
        {
            "category":"Farming",
            "subcategory":"Farm",
            "type":"Manufacturing & Wholesale Goods"
        }
    ],
    "sg:postcode":"HG3 2BB",
    "sg:province":"North Yorkshire",
    "sg:tags":[
        "mixed",
        "crop"
    ],
    "wof:name":"I Voakes",
    "wof:placetype":"venue"
},
  "geometry": {"coordinates":[-1.65457201,54.0109634399],"type":"Point"}
}