{
  "type": "Feature",
  "properties": {
    "iso:country":"GB",
    "sg:address":"Front St",
    "sg:city":"Consett",
    "sg:classifiers":[
        {
            "category":"Bars & Pubs",
            "type":"Food & Drink"
        }
    ],
    "sg:phone":"+44 1207 560213",
    "sg:postcode":"DH8 0PJ",
    "sg:province":"Durham",
    "sg:tags":[
        "pubs",
        "inn"
    ],
    "wof:name":"The Chelmsford",
    "wof:placetype":"venue"
},
  "geometry": {"coordinates":[-1.858649,54.871765],"type":"Point"}
}