{
  "type": "Feature",
  "properties": {
    "iso:country":"GB",
    "sg:address":"30 Earsham Street",
    "sg:city":"Bungay",
    "sg:classifiers":[
        {
            "category":"Shopping",
            "subcategory":"Antiques",
            "type":"Retail Goods"
        }
    ],
    "sg:postcode":"NR35 1AQ",
    "sg:province":"Norfolk",
    "wof:name":"COUNTRY HOUSE ANTIQUES",
    "wof:placetype":"venue"
},
  "geometry": {"coordinates":[1.43496,52.456589],"type":"Point"}
}