{
  "type": "Feature",
  "properties": {
    "addr:full":"Westfield Industrial Estate, Portsmouth Rd Waterlooville Hampshire PO8 9JX",
    "addr:postcode":"po8 9jx",
    "addr:street":"Estate Portsmouth Rd",
    "iso:country":"GB",
    "sg:address":"Westfield Industrial Estate, Portsmouth Rd",
    "sg:city":"Waterlooville",
    "sg:classifiers":[
        {
            "category":"Retail",
            "subcategory":"Auto Repair",
            "type":"Services"
        }
    ],
    "sg:phone":"+44 23 9257 1150",
    "sg:postcode":"PO8 9JX",
    "sg:province":"Hampshire",
    "sg:tags":[
        "retreading",
        "tyre"
    ],
    "wof:name":"Tyre Express",
    "wof:placetype":"venue"
},
  "geometry": {"coordinates":[-0.9984599948,50.9136505127],"type":"Point"}
}