{
  "type": "Feature",
  "properties": {
    "iso:country":"GB",
    "sg:address":"Beechwood, Bridge Street, Saline",
    "sg:city":"Dunfermline",
    "sg:classifiers":[
        {
            "category":"Professional",
            "subcategory":"Management & Consulting",
            "type":"Services"
        }
    ],
    "sg:postcode":"KY12 9TS",
    "sg:province":"Fife",
    "sg:tags":[
        "consultant",
        "business"
    ],
    "wof:name":"Robb Clark Associates",
    "wof:placetype":"venue"
},
  "geometry": {"coordinates":[-3.572988987,56.1148986816],"type":"Point"}
}