{
  "type": "Feature",
  "properties": {
    "addr:full":"50 Main St Leeds North Yorkshire LS25 1AA",
    "addr:housenumber":"50",
    "addr:postcode":"ls25 1aa",
    "addr:street":"Main St",
    "iso:country":"GB",
    "sg:address":"50 Main St",
    "sg:city":"Leeds",
    "sg:classifiers":[
        {
            "category":"Manufacturing",
            "subcategory":"Wood Products",
            "type":"Manufacturing & Wholesale Goods"
        }
    ],
    "sg:postcode":"LS25 1AA",
    "sg:province":"North Yorkshire",
    "sg:tags":[
        "packaging",
        "crate",
        "pallets"
    ],
    "wof:name":"Schurpack Horsens",
    "wof:placetype":"venue"
},
  "geometry": {"coordinates":[-1.388100028,53.7945747375],"type":"Point"}
}