{
  "type": "Feature",
  "properties": {
    "addr:full":"144 Keppochhill Road Glasgow East Dunbartonshire G21 1HE",
    "addr:housenumber":"144",
    "addr:postcode":"g21 1he",
    "addr:street":"Keppochhill Road",
    "iso:country":"GB",
    "sg:address":"144 Keppochhill Road",
    "sg:city":"Glasgow",
    "sg:classifiers":[
        {
            "category":"Cafe",
            "type":"Food & Drink"
        }
    ],
    "sg:postcode":"G21 1HE",
    "sg:province":"East Dunbartonshire",
    "sg:tags":[
        "tea",
        "room"
    ],
    "wof:name":"Snack Stop",
    "wof:placetype":"venue"
},
  "geometry": {"coordinates":[-4.238424778,55.8795433044],"type":"Point"}
}