{
  "type": "Feature",
  "properties": {
    "iso:country":"GB",
    "sg:address":"Swan Close",
    "sg:city":"Stafford",
    "sg:classifiers":[
        {
            "category":"Shopping",
            "subcategory":"Stationery & Office Supplies",
            "type":"Retail Goods"
        }
    ],
    "sg:postcode":"ST16 1AU",
    "sg:province":"Staffordshire",
    "sg:tags":[
        "item",
        "promotional"
    ],
    "wof:name":"Bourne Publicity Ltd.",
    "wof:placetype":"venue"
},
  "geometry": {"coordinates":[-2.133022,52.80257],"type":"Point"}
}