{
  "type": "Feature",
  "properties": {
    "addr:full":"Manor House, 23 Robin Lane Pudsey West Yorkshire LS28 7BR",
    "addr:housenumber":"23",
    "addr:postcode":"ls28 7br",
    "addr:street":"Manor;Robin Lane",
    "iso:country":"GB",
    "sg:address":"Manor House, 23 Robin Lane",
    "sg:city":"Pudsey",
    "sg:classifiers":[
        {
            "category":"Professional",
            "subcategory":"Computer Services",
            "type":"Services"
        }
    ],
    "sg:phone":"+44 113 255 4115",
    "sg:postcode":"LS28 7BR",
    "sg:province":"West Yorkshire",
    "sg:tags":[
        "system",
        "software"
    ],
    "wof:name":"Propath Software Ltd.",
    "wof:placetype":"venue"
},
  "geometry": {"coordinates":[-1.660724,53.795361],"type":"Point"}
}