{
  "type": "Feature",
  "properties": {
    "iso:country":"GB",
    "sg:address":"37 Fore Street",
    "sg:city":"Chard",
    "sg:classifiers":[
        {
            "category":"Banks & Credit Unions",
            "subcategory":"Bank",
            "type":"Services"
        },
        {
            "category":"Banks & Credit Unions",
            "subcategory":"Financial Services",
            "type":"Services"
        }
    ],
    "sg:phone":"+44 1460 66623",
    "sg:postcode":"TA20 1PT",
    "sg:province":"Devon",
    "sg:tags":[
        "adviser",
        "broker",
        "mortgage"
    ],
    "wof:name":"PAUL ATTIWELL",
    "wof:placetype":"venue"
},
  "geometry": {"coordinates":[-2.963541,50.873047],"type":"Point"}
}