{
  "type": "Feature",
  "properties": {
    "addr:full":"The Lodge, Stocking La Hertford Hertfordshire SG13 8PJ",
    "addr:postcode":"sg13 8pj",
    "addr:street":"Stocking La Hertford",
    "iso:country":"GB",
    "sg:address":"The Lodge, Stocking La",
    "sg:city":"Hertford",
    "sg:classifiers":[
        {
            "category":"Professional",
            "subcategory":"Business Services",
            "type":"Services"
        }
    ],
    "sg:phone":"+44 1992 511229",
    "sg:postcode":"SG13 8PJ",
    "sg:province":"Hertfordshire",
    "sg:tags":[
        "import",
        "export",
        "agent"
    ],
    "wof:name":"D H Garner",
    "wof:placetype":"venue"
},
  "geometry": {"coordinates":[-0.086882,51.783283],"type":"Point"}
}