{
  "type": "Feature",
  "properties": {
    "addr:full":"60 Market Place Driffield East Riding of Yorkshire YO25 6AW",
    "addr:housenumber":"60",
    "addr:postcode":"yo25 6aw",
    "addr:street":"Market Place",
    "iso:country":"GB",
    "sg:address":"60 Market Place",
    "sg:city":"Driffield",
    "sg:classifiers":[
        {
            "category":"Travel",
            "subcategory":"Travel Agent",
            "type":"Entertainment"
        }
    ],
    "sg:phone":"+44 1377 257644",
    "sg:postcode":"YO25 6AW",
    "sg:province":"East Riding of Yorkshire",
    "wof:name":"Driffield Travel",
    "wof:placetype":"venue"
},
  "geometry": {"coordinates":[-0.438586,54.00491],"type":"Point"}
}