{
  "type": "Feature",
  "properties": {
    "iso:country":"GB",
    "sg:address":"63 Newtown Ave",
    "sg:city":"Bognor Regis",
    "sg:classifiers":[
        {
            "category":"Home & Garden",
            "subcategory":"Carpets & Floor Coverings",
            "type":"Retail Goods"
        }
    ],
    "sg:phone":"+44 1243 842007",
    "sg:postcode":"PO21 5AR",
    "sg:province":"West Sussex",
    "sg:tags":[
        "cleaner",
        "upholstery"
    ],
    "wof:name":"Yenroc Stable Cleaning Services",
    "wof:placetype":"venue"
},
  "geometry": {"coordinates":[-0.6943669915,50.7979469299],"type":"Point"}
}