{
  "type": "Feature",
  "properties": {
    "iso:country":"GB",
    "sg:address":"Newport",
    "sg:city":"Lincoln",
    "sg:classifiers":[
        {
            "category":"Education",
            "subcategory":"University",
            "type":"Public Place"
        }
    ],
    "sg:phone":"+44 1522 527347",
    "sg:postcode":"LN1 3DY",
    "sg:province":"Lincolnshire",
    "sg:tags":[
        "school",
        "college",
        "medical",
        "higher"
    ],
    "sg:website":"http://www.btc.ac.uk",
    "wof:name":"Bishop Grosseteste College",
    "wof:placetype":"venue"
},
  "geometry": {"coordinates":[-0.53789,53.243462],"type":"Point"}
}