{
  "type": "Feature",
  "properties": {
    "addr:full":"147b Uxbridge Road, Ealing London Greater London W13 9AU",
    "addr:housenumber":"147b",
    "addr:postcode":"w13 9au",
    "addr:street":"Uxbridge Road",
    "iso:country":"GB",
    "sg:address":"147b Uxbridge Road, Ealing",
    "sg:city":"London",
    "sg:classifiers":[
        {
            "category":"Building & Trades",
            "subcategory":"Plumbing",
            "type":"Services"
        }
    ],
    "sg:phone":"+44 20 8567 5111",
    "sg:postcode":"W13 9AU",
    "sg:province":"Greater London",
    "sg:tags":[
        "heating"
    ],
    "wof:name":"1st Assistance Services Ltd.",
    "wof:placetype":"venue"
},
  "geometry": {"coordinates":[-0.318317,51.511196],"type":"Point"}
}