{
  "type": "Feature",
  "properties": {
    "iso:country":"GB",
    "sg:address":"95 Preston Rd",
    "sg:city":"Yeovil",
    "sg:classifiers":[
        {
            "category":"Shopping",
            "subcategory":"News",
            "type":"Retail Goods"
        }
    ],
    "sg:phone":"+44 1935 478513",
    "sg:postcode":"BA20 2DW",
    "sg:province":"Somerset",
    "sg:tags":[
        "newsagent"
    ],
    "wof:name":"R & B News",
    "wof:placetype":"venue"
},
  "geometry": {"coordinates":[-2.651022,50.945248],"type":"Point"}
}