{
  "type": "Feature",
  "properties": {
    "iso:country":"GB",
    "sg:address":"Milton Crescent",
    "sg:city":"Dudley",
    "sg:classifiers":[
        {
            "category":"Farming",
            "subcategory":"Nursery",
            "type":"Manufacturing & Wholesale Goods"
        },
        {
            "category":"Education",
            "subcategory":"Preschool",
            "type":"Public Place"
        }
    ],
    "sg:phone":"+44 1902 881021",
    "sg:postcode":"DY3 3DR",
    "sg:province":"Staffordshire",
    "sg:tags":[
        "school",
        "creche"
    ],
    "wof:name":"Happy Hours Day Nursery",
    "wof:placetype":"venue"
},
  "geometry": {"coordinates":[-2.141823,52.528942],"type":"Point"}
}