{
  "type": "Feature",
  "properties": {
    "addr:full":"International Press Centre, 76 Shoe Lane St Paul's Greater London EC4A 3JB",
    "addr:housenumber":"76",
    "addr:postcode":"ec4a 3jb",
    "addr:street":"Shoe Lane",
    "iso:country":"GB",
    "sg:address":"International Press Centre, 76 Shoe Lane",
    "sg:city":"St Paul's",
    "sg:classifiers":[
        {
            "category":"Wholesale",
            "subcategory":"Books, Periodicals, & Newspapers",
            "type":"Manufacturing & Wholesale Goods"
        }
    ],
    "sg:phone":"+44 20 7842 2700",
    "sg:postcode":"EC4A 3JB",
    "sg:province":"Greater London",
    "sg:tags":[
        "publishing"
    ],
    "wof:name":"Tradewinds Shipping Gazette",
    "wof:placetype":"venue"
},
  "geometry": {"coordinates":[-0.094041,51.536476],"type":"Point"}
}