{
  "type": "Feature",
  "properties": {
    "addr:full":"283 Dinas, Treowen Newtown Powys SY16 1NW",
    "addr:housenumber":"283",
    "addr:postcode":"sy16 1nw",
    "addr:street":"Dinas Treowen",
    "iso:country":"GB",
    "sg:address":"283 Dinas, Treowen",
    "sg:city":"Newtown",
    "sg:classifiers":[
        {
            "category":"Government",
            "subcategory":"Fire Station",
            "type":"Public Place"
        }
    ],
    "sg:phone":"+44 1686 626312",
    "sg:postcode":"SY16 1NW",
    "sg:province":"Powys",
    "sg:tags":[
        "security"
    ],
    "wof:name":"K P Fire",
    "wof:placetype":"venue"
},
  "geometry": {"coordinates":[-3.3246090412,52.5088615417],"type":"Point"}
}