{
  "type": "Feature",
  "properties": {
    "addr:full":"Ashton Road Lancaster Lancashire LA1 4RS",
    "addr:postcode":"la1 4rs",
    "addr:street":"Ashton Road",
    "iso:country":"GB",
    "sg:address":"Ashton Road",
    "sg:city":"Lancaster",
    "sg:classifiers":[
        {
            "category":"Education",
            "subcategory":"School",
            "type":"Public Place"
        }
    ],
    "sg:phone":"+44 1524 64496",
    "sg:postcode":"LA1 4RS",
    "sg:province":"Lancashire",
    "sg:tags":[
        "local",
        "authority"
    ],
    "wof:name":"Ripley St. Thomas Church of England School",
    "wof:placetype":"venue"
},
  "geometry": {"coordinates":[-2.800474,54.038639],"type":"Point"}
}