{
  "type": "Feature",
  "properties": {
    "iso:country":"GB",
    "sg:address":"W & S Wharf, Prince Consort Rd",
    "sg:city":"Hebburn",
    "sg:classifiers":[
        {
            "category":"Taxi",
            "type":"Transportation"
        }
    ],
    "sg:phone":"+44 191 430 0222",
    "sg:postcode":"NE31 1DT",
    "sg:province":"Tyne and Wear",
    "sg:tags":[
        "mini",
        "cab"
    ],
    "wof:name":"Newtown Taxis",
    "wof:placetype":"venue"
},
  "geometry": {"coordinates":[-1.5208699703,54.976600647],"type":"Point"}
}