{
  "type": "Feature",
  "properties": {
    "iso:country":"GB",
    "sg:address":"1 Cavalier Way",
    "sg:city":"East Grinstead",
    "sg:classifiers":[
        {
            "category":"Food & Beverages",
            "subcategory":"Specialty",
            "type":"Retail Goods"
        }
    ],
    "sg:phone":"+44 1342 321785",
    "sg:postcode":"RH19 4SE",
    "sg:province":"East Sussex",
    "sg:tags":[
        "dietetic",
        "homogenised"
    ],
    "wof:name":"Matol Botanical Independent Distributors",
    "wof:placetype":"venue"
},
  "geometry": {"coordinates":[-0.005263,51.119034],"type":"Point"}
}