{
  "type": "Feature",
  "properties": {
    "iso:country":"GB",
    "sg:address":"1a Westbourne St",
    "sg:city":"Stockton On Tees",
    "sg:classifiers":[
        {
            "category":"Manufacturing",
            "subcategory":"Furniture",
            "type":"Manufacturing & Wholesale Goods"
        }
    ],
    "sg:phone":"+44 1642 657184",
    "sg:postcode":"TS18 3EH",
    "sg:province":"Durham",
    "sg:tags":[
        "mnfr",
        "upholsterer"
    ],
    "wof:name":"A.J.L Upholstery",
    "wof:placetype":"venue"
},
  "geometry": {"coordinates":[-1.318257,54.559441],"type":"Point"}
}