{
  "type": "Feature",
  "properties": {
    "addr:full":"70 Cleveland St West End Hampshire W1P 5DS",
    "addr:housenumber":"70",
    "addr:postcode":"w1p 5ds",
    "addr:street":"Cleveland St",
    "iso:country":"GB",
    "sg:address":"70 Cleveland St",
    "sg:city":"West End",
    "sg:classifiers":[
        {
            "category":"Insurance",
            "subcategory":"Insurance Agent",
            "type":"Services"
        }
    ],
    "sg:phone":"+44 20 7436 2881",
    "sg:postcode":"W1P 5DS",
    "sg:province":"Hampshire",
    "sg:tags":[
        "broker"
    ],
    "wof:name":"Northwood Ltd",
    "wof:placetype":"venue"
},
  "geometry": {"coordinates":[-0.1389899999,51.5075798035],"type":"Point"}
}