{
  "type": "Feature",
  "properties": {
    "addr:full":"530 York Road Leeds West Yorkshire LS9 0HH",
    "addr:housenumber":"530",
    "addr:postcode":"ls9 0hh",
    "addr:street":"York Road",
    "iso:country":"GB",
    "sg:address":"530 York Road",
    "sg:city":"Leeds",
    "sg:classifiers":[
        {
            "category":"Food & Beverages",
            "subcategory":"Groceries & Convenience Stores",
            "type":"Retail Goods"
        }
    ],
    "sg:phone":"+44 113 249 3277",
    "sg:postcode":"LS9 0HH",
    "sg:province":"West Yorkshire",
    "wof:name":"Rookwood Stores",
    "wof:placetype":"venue"
},
  "geometry": {"coordinates":[-1.488244,53.801487],"type":"Point"}
}