{
  "type": "Feature",
  "properties": {
    "iso:country":"GB",
    "sg:address":"100 Bonnygate",
    "sg:city":"Cupar",
    "sg:classifiers":[
        {
            "category":"Sports & Exercise",
            "subcategory":"Sports Center",
            "type":"Entertainment"
        }
    ],
    "sg:phone":"+44 1334 655311",
    "sg:postcode":"KY15 4LF",
    "sg:province":"Fife",
    "sg:tags":[
        "shop",
        "good"
    ],
    "wof:name":"Ultimate Kit",
    "wof:placetype":"venue"
},
  "geometry": {"coordinates":[-3.015927,56.319214],"type":"Point"}
}