{
  "type": "Feature",
  "properties": {
    "addr:full":"9 Orchard Road, St Anne's Lytham St Annes Lancashire FY8 1RY",
    "addr:housenumber":"9",
    "addr:postcode":"fy8 1ry",
    "addr:street":"Orchard Road St Anne'S",
    "iso:country":"GB",
    "sg:address":"9 Orchard Road, St Anne's",
    "sg:city":"Lytham St Annes",
    "sg:classifiers":[
        {
            "category":"Shopping",
            "subcategory":"Shoes",
            "type":"Retail Goods"
        }
    ],
    "sg:phone":"+44 1253 724159",
    "sg:postcode":"FY8 1RY",
    "sg:province":"Lancashire",
    "wof:name":"Star Shoe Repairs Ltd.",
    "wof:placetype":"venue"
},
  "geometry": {"coordinates":[-3.0308120251,53.7507324219],"type":"Point"}
}