{
  "type": "Feature",
  "properties": {
    "addr:full":"Mochdre Indust Est Newtown Powys SY16 4LE",
    "addr:postcode":"sy16 4le",
    "iso:country":"GB",
    "sg:address":"Mochdre Indust Est",
    "sg:city":"Newtown",
    "sg:classifiers":[
        {
            "category":"Manufacturing",
            "subcategory":"Buildings",
            "type":"Manufacturing & Wholesale Goods"
        }
    ],
    "sg:phone":"+44 1686 628520",
    "sg:postcode":"SY16 4LE",
    "sg:province":"Powys",
    "sg:tags":[
        "portable"
    ],
    "wof:name":"Elliott Group Ltd",
    "wof:placetype":"venue"
},
  "geometry": {"coordinates":[-3.366463,52.484905],"type":"Point"}
}