{
  "type": "Feature",
  "properties": {
    "addr:full":"254 Holyhead Road Coventry West Midlands CV5 8JN",
    "addr:housenumber":"254",
    "addr:postcode":"cv5 8jn",
    "addr:street":"Holyhead Road",
    "iso:country":"GB",
    "sg:address":"254 Holyhead Road",
    "sg:city":"Coventry",
    "sg:classifiers":[
        {
            "category":"Personal",
            "subcategory":"Beauty Salon",
            "type":"Services"
        },
        {
            "category":"Personal",
            "subcategory":"Barber",
            "type":"Services"
        }
    ],
    "sg:phone":"+44 24 7659 3649",
    "sg:postcode":"CV5 8JN",
    "sg:province":"West Midlands",
    "sg:tags":[
        "unisex",
        "hairdresser"
    ],
    "wof:name":"Artisan Hair Co",
    "wof:placetype":"venue"
},
  "geometry": {"coordinates":[-1.5339790583,52.4149208069],"type":"Point"}
}