{
  "type": "Feature",
  "properties": {
    "addr:full":"388 Humberstone Road Leicester Leicestershire LE5 0AS",
    "addr:housenumber":"388",
    "addr:postcode":"le5 0as",
    "addr:street":"Humberstone Road",
    "iso:country":"GB",
    "sg:address":"388 Humberstone Road",
    "sg:city":"Leicester",
    "sg:classifiers":[
        {
            "category":"Insurance",
            "subcategory":"Insurance Agent",
            "type":"Services"
        }
    ],
    "sg:phone":"+44 116 276 6616",
    "sg:postcode":"LE5 0AS",
    "sg:province":"Leicestershire",
    "wof:name":"Colonnade Insurance Brokers",
    "wof:placetype":"venue"
},
  "geometry": {"coordinates":[-1.1059989929,52.6421318054],"type":"Point"}
}