{
  "type": "Feature",
  "properties": {
    "iso:country":"GB",
    "sg:address":"4 St Georges, Redhill",
    "sg:city":"Telford",
    "sg:classifiers":[
        {
            "category":"Professional",
            "subcategory":"Detective & Security Services",
            "type":"Services"
        }
    ],
    "sg:phone":"+44 1952 610894",
    "sg:postcode":"TF2 9PA",
    "sg:province":"Shropshire",
    "wof:name":"Mercia Security",
    "wof:placetype":"venue"
},
  "geometry": {"coordinates":[-2.400939,52.694923],"type":"Point"}
}