{
  "type": "Feature",
  "properties": {
    "addr:full":"High Street, Shirrell Heath Southampton Hampshire SO32 2JN",
    "addr:postcode":"so32 2jn",
    "addr:street":"High Street",
    "iso:country":"GB",
    "sg:address":"High Street, Shirrell Heath",
    "sg:city":"Southampton",
    "sg:classifiers":[
        {
            "category":"Social Services",
            "subcategory":"Retirement Home",
            "type":"Services"
        }
    ],
    "sg:phone":"+44 1329 833328",
    "sg:postcode":"SO32 2JN",
    "sg:province":"Hampshire",
    "sg:tags":[
        "rest"
    ],
    "wof:name":"Hill House Rest Home",
    "wof:placetype":"venue"
},
  "geometry": {"coordinates":[-1.186184,50.925385],"type":"Point"}
}