{
  "type": "Feature",
  "properties": {
    "iso:country":"GB",
    "sg:address":"Viola House, Church Road, Freiston",
    "sg:city":"Boston",
    "sg:classifiers":[
        {
            "category":"Building & Trades",
            "subcategory":"Construction",
            "type":"Services"
        }
    ],
    "sg:phone":"+44 1205 760316",
    "sg:postcode":"PE22 0LA",
    "sg:province":"Lincolnshire",
    "sg:tags":[
        "builder",
        "joiner",
        "carpenter"
    ],
    "wof:name":"J E Hayes",
    "wof:placetype":"venue"
},
  "geometry": {"coordinates":[0.04558,52.976391],"type":"Point"}
}