{
  "type": "Feature",
  "properties": {
    "addr:full":"13 Bridgman Terrace Wigan Lancashire WN1 1SX",
    "addr:housenumber":"13",
    "addr:postcode":"wn1 1sx",
    "addr:street":"Bridgman Terrace",
    "iso:country":"GB",
    "sg:address":"13 Bridgman Terrace",
    "sg:city":"Wigan",
    "sg:classifiers":[
        {
            "category":"Professional",
            "subcategory":"Lawyer & Legal Services",
            "type":"Services"
        }
    ],
    "sg:phone":"+44 1942 241421",
    "sg:postcode":"WN1 1SX",
    "sg:province":"Lancashire",
    "sg:tags":[
        "solicitor"
    ],
    "wof:name":"Vincent & Co.",
    "wof:placetype":"venue"
},
  "geometry": {"coordinates":[-2.634235,53.551517],"type":"Point"}
}