{
  "type": "Feature",
  "properties": {
    "addr:full":"West Nistaben, Stenness Stromness Orkney Islands KW16 3HE",
    "addr:postcode":"kw16 3he",
    "addr:street":"West;Stenness",
    "iso:country":"GB",
    "sg:address":"West Nistaben, Stenness",
    "sg:city":"Stromness",
    "sg:classifiers":[
        {
            "category":"Farming",
            "subcategory":"Livestock Farm",
            "type":"Manufacturing & Wholesale Goods"
        }
    ],
    "sg:postcode":"KW16 3HE",
    "sg:province":"Orkney Islands",
    "sg:tags":[
        "others"
    ],
    "wof:name":"Bruce Learmonth",
    "wof:placetype":"venue"
},
  "geometry": {"coordinates":[-3.297759,58.963486],"type":"Point"}
}