{
  "type": "Feature",
  "properties": {
    "iso:country":"GB",
    "sg:address":"20 Wellington Square",
    "sg:city":"Hastings",
    "sg:classifiers":[
        {
            "category":"Professional",
            "subcategory":"Accounting & Tax Preparation",
            "type":"Services"
        }
    ],
    "sg:phone":"+44 1424 433305",
    "sg:postcode":"TN34 1PN",
    "sg:province":"East Sussex",
    "sg:tags":[
        "accountant"
    ],
    "wof:name":"A J Taylor & Co",
    "wof:placetype":"venue"
},
  "geometry": {"coordinates":[0.583538,50.856445],"type":"Point"}
}