{
  "type": "Feature",
  "properties": {
    "addr:full":"28-29 Odessa Street, Dowlais Merthyr Tydfil Caerphilly CF48 3AU",
    "addr:housenumber":"28-29",
    "addr:postcode":"cf48 3au",
    "addr:street":"Odessa Street",
    "iso:country":"GB",
    "sg:address":"28-29 Odessa Street, Dowlais",
    "sg:city":"Merthyr Tydfil",
    "sg:classifiers":[
        {
            "category":"Personal",
            "subcategory":"Beauty Salon",
            "type":"Services"
        }
    ],
    "sg:phone":"+44 1685 388403",
    "sg:postcode":"CF48 3AU",
    "sg:province":"Caerphilly",
    "sg:tags":[
        "unisex",
        "hairdresser"
    ],
    "wof:name":"Studio 5",
    "wof:placetype":"venue"
},
  "geometry": {"coordinates":[-3.3568270206,51.764289856],"type":"Point"}
}