{
  "type": "Feature",
  "properties": {
    "addr:full":"1 Forty Acre Lane, Alveston Bristol Gloucestershire BS35 3QU",
    "addr:housenumber":"1",
    "addr:postcode":"bs35 3qu",
    "addr:street":"Forty Acre Lane",
    "iso:country":"GB",
    "sg:address":"1 Forty Acre Lane, Alveston",
    "sg:city":"Bristol",
    "sg:classifiers":[
        {
            "category":"Professional",
            "subcategory":"Printing & Photocopies",
            "type":"Services"
        }
    ],
    "sg:phone":"+44 1454 411006",
    "sg:postcode":"BS35 3QU",
    "sg:province":"Gloucestershire",
    "sg:tags":[
        "printer"
    ],
    "wof:name":"S Sims",
    "wof:placetype":"venue"
},
  "geometry": {"coordinates":[-2.528941,51.584576],"type":"Point"}
}