{
  "type": "Feature",
  "properties": {
    "addr:full":"1 Park View, Padiham Burnley Lancashire BB12 8EE",
    "addr:housenumber":"1",
    "addr:postcode":"bb12 8ee",
    "addr:street":"Park View",
    "iso:country":"GB",
    "sg:address":"1 Park View, Padiham",
    "sg:city":"Burnley",
    "sg:classifiers":[
        {
            "category":"Freight",
            "type":"Transportation"
        }
    ],
    "sg:phone":"+44 1282 774992",
    "sg:postcode":"BB12 8EE",
    "sg:province":"Lancashire",
    "sg:tags":[
        "haulage",
        "road"
    ],
    "wof:name":"McFall Transport",
    "wof:placetype":"venue"
},
  "geometry": {"coordinates":[-2.3165130615,53.8004264832],"type":"Point"}
}