{
  "type": "Feature",
  "properties": {
    "iso:country":"GB",
    "sg:address":"Southey Street",
    "sg:city":"Keswick",
    "sg:classifiers":[
        {
            "category":"Health Services",
            "subcategory":"Optometrist",
            "type":"Services"
        }
    ],
    "sg:phone":"+44 17687 72147",
    "sg:postcode":"CA12 4HH",
    "sg:province":"Cumbria",
    "sg:tags":[
        "optician"
    ],
    "wof:name":"Katharine Mary Butterfield",
    "wof:placetype":"venue"
},
  "geometry": {"coordinates":[-3.134223938,54.6004753113],"type":"Point"}
}