{
  "type": "Feature",
  "properties": {
    "addr:full":"6 King Street, Delph Oldham Lancashire OL3 5DQ",
    "addr:housenumber":"6",
    "addr:postcode":"ol3 5dq",
    "addr:street":"King Street",
    "iso:country":"GB",
    "sg:address":"6 King Street, Delph",
    "sg:city":"Oldham",
    "sg:classifiers":[
        {
            "category":"Banks & Credit Unions",
            "subcategory":"Financial Services",
            "type":"Services"
        }
    ],
    "sg:postcode":"OL3 5DQ",
    "sg:province":"Lancashire",
    "sg:tags":[
        "adviser"
    ],
    "wof:name":"Effective Financial Planning Ltd.",
    "wof:placetype":"venue"
},
  "geometry": {"coordinates":[-2.023237,53.567314],"type":"Point"}
}