{
  "type": "Feature",
  "properties": {
    "addr:full":"5 Beoley Road West Redditch Warwickshire B98 8LR",
    "addr:housenumber":"5",
    "addr:postcode":"b98 8lr",
    "addr:street":"Beoley Road West",
    "iso:country":"GB",
    "sg:address":"5 Beoley Road West",
    "sg:city":"Redditch",
    "sg:classifiers":[
        {
            "category":"Personal",
            "subcategory":"Beauty Salon",
            "type":"Services"
        }
    ],
    "sg:phone":"+44 1527 584079",
    "sg:postcode":"B98 8LR",
    "sg:province":"Warwickshire",
    "sg:tags":[
        "unisex",
        "hairdresser"
    ],
    "wof:name":"Haircraft",
    "wof:placetype":"venue"
},
  "geometry": {"coordinates":[-1.928329,52.306225],"type":"Point"}
}