{
  "type": "Feature",
  "properties": {
    "iso:country":"GB",
    "sg:address":"6 Boden St",
    "sg:city":"Glasgow",
    "sg:classifiers":[
        {
            "category":"Community Center",
            "subcategory":"Youth",
            "type":"Public Place"
        }
    ],
    "sg:phone":"+44 141 646 2165",
    "sg:postcode":"G40 3PU",
    "sg:province":"Glasgow City",
    "sg:tags":[
        "organisation",
        "centre"
    ],
    "wof:name":"Bridgeton St Francis In The East Church House",
    "wof:placetype":"venue"
},
  "geometry": {"coordinates":[-4.214637,55.848175],"type":"Point"}
}