{
  "type": "Feature",
  "properties": {
    "addr:full":"244a London Road, Hadleigh Benfleet Essex SS7 2DE",
    "addr:housenumber":"244a",
    "addr:postcode":"ss7 2de",
    "addr:street":"London Road",
    "iso:country":"GB",
    "sg:address":"244a London Road, Hadleigh",
    "sg:city":"Benfleet",
    "sg:classifiers":[
        {
            "category":"Professional",
            "subcategory":"Business Services",
            "type":"Services"
        }
    ],
    "sg:phone":"+44 1702 552912",
    "sg:postcode":"SS7 2DE",
    "sg:province":"Essex",
    "sg:tags":[
        "publishers'"
    ],
    "wof:name":"Book Representation & Distribution Ltd.",
    "wof:placetype":"venue"
},
  "geometry": {"coordinates":[0.610439,51.552937],"type":"Point"}
}