{
  "type": "Feature",
  "properties": {
    "addr:full":"Unit L Kershaw Business Centre, Baldwin Street Bolton Lancashire BL3 5BF",
    "addr:postcode":"bl3 5bf",
    "addr:street":"Baldwin Street",
    "iso:country":"GB",
    "sg:address":"Unit L Kershaw Business Centre, Baldwin Street",
    "sg:city":"Bolton",
    "sg:classifiers":[
        {
            "category":"Shopping",
            "subcategory":"Pharmacy",
            "type":"Retail Goods"
        }
    ],
    "sg:phone":"+44 1204 364090",
    "sg:postcode":"BL3 5BF",
    "sg:province":"Lancashire",
    "sg:tags":[
        "pharmacist",
        "chemist"
    ],
    "wof:name":"Gorgemead Ltd.",
    "wof:placetype":"venue"
},
  "geometry": {"coordinates":[-2.44862,53.570999],"type":"Point"}
}