{
  "type": "Feature",
  "properties": {
    "addr:full":"125-127 Binfield Rd Bracknell Berkshire RG42 2AP",
    "addr:postcode":"125-127;rg42 2ap",
    "addr:street":"Binfield Rd",
    "iso:country":"GB",
    "sg:address":"125-127 Binfield Rd",
    "sg:city":"Bracknell",
    "sg:classifiers":[
        {
            "category":"Food & Beverages",
            "subcategory":"Liquor & Beverages",
            "type":"Retail Goods"
        }
    ],
    "sg:phone":"+44 1344 421658",
    "sg:postcode":"RG42 2AP",
    "sg:province":"Berkshire",
    "sg:tags":[
        "beer",
        "spirit",
        "wines"
    ],
    "wof:name":"Thresher",
    "wof:placetype":"venue"
},
  "geometry": {"coordinates":[-0.758788,51.421162],"type":"Point"}
}