{
  "type": "Feature",
  "properties": {
    "iso:country":"GB",
    "sg:address":"Watling Street",
    "sg:city":"Hinckley",
    "sg:classifiers":[
        {
            "category":"Autos & Motor Vehicles",
            "subcategory":"Auto Supplies",
            "type":"Retail Goods"
        }
    ],
    "sg:phone":"+44 1455 634156",
    "sg:postcode":"LE10 3ED",
    "sg:province":"Leicestershire",
    "sg:tags":[
        "rubber",
        "tyre"
    ],
    "wof:name":"Tyre Save Uk",
    "wof:placetype":"venue"
},
  "geometry": {"coordinates":[-1.360669,52.514294],"type":"Point"}
}