{
  "type": "Feature",
  "properties": {
    "iso:country":"GB",
    "sg:address":"4 Heaton Terrace",
    "sg:city":"North Shields",
    "sg:classifiers":[
        {
            "category":"Professional",
            "subcategory":"Engineering",
            "type":"Services"
        }
    ],
    "sg:phone":"+44 191 257 6043",
    "sg:postcode":"NE29 7HJ",
    "sg:province":"Tyne and Wear",
    "sg:tags":[
        "contractor",
        "electrical",
        "engineer"
    ],
    "wof:name":"Bosanko Ltd.",
    "wof:placetype":"venue"
},
  "geometry": {"coordinates":[-1.464092,55.008286],"type":"Point"}
}