{
  "type": "Feature",
  "properties": {
    "addr:full":"Hillside, Manston Sturminster Newton Dorset DT10 1EY",
    "addr:housenumber":"newton",
    "addr:postcode":"dt10 1ey",
    "iso:country":"GB",
    "sg:address":"Hillside, Manston",
    "sg:city":"Sturminster Newton",
    "sg:classifiers":[
        {
            "category":"Building & Trades",
            "subcategory":"Construction",
            "type":"Services"
        }
    ],
    "sg:phone":"+44 1258 472882",
    "sg:postcode":"DT10 1EY",
    "sg:province":"Dorset",
    "sg:tags":[
        "builder"
    ],
    "wof:name":"Martyn Lewis Ltd.",
    "wof:placetype":"venue"
},
  "geometry": {"coordinates":[-2.266886,50.938557],"type":"Point"}
}