{
  "type": "Feature",
  "properties": {
    "addr:full":"Hareness Circle, Altens Ind Est, Altens Aberdeen Aberdeen City AB12 3LY",
    "addr:postcode":"ab12 3ly",
    "addr:street":"Hareness Circle;Ind Est Altens",
    "iso:country":"GB",
    "sg:address":"Hareness Circle, Altens Ind Est, Altens",
    "sg:city":"Aberdeen",
    "sg:classifiers":[
        {
            "category":"Freight",
            "type":"Transportation"
        }
    ],
    "sg:phone":"+44 1224 877148",
    "sg:postcode":"AB12 3LY",
    "sg:province":"Aberdeen City",
    "sg:tags":[
        "haulage",
        "road"
    ],
    "wof:name":"Securicor Omega Express",
    "wof:placetype":"venue"
},
  "geometry": {"coordinates":[-2.080849,57.109871],"type":"Point"}
}