{
  "type": "Feature",
  "properties": {
    "addr:full":"154 Biggleswade Road, Upper Caldecote Biggleswade Bedfordshire SG18 9BJ",
    "addr:housenumber":"154",
    "addr:postcode":"sg18 9bj",
    "addr:street":"Biggleswade Road Upper",
    "iso:country":"GB",
    "sg:address":"154 Biggleswade Road, Upper Caldecote",
    "sg:city":"Biggleswade",
    "sg:classifiers":[
        {
            "category":"Retail",
            "subcategory":"Auto Repair",
            "type":"Services"
        }
    ],
    "sg:phone":"+44 1767 314581",
    "sg:postcode":"SG18 9BJ",
    "sg:province":"Bedfordshire",
    "sg:tags":[
        "modification",
        "garage"
    ],
    "wof:name":"P R Servicing and Repairs",
    "wof:placetype":"venue"
},
  "geometry": {"coordinates":[-0.2854459882,52.0996932983],"type":"Point"}
}