{
  "type": "Feature",
  "properties": {
    "iso:country":"GB",
    "sg:address":"Old Rectory Nursing Home, Church St, North Kilworth",
    "sg:city":"Lutterworth",
    "sg:classifiers":[
        {
            "category":"Health Services",
            "subcategory":"Nursing And Care Facility",
            "type":"Services"
        }
    ],
    "sg:postcode":"LE17 6EZ",
    "sg:province":"Leicestershire",
    "sg:tags":[
        "home"
    ],
    "wof:name":"Rundle,P J,",
    "wof:placetype":"venue"
},
  "geometry": {"coordinates":[-1.0923340321,52.4466743469],"type":"Point"}
}