{
  "type": "Feature",
  "properties": {
    "addr:full":"26 Wood Street, Old Town Swindon Wiltshire SN1 4AB",
    "addr:housenumber":"26",
    "addr:postcode":"sn1 4ab",
    "addr:street":"Wood Street",
    "iso:country":"GB",
    "sg:address":"26 Wood Street, Old Town",
    "sg:city":"Swindon",
    "sg:classifiers":[
        {
            "category":"Shopping",
            "subcategory":"Clothing, Apparel, & Fashions",
            "type":"Retail Goods"
        }
    ],
    "sg:phone":"+44 1793 513196",
    "sg:postcode":"SN1 4AB",
    "sg:province":"Wiltshire",
    "sg:tags":[
        "shop"
    ],
    "wof:name":"Juvals",
    "wof:placetype":"venue"
},
  "geometry": {"coordinates":[-1.776219,51.552593],"type":"Point"}
}