{
  "type": "Feature",
  "properties": {
    "iso:country":"GB",
    "sg:address":"29 Forest Road",
    "sg:city":"Horsham",
    "sg:classifiers":[
        {
            "category":"Building & Trades",
            "subcategory":"Construction",
            "type":"Services"
        }
    ],
    "sg:phone":"+44 1403 258474",
    "sg:postcode":"RH12 4HJ",
    "sg:province":"West Sussex",
    "sg:tags":[
        "builder"
    ],
    "wof:name":"Alan A Ells",
    "wof:placetype":"venue"
},
  "geometry": {"coordinates":[-0.29068,51.075169],"type":"Point"}
}