{
  "type": "Feature",
  "properties": {
    "iso:country":"GB",
    "sg:address":"65 Liddesdale Square",
    "sg:city":"Glasgow",
    "sg:classifiers":[
        {
            "category":"Food & Beverages",
            "subcategory":"Groceries & Convenience Stores",
            "type":"Retail Goods"
        }
    ],
    "sg:phone":"+44 141 772 2043",
    "sg:postcode":"G22 7BT",
    "sg:province":"Glasgow City",
    "wof:name":"P G C GROCERS",
    "wof:placetype":"venue"
},
  "geometry": {"coordinates":[-4.2410769463,55.8967018127],"type":"Point"}
}