{
  "type": "Feature",
  "properties": {
    "iso:country":"GB",
    "sg:address":"Pirrie Road",
    "sg:city":"Liverpool",
    "sg:classifiers":[
        {
            "category":"Organizations",
            "subcategory":"Community Association",
            "type":"Services"
        },
        {
            "category":"Organizations",
            "subcategory":"Membership Organization",
            "type":"Services"
        }
    ],
    "sg:phone":"+44 151 284 8084",
    "sg:postcode":"L9 6AB",
    "sg:province":"Merseyside",
    "sg:tags":[
        "club",
        "social"
    ],
    "wof:name":"OUR LADY OF SORROWS",
    "wof:placetype":"venue"
},
  "geometry": {"coordinates":[-2.938424,53.450554],"type":"Point"}
}