{
  "type": "Feature",
  "properties": {
    "addr:full":"Unit 14 The Hildreds Skegness Lincolnshire PE25 2NR",
    "addr:housenumber":"unit 14",
    "addr:postcode":"pe25 2nr",
    "addr:street":"The Hildreds",
    "iso:country":"GB",
    "sg:address":"Unit 14 The Hildreds",
    "sg:city":"Skegness",
    "sg:classifiers":[
        {
            "category":"Cafe",
            "type":"Food & Drink"
        }
    ],
    "sg:postcode":"PE25 2NR",
    "sg:province":"Lincolnshire",
    "sg:tags":[
        "tea",
        "room"
    ],
    "wof:name":"The Cottage Loaf",
    "wof:placetype":"venue"
},
  "geometry": {"coordinates":[0.337,53.145271],"type":"Point"}
}