{
  "type": "Feature",
  "properties": {
    "iso:country":"GB",
    "sg:address":"Newport Street, Off Stuart Road",
    "sg:city":"Pontefract",
    "sg:classifiers":[
        {
            "category":"Home & Garden",
            "subcategory":"Building Materials",
            "type":"Retail Goods"
        }
    ],
    "sg:phone":"+44 1977 797705",
    "sg:postcode":"WF8 4PQ",
    "sg:province":"North Yorkshire",
    "sg:tags":[
        "fencing"
    ],
    "wof:name":"Preece Concrete Products",
    "wof:placetype":"venue"
},
  "geometry": {"coordinates":[-1.317409,53.693871],"type":"Point"}
}