{
  "type": "Feature",
  "properties": {
    "addr:full":"23-27 Trelowarren Street Camborne Cornwall TR14 8AD",
    "addr:housenumber":"23-27",
    "addr:postcode":"tr14 8ad",
    "addr:street":"Trelowarren Street",
    "iso:country":"GB",
    "sg:address":"23-27 Trelowarren Street",
    "sg:city":"Camborne",
    "sg:classifiers":[
        {
            "category":"Shopping",
            "subcategory":"Clothing, Apparel, & Fashions",
            "type":"Retail Goods"
        }
    ],
    "sg:phone":"+44 1209 712902",
    "sg:postcode":"TR14 8AD",
    "sg:province":"Cornwall",
    "sg:tags":[
        "shop"
    ],
    "wof:name":"Mackays Stores Ltd.",
    "wof:placetype":"venue"
},
  "geometry": {"coordinates":[-5.298556,50.214268],"type":"Point"}
}