{
  "type": "Feature",
  "properties": {
    "iso:country":"GB",
    "sg:address":"168 Manchester Road",
    "sg:city":"Huddersfield",
    "sg:classifiers":[
        {
            "category":"Taxi",
            "type":"Transportation"
        },
        {
            "category":"Military Area",
            "subcategory":"Air Force Base",
            "type":"Public Place"
        }
    ],
    "sg:phone":"+44 1484 532222",
    "sg:postcode":"HD1 3JA",
    "sg:province":"West Yorkshire",
    "sg:tags":[
        "hire",
        "private"
    ],
    "wof:name":"Bridge Taxis",
    "wof:placetype":"venue"
},
  "geometry": {"coordinates":[-1.7955559492,53.6418228149],"type":"Point"}
}