{
  "type": "Feature",
  "properties": {
    "addr:full":"12 London Road St Albans Hertfordshire AL1 1NG",
    "addr:housenumber":"12",
    "addr:postcode":"al1 1ng",
    "addr:street":"London Road",
    "iso:country":"GB",
    "sg:address":"12 London Road",
    "sg:city":"St Albans",
    "sg:classifiers":[
        {
            "category":"Real Estate",
            "subcategory":"Real Estate Agent",
            "type":"Services"
        }
    ],
    "sg:phone":"+44 1727 855232",
    "sg:postcode":"AL1 1NG",
    "sg:province":"Hertfordshire",
    "wof:name":"Druce & Partners",
    "wof:placetype":"venue"
},
  "geometry": {"coordinates":[-0.3385129869,51.7504844666],"type":"Point"}
}