{
  "type": "Feature",
  "properties": {
    "addr:full":"4 Church View Rhyl Conwy LL18 5TF",
    "addr:housenumber":"4",
    "addr:postcode":"ll18 5tf",
    "addr:street":"Church View",
    "iso:country":"GB",
    "sg:address":"4 Church View",
    "sg:city":"Rhyl",
    "sg:classifiers":[
        {
            "category":"Food & Beverages",
            "subcategory":"Supermarket",
            "type":"Retail Goods"
        },
        {
            "category":"Food & Beverages",
            "subcategory":"Fruits & Vegetables",
            "type":"Retail Goods"
        }
    ],
    "sg:postcode":"LL18 5TF",
    "sg:province":"Conwy",
    "sg:tags":[
        "greengrocer"
    ],
    "wof:name":"Whitworth,Colin R,",
    "wof:placetype":"venue"
},
  "geometry": {"coordinates":[-3.507199,53.269337],"type":"Point"}
}