{
  "type": "Feature",
  "properties": {
    "addr:full":"St Annes Well Road Nottingham Nottinghamshire NG3 3PX",
    "addr:postcode":"ng3 3px",
    "addr:street":"St Annes Well Road",
    "iso:country":"GB",
    "sg:address":"St Annes Well Road",
    "sg:city":"Nottingham",
    "sg:classifiers":[
        {
            "category":"Health Services",
            "subcategory":"Doctor",
            "type":"Services"
        }
    ],
    "sg:phone":"+44 115 948 0560",
    "sg:postcode":"NG3 3PX",
    "sg:province":"Nottinghamshire",
    "sg:tags":[
        "practitioners"
    ],
    "wof:name":"St Annes Health Centre",
    "wof:placetype":"venue"
},
  "geometry": {"coordinates":[-1.133214,52.963524],"type":"Point"}
}