{
  "type": "Feature",
  "properties": {
    "iso:country":"GB",
    "sg:address":"22 London Rd",
    "sg:city":"Attleborough",
    "sg:classifiers":[
        {
            "category":"Fast Food",
            "type":"Food & Drink"
        }
    ],
    "sg:postcode":"NR17 2BU",
    "sg:province":"Norfolk",
    "sg:tags":[
        "away",
        "take"
    ],
    "wof:name":"Brown,P,",
    "wof:placetype":"venue"
},
  "geometry": {"coordinates":[1.010279,52.514954],"type":"Point"}
}