{
  "type": "Feature",
  "properties": {
    "iso:country":"GB",
    "sg:address":"11 Penrhyn Road",
    "sg:city":"Kingston-upon-thames",
    "sg:classifiers":[
        {
            "category":"Real Estate",
            "subcategory":"Real Estate Agent",
            "type":"Services"
        }
    ],
    "sg:phone":"+44 20 8541 5001",
    "sg:postcode":"KT1 2BZ",
    "sg:province":"Greater London",
    "wof:name":"Tradsco (U K) Ltd.",
    "wof:placetype":"venue"
},
  "geometry": {"coordinates":[-0.3038679957,51.4053153992],"type":"Point"}
}