{
  "type": "Feature",
  "properties": {
    "iso:country":"GB",
    "sg:address":"Millshaw Court",
    "sg:city":"Leeds",
    "sg:classifiers":[
        {
            "category":"Banks & Credit Unions",
            "subcategory":"Bank",
            "type":"Services"
        }
    ],
    "sg:phone":"+44 20 7699 5000",
    "sg:postcode":"LS11 8DD",
    "sg:province":"West Yorkshire",
    "wof:name":"Barclays Direct Mortgage Service",
    "wof:placetype":"venue"
},
  "geometry": {"coordinates":[-1.574751,53.766033],"type":"Point"}
}