{
  "type": "Feature",
  "properties": {
    "iso:country":"GB",
    "sg:address":"Camberwell House, Common Road",
    "sg:city":"Diss",
    "sg:classifiers":[
        {
            "category":"Sports & Exercise",
            "subcategory":"Swimming Pool",
            "type":"Entertainment"
        }
    ],
    "sg:postcode":"IP21 4PJ",
    "sg:province":"Norfolk",
    "sg:tags":[
        "tank",
        "septic"
    ],
    "wof:name":"V Blake",
    "wof:placetype":"venue"
},
  "geometry": {"coordinates":[1.196532,52.386959],"type":"Point"}
}