{
  "type": "Feature",
  "properties": {
    "addr:full":"301 Chapel Lane, New Longton Preston Lancashire PR4 4AB",
    "addr:housenumber":"301",
    "addr:postcode":"pr4 4ab",
    "addr:street":"Chapel Lane",
    "iso:country":"GB",
    "sg:address":"301 Chapel Lane, New Longton",
    "sg:city":"Preston",
    "sg:classifiers":[
        {
            "category":"Personal",
            "type":"Services"
        }
    ],
    "sg:phone":"+44 1772 613130",
    "sg:postcode":"PR4 4AB",
    "sg:province":"Lancashire",
    "sg:tags":[
        "wedding"
    ],
    "wof:name":"Vintage & Modern Wedding Cars",
    "wof:placetype":"venue"
},
  "geometry": {"coordinates":[-2.752091,53.726799],"type":"Point"}
}