{
  "type": "Feature",
  "properties": {
    "iso:country":"GB",
    "sg:address":"11 Concord Way",
    "sg:city":"Dukinfield",
    "sg:classifiers":[
        {
            "category":"Food & Beverages",
            "subcategory":"Meat & Fish",
            "type":"Retail Goods"
        }
    ],
    "sg:phone":"+44 161 330 4585",
    "sg:postcode":"SK16 4DB",
    "sg:province":"Greater Manchester",
    "sg:tags":[
        "butcher"
    ],
    "wof:name":"R Denerley",
    "wof:placetype":"venue"
},
  "geometry": {"coordinates":[-2.0829188824,53.4762382507],"type":"Point"}
}