{
  "type": "Feature",
  "properties": {
    "addr:full":"160 Cuxton Road Rochester Kent ME2 2NH",
    "addr:housenumber":"160",
    "addr:postcode":"me2 2nh",
    "addr:street":"Cuxton Road Rochester",
    "iso:country":"GB",
    "sg:address":"160 Cuxton Road",
    "sg:city":"Rochester",
    "sg:classifiers":[
        {
            "category":"Retail",
            "subcategory":"Driving School",
            "type":"Services"
        }
    ],
    "sg:phone":"+44 1634 726142",
    "sg:postcode":"ME2 2NH",
    "sg:province":"Kent",
    "wof:name":"Mervyn Avery School of Motoring",
    "wof:placetype":"venue"
},
  "geometry": {"coordinates":[0.484182,51.391026],"type":"Point"}
}