{
  "type": "Feature",
  "properties": {
    "iso:country":"GB",
    "sg:address":"Harmers Foundry, Hall Lane",
    "sg:city":"Walton-on-the-naze",
    "sg:classifiers":[
        {
            "category":"Autos & Motor Vehicles",
            "subcategory":"Automobile Sales",
            "type":"Retail Goods"
        }
    ],
    "sg:phone":"+44 1255 880933",
    "sg:postcode":"CO14 8HW",
    "sg:province":"Essex",
    "sg:tags":[
        "car",
        "specialist",
        "sales",
        "classic"
    ],
    "wof:name":"Classic Metal Shaping",
    "wof:placetype":"venue"
},
  "geometry": {"coordinates":[1.2673050165,51.8487014771],"type":"Point"}
}