{
  "type": "Feature",
  "properties": {
    "addr:full":"26 High Street Paisley Renfrewshire PA1 2BZ",
    "addr:housenumber":"26",
    "addr:postcode":"pa1 2bz",
    "addr:street":"High Street",
    "iso:country":"GB",
    "sg:address":"26 High Street",
    "sg:city":"Paisley",
    "sg:classifiers":[
        {
            "category":"Professional",
            "subcategory":"Art Services",
            "type":"Services"
        }
    ],
    "sg:postcode":"PA1 2BZ",
    "sg:province":"Renfrewshire",
    "sg:tags":[
        "photographer"
    ],
    "wof:name":"Strathclyde Studios",
    "wof:placetype":"venue"
},
  "geometry": {"coordinates":[-4.426069,55.845436],"type":"Point"}
}