{
  "type": "Feature",
  "properties": {
    "addr:full":"Unit D1 Taylor Business Park Warrington Cheshire WA3 6BL",
    "addr:housenumber":"d1",
    "addr:postcode":"wa3 6bl",
    "addr:street":"Taylor Business Park",
    "iso:country":"GB",
    "sg:address":"Unit D1 Taylor Business Park",
    "sg:city":"Warrington",
    "sg:classifiers":[
        {
            "category":"Retail",
            "subcategory":"Auto Repair",
            "type":"Services"
        }
    ],
    "sg:phone":"+44 1925 766987",
    "sg:postcode":"WA3 6BL",
    "sg:province":"Cheshire",
    "sg:tags":[
        "car",
        "specialist",
        "customizing"
    ],
    "wof:name":"T S T Performance Tyres",
    "wof:placetype":"venue"
},
  "geometry": {"coordinates":[-2.5213589668,53.4444732666],"type":"Point"}
}