{
  "type": "Feature",
  "properties": {
    "iso:country":"GB",
    "sg:address":"Newtonlea, Main Street East End",
    "sg:city":"Duns",
    "sg:classifiers":[
        {
            "category":"Communications",
            "type":"Services"
        }
    ],
    "sg:phone":"+44 1890 818680",
    "sg:postcode":"TD11 3XR",
    "sg:province":"East Lothian",
    "sg:tags":[
        "broadcasting"
    ],
    "wof:name":"Charisma Vision",
    "wof:placetype":"venue"
},
  "geometry": {"coordinates":[-2.3411068916,55.7757759094],"type":"Point"}
}