{
  "type": "Feature",
  "properties": {
    "addr:full":"23 High Court Lane Leeds West Yorkshire LS2 7EU",
    "addr:housenumber":"23",
    "addr:postcode":"ls2 7eu",
    "addr:street":"High Court Lane",
    "iso:country":"GB",
    "sg:address":"23 High Court Lane",
    "sg:city":"Leeds",
    "sg:classifiers":[
        {
            "category":"Retail",
            "subcategory":"Auto Repair",
            "type":"Services"
        }
    ],
    "sg:phone":"+44 113 244 1437",
    "sg:postcode":"LS2 7EU",
    "sg:province":"West Yorkshire",
    "sg:tags":[
        "modification",
        "garage",
        "related"
    ],
    "wof:name":"Americo Motors",
    "wof:placetype":"venue"
},
  "geometry": {"coordinates":[-1.5372149944,53.7947692871],"type":"Point"}
}