{
  "type": "Feature",
  "properties": {
    "addr:full":"Unit 1/2 Prospect Business Park, Longford Road Cannock Staffordshire WS11 3LG",
    "addr:housenumber":"unit 1 / 2",
    "addr:postcode":"ws11 3lg",
    "addr:street":"Prospect Business Park Longford Road",
    "iso:country":"GB",
    "sg:address":"Unit 1/2 Prospect Business Park, Longford Road",
    "sg:city":"Cannock",
    "sg:classifiers":[
        {
            "category":"Food & Beverages",
            "subcategory":"Groceries & Convenience Stores",
            "type":"Retail Goods"
        }
    ],
    "sg:phone":"+44 1543 570961",
    "sg:postcode":"WS11 3LG",
    "sg:province":"Staffordshire",
    "sg:tags":[
        "frozen",
        "ice"
    ],
    "wof:name":"G M Jones & Son",
    "wof:placetype":"venue"
},
  "geometry": {"coordinates":[-2.0331449509,52.690952301],"type":"Point"}
}