{
  "type": "Feature",
  "properties": {
    "iso:country":"GB",
    "sg:address":"Green Lane",
    "sg:city":"Walsall",
    "sg:classifiers":[
        {
            "category":"Utilities",
            "subcategory":"Water",
            "type":"Services"
        }
    ],
    "sg:postcode":"WS2 7PD",
    "sg:province":"West Midlands",
    "wof:name":"South Staffordshire Water Services Ltd",
    "wof:placetype":"venue"
},
  "geometry": {"coordinates":[-1.998413,52.603577],"type":"Point"}
}