{
  "type": "Feature",
  "properties": {
    "addr:full":"5-9 East Rd Colchester Essex CO5 8EB",
    "addr:housenumber":"5-9",
    "addr:postcode":"co5 8eb",
    "addr:street":"East Rd",
    "iso:country":"GB",
    "sg:address":"5-9 East Rd",
    "sg:city":"Colchester",
    "sg:classifiers":[
        {
            "category":"Government",
            "subcategory":"Police Station",
            "type":"Public Place"
        }
    ],
    "sg:phone":"+44 1206 382930",
    "sg:postcode":"CO5 8EB",
    "sg:province":"Essex",
    "sg:tags":[
        "support"
    ],
    "wof:name":"West Mersea Police Station",
    "wof:placetype":"venue"
},
  "geometry": {"coordinates":[0.9209060073,51.7809448242],"type":"Point"}
}