{
  "type": "Feature",
  "properties": {
    "addr:full":"88 Broadway Frome Somerset BA11 3HG",
    "addr:housenumber":"88",
    "addr:postcode":"ba11 3hg",
    "addr:street":"Broadway",
    "iso:country":"GB",
    "sg:address":"88 Broadway",
    "sg:city":"Frome",
    "sg:classifiers":[
        {
            "category":"Professional",
            "subcategory":"Printing & Photocopies",
            "type":"Services"
        }
    ],
    "sg:phone":"+44 1373 467137",
    "sg:postcode":"BA11 3HG",
    "sg:province":"Somerset",
    "sg:tags":[
        "top",
        "publishing",
        "desk"
    ],
    "wof:name":"Printing Prospects",
    "wof:placetype":"venue"
},
  "geometry": {"coordinates":[-2.335394,51.232021],"type":"Point"}
}