{
  "type": "Feature",
  "properties": {
    "iso:country":"GB",
    "sg:address":"Smallshaw Industrial Estate, Accrington Road",
    "sg:city":"Burnley",
    "sg:classifiers":[
        {
            "category":"Shopping",
            "subcategory":"Stationery & Office Supplies",
            "type":"Retail Goods"
        }
    ],
    "sg:phone":"+44 1282 411220",
    "sg:postcode":"BB11 5DR",
    "sg:province":"Lancashire",
    "sg:tags":[
        "box",
        "carton"
    ],
    "wof:name":"Amalgamated Packaging",
    "wof:placetype":"venue"
},
  "geometry": {"coordinates":[-2.2438089848,53.7880096436],"type":"Point"}
}