{
  "type": "Feature",
  "properties": {
    "iso:country":"GB",
    "sg:address":"Ford Cottage, Low Road, West Acre",
    "sg:city":"King's Lynn",
    "sg:classifiers":[
        {
            "category":"Building & Trades",
            "subcategory":"Construction",
            "type":"Services"
        }
    ],
    "sg:phone":"+44 1760 755626",
    "sg:postcode":"PE32 1TR",
    "sg:province":"Norfolk",
    "sg:tags":[
        "monumental",
        "mason"
    ],
    "wof:name":"D Baker",
    "wof:placetype":"venue"
},
  "geometry": {"coordinates":[0.63669,52.706322],"type":"Point"}
}