{
  "type": "Feature",
  "properties": {
    "iso:country":"GB",
    "sg:address":"45b George Street",
    "sg:city":"Hastings",
    "sg:classifiers":[
        {
            "category":"Personal",
            "subcategory":"Beauty Salon",
            "type":"Services"
        }
    ],
    "sg:postcode":"TN34 3EA",
    "sg:province":"East Sussex",
    "sg:tags":[
        "unisex",
        "hairdresser"
    ],
    "wof:name":"J J's Hair Design",
    "wof:placetype":"venue"
},
  "geometry": {"coordinates":[0.589198,50.856087],"type":"Point"}
}