{
  "type": "Feature",
  "properties": {
    "addr:full":"35 Queensway London Greater London W2 4QJ",
    "addr:housenumber":"35",
    "addr:postcode":"w2 4qj",
    "addr:street":"Queensway",
    "iso:country":"GB",
    "sg:address":"35 Queensway",
    "sg:city":"London",
    "sg:classifiers":[
        {
            "category":"Sports & Exercise",
            "subcategory":"Sports Center",
            "type":"Entertainment"
        }
    ],
    "sg:phone":"+44 20 7727 4669",
    "sg:postcode":"W2 4QJ",
    "sg:province":"Greater London",
    "sg:tags":[
        "shop",
        "good"
    ],
    "wof:name":"Queen's Skate Shop",
    "wof:placetype":"venue"
},
  "geometry": {"coordinates":[-0.1874530017,51.5113487244],"type":"Point"}
}