{
  "type": "Feature",
  "properties": {
    "iso:country":"GB",
    "sg:address":"Wardle Rd",
    "sg:city":"Rochdale",
    "sg:classifiers":[
        {
            "category":"Community Center",
            "type":"Public Place"
        }
    ],
    "sg:phone":"+44 1706 353615",
    "sg:postcode":"OL12 9ER",
    "sg:province":"Lancashire",
    "sg:tags":[
        "centre"
    ],
    "wof:name":"Wardle & Smallbridge Community Centre",
    "wof:placetype":"venue"
},
  "geometry": {"coordinates":[-2.132834,53.646236],"type":"Point"}
}