{
  "type": "Feature",
  "properties": {
    "iso:country":"GB",
    "sg:address":"3 Preston Old Rd, Freckleton",
    "sg:city":"Preston",
    "sg:classifiers":[
        {
            "category":"Shopping",
            "subcategory":"Department Store",
            "type":"Retail Goods"
        }
    ],
    "sg:phone":"+44 1772 633552",
    "sg:postcode":"PR4 1PB",
    "sg:province":"Lancashire",
    "wof:name":"The New Goodbuys",
    "wof:placetype":"venue"
},
  "geometry": {"coordinates":[-2.864763,53.754612],"type":"Point"}
}