{
  "type": "Feature",
  "properties": {
    "iso:country":"GB",
    "sg:address":"Stainsbridge Mill, Gloucester Rd",
    "sg:city":"Malmesbury",
    "sg:classifiers":[
        {
            "category":"Manufacturing",
            "subcategory":"Metals",
            "type":"Manufacturing & Wholesale Goods"
        }
    ],
    "sg:postcode":"SN16 0AJ",
    "sg:province":"Wiltshire",
    "sg:tags":[
        "steel",
        "fabricator",
        "erectors"
    ],
    "wof:name":"Steel Structures (Gb) Ltd",
    "wof:placetype":"venue"
},
  "geometry": {"coordinates":[-2.097419,51.582245],"type":"Point"}
}