{
  "type": "Feature",
  "properties": {
    "iso:country":"GB",
    "sg:address":"Perrywood Wlk",
    "sg:city":"Worcester",
    "sg:classifiers":[
        {
            "category":"Professional",
            "subcategory":"Engineering",
            "type":"Services"
        }
    ],
    "sg:phone":"+44 1905 762000",
    "sg:postcode":"WR5 1EG",
    "sg:province":"Worcestershire",
    "wof:name":"Crown Packaging Uk Plc",
    "wof:placetype":"venue"
},
  "geometry": {"coordinates":[-2.201709,52.18681],"type":"Point"}
}