{
  "type": "Feature",
  "properties": {
    "addr:full":"Boggart House Farm, Station Lane, Barton Preston Lancashire PR3 5DY",
    "addr:postcode":"pr3 5dy",
    "addr:street":"Station Lane",
    "iso:country":"GB",
    "sg:address":"Boggart House Farm, Station Lane, Barton",
    "sg:city":"Preston",
    "sg:classifiers":[
        {
            "category":"Farming",
            "subcategory":"Dairy Farm",
            "type":"Manufacturing & Wholesale Goods"
        }
    ],
    "sg:phone":"+44 1772 862839",
    "sg:postcode":"PR3 5DY",
    "sg:province":"Lancashire",
    "sg:tags":[
        "farmer"
    ],
    "wof:name":"D P & S J Berry",
    "wof:placetype":"venue"
},
  "geometry": {"coordinates":[-2.735304,53.832909],"type":"Point"}
}