{
  "type": "Feature",
  "properties": {
    "iso:country":"GB",
    "sg:address":"34 Fartown Green Rd",
    "sg:city":"Huddersfield",
    "sg:classifiers":[
        {
            "category":"Health Services",
            "subcategory":"Doctor",
            "type":"Services"
        }
    ],
    "sg:phone":"+44 1484 534386",
    "sg:postcode":"HD2 1AE",
    "sg:province":"West Yorkshire",
    "sg:tags":[
        "practitioners"
    ],
    "wof:name":"Dr S.M Handa",
    "wof:placetype":"venue"
},
  "geometry": {"coordinates":[-1.778171,53.662697],"type":"Point"}
}