{
  "type": "Feature",
  "properties": {
    "addr:full":", Blencow Penrith Cumbria CA11 0DG",
    "addr:postcode":"ca11 0dg",
    "iso:country":"GB",
    "sg:address":", Blencow",
    "sg:city":"Penrith",
    "sg:classifiers":[
        {
            "category":"Bars & Pubs",
            "type":"Food & Drink"
        }
    ],
    "sg:phone":"+44 17684 83369",
    "sg:postcode":"CA11 0DG",
    "sg:province":"Cumbria",
    "sg:tags":[
        "pubs",
        "inn"
    ],
    "wof:name":"Crown Inn",
    "wof:placetype":"venue"
},
  "geometry": {"coordinates":[-2.848195076,54.6865844727],"type":"Point"}
}