{
  "type": "Feature",
  "properties": {
    "iso:country":"GB",
    "sg:address":"108 Neville Rd, Shirley",
    "sg:city":"Solihull",
    "sg:classifiers":[
        {
            "category":"Building & Trades",
            "subcategory":"Construction",
            "type":"Services"
        }
    ],
    "sg:postcode":"B90 2QN",
    "sg:province":"West Midlands",
    "sg:tags":[
        "roofing"
    ],
    "wof:name":"Quinn,Sean,",
    "wof:placetype":"venue"
},
  "geometry": {"coordinates":[-1.844237,52.400307],"type":"Point"}
}