{
  "type": "Feature",
  "properties": {
    "iso:country":"GB",
    "sg:address":"62 Hillfoot Avenue, Collier Row",
    "sg:city":"Romford",
    "sg:classifiers":[
        {
            "category":"Parking",
            "type":"Transportation"
        }
    ],
    "sg:phone":"+44 1708 731916",
    "sg:postcode":"RM5 3LH",
    "sg:province":"Essex",
    "sg:tags":[
        "car",
        "valet"
    ],
    "wof:name":"Curtis Auto Valet",
    "wof:placetype":"venue"
},
  "geometry": {"coordinates":[0.1663620025,51.5963745117],"type":"Point"}
}