{
  "type": "Feature",
  "properties": {
    "addr:full":"Ashurst Mount, Claytons Lane, Ashurst Tunbridge Wells East Sussex TN3 9TD",
    "addr:postcode":"tn3 9td",
    "addr:street":"Mount Claytons Lane",
    "iso:country":"GB",
    "sg:address":"Ashurst Mount, Claytons Lane, Ashurst",
    "sg:city":"Tunbridge Wells",
    "sg:classifiers":[
        {
            "category":"Real Estate",
            "subcategory":"Real Estate Agent",
            "type":"Services"
        }
    ],
    "sg:phone":"+44 1892 740072",
    "sg:postcode":"TN3 9TD",
    "sg:province":"East Sussex",
    "wof:name":"The County Homesearch Co. (Corporate Clients Division) Ltd.",
    "wof:placetype":"venue"
},
  "geometry": {"coordinates":[0.1771239936,51.1299324036],"type":"Point"}
}