{
  "type": "Feature",
  "properties": {
    "addr:full":"A6 Cabas, Garstang Preston Lancashire PR3 1PH",
    "addr:postcode":"pr3 1ph",
    "iso:country":"GB",
    "sg:address":"A6 Cabas, Garstang",
    "sg:city":"Preston",
    "sg:classifiers":[
        {
            "category":"Restaurant",
            "type":"Food & Drink"
        }
    ],
    "sg:phone":"+44 1995 601797",
    "sg:postcode":"PR3 1PH",
    "sg:province":"Lancashire",
    "sg:tags":[
        "chinese"
    ],
    "wof:name":"Great Season",
    "wof:placetype":"venue"
},
  "geometry": {"coordinates":[-2.774599,53.938816],"type":"Point"}
}