{
  "type": "Feature",
  "properties": {
    "iso:country":"GB",
    "sg:address":"367 High Road",
    "sg:city":"London",
    "sg:classifiers":[
        {
            "category":"Fast Food",
            "type":"Food & Drink"
        }
    ],
    "sg:phone":"+44 20 8451 6272",
    "sg:postcode":"NW10 2JR",
    "sg:province":"Greater London",
    "sg:tags":[
        "away",
        "take"
    ],
    "wof:name":"Chorum Kebab House",
    "wof:placetype":"venue"
},
  "geometry": {"coordinates":[-0.2410939932,51.548248291],"type":"Point"}
}