{
  "type": "Feature",
  "properties": {
    "addr:full":"Unit 33 Sketchley Indtl Estate Hinckley Leicestershire LE10 3ES",
    "addr:housenumber":"unit 33",
    "addr:postcode":"le10 3es",
    "addr:street":"Sketchley Indtl Estate",
    "iso:country":"GB",
    "sg:address":"Unit 33 Sketchley Indtl Estate",
    "sg:city":"Hinckley",
    "sg:classifiers":[
        {
            "category":"Professional",
            "subcategory":"Engineering",
            "type":"Services"
        }
    ],
    "sg:phone":"+44 1455 617770",
    "sg:postcode":"LE10 3ES",
    "sg:province":"Leicestershire",
    "sg:tags":[
        "precision",
        "engineer"
    ],
    "wof:name":"Eurotech Precision",
    "wof:placetype":"venue"
},
  "geometry": {"coordinates":[-1.375123,52.526314],"type":"Point"}
}