{
  "type": "Feature",
  "properties": {
    "iso:country":"GB",
    "sg:address":"2 Thornhill Road, Middlestown",
    "sg:city":"Wakefield",
    "sg:classifiers":[
        {
            "category":"Government",
            "subcategory":"Post Office",
            "type":"Public Place"
        }
    ],
    "sg:phone":"+44 1924 274336",
    "sg:postcode":"WF4 4PD",
    "sg:province":"West Yorkshire",
    "wof:name":"Middlestown Post Office",
    "wof:placetype":"venue"
},
  "geometry": {"coordinates":[-1.599281,53.652054],"type":"Point"}
}