{
  "type": "Feature",
  "properties": {
    "iso:country":"GB",
    "sg:address":"1 Britannia Street",
    "sg:city":"Leicester",
    "sg:classifiers":[
        {
            "category":"Professional",
            "subcategory":"Printing & Photocopies",
            "type":"Services"
        }
    ],
    "sg:phone":"+44 116 253 2124",
    "sg:postcode":"LE1 3LE",
    "sg:province":"Leicestershire",
    "sg:tags":[
        "printer"
    ],
    "wof:name":"The Duplicating Centre",
    "wof:placetype":"venue"
},
  "geometry": {"coordinates":[-1.127871,52.642681],"type":"Point"}
}