{
  "type": "Feature",
  "properties": {
    "addr:full":"Unit G, Harvey Works Stoke-on-trent Staffordshire ST6 1ED",
    "addr:housenumber":"unit g",
    "addr:postcode":"staffordshire st6 1ed",
    "iso:country":"GB",
    "sg:address":"Unit G, Harvey Works",
    "sg:city":"Stoke-on-trent",
    "sg:classifiers":[
        {
            "category":"Brewery",
            "type":"Food & Drink"
        }
    ],
    "sg:phone":"+44 1782 823447",
    "sg:postcode":"ST6 1ED",
    "sg:province":"Staffordshire",
    "sg:tags":[
        "brewer"
    ],
    "wof:name":"Titanic Brewery",
    "wof:placetype":"venue"
},
  "geometry": {"coordinates":[-2.18808,53.04678],"type":"Point"}
}