{
  "type": "Feature",
  "properties": {
    "iso:country":"GB",
    "sg:address":"Station Yard, Station Rd, Stowbridge",
    "sg:city":"King's Lynn",
    "sg:classifiers":[
        {
            "category":"Retail",
            "subcategory":"Auto Repair",
            "type":"Services"
        }
    ],
    "sg:phone":"+44 1366 382620",
    "sg:postcode":"PE34 3PH",
    "sg:province":"Lincolnshire",
    "sg:tags":[
        "body",
        "car"
    ],
    "wof:name":"Ian Halliday",
    "wof:placetype":"venue"
},
  "geometry": {"coordinates":[0.37492,52.636829],"type":"Point"}
}