{
  "type": "Feature",
  "properties": {
    "iso:country":"GB",
    "sg:address":"Limekiln Lane, Yardley Wood",
    "sg:city":"Birmingham",
    "sg:classifiers":[
        {
            "category":"Manufacturing",
            "subcategory":"Metals",
            "type":"Manufacturing & Wholesale Goods"
        }
    ],
    "sg:phone":"+44 121 474 2500",
    "sg:postcode":"B14 4SP",
    "sg:province":"West Midlands",
    "sg:tags":[
        "product",
        "fabricated"
    ],
    "wof:name":"Cogent Contracts Ltd.",
    "wof:placetype":"venue"
},
  "geometry": {"coordinates":[-1.868831,52.412399],"type":"Point"}
}