{
  "type": "Feature",
  "properties": {
    "iso:country":"GB",
    "sg:address":"Thicket Road, Penge",
    "sg:city":"London",
    "sg:classifiers":[
        {
            "category":"Landmark",
            "subcategory":"Tourist Attraction",
            "type":"Public Place"
        }
    ],
    "sg:postcode":"SE20 8UT",
    "sg:province":"Greater London",
    "sg:tags":[
        "interest"
    ],
    "wof:name":"Crystal Palace Park",
    "wof:placetype":"venue"
},
  "geometry": {"coordinates":[-0.0673429966,51.4163322449],"type":"Point"}
}