{
  "type": "Feature",
  "properties": {
    "addr:full":"18 York Road Maidenhead Berkshire SL6 1SF",
    "addr:housenumber":"18",
    "addr:postcode":"sl6 1sf",
    "addr:street":"York Road",
    "iso:country":"GB",
    "sg:address":"18 York Road",
    "sg:city":"Maidenhead",
    "sg:classifiers":[
        {
            "category":"Manufacturing",
            "subcategory":"Building Materials",
            "type":"Manufacturing & Wholesale Goods"
        }
    ],
    "sg:phone":"+44 1628 635911",
    "sg:postcode":"SL6 1SF",
    "sg:province":"Berkshire",
    "sg:tags":[
        "tube",
        "manipulator",
        "bender"
    ],
    "wof:name":"Pipework Fittings & Forgings Ltd.",
    "wof:placetype":"venue"
},
  "geometry": {"coordinates":[-0.7197830081,51.5204315186],"type":"Point"}
}