{
  "type": "Feature",
  "properties": {
    "iso:country":"GB",
    "sg:address":"Bristol Royal Infirmary, Maudlin St",
    "sg:city":"Bristol",
    "sg:classifiers":[
        {
            "category":"Communications",
            "type":"Services"
        }
    ],
    "sg:phone":"+44 117 929 3303",
    "sg:postcode":"BS2 8HW",
    "sg:province":"City of Bristol",
    "sg:tags":[
        "broadcasting"
    ],
    "wof:name":"Bristol Hospital Broadcasts Service",
    "wof:placetype":"venue"
},
  "geometry": {"coordinates":[-2.5960800648,51.4593505859],"type":"Point"}
}