{
  "type": "Feature",
  "properties": {
    "addr:full":"Mutton Hall Lane Heathfield East Sussex TN21 8NR",
    "addr:postcode":"tn21 8nr",
    "addr:street":"Hall Lane",
    "iso:country":"GB",
    "sg:address":"Mutton Hall Lane",
    "sg:city":"Heathfield",
    "sg:classifiers":[
        {
            "category":"Travel",
            "subcategory":"Hotels & Motels",
            "type":"Entertainment"
        }
    ],
    "sg:postcode":"TN21 8NR",
    "sg:province":"East Sussex",
    "sg:tags":[
        "house",
        "guest"
    ],
    "wof:name":"Iwood",
    "wof:placetype":"venue"
},
  "geometry": {"coordinates":[0.257493,50.973854],"type":"Point"}
}