{
  "type": "Feature",
  "properties": {
    "addr:full":"26 Netherkirkgate Aberdeen Aberdeen City AB10 1AU",
    "addr:housenumber":"26",
    "addr:postcode":"ab10 1au",
    "addr:street":"Netherkirkgate",
    "iso:country":"GB",
    "sg:address":"26 Netherkirkgate",
    "sg:city":"Aberdeen",
    "sg:classifiers":[
        {
            "category":"Shopping",
            "subcategory":"Clothing, Apparel, & Fashions",
            "type":"Retail Goods"
        },
        {
            "category":"Sports & Exercise",
            "subcategory":"Sports Center",
            "type":"Entertainment"
        }
    ],
    "sg:phone":"+44 1224 634934",
    "sg:postcode":"AB10 1AU",
    "sg:province":"Aberdeen City",
    "sg:tags":[
        "shop",
        "equipment",
        "outdoor",
        "clothing"
    ],
    "wof:name":"Graham Tiso",
    "wof:placetype":"venue"
},
  "geometry": {"coordinates":[-2.09654,57.147694],"type":"Point"}
}