{
  "type": "Feature",
  "properties": {
    "addr:full":"233a Horseley Heath Tipton West Midlands DY4 7QT",
    "addr:housenumber":"233a",
    "addr:postcode":"dy4 7qt",
    "addr:street":"Horseley Heath Tipton",
    "iso:country":"GB",
    "sg:address":"233a Horseley Heath",
    "sg:city":"Tipton",
    "sg:classifiers":[
        {
            "category":"Recreation",
            "subcategory":"Dog Park",
            "type":"Entertainment"
        }
    ],
    "sg:phone":"+44 121 557 4933",
    "sg:postcode":"DY4 7QT",
    "sg:province":"West Midlands",
    "wof:name":"Tops & Tails",
    "wof:placetype":"venue"
},
  "geometry": {"coordinates":[-2.045921,52.526089],"type":"Point"}
}