{
  "type": "Feature",
  "properties": {
    "addr:full":"25 Maelfa, Llanedeyrn Cardiff Cardiff CF23 9PL",
    "addr:housenumber":"25",
    "addr:postcode":"cf23 9pl",
    "addr:street":"Maelfa Llanedeyrn",
    "iso:country":"GB",
    "sg:address":"25 Maelfa, Llanedeyrn",
    "sg:city":"Cardiff",
    "sg:classifiers":[
        {
            "category":"Home & Garden",
            "subcategory":"Furniture",
            "type":"Retail Goods"
        }
    ],
    "sg:phone":"+44 29 2061 9530",
    "sg:postcode":"CF23 9PL",
    "sg:province":"Cardiff",
    "wof:name":"Llanederyn Furniture & Carpet Centre",
    "wof:placetype":"venue"
},
  "geometry": {"coordinates":[-3.149116,51.50742],"type":"Point"}
}