{
  "type": "Feature",
  "properties": {
    "addr:full":"13 The Workshop Greenock Inverclyde PA16 8JL",
    "addr:housenumber":"13;workshop",
    "addr:postcode":"pa16 8jl",
    "addr:street":"The",
    "iso:country":"GB",
    "sg:address":"13 The Workshop",
    "sg:city":"Greenock",
    "sg:classifiers":[
        {
            "category":"Professional",
            "subcategory":"Art Services",
            "type":"Services"
        }
    ],
    "sg:postcode":"PA16 8JL",
    "sg:province":"Inverclyde",
    "sg:tags":[
        "framing"
    ],
    "wof:name":"Inverclyde Art & Framing",
    "wof:placetype":"venue"
},
  "geometry": {"coordinates":[-4.7663297653,55.9513587952],"type":"Point"}
}