{
  "type": "Feature",
  "properties": {
    "addr:full":"54a Sandwell Road West Bromwich West Midlands B70 8TG",
    "addr:housenumber":"54a",
    "addr:postcode":"b70 8tg",
    "addr:street":"Sandwell Road",
    "iso:country":"GB",
    "sg:address":"54a Sandwell Road",
    "sg:city":"West Bromwich",
    "sg:classifiers":[
        {
            "category":"Retail",
            "subcategory":"Emissions Testing",
            "type":"Services"
        },
        {
            "category":"Retail",
            "subcategory":"Auto Repair",
            "type":"Services"
        }
    ],
    "sg:phone":"+44 121 553 0296",
    "sg:postcode":"B70 8TG",
    "sg:province":"West Midlands",
    "sg:tags":[
        "modification",
        "garage",
        "mot"
    ],
    "wof:name":"Sun Garage Co.",
    "wof:placetype":"venue"
},
  "geometry": {"coordinates":[-1.99737,52.523228],"type":"Point"}
}