{
  "type": "Feature",
  "properties": {
    "addr:full":"181 Haunchwood Rd Nuneaton Leicestershire CV10 8DG",
    "addr:housenumber":"181",
    "addr:postcode":"cv10 8dg",
    "addr:street":"Haunchwood Rd",
    "iso:country":"GB",
    "sg:address":"181 Haunchwood Rd",
    "sg:city":"Nuneaton",
    "sg:classifiers":[
        {
            "category":"Shopping",
            "subcategory":"Stationery & Office Supplies",
            "type":"Retail Goods"
        }
    ],
    "sg:phone":"+44 24 7632 5795",
    "sg:postcode":"CV10 8DG",
    "sg:province":"Leicestershire",
    "sg:tags":[
        "equipment"
    ],
    "wof:name":"Abbey Office Equipment",
    "wof:placetype":"venue"
},
  "geometry": {"coordinates":[-1.5012489557,52.5214004517],"type":"Point"}
}