{
  "type": "Feature",
  "properties": {
    "addr:full":"38 Beresford Road, Seaton Sluice Whitley Bay Northumberland NE26 4RQ",
    "addr:housenumber":"38",
    "addr:postcode":"ne26 4rq",
    "addr:street":"Beresford Road",
    "iso:country":"GB",
    "sg:address":"38 Beresford Road, Seaton Sluice",
    "sg:city":"Whitley Bay",
    "sg:classifiers":[
        {
            "category":"Shopping",
            "subcategory":"News",
            "type":"Retail Goods"
        }
    ],
    "sg:phone":"+44 191 237 0283",
    "sg:postcode":"NE26 4RQ",
    "sg:province":"Northumberland",
    "sg:tags":[
        "newsagent"
    ],
    "wof:name":"Davis Newsagents",
    "wof:placetype":"venue"
},
  "geometry": {"coordinates":[-1.473639,55.082584],"type":"Point"}
}