{
  "type": "Feature",
  "properties": {
    "addr:full":"38 London Road Bagshot Berkshire GU19 5HN",
    "addr:housenumber":"38",
    "addr:postcode":"gu19 5hn",
    "addr:street":"London Road",
    "iso:country":"GB",
    "sg:address":"38 London Road",
    "sg:city":"Bagshot",
    "sg:classifiers":[
        {
            "category":"Recreation",
            "subcategory":"Dog Park",
            "type":"Entertainment"
        }
    ],
    "sg:phone":"+44 1276 472462",
    "sg:postcode":"GU19 5HN",
    "sg:province":"Berkshire",
    "wof:name":"Canine Beautician",
    "wof:placetype":"venue"
},
  "geometry": {"coordinates":[-0.690863,51.364414],"type":"Point"}
}