{
  "type": "Feature",
  "properties": {
    "iso:country":"GB",
    "sg:address":"Dudley St",
    "sg:city":"Wednesbury",
    "sg:classifiers":[
        {
            "category":"Recreation",
            "subcategory":"Dance Hall",
            "type":"Entertainment"
        }
    ],
    "sg:phone":"+44 121 556 2689",
    "sg:postcode":"WS10 7DR",
    "sg:province":"West Midlands",
    "sg:tags":[
        "bingo"
    ],
    "wof:name":"Mecca Leisure Ltd",
    "wof:placetype":"venue"
},
  "geometry": {"coordinates":[-2.022647,52.553486],"type":"Point"}
}