{
  "type": "Feature",
  "properties": {
    "addr:full":"The Belfry Redhill Surrey RH1 1PW",
    "addr:postcode":"rh1 1pw",
    "iso:country":"GB",
    "sg:address":"The Belfry",
    "sg:city":"Redhill",
    "sg:classifiers":[
        {
            "category":"Shopping",
            "subcategory":"Beauty & Cosmetics",
            "type":"Retail Goods"
        }
    ],
    "sg:phone":"+44 1737 768840",
    "sg:postcode":"RH1 1PW",
    "sg:province":"Surrey",
    "sg:tags":[
        "product"
    ],
    "wof:name":"The Body Shop",
    "wof:placetype":"venue"
},
  "geometry": {"coordinates":[-0.1688790023,51.2381782532],"type":"Point"}
}