{
  "type": "Feature",
  "properties": {
    "addr:full":"5 Shopping Centre, Earls Field, Raf Lakenheath Brandon Norfolk IP27 9RX",
    "addr:housenumber":"5",
    "addr:postcode":"ip27 9rx",
    "addr:street":"Shopping Centre Earls Field",
    "iso:country":"GB",
    "sg:address":"5 Shopping Centre, Earls Field, Raf Lakenheath",
    "sg:city":"Brandon",
    "sg:classifiers":[
        {
            "category":"Home & Garden",
            "subcategory":"Furniture",
            "type":"Retail Goods"
        }
    ],
    "sg:phone":"+44 1638 532999",
    "sg:postcode":"IP27 9RX",
    "sg:province":"Norfolk",
    "wof:name":"A S B I",
    "wof:placetype":"venue"
},
  "geometry": {"coordinates":[0.526910007,52.4061012268],"type":"Point"}
}