{
  "type": "Feature",
  "properties": {
    "addr:full":"Dean Road, Cox's Northern Site Bristol City of Bristol BS11 8AT",
    "addr:postcode":"bs11 8at",
    "addr:street":"Dean Road",
    "iso:country":"GB",
    "sg:address":"Dean Road, Cox's Northern Site",
    "sg:city":"Bristol",
    "sg:classifiers":[
        {
            "category":"Retail",
            "subcategory":"Auto Repair",
            "type":"Services"
        }
    ],
    "sg:phone":"+44 117 982 6944",
    "sg:postcode":"BS11 8AT",
    "sg:province":"City of Bristol",
    "sg:tags":[
        "bodybuilder",
        "repairer"
    ],
    "wof:name":"Boalloy",
    "wof:placetype":"venue"
},
  "geometry": {"coordinates":[-2.6785099506,51.5102081299],"type":"Point"}
}