{
  "type": "Feature",
  "properties": {
    "addr:full":"252 Causewayside Edinburgh EH9 1UU",
    "addr:housenumber":"252",
    "addr:postcode":"eh9 1uu",
    "addr:street":"Causewayside",
    "iso:country":"GB",
    "sg:address":"252 Causewayside",
    "sg:city":"Edinburgh",
    "sg:classifiers":[
        {
            "category":"Professional",
            "subcategory":"Computer Services",
            "type":"Services"
        }
    ],
    "sg:postcode":"EH9 1UU",
    "sg:website":"http://www.pufferfishdisplays.co.uk",
    "wof:name":"Pufferfish",
    "wof:placetype":"venue"
},
  "geometry": {"coordinates":[-3.1795482,55.9345905],"type":"Point"}
}