{
  "type": "Feature",
  "properties": {
    "addr:full":"178 Front Street Chester-le-street Durham DH3 3AZ",
    "addr:housenumber":"178",
    "addr:postcode":"dh3 3az",
    "addr:street":"Front Street",
    "iso:country":"GB",
    "sg:address":"178 Front Street",
    "sg:city":"Chester-le-street",
    "sg:classifiers":[
        {
            "category":"Food & Beverages",
            "subcategory":"Meat & Fish",
            "type":"Retail Goods"
        }
    ],
    "sg:phone":"+44 191 387 1143",
    "sg:postcode":"DH3 3AZ",
    "sg:province":"Durham",
    "sg:tags":[
        "butcher"
    ],
    "wof:name":"J Loughlin & Sons",
    "wof:placetype":"venue"
},
  "geometry": {"coordinates":[-1.573094964,54.8527984619],"type":"Point"}
}