{
  "type": "Feature",
  "properties": {
    "iso:country":"GB",
    "sg:address":"29 Water Lane",
    "sg:city":"Wilmslow",
    "sg:classifiers":[
        {
            "category":"Insurance",
            "subcategory":"Insurance Agent",
            "type":"Services"
        }
    ],
    "sg:postcode":"SK9 5AR",
    "sg:province":"Cheshire",
    "wof:name":"Swinton",
    "wof:placetype":"venue"
},
  "geometry": {"coordinates":[-2.234958,53.326103],"type":"Point"}
}