{
  "type": "Feature",
  "properties": {
    "addr:full":"1881 Leek Rd Stoke On Trent Staffordshire ST2 7AQ",
    "addr:housenumber":"1881",
    "addr:postcode":"st2 7aq",
    "addr:street":"Leek Rd",
    "iso:country":"GB",
    "sg:address":"1881 Leek Rd",
    "sg:city":"Stoke On Trent",
    "sg:classifiers":[
        {
            "category":"Personal",
            "subcategory":"Beauty Salon",
            "type":"Services"
        }
    ],
    "sg:phone":"+44 1782 534287",
    "sg:postcode":"ST2 7AQ",
    "sg:province":"Staffordshire",
    "sg:tags":[
        "unisex",
        "hairdresser"
    ],
    "wof:name":"Marwin Salon",
    "wof:placetype":"venue"
},
  "geometry": {"coordinates":[-2.140427,53.048706],"type":"Point"}
}