{
  "type": "Feature",
  "properties": {
    "addr:full":"Jasmine House, High Street Henfield West Sussex BN5 9HN",
    "addr:postcode":"bn5 9hn",
    "addr:street":"High Street",
    "iso:country":"GB",
    "sg:address":"Jasmine House, High Street",
    "sg:city":"Henfield",
    "sg:classifiers":[
        {
            "category":"Shopping",
            "subcategory":"Computers & Home Electronics",
            "type":"Retail Goods"
        }
    ],
    "sg:postcode":"BN5 9HN",
    "sg:province":"West Sussex",
    "sg:tags":[
        "electrical"
    ],
    "wof:name":"Product Creation Ltd.",
    "wof:placetype":"venue"
},
  "geometry": {"coordinates":[-0.272319,50.930904],"type":"Point"}
}