{
  "type": "Feature",
  "properties": {
    "iso:country":"GB",
    "sg:address":"Greg Street, South Reddish",
    "sg:city":"Stockport",
    "sg:classifiers":[
        {
            "category":"Landmark",
            "subcategory":"Tourist Attraction",
            "type":"Public Place"
        }
    ],
    "sg:phone":"+44 161 477 8081",
    "sg:postcode":"SK5 7LN",
    "sg:province":"Cheshire",
    "sg:tags":[
        "interest"
    ],
    "wof:name":"South Reddish Park",
    "wof:placetype":"venue"
},
  "geometry": {"coordinates":[-2.157879,53.434635],"type":"Point"}
}