{
  "type": "Feature",
  "properties": {
    "addr:full":"6 Willow Close, Earlsfield London Greater London SW18 3EL",
    "addr:housenumber":"6",
    "addr:postcode":"sw18 3el",
    "addr:street":"Willow Close",
    "iso:country":"GB",
    "sg:address":"6 Willow Close, Earlsfield",
    "sg:city":"London",
    "sg:classifiers":[
        {
            "category":"Communications",
            "type":"Services"
        }
    ],
    "sg:postcode":"SW18 3EL",
    "sg:province":"Greater London",
    "sg:tags":[
        "telecommunication"
    ],
    "wof:name":"Bizzy Communications Ltd",
    "wof:placetype":"venue"
},
  "geometry": {"coordinates":[-0.296469003,51.502494812],"type":"Point"}
}