{
  "type": "Feature",
  "properties": {
    "iso:country":"GB",
    "sg:address":"Little Dalcross",
    "sg:city":"Inverness",
    "sg:classifiers":[
        {
            "category":"Farming",
            "subcategory":"Livestock Farm",
            "type":"Manufacturing & Wholesale Goods"
        }
    ],
    "sg:phone":"+44 1667 493224",
    "sg:postcode":"IV1 2PS",
    "sg:province":"Highland",
    "sg:tags":[
        "others"
    ],
    "wof:name":"D F & D A Douglas",
    "wof:placetype":"venue"
},
  "geometry": {"coordinates":[-4.0437898636,57.5132598877],"type":"Point"}
}