{
  "type": "Feature",
  "properties": {
    "addr:full":"49 Duke St Darlington Durham DL3 7SD",
    "addr:housenumber":"49",
    "addr:postcode":"dl3 7sd",
    "addr:street":"Duke St",
    "iso:country":"GB",
    "sg:address":"49 Duke St",
    "sg:city":"Darlington",
    "sg:classifiers":[
        {
            "category":"Professional",
            "subcategory":"Lawyer & Legal Services",
            "type":"Services"
        }
    ],
    "sg:postcode":"DL3 7SD",
    "sg:province":"Durham",
    "sg:tags":[
        "practitioner",
        "insolvency"
    ],
    "wof:name":"Armstrong Watson & Co",
    "wof:placetype":"venue"
},
  "geometry": {"coordinates":[-1.5610159636,54.5253067017],"type":"Point"}
}