{
  "type": "Feature",
  "properties": {
    "iso:country":"GB",
    "sg:address":"90-92 High Street",
    "sg:city":"Edgware",
    "sg:classifiers":[
        {
            "category":"Sports & Exercise",
            "subcategory":"Sports Center",
            "type":"Entertainment"
        }
    ],
    "sg:postcode":"HA8 7HF",
    "sg:province":"Greater London",
    "sg:tags":[
        "shop",
        "good"
    ],
    "wof:name":"Sharp Sports",
    "wof:placetype":"venue"
},
  "geometry": {"coordinates":[-0.281189,51.612396],"type":"Point"}
}