{
  "type": "Feature",
  "properties": {
    "addr:full":"130 North Walls Stafford Staffordshire ST16 3AD",
    "addr:housenumber":"130",
    "addr:postcode":"st16 3ad",
    "addr:street":"North Walls",
    "iso:country":"GB",
    "sg:address":"130 North Walls",
    "sg:city":"Stafford",
    "sg:classifiers":[
        {
            "category":"Retail",
            "subcategory":"Auto Repair",
            "type":"Services"
        }
    ],
    "sg:postcode":"ST16 3AD",
    "sg:province":"Staffordshire",
    "sg:tags":[
        "modification",
        "garage"
    ],
    "wof:name":"Mc Curry,Jerry",
    "wof:placetype":"venue"
},
  "geometry": {"coordinates":[-2.112643,52.806919],"type":"Point"}
}