{
  "type": "Feature",
  "properties": {
    "iso:country":"GB",
    "sg:address":"18 Thurstaston Road, Irby",
    "sg:city":"Wirral",
    "sg:classifiers":[
        {
            "category":"Health Services",
            "subcategory":"Health Practitioner",
            "type":"Services"
        }
    ],
    "sg:phone":"+44 151 648 1759",
    "sg:postcode":"CH61 0HE",
    "sg:province":"Merseyside",
    "sg:tags":[
        "psychologist"
    ],
    "wof:name":"A Sinnott",
    "wof:placetype":"venue"
},
  "geometry": {"coordinates":[-3.121846,53.353176],"type":"Point"}
}