{
  "type": "Feature",
  "properties": {
    "addr:full":"Jaicey Farm, North Newton Bridgwater Somerset TA7 0BN",
    "addr:postcode":"ta7 0bn",
    "addr:street":"North Newton",
    "iso:country":"GB",
    "sg:address":"Jaicey Farm, North Newton",
    "sg:city":"Bridgwater",
    "sg:classifiers":[
        {
            "category":"Home & Garden",
            "subcategory":"Garden Supply",
            "type":"Retail Goods"
        },
        {
            "category":"Farming",
            "subcategory":"Livestock Farm",
            "type":"Manufacturing & Wholesale Goods"
        }
    ],
    "sg:postcode":"TA7 0BN",
    "sg:province":"Somerset",
    "sg:tags":[
        "bulb",
        "grower",
        "others"
    ],
    "wof:name":"John Bernard Collard",
    "wof:placetype":"venue"
},
  "geometry": {"coordinates":[-3.0004739761,51.074546814],"type":"Point"}
}