{
  "type": "Feature",
  "properties": {
    "iso:country":"GB",
    "sg:address":"29 Charlesford Avenue, Kingswood",
    "sg:city":"Maidstone",
    "sg:classifiers":[
        {
            "category":"Shopping",
            "subcategory":"News",
            "type":"Retail Goods"
        },
        {
            "category":"Government",
            "subcategory":"Post Office",
            "type":"Public Place"
        },
        {
            "category":"Food & Beverages",
            "subcategory":"Groceries & Convenience Stores",
            "type":"Retail Goods"
        }
    ],
    "sg:phone":"+44 1622 844594",
    "sg:postcode":"ME17 3PE",
    "sg:province":"Kent",
    "sg:tags":[
        "newsagent"
    ],
    "wof:name":"KINGSWOOD POST OFFICE",
    "wof:placetype":"venue"
},
  "geometry": {"coordinates":[0.6318119764,51.2291679382],"type":"Point"}
}