{
  "type": "Feature",
  "properties": {
    "addr:full":"12 Burleigh View, Bussage, Stroud Gloucestershire GL6 8DD",
    "addr:housenumber":"12",
    "addr:postcode":"gl6 8dd",
    "addr:street":"Burleigh View",
    "iso:country":"GB",
    "sg:address":"12 Burleigh View, Bussage,",
    "sg:city":"Stroud",
    "sg:classifiers":[
        {
            "category":"Professional",
            "subcategory":"Engineering",
            "type":"Services"
        }
    ],
    "sg:postcode":"GL6 8DD",
    "sg:province":"Gloucestershire",
    "sg:tags":[
        "contractor",
        "electrical",
        "engineer"
    ],
    "wof:name":"Purse  Graham",
    "wof:placetype":"venue"
},
  "geometry": {"coordinates":[-2.1672980785,51.7307548523],"type":"Point"}
}