{
  "type": "Feature",
  "properties": {
    "addr:full":"1a Clayton Park Square Newcastle-upon-tyne Tyne and Wear NE2 4DP",
    "addr:housenumber":"1a",
    "addr:postcode":"ne2 4dp",
    "addr:street":"Clayton Park Square",
    "iso:country":"GB",
    "sg:address":"1a Clayton Park Square",
    "sg:city":"Newcastle-upon-tyne",
    "sg:classifiers":[
        {
            "category":"Communications",
            "subcategory":"News Services",
            "type":"Services"
        }
    ],
    "sg:phone":"+44 191 281 0619",
    "sg:postcode":"NE2 4DP",
    "sg:province":"Tyne and Wear",
    "sg:tags":[
        "journalist"
    ],
    "wof:name":"John Wardle",
    "wof:placetype":"venue"
},
  "geometry": {"coordinates":[-1.610574,54.985497],"type":"Point"}
}