{
  "type": "Feature",
  "properties": {
    "iso:country":"GB",
    "sg:address":"The Development Centre, Valley Dr",
    "sg:city":"Ilkley",
    "sg:classifiers":[
        {
            "category":"Professional",
            "subcategory":"Printing & Photocopies",
            "type":"Services"
        }
    ],
    "sg:phone":"+44 1943 816200",
    "sg:postcode":"LS29 8AL",
    "sg:province":"North Yorkshire",
    "sg:tags":[
        "printer"
    ],
    "wof:name":"Emka Print",
    "wof:placetype":"venue"
},
  "geometry": {"coordinates":[-1.821754,53.924461],"type":"Point"}
}