{
  "type": "Feature",
  "properties": {
    "addr:full":"First Floor Beaumont House, Lambton Road London Greater London SW20 0LW",
    "addr:postcode":"sw20 0lw",
    "addr:street":"Lambton Road",
    "iso:country":"GB",
    "sg:address":"First Floor Beaumont House, Lambton Road",
    "sg:city":"London",
    "sg:classifiers":[
        {
            "category":"Travel",
            "subcategory":"Travel Agent",
            "type":"Entertainment"
        }
    ],
    "sg:phone":"+44 20 8288 1430",
    "sg:postcode":"SW20 0LW",
    "sg:province":"Greater London",
    "wof:name":"A A C",
    "wof:placetype":"venue"
},
  "geometry": {"coordinates":[-0.231619,51.413544],"type":"Point"}
}