{
  "type": "Feature",
  "properties": {
    "iso:country":"GB",
    "sg:address":"Rivelin Glen",
    "sg:city":"Sheffield",
    "sg:classifiers":[
        {
            "category":"Manufacturing",
            "subcategory":"Building Materials",
            "type":"Manufacturing & Wholesale Goods"
        }
    ],
    "sg:phone":"+44 114 234 7630",
    "sg:postcode":"S6 5SE",
    "sg:province":"South Yorkshire",
    "sg:tags":[
        "stonemason"
    ],
    "wof:name":"Rivelin Glen Quarry",
    "wof:placetype":"venue"
},
  "geometry": {"coordinates":[-1.5657269955,53.3803939819],"type":"Point"}
}