{
  "type": "Feature",
  "properties": {
    "addr:full":"77 Lampton Road Hounslow Greater London TW3 4JX",
    "addr:housenumber":"77",
    "addr:postcode":"tw3 4jx",
    "addr:street":"Lampton Road",
    "iso:country":"GB",
    "sg:address":"77 Lampton Road",
    "sg:city":"Hounslow",
    "sg:classifiers":[
        {
            "category":"Health Services",
            "subcategory":"Doctor",
            "type":"Services"
        }
    ],
    "sg:phone":"+44 20 8572 1497",
    "sg:postcode":"TW3 4JX",
    "sg:province":"Greater London",
    "sg:tags":[
        "practitioners"
    ],
    "wof:name":"Parvinder Garcha & Signh",
    "wof:placetype":"venue"
},
  "geometry": {"coordinates":[-0.3665030003,51.4731712341],"type":"Point"}
}