{
  "type": "Feature",
  "properties": {
    "iso:country":"GB",
    "sg:address":"1 Market Square, Wellington",
    "sg:city":"Telford",
    "sg:classifiers":[
        {
            "category":"Retail",
            "subcategory":"Photofinishing",
            "type":"Services"
        },
        {
            "category":"Retail",
            "subcategory":"Laundry & Dry Cleaning",
            "type":"Services"
        }
    ],
    "sg:phone":"+44 1952 252770",
    "sg:postcode":"TF1 1DB",
    "sg:province":"Shropshire",
    "sg:tags":[
        "photographic",
        "alteration",
        "processor"
    ],
    "wof:name":"Sketchley Retail Ltd.",
    "wof:placetype":"venue"
},
  "geometry": {"coordinates":[-2.518679,52.70097],"type":"Point"}
}