{
  "type": "Feature",
  "properties": {
    "iso:country":"GB",
    "sg:address":"2b Briton Hill Road, Sanderstead",
    "sg:city":"South Croydon",
    "sg:classifiers":[
        {
            "category":"Building & Trades",
            "subcategory":"Plumbing",
            "type":"Services"
        }
    ],
    "sg:phone":"+44 20 8651 3079",
    "sg:postcode":"CR2 0JL",
    "sg:province":"Surrey",
    "sg:tags":[
        "central",
        "heating"
    ],
    "wof:name":"R & J Loveland",
    "wof:placetype":"venue"
},
  "geometry": {"coordinates":[-0.0858089998,51.3415565491],"type":"Point"}
}