{
  "type": "Feature",
  "properties": {
    "addr:full":"41 Breton Side Plymouth Devon PL4 0BB",
    "addr:housenumber":"41",
    "addr:postcode":"pl4 0bb",
    "addr:street":"Breton Side",
    "iso:country":"GB",
    "sg:address":"41 Breton Side",
    "sg:city":"Plymouth",
    "sg:classifiers":[
        {
            "category":"Retail",
            "subcategory":"Repair Shop",
            "type":"Services"
        }
    ],
    "sg:postcode":"PL4 0BB",
    "sg:province":"Devon",
    "sg:tags":[
        "clocks",
        "watch"
    ],
    "wof:name":"Plymouth Clock Centre",
    "wof:placetype":"venue"
},
  "geometry": {"coordinates":[-4.134532,50.370827],"type":"Point"}
}