{
  "type": "Feature",
  "properties": {
    "iso:country":"GB",
    "sg:address":"61 Woodstock Rd",
    "sg:city":"Oxford",
    "sg:classifiers":[
        {
            "category":"Retail",
            "subcategory":"Laundry & Dry Cleaning",
            "type":"Services"
        }
    ],
    "sg:phone":"+44 1865 552560",
    "sg:postcode":"OX2 6HJ",
    "sg:province":"Oxfordshire",
    "sg:tags":[
        "cleaner",
        "alteration"
    ],
    "wof:name":"Johnsons The Cleaners",
    "wof:placetype":"venue"
},
  "geometry": {"coordinates":[-1.2634129524,51.7621688843],"type":"Point"}
}