{
  "type": "Feature",
  "properties": {
    "iso:country":"GB",
    "sg:address":"Zetland School, Middle Street Lane",
    "sg:city":"Grangemouth",
    "sg:classifiers":[
        {
            "category":"Building & Trades",
            "subcategory":"Plumbing",
            "type":"Services"
        },
        {
            "category":"Building & Trades",
            "subcategory":"Construction",
            "type":"Services"
        }
    ],
    "sg:phone":"+44 1324 473305",
    "sg:postcode":"FK3 8EH",
    "sg:province":"Falkirk",
    "sg:tags":[
        "joiner",
        "heating",
        "carpenter"
    ],
    "wof:name":"John McIntyre Joinery & Building Ltd.",
    "wof:placetype":"venue"
},
  "geometry": {"coordinates":[-3.723894,56.009331],"type":"Point"}
}