{
  "type": "Feature",
  "properties": {
    "addr:full":"4 Exmouth Road Gillingham Kent ME7 1PF",
    "addr:housenumber":"4",
    "addr:postcode":"me7 1pf",
    "addr:street":"Exmouth Road",
    "iso:country":"GB",
    "sg:address":"4 Exmouth Road",
    "sg:city":"Gillingham",
    "sg:classifiers":[
        {
            "category":"Autos & Motor Vehicles",
            "subcategory":"Automobile Sales",
            "type":"Retail Goods"
        }
    ],
    "sg:phone":"+44 1634 856575",
    "sg:postcode":"ME7 1PF",
    "sg:province":"Kent",
    "sg:tags":[
        "car",
        "used"
    ],
    "wof:name":"P Jennings",
    "wof:placetype":"venue"
},
  "geometry": {"coordinates":[0.547308,51.39436],"type":"Point"}
}