{
  "type": "Feature",
  "properties": {
    "iso:country":"GB",
    "sg:address":"Derwent Rd",
    "sg:city":"Widnes",
    "sg:classifiers":[
        {
            "category":"Organizations",
            "subcategory":"Membership Organization",
            "type":"Services"
        }
    ],
    "sg:postcode":"WA8 8ES",
    "sg:province":"Cheshire",
    "sg:tags":[
        "club"
    ],
    "wof:name":"Ditton Sports & Social Club",
    "wof:placetype":"venue"
},
  "geometry": {"coordinates":[-2.7661299706,53.3695220947],"type":"Point"}
}