{
  "type": "Feature",
  "properties": {
    "iso:country":"GB",
    "sg:address":"Unit 1, 24 Station Road",
    "sg:city":"Hinckley",
    "sg:classifiers":[
        {
            "category":"Shopping",
            "subcategory":"Computers & Home Electronics",
            "type":"Retail Goods"
        }
    ],
    "sg:phone":"+44 1455 233444",
    "sg:postcode":"LE10 1AW",
    "sg:province":"Leicestershire",
    "sg:tags":[
        "equipment",
        "video",
        "cctv"
    ],
    "wof:name":"Sam Bennett",
    "wof:placetype":"venue"
},
  "geometry": {"coordinates":[-1.3730560541,52.5392951965],"type":"Point"}
}