{
  "type": "Feature",
  "properties": {
    "iso:country":"GB",
    "sg:address":"Unit 4 Harewood Terrace, Norwood Grn",
    "sg:city":"Southall",
    "sg:classifiers":[
        {
            "category":"Building & Trades",
            "subcategory":"Construction",
            "type":"Services"
        }
    ],
    "sg:postcode":"UB2 4JL",
    "sg:province":"Greater London",
    "sg:tags":[
        "joiner",
        "carpenter"
    ],
    "wof:name":"Thef Joinery",
    "wof:placetype":"venue"
},
  "geometry": {"coordinates":[-0.374434,51.497509],"type":"Point"}
}