{
  "type": "Feature",
  "properties": {
    "iso:country":"GB",
    "sg:address":"23 Maristow Street",
    "sg:city":"Westbury",
    "sg:classifiers":[
        {
            "category":"Shopping",
            "subcategory":"Shoes",
            "type":"Retail Goods"
        }
    ],
    "sg:postcode":"BA13 3DN",
    "sg:province":"Wiltshire",
    "sg:tags":[
        "shop"
    ],
    "wof:name":"Jevrocke Shoes & Leather",
    "wof:placetype":"venue"
},
  "geometry": {"coordinates":[-2.183392,51.261921],"type":"Point"}
}