{
  "type": "Feature",
  "properties": {
    "addr:full":"2 Dewhurst St Manchester Greater Manchester M8 8FT",
    "addr:housenumber":"2",
    "addr:postcode":"m8 8ft",
    "addr:street":"Dewhurst St",
    "iso:country":"GB",
    "sg:address":"2 Dewhurst St",
    "sg:city":"Manchester",
    "sg:classifiers":[
        {
            "category":"Shopping",
            "subcategory":"Clothing, Apparel, & Fashions",
            "type":"Retail Goods"
        }
    ],
    "sg:phone":"+44 161 832 2829",
    "sg:postcode":"M8 8FT",
    "sg:province":"Greater Manchester",
    "sg:tags":[
        "clothing"
    ],
    "wof:name":"Maliks Ltd",
    "wof:placetype":"venue"
},
  "geometry": {"coordinates":[-2.2491090298,53.4933547974],"type":"Point"}
}