{
  "type": "Feature",
  "properties": {
    "iso:country":"GB",
    "sg:address":"Sovereign Building, 45 Bath La",
    "sg:city":"Newcastle Upon Tyne",
    "sg:classifiers":[
        {
            "category":"Shopping",
            "subcategory":"Pharmacy",
            "type":"Retail Goods"
        }
    ],
    "sg:phone":"+44 191 233 0293",
    "sg:postcode":"NE4 5SP",
    "sg:province":"Tyne and Wear",
    "sg:tags":[
        "toiletry"
    ],
    "wof:name":"Prelude UK Ltd",
    "wof:placetype":"venue"
},
  "geometry": {"coordinates":[-1.6219069958,54.9717407227],"type":"Point"}
}