{
  "type": "Feature",
  "properties": {
    "addr:full":"Polebarn Road Trowbridge Wiltshire BA14 7EG",
    "addr:postcode":"ba14 7eg",
    "addr:street":"Polebarn Road",
    "iso:country":"GB",
    "sg:address":"Polebarn Road",
    "sg:city":"Trowbridge",
    "sg:classifiers":[
        {
            "category":"Building & Trades",
            "subcategory":"Construction",
            "type":"Services"
        }
    ],
    "sg:phone":"+44 1225 763058",
    "sg:postcode":"BA14 7EG",
    "sg:province":"Wiltshire",
    "sg:tags":[
        "joinery"
    ],
    "wof:name":"Magnet",
    "wof:placetype":"venue"
},
  "geometry": {"coordinates":[-2.2028439045,51.3202705383],"type":"Point"}
}