{
  "type": "Feature",
  "properties": {
    "iso:country":"GB",
    "sg:address":"103 Park Lane",
    "sg:city":"Macclesfield",
    "sg:classifiers":[
        {
            "category":"Health Services",
            "subcategory":"Optometrist",
            "type":"Services"
        }
    ],
    "sg:phone":"+44 1625 432777",
    "sg:postcode":"SK11 6UA",
    "sg:province":"Cheshire",
    "sg:tags":[
        "optician"
    ],
    "wof:name":"Barker Bramley Opticians",
    "wof:placetype":"venue"
},
  "geometry": {"coordinates":[-2.126757,53.254459],"type":"Point"}
}