{
  "type": "Feature",
  "properties": {
    "addr:full":"18 Johnson Close Congleton Cheshire CW12 3TQ",
    "addr:housenumber":"18",
    "addr:postcode":"cw12 3tq",
    "addr:street":"Johnson Close",
    "iso:country":"GB",
    "sg:address":"18 Johnson Close",
    "sg:city":"Congleton",
    "sg:classifiers":[
        {
            "category":"Professional",
            "subcategory":"Advertising",
            "type":"Services"
        }
    ],
    "sg:postcode":"CW12 3TQ",
    "sg:province":"Cheshire",
    "wof:name":"Cath Conlan Marketing Services",
    "wof:placetype":"venue"
},
  "geometry": {"coordinates":[-2.188354,53.156437],"type":"Point"}
}