{
  "type": "Feature",
  "properties": {
    "iso:country":"GB",
    "sg:address":"4-8 Borras Road",
    "sg:city":"Wrexham",
    "sg:classifiers":[
        {
            "category":"Fast Food",
            "type":"Food & Drink"
        },
        {
            "category":"Restaurant",
            "type":"Food & Drink"
        }
    ],
    "sg:phone":"+44 1978 313591",
    "sg:postcode":"LL12 7EG",
    "sg:province":"Wrexham",
    "sg:tags":[
        "away",
        "meal",
        "outlet",
        "take"
    ],
    "wof:name":"Fongs Garden",
    "wof:placetype":"venue"
},
  "geometry": {"coordinates":[-2.98018,53.051159],"type":"Point"}
}