{
  "type": "Feature",
  "properties": {
    "iso:country":"GB",
    "sg:address":"Island Square",
    "sg:city":"St Ives",
    "sg:classifiers":[
        {
            "category":"Food & Beverages",
            "subcategory":"Specialty",
            "type":"Retail Goods"
        }
    ],
    "sg:phone":"+44 1736 793621",
    "sg:postcode":"TR26 1NX",
    "sg:province":"Cornwall",
    "sg:tags":[
        "vegetarian"
    ],
    "wof:name":"The Cafe",
    "wof:placetype":"venue"
},
  "geometry": {"coordinates":[-5.477984,50.215855],"type":"Point"}
}