{
  "type": "Feature",
  "properties": {
    "iso:country":"GB",
    "sg:address":"Church Road",
    "sg:city":"Brandon",
    "sg:classifiers":[
        {
            "category":"Organizations",
            "subcategory":"Community Association",
            "type":"Services"
        },
        {
            "category":"Organizations",
            "subcategory":"Membership Organization",
            "type":"Services"
        }
    ],
    "sg:phone":"+44 1842 813177",
    "sg:postcode":"IP27 0JB",
    "sg:province":"Norfolk",
    "sg:tags":[
        "club",
        "social"
    ],
    "wof:name":"Brandon Rememberance Sports & Social Club",
    "wof:placetype":"venue"
},
  "geometry": {"coordinates":[0.615367,52.445061],"type":"Point"}
}