{
  "type": "Feature",
  "properties": {
    "addr:full":"16 High Street Stone Staffordshire ST15 8AW",
    "addr:housenumber":"16",
    "addr:postcode":"st15 8aw",
    "addr:street":"High Street",
    "iso:country":"GB",
    "sg:address":"16 High Street",
    "sg:city":"Stone",
    "sg:classifiers":[
        {
            "category":"Shopping",
            "subcategory":"Pharmacy",
            "type":"Retail Goods"
        }
    ],
    "sg:phone":"+44 1785 812597",
    "sg:postcode":"ST15 8AW",
    "sg:province":"Staffordshire",
    "sg:tags":[
        "pharmacist",
        "chemist"
    ],
    "wof:name":"Birchill & Watson Co. Ltd.",
    "wof:placetype":"venue"
},
  "geometry": {"coordinates":[-2.1462600231,52.9017066956],"type":"Point"}
}