{
  "type": "Feature",
  "properties": {
    "addr:full":"Gostins Building 32-36 Hanover S Liverpool Merseyside L1 4LN",
    "addr:housenumber":"32-36",
    "addr:postcode":"l1 4ln",
    "addr:street":"Hanover S",
    "iso:country":"GB",
    "sg:address":"Gostins Building 32-36 Hanover S",
    "sg:city":"Liverpool",
    "sg:classifiers":[
        {
            "category":"Education",
            "subcategory":"Special Training",
            "type":"Public Place"
        }
    ],
    "sg:phone":"+44 151 707 9955",
    "sg:postcode":"L1 4LN",
    "sg:province":"Merseyside",
    "sg:tags":[
        "product",
        "centre"
    ],
    "wof:name":"Care Training Services Ltd.",
    "wof:placetype":"venue"
},
  "geometry": {"coordinates":[-2.978481,53.409775],"type":"Point"}
}