{
  "type": "Feature",
  "properties": {
    "addr:full":"36 Gravelly Industrial Park, Tyburn Road Birmingham West Midlands B24 8TA",
    "addr:housenumber":"36",
    "addr:postcode":"b24 8ta",
    "addr:street":"Gravelly Industrial Park Tyburn Road",
    "iso:country":"GB",
    "sg:address":"36 Gravelly Industrial Park, Tyburn Road",
    "sg:city":"Birmingham",
    "sg:classifiers":[
        {
            "category":"Professional",
            "subcategory":"Business Services",
            "type":"Services"
        }
    ],
    "sg:phone":"+44 121 326 1234",
    "sg:postcode":"B24 8TA",
    "sg:province":"West Midlands",
    "sg:tags":[
        "distribution"
    ],
    "wof:name":"Siemens V D O Trading Ltd.",
    "wof:placetype":"venue"
},
  "geometry": {"coordinates":[-1.8468639851,52.5089149475],"type":"Point"}
}