{
  "type": "Feature",
  "properties": {
    "addr:full":"Unit A1 Pottington Road Barnstaple Devon EX31 1JH",
    "addr:postcode":"ex31 1jh",
    "addr:street":"Pottington Road",
    "iso:country":"GB",
    "sg:address":"Unit A1 Pottington Road",
    "sg:city":"Barnstaple",
    "sg:classifiers":[
        {
            "category":"Building & Trades",
            "subcategory":"Cleaning & Sanitation",
            "type":"Services"
        }
    ],
    "sg:phone":"+44 1271 374600",
    "sg:postcode":"EX31 1JH",
    "sg:province":"Devon",
    "sg:tags":[
        "dry",
        "control",
        "damp",
        "rot"
    ],
    "wof:name":"D P C Remedial Services",
    "wof:placetype":"venue"
},
  "geometry": {"coordinates":[-4.066740036,51.0831108093],"type":"Point"}
}