{
  "type": "Feature",
  "properties": {
    "addr:full":"70 Sherburn Crescent Scunthorpe Lincolnshire DN15 8BX",
    "addr:housenumber":"70",
    "addr:postcode":"dn15 8bx",
    "addr:street":"Sherburn Crescent",
    "iso:country":"GB",
    "sg:address":"70 Sherburn Crescent",
    "sg:city":"Scunthorpe",
    "sg:classifiers":[
        {
            "category":"Manufacturing",
            "subcategory":"Building Materials",
            "type":"Manufacturing & Wholesale Goods"
        }
    ],
    "sg:postcode":"DN15 8BX",
    "sg:province":"Lincolnshire",
    "sg:tags":[
        "mnfr",
        "maker",
        "cabinet"
    ],
    "wof:name":"Craftsman Cabinets",
    "wof:placetype":"venue"
},
  "geometry": {"coordinates":[-0.6742200255,53.5970840454],"type":"Point"}
}