{
  "type": "Feature",
  "properties": {
    "iso:country":"GB",
    "sg:address":"95 High Street",
    "sg:city":"Stoke-on-trent",
    "sg:classifiers":[
        {
            "category":"Food & Beverages",
            "subcategory":"Candy",
            "type":"Retail Goods"
        }
    ],
    "sg:postcode":"ST8 6AB",
    "sg:province":"Staffordshire",
    "sg:tags":[
        "confectioner"
    ],
    "wof:name":"Kayes",
    "wof:placetype":"venue"
},
  "geometry": {"coordinates":[-2.176167,53.11525],"type":"Point"}
}