{
  "type": "Feature",
  "properties": {
    "addr:full":"Portland House, Mansfield Road Rotherham South Yorkshire S60 2BX",
    "addr:postcode":"s60 2bx",
    "addr:street":"Mansfield Road",
    "iso:country":"GB",
    "sg:address":"Portland House, Mansfield Road",
    "sg:city":"Rotherham",
    "sg:classifiers":[
        {
            "category":"Government",
            "subcategory":"Court House",
            "type":"Public Place"
        }
    ],
    "sg:phone":"+44 1709 364786",
    "sg:postcode":"S60 2BX",
    "sg:province":"South Yorkshire",
    "wof:name":"Rotherham County Court",
    "wof:placetype":"venue"
},
  "geometry": {"coordinates":[-1.353109,53.428455],"type":"Point"}
}