{
  "type": "Feature",
  "properties": {
    "iso:country":"GB",
    "sg:address":"Sandybed Court, Sandybed Lane",
    "sg:city":"Scarborough",
    "sg:classifiers":[
        {
            "category":"Social Services",
            "subcategory":"Adult Care",
            "type":"Services"
        },
        {
            "category":"Government",
            "subcategory":"Office",
            "type":"Public Place"
        }
    ],
    "sg:phone":"+44 1723 360820",
    "sg:postcode":"YO12 5LP",
    "sg:province":"North Yorkshire",
    "sg:tags":[
        "housing",
        "local",
        "sheltered"
    ],
    "wof:name":"Sandybed Court Sheltered Housing",
    "wof:placetype":"venue"
},
  "geometry": {"coordinates":[-0.429439,54.275009],"type":"Point"}
}