{
  "type": "Feature",
  "properties": {
    "addr:full":"P O Box 1606, Hendon London Greater London NW4 2WW",
    "addr:housenumber":"p o;1606",
    "addr:postcode":"nw4 2ww",
    "addr:street":"Hendon",
    "iso:country":"GB",
    "sg:address":"P O Box 1606, Hendon",
    "sg:city":"London",
    "sg:classifiers":[
        {
            "category":"Professional",
            "subcategory":"Accounting & Tax Preparation",
            "type":"Services"
        }
    ],
    "sg:phone":"+44 20 8202 2786",
    "sg:postcode":"NW4 2WW",
    "sg:province":"Greater London",
    "sg:tags":[
        "accountant"
    ],
    "wof:name":"K N Shah & Co",
    "wof:placetype":"venue"
},
  "geometry": {"coordinates":[-0.2178200036,51.5856399536],"type":"Point"}
}