{
  "type": "Feature",
  "properties": {
    "iso:country":"GB",
    "sg:address":"3 Birmingham Road",
    "sg:city":"Kidderminster",
    "sg:classifiers":[
        {
            "category":"Education",
            "subcategory":"Dance Studio",
            "type":"Public Place"
        }
    ],
    "sg:phone":"+44 1562 823058",
    "sg:postcode":"DY10 2BX",
    "sg:province":"Staffordshire",
    "sg:tags":[
        "school",
        "dancing"
    ],
    "wof:name":"Brockway Morris School of Dance",
    "wof:placetype":"venue"
},
  "geometry": {"coordinates":[-2.240087,52.390411],"type":"Point"}
}