{
  "type": "Feature",
  "properties": {
    "iso:country":"GB",
    "sg:address":"60 Sedgley Road West",
    "sg:city":"Tipton",
    "sg:classifiers":[
        {
            "category":"Travel",
            "subcategory":"Hotels & Motels",
            "type":"Entertainment"
        }
    ],
    "sg:postcode":"DY4 8AD",
    "sg:province":"West Midlands",
    "wof:name":"Silverdale Hotel",
    "wof:placetype":"venue"
},
  "geometry": {"coordinates":[-2.081872,52.53043],"type":"Point"}
}