{
  "type": "Feature",
  "properties": {
    "addr:full":"The Old Hall, Sugar Lane, Rainow Macclesfield Cheshire SK10 5UJ",
    "addr:postcode":"sk10 5uj",
    "addr:street":"Sugar Lane",
    "iso:country":"GB",
    "sg:address":"The Old Hall, Sugar Lane, Rainow",
    "sg:city":"Macclesfield",
    "sg:classifiers":[
        {
            "category":"Transit Center",
            "subcategory":"Passenger",
            "type":"Transportation"
        },
        {
            "category":"Retail",
            "subcategory":"Pet Boarding",
            "type":"Services"
        }
    ],
    "sg:phone":"+44 1625 575129",
    "sg:postcode":"SK10 5UJ",
    "sg:province":"Cheshire",
    "sg:tags":[
        "kennel",
        "catteries"
    ],
    "wof:name":"Rainow Cattery",
    "wof:placetype":"venue"
},
  "geometry": {"coordinates":[-2.0747320652,53.2813911438],"type":"Point"}
}