{
  "type": "Feature",
  "properties": {
    "iso:country":"GB",
    "sg:address":"31 Five Oaks Rd",
    "sg:city":"Willenhall",
    "sg:classifiers":[
        {
            "category":"Manufacturing",
            "subcategory":"Signs",
            "type":"Manufacturing & Wholesale Goods"
        }
    ],
    "sg:phone":"+44 1902 566432",
    "sg:postcode":"WV13 3JU",
    "sg:province":"West Midlands",
    "sg:tags":[
        "writer"
    ],
    "wof:name":"Eagle Signs & Glass",
    "wof:placetype":"venue"
},
  "geometry": {"coordinates":[-2.0690639019,52.5769424438],"type":"Point"}
}