{
  "type": "Feature",
  "properties": {
    "addr:full":"113 Rhosmaen St Llandeilo Carmarthenshire SA19 6EN",
    "addr:housenumber":"113",
    "addr:postcode":"sa19 6en",
    "addr:street":"Rhosmaen St",
    "iso:country":"GB",
    "sg:address":"113 Rhosmaen St",
    "sg:city":"Llandeilo",
    "sg:classifiers":[
        {
            "category":"Bars & Pubs",
            "type":"Food & Drink"
        }
    ],
    "sg:phone":"+44 1558 823446",
    "sg:postcode":"SA19 6EN",
    "sg:province":"Carmarthenshire",
    "sg:tags":[
        "pubs",
        "inn"
    ],
    "wof:name":"Castle Hotel",
    "wof:placetype":"venue"
},
  "geometry": {"coordinates":[-3.9922580719,51.8833503723],"type":"Point"}
}