{
  "type": "Feature",
  "properties": {
    "addr:full":"75-77 Gladstone Road Northampton Northamptonshire NN5 7EG",
    "addr:housenumber":"75-77",
    "addr:postcode":"nn5 7eg",
    "addr:street":"Gladstone Road",
    "iso:country":"GB",
    "sg:address":"75-77 Gladstone Road",
    "sg:city":"Northampton",
    "sg:classifiers":[
        {
            "category":"Government",
            "subcategory":"Post Office",
            "type":"Public Place"
        }
    ],
    "sg:postcode":"NN5 7EG",
    "sg:province":"Northamptonshire",
    "wof:name":"Dallington Post Office",
    "wof:placetype":"venue"
},
  "geometry": {"coordinates":[-0.915929,52.25423],"type":"Point"}
}