{
  "type": "Feature",
  "properties": {
    "addr:full":"653 Manchester Road, Denton Manchester Greater Manchester M34 2NS",
    "addr:housenumber":"653",
    "addr:postcode":"m34 2ns",
    "addr:street":"Manchester Road",
    "iso:country":"GB",
    "sg:address":"653 Manchester Road, Denton",
    "sg:city":"Manchester",
    "sg:classifiers":[
        {
            "category":"Building & Trades",
            "subcategory":"Landscaping Services",
            "type":"Services"
        }
    ],
    "sg:postcode":"M34 2NS",
    "sg:province":"Greater Manchester",
    "sg:tags":[
        "pond",
        "aquarium"
    ],
    "wof:name":"Tropical Centre (Manchester)",
    "wof:placetype":"venue"
},
  "geometry": {"coordinates":[-2.149132,53.457397],"type":"Point"}
}