{
  "type": "Feature",
  "properties": {
    "addr:full":", Skene Westhill Aberdeen City AB32 6YJ",
    "addr:postcode":"ab32 6yj",
    "iso:country":"GB",
    "sg:address":", Skene",
    "sg:city":"Westhill",
    "sg:classifiers":[
        {
            "category":"Education",
            "subcategory":"School",
            "type":"Public Place"
        }
    ],
    "sg:phone":"+44 1224 743242",
    "sg:postcode":"AB32 6YJ",
    "sg:province":"Aberdeen City",
    "sg:tags":[
        "local",
        "authority"
    ],
    "wof:name":"Skene Primary School",
    "wof:placetype":"venue"
},
  "geometry": {"coordinates":[-2.2926840782,57.1494445801],"type":"Point"}
}