{
  "type": "Feature",
  "properties": {
    "iso:country":"GB",
    "sg:address":"16c Sandown Road, Lake",
    "sg:city":"Sandown",
    "sg:classifiers":[
        {
            "category":"Professional",
            "subcategory":"Accounting & Tax Preparation",
            "type":"Services"
        }
    ],
    "sg:postcode":"PO36 9JP",
    "sg:province":"Isle of Wight",
    "sg:tags":[
        "accountant"
    ],
    "wof:name":"Allegri & Co.",
    "wof:placetype":"venue"
},
  "geometry": {"coordinates":[-1.1680239439,50.6486206055],"type":"Point"}
}