{
  "type": "Feature",
  "properties": {
    "addr:full":"Yennards Farm Croft Road, Thurlaston Leicester Leicestershire LE9 7TB",
    "addr:postcode":"le9 7tb",
    "addr:street":"Croft Road",
    "iso:country":"GB",
    "sg:address":"Yennards Farm Croft Road, Thurlaston",
    "sg:city":"Leicester",
    "sg:classifiers":[
        {
            "category":"Farming",
            "subcategory":"Farm",
            "type":"Manufacturing & Wholesale Goods"
        }
    ],
    "sg:phone":"+44 1455 888481",
    "sg:postcode":"LE9 7TB",
    "sg:province":"Leicestershire",
    "sg:tags":[
        "mixed",
        "crop"
    ],
    "wof:name":"R A Jelley (Farms)",
    "wof:placetype":"venue"
},
  "geometry": {"coordinates":[-1.2591439486,52.5871009827],"type":"Point"}
}