{
  "type": "Feature",
  "properties": {
    "addr:full":"27 Mount Pleasant, Saltney Chester Cheshire CH4 8BN",
    "addr:housenumber":"27",
    "addr:postcode":"ch4 8bn",
    "addr:street":"Mount Pleasant",
    "iso:country":"GB",
    "sg:address":"27 Mount Pleasant, Saltney",
    "sg:city":"Chester",
    "sg:classifiers":[
        {
            "category":"Home & Garden",
            "subcategory":"Home Furnishings",
            "type":"Retail Goods"
        },
        {
            "category":"Home & Garden",
            "subcategory":"Building Materials",
            "type":"Retail Goods"
        }
    ],
    "sg:phone":"+44 1244 683380",
    "sg:postcode":"CH4 8BN",
    "sg:province":"Cheshire",
    "sg:tags":[
        "installers",
        "planner",
        "kitchen",
        "furnishers"
    ],
    "wof:name":"Maplewood Kitchens & Bedrooms",
    "wof:placetype":"venue"
},
  "geometry": {"coordinates":[-2.9140410423,53.1812820435],"type":"Point"}
}