{
  "type": "Feature",
  "properties": {
    "iso:country":"GB",
    "sg:address":"20 High Street",
    "sg:city":"Devizes",
    "sg:classifiers":[
        {
            "category":"Shopping",
            "subcategory":"Antiques",
            "type":"Retail Goods"
        }
    ],
    "sg:postcode":"SN10 1AT",
    "sg:province":"Wiltshire",
    "wof:name":"Julia Bullen Antiques & Secondhand",
    "wof:placetype":"venue"
},
  "geometry": {"coordinates":[-1.994576,51.351959],"type":"Point"}
}