{
  "type": "Feature",
  "properties": {
    "iso:country":"GB",
    "sg:address":"54 South Bank Avenue",
    "sg:city":"York",
    "sg:classifiers":[
        {
            "category":"Personal",
            "subcategory":"Beauty Salon",
            "type":"Services"
        },
        {
            "category":"Personal",
            "subcategory":"Barber",
            "type":"Services"
        }
    ],
    "sg:phone":"+44 1904 656427",
    "sg:postcode":"YO23 1EA",
    "sg:province":"North Yorkshire",
    "sg:tags":[
        "unisex",
        "hairdresser"
    ],
    "wof:name":"Brians Hair Fashions",
    "wof:placetype":"venue"
},
  "geometry": {"coordinates":[-1.088669,53.946411],"type":"Point"}
}