{
  "type": "Feature",
  "properties": {
    "addr:full":"4 Main Street, Fauldhouse Bathgate North Lanarkshire EH47 9JA",
    "addr:housenumber":"4",
    "addr:postcode":"eh47 9ja",
    "addr:street":"Main Street;Bathgate",
    "iso:country":"GB",
    "sg:address":"4 Main Street, Fauldhouse",
    "sg:city":"Bathgate",
    "sg:classifiers":[
        {
            "category":"Restaurant",
            "type":"Food & Drink"
        }
    ],
    "sg:phone":"+44 1501 770166",
    "sg:postcode":"EH47 9JA",
    "sg:province":"North Lanarkshire",
    "sg:tags":[
        "-",
        "chinese"
    ],
    "wof:name":"Ocean City",
    "wof:placetype":"venue"
},
  "geometry": {"coordinates":[-3.7066500187,55.828037262],"type":"Point"}
}