{
  "type": "Feature",
  "properties": {
    "iso:country":"GB",
    "sg:address":"Tyn Y Pwll, Llanllyfni",
    "sg:city":"Caernarfon",
    "sg:classifiers":[
        {
            "category":"Travel",
            "subcategory":"Hotels & Motels",
            "type":"Entertainment"
        },
        {
            "category":"Recreation",
            "subcategory":"Campground",
            "type":"Entertainment"
        }
    ],
    "sg:postcode":"LL54 6RP",
    "sg:province":"Gwynedd",
    "sg:tags":[
        "house",
        "camp",
        "holiday",
        "guest",
        "centre"
    ],
    "wof:name":"Ozanam Centre (North Wales) Ltd.",
    "wof:placetype":"venue"
},
  "geometry": {"coordinates":[-4.283814,53.041245],"type":"Point"}
}