{
  "type": "Feature",
  "properties": {
    "addr:full":"8 Victoria Road Shipley West Yorkshire BD18 3LA",
    "addr:housenumber":"8",
    "addr:postcode":"bd18 3la",
    "addr:street":"Victoria Road",
    "iso:country":"GB",
    "sg:address":"8 Victoria Road",
    "sg:city":"Shipley",
    "sg:classifiers":[
        {
            "category":"Cafe",
            "type":"Food & Drink"
        }
    ],
    "sg:phone":"+44 1274 823092",
    "sg:postcode":"BD18 3LA",
    "sg:province":"West Yorkshire",
    "sg:tags":[
        "tea",
        "snack",
        "bar",
        "room"
    ],
    "wof:name":"Victoria Tea Rooms",
    "wof:placetype":"venue"
},
  "geometry": {"coordinates":[-1.7899659872,53.8378753662],"type":"Point"}
}