{
  "type": "Feature",
  "properties": {
    "iso:country":"GB",
    "sg:address":"129 Hughenden Avenue",
    "sg:city":"High Wycombe",
    "sg:classifiers":[
        {
            "category":"Taxi",
            "type":"Transportation"
        }
    ],
    "sg:phone":"+44 1494 463344",
    "sg:postcode":"HP13 5SS",
    "sg:province":"Buckinghamshire",
    "sg:tags":[
        "mini",
        "cab"
    ],
    "wof:name":"A S Bhllaon",
    "wof:placetype":"venue"
},
  "geometry": {"coordinates":[-0.762225,51.63781],"type":"Point"}
}