{
  "type": "Feature",
  "properties": {
    "addr:full":"15 Percy St West End Greater London W1T 1EE",
    "addr:housenumber":"15",
    "addr:postcode":"w1t 1ee",
    "addr:street":"Percy St",
    "iso:country":"GB",
    "sg:address":"15 Percy St",
    "sg:city":"West End",
    "sg:classifiers":[
        {
            "category":"Communications",
            "subcategory":"Television Station",
            "type":"Services"
        }
    ],
    "sg:phone":"+44 20 7291 0890",
    "sg:postcode":"W1T 1EE",
    "sg:province":"Greater London",
    "sg:tags":[
        "audio-visual"
    ],
    "wof:name":"Protape",
    "wof:placetype":"venue"
},
  "geometry": {"coordinates":[-0.13291,51.518471],"type":"Point"}
}