{
  "type": "Feature",
  "properties": {
    "iso:country":"GB",
    "sg:address":"Armond Carr Farm, Tow Law",
    "sg:city":"Bishop Auckland",
    "sg:classifiers":[
        {
            "category":"Farming",
            "subcategory":"Livestock Farm",
            "type":"Manufacturing & Wholesale Goods"
        }
    ],
    "sg:phone":"+44 1388 730205",
    "sg:postcode":"DL13 4HH",
    "sg:province":"Durham",
    "sg:tags":[
        "others"
    ],
    "wof:name":"R & J Crammond",
    "wof:placetype":"venue"
},
  "geometry": {"coordinates":[-1.815234,54.747856],"type":"Point"}
}