{
  "type": "Feature",
  "properties": {
    "addr:full":"7 Elm Lane Sheffield South Yorkshire S5 7TR",
    "addr:housenumber":"7",
    "addr:postcode":"s5 7tr",
    "addr:street":"Elm Lane",
    "iso:country":"GB",
    "sg:address":"7 Elm Lane",
    "sg:city":"Sheffield",
    "sg:classifiers":[
        {
            "category":"Food & Beverages",
            "subcategory":"Meat & Fish",
            "type":"Retail Goods"
        }
    ],
    "sg:phone":"+44 114 245 6131",
    "sg:postcode":"S5 7TR",
    "sg:province":"South Yorkshire",
    "sg:tags":[
        "chip"
    ],
    "wof:name":"Elm Lane Fish & Chips",
    "wof:placetype":"venue"
},
  "geometry": {"coordinates":[-1.4553689957,53.4219055176],"type":"Point"}
}