{
  "type": "Feature",
  "properties": {
    "iso:country":"GB",
    "sg:address":"4 Barn Croft",
    "sg:city":"Preston",
    "sg:classifiers":[
        {
            "category":"Food & Beverages",
            "subcategory":"Specialty",
            "type":"Retail Goods"
        },
        {
            "category":"Health Services",
            "subcategory":"Nursing And Care Facility",
            "type":"Services"
        }
    ],
    "sg:postcode":"PR26 7UD",
    "sg:province":"Lancashire",
    "sg:tags":[
        "residential",
        "homogenised",
        "dietetic"
    ],
    "wof:name":"Zenith Healthcare",
    "wof:placetype":"venue"
},
  "geometry": {"coordinates":[-2.7322580814,53.7458724976],"type":"Point"}
}