{
  "type": "Feature",
  "properties": {
    "iso:country":"GB",
    "sg:address":"55 Tanners Lane",
    "sg:city":"Coventry",
    "sg:classifiers":[
        {
            "category":"Autos & Motor Vehicles",
            "subcategory":"Automobile Sales",
            "type":"Retail Goods"
        }
    ],
    "sg:postcode":"CV4 9HX",
    "sg:province":"Warwickshire",
    "sg:tags":[
        "car"
    ],
    "wof:name":"The Garage At Tanner Lane",
    "wof:placetype":"venue"
},
  "geometry": {"coordinates":[-1.5995420218,52.4007339478],"type":"Point"}
}