{
  "type": "Feature",
  "properties": {
    "iso:country":"GB",
    "sg:address":"35 Montpelier Road",
    "sg:city":"Brighton",
    "sg:classifiers":[
        {
            "category":"Cafe",
            "type":"Food & Drink"
        }
    ],
    "sg:postcode":"BN1 3BA",
    "sg:province":"East Sussex",
    "sg:tags":[
        "tea",
        "room"
    ],
    "wof:name":"Esprit",
    "wof:placetype":"venue"
},
  "geometry": {"coordinates":[-0.152903,50.825092],"type":"Point"}
}