{
  "type": "Feature",
  "properties": {
    "iso:country":"GB",
    "sg:address":"7 Market Place",
    "sg:city":"Poulton-le-fylde",
    "sg:classifiers":[
        {
            "category":"Travel",
            "subcategory":"Travel Agent",
            "type":"Entertainment"
        }
    ],
    "sg:phone":"+44 1253 892255",
    "sg:postcode":"FY6 7BQ",
    "sg:province":"Lancashire",
    "wof:name":"Destinations",
    "wof:placetype":"venue"
},
  "geometry": {"coordinates":[-2.9927918911,53.8468284607],"type":"Point"}
}