{
  "type": "Feature",
  "properties": {
    "addr:full":"Unit 8, Boundoak,, Eversley Rd, Arborfield, Reading Berkshire RG2 9PN",
    "addr:housenumber":"unit 8",
    "addr:postcode":"rg2 9pn",
    "addr:street":"Boundoak Eversley Rd",
    "iso:country":"GB",
    "sg:address":"Unit 8, Boundoak,, Eversley Rd, Arborfield,",
    "sg:city":"Reading",
    "sg:classifiers":[
        {
            "category":"Building & Trades",
            "subcategory":"Construction",
            "type":"Services"
        }
    ],
    "sg:postcode":"RG2 9PN",
    "sg:province":"Berkshire",
    "sg:tags":[
        "builder"
    ],
    "wof:name":"P T K Exhibitions & Support Services",
    "wof:placetype":"venue"
},
  "geometry": {"coordinates":[-0.920774,51.401566],"type":"Point"}
}