{
  "type": "Feature",
  "properties": {
    "iso:country":"GB",
    "sg:address":"50 Cotton St",
    "sg:city":"Aberdeen",
    "sg:classifiers":[
        {
            "category":"Wholesale",
            "subcategory":"Machinery & Supplies",
            "type":"Manufacturing & Wholesale Goods"
        }
    ],
    "sg:phone":"+44 1224 212366",
    "sg:postcode":"AB11 5EE",
    "sg:province":"Aberdeen City",
    "sg:tags":[
        "industrial",
        "commercial"
    ],
    "wof:name":"Hurstwell Roberts",
    "wof:placetype":"venue"
},
  "geometry": {"coordinates":[-2.0829229355,57.1510620117],"type":"Point"}
}