{
  "type": "Feature",
  "properties": {
    "addr:full":"Manfield Way St Austell Cornwall PL25 3HQ",
    "addr:postcode":"pl25 3hq",
    "addr:street":"Manfield Way",
    "iso:country":"GB",
    "sg:address":"Manfield Way",
    "sg:city":"St Austell",
    "sg:classifiers":[
        {
            "category":"Manufacturing",
            "subcategory":"Tools & Machinery",
            "type":"Manufacturing & Wholesale Goods"
        },
        {
            "category":"Home & Garden",
            "subcategory":"Hardware",
            "type":"Retail Goods"
        }
    ],
    "sg:phone":"+44 1726 69047",
    "sg:postcode":"PL25 3HQ",
    "sg:province":"Cornwall",
    "sg:tags":[
        "manufacture",
        "supply",
        "fixing",
        "powertools",
        "fastener",
        "device"
    ],
    "wof:name":"Kernow Fixings",
    "wof:placetype":"venue"
},
  "geometry": {"coordinates":[-4.755317,50.342106],"type":"Point"}
}