{
  "type": "Feature",
  "properties": {
    "addr:full":"11 Avenue Parade Accrington Lancashire BB5 6PN",
    "addr:housenumber":"11",
    "addr:postcode":"bb5 6pn",
    "addr:street":"Avenue Parade",
    "iso:country":"GB",
    "sg:address":"11 Avenue Parade",
    "sg:city":"Accrington",
    "sg:classifiers":[
        {
            "category":"Health Services",
            "subcategory":"Health Practitioner",
            "type":"Services"
        }
    ],
    "sg:phone":"+44 1254 872442",
    "sg:postcode":"BB5 6PN",
    "sg:province":"Lancashire",
    "sg:tags":[
        "hypnotherapists"
    ],
    "wof:name":"David Masters",
    "wof:placetype":"venue"
},
  "geometry": {"coordinates":[-2.3620700836,53.7541732788],"type":"Point"}
}