{
  "type": "Feature",
  "properties": {
    "iso:country":"GB",
    "sg:address":"8 Gold Street",
    "sg:city":"Tiverton",
    "sg:classifiers":[
        {
            "category":"Shopping",
            "subcategory":"Florist",
            "type":"Retail Goods"
        }
    ],
    "sg:phone":"+44 1884 252251",
    "sg:postcode":"EX16 6PZ",
    "sg:province":"Devon",
    "wof:name":"Mayflower",
    "wof:placetype":"venue"
},
  "geometry": {"coordinates":[-3.485868,50.903217],"type":"Point"}
}