{
  "type": "Feature",
  "properties": {
    "iso:country":"GB",
    "sg:address":"Olympia House, Thames Street",
    "sg:city":"Leicester",
    "sg:classifiers":[
        {
            "category":"Shopping",
            "subcategory":"Crafts & Fabrics",
            "type":"Retail Goods"
        }
    ],
    "sg:postcode":"LE1 3WN",
    "sg:province":"Leicestershire",
    "sg:tags":[
        "knitwear",
        "yarn"
    ],
    "wof:name":"Olympia Knitwear (Leicester) Ltd.",
    "wof:placetype":"venue"
},
  "geometry": {"coordinates":[-1.132064,52.641651],"type":"Point"}
}