{
  "type": "Feature",
  "properties": {
    "addr:full":"1901 Fore Street, Topsham Exeter Devon EX3 0HE",
    "addr:housenumber":"1901",
    "addr:postcode":"ex3 0he",
    "addr:street":"Fore Street",
    "iso:country":"GB",
    "sg:address":"1901 Fore Street, Topsham",
    "sg:city":"Exeter",
    "sg:classifiers":[
        {
            "category":"Health Services",
            "subcategory":"Doctor",
            "type":"Services"
        },
        {
            "category":"Health Services",
            "subcategory":"Clinic",
            "type":"Services"
        }
    ],
    "sg:phone":"+44 1392 875777",
    "sg:postcode":"EX3 0HE",
    "sg:province":"Devon",
    "sg:tags":[
        "nh",
        "practitioners"
    ],
    "wof:name":"Chapel Platt Surgery",
    "wof:placetype":"venue"
},
  "geometry": {"coordinates":[-3.4667890072,50.6849403381],"type":"Point"}
}