{
  "type": "Feature",
  "properties": {
    "iso:country":"GB",
    "sg:address":"162 Wandsworth Bridge Road",
    "sg:city":"London",
    "sg:classifiers":[
        {
            "category":"Government",
            "subcategory":"Fire Station",
            "type":"Public Place"
        }
    ],
    "sg:phone":"+44 20 7384 1485",
    "sg:postcode":"SW6 2UQ",
    "sg:province":"Greater London",
    "sg:tags":[
        "w'sale",
        "lighting"
    ],
    "wof:name":"Tindle",
    "wof:placetype":"venue"
},
  "geometry": {"coordinates":[-0.1914239973,51.4712715149],"type":"Point"}
}