{
  "type": "Feature",
  "properties": {
    "addr:full":"Brickfields Depot West Malling Kent ME19 5AG",
    "addr:postcode":"me19 5ag",
    "addr:street":"West",
    "iso:country":"GB",
    "sg:address":"Brickfields Depot",
    "sg:city":"West Malling",
    "sg:classifiers":[
        {
            "category":"Professional",
            "subcategory":"Engineering",
            "type":"Services"
        }
    ],
    "sg:phone":"+44 1732 522277",
    "sg:postcode":"ME19 5AG",
    "sg:province":"Kent",
    "sg:tags":[
        "civil",
        "engineer"
    ],
    "wof:name":"Bearsted Civil Engineers Ltd.",
    "wof:placetype":"venue"
},
  "geometry": {"coordinates":[0.4046199918,51.3005752563],"type":"Point"}
}