{
  "type": "Feature",
  "properties": {
    "addr:full":"C/o Lofthouse & Co, 29 Ropergate Pontefract North Yorkshire WF8 1LG",
    "addr:housenumber":"29",
    "addr:postcode":"wf8 1lg",
    "addr:street":"C / O;Ropergate Pontefract",
    "iso:country":"GB",
    "sg:address":"C/o Lofthouse & Co, 29 Ropergate",
    "sg:city":"Pontefract",
    "sg:classifiers":[
        {
            "category":"Manufacturing",
            "subcategory":"Electronics",
            "type":"Manufacturing & Wholesale Goods"
        }
    ],
    "sg:postcode":"WF8 1LG",
    "sg:province":"North Yorkshire",
    "sg:tags":[
        "mnfrs",
        "transformer"
    ],
    "wof:name":"Universal Transformers Ltd",
    "wof:placetype":"venue"
},
  "geometry": {"coordinates":[-1.3129700422,53.6900596619],"type":"Point"}
}