{
  "type": "Feature",
  "properties": {
    "addr:full":"2 Beatrice Street Oswestry Shropshire SY11 1QG",
    "addr:housenumber":"2",
    "addr:postcode":"sy11 1qg",
    "addr:street":"Beatrice Street",
    "iso:country":"GB",
    "sg:address":"2 Beatrice Street",
    "sg:city":"Oswestry",
    "sg:classifiers":[
        {
            "category":"Fast Food",
            "type":"Food & Drink"
        }
    ],
    "sg:phone":"+44 1691 662694",
    "sg:postcode":"SY11 1QG",
    "sg:province":"Shropshire",
    "sg:tags":[
        "away",
        "take"
    ],
    "wof:name":"Kwang Tung House",
    "wof:placetype":"venue"
},
  "geometry": {"coordinates":[-3.0537569523,52.8604812622],"type":"Point"}
}