{
  "type": "Feature",
  "properties": {
    "iso:country":"GB",
    "sg:address":"30 St Marys Street, Eynesbury, St Neots",
    "sg:city":"Huntingdon",
    "sg:classifiers":[
        {
            "category":"Professional",
            "subcategory":"Art Services",
            "type":"Services"
        }
    ],
    "sg:postcode":"PE19 2TA",
    "sg:province":"Bedfordshire",
    "sg:tags":[
        "photographer"
    ],
    "wof:name":"Alexandra Studio",
    "wof:placetype":"venue"
},
  "geometry": {"coordinates":[-0.2682110071,52.2251091003],"type":"Point"}
}