{
  "type": "Feature",
  "properties": {
    "iso:country":"GB",
    "sg:address":"Marlborough Road",
    "sg:city":"Nuneaton",
    "sg:classifiers":[
        {
            "category":"Health Services",
            "subcategory":"Doctor",
            "type":"Services"
        },
        {
            "category":"Health Services",
            "subcategory":"Clinic",
            "type":"Services"
        }
    ],
    "sg:phone":"+44 24 7638 2554",
    "sg:postcode":"CV11 5PG",
    "sg:province":"Leicestershire",
    "sg:tags":[
        "nh",
        "practitioners"
    ],
    "wof:name":"Old Mill Surgery",
    "wof:placetype":"venue"
},
  "geometry": {"coordinates":[-1.474699,52.519001],"type":"Point"}
}