{
  "type": "Feature",
  "properties": {
    "addr:full":"8-9 Castle View, Humberstone Leicester Leicestershire LE1 5WH",
    "addr:housenumber":"8-9",
    "addr:postcode":"le1 5wh",
    "addr:street":"Castle View",
    "iso:country":"GB",
    "sg:address":"8-9 Castle View, Humberstone",
    "sg:city":"Leicester",
    "sg:classifiers":[
        {
            "category":"Government",
            "subcategory":"Post Office",
            "type":"Public Place"
        }
    ],
    "sg:postcode":"LE1 5WH",
    "sg:province":"Leicestershire",
    "sg:tags":[
        "messenger",
        "courier"
    ],
    "wof:name":"A D Y Express Transport (Express Couriers)",
    "wof:placetype":"venue"
},
  "geometry": {"coordinates":[-1.1400820017,52.631778717],"type":"Point"}
}