{
  "type": "Feature",
  "properties": {
    "iso:country":"GB",
    "sg:address":"Bosham Lane, Bosham",
    "sg:city":"Chichester",
    "sg:classifiers":[
        {
            "category":"Retail",
            "subcategory":"Auto Repair",
            "type":"Services"
        }
    ],
    "sg:postcode":"PO18 8HG",
    "sg:province":"West Sussex",
    "sg:tags":[
        "modification",
        "garage"
    ],
    "wof:name":"Bosham Service Station Ltd.",
    "wof:placetype":"venue"
},
  "geometry": {"coordinates":[-0.851004,50.836319],"type":"Point"}
}