{
  "type": "Feature",
  "properties": {
    "addr:full":"Braywick Road Maidenhead Berkshire SL6 1BN",
    "addr:postcode":"sl6 1bn",
    "addr:street":"Braywick Road",
    "iso:country":"GB",
    "sg:address":"Braywick Road",
    "sg:city":"Maidenhead",
    "sg:classifiers":[
        {
            "category":"Sports & Exercise",
            "subcategory":"Golf",
            "type":"Entertainment"
        }
    ],
    "sg:phone":"+44 1628 676910",
    "sg:postcode":"SL6 1BN",
    "sg:province":"Berkshire",
    "sg:tags":[
        "range",
        "driving"
    ],
    "wof:name":"Braywick Golf Park",
    "wof:placetype":"venue"
},
  "geometry": {"coordinates":[-0.719394,51.514809],"type":"Point"}
}