{
  "type": "Feature",
  "properties": {
    "iso:country":"GB",
    "sg:address":"119 St. Johns Rd",
    "sg:city":"Liverpool",
    "sg:classifiers":[
        {
            "category":"Food & Beverages",
            "subcategory":"Liquor & Beverages",
            "type":"Retail Goods"
        }
    ],
    "sg:postcode":"L22 9QE",
    "sg:province":"Merseyside",
    "sg:tags":[
        "beer",
        "spirit",
        "wines"
    ],
    "wof:name":"Brett,Simon,",
    "wof:placetype":"venue"
},
  "geometry": {"coordinates":[-3.0256390572,53.4790229797],"type":"Point"}
}