{
  "type": "Feature",
  "properties": {
    "addr:full":"9-11 Orwell Rd Felixstowe Suffolk IP11 7HE",
    "addr:housenumber":"9-11",
    "addr:postcode":"ip11 7he",
    "addr:street":"Orwell Rd",
    "iso:country":"GB",
    "sg:address":"9-11 Orwell Rd",
    "sg:city":"Felixstowe",
    "sg:classifiers":[
        {
            "category":"Food & Beverages",
            "subcategory":"Meat & Fish",
            "type":"Retail Goods"
        }
    ],
    "sg:phone":"+44 1394 282540",
    "sg:postcode":"IP11 7HE",
    "sg:province":"Suffolk",
    "sg:tags":[
        "chip"
    ],
    "wof:name":"D K & B Muddock",
    "wof:placetype":"venue"
},
  "geometry": {"coordinates":[1.352352,51.961582],"type":"Point"}
}