{
  "type": "Feature",
  "properties": {
    "iso:country":"GB",
    "sg:address":"15 Church End, Rampton",
    "sg:city":"Cambridge",
    "sg:classifiers":[
        {
            "category":"Social Services",
            "subcategory":"Retirement Home",
            "type":"Services"
        }
    ],
    "sg:phone":"+44 1954 250773",
    "sg:postcode":"CB4 8QA",
    "sg:province":"Cambridgeshire",
    "sg:tags":[
        "rest"
    ],
    "wof:name":"Old Rectory",
    "wof:placetype":"venue"
},
  "geometry": {"coordinates":[0.094072,52.291477],"type":"Point"}
}