{
  "type": "Feature",
  "properties": {
    "addr:full":"New Road Garage, A38, Weare Axbridge Somerset BS26 2JE",
    "addr:housenumber":"axbridge",
    "addr:postcode":"bs26 2je",
    "addr:street":"Somerset",
    "iso:country":"GB",
    "sg:address":"New Road Garage, A38, Weare",
    "sg:city":"Axbridge",
    "sg:classifiers":[
        {
            "category":"Home & Garden",
            "subcategory":"Household Appliances",
            "type":"Retail Goods"
        }
    ],
    "sg:postcode":"BS26 2JE",
    "sg:province":"Somerset",
    "sg:tags":[
        "refrigeration",
        "air conditioning"
    ],
    "wof:name":"S W Motors",
    "wof:placetype":"venue"
},
  "geometry": {"coordinates":[-2.818409,51.288391],"type":"Point"}
}