{
  "type": "Feature",
  "properties": {
    "addr:full":"Whittlees, Gilsland Brampton Cumbria CA8 7EL",
    "addr:postcode":"ca8 7el",
    "addr:street":"Gilsland",
    "iso:country":"GB",
    "sg:address":"Whittlees, Gilsland",
    "sg:city":"Brampton",
    "sg:classifiers":[
        {
            "category":"Military Area",
            "subcategory":"Army Base",
            "type":"Public Place"
        }
    ],
    "sg:postcode":"CA8 7EL",
    "sg:province":"Cumbria",
    "sg:tags":[
        "transportation",
        "livestock"
    ],
    "wof:name":"R R & K Kennedy Haulage Contractors",
    "wof:placetype":"venue"
},
  "geometry": {"coordinates":[-2.571846,54.991322],"type":"Point"}
}