{
  "type": "Feature",
  "properties": {
    "addr:full":"36 Lower Addiscombe Road Croydon Surrey CR0 6AA",
    "addr:housenumber":"36",
    "addr:postcode":"cr0 6aa",
    "addr:street":"Lower Addiscombe Road",
    "iso:country":"GB",
    "sg:address":"36 Lower Addiscombe Road",
    "sg:city":"Croydon",
    "sg:classifiers":[
        {
            "category":"Professional",
            "subcategory":"Accounting & Tax Preparation",
            "type":"Services"
        }
    ],
    "sg:phone":"+44 20 8680 4723",
    "sg:postcode":"CR0 6AA",
    "sg:province":"Surrey",
    "sg:tags":[
        "accountant"
    ],
    "wof:name":"Perera and Co",
    "wof:placetype":"venue"
},
  "geometry": {"coordinates":[-0.088257,51.380508],"type":"Point"}
}