{
  "type": "Feature",
  "properties": {
    "iso:country":"GB",
    "sg:address":"Lodge Hill Farm, Lodge Hill, Chapmanslade",
    "sg:city":"Westbury",
    "sg:classifiers":[
        {
            "category":"Professional",
            "subcategory":"Engineering",
            "type":"Services"
        }
    ],
    "sg:phone":"+44 1373 832259",
    "sg:postcode":"BA13 4AR",
    "sg:province":"Wiltshire",
    "wof:name":"Lodge Hill Farm Services",
    "wof:placetype":"venue"
},
  "geometry": {"coordinates":[-2.2754209042,51.23412323],"type":"Point"}
}