{
  "type": "Feature",
  "properties": {
    "addr:full":"45 Beauchamp Place London Greater London SW3 1NX",
    "addr:housenumber":"45",
    "addr:postcode":"sw3 1nx",
    "addr:street":"Beauchamp Place",
    "iso:country":"GB",
    "sg:address":"45 Beauchamp Place",
    "sg:city":"London",
    "sg:classifiers":[
        {
            "category":"Shopping",
            "subcategory":"Comic Books",
            "type":"Retail Goods"
        }
    ],
    "sg:phone":"+44 20 7589 0552",
    "sg:postcode":"SW3 1NX",
    "sg:province":"Greater London",
    "sg:tags":[
        "jeweller"
    ],
    "wof:name":"Follie-Follie",
    "wof:placetype":"venue"
},
  "geometry": {"coordinates":[-0.1648869962,51.4974708557],"type":"Point"}
}