{
  "type": "Feature",
  "properties": {
    "addr:full":"51a The Rise, Beaufort Ebbw Vale Blaenau Gwent NP23 5JG",
    "addr:housenumber":"51a",
    "addr:postcode":"ebbw;np23 5jg",
    "addr:street":"The Rise",
    "iso:country":"GB",
    "sg:address":"51a The Rise, Beaufort",
    "sg:city":"Ebbw Vale",
    "sg:classifiers":[
        {
            "category":"Social Services",
            "subcategory":"Adult Care",
            "type":"Services"
        }
    ],
    "sg:phone":"+44 1495 308954",
    "sg:postcode":"NP23 5JG",
    "sg:province":"Blaenau Gwent",
    "sg:tags":[
        "domestic",
        "cleaning"
    ],
    "wof:name":"Industrial Cleaning Services",
    "wof:placetype":"venue"
},
  "geometry": {"coordinates":[-3.2146859169,51.7970275879],"type":"Point"}
}