{
  "type": "Feature",
  "properties": {
    "addr:full":"108 Litchfield Street Walsall West Midlands WS1 1TQ",
    "addr:housenumber":"108",
    "addr:postcode":"ws1 1tq",
    "addr:street":"Litchfield Street",
    "iso:country":"GB",
    "sg:address":"108 Litchfield Street",
    "sg:city":"Walsall",
    "sg:classifiers":[
        {
            "category":"Shopping",
            "subcategory":"Clothing, Apparel, & Fashions",
            "type":"Retail Goods"
        }
    ],
    "sg:phone":"+44 1922 622998",
    "sg:postcode":"WS1 1TQ",
    "sg:province":"West Midlands",
    "sg:tags":[
        "shop"
    ],
    "wof:name":"Rowleys of Walsall",
    "wof:placetype":"venue"
},
  "geometry": {"coordinates":[-1.976104,52.585289],"type":"Point"}
}