{
  "type": "Feature",
  "properties": {
    "addr:full":"26a Outram Street Sutton In Ashfield Nottinghamshire NG17 4FS",
    "addr:housenumber":"26a",
    "addr:postcode":"ng17 4fs",
    "addr:street":"Outram Street",
    "iso:country":"GB",
    "sg:address":"26a Outram Street",
    "sg:city":"Sutton In Ashfield",
    "sg:classifiers":[
        {
            "category":"Professional",
            "subcategory":"Business Services",
            "type":"Services"
        }
    ],
    "sg:phone":"+44 1623 443458",
    "sg:postcode":"NG17 4FS",
    "sg:province":"Nottinghamshire",
    "sg:tags":[
        "import",
        "export",
        "agent"
    ],
    "wof:name":"Reece Lindsay",
    "wof:placetype":"venue"
},
  "geometry": {"coordinates":[-1.257579,53.127449],"type":"Point"}
}