{
  "type": "Feature",
  "properties": {
    "iso:country":"GB",
    "sg:address":"Queen Anne House, 66 Cricklade St",
    "sg:city":"Cirencester",
    "sg:classifiers":[
        {
            "category":"Professional",
            "subcategory":"Accounting & Tax Preparation",
            "type":"Services"
        }
    ],
    "sg:phone":"+44 1285 642001",
    "sg:postcode":"GL7 1JN",
    "sg:province":"Gloucestershire",
    "sg:tags":[
        "accountant"
    ],
    "wof:name":"Swift & Cansdale",
    "wof:placetype":"venue"
},
  "geometry": {"coordinates":[-1.967027,51.71463],"type":"Point"}
}