{
  "type": "Feature",
  "properties": {
    "iso:country":"GB",
    "sg:address":"11 Hillcrest Road",
    "sg:city":"Bideford",
    "sg:classifiers":[
        {
            "category":"Shopping",
            "subcategory":"Hobbies, Toys, & Games",
            "type":"Retail Goods"
        }
    ],
    "sg:postcode":"EX39 4DQ",
    "sg:province":"Devon",
    "sg:tags":[
        "collectors'",
        "item"
    ],
    "wof:name":"Market Coins",
    "wof:placetype":"venue"
},
  "geometry": {"coordinates":[-4.185629,51.010616],"type":"Point"}
}