{
  "type": "Feature",
  "properties": {
    "addr:full":"65 Edward St Brighton East Sussex BN2 0FF",
    "addr:housenumber":"65",
    "addr:postcode":"bn2 0ff",
    "addr:street":"Edward St",
    "iso:country":"GB",
    "sg:address":"65 Edward St",
    "sg:city":"Brighton",
    "sg:classifiers":[
        {
            "category":"Retail",
            "subcategory":"Auto Repair",
            "type":"Services"
        }
    ],
    "sg:postcode":"BN2 0FF",
    "sg:province":"East Sussex",
    "sg:tags":[
        "modification",
        "garage"
    ],
    "wof:name":"Cander,M J,",
    "wof:placetype":"venue"
},
  "geometry": {"coordinates":[-0.1300189942,50.8220481873],"type":"Point"}
}