{
  "type": "Feature",
  "properties": {
    "addr:full":"4 Churchfield Road Walton-on-thames Surrey KT12 2TF",
    "addr:housenumber":"4",
    "addr:postcode":"kt12 2tf",
    "addr:street":"Churchfield Road",
    "iso:country":"GB",
    "sg:address":"4 Churchfield Road",
    "sg:city":"Walton-on-thames",
    "sg:classifiers":[
        {
            "category":"Building & Trades",
            "subcategory":"Plumbing",
            "type":"Services"
        }
    ],
    "sg:phone":"+44 1932 223560",
    "sg:postcode":"KT12 2TF",
    "sg:province":"Surrey",
    "sg:tags":[
        "merchant",
        "plumbers'"
    ],
    "wof:name":"Universal Heating & Plumbing Supplies",
    "wof:placetype":"venue"
},
  "geometry": {"coordinates":[-0.4179559946,51.3851356506],"type":"Point"}
}