{
  "type": "Feature",
  "properties": {
    "iso:country":"GB",
    "sg:address":"69 Marine Drive, Rhos-on-sea",
    "sg:city":"Colwyn Bay",
    "sg:classifiers":[
        {
            "category":"Health Services",
            "subcategory":"Health Practitioner",
            "type":"Services"
        }
    ],
    "sg:phone":"+44 1492 547525",
    "sg:postcode":"LL28 4HT",
    "sg:province":"Conwy",
    "sg:tags":[
        "osteopath"
    ],
    "wof:name":"Keith Greenhalgh",
    "wof:placetype":"venue"
},
  "geometry": {"coordinates":[-3.7437388897,53.3151817322],"type":"Point"}
}