{
  "type": "Feature",
  "properties": {
    "addr:full":"1 Beckets Walk, Amwell End Ware Hertfordshire SG12 9HQ",
    "addr:housenumber":"1",
    "addr:postcode":"sg12 9hq",
    "addr:street":"Beckets Walk Amwell End Ware",
    "iso:country":"GB",
    "sg:address":"1 Beckets Walk, Amwell End",
    "sg:city":"Ware",
    "sg:classifiers":[
        {
            "category":"Shopping",
            "subcategory":"Gifts & Souvenirs",
            "type":"Retail Goods"
        }
    ],
    "sg:phone":"+44 1920 486188",
    "sg:postcode":"SG12 9HQ",
    "sg:province":"Hertfordshire",
    "sg:tags":[
        "shop"
    ],
    "wof:name":"Keepsakes",
    "wof:placetype":"venue"
},
  "geometry": {"coordinates":[-0.035126999,51.8163375854],"type":"Point"}
}