{
  "type": "Feature",
  "properties": {
    "addr:full":"Angel Meadow Sawmill, Style Street, Off Angel Street Manchester Greater Manchester M4 4DF",
    "addr:postcode":"greater;m4 4df",
    "addr:street":"Angel Meadow;Street;Angel Street",
    "iso:country":"GB",
    "sg:address":"Angel Meadow Sawmill, Style Street, Off Angel Street",
    "sg:city":"Manchester",
    "sg:classifiers":[
        {
            "category":"Home & Garden",
            "subcategory":"Building Materials",
            "type":"Retail Goods"
        }
    ],
    "sg:phone":"+44 161 834 8407",
    "sg:postcode":"M4 4DF",
    "sg:province":"Greater Manchester",
    "sg:tags":[
        "fencing"
    ],
    "wof:name":"Manchester Chestnut Fencing",
    "wof:placetype":"venue"
},
  "geometry": {"coordinates":[-2.2352790833,53.4870796204],"type":"Point"}
}