{
  "type": "Feature",
  "properties": {
    "iso:country":"GB",
    "sg:address":"61 St. Peters Rd",
    "sg:city":"Great Yarmouth",
    "sg:classifiers":[
        {
            "category":"Restaurant",
            "type":"Food & Drink"
        }
    ],
    "sg:phone":"+44 1493 853975",
    "sg:postcode":"NR30 3BQ",
    "sg:province":"Norfolk",
    "sg:tags":[
        "thai",
        "-"
    ],
    "wof:name":"Sawadee Thai Restaurant",
    "wof:placetype":"venue"
},
  "geometry": {"coordinates":[1.73396,52.602409],"type":"Point"}
}