{
  "type": "Feature",
  "properties": {
    "iso:country":"GB",
    "sg:address":"King Edward Street",
    "sg:city":"Barmouth",
    "sg:classifiers":[
        {
            "category":"Bars & Pubs",
            "type":"Food & Drink"
        },
        {
            "category":"Bars & Pubs",
            "subcategory":"Nightclub",
            "type":"Food & Drink"
        }
    ],
    "sg:postcode":"LL42 1AN",
    "sg:province":"Gwynedd",
    "sg:tags":[
        "pubs",
        "inn",
        "activity"
    ],
    "wof:name":"Chaplins",
    "wof:placetype":"venue"
},
  "geometry": {"coordinates":[-4.0551590919,52.7226638794],"type":"Point"}
}