{
  "type": "Feature",
  "properties": {
    "addr:full":"The Old Chillingtons Works, Hickman Avenue Wolverhampton West Midlands WV1 2UA",
    "addr:postcode":"wv1 2ua",
    "addr:street":"Hickman Avenue",
    "iso:country":"GB",
    "sg:address":"The Old Chillingtons Works, Hickman Avenue",
    "sg:city":"Wolverhampton",
    "sg:classifiers":[
        {
            "category":"Building & Trades",
            "subcategory":"Electrical",
            "type":"Services"
        }
    ],
    "sg:phone":"+44 1902 870085",
    "sg:postcode":"WV1 2UA",
    "sg:province":"West Midlands",
    "sg:tags":[
        "galvanising"
    ],
    "wof:name":"Hickmans Metal Finishing",
    "wof:placetype":"venue"
},
  "geometry": {"coordinates":[-2.1053628922,52.5822029114],"type":"Point"}
}