{
  "type": "Feature",
  "properties": {
    "addr:full":"Kinglassie Library & Clinic, 34 Main St Lochgelly Fife KY5 0XA",
    "addr:housenumber":"34",
    "addr:postcode":"ky5 0xa",
    "addr:street":"Main St",
    "iso:country":"GB",
    "sg:address":"Kinglassie Library & Clinic, 34 Main St",
    "sg:city":"Lochgelly",
    "sg:classifiers":[
        {
            "category":"Social Services",
            "type":"Services"
        },
        {
            "category":"Organizations",
            "subcategory":"Community Association",
            "type":"Services"
        }
    ],
    "sg:phone":"+44 1592 882520",
    "sg:postcode":"KY5 0XA",
    "sg:province":"Fife",
    "sg:tags":[
        "associations",
        "co-operatives",
        "housing",
        "trust",
        "societies"
    ],
    "wof:name":"SOCIAL SERVICES COMMUNITY ACCESS POINT",
    "wof:placetype":"venue"
},
  "geometry": {"coordinates":[-3.242136,56.173874],"type":"Point"}
}