{
  "type": "Feature",
  "properties": {
    "addr:full":"Oxford Road, Waterloo Liverpool Merseyside L22 8QE",
    "addr:postcode":"l22 8qe",
    "addr:street":"Oxford Road",
    "iso:country":"GB",
    "sg:address":"Oxford Road, Waterloo",
    "sg:city":"Liverpool",
    "sg:classifiers":[
        {
            "category":"Farming",
            "subcategory":"Nursery",
            "type":"Manufacturing & Wholesale Goods"
        },
        {
            "category":"Education",
            "subcategory":"Preschool",
            "type":"Public Place"
        }
    ],
    "sg:phone":"+44 151 928 6661",
    "sg:postcode":"L22 8QE",
    "sg:province":"Merseyside",
    "sg:tags":[
        "school",
        "creche"
    ],
    "wof:name":"Carousel Day Nursery",
    "wof:placetype":"venue"
},
  "geometry": {"coordinates":[-3.030904,53.476303],"type":"Point"}
}