{
  "type": "Feature",
  "properties": {
    "addr:full":"2 Boxhill Road Abingdon Oxfordshire OX14 2EU",
    "addr:housenumber":"2",
    "addr:postcode":"ox14 2eu",
    "addr:street":"Boxhill Road",
    "iso:country":"GB",
    "sg:address":"2 Boxhill Road",
    "sg:city":"Abingdon",
    "sg:classifiers":[
        {
            "category":"Building & Trades",
            "subcategory":"Construction",
            "type":"Services"
        }
    ],
    "sg:postcode":"OX14 2EU",
    "sg:province":"Oxfordshire",
    "sg:tags":[
        "builder"
    ],
    "wof:name":"G W Leighton",
    "wof:placetype":"venue"
},
  "geometry": {"coordinates":[-1.277361989,51.6769943237],"type":"Point"}
}