{
  "type": "Feature",
  "properties": {
    "iso:country":"GB",
    "sg:address":"2 Butt Lane, Manuden",
    "sg:city":"Bishops Stortford",
    "sg:classifiers":[
        {
            "category":"Shopping",
            "subcategory":"Discount & Variety Stores",
            "type":"Retail Goods"
        }
    ],
    "sg:postcode":"CM23 1DL",
    "sg:province":"Essex",
    "sg:tags":[
        "cleaning",
        "supply"
    ],
    "wof:name":"Air Fresh Services",
    "wof:placetype":"venue"
},
  "geometry": {"coordinates":[0.15586,51.920631],"type":"Point"}
}