{
  "type": "Feature",
  "properties": {
    "addr:full":"Stafford Ct, Stafford Park 1 Telford Shropshire TF3 3BD",
    "addr:housenumber":"1",
    "addr:postcode":"tf3 3bd",
    "addr:street":"Stafford Ct Stafford Park",
    "iso:country":"GB",
    "sg:address":"Stafford Ct, Stafford Park 1",
    "sg:city":"Telford",
    "sg:classifiers":[
        {
            "category":"Professional",
            "subcategory":"Management & Consulting",
            "type":"Services"
        }
    ],
    "sg:phone":"+44 1952 200444",
    "sg:postcode":"TF3 3BD",
    "sg:province":"Shropshire",
    "sg:tags":[
        "consultant",
        "business"
    ],
    "wof:name":"3d Business Analysis",
    "wof:placetype":"venue"
},
  "geometry": {"coordinates":[-2.437082,52.679028],"type":"Point"}
}