{
  "type": "Feature",
  "properties": {
    "addr:full":"Commercial Coachworks, Dunston Road Gateshead Tyne and Wear NE11 9EE",
    "addr:postcode":"ne11 9ee",
    "addr:street":"Dunston Road",
    "iso:country":"GB",
    "sg:address":"Commercial Coachworks, Dunston Road",
    "sg:city":"Gateshead",
    "sg:classifiers":[
        {
            "category":"Retail",
            "subcategory":"Auto Repair",
            "type":"Services"
        }
    ],
    "sg:phone":"+44 191 461 0791",
    "sg:postcode":"NE11 9EE",
    "sg:province":"Tyne and Wear",
    "sg:tags":[
        "modification",
        "garage"
    ],
    "wof:name":"J Ford",
    "wof:placetype":"venue"
},
  "geometry": {"coordinates":[-1.6488989592,54.9527626038],"type":"Point"}
}