{
  "type": "Feature",
  "properties": {
    "iso:country":"GB",
    "sg:address":"44 Argyll Road",
    "sg:city":"Kinross",
    "sg:classifiers":[
        {
            "category":"Retail",
            "subcategory":"Driving School",
            "type":"Services"
        }
    ],
    "sg:postcode":"KY13 8BY",
    "sg:province":"Clackmannanshire",
    "wof:name":"Deas Kinross School of Motoring",
    "wof:placetype":"venue"
},
  "geometry": {"coordinates":[-3.43042,56.212719],"type":"Point"}
}