{
  "type": "Feature",
  "properties": {
    "iso:country":"GB",
    "sg:address":"19 Weir Road",
    "sg:city":"Walton-on-thames",
    "sg:classifiers":[
        {
            "category":"Communications",
            "type":"Services"
        },
        {
            "category":"Communications",
            "subcategory":"Television Station",
            "type":"Services"
        }
    ],
    "sg:phone":"+44 1932 220368",
    "sg:postcode":"KT12 2LE",
    "sg:province":"Surrey",
    "sg:tags":[
        "satellite",
        "tv",
        "related",
        "equipment",
        "video",
        "radio"
    ],
    "wof:name":"Aerial Services",
    "wof:placetype":"venue"
},
  "geometry": {"coordinates":[-0.4153540134,51.3937606812],"type":"Point"}
}