{
  "type": "Feature",
  "properties": {
    "iso:country":"GB",
    "sg:address":"217 Upper Richmond Road West",
    "sg:city":"London",
    "sg:classifiers":[
        {
            "category":"Professional",
            "subcategory":"Management & Consulting",
            "type":"Services"
        }
    ],
    "sg:postcode":"SW14 8QS",
    "sg:province":"Greater London",
    "sg:tags":[
        "consultant",
        "business"
    ],
    "wof:name":"Montagu's Trading Ltd",
    "wof:placetype":"venue"
},
  "geometry": {"coordinates":[-0.261991,51.465031],"type":"Point"}
}