{
  "type": "Feature",
  "properties": {
    "iso:country":"GB",
    "sg:address":"36 Eastern Avenue",
    "sg:city":"Oxford",
    "sg:classifiers":[
        {
            "category":"Building & Trades",
            "subcategory":"Construction",
            "type":"Services"
        }
    ],
    "sg:postcode":"OX4 4QS",
    "sg:province":"Oxfordshire",
    "sg:tags":[
        "builder",
        "flooring"
    ],
    "wof:name":"Michael Dwyer",
    "wof:placetype":"venue"
},
  "geometry": {"coordinates":[-1.221214,51.726051],"type":"Point"}
}