{
  "type": "Feature",
  "properties": {
    "iso:country":"GB",
    "sg:address":"34 Chaucer Crescent",
    "sg:city":"Sutton-in-ashfield",
    "sg:classifiers":[
        {
            "category":"Professional",
            "subcategory":"Printing & Photocopies",
            "type":"Services"
        }
    ],
    "sg:phone":"+44 1623 515448",
    "sg:postcode":"NG17 4JG",
    "sg:province":"Nottinghamshire",
    "sg:tags":[
        "printer"
    ],
    "wof:name":"The Marketing Co",
    "wof:placetype":"venue"
},
  "geometry": {"coordinates":[-1.242419,53.132603],"type":"Point"}
}