{
  "type": "Feature",
  "properties": {
    "addr:full":"67a Oldfield Road Sale Cheshire M33 2AP",
    "addr:housenumber":"67a",
    "addr:postcode":"m33 2ap",
    "addr:street":"Oldfield Road",
    "iso:country":"GB",
    "sg:address":"67a Oldfield Road",
    "sg:city":"Sale",
    "sg:classifiers":[
        {
            "category":"Retail",
            "subcategory":"Auto Repair",
            "type":"Services"
        }
    ],
    "sg:phone":"+44 161 905 2907",
    "sg:postcode":"M33 2AP",
    "sg:province":"Cheshire",
    "sg:tags":[
        "modification",
        "garage",
        "related"
    ],
    "wof:name":"Taxi & General",
    "wof:placetype":"venue"
},
  "geometry": {"coordinates":[-2.3145430088,53.4276390076],"type":"Point"}
}