{
  "type": "Feature",
  "properties": {
    "iso:country":"GB",
    "sg:address":"9 Market Square, Kirkby",
    "sg:city":"Liverpool",
    "sg:classifiers":[
        {
            "category":"Food & Beverages",
            "subcategory":"Fruits & Vegetables",
            "type":"Retail Goods"
        }
    ],
    "sg:phone":"+44 151 549 1240",
    "sg:postcode":"L32 8RG",
    "sg:province":"Merseyside",
    "sg:tags":[
        "greengrocer"
    ],
    "wof:name":"The Big Apple",
    "wof:placetype":"venue"
},
  "geometry": {"coordinates":[-2.885204,53.482327],"type":"Point"}
}