{
  "type": "Feature",
  "properties": {
    "addr:full":"Polar House, Bowburn North Industrial Estate, Bowburn Durham Durham DH6 5PF",
    "addr:postcode":"dh6 5pf",
    "addr:street":"Estate",
    "iso:country":"GB",
    "sg:address":"Polar House, Bowburn North Industrial Estate, Bowburn",
    "sg:city":"Durham",
    "sg:classifiers":[
        {
            "category":"Home & Garden",
            "subcategory":"Household Appliances",
            "type":"Retail Goods"
        }
    ],
    "sg:phone":"+44 191 377 9777",
    "sg:postcode":"DH6 5PF",
    "sg:province":"Durham",
    "sg:tags":[
        "refrigeration",
        "air conditioning"
    ],
    "wof:name":"Coolertronics Ltd.",
    "wof:placetype":"venue"
},
  "geometry": {"coordinates":[-1.528119,54.736305],"type":"Point"}
}