{
  "type": "Feature",
  "properties": {
    "addr:full":"17 Tryfan Close, Redbridge Ilford Essex IG4 5JX",
    "addr:housenumber":"17",
    "addr:postcode":"ig4 5jx",
    "addr:street":"Tryfan Close",
    "iso:country":"GB",
    "sg:address":"17 Tryfan Close, Redbridge",
    "sg:city":"Ilford",
    "sg:classifiers":[
        {
            "category":"Building & Trades",
            "subcategory":"Construction",
            "type":"Services"
        }
    ],
    "sg:phone":"+44 20 8550 5698",
    "sg:postcode":"IG4 5JX",
    "sg:province":"Essex",
    "sg:tags":[
        "builder"
    ],
    "wof:name":"B & J Builders Ltd.",
    "wof:placetype":"venue"
},
  "geometry": {"coordinates":[0.047722999,51.5802307129],"type":"Point"}
}