{
  "type": "Feature",
  "properties": {
    "iso:country":"GB",
    "sg:address":"67 Station Road",
    "sg:city":"London",
    "sg:classifiers":[
        {
            "category":"Professional",
            "subcategory":"Management & Consulting",
            "type":"Services"
        }
    ],
    "sg:postcode":"NW4 4PH",
    "sg:province":"Greater London",
    "sg:tags":[
        "project"
    ],
    "wof:name":"E C M Associates",
    "wof:placetype":"venue"
},
  "geometry": {"coordinates":[-0.23581,51.581512],"type":"Point"}
}