{
  "type": "Feature",
  "properties": {
    "addr:full":"8 High Street Sidcup Kent DA14 6EZ",
    "addr:housenumber":"8",
    "addr:postcode":"da14 6ez",
    "addr:street":"High Street",
    "iso:country":"GB",
    "sg:address":"8 High Street",
    "sg:city":"Sidcup",
    "sg:classifiers":[
        {
            "category":"Travel",
            "subcategory":"Travel Agent",
            "type":"Entertainment"
        }
    ],
    "sg:phone":"+44 20 8300 7911",
    "sg:postcode":"DA14 6EZ",
    "sg:province":"Kent",
    "wof:name":"Lunn Poly",
    "wof:placetype":"venue"
},
  "geometry": {"coordinates":[0.103945002,51.4259185791],"type":"Point"}
}