{
  "type": "Feature",
  "properties": {
    "addr:full":"The Butts Worcester Worcestershire WR1 3PA",
    "addr:postcode":"wr1 3pa",
    "addr:street":"The Butts",
    "iso:country":"GB",
    "sg:address":"The Butts",
    "sg:city":"Worcester",
    "sg:classifiers":[
        {
            "category":"Retail",
            "subcategory":"Auto Repair",
            "type":"Services"
        }
    ],
    "sg:phone":"+44 1905 21382",
    "sg:postcode":"WR1 3PA",
    "sg:province":"Worcestershire",
    "sg:tags":[
        "modification",
        "garage"
    ],
    "wof:name":"Nw Autocentres Ltd.",
    "wof:placetype":"venue"
},
  "geometry": {"coordinates":[-2.224599,52.193851],"type":"Point"}
}