{
  "type": "Feature",
  "properties": {
    "addr:full":"Unit 1, Mill Walk (the) Birmingham West Midlands B31 4HL",
    "addr:housenumber":"unit 1;birmingham",
    "addr:postcode":"b31 4hl",
    "addr:street":"Mill Walk The",
    "iso:country":"GB",
    "sg:address":"Unit 1, Mill Walk (the)",
    "sg:city":"Birmingham",
    "sg:classifiers":[
        {
            "category":"Military Area",
            "subcategory":"Air Force Base",
            "type":"Public Place"
        }
    ],
    "sg:phone":"+44 121 608 2001",
    "sg:postcode":"B31 4HL",
    "sg:province":"West Midlands",
    "sg:tags":[
        "taxi",
        "hire",
        "private"
    ],
    "wof:name":"Rubery Radio Systems Ltd.",
    "wof:placetype":"venue"
},
  "geometry": {"coordinates":[-1.9675619602,52.4071464539],"type":"Point"}
}