{
  "type": "Feature",
  "properties": {
    "addr:full":"43 Empingham Road Stamford Cambridgeshire PE9 2RJ",
    "addr:housenumber":"43",
    "addr:postcode":"pe9 2rj",
    "addr:street":"Empingham Road",
    "iso:country":"GB",
    "sg:address":"43 Empingham Road",
    "sg:city":"Stamford",
    "sg:classifiers":[
        {
            "category":"Retail",
            "subcategory":"Veterinary Services",
            "type":"Services"
        }
    ],
    "sg:phone":"+44 1780 764333",
    "sg:postcode":"PE9 2RJ",
    "sg:province":"Cambridgeshire",
    "sg:tags":[
        "surgeon",
        "activity"
    ],
    "wof:name":"R Pontefract",
    "wof:placetype":"venue"
},
  "geometry": {"coordinates":[-0.495104,52.653374],"type":"Point"}
}