{
  "type": "Feature",
  "properties": {
    "addr:full":"71 Mere Green Road Sutton Coldfield Staffordshire B75 5BY",
    "addr:housenumber":"71",
    "addr:postcode":"b75 5by",
    "addr:street":"Mere Green Road",
    "iso:country":"GB",
    "sg:address":"71 Mere Green Road",
    "sg:city":"Sutton Coldfield",
    "sg:classifiers":[
        {
            "category":"Professional",
            "subcategory":"Detective & Security Services",
            "type":"Services"
        },
        {
            "category":"Building & Trades",
            "subcategory":"Locksmith",
            "type":"Services"
        }
    ],
    "sg:phone":"+44 121 308 8242",
    "sg:postcode":"B75 5BY",
    "sg:province":"Staffordshire",
    "wof:name":"Four Oaks Lock Co",
    "wof:placetype":"venue"
},
  "geometry": {"coordinates":[-1.8232419491,52.5877838135],"type":"Point"}
}