{
  "type": "Feature",
  "properties": {
    "addr:full":"215-221 Staines Road Hounslow Greater London TW3 3JJ",
    "addr:housenumber":"215-221",
    "addr:postcode":"tw3 3jj",
    "addr:street":"Staines Road",
    "iso:country":"GB",
    "sg:address":"215-221 Staines Road",
    "sg:city":"Hounslow",
    "sg:classifiers":[
        {
            "category":"Travel",
            "subcategory":"Hotels & Motels",
            "type":"Entertainment"
        },
        {
            "category":"Personal",
            "type":"Services"
        }
    ],
    "sg:phone":"+44 20 8577 7070",
    "sg:postcode":"TW3 3JJ",
    "sg:province":"Greater London",
    "sg:tags":[
        "wedding"
    ],
    "wof:name":"Shalimar Hotel",
    "wof:placetype":"venue"
},
  "geometry": {"coordinates":[-0.375295,51.465969],"type":"Point"}
}