{
  "type": "Feature",
  "properties": {
    "addr:full":"1 Sandhill, Littleport Ely Cambridgeshire CB6 1NT",
    "addr:housenumber":"1;littleport",
    "addr:postcode":"cb6 1nt",
    "addr:street":"Sandhill",
    "iso:country":"GB",
    "sg:address":"1 Sandhill, Littleport",
    "sg:city":"Ely",
    "sg:classifiers":[
        {
            "category":"Bars & Pubs",
            "type":"Food & Drink"
        }
    ],
    "sg:phone":"+44 1353 860328",
    "sg:postcode":"CB6 1NT",
    "sg:province":"Cambridgeshire",
    "sg:tags":[
        "pubs",
        "inn"
    ],
    "wof:name":"Phoenix Inns Ltd",
    "wof:placetype":"venue"
},
  "geometry": {"coordinates":[0.284259,52.44907],"type":"Point"}
}