{
  "type": "Feature",
  "properties": {
    "iso:country":"GB",
    "sg:address":"10 The Pantiles",
    "sg:city":"Billericay",
    "sg:classifiers":[
        {
            "category":"Shopping",
            "subcategory":"Pharmacy",
            "type":"Retail Goods"
        }
    ],
    "sg:phone":"+44 1277 653035",
    "sg:postcode":"CM12 0UA",
    "sg:province":"Essex",
    "sg:tags":[
        "pharmacist",
        "chemist"
    ],
    "wof:name":"Moss Chemists",
    "wof:placetype":"venue"
},
  "geometry": {"coordinates":[0.413695,51.637157],"type":"Point"}
}