{
  "type": "Feature",
  "properties": {
    "addr:full":"The Studio, 16-18 Pampisford Road Purley Surrey CR8 2NE",
    "addr:housenumber":"16-18",
    "addr:postcode":"cr8 2ne",
    "addr:street":"Pampisford Road",
    "iso:country":"GB",
    "sg:address":"The Studio, 16-18 Pampisford Road",
    "sg:city":"Purley",
    "sg:classifiers":[
        {
            "category":"Professional",
            "type":"Services"
        }
    ],
    "sg:phone":"+44 20 8763 2028",
    "sg:postcode":"CR8 2NE",
    "sg:province":"Surrey",
    "sg:tags":[
        "hire",
        "agency",
        "driver"
    ],
    "wof:name":"Driver Hire Croydon",
    "wof:placetype":"venue"
},
  "geometry": {"coordinates":[-0.1167339981,51.3386650085],"type":"Point"}
}