{
  "type": "Feature",
  "properties": {
    "addr:full":"46 Winnock Road Colchester Essex CO1 2BJ",
    "addr:housenumber":"46",
    "addr:postcode":"co1 2bj",
    "addr:street":"Winnock Road Colchester",
    "iso:country":"GB",
    "sg:address":"46 Winnock Road",
    "sg:city":"Colchester",
    "sg:classifiers":[
        {
            "category":"Building & Trades",
            "subcategory":"Plumbing",
            "type":"Services"
        }
    ],
    "sg:phone":"+44 1206 769844",
    "sg:postcode":"CO1 2BJ",
    "sg:province":"Essex",
    "sg:tags":[
        "heating"
    ],
    "wof:name":"Michael Brooks",
    "wof:placetype":"venue"
},
  "geometry": {"coordinates":[0.9096369743,51.8838882446],"type":"Point"}
}