{
  "type": "Feature",
  "properties": {
    "addr:full":"Building 3 Stanmore Indust Est Bridgnorth Shropshire WV15 5HP",
    "addr:postcode":"wv15 5hp",
    "iso:country":"GB",
    "sg:address":"Building 3 Stanmore Indust Est",
    "sg:city":"Bridgnorth",
    "sg:classifiers":[
        {
            "category":"Home & Garden",
            "subcategory":"Building Materials",
            "type":"Retail Goods"
        }
    ],
    "sg:phone":"+44 1746 766466",
    "sg:postcode":"WV15 5HP",
    "sg:province":"Shropshire",
    "sg:tags":[
        "furnishers",
        "bathroom",
        "planner"
    ],
    "wof:name":"Coram (Uk) Ltd",
    "wof:placetype":"venue"
},
  "geometry": {"coordinates":[-2.384303093,52.5323982239],"type":"Point"}
}