{
  "type": "Feature",
  "properties": {
    "iso:country":"GB",
    "sg:address":"22 Watling Street",
    "sg:city":"Gillingham",
    "sg:classifiers":[
        {
            "category":"Retail",
            "subcategory":"Auto Repair",
            "type":"Services"
        }
    ],
    "sg:phone":"+44 1634 577747",
    "sg:postcode":"ME7 2YH",
    "sg:province":"Kent",
    "sg:tags":[
        "engine",
        "car",
        "specialist"
    ],
    "wof:name":"Hunters Mobile Tuning",
    "wof:placetype":"venue"
},
  "geometry": {"coordinates":[0.554714,51.373184],"type":"Point"}
}