{
  "type": "Feature",
  "properties": {
    "iso:country":"GB",
    "sg:address":"3 Priory Business Park",
    "sg:city":"Bedford",
    "sg:classifiers":[
        {
            "category":"Education",
            "subcategory":"School",
            "type":"Public Place"
        }
    ],
    "sg:phone":"+44 1234 831090",
    "sg:postcode":"MK44 3WH",
    "sg:province":"Bedfordshire",
    "sg:tags":[
        "local",
        "authority"
    ],
    "wof:name":"Learning for Life Bedfordshire & Luton",
    "wof:placetype":"venue"
},
  "geometry": {"coordinates":[-0.319379,52.132729],"type":"Point"}
}