{
  "type": "Feature",
  "properties": {
    "iso:country":"GB",
    "sg:address":"6 Springfield Green, Sedgley",
    "sg:city":"Dudley",
    "sg:classifiers":[
        {
            "category":"Building & Trades",
            "subcategory":"Construction",
            "type":"Services"
        }
    ],
    "sg:phone":"+44 1384 239305",
    "sg:postcode":"DY3 1PT",
    "sg:province":"Staffordshire",
    "sg:tags":[
        "builder"
    ],
    "wof:name":"Handyman Builders",
    "wof:placetype":"venue"
},
  "geometry": {"coordinates":[-2.118641,52.547131],"type":"Point"}
}