{
  "type": "Feature",
  "properties": {
    "iso:country":"GB",
    "sg:address":"20 Sandy Park Road",
    "sg:city":"Bristol",
    "sg:classifiers":[
        {
            "category":"Real Estate",
            "subcategory":"Real Estate Agent",
            "type":"Services"
        }
    ],
    "sg:phone":"+44 117 971 3349",
    "sg:postcode":"BS4 3PE",
    "sg:province":"City of Bristol",
    "wof:name":"Taylors Estate Agents",
    "wof:placetype":"venue"
},
  "geometry": {"coordinates":[-2.555066,51.4408],"type":"Point"}
}