{
  "type": "Feature",
  "properties": {
    "addr:full":"6 Tresco Road Berkhamsted Bedfordshire HP4 3JZ",
    "addr:housenumber":"6",
    "addr:postcode":"hp4 3jz",
    "addr:street":"Tresco Road",
    "iso:country":"GB",
    "sg:address":"6 Tresco Road",
    "sg:city":"Berkhamsted",
    "sg:classifiers":[
        {
            "category":"Professional",
            "subcategory":"Business Services",
            "type":"Services"
        }
    ],
    "sg:phone":"+44 1442 872131",
    "sg:postcode":"HP4 3JZ",
    "sg:province":"Bedfordshire",
    "sg:tags":[
        "code",
        "bar"
    ],
    "wof:name":"Pankaj Rach",
    "wof:placetype":"venue"
},
  "geometry": {"coordinates":[-0.583631,51.76162],"type":"Point"}
}