{
  "type": "Feature",
  "properties": {
    "iso:country":"GB",
    "sg:address":"Tarraby Farm",
    "sg:city":"Carlisle",
    "sg:classifiers":[
        {
            "category":"Freight",
            "type":"Transportation"
        }
    ],
    "sg:phone":"+44 1228 522971",
    "sg:postcode":"CA3 0JS",
    "sg:province":"Cumbria",
    "sg:tags":[
        "haulage",
        "road"
    ],
    "wof:name":"T H Littleton",
    "wof:placetype":"venue"
},
  "geometry": {"coordinates":[-2.9235620499,54.9143333435],"type":"Point"}
}