{
  "type": "Feature",
  "properties": {
    "addr:full":"Castle Hill, Kielder Hexham Northumberland NE48 1ER",
    "addr:postcode":"ne48 1er",
    "addr:street":"Hill",
    "iso:country":"GB",
    "sg:address":"Castle Hill, Kielder",
    "sg:city":"Hexham",
    "sg:classifiers":[
        {
            "category":"Shopping",
            "subcategory":"Bicycles & Sporting Goods",
            "type":"Retail Goods"
        }
    ],
    "sg:postcode":"NE48 1ER",
    "sg:province":"Northumberland",
    "sg:tags":[
        "cycle",
        "accessory"
    ],
    "wof:name":"Kielder Bikes",
    "wof:placetype":"venue"
},
  "geometry": {"coordinates":[-2.586623,55.23468],"type":"Point"}
}