{
  "type": "Feature",
  "properties": {
    "addr:full":"162 Hednesford Road Cannock Staffordshire WS12 5DZ",
    "addr:housenumber":"162",
    "addr:postcode":"ws12 5dz",
    "addr:street":"Hednesford Road",
    "iso:country":"GB",
    "sg:address":"162 Hednesford Road",
    "sg:city":"Cannock",
    "sg:classifiers":[
        {
            "category":"Home & Garden",
            "subcategory":"Home Furnishings",
            "type":"Retail Goods"
        }
    ],
    "sg:phone":"+44 1543 279262",
    "sg:postcode":"WS12 5DZ",
    "sg:province":"Staffordshire",
    "sg:tags":[
        "beds",
        "bedding",
        "blanket"
    ],
    "wof:name":"Parkin",
    "wof:placetype":"venue"
},
  "geometry": {"coordinates":[-1.9823440313,52.6898880005],"type":"Point"}
}