{
  "type": "Feature",
  "properties": {
    "iso:country":"GB",
    "sg:address":"1595 London Road",
    "sg:city":"Leigh-on-sea",
    "sg:classifiers":[
        {
            "category":"Restaurant",
            "type":"Food & Drink"
        }
    ],
    "sg:phone":"+44 1702 712910",
    "sg:postcode":"SS9 2SG",
    "sg:province":"Essex",
    "wof:name":"Montys Bar & Bistro",
    "wof:placetype":"venue"
},
  "geometry": {"coordinates":[0.638465,51.547958],"type":"Point"}
}