{
  "type": "Feature",
  "properties": {
    "addr:full":"68 Eyre Place Edinburgh City of Edinburgh EH3 5EJ",
    "addr:housenumber":"68",
    "addr:postcode":"eh3 5ej",
    "addr:street":"Eyre Place Edinburgh",
    "iso:country":"GB",
    "sg:address":"68 Eyre Place",
    "sg:city":"Edinburgh",
    "sg:classifiers":[
        {
            "category":"Professional",
            "subcategory":"Business Services",
            "type":"Services"
        }
    ],
    "sg:postcode":"EH3 5EJ",
    "sg:province":"City of Edinburgh",
    "sg:tags":[
        "import",
        "export",
        "agent"
    ],
    "wof:name":"Veecom Systems",
    "wof:placetype":"venue"
},
  "geometry": {"coordinates":[-3.197332,55.962044],"type":"Point"}
}