{
  "type": "Feature",
  "properties": {
    "iso:country":"GB",
    "sg:address":"St Austell, Wilkie Road",
    "sg:city":"Birchington",
    "sg:classifiers":[
        {
            "category":"Communications",
            "subcategory":"Film & Video Production",
            "type":"Services"
        }
    ],
    "sg:phone":"+44 1843 841226",
    "sg:postcode":"CT7 9HE",
    "sg:province":"Kent",
    "sg:tags":[
        "illustrator",
        "artist"
    ],
    "wof:name":"Campbell Henry",
    "wof:placetype":"venue"
},
  "geometry": {"coordinates":[1.3089419603,51.3740158081],"type":"Point"}
}