{
  "type": "Feature",
  "properties": {
    "addr:full":"246 Wimbledon Park Road London Greater London SW18 5RL",
    "addr:housenumber":"246",
    "addr:postcode":"sw18 5rl",
    "addr:street":"Wimbledon Park Road",
    "iso:country":"GB",
    "sg:address":"246 Wimbledon Park Road",
    "sg:city":"London",
    "sg:classifiers":[
        {
            "category":"Retail",
            "subcategory":"Photofinishing",
            "type":"Services"
        }
    ],
    "sg:phone":"+44 20 8780 0042",
    "sg:postcode":"SW18 5RL",
    "sg:province":"Greater London",
    "sg:tags":[
        "photographic",
        "processor"
    ],
    "wof:name":"A Set Print",
    "wof:placetype":"venue"
},
  "geometry": {"coordinates":[-0.2065699995,51.4450111389],"type":"Point"}
}