{
  "type": "Feature",
  "properties": {
    "iso:country":"GB",
    "sg:address":"Tempus 249 Midsummer Blvd, Central Milton Keynes",
    "sg:city":"Milton Keynes",
    "sg:classifiers":[
        {
            "category":"Professional",
            "subcategory":"Management & Consulting",
            "type":"Services"
        }
    ],
    "sg:phone":"+44 1908 660005",
    "sg:postcode":"MK9 1EU",
    "sg:province":"Buckinghamshire",
    "sg:tags":[
        "consultant",
        "training"
    ],
    "wof:name":"Training and Development Unit",
    "wof:placetype":"venue"
},
  "geometry": {"coordinates":[-0.7673299909,52.0379981995],"type":"Point"}
}