{
  "type": "Feature",
  "properties": {
    "addr:full":"188 Picton Rd Liverpool Merseyside L15 4LL",
    "addr:housenumber":"188",
    "addr:postcode":"l15 4ll",
    "addr:street":"Picton Rd",
    "iso:country":"GB",
    "sg:address":"188 Picton Rd",
    "sg:city":"Liverpool",
    "sg:classifiers":[
        {
            "category":"Shopping",
            "subcategory":"Florist",
            "type":"Retail Goods"
        }
    ],
    "sg:phone":"+44 151 734 5533",
    "sg:postcode":"L15 4LL",
    "sg:province":"Merseyside",
    "wof:name":"Picton Road Florist",
    "wof:placetype":"venue"
},
  "geometry": {"coordinates":[-2.927932024,53.400177002],"type":"Point"}
}