{
  "type": "Feature",
  "properties": {
    "addr:full":"Trafalgar Place Portsmouth Hampshire PO1 5JJ",
    "addr:postcode":"hampshire po1 5jj",
    "addr:street":"Trafalgar Place",
    "iso:country":"GB",
    "sg:address":"Trafalgar Place",
    "sg:city":"Portsmouth",
    "sg:classifiers":[
        {
            "category":"Deli",
            "type":"Food & Drink"
        }
    ],
    "sg:postcode":"PO1 5JJ",
    "sg:province":"Hampshire",
    "sg:tags":[
        "delivery",
        "sandwich"
    ],
    "wof:name":"The Sandwich Round",
    "wof:placetype":"venue"
},
  "geometry": {"coordinates":[-1.076404,50.800968],"type":"Point"}
}