{
  "type": "Feature",
  "properties": {
    "addr:full":"Unit 3, Temple Industrial Estate, Windsor Street Cheltenham Gloucestershire GL52 2DE",
    "addr:housenumber":"unit 3",
    "addr:postcode":"gl52 2de",
    "addr:street":"Temple Industrial Estate Windsor Street",
    "iso:country":"GB",
    "sg:address":"Unit 3, Temple Industrial Estate, Windsor Street",
    "sg:city":"Cheltenham",
    "sg:classifiers":[
        {
            "category":"Professional",
            "subcategory":"Management & Consulting",
            "type":"Services"
        }
    ],
    "sg:postcode":"GL52 2DE",
    "sg:province":"Gloucestershire",
    "sg:tags":[
        "consultant",
        "business"
    ],
    "wof:name":"Utilica",
    "wof:placetype":"venue"
},
  "geometry": {"coordinates":[-2.06366992,51.9075393677],"type":"Point"}
}