{
  "type": "Feature",
  "properties": {
    "addr:full":"14 South Crescent Road, South Beach Ardrossan North Ayrshire KA22 8DY",
    "addr:housenumber":"14",
    "addr:postcode":"ka22 8dy",
    "addr:street":"South Crescent Road",
    "iso:country":"GB",
    "sg:address":"14 South Crescent Road, South Beach",
    "sg:city":"Ardrossan",
    "sg:classifiers":[
        {
            "category":"Travel",
            "subcategory":"Hotels & Motels",
            "type":"Entertainment"
        }
    ],
    "sg:postcode":"KA22 8DY",
    "sg:province":"North Ayrshire",
    "wof:name":"Ingledene Hotel",
    "wof:placetype":"venue"
},
  "geometry": {"coordinates":[-4.802649,55.640446],"type":"Point"}
}