{
  "type": "Feature",
  "properties": {
    "addr:full":"Glenroyd, Burnley Road Todmorden Lancashire OL14 7DJ",
    "addr:postcode":"ol14 7dj",
    "addr:street":"Burnley Road",
    "iso:country":"GB",
    "sg:address":"Glenroyd, Burnley Road",
    "sg:city":"Todmorden",
    "sg:classifiers":[
        {
            "category":"Professional",
            "subcategory":"Business Services",
            "type":"Services"
        },
        {
            "category":"Train Station",
            "subcategory":"Rail",
            "type":"Transportation"
        }
    ],
    "sg:phone":"+44 1706 812832",
    "sg:postcode":"OL14 7DJ",
    "sg:province":"Lancashire",
    "sg:tags":[
        "caravan",
        "manufacturer"
    ],
    "wof:name":"M G Caravan Co Ltd",
    "wof:placetype":"venue"
},
  "geometry": {"coordinates":[-2.097308,53.71431],"type":"Point"}
}