{
  "type": "Feature",
  "properties": {
    "addr:full":"Digby Fen, Billinghay Lincoln Lincolnshire LN4 4DT",
    "addr:postcode":"ln4 4dt",
    "iso:country":"GB",
    "sg:address":"Digby Fen, Billinghay",
    "sg:city":"Lincoln",
    "sg:classifiers":[
        {
            "category":"Farming",
            "subcategory":"Crops",
            "type":"Manufacturing & Wholesale Goods"
        },
        {
            "category":"Farming",
            "subcategory":"Farm",
            "type":"Manufacturing & Wholesale Goods"
        }
    ],
    "sg:phone":"+44 1526 860404",
    "sg:postcode":"LN4 4DT",
    "sg:province":"Lincolnshire",
    "sg:tags":[
        "mixed",
        "arable"
    ],
    "wof:name":"K Maltby & Son",
    "wof:placetype":"venue"
},
  "geometry": {"coordinates":[-0.28111,53.079254],"type":"Point"}
}