{
  "type": "Feature",
  "properties": {
    "iso:country":"GB",
    "sg:address":"Executive Ho, 55 Carshalton Rd",
    "sg:city":"Sutton",
    "sg:classifiers":[
        {
            "category":"Building & Trades",
            "subcategory":"Construction",
            "type":"Services"
        }
    ],
    "sg:phone":"+44 20 8642 8000",
    "sg:postcode":"SM1 4LH",
    "sg:province":"Surrey",
    "sg:tags":[
        "heating",
        "contractor"
    ],
    "wof:name":"Baker Mechanical Services Ltd",
    "wof:placetype":"venue"
},
  "geometry": {"coordinates":[-0.197558,51.361191],"type":"Point"}
}