{
  "type": "Feature",
  "properties": {
    "addr:full":"Stalls 14-16 New Smithfield Market, Openshore Manchester Greater Manchester M11 2WJ",
    "addr:housenumber":"14-16",
    "addr:postcode":"m11 2wj",
    "addr:street":"Stalls;New Smithfield Market Openshore",
    "iso:country":"GB",
    "sg:address":"Stalls 14-16 New Smithfield Market, Openshore",
    "sg:city":"Manchester",
    "sg:classifiers":[
        {
            "category":"Food & Beverages",
            "subcategory":"Fruits & Vegetables",
            "type":"Retail Goods"
        }
    ],
    "sg:phone":"+44 161 223 7900",
    "sg:postcode":"M11 2WJ",
    "sg:province":"Greater Manchester",
    "sg:tags":[
        "greengrocer"
    ],
    "wof:name":"Thompsons Fruit (Manchester) Ltd.",
    "wof:placetype":"venue"
},
  "geometry": {"coordinates":[-2.1857790947,53.4766693115],"type":"Point"}
}