{
  "type": "Feature",
  "properties": {
    "addr:full":"Unit 2, Mortons Entry, Off Victoria Street Newton Stewart Dumfries and Galloway DG8 6NH",
    "addr:housenumber":"unit 2",
    "addr:postcode":"dg8 6nh",
    "addr:street":"Mortons Entry Off Victoria Street",
    "iso:country":"GB",
    "sg:address":"Unit 2, Mortons Entry, Off Victoria Street",
    "sg:city":"Newton Stewart",
    "sg:classifiers":[
        {
            "category":"Personal",
            "subcategory":"Beauty Salon",
            "type":"Services"
        }
    ],
    "sg:phone":"+44 1671 403731",
    "sg:postcode":"DG8 6NH",
    "sg:province":"Dumfries and Galloway",
    "sg:tags":[
        "unisex",
        "hairdresser"
    ],
    "wof:name":"Snips",
    "wof:placetype":"venue"
},
  "geometry": {"coordinates":[-4.482984,54.954784],"type":"Point"}
}