{
  "type": "Feature",
  "properties": {
    "addr:full":"Martley Rd Birmingham West Midlands B69 1DZ",
    "addr:postcode":"b69 1dz",
    "addr:street":"Martley Rd",
    "iso:country":"GB",
    "sg:address":"Martley Rd",
    "sg:city":"Birmingham",
    "sg:classifiers":[
        {
            "category":"Education",
            "subcategory":"Library",
            "type":"Public Place"
        }
    ],
    "sg:phone":"+44 121 552 2879",
    "sg:postcode":"B69 1DZ",
    "sg:province":"West Midlands",
    "sg:tags":[
        "book"
    ],
    "wof:name":"SANDWELL METROPOLITAN BOROUGH COUNCIL",
    "wof:placetype":"venue"
},
  "geometry": {"coordinates":[-2.0339899063,52.4938201904],"type":"Point"}
}