{
  "type": "Feature",
  "properties": {
    "addr:full":"Freemans Lane, Bonby Brigg Lincolnshire DN20 0PN",
    "addr:postcode":"dn20 0pn",
    "addr:street":"Freemans Lane;Brigg",
    "iso:country":"GB",
    "sg:address":"Freemans Lane, Bonby",
    "sg:city":"Brigg",
    "sg:classifiers":[
        {
            "category":"Personal",
            "subcategory":"Beauty Salon",
            "type":"Services"
        },
        {
            "category":"Personal",
            "subcategory":"Barber",
            "type":"Services"
        }
    ],
    "sg:phone":"+44 1652 618629",
    "sg:postcode":"DN20 0PN",
    "sg:province":"Lincolnshire",
    "sg:tags":[
        "unisex",
        "hairdresser"
    ],
    "wof:name":"Tina's Hair & Beauty",
    "wof:placetype":"venue"
},
  "geometry": {"coordinates":[-0.485457,53.625443],"type":"Point"}
}