{
  "type": "Feature",
  "properties": {
    "addr:full":"Ringley Hey, Slaidburn Road, Waddington Clitheroe Lancashire BB7 3JJ",
    "addr:postcode":"bb7 3jj",
    "addr:street":"Ringley;Slaidburn Road",
    "iso:country":"GB",
    "sg:address":"Ringley Hey, Slaidburn Road, Waddington",
    "sg:city":"Clitheroe",
    "sg:classifiers":[
        {
            "category":"Banks & Credit Unions",
            "subcategory":"Financial Services",
            "type":"Services"
        }
    ],
    "sg:phone":"+44 1200 442200",
    "sg:postcode":"BB7 3JJ",
    "sg:province":"Lancashire",
    "sg:tags":[
        "adviser",
        "independent"
    ],
    "wof:name":"Financial Integrity",
    "wof:placetype":"venue"
},
  "geometry": {"coordinates":[-2.441257,53.966885],"type":"Point"}
}