{
  "type": "Feature",
  "properties": {
    "addr:full":"2 Farrar Road Bangor Gwynedd LL57 1LJ",
    "addr:housenumber":"2",
    "addr:postcode":"ll57 1lj",
    "addr:street":"Farrar Road",
    "iso:country":"GB",
    "sg:address":"2 Farrar Road",
    "sg:city":"Bangor",
    "sg:classifiers":[
        {
            "category":"Shopping",
            "subcategory":"Mobile Phones",
            "type":"Retail Goods"
        }
    ],
    "sg:phone":"+44 1248 370055",
    "sg:postcode":"LL57 1LJ",
    "sg:province":"Gwynedd",
    "wof:name":"Vanguard Communications",
    "wof:placetype":"venue"
},
  "geometry": {"coordinates":[-4.1322507858,53.2234916687],"type":"Point"}
}