{
  "type": "Feature",
  "properties": {
    "iso:country":"GB",
    "sg:address":"Morrison Houset, 12 Atholl Crescent",
    "sg:city":"Edinburgh",
    "sg:classifiers":[
        {
            "category":"Real Estate",
            "subcategory":"Real Estate Agent",
            "type":"Services"
        }
    ],
    "sg:postcode":"EH3 8HA",
    "sg:province":"City of Edinburgh",
    "wof:name":"Richlea Residential Ltd",
    "wof:placetype":"venue"
},
  "geometry": {"coordinates":[-3.2115800381,55.9481010437],"type":"Point"}
}