{
  "type": "Feature",
  "properties": {
    "addr:full":"Unit 112 Cribbs Causeway Region, Patchway Bristol Gloucestershire BS34 5DG",
    "addr:housenumber":"112",
    "addr:postcode":"bs34 5dg",
    "addr:street":"Cribbs Causeway",
    "iso:country":"GB",
    "sg:address":"Unit 112 Cribbs Causeway Region, Patchway",
    "sg:city":"Bristol",
    "sg:classifiers":[
        {
            "category":"Shopping",
            "subcategory":"Clothing, Apparel, & Fashions",
            "type":"Retail Goods"
        }
    ],
    "sg:phone":"+44 117 950 9622",
    "sg:postcode":"BS34 5DG",
    "sg:province":"Gloucestershire",
    "sg:tags":[
        "shop"
    ],
    "wof:name":"River Island Clothing Co. Ltd.",
    "wof:placetype":"venue"
},
  "geometry": {"coordinates":[-2.59539,51.525108],"type":"Point"}
}