{
  "type": "Feature",
  "properties": {
    "addr:full":"5-7 Garland Road Stanmore Greater London HA7 1QU",
    "addr:housenumber":"5-7",
    "addr:postcode":"ha7 1qu",
    "addr:street":"Garland Road",
    "iso:country":"GB",
    "sg:address":"5-7 Garland Road",
    "sg:city":"Stanmore",
    "sg:classifiers":[
        {
            "category":"Manufacturing",
            "subcategory":"Food",
            "type":"Manufacturing & Wholesale Goods"
        },
        {
            "category":"Wholesale",
            "subcategory":"Groceries",
            "type":"Manufacturing & Wholesale Goods"
        }
    ],
    "sg:phone":"+44 20 8951 3636",
    "sg:postcode":"HA7 1QU",
    "sg:province":"Greater London",
    "sg:tags":[
        "supplier",
        "import",
        "exporter",
        "agent",
        "drink"
    ],
    "wof:name":"TOP-OP (FOODS) LTD",
    "wof:placetype":"venue"
},
  "geometry": {"coordinates":[-0.296706,51.604076],"type":"Point"}
}