{
  "type": "Feature",
  "properties": {
    "addr:full":"25 Station Rd Aldershot Hampshire GU11 1HT",
    "addr:housenumber":"25",
    "addr:postcode":"gu11 1ht",
    "addr:street":"Station Rd",
    "iso:country":"GB",
    "sg:address":"25 Station Rd",
    "sg:city":"Aldershot",
    "sg:classifiers":[
        {
            "category":"Personal",
            "subcategory":"Beauty Salon",
            "type":"Services"
        }
    ],
    "sg:postcode":"GU11 1HT",
    "sg:province":"Hampshire",
    "sg:tags":[
        "unisex",
        "hairdresser"
    ],
    "wof:name":"Gommas,G,",
    "wof:placetype":"venue"
},
  "geometry": {"coordinates":[-0.7613610029,51.2479171753],"type":"Point"}
}