{
  "type": "Feature",
  "properties": {
    "iso:country":"GB",
    "sg:address":"1 Queensway",
    "sg:city":"Crewe",
    "sg:classifiers":[
        {
            "category":"Communications",
            "type":"Services"
        }
    ],
    "sg:phone":"+44 1270 256820",
    "sg:postcode":"CW1 2HL",
    "sg:province":"Cheshire",
    "sg:tags":[
        "tv",
        "video",
        "radio"
    ],
    "wof:name":"Martin Dawes",
    "wof:placetype":"venue"
},
  "geometry": {"coordinates":[-2.442372,53.097851],"type":"Point"}
}