{
  "type": "Feature",
  "properties": {
    "addr:full":"15 The Parade Bourne End Berkshire SL8 5SA",
    "addr:housenumber":"15",
    "addr:postcode":"sl8 5sa",
    "addr:street":"The Parade Bourne",
    "iso:country":"GB",
    "sg:address":"15 The Parade",
    "sg:city":"Bourne End",
    "sg:classifiers":[
        {
            "category":"Personal",
            "subcategory":"Beauty Salon",
            "type":"Services"
        }
    ],
    "sg:phone":"+44 1628 528032",
    "sg:postcode":"SL8 5SA",
    "sg:province":"Berkshire",
    "sg:tags":[
        "unisex",
        "hairdresser"
    ],
    "wof:name":"Hair Bourne",
    "wof:placetype":"venue"
},
  "geometry": {"coordinates":[-0.7119039893,51.5786399841],"type":"Point"}
}