{
  "type": "Feature",
  "properties": {
    "addr:full":"214 High Street Loughton Essex IG10 1ET",
    "addr:housenumber":"214",
    "addr:postcode":"ig10 1et",
    "addr:street":"High Street",
    "iso:country":"GB",
    "sg:address":"214 High Street",
    "sg:city":"Loughton",
    "sg:classifiers":[
        {
            "category":"Sports & Exercise",
            "subcategory":"Sports Center",
            "type":"Entertainment"
        }
    ],
    "sg:phone":"+44 20 8508 3123",
    "sg:postcode":"IG10 1ET",
    "sg:province":"Essex",
    "sg:tags":[
        "shop",
        "good"
    ],
    "wof:name":"Intersport (Eccere Sports)",
    "wof:placetype":"venue"
},
  "geometry": {"coordinates":[0.055104,51.647709],"type":"Point"}
}