{
  "type": "Feature",
  "properties": {
    "addr:full":"2 Elers Road London Greater London W13 9QD",
    "addr:housenumber":"2",
    "addr:postcode":"w13 9qd",
    "addr:street":"Elers Road",
    "iso:country":"GB",
    "sg:address":"2 Elers Road",
    "sg:city":"London",
    "sg:classifiers":[
        {
            "category":"Health Services",
            "subcategory":"Nursing And Care Facility",
            "type":"Services"
        },
        {
            "category":"Community Center",
            "subcategory":"Youth",
            "type":"Public Place"
        }
    ],
    "sg:phone":"+44 20 8566 1039",
    "sg:postcode":"W13 9QD",
    "sg:province":"Greater London",
    "sg:tags":[
        "home",
        "children's",
        "activity"
    ],
    "wof:name":"The Lammas Park Nursing Home",
    "wof:placetype":"venue"
},
  "geometry": {"coordinates":[-0.3119490147,51.5054283142],"type":"Point"}
}