{
  "type": "Feature",
  "properties": {
    "iso:country":"GB",
    "sg:address":"Whitney Rd",
    "sg:city":"Basingstoke",
    "sg:classifiers":[
        {
            "category":"Professional",
            "subcategory":"Engineering",
            "type":"Services"
        }
    ],
    "sg:phone":"+44 1256 476747",
    "sg:postcode":"RG24 8NS",
    "sg:province":"Hampshire",
    "sg:tags":[
        "electronic",
        "engineer"
    ],
    "wof:name":"Transpower",
    "wof:placetype":"venue"
},
  "geometry": {"coordinates":[-1.066396,51.274242],"type":"Point"}
}