{
  "type": "Feature",
  "properties": {
    "addr:full":"Lionsgate Ayr East Ayrshire KA6 6AJ",
    "addr:postcode":"ka6 6aj",
    "addr:street":"Lionsgate;East",
    "iso:country":"GB",
    "sg:address":"Lionsgate",
    "sg:city":"Ayr",
    "sg:classifiers":[
        {
            "category":"Sports & Exercise",
            "subcategory":"Stables",
            "type":"Entertainment"
        },
        {
            "category":"Personal",
            "subcategory":"Adult",
            "type":"Services"
        }
    ],
    "sg:phone":"+44 1292 261556",
    "sg:postcode":"KA6 6AJ",
    "sg:province":"East Ayrshire",
    "sg:tags":[
        "equestrian",
        "centre",
        "livery",
        "schools",
        "riding",
        "education"
    ],
    "wof:name":"Lionsgate Stables",
    "wof:placetype":"venue"
},
  "geometry": {"coordinates":[-4.5345788002,55.4334602356],"type":"Point"}
}