{
  "type": "Feature",
  "properties": {
    "iso:country":"GB",
    "sg:address":"Newthorpe Farm, Newthorpe, South Milford",
    "sg:city":"Leeds",
    "sg:classifiers":[
        {
            "category":"Farming",
            "subcategory":"Farm",
            "type":"Manufacturing & Wholesale Goods"
        }
    ],
    "sg:phone":"+44 1977 682386",
    "sg:postcode":"LS25 6JP",
    "sg:province":"North Yorkshire",
    "sg:tags":[
        "mixed",
        "crop"
    ],
    "wof:name":"W Hare & Sons",
    "wof:placetype":"venue"
},
  "geometry": {"coordinates":[-1.307,53.790909],"type":"Point"}
}