{
  "type": "Feature",
  "properties": {
    "addr:full":"34 Malvern Park, Beltine Herne Bay Kent CT6 6LW",
    "addr:housenumber":"34",
    "addr:postcode":"ct6 6lw",
    "addr:street":"Malvern Park",
    "iso:country":"GB",
    "sg:address":"34 Malvern Park, Beltine",
    "sg:city":"Herne Bay",
    "sg:classifiers":[
        {
            "category":"Utilities",
            "subcategory":"Refuse",
            "type":"Services"
        }
    ],
    "sg:phone":"+44 1227 360308",
    "sg:postcode":"CT6 6LW",
    "sg:province":"Kent",
    "sg:tags":[
        "skip",
        "hire"
    ],
    "wof:name":"Waynes Skips",
    "wof:placetype":"venue"
},
  "geometry": {"coordinates":[1.1534210443,51.3673934937],"type":"Point"}
}