{
  "type": "Feature",
  "properties": {
    "addr:full":"Unit 2b Bedford Rd Petersfield Hampshire GU32 3LT",
    "addr:housenumber":"unit 2b",
    "addr:postcode":"gu32 3lt",
    "addr:street":"Bedford Rd",
    "iso:country":"GB",
    "sg:address":"Unit 2b Bedford Rd",
    "sg:city":"Petersfield",
    "sg:classifiers":[
        {
            "category":"Retail",
            "subcategory":"Auto Repair",
            "type":"Services"
        }
    ],
    "sg:phone":"+44 1420 538140",
    "sg:postcode":"GU32 3LT",
    "sg:province":"Hampshire",
    "sg:tags":[
        "modification",
        "garage"
    ],
    "wof:name":"Bush Motor Engineering",
    "wof:placetype":"venue"
},
  "geometry": {"coordinates":[-0.947446,51.002789],"type":"Point"}
}