{
  "type": "Feature",
  "properties": {
    "addr:full":"Stanton Road, Stapenhill Burton-on-trent Derbyshire DE15 9RP",
    "addr:postcode":"de15 9rp",
    "addr:street":"Stanton Road",
    "iso:country":"GB",
    "sg:address":"Stanton Road, Stapenhill",
    "sg:city":"Burton-on-trent",
    "sg:classifiers":[
        {
            "category":"Farming",
            "subcategory":"Nursery",
            "type":"Manufacturing & Wholesale Goods"
        }
    ],
    "sg:phone":"+44 1283 565069",
    "sg:postcode":"DE15 9RP",
    "sg:province":"Derbyshire",
    "sg:tags":[
        "creche"
    ],
    "wof:name":"Highwood Day Nursery",
    "wof:placetype":"venue"
},
  "geometry": {"coordinates":[-1.619659,52.791512],"type":"Point"}
}