{
  "type": "Feature",
  "properties": {
    "addr:full":"1st Floor, 1-7 Princess St Manchester Greater Manchester M2 4DF",
    "addr:housenumber":"1-7",
    "addr:postcode":"m2 4df",
    "addr:street":"Princess St",
    "iso:country":"GB",
    "sg:address":"1st Floor, 1-7 Princess St",
    "sg:city":"Manchester",
    "sg:classifiers":[
        {
            "category":"Banks & Credit Unions",
            "subcategory":"Bank",
            "type":"Services"
        }
    ],
    "sg:phone":"+44 161 834 6484",
    "sg:postcode":"M2 4DF",
    "sg:province":"Greater Manchester",
    "wof:name":"Northern Rock Commercial Finance",
    "wof:placetype":"venue"
},
  "geometry": {"coordinates":[-2.2450230122,53.480178833],"type":"Point"}
}