{
  "type": "Feature",
  "properties": {
    "addr:full":"199 Burchfield Road, Perry Bar Birmingham West Midlands B19 1LL",
    "addr:housenumber":"199",
    "addr:postcode":"b19 1ll",
    "addr:street":"Burchfield Road",
    "iso:country":"GB",
    "sg:address":"199 Burchfield Road, Perry Bar",
    "sg:city":"Birmingham",
    "sg:classifiers":[
        {
            "category":"Shopping",
            "subcategory":"Pharmacy",
            "type":"Retail Goods"
        }
    ],
    "sg:phone":"+44 121 551 6845",
    "sg:postcode":"B19 1LL",
    "sg:province":"West Midlands",
    "sg:tags":[
        "pharmacist",
        "chemist"
    ],
    "wof:name":"Parade Dispensing Chemist",
    "wof:placetype":"venue"
},
  "geometry": {"coordinates":[-1.9028769732,52.508026123],"type":"Point"}
}