{
  "type": "Feature",
  "properties": {
    "iso:country":"GB",
    "sg:address":"114-116 Stricklandgate",
    "sg:city":"Kendal",
    "sg:classifiers":[
        {
            "category":"Professional",
            "subcategory":"Lawyer & Legal Services",
            "type":"Services"
        }
    ],
    "sg:phone":"+44 1539 721945",
    "sg:postcode":"LA9 4QA",
    "sg:province":"Cumbria",
    "sg:tags":[
        "solicitor"
    ],
    "wof:name":"C G Thomson & Wilson",
    "wof:placetype":"venue"
},
  "geometry": {"coordinates":[-2.747435,54.330284],"type":"Point"}
}