{
  "type": "Feature",
  "properties": {
    "addr:full":"7 West Square Harlow Essex CM20 1NG",
    "addr:housenumber":"7",
    "addr:postcode":"cm20 1ng",
    "addr:street":"West Square",
    "iso:country":"GB",
    "sg:address":"7 West Square",
    "sg:city":"Harlow",
    "sg:classifiers":[
        {
            "category":"Banks & Credit Unions",
            "subcategory":"Financial Services",
            "type":"Services"
        }
    ],
    "sg:phone":"+44 1279 411020",
    "sg:postcode":"CM20 1NG",
    "sg:province":"Essex",
    "sg:tags":[
        "building",
        "society"
    ],
    "wof:name":"Bristol & West Plc",
    "wof:placetype":"venue"
},
  "geometry": {"coordinates":[0.092092,51.770119],"type":"Point"}
}