{
  "type": "Feature",
  "properties": {
    "addr:full":"12 The Broadway Amersham Buckinghamshire HP7 0HP",
    "addr:housenumber":"12",
    "addr:postcode":"hp7 0hp",
    "addr:street":"The Broadway",
    "iso:country":"GB",
    "sg:address":"12 The Broadway",
    "sg:city":"Amersham",
    "sg:classifiers":[
        {
            "category":"Restaurant",
            "type":"Food & Drink"
        }
    ],
    "sg:phone":"+44 1494 725175",
    "sg:postcode":"HP7 0HP",
    "sg:province":"Buckinghamshire",
    "wof:name":"Griffin The",
    "wof:placetype":"venue"
},
  "geometry": {"coordinates":[-0.613270998,51.6656990051],"type":"Point"}
}