{
  "type": "Feature",
  "properties": {
    "addr:full":"Montgomery Street Innerleithen Scottish Borders EH44 6JS",
    "addr:postcode":"eh44 6js",
    "addr:street":"Montgomery Street",
    "iso:country":"GB",
    "sg:address":"Montgomery Street",
    "sg:city":"Innerleithen",
    "sg:classifiers":[
        {
            "category":"Recreation",
            "subcategory":"Campground",
            "type":"Entertainment"
        }
    ],
    "sg:phone":"+44 1896 831271",
    "sg:postcode":"EH44 6JS",
    "sg:province":"Scottish Borders",
    "sg:tags":[
        "caravan",
        "park"
    ],
    "wof:name":"Tweedside Caravan Parks",
    "wof:placetype":"venue"
},
  "geometry": {"coordinates":[-3.052639,55.61969],"type":"Point"}
}