{
  "type": "Feature",
  "properties": {
    "addr:full":"The Depot, Salts Farm, Fawkham Rd Longfield Kent DA3 7BJ",
    "addr:postcode":"da3 7bj",
    "addr:street":"Fawkham Rd",
    "iso:country":"GB",
    "sg:address":"The Depot, Salts Farm, Fawkham Rd",
    "sg:city":"Longfield",
    "sg:classifiers":[
        {
            "category":"Utilities",
            "subcategory":"Fuel Oil & Lpg",
            "type":"Services"
        }
    ],
    "sg:phone":"+44 1474 708801",
    "sg:postcode":"DA3 7BJ",
    "sg:province":"Kent",
    "sg:tags":[
        "distributor"
    ],
    "wof:name":"Crouch & Son",
    "wof:placetype":"venue"
},
  "geometry": {"coordinates":[0.304201,51.392845],"type":"Point"}
}