{
  "type": "Feature",
  "properties": {
    "iso:country":"GB",
    "sg:address":"3 College Street",
    "sg:city":"St Albans",
    "sg:classifiers":[
        {
            "category":"Professional",
            "subcategory":"Accounting & Tax Preparation",
            "type":"Services"
        }
    ],
    "sg:postcode":"AL3 4PW",
    "sg:province":"Hertfordshire",
    "sg:tags":[
        "accountant"
    ],
    "wof:name":"Wilton Mutlow & Co",
    "wof:placetype":"venue"
},
  "geometry": {"coordinates":[-0.342037,51.753487],"type":"Point"}
}