{
  "type": "Feature",
  "properties": {
    "iso:country":"GB",
    "sg:address":"15 Porchester Gardens",
    "sg:city":"London",
    "sg:classifiers":[
        {
            "category":"Health Services",
            "subcategory":"Health Practitioner",
            "type":"Services"
        }
    ],
    "sg:phone":"+44 20 7727 6778",
    "sg:postcode":"W2 4DB",
    "sg:province":"Greater London",
    "sg:tags":[
        "acupuncture"
    ],
    "wof:name":"Lily Cheung",
    "wof:placetype":"venue"
},
  "geometry": {"coordinates":[-0.1882559955,51.5136146545],"type":"Point"}
}