{
  "type": "Feature",
  "properties": {
    "addr:full":"83 Prenton Farm Rd Birkenhead Merseyside L43 3DY",
    "addr:housenumber":"83",
    "addr:postcode":"l43 3dy",
    "addr:street":"Prenton Farm Rd",
    "iso:country":"GB",
    "sg:address":"83 Prenton Farm Rd",
    "sg:city":"Birkenhead",
    "sg:classifiers":[
        {
            "category":"Professional",
            "subcategory":"Management & Consulting",
            "type":"Services"
        }
    ],
    "sg:phone":"+44 151 608 3292",
    "sg:postcode":"L43 3DY",
    "sg:province":"Merseyside",
    "sg:tags":[
        "consultant",
        "specialist"
    ],
    "wof:name":"Essential Beauty & Nails By Ruth",
    "wof:placetype":"venue"
},
  "geometry": {"coordinates":[-3.047832,53.365086],"type":"Point"}
}