{
  "type": "Feature",
  "properties": {
    "addr:full":"Unit 8, New Enterprise Centre, Monmore Rd Wolverhampton West Midlands WV1 2TZ",
    "addr:housenumber":"unit 8",
    "addr:postcode":"wv1 2tz",
    "addr:street":"New Enterprise Centre Monmore Rd",
    "iso:country":"GB",
    "sg:address":"Unit 8, New Enterprise Centre, Monmore Rd",
    "sg:city":"Wolverhampton",
    "sg:classifiers":[
        {
            "category":"Shopping",
            "subcategory":"Computers & Home Electronics",
            "type":"Retail Goods"
        }
    ],
    "sg:phone":"+44 1902 494848",
    "sg:postcode":"WV1 2TZ",
    "sg:province":"West Midlands",
    "wof:name":"Ribbon Revival",
    "wof:placetype":"venue"
},
  "geometry": {"coordinates":[-2.121669054,52.5886497498],"type":"Point"}
}