{
  "type": "Feature",
  "properties": {
    "addr:full":"19 London Road Sandy Bedfordshire SG19 1HA",
    "addr:housenumber":"19",
    "addr:postcode":"sg19 1ha",
    "addr:street":"London Road",
    "iso:country":"GB",
    "sg:address":"19 London Road",
    "sg:city":"Sandy",
    "sg:classifiers":[
        {
            "category":"Professional",
            "subcategory":"Art Services",
            "type":"Services"
        }
    ],
    "sg:phone":"+44 1767 683829",
    "sg:postcode":"SG19 1HA",
    "sg:province":"Bedfordshire",
    "sg:tags":[
        "consultant",
        "design"
    ],
    "wof:name":"Preview Systems Ltd.",
    "wof:placetype":"venue"
},
  "geometry": {"coordinates":[-0.2992149889,52.1302223206],"type":"Point"}
}