{
  "type": "Feature",
  "properties": {
    "addr:full":"78 Uphill Way Weston Super Mare Somerset BS23 4TN",
    "addr:housenumber":"78",
    "addr:postcode":"bs23 4tn",
    "addr:street":"Uphill Way",
    "iso:country":"GB",
    "sg:address":"78 Uphill Way",
    "sg:city":"Weston Super Mare",
    "sg:classifiers":[
        {
            "category":"Building & Trades",
            "subcategory":"Construction",
            "type":"Services"
        }
    ],
    "sg:phone":"+44 1934 635181",
    "sg:postcode":"BS23 4TN",
    "sg:province":"Somerset",
    "sg:tags":[
        "window",
        "replacement"
    ],
    "wof:name":"Weatherguard",
    "wof:placetype":"venue"
},
  "geometry": {"coordinates":[-2.981317997,51.3213272095],"type":"Point"}
}