{
  "type": "Feature",
  "properties": {
    "iso:country":"GB",
    "sg:address":"Paradise Park, White Stubbs Lane",
    "sg:city":"Broxbourne",
    "sg:classifiers":[
        {
            "category":"Bus Charters",
            "type":"Transportation"
        }
    ],
    "sg:phone":"+44 1992 471964",
    "sg:postcode":"EN10 7QA",
    "sg:province":"Essex",
    "sg:tags":[
        "hire",
        "coach"
    ],
    "wof:name":"Parkside Travel",
    "wof:placetype":"venue"
},
  "geometry": {"coordinates":[-0.049724,51.743641],"type":"Point"}
}