{
  "type": "Feature",
  "properties": {
    "iso:country":"GB",
    "sg:address":"40 Main Street, New Abbey",
    "sg:city":"Dumfries",
    "sg:classifiers":[
        {
            "category":"Wholesale",
            "subcategory":"Farm Supplies",
            "type":"Manufacturing & Wholesale Goods"
        },
        {
            "category":"Wholesale",
            "subcategory":"Construction Materials",
            "type":"Manufacturing & Wholesale Goods"
        }
    ],
    "sg:phone":"+44 1387 850282",
    "sg:postcode":"DG2 8BY",
    "sg:province":"Dumfries and Galloway",
    "sg:tags":[
        "merchant",
        "grain",
        "sawmill",
        "activity"
    ],
    "wof:name":"James Kingan & Sons Ltd.",
    "wof:placetype":"venue"
},
  "geometry": {"coordinates":[-3.616181,54.977833],"type":"Point"}
}