{
  "type": "Feature",
  "properties": {
    "addr:full":"The Vicarage, Brynna Rd Pontyclun Bridgend CF72 9QE",
    "addr:postcode":"cf72 9qe",
    "addr:street":"Brynna Rd",
    "iso:country":"GB",
    "sg:address":"The Vicarage, Brynna Rd",
    "sg:city":"Pontyclun",
    "sg:classifiers":[
        {
            "category":"Place Of Worship",
            "type":"Public Place"
        }
    ],
    "sg:phone":"+44 1443 226307",
    "sg:postcode":"CF72 9QE",
    "sg:province":"Bridgend",
    "wof:name":"Llanaran Parish Church",
    "wof:placetype":"venue"
},
  "geometry": {"coordinates":[-3.3920590878,51.5222854614],"type":"Point"}
}