{
  "type": "Feature",
  "properties": {
    "addr:full":"Butterfield Lodge, Butterfield Chase Chelmsford Essex CM3 6LE",
    "addr:postcode":"cm3 6le",
    "addr:street":"Butterfield Chase",
    "iso:country":"GB",
    "sg:address":"Butterfield Lodge, Butterfield Chase",
    "sg:city":"Chelmsford",
    "sg:classifiers":[
        {
            "category":"Professional",
            "subcategory":"Lawyer & Legal Services",
            "type":"Services"
        }
    ],
    "sg:phone":"+44 1621 741098",
    "sg:postcode":"CM3 6LE",
    "sg:province":"Essex",
    "sg:tags":[
        "advice",
        "counselling"
    ],
    "wof:name":"Leah Betts Helpline Action For Drugs Awareness",
    "wof:placetype":"venue"
},
  "geometry": {"coordinates":[0.7209399939,51.6768798828],"type":"Point"}
}