{
  "type": "Feature",
  "properties": {
    "addr:full":"85 Maidenhead Rd Windsor Berkshire SL4 5EJ",
    "addr:housenumber":"85",
    "addr:postcode":"sl4 5ej",
    "addr:street":"Maidenhead Rd",
    "iso:country":"GB",
    "sg:address":"85 Maidenhead Rd",
    "sg:city":"Windsor",
    "sg:classifiers":[
        {
            "category":"Building & Trades",
            "subcategory":"Construction",
            "type":"Services"
        }
    ],
    "sg:phone":"+44 1753 858545",
    "sg:postcode":"SL4 5EJ",
    "sg:province":"Berkshire",
    "sg:tags":[
        "excavation",
        "groundwork",
        "contractor"
    ],
    "wof:name":"J.W Plant Services",
    "wof:placetype":"venue"
},
  "geometry": {"coordinates":[-0.6251829863,51.4836425781],"type":"Point"}
}