{
  "type": "Feature",
  "properties": {
    "addr:full":"St Clairs Cottage, Greenbank Road, Glenfarg Perth Perth and Kinross PH2 9NR",
    "addr:postcode":"ph2 9nr",
    "addr:street":"St;Greenbank Road",
    "iso:country":"GB",
    "sg:address":"St Clairs Cottage, Greenbank Road, Glenfarg",
    "sg:city":"Perth",
    "sg:classifiers":[
        {
            "category":"Professional",
            "type":"Services"
        }
    ],
    "sg:phone":"+44 1577 830820",
    "sg:postcode":"PH2 9NR",
    "sg:province":"Perth and Kinross",
    "sg:tags":[
        "repair",
        "tech",
        "maintenance"
    ],
    "wof:name":"Straitway",
    "wof:placetype":"venue"
},
  "geometry": {"coordinates":[-3.3986430168,56.2783546448],"type":"Point"}
}