{
  "type": "Feature",
  "properties": {
    "iso:country":"GB",
    "sg:address":"7 The Parade, Donnington",
    "sg:city":"Telford",
    "sg:classifiers":[
        {
            "category":"Personal",
            "subcategory":"Beauty Salon",
            "type":"Services"
        }
    ],
    "sg:phone":"+44 1952 604253",
    "sg:postcode":"TF2 8EB",
    "sg:province":"Shropshire",
    "sg:tags":[
        "unisex",
        "hairdresser"
    ],
    "wof:name":"The Cutting Edge",
    "wof:placetype":"venue"
},
  "geometry": {"coordinates":[-2.439414,52.716915],"type":"Point"}
}