{
  "type": "Feature",
  "properties": {
    "iso:country":"GB",
    "sg:address":"Unit 3 Regal Road",
    "sg:city":"Wisbech",
    "sg:classifiers":[
        {
            "category":"Wholesale",
            "subcategory":"Electrical",
            "type":"Manufacturing & Wholesale Goods"
        },
        {
            "category":"Shopping",
            "subcategory":"Computers & Home Electronics",
            "type":"Retail Goods"
        }
    ],
    "sg:phone":"+44 1945 583712",
    "sg:postcode":"PE13 2RQ",
    "sg:province":"Cambridgeshire",
    "sg:tags":[
        "wholesaler"
    ],
    "wof:name":"Newey & Eyre Ltd",
    "wof:placetype":"venue"
},
  "geometry": {"coordinates":[0.1567000002,52.6538963318],"type":"Point"}
}