{
  "type": "Feature",
  "properties": {
    "iso:country":"GB",
    "sg:address":"Unit 11, In Shop, 35-43 High Rd, Wealdstone",
    "sg:city":"Harrow",
    "sg:classifiers":[
        {
            "category":"Banks & Credit Unions",
            "subcategory":"Financial Services",
            "type":"Services"
        }
    ],
    "sg:phone":"+44 20 8427 7887",
    "sg:postcode":"HA3 5DE",
    "sg:province":"Greater London",
    "sg:tags":[
        "cashing",
        "cheque"
    ],
    "wof:name":"C-4-c",
    "wof:placetype":"venue"
},
  "geometry": {"coordinates":[-0.335298,51.596008],"type":"Point"}
}