{
  "type": "Feature",
  "properties": {
    "addr:full":"The Cottage, 4 Church La Melton Mowbray Leicestershire LE14 2HW",
    "addr:housenumber":"4",
    "addr:postcode":"le14 2hw",
    "addr:street":"Church La",
    "iso:country":"GB",
    "sg:address":"The Cottage, 4 Church La",
    "sg:city":"Melton Mowbray",
    "sg:classifiers":[
        {
            "category":"Manufacturing",
            "subcategory":"Petroleum Products",
            "type":"Manufacturing & Wholesale Goods"
        }
    ],
    "sg:phone":"+44 1664 840580",
    "sg:postcode":"LE14 2HW",
    "sg:province":"Leicestershire",
    "sg:tags":[
        "double",
        "glazing"
    ],
    "wof:name":"Tony Wilkinson",
    "wof:placetype":"venue"
},
  "geometry": {"coordinates":[-0.92074,52.68362],"type":"Point"}
}