{
  "type": "Feature",
  "properties": {
    "addr:full":"Unit 1 Mussons Path Luton Bedfordshire LU2 7RQ",
    "addr:housenumber":"unit 1",
    "addr:postcode":"lu2 7rq",
    "addr:street":"Mussons Path",
    "iso:country":"GB",
    "sg:address":"Unit 1 Mussons Path",
    "sg:city":"Luton",
    "sg:classifiers":[
        {
            "category":"Retail",
            "subcategory":"Auto Repair",
            "type":"Services"
        }
    ],
    "sg:phone":"+44 1582 400117",
    "sg:postcode":"LU2 7RQ",
    "sg:province":"Bedfordshire",
    "sg:tags":[
        "modification",
        "garage"
    ],
    "wof:name":"Aston Garages",
    "wof:placetype":"venue"
},
  "geometry": {"coordinates":[-0.413643986,51.8864440918],"type":"Point"}
}