{
  "type": "Feature",
  "properties": {
    "iso:country":"GB",
    "sg:address":"60 Osmaston Road",
    "sg:city":"Derby",
    "sg:classifiers":[
        {
            "category":"Taxi",
            "type":"Transportation"
        }
    ],
    "sg:phone":"+44 1332 331331",
    "sg:postcode":"DE1 2HZ",
    "sg:province":"Derbyshire",
    "sg:tags":[
        "mini",
        "cab"
    ],
    "wof:name":"Western Car Co Ltd",
    "wof:placetype":"venue"
},
  "geometry": {"coordinates":[-1.474577,52.917736],"type":"Point"}
}