{
  "type": "Feature",
  "properties": {
    "addr:full":"86 Dalrymple Street Girvan South Ayrshire KA26 9BT",
    "addr:housenumber":"86",
    "addr:postcode":"ka26 9bt",
    "addr:street":"Dalrymple Street",
    "iso:country":"GB",
    "sg:address":"86 Dalrymple Street",
    "sg:city":"Girvan",
    "sg:classifiers":[
        {
            "category":"Farming",
            "subcategory":"Fish & Marine Products",
            "type":"Manufacturing & Wholesale Goods"
        },
        {
            "category":"Food & Beverages",
            "subcategory":"Meat & Fish",
            "type":"Retail Goods"
        }
    ],
    "sg:phone":"+44 1465 713132",
    "sg:postcode":"KA26 9BT",
    "sg:province":"South Ayrshire",
    "sg:tags":[
        "fishmonger",
        "butcher"
    ],
    "wof:name":"Allan & Son",
    "wof:placetype":"venue"
},
  "geometry": {"coordinates":[-4.8556637764,55.240978241],"type":"Point"}
}