{
  "type": "Feature",
  "properties": {
    "addr:full":"12 Grosvenor Road, Jesmond Newcastle-upon-tyne Tyne and Wear NE2 2RP",
    "addr:housenumber":"12",
    "addr:postcode":"ne2 2rp",
    "addr:street":"Grosvenor Road",
    "iso:country":"GB",
    "sg:address":"12 Grosvenor Road, Jesmond",
    "sg:city":"Newcastle-upon-tyne",
    "sg:classifiers":[
        {
            "category":"Fast Food",
            "type":"Food & Drink"
        }
    ],
    "sg:phone":"+44 191 281 2372",
    "sg:postcode":"NE2 2RP",
    "sg:province":"Tyne and Wear",
    "sg:tags":[
        "away",
        "take"
    ],
    "wof:name":"Futurenorth Ltd.",
    "wof:placetype":"venue"
},
  "geometry": {"coordinates":[-1.600434,54.991653],"type":"Point"}
}