{
  "type": "Feature",
  "properties": {
    "addr:full":"40 Eastgate Leeds West Yorkshire LS2 7JJ",
    "addr:housenumber":"40",
    "addr:postcode":"ls2 7jj",
    "addr:street":"Eastgate Leeds West",
    "iso:country":"GB",
    "sg:address":"40 Eastgate",
    "sg:city":"Leeds",
    "sg:classifiers":[
        {
            "category":"Professional",
            "subcategory":"Art Services",
            "type":"Services"
        }
    ],
    "sg:phone":"+44 113 246 0665",
    "sg:postcode":"LS2 7JJ",
    "sg:province":"West Yorkshire",
    "sg:tags":[
        "framing"
    ],
    "wof:name":"Frame It",
    "wof:placetype":"venue"
},
  "geometry": {"coordinates":[-1.536954,53.798512],"type":"Point"}
}