{
  "type": "Feature",
  "properties": {
    "iso:country":"GB",
    "sg:address":"Brookes Avenue, Croft",
    "sg:city":"Leicester",
    "sg:classifiers":[
        {
            "category":"Education",
            "subcategory":"School",
            "type":"Public Place"
        }
    ],
    "sg:phone":"+44 1455 282643",
    "sg:postcode":"LE9 3GJ",
    "sg:province":"Leicestershire",
    "sg:tags":[
        "local",
        "authority"
    ],
    "wof:name":"Croft Church of England Primary School",
    "wof:placetype":"venue"
},
  "geometry": {"coordinates":[-1.23991,52.554607],"type":"Point"}
}