{
  "type": "Feature",
  "properties": {
    "addr:full":"6 Abbotts Close Cheltenham Gloucestershire GL51 3DX",
    "addr:housenumber":"6",
    "addr:postcode":"gl51 3dx",
    "addr:street":"Abbotts Close",
    "iso:country":"GB",
    "sg:address":"6 Abbotts Close",
    "sg:city":"Cheltenham",
    "sg:classifiers":[
        {
            "category":"Community Center",
            "subcategory":"Youth",
            "type":"Public Place"
        }
    ],
    "sg:postcode":"GL51 3DX",
    "sg:province":"Gloucestershire",
    "sg:tags":[
        "organisation",
        "centre"
    ],
    "wof:name":"The Campaigners",
    "wof:placetype":"venue"
},
  "geometry": {"coordinates":[-2.094473,51.881611],"type":"Point"}
}