{
  "type": "Feature",
  "properties": {
    "iso:country":"GB",
    "sg:address":"238 Winchester Road",
    "sg:city":"Southampton",
    "sg:classifiers":[
        {
            "category":"Utilities",
            "subcategory":"Telephone",
            "type":"Services"
        },
        {
            "category":"Communications",
            "type":"Services"
        }
    ],
    "sg:phone":"+44 23 8090 2900",
    "sg:postcode":"SO16 6YA",
    "sg:province":"Hampshire",
    "sg:tags":[
        "telecommunication"
    ],
    "wof:name":"Thornton Communications Ltd.",
    "wof:placetype":"venue"
},
  "geometry": {"coordinates":[-1.426748,50.929996],"type":"Point"}
}