{
  "type": "Feature",
  "properties": {
    "iso:country":"GB",
    "sg:address":"1 Freesia Close",
    "sg:city":"Orpington",
    "sg:classifiers":[
        {
            "category":"Real Estate",
            "subcategory":"Surveying",
            "type":"Services"
        }
    ],
    "sg:postcode":"BR6 6NB",
    "sg:province":"Kent",
    "sg:tags":[
        "surveyor",
        "valuer"
    ],
    "wof:name":"T J Consultants",
    "wof:placetype":"venue"
},
  "geometry": {"coordinates":[0.0905300006,51.3577346802],"type":"Point"}
}