{
  "type": "Feature",
  "properties": {
    "addr:full":"Guernsey Farm, Yapton Road Bognor Regis West Sussex PO22 6DY",
    "addr:postcode":"po22 6dy",
    "addr:street":"Yapton Road",
    "iso:country":"GB",
    "sg:address":"Guernsey Farm, Yapton Road",
    "sg:city":"Bognor Regis",
    "sg:classifiers":[
        {
            "category":"Food & Beverages",
            "subcategory":"Farmers Market",
            "type":"Retail Goods"
        }
    ],
    "sg:postcode":"PO22 6DY",
    "sg:province":"West Sussex",
    "sg:tags":[
        "farm",
        "shop",
        "pyo"
    ],
    "wof:name":"Middleton Farm Shop",
    "wof:placetype":"venue"
},
  "geometry": {"coordinates":[-0.632379,50.795376],"type":"Point"}
}