{
  "type": "Feature",
  "properties": {
    "iso:country":"GB",
    "sg:address":"Southfields Farm, Packington Lane, Coleshill",
    "sg:city":"Birmingham",
    "sg:classifiers":[
        {
            "category":"Professional",
            "subcategory":"Computer Services",
            "type":"Services"
        }
    ],
    "sg:phone":"+44 1675 463879",
    "sg:postcode":"B46 3EJ",
    "sg:province":"Warwickshire",
    "sg:tags":[
        "system",
        "software"
    ],
    "wof:name":"Adweb",
    "wof:placetype":"venue"
},
  "geometry": {"coordinates":[-1.70588,52.489445],"type":"Point"}
}