{
  "type": "Feature",
  "properties": {
    "addr:full":"41 Kiddemore Green Road, Brewood Stafford Shropshire ST19 9BQ",
    "addr:housenumber":"41",
    "addr:postcode":"st19 9bq",
    "addr:street":"Kiddemore Green Road",
    "iso:country":"GB",
    "sg:address":"41 Kiddemore Green Road, Brewood",
    "sg:city":"Stafford",
    "sg:classifiers":[
        {
            "category":"Building & Trades",
            "subcategory":"Landscaping Services",
            "type":"Services"
        }
    ],
    "sg:phone":"+44 1902 850714",
    "sg:postcode":"ST19 9BQ",
    "sg:province":"Shropshire",
    "sg:tags":[
        "forestry",
        "tree"
    ],
    "wof:name":"Brewood Tree Services",
    "wof:placetype":"venue"
},
  "geometry": {"coordinates":[-2.1970069408,52.6767349243],"type":"Point"}
}