{
  "type": "Feature",
  "properties": {
    "iso:country":"GB",
    "sg:address":"26 Hawthorn Villas",
    "sg:city":"Cramlington",
    "sg:classifiers":[
        {
            "category":"Home & Garden",
            "subcategory":"Carpets & Floor Coverings",
            "type":"Retail Goods"
        }
    ],
    "sg:phone":"+44 1670 714650",
    "sg:postcode":"NE23 9AE",
    "sg:province":"Northumberland",
    "sg:tags":[
        "cleaner",
        "upholstery"
    ],
    "wof:name":"Powerclean",
    "wof:placetype":"venue"
},
  "geometry": {"coordinates":[-1.5703810453,55.0843887329],"type":"Point"}
}