{
  "type": "Feature",
  "properties": {
    "iso:country":"GB",
    "sg:address":"The Haugh, Carnbo",
    "sg:city":"Kinross",
    "sg:classifiers":[
        {
            "category":"Professional",
            "subcategory":"Engineering",
            "type":"Services"
        }
    ],
    "sg:postcode":"KY13 0NX",
    "sg:province":"Clackmannanshire",
    "sg:tags":[
        "consulting",
        "engineer"
    ],
    "wof:name":"Read Associates",
    "wof:placetype":"venue"
},
  "geometry": {"coordinates":[-3.5298500061,56.2106208801],"type":"Point"}
}