{
  "type": "Feature",
  "properties": {
    "addr:full":"Unit 3 Garvis Business Park, Highland Road Glasgow East Dunbartonshire G62 8NY",
    "addr:housenumber":"unit 3",
    "addr:postcode":"g62 8ny",
    "addr:street":"Garvis Business Park Highland Road",
    "iso:country":"GB",
    "sg:address":"Unit 3 Garvis Business Park, Highland Road",
    "sg:city":"Glasgow",
    "sg:classifiers":[
        {
            "category":"Parking",
            "type":"Transportation"
        }
    ],
    "sg:postcode":"G62 8NY",
    "sg:province":"East Dunbartonshire",
    "sg:tags":[
        "car",
        "valet"
    ],
    "wof:name":"Kevin Thomson",
    "wof:placetype":"venue"
},
  "geometry": {"coordinates":[-4.3182001114,55.9442405701],"type":"Point"}
}