{
  "type": "Feature",
  "properties": {
    "addr:full":"Cannon Street Ho, Cannon St Louth Lincolnshire LN11 9NL",
    "addr:postcode":"ln11 9nl",
    "addr:street":"Cannon Street;Cannon St Louth",
    "iso:country":"GB",
    "sg:address":"Cannon Street Ho, Cannon St",
    "sg:city":"Louth",
    "sg:classifiers":[
        {
            "category":"Professional",
            "subcategory":"Computer Services",
            "type":"Services"
        }
    ],
    "sg:phone":"+44 1507 601729",
    "sg:postcode":"LN11 9NL",
    "sg:province":"Lincolnshire",
    "sg:tags":[
        "system",
        "software"
    ],
    "wof:name":"Lindum Computer Systems",
    "wof:placetype":"venue"
},
  "geometry": {"coordinates":[-0.005204,53.367451],"type":"Point"}
}