{
  "type": "Feature",
  "properties": {
    "addr:full":"Birchwood Gairloch Highland IV21 2AH",
    "addr:postcode":"iv21 2ah",
    "addr:street":"Birchwood Gairloch",
    "iso:country":"GB",
    "sg:address":"Birchwood",
    "sg:city":"Gairloch",
    "sg:classifiers":[
        {
            "category":"Travel",
            "subcategory":"Hotels & Motels",
            "type":"Entertainment"
        }
    ],
    "sg:postcode":"IV21 2AH",
    "sg:province":"Highland",
    "sg:tags":[
        "house",
        "guest"
    ],
    "wof:name":"Birchwood Guest House",
    "wof:placetype":"venue"
},
  "geometry": {"coordinates":[-5.693689,57.728615],"type":"Point"}
}