{
  "type": "Feature",
  "properties": {
    "addr:full":"High Street, Nutfield Redhill Surrey RH1 4HH",
    "addr:postcode":"rh1 4hh",
    "addr:street":"High Street;Redhill",
    "iso:country":"GB",
    "sg:address":"High Street, Nutfield",
    "sg:city":"Redhill",
    "sg:classifiers":[
        {
            "category":"Bars & Pubs",
            "type":"Food & Drink"
        }
    ],
    "sg:phone":"+44 1737 822252",
    "sg:postcode":"RH1 4HH",
    "sg:province":"Surrey",
    "sg:tags":[
        "pubs",
        "inn"
    ],
    "wof:name":"Dean Edward Pate",
    "wof:placetype":"venue"
},
  "geometry": {"coordinates":[-0.1007739976,51.2406616211],"type":"Point"}
}