{
  "type": "Feature",
  "properties": {
    "addr:full":"21 Bradbury Lane Cannock Staffordshire WS12 4EH",
    "addr:housenumber":"21",
    "addr:postcode":"ws12 4eh",
    "addr:street":"Bradbury Lane",
    "iso:country":"GB",
    "sg:address":"21 Bradbury Lane",
    "sg:city":"Cannock",
    "sg:classifiers":[
        {
            "category":"Shopping",
            "subcategory":"Department Store",
            "type":"Retail Goods"
        }
    ],
    "sg:phone":"+44 1543 422603",
    "sg:postcode":"WS12 4EH",
    "sg:province":"Staffordshire",
    "wof:name":"Kashmer Singh",
    "wof:placetype":"venue"
},
  "geometry": {"coordinates":[-1.9996409416,52.7180099487],"type":"Point"}
}