{
  "type": "Feature",
  "properties": {
    "addr:full":"24a St John Street London Greater London EC1M 4AY",
    "addr:housenumber":"24a",
    "addr:postcode":"ec1m 4ay",
    "addr:street":"St John Street",
    "iso:country":"GB",
    "sg:address":"24a St John Street",
    "sg:city":"London",
    "sg:classifiers":[
        {
            "category":"Professional",
            "subcategory":"Art Services",
            "type":"Services"
        }
    ],
    "sg:phone":"+44 20 7490 1144",
    "sg:postcode":"EC1M 4AY",
    "sg:province":"Greater London",
    "sg:tags":[
        "consultant",
        "design"
    ],
    "wof:name":"Lee Design Services Ltd.",
    "wof:placetype":"venue"
},
  "geometry": {"coordinates":[-0.1015169993,51.5203132629],"type":"Point"}
}