{
  "type": "Feature",
  "properties": {
    "iso:country":"GB",
    "sg:address":"Elmridge",
    "sg:city":"Leigh",
    "sg:classifiers":[
        {
            "category":"Manufacturing",
            "subcategory":"Petroleum Products",
            "type":"Manufacturing & Wholesale Goods"
        }
    ],
    "sg:phone":"+44 1942 200888",
    "sg:postcode":"WN7 1HN",
    "sg:province":"Lancashire",
    "sg:tags":[
        "double",
        "glazing"
    ],
    "wof:name":"Lakeside Associates & Classic Improvements",
    "wof:placetype":"venue"
},
  "geometry": {"coordinates":[-2.504989,53.502888],"type":"Point"}
}