{
  "type": "Feature",
  "properties": {
    "iso:country":"GB",
    "sg:address":"35 Davies St",
    "sg:city":"London",
    "sg:classifiers":[
        {
            "category":"Communications",
            "type":"Services"
        }
    ],
    "sg:phone":"+44 20 8215 0118",
    "sg:postcode":"W1K 4LS",
    "sg:province":"Greater London",
    "sg:tags":[
        "audio-visual"
    ],
    "wof:name":"Shirley,Edwin,Productions Ltd",
    "wof:placetype":"venue"
},
  "geometry": {"coordinates":[-0.148164,51.512005],"type":"Point"}
}