{
  "type": "Feature",
  "properties": {
    "addr:full":"20 Tamblyn Close, Radstock Bath Somerset BA3 3JA",
    "addr:housenumber":"20",
    "addr:postcode":"ba3 3ja",
    "addr:street":"Tamblyn Close",
    "iso:country":"GB",
    "sg:address":"20 Tamblyn Close, Radstock",
    "sg:city":"Bath",
    "sg:classifiers":[
        {
            "category":"Building & Trades",
            "subcategory":"Construction",
            "type":"Services"
        }
    ],
    "sg:postcode":"BA3 3JA",
    "sg:province":"Somerset",
    "sg:tags":[
        "roofing"
    ],
    "wof:name":"P Starr Construction",
    "wof:placetype":"venue"
},
  "geometry": {"coordinates":[-2.4440898895,51.2962913513],"type":"Point"}
}