{
  "type": "Feature",
  "properties": {
    "iso:country":"GB",
    "sg:address":"39 Streatham Rd",
    "sg:city":"Mitcham",
    "sg:classifiers":[
        {
            "category":"Retail",
            "subcategory":"Auto Repair",
            "type":"Services"
        }
    ],
    "sg:postcode":"CR4 2AD",
    "sg:province":"Greater London",
    "sg:tags":[
        "modification",
        "garage"
    ],
    "wof:name":"Mitcham Lada Specialists",
    "wof:placetype":"venue"
},
  "geometry": {"coordinates":[-0.158306,51.412266],"type":"Point"}
}