{
  "type": "Feature",
  "properties": {
    "iso:country":"GB",
    "sg:address":"Ridge Avenue, Winchmore Hill",
    "sg:city":"London",
    "sg:classifiers":[
        {
            "category":"Arena",
            "subcategory":"Sports Club",
            "type":"Entertainment"
        }
    ],
    "sg:phone":"+44 20 8360 1384",
    "sg:postcode":"N21 2AJ",
    "sg:province":"Greater London",
    "wof:name":"Hazelwood Lawn Tennis & Squash Club Ltd.",
    "wof:placetype":"venue"
},
  "geometry": {"coordinates":[-0.08851,51.636211],"type":"Point"}
}