{
  "type": "Feature",
  "properties": {
    "addr:full":"Unit 1, Manway Business Park, Canal Road Knutsford Cheshire WA14 1TD",
    "addr:housenumber":"unit 1",
    "addr:postcode":"wa14 1td",
    "addr:street":"Manway Business Park Canal Road",
    "iso:country":"GB",
    "sg:address":"Unit 1, Manway Business Park, Canal Road",
    "sg:city":"Knutsford",
    "sg:classifiers":[
        {
            "category":"Retail",
            "subcategory":"Auto Repair",
            "type":"Services"
        }
    ],
    "sg:postcode":"WA14 1TD",
    "sg:province":"Cheshire",
    "sg:tags":[
        "modification",
        "garage"
    ],
    "wof:name":"A P Needham",
    "wof:placetype":"venue"
},
  "geometry": {"coordinates":[-2.34204,53.401531],"type":"Point"}
}