{
  "type": "Feature",
  "properties": {
    "iso:country":"GB",
    "sg:address":"Reperry, Lanivet",
    "sg:city":"Bodmin",
    "sg:classifiers":[
        {
            "category":"Retail",
            "subcategory":"Laundry & Dry Cleaning",
            "type":"Services"
        }
    ],
    "sg:phone":"+44 1208 831369",
    "sg:postcode":"PL30 5JD",
    "sg:province":"Cornwall",
    "sg:tags":[
        "straw",
        "hay"
    ],
    "wof:name":"Jack Kingdon Plant Hire",
    "wof:placetype":"venue"
},
  "geometry": {"coordinates":[-4.7638411522,50.4403686523],"type":"Point"}
}