{
  "type": "Feature",
  "properties": {
    "iso:country":"GB",
    "sg:address":"21 Northenden Road",
    "sg:city":"Sale",
    "sg:classifiers":[
        {
            "category":"Shopping",
            "subcategory":"Florist",
            "type":"Retail Goods"
        }
    ],
    "sg:phone":"+44 161 973 7137",
    "sg:postcode":"M33 2DH",
    "sg:province":"Cheshire",
    "wof:name":"CRAGGS OF SALE",
    "wof:placetype":"venue"
},
  "geometry": {"coordinates":[-2.3151080608,53.4235839844],"type":"Point"}
}