{
  "type": "Feature",
  "properties": {
    "addr:full":"4 Nags Corner, Wiston Road, Nayland Colchester Essex CO6 4LT",
    "addr:postcode":"co6 4lt",
    "addr:street":"Nags Corner Wiston Road Nayland Colchester",
    "iso:country":"GB",
    "sg:address":"4 Nags Corner, Wiston Road, Nayland",
    "sg:city":"Colchester",
    "sg:classifiers":[
        {
            "category":"Education",
            "subcategory":"Special Training",
            "type":"Public Place"
        }
    ],
    "sg:phone":"+44 1206 263007",
    "sg:postcode":"CO6 4LT",
    "sg:province":"Essex",
    "sg:tags":[
        "product",
        "centre"
    ],
    "wof:name":"Change Winners Ltd.",
    "wof:placetype":"venue"
},
  "geometry": {"coordinates":[0.8717740178,51.972328186],"type":"Point"}
}