{
  "type": "Feature",
  "properties": {
    "addr:full":"23 Glenroyd Gardens Bournemouth Dorset BH6 3JN",
    "addr:housenumber":"23",
    "addr:postcode":"bh6 3jn",
    "addr:street":"Glenroyd Gardens",
    "iso:country":"GB",
    "sg:address":"23 Glenroyd Gardens",
    "sg:city":"Bournemouth",
    "sg:classifiers":[
        {
            "category":"Building & Trades",
            "subcategory":"Construction",
            "type":"Services"
        }
    ],
    "sg:postcode":"BH6 3JN",
    "sg:province":"Dorset",
    "sg:tags":[
        "builder"
    ],
    "wof:name":"John Francis Dewhirst",
    "wof:placetype":"venue"
},
  "geometry": {"coordinates":[-1.802173,50.727013],"type":"Point"}
}