{
  "type": "Feature",
  "properties": {
    "addr:full":"9 Oakland Rd Leicester Leicestershire LE2 6AN",
    "addr:housenumber":"9",
    "addr:postcode":"le2 6an",
    "addr:street":"Oakland Rd",
    "iso:country":"GB",
    "sg:address":"9 Oakland Rd",
    "sg:city":"Leicester",
    "sg:classifiers":[
        {
            "category":"Autos & Motor Vehicles",
            "subcategory":"Auto Supplies",
            "type":"Retail Goods"
        }
    ],
    "sg:phone":"+44 116 270 8146",
    "sg:postcode":"LE2 6AN",
    "sg:province":"Leicestershire",
    "sg:tags":[
        "car",
        "audio"
    ],
    "wof:name":"Car Radio Services",
    "wof:placetype":"venue"
},
  "geometry": {"coordinates":[-1.124949,52.614498],"type":"Point"}
}