{
  "type": "Feature",
  "properties": {
    "iso:country":"GB",
    "sg:address":"57 Market Street",
    "sg:city":"Alfreton",
    "sg:classifiers":[
        {
            "category":"Food & Beverages",
            "subcategory":"Meat & Fish",
            "type":"Retail Goods"
        }
    ],
    "sg:postcode":"DE55 2AB",
    "sg:province":"Derbyshire",
    "sg:tags":[
        "butcher"
    ],
    "wof:name":"A Stoppard & Sons",
    "wof:placetype":"venue"
},
  "geometry": {"coordinates":[-1.3436620235,53.1025276184],"type":"Point"}
}