{
  "type": "Feature",
  "properties": {
    "iso:country":"GB",
    "sg:address":"5 Carlton Drive",
    "sg:city":"Leigh-on-sea",
    "sg:classifiers":[
        {
            "category":"Communications",
            "subcategory":"Film & Video Production",
            "type":"Services"
        }
    ],
    "sg:phone":"+44 1702 480884",
    "sg:postcode":"SS9 1DE",
    "sg:province":"Essex",
    "sg:tags":[
        "illustrator",
        "artist"
    ],
    "wof:name":"Art House",
    "wof:placetype":"venue"
},
  "geometry": {"coordinates":[0.665095,51.543056],"type":"Point"}
}