{
  "type": "Feature",
  "properties": {
    "addr:full":"Units 12 & 13, Bentley Lane Industrial Park, Bentley Lane Walsall West Midlands WS2 8TW",
    "addr:housenumber":"units 12 & 13",
    "addr:postcode":"ws2 8tw",
    "addr:street":"Bentley Lane Industrial Park Bentley Lane",
    "iso:country":"GB",
    "sg:address":"Units 12 & 13, Bentley Lane Industrial Park, Bentley Lane",
    "sg:city":"Walsall",
    "sg:classifiers":[
        {
            "category":"Manufacturing",
            "subcategory":"Tools & Machinery",
            "type":"Manufacturing & Wholesale Goods"
        }
    ],
    "sg:phone":"+44 1922 639864",
    "sg:postcode":"WS2 8TW",
    "sg:province":"West Midlands",
    "sg:tags":[
        "design",
        "maker"
    ],
    "wof:name":"Coldform Tools (Walsall) Ltd.",
    "wof:placetype":"venue"
},
  "geometry": {"coordinates":[-2.0078799725,52.5922012329],"type":"Point"}
}