{
  "type": "Feature",
  "properties": {
    "iso:country":"GB",
    "sg:address":"Yew House, 26 The Heath",
    "sg:city":"Caterham",
    "sg:classifiers":[
        {
            "category":"Building & Trades",
            "subcategory":"Construction",
            "type":"Services"
        }
    ],
    "sg:postcode":"CR3 5DG",
    "sg:province":"Surrey",
    "sg:tags":[
        "roofing",
        "ceiling",
        "contractor"
    ],
    "wof:name":"Charles R Loyd",
    "wof:placetype":"venue"
},
  "geometry": {"coordinates":[-0.1034940034,51.2796363831],"type":"Point"}
}