{
  "type": "Feature",
  "properties": {
    "addr:full":"Glebe House, The Manor Beeches York North Yorkshire YO19 5PX",
    "addr:postcode":"yo19 5px",
    "addr:street":"Beeches",
    "iso:country":"GB",
    "sg:address":"Glebe House, The Manor Beeches",
    "sg:city":"York",
    "sg:classifiers":[
        {
            "category":"Professional",
            "subcategory":"Management & Consulting",
            "type":"Services"
        }
    ],
    "sg:phone":"+44 1904 489522",
    "sg:postcode":"YO19 5PX",
    "sg:province":"North Yorkshire",
    "sg:tags":[
        "consultant",
        "business"
    ],
    "wof:name":"Taylor Kay Associates",
    "wof:placetype":"venue"
},
  "geometry": {"coordinates":[-0.9822859764,53.9651870728],"type":"Point"}
}