{
  "type": "Feature",
  "properties": {
    "addr:full":"High Street, Downley High Wycombe Buckinghamshire HP13 5XJ",
    "addr:postcode":"hp13 5xj",
    "addr:street":"High Street",
    "iso:country":"GB",
    "sg:address":"High Street, Downley",
    "sg:city":"High Wycombe",
    "sg:classifiers":[
        {
            "category":"Government",
            "subcategory":"Post Office",
            "type":"Public Place"
        }
    ],
    "sg:phone":"+44 1494 520680",
    "sg:postcode":"HP13 5XJ",
    "sg:province":"Buckinghamshire",
    "wof:name":"DOWNLEY POST OFFICE",
    "wof:placetype":"venue"
},
  "geometry": {"coordinates":[-0.7760570049,51.6499176025],"type":"Point"}
}