{
  "type": "Feature",
  "properties": {
    "addr:full":"32 Paton Street Alloa Clackmannanshire FK10 2DY",
    "addr:housenumber":"32",
    "addr:postcode":"fk10 2dy",
    "addr:street":"Paton Street",
    "iso:country":"GB",
    "sg:address":"32 Paton Street",
    "sg:city":"Alloa",
    "sg:classifiers":[
        {
            "category":"Building & Trades",
            "subcategory":"Landscaping Services",
            "type":"Services"
        }
    ],
    "sg:phone":"+44 1259 213493",
    "sg:postcode":"FK10 2DY",
    "sg:province":"Clackmannanshire",
    "sg:tags":[
        "landscape",
        "contractor"
    ],
    "wof:name":"Elistoun Kean Ltd.",
    "wof:placetype":"venue"
},
  "geometry": {"coordinates":[-3.8002169132,56.1203994751],"type":"Point"}
}