{
  "type": "Feature",
  "properties": {
    "addr:full":"The Pilot Office, The Quay Poole Dorset BH15 1HA",
    "addr:postcode":"bh15 1ha",
    "addr:street":"The Quay",
    "iso:country":"GB",
    "sg:address":"The Pilot Office, The Quay",
    "sg:city":"Poole",
    "sg:classifiers":[
        {
            "category":"Professional",
            "type":"Services"
        }
    ],
    "sg:phone":"+44 1202 666401",
    "sg:postcode":"BH15 1HA",
    "sg:province":"Dorset",
    "sg:tags":[
        "marine"
    ],
    "wof:name":"Pilot Boats",
    "wof:placetype":"venue"
},
  "geometry": {"coordinates":[-1.9867390394,50.7144851685],"type":"Point"}
}