{
  "type": "Feature",
  "properties": {
    "addr:full":"25 Lombard Rd Wimbledon Greater London SW19 3TZ",
    "addr:housenumber":"25",
    "addr:postcode":"sw19 3tz",
    "addr:street":"Lombard Rd",
    "iso:country":"GB",
    "sg:address":"25 Lombard Rd",
    "sg:city":"Wimbledon",
    "sg:classifiers":[
        {
            "category":"Building & Trades",
            "subcategory":"Cleaning & Sanitation",
            "type":"Services"
        }
    ],
    "sg:phone":"+44 20 8545 9000",
    "sg:postcode":"SW19 3TZ",
    "sg:province":"Greater London",
    "sg:tags":[
        "commercial"
    ],
    "wof:name":"Li Group",
    "wof:placetype":"venue"
},
  "geometry": {"coordinates":[-0.188179,51.409595],"type":"Point"}
}