{
  "type": "Feature",
  "properties": {
    "iso:country":"GB",
    "sg:address":"7 Lime Close, Bentley",
    "sg:city":"Walsall",
    "sg:classifiers":[
        {
            "category":"Building & Trades",
            "subcategory":"Construction",
            "type":"Services"
        }
    ],
    "sg:phone":"+44 1922 642188",
    "sg:postcode":"WS2 0JR",
    "sg:province":"West Midlands",
    "sg:tags":[
        "decorator",
        "painter"
    ],
    "wof:name":"Stuart Smith",
    "wof:placetype":"venue"
},
  "geometry": {"coordinates":[-2.0241770744,52.5908241272],"type":"Point"}
}