{
  "type": "Feature",
  "properties": {
    "addr:full":"41 Cardigan Street London Greater London SE11 5PF",
    "addr:housenumber":"41",
    "addr:postcode":"se11 5pf",
    "addr:street":"Cardigan Street",
    "iso:country":"GB",
    "sg:address":"41 Cardigan Street",
    "sg:city":"London",
    "sg:classifiers":[
        {
            "category":"Real Estate",
            "subcategory":"Architect",
            "type":"Services"
        }
    ],
    "sg:phone":"+44 20 7582 0748",
    "sg:postcode":"SE11 5PF",
    "sg:province":"Greater London",
    "wof:name":"Giles Quarme & Associates",
    "wof:placetype":"venue"
},
  "geometry": {"coordinates":[-0.113293,51.488895],"type":"Point"}
}