{
  "type": "Feature",
  "properties": {
    "iso:country":"GB",
    "sg:address":"32 Compton Hill Drive, Compton",
    "sg:city":"Wolverhampton",
    "sg:classifiers":[
        {
            "category":"Building & Trades",
            "subcategory":"Construction",
            "type":"Services"
        }
    ],
    "sg:phone":"+44 1902 754444",
    "sg:postcode":"WV3 9DL",
    "sg:province":"Staffordshire",
    "sg:tags":[
        "builder"
    ],
    "wof:name":"Mee Construction Ltd.",
    "wof:placetype":"venue"
},
  "geometry": {"coordinates":[-2.169977,52.588211],"type":"Point"}
}