{
  "type": "Feature",
  "properties": {
    "addr:full":"26 Alexander Street Clydebank East Dunbartonshire G81 1RZ",
    "addr:housenumber":"26",
    "addr:postcode":"g81 1rz",
    "addr:street":"Alexander Street",
    "iso:country":"GB",
    "sg:address":"26 Alexander Street",
    "sg:city":"Clydebank",
    "sg:classifiers":[
        {
            "category":"Restaurant",
            "type":"Food & Drink"
        }
    ],
    "sg:phone":"+44 141 952 5445",
    "sg:postcode":"G81 1RZ",
    "sg:province":"East Dunbartonshire",
    "sg:tags":[
        "chinese"
    ],
    "wof:name":"Flora City",
    "wof:placetype":"venue"
},
  "geometry": {"coordinates":[-4.4046549797,55.9007110596],"type":"Point"}
}