{
  "type": "Feature",
  "properties": {
    "addr:full":"67 St Matthews Street Ipswich Suffolk IP1 3EW",
    "addr:housenumber":"67",
    "addr:postcode":"ip1 3ew",
    "addr:street":"St Matthews Street",
    "iso:country":"GB",
    "sg:address":"67 St Matthews Street",
    "sg:city":"Ipswich",
    "sg:classifiers":[
        {
            "category":"Shopping",
            "subcategory":"Comic Books",
            "type":"Retail Goods"
        }
    ],
    "sg:postcode":"IP1 3EW",
    "sg:province":"Suffolk",
    "sg:tags":[
        "jeweller"
    ],
    "wof:name":"Jems",
    "wof:placetype":"venue"
},
  "geometry": {"coordinates":[1.1467180252,52.0599708557],"type":"Point"}
}