{
  "type": "Feature",
  "properties": {
    "iso:country":"GB",
    "sg:address":"Westhall Garage, Duntrune",
    "sg:city":"Dundee",
    "sg:classifiers":[
        {
            "category":"Freight",
            "type":"Transportation"
        }
    ],
    "sg:phone":"+44 1382 350329",
    "sg:postcode":"DD4 0PP",
    "sg:province":"Dundee City",
    "sg:tags":[
        "haulage",
        "transport",
        "road"
    ],
    "wof:name":"MRS DOUGLAS , LYNNE",
    "wof:placetype":"venue"
},
  "geometry": {"coordinates":[-2.902376,56.504734],"type":"Point"}
}