{
  "type": "Feature",
  "properties": {
    "addr:full":"Pine Court, 36 Gervis Road Bournemouth Dorset BH1 3DH",
    "addr:housenumber":"36",
    "addr:postcode":"bh1 3dh",
    "addr:street":"Pine;Gervis Road",
    "iso:country":"GB",
    "sg:address":"Pine Court, 36 Gervis Road",
    "sg:city":"Bournemouth",
    "sg:classifiers":[
        {
            "category":"Communications",
            "subcategory":"Film & Video Production",
            "type":"Services"
        }
    ],
    "sg:phone":"+44 1202 780390",
    "sg:postcode":"BH1 3DH",
    "sg:province":"Dorset",
    "sg:tags":[
        "illustrator",
        "artist"
    ],
    "wof:name":"Chris Chapman",
    "wof:placetype":"venue"
},
  "geometry": {"coordinates":[-1.868003,50.719975],"type":"Point"}
}