{
  "type": "Feature",
  "properties": {
    "iso:country":"GB",
    "sg:address":"8 Back Sitwell Street",
    "sg:city":"Derby",
    "sg:classifiers":[
        {
            "category":"Retail",
            "subcategory":"Auto Repair",
            "type":"Services"
        }
    ],
    "sg:postcode":"DE1 2JX",
    "sg:province":"Derbyshire",
    "sg:tags":[
        "modification",
        "garage"
    ],
    "wof:name":"Philip Bates",
    "wof:placetype":"venue"
},
  "geometry": {"coordinates":[-1.475706,52.918453],"type":"Point"}
}