{
  "type": "Feature",
  "properties": {
    "iso:country":"GB",
    "sg:address":"1a Yew Crea Court, Bedford Road, Wootton",
    "sg:city":"Bedford",
    "sg:classifiers":[
        {
            "category":"Food & Beverages",
            "subcategory":"Meat & Fish",
            "type":"Retail Goods"
        }
    ],
    "sg:phone":"+44 1234 767656",
    "sg:postcode":"MK43 9JU",
    "sg:province":"Bedfordshire",
    "sg:tags":[
        "chip"
    ],
    "wof:name":"Pats Plaice",
    "wof:placetype":"venue"
},
  "geometry": {"coordinates":[-0.527198,52.097931],"type":"Point"}
}