{
  "type": "Feature",
  "properties": {
    "iso:country":"GB",
    "sg:address":"80 Bucknalls Lane",
    "sg:city":"Watford",
    "sg:classifiers":[
        {
            "category":"Building & Trades",
            "subcategory":"Construction",
            "type":"Services"
        }
    ],
    "sg:phone":"+44 70 0023 8339",
    "sg:postcode":"WD2 7NQ",
    "sg:province":"Hertfordshire",
    "sg:tags":[
        "contractor",
        "paving",
        "driveway"
    ],
    "wof:name":"A & J Modern Driveways",
    "wof:placetype":"venue"
},
  "geometry": {"coordinates":[-0.3786869943,51.6981315613],"type":"Point"}
}