{
  "type": "Feature",
  "properties": {
    "addr:full":"Little Brocks, Great Easton Dunmow Essex CM6 2HG",
    "addr:housenumber":"great easton",
    "addr:postcode":"cm6 2hg",
    "iso:country":"GB",
    "sg:address":"Little Brocks, Great Easton",
    "sg:city":"Dunmow",
    "sg:classifiers":[
        {
            "category":"Building & Trades",
            "subcategory":"Construction",
            "type":"Services"
        }
    ],
    "sg:phone":"+44 1371 870267",
    "sg:postcode":"CM6 2HG",
    "sg:province":"Essex",
    "sg:tags":[
        "builder",
        "contractor"
    ],
    "wof:name":"Pickford Builders Ltd.",
    "wof:placetype":"venue"
},
  "geometry": {"coordinates":[0.3403100073,51.9045410156],"type":"Point"}
}