{
  "type": "Feature",
  "properties": {
    "addr:full":"Winner St Paignton Devon TQ3 3BH",
    "addr:postcode":"tq3 3bh",
    "addr:street":"Winner St",
    "iso:country":"GB",
    "sg:address":"Winner St",
    "sg:city":"Paignton",
    "sg:classifiers":[
        {
            "category":"Place Of Worship",
            "type":"Public Place"
        }
    ],
    "sg:phone":"+44 1803 557557",
    "sg:postcode":"TQ3 3BH",
    "sg:province":"Devon",
    "wof:name":"Paignton Baptist Church",
    "wof:placetype":"venue"
},
  "geometry": {"coordinates":[-3.572309,50.437401],"type":"Point"}
}