{
  "type": "Feature",
  "properties": {
    "addr:full":"22 Coney St York North Yorkshire YO1 1ND",
    "addr:housenumber":"22",
    "addr:postcode":"yo1 1nd",
    "addr:street":"Coney St",
    "iso:country":"GB",
    "sg:address":"22 Coney St",
    "sg:city":"York",
    "sg:classifiers":[
        {
            "category":"Food & Beverages",
            "subcategory":"Candy",
            "type":"Retail Goods"
        }
    ],
    "sg:postcode":"YO1 1ND",
    "sg:province":"North Yorkshire",
    "sg:tags":[
        "confectioner"
    ],
    "wof:name":"Thorntons Plc",
    "wof:placetype":"venue"
},
  "geometry": {"coordinates":[-1.0836650133,53.9591331482],"type":"Point"}
}