{
  "type": "Feature",
  "properties": {
    "iso:country":"GB",
    "sg:address":"Northway Lane, Newtown Industrial Estate",
    "sg:city":"Tewkesbury",
    "sg:classifiers":[
        {
            "category":"Retail",
            "subcategory":"Auto Repair",
            "type":"Services"
        }
    ],
    "sg:postcode":"GL20 8JG",
    "sg:province":"Gloucestershire",
    "sg:tags":[
        "body",
        "car"
    ],
    "wof:name":"Mervin B Blackwell",
    "wof:placetype":"venue"
},
  "geometry": {"coordinates":[-2.1244709492,52.002784729],"type":"Point"}
}