{
  "type": "Feature",
  "properties": {
    "addr:full":"43 Market St Bolton Lancashire BL5 3AG",
    "addr:housenumber":"43",
    "addr:postcode":"bl5 3ag",
    "addr:street":"Market St",
    "iso:country":"GB",
    "sg:address":"43 Market St",
    "sg:city":"Bolton",
    "sg:classifiers":[
        {
            "category":"Health Services",
            "subcategory":"Optometrist",
            "type":"Services"
        }
    ],
    "sg:phone":"+44 1942 818833",
    "sg:postcode":"BL5 3AG",
    "sg:province":"Lancashire",
    "sg:tags":[
        "optician"
    ],
    "wof:name":"Keegan Opticians Ltd",
    "wof:placetype":"venue"
},
  "geometry": {"coordinates":[-2.5219531059,53.5488548279],"type":"Point"}
}