{
  "type": "Feature",
  "properties": {
    "addr:full":"May Tree House, The Grn Ely Cambridgeshire CB7 5XR",
    "addr:postcode":"cb7 5xr",
    "addr:street":"May;The Grn Ely",
    "iso:country":"GB",
    "sg:address":"May Tree House, The Grn",
    "sg:city":"Ely",
    "sg:classifiers":[
        {
            "category":"Professional",
            "subcategory":"Management & Consulting",
            "type":"Services"
        },
        {
            "category":"Organizations",
            "subcategory":"Community Association",
            "type":"Services"
        }
    ],
    "sg:phone":"+44 1353 721991",
    "sg:postcode":"CB7 5XR",
    "sg:province":"Cambridgeshire",
    "sg:tags":[
        "consultant",
        "relation",
        "public"
    ],
    "wof:name":"Mms Marketing Ltd.",
    "wof:placetype":"venue"
},
  "geometry": {"coordinates":[0.412865,52.338703],"type":"Point"}
}