{
  "type": "Feature",
  "properties": {
    "addr:full":"33 Hill View Pk, Sunnyhill La, Oare Marlborough Berkshire SN8 4JF",
    "addr:housenumber":"33",
    "addr:postcode":"sn8 4jf",
    "addr:street":"Hill View Pk Sunnyhill La Oare",
    "iso:country":"GB",
    "sg:address":"33 Hill View Pk, Sunnyhill La, Oare",
    "sg:city":"Marlborough",
    "sg:classifiers":[
        {
            "category":"Professional",
            "subcategory":"Detective & Security Services",
            "type":"Services"
        }
    ],
    "sg:postcode":"SN8 4JF",
    "sg:province":"Berkshire",
    "sg:tags":[
        "locksmith"
    ],
    "wof:name":"Biggs,John,",
    "wof:placetype":"venue"
},
  "geometry": {"coordinates":[-1.865918,51.356663],"type":"Point"}
}