{
  "type": "Feature",
  "properties": {
    "addr:full":"208 Clifton Road Darlington Durham DL1 5EA",
    "addr:housenumber":"208",
    "addr:postcode":"dl1 5ea",
    "addr:street":"Clifton Road",
    "iso:country":"GB",
    "sg:address":"208 Clifton Road",
    "sg:city":"Darlington",
    "sg:classifiers":[
        {
            "category":"Building & Trades",
            "subcategory":"Plumbing",
            "type":"Services"
        }
    ],
    "sg:phone":"+44 1325 482822",
    "sg:postcode":"DL1 5EA",
    "sg:province":"Durham",
    "sg:tags":[
        "heating"
    ],
    "wof:name":"R Mellett",
    "wof:placetype":"venue"
},
  "geometry": {"coordinates":[-1.550965,54.514683],"type":"Point"}
}