{
  "type": "Feature",
  "properties": {
    "addr:full":"26b Bushey Hill Road London Greater London SE5 8QJ",
    "addr:housenumber":"26b",
    "addr:postcode":"se5 8qj",
    "addr:street":"Bushey Hill Road",
    "iso:country":"GB",
    "sg:address":"26b Bushey Hill Road",
    "sg:city":"London",
    "sg:classifiers":[
        {
            "category":"Building & Trades",
            "subcategory":"Construction",
            "type":"Services"
        }
    ],
    "sg:postcode":"SE5 8QJ",
    "sg:province":"Greater London",
    "sg:tags":[
        "dry",
        "lining",
        "plasterers",
        "screeders"
    ],
    "wof:name":"D & S Plastering Contractors",
    "wof:placetype":"venue"
},
  "geometry": {"coordinates":[-0.0793950036,51.4729690552],"type":"Point"}
}