{
  "type": "Feature",
  "properties": {
    "addr:full":"Station Road Burton-on-trent Derbyshire DE13 8DS",
    "addr:postcode":"de13 8ds",
    "addr:street":"Station Road",
    "iso:country":"GB",
    "sg:address":"Station Road",
    "sg:city":"Burton-on-trent",
    "sg:classifiers":[
        {
            "category":"Education",
            "subcategory":"School",
            "type":"Public Place"
        }
    ],
    "sg:phone":"+44 1283 239350",
    "sg:postcode":"DE13 8DS",
    "sg:province":"Derbyshire",
    "sg:tags":[
        "local",
        "authority"
    ],
    "wof:name":"Thomas Russell Infants School",
    "wof:placetype":"venue"
},
  "geometry": {"coordinates":[-1.7203589678,52.763458252],"type":"Point"}
}