{
  "type": "Feature",
  "properties": {
    "addr:full":"Units 1 & 2 Chapel Road, Cuminestown Industrial Estate Turriff Aberdeenshire AB53 5ZA",
    "addr:housenumber":"units 1 & 2",
    "addr:postcode":"ab53 5za",
    "addr:street":"Chapel Road Cuminestown Industrial Estate",
    "iso:country":"GB",
    "sg:address":"Units 1 & 2 Chapel Road, Cuminestown Industrial Estate",
    "sg:city":"Turriff",
    "sg:classifiers":[
        {
            "category":"Building & Trades",
            "subcategory":"Construction",
            "type":"Services"
        }
    ],
    "sg:postcode":"AB53 5ZA",
    "sg:province":"Aberdeenshire",
    "sg:tags":[
        "woodwork",
        "architectural"
    ],
    "wof:name":"The Joiners Shop",
    "wof:placetype":"venue"
},
  "geometry": {"coordinates":[-2.32119,57.545139],"type":"Point"}
}