{
  "type": "Feature",
  "properties": {
    "addr:full":"70-71 Mill Street Kidderminster Staffordshire DY11 6XJ",
    "addr:housenumber":"70-71",
    "addr:postcode":"dy11 6xj",
    "addr:street":"Mill Street",
    "iso:country":"GB",
    "sg:address":"70-71 Mill Street",
    "sg:city":"Kidderminster",
    "sg:classifiers":[
        {
            "category":"Personal",
            "type":"Services"
        }
    ],
    "sg:phone":"+44 1562 820118",
    "sg:postcode":"DY11 6XJ",
    "sg:province":"Staffordshire",
    "sg:tags":[
        "wedding"
    ],
    "wof:name":"The Lace Mill",
    "wof:placetype":"venue"
},
  "geometry": {"coordinates":[-2.256121,52.388645],"type":"Point"}
}