{
  "type": "Feature",
  "properties": {
    "iso:country":"GB",
    "sg:address":"Russell House, Middleton Street",
    "sg:city":"Llandrindod Wells",
    "sg:classifiers":[
        {
            "category":"Banks & Credit Unions",
            "subcategory":"Bank",
            "type":"Services"
        }
    ],
    "sg:phone":"+44 845 765 4321",
    "sg:postcode":"LD1 5ET",
    "sg:province":"Powys",
    "wof:name":"Abbey National Plc",
    "wof:placetype":"venue"
},
  "geometry": {"coordinates":[-3.379399,52.240181],"type":"Point"}
}