{
  "type": "Feature",
  "properties": {
    "addr:full":"1 Wilkinson Close, Eaton Socon, Eaton Socon St Neots Bedfordshire PE19 8HJ",
    "addr:housenumber":"1",
    "addr:postcode":"pe19 8hj",
    "addr:street":"Wilkinson Close;Socon;Socon",
    "iso:country":"GB",
    "sg:address":"1 Wilkinson Close, Eaton Socon, Eaton Socon",
    "sg:city":"St Neots",
    "sg:classifiers":[
        {
            "category":"Real Estate",
            "subcategory":"Surveying",
            "type":"Services"
        }
    ],
    "sg:phone":"+44 1480 473455",
    "sg:postcode":"PE19 8HJ",
    "sg:province":"Bedfordshire",
    "sg:tags":[
        "surveyor",
        "valuer"
    ],
    "wof:name":"St. Neots Surveying Services",
    "wof:placetype":"venue"
},
  "geometry": {"coordinates":[-0.2893750072,52.2174720764],"type":"Point"}
}