{
  "type": "Feature",
  "properties": {
    "addr:full":"78 Main St Newmilns East Ayrshire KA16 9DH",
    "addr:housenumber":"78",
    "addr:postcode":"ka16 9dh",
    "addr:street":"Main St",
    "iso:country":"GB",
    "sg:address":"78 Main St",
    "sg:city":"Newmilns",
    "sg:classifiers":[
        {
            "category":"Professional",
            "subcategory":"Business Services",
            "type":"Services"
        }
    ],
    "sg:phone":"+44 1560 329090",
    "sg:postcode":"KA16 9DH",
    "sg:province":"East Ayrshire",
    "sg:tags":[
        "bookmaker"
    ],
    "wof:name":"G & D Racing",
    "wof:placetype":"venue"
},
  "geometry": {"coordinates":[-4.323777,55.607464],"type":"Point"}
}