{
  "type": "Feature",
  "properties": {
    "iso:country":"GB",
    "sg:address":"Hinwick Road, Wollaston",
    "sg:city":"Wellingborough",
    "sg:classifiers":[
        {
            "category":"Organizations",
            "subcategory":"Non-profit Organization",
            "type":"Services"
        }
    ],
    "sg:phone":"+44 1933 664412",
    "sg:postcode":"NN29 7QT",
    "sg:province":"Bedfordshire",
    "sg:tags":[
        "charitable",
        "organisation",
        "voluntary",
        "charity"
    ],
    "wof:name":"The Salvation Army",
    "wof:placetype":"venue"
},
  "geometry": {"coordinates":[-0.6233890057,52.2521476746],"type":"Point"}
}