{
  "type": "Feature",
  "properties": {
    "addr:full":"Davenport House, Beaufoys Avenue Ferndown Dorset BH22 9RJ",
    "addr:postcode":"bh22 9rj",
    "addr:street":"Beaufoys Avenue",
    "iso:country":"GB",
    "sg:address":"Davenport House, Beaufoys Avenue",
    "sg:city":"Ferndown",
    "sg:classifiers":[
        {
            "category":"Home & Garden",
            "subcategory":"Home Furnishings",
            "type":"Retail Goods"
        }
    ],
    "sg:postcode":"BH22 9RJ",
    "sg:province":"Dorset",
    "sg:tags":[
        "racking",
        "shelving",
        "diy"
    ],
    "wof:name":"Keeping Storage Systems",
    "wof:placetype":"venue"
},
  "geometry": {"coordinates":[-1.887589,50.813309],"type":"Point"}
}