{
  "type": "Feature",
  "properties": {
    "addr:full":"Flat 2 1 101 Glenfield Road, Glenburn Paisley East Renfrewshire PA2 8JL",
    "addr:housenumber":"1 101",
    "addr:postcode":"pa2 8jl",
    "addr:street":"Glenfield Road;Paisley East",
    "iso:country":"GB",
    "sg:address":"Flat 2 1 101 Glenfield Road, Glenburn",
    "sg:city":"Paisley",
    "sg:classifiers":[
        {
            "category":"Farming",
            "subcategory":"Nursery",
            "type":"Manufacturing & Wholesale Goods"
        }
    ],
    "sg:postcode":"PA2 8JL",
    "sg:province":"East Renfrewshire",
    "sg:tags":[
        "creche"
    ],
    "wof:name":"Langcraigs Nursery Group",
    "wof:placetype":"venue"
},
  "geometry": {"coordinates":[-4.4341897964,55.8180999756],"type":"Point"}
}