{
  "type": "Feature",
  "properties": {
    "addr:full":"47 Priory Road Reigate Surrey RH2 8JA",
    "addr:housenumber":"47",
    "addr:postcode":"rh2 8ja",
    "addr:street":"Priory Road",
    "iso:country":"GB",
    "sg:address":"47 Priory Road",
    "sg:city":"Reigate",
    "sg:classifiers":[
        {
            "category":"Real Estate",
            "subcategory":"Real Estate Operator",
            "type":"Services"
        }
    ],
    "sg:postcode":"RH2 8JA",
    "sg:province":"Surrey",
    "sg:tags":[
        "letting",
        "agent"
    ],
    "wof:name":"A Lagourderis",
    "wof:placetype":"venue"
},
  "geometry": {"coordinates":[-0.209133,51.225903],"type":"Point"}
}