{
  "type": "Feature",
  "properties": {
    "iso:country":"GB",
    "sg:address":"Common Crown La",
    "sg:city":"Chislehurst",
    "sg:classifiers":[
        {
            "category":"Place Of Worship",
            "type":"Public Place"
        }
    ],
    "sg:phone":"+44 20 8467 3215",
    "sg:postcode":"BR7 5PL",
    "sg:province":"Kent",
    "wof:name":"St Mary's Catholic Church",
    "wof:placetype":"venue"
},
  "geometry": {"coordinates":[0.0663900003,51.4192848206],"type":"Point"}
}