{
  "type": "Feature",
  "properties": {
    "addr:full":"3a Hume Street Kidderminster Staffordshire DY11 6RD",
    "addr:housenumber":"3a",
    "addr:postcode":"dy11 6rd",
    "addr:street":"Hume Street",
    "iso:country":"GB",
    "sg:address":"3a Hume Street",
    "sg:city":"Kidderminster",
    "sg:classifiers":[
        {
            "category":"Professional",
            "subcategory":"Printing & Photocopies",
            "type":"Services"
        }
    ],
    "sg:phone":"+44 1562 861045",
    "sg:postcode":"DY11 6RD",
    "sg:province":"Staffordshire",
    "sg:tags":[
        "embroiderer"
    ],
    "wof:name":"T M Embroidery Ltd.",
    "wof:placetype":"venue"
},
  "geometry": {"coordinates":[-2.2618460655,52.3836517334],"type":"Point"}
}