{
  "type": "Feature",
  "properties": {
    "iso:country":"GB",
    "sg:address":"8 Holding Cochno Road, Hardgate",
    "sg:city":"Clydebank",
    "sg:classifiers":[
        {
            "category":"Transit Center",
            "subcategory":"Passenger",
            "type":"Transportation"
        }
    ],
    "sg:phone":"+44 1389 873312",
    "sg:postcode":"G81 6RT",
    "sg:province":"East Dunbartonshire",
    "sg:tags":[
        "boarding",
        "kennel",
        "catteries"
    ],
    "wof:name":"Rubilyn Kennels",
    "wof:placetype":"venue"
},
  "geometry": {"coordinates":[-4.403649,55.910858],"type":"Point"}
}