{
  "type": "Feature",
  "properties": {
    "iso:country":"GB",
    "sg:address":"207 Sutton Road",
    "sg:city":"Kidderminster",
    "sg:classifiers":[
        {
            "category":"Bars & Pubs",
            "type":"Food & Drink"
        }
    ],
    "sg:phone":"+44 1562 66254",
    "sg:postcode":"DY11 6QJ",
    "sg:province":"Staffordshire",
    "sg:tags":[
        "pubs",
        "inn"
    ],
    "wof:name":"The Grand Turk",
    "wof:placetype":"venue"
},
  "geometry": {"coordinates":[-2.263324,52.3853],"type":"Point"}
}