{
  "type": "Feature",
  "properties": {
    "iso:country":"GB",
    "sg:address":"261 Rayne Rd",
    "sg:city":"Braintree",
    "sg:classifiers":[
        {
            "category":"Retail",
            "subcategory":"Auto Repair",
            "type":"Services"
        }
    ],
    "sg:phone":"+44 1376 329297",
    "sg:postcode":"CM7 2QF",
    "sg:province":"Essex",
    "sg:tags":[
        "modification",
        "garage"
    ],
    "wof:name":"National Tyres & Autocare",
    "wof:placetype":"venue"
},
  "geometry": {"coordinates":[0.537497,51.87838],"type":"Point"}
}