{
  "type": "Feature",
  "properties": {
    "addr:full":"Shaws Corner, Hatchlands Rd Redhill Surrey RH1 6AU",
    "addr:postcode":"rh1 6au",
    "addr:street":"Hatchlands Rd",
    "iso:country":"GB",
    "sg:address":"Shaws Corner, Hatchlands Rd",
    "sg:city":"Redhill",
    "sg:classifiers":[
        {
            "category":"Place Of Worship",
            "type":"Public Place"
        }
    ],
    "sg:phone":"+44 1737 773270",
    "sg:postcode":"RH1 6AU",
    "sg:province":"Surrey",
    "wof:name":"Redhill United Reformed Church",
    "wof:placetype":"venue"
},
  "geometry": {"coordinates":[-0.1688790023,51.2381782532],"type":"Point"}
}