{
  "type": "Feature",
  "properties": {
    "addr:full":"Unit 1, 30 Churchfield St Dudley West Midlands DY2 8QR",
    "addr:housenumber":"unit;30",
    "addr:postcode":"dy2 8qr",
    "addr:street":"Churchfield St",
    "iso:country":"GB",
    "sg:address":"Unit 1, 30 Churchfield St",
    "sg:city":"Dudley",
    "sg:classifiers":[
        {
            "category":"Manufacturing",
            "subcategory":"Petroleum Products",
            "type":"Manufacturing & Wholesale Goods"
        }
    ],
    "sg:phone":"+44 1384 826675",
    "sg:postcode":"DY2 8QR",
    "sg:province":"West Midlands",
    "sg:tags":[
        "double",
        "glazing"
    ],
    "wof:name":"Ash Glazing",
    "wof:placetype":"venue"
},
  "geometry": {"coordinates":[-2.08739,52.505943],"type":"Point"}
}