{
  "type": "Feature",
  "properties": {
    "addr:full":"Birch Farm, Hintlesham Ipswich Suffolk IP8 3NJ",
    "addr:postcode":"ip8 3nj",
    "iso:country":"GB",
    "sg:address":"Birch Farm, Hintlesham",
    "sg:city":"Ipswich",
    "sg:classifiers":[
        {
            "category":"Farming",
            "subcategory":"Nursery",
            "type":"Manufacturing & Wholesale Goods"
        }
    ],
    "sg:phone":"+44 1473 652249",
    "sg:postcode":"IP8 3NJ",
    "sg:province":"Suffolk",
    "sg:tags":[
        "creche"
    ],
    "wof:name":"Birch Farm Nursery Ltd.",
    "wof:placetype":"venue"
},
  "geometry": {"coordinates":[1.038310051,52.0506439209],"type":"Point"}
}