{
  "type": "Feature",
  "properties": {
    "addr:full":"17 Rosebank Ave Glasgow Glasgow City G3 8TB",
    "addr:housenumber":"17",
    "addr:postcode":"g3 8tb",
    "addr:street":"Rosebank Ave",
    "iso:country":"GB",
    "sg:address":"17 Rosebank Ave",
    "sg:city":"Glasgow",
    "sg:classifiers":[
        {
            "category":"Government",
            "subcategory":"Customs House",
            "type":"Public Place"
        }
    ],
    "sg:phone":"+44 1698 829401",
    "sg:postcode":"G3 8TB",
    "sg:province":"Glasgow City",
    "sg:tags":[
        "clearance"
    ],
    "wof:name":"Glenndinnin J",
    "wof:placetype":"venue"
},
  "geometry": {"coordinates":[-4.28546,55.864948],"type":"Point"}
}