{
  "type": "Feature",
  "properties": {
    "iso:country":"GB",
    "sg:address":"292 Poulton Road",
    "sg:city":"Fleetwood",
    "sg:classifiers":[
        {
            "category":"Personal",
            "subcategory":"Beauty Salon",
            "type":"Services"
        }
    ],
    "sg:phone":"+44 1253 874035",
    "sg:postcode":"FY7 7LA",
    "sg:province":"Lancashire",
    "sg:tags":[
        "ladies",
        "lady",
        "hairdresser"
    ],
    "wof:name":"Diana",
    "wof:placetype":"venue"
},
  "geometry": {"coordinates":[-3.031092,53.919197],"type":"Point"}
}