{
  "type": "Feature",
  "properties": {
    "addr:full":"162 Conway Road Colwyn Bay Conwy LL29 7LR",
    "addr:housenumber":"162",
    "addr:postcode":"ll29 7lr",
    "addr:street":"Conway Road",
    "iso:country":"GB",
    "sg:address":"162 Conway Road",
    "sg:city":"Colwyn Bay",
    "sg:classifiers":[
        {
            "category":"Shopping",
            "subcategory":"News",
            "type":"Retail Goods"
        }
    ],
    "sg:postcode":"LL29 7LR",
    "sg:province":"Conwy",
    "sg:tags":[
        "newsagent"
    ],
    "wof:name":"E & M's News",
    "wof:placetype":"venue"
},
  "geometry": {"coordinates":[-3.7407050133,53.3000640869],"type":"Point"}
}