{
  "type": "Feature",
  "properties": {
    "addr:full":"St Lukes Hall, William Street, Bedminster Bristol City of Bristol BS3 4BW",
    "addr:postcode":"bs3 4bw",
    "addr:street":"William Street",
    "iso:country":"GB",
    "sg:address":"St Lukes Hall, William Street, Bedminster",
    "sg:city":"Bristol",
    "sg:classifiers":[
        {
            "category":"Shopping",
            "subcategory":"Discount & Variety Stores",
            "type":"Retail Goods"
        },
        {
            "category":"Building & Trades",
            "subcategory":"Construction",
            "type":"Services"
        }
    ],
    "sg:phone":"+44 117 966 8171",
    "sg:postcode":"BS3 4BW",
    "sg:province":"City of Bristol",
    "sg:tags":[
        "cleaning",
        "flooring",
        "supply"
    ],
    "wof:name":"Tru-Shine Floor Renovations Ltd.",
    "wof:placetype":"venue"
},
  "geometry": {"coordinates":[-2.584733963,51.4452285767],"type":"Point"}
}