{
  "type": "Feature",
  "properties": {
    "addr:full":"Wells Bottom Farm, Wells Lea Hermitage Rd East Grinstead East Sussex RH19 2SE",
    "addr:housenumber":"wells",
    "addr:postcode":"rh19 2se",
    "addr:street":"Lea Hermitage Rd",
    "iso:country":"GB",
    "sg:address":"Wells Bottom Farm, Wells Lea Hermitage Rd",
    "sg:city":"East Grinstead",
    "sg:classifiers":[
        {
            "category":"Travel",
            "subcategory":"Travel Agent",
            "type":"Entertainment"
        }
    ],
    "sg:phone":"+44 1342 318199",
    "sg:postcode":"RH19 2SE",
    "sg:province":"East Sussex",
    "wof:name":"Travel Counsellors",
    "wof:placetype":"venue"
},
  "geometry": {"coordinates":[-0.007568,51.123981],"type":"Point"}
}