{
  "type": "Feature",
  "properties": {
    "addr:full":"Unit 1/2, Phoenix Road Industrial Estate Wolverhampton Staffordshire WV11 3PX",
    "addr:housenumber":"unit 1 / 2",
    "addr:postcode":"wv11 3px",
    "addr:street":"Phoenix Road Industrial Estate",
    "iso:country":"GB",
    "sg:address":"Unit 1/2, Phoenix Road Industrial Estate",
    "sg:city":"Wolverhampton",
    "sg:classifiers":[
        {
            "category":"Autos & Motor Vehicles",
            "subcategory":"Auto Supplies",
            "type":"Retail Goods"
        }
    ],
    "sg:phone":"+44 1902 863005",
    "sg:postcode":"WV11 3PX",
    "sg:province":"Staffordshire",
    "sg:tags":[
        "car",
        "audio"
    ],
    "wof:name":"Bass Junkies",
    "wof:placetype":"venue"
},
  "geometry": {"coordinates":[-2.0782599449,52.5927429199],"type":"Point"}
}