{
  "type": "Feature",
  "properties": {
    "addr:full":"3 Beech Avenue, Timperley Altrincham Cheshire WA15 6EG",
    "addr:housenumber":"3",
    "addr:postcode":"wa15 6eg",
    "addr:street":"Beech Avenue",
    "iso:country":"GB",
    "sg:address":"3 Beech Avenue, Timperley",
    "sg:city":"Altrincham",
    "sg:classifiers":[
        {
            "category":"Professional",
            "subcategory":"Detective & Security Services",
            "type":"Services"
        }
    ],
    "sg:postcode":"WA15 6EG",
    "sg:province":"Cheshire",
    "sg:tags":[
        "agency"
    ],
    "wof:name":"Newman Investigations",
    "wof:placetype":"venue"
},
  "geometry": {"coordinates":[-2.3215429783,53.404510498],"type":"Point"}
}