{
  "type": "Feature",
  "properties": {
    "iso:country":"GB",
    "sg:address":"Old Torrington Rd",
    "sg:city":"Barnstaple",
    "sg:classifiers":[
        {
            "category":"Retail",
            "subcategory":"Funeral Services",
            "type":"Services"
        }
    ],
    "sg:postcode":"EX31 3NW",
    "sg:province":"Devon",
    "sg:tags":[
        "cemetery",
        "crematorium"
    ],
    "wof:name":"North Devon Crematorium",
    "wof:placetype":"venue"
},
  "geometry": {"coordinates":[-4.075606,51.068237],"type":"Point"}
}