{
  "type": "Feature",
  "properties": {
    "addr:full":"23 Queens Av Canterbury Kent CT2 8BA",
    "addr:housenumber":"23",
    "addr:postcode":"ct2 8ba",
    "addr:street":"Queens Av Canterbury",
    "iso:country":"GB",
    "sg:address":"23 Queens Av",
    "sg:city":"Canterbury",
    "sg:classifiers":[
        {
            "category":"Professional",
            "subcategory":"Accounting & Tax Preparation",
            "type":"Services"
        }
    ],
    "sg:phone":"+44 1227 786660",
    "sg:postcode":"CT2 8BA",
    "sg:province":"Kent",
    "sg:tags":[
        "accountant"
    ],
    "wof:name":"Phelps-Smith Business Administration Services Ltd",
    "wof:placetype":"venue"
},
  "geometry": {"coordinates":[1.0667979717,51.2815666199],"type":"Point"}
}