{
  "type": "Feature",
  "properties": {
    "addr:full":"5 Georges Road Sale Cheshire M33 3NJ",
    "addr:housenumber":"5",
    "addr:postcode":"m33 3nj",
    "addr:street":"Georges Road",
    "iso:country":"GB",
    "sg:address":"5 Georges Road",
    "sg:city":"Sale",
    "sg:classifiers":[
        {
            "category":"Professional",
            "subcategory":"Printing & Photocopies",
            "type":"Services"
        }
    ],
    "sg:phone":"+44 161 962 3365",
    "sg:postcode":"M33 3NJ",
    "sg:province":"Cheshire",
    "sg:tags":[
        "printer"
    ],
    "wof:name":"Sale Print & Design",
    "wof:placetype":"venue"
},
  "geometry": {"coordinates":[-2.318676,53.41679],"type":"Point"}
}