{
  "type": "Feature",
  "properties": {
    "addr:full":"28 Dickens Av South Shields Tyne and Wear NE34 9SY",
    "addr:housenumber":"28",
    "addr:postcode":"ne34 9sy",
    "addr:street":"Dickens Av",
    "iso:country":"GB",
    "sg:address":"28 Dickens Av",
    "sg:city":"South Shields",
    "sg:classifiers":[
        {
            "category":"Shopping",
            "subcategory":"Department Store",
            "type":"Retail Goods"
        }
    ],
    "sg:phone":"+44 191 536 4051",
    "sg:postcode":"NE34 9SY",
    "sg:province":"Tyne and Wear",
    "wof:name":"A Beard",
    "wof:placetype":"venue"
},
  "geometry": {"coordinates":[-1.4400140047,54.9627380371],"type":"Point"}
}