{
  "type": "Feature",
  "properties": {
    "addr:full":"Hobden Street Glasgow East Dunbartonshire G21 4AQ",
    "addr:postcode":"g21 4aq",
    "addr:street":"Hobden Street",
    "iso:country":"GB",
    "sg:address":"Hobden Street",
    "sg:city":"Glasgow",
    "sg:classifiers":[
        {
            "category":"Retail",
            "subcategory":"Driving School",
            "type":"Services"
        }
    ],
    "sg:phone":"+44 141 557 2212",
    "sg:postcode":"G21 4AQ",
    "sg:province":"East Dunbartonshire",
    "wof:name":"Ritchies H G V Training Centre Ltd.",
    "wof:placetype":"venue"
},
  "geometry": {"coordinates":[-4.217344,55.877487],"type":"Point"}
}