{
  "type": "Feature",
  "properties": {
    "iso:country":"GB",
    "sg:address":"Unit D Meadow Gro, Meadow Lane",
    "sg:city":"Nottingham",
    "sg:classifiers":[
        {
            "category":"Home & Garden",
            "subcategory":"Building Materials",
            "type":"Retail Goods"
        }
    ],
    "sg:phone":"+44 1384 418600",
    "sg:postcode":"NG2 3HF",
    "sg:province":"Nottinghamshire",
    "sg:tags":[
        "ventilator",
        "ventilation",
        "system"
    ],
    "wof:name":"Sa (Finchley Road) Ltd.",
    "wof:placetype":"venue"
},
  "geometry": {"coordinates":[-1.13719,52.942619],"type":"Point"}
}