{
  "type": "Feature",
  "properties": {
    "addr:full":"29-30 Crompton Place Bolton Lancashire BL1 1EA",
    "addr:housenumber":"29-30",
    "addr:postcode":"bl1 1ea",
    "addr:street":"Crompton Place",
    "iso:country":"GB",
    "sg:address":"29-30 Crompton Place",
    "sg:city":"Bolton",
    "sg:classifiers":[
        {
            "category":"Home & Garden",
            "subcategory":"Furniture",
            "type":"Retail Goods"
        }
    ],
    "sg:phone":"+44 1204 396960",
    "sg:postcode":"BL1 1EA",
    "sg:province":"Lancashire",
    "wof:name":"Walmsleys Suite Superstore",
    "wof:placetype":"venue"
},
  "geometry": {"coordinates":[-2.426595,53.578796],"type":"Point"}
}