{
  "type": "Feature",
  "properties": {
    "addr:full":"Wellmeadow Lodge, Meadow Way, Newton Mearns Glasgow East Ayrshire G77 6XJ",
    "addr:postcode":"g77 6xj",
    "addr:street":"Meadow Way",
    "iso:country":"GB",
    "sg:address":"Wellmeadow Lodge, Meadow Way, Newton Mearns",
    "sg:city":"Glasgow",
    "sg:classifiers":[
        {
            "category":"Health Services",
            "subcategory":"Nursing And Care Facility",
            "type":"Services"
        }
    ],
    "sg:phone":"+44 141 639 9644",
    "sg:postcode":"G77 6XJ",
    "sg:province":"East Ayrshire",
    "sg:tags":[
        "home"
    ],
    "wof:name":"Ashbourne Homes Ltd.",
    "wof:placetype":"venue"
},
  "geometry": {"coordinates":[-4.3301959038,55.7747344971],"type":"Point"}
}