{
  "type": "Feature",
  "properties": {
    "addr:full":"13 Queens Road Paignton Devon TQ4 6AT",
    "addr:housenumber":"13",
    "addr:postcode":"tq4 6at",
    "addr:street":"Queens Road",
    "iso:country":"GB",
    "sg:address":"13 Queens Road",
    "sg:city":"Paignton",
    "sg:classifiers":[
        {
            "category":"Travel",
            "subcategory":"Hotels & Motels",
            "type":"Entertainment"
        }
    ],
    "sg:phone":"+44 1803 556702",
    "sg:postcode":"TQ4 6AT",
    "sg:province":"Devon",
    "sg:tags":[
        "house",
        "guest"
    ],
    "wof:name":"Rockview",
    "wof:placetype":"venue"
},
  "geometry": {"coordinates":[-3.5626499653,50.4332771301],"type":"Point"}
}