{
  "type": "Feature",
  "properties": {
    "iso:country":"GB",
    "sg:address":"12a Caunce St",
    "sg:city":"Blackpool",
    "sg:classifiers":[
        {
            "category":"Personal",
            "subcategory":"Beauty Salon",
            "type":"Services"
        }
    ],
    "sg:phone":"+44 1253 622138",
    "sg:postcode":"FY1 3DN",
    "sg:province":"Lancashire",
    "sg:tags":[
        "unisex",
        "hairdresser"
    ],
    "wof:name":"October Hair",
    "wof:placetype":"venue"
},
  "geometry": {"coordinates":[-3.0478219986,53.8184661865],"type":"Point"}
}