{
  "type": "Feature",
  "properties": {
    "addr:full":"Cathedral Lanes Shopping Centre, Broadgate Coventry West Midlands CV1 1LL",
    "addr:postcode":"cv1 1ll",
    "addr:street":"Centre Broadgate",
    "iso:country":"GB",
    "sg:address":"Cathedral Lanes Shopping Centre, Broadgate",
    "sg:city":"Coventry",
    "sg:classifiers":[
        {
            "category":"Bars & Pubs",
            "type":"Food & Drink"
        }
    ],
    "sg:phone":"+44 24 7623 4880",
    "sg:postcode":"CV1 1LL",
    "sg:province":"West Midlands",
    "sg:tags":[
        "pubs",
        "inn"
    ],
    "wof:name":"Bar Coast",
    "wof:placetype":"venue"
},
  "geometry": {"coordinates":[-1.5077680349,52.4069862366],"type":"Point"}
}