{
  "type": "Feature",
  "properties": {
    "addr:full":"Unit 5, 10 Allens Lane, Hamworthy Poole Dorset BH16 5DA",
    "addr:housenumber":"unit;10",
    "addr:postcode":"bh16 5da",
    "addr:street":"Allens Lane",
    "iso:country":"GB",
    "sg:address":"Unit 5, 10 Allens Lane, Hamworthy",
    "sg:city":"Poole",
    "sg:classifiers":[
        {
            "category":"Retail",
            "subcategory":"Emissions Testing",
            "type":"Services"
        },
        {
            "category":"Professional",
            "subcategory":"Testing Lab",
            "type":"Services"
        }
    ],
    "sg:phone":"+44 1202 624575",
    "sg:postcode":"BH16 5DA",
    "sg:province":"Dorset",
    "sg:tags":[
        "mot"
    ],
    "sg:website":"http://www.hemscott.net",
    "wof:name":"R D Motors",
    "wof:placetype":"venue"
},
  "geometry": {"coordinates":[-2.018951,50.730297],"type":"Point"}
}