{
  "type": "Feature",
  "properties": {
    "iso:country":"GB",
    "sg:address":"Pheonix Ho, Staithes Rd",
    "sg:city":"Gateshead",
    "sg:classifiers":[
        {
            "category":"Building & Trades",
            "subcategory":"Construction",
            "type":"Services"
        }
    ],
    "sg:phone":"+44 191 460 0360",
    "sg:postcode":"NE11 9DR",
    "sg:province":"Tyne and Wear",
    "sg:tags":[
        "heating",
        "contractor"
    ],
    "wof:name":"M R Heating Services",
    "wof:placetype":"venue"
},
  "geometry": {"coordinates":[-1.6389600039,54.9567985535],"type":"Point"}
}