{
  "type": "Feature",
  "properties": {
    "addr:full":"Dover Lodge, 117 Charlotte Street Fraserburgh Aberdeenshire AB43 9LS",
    "addr:housenumber":"117",
    "addr:postcode":"ab43 9ls",
    "addr:street":"Charlotte Street",
    "iso:country":"GB",
    "sg:address":"Dover Lodge, 117 Charlotte Street",
    "sg:city":"Fraserburgh",
    "sg:classifiers":[
        {
            "category":"Government",
            "subcategory":"Office",
            "type":"Public Place"
        }
    ],
    "sg:phone":"+44 1346 515303",
    "sg:postcode":"AB43 9LS",
    "sg:province":"Aberdeenshire",
    "sg:tags":[
        "local"
    ],
    "wof:name":"ABERDEENSHIRE COUNCIL",
    "wof:placetype":"venue"
},
  "geometry": {"coordinates":[-2.010809,57.690781],"type":"Point"}
}