{
  "type": "Feature",
  "properties": {
    "iso:country":"GB",
    "sg:address":"284 Astwood Road",
    "sg:city":"Worcester",
    "sg:classifiers":[
        {
            "category":"Military Area",
            "subcategory":"Air Force Base",
            "type":"Public Place"
        }
    ],
    "sg:postcode":"WR3 8DD",
    "sg:province":"Worcestershire",
    "sg:tags":[
        "taxi",
        "hire",
        "private"
    ],
    "wof:name":"Golden Wings (Worcester) Ltd.",
    "wof:placetype":"venue"
},
  "geometry": {"coordinates":[-2.205299,52.2066],"type":"Point"}
}