{
  "type": "Feature",
  "properties": {
    "iso:country":"GB",
    "sg:address":"Back Market St, Earlestown",
    "sg:city":"Newton Le Willows",
    "sg:classifiers":[
        {
            "category":"Organizations",
            "subcategory":"Membership Organization",
            "type":"Services"
        }
    ],
    "sg:phone":"+44 1925 224436",
    "sg:postcode":"WA12 9DR",
    "sg:province":"Cheshire",
    "sg:tags":[
        "club"
    ],
    "wof:name":"The Shamrock Club",
    "wof:placetype":"venue"
},
  "geometry": {"coordinates":[-2.645804,53.45488],"type":"Point"}
}