{
  "type": "Feature",
  "properties": {
    "iso:country":"GB",
    "sg:address":"Unit 10 Diplock Building, Diplock Way",
    "sg:city":"Hailsham",
    "sg:classifiers":[
        {
            "category":"Professional",
            "subcategory":"Printing & Photocopies",
            "type":"Services"
        }
    ],
    "sg:phone":"+44 1323 449477",
    "sg:postcode":"BN27 3JF",
    "sg:province":"East Sussex",
    "sg:tags":[
        "plate",
        "lithographic",
        "maker"
    ],
    "wof:name":"M & S Print Services Ltd.",
    "wof:placetype":"venue"
},
  "geometry": {"coordinates":[0.24744,50.863106],"type":"Point"}
}