{
  "type": "Feature",
  "properties": {
    "iso:country":"GB",
    "sg:address":"28 Kirkgate",
    "sg:city":"Tadcaster",
    "sg:classifiers":[
        {
            "category":"Shopping",
            "subcategory":"News",
            "type":"Retail Goods"
        }
    ],
    "sg:phone":"+44 1937 835170",
    "sg:postcode":"LS24 9AD",
    "sg:province":"North Yorkshire",
    "sg:tags":[
        "newsagent"
    ],
    "wof:name":"The Old Chocolate Box",
    "wof:placetype":"venue"
},
  "geometry": {"coordinates":[-1.261693,53.884354],"type":"Point"}
}