{
  "type": "Feature",
  "properties": {
    "iso:country":"GB",
    "sg:address":"10-14 Fitzwilliam Street",
    "sg:city":"Rushden",
    "sg:classifiers":[
        {
            "category":"Manufacturing",
            "subcategory":"Building Materials",
            "type":"Manufacturing & Wholesale Goods"
        }
    ],
    "sg:phone":"+44 1933 312452",
    "sg:postcode":"NN10 9YR",
    "sg:province":"Bedfordshire",
    "sg:tags":[
        "merchant",
        "builder"
    ],
    "wof:name":"Building & Homemaker Supply Co. Ltd.",
    "wof:placetype":"venue"
},
  "geometry": {"coordinates":[-0.6015819907,52.2909049988],"type":"Point"}
}