{
  "type": "Feature",
  "properties": {
    "iso:country":"GB",
    "sg:address":"123a Shakespeare Street",
    "sg:city":"Southport",
    "sg:classifiers":[
        {
            "category":"Retail",
            "subcategory":"Auto Repair",
            "type":"Services"
        }
    ],
    "sg:phone":"+44 1704 500184",
    "sg:postcode":"PR8 5AN",
    "sg:province":"Lancashire",
    "sg:tags":[
        "modification",
        "garage"
    ],
    "wof:name":"J Houghton & Sons",
    "wof:placetype":"venue"
},
  "geometry": {"coordinates":[-3.00624,53.638332],"type":"Point"}
}