{
  "type": "Feature",
  "properties": {
    "addr:full":"18 The Mall, Arndale Centre Nelson Lancashire BB9 9XZ",
    "addr:housenumber":"18",
    "addr:postcode":"bb9 9xz",
    "addr:street":"The Mall Arndale Centre",
    "iso:country":"GB",
    "sg:address":"18 The Mall, Arndale Centre",
    "sg:city":"Nelson",
    "sg:classifiers":[
        {
            "category":"Shopping",
            "subcategory":"Stationery & Office Supplies",
            "type":"Retail Goods"
        }
    ],
    "sg:phone":"+44 1282 615619",
    "sg:postcode":"BB9 9XZ",
    "sg:province":"Lancashire",
    "wof:name":"Stationery Box Ltd.",
    "wof:placetype":"venue"
},
  "geometry": {"coordinates":[-2.213340044,53.8359680176],"type":"Point"}
}