{
  "type": "Feature",
  "properties": {
    "iso:country":"GB",
    "sg:address":"319 Hasland Road, Hasland",
    "sg:city":"Chesterfield",
    "sg:classifiers":[
        {
            "category":"Building & Trades",
            "subcategory":"Landscaping Services",
            "type":"Services"
        },
        {
            "category":"Professional",
            "subcategory":"Printing & Photocopies",
            "type":"Services"
        }
    ],
    "sg:phone":"+44 1246 555525",
    "sg:postcode":"S41 0AA",
    "sg:province":"Derbyshire",
    "sg:tags":[
        "horticultural",
        "duplicating",
        "copying",
        "consultant"
    ],
    "wof:name":"Copy Wise",
    "wof:placetype":"venue"
},
  "geometry": {"coordinates":[-1.413455,53.223064],"type":"Point"}
}