{
  "type": "Feature",
  "properties": {
    "addr:full":"121 Princes Avenue Walsall West Midlands WS1 2DH",
    "addr:housenumber":"121",
    "addr:postcode":"ws1 2dh",
    "addr:street":"Princes Avenue",
    "iso:country":"GB",
    "sg:address":"121 Princes Avenue",
    "sg:city":"Walsall",
    "sg:classifiers":[
        {
            "category":"Retail",
            "subcategory":"Laundry & Dry Cleaning",
            "type":"Services"
        }
    ],
    "sg:phone":"+44 1922 620963",
    "sg:postcode":"WS1 2DH",
    "sg:province":"West Midlands",
    "sg:tags":[
        "launderette"
    ],
    "wof:name":"Broadway Cleaning",
    "wof:placetype":"venue"
},
  "geometry": {"coordinates":[-1.9647419453,52.5847930908],"type":"Point"}
}