{
  "type": "Feature",
  "properties": {
    "addr:full":"18 Church Farm Rd Sittingbourne Kent ME9 7AG",
    "addr:housenumber":"18",
    "addr:postcode":"me9 7ag",
    "addr:street":"Church Farm Rd",
    "iso:country":"GB",
    "sg:address":"18 Church Farm Rd",
    "sg:city":"Sittingbourne",
    "sg:classifiers":[
        {
            "category":"Shopping",
            "subcategory":"Catalog Store",
            "type":"Retail Goods"
        }
    ],
    "sg:phone":"+44 1634 231303",
    "sg:postcode":"ME9 7AG",
    "sg:province":"Kent",
    "sg:tags":[
        "mail",
        "order"
    ],
    "wof:name":"Kleeneze",
    "wof:placetype":"venue"
},
  "geometry": {"coordinates":[0.648731,51.375694],"type":"Point"}
}