{
  "type": "Feature",
  "properties": {
    "addr:full":"1 Poplar Street, Waldridge Chester-le-street Durham DH2 3SE",
    "addr:housenumber":"1",
    "addr:postcode":"dh2 3se",
    "addr:street":"Poplar Street",
    "iso:country":"GB",
    "sg:address":"1 Poplar Street, Waldridge",
    "sg:city":"Chester-le-street",
    "sg:classifiers":[
        {
            "category":"Government",
            "subcategory":"Office",
            "type":"Public Place"
        }
    ],
    "sg:phone":"+44 191 388 4996",
    "sg:postcode":"DH2 3SE",
    "sg:province":"Durham",
    "sg:tags":[
        "education",
        "agency",
        "authority"
    ],
    "wof:name":"The Village Montessori Nursery School",
    "wof:placetype":"venue"
},
  "geometry": {"coordinates":[-1.6086740494,54.8466262817],"type":"Point"}
}