{
  "type": "Feature",
  "properties": {
    "addr:full":"Ormond House, Montpellier Cheltenham Gloucestershire GL50 1SH",
    "addr:postcode":"gl50 1sh",
    "iso:country":"GB",
    "sg:address":"Ormond House, Montpellier",
    "sg:city":"Cheltenham",
    "sg:classifiers":[
        {
            "category":"Shopping",
            "subcategory":"Music",
            "type":"Retail Goods"
        },
        {
            "category":"Food & Beverages",
            "subcategory":"Groceries & Convenience Stores",
            "type":"Retail Goods"
        }
    ],
    "sg:phone":"+44 1242 512056",
    "sg:postcode":"GL50 1SH",
    "sg:province":"Gloucestershire",
    "sg:tags":[
        "shop"
    ],
    "wof:name":"Montpellier News",
    "wof:placetype":"venue"
},
  "geometry": {"coordinates":[-2.0764839649,51.8946990967],"type":"Point"}
}