{
  "type": "Feature",
  "properties": {
    "addr:full":"66 Suffolk Road Cheltenham Gloucestershire GL50 2ED",
    "addr:housenumber":"66",
    "addr:postcode":"gl50 2ed",
    "addr:street":"Suffolk Road",
    "iso:country":"GB",
    "sg:address":"66 Suffolk Road",
    "sg:city":"Cheltenham",
    "sg:classifiers":[
        {
            "category":"Retail",
            "subcategory":"Event Space",
            "type":"Services"
        },
        {
            "category":"Health Services",
            "subcategory":"Health Practitioner",
            "type":"Services"
        },
        {
            "category":"Shopping",
            "subcategory":"Pharmacy",
            "type":"Retail Goods"
        },
        {
            "category":"Health Services",
            "subcategory":"Clinic",
            "type":"Services"
        }
    ],
    "sg:postcode":"GL50 2ED",
    "sg:province":"Gloucestershire",
    "sg:tags":[
        "aromatherapy",
        "psychotherapist",
        "technique",
        "medicine",
        "therapy",
        "relaxation",
        "acupuncture"
    ],
    "wof:name":"Cheltenham Holistic Health Centre",
    "wof:placetype":"venue"
},
  "geometry": {"coordinates":[-2.082998991,51.8919792175],"type":"Point"}
}