{
  "type": "Feature",
  "properties": {
    "iso:country":"GB",
    "sg:address":"Unit A, Millbrook Business Centre, Floats Road",
    "sg:city":"Manchester",
    "sg:classifiers":[
        {
            "category":"Professional",
            "subcategory":"Testing Lab",
            "type":"Services"
        }
    ],
    "sg:phone":"+44 161 286 7890",
    "sg:postcode":"M23 9YJ",
    "sg:province":"Cheshire",
    "sg:tags":[
        "laboratory"
    ],
    "wof:name":"G C 2 Chromatography Ltd.",
    "wof:placetype":"venue"
},
  "geometry": {"coordinates":[-2.29648,53.389225],"type":"Point"}
}