{
  "type": "Feature",
  "properties": {
    "iso:country":"GB",
    "sg:address":"7a Merkins Avenue, Bellsmyre",
    "sg:city":"Dumbarton",
    "sg:classifiers":[
        {
            "category":"Shopping",
            "subcategory":"News",
            "type":"Retail Goods"
        }
    ],
    "sg:postcode":"G82 3EB",
    "sg:province":"Argyll and Bute",
    "sg:tags":[
        "newsagent"
    ],
    "wof:name":"J & D McDonald",
    "wof:placetype":"venue"
},
  "geometry": {"coordinates":[-4.5533308983,55.9577407837],"type":"Point"}
}