{
  "type": "Feature",
  "properties": {
    "iso:country":"GB",
    "sg:address":"25 Hayter Road",
    "sg:city":"London",
    "sg:classifiers":[
        {
            "category":"Communications",
            "subcategory":"Newspaper",
            "type":"Services"
        },
        {
            "category":"Shopping",
            "subcategory":"Books",
            "type":"Retail Goods"
        }
    ],
    "sg:phone":"+44 20 7737 8280",
    "sg:postcode":"SW2 5AR",
    "sg:province":"Greater London",
    "sg:tags":[
        "magazine"
    ],
    "wof:name":"Global Africa Pocket News",
    "wof:placetype":"venue"
},
  "geometry": {"coordinates":[-0.120278,51.457664],"type":"Point"}
}