{
  "type": "Feature",
  "properties": {
    "iso:country":"GB",
    "sg:address":"6 Honey Street",
    "sg:city":"Manchester",
    "sg:classifiers":[
        {
            "category":"Bars & Pubs",
            "type":"Food & Drink"
        }
    ],
    "sg:phone":"+44 161 834 4239",
    "sg:postcode":"M8 8RG",
    "sg:province":"Greater Manchester",
    "sg:tags":[
        "pubs",
        "inn"
    ],
    "wof:name":"The Queens Arms",
    "wof:placetype":"venue"
},
  "geometry": {"coordinates":[-2.235961,53.492943],"type":"Point"}
}