{
  "type": "Feature",
  "properties": {
    "addr:full":"Unit 15 Beechwood Business Park, Burdock Close Cannock Staffordshire WS11 2GB",
    "addr:housenumber":"unit 15",
    "addr:postcode":"ws11 2gb",
    "addr:street":"Beechwood Business Park Burdock Close",
    "iso:country":"GB",
    "sg:address":"Unit 15 Beechwood Business Park, Burdock Close",
    "sg:city":"Cannock",
    "sg:classifiers":[
        {
            "category":"Manufacturing",
            "subcategory":"Metals",
            "type":"Manufacturing & Wholesale Goods"
        }
    ],
    "sg:phone":"+44 1543 500811",
    "sg:postcode":"WS11 2GB",
    "sg:province":"Staffordshire",
    "sg:tags":[
        "die-casting"
    ],
    "wof:name":"Italpresse (U K) Ltd.",
    "wof:placetype":"venue"
},
  "geometry": {"coordinates":[-2.033145,52.690952],"type":"Point"}
}