{
  "type": "Feature",
  "properties": {
    "addr:full":"26-28 Chancery St Leicester Leicestershire LE1 5WD",
    "addr:housenumber":"26-28",
    "addr:postcode":"le1 5wd",
    "addr:street":"Chancery St",
    "iso:country":"GB",
    "sg:address":"26-28 Chancery St",
    "sg:city":"Leicester",
    "sg:classifiers":[
        {
            "category":"Professional",
            "subcategory":"Employment Agencies",
            "type":"Services"
        }
    ],
    "sg:phone":"+44 116 254 8882",
    "sg:postcode":"LE1 5WD",
    "sg:province":"Leicestershire",
    "sg:tags":[
        "consultant"
    ],
    "wof:name":"Itec Recruitment",
    "wof:placetype":"venue"
},
  "geometry": {"coordinates":[-1.1349289417,52.632270813],"type":"Point"}
}