{
  "type": "Feature",
  "properties": {
    "iso:country":"GB",
    "sg:address":"Westbank Terminal, Wherstead Road",
    "sg:city":"Ipswich",
    "sg:classifiers":[
        {
            "category":"Manufacturing",
            "subcategory":"Lumber",
            "type":"Manufacturing & Wholesale Goods"
        }
    ],
    "sg:phone":"+44 1473 692753",
    "sg:postcode":"IP2 8NB",
    "sg:province":"Suffolk",
    "sg:tags":[
        "importer",
        "merchants",
        "agent",
        "timber"
    ],
    "wof:name":"Westbank Timber Ltd.",
    "wof:placetype":"venue"
},
  "geometry": {"coordinates":[1.15434,52.041721],"type":"Point"}
}