{
  "type": "Feature",
  "properties": {
    "addr:full":"27 Bonds Mill Stonehouse Gloucestershire GL10 3RG",
    "addr:housenumber":"27",
    "addr:postcode":"gl10 3rg",
    "addr:street":"Bonds Mill",
    "iso:country":"GB",
    "sg:address":"27 Bonds Mill",
    "sg:city":"Stonehouse",
    "sg:classifiers":[
        {
            "category":"Home & Garden",
            "subcategory":"Carpets & Floor Coverings",
            "type":"Retail Goods"
        }
    ],
    "sg:postcode":"GL10 3RG",
    "sg:province":"Gloucestershire",
    "sg:tags":[
        "carpets",
        "rug",
        "matting"
    ],
    "wof:name":"Morgan,S,",
    "wof:placetype":"venue"
},
  "geometry": {"coordinates":[-2.299894,51.746845],"type":"Point"}
}