{
  "type": "Feature",
  "properties": {
    "iso:country":"GB",
    "sg:address":"5 High Street",
    "sg:city":"Leighton Buzzard",
    "sg:classifiers":[
        {
            "category":"Shopping",
            "subcategory":"Clothing, Apparel, & Fashions",
            "type":"Retail Goods"
        }
    ],
    "sg:postcode":"LU7 1DN",
    "sg:province":"Bedfordshire",
    "sg:tags":[
        "menswear"
    ],
    "wof:name":"M Taylor",
    "wof:placetype":"venue"
},
  "geometry": {"coordinates":[-0.662386,51.916416],"type":"Point"}
}