{
  "type": "Feature",
  "properties": {
    "addr:full":"Milbourne House, 66-70 Coombe Road New Malden Surrey KT3 4QW",
    "addr:housenumber":"66-70",
    "addr:postcode":"kt3 4qw",
    "addr:street":"Coombe Road",
    "iso:country":"GB",
    "sg:address":"Milbourne House, 66-70 Coombe Road",
    "sg:city":"New Malden",
    "sg:classifiers":[
        {
            "category":"Banks & Credit Unions",
            "subcategory":"Financial Services",
            "type":"Services"
        }
    ],
    "sg:phone":"+44 20 8949 4261",
    "sg:postcode":"KT3 4QW",
    "sg:province":"Surrey",
    "sg:tags":[
        "adviser"
    ],
    "wof:name":"Milbourne Financial Services Ltd.",
    "wof:placetype":"venue"
},
  "geometry": {"coordinates":[-0.2572070062,51.4055099487],"type":"Point"}
}