{
  "type": "Feature",
  "properties": {
    "addr:full":"12 Oulton Clo Aylesbury Buckinghamshire HP21 7JY",
    "addr:housenumber":"12",
    "addr:postcode":"hp21 7jy",
    "addr:street":"Oulton Clo",
    "iso:country":"GB",
    "sg:address":"12 Oulton Clo",
    "sg:city":"Aylesbury",
    "sg:classifiers":[
        {
            "category":"Home & Garden",
            "subcategory":"Household Appliances",
            "type":"Retail Goods"
        }
    ],
    "sg:postcode":"HP21 7JY",
    "sg:province":"Buckinghamshire",
    "sg:tags":[
        "electrical"
    ],
    "wof:name":"Bruce,Michael R,",
    "wof:placetype":"venue"
},
  "geometry": {"coordinates":[-0.792877,51.804085],"type":"Point"}
}