{
  "type": "Feature",
  "properties": {
    "addr:full":"46 Penrhiwceiber Road Mountain Ash Rhondda, Cynon, Taff CF45 3SP",
    "addr:housenumber":"46",
    "addr:postcode":"cf45 3sp",
    "addr:street":"Penrhiwceiber Road;Cynon Taff",
    "iso:country":"GB",
    "sg:address":"46 Penrhiwceiber Road",
    "sg:city":"Mountain Ash",
    "sg:classifiers":[
        {
            "category":"Shopping",
            "subcategory":"Pets & Pet Supplies",
            "type":"Retail Goods"
        }
    ],
    "sg:postcode":"CF45 3SP",
    "sg:province":"Rhondda, Cynon, Taff",
    "wof:name":"I C S Corn Stores",
    "wof:placetype":"venue"
},
  "geometry": {"coordinates":[-3.36124,51.669453],"type":"Point"}
}