{
  "type": "Feature",
  "properties": {
    "iso:country":"GB",
    "sg:address":"44a Seafield Road",
    "sg:city":"Inverness",
    "sg:classifiers":[
        {
            "category":"Retail",
            "subcategory":"Repair Shop",
            "type":"Services"
        }
    ],
    "sg:phone":"+44 1463 221126",
    "sg:postcode":"IV1 1SG",
    "sg:province":"Highland",
    "sg:tags":[
        "upholstering",
        "upholsterer"
    ],
    "wof:name":"Mcewan Of Inverness",
    "wof:placetype":"venue"
},
  "geometry": {"coordinates":[-4.216274,57.487217],"type":"Point"}
}