{
  "type": "Feature",
  "properties": {
    "addr:full":"Pennygate Spalding Lincolnshire PE11 1NW",
    "addr:postcode":"pe11 1nw",
    "addr:street":"Pennygate Spalding",
    "iso:country":"GB",
    "sg:address":"Pennygate",
    "sg:city":"Spalding",
    "sg:classifiers":[
        {
            "category":"Retail",
            "subcategory":"Storage",
            "type":"Services"
        }
    ],
    "sg:phone":"+44 1775 724607",
    "sg:postcode":"PE11 1NW",
    "sg:province":"Lincolnshire",
    "sg:tags":[
        "cold"
    ],
    "wof:name":"West End Cold Stores Ltd.",
    "wof:placetype":"venue"
},
  "geometry": {"coordinates":[-0.162084,52.789066],"type":"Point"}
}