{
  "type": "Feature",
  "properties": {
    "iso:country":"GB",
    "sg:address":"Bagden Hall Farm, Wakefield Road, Scissett",
    "sg:city":"Huddersfield",
    "sg:classifiers":[
        {
            "category":"Farming",
            "subcategory":"Dairy Farm",
            "type":"Manufacturing & Wholesale Goods"
        }
    ],
    "sg:phone":"+44 1484 863549",
    "sg:postcode":"HD8 9LE",
    "sg:province":"South Yorkshire",
    "wof:name":"D Dodson & Sons",
    "wof:placetype":"venue"
},
  "geometry": {"coordinates":[-1.609244,53.600716],"type":"Point"}
}