{
  "type": "Feature",
  "properties": {
    "addr:full":"16a North Bar St Banbury Oxfordshire OX16 0TF",
    "addr:housenumber":"16a",
    "addr:postcode":"ox16 0tf",
    "addr:street":"North Bar St",
    "iso:country":"GB",
    "sg:address":"16a North Bar St",
    "sg:city":"Banbury",
    "sg:classifiers":[
        {
            "category":"Organizations",
            "subcategory":"Political Organization",
            "type":"Services"
        }
    ],
    "sg:phone":"+44 1295 262341",
    "sg:postcode":"OX16 0TF",
    "sg:province":"Oxfordshire",
    "sg:tags":[
        "party"
    ],
    "wof:name":"Conservative Party The",
    "wof:placetype":"venue"
},
  "geometry": {"coordinates":[-1.339729,52.062908],"type":"Point"}
}