{
  "type": "Feature",
  "properties": {
    "addr:full":"15 King Street Whitehaven Cumbria CA28 7ED",
    "addr:housenumber":"15",
    "addr:postcode":"ca28 7ed",
    "addr:street":"King Street",
    "iso:country":"GB",
    "sg:address":"15 King Street",
    "sg:city":"Whitehaven",
    "sg:classifiers":[
        {
            "category":"Retail",
            "subcategory":"Photofinishing",
            "type":"Services"
        }
    ],
    "sg:postcode":"CA28 7ED",
    "sg:province":"Cumbria",
    "sg:tags":[
        "photographic",
        "processor"
    ],
    "wof:name":"P D Hendren Cameras",
    "wof:placetype":"venue"
},
  "geometry": {"coordinates":[-3.590099,54.548065],"type":"Point"}
}