{
  "type": "Feature",
  "properties": {
    "iso:country":"GB",
    "sg:address":"89 High Street, Coleshill",
    "sg:city":"Birmingham",
    "sg:classifiers":[
        {
            "category":"Shopping",
            "subcategory":"Clothing, Apparel, & Fashions",
            "type":"Retail Goods"
        }
    ],
    "sg:phone":"+44 1675 463837",
    "sg:postcode":"B46 3AG",
    "sg:province":"Warwickshire",
    "sg:tags":[
        "shop"
    ],
    "wof:name":"Gimbles",
    "wof:placetype":"venue"
},
  "geometry": {"coordinates":[-1.7068389654,52.4990692139],"type":"Point"}
}