{
  "type": "Feature",
  "properties": {
    "addr:full":"90 Alpine Road Redhill Surrey RH1 2LF",
    "addr:housenumber":"90",
    "addr:postcode":"rh1 2lf",
    "addr:street":"Alpine Road",
    "iso:country":"GB",
    "sg:address":"90 Alpine Road",
    "sg:city":"Redhill",
    "sg:classifiers":[
        {
            "category":"Retail",
            "subcategory":"Driving School",
            "type":"Services"
        }
    ],
    "sg:postcode":"RH1 2LF",
    "sg:province":"Surrey",
    "wof:name":"Anthony Cooper School of Motoring",
    "wof:placetype":"venue"
},
  "geometry": {"coordinates":[-0.1609289944,51.2495384216],"type":"Point"}
}