{
  "type": "Feature",
  "properties": {
    "addr:full":"Windwood, The Crossway Tunbridge Wells Kent TN4 8NL",
    "addr:postcode":"tn4 8nl",
    "iso:country":"GB",
    "sg:address":"Windwood, The Crossway",
    "sg:city":"Tunbridge Wells",
    "sg:classifiers":[
        {
            "category":"Health Services",
            "subcategory":"Doctor",
            "type":"Services"
        }
    ],
    "sg:postcode":"TN4 8NL",
    "sg:province":"Kent",
    "sg:tags":[
        "surgeon",
        "practitioners"
    ],
    "wof:name":"D B Garrioch",
    "wof:placetype":"venue"
},
  "geometry": {"coordinates":[0.2384900004,51.1283988953],"type":"Point"}
}