{
  "type": "Feature",
  "properties": {
    "iso:country":"GB",
    "sg:address":"Claypits Farm, Coggeshall Road, Earls Colne",
    "sg:city":"Colchester",
    "sg:classifiers":[
        {
            "category":"Farming",
            "subcategory":"Dairy Farm",
            "type":"Manufacturing & Wholesale Goods"
        }
    ],
    "sg:phone":"+44 1787 222525",
    "sg:postcode":"CO6 2JS",
    "sg:province":"Essex",
    "sg:tags":[
        "farmer"
    ],
    "wof:name":"Robert G Bull",
    "wof:placetype":"venue"
},
  "geometry": {"coordinates":[0.699067,51.927967],"type":"Point"}
}