{
  "type": "Feature",
  "properties": {
    "iso:country":"GB",
    "sg:address":"Unit 8 Curtis Units, Manor Furlong Road",
    "sg:city":"Frome",
    "sg:classifiers":[
        {
            "category":"Professional",
            "subcategory":"Printing & Photocopies",
            "type":"Services"
        }
    ],
    "sg:postcode":"BA11 4RN",
    "sg:province":"Somerset",
    "sg:tags":[
        "print",
        "finisher"
    ],
    "wof:name":"Irene Edwards",
    "wof:placetype":"venue"
},
  "geometry": {"coordinates":[-2.327248,51.220543],"type":"Point"}
}