{
  "type": "Feature",
  "properties": {
    "iso:country":"GB",
    "sg:address":"Unit 31 H T M Business Park, Abergele Road, Rhuddlan",
    "sg:city":"Rhyl",
    "sg:classifiers":[
        {
            "category":"Manufacturing",
            "subcategory":"Petroleum Products",
            "type":"Manufacturing & Wholesale Goods"
        }
    ],
    "sg:postcode":"LL18 5UZ",
    "sg:province":"Conwy",
    "sg:tags":[
        "double",
        "glazing"
    ],
    "wof:name":"Cheadle Window Co",
    "wof:placetype":"venue"
},
  "geometry": {"coordinates":[-3.47781,53.28857],"type":"Point"}
}