{
  "type": "Feature",
  "properties": {
    "iso:country":"GB",
    "sg:address":"69 Hook Road",
    "sg:city":"Goole",
    "sg:classifiers":[
        {
            "category":"Health Services",
            "subcategory":"Nursing And Care Facility",
            "type":"Services"
        },
        {
            "category":"Social Services",
            "subcategory":"Retirement Home",
            "type":"Services"
        }
    ],
    "sg:phone":"+44 1405 766217",
    "sg:postcode":"DN14 5JN",
    "sg:province":"East Riding of Yorkshire",
    "sg:tags":[
        "residential"
    ],
    "wof:name":"Shamrock House",
    "wof:placetype":"venue"
},
  "geometry": {"coordinates":[-0.861368,53.705425],"type":"Point"}
}