{
  "type": "Feature",
  "properties": {
    "addr:full":"Portland House, 2 Portland Road, Holland Park London Greater London W11 4LA",
    "addr:housenumber":"2",
    "addr:postcode":"w11 4la",
    "addr:street":"Portland Road",
    "iso:country":"GB",
    "sg:address":"Portland House, 2 Portland Road, Holland Park",
    "sg:city":"London",
    "sg:classifiers":[
        {
            "category":"Professional",
            "subcategory":"Management & Consulting",
            "type":"Services"
        }
    ],
    "sg:phone":"+44 20 7221 7883",
    "sg:postcode":"W11 4LA",
    "sg:province":"Greater London",
    "sg:tags":[
        "consultant",
        "business"
    ],
    "wof:name":"Kallaway Ltd.",
    "wof:placetype":"venue"
},
  "geometry": {"coordinates":[-0.2076060027,51.506778717],"type":"Point"}
}