{
  "type": "Feature",
  "properties": {
    "iso:country":"GB",
    "sg:address":"45 Chiltern Street",
    "sg:city":"London",
    "sg:classifiers":[
        {
            "category":"Real Estate",
            "subcategory":"Real Estate Agent",
            "type":"Services"
        }
    ],
    "sg:phone":"+44 20 7486 6338",
    "sg:postcode":"W1U 6LT",
    "sg:province":"Greater London",
    "wof:name":"Oastcrown Properties Ltd.",
    "wof:placetype":"venue"
},
  "geometry": {"coordinates":[-0.1554459929,51.5197486877],"type":"Point"}
}