{
  "type": "Feature",
  "properties": {
    "iso:country":"GB",
    "sg:address":"14 Worple Road",
    "sg:city":"London",
    "sg:classifiers":[
        {
            "category":"Government",
            "subcategory":"Office",
            "type":"Public Place"
        }
    ],
    "sg:phone":"+44 20 8879 1973",
    "sg:postcode":"SW19 4DD",
    "sg:province":"Greater London",
    "sg:tags":[
        "education",
        "agency",
        "authority"
    ],
    "wof:name":"The Association of Business Executives Ltd.",
    "wof:placetype":"venue"
},
  "geometry": {"coordinates":[-0.2093210071,51.421131134],"type":"Point"}
}