{
  "type": "Feature",
  "properties": {
    "iso:country":"GB",
    "sg:address":"20 The Wharf, Shardlow",
    "sg:city":"Derby",
    "sg:classifiers":[
        {
            "category":"Professional",
            "subcategory":"Secretarial Services",
            "type":"Services"
        }
    ],
    "sg:phone":"+44 1332 792363",
    "sg:postcode":"DE72 2GH",
    "sg:province":"Derbyshire",
    "wof:name":"Advanced Typing Services",
    "wof:placetype":"venue"
},
  "geometry": {"coordinates":[-1.3448120356,52.8688774109],"type":"Point"}
}