{
  "type": "Feature",
  "properties": {
    "iso:country":"GB",
    "sg:address":"Criterion Chambers, Finkle Street",
    "sg:city":"Malton",
    "sg:classifiers":[
        {
            "category":"Health Services",
            "subcategory":"Dentist",
            "type":"Services"
        }
    ],
    "sg:postcode":"YO17 7JD",
    "sg:province":"North Yorkshire",
    "wof:name":"Weir C D Bds (Edin)",
    "wof:placetype":"venue"
},
  "geometry": {"coordinates":[-0.800224,54.137825],"type":"Point"}
}