{
  "type": "Feature",
  "properties": {
    "addr:full":"Unit 20 Silver Court, Inter City Wy Leeds West Yorkshire LS13 4LY",
    "addr:housenumber":"unit 20",
    "addr:postcode":"ls13 4ly",
    "addr:street":"Silver Court;City Wy",
    "iso:country":"GB",
    "sg:address":"Unit 20 Silver Court, Inter City Wy",
    "sg:city":"Leeds",
    "sg:classifiers":[
        {
            "category":"Wholesale",
            "subcategory":"Machinery & Supplies",
            "type":"Manufacturing & Wholesale Goods"
        }
    ],
    "sg:phone":"+44 113 236 1367",
    "sg:postcode":"LS13 4LY",
    "sg:province":"West Yorkshire",
    "sg:tags":[
        "hydraulic"
    ],
    "wof:name":"Hydra-Perm-Co. Ltd.",
    "wof:placetype":"venue"
},
  "geometry": {"coordinates":[-1.6500409842,53.8050613403],"type":"Point"}
}