{
  "type": "Feature",
  "properties": {
    "addr:full":"13 Warwick Road Barnsley South Yorkshire S71 2NN",
    "addr:housenumber":"13",
    "addr:postcode":"s71 2nn",
    "addr:street":"Warwick Road;Yorkshire",
    "iso:country":"GB",
    "sg:address":"13 Warwick Road",
    "sg:city":"Barnsley",
    "sg:classifiers":[
        {
            "category":"Home & Garden",
            "subcategory":"Household Appliances",
            "type":"Retail Goods"
        }
    ],
    "sg:postcode":"S71 2NN",
    "sg:province":"South Yorkshire",
    "sg:tags":[
        "electrical"
    ],
    "wof:name":"The Washer Doctor",
    "wof:placetype":"venue"
},
  "geometry": {"coordinates":[-1.461138,53.562771],"type":"Point"}
}