{
  "type": "Feature",
  "properties": {
    "addr:full":"The Estate Office, Guildford Road, Wotton Dorking Surrey RH5 6QB",
    "addr:postcode":"rh5 6qb",
    "addr:street":"Guildford Road",
    "iso:country":"GB",
    "sg:address":"The Estate Office, Guildford Road, Wotton",
    "sg:city":"Dorking",
    "sg:classifiers":[
        {
            "category":"Farming",
            "subcategory":"Dairy Farm",
            "type":"Manufacturing & Wholesale Goods"
        },
        {
            "category":"Farming",
            "subcategory":"Livestock Farm",
            "type":"Manufacturing & Wholesale Goods"
        }
    ],
    "sg:phone":"+44 1306 730482",
    "sg:postcode":"RH5 6QB",
    "sg:province":"Surrey",
    "sg:tags":[
        "others",
        "farmer"
    ],
    "wof:name":"J P M H Evelyn",
    "wof:placetype":"venue"
},
  "geometry": {"coordinates":[-0.389594,51.216721],"type":"Point"}
}