{
  "type": "Feature",
  "properties": {
    "iso:country":"GB",
    "sg:address":"25-27 Victoria Road",
    "sg:city":"Cirencester",
    "sg:classifiers":[
        {
            "category":"Retail",
            "subcategory":"Auto Repair",
            "type":"Services"
        }
    ],
    "sg:phone":"+44 1285 653020",
    "sg:postcode":"GL7 1EN",
    "sg:province":"Gloucestershire",
    "sg:tags":[
        "modification",
        "garage"
    ],
    "wof:name":"Bennetts Garage",
    "wof:placetype":"venue"
},
  "geometry": {"coordinates":[-1.9615830183,51.7149734497],"type":"Point"}
}