{
  "type": "Feature",
  "properties": {
    "addr:full":"14 Broad Street Ludlow Herefordshire SY8 1NG",
    "addr:housenumber":"14",
    "addr:postcode":"sy8 1ng",
    "addr:street":"Broad Street",
    "iso:country":"GB",
    "sg:address":"14 Broad Street",
    "sg:city":"Ludlow",
    "sg:classifiers":[
        {
            "category":"Shopping",
            "subcategory":"Antiques",
            "type":"Retail Goods"
        }
    ],
    "sg:phone":"+44 1584 873568",
    "sg:postcode":"SY8 1NG",
    "sg:province":"Herefordshire",
    "wof:name":"R G Cave & Sons (Antiques) Ltd.",
    "wof:placetype":"venue"
},
  "geometry": {"coordinates":[-2.718575,52.367126],"type":"Point"}
}