{
  "type": "Feature",
  "properties": {
    "iso:country":"GB",
    "sg:address":"Cleobury Mortimer, Stottesdon",
    "sg:city":"Kidderminster",
    "sg:classifiers":[
        {
            "category":"Home & Garden",
            "subcategory":"Garden Supply",
            "type":"Retail Goods"
        }
    ],
    "sg:postcode":"DY14 8LR",
    "sg:province":"Shropshire",
    "sg:tags":[
        "bulb",
        "grower"
    ],
    "wof:name":"Evelyn Price",
    "wof:placetype":"venue"
},
  "geometry": {"coordinates":[-2.482934,52.378525],"type":"Point"}
}