{
  "type": "Feature",
  "properties": {
    "iso:country":"GB",
    "sg:address":"Shipping Information Office, Curlew Ho, The Dock",
    "sg:city":"Felixstowe",
    "sg:classifiers":[
        {
            "category":"Harbor",
            "type":"Transportation"
        }
    ],
    "sg:phone":"+44 1394 604720",
    "sg:postcode":"IP11 8SR",
    "sg:province":"Suffolk",
    "sg:tags":[
        "dock",
        "ports",
        "harbour"
    ],
    "wof:name":"Port Of Felixstowe",
    "wof:placetype":"venue"
},
  "geometry": {"coordinates":[1.34246,51.961369],"type":"Point"}
}