{
  "type": "Feature",
  "properties": {
    "iso:country":"GB",
    "sg:address":"69-71 Featherstall Road North",
    "sg:city":"Oldham",
    "sg:classifiers":[
        {
            "category":"Restaurant",
            "type":"Food & Drink"
        }
    ],
    "sg:phone":"+44 161 627 0586",
    "sg:postcode":"OL9 6QB",
    "sg:province":"Lancashire",
    "sg:tags":[
        "indian"
    ],
    "wof:name":"Surma Tandoori",
    "wof:placetype":"venue"
},
  "geometry": {"coordinates":[-2.1270940304,53.547416687],"type":"Point"}
}