{
  "type": "Feature",
  "properties": {
    "addr:full":"Kirkhead Road, Kents Bank Grange-over-sands Cumbria LA11 7BG",
    "addr:postcode":"la11 7bg",
    "addr:street":"Kirkhead Road",
    "iso:country":"GB",
    "sg:address":"Kirkhead Road, Kents Bank",
    "sg:city":"Grange-over-sands",
    "sg:classifiers":[
        {
            "category":"Travel",
            "subcategory":"Hotels & Motels",
            "type":"Entertainment"
        }
    ],
    "sg:phone":"+44 15395 32896",
    "sg:postcode":"LA11 7BG",
    "sg:province":"Cumbria",
    "wof:name":"Christian Guild Holidays",
    "wof:placetype":"venue"
},
  "geometry": {"coordinates":[-2.9216399193,54.1841583252],"type":"Point"}
}