{
  "type": "Feature",
  "properties": {
    "addr:full":"33 Station Road Ely Cambridgeshire CB7 4BW",
    "addr:housenumber":"33",
    "addr:postcode":"cb7 4bw",
    "addr:street":"Station Road",
    "iso:country":"GB",
    "sg:address":"33 Station Road",
    "sg:city":"Ely",
    "sg:classifiers":[
        {
            "category":"Retail",
            "subcategory":"Auto Repair",
            "type":"Services"
        }
    ],
    "sg:phone":"+44 1353 667291",
    "sg:postcode":"CB7 4BW",
    "sg:province":"Cambridgeshire",
    "sg:tags":[
        "modification",
        "garage"
    ],
    "wof:name":"Benton",
    "wof:placetype":"venue"
},
  "geometry": {"coordinates":[0.2655920088,52.3937492371],"type":"Point"}
}