{
  "type": "Feature",
  "properties": {
    "iso:country":"GB",
    "sg:address":"Unit 26-27 Sibthorpe Street",
    "sg:city":"Mansfield",
    "sg:classifiers":[
        {
            "category":"Retail",
            "subcategory":"Auto Repair",
            "type":"Services"
        }
    ],
    "sg:postcode":"NG18 5DE",
    "sg:province":"Nottinghamshire",
    "sg:tags":[
        "body",
        "car"
    ],
    "wof:name":"C D K Bodyshop",
    "wof:placetype":"venue"
},
  "geometry": {"coordinates":[-1.204623,53.137394],"type":"Point"}
}