{
  "type": "Feature",
  "properties": {
    "iso:country":"GB",
    "sg:address":"Bryanstone Road",
    "sg:city":"Waltham Cross",
    "sg:classifiers":[
        {
            "category":"Manufacturing",
            "subcategory":"Wood Products",
            "type":"Manufacturing & Wholesale Goods"
        }
    ],
    "sg:phone":"+44 1992 761116",
    "sg:postcode":"EN8 7PJ",
    "sg:province":"Essex",
    "sg:tags":[
        "packaging",
        "crate",
        "pallets"
    ],
    "wof:name":"P R Pallets",
    "wof:placetype":"venue"
},
  "geometry": {"coordinates":[-0.023854,51.685814],"type":"Point"}
}