{
  "type": "Feature",
  "properties": {
    "addr:full":"55 Aldene Rd Sheffield South Yorkshire S6 4BR",
    "addr:housenumber":"55",
    "addr:postcode":"s6 4br",
    "addr:street":"Aldene Rd",
    "iso:country":"GB",
    "sg:address":"55 Aldene Rd",
    "sg:city":"Sheffield",
    "sg:classifiers":[
        {
            "category":"Building & Trades",
            "subcategory":"Plumbing",
            "type":"Services"
        }
    ],
    "sg:phone":"+44 114 234 9188",
    "sg:postcode":"S6 4BR",
    "sg:province":"South Yorkshire",
    "sg:tags":[
        "heating"
    ],
    "wof:name":"Bridges Plumbers",
    "wof:placetype":"venue"
},
  "geometry": {"coordinates":[-1.5243320465,53.4105911255],"type":"Point"}
}