{
  "type": "Feature",
  "properties": {
    "addr:full":"Springfield Mills, Norman Rd Huddersfield South Yorkshire HD8 8TH",
    "addr:postcode":"hd8 8th",
    "addr:street":"Norman Rd",
    "iso:country":"GB",
    "sg:address":"Springfield Mills, Norman Rd",
    "sg:city":"Huddersfield",
    "sg:classifiers":[
        {
            "category":"Shopping",
            "subcategory":"Clothing, Apparel, & Fashions",
            "type":"Retail Goods"
        }
    ],
    "sg:phone":"+44 1484 865082",
    "sg:postcode":"HD8 8TH",
    "sg:province":"South Yorkshire",
    "sg:tags":[
        "shop"
    ],
    "wof:name":"Mill Shop The",
    "wof:placetype":"venue"
},
  "geometry": {"coordinates":[-1.6580499411,53.5718917847],"type":"Point"}
}