{
  "type": "Feature",
  "properties": {
    "addr:full":"Suite 1, 14 Causeway Bishop's Stortford Essex CM23 2EL",
    "addr:housenumber":"suite 1 14",
    "addr:postcode":"cm23 2el",
    "addr:street":"Causeway Bishop'S",
    "iso:country":"GB",
    "sg:address":"Suite 1, 14 Causeway",
    "sg:city":"Bishop's Stortford",
    "sg:classifiers":[
        {
            "category":"Professional",
            "subcategory":"Employment Agencies",
            "type":"Services"
        }
    ],
    "sg:phone":"+44 1279 503117",
    "sg:postcode":"CM23 2EL",
    "sg:province":"Essex",
    "sg:tags":[
        "asbestos",
        "mnfrs",
        "removal"
    ],
    "wof:name":"Sjw Consultancy",
    "wof:placetype":"venue"
},
  "geometry": {"coordinates":[0.16246,51.870209],"type":"Point"}
}