{
  "type": "Feature",
  "properties": {
    "addr:full":"Unit 41 Sutton Coldfield Warwickshire B76 1AH",
    "addr:housenumber":"unit 41",
    "addr:postcode":"b76 1ah",
    "iso:country":"GB",
    "sg:address":"Unit 41",
    "sg:city":"Sutton Coldfield",
    "sg:classifiers":[
        {
            "category":"Manufacturing",
            "subcategory":"Rubber & Plastics",
            "type":"Manufacturing & Wholesale Goods"
        }
    ],
    "sg:postcode":"B76 1AH",
    "sg:province":"Warwickshire",
    "sg:tags":[
        "forming",
        "vacuum"
    ],
    "wof:name":"Plastic Shapes Ltd.",
    "wof:placetype":"venue"
},
  "geometry": {"coordinates":[-1.8002090454,52.5385093689],"type":"Point"}
}