{
  "type": "Feature",
  "properties": {
    "addr:full":"Unit 19a Fowkes Road, Hay Lane Trading Estate, Lye Stourbridge West Midlands DY9 8TQ",
    "addr:housenumber":"unit 19a",
    "addr:postcode":"dy9 8tq",
    "addr:street":"Fowkes Road Hay Lane Trading Estate",
    "iso:country":"GB",
    "sg:address":"Unit 19a Fowkes Road, Hay Lane Trading Estate, Lye",
    "sg:city":"Stourbridge",
    "sg:classifiers":[
        {
            "category":"Freight",
            "type":"Transportation"
        }
    ],
    "sg:phone":"+44 1384 891204",
    "sg:postcode":"DY9 8TQ",
    "sg:province":"West Midlands",
    "sg:tags":[
        "haulage",
        "road"
    ],
    "wof:name":"C J Transport",
    "wof:placetype":"venue"
},
  "geometry": {"coordinates":[-2.1022720337,52.4591522217],"type":"Point"}
}