{
  "type": "Feature",
  "properties": {
    "addr:full":"4 Water Lane, Oakington Cambridge Cambridgeshire CB4 5AL",
    "addr:housenumber":"4",
    "addr:postcode":"cb4 5al",
    "addr:street":"Water Lane",
    "iso:country":"GB",
    "sg:address":"4 Water Lane, Oakington",
    "sg:city":"Cambridge",
    "sg:classifiers":[
        {
            "category":"Retail",
            "subcategory":"Auto Repair",
            "type":"Services"
        }
    ],
    "sg:phone":"+44 1223 233250",
    "sg:postcode":"CB4 5AL",
    "sg:province":"Cambridgeshire",
    "sg:tags":[
        "body",
        "car"
    ],
    "wof:name":"L F Dean & Sons",
    "wof:placetype":"venue"
},
  "geometry": {"coordinates":[0.065267,52.258305],"type":"Point"}
}