{
  "type": "Feature",
  "properties": {
    "addr:full":"23 Shore Street Anstruther Fife KY10 3AQ",
    "addr:housenumber":"23",
    "addr:postcode":"ky10 3aq",
    "addr:street":"Shore Street",
    "iso:country":"GB",
    "sg:address":"23 Shore Street",
    "sg:city":"Anstruther",
    "sg:classifiers":[
        {
            "category":"Food & Beverages",
            "subcategory":"Meat & Fish",
            "type":"Retail Goods"
        }
    ],
    "sg:phone":"+44 1333 310546",
    "sg:postcode":"KY10 3AQ",
    "sg:province":"Fife",
    "sg:tags":[
        "butcher"
    ],
    "wof:name":"James Syme Butchers",
    "wof:placetype":"venue"
},
  "geometry": {"coordinates":[-2.6832299232,56.2257232666],"type":"Point"}
}