{
  "type": "Feature",
  "properties": {
    "addr:full":"Elm Rd Reading Berkshire RG6 5TS",
    "addr:postcode":"rg6 5ts",
    "addr:street":"Elm Rd",
    "iso:country":"GB",
    "sg:address":"Elm Rd",
    "sg:city":"Reading",
    "sg:classifiers":[
        {
            "category":"Place Of Worship",
            "type":"Public Place"
        }
    ],
    "sg:phone":"+44 118 987 1718",
    "sg:postcode":"RG6 5TS",
    "sg:province":"Berkshire",
    "wof:name":"St. Barnabas Church",
    "wof:placetype":"venue"
},
  "geometry": {"coordinates":[-0.943568,51.429508],"type":"Point"}
}