{
  "type": "Feature",
  "properties": {
    "addr:full":"1 Artillary Row 204 London Road, Ackworth Road, Hilsea Portsmouth Hampshire PO3 5HU",
    "addr:housenumber":"1;204",
    "addr:postcode":"hampshire po3 5hu",
    "addr:street":"Artillary Row;London Road Ackworth Road",
    "iso:country":"GB",
    "sg:address":"1 Artillary Row 204 London Road, Ackworth Road, Hilsea",
    "sg:city":"Portsmouth",
    "sg:classifiers":[
        {
            "category":"Manufacturing",
            "subcategory":"Metals",
            "type":"Manufacturing & Wholesale Goods"
        }
    ],
    "sg:postcode":"PO3 5HU",
    "sg:province":"Hampshire",
    "sg:tags":[
        "steel",
        "fabricator",
        "erectors"
    ],
    "wof:name":"B S Steels Ltd.",
    "wof:placetype":"venue"
},
  "geometry": {"coordinates":[-1.0594899654,50.8331794739],"type":"Point"}
}