{
  "type": "Feature",
  "properties": {
    "iso:country":"GB",
    "sg:address":"4-7a Blackall Industrial Estate, Hamberts Road, South Woodham Ferrers",
    "sg:city":"Chelmsford",
    "sg:classifiers":[
        {
            "category":"Utilities",
            "subcategory":"Recycling",
            "type":"Services"
        },
        {
            "category":"Home & Garden",
            "subcategory":"Hardware",
            "type":"Retail Goods"
        }
    ],
    "sg:phone":"+44 1245 324900",
    "sg:postcode":"CM3 5UW",
    "sg:province":"Essex",
    "sg:tags":[
        "equipment",
        "heating",
        "sale"
    ],
    "wof:name":"Smith's Environmental Products Ltd.",
    "wof:placetype":"venue"
},
  "geometry": {"coordinates":[0.6225900054,51.6519088745],"type":"Point"}
}