{
  "type": "Feature",
  "properties": {
    "addr:full":"Peal House, Peal Rd, West Pimbo Skelmersdale Lancashire WN8 9PT",
    "addr:postcode":"wn8 9pt",
    "addr:street":"Peal Rd West",
    "iso:country":"GB",
    "sg:address":"Peal House, Peal Rd, West Pimbo",
    "sg:city":"Skelmersdale",
    "sg:classifiers":[
        {
            "category":"Professional",
            "subcategory":"Engineering",
            "type":"Services"
        }
    ],
    "sg:phone":"+44 1695 50586",
    "sg:postcode":"WN8 9PT",
    "sg:province":"Lancashire",
    "sg:tags":[
        "contractor",
        "electrical",
        "engineer"
    ],
    "wof:name":"Kaltec Instrumentation Ltd",
    "wof:placetype":"venue"
},
  "geometry": {"coordinates":[-2.754859,53.530418],"type":"Point"}
}