{
  "type": "Feature",
  "properties": {
    "iso:country":"GB",
    "sg:address":"8 Hawkins Av",
    "sg:city":"Chapeltown",
    "sg:classifiers":[
        {
            "category":"Home & Garden",
            "subcategory":"Kitchen Supply",
            "type":"Retail Goods"
        }
    ],
    "sg:phone":"+44 114 245 4006",
    "sg:postcode":"S35 1TU",
    "sg:province":"South Yorkshire",
    "sg:tags":[
        "equipment",
        "catering"
    ],
    "wof:name":"Cross Catering Equipment",
    "wof:placetype":"venue"
},
  "geometry": {"coordinates":[-1.4801640511,53.4618186951],"type":"Point"}
}