{
  "type": "Feature",
  "properties": {
    "iso:country":"GB",
    "sg:address":"Woolram Wygate",
    "sg:city":"Spalding",
    "sg:classifiers":[
        {
            "category":"Health Services",
            "subcategory":"Nursing And Care Facility",
            "type":"Services"
        },
        {
            "category":"Social Services",
            "subcategory":"Retirement Home",
            "type":"Services"
        }
    ],
    "sg:phone":"+44 1775 724612",
    "sg:postcode":"PE11 1PS",
    "sg:province":"Lincolnshire",
    "sg:tags":[
        "residential"
    ],
    "wof:name":"Southfield House",
    "wof:placetype":"venue"
},
  "geometry": {"coordinates":[-0.162351,52.795422],"type":"Point"}
}