{
  "type": "Feature",
  "properties": {
    "iso:country":"GB",
    "sg:address":"90 High Street",
    "sg:city":"Dalkeith",
    "sg:classifiers":[
        {
            "category":"Shopping",
            "subcategory":"Gifts & Souvenirs",
            "type":"Retail Goods"
        }
    ],
    "sg:phone":"+44 131 663 2381",
    "sg:postcode":"EH22 1HZ",
    "sg:province":"City of Edinburgh",
    "sg:tags":[
        "shop"
    ],
    "wof:name":"Shopping Mall Ltd.",
    "wof:placetype":"venue"
},
  "geometry": {"coordinates":[-3.070044,55.894417],"type":"Point"}
}