{
  "type": "Feature",
  "properties": {
    "iso:country":"GB",
    "sg:address":"The Glade",
    "sg:city":"Epsom",
    "sg:classifiers":[
        {
            "category":"Place Of Worship",
            "type":"Public Place"
        }
    ],
    "sg:phone":"+44 20 8393 3012",
    "sg:postcode":"KT17 2HL",
    "sg:province":"Surrey",
    "wof:name":"Stoneleigh Baptist Church",
    "wof:placetype":"venue"
},
  "geometry": {"coordinates":[-0.2439289987,51.3619194031],"type":"Point"}
}