{
  "type": "Feature",
  "properties": {
    "addr:full":"5 Aldershot Road Fleet Hampshire GU52 8NG",
    "addr:housenumber":"5",
    "addr:postcode":"gu52 8ng",
    "addr:street":"Aldershot Road",
    "iso:country":"GB",
    "sg:address":"5 Aldershot Road",
    "sg:city":"Fleet",
    "sg:classifiers":[
        {
            "category":"Organizations",
            "subcategory":"Non-profit Organization",
            "type":"Services"
        }
    ],
    "sg:phone":"+44 1252 810472",
    "sg:postcode":"GU52 8NG",
    "sg:province":"Hampshire",
    "sg:tags":[
        "organisation",
        "voluntary",
        "charity"
    ],
    "wof:name":"The Marsan Association",
    "wof:placetype":"venue"
},
  "geometry": {"coordinates":[-0.8411120176,51.2765083313],"type":"Point"}
}