{
  "type": "Feature",
  "properties": {
    "iso:country":"GB",
    "sg:address":"66 Winchester Road",
    "sg:city":"Southampton",
    "sg:classifiers":[
        {
            "category":"Manufacturing",
            "subcategory":"Signs",
            "type":"Manufacturing & Wholesale Goods"
        }
    ],
    "sg:phone":"+44 23 8078 0780",
    "sg:postcode":"SO16 6UL",
    "sg:province":"Hampshire",
    "sg:tags":[
        "nameplate"
    ],
    "wof:name":"Wellington Signs & Designs",
    "wof:placetype":"venue"
},
  "geometry": {"coordinates":[-1.4365069866,50.926486969],"type":"Point"}
}