{
  "type": "Feature",
  "properties": {
    "addr:full":"11 Commercial Road Huddersfield South Yorkshire HD8 9DA",
    "addr:housenumber":"11",
    "addr:postcode":"hd8 9da",
    "addr:street":"Commercial Road",
    "iso:country":"GB",
    "sg:address":"11 Commercial Road",
    "sg:city":"Huddersfield",
    "sg:classifiers":[
        {
            "category":"Shopping",
            "subcategory":"Clothing, Apparel, & Fashions",
            "type":"Retail Goods"
        }
    ],
    "sg:phone":"+44 1484 866801",
    "sg:postcode":"HD8 9DA",
    "sg:province":"South Yorkshire",
    "sg:tags":[
        "shop"
    ],
    "wof:name":"Home & Garden Supplies",
    "wof:placetype":"venue"
},
  "geometry": {"coordinates":[-1.651255,53.591713],"type":"Point"}
}