{
  "type": "Feature",
  "properties": {
    "addr:full":"23 Otley Rd Leeds West Yorkshire LS6 3AA",
    "addr:housenumber":"23",
    "addr:postcode":"ls6 3aa",
    "addr:street":"Otley Rd",
    "iso:country":"GB",
    "sg:address":"23 Otley Rd",
    "sg:city":"Leeds",
    "sg:classifiers":[
        {
            "category":"Fast Food",
            "type":"Food & Drink"
        }
    ],
    "sg:phone":"+44 113 278 2415",
    "sg:postcode":"LS6 3AA",
    "sg:province":"West Yorkshire",
    "sg:tags":[
        "away",
        "take"
    ],
    "wof:name":"Harpo's Pizza Pasta Take Out",
    "wof:placetype":"venue"
},
  "geometry": {"coordinates":[-1.5770059824,53.8203353882],"type":"Point"}
}