{
  "type": "Feature",
  "properties": {
    "addr:full":"Care Of 111 King Richards Rd Leicester Leicestershire LE3 5QG",
    "addr:housenumber":"111",
    "addr:postcode":"le3 5qg",
    "addr:street":"King Richards Rd",
    "iso:country":"GB",
    "sg:address":"Care Of 111 King Richards Rd",
    "sg:city":"Leicester",
    "sg:classifiers":[
        {
            "category":"Government",
            "subcategory":"Post Office",
            "type":"Public Place"
        }
    ],
    "sg:phone":"+44 1509 236962",
    "sg:postcode":"LE3 5QG",
    "sg:province":"Leicestershire",
    "sg:tags":[
        "messenger",
        "courier"
    ],
    "wof:name":"Roadrunner Despatch (Loughborough) Ltd",
    "wof:placetype":"venue"
},
  "geometry": {"coordinates":[-1.1487599611,52.6341896057],"type":"Point"}
}