{
  "type": "Feature",
  "properties": {
    "addr:full":"Unit 3 22 Camelon Street, Carntyne Industrial Estate Glasgow Glasgow City G32 6AF",
    "addr:housenumber":"unit;22",
    "addr:postcode":"g32 6af",
    "addr:street":"Camelon Street;Industrial Estate",
    "iso:country":"GB",
    "sg:address":"Unit 3 22 Camelon Street, Carntyne Industrial Estate",
    "sg:city":"Glasgow",
    "sg:classifiers":[
        {
            "category":"Retail",
            "subcategory":"Auto Repair",
            "type":"Services"
        }
    ],
    "sg:phone":"+44 141 778 5314",
    "sg:postcode":"G32 6AF",
    "sg:province":"Glasgow City",
    "sg:tags":[
        "modification",
        "garage",
        "related"
    ],
    "wof:name":"T J O'Neill",
    "wof:placetype":"venue"
},
  "geometry": {"coordinates":[-4.181899,55.856712],"type":"Point"}
}