{
  "type": "Feature",
  "properties": {
    "iso:country":"GB",
    "sg:address":"Woodside Mill",
    "sg:city":"Elland",
    "sg:classifiers":[
        {
            "category":"Manufacturing",
            "subcategory":"Glass & Minerals",
            "type":"Manufacturing & Wholesale Goods"
        }
    ],
    "sg:phone":"+44 1422 377464",
    "sg:postcode":"HX5 0SH",
    "sg:province":"West Yorkshire",
    "sg:tags":[
        "fibre",
        "material"
    ],
    "wof:name":"T Severn (Fibreglass Products) Ltd.",
    "wof:placetype":"venue"
},
  "geometry": {"coordinates":[-1.8358789682,53.6862564087],"type":"Point"}
}