{
  "type": "Feature",
  "properties": {
    "addr:full":"Unit 20 Stayfast Works, 126 Harliquin Avenue Brentford Greater London TW8 9EW",
    "addr:housenumber":"unit 20;126",
    "addr:postcode":"tw8 9ew",
    "addr:street":"Harliquin Avenue",
    "iso:country":"GB",
    "sg:address":"Unit 20 Stayfast Works, 126 Harliquin Avenue",
    "sg:city":"Brentford",
    "sg:classifiers":[
        {
            "category":"Professional",
            "subcategory":"Art Services",
            "type":"Services"
        }
    ],
    "sg:phone":"+44 20 8560 5607",
    "sg:postcode":"TW8 9EW",
    "sg:province":"Greater London",
    "sg:tags":[
        "photographer"
    ],
    "wof:name":"20 20 Photography",
    "wof:placetype":"venue"
},
  "geometry": {"coordinates":[-0.3067240119,51.4841346741],"type":"Point"}
}