{
  "type": "Feature",
  "properties": {
    "addr:full":"23 High Street, Cheddington Leighton Buzzard Bedfordshire LU7 0RG",
    "addr:housenumber":"23",
    "addr:postcode":"lu7 0rg",
    "addr:street":"High Street",
    "iso:country":"GB",
    "sg:address":"23 High Street, Cheddington",
    "sg:city":"Leighton Buzzard",
    "sg:classifiers":[
        {
            "category":"Education",
            "subcategory":"School",
            "type":"Public Place"
        }
    ],
    "sg:phone":"+44 1296 668324",
    "sg:postcode":"LU7 0RG",
    "sg:province":"Bedfordshire",
    "sg:tags":[
        "local",
        "authority"
    ],
    "wof:name":"Cheddington County Combined School",
    "wof:placetype":"venue"
},
  "geometry": {"coordinates":[-0.724470973,51.9046020508],"type":"Point"}
}