{
  "type": "Feature",
  "properties": {
    "addr:full":"312 Wells Road, Knowle Bristol City of Bristol BS4 2QG",
    "addr:housenumber":"312",
    "addr:postcode":"bs4 2qg",
    "addr:street":"Wells Road",
    "iso:country":"GB",
    "sg:address":"312 Wells Road, Knowle",
    "sg:city":"Bristol",
    "sg:classifiers":[
        {
            "category":"Fast Food",
            "type":"Food & Drink"
        }
    ],
    "sg:phone":"+44 117 977 6348",
    "sg:postcode":"BS4 2QG",
    "sg:province":"City of Bristol",
    "sg:tags":[
        "away",
        "take"
    ],
    "wof:name":"Miss Millies Fried Chicken",
    "wof:placetype":"venue"
},
  "geometry": {"coordinates":[-2.5665860176,51.434589386],"type":"Point"}
}