{
  "type": "Feature",
  "properties": {
    "iso:country":"GB",
    "sg:address":"85 The Moor",
    "sg:city":"Sheffield",
    "sg:classifiers":[
        {
            "category":"Home & Garden",
            "subcategory":"Home Furnishings",
            "type":"Retail Goods"
        }
    ],
    "sg:phone":"+44 114 276 2696",
    "sg:postcode":"S1 4PG",
    "sg:province":"South Yorkshire",
    "sg:tags":[
        "blind",
        "curtain",
        "fitting"
    ],
    "wof:name":"Curtain Discount Store The",
    "wof:placetype":"venue"
},
  "geometry": {"coordinates":[-1.473494,53.376163],"type":"Point"}
}