{
  "type": "Feature",
  "properties": {
    "addr:full":"687 Garscube Road Glasgow Glasgow City G20 7JX",
    "addr:housenumber":"687",
    "addr:postcode":"g20 7jx",
    "addr:street":"Garscube Road",
    "iso:country":"GB",
    "sg:address":"687 Garscube Road",
    "sg:city":"Glasgow",
    "sg:classifiers":[
        {
            "category":"Bars & Pubs",
            "type":"Food & Drink"
        },
        {
            "category":"Community Center",
            "subcategory":"Social",
            "type":"Public Place"
        }
    ],
    "sg:phone":"+44 141 332 4358",
    "sg:postcode":"G20 7JX",
    "sg:province":"Glasgow City",
    "sg:tags":[
        "pubs",
        "house",
        "inn",
        "activity"
    ],
    "wof:name":"Tennants Taverns",
    "wof:placetype":"venue"
},
  "geometry": {"coordinates":[-4.2681589127,55.8782958984],"type":"Point"}
}