{
  "type": "Feature",
  "properties": {
    "addr:full":"10 Beare Green Court Dorking Surrey RH5 4QU",
    "addr:housenumber":"10",
    "addr:postcode":"rh5 4qu",
    "addr:street":"Beare Green Court",
    "iso:country":"GB",
    "sg:address":"10 Beare Green Court",
    "sg:city":"Dorking",
    "sg:classifiers":[
        {
            "category":"Restaurant",
            "type":"Food & Drink"
        }
    ],
    "sg:postcode":"RH5 4QU",
    "sg:province":"Surrey",
    "wof:name":"Iaria,Gerrardo,",
    "wof:placetype":"venue"
},
  "geometry": {"coordinates":[-0.3174270093,51.1798706055],"type":"Point"}
}