{
  "type": "Feature",
  "properties": {
    "addr:full":"Priory Street Ware Hertfordshire SG12 0DJ",
    "addr:postcode":"sg12 0dj",
    "addr:street":"Priory Street Ware",
    "iso:country":"GB",
    "sg:address":"Priory Street",
    "sg:city":"Ware",
    "sg:classifiers":[
        {
            "category":"Shopping",
            "subcategory":"Pharmacy",
            "type":"Retail Goods"
        }
    ],
    "sg:phone":"+44 1920 463993",
    "sg:postcode":"SG12 0DJ",
    "sg:province":"Hertfordshire",
    "sg:tags":[
        "pharmaceutical"
    ],
    "wof:name":"Glaxo Welcome Operations",
    "wof:placetype":"venue"
},
  "geometry": {"coordinates":[-0.040205,51.811256],"type":"Point"}
}