{
  "type": "Feature",
  "properties": {
    "iso:country":"GB",
    "sg:address":"49 Shad Thames",
    "sg:city":"Southwark",
    "sg:classifiers":[
        {
            "category":"Shopping",
            "subcategory":"Books",
            "type":"Retail Goods"
        }
    ],
    "sg:phone":"+44 20 7403 7750",
    "sg:postcode":"SE1 2NJ",
    "sg:province":"Greater London",
    "sg:tags":[
        "bookseller"
    ],
    "wof:name":"Riverside Bookshop The",
    "wof:placetype":"venue"
},
  "geometry": {"coordinates":[-0.07332,51.503258],"type":"Point"}
}