{
  "type": "Feature",
  "properties": {
    "addr:full":"Clerks Office, Quay Street Newport Isle of Wight PO30 5BB",
    "addr:postcode":"po30 5bb",
    "addr:street":"Quay Street",
    "iso:country":"GB",
    "sg:address":"Clerks Office, Quay Street",
    "sg:city":"Newport",
    "sg:classifiers":[
        {
            "category":"Government",
            "subcategory":"Court House",
            "type":"Public Place"
        }
    ],
    "sg:phone":"+44 1983 524244",
    "sg:postcode":"PO30 5BB",
    "sg:province":"Isle of Wight",
    "wof:name":"Magistrates Court",
    "wof:placetype":"venue"
},
  "geometry": {"coordinates":[-1.2959389687,50.7000999451],"type":"Point"}
}