{
  "type": "Feature",
  "properties": {
    "iso:country":"GB",
    "sg:address":"16-34 Parsonage Lane",
    "sg:city":"Enfield",
    "sg:classifiers":[
        {
            "category":"Autos & Motor Vehicles",
            "subcategory":"Automobile Sales",
            "type":"Retail Goods"
        }
    ],
    "sg:phone":"+44 20 8367 2008",
    "sg:postcode":"EN2 0AJ",
    "sg:province":"Greater London",
    "sg:tags":[
        "car"
    ],
    "wof:name":"A F Motors",
    "wof:placetype":"venue"
},
  "geometry": {"coordinates":[-0.086287,51.65921],"type":"Point"}
}