{
  "type": "Feature",
  "properties": {
    "iso:country":"GB",
    "sg:address":"38 Lower High Street",
    "sg:city":"Wednesbury",
    "sg:classifiers":[
        {
            "category":"Shopping",
            "subcategory":"Clothing, Apparel, & Fashions",
            "type":"Retail Goods"
        }
    ],
    "sg:phone":"+44 121 556 0793",
    "sg:postcode":"WS10 7AQ",
    "sg:province":"West Midlands",
    "sg:tags":[
        "menswear"
    ],
    "wof:name":"Jon Harcourt (Menswear)",
    "wof:placetype":"venue"
},
  "geometry": {"coordinates":[-2.018908,52.551949],"type":"Point"}
}