{
  "type": "Feature",
  "properties": {
    "addr:full":"39 Ashton Rd, Golborne Warrington Cheshire WA3 3UU",
    "addr:housenumber":"39",
    "addr:postcode":"wa3 3uu",
    "addr:street":"Ashton Rd",
    "iso:country":"GB",
    "sg:address":"39 Ashton Rd, Golborne",
    "sg:city":"Warrington",
    "sg:classifiers":[
        {
            "category":"Taxi",
            "type":"Transportation"
        }
    ],
    "sg:phone":"+44 1942 271010",
    "sg:postcode":"WA3 3UU",
    "sg:province":"Cheshire",
    "sg:tags":[
        "mini",
        "cab"
    ],
    "wof:name":"Knowles Taxis",
    "wof:placetype":"venue"
},
  "geometry": {"coordinates":[-2.6091029644,53.4865455627],"type":"Point"}
}