{
  "type": "Feature",
  "properties": {
    "addr:full":"P O Box 452 Windsor Berkshire SL4 1GB",
    "addr:housenumber":"452",
    "addr:postcode":"sl4 1gb",
    "addr:street":"P O Box",
    "iso:country":"GB",
    "sg:address":"P O Box 452",
    "sg:city":"Windsor",
    "sg:classifiers":[
        {
            "category":"Coffee & Tea",
            "type":"Food & Drink"
        }
    ],
    "sg:phone":"+44 1753 801299",
    "sg:postcode":"SL4 1GB",
    "sg:province":"Berkshire",
    "wof:name":"R G B Coffee Ltd.",
    "wof:placetype":"venue"
},
  "geometry": {"coordinates":[-0.608379,51.482841],"type":"Point"}
}