{
  "type": "Feature",
  "properties": {
    "addr:full":"Mardale Road, Penrith Industrial Estate Penrith Cumbria CA11 9EH",
    "addr:postcode":"ca11 9eh",
    "addr:street":"Mardale Road;Industrial Estate",
    "iso:country":"GB",
    "sg:address":"Mardale Road, Penrith Industrial Estate",
    "sg:city":"Penrith",
    "sg:classifiers":[
        {
            "category":"Farming",
            "subcategory":"Livestock Farm",
            "type":"Manufacturing & Wholesale Goods"
        }
    ],
    "sg:phone":"+44 1768 864141",
    "sg:postcode":"CA11 9EH",
    "sg:province":"Cumbria",
    "sg:tags":[
        "others"
    ],
    "wof:name":"Genus Plc",
    "wof:placetype":"venue"
},
  "geometry": {"coordinates":[-2.766283989,54.6592483521],"type":"Point"}
}