{
  "type": "Feature",
  "properties": {
    "addr:full":"4 Millers Close, Heighington Lincoln Lincolnshire LN4 1TZ",
    "addr:housenumber":"4",
    "addr:postcode":"ln4 1tz",
    "addr:street":"Millers Close",
    "iso:country":"GB",
    "sg:address":"4 Millers Close, Heighington",
    "sg:city":"Lincoln",
    "sg:classifiers":[
        {
            "category":"Home & Garden",
            "subcategory":"Household Appliances",
            "type":"Retail Goods"
        },
        {
            "category":"Retail",
            "subcategory":"Repair Shop",
            "type":"Services"
        }
    ],
    "sg:phone":"+44 1522 793274",
    "sg:postcode":"LN4 1TZ",
    "sg:province":"Lincolnshire",
    "sg:tags":[
        "machine",
        "electrical",
        "washing"
    ],
    "wof:name":"Reginald S G Mugford",
    "wof:placetype":"venue"
},
  "geometry": {"coordinates":[-0.466193,53.214832],"type":"Point"}
}