{
  "type": "Feature",
  "properties": {
    "addr:full":"202 Walton Street London Greater London SW3 2JL",
    "addr:housenumber":"202",
    "addr:postcode":"sw3 2jl",
    "addr:street":"Walton Street",
    "iso:country":"GB",
    "sg:address":"202 Walton Street",
    "sg:city":"London",
    "sg:classifiers":[
        {
            "category":"Personal",
            "subcategory":"Beauty Salon",
            "type":"Services"
        }
    ],
    "sg:postcode":"SW3 2JL",
    "sg:province":"Greater London",
    "wof:name":"Figure Shapers of Knightsbridge (Beauty Specialists) Ltd.",
    "wof:placetype":"venue"
},
  "geometry": {"coordinates":[-0.168181,51.493977],"type":"Point"}
}