{
  "type": "Feature",
  "properties": {
    "addr:full":"34 The Avenue Watford Hertfordshire WD17 4NS",
    "addr:housenumber":"34",
    "addr:postcode":"wd17 4ns",
    "addr:street":"The Avenue",
    "iso:country":"GB",
    "sg:address":"34 The Avenue",
    "sg:city":"Watford",
    "sg:classifiers":[
        {
            "category":"Health Services",
            "subcategory":"Clinic",
            "type":"Services"
        }
    ],
    "sg:phone":"+44 1923 225646",
    "sg:postcode":"WD17 4NS",
    "sg:province":"Hertfordshire",
    "sg:tags":[
        "aromatherapy"
    ],
    "wof:name":"Loveridge Kathleen Complimentary Therapist",
    "wof:placetype":"venue"
},
  "geometry": {"coordinates":[-0.404476,51.661697],"type":"Point"}
}