{
  "type": "Feature",
  "properties": {
    "iso:country":"GB",
    "sg:address":"394 Caledonian Road",
    "sg:city":"London",
    "sg:classifiers":[
        {
            "category":"Manufacturing",
            "subcategory":"Metals",
            "type":"Manufacturing & Wholesale Goods"
        }
    ],
    "sg:phone":"+44 20 7609 0934",
    "sg:postcode":"N1 1DN",
    "sg:province":"Greater London",
    "sg:tags":[
        "product",
        "fabricated"
    ],
    "wof:name":"The Cast Iron Shop",
    "wof:placetype":"venue"
},
  "geometry": {"coordinates":[-0.117083,51.542446],"type":"Point"}
}