{
  "type": "Feature",
  "properties": {
    "addr:full":"Luncarty Perth Perth and Kinross PH1 3HE",
    "addr:postcode":"ph1 3he",
    "iso:country":"GB",
    "sg:address":"Luncarty",
    "sg:city":"Perth",
    "sg:classifiers":[
        {
            "category":"Real Estate",
            "subcategory":"Developer",
            "type":"Services"
        }
    ],
    "sg:postcode":"PH1 3HE",
    "sg:province":"Perth and Kinross",
    "sg:tags":[
        "property"
    ],
    "wof:name":"Glenparke Ltd.",
    "wof:placetype":"venue"
},
  "geometry": {"coordinates":[-3.461509943,56.4489898682],"type":"Point"}
}