{
  "type": "Feature",
  "properties": {
    "addr:full":"15 Amersham Hill High Wycombe Buckinghamshire HP13 6NR",
    "addr:housenumber":"15",
    "addr:postcode":"hp13 6nr",
    "addr:street":"Amersham Hill",
    "iso:country":"GB",
    "sg:address":"15 Amersham Hill",
    "sg:city":"High Wycombe",
    "sg:classifiers":[
        {
            "category":"Health Services",
            "subcategory":"Dentist",
            "type":"Services"
        }
    ],
    "sg:phone":"+44 1494 442922",
    "sg:postcode":"HP13 6NR",
    "sg:province":"Buckinghamshire",
    "wof:name":"Wycombe Dental Centre",
    "wof:placetype":"venue"
},
  "geometry": {"coordinates":[-0.74624,51.63105],"type":"Point"}
}