{
  "type": "Feature",
  "properties": {
    "addr:full":"19 West Church Street Buckie Moray AB56 1BN",
    "addr:housenumber":"19",
    "addr:postcode":"ab56 1bn",
    "addr:street":"West Church Street",
    "iso:country":"GB",
    "sg:address":"19 West Church Street",
    "sg:city":"Buckie",
    "sg:classifiers":[
        {
            "category":"Fast Food",
            "type":"Food & Drink"
        },
        {
            "category":"Food & Beverages",
            "subcategory":"Meat & Fish",
            "type":"Retail Goods"
        }
    ],
    "sg:phone":"+44 1542 834666",
    "sg:postcode":"AB56 1BN",
    "sg:province":"Moray",
    "sg:tags":[
        "outlet",
        "chip",
        "meal",
        "away",
        "take"
    ],
    "wof:name":"PAUL & STEPHEN WOGCIK",
    "wof:placetype":"venue"
},
  "geometry": {"coordinates":[-2.9672698975,57.6755409241],"type":"Point"}
}