{
  "type": "Feature",
  "properties": {
    "addr:full":"Unit 1, Imill Buss Park Leeds West Yorkshire LS27 0WJ",
    "addr:housenumber":"unit 1",
    "addr:postcode":"ls27 0wj",
    "addr:street":"Buss Park",
    "iso:country":"GB",
    "sg:address":"Unit 1, Imill Buss Park",
    "sg:city":"Leeds",
    "sg:classifiers":[
        {
            "category":"Taxi",
            "type":"Transportation"
        },
        {
            "category":"Military Area",
            "subcategory":"Air Force Base",
            "type":"Public Place"
        }
    ],
    "sg:phone":"+44 113 252 2222",
    "sg:postcode":"LS27 0WJ",
    "sg:province":"West Yorkshire",
    "sg:tags":[
        "hire",
        "private",
        "vehicle"
    ],
    "wof:name":"Morley Cars",
    "wof:placetype":"venue"
},
  "geometry": {"coordinates":[-1.5998300314,53.7436981201],"type":"Point"}
}