{
  "type": "Feature",
  "properties": {
    "addr:full":"12a Princes Avenue Hull East Riding of Yorkshire HU5 3QA",
    "addr:housenumber":"12a",
    "addr:postcode":"hu5 3qa",
    "addr:street":"Princes Avenue",
    "iso:country":"GB",
    "sg:address":"12a Princes Avenue",
    "sg:city":"Hull",
    "sg:classifiers":[
        {
            "category":"Retail",
            "subcategory":"Laundry & Dry Cleaning",
            "type":"Services"
        }
    ],
    "sg:phone":"+44 1482 343932",
    "sg:postcode":"HU5 3QA",
    "sg:province":"East Riding of Yorkshire",
    "sg:tags":[
        "alteration"
    ],
    "wof:name":"Beverley Kennington & Rosalyn Sidgett",
    "wof:placetype":"venue"
},
  "geometry": {"coordinates":[-0.360101,53.753391],"type":"Point"}
}