{
  "type": "Feature",
  "properties": {
    "addr:full":"Pilcot, Dogmersfield Hook Berkshire RG27 8SY",
    "addr:postcode":"rg27 8sy",
    "iso:country":"GB",
    "sg:address":"Pilcot, Dogmersfield",
    "sg:city":"Hook",
    "sg:classifiers":[
        {
            "category":"Bars & Pubs",
            "type":"Food & Drink"
        }
    ],
    "sg:phone":"+44 1252 613531",
    "sg:postcode":"RG27 8SY",
    "sg:province":"Berkshire",
    "sg:tags":[
        "pubs",
        "inn"
    ],
    "wof:name":"Queens Head",
    "wof:placetype":"venue"
},
  "geometry": {"coordinates":[-0.8743399978,51.269657135],"type":"Point"}
}