{
  "type": "Feature",
  "properties": {
    "addr:full":"2 Chapel Street, Castle Gresley Derby Derbyshire DE11 9HZ",
    "addr:housenumber":"2",
    "addr:postcode":"de11 9hz",
    "addr:street":"Chapel Street",
    "iso:country":"GB",
    "sg:address":"2 Chapel Street, Castle Gresley",
    "sg:city":"Derby",
    "sg:classifiers":[
        {
            "category":"Utilities",
            "subcategory":"Fuel Oil & Lpg",
            "type":"Services"
        }
    ],
    "sg:phone":"+44 1283 212332",
    "sg:postcode":"DE11 9HZ",
    "sg:province":"Derbyshire",
    "sg:tags":[
        "merchant",
        "coal",
        "smokeless"
    ],
    "wof:name":"John G W Jones",
    "wof:placetype":"venue"
},
  "geometry": {"coordinates":[-1.5676640272,52.7607345581],"type":"Point"}
}