{
  "type": "Feature",
  "properties": {
    "iso:country":"GB",
    "sg:address":"Geneva House, Park Road",
    "sg:city":"Peterborough",
    "sg:classifiers":[
        {
            "category":"Professional",
            "subcategory":"Employment Agencies",
            "type":"Services"
        }
    ],
    "sg:phone":"+44 1733 319995",
    "sg:postcode":"PE1 2UX",
    "sg:province":"Cambridgeshire",
    "sg:tags":[
        "consultant"
    ],
    "wof:name":"Taskforce Recruitment Ltd.",
    "wof:placetype":"venue"
},
  "geometry": {"coordinates":[-0.239449,52.587246],"type":"Point"}
}