{
  "type": "Feature",
  "properties": {
    "iso:country":"GB",
    "sg:address":"112 Logie Street",
    "sg:city":"Dundee",
    "sg:classifiers":[
        {
            "category":"Shopping",
            "subcategory":"News",
            "type":"Retail Goods"
        }
    ],
    "sg:phone":"+44 1382 667706",
    "sg:postcode":"DD2 2PY",
    "sg:province":"Dundee City",
    "sg:tags":[
        "newsagent"
    ],
    "wof:name":"MESSRS NORRIE",
    "wof:placetype":"venue"
},
  "geometry": {"coordinates":[-3.002709,56.468521],"type":"Point"}
}