{
  "type": "Feature",
  "properties": {
    "iso:country":"GB",
    "sg:address":"Carlton Road",
    "sg:city":"Erith",
    "sg:classifiers":[
        {
            "category":"Place Of Worship",
            "type":"Public Place"
        },
        {
            "category":"Organizations",
            "subcategory":"Religious Organization",
            "type":"Services"
        }
    ],
    "sg:phone":"+44 1322 433193",
    "sg:postcode":"DA8 1DN",
    "sg:province":"Kent",
    "sg:tags":[
        "organisation"
    ],
    "wof:name":"Franciscan Friary",
    "wof:placetype":"venue"
},
  "geometry": {"coordinates":[0.156256,51.478764],"type":"Point"}
}