{
  "type": "Feature",
  "properties": {
    "iso:country":"GB",
    "sg:address":"Bumpers Way",
    "sg:city":"Chippenham",
    "sg:classifiers":[
        {
            "category":"Building & Trades",
            "subcategory":"Electrical",
            "type":"Services"
        }
    ],
    "sg:phone":"+44 1249 443515",
    "sg:postcode":"SN14 6LF",
    "sg:province":"Gloucestershire",
    "sg:tags":[
        "lighting"
    ],
    "wof:name":"Druryway Auto Group Ltd.",
    "wof:placetype":"venue"
},
  "geometry": {"coordinates":[-2.142954,51.468189],"type":"Point"}
}