{
  "type": "Feature",
  "properties": {
    "addr:full":"16 Buckingham Clo High Wycombe Buckinghamshire HP13 7YD",
    "addr:housenumber":"16",
    "addr:postcode":"hp13 7yd",
    "addr:street":"Buckingham Clo",
    "iso:country":"GB",
    "sg:address":"16 Buckingham Clo",
    "sg:city":"High Wycombe",
    "sg:classifiers":[
        {
            "category":"Government",
            "subcategory":"Post Office",
            "type":"Public Place"
        }
    ],
    "sg:phone":"+44 1494 464923",
    "sg:postcode":"HP13 7YD",
    "sg:province":"Buckinghamshire",
    "sg:tags":[
        "messenger",
        "courier"
    ],
    "wof:name":"Overdrive International",
    "wof:placetype":"venue"
},
  "geometry": {"coordinates":[-0.7138969898,51.6287269592],"type":"Point"}
}