{
  "type": "Feature",
  "properties": {
    "addr:full":"Gomshall Lane, Shere Guildford Surrey GU5 9HB",
    "addr:postcode":"gu5 9hb",
    "addr:street":"Gomshall Lane",
    "iso:country":"GB",
    "sg:address":"Gomshall Lane, Shere",
    "sg:city":"Guildford",
    "sg:classifiers":[
        {
            "category":"Education",
            "subcategory":"School",
            "type":"Public Place"
        },
        {
            "category":"Government",
            "subcategory":"Office",
            "type":"Public Place"
        }
    ],
    "sg:phone":"+44 1483 202198",
    "sg:postcode":"GU5 9HB",
    "sg:province":"Surrey",
    "sg:tags":[
        "local",
        "authority"
    ],
    "wof:name":"Shere C Of E Infant School",
    "wof:placetype":"venue"
},
  "geometry": {"coordinates":[-0.4588870108,51.2205085754],"type":"Point"}
}