{
  "type": "Feature",
  "properties": {
    "addr:full":"1 Lower Farm Cottage, Langford Lechlade Gloucestershire GL7 3LF",
    "addr:housenumber":"1;farm",
    "addr:postcode":"gl7 3lf",
    "addr:street":"Lower",
    "iso:country":"GB",
    "sg:address":"1 Lower Farm Cottage, Langford",
    "sg:city":"Lechlade",
    "sg:classifiers":[
        {
            "category":"Shopping",
            "subcategory":"Photographic Equipment",
            "type":"Retail Goods"
        }
    ],
    "sg:phone":"+44 1367 860443",
    "sg:postcode":"GL7 3LF",
    "sg:province":"Gloucestershire",
    "wof:name":"Patrica Grace Photography",
    "wof:placetype":"venue"
},
  "geometry": {"coordinates":[-1.6919089556,51.6940765381],"type":"Point"}
}