{
  "type": "Feature",
  "properties": {
    "iso:country":"GB",
    "sg:address":"Field Street, Valley",
    "sg:city":"Holyhead",
    "sg:classifiers":[
        {
            "category":"Utilities",
            "subcategory":"Fuel Oil & Lpg",
            "type":"Services"
        }
    ],
    "sg:phone":"+44 1407 740207",
    "sg:postcode":"LL65 3EG",
    "sg:province":"Isle of Anglesey",
    "sg:tags":[
        "distributor"
    ],
    "sg:website":"http://www.trjones.co.uk",
    "wof:name":"T R Jones & Sons",
    "wof:placetype":"venue"
},
  "geometry": {"coordinates":[-4.56243,53.28289],"type":"Point"}
}