{
  "type": "Feature",
  "properties": {
    "iso:country":"GB",
    "sg:address":"58 Chester Road, Helsby",
    "sg:city":"Warrington",
    "sg:classifiers":[
        {
            "category":"Social Services",
            "subcategory":"Child Care",
            "type":"Services"
        }
    ],
    "sg:postcode":"WA6 0DW",
    "sg:province":"Cheshire",
    "sg:tags":[
        "childminders"
    ],
    "wof:name":"Sara Satchell",
    "wof:placetype":"venue"
},
  "geometry": {"coordinates":[-2.773725,53.264545],"type":"Point"}
}