{
  "type": "Feature",
  "properties": {
    "iso:country":"GB",
    "sg:address":"Wychwood, Ash La",
    "sg:city":"Stone",
    "sg:classifiers":[
        {
            "category":"Building & Trades",
            "subcategory":"Construction",
            "type":"Services"
        }
    ],
    "sg:phone":"+44 1785 760370",
    "sg:postcode":"ST15 0NJ",
    "sg:province":"Staffordshire",
    "sg:tags":[
        "builder"
    ],
    "wof:name":"Thomas D E",
    "wof:placetype":"venue"
},
  "geometry": {"coordinates":[-2.139495,52.885529],"type":"Point"}
}