{
  "type": "Feature",
  "properties": {
    "addr:full":"209 High St Eltham Eltham Greater London SE9 1TX",
    "addr:housenumber":"209",
    "addr:postcode":"se9 1tx",
    "addr:street":"High St",
    "iso:country":"GB",
    "sg:address":"209 High St Eltham",
    "sg:city":"Eltham",
    "sg:classifiers":[
        {
            "category":"Communications",
            "type":"Services"
        }
    ],
    "sg:phone":"+44 20 8859 5055",
    "sg:postcode":"SE9 1TX",
    "sg:province":"Greater London",
    "sg:tags":[
        "telecommunication"
    ],
    "wof:name":"Swale Telecom",
    "wof:placetype":"venue"
},
  "geometry": {"coordinates":[0.0509879999,51.5391273499],"type":"Point"}
}