{
  "type": "Feature",
  "properties": {
    "iso:country":"GB",
    "sg:address":"159 Marsh Rd",
    "sg:city":"Luton",
    "sg:classifiers":[
        {
            "category":"Personal",
            "subcategory":"Beauty Salon",
            "type":"Services"
        }
    ],
    "sg:postcode":"LU3 2QQ",
    "sg:province":"Bedfordshire",
    "sg:tags":[
        "unisex",
        "hairdresser"
    ],
    "wof:name":"New Rennaisance",
    "wof:placetype":"venue"
},
  "geometry": {"coordinates":[-0.452561,51.903786],"type":"Point"}
}