{
  "type": "Feature",
  "properties": {
    "iso:country":"GB",
    "sg:address":"Hele House, Brompton Ralph",
    "sg:city":"Taunton",
    "sg:classifiers":[
        {
            "category":"Professional",
            "subcategory":"Management & Consulting",
            "type":"Services"
        }
    ],
    "sg:phone":"+44 1984 624118",
    "sg:postcode":"TA4 2SG",
    "sg:province":"Devon",
    "sg:tags":[
        "marketing",
        "consultant"
    ],
    "wof:name":"David Whiting Associates",
    "wof:placetype":"venue"
},
  "geometry": {"coordinates":[-3.338509,51.033569],"type":"Point"}
}