{
  "type": "Feature",
  "properties": {
    "addr:full":"176 Church Street, Stoke Newington London Greater London N16 0JL",
    "addr:housenumber":"176",
    "addr:postcode":"n16 0jl",
    "addr:street":"Church Street",
    "iso:country":"GB",
    "sg:address":"176 Church Street, Stoke Newington",
    "sg:city":"London",
    "sg:classifiers":[
        {
            "category":"Bars & Pubs",
            "subcategory":"Wine Bar",
            "type":"Food & Drink"
        }
    ],
    "sg:phone":"+44 20 7254 5975",
    "sg:postcode":"N16 0JL",
    "sg:province":"Greater London",
    "wof:name":"The Fox Reformed",
    "wof:placetype":"venue"
},
  "geometry": {"coordinates":[-0.06827,51.626701],"type":"Point"}
}