{
  "type": "Feature",
  "properties": {
    "addr:full":"Southgate Wincanton Somerset BA9 9EB",
    "addr:postcode":"ba9 9eb",
    "addr:street":"Southgate",
    "iso:country":"GB",
    "sg:address":"Southgate",
    "sg:city":"Wincanton",
    "sg:classifiers":[
        {
            "category":"Manufacturing",
            "subcategory":"Wood Products",
            "type":"Manufacturing & Wholesale Goods"
        }
    ],
    "sg:postcode":"BA9 9EB",
    "sg:province":"Somerset",
    "sg:tags":[
        "maker",
        "cabinet"
    ],
    "wof:name":"Martin J Dodge Ltd.",
    "wof:placetype":"venue"
},
  "geometry": {"coordinates":[-2.407943964,51.0520362854],"type":"Point"}
}