{
  "type": "Feature",
  "properties": {
    "iso:country":"GB",
    "sg:address":"55 Drumilaw Road, Rutherglen",
    "sg:city":"Glasgow",
    "sg:classifiers":[
        {
            "category":"Building & Trades",
            "subcategory":"Cleaning & Sanitation",
            "type":"Services"
        }
    ],
    "sg:postcode":"G73 4NS",
    "sg:province":"Glasgow City",
    "sg:tags":[
        "commercial"
    ],
    "wof:name":"Global Office Cleaning",
    "wof:placetype":"venue"
},
  "geometry": {"coordinates":[-4.212717,55.814495],"type":"Point"}
}