{
  "type": "Feature",
  "properties": {
    "addr:full":"Royalty House, 72-74 Dean St West End Hampshire W1V 6AE",
    "addr:housenumber":"72-74",
    "addr:postcode":"w1v 6ae",
    "addr:street":"Dean St",
    "iso:country":"GB",
    "sg:address":"Royalty House, 72-74 Dean St",
    "sg:city":"West End",
    "sg:classifiers":[
        {
            "category":"Professional",
            "subcategory":"Advertising",
            "type":"Services"
        }
    ],
    "sg:phone":"+44 20 7439 1228",
    "sg:postcode":"W1V 6AE",
    "sg:province":"Hampshire",
    "sg:tags":[
        "agency"
    ],
    "wof:name":"David Pilton Advertising Ltd",
    "wof:placetype":"venue"
},
  "geometry": {"coordinates":[-0.1328739971,51.5138626099],"type":"Point"}
}