{
  "type": "Feature",
  "properties": {
    "addr:full":"790 Alcester Road South Birmingham West Midlands B14 5EZ",
    "addr:housenumber":"790",
    "addr:postcode":"b14 5ez",
    "addr:street":"Alcester Road South",
    "iso:country":"GB",
    "sg:address":"790 Alcester Road South",
    "sg:city":"Birmingham",
    "sg:classifiers":[
        {
            "category":"Shopping",
            "subcategory":"Computers & Home Electronics",
            "type":"Retail Goods"
        },
        {
            "category":"Communications",
            "type":"Services"
        }
    ],
    "sg:phone":"+44 121 430 5423",
    "sg:postcode":"B14 5EZ",
    "sg:province":"West Midlands",
    "sg:tags":[
        "tv",
        "radio",
        "television",
        "video",
        "sale"
    ],
    "wof:name":"Richards Quality Radio",
    "wof:placetype":"venue"
},
  "geometry": {"coordinates":[-1.886424,52.410973],"type":"Point"}
}