{
  "type": "Feature",
  "properties": {
    "iso:country":"GB",
    "sg:address":"63 Bristol Road, Keynsham",
    "sg:city":"Bristol",
    "sg:classifiers":[
        {
            "category":"Travel",
            "subcategory":"Hotels & Motels",
            "type":"Entertainment"
        }
    ],
    "sg:phone":"+44 117 986 2150",
    "sg:postcode":"BS31 2WA",
    "sg:province":"City of Bristol",
    "sg:tags":[
        "house",
        "guest"
    ],
    "wof:name":"The Crown Inn",
    "wof:placetype":"venue"
},
  "geometry": {"coordinates":[-2.505936,51.418137],"type":"Point"}
}