{
  "type": "Feature",
  "properties": {
    "iso:country":"GB",
    "sg:address":"15-17 Huntsworth Mews",
    "sg:city":"London",
    "sg:classifiers":[
        {
            "category":"Organizations",
            "subcategory":"Community Association",
            "type":"Services"
        }
    ],
    "sg:postcode":"NW1 6DD",
    "sg:province":"Greater London",
    "sg:tags":[
        "relation",
        "public"
    ],
    "wof:name":"The Counsel Group Ltd.",
    "wof:placetype":"venue"
},
  "geometry": {"coordinates":[-0.161181,51.523605],"type":"Point"}
}