{
  "type": "Feature",
  "properties": {
    "addr:full":"41 Kirkway Rochdale Lancashire OL11 2JD",
    "addr:housenumber":"41",
    "addr:postcode":"ol11 2jd",
    "addr:street":"Kirkway Rochdale",
    "iso:country":"GB",
    "sg:address":"41 Kirkway",
    "sg:city":"Rochdale",
    "sg:classifiers":[
        {
            "category":"Organizations",
            "subcategory":"Non-profit Organization",
            "type":"Services"
        }
    ],
    "sg:phone":"+44 1706 718004",
    "sg:postcode":"OL11 2JD",
    "sg:province":"Lancashire",
    "sg:tags":[
        "organisation",
        "voluntary",
        "charity"
    ],
    "wof:name":"Peopleprint",
    "wof:placetype":"venue"
},
  "geometry": {"coordinates":[-2.169594,53.592312],"type":"Point"}
}