{
  "type": "Feature",
  "properties": {
    "addr:full":"Kingoldrum Kirriemuir Angus DD8 5HY",
    "addr:postcode":"dd8 5hy",
    "iso:country":"GB",
    "sg:address":"Kingoldrum",
    "sg:city":"Kirriemuir",
    "sg:classifiers":[
        {
            "category":"Travel",
            "subcategory":"Hotels & Motels",
            "type":"Entertainment"
        }
    ],
    "sg:postcode":"DD8 5HY",
    "sg:province":"Angus",
    "sg:tags":[
        "house",
        "guest"
    ],
    "wof:name":"Welton Farm",
    "wof:placetype":"venue"
},
  "geometry": {"coordinates":[-3.0759689808,56.6693687439],"type":"Point"}
}