{
  "type": "Feature",
  "properties": {
    "addr:full":"The Street Newmarket Cambridgeshire CB8 8RB",
    "addr:postcode":"cb8 8rb",
    "addr:street":"The Street",
    "iso:country":"GB",
    "sg:address":"The Street",
    "sg:city":"Newmarket",
    "sg:classifiers":[
        {
            "category":"Sports & Exercise",
            "subcategory":"Stables",
            "type":"Entertainment"
        }
    ],
    "sg:phone":"+44 1638 751223",
    "sg:postcode":"CB8 8RB",
    "sg:province":"Cambridgeshire",
    "sg:tags":[
        "education",
        "equestrian"
    ],
    "wof:name":"Cherry Orchard Stables",
    "wof:placetype":"venue"
},
  "geometry": {"coordinates":[0.520741,52.228168],"type":"Point"}
}