{
  "type": "Feature",
  "properties": {
    "iso:country":"GB",
    "sg:address":"10 Chasetown Close",
    "sg:city":"Manchester",
    "sg:classifiers":[
        {
            "category":"Recreation",
            "subcategory":"Amusement Park",
            "type":"Entertainment"
        }
    ],
    "sg:phone":"+44 161 998 8852",
    "sg:postcode":"M23 9NS",
    "sg:province":"Cheshire",
    "sg:tags":[
        "arcade"
    ],
    "wof:name":"Swann Leisure Services",
    "wof:placetype":"venue"
},
  "geometry": {"coordinates":[-2.2964799404,53.3892250061],"type":"Point"}
}