{
  "type": "Feature",
  "properties": {
    "iso:country":"GB",
    "sg:address":"93a London Road",
    "sg:city":"Colchester",
    "sg:classifiers":[
        {
            "category":"Shopping",
            "type":"Retail Goods"
        }
    ],
    "sg:phone":"+44 1206 211782",
    "sg:postcode":"CO6 1EB",
    "sg:province":"Essex",
    "sg:tags":[
        "part",
        "accessory"
    ],
    "wof:name":"Marks Tey Autospares",
    "wof:placetype":"venue"
},
  "geometry": {"coordinates":[0.77071,51.872002],"type":"Point"}
}