{
  "type": "Feature",
  "properties": {
    "addr:full":"Hill Farm, Pan Lane, East Hanningfield Chelmsford Essex CM3 8BJ",
    "addr:postcode":"cm3 8bj",
    "addr:street":"Hill;Pan Lane",
    "iso:country":"GB",
    "sg:address":"Hill Farm, Pan Lane, East Hanningfield",
    "sg:city":"Chelmsford",
    "sg:classifiers":[
        {
            "category":"Sports & Exercise",
            "subcategory":"Stables",
            "type":"Entertainment"
        }
    ],
    "sg:phone":"+44 1245 401342",
    "sg:postcode":"CM3 8BJ",
    "sg:province":"Essex",
    "sg:tags":[
        "education",
        "equestrian"
    ],
    "wof:name":"Hill Farm Equestrian Centre",
    "wof:placetype":"venue"
},
  "geometry": {"coordinates":[0.5412899852,51.677898407],"type":"Point"}
}