{
  "type": "Feature",
  "properties": {
    "iso:country":"GB",
    "sg:address":"2 Cliff Rd",
    "sg:city":"Bridgnorth",
    "sg:classifiers":[
        {
            "category":"Organizations",
            "subcategory":"Political Organization",
            "type":"Services"
        }
    ],
    "sg:phone":"+44 1746 767469",
    "sg:postcode":"WV16 4EY",
    "sg:province":"Shropshire",
    "sg:tags":[
        "party"
    ],
    "wof:name":"Ludlow Constituency Liberal Democrats",
    "wof:placetype":"venue"
},
  "geometry": {"coordinates":[-2.420054,52.537418],"type":"Point"}
}