{
  "type": "Feature",
  "properties": {
    "iso:country":"GB",
    "sg:address":"2 Highgrove",
    "sg:city":"Battle",
    "sg:classifiers":[
        {
            "category":"Manufacturing",
            "subcategory":"Rubber & Plastics",
            "type":"Manufacturing & Wholesale Goods"
        }
    ],
    "sg:phone":"+44 1424 774437",
    "sg:postcode":"TN33 0EL",
    "sg:province":"East Sussex",
    "wof:name":"Actual Extrusion UK",
    "wof:placetype":"venue"
},
  "geometry": {"coordinates":[0.467754,50.917019],"type":"Point"}
}