{
  "type": "Feature",
  "properties": {
    "iso:country":"GB",
    "sg:address":"Heath Hall, Heath",
    "sg:city":"Wakefield",
    "sg:classifiers":[
        {
            "category":"Real Estate",
            "subcategory":"Developer",
            "type":"Services"
        }
    ],
    "sg:phone":"+44 1924 366600",
    "sg:postcode":"WF1 5SL",
    "sg:province":"West Yorkshire",
    "sg:tags":[
        "property"
    ],
    "wof:name":"Magna Holdings Ltd.",
    "wof:placetype":"venue"
},
  "geometry": {"coordinates":[-1.462791,53.674152],"type":"Point"}
}