{
  "type": "Feature",
  "properties": {
    "iso:country":"GB",
    "sg:address":"Unit 1 Gas St",
    "sg:city":"Skipton",
    "sg:classifiers":[
        {
            "category":"Shopping",
            "subcategory":"Mobile Phones",
            "type":"Retail Goods"
        }
    ],
    "sg:phone":"+44 1756 796697",
    "sg:postcode":"BD23 1RP",
    "sg:province":"Lancashire",
    "wof:name":"Skipton Communications Centre",
    "wof:placetype":"venue"
},
  "geometry": {"coordinates":[-2.020039,53.95871],"type":"Point"}
}