{
  "type": "Feature",
  "properties": {
    "iso:country":"GB",
    "sg:address":"31 Lister Street, Attleborough",
    "sg:city":"Nuneaton",
    "sg:classifiers":[
        {
            "category":"Professional",
            "subcategory":"Computer Services",
            "type":"Services"
        }
    ],
    "sg:phone":"+44 24 7637 3944",
    "sg:postcode":"CV11 4NX",
    "sg:province":"Leicestershire",
    "sg:tags":[
        "consultant"
    ],
    "wof:name":"Different Computing Ltd.",
    "wof:placetype":"venue"
},
  "geometry": {"coordinates":[-1.4576489925,52.5179023743],"type":"Point"}
}