{
  "type": "Feature",
  "properties": {
    "addr:full":"11 Pydar Street Truro Cornwall TR1 2AX",
    "addr:housenumber":"11",
    "addr:postcode":"tr1 2ax",
    "addr:street":"Pydar Street",
    "iso:country":"GB",
    "sg:address":"11 Pydar Street",
    "sg:city":"Truro",
    "sg:classifiers":[
        {
            "category":"Shopping",
            "subcategory":"Bicycles & Sporting Goods",
            "type":"Retail Goods"
        }
    ],
    "sg:phone":"+44 1872 240973",
    "sg:postcode":"TR1 2AX",
    "sg:province":"Cornwall",
    "sg:tags":[
        "equipment",
        "camping"
    ],
    "wof:name":"Millets",
    "wof:placetype":"venue"
},
  "geometry": {"coordinates":[-5.05348,50.264378],"type":"Point"}
}