{
  "type": "Feature",
  "properties": {
    "iso:country":"GB",
    "sg:address":"Common Hill Farm, Warthill",
    "sg:city":"York",
    "sg:classifiers":[
        {
            "category":"Farming",
            "subcategory":"Poultry Farm",
            "type":"Manufacturing & Wholesale Goods"
        }
    ],
    "sg:postcode":"YO3 9XS",
    "sg:province":"East Riding of Yorkshire",
    "sg:tags":[
        "game"
    ],
    "wof:name":"Premier Chickens",
    "wof:placetype":"venue"
},
  "geometry": {"coordinates":[-0.9715499878,53.9892082214],"type":"Point"}
}