{
  "type": "Feature",
  "properties": {
    "iso:country":"GB",
    "sg:address":"Newbury & Community Hospital",
    "sg:city":"Newbury",
    "sg:classifiers":[
        {
            "category":"Health Services",
            "subcategory":"Hospital",
            "type":"Services"
        }
    ],
    "sg:phone":"+44 1635 32500",
    "sg:postcode":"RG14 6LS",
    "sg:province":"Berkshire",
    "wof:name":"Newbury & Community Primary Care Trust",
    "wof:placetype":"venue"
},
  "geometry": {"coordinates":[-1.32756,51.394901],"type":"Point"}
}