{
  "type": "Feature",
  "properties": {
    "iso:country":"GB",
    "sg:address":"8 The Maltings, Roushill",
    "sg:city":"Shrewsbury",
    "sg:classifiers":[
        {
            "category":"Shopping",
            "subcategory":"Books",
            "type":"Retail Goods"
        }
    ],
    "sg:postcode":"SY1 1PQ",
    "sg:province":"Shropshire",
    "sg:tags":[
        "second-hand"
    ],
    "wof:name":"Joan's Attic",
    "wof:placetype":"venue"
},
  "geometry": {"coordinates":[-2.754469,52.708179],"type":"Point"}
}