{
  "type": "Feature",
  "properties": {
    "addr:full":"41 Melbourne Road Wallington Surrey SM6 8SH",
    "addr:housenumber":"41",
    "addr:postcode":"sm6 8sh",
    "addr:street":"Melbourne Road",
    "iso:country":"GB",
    "sg:address":"41 Melbourne Road",
    "sg:city":"Wallington",
    "sg:classifiers":[
        {
            "category":"Building & Trades",
            "subcategory":"Construction",
            "type":"Services"
        }
    ],
    "sg:postcode":"SM6 8SH",
    "sg:province":"Surrey",
    "sg:tags":[
        "builder"
    ],
    "wof:name":"Heritage Roofing",
    "wof:placetype":"venue"
},
  "geometry": {"coordinates":[-0.1466349959,51.3618087769],"type":"Point"}
}