{
  "type": "Feature",
  "properties": {
    "iso:country":"GB",
    "sg:address":"12 Waters Road",
    "sg:city":"Salisbury",
    "sg:classifiers":[
        {
            "category":"Government",
            "subcategory":"Fire Station",
            "type":"Public Place"
        },
        {
            "category":"Utilities",
            "subcategory":"Natural Gas",
            "type":"Services"
        }
    ],
    "sg:phone":"+44 1722 337606",
    "sg:postcode":"SP1 3NX",
    "sg:province":"Wiltshire",
    "sg:tags":[
        "technician",
        "firework"
    ],
    "wof:name":"Flameburst Effects Ltd.",
    "wof:placetype":"venue"
},
  "geometry": {"coordinates":[-1.801341,51.08289],"type":"Point"}
}