{
  "type": "Feature",
  "properties": {
    "addr:full":"68 Main Street, Rosliston Swadlincote Derbyshire DE12 8JL",
    "addr:housenumber":"68",
    "addr:postcode":"de12 8jl",
    "addr:street":"Main Street",
    "iso:country":"GB",
    "sg:address":"68 Main Street, Rosliston",
    "sg:city":"Swadlincote",
    "sg:classifiers":[
        {
            "category":"Bars & Pubs",
            "type":"Food & Drink"
        }
    ],
    "sg:phone":"+44 1283 761354",
    "sg:postcode":"DE12 8JL",
    "sg:province":"Derbyshire",
    "sg:tags":[
        "pubs",
        "inn"
    ],
    "wof:name":"The Plough Inn",
    "wof:placetype":"venue"
},
  "geometry": {"coordinates":[-1.683019,52.76001],"type":"Point"}
}