{
  "type": "Feature",
  "properties": {
    "addr:full":"Whitford Gardens Mitcham Greater London CR4 4AA",
    "addr:postcode":"cr4 4aa",
    "addr:street":"Whitford Gardens",
    "iso:country":"GB",
    "sg:address":"Whitford Gardens",
    "sg:city":"Mitcham",
    "sg:classifiers":[
        {
            "category":"Health Services",
            "subcategory":"Nursing And Care Facility",
            "type":"Services"
        }
    ],
    "sg:phone":"+44 20 8646 1551",
    "sg:postcode":"CR4 4AA",
    "sg:province":"Greater London",
    "sg:tags":[
        "home"
    ],
    "wof:name":"Cumberland Nursing Home The",
    "wof:placetype":"venue"
},
  "geometry": {"coordinates":[-0.164414,51.402889],"type":"Point"}
}