{
  "type": "Feature",
  "properties": {
    "addr:full":"23-25 St Augustines Street Norwich Norfolk NR3 3BY",
    "addr:housenumber":"23-25",
    "addr:postcode":"nr3 3by",
    "addr:street":"St Augustines Street",
    "iso:country":"GB",
    "sg:address":"23-25 St Augustines Street",
    "sg:city":"Norwich",
    "sg:classifiers":[
        {
            "category":"Personal",
            "subcategory":"Tattoo Parlor",
            "type":"Services"
        }
    ],
    "sg:phone":"+44 1603 667511",
    "sg:postcode":"NR3 3BY",
    "sg:province":"Norfolk",
    "sg:tags":[
        "tattooing",
        "piercing",
        "artist"
    ],
    "wof:name":"Styx Tattoo Studio",
    "wof:placetype":"venue"
},
  "geometry": {"coordinates":[1.2927930355,52.6376724243],"type":"Point"}
}