{
  "type": "Feature",
  "properties": {
    "iso:country":"GB",
    "sg:address":"Brooklyn 8 West Hill",
    "sg:city":"Budleigh Salterton",
    "sg:classifiers":[
        {
            "category":"Professional",
            "subcategory":"Art Services",
            "type":"Services"
        }
    ],
    "sg:phone":"+44 1395 443381",
    "sg:postcode":"EX9 6BW",
    "sg:province":"Devon",
    "sg:tags":[
        "graphic",
        "designer"
    ],
    "wof:name":"N.r.graphics",
    "wof:placetype":"venue"
},
  "geometry": {"coordinates":[-3.3303,50.629742],"type":"Point"}
}