{
  "type": "Feature",
  "properties": {
    "addr:full":"16-20 Platt Street Sheffield South Yorkshire S3 8BQ",
    "addr:housenumber":"16-20",
    "addr:postcode":"s3 8bq",
    "addr:street":"Platt Street",
    "iso:country":"GB",
    "sg:address":"16-20 Platt Street",
    "sg:city":"Sheffield",
    "sg:classifiers":[
        {
            "category":"Building & Trades",
            "subcategory":"Construction",
            "type":"Services"
        }
    ],
    "sg:phone":"+44 114 272 5399",
    "sg:postcode":"S3 8BQ",
    "sg:province":"South Yorkshire",
    "sg:tags":[
        "roofing"
    ],
    "wof:name":"Malden Roofing Contractors (Sheffield) Ltd.",
    "wof:placetype":"venue"
},
  "geometry": {"coordinates":[-1.474456,53.393276],"type":"Point"}
}