{
  "type": "Feature",
  "properties": {
    "iso:country":"GB",
    "sg:address":"9 The Row, Market Street",
    "sg:city":"Wirral",
    "sg:classifiers":[
        {
            "category":"Food & Beverages",
            "subcategory":"Fruits & Vegetables",
            "type":"Retail Goods"
        }
    ],
    "sg:phone":"+44 151 632 1981",
    "sg:postcode":"CH47 3BB",
    "sg:province":"Merseyside",
    "sg:tags":[
        "greengrocer"
    ],
    "wof:name":"A & D Doyles",
    "wof:placetype":"venue"
},
  "geometry": {"coordinates":[-3.17655,53.392941],"type":"Point"}
}