{
  "type": "Feature",
  "properties": {
    "iso:country":"GB",
    "sg:address":"7 Boothferry Road",
    "sg:city":"Goole",
    "sg:classifiers":[
        {
            "category":"Shopping",
            "subcategory":"Jewelry",
            "type":"Retail Goods"
        },
        {
            "category":"Shopping",
            "subcategory":"Comic Books",
            "type":"Retail Goods"
        }
    ],
    "sg:phone":"+44 1405 763556",
    "sg:postcode":"DN14 5DE",
    "sg:province":"East Riding of Yorkshire",
    "sg:tags":[
        "jeweller",
        "sale",
        "jewellery"
    ],
    "wof:name":"Arthur Read Ltd",
    "wof:placetype":"venue"
},
  "geometry": {"coordinates":[-0.871882,53.703876],"type":"Point"}
}