{
  "type": "Feature",
  "properties": {
    "addr:full":"Highfield Farm, Hemingby Rd Horncastle Lincolnshire LN9 5QN",
    "addr:housenumber":"highfield",
    "addr:postcode":"ln9 5qn",
    "addr:street":"Hemingby Rd",
    "iso:country":"GB",
    "sg:address":"Highfield Farm, Hemingby Rd",
    "sg:city":"Horncastle",
    "sg:classifiers":[
        {
            "category":"Farming",
            "subcategory":"Farm",
            "type":"Manufacturing & Wholesale Goods"
        }
    ],
    "sg:phone":"+44 1507 533730",
    "sg:postcode":"LN9 5QN",
    "sg:province":"Lincolnshire",
    "sg:tags":[
        "mixed",
        "crop"
    ],
    "wof:name":"J M Morton & Sons",
    "wof:placetype":"venue"
},
  "geometry": {"coordinates":[-0.1147650033,53.2085227966],"type":"Point"}
}