{
  "type": "Feature",
  "properties": {
    "addr:full":"Rear Of, 18 Portland Road, South Norwood London Greater London SE25 4PF",
    "addr:housenumber":"rear of 18",
    "addr:postcode":"se25 4pf",
    "addr:street":"Portland Road",
    "iso:country":"GB",
    "sg:address":"Rear Of, 18 Portland Road, South Norwood",
    "sg:city":"London",
    "sg:classifiers":[
        {
            "category":"Professional",
            "subcategory":"Printing & Photocopies",
            "type":"Services"
        }
    ],
    "sg:phone":"+44 20 8654 1324",
    "sg:postcode":"SE25 4PF",
    "sg:province":"Greater London",
    "sg:tags":[
        "printer"
    ],
    "wof:name":"Christopher Gordon Ltd.",
    "wof:placetype":"venue"
},
  "geometry": {"coordinates":[-0.0739940032,51.3991546631],"type":"Point"}
}