{
  "type": "Feature",
  "properties": {
    "addr:full":"2 New Gap, Manchester Road Heywood Lancashire OL10 2AH",
    "addr:housenumber":"2",
    "addr:postcode":"ol10 2ah",
    "addr:street":"New Gap Manchester Road",
    "iso:country":"GB",
    "sg:address":"2 New Gap, Manchester Road",
    "sg:city":"Heywood",
    "sg:classifiers":[
        {
            "category":"Bars & Pubs",
            "type":"Food & Drink"
        }
    ],
    "sg:phone":"+44 1706 369121",
    "sg:postcode":"OL10 2AH",
    "sg:province":"Lancashire",
    "sg:tags":[
        "pubs",
        "inn"
    ],
    "wof:name":"The Gardeners Arms",
    "wof:placetype":"venue"
},
  "geometry": {"coordinates":[-2.2110040188,53.5890808105],"type":"Point"}
}