{
  "type": "Feature",
  "properties": {
    "iso:country":"GB",
    "sg:address":"Westwood Farm Bretton Gate, Westwood",
    "sg:city":"Peterborough",
    "sg:classifiers":[
        {
            "category":"Food & Beverages",
            "subcategory":"Supermarket",
            "type":"Retail Goods"
        }
    ],
    "sg:phone":"+44 1733 262601",
    "sg:postcode":"PE3 9UP",
    "sg:province":"Cambridgeshire",
    "sg:tags":[
        "frozen"
    ],
    "wof:name":"The New Covent Garden Soup Co. Ltd.",
    "wof:placetype":"venue"
},
  "geometry": {"coordinates":[-0.250052,52.572987],"type":"Point"}
}