{
  "type": "Feature",
  "properties": {
    "addr:full":"390 Barking Road London Greater London E13 8HJ",
    "addr:housenumber":"390",
    "addr:postcode":"e13 8hj",
    "addr:street":"Barking Road",
    "iso:country":"GB",
    "sg:address":"390 Barking Road",
    "sg:city":"London",
    "sg:classifiers":[
        {
            "category":"Autos & Motor Vehicles",
            "subcategory":"Automobile Sales",
            "type":"Retail Goods"
        },
        {
            "category":"Cafe",
            "type":"Food & Drink"
        }
    ],
    "sg:phone":"+44 20 7476 3637",
    "sg:postcode":"E13 8HJ",
    "sg:province":"Greater London",
    "sg:tags":[
        "tea",
        "snack",
        "bar",
        "room",
        "car"
    ],
    "wof:name":"Abbey Restaurant",
    "wof:placetype":"venue"
},
  "geometry": {"coordinates":[0.022806,51.5223388672],"type":"Point"}
}