{
  "type": "Feature",
  "properties": {
    "iso:country":"GB",
    "sg:address":"Room 4, 111 Haughton Green Rd",
    "sg:city":"Manchester",
    "sg:classifiers":[
        {
            "category":"Professional",
            "subcategory":"Detective & Security Services",
            "type":"Services"
        }
    ],
    "sg:postcode":"M34 7AW",
    "sg:province":"Greater Manchester",
    "sg:tags":[
        "agency"
    ],
    "wof:name":"Centrepoint Investigations Ltd",
    "wof:placetype":"venue"
},
  "geometry": {"coordinates":[-2.0985200405,53.4408035278],"type":"Point"}
}