{
  "type": "Feature",
  "properties": {
    "iso:country":"GB",
    "sg:address":"217 Woodhouse Lane East, Timperley",
    "sg:city":"Altrincham",
    "sg:classifiers":[
        {
            "category":"Home & Garden",
            "subcategory":"Household Appliances",
            "type":"Retail Goods"
        }
    ],
    "sg:phone":"+44 161 969 4600",
    "sg:postcode":"WA15 6AS",
    "sg:province":"Cheshire",
    "sg:tags":[
        "electrical"
    ],
    "wof:name":"Washdays",
    "wof:placetype":"venue"
},
  "geometry": {"coordinates":[-2.3224339485,53.4072265625],"type":"Point"}
}