{
  "type": "Feature",
  "properties": {
    "addr:full":"46 Sompting Road Lancing West Sussex BN15 9JX",
    "addr:housenumber":"46",
    "addr:postcode":"bn15 9jx",
    "addr:street":"Sompting Road",
    "iso:country":"GB",
    "sg:address":"46 Sompting Road",
    "sg:city":"Lancing",
    "sg:classifiers":[
        {
            "category":"Health Services",
            "subcategory":"Clinic",
            "type":"Services"
        }
    ],
    "sg:postcode":"BN15 9JX",
    "sg:province":"West Sussex",
    "sg:tags":[
        "private"
    ],
    "wof:name":"Sompting Manor Clinic",
    "wof:placetype":"venue"
},
  "geometry": {"coordinates":[-0.3268719912,50.8279533386],"type":"Point"}
}