{
  "type": "Feature",
  "properties": {
    "addr:full":"17 St Annes Close Bristol Gloucestershire BS30 8EH",
    "addr:housenumber":"17",
    "addr:postcode":"bs30 8eh",
    "addr:street":"St Annes Close",
    "iso:country":"GB",
    "sg:address":"17 St Annes Close",
    "sg:city":"Bristol",
    "sg:classifiers":[
        {
            "category":"Professional",
            "subcategory":"Computer Services",
            "type":"Services"
        }
    ],
    "sg:phone":"+44 117 908 2708",
    "sg:postcode":"BS30 8EH",
    "sg:province":"Gloucestershire",
    "sg:tags":[
        "system",
        "software"
    ],
    "wof:name":"Datahawk Business Systems",
    "wof:placetype":"venue"
},
  "geometry": {"coordinates":[-2.4834520817,51.4427490234],"type":"Point"}
}