{
  "type": "Feature",
  "properties": {
    "iso:country":"GB",
    "sg:address":"20 Howick Park Close, Penwortham",
    "sg:city":"Preston",
    "sg:classifiers":[
        {
            "category":"Building & Trades",
            "subcategory":"Construction",
            "type":"Services"
        }
    ],
    "sg:phone":"+44 1772 741753",
    "sg:postcode":"PR1 0LT",
    "sg:province":"Lancashire",
    "sg:tags":[
        "joiner",
        "carpenter"
    ],
    "wof:name":"Rosewood Joinery",
    "wof:placetype":"venue"
},
  "geometry": {"coordinates":[-2.747517,53.743599],"type":"Point"}
}