{
  "type": "Feature",
  "properties": {
    "iso:country":"GB",
    "sg:address":"143 Unthank Road",
    "sg:city":"Norwich",
    "sg:classifiers":[
        {
            "category":"Shopping",
            "subcategory":"Pharmacy",
            "type":"Retail Goods"
        }
    ],
    "sg:phone":"+44 1603 623769",
    "sg:postcode":"NR2 2PE",
    "sg:province":"Norfolk",
    "sg:tags":[
        "pharmacist",
        "dispensing",
        "chemist"
    ],
    "wof:name":"Hurn Chemist",
    "wof:placetype":"venue"
},
  "geometry": {"coordinates":[1.276451,52.623508],"type":"Point"}
}