{
  "type": "Feature",
  "properties": {
    "addr:full":"Lanrigg Avenue, Fauldhouse Bathgate North Lanarkshire EH47 9JR",
    "addr:postcode":"eh47 9jr",
    "addr:street":"Avenue;Bathgate",
    "iso:country":"GB",
    "sg:address":"Lanrigg Avenue, Fauldhouse",
    "sg:city":"Bathgate",
    "sg:classifiers":[
        {
            "category":"Health Services",
            "subcategory":"Clinic",
            "type":"Services"
        }
    ],
    "sg:phone":"+44 1501 770205",
    "sg:postcode":"EH47 9JR",
    "sg:province":"North Lanarkshire",
    "sg:tags":[
        "private"
    ],
    "wof:name":"Community Dental Service",
    "wof:placetype":"venue"
},
  "geometry": {"coordinates":[-3.7006709576,55.8338317871],"type":"Point"}
}