{
  "type": "Feature",
  "properties": {
    "addr:full":"16 Electric Parade, George Lane London Greater London E18 2LY",
    "addr:housenumber":"16",
    "addr:postcode":"e18 2ly",
    "addr:street":"Electric Parade George Lane",
    "iso:country":"GB",
    "sg:address":"16 Electric Parade, George Lane",
    "sg:city":"London",
    "sg:classifiers":[
        {
            "category":"Shopping",
            "subcategory":"Jewelry",
            "type":"Retail Goods"
        },
        {
            "category":"Shopping",
            "subcategory":"Comic Books",
            "type":"Retail Goods"
        }
    ],
    "sg:phone":"+44 20 8530 3510",
    "sg:postcode":"E18 2LY",
    "sg:province":"Greater London",
    "sg:tags":[
        "jeweller",
        "sale",
        "jewellery"
    ],
    "wof:name":"Time Batteries Ltd.",
    "wof:placetype":"venue"
},
  "geometry": {"coordinates":[0.0231759995,51.5948638916],"type":"Point"}
}