{
  "type": "Feature",
  "properties": {
    "iso:country":"GB",
    "sg:address":"Buckland Drive, Netherfield",
    "sg:city":"Milton Keynes",
    "sg:classifiers":[
        {
            "category":"Building & Trades",
            "subcategory":"Construction",
            "type":"Services"
        },
        {
            "category":"Home & Garden",
            "subcategory":"Carpets & Floor Coverings",
            "type":"Retail Goods"
        }
    ],
    "sg:phone":"+44 1908 607000",
    "sg:postcode":"MK6 4JR",
    "sg:province":"Buckinghamshire",
    "sg:tags":[
        "textile",
        "tiling",
        "floorcoverings",
        "contractor"
    ],
    "wof:name":"Captain Carpet",
    "wof:placetype":"venue"
},
  "geometry": {"coordinates":[-0.7356789708,52.0206947327],"type":"Point"}
}