{
  "type": "Feature",
  "properties": {
    "addr:full":"3 Fairgreen Parade, London Road Mitcham Greater London CR4 3NA",
    "addr:housenumber":"3",
    "addr:postcode":"cr4 3na",
    "addr:street":"Fairgreen Parade London Road",
    "iso:country":"GB",
    "sg:address":"3 Fairgreen Parade, London Road",
    "sg:city":"Mitcham",
    "sg:classifiers":[
        {
            "category":"Organizations",
            "subcategory":"Non-profit Organization",
            "type":"Services"
        }
    ],
    "sg:phone":"+44 20 8648 5863",
    "sg:postcode":"CR4 3NA",
    "sg:province":"Greater London",
    "sg:tags":[
        "organisation",
        "voluntary",
        "charity"
    ],
    "wof:name":"Cancer Research Campaign",
    "wof:placetype":"venue"
},
  "geometry": {"coordinates":[-0.164255,51.40715],"type":"Point"}
}