{
  "type": "Feature",
  "properties": {
    "addr:full":"Wyken, Worfield Bridgnorth Shropshire WV15 5NW",
    "addr:housenumber":"bridgnorth",
    "addr:postcode":"wv15 5nw",
    "iso:country":"GB",
    "sg:address":"Wyken, Worfield",
    "sg:city":"Bridgnorth",
    "sg:classifiers":[
        {
            "category":"Food & Beverages",
            "subcategory":"Meat & Fish",
            "type":"Retail Goods"
        }
    ],
    "sg:phone":"+44 1746 716529",
    "sg:postcode":"WV15 5NW",
    "sg:province":"Shropshire",
    "sg:tags":[
        "butcher"
    ],
    "wof:name":"R S Lee (Butchers) Ltd.",
    "wof:placetype":"venue"
},
  "geometry": {"coordinates":[-2.358624,52.556946],"type":"Point"}
}