{
  "type": "Feature",
  "properties": {
    "iso:country":"GB",
    "sg:address":"The Old Barn, Jericho Farm, Worton",
    "sg:city":"Witney",
    "sg:classifiers":[
        {
            "category":"Professional",
            "subcategory":"Management & Consulting",
            "type":"Services"
        }
    ],
    "sg:phone":"+44 1865 316317",
    "sg:postcode":"OX29 4EB",
    "sg:province":"Oxfordshire",
    "sg:tags":[
        "marketing",
        "consultant"
    ],
    "wof:name":"The Oxford Partnership",
    "wof:placetype":"venue"
},
  "geometry": {"coordinates":[-1.332038,51.799561],"type":"Point"}
}