{
  "type": "Feature",
  "properties": {
    "iso:country":"GB",
    "sg:address":"285 Rishton Lane",
    "sg:city":"Bolton",
    "sg:classifiers":[
        {
            "category":"Food & Beverages",
            "subcategory":"Liquor & Beverages",
            "type":"Retail Goods"
        }
    ],
    "sg:phone":"+44 1204 526456",
    "sg:postcode":"BL3 2EH",
    "sg:province":"Lancashire",
    "sg:tags":[
        "beer",
        "spirit",
        "wines"
    ],
    "wof:name":"Regency Wine Shop",
    "wof:placetype":"venue"
},
  "geometry": {"coordinates":[-2.4287230968,53.5607223511],"type":"Point"}
}