{
  "type": "Feature",
  "properties": {
    "addr:full":"19 Glebe Close Hemel Hempstead Hertfordshire HP3 9PA",
    "addr:housenumber":"19",
    "addr:postcode":"hp3 9pa",
    "addr:street":"Glebe Close",
    "iso:country":"GB",
    "sg:address":"19 Glebe Close",
    "sg:city":"Hemel Hempstead",
    "sg:classifiers":[
        {
            "category":"Professional",
            "subcategory":"Management & Consulting",
            "type":"Services"
        }
    ],
    "sg:postcode":"HP3 9PA",
    "sg:province":"Hertfordshire",
    "sg:tags":[
        "consultant",
        "business"
    ],
    "wof:name":"Cooper-Munro Marketing Management & Services",
    "wof:placetype":"venue"
},
  "geometry": {"coordinates":[-0.460252,51.738636],"type":"Point"}
}