{
  "type": "Feature",
  "properties": {
    "iso:country":"GB",
    "sg:address":"Hill Brow",
    "sg:city":"Hove",
    "sg:classifiers":[
        {
            "category":"Professional",
            "subcategory":"Employment Agencies",
            "type":"Services"
        }
    ],
    "sg:phone":"+44 1883 744405",
    "sg:postcode":"BN3 6QG",
    "sg:province":"East Sussex",
    "sg:tags":[
        "introduction"
    ],
    "wof:name":"Elite Introductions Ltd.",
    "wof:placetype":"venue"
},
  "geometry": {"coordinates":[-0.171107,50.853794],"type":"Point"}
}