{
  "type": "Feature",
  "properties": {
    "addr:full":"28 Avenue Rd Seven Sisters Greater London N15 5JH",
    "addr:housenumber":"28",
    "addr:postcode":"n15 5jh",
    "addr:street":"Avenue Rd",
    "iso:country":"GB",
    "sg:address":"28 Avenue Rd",
    "sg:city":"Seven Sisters",
    "sg:classifiers":[
        {
            "category":"Government",
            "subcategory":"Customs House",
            "type":"Public Place"
        }
    ],
    "sg:phone":"+44 20 8800 1002",
    "sg:postcode":"N15 5JH",
    "sg:province":"Greater London",
    "sg:tags":[
        "clearance"
    ],
    "wof:name":"Ron Salter",
    "wof:placetype":"venue"
},
  "geometry": {"coordinates":[-0.0845379978,51.5820121765],"type":"Point"}
}