{
  "type": "Feature",
  "properties": {
    "addr:full":"Gobions Farm, Collier Row Road Romford Essex RM5 2BH",
    "addr:postcode":"rm5 2bh",
    "addr:street":"Collier Row Road",
    "iso:country":"GB",
    "sg:address":"Gobions Farm, Collier Row Road",
    "sg:city":"Romford",
    "sg:classifiers":[
        {
            "category":"Building & Trades",
            "subcategory":"Construction",
            "type":"Services"
        }
    ],
    "sg:phone":"+44 1708 769511",
    "sg:postcode":"RM5 2BH",
    "sg:province":"Essex",
    "sg:tags":[
        "roofing"
    ],
    "wof:name":"Rouse Roofing Co",
    "wof:placetype":"venue"
},
  "geometry": {"coordinates":[0.156395,51.597965],"type":"Point"}
}