{
  "type": "Feature",
  "properties": {
    "iso:country":"GB",
    "sg:address":"Units 3-3a, Roe Farm, Whiston Road",
    "sg:city":"Northampton",
    "sg:classifiers":[
        {
            "category":"Shopping",
            "subcategory":"Computers & Home Electronics",
            "type":"Retail Goods"
        },
        {
            "category":"Home & Garden",
            "subcategory":"Furniture",
            "type":"Retail Goods"
        }
    ],
    "sg:phone":"+44 1604 890956",
    "sg:postcode":"NN7 1NL",
    "sg:province":"Buckinghamshire",
    "sg:website":"http://www.yotfc.co.uk",
    "wof:name":"Ye Olde Traditional Furniture Co Ltd",
    "wof:placetype":"venue"
},
  "geometry": {"coordinates":[-0.7582,52.237385],"type":"Point"}
}