{
  "type": "Feature",
  "properties": {
    "addr:full":"4 Windsor Street Leamington Spa Warwickshire CV32 5EB",
    "addr:housenumber":"4",
    "addr:postcode":"cv32 5eb",
    "addr:street":"Windsor Street",
    "iso:country":"GB",
    "sg:address":"4 Windsor Street",
    "sg:city":"Leamington Spa",
    "sg:classifiers":[
        {
            "category":"Shopping",
            "subcategory":"Antiques",
            "type":"Retail Goods"
        }
    ],
    "sg:phone":"+44 1926 422927",
    "sg:postcode":"CV32 5EB",
    "sg:province":"Warwickshire",
    "wof:name":"Kings Cottage Antiques",
    "wof:placetype":"venue"
},
  "geometry": {"coordinates":[-1.538513,52.291203],"type":"Point"}
}