{
  "type": "Feature",
  "properties": {
    "addr:full":"Springfield Ho, Woodstock Rd Coulsdon Surrey CR5 3HS",
    "addr:postcode":"cr5 3hs",
    "addr:street":"Woodstock Rd",
    "iso:country":"GB",
    "sg:address":"Springfield Ho, Woodstock Rd",
    "sg:city":"Coulsdon",
    "sg:classifiers":[
        {
            "category":"Arena",
            "subcategory":"Sports Club",
            "type":"Entertainment"
        }
    ],
    "sg:phone":"+44 1737 555152",
    "sg:postcode":"CR5 3HS",
    "sg:province":"Surrey",
    "wof:name":"British Bobsleigh Association",
    "wof:placetype":"venue"
},
  "geometry": {"coordinates":[-0.139179,51.318924],"type":"Point"}
}