{
  "type": "Feature",
  "properties": {
    "iso:country":"GB",
    "sg:address":"29 Hatherley Street",
    "sg:city":"Liverpool",
    "sg:classifiers":[
        {
            "category":"Organizations",
            "subcategory":"Religious Organization",
            "type":"Services"
        }
    ],
    "sg:phone":"+44 151 708 9909",
    "sg:postcode":"L8 2TJ",
    "sg:province":"Merseyside",
    "sg:tags":[
        "organisation",
        "place",
        "worship"
    ],
    "wof:name":"Liverpool Islamic Cultural Centre",
    "wof:placetype":"venue"
},
  "geometry": {"coordinates":[-2.960299,53.39423],"type":"Point"}
}