{
  "type": "Feature",
  "properties": {
    "addr:full":"12 The Walk Ipswich Suffolk IP1 1EE",
    "addr:housenumber":"12",
    "addr:postcode":"ip1 1ee",
    "addr:street":"The Walk",
    "iso:country":"GB",
    "sg:address":"12 The Walk",
    "sg:city":"Ipswich",
    "sg:classifiers":[
        {
            "category":"Wholesale",
            "subcategory":"Groceries",
            "type":"Manufacturing & Wholesale Goods"
        }
    ],
    "sg:phone":"+44 1473 281191",
    "sg:postcode":"IP1 1EE",
    "sg:province":"Suffolk",
    "sg:tags":[
        "sausage",
        "product"
    ],
    "wof:name":"Procters Speciality Sausages",
    "wof:placetype":"venue"
},
  "geometry": {"coordinates":[1.2343109846,52.0649757385],"type":"Point"}
}