{
  "type": "Feature",
  "properties": {
    "addr:full":"150 Hastings Road Battle East Sussex TN33 0TW",
    "addr:housenumber":"150",
    "addr:postcode":"tn33 0tw",
    "addr:street":"Hastings Road Battle",
    "iso:country":"GB",
    "sg:address":"150 Hastings Road",
    "sg:city":"Battle",
    "sg:classifiers":[
        {
            "category":"Professional",
            "subcategory":"Computer Services",
            "type":"Services"
        }
    ],
    "sg:phone":"+44 1424 774748",
    "sg:postcode":"TN33 0TW",
    "sg:province":"East Sussex",
    "sg:tags":[
        "consultant"
    ],
    "wof:name":"M C G Applications Ltd.",
    "wof:placetype":"venue"
},
  "geometry": {"coordinates":[0.5106580257,50.9051055908],"type":"Point"}
}