{
  "type": "Feature",
  "properties": {
    "addr:full":"34 Bedwlwyn Road Hengoed Caerphilly CF82 7AD",
    "addr:housenumber":"34",
    "addr:postcode":"cf82 7ad",
    "addr:street":"Bedwlwyn Road",
    "iso:country":"GB",
    "sg:address":"34 Bedwlwyn Road",
    "sg:city":"Hengoed",
    "sg:classifiers":[
        {
            "category":"Food & Beverages",
            "subcategory":"Meat & Fish",
            "type":"Retail Goods"
        }
    ],
    "sg:postcode":"CF82 7AD",
    "sg:province":"Caerphilly",
    "sg:tags":[
        "butcher"
    ],
    "wof:name":"T J Waters",
    "wof:placetype":"venue"
},
  "geometry": {"coordinates":[-3.235200882,51.6422615051],"type":"Point"}
}