{
  "type": "Feature",
  "properties": {
    "iso:country":"GB",
    "sg:address":"21 Upton Rd",
    "sg:city":"Birkenhead",
    "sg:classifiers":[
        {
            "category":"Shopping",
            "subcategory":"Florist",
            "type":"Retail Goods"
        }
    ],
    "sg:phone":"+44 151 653 8188",
    "sg:postcode":"L43 8TG",
    "sg:province":"Merseyside",
    "wof:name":"Sylvia's Flower World",
    "wof:placetype":"venue"
},
  "geometry": {"coordinates":[-3.057763,53.394558],"type":"Point"}
}