{
  "type": "Feature",
  "properties": {
    "addr:full":"832 Newport Road Cardiff Caerphilly CF3 4LH",
    "addr:housenumber":"832",
    "addr:postcode":"cf3 4lh",
    "addr:street":"Newport Road",
    "iso:country":"GB",
    "sg:address":"832 Newport Road",
    "sg:city":"Cardiff",
    "sg:classifiers":[
        {
            "category":"Food & Beverages",
            "subcategory":"Specialty",
            "type":"Retail Goods"
        }
    ],
    "sg:phone":"+44 29 2036 1427",
    "sg:postcode":"CF3 4LH",
    "sg:province":"Caerphilly",
    "sg:tags":[
        "product",
        "health"
    ],
    "wof:name":"Healthcare Shop",
    "wof:placetype":"venue"
},
  "geometry": {"coordinates":[-3.130108,51.509628],"type":"Point"}
}