{
  "type": "Feature",
  "properties": {
    "addr:full":"P O Box 253 Watford Hertfordshire WD1 8AJ",
    "addr:housenumber":"253",
    "addr:postcode":"wd1 8aj",
    "addr:street":"P O Box",
    "iso:country":"GB",
    "sg:address":"P O Box 253",
    "sg:city":"Watford",
    "sg:classifiers":[
        {
            "category":"Organizations",
            "subcategory":"Non-profit Organization",
            "type":"Services"
        }
    ],
    "sg:postcode":"WD1 8AJ",
    "sg:province":"Hertfordshire",
    "sg:tags":[
        "organisation",
        "voluntary",
        "charity"
    ],
    "wof:name":"Womens Aid Federation (England) Ltd",
    "wof:placetype":"venue"
},
  "geometry": {"coordinates":[-0.39072,51.652119],"type":"Point"}
}