{
  "type": "Feature",
  "properties": {
    "iso:country":"GB",
    "sg:address":"35 Hampton Close, Caister-on-sea",
    "sg:city":"Great Yarmouth",
    "sg:classifiers":[
        {
            "category":"Professional",
            "subcategory":"Engineering",
            "type":"Services"
        },
        {
            "category":"Professional",
            "subcategory":"Computer Services",
            "type":"Services"
        }
    ],
    "sg:phone":"+44 1493 300623",
    "sg:postcode":"NR30 5AY",
    "sg:province":"Norfolk",
    "wof:name":"THE AVENUE (ANGLIA) LTD",
    "wof:placetype":"venue"
},
  "geometry": {"coordinates":[1.716233,52.64801],"type":"Point"}
}