{
  "type": "Feature",
  "properties": {
    "addr:full":"Town Centre, Velizy Avenue Harlow Essex CM20 3LH",
    "addr:postcode":"cm20 3lh",
    "addr:street":"Velizy Avenue",
    "iso:country":"GB",
    "sg:address":"Town Centre, Velizy Avenue",
    "sg:city":"Harlow",
    "sg:classifiers":[
        {
            "category":"Restaurant",
            "type":"Food & Drink"
        }
    ],
    "sg:phone":"+44 1279 868060",
    "sg:postcode":"CM20 3LH",
    "sg:province":"Essex",
    "wof:name":"Harlow Technical College",
    "wof:placetype":"venue"
},
  "geometry": {"coordinates":[0.0975060016,51.7731513977],"type":"Point"}
}