{
  "type": "Feature",
  "properties": {
    "addr:full":"103 Garrowsfield, Dollis Valley Way Barnet Hertfordshire EN5 2TZ",
    "addr:housenumber":"103",
    "addr:postcode":"en5 2tz",
    "addr:street":"Garrowsfield Dollis Valley Way",
    "iso:country":"GB",
    "sg:address":"103 Garrowsfield, Dollis Valley Way",
    "sg:city":"Barnet",
    "sg:classifiers":[
        {
            "category":"Building & Trades",
            "subcategory":"Landscaping Services",
            "type":"Services"
        }
    ],
    "sg:postcode":"EN5 2TZ",
    "sg:province":"Hertfordshire",
    "sg:tags":[
        "landscape",
        "contractor"
    ],
    "wof:name":"Monogram",
    "wof:placetype":"venue"
},
  "geometry": {"coordinates":[-0.1992830038,51.645450592],"type":"Point"}
}