{
  "type": "Feature",
  "properties": {
    "addr:full":"5 Station App Croydon Surrey CR0 1LF",
    "addr:housenumber":"5",
    "addr:postcode":"cr0 1lf",
    "iso:country":"GB",
    "sg:address":"5 Station App",
    "sg:city":"Croydon",
    "sg:classifiers":[
        {
            "category":"Shopping",
            "subcategory":"Shoes",
            "type":"Retail Goods"
        }
    ],
    "sg:phone":"+44 20 8681 1292",
    "sg:postcode":"CR0 1LF",
    "sg:province":"Surrey",
    "wof:name":"Timpson Shoe Repairs",
    "wof:placetype":"venue"
},
  "geometry": {"coordinates":[-0.09333,51.37487],"type":"Point"}
}