{
  "type": "Feature",
  "properties": {
    "iso:country":"GB",
    "sg:address":"120 Crescent Road",
    "sg:city":"Middlesbrough",
    "sg:classifiers":[
        {
            "category":"Home & Garden",
            "subcategory":"Hardware",
            "type":"Retail Goods"
        }
    ],
    "sg:postcode":"TS1 4QS",
    "sg:province":"North Yorkshire",
    "sg:tags":[
        "equipment",
        "welding"
    ],
    "wof:name":"Tees Weld",
    "wof:placetype":"venue"
},
  "geometry": {"coordinates":[-1.249324,54.567734],"type":"Point"}
}