{
  "type": "Feature",
  "properties": {
    "addr:full":"71 Cambridge Road Teddington Greater London TW11 8DW",
    "addr:housenumber":"71",
    "addr:postcode":"tw11 8dw",
    "addr:street":"Cambridge Road",
    "iso:country":"GB",
    "sg:address":"71 Cambridge Road",
    "sg:city":"Teddington",
    "sg:classifiers":[
        {
            "category":"Professional",
            "subcategory":"Management & Consulting",
            "type":"Services"
        }
    ],
    "sg:phone":"+44 20 8274 9675",
    "sg:postcode":"TW11 8DW",
    "sg:province":"Greater London",
    "sg:tags":[
        "consultant",
        "business"
    ],
    "wof:name":"G D H Consultancy Ltd.",
    "wof:placetype":"venue"
},
  "geometry": {"coordinates":[-0.330162,51.430088],"type":"Point"}
}