{
  "type": "Feature",
  "properties": {
    "addr:full":"35h Parsonage St Dursley Gloucestershire GL11 4BP",
    "addr:housenumber":"35h",
    "addr:postcode":"gl11 4bp",
    "addr:street":"Parsonage St",
    "iso:country":"GB",
    "sg:address":"35h Parsonage St",
    "sg:city":"Dursley",
    "sg:classifiers":[
        {
            "category":"Shopping",
            "subcategory":"Clothing, Apparel, & Fashions",
            "type":"Retail Goods"
        }
    ],
    "sg:postcode":"GL11 4BP",
    "sg:province":"Gloucestershire",
    "sg:tags":[
        "shop"
    ],
    "wof:name":"Munyard,Joy,",
    "wof:placetype":"venue"
},
  "geometry": {"coordinates":[-2.357098,51.681862],"type":"Point"}
}