{
  "type": "Feature",
  "properties": {
    "iso:country":"GB",
    "sg:address":"35 Market Street, Church Gresley",
    "sg:city":"Swadlincote",
    "sg:classifiers":[
        {
            "category":"Shopping",
            "subcategory":"Gifts & Souvenirs",
            "type":"Retail Goods"
        },
        {
            "category":"Government",
            "subcategory":"Post Office",
            "type":"Public Place"
        }
    ],
    "sg:phone":"+44 1283 217555",
    "sg:postcode":"DE11 9PR",
    "sg:province":"Derbyshire",
    "sg:tags":[
        "poster",
        "card"
    ],
    "wof:name":"Church Gresley Post Office",
    "wof:placetype":"venue"
},
  "geometry": {"coordinates":[-1.572079,52.76392],"type":"Point"}
}