{
  "type": "Feature",
  "properties": {
    "addr:full":"Lodge Farm, Childrey Wantage Berkshire OX12 9XA",
    "addr:postcode":"ox12 9xa",
    "addr:street":"Lodge",
    "iso:country":"GB",
    "sg:address":"Lodge Farm, Childrey",
    "sg:city":"Wantage",
    "sg:classifiers":[
        {
            "category":"Professional",
            "subcategory":"Computer Services",
            "type":"Services"
        }
    ],
    "sg:phone":"+44 1235 751335",
    "sg:postcode":"OX12 9XA",
    "sg:province":"Berkshire",
    "sg:tags":[
        "consultant"
    ],
    "wof:name":"Lucy Byrom",
    "wof:placetype":"venue"
},
  "geometry": {"coordinates":[-1.479599,51.584919],"type":"Point"}
}