{
  "type": "Feature",
  "properties": {
    "addr:full":"Old Oscott Hill Birmingham West Midlands B44 9SR",
    "addr:postcode":"b44 9sr",
    "addr:street":"Old Oscott Hill",
    "iso:country":"GB",
    "sg:address":"Old Oscott Hill",
    "sg:city":"Birmingham",
    "sg:classifiers":[
        {
            "category":"Education",
            "subcategory":"School",
            "type":"Public Place"
        },
        {
            "category":"Government",
            "subcategory":"Office",
            "type":"Public Place"
        }
    ],
    "sg:phone":"+44 121 360 6383",
    "sg:postcode":"B44 9SR",
    "sg:province":"West Midlands",
    "sg:tags":[
        "local",
        "authority"
    ],
    "wof:name":"Cardinal Wiseman R C Secondary School",
    "wof:placetype":"venue"
},
  "geometry": {"coordinates":[-1.8859889507,52.5490684509],"type":"Point"}
}