{
  "type": "Feature",
  "properties": {
    "iso:country":"GB",
    "sg:address":"15 King Street",
    "sg:city":"Hereford",
    "sg:classifiers":[
        {
            "category":"Education",
            "subcategory":"Special Training",
            "type":"Public Place"
        }
    ],
    "sg:phone":"+44 1432 359244",
    "sg:postcode":"HR4 9BX",
    "sg:province":"Herefordshire",
    "sg:tags":[
        "product",
        "centre"
    ],
    "wof:name":"Riverside Training Ltd.",
    "wof:placetype":"venue"
},
  "geometry": {"coordinates":[-2.71911,52.054443],"type":"Point"}
}