{
  "type": "Feature",
  "properties": {
    "iso:country":"GB",
    "sg:address":"Llandeilo Road, Llandybie",
    "sg:city":"Ammanford",
    "sg:classifiers":[
        {
            "category":"Bars & Pubs",
            "type":"Food & Drink"
        }
    ],
    "sg:phone":"+44 1269 851202",
    "sg:postcode":"SA18 3JA",
    "sg:province":"Carmarthenshire",
    "sg:tags":[
        "pubs",
        "inn"
    ],
    "wof:name":"Red Lion Hotel",
    "wof:placetype":"venue"
},
  "geometry": {"coordinates":[-4.010349,51.824448],"type":"Point"}
}