{
  "type": "Feature",
  "properties": {
    "addr:full":"21 Edgehill Terrace Aberdeen Aberdeen City AB15 5HA",
    "addr:housenumber":"21",
    "addr:postcode":"ab15 5ha",
    "addr:street":"Edgehill Terrace",
    "iso:country":"GB",
    "sg:address":"21 Edgehill Terrace",
    "sg:city":"Aberdeen",
    "sg:classifiers":[
        {
            "category":"Professional",
            "subcategory":"Management & Consulting",
            "type":"Services"
        },
        {
            "category":"Professional",
            "subcategory":"Computer Services",
            "type":"Services"
        }
    ],
    "sg:phone":"+44 1224 325230",
    "sg:postcode":"AB15 5HA",
    "sg:province":"Aberdeen City",
    "sg:tags":[
        "development",
        "consultant",
        "business",
        "software"
    ],
    "wof:name":"Management & Operational Systems Ltd.",
    "wof:placetype":"venue"
},
  "geometry": {"coordinates":[-2.146192,57.147259],"type":"Point"}
}