{
  "type": "Feature",
  "properties": {
    "addr:full":"21 Ridge Avenue London Greater London N21 2RL",
    "addr:housenumber":"21",
    "addr:postcode":"n21 2rl",
    "addr:street":"Ridge Avenue",
    "iso:country":"GB",
    "sg:address":"21 Ridge Avenue",
    "sg:city":"London",
    "sg:classifiers":[
        {
            "category":"Building & Trades",
            "subcategory":"Cleaning & Sanitation",
            "type":"Services"
        }
    ],
    "sg:phone":"+44 20 8360 0905",
    "sg:postcode":"N21 2RL",
    "sg:province":"Greater London",
    "sg:tags":[
        "contracting",
        "commercial"
    ],
    "wof:name":"E J Cleaning Services",
    "wof:placetype":"venue"
},
  "geometry": {"coordinates":[-0.0878489986,51.6358718872],"type":"Point"}
}