{
  "type": "Feature",
  "properties": {
    "addr:full":"49 Head Street Colchester Essex CO1 1NY",
    "addr:housenumber":"49",
    "addr:postcode":"co1 1ny",
    "addr:street":"Head Street",
    "iso:country":"GB",
    "sg:address":"49 Head Street",
    "sg:city":"Colchester",
    "sg:classifiers":[
        {
            "category":"Fast Food",
            "type":"Food & Drink"
        }
    ],
    "sg:phone":"+44 1206 577719",
    "sg:postcode":"CO1 1NY",
    "sg:province":"Essex",
    "sg:tags":[
        "away",
        "take"
    ],
    "wof:name":"Goodlife Sandwich Bar",
    "wof:placetype":"venue"
},
  "geometry": {"coordinates":[0.896098,51.888119],"type":"Point"}
}