{
  "type": "Feature",
  "properties": {
    "iso:country":"GB",
    "sg:address":"Bingley, Llanfwrog",
    "sg:city":"Ruthin",
    "sg:classifiers":[
        {
            "category":"Building & Trades",
            "subcategory":"Construction",
            "type":"Services"
        }
    ],
    "sg:phone":"+44 1824 705298",
    "sg:postcode":"LL15 2AH",
    "sg:province":"Denbighshire",
    "sg:tags":[
        "contractor"
    ],
    "wof:name":"Lloyd Building Services (Clwyd)",
    "wof:placetype":"venue"
},
  "geometry": {"coordinates":[-3.32648,53.109814],"type":"Point"}
}