{
  "type": "Feature",
  "properties": {
    "iso:country":"GB",
    "sg:address":"2a Beech Avenue, Cambuslang",
    "sg:city":"Glasgow",
    "sg:classifiers":[
        {
            "category":"Manufacturing",
            "subcategory":"Electronics",
            "type":"Manufacturing & Wholesale Goods"
        }
    ],
    "sg:phone":"+44 141 646 2410",
    "sg:postcode":"G72 8AU",
    "sg:province":"South Lanarkshire",
    "sg:tags":[
        "mnfr",
        "component",
        "electronic"
    ],
    "wof:name":"Re-tek Ltd",
    "wof:placetype":"venue"
},
  "geometry": {"coordinates":[-4.1744060516,55.8195304871],"type":"Point"}
}