{
  "type": "Feature",
  "properties": {
    "addr:full":"Unit 6, Uplands Business Park, Blackhorse Lane Walthamstow Greater London E17 5QN",
    "addr:housenumber":"unit 6",
    "addr:postcode":"e17 5qn",
    "addr:street":"Uplands Business Park Blackhorse Lane",
    "iso:country":"GB",
    "sg:address":"Unit 6, Uplands Business Park, Blackhorse Lane",
    "sg:city":"Walthamstow",
    "sg:classifiers":[
        {
            "category":"Shopping",
            "subcategory":"Clothing, Apparel, & Fashions",
            "type":"Retail Goods"
        }
    ],
    "sg:phone":"+44 20 8531 7651",
    "sg:postcode":"E17 5QN",
    "sg:province":"Greater London",
    "sg:tags":[
        "menswear"
    ],
    "wof:name":"Mister Byrite",
    "wof:placetype":"venue"
},
  "geometry": {"coordinates":[-0.041224,51.594372],"type":"Point"}
}