{
  "type": "Feature",
  "properties": {
    "iso:country":"GB",
    "sg:address":"76 Duckpool Road",
    "sg:city":"Newport",
    "sg:classifiers":[
        {
            "category":"Building & Trades",
            "subcategory":"Construction",
            "type":"Services"
        }
    ],
    "sg:postcode":"NP19 7EQ",
    "sg:province":"Newport",
    "sg:tags":[
        "dry",
        "lining",
        "plasterers",
        "screeders"
    ],
    "wof:name":"Elite Plastering Contractors",
    "wof:placetype":"venue"
},
  "geometry": {"coordinates":[-2.9829308987,51.5952682495],"type":"Point"}
}