{
  "type": "Feature",
  "properties": {
    "iso:country":"GB",
    "sg:address":"Afcama House",
    "sg:city":"Aberdeen",
    "sg:classifiers":[
        {
            "category":"Professional",
            "subcategory":"Business Services",
            "type":"Services"
        },
        {
            "category":"Recreation",
            "subcategory":"Fishing",
            "type":"Entertainment"
        }
    ],
    "sg:postcode":"AB11 9FJ",
    "sg:province":"Aberdeen City",
    "sg:tags":[
        "angling",
        "trade"
    ],
    "wof:name":"Aberdeen Fish Curers & Merchants Association Ltd.",
    "wof:placetype":"venue"
},
  "geometry": {"coordinates":[-2.082119,57.13665],"type":"Point"}
}