{
  "type": "Feature",
  "properties": {
    "iso:country":"GB",
    "sg:address":"65 The Thoroughfare",
    "sg:city":"Woodbridge",
    "sg:classifiers":[
        {
            "category":"Restaurant",
            "type":"Food & Drink"
        }
    ],
    "sg:phone":"+44 1394 385633",
    "sg:postcode":"IP12 1AH",
    "sg:province":"Suffolk",
    "wof:name":"Mrs Piper's",
    "wof:placetype":"venue"
},
  "geometry": {"coordinates":[1.330812,52.106033],"type":"Point"}
}