{
  "type": "Feature",
  "properties": {
    "iso:country":"GB",
    "sg:address":"86 Temple Fortune Lane",
    "sg:city":"London",
    "sg:classifiers":[
        {
            "category":"Professional",
            "subcategory":"Management & Consulting",
            "type":"Services"
        },
        {
            "category":"Professional",
            "subcategory":"Employment Agencies",
            "type":"Services"
        }
    ],
    "sg:phone":"+44 20 8922 9222",
    "sg:postcode":"NW11 7TX",
    "sg:province":"Greater London",
    "sg:tags":[
        "consultant",
        "business"
    ],
    "wof:name":"Cloverhawk Ltd.",
    "wof:placetype":"venue"
},
  "geometry": {"coordinates":[-0.196949,51.580879],"type":"Point"}
}