{
  "type": "Feature",
  "properties": {
    "iso:country":"GB",
    "sg:address":"21 Sydney Road, Wollaton",
    "sg:city":"Nottingham",
    "sg:classifiers":[
        {
            "category":"Building & Trades",
            "subcategory":"Cleaning & Sanitation",
            "type":"Services"
        }
    ],
    "sg:phone":"+44 115 928 3734",
    "sg:postcode":"NG8 1LH",
    "sg:province":"Nottinghamshire",
    "sg:tags":[
        "boiler"
    ],
    "wof:name":"Alan Dinley Heating Services",
    "wof:placetype":"venue"
},
  "geometry": {"coordinates":[-1.1996480227,52.9575691223],"type":"Point"}
}