{
  "type": "Feature",
  "properties": {
    "addr:full":"Woodside Industrial Estate Usk Monmouthshire NP15 1SS",
    "addr:postcode":"np15 1ss",
    "addr:street":"Industrial Estate",
    "iso:country":"GB",
    "sg:address":"Woodside Industrial Estate",
    "sg:city":"Usk",
    "sg:classifiers":[
        {
            "category":"Home & Garden",
            "subcategory":"Hardware",
            "type":"Retail Goods"
        }
    ],
    "sg:phone":"+44 1291 673484",
    "sg:postcode":"NP15 1SS",
    "sg:province":"Monmouthshire",
    "sg:tags":[
        "lawnmowers",
        "machinery"
    ],
    "wof:name":"R & C Field",
    "wof:placetype":"venue"
},
  "geometry": {"coordinates":[-2.902849,51.703735],"type":"Point"}
}