{
  "type": "Feature",
  "properties": {
    "iso:country":"GB",
    "sg:address":"Unit 4a Allens Industrial Park, Coulman Road",
    "sg:city":"Doncaster",
    "sg:classifiers":[
        {
            "category":"Building & Trades",
            "subcategory":"Construction",
            "type":"Services"
        }
    ],
    "sg:postcode":"DN8 5JU",
    "sg:province":"East Riding of Yorkshire",
    "sg:tags":[
        "welder"
    ],
    "wof:name":"Shield",
    "wof:placetype":"venue"
},
  "geometry": {"coordinates":[-0.950053,53.618034],"type":"Point"}
}