{
  "type": "Feature",
  "properties": {
    "addr:full":"30 Long Street, Easingwold York North Yorkshire YO61 3HT",
    "addr:housenumber":"30",
    "addr:postcode":"yo61 3ht",
    "addr:street":"Long Street",
    "iso:country":"GB",
    "sg:address":"30 Long Street, Easingwold",
    "sg:city":"York",
    "sg:classifiers":[
        {
            "category":"Home & Garden",
            "subcategory":"Home Furnishings",
            "type":"Retail Goods"
        }
    ],
    "sg:phone":"+44 1347 821188",
    "sg:postcode":"YO61 3HT",
    "sg:province":"North Yorkshire",
    "sg:tags":[
        "mantelpiece",
        "fireplace"
    ],
    "wof:name":"Old Flames",
    "wof:placetype":"venue"
},
  "geometry": {"coordinates":[-1.19646,54.121426],"type":"Point"}
}