{
  "type": "Feature",
  "properties": {
    "addr:full":"Tan Rhiw, Beach Road Pentraeth Isle of Anglesey LL75 8YG",
    "addr:postcode":"ll75 8yg",
    "addr:street":"Rhiw Beach Road",
    "iso:country":"GB",
    "sg:address":"Tan Rhiw, Beach Road",
    "sg:city":"Pentraeth",
    "sg:classifiers":[
        {
            "category":"Manufacturing",
            "subcategory":"Building Materials",
            "type":"Manufacturing & Wholesale Goods"
        }
    ],
    "sg:postcode":"LL75 8YG",
    "sg:province":"Isle of Anglesey",
    "sg:tags":[
        "stonemason"
    ],
    "wof:name":"Anglesey Powerclean Ltd",
    "wof:placetype":"venue"
},
  "geometry": {"coordinates":[-4.2166237831,53.2825965881],"type":"Point"}
}