{
  "type": "Feature",
  "properties": {
    "addr:full":"Sarah Duffen Cntr, Belmont Street Southsea Hampshire PO5 1NA",
    "addr:postcode":"po5 1na",
    "addr:street":"Belmont Street",
    "iso:country":"GB",
    "sg:address":"Sarah Duffen Cntr, Belmont Street",
    "sg:city":"Southsea",
    "sg:classifiers":[
        {
            "category":"Organizations",
            "subcategory":"Non-profit Organization",
            "type":"Services"
        }
    ],
    "sg:phone":"+44 23 9282 4261",
    "sg:postcode":"PO5 1NA",
    "sg:province":"Hampshire",
    "sg:tags":[
        "organisation",
        "voluntary",
        "charity"
    ],
    "wof:name":"The Portsmouth Down Syndrom Trust",
    "wof:placetype":"venue"
},
  "geometry": {"coordinates":[-1.0881639719,50.7846641541],"type":"Point"}
}