{
  "type": "Feature",
  "properties": {
    "addr:full":"55 Christie Close, Walderslade Chatham Kent ME5 7NQ",
    "addr:housenumber":"55",
    "addr:postcode":"me5 7nq",
    "addr:street":"Christie Close",
    "iso:country":"GB",
    "sg:address":"55 Christie Close, Walderslade",
    "sg:city":"Chatham",
    "sg:classifiers":[
        {
            "category":"Retail",
            "subcategory":"Driving School",
            "type":"Services"
        }
    ],
    "sg:postcode":"ME5 7NQ",
    "sg:province":"Kent",
    "wof:name":"Kevin McCaffery",
    "wof:placetype":"venue"
},
  "geometry": {"coordinates":[0.537065,51.352875],"type":"Point"}
}