{
  "type": "Feature",
  "properties": {
    "addr:full":"194 Honeypot Lane Stanmore Greater London HA7 1EE",
    "addr:housenumber":"194",
    "addr:postcode":"ha7 1ee",
    "addr:street":"Honeypot Lane",
    "iso:country":"GB",
    "sg:address":"194 Honeypot Lane",
    "sg:city":"Stanmore",
    "sg:classifiers":[
        {
            "category":"Shopping",
            "type":"Retail Goods"
        }
    ],
    "sg:phone":"+44 20 8206 0170",
    "sg:postcode":"HA7 1EE",
    "sg:province":"Greater London",
    "sg:tags":[
        "part",
        "accessory"
    ],
    "wof:name":"Discount Motor Spares",
    "wof:placetype":"venue"
},
  "geometry": {"coordinates":[-0.290422,51.593735],"type":"Point"}
}