{
  "type": "Feature",
  "properties": {
    "addr:full":"8 Middlesbrough Rd Middlesbrough North Yorkshire TS6 6NR",
    "addr:housenumber":"8",
    "addr:postcode":"ts6 6nr",
    "addr:street":"Middlesbrough Rd",
    "iso:country":"GB",
    "sg:address":"8 Middlesbrough Rd",
    "sg:city":"Middlesbrough",
    "sg:classifiers":[
        {
            "category":"Shopping",
            "subcategory":"Used Merchandise",
            "type":"Retail Goods"
        }
    ],
    "sg:phone":"+44 1642 452710",
    "sg:postcode":"TS6 6NR",
    "sg:province":"North Yorkshire",
    "sg:tags":[
        "shop",
        "second-hand"
    ],
    "wof:name":"Richies",
    "wof:placetype":"venue"
},
  "geometry": {"coordinates":[-1.1759029627,54.5802497864],"type":"Point"}
}