{
  "type": "Feature",
  "properties": {
    "iso:country":"GB",
    "sg:address":"11 Selsdon Way",
    "sg:city":"Poplar",
    "sg:classifiers":[
        {
            "category":"Health Services",
            "subcategory":"Health Practitioner",
            "type":"Services"
        }
    ],
    "sg:phone":"+44 20 7515 4000",
    "sg:postcode":"E14 9GL",
    "sg:province":"Greater London",
    "sg:tags":[
        "osteopath"
    ],
    "wof:name":"London School of Osteopathy",
    "wof:placetype":"venue"
},
  "geometry": {"coordinates":[-0.015323,51.494457],"type":"Point"}
}