{
  "type": "Feature",
  "properties": {
    "addr:full":"16 Hainton Avenue Grimsby Lincolnshire DN32 9BB",
    "addr:housenumber":"16",
    "addr:postcode":"dn32 9bb",
    "addr:street":"Hainton Avenue",
    "iso:country":"GB",
    "sg:address":"16 Hainton Avenue",
    "sg:city":"Grimsby",
    "sg:classifiers":[
        {
            "category":"Manufacturing",
            "subcategory":"Tools & Machinery",
            "type":"Manufacturing & Wholesale Goods"
        }
    ],
    "sg:postcode":"DN32 9BB",
    "sg:province":"Lincolnshire",
    "sg:tags":[
        "society",
        "friendly"
    ],
    "wof:name":"Bell Insurance Services",
    "wof:placetype":"venue"
},
  "geometry": {"coordinates":[-0.075279,53.566174],"type":"Point"}
}