{
  "type": "Feature",
  "properties": {
    "addr:full":"Unit 2 Small Heath Industrial Estate Birmingham West Midlands B11 2RJ",
    "addr:housenumber":"unit 2",
    "addr:postcode":"b11 2rj",
    "addr:street":"Industrial Estate",
    "iso:country":"GB",
    "sg:address":"Unit 2 Small Heath Industrial Estate",
    "sg:city":"Birmingham",
    "sg:classifiers":[
        {
            "category":"Manufacturing",
            "subcategory":"Tools & Machinery",
            "type":"Manufacturing & Wholesale Goods"
        }
    ],
    "sg:phone":"+44 121 753 0027",
    "sg:postcode":"B11 2RJ",
    "sg:province":"West Midlands",
    "sg:tags":[
        "design",
        "maker"
    ],
    "wof:name":"Hardmetal Form Techs Ltd.",
    "wof:placetype":"venue"
},
  "geometry": {"coordinates":[-1.854938,52.460262],"type":"Point"}
}