{
  "type": "Feature",
  "properties": {
    "addr:full":"Brompton Barracks Chatham Kent ME4 4UG",
    "addr:postcode":"me4 4ug",
    "iso:country":"GB",
    "sg:address":"Brompton Barracks",
    "sg:city":"Chatham",
    "sg:classifiers":[
        {
            "category":"Organizations",
            "subcategory":"Non-profit Organization",
            "type":"Services"
        }
    ],
    "sg:phone":"+44 1634 848030",
    "sg:postcode":"ME4 4UG",
    "sg:province":"Kent",
    "sg:tags":[
        "organisation",
        "voluntary",
        "charity"
    ],
    "wof:name":"Royal Engineers Museum Foundation",
    "wof:placetype":"venue"
},
  "geometry": {"coordinates":[0.52244,51.381889],"type":"Point"}
}