{
  "type": "Feature",
  "properties": {
    "iso:country":"GB",
    "sg:address":"12 Silver St, Durham City",
    "sg:city":"Durham",
    "sg:classifiers":[
        {
            "category":"Communications",
            "subcategory":"Film & Video Production",
            "type":"Services"
        }
    ],
    "sg:phone":"+44 191 384 9300",
    "sg:postcode":"DH1 3RB",
    "sg:province":"Durham",
    "sg:tags":[
        "tv"
    ],
    "wof:name":"Granada Home Technology",
    "wof:placetype":"venue"
},
  "geometry": {"coordinates":[-1.574876,54.777527],"type":"Point"}
}