{
  "type": "Feature",
  "properties": {
    "addr:full":"Oakleigh Road Stratford-upon-avon Warwickshire CV37 0DP",
    "addr:postcode":"cv37 0dp",
    "addr:street":"Oakleigh Road",
    "iso:country":"GB",
    "sg:address":"Oakleigh Road",
    "sg:city":"Stratford-upon-avon",
    "sg:classifiers":[
        {
            "category":"Government",
            "subcategory":"City Hall",
            "type":"Public Place"
        },
        {
            "category":"Shopping",
            "subcategory":"Party Supplies",
            "type":"Retail Goods"
        }
    ],
    "sg:phone":"+44 1789 205897",
    "sg:postcode":"CV37 0DP",
    "sg:province":"Warwickshire",
    "sg:tags":[
        "inflatables",
        "castle",
        "hire",
        "bouncy"
    ],
    "wof:name":"Boing Boing",
    "wof:placetype":"venue"
},
  "geometry": {"coordinates":[-1.715086,52.205891],"type":"Point"}
}