{
  "type": "Feature",
  "properties": {
    "addr:full":"Rannoch Drive, Condorrat, Cumbernauld Glasgow Falkirk G67 4ES",
    "addr:postcode":"g67 4es",
    "addr:street":"Rannoch Drive",
    "iso:country":"GB",
    "sg:address":"Rannoch Drive, Condorrat, Cumbernauld",
    "sg:city":"Glasgow",
    "sg:classifiers":[
        {
            "category":"Health Services",
            "subcategory":"Nursing And Care Facility",
            "type":"Services"
        }
    ],
    "sg:phone":"+44 1236 729273",
    "sg:postcode":"G67 4ES",
    "sg:province":"Falkirk",
    "sg:tags":[
        "home",
        "agency"
    ],
    "wof:name":"S & I Green",
    "wof:placetype":"venue"
},
  "geometry": {"coordinates":[-4.0224947929,55.9324951172],"type":"Point"}
}