{
  "type": "Feature",
  "properties": {
    "addr:full":"17 Commercial Street, Norton Malton North Yorkshire YO17 9HX",
    "addr:housenumber":"17",
    "addr:postcode":"yo17 9hx",
    "addr:street":"Commercial Street",
    "iso:country":"GB",
    "sg:address":"17 Commercial Street, Norton",
    "sg:city":"Malton",
    "sg:classifiers":[
        {
            "category":"Shopping",
            "subcategory":"Pets & Pet Supplies",
            "type":"Retail Goods"
        }
    ],
    "sg:phone":"+44 1653 693304",
    "sg:postcode":"YO17 9HX",
    "sg:province":"North Yorkshire",
    "sg:tags":[
        "shop"
    ],
    "wof:name":"Norton Aquaria",
    "wof:placetype":"venue"
},
  "geometry": {"coordinates":[-0.7866529822,54.1323852539],"type":"Point"}
}