{
  "type": "Feature",
  "properties": {
    "addr:full":"163 Mottram Road Stalybridge Greater Manchester SK15 2QU",
    "addr:housenumber":"163",
    "addr:postcode":"sk15 2qu",
    "addr:street":"Mottram Road",
    "iso:country":"GB",
    "sg:address":"163 Mottram Road",
    "sg:city":"Stalybridge",
    "sg:classifiers":[
        {
            "category":"Personal",
            "type":"Services"
        }
    ],
    "sg:postcode":"SK15 2QU",
    "sg:province":"Greater Manchester",
    "sg:tags":[
        "wedding"
    ],
    "wof:name":"Kingfisher Bridal Cars of Stalybridge",
    "wof:placetype":"venue"
},
  "geometry": {"coordinates":[-2.047181,53.480595],"type":"Point"}
}