{
  "type": "Feature",
  "properties": {
    "addr:full":"19 Lyndhurst Drive New Malden Surrey KT3 5LL",
    "addr:housenumber":"19",
    "addr:postcode":"kt3 5ll",
    "addr:street":"Lyndhurst Drive",
    "iso:country":"GB",
    "sg:address":"19 Lyndhurst Drive",
    "sg:city":"New Malden",
    "sg:classifiers":[
        {
            "category":"Professional",
            "subcategory":"Accounting & Tax Preparation",
            "type":"Services"
        }
    ],
    "sg:phone":"+44 20 8715 4347",
    "sg:postcode":"KT3 5LL",
    "sg:province":"Surrey",
    "sg:tags":[
        "accountant"
    ],
    "wof:name":"Compassist Support Ltd.",
    "wof:placetype":"venue"
},
  "geometry": {"coordinates":[-0.255045,51.388298],"type":"Point"}
}