{
  "type": "Feature",
  "properties": {
    "addr:full":"Discovery Park Stockport Cheshire SK4 5DZ",
    "addr:postcode":"sk4 5dz",
    "addr:street":"Discovery Park",
    "iso:country":"GB",
    "sg:address":"Discovery Park",
    "sg:city":"Stockport",
    "sg:classifiers":[
        {
            "category":"Home & Garden",
            "subcategory":"Hardware",
            "type":"Retail Goods"
        }
    ],
    "sg:phone":"+44 161 432 6161",
    "sg:postcode":"SK4 5DZ",
    "sg:province":"Cheshire",
    "sg:tags":[
        "equipment",
        "bathroom",
        "fitting"
    ],
    "wof:name":"G R Hullcock (1994) Ltd.",
    "wof:placetype":"venue"
},
  "geometry": {"coordinates":[-2.189049,53.434334],"type":"Point"}
}