{
  "type": "Feature",
  "properties": {
    "addr:full":"47 Sewell Street Runcorn Cheshire WA7 5SY",
    "addr:housenumber":"47",
    "addr:postcode":"wa7 5sy",
    "addr:street":"Sewell Street",
    "iso:country":"GB",
    "sg:address":"47 Sewell Street",
    "sg:city":"Runcorn",
    "sg:classifiers":[
        {
            "category":"Retail",
            "subcategory":"Auto Repair",
            "type":"Services"
        }
    ],
    "sg:phone":"+44 1928 578194",
    "sg:postcode":"WA7 5SY",
    "sg:province":"Cheshire",
    "sg:tags":[
        "modification",
        "garage"
    ],
    "wof:name":"Kevin Marley",
    "wof:placetype":"venue"
},
  "geometry": {"coordinates":[-2.72298,53.338371],"type":"Point"}
}