{
  "type": "Feature",
  "properties": {
    "addr:full":"2 Redbourne Dr Lincoln Lincolnshire LN2 2HG",
    "addr:housenumber":"2",
    "addr:postcode":"ln2 2hg",
    "addr:street":"Redbourne Dr",
    "iso:country":"GB",
    "sg:address":"2 Redbourne Dr",
    "sg:city":"Lincoln",
    "sg:classifiers":[
        {
            "category":"Organizations",
            "subcategory":"Membership Organization",
            "type":"Services"
        }
    ],
    "sg:postcode":"LN2 2HG",
    "sg:province":"Lincolnshire",
    "sg:tags":[
        "club"
    ],
    "wof:name":"Crane,Michael,",
    "wof:placetype":"venue"
},
  "geometry": {"coordinates":[-0.5253250003,53.2483253479],"type":"Point"}
}