{
  "type": "Feature",
  "properties": {
    "iso:country":"GB",
    "sg:address":"Barlow House Medical Centre, Hamilton Terr",
    "sg:city":"Milford Haven",
    "sg:classifiers":[
        {
            "category":"Health Services",
            "subcategory":"Doctor",
            "type":"Services"
        }
    ],
    "sg:phone":"+44 1646 690674",
    "sg:postcode":"SA73 3JL",
    "sg:province":"Pembrokeshire",
    "sg:tags":[
        "practitioners"
    ],
    "wof:name":"Roberts, J G",
    "wof:placetype":"venue"
},
  "geometry": {"coordinates":[-5.0270438194,51.7168083191],"type":"Point"}
}