{
  "type": "Feature",
  "properties": {
    "iso:country":"GB",
    "sg:address":"12a Burnham Street",
    "sg:city":"Swansea",
    "sg:classifiers":[
        {
            "category":"Retail",
            "subcategory":"Repair Shop",
            "type":"Services"
        }
    ],
    "sg:phone":"+44 1792 470744",
    "sg:postcode":"SA1 6BW",
    "sg:province":"Neath Port Talbot",
    "sg:tags":[
        "maintenance"
    ],
    "wof:name":"Briter Property Maintenence Contractors",
    "wof:placetype":"venue"
},
  "geometry": {"coordinates":[-3.940929,51.623154],"type":"Point"}
}