{
  "type": "Feature",
  "properties": {
    "addr:full":"4 Beech Gro Warrington Cheshire WA4 1EG",
    "addr:housenumber":"4",
    "addr:postcode":"wa4 1eg",
    "addr:street":"Beech Gro",
    "iso:country":"GB",
    "sg:address":"4 Beech Gro",
    "sg:city":"Warrington",
    "sg:classifiers":[
        {
            "category":"Education",
            "subcategory":"Dance Studio",
            "type":"Public Place"
        }
    ],
    "sg:phone":"+44 1925 419505",
    "sg:postcode":"WA4 1EG",
    "sg:province":"Cheshire",
    "sg:tags":[
        "school",
        "dancing"
    ],
    "wof:name":"Alex Bottle",
    "wof:placetype":"venue"
},
  "geometry": {"coordinates":[-2.5760979652,53.3808708191],"type":"Point"}
}