{
  "type": "Feature",
  "properties": {
    "iso:country":"GB",
    "sg:address":"Unit 3b Meteor Centre, Mansfield Rd",
    "sg:city":"Derby",
    "sg:classifiers":[
        {
            "category":"Autos & Motor Vehicles",
            "subcategory":"Automobile Sales",
            "type":"Retail Goods"
        }
    ],
    "sg:phone":"+44 1332 360603",
    "sg:postcode":"DE21 4SY",
    "sg:province":"Derbyshire",
    "sg:tags":[
        "car"
    ],
    "wof:name":"Daewoo Cars Ltd",
    "wof:placetype":"venue"
},
  "geometry": {"coordinates":[-1.46436,52.942032],"type":"Point"}
}