{
  "type": "Feature",
  "properties": {
    "addr:full":"58 Chapel Ash Wolverhampton Staffordshire WV3 0TT",
    "addr:housenumber":"58",
    "addr:postcode":"wv3 0tt",
    "addr:street":"Chapel Ash",
    "iso:country":"GB",
    "sg:address":"58 Chapel Ash",
    "sg:city":"Wolverhampton",
    "sg:classifiers":[
        {
            "category":"Fast Food",
            "type":"Food & Drink"
        }
    ],
    "sg:phone":"+44 1902 423330",
    "sg:postcode":"WV3 0TT",
    "sg:province":"Staffordshire",
    "sg:tags":[
        "away",
        "take"
    ],
    "wof:name":"Turkish Delight Kebabs & Burger House",
    "wof:placetype":"venue"
},
  "geometry": {"coordinates":[-2.138715,52.585289],"type":"Point"}
}