{
  "type": "Feature",
  "properties": {
    "addr:full":"130 High Street, Irchester Wellingborough Bedfordshire NN29 7AB",
    "addr:housenumber":"130",
    "addr:postcode":"nn29 7ab",
    "addr:street":"High Street",
    "iso:country":"GB",
    "sg:address":"130 High Street, Irchester",
    "sg:city":"Wellingborough",
    "sg:classifiers":[
        {
            "category":"Communications",
            "subcategory":"Film & Video Production",
            "type":"Services"
        }
    ],
    "sg:postcode":"NN29 7AB",
    "sg:province":"Bedfordshire",
    "sg:tags":[
        "hot",
        "stamping",
        "foil"
    ],
    "wof:name":"Addamark",
    "wof:placetype":"venue"
},
  "geometry": {"coordinates":[-0.643278,52.285927],"type":"Point"}
}