{
  "type": "Feature",
  "properties": {
    "addr:full":"Arena House, Green Acres Road Oldham Lancashire OL4 1HA",
    "addr:postcode":"ol4 1ha",
    "addr:street":"Green Acres Road",
    "iso:country":"GB",
    "sg:address":"Arena House, Green Acres Road",
    "sg:city":"Oldham",
    "sg:classifiers":[
        {
            "category":"Shopping",
            "subcategory":"Clothing, Apparel, & Fashions",
            "type":"Retail Goods"
        },
        {
            "category":"Wholesale",
            "subcategory":"Apparel",
            "type":"Manufacturing & Wholesale Goods"
        }
    ],
    "sg:phone":"+44 161 628 2339",
    "sg:postcode":"OL4 1HA",
    "sg:province":"Lancashire",
    "sg:tags":[
        "supplier",
        "lingerie",
        "clothing"
    ],
    "wof:name":"New Star Fashions Ltd",
    "wof:placetype":"venue"
},
  "geometry": {"coordinates":[-2.0928740501,53.5443000793],"type":"Point"}
}