{
  "type": "Feature",
  "properties": {
    "iso:country":"GB",
    "sg:address":"Aldermanbury Sq",
    "sg:city":"Moorgate",
    "sg:classifiers":[
        {
            "category":"Professional",
            "subcategory":"Business Services",
            "type":"Services"
        }
    ],
    "sg:phone":"+44 20 7600 3366",
    "sg:postcode":"EC2V 7HR",
    "sg:province":"Greater London",
    "sg:tags":[
        "broker",
        "commodity"
    ],
    "wof:name":"RST Resources Ltd",
    "wof:placetype":"venue"
},
  "geometry": {"coordinates":[-0.092384,51.516987],"type":"Point"}
}