{
  "type": "Feature",
  "properties": {
    "iso:country":"GB",
    "sg:address":"11 Yarrow Ct",
    "sg:city":"Gillingham",
    "sg:classifiers":[
        {
            "category":"Building & Trades",
            "subcategory":"Plumbing",
            "type":"Services"
        }
    ],
    "sg:phone":"+44 1747 826444",
    "sg:postcode":"SP8 4XD",
    "sg:province":"Dorset",
    "sg:tags":[
        "heating"
    ],
    "wof:name":"M E N Bowden",
    "wof:placetype":"venue"
},
  "geometry": {"coordinates":[-2.291139,51.04055],"type":"Point"}
}