{
  "type": "Feature",
  "properties": {
    "iso:country":"GB",
    "sg:address":"38 Main Rd, Twycross",
    "sg:city":"Atherstone",
    "sg:classifiers":[
        {
            "category":"Building & Trades",
            "subcategory":"Cleaning & Sanitation",
            "type":"Services"
        },
        {
            "category":"Manufacturing",
            "subcategory":"Petroleum Products",
            "type":"Manufacturing & Wholesale Goods"
        }
    ],
    "sg:phone":"+44 1827 881120",
    "sg:postcode":"CV9 3PL",
    "sg:province":"Leicestershire",
    "sg:tags":[
        "double",
        "window",
        "glazing"
    ],
    "wof:name":"Lab Cote Windows",
    "wof:placetype":"venue"
},
  "geometry": {"coordinates":[-1.518903,52.609596],"type":"Point"}
}