{
  "type": "Feature",
  "properties": {
    "iso:country":"GB",
    "sg:address":"490a Kings Road",
    "sg:city":"London",
    "sg:classifiers":[
        {
            "category":"Shopping",
            "subcategory":"Antiques",
            "type":"Retail Goods"
        }
    ],
    "sg:postcode":"SW10 0LF",
    "sg:province":"Greater London",
    "wof:name":"End of the World Antiques",
    "wof:placetype":"venue"
},
  "geometry": {"coordinates":[-0.1801649928,51.4820823669],"type":"Point"}
}