{
  "type": "Feature",
  "properties": {
    "addr:full":"Highfield Rd Pontefract West Yorkshire WF9 4DP",
    "addr:postcode":"wf9 4dp",
    "addr:street":"Highfield Rd",
    "iso:country":"GB",
    "sg:address":"Highfield Rd",
    "sg:city":"Pontefract",
    "sg:classifiers":[
        {
            "category":"Health Services",
            "subcategory":"Clinic",
            "type":"Services"
        }
    ],
    "sg:phone":"+44 1977 610009",
    "sg:postcode":"WF9 4DP",
    "sg:province":"West Yorkshire",
    "sg:tags":[
        "nh"
    ],
    "wof:name":"Grange Medical Centre",
    "wof:placetype":"venue"
},
  "geometry": {"coordinates":[-1.354128,53.611809],"type":"Point"}
}