{
  "type": "Feature",
  "properties": {
    "addr:full":"Salix, Woodside Close Gerrards Cross Buckinghamshire SL9 9TA",
    "addr:postcode":"sl9 9ta",
    "addr:street":"Woodside Close",
    "iso:country":"GB",
    "sg:address":"Salix, Woodside Close",
    "sg:city":"Gerrards Cross",
    "sg:classifiers":[
        {
            "category":"Professional",
            "subcategory":"Advertising",
            "type":"Services"
        }
    ],
    "sg:postcode":"SL9 9TA",
    "sg:province":"Buckinghamshire",
    "sg:tags":[
        "mail",
        "direct"
    ],
    "wof:name":"D & P Mead",
    "wof:placetype":"venue"
},
  "geometry": {"coordinates":[-0.553269,51.603527],"type":"Point"}
}