{
  "type": "Feature",
  "properties": {
    "addr:full":"118 Union St Oldham Lancashire OL1 1DU",
    "addr:housenumber":"118",
    "addr:postcode":"ol1 1du",
    "addr:street":"Union St",
    "iso:country":"GB",
    "sg:address":"118 Union St",
    "sg:city":"Oldham",
    "sg:classifiers":[
        {
            "category":"Restaurant",
            "type":"Food & Drink"
        }
    ],
    "sg:phone":"+44 161 627 0689",
    "sg:postcode":"OL1 1DU",
    "sg:province":"Lancashire",
    "sg:tags":[
        "indian"
    ],
    "wof:name":"Cabana Tandoori Restaurant",
    "wof:placetype":"venue"
},
  "geometry": {"coordinates":[-2.1071650982,53.5411567688],"type":"Point"}
}