{
  "type": "Feature",
  "properties": {
    "iso:country":"GB",
    "sg:address":"180 Trealaw Rd",
    "sg:city":"Tonypandy",
    "sg:classifiers":[
        {
            "category":"Food & Beverages",
            "subcategory":"Fruits & Vegetables",
            "type":"Retail Goods"
        }
    ],
    "sg:postcode":"CF40 2NT",
    "sg:province":"Rhondda, Cynon, Taff",
    "sg:tags":[
        "greengrocer"
    ],
    "wof:name":"Roach,Sian,",
    "wof:placetype":"venue"
},
  "geometry": {"coordinates":[-3.452495,51.624069],"type":"Point"}
}