{
  "type": "Feature",
  "properties": {
    "addr:full":"191 Wokingham Road Reading Berkshire RG6 1LT",
    "addr:housenumber":"191",
    "addr:postcode":"rg6 1lt",
    "addr:street":"Wokingham Road",
    "iso:country":"GB",
    "sg:address":"191 Wokingham Road",
    "sg:city":"Reading",
    "sg:classifiers":[
        {
            "category":"Bars & Pubs",
            "type":"Food & Drink"
        }
    ],
    "sg:phone":"+44 118 926 2170",
    "sg:postcode":"RG6 1LT",
    "sg:province":"Berkshire",
    "sg:tags":[
        "pubs",
        "inn"
    ],
    "wof:name":"The Three Tuns",
    "wof:placetype":"venue"
},
  "geometry": {"coordinates":[-0.931406,51.442574],"type":"Point"}
}