{
  "type": "Feature",
  "properties": {
    "addr:full":"22 The Scotch Hill, Keresley Coventry Warwickshire CV6 3ES",
    "addr:housenumber":"22",
    "addr:postcode":"cv6 3es",
    "addr:street":"The Scotch Hill",
    "iso:country":"GB",
    "sg:address":"22 The Scotch Hill, Keresley",
    "sg:city":"Coventry",
    "sg:classifiers":[
        {
            "category":"Real Estate",
            "subcategory":"Surveying",
            "type":"Services"
        }
    ],
    "sg:phone":"+44 24 7669 1789",
    "sg:postcode":"CV6 3ES",
    "sg:province":"Warwickshire",
    "sg:tags":[
        "building",
        "surveyor"
    ],
    "wof:name":"N Higgins",
    "wof:placetype":"venue"
},
  "geometry": {"coordinates":[-1.5172400475,52.4301490784],"type":"Point"}
}