{
  "type": "Feature",
  "properties": {
    "iso:country":"GB",
    "sg:address":"63 Goodmayes Road",
    "sg:city":"Ilford",
    "sg:classifiers":[
        {
            "category":"Food & Beverages",
            "subcategory":"Meat & Fish",
            "type":"Retail Goods"
        },
        {
            "category":"Food & Beverages",
            "subcategory":"Groceries & Convenience Stores",
            "type":"Retail Goods"
        }
    ],
    "sg:phone":"+44 20 8590 1800",
    "sg:postcode":"IG3 9UB",
    "sg:province":"Essex",
    "sg:tags":[
        "shop",
        "chip"
    ],
    "wof:name":"Patricia Goodgain",
    "wof:placetype":"venue"
},
  "geometry": {"coordinates":[0.110298,51.563225],"type":"Point"}
}