{
  "type": "Feature",
  "properties": {
    "addr:full":"214 Hangleton Road Hove East Sussex BN3 7LP",
    "addr:housenumber":"214",
    "addr:postcode":"bn3 7lp",
    "addr:street":"Hangleton Road",
    "iso:country":"GB",
    "sg:address":"214 Hangleton Road",
    "sg:city":"Hove",
    "sg:classifiers":[
        {
            "category":"Shopping",
            "subcategory":"News",
            "type":"Retail Goods"
        }
    ],
    "sg:phone":"+44 1273 325605",
    "sg:postcode":"BN3 7LP",
    "sg:province":"East Sussex",
    "sg:tags":[
        "newsagent"
    ],
    "wof:name":"Warr Newsagents",
    "wof:placetype":"venue"
},
  "geometry": {"coordinates":[-0.191622,50.845627],"type":"Point"}
}