{
  "type": "Feature",
  "properties": {
    "addr:full":"59 Booker Avenue Liverpool Merseyside L18 4QZ",
    "addr:housenumber":"59",
    "addr:postcode":"l18 4qz",
    "addr:street":"Booker Avenue",
    "iso:country":"GB",
    "sg:address":"59 Booker Avenue",
    "sg:city":"Liverpool",
    "sg:classifiers":[
        {
            "category":"Personal",
            "subcategory":"Beauty Salon",
            "type":"Services"
        }
    ],
    "sg:phone":"+44 151 724 3838",
    "sg:postcode":"L18 4QZ",
    "sg:province":"Merseyside",
    "sg:tags":[
        "unisex",
        "hairdresser"
    ],
    "wof:name":"Kathryn Hamill Hair & Beauty",
    "wof:placetype":"venue"
},
  "geometry": {"coordinates":[-2.9088869095,53.3696784973],"type":"Point"}
}