{
  "type": "Feature",
  "properties": {
    "addr:full":"Norden Farm, Corfe Castle Wareham Dorset BH20 5DS",
    "addr:postcode":"bh20 5ds",
    "addr:street":"Norden",
    "iso:country":"GB",
    "sg:address":"Norden Farm, Corfe Castle",
    "sg:city":"Wareham",
    "sg:classifiers":[
        {
            "category":"Recreation",
            "subcategory":"Campground",
            "type":"Entertainment"
        }
    ],
    "sg:phone":"+44 1929 480348",
    "sg:postcode":"BH20 5DS",
    "sg:province":"Dorset",
    "sg:tags":[
        "operator",
        "site",
        "camping"
    ],
    "wof:name":"M S Ramm & Son",
    "wof:placetype":"venue"
},
  "geometry": {"coordinates":[-2.0535941124,50.6338386536],"type":"Point"}
}