{
  "type": "Feature",
  "properties": {
    "addr:full":"Ton Y Bwlch, Blaengwynlais Caerphilly Caerphilly CF83 1NG",
    "addr:postcode":"cf83 1ng",
    "iso:country":"GB",
    "sg:address":"Ton Y Bwlch, Blaengwynlais",
    "sg:city":"Caerphilly",
    "sg:classifiers":[
        {
            "category":"Organizations",
            "subcategory":"Community Association",
            "type":"Services"
        }
    ],
    "sg:phone":"+44 29 2088 1419",
    "sg:postcode":"CF83 1NG",
    "sg:province":"Caerphilly",
    "sg:tags":[
        "relation",
        "public"
    ],
    "wof:name":"Stevanna PR",
    "wof:placetype":"venue"
},
  "geometry": {"coordinates":[-3.217728,51.576588],"type":"Point"}
}