{
  "type": "Feature",
  "properties": {
    "addr:full":"Skew Bridge, Bittaford Ivybridge Devon PL21 0ES",
    "addr:postcode":"pl21 0es",
    "addr:street":"Skew",
    "iso:country":"GB",
    "sg:address":"Skew Bridge, Bittaford",
    "sg:city":"Ivybridge",
    "sg:classifiers":[
        {
            "category":"Manufacturing",
            "subcategory":"Building Materials",
            "type":"Manufacturing & Wholesale Goods"
        }
    ],
    "sg:phone":"+44 1752 691105",
    "sg:postcode":"PL21 0ES",
    "sg:province":"Devon",
    "sg:tags":[
        "merchant",
        "builder"
    ],
    "wof:name":"Steptoe's Reclamation Yard of Ivybridge",
    "wof:placetype":"venue"
},
  "geometry": {"coordinates":[-3.877413,50.397327],"type":"Point"}
}