{
  "type": "Feature",
  "properties": {
    "iso:country":"GB",
    "sg:address":"145 Buccleuch Street",
    "sg:city":"Edinburgh",
    "sg:classifiers":[
        {
            "category":"Professional",
            "subcategory":"Computer Services",
            "type":"Services"
        }
    ],
    "sg:phone":"+44 131 662 0630",
    "sg:postcode":"EH8 9NE",
    "sg:province":"City of Edinburgh",
    "sg:tags":[
        "system",
        "software"
    ],
    "wof:name":"Management Solutions",
    "wof:placetype":"venue"
},
  "geometry": {"coordinates":[-3.1831810474,55.9415016174],"type":"Point"}
}