{
  "type": "Feature",
  "properties": {
    "iso:country":"GB",
    "sg:address":"St Georges Road",
    "sg:city":"Lytham St Annes",
    "sg:classifiers":[
        {
            "category":"Cafe",
            "type":"Food & Drink"
        }
    ],
    "sg:phone":"+44 1253 713545",
    "sg:postcode":"FY8 2AE",
    "sg:province":"Lancashire",
    "sg:tags":[
        "tea",
        "snack",
        "bar",
        "room"
    ],
    "wof:name":"Ashton Gardens Cafeteria",
    "wof:placetype":"venue"
},
  "geometry": {"coordinates":[-3.031129,53.752853],"type":"Point"}
}