{
  "type": "Feature",
  "properties": {
    "addr:full":"40 Gorway Road Walsall West Midlands WS1 3BG",
    "addr:housenumber":"40",
    "addr:postcode":"ws1 3bg",
    "addr:street":"Gorway Road",
    "iso:country":"GB",
    "sg:address":"40 Gorway Road",
    "sg:city":"Walsall",
    "sg:classifiers":[
        {
            "category":"Social Services",
            "subcategory":"Retirement Home",
            "type":"Services"
        }
    ],
    "sg:phone":"+44 1922 615515",
    "sg:postcode":"WS1 3BG",
    "sg:province":"West Midlands",
    "sg:tags":[
        "rest"
    ],
    "wof:name":"Gorway House",
    "wof:placetype":"venue"
},
  "geometry": {"coordinates":[-1.973358,52.574711],"type":"Point"}
}