{
  "type": "Feature",
  "properties": {
    "addr:full":"31 Commercial Road, Paddock Wood Tonbridge Kent TN12 6EN",
    "addr:housenumber":"31",
    "addr:postcode":"tn12 6en",
    "addr:street":"Commercial Road Paddock",
    "iso:country":"GB",
    "sg:address":"31 Commercial Road, Paddock Wood",
    "sg:city":"Tonbridge",
    "sg:classifiers":[
        {
            "category":"Retail",
            "subcategory":"Laundry & Dry Cleaning",
            "type":"Services"
        }
    ],
    "sg:postcode":"TN12 6EN",
    "sg:province":"Kent",
    "sg:tags":[
        "alteration"
    ],
    "wof:name":"Elite Cleaners",
    "wof:placetype":"venue"
},
  "geometry": {"coordinates":[0.388877,51.180874],"type":"Point"}
}