{
  "type": "Feature",
  "properties": {
    "addr:full":"10 Waterworks Rd Winchester Hampshire SO21 2DP",
    "addr:housenumber":"10",
    "addr:postcode":"so21 2dp",
    "addr:street":"Waterworks Rd",
    "iso:country":"GB",
    "sg:address":"10 Waterworks Rd",
    "sg:city":"Winchester",
    "sg:classifiers":[
        {
            "category":"Shopping",
            "subcategory":"Musical Instruments",
            "type":"Retail Goods"
        }
    ],
    "sg:phone":"+44 1962 714582",
    "sg:postcode":"SO21 2DP",
    "sg:province":"Hampshire",
    "wof:name":"Matthew Fisk",
    "wof:placetype":"venue"
},
  "geometry": {"coordinates":[-1.3379759789,51.0111541748],"type":"Point"}
}