{
  "type": "Feature",
  "properties": {
    "addr:full":"3 Riverford Clo, Woolwell Plymouth Devon PL6 7QG",
    "addr:housenumber":"3",
    "addr:postcode":"pl6 7qg",
    "addr:street":"Riverford Clo Woolwell",
    "iso:country":"GB",
    "sg:address":"3 Riverford Clo, Woolwell",
    "sg:city":"Plymouth",
    "sg:classifiers":[
        {
            "category":"Food & Beverages",
            "subcategory":"Bakery",
            "type":"Retail Goods"
        }
    ],
    "sg:postcode":"PL6 7QG",
    "sg:province":"Devon",
    "sg:tags":[
        "confectionery"
    ],
    "wof:name":"West Country Popcorn",
    "wof:placetype":"venue"
},
  "geometry": {"coordinates":[-4.1057419777,50.4330482483],"type":"Point"}
}