{
  "type": "Feature",
  "properties": {
    "addr:full":"12 Dowanhill Road London Greater London SE6 1HJ",
    "addr:housenumber":"12",
    "addr:postcode":"se6 1hj",
    "addr:street":"Dowanhill Road",
    "iso:country":"GB",
    "sg:address":"12 Dowanhill Road",
    "sg:city":"London",
    "sg:classifiers":[
        {
            "category":"Travel",
            "subcategory":"Hotels & Motels",
            "type":"Entertainment"
        }
    ],
    "sg:postcode":"SE6 1HJ",
    "sg:province":"Greater London",
    "sg:tags":[
        "house",
        "guest"
    ],
    "wof:name":"Highfield House",
    "wof:placetype":"venue"
},
  "geometry": {"coordinates":[0.004353,51.44054],"type":"Point"}
}