{
  "type": "Feature",
  "properties": {
    "addr:full":"Harby Road, Langar North Trading Estate Nottingham Leicestershire NG13 9HY",
    "addr:postcode":"ng13 9hy",
    "addr:street":"Harby Road;North Trading Estate",
    "iso:country":"GB",
    "sg:address":"Harby Road, Langar North Trading Estate",
    "sg:city":"Nottingham",
    "sg:classifiers":[
        {
            "category":"Autos & Motor Vehicles",
            "subcategory":"Auto Supplies",
            "type":"Retail Goods"
        }
    ],
    "sg:phone":"+44 1949 860786",
    "sg:postcode":"NG13 9HY",
    "sg:province":"Leicestershire",
    "sg:tags":[
        "towing",
        "eqpt",
        "trailer"
    ],
    "wof:name":"R T S Trailer Master",
    "wof:placetype":"venue"
},
  "geometry": {"coordinates":[-0.919797,52.901695],"type":"Point"}
}