{
  "type": "Feature",
  "properties": {
    "addr:full":"3 Topcliffe Road Thirsk North Yorkshire YO7 1RQ",
    "addr:housenumber":"3",
    "addr:postcode":"yo7 1rq",
    "addr:street":"Topcliffe Road",
    "iso:country":"GB",
    "sg:address":"3 Topcliffe Road",
    "sg:city":"Thirsk",
    "sg:classifiers":[
        {
            "category":"Personal",
            "subcategory":"Beauty Salon",
            "type":"Services"
        }
    ],
    "sg:phone":"+44 1845 522163",
    "sg:postcode":"YO7 1RQ",
    "sg:province":"North Yorkshire",
    "sg:tags":[
        "unisex",
        "hairdresser"
    ],
    "wof:name":"Fringe Benefits",
    "wof:placetype":"venue"
},
  "geometry": {"coordinates":[-1.350334,54.221478],"type":"Point"}
}