{
  "type": "Feature",
  "properties": {
    "addr:full":"279-281 Kenton Lane Harrow Greater London HA3 8RR",
    "addr:housenumber":"279-281",
    "addr:postcode":"ha3 8rr",
    "addr:street":"Kenton Lane",
    "iso:country":"GB",
    "sg:address":"279-281 Kenton Lane",
    "sg:city":"Harrow",
    "sg:classifiers":[
        {
            "category":"Shopping",
            "subcategory":"Bicycles & Sporting Goods",
            "type":"Retail Goods"
        }
    ],
    "sg:phone":"+44 20 8907 5676",
    "sg:postcode":"HA3 8RR",
    "sg:province":"Greater London",
    "sg:tags":[
        "cycle",
        "accessory"
    ],
    "wof:name":"Bicycles Cash & Carry",
    "wof:placetype":"venue"
},
  "geometry": {"coordinates":[-0.313383,51.597202],"type":"Point"}
}