{
  "type": "Feature",
  "properties": {
    "addr:full":"Sovereign House, South Parade Leeds West Yorkshire LS1 5QX",
    "addr:postcode":"ls1 5qx",
    "addr:street":"South Parade",
    "iso:country":"GB",
    "sg:address":"Sovereign House, South Parade",
    "sg:city":"Leeds",
    "sg:classifiers":[
        {
            "category":"Bars & Pubs",
            "type":"Food & Drink"
        }
    ],
    "sg:phone":"+44 113 204 8581",
    "sg:postcode":"LS1 5QX",
    "sg:province":"West Yorkshire",
    "sg:tags":[
        "pubs",
        "inn"
    ],
    "wof:name":"O'Neill's Irish Bar",
    "wof:placetype":"venue"
},
  "geometry": {"coordinates":[-1.548064,53.799061],"type":"Point"}
}