{
  "type": "Feature",
  "properties": {
    "iso:country":"GB",
    "sg:address":"London Road",
    "sg:city":"Beccles",
    "sg:classifiers":[
        {
            "category":"Bars & Pubs",
            "type":"Food & Drink"
        },
        {
            "category":"Community Center",
            "subcategory":"Social",
            "type":"Public Place"
        }
    ],
    "sg:phone":"+44 1502 712243",
    "sg:postcode":"NR34 9YT",
    "sg:province":"Norfolk",
    "sg:tags":[
        "pubs",
        "house",
        "inn",
        "activity"
    ],
    "sg:website":"http://www.mypub.org.uk",
    "wof:name":"The Butchers Arms",
    "wof:placetype":"venue"
},
  "geometry": {"coordinates":[1.56389,52.455166],"type":"Point"}
}