{
  "type": "Feature",
  "properties": {
    "addr:full":"Ty Goch Farm, Llansor Newport Monmouthshire NP18 1LS",
    "addr:postcode":"np18 1ls",
    "addr:street":"Ty",
    "iso:country":"GB",
    "sg:address":"Ty Goch Farm, Llansor",
    "sg:city":"Newport",
    "sg:classifiers":[
        {
            "category":"Farming",
            "subcategory":"Livestock Farm",
            "type":"Manufacturing & Wholesale Goods"
        }
    ],
    "sg:phone":"+44 1633 450271",
    "sg:postcode":"NP18 1LS",
    "sg:province":"Monmouthshire",
    "sg:tags":[
        "others"
    ],
    "wof:name":"D M Tucker & Sons",
    "wof:placetype":"venue"
},
  "geometry": {"coordinates":[-2.9403400421,51.6487388611],"type":"Point"}
}