{
  "type": "Feature",
  "properties": {
    "iso:country":"GB",
    "sg:address":"Garn Service Station, Bailey St",
    "sg:city":"Pontypool",
    "sg:classifiers":[
        {
            "category":"Home & Garden",
            "subcategory":"Kitchen Supply",
            "type":"Retail Goods"
        }
    ],
    "sg:phone":"+44 1495 773229",
    "sg:postcode":"NP4 7QL",
    "sg:province":"Monmouthshire",
    "sg:tags":[
        "equipment",
        "catering"
    ],
    "wof:name":"Blackburn J J & Co",
    "wof:placetype":"venue"
},
  "geometry": {"coordinates":[-3.04319,51.703087],"type":"Point"}
}