{
  "type": "Feature",
  "properties": {
    "addr:full":"Bute St, Treherbert Treorchy Rhondda, Cynon, Taff CF42 5NR",
    "addr:postcode":"cf42 5nr",
    "addr:street":"Bute St;Cynon Taff",
    "iso:country":"GB",
    "sg:address":"Bute St, Treherbert",
    "sg:city":"Treorchy",
    "sg:classifiers":[
        {
            "category":"Food & Beverages",
            "subcategory":"Supermarket",
            "type":"Retail Goods"
        }
    ],
    "sg:phone":"+44 1443 772671",
    "sg:postcode":"CF42 5NR",
    "sg:province":"Rhondda, Cynon, Taff",
    "wof:name":"W.G Pritchard & Son",
    "wof:placetype":"venue"
},
  "geometry": {"coordinates":[-3.535374,51.674244],"type":"Point"}
}