{
  "type": "Feature",
  "properties": {
    "addr:full":"34 Bathford Hill Bath Bath and North East Somerset BA1 7SL",
    "addr:housenumber":"34",
    "addr:postcode":"ba1 7sl",
    "addr:street":"Bathford Hill",
    "iso:country":"GB",
    "sg:address":"34 Bathford Hill",
    "sg:city":"Bath",
    "sg:classifiers":[
        {
            "category":"Farming",
            "subcategory":"Dairy Farm",
            "type":"Manufacturing & Wholesale Goods"
        }
    ],
    "sg:postcode":"BA1 7SL",
    "sg:province":"Bath and North East Somerset",
    "wof:name":"L W Gage & Sons",
    "wof:placetype":"venue"
},
  "geometry": {"coordinates":[-2.303858,51.400936],"type":"Point"}
}