{
  "type": "Feature",
  "properties": {
    "addr:full":"23 St Mary St Chepstow Gloucestershire NP6 5EU",
    "addr:housenumber":"23",
    "addr:postcode":"np6 5eu",
    "addr:street":"St Mary St",
    "iso:country":"GB",
    "sg:address":"23 St Mary St",
    "sg:city":"Chepstow",
    "sg:classifiers":[
        {
            "category":"Home & Garden",
            "subcategory":"Garden Supply",
            "type":"Retail Goods"
        }
    ],
    "sg:phone":"+44 1291 622299",
    "sg:postcode":"NP6 5EU",
    "sg:province":"Gloucestershire",
    "sg:tags":[
        "nursery",
        "centre"
    ],
    "wof:name":"June's Garden & Seed Centre",
    "wof:placetype":"venue"
},
  "geometry": {"coordinates":[-2.6745181084,51.6423301697],"type":"Point"}
}