{
  "type": "Feature",
  "properties": {
    "addr:full":"12 Mayfair Drive, Aspull Wigan Lancashire WN2 2ST",
    "addr:housenumber":"12",
    "addr:postcode":"wn2 2st",
    "addr:street":"Mayfair Drive",
    "iso:country":"GB",
    "sg:address":"12 Mayfair Drive, Aspull",
    "sg:city":"Wigan",
    "sg:classifiers":[
        {
            "category":"Building & Trades",
            "subcategory":"Construction",
            "type":"Services"
        }
    ],
    "sg:postcode":"WN2 2ST",
    "sg:province":"Lancashire",
    "sg:tags":[
        "builder"
    ],
    "wof:name":"Alexander Livingston Peach",
    "wof:placetype":"venue"
},
  "geometry": {"coordinates":[-2.577221,53.554192],"type":"Point"}
}