{
  "type": "Feature",
  "properties": {
    "addr:full":"189 Well Street London Greater London E9 6QU",
    "addr:housenumber":"189",
    "addr:postcode":"e9 6qu",
    "addr:street":"Well Street",
    "iso:country":"GB",
    "sg:address":"189 Well Street",
    "sg:city":"London",
    "sg:classifiers":[
        {
            "category":"Organizations",
            "subcategory":"Non-profit Organization",
            "type":"Services"
        }
    ],
    "sg:phone":"+44 20 8533 6922",
    "sg:postcode":"E9 6QU",
    "sg:province":"Greater London",
    "sg:tags":[
        "organisation",
        "voluntary",
        "charity"
    ],
    "wof:name":"Mother & Baby Clinic",
    "wof:placetype":"venue"
},
  "geometry": {"coordinates":[-0.0482060015,51.5431671143],"type":"Point"}
}