{
  "type": "Feature",
  "properties": {
    "addr:full":"38 Hill Street Corbridge Northumberland NE45 5AA",
    "addr:housenumber":"38",
    "addr:postcode":"ne45 5aa",
    "addr:street":"Hill Street;Northumberland",
    "iso:country":"GB",
    "sg:address":"38 Hill Street",
    "sg:city":"Corbridge",
    "sg:classifiers":[
        {
            "category":"Health Services",
            "subcategory":"Dentist",
            "type":"Services"
        }
    ],
    "sg:phone":"+44 1434 632810",
    "sg:postcode":"NE45 5AA",
    "sg:province":"Northumberland",
    "wof:name":"Beech Cottage Surgery",
    "wof:placetype":"venue"
},
  "geometry": {"coordinates":[-2.0196580887,54.9749565125],"type":"Point"}
}