{
  "type": "Feature",
  "properties": {
    "iso:country":"GB",
    "sg:address":"Lochavullin Industrial Estate, Lochavullin Drive",
    "sg:city":"Oban",
    "sg:classifiers":[
        {
            "category":"Shopping",
            "subcategory":"Catalog Store",
            "type":"Retail Goods"
        }
    ],
    "sg:phone":"+44 1631 570912",
    "sg:postcode":"PA34 4BW",
    "sg:province":"Argyll and Bute",
    "sg:tags":[
        "catalogue",
        "showroom"
    ],
    "wof:name":"Argos Ltd.",
    "wof:placetype":"venue"
},
  "geometry": {"coordinates":[-5.469119,56.407982],"type":"Point"}
}