{
  "type": "Feature",
  "properties": {
    "iso:country":"GB",
    "sg:address":"88-94 Wentworth Street",
    "sg:city":"London",
    "sg:classifiers":[
        {
            "category":"Social Services",
            "type":"Services"
        }
    ],
    "sg:phone":"+44 20 7247 8776",
    "sg:postcode":"E1 7SA",
    "sg:province":"Greater London",
    "sg:tags":[
        "need",
        "disability",
        "special"
    ],
    "wof:name":"Disability Alliance Educational & Research Association Ltd.",
    "wof:placetype":"venue"
},
  "geometry": {"coordinates":[-0.071232,51.517075],"type":"Point"}
}