{
  "type": "Feature",
  "properties": {
    "addr:full":"59 Abbeville Road London Greater London SW4 9JW",
    "addr:housenumber":"59",
    "addr:postcode":"sw4 9jw",
    "addr:street":"Abbeville Road",
    "iso:country":"GB",
    "sg:address":"59 Abbeville Road",
    "sg:city":"London",
    "sg:classifiers":[
        {
            "category":"Food & Beverages",
            "subcategory":"Supermarket",
            "type":"Retail Goods"
        }
    ],
    "sg:phone":"+44 20 8673 1826",
    "sg:postcode":"SW4 9JW",
    "sg:province":"Greater London",
    "wof:name":"Mace Food Store",
    "wof:placetype":"venue"
},
  "geometry": {"coordinates":[-0.139768,51.454758],"type":"Point"}
}