{
  "type": "Feature",
  "properties": {
    "addr:full":"2 Church Street Brighouse West Yorkshire HD6 3NF",
    "addr:housenumber":"2",
    "addr:postcode":"hd6 3nf",
    "addr:street":"Church Street",
    "iso:country":"GB",
    "sg:address":"2 Church Street",
    "sg:city":"Brighouse",
    "sg:classifiers":[
        {
            "category":"Cinema",
            "subcategory":"Movie Rental",
            "type":"Entertainment"
        }
    ],
    "sg:phone":"+44 1484 722591",
    "sg:postcode":"HD6 3NF",
    "sg:province":"West Yorkshire",
    "sg:tags":[
        "video",
        "library"
    ],
    "wof:name":"Ace Videos",
    "wof:placetype":"venue"
},
  "geometry": {"coordinates":[-1.791128993,53.6911773682],"type":"Point"}
}