{
  "type": "Feature",
  "properties": {
    "addr:full":"Anerley Court, Half Moon Lane, Hildenborough Tonbridge Kent TN11 9HU",
    "addr:postcode":"tn11 9hu",
    "addr:street":"Anerley Court Half Moon Lane",
    "iso:country":"GB",
    "sg:address":"Anerley Court, Half Moon Lane, Hildenborough",
    "sg:city":"Tonbridge",
    "sg:classifiers":[
        {
            "category":"Building & Trades",
            "subcategory":"Construction",
            "type":"Services"
        }
    ],
    "sg:phone":"+44 1732 838608",
    "sg:postcode":"TN11 9HU",
    "sg:province":"Kent",
    "sg:tags":[
        "builder"
    ],
    "wof:name":"C R Richardson (Contractors) Ltd.",
    "wof:placetype":"venue"
},
  "geometry": {"coordinates":[0.24739,51.214031],"type":"Point"}
}