{
  "type": "Feature",
  "properties": {
    "addr:full":"58 Rede Wood Road, Barming Maidstone Kent ME16 9HR",
    "addr:housenumber":"58",
    "addr:postcode":"me16 9hr",
    "addr:street":"Rede Wood Road",
    "iso:country":"GB",
    "sg:address":"58 Rede Wood Road, Barming",
    "sg:city":"Maidstone",
    "sg:classifiers":[
        {
            "category":"Building & Trades",
            "subcategory":"Plumbing",
            "type":"Services"
        }
    ],
    "sg:phone":"+44 1622 728485",
    "sg:postcode":"ME16 9HR",
    "sg:province":"Kent",
    "sg:tags":[
        "heating"
    ],
    "wof:name":"H W Gilliver",
    "wof:placetype":"venue"
},
  "geometry": {"coordinates":[0.471822,51.270584],"type":"Point"}
}