{
  "type": "Feature",
  "properties": {
    "addr:full":"7 Old Court Hall, Godmanchester Huntingdon Cambridgeshire PE29 2HS",
    "addr:housenumber":"7",
    "addr:postcode":"pe29 2hs",
    "addr:street":"Old Court",
    "iso:country":"GB",
    "sg:address":"7 Old Court Hall, Godmanchester",
    "sg:city":"Huntingdon",
    "sg:classifiers":[
        {
            "category":"Shopping",
            "subcategory":"Bicycles & Sporting Goods",
            "type":"Retail Goods"
        },
        {
            "category":"Recreation",
            "subcategory":"Fishing",
            "type":"Entertainment"
        }
    ],
    "sg:phone":"+44 1480 453303",
    "sg:postcode":"PE29 2HS",
    "sg:province":"Cambridgeshire",
    "sg:tags":[
        "equipment",
        "angling"
    ],
    "wof:name":"Stanjay Fishing Tackle & Trophies",
    "wof:placetype":"venue"
},
  "geometry": {"coordinates":[-0.169954,52.318825],"type":"Point"}
}