{
  "type": "Feature",
  "properties": {
    "addr:full":"17b Balls Rd Birkenhead Merseyside L43 5RF",
    "addr:housenumber":"17b",
    "addr:postcode":"l43 5rf",
    "addr:street":"Balls Rd",
    "iso:country":"GB",
    "sg:address":"17b Balls Rd",
    "sg:city":"Birkenhead",
    "sg:classifiers":[
        {
            "category":"Organizations",
            "subcategory":"Non-profit Organization",
            "type":"Services"
        }
    ],
    "sg:phone":"+44 151 670 0343",
    "sg:postcode":"L43 5RF",
    "sg:province":"Merseyside",
    "sg:tags":[
        "organisation",
        "voluntary",
        "charity"
    ],
    "wof:name":"Alzheimers Disease Society",
    "wof:placetype":"venue"
},
  "geometry": {"coordinates":[-3.03847,53.384727],"type":"Point"}
}