{
  "type": "Feature",
  "properties": {
    "iso:country":"GB",
    "sg:address":"Hillside, Salisbury Road",
    "sg:city":"Tidworth",
    "sg:classifiers":[
        {
            "category":"Autos & Motor Vehicles",
            "subcategory":"Automobile Sales",
            "type":"Retail Goods"
        }
    ],
    "sg:postcode":"SP9 7UW",
    "sg:province":"Hampshire",
    "sg:tags":[
        "car"
    ],
    "wof:name":"Shipton Car Sales",
    "wof:placetype":"venue"
},
  "geometry": {"coordinates":[-1.664009,51.236897],"type":"Point"}
}