{
  "type": "Feature",
  "properties": {
    "iso:country":"GB",
    "sg:address":"106 High Street, New Pitsligo",
    "sg:city":"Fraserburgh",
    "sg:classifiers":[
        {
            "category":"Building & Trades",
            "subcategory":"Plumbing",
            "type":"Services"
        }
    ],
    "sg:postcode":"AB43 6NN",
    "sg:province":"Aberdeenshire",
    "sg:tags":[
        "heating"
    ],
    "wof:name":"Alistair Wilson",
    "wof:placetype":"venue"
},
  "geometry": {"coordinates":[-2.1947410107,57.58934021],"type":"Point"}
}