{
  "type": "Feature",
  "properties": {
    "addr:full":"49 Badminton Rd Maidenhead Berkshire SL6 4QS",
    "addr:housenumber":"49",
    "addr:postcode":"sl6 4qs",
    "addr:street":"Badminton Rd",
    "iso:country":"GB",
    "sg:address":"49 Badminton Rd",
    "sg:city":"Maidenhead",
    "sg:classifiers":[
        {
            "category":"Taxi",
            "type":"Transportation"
        }
    ],
    "sg:phone":"+44 1628 410000",
    "sg:postcode":"SL6 4QS",
    "sg:province":"Berkshire",
    "sg:tags":[
        "mini",
        "cab"
    ],
    "wof:name":"A Brittania",
    "wof:placetype":"venue"
},
  "geometry": {"coordinates":[-0.7476419806,51.5179443359],"type":"Point"}
}