{
  "type": "Feature",
  "properties": {
    "addr:full":"2 Minerva Rd Kingston Upon Thames Greater London KT1 2QA",
    "addr:housenumber":"2",
    "addr:postcode":"kt1 2qa",
    "addr:street":"Minerva Rd",
    "iso:country":"GB",
    "sg:address":"2 Minerva Rd",
    "sg:city":"Kingston Upon Thames",
    "sg:classifiers":[
        {
            "category":"Building & Trades",
            "subcategory":"Construction",
            "type":"Services"
        }
    ],
    "sg:phone":"+44 20 8546 3632",
    "sg:postcode":"KT1 2QA",
    "sg:province":"Greater London",
    "sg:tags":[
        "builder"
    ],
    "wof:name":"C L P Builders",
    "wof:placetype":"venue"
},
  "geometry": {"coordinates":[-0.2953880131,51.4092903137],"type":"Point"}
}