{
  "type": "Feature",
  "properties": {
    "addr:full":"Royal House, Parabola Road Cheltenham Gloucestershire GL50 3AH",
    "addr:postcode":"gl50 3ah",
    "addr:street":"Parabola Road",
    "iso:country":"GB",
    "sg:address":"Royal House, Parabola Road",
    "sg:city":"Cheltenham",
    "sg:classifiers":[
        {
            "category":"Professional",
            "subcategory":"Research",
            "type":"Services"
        }
    ],
    "sg:postcode":"GL50 3AH",
    "sg:province":"Gloucestershire",
    "sg:tags":[
        "market"
    ],
    "wof:name":"Twenty K Ltd",
    "wof:placetype":"venue"
},
  "geometry": {"coordinates":[-2.0851809978,51.8965415955],"type":"Point"}
}