{
  "type": "Feature",
  "properties": {
    "addr:full":"30 Stoneycroft Cannock Staffordshire WS11 2XU",
    "addr:housenumber":"30",
    "addr:postcode":"ws11 2xu",
    "addr:street":"Stoneycroft",
    "iso:country":"GB",
    "sg:address":"30 Stoneycroft",
    "sg:city":"Cannock",
    "sg:classifiers":[
        {
            "category":"Building & Trades",
            "subcategory":"Construction",
            "type":"Services"
        }
    ],
    "sg:phone":"+44 1543 570944",
    "sg:postcode":"WS11 2XU",
    "sg:province":"Staffordshire",
    "sg:tags":[
        "builder"
    ],
    "wof:name":"East Cannock Building Services Ltd.",
    "wof:placetype":"venue"
},
  "geometry": {"coordinates":[-2.0172789097,52.7023887634],"type":"Point"}
}