{
  "type": "Feature",
  "properties": {
    "addr:full":"Laxton Place, Longford Street London Greater London NW1 3PT",
    "addr:postcode":"nw1 3pt",
    "addr:street":"Laxton Place Longford Street",
    "iso:country":"GB",
    "sg:address":"Laxton Place, Longford Street",
    "sg:city":"London",
    "sg:classifiers":[
        {
            "category":"Place Of Worship",
            "type":"Public Place"
        }
    ],
    "sg:phone":"+44 20 7387 3833",
    "sg:postcode":"NW1 3PT",
    "sg:province":"Greater London",
    "wof:name":"St.Ann S R C Church",
    "wof:placetype":"venue"
},
  "geometry": {"coordinates":[-0.1421039999,51.5259094238],"type":"Point"}
}