{
  "type": "Feature",
  "properties": {
    "addr:full":"Kingston Crescent Portsmouth Hampshire PO2 8QL",
    "addr:postcode":"hampshire po2 8ql",
    "addr:street":"Kingston Crescent",
    "iso:country":"GB",
    "sg:address":"Kingston Crescent",
    "sg:city":"Portsmouth",
    "sg:classifiers":[
        {
            "category":"Manufacturing",
            "subcategory":"Tools & Machinery",
            "type":"Manufacturing & Wholesale Goods"
        },
        {
            "category":"Insurance",
            "subcategory":"Insurance Agent",
            "type":"Services"
        }
    ],
    "sg:postcode":"PO2 8QL",
    "sg:province":"Hampshire",
    "sg:tags":[
        "society",
        "friendly"
    ],
    "wof:name":"The British Diabetic Association",
    "wof:placetype":"venue"
},
  "geometry": {"coordinates":[-1.0828989744,50.8134346008],"type":"Point"}
}