{
  "type": "Feature",
  "properties": {
    "addr:full":"Walnut Tree Farm, West Carr Road Attleborough Norfolk NR17 1AN",
    "addr:postcode":"nr17 1an",
    "addr:street":"Walnut;West Carr Road",
    "iso:country":"GB",
    "sg:address":"Walnut Tree Farm, West Carr Road",
    "sg:city":"Attleborough",
    "sg:classifiers":[
        {
            "category":"Building & Trades",
            "subcategory":"Landscaping Services",
            "type":"Services"
        }
    ],
    "sg:postcode":"NR17 1AN",
    "sg:province":"Norfolk",
    "sg:tags":[
        "gardening"
    ],
    "wof:name":"Homecare Garden Services",
    "wof:placetype":"venue"
},
  "geometry": {"coordinates":[1.014435,52.519054],"type":"Point"}
}