{
  "type": "Feature",
  "properties": {
    "iso:country":"GB",
    "sg:address":"38-42 Osborne Road",
    "sg:city":"Windsor",
    "sg:classifiers":[
        {
            "category":"Health Services",
            "subcategory":"Doctor",
            "type":"Services"
        }
    ],
    "sg:phone":"+44 1753 620971",
    "sg:postcode":"SL4 3SJ",
    "sg:province":"Berkshire",
    "sg:tags":[
        "surgeon"
    ],
    "wof:name":"PETER M DAWSON",
    "wof:placetype":"venue"
},
  "geometry": {"coordinates":[-0.611573,51.474808],"type":"Point"}
}