{
  "type": "Feature",
  "properties": {
    "iso:country":"GB",
    "sg:address":"14-16 Briton Street",
    "sg:city":"Leicester",
    "sg:classifiers":[
        {
            "category":"Recreation",
            "type":"Entertainment"
        }
    ],
    "sg:phone":"+44 116 254 8818",
    "sg:postcode":"LE3 0AA",
    "sg:province":"Leicestershire",
    "sg:tags":[
        "outdoor",
        "pursuit"
    ],
    "wof:name":"British Motorcyclists Federation (Promotions) Ltd.",
    "wof:placetype":"venue"
},
  "geometry": {"coordinates":[-1.148778,52.62851],"type":"Point"}
}