{
  "type": "Feature",
  "properties": {
    "iso:country":"GB",
    "sg:address":"Stokesley Rd",
    "sg:city":"Middlesbrough",
    "sg:classifiers":[
        {
            "category":"Education",
            "subcategory":"Special Training",
            "type":"Public Place"
        }
    ],
    "sg:phone":"+44 1642 595778",
    "sg:postcode":"TS8 9DY",
    "sg:province":"North Yorkshire",
    "sg:tags":[
        "product",
        "centre"
    ],
    "wof:name":"Whinstone Training Guild",
    "wof:placetype":"venue"
},
  "geometry": {"coordinates":[-1.200381,54.53159],"type":"Point"}
}