{
  "type": "Feature",
  "properties": {
    "iso:country":"GB",
    "sg:address":"Crescent Road",
    "sg:city":"Ivybridge",
    "sg:classifiers":[
        {
            "category":"Building & Trades",
            "subcategory":"Construction",
            "type":"Services"
        }
    ],
    "sg:phone":"+44 1752 892446",
    "sg:postcode":"PL21 0BP",
    "sg:province":"Devon",
    "sg:tags":[
        "builder"
    ],
    "wof:name":"Hosgood & Sons (Ivybridge) Limited",
    "wof:placetype":"venue"
},
  "geometry": {"coordinates":[-3.9224550724,50.395275116],"type":"Point"}
}