{
  "type": "Feature",
  "properties": {
    "addr:full":"St Georges Road Redditch Warwickshire B98 8EF",
    "addr:postcode":"b98 8ef",
    "addr:street":"St Georges Road",
    "iso:country":"GB",
    "sg:address":"St Georges Road",
    "sg:city":"Redditch",
    "sg:classifiers":[
        {
            "category":"Manufacturing",
            "subcategory":"Metals",
            "type":"Manufacturing & Wholesale Goods"
        },
        {
            "category":"Wholesale",
            "subcategory":"Construction Materials",
            "type":"Manufacturing & Wholesale Goods"
        }
    ],
    "sg:phone":"+44 1527 63617",
    "sg:postcode":"B98 8EF",
    "sg:province":"Warwickshire",
    "sg:tags":[
        "distributor",
        "spring",
        "manufacturer"
    ],
    "wof:name":"Quality Springs & Pressings Ltd.",
    "wof:placetype":"venue"
},
  "geometry": {"coordinates":[-1.929929,52.307091],"type":"Point"}
}