{
  "type": "Feature",
  "properties": {
    "addr:full":"301 Silbury Boulevard Milton Keynes Buckinghamshire MK9 2YH",
    "addr:housenumber":"301",
    "addr:postcode":"mk9 2yh",
    "addr:street":"Silbury Boulevard",
    "iso:country":"GB",
    "sg:address":"301 Silbury Boulevard",
    "sg:city":"Milton Keynes",
    "sg:classifiers":[
        {
            "category":"Government",
            "subcategory":"Office",
            "type":"Public Place"
        }
    ],
    "sg:phone":"+44 1908 679734",
    "sg:postcode":"MK9 2YH",
    "sg:province":"Buckinghamshire",
    "sg:tags":[
        "central"
    ],
    "wof:name":"The Probation Service",
    "wof:placetype":"venue"
},
  "geometry": {"coordinates":[-0.764729023,52.0410690308],"type":"Point"}
}