{
  "type": "Feature",
  "properties": {
    "iso:country":"GB",
    "sg:address":"21 Oxford Road, Mosley",
    "sg:city":"Birmingham",
    "sg:classifiers":[
        {
            "category":"Travel",
            "subcategory":"Hotels & Motels",
            "type":"Entertainment"
        }
    ],
    "sg:postcode":"B13 9EH",
    "sg:province":"West Midlands",
    "wof:name":"Clona Developments Ltd.",
    "wof:placetype":"venue"
},
  "geometry": {"coordinates":[-1.884479,52.444008],"type":"Point"}
}