{
  "type": "Feature",
  "properties": {
    "addr:full":"210 London Road, Burpham Guildford Surrey GU4 7JS",
    "addr:housenumber":"210",
    "addr:postcode":"gu4 7js",
    "addr:street":"London Road",
    "iso:country":"GB",
    "sg:address":"210 London Road, Burpham",
    "sg:city":"Guildford",
    "sg:classifiers":[
        {
            "category":"Education",
            "subcategory":"College",
            "type":"Public Place"
        }
    ],
    "sg:phone":"+44 1483 577835",
    "sg:postcode":"GU4 7JS",
    "sg:province":"Surrey",
    "sg:tags":[
        "school"
    ],
    "wof:name":"Howzat Sports & Leisure",
    "wof:placetype":"venue"
},
  "geometry": {"coordinates":[-0.546258986,51.2576408386],"type":"Point"}
}