{
  "type": "Feature",
  "properties": {
    "iso:country":"GB",
    "sg:address":"Trevecca, Culverland Road",
    "sg:city":"Liskeard",
    "sg:classifiers":[
        {
            "category":"Professional",
            "subcategory":"Detective & Security Services",
            "type":"Services"
        }
    ],
    "sg:phone":"+44 1579 343338",
    "sg:postcode":"PL14 6RE",
    "sg:province":"Cornwall",
    "wof:name":"Orion Security Ltd.",
    "wof:placetype":"venue"
},
  "geometry": {"coordinates":[-4.462109,50.463806],"type":"Point"}
}