{
  "type": "Feature",
  "properties": {
    "iso:country":"GB",
    "sg:address":"33 Norbury Crescent",
    "sg:city":"London",
    "sg:classifiers":[
        {
            "category":"Professional",
            "type":"Services"
        }
    ],
    "sg:phone":"+44 20 8764 8891",
    "sg:postcode":"SW16 4JS",
    "sg:province":"Greater London",
    "sg:tags":[
        "entertainer"
    ],
    "wof:name":"Seaforth Entertainment",
    "wof:placetype":"venue"
},
  "geometry": {"coordinates":[-0.1204940006,51.4101295471],"type":"Point"}
}