{
  "type": "Feature",
  "properties": {
    "iso:country":"GB",
    "sg:address":"Bog Mines, The Bog, Minsterley",
    "sg:city":"Shrewsbury",
    "sg:classifiers":[
        {
            "category":"Transit Center",
            "subcategory":"Passenger",
            "type":"Transportation"
        }
    ],
    "sg:postcode":"SY5 0NJ",
    "sg:province":"Shropshire",
    "sg:tags":[
        "boarding",
        "kennel",
        "catteries"
    ],
    "wof:name":"Bog Mine Pet Centre",
    "wof:placetype":"venue"
},
  "geometry": {"coordinates":[-2.925398,52.638226],"type":"Point"}
}