{
  "type": "Feature",
  "properties": {
    "addr:full":"Quarrylea Villa, 34 Packman Way Rotherham South Yorkshire S63 6BR",
    "addr:housenumber":"34",
    "addr:postcode":"s63 6br",
    "addr:street":"Packman Way",
    "iso:country":"GB",
    "sg:address":"Quarrylea Villa, 34 Packman Way",
    "sg:city":"Rotherham",
    "sg:classifiers":[
        {
            "category":"Home & Garden",
            "subcategory":"Home Furnishings",
            "type":"Retail Goods"
        },
        {
            "category":"Building & Trades",
            "subcategory":"Construction",
            "type":"Services"
        }
    ],
    "sg:phone":"+44 1709 875293",
    "sg:postcode":"S63 6BR",
    "sg:province":"South Yorkshire",
    "sg:tags":[
        "mantelpiece",
        "fireplace"
    ],
    "wof:name":"Sapphire Plumbing & Heating",
    "wof:placetype":"venue"
},
  "geometry": {"coordinates":[-1.37027,53.502609],"type":"Point"}
}