{
  "type": "Feature",
  "properties": {
    "addr:full":"195 Euston Rd Camden Greater London NW1 2BN",
    "addr:housenumber":"195",
    "addr:postcode":"nw1 2bn",
    "addr:street":"Euston Rd",
    "iso:country":"GB",
    "sg:address":"195 Euston Rd",
    "sg:city":"Camden",
    "sg:classifiers":[
        {
            "category":"Professional",
            "subcategory":"Advertising",
            "type":"Services"
        }
    ],
    "sg:phone":"+44 20 7753 8683",
    "sg:postcode":"NW1 2BN",
    "sg:province":"Greater London",
    "sg:tags":[
        "agency"
    ],
    "wof:name":"Hyde Arc",
    "wof:placetype":"venue"
},
  "geometry": {"coordinates":[-0.134345,51.525944],"type":"Point"}
}