{
  "type": "Feature",
  "properties": {
    "iso:country":"GB",
    "sg:address":"73 Lidget Lane, Thurnscoe",
    "sg:city":"Rotherham",
    "sg:classifiers":[
        {
            "category":"Shopping",
            "subcategory":"Department Store",
            "type":"Retail Goods"
        }
    ],
    "sg:phone":"+44 1709 892227",
    "sg:postcode":"S63 0BZ",
    "sg:province":"South Yorkshire",
    "wof:name":"M D W Turner",
    "wof:placetype":"venue"
},
  "geometry": {"coordinates":[-1.303849,53.544052],"type":"Point"}
}