{
  "type": "Feature",
  "properties": {
    "addr:full":"8 South Molton Street London Greater London W1K 5QQ",
    "addr:housenumber":"8",
    "addr:postcode":"w1k 5qq",
    "addr:street":"South Molton Street",
    "iso:country":"GB",
    "sg:address":"8 South Molton Street",
    "sg:city":"London",
    "sg:classifiers":[
        {
            "category":"Professional",
            "subcategory":"Accounting & Tax Preparation",
            "type":"Services"
        }
    ],
    "sg:postcode":"W1K 5QQ",
    "sg:province":"Greater London",
    "sg:tags":[
        "accountant"
    ],
    "wof:name":"Avocim Finance Ltd.",
    "wof:placetype":"venue"
},
  "geometry": {"coordinates":[-0.147629,51.513416],"type":"Point"}
}