{
  "type": "Feature",
  "properties": {
    "addr:full":"55-57 Causewayside Edinburgh City of Edinburgh EH9 1QF",
    "addr:housenumber":"55-57",
    "addr:postcode":"eh9 1qf",
    "addr:street":"Causewayside",
    "iso:country":"GB",
    "sg:address":"55-57 Causewayside",
    "sg:city":"Edinburgh",
    "sg:classifiers":[
        {
            "category":"Shopping",
            "subcategory":"Musical Instruments",
            "type":"Retail Goods"
        }
    ],
    "sg:phone":"+44 131 662 1862",
    "sg:postcode":"EH9 1QF",
    "sg:province":"City of Edinburgh",
    "sg:tags":[
        "music",
        "sheet"
    ],
    "wof:name":"Stringers Musical Instruments",
    "wof:placetype":"venue"
},
  "geometry": {"coordinates":[-3.188699007,55.9380493164],"type":"Point"}
}