{
  "type": "Feature",
  "properties": {
    "iso:country":"GB",
    "sg:address":"10 London Road",
    "sg:city":"Alderley Edge",
    "sg:classifiers":[
        {
            "category":"Banks & Credit Unions",
            "subcategory":"Financial Services",
            "type":"Services"
        }
    ],
    "sg:phone":"+44 1625 585185",
    "sg:postcode":"SK9 7JS",
    "sg:province":"Cheshire",
    "sg:tags":[
        "building",
        "society"
    ],
    "wof:name":"Cheshire Building Society",
    "wof:placetype":"venue"
},
  "geometry": {"coordinates":[-2.2364490032,53.3021621704],"type":"Point"}
}