{
  "type": "Feature",
  "properties": {
    "iso:country":"GB",
    "sg:address":"9 Talisman Sq",
    "sg:city":"Kenilworth",
    "sg:classifiers":[
        {
            "category":"Shopping",
            "subcategory":"Music",
            "type":"Retail Goods"
        }
    ],
    "sg:phone":"+44 1926 857012",
    "sg:postcode":"CV8 1JB",
    "sg:province":"Warwickshire",
    "sg:tags":[
        "record",
        "tape",
        "cd"
    ],
    "wof:name":"What Records",
    "wof:placetype":"venue"
},
  "geometry": {"coordinates":[-1.5813169479,52.3404045105],"type":"Point"}
}