{
  "type": "Feature",
  "properties": {
    "iso:country":"GB",
    "sg:address":"Unit 10, Institute Lane",
    "sg:city":"Alfreton",
    "sg:classifiers":[
        {
            "category":"Government",
            "subcategory":"Post Office",
            "type":"Public Place"
        }
    ],
    "sg:phone":"+44 1773 832072",
    "sg:postcode":"DE55 7BQ",
    "sg:province":"Derbyshire",
    "wof:name":"F P O Alfreton",
    "wof:placetype":"venue"
},
  "geometry": {"coordinates":[-1.3884439468,53.0969352722],"type":"Point"}
}