{
  "type": "Feature",
  "properties": {
    "iso:country":"GB",
    "sg:address":"2 Borough Road",
    "sg:city":"Middlesbrough",
    "sg:classifiers":[
        {
            "category":"Shopping",
            "type":"Retail Goods"
        }
    ],
    "sg:phone":"+44 1642 253525",
    "sg:postcode":"TS1 5DP",
    "sg:province":"North Yorkshire",
    "sg:tags":[
        "part",
        "accessory"
    ],
    "wof:name":"Jap City",
    "wof:placetype":"venue"
},
  "geometry": {"coordinates":[-1.240626,54.573357],"type":"Point"}
}