{
  "type": "Feature",
  "properties": {
    "addr:full":"Church Road, Aspley Heath Milton Keynes Bedfordshire MK17 8TJ",
    "addr:postcode":"mk17 8tj",
    "addr:street":"Church Road",
    "iso:country":"GB",
    "sg:address":"Church Road, Aspley Heath",
    "sg:city":"Milton Keynes",
    "sg:classifiers":[
        {
            "category":"Education",
            "subcategory":"School",
            "type":"Public Place"
        }
    ],
    "sg:phone":"+44 1908 583541",
    "sg:postcode":"MK17 8TJ",
    "sg:province":"Bedfordshire",
    "sg:tags":[
        "independent",
        "preparatory"
    ],
    "wof:name":"Fernwood School Ltd.",
    "wof:placetype":"venue"
},
  "geometry": {"coordinates":[-0.6519839764,52.0040168762],"type":"Point"}
}