{
  "type": "Feature",
  "properties": {
    "iso:country":"GB",
    "sg:address":"13-15 Queen Street",
    "sg:city":"Stranraer",
    "sg:classifiers":[
        {
            "category":"Fast Food",
            "type":"Food & Drink"
        },
        {
            "category":"Restaurant",
            "type":"Food & Drink"
        }
    ],
    "sg:phone":"+44 1776 705176",
    "sg:postcode":"DG9 7LQ",
    "sg:province":"Dumfries and Galloway",
    "sg:tags":[
        "outlet",
        "away",
        "meal",
        "chinese",
        "take"
    ],
    "wof:name":"Sunkai Chinese Takeaway",
    "wof:placetype":"venue"
},
  "geometry": {"coordinates":[-5.028437,54.905376],"type":"Point"}
}