{
  "type": "Feature",
  "properties": {
    "iso:country":"GB",
    "sg:address":"Four Oakes Garage, 270 Lichfield Road",
    "sg:city":"Sutton Coldfield",
    "sg:classifiers":[
        {
            "category":"Retail",
            "subcategory":"Auto Repair",
            "type":"Services"
        }
    ],
    "sg:phone":"+44 121 308 0309",
    "sg:postcode":"B74 2UH",
    "sg:province":"Staffordshire",
    "sg:tags":[
        "modification",
        "garage",
        "related"
    ],
    "wof:name":"G Chamberlain & Son",
    "wof:placetype":"venue"
},
  "geometry": {"coordinates":[-1.8291,52.584949],"type":"Point"}
}