{
  "type": "Feature",
  "properties": {
    "iso:country":"GB",
    "sg:address":"Medical Centre, 5 Acorn Way",
    "sg:city":"Telford",
    "sg:classifiers":[
        {
            "category":"Health Services",
            "subcategory":"Doctor",
            "type":"Services"
        }
    ],
    "sg:phone":"+44 1952 641555",
    "sg:postcode":"TF5 0LT",
    "sg:province":"Shropshire",
    "sg:tags":[
        "practitioners"
    ],
    "wof:name":"Herd, E",
    "wof:placetype":"venue"
},
  "geometry": {"coordinates":[-2.53052,52.718658],"type":"Point"}
}