{
  "type": "Feature",
  "properties": {
    "addr:full":"Unit 99 Road B, Boughton Indust Estate, Ollerton Newark Nottinghamshire NG22 9LD",
    "addr:housenumber":"unit 99",
    "addr:postcode":"ng22 9ld",
    "addr:street":"Road B Boughton Indust Estate",
    "iso:country":"GB",
    "sg:address":"Unit 99 Road B, Boughton Indust Estate, Ollerton",
    "sg:city":"Newark",
    "sg:classifiers":[
        {
            "category":"Wholesale",
            "subcategory":"Scrap",
            "type":"Manufacturing & Wholesale Goods"
        }
    ],
    "sg:phone":"+44 1623 863164",
    "sg:postcode":"NG22 9LD",
    "sg:province":"Nottinghamshire",
    "sg:tags":[
        "breaker",
        "dismantlers"
    ],
    "wof:name":"Star Auto Salvage",
    "wof:placetype":"venue"
},
  "geometry": {"coordinates":[-0.9933720231,53.2082672119],"type":"Point"}
}