{
  "type": "Feature",
  "properties": {
    "addr:full":"Ebberns Road Hemel Hempstead Hertfordshire HP3 9RD",
    "addr:postcode":"hp3 9rd",
    "addr:street":"Ebberns Road",
    "iso:country":"GB",
    "sg:address":"Ebberns Road",
    "sg:city":"Hemel Hempstead",
    "sg:classifiers":[
        {
            "category":"Communications",
            "type":"Services"
        }
    ],
    "sg:phone":"+44 1442 257502",
    "sg:postcode":"HP3 9RD",
    "sg:province":"Hertfordshire",
    "sg:tags":[
        "telecommunication"
    ],
    "wof:name":"Suburban Aerial Contractors",
    "wof:placetype":"venue"
},
  "geometry": {"coordinates":[-0.464678,51.738621],"type":"Point"}
}