{
  "type": "Feature",
  "properties": {
    "addr:full":"Moorlaws Farm Alnwick Northumberland NE66 2AY",
    "addr:postcode":"ne66 2ay",
    "iso:country":"GB",
    "sg:address":"Moorlaws Farm",
    "sg:city":"Alnwick",
    "sg:classifiers":[
        {
            "category":"Farming",
            "subcategory":"Livestock Farm",
            "type":"Manufacturing & Wholesale Goods"
        }
    ],
    "sg:postcode":"NE66 2AY",
    "sg:province":"Northumberland",
    "sg:tags":[
        "others"
    ],
    "wof:name":"H Frater & Son",
    "wof:placetype":"venue"
},
  "geometry": {"coordinates":[-1.703514,55.412601],"type":"Point"}
}