{
  "type": "Feature",
  "properties": {
    "addr:full":"23 Commonside Sheffield South Yorkshire S10 1GD",
    "addr:housenumber":"23",
    "addr:postcode":"s10 1gd",
    "addr:street":"Commonside",
    "iso:country":"GB",
    "sg:address":"23 Commonside",
    "sg:city":"Sheffield",
    "sg:classifiers":[
        {
            "category":"Shopping",
            "subcategory":"Jewelry",
            "type":"Retail Goods"
        },
        {
            "category":"Shopping",
            "subcategory":"Comic Books",
            "type":"Retail Goods"
        }
    ],
    "sg:phone":"+44 114 266 9253",
    "sg:postcode":"S10 1GD",
    "sg:province":"South Yorkshire",
    "sg:tags":[
        "jeweller",
        "sale",
        "jewellery"
    ],
    "wof:name":"P A Jewellery Supplies Ltd",
    "wof:placetype":"venue"
},
  "geometry": {"coordinates":[-1.496984005,53.3867263794],"type":"Point"}
}