{
  "type": "Feature",
  "properties": {
    "addr:full":"Unit 3/4 Pennywell Industrial Estate Sunderland Tyne and Wear SR4 9EN",
    "addr:housenumber":"unit 3 / 4;estate",
    "addr:postcode":"sr4 9en",
    "addr:street":"Pennywell Industrial",
    "iso:country":"GB",
    "sg:address":"Unit 3/4 Pennywell Industrial Estate",
    "sg:city":"Sunderland",
    "sg:classifiers":[
        {
            "category":"Manufacturing",
            "subcategory":"Metals",
            "type":"Manufacturing & Wholesale Goods"
        }
    ],
    "sg:phone":"+44 191 534 3080",
    "sg:postcode":"SR4 9EN",
    "sg:province":"Tyne and Wear",
    "sg:tags":[
        "work",
        "sheet"
    ],
    "wof:name":"Contractors Pumps (Northern)",
    "wof:placetype":"venue"
},
  "geometry": {"coordinates":[-1.4376159906,54.893699646],"type":"Point"}
}