{
  "type": "Feature",
  "properties": {
    "addr:full":"Holme Farm, Middleton Sedbergh Cumbria LA10 5ET",
    "addr:postcode":"la10 5et",
    "iso:country":"GB",
    "sg:address":"Holme Farm, Middleton",
    "sg:city":"Sedbergh",
    "sg:classifiers":[
        {
            "category":"Farming",
            "subcategory":"Livestock Farm",
            "type":"Manufacturing & Wholesale Goods"
        }
    ],
    "sg:phone":"+44 15396 20654",
    "sg:postcode":"LA10 5ET",
    "sg:province":"Cumbria",
    "sg:tags":[
        "others"
    ],
    "wof:name":"J H & A Metcalfe & Son",
    "wof:placetype":"venue"
},
  "geometry": {"coordinates":[-2.527837038,54.3219451904],"type":"Point"}
}