{
  "type": "Feature",
  "properties": {
    "iso:country":"GB",
    "sg:address":"35 Harboro Road",
    "sg:city":"Sale",
    "sg:classifiers":[
        {
            "category":"Travel",
            "subcategory":"Hotels & Motels",
            "type":"Entertainment"
        }
    ],
    "sg:phone":"+44 161 973 6770",
    "sg:postcode":"M33 5AN",
    "sg:province":"Cheshire",
    "wof:name":"Eskdale Lodge Hotel",
    "wof:placetype":"venue"
},
  "geometry": {"coordinates":[-2.3385128975,53.4224090576],"type":"Point"}
}