{
  "type": "Feature",
  "properties": {
    "iso:country":"GB",
    "sg:address":"Dorchester South Railway Station, Station App",
    "sg:city":"Dorchester",
    "sg:classifiers":[
        {
            "category":"Retail",
            "subcategory":"Auto Rental",
            "type":"Services"
        }
    ],
    "sg:phone":"+44 1305 251995",
    "sg:postcode":"DT1 1QX",
    "sg:province":"Dorset",
    "sg:tags":[
        "truck",
        "hire",
        "van"
    ],
    "wof:name":"U Drive Rental",
    "wof:placetype":"venue"
},
  "geometry": {"coordinates":[-2.441564,50.711906],"type":"Point"}
}