{
  "type": "Feature",
  "properties": {
    "addr:full":"Graham House, 21 Owens Court, Skypark Liverpool Merseyside L24 1UU",
    "addr:housenumber":"21",
    "addr:postcode":"l24 1uu",
    "addr:street":"Owens Court",
    "iso:country":"GB",
    "sg:address":"Graham House, 21 Owens Court, Skypark",
    "sg:city":"Liverpool",
    "sg:classifiers":[
        {
            "category":"Banks & Credit Unions",
            "subcategory":"Investment Brokerage",
            "type":"Services"
        }
    ],
    "sg:phone":"+44 151 486 3338",
    "sg:postcode":"L24 1UU",
    "sg:province":"Merseyside",
    "sg:tags":[
        "sheeting",
        "polythene",
        "plastic"
    ],
    "wof:name":"Graham's Paper & Polythene Ltd.",
    "wof:placetype":"venue"
},
  "geometry": {"coordinates":[-2.8597040176,53.3406982422],"type":"Point"}
}