{
  "type": "Feature",
  "properties": {
    "addr:full":"26 St Chads Crescent Oldham Lancashire OL8 3LD",
    "addr:housenumber":"26",
    "addr:postcode":"ol8 3ld",
    "addr:street":"St Chads Crescent",
    "iso:country":"GB",
    "sg:address":"26 St Chads Crescent",
    "sg:city":"Oldham",
    "sg:classifiers":[
        {
            "category":"Food & Beverages",
            "subcategory":"Groceries & Convenience Stores",
            "type":"Retail Goods"
        }
    ],
    "sg:postcode":"OL8 3LD",
    "sg:province":"Lancashire",
    "wof:name":"Limeside Oasis",
    "wof:placetype":"venue"
},
  "geometry": {"coordinates":[-2.126477,53.514828],"type":"Point"}
}