{
  "type": "Feature",
  "properties": {
    "iso:country":"GB",
    "sg:address":"The Old Telephone Exchange, Market Hill",
    "sg:city":"Buckingham",
    "sg:classifiers":[
        {
            "category":"Home & Garden",
            "subcategory":"Household Appliances",
            "type":"Retail Goods"
        }
    ],
    "sg:phone":"+44 1869 242945",
    "sg:postcode":"MK18 1JT",
    "sg:province":"Buckinghamshire",
    "sg:tags":[
        "electrical",
        "domestic",
        "centre"
    ],
    "wof:name":"Thorne Appliance Services",
    "wof:placetype":"venue"
},
  "geometry": {"coordinates":[-0.986479,52.000751],"type":"Point"}
}