{
  "type": "Feature",
  "properties": {
    "iso:country":"GB",
    "sg:address":"Station House, Station Road",
    "sg:city":"Lingfield",
    "sg:classifiers":[
        {
            "category":"Professional",
            "subcategory":"Art Services",
            "type":"Services"
        }
    ],
    "sg:phone":"+44 1342 836504",
    "sg:postcode":"RH7 6EF",
    "sg:province":"Surrey",
    "sg:tags":[
        "photographer"
    ],
    "wof:name":"Captured Images",
    "wof:placetype":"venue"
},
  "geometry": {"coordinates":[-0.011332,51.181946],"type":"Point"}
}