{
  "type": "Feature",
  "properties": {
    "addr:full":"Empire House, 18 Retiro St Oldham Lancashire OL1 1SA",
    "addr:housenumber":"18",
    "addr:postcode":"ol1 1sa",
    "addr:street":"Retiro St",
    "iso:country":"GB",
    "sg:address":"Empire House, 18 Retiro St",
    "sg:city":"Oldham",
    "sg:classifiers":[
        {
            "category":"Insurance",
            "subcategory":"Insurance Agent",
            "type":"Services"
        }
    ],
    "sg:phone":"+44 161 627 4922",
    "sg:postcode":"OL1 1SA",
    "sg:province":"Lancashire",
    "sg:tags":[
        "broker"
    ],
    "wof:name":"Empire Claims Services",
    "wof:placetype":"venue"
},
  "geometry": {"coordinates":[-2.1096189022,53.5418434143],"type":"Point"}
}