{
  "type": "Feature",
  "properties": {
    "iso:country":"GB",
    "sg:address":"38a High Street",
    "sg:city":"London",
    "sg:classifiers":[
        {
            "category":"Professional",
            "subcategory":"Secretarial Services",
            "type":"Services"
        }
    ],
    "sg:phone":"+44 20 8579 1881",
    "sg:postcode":"W5 5DB",
    "sg:province":"Greater London",
    "wof:name":"Wordplex Bureau",
    "wof:placetype":"venue"
},
  "geometry": {"coordinates":[-0.3048219979,51.5125923157],"type":"Point"}
}