{
  "type": "Feature",
  "properties": {
    "addr:full":"47 Abbey Grove Abbey Wood Greater London SE2 9EU",
    "addr:housenumber":"47",
    "addr:postcode":"se2 9eu",
    "addr:street":"Abbey Grove",
    "iso:country":"GB",
    "sg:address":"47 Abbey Grove",
    "sg:city":"Abbey Wood",
    "sg:classifiers":[
        {
            "category":"Farming",
            "subcategory":"Nursery",
            "type":"Manufacturing & Wholesale Goods"
        }
    ],
    "sg:phone":"+44 20 8310 9659",
    "sg:postcode":"SE2 9EU",
    "sg:province":"Greater London",
    "sg:tags":[
        "creche"
    ],
    "wof:name":"Abbey Grove Day Nursery",
    "wof:placetype":"venue"
},
  "geometry": {"coordinates":[0.1165409982,51.4904785156],"type":"Point"}
}