{
  "type": "Feature",
  "properties": {
    "addr:full":"10 Hatton Garden London Greater London EC1N 8AH",
    "addr:housenumber":"10",
    "addr:postcode":"ec1n 8ah",
    "addr:street":"Hatton Garden",
    "iso:country":"GB",
    "sg:address":"10 Hatton Garden",
    "sg:city":"London",
    "sg:classifiers":[
        {
            "category":"Manufacturing",
            "subcategory":"Jewelry",
            "type":"Manufacturing & Wholesale Goods"
        }
    ],
    "sg:phone":"+44 20 7430 1662",
    "sg:postcode":"EC1N 8AH",
    "sg:province":"Greater London",
    "sg:tags":[
        "repair",
        "jewellery"
    ],
    "wof:name":"A M L Polishing",
    "wof:placetype":"venue"
},
  "geometry": {"coordinates":[-0.10773,51.51841],"type":"Point"}
}