{
  "type": "Feature",
  "properties": {
    "iso:country":"GB",
    "sg:address":"86 Evelina Rd",
    "sg:city":"Peckham",
    "sg:classifiers":[
        {
            "category":"Autos & Motor Vehicles",
            "subcategory":"Automobile Sales",
            "type":"Retail Goods"
        }
    ],
    "sg:phone":"+44 20 7635 6212",
    "sg:postcode":"SE15 3HL",
    "sg:province":"Greater London",
    "sg:tags":[
        "car"
    ],
    "wof:name":"B & A Car Sales",
    "wof:placetype":"venue"
},
  "geometry": {"coordinates":[-0.055866,51.466732],"type":"Point"}
}