{
  "type": "Feature",
  "properties": {
    "addr:full":"7-8 Wych Ho, Hamstel Rd Harlow Essex CM20 1EP",
    "addr:housenumber":"7-8",
    "addr:postcode":"cm20 1ep",
    "addr:street":"Wych Ho Hamstel Rd",
    "iso:country":"GB",
    "sg:address":"7-8 Wych Ho, Hamstel Rd",
    "sg:city":"Harlow",
    "sg:classifiers":[
        {
            "category":"Health Services",
            "subcategory":"Health Practitioner",
            "type":"Services"
        }
    ],
    "sg:phone":"+44 1279 410136",
    "sg:postcode":"CM20 1EP",
    "sg:province":"Essex",
    "sg:tags":[
        "osteopath"
    ],
    "wof:name":"B Grace",
    "wof:placetype":"venue"
},
  "geometry": {"coordinates":[0.085019,51.774479],"type":"Point"}
}