{
  "type": "Feature",
  "properties": {
    "iso:country":"GB",
    "sg:address":"Ravenscroft Lake Rd",
    "sg:city":"Windermere",
    "sg:classifiers":[
        {
            "category":"Banks & Credit Unions",
            "subcategory":"Investment Brokerage",
            "type":"Services"
        }
    ],
    "sg:postcode":"LA23 2EQ",
    "sg:province":"Cumbria",
    "wof:name":"House,James,",
    "wof:placetype":"venue"
},
  "geometry": {"coordinates":[-2.906404,54.379665],"type":"Point"}
}