{
  "type": "Feature",
  "properties": {
    "addr:full":"Jubilee House, On East Park Road Leicester Leicestershire LE5 4PD",
    "addr:postcode":"le5 4pd",
    "addr:street":"East Park Road",
    "iso:country":"GB",
    "sg:address":"Jubilee House, On East Park Road",
    "sg:city":"Leicester",
    "sg:classifiers":[
        {
            "category":"Shopping",
            "type":"Retail Goods"
        }
    ],
    "sg:postcode":"LE5 4PD",
    "sg:province":"Leicestershire",
    "sg:tags":[
        "part",
        "accessory"
    ],
    "wof:name":"Leicester Auto Parts",
    "wof:placetype":"venue"
},
  "geometry": {"coordinates":[-1.100839,52.637489],"type":"Point"}
}