{
  "type": "Feature",
  "properties": {
    "addr:full":"Coombe Hall, Coombe Hill Rd East Grinstead East Sussex RH19 4NA",
    "addr:postcode":"rh19 4na",
    "addr:street":"Coombe Hill Rd",
    "iso:country":"GB",
    "sg:address":"Coombe Hall, Coombe Hill Rd",
    "sg:city":"East Grinstead",
    "sg:classifiers":[
        {
            "category":"Education",
            "subcategory":"School",
            "type":"Public Place"
        }
    ],
    "sg:phone":"+44 1342 314577",
    "sg:postcode":"RH19 4NA",
    "sg:province":"East Sussex",
    "sg:tags":[
        "independent",
        "preparatory"
    ],
    "wof:name":"Greenfield School",
    "wof:placetype":"venue"
},
  "geometry": {"coordinates":[-0.0141110001,51.1134147644],"type":"Point"}
}