{
  "type": "Feature",
  "properties": {
    "iso:country":"GB",
    "sg:address":"63-65 Pentire Avenue",
    "sg:city":"Newquay",
    "sg:classifiers":[
        {
            "category":"Social Services",
            "subcategory":"Retirement Home",
            "type":"Services"
        }
    ],
    "sg:phone":"+44 1637 878437",
    "sg:postcode":"TR7 1PD",
    "sg:province":"Cornwall",
    "sg:tags":[
        "residential",
        "care"
    ],
    "wof:name":"Pentree Lodge Care Homes",
    "wof:placetype":"venue"
},
  "geometry": {"coordinates":[-5.105855,50.41087],"type":"Point"}
}