{
  "type": "Feature",
  "properties": {
    "iso:country":"GB",
    "sg:address":"1240 Leeds Rd",
    "sg:city":"Bradford",
    "sg:classifiers":[
        {
            "category":"Food & Beverages",
            "subcategory":"Meat & Fish",
            "type":"Retail Goods"
        }
    ],
    "sg:postcode":"BD3 8LG",
    "sg:province":"West Yorkshire",
    "sg:tags":[
        "butcher"
    ],
    "wof:name":"Jhatka Meat Cash & Carry",
    "wof:placetype":"venue"
},
  "geometry": {"coordinates":[-1.716185,53.793961],"type":"Point"}
}