{
  "type": "Feature",
  "properties": {
    "addr:full":"245 Stratford Road, Sparkbrook Birmingham West Midlands B11 1QY",
    "addr:housenumber":"245",
    "addr:postcode":"b11 1qy",
    "addr:street":"Stratford Road",
    "iso:country":"GB",
    "sg:address":"245 Stratford Road, Sparkbrook",
    "sg:city":"Birmingham",
    "sg:classifiers":[
        {
            "category":"Shopping",
            "subcategory":"Computers & Home Electronics",
            "type":"Retail Goods"
        }
    ],
    "sg:phone":"+44 121 772 5451",
    "sg:postcode":"B11 1QY",
    "sg:province":"West Midlands",
    "sg:tags":[
        "electrical"
    ],
    "wof:name":"Scotrose Ltd.",
    "wof:placetype":"venue"
},
  "geometry": {"coordinates":[-1.873281,52.460842],"type":"Point"}
}