{
  "type": "Feature",
  "properties": {
    "addr:full":"116 New Street Torrington Devon EX38 8BT",
    "addr:housenumber":"116",
    "addr:postcode":"ex38 8bt",
    "addr:street":"New Street",
    "iso:country":"GB",
    "sg:address":"116 New Street",
    "sg:city":"Torrington",
    "sg:classifiers":[
        {
            "category":"Building & Trades",
            "subcategory":"Construction",
            "type":"Services"
        }
    ],
    "sg:phone":"+44 1805 623293",
    "sg:postcode":"EX38 8BT",
    "sg:province":"Devon",
    "sg:tags":[
        "heating",
        "contractor"
    ],
    "wof:name":"Ron Sussex & Sons",
    "wof:placetype":"venue"
},
  "geometry": {"coordinates":[-4.1483159065,50.9527168274],"type":"Point"}
}