{
  "type": "Feature",
  "properties": {
    "addr:full":"89 George Street Edinburgh City of Edinburgh EH2 3EZ",
    "addr:housenumber":"89",
    "addr:postcode":"eh2 3ez",
    "addr:street":"George Street",
    "iso:country":"GB",
    "sg:address":"89 George Street",
    "sg:city":"Edinburgh",
    "sg:classifiers":[
        {
            "category":"Home & Garden",
            "subcategory":"Hardware",
            "type":"Retail Goods"
        }
    ],
    "sg:phone":"+44 131 225 7381",
    "sg:postcode":"EH2 3EZ",
    "sg:province":"City of Edinburgh",
    "wof:name":"James Gray & Son Ironmongers & Electricians Ltd.",
    "wof:placetype":"venue"
},
  "geometry": {"coordinates":[-3.20193,55.95293],"type":"Point"}
}