{
  "type": "Feature",
  "properties": {
    "iso:country":"GB",
    "sg:address":"Shuthonger",
    "sg:city":"Tewkesbury",
    "sg:classifiers":[
        {
            "category":"Professional",
            "subcategory":"Detective & Security Services",
            "type":"Services"
        }
    ],
    "sg:phone":"+44 1684 298585",
    "sg:postcode":"GL20 6ES",
    "sg:province":"Gloucestershire",
    "sg:tags":[
        "equipment"
    ],
    "wof:name":"Eriksons Ltd.",
    "wof:placetype":"venue"
},
  "geometry": {"coordinates":[-2.1657140255,52.0168647766],"type":"Point"}
}