{
  "type": "Feature",
  "properties": {
    "iso:country":"GB",
    "sg:address":"Main Street, North Sunderland",
    "sg:city":"Seahouses",
    "sg:classifiers":[
        {
            "category":"Education",
            "subcategory":"School",
            "type":"Public Place"
        }
    ],
    "sg:phone":"+44 1665 720923",
    "sg:postcode":"NE68 7UE",
    "sg:province":"Northumberland",
    "sg:tags":[
        "local",
        "authority"
    ],
    "wof:name":"Seahouses County First School",
    "wof:placetype":"venue"
},
  "geometry": {"coordinates":[-1.652386,55.582481],"type":"Point"}
}