{
  "type": "Feature",
  "properties": {
    "iso:country":"GB",
    "sg:address":"Eastboro Way",
    "sg:city":"Nuneaton",
    "sg:classifiers":[
        {
            "category":"Military Area",
            "subcategory":"Army Base",
            "type":"Public Place"
        },
        {
            "category":"Building & Trades",
            "subcategory":"Construction",
            "type":"Services"
        }
    ],
    "sg:postcode":"CV11 4PZ",
    "sg:province":"Leicestershire",
    "sg:tags":[
        "joinery",
        "centre"
    ],
    "wof:name":"Kearnes,Jim,",
    "wof:placetype":"venue"
},
  "geometry": {"coordinates":[-1.4567840099,52.5119781494],"type":"Point"}
}