{
  "type": "Feature",
  "properties": {
    "iso:country":"GB",
    "sg:address":"31 St Johns Street",
    "sg:city":"Bury St Edmunds",
    "sg:classifiers":[
        {
            "category":"Education",
            "subcategory":"Special Training",
            "type":"Public Place"
        }
    ],
    "sg:phone":"+44 1284 700640",
    "sg:postcode":"IP33 1SN",
    "sg:province":"Suffolk",
    "sg:tags":[
        "product",
        "centre"
    ],
    "wof:name":"Cambridge & District Saddlery Courses (International) Ltd.",
    "wof:placetype":"venue"
},
  "geometry": {"coordinates":[0.71204,52.248856],"type":"Point"}
}