{
  "type": "Feature",
  "properties": {
    "addr:full":"8 Great Chapel Street London Greater London W1F 8FA",
    "addr:housenumber":"8",
    "addr:postcode":"w1f 8fa",
    "addr:street":"Great Chapel Street",
    "iso:country":"GB",
    "sg:address":"8 Great Chapel Street",
    "sg:city":"London",
    "sg:classifiers":[
        {
            "category":"Travel",
            "subcategory":"Travel Agent",
            "type":"Entertainment"
        }
    ],
    "sg:phone":"+44 20 7734 2562",
    "sg:postcode":"W1F 8FA",
    "sg:province":"Greater London",
    "wof:name":"Greekorama Travel & Tourism Ltd.",
    "wof:placetype":"venue"
},
  "geometry": {"coordinates":[-0.1342789978,51.5155258179],"type":"Point"}
}