{
  "type": "Feature",
  "properties": {
    "iso:country":"GB",
    "sg:address":"22 Main Road, Long Bennington",
    "sg:city":"Newark",
    "sg:classifiers":[
        {
            "category":"Bars & Pubs",
            "type":"Food & Drink"
        }
    ],
    "sg:phone":"+44 1400 281382",
    "sg:postcode":"NG23 5EH",
    "sg:province":"Lincolnshire",
    "sg:tags":[
        "pubs",
        "inn"
    ],
    "wof:name":"Reindeer Inn",
    "wof:placetype":"venue"
},
  "geometry": {"coordinates":[-0.756368,52.990894],"type":"Point"}
}