{
  "type": "Feature",
  "properties": {
    "iso:country":"GB",
    "sg:address":"77 Harpesford Avenue",
    "sg:city":"Virginia Water",
    "sg:classifiers":[
        {
            "category":"Building & Trades",
            "subcategory":"Construction",
            "type":"Services"
        }
    ],
    "sg:postcode":"GU25 4RG",
    "sg:province":"Surrey",
    "sg:tags":[
        "heating",
        "contractor"
    ],
    "wof:name":"Nec Building Services",
    "wof:placetype":"venue"
},
  "geometry": {"coordinates":[-0.579849,51.398891],"type":"Point"}
}