{
  "type": "Feature",
  "properties": {
    "addr:full":"62a Packhorse Road Gerrards Cross Buckinghamshire SL9 8EF",
    "addr:housenumber":"62a",
    "addr:postcode":"sl9 8ef",
    "addr:street":"Packhorse Road",
    "iso:country":"GB",
    "sg:address":"62a Packhorse Road",
    "sg:city":"Gerrards Cross",
    "sg:classifiers":[
        {
            "category":"Freight",
            "type":"Transportation"
        }
    ],
    "sg:phone":"+44 1753 893642",
    "sg:postcode":"SL9 8EF",
    "sg:province":"Buckinghamshire",
    "sg:tags":[
        "forwarders"
    ],
    "wof:name":"Corporate International Spedition Ltd",
    "wof:placetype":"venue"
},
  "geometry": {"coordinates":[-0.551997,51.589035],"type":"Point"}
}