{
  "type": "Feature",
  "properties": {
    "addr:full":"Highlands, Bridgerule Holsworthy Cornwall EX22 7EA",
    "addr:postcode":"ex22 7ea",
    "iso:country":"GB",
    "sg:address":"Highlands, Bridgerule",
    "sg:city":"Holsworthy",
    "sg:classifiers":[
        {
            "category":"Farming",
            "subcategory":"Livestock Farm",
            "type":"Manufacturing & Wholesale Goods"
        }
    ],
    "sg:postcode":"EX22 7EA",
    "sg:province":"Cornwall",
    "sg:tags":[
        "others"
    ],
    "wof:name":"Peter John Harris",
    "wof:placetype":"venue"
},
  "geometry": {"coordinates":[-4.455791,50.799919],"type":"Point"}
}