{
  "type": "Feature",
  "properties": {
    "addr:full":"772-774 High Road, Finchley London Greater London N12 9QH",
    "addr:housenumber":"772-774",
    "addr:postcode":"n12 9qh",
    "addr:street":"High Road",
    "iso:country":"GB",
    "sg:address":"772-774 High Road, Finchley",
    "sg:city":"London",
    "sg:classifiers":[
        {
            "category":"Fast Food",
            "type":"Food & Drink"
        }
    ],
    "sg:phone":"+44 20 8446 8301",
    "sg:postcode":"N12 9QH",
    "sg:province":"Greater London",
    "sg:tags":[
        "away",
        "take"
    ],
    "wof:name":"McDonalds Restaurants Ltd.",
    "wof:placetype":"venue"
},
  "geometry": {"coordinates":[-0.1765349954,51.6156044006],"type":"Point"}
}