{
  "type": "Feature",
  "properties": {
    "iso:country":"GB",
    "sg:address":"90 Duddon Road",
    "sg:city":"Askam-in-furness",
    "sg:classifiers":[
        {
            "category":"Bars & Pubs",
            "type":"Food & Drink"
        }
    ],
    "sg:phone":"+44 1229 463838",
    "sg:postcode":"LA16 7FB",
    "sg:province":"Cumbria",
    "sg:tags":[
        "pubs",
        "inn"
    ],
    "wof:name":"The London Tavern",
    "wof:placetype":"venue"
},
  "geometry": {"coordinates":[-3.207901,54.190151],"type":"Point"}
}