{
  "type": "Feature",
  "properties": {
    "iso:country":"GB",
    "sg:address":"64 Ninian Road, Roath Park",
    "sg:city":"Cardiff",
    "sg:classifiers":[
        {
            "category":"Social Services",
            "subcategory":"Retirement Home",
            "type":"Services"
        }
    ],
    "sg:postcode":"CF23 5EL",
    "sg:province":"Cardiff",
    "sg:tags":[
        "rest"
    ],
    "wof:name":"Ninian House",
    "wof:placetype":"venue"
},
  "geometry": {"coordinates":[-3.170832,51.498981],"type":"Point"}
}