{
  "type": "Feature",
  "properties": {
    "addr:full":"5 Station Road, Albrighton Wolverhampton Shropshire WV7 3QH",
    "addr:housenumber":"5",
    "addr:postcode":"wv7 3qh",
    "addr:street":"Station Road",
    "iso:country":"GB",
    "sg:address":"5 Station Road, Albrighton",
    "sg:city":"Wolverhampton",
    "sg:classifiers":[
        {
            "category":"Shopping",
            "subcategory":"Florist",
            "type":"Retail Goods"
        }
    ],
    "sg:phone":"+44 1902 373110",
    "sg:postcode":"WV7 3QH",
    "sg:province":"Shropshire",
    "wof:name":"Country Flowers",
    "wof:placetype":"venue"
},
  "geometry": {"coordinates":[-2.2780370712,52.6352615356],"type":"Point"}
}