{
  "type": "Feature",
  "properties": {
    "addr:full":"Classic House Unit 1 Stamford Street, Amblecote Stourbridge Staffordshire DY8 4HJ",
    "addr:housenumber":"unit 1",
    "addr:postcode":"dy8 4hj",
    "addr:street":"Stamford Street",
    "iso:country":"GB",
    "sg:address":"Classic House Unit 1 Stamford Street, Amblecote",
    "sg:city":"Stourbridge",
    "sg:classifiers":[
        {
            "category":"Manufacturing",
            "subcategory":"Furniture",
            "type":"Manufacturing & Wholesale Goods"
        }
    ],
    "sg:postcode":"DY8 4HJ",
    "sg:province":"Staffordshire",
    "sg:tags":[
        "mnfr",
        "upholsterer"
    ],
    "wof:name":"Coeasy Ltd.",
    "wof:placetype":"venue"
},
  "geometry": {"coordinates":[-2.151364,52.46508],"type":"Point"}
}