{
  "type": "Feature",
  "properties": {
    "iso:country":"GB",
    "sg:address":"3 Piersfield Gro",
    "sg:city":"Edinburgh",
    "sg:classifiers":[
        {
            "category":"Building & Trades",
            "subcategory":"Construction",
            "type":"Services"
        }
    ],
    "sg:postcode":"EH8 7BT",
    "sg:province":"City of Edinburgh",
    "sg:tags":[
        "roofing"
    ],
    "wof:name":"Ritchie W A Roofing & Building Contractor",
    "wof:placetype":"venue"
},
  "geometry": {"coordinates":[-3.144238,55.955551],"type":"Point"}
}