{
  "type": "Feature",
  "properties": {
    "addr:full":"Unit 22, Waymills Industrial Estate, Waymills Whitchurch Cheshire SY13 1TT",
    "addr:housenumber":"unit 22",
    "addr:postcode":"sy13 1tt",
    "addr:street":"Waymills Industrial Estate;Whitchurch",
    "iso:country":"GB",
    "sg:address":"Unit 22, Waymills Industrial Estate, Waymills",
    "sg:city":"Whitchurch",
    "sg:classifiers":[
        {
            "category":"Manufacturing",
            "subcategory":"Building Materials",
            "type":"Manufacturing & Wholesale Goods"
        }
    ],
    "sg:phone":"+44 1948 665321",
    "sg:postcode":"SY13 1TT",
    "sg:province":"Cheshire",
    "sg:tags":[
        "distributor",
        "mnfrs",
        "cement"
    ],
    "wof:name":"Bcm Grc Ltd.",
    "wof:placetype":"venue"
},
  "geometry": {"coordinates":[-2.6852090359,52.9705581665],"type":"Point"}
}