{
  "type": "Feature",
  "properties": {
    "iso:country":"GB",
    "sg:address":"Stratton House, High West Street",
    "sg:city":"Dorchester",
    "sg:classifiers":[
        {
            "category":"Utilities",
            "subcategory":"Refuse",
            "type":"Services"
        },
        {
            "category":"Government",
            "subcategory":"Office",
            "type":"Public Place"
        }
    ],
    "sg:phone":"+44 1305 251010",
    "sg:postcode":"DT1 1UZ",
    "sg:province":"Dorset",
    "sg:tags":[
        "local",
        "collection"
    ],
    "wof:name":"West Dorset District Council",
    "wof:placetype":"venue"
},
  "geometry": {"coordinates":[-2.4387340546,50.715259552],"type":"Point"}
}