{
  "type": "Feature",
  "properties": {
    "addr:full":"Unit 1 Block A Milethorn Lane Doncaster South Yorkshire DN1 2SU",
    "addr:housenumber":"unit 1 block a",
    "addr:postcode":"dn1 2su",
    "addr:street":"Milethorn Lane",
    "iso:country":"GB",
    "sg:address":"Unit 1 Block A Milethorn Lane",
    "sg:city":"Doncaster",
    "sg:classifiers":[
        {
            "category":"Home & Garden",
            "subcategory":"Hardware",
            "type":"Retail Goods"
        }
    ],
    "sg:phone":"+44 1302 325806",
    "sg:postcode":"DN1 2SU",
    "sg:province":"South Yorkshire",
    "sg:tags":[
        "retailer",
        "diy"
    ],
    "wof:name":"Hampden Group Ltd.",
    "wof:placetype":"venue"
},
  "geometry": {"coordinates":[-1.125959,53.531937],"type":"Point"}
}