{
  "type": "Feature",
  "properties": {
    "iso:country":"GB",
    "sg:address":"295 Yarm Road",
    "sg:city":"Darlington",
    "sg:classifiers":[
        {
            "category":"Cinema",
            "subcategory":"Movie Rental",
            "type":"Entertainment"
        }
    ],
    "sg:phone":"+44 1325 384620",
    "sg:postcode":"DL1 1BA",
    "sg:province":"Durham",
    "sg:tags":[
        "video",
        "library"
    ],
    "wof:name":"Blockbuster Video",
    "wof:placetype":"venue"
},
  "geometry": {"coordinates":[-1.524342,54.522369],"type":"Point"}
}