{
  "type": "Feature",
  "properties": {
    "addr:full":"3 Summer Gardens York North Yorkshire YO30 5FR",
    "addr:housenumber":"3",
    "addr:postcode":"yo30 5fr",
    "addr:street":"Summer Gardens",
    "iso:country":"GB",
    "sg:address":"3 Summer Gardens",
    "sg:city":"York",
    "sg:classifiers":[
        {
            "category":"Professional",
            "subcategory":"Engineering",
            "type":"Services"
        }
    ],
    "sg:phone":"+44 1904 782278",
    "sg:postcode":"YO30 5FR",
    "sg:province":"North Yorkshire",
    "sg:tags":[
        "contractor",
        "electrical",
        "engineer"
    ],
    "wof:name":"I D Hunter Elcetrical",
    "wof:placetype":"venue"
},
  "geometry": {"coordinates":[-1.108392,53.978012],"type":"Point"}
}