{
  "type": "Feature",
  "properties": {
    "addr:full":"16-20 South Street, Hythe Southampton Hampshire SO45 6EB",
    "addr:housenumber":"16-20",
    "addr:postcode":"so45 6eb",
    "addr:street":"South Street",
    "iso:country":"GB",
    "sg:address":"16-20 South Street, Hythe",
    "sg:city":"Southampton",
    "sg:classifiers":[
        {
            "category":"Fast Food",
            "type":"Food & Drink"
        }
    ],
    "sg:postcode":"SO45 6EB",
    "sg:province":"Hampshire",
    "sg:tags":[
        "away",
        "take"
    ],
    "wof:name":"China China Restaurant",
    "wof:placetype":"venue"
},
  "geometry": {"coordinates":[-1.3976089954,50.8674621582],"type":"Point"}
}