{
  "type": "Feature",
  "properties": {
    "iso:country":"GB",
    "sg:address":"1st Floor, Bengal Mill, Upper Helena Street",
    "sg:city":"Manchester",
    "sg:classifiers":[
        {
            "category":"Shopping",
            "subcategory":"Clothing, Apparel, & Fashions",
            "type":"Retail Goods"
        }
    ],
    "sg:phone":"+44 161 273 6356",
    "sg:postcode":"M40 7EQ",
    "sg:province":"Greater Manchester",
    "sg:tags":[
        "clothing",
        "fabric"
    ],
    "wof:name":"Karpelle Ltd.",
    "wof:placetype":"venue"
},
  "geometry": {"coordinates":[-2.211509943,53.4858016968],"type":"Point"}
}