{
  "type": "Feature",
  "properties": {
    "addr:full":"302 Caledonian Road Wishaw North Lanarkshire ML2 0HY",
    "addr:housenumber":"302",
    "addr:postcode":"ml2 0hy",
    "addr:street":"Caledonian Road",
    "iso:country":"GB",
    "sg:address":"302 Caledonian Road",
    "sg:city":"Wishaw",
    "sg:classifiers":[
        {
            "category":"Shopping",
            "subcategory":"News",
            "type":"Retail Goods"
        }
    ],
    "sg:phone":"+44 1698 372943",
    "sg:postcode":"ML2 0HY",
    "sg:province":"North Lanarkshire",
    "sg:tags":[
        "newsagent"
    ],
    "wof:name":"M & A Brothers",
    "wof:placetype":"venue"
},
  "geometry": {"coordinates":[-3.927136898,55.7692642212],"type":"Point"}
}