{
  "type": "Feature",
  "properties": {
    "iso:country":"GB",
    "sg:address":"167 Commercial Street",
    "sg:city":"Kirkcaldy",
    "sg:classifiers":[
        {
            "category":"Personal",
            "subcategory":"Beauty Salon",
            "type":"Services"
        }
    ],
    "sg:postcode":"KY1 2NS",
    "sg:province":"Fife",
    "wof:name":"S D Hair & Beauty",
    "wof:placetype":"venue"
},
  "geometry": {"coordinates":[-3.1440010071,56.1220664978],"type":"Point"}
}