{
  "type": "Feature",
  "properties": {
    "addr:full":"Unit 3, Cliffnook La Newark Nottinghamshire NG24 1LY",
    "addr:housenumber":"unit 3",
    "addr:postcode":"ng24 1ly",
    "addr:street":"Cliffnook La Newark",
    "iso:country":"GB",
    "sg:address":"Unit 3, Cliffnook La",
    "sg:city":"Newark",
    "sg:classifiers":[
        {
            "category":"Retail",
            "subcategory":"Auto Repair",
            "type":"Services"
        }
    ],
    "sg:postcode":"NG24 1LY",
    "sg:province":"Nottinghamshire",
    "sg:tags":[
        "body",
        "car"
    ],
    "wof:name":"Ridout,Mark,",
    "wof:placetype":"venue"
},
  "geometry": {"coordinates":[-0.801744,53.079575],"type":"Point"}
}