{
  "type": "Feature",
  "properties": {
    "iso:country":"GB",
    "sg:address":"59/61 Duke St",
    "sg:city":"Barrow-in-furness",
    "sg:classifiers":[
        {
            "category":"Bars & Pubs",
            "type":"Food & Drink"
        }
    ],
    "sg:postcode":"LA14 1RW",
    "sg:province":"Cumbria",
    "sg:tags":[
        "pubs",
        "inn"
    ],
    "wof:name":"Durdin,D J,",
    "wof:placetype":"venue"
},
  "geometry": {"coordinates":[-3.228636,54.112495],"type":"Point"}
}