{
  "type": "Feature",
  "properties": {
    "addr:full":"20 Victoria Road Ruislip Greater London HA4 0AB",
    "addr:housenumber":"20",
    "addr:postcode":"ha4 0ab",
    "addr:street":"Victoria Road",
    "iso:country":"GB",
    "sg:address":"20 Victoria Road",
    "sg:city":"Ruislip",
    "sg:classifiers":[
        {
            "category":"Fast Food",
            "type":"Food & Drink"
        }
    ],
    "sg:phone":"+44 1895 622227",
    "sg:postcode":"HA4 0AB",
    "sg:province":"Greater London",
    "sg:tags":[
        "away",
        "take"
    ],
    "wof:name":"Joy Balti",
    "wof:placetype":"venue"
},
  "geometry": {"coordinates":[-0.4112089872,51.5707092285],"type":"Point"}
}