{
  "type": "Feature",
  "properties": {
    "addr:full":"6 Chancel Street London Greater London SE1 0UU",
    "addr:housenumber":"6",
    "addr:postcode":"se1 0uu",
    "addr:street":"Chancel Street",
    "iso:country":"GB",
    "sg:address":"6 Chancel Street",
    "sg:city":"London",
    "sg:classifiers":[
        {
            "category":"Organizations",
            "subcategory":"Non-profit Organization",
            "type":"Services"
        }
    ],
    "sg:phone":"+44 20 7928 2076",
    "sg:postcode":"SE1 0UU",
    "sg:province":"Greater London",
    "sg:tags":[
        "organisation",
        "voluntary",
        "charity"
    ],
    "wof:name":"Make Votes Count",
    "wof:placetype":"venue"
},
  "geometry": {"coordinates":[-0.102961,51.505272],"type":"Point"}
}