{
  "type": "Feature",
  "properties": {
    "addr:full":"81 Worcester Road, Hagley Stourbridge West Midlands DY9 0LF",
    "addr:housenumber":"81",
    "addr:postcode":"dy9 0lf",
    "addr:street":"Worcester Road",
    "iso:country":"GB",
    "sg:address":"81 Worcester Road, Hagley",
    "sg:city":"Stourbridge",
    "sg:classifiers":[
        {
            "category":"Professional",
            "subcategory":"Management & Consulting",
            "type":"Services"
        }
    ],
    "sg:phone":"+44 1562 886516",
    "sg:postcode":"DY9 0LF",
    "sg:province":"West Midlands",
    "sg:tags":[
        "consultant",
        "specialist"
    ],
    "wof:name":"Natural Beauty",
    "wof:placetype":"venue"
},
  "geometry": {"coordinates":[-2.14485,52.417786],"type":"Point"}
}