{
  "type": "Feature",
  "properties": {
    "iso:country":"GB",
    "sg:address":"339 Gathurst Road, Orrell",
    "sg:city":"Wigan",
    "sg:classifiers":[
        {
            "category":"Wholesale",
            "subcategory":"Office Equipment",
            "type":"Manufacturing & Wholesale Goods"
        }
    ],
    "sg:phone":"+44 1942 228424",
    "sg:postcode":"WN5 8QE",
    "sg:province":"Lancashire",
    "sg:tags":[
        "register",
        "cash",
        "accessory"
    ],
    "wof:name":"A & M Business Equipment",
    "wof:placetype":"venue"
},
  "geometry": {"coordinates":[-2.7045059204,53.549331665],"type":"Point"}
}