{
  "type": "Feature",
  "properties": {
    "addr:full":"116 Bellegrove Road Welling Kent DA16 3QR",
    "addr:housenumber":"116",
    "addr:postcode":"da16 3qr",
    "addr:street":"Bellegrove Road",
    "iso:country":"GB",
    "sg:address":"116 Bellegrove Road",
    "sg:city":"Welling",
    "sg:classifiers":[
        {
            "category":"Home & Garden",
            "subcategory":"Household Appliances",
            "type":"Retail Goods"
        },
        {
            "category":"Retail",
            "subcategory":"Event Space",
            "type":"Services"
        }
    ],
    "sg:phone":"+44 20 8298 1878",
    "sg:postcode":"DA16 3QR",
    "sg:province":"Kent",
    "sg:tags":[
        "electrical",
        "product",
        "domestic",
        "sales"
    ],
    "wof:name":"Didi Electronics",
    "wof:placetype":"venue"
},
  "geometry": {"coordinates":[0.1007229984,51.4636993408],"type":"Point"}
}