{
  "type": "Feature",
  "properties": {
    "addr:full":"10 Market Square Ebbw Vale Blaenau Gwent NP23 4AJ",
    "addr:housenumber":"10",
    "addr:postcode":"np23 4aj",
    "addr:street":"Market Square",
    "iso:country":"GB",
    "sg:address":"10 Market Square",
    "sg:city":"Ebbw Vale",
    "sg:classifiers":[
        {
            "category":"Shopping",
            "subcategory":"Discount & Variety Stores",
            "type":"Retail Goods"
        }
    ],
    "sg:phone":"+44 1495 311218",
    "sg:postcode":"NP23 4AJ",
    "sg:province":"Blaenau Gwent",
    "sg:tags":[
        "centre"
    ],
    "wof:name":"Haven",
    "wof:placetype":"venue"
},
  "geometry": {"coordinates":[-3.1738231182,51.7984466553],"type":"Point"}
}