{
  "type": "Feature",
  "properties": {
    "addr:full":"9-15 Allan Street Arbroath Angus DD11 1EB",
    "addr:housenumber":"9-15",
    "addr:postcode":"dd11 1eb",
    "addr:street":"Allan Street",
    "iso:country":"GB",
    "sg:address":"9-15 Allan Street",
    "sg:city":"Arbroath",
    "sg:classifiers":[
        {
            "category":"Food & Beverages",
            "subcategory":"Meat & Fish",
            "type":"Retail Goods"
        },
        {
            "category":"Food & Beverages",
            "subcategory":"Groceries & Convenience Stores",
            "type":"Retail Goods"
        }
    ],
    "sg:phone":"+44 1241 872419",
    "sg:postcode":"DD11 1EB",
    "sg:province":"Angus",
    "sg:tags":[
        "shop",
        "chip"
    ],
    "wof:name":"Round O Fish Bar",
    "wof:placetype":"venue"
},
  "geometry": {"coordinates":[-2.5814299583,56.560798645],"type":"Point"}
}