{
  "type": "Feature",
  "properties": {
    "addr:full":"1 Marigold Clo Selby East Riding of Yorkshire YO8 9RF",
    "addr:housenumber":"1",
    "addr:postcode":"yo8 9rf",
    "addr:street":"Marigold Clo",
    "iso:country":"GB",
    "sg:address":"1 Marigold Clo",
    "sg:city":"Selby",
    "sg:classifiers":[
        {
            "category":"Place Of Worship",
            "type":"Public Place"
        }
    ],
    "sg:phone":"+44 1757 709660",
    "sg:postcode":"YO8 9RF",
    "sg:province":"East Riding of Yorkshire",
    "wof:name":"Selby Baptist Church",
    "wof:placetype":"venue"
},
  "geometry": {"coordinates":[-1.072363019,53.7707672119],"type":"Point"}
}