{
  "type": "Feature",
  "properties": {
    "addr:full":"5 Archers Ct, 48 Masons Hill Bromley Kent BR2 9JG",
    "addr:housenumber":"5;48",
    "addr:postcode":"br2 9jg",
    "addr:street":"Archers Ct;Masons Hill",
    "iso:country":"GB",
    "sg:address":"5 Archers Ct, 48 Masons Hill",
    "sg:city":"Bromley",
    "sg:classifiers":[
        {
            "category":"Wholesale",
            "subcategory":"Non-durable Goods",
            "type":"Manufacturing & Wholesale Goods"
        }
    ],
    "sg:phone":"+44 20 8313 3230",
    "sg:postcode":"BR2 9JG",
    "sg:province":"Kent",
    "sg:tags":[
        "carry",
        "cash"
    ],
    "wof:name":"Booker Plc",
    "wof:placetype":"venue"
},
  "geometry": {"coordinates":[0.02408,51.396389],"type":"Point"}
}