{
  "type": "Feature",
  "properties": {
    "addr:full":"Unit, 202, St. Nicholas Way Sutton Surrey SM1 1AY",
    "addr:housenumber":"202",
    "addr:postcode":"sm1 1ay",
    "addr:street":"St. Nicholas Way",
    "iso:country":"GB",
    "sg:address":"Unit, 202, St. Nicholas Way",
    "sg:city":"Sutton",
    "sg:classifiers":[
        {
            "category":"Shopping",
            "subcategory":"Clothing, Apparel, & Fashions",
            "type":"Retail Goods"
        }
    ],
    "sg:phone":"+44 20 8642 3656",
    "sg:postcode":"SM1 1AY",
    "sg:province":"Surrey",
    "sg:tags":[
        "ladieswear"
    ],
    "wof:name":"Bay Trading Co.",
    "wof:placetype":"venue"
},
  "geometry": {"coordinates":[-0.196044,51.367153],"type":"Point"}
}