{
  "type": "Feature",
  "properties": {
    "iso:country":"GB",
    "sg:address":"Unit 47, Hayhill Industrial Estate, Barrow-on-soar",
    "sg:city":"Loughborough",
    "sg:classifiers":[
        {
            "category":"Home & Garden",
            "subcategory":"Garden Supply",
            "type":"Retail Goods"
        }
    ],
    "sg:phone":"+44 1509 815335",
    "sg:postcode":"LE12 8LD",
    "sg:province":"Leicestershire",
    "sg:tags":[
        "equipment",
        "playground"
    ],
    "wof:name":"Street Design Ltd.",
    "wof:placetype":"venue"
},
  "geometry": {"coordinates":[-1.12447,52.741859],"type":"Point"}
}