{
  "type": "Feature",
  "properties": {
    "iso:country":"GB",
    "sg:address":"Unit A1 The Sidings, Station Rd, Amptill Indstl Est",
    "sg:city":"Bedford",
    "sg:classifiers":[
        {
            "category":"Professional",
            "type":"Services"
        }
    ],
    "sg:phone":"+44 1525 840800",
    "sg:postcode":"MK45 2QY",
    "sg:province":"Bedfordshire",
    "sg:tags":[
        "services",
        "belt",
        "conveyor"
    ],
    "wof:name":"Ebtech Ltd",
    "wof:placetype":"venue"
},
  "geometry": {"coordinates":[-0.4949940145,52.0279464722],"type":"Point"}
}