{
  "type": "Feature",
  "properties": {
    "iso:country":"GB",
    "sg:address":"Unit F, Meadowside Street",
    "sg:city":"Renfrew",
    "sg:classifiers":[
        {
            "category":"Bus Charters",
            "type":"Transportation"
        }
    ],
    "sg:phone":"+44 141 886 3000",
    "sg:postcode":"PA4 8SP",
    "sg:province":"Renfrewshire",
    "sg:tags":[
        "coach"
    ],
    "wof:name":"Lippen Coaches Ltd.",
    "wof:placetype":"venue"
},
  "geometry": {"coordinates":[-4.386605,55.884613],"type":"Point"}
}