{
  "type": "Feature",
  "properties": {
    "addr:full":"Unit 5 Wakering Rd Barking Essex IG11 8PD",
    "addr:housenumber":"unit 5",
    "addr:postcode":"ig11 8pd",
    "addr:street":"Wakering Rd",
    "iso:country":"GB",
    "sg:address":"Unit 5 Wakering Rd",
    "sg:city":"Barking",
    "sg:classifiers":[
        {
            "category":"Education",
            "subcategory":"Special Training",
            "type":"Public Place"
        }
    ],
    "sg:phone":"+44 20 8507 1551",
    "sg:postcode":"IG11 8PD",
    "sg:province":"Essex",
    "sg:tags":[
        "product",
        "centre"
    ],
    "wof:name":"T G B Learning East London",
    "wof:placetype":"venue"
},
  "geometry": {"coordinates":[0.080253,51.54092],"type":"Point"}
}