{
  "type": "Feature",
  "properties": {
    "iso:country":"GB",
    "sg:address":"Alder Row, West Woodlands",
    "sg:city":"Frome",
    "sg:classifiers":[
        {
            "category":"Building & Trades",
            "subcategory":"Landscaping Services",
            "type":"Services"
        },
        {
            "category":"Professional",
            "subcategory":"Engineering",
            "type":"Services"
        }
    ],
    "sg:postcode":"BA11 5EN",
    "sg:province":"Somerset",
    "sg:tags":[
        "horticultural"
    ],
    "wof:name":"R S Bevan",
    "wof:placetype":"venue"
},
  "geometry": {"coordinates":[-2.318369,51.191845],"type":"Point"}
}