{
  "type": "Feature",
  "properties": {
    "iso:country":"GB",
    "sg:address":"11 Eyam Gro",
    "sg:city":"Stockport",
    "sg:classifiers":[
        {
            "category":"Professional",
            "subcategory":"Engineering",
            "type":"Services"
        }
    ],
    "sg:phone":"+44 161 456 6125",
    "sg:postcode":"SK2 7LZ",
    "sg:province":"Cheshire",
    "sg:tags":[
        "contractor",
        "electrical",
        "engineer"
    ],
    "wof:name":"G & S Electrical Services",
    "wof:placetype":"venue"
},
  "geometry": {"coordinates":[-2.126755,53.389561],"type":"Point"}
}