{
  "type": "Feature",
  "properties": {
    "addr:full":"121 High Street, Hurstpierpoint Hassocks East Sussex BN6 9PU",
    "addr:housenumber":"121",
    "addr:postcode":"bn6 9pu",
    "addr:street":"High Street",
    "iso:country":"GB",
    "sg:address":"121 High Street, Hurstpierpoint",
    "sg:city":"Hassocks",
    "sg:classifiers":[
        {
            "category":"Home & Garden",
            "subcategory":"Garden Supply",
            "type":"Retail Goods"
        }
    ],
    "sg:phone":"+44 1273 835442",
    "sg:postcode":"BN6 9PU",
    "sg:province":"East Sussex",
    "sg:tags":[
        "ornament"
    ],
    "wof:name":"Chris W Smith",
    "wof:placetype":"venue"
},
  "geometry": {"coordinates":[-0.1755629927,50.9327774048],"type":"Point"}
}