{
  "type": "Feature",
  "properties": {
    "addr:full":"York Road, Boroughbridge York North Yorkshire YO51 9EW",
    "addr:postcode":"yo51 9ew",
    "addr:street":"York Road",
    "iso:country":"GB",
    "sg:address":"York Road, Boroughbridge",
    "sg:city":"York",
    "sg:classifiers":[
        {
            "category":"Social Services",
            "type":"Services"
        }
    ],
    "sg:phone":"+44 1423 322189",
    "sg:postcode":"YO51 9EW",
    "sg:province":"North Yorkshire",
    "wof:name":"Springfield Garth",
    "wof:placetype":"venue"
},
  "geometry": {"coordinates":[-1.391323,54.092697],"type":"Point"}
}