{
  "type": "Feature",
  "properties": {
    "addr:full":"34 New Rd, Aston Clinton Aylesbury Buckinghamshire HP22 5JD",
    "addr:housenumber":"34",
    "addr:postcode":"hp22 5jd",
    "addr:street":"New Rd",
    "iso:country":"GB",
    "sg:address":"34 New Rd, Aston Clinton",
    "sg:city":"Aylesbury",
    "sg:classifiers":[
        {
            "category":"Building & Trades",
            "subcategory":"Construction",
            "type":"Services"
        }
    ],
    "sg:phone":"+44 1296 631722",
    "sg:postcode":"HP22 5JD",
    "sg:province":"Buckinghamshire",
    "sg:tags":[
        "dry",
        "lining",
        "plasterers",
        "screeders"
    ],
    "wof:name":"Knight,Dave,",
    "wof:placetype":"venue"
},
  "geometry": {"coordinates":[-0.7187139988,51.8032913208],"type":"Point"}
}