{
  "type": "Feature",
  "properties": {
    "addr:full":"Finsbury Business Centre, 40 Bowling Green Lane London Greater London EC1R 0NE",
    "addr:housenumber":"40",
    "addr:postcode":"ec1r 0ne",
    "addr:street":"Bowling Green Lane",
    "iso:country":"GB",
    "sg:address":"Finsbury Business Centre, 40 Bowling Green Lane",
    "sg:city":"London",
    "sg:classifiers":[
        {
            "category":"Shopping",
            "subcategory":"Event Tickets",
            "type":"Retail Goods"
        }
    ],
    "sg:postcode":"EC1R 0NE",
    "sg:province":"Greater London",
    "sg:tags":[
        "agency"
    ],
    "wof:name":"Good Time Tickets Ltd",
    "wof:placetype":"venue"
},
  "geometry": {"coordinates":[-0.10731,51.524731],"type":"Point"}
}