{
  "type": "Feature",
  "properties": {
    "addr:full":"38 Strutton Ground London Greater London SW1P 2HR",
    "addr:housenumber":"38",
    "addr:postcode":"sw1p 2hr",
    "addr:street":"Strutton Ground",
    "iso:country":"GB",
    "sg:address":"38 Strutton Ground",
    "sg:city":"London",
    "sg:classifiers":[
        {
            "category":"Food & Beverages",
            "subcategory":"Meat & Fish",
            "type":"Retail Goods"
        }
    ],
    "sg:phone":"+44 20 7799 2844",
    "sg:postcode":"SW1P 2HR",
    "sg:province":"Greater London",
    "sg:tags":[
        "chip"
    ],
    "wof:name":"The Laughing Halibut",
    "wof:placetype":"venue"
},
  "geometry": {"coordinates":[-0.133945,51.49667],"type":"Point"}
}