{
  "type": "Feature",
  "properties": {
    "addr:full":"Blue Circle, Holborough Works Snodland Kent ME6 5PH",
    "addr:postcode":"me6 5ph",
    "addr:street":"Blue;Snodland",
    "iso:country":"GB",
    "sg:address":"Blue Circle, Holborough Works",
    "sg:city":"Snodland",
    "sg:classifiers":[
        {
            "category":"Freight",
            "type":"Transportation"
        }
    ],
    "sg:phone":"+44 1634 245375",
    "sg:postcode":"ME6 5PH",
    "sg:province":"Kent",
    "sg:tags":[
        "haulage",
        "road"
    ],
    "wof:name":"M & S Turner & Son",
    "wof:placetype":"venue"
},
  "geometry": {"coordinates":[0.4461649954,51.3270263672],"type":"Point"}
}