{
  "type": "Feature",
  "properties": {
    "iso:country":"GB",
    "sg:address":"111 Fleet St",
    "sg:city":"London",
    "sg:classifiers":[
        {
            "category":"Retail",
            "subcategory":"Photofinishing",
            "type":"Services"
        }
    ],
    "sg:postcode":"EC4A 2AB",
    "sg:province":"Greater London",
    "sg:tags":[
        "photographic",
        "processor"
    ],
    "wof:name":"Formbourne Ltd",
    "wof:placetype":"venue"
},
  "geometry": {"coordinates":[-0.105061,51.514309],"type":"Point"}
}