{
  "type": "Feature",
  "properties": {
    "iso:country":"GB",
    "sg:address":"Bath Road, Peasedown St John",
    "sg:city":"Bath",
    "sg:classifiers":[
        {
            "category":"Retail",
            "subcategory":"Auto Repair",
            "type":"Services"
        }
    ],
    "sg:phone":"+44 1761 439539",
    "sg:postcode":"BA2 8DN",
    "sg:province":"Somerset",
    "sg:tags":[
        "modification",
        "garage"
    ],
    "wof:name":"R & S Motors",
    "wof:placetype":"venue"
},
  "geometry": {"coordinates":[-2.38075,51.326221],"type":"Point"}
}