{
  "type": "Feature",
  "properties": {
    "iso:country":"GB",
    "sg:address":"41 Studholme Crescent, Penwortham",
    "sg:city":"Preston",
    "sg:classifiers":[
        {
            "category":"Home & Garden",
            "subcategory":"Carpets & Floor Coverings",
            "type":"Retail Goods"
        }
    ],
    "sg:phone":"+44 1772 741582",
    "sg:postcode":"PR1 9NE",
    "sg:province":"Lancashire",
    "sg:tags":[
        "cleaner",
        "upholstery"
    ],
    "wof:name":"Ray Evans",
    "wof:placetype":"venue"
},
  "geometry": {"coordinates":[-2.707758,53.735889],"type":"Point"}
}