{
  "type": "Feature",
  "properties": {
    "iso:country":"GB",
    "sg:address":"Unit 50, Sandford Lane, Kennington",
    "sg:city":"Oxford",
    "sg:classifiers":[
        {
            "category":"Professional",
            "subcategory":"Management & Consulting",
            "type":"Services"
        }
    ],
    "sg:phone":"+44 1865 326677",
    "sg:postcode":"OX1 5RP",
    "sg:province":"Oxfordshire",
    "sg:tags":[
        "consultant",
        "business"
    ],
    "wof:name":"Viewpoint Management Systems",
    "wof:placetype":"venue"
},
  "geometry": {"coordinates":[-1.236072,51.706306],"type":"Point"}
}