{
  "type": "Feature",
  "properties": {
    "addr:full":"Midland Bank Chambers, Hick Lane Batley West Yorkshire WF17 5TD",
    "addr:postcode":"wf17 5td",
    "addr:street":"Hick Lane",
    "iso:country":"GB",
    "sg:address":"Midland Bank Chambers, Hick Lane",
    "sg:city":"Batley",
    "sg:classifiers":[
        {
            "category":"Professional",
            "subcategory":"Accounting & Tax Preparation",
            "type":"Services"
        }
    ],
    "sg:phone":"+44 1924 441244",
    "sg:postcode":"WF17 5TD",
    "sg:province":"West Yorkshire",
    "sg:tags":[
        "accountant"
    ],
    "wof:name":"Milnes & Gooder",
    "wof:placetype":"venue"
},
  "geometry": {"coordinates":[-1.654499,53.726421],"type":"Point"}
}