{
  "type": "Feature",
  "properties": {
    "iso:country":"GB",
    "sg:address":"Burston House, Rectory Road, Burston",
    "sg:city":"Diss",
    "sg:classifiers":[
        {
            "category":"Health Services",
            "subcategory":"Nursing And Care Facility",
            "type":"Services"
        }
    ],
    "sg:phone":"+44 1379 741562",
    "sg:postcode":"IP22 5TU",
    "sg:province":"Norfolk",
    "sg:tags":[
        "mental",
        "centre"
    ],
    "wof:name":"Care Prospective",
    "wof:placetype":"venue"
},
  "geometry": {"coordinates":[1.157524,52.422829],"type":"Point"}
}