{
  "type": "Feature",
  "properties": {
    "iso:country":"GB",
    "sg:address":"14 Bridge Street",
    "sg:city":"Newhaven",
    "sg:classifiers":[
        {
            "category":"Retail",
            "subcategory":"Repair Shop",
            "type":"Services"
        }
    ],
    "sg:phone":"+44 1273 487070",
    "sg:postcode":"BN9 9PJ",
    "sg:province":"East Sussex",
    "sg:tags":[
        "radio",
        "television",
        "video"
    ],
    "wof:name":"Teleka Electronic Services Ltd.",
    "wof:placetype":"venue"
},
  "geometry": {"coordinates":[0.051553,50.794224],"type":"Point"}
}