{
  "type": "Feature",
  "properties": {
    "iso:country":"GB",
    "sg:address":"10-12 Southgate",
    "sg:city":"Elland",
    "sg:classifiers":[
        {
            "category":"Building & Trades",
            "subcategory":"Cleaning & Sanitation",
            "type":"Services"
        },
        {
            "category":"Building & Trades",
            "subcategory":"Construction",
            "type":"Services"
        }
    ],
    "sg:phone":"+44 1422 370599",
    "sg:postcode":"HX5 0PS",
    "sg:province":"West Yorkshire",
    "sg:tags":[
        "dry",
        "control",
        "damp",
        "rot",
        "builder"
    ],
    "wof:name":"Building Services Intercare",
    "wof:placetype":"venue"
},
  "geometry": {"coordinates":[-1.838149,53.686031],"type":"Point"}
}