{
  "type": "Feature",
  "properties": {
    "iso:country":"GB",
    "sg:address":"Queen St",
    "sg:city":"Aberdeen",
    "sg:classifiers":[
        {
            "category":"Place Of Worship",
            "type":"Public Place"
        }
    ],
    "sg:phone":"+44 1224 644719",
    "sg:postcode":"AB10 1AP",
    "sg:province":"Aberdeen City",
    "wof:name":"Greyfriars John Knox",
    "wof:placetype":"venue"
},
  "geometry": {"coordinates":[-2.09483,57.149639],"type":"Point"}
}