{
  "type": "Feature",
  "properties": {
    "addr:full":"Ace Ct, Warren St Tenby Pembrokeshire SA70 7JY",
    "addr:postcode":"sa70 7jy",
    "addr:street":"Ace Ct Warren St",
    "iso:country":"GB",
    "sg:address":"Ace Ct, Warren St",
    "sg:city":"Tenby",
    "sg:classifiers":[
        {
            "category":"Shopping",
            "subcategory":"Used Merchandise",
            "type":"Retail Goods"
        }
    ],
    "sg:phone":"+44 1834 842284",
    "sg:postcode":"SA70 7JY",
    "sg:province":"Pembrokeshire",
    "sg:tags":[
        "shop",
        "second-hand"
    ],
    "wof:name":"Secondhand Shop The",
    "wof:placetype":"venue"
},
  "geometry": {"coordinates":[-4.7049241066,51.6724281311],"type":"Point"}
}