{
  "type": "Feature",
  "properties": {
    "addr:full":"33a Franklin Road Harrogate North Yorkshire HG1 5ED",
    "addr:housenumber":"33a",
    "addr:postcode":"hg1 5ed",
    "addr:street":"Franklin Road",
    "iso:country":"GB",
    "sg:address":"33a Franklin Road",
    "sg:city":"Harrogate",
    "sg:classifiers":[
        {
            "category":"Retail",
            "subcategory":"Auto Repair",
            "type":"Services"
        }
    ],
    "sg:phone":"+44 1423 565895",
    "sg:postcode":"HG1 5ED",
    "sg:province":"North Yorkshire",
    "sg:tags":[
        "modification",
        "garage",
        "related"
    ],
    "wof:name":"D C D Motors",
    "wof:placetype":"venue"
},
  "geometry": {"coordinates":[-1.538842,53.997459],"type":"Point"}
}