{
  "type": "Feature",
  "properties": {
    "addr:full":"11 Woodside Road Poole Dorset BH14 9JH",
    "addr:housenumber":"11",
    "addr:postcode":"bh14 9jh",
    "addr:street":"Woodside Road",
    "iso:country":"GB",
    "sg:address":"11 Woodside Road",
    "sg:city":"Poole",
    "sg:classifiers":[
        {
            "category":"Health Services",
            "subcategory":"Podiatrist",
            "type":"Services"
        }
    ],
    "sg:phone":"+44 1202 742365",
    "sg:postcode":"BH14 9JH",
    "sg:province":"Dorset",
    "sg:tags":[
        "podiatrists",
        "chiropodist"
    ],
    "wof:name":"Adrian Robert Grier",
    "wof:placetype":"venue"
},
  "geometry": {"coordinates":[-1.9404040575,50.7221679688],"type":"Point"}
}