{
  "type": "Feature",
  "properties": {
    "addr:full":"10 Bernards Close, Cuddington Aylesbury Buckinghamshire HP18 0AJ",
    "addr:housenumber":"10",
    "addr:postcode":"hp18 0aj",
    "addr:street":"Bernards Close",
    "iso:country":"GB",
    "sg:address":"10 Bernards Close, Cuddington",
    "sg:city":"Aylesbury",
    "sg:classifiers":[
        {
            "category":"Communications",
            "subcategory":"Film & Video Production",
            "type":"Services"
        },
        {
            "category":"Manufacturing",
            "subcategory":"Glass & Minerals",
            "type":"Manufacturing & Wholesale Goods"
        }
    ],
    "sg:phone":"+44 1844 292813",
    "sg:postcode":"HP18 0AJ",
    "sg:province":"Buckinghamshire",
    "sg:tags":[
        "product",
        "supp",
        "leaded",
        "window",
        "vessel",
        "manufacturer"
    ],
    "wof:name":"D BOWMAN",
    "wof:placetype":"venue"
},
  "geometry": {"coordinates":[-0.9292039871,51.7928390503],"type":"Point"}
}