{
  "type": "Feature",
  "properties": {
    "iso:country":"GB",
    "sg:address":"43 Kingsley Close, Shaw",
    "sg:city":"Newbury",
    "sg:classifiers":[
        {
            "category":"Retail",
            "subcategory":"Repair Shop",
            "type":"Services"
        }
    ],
    "sg:postcode":"RG14 2EB",
    "sg:province":"Berkshire",
    "sg:tags":[
        "maintenance"
    ],
    "wof:name":"Chris Cook",
    "wof:placetype":"venue"
},
  "geometry": {"coordinates":[-1.312762022,51.4149017334],"type":"Point"}
}