{
  "type": "Feature",
  "properties": {
    "iso:country":"GB",
    "sg:address":"Nicholls Farm, Redbourne",
    "sg:city":"St Albans",
    "sg:classifiers":[
        {
            "category":"Retail",
            "subcategory":"Auto Repair",
            "type":"Services"
        }
    ],
    "sg:postcode":"AL3 7JH",
    "sg:province":"Hertfordshire",
    "sg:tags":[
        "modification",
        "garage"
    ],
    "wof:name":"Halls Vehicle Services",
    "wof:placetype":"venue"
},
  "geometry": {"coordinates":[-0.4162699878,51.8047904968],"type":"Point"}
}