{
  "type": "Feature",
  "properties": {
    "iso:country":"GB",
    "sg:address":"Mountneys Farm, Chase La, Kingswood",
    "sg:city":"Wotton-under-edge",
    "sg:classifiers":[
        {
            "category":"Farming",
            "subcategory":"Farm",
            "type":"Manufacturing & Wholesale Goods"
        }
    ],
    "sg:postcode":"GL12 8JY",
    "sg:province":"Gloucestershire",
    "sg:tags":[
        "mixed",
        "crop"
    ],
    "wof:name":"Bishop,M E,",
    "wof:placetype":"venue"
},
  "geometry": {"coordinates":[-2.351894,51.638985],"type":"Point"}
}