{
  "type": "Feature",
  "properties": {
    "iso:country":"GB",
    "sg:address":"Purslow, Clunbury",
    "sg:city":"Craven Arms",
    "sg:classifiers":[
        {
            "category":"Bars & Pubs",
            "type":"Food & Drink"
        }
    ],
    "sg:phone":"+44 1588 660541",
    "sg:postcode":"SY7 0HJ",
    "sg:province":"Herefordshire",
    "sg:tags":[
        "pubs",
        "inn"
    ],
    "wof:name":"Hundred House Inn",
    "wof:placetype":"venue"
},
  "geometry": {"coordinates":[-2.92603,52.418682],"type":"Point"}
}