{
  "type": "Feature",
  "properties": {
    "addr:full":"44 Vicarage Lane Blackpool Lancashire FY4 4EQ",
    "addr:housenumber":"44",
    "addr:postcode":"fy4 4eq",
    "addr:street":"Vicarage Lane",
    "iso:country":"GB",
    "sg:address":"44 Vicarage Lane",
    "sg:city":"Blackpool",
    "sg:classifiers":[
        {
            "category":"Home & Garden",
            "subcategory":"Building Materials",
            "type":"Retail Goods"
        }
    ],
    "sg:postcode":"FY4 4EQ",
    "sg:province":"Lancashire",
    "sg:tags":[
        "insulation",
        "installers"
    ],
    "wof:name":"G C Insulation Services",
    "wof:placetype":"venue"
},
  "geometry": {"coordinates":[-3.0273780823,53.8017425537],"type":"Point"}
}