{
  "type": "Feature",
  "properties": {
    "addr:full":"Unit 7, Robert Court, Barbot Hall Industrial Estate Rotherham South Yorkshire S62 6DR",
    "addr:housenumber":"unit 7;estate",
    "addr:postcode":"s62 6dr",
    "addr:street":"Robert Court Barbot Hall Industrial;South",
    "iso:country":"GB",
    "sg:address":"Unit 7, Robert Court, Barbot Hall Industrial Estate",
    "sg:city":"Rotherham",
    "sg:classifiers":[
        {
            "category":"Professional",
            "subcategory":"Art Services",
            "type":"Services"
        }
    ],
    "sg:phone":"+44 1709 528007",
    "sg:postcode":"S62 6DR",
    "sg:province":"South Yorkshire",
    "sg:tags":[
        "graphic",
        "designer"
    ],
    "wof:name":"Department X Advertising",
    "wof:placetype":"venue"
},
  "geometry": {"coordinates":[-1.351999,53.447498],"type":"Point"}
}