{
  "type": "Feature",
  "properties": {
    "addr:full":"170 Fairholme Cres Hayes Greater London UB4 8QY",
    "addr:housenumber":"170",
    "addr:postcode":"ub4 8qy",
    "addr:street":"Fairholme Cres",
    "iso:country":"GB",
    "sg:address":"170 Fairholme Cres",
    "sg:city":"Hayes",
    "sg:classifiers":[
        {
            "category":"Professional",
            "subcategory":"Accounting & Tax Preparation",
            "type":"Services"
        }
    ],
    "sg:postcode":"UB4 8QY",
    "sg:province":"Greater London",
    "sg:tags":[
        "accountant"
    ],
    "wof:name":"Ballinger,J E, Book Keeping & Accountanc",
    "wof:placetype":"venue"
},
  "geometry": {"coordinates":[-0.417782,51.530575],"type":"Point"}
}