{
  "type": "Feature",
  "properties": {
    "addr:full":"42 The Pallasades Birmingham West Midlands B2 4XH",
    "addr:housenumber":"42",
    "addr:postcode":"4xh",
    "addr:street":"The Pallasades",
    "iso:country":"GB",
    "sg:address":"42 The Pallasades",
    "sg:city":"Birmingham",
    "sg:classifiers":[
        {
            "category":"Professional",
            "subcategory":"Computer Services",
            "type":"Services"
        }
    ],
    "sg:phone":"+44 121 643 0337",
    "sg:postcode":"B2 4XH",
    "sg:province":"West Midlands",
    "sg:tags":[
        "system",
        "software"
    ],
    "wof:name":"Computer Junkie Ltd.",
    "wof:placetype":"venue"
},
  "geometry": {"coordinates":[-1.89867,52.4781],"type":"Point"}
}