{
  "type": "Feature",
  "properties": {
    "addr:full":"52a Portland Avenue Hove East Sussex BN3 5NG",
    "addr:housenumber":"52a",
    "addr:postcode":"bn3 5ng",
    "addr:street":"Portland Avenue",
    "iso:country":"GB",
    "sg:address":"52a Portland Avenue",
    "sg:city":"Hove",
    "sg:classifiers":[
        {
            "category":"Building & Trades",
            "subcategory":"Plumbing",
            "type":"Services"
        }
    ],
    "sg:postcode":"BN3 5NG",
    "sg:province":"East Sussex",
    "sg:tags":[
        "heating"
    ],
    "wof:name":"Mark D Stevens",
    "wof:placetype":"venue"
},
  "geometry": {"coordinates":[-0.195188,50.834129],"type":"Point"}
}