{
  "type": "Feature",
  "properties": {
    "iso:country":"GB",
    "sg:address":"5 Broomhall Bank",
    "sg:city":"Edinburgh",
    "sg:classifiers":[
        {
            "category":"Professional",
            "subcategory":"Printing & Photocopies",
            "type":"Services"
        }
    ],
    "sg:phone":"+44 131 334 4513",
    "sg:postcode":"EH12 7PH",
    "sg:province":"City of Edinburgh",
    "sg:tags":[
        "typesetter"
    ],
    "wof:name":"E.P.G",
    "wof:placetype":"venue"
},
  "geometry": {"coordinates":[-3.293,55.942093],"type":"Point"}
}