{
  "type": "Feature",
  "properties": {
    "iso:country":"GB",
    "sg:address":"90-92a Forest Road",
    "sg:city":"London",
    "sg:classifiers":[
        {
            "category":"Shopping",
            "type":"Retail Goods"
        }
    ],
    "sg:postcode":"E17 6JQ",
    "sg:province":"Greater London",
    "sg:tags":[
        "part",
        "accessory"
    ],
    "wof:name":"V R Stolworthy & Co. Ltd.",
    "wof:placetype":"venue"
},
  "geometry": {"coordinates":[-0.0347240008,51.5877876282],"type":"Point"}
}