{
  "type": "Feature",
  "properties": {
    "addr:full":"57 Adelaide Road High Wycombe Buckinghamshire HP13 6UW",
    "addr:housenumber":"57",
    "addr:postcode":"hp13 6uw",
    "addr:street":"Adelaide Road",
    "iso:country":"GB",
    "sg:address":"57 Adelaide Road",
    "sg:city":"High Wycombe",
    "sg:classifiers":[
        {
            "category":"Military Area",
            "subcategory":"Air Force Base",
            "type":"Public Place"
        }
    ],
    "sg:phone":"+44 1494 444414",
    "sg:postcode":"HP13 6UW",
    "sg:province":"Buckinghamshire",
    "sg:tags":[
        "taxi",
        "hire",
        "private"
    ],
    "wof:name":"Eagle Taxis",
    "wof:placetype":"venue"
},
  "geometry": {"coordinates":[-0.7335289717,51.6392555237],"type":"Point"}
}