{
  "type": "Feature",
  "properties": {
    "addr:full":"75 Sandown Lodge, Avenue Road Epsom Surrey KT18 7QU",
    "addr:housenumber":"75",
    "addr:postcode":"kt18 7qu",
    "addr:street":"Lodge Avenue Road",
    "iso:country":"GB",
    "sg:address":"75 Sandown Lodge, Avenue Road",
    "sg:city":"Epsom",
    "sg:classifiers":[
        {
            "category":"Organizations",
            "subcategory":"Community Association",
            "type":"Services"
        }
    ],
    "sg:phone":"+44 1372 722243",
    "sg:postcode":"KT18 7QU",
    "sg:province":"Surrey",
    "sg:tags":[
        "domestic",
        "staff"
    ],
    "wof:name":"D J Newman",
    "wof:placetype":"venue"
},
  "geometry": {"coordinates":[-0.26741,51.32674],"type":"Point"}
}