{
  "type": "Feature",
  "properties": {
    "addr:full":"Spencer House, Manor Farm Road Reading Berkshire RG2 0JN",
    "addr:postcode":"rg2 0jn",
    "addr:street":"Manor Farm Road",
    "iso:country":"GB",
    "sg:address":"Spencer House, Manor Farm Road",
    "sg:city":"Reading",
    "sg:classifiers":[
        {
            "category":"Utilities",
            "subcategory":"Water",
            "type":"Services"
        },
        {
            "category":"Recreation",
            "subcategory":"Fishing",
            "type":"Entertainment"
        }
    ],
    "sg:phone":"+44 118 923 6222",
    "sg:postcode":"RG2 0JN",
    "sg:province":"Berkshire",
    "sg:tags":[
        "angling"
    ],
    "wof:name":"The Water Quality Centre",
    "wof:placetype":"venue"
},
  "geometry": {"coordinates":[-0.968994,51.430264],"type":"Point"}
}