{
  "type": "Feature",
  "properties": {
    "iso:country":"GB",
    "sg:address":"176 High St",
    "sg:city":"Ruislip",
    "sg:classifiers":[
        {
            "category":"Restaurant",
            "type":"Food & Drink"
        }
    ],
    "sg:phone":"+44 1895 634388",
    "sg:postcode":"HA4 8LJ",
    "sg:province":"Greater London",
    "wof:name":"Wimpy Bar",
    "wof:placetype":"venue"
},
  "geometry": {"coordinates":[-0.4228250086,51.5723495483],"type":"Point"}
}