{
  "type": "Feature",
  "properties": {
    "addr:full":"34a Hurlingham Rd Fulham Greater London SW6 3RF",
    "addr:housenumber":"34a",
    "addr:postcode":"sw6 3rf",
    "addr:street":"Hurlingham Rd",
    "iso:country":"GB",
    "sg:address":"34a Hurlingham Rd",
    "sg:city":"Fulham",
    "sg:classifiers":[
        {
            "category":"Health Services",
            "subcategory":"Doctor",
            "type":"Services"
        }
    ],
    "sg:phone":"+44 20 7736 0095",
    "sg:postcode":"SW6 3RF",
    "sg:province":"Greater London",
    "sg:tags":[
        "practitioners"
    ],
    "wof:name":"Atkinson, J A",
    "wof:placetype":"venue"
},
  "geometry": {"coordinates":[-0.2018190026,51.4706192017],"type":"Point"}
}