{
  "type": "Feature",
  "properties": {
    "iso:country":"GB",
    "sg:address":"73 Trinity View, Caerleon",
    "sg:city":"Newport",
    "sg:classifiers":[
        {
            "category":"Professional",
            "subcategory":"Management & Consulting",
            "type":"Services"
        }
    ],
    "sg:postcode":"NP18 3SW",
    "sg:province":"Monmouthshire",
    "sg:tags":[
        "consultant",
        "business"
    ],
    "wof:name":"Jilicrinic Business Development Consulta",
    "wof:placetype":"venue"
},
  "geometry": {"coordinates":[-2.95921,51.616547],"type":"Point"}
}