{
  "type": "Feature",
  "properties": {
    "iso:country":"GB",
    "sg:address":"Unit 5, Vale La, Hartcliffe Way, Bedminster",
    "sg:city":"Bristol",
    "sg:classifiers":[
        {
            "category":"Home & Garden",
            "subcategory":"Building Materials",
            "type":"Retail Goods"
        }
    ],
    "sg:phone":"+44 117 953 3060",
    "sg:postcode":"BS3 5SD",
    "sg:province":"City of Bristol",
    "sg:tags":[
        "insulation",
        "installers"
    ],
    "wof:name":"Crown Insulation Energy Services Ltd",
    "wof:placetype":"venue"
},
  "geometry": {"coordinates":[-2.6051421165,51.4270782471],"type":"Point"}
}