{
  "type": "Feature",
  "properties": {
    "addr:full":"Wonastow Road Industrial Estate West Monmouth Gloucestershire NP25 5JA",
    "addr:postcode":"np25 5ja",
    "addr:street":"Wonastow Road Industrial Estate West",
    "iso:country":"GB",
    "sg:address":"Wonastow Road Industrial Estate West",
    "sg:city":"Monmouth",
    "sg:classifiers":[
        {
            "category":"Home & Garden",
            "subcategory":"Garden Supply",
            "type":"Retail Goods"
        },
        {
            "category":"Home & Garden",
            "subcategory":"Hardware",
            "type":"Retail Goods"
        }
    ],
    "sg:phone":"+44 1600 715520",
    "sg:postcode":"NP25 5JA",
    "sg:province":"Gloucestershire",
    "sg:tags":[
        "lawnmowers",
        "sales",
        "machinery"
    ],
    "wof:name":"Monnow Mowers & Machinery Ltd",
    "wof:placetype":"venue"
},
  "geometry": {"coordinates":[-2.7229290009,51.8092193604],"type":"Point"}
}