{
  "type": "Feature",
  "properties": {
    "addr:full":"Audley Road Birmingham West Midlands B33 9HY",
    "addr:postcode":"b33 9hy",
    "addr:street":"Audley Road",
    "iso:country":"GB",
    "sg:address":"Audley Road",
    "sg:city":"Birmingham",
    "sg:classifiers":[
        {
            "category":"Education",
            "subcategory":"School",
            "type":"Public Place"
        },
        {
            "category":"Government",
            "subcategory":"Office",
            "type":"Public Place"
        }
    ],
    "sg:phone":"+44 121 783 3139",
    "sg:postcode":"B33 9HY",
    "sg:province":"West Midlands",
    "sg:tags":[
        "local",
        "authority"
    ],
    "wof:name":"Audley Junior School",
    "wof:placetype":"venue"
},
  "geometry": {"coordinates":[-1.806784,52.487724],"type":"Point"}
}