{
  "type": "Feature",
  "properties": {
    "iso:country":"GB",
    "sg:address":"8 Williams Rd",
    "sg:city":"Chichester",
    "sg:classifiers":[
        {
            "category":"Building & Trades",
            "subcategory":"Construction",
            "type":"Services"
        }
    ],
    "sg:phone":"+44 1243 573330",
    "sg:postcode":"PO18 8JS",
    "sg:province":"West Sussex",
    "sg:tags":[
        "decorator",
        "painter"
    ],
    "wof:name":"D H Smith",
    "wof:placetype":"venue"
},
  "geometry": {"coordinates":[-0.84739,50.841553],"type":"Point"}
}