{
  "type": "Feature",
  "properties": {
    "addr:full":"45 High Street Cranbrook Kent TN17 3EE",
    "addr:housenumber":"45",
    "addr:postcode":"tn17 3ee",
    "addr:street":"High Street",
    "iso:country":"GB",
    "sg:address":"45 High Street",
    "sg:city":"Cranbrook",
    "sg:classifiers":[
        {
            "category":"Professional",
            "subcategory":"Management & Consulting",
            "type":"Services"
        }
    ],
    "sg:postcode":"TN17 3EE",
    "sg:province":"Kent",
    "sg:tags":[
        "consultant",
        "specialist"
    ],
    "wof:name":"Jeneleen Beauty Salon",
    "wof:placetype":"venue"
},
  "geometry": {"coordinates":[0.5339490175,51.0962715149],"type":"Point"}
}