{
  "type": "Feature",
  "properties": {
    "addr:full":"Parkview Business Centre, 6 Woodside Place Glasgow Glasgow City G3 7QF",
    "addr:housenumber":"6",
    "addr:postcode":"g3 7qf",
    "addr:street":"Woodside Place",
    "iso:country":"GB",
    "sg:address":"Parkview Business Centre, 6 Woodside Place",
    "sg:city":"Glasgow",
    "sg:classifiers":[
        {
            "category":"Manufacturing",
            "subcategory":"Buildings",
            "type":"Manufacturing & Wholesale Goods"
        }
    ],
    "sg:phone":"+44 141 353 3890",
    "sg:postcode":"G3 7QF",
    "sg:province":"Glasgow City",
    "sg:tags":[
        "framed",
        "timber"
    ],
    "wof:name":"Century Homes",
    "wof:placetype":"venue"
},
  "geometry": {"coordinates":[-4.2734799385,55.8670883179],"type":"Point"}
}