{
  "type": "Feature",
  "properties": {
    "addr:full":"Lolesworth Close London Greater London E1 6LR",
    "addr:postcode":"e1 6lr",
    "addr:street":"Lolesworth Close",
    "iso:country":"GB",
    "sg:address":"Lolesworth Close",
    "sg:city":"London",
    "sg:classifiers":[
        {
            "category":"Education",
            "subcategory":"Preschool",
            "type":"Public Place"
        }
    ],
    "sg:phone":"+44 20 7247 1281",
    "sg:postcode":"E1 6LR",
    "sg:province":"Greater London",
    "sg:tags":[
        "pre-school",
        "playgroups"
    ],
    "wof:name":"The Attlee Adventure Playground",
    "wof:placetype":"venue"
},
  "geometry": {"coordinates":[-0.0737939999,51.5179443359],"type":"Point"}
}