{
  "type": "Feature",
  "properties": {
    "addr:full":"117 Newland Street Witham Essex CM8 1BE",
    "addr:housenumber":"117",
    "addr:postcode":"cm8 1be",
    "addr:street":"Newland Street",
    "iso:country":"GB",
    "sg:address":"117 Newland Street",
    "sg:city":"Witham",
    "sg:classifiers":[
        {
            "category":"Fast Food",
            "type":"Food & Drink"
        }
    ],
    "sg:phone":"+44 1376 515335",
    "sg:postcode":"CM8 1BE",
    "sg:province":"Essex",
    "sg:tags":[
        "away",
        "take"
    ],
    "wof:name":"The Witham House",
    "wof:placetype":"venue"
},
  "geometry": {"coordinates":[0.6377130151,51.7977752686],"type":"Point"}
}