{
  "type": "Feature",
  "properties": {
    "iso:country":"GB",
    "sg:address":"14 Phoenix Ct, Norreys Dr",
    "sg:city":"Maidenhead",
    "sg:classifiers":[
        {
            "category":"Building & Trades",
            "subcategory":"Landscaping Services",
            "type":"Services"
        }
    ],
    "sg:phone":"+44 1628 624202",
    "sg:postcode":"SL6 4BS",
    "sg:province":"Berkshire",
    "sg:tags":[
        "landscape",
        "contractor"
    ],
    "wof:name":"R & S Groundworks",
    "wof:placetype":"venue"
},
  "geometry": {"coordinates":[-0.734855,51.509117],"type":"Point"}
}