{
  "type": "Feature",
  "properties": {
    "iso:country":"GB",
    "sg:address":"Wreakes Lane",
    "sg:city":"Dronfield",
    "sg:classifiers":[
        {
            "category":"Retail",
            "subcategory":"Storage",
            "type":"Services"
        }
    ],
    "sg:phone":"+44 1246 290590",
    "sg:postcode":"S18 1PN",
    "sg:province":"Derbyshire",
    "sg:tags":[
        "household",
        "removal"
    ],
    "wof:name":"Dronfield Storage Centre",
    "wof:placetype":"venue"
},
  "geometry": {"coordinates":[-1.477594018,53.308719635],"type":"Point"}
}