{
  "type": "Feature",
  "properties": {
    "iso:country":"GB",
    "sg:address":"The Old Chapel, Cote Lane",
    "sg:city":"Sheffield",
    "sg:classifiers":[
        {
            "category":"Building & Trades",
            "subcategory":"Construction",
            "type":"Services"
        }
    ],
    "sg:phone":"+44 114 288 4127",
    "sg:postcode":"S35 7AE",
    "sg:province":"South Yorkshire",
    "sg:tags":[
        "joinery"
    ],
    "wof:name":"C R Joinery",
    "wof:placetype":"venue"
},
  "geometry": {"coordinates":[-1.56259,53.50209],"type":"Point"}
}