{
  "type": "Feature",
  "properties": {
    "addr:full":"91 New Barn Lane Cheltenham Gloucestershire GL52 3LF",
    "addr:housenumber":"91",
    "addr:postcode":"gl52 3lf",
    "addr:street":"New Barn Lane",
    "iso:country":"GB",
    "sg:address":"91 New Barn Lane",
    "sg:city":"Cheltenham",
    "sg:classifiers":[
        {
            "category":"Retail",
            "subcategory":"Auto Repair",
            "type":"Services"
        }
    ],
    "sg:phone":"+44 1242 245698",
    "sg:postcode":"GL52 3LF",
    "sg:province":"Gloucestershire",
    "sg:tags":[
        "body",
        "car"
    ],
    "wof:name":"B P Motor Body Builders & Engineers",
    "wof:placetype":"venue"
},
  "geometry": {"coordinates":[-2.061229,51.914463],"type":"Point"}
}