{
  "type": "Feature",
  "properties": {
    "addr:full":"1-9 Borough Arcade Hyde Cheshire SK14 2AA",
    "addr:housenumber":"1-9",
    "addr:postcode":"sk14 2aa",
    "addr:street":"Borough",
    "iso:country":"GB",
    "sg:address":"1-9 Borough Arcade",
    "sg:city":"Hyde",
    "sg:classifiers":[
        {
            "category":"Sports & Exercise",
            "subcategory":"Gym",
            "type":"Entertainment"
        }
    ],
    "sg:phone":"+44 161 367 9026",
    "sg:postcode":"SK14 2AA",
    "sg:province":"Cheshire",
    "sg:tags":[
        "fitness",
        "health",
        "centre"
    ],
    "wof:name":"Powerhouse Health & Fitness Centre",
    "wof:placetype":"venue"
},
  "geometry": {"coordinates":[-2.079304,53.451817],"type":"Point"}
}