{
  "type": "Feature",
  "properties": {
    "iso:country":"GB",
    "sg:address":"9 Long Ayres, Caldecotte",
    "sg:city":"Milton Keynes",
    "sg:classifiers":[
        {
            "category":"Government",
            "subcategory":"Post Office",
            "type":"Public Place"
        }
    ],
    "sg:postcode":"MK7 8HF",
    "sg:province":"Buckinghamshire",
    "sg:tags":[
        "messenger",
        "courier"
    ],
    "wof:name":"Pat Murray",
    "wof:placetype":"venue"
},
  "geometry": {"coordinates":[-0.697405,52.010513],"type":"Point"}
}