{
  "type": "Feature",
  "properties": {
    "addr:full":"362 Cowbridge Rd, East Canton Cardiff Cardiff CF5 1HE",
    "addr:housenumber":"362",
    "addr:postcode":"cf5 1he",
    "addr:street":"Cowbridge Rd",
    "iso:country":"GB",
    "sg:address":"362 Cowbridge Rd, East Canton",
    "sg:city":"Cardiff",
    "sg:classifiers":[
        {
            "category":"Professional",
            "subcategory":"Printing & Photocopies",
            "type":"Services"
        }
    ],
    "sg:postcode":"CF5 1HE",
    "sg:province":"Cardiff",
    "sg:tags":[
        "printer"
    ],
    "wof:name":"Elite Print",
    "wof:placetype":"venue"
},
  "geometry": {"coordinates":[-3.213299036,51.4827728271],"type":"Point"}
}