{
  "type": "Feature",
  "properties": {
    "addr:full":"14 Orchard Road Wirral Merseyside CH46 8TS",
    "addr:housenumber":"14",
    "addr:postcode":"ch46 8ts",
    "addr:street":"Orchard Road",
    "iso:country":"GB",
    "sg:address":"14 Orchard Road",
    "sg:city":"Wirral",
    "sg:classifiers":[
        {
            "category":"Organizations",
            "subcategory":"Non-profit Organization",
            "type":"Services"
        }
    ],
    "sg:phone":"+44 151 677 6767",
    "sg:postcode":"CH46 8TS",
    "sg:province":"Merseyside",
    "sg:tags":[
        "organisation",
        "voluntary",
        "charity"
    ],
    "wof:name":"Intercessors for Britain",
    "wof:placetype":"venue"
},
  "geometry": {"coordinates":[-3.108375,53.402214],"type":"Point"}
}