{
  "type": "Feature",
  "properties": {
    "addr:full":"22 St Christophers Place London Greater London W1U 1NP",
    "addr:housenumber":"22",
    "addr:postcode":"w1u 1np",
    "addr:street":"St Christophers Place",
    "iso:country":"GB",
    "sg:address":"22 St Christophers Place",
    "sg:city":"London",
    "sg:classifiers":[
        {
            "category":"Restaurant",
            "type":"Food & Drink"
        }
    ],
    "sg:phone":"+44 20 7486 0777",
    "sg:postcode":"W1U 1NP",
    "sg:province":"Greater London",
    "wof:name":"Chaopraya Restaurant",
    "wof:placetype":"venue"
},
  "geometry": {"coordinates":[-0.150564,51.515656],"type":"Point"}
}