{
  "type": "Feature",
  "properties": {
    "addr:full":"Manchester Road Stockport Cheshire SK4 1TY",
    "addr:postcode":"sk4 1ty",
    "addr:street":"Manchester Road",
    "iso:country":"GB",
    "sg:address":"Manchester Road",
    "sg:city":"Stockport",
    "sg:classifiers":[
        {
            "category":"Bars & Pubs",
            "type":"Food & Drink"
        }
    ],
    "sg:phone":"+44 161 480 6626",
    "sg:postcode":"SK4 1TY",
    "sg:province":"Cheshire",
    "sg:tags":[
        "pubs",
        "inn"
    ],
    "wof:name":"The Navigation Inn",
    "wof:placetype":"venue"
},
  "geometry": {"coordinates":[-2.167987,53.422859],"type":"Point"}
}