{
  "type": "Feature",
  "properties": {
    "addr:full":"13 Slades Drive Chislehurst Kent BR7 6JU",
    "addr:housenumber":"13",
    "addr:postcode":"br7 6ju",
    "addr:street":"Slades Drive",
    "iso:country":"GB",
    "sg:address":"13 Slades Drive",
    "sg:city":"Chislehurst",
    "sg:classifiers":[
        {
            "category":"Retail",
            "subcategory":"Repair Shop",
            "type":"Services"
        }
    ],
    "sg:phone":"+44 20 8467 8393",
    "sg:postcode":"BR7 6JU",
    "sg:province":"Kent",
    "sg:tags":[
        "maintenance"
    ],
    "wof:name":"J M C Plastering & Building",
    "wof:placetype":"venue"
},
  "geometry": {"coordinates":[0.074923,51.42823],"type":"Point"}
}