{
  "type": "Feature",
  "properties": {
    "addr:full":"103 Park Street London Greater London W1K 7JN",
    "addr:housenumber":"103",
    "addr:postcode":"w1k 7jn",
    "addr:street":"Park Street",
    "iso:country":"GB",
    "sg:address":"103 Park Street",
    "sg:city":"London",
    "sg:classifiers":[
        {
            "category":"Real Estate",
            "subcategory":"Real Estate Agent",
            "type":"Services"
        }
    ],
    "sg:phone":"+44 20 7493 5311",
    "sg:postcode":"W1K 7JN",
    "sg:province":"Greater London",
    "wof:name":"Sellar Properties (Western) Ltd.",
    "wof:placetype":"venue"
},
  "geometry": {"coordinates":[-0.1555670053,51.5124282837],"type":"Point"}
}