{
  "type": "Feature",
  "properties": {
    "iso:country":"GB",
    "sg:address":"Knightsford Ho Church Rd, Wombourne",
    "sg:city":"Wolverhampton",
    "sg:classifiers":[
        {
            "category":"Military Area",
            "subcategory":"Air Force Base",
            "type":"Public Place"
        }
    ],
    "sg:phone":"+44 1902 892299",
    "sg:postcode":"WV5 9EX",
    "sg:province":"Shropshire",
    "sg:tags":[
        "magnet"
    ],
    "wof:name":"H.D.L Magnetic Systems Ltd",
    "wof:placetype":"venue"
},
  "geometry": {"coordinates":[-2.187339,52.53685],"type":"Point"}
}