{
  "type": "Feature",
  "properties": {
    "addr:full":"Rochdale Road Sowerby Bridge West Yorkshire HX6 3BB",
    "addr:postcode":"hx6 3bb",
    "addr:street":"Rochdale Road",
    "iso:country":"GB",
    "sg:address":"Rochdale Road",
    "sg:city":"Sowerby Bridge",
    "sg:classifiers":[
        {
            "category":"Sports & Exercise",
            "subcategory":"Bowling",
            "type":"Entertainment"
        }
    ],
    "sg:phone":"+44 1422 833379",
    "sg:postcode":"HX6 3BB",
    "sg:province":"West Yorkshire",
    "wof:name":"West End Bowling Club",
    "wof:placetype":"venue"
},
  "geometry": {"coordinates":[-1.922279,53.702351],"type":"Point"}
}