{
  "type": "Feature",
  "properties": {
    "addr:full":"37 Market Place Cockermouth Cumbria CA13 9NF",
    "addr:housenumber":"37",
    "addr:postcode":"ca13 9nf",
    "addr:street":"Market Place",
    "iso:country":"GB",
    "sg:address":"37 Market Place",
    "sg:city":"Cockermouth",
    "sg:classifiers":[
        {
            "category":"Shopping",
            "subcategory":"Bicycles & Sporting Goods",
            "type":"Retail Goods"
        },
        {
            "category":"Sports & Exercise",
            "subcategory":"Sports Center",
            "type":"Entertainment"
        }
    ],
    "sg:phone":"+44 1900 823071",
    "sg:postcode":"CA13 9NF",
    "sg:province":"Cumbria",
    "sg:tags":[
        "shop",
        "sale"
    ],
    "wof:name":"Fellside Sports",
    "wof:placetype":"venue"
},
  "geometry": {"coordinates":[-3.3613359928,54.6641273499],"type":"Point"}
}