{
  "type": "Feature",
  "properties": {
    "iso:country":"GB",
    "sg:address":"Ince Power Station, Ash Rd",
    "sg:city":"Chester",
    "sg:classifiers":[
        {
            "category":"Utilities",
            "subcategory":"Electric",
            "type":"Services"
        }
    ],
    "sg:phone":"+44 1928 723511",
    "sg:postcode":"CH2 4LF",
    "sg:province":"Cheshire",
    "sg:tags":[
        "electricity"
    ],
    "wof:name":"Powergen PLC",
    "wof:placetype":"venue"
},
  "geometry": {"coordinates":[-2.826079,53.284302],"type":"Point"}
}