{
  "type": "Feature",
  "properties": {
    "addr:full":"176 Bellenden Road London Greater London SE15 4BW",
    "addr:housenumber":"176",
    "addr:postcode":"se15 4bw",
    "addr:street":"Bellenden Road",
    "iso:country":"GB",
    "sg:address":"176 Bellenden Road",
    "sg:city":"London",
    "sg:classifiers":[
        {
            "category":"Fast Food",
            "type":"Food & Drink"
        }
    ],
    "sg:phone":"+44 20 7639 5830",
    "sg:postcode":"SE15 4BW",
    "sg:province":"Greater London",
    "sg:tags":[
        "away",
        "take"
    ],
    "wof:name":"Lotus House",
    "wof:placetype":"venue"
},
  "geometry": {"coordinates":[-0.0727119967,51.4672241211],"type":"Point"}
}