{
  "type": "Feature",
  "properties": {
    "iso:country":"GB",
    "sg:address":"229-231 Shields Road",
    "sg:city":"Newcastle-upon-tyne",
    "sg:classifiers":[
        {
            "category":"Banks & Credit Unions",
            "subcategory":"Financial Services",
            "type":"Services"
        }
    ],
    "sg:phone":"+44 191 276 4903",
    "sg:postcode":"NE6 1DQ",
    "sg:province":"Tyne and Wear",
    "sg:tags":[
        "consultant",
        "finance"
    ],
    "wof:name":"London Scottish Finance Ltd",
    "wof:placetype":"venue"
},
  "geometry": {"coordinates":[-1.577436,54.977806],"type":"Point"}
}