{
  "type": "Feature",
  "properties": {
    "addr:full":"Heol Y Nant, Llannon Llanelli Carmarthenshire SA14 6AE",
    "addr:postcode":"sa14 6ae",
    "addr:street":"Heol Y",
    "iso:country":"GB",
    "sg:address":"Heol Y Nant, Llannon",
    "sg:city":"Llanelli",
    "sg:classifiers":[
        {
            "category":"Education",
            "subcategory":"School",
            "type":"Public Place"
        }
    ],
    "sg:phone":"+44 1269 841563",
    "sg:postcode":"SA14 6AE",
    "sg:province":"Carmarthenshire",
    "sg:tags":[
        "local",
        "authority"
    ],
    "wof:name":"Llannon Primary School",
    "wof:placetype":"venue"
},
  "geometry": {"coordinates":[-4.1177887917,51.7543067932],"type":"Point"}
}