{
  "type": "Feature",
  "properties": {
    "iso:country":"GB",
    "sg:address":"St Columb Major",
    "sg:city":"St Columb",
    "sg:classifiers":[
        {
            "category":"Recreation",
            "subcategory":"Campground",
            "type":"Entertainment"
        }
    ],
    "sg:phone":"+44 1637 880482",
    "sg:postcode":"TR9 6JH",
    "sg:province":"Cornwall",
    "sg:tags":[
        "caravan",
        "park"
    ],
    "wof:name":"Tregatillian Caravan Park",
    "wof:placetype":"venue"
},
  "geometry": {"coordinates":[-4.936884,50.43256],"type":"Point"}
}