{
  "type": "Feature",
  "properties": {
    "iso:country":"GB",
    "sg:address":"Solway Estate",
    "sg:city":"Maryport",
    "sg:classifiers":[
        {
            "category":"Professional",
            "subcategory":"Engineering",
            "type":"Services"
        }
    ],
    "sg:phone":"+44 1900 814949",
    "sg:postcode":"CA15 8NJ",
    "sg:province":"Cumbria",
    "sg:tags":[
        "contractor",
        "electrical",
        "engineer"
    ],
    "wof:name":"Cumbria Control Systems",
    "wof:placetype":"venue"
},
  "geometry": {"coordinates":[-3.5191910267,54.6866645813],"type":"Point"}
}