{
  "type": "Feature",
  "properties": {
    "iso:country":"GB",
    "sg:address":"76 Uxbridge Road",
    "sg:city":"London",
    "sg:classifiers":[
        {
            "category":"Personal",
            "subcategory":"Barber",
            "type":"Services"
        }
    ],
    "sg:phone":"+44 20 8810 0760",
    "sg:postcode":"W7 3SU",
    "sg:province":"Greater London",
    "sg:tags":[
        "men's",
        "gents",
        "hairdresser"
    ],
    "wof:name":"Tony's Hair Stylist",
    "wof:placetype":"venue"
},
  "geometry": {"coordinates":[-0.335724,51.508648],"type":"Point"}
}