{
  "type": "Feature",
  "properties": {
    "iso:country":"GB",
    "sg:address":"53a Bayham Street",
    "sg:city":"London",
    "sg:classifiers":[
        {
            "category":"Professional",
            "subcategory":"Art Services",
            "type":"Services"
        }
    ],
    "sg:phone":"+44 118 981 9891",
    "sg:postcode":"NW1 0AA",
    "sg:province":"Greater London",
    "sg:tags":[
        "photographer"
    ],
    "wof:name":"Steven Harper Associates",
    "wof:placetype":"venue"
},
  "geometry": {"coordinates":[-0.1393869966,51.5367584229],"type":"Point"}
}