{
  "type": "Feature",
  "properties": {
    "addr:full":"212 Western Road Southall Greater London UB2 5JW",
    "addr:housenumber":"212",
    "addr:postcode":"ub2 5jw",
    "addr:street":"Western Road",
    "iso:country":"GB",
    "sg:address":"212 Western Road",
    "sg:city":"Southall",
    "sg:classifiers":[
        {
            "category":"Wholesale",
            "subcategory":"Non-durable Goods",
            "type":"Manufacturing & Wholesale Goods"
        }
    ],
    "sg:phone":"+44 20 8574 4898",
    "sg:postcode":"UB2 5JW",
    "sg:province":"Greater London",
    "sg:tags":[
        "carry",
        "cash"
    ],
    "wof:name":"Western Cash and Carry",
    "wof:placetype":"venue"
},
  "geometry": {"coordinates":[-0.3922150135,51.4988098145],"type":"Point"}
}