{
  "type": "Feature",
  "properties": {
    "iso:country":"GB",
    "sg:address":"Portview Road",
    "sg:city":"Bristol",
    "sg:classifiers":[
        {
            "category":"Food & Beverages",
            "subcategory":"Groceries & Convenience Stores",
            "type":"Retail Goods"
        }
    ],
    "sg:phone":"+44 117 982 2222",
    "sg:postcode":"BS11 9JF",
    "sg:province":"City of Bristol",
    "wof:name":"Portview Store",
    "wof:placetype":"venue"
},
  "geometry": {"coordinates":[-2.6986839771,51.4996986389],"type":"Point"}
}