{
  "type": "Feature",
  "properties": {
    "addr:full":"Shorrock Lane Blackburn Lancashire BB2 4DA",
    "addr:postcode":"bb2 4da",
    "addr:street":"Shorrock Lane",
    "iso:country":"GB",
    "sg:address":"Shorrock Lane",
    "sg:city":"Blackburn",
    "sg:classifiers":[
        {
            "category":"Social Services",
            "type":"Services"
        }
    ],
    "sg:phone":"+44 1254 55826",
    "sg:postcode":"BB2 4DA",
    "sg:province":"Lancashire",
    "wof:name":"Laneside Home for the Elderly",
    "wof:placetype":"venue"
},
  "geometry": {"coordinates":[-2.5049090385,53.7344512939],"type":"Point"}
}