{
  "type": "Feature",
  "properties": {
    "iso:country":"GB",
    "sg:address":"Royal Exchange House, 100 Queen Street",
    "sg:city":"Glasgow",
    "sg:classifiers":[
        {
            "category":"Professional",
            "subcategory":"Advertising",
            "type":"Services"
        }
    ],
    "sg:phone":"+44 141 243 7450",
    "sg:postcode":"G1 3DL",
    "sg:province":"Glasgow City",
    "sg:tags":[
        "agency"
    ],
    "wof:name":"The Monster Board",
    "wof:placetype":"venue"
},
  "geometry": {"coordinates":[-4.251931,55.859859],"type":"Point"}
}