{
  "type": "Feature",
  "properties": {
    "addr:full":"586 Great Horton Road Bradford West Yorkshire BD7 3EU",
    "addr:housenumber":"586",
    "addr:postcode":"bd7 3eu",
    "addr:street":"Great Horton Road",
    "iso:country":"GB",
    "sg:address":"586 Great Horton Road",
    "sg:city":"Bradford",
    "sg:classifiers":[
        {
            "category":"Restaurant",
            "type":"Food & Drink"
        }
    ],
    "sg:phone":"+44 1274 502521",
    "sg:postcode":"BD7 3EU",
    "sg:province":"West Yorkshire",
    "sg:tags":[
        "indian",
        "-"
    ],
    "wof:name":"KEZ'S TANDOORI RESTAURANT",
    "wof:placetype":"venue"
},
  "geometry": {"coordinates":[-1.783313036,53.7820854187],"type":"Point"}
}