{
  "type": "Feature",
  "properties": {
    "iso:country":"GB",
    "sg:address":"1 Hook Cottage, Hook Rd, Wimblington",
    "sg:city":"March",
    "sg:classifiers":[
        {
            "category":"Building & Trades",
            "subcategory":"Landscaping Services",
            "type":"Services"
        },
        {
            "category":"Building & Trades",
            "subcategory":"Construction",
            "type":"Services"
        }
    ],
    "sg:phone":"+44 1354 740401",
    "sg:postcode":"PE15 0QL",
    "sg:province":"Cambridgeshire",
    "sg:tags":[
        "specialised",
        "landscape",
        "contractor"
    ],
    "wof:name":"Demeter Design Ltd",
    "wof:placetype":"venue"
},
  "geometry": {"coordinates":[0.08618,52.508385],"type":"Point"}
}