{
  "type": "Feature",
  "properties": {
    "addr:full":"23 Boyton Rd Hornsey Greater London N8 7AZ",
    "addr:housenumber":"23",
    "addr:postcode":"n8 7az",
    "addr:street":"Boyton Rd",
    "iso:country":"GB",
    "sg:address":"23 Boyton Rd",
    "sg:city":"Hornsey",
    "sg:classifiers":[
        {
            "category":"Social Services",
            "subcategory":"Adult Care",
            "type":"Services"
        },
        {
            "category":"Social Services",
            "subcategory":"Retirement Home",
            "type":"Services"
        }
    ],
    "sg:phone":"+44 20 8348 6973",
    "sg:postcode":"N8 7AZ",
    "sg:province":"Greater London",
    "sg:tags":[
        "housing",
        "sheltered",
        "accommodation"
    ],
    "wof:name":"Bedale House",
    "wof:placetype":"venue"
},
  "geometry": {"coordinates":[-0.1208920032,51.5901603699],"type":"Point"}
}