{
  "type": "Feature",
  "properties": {
    "addr:full":"2 Bolton Road Luton Bedfordshire LU1 3HR",
    "addr:housenumber":"2",
    "addr:postcode":"lu1 3hr",
    "addr:street":"Bolton Road",
    "iso:country":"GB",
    "sg:address":"2 Bolton Road",
    "sg:city":"Luton",
    "sg:classifiers":[
        {
            "category":"Shopping",
            "subcategory":"Stationery & Office Supplies",
            "type":"Retail Goods"
        }
    ],
    "sg:postcode":"LU1 3HR",
    "sg:province":"Bedfordshire",
    "sg:tags":[
        "box",
        "carton"
    ],
    "wof:name":"Osonpack",
    "wof:placetype":"venue"
},
  "geometry": {"coordinates":[-0.4072099924,51.8773155212],"type":"Point"}
}