{
  "type": "Feature",
  "properties": {
    "addr:full":"Cherrytree, Stoven Beccles Norfolk NR34 8ER",
    "addr:postcode":"nr34 8er",
    "addr:street":"Cherrytree Stoven",
    "iso:country":"GB",
    "sg:address":"Cherrytree, Stoven",
    "sg:city":"Beccles",
    "sg:classifiers":[
        {
            "category":"Bars & Pubs",
            "type":"Food & Drink"
        }
    ],
    "sg:phone":"+44 1502 575308",
    "sg:postcode":"NR34 8ER",
    "sg:province":"Norfolk",
    "sg:tags":[
        "pubs",
        "inn"
    ],
    "wof:name":"Cherrytree Restaurant",
    "wof:placetype":"venue"
},
  "geometry": {"coordinates":[1.5953500271,52.3780708313],"type":"Point"}
}