{
  "type": "Feature",
  "properties": {
    "iso:country":"GB",
    "sg:address":"10 Kent St",
    "sg:city":"Preston",
    "sg:classifiers":[
        {
            "category":"Professional",
            "subcategory":"Engineering",
            "type":"Services"
        }
    ],
    "sg:phone":"+44 1772 257919",
    "sg:postcode":"PR1 1PE",
    "sg:province":"Lancashire",
    "sg:tags":[
        "contractor",
        "electrical",
        "engineer"
    ],
    "wof:name":"Brian Smith & Son",
    "wof:placetype":"venue"
},
  "geometry": {"coordinates":[-2.6989290714,53.7670249939],"type":"Point"}
}