{
  "type": "Feature",
  "properties": {
    "addr:full":"123 George St Richmond Greater London TW9 1HE",
    "addr:housenumber":"123",
    "addr:postcode":"tw9 1he",
    "addr:street":"George St",
    "iso:country":"GB",
    "sg:address":"123 George St",
    "sg:city":"Richmond",
    "sg:classifiers":[
        {
            "category":"Arts & Performance",
            "subcategory":"Music",
            "type":"Entertainment"
        }
    ],
    "sg:phone":"+44 20 8958 9891",
    "sg:postcode":"TW9 1HE",
    "sg:province":"Greater London",
    "sg:tags":[
        "mobile",
        "disco"
    ],
    "wof:name":"Ace Discos & Equipment Hire",
    "wof:placetype":"venue"
},
  "geometry": {"coordinates":[-0.3052290082,51.4603996277],"type":"Point"}
}