{
  "type": "Feature",
  "properties": {
    "addr:full":"The Smiddy, Ecclesmachan Broxburn City of Edinburgh EH52 6NG",
    "addr:postcode":"eh52 6ng",
    "addr:street":"Ecclesmachan",
    "iso:country":"GB",
    "sg:address":"The Smiddy, Ecclesmachan",
    "sg:city":"Broxburn",
    "sg:classifiers":[
        {
            "category":"Professional",
            "subcategory":"Secretarial Services",
            "type":"Services"
        }
    ],
    "sg:phone":"+44 1506 858070",
    "sg:postcode":"EH52 6NG",
    "sg:province":"City of Edinburgh",
    "wof:name":"Mackin Office Services",
    "wof:placetype":"venue"
},
  "geometry": {"coordinates":[-3.5086789131,55.9421081543],"type":"Point"}
}