{
  "type": "Feature",
  "properties": {
    "addr:full":"78 Fulbourn Road Cambridge Cambridgeshire CB1 9JN",
    "addr:housenumber":"78",
    "addr:postcode":"cb1 9jn",
    "addr:street":"Fulbourn Road",
    "iso:country":"GB",
    "sg:address":"78 Fulbourn Road",
    "sg:city":"Cambridge",
    "sg:classifiers":[
        {
            "category":"Building & Trades",
            "subcategory":"Construction",
            "type":"Services"
        }
    ],
    "sg:postcode":"CB1 9JN",
    "sg:province":"Cambridgeshire",
    "sg:tags":[
        "builder"
    ],
    "wof:name":"Leeds Builders",
    "wof:placetype":"venue"
},
  "geometry": {"coordinates":[0.180103,52.182964],"type":"Point"}
}