{
  "type": "Feature",
  "properties": {
    "iso:country":"GB",
    "sg:address":"22-24 South St, Tarring",
    "sg:city":"Worthing",
    "sg:classifiers":[
        {
            "category":"Manufacturing",
            "subcategory":"Textiles",
            "type":"Manufacturing & Wholesale Goods"
        }
    ],
    "sg:phone":"+44 1903 203020",
    "sg:postcode":"BN14 7LH",
    "sg:province":"West Sussex",
    "sg:tags":[
        "made-up"
    ],
    "wof:name":"Beautiful Beds",
    "wof:placetype":"venue"
},
  "geometry": {"coordinates":[-0.39194,50.819042],"type":"Point"}
}