{
  "type": "Feature",
  "properties": {
    "addr:full":"21-35 Warner Drive, Springwood Industrial Estate Braintree Essex CM7 2YW",
    "addr:housenumber":"21-35",
    "addr:postcode":"cm7 2yw",
    "addr:street":"Warner Drive;Industrial Estate",
    "iso:country":"GB",
    "sg:address":"21-35 Warner Drive, Springwood Industrial Estate",
    "sg:city":"Braintree",
    "sg:classifiers":[
        {
            "category":"Manufacturing",
            "subcategory":"Electronics",
            "type":"Manufacturing & Wholesale Goods"
        }
    ],
    "sg:postcode":"CM7 2YW",
    "sg:province":"Essex",
    "sg:tags":[
        "printed",
        "circuit"
    ],
    "wof:name":"Knopp Electronic Services Ltd.",
    "wof:placetype":"venue"
},
  "geometry": {"coordinates":[0.5346440077,51.8791503906],"type":"Point"}
}