{
  "type": "Feature",
  "properties": {
    "addr:full":"7 Market Square, Alyth Blairgowrie Angus PH11 8AA",
    "addr:housenumber":"7",
    "addr:postcode":"ph11 8aa",
    "addr:street":"Market Square Alyth",
    "iso:country":"GB",
    "sg:address":"7 Market Square, Alyth",
    "sg:city":"Blairgowrie",
    "sg:classifiers":[
        {
            "category":"Banks & Credit Unions",
            "subcategory":"Bank",
            "type":"Services"
        }
    ],
    "sg:phone":"+44 1828 632388",
    "sg:postcode":"PH11 8AA",
    "sg:province":"Angus",
    "wof:name":"The Royal Bank of Scotland Plc",
    "wof:placetype":"venue"
},
  "geometry": {"coordinates":[-3.2307,56.622768],"type":"Point"}
}