{
  "type": "Feature",
  "properties": {
    "addr:full":"12 Albany Road Cardiff Cardiff CF24 3RP",
    "addr:housenumber":"12",
    "addr:postcode":"cf24 3rp",
    "addr:street":"Albany Road",
    "iso:country":"GB",
    "sg:address":"12 Albany Road",
    "sg:city":"Cardiff",
    "sg:classifiers":[
        {
            "category":"Professional",
            "subcategory":"Lawyer & Legal Services",
            "type":"Services"
        }
    ],
    "sg:phone":"+44 29 2046 0000",
    "sg:postcode":"CF24 3RP",
    "sg:province":"Cardiff",
    "sg:tags":[
        "solicitor"
    ],
    "wof:name":"Paul Malekin & Co",
    "wof:placetype":"venue"
},
  "geometry": {"coordinates":[-3.1701738834,51.4928283691],"type":"Point"}
}