{
  "type": "Feature",
  "properties": {
    "addr:full":"9 Hay Lane, Kingsbury London Greater London NW9 0NH",
    "addr:housenumber":"9",
    "addr:postcode":"nw9 0nh",
    "addr:street":"Hay Lane",
    "iso:country":"GB",
    "sg:address":"9 Hay Lane, Kingsbury",
    "sg:city":"London",
    "sg:classifiers":[
        {
            "category":"Shopping",
            "subcategory":"News",
            "type":"Retail Goods"
        }
    ],
    "sg:postcode":"NW9 0NH",
    "sg:province":"Greater London",
    "sg:tags":[
        "newsagent"
    ],
    "wof:name":"S N B News",
    "wof:placetype":"venue"
},
  "geometry": {"coordinates":[-0.2634209991,51.58826828],"type":"Point"}
}