{
  "type": "Feature",
  "properties": {
    "iso:country":"GB",
    "sg:address":"Highway Park, Catsfield Road",
    "sg:city":"Battle",
    "sg:classifiers":[
        {
            "category":"Home & Garden",
            "subcategory":"Home Furnishings",
            "type":"Retail Goods"
        }
    ],
    "sg:postcode":"TN33 9JA",
    "sg:province":"East Sussex",
    "sg:tags":[
        "pipe",
        "fitting"
    ],
    "wof:name":"Ashworth Frazer (Northern) Ltd.",
    "wof:placetype":"venue"
},
  "geometry": {"coordinates":[0.44803,50.896187],"type":"Point"}
}