{
  "type": "Feature",
  "properties": {
    "addr:full":"9 Sharow Gro Blackpool Lancashire FY1 5NE",
    "addr:housenumber":"9",
    "addr:postcode":"fy1 5ne",
    "addr:street":"Sharow Gro",
    "iso:country":"GB",
    "sg:address":"9 Sharow Gro",
    "sg:city":"Blackpool",
    "sg:classifiers":[
        {
            "category":"Professional",
            "type":"Services"
        }
    ],
    "sg:postcode":"FY1 5NE",
    "sg:province":"Lancashire",
    "sg:tags":[
        "entertainer"
    ],
    "wof:name":"Reval Magical Entertainer",
    "wof:placetype":"venue"
},
  "geometry": {"coordinates":[-3.0387630463,53.8061256409],"type":"Point"}
}