{
  "type": "Feature",
  "properties": {
    "iso:country":"GB",
    "sg:address":"9-10 Criterion Arcade, Christchurch Road",
    "sg:city":"Bournemouth",
    "sg:classifiers":[
        {
            "category":"Shopping",
            "subcategory":"Discount & Variety Stores",
            "type":"Retail Goods"
        }
    ],
    "sg:phone":"+44 1202 552634",
    "sg:postcode":"BH1 1BU",
    "sg:province":"Dorset",
    "sg:tags":[
        "centre"
    ],
    "wof:name":"Victors Super Discount",
    "wof:placetype":"venue"
},
  "geometry": {"coordinates":[-1.877002,50.720741],"type":"Point"}
}