{
  "type": "Feature",
  "properties": {
    "iso:country":"GB",
    "sg:address":"6 Grange Avenue",
    "sg:city":"Henley-on-thames",
    "sg:classifiers":[
        {
            "category":"Professional",
            "subcategory":"Lawyer & Legal Services",
            "type":"Services"
        }
    ],
    "sg:phone":"+44 1491 628716",
    "sg:postcode":"RG9 5JP",
    "sg:province":"Berkshire",
    "sg:tags":[
        "solicitor"
    ],
    "wof:name":"Conway & Co.",
    "wof:placetype":"venue"
},
  "geometry": {"coordinates":[-0.9727609754,51.5294113159],"type":"Point"}
}