{
  "type": "Feature",
  "properties": {
    "iso:country":"GB",
    "sg:address":"Pyramid House, Winchester Road, Four Marks",
    "sg:city":"Alton",
    "sg:classifiers":[
        {
            "category":"Manufacturing",
            "subcategory":"Glass & Minerals",
            "type":"Manufacturing & Wholesale Goods"
        }
    ],
    "sg:phone":"+44 1420 561200",
    "sg:postcode":"GU34 5HR",
    "sg:province":"Hampshire",
    "sg:tags":[
        "fibre",
        "optic"
    ],
    "wof:name":"Oxford Electronics Ltd.",
    "wof:placetype":"venue"
},
  "geometry": {"coordinates":[-1.026038,51.11903],"type":"Point"}
}