{
  "type": "Feature",
  "properties": {
    "addr:full":"Heathlands, The Lane York East Riding of Yorkshire YO4 1JT",
    "addr:postcode":"yo4 1jt",
    "addr:street":"The Lane",
    "iso:country":"GB",
    "sg:address":"Heathlands, The Lane",
    "sg:city":"York",
    "sg:classifiers":[
        {
            "category":"Building & Trades",
            "subcategory":"Construction",
            "type":"Services"
        }
    ],
    "sg:phone":"+44 1904 411314",
    "sg:postcode":"YO4 1JT",
    "sg:province":"East Riding of Yorkshire",
    "sg:tags":[
        "contractor",
        "paving",
        "driveway"
    ],
    "wof:name":"Trevor Smith",
    "wof:placetype":"venue"
},
  "geometry": {"coordinates":[-1.0834200382,53.9533309937],"type":"Point"}
}