{
  "type": "Feature",
  "properties": {
    "addr:full":"9 Fishers Lane London Greater London W4 1RX",
    "addr:housenumber":"9",
    "addr:postcode":"w4 1rx",
    "addr:street":"Fishers Lane",
    "iso:country":"GB",
    "sg:address":"9 Fishers Lane",
    "sg:city":"London",
    "sg:classifiers":[
        {
            "category":"Professional",
            "subcategory":"Management & Consulting",
            "type":"Services"
        }
    ],
    "sg:phone":"+44 20 8987 9011",
    "sg:postcode":"W4 1RX",
    "sg:province":"Greater London",
    "sg:tags":[
        "consultant",
        "business"
    ],
    "wof:name":"Goal Focus",
    "wof:placetype":"venue"
},
  "geometry": {"coordinates":[-0.260307,51.493565],"type":"Point"}
}