{
  "type": "Feature",
  "properties": {
    "addr:full":"Avenue 4, Station Lane Witney Oxfordshire OX28 4BH",
    "addr:postcode":"ox28 4bh",
    "addr:street":"Avenue 4 Station Lane",
    "iso:country":"GB",
    "sg:address":"Avenue 4, Station Lane",
    "sg:city":"Witney",
    "sg:classifiers":[
        {
            "category":"Home & Garden",
            "subcategory":"Carpets & Floor Coverings",
            "type":"Retail Goods"
        }
    ],
    "sg:phone":"+44 1993 703833",
    "sg:postcode":"OX28 4BH",
    "sg:province":"Oxfordshire",
    "sg:tags":[
        "carpets",
        "rug",
        "matting"
    ],
    "wof:name":"Carpet Options Ltd.",
    "wof:placetype":"venue"
},
  "geometry": {"coordinates":[-1.481767,51.778904],"type":"Point"}
}