{
  "type": "Feature",
  "properties": {
    "iso:country":"GB",
    "sg:address":"Addison Terrace",
    "sg:city":"Wednesbury",
    "sg:classifiers":[
        {
            "category":"Education",
            "subcategory":"School",
            "type":"Public Place"
        }
    ],
    "sg:phone":"+44 121 556 0269",
    "sg:postcode":"WS10 7AL",
    "sg:province":"West Midlands",
    "sg:tags":[
        "local",
        "authority"
    ],
    "wof:name":"St Johns C of E Primary School",
    "wof:placetype":"venue"
},
  "geometry": {"coordinates":[-2.019254,52.552731],"type":"Point"}
}