{
  "type": "Feature",
  "properties": {
    "addr:full":"15 Lambourne Cres Cardiff Cardiff CF4 5GJ",
    "addr:housenumber":"15",
    "addr:postcode":"cf4 5gj",
    "addr:street":"Lambourne Cres",
    "iso:country":"GB",
    "sg:address":"15 Lambourne Cres",
    "sg:city":"Cardiff",
    "sg:classifiers":[
        {
            "category":"Banks & Credit Unions",
            "subcategory":"Financial Services",
            "type":"Services"
        }
    ],
    "sg:phone":"+44 29 2076 6988",
    "sg:postcode":"CF4 5GJ",
    "sg:province":"Cardiff",
    "sg:tags":[
        "adviser"
    ],
    "wof:name":"B M A Services Ltd",
    "wof:placetype":"venue"
},
  "geometry": {"coordinates":[-3.1919779778,51.5223464966],"type":"Point"}
}