{
  "type": "Feature",
  "properties": {
    "iso:country":"GB",
    "sg:address":"62 Castleton Avenue, Arnold",
    "sg:city":"Nottingham",
    "sg:classifiers":[
        {
            "category":"Communications",
            "type":"Services"
        }
    ],
    "sg:postcode":"NG5 6NJ",
    "sg:province":"Nottinghamshire",
    "sg:tags":[
        "data",
        "network"
    ],
    "wof:name":"Spaceline Data Ltd.",
    "wof:placetype":"venue"
},
  "geometry": {"coordinates":[-1.12458,52.998569],"type":"Point"}
}