{
  "type": "Feature",
  "properties": {
    "addr:full":"9 St Johns Street Bedford Bedfordshire MK42 0AH",
    "addr:housenumber":"9",
    "addr:postcode":"mk42 0ah",
    "addr:street":"St Johns Street",
    "iso:country":"GB",
    "sg:address":"9 St Johns Street",
    "sg:city":"Bedford",
    "sg:classifiers":[
        {
            "category":"Restaurant",
            "type":"Food & Drink"
        }
    ],
    "sg:postcode":"MK42 0AH",
    "sg:province":"Bedfordshire",
    "wof:name":"Peking Palace Restaurant",
    "wof:placetype":"venue"
},
  "geometry": {"coordinates":[-0.465734005,52.132270813],"type":"Point"}
}