{
  "type": "Feature",
  "properties": {
    "addr:full":"Sharpham Road Cheddar Somerset BS27 3DR",
    "addr:postcode":"bs27 3dr",
    "addr:street":"Sharpham Road",
    "iso:country":"GB",
    "sg:address":"Sharpham Road",
    "sg:city":"Cheddar",
    "sg:classifiers":[
        {
            "category":"Professional",
            "subcategory":"Art Services",
            "type":"Services"
        }
    ],
    "sg:phone":"+44 1934 744634",
    "sg:postcode":"BS27 3DR",
    "sg:province":"Somerset",
    "sg:tags":[
        "model",
        "maker"
    ],
    "wof:name":"Cheddar Models Ltd.",
    "wof:placetype":"venue"
},
  "geometry": {"coordinates":[-2.7910449505,51.2775306702],"type":"Point"}
}