{
  "type": "Feature",
  "properties": {
    "addr:full":"4 Gladstone Ct Bolton Lancashire BL4 7EU",
    "addr:housenumber":"4",
    "addr:postcode":"bl4 7eu",
    "addr:street":"Gladstone Ct",
    "iso:country":"GB",
    "sg:address":"4 Gladstone Ct",
    "sg:city":"Bolton",
    "sg:classifiers":[
        {
            "category":"Manufacturing",
            "subcategory":"Petroleum Products",
            "type":"Manufacturing & Wholesale Goods"
        }
    ],
    "sg:phone":"+44 1204 571122",
    "sg:postcode":"BL4 7EU",
    "sg:province":"Lancashire",
    "sg:tags":[
        "double",
        "glazing"
    ],
    "wof:name":"Quality Window Systems",
    "wof:placetype":"venue"
},
  "geometry": {"coordinates":[-2.4024190903,53.5524749756],"type":"Point"}
}