{
  "type": "Feature",
  "properties": {
    "iso:country":"GB",
    "sg:address":"20 Maypole Gro",
    "sg:city":"Birmingham",
    "sg:classifiers":[
        {
            "category":"Social Services",
            "subcategory":"Adult Care",
            "type":"Services"
        }
    ],
    "sg:phone":"+44 121 430 7070",
    "sg:postcode":"B14 4LP",
    "sg:province":"West Midlands",
    "sg:tags":[
        "day",
        "centre"
    ],
    "wof:name":"Maypole Grove Day Centre",
    "wof:placetype":"venue"
},
  "geometry": {"coordinates":[-1.870135,52.406586],"type":"Point"}
}