{
  "type": "Feature",
  "properties": {
    "iso:country":"GB",
    "sg:address":"Milton House, Gatehouse Road, Gatehouse Industrial Area",
    "sg:city":"Aylesbury",
    "sg:classifiers":[
        {
            "category":"Health Services",
            "subcategory":"Chiropractor",
            "type":"Services"
        }
    ],
    "sg:phone":"+44 1296 489231",
    "sg:postcode":"HP19 8EL",
    "sg:province":"Buckinghamshire",
    "wof:name":"Aylesbury Chiropractic Clinic",
    "wof:placetype":"venue"
},
  "geometry": {"coordinates":[-0.8202490211,51.8180503845],"type":"Point"}
}