{
  "type": "Feature",
  "properties": {
    "iso:country":"GB",
    "sg:address":"Haywood Road, Stanfields",
    "sg:city":"Stoke-on-trent",
    "sg:classifiers":[
        {
            "category":"Bars & Pubs",
            "type":"Food & Drink"
        }
    ],
    "sg:phone":"+44 1782 811653",
    "sg:postcode":"ST6 7AH",
    "sg:province":"Staffordshire",
    "sg:tags":[
        "pubs",
        "inn"
    ],
    "wof:name":"The Goose Inn",
    "wof:placetype":"venue"
},
  "geometry": {"coordinates":[-2.192739,53.055115],"type":"Point"}
}