{
  "type": "Feature",
  "properties": {
    "addr:full":"9 Whitehall Crescent Dundee Dundee City DD1 4AR",
    "addr:housenumber":"9",
    "addr:postcode":"dd1 4ar",
    "addr:street":"Whitehall Crescent",
    "iso:country":"GB",
    "sg:address":"9 Whitehall Crescent",
    "sg:city":"Dundee",
    "sg:classifiers":[
        {
            "category":"Real Estate",
            "subcategory":"Real Estate Agent",
            "type":"Services"
        }
    ],
    "sg:phone":"+44 1382 228770",
    "sg:postcode":"DD1 4AR",
    "sg:province":"Dundee City",
    "wof:name":"Tayside Solicitors Property Centre",
    "wof:placetype":"venue"
},
  "geometry": {"coordinates":[-2.9697630405,56.4594192505],"type":"Point"}
}