{
  "type": "Feature",
  "properties": {
    "addr:full":"Ash Hall, Ystradowen Cowbridge The Vale of Glamorgan CF71 7SY",
    "addr:postcode":"cf71 7sy",
    "addr:street":"Ystradowen;The Vale",
    "iso:country":"GB",
    "sg:address":"Ash Hall, Ystradowen",
    "sg:city":"Cowbridge",
    "sg:classifiers":[
        {
            "category":"Professional",
            "subcategory":"Engineering",
            "type":"Services"
        }
    ],
    "sg:phone":"+44 1443 209024",
    "sg:postcode":"CF71 7SY",
    "sg:province":"The Vale of Glamorgan",
    "wof:name":"Reliance-Barker-Davies Ltd",
    "wof:placetype":"venue"
},
  "geometry": {"coordinates":[-3.450425,51.462391],"type":"Point"}
}