{
  "type": "Feature",
  "properties": {
    "addr:full":"South Street Northampton Northamptonshire NN1 5HS",
    "addr:postcode":"nn1 5hs",
    "addr:street":"South Street",
    "iso:country":"GB",
    "sg:address":"South Street",
    "sg:city":"Northampton",
    "sg:classifiers":[
        {
            "category":"Organizations",
            "subcategory":"Membership Organization",
            "type":"Services"
        }
    ],
    "sg:phone":"+44 1604 632775",
    "sg:postcode":"NN1 5HS",
    "sg:province":"Northamptonshire",
    "sg:tags":[
        "club"
    ],
    "wof:name":"R A O B Club",
    "wof:placetype":"venue"
},
  "geometry": {"coordinates":[-0.8766940236,52.2402839661],"type":"Point"}
}