{
  "type": "Feature",
  "properties": {
    "iso:country":"GB",
    "sg:address":"65 Minster Road",
    "sg:city":"Stourport-on-severn",
    "sg:classifiers":[
        {
            "category":"Professional",
            "subcategory":"Advertising",
            "type":"Services"
        },
        {
            "category":"Manufacturing",
            "subcategory":"Signs",
            "type":"Manufacturing & Wholesale Goods"
        }
    ],
    "sg:phone":"+44 1299 877605",
    "sg:postcode":"DY13 8AS",
    "sg:province":"Worcestershire",
    "sg:tags":[
        "writer",
        "signwriters"
    ],
    "wof:name":"Heath Advertising Signs",
    "wof:placetype":"venue"
},
  "geometry": {"coordinates":[-2.274212,52.348652],"type":"Point"}
}