{
  "type": "Feature",
  "properties": {
    "iso:country":"GB",
    "sg:address":"Irvine Rd",
    "sg:city":"Largs",
    "sg:classifiers":[
        {
            "category":"Sports & Exercise",
            "subcategory":"Golf",
            "type":"Entertainment"
        }
    ],
    "sg:postcode":"KA30 8EU",
    "sg:province":"North Ayrshire",
    "sg:tags":[
        "equipment"
    ],
    "wof:name":"Colliston,Robert,Professional Shop",
    "wof:placetype":"venue"
},
  "geometry": {"coordinates":[-4.863448143,55.7916679382],"type":"Point"}
}