{
  "type": "Feature",
  "properties": {
    "iso:country":"GB",
    "sg:address":"The Surgery, Village Hall, Worthen",
    "sg:city":"Shrewsbury",
    "sg:classifiers":[
        {
            "category":"Health Services",
            "subcategory":"Doctor",
            "type":"Services"
        }
    ],
    "sg:phone":"+44 1743 891401",
    "sg:postcode":"SY5 9HT",
    "sg:province":"Shropshire",
    "sg:tags":[
        "practitioners"
    ],
    "wof:name":"T.R Watson",
    "wof:placetype":"venue"
},
  "geometry": {"coordinates":[-2.9954590797,52.6356544495],"type":"Point"}
}