{
  "type": "Feature",
  "properties": {
    "addr:full":"Somerton Rd Newport East Riding of Yorkshire NP9 0JZ",
    "addr:postcode":"np9 0jz",
    "addr:street":"Somerton Rd",
    "iso:country":"GB",
    "sg:address":"Somerton Rd",
    "sg:city":"Newport",
    "sg:classifiers":[
        {
            "category":"Place Of Worship",
            "type":"Public Place"
        }
    ],
    "sg:phone":"+44 1633 271904",
    "sg:postcode":"NP9 0JZ",
    "sg:province":"East Riding of Yorkshire",
    "wof:name":"St Andrew's Church",
    "wof:placetype":"venue"
},
  "geometry": {"coordinates":[-2.9625689983,51.5825119019],"type":"Point"}
}