{
  "type": "Feature",
  "properties": {
    "addr:full":"Tynewydd, Llanllwni Pencader Carmarthenshire SA39 9EE",
    "addr:postcode":"sa39 9ee",
    "iso:country":"GB",
    "sg:address":"Tynewydd, Llanllwni",
    "sg:city":"Pencader",
    "sg:classifiers":[
        {
            "category":"Farming",
            "subcategory":"Livestock Farm",
            "type":"Manufacturing & Wholesale Goods"
        }
    ],
    "sg:phone":"+44 1559 395414",
    "sg:postcode":"SA39 9EE",
    "sg:province":"Carmarthenshire",
    "sg:tags":[
        "others"
    ],
    "wof:name":"T J Orr",
    "wof:placetype":"venue"
},
  "geometry": {"coordinates":[-4.265864,52.000229],"type":"Point"}
}