{
  "type": "Feature",
  "properties": {
    "iso:country":"GB",
    "sg:address":"681 George Street",
    "sg:city":"Aberdeen",
    "sg:classifiers":[
        {
            "category":"Personal",
            "subcategory":"Skin Care",
            "type":"Services"
        }
    ],
    "sg:postcode":"AB25 3XP",
    "sg:province":"Aberdeen City",
    "sg:tags":[
        "leather",
        "merchant"
    ],
    "wof:name":"A & A Hyland",
    "wof:placetype":"venue"
},
  "geometry": {"coordinates":[-2.110596,57.157799],"type":"Point"}
}