{
  "type": "Feature",
  "properties": {
    "iso:country":"GB",
    "sg:address":"Unit 7, Springway Lane, Weston Zoyland",
    "sg:city":"Bridgwater",
    "sg:classifiers":[
        {
            "category":"Manufacturing",
            "subcategory":"Glass & Minerals",
            "type":"Manufacturing & Wholesale Goods"
        }
    ],
    "sg:phone":"+44 1278 691647",
    "sg:postcode":"TA7 0JS",
    "sg:province":"Somerset",
    "sg:tags":[
        "fibre",
        "moulding"
    ],
    "wof:name":"J S Mouldings International",
    "wof:placetype":"venue"
},
  "geometry": {"coordinates":[-2.90855,51.100601],"type":"Point"}
}