{
  "type": "Feature",
  "properties": {
    "addr:full":"Environmental Education Centre Pontypridd Caerphilly CF37 4HW",
    "addr:postcode":"cf37 4hw",
    "iso:country":"GB",
    "sg:address":"Environmental Education Centre",
    "sg:city":"Pontypridd",
    "sg:classifiers":[
        {
            "category":"Government",
            "subcategory":"Office",
            "type":"Public Place"
        }
    ],
    "sg:phone":"+44 1443 492720",
    "sg:postcode":"CF37 4HW",
    "sg:province":"Caerphilly",
    "sg:tags":[
        "education",
        "agency",
        "authority"
    ],
    "wof:name":"Hyder Operations",
    "wof:placetype":"venue"
},
  "geometry": {"coordinates":[-3.3309590816,51.5975494385],"type":"Point"}
}