{
  "type": "Feature",
  "properties": {
    "iso:country":"GB",
    "sg:address":"Unit 6 Broomvale Business Cntr, Bramford Road",
    "sg:city":"Ipswich",
    "sg:classifiers":[
        {
            "category":"Building & Trades",
            "subcategory":"Landscaping Services",
            "type":"Services"
        }
    ],
    "sg:phone":"+44 1473 833747",
    "sg:postcode":"IP8 4JU",
    "sg:province":"Suffolk",
    "sg:tags":[
        "horticultural",
        "consultant"
    ],
    "wof:name":"Singleton Flint Ltd.",
    "wof:placetype":"venue"
},
  "geometry": {"coordinates":[1.097389,52.07589],"type":"Point"}
}