{
  "type": "Feature",
  "properties": {
    "addr:full":"39 Merkland Drive Glasgow East Dunbartonshire G66 3SD",
    "addr:housenumber":"39",
    "addr:postcode":"g66 3sd",
    "addr:street":"Merkland Drive",
    "iso:country":"GB",
    "sg:address":"39 Merkland Drive",
    "sg:city":"Glasgow",
    "sg:classifiers":[
        {
            "category":"Communications",
            "subcategory":"Film & Video Production",
            "type":"Services"
        },
        {
            "category":"Communications",
            "type":"Services"
        }
    ],
    "sg:phone":"+44 141 776 3655",
    "sg:postcode":"G66 3SD",
    "sg:province":"East Dunbartonshire",
    "sg:tags":[
        "equipment",
        "audio-visual"
    ],
    "wof:name":"Caught In The Act",
    "wof:placetype":"venue"
},
  "geometry": {"coordinates":[-4.129541,55.938309],"type":"Point"}
}