{
  "type": "Feature",
  "properties": {
    "addr:full":"Drinkwater Lane, Bretforton Evesham Gloucestershire WR11 7JQ",
    "addr:postcode":"wr11 7jq",
    "addr:street":"Drinkwater Lane",
    "iso:country":"GB",
    "sg:address":"Drinkwater Lane, Bretforton",
    "sg:city":"Evesham",
    "sg:classifiers":[
        {
            "category":"Building & Trades",
            "subcategory":"Construction",
            "type":"Services"
        }
    ],
    "sg:phone":"+44 1386 833384",
    "sg:postcode":"WR11 7JQ",
    "sg:province":"Gloucestershire",
    "sg:tags":[
        "builder"
    ],
    "wof:name":"G S Johns & Co. (Builders) Ltd.",
    "wof:placetype":"venue"
},
  "geometry": {"coordinates":[-1.8657310009,52.0940856934],"type":"Point"}
}