{
  "type": "Feature",
  "properties": {
    "addr:full":"Copthal Bridge House, 1 East Parade Harrogate North Yorkshire HG1 1UG",
    "addr:housenumber":"1",
    "addr:postcode":"hg1 1ug",
    "addr:street":"East Parade",
    "iso:country":"GB",
    "sg:address":"Copthal Bridge House, 1 East Parade",
    "sg:city":"Harrogate",
    "sg:classifiers":[
        {
            "category":"Freight",
            "type":"Transportation"
        }
    ],
    "sg:phone":"+44 1423 506181",
    "sg:postcode":"HG1 1UG",
    "sg:province":"North Yorkshire",
    "sg:tags":[
        "haulage",
        "road"
    ],
    "wof:name":"Exel",
    "wof:placetype":"venue"
},
  "geometry": {"coordinates":[-1.536204,53.992409],"type":"Point"}
}