{
  "type": "Feature",
  "properties": {
    "iso:country":"GB",
    "sg:address":"19 Market Street, Huthwaite",
    "sg:city":"Sutton-in-ashfield",
    "sg:classifiers":[
        {
            "category":"Government",
            "subcategory":"Post Office",
            "type":"Public Place"
        }
    ],
    "sg:phone":"+44 1623 554073",
    "sg:postcode":"NG17 2QY",
    "sg:province":"Nottinghamshire",
    "wof:name":"S & L B Flintham",
    "wof:placetype":"venue"
},
  "geometry": {"coordinates":[-1.3022199869,53.1287612915],"type":"Point"}
}