{
  "type": "Feature",
  "properties": {
    "addr:full":"7 Gloucester Road Ross-on-wye Gloucestershire HR9 5BU",
    "addr:housenumber":"7",
    "addr:postcode":"hr9 5bu",
    "addr:street":"Gloucester Road",
    "iso:country":"GB",
    "sg:address":"7 Gloucester Road",
    "sg:city":"Ross-on-wye",
    "sg:classifiers":[
        {
            "category":"Bars & Pubs",
            "type":"Food & Drink"
        }
    ],
    "sg:phone":"+44 1989 769994",
    "sg:postcode":"HR9 5BU",
    "sg:province":"Gloucestershire",
    "sg:tags":[
        "pubs",
        "inn"
    ],
    "wof:name":"Kings Arm",
    "wof:placetype":"venue"
},
  "geometry": {"coordinates":[-2.5829639435,51.9140777588],"type":"Point"}
}