{
  "type": "Feature",
  "properties": {
    "addr:full":"5 Station Road Gorebridge Midlothian EH23 4JX",
    "addr:housenumber":"5",
    "addr:postcode":"eh23 4jx",
    "addr:street":"Station Road",
    "iso:country":"GB",
    "sg:address":"5 Station Road",
    "sg:city":"Gorebridge",
    "sg:classifiers":[
        {
            "category":"Restaurant",
            "type":"Food & Drink"
        }
    ],
    "sg:phone":"+44 1875 822230",
    "sg:postcode":"EH23 4JX",
    "sg:province":"Midlothian",
    "wof:name":"Wright Inns Ltd.",
    "wof:placetype":"venue"
},
  "geometry": {"coordinates":[-3.047053,55.839584],"type":"Point"}
}