{
  "type": "Feature",
  "properties": {
    "iso:country":"GB",
    "sg:address":"237 Victoria Road",
    "sg:city":"Plymouth",
    "sg:classifiers":[
        {
            "category":"Building & Trades",
            "subcategory":"Construction",
            "type":"Services"
        }
    ],
    "sg:phone":"+44 1752 350724",
    "sg:postcode":"PL5 2DQ",
    "sg:province":"Devon",
    "sg:tags":[
        "roofing"
    ],
    "wof:name":"G K P Roofing & Building Maintenance",
    "wof:placetype":"venue"
},
  "geometry": {"coordinates":[-4.181016922,50.4097900391],"type":"Point"}
}