{
  "type": "Feature",
  "properties": {
    "addr:full":"Golden Lane Pembroke Pembrokeshire SA71 4PR",
    "addr:postcode":"sa71 4pr",
    "addr:street":"Lane",
    "iso:country":"GB",
    "sg:address":"Golden Lane",
    "sg:city":"Pembroke",
    "sg:classifiers":[
        {
            "category":"Health Services",
            "subcategory":"Nursing And Care Facility",
            "type":"Services"
        }
    ],
    "sg:phone":"+44 1646 681037",
    "sg:postcode":"SA71 4PR",
    "sg:province":"Pembrokeshire",
    "sg:tags":[
        "home"
    ],
    "wof:name":"Ashdale",
    "wof:placetype":"venue"
},
  "geometry": {"coordinates":[-4.910929,51.678307],"type":"Point"}
}