{
  "type": "Feature",
  "properties": {
    "addr:full":"76 Doncaster Road, Westwoodside Doncaster Lincolnshire DN9 2EE",
    "addr:housenumber":"76",
    "addr:postcode":"dn9 2ee",
    "addr:street":"Doncaster Road",
    "iso:country":"GB",
    "sg:address":"76 Doncaster Road, Westwoodside",
    "sg:city":"Doncaster",
    "sg:classifiers":[
        {
            "category":"Building & Trades",
            "subcategory":"Cleaning & Sanitation",
            "type":"Services"
        }
    ],
    "sg:phone":"+44 1427 753056",
    "sg:postcode":"DN9 2EE",
    "sg:province":"Lincolnshire",
    "sg:tags":[
        "repairing",
        "tank"
    ],
    "wof:name":"Roy & June Michael",
    "wof:placetype":"venue"
},
  "geometry": {"coordinates":[-0.8784,53.488026],"type":"Point"}
}