{
  "type": "Feature",
  "properties": {
    "iso:country":"GB",
    "sg:address":"26 Countisbury Avenue, Llanrumney",
    "sg:city":"Cardiff",
    "sg:classifiers":[
        {
            "category":"Food & Beverages",
            "subcategory":"Bakery",
            "type":"Retail Goods"
        }
    ],
    "sg:postcode":"CF3 5SJ",
    "sg:province":"Caerphilly",
    "sg:tags":[
        "baker"
    ],
    "wof:name":"Fords the Baker",
    "wof:placetype":"venue"
},
  "geometry": {"coordinates":[-3.120033,51.52029],"type":"Point"}
}