{
  "type": "Feature",
  "properties": {
    "addr:full":"Rotunda Amusement Park, The Seafront Folkestone Kent CT20 1PX",
    "addr:postcode":"ct20 1px",
    "iso:country":"GB",
    "sg:address":"Rotunda Amusement Park, The Seafront",
    "sg:city":"Folkestone",
    "sg:classifiers":[
        {
            "category":"Recreation",
            "subcategory":"Amusement Park",
            "type":"Entertainment"
        }
    ],
    "sg:phone":"+44 1303 245245",
    "sg:postcode":"CT20 1PX",
    "sg:province":"Kent",
    "sg:tags":[
        "arcade"
    ],
    "wof:name":"Dreamland Leisure Ltd.",
    "wof:placetype":"venue"
},
  "geometry": {"coordinates":[1.1835000515,51.077911377],"type":"Point"}
}