{
  "type": "Feature",
  "properties": {
    "addr:full":"Windmill Road, Markyate St Albans Hertfordshire AL3 8LP",
    "addr:postcode":"al3 8lp",
    "addr:street":"Windmill Road",
    "iso:country":"GB",
    "sg:address":"Windmill Road, Markyate",
    "sg:city":"St Albans",
    "sg:classifiers":[
        {
            "category":"Transit Center",
            "subcategory":"Passenger",
            "type":"Transportation"
        }
    ],
    "sg:phone":"+44 1582 842242",
    "sg:postcode":"AL3 8LP",
    "sg:province":"Hertfordshire",
    "sg:tags":[
        "boarding",
        "kennel",
        "catteries"
    ],
    "wof:name":"Hazel Corner Boarding Kennels",
    "wof:placetype":"venue"
},
  "geometry": {"coordinates":[-0.460974,51.836399],"type":"Point"}
}