{
  "type": "Feature",
  "properties": {
    "iso:country":"GB",
    "sg:address":"Broadmead Farm, Yeovil Marsh",
    "sg:city":"Yeovil",
    "sg:classifiers":[
        {
            "category":"Farming",
            "subcategory":"Livestock Farm",
            "type":"Manufacturing & Wholesale Goods"
        }
    ],
    "sg:phone":"+44 1935 474966",
    "sg:postcode":"BA21 3QD",
    "sg:province":"Somerset",
    "sg:tags":[
        "others"
    ],
    "wof:name":"Maurice L Loder",
    "wof:placetype":"venue"
},
  "geometry": {"coordinates":[-2.639292,50.948441],"type":"Point"}
}