{
  "type": "Feature",
  "properties": {
    "iso:country":"GB",
    "sg:address":"2-12 Whitchurch Road, Pangbourne",
    "sg:city":"Reading",
    "sg:classifiers":[
        {
            "category":"Home & Garden",
            "subcategory":"Carpets & Floor Coverings",
            "type":"Retail Goods"
        }
    ],
    "sg:phone":"+44 118 984 2674",
    "sg:postcode":"RG8 7BP",
    "sg:province":"Berkshire",
    "sg:tags":[
        "wall",
        "tie",
        "replacement"
    ],
    "wof:name":"British Wall Tie Association",
    "wof:placetype":"venue"
},
  "geometry": {"coordinates":[-1.0862250328,51.4840354919],"type":"Point"}
}