{
  "type": "Feature",
  "properties": {
    "addr:full":"Charmwood, Mortimer Avenue Paignton Devon TQ3 1LR",
    "addr:postcode":"tq3 1lr",
    "addr:street":"Mortimer Avenue",
    "iso:country":"GB",
    "sg:address":"Charmwood, Mortimer Avenue",
    "sg:city":"Paignton",
    "sg:classifiers":[
        {
            "category":"Professional",
            "subcategory":"Computer Services",
            "type":"Services"
        }
    ],
    "sg:phone":"+44 1803 551001",
    "sg:postcode":"TQ3 1LR",
    "sg:province":"Devon",
    "sg:tags":[
        "consultant"
    ],
    "wof:name":"Discover It",
    "wof:placetype":"venue"
},
  "geometry": {"coordinates":[-3.5676140785,50.4385681152],"type":"Point"}
}