{
  "type": "Feature",
  "properties": {
    "addr:full":"43 Sincil Street Lincoln Lincolnshire LN5 7ET",
    "addr:housenumber":"43",
    "addr:postcode":"ln5 7et",
    "addr:street":"Sincil Street",
    "iso:country":"GB",
    "sg:address":"43 Sincil Street",
    "sg:city":"Lincoln",
    "sg:classifiers":[
        {
            "category":"Shopping",
            "subcategory":"Comic Books",
            "type":"Retail Goods"
        }
    ],
    "sg:phone":"+44 1522 523201",
    "sg:postcode":"LN5 7ET",
    "sg:province":"Lincolnshire",
    "sg:tags":[
        "jeweller"
    ],
    "wof:name":"Bates",
    "wof:placetype":"venue"
},
  "geometry": {"coordinates":[-0.538402,53.227791],"type":"Point"}
}