{
  "type": "Feature",
  "properties": {
    "addr:full":"Units 1&2 Bishops Road Lincoln Lincolnshire LN2 4JZ",
    "addr:housenumber":"units 1 & 2",
    "addr:postcode":"ln2 4jz",
    "addr:street":"Bishops Road",
    "iso:country":"GB",
    "sg:address":"Units 1&2 Bishops Road",
    "sg:city":"Lincoln",
    "sg:classifiers":[
        {
            "category":"Manufacturing",
            "subcategory":"Rubber & Plastics",
            "type":"Manufacturing & Wholesale Goods"
        }
    ],
    "sg:phone":"+44 1522 575400",
    "sg:postcode":"LN2 4JZ",
    "sg:province":"Lincolnshire",
    "sg:tags":[
        "supplier",
        "stockist"
    ],
    "wof:name":"Eastern Building Plastics Ltd.",
    "wof:placetype":"venue"
},
  "geometry": {"coordinates":[-0.51023,53.238453],"type":"Point"}
}