{
  "type": "Feature",
  "properties": {
    "iso:country":"GB",
    "sg:address":"1 Regent Street",
    "sg:city":"Weston-super-mare",
    "sg:classifiers":[
        {
            "category":"Fast Food",
            "type":"Food & Drink"
        }
    ],
    "sg:phone":"+44 1934 644795",
    "sg:postcode":"BS23 1SE",
    "sg:province":"Somerset",
    "sg:tags":[
        "away",
        "take"
    ],
    "wof:name":"la Costa Get Stuffed Take Away",
    "wof:placetype":"venue"
},
  "geometry": {"coordinates":[-2.9815208912,51.3475570679],"type":"Point"}
}