{
  "type": "Feature",
  "properties": {
    "addr:full":"Rainsford Way Hornchurch Essex RM12 4BP",
    "addr:postcode":"rm12 4bp",
    "addr:street":"Rainsford Way",
    "iso:country":"GB",
    "sg:address":"Rainsford Way",
    "sg:city":"Hornchurch",
    "sg:classifiers":[
        {
            "category":"Education",
            "subcategory":"School",
            "type":"Public Place"
        }
    ],
    "sg:phone":"+44 1708 448187",
    "sg:postcode":"RM12 4BP",
    "sg:province":"Essex",
    "sg:tags":[
        "local",
        "authority"
    ],
    "wof:name":"Wykeham Primary School",
    "wof:placetype":"venue"
},
  "geometry": {"coordinates":[0.1922470033,51.5640602112],"type":"Point"}
}