{
  "type": "Feature",
  "properties": {
    "addr:full":"12 Churchgate Loughborough Leicestershire LE11 1UD",
    "addr:housenumber":"12",
    "addr:postcode":"le11 1ud",
    "addr:street":"Churchgate",
    "iso:country":"GB",
    "sg:address":"12 Churchgate",
    "sg:city":"Loughborough",
    "sg:classifiers":[
        {
            "category":"Retail",
            "subcategory":"Repair Shop",
            "type":"Services"
        },
        {
            "category":"Shopping",
            "subcategory":"Luggage & Leather Goods",
            "type":"Retail Goods"
        }
    ],
    "sg:phone":"+44 1509 214388",
    "sg:postcode":"LE11 1UD",
    "sg:province":"Leicestershire",
    "sg:tags":[
        "leathergoods"
    ],
    "wof:name":"Stuarts",
    "wof:placetype":"venue"
},
  "geometry": {"coordinates":[-1.2053339481,52.7732658386],"type":"Point"}
}