{
  "type": "Feature",
  "properties": {
    "addr:full":"83 Gower Street London Greater London WC1E 6HJ",
    "addr:housenumber":"83",
    "addr:postcode":"wc1e 6hj",
    "addr:street":"Gower Street",
    "iso:country":"GB",
    "sg:address":"83 Gower Street",
    "sg:city":"London",
    "sg:classifiers":[
        {
            "category":"Travel",
            "subcategory":"Hotels & Motels",
            "type":"Entertainment"
        }
    ],
    "sg:phone":"+44 20 7636 2115",
    "sg:postcode":"WC1E 6HJ",
    "sg:province":"Greater London",
    "wof:name":"Arosfa Hotel",
    "wof:placetype":"venue"
},
  "geometry": {"coordinates":[-0.132624,51.522198],"type":"Point"}
}