{
  "type": "Feature",
  "properties": {
    "iso:country":"GB",
    "sg:address":"Westall House, Birchgrove Road, Horsted Keynes",
    "sg:city":"Haywards Heath",
    "sg:classifiers":[
        {
            "category":"Social Services",
            "subcategory":"Retirement Home",
            "type":"Services"
        }
    ],
    "sg:phone":"+44 1825 791157",
    "sg:postcode":"RH17 7BS",
    "sg:province":"East Sussex",
    "sg:tags":[
        "residential",
        "care"
    ],
    "wof:name":"The Abbeyfield Mid Sussex Society Ltd.",
    "wof:placetype":"venue"
},
  "geometry": {"coordinates":[-0.020793,51.036827],"type":"Point"}
}