{
  "type": "Feature",
  "properties": {
    "addr:full":"The Poplars, Alcester Road, Inkberrow Worcester Worcestershire WR7 4LS",
    "addr:postcode":"wr7 4ls",
    "addr:street":"Alcester Road",
    "iso:country":"GB",
    "sg:address":"The Poplars, Alcester Road, Inkberrow",
    "sg:city":"Worcester",
    "sg:classifiers":[
        {
            "category":"Utilities",
            "subcategory":"Fuel Oil & Lpg",
            "type":"Services"
        }
    ],
    "sg:postcode":"WR7 4LS",
    "sg:province":"Worcestershire",
    "sg:tags":[
        "coal",
        "smokeless"
    ],
    "wof:name":"P J Laight",
    "wof:placetype":"venue"
},
  "geometry": {"coordinates":[-1.980557,52.21323],"type":"Point"}
}