{
  "type": "Feature",
  "properties": {
    "iso:country":"GB",
    "sg:address":"139 Holland Park Avenue",
    "sg:city":"London",
    "sg:classifiers":[
        {
            "category":"Professional",
            "subcategory":"Employment Agencies",
            "type":"Services"
        }
    ],
    "sg:phone":"+44 20 7313 2630",
    "sg:postcode":"W11 4UT",
    "sg:province":"Greater London",
    "sg:tags":[
        "consultant"
    ],
    "wof:name":"Europteam Consultants Ltd.",
    "wof:placetype":"venue"
},
  "geometry": {"coordinates":[-0.210085,51.506115],"type":"Point"}
}