{
  "type": "Feature",
  "properties": {
    "addr:full":"Bon Marche Building, 444 Brixton Rd Brixton Greater London SW9 8EJ",
    "addr:housenumber":"444",
    "addr:postcode":"sw9 8ej",
    "addr:street":"Brixton Rd",
    "iso:country":"GB",
    "sg:address":"Bon Marche Building, 444 Brixton Rd",
    "sg:city":"Brixton",
    "sg:classifiers":[
        {
            "category":"Communications",
            "subcategory":"Newspaper",
            "type":"Services"
        }
    ],
    "sg:phone":"+44 20 7924 9966",
    "sg:postcode":"SW9 8EJ",
    "sg:province":"Greater London",
    "sg:tags":[
        "magazine"
    ],
    "wof:name":"Second Generation",
    "wof:placetype":"venue"
},
  "geometry": {"coordinates":[-0.1149699986,51.4625015259],"type":"Point"}
}