{
  "type": "Feature",
  "properties": {
    "addr:full":"19 Church Road Lymm Cheshire WA13 0QG",
    "addr:housenumber":"19",
    "addr:postcode":"wa13 0qg",
    "addr:street":"Church Road",
    "iso:country":"GB",
    "sg:address":"19 Church Road",
    "sg:city":"Lymm",
    "sg:classifiers":[
        {
            "category":"Personal",
            "type":"Services"
        }
    ],
    "sg:postcode":"WA13 0QG",
    "sg:province":"Cheshire",
    "sg:tags":[
        "wedding"
    ],
    "wof:name":"Brenda Green",
    "wof:placetype":"venue"
},
  "geometry": {"coordinates":[-2.4843740463,53.37940979],"type":"Point"}
}