{
  "type": "Feature",
  "properties": {
    "addr:full":"91 Blatchington Rd Hove East Sussex BN3 3YG",
    "addr:housenumber":"91",
    "addr:postcode":"bn3 3yg",
    "addr:street":"Blatchington Rd",
    "iso:country":"GB",
    "sg:address":"91 Blatchington Rd",
    "sg:city":"Hove",
    "sg:classifiers":[
        {
            "category":"Shopping",
            "subcategory":"Pharmacy",
            "type":"Retail Goods"
        }
    ],
    "sg:phone":"+44 1273 735108",
    "sg:postcode":"BN3 3YG",
    "sg:province":"East Sussex",
    "sg:tags":[
        "pharmacist",
        "chemist"
    ],
    "wof:name":"Russell Green Ltd",
    "wof:placetype":"venue"
},
  "geometry": {"coordinates":[-0.1739269942,50.8313293457],"type":"Point"}
}