{
  "type": "Feature",
  "properties": {
    "iso:country":"GB",
    "sg:address":"Greyfriars Ho, Greyfriars Rd",
    "sg:city":"Doncaster",
    "sg:classifiers":[
        {
            "category":"Professional",
            "subcategory":"Testing Lab",
            "type":"Services"
        }
    ],
    "sg:phone":"+44 1302 321525",
    "sg:postcode":"DN1 1QN",
    "sg:province":"South Yorkshire",
    "sg:tags":[
        "inspection",
        "calibration"
    ],
    "wof:name":"Don Calibration Services Ltd",
    "wof:placetype":"venue"
},
  "geometry": {"coordinates":[-1.1305650473,53.5243911743],"type":"Point"}
}