{
  "type": "Feature",
  "properties": {
    "addr:full":"3 Hurts Yard, Long Row Nottingham Nottinghamshire NG1 6JD",
    "addr:housenumber":"3",
    "addr:postcode":"ng1 6jd",
    "addr:street":"Hurts Yard Long Row",
    "iso:country":"GB",
    "sg:address":"3 Hurts Yard, Long Row",
    "sg:city":"Nottingham",
    "sg:classifiers":[
        {
            "category":"Retail",
            "subcategory":"Laundry & Dry Cleaning",
            "type":"Services"
        }
    ],
    "sg:phone":"+44 115 941 9216",
    "sg:postcode":"NG1 6JD",
    "sg:province":"Nottinghamshire",
    "sg:tags":[
        "alteration"
    ],
    "wof:name":"High Society",
    "wof:placetype":"venue"
},
  "geometry": {"coordinates":[-1.1522519588,52.9545936584],"type":"Point"}
}