{
  "type": "Feature",
  "properties": {
    "addr:full":"9a Queen St Telford Shropshire TF1 1EH",
    "addr:housenumber":"9a",
    "addr:postcode":"tf1 1eh",
    "addr:street":"Queen St",
    "iso:country":"GB",
    "sg:address":"9a Queen St",
    "sg:city":"Telford",
    "sg:classifiers":[
        {
            "category":"Organizations",
            "subcategory":"Professional Association",
            "type":"Services"
        }
    ],
    "sg:phone":"+44 1952 223015",
    "sg:postcode":"TF1 1EH",
    "sg:province":"Shropshire",
    "sg:tags":[
        "union",
        "trade"
    ],
    "wof:name":"AEEU",
    "wof:placetype":"venue"
},
  "geometry": {"coordinates":[-2.520804882,52.702419281],"type":"Point"}
}