{
  "type": "Feature",
  "properties": {
    "addr:full":"Unit 2 Martor Industrial Estate, Tormarton Road Chippenham Gloucestershire SN14 8LZ",
    "addr:housenumber":"unit 2",
    "addr:postcode":"sn14 8lz",
    "addr:street":"Martor Industrial Estate Tormarton Road",
    "iso:country":"GB",
    "sg:address":"Unit 2 Martor Industrial Estate, Tormarton Road",
    "sg:city":"Chippenham",
    "sg:classifiers":[
        {
            "category":"Manufacturing",
            "subcategory":"Chemicals & Compounds",
            "type":"Manufacturing & Wholesale Goods"
        },
        {
            "category":"Building & Trades",
            "subcategory":"Construction",
            "type":"Services"
        }
    ],
    "sg:phone":"+44 1225 891190",
    "sg:postcode":"SN14 8LZ",
    "sg:province":"Gloucestershire",
    "sg:tags":[
        "roofing",
        "product",
        "cleaning",
        "abrasive"
    ],
    "wof:name":"Marshfield Stone Tile Co. Ltd.",
    "wof:placetype":"venue"
},
  "geometry": {"coordinates":[-2.3243598938,51.4621200562],"type":"Point"}
}