{
  "type": "Feature",
  "properties": {
    "addr:full":"168 Copster Hill Road Oldham Lancashire OL8 1QQ",
    "addr:housenumber":"168",
    "addr:postcode":"ol8 1qq",
    "addr:street":"Copster Hill Road",
    "iso:country":"GB",
    "sg:address":"168 Copster Hill Road",
    "sg:city":"Oldham",
    "sg:classifiers":[
        {
            "category":"Food & Beverages",
            "subcategory":"Liquor & Beverages",
            "type":"Retail Goods"
        }
    ],
    "sg:phone":"+44 161 624 4966",
    "sg:postcode":"OL8 1QQ",
    "sg:province":"Lancashire",
    "sg:tags":[
        "beer",
        "wine",
        "spirit",
        "wines"
    ],
    "wof:name":"ABDUL KHALIQ",
    "wof:placetype":"venue"
},
  "geometry": {"coordinates":[-2.116363,53.528587],"type":"Point"}
}