{
  "type": "Feature",
  "properties": {
    "iso:country":"GB",
    "sg:address":"27 Clarence Rd",
    "sg:city":"Southport",
    "sg:classifiers":[
        {
            "category":"Organizations",
            "subcategory":"Non-profit Organization",
            "type":"Services"
        }
    ],
    "sg:phone":"+44 1704 563603",
    "sg:postcode":"PR8 4BH",
    "sg:province":"Lancashire",
    "sg:tags":[
        "charitable",
        "organisation",
        "voluntary",
        "charity"
    ],
    "wof:name":"Cystic Fibrosis Trust",
    "wof:placetype":"venue"
},
  "geometry": {"coordinates":[-3.010085,53.633789],"type":"Point"}
}