{
  "type": "Feature",
  "properties": {
    "iso:country":"GB",
    "sg:address":"34 Birch Road East, Witton",
    "sg:city":"Birmingham",
    "sg:classifiers":[
        {
            "category":"Manufacturing",
            "subcategory":"Metals",
            "type":"Manufacturing & Wholesale Goods"
        }
    ],
    "sg:postcode":"B6 7DB",
    "sg:province":"West Midlands",
    "sg:tags":[
        "steel",
        "fabricator",
        "erectors"
    ],
    "wof:name":"Erdington Welded Fabrications Ltd.",
    "wof:placetype":"venue"
},
  "geometry": {"coordinates":[-1.876469,52.51717],"type":"Point"}
}