{
  "type": "Feature",
  "properties": {
    "iso:country":"GB",
    "sg:address":"Groundwork Environment Centre, Dolton Way",
    "sg:city":"Tipton",
    "sg:classifiers":[
        {
            "category":"Organizations",
            "subcategory":"Non-profit Organization",
            "type":"Services"
        }
    ],
    "sg:phone":"+44 121 530 5500",
    "sg:postcode":"DY4 9AL",
    "sg:province":"West Midlands",
    "sg:tags":[
        "organisation",
        "voluntary",
        "charity"
    ],
    "wof:name":"Groundwork Black Country",
    "wof:placetype":"venue"
},
  "geometry": {"coordinates":[-2.070697,52.528137],"type":"Point"}
}