{
  "type": "Feature",
  "properties": {
    "addr:full":"Shay Lane Indust Estate, Shay Lane, Longridge Preston Lancashire PR3 3BT",
    "addr:postcode":"pr3 3bt",
    "addr:street":"Shay Lane Indust Estate Shay Lane",
    "iso:country":"GB",
    "sg:address":"Shay Lane Indust Estate, Shay Lane, Longridge",
    "sg:city":"Preston",
    "sg:classifiers":[
        {
            "category":"Wholesale",
            "subcategory":"Sporting Goods",
            "type":"Manufacturing & Wholesale Goods"
        }
    ],
    "sg:phone":"+44 1772 786945",
    "sg:postcode":"PR3 3BT",
    "sg:province":"Lancashire",
    "sg:tags":[
        "mnfr",
        "sport",
        "equipment"
    ],
    "wof:name":"Direct Sports Equipment",
    "wof:placetype":"venue"
},
  "geometry": {"coordinates":[-2.6109259129,53.8241844177],"type":"Point"}
}