{
  "type": "Feature",
  "properties": {
    "addr:full":"Unit 1e Hawes Rural Workshop Estate, Brunt Acres Road Hawes North Yorkshire DL8 3UZ",
    "addr:housenumber":"1e;estate",
    "addr:postcode":"dl8 3uz",
    "addr:street":"Brunt Acres Road",
    "iso:country":"GB",
    "sg:address":"Unit 1e Hawes Rural Workshop Estate, Brunt Acres Road",
    "sg:city":"Hawes",
    "sg:classifiers":[
        {
            "category":"Retail",
            "subcategory":"Auto Repair",
            "type":"Services"
        }
    ],
    "sg:phone":"+44 1969 667765",
    "sg:postcode":"DL8 3UZ",
    "sg:province":"North Yorkshire",
    "sg:tags":[
        "modification",
        "garage"
    ],
    "wof:name":"Stevron Auto Services",
    "wof:placetype":"venue"
},
  "geometry": {"coordinates":[-2.1994268894,54.3041763306],"type":"Point"}
}