{
  "type": "Feature",
  "properties": {
    "iso:country":"GB",
    "sg:address":"Unit 240c Picton Rd, Wavertree",
    "sg:city":"Liverpool",
    "sg:classifiers":[
        {
            "category":"Home & Garden",
            "subcategory":"Building Materials",
            "type":"Retail Goods"
        }
    ],
    "sg:postcode":"L15 4LP",
    "sg:province":"Merseyside",
    "sg:tags":[
        "ironwork",
        "diy",
        "wrought"
    ],
    "wof:name":"Charnock,Frank,",
    "wof:placetype":"venue"
},
  "geometry": {"coordinates":[-2.938819,53.402985],"type":"Point"}
}