{
  "type": "Feature",
  "properties": {
    "addr:full":"Unit 5, Bettws Park Workshop Ammanford Carmarthenshire SA18 2ET",
    "addr:housenumber":"unit 5",
    "addr:postcode":"sa18 2et",
    "addr:street":"Bettws Park",
    "iso:country":"GB",
    "sg:address":"Unit 5, Bettws Park Workshop",
    "sg:city":"Ammanford",
    "sg:classifiers":[
        {
            "category":"Professional",
            "subcategory":"Business Services",
            "type":"Services"
        }
    ],
    "sg:phone":"+44 1269 595400",
    "sg:postcode":"SA18 2ET",
    "sg:province":"Carmarthenshire",
    "sg:tags":[
        "trade"
    ],
    "wof:name":"Wales Association of Communities & Town Councils",
    "wof:placetype":"venue"
},
  "geometry": {"coordinates":[-3.985546,51.780876],"type":"Point"}
}