{
  "type": "Feature",
  "properties": {
    "addr:full":"41 Kestrel Close, East Wittering Chichester West Sussex PO20 8PQ",
    "addr:housenumber":"41",
    "addr:postcode":"po20 8pq",
    "addr:street":"Kestrel Close",
    "iso:country":"GB",
    "sg:address":"41 Kestrel Close, East Wittering",
    "sg:city":"Chichester",
    "sg:classifiers":[
        {
            "category":"Professional",
            "subcategory":"Engineering",
            "type":"Services"
        }
    ],
    "sg:phone":"+44 1243 670178",
    "sg:postcode":"PO20 8PQ",
    "sg:province":"West Sussex",
    "sg:tags":[
        "gas",
        "engineer"
    ],
    "wof:name":"KW Property Service Engineers",
    "wof:placetype":"venue"
},
  "geometry": {"coordinates":[-0.859792,50.764252],"type":"Point"}
}