{
  "type": "Feature",
  "properties": {
    "addr:full":"King William House, 13 Queen Square Bristol City of Bristol BS1 4NT",
    "addr:housenumber":"13",
    "addr:postcode":"bs1 4nt",
    "addr:street":"Queen Square",
    "iso:country":"GB",
    "sg:address":"King William House, 13 Queen Square",
    "sg:city":"Bristol",
    "sg:classifiers":[
        {
            "category":"Professional",
            "subcategory":"Lawyer & Legal Services",
            "type":"Services"
        }
    ],
    "sg:phone":"+44 117 925 8080",
    "sg:postcode":"BS1 4NT",
    "sg:province":"City of Bristol",
    "sg:tags":[
        "solicitor"
    ],
    "wof:name":"Barcan Woodward Solicitors",
    "wof:placetype":"venue"
},
  "geometry": {"coordinates":[-2.593067,51.451241],"type":"Point"}
}