{
  "type": "Feature",
  "properties": {
    "addr:full":"Warmington Rd, Sheldon Birmingham West Midlands B26 3SX",
    "addr:postcode":"b26 3sx",
    "addr:street":"Warmington Rd",
    "iso:country":"GB",
    "sg:address":"Warmington Rd, Sheldon",
    "sg:city":"Birmingham",
    "sg:classifiers":[
        {
            "category":"Bars & Pubs",
            "type":"Food & Drink"
        }
    ],
    "sg:phone":"+44 121 743 2112",
    "sg:postcode":"B26 3SX",
    "sg:province":"West Midlands",
    "sg:tags":[
        "pubs",
        "inn"
    ],
    "wof:name":"The Sheldon",
    "wof:placetype":"venue"
},
  "geometry": {"coordinates":[-1.780129,52.459049],"type":"Point"}
}