{
  "type": "Feature",
  "properties": {
    "iso:country":"GB",
    "sg:address":"210 Bedford Road, Kempston",
    "sg:city":"Bedford",
    "sg:classifiers":[
        {
            "category":"Manufacturing",
            "subcategory":"Petroleum Products",
            "type":"Manufacturing & Wholesale Goods"
        }
    ],
    "sg:phone":"+44 1234 854812",
    "sg:postcode":"MK42 8BL",
    "sg:province":"Bedfordshire",
    "sg:tags":[
        "double",
        "glazing"
    ],
    "wof:name":"Kingston Windows",
    "wof:placetype":"venue"
},
  "geometry": {"coordinates":[-0.494587,52.118763],"type":"Point"}
}