{
  "type": "Feature",
  "properties": {
    "iso:country":"GB",
    "sg:address":"151 Wyndford Road",
    "sg:city":"Glasgow",
    "sg:classifiers":[
        {
            "category":"Social Services",
            "subcategory":"Retirement Home",
            "type":"Services"
        },
        {
            "category":"Organizations",
            "subcategory":"Non-profit Organization",
            "type":"Services"
        }
    ],
    "sg:phone":"+44 141 945 4085",
    "sg:postcode":"G20 8DZ",
    "sg:province":"Glasgow City",
    "sg:tags":[
        "charity",
        "residential",
        "organisation",
        "care",
        "charitable"
    ],
    "wof:name":"Scottish Association For Mental Health",
    "wof:placetype":"venue"
},
  "geometry": {"coordinates":[-4.2949318886,55.8872795105],"type":"Point"}
}