{
  "type": "Feature",
  "properties": {
    "addr:full":"11 Carlton Hill Exmouth Devon EX8 2AJ",
    "addr:housenumber":"11",
    "addr:postcode":"ex8 2aj",
    "addr:street":"Carlton Hill",
    "iso:country":"GB",
    "sg:address":"11 Carlton Hill",
    "sg:city":"Exmouth",
    "sg:classifiers":[
        {
            "category":"Travel",
            "subcategory":"Hotels & Motels",
            "type":"Entertainment"
        }
    ],
    "sg:postcode":"EX8 2AJ",
    "sg:province":"Devon",
    "sg:tags":[
        "house",
        "guest"
    ],
    "wof:name":"The Swallows",
    "wof:placetype":"venue"
},
  "geometry": {"coordinates":[-3.408262,50.615559],"type":"Point"}
}