{
  "type": "Feature",
  "properties": {
    "addr:full":"9 Stn Maltings, Stn Rd, Newport Saffron Walden Essex CB11 3PL",
    "addr:housenumber":"9",
    "addr:postcode":"cb11 3pl",
    "addr:street":"Stn Maltings Stn Rd",
    "iso:country":"GB",
    "sg:address":"9 Stn Maltings, Stn Rd, Newport",
    "sg:city":"Saffron Walden",
    "sg:classifiers":[
        {
            "category":"Retail",
            "subcategory":"Auto Repair",
            "type":"Services"
        }
    ],
    "sg:postcode":"CB11 3PL",
    "sg:province":"Essex",
    "sg:tags":[
        "modification",
        "garage"
    ],
    "wof:name":"Priest,Duncan,",
    "wof:placetype":"venue"
},
  "geometry": {"coordinates":[0.20879,52.005871],"type":"Point"}
}