{
  "type": "Feature",
  "properties": {
    "addr:full":"Chestnut Way, Gurnos Merthyr Tydfil Merthyr Tydfil CF47 9SB",
    "addr:postcode":"cf47 9sb",
    "addr:street":"Chestnut Way;Tydfil",
    "iso:country":"GB",
    "sg:address":"Chestnut Way, Gurnos",
    "sg:city":"Merthyr Tydfil",
    "sg:classifiers":[
        {
            "category":"Place Of Worship",
            "type":"Public Place"
        }
    ],
    "sg:phone":"+44 1685 722672",
    "sg:postcode":"CF47 9SB",
    "sg:province":"Merthyr Tydfil",
    "wof:name":"St.Aloysius",
    "wof:placetype":"venue"
},
  "geometry": {"coordinates":[-3.391371,51.761368],"type":"Point"}
}