{
  "type": "Feature",
  "properties": {
    "addr:full":"11 Whitecliff Way Folkestone Kent CT19 6DX",
    "addr:housenumber":"11",
    "addr:postcode":"ct19 6dx",
    "addr:street":"Whitecliff Way",
    "iso:country":"GB",
    "sg:address":"11 Whitecliff Way",
    "sg:city":"Folkestone",
    "sg:classifiers":[
        {
            "category":"Building & Trades",
            "subcategory":"Construction",
            "type":"Services"
        }
    ],
    "sg:phone":"+44 1303 241104",
    "sg:postcode":"CT19 6DX",
    "sg:province":"Kent",
    "sg:tags":[
        "builder"
    ],
    "wof:name":"Anthony John Wrigley",
    "wof:placetype":"venue"
},
  "geometry": {"coordinates":[1.1960220337,51.0876426697],"type":"Point"}
}