{
  "type": "Feature",
  "properties": {
    "addr:full":"Unit 3 Lambourne House, Bridge Cross Rr, Chase Terrace Stafford Staffordshire WS7 2BX",
    "addr:housenumber":"unit 3 lambourne house",
    "addr:postcode":"ws7 2bx",
    "addr:street":"Bridge Cross Rr Chase Terrace",
    "iso:country":"GB",
    "sg:address":"Unit 3 Lambourne House, Bridge Cross Rr, Chase Terrace",
    "sg:city":"Stafford",
    "sg:classifiers":[
        {
            "category":"Shopping",
            "subcategory":"Clothing, Apparel, & Fashions",
            "type":"Retail Goods"
        }
    ],
    "sg:phone":"+44 1543 682181",
    "sg:postcode":"WS7 2BX",
    "sg:province":"Staffordshire",
    "sg:tags":[
        "t-shirt"
    ],
    "wof:name":"Colour Graphics",
    "wof:placetype":"venue"
},
  "geometry": {"coordinates":[-1.9328399897,52.6812896729],"type":"Point"}
}