{
  "type": "Feature",
  "properties": {
    "iso:country":"GB",
    "sg:address":"6 Burnside",
    "sg:city":"Belford",
    "sg:classifiers":[
        {
            "category":"Professional",
            "subcategory":"Business Services",
            "type":"Services"
        }
    ],
    "sg:phone":"+44 1668 213481",
    "sg:postcode":"NE70 7QG",
    "sg:province":"Northumberland",
    "sg:tags":[
        "import",
        "export",
        "agent"
    ],
    "wof:name":"Murray Fruit",
    "wof:placetype":"venue"
},
  "geometry": {"coordinates":[-1.830648,55.597336],"type":"Point"}
}