{
  "type": "Feature",
  "properties": {
    "iso:country":"GB",
    "sg:address":"Clifford Bridge Road",
    "sg:city":"Coventry",
    "sg:classifiers":[
        {
            "category":"Government",
            "subcategory":"Office",
            "type":"Public Place"
        }
    ],
    "sg:phone":"+44 24 7661 1848",
    "sg:postcode":"CV2 2DX",
    "sg:province":"Warwickshire",
    "sg:tags":[
        "local",
        "agency",
        "education",
        "authority"
    ],
    "wof:name":"Coventry Hospital Home Tuition Service",
    "wof:placetype":"venue"
},
  "geometry": {"coordinates":[-1.4476690292,52.4216384888],"type":"Point"}
}