{
  "type": "Feature",
  "properties": {
    "iso:country":"GB",
    "sg:address":"31 Tan Y Foel, Borthygest",
    "sg:city":"Porthmadog",
    "sg:classifiers":[
        {
            "category":"Shopping",
            "subcategory":"Musical Instruments",
            "type":"Retail Goods"
        }
    ],
    "sg:phone":"+44 1766 513700",
    "sg:postcode":"LL49 9UE",
    "sg:province":"Gwynedd",
    "wof:name":"D I Jones Piano Tuning Services",
    "wof:placetype":"venue"
},
  "geometry": {"coordinates":[-4.132989,52.927738],"type":"Point"}
}