{
  "type": "Feature",
  "properties": {
    "addr:full":"Devlin House, 36 Saint George Street London Greater London W1S 2FJ",
    "addr:housenumber":"36",
    "addr:postcode":"w1s 2fj",
    "addr:street":"Saint George Street",
    "iso:country":"GB",
    "sg:address":"Devlin House, 36 Saint George Street",
    "sg:city":"London",
    "sg:classifiers":[
        {
            "category":"Real Estate",
            "subcategory":"Real Estate Agent",
            "type":"Services"
        }
    ],
    "sg:postcode":"W1S 2FJ",
    "sg:province":"Greater London",
    "wof:name":"Landmark Virtual Offices Ltd",
    "wof:placetype":"venue"
},
  "geometry": {"coordinates":[-0.1429139972,51.5124893188],"type":"Point"}
}