{
  "type": "Feature",
  "properties": {
    "addr:full":"Montague Place, Chatham Maritime Chatham Kent ME4 4QU",
    "addr:postcode":"me4 4qu",
    "addr:street":"Montague Place",
    "iso:country":"GB",
    "sg:address":"Montague Place, Chatham Maritime",
    "sg:city":"Chatham",
    "sg:classifiers":[
        {
            "category":"Communications",
            "type":"Services"
        }
    ],
    "sg:postcode":"ME4 4QU",
    "sg:province":"Kent",
    "sg:tags":[
        "telecommunication"
    ],
    "wof:name":"Medway Data Communications Ltd",
    "wof:placetype":"venue"
},
  "geometry": {"coordinates":[0.52244,51.381889],"type":"Point"}
}