{
  "type": "Feature",
  "properties": {
    "iso:country":"GB",
    "sg:address":"12 Pendarves Terrace",
    "sg:city":"Port Talbot",
    "sg:classifiers":[
        {
            "category":"Building & Trades",
            "subcategory":"Plumbing",
            "type":"Services"
        },
        {
            "category":"Building & Trades",
            "subcategory":"Construction",
            "type":"Services"
        }
    ],
    "sg:phone":"+44 1639 897809",
    "sg:postcode":"SA12 6DX",
    "sg:province":"Neath Port Talbot",
    "sg:tags":[
        "central",
        "installation",
        "system",
        "servicing",
        "heating"
    ],
    "wof:name":"R V Harris Heating Engineers Port Talbot",
    "wof:placetype":"venue"
},
  "geometry": {"coordinates":[-3.802369,51.591385],"type":"Point"}
}