{
  "type": "Feature",
  "properties": {
    "addr:full":"Enterprise House, 113-115 George Lane South Woodford Greater London E18 1AB",
    "addr:housenumber":"113-115",
    "addr:postcode":"e18 1ab",
    "addr:street":"George Lane",
    "iso:country":"GB",
    "sg:address":"Enterprise House, 113-115 George Lane",
    "sg:city":"South Woodford",
    "sg:classifiers":[
        {
            "category":"Professional",
            "subcategory":"Employment Agencies",
            "type":"Services"
        }
    ],
    "sg:phone":"+44 20 8530 8555",
    "sg:postcode":"E18 1AB",
    "sg:province":"Greater London",
    "sg:tags":[
        "consultant"
    ],
    "wof:name":"T.A.P Associates",
    "wof:placetype":"venue"
},
  "geometry": {"coordinates":[0.026783,51.592583],"type":"Point"}
}