{
  "type": "Feature",
  "properties": {
    "addr:full":"32 Central Avenue Carlisle Cumbria CA1 3QB",
    "addr:housenumber":"32",
    "addr:postcode":"ca1 3qb",
    "addr:street":"Central Avenue",
    "iso:country":"GB",
    "sg:address":"32 Central Avenue",
    "sg:city":"Carlisle",
    "sg:classifiers":[
        {
            "category":"Retail",
            "subcategory":"Laundry & Dry Cleaning",
            "type":"Services"
        }
    ],
    "sg:postcode":"CA1 3QB",
    "sg:province":"Cumbria",
    "sg:tags":[
        "launderette",
        "alteration"
    ],
    "wof:name":"Launderette Harraby",
    "wof:placetype":"venue"
},
  "geometry": {"coordinates":[-2.9012129307,54.8816108704],"type":"Point"}
}