{
  "type": "Feature",
  "properties": {
    "addr:full":"Globe House, High Street Llanfyllin Shropshire SY22 5AT",
    "addr:postcode":"sy22 5at",
    "addr:street":"High Street",
    "iso:country":"GB",
    "sg:address":"Globe House, High Street",
    "sg:city":"Llanfyllin",
    "sg:classifiers":[
        {
            "category":"Manufacturing",
            "subcategory":"Signs",
            "type":"Manufacturing & Wholesale Goods"
        }
    ],
    "sg:phone":"+44 1691 648610",
    "sg:postcode":"SY22 5AT",
    "sg:province":"Shropshire",
    "sg:tags":[
        "writer"
    ],
    "wof:name":"Signrite",
    "wof:placetype":"venue"
},
  "geometry": {"coordinates":[-3.273319,52.766289],"type":"Point"}
}