{
  "type": "Feature",
  "properties": {
    "addr:full":"6 Kimbers Drive, Burnham Slough Berkshire SL1 8JE",
    "addr:housenumber":"6",
    "addr:postcode":"sl1 8je",
    "addr:street":"Kimbers Drive",
    "iso:country":"GB",
    "sg:address":"6 Kimbers Drive, Burnham",
    "sg:city":"Slough",
    "sg:classifiers":[
        {
            "category":"Building & Trades",
            "subcategory":"Construction",
            "type":"Services"
        }
    ],
    "sg:phone":"+44 1628 667894",
    "sg:postcode":"SL1 8JE",
    "sg:province":"Berkshire",
    "sg:tags":[
        "contractor",
        "paving",
        "driveway"
    ],
    "wof:name":"Burnham Surfacing",
    "wof:placetype":"venue"
},
  "geometry": {"coordinates":[-0.65076,51.538021],"type":"Point"}
}