{
  "type": "Feature",
  "properties": {
    "iso:country":"GB",
    "sg:address":"4 Hall St",
    "sg:city":"Todmorden",
    "sg:classifiers":[
        {
            "category":"Government",
            "subcategory":"Office",
            "type":"Public Place"
        }
    ],
    "sg:phone":"+44 1706 812091",
    "sg:postcode":"OL14 7AD",
    "sg:province":"Lancashire",
    "sg:tags":[
        "central"
    ],
    "wof:name":"Probation Service",
    "wof:placetype":"venue"
},
  "geometry": {"coordinates":[-2.09886,53.712994],"type":"Point"}
}