{
  "type": "Feature",
  "properties": {
    "addr:full":"80-92 Station Road Kenilworth Warwickshire CV8 1JF",
    "addr:housenumber":"80-92",
    "addr:postcode":"cv8 1jf",
    "addr:street":"Station Road",
    "iso:country":"GB",
    "sg:address":"80-92 Station Road",
    "sg:city":"Kenilworth",
    "sg:classifiers":[
        {
            "category":"Parking",
            "type":"Transportation"
        }
    ],
    "sg:phone":"+44 1926 864146",
    "sg:postcode":"CV8 1JF",
    "sg:province":"Warwickshire",
    "sg:tags":[
        "car",
        "valet"
    ],
    "wof:name":"Kenilworth Car Valeting Centre",
    "wof:placetype":"venue"
},
  "geometry": {"coordinates":[-1.5786169767,52.3429260254],"type":"Point"}
}