{
  "type": "Feature",
  "properties": {
    "addr:full":"63 Bolingbroke Road Cleethorpes Lincolnshire DN35 0HF",
    "addr:housenumber":"63",
    "addr:postcode":"dn35 0hf",
    "addr:street":"Bolingbroke Road",
    "iso:country":"GB",
    "sg:address":"63 Bolingbroke Road",
    "sg:city":"Cleethorpes",
    "sg:classifiers":[
        {
            "category":"Personal",
            "type":"Services"
        }
    ],
    "sg:postcode":"DN35 0HF",
    "sg:province":"Lincolnshire",
    "sg:tags":[
        "wedding"
    ],
    "wof:name":"Special Occasions",
    "wof:placetype":"venue"
},
  "geometry": {"coordinates":[-0.0147390002,53.5444068909],"type":"Point"}
}