{
  "type": "Feature",
  "properties": {
    "addr:full":"1 Wellington Street, Winson Grn Birmingham West Midlands B18 4NN",
    "addr:housenumber":"1",
    "addr:postcode":"west;b18 4nn",
    "addr:street":"Wellington Street;Grn",
    "iso:country":"GB",
    "sg:address":"1 Wellington Street, Winson Grn",
    "sg:city":"Birmingham",
    "sg:classifiers":[
        {
            "category":"Home & Garden",
            "subcategory":"Building Materials",
            "type":"Retail Goods"
        }
    ],
    "sg:postcode":"B18 4NN",
    "sg:province":"West Midlands",
    "sg:tags":[
        "window",
        "frame"
    ],
    "wof:name":"Ecco Windows Ltd.",
    "wof:placetype":"venue"
},
  "geometry": {"coordinates":[-1.9405879974,52.4919700623],"type":"Point"}
}