{
  "type": "Feature",
  "properties": {
    "iso:country":"GB",
    "sg:address":"Doranda Way",
    "sg:city":"West Bromwich",
    "sg:classifiers":[
        {
            "category":"Manufacturing",
            "subcategory":"Tools & Machinery",
            "type":"Manufacturing & Wholesale Goods"
        }
    ],
    "sg:phone":"+44 121 553 3322",
    "sg:postcode":"B71 4LU",
    "sg:province":"West Midlands",
    "wof:name":"Protech Industrial Supplies Ltd.",
    "wof:placetype":"venue"
},
  "geometry": {"coordinates":[-1.974944,52.508999],"type":"Point"}
}