{
  "type": "Feature",
  "properties": {
    "iso:country":"GB",
    "sg:address":"79 Sandringham Rd, Intake",
    "sg:city":"Doncaster",
    "sg:classifiers":[
        {
            "category":"Home & Garden",
            "subcategory":"Home Furnishings",
            "type":"Retail Goods"
        }
    ],
    "sg:phone":"+44 1302 344476",
    "sg:postcode":"DN2 5JA",
    "sg:province":"South Yorkshire",
    "sg:tags":[
        "wall",
        "wallpaper",
        "covering"
    ],
    "wof:name":"T C Discount Wallcoverings",
    "wof:placetype":"venue"
},
  "geometry": {"coordinates":[-1.105519,53.526775],"type":"Point"}
}