{
  "type": "Feature",
  "properties": {
    "iso:country":"GB",
    "sg:address":"Unit 29 Garden City Industrial Estate, Sealand Avenue",
    "sg:city":"Deeside",
    "sg:classifiers":[
        {
            "category":"Building & Trades",
            "subcategory":"Construction",
            "type":"Services"
        }
    ],
    "sg:phone":"+44 1244 812828",
    "sg:postcode":"CH5 2HW",
    "sg:province":"Flintshire",
    "sg:tags":[
        "valve"
    ],
    "wof:name":"Nicholas Holland",
    "wof:placetype":"venue"
},
  "geometry": {"coordinates":[-3.0103769302,53.2177314758],"type":"Point"}
}