{
  "type": "Feature",
  "properties": {
    "addr:full":"1 India Buildings Edinburgh City of Edinburgh EH1 2HE",
    "addr:housenumber":"1",
    "addr:postcode":"eh1 2he",
    "addr:street":"India Buildings",
    "iso:country":"GB",
    "sg:address":"1 India Buildings",
    "sg:city":"Edinburgh",
    "sg:classifiers":[
        {
            "category":"Communications",
            "subcategory":"Newspaper",
            "type":"Services"
        }
    ],
    "sg:phone":"+44 131 220 5770",
    "sg:postcode":"EH1 2HE",
    "sg:province":"City of Edinburgh",
    "sg:tags":[
        "magazine"
    ],
    "wof:name":"Scotland in Business",
    "wof:placetype":"venue"
},
  "geometry": {"coordinates":[-3.192413,55.94857],"type":"Point"}
}