{
  "type": "Feature",
  "properties": {
    "addr:full":"339 Oxford Road Manchester Greater Manchester M13 9PG",
    "addr:housenumber":"339",
    "addr:postcode":"m13 9pg",
    "addr:street":"Oxford Road",
    "iso:country":"GB",
    "sg:address":"339 Oxford Road",
    "sg:city":"Manchester",
    "sg:classifiers":[
        {
            "category":"Place Of Worship",
            "type":"Public Place"
        }
    ],
    "sg:phone":"+44 161 273 2435",
    "sg:postcode":"M13 9PG",
    "sg:province":"Greater Manchester",
    "wof:name":"Holy Name Church",
    "wof:placetype":"venue"
},
  "geometry": {"coordinates":[-2.2315309048,53.4643821716],"type":"Point"}
}