{
  "type": "Feature",
  "properties": {
    "iso:country":"GB",
    "sg:address":"Unit 7 Sandy Lane",
    "sg:city":"Coventry",
    "sg:classifiers":[
        {
            "category":"Professional",
            "subcategory":"Engineering",
            "type":"Services"
        }
    ],
    "sg:phone":"+44 24 7663 3353",
    "sg:postcode":"CV1 4DQ",
    "sg:province":"West Midlands",
    "sg:tags":[
        "contractor",
        "electrical",
        "engineer"
    ],
    "wof:name":"J & B (Electrical) Contractors Ltd.",
    "wof:placetype":"venue"
},
  "geometry": {"coordinates":[-1.514049,52.415932],"type":"Point"}
}