{
  "type": "Feature",
  "properties": {
    "addr:full":"Suite 2,1 Cranbourn Alley,cranbourn St, Leicester Sq London Greater London WC2H 7AW",
    "addr:housenumber":"suite 2,1",
    "addr:postcode":"sq;wc2h 7aw",
    "addr:street":"Cranbourn Alley Cranbourn St",
    "iso:country":"GB",
    "sg:address":"Suite 2,1 Cranbourn Alley,cranbourn St, Leicester Sq",
    "sg:city":"London",
    "sg:classifiers":[
        {
            "category":"Professional",
            "subcategory":"Accounting & Tax Preparation",
            "type":"Services"
        }
    ],
    "sg:postcode":"WC2H 7AW",
    "sg:province":"Greater London",
    "sg:tags":[
        "accountant"
    ],
    "wof:name":"Burford & Co",
    "wof:placetype":"venue"
},
  "geometry": {"coordinates":[-0.1297550052,51.5110702515],"type":"Point"}
}