{
  "type": "Feature",
  "properties": {
    "iso:country":"GB",
    "sg:address":"37 Lockhurst Street",
    "sg:city":"London",
    "sg:classifiers":[
        {
            "category":"Health Services",
            "subcategory":"Health Practitioner",
            "type":"Services"
        }
    ],
    "sg:postcode":"E5 0AP",
    "sg:province":"Greater London",
    "sg:tags":[
        "osteopath"
    ],
    "wof:name":"Patricia Row",
    "wof:placetype":"venue"
},
  "geometry": {"coordinates":[-0.043939,51.55555],"type":"Point"}
}