{
  "type": "Feature",
  "properties": {
    "addr:full":"35 St Augustines Cres Whitstable Kent CT5 2NW",
    "addr:housenumber":"35",
    "addr:postcode":"ct5 2nw",
    "addr:street":"St Augustines Cres Whitstable",
    "iso:country":"GB",
    "sg:address":"35 St Augustines Cres",
    "sg:city":"Whitstable",
    "sg:classifiers":[
        {
            "category":"Autos & Motor Vehicles",
            "subcategory":"Auto Supplies",
            "type":"Retail Goods"
        }
    ],
    "sg:phone":"+44 1227 793067",
    "sg:postcode":"CT5 2NW",
    "sg:province":"Kent",
    "sg:tags":[
        "windscreen"
    ],
    "wof:name":"Fix-A-Screen",
    "wof:placetype":"venue"
},
  "geometry": {"coordinates":[1.068363,51.363575],"type":"Point"}
}