{
  "type": "Feature",
  "properties": {
    "iso:country":"GB",
    "sg:address":"Hall Street, South Hetton",
    "sg:city":"Durham",
    "sg:classifiers":[
        {
            "category":"Retail",
            "subcategory":"Veterinary Services",
            "type":"Services"
        }
    ],
    "sg:phone":"+44 191 526 2963",
    "sg:postcode":"DH6 2TU",
    "sg:province":"Durham",
    "sg:tags":[
        "surgeon"
    ],
    "wof:name":"White Lion Veterinary Clinic",
    "wof:placetype":"venue"
},
  "geometry": {"coordinates":[-1.408578,54.799976],"type":"Point"}
}