{
  "type": "Feature",
  "properties": {
    "iso:country":"GB",
    "sg:address":"51 Shaw Road",
    "sg:city":"Blackpool",
    "sg:classifiers":[
        {
            "category":"Travel",
            "subcategory":"Hotels & Motels",
            "type":"Entertainment"
        }
    ],
    "sg:phone":"+44 1253 346423",
    "sg:postcode":"FY1 6HA",
    "sg:province":"Lancashire",
    "sg:tags":[
        "house",
        "guest"
    ],
    "wof:name":"John & Joy Greensmith",
    "wof:placetype":"venue"
},
  "geometry": {"coordinates":[-3.0513210297,53.8000984192],"type":"Point"}
}