{
  "type": "Feature",
  "properties": {
    "iso:country":"GB",
    "sg:address":"150 Fortess Rd",
    "sg:city":"London",
    "sg:classifiers":[
        {
            "category":"Food & Beverages",
            "subcategory":"Liquor & Beverages",
            "type":"Retail Goods"
        }
    ],
    "sg:phone":"+44 20 7267 9663",
    "sg:postcode":"NW5 2HP",
    "sg:province":"Greater London",
    "sg:tags":[
        "beer",
        "spirit",
        "wines"
    ],
    "wof:name":"Thirst Quencher Ltd",
    "wof:placetype":"venue"
},
  "geometry": {"coordinates":[-0.1391379982,51.5556602478],"type":"Point"}
}