{
  "type": "Feature",
  "properties": {
    "addr:full":"48 Buxton Road, Frettenham Norwich Norfolk NR12 7NJ",
    "addr:housenumber":"48",
    "addr:postcode":"nr12 7nj",
    "addr:street":"Buxton Road",
    "iso:country":"GB",
    "sg:address":"48 Buxton Road, Frettenham",
    "sg:city":"Norwich",
    "sg:classifiers":[
        {
            "category":"Retail",
            "subcategory":"Auto Repair",
            "type":"Services"
        }
    ],
    "sg:phone":"+44 1603 890627",
    "sg:postcode":"NR12 7NJ",
    "sg:province":"Norfolk",
    "sg:tags":[
        "modification",
        "garage",
        "related"
    ],
    "wof:name":"Pound Garage",
    "wof:placetype":"venue"
},
  "geometry": {"coordinates":[1.314052,52.71088],"type":"Point"}
}