{
  "type": "Feature",
  "properties": {
    "addr:full":"Old British Legion Building Newport, Road Cwmcarn, Cross Keys Newport Blaenau Gwent NP11 7NE",
    "addr:postcode":"np11 7ne",
    "addr:street":"Old;Newport Road Cwmcarn",
    "iso:country":"GB",
    "sg:address":"Old British Legion Building Newport, Road Cwmcarn, Cross Keys",
    "sg:city":"Newport",
    "sg:classifiers":[
        {
            "category":"Arena",
            "subcategory":"Sports Club",
            "type":"Entertainment"
        }
    ],
    "sg:phone":"+44 1495 270998",
    "sg:postcode":"NP11 7NE",
    "sg:province":"Blaenau Gwent",
    "wof:name":"Cwmcarn Amateur Boxing Club",
    "wof:placetype":"venue"
},
  "geometry": {"coordinates":[-3.124159,51.619598],"type":"Point"}
}