{
  "type": "Feature",
  "properties": {
    "addr:full":"176 Commercial Road London Greater London E1 2JY",
    "addr:housenumber":"176",
    "addr:postcode":"e1 2jy",
    "addr:street":"Commercial Road",
    "iso:country":"GB",
    "sg:address":"176 Commercial Road",
    "sg:city":"London",
    "sg:classifiers":[
        {
            "category":"Organizations",
            "subcategory":"Membership Organization",
            "type":"Services"
        }
    ],
    "sg:phone":"+44 20 7790 0756",
    "sg:postcode":"E1 2JY",
    "sg:province":"Greater London",
    "sg:tags":[
        "club"
    ],
    "wof:name":"Indopak Social Club",
    "wof:placetype":"venue"
},
  "geometry": {"coordinates":[-0.0610489994,51.5146636963],"type":"Point"}
}