{
  "type": "Feature",
  "properties": {
    "iso:country":"GB",
    "sg:address":"18 Bridge Rd",
    "sg:city":"Gainsborough",
    "sg:classifiers":[
        {
            "category":"Bars & Pubs",
            "type":"Food & Drink"
        }
    ],
    "sg:phone":"+44 1427 614040",
    "sg:postcode":"DN21 1JU",
    "sg:province":"Lincolnshire",
    "sg:tags":[
        "pubs",
        "inn"
    ],
    "wof:name":"Yarborough Hotel",
    "wof:placetype":"venue"
},
  "geometry": {"coordinates":[-0.7730839849,53.3924942017],"type":"Point"}
}