{
  "type": "Feature",
  "properties": {
    "addr:full":"Bridge Farm, Dickleburgh Diss Norfolk IP21 4NR",
    "addr:postcode":"ip21 4nr",
    "addr:street":"Bridge",
    "iso:country":"GB",
    "sg:address":"Bridge Farm, Dickleburgh",
    "sg:city":"Diss",
    "sg:classifiers":[
        {
            "category":"Farming",
            "subcategory":"Livestock Farm",
            "type":"Manufacturing & Wholesale Goods"
        }
    ],
    "sg:postcode":"IP21 4NR",
    "sg:province":"Norfolk",
    "sg:tags":[
        "others"
    ],
    "wof:name":"V G & E M Prewer",
    "wof:placetype":"venue"
},
  "geometry": {"coordinates":[1.179402,52.395451],"type":"Point"}
}