{
  "type": "Feature",
  "properties": {
    "iso:country":"GB",
    "sg:address":"12 Allport Lane",
    "sg:city":"Wirral",
    "sg:classifiers":[
        {
            "category":"Fast Food",
            "type":"Food & Drink"
        }
    ],
    "sg:phone":"+44 151 334 2152",
    "sg:postcode":"CH62 7HP",
    "sg:province":"Cheshire",
    "sg:tags":[
        "away",
        "take"
    ],
    "wof:name":"Philip Burgess",
    "wof:placetype":"venue"
},
  "geometry": {"coordinates":[-2.978549,53.329514],"type":"Point"}
}