{
  "type": "Feature",
  "properties": {
    "iso:country":"GB",
    "sg:address":"1a St John Street",
    "sg:city":"Colchester",
    "sg:classifiers":[
        {
            "category":"Bars & Pubs",
            "type":"Food & Drink"
        }
    ],
    "sg:phone":"+44 1206 560545",
    "sg:postcode":"CO2 7AA",
    "sg:province":"Essex",
    "sg:tags":[
        "pubs",
        "inn"
    ],
    "wof:name":"The Really Good Pub Co. Ltd.",
    "wof:placetype":"venue"
},
  "geometry": {"coordinates":[0.8976250291,51.8875045776],"type":"Point"}
}