{
  "type": "Feature",
  "properties": {
    "addr:full":"66 Banbury Road Oxford Oxfordshire OX2 6PR",
    "addr:housenumber":"66",
    "addr:postcode":"ox2 6pr",
    "addr:street":"Banbury Road",
    "iso:country":"GB",
    "sg:address":"66 Banbury Road",
    "sg:city":"Oxford",
    "sg:classifiers":[
        {
            "category":"Professional",
            "subcategory":"Computer Services",
            "type":"Services"
        }
    ],
    "sg:phone":"+44 1865 512678",
    "sg:postcode":"OX2 6PR",
    "sg:province":"Oxfordshire",
    "sg:tags":[
        "system",
        "software"
    ],
    "wof:name":"Camel Services Ltd.",
    "wof:placetype":"venue"
},
  "geometry": {"coordinates":[-1.2607090473,51.7652244568],"type":"Point"}
}