{
  "type": "Feature",
  "properties": {
    "iso:country":"GB",
    "sg:address":"10 Friday St",
    "sg:city":"Henley On Thames",
    "sg:classifiers":[
        {
            "category":"Fast Food",
            "type":"Food & Drink"
        }
    ],
    "sg:phone":"+44 1491 573656",
    "sg:postcode":"RG9 1AH",
    "sg:province":"Berkshire",
    "sg:tags":[
        "away",
        "take"
    ],
    "wof:name":"Full House Fish & Chips",
    "wof:placetype":"venue"
},
  "geometry": {"coordinates":[-0.90304,51.53624],"type":"Point"}
}