{
  "type": "Feature",
  "properties": {
    "iso:country":"GB",
    "sg:address":"5 Cove Road",
    "sg:city":"Farnborough",
    "sg:classifiers":[
        {
            "category":"Shopping",
            "subcategory":"Department Store",
            "type":"Retail Goods"
        },
        {
            "category":"Shopping",
            "subcategory":"Bicycles & Sporting Goods",
            "type":"Retail Goods"
        }
    ],
    "sg:phone":"+44 1252 543778",
    "sg:postcode":"GU14 0EH",
    "sg:province":"Hampshire",
    "sg:tags":[
        "accessory",
        "cycle"
    ],
    "wof:name":"Silvester Bros",
    "wof:placetype":"venue"
},
  "geometry": {"coordinates":[-0.764329,51.292824],"type":"Point"}
}