{
  "type": "Feature",
  "properties": {
    "iso:country":"GB",
    "sg:address":"North Carr Farmhouse, Haxey Road, Misterton",
    "sg:city":"Doncaster",
    "sg:classifiers":[
        {
            "category":"Building & Trades",
            "subcategory":"Construction",
            "type":"Services"
        }
    ],
    "sg:phone":"+44 1427 890208",
    "sg:postcode":"DN10 4BA",
    "sg:province":"Lincolnshire",
    "sg:tags":[
        "builder"
    ],
    "wof:name":"Coffee Time Services",
    "wof:placetype":"venue"
},
  "geometry": {"coordinates":[-0.850294,53.444641],"type":"Point"}
}