{
  "type": "Feature",
  "properties": {
    "addr:full":"Unit 8, Liss Business Centre, Station Rd Liss Hampshire GU33 7AW",
    "addr:housenumber":"unit 8",
    "addr:postcode":"gu33 7aw",
    "addr:street":"Liss Business Centre Station Rd",
    "iso:country":"GB",
    "sg:address":"Unit 8, Liss Business Centre, Station Rd",
    "sg:city":"Liss",
    "sg:classifiers":[
        {
            "category":"Shopping",
            "subcategory":"Stationery & Office Supplies",
            "type":"Retail Goods"
        }
    ],
    "sg:phone":"+44 1730 891131",
    "sg:postcode":"GU33 7AW",
    "sg:province":"Hampshire",
    "wof:name":"Michael Roger Press Inc",
    "wof:placetype":"venue"
},
  "geometry": {"coordinates":[-0.8926500082,51.0430259705],"type":"Point"}
}