{
  "type": "Feature",
  "properties": {
    "addr:full":"Unit 10 Southfolds Road, Oakley Hay Industrial Estate Corby Northamptonshire NN18 9EU",
    "addr:housenumber":"unit 10",
    "addr:postcode":"nn18 9eu",
    "addr:street":"Southfolds Road;Hay Industrial Estate",
    "iso:country":"GB",
    "sg:address":"Unit 10 Southfolds Road, Oakley Hay Industrial Estate",
    "sg:city":"Corby",
    "sg:classifiers":[
        {
            "category":"Professional",
            "subcategory":"Engineering",
            "type":"Services"
        }
    ],
    "sg:phone":"+44 1536 744400",
    "sg:postcode":"NN18 9EU",
    "sg:province":"Northamptonshire",
    "sg:tags":[
        "engineer",
        "mechanical"
    ],
    "wof:name":"Hercules Industrial Services Ltd.",
    "wof:placetype":"venue"
},
  "geometry": {"coordinates":[-0.73599,52.465836],"type":"Point"}
}