{
  "type": "Feature",
  "properties": {
    "iso:country":"GB",
    "sg:address":"18 High St, Lambourn",
    "sg:city":"Hungerford",
    "sg:classifiers":[
        {
            "category":"Professional",
            "subcategory":"Art Services",
            "type":"Services"
        }
    ],
    "sg:phone":"+44 1488 72378",
    "sg:postcode":"RG17 8XN",
    "sg:province":"Berkshire",
    "sg:tags":[
        "consultant",
        "design"
    ],
    "wof:name":"Stop Press Promotional Services",
    "wof:placetype":"venue"
},
  "geometry": {"coordinates":[-1.53196,51.507126],"type":"Point"}
}