{
  "type": "Feature",
  "properties": {
    "addr:full":"General Enquiries, Drake Circus Plymouth Devon PL4 8AL",
    "addr:postcode":"pl4 8al",
    "addr:street":"Drake Circus",
    "iso:country":"GB",
    "sg:address":"General Enquiries, Drake Circus",
    "sg:city":"Plymouth",
    "sg:classifiers":[
        {
            "category":"Education",
            "subcategory":"Library",
            "type":"Public Place"
        },
        {
            "category":"Government",
            "subcategory":"Office",
            "type":"Public Place"
        }
    ],
    "sg:phone":"+44 1752 305923",
    "sg:postcode":"PL4 8AL",
    "sg:province":"Devon",
    "sg:tags":[
        "book",
        "local"
    ],
    "wof:name":"Central Library",
    "wof:placetype":"venue"
},
  "geometry": {"coordinates":[-4.1368942261,50.3758049011],"type":"Point"}
}