{
  "type": "Feature",
  "properties": {
    "iso:country":"GB",
    "sg:address":"7 Hatton Street",
    "sg:city":"London",
    "sg:classifiers":[
        {
            "category":"Real Estate",
            "subcategory":"Architect",
            "type":"Services"
        }
    ],
    "sg:phone":"+44 20 7258 3433",
    "sg:postcode":"NW8 8PL",
    "sg:province":"Greater London",
    "wof:name":"Terry Farrell & Partners Ltd.",
    "wof:placetype":"venue"
},
  "geometry": {"coordinates":[-0.173704,51.523392],"type":"Point"}
}