{
  "type": "Feature",
  "properties": {
    "iso:country":"GB",
    "sg:address":"Cherry Tree Farm, Church Lane, Stanfield",
    "sg:city":"Dereham",
    "sg:classifiers":[
        {
            "category":"Utilities",
            "subcategory":"Refuse",
            "type":"Services"
        }
    ],
    "sg:phone":"+44 1328 700275",
    "sg:postcode":"NR20 4AP",
    "sg:province":"Norfolk",
    "sg:tags":[
        "disposal",
        "waste"
    ],
    "wof:name":"Roger H Duffield",
    "wof:placetype":"venue"
},
  "geometry": {"coordinates":[0.86659,52.749207],"type":"Point"}
}