{
  "type": "Feature",
  "properties": {
    "addr:full":"St Mary Street, Nether Stowey Bridgwater Somerset TA5 1LJ",
    "addr:postcode":"ta5 1lj",
    "addr:street":"St Mary Street",
    "iso:country":"GB",
    "sg:address":"St Mary Street, Nether Stowey",
    "sg:city":"Bridgwater",
    "sg:classifiers":[
        {
            "category":"Bars & Pubs",
            "type":"Food & Drink"
        },
        {
            "category":"Community Center",
            "subcategory":"Social",
            "type":"Public Place"
        }
    ],
    "sg:phone":"+44 1278 691382",
    "sg:postcode":"TA5 1LJ",
    "sg:province":"Somerset",
    "sg:tags":[
        "pubs",
        "house",
        "inn",
        "activity"
    ],
    "wof:name":"The Rose & Crown",
    "wof:placetype":"venue"
},
  "geometry": {"coordinates":[-3.155381,51.150513],"type":"Point"}
}