{
  "type": "Feature",
  "properties": {
    "addr:full":"62 Shepherds Way Rickmansworth Hertfordshire WD3 7NL",
    "addr:housenumber":"62",
    "addr:postcode":"wd3 7nl",
    "addr:street":"Shepherds Way",
    "iso:country":"GB",
    "sg:address":"62 Shepherds Way",
    "sg:city":"Rickmansworth",
    "sg:classifiers":[
        {
            "category":"Home & Garden",
            "subcategory":"Home Furnishings",
            "type":"Retail Goods"
        }
    ],
    "sg:postcode":"WD3 7NL",
    "sg:province":"Hertfordshire",
    "sg:tags":[
        "awning",
        "canopy",
        "blinds"
    ],
    "wof:name":"Supreme Blinds",
    "wof:placetype":"venue"
},
  "geometry": {"coordinates":[-0.486538,51.642986],"type":"Point"}
}