{
  "type": "Feature",
  "properties": {
    "addr:full":"The Bruce, Castle Street, Lochmaben Dumfries Dumfries and Galloway DG11 1NY",
    "addr:postcode":"dg11 1ny",
    "addr:street":"Castle Street",
    "iso:country":"GB",
    "sg:address":"The Bruce, Castle Street, Lochmaben",
    "sg:city":"Dumfries",
    "sg:classifiers":[
        {
            "category":"Bars & Pubs",
            "type":"Food & Drink"
        }
    ],
    "sg:phone":"+44 1387 810314",
    "sg:postcode":"DG11 1NY",
    "sg:province":"Dumfries and Galloway",
    "sg:tags":[
        "pubs",
        "inn"
    ],
    "wof:name":"Bruce Arms",
    "wof:placetype":"venue"
},
  "geometry": {"coordinates":[-3.440839,55.12846],"type":"Point"}
}