{
  "type": "Feature",
  "properties": {
    "iso:country":"GB",
    "sg:address":"Unit 1b, Sewstern Ind Est, Gunby Rd",
    "sg:city":"Grantham",
    "sg:classifiers":[
        {
            "category":"Building & Trades",
            "subcategory":"Construction",
            "type":"Services"
        }
    ],
    "sg:phone":"+44 1476 861438",
    "sg:postcode":"NG33 5RD",
    "sg:province":"Leicestershire",
    "sg:tags":[
        "joinery"
    ],
    "wof:name":"The Woodcutters",
    "wof:placetype":"venue"
},
  "geometry": {"coordinates":[-0.67568,52.78693],"type":"Point"}
}