{
  "type": "Feature",
  "properties": {
    "iso:country":"GB",
    "sg:address":"187 High Street",
    "sg:city":"Dorking",
    "sg:classifiers":[
        {
            "category":"Bars & Pubs",
            "type":"Food & Drink"
        },
        {
            "category":"Restaurant",
            "type":"Food & Drink"
        }
    ],
    "sg:phone":"+44 1306 883292",
    "sg:postcode":"RH4 1RU",
    "sg:province":"Surrey",
    "sg:tags":[
        "pubs",
        "inn",
        "indian"
    ],
    "wof:name":"The Zafron",
    "wof:placetype":"venue"
},
  "geometry": {"coordinates":[-0.3294279873,51.2331962585],"type":"Point"}
}