{
  "type": "Feature",
  "properties": {
    "iso:country":"GB",
    "sg:address":"44 Hillcrest Avenue",
    "sg:city":"Scarborough",
    "sg:classifiers":[
        {
            "category":"Professional",
            "subcategory":"Advertising",
            "type":"Services"
        },
        {
            "category":"Manufacturing",
            "subcategory":"Signs",
            "type":"Manufacturing & Wholesale Goods"
        }
    ],
    "sg:phone":"+44 1723 368550",
    "sg:postcode":"YO12 6RQ",
    "sg:province":"North Yorkshire",
    "sg:tags":[
        "writer",
        "signwriters"
    ],
    "wof:name":"Milburn Signs",
    "wof:placetype":"venue"
},
  "geometry": {"coordinates":[-0.4259029925,54.3001976013],"type":"Point"}
}