{
  "type": "Feature",
  "properties": {
    "iso:country":"GB",
    "sg:address":"213c Rise Park Road, Rise Park Parade Rechitts Lane",
    "sg:city":"Romford",
    "sg:classifiers":[
        {
            "category":"Professional",
            "type":"Services"
        }
    ],
    "sg:postcode":"RM1 4NU",
    "sg:province":"Essex",
    "sg:tags":[
        "entertainer"
    ],
    "wof:name":"Mr Ballooneys",
    "wof:placetype":"venue"
},
  "geometry": {"coordinates":[0.18122,51.592918],"type":"Point"}
}