{
  "type": "Feature",
  "properties": {
    "addr:full":"49 Bridge Road Chessington Surrey KT9 2RX",
    "addr:housenumber":"49",
    "addr:postcode":"kt9 2rx",
    "addr:street":"Bridge Road",
    "iso:country":"GB",
    "sg:address":"49 Bridge Road",
    "sg:city":"Chessington",
    "sg:classifiers":[
        {
            "category":"Wholesale",
            "subcategory":"Electrical",
            "type":"Manufacturing & Wholesale Goods"
        }
    ],
    "sg:phone":"+44 20 8391 1622",
    "sg:postcode":"KT9 2RX",
    "sg:province":"Surrey",
    "sg:tags":[
        "equipment",
        "refrigeration"
    ],
    "wof:name":"Coldrooms Ltd.",
    "wof:placetype":"venue"
},
  "geometry": {"coordinates":[-0.3049089909,51.3633880615],"type":"Point"}
}