{
  "type": "Feature",
  "properties": {
    "addr:full":"Within Kwik Save, Allport Lane Precinct, Bromborough Wirral Cheshire CH62 7HP",
    "addr:postcode":"ch62 7hp",
    "addr:street":"Allport Lane Precinct",
    "iso:country":"GB",
    "sg:address":"Within Kwik Save, Allport Lane Precinct, Bromborough",
    "sg:city":"Wirral",
    "sg:classifiers":[
        {
            "category":"Food & Beverages",
            "subcategory":"Fruits & Vegetables",
            "type":"Retail Goods"
        }
    ],
    "sg:phone":"+44 151 343 1528",
    "sg:postcode":"CH62 7HP",
    "sg:province":"Cheshire",
    "sg:tags":[
        "greengrocer"
    ],
    "wof:name":"Kwikfruit Chester",
    "wof:placetype":"venue"
},
  "geometry": {"coordinates":[-2.97818,53.331699],"type":"Point"}
}