{
  "type": "Feature",
  "properties": {
    "addr:full":"44 Bodmin Avenue Macclesfield Cheshire SK10 3JU",
    "addr:housenumber":"44",
    "addr:postcode":"sk10 3ju",
    "addr:street":"Bodmin Avenue",
    "iso:country":"GB",
    "sg:address":"44 Bodmin Avenue",
    "sg:city":"Macclesfield",
    "sg:classifiers":[
        {
            "category":"Professional",
            "subcategory":"Engineering",
            "type":"Services"
        },
        {
            "category":"Building & Trades",
            "subcategory":"Electrical",
            "type":"Services"
        }
    ],
    "sg:phone":"+44 1625 427903",
    "sg:postcode":"SK10 3JU",
    "sg:province":"Cheshire",
    "sg:tags":[
        "engineer",
        "electrician",
        "contractor"
    ],
    "wof:name":"Jackson & Worth",
    "wof:placetype":"venue"
},
  "geometry": {"coordinates":[-2.166111,53.263145],"type":"Point"}
}