{
  "type": "Feature",
  "properties": {
    "addr:full":"Springfield, Ringwood Road Wimborne Dorset BH21 6RD",
    "addr:postcode":"bh21 6rd",
    "addr:street":"Ringwood Road",
    "iso:country":"GB",
    "sg:address":"Springfield, Ringwood Road",
    "sg:city":"Wimborne",
    "sg:classifiers":[
        {
            "category":"Building & Trades",
            "subcategory":"Construction",
            "type":"Services"
        }
    ],
    "sg:phone":"+44 1202 828417",
    "sg:postcode":"BH21 6RD",
    "sg:province":"Dorset",
    "sg:tags":[
        "roofing"
    ],
    "wof:name":"Ashley Builders & Roofing",
    "wof:placetype":"venue"
},
  "geometry": {"coordinates":[-1.988709,50.802235],"type":"Point"}
}