{
  "type": "Feature",
  "properties": {
    "addr:full":"4 Claremont Road Nottingham Nottinghamshire NG5 1BH",
    "addr:housenumber":"4",
    "addr:postcode":"ng5 1bh",
    "addr:street":"Claremont Road",
    "iso:country":"GB",
    "sg:address":"4 Claremont Road",
    "sg:city":"Nottingham",
    "sg:classifiers":[
        {
            "category":"Social Services",
            "subcategory":"Retirement Home",
            "type":"Services"
        }
    ],
    "sg:phone":"+44 115 985 7841",
    "sg:postcode":"NG5 1BH",
    "sg:province":"Nottinghamshire",
    "sg:tags":[
        "residential",
        "care"
    ],
    "wof:name":"Nottingham Community Housing Association Ltd.",
    "wof:placetype":"venue"
},
  "geometry": {"coordinates":[-1.159689,52.973064],"type":"Point"}
}