{
  "type": "Feature",
  "properties": {
    "iso:country":"GB",
    "sg:address":"Unit 6 Satelite Business Pk, Blackswarth Rd",
    "sg:city":"Bristol",
    "sg:classifiers":[
        {
            "category":"Shopping",
            "subcategory":"Baby Store",
            "type":"Retail Goods"
        }
    ],
    "sg:postcode":"BS5 8AU",
    "sg:province":"City of Bristol",
    "sg:tags":[
        "nursery",
        "accessory"
    ],
    "wof:name":"Jazzi Babes",
    "wof:placetype":"venue"
},
  "geometry": {"coordinates":[-2.549717,51.454662],"type":"Point"}
}