{
  "type": "Feature",
  "properties": {
    "addr:full":", Pennymoor Tiverton Devon EX16 8LJ",
    "addr:postcode":"ex16 8lj",
    "iso:country":"GB",
    "sg:address":", Pennymoor",
    "sg:city":"Tiverton",
    "sg:classifiers":[
        {
            "category":"Retail",
            "subcategory":"Auto Repair",
            "type":"Services"
        }
    ],
    "sg:phone":"+44 1363 866785",
    "sg:postcode":"EX16 8LJ",
    "sg:province":"Devon",
    "sg:tags":[
        "modification",
        "garage"
    ],
    "wof:name":"Gunns Garage",
    "wof:placetype":"venue"
},
  "geometry": {"coordinates":[-3.6331789494,50.9112892151],"type":"Point"}
}