{
  "type": "Feature",
  "properties": {
    "addr:full":"2 Boteler Cotts, Gore Lane, Eastry Sandwich Kent CT13 0LQ",
    "addr:housenumber":"2;cotts",
    "addr:postcode":"ct13 0lq",
    "addr:street":"Boteler;Gore Lane;Sandwich",
    "iso:country":"GB",
    "sg:address":"2 Boteler Cotts, Gore Lane, Eastry",
    "sg:city":"Sandwich",
    "sg:classifiers":[
        {
            "category":"Building & Trades",
            "subcategory":"Construction",
            "type":"Services"
        }
    ],
    "sg:postcode":"CT13 0LQ",
    "sg:province":"Kent",
    "sg:tags":[
        "builder"
    ],
    "wof:name":"D L Bushell",
    "wof:placetype":"venue"
},
  "geometry": {"coordinates":[1.3092050552,51.2485542297],"type":"Point"}
}