{
  "type": "Feature",
  "properties": {
    "iso:country":"GB",
    "sg:address":"St Gabriels Hall, St Helens Avenue",
    "sg:city":"Swansea",
    "sg:classifiers":[
        {
            "category":"Shopping",
            "subcategory":"Clothing, Apparel, & Fashions",
            "type":"Retail Goods"
        }
    ],
    "sg:phone":"+44 1792 644666",
    "sg:postcode":"SA1 4NN",
    "sg:province":"Neath Port Talbot",
    "sg:tags":[
        "clothing"
    ],
    "wof:name":"Partizan",
    "wof:placetype":"venue"
},
  "geometry": {"coordinates":[-3.940928936,51.6231536865],"type":"Point"}
}