{
  "type": "Feature",
  "properties": {
    "iso:country":"GB",
    "sg:address":"Thistledown, Henley Common, Fernhurst",
    "sg:city":"Haslemere",
    "sg:classifiers":[
        {
            "category":"Manufacturing",
            "subcategory":"Apparel",
            "type":"Manufacturing & Wholesale Goods"
        }
    ],
    "sg:phone":"+44 1428 658375",
    "sg:postcode":"GU27 3HB",
    "sg:province":"Hampshire",
    "sg:tags":[
        "shirt",
        "maker"
    ],
    "wof:name":"Egyptian Cotton Company for Clothing",
    "wof:placetype":"venue"
},
  "geometry": {"coordinates":[-0.722334,51.049294],"type":"Point"}
}