{
  "type": "Feature",
  "properties": {
    "addr:full":"10 Broad Street Seaford East Sussex BN25 1NB",
    "addr:housenumber":"10",
    "addr:postcode":"bn25 1nb",
    "addr:street":"Broad Street",
    "iso:country":"GB",
    "sg:address":"10 Broad Street",
    "sg:city":"Seaford",
    "sg:classifiers":[
        {
            "category":"Professional",
            "subcategory":"Computer Services",
            "type":"Services"
        }
    ],
    "sg:phone":"+44 1323 490565",
    "sg:postcode":"BN25 1NB",
    "sg:province":"East Sussex",
    "sg:tags":[
        "system",
        "software"
    ],
    "wof:name":"Star Seaford",
    "wof:placetype":"venue"
},
  "geometry": {"coordinates":[0.102144,50.774036],"type":"Point"}
}