{
  "type": "Feature",
  "properties": {
    "iso:country":"GB",
    "sg:address":"100 New Rd, Rubery",
    "sg:city":"Birmingham",
    "sg:classifiers":[
        {
            "category":"Communications",
            "type":"Services"
        }
    ],
    "sg:postcode":"B45 9HY",
    "sg:province":"West Midlands",
    "sg:tags":[
        "data",
        "network"
    ],
    "wof:name":"H S Electrical Ltd",
    "wof:placetype":"venue"
},
  "geometry": {"coordinates":[-2.023106,52.392044],"type":"Point"}
}