{
  "type": "Feature",
  "properties": {
    "addr:full":"2 Hurst Close Fareham Hampshire PO14 3ND",
    "addr:housenumber":"2",
    "addr:postcode":"po14 3nd",
    "addr:street":"Hurst Close",
    "iso:country":"GB",
    "sg:address":"2 Hurst Close",
    "sg:city":"Fareham",
    "sg:classifiers":[
        {
            "category":"Building & Trades",
            "subcategory":"Plumbing",
            "type":"Services"
        }
    ],
    "sg:phone":"+44 1329 667977",
    "sg:postcode":"PO14 3ND",
    "sg:province":"Hampshire",
    "sg:tags":[
        "plumber",
        "heating"
    ],
    "wof:name":"Mchardy Plumbing & Heating Ltd",
    "wof:placetype":"venue"
},
  "geometry": {"coordinates":[-1.229874,50.81675],"type":"Point"}
}