{
  "type": "Feature",
  "properties": {
    "addr:full":"74 High Street Southwold Suffolk IP18 6DN",
    "addr:housenumber":"74",
    "addr:postcode":"ip18 6dn",
    "addr:street":"High Street",
    "iso:country":"GB",
    "sg:address":"74 High Street",
    "sg:city":"Southwold",
    "sg:classifiers":[
        {
            "category":"Shopping",
            "subcategory":"Clothing, Apparel, & Fashions",
            "type":"Retail Goods"
        }
    ],
    "sg:phone":"+44 1502 722069",
    "sg:postcode":"IP18 6DN",
    "sg:province":"Suffolk",
    "sg:tags":[
        "ladieswear"
    ],
    "wof:name":"Streetwize",
    "wof:placetype":"venue"
},
  "geometry": {"coordinates":[1.678,52.327026],"type":"Point"}
}