{
  "type": "Feature",
  "properties": {
    "addr:full":"2 The Shambles Worcester Worcestershire WR1 2RF",
    "addr:housenumber":"2",
    "addr:postcode":"wr1 2rf",
    "addr:street":"The Shambles",
    "iso:country":"GB",
    "sg:address":"2 The Shambles",
    "sg:city":"Worcester",
    "sg:classifiers":[
        {
            "category":"Shopping",
            "subcategory":"Catalog Store",
            "type":"Retail Goods"
        }
    ],
    "sg:phone":"+44 1905 612061",
    "sg:postcode":"WR1 2RF",
    "sg:province":"Worcestershire",
    "sg:tags":[
        "catalogue",
        "showroom"
    ],
    "wof:name":"Argos Ltd.",
    "wof:placetype":"venue"
},
  "geometry": {"coordinates":[-2.2199730873,52.1922531128],"type":"Point"}
}