{
  "type": "Feature",
  "properties": {
    "addr:full":"8 Allerton Grange Gardens Leeds North Yorkshire LS17 6LL",
    "addr:housenumber":"8",
    "addr:postcode":"ls17 6ll",
    "addr:street":"Allerton Grange Gardens Leeds",
    "iso:country":"GB",
    "sg:address":"8 Allerton Grange Gardens",
    "sg:city":"Leeds",
    "sg:classifiers":[
        {
            "category":"Building & Trades",
            "subcategory":"Cleaning & Sanitation",
            "type":"Services"
        }
    ],
    "sg:phone":"+44 113 266 1842",
    "sg:postcode":"LS17 6LL",
    "sg:province":"North Yorkshire",
    "sg:tags":[
        "sweep",
        "chimney"
    ],
    "wof:name":"D Pygott",
    "wof:placetype":"venue"
},
  "geometry": {"coordinates":[-1.527158,53.83955],"type":"Point"}
}