{
  "type": "Feature",
  "properties": {
    "addr:full":"Europa Drive Sheffield South Yorkshire S9 1XT",
    "addr:postcode":"s9 1xt",
    "addr:street":"Europa Drive",
    "iso:country":"GB",
    "sg:address":"Europa Drive",
    "sg:city":"Sheffield",
    "sg:classifiers":[
        {
            "category":"Building & Trades",
            "subcategory":"Landscaping Services",
            "type":"Services"
        },
        {
            "category":"Banks & Credit Unions",
            "subcategory":"Investment Brokerage",
            "type":"Services"
        }
    ],
    "sg:phone":"+44 114 289 0440",
    "sg:postcode":"S9 1XT",
    "sg:province":"South Yorkshire",
    "sg:tags":[
        "gardening",
        "contractor"
    ],
    "wof:name":"Cartledge Farms Ltd.",
    "wof:placetype":"venue"
},
  "geometry": {"coordinates":[-1.4044430256,53.3999786377],"type":"Point"}
}