{
  "type": "Feature",
  "properties": {
    "addr:full":"Solitaire Avenue Worcester Worcestershire WR2 5PP",
    "addr:postcode":"wr2 5pp",
    "addr:street":"Solitaire Avenue",
    "iso:country":"GB",
    "sg:address":"Solitaire Avenue",
    "sg:city":"Worcester",
    "sg:classifiers":[
        {
            "category":"Shopping",
            "subcategory":"Department Store",
            "type":"Retail Goods"
        }
    ],
    "sg:phone":"+44 1905 428795",
    "sg:postcode":"WR2 5PP",
    "sg:province":"Worcestershire",
    "wof:name":"Solitaire Stores",
    "wof:placetype":"venue"
},
  "geometry": {"coordinates":[-2.247624,52.196445],"type":"Point"}
}