{
  "type": "Feature",
  "properties": {
    "addr:full":"Burroughs Farm, Hargham Road Attleborough Norfolk NR17 1NU",
    "addr:postcode":"nr17 1nu",
    "addr:street":"Burroughs;Hargham Road",
    "iso:country":"GB",
    "sg:address":"Burroughs Farm, Hargham Road",
    "sg:city":"Attleborough",
    "sg:classifiers":[
        {
            "category":"Communications",
            "subcategory":"News Services",
            "type":"Services"
        }
    ],
    "sg:phone":"+44 1953 887251",
    "sg:postcode":"NR17 1NU",
    "sg:province":"Norfolk",
    "sg:tags":[
        "photo",
        "agency"
    ],
    "wof:name":"Norman G Cawston",
    "wof:placetype":"venue"
},
  "geometry": {"coordinates":[1.0144350529,52.5190544128],"type":"Point"}
}