{
  "type": "Feature",
  "properties": {
    "addr:full":"46 Barkers Mead, Yate Bristol Gloucestershire BS37 7LF",
    "addr:housenumber":"46",
    "addr:postcode":"bs37 7lf",
    "addr:street":"Barkers Mead Yate Bristol",
    "iso:country":"GB",
    "sg:address":"46 Barkers Mead, Yate",
    "sg:city":"Bristol",
    "sg:classifiers":[
        {
            "category":"Professional",
            "subcategory":"Computer Services",
            "type":"Services"
        }
    ],
    "sg:postcode":"BS37 7LF",
    "sg:province":"Gloucestershire",
    "sg:tags":[
        "system",
        "software"
    ],
    "wof:name":"Octagon (D.B.) Ltd",
    "wof:placetype":"venue"
},
  "geometry": {"coordinates":[-2.410039,51.554497],"type":"Point"}
}