{
  "type": "Feature",
  "properties": {
    "addr:full":"67 High St, Biddulph Stoke-on-trent Staffordshire ST8 6AA",
    "addr:housenumber":"67",
    "addr:postcode":"st8 6aa",
    "addr:street":"High St",
    "iso:country":"GB",
    "sg:address":"67 High St, Biddulph",
    "sg:city":"Stoke-on-trent",
    "sg:classifiers":[
        {
            "category":"Shopping",
            "subcategory":"Pharmacy",
            "type":"Retail Goods"
        },
        {
            "category":"Food & Beverages",
            "subcategory":"Groceries & Convenience Stores",
            "type":"Retail Goods"
        }
    ],
    "sg:postcode":"ST8 6AA",
    "sg:province":"Staffordshire",
    "sg:tags":[
        "pharmacist",
        "chemist"
    ],
    "wof:name":"United Norwest Co-Operatives Ltd",
    "wof:placetype":"venue"
},
  "geometry": {"coordinates":[-2.176042,53.115505],"type":"Point"}
}