{
  "type": "Feature",
  "properties": {
    "addr:full":"Loyal North Shropshire District Lodge, St Marys St Whitchurch Cheshire SY13 1QY",
    "addr:postcode":"lodge;sy13 1qy",
    "addr:street":"Loyal North;St Marys St",
    "iso:country":"GB",
    "sg:address":"Loyal North Shropshire District Lodge, St Marys St",
    "sg:city":"Whitchurch",
    "sg:classifiers":[
        {
            "category":"Manufacturing",
            "subcategory":"Tools & Machinery",
            "type":"Manufacturing & Wholesale Goods"
        }
    ],
    "sg:phone":"+44 1939 200673",
    "sg:postcode":"SY13 1QY",
    "sg:province":"Cheshire",
    "sg:tags":[
        "society",
        "friendly"
    ],
    "wof:name":"Oddfellows",
    "wof:placetype":"venue"
},
  "geometry": {"coordinates":[-2.685209,52.970558],"type":"Point"}
}