{
  "type": "Feature",
  "properties": {
    "addr:full":"Curtis House, 34 Third Avenue Hove East Sussex BN3 2PD",
    "addr:housenumber":"34",
    "addr:postcode":"bn3 2pd",
    "addr:street":"Third Avenue",
    "iso:country":"GB",
    "sg:address":"Curtis House, 34 Third Avenue",
    "sg:city":"Hove",
    "sg:classifiers":[
        {
            "category":"Shopping",
            "subcategory":"Clothing, Apparel, & Fashions",
            "type":"Retail Goods"
        }
    ],
    "sg:postcode":"BN3 2PD",
    "sg:province":"East Sussex",
    "sg:tags":[
        "tie",
        "neckwear"
    ],
    "wof:name":"Identity Neckwear",
    "wof:placetype":"venue"
},
  "geometry": {"coordinates":[-0.170321,50.827499],"type":"Point"}
}