{
  "type": "Feature",
  "properties": {
    "iso:country":"GB",
    "sg:address":"Unit 6 Sketchley Lane",
    "sg:city":"Hinckley",
    "sg:classifiers":[
        {
            "category":"Building & Trades",
            "subcategory":"Construction",
            "type":"Services"
        }
    ],
    "sg:phone":"+44 1455 239564",
    "sg:postcode":"LE10 3ES",
    "sg:province":"Leicestershire",
    "sg:tags":[
        "window",
        "replacement"
    ],
    "wof:name":"Staybrite Windows Ltd.",
    "wof:placetype":"venue"
},
  "geometry": {"coordinates":[-1.374649,52.524899],"type":"Point"}
}