{
  "type": "Feature",
  "properties": {
    "addr:full":"Unit 12 Taylors, Gravel La Chigwell Essex IG7 6DQ",
    "addr:housenumber":"unit 12",
    "addr:postcode":"ig7 6dq",
    "addr:street":"Gravel;Chigwell",
    "iso:country":"GB",
    "sg:address":"Unit 12 Taylors, Gravel La",
    "sg:city":"Chigwell",
    "sg:classifiers":[
        {
            "category":"Wholesale",
            "subcategory":"Chemicals & Plastics",
            "type":"Manufacturing & Wholesale Goods"
        }
    ],
    "sg:phone":"+44 20 8501 0500",
    "sg:postcode":"IG7 6DQ",
    "sg:province":"Essex",
    "sg:tags":[
        "retail",
        "freezer",
        "refrigerator"
    ],
    "wof:name":"Lanbourne Refrigeration",
    "wof:placetype":"venue"
},
  "geometry": {"coordinates":[0.0750949979,51.6189460754],"type":"Point"}
}