{
  "type": "Feature",
  "properties": {
    "iso:country":"GB",
    "sg:address":"Sugarbrook Lane, Stokepound",
    "sg:city":"Bromsgrove",
    "sg:classifiers":[
        {
            "category":"Home & Garden",
            "subcategory":"Garden Supply",
            "type":"Retail Goods"
        },
        {
            "category":"Education",
            "subcategory":"Preschool",
            "type":"Public Place"
        }
    ],
    "sg:phone":"+44 1527 833161",
    "sg:postcode":"B60 3AU",
    "sg:province":"Worcestershire",
    "sg:tags":[
        "planting",
        "school",
        "nursery",
        "tree",
        "shrub"
    ],
    "wof:name":"Sugarbrook Nurseries Ltd",
    "wof:placetype":"venue"
},
  "geometry": {"coordinates":[-2.059634,52.310585],"type":"Point"}
}