{
  "type": "Feature",
  "properties": {
    "addr:full":"283 Madeira Drive Arches Brighton East Sussex BN2 1PT",
    "addr:housenumber":"283",
    "addr:postcode":"bn2 1pt",
    "addr:street":"Madeira Drive Arches",
    "iso:country":"GB",
    "sg:address":"283 Madeira Drive Arches",
    "sg:city":"Brighton",
    "sg:classifiers":[
        {
            "category":"Professional",
            "subcategory":"Art Services",
            "type":"Services"
        }
    ],
    "sg:postcode":"BN2 1PT",
    "sg:province":"East Sussex",
    "sg:tags":[
        "framing"
    ],
    "wof:name":"Athina Beach Framing",
    "wof:placetype":"venue"
},
  "geometry": {"coordinates":[-0.128036,50.818096],"type":"Point"}
}