{
  "type": "Feature",
  "properties": {
    "addr:full":"64 Appledore Crescent Sidcup Kent DA14 6RQ",
    "addr:housenumber":"64",
    "addr:postcode":"da14 6rq",
    "addr:street":"Appledore Crescent",
    "iso:country":"GB",
    "sg:address":"64 Appledore Crescent",
    "sg:city":"Sidcup",
    "sg:classifiers":[
        {
            "category":"Health Services",
            "subcategory":"Podiatrist",
            "type":"Services"
        }
    ],
    "sg:phone":"+44 20 8302 8324",
    "sg:postcode":"DA14 6RQ",
    "sg:province":"Kent",
    "sg:tags":[
        "podiatrists",
        "chiropodist"
    ],
    "wof:name":"J Ansell & Son",
    "wof:placetype":"venue"
},
  "geometry": {"coordinates":[0.093107,51.4296302795],"type":"Point"}
}