{
  "type": "Feature",
  "properties": {
    "iso:country":"GB",
    "sg:address":"17 New Leys, Fernhurst",
    "sg:city":"Haslemere",
    "sg:classifiers":[
        {
            "category":"Building & Trades",
            "subcategory":"Construction",
            "type":"Services"
        }
    ],
    "sg:postcode":"GU27 3JY",
    "sg:province":"Hampshire",
    "sg:tags":[
        "builder"
    ],
    "wof:name":"J Holmes & Son",
    "wof:placetype":"venue"
},
  "geometry": {"coordinates":[-0.737244,51.082951],"type":"Point"}
}