{
  "type": "Feature",
  "properties": {
    "iso:country":"GB",
    "sg:address":"Borders General Hospital",
    "sg:city":"Melrose",
    "sg:classifiers":[
        {
            "category":"Social Services",
            "type":"Services"
        },
        {
            "category":"Government",
            "subcategory":"Office",
            "type":"Public Place"
        }
    ],
    "sg:phone":"+44 1896 754333",
    "sg:postcode":"TD6 9BS",
    "sg:province":"Scottish Borders",
    "sg:tags":[
        "local"
    ],
    "wof:name":"Hospital Social Work Team",
    "wof:placetype":"venue"
},
  "geometry": {"coordinates":[-2.737578,55.598831],"type":"Point"}
}