{
  "type": "Feature",
  "properties": {
    "iso:country":"GB",
    "sg:address":"336 Bury Rd",
    "sg:city":"Rochdale",
    "sg:classifiers":[
        {
            "category":"Cafe",
            "type":"Food & Drink"
        }
    ],
    "sg:phone":"+44 1706 640462",
    "sg:postcode":"OL11 4EB",
    "sg:province":"Lancashire",
    "sg:tags":[
        "tea",
        "room"
    ],
    "wof:name":"Elaine's",
    "wof:placetype":"venue"
},
  "geometry": {"coordinates":[-2.1737411022,53.6145896912],"type":"Point"}
}