{
  "type": "Feature",
  "properties": {
    "addr:full":"Forsyth Court, 117 The Headrow Leeds West Yorkshire LS1 5JX",
    "addr:housenumber":"117",
    "addr:postcode":"ls1 5jx",
    "addr:street":"Forsyth;The Headrow",
    "iso:country":"GB",
    "sg:address":"Forsyth Court, 117 The Headrow",
    "sg:city":"Leeds",
    "sg:classifiers":[
        {
            "category":"Professional",
            "subcategory":"Management & Consulting",
            "type":"Services"
        }
    ],
    "sg:postcode":"LS1 5JX",
    "sg:province":"West Yorkshire",
    "sg:tags":[
        "consultant",
        "business"
    ],
    "wof:name":"The Rosewood Partnership (Uk) Ltd.",
    "wof:placetype":"venue"
},
  "geometry": {"coordinates":[-1.5467300415,53.7994003296],"type":"Point"}
}