{
  "type": "Feature",
  "properties": {
    "addr:full":"160a Brick Lane London Greater London E1 6RU",
    "addr:housenumber":"160a",
    "addr:postcode":"e1 6ru",
    "addr:street":"Brick Lane",
    "iso:country":"GB",
    "sg:address":"160a Brick Lane",
    "sg:city":"London",
    "sg:classifiers":[
        {
            "category":"Building & Trades",
            "subcategory":"Pest Control",
            "type":"Services"
        }
    ],
    "sg:phone":"+44 20 7247 2307",
    "sg:postcode":"E1 6RU",
    "sg:province":"Greater London",
    "sg:tags":[
        "fastener"
    ],
    "wof:name":"Reece Buttonhole Works",
    "wof:placetype":"venue"
},
  "geometry": {"coordinates":[-0.0714489967,51.5222206116],"type":"Point"}
}