{
  "type": "Feature",
  "properties": {
    "iso:country":"GB",
    "sg:address":"8 Daykin Close, Darton",
    "sg:city":"Barnsley",
    "sg:classifiers":[
        {
            "category":"Professional",
            "subcategory":"Testing Lab",
            "type":"Services"
        }
    ],
    "sg:postcode":"S75 5HA",
    "sg:province":"South Yorkshire",
    "sg:tags":[
        "inspection",
        "calibration"
    ],
    "wof:name":"Magnetic Analysis Ltd.",
    "wof:placetype":"venue"
},
  "geometry": {"coordinates":[-1.539592,53.58252],"type":"Point"}
}