{
  "type": "Feature",
  "properties": {
    "addr:full":"483 Green Lanes London Greater London N13 4BS",
    "addr:housenumber":"483",
    "addr:postcode":"n13 4bs",
    "addr:street":"Green Lanes",
    "iso:country":"GB",
    "sg:address":"483 Green Lanes",
    "sg:city":"London",
    "sg:classifiers":[
        {
            "category":"Real Estate",
            "subcategory":"Surveying",
            "type":"Services"
        }
    ],
    "sg:postcode":"N13 4BS",
    "sg:province":"Greater London",
    "sg:tags":[
        "building",
        "surveyor"
    ],
    "wof:name":"Adams & Wagstaff Chartered Surveyors",
    "wof:placetype":"venue"
},
  "geometry": {"coordinates":[-0.1052699983,51.6224365234],"type":"Point"}
}