{
  "type": "Feature",
  "properties": {
    "addr:full":"3a Goodge Street London Greater London W1T 2QW",
    "addr:housenumber":"3a",
    "addr:postcode":"w1t 2qw",
    "addr:street":"Goodge Street",
    "iso:country":"GB",
    "sg:address":"3a Goodge Street",
    "sg:city":"London",
    "sg:classifiers":[
        {
            "category":"Personal",
            "subcategory":"Barber",
            "type":"Services"
        }
    ],
    "sg:phone":"+44 20 7637 1809",
    "sg:postcode":"W1T 2QW",
    "sg:province":"Greater London",
    "sg:tags":[
        "men's",
        "hairdresser"
    ],
    "wof:name":"Nicholas Hairdressers",
    "wof:placetype":"venue"
},
  "geometry": {"coordinates":[-0.1339080036,51.5199584961],"type":"Point"}
}