{
  "type": "Feature",
  "properties": {
    "addr:full":"27 Dudley Road, Lye Stourbridge West Midlands DY9 8EX",
    "addr:housenumber":"27",
    "addr:postcode":"dy9 8ex",
    "addr:street":"Dudley Road",
    "iso:country":"GB",
    "sg:address":"27 Dudley Road, Lye",
    "sg:city":"Stourbridge",
    "sg:classifiers":[
        {
            "category":"Professional",
            "subcategory":"Engineering",
            "type":"Services"
        }
    ],
    "sg:phone":"+44 1384 892458",
    "sg:postcode":"DY9 8EX",
    "sg:province":"West Midlands",
    "sg:tags":[
        "precision",
        "engineer"
    ],
    "wof:name":"Portway Tool & Gauge Ltd.",
    "wof:placetype":"venue"
},
  "geometry": {"coordinates":[-2.1174869537,52.4600906372],"type":"Point"}
}