{
  "type": "Feature",
  "properties": {
    "addr:full":"47 West Church Street Buckie Moray AB56 1BP",
    "addr:housenumber":"47",
    "addr:postcode":"ab56 1bp",
    "addr:street":"West Church Street",
    "iso:country":"GB",
    "sg:address":"47 West Church Street",
    "sg:city":"Buckie",
    "sg:classifiers":[
        {
            "category":"Communications",
            "subcategory":"Film & Video Production",
            "type":"Services"
        }
    ],
    "sg:phone":"+44 1542 832345",
    "sg:postcode":"AB56 1BP",
    "sg:province":"Moray",
    "sg:tags":[
        "tv",
        "studio"
    ],
    "wof:name":"Jamiesons Radio & T V",
    "wof:placetype":"venue"
},
  "geometry": {"coordinates":[-2.9686069489,57.6751708984],"type":"Point"}
}