{
  "type": "Feature",
  "properties": {
    "addr:full":"28 Billing Road Northampton Northamptonshire NN1 5AJ",
    "addr:housenumber":"28",
    "addr:postcode":"nn1 5aj",
    "addr:street":"Billing Road",
    "iso:country":"GB",
    "sg:address":"28 Billing Road",
    "sg:city":"Northampton",
    "sg:classifiers":[
        {
            "category":"Building & Trades",
            "subcategory":"Construction",
            "type":"Services"
        }
    ],
    "sg:postcode":"NN1 5AJ",
    "sg:province":"Northamptonshire",
    "sg:tags":[
        "roofing"
    ],
    "wof:name":"Oakleaf Roofing Ltd",
    "wof:placetype":"venue"
},
  "geometry": {"coordinates":[-0.883397,52.238018],"type":"Point"}
}