{
  "type": "Feature",
  "properties": {
    "iso:country":"GB",
    "sg:address":"44 Atholl Street",
    "sg:city":"Perth",
    "sg:classifiers":[
        {
            "category":"Travel",
            "subcategory":"Hotels & Motels",
            "type":"Entertainment"
        },
        {
            "category":"Community Center",
            "subcategory":"Social",
            "type":"Public Place"
        }
    ],
    "sg:phone":"+44 1738 624623",
    "sg:postcode":"PH1 5NN",
    "sg:province":"Perth and Kinross",
    "sg:tags":[
        "house",
        "activity"
    ],
    "wof:name":"Corinna Hotel",
    "wof:placetype":"venue"
},
  "geometry": {"coordinates":[-3.434276104,56.3995666504],"type":"Point"}
}