{
  "type": "Feature",
  "properties": {
    "addr:full":"5 Coates Lane Whitehaven Cumbria CA28 7BZ",
    "addr:housenumber":"5",
    "addr:postcode":"ca28 7bz",
    "addr:street":"Coates Lane",
    "iso:country":"GB",
    "sg:address":"5 Coates Lane",
    "sg:city":"Whitehaven",
    "sg:classifiers":[
        {
            "category":"Manufacturing",
            "subcategory":"Metals",
            "type":"Manufacturing & Wholesale Goods"
        },
        {
            "category":"Professional",
            "subcategory":"Printing & Photocopies",
            "type":"Services"
        }
    ],
    "sg:phone":"+44 1946 693670",
    "sg:postcode":"CA28 7BZ",
    "sg:province":"Cumbria",
    "sg:tags":[
        "engraving",
        "engraver",
        "-",
        "heat",
        "treatment"
    ],
    "wof:name":"Whitehaven Trophies",
    "wof:placetype":"venue"
},
  "geometry": {"coordinates":[-3.5892779827,54.5469970703],"type":"Point"}
}