{
  "type": "Feature",
  "properties": {
    "iso:country":"GB",
    "sg:address":"Deansgate Garage, Keele Road",
    "sg:city":"Newcastle",
    "sg:classifiers":[
        {
            "category":"Autos & Motor Vehicles",
            "subcategory":"Automobile Sales",
            "type":"Retail Goods"
        }
    ],
    "sg:phone":"+44 1782 622141",
    "sg:postcode":"ST5 2HN",
    "sg:province":"Staffordshire",
    "sg:tags":[
        "car"
    ],
    "wof:name":"B S Marson & Sons (Holdings) Ltd.",
    "wof:placetype":"venue"
},
  "geometry": {"coordinates":[-2.228601,53.008801],"type":"Point"}
}