{
  "type": "Feature",
  "properties": {
    "iso:country":"GB",
    "sg:address":"186 Grove Lane, Hale",
    "sg:city":"Altrincham",
    "sg:classifiers":[
        {
            "category":"Shopping",
            "subcategory":"Pharmacy",
            "type":"Retail Goods"
        }
    ],
    "sg:phone":"+44 161 980 2424",
    "sg:postcode":"WA15 8PU",
    "sg:province":"Cheshire",
    "sg:tags":[
        "pharmacist",
        "chemist"
    ],
    "wof:name":"Terry's Chemist",
    "wof:placetype":"venue"
},
  "geometry": {"coordinates":[-2.315738,53.380604],"type":"Point"}
}