{
  "type": "Feature",
  "properties": {
    "addr:full":"Leicester St Northampton Northamptonshire NN1 3RS",
    "addr:postcode":"nn1 3rs",
    "addr:street":"Leicester St",
    "iso:country":"GB",
    "sg:address":"Leicester St",
    "sg:city":"Northampton",
    "sg:classifiers":[
        {
            "category":"Government",
            "subcategory":"Office",
            "type":"Public Place"
        }
    ],
    "sg:postcode":"NN1 3RS",
    "sg:province":"Northamptonshire",
    "sg:tags":[
        "local"
    ],
    "wof:name":"Northampton Borough Council",
    "wof:placetype":"venue"
},
  "geometry": {"coordinates":[-0.896267,52.245712],"type":"Point"}
}