{
  "type": "Feature",
  "properties": {
    "iso:country":"GB",
    "sg:address":"Birchanger Indust Estate",
    "sg:city":"Bishop's Stortford",
    "sg:classifiers":[
        {
            "category":"Organizations",
            "subcategory":"Non-profit Organization",
            "type":"Services"
        }
    ],
    "sg:phone":"+44 1279 461999",
    "sg:postcode":"CM23 2TH",
    "sg:province":"Essex",
    "sg:tags":[
        "organisation",
        "voluntary",
        "charity"
    ],
    "wof:name":"National Meningitis Support Fund",
    "wof:placetype":"venue"
},
  "geometry": {"coordinates":[0.17324,51.884579],"type":"Point"}
}