{
  "type": "Feature",
  "properties": {
    "iso:country":"GB",
    "sg:address":"45 Marlborough Street",
    "sg:city":"Plymouth",
    "sg:classifiers":[
        {
            "category":"Fast Food",
            "type":"Food & Drink"
        }
    ],
    "sg:phone":"+44 1752 563465",
    "sg:postcode":"PL1 4AW",
    "sg:province":"Devon",
    "sg:tags":[
        "away",
        "take"
    ],
    "wof:name":"Julius Chinese Takeout",
    "wof:placetype":"venue"
},
  "geometry": {"coordinates":[-4.1785349846,50.3729705811],"type":"Point"}
}