{
  "type": "Feature",
  "properties": {
    "iso:country":"GB",
    "sg:address":"1168-1170 Melton Road, Syston",
    "sg:city":"Leicester",
    "sg:classifiers":[
        {
            "category":"Professional",
            "subcategory":"Accounting & Tax Preparation",
            "type":"Services"
        }
    ],
    "sg:phone":"+44 116 269 8484",
    "sg:postcode":"LE7 2HB",
    "sg:province":"Leicestershire",
    "sg:tags":[
        "accountant"
    ],
    "wof:name":"Conley Ward",
    "wof:placetype":"venue"
},
  "geometry": {"coordinates":[-1.0765229464,52.696762085],"type":"Point"}
}