{
  "type": "Feature",
  "properties": {
    "addr:full":"358 Soho Rd Birmingham West Midlands B21 9QL",
    "addr:housenumber":"358",
    "addr:postcode":"b21 9ql",
    "addr:street":"Soho Rd",
    "iso:country":"GB",
    "sg:address":"358 Soho Rd",
    "sg:city":"Birmingham",
    "sg:classifiers":[
        {
            "category":"Airline",
            "type":"Transportation"
        }
    ],
    "sg:phone":"+44 121 507 1800",
    "sg:postcode":"B21 9QL",
    "sg:province":"West Midlands",
    "wof:name":"Kyrgyzstan Airlines Ltd",
    "wof:placetype":"venue"
},
  "geometry": {"coordinates":[-1.941738,52.504772],"type":"Point"}
}