{
  "type": "Feature",
  "properties": {
    "iso:country":"GB",
    "sg:address":"30 Pellon Lane",
    "sg:city":"Halifax",
    "sg:classifiers":[
        {
            "category":"Fast Food",
            "type":"Food & Drink"
        },
        {
            "category":"Food & Beverages",
            "subcategory":"Specialty",
            "type":"Retail Goods"
        }
    ],
    "sg:phone":"+44 1422 320885",
    "sg:postcode":"HX1 5SP",
    "sg:province":"West Yorkshire",
    "sg:tags":[
        "delivery",
        "away",
        "snack",
        "take",
        "sandwich"
    ],
    "wof:name":"Belly Busters",
    "wof:placetype":"venue"
},
  "geometry": {"coordinates":[-1.864763,53.724388],"type":"Point"}
}