{
  "type": "Feature",
  "properties": {
    "addr:full":"12 Market Hill Barnsley South Yorkshire S70 2QE",
    "addr:housenumber":"12",
    "addr:postcode":"s70 2qe",
    "addr:street":"Market Hill;Yorkshire",
    "iso:country":"GB",
    "sg:address":"12 Market Hill",
    "sg:city":"Barnsley",
    "sg:classifiers":[
        {
            "category":"Fast Food",
            "type":"Food & Drink"
        }
    ],
    "sg:phone":"+44 1226 242424",
    "sg:postcode":"S70 2QE",
    "sg:province":"South Yorkshire",
    "sg:tags":[
        "away",
        "take"
    ],
    "wof:name":"Americano's Pizza's",
    "wof:placetype":"venue"
},
  "geometry": {"coordinates":[-1.481588006,53.5534896851],"type":"Point"}
}