{
  "type": "Feature",
  "properties": {
    "iso:country":"GB",
    "sg:address":"Dolphin Street",
    "sg:city":"Colyton",
    "sg:classifiers":[
        {
            "category":"Fast Food",
            "type":"Food & Drink"
        },
        {
            "category":"Restaurant",
            "type":"Food & Drink"
        }
    ],
    "sg:phone":"+44 1297 552825",
    "sg:postcode":"EX24 6NA",
    "sg:province":"Devon",
    "sg:tags":[
        "away",
        "-",
        "take",
        "french"
    ],
    "sg:website":"http://www.colyton.net",
    "wof:name":"Cobblers",
    "wof:placetype":"venue"
},
  "geometry": {"coordinates":[-3.069409,50.740891],"type":"Point"}
}