{
  "type": "Feature",
  "properties": {
    "iso:country":"GB",
    "sg:address":"41 Market Street",
    "sg:city":"Bacup",
    "sg:classifiers":[
        {
            "category":"Retail",
            "subcategory":"Funeral Services",
            "type":"Services"
        }
    ],
    "sg:phone":"+44 1706 877982",
    "sg:postcode":"OL13 0AJ",
    "sg:province":"Lancashire",
    "sg:tags":[
        "director"
    ],
    "wof:name":"A Johnson",
    "wof:placetype":"venue"
},
  "geometry": {"coordinates":[-2.2012269497,53.7019462585],"type":"Point"}
}