{
  "type": "Feature",
  "properties": {
    "addr:full":"32 Salt Hill Drive Slough Berkshire SL1 3TH",
    "addr:housenumber":"32",
    "addr:postcode":"sl1 3th",
    "addr:street":"Salt Hill Drive",
    "iso:country":"GB",
    "sg:address":"32 Salt Hill Drive",
    "sg:city":"Slough",
    "sg:classifiers":[
        {
            "category":"Building & Trades",
            "subcategory":"Construction",
            "type":"Services"
        }
    ],
    "sg:postcode":"SL1 3TH",
    "sg:province":"Berkshire",
    "sg:tags":[
        "heating",
        "contractor"
    ],
    "wof:name":"Ronald H Peckover",
    "wof:placetype":"venue"
},
  "geometry": {"coordinates":[-0.610477,51.5131],"type":"Point"}
}