{
  "type": "Feature",
  "properties": {
    "addr:full":"Game Farm, Main Road, West Bilney King's Lynn Norfolk PE32 1HP",
    "addr:postcode":"pe32 1hp",
    "addr:street":"Game;Main Road West Bilney;Lynn",
    "iso:country":"GB",
    "sg:address":"Game Farm, Main Road, West Bilney",
    "sg:city":"King's Lynn",
    "sg:classifiers":[
        {
            "category":"Farming",
            "subcategory":"Livestock Farm",
            "type":"Manufacturing & Wholesale Goods"
        }
    ],
    "sg:phone":"+44 1760 337552",
    "sg:postcode":"PE32 1HP",
    "sg:province":"Norfolk",
    "sg:tags":[
        "others"
    ],
    "wof:name":"Davison & Co",
    "wof:placetype":"venue"
},
  "geometry": {"coordinates":[0.418327,52.757504],"type":"Point"}
}