{
  "type": "Feature",
  "properties": {
    "iso:country":"GB",
    "sg:address":"7 Gwalia Road",
    "sg:city":"Tywyn",
    "sg:classifiers":[
        {
            "category":"Personal",
            "subcategory":"Beauty Salon",
            "type":"Services"
        }
    ],
    "sg:postcode":"LL36 9DH",
    "sg:province":"Gwynedd",
    "sg:tags":[
        "lady",
        "hairdresser"
    ],
    "wof:name":"Sues Salon",
    "wof:placetype":"venue"
},
  "geometry": {"coordinates":[-4.086848,52.592449],"type":"Point"}
}