{
  "type": "Feature",
  "properties": {
    "addr:full":"4 Swinton Mill Cottage Coldstream Northumberland TD12 4JS",
    "addr:housenumber":"4",
    "addr:postcode":"td12 4js",
    "addr:street":"Swinton Mill;Northumberland",
    "iso:country":"GB",
    "sg:address":"4 Swinton Mill Cottage",
    "sg:city":"Coldstream",
    "sg:classifiers":[
        {
            "category":"Building & Trades",
            "subcategory":"Construction",
            "type":"Services"
        }
    ],
    "sg:phone":"+44 1890 840500",
    "sg:postcode":"TD12 4JS",
    "sg:province":"Northumberland",
    "sg:tags":[
        "builder"
    ],
    "wof:name":"J Renwick",
    "wof:placetype":"venue"
},
  "geometry": {"coordinates":[-2.2080740929,55.6359481812],"type":"Point"}
}