{
  "type": "Feature",
  "properties": {
    "addr:full":"23 Salisbury Rd, Chingford London Greater London E4 6TA",
    "addr:housenumber":"23",
    "addr:postcode":"e4 6ta",
    "addr:street":"Salisbury Rd",
    "iso:country":"GB",
    "sg:address":"23 Salisbury Rd, Chingford",
    "sg:city":"London",
    "sg:classifiers":[
        {
            "category":"Building & Trades",
            "subcategory":"Construction",
            "type":"Services"
        }
    ],
    "sg:phone":"+44 20 8524 6858",
    "sg:postcode":"E4 6TA",
    "sg:province":"Greater London",
    "sg:tags":[
        "dry",
        "lining",
        "plasterers",
        "screeders"
    ],
    "wof:name":"Superior Plastering Co Ltd",
    "wof:placetype":"venue"
},
  "geometry": {"coordinates":[-0.015676,51.619728],"type":"Point"}
}