{
  "type": "Feature",
  "properties": {
    "iso:country":"GB",
    "sg:address":"15 Sherbourne Road, Dersingham",
    "sg:city":"King's Lynn",
    "sg:classifiers":[
        {
            "category":"Manufacturing",
            "subcategory":"Lumber",
            "type":"Manufacturing & Wholesale Goods"
        },
        {
            "category":"Government",
            "subcategory":"Office",
            "type":"Public Place"
        }
    ],
    "sg:phone":"+44 1485 544333",
    "sg:postcode":"PE31 6HZ",
    "sg:province":"Norfolk",
    "sg:tags":[
        "merchants",
        "local",
        "importer",
        "agent",
        "timber"
    ],
    "wof:name":"Sawmill Marketing Ltd.",
    "wof:placetype":"venue"
},
  "geometry": {"coordinates":[0.51628,52.84565],"type":"Point"}
}