{
  "type": "Feature",
  "properties": {
    "iso:country":"GB",
    "sg:address":"175-177 Lockwood Road",
    "sg:city":"Huddersfield",
    "sg:classifiers":[
        {
            "category":"Home & Garden",
            "subcategory":"Home Furnishings",
            "type":"Retail Goods"
        }
    ],
    "sg:phone":"+44 1484 512741",
    "sg:postcode":"HD1 3TG",
    "sg:province":"West Yorkshire",
    "sg:tags":[
        "awning",
        "canopy",
        "blinds"
    ],
    "wof:name":"Swift Blinds Ltd.",
    "wof:placetype":"venue"
},
  "geometry": {"coordinates":[-1.792718,53.634613],"type":"Point"}
}