{
  "type": "Feature",
  "properties": {
    "addr:full":"Bakers Ct, 88 Church St Crowthorne Berkshire RG11 7AL",
    "addr:housenumber":"88",
    "addr:postcode":"rg11 7al",
    "addr:street":"Bakers Ct;Church St",
    "iso:country":"GB",
    "sg:address":"Bakers Ct, 88 Church St",
    "sg:city":"Crowthorne",
    "sg:classifiers":[
        {
            "category":"Fast Food",
            "type":"Food & Drink"
        }
    ],
    "sg:phone":"+44 1344 777732",
    "sg:postcode":"RG11 7AL",
    "sg:province":"Berkshire",
    "sg:tags":[
        "away",
        "take"
    ],
    "wof:name":"Shahidas Ltd.",
    "wof:placetype":"venue"
},
  "geometry": {"coordinates":[-0.8019899726,51.3699493408],"type":"Point"}
}