{
  "type": "Feature",
  "properties": {
    "addr:full":"109 Chorley Road, Swinton Manchester Greater Manchester M27 4AA",
    "addr:housenumber":"109",
    "addr:postcode":"m27 4aa",
    "addr:street":"Chorley Road",
    "iso:country":"GB",
    "sg:address":"109 Chorley Road, Swinton",
    "sg:city":"Manchester",
    "sg:classifiers":[
        {
            "category":"Professional",
            "subcategory":"Employment Agencies",
            "type":"Services"
        }
    ],
    "sg:phone":"+44 161 794 8667",
    "sg:postcode":"M27 4AA",
    "sg:province":"Greater Manchester",
    "sg:tags":[
        "consultant"
    ],
    "wof:name":"Linda Taylor",
    "wof:placetype":"venue"
},
  "geometry": {"coordinates":[-2.3370358944,53.5107307434],"type":"Point"}
}