{
  "type": "Feature",
  "properties": {
    "iso:country":"GB",
    "sg:address":"3 Teme St",
    "sg:city":"Tenbury Wells",
    "sg:classifiers":[
        {
            "category":"Building & Trades",
            "subcategory":"Construction",
            "type":"Services"
        }
    ],
    "sg:phone":"+44 1584 810613",
    "sg:postcode":"WR15 8BB",
    "sg:province":"Herefordshire",
    "sg:tags":[
        "builder"
    ],
    "wof:name":"Robert Hunt Builders",
    "wof:placetype":"venue"
},
  "geometry": {"coordinates":[-2.593896,52.311501],"type":"Point"}
}