{
  "type": "Feature",
  "properties": {
    "addr:full":"Oak Lodge, Studland Avenue Wickford Essex SS12 0JF",
    "addr:postcode":"ss12 0jf",
    "addr:street":"Studland Avenue Wickford",
    "iso:country":"GB",
    "sg:address":"Oak Lodge, Studland Avenue",
    "sg:city":"Wickford",
    "sg:classifiers":[
        {
            "category":"Mining & Drilling",
            "type":"Manufacturing & Wholesale Goods"
        }
    ],
    "sg:postcode":"SS12 0JF",
    "sg:province":"Essex",
    "sg:tags":[
        "contractor"
    ],
    "wof:name":"Barcol Ltd.",
    "wof:placetype":"venue"
},
  "geometry": {"coordinates":[0.518915,51.611435],"type":"Point"}
}