{
  "type": "Feature",
  "properties": {
    "iso:country":"GB",
    "sg:address":"25 Lower Gungate",
    "sg:city":"Tamworth",
    "sg:classifiers":[
        {
            "category":"Health Services",
            "subcategory":"Health Practitioner",
            "type":"Services"
        },
        {
            "category":"Shopping",
            "subcategory":"Pharmacy",
            "type":"Retail Goods"
        }
    ],
    "sg:postcode":"B79 7AT",
    "sg:province":"Staffordshire",
    "sg:tags":[
        "acupuncture",
        "medicine",
        "therapy"
    ],
    "wof:name":"Suman Gohil",
    "wof:placetype":"venue"
},
  "geometry": {"coordinates":[-1.694369,52.637745],"type":"Point"}
}