{
  "type": "Feature",
  "properties": {
    "addr:full":"37 The Square, St Annes Road West Lytham St Annes Lancashire FY8 1SE",
    "addr:housenumber":"37",
    "addr:postcode":"fy8 1se",
    "addr:street":"The Square St Annes Road West;St",
    "iso:country":"GB",
    "sg:address":"37 The Square, St Annes Road West",
    "sg:city":"Lytham St Annes",
    "sg:classifiers":[
        {
            "category":"Real Estate",
            "subcategory":"Real Estate Agent",
            "type":"Services"
        }
    ],
    "sg:phone":"+44 1253 725166",
    "sg:postcode":"FY8 1SE",
    "sg:province":"Lancashire",
    "wof:name":"B B G Estate Agencies",
    "wof:placetype":"venue"
},
  "geometry": {"coordinates":[-3.03168,53.7514],"type":"Point"}
}