{
  "type": "Feature",
  "properties": {
    "iso:country":"GB",
    "sg:address":"9-10 Upper Rushall Street",
    "sg:city":"Walsall",
    "sg:classifiers":[
        {
            "category":"Travel",
            "subcategory":"Hotels & Motels",
            "type":"Entertainment"
        }
    ],
    "sg:postcode":"WS1 2HA",
    "sg:province":"West Midlands",
    "wof:name":"Lyndon House Hotel",
    "wof:placetype":"venue"
},
  "geometry": {"coordinates":[-1.9765180349,52.5844917297],"type":"Point"}
}