{
  "type": "Feature",
  "properties": {
    "addr:full":"36 Bravington Close Shepperton Surrey TW17 0JG",
    "addr:housenumber":"36",
    "addr:postcode":"tw17 0jg",
    "addr:street":"Bravington Close",
    "iso:country":"GB",
    "sg:address":"36 Bravington Close",
    "sg:city":"Shepperton",
    "sg:classifiers":[
        {
            "category":"Building & Trades",
            "subcategory":"Construction",
            "type":"Services"
        }
    ],
    "sg:phone":"+44 1932 563676",
    "sg:postcode":"TW17 0JG",
    "sg:province":"Surrey",
    "sg:tags":[
        "demolition",
        "contractor"
    ],
    "wof:name":"B Elliott Demolition",
    "wof:placetype":"venue"
},
  "geometry": {"coordinates":[-0.466206,51.400547],"type":"Point"}
}