{
  "type": "Feature",
  "properties": {
    "iso:country":"GB",
    "sg:address":"41-42 Berners Street",
    "sg:city":"London",
    "sg:classifiers":[
        {
            "category":"Wholesale",
            "subcategory":"Construction Materials",
            "type":"Manufacturing & Wholesale Goods"
        }
    ],
    "sg:postcode":"W1T 3NB",
    "sg:province":"Greater London",
    "sg:tags":[
        "lift"
    ],
    "wof:name":"Wickham Hoist Ltd",
    "wof:placetype":"venue"
},
  "geometry": {"coordinates":[-0.137584,51.51815],"type":"Point"}
}