{
  "type": "Feature",
  "properties": {
    "iso:country":"GB",
    "sg:address":"2 Market Pl",
    "sg:city":"Belford",
    "sg:classifiers":[
        {
            "category":"Manufacturing",
            "subcategory":"Pottery",
            "type":"Manufacturing & Wholesale Goods"
        }
    ],
    "sg:phone":"+44 1668 213090",
    "sg:postcode":"NE70 7ND",
    "sg:province":"Northumberland",
    "wof:name":"Belford Pottery",
    "wof:placetype":"venue"
},
  "geometry": {"coordinates":[-1.8296370506,55.5989341736],"type":"Point"}
}