{
  "type": "Feature",
  "properties": {
    "addr:full":"Wattlesborough Heath Garage, Halfway House Shrewsbury Shropshire SY5 9EG",
    "addr:postcode":"sy5 9eg",
    "iso:country":"GB",
    "sg:address":"Wattlesborough Heath Garage, Halfway House",
    "sg:city":"Shrewsbury",
    "sg:classifiers":[
        {
            "category":"Retail",
            "subcategory":"Auto Repair",
            "type":"Services"
        }
    ],
    "sg:phone":"+44 1743 885018",
    "sg:postcode":"SY5 9EG",
    "sg:province":"Shropshire",
    "sg:tags":[
        "modification",
        "garage",
        "repairer",
        "bodybuilder"
    ],
    "wof:name":"T J Parry & Sons",
    "wof:placetype":"venue"
},
  "geometry": {"coordinates":[-2.9564890862,52.6989173889],"type":"Point"}
}