{
  "type": "Feature",
  "properties": {
    "addr:full":"Chapel Place, The Valley Selkirk Scottish Borders TD7 4DQ",
    "addr:postcode":"td7 4dq",
    "addr:street":"Chapel Place The Valley",
    "iso:country":"GB",
    "sg:address":"Chapel Place, The Valley",
    "sg:city":"Selkirk",
    "sg:classifiers":[
        {
            "category":"Organizations",
            "subcategory":"Membership Organization",
            "type":"Services"
        }
    ],
    "sg:phone":"+44 1750 21371",
    "sg:postcode":"TD7 4DQ",
    "sg:province":"Scottish Borders",
    "sg:tags":[
        "club"
    ],
    "wof:name":"The Royal British Legion Scotland",
    "wof:placetype":"venue"
},
  "geometry": {"coordinates":[-2.8394839764,55.5493354797],"type":"Point"}
}