{
  "type": "Feature",
  "properties": {
    "iso:country":"GB",
    "sg:address":"6 Manners Corner, Manners Way",
    "sg:city":"Southend-on-sea",
    "sg:classifiers":[
        {
            "category":"Food & Beverages",
            "subcategory":"Meat & Fish",
            "type":"Retail Goods"
        }
    ],
    "sg:phone":"+44 1702 337307",
    "sg:postcode":"SS2 6QR",
    "sg:province":"Essex",
    "sg:tags":[
        "chip"
    ],
    "wof:name":"Good Manners Fish to Go",
    "wof:placetype":"venue"
},
  "geometry": {"coordinates":[0.70262,51.562721],"type":"Point"}
}