{
  "type": "Feature",
  "properties": {
    "addr:full":"25 Bold St Liverpool Merseyside L1 4DN",
    "addr:housenumber":"25",
    "addr:postcode":"l1 4dn",
    "addr:street":"Bold St",
    "iso:country":"GB",
    "sg:address":"25 Bold St",
    "sg:city":"Liverpool",
    "sg:classifiers":[
        {
            "category":"Shopping",
            "subcategory":"Bicycles & Sporting Goods",
            "type":"Retail Goods"
        }
    ],
    "sg:postcode":"L1 4DN",
    "sg:province":"Merseyside",
    "sg:tags":[
        "equipment",
        "accessory",
        "camping",
        "cycle"
    ],
    "wof:name":"Y H A Adventure Shops Plc",
    "wof:placetype":"venue"
},
  "geometry": {"coordinates":[-2.9796209335,53.4039154053],"type":"Point"}
}