{
  "type": "Feature",
  "properties": {
    "iso:country":"GB",
    "sg:address":"Oak Tree Lane, Haxby",
    "sg:city":"York",
    "sg:classifiers":[
        {
            "category":"Education",
            "subcategory":"School",
            "type":"Public Place"
        }
    ],
    "sg:phone":"+44 1904 762356",
    "sg:postcode":"YO32 3YH",
    "sg:province":"North Yorkshire",
    "sg:tags":[
        "local",
        "authority"
    ],
    "wof:name":"Headlands County Primary School",
    "wof:placetype":"venue"
},
  "geometry": {"coordinates":[-1.074009,54.015755],"type":"Point"}
}