{
  "type": "Feature",
  "properties": {
    "addr:full":"Housing Advice Private Sector, Farrier Ho, Farrier St Worcester Worcestershire WR1 3ES",
    "addr:postcode":"wr1 3es",
    "addr:street":"St",
    "iso:country":"GB",
    "sg:address":"Housing Advice Private Sector, Farrier Ho, Farrier St",
    "sg:city":"Worcester",
    "sg:classifiers":[
        {
            "category":"Government",
            "subcategory":"Office",
            "type":"Public Place"
        }
    ],
    "sg:phone":"+44 1905 722276",
    "sg:postcode":"WR1 3ES",
    "sg:province":"Worcestershire",
    "sg:tags":[
        "local"
    ],
    "wof:name":"Worcester City Council",
    "wof:placetype":"venue"
},
  "geometry": {"coordinates":[-2.222274,52.191067],"type":"Point"}
}