{
  "type": "Feature",
  "properties": {
    "iso:country":"GB",
    "sg:address":"40 Southgate, Honley",
    "sg:city":"Huddersfield",
    "sg:classifiers":[
        {
            "category":"Communications",
            "subcategory":"Film & Video Production",
            "type":"Services"
        }
    ],
    "sg:postcode":"HD9 6NT",
    "sg:province":"South Yorkshire",
    "sg:tags":[
        "illustrator",
        "artist"
    ],
    "wof:name":"Michelle Drake",
    "wof:placetype":"venue"
},
  "geometry": {"coordinates":[-1.7893090248,53.6027793884],"type":"Point"}
}