{
  "type": "Feature",
  "properties": {
    "iso:country":"GB",
    "sg:address":"4th Floor 10 Little Lever St",
    "sg:city":"Manchester",
    "sg:classifiers":[
        {
            "category":"Government",
            "subcategory":"Post Office",
            "type":"Public Place"
        }
    ],
    "sg:phone":"+44 161 907 8404",
    "sg:postcode":"M1 1HR",
    "sg:province":"Greater Manchester",
    "sg:tags":[
        "print",
        "typesetter"
    ],
    "wof:name":"Guy Foam Type & Image Setting",
    "wof:placetype":"venue"
},
  "geometry": {"coordinates":[-2.23336,53.482117],"type":"Point"}
}