{
  "type": "Feature",
  "properties": {
    "addr:full":"Brook House, Brook Road, Shotton Deeside Flintshire CH5 1HL",
    "addr:postcode":"ch5 1hl",
    "addr:street":"Brook Road",
    "iso:country":"GB",
    "sg:address":"Brook House, Brook Road, Shotton",
    "sg:city":"Deeside",
    "sg:classifiers":[
        {
            "category":"Manufacturing",
            "subcategory":"Tools & Machinery",
            "type":"Manufacturing & Wholesale Goods"
        },
        {
            "category":"Banks & Credit Unions",
            "subcategory":"Financial Services",
            "type":"Services"
        }
    ],
    "sg:postcode":"CH5 1HL",
    "sg:province":"Flintshire",
    "sg:tags":[
        "adviser",
        "friendly",
        "society"
    ],
    "wof:name":"Whittam & Co",
    "wof:placetype":"venue"
},
  "geometry": {"coordinates":[-3.0457770824,53.2131652832],"type":"Point"}
}