{
  "type": "Feature",
  "properties": {
    "addr:full":"23 Edwalton Ave Peterborough Cambridgeshire PE3 6ER",
    "addr:housenumber":"23",
    "addr:postcode":"pe3 6er",
    "addr:street":"Edwalton Ave",
    "iso:country":"GB",
    "sg:address":"23 Edwalton Ave",
    "sg:city":"Peterborough",
    "sg:classifiers":[
        {
            "category":"Building & Trades",
            "subcategory":"Construction",
            "type":"Services"
        }
    ],
    "sg:postcode":"PE3 6ER",
    "sg:province":"Cambridgeshire",
    "sg:tags":[
        "builder"
    ],
    "wof:name":"C & R Builders",
    "wof:placetype":"venue"
},
  "geometry": {"coordinates":[-0.2554540038,52.5790748596],"type":"Point"}
}