{
  "type": "Feature",
  "properties": {
    "addr:full":"24 Pepper Street Nantwich Cheshire CW5 5AB",
    "addr:housenumber":"24",
    "addr:postcode":"cw5 5ab",
    "addr:street":"Pepper Street",
    "iso:country":"GB",
    "sg:address":"24 Pepper Street",
    "sg:city":"Nantwich",
    "sg:classifiers":[
        {
            "category":"Shopping",
            "subcategory":"Crafts & Fabrics",
            "type":"Retail Goods"
        }
    ],
    "sg:phone":"+44 1270 623603",
    "sg:postcode":"CW5 5AB",
    "sg:province":"Cheshire",
    "sg:tags":[
        "shop",
        "linen"
    ],
    "wof:name":"Nightlines",
    "wof:placetype":"venue"
},
  "geometry": {"coordinates":[-2.5219891071,53.0679016113],"type":"Point"}
}