{
  "type": "Feature",
  "properties": {
    "addr:full":"80 Greenfield Road London Greater London E1 1EJ",
    "addr:housenumber":"80",
    "addr:postcode":"e1 1ej",
    "addr:street":"Greenfield Road",
    "iso:country":"GB",
    "sg:address":"80 Greenfield Road",
    "sg:city":"London",
    "sg:classifiers":[
        {
            "category":"Shopping",
            "subcategory":"Clothing, Apparel, & Fashions",
            "type":"Retail Goods"
        },
        {
            "category":"Home & Garden",
            "subcategory":"Home Furnishings",
            "type":"Retail Goods"
        }
    ],
    "sg:phone":"+44 20 7247 1235",
    "sg:postcode":"E1 1EJ",
    "sg:province":"Greater London",
    "sg:tags":[
        "beds",
        "bedding",
        "clothing",
        "blanket"
    ],
    "wof:name":"Simon David & Co. Ltd.",
    "wof:placetype":"venue"
},
  "geometry": {"coordinates":[-0.065149,51.516251],"type":"Point"}
}