{
  "type": "Feature",
  "properties": {
    "addr:full":"13 Charnhill Crescent Bristol City of Bristol BS16 9JU",
    "addr:housenumber":"13",
    "addr:postcode":"bs16 9ju",
    "addr:street":"Charnhill Crescent",
    "iso:country":"GB",
    "sg:address":"13 Charnhill Crescent",
    "sg:city":"Bristol",
    "sg:classifiers":[
        {
            "category":"Professional",
            "subcategory":"Computer Services",
            "type":"Services"
        }
    ],
    "sg:postcode":"BS16 9JU",
    "sg:province":"City of Bristol",
    "sg:tags":[
        "system",
        "software"
    ],
    "wof:name":"Deluxe Corporation Ltd.",
    "wof:placetype":"venue"
},
  "geometry": {"coordinates":[-2.4917008877,51.4782714844],"type":"Point"}
}