{
  "type": "Feature",
  "properties": {
    "addr:full":"7 Hazeldene House, Central Square Telford Shropshire TF3 4JL",
    "addr:housenumber":"7",
    "addr:postcode":"tf3 4jl",
    "addr:street":"Hazeldene House",
    "iso:country":"GB",
    "sg:address":"7 Hazeldene House, Central Square",
    "sg:city":"Telford",
    "sg:classifiers":[
        {
            "category":"Real Estate",
            "subcategory":"Real Estate Agent",
            "type":"Services"
        }
    ],
    "sg:phone":"+44 1952 292300",
    "sg:postcode":"TF3 4JL",
    "sg:province":"Shropshire",
    "wof:name":"Nock Deighton Estate Agents",
    "wof:placetype":"venue"
},
  "geometry": {"coordinates":[-2.44176507,52.6766624451],"type":"Point"}
}