{
  "type": "Feature",
  "properties": {
    "iso:country":"GB",
    "sg:address":"10a5 Elstow Storage Depot, Kempston Hardwick",
    "sg:city":"Bedford",
    "sg:classifiers":[
        {
            "category":"Manufacturing",
            "subcategory":"Metals",
            "type":"Manufacturing & Wholesale Goods"
        }
    ],
    "sg:postcode":"MK45 2NL",
    "sg:province":"Bedfordshire",
    "sg:tags":[
        "work",
        "sheet"
    ],
    "wof:name":"C & P Engineering",
    "wof:placetype":"venue"
},
  "geometry": {"coordinates":[-0.4949940145,52.0279464722],"type":"Point"}
}