{
  "type": "Feature",
  "properties": {
    "iso:country":"GB",
    "sg:address":"137 Stamford Rd",
    "sg:city":"Kettering",
    "sg:classifiers":[
        {
            "category":"Shopping",
            "subcategory":"Crafts & Fabrics",
            "type":"Retail Goods"
        }
    ],
    "sg:postcode":"NN16 8YA",
    "sg:province":"Northamptonshire",
    "sg:tags":[
        "shop",
        "needlecraft",
        "wool"
    ],
    "wof:name":"Rowena Wool Shop",
    "wof:placetype":"venue"
},
  "geometry": {"coordinates":[-0.712458,52.404175],"type":"Point"}
}