{
  "type": "Feature",
  "properties": {
    "addr:full":"2 Albert Road, Fulwood Preston Lancashire PR2 8PJ",
    "addr:housenumber":"2",
    "addr:postcode":"pr2 8pj",
    "addr:street":"Albert Road",
    "iso:country":"GB",
    "sg:address":"2 Albert Road, Fulwood",
    "sg:city":"Preston",
    "sg:classifiers":[
        {
            "category":"Health Services",
            "subcategory":"Health Practitioner",
            "type":"Services"
        },
        {
            "category":"Shopping",
            "subcategory":"Pharmacy",
            "type":"Retail Goods"
        }
    ],
    "sg:phone":"+44 1772 712048",
    "sg:postcode":"PR2 8PJ",
    "sg:province":"Lancashire",
    "sg:tags":[
        "medicine",
        "medical",
        "therapy",
        "treatment",
        "alternative"
    ],
    "wof:name":"Michael Gregson",
    "wof:placetype":"venue"
},
  "geometry": {"coordinates":[-2.702562,53.777641],"type":"Point"}
}