{
  "type": "Feature",
  "properties": {
    "iso:country":"GB",
    "sg:address":"519 Gale Street",
    "sg:city":"Dagenham",
    "sg:classifiers":[
        {
            "category":"Home & Garden",
            "subcategory":"Carpets & Floor Coverings",
            "type":"Retail Goods"
        }
    ],
    "sg:phone":"+44 20 8592 5048",
    "sg:postcode":"RM9 4TP",
    "sg:province":"Essex",
    "sg:tags":[
        "carpets",
        "rug",
        "matting"
    ],
    "wof:name":"York Carpets",
    "wof:placetype":"venue"
},
  "geometry": {"coordinates":[0.127893,51.539631],"type":"Point"}
}