{
  "type": "Feature",
  "properties": {
    "iso:country":"GB",
    "sg:address":"4 The Strand",
    "sg:city":"Dawlish",
    "sg:classifiers":[
        {
            "category":"Food & Beverages",
            "subcategory":"Supermarket",
            "type":"Retail Goods"
        }
    ],
    "sg:phone":"+44 1626 862672",
    "sg:postcode":"EX7 9PS",
    "sg:province":"Devon",
    "wof:name":"Somerfield Stores Ltd",
    "wof:placetype":"venue"
},
  "geometry": {"coordinates":[-3.467219,50.581276],"type":"Point"}
}