{
  "type": "Feature",
  "properties": {
    "addr:full":"28 South View Rise, Loxley Sheffield South Yorkshire S6 6SZ",
    "addr:housenumber":"28",
    "addr:postcode":"s6 6sz",
    "addr:street":"South View Rise",
    "iso:country":"GB",
    "sg:address":"28 South View Rise, Loxley",
    "sg:city":"Sheffield",
    "sg:classifiers":[
        {
            "category":"Health Services",
            "subcategory":"Health Practitioner",
            "type":"Services"
        }
    ],
    "sg:phone":"+44 114 234 0452",
    "sg:postcode":"S6 6SZ",
    "sg:province":"South Yorkshire",
    "sg:tags":[
        "hypnotherapists"
    ],
    "wof:name":"June Boorman",
    "wof:placetype":"venue"
},
  "geometry": {"coordinates":[-1.542106,53.40527],"type":"Point"}
}