{
  "type": "Feature",
  "properties": {
    "iso:country":"GB",
    "sg:address":"2 Woodlands Business Village, Coronation Road",
    "sg:city":"Basingstoke",
    "sg:classifiers":[
        {
            "category":"Home & Garden",
            "subcategory":"Home Furnishings",
            "type":"Retail Goods"
        },
        {
            "category":"Organizations",
            "subcategory":"Community Association",
            "type":"Services"
        }
    ],
    "sg:phone":"+44 1256 818915",
    "sg:postcode":"RG21 4JX",
    "sg:province":"Hampshire",
    "sg:tags":[
        "shelving",
        "installers",
        "system",
        "supplier",
        "diy",
        "racking"
    ],
    "wof:name":"Createability Ltd",
    "wof:placetype":"venue"
},
  "geometry": {"coordinates":[-1.083088994,51.2624435425],"type":"Point"}
}