{
  "type": "Feature",
  "properties": {
    "addr:full":"The Acorns, Pinstone Way Gerrards Cross Buckinghamshire SL9 7BJ",
    "addr:postcode":"sl9 7bj",
    "addr:street":"Pinstone Way",
    "iso:country":"GB",
    "sg:address":"The Acorns, Pinstone Way",
    "sg:city":"Gerrards Cross",
    "sg:classifiers":[
        {
            "category":"Building & Trades",
            "subcategory":"Plumbing",
            "type":"Services"
        }
    ],
    "sg:phone":"+44 1753 883067",
    "sg:postcode":"SL9 7BJ",
    "sg:province":"Buckinghamshire",
    "sg:tags":[
        "heating"
    ],
    "wof:name":"R & G Plumbing & Heating",
    "wof:placetype":"venue"
},
  "geometry": {"coordinates":[-0.5625789762,51.5789756775],"type":"Point"}
}