{
  "type": "Feature",
  "properties": {
    "addr:full":"8 Lyon Clo, Penarth Rd Cardiff Cardiff CF11 8TZ",
    "addr:housenumber":"8",
    "addr:postcode":"cf11 8tz",
    "addr:street":"Lyon Clo Penarth Rd",
    "iso:country":"GB",
    "sg:address":"8 Lyon Clo, Penarth Rd",
    "sg:city":"Cardiff",
    "sg:classifiers":[
        {
            "category":"Home & Garden",
            "subcategory":"Hardware",
            "type":"Retail Goods"
        }
    ],
    "sg:postcode":"CF11 8TZ",
    "sg:province":"Cardiff",
    "sg:tags":[
        "equipment",
        "heating"
    ],
    "wof:name":"Exotherm Products Ltd",
    "wof:placetype":"venue"
},
  "geometry": {"coordinates":[-3.197539,51.460236],"type":"Point"}
}