{
  "type": "Feature",
  "properties": {
    "iso:country":"GB",
    "sg:address":"Victoria House, Garnett Street",
    "sg:city":"Bradford",
    "sg:classifiers":[
        {
            "category":"Building & Trades",
            "subcategory":"Construction",
            "type":"Services"
        }
    ],
    "sg:postcode":"BD3 9HJ",
    "sg:province":"West Yorkshire",
    "sg:tags":[
        "demolition",
        "contractor"
    ],
    "wof:name":"W & S Reidy",
    "wof:placetype":"venue"
},
  "geometry": {"coordinates":[-1.7392139435,53.7964286804],"type":"Point"}
}