{
  "type": "Feature",
  "properties": {
    "iso:country":"GB",
    "sg:address":"99 Smarts Lane",
    "sg:city":"Loughton",
    "sg:classifiers":[
        {
            "category":"Bars & Pubs",
            "type":"Food & Drink"
        },
        {
            "category":"Community Center",
            "subcategory":"Social",
            "type":"Public Place"
        }
    ],
    "sg:phone":"+44 20 8502 1382",
    "sg:postcode":"IG10 4BP",
    "sg:province":"Essex",
    "sg:tags":[
        "pubs",
        "house",
        "inn",
        "activity"
    ],
    "wof:name":"Carpenters Arms",
    "wof:placetype":"venue"
},
  "geometry": {"coordinates":[0.052927,51.647629],"type":"Point"}
}