{
  "type": "Feature",
  "properties": {
    "addr:full":"165 Lunsford Lane Aylesford Kent ME20 6HP",
    "addr:housenumber":"165",
    "addr:postcode":"me20 6hp",
    "addr:street":"Lunsford Lane",
    "iso:country":"GB",
    "sg:address":"165 Lunsford Lane",
    "sg:city":"Aylesford",
    "sg:classifiers":[
        {
            "category":"Building & Trades",
            "subcategory":"Construction",
            "type":"Services"
        }
    ],
    "sg:phone":"+44 1732 846755",
    "sg:postcode":"ME20 6HP",
    "sg:province":"Kent",
    "sg:tags":[
        "builder"
    ],
    "wof:name":"Able Trades General Builders & Developers",
    "wof:placetype":"venue"
},
  "geometry": {"coordinates":[0.43343,51.30558],"type":"Point"}
}