{
  "type": "Feature",
  "properties": {
    "iso:country":"GB",
    "sg:address":"2 Fairways",
    "sg:city":"Stanmore",
    "sg:classifiers":[
        {
            "category":"Building & Trades",
            "subcategory":"Construction",
            "type":"Services"
        }
    ],
    "sg:phone":"+44 20 8905 0644",
    "sg:postcode":"HA7 1JG",
    "sg:province":"Greater London",
    "sg:tags":[
        "builder"
    ],
    "wof:name":"Kaystar Construction",
    "wof:placetype":"venue"
},
  "geometry": {"coordinates":[-0.296401,51.599426],"type":"Point"}
}