{
  "type": "Feature",
  "properties": {
    "iso:country":"GB",
    "sg:address":"Bottomley Bank Farm, Bottomley Bank Lane, Crawshawbooth",
    "sg:city":"Rossendale",
    "sg:classifiers":[
        {
            "category":"Farming",
            "subcategory":"Livestock Farm",
            "type":"Manufacturing & Wholesale Goods"
        },
        {
            "category":"Farming",
            "subcategory":"Farm",
            "type":"Manufacturing & Wholesale Goods"
        }
    ],
    "sg:phone":"+44 1706 214347",
    "sg:postcode":"BB4 8TL",
    "sg:province":"Lancashire",
    "sg:tags":[
        "mixed",
        "crop",
        "others"
    ],
    "wof:name":"Briggs R & L A",
    "wof:placetype":"venue"
},
  "geometry": {"coordinates":[-2.275276,53.728302],"type":"Point"}
}