{
  "type": "Feature",
  "properties": {
    "addr:full":"160 Ampthill Road Bedford Bedfordshire MK42 9PU",
    "addr:housenumber":"160",
    "addr:postcode":"mk42 9pu",
    "addr:street":"Ampthill Road",
    "iso:country":"GB",
    "sg:address":"160 Ampthill Road",
    "sg:city":"Bedford",
    "sg:classifiers":[
        {
            "category":"Shopping",
            "subcategory":"News",
            "type":"Retail Goods"
        }
    ],
    "sg:phone":"+44 1234 358501",
    "sg:postcode":"MK42 9PU",
    "sg:province":"Bedfordshire",
    "sg:tags":[
        "newsagent"
    ],
    "wof:name":"Gharu's Superstore",
    "wof:placetype":"venue"
},
  "geometry": {"coordinates":[-0.4730319977,52.122215271],"type":"Point"}
}