{
  "type": "Feature",
  "properties": {
    "iso:country":"GB",
    "sg:address":"22 Crescent Way",
    "sg:city":"Orpington",
    "sg:classifiers":[
        {
            "category":"Shopping",
            "subcategory":"Pets & Pet Supplies",
            "type":"Retail Goods"
        }
    ],
    "sg:phone":"+44 1689 856361",
    "sg:postcode":"BR6 9LS",
    "sg:province":"Kent",
    "wof:name":"Pet Perfection",
    "wof:placetype":"venue"
},
  "geometry": {"coordinates":[0.087961,51.360035],"type":"Point"}
}