{
  "type": "Feature",
  "properties": {
    "iso:country":"GB",
    "sg:address":"24 Rosemount Place",
    "sg:city":"Aberdeen",
    "sg:classifiers":[
        {
            "category":"Home & Garden",
            "subcategory":"Home Furnishings",
            "type":"Retail Goods"
        },
        {
            "category":"Home & Garden",
            "subcategory":"Building Materials",
            "type":"Retail Goods"
        }
    ],
    "sg:phone":"+44 20 8855 5404",
    "sg:postcode":"AB25 2XU",
    "sg:province":"Aberdeen City",
    "sg:tags":[
        "furnishers",
        "bathroom",
        "planner"
    ],
    "wof:name":"Elegant Bathrooms",
    "wof:placetype":"venue"
},
  "geometry": {"coordinates":[-2.112023,57.150734],"type":"Point"}
}