{
  "type": "Feature",
  "properties": {
    "iso:country":"GB",
    "sg:address":"Castle View",
    "sg:city":"Liskeard",
    "sg:classifiers":[
        {
            "category":"Insurance",
            "subcategory":"Insurance Agent",
            "type":"Services"
        }
    ],
    "sg:phone":"+44 1579 342206",
    "sg:postcode":"PL14 3AW",
    "sg:province":"Cornwall",
    "wof:name":"Trevor Maybee Insurance",
    "wof:placetype":"venue"
},
  "geometry": {"coordinates":[-4.4624538422,50.4548034668],"type":"Point"}
}