{
  "type": "Feature",
  "properties": {
    "addr:full":"Unit 9, Sidings Industrial Estate, Hound Road Southampton Hampshire SO31 5QA",
    "addr:housenumber":"unit 9",
    "addr:postcode":"so31 5qa",
    "addr:street":"Sidings Industrial Estate Hound Road",
    "iso:country":"GB",
    "sg:address":"Unit 9, Sidings Industrial Estate, Hound Road",
    "sg:city":"Southampton",
    "sg:classifiers":[
        {
            "category":"Sports & Exercise",
            "subcategory":"Race Track",
            "type":"Entertainment"
        }
    ],
    "sg:phone":"+44 23 8045 7178",
    "sg:postcode":"SO31 5QA",
    "sg:province":"Hampshire",
    "sg:tags":[
        "motor"
    ],
    "wof:name":"Tom Denyer Racing",
    "wof:placetype":"venue"
},
  "geometry": {"coordinates":[-1.33921,50.872391],"type":"Point"}
}