{
  "type": "Feature",
  "properties": {
    "iso:country":"GB",
    "sg:address":"100 Sheep Street",
    "sg:city":"Bicester",
    "sg:classifiers":[
        {
            "category":"Shopping",
            "subcategory":"Optician",
            "type":"Retail Goods"
        },
        {
            "category":"Health Services",
            "subcategory":"Optometrist",
            "type":"Services"
        }
    ],
    "sg:phone":"+44 1869 242740",
    "sg:postcode":"OX26 6LP",
    "sg:province":"Oxfordshire",
    "sg:tags":[
        "opthalmic"
    ],
    "wof:name":"BERNARD J CONWAY",
    "wof:placetype":"venue"
},
  "geometry": {"coordinates":[-1.1529860497,51.8999328613],"type":"Point"}
}