{
  "type": "Feature",
  "properties": {
    "addr:full":"Unit 7 Mayfields Wks Redditch Warwickshire B98 7DU",
    "addr:housenumber":"unit 7",
    "addr:postcode":"b98 7du",
    "addr:street":"Mayfields Wks",
    "iso:country":"GB",
    "sg:address":"Unit 7 Mayfields Wks",
    "sg:city":"Redditch",
    "sg:classifiers":[
        {
            "category":"Retail",
            "subcategory":"Auto Repair",
            "type":"Services"
        }
    ],
    "sg:postcode":"B98 7DU",
    "sg:province":"Warwickshire",
    "sg:tags":[
        "modification",
        "garage"
    ],
    "wof:name":"Strugnell,T D,",
    "wof:placetype":"venue"
},
  "geometry": {"coordinates":[-1.938859,52.299049],"type":"Point"}
}