{
  "type": "Feature",
  "properties": {
    "iso:country":"GB",
    "sg:address":"10 Manor St",
    "sg:city":"Falkirk",
    "sg:classifiers":[
        {
            "category":"Recreation",
            "subcategory":"Fishing",
            "type":"Entertainment"
        }
    ],
    "sg:phone":"+44 1324 625086",
    "sg:postcode":"FK1 1NH",
    "sg:province":"Falkirk",
    "sg:tags":[
        "angling"
    ],
    "wof:name":"Crockarts of Stirling",
    "wof:placetype":"venue"
},
  "geometry": {"coordinates":[-3.784462,55.999588],"type":"Point"}
}