{
  "type": "Feature",
  "properties": {
    "iso:country":"GB",
    "sg:address":"15 Bideford Street",
    "sg:city":"Sunderland",
    "sg:classifiers":[
        {
            "category":"Building & Trades",
            "subcategory":"Cleaning & Sanitation",
            "type":"Services"
        }
    ],
    "sg:phone":"+44 191 514 4557",
    "sg:postcode":"SR2 9QW",
    "sg:province":"Tyne and Wear",
    "sg:tags":[
        "cleaner",
        "window"
    ],
    "wof:name":"Phoenix Window Cleaning",
    "wof:placetype":"venue"
},
  "geometry": {"coordinates":[-1.365635,54.886478],"type":"Point"}
}