{
  "type": "Feature",
  "properties": {
    "iso:country":"GB",
    "sg:address":"17 Victoria Rd",
    "sg:city":"Colne",
    "sg:classifiers":[
        {
            "category":"Food & Beverages",
            "subcategory":"Meat & Fish",
            "type":"Retail Goods"
        }
    ],
    "sg:phone":"+44 1282 842425",
    "sg:postcode":"BB8 6UN",
    "sg:province":"Lancashire",
    "sg:tags":[
        "butcher"
    ],
    "wof:name":"David Lancaster",
    "wof:placetype":"venue"
},
  "geometry": {"coordinates":[-2.1437370777,53.9165916443],"type":"Point"}
}