{
  "type": "Feature",
  "properties": {
    "iso:country":"GB",
    "sg:address":"94 High Street",
    "sg:city":"Sevenoaks",
    "sg:classifiers":[
        {
            "category":"Bars & Pubs",
            "type":"Food & Drink"
        },
        {
            "category":"Shopping",
            "subcategory":"Books",
            "type":"Retail Goods"
        }
    ],
    "sg:phone":"+44 1732 743144",
    "sg:postcode":"TN13 1LP",
    "sg:province":"Kent",
    "sg:tags":[
        "bookseller",
        "pubs",
        "inn"
    ],
    "wof:name":"Bligh's Bargain Bookstores Ltd.",
    "wof:placetype":"venue"
},
  "geometry": {"coordinates":[0.1930370033,51.2704963684],"type":"Point"}
}