{
  "type": "Feature",
  "properties": {
    "iso:country":"GB",
    "sg:address":"Unit 14 Chase Lane Indust Est, Eastern Av",
    "sg:city":"Gloucester",
    "sg:classifiers":[
        {
            "category":"Building & Trades",
            "subcategory":"Construction",
            "type":"Services"
        }
    ],
    "sg:phone":"+44 1452 303061",
    "sg:postcode":"GL4 6PH",
    "sg:province":"Gloucestershire",
    "sg:tags":[
        "welder"
    ],
    "wof:name":"Hawk Welding Services",
    "wof:placetype":"venue"
},
  "geometry": {"coordinates":[-2.22517,51.853088],"type":"Point"}
}