{
  "type": "Feature",
  "properties": {
    "iso:country":"GB",
    "sg:address":"1 Main Street",
    "sg:city":"Coatbridge",
    "sg:classifiers":[
        {
            "category":"Banks & Credit Unions",
            "subcategory":"Bank",
            "type":"Services"
        }
    ],
    "sg:phone":"+44 1236 423065",
    "sg:postcode":"ML5 3AJ",
    "sg:province":"North Lanarkshire",
    "wof:name":"Airdrie Savings Bank",
    "wof:placetype":"venue"
},
  "geometry": {"coordinates":[-4.029066,55.862545],"type":"Point"}
}