{
  "type": "Feature",
  "properties": {
    "iso:country":"GB",
    "sg:address":"Elms Farm, Mount Bures",
    "sg:city":"Bures",
    "sg:classifiers":[
        {
            "category":"Farming",
            "subcategory":"Crops",
            "type":"Manufacturing & Wholesale Goods"
        },
        {
            "category":"Farming",
            "subcategory":"Livestock Farm",
            "type":"Manufacturing & Wholesale Goods"
        }
    ],
    "sg:phone":"+44 1787 227393",
    "sg:postcode":"CO8 5BA",
    "sg:province":"Essex",
    "sg:tags":[
        "arable",
        "others"
    ],
    "wof:name":"G W R Lucking & Son",
    "wof:placetype":"venue"
},
  "geometry": {"coordinates":[0.7706599832,51.9718017578],"type":"Point"}
}