{
  "type": "Feature",
  "properties": {
    "addr:full":"Wearde Farm, Wearde Road Saltash Cornwall PL12 4AS",
    "addr:postcode":"pl12 4as",
    "addr:street":"Wearde Road",
    "iso:country":"GB",
    "sg:address":"Wearde Farm, Wearde Road",
    "sg:city":"Saltash",
    "sg:classifiers":[
        {
            "category":"Building & Trades",
            "subcategory":"Construction",
            "type":"Services"
        }
    ],
    "sg:phone":"+44 1752 843205",
    "sg:postcode":"PL12 4AS",
    "sg:province":"Cornwall",
    "sg:tags":[
        "demolition",
        "contractor"
    ],
    "wof:name":"Alan Maunder",
    "wof:placetype":"venue"
},
  "geometry": {"coordinates":[-4.214715,50.406467],"type":"Point"}
}