{
  "type": "Feature",
  "properties": {
    "iso:country":"GB",
    "sg:address":"Rose Cottage, Engine Lane, Yarbough",
    "sg:city":"Louth",
    "sg:classifiers":[
        {
            "category":"Building & Trades",
            "subcategory":"Construction",
            "type":"Services"
        }
    ],
    "sg:phone":"+44 1507 363855",
    "sg:postcode":"LN11 0PW",
    "sg:province":"Lincolnshire",
    "sg:tags":[
        "builder"
    ],
    "wof:name":"H Braithwaite & Son",
    "wof:placetype":"venue"
},
  "geometry": {"coordinates":[0.0307,53.415482],"type":"Point"}
}