{
  "type": "Feature",
  "properties": {
    "addr:full":"77 Frenchay Close Bristol City of Bristol BS16 2QJ",
    "addr:housenumber":"77",
    "addr:postcode":"bs16 2qj",
    "addr:street":"Frenchay Close",
    "iso:country":"GB",
    "sg:address":"77 Frenchay Close",
    "sg:city":"Bristol",
    "sg:classifiers":[
        {
            "category":"Professional",
            "subcategory":"Management & Consulting",
            "type":"Services"
        }
    ],
    "sg:postcode":"BS16 2QJ",
    "sg:province":"City of Bristol",
    "sg:tags":[
        "consultant",
        "business"
    ],
    "wof:name":"Eve Forbes Consultancy Ltd.",
    "wof:placetype":"venue"
},
  "geometry": {"coordinates":[-2.520608902,51.4909591675],"type":"Point"}
}