{
  "type": "Feature",
  "properties": {
    "iso:country":"GB",
    "sg:address":"Park Road",
    "sg:city":"Camberley",
    "sg:classifiers":[
        {
            "category":"Community Center",
            "type":"Public Place"
        }
    ],
    "sg:phone":"+44 1276 26877",
    "sg:postcode":"GU15 2LW",
    "sg:province":"Berkshire",
    "sg:tags":[
        "recreation",
        "leisure",
        "centre"
    ],
    "wof:name":"Watchetts Recreation Ground",
    "wof:placetype":"venue"
},
  "geometry": {"coordinates":[-0.742949,51.334694],"type":"Point"}
}