{
  "type": "Feature",
  "properties": {
    "addr:full":"6 St Johns Road Newbury Berkshire RG14 7LW",
    "addr:housenumber":"6",
    "addr:postcode":"rg14 7lw",
    "addr:street":"St Johns Road",
    "iso:country":"GB",
    "sg:address":"6 St Johns Road",
    "sg:city":"Newbury",
    "sg:classifiers":[
        {
            "category":"Health Services",
            "subcategory":"Doctor",
            "type":"Services"
        }
    ],
    "sg:phone":"+44 1635 41495",
    "sg:postcode":"RG14 7LW",
    "sg:province":"Berkshire",
    "sg:tags":[
        "practitioners"
    ],
    "wof:name":"Eastfield House Surgery",
    "wof:placetype":"venue"
},
  "geometry": {"coordinates":[-1.32327,51.395477],"type":"Point"}
}