{
  "type": "Feature",
  "properties": {
    "iso:country":"GB",
    "sg:address":"Unit 12/13 Essington Light Indu, Strial Estate, Bognop Road Essington",
    "sg:city":"Wolverhampton",
    "sg:classifiers":[
        {
            "category":"Professional",
            "subcategory":"Engineering",
            "type":"Services"
        }
    ],
    "sg:postcode":"WV11 2BH",
    "sg:province":"Staffordshire",
    "sg:tags":[
        "engineer"
    ],
    "wof:name":"Chevron Supplies Ltd.",
    "wof:placetype":"venue"
},
  "geometry": {"coordinates":[-2.121669,52.58865],"type":"Point"}
}