{
  "type": "Feature",
  "properties": {
    "addr:full":"Unit 8 Barton Arcade, Deansgate Manchester Greater Manchester M3 2BB",
    "addr:housenumber":"unit 8;arcade",
    "addr:postcode":"m3 2bb",
    "addr:street":"Barton;Deansgate",
    "iso:country":"GB",
    "sg:address":"Unit 8 Barton Arcade, Deansgate",
    "sg:city":"Manchester",
    "sg:classifiers":[
        {
            "category":"Food & Beverages",
            "subcategory":"Liquor & Beverages",
            "type":"Retail Goods"
        }
    ],
    "sg:phone":"+44 161 834 7328",
    "sg:postcode":"M3 2BB",
    "sg:province":"Greater Manchester",
    "sg:tags":[
        "beer",
        "wine",
        "spirit",
        "wines"
    ],
    "wof:name":"Oddbins Ltd",
    "wof:placetype":"venue"
},
  "geometry": {"coordinates":[-2.246374,53.482346],"type":"Point"}
}