{
  "type": "Feature",
  "properties": {
    "iso:country":"GB",
    "sg:address":"Washington Rd",
    "sg:city":"Reading",
    "sg:classifiers":[
        {
            "category":"Education",
            "subcategory":"School",
            "type":"Public Place"
        }
    ],
    "sg:phone":"+44 118 947 3129",
    "sg:postcode":"RG4 5AA",
    "sg:province":"Berkshire",
    "sg:tags":[
        "local",
        "authority"
    ],
    "wof:name":"St Anne's R C Primary",
    "wof:placetype":"venue"
},
  "geometry": {"coordinates":[-0.965664,51.46701],"type":"Point"}
}