{
  "type": "Feature",
  "properties": {
    "addr:full":"Coal Yard, Bolham Retford Nottinghamshire DN22 9JG",
    "addr:postcode":"dn22 9jg",
    "iso:country":"GB",
    "sg:address":"Coal Yard, Bolham",
    "sg:city":"Retford",
    "sg:classifiers":[
        {
            "category":"Utilities",
            "subcategory":"Fuel Oil & Lpg",
            "type":"Services"
        }
    ],
    "sg:phone":"+44 1777 702428",
    "sg:postcode":"DN22 9JG",
    "sg:province":"Nottinghamshire",
    "sg:tags":[
        "coal",
        "smokeless"
    ],
    "wof:name":"P N Fennessy",
    "wof:placetype":"venue"
},
  "geometry": {"coordinates":[-0.9378039837,53.3366584778],"type":"Point"}
}