{
  "type": "Feature",
  "properties": {
    "addr:full":"7 Manor Crescent, Bursledon Southampton Hampshire SO31 8DQ",
    "addr:housenumber":"7",
    "addr:postcode":"so31 8dq",
    "addr:street":"Manor Crescent",
    "iso:country":"GB",
    "sg:address":"7 Manor Crescent, Bursledon",
    "sg:city":"Southampton",
    "sg:classifiers":[
        {
            "category":"Health Services",
            "subcategory":"Doctor",
            "type":"Services"
        }
    ],
    "sg:phone":"+44 23 8040 4671",
    "sg:postcode":"SO31 8DQ",
    "sg:province":"Hampshire",
    "sg:tags":[
        "practitioners"
    ],
    "wof:name":"Dr Bauchop",
    "wof:placetype":"venue"
},
  "geometry": {"coordinates":[-1.322877,50.890018],"type":"Point"}
}