{
  "type": "Feature",
  "properties": {
    "addr:full":"156 High Street Burton On Trent Derbyshire DE14 1JE",
    "addr:housenumber":"156",
    "addr:postcode":"de14 1je",
    "addr:street":"High Street",
    "iso:country":"GB",
    "sg:address":"156 High Street",
    "sg:city":"Burton On Trent",
    "sg:classifiers":[
        {
            "category":"Farming",
            "subcategory":"Livestock Farm",
            "type":"Manufacturing & Wholesale Goods"
        }
    ],
    "sg:phone":"+44 1283 517019",
    "sg:postcode":"DE14 1JE",
    "sg:province":"Derbyshire",
    "sg:tags":[
        "breeder"
    ],
    "wof:name":"Brian Johnson",
    "wof:placetype":"venue"
},
  "geometry": {"coordinates":[-1.629365,52.803036],"type":"Point"}
}