{
  "type": "Feature",
  "properties": {
    "addr:full":"68a Sitwell Street, Spondon Derby Derbyshire DE21 7FG",
    "addr:housenumber":"68a",
    "addr:postcode":"de21 7fg",
    "addr:street":"Sitwell Street",
    "iso:country":"GB",
    "sg:address":"68a Sitwell Street, Spondon",
    "sg:city":"Derby",
    "sg:classifiers":[
        {
            "category":"Banks & Credit Unions",
            "subcategory":"Financial Services",
            "type":"Services"
        }
    ],
    "sg:phone":"+44 1332 670301",
    "sg:postcode":"DE21 7FG",
    "sg:province":"Derbyshire",
    "sg:tags":[
        "building",
        "society"
    ],
    "wof:name":"Derbyshire Building Society",
    "wof:placetype":"venue"
},
  "geometry": {"coordinates":[-1.404411,52.920506],"type":"Point"}
}