{
  "type": "Feature",
  "properties": {
    "iso:country":"GB",
    "sg:address":"Lenten Ho, Lenten St",
    "sg:city":"Alton",
    "sg:classifiers":[
        {
            "category":"Health Services",
            "subcategory":"Clinic",
            "type":"Services"
        }
    ],
    "sg:phone":"+44 1420 543511",
    "sg:postcode":"GU34 1HG",
    "sg:province":"Hampshire",
    "sg:tags":[
        "medical"
    ],
    "wof:name":"Merck Biomaterials",
    "wof:placetype":"venue"
},
  "geometry": {"coordinates":[-0.981462,51.149055],"type":"Point"}
}