{
  "type": "Feature",
  "properties": {
    "addr:full":"65 Aylesbury Street, Bletchly Milton Keynes Buckinghamshire MK2 2BJ",
    "addr:housenumber":"65",
    "addr:postcode":"mk2 2bj",
    "addr:street":"Aylesbury Street",
    "iso:country":"GB",
    "sg:address":"65 Aylesbury Street, Bletchly",
    "sg:city":"Milton Keynes",
    "sg:classifiers":[
        {
            "category":"Professional",
            "subcategory":"Computer Services",
            "type":"Services"
        }
    ],
    "sg:postcode":"MK2 2BJ",
    "sg:province":"Buckinghamshire",
    "sg:tags":[
        "system",
        "software"
    ],
    "wof:name":"Depson Business Systems",
    "wof:placetype":"venue"
},
  "geometry": {"coordinates":[-0.716568,51.997559],"type":"Point"}
}