{
  "type": "Feature",
  "properties": {
    "iso:country":"GB",
    "sg:address":"69 The Horsefair",
    "sg:city":"Bristol",
    "sg:classifiers":[
        {
            "category":"Shopping",
            "subcategory":"Shoes",
            "type":"Retail Goods"
        }
    ],
    "sg:phone":"+44 117 921 5233",
    "sg:postcode":"BS1 3JP",
    "sg:province":"City of Bristol",
    "sg:tags":[
        "shop"
    ],
    "wof:name":"K Shoes",
    "wof:placetype":"venue"
},
  "geometry": {"coordinates":[-2.588474,51.458931],"type":"Point"}
}