{
  "type": "Feature",
  "properties": {
    "iso:country":"GB",
    "sg:address":"6 Nottingham Street",
    "sg:city":"London",
    "sg:classifiers":[
        {
            "category":"Professional",
            "subcategory":"Art Services",
            "type":"Services"
        }
    ],
    "sg:postcode":"W1U 5EJ",
    "sg:province":"Greater London",
    "sg:tags":[
        "consultant",
        "design"
    ],
    "wof:name":"Thames McGurk Ltd.",
    "wof:placetype":"venue"
},
  "geometry": {"coordinates":[-0.1528040022,51.5214538574],"type":"Point"}
}