{
  "type": "Feature",
  "properties": {
    "addr:full":"Cop Hill Huddersfield West Yorkshire HD7 5XA",
    "addr:postcode":"hd7 5xa",
    "addr:street":"Cop Hill",
    "iso:country":"GB",
    "sg:address":"Cop Hill",
    "sg:city":"Huddersfield",
    "sg:classifiers":[
        {
            "category":"Bars & Pubs",
            "type":"Food & Drink"
        },
        {
            "category":"Restaurant",
            "type":"Food & Drink"
        }
    ],
    "sg:phone":"+44 1484 844410",
    "sg:postcode":"HD7 5XA",
    "sg:province":"West Yorkshire",
    "sg:tags":[
        "-"
    ],
    "wof:name":"Rose & Crown The",
    "wof:placetype":"venue"
},
  "geometry": {"coordinates":[-1.910264,53.62096],"type":"Point"}
}