{
  "type": "Feature",
  "properties": {
    "iso:country":"GB",
    "sg:address":"112 Ravenswood Rise",
    "sg:city":"Livingston",
    "sg:classifiers":[
        {
            "category":"Social Services",
            "subcategory":"Job Training",
            "type":"Services"
        }
    ],
    "sg:phone":"+44 1506 496015",
    "sg:postcode":"EH54 6PG",
    "sg:province":"West Lothian",
    "sg:tags":[
        "translator",
        "interpreter"
    ],
    "wof:name":"Alnet Technical Translations & Electronic Services",
    "wof:placetype":"venue"
},
  "geometry": {"coordinates":[-3.5183660984,55.8748474121],"type":"Point"}
}