{
  "type": "Feature",
  "properties": {
    "iso:country":"GB",
    "sg:address":"65 Gudge Heath Lane",
    "sg:city":"Fareham",
    "sg:classifiers":[
        {
            "category":"Shopping",
            "subcategory":"Department Store",
            "type":"Retail Goods"
        }
    ],
    "sg:postcode":"PO15 5AX",
    "sg:province":"Hampshire",
    "wof:name":"St. Louis Stores",
    "wof:placetype":"venue"
},
  "geometry": {"coordinates":[-1.1980040073,50.8554191589],"type":"Point"}
}