{
  "type": "Feature",
  "properties": {
    "addr:full":"137 Botchergate Carlisle Cumbria CA1 1RZ",
    "addr:housenumber":"137",
    "addr:postcode":"ca1 1rz",
    "addr:street":"Botchergate",
    "iso:country":"GB",
    "sg:address":"137 Botchergate",
    "sg:city":"Carlisle",
    "sg:classifiers":[
        {
            "category":"Professional",
            "type":"Services"
        }
    ],
    "sg:phone":"+44 1228 26469",
    "sg:postcode":"CA1 1RZ",
    "sg:province":"Cumbria",
    "sg:tags":[
        "directory",
        "pub"
    ],
    "wof:name":"Andrew Cunningham",
    "wof:placetype":"venue"
},
  "geometry": {"coordinates":[-2.9282200336,54.889793396],"type":"Point"}
}