{
  "type": "Feature",
  "properties": {
    "addr:full":"54 Fulneck Pudsey West Yorkshire LS28 8NT",
    "addr:housenumber":"54",
    "addr:postcode":"ls28 8nt",
    "addr:street":"Fulneck Pudsey West",
    "iso:country":"GB",
    "sg:address":"54 Fulneck",
    "sg:city":"Pudsey",
    "sg:classifiers":[
        {
            "category":"Restaurant",
            "type":"Food & Drink"
        }
    ],
    "sg:phone":"+44 113 256 4069",
    "sg:postcode":"LS28 8NT",
    "sg:province":"West Yorkshire",
    "wof:name":"Fulneck Restaurant",
    "wof:placetype":"venue"
},
  "geometry": {"coordinates":[-1.667601943,53.7837104797],"type":"Point"}
}