{
  "type": "Feature",
  "properties": {
    "iso:country":"GB",
    "sg:address":"32 Chalcrafts",
    "sg:city":"Alton",
    "sg:classifiers":[
        {
            "category":"Manufacturing",
            "subcategory":"Metals",
            "type":"Manufacturing & Wholesale Goods"
        }
    ],
    "sg:phone":"+44 1420 86348",
    "sg:postcode":"GU34 2HD",
    "sg:province":"Hampshire",
    "wof:name":"B.F Ltd",
    "wof:placetype":"venue"
},
  "geometry": {"coordinates":[-0.968033,51.155605],"type":"Point"}
}