{
  "type": "Feature",
  "properties": {
    "addr:full":"The Corner House, Hight St Cranbrook Tonbridge Kent TN17 3DF",
    "addr:postcode":"tn17 3df",
    "addr:street":"Hight St",
    "iso:country":"GB",
    "sg:address":"The Corner House, Hight St Cranbrook",
    "sg:city":"Tonbridge",
    "sg:classifiers":[
        {
            "category":"Professional",
            "subcategory":"Accounting & Tax Preparation",
            "type":"Services"
        }
    ],
    "sg:phone":"+44 1580 720888",
    "sg:postcode":"TN17 3DF",
    "sg:province":"Kent",
    "sg:tags":[
        "accountant"
    ],
    "wof:name":"Horden Accountancy & Business Services",
    "wof:placetype":"venue"
},
  "geometry": {"coordinates":[0.5352450013,51.0965003967],"type":"Point"}
}