{
  "type": "Feature",
  "properties": {
    "addr:full":"3 Millburngate Shopping Centre Durham Durham DH1 4SL",
    "addr:housenumber":"3",
    "addr:postcode":"dh1 4sl",
    "addr:street":"Millburngate Shopping",
    "iso:country":"GB",
    "sg:address":"3 Millburngate Shopping Centre",
    "sg:city":"Durham",
    "sg:classifiers":[
        {
            "category":"Shopping",
            "subcategory":"Shoes",
            "type":"Retail Goods"
        }
    ],
    "sg:phone":"+44 191 386 9467",
    "sg:postcode":"DH1 4SL",
    "sg:province":"Durham",
    "wof:name":"Timpson Group Plc",
    "wof:placetype":"venue"
},
  "geometry": {"coordinates":[-1.579021,54.777054],"type":"Point"}
}