{
  "type": "Feature",
  "properties": {
    "iso:country":"GB",
    "sg:address":"1 Stella Gill Industrial Estate, Newfield",
    "sg:city":"Chester-le-street",
    "sg:classifiers":[
        {
            "category":"Retail",
            "subcategory":"Auto Repair",
            "type":"Services"
        }
    ],
    "sg:phone":"+44 191 388 9066",
    "sg:postcode":"DH2 2RG",
    "sg:province":"Durham",
    "sg:tags":[
        "modification",
        "garage",
        "related"
    ],
    "wof:name":"A.HEDLEY (MOTOR ENGINEERS) LTD",
    "wof:placetype":"venue"
},
  "geometry": {"coordinates":[-1.60358,54.862862],"type":"Point"}
}