{
  "type": "Feature",
  "properties": {
    "addr:full":"2 Bradley Street, Sandiacre Nottingham Derbyshire NG10 5AH",
    "addr:housenumber":"2",
    "addr:postcode":"ng10 5ah",
    "addr:street":"Bradley Street",
    "iso:country":"GB",
    "sg:address":"2 Bradley Street, Sandiacre",
    "sg:city":"Nottingham",
    "sg:classifiers":[
        {
            "category":"Shopping",
            "subcategory":"Stationery & Office Supplies",
            "type":"Retail Goods"
        }
    ],
    "sg:phone":"+44 115 949 7167",
    "sg:postcode":"NG10 5AH",
    "sg:province":"Derbyshire",
    "sg:tags":[
        "equipment",
        "educational",
        "school"
    ],
    "wof:name":"BEECROFT & PARTNERS LTD",
    "wof:placetype":"venue"
},
  "geometry": {"coordinates":[-1.284966,52.922127],"type":"Point"}
}