{
  "type": "Feature",
  "properties": {
    "iso:country":"GB",
    "sg:address":"8 Sipson Road",
    "sg:city":"West Drayton",
    "sg:classifiers":[
        {
            "category":"Shopping",
            "subcategory":"News",
            "type":"Retail Goods"
        }
    ],
    "sg:phone":"+44 1895 442487",
    "sg:postcode":"UB7 9DP",
    "sg:province":"Greater London",
    "sg:tags":[
        "newsagent"
    ],
    "wof:name":"A & A News",
    "wof:placetype":"venue"
},
  "geometry": {"coordinates":[-0.466533,51.501907],"type":"Point"}
}