{
  "type": "Feature",
  "properties": {
    "iso:country":"GB",
    "sg:address":"Unit 6 Northside Business Park, Hawkins Lane",
    "sg:city":"Burton-on-trent",
    "sg:classifiers":[
        {
            "category":"Manufacturing",
            "subcategory":"Signs",
            "type":"Manufacturing & Wholesale Goods"
        }
    ],
    "sg:postcode":"DE14 1DB",
    "sg:province":"Derbyshire",
    "sg:tags":[
        "writer"
    ],
    "wof:name":"Autographs & Signatures",
    "wof:placetype":"venue"
},
  "geometry": {"coordinates":[-1.626979,52.817554],"type":"Point"}
}