{
  "type": "Feature",
  "properties": {
    "addr:full":"Stafford Road Stone Staffordshire ST15 0DG",
    "addr:postcode":"st15 0dg",
    "addr:street":"Stafford Road",
    "iso:country":"GB",
    "sg:address":"Stafford Road",
    "sg:city":"Stone",
    "sg:classifiers":[
        {
            "category":"Professional",
            "subcategory":"Computer Services",
            "type":"Services"
        }
    ],
    "sg:phone":"+44 1785 810800",
    "sg:postcode":"ST15 0DG",
    "sg:province":"Staffordshire",
    "sg:tags":[
        "system",
        "software"
    ],
    "wof:name":"Datel Electronics Ltd.",
    "wof:placetype":"venue"
},
  "geometry": {"coordinates":[-2.1476500034,52.8951835632],"type":"Point"}
}