{
  "type": "Feature",
  "properties": {
    "addr:full":"5 Wood St Banff Aberdeenshire AB45 1JX",
    "addr:housenumber":"5",
    "addr:postcode":"ab45 1jx",
    "addr:street":"Wood St",
    "iso:country":"GB",
    "sg:address":"5 Wood St",
    "sg:city":"Banff",
    "sg:classifiers":[
        {
            "category":"Building & Trades",
            "subcategory":"Construction",
            "type":"Services"
        }
    ],
    "sg:phone":"+44 1261 812908",
    "sg:postcode":"AB45 1JX",
    "sg:province":"Aberdeenshire",
    "sg:tags":[
        "monumental",
        "mason"
    ],
    "wof:name":"Graham Watt",
    "wof:placetype":"venue"
},
  "geometry": {"coordinates":[-2.5310180187,57.6684532166],"type":"Point"}
}