{
  "type": "Feature",
  "properties": {
    "addr:full":"27 Seaside Eastbourne East Sussex BN22 7NB",
    "addr:housenumber":"27",
    "addr:postcode":"bn22 7nb",
    "addr:street":"Seaside",
    "iso:country":"GB",
    "sg:address":"27 Seaside",
    "sg:city":"Eastbourne",
    "sg:classifiers":[
        {
            "category":"Professional",
            "subcategory":"Accounting & Tax Preparation",
            "type":"Services"
        }
    ],
    "sg:postcode":"BN22 7NB",
    "sg:province":"East Sussex",
    "sg:tags":[
        "accountant"
    ],
    "wof:name":"D Craner",
    "wof:placetype":"venue"
},
  "geometry": {"coordinates":[0.2947419882,50.7700271606],"type":"Point"}
}