{
  "type": "Feature",
  "properties": {
    "addr:full":"West End Early Years Centre, Katherine St Ashton Under Lyne Greater Manchester OL7 0HE",
    "addr:postcode":"ol7 0he",
    "addr:street":"Katherine St;Under Lyne",
    "iso:country":"GB",
    "sg:address":"West End Early Years Centre, Katherine St",
    "sg:city":"Ashton Under Lyne",
    "sg:classifiers":[
        {
            "category":"Professional",
            "subcategory":"Lawyer & Legal Services",
            "type":"Services"
        }
    ],
    "sg:phone":"+44 161 339 6705",
    "sg:postcode":"OL7 0HE",
    "sg:province":"Greater Manchester",
    "sg:tags":[
        "advice",
        "counselling"
    ],
    "wof:name":"Child Care Options & Advisory Service",
    "wof:placetype":"venue"
},
  "geometry": {"coordinates":[-2.1037371159,53.48179245],"type":"Point"}
}