{
  "type": "Feature",
  "properties": {
    "addr:full":"Archard House, Waverley Road Weymouth Dorset DT3 5HL",
    "addr:postcode":"dt3 5hl",
    "addr:street":"Waverley Road",
    "iso:country":"GB",
    "sg:address":"Archard House, Waverley Road",
    "sg:city":"Weymouth",
    "sg:classifiers":[
        {
            "category":"Fast Food",
            "type":"Food & Drink"
        },
        {
            "category":"Restaurant",
            "type":"Food & Drink"
        }
    ],
    "sg:postcode":"DT3 5HL",
    "sg:province":"Dorset",
    "sg:tags":[
        "away",
        "take"
    ],
    "wof:name":"Riverboat Inns Ltd.",
    "wof:placetype":"venue"
},
  "geometry": {"coordinates":[-2.4610168934,50.6273880005],"type":"Point"}
}