{
  "type": "Feature",
  "properties": {
    "iso:country":"GB",
    "sg:address":"62 Eastgate",
    "sg:city":"Cowbridge",
    "sg:classifiers":[
        {
            "category":"Professional",
            "subcategory":"Lawyer & Legal Services",
            "type":"Services"
        }
    ],
    "sg:phone":"+44 1446 772011",
    "sg:postcode":"CF71 7YF",
    "sg:province":"The Vale of Glamorgan",
    "sg:tags":[
        "solicitor"
    ],
    "wof:name":"Gwyn & Gwyn Solicitors",
    "wof:placetype":"venue"
},
  "geometry": {"coordinates":[-3.4451189041,51.4608535767],"type":"Point"}
}