{
  "type": "Feature",
  "properties": {
    "addr:full":"11 Castle Cumnock East Ayrshire KA18 4AN",
    "addr:housenumber":"11",
    "addr:postcode":"ka18 4an",
    "addr:street":"Castle Cumnock East",
    "iso:country":"GB",
    "sg:address":"11 Castle",
    "sg:city":"Cumnock",
    "sg:classifiers":[
        {
            "category":"Personal",
            "type":"Services"
        }
    ],
    "sg:phone":"+44 1290 338251",
    "sg:postcode":"KA18 4AN",
    "sg:province":"East Ayrshire",
    "sg:tags":[
        "wedding"
    ],
    "wof:name":"The Crown Hotel",
    "wof:placetype":"venue"
},
  "geometry": {"coordinates":[-4.184844017,55.3951950073],"type":"Point"}
}