{
  "type": "Feature",
  "properties": {
    "addr:full":"85 Gloucester Rd Croydon Surrey CR0 2DN",
    "addr:housenumber":"85",
    "addr:postcode":"cr0 2dn",
    "addr:street":"Gloucester Rd",
    "iso:country":"GB",
    "sg:address":"85 Gloucester Rd",
    "sg:city":"Croydon",
    "sg:classifiers":[
        {
            "category":"Building & Trades",
            "subcategory":"Construction",
            "type":"Services"
        }
    ],
    "sg:phone":"+44 20 8683 2190",
    "sg:postcode":"CR0 2DN",
    "sg:province":"Surrey",
    "sg:tags":[
        "builder"
    ],
    "wof:name":"Network Construction",
    "wof:placetype":"venue"
},
  "geometry": {"coordinates":[-0.0896669999,51.3852920532],"type":"Point"}
}