{
  "type": "Feature",
  "properties": {
    "addr:full":"Bwlan, Aberffraw Ty Croes Isle of Anglesey LL63 5AX",
    "addr:postcode":"ll63 5ax",
    "addr:street":"Ty Croes",
    "iso:country":"GB",
    "sg:address":"Bwlan, Aberffraw",
    "sg:city":"Ty Croes",
    "sg:classifiers":[
        {
            "category":"Farming",
            "subcategory":"Livestock Farm",
            "type":"Manufacturing & Wholesale Goods"
        }
    ],
    "sg:phone":"+44 1407 840214",
    "sg:postcode":"LL63 5AX",
    "sg:province":"Isle of Anglesey",
    "sg:tags":[
        "others"
    ],
    "wof:name":"Owen R Lewis",
    "wof:placetype":"venue"
},
  "geometry": {"coordinates":[-4.474903,53.222897],"type":"Point"}
}