{
  "type": "Feature",
  "properties": {
    "addr:full":"23b Uttoxeter Road, Longton Stoke-on-trent Staffordshire ST3 1NY",
    "addr:housenumber":"23b",
    "addr:postcode":"staffordshire st3 1ny",
    "addr:street":"Uttoxeter Road",
    "iso:country":"GB",
    "sg:address":"23b Uttoxeter Road, Longton",
    "sg:city":"Stoke-on-trent",
    "sg:classifiers":[
        {
            "category":"Retail",
            "subcategory":"Auto Repair",
            "type":"Services"
        }
    ],
    "sg:phone":"+44 1782 311286",
    "sg:postcode":"ST3 1NY",
    "sg:province":"Staffordshire",
    "sg:tags":[
        "modification",
        "garage"
    ],
    "wof:name":"D & D Motors",
    "wof:placetype":"venue"
},
  "geometry": {"coordinates":[-2.131605,52.987171],"type":"Point"}
}