{
  "type": "Feature",
  "properties": {
    "addr:full":"19 Maurice Road Industrial Estate Wallsend Tyne and Wear NE28 6BY",
    "addr:housenumber":"19",
    "addr:postcode":"ne28 6by",
    "addr:street":"Maurice Road Industrial Estate",
    "iso:country":"GB",
    "sg:address":"19 Maurice Road Industrial Estate",
    "sg:city":"Wallsend",
    "sg:classifiers":[
        {
            "category":"Professional",
            "subcategory":"Art Services",
            "type":"Services"
        }
    ],
    "sg:postcode":"NE28 6BY",
    "sg:province":"Tyne and Wear",
    "sg:tags":[
        "decorating",
        "painting"
    ],
    "wof:name":"Panache Plasterwork",
    "wof:placetype":"venue"
},
  "geometry": {"coordinates":[-1.5386890173,54.9842414856],"type":"Point"}
}