{
  "type": "Feature",
  "properties": {
    "addr:full":"27/29 Ribblesdale Place Preston Lancashire PR1 3NA",
    "addr:housenumber":"27 / 29",
    "addr:postcode":"pr1 3na",
    "addr:street":"Ribblesdale Place",
    "iso:country":"GB",
    "sg:address":"27/29 Ribblesdale Place",
    "sg:city":"Preston",
    "sg:classifiers":[
        {
            "category":"Professional",
            "subcategory":"Accounting & Tax Preparation",
            "type":"Services"
        }
    ],
    "sg:phone":"+44 1772 822931",
    "sg:postcode":"PR1 3NA",
    "sg:province":"Lancashire",
    "sg:tags":[
        "accountant"
    ],
    "wof:name":"Paul Clegg & Co",
    "wof:placetype":"venue"
},
  "geometry": {"coordinates":[-2.7001950741,53.754611969],"type":"Point"}
}