{
  "type": "Feature",
  "properties": {
    "addr:full":"Leonard House, 12/14 Silver Street Tamworth Staffordshire B79 7NH",
    "addr:housenumber":"12 / 14",
    "addr:postcode":"b79 7nh",
    "addr:street":"Silver Street",
    "iso:country":"GB",
    "sg:address":"Leonard House, 12/14 Silver Street",
    "sg:city":"Tamworth",
    "sg:classifiers":[
        {
            "category":"Food & Beverages",
            "subcategory":"Supermarket",
            "type":"Retail Goods"
        }
    ],
    "sg:phone":"+44 1827 311288",
    "sg:postcode":"B79 7NH",
    "sg:province":"Staffordshire",
    "sg:tags":[
        "frozen"
    ],
    "wof:name":"A B Technologies Alimentaires Ltd.",
    "wof:placetype":"venue"
},
  "geometry": {"coordinates":[-1.697459,52.63356],"type":"Point"}
}