{
  "type": "Feature",
  "properties": {
    "iso:country":"GB",
    "sg:address":"87 Bromshill Green Road, Coundon",
    "sg:city":"Coventry",
    "sg:classifiers":[
        {
            "category":"Shopping",
            "subcategory":"Clothing, Apparel, & Fashions",
            "type":"Retail Goods"
        }
    ],
    "sg:postcode":"CV6 2AQ",
    "sg:province":"Warwickshire",
    "sg:tags":[
        "shop"
    ],
    "wof:name":"The Frock Shop",
    "wof:placetype":"venue"
},
  "geometry": {"coordinates":[-1.533306,52.430103],"type":"Point"}
}