{
  "type": "Feature",
  "properties": {
    "iso:country":"GB",
    "sg:address":"Fourways House, St Marys Street",
    "sg:city":"Stroud",
    "sg:classifiers":[
        {
            "category":"Professional",
            "subcategory":"Management & Consulting",
            "type":"Services"
        }
    ],
    "sg:postcode":"GL6 6QB",
    "sg:province":"Gloucestershire",
    "sg:tags":[
        "consultant"
    ],
    "wof:name":"Flint Communications",
    "wof:placetype":"venue"
},
  "geometry": {"coordinates":[-2.193078,51.785976],"type":"Point"}
}