{
  "type": "Feature",
  "properties": {
    "addr:full":"61-63 Riverside Road Norwich Norfolk NR1 1SR",
    "addr:housenumber":"61-63",
    "addr:postcode":"nr1 1sr",
    "addr:street":"Riverside Road Norwich Norfolk",
    "iso:country":"GB",
    "sg:address":"61-63 Riverside Road",
    "sg:city":"Norwich",
    "sg:classifiers":[
        {
            "category":"Home & Garden",
            "subcategory":"Hardware",
            "type":"Retail Goods"
        }
    ],
    "sg:phone":"+44 1603 883788",
    "sg:postcode":"NR1 1SR",
    "sg:province":"Norfolk",
    "sg:tags":[
        "retailer",
        "diy"
    ],
    "wof:name":"Godfrey D I Y Supermarkets Ltd.",
    "wof:placetype":"venue"
},
  "geometry": {"coordinates":[1.3089499474,52.6319503784],"type":"Point"}
}