{
  "type": "Feature",
  "properties": {
    "addr:full":"Farr Inverness Highland IV2 6AN",
    "addr:postcode":"iv2 6an",
    "iso:country":"GB",
    "sg:address":"Farr",
    "sg:city":"Inverness",
    "sg:classifiers":[
        {
            "category":"Farming",
            "subcategory":"Livestock Farm",
            "type":"Manufacturing & Wholesale Goods"
        }
    ],
    "sg:postcode":"IV2 6AN",
    "sg:province":"Highland",
    "sg:tags":[
        "others"
    ],
    "wof:name":"Andrew C Smith",
    "wof:placetype":"venue"
},
  "geometry": {"coordinates":[-4.3327388763,57.3814201355],"type":"Point"}
}