{
  "type": "Feature",
  "properties": {
    "addr:full":"The Showroom, Castlegate Malton North Yorkshire YO17 7DZ",
    "addr:postcode":"yo17 7dz",
    "addr:street":"Castlegate",
    "iso:country":"GB",
    "sg:address":"The Showroom, Castlegate",
    "sg:city":"Malton",
    "sg:classifiers":[
        {
            "category":"Recreation",
            "subcategory":"Amusement Park",
            "type":"Entertainment"
        }
    ],
    "sg:phone":"+44 1653 697305",
    "sg:postcode":"YO17 7DZ",
    "sg:province":"North Yorkshire",
    "sg:tags":[
        "arcade"
    ],
    "wof:name":"Malton Leisure Centre",
    "wof:placetype":"venue"
},
  "geometry": {"coordinates":[-0.8002240062,54.1378250122],"type":"Point"}
}