{
  "type": "Feature",
  "properties": {
    "addr:full":"484 Halliwell Road Bolton Lancashire BL1 8AN",
    "addr:housenumber":"484",
    "addr:postcode":"bl1 8an",
    "addr:street":"Halliwell Road",
    "iso:country":"GB",
    "sg:address":"484 Halliwell Road",
    "sg:city":"Bolton",
    "sg:classifiers":[
        {
            "category":"Home & Garden",
            "subcategory":"Hardware",
            "type":"Retail Goods"
        }
    ],
    "sg:phone":"+44 1204 840483",
    "sg:postcode":"BL1 8AN",
    "sg:province":"Lancashire",
    "sg:tags":[
        "retailer",
        "diy"
    ],
    "wof:name":"John E Comber",
    "wof:placetype":"venue"
},
  "geometry": {"coordinates":[-2.4453620911,53.5948791504],"type":"Point"}
}