{
  "type": "Feature",
  "properties": {
    "addr:full":"15 Lisle St London Greater London WC2H 7BE",
    "addr:housenumber":"15",
    "addr:postcode":"wc2h 7be",
    "addr:street":"Lisle St",
    "iso:country":"GB",
    "sg:address":"15 Lisle St",
    "sg:city":"London",
    "sg:classifiers":[
        {
            "category":"Restaurant",
            "type":"Food & Drink"
        }
    ],
    "sg:phone":"+44 20 7437 1539",
    "sg:postcode":"WC2H 7BE",
    "sg:province":"Greater London",
    "wof:name":"Forum Restaurant Limited",
    "wof:placetype":"venue"
},
  "geometry": {"coordinates":[-0.1308369935,51.5115585327],"type":"Point"}
}