{
  "type": "Feature",
  "properties": {
    "addr:full":"1-2 The Paragon Bristol City of Bristol BS8 4LA",
    "addr:housenumber":"1-2",
    "addr:postcode":"bs8 4la",
    "addr:street":"The Paragon",
    "iso:country":"GB",
    "sg:address":"1-2 The Paragon",
    "sg:city":"Bristol",
    "sg:classifiers":[
        {
            "category":"Education",
            "subcategory":"School",
            "type":"Public Place"
        }
    ],
    "sg:phone":"+44 117 973 2055",
    "sg:postcode":"BS8 4LA",
    "sg:province":"City of Bristol",
    "sg:tags":[
        "private",
        "tuition"
    ],
    "wof:name":"Maths Physics Statistics",
    "wof:placetype":"venue"
},
  "geometry": {"coordinates":[-2.623418,51.45266],"type":"Point"}
}