{
  "type": "Feature",
  "properties": {
    "iso:country":"GB",
    "sg:address":"Dovers Orchard, Hoo Lane",
    "sg:city":"Chipping Campden",
    "sg:classifiers":[
        {
            "category":"Farming",
            "subcategory":"Livestock Farm",
            "type":"Manufacturing & Wholesale Goods"
        }
    ],
    "sg:phone":"+44 1386 840550",
    "sg:postcode":"GL55 6AZ",
    "sg:province":"Gloucestershire",
    "sg:tags":[
        "others"
    ],
    "wof:name":"S R Wheatcroft & Son",
    "wof:placetype":"venue"
},
  "geometry": {"coordinates":[-1.779454,52.051388],"type":"Point"}
}