{
  "type": "Feature",
  "properties": {
    "addr:full":"Cwmmantgwyn Builth Wells Powys LD2 3RQ",
    "addr:postcode":"ld2 3rq",
    "iso:country":"GB",
    "sg:address":"Cwmmantgwyn",
    "sg:city":"Builth Wells",
    "sg:classifiers":[
        {
            "category":"Farming",
            "subcategory":"Livestock Farm",
            "type":"Manufacturing & Wholesale Goods"
        }
    ],
    "sg:postcode":"LD2 3RQ",
    "sg:province":"Powys",
    "sg:tags":[
        "others"
    ],
    "wof:name":"Wilson,Peter",
    "wof:placetype":"venue"
},
  "geometry": {"coordinates":[-3.4030599594,52.148273468],"type":"Point"}
}