{
  "type": "Feature",
  "properties": {
    "addr:full":"Hurst Road West Molesey Greater London KT8 1QS",
    "addr:postcode":"kt8 1qs",
    "addr:street":"Hurst Road",
    "iso:country":"GB",
    "sg:address":"Hurst Road",
    "sg:city":"West Molesey",
    "sg:classifiers":[
        {
            "category":"Education",
            "subcategory":"School",
            "type":"Public Place"
        }
    ],
    "sg:phone":"+44 20 8224 9119",
    "sg:postcode":"KT8 1QS",
    "sg:province":"Greater London",
    "sg:tags":[
        "local",
        "authority"
    ],
    "wof:name":"John Nightingale School",
    "wof:placetype":"venue"
},
  "geometry": {"coordinates":[-0.3667440116,51.4077911377],"type":"Point"}
}