{
  "type": "Feature",
  "properties": {
    "addr:full":"74 Dam La Warrington Cheshire WA1 4EP",
    "addr:housenumber":"74",
    "addr:postcode":"wa1 4ep",
    "addr:street":"Dam La Warrington Cheshire",
    "iso:country":"GB",
    "sg:address":"74 Dam La",
    "sg:city":"Warrington",
    "sg:classifiers":[
        {
            "category":"Professional",
            "subcategory":"Business Services",
            "type":"Services"
        }
    ],
    "sg:phone":"+44 1925 825726",
    "sg:postcode":"WA1 4EP",
    "sg:province":"Cheshire",
    "sg:tags":[
        "bookmaker"
    ],
    "wof:name":"Red Rose Racing",
    "wof:placetype":"venue"
},
  "geometry": {"coordinates":[-2.531194,53.401966],"type":"Point"}
}