{
  "type": "Feature",
  "properties": {
    "addr:full":"80 Manse Road Motherwell North Lanarkshire ML1 2PT",
    "addr:housenumber":"80",
    "addr:postcode":"ml1 2pt",
    "addr:street":"Manse Road",
    "iso:country":"GB",
    "sg:address":"80 Manse Road",
    "sg:city":"Motherwell",
    "sg:classifiers":[
        {
            "category":"Building & Trades",
            "subcategory":"Construction",
            "type":"Services"
        }
    ],
    "sg:postcode":"ML1 2PT",
    "sg:province":"North Lanarkshire",
    "sg:tags":[
        "builder"
    ],
    "wof:name":"B & M Builders",
    "wof:placetype":"venue"
},
  "geometry": {"coordinates":[-3.983598,55.78022],"type":"Point"}
}