{
  "type": "Feature",
  "properties": {
    "addr:full":"12 Southchurch Road Southend-on-sea Essex SS1 2NE",
    "addr:housenumber":"12",
    "addr:postcode":"ss1 2ne",
    "addr:street":"Southchurch Road",
    "iso:country":"GB",
    "sg:address":"12 Southchurch Road",
    "sg:city":"Southend-on-sea",
    "sg:classifiers":[
        {
            "category":"Shopping",
            "subcategory":"Hobbies, Toys, & Games",
            "type":"Retail Goods"
        }
    ],
    "sg:phone":"+44 1702 461251",
    "sg:postcode":"SS1 2NE",
    "sg:province":"Essex",
    "sg:tags":[
        "shop"
    ],
    "wof:name":"Games Workshop Ltd.",
    "wof:placetype":"venue"
},
  "geometry": {"coordinates":[0.7130489945,51.5399513245],"type":"Point"}
}