{
  "type": "Feature",
  "properties": {
    "iso:country":"GB",
    "sg:address":"Felden House, High Street",
    "sg:city":"Berkhamsted",
    "sg:classifiers":[
        {
            "category":"Professional",
            "subcategory":"Lawyer & Legal Services",
            "type":"Services"
        }
    ],
    "sg:phone":"+44 1442 875961",
    "sg:postcode":"HP4 2BL",
    "sg:province":"Bedfordshire",
    "sg:tags":[
        "patent",
        "agent"
    ],
    "wof:name":"Bowles Horton",
    "wof:placetype":"venue"
},
  "geometry": {"coordinates":[-0.5656189919,51.7607307434],"type":"Point"}
}