{
  "type": "Feature",
  "properties": {
    "iso:country":"GB",
    "sg:address":"Spindlewood Country Holiday Pk, Rock La",
    "sg:city":"Hastings",
    "sg:classifiers":[
        {
            "category":"Recreation",
            "subcategory":"Campground",
            "type":"Entertainment"
        }
    ],
    "sg:postcode":"TN35 4JN",
    "sg:province":"East Sussex",
    "sg:tags":[
        "holiday",
        "centre",
        "camp"
    ],
    "wof:name":"Newland,B,",
    "wof:placetype":"venue"
},
  "geometry": {"coordinates":[0.60927,50.87746],"type":"Point"}
}