{
  "type": "Feature",
  "properties": {
    "addr:full":"3 Cheap St Sherborne Dorset DT9 3PT",
    "addr:housenumber":"3",
    "addr:postcode":"dt9 3pt",
    "addr:street":"Cheap St",
    "iso:country":"GB",
    "sg:address":"3 Cheap St",
    "sg:city":"Sherborne",
    "sg:classifiers":[
        {
            "category":"Shopping",
            "subcategory":"Florist",
            "type":"Retail Goods"
        }
    ],
    "sg:postcode":"DT9 3PT",
    "sg:province":"Dorset",
    "wof:name":"Watts,E G & R,",
    "wof:placetype":"venue"
},
  "geometry": {"coordinates":[-2.516657114,50.9497718811],"type":"Point"}
}