{
  "type": "Feature",
  "properties": {
    "iso:country":"GB",
    "sg:address":"South Terminal, London Gatwick Airport",
    "sg:city":"Gatwick",
    "sg:classifiers":[
        {
            "category":"Banks & Credit Unions",
            "subcategory":"Bureau De Change",
            "type":"Services"
        }
    ],
    "sg:phone":"+44 1293 567744",
    "sg:postcode":"RH6 0NN",
    "sg:province":"Surrey",
    "wof:name":"Travelex Uk",
    "wof:placetype":"venue"
},
  "geometry": {"coordinates":[-0.1723539978,51.1617736816],"type":"Point"}
}