{
  "type": "Feature",
  "properties": {
    "iso:country":"GB",
    "sg:address":"155 Arthur Road, Wimbledon Park",
    "sg:city":"London",
    "sg:classifiers":[
        {
            "category":"Food & Beverages",
            "subcategory":"Liquor & Beverages",
            "type":"Retail Goods"
        }
    ],
    "sg:phone":"+44 20 8946 0696",
    "sg:postcode":"SW19 8AD",
    "sg:province":"Greater London",
    "sg:tags":[
        "beer",
        "spirit",
        "wines"
    ],
    "wof:name":"Thresher",
    "wof:placetype":"venue"
},
  "geometry": {"coordinates":[-0.1982329935,51.4349899292],"type":"Point"}
}