{
  "type": "Feature",
  "properties": {
    "addr:full":"111 Knatchbull Road London Greater London SE5 9QU",
    "addr:housenumber":"111",
    "addr:postcode":"se5 9qu",
    "addr:street":"Knatchbull Road",
    "iso:country":"GB",
    "sg:address":"111 Knatchbull Road",
    "sg:city":"London",
    "sg:classifiers":[
        {
            "category":"Professional",
            "subcategory":"Detective & Security Services",
            "type":"Services"
        }
    ],
    "sg:phone":"+44 20 7978 9789",
    "sg:postcode":"SE5 9QU",
    "sg:province":"Greater London",
    "sg:tags":[
        "car"
    ],
    "wof:name":"The Alarm Team",
    "wof:placetype":"venue"
},
  "geometry": {"coordinates":[-0.104754,51.471478],"type":"Point"}
}