{
  "type": "Feature",
  "properties": {
    "addr:full":"61-63 Woodhouse Road London Greater London N12 9ET",
    "addr:housenumber":"61-63",
    "addr:postcode":"n12 9et",
    "addr:street":"Woodhouse Road",
    "iso:country":"GB",
    "sg:address":"61-63 Woodhouse Road",
    "sg:city":"London",
    "sg:classifiers":[
        {
            "category":"Food & Beverages",
            "subcategory":"Supermarket",
            "type":"Retail Goods"
        }
    ],
    "sg:phone":"+44 20 8343 9111",
    "sg:postcode":"N12 9ET",
    "sg:province":"Greater London",
    "wof:name":"M M S SUPERMARKET",
    "wof:placetype":"venue"
},
  "geometry": {"coordinates":[-0.1727309972,51.6120491028],"type":"Point"}
}