{
  "type": "Feature",
  "properties": {
    "addr:full":"Front Street Durham Durham DH7 0BJ",
    "addr:postcode":"dh7 0bj",
    "addr:street":"Front Street",
    "iso:country":"GB",
    "sg:address":"Front Street",
    "sg:city":"Durham",
    "sg:classifiers":[
        {
            "category":"Shopping",
            "subcategory":"Department Store",
            "type":"Retail Goods"
        }
    ],
    "sg:postcode":"DH7 0BJ",
    "sg:province":"Durham",
    "wof:name":"Burnhope Foodstore",
    "wof:placetype":"venue"
},
  "geometry": {"coordinates":[-1.7453240156,54.8230705261],"type":"Point"}
}