{
  "type": "Feature",
  "properties": {
    "addr:full":"145 St Michaels Hill Bristol City of Bristol BS2 8DB",
    "addr:housenumber":"145",
    "addr:postcode":"bs2 8db",
    "addr:street":"St Michaels Hill",
    "iso:country":"GB",
    "sg:address":"145 St Michaels Hill",
    "sg:city":"Bristol",
    "sg:classifiers":[
        {
            "category":"Cafe",
            "type":"Food & Drink"
        }
    ],
    "sg:postcode":"BS2 8DB",
    "sg:province":"City of Bristol",
    "sg:tags":[
        "tea",
        "room"
    ],
    "wof:name":"St. Michaels Cafe",
    "wof:placetype":"venue"
},
  "geometry": {"coordinates":[-2.6021330357,51.4608268738],"type":"Point"}
}