{
  "type": "Feature",
  "properties": {
    "addr:full":"591 Thornton Road Bradford West Yorkshire BD8 9RA",
    "addr:housenumber":"591",
    "addr:postcode":"bd8 9ra",
    "addr:street":"Thornton Road",
    "iso:country":"GB",
    "sg:address":"591 Thornton Road",
    "sg:city":"Bradford",
    "sg:classifiers":[
        {
            "category":"Home & Garden",
            "subcategory":"Furniture",
            "type":"Retail Goods"
        }
    ],
    "sg:postcode":"BD8 9RA",
    "sg:province":"West Yorkshire",
    "wof:name":"Airedale Furnishings",
    "wof:placetype":"venue"
},
  "geometry": {"coordinates":[-1.7919050455,53.7988929749],"type":"Point"}
}