{
  "type": "Feature",
  "properties": {
    "addr:full":"17 Front Street Washington Tyne and Wear NE37 2BA",
    "addr:housenumber":"17",
    "addr:postcode":"ne37 2ba",
    "addr:street":"Front Street",
    "iso:country":"GB",
    "sg:address":"17 Front Street",
    "sg:city":"Washington",
    "sg:classifiers":[
        {
            "category":"Food & Beverages",
            "subcategory":"Bakery",
            "type":"Retail Goods"
        }
    ],
    "sg:phone":"+44 191 416 8688",
    "sg:postcode":"NE37 2BA",
    "sg:province":"Tyne and Wear",
    "sg:tags":[
        "shop",
        "baker",
        "confectionery"
    ],
    "wof:name":"Marshalls the Bakers Ltd.",
    "wof:placetype":"venue"
},
  "geometry": {"coordinates":[-1.5173710585,54.9127388],"type":"Point"}
}