{
  "type": "Feature",
  "properties": {
    "addr:full":"8 Fircroft Bicester Oxfordshire OX6 9XX",
    "addr:housenumber":"8",
    "addr:postcode":"ox6 9xx",
    "addr:street":"Fircroft Bicester",
    "iso:country":"GB",
    "sg:address":"8 Fircroft",
    "sg:city":"Bicester",
    "sg:classifiers":[
        {
            "category":"Building & Trades",
            "subcategory":"Landscaping Services",
            "type":"Services"
        }
    ],
    "sg:phone":"+44 70 0075 0131",
    "sg:postcode":"OX6 9XX",
    "sg:province":"Oxfordshire",
    "sg:tags":[
        "landscape",
        "contractor"
    ],
    "wof:name":"L A Services",
    "wof:placetype":"venue"
},
  "geometry": {"coordinates":[-1.1469210386,51.9137229919],"type":"Point"}
}