{
  "type": "Feature",
  "properties": {
    "addr:full":"Tellcom Technology Center, 20 Clifton Road Blackpool Lancashire FY4 4QA",
    "addr:housenumber":"20",
    "addr:postcode":"fy4 4qa",
    "addr:street":"Clifton Road",
    "iso:country":"GB",
    "sg:address":"Tellcom Technology Center, 20 Clifton Road",
    "sg:city":"Blackpool",
    "sg:classifiers":[
        {
            "category":"Professional",
            "subcategory":"Computer Services",
            "type":"Services"
        }
    ],
    "sg:phone":"+44 870 707 0888",
    "sg:postcode":"FY4 4QA",
    "sg:province":"Lancashire",
    "sg:tags":[
        "system",
        "software"
    ],
    "wof:name":"Tellcom Technology Group",
    "wof:placetype":"venue"
},
  "geometry": {"coordinates":[-3.00831,53.799728],"type":"Point"}
}