{
  "type": "Feature",
  "properties": {
    "addr:full":"Unit 116 Oystons Mill Preston Lancashire PR1 8UR",
    "addr:housenumber":"116",
    "addr:postcode":"pr1 8ur",
    "addr:street":"Oystons Mill",
    "iso:country":"GB",
    "sg:address":"Unit 116 Oystons Mill",
    "sg:city":"Preston",
    "sg:classifiers":[
        {
            "category":"Professional",
            "subcategory":"Employment Agencies",
            "type":"Services"
        }
    ],
    "sg:postcode":"PR1 8UR",
    "sg:province":"Lancashire",
    "sg:tags":[
        "recr",
        "hire",
        "driver"
    ],
    "wof:name":"Agency Drivers Services Ltd.",
    "wof:placetype":"venue"
},
  "geometry": {"coordinates":[-2.7057290077,53.7579612732],"type":"Point"}
}