{
  "type": "Feature",
  "properties": {
    "iso:country":"GB",
    "sg:address":"484 Barking Road",
    "sg:city":"London",
    "sg:classifiers":[
        {
            "category":"Professional",
            "subcategory":"Printing & Photocopies",
            "type":"Services"
        }
    ],
    "sg:phone":"+44 20 8552 8120",
    "sg:postcode":"E6 2LT",
    "sg:province":"Greater London",
    "sg:tags":[
        "printer"
    ],
    "wof:name":"A L-Shafi Print",
    "wof:placetype":"venue"
},
  "geometry": {"coordinates":[0.064696,51.53392],"type":"Point"}
}