{
  "type": "Feature",
  "properties": {
    "addr:full":"12 Victoria Place St Austell Cornwall PL25 5PE",
    "addr:housenumber":"12",
    "addr:postcode":"pl25 5pe",
    "addr:street":"Victoria Place",
    "iso:country":"GB",
    "sg:address":"12 Victoria Place",
    "sg:city":"St Austell",
    "sg:classifiers":[
        {
            "category":"Communications",
            "type":"Services"
        }
    ],
    "sg:phone":"+44 1726 75222",
    "sg:postcode":"PL25 5PE",
    "sg:province":"Cornwall",
    "sg:tags":[
        "tv",
        "video",
        "radio"
    ],
    "wof:name":"Hicklings",
    "wof:placetype":"venue"
},
  "geometry": {"coordinates":[-4.792496,50.338001],"type":"Point"}
}