{
  "type": "Feature",
  "properties": {
    "addr:full":"Pathfields Industrial Estate South Molton Devon EX36 3LH",
    "addr:postcode":"ex36 3lh",
    "addr:street":"Estate",
    "iso:country":"GB",
    "sg:address":"Pathfields Industrial Estate",
    "sg:city":"South Molton",
    "sg:classifiers":[
        {
            "category":"Professional",
            "subcategory":"Engineering",
            "type":"Services"
        }
    ],
    "sg:phone":"+44 1202 882121",
    "sg:postcode":"EX36 3LH",
    "sg:province":"Devon",
    "wof:name":"F R Hitemp",
    "wof:placetype":"venue"
},
  "geometry": {"coordinates":[-3.828109026,51.0277442932],"type":"Point"}
}