{
  "type": "Feature",
  "properties": {
    "addr:full":"21 Chapel St Blackpool Lancashire FY1 5AW",
    "addr:housenumber":"21",
    "addr:postcode":"fy1 5aw",
    "addr:street":"Chapel St",
    "iso:country":"GB",
    "sg:address":"21 Chapel St",
    "sg:city":"Blackpool",
    "sg:classifiers":[
        {
            "category":"Fast Food",
            "type":"Food & Drink"
        },
        {
            "category":"Cafe",
            "type":"Food & Drink"
        }
    ],
    "sg:postcode":"FY1 5AW",
    "sg:province":"Lancashire",
    "sg:tags":[
        "tea",
        "away",
        "room",
        "take"
    ],
    "wof:name":"Riccuti,J,",
    "wof:placetype":"venue"
},
  "geometry": {"coordinates":[-3.05351,53.811287],"type":"Point"}
}