{
  "type": "Feature",
  "properties": {
    "addr:full":"The Thistle Centre Stirling Stirling FK8 2EE",
    "addr:postcode":"fk8 2ee",
    "addr:street":"Stirling",
    "iso:country":"GB",
    "sg:address":"The Thistle Centre",
    "sg:city":"Stirling",
    "sg:classifiers":[
        {
            "category":"Shopping",
            "subcategory":"Clothing, Apparel, & Fashions",
            "type":"Retail Goods"
        }
    ],
    "sg:phone":"+44 1786 450087",
    "sg:postcode":"FK8 2EE",
    "sg:province":"Stirling",
    "sg:tags":[
        "ladieswear"
    ],
    "wof:name":"Bay Trading Co",
    "wof:placetype":"venue"
},
  "geometry": {"coordinates":[-3.9395198822,56.1173591614],"type":"Point"}
}