{
  "type": "Feature",
  "properties": {
    "addr:full":"60-64 Main Street, East Leake Loughborough Leicestershire LE12 6PG",
    "addr:housenumber":"60-64",
    "addr:postcode":"le12 6pg",
    "addr:street":"Main Street",
    "iso:country":"GB",
    "sg:address":"60-64 Main Street, East Leake",
    "sg:city":"Loughborough",
    "sg:classifiers":[
        {
            "category":"Food & Beverages",
            "subcategory":"Groceries & Convenience Stores",
            "type":"Retail Goods"
        }
    ],
    "sg:phone":"+44 1509 852773",
    "sg:postcode":"LE12 6PG",
    "sg:province":"Leicestershire",
    "wof:name":"Alldays",
    "wof:placetype":"venue"
},
  "geometry": {"coordinates":[-1.151747,52.83173],"type":"Point"}
}