{
  "type": "Feature",
  "properties": {
    "addr:full":"13-15 High St Staines Berkshire TW18 4QY",
    "addr:housenumber":"13-15",
    "addr:postcode":"tw18 4qy",
    "addr:street":"High St",
    "iso:country":"GB",
    "sg:address":"13-15 High St",
    "sg:city":"Staines",
    "sg:classifiers":[
        {
            "category":"Bars & Pubs",
            "type":"Food & Drink"
        }
    ],
    "sg:postcode":"TW18 4QY",
    "sg:province":"Berkshire",
    "sg:tags":[
        "pubs",
        "inn"
    ],
    "wof:name":"Blue Anchor Inn (The)",
    "wof:placetype":"venue"
},
  "geometry": {"coordinates":[-0.51225,51.433514],"type":"Point"}
}