{
  "type": "Feature",
  "properties": {
    "iso:country":"GB",
    "sg:address":"13-15 High St",
    "sg:city":"Staines",
    "sg:classifiers":[
        {
            "category":"Bars & Pubs",
            "type":"Food & Drink"
        }
    ],
    "sg:postcode":"TW18 4QY",
    "sg:province":"Berkshire",
    "sg:tags":[
        "pubs",
        "inn"
    ],
    "wof:name":"Blue Anchor Inn (The)",
    "wof:placetype":"venue"
},
  "geometry": {"coordinates":[-0.51225,51.433514],"type":"Point"}
}