{
  "type": "Feature",
  "properties": {
    "addr:full":"Brook Lane Nurseries, Brook La Warrington Cheshire WA3 6DS",
    "addr:postcode":"wa3 6ds",
    "addr:street":"Brook Lane Nurseries Brook La Warrington Cheshire",
    "iso:country":"GB",
    "sg:address":"Brook Lane Nurseries, Brook La",
    "sg:city":"Warrington",
    "sg:classifiers":[
        {
            "category":"Shopping",
            "subcategory":"Florist",
            "type":"Retail Goods"
        }
    ],
    "sg:phone":"+44 1925 814715",
    "sg:postcode":"WA3 6DS",
    "sg:province":"Cheshire",
    "wof:name":"W Blundell & Son",
    "wof:placetype":"venue"
},
  "geometry": {"coordinates":[-2.505062,53.401958],"type":"Point"}
}