{
  "type": "Feature",
  "properties": {
    "iso:country":"GB",
    "sg:address":"5 Elswick Rd",
    "sg:city":"Washington",
    "sg:classifiers":[
        {
            "category":"Autos & Motor Vehicles",
            "subcategory":"Auto Supplies",
            "type":"Retail Goods"
        }
    ],
    "sg:phone":"+44 191 415 1517",
    "sg:postcode":"NE37 1LH",
    "sg:province":"Tyne and Wear",
    "sg:tags":[
        "part",
        "motorcycle",
        "accessory"
    ],
    "wof:name":"Hood Motor Cycle Tyres Ltd",
    "wof:placetype":"venue"
},
  "geometry": {"coordinates":[-1.5451660156,54.908203125],"type":"Point"}
}