{
  "type": "Feature",
  "properties": {
    "addr:full":"13 Whyteladyes Lane, Cookham Maidenhead Berkshire SL6 9LZ",
    "addr:housenumber":"13",
    "addr:postcode":"sl6 9lz",
    "addr:street":"Whyteladyes Lane",
    "iso:country":"GB",
    "sg:address":"13 Whyteladyes Lane, Cookham",
    "sg:city":"Maidenhead",
    "sg:classifiers":[
        {
            "category":"Home & Garden",
            "subcategory":"Household Appliances",
            "type":"Retail Goods"
        }
    ],
    "sg:phone":"+44 1628 526621",
    "sg:postcode":"SL6 9LZ",
    "sg:province":"Berkshire",
    "sg:tags":[
        "repairs",
        "electrical",
        "domestic",
        "servicing"
    ],
    "wof:name":"Barry Taylor",
    "wof:placetype":"venue"
},
  "geometry": {"coordinates":[-0.727058,51.551849],"type":"Point"}
}