{
  "type": "Feature",
  "properties": {
    "iso:country":"GB",
    "sg:address":"174 Main Street",
    "sg:city":"Bellshill",
    "sg:classifiers":[
        {
            "category":"Shopping",
            "subcategory":"Pharmacy",
            "type":"Retail Goods"
        }
    ],
    "sg:phone":"+44 1698 747870",
    "sg:postcode":"ML4 1AE",
    "sg:province":"North Lanarkshire",
    "sg:tags":[
        "pharmacist",
        "chemist"
    ],
    "wof:name":"McEwan Chemists",
    "wof:placetype":"venue"
},
  "geometry": {"coordinates":[-4.025224,55.818714],"type":"Point"}
}