{
  "type": "Feature",
  "properties": {
    "addr:full":"3 George Mann Road Leeds West Yorkshire LS10 1DJ",
    "addr:housenumber":"3",
    "addr:postcode":"ls10 1dj",
    "addr:street":"George Mann Road",
    "iso:country":"GB",
    "sg:address":"3 George Mann Road",
    "sg:city":"Leeds",
    "sg:classifiers":[
        {
            "category":"Professional",
            "subcategory":"Printing & Photocopies",
            "type":"Services"
        }
    ],
    "sg:phone":"+44 113 385 5000",
    "sg:postcode":"LS10 1DJ",
    "sg:province":"West Yorkshire",
    "sg:tags":[
        "printer"
    ],
    "wof:name":"Scientific Games International Ltd.",
    "wof:placetype":"venue"
},
  "geometry": {"coordinates":[-1.516091,53.776726],"type":"Point"}
}