{
  "type": "Feature",
  "properties": {
    "addr:full":"239 Westbourne Gro London Greater London W11 2SE",
    "addr:housenumber":"239",
    "addr:postcode":"w11 2se",
    "addr:street":"Westbourne Gro",
    "iso:country":"GB",
    "sg:address":"239 Westbourne Gro",
    "sg:city":"London",
    "sg:classifiers":[
        {
            "category":"Shopping",
            "subcategory":"Pharmacy",
            "type":"Retail Goods"
        }
    ],
    "sg:phone":"+44 20 7229 4553",
    "sg:postcode":"W11 2SE",
    "sg:province":"Greater London",
    "sg:tags":[
        "pharmacist",
        "chemist"
    ],
    "wof:name":"Greatvale Ltd.",
    "wof:placetype":"venue"
},
  "geometry": {"coordinates":[-0.2040790021,51.5144386292],"type":"Point"}
}