{
  "type": "Feature",
  "properties": {
    "addr:full":"14 Mathercroft Leamington Spa Warwickshire CV31 1YG",
    "addr:housenumber":"14",
    "addr:postcode":"cv31 1yg",
    "addr:street":"Mathercroft",
    "iso:country":"GB",
    "sg:address":"14 Mathercroft",
    "sg:city":"Leamington Spa",
    "sg:classifiers":[
        {
            "category":"Building & Trades",
            "subcategory":"Plumbing",
            "type":"Services"
        }
    ],
    "sg:postcode":"CV31 1YG",
    "sg:province":"Warwickshire",
    "sg:tags":[
        "heating"
    ],
    "wof:name":"Rodney P N Dunkerley",
    "wof:placetype":"venue"
},
  "geometry": {"coordinates":[-1.514217,52.276443],"type":"Point"}
}