{
  "type": "Feature",
  "properties": {
    "addr:full":"Unit 17 Parham Drive, Boyatt Wood Industrial Estate Eastleigh Hampshire SO50 4NU",
    "addr:housenumber":"unit 17",
    "addr:postcode":"so50 4nu",
    "addr:street":"Parham Drive Boyatt Wood Industrial Estate",
    "iso:country":"GB",
    "sg:address":"Unit 17 Parham Drive, Boyatt Wood Industrial Estate",
    "sg:city":"Eastleigh",
    "sg:classifiers":[
        {
            "category":"Government",
            "subcategory":"Post Office",
            "type":"Public Place"
        }
    ],
    "sg:phone":"+44 23 8061 8891",
    "sg:postcode":"SO50 4NU",
    "sg:province":"Hampshire",
    "sg:tags":[
        "copper",
        "brass"
    ],
    "wof:name":"Advanced Alloys Ltd.",
    "wof:placetype":"venue"
},
  "geometry": {"coordinates":[-1.363589,50.975971],"type":"Point"}
}