{
  "type": "Feature",
  "properties": {
    "addr:full":"33 Whitehead Close Dartford Kent DA2 7PR",
    "addr:housenumber":"33",
    "addr:postcode":"da2 7pr",
    "addr:street":"Whitehead Close",
    "iso:country":"GB",
    "sg:address":"33 Whitehead Close",
    "sg:city":"Dartford",
    "sg:classifiers":[
        {
            "category":"Professional",
            "subcategory":"Engineering",
            "type":"Services"
        }
    ],
    "sg:phone":"+44 1322 278674",
    "sg:postcode":"DA2 7PR",
    "sg:province":"Kent",
    "sg:tags":[
        "contractor",
        "electrical",
        "engineer"
    ],
    "wof:name":"Electro-Check",
    "wof:placetype":"venue"
},
  "geometry": {"coordinates":[0.2028409988,51.4264602661],"type":"Point"}
}