{
  "type": "Feature",
  "properties": {
    "addr:full":"Darwin Court, Clayton Way Shrewsbury Shropshire SY3 5AL",
    "addr:postcode":"sy3 5al",
    "addr:street":"Darwin Court;Way",
    "iso:country":"GB",
    "sg:address":"Darwin Court, Clayton Way",
    "sg:city":"Shrewsbury",
    "sg:classifiers":[
        {
            "category":"Professional",
            "subcategory":"Accounting & Tax Preparation",
            "type":"Services"
        }
    ],
    "sg:phone":"+44 1743 231400",
    "sg:postcode":"SY3 5AL",
    "sg:province":"Shropshire",
    "sg:tags":[
        "accountant"
    ],
    "wof:name":"Barcroft Orme",
    "wof:placetype":"venue"
},
  "geometry": {"coordinates":[-2.799604,52.71587],"type":"Point"}
}