{
  "type": "Feature",
  "properties": {
    "iso:country":"GB",
    "sg:address":"171 Bicester Road",
    "sg:city":"Aylesbury",
    "sg:classifiers":[
        {
            "category":"Autos & Motor Vehicles",
            "subcategory":"Fuel & Gas Station",
            "type":"Retail Goods"
        }
    ],
    "sg:postcode":"HP19 9BB",
    "sg:province":"Buckinghamshire",
    "sg:tags":[
        "petrol",
        "filling"
    ],
    "wof:name":"Derek Taylor",
    "wof:placetype":"venue"
},
  "geometry": {"coordinates":[-0.8263289928,51.8230781555],"type":"Point"}
}