{
  "type": "Feature",
  "properties": {
    "addr:full":"50 Brunswick Street East Hove East Sussex BN3 1AU",
    "addr:housenumber":"50",
    "addr:postcode":"bn3 1au",
    "addr:street":"Brunswick Street East Hove",
    "iso:country":"GB",
    "sg:address":"50 Brunswick Street East",
    "sg:city":"Hove",
    "sg:classifiers":[
        {
            "category":"Retail",
            "subcategory":"Auto Repair",
            "type":"Services"
        }
    ],
    "sg:phone":"+44 1273 732087",
    "sg:postcode":"BN3 1AU",
    "sg:province":"East Sussex",
    "sg:tags":[
        "modification",
        "garage"
    ],
    "wof:name":"T Flint",
    "wof:placetype":"venue"
},
  "geometry": {"coordinates":[-0.157839,50.82465],"type":"Point"}
}