{
  "type": "Feature",
  "properties": {
    "iso:country":"GB",
    "sg:address":"108-110 Bootham",
    "sg:city":"York",
    "sg:classifiers":[
        {
            "category":"Travel",
            "subcategory":"Hotels & Motels",
            "type":"Entertainment"
        }
    ],
    "sg:phone":"+44 1904 624412",
    "sg:postcode":"YO30 7DG",
    "sg:province":"North Yorkshire",
    "wof:name":"The Bedford Hotel",
    "wof:placetype":"venue"
},
  "geometry": {"coordinates":[-1.0906089544,53.9657592773],"type":"Point"}
}