{
  "type": "Feature",
  "properties": {
    "iso:country":"GB",
    "sg:address":"Banbury Hill Farm, Vicarage Lane, Charlton",
    "sg:city":"Malmesbury",
    "sg:classifiers":[
        {
            "category":"Farming",
            "subcategory":"Dairy Farm",
            "type":"Manufacturing & Wholesale Goods"
        }
    ],
    "sg:phone":"+44 1666 577268",
    "sg:postcode":"SN16 9DW",
    "sg:province":"Wiltshire",
    "sg:tags":[
        "farmer"
    ],
    "wof:name":"S & M SHEPPARD",
    "wof:placetype":"venue"
},
  "geometry": {"coordinates":[-2.097419,51.582245],"type":"Point"}
}