{
  "type": "Feature",
  "properties": {
    "addr:full":"80 Lyonsdown Road, New Barnet Barnet Hertfordshire EN5 1JL",
    "addr:housenumber":"80",
    "addr:postcode":"en5 1jl",
    "addr:street":"Lyonsdown Road",
    "iso:country":"GB",
    "sg:address":"80 Lyonsdown Road, New Barnet",
    "sg:city":"Barnet",
    "sg:classifiers":[
        {
            "category":"Professional",
            "subcategory":"Accounting & Tax Preparation",
            "type":"Services"
        }
    ],
    "sg:postcode":"EN5 1JL",
    "sg:province":"Hertfordshire",
    "sg:tags":[
        "accountant"
    ],
    "wof:name":"Themis & Co",
    "wof:placetype":"venue"
},
  "geometry": {"coordinates":[-0.1800000072,51.6426811218],"type":"Point"}
}