{
  "type": "Feature",
  "properties": {
    "addr:full":"Lollard Street London Greater London SE11 6PY",
    "addr:postcode":"se11 6py",
    "addr:street":"Lollard Street",
    "iso:country":"GB",
    "sg:address":"Lollard Street",
    "sg:city":"London",
    "sg:classifiers":[
        {
            "category":"Education",
            "subcategory":"School",
            "type":"Public Place"
        }
    ],
    "sg:phone":"+44 20 7735 3105",
    "sg:postcode":"SE11 6PY",
    "sg:province":"Greater London",
    "sg:tags":[
        "local",
        "authority"
    ],
    "wof:name":"Lilian Baylis School",
    "wof:placetype":"venue"
},
  "geometry": {"coordinates":[-0.1155589968,51.4932632446],"type":"Point"}
}