{
  "type": "Feature",
  "properties": {
    "addr:full":"2 Stankelt Road, Silverdale Carnforth Cumbria LA5 0TA",
    "addr:housenumber":"2",
    "addr:postcode":"la5 0ta",
    "addr:street":"Stankelt Road",
    "iso:country":"GB",
    "sg:address":"2 Stankelt Road, Silverdale",
    "sg:city":"Carnforth",
    "sg:classifiers":[
        {
            "category":"Social Services",
            "subcategory":"Retirement Home",
            "type":"Services"
        }
    ],
    "sg:phone":"+44 1524 701212",
    "sg:postcode":"LA5 0TA",
    "sg:province":"Cumbria",
    "sg:tags":[
        "residential",
        "care"
    ],
    "wof:name":"West Lindeth Residential Home",
    "wof:placetype":"venue"
},
  "geometry": {"coordinates":[-2.826693,54.167404],"type":"Point"}
}