{
  "type": "Feature",
  "properties": {
    "addr:full":"14 Arwenack Street Falmouth Cornwall TR11 3DR",
    "addr:housenumber":"14",
    "addr:postcode":"tr11 3dr",
    "addr:street":"Arwenack Street",
    "iso:country":"GB",
    "sg:address":"14 Arwenack Street",
    "sg:city":"Falmouth",
    "sg:classifiers":[
        {
            "category":"Organizations",
            "subcategory":"Membership Organization",
            "type":"Services"
        }
    ],
    "sg:phone":"+44 1326 311078",
    "sg:postcode":"TR11 3DR",
    "sg:province":"Cornwall",
    "sg:tags":[
        "club"
    ],
    "wof:name":"The Royal British Legion",
    "wof:placetype":"venue"
},
  "geometry": {"coordinates":[-5.067564,50.153118],"type":"Point"}
}