{
  "type": "Feature",
  "properties": {
    "iso:country":"GB",
    "sg:address":"Unit 2, 251 Holt Rd, Horsford",
    "sg:city":"Norwich",
    "sg:classifiers":[
        {
            "category":"Manufacturing",
            "subcategory":"Glass & Minerals",
            "type":"Manufacturing & Wholesale Goods"
        },
        {
            "category":"Building & Trades",
            "subcategory":"Construction",
            "type":"Services"
        }
    ],
    "sg:phone":"+44 1603 897165",
    "sg:postcode":"NR10 3EB",
    "sg:province":"Norfolk",
    "sg:tags":[
        "product",
        "leaded",
        "window"
    ],
    "wof:name":"The Historic Glass & Glazing Workshop",
    "wof:placetype":"venue"
},
  "geometry": {"coordinates":[1.263926,52.675861],"type":"Point"}
}