{
  "type": "Feature",
  "properties": {
    "addr:full":"Hamley Heath Rugeley Staffordshire WS15 3LS",
    "addr:postcode":"ws15 3ls",
    "addr:street":"Hamley Heath",
    "iso:country":"GB",
    "sg:address":"Hamley Heath",
    "sg:city":"Rugeley",
    "sg:classifiers":[
        {
            "category":"Transit Center",
            "subcategory":"Passenger",
            "type":"Transportation"
        }
    ],
    "sg:postcode":"WS15 3LS",
    "sg:province":"Staffordshire",
    "sg:tags":[
        "boarding",
        "kennel",
        "catteries"
    ],
    "wof:name":"Parker,Graham,",
    "wof:placetype":"venue"
},
  "geometry": {"coordinates":[-1.906416,52.844292],"type":"Point"}
}