{
  "type": "Feature",
  "properties": {
    "addr:full":"60 Ashley Rd Poole Dorset BH14 9BN",
    "addr:housenumber":"60",
    "addr:postcode":"bh14 9bn",
    "addr:street":"Ashley Rd",
    "iso:country":"GB",
    "sg:address":"60 Ashley Rd",
    "sg:city":"Poole",
    "sg:classifiers":[
        {
            "category":"Fast Food",
            "type":"Food & Drink"
        }
    ],
    "sg:postcode":"BH14 9BN",
    "sg:province":"Dorset",
    "sg:tags":[
        "away",
        "take"
    ],
    "wof:name":"Chang,Ho Kee,",
    "wof:placetype":"venue"
},
  "geometry": {"coordinates":[-1.9263609648,50.7282409668],"type":"Point"}
}