{
  "type": "Feature",
  "properties": {
    "addr:full":"7 Oakwood Avenue Borehamwood Hertfordshire WD6 1SP",
    "addr:housenumber":"7",
    "addr:postcode":"wd6 1sp",
    "addr:street":"Oakwood Avenue Borehamwood",
    "iso:country":"GB",
    "sg:address":"7 Oakwood Avenue",
    "sg:city":"Borehamwood",
    "sg:classifiers":[
        {
            "category":"Building & Trades",
            "subcategory":"Construction",
            "type":"Services"
        }
    ],
    "sg:phone":"+44 20 8953 0732",
    "sg:postcode":"WD6 1SP",
    "sg:province":"Hertfordshire",
    "sg:tags":[
        "builder"
    ],
    "wof:name":"J Short Building Services",
    "wof:placetype":"venue"
},
  "geometry": {"coordinates":[-0.270537,51.651794],"type":"Point"}
}