{
  "type": "Feature",
  "properties": {
    "addr:full":"9 Guildford Road, Frimley Grn Camberley Hampshire GU16 6NL",
    "addr:housenumber":"9",
    "addr:postcode":"gu16 6nl",
    "addr:street":"Guildford Road",
    "iso:country":"GB",
    "sg:address":"9 Guildford Road, Frimley Grn",
    "sg:city":"Camberley",
    "sg:classifiers":[
        {
            "category":"Banks & Credit Unions",
            "subcategory":"Financial Services",
            "type":"Services"
        }
    ],
    "sg:phone":"+44 1252 836282",
    "sg:postcode":"GU16 6NL",
    "sg:province":"Hampshire",
    "sg:tags":[
        "adviser"
    ],
    "wof:name":"D & P Life & Pensions",
    "wof:placetype":"venue"
},
  "geometry": {"coordinates":[-0.727042973,51.3020896912],"type":"Point"}
}