{
  "type": "Feature",
  "properties": {
    "iso:country":"GB",
    "sg:address":"149 Dyke Road",
    "sg:city":"Hove",
    "sg:classifiers":[
        {
            "category":"Food & Beverages",
            "subcategory":"Bakery",
            "type":"Retail Goods"
        }
    ],
    "sg:phone":"+44 1273 733050",
    "sg:postcode":"BN3 1TJ",
    "sg:province":"East Sussex",
    "sg:tags":[
        "baker"
    ],
    "wof:name":"Forfars Bakers Ltd.",
    "wof:placetype":"venue"
},
  "geometry": {"coordinates":[-0.14813,50.831589],"type":"Point"}
}