{
  "type": "Feature",
  "properties": {
    "iso:country":"GB",
    "sg:address":"Uniqwin House, 38 Fieldway, Weaverham",
    "sg:city":"Northwich",
    "sg:classifiers":[
        {
            "category":"Professional",
            "subcategory":"Detective & Security Services",
            "type":"Services"
        }
    ],
    "sg:phone":"+44 1606 854888",
    "sg:postcode":"CW8 3HW",
    "sg:province":"Cheshire",
    "wof:name":"Association of Crime Risk Managers",
    "wof:placetype":"venue"
},
  "geometry": {"coordinates":[-2.579638958,53.2630386353],"type":"Point"}
}