{
  "type": "Feature",
  "properties": {
    "addr:full":"Olympus Business Park, Bristol Rd Gloucester Gloucestershire GL2 5HB",
    "addr:postcode":"gl2 5hb",
    "addr:street":"Business Park Bristol Rd",
    "iso:country":"GB",
    "sg:address":"Olympus Business Park, Bristol Rd",
    "sg:city":"Gloucester",
    "sg:classifiers":[
        {
            "category":"Shopping",
            "subcategory":"Party Supplies",
            "type":"Retail Goods"
        }
    ],
    "sg:phone":"+44 1452 720960",
    "sg:postcode":"GL2 5HB",
    "sg:province":"Gloucestershire",
    "sg:tags":[
        "plan",
        "agent"
    ],
    "wof:name":"Tupperware Distributor",
    "wof:placetype":"venue"
},
  "geometry": {"coordinates":[-2.2721800804,51.8499412537],"type":"Point"}
}