{
  "type": "Feature",
  "properties": {
    "addr:full":"Room 21 Victoria Buildings, Violet Street Paisley Renfrewshire PA1 1PA",
    "addr:housenumber":"21",
    "addr:postcode":"pa1 1pa",
    "addr:street":"Victoria Buildings Violet Street",
    "iso:country":"GB",
    "sg:address":"Room 21 Victoria Buildings, Violet Street",
    "sg:city":"Paisley",
    "sg:classifiers":[
        {
            "category":"Home & Garden",
            "subcategory":"Home Furnishings",
            "type":"Retail Goods"
        }
    ],
    "sg:phone":"+44 141 848 6577",
    "sg:postcode":"PA1 1PA",
    "sg:province":"Renfrewshire",
    "sg:tags":[
        "blind",
        "curtain",
        "fitting"
    ],
    "wof:name":"Castle Blinds Ltd.",
    "wof:placetype":"venue"
},
  "geometry": {"coordinates":[-4.40904,55.843868],"type":"Point"}
}