{
  "type": "Feature",
  "properties": {
    "addr:full":"1 Weoley Avenue Birmingham West Midlands B29 6PP",
    "addr:housenumber":"1",
    "addr:postcode":"b29 6pp",
    "addr:street":"Weoley Avenue",
    "iso:country":"GB",
    "sg:address":"1 Weoley Avenue",
    "sg:city":"Birmingham",
    "sg:classifiers":[
        {
            "category":"Building & Trades",
            "subcategory":"Construction",
            "type":"Services"
        }
    ],
    "sg:phone":"+44 121 472 0834",
    "sg:postcode":"B29 6PP",
    "sg:province":"West Midlands",
    "sg:tags":[
        "monumental",
        "mason"
    ],
    "wof:name":"William Loxley Memorials",
    "wof:placetype":"venue"
},
  "geometry": {"coordinates":[-1.9533640146,52.4386940002],"type":"Point"}
}