{
  "type": "Feature",
  "properties": {
    "iso:country":"GB",
    "sg:address":"Unit 16 Greenlands Business Centre, Studley Rd",
    "sg:city":"Redditch",
    "sg:classifiers":[
        {
            "category":"Professional",
            "subcategory":"Business Services",
            "type":"Services"
        }
    ],
    "sg:phone":"+44 1527 514744",
    "sg:postcode":"B98 7HD",
    "sg:province":"Warwickshire",
    "sg:tags":[
        "trade"
    ],
    "wof:name":"British Metalforming Trades Association The",
    "wof:placetype":"venue"
},
  "geometry": {"coordinates":[-1.91972,52.292439],"type":"Point"}
}