{
  "type": "Feature",
  "properties": {
    "iso:country":"GB",
    "sg:address":"Bromsgrove St",
    "sg:city":"Kidderminster",
    "sg:classifiers":[
        {
            "category":"Sports & Exercise",
            "subcategory":"Gym",
            "type":"Entertainment"
        }
    ],
    "sg:phone":"+44 1562 747737",
    "sg:postcode":"DY10 1PP",
    "sg:province":"Staffordshire",
    "sg:tags":[
        "fitness",
        "health",
        "centre"
    ],
    "wof:name":"L'Image Fitness & Health",
    "wof:placetype":"venue"
},
  "geometry": {"coordinates":[-2.245989,52.388676],"type":"Point"}
}