{
  "type": "Feature",
  "properties": {
    "iso:country":"GB",
    "sg:address":"16 Violet Bank Rd",
    "sg:city":"Sheffield",
    "sg:classifiers":[
        {
            "category":"Shopping",
            "subcategory":"Gifts & Souvenirs",
            "type":"Retail Goods"
        }
    ],
    "sg:postcode":"S7 1RZ",
    "sg:province":"South Yorkshire",
    "sg:tags":[
        "greeting",
        "card"
    ],
    "wof:name":"West,Alan,",
    "wof:placetype":"venue"
},
  "geometry": {"coordinates":[-1.489380002,53.3597984314],"type":"Point"}
}