{
  "type": "Feature",
  "properties": {
    "iso:country":"GB",
    "sg:address":"Higher Swan La",
    "sg:city":"Bolton",
    "sg:classifiers":[
        {
            "category":"Home & Garden",
            "subcategory":"Furniture",
            "type":"Retail Goods"
        }
    ],
    "sg:postcode":"BL3 3BJ",
    "sg:province":"Lancashire",
    "wof:name":"British Curtains",
    "wof:placetype":"venue"
},
  "geometry": {"coordinates":[-2.441054,53.561756],"type":"Point"}
}