{
  "type": "Feature",
  "properties": {
    "iso:country":"GB",
    "sg:address":"753/755 Wilmslow Road, Didsbury",
    "sg:city":"Manchester",
    "sg:classifiers":[
        {
            "category":"Banks & Credit Unions",
            "subcategory":"Bank",
            "type":"Services"
        }
    ],
    "sg:phone":"+44 161 251 3000",
    "sg:postcode":"M20 6RN",
    "sg:province":"Greater Manchester",
    "wof:name":"Barclays Bank Plc",
    "wof:placetype":"venue"
},
  "geometry": {"coordinates":[-2.2317221165,53.4159164429],"type":"Point"}
}