{
  "type": "Feature",
  "properties": {
    "iso:country":"GB",
    "sg:address":"Unit 2, Sandwash Clo, Rainford",
    "sg:city":"St Helens",
    "sg:classifiers":[
        {
            "category":"Manufacturing",
            "subcategory":"Rubber & Plastics",
            "type":"Manufacturing & Wholesale Goods"
        }
    ],
    "sg:postcode":"WA11 8LY",
    "sg:province":"Lancashire",
    "sg:tags":[
        "product"
    ],
    "wof:name":"Rainbow Plastics Ltd",
    "wof:placetype":"venue"
},
  "geometry": {"coordinates":[-2.772113,53.492466],"type":"Point"}
}