{
  "type": "Feature",
  "properties": {
    "addr:full":"19 Goodge Street London Greater London W1T 2PJ",
    "addr:housenumber":"19",
    "addr:postcode":"w1t 2pj",
    "addr:street":"Goodge Street",
    "iso:country":"GB",
    "sg:address":"19 Goodge Street",
    "sg:city":"London",
    "sg:classifiers":[
        {
            "category":"Real Estate",
            "subcategory":"Real Estate Agent",
            "type":"Services"
        }
    ],
    "sg:postcode":"W1T 2PJ",
    "sg:province":"Greater London",
    "wof:name":"Jacey Property Company Limited",
    "wof:placetype":"venue"
},
  "geometry": {"coordinates":[-0.1346729994,51.5196762085],"type":"Point"}
}