{
  "type": "Feature",
  "properties": {
    "iso:country":"GB",
    "sg:address":"12 Addison Road, Beechwood Park",
    "sg:city":"Worcester",
    "sg:classifiers":[
        {
            "category":"Retail",
            "subcategory":"Driving School",
            "type":"Services"
        }
    ],
    "sg:phone":"+44 1905 455316",
    "sg:postcode":"WR3 8EA",
    "sg:province":"Worcestershire",
    "wof:name":"West Mercia School of Motoring",
    "wof:placetype":"venue"
},
  "geometry": {"coordinates":[-2.220581,52.210106],"type":"Point"}
}