{
  "type": "Feature",
  "properties": {
    "addr:full":"21 Kings Road St Leonards-on-sea East Sussex TN37 6DU",
    "addr:housenumber":"21",
    "addr:postcode":"leonards-on-sea;tn37 6du",
    "addr:street":"Kings Road St",
    "iso:country":"GB",
    "sg:address":"21 Kings Road",
    "sg:city":"St Leonards-on-sea",
    "sg:classifiers":[
        {
            "category":"Restaurant",
            "type":"Food & Drink"
        }
    ],
    "sg:phone":"+44 1424 718598",
    "sg:postcode":"TN37 6DU",
    "sg:province":"East Sussex",
    "wof:name":"Victoria's",
    "wof:placetype":"venue"
},
  "geometry": {"coordinates":[0.560394,50.854099],"type":"Point"}
}