{
  "type": "Feature",
  "properties": {
    "iso:country":"GB",
    "sg:address":"28 Lawmoor Road, Dixon Blazes Industrial Estate",
    "sg:city":"Glasgow",
    "sg:classifiers":[
        {
            "category":"Freight",
            "type":"Transportation"
        }
    ],
    "sg:phone":"+44 141 429 4384",
    "sg:postcode":"G5 0UG",
    "sg:province":"Glasgow City",
    "sg:tags":[
        "haulage",
        "road"
    ],
    "wof:name":"Edwards of Hull",
    "wof:placetype":"venue"
},
  "geometry": {"coordinates":[-4.2490677834,55.8398323059],"type":"Point"}
}