{
  "type": "Feature",
  "properties": {
    "addr:full":"Wellbar House, Gallowgate Newcastle Upon Tyne Tyne and Wear NE1 4TD",
    "addr:postcode":"ne1 4td",
    "addr:street":"Gallowgate",
    "iso:country":"GB",
    "sg:address":"Wellbar House, Gallowgate",
    "sg:city":"Newcastle Upon Tyne",
    "sg:classifiers":[
        {
            "category":"Professional",
            "subcategory":"Management & Consulting",
            "type":"Services"
        }
    ],
    "sg:phone":"+44 191 201 3343",
    "sg:postcode":"NE1 4TD",
    "sg:province":"Tyne and Wear",
    "sg:tags":[
        "consultant",
        "energy",
        "conservation"
    ],
    "wof:name":"Energy Efficiencey Office",
    "wof:placetype":"venue"
},
  "geometry": {"coordinates":[-1.61959,54.973999],"type":"Point"}
}