{
  "type": "Feature",
  "properties": {
    "iso:country":"GB",
    "sg:address":"18 Woodfield Lane",
    "sg:city":"Ashtead",
    "sg:classifiers":[
        {
            "category":"Professional",
            "type":"Services"
        }
    ],
    "sg:phone":"+44 1372 275545",
    "sg:postcode":"KT21 2BE",
    "sg:province":"Surrey",
    "sg:tags":[
        "caterer"
    ],
    "wof:name":"ASHTON OUTSIDE CATERERS",
    "wof:placetype":"venue"
},
  "geometry": {"coordinates":[-0.3002130091,51.3107910156],"type":"Point"}
}