{
  "type": "Feature",
  "properties": {
    "addr:full":"8-12 Abbotsinch Road Grangemouth Falkirk FK3 9UX",
    "addr:housenumber":"8-12",
    "addr:postcode":"fk3 9ux",
    "addr:street":"Abbotsinch Road",
    "iso:country":"GB",
    "sg:address":"8-12 Abbotsinch Road",
    "sg:city":"Grangemouth",
    "sg:classifiers":[
        {
            "category":"Shopping",
            "subcategory":"Clothing, Apparel, & Fashions",
            "type":"Retail Goods"
        }
    ],
    "sg:phone":"+44 1324 483256",
    "sg:postcode":"FK3 9UX",
    "sg:province":"Falkirk",
    "sg:tags":[
        "clothing",
        "fabric"
    ],
    "wof:name":"Delta Textiles London Ltd.",
    "wof:placetype":"venue"
},
  "geometry": {"coordinates":[-3.705792,56.014687],"type":"Point"}
}