{
  "type": "Feature",
  "properties": {
    "addr:full":"13 Brent Street, Hendon London Greater London NW4 2EX",
    "addr:housenumber":"13",
    "addr:postcode":"nw4 2ex",
    "addr:street":"Brent Street",
    "iso:country":"GB",
    "sg:address":"13 Brent Street, Hendon",
    "sg:city":"London",
    "sg:classifiers":[
        {
            "category":"Wholesale",
            "subcategory":"Electrical",
            "type":"Manufacturing & Wholesale Goods"
        },
        {
            "category":"Shopping",
            "subcategory":"Computers & Home Electronics",
            "type":"Retail Goods"
        }
    ],
    "sg:phone":"+44 20 8202 0005",
    "sg:postcode":"NW4 2EX",
    "sg:province":"Greater London",
    "sg:tags":[
        "wholesaler"
    ],
    "wof:name":"Massgrove Electrical Ltd.",
    "wof:placetype":"venue"
},
  "geometry": {"coordinates":[-0.215759,51.583073],"type":"Point"}
}