{
  "type": "Feature",
  "properties": {
    "addr:full":"Knowle Top Farm, Ellers Road, Sutton-in-craven Keighley North Yorkshire BD20 7BH",
    "addr:postcode":"bd20 7bh",
    "addr:street":"Ellers Road",
    "iso:country":"GB",
    "sg:address":"Knowle Top Farm, Ellers Road, Sutton-in-craven",
    "sg:city":"Keighley",
    "sg:classifiers":[
        {
            "category":"Farming",
            "subcategory":"Dairy Farm",
            "type":"Manufacturing & Wholesale Goods"
        }
    ],
    "sg:postcode":"BD20 7BH",
    "sg:province":"North Yorkshire",
    "wof:name":"Donald Jeffrey",
    "wof:placetype":"venue"
},
  "geometry": {"coordinates":[-1.992947,53.892651],"type":"Point"}
}