{
  "type": "Feature",
  "properties": {
    "addr:full":"325 Fulham Palace Rd London Greater London SW6 6TJ",
    "addr:housenumber":"325",
    "addr:postcode":"sw6 6tj",
    "addr:street":"Fulham Palace Rd",
    "iso:country":"GB",
    "sg:address":"325 Fulham Palace Rd",
    "sg:city":"London",
    "sg:classifiers":[
        {
            "category":"Taxi",
            "type":"Transportation"
        }
    ],
    "sg:postcode":"SW6 6TJ",
    "sg:province":"Greater London",
    "sg:tags":[
        "mini",
        "cab"
    ],
    "wof:name":"Traffic Car Hire Ltd",
    "wof:placetype":"venue"
},
  "geometry": {"coordinates":[-0.2154809982,51.4765319824],"type":"Point"}
}