{
  "type": "Feature",
  "properties": {
    "addr:full":"8 Franklin Road Harrogate North Yorkshire HG1 5EE",
    "addr:housenumber":"8",
    "addr:postcode":"hg1 5ee",
    "addr:street":"Franklin Road",
    "iso:country":"GB",
    "sg:address":"8 Franklin Road",
    "sg:city":"Harrogate",
    "sg:classifiers":[
        {
            "category":"Retail",
            "subcategory":"Repair Shop",
            "type":"Services"
        }
    ],
    "sg:phone":"+44 1423 507286",
    "sg:postcode":"HG1 5EE",
    "sg:province":"North Yorkshire",
    "sg:tags":[
        "clocks",
        "watch"
    ],
    "wof:name":"Alan Hobkinson",
    "wof:placetype":"venue"
},
  "geometry": {"coordinates":[-1.538886,53.996925],"type":"Point"}
}