{
  "type": "Feature",
  "properties": {
    "addr:full":"50 Romsey Road Dagenham Essex RM9 6BL",
    "addr:housenumber":"50",
    "addr:postcode":"rm9 6bl",
    "addr:street":"Romsey Road",
    "iso:country":"GB",
    "sg:address":"50 Romsey Road",
    "sg:city":"Dagenham",
    "sg:classifiers":[
        {
            "category":"Building & Trades",
            "subcategory":"Landscaping Services",
            "type":"Services"
        }
    ],
    "sg:phone":"+44 20 8592 0718",
    "sg:postcode":"RM9 6BL",
    "sg:province":"Essex",
    "sg:tags":[
        "landscape",
        "contractor"
    ],
    "wof:name":"V R C Tree & Garden Care",
    "wof:placetype":"venue"
},
  "geometry": {"coordinates":[0.1290040016,51.5347747803],"type":"Point"}
}