{
  "type": "Feature",
  "properties": {
    "iso:country":"GB",
    "sg:address":"Church Farm, Llansannor",
    "sg:city":"Cowbridge",
    "sg:classifiers":[
        {
            "category":"Farming",
            "subcategory":"Dairy Farm",
            "type":"Manufacturing & Wholesale Goods"
        },
        {
            "category":"Farming",
            "subcategory":"Livestock Farm",
            "type":"Manufacturing & Wholesale Goods"
        }
    ],
    "sg:phone":"+44 1446 772478",
    "sg:postcode":"CF71 7RX",
    "sg:province":"The Vale of Glamorgan",
    "sg:tags":[
        "others",
        "farmer"
    ],
    "wof:name":"J E Jarvis Son",
    "wof:placetype":"venue"
},
  "geometry": {"coordinates":[-3.4504249096,51.4623908997],"type":"Point"}
}