{
  "type": "Feature",
  "properties": {
    "addr:full":"25 North Road, Highgate London Greater London N6 4BE",
    "addr:housenumber":"25",
    "addr:postcode":"n6 4be",
    "addr:street":"North Road Highgate",
    "iso:country":"GB",
    "sg:address":"25 North Road, Highgate",
    "sg:city":"London",
    "sg:classifiers":[
        {
            "category":"Bars & Pubs",
            "type":"Food & Drink"
        },
        {
            "category":"Community Center",
            "subcategory":"Social",
            "type":"Public Place"
        }
    ],
    "sg:phone":"+44 20 8340 1780",
    "sg:postcode":"N6 4BE",
    "sg:province":"Greater London",
    "sg:tags":[
        "pubs",
        "house",
        "inn",
        "activity"
    ],
    "wof:name":"The Red Lion & Sun",
    "wof:placetype":"venue"
},
  "geometry": {"coordinates":[-0.150014,51.572586],"type":"Point"}
}