{
  "type": "Feature",
  "properties": {
    "addr:full":"Goldings Hill Clinic, 1 Lower Road Loughton Essex IG10 2RS",
    "addr:housenumber":"1",
    "addr:postcode":"ig10 2rs",
    "addr:street":"Goldings;Lower Road",
    "iso:country":"GB",
    "sg:address":"Goldings Hill Clinic, 1 Lower Road",
    "sg:city":"Loughton",
    "sg:classifiers":[
        {
            "category":"Health Services",
            "subcategory":"Podiatrist",
            "type":"Services"
        }
    ],
    "sg:postcode":"IG10 2RS",
    "sg:province":"Essex",
    "sg:tags":[
        "podiatrists",
        "chiropodist"
    ],
    "wof:name":"J Silver",
    "wof:placetype":"venue"
},
  "geometry": {"coordinates":[0.055179,51.647373],"type":"Point"}
}