{
  "type": "Feature",
  "properties": {
    "addr:full":"Handbridge Chester Cheshire CH4 7JF",
    "addr:postcode":"ch4 7jf",
    "iso:country":"GB",
    "sg:address":"Handbridge",
    "sg:city":"Chester",
    "sg:classifiers":[
        {
            "category":"Place Of Worship",
            "type":"Public Place"
        }
    ],
    "sg:phone":"+44 1244 342324",
    "sg:postcode":"CH4 7JF",
    "sg:province":"Cheshire",
    "wof:name":"Handbridge United Reformed Church",
    "wof:placetype":"venue"
},
  "geometry": {"coordinates":[-2.8880500793,53.1834907532],"type":"Point"}
}