{
  "type": "Feature",
  "properties": {
    "addr:full":"Meadow Farm, Cross Moor Lane, Haxby York North Yorkshire YO32 2QR",
    "addr:postcode":"yo32 2qr",
    "addr:street":"Meadow Farm Cross Moor Lane",
    "iso:country":"GB",
    "sg:address":"Meadow Farm, Cross Moor Lane, Haxby",
    "sg:city":"York",
    "sg:classifiers":[
        {
            "category":"Professional",
            "subcategory":"Engineering",
            "type":"Services"
        },
        {
            "category":"Farming",
            "subcategory":"Poultry Farm",
            "type":"Manufacturing & Wholesale Goods"
        }
    ],
    "sg:phone":"+44 1904 760370",
    "sg:postcode":"YO32 2QR",
    "sg:province":"North Yorkshire",
    "sg:tags":[
        "related"
    ],
    "wof:name":"B & P Engineering",
    "wof:placetype":"venue"
},
  "geometry": {"coordinates":[-1.0697499514,54.031539917],"type":"Point"}
}