{
  "type": "Feature",
  "properties": {
    "addr:full":"49 Nicholls Lane Bristol Gloucestershire BS36 1NG",
    "addr:housenumber":"49",
    "addr:postcode":"bs36 1ng",
    "addr:street":"Nicholls Lane",
    "iso:country":"GB",
    "sg:address":"49 Nicholls Lane",
    "sg:city":"Bristol",
    "sg:classifiers":[
        {
            "category":"Building & Trades",
            "subcategory":"Construction",
            "type":"Services"
        }
    ],
    "sg:phone":"+44 1454 773684",
    "sg:postcode":"BS36 1NG",
    "sg:province":"Gloucestershire",
    "sg:tags":[
        "builder"
    ],
    "wof:name":"A E & Son Rollin",
    "wof:placetype":"venue"
},
  "geometry": {"coordinates":[-2.5014519691,51.5266494751],"type":"Point"}
}