{
  "type": "Feature",
  "properties": {
    "iso:country":"GB",
    "sg:address":"Unit 32 Blackburne St",
    "sg:city":"Liverpool",
    "sg:classifiers":[
        {
            "category":"Bus Charters",
            "type":"Transportation"
        }
    ],
    "sg:postcode":"L19 8JA",
    "sg:province":"Merseyside",
    "sg:tags":[
        "hire",
        "coach"
    ],
    "wof:name":"Burch,Edmund,",
    "wof:placetype":"venue"
},
  "geometry": {"coordinates":[-2.970784,53.3997],"type":"Point"}
}