{
  "type": "Feature",
  "properties": {
    "addr:full":"Charles Street, Headless Cross Redditch Warwickshire B97 5AA",
    "addr:postcode":"b97 5aa",
    "addr:street":"Charles Street",
    "iso:country":"GB",
    "sg:address":"Charles Street, Headless Cross",
    "sg:city":"Redditch",
    "sg:classifiers":[
        {
            "category":"Building & Trades",
            "subcategory":"Construction",
            "type":"Services"
        }
    ],
    "sg:phone":"+44 1527 545569",
    "sg:postcode":"B97 5AA",
    "sg:province":"Warwickshire",
    "sg:tags":[
        "glazier"
    ],
    "wof:name":"B G Elvins Ltd.",
    "wof:placetype":"venue"
},
  "geometry": {"coordinates":[-1.9538949728,52.2948875427],"type":"Point"}
}