{
  "type": "Feature",
  "properties": {
    "addr:full":"6 The Potteries, Ditchling Common Ditchling Hassocks East Sussex BN6 8SJ",
    "addr:housenumber":"6",
    "addr:postcode":"bn6 8sj",
    "addr:street":"The Potteries",
    "iso:country":"GB",
    "sg:address":"6 The Potteries, Ditchling Common Ditchling",
    "sg:city":"Hassocks",
    "sg:classifiers":[
        {
            "category":"Professional",
            "subcategory":"Management & Consulting",
            "type":"Services"
        }
    ],
    "sg:phone":"+44 1798 812873",
    "sg:postcode":"BN6 8SJ",
    "sg:province":"East Sussex",
    "sg:tags":[
        "consultant",
        "business"
    ],
    "wof:name":"Field System Integrators Ltd.",
    "wof:placetype":"venue"
},
  "geometry": {"coordinates":[-0.1402689964,50.9239959717],"type":"Point"}
}