{
  "type": "Feature",
  "properties": {
    "addr:full":"Physio & Hyrdrotherpay Clinic, Southgate Ripon North Yorkshire HG4 1PG",
    "addr:postcode":"hg4 1pg",
    "addr:street":"Southgate",
    "iso:country":"GB",
    "sg:address":"Physio & Hyrdrotherpay Clinic, Southgate",
    "sg:city":"Ripon",
    "sg:classifiers":[
        {
            "category":"Health Services",
            "subcategory":"Health Practitioner",
            "type":"Services"
        }
    ],
    "sg:phone":"+44 1765 604700",
    "sg:postcode":"HG4 1PG",
    "sg:province":"North Yorkshire",
    "sg:tags":[
        "physiotherapist"
    ],
    "wof:name":"Joan Burton",
    "wof:placetype":"venue"
},
  "geometry": {"coordinates":[-1.525069952,54.1308403015],"type":"Point"}
}