{
  "type": "Feature",
  "properties": {
    "addr:full":"Station Road, Tupton Chesterfield Derbyshire S42 6DA",
    "addr:postcode":"s42 6da",
    "addr:street":"Station Road",
    "iso:country":"GB",
    "sg:address":"Station Road, Tupton",
    "sg:city":"Chesterfield",
    "sg:classifiers":[
        {
            "category":"Retail",
            "subcategory":"Auto Repair",
            "type":"Services"
        }
    ],
    "sg:phone":"+44 1246 851175",
    "sg:postcode":"S42 6DA",
    "sg:province":"Derbyshire",
    "sg:tags":[
        "bodybuilder",
        "repairer"
    ],
    "wof:name":"Abel Demountable Systems Ltd.",
    "wof:placetype":"venue"
},
  "geometry": {"coordinates":[-1.415599,53.183956],"type":"Point"}
}