{
  "type": "Feature",
  "properties": {
    "addr:full":"1 St Marys Road, Garston Liverpool Merseyside L19 2NJ",
    "addr:housenumber":"1",
    "addr:postcode":"l19 2nj",
    "addr:street":"St Marys Road",
    "iso:country":"GB",
    "sg:address":"1 St Marys Road, Garston",
    "sg:city":"Liverpool",
    "sg:classifiers":[
        {
            "category":"Bars & Pubs",
            "type":"Food & Drink"
        }
    ],
    "sg:postcode":"L19 2NJ",
    "sg:province":"Merseyside",
    "sg:tags":[
        "pubs",
        "inn"
    ],
    "wof:name":"QUEENS HOTEL",
    "wof:placetype":"venue"
},
  "geometry": {"coordinates":[-2.897703886,53.3536186218],"type":"Point"}
}