{
  "type": "Feature",
  "properties": {
    "addr:full":"Delta House, Chilworth Research Centre, Chilworth Southampton Hampshire SO16 7NS",
    "addr:postcode":"so16 7ns",
    "iso:country":"GB",
    "sg:address":"Delta House, Chilworth Research Centre, Chilworth",
    "sg:city":"Southampton",
    "sg:classifiers":[
        {
            "category":"Professional",
            "subcategory":"Art Services",
            "type":"Services"
        }
    ],
    "sg:phone":"+44 23 8076 9008",
    "sg:postcode":"SO16 7NS",
    "sg:province":"Hampshire",
    "sg:tags":[
        "consultant",
        "design"
    ],
    "wof:name":"Acapella Ltd.",
    "wof:placetype":"venue"
},
  "geometry": {"coordinates":[-1.4180740118,50.9628410339],"type":"Point"}
}