{
  "type": "Feature",
  "properties": {
    "iso:country":"GB",
    "sg:address":"Within Ussu Wearmouth Hall, Chester Road",
    "sg:city":"Sunderland",
    "sg:classifiers":[
        {
            "category":"Travel",
            "subcategory":"Travel Agent",
            "type":"Entertainment"
        }
    ],
    "sg:phone":"+44 191 565 7810",
    "sg:postcode":"SR1 3SD",
    "sg:province":"Tyne and Wear",
    "wof:name":"Uc Realisations Ltd.",
    "wof:placetype":"venue"
},
  "geometry": {"coordinates":[-1.39144,54.90464],"type":"Point"}
}