{
  "type": "Feature",
  "properties": {
    "addr:full":"Park Lane Keighley West Yorkshire BD21 4QQ",
    "addr:postcode":"bd21 4qq",
    "addr:street":"Park Lane",
    "iso:country":"GB",
    "sg:address":"Park Lane",
    "sg:city":"Keighley",
    "sg:classifiers":[
        {
            "category":"Shopping",
            "subcategory":"Hobbies, Toys, & Games",
            "type":"Retail Goods"
        }
    ],
    "sg:phone":"+44 1535 605445",
    "sg:postcode":"BD21 4QQ",
    "sg:province":"West Yorkshire",
    "sg:tags":[
        "gunsmith"
    ],
    "wof:name":"John S Ramsbottom",
    "wof:placetype":"venue"
},
  "geometry": {"coordinates":[-1.904638052,53.8598709106],"type":"Point"}
}