{
  "type": "Feature",
  "properties": {
    "iso:country":"GB",
    "sg:address":"74 Main Rd",
    "sg:city":"Banbury",
    "sg:classifiers":[
        {
            "category":"Professional",
            "subcategory":"Engineering",
            "type":"Services"
        }
    ],
    "sg:phone":"+44 1295 712705",
    "sg:postcode":"OX17 2LR",
    "sg:province":"Northamptonshire",
    "sg:tags":[
        "gas",
        "engineer"
    ],
    "wof:name":"Heritage Plumbing & Heating",
    "wof:placetype":"venue"
},
  "geometry": {"coordinates":[-1.2675780058,52.0720596313],"type":"Point"}
}