{
  "type": "Feature",
  "properties": {
    "addr:full":"110 Birchfield Road, Headless Cross Redditch Warwickshire B97 4LT",
    "addr:housenumber":"110",
    "addr:postcode":"b97 4lt",
    "addr:street":"Birchfield Road",
    "iso:country":"GB",
    "sg:address":"110 Birchfield Road, Headless Cross",
    "sg:city":"Redditch",
    "sg:classifiers":[
        {
            "category":"Communications",
            "subcategory":"Film & Video Production",
            "type":"Services"
        },
        {
            "category":"Retail",
            "subcategory":"Repair Shop",
            "type":"Services"
        }
    ],
    "sg:phone":"+44 1527 546298",
    "sg:postcode":"B97 4LT",
    "sg:province":"Warwickshire",
    "sg:tags":[
        "tv",
        "radio",
        "television",
        "studio"
    ],
    "wof:name":"Teague's Television",
    "wof:placetype":"venue"
},
  "geometry": {"coordinates":[-1.951073,52.29464],"type":"Point"}
}