{
  "type": "Feature",
  "properties": {
    "addr:full":"5 Freshford Close, Langley Eastbourne East Sussex BN23 7NT",
    "addr:housenumber":"5",
    "addr:postcode":"bn23 7nt",
    "addr:street":"Freshford Close",
    "iso:country":"GB",
    "sg:address":"5 Freshford Close, Langley",
    "sg:city":"Eastbourne",
    "sg:classifiers":[
        {
            "category":"Building & Trades",
            "subcategory":"Landscaping Services",
            "type":"Services"
        }
    ],
    "sg:postcode":"BN23 7NT",
    "sg:province":"East Sussex",
    "sg:tags":[
        "gardening"
    ],
    "wof:name":"Anthony Fuller Landscaping",
    "wof:placetype":"venue"
},
  "geometry": {"coordinates":[0.3086329997,50.8021430969],"type":"Point"}
}