{
  "type": "Feature",
  "properties": {
    "addr:full":"4 Turner Rise, Oadby Leicester Leicestershire LE2 5SG",
    "addr:housenumber":"4",
    "addr:postcode":"le2 5sg",
    "addr:street":"Turner Rise",
    "iso:country":"GB",
    "sg:address":"4 Turner Rise, Oadby",
    "sg:city":"Leicester",
    "sg:classifiers":[
        {
            "category":"Health Services",
            "subcategory":"Hospital",
            "type":"Services"
        },
        {
            "category":"Health Services",
            "subcategory":"Nursing And Care Facility",
            "type":"Services"
        }
    ],
    "sg:phone":"+44 116 271 8485",
    "sg:postcode":"LE2 5SG",
    "sg:province":"Leicestershire",
    "sg:tags":[
        "residential"
    ],
    "wof:name":"Turner Rise Group Home",
    "wof:placetype":"venue"
},
  "geometry": {"coordinates":[-1.0732909441,52.5936279297],"type":"Point"}
}