{
  "type": "Feature",
  "properties": {
    "addr:full":"Beechcroft Road Swindon Wiltshire SN2 7RD",
    "addr:postcode":"sn2 7rd",
    "addr:street":"Beechcroft Road",
    "iso:country":"GB",
    "sg:address":"Beechcroft Road",
    "sg:city":"Swindon",
    "sg:classifiers":[
        {
            "category":"Education",
            "subcategory":"Preschool",
            "type":"Public Place"
        }
    ],
    "sg:phone":"+44 1793 705769",
    "sg:postcode":"SN2 7RD",
    "sg:province":"Wiltshire",
    "sg:tags":[
        "pre",
        "school",
        "playgroups",
        "pre-school"
    ],
    "wof:name":"St Phillips Church Playgroup",
    "wof:placetype":"venue"
},
  "geometry": {"coordinates":[-1.763193965,51.5911560059],"type":"Point"}
}