{
  "type": "Feature",
  "properties": {
    "iso:country":"GB",
    "sg:address":"Clutha House, 10 Storeys Gate",
    "sg:city":"London",
    "sg:classifiers":[
        {
            "category":"Professional",
            "subcategory":"Lawyer & Legal Services",
            "type":"Services"
        }
    ],
    "sg:phone":"+44 20 7222 5002",
    "sg:postcode":"SW1P 3AY",
    "sg:province":"Greater London",
    "sg:tags":[
        "solicitor"
    ],
    "wof:name":"Jenkins & Hand",
    "wof:placetype":"venue"
},
  "geometry": {"coordinates":[-0.12969,51.500389],"type":"Point"}
}