{
  "type": "Feature",
  "properties": {
    "iso:country":"GB",
    "sg:address":"7 Ashley Rd",
    "sg:city":"Salisbury",
    "sg:classifiers":[
        {
            "category":"Building & Trades",
            "subcategory":"Construction",
            "type":"Services"
        }
    ],
    "sg:phone":"+44 1722 320655",
    "sg:postcode":"SP2 7BZ",
    "sg:province":"Wiltshire",
    "sg:tags":[
        "dry",
        "lining",
        "plasterers",
        "screeders"
    ],
    "wof:name":"A K Plastering Services",
    "wof:placetype":"venue"
},
  "geometry": {"coordinates":[-1.8070889711,51.0752716064],"type":"Point"}
}