{
  "type": "Feature",
  "properties": {
    "iso:country":"GB",
    "sg:address":"15 Milton Rd",
    "sg:city":"Brighton",
    "sg:classifiers":[
        {
            "category":"Retail",
            "subcategory":"Repair Shop",
            "type":"Services"
        }
    ],
    "sg:phone":"+44 1273 693184",
    "sg:postcode":"BN2 2TQ",
    "sg:province":"East Sussex",
    "sg:tags":[
        "maintenance"
    ],
    "wof:name":"J & N Construction",
    "wof:placetype":"venue"
},
  "geometry": {"coordinates":[-0.127738,50.831177],"type":"Point"}
}