{
  "type": "Feature",
  "properties": {
    "iso:country":"GB",
    "sg:address":"119 Congleton Road",
    "sg:city":"Macclesfield",
    "sg:classifiers":[
        {
            "category":"Building & Trades",
            "subcategory":"Construction",
            "type":"Services"
        }
    ],
    "sg:phone":"+44 1625 263678",
    "sg:postcode":"SK11 7XD",
    "sg:province":"Cheshire",
    "sg:tags":[
        "roofing"
    ],
    "wof:name":"Alan Johnson",
    "wof:placetype":"venue"
},
  "geometry": {"coordinates":[-2.1473670006,53.244934082],"type":"Point"}
}