{
  "type": "Feature",
  "properties": {
    "addr:full":"8 Llandudno Road, Penrhyn Bay Llandudno Conwy LL30 3HA",
    "addr:housenumber":"8",
    "addr:postcode":"ll30 3ha",
    "addr:street":"Llandudno Road",
    "iso:country":"GB",
    "sg:address":"8 Llandudno Road, Penrhyn Bay",
    "sg:city":"Llandudno",
    "sg:classifiers":[
        {
            "category":"Food & Beverages",
            "subcategory":"Liquor & Beverages",
            "type":"Retail Goods"
        }
    ],
    "sg:phone":"+44 1492 549403",
    "sg:postcode":"LL30 3HA",
    "sg:province":"Conwy",
    "sg:tags":[
        "beer",
        "spirit",
        "wines"
    ],
    "wof:name":"Victoria Wine",
    "wof:placetype":"venue"
},
  "geometry": {"coordinates":[-3.7761859894,53.3173217773],"type":"Point"}
}