{
  "type": "Feature",
  "properties": {
    "addr:full":"Ash Hurst 17 Duke Street, Formby Liverpool Lancashire L37 4AN",
    "addr:housenumber":"17",
    "addr:postcode":"l37 4an",
    "addr:street":"Ash Hurst;Duke Street",
    "iso:country":"GB",
    "sg:address":"Ash Hurst 17 Duke Street, Formby",
    "sg:city":"Liverpool",
    "sg:classifiers":[
        {
            "category":"Organizations",
            "subcategory":"Community Association",
            "type":"Services"
        }
    ],
    "sg:phone":"+44 1704 879399",
    "sg:postcode":"L37 4AN",
    "sg:province":"Lancashire",
    "sg:tags":[
        "society",
        "housing"
    ],
    "wof:name":"Quest Housing Association Ltd.",
    "wof:placetype":"venue"
},
  "geometry": {"coordinates":[-3.061378,53.556786],"type":"Point"}
}