{
  "type": "Feature",
  "properties": {
    "addr:full":"2a Swiss Road Weston-super-mare Somerset BS23 3AU",
    "addr:housenumber":"2a",
    "addr:postcode":"bs23 3au",
    "addr:street":"Swiss Road",
    "iso:country":"GB",
    "sg:address":"2a Swiss Road",
    "sg:city":"Weston-super-mare",
    "sg:classifiers":[
        {
            "category":"Retail",
            "subcategory":"Repair Shop",
            "type":"Services"
        }
    ],
    "sg:phone":"+44 1934 419753",
    "sg:postcode":"BS23 3AU",
    "sg:province":"Somerset",
    "sg:tags":[
        "upholsterer"
    ],
    "wof:name":"Tony Slingsby",
    "wof:placetype":"venue"
},
  "geometry": {"coordinates":[-2.970412,51.346317],"type":"Point"}
}