{
  "type": "Feature",
  "properties": {
    "addr:full":"Beambridge Wellington Devon TA21 0HB",
    "addr:postcode":"ta21 0hb",
    "iso:country":"GB",
    "sg:address":"Beambridge",
    "sg:city":"Wellington",
    "sg:classifiers":[
        {
            "category":"Travel",
            "subcategory":"Hotels & Motels",
            "type":"Entertainment"
        }
    ],
    "sg:postcode":"TA21 0HB",
    "sg:province":"Devon",
    "wof:name":"Beambridge Hotel",
    "wof:placetype":"venue"
},
  "geometry": {"coordinates":[-3.2713620663,50.9663124084],"type":"Point"}
}