{
  "type": "Feature",
  "properties": {
    "iso:country":"GB",
    "sg:address":"Unit 1, Fishmarket Quay, Maritime Quarter",
    "sg:city":"Swansea",
    "sg:classifiers":[
        {
            "category":"Autos & Motor Vehicles",
            "subcategory":"Boat Sales",
            "type":"Retail Goods"
        }
    ],
    "sg:phone":"+44 1792 645303",
    "sg:postcode":"SA1 1UP",
    "sg:province":"Neath Port Talbot",
    "sg:tags":[
        "repair",
        "builder"
    ],
    "sg:website":"http://www.dickies.co.uk",
    "wof:name":"Dickie's Yacht Sales",
    "wof:placetype":"venue"
},
  "geometry": {"coordinates":[-3.940929,51.623154],"type":"Point"}
}