{
  "type": "Feature",
  "properties": {
    "iso:country":"GB",
    "sg:address":"126 Nottingham Road, Burton Joyce",
    "sg:city":"Nottingham",
    "sg:classifiers":[
        {
            "category":"Building & Trades",
            "subcategory":"Construction",
            "type":"Services"
        }
    ],
    "sg:phone":"+44 115 931 3007",
    "sg:postcode":"NG14 5AT",
    "sg:province":"Nottinghamshire",
    "sg:tags":[
        "joiner",
        "carpenter"
    ],
    "wof:name":"R C Henshaw Joinery Services",
    "wof:placetype":"venue"
},
  "geometry": {"coordinates":[-1.050811,52.981827],"type":"Point"}
}