{
  "type": "Feature",
  "properties": {
    "iso:country":"GB",
    "sg:address":"Culbokie",
    "sg:city":"Dingwall",
    "sg:classifiers":[
        {
            "category":"Shopping",
            "subcategory":"Department Store",
            "type":"Retail Goods"
        }
    ],
    "sg:postcode":"IV7 8JH",
    "sg:province":"Highland",
    "wof:name":"Culbokie Post Office",
    "wof:placetype":"venue"
},
  "geometry": {"coordinates":[-4.339747,57.600994],"type":"Point"}
}