{
  "type": "Feature",
  "properties": {
    "iso:country":"GB",
    "sg:address":"2 Bowness Way, Gunthorpe",
    "sg:city":"Peterborough",
    "sg:classifiers":[
        {
            "category":"Freight",
            "type":"Transportation"
        }
    ],
    "sg:postcode":"PE4 7ZE",
    "sg:province":"Cambridgeshire",
    "sg:tags":[
        "haulage",
        "road"
    ],
    "wof:name":"European Trailers Ltd",
    "wof:placetype":"venue"
},
  "geometry": {"coordinates":[-0.244688,52.610718],"type":"Point"}
}