{
  "type": "Feature",
  "properties": {
    "addr:full":"49 St Peter's Street St Albans Hertfordshire AL1 3DY",
    "addr:housenumber":"49",
    "addr:postcode":"al1 3dy",
    "addr:street":"St Peter'S Street",
    "iso:country":"GB",
    "sg:address":"49 St Peter's Street",
    "sg:city":"St Albans",
    "sg:classifiers":[
        {
            "category":"Banks & Credit Unions",
            "subcategory":"Financial Services",
            "type":"Services"
        }
    ],
    "sg:phone":"+44 1727 850594",
    "sg:postcode":"AL1 3DY",
    "sg:province":"Hertfordshire",
    "sg:tags":[
        "building",
        "society"
    ],
    "wof:name":"Britannia Building Society",
    "wof:placetype":"venue"
},
  "geometry": {"coordinates":[-0.3375700116,51.7536811829],"type":"Point"}
}