{
  "type": "Feature",
  "properties": {
    "addr:full":"Grove Farm Estate, Bures Road, Wormingford Colchester Essex CO6 3AJ",
    "addr:postcode":"co6 3aj",
    "addr:street":"Bures Road",
    "iso:country":"GB",
    "sg:address":"Grove Farm Estate, Bures Road, Wormingford",
    "sg:city":"Colchester",
    "sg:classifiers":[
        {
            "category":"Freight",
            "type":"Transportation"
        }
    ],
    "sg:phone":"+44 1206 241880",
    "sg:postcode":"CO6 3AJ",
    "sg:province":"Essex",
    "sg:tags":[
        "forwarders"
    ],
    "wof:name":"Summit Shipping Ltd.",
    "wof:placetype":"venue"
},
  "geometry": {"coordinates":[0.80932,51.948563],"type":"Point"}
}