{
  "type": "Feature",
  "properties": {
    "iso:country":"GB",
    "sg:address":"Chedgrave Common",
    "sg:city":"Norwich",
    "sg:classifiers":[
        {
            "category":"Travel",
            "subcategory":"Hotels & Motels",
            "type":"Entertainment"
        }
    ],
    "sg:postcode":"NR14 6BE",
    "sg:province":"Norfolk",
    "sg:tags":[
        "house",
        "guest"
    ],
    "wof:name":"The Farmhouse",
    "wof:placetype":"venue"
},
  "geometry": {"coordinates":[1.479366,52.541355],"type":"Point"}
}