{
  "type": "Feature",
  "properties": {
    "addr:full":"2a Tudor Road Hampton Greater London TW12 2NQ",
    "addr:housenumber":"2a",
    "addr:postcode":"tw12 2nq",
    "addr:street":"Tudor Road",
    "iso:country":"GB",
    "sg:address":"2a Tudor Road",
    "sg:city":"Hampton",
    "sg:classifiers":[
        {
            "category":"Professional",
            "subcategory":"Accounting & Tax Preparation",
            "type":"Services"
        }
    ],
    "sg:phone":"+44 20 8783 1352",
    "sg:postcode":"TW12 2NQ",
    "sg:province":"Greater London",
    "sg:tags":[
        "accountant"
    ],
    "wof:name":"Alan R Corbett",
    "wof:placetype":"venue"
},
  "geometry": {"coordinates":[-0.370167,51.417816],"type":"Point"}
}