{
  "type": "Feature",
  "properties": {
    "addr:full":"91 Lowesmoor Worcester Worcestershire WR1 2RS",
    "addr:housenumber":"91",
    "addr:postcode":"wr1 2rs",
    "addr:street":"Lowesmoor",
    "iso:country":"GB",
    "sg:address":"91 Lowesmoor",
    "sg:city":"Worcester",
    "sg:classifiers":[
        {
            "category":"Health Services",
            "subcategory":"Dentist",
            "type":"Services"
        }
    ],
    "sg:phone":"+44 1905 724633",
    "sg:postcode":"WR1 2RS",
    "sg:province":"Worcestershire",
    "wof:name":"Lowesmoor Dental Practice",
    "wof:placetype":"venue"
},
  "geometry": {"coordinates":[-2.2162389755,52.1950798035],"type":"Point"}
}