{
  "type": "Feature",
  "properties": {
    "addr:full":"1 York House, Langston Road Loughton Essex IG10 3TQ",
    "addr:housenumber":"1",
    "addr:postcode":"ig10 3tq",
    "addr:street":"York House Langston Road",
    "iso:country":"GB",
    "sg:address":"1 York House, Langston Road",
    "sg:city":"Loughton",
    "sg:classifiers":[
        {
            "category":"Professional",
            "type":"Services"
        }
    ],
    "sg:phone":"+44 20 8508 2224",
    "sg:postcode":"IG10 3TQ",
    "sg:province":"Essex",
    "sg:tags":[
        "exhibition"
    ],
    "wof:name":"Worldwide Exhibition Specialists Ltd.",
    "wof:placetype":"venue"
},
  "geometry": {"coordinates":[0.055179,51.647373],"type":"Point"}
}