{
  "type": "Feature",
  "properties": {
    "iso:country":"GB",
    "sg:address":"27 Newland Road",
    "sg:city":"Goole",
    "sg:classifiers":[
        {
            "category":"Retail",
            "subcategory":"Driving School",
            "type":"Services"
        }
    ],
    "sg:postcode":"DN14 6DZ",
    "sg:province":"East Riding of Yorkshire",
    "wof:name":"Hunt's School of Motoring",
    "wof:placetype":"venue"
},
  "geometry": {"coordinates":[-0.877267,53.709915],"type":"Point"}
}