{
  "type": "Feature",
  "properties": {
    "addr:full":"Cruttenden, Brook Street, Woodchurch Ashford Kent TN26 3SR",
    "addr:postcode":"tn26 3sr",
    "addr:street":"Brook Street",
    "iso:country":"GB",
    "sg:address":"Cruttenden, Brook Street, Woodchurch",
    "sg:city":"Ashford",
    "sg:classifiers":[
        {
            "category":"Professional",
            "subcategory":"Computer Services",
            "type":"Services"
        }
    ],
    "sg:phone":"+44 1233 861428",
    "sg:postcode":"TN26 3SR",
    "sg:province":"Kent",
    "sg:tags":[
        "system",
        "software"
    ],
    "wof:name":"Rosalyn Friday Associates",
    "wof:placetype":"venue"
},
  "geometry": {"coordinates":[0.773845017,51.0757446289],"type":"Point"}
}