{
  "type": "Feature",
  "properties": {
    "iso:country":"GB",
    "sg:address":"20a Lanepwing Lane",
    "sg:city":"Manchester",
    "sg:classifiers":[
        {
            "category":"Real Estate",
            "subcategory":"Real Estate Operator",
            "type":"Services"
        }
    ],
    "sg:phone":"+44 161 445 7000",
    "sg:postcode":"M20 2WS",
    "sg:province":"Greater Manchester",
    "sg:tags":[
        "letting",
        "agent"
    ],
    "wof:name":"Montrose Properties",
    "wof:placetype":"venue"
},
  "geometry": {"coordinates":[-2.239579,53.427094],"type":"Point"}
}