{
  "type": "Feature",
  "properties": {
    "addr:full":"71 Bowring Park Ave Liverpool Merseyside L16 2NH",
    "addr:housenumber":"71",
    "addr:postcode":"l16 2nh",
    "addr:street":"Bowring Park Ave",
    "iso:country":"GB",
    "sg:address":"71 Bowring Park Ave",
    "sg:city":"Liverpool",
    "sg:classifiers":[
        {
            "category":"Professional",
            "subcategory":"Engineering",
            "type":"Services"
        }
    ],
    "sg:postcode":"L16 2NH",
    "sg:province":"Merseyside",
    "sg:tags":[
        "contractor",
        "electrical",
        "engineer"
    ],
    "wof:name":"Britton,William,",
    "wof:placetype":"venue"
},
  "geometry": {"coordinates":[-2.870119,53.405079],"type":"Point"}
}