{
  "type": "Feature",
  "properties": {
    "addr:full":"113 Lambeth Road London Greater London SE1 7LS",
    "addr:housenumber":"113",
    "addr:postcode":"se1 7ls",
    "addr:street":"Lambeth Road",
    "iso:country":"GB",
    "sg:address":"113 Lambeth Road",
    "sg:city":"London",
    "sg:classifiers":[
        {
            "category":"Travel",
            "subcategory":"Hotels & Motels",
            "type":"Entertainment"
        }
    ],
    "sg:phone":"+44 20 7793 1010",
    "sg:postcode":"SE1 7LS",
    "sg:province":"Greater London",
    "wof:name":"Novotel London Waterloo",
    "wof:placetype":"venue"
},
  "geometry": {"coordinates":[-0.118411,51.494778],"type":"Point"}
}