{
  "type": "Feature",
  "properties": {
    "iso:country":"GB",
    "sg:address":"1246 Evesham Road",
    "sg:city":"Redditch",
    "sg:classifiers":[
        {
            "category":"Food & Beverages",
            "subcategory":"Meat & Fish",
            "type":"Retail Goods"
        }
    ],
    "sg:postcode":"B96 6AA",
    "sg:province":"Warwickshire",
    "sg:tags":[
        "butcher"
    ],
    "wof:name":"Pete the Meat",
    "wof:placetype":"venue"
},
  "geometry": {"coordinates":[-1.9374860525,52.2578544617],"type":"Point"}
}