{
  "type": "Feature",
  "properties": {
    "addr:full":"32 Brookwood Road Hounslow Greater London TW3 4HD",
    "addr:housenumber":"32",
    "addr:postcode":"tw3 4hd",
    "addr:street":"Brookwood Road",
    "iso:country":"GB",
    "sg:address":"32 Brookwood Road",
    "sg:city":"Hounslow",
    "sg:classifiers":[
        {
            "category":"Building & Trades",
            "subcategory":"Construction",
            "type":"Services"
        }
    ],
    "sg:postcode":"TW3 4HD",
    "sg:province":"Greater London",
    "sg:tags":[
        "decorator",
        "painter"
    ],
    "wof:name":"Dougies Dirt Devils Ltd.",
    "wof:placetype":"venue"
},
  "geometry": {"coordinates":[-0.3627679944,51.475944519],"type":"Point"}
}