{
  "type": "Feature",
  "properties": {
    "addr:full":"Unit 15, Merchants Quay, Pennygillam Ind Est Launceston Cornwall PL15 7ED",
    "addr:housenumber":"unit 15",
    "addr:postcode":"pl15 7ed",
    "addr:street":"Merchants Quay Pennygillam",
    "iso:country":"GB",
    "sg:address":"Unit 15, Merchants Quay, Pennygillam Ind Est",
    "sg:city":"Launceston",
    "sg:classifiers":[
        {
            "category":"Autos & Motor Vehicles",
            "subcategory":"Auto Supplies",
            "type":"Retail Goods"
        }
    ],
    "sg:phone":"+44 1566 774699",
    "sg:postcode":"PL15 7ED",
    "sg:province":"Cornwall",
    "sg:tags":[
        "windscreen"
    ],
    "wof:name":"Nationwide Auto Glazing",
    "wof:placetype":"venue"
},
  "geometry": {"coordinates":[-4.3633441925,50.6367073059],"type":"Point"}
}