{
  "type": "Feature",
  "properties": {
    "addr:full":"Old School, The Grn, Great Milton Oxford Oxfordshire OX44 7NT",
    "addr:postcode":"ox44 7nt",
    "addr:street":"The Grn",
    "iso:country":"GB",
    "sg:address":"Old School, The Grn, Great Milton",
    "sg:city":"Oxford",
    "sg:classifiers":[
        {
            "category":"Banks & Credit Unions",
            "subcategory":"Investment Brokerage",
            "type":"Services"
        }
    ],
    "sg:phone":"+44 1844 278332",
    "sg:postcode":"OX44 7NT",
    "sg:province":"Oxfordshire",
    "sg:tags":[
        "firework",
        "stockist"
    ],
    "wof:name":"Fantastic Fireworks",
    "wof:placetype":"venue"
},
  "geometry": {"coordinates":[-1.0862790346,51.7205696106],"type":"Point"}
}