{
  "type": "Feature",
  "properties": {
    "iso:country":"GB",
    "sg:address":"Poplar Cotts, Hooe",
    "sg:city":"Battle",
    "sg:classifiers":[
        {
            "category":"Home & Garden",
            "subcategory":"Building Materials",
            "type":"Retail Goods"
        }
    ],
    "sg:phone":"+44 1424 843363",
    "sg:postcode":"TN33 9HG",
    "sg:province":"East Sussex",
    "sg:tags":[
        "fencing"
    ],
    "wof:name":"Keila Fencing",
    "wof:placetype":"venue"
},
  "geometry": {"coordinates":[0.398087,50.858673],"type":"Point"}
}