{
  "type": "Feature",
  "properties": {
    "addr:full":"79 Perth Road Cowdenbeath Fife KY4 9BG",
    "addr:housenumber":"79",
    "addr:postcode":"ky4 9bg",
    "addr:street":"Perth Road",
    "iso:country":"GB",
    "sg:address":"79 Perth Road",
    "sg:city":"Cowdenbeath",
    "sg:classifiers":[
        {
            "category":"Bars & Pubs",
            "type":"Food & Drink"
        }
    ],
    "sg:phone":"+44 1383 510089",
    "sg:postcode":"KY4 9BG",
    "sg:province":"Fife",
    "sg:tags":[
        "pubs",
        "inn"
    ],
    "wof:name":"Junction Bar",
    "wof:placetype":"venue"
},
  "geometry": {"coordinates":[-3.3430581093,56.1165084839],"type":"Point"}
}