{
  "type": "Feature",
  "properties": {
    "iso:country":"GB",
    "sg:address":"37 Park Lane, Cowplain",
    "sg:city":"Waterlooville",
    "sg:classifiers":[
        {
            "category":"Retail",
            "subcategory":"Repair Shop",
            "type":"Services"
        }
    ],
    "sg:phone":"+44 23 9225 8345",
    "sg:postcode":"PO8 8AG",
    "sg:province":"Hampshire",
    "sg:tags":[
        "sharpening",
        "tool"
    ],
    "wof:name":"David J Richards",
    "wof:placetype":"venue"
},
  "geometry": {"coordinates":[-1.0121660233,50.8908576965],"type":"Point"}
}