{
  "type": "Feature",
  "properties": {
    "iso:country":"GB",
    "sg:address":"3 Littabourne, Pilton",
    "sg:city":"Barnstaple",
    "sg:classifiers":[
        {
            "category":"Professional",
            "subcategory":"Business Services",
            "type":"Services"
        }
    ],
    "sg:postcode":"EX31 1PX",
    "sg:province":"Devon",
    "sg:tags":[
        "assessment",
        "quality"
    ],
    "wof:name":"Winfield,Shaun,",
    "wof:placetype":"venue"
},
  "geometry": {"coordinates":[-4.0598101616,51.0891265869],"type":"Point"}
}