{
  "type": "Feature",
  "properties": {
    "iso:country":"GB",
    "sg:address":"I D R C, 8 Breans Buildings, Chanchery Lane",
    "sg:city":"London",
    "sg:classifiers":[
        {
            "category":"Professional",
            "subcategory":"Lawyer & Legal Services",
            "type":"Services"
        }
    ],
    "sg:phone":"+44 20 7440 7373",
    "sg:postcode":"EC4A 1HP",
    "sg:province":"Greater London",
    "wof:name":"The City Disputes Panel",
    "wof:placetype":"venue"
},
  "geometry": {"coordinates":[-0.11052,51.515942],"type":"Point"}
}