{
  "type": "Feature",
  "properties": {
    "addr:full":"151 Elm Drive Hove East Sussex BN3 7JA",
    "addr:housenumber":"151",
    "addr:postcode":"bn3 7ja",
    "addr:street":"Elm Drive",
    "iso:country":"GB",
    "sg:address":"151 Elm Drive",
    "sg:city":"Hove",
    "sg:classifiers":[
        {
            "category":"Professional",
            "subcategory":"Engineering",
            "type":"Services"
        }
    ],
    "sg:phone":"+44 1273 882796",
    "sg:postcode":"BN3 7JA",
    "sg:province":"East Sussex",
    "sg:tags":[
        "contractor",
        "electrical",
        "engineer"
    ],
    "wof:name":"Home Care Services",
    "wof:placetype":"venue"
},
  "geometry": {"coordinates":[-0.1942770034,50.8417663574],"type":"Point"}
}