{
  "type": "Feature",
  "properties": {
    "iso:country":"GB",
    "sg:address":"12 Dyke Road",
    "sg:city":"Brighton",
    "sg:classifiers":[
        {
            "category":"Real Estate",
            "subcategory":"Real Estate Operator",
            "type":"Services"
        }
    ],
    "sg:phone":"+44 1273 724869",
    "sg:postcode":"BN1 3FE",
    "sg:province":"East Sussex",
    "sg:tags":[
        "letting",
        "agent"
    ],
    "wof:name":"Stuart Wyse Ogilvie Estates Ltd.",
    "wof:placetype":"venue"
},
  "geometry": {"coordinates":[-0.144527,50.824203],"type":"Point"}
}