{
  "type": "Feature",
  "properties": {
    "iso:country":"GB",
    "sg:address":"94 Dawes Road, Fulham",
    "sg:city":"London",
    "sg:classifiers":[
        {
            "category":"Retail",
            "subcategory":"Veterinary Services",
            "type":"Services"
        }
    ],
    "sg:phone":"+44 20 7381 3939",
    "sg:postcode":"SW6 7EJ",
    "sg:province":"Greater London",
    "sg:tags":[
        "surgeon"
    ],
    "wof:name":"Simon Meyer & Associates",
    "wof:placetype":"venue"
},
  "geometry": {"coordinates":[-0.202722,51.480259],"type":"Point"}
}