{
  "type": "Feature",
  "properties": {
    "addr:full":"Coach Depot, Brunswick Park Road London Greater London N11 1HA",
    "addr:postcode":"n11 1ha",
    "addr:street":"Brunswick Park Road",
    "iso:country":"GB",
    "sg:address":"Coach Depot, Brunswick Park Road",
    "sg:city":"London",
    "sg:classifiers":[
        {
            "category":"Bus Charters",
            "type":"Transportation"
        }
    ],
    "sg:phone":"+44 20 8368 3190",
    "sg:postcode":"N11 1HA",
    "sg:province":"Greater London",
    "sg:tags":[
        "hire",
        "coach"
    ],
    "wof:name":"Southgate & Finchley Coaches Ltd.",
    "wof:placetype":"venue"
},
  "geometry": {"coordinates":[-0.1484300047,51.6277198792],"type":"Point"}
}