{
  "type": "Feature",
  "properties": {
    "addr:full":"31 Winfield Gro, Newdigate Dorking Surrey RH5 5AX",
    "addr:housenumber":"31",
    "addr:postcode":"rh5 5ax",
    "addr:street":"Winfield Gro Newdigate Dorking",
    "iso:country":"GB",
    "sg:address":"31 Winfield Gro, Newdigate",
    "sg:city":"Dorking",
    "sg:classifiers":[
        {
            "category":"Home & Garden",
            "subcategory":"Carpets & Floor Coverings",
            "type":"Retail Goods"
        }
    ],
    "sg:phone":"+44 1306 711585",
    "sg:postcode":"RH5 5AX",
    "sg:province":"Surrey",
    "sg:tags":[
        "carpets",
        "rug",
        "matting"
    ],
    "wof:name":"A J Roberts Carpets",
    "wof:placetype":"venue"
},
  "geometry": {"coordinates":[-0.333659,51.146042],"type":"Point"}
}