{
  "type": "Feature",
  "properties": {
    "iso:country":"GB",
    "sg:address":"37b Elmore Street, Islington",
    "sg:city":"London",
    "sg:classifiers":[
        {
            "category":"Utilities",
            "type":"Services"
        }
    ],
    "sg:postcode":"N1 3AJ",
    "sg:province":"Greater London",
    "sg:tags":[
        "internet"
    ],
    "wof:name":"Zelica",
    "wof:placetype":"venue"
},
  "geometry": {"coordinates":[-0.0884030014,51.5416984558],"type":"Point"}
}