{
  "type": "Feature",
  "properties": {
    "iso:country":"GB",
    "sg:address":"16 Swinegate",
    "sg:city":"York",
    "sg:classifiers":[
        {
            "category":"Home & Garden",
            "subcategory":"Furniture",
            "type":"Retail Goods"
        }
    ],
    "sg:phone":"+44 1904 671241",
    "sg:postcode":"YO1 8AZ",
    "sg:province":"North Yorkshire",
    "sg:tags":[
        "outlet"
    ],
    "wof:name":"Porcupine",
    "wof:placetype":"venue"
},
  "geometry": {"coordinates":[-1.081232,53.960125],"type":"Point"}
}