{
  "type": "Feature",
  "properties": {
    "iso:country":"GB",
    "sg:address":"44 Clifford Lane, Kinning Park",
    "sg:city":"Glasgow",
    "sg:classifiers":[
        {
            "category":"Professional",
            "subcategory":"Management & Consulting",
            "type":"Services"
        }
    ],
    "sg:phone":"+44 141 427 6578",
    "sg:postcode":"G51 1NR",
    "sg:province":"Glasgow City",
    "sg:tags":[
        "consultant",
        "business"
    ],
    "wof:name":"W L R Associates Ltd.",
    "wof:placetype":"venue"
},
  "geometry": {"coordinates":[-4.2936887741,55.8516044617],"type":"Point"}
}