{
  "type": "Feature",
  "properties": {
    "addr:full":"Vyner Street, Studios 21-23 Vyner St Bethnal Green Greater London E2 9DG",
    "addr:housenumber":"21-23",
    "addr:postcode":"e2 9dg",
    "addr:street":"Vyner;Vyner St",
    "iso:country":"GB",
    "sg:address":"Vyner Street, Studios 21-23 Vyner St",
    "sg:city":"Bethnal Green",
    "sg:classifiers":[
        {
            "category":"Shopping",
            "subcategory":"Photographic Equipment",
            "type":"Retail Goods"
        }
    ],
    "sg:phone":"+44 20 8983 4388",
    "sg:postcode":"E2 9DG",
    "sg:province":"Greater London",
    "wof:name":"Richard Barnes",
    "wof:placetype":"venue"
},
  "geometry": {"coordinates":[-0.0567100011,51.5344009399],"type":"Point"}
}