{
  "type": "Feature",
  "properties": {
    "iso:country":"GB",
    "sg:address":"Units 6 & 7, Innovation Centre",
    "sg:city":"Stafford",
    "sg:classifiers":[
        {
            "category":"Wholesale",
            "subcategory":"Hardware",
            "type":"Manufacturing & Wholesale Goods"
        }
    ],
    "sg:phone":"+44 1785 229191",
    "sg:postcode":"ST18 0AR",
    "sg:province":"Staffordshire",
    "sg:tags":[
        "merchant",
        "ironmonger"
    ],
    "wof:name":"Amf Computers Ltd.",
    "wof:placetype":"venue"
},
  "geometry": {"coordinates":[-2.083920002,52.8148994446],"type":"Point"}
}