{
  "type": "Feature",
  "properties": {
    "addr:full":"Crown Farm, Sturton By Stow Lincoln Lincolnshire LN1 2AR",
    "addr:postcode":"ln1 2ar",
    "addr:street":"Lincoln",
    "iso:country":"GB",
    "sg:address":"Crown Farm, Sturton By Stow",
    "sg:city":"Lincoln",
    "sg:classifiers":[
        {
            "category":"Farming",
            "subcategory":"Livestock Farm",
            "type":"Manufacturing & Wholesale Goods"
        }
    ],
    "sg:phone":"+44 1427 788374",
    "sg:postcode":"LN1 2AR",
    "sg:province":"Lincolnshire",
    "sg:tags":[
        "others"
    ],
    "wof:name":"Albert A Bradshaw",
    "wof:placetype":"venue"
},
  "geometry": {"coordinates":[-0.676353991,53.3270759583],"type":"Point"}
}