{
  "type": "Feature",
  "properties": {
    "addr:full":"15 Nicol Street Kirkcaldy Fife KY1 1NY",
    "addr:housenumber":"15",
    "addr:postcode":"ky1 1ny",
    "addr:street":"Nicol Street",
    "iso:country":"GB",
    "sg:address":"15 Nicol Street",
    "sg:city":"Kirkcaldy",
    "sg:classifiers":[
        {
            "category":"Social Services",
            "subcategory":"Job Training",
            "type":"Services"
        },
        {
            "category":"Real Estate",
            "subcategory":"Architect",
            "type":"Services"
        }
    ],
    "sg:phone":"+44 1592 263706",
    "sg:postcode":"KY1 1NY",
    "sg:province":"Fife",
    "sg:tags":[
        "draughtsman",
        "drawing"
    ],
    "wof:name":"Termack Engineering Services",
    "wof:placetype":"venue"
},
  "geometry": {"coordinates":[-3.160892,56.106476],"type":"Point"}
}