{
  "type": "Feature",
  "properties": {
    "addr:full":"34 Kings Head Hill, Chingford London Greater London E4 7LY",
    "addr:housenumber":"34",
    "addr:postcode":"e4 7ly",
    "addr:street":"Kings Head Hill",
    "iso:country":"GB",
    "sg:address":"34 Kings Head Hill, Chingford",
    "sg:city":"London",
    "sg:classifiers":[
        {
            "category":"Autos & Motor Vehicles",
            "subcategory":"Motorcycle Sales",
            "type":"Retail Goods"
        }
    ],
    "sg:postcode":"E4 7LY",
    "sg:province":"Greater London",
    "sg:tags":[
        "chauffeur",
        "driven",
        "car"
    ],
    "wof:name":"Location Chauffeurs",
    "wof:placetype":"venue"
},
  "geometry": {"coordinates":[0.0065890001,51.5707397461],"type":"Point"}
}