{
  "type": "Feature",
  "properties": {
    "iso:country":"GB",
    "sg:address":"166 Tregwilym Road, Rogerstone",
    "sg:city":"Newport",
    "sg:classifiers":[
        {
            "category":"Organizations",
            "subcategory":"Community Association",
            "type":"Services"
        },
        {
            "category":"Organizations",
            "subcategory":"Membership Organization",
            "type":"Services"
        }
    ],
    "sg:phone":"+44 1633 666662",
    "sg:postcode":"NP10 9EL",
    "sg:province":"Caerphilly",
    "sg:tags":[
        "club",
        "social"
    ],
    "wof:name":"The Redwood Club",
    "wof:placetype":"venue"
},
  "geometry": {"coordinates":[-3.056335,51.586025],"type":"Point"}
}