{
  "type": "Feature",
  "properties": {
    "addr:full":"12 Ladygate Centre, High Street Wickford Essex SS12 9AJ",
    "addr:housenumber":"12",
    "addr:postcode":"ss12 9aj",
    "addr:street":"Ladygate;High Street",
    "iso:country":"GB",
    "sg:address":"12 Ladygate Centre, High Street",
    "sg:city":"Wickford",
    "sg:classifiers":[
        {
            "category":"Shopping",
            "subcategory":"Clothing, Apparel, & Fashions",
            "type":"Retail Goods"
        }
    ],
    "sg:postcode":"SS12 9AJ",
    "sg:province":"Essex",
    "sg:tags":[
        "shop"
    ],
    "wof:name":"Elan",
    "wof:placetype":"venue"
},
  "geometry": {"coordinates":[0.518915,51.611435],"type":"Point"}
}