{
  "type": "Feature",
  "properties": {
    "addr:full":"251 Heathwood Road Cardiff Cardiff CF14 4HS",
    "addr:housenumber":"251",
    "addr:postcode":"cf14 4hs",
    "addr:street":"Heathwood Road",
    "iso:country":"GB",
    "sg:address":"251 Heathwood Road",
    "sg:city":"Cardiff",
    "sg:classifiers":[
        {
            "category":"Personal",
            "subcategory":"Beauty Salon",
            "type":"Services"
        }
    ],
    "sg:phone":"+44 29 2075 5048",
    "sg:postcode":"CF14 4HS",
    "sg:province":"Cardiff",
    "sg:tags":[
        "ladies",
        "lady",
        "hairdresser"
    ],
    "wof:name":"Headmasters",
    "wof:placetype":"venue"
},
  "geometry": {"coordinates":[-3.18237,51.51844],"type":"Point"}
}