{
  "type": "Feature",
  "properties": {
    "addr:full":"57 Longcauseway Bolton Lancashire BL4 9BW",
    "addr:housenumber":"57",
    "addr:postcode":"bl4 9bw",
    "addr:street":"Longcauseway Bolton",
    "iso:country":"GB",
    "sg:address":"57 Longcauseway",
    "sg:city":"Bolton",
    "sg:classifiers":[
        {
            "category":"Shopping",
            "subcategory":"Department Store",
            "type":"Retail Goods"
        }
    ],
    "sg:postcode":"BL4 9BW",
    "sg:province":"Lancashire",
    "wof:name":"Sunnys",
    "wof:placetype":"venue"
},
  "geometry": {"coordinates":[-2.391589,53.544476],"type":"Point"}
}