{
  "type": "Feature",
  "properties": {
    "iso:country":"GB",
    "sg:address":"Moor Road, Ashover",
    "sg:city":"Chesterfield",
    "sg:classifiers":[
        {
            "category":"Social Services",
            "subcategory":"Retirement Home",
            "type":"Services"
        }
    ],
    "sg:phone":"+44 1246 590222",
    "sg:postcode":"S45 0AQ",
    "sg:province":"Derbyshire",
    "sg:tags":[
        "residential",
        "care"
    ],
    "wof:name":"Peak Care Ltd.",
    "wof:placetype":"venue"
},
  "geometry": {"coordinates":[-1.4786779881,53.1653823853],"type":"Point"}
}