{
  "type": "Feature",
  "properties": {
    "addr:full":"142 Albert Road, Farnworth Bolton Lancashire BL4 9HE",
    "addr:housenumber":"142",
    "addr:postcode":"bl4 9he",
    "addr:street":"Albert Road",
    "iso:country":"GB",
    "sg:address":"142 Albert Road, Farnworth",
    "sg:city":"Bolton",
    "sg:classifiers":[
        {
            "category":"Bars & Pubs",
            "type":"Food & Drink"
        }
    ],
    "sg:phone":"+44 1204 574845",
    "sg:postcode":"BL4 9HE",
    "sg:province":"Lancashire",
    "sg:tags":[
        "pubs",
        "inn"
    ],
    "wof:name":"Royal Hotel",
    "wof:placetype":"venue"
},
  "geometry": {"coordinates":[-2.3997271061,53.5456161499],"type":"Point"}
}