{
  "type": "Feature",
  "properties": {
    "addr:full":"25 Commercial Rd Swindon Wiltshire SN1 5NS",
    "addr:housenumber":"25",
    "addr:postcode":"sn1 5ns",
    "addr:street":"Commercial Rd",
    "iso:country":"GB",
    "sg:address":"25 Commercial Rd",
    "sg:city":"Swindon",
    "sg:classifiers":[
        {
            "category":"Real Estate",
            "subcategory":"Real Estate Agent",
            "type":"Services"
        }
    ],
    "sg:phone":"+44 1793 522244",
    "sg:postcode":"SN1 5NS",
    "sg:province":"Wiltshire",
    "wof:name":"New Homes Direct",
    "wof:placetype":"venue"
},
  "geometry": {"coordinates":[-1.784084,51.558655],"type":"Point"}
}