{
  "type": "Feature",
  "properties": {
    "addr:full":"3 White Hart Street Thetford Norfolk IP24 1AB",
    "addr:housenumber":"3",
    "addr:postcode":"ip24 1ab",
    "addr:street":"White Hart Street",
    "iso:country":"GB",
    "sg:address":"3 White Hart Street",
    "sg:city":"Thetford",
    "sg:classifiers":[
        {
            "category":"Insurance",
            "subcategory":"Insurance Agent",
            "type":"Services"
        }
    ],
    "sg:phone":"+44 1842 754282",
    "sg:postcode":"IP24 1AB",
    "sg:province":"Norfolk",
    "wof:name":"Newhouse & General (Thetford) Ltd.",
    "wof:placetype":"venue"
},
  "geometry": {"coordinates":[0.747785,52.415771],"type":"Point"}
}