{
  "type": "Feature",
  "properties": {
    "addr:full":"50 Birch Gro, Kippax Leeds North Yorkshire LS25 7DD",
    "addr:housenumber":"50",
    "addr:postcode":"ls25 7dd",
    "addr:street":"Birch Gro Kippax Leeds",
    "iso:country":"GB",
    "sg:address":"50 Birch Gro, Kippax",
    "sg:city":"Leeds",
    "sg:classifiers":[
        {
            "category":"Food & Beverages",
            "subcategory":"Meat & Fish",
            "type":"Retail Goods"
        }
    ],
    "sg:postcode":"LS25 7DD",
    "sg:province":"North Yorkshire",
    "sg:tags":[
        "butcher"
    ],
    "wof:name":"Singh,F,",
    "wof:placetype":"venue"
},
  "geometry": {"coordinates":[-1.3787269592,53.7749862671],"type":"Point"}
}