{
  "type": "Feature",
  "properties": {
    "addr:full":"2 Upper Riochan Inveraray Argyll and Bute PA32 8UR",
    "addr:housenumber":"2",
    "addr:postcode":"pa32 8ur",
    "addr:street":"Upper Riochan Inveraray",
    "iso:country":"GB",
    "sg:address":"2 Upper Riochan",
    "sg:city":"Inveraray",
    "sg:classifiers":[
        {
            "category":"Building & Trades",
            "subcategory":"Construction",
            "type":"Services"
        }
    ],
    "sg:phone":"+44 1499 302390",
    "sg:postcode":"PA32 8UR",
    "sg:province":"Argyll and Bute",
    "sg:tags":[
        "decorator",
        "painter"
    ],
    "wof:name":"P J Decorators",
    "wof:placetype":"venue"
},
  "geometry": {"coordinates":[-5.0818,56.225487],"type":"Point"}
}