{
  "type": "Feature",
  "properties": {
    "addr:full":"Consett Rd Durham Durham DH7 0RB",
    "addr:postcode":"dh7 0rb",
    "addr:street":"Consett Rd",
    "iso:country":"GB",
    "sg:address":"Consett Rd",
    "sg:city":"Durham",
    "sg:classifiers":[
        {
            "category":"Autos & Motor Vehicles",
            "subcategory":"Fuel & Gas Station",
            "type":"Retail Goods"
        }
    ],
    "sg:phone":"+44 1207 521720",
    "sg:postcode":"DH7 0RB",
    "sg:province":"Durham",
    "sg:tags":[
        "petrol",
        "filling"
    ],
    "wof:name":"Fenhall Service Station",
    "wof:placetype":"venue"
},
  "geometry": {"coordinates":[-1.6898440123,54.7914352417],"type":"Point"}
}