{
  "type": "Feature",
  "properties": {
    "iso:country":"GB",
    "sg:address":"17 Nelson Street",
    "sg:city":"Market Harborough",
    "sg:classifiers":[
        {
            "category":"Fast Food",
            "type":"Food & Drink"
        }
    ],
    "sg:postcode":"LE16 9AX",
    "sg:province":"Leicestershire",
    "sg:tags":[
        "away",
        "meal",
        "outlet",
        "take"
    ],
    "wof:name":"Jaflong",
    "wof:placetype":"venue"
},
  "geometry": {"coordinates":[-0.926047,52.478146],"type":"Point"}
}