{
  "type": "Feature",
  "properties": {
    "iso:country":"GB",
    "sg:address":"60 Flixton Road, Urmston",
    "sg:city":"Manchester",
    "sg:classifiers":[
        {
            "category":"Retail",
            "subcategory":"Funeral Services",
            "type":"Services"
        }
    ],
    "sg:phone":"+44 161 748 2321",
    "sg:postcode":"M41 5AB",
    "sg:province":"Cheshire",
    "wof:name":"Frank Bray",
    "wof:placetype":"venue"
},
  "geometry": {"coordinates":[-2.35661,53.448414],"type":"Point"}
}