{
  "type": "Feature",
  "properties": {
    "addr:full":"42 Princes Street Thurso Highland KW14 7AB",
    "addr:housenumber":"42",
    "addr:postcode":"kw14 7ab",
    "addr:street":"Princes Street",
    "iso:country":"GB",
    "sg:address":"42 Princes Street",
    "sg:city":"Thurso",
    "sg:classifiers":[
        {
            "category":"Personal",
            "subcategory":"Beauty Salon",
            "type":"Services"
        }
    ],
    "sg:phone":"+44 1847 894271",
    "sg:postcode":"KW14 7AB",
    "sg:province":"Highland",
    "sg:tags":[
        "unisex",
        "hairdresser"
    ],
    "wof:name":"Rumours",
    "wof:placetype":"venue"
},
  "geometry": {"coordinates":[-3.521474,58.594761],"type":"Point"}
}