{
  "type": "Feature",
  "properties": {
    "addr:full":"630 Bristol Road South, Northfield Birmingham West Midlands B31 2JR",
    "addr:housenumber":"630",
    "addr:postcode":"b31 2jr",
    "addr:street":"Bristol Road South",
    "iso:country":"GB",
    "sg:address":"630 Bristol Road South, Northfield",
    "sg:city":"Birmingham",
    "sg:classifiers":[
        {
            "category":"Manufacturing",
            "subcategory":"Tools & Machinery",
            "type":"Manufacturing & Wholesale Goods"
        },
        {
            "category":"Home & Garden",
            "subcategory":"Hardware",
            "type":"Retail Goods"
        }
    ],
    "sg:phone":"+44 121 477 5222",
    "sg:postcode":"B31 2JR",
    "sg:province":"West Midlands",
    "sg:tags":[
        "machine",
        "equipment",
        "welding",
        "manufacturer"
    ],
    "wof:name":"The Tool Box",
    "wof:placetype":"venue"
},
  "geometry": {"coordinates":[-1.965487,52.418686],"type":"Point"}
}