{
  "type": "Feature",
  "properties": {
    "iso:country":"GB",
    "sg:address":"Camp Hill, Lower School Dayrell Road",
    "sg:city":"Northampton",
    "sg:classifiers":[
        {
            "category":"Community Center",
            "type":"Public Place"
        }
    ],
    "sg:phone":"+44 1604 766224",
    "sg:postcode":"NN4 9RR",
    "sg:province":"Northamptonshire",
    "sg:tags":[
        "centre"
    ],
    "wof:name":"Camp Hill & Hunsbury Community Centre",
    "wof:placetype":"venue"
},
  "geometry": {"coordinates":[-0.9217399955,52.221408844],"type":"Point"}
}