{
  "type": "Feature",
  "properties": {
    "iso:country":"GB",
    "sg:address":"19 Allandale Road",
    "sg:city":"Leicester",
    "sg:classifiers":[
        {
            "category":"Shopping",
            "subcategory":"Comic Books",
            "type":"Retail Goods"
        }
    ],
    "sg:postcode":"LE2 2DA",
    "sg:province":"Leicestershire",
    "sg:tags":[
        "jeweller"
    ],
    "wof:name":"J R Moate",
    "wof:placetype":"venue"
},
  "geometry": {"coordinates":[-1.1000030041,52.6164588928],"type":"Point"}
}