{
  "type": "Feature",
  "properties": {
    "addr:full":"31 Walmgate York North Yorkshire YO1 9TX",
    "addr:housenumber":"31",
    "addr:postcode":"yo1 9tx",
    "addr:street":"Walmgate York",
    "iso:country":"GB",
    "sg:address":"31 Walmgate",
    "sg:city":"York",
    "sg:classifiers":[
        {
            "category":"Education",
            "subcategory":"Special Training",
            "type":"Public Place"
        }
    ],
    "sg:phone":"+44 1904 624443",
    "sg:postcode":"YO1 9TX",
    "sg:province":"North Yorkshire",
    "sg:tags":[
        "product",
        "centre"
    ],
    "wof:name":"Vt Plus Training Plc",
    "wof:placetype":"venue"
},
  "geometry": {"coordinates":[-1.076455,53.957043],"type":"Point"}
}