{
  "type": "Feature",
  "properties": {
    "addr:full":"Top House Farm, Leicester Road, North Kilworth Lutterworth Leicestershire LE17 6NG",
    "addr:postcode":"le17 6ng",
    "addr:street":"Leicester Road North",
    "iso:country":"GB",
    "sg:address":"Top House Farm, Leicester Road, North Kilworth",
    "sg:city":"Lutterworth",
    "sg:classifiers":[
        {
            "category":"Farming",
            "subcategory":"Livestock Farm",
            "type":"Manufacturing & Wholesale Goods"
        }
    ],
    "sg:phone":"+44 1858 880279",
    "sg:postcode":"LE17 6NG",
    "sg:province":"Leicestershire",
    "sg:tags":[
        "others"
    ],
    "wof:name":"F S E & F H Sherratt",
    "wof:placetype":"venue"
},
  "geometry": {"coordinates":[-1.092334,52.446674],"type":"Point"}
}