{
  "type": "Feature",
  "properties": {
    "iso:country":"GB",
    "sg:address":"Offco House, Town Street, Stanningley",
    "sg:city":"Leeds",
    "sg:classifiers":[
        {
            "category":"Building & Trades",
            "subcategory":"Landscaping Services",
            "type":"Services"
        },
        {
            "category":"Building & Trades",
            "subcategory":"Cleaning & Sanitation",
            "type":"Services"
        }
    ],
    "sg:phone":"+44 113 236 0136",
    "sg:postcode":"LS28 6HQ",
    "sg:province":"West Yorkshire",
    "sg:tags":[
        "industrial",
        "business",
        "removal"
    ],
    "sg:website":"http://www.businessmoves.com",
    "wof:name":"Business Moves Ltd.",
    "wof:placetype":"venue"
},
  "geometry": {"coordinates":[-1.659892,53.807858],"type":"Point"}
}