{
  "type": "Feature",
  "properties": {
    "iso:country":"GB",
    "sg:address":"16 Croham Road",
    "sg:city":"South Croydon",
    "sg:classifiers":[
        {
            "category":"Health Services",
            "subcategory":"Nursing And Care Facility",
            "type":"Services"
        }
    ],
    "sg:phone":"+44 20 8686 8881",
    "sg:postcode":"CR2 7BA",
    "sg:province":"Surrey",
    "sg:tags":[
        "home"
    ],
    "wof:name":"Direct Nursing Agency",
    "wof:placetype":"venue"
},
  "geometry": {"coordinates":[-0.0947569981,51.3621025085],"type":"Point"}
}