{
  "type": "Feature",
  "properties": {
    "iso:country":"GB",
    "sg:address":"Main Road, Llantwit Fadre",
    "sg:city":"Pontypridd",
    "sg:classifiers":[
        {
            "category":"Shopping",
            "subcategory":"Baby Store",
            "type":"Retail Goods"
        }
    ],
    "sg:phone":"+44 1443 204192",
    "sg:postcode":"CF38 2LT",
    "sg:province":"Rhondda, Cynon, Taff",
    "sg:tags":[
        "nursery",
        "accessory"
    ],
    "wof:name":"Nursery Shop",
    "wof:placetype":"venue"
},
  "geometry": {"coordinates":[-3.33087,51.55954],"type":"Point"}
}