{
  "type": "Feature",
  "properties": {
    "addr:full":"537 Stafford Road Wolverhampton Staffordshire WV10 6QE",
    "addr:housenumber":"537",
    "addr:postcode":"wv10 6qe",
    "addr:street":"Stafford Road",
    "iso:country":"GB",
    "sg:address":"537 Stafford Road",
    "sg:city":"Wolverhampton",
    "sg:classifiers":[
        {
            "category":"Building & Trades",
            "subcategory":"Construction",
            "type":"Services"
        }
    ],
    "sg:phone":"+44 1902 788493",
    "sg:postcode":"WV10 6QE",
    "sg:province":"Staffordshire",
    "sg:tags":[
        "flooring"
    ],
    "wof:name":"McManus Flooring",
    "wof:placetype":"venue"
},
  "geometry": {"coordinates":[-2.129007,52.622753],"type":"Point"}
}