{
  "type": "Feature",
  "properties": {
    "addr:full":"Unit 4/9, Lasham Depot Alton Hampshire GU34 5SQ",
    "addr:housenumber":"unit 4 / 9",
    "addr:postcode":"gu34 5sq",
    "iso:country":"GB",
    "sg:address":"Unit 4/9, Lasham Depot",
    "sg:city":"Alton",
    "sg:classifiers":[
        {
            "category":"Professional",
            "type":"Services"
        }
    ],
    "sg:phone":"+44 1256 381507",
    "sg:postcode":"GU34 5SQ",
    "sg:province":"Hampshire",
    "sg:tags":[
        "aircraft",
        "maintenance"
    ],
    "wof:name":"Triumph Aftermarket Services (Europe) Ltd.",
    "wof:placetype":"venue"
},
  "geometry": {"coordinates":[-1.046129,51.117802],"type":"Point"}
}