{
  "type": "Feature",
  "properties": {
    "iso:country":"GB",
    "sg:address":"49 Prossers Terrace, Abercregan",
    "sg:city":"Port Talbot",
    "sg:classifiers":[
        {
            "category":"Government",
            "subcategory":"Post Office",
            "type":"Public Place"
        }
    ],
    "sg:phone":"+44 1639 850241",
    "sg:postcode":"SA13 3LE",
    "sg:province":"Neath Port Talbot",
    "wof:name":"A M James",
    "wof:placetype":"venue"
},
  "geometry": {"coordinates":[-3.6641359329,51.6565856934],"type":"Point"}
}