{
  "type": "Feature",
  "properties": {
    "addr:full":"49 Prossers Terrace, Abercregan Port Talbot Neath Port Talbot SA13 3LE",
    "addr:housenumber":"49",
    "addr:postcode":"sa13 3le",
    "addr:street":"Prossers Terrace Abercregan Port Talbot",
    "iso:country":"GB",
    "sg:address":"49 Prossers Terrace, Abercregan",
    "sg:city":"Port Talbot",
    "sg:classifiers":[
        {
            "category":"Government",
            "subcategory":"Post Office",
            "type":"Public Place"
        }
    ],
    "sg:phone":"+44 1639 850241",
    "sg:postcode":"SA13 3LE",
    "sg:province":"Neath Port Talbot",
    "wof:name":"A M James",
    "wof:placetype":"venue"
},
  "geometry": {"coordinates":[-3.6641359329,51.6565856934],"type":"Point"}
}