{
  "type": "Feature",
  "properties": {
    "addr:full":"Robert Wynd, Woodcross Bilston West Midlands WV14 9SB",
    "addr:postcode":"wv14 9sb",
    "addr:street":"Robert Wynd Woodcross",
    "iso:country":"GB",
    "sg:address":"Robert Wynd, Woodcross",
    "sg:city":"Bilston",
    "sg:classifiers":[
        {
            "category":"Bars & Pubs",
            "type":"Food & Drink"
        }
    ],
    "sg:phone":"+44 1902 659666",
    "sg:postcode":"WV14 9SB",
    "sg:province":"West Midlands",
    "sg:tags":[
        "pubs",
        "inn"
    ],
    "wof:name":"Horse & Jockey",
    "wof:placetype":"venue"
},
  "geometry": {"coordinates":[-2.1016008854,52.5489044189],"type":"Point"}
}