{
  "type": "Feature",
  "properties": {
    "addr:full":"1 Hernden Court, Broom Road Glasgow East Ayrshire G77 5DW",
    "addr:housenumber":"1",
    "addr:postcode":"g77 5dw",
    "addr:street":"Hernden Court Broom Road",
    "iso:country":"GB",
    "sg:address":"1 Hernden Court, Broom Road",
    "sg:city":"Glasgow",
    "sg:classifiers":[
        {
            "category":"Professional",
            "subcategory":"Art Services",
            "type":"Services"
        },
        {
            "category":"Building & Trades",
            "subcategory":"Construction",
            "type":"Services"
        }
    ],
    "sg:phone":"+44 141 639 8967",
    "sg:postcode":"G77 5DW",
    "sg:province":"East Ayrshire",
    "sg:tags":[
        "decorator",
        "painter"
    ],
    "wof:name":"Eastwood Decor",
    "wof:placetype":"venue"
},
  "geometry": {"coordinates":[-4.310404,55.782242],"type":"Point"}
}