{
  "type": "Feature",
  "properties": {
    "iso:country":"GB",
    "sg:address":"1231-5 Bourges Blvd",
    "sg:city":"Peterborough",
    "sg:classifiers":[
        {
            "category":"Retail",
            "subcategory":"Repair Shop",
            "type":"Services"
        }
    ],
    "sg:phone":"+44 1733 553666",
    "sg:postcode":"PE1 2AU",
    "sg:province":"Cambridgeshire",
    "sg:tags":[
        "radio",
        "television",
        "video"
    ],
    "wof:name":"Richard Elmer Television",
    "wof:placetype":"venue"
},
  "geometry": {"coordinates":[-0.255416,52.592037],"type":"Point"}
}