{
  "type": "Feature",
  "properties": {
    "addr:full":"27 Belmont Road Wallington Surrey SM6 8TE",
    "addr:housenumber":"27",
    "addr:postcode":"sm6 8te",
    "addr:street":"Belmont Road",
    "iso:country":"GB",
    "sg:address":"27 Belmont Road",
    "sg:city":"Wallington",
    "sg:classifiers":[
        {
            "category":"Freight",
            "type":"Transportation"
        }
    ],
    "sg:phone":"+44 20 8669 5800",
    "sg:postcode":"SM6 8TE",
    "sg:province":"Surrey",
    "sg:tags":[
        "cargo",
        "handling"
    ],
    "wof:name":"Quay Bulk Services Ltd",
    "wof:placetype":"venue"
},
  "geometry": {"coordinates":[-0.1476520002,51.3623847961],"type":"Point"}
}