{
  "type": "Feature",
  "properties": {
    "addr:full":"Hart Leap Well, Henllys Lane Beaumaris Isle of Anglesey LL58 8HU",
    "addr:postcode":"ll58 8hu",
    "addr:street":"Henllys Lane",
    "iso:country":"GB",
    "sg:address":"Hart Leap Well, Henllys Lane",
    "sg:city":"Beaumaris",
    "sg:classifiers":[
        {
            "category":"Transit Center",
            "subcategory":"Passenger",
            "type":"Transportation"
        }
    ],
    "sg:phone":"+44 1248 811519",
    "sg:postcode":"LL58 8HU",
    "sg:province":"Isle of Anglesey",
    "sg:tags":[
        "boarding",
        "kennel",
        "catteries"
    ],
    "wof:name":"Beaumaris Luxury Cattery",
    "wof:placetype":"venue"
},
  "geometry": {"coordinates":[-4.1010451317,53.2773246765],"type":"Point"}
}