{
  "type": "Feature",
  "properties": {
    "addr:full":"Turret House, 77 Portsmouth Road Guildford Surrey GU2 5BU",
    "addr:housenumber":"77",
    "addr:postcode":"gu2 5bu",
    "addr:street":"Portsmouth Road",
    "iso:country":"GB",
    "sg:address":"Turret House, 77 Portsmouth Road",
    "sg:city":"Guildford",
    "sg:classifiers":[
        {
            "category":"Professional",
            "subcategory":"Employment Agencies",
            "type":"Services"
        }
    ],
    "sg:phone":"+44 1428 653598",
    "sg:postcode":"GU2 5BU",
    "sg:province":"Surrey",
    "sg:tags":[
        "consultant"
    ],
    "wof:name":"Melanie Bishop Associates Ltd.",
    "wof:placetype":"venue"
},
  "geometry": {"coordinates":[-0.5788689852,51.2318229675],"type":"Point"}
}