{
  "type": "Feature",
  "properties": {
    "addr:full":"11 Burton Manor Road Stafford Staffordshire ST17 9QW",
    "addr:housenumber":"11",
    "addr:postcode":"st17 9qw",
    "addr:street":"Burton Manor Road",
    "iso:country":"GB",
    "sg:address":"11 Burton Manor Road",
    "sg:city":"Stafford",
    "sg:classifiers":[
        {
            "category":"Building & Trades",
            "subcategory":"Plumbing",
            "type":"Services"
        }
    ],
    "sg:phone":"+44 1785 257651",
    "sg:postcode":"ST17 9QW",
    "sg:province":"Staffordshire",
    "sg:tags":[
        "heating"
    ],
    "wof:name":"Stafford Gas Installations",
    "wof:placetype":"venue"
},
  "geometry": {"coordinates":[-2.1213560104,52.7887077332],"type":"Point"}
}