{
  "type": "Feature",
  "properties": {
    "addr:full":"246 Stapleton Rd Bristol City of Bristol BS5 0NT",
    "addr:housenumber":"246",
    "addr:postcode":"bs5 0nt",
    "addr:street":"Stapleton Rd",
    "iso:country":"GB",
    "sg:address":"246 Stapleton Rd",
    "sg:city":"Bristol",
    "sg:classifiers":[
        {
            "category":"Military Area",
            "subcategory":"Air Force Base",
            "type":"Public Place"
        }
    ],
    "sg:postcode":"BS5 0NT",
    "sg:province":"City of Bristol",
    "sg:tags":[
        "taxi",
        "hire",
        "private"
    ],
    "wof:name":"Richards,L,",
    "wof:placetype":"venue"
},
  "geometry": {"coordinates":[-2.569535017,51.4656829834],"type":"Point"}
}