{
  "type": "Feature",
  "properties": {
    "iso:country":"GB",
    "sg:address":"Piperdam Golf & Leisure Resort, Fowlis",
    "sg:city":"Dundee",
    "sg:classifiers":[
        {
            "category":"Sports & Exercise",
            "subcategory":"Golf",
            "type":"Entertainment"
        }
    ],
    "sg:phone":"+44 1382 581374",
    "sg:postcode":"DD2 5LP",
    "sg:province":"Dundee City",
    "sg:tags":[
        "club",
        "course"
    ],
    "wof:name":"Piperdam Golf & Leisure Resort Ltd.",
    "wof:placetype":"venue"
},
  "geometry": {"coordinates":[-3.10093,56.48695],"type":"Point"}
}