{
  "type": "Feature",
  "properties": {
    "addr:full":"11 Hide Hill Berwick-upon-tweed Northumberland TD15 1EQ",
    "addr:housenumber":"11",
    "addr:postcode":"td15 1eq",
    "addr:street":"Hide Hill;Northumberland",
    "iso:country":"GB",
    "sg:address":"11 Hide Hill",
    "sg:city":"Berwick-upon-tweed",
    "sg:classifiers":[
        {
            "category":"Shopping",
            "subcategory":"Clothing, Apparel, & Fashions",
            "type":"Retail Goods"
        }
    ],
    "sg:postcode":"TD15 1EQ",
    "sg:province":"Northumberland",
    "sg:tags":[
        "shop"
    ],
    "wof:name":"Clothesline",
    "wof:placetype":"venue"
},
  "geometry": {"coordinates":[-2.002374,55.768925],"type":"Point"}
}