{
  "type": "Feature",
  "properties": {
    "addr:full":"Italy Street Middlesbrough Durham TS2 1DP",
    "addr:postcode":"ts2 1dp",
    "addr:street":"Italy Street",
    "iso:country":"GB",
    "sg:address":"Italy Street",
    "sg:city":"Middlesbrough",
    "sg:classifiers":[
        {
            "category":"Building & Trades",
            "subcategory":"Construction",
            "type":"Services"
        }
    ],
    "sg:phone":"+44 1642 240070",
    "sg:postcode":"TS2 1DP",
    "sg:province":"Durham",
    "sg:tags":[
        "ceiling",
        "contractor"
    ],
    "wof:name":"John Henry & Dennis Hill",
    "wof:placetype":"venue"
},
  "geometry": {"coordinates":[-1.241734,54.580589],"type":"Point"}
}