{
  "type": "Feature",
  "properties": {
    "iso:country":"GB",
    "sg:address":"2-4 Green Lane, Baildon",
    "sg:city":"Shipley",
    "sg:classifiers":[
        {
            "category":"Professional",
            "subcategory":"Detective & Security Services",
            "type":"Services"
        }
    ],
    "sg:phone":"+44 1274 597708",
    "sg:postcode":"BD17 5JS",
    "sg:province":"West Yorkshire",
    "sg:tags":[
        "alarm",
        "burglar",
        "system"
    ],
    "wof:name":"M P Automatic Alarm Systems",
    "wof:placetype":"venue"
},
  "geometry": {"coordinates":[-1.773043,53.838432],"type":"Point"}
}