{
  "type": "Feature",
  "properties": {
    "addr:full":"218-223 Flower Market, New Covent Garden Market London Greater London SW8 5ND",
    "addr:housenumber":"218-223;garden",
    "addr:postcode":"sw8 5nd",
    "addr:street":"Flower;New;Market",
    "iso:country":"GB",
    "sg:address":"218-223 Flower Market, New Covent Garden Market",
    "sg:city":"London",
    "sg:classifiers":[
        {
            "category":"Wholesale",
            "subcategory":"Fruits & Vegetables",
            "type":"Manufacturing & Wholesale Goods"
        },
        {
            "category":"Shopping",
            "subcategory":"Florist",
            "type":"Retail Goods"
        }
    ],
    "sg:phone":"+44 20 7720 6917",
    "sg:postcode":"SW8 5ND",
    "sg:province":"Greater London",
    "wof:name":"J Collingridge Ltd.",
    "wof:placetype":"venue"
},
  "geometry": {"coordinates":[-0.1228,51.511589],"type":"Point"}
}