{
  "type": "Feature",
  "properties": {
    "iso:country":"GB",
    "sg:address":"Mitchells Enterprise Centre, Bradberry Balk Lane, Wombwell",
    "sg:city":"Barnsley",
    "sg:classifiers":[
        {
            "category":"Real Estate",
            "subcategory":"Real Estate Services",
            "type":"Services"
        },
        {
            "category":"Building & Trades",
            "subcategory":"Construction",
            "type":"Services"
        }
    ],
    "sg:phone":"+44 1226 270550",
    "sg:postcode":"S73 8HR",
    "sg:province":"South Yorkshire",
    "sg:tags":[
        "builder"
    ],
    "wof:name":"P W Shaw & Co",
    "wof:placetype":"venue"
},
  "geometry": {"coordinates":[-1.408518,53.531796],"type":"Point"}
}