{
  "type": "Feature",
  "properties": {
    "addr:full":"The Lock Office, Gillender Street London Greater London E3 3JY",
    "addr:postcode":"e3 3jy",
    "addr:street":"Gillender Street",
    "iso:country":"GB",
    "sg:address":"The Lock Office, Gillender Street",
    "sg:city":"London",
    "sg:classifiers":[
        {
            "category":"Professional",
            "subcategory":"Engineering",
            "type":"Services"
        }
    ],
    "sg:phone":"+44 20 7515 3337",
    "sg:postcode":"E3 3JY",
    "sg:province":"Greater London",
    "sg:tags":[
        "consulting",
        "engineer"
    ],
    "wof:name":"Lea Rivers Trust",
    "wof:placetype":"venue"
},
  "geometry": {"coordinates":[-0.00853,51.522511],"type":"Point"}
}