{
  "type": "Feature",
  "properties": {
    "iso:country":"GB",
    "sg:address":"Ellingham Industrial Centre, Ellingham Way",
    "sg:city":"Ashford",
    "sg:classifiers":[
        {
            "category":"Autos & Motor Vehicles",
            "subcategory":"Auto Supplies",
            "type":"Retail Goods"
        }
    ],
    "sg:phone":"+44 1233 640407",
    "sg:postcode":"TN23 6NF",
    "sg:province":"Kent",
    "sg:tags":[
        "component"
    ],
    "wof:name":"G.K. Auto Parts",
    "wof:placetype":"venue"
},
  "geometry": {"coordinates":[0.8760370016,51.1466331482],"type":"Point"}
}