{
  "type": "Feature",
  "properties": {
    "iso:country":"GB",
    "sg:address":"13 Queensway",
    "sg:city":"Stevenage",
    "sg:classifiers":[
        {
            "category":"Professional",
            "subcategory":"Employment Agencies",
            "type":"Services"
        }
    ],
    "sg:phone":"+44 1438 740077",
    "sg:postcode":"SG1 1DA",
    "sg:province":"Hertfordshire",
    "sg:tags":[
        "consultant"
    ],
    "wof:name":"Employment Agency & Consultants",
    "wof:placetype":"venue"
},
  "geometry": {"coordinates":[-0.1982789934,51.8993186951],"type":"Point"}
}