{
  "type": "Feature",
  "properties": {
    "iso:country":"GB",
    "sg:address":"Manor Road, St Helen Auckland",
    "sg:city":"Bishop Auckland",
    "sg:classifiers":[
        {
            "category":"Place Of Worship",
            "type":"Public Place"
        }
    ],
    "sg:phone":"+44 1388 604169",
    "sg:postcode":"DL14 9ER",
    "sg:province":"Durham",
    "wof:name":"St Paulinus R C Church",
    "wof:placetype":"venue"
},
  "geometry": {"coordinates":[-1.758572,54.619362],"type":"Point"}
}