{
  "type": "Feature",
  "properties": {
    "addr:full":"4 Broad Quay Bristol City of Bristol BS1 4DA",
    "addr:housenumber":"4",
    "addr:postcode":"bs1 4da",
    "addr:street":"Broad Quay",
    "iso:country":"GB",
    "sg:address":"4 Broad Quay",
    "sg:city":"Bristol",
    "sg:classifiers":[
        {
            "category":"Bars & Pubs",
            "type":"Food & Drink"
        }
    ],
    "sg:phone":"+44 117 926 4676",
    "sg:postcode":"BS1 4DA",
    "sg:province":"City of Bristol",
    "sg:tags":[
        "pubs",
        "inn"
    ],
    "wof:name":"The Sedan Chair",
    "wof:placetype":"venue"
},
  "geometry": {"coordinates":[-2.5970571041,51.4531974792],"type":"Point"}
}