{
  "type": "Feature",
  "properties": {
    "addr:full":"20 Cliddesden Rd Basingstoke Hampshire RG21 3DT",
    "addr:housenumber":"20",
    "addr:postcode":"rg21 3dt",
    "addr:street":"Cliddesden Rd",
    "iso:country":"GB",
    "sg:address":"20 Cliddesden Rd",
    "sg:city":"Basingstoke",
    "sg:classifiers":[
        {
            "category":"Professional",
            "subcategory":"Management & Consulting",
            "type":"Services"
        }
    ],
    "sg:phone":"+44 1256 353646",
    "sg:postcode":"RG21 3DT",
    "sg:province":"Hampshire",
    "sg:tags":[
        "consultant",
        "business"
    ],
    "wof:name":"The Nicholson Consultancy",
    "wof:placetype":"venue"
},
  "geometry": {"coordinates":[-1.084985,51.258968],"type":"Point"}
}