{
  "type": "Feature",
  "properties": {
    "addr:full":"St Aldate Street Gloucester Gloucestershire GL1 1RP",
    "addr:postcode":"gl1 1rp",
    "addr:street":"Aldate Street",
    "iso:country":"GB",
    "sg:address":"St Aldate Street",
    "sg:city":"Gloucester",
    "sg:classifiers":[
        {
            "category":"Building & Trades",
            "subcategory":"Locksmith",
            "type":"Services"
        }
    ],
    "sg:phone":"+44 1452 502024",
    "sg:postcode":"GL1 1RP",
    "sg:province":"Gloucestershire",
    "sg:tags":[
        "cutting",
        "key"
    ],
    "wof:name":"Clevercloggs",
    "wof:placetype":"venue"
},
  "geometry": {"coordinates":[-2.2434570789,51.8661117554],"type":"Point"}
}