{
  "type": "Feature",
  "properties": {
    "addr:full":"Tower Ho, Fairfax St Bristol City of Bristol BS1 3NN",
    "addr:postcode":"bs1 3nn",
    "addr:street":"Fairfax St",
    "iso:country":"GB",
    "sg:address":"Tower Ho, Fairfax St",
    "sg:city":"Bristol",
    "sg:classifiers":[
        {
            "category":"Organizations",
            "subcategory":"Membership Organization",
            "type":"Services"
        }
    ],
    "sg:phone":"+44 117 926 5703",
    "sg:postcode":"BS1 3NN",
    "sg:province":"City of Bristol",
    "sg:tags":[
        "organisation",
        "consumer"
    ],
    "wof:name":"Office of the Rail Regulator",
    "wof:placetype":"venue"
},
  "geometry": {"coordinates":[-2.591429,51.453667],"type":"Point"}
}