{
  "type": "Feature",
  "properties": {
    "addr:full":"4 Birch Hall Lane Manchester Greater Manchester M13 0XE",
    "addr:housenumber":"4",
    "addr:postcode":"m13 0xe",
    "addr:street":"Birch Hall Lane",
    "iso:country":"GB",
    "sg:address":"4 Birch Hall Lane",
    "sg:city":"Manchester",
    "sg:classifiers":[
        {
            "category":"Health Services",
            "subcategory":"Nursing And Care Facility",
            "type":"Services"
        }
    ],
    "sg:phone":"+44 161 257 2801",
    "sg:postcode":"M13 0XE",
    "sg:province":"Greater Manchester",
    "sg:tags":[
        "home"
    ],
    "wof:name":"Acorn Lodge Care Centre",
    "wof:placetype":"venue"
},
  "geometry": {"coordinates":[-2.2046759129,53.4597053528],"type":"Point"}
}