{
  "type": "Feature",
  "properties": {
    "addr:full":"20 West Street Swadlincote Derbyshire DE11 9DE",
    "addr:housenumber":"20",
    "addr:postcode":"de11 9de",
    "addr:street":"West Street",
    "iso:country":"GB",
    "sg:address":"20 West Street",
    "sg:city":"Swadlincote",
    "sg:classifiers":[
        {
            "category":"Retail",
            "subcategory":"Funeral Services",
            "type":"Services"
        }
    ],
    "sg:phone":"+44 1283 215969",
    "sg:postcode":"DE11 9DE",
    "sg:province":"Derbyshire",
    "sg:tags":[
        "director"
    ],
    "wof:name":"Ward & Brewin Funeral Services",
    "wof:placetype":"venue"
},
  "geometry": {"coordinates":[-1.558128,52.770977],"type":"Point"}
}