{
  "type": "Feature",
  "properties": {
    "addr:full":"333 Nitshill Road Glasgow East Renfrewshire G53 7BL",
    "addr:housenumber":"333",
    "addr:postcode":"g53 7bl",
    "addr:street":"Nitshill Road",
    "iso:country":"GB",
    "sg:address":"333 Nitshill Road",
    "sg:city":"Glasgow",
    "sg:classifiers":[
        {
            "category":"Personal",
            "subcategory":"Beauty Salon",
            "type":"Services"
        },
        {
            "category":"Personal",
            "subcategory":"Barber",
            "type":"Services"
        }
    ],
    "sg:phone":"+44 141 881 1297",
    "sg:postcode":"G53 7BL",
    "sg:province":"East Renfrewshire",
    "sg:tags":[
        "unisex",
        "hairdresser"
    ],
    "wof:name":"Hair Gossip",
    "wof:placetype":"venue"
},
  "geometry": {"coordinates":[-4.360461235,55.814365387],"type":"Point"}
}