{
  "type": "Feature",
  "properties": {
    "iso:country":"GB",
    "sg:address":"206 Shipton Rd",
    "sg:city":"York",
    "sg:classifiers":[
        {
            "category":"Manufacturing",
            "subcategory":"Building Materials",
            "type":"Manufacturing & Wholesale Goods"
        }
    ],
    "sg:postcode":"YO30 5RZ",
    "sg:province":"North Yorkshire",
    "sg:tags":[
        "stonemason"
    ],
    "wof:name":"Ficco,Wayne,",
    "wof:placetype":"venue"
},
  "geometry": {"coordinates":[-1.1181819439,53.983959198],"type":"Point"}
}