{
  "type": "Feature",
  "properties": {
    "iso:country":"GB",
    "sg:address":"89 Church Street",
    "sg:city":"Whitby",
    "sg:classifiers":[
        {
            "category":"Food & Beverages",
            "subcategory":"Meat & Fish",
            "type":"Retail Goods"
        }
    ],
    "sg:phone":"+44 1947 621525",
    "sg:postcode":"YO22 4BH",
    "sg:province":"North Yorkshire",
    "sg:tags":[
        "butcher"
    ],
    "wof:name":"Johnson of Whitby",
    "wof:placetype":"venue"
},
  "geometry": {"coordinates":[-0.6115469933,54.4874305725],"type":"Point"}
}