{
  "type": "Feature",
  "properties": {
    "iso:country":"GB",
    "sg:address":"White House Farm, Flixton",
    "sg:city":"Lowestoft",
    "sg:classifiers":[
        {
            "category":"Farming",
            "subcategory":"Farm",
            "type":"Manufacturing & Wholesale Goods"
        }
    ],
    "sg:postcode":"NR32 5PG",
    "sg:province":"Suffolk",
    "sg:tags":[
        "mixed",
        "crop"
    ],
    "wof:name":"D B G & E A Hume",
    "wof:placetype":"venue"
},
  "geometry": {"coordinates":[1.701617,52.505287],"type":"Point"}
}