{
  "type": "Feature",
  "properties": {
    "addr:full":"Caravan Park, Llanmadoc Swansea Swansea SA3 1DE",
    "addr:postcode":"sa3 1de",
    "iso:country":"GB",
    "sg:address":"Caravan Park, Llanmadoc",
    "sg:city":"Swansea",
    "sg:classifiers":[
        {
            "category":"Recreation",
            "subcategory":"Campground",
            "type":"Entertainment"
        }
    ],
    "sg:postcode":"SA3 1DE",
    "sg:province":"Swansea",
    "sg:tags":[
        "caravan",
        "park"
    ],
    "wof:name":"Whiteford Bay Leisure Park",
    "wof:placetype":"venue"
},
  "geometry": {"coordinates":[-4.261107,51.618435],"type":"Point"}
}