{
  "type": "Feature",
  "properties": {
    "addr:full":"333 Shirland Rd London Greater London W9 3JJ",
    "addr:housenumber":"333",
    "addr:postcode":"w9 3jj",
    "addr:street":"Shirland Rd",
    "iso:country":"GB",
    "sg:address":"333 Shirland Rd",
    "sg:city":"London",
    "sg:classifiers":[
        {
            "category":"Shopping",
            "subcategory":"Department Store",
            "type":"Retail Goods"
        }
    ],
    "sg:postcode":"W9 3JJ",
    "sg:province":"Greater London",
    "wof:name":"Hybrid Music Ltd",
    "wof:placetype":"venue"
},
  "geometry": {"coordinates":[-0.204055,51.52919],"type":"Point"}
}