{
  "type": "Feature",
  "properties": {
    "iso:country":"GB",
    "sg:address":"1 Amanda Rd, Rainhill",
    "sg:city":"Prescot",
    "sg:classifiers":[
        {
            "category":"Retail",
            "subcategory":"Storage",
            "type":"Services"
        }
    ],
    "sg:phone":"+44 151 426 3654",
    "sg:postcode":"L35 8PN",
    "sg:province":"Cheshire",
    "sg:tags":[
        "household",
        "removal"
    ],
    "wof:name":"Geo Hamilton & Son",
    "wof:placetype":"venue"
},
  "geometry": {"coordinates":[-2.7755050659,53.4231948853],"type":"Point"}
}