{
  "type": "Feature",
  "properties": {
    "addr:full":"Charter Place, Vine Street Uxbridge Buckinghamshire UB8 1EY",
    "addr:postcode":"ub8 1ey",
    "addr:street":"Charter Place Vine Street",
    "iso:country":"GB",
    "sg:address":"Charter Place, Vine Street",
    "sg:city":"Uxbridge",
    "sg:classifiers":[
        {
            "category":"Banks & Credit Unions",
            "subcategory":"Financial Services",
            "type":"Services"
        }
    ],
    "sg:phone":"+44 1895 208600",
    "sg:postcode":"UB8 1EY",
    "sg:province":"Buckinghamshire",
    "sg:tags":[
        "consultant"
    ],
    "wof:name":"R F S Ltd.",
    "wof:placetype":"venue"
},
  "geometry": {"coordinates":[-0.4788140059,51.5452651978],"type":"Point"}
}