{
  "type": "Feature",
  "properties": {
    "addr:full":"2 Winton Road Petersfield Hampshire GU32 3LL",
    "addr:housenumber":"2",
    "addr:postcode":"gu32 3ll",
    "addr:street":"Winton Road",
    "iso:country":"GB",
    "sg:address":"2 Winton Road",
    "sg:city":"Petersfield",
    "sg:classifiers":[
        {
            "category":"Professional",
            "subcategory":"Management & Consulting",
            "type":"Services"
        }
    ],
    "sg:phone":"+44 1730 266666",
    "sg:postcode":"GU32 3LL",
    "sg:province":"Hampshire",
    "sg:tags":[
        "consultant",
        "business"
    ],
    "wof:name":"FLEET AUDITS LTD",
    "wof:placetype":"venue"
},
  "geometry": {"coordinates":[-0.936654,51.006813],"type":"Point"}
}