{
  "type": "Feature",
  "properties": {
    "iso:country":"GB",
    "sg:address":"11 Beechbank Drive, Thorpe End",
    "sg:city":"Norwich",
    "sg:classifiers":[
        {
            "category":"Real Estate",
            "subcategory":"Architect",
            "type":"Services"
        }
    ],
    "sg:postcode":"NR13 5BW",
    "sg:province":"Norfolk",
    "sg:tags":[
        "technologist",
        "architectural"
    ],
    "wof:name":"Robert J Bilbie",
    "wof:placetype":"venue"
},
  "geometry": {"coordinates":[1.367728,52.650356],"type":"Point"}
}