{
  "type": "Feature",
  "properties": {
    "addr:full":"West Cliff Hotel, 1 West Cliff Road Bournemouth Dorset BH2 5ES",
    "addr:housenumber":"1",
    "addr:postcode":"bh2 5es",
    "addr:street":"West;West Cliff Road",
    "iso:country":"GB",
    "sg:address":"West Cliff Hotel, 1 West Cliff Road",
    "sg:city":"Bournemouth",
    "sg:classifiers":[
        {
            "category":"Travel",
            "subcategory":"Hotels & Motels",
            "type":"Entertainment"
        },
        {
            "category":"Building & Trades",
            "subcategory":"Construction",
            "type":"Services"
        }
    ],
    "sg:phone":"+44 1202 557349",
    "sg:postcode":"BH2 5ES",
    "sg:province":"Dorset",
    "sg:tags":[
        "dry",
        "lining",
        "plasterers",
        "screeders"
    ],
    "wof:name":"Warwick Plastering",
    "wof:placetype":"venue"
},
  "geometry": {"coordinates":[-1.880916,50.720406],"type":"Point"}
}