{
  "type": "Feature",
  "properties": {
    "iso:country":"GB",
    "sg:address":"19 Bishops Court, Kennoway",
    "sg:city":"Leven",
    "sg:classifiers":[
        {
            "category":"Shopping",
            "subcategory":"Pharmacy",
            "type":"Retail Goods"
        }
    ],
    "sg:phone":"+44 1333 350327",
    "sg:postcode":"KY8 5LA",
    "sg:province":"Fife",
    "sg:tags":[
        "pharmacist",
        "chemist"
    ],
    "wof:name":"Lloyds Chemist",
    "wof:placetype":"venue"
},
  "geometry": {"coordinates":[-3.047541,56.209965],"type":"Point"}
}