{
  "type": "Feature",
  "properties": {
    "addr:full":"Unit B, Mapplewell Business Park, Blacker Road Barnsley South Yorkshire S75 6BS",
    "addr:postcode":"s75 6bs",
    "addr:street":"Business Park Blacker Road;Yorkshire",
    "iso:country":"GB",
    "sg:address":"Unit B, Mapplewell Business Park, Blacker Road",
    "sg:city":"Barnsley",
    "sg:classifiers":[
        {
            "category":"Autos & Motor Vehicles",
            "subcategory":"Auto Supplies",
            "type":"Retail Goods"
        }
    ],
    "sg:phone":"+44 1226 380091",
    "sg:postcode":"S75 6BS",
    "sg:province":"South Yorkshire",
    "sg:tags":[
        "towing",
        "eqpt",
        "trailer"
    ],
    "wof:name":"S W Trailer Hire",
    "wof:placetype":"venue"
},
  "geometry": {"coordinates":[-1.50078,53.58606],"type":"Point"}
}