{
  "type": "Feature",
  "properties": {
    "iso:country":"GB",
    "sg:address":"5 Reform St",
    "sg:city":"Hull",
    "sg:classifiers":[
        {
            "category":"Professional",
            "subcategory":"Art Services",
            "type":"Services"
        }
    ],
    "sg:phone":"+44 1482 321154",
    "sg:postcode":"HU2 8EF",
    "sg:province":"East Riding of Yorkshire",
    "sg:tags":[
        "decorating",
        "painting"
    ],
    "wof:name":"Industrial Paint Suppliers Ltd",
    "wof:placetype":"venue"
},
  "geometry": {"coordinates":[-0.34009,53.749786],"type":"Point"}
}