{
  "type": "Feature",
  "properties": {
    "addr:full":"Westward Drive, Pill Bristol Somerset BS20 0JP",
    "addr:postcode":"bs20 0jp",
    "addr:street":"Westward Drive",
    "iso:country":"GB",
    "sg:address":"Westward Drive, Pill",
    "sg:city":"Bristol",
    "sg:classifiers":[
        {
            "category":"Education",
            "subcategory":"School",
            "type":"Public Place"
        },
        {
            "category":"Government",
            "subcategory":"Office",
            "type":"Public Place"
        }
    ],
    "sg:postcode":"BS20 0JP",
    "sg:province":"Somerset",
    "sg:tags":[
        "local",
        "authority"
    ],
    "wof:name":"Crockerne Pill Controlled Infant School",
    "wof:placetype":"venue"
},
  "geometry": {"coordinates":[-2.6901640892,51.4801445007],"type":"Point"}
}