{
  "type": "Feature",
  "properties": {
    "addr:full":"6 Redwood Crescent, East Kilbride Glasgow South Lanarkshire G74 5PA",
    "addr:housenumber":"6",
    "addr:postcode":"g74 5pa",
    "addr:street":"Redwood Crescent",
    "iso:country":"GB",
    "sg:address":"6 Redwood Crescent, East Kilbride",
    "sg:city":"Glasgow",
    "sg:classifiers":[
        {
            "category":"Utilities",
            "subcategory":"Fuel Oil & Lpg",
            "type":"Services"
        },
        {
            "category":"Professional",
            "subcategory":"Printing & Photocopies",
            "type":"Services"
        }
    ],
    "sg:phone":"+44 1355 840021",
    "sg:postcode":"G74 5PA",
    "sg:province":"South Lanarkshire",
    "sg:tags":[
        "stamping",
        "imprinting",
        "tag",
        "label",
        "equipment",
        "computer",
        "labelling"
    ],
    "wof:name":"Precision Identification Ltd",
    "wof:placetype":"venue"
},
  "geometry": {"coordinates":[-4.2293839455,55.7654380798],"type":"Point"}
}