{
  "type": "Feature",
  "properties": {
    "addr:full":"81 Birch Gro, Llanmartin Newport Monmouthshire NP18 2JB",
    "addr:housenumber":"81",
    "addr:postcode":"np18 2jb",
    "addr:street":"Birch Gro Llanmartin",
    "iso:country":"GB",
    "sg:address":"81 Birch Gro, Llanmartin",
    "sg:city":"Newport",
    "sg:classifiers":[
        {
            "category":"Health Services",
            "subcategory":"Doctor",
            "type":"Services"
        },
        {
            "category":"Health Services",
            "subcategory":"Clinic",
            "type":"Services"
        }
    ],
    "sg:phone":"+44 1633 413258",
    "sg:postcode":"NP18 2JB",
    "sg:province":"Monmouthshire",
    "sg:tags":[
        "nh",
        "practitioners"
    ],
    "wof:name":"Gwent Healthcare N H S Trust",
    "wof:placetype":"venue"
},
  "geometry": {"coordinates":[-2.887609,51.59845],"type":"Point"}
}