{
  "type": "Feature",
  "properties": {
    "iso:country":"GB",
    "sg:address":"31 New Road",
    "sg:city":"Kidderminster",
    "sg:classifiers":[
        {
            "category":"Bars & Pubs",
            "type":"Food & Drink"
        },
        {
            "category":"Community Center",
            "subcategory":"Social",
            "type":"Public Place"
        }
    ],
    "sg:phone":"+44 1562 753006",
    "sg:postcode":"DY10 1AF",
    "sg:province":"Staffordshire",
    "sg:tags":[
        "pubs",
        "house",
        "inn",
        "activity"
    ],
    "wof:name":"The Royal Exchange",
    "wof:placetype":"venue"
},
  "geometry": {"coordinates":[-2.2481400967,52.3839836121],"type":"Point"}
}