{
  "type": "Feature",
  "properties": {
    "iso:country":"GB",
    "sg:address":"170 Woodthorpe Road",
    "sg:city":"Birmingham",
    "sg:classifiers":[
        {
            "category":"Food & Beverages",
            "subcategory":"Liquor & Beverages",
            "type":"Retail Goods"
        }
    ],
    "sg:postcode":"B14 6EQ",
    "sg:province":"West Midlands",
    "sg:tags":[
        "beer",
        "spirit",
        "wines"
    ],
    "wof:name":"Woodthorpe Wine Store",
    "wof:placetype":"venue"
},
  "geometry": {"coordinates":[-1.900371,52.419209],"type":"Point"}
}