{
  "type": "Feature",
  "properties": {
    "iso:country":"GB",
    "sg:address":"Sha-karn Hepley View, Barnsley Road Flockton",
    "sg:city":"Wakefield",
    "sg:classifiers":[
        {
            "category":"Building & Trades",
            "subcategory":"Construction",
            "type":"Services"
        }
    ],
    "sg:phone":"+44 1924 848672",
    "sg:postcode":"WF4 4ES",
    "sg:province":"West Yorkshire",
    "sg:tags":[
        "builder"
    ],
    "wof:name":"Blakeley B (Highfield Builders)",
    "wof:placetype":"venue"
},
  "geometry": {"coordinates":[-1.635486,53.630836],"type":"Point"}
}