{
  "type": "Feature",
  "properties": {
    "iso:country":"GB",
    "sg:address":"Norman House, Great North Road, Norman Cross",
    "sg:city":"Peterborough",
    "sg:classifiers":[
        {
            "category":"Personal",
            "type":"Services"
        }
    ],
    "sg:postcode":"PE7 3TB",
    "sg:province":"Cambridgeshire",
    "sg:tags":[
        "wedding"
    ],
    "wof:name":"Chariots of Hire",
    "wof:placetype":"venue"
},
  "geometry": {"coordinates":[-0.337559998,52.550617218],"type":"Point"}
}