{
  "type": "Feature",
  "properties": {
    "addr:full":"Unit 85 Hartlebury Trading Est Kidderminster Staffordshire DY10 4JB",
    "addr:housenumber":"unit 85 hartlebury",
    "addr:postcode":"dy10 4jb",
    "iso:country":"GB",
    "sg:address":"Unit 85 Hartlebury Trading Est",
    "sg:city":"Kidderminster",
    "sg:classifiers":[
        {
            "category":"Real Estate",
            "subcategory":"Architect",
            "type":"Services"
        }
    ],
    "sg:phone":"+44 1299 250144",
    "sg:postcode":"DY10 4JB",
    "sg:province":"Staffordshire",
    "sg:tags":[
        "kilt",
        "accessory"
    ],
    "wof:name":"Glenfirth Highland Products",
    "wof:placetype":"venue"
},
  "geometry": {"coordinates":[-2.211575985,52.3237495422],"type":"Point"}
}