{
  "type": "Feature",
  "properties": {
    "addr:full":"Unit 35 Vale Business Park Cowbridge The Vale of Glamorgan CF71 7PF",
    "addr:housenumber":"unit 35",
    "addr:postcode":"cf71 7pf",
    "addr:street":"Vale Business Park;Vale",
    "iso:country":"GB",
    "sg:address":"Unit 35 Vale Business Park",
    "sg:city":"Cowbridge",
    "sg:classifiers":[
        {
            "category":"Manufacturing",
            "subcategory":"Metals",
            "type":"Manufacturing & Wholesale Goods"
        }
    ],
    "sg:postcode":"CF71 7PF",
    "sg:province":"The Vale of Glamorgan",
    "sg:tags":[
        "steel",
        "fabricator",
        "erectors"
    ],
    "wof:name":"Ledley Engineering Ltd.",
    "wof:placetype":"venue"
},
  "geometry": {"coordinates":[-3.4991500378,51.4403686523],"type":"Point"}
}