{
  "type": "Feature",
  "properties": {
    "iso:country":"GB",
    "sg:address":"Ashlands (private Rd), Burgh, Aylsham",
    "sg:city":"Norwich",
    "sg:classifiers":[
        {
            "category":"Home & Garden",
            "subcategory":"Furniture",
            "type":"Retail Goods"
        }
    ],
    "sg:phone":"+44 1603 279162",
    "sg:postcode":"NR11 6TN",
    "sg:province":"Norfolk",
    "wof:name":"Mill Joinery Services",
    "wof:placetype":"venue"
},
  "geometry": {"coordinates":[1.250354,52.795067],"type":"Point"}
}