{
  "type": "Feature",
  "properties": {
    "addr:full":"1 Riverside Dr Aberdeen Aberdeen City AB11 7LH",
    "addr:housenumber":"1",
    "addr:postcode":"ab11 7lh",
    "addr:street":"Riverside Dr",
    "iso:country":"GB",
    "sg:address":"1 Riverside Dr",
    "sg:city":"Aberdeen",
    "sg:classifiers":[
        {
            "category":"Professional",
            "subcategory":"Computer Services",
            "type":"Services"
        }
    ],
    "sg:phone":"+44 1224 213478",
    "sg:postcode":"AB11 7LH",
    "sg:province":"Aberdeen City",
    "sg:tags":[
        "system",
        "software"
    ],
    "wof:name":"Oryx North East Ltd",
    "wof:placetype":"venue"
},
  "geometry": {"coordinates":[-2.096539,57.135567],"type":"Point"}
}