{
  "type": "Feature",
  "properties": {
    "addr:full":"40 Queensway Enfield Greater London EN3 4SA",
    "addr:housenumber":"40",
    "addr:postcode":"en3 4sa",
    "addr:street":"Queensway",
    "iso:country":"GB",
    "sg:address":"40 Queensway",
    "sg:city":"Enfield",
    "sg:classifiers":[
        {
            "category":"Government",
            "subcategory":"Fire Station",
            "type":"Public Place"
        }
    ],
    "sg:phone":"+44 20 8443 1123",
    "sg:postcode":"EN3 4SA",
    "sg:province":"Greater London",
    "sg:tags":[
        "security"
    ],
    "wof:name":"Enfield Extinguishers",
    "wof:placetype":"venue"
},
  "geometry": {"coordinates":[-0.0496650003,51.6466674805],"type":"Point"}
}