{
  "type": "Feature",
  "properties": {
    "addr:full":"Academy House London Greater London NW1 7DT",
    "addr:postcode":"nw1 7dt",
    "iso:country":"GB",
    "sg:address":"Academy House",
    "sg:city":"London",
    "sg:classifiers":[
        {
            "category":"Communications",
            "subcategory":"Newspaper",
            "type":"Services"
        }
    ],
    "sg:phone":"+44 20 7241 8000",
    "sg:postcode":"NW1 7DT",
    "sg:province":"Greater London",
    "sg:tags":[
        "magazine"
    ],
    "wof:name":"H Bauer Publishing Ltd.",
    "wof:placetype":"venue"
},
  "geometry": {"coordinates":[-0.0879139975,51.5073699951],"type":"Point"}
}