{
  "type": "Feature",
  "properties": {
    "addr:full":"77 Palmerston Rd London Greater London E17 6PZ",
    "addr:housenumber":"77",
    "addr:postcode":"e17 6pz",
    "addr:street":"Palmerston Rd",
    "iso:country":"GB",
    "sg:address":"77 Palmerston Rd",
    "sg:city":"London",
    "sg:classifiers":[
        {
            "category":"Personal",
            "subcategory":"Barber",
            "type":"Services"
        }
    ],
    "sg:postcode":"E17 6PZ",
    "sg:province":"Greater London",
    "sg:tags":[
        "men's",
        "hairdresser"
    ],
    "wof:name":"Akthar,Ghanei,",
    "wof:placetype":"venue"
},
  "geometry": {"coordinates":[-0.030222,51.587826],"type":"Point"}
}