{
  "type": "Feature",
  "properties": {
    "addr:full":"The Willows, Tydd St. Mary Wisbech Cambridgeshire PE13 5QX",
    "addr:postcode":"pe13 5qx",
    "iso:country":"GB",
    "sg:address":"The Willows, Tydd St. Mary",
    "sg:city":"Wisbech",
    "sg:classifiers":[
        {
            "category":"Autos & Motor Vehicles",
            "subcategory":"Automobile Sales",
            "type":"Retail Goods"
        },
        {
            "category":"Retail",
            "subcategory":"Car Wash",
            "type":"Services"
        }
    ],
    "sg:phone":"+44 1945 420313",
    "sg:postcode":"PE13 5QX",
    "sg:province":"Cambridgeshire",
    "sg:tags":[
        "transportation"
    ],
    "wof:name":"Hunters",
    "wof:placetype":"venue"
},
  "geometry": {"coordinates":[0.157228,52.669689],"type":"Point"}
}