{
  "type": "Feature",
  "properties": {
    "iso:country":"GB",
    "sg:address":"Norwich Road, Lenwade",
    "sg:city":"Norwich",
    "sg:classifiers":[
        {
            "category":"Freight",
            "type":"Transportation"
        }
    ],
    "sg:phone":"+44 1603 871366",
    "sg:postcode":"NR9 5SH",
    "sg:province":"Norfolk",
    "sg:tags":[
        "haulage",
        "road"
    ],
    "wof:name":"Advance Heavy Haulage Ltd.",
    "wof:placetype":"venue"
},
  "geometry": {"coordinates":[1.114235,52.645939],"type":"Point"}
}