{
  "type": "Feature",
  "properties": {
    "iso:country":"GB",
    "sg:address":"Vincents Yard, 65a Susans Road",
    "sg:city":"Eastbourne",
    "sg:classifiers":[
        {
            "category":"Professional",
            "subcategory":"Printing & Photocopies",
            "type":"Services"
        }
    ],
    "sg:phone":"+44 1323 725778",
    "sg:postcode":"BN21 3TG",
    "sg:province":"East Sussex",
    "sg:tags":[
        "printer"
    ],
    "wof:name":"Russell Enterprises",
    "wof:placetype":"venue"
},
  "geometry": {"coordinates":[0.2853499949,50.766910553],"type":"Point"}
}