{
  "type": "Feature",
  "properties": {
    "iso:country":"GB",
    "sg:address":"Back Lane, Bomere Heath",
    "sg:city":"Shrewsbury",
    "sg:classifiers":[
        {
            "category":"Building & Trades",
            "subcategory":"Construction",
            "type":"Services"
        }
    ],
    "sg:phone":"+44 1939 290450",
    "sg:postcode":"SY4 3PL",
    "sg:province":"Shropshire",
    "sg:tags":[
        "builder"
    ],
    "wof:name":"David T Roberts",
    "wof:placetype":"venue"
},
  "geometry": {"coordinates":[-2.782755,52.772366],"type":"Point"}
}