{
  "type": "Feature",
  "properties": {
    "addr:full":"35 Church Road, Lower Parkstone Poole Dorset BH14 8UF",
    "addr:housenumber":"35",
    "addr:postcode":"bh14 8uf",
    "addr:street":"Church Road Lower",
    "iso:country":"GB",
    "sg:address":"35 Church Road, Lower Parkstone",
    "sg:city":"Poole",
    "sg:classifiers":[
        {
            "category":"Shopping",
            "subcategory":"Thrift Store",
            "type":"Retail Goods"
        },
        {
            "category":"Banks & Credit Unions",
            "subcategory":"Financial Services",
            "type":"Services"
        }
    ],
    "sg:phone":"+44 1202 742934",
    "sg:postcode":"BH14 8UF",
    "sg:province":"Dorset",
    "sg:tags":[
        "shop",
        "consultant",
        "charity"
    ],
    "wof:name":"S S A F A Forces Help",
    "wof:placetype":"venue"
},
  "geometry": {"coordinates":[-1.949948,50.724361],"type":"Point"}
}