{
  "type": "Feature",
  "properties": {
    "addr:full":"Howe Lane Verwood Dorset BH31 6JF",
    "addr:postcode":"bh31 6jf",
    "addr:street":"Howe Lane",
    "iso:country":"GB",
    "sg:address":"Howe Lane",
    "sg:city":"Verwood",
    "sg:classifiers":[
        {
            "category":"Education",
            "subcategory":"School",
            "type":"Public Place"
        }
    ],
    "sg:phone":"+44 1202 822652",
    "sg:postcode":"BH31 6JF",
    "sg:province":"Dorset",
    "sg:tags":[
        "local",
        "authority"
    ],
    "wof:name":"Verwood C of E First School",
    "wof:placetype":"venue"
},
  "geometry": {"coordinates":[-1.880185008,50.8718948364],"type":"Point"}
}