{
  "type": "Feature",
  "properties": {
    "addr:full":"121 Cotmandene Cres, St Pauls Cray Orpington Kent BR5 2RB",
    "addr:housenumber":"121",
    "addr:postcode":"br5 2rb",
    "addr:street":"Cotmandene Cres St;Orpington",
    "iso:country":"GB",
    "sg:address":"121 Cotmandene Cres, St Pauls Cray",
    "sg:city":"Orpington",
    "sg:classifiers":[
        {
            "category":"Government",
            "subcategory":"Customs House",
            "type":"Public Place"
        }
    ],
    "sg:postcode":"BR5 2RB",
    "sg:province":"Kent",
    "sg:tags":[
        "clearance"
    ],
    "wof:name":"Past & Present Furniture",
    "wof:placetype":"venue"
},
  "geometry": {"coordinates":[0.1066719964,51.4033203125],"type":"Point"}
}