{
  "type": "Feature",
  "properties": {
    "addr:full":"Suite 309, Oxford House Reading Berkshire RG1 7AA",
    "addr:housenumber":"suite 309 oxford",
    "addr:postcode":"rg1 7aa",
    "iso:country":"GB",
    "sg:address":"Suite 309, Oxford House",
    "sg:city":"Reading",
    "sg:classifiers":[
        {
            "category":"Building & Trades",
            "subcategory":"Cleaning & Sanitation",
            "type":"Services"
        }
    ],
    "sg:phone":"+44 118 950 9079",
    "sg:postcode":"RG1 7AA",
    "sg:province":"Berkshire",
    "sg:tags":[
        "cleaner",
        "window"
    ],
    "wof:name":"C.R.C",
    "wof:placetype":"venue"
},
  "geometry": {"coordinates":[-0.9895840287,51.4557342529],"type":"Point"}
}