{
  "type": "Feature",
  "properties": {
    "addr:full":"11 Croftfield Crescent, Newton Swansea Swansea SA3 4UL",
    "addr:housenumber":"11",
    "addr:postcode":"sa3 4ul",
    "addr:street":"Croftfield Crescent",
    "iso:country":"GB",
    "sg:address":"11 Croftfield Crescent, Newton",
    "sg:city":"Swansea",
    "sg:classifiers":[
        {
            "category":"Retail",
            "subcategory":"Driving School",
            "type":"Services"
        }
    ],
    "sg:postcode":"SA3 4UL",
    "sg:province":"Swansea",
    "wof:name":"Intercounty Driving School",
    "wof:placetype":"venue"
},
  "geometry": {"coordinates":[-4.017228,51.574066],"type":"Point"}
}