{
  "type": "Feature",
  "properties": {
    "addr:full":"2a Billingham Rd, Norton Stockton On Tees Durham TS20 2RZ",
    "addr:housenumber":"2a",
    "addr:postcode":"ts20 2rz",
    "addr:street":"Billingham Rd;On",
    "iso:country":"GB",
    "sg:address":"2a Billingham Rd, Norton",
    "sg:city":"Stockton On Tees",
    "sg:classifiers":[
        {
            "category":"Personal",
            "type":"Services"
        }
    ],
    "sg:phone":"+44 1325 381324",
    "sg:postcode":"TS20 2RZ",
    "sg:province":"Durham",
    "sg:tags":[
        "stress",
        "management"
    ],
    "wof:name":"Gill Naisby B.A.C.Acc.",
    "wof:placetype":"venue"
},
  "geometry": {"coordinates":[-1.30881,54.58754],"type":"Point"}
}