{
  "type": "Feature",
  "properties": {
    "addr:full":"Lexington Ho Bromyard Herefordshire HR7 4PA",
    "addr:postcode":"hr7 4pa",
    "iso:country":"GB",
    "sg:address":"Lexington Ho",
    "sg:city":"Bromyard",
    "sg:classifiers":[
        {
            "category":"Health Services",
            "subcategory":"Clinic",
            "type":"Services"
        }
    ],
    "sg:phone":"+44 1885 483919",
    "sg:postcode":"HR7 4PA",
    "sg:province":"Herefordshire",
    "sg:tags":[
        "injury",
        "sport"
    ],
    "wof:name":"Catherine Williams",
    "wof:placetype":"venue"
},
  "geometry": {"coordinates":[-2.5103991032,52.1890983582],"type":"Point"}
}