{
  "type": "Feature",
  "properties": {
    "addr:full":"172 High Street Crowthorne Berkshire RG45 7AP",
    "addr:housenumber":"172",
    "addr:postcode":"rg45 7ap",
    "addr:street":"High Street",
    "iso:country":"GB",
    "sg:address":"172 High Street",
    "sg:city":"Crowthorne",
    "sg:classifiers":[
        {
            "category":"Home & Garden",
            "subcategory":"Household Appliances",
            "type":"Retail Goods"
        },
        {
            "category":"Communications",
            "type":"Services"
        }
    ],
    "sg:phone":"+44 1344 772056",
    "sg:postcode":"RG45 7AP",
    "sg:province":"Berkshire",
    "sg:tags":[
        "tv",
        "video",
        "electrical",
        "domestic",
        "radio"
    ],
    "wof:name":"C T Bell (Crowthorne) Ltd.",
    "wof:placetype":"venue"
},
  "geometry": {"coordinates":[-0.794204,51.367565],"type":"Point"}
}