{
  "type": "Feature",
  "properties": {
    "iso:country":"GB",
    "sg:address":"54 Western Road",
    "sg:city":"Tring",
    "sg:classifiers":[
        {
            "category":"Home & Garden",
            "subcategory":"Home Furnishings",
            "type":"Retail Goods"
        }
    ],
    "sg:phone":"+44 1442 890808",
    "sg:postcode":"HP23 4BB",
    "sg:province":"Buckinghamshire",
    "sg:tags":[
        "furnishers",
        "planner",
        "kitchen"
    ],
    "wof:name":"Magisco Kitchens",
    "wof:placetype":"venue"
},
  "geometry": {"coordinates":[-0.6680369973,51.7916603088],"type":"Point"}
}