{
  "type": "Feature",
  "properties": {
    "addr:full":"18 Goldsmith Road Eastleigh Hampshire SO50 5EP",
    "addr:housenumber":"18",
    "addr:postcode":"so50 5ep",
    "addr:street":"Goldsmith Road",
    "iso:country":"GB",
    "sg:address":"18 Goldsmith Road",
    "sg:city":"Eastleigh",
    "sg:classifiers":[
        {
            "category":"Professional",
            "subcategory":"Engineering",
            "type":"Services"
        }
    ],
    "sg:postcode":"SO50 5EP",
    "sg:province":"Hampshire",
    "sg:tags":[
        "industrial",
        "engineer"
    ],
    "wof:name":"Jim Perrett",
    "wof:placetype":"venue"
},
  "geometry": {"coordinates":[-1.3614560366,50.9632301331],"type":"Point"}
}