{
  "type": "Feature",
  "properties": {
    "iso:country":"GB",
    "sg:address":"Highfield Stables, Beverley Road, Norton",
    "sg:city":"Malton",
    "sg:classifiers":[
        {
            "category":"Sports & Exercise",
            "subcategory":"Stables",
            "type":"Entertainment"
        },
        {
            "category":"Banks & Credit Unions",
            "subcategory":"Financial Services",
            "type":"Services"
        }
    ],
    "sg:phone":"+44 1653 696778",
    "sg:postcode":"YO17 9PJ",
    "sg:province":"North Yorkshire",
    "sg:tags":[
        "cashing",
        "operation",
        "education",
        "equestrian",
        "cheque"
    ],
    "wof:name":"JAMES HETHERTON",
    "wof:placetype":"venue"
},
  "geometry": {"coordinates":[-0.785139,54.132477],"type":"Point"}
}