{
  "type": "Feature",
  "properties": {
    "addr:full":"281 Main Rd Sidcup Kent DA14 6QR",
    "addr:housenumber":"281",
    "addr:postcode":"da14 6qr",
    "addr:street":"Main Rd",
    "iso:country":"GB",
    "sg:address":"281 Main Rd",
    "sg:city":"Sidcup",
    "sg:classifiers":[
        {
            "category":"Shopping",
            "subcategory":"Pharmacy",
            "type":"Retail Goods"
        }
    ],
    "sg:phone":"+44 20 8300 1304",
    "sg:postcode":"DA14 6QR",
    "sg:province":"Kent",
    "sg:tags":[
        "pharmacist",
        "chemist"
    ],
    "wof:name":"Alkend Ltd",
    "wof:placetype":"venue"
},
  "geometry": {"coordinates":[0.085788,51.430374],"type":"Point"}
}