{
  "type": "Feature",
  "properties": {
    "addr:full":"264 London Road, Charlton Kings Cheltenham Gloucestershire GL52 6HF",
    "addr:housenumber":"264",
    "addr:postcode":"gl52 6hf",
    "addr:street":"London Road",
    "iso:country":"GB",
    "sg:address":"264 London Road, Charlton Kings",
    "sg:city":"Cheltenham",
    "sg:classifiers":[
        {
            "category":"Professional",
            "subcategory":"Accounting & Tax Preparation",
            "type":"Services"
        }
    ],
    "sg:postcode":"GL52 6HF",
    "sg:province":"Gloucestershire",
    "sg:tags":[
        "accountant"
    ],
    "wof:name":"Sixways Accountancy Services",
    "wof:placetype":"venue"
},
  "geometry": {"coordinates":[-2.05294,51.888542],"type":"Point"}
}