{
  "type": "Feature",
  "properties": {
    "addr:full":"George Baylis Road Droitwich Worcestershire WR9 9RB",
    "addr:postcode":"wr9 9rb",
    "addr:street":"George Baylis Road",
    "iso:country":"GB",
    "sg:address":"George Baylis Road",
    "sg:city":"Droitwich",
    "sg:classifiers":[
        {
            "category":"Cafe",
            "type":"Food & Drink"
        }
    ],
    "sg:phone":"+44 1905 776406",
    "sg:postcode":"WR9 9RB",
    "sg:province":"Worcestershire",
    "sg:tags":[
        "tea",
        "room"
    ],
    "wof:name":"The Cafe",
    "wof:placetype":"venue"
},
  "geometry": {"coordinates":[-2.157495,52.274254],"type":"Point"}
}