{
  "type": "Feature",
  "properties": {
    "addr:full":"1st Floor 938 High Rd North Finchley Greater London N12 9RT",
    "addr:housenumber":"938",
    "addr:postcode":"n12 9rt",
    "addr:street":"High Rd",
    "iso:country":"GB",
    "sg:address":"1st Floor 938 High Rd",
    "sg:city":"North Finchley",
    "sg:classifiers":[
        {
            "category":"Professional",
            "subcategory":"Accounting & Tax Preparation",
            "type":"Services"
        }
    ],
    "sg:phone":"+44 20 8343 7341",
    "sg:postcode":"N12 9RT",
    "sg:province":"Greater London",
    "sg:tags":[
        "accountant"
    ],
    "wof:name":"Alexander & Associates",
    "wof:placetype":"venue"
},
  "geometry": {"coordinates":[-0.1765020043,51.6213531494],"type":"Point"}
}