{
  "type": "Feature",
  "properties": {
    "addr:full":"54 Edmonton Avenue Birmingham West Midlands B44 0XE",
    "addr:housenumber":"54",
    "addr:postcode":"b44 0xe",
    "addr:street":"Edmonton Avenue",
    "iso:country":"GB",
    "sg:address":"54 Edmonton Avenue",
    "sg:city":"Birmingham",
    "sg:classifiers":[
        {
            "category":"Shopping",
            "subcategory":"News",
            "type":"Retail Goods"
        }
    ],
    "sg:phone":"+44 121 382 7929",
    "sg:postcode":"B44 0XE",
    "sg:province":"West Midlands",
    "sg:tags":[
        "newsagent"
    ],
    "wof:name":"Raja Tan News",
    "wof:placetype":"venue"
},
  "geometry": {"coordinates":[-1.8746919632,52.5472335815],"type":"Point"}
}