{
  "type": "Feature",
  "properties": {
    "iso:country":"GB",
    "sg:address":"42 Canterbury Road",
    "sg:city":"Peterborough",
    "sg:classifiers":[
        {
            "category":"Building & Trades",
            "subcategory":"Construction",
            "type":"Services"
        }
    ],
    "sg:postcode":"PE4 6PD",
    "sg:province":"Cambridgeshire",
    "sg:tags":[
        "heating",
        "contractor"
    ],
    "wof:name":"Pitts Heating & Plumbing Ltd.",
    "wof:placetype":"venue"
},
  "geometry": {"coordinates":[-0.277456,52.614059],"type":"Point"}
}