{
  "type": "Feature",
  "properties": {
    "addr:full":"243 Lozells Road Birmingham West Midlands B19 1RJ",
    "addr:housenumber":"243",
    "addr:postcode":"b19 1rj",
    "addr:street":"Lozells Road",
    "iso:country":"GB",
    "sg:address":"243 Lozells Road",
    "sg:city":"Birmingham",
    "sg:classifiers":[
        {
            "category":"Professional",
            "subcategory":"Management & Consulting",
            "type":"Services"
        }
    ],
    "sg:phone":"+44 121 523 4100",
    "sg:postcode":"B19 1RJ",
    "sg:province":"West Midlands",
    "sg:tags":[
        "consultant",
        "business"
    ],
    "wof:name":"L & G Enterprises",
    "wof:placetype":"venue"
},
  "geometry": {"coordinates":[-1.914031,52.502857],"type":"Point"}
}