{
  "type": "Feature",
  "properties": {
    "iso:country":"GB",
    "sg:address":"5th Floor, Barkers Pool House",
    "sg:city":"Sheffield",
    "sg:classifiers":[
        {
            "category":"Banks & Credit Unions",
            "subcategory":"Financial Services",
            "type":"Services"
        }
    ],
    "sg:phone":"+44 114 276 6696",
    "sg:postcode":"S1 2HF",
    "sg:province":"South Yorkshire",
    "sg:tags":[
        "consultant"
    ],
    "wof:name":"AXA Assurance",
    "wof:placetype":"venue"
},
  "geometry": {"coordinates":[-1.470842,53.380684],"type":"Point"}
}