{
  "type": "Feature",
  "properties": {
    "addr:full":"Kegworth House 28 Market Place, Kegworth Derby Leicestershire DE74 2EE",
    "addr:housenumber":"28",
    "addr:postcode":"de74 2ee",
    "addr:street":"Market Place",
    "iso:country":"GB",
    "sg:address":"Kegworth House 28 Market Place, Kegworth",
    "sg:city":"Derby",
    "sg:classifiers":[
        {
            "category":"Real Estate",
            "subcategory":"Architect",
            "type":"Services"
        }
    ],
    "sg:phone":"+44 1509 670110",
    "sg:postcode":"DE74 2EE",
    "sg:province":"Leicestershire",
    "wof:name":"D & D Building Services Consulting Engineers Ltd.",
    "wof:placetype":"venue"
},
  "geometry": {"coordinates":[-1.2781840563,52.8353767395],"type":"Point"}
}