{
  "type": "Feature",
  "properties": {
    "addr:full":"96a High Street Lee-on-the-solent Hampshire PO13 9DA",
    "addr:housenumber":"96a",
    "addr:postcode":"po13 9da",
    "addr:street":"High Street",
    "iso:country":"GB",
    "sg:address":"96a High Street",
    "sg:city":"Lee-on-the-solent",
    "sg:classifiers":[
        {
            "category":"Professional",
            "subcategory":"Accounting & Tax Preparation",
            "type":"Services"
        }
    ],
    "sg:phone":"+44 23 9255 1471",
    "sg:postcode":"PO13 9DA",
    "sg:province":"Hampshire",
    "sg:tags":[
        "accountant"
    ],
    "wof:name":"D B Rayner & Co",
    "wof:placetype":"venue"
},
  "geometry": {"coordinates":[-1.201554,50.801525],"type":"Point"}
}