{
  "type": "Feature",
  "properties": {
    "iso:country":"GB",
    "sg:address":"31 Station Road, Milngavie",
    "sg:city":"Glasgow",
    "sg:classifiers":[
        {
            "category":"Building & Trades",
            "subcategory":"Plumbing",
            "type":"Services"
        }
    ],
    "sg:phone":"+44 141 956 1680",
    "sg:postcode":"G62 8PG",
    "sg:province":"East Dunbartonshire",
    "sg:tags":[
        "heating"
    ],
    "wof:name":"Gardner  John M & Son",
    "wof:placetype":"venue"
},
  "geometry": {"coordinates":[-4.315719,55.942169],"type":"Point"}
}