{
  "type": "Feature",
  "properties": {
    "addr:full":"The Gro, Fir Tree Crook Durham DL15 8DD",
    "addr:postcode":"dl15 8dd",
    "addr:street":"Fir Tree",
    "iso:country":"GB",
    "sg:address":"The Gro, Fir Tree",
    "sg:city":"Crook",
    "sg:classifiers":[
        {
            "category":"Travel",
            "subcategory":"Hotels & Motels",
            "type":"Entertainment"
        }
    ],
    "sg:postcode":"DL15 8DD",
    "sg:province":"Durham",
    "wof:name":"Fir Tree Hotel",
    "wof:placetype":"venue"
},
  "geometry": {"coordinates":[-1.783594,54.704731],"type":"Point"}
}