{
  "type": "Feature",
  "properties": {
    "addr:full":"46 Parkway Rd Dudley West Midlands DY1 2QA",
    "addr:housenumber":"46",
    "addr:postcode":"dy1 2qa",
    "addr:street":"Parkway Rd",
    "iso:country":"GB",
    "sg:address":"46 Parkway Rd",
    "sg:city":"Dudley",
    "sg:classifiers":[
        {
            "category":"Organizations",
            "subcategory":"Non-profit Organization",
            "type":"Services"
        }
    ],
    "sg:phone":"+44 1384 234113",
    "sg:postcode":"DY1 2QA",
    "sg:province":"West Midlands",
    "sg:tags":[
        "organisation",
        "voluntary",
        "charity"
    ],
    "wof:name":"West Midlands Quaker Peace Education Project",
    "wof:placetype":"venue"
},
  "geometry": {"coordinates":[-2.096674,52.512581],"type":"Point"}
}