{
  "type": "Feature",
  "properties": {
    "iso:country":"GB",
    "sg:address":"Unit 17 Bedford Wy, Beacon Ctr",
    "sg:city":"North Shields",
    "sg:classifiers":[
        {
            "category":"Food & Beverages",
            "subcategory":"Meat & Fish",
            "type":"Retail Goods"
        }
    ],
    "sg:postcode":"NE29 6QA",
    "sg:province":"Tyne and Wear",
    "sg:tags":[
        "butcher"
    ],
    "wof:name":"M & M Meats",
    "wof:placetype":"venue"
},
  "geometry": {"coordinates":[-1.4467699528,55.0086212158],"type":"Point"}
}