{
  "type": "Feature",
  "properties": {
    "addr:full":"6 Stoke Road Hinckley Leicestershire LE10 0EA",
    "addr:housenumber":"6",
    "addr:postcode":"le10 0ea",
    "addr:street":"Stoke Road",
    "iso:country":"GB",
    "sg:address":"6 Stoke Road",
    "sg:city":"Hinckley",
    "sg:classifiers":[
        {
            "category":"Home & Garden",
            "subcategory":"Kitchen Supply",
            "type":"Retail Goods"
        }
    ],
    "sg:postcode":"LE10 0EA",
    "sg:province":"Leicestershire",
    "sg:tags":[
        "measuring",
        "scale"
    ],
    "wof:name":"Libra Weigh Ltd.",
    "wof:placetype":"venue"
},
  "geometry": {"coordinates":[-1.3831260204,52.5496864319],"type":"Point"}
}