{
  "type": "Feature",
  "properties": {
    "addr:full":"839 Moss Bank Way Bolton Lancashire BL1 5SN",
    "addr:housenumber":"839",
    "addr:postcode":"bl1 5sn",
    "addr:street":"Moss Bank Way",
    "iso:country":"GB",
    "sg:address":"839 Moss Bank Way",
    "sg:city":"Bolton",
    "sg:classifiers":[
        {
            "category":"Fast Food",
            "type":"Food & Drink"
        }
    ],
    "sg:postcode":"BL1 5SN",
    "sg:province":"Lancashire",
    "sg:tags":[
        "away",
        "take"
    ],
    "wof:name":"Moss Bank Tandoori",
    "wof:placetype":"venue"
},
  "geometry": {"coordinates":[-2.477445,53.591629],"type":"Point"}
}