{
  "type": "Feature",
  "properties": {
    "addr:full":"29 West Cliff Road Ramsgate Kent CT11 9JP",
    "addr:housenumber":"29",
    "addr:postcode":"ct11 9jp",
    "addr:street":"West Cliff Road Ramsgate",
    "iso:country":"GB",
    "sg:address":"29 West Cliff Road",
    "sg:city":"Ramsgate",
    "sg:classifiers":[
        {
            "category":"Bars & Pubs",
            "type":"Food & Drink"
        }
    ],
    "sg:phone":"+44 1843 592459",
    "sg:postcode":"CT11 9JP",
    "sg:province":"Kent",
    "sg:tags":[
        "pubs",
        "inn"
    ],
    "wof:name":"The Bedford Inn",
    "wof:placetype":"venue"
},
  "geometry": {"coordinates":[1.4129140377,51.3314743042],"type":"Point"}
}