{
  "type": "Feature",
  "properties": {
    "addr:full":"30 Darenth Rd Stoke Newington Greater London N16 6EL",
    "addr:housenumber":"30",
    "addr:postcode":"n16 6el",
    "addr:street":"Darenth Rd",
    "iso:country":"GB",
    "sg:address":"30 Darenth Rd",
    "sg:city":"Stoke Newington",
    "sg:classifiers":[
        {
            "category":"Manufacturing",
            "subcategory":"Tools & Machinery",
            "type":"Manufacturing & Wholesale Goods"
        }
    ],
    "sg:phone":"+44 20 8806 3648",
    "sg:postcode":"N16 6EL",
    "sg:province":"Greater London",
    "sg:tags":[
        "society",
        "friendly"
    ],
    "wof:name":"Lesbern Brokers",
    "wof:placetype":"venue"
},
  "geometry": {"coordinates":[-0.0694520026,51.5690231323],"type":"Point"}
}