{
  "type": "Feature",
  "properties": {
    "addr:full":"Main Road, Llantwit Fardre Pontypridd Rhondda, Cynon, Taff CF38 2LT",
    "addr:postcode":"cf38 2lt",
    "addr:street":"Main Road Llantwit Fardre",
    "iso:country":"GB",
    "sg:address":"Main Road, Llantwit Fardre",
    "sg:city":"Pontypridd",
    "sg:classifiers":[
        {
            "category":"Travel",
            "subcategory":"Hotels & Motels",
            "type":"Entertainment"
        },
        {
            "category":"Personal",
            "type":"Services"
        }
    ],
    "sg:phone":"+44 1443 217111",
    "sg:postcode":"CF38 2LT",
    "sg:province":"Rhondda, Cynon, Taff",
    "sg:tags":[
        "wedding"
    ],
    "wof:name":"Scotts Hotel Ltd.",
    "wof:placetype":"venue"
},
  "geometry": {"coordinates":[-3.334507,51.5578],"type":"Point"}
}