{
  "type": "Feature",
  "properties": {
    "iso:country":"GB",
    "sg:address":"55 Midland Place, Llansamlet",
    "sg:city":"Swansea",
    "sg:classifiers":[
        {
            "category":"Retail",
            "subcategory":"Auto Repair",
            "type":"Services"
        }
    ],
    "sg:phone":"+44 1792 771720",
    "sg:postcode":"SA7 9QX",
    "sg:province":"Neath Port Talbot",
    "sg:tags":[
        "modification",
        "garage"
    ],
    "wof:name":"L W Motors",
    "wof:placetype":"venue"
},
  "geometry": {"coordinates":[-3.898481,51.659065],"type":"Point"}
}