{
  "type": "Feature",
  "properties": {
    "addr:full":"110 Main St Markfield Leicestershire LE67 9UU",
    "addr:housenumber":"110",
    "addr:postcode":"le67 9uu",
    "addr:street":"Main St",
    "iso:country":"GB",
    "sg:address":"110 Main St",
    "sg:city":"Markfield",
    "sg:classifiers":[
        {
            "category":"Shopping",
            "subcategory":"Crafts & Fabrics",
            "type":"Retail Goods"
        }
    ],
    "sg:phone":"+44 1530 244008",
    "sg:postcode":"LE67 9UU",
    "sg:province":"Leicestershire",
    "sg:tags":[
        "shop",
        "needlecraft",
        "wool"
    ],
    "wof:name":"Wool & Things",
    "wof:placetype":"venue"
},
  "geometry": {"coordinates":[-1.2785320282,52.6854324341],"type":"Point"}
}