{
  "type": "Feature",
  "properties": {
    "iso:country":"GB",
    "sg:address":"96c Ilford Lane",
    "sg:city":"Ilford",
    "sg:classifiers":[
        {
            "category":"Professional",
            "subcategory":"Management & Consulting",
            "type":"Services"
        }
    ],
    "sg:phone":"+44 20 8478 7666",
    "sg:postcode":"IG1 2LD",
    "sg:province":"Essex",
    "sg:tags":[
        "marketing",
        "consultant"
    ],
    "wof:name":"Nation Newspaper",
    "wof:placetype":"venue"
},
  "geometry": {"coordinates":[0.0724750012,51.5543365479],"type":"Point"}
}