{
  "type": "Feature",
  "properties": {
    "addr:full":"110 Layerthorpe York North Yorkshire YO31 7XY",
    "addr:housenumber":"110",
    "addr:postcode":"yo31 7xy",
    "addr:street":"Layerthorpe",
    "iso:country":"GB",
    "sg:address":"110 Layerthorpe",
    "sg:city":"York",
    "sg:classifiers":[
        {
            "category":"Autos & Motor Vehicles",
            "subcategory":"Auto Supplies",
            "type":"Retail Goods"
        }
    ],
    "sg:phone":"+44 1904 628479",
    "sg:postcode":"YO31 7XY",
    "sg:province":"North Yorkshire",
    "sg:tags":[
        "tyre"
    ],
    "wof:name":"A T S North Eastern Ltd.",
    "wof:placetype":"venue"
},
  "geometry": {"coordinates":[-1.069857,53.963371],"type":"Point"}
}