{
  "type": "Feature",
  "properties": {
    "iso:country":"GB",
    "sg:address":"9 Park Place, Newdigate Road, Harefield",
    "sg:city":"Uxbridge",
    "sg:classifiers":[
        {
            "category":"Real Estate",
            "subcategory":"Surveying",
            "type":"Services"
        }
    ],
    "sg:phone":"+44 1895 822577",
    "sg:postcode":"UB9 6EJ",
    "sg:province":"Buckinghamshire",
    "sg:tags":[
        "surveyor",
        "quantity"
    ],
    "wof:name":"Andrew Turner & Co",
    "wof:placetype":"venue"
},
  "geometry": {"coordinates":[-0.482254,51.604378],"type":"Point"}
}