{
  "type": "Feature",
  "properties": {
    "addr:full":"Shepherds Rest, Canada Road Romsey Hampshire SO51 6DD",
    "addr:postcode":"so51 6dd",
    "addr:street":"Canada Road",
    "iso:country":"GB",
    "sg:address":"Shepherds Rest, Canada Road",
    "sg:city":"Romsey",
    "sg:classifiers":[
        {
            "category":"Education",
            "subcategory":"Special Training",
            "type":"Public Place"
        }
    ],
    "sg:phone":"+44 1794 323025",
    "sg:postcode":"SO51 6DD",
    "sg:province":"Hampshire",
    "sg:tags":[
        "product",
        "centre"
    ],
    "wof:name":"Colesway College",
    "wof:placetype":"venue"
},
  "geometry": {"coordinates":[-1.495391,50.988583],"type":"Point"}
}