{
  "type": "Feature",
  "properties": {
    "iso:country":"GB",
    "sg:address":"Unit 4, Londesborough Road",
    "sg:city":"Scarborough",
    "sg:classifiers":[
        {
            "category":"Building & Trades",
            "subcategory":"Construction",
            "type":"Services"
        }
    ],
    "sg:phone":"+44 1723 501468",
    "sg:postcode":"YO12 5AF",
    "sg:province":"North Yorkshire",
    "sg:tags":[
        "repair",
        "window",
        "replacement"
    ],
    "wof:name":"1st Choice Window Centre",
    "wof:placetype":"venue"
},
  "geometry": {"coordinates":[-0.4103440046,54.2776489258],"type":"Point"}
}