{
  "type": "Feature",
  "properties": {
    "iso:country":"GB",
    "sg:address":"23 Southam Road, Hall Green",
    "sg:city":"Birmingham",
    "sg:classifiers":[
        {
            "category":"Professional",
            "subcategory":"Accounting & Tax Preparation",
            "type":"Services"
        }
    ],
    "sg:phone":"+44 121 777 1786",
    "sg:postcode":"B28 8DQ",
    "sg:province":"West Midlands",
    "sg:tags":[
        "accountant"
    ],
    "wof:name":"Vacfurn",
    "wof:placetype":"venue"
},
  "geometry": {"coordinates":[-1.8487950563,52.4368934631],"type":"Point"}
}