{
  "type": "Feature",
  "properties": {
    "addr:full":"151 Walton Lane Nelson Lancashire BB9 8BH",
    "addr:housenumber":"151",
    "addr:postcode":"bb9 8bh",
    "addr:street":"Walton Lane",
    "iso:country":"GB",
    "sg:address":"151 Walton Lane",
    "sg:city":"Nelson",
    "sg:classifiers":[
        {
            "category":"Home & Garden",
            "subcategory":"Home Furnishings",
            "type":"Retail Goods"
        }
    ],
    "sg:phone":"+44 1282 617325",
    "sg:postcode":"BB9 8BH",
    "sg:province":"Lancashire",
    "sg:tags":[
        "blind",
        "manufacture",
        "fitting",
        "curtain"
    ],
    "wof:name":"Hallbank Interiors",
    "wof:placetype":"venue"
},
  "geometry": {"coordinates":[-2.186002,53.839714],"type":"Point"}
}