{
  "type": "Feature",
  "properties": {
    "addr:full":"92 Baytree Road Weston-super-mare Somerset BS22 8HP",
    "addr:housenumber":"92",
    "addr:postcode":"bs22 8hp",
    "addr:street":"Baytree Road",
    "iso:country":"GB",
    "sg:address":"92 Baytree Road",
    "sg:city":"Weston-super-mare",
    "sg:classifiers":[
        {
            "category":"Retail",
            "subcategory":"Auto Repair",
            "type":"Services"
        }
    ],
    "sg:phone":"+44 1934 623088",
    "sg:postcode":"BS22 8HP",
    "sg:province":"Somerset",
    "sg:tags":[
        "modification",
        "garage"
    ],
    "wof:name":"Baytree Road Garage",
    "wof:placetype":"venue"
},
  "geometry": {"coordinates":[-2.946386,51.357906],"type":"Point"}
}