{
  "type": "Feature",
  "properties": {
    "iso:country":"GB",
    "sg:address":"160 Fonthill Rd",
    "sg:city":"Finsbury Park",
    "sg:classifiers":[
        {
            "category":"Shopping",
            "subcategory":"Clothing, Apparel, & Fashions",
            "type":"Retail Goods"
        }
    ],
    "sg:phone":"+44 20 7272 9863",
    "sg:postcode":"N4 3HP",
    "sg:province":"Greater London",
    "sg:tags":[
        "clothing",
        "fabric"
    ],
    "wof:name":"Lace Co Ltd",
    "wof:placetype":"venue"
},
  "geometry": {"coordinates":[-0.1080600023,51.5633125305],"type":"Point"}
}