{
  "type": "Feature",
  "properties": {
    "addr:full":"Little Mt, Soames Lane, Ropley Alresford Hampshire SO24 0ER",
    "addr:postcode":"so24 0er",
    "addr:street":"Soames Lane",
    "iso:country":"GB",
    "sg:address":"Little Mt, Soames Lane, Ropley",
    "sg:city":"Alresford",
    "sg:classifiers":[
        {
            "category":"Building & Trades",
            "subcategory":"Construction",
            "type":"Services"
        }
    ],
    "sg:phone":"+44 1962 772473",
    "sg:postcode":"SO24 0ER",
    "sg:province":"Hampshire",
    "sg:tags":[
        "decorator",
        "painter"
    ],
    "wof:name":"Savoir Faire Decorating",
    "wof:placetype":"venue"
},
  "geometry": {"coordinates":[-1.089354,51.080662],"type":"Point"}
}