{
  "type": "Feature",
  "properties": {
    "addr:full":"7 Byram Street Huddersfield West Yorkshire HD1 1BX",
    "addr:housenumber":"7",
    "addr:postcode":"hd1 1bx",
    "addr:street":"Byram Street",
    "iso:country":"GB",
    "sg:address":"7 Byram Street",
    "sg:city":"Huddersfield",
    "sg:classifiers":[
        {
            "category":"Shopping",
            "subcategory":"Shoes",
            "type":"Retail Goods"
        }
    ],
    "sg:phone":"+44 1484 530431",
    "sg:postcode":"HD1 1BX",
    "sg:province":"West Yorkshire",
    "sg:tags":[
        "shop"
    ],
    "wof:name":"Harry Earnshaw Ltd.",
    "wof:placetype":"venue"
},
  "geometry": {"coordinates":[-1.7817059755,53.6474342346],"type":"Point"}
}