{
  "type": "Feature",
  "properties": {
    "iso:country":"GB",
    "sg:address":"New Universal House, 303 Chase Road",
    "sg:city":"London",
    "sg:classifiers":[
        {
            "category":"Shopping",
            "subcategory":"Pharmacy",
            "type":"Retail Goods"
        }
    ],
    "sg:postcode":"N14 6JB",
    "sg:province":"Greater London",
    "sg:tags":[
        "medical"
    ],
    "wof:name":"Smiths Medical Distribution Ltd.",
    "wof:placetype":"venue"
},
  "geometry": {"coordinates":[-0.12753,51.633743],"type":"Point"}
}