{
  "type": "Feature",
  "properties": {
    "addr:full":"51 Portia Avenue, Shirley Solihull West Midlands B90 2NW",
    "addr:housenumber":"51",
    "addr:postcode":"b90 2nw",
    "addr:street":"Portia Avenue",
    "iso:country":"GB",
    "sg:address":"51 Portia Avenue, Shirley",
    "sg:city":"Solihull",
    "sg:classifiers":[
        {
            "category":"Professional",
            "subcategory":"Engineering",
            "type":"Services"
        },
        {
            "category":"Building & Trades",
            "subcategory":"Electrical",
            "type":"Services"
        }
    ],
    "sg:phone":"+44 121 744 4317",
    "sg:postcode":"B90 2NW",
    "sg:province":"West Midlands",
    "sg:tags":[
        "engineer",
        "electrician",
        "contractor"
    ],
    "wof:name":"Portia Electrics",
    "wof:placetype":"venue"
},
  "geometry": {"coordinates":[-1.826005,52.402939],"type":"Point"}
}