{
  "type": "Feature",
  "properties": {
    "addr:full":"38-41 Camperdown Great Yarmouth Norfolk NR30 3JB",
    "addr:housenumber":"38-41",
    "addr:postcode":"nr30 3jb",
    "addr:street":"Camperdown Great Yarmouth",
    "iso:country":"GB",
    "sg:address":"38-41 Camperdown",
    "sg:city":"Great Yarmouth",
    "sg:classifiers":[
        {
            "category":"Travel",
            "subcategory":"Hotels & Motels",
            "type":"Entertainment"
        }
    ],
    "sg:phone":"+44 1493 843135",
    "sg:postcode":"NR30 3JB",
    "sg:province":"Norfolk",
    "wof:name":"The Embassy Hotel (Great Yarmouth) Ltd.",
    "wof:placetype":"venue"
},
  "geometry": {"coordinates":[1.7350000143,52.6005210876],"type":"Point"}
}