{
  "type": "Feature",
  "properties": {
    "iso:country":"GB",
    "sg:address":"Orchard Cottage, Lower Icknield Way",
    "sg:city":"Chinnor",
    "sg:classifiers":[
        {
            "category":"Health Services",
            "subcategory":"Health Practitioner",
            "type":"Services"
        }
    ],
    "sg:phone":"+44 1844 353037",
    "sg:postcode":"OX39 4EB",
    "sg:province":"Buckinghamshire",
    "sg:tags":[
        "physiotherapist"
    ],
    "wof:name":"Rosmanund Suter",
    "wof:placetype":"venue"
},
  "geometry": {"coordinates":[-0.9099220037,51.7020874023],"type":"Point"}
}