{
  "type": "Feature",
  "properties": {
    "addr:full":"Victoria Chambers, 55 Lower High Street Wednesbury West Midlands WS10 7AL",
    "addr:housenumber":"55",
    "addr:postcode":"ws10 7al",
    "addr:street":"Lower High Street",
    "iso:country":"GB",
    "sg:address":"Victoria Chambers, 55 Lower High Street",
    "sg:city":"Wednesbury",
    "sg:classifiers":[
        {
            "category":"Professional",
            "subcategory":"Art Services",
            "type":"Services"
        }
    ],
    "sg:phone":"+44 121 556 1784",
    "sg:postcode":"WS10 7AL",
    "sg:province":"West Midlands",
    "sg:tags":[
        "photographer"
    ],
    "wof:name":"Alan Johnson Photography",
    "wof:placetype":"venue"
},
  "geometry": {"coordinates":[-2.019254,52.552731],"type":"Point"}
}