{
  "type": "Feature",
  "properties": {
    "iso:country":"GB",
    "sg:address":"8 Beverley Gardens, Ashburton",
    "sg:city":"Newton Abbot",
    "sg:classifiers":[
        {
            "category":"Professional",
            "subcategory":"Engineering",
            "type":"Services"
        }
    ],
    "sg:postcode":"TQ13 7BL",
    "sg:province":"Devon",
    "sg:tags":[
        "contractor",
        "electrical",
        "engineer"
    ],
    "wof:name":"Martin Amos Electrical Contractor",
    "wof:placetype":"venue"
},
  "geometry": {"coordinates":[-3.7494540215,50.522441864],"type":"Point"}
}