{
  "type": "Feature",
  "properties": {
    "iso:country":"GB",
    "sg:address":"11 Thornton Rd",
    "sg:city":"Liverpool",
    "sg:classifiers":[
        {
            "category":"Home & Garden",
            "subcategory":"Building Materials",
            "type":"Retail Goods"
        }
    ],
    "sg:phone":"+44 151 281 9842",
    "sg:postcode":"L16 2LP",
    "sg:province":"Merseyside",
    "sg:tags":[
        "fencing"
    ],
    "wof:name":"Thornwood Fencing",
    "wof:placetype":"venue"
},
  "geometry": {"coordinates":[-2.881897,53.40461],"type":"Point"}
}