{
  "type": "Feature",
  "properties": {
    "iso:country":"GB",
    "sg:address":"149a Uphall Station Rd",
    "sg:city":"Livingston",
    "sg:classifiers":[
        {
            "category":"Restaurant",
            "type":"Food & Drink"
        }
    ],
    "sg:phone":"+44 1506 433002",
    "sg:postcode":"EH53 0PB",
    "sg:province":"City of Edinburgh",
    "wof:name":"Brochela Restaurant",
    "wof:placetype":"venue"
},
  "geometry": {"coordinates":[-3.49591,55.909573],"type":"Point"}
}