{
  "type": "Feature",
  "properties": {
    "iso:country":"GB",
    "sg:address":"Rhydiau",
    "sg:city":"Crymych",
    "sg:classifiers":[
        {
            "category":"Freight",
            "type":"Transportation"
        }
    ],
    "sg:postcode":"SA41 3QT",
    "sg:province":"Pembrokeshire",
    "sg:tags":[
        "haulage",
        "road"
    ],
    "wof:name":"Davies,Gwilym,& Son",
    "wof:placetype":"venue"
},
  "geometry": {"coordinates":[-4.71146,51.994526],"type":"Point"}
}