{
  "type": "Feature",
  "properties": {
    "addr:full":"Hammill Road, Woodnesborough Sandwich Kent CT13 0PR",
    "addr:postcode":"ct13 0pr",
    "addr:street":"Hammill Road;Sandwich",
    "iso:country":"GB",
    "sg:address":"Hammill Road, Woodnesborough",
    "sg:city":"Sandwich",
    "sg:classifiers":[
        {
            "category":"Retail",
            "subcategory":"Auto Repair",
            "type":"Services"
        }
    ],
    "sg:phone":"+44 1304 812349",
    "sg:postcode":"CT13 0PR",
    "sg:province":"Kent",
    "sg:tags":[
        "modification",
        "garage"
    ],
    "wof:name":"Wood-Ash Garage Ltd.",
    "wof:placetype":"venue"
},
  "geometry": {"coordinates":[1.3069449663,51.2626914978],"type":"Point"}
}