{
  "type": "Feature",
  "properties": {
    "addr:full":"Argyle Crescent, Hillhouse Industrial Estate Hamilton South Lanarkshire ML3 9BQ",
    "addr:postcode":"ml3 9bq",
    "addr:street":"Argyle Crescent;Industrial Estate",
    "iso:country":"GB",
    "sg:address":"Argyle Crescent, Hillhouse Industrial Estate",
    "sg:city":"Hamilton",
    "sg:classifiers":[
        {
            "category":"Building & Trades",
            "subcategory":"Plumbing",
            "type":"Services"
        }
    ],
    "sg:phone":"+44 1698 282991",
    "sg:postcode":"ML3 9BQ",
    "sg:province":"South Lanarkshire",
    "sg:tags":[
        "merchant",
        "plumbers'"
    ],
    "wof:name":"Plumbcenter",
    "wof:placetype":"venue"
},
  "geometry": {"coordinates":[-4.0704331398,55.7755584717],"type":"Point"}
}