{
  "type": "Feature",
  "properties": {
    "iso:country":"GB",
    "sg:address":"14 Royal Crescent",
    "sg:city":"Cheltenham",
    "sg:classifiers":[
        {
            "category":"Professional",
            "subcategory":"Lawyer & Legal Services",
            "type":"Services"
        }
    ],
    "sg:phone":"+44 1242 522491",
    "sg:postcode":"GL50 3DA",
    "sg:province":"Gloucestershire",
    "sg:tags":[
        "advice",
        "counselling"
    ],
    "wof:name":"Citizens Advice Bureaux",
    "wof:placetype":"venue"
},
  "geometry": {"coordinates":[-2.079114,51.899704],"type":"Point"}
}