{
  "type": "Feature",
  "properties": {
    "iso:country":"GB",
    "sg:address":"The Sawmills, West Dean",
    "sg:city":"Salisbury",
    "sg:classifiers":[
        {
            "category":"Manufacturing",
            "subcategory":"Lumber",
            "type":"Manufacturing & Wholesale Goods"
        }
    ],
    "sg:phone":"+44 1794 340270",
    "sg:postcode":"SP5 1JA",
    "sg:province":"Dorset",
    "sg:tags":[
        "importer",
        "merchants",
        "agent",
        "timber"
    ],
    "wof:name":"East Bros (Timber) Ltd.",
    "wof:placetype":"venue"
},
  "geometry": {"coordinates":[-1.636244,51.041618],"type":"Point"}
}