{
  "type": "Feature",
  "properties": {
    "addr:full":"11 Lindon Drive, Alvaston Derby Derbyshire DE24 0LP",
    "addr:housenumber":"11",
    "addr:postcode":"de24 0lp",
    "addr:street":"Lindon Drive",
    "iso:country":"GB",
    "sg:address":"11 Lindon Drive, Alvaston",
    "sg:city":"Derby",
    "sg:classifiers":[
        {
            "category":"Building & Trades",
            "subcategory":"Construction",
            "type":"Services"
        }
    ],
    "sg:phone":"+44 1332 752516",
    "sg:postcode":"DE24 0LP",
    "sg:province":"Derbyshire",
    "sg:tags":[
        "decorator",
        "painter"
    ],
    "wof:name":"Michael Hayward",
    "wof:placetype":"venue"
},
  "geometry": {"coordinates":[-1.417915,52.893604],"type":"Point"}
}