{
  "type": "Feature",
  "properties": {
    "addr:full":"2b Franklin Road Watford Hertfordshire WD17 1QD",
    "addr:housenumber":"2b",
    "addr:postcode":"wd17 1qd",
    "addr:street":"Franklin Road",
    "iso:country":"GB",
    "sg:address":"2b Franklin Road",
    "sg:city":"Watford",
    "sg:classifiers":[
        {
            "category":"Health Services",
            "subcategory":"Health Practitioner",
            "type":"Services"
        }
    ],
    "sg:postcode":"WD17 1QD",
    "sg:province":"Hertfordshire",
    "sg:tags":[
        "homoeopathic"
    ],
    "wof:name":"British Homeopathic Dental Association",
    "wof:placetype":"venue"
},
  "geometry": {"coordinates":[-0.3994449973,51.6616477966],"type":"Point"}
}