{
  "type": "Feature",
  "properties": {
    "addr:full":"3 Hardwick Shopping Centre, Home Farm Lane Bury St Edmunds Suffolk IP33 2RH",
    "addr:housenumber":"3",
    "addr:postcode":"ip33 2rh",
    "addr:street":"Hardwick Shopping;Home Farm Lane",
    "iso:country":"GB",
    "sg:address":"3 Hardwick Shopping Centre, Home Farm Lane",
    "sg:city":"Bury St Edmunds",
    "sg:classifiers":[
        {
            "category":"Government",
            "subcategory":"Post Office",
            "type":"Public Place"
        }
    ],
    "sg:phone":"+44 1284 763954",
    "sg:postcode":"IP33 2RH",
    "sg:province":"Suffolk",
    "wof:name":"Hardwick Post Office",
    "wof:placetype":"venue"
},
  "geometry": {"coordinates":[0.7093200088,52.2499046326],"type":"Point"}
}