{
  "type": "Feature",
  "properties": {
    "addr:full":"Mid Way, Abnash, Chalford Hill Stroud Gloucestershire GL6 8QL",
    "addr:postcode":"gl6 8ql",
    "addr:street":"Mid Way Abnash Chalford Hill",
    "iso:country":"GB",
    "sg:address":"Mid Way, Abnash, Chalford Hill",
    "sg:city":"Stroud",
    "sg:classifiers":[
        {
            "category":"Fast Food",
            "type":"Food & Drink"
        },
        {
            "category":"Food & Beverages",
            "subcategory":"Meat & Fish",
            "type":"Retail Goods"
        }
    ],
    "sg:phone":"+44 1453 884998",
    "sg:postcode":"GL6 8QL",
    "sg:province":"Gloucestershire",
    "sg:tags":[
        "outlet",
        "chip",
        "meal",
        "away",
        "take"
    ],
    "wof:name":"FISH IN",
    "wof:placetype":"venue"
},
  "geometry": {"coordinates":[-2.1549890041,51.7270431519],"type":"Point"}
}