{
  "type": "Feature",
  "properties": {
    "iso:country":"GB",
    "sg:address":"7 Baden Road",
    "sg:city":"Brighton",
    "sg:classifiers":[
        {
            "category":"Shopping",
            "subcategory":"Department Store",
            "type":"Retail Goods"
        }
    ],
    "sg:phone":"+44 1273 687202",
    "sg:postcode":"BN2 4DP",
    "sg:province":"East Sussex",
    "wof:name":"Baden Stores",
    "wof:placetype":"venue"
},
  "geometry": {"coordinates":[-0.114629,50.838379],"type":"Point"}
}