{
  "type": "Feature",
  "properties": {
    "addr:full":"Kings Reach Tower, Stamford St Southwark Greater London SE1 9LS",
    "addr:postcode":"se1 9ls",
    "addr:street":"Kings;Stamford St",
    "iso:country":"GB",
    "sg:address":"Kings Reach Tower, Stamford St",
    "sg:city":"Southwark",
    "sg:classifiers":[
        {
            "category":"Wholesale",
            "subcategory":"Books, Periodicals, & Newspapers",
            "type":"Manufacturing & Wholesale Goods"
        }
    ],
    "sg:phone":"+44 20 7261 6349",
    "sg:postcode":"SE1 9LS",
    "sg:province":"Greater London",
    "sg:tags":[
        "publishing"
    ],
    "wof:name":"Instant Picture Network",
    "wof:placetype":"venue"
},
  "geometry": {"coordinates":[-0.088969,51.505634],"type":"Point"}
}