{
  "type": "Feature",
  "properties": {
    "iso:country":"GB",
    "sg:address":"19 Front Street",
    "sg:city":"Blaydon-on-tyne",
    "sg:classifiers":[
        {
            "category":"Personal",
            "subcategory":"Beauty Salon",
            "type":"Services"
        }
    ],
    "sg:phone":"+44 191 414 8800",
    "sg:postcode":"NE21 4RE",
    "sg:province":"Tyne and Wear",
    "sg:tags":[
        "ladies",
        "lady",
        "hairdresser"
    ],
    "wof:name":"Winleton Hair Studio",
    "wof:placetype":"venue"
},
  "geometry": {"coordinates":[-1.7244540453,54.9549942017],"type":"Point"}
}