{
  "type": "Feature",
  "properties": {
    "addr:full":"62 Oaklands Road London Greater London NW2 6DG",
    "addr:housenumber":"62",
    "addr:postcode":"nw2 6dg",
    "addr:street":"Oaklands Road",
    "iso:country":"GB",
    "sg:address":"62 Oaklands Road",
    "sg:city":"London",
    "sg:classifiers":[
        {
            "category":"Professional",
            "subcategory":"Computer Services",
            "type":"Services"
        }
    ],
    "sg:phone":"+44 20 7431 6700",
    "sg:postcode":"NW2 6DG",
    "sg:province":"Greater London",
    "sg:tags":[
        "system",
        "software"
    ],
    "wof:name":"Primemark Computer Consultants Ltd.",
    "wof:placetype":"venue"
},
  "geometry": {"coordinates":[-0.21825,51.554787],"type":"Point"}
}