{
  "type": "Feature",
  "properties": {
    "iso:country":"GB",
    "sg:address":"Upper Harbour, Shore Road",
    "sg:city":"Perth",
    "sg:classifiers":[
        {
            "category":"Manufacturing",
            "subcategory":"Glass & Minerals",
            "type":"Manufacturing & Wholesale Goods"
        }
    ],
    "sg:phone":"+44 1738 625356",
    "sg:postcode":"PH2 8BH",
    "sg:province":"Perth and Kinross",
    "sg:tags":[
        "chalk",
        "stone",
        "slate"
    ],
    "wof:name":"Scottish Aggregates Ltd.",
    "wof:placetype":"venue"
},
  "geometry": {"coordinates":[-3.4324140549,56.3960533142],"type":"Point"}
}