{
  "type": "Feature",
  "properties": {
    "addr:full":"14 Mount Pleasant Road Tunbridge Wells Kent TN1 1QU",
    "addr:housenumber":"14",
    "addr:postcode":"tn1 1qu",
    "addr:street":"Mount Pleasant Road",
    "iso:country":"GB",
    "sg:address":"14 Mount Pleasant Road",
    "sg:city":"Tunbridge Wells",
    "sg:classifiers":[
        {
            "category":"Food & Beverages",
            "subcategory":"Specialty",
            "type":"Retail Goods"
        }
    ],
    "sg:postcode":"TN1 1QU",
    "sg:province":"Kent",
    "sg:tags":[
        "product",
        "health"
    ],
    "wof:name":"Advance Nutrition",
    "wof:placetype":"venue"
},
  "geometry": {"coordinates":[0.263564,51.130165],"type":"Point"}
}