{
  "type": "Feature",
  "properties": {
    "iso:country":"GB",
    "sg:address":"Nelson Works, 10 Lyon Road, Wimbledon",
    "sg:city":"London",
    "sg:classifiers":[
        {
            "category":"Wholesale",
            "subcategory":"Construction Materials",
            "type":"Manufacturing & Wholesale Goods"
        }
    ],
    "sg:postcode":"SW19 2RT",
    "sg:province":"Greater London",
    "sg:tags":[
        "coating",
        "powder"
    ],
    "wof:name":"Becker Powder Coatings (South) Ltd.",
    "wof:placetype":"venue"
},
  "geometry": {"coordinates":[-0.207024,51.420998],"type":"Point"}
}