{
  "type": "Feature",
  "properties": {
    "addr:full":"75 Middle Street, South Driffield East Riding of Yorkshire YO25 6QF",
    "addr:housenumber":"75",
    "addr:postcode":"yo25 6qf",
    "addr:street":"Middle Street South",
    "iso:country":"GB",
    "sg:address":"75 Middle Street, South",
    "sg:city":"Driffield",
    "sg:classifiers":[
        {
            "category":"Shopping",
            "subcategory":"Clothing, Apparel, & Fashions",
            "type":"Retail Goods"
        }
    ],
    "sg:postcode":"YO25 6QF",
    "sg:province":"East Riding of Yorkshire",
    "sg:tags":[
        "menswear"
    ],
    "wof:name":"Hall Ossey Ltd.",
    "wof:placetype":"venue"
},
  "geometry": {"coordinates":[-0.4368880093,54.0037460327],"type":"Point"}
}