{
  "type": "Feature",
  "properties": {
    "addr:full":"17 Edward Pavilion Liverpool Merseyside L1 4AF",
    "addr:housenumber":"17",
    "addr:postcode":"l1 4af",
    "addr:street":"Edward",
    "iso:country":"GB",
    "sg:address":"17 Edward Pavilion",
    "sg:city":"Liverpool",
    "sg:classifiers":[
        {
            "category":"Restaurant",
            "type":"Food & Drink"
        }
    ],
    "sg:phone":"+44 151 709 7097",
    "sg:postcode":"L1 4AF",
    "sg:province":"Merseyside",
    "wof:name":"Blue Bar & Grill",
    "wof:placetype":"venue"
},
  "geometry": {"coordinates":[-2.978481,53.409775],"type":"Point"}
}