{
  "type": "Feature",
  "properties": {
    "iso:country":"GB",
    "sg:address":"Nantwich Rd, Woore",
    "sg:city":"Crewe",
    "sg:classifiers":[
        {
            "category":"Bars & Pubs",
            "type":"Food & Drink"
        }
    ],
    "sg:phone":"+44 1630 647220",
    "sg:postcode":"CW3 9SA",
    "sg:province":"Cheshire",
    "sg:tags":[
        "pubs",
        "house",
        "inn",
        "public",
        "activity"
    ],
    "wof:name":"The Swan at Woore",
    "wof:placetype":"venue"
},
  "geometry": {"coordinates":[-2.401946,52.977428],"type":"Point"}
}