{
  "type": "Feature",
  "properties": {
    "addr:full":"New Monkray Farm, Hensingham Whitehaven Cumbria CA28 8XX",
    "addr:postcode":"ca28 8xx",
    "addr:street":"Hensingham Whitehaven",
    "iso:country":"GB",
    "sg:address":"New Monkray Farm, Hensingham",
    "sg:city":"Whitehaven",
    "sg:classifiers":[
        {
            "category":"Farming",
            "subcategory":"Farm",
            "type":"Manufacturing & Wholesale Goods"
        }
    ],
    "sg:phone":"+44 1946 62417",
    "sg:postcode":"CA28 8XX",
    "sg:province":"Cumbria",
    "sg:tags":[
        "mixed",
        "crop"
    ],
    "wof:name":"I & G Lister",
    "wof:placetype":"venue"
},
  "geometry": {"coordinates":[-3.565859,54.537563],"type":"Point"}
}