{
  "type": "Feature",
  "properties": {
    "iso:country":"GB",
    "sg:address":"242 Halifax Road",
    "sg:city":"Rochdale",
    "sg:classifiers":[
        {
            "category":"Bars & Pubs",
            "type":"Food & Drink"
        },
        {
            "category":"Community Center",
            "subcategory":"Social",
            "type":"Public Place"
        }
    ],
    "sg:phone":"+44 1706 646554",
    "sg:postcode":"OL16 2NT",
    "sg:province":"Lancashire",
    "sg:tags":[
        "pubs",
        "house",
        "inn",
        "activity"
    ],
    "wof:name":"Gala Holdings Ltd.",
    "wof:placetype":"venue"
},
  "geometry": {"coordinates":[-2.1419289112,53.6278915405],"type":"Point"}
}