{
  "type": "Feature",
  "properties": {
    "addr:full":"6 Heatherlie Park Selkirk Scottish Borders TD7 5AL",
    "addr:housenumber":"6",
    "addr:postcode":"td7 5al",
    "addr:street":"Heatherlie Park Selkirk",
    "iso:country":"GB",
    "sg:address":"6 Heatherlie Park",
    "sg:city":"Selkirk",
    "sg:classifiers":[
        {
            "category":"Professional",
            "subcategory":"Management & Consulting",
            "type":"Services"
        }
    ],
    "sg:phone":"+44 1750 20850",
    "sg:postcode":"TD7 5AL",
    "sg:province":"Scottish Borders",
    "sg:tags":[
        "consultant",
        "specialist"
    ],
    "wof:name":"Color Me Beautiful",
    "wof:placetype":"venue"
},
  "geometry": {"coordinates":[-2.907738924,55.5322685242],"type":"Point"}
}