{
  "type": "Feature",
  "properties": {
    "addr:full":"1001 Christchurch Rd Bournemouth Dorset BH7 6BB",
    "addr:housenumber":"1001",
    "addr:postcode":"bh7 6bb",
    "addr:street":"Christchurch Rd",
    "iso:country":"GB",
    "sg:address":"1001 Christchurch Rd",
    "sg:city":"Bournemouth",
    "sg:classifiers":[
        {
            "category":"Fast Food",
            "type":"Food & Drink"
        }
    ],
    "sg:phone":"+44 1202 779555",
    "sg:postcode":"BH7 6BB",
    "sg:province":"Dorset",
    "sg:tags":[
        "away",
        "take"
    ],
    "wof:name":"Perfect Fried Chicken",
    "wof:placetype":"venue"
},
  "geometry": {"coordinates":[-1.8205039501,50.7324905396],"type":"Point"}
}