{
  "type": "Feature",
  "properties": {
    "addr:full":"Valley View Jarrow Tyne and Wear NE32 5QT",
    "addr:postcode":"ne32 5qt",
    "iso:country":"GB",
    "sg:address":"Valley View",
    "sg:city":"Jarrow",
    "sg:classifiers":[
        {
            "category":"Education",
            "subcategory":"School",
            "type":"Public Place"
        },
        {
            "category":"Government",
            "subcategory":"Office",
            "type":"Public Place"
        }
    ],
    "sg:phone":"+44 191 489 8358",
    "sg:postcode":"NE32 5QT",
    "sg:province":"Tyne and Wear",
    "sg:tags":[
        "local",
        "authority"
    ],
    "wof:name":"Valley View Jmi & Nursery School",
    "wof:placetype":"venue"
},
  "geometry": {"coordinates":[-1.4869790077,54.9683036804],"type":"Point"}
}