{
  "type": "Feature",
  "properties": {
    "addr:full":"Chesterfield Road, Holmewood Chesterfield Derbyshire S42 5TD",
    "addr:postcode":"s42 5td",
    "addr:street":"Chesterfield Road",
    "iso:country":"GB",
    "sg:address":"Chesterfield Road, Holmewood",
    "sg:city":"Chesterfield",
    "sg:classifiers":[
        {
            "category":"Bars & Pubs",
            "type":"Food & Drink"
        }
    ],
    "sg:phone":"+44 1246 850201",
    "sg:postcode":"S42 5TD",
    "sg:province":"Derbyshire",
    "sg:tags":[
        "pubs",
        "inn"
    ],
    "wof:name":"William Thorpe Hotel",
    "wof:placetype":"venue"
},
  "geometry": {"coordinates":[-1.3562289476,53.1876907349],"type":"Point"}
}