{
  "type": "Feature",
  "properties": {
    "iso:country":"GB",
    "sg:address":"Nuttery Vale, Hoxne",
    "sg:city":"Eye",
    "sg:classifiers":[
        {
            "category":"Transit Center",
            "subcategory":"Passenger",
            "type":"Transportation"
        },
        {
            "category":"Retail",
            "subcategory":"Pet Boarding",
            "type":"Services"
        }
    ],
    "sg:phone":"+44 1379 668267",
    "sg:postcode":"IP21 5BB",
    "sg:province":"Norfolk",
    "sg:tags":[
        "kennel",
        "catteries"
    ],
    "wof:name":"Goldbrook Boarding Kennels & Cattery",
    "wof:placetype":"venue"
},
  "geometry": {"coordinates":[1.200589,52.351547],"type":"Point"}
}