{
  "type": "Feature",
  "properties": {
    "addr:full":"Shirburn Castle Watlington Buckinghamshire OX9 5DL",
    "addr:housenumber":"shirburn",
    "addr:postcode":"ox9 5dl",
    "addr:street":"Castle Watlington",
    "iso:country":"GB",
    "sg:address":"Shirburn Castle",
    "sg:city":"Watlington",
    "sg:classifiers":[
        {
            "category":"Professional",
            "subcategory":"Management & Consulting",
            "type":"Services"
        }
    ],
    "sg:phone":"+44 1491 613702",
    "sg:postcode":"OX9 5DL",
    "sg:province":"Buckinghamshire",
    "sg:tags":[
        "marketing",
        "consultant"
    ],
    "wof:name":"Marketing Communications Consultancy",
    "wof:placetype":"venue"
},
  "geometry": {"coordinates":[-1.005679965,51.6440811157],"type":"Point"}
}