{
  "type": "Feature",
  "properties": {
    "iso:country":"GB",
    "sg:address":"99 Lodge Lane",
    "sg:city":"Grays",
    "sg:classifiers":[
        {
            "category":"Real Estate",
            "subcategory":"Real Estate Operator",
            "type":"Services"
        },
        {
            "category":"Real Estate",
            "subcategory":"Real Estate Agent",
            "type":"Services"
        }
    ],
    "sg:phone":"+44 1375 390525",
    "sg:postcode":"RM17 5SE",
    "sg:province":"Essex",
    "sg:tags":[
        "letting"
    ],
    "wof:name":"Cosmos Accommodation",
    "wof:placetype":"venue"
},
  "geometry": {"coordinates":[0.335424,51.488937],"type":"Point"}
}