{
  "type": "Feature",
  "properties": {
    "iso:country":"GB",
    "sg:address":"The Street",
    "sg:city":"Halesworth",
    "sg:classifiers":[
        {
            "category":"Government",
            "subcategory":"Post Office",
            "type":"Public Place"
        }
    ],
    "sg:phone":"+44 1502 478248",
    "sg:postcode":"IP19 9DP",
    "sg:province":"Suffolk",
    "wof:name":"Wenhaston Post Office Stores",
    "wof:placetype":"venue"
},
  "geometry": {"coordinates":[1.5971699953,52.3209495544],"type":"Point"}
}