{
  "type": "Feature",
  "properties": {
    "iso:country":"GB",
    "sg:address":"2 Drybank Road",
    "sg:city":"Haverhill",
    "sg:classifiers":[
        {
            "category":"Building & Trades",
            "subcategory":"Construction",
            "type":"Services"
        }
    ],
    "sg:phone":"+44 1440 706051",
    "sg:postcode":"CB9 7FR",
    "sg:province":"Essex",
    "sg:tags":[
        "builder"
    ],
    "wof:name":"H C Moss (Builders) Ltd.",
    "wof:placetype":"venue"
},
  "geometry": {"coordinates":[0.407682,52.048355],"type":"Point"}
}