{
  "type": "Feature",
  "properties": {
    "addr:full":"303a Ley St Ilford Essex IG1 4BN",
    "addr:housenumber":"303a",
    "addr:postcode":"ig1 4bn",
    "addr:street":"Ley St",
    "iso:country":"GB",
    "sg:address":"303a Ley St",
    "sg:city":"Ilford",
    "sg:classifiers":[
        {
            "category":"Organizations",
            "subcategory":"Membership Organization",
            "type":"Services"
        }
    ],
    "sg:postcode":"IG1 4BN",
    "sg:province":"Essex",
    "sg:tags":[
        "club"
    ],
    "wof:name":"B A E Systems (Defence Systems) Ltd",
    "wof:placetype":"venue"
},
  "geometry": {"coordinates":[0.0819329992,51.5637435913],"type":"Point"}
}