{
  "type": "Feature",
  "properties": {
    "iso:country":"GB",
    "sg:address":"Church App, Bishops Cleeve",
    "sg:city":"Cheltenham",
    "sg:classifiers":[
        {
            "category":"Wholesale",
            "subcategory":"Toys & Hobbies",
            "type":"Manufacturing & Wholesale Goods"
        }
    ],
    "sg:phone":"+44 870 444 2643",
    "sg:postcode":"GL52 8NG",
    "sg:province":"Gloucestershire",
    "sg:tags":[
        "game"
    ],
    "wof:name":"Orange Tree",
    "wof:placetype":"venue"
},
  "geometry": {"coordinates":[-2.0602440834,51.948890686],"type":"Point"}
}