{
  "type": "Feature",
  "properties": {
    "addr:full":"240 Crystal Palace Rd East Dulwich Greater London SE22 9JQ",
    "addr:housenumber":"240",
    "addr:postcode":"se22 9jq",
    "addr:street":"Crystal Palace Rd",
    "iso:country":"GB",
    "sg:address":"240 Crystal Palace Rd",
    "sg:city":"East Dulwich",
    "sg:classifiers":[
        {
            "category":"Home & Garden",
            "subcategory":"Hardware",
            "type":"Retail Goods"
        }
    ],
    "sg:phone":"+44 20 8693 6718",
    "sg:postcode":"SE22 9JQ",
    "sg:province":"Greater London",
    "sg:tags":[
        "paint",
        "coating"
    ],
    "wof:name":"New Bronze",
    "wof:placetype":"venue"
},
  "geometry": {"coordinates":[-0.0724000037,51.4535636902],"type":"Point"}
}