{
  "type": "Feature",
  "properties": {
    "addr:full":"Unit 1 Selby Street, Off Bold Street, Strand Preston Lancashire PR1 7NY",
    "addr:housenumber":"unit 1",
    "addr:postcode":"pr1 7ny",
    "addr:street":"Selby Street Off Bold Street",
    "iso:country":"GB",
    "sg:address":"Unit 1 Selby Street, Off Bold Street, Strand",
    "sg:city":"Preston",
    "sg:classifiers":[
        {
            "category":"Home & Garden",
            "subcategory":"Household Appliances",
            "type":"Retail Goods"
        }
    ],
    "sg:phone":"+44 1772 731280",
    "sg:postcode":"PR1 7NY",
    "sg:province":"Lancashire",
    "sg:tags":[
        "domestic",
        "centre"
    ],
    "wof:name":"Errol Kerrone",
    "wof:placetype":"venue"
},
  "geometry": {"coordinates":[-2.715789,53.768406],"type":"Point"}
}