{
  "type": "Feature",
  "properties": {
    "addr:full":"1 Azara Parade, Bracklesham Lane, Bracklesham Bay Chichester West Sussex PO20 8HP",
    "addr:housenumber":"1",
    "addr:postcode":"po20 8hp",
    "addr:street":"Azara Parade Bracklesham Lane Bracklesham Bay",
    "iso:country":"GB",
    "sg:address":"1 Azara Parade, Bracklesham Lane, Bracklesham Bay",
    "sg:city":"Chichester",
    "sg:classifiers":[
        {
            "category":"Restaurant",
            "type":"Food & Drink"
        }
    ],
    "sg:phone":"+44 1243 671336",
    "sg:postcode":"PO20 8HP",
    "sg:province":"West Sussex",
    "sg:tags":[
        "-",
        "chinese"
    ],
    "wof:name":"Number One Chinese Restaurant",
    "wof:placetype":"venue"
},
  "geometry": {"coordinates":[-0.8566330075,50.7661590576],"type":"Point"}
}