{
  "type": "Feature",
  "properties": {
    "addr:full":"22 Lockyer Road Plymouth Devon PL3 4RL",
    "addr:housenumber":"22",
    "addr:postcode":"pl3 4rl",
    "addr:street":"Lockyer Road",
    "iso:country":"GB",
    "sg:address":"22 Lockyer Road",
    "sg:city":"Plymouth",
    "sg:classifiers":[
        {
            "category":"Travel",
            "subcategory":"Hotels & Motels",
            "type":"Entertainment"
        }
    ],
    "sg:phone":"+44 1752 220726",
    "sg:postcode":"PL3 4RL",
    "sg:province":"Devon",
    "sg:tags":[
        "house",
        "guest"
    ],
    "wof:name":"Devonshire Guest House",
    "wof:placetype":"venue"
},
  "geometry": {"coordinates":[-4.135329,50.384975],"type":"Point"}
}