{
  "type": "Feature",
  "properties": {
    "addr:full":"4 Hinton Way, Wilburton Ely Cambridgeshire CB6 3SE",
    "addr:housenumber":"4",
    "addr:postcode":"cb6 3se",
    "addr:street":"Hinton Way",
    "iso:country":"GB",
    "sg:address":"4 Hinton Way, Wilburton",
    "sg:city":"Ely",
    "sg:classifiers":[
        {
            "category":"Building & Trades",
            "subcategory":"Construction",
            "type":"Services"
        }
    ],
    "sg:postcode":"CB6 3SE",
    "sg:province":"Cambridgeshire",
    "sg:tags":[
        "heating",
        "contractor"
    ],
    "wof:name":"J R Webster Plumbing & Heating",
    "wof:placetype":"venue"
},
  "geometry": {"coordinates":[0.173733,52.355354],"type":"Point"}
}