{
  "type": "Feature",
  "properties": {
    "addr:full":"11 Powburn Crescent, Uddingston Glasgow Glasgow City G71 7SS",
    "addr:housenumber":"11",
    "addr:postcode":"g71 7ss",
    "addr:street":"Powburn Crescent",
    "iso:country":"GB",
    "sg:address":"11 Powburn Crescent, Uddingston",
    "sg:city":"Glasgow",
    "sg:classifiers":[
        {
            "category":"Building & Trades",
            "subcategory":"Construction",
            "type":"Services"
        }
    ],
    "sg:postcode":"G71 7SS",
    "sg:province":"Glasgow City",
    "sg:tags":[
        "roofing"
    ],
    "wof:name":"Dennis M Malone",
    "wof:placetype":"venue"
},
  "geometry": {"coordinates":[-4.0934,55.826847],"type":"Point"}
}