{
  "type": "Feature",
  "properties": {
    "iso:country":"GB",
    "sg:address":"44 Southhouse Road",
    "sg:city":"Edinburgh",
    "sg:classifiers":[
        {
            "category":"Food & Beverages",
            "subcategory":"Supermarket",
            "type":"Retail Goods"
        }
    ],
    "sg:postcode":"EH17 8EW",
    "sg:province":"City of Edinburgh",
    "wof:name":"J P S Superstores",
    "wof:placetype":"venue"
},
  "geometry": {"coordinates":[-3.1572699547,55.8984260559],"type":"Point"}
}