{
  "type": "Feature",
  "properties": {
    "addr:full":"Adelaide Place Dundee Dundee City DD3 6LF",
    "addr:postcode":"dd3 6lf",
    "addr:street":"Adelaide Place",
    "iso:country":"GB",
    "sg:address":"Adelaide Place",
    "sg:city":"Dundee",
    "sg:classifiers":[
        {
            "category":"Arena",
            "subcategory":"Sports Club",
            "type":"Entertainment"
        }
    ],
    "sg:phone":"+44 1382 224516",
    "sg:postcode":"DD3 6LF",
    "sg:province":"Dundee City",
    "wof:name":"Dudhope Bowling Club",
    "wof:placetype":"venue"
},
  "geometry": {"coordinates":[-2.9829781055,56.4682197571],"type":"Point"}
}