{
  "type": "Feature",
  "properties": {
    "addr:full":"New House, Winslow Bromyard Herefordshire HR7 4SF",
    "addr:postcode":"hr7 4sf",
    "iso:country":"GB",
    "sg:address":"New House, Winslow",
    "sg:city":"Bromyard",
    "sg:classifiers":[
        {
            "category":"Farming",
            "subcategory":"Livestock Farm",
            "type":"Manufacturing & Wholesale Goods"
        }
    ],
    "sg:postcode":"HR7 4SF",
    "sg:province":"Herefordshire",
    "sg:tags":[
        "others"
    ],
    "wof:name":"S M & S D Jones",
    "wof:placetype":"venue"
},
  "geometry": {"coordinates":[-2.5103991032,52.1890983582],"type":"Point"}
}