{
  "type": "Feature",
  "properties": {
    "addr:full":"33-35 Markham Street, Chelsea Grn London Greater London SW3 3NR",
    "addr:housenumber":"33-35",
    "addr:postcode":"sw3 3nr",
    "addr:street":"Markham Street",
    "iso:country":"GB",
    "sg:address":"33-35 Markham Street, Chelsea Grn",
    "sg:city":"London",
    "sg:classifiers":[
        {
            "category":"Professional",
            "subcategory":"Art Services",
            "type":"Services"
        }
    ],
    "sg:postcode":"SW3 3NR",
    "sg:province":"Greater London",
    "sg:tags":[
        "framing"
    ],
    "wof:name":"The Fine Art Publishing Co. Ltd.",
    "wof:placetype":"venue"
},
  "geometry": {"coordinates":[-0.165897,51.490276],"type":"Point"}
}