{
  "type": "Feature",
  "properties": {
    "iso:country":"GB",
    "sg:address":"Vantage House, Harfreys Road, Harfreys Industrial Estate",
    "sg:city":"Great Yarmouth",
    "sg:classifiers":[
        {
            "category":"Professional",
            "subcategory":"Detective & Security Services",
            "type":"Services"
        },
        {
            "category":"Building & Trades",
            "subcategory":"Construction",
            "type":"Services"
        }
    ],
    "sg:phone":"+44 1493 656521",
    "sg:postcode":"NR31 0LS",
    "sg:province":"Norfolk",
    "sg:tags":[
        "platform",
        "work",
        "scaffolding"
    ],
    "wof:name":"Dmgy Offshore Fabric Maintenance Services Ltd.",
    "wof:placetype":"venue"
},
  "geometry": {"coordinates":[1.71691,52.592861],"type":"Point"}
}