{
  "type": "Feature",
  "properties": {
    "addr:full":"Main Street, Heath Chesterfield Derbyshire S44 5SN",
    "addr:postcode":"s44 5sn",
    "addr:street":"Main Street",
    "iso:country":"GB",
    "sg:address":"Main Street, Heath",
    "sg:city":"Chesterfield",
    "sg:classifiers":[
        {
            "category":"Government",
            "subcategory":"Post Office",
            "type":"Public Place"
        }
    ],
    "sg:phone":"+44 1246 850303",
    "sg:postcode":"S44 5SN",
    "sg:province":"Derbyshire",
    "wof:name":"Heath Post Office",
    "wof:placetype":"venue"
},
  "geometry": {"coordinates":[-1.331733942,53.1980667114],"type":"Point"}
}