{
  "type": "Feature",
  "properties": {
    "iso:country":"GB",
    "sg:address":"Visitors Centre, Alveley",
    "sg:city":"Bridgnorth",
    "sg:classifiers":[
        {
            "category":"Landmark",
            "subcategory":"Tourist Attraction",
            "type":"Public Place"
        }
    ],
    "sg:phone":"+44 1746 781192",
    "sg:postcode":"WV15 6NE",
    "sg:province":"Shropshire",
    "sg:tags":[
        "interest"
    ],
    "wof:name":"Severn Valley Country Park",
    "wof:placetype":"venue"
},
  "geometry": {"coordinates":[-2.34337,52.458767],"type":"Point"}
}