{
  "type": "Feature",
  "properties": {
    "iso:country":"GB",
    "sg:address":"3 Station Court, Borough Green",
    "sg:city":"West Malling",
    "sg:classifiers":[
        {
            "category":"Recreation",
            "subcategory":"Gun Range",
            "type":"Entertainment"
        }
    ],
    "sg:phone":"+44 1732 886666",
    "sg:postcode":"TN15 8AF",
    "sg:province":"Kent",
    "sg:tags":[
        "operator",
        "tour"
    ],
    "wof:name":"Tangney Tours",
    "wof:placetype":"venue"
},
  "geometry": {"coordinates":[0.307263,51.292831],"type":"Point"}
}