{
  "type": "Feature",
  "properties": {
    "addr:full":"Tanum House, Hawkshead Road Potters Bar Greater London EN6 1LX",
    "addr:postcode":"en6 1lx",
    "addr:street":"Hawkshead Road",
    "iso:country":"GB",
    "sg:address":"Tanum House, Hawkshead Road",
    "sg:city":"Potters Bar",
    "sg:classifiers":[
        {
            "category":"Shopping",
            "type":"Retail Goods"
        }
    ],
    "sg:postcode":"EN6 1LX",
    "sg:province":"Greater London",
    "sg:tags":[
        "bag",
        "product",
        "disposable"
    ],
    "wof:name":"Lawrence Izen",
    "wof:placetype":"venue"
},
  "geometry": {"coordinates":[-0.1849250048,51.7113990784],"type":"Point"}
}