{
  "type": "Feature",
  "properties": {
    "addr:full":"Old Church Rd, Harborne Birmingham West Midlands B17 0BB",
    "addr:postcode":"b17 0bb",
    "addr:street":"Old Church Rd",
    "iso:country":"GB",
    "sg:address":"Old Church Rd, Harborne",
    "sg:city":"Birmingham",
    "sg:classifiers":[
        {
            "category":"Bars & Pubs",
            "type":"Food & Drink"
        },
        {
            "category":"Community Center",
            "subcategory":"Social",
            "type":"Public Place"
        }
    ],
    "sg:phone":"+44 121 427 0934",
    "sg:postcode":"B17 0BB",
    "sg:province":"West Midlands",
    "sg:tags":[
        "pubs",
        "house",
        "inn",
        "activity"
    ],
    "wof:name":"The Bell",
    "wof:placetype":"venue"
},
  "geometry": {"coordinates":[-1.959772,52.453728],"type":"Point"}
}