{
  "type": "Feature",
  "properties": {
    "addr:full":"Within Wooler First School, Ryecroft Way Wooler Northumberland NE71 6EB",
    "addr:postcode":"ne71 6eb",
    "addr:street":"Ryecroft Way",
    "iso:country":"GB",
    "sg:address":"Within Wooler First School, Ryecroft Way",
    "sg:city":"Wooler",
    "sg:classifiers":[
        {
            "category":"Organizations",
            "subcategory":"Non-profit Organization",
            "type":"Services"
        }
    ],
    "sg:phone":"+44 1668 282458",
    "sg:postcode":"NE71 6EB",
    "sg:province":"Northumberland",
    "sg:tags":[
        "organisation",
        "voluntary",
        "charity"
    ],
    "wof:name":"Glendale Play Group",
    "wof:placetype":"venue"
},
  "geometry": {"coordinates":[-2.0115840435,55.5477714539],"type":"Point"}
}