{
  "type": "Feature",
  "properties": {
    "iso:country":"GB",
    "sg:address":"7 Collinsons Court, Church Street",
    "sg:city":"Warrington",
    "sg:classifiers":[
        {
            "category":"Manufacturing",
            "subcategory":"Metals",
            "type":"Manufacturing & Wholesale Goods"
        }
    ],
    "sg:postcode":"WA6 6PN",
    "sg:province":"Cheshire",
    "sg:tags":[
        "steel",
        "stockholder"
    ],
    "wof:name":"I V M Intertrade Ltd.",
    "wof:placetype":"venue"
},
  "geometry": {"coordinates":[-2.7243599892,53.2948913574],"type":"Point"}
}