{
  "type": "Feature",
  "properties": {
    "addr:full":"149 Sandhurst Road London Greater London N9 8BB",
    "addr:housenumber":"149",
    "addr:postcode":"n9 8bb",
    "addr:street":"Sandhurst Road",
    "iso:country":"GB",
    "sg:address":"149 Sandhurst Road",
    "sg:city":"London",
    "sg:classifiers":[
        {
            "category":"Personal",
            "subcategory":"Psychics & Astrologers",
            "type":"Services"
        }
    ],
    "sg:phone":"+44 20 8804 1547",
    "sg:postcode":"N9 8BB",
    "sg:province":"Greater London",
    "sg:tags":[
        "clairvoyant",
        "palmist"
    ],
    "wof:name":"Linda Barker",
    "wof:placetype":"venue"
},
  "geometry": {"coordinates":[-0.042143,51.638874],"type":"Point"}
}