{
  "type": "Feature",
  "properties": {
    "iso:country":"GB",
    "sg:address":"Oak Mills, Topcliffe Lane, Morley",
    "sg:city":"Leeds",
    "sg:classifiers":[
        {
            "category":"Manufacturing",
            "subcategory":"Textiles",
            "type":"Manufacturing & Wholesale Goods"
        }
    ],
    "sg:phone":"+44 113 252 4271",
    "sg:postcode":"LS27 0HL",
    "sg:province":"West Yorkshire",
    "sg:tags":[
        "made-up",
        "manufacturer"
    ],
    "wof:name":"J D Matthewman Textiles Ltd",
    "wof:placetype":"venue"
},
  "geometry": {"coordinates":[-1.5886490345,53.7353858948],"type":"Point"}
}