{
  "type": "Feature",
  "properties": {
    "iso:country":"GB",
    "sg:address":"38-40 East High Street",
    "sg:city":"Forfar",
    "sg:classifiers":[
        {
            "category":"Real Estate",
            "subcategory":"Surveying",
            "type":"Services"
        }
    ],
    "sg:phone":"+44 1307 463657",
    "sg:postcode":"DD8 2EG",
    "sg:province":"Angus",
    "sg:tags":[
        "surveyor",
        "valuer"
    ],
    "wof:name":"David Wardhaugh & Son",
    "wof:placetype":"venue"
},
  "geometry": {"coordinates":[-2.886709,56.644398],"type":"Point"}
}