{
  "type": "Feature",
  "properties": {
    "addr:full":"St Andrew Place Edinburgh City of Edinburgh EH6 7EG",
    "addr:postcode":"eh6 7eg",
    "addr:street":"St Andrew Place Edinburgh",
    "iso:country":"GB",
    "sg:address":"St Andrew Place",
    "sg:city":"Edinburgh",
    "sg:classifiers":[
        {
            "category":"Education",
            "subcategory":"School",
            "type":"Public Place"
        }
    ],
    "sg:phone":"+44 131 554 4844",
    "sg:postcode":"EH6 7EG",
    "sg:province":"City of Edinburgh",
    "sg:tags":[
        "local",
        "authority"
    ],
    "wof:name":"Leith Primary School",
    "wof:placetype":"venue"
},
  "geometry": {"coordinates":[-3.168742,55.970764],"type":"Point"}
}