{
  "type": "Feature",
  "properties": {
    "iso:country":"GB",
    "sg:address":"19 Garrick Way",
    "sg:city":"Ipswich",
    "sg:classifiers":[
        {
            "category":"Food & Beverages",
            "subcategory":"Fruits & Vegetables",
            "type":"Retail Goods"
        }
    ],
    "sg:phone":"+44 1473 741010",
    "sg:postcode":"IP1 6NF",
    "sg:province":"Suffolk",
    "sg:tags":[
        "greengrocer"
    ],
    "wof:name":"P A Collings",
    "wof:placetype":"venue"
},
  "geometry": {"coordinates":[1.137876,52.080025],"type":"Point"}
}