{
  "type": "Feature",
  "properties": {
    "addr:full":"The Depot, Cess Road Great Yarmouth Norfolk NR29 4RF",
    "addr:postcode":"nr29 4rf",
    "addr:street":"Cess Road",
    "iso:country":"GB",
    "sg:address":"The Depot, Cess Road",
    "sg:city":"Great Yarmouth",
    "sg:classifiers":[
        {
            "category":"Sports & Exercise",
            "subcategory":"Swimming Pool",
            "type":"Entertainment"
        }
    ],
    "sg:postcode":"NR29 4RF",
    "sg:province":"Norfolk",
    "sg:tags":[
        "diver"
    ],
    "wof:name":"Durrant Port Diving Services",
    "wof:placetype":"venue"
},
  "geometry": {"coordinates":[1.6152499914,52.7061195374],"type":"Point"}
}