{
  "type": "Feature",
  "properties": {
    "addr:full":"The Kennels House, High Street Broadway Gloucestershire WR12 7DP",
    "addr:postcode":"wr12 7dp",
    "addr:street":"High Street",
    "iso:country":"GB",
    "sg:address":"The Kennels House, High Street",
    "sg:city":"Broadway",
    "sg:classifiers":[
        {
            "category":"Shopping",
            "subcategory":"Crafts & Fabrics",
            "type":"Retail Goods"
        }
    ],
    "sg:phone":"+44 1386 854808",
    "sg:postcode":"WR12 7DP",
    "sg:province":"Gloucestershire",
    "sg:tags":[
        "sewing",
        "centre"
    ],
    "wof:name":"Bobbins of Broadway",
    "wof:placetype":"venue"
},
  "geometry": {"coordinates":[-1.8505690098,52.0365638733],"type":"Point"}
}