{
  "type": "Feature",
  "properties": {
    "addr:full":"4 Winmarleigh Street Warrington Cheshire WA1 1NB",
    "addr:housenumber":"4",
    "addr:postcode":"wa1 1nb",
    "addr:street":"Winmarleigh Street",
    "iso:country":"GB",
    "sg:address":"4 Winmarleigh Street",
    "sg:city":"Warrington",
    "sg:classifiers":[
        {
            "category":"Professional",
            "type":"Services"
        }
    ],
    "sg:phone":"+44 1925 240856",
    "sg:postcode":"WA1 1NB",
    "sg:province":"Cheshire",
    "sg:tags":[
        "interior",
        "furnishers",
        "designer"
    ],
    "wof:name":"Innex Design",
    "wof:placetype":"venue"
},
  "geometry": {"coordinates":[-2.599228,53.388378],"type":"Point"}
}