{
  "type": "Feature",
  "properties": {
    "iso:country":"GB",
    "sg:address":"309 Station Rd",
    "sg:city":"Harrow",
    "sg:classifiers":[
        {
            "category":"Health Services",
            "subcategory":"Optometrist",
            "type":"Services"
        },
        {
            "category":"Shopping",
            "subcategory":"Optician",
            "type":"Retail Goods"
        }
    ],
    "sg:phone":"+44 20 8861 3725",
    "sg:postcode":"HA1 1LF",
    "sg:province":"Greater London",
    "sg:tags":[
        "ophthalmic"
    ],
    "wof:name":"Optical Express Ltd",
    "wof:placetype":"venue"
},
  "geometry": {"coordinates":[-0.333456,51.581593],"type":"Point"}
}