{
  "type": "Feature",
  "properties": {
    "addr:full":"2 Quoits Field, Claydon Ipswich Suffolk IP6 0AY",
    "addr:housenumber":"2",
    "addr:postcode":"ip6 0ay",
    "addr:street":"Quoits Field",
    "iso:country":"GB",
    "sg:address":"2 Quoits Field, Claydon",
    "sg:city":"Ipswich",
    "sg:classifiers":[
        {
            "category":"Utilities",
            "subcategory":"Fuel Oil & Lpg",
            "type":"Services"
        },
        {
            "category":"Manufacturing",
            "subcategory":"Musical Instruments",
            "type":"Manufacturing & Wholesale Goods"
        }
    ],
    "sg:phone":"+44 1473 830000",
    "sg:postcode":"IP6 0AY",
    "sg:province":"Suffolk",
    "sg:tags":[
        "gas",
        "agent",
        "manufacturer"
    ],
    "wof:name":"M R M Technical Services Ltd.",
    "wof:placetype":"venue"
},
  "geometry": {"coordinates":[1.110278,52.106472],"type":"Point"}
}