{
  "type": "Feature",
  "properties": {
    "addr:full":"14 Church Street, Treherbert Treorchy Rhondda, Cynon, Taff CF42 5PU",
    "addr:housenumber":"14",
    "addr:postcode":"cf42 5pu",
    "addr:street":"Church Street;Cynon Taff",
    "iso:country":"GB",
    "sg:address":"14 Church Street, Treherbert",
    "sg:city":"Treorchy",
    "sg:classifiers":[
        {
            "category":"Home & Garden",
            "subcategory":"Carpets & Floor Coverings",
            "type":"Retail Goods"
        }
    ],
    "sg:phone":"+44 1443 776257",
    "sg:postcode":"CF42 5PU",
    "sg:province":"Rhondda, Cynon, Taff",
    "sg:tags":[
        "carpets",
        "rug",
        "matting"
    ],
    "wof:name":"Wayne Lewis",
    "wof:placetype":"venue"
},
  "geometry": {"coordinates":[-3.533521,51.674896],"type":"Point"}
}