{
  "type": "Feature",
  "properties": {
    "addr:full":"173 Rannoch Rd Perth Perth and Kinross PH1 2DP",
    "addr:housenumber":"173",
    "addr:postcode":"ph1 2dp",
    "addr:street":"Rannoch Rd",
    "iso:country":"GB",
    "sg:address":"173 Rannoch Rd",
    "sg:city":"Perth",
    "sg:classifiers":[
        {
            "category":"Food & Beverages",
            "subcategory":"Meat & Fish",
            "type":"Retail Goods"
        }
    ],
    "sg:phone":"+44 1738 625592",
    "sg:postcode":"PH1 2DP",
    "sg:province":"Perth and Kinross",
    "sg:tags":[
        "chip"
    ],
    "wof:name":"Christines Chip Shop",
    "wof:placetype":"venue"
},
  "geometry": {"coordinates":[-3.4671258926,56.4012489319],"type":"Point"}
}