{
  "type": "Feature",
  "properties": {
    "iso:country":"GB",
    "sg:address":"Chiltongate Kennels, Bickley",
    "sg:city":"Tiverton",
    "sg:classifiers":[
        {
            "category":"Organizations",
            "subcategory":"Community Association",
            "type":"Services"
        },
        {
            "category":"Organizations",
            "subcategory":"Non-profit Organization",
            "type":"Services"
        }
    ],
    "sg:phone":"+44 1884 855291",
    "sg:postcode":"EX16 8RS",
    "sg:province":"Devon",
    "sg:tags":[
        "organisation",
        "care",
        "animal",
        "welfare"
    ],
    "wof:name":"Blue Cross Animal Welfare Centre",
    "wof:placetype":"venue"
},
  "geometry": {"coordinates":[-3.540184,50.842716],"type":"Point"}
}