{
  "type": "Feature",
  "properties": {
    "addr:full":"Penkyn Mill Lane, Fishbourne Chichester West Sussex PO19 3JN",
    "addr:postcode":"po19 3jn",
    "addr:street":"Mill Lane",
    "iso:country":"GB",
    "sg:address":"Penkyn Mill Lane, Fishbourne",
    "sg:city":"Chichester",
    "sg:classifiers":[
        {
            "category":"Professional",
            "subcategory":"Lawyer & Legal Services",
            "type":"Services"
        }
    ],
    "sg:phone":"+44 1243 531279",
    "sg:postcode":"PO19 3JN",
    "sg:province":"West Sussex",
    "sg:tags":[
        "solicitor"
    ],
    "wof:name":"Trafeco Ltd.",
    "wof:placetype":"venue"
},
  "geometry": {"coordinates":[-0.7754290104,50.8361663818],"type":"Point"}
}