{
  "type": "Feature",
  "properties": {
    "addr:full":"50 King Street Belper Derbyshire DE56 1PL",
    "addr:housenumber":"50",
    "addr:postcode":"de56 1pl",
    "addr:street":"King Street",
    "iso:country":"GB",
    "sg:address":"50 King Street",
    "sg:city":"Belper",
    "sg:classifiers":[
        {
            "category":"Health Services",
            "subcategory":"Optometrist",
            "type":"Services"
        }
    ],
    "sg:phone":"+44 1773 820744",
    "sg:postcode":"DE56 1PL",
    "sg:province":"Derbyshire",
    "sg:tags":[
        "optician"
    ],
    "wof:name":"J F Fell",
    "wof:placetype":"venue"
},
  "geometry": {"coordinates":[-1.481721,53.023132],"type":"Point"}
}