{
  "type": "Feature",
  "properties": {
    "iso:country":"GB",
    "sg:address":"Lower Breakish, Breakish",
    "sg:city":"Isle Of Skye",
    "sg:classifiers":[
        {
            "category":"Retail",
            "subcategory":"Storage",
            "type":"Services"
        }
    ],
    "sg:phone":"+44 1471 822777",
    "sg:postcode":"IV42 8QA",
    "sg:province":"Highland",
    "sg:tags":[
        "household",
        "removal"
    ],
    "wof:name":"Macdougalls the Auctioneers",
    "wof:placetype":"venue"
},
  "geometry": {"coordinates":[-5.85169,57.244148],"type":"Point"}
}