{
  "type": "Feature",
  "properties": {
    "addr:full":"52-56 Minories London Greater London EC3N 1JJ",
    "addr:housenumber":"52-56",
    "addr:postcode":"ec3n 1jj",
    "addr:street":"Minories",
    "iso:country":"GB",
    "sg:address":"52-56 Minories",
    "sg:city":"London",
    "sg:classifiers":[
        {
            "category":"Insurance",
            "subcategory":"Insurance Agent",
            "type":"Services"
        }
    ],
    "sg:phone":"+44 20 7480 6622",
    "sg:postcode":"EC3N 1JJ",
    "sg:province":"Greater London",
    "sg:tags":[
        "broker"
    ],
    "wof:name":"P W S International Ltd.",
    "wof:placetype":"venue"
},
  "geometry": {"coordinates":[-0.0751110017,51.5114822388],"type":"Point"}
}