{
  "type": "Feature",
  "properties": {
    "addr:full":"Station Garage, High Road Cookham Maidenhead Berkshire SL6 9HR",
    "addr:postcode":"sl6 9hr",
    "addr:street":"High Road",
    "iso:country":"GB",
    "sg:address":"Station Garage, High Road Cookham",
    "sg:city":"Maidenhead",
    "sg:classifiers":[
        {
            "category":"Retail",
            "subcategory":"Auto Repair",
            "type":"Services"
        }
    ],
    "sg:phone":"+44 1628 520371",
    "sg:postcode":"SL6 9HR",
    "sg:province":"Berkshire",
    "sg:tags":[
        "modification",
        "garage"
    ],
    "wof:name":"D & W Autos",
    "wof:placetype":"venue"
},
  "geometry": {"coordinates":[-0.707164,51.557995],"type":"Point"}
}