{
  "type": "Feature",
  "properties": {
    "addr:full":"136 Dean Road South Shields Tyne and Wear NE33 4AW",
    "addr:housenumber":"136",
    "addr:postcode":"ne33 4aw",
    "addr:street":"Dean Road",
    "iso:country":"GB",
    "sg:address":"136 Dean Road",
    "sg:city":"South Shields",
    "sg:classifiers":[
        {
            "category":"Home & Garden",
            "subcategory":"Household Appliances",
            "type":"Retail Goods"
        }
    ],
    "sg:phone":"+44 191 454 3700",
    "sg:postcode":"NE33 4AW",
    "sg:province":"Tyne and Wear",
    "sg:tags":[
        "domestic",
        "centre"
    ],
    "wof:name":"Dean Road Appliances",
    "wof:placetype":"venue"
},
  "geometry": {"coordinates":[-1.42875,54.986652],"type":"Point"}
}