{
  "type": "Feature",
  "properties": {
    "iso:country":"GB",
    "sg:address":"6 South Walk",
    "sg:city":"Basildon",
    "sg:classifiers":[
        {
            "category":"Personal",
            "subcategory":"Beauty Salon",
            "type":"Services"
        }
    ],
    "sg:phone":"+44 1268 272737",
    "sg:postcode":"SS14 1BZ",
    "sg:province":"Essex",
    "sg:tags":[
        "unisex",
        "hairdresser"
    ],
    "wof:name":"Amanda Balchin",
    "wof:placetype":"venue"
},
  "geometry": {"coordinates":[0.4953570068,51.5677642822],"type":"Point"}
}