{
  "type": "Feature",
  "properties": {
    "addr:full":"Studio 17-19 Cocker Av Cwmbran Monmouthshire NP44 7JL",
    "addr:housenumber":"17-19",
    "addr:postcode":"np44 7jl",
    "addr:street":"Cocker Av",
    "iso:country":"GB",
    "sg:address":"Studio 17-19 Cocker Av",
    "sg:city":"Cwmbran",
    "sg:classifiers":[
        {
            "category":"Retail",
            "subcategory":"Portrait Studio",
            "type":"Services"
        },
        {
            "category":"Professional",
            "subcategory":"Art Services",
            "type":"Services"
        }
    ],
    "sg:phone":"+44 1633 874631",
    "sg:postcode":"NP44 7JL",
    "sg:province":"Monmouthshire",
    "sg:tags":[
        "photographer",
        "commercial"
    ],
    "wof:name":"Alastair Cunnington",
    "wof:placetype":"venue"
},
  "geometry": {"coordinates":[-3.025864,51.657467],"type":"Point"}
}