{
  "type": "Feature",
  "properties": {
    "addr:full":"57 Canford Cliffs Rd Poole Dorset BH13 7AQ",
    "addr:housenumber":"57",
    "addr:postcode":"bh13 7aq",
    "addr:street":"Canford Cliffs Rd",
    "iso:country":"GB",
    "sg:address":"57 Canford Cliffs Rd",
    "sg:city":"Poole",
    "sg:classifiers":[
        {
            "category":"Shopping",
            "subcategory":"Pharmacy",
            "type":"Retail Goods"
        }
    ],
    "sg:phone":"+44 1202 706359",
    "sg:postcode":"BH13 7AQ",
    "sg:province":"Dorset",
    "sg:tags":[
        "toiletry"
    ],
    "wof:name":"Tower Health Products Ltd",
    "wof:placetype":"venue"
},
  "geometry": {"coordinates":[-1.925651,50.714649],"type":"Point"}
}