{
  "type": "Feature",
  "properties": {
    "addr:full":"129 East High Street Forfar Angus DD8 2EQ",
    "addr:housenumber":"129",
    "addr:postcode":"dd8 2eq",
    "addr:street":"East High Street",
    "iso:country":"GB",
    "sg:address":"129 East High Street",
    "sg:city":"Forfar",
    "sg:classifiers":[
        {
            "category":"Home & Garden",
            "subcategory":"Carpets & Floor Coverings",
            "type":"Retail Goods"
        }
    ],
    "sg:postcode":"DD8 2EQ",
    "sg:province":"Angus",
    "sg:tags":[
        "carpets",
        "rug",
        "matting"
    ],
    "wof:name":"Mac's Floor Coverings",
    "wof:placetype":"venue"
},
  "geometry": {"coordinates":[-2.88353,56.645496],"type":"Point"}
}