{
  "type": "Feature",
  "properties": {
    "addr:full":"Club House, Links Drive Totteridge London Greater London N20 8QU",
    "addr:postcode":"n20 8qu",
    "addr:street":"Club;Links Drive",
    "iso:country":"GB",
    "sg:address":"Club House, Links Drive Totteridge",
    "sg:city":"London",
    "sg:classifiers":[
        {
            "category":"Professional",
            "type":"Services"
        }
    ],
    "sg:phone":"+44 20 8445 0117",
    "sg:postcode":"N20 8QU",
    "sg:province":"Greater London",
    "sg:tags":[
        "caterer"
    ],
    "wof:name":"South Herts Golf Club",
    "wof:placetype":"venue"
},
  "geometry": {"coordinates":[-0.18845,51.632751],"type":"Point"}
}