{
  "type": "Feature",
  "properties": {
    "iso:country":"GB",
    "sg:address":"135 Gelderd Road",
    "sg:city":"Leeds",
    "sg:classifiers":[
        {
            "category":"Professional",
            "subcategory":"Art Services",
            "type":"Services"
        }
    ],
    "sg:phone":"+44 113 251 1450",
    "sg:postcode":"LS12 6BE",
    "sg:province":"West Yorkshire",
    "sg:tags":[
        "decorating",
        "painting"
    ],
    "wof:name":"Mosley Stone Ltd.",
    "wof:placetype":"venue"
},
  "geometry": {"coordinates":[-1.574806,53.78455],"type":"Point"}
}