{
  "type": "Feature",
  "properties": {
    "addr:full":"85 Ealing Road Brentford Greater London TW8 0LQ",
    "addr:housenumber":"85",
    "addr:postcode":"tw8 0lq",
    "addr:street":"Ealing Road",
    "iso:country":"GB",
    "sg:address":"85 Ealing Road",
    "sg:city":"Brentford",
    "sg:classifiers":[
        {
            "category":"Personal",
            "subcategory":"Beauty Salon",
            "type":"Services"
        }
    ],
    "sg:phone":"+44 20 8560 2335",
    "sg:postcode":"TW8 0LQ",
    "sg:province":"Greater London",
    "sg:tags":[
        "ladies",
        "lady",
        "hairdresser"
    ],
    "wof:name":"Valerie",
    "wof:placetype":"venue"
},
  "geometry": {"coordinates":[-0.3007659912,51.487613678],"type":"Point"}
}