{
  "type": "Feature",
  "properties": {
    "iso:country":"GB",
    "sg:address":"85 Ealing Road",
    "sg:city":"Brentford",
    "sg:classifiers":[
        {
            "category":"Personal",
            "subcategory":"Beauty Salon",
            "type":"Services"
        }
    ],
    "sg:phone":"+44 20 8560 2335",
    "sg:postcode":"TW8 0LQ",
    "sg:province":"Greater London",
    "sg:tags":[
        "ladies",
        "lady",
        "hairdresser"
    ],
    "wof:name":"Valerie",
    "wof:placetype":"venue"
},
  "geometry": {"coordinates":[-0.3007659912,51.487613678],"type":"Point"}
}