{
  "type": "Feature",
  "properties": {
    "addr:full":"44 Uxbridge Street London Greater London W8 7TG",
    "addr:housenumber":"44",
    "addr:postcode":"w8 7tg",
    "addr:street":"Uxbridge Street",
    "iso:country":"GB",
    "sg:address":"44 Uxbridge Street",
    "sg:city":"London",
    "sg:classifiers":[
        {
            "category":"Arts & Performance",
            "subcategory":"Art Gallery",
            "type":"Entertainment"
        }
    ],
    "sg:postcode":"W8 7TG",
    "sg:province":"Greater London",
    "wof:name":"Dreamtime Gallery Ltd.",
    "wof:placetype":"venue"
},
  "geometry": {"coordinates":[-0.196679,51.508583],"type":"Point"}
}