{
  "type": "Feature",
  "properties": {
    "addr:full":"Wordswoth House, Ticehurst Wadhurst East Sussex TN5 7BQ",
    "addr:postcode":"tn5 7bq",
    "addr:street":"Ticehurst",
    "iso:country":"GB",
    "sg:address":"Wordswoth House, Ticehurst",
    "sg:city":"Wadhurst",
    "sg:classifiers":[
        {
            "category":"Home & Garden",
            "subcategory":"Household Appliances",
            "type":"Retail Goods"
        },
        {
            "category":"Communications",
            "subcategory":"News Services",
            "type":"Services"
        }
    ],
    "sg:phone":"+44 1580 201000",
    "sg:postcode":"TN5 7BQ",
    "sg:province":"East Sussex",
    "sg:tags":[
        "domestic",
        "journalist",
        "centre"
    ],
    "wof:name":"D L P Communications",
    "wof:placetype":"venue"
},
  "geometry": {"coordinates":[0.372834,51.029148],"type":"Point"}
}