{
  "type": "Feature",
  "properties": {
    "iso:country":"GB",
    "sg:address":"9 Silverdale, Lancaster Rd",
    "sg:city":"Southport",
    "sg:classifiers":[
        {
            "category":"Professional",
            "subcategory":"Accounting & Tax Preparation",
            "type":"Services"
        }
    ],
    "sg:phone":"+44 1704 550911",
    "sg:postcode":"PR8 2LF",
    "sg:province":"Lancashire",
    "sg:tags":[
        "accountant",
        "chartered"
    ],
    "wof:name":"Roger Fieldhouse FCA FCMA CPFA",
    "wof:placetype":"venue"
},
  "geometry": {"coordinates":[-3.006304,53.647915],"type":"Point"}
}