{
  "type": "Feature",
  "properties": {
    "iso:country":"GB",
    "sg:address":"Bengeworth Fields House, Badsey Rd",
    "sg:city":"Evesham",
    "sg:classifiers":[
        {
            "category":"Social Services",
            "subcategory":"Retirement Home",
            "type":"Services"
        }
    ],
    "sg:phone":"+44 1386 446861",
    "sg:postcode":"WR11 5PA",
    "sg:province":"Gloucestershire",
    "sg:tags":[
        "residential",
        "care"
    ],
    "wof:name":"Bengeworth Field Rest Home",
    "wof:placetype":"venue"
},
  "geometry": {"coordinates":[-1.925472,52.091934],"type":"Point"}
}