{
  "type": "Feature",
  "properties": {
    "iso:country":"GB",
    "sg:address":"49 Moorburn Rd",
    "sg:city":"Largs",
    "sg:classifiers":[
        {
            "category":"Home & Garden",
            "subcategory":"Household Appliances",
            "type":"Retail Goods"
        }
    ],
    "sg:postcode":"KA30 9DD",
    "sg:province":"North Ayrshire",
    "sg:tags":[
        "electrical"
    ],
    "wof:name":"McDonald,Robert,",
    "wof:placetype":"venue"
},
  "geometry": {"coordinates":[-4.859873,55.799992],"type":"Point"}
}