{
  "type": "Feature",
  "properties": {
    "addr:full":"Station Road Morecambe Lancashire LA4 5JL",
    "addr:postcode":"la4 5jl",
    "addr:street":"Station Road",
    "iso:country":"GB",
    "sg:address":"Station Road",
    "sg:city":"Morecambe",
    "sg:classifiers":[
        {
            "category":"Education",
            "subcategory":"School",
            "type":"Public Place"
        }
    ],
    "sg:postcode":"LA4 5JL",
    "sg:province":"Lancashire",
    "sg:tags":[
        "local",
        "authority"
    ],
    "wof:name":"Lancashire County Council",
    "wof:placetype":"venue"
},
  "geometry": {"coordinates":[-2.8615179062,54.0721321106],"type":"Point"}
}