{
  "type": "Feature",
  "properties": {
    "addr:full":"18 Spey Drive, Rothes Aberlour Moray AB38 7BY",
    "addr:housenumber":"18",
    "addr:postcode":"ab38 7by",
    "addr:street":"Spey Drive",
    "iso:country":"GB",
    "sg:address":"18 Spey Drive, Rothes",
    "sg:city":"Aberlour",
    "sg:classifiers":[
        {
            "category":"Professional",
            "subcategory":"Engineering",
            "type":"Services"
        },
        {
            "category":"Building & Trades",
            "subcategory":"Electrical",
            "type":"Services"
        }
    ],
    "sg:phone":"+44 1340 831406",
    "sg:postcode":"AB38 7BY",
    "sg:province":"Moray",
    "sg:tags":[
        "engineer",
        "electrician",
        "contractor"
    ],
    "wof:name":"G M KELMAN",
    "wof:placetype":"venue"
},
  "geometry": {"coordinates":[-3.2055709362,57.525718689],"type":"Point"}
}