{
  "type": "Feature",
  "properties": {
    "addr:full":"Field Terrace Leeds West Yorkshire LS15 7RE",
    "addr:postcode":"ls15 7re",
    "addr:street":"Field Terrace",
    "iso:country":"GB",
    "sg:address":"Field Terrace",
    "sg:city":"Leeds",
    "sg:classifiers":[
        {
            "category":"Social Services",
            "type":"Services"
        }
    ],
    "sg:postcode":"LS15 7RE",
    "sg:province":"West Yorkshire",
    "wof:name":"Pinfolds",
    "wof:placetype":"venue"
},
  "geometry": {"coordinates":[-1.4655740261,53.7997894287],"type":"Point"}
}