{
  "type": "Feature",
  "properties": {
    "iso:country":"GB",
    "sg:address":"474 Hatfield Road",
    "sg:city":"St Albans",
    "sg:classifiers":[
        {
            "category":"Professional",
            "subcategory":"Engineering",
            "type":"Services"
        },
        {
            "category":"Shopping",
            "subcategory":"Computers & Home Electronics",
            "type":"Retail Goods"
        },
        {
            "category":"Organizations",
            "subcategory":"Membership Organization",
            "type":"Services"
        }
    ],
    "sg:phone":"+44 845 130 4021",
    "sg:postcode":"AL4 0XS",
    "sg:province":"Hertfordshire",
    "sg:tags":[
        "mnfr",
        "intercom",
        "system",
        "contractor",
        "electrical",
        "engineer"
    ],
    "wof:name":"Anchor Sound & Security",
    "wof:placetype":"venue"
},
  "geometry": {"coordinates":[-0.292634,51.751324],"type":"Point"}
}