{
  "type": "Feature",
  "properties": {
    "iso:country":"GB",
    "sg:address":"West House, 11 High Street",
    "sg:city":"Burnham-on-crouch",
    "sg:classifiers":[
        {
            "category":"Shopping",
            "subcategory":"Department Store",
            "type":"Retail Goods"
        },
        {
            "category":"Shopping",
            "subcategory":"Crafts & Fabrics",
            "type":"Retail Goods"
        }
    ],
    "sg:phone":"+44 1621 782375",
    "sg:postcode":"CM0 8AG",
    "sg:province":"Essex",
    "sg:tags":[
        "shop",
        "needlecraft",
        "wool",
        "retailer"
    ],
    "wof:name":"The Spinning Wheel",
    "wof:placetype":"venue"
},
  "geometry": {"coordinates":[0.815427,51.63184],"type":"Point"}
}