{
  "type": "Feature",
  "properties": {
    "addr:full":"Summit Close Southwell Industrial Estate, Kirkby In Ashfield Nottingham Nottinghamshire NG17 8GJ",
    "addr:housenumber":"estate",
    "addr:postcode":"ng17 8gj",
    "addr:street":"Summit Close;Industrial;In Ashfield",
    "iso:country":"GB",
    "sg:address":"Summit Close Southwell Industrial Estate, Kirkby In Ashfield",
    "sg:city":"Nottingham",
    "sg:classifiers":[
        {
            "category":"Professional",
            "subcategory":"Engineering",
            "type":"Services"
        },
        {
            "category":"Bus Stop",
            "subcategory":"None",
            "type":"Transportation"
        }
    ],
    "sg:phone":"+44 1623 721721",
    "sg:postcode":"NG17 8GJ",
    "sg:province":"Nottinghamshire",
    "sg:tags":[
        "filter",
        "electrical",
        "engineer"
    ],
    "wof:name":"Wycliff Services Ltd.",
    "wof:placetype":"venue"
},
  "geometry": {"coordinates":[-1.253229022,53.1073951721],"type":"Point"}
}