{
  "type": "Feature",
  "properties": {
    "iso:country":"GB",
    "sg:address":"104 West Av",
    "sg:city":"Halifax",
    "sg:classifiers":[
        {
            "category":"Retail",
            "subcategory":"Storage",
            "type":"Services"
        }
    ],
    "sg:phone":"+44 1422 205184",
    "sg:postcode":"HX3 8TJ",
    "sg:province":"West Yorkshire",
    "sg:tags":[
        "household",
        "removal"
    ],
    "wof:name":"R & M Transport",
    "wof:placetype":"venue"
},
  "geometry": {"coordinates":[-1.788015008,53.7234611511],"type":"Point"}
}