{
  "type": "Feature",
  "properties": {
    "iso:country":"GB",
    "sg:address":"Elmfield Hall, Gatty Park, Highburn Road Church",
    "sg:city":"Accrington",
    "sg:classifiers":[
        {
            "category":"Organizations",
            "subcategory":"Membership Organization",
            "type":"Services"
        }
    ],
    "sg:postcode":"BB5 4AE",
    "sg:province":"Lancashire",
    "sg:tags":[
        "club"
    ],
    "wof:name":"Church Central Residents Association",
    "wof:placetype":"venue"
},
  "geometry": {"coordinates":[-2.38802,53.754425],"type":"Point"}
}