{
  "type": "Feature",
  "properties": {
    "addr:full":"1 Fisher Street Carlisle Cumbria CA3 8RR",
    "addr:housenumber":"1",
    "addr:postcode":"ca3 8rr",
    "addr:street":"Fisher Street",
    "iso:country":"GB",
    "sg:address":"1 Fisher Street",
    "sg:city":"Carlisle",
    "sg:classifiers":[
        {
            "category":"Real Estate",
            "subcategory":"Surveying",
            "type":"Services"
        }
    ],
    "sg:phone":"+44 1228 591131",
    "sg:postcode":"CA3 8RR",
    "sg:province":"Cumbria",
    "sg:tags":[
        "building",
        "surveyor"
    ],
    "wof:name":"Peter Fall Cowie Associates",
    "wof:placetype":"venue"
},
  "geometry": {"coordinates":[-2.9385530949,54.8964767456],"type":"Point"}
}