{
  "type": "Feature",
  "properties": {
    "iso:country":"GB",
    "sg:address":"131 High Street, Great Ayton",
    "sg:city":"Middlesbrough",
    "sg:classifiers":[
        {
            "category":"Shopping",
            "subcategory":"Pharmacy",
            "type":"Retail Goods"
        }
    ],
    "sg:phone":"+44 1642 722254",
    "sg:postcode":"TS9 6BW",
    "sg:province":"North Yorkshire",
    "sg:tags":[
        "pharmacist",
        "dispensing",
        "chemist"
    ],
    "wof:name":"D Cooper Pharmacy Ltd",
    "wof:placetype":"venue"
},
  "geometry": {"coordinates":[-1.13251,54.488617],"type":"Point"}
}