{
  "type": "Feature",
  "properties": {
    "addr:full":"60a George Street Edinburgh City of Edinburgh EH2 2LR",
    "addr:housenumber":"60a",
    "addr:postcode":"eh2 2lr",
    "addr:street":"George Street",
    "iso:country":"GB",
    "sg:address":"60a George Street",
    "sg:city":"Edinburgh",
    "sg:classifiers":[
        {
            "category":"Personal",
            "type":"Services"
        },
        {
            "category":"Sports & Exercise",
            "subcategory":"Playing Field",
            "type":"Entertainment"
        }
    ],
    "sg:phone":"+44 131 225 6250",
    "sg:postcode":"EH2 2LR",
    "sg:province":"City of Edinburgh",
    "sg:tags":[
        "club",
        "slimming",
        "product"
    ],
    "wof:name":"National Slimming Centre",
    "wof:placetype":"venue"
},
  "geometry": {"coordinates":[-3.1991360188,55.9530067444],"type":"Point"}
}