{
  "type": "Feature",
  "properties": {
    "addr:full":"17 Andalus Road, Clapham North London Greater London SW9 9PQ",
    "addr:housenumber":"17",
    "addr:postcode":"sw9 9pq",
    "addr:street":"Andalus Road",
    "iso:country":"GB",
    "sg:address":"17 Andalus Road, Clapham North",
    "sg:city":"London",
    "sg:classifiers":[
        {
            "category":"Professional",
            "subcategory":"Computer Services",
            "type":"Services"
        }
    ],
    "sg:postcode":"SW9 9PQ",
    "sg:province":"Greater London",
    "sg:tags":[
        "system",
        "software"
    ],
    "wof:name":"Stylemost Ltd",
    "wof:placetype":"venue"
},
  "geometry": {"coordinates":[-0.125003,51.465221],"type":"Point"}
}