{
  "type": "Feature",
  "properties": {
    "addr:full":"102 Cross Arthurlie Street, Barrhead Glasgow East Ayrshire G78 1EB",
    "addr:housenumber":"102",
    "addr:postcode":"g78 1eb",
    "addr:street":"Cross Arthurlie Street",
    "iso:country":"GB",
    "sg:address":"102 Cross Arthurlie Street, Barrhead",
    "sg:city":"Glasgow",
    "sg:classifiers":[
        {
            "category":"Professional",
            "subcategory":"Lawyer & Legal Services",
            "type":"Services"
        }
    ],
    "sg:phone":"+44 141 880 8448",
    "sg:postcode":"G78 1EB",
    "sg:province":"East Ayrshire",
    "sg:tags":[
        "solicitor"
    ],
    "wof:name":"Bilkus & Boyle",
    "wof:placetype":"venue"
},
  "geometry": {"coordinates":[-4.397755,55.801495],"type":"Point"}
}