{
  "type": "Feature",
  "properties": {
    "iso:country":"GB",
    "sg:address":"66a Lowesmoor",
    "sg:city":"Worcester",
    "sg:classifiers":[
        {
            "category":"Manufacturing",
            "subcategory":"Signs",
            "type":"Manufacturing & Wholesale Goods"
        }
    ],
    "sg:phone":"+44 1905 616115",
    "sg:postcode":"WR1 2SE",
    "sg:province":"Worcestershire",
    "sg:tags":[
        "writer"
    ],
    "wof:name":"Sign Shop (Worcester) Ltd The",
    "wof:placetype":"venue"
},
  "geometry": {"coordinates":[-2.2169229984,52.1945877075],"type":"Point"}
}