{
  "type": "Feature",
  "properties": {
    "iso:country":"GB",
    "sg:address":"2 Gisburn Rd",
    "sg:city":"Colne",
    "sg:classifiers":[
        {
            "category":"Home & Garden",
            "subcategory":"Carpets & Floor Coverings",
            "type":"Retail Goods"
        }
    ],
    "sg:phone":"+44 1282 850770",
    "sg:postcode":"BB8 5HH",
    "sg:province":"Lancashire",
    "sg:tags":[
        "carpets",
        "rug",
        "matting"
    ],
    "wof:name":"Victoria Carpets Barlick",
    "wof:placetype":"venue"
},
  "geometry": {"coordinates":[-2.188725,53.919025],"type":"Point"}
}