{
  "type": "Feature",
  "properties": {
    "addr:full":"Warehouse Mylord Crescent, Camperdown Industrial Estate Kil Newcastle-upon-tyne Tyne and Wear NE12 6SP",
    "addr:postcode":"ne12 6sp",
    "addr:street":"Mylord Crescent;Industrial Estate",
    "iso:country":"GB",
    "sg:address":"Warehouse Mylord Crescent, Camperdown Industrial Estate Kil",
    "sg:city":"Newcastle-upon-tyne",
    "sg:classifiers":[
        {
            "category":"Structure",
            "subcategory":"Warehouse",
            "type":"Public Place"
        }
    ],
    "sg:phone":"+44 191 268 2007",
    "sg:postcode":"NE12 6SP",
    "sg:province":"Tyne and Wear",
    "wof:name":"Fenwick Ltd.",
    "wof:placetype":"venue"
},
  "geometry": {"coordinates":[-1.5628340244,55.0426750183],"type":"Point"}
}