{
  "type": "Feature",
  "properties": {
    "addr:full":"Unit 4 Smallwood Mill, Martins Moss, Smallwood Sandbach Cheshire CW11 2UW",
    "addr:housenumber":"unit 4",
    "addr:postcode":"cw11 2uw",
    "addr:street":"Smallwood Mill Martins Moss",
    "iso:country":"GB",
    "sg:address":"Unit 4 Smallwood Mill, Martins Moss, Smallwood",
    "sg:city":"Sandbach",
    "sg:classifiers":[
        {
            "category":"Manufacturing",
            "subcategory":"Electronics",
            "type":"Manufacturing & Wholesale Goods"
        }
    ],
    "sg:phone":"+44 1477 500449",
    "sg:postcode":"CW11 2UW",
    "sg:province":"Cheshire",
    "sg:tags":[
        "printed",
        "circuit"
    ],
    "wof:name":"Lloyd Doyle Ltd.",
    "wof:placetype":"venue"
},
  "geometry": {"coordinates":[-2.2913239002,53.1378250122],"type":"Point"}
}