{
  "type": "Feature",
  "properties": {
    "addr:full":"2 Osborne Av Hexham Northumberland NE46 3JP",
    "addr:housenumber":"2",
    "addr:postcode":"ne46 3jp",
    "addr:street":"Osborne Av",
    "iso:country":"GB",
    "sg:address":"2 Osborne Av",
    "sg:city":"Hexham",
    "sg:classifiers":[
        {
            "category":"Professional",
            "subcategory":"Computer Services",
            "type":"Services"
        }
    ],
    "sg:phone":"+44 1434 608003",
    "sg:postcode":"NE46 3JP",
    "sg:province":"Northumberland",
    "sg:tags":[
        "system",
        "software"
    ],
    "wof:name":"Almandyne Ltd",
    "wof:placetype":"venue"
},
  "geometry": {"coordinates":[-2.1136550903,54.9725456238],"type":"Point"}
}