{
  "type": "Feature",
  "properties": {
    "iso:country":"GB",
    "sg:address":"142 Macdonald Road",
    "sg:city":"Lightwater",
    "sg:classifiers":[
        {
            "category":"Professional",
            "subcategory":"Engineering",
            "type":"Services"
        },
        {
            "category":"Freight",
            "type":"Transportation"
        },
        {
            "category":"Building & Trades",
            "subcategory":"Construction",
            "type":"Services"
        }
    ],
    "sg:phone":"+44 1276 451161",
    "sg:postcode":"GU18 5YA",
    "sg:province":"Surrey",
    "sg:tags":[
        "civil",
        "weighbridge",
        "engineer",
        "public",
        "contractor"
    ],
    "wof:name":"Thomas Construction",
    "wof:placetype":"venue"
},
  "geometry": {"coordinates":[-0.679464,51.347878],"type":"Point"}
}