{
  "type": "Feature",
  "properties": {
    "addr:full":"Unit E7/8, Stonehill Business Pk, Angel Rd London Greater London N18 3LD",
    "addr:housenumber":"8",
    "addr:postcode":"n18 3ld",
    "addr:street":"Stonehill Business Pk Angel Rd",
    "iso:country":"GB",
    "sg:address":"Unit E7/8, Stonehill Business Pk, Angel Rd",
    "sg:city":"London",
    "sg:classifiers":[
        {
            "category":"Professional",
            "subcategory":"Management & Consulting",
            "type":"Services"
        }
    ],
    "sg:postcode":"N18 3LD",
    "sg:province":"Greater London",
    "sg:tags":[
        "consultant",
        "business"
    ],
    "wof:name":"Churchill Business Services Ltd",
    "wof:placetype":"venue"
},
  "geometry": {"coordinates":[-0.038089,51.610424],"type":"Point"}
}