{
  "type": "Feature",
  "properties": {
    "addr:full":"21 Pembroke Avenue Enfield Greater London EN1 4HD",
    "addr:housenumber":"21",
    "addr:postcode":"en1 4hd",
    "addr:street":"Pembroke Avenue",
    "iso:country":"GB",
    "sg:address":"21 Pembroke Avenue",
    "sg:city":"Enfield",
    "sg:classifiers":[
        {
            "category":"Retail",
            "subcategory":"Driving School",
            "type":"Services"
        }
    ],
    "sg:phone":"+44 20 8804 7771",
    "sg:postcode":"EN1 4HD",
    "sg:province":"Greater London",
    "wof:name":"Merrick School Of Motoring",
    "wof:placetype":"venue"
},
  "geometry": {"coordinates":[-0.0526730008,51.6609153748],"type":"Point"}
}