{
  "type": "Feature",
  "properties": {
    "addr:full":"Ardath Road, Kings Norton Birmingham West Midlands B38 9PN",
    "addr:postcode":"b38 9pn",
    "addr:street":"Ardath Road",
    "iso:country":"GB",
    "sg:address":"Ardath Road, Kings Norton",
    "sg:city":"Birmingham",
    "sg:classifiers":[
        {
            "category":"Professional",
            "subcategory":"Engineering",
            "type":"Services"
        }
    ],
    "sg:phone":"+44 121 433 3444",
    "sg:postcode":"B38 9PN",
    "sg:province":"West Midlands",
    "wof:name":"Metalrax Group Services Ltd.",
    "wof:placetype":"venue"
},
  "geometry": {"coordinates":[-1.921829,52.407784],"type":"Point"}
}