{
  "type": "Feature",
  "properties": {
    "addr:full":"191 The Vale London Greater London W3 7QS",
    "addr:housenumber":"191",
    "addr:postcode":"w3 7qs",
    "addr:street":"The Vale",
    "iso:country":"GB",
    "sg:address":"191 The Vale",
    "sg:city":"London",
    "sg:classifiers":[
        {
            "category":"Shopping",
            "subcategory":"Mobile Phones",
            "type":"Retail Goods"
        }
    ],
    "sg:phone":"+44 20 8740 4444",
    "sg:postcode":"W3 7QS",
    "sg:province":"Greater London",
    "wof:name":"Spectrum Communications Ltd",
    "wof:placetype":"venue"
},
  "geometry": {"coordinates":[-0.2586840093,51.5063247681],"type":"Point"}
}