{
  "type": "Feature",
  "properties": {
    "addr:full":"Foxbury Stables, Woodside Road, Lower Woodside Luton Bedfordshire LU1 4DQ",
    "addr:postcode":"lu1 4dq",
    "addr:street":"Woodside Road Lower",
    "iso:country":"GB",
    "sg:address":"Foxbury Stables, Woodside Road, Lower Woodside",
    "sg:city":"Luton",
    "sg:classifiers":[
        {
            "category":"Sports & Exercise",
            "subcategory":"Stables",
            "type":"Entertainment"
        },
        {
            "category":"Personal",
            "subcategory":"Adult",
            "type":"Services"
        }
    ],
    "sg:phone":"+44 1582 724049",
    "sg:postcode":"LU1 4DQ",
    "sg:province":"Bedfordshire",
    "sg:tags":[
        "education",
        "equestrian"
    ],
    "wof:name":"Foxbury Stables & Stud",
    "wof:placetype":"venue"
},
  "geometry": {"coordinates":[-0.435402,51.86232],"type":"Point"}
}