{
  "type": "Feature",
  "properties": {
    "iso:country":"GB",
    "sg:address":"26 Winckley Square",
    "sg:city":"Preston",
    "sg:classifiers":[
        {
            "category":"Professional",
            "subcategory":"Employment Agencies",
            "type":"Services"
        }
    ],
    "sg:postcode":"PR1 3JJ",
    "sg:province":"Lancashire",
    "sg:tags":[
        "consultant"
    ],
    "wof:name":"Capital Recruitment (Manchester) Ltd.",
    "wof:placetype":"venue"
},
  "geometry": {"coordinates":[-2.702178,53.755882],"type":"Point"}
}