{
  "type": "Feature",
  "properties": {
    "addr:full":"7 St Wilfrids Court Doncaster South Yorkshire DN4 6ED",
    "addr:housenumber":"7",
    "addr:postcode":"dn4 6ed",
    "addr:street":"St Wilfrids Court",
    "iso:country":"GB",
    "sg:address":"7 St Wilfrids Court",
    "sg:city":"Doncaster",
    "sg:classifiers":[
        {
            "category":"Shopping",
            "subcategory":"Pharmacy",
            "type":"Retail Goods"
        }
    ],
    "sg:phone":"+44 1302 535522",
    "sg:postcode":"DN4 6ED",
    "sg:province":"South Yorkshire",
    "sg:tags":[
        "pharmacist",
        "chemist"
    ],
    "wof:name":"H I Welldrick",
    "wof:placetype":"venue"
},
  "geometry": {"coordinates":[-1.0895539522,53.5131759644],"type":"Point"}
}