{
  "type": "Feature",
  "properties": {
    "addr:full":"Wells Road, Radstock Bath Somerset BA3 3SA",
    "addr:postcode":"ba3 3sa",
    "addr:street":"Wells Road",
    "iso:country":"GB",
    "sg:address":"Wells Road, Radstock",
    "sg:city":"Bath",
    "sg:classifiers":[
        {
            "category":"Shopping",
            "subcategory":"Department Store",
            "type":"Retail Goods"
        }
    ],
    "sg:postcode":"BA3 3SA",
    "sg:province":"Somerset",
    "wof:name":"Wells Road Stores",
    "wof:placetype":"venue"
},
  "geometry": {"coordinates":[-2.4383490086,51.2910118103],"type":"Point"}
}