{
  "type": "Feature",
  "properties": {
    "addr:full":"Wavendon Road, Salford Milton Keynes Bedfordshire MK17 8AZ",
    "addr:postcode":"mk17 8az",
    "addr:street":"Wavendon Road",
    "iso:country":"GB",
    "sg:address":"Wavendon Road, Salford",
    "sg:city":"Milton Keynes",
    "sg:classifiers":[
        {
            "category":"Travel",
            "subcategory":"Hotels & Motels",
            "type":"Entertainment"
        }
    ],
    "sg:phone":"+44 1908 583117",
    "sg:postcode":"MK17 8AZ",
    "sg:province":"Bedfordshire",
    "wof:name":"Red Lion Hotel",
    "wof:placetype":"venue"
},
  "geometry": {"coordinates":[-0.6366860271,52.0431365967],"type":"Point"}
}