{
  "type": "Feature",
  "properties": {
    "addr:full":"Unit 2 Walton-on-thames Surrey KT12 1QB",
    "addr:housenumber":"unit 2",
    "addr:postcode":"kt12 1qb",
    "iso:country":"GB",
    "sg:address":"Unit 2",
    "sg:city":"Walton-on-thames",
    "sg:classifiers":[
        {
            "category":"Shopping",
            "subcategory":"Bicycles & Sporting Goods",
            "type":"Retail Goods"
        }
    ],
    "sg:postcode":"KT12 1QB",
    "sg:province":"Surrey",
    "sg:tags":[
        "cycle",
        "accessory"
    ],
    "wof:name":"Walton Computers Ltd.",
    "wof:placetype":"venue"
},
  "geometry": {"coordinates":[-0.4408200085,51.3842811584],"type":"Point"}
}