{
  "type": "Feature",
  "properties": {
    "iso:country":"GB",
    "sg:address":"2 Silver Street",
    "sg:city":"Kettering",
    "sg:classifiers":[
        {
            "category":"Real Estate",
            "subcategory":"Real Estate Agent",
            "type":"Services"
        }
    ],
    "sg:phone":"+44 1536 312945",
    "sg:postcode":"NN16 0BN",
    "sg:province":"Northamptonshire",
    "wof:name":"Lucas Estate Agents",
    "wof:placetype":"venue"
},
  "geometry": {"coordinates":[-0.7259010077,52.4002990723],"type":"Point"}
}