{
  "type": "Feature",
  "properties": {
    "iso:country":"GB",
    "sg:address":"Unit 3 Saxon Way, Battledown Industrial Estate",
    "sg:city":"Cheltenham",
    "sg:classifiers":[
        {
            "category":"Shopping",
            "subcategory":"Computers & Home Electronics",
            "type":"Retail Goods"
        }
    ],
    "sg:phone":"+44 1242 224832",
    "sg:postcode":"GL52 6QX",
    "sg:province":"Gloucestershire",
    "sg:tags":[
        "mnfr",
        "system",
        "intercom"
    ],
    "wof:name":"K Jones Technical Services",
    "wof:placetype":"venue"
},
  "geometry": {"coordinates":[-2.05866,51.895302],"type":"Point"}
}