{
  "type": "Feature",
  "properties": {
    "iso:country":"GB",
    "sg:address":"25 Garden Walk",
    "sg:city":"Royston",
    "sg:classifiers":[
        {
            "category":"Building & Trades",
            "subcategory":"Construction",
            "type":"Services"
        }
    ],
    "sg:phone":"+44 1763 244586",
    "sg:postcode":"SG8 7HP",
    "sg:province":"Bedfordshire",
    "sg:tags":[
        "builder"
    ],
    "wof:name":"C F Grantham",
    "wof:placetype":"venue"
},
  "geometry": {"coordinates":[-0.017402,52.051456],"type":"Point"}
}