{
  "type": "Feature",
  "properties": {
    "addr:full":"Kingsbury Square Melksham Wiltshire SN12 6HL",
    "addr:postcode":"sn12 6hl",
    "addr:street":"Kingsbury Square",
    "iso:country":"GB",
    "sg:address":"Kingsbury Square",
    "sg:city":"Melksham",
    "sg:classifiers":[
        {
            "category":"Retail",
            "subcategory":"Auto Repair",
            "type":"Services"
        }
    ],
    "sg:phone":"+44 1225 709055",
    "sg:postcode":"SN12 6HL",
    "sg:province":"Wiltshire",
    "sg:tags":[
        "body",
        "car"
    ],
    "wof:name":"Impact Body Repairs",
    "wof:placetype":"venue"
},
  "geometry": {"coordinates":[-2.1374089718,51.3700141907],"type":"Point"}
}