{
  "type": "Feature",
  "properties": {
    "iso:country":"GB",
    "sg:address":"Bowithick Quarry",
    "sg:city":"Tintagel",
    "sg:classifiers":[
        {
            "category":"Utilities",
            "subcategory":"Refuse",
            "type":"Services"
        }
    ],
    "sg:phone":"+44 1840 770778",
    "sg:postcode":"PL34 0HH",
    "sg:province":"Cornwall",
    "sg:tags":[
        "disposal",
        "waste",
        "retail"
    ],
    "wof:name":"County Environmental Services Ltd.",
    "wof:placetype":"venue"
},
  "geometry": {"coordinates":[-4.744604,50.662922],"type":"Point"}
}