{
  "type": "Feature",
  "properties": {
    "iso:country":"GB",
    "sg:address":"Unit 2,north Town Trad Est, North La",
    "sg:city":"Aldershot",
    "sg:classifiers":[
        {
            "category":"Shopping",
            "subcategory":"Beauty & Cosmetics",
            "type":"Retail Goods"
        }
    ],
    "sg:postcode":"GU12 4QN",
    "sg:province":"Hampshire",
    "sg:tags":[
        "equipment",
        "supply",
        "hairdressing"
    ],
    "wof:name":"Capital (Hair & Beauty) Ltd",
    "wof:placetype":"venue"
},
  "geometry": {"coordinates":[-0.7413399816,51.2470207214],"type":"Point"}
}