{
  "type": "Feature",
  "properties": {
    "addr:full":"26 Whitley Rd Whitley Bay Northumberland NE26 2NF",
    "addr:housenumber":"26",
    "addr:postcode":"ne26 2nf",
    "addr:street":"Whitley Rd",
    "iso:country":"GB",
    "sg:address":"26 Whitley Rd",
    "sg:city":"Whitley Bay",
    "sg:classifiers":[
        {
            "category":"Health Services",
            "subcategory":"Health Practitioner",
            "type":"Services"
        }
    ],
    "sg:phone":"+44 191 252 5650",
    "sg:postcode":"NE26 2NF",
    "sg:province":"Northumberland",
    "sg:tags":[
        "osteopath"
    ],
    "wof:name":"J C Dent",
    "wof:placetype":"venue"
},
  "geometry": {"coordinates":[-1.436151,55.039028],"type":"Point"}
}