{
  "type": "Feature",
  "properties": {
    "iso:country":"GB",
    "sg:address":"Upper Roadside Farm, Templeton",
    "sg:city":"Narberth",
    "sg:classifiers":[
        {
            "category":"Travel",
            "subcategory":"Hotels & Motels",
            "type":"Entertainment"
        },
        {
            "category":"Farming",
            "subcategory":"Livestock Farm",
            "type":"Manufacturing & Wholesale Goods"
        }
    ],
    "sg:postcode":"SA67 8DA",
    "sg:province":"Carmarthenshire",
    "sg:tags":[
        "house",
        "guest",
        "others"
    ],
    "wof:name":"D A & S C Crowley",
    "wof:placetype":"venue"
},
  "geometry": {"coordinates":[-4.736468792,51.7715835571],"type":"Point"}
}