{
  "type": "Feature",
  "properties": {
    "addr:full":"Barugh Farm, Waverton Wigton Cumbria CA7 0AW",
    "addr:postcode":"ca7 0aw",
    "iso:country":"GB",
    "sg:address":"Barugh Farm, Waverton",
    "sg:city":"Wigton",
    "sg:classifiers":[
        {
            "category":"Farming",
            "subcategory":"Livestock Farm",
            "type":"Manufacturing & Wholesale Goods"
        }
    ],
    "sg:phone":"+44 16973 42580",
    "sg:postcode":"CA7 0AW",
    "sg:province":"Cumbria",
    "sg:tags":[
        "others"
    ],
    "wof:name":"W Hodgson",
    "wof:placetype":"venue"
},
  "geometry": {"coordinates":[-3.2053899765,54.8169937134],"type":"Point"}
}