{
  "type": "Feature",
  "properties": {
    "iso:country":"GB",
    "sg:address":"7 Sunbury Road",
    "sg:city":"Birmingham",
    "sg:classifiers":[
        {
            "category":"Food & Beverages",
            "subcategory":"Meat & Fish",
            "type":"Retail Goods"
        }
    ],
    "sg:postcode":"B31 4LL",
    "sg:province":"West Midlands",
    "sg:tags":[
        "butcher"
    ],
    "wof:name":"Choice Cuts",
    "wof:placetype":"venue"
},
  "geometry": {"coordinates":[-1.9798649549,52.3954353333],"type":"Point"}
}