{
  "type": "Feature",
  "properties": {
    "addr:full":"Unit L5, Cherrycourt Way Leighton Buzzard Bedfordshire LU7 4UH",
    "addr:housenumber":"l5",
    "addr:postcode":"lu7 4uh",
    "addr:street":"Cherrycourt Way",
    "iso:country":"GB",
    "sg:address":"Unit L5, Cherrycourt Way",
    "sg:city":"Leighton Buzzard",
    "sg:classifiers":[
        {
            "category":"Professional",
            "subcategory":"Art Services",
            "type":"Services"
        }
    ],
    "sg:phone":"+44 1525 378888",
    "sg:postcode":"LU7 4UH",
    "sg:province":"Bedfordshire",
    "sg:tags":[
        "model",
        "maker"
    ],
    "wof:name":"F E Phelps Models Ltd.",
    "wof:placetype":"venue"
},
  "geometry": {"coordinates":[-0.635334,51.915813],"type":"Point"}
}