{
  "type": "Feature",
  "properties": {
    "addr:full":"Farringdon House, 105/107 Farringdon Road London Greater London EC1R 3BT",
    "addr:housenumber":"105 / 107",
    "addr:postcode":"ec1r 3bt",
    "addr:street":"Farringdon Road",
    "iso:country":"GB",
    "sg:address":"Farringdon House, 105/107 Farringdon Road",
    "sg:city":"London",
    "sg:classifiers":[
        {
            "category":"Government",
            "subcategory":"Post Office",
            "type":"Public Place"
        }
    ],
    "sg:phone":"+44 20 7491 3320",
    "sg:postcode":"EC1R 3BT",
    "sg:province":"Greater London",
    "sg:tags":[
        "organisation",
        "soc",
        "research"
    ],
    "wof:name":"Kenmar Research Ltd.",
    "wof:placetype":"venue"
},
  "geometry": {"coordinates":[-0.1076629981,51.5226173401],"type":"Point"}
}