{
  "type": "Feature",
  "properties": {
    "addr:full":"20 Knockholt Chase Greenhithe Kent DA9 9EN",
    "addr:housenumber":"20",
    "addr:postcode":"da9 9en",
    "addr:street":"Knockholt Chase",
    "iso:country":"GB",
    "sg:address":"20 Knockholt Chase",
    "sg:city":"Greenhithe",
    "sg:classifiers":[
        {
            "category":"Coffee & Tea",
            "type":"Food & Drink"
        }
    ],
    "sg:phone":"+44 1322 387217",
    "sg:postcode":"DA9 9EN",
    "sg:province":"Kent",
    "wof:name":"Bewleys Countryside Coffee",
    "wof:placetype":"venue"
},
  "geometry": {"coordinates":[0.2783890069,51.4502983093],"type":"Point"}
}