{
  "type": "Feature",
  "properties": {
    "addr:full":"83 New Street, Mapplewell Barnsley South Yorkshire S75 6EL",
    "addr:housenumber":"83",
    "addr:postcode":"s75 6el",
    "addr:street":"New Street;Yorkshire",
    "iso:country":"GB",
    "sg:address":"83 New Street, Mapplewell",
    "sg:city":"Barnsley",
    "sg:classifiers":[
        {
            "category":"Wholesale",
            "subcategory":"Office Equipment",
            "type":"Manufacturing & Wholesale Goods"
        }
    ],
    "sg:phone":"+44 1226 388325",
    "sg:postcode":"S75 6EL",
    "sg:province":"South Yorkshire",
    "sg:tags":[
        "partition",
        "cubicle"
    ],
    "wof:name":"Acoustic Installations Ltd.",
    "wof:placetype":"venue"
},
  "geometry": {"coordinates":[-1.5067919493,53.5883789062],"type":"Point"}
}