{
  "type": "Feature",
  "properties": {
    "addr:full":"11 Maiden Lane London Greater London WC2E 7NA",
    "addr:housenumber":"11",
    "addr:postcode":"wc2e 7na",
    "addr:street":"Maiden Lane",
    "iso:country":"GB",
    "sg:address":"11 Maiden Lane",
    "sg:city":"London",
    "sg:classifiers":[
        {
            "category":"Communications",
            "type":"Services"
        }
    ],
    "sg:postcode":"WC2E 7NA",
    "sg:province":"Greater London",
    "sg:tags":[
        "data",
        "network"
    ],
    "wof:name":"H2g2 Ltd.",
    "wof:placetype":"venue"
},
  "geometry": {"coordinates":[-0.1227239966,51.510723114],"type":"Point"}
}