{
  "type": "Feature",
  "properties": {
    "iso:country":"GB",
    "sg:address":"1 New Tythe Street, Long Eaton",
    "sg:city":"Nottingham",
    "sg:classifiers":[
        {
            "category":"Home & Garden",
            "subcategory":"Hardware",
            "type":"Retail Goods"
        }
    ],
    "sg:phone":"+44 115 946 5510",
    "sg:postcode":"NG10 2DL",
    "sg:province":"Derbyshire",
    "sg:tags":[
        "compressor",
        "air"
    ],
    "wof:name":"Air Cat Ltd.",
    "wof:placetype":"venue"
},
  "geometry": {"coordinates":[-1.264599,52.896488],"type":"Point"}
}