{
  "type": "Feature",
  "properties": {
    "addr:full":"26 Lidget St Huddersfield West Yorkshire HD3 3JP",
    "addr:housenumber":"26",
    "addr:postcode":"hd3 3jp",
    "addr:street":"Lidget St",
    "iso:country":"GB",
    "sg:address":"26 Lidget St",
    "sg:city":"Huddersfield",
    "sg:classifiers":[
        {
            "category":"Shopping",
            "subcategory":"Department Store",
            "type":"Retail Goods"
        },
        {
            "category":"Shopping",
            "subcategory":"Crafts & Fabrics",
            "type":"Retail Goods"
        }
    ],
    "sg:postcode":"HD3 3JP",
    "sg:province":"West Yorkshire",
    "sg:tags":[
        "shop",
        "needlecraft",
        "wool"
    ],
    "wof:name":"Janes,Joy,",
    "wof:placetype":"venue"
},
  "geometry": {"coordinates":[-1.8237270117,53.6609954834],"type":"Point"}
}