{
  "type": "Feature",
  "properties": {
    "addr:full":"Lynn Road, Chittering Ely Cambridgeshire CB6 1SA",
    "addr:postcode":"cb6 1sa",
    "addr:street":"Lynn Road",
    "iso:country":"GB",
    "sg:address":"Lynn Road, Chittering",
    "sg:city":"Ely",
    "sg:classifiers":[
        {
            "category":"Shopping",
            "subcategory":"Bicycles & Sporting Goods",
            "type":"Retail Goods"
        }
    ],
    "sg:phone":"+44 1353 667627",
    "sg:postcode":"CB6 1SA",
    "sg:province":"Cambridgeshire",
    "sg:tags":[
        "cycle",
        "accessory"
    ],
    "wof:name":"J T Cycles",
    "wof:placetype":"venue"
},
  "geometry": {"coordinates":[0.2748000026,52.4221000671],"type":"Point"}
}