{
  "type": "Feature",
  "properties": {
    "iso:country":"GB",
    "sg:address":"24 Ten Ashes Lane, Cofton Hacket, Rednal",
    "sg:city":"Birmingham",
    "sg:classifiers":[
        {
            "category":"Manufacturing",
            "subcategory":"Metals",
            "type":"Manufacturing & Wholesale Goods"
        }
    ],
    "sg:phone":"+44 121 445 3476",
    "sg:postcode":"B45 8PE",
    "sg:province":"West Midlands",
    "wof:name":"Doxmead Ltd.",
    "wof:placetype":"venue"
},
  "geometry": {"coordinates":[-1.9986510277,52.379524231],"type":"Point"}
}