{
  "type": "Feature",
  "properties": {
    "iso:country":"GB",
    "sg:address":"96 Milnbank Street",
    "sg:city":"Glasgow",
    "sg:classifiers":[
        {
            "category":"Banks & Credit Unions",
            "subcategory":"Financial Services",
            "type":"Services"
        }
    ],
    "sg:phone":"+44 141 556 7691",
    "sg:postcode":"G31 3AL",
    "sg:province":"Glasgow City",
    "sg:tags":[
        "consultant"
    ],
    "wof:name":"Lenzie Finance Co. Ltd.",
    "wof:placetype":"venue"
},
  "geometry": {"coordinates":[-4.221101,55.865032],"type":"Point"}
}