{
  "type": "Feature",
  "properties": {
    "iso:country":"GB",
    "sg:address":"Bruern Farm",
    "sg:city":"Chipping Norton",
    "sg:classifiers":[
        {
            "category":"Farming",
            "subcategory":"Livestock Farm",
            "type":"Manufacturing & Wholesale Goods"
        }
    ],
    "sg:phone":"+44 1993 830387",
    "sg:postcode":"OX7 6QA",
    "sg:province":"Gloucestershire",
    "sg:tags":[
        "others"
    ],
    "wof:name":"David W Astor",
    "wof:placetype":"venue"
},
  "geometry": {"coordinates":[-1.617659,51.870052],"type":"Point"}
}