{
  "type": "Feature",
  "properties": {
    "iso:country":"GB",
    "sg:address":"5 Downscroft Gardens",
    "sg:city":"Southampton",
    "sg:classifiers":[
        {
            "category":"Retail",
            "subcategory":"Repair Shop",
            "type":"Services"
        }
    ],
    "sg:phone":"+44 1489 788522",
    "sg:postcode":"SO30 4RR",
    "sg:province":"Hampshire",
    "sg:tags":[
        "maintenance"
    ],
    "wof:name":"Magpie Property Services",
    "wof:placetype":"venue"
},
  "geometry": {"coordinates":[-1.3078769445,50.9187698364],"type":"Point"}
}