{
  "type": "Feature",
  "properties": {
    "iso:country":"GB",
    "sg:address":"19 Tennyson Avenue",
    "sg:city":"Grays",
    "sg:classifiers":[
        {
            "category":"Recreation",
            "subcategory":"Water Park",
            "type":"Entertainment"
        }
    ],
    "sg:phone":"+44 1375 391888",
    "sg:postcode":"RM17 5RG",
    "sg:province":"Essex",
    "sg:tags":[
        "keg",
        "drums",
        "cask"
    ],
    "wof:name":"Benfleet Container Services",
    "wof:placetype":"venue"
},
  "geometry": {"coordinates":[0.333439,51.487747],"type":"Point"}
}