{
  "type": "Feature",
  "properties": {
    "iso:country":"GB",
    "sg:address":"1 Atlantic Quay, Broomielaw",
    "sg:city":"Glasgow",
    "sg:classifiers":[
        {
            "category":"Professional",
            "subcategory":"Management & Consulting",
            "type":"Services"
        }
    ],
    "sg:phone":"+44 141 248 2128",
    "sg:postcode":"G2 8JE",
    "sg:province":"Glasgow City",
    "sg:tags":[
        "consultant",
        "business"
    ],
    "wof:name":"Project Management International",
    "wof:placetype":"venue"
},
  "geometry": {"coordinates":[-4.2617,55.857101],"type":"Point"}
}