{
  "type": "Feature",
  "properties": {
    "addr:full":"Old Station Road Loughton Essex IG10 4PE",
    "addr:postcode":"ig10 4pe",
    "addr:street":"Old Station Road",
    "iso:country":"GB",
    "sg:address":"Old Station Road",
    "sg:city":"Loughton",
    "sg:classifiers":[
        {
            "category":"Autos & Motor Vehicles",
            "subcategory":"Automobile Sales",
            "type":"Retail Goods"
        }
    ],
    "sg:phone":"+44 20 8508 9121",
    "sg:postcode":"IG10 4PE",
    "sg:province":"Essex",
    "sg:tags":[
        "car"
    ],
    "wof:name":"A. & D. STEVENSON (TRADING) LTD",
    "wof:placetype":"venue"
},
  "geometry": {"coordinates":[0.0542050004,51.642791748],"type":"Point"}
}