{
  "type": "Feature",
  "properties": {
    "addr:full":"Railway Station Driffield East Riding of Yorkshire YO25 6PX",
    "addr:postcode":"yo25 6px",
    "iso:country":"GB",
    "sg:address":"Railway Station",
    "sg:city":"Driffield",
    "sg:classifiers":[
        {
            "category":"Bars & Pubs",
            "type":"Food & Drink"
        }
    ],
    "sg:phone":"+44 1377 254421",
    "sg:postcode":"YO25 6PX",
    "sg:province":"East Riding of Yorkshire",
    "sg:tags":[
        "pubs",
        "inn"
    ],
    "wof:name":"The Sidings",
    "wof:placetype":"venue"
},
  "geometry": {"coordinates":[-0.436299,54.008968],"type":"Point"}
}