{
  "type": "Feature",
  "properties": {
    "addr:full":"56-57 Catherine Street Swansea Neath Port Talbot SA1 4JS",
    "addr:housenumber":"56-57",
    "addr:postcode":"sa1 4js",
    "addr:street":"Catherine Street",
    "iso:country":"GB",
    "sg:address":"56-57 Catherine Street",
    "sg:city":"Swansea",
    "sg:classifiers":[
        {
            "category":"Transit Center",
            "subcategory":"Freight",
            "type":"Transportation"
        }
    ],
    "sg:postcode":"SA1 4JS",
    "sg:province":"Neath Port Talbot",
    "sg:tags":[
        "shop",
        "craft",
        "centre"
    ],
    "wof:name":"Craft Workshops",
    "wof:placetype":"venue"
},
  "geometry": {"coordinates":[-3.957469,51.617908],"type":"Point"}
}