{
  "type": "Feature",
  "properties": {
    "addr:full":"Fen Farm, Wabendon Milton Keynes Bedfordshire MK17 8AA",
    "addr:postcode":"mk17 8aa",
    "iso:country":"GB",
    "sg:address":"Fen Farm, Wabendon",
    "sg:city":"Milton Keynes",
    "sg:classifiers":[
        {
            "category":"Freight",
            "type":"Transportation"
        }
    ],
    "sg:phone":"+44 1908 281261",
    "sg:postcode":"MK17 8AA",
    "sg:province":"Bedfordshire",
    "sg:tags":[
        "haulage",
        "road"
    ],
    "wof:name":"R & B Commercials Ltd.",
    "wof:placetype":"venue"
},
  "geometry": {"coordinates":[-0.727749,52.005856],"type":"Point"}
}