{
  "type": "Feature",
  "properties": {
    "iso:country":"GB",
    "sg:address":"25 Glenhill Close, Finchley",
    "sg:city":"London",
    "sg:classifiers":[
        {
            "category":"Professional",
            "subcategory":"Accounting & Tax Preparation",
            "type":"Services"
        }
    ],
    "sg:postcode":"N3 2JS",
    "sg:province":"Greater London",
    "sg:tags":[
        "accountant"
    ],
    "wof:name":"Kingston Contracts Ltd",
    "wof:placetype":"venue"
},
  "geometry": {"coordinates":[-0.1919459999,51.5983428955],"type":"Point"}
}