{
  "type": "Feature",
  "properties": {
    "addr:full":"41 Trinity Close London Greater London E11 4RP",
    "addr:housenumber":"41",
    "addr:postcode":"e11 4rp",
    "addr:street":"Trinity Close",
    "iso:country":"GB",
    "sg:address":"41 Trinity Close",
    "sg:city":"London",
    "sg:classifiers":[
        {
            "category":"Health Services",
            "subcategory":"Clinic",
            "type":"Services"
        }
    ],
    "sg:phone":"+44 20 8539 8565",
    "sg:postcode":"E11 4RP",
    "sg:province":"Greater London",
    "sg:tags":[
        "nh"
    ],
    "wof:name":"Granleigh Health Clinic",
    "wof:placetype":"venue"
},
  "geometry": {"coordinates":[0.008463,51.563217],"type":"Point"}
}