{
  "type": "Feature",
  "properties": {
    "iso:country":"GB",
    "sg:address":"Derby Youth Justice Team, The Mt, 4 Albany Rd",
    "sg:city":"Derby",
    "sg:classifiers":[
        {
            "category":"Social Services",
            "type":"Services"
        }
    ],
    "sg:postcode":"DE22 3LW",
    "sg:province":"Derbyshire",
    "wof:name":"Derby City Council",
    "wof:placetype":"venue"
},
  "geometry": {"coordinates":[-1.50362,52.916691],"type":"Point"}
}