{
  "type": "Feature",
  "properties": {
    "iso:country":"GB",
    "sg:address":"Sparable Lane",
    "sg:city":"Wakefield",
    "sg:classifiers":[
        {
            "category":"Education",
            "subcategory":"Library",
            "type":"Public Place"
        },
        {
            "category":"Government",
            "subcategory":"Office",
            "type":"Public Place"
        }
    ],
    "sg:phone":"+44 1924 303355",
    "sg:postcode":"WF1 5NG",
    "sg:province":"West Yorkshire",
    "sg:tags":[
        "book",
        "local"
    ],
    "wof:name":"Sandal Library",
    "wof:placetype":"venue"
},
  "geometry": {"coordinates":[-1.485833,53.667625],"type":"Point"}
}