{
  "type": "Feature",
  "properties": {
    "iso:country":"GB",
    "sg:address":"Eddystone House, Aberderfyn Rd, Johnstown",
    "sg:city":"Wrexham",
    "sg:classifiers":[
        {
            "category":"Professional",
            "subcategory":"Accounting & Tax Preparation",
            "type":"Services"
        }
    ],
    "sg:phone":"+44 1978 846609",
    "sg:postcode":"LL14 1PB",
    "sg:province":"Wrexham",
    "sg:tags":[
        "accountant"
    ],
    "wof:name":"Hills Accountants & Registered Auditors",
    "wof:placetype":"venue"
},
  "geometry": {"coordinates":[-3.04804,53.012325],"type":"Point"}
}