{
  "type": "Feature",
  "properties": {
    "addr:full":"Bangalore, Church Lane Hastings East Sussex TN35 4QB",
    "addr:postcode":"tn35 4qb",
    "addr:street":"Church Lane",
    "iso:country":"GB",
    "sg:address":"Bangalore, Church Lane",
    "sg:city":"Hastings",
    "sg:classifiers":[
        {
            "category":"Professional",
            "subcategory":"Management & Consulting",
            "type":"Services"
        }
    ],
    "sg:postcode":"TN35 4QB",
    "sg:province":"East Sussex",
    "sg:tags":[
        "consultant",
        "business"
    ],
    "wof:name":"Neat Consultants Ltd.",
    "wof:placetype":"venue"
},
  "geometry": {"coordinates":[0.5751399994,50.9092597961],"type":"Point"}
}