{
  "type": "Feature",
  "properties": {
    "iso:country":"GB",
    "sg:address":"Wear View Farm, Hamsterley",
    "sg:city":"Bishop Auckland",
    "sg:classifiers":[
        {
            "category":"Farming",
            "subcategory":"Livestock Farm",
            "type":"Manufacturing & Wholesale Goods"
        },
        {
            "category":"Professional",
            "subcategory":"Art Services",
            "type":"Services"
        }
    ],
    "sg:phone":"+44 1388 488486",
    "sg:postcode":"DL13 3NG",
    "sg:province":"Durham",
    "sg:tags":[
        "decorator",
        "painter",
        "others"
    ],
    "wof:name":"R & E COATSWORTH",
    "wof:placetype":"venue"
},
  "geometry": {"coordinates":[-1.818031,54.674576],"type":"Point"}
}