{
  "type": "Feature",
  "properties": {
    "iso:country":"GB",
    "sg:address":"1518 Stratford Road, Hall Grn",
    "sg:city":"Birmingham",
    "sg:classifiers":[
        {
            "category":"Shopping",
            "subcategory":"Department Store",
            "type":"Retail Goods"
        }
    ],
    "sg:phone":"+44 121 733 8688",
    "sg:postcode":"B28 9ET",
    "sg:province":"West Midlands",
    "wof:name":"The Stitchery",
    "wof:placetype":"venue"
},
  "geometry": {"coordinates":[-1.8349920511,52.4213523865],"type":"Point"}
}