{
  "type": "Feature",
  "properties": {
    "addr:full":"1 Hedley Road St Albans Hertfordshire AL1 5JL",
    "addr:housenumber":"1",
    "addr:postcode":"al1 5jl",
    "addr:street":"Hedley Road",
    "iso:country":"GB",
    "sg:address":"1 Hedley Road",
    "sg:city":"St Albans",
    "sg:classifiers":[
        {
            "category":"Manufacturing",
            "subcategory":"Metals",
            "type":"Manufacturing & Wholesale Goods"
        }
    ],
    "sg:postcode":"AL1 5JL",
    "sg:province":"Hertfordshire",
    "sg:tags":[
        "work",
        "sheet"
    ],
    "wof:name":"P S M Dunbar & Co.",
    "wof:placetype":"venue"
},
  "geometry": {"coordinates":[-0.3089779913,51.7500991821],"type":"Point"}
}