{
  "type": "Feature",
  "properties": {
    "addr:full":"Southampton Row, 6 Victoria Colonnade London Greater London WC1B 5HP",
    "addr:housenumber":"6",
    "addr:postcode":"wc1b 5hp",
    "addr:street":"Southampton;Victoria Colonnade",
    "iso:country":"GB",
    "sg:address":"Southampton Row, 6 Victoria Colonnade",
    "sg:city":"London",
    "sg:classifiers":[
        {
            "category":"Retail",
            "subcategory":"Photofinishing",
            "type":"Services"
        }
    ],
    "sg:phone":"+44 20 7831 5114",
    "sg:postcode":"WC1B 5HP",
    "sg:province":"Greater London",
    "sg:tags":[
        "photographic",
        "processor"
    ],
    "wof:name":"Photomill Ltd.",
    "wof:placetype":"venue"
},
  "geometry": {"coordinates":[-0.12212,51.51915],"type":"Point"}
}