{
  "type": "Feature",
  "properties": {
    "iso:country":"GB",
    "sg:address":"81 Garamonde Drive, Wymbush",
    "sg:city":"Milton Keynes",
    "sg:classifiers":[
        {
            "category":"Professional",
            "type":"Services"
        }
    ],
    "sg:phone":"+44 1908 265374",
    "sg:postcode":"MK8 8DD",
    "sg:province":"Buckinghamshire",
    "sg:tags":[
        "repair",
        "tech",
        "maintenance"
    ],
    "wof:name":"Centronic Services",
    "wof:placetype":"venue"
},
  "geometry": {"coordinates":[-0.798649013,52.0441627502],"type":"Point"}
}