{
  "type": "Feature",
  "properties": {
    "addr:full":"30 Longtye Drive Whitstable Kent CT5 3NF",
    "addr:housenumber":"30",
    "addr:postcode":"ct5 3nf",
    "addr:street":"Longtye Drive",
    "iso:country":"GB",
    "sg:address":"30 Longtye Drive",
    "sg:city":"Whitstable",
    "sg:classifiers":[
        {
            "category":"Building & Trades",
            "subcategory":"Plumbing",
            "type":"Services"
        }
    ],
    "sg:postcode":"CT5 3NF",
    "sg:province":"Kent",
    "sg:tags":[
        "heating"
    ],
    "wof:name":"David A Larkins",
    "wof:placetype":"venue"
},
  "geometry": {"coordinates":[1.0606620312,51.3477096558],"type":"Point"}
}