{
  "type": "Feature",
  "properties": {
    "addr:full":"Sabden Medical Centre, Whalley Rd Clitheroe Lancashire BB7 9DZ",
    "addr:postcode":"bb7 9dz",
    "addr:street":"Whalley Rd",
    "iso:country":"GB",
    "sg:address":"Sabden Medical Centre, Whalley Rd",
    "sg:city":"Clitheroe",
    "sg:classifiers":[
        {
            "category":"Health Services",
            "subcategory":"Doctor",
            "type":"Services"
        }
    ],
    "sg:phone":"+44 1282 772045",
    "sg:postcode":"BB7 9DZ",
    "sg:province":"Lancashire",
    "sg:tags":[
        "practitioners"
    ],
    "wof:name":"Smith, B",
    "wof:placetype":"venue"
},
  "geometry": {"coordinates":[-2.4065639973,53.8223686218],"type":"Point"}
}