{
  "type": "Feature",
  "properties": {
    "addr:full":"465 Glossop Road Sheffield South Yorkshire S10 2QE",
    "addr:housenumber":"465",
    "addr:postcode":"s10 2qe",
    "addr:street":"Glossop Road",
    "iso:country":"GB",
    "sg:address":"465 Glossop Road",
    "sg:city":"Sheffield",
    "sg:classifiers":[
        {
            "category":"Fast Food",
            "type":"Food & Drink"
        }
    ],
    "sg:phone":"+44 114 268 2529",
    "sg:postcode":"S10 2QE",
    "sg:province":"South Yorkshire",
    "sg:tags":[
        "away",
        "take"
    ],
    "wof:name":"Nibbles Pizza",
    "wof:placetype":"venue"
},
  "geometry": {"coordinates":[-1.50058,53.376621],"type":"Point"}
}