{
  "type": "Feature",
  "properties": {
    "iso:country":"GB",
    "sg:address":"26a Village Road, West Kirby",
    "sg:city":"Wirral",
    "sg:classifiers":[
        {
            "category":"Retail",
            "subcategory":"Auto Repair",
            "type":"Services"
        }
    ],
    "sg:phone":"+44 151 625 7984",
    "sg:postcode":"CH48 3JW",
    "sg:province":"Merseyside",
    "sg:tags":[
        "modification",
        "garage"
    ],
    "wof:name":"D & M Motors",
    "wof:placetype":"venue"
},
  "geometry": {"coordinates":[-3.1742470264,53.3678779602],"type":"Point"}
}