{
  "type": "Feature",
  "properties": {
    "addr:full":"43-49 Minerva Road, Park Royal Willesden Greater London NW10 6HJ",
    "addr:housenumber":"43-49",
    "addr:postcode":"nw10 6hj",
    "addr:street":"Minerva Road",
    "iso:country":"GB",
    "sg:address":"43-49 Minerva Road, Park Royal",
    "sg:city":"Willesden",
    "sg:classifiers":[
        {
            "category":"Banks & Credit Unions",
            "subcategory":"Bureau De Change",
            "type":"Services"
        }
    ],
    "sg:phone":"+44 20 8961 7595",
    "sg:postcode":"NW10 6HJ",
    "sg:province":"Greater London",
    "sg:tags":[
        "overseas",
        "removal"
    ],
    "wof:name":"A G S London Ltd",
    "wof:placetype":"venue"
},
  "geometry": {"coordinates":[-0.2634600103,51.5291519165],"type":"Point"}
}