{
  "type": "Feature",
  "properties": {
    "iso:country":"GB",
    "sg:address":"253 Barnsley Road, Sandal",
    "sg:city":"Wakefield",
    "sg:classifiers":[
        {
            "category":"Place Of Worship",
            "type":"Public Place"
        }
    ],
    "sg:phone":"+44 1924 254558",
    "sg:postcode":"WF1 5NU",
    "sg:province":"West Yorkshire",
    "wof:name":"Sandal Methodist Church",
    "wof:placetype":"venue"
},
  "geometry": {"coordinates":[-1.485901,53.665668],"type":"Point"}
}