{
  "type": "Feature",
  "properties": {
    "iso:country":"GB",
    "sg:address":"Doncaster Rd",
    "sg:city":"Rotherham",
    "sg:classifiers":[
        {
            "category":"Social Services",
            "subcategory":"Retirement Home",
            "type":"Services"
        }
    ],
    "sg:phone":"+44 1709 382334",
    "sg:postcode":"S65 1NN",
    "sg:province":"South Yorkshire",
    "sg:tags":[
        "residential",
        "care"
    ],
    "wof:name":"Beech Cliffe Residential Home",
    "wof:placetype":"venue"
},
  "geometry": {"coordinates":[-1.345704,53.433006],"type":"Point"}
}