{
  "type": "Feature",
  "properties": {
    "iso:country":"GB",
    "sg:address":"63 Laurel Road",
    "sg:city":"Plymouth",
    "sg:classifiers":[
        {
            "category":"Building & Trades",
            "subcategory":"Plumbing",
            "type":"Services"
        }
    ],
    "sg:phone":"+44 1752 564466",
    "sg:postcode":"PL2 2QD",
    "sg:province":"Devon",
    "sg:tags":[
        "central",
        "heating"
    ],
    "wof:name":"G P Plumbing",
    "wof:placetype":"venue"
},
  "geometry": {"coordinates":[-4.166393,50.393223],"type":"Point"}
}