{
  "type": "Feature",
  "properties": {
    "iso:country":"GB",
    "sg:address":"1 Shortbridge Street",
    "sg:city":"Llanidloes",
    "sg:classifiers":[
        {
            "category":"Home & Garden",
            "subcategory":"Household Appliances",
            "type":"Retail Goods"
        }
    ],
    "sg:phone":"+44 1686 412295",
    "sg:postcode":"SY18 6AD",
    "sg:province":"Powys",
    "sg:tags":[
        "electrical",
        "domestic"
    ],
    "wof:name":"W H Price",
    "wof:placetype":"venue"
},
  "geometry": {"coordinates":[-3.540368,52.448662],"type":"Point"}
}