{
  "type": "Feature",
  "properties": {
    "addr:full":"Haywood Farm, Haywood Lane, Cheswardine Market Drayton Shropshire TF9 2LW",
    "addr:postcode":"tf9 2lw",
    "addr:street":"Haywood Lane",
    "iso:country":"GB",
    "sg:address":"Haywood Farm, Haywood Lane, Cheswardine",
    "sg:city":"Market Drayton",
    "sg:classifiers":[
        {
            "category":"Farming",
            "subcategory":"Farm",
            "type":"Manufacturing & Wholesale Goods"
        }
    ],
    "sg:phone":"+44 1630 661205",
    "sg:postcode":"TF9 2LW",
    "sg:province":"Shropshire",
    "sg:tags":[
        "mixed",
        "crop"
    ],
    "wof:name":"W Wellings",
    "wof:placetype":"venue"
},
  "geometry": {"coordinates":[-2.417275,52.863724],"type":"Point"}
}