{
  "type": "Feature",
  "properties": {
    "addr:full":"Devonshire House, Mayfair Place London Greater London W1J 8AJ",
    "addr:postcode":"w1j 8aj",
    "addr:street":"Place",
    "iso:country":"GB",
    "sg:address":"Devonshire House, Mayfair Place",
    "sg:city":"London",
    "sg:classifiers":[
        {
            "category":"Professional",
            "subcategory":"Management & Consulting",
            "type":"Services"
        }
    ],
    "sg:phone":"+44 20 7493 3882",
    "sg:postcode":"W1J 8AJ",
    "sg:province":"Greater London",
    "sg:tags":[
        "consultant",
        "business"
    ],
    "wof:name":"E Z I Ltd.",
    "wof:placetype":"venue"
},
  "geometry": {"coordinates":[-0.14289,51.50716],"type":"Point"}
}