{
  "type": "Feature",
  "properties": {
    "iso:country":"GB",
    "sg:address":"13 High Street",
    "sg:city":"Bridlington",
    "sg:classifiers":[
        {
            "category":"Retail",
            "subcategory":"Repair Shop",
            "type":"Services"
        }
    ],
    "sg:phone":"+44 1262 602802",
    "sg:postcode":"YO16 4PR",
    "sg:province":"East Riding of Yorkshire",
    "sg:tags":[
        "clocks",
        "watch",
        "sale",
        "clock"
    ],
    "wof:name":"Clockcraft Antiques",
    "wof:placetype":"venue"
},
  "geometry": {"coordinates":[-0.2052890062,54.0930938721],"type":"Point"}
}