{
  "type": "Feature",
  "properties": {
    "addr:full":"20 Spring Close, Histon Cambridge Cambridgeshire CB4 9HT",
    "addr:housenumber":"20",
    "addr:postcode":"cb4 9ht",
    "addr:street":"Spring Close Histon",
    "iso:country":"GB",
    "sg:address":"20 Spring Close, Histon",
    "sg:city":"Cambridge",
    "sg:classifiers":[
        {
            "category":"Professional",
            "subcategory":"Management & Consulting",
            "type":"Services"
        }
    ],
    "sg:phone":"+44 1223 234744",
    "sg:postcode":"CB4 9HT",
    "sg:province":"Cambridgeshire",
    "sg:tags":[
        "consultant",
        "business"
    ],
    "wof:name":"Independent Research & Consultancy",
    "wof:placetype":"venue"
},
  "geometry": {"coordinates":[0.1109770015,52.2548408508],"type":"Point"}
}