{
  "type": "Feature",
  "properties": {
    "addr:full":"2a Lismore Av South Shields Tyne and Wear NE33 4SD",
    "addr:housenumber":"2a",
    "addr:postcode":"ne33 4sd",
    "addr:street":"Lismore Av",
    "iso:country":"GB",
    "sg:address":"2a Lismore Av",
    "sg:city":"South Shields",
    "sg:classifiers":[
        {
            "category":"Shopping",
            "subcategory":"Department Store",
            "type":"Retail Goods"
        }
    ],
    "sg:phone":"+44 191 456 3615",
    "sg:postcode":"NE33 4SD",
    "sg:province":"Tyne and Wear",
    "wof:name":"J Reay",
    "wof:placetype":"venue"
},
  "geometry": {"coordinates":[-1.4312829971,54.9798202515],"type":"Point"}
}