{
  "type": "Feature",
  "properties": {
    "iso:country":"GB",
    "sg:address":"118 High St",
    "sg:city":"Swadlincote",
    "sg:classifiers":[
        {
            "category":"Food & Beverages",
            "subcategory":"Meat & Fish",
            "type":"Retail Goods"
        }
    ],
    "sg:phone":"+44 1283 216699",
    "sg:postcode":"DE11 7DU",
    "sg:province":"Derbyshire",
    "sg:tags":[
        "butcher"
    ],
    "wof:name":"Smiths",
    "wof:placetype":"venue"
},
  "geometry": {"coordinates":[-1.5339989662,52.7691459656],"type":"Point"}
}