{
  "type": "Feature",
  "properties": {
    "iso:country":"GB",
    "sg:address":"22 Stockport Rd, Romiley",
    "sg:city":"Stockport",
    "sg:classifiers":[
        {
            "category":"Manufacturing",
            "subcategory":"Metals",
            "type":"Manufacturing & Wholesale Goods"
        }
    ],
    "sg:phone":"+44 161 406 9577",
    "sg:postcode":"SK6 4BN",
    "sg:province":"Cheshire",
    "sg:tags":[
        "die-casting"
    ],
    "wof:name":"Direct Tools",
    "wof:placetype":"venue"
},
  "geometry": {"coordinates":[-2.089813,53.413998],"type":"Point"}
}