{
  "type": "Feature",
  "properties": {
    "addr:full":"Zimbabwe House, 429 Strand London Greater London WC2R 0QE",
    "addr:housenumber":"429",
    "addr:postcode":"wc2r 0qe",
    "addr:street":"Strand",
    "iso:country":"GB",
    "sg:address":"Zimbabwe House, 429 Strand",
    "sg:city":"London",
    "sg:classifiers":[
        {
            "category":"Government",
            "subcategory":"Embassy",
            "type":"Public Place"
        }
    ],
    "sg:phone":"+44 20 7836 7755",
    "sg:postcode":"WC2R 0QE",
    "sg:province":"Greater London",
    "sg:tags":[
        "consulate"
    ],
    "wof:name":"High Commission for the Republic of Zimbabwe",
    "wof:placetype":"venue"
},
  "geometry": {"coordinates":[-0.119189,51.51128],"type":"Point"}
}