{
  "type": "Feature",
  "properties": {
    "addr:full":"135 Highland Road Southsea Hampshire PO4 9EY",
    "addr:housenumber":"135",
    "addr:postcode":"po4 9ey",
    "addr:street":"Highland Road",
    "iso:country":"GB",
    "sg:address":"135 Highland Road",
    "sg:city":"Southsea",
    "sg:classifiers":[
        {
            "category":"Fast Food",
            "type":"Food & Drink"
        },
        {
            "category":"Food & Beverages",
            "subcategory":"Meat & Fish",
            "type":"Retail Goods"
        }
    ],
    "sg:phone":"+44 23 9273 4199",
    "sg:postcode":"PO4 9EY",
    "sg:province":"Hampshire",
    "sg:tags":[
        "outlet",
        "chip",
        "meal",
        "away",
        "take"
    ],
    "wof:name":"Highland Fling",
    "wof:placetype":"venue"
},
  "geometry": {"coordinates":[-1.064628005,50.7870330811],"type":"Point"}
}