{
  "type": "Feature",
  "properties": {
    "addr:full":"101a Red Bank Road Blackpool Lancashire FY2 9HZ",
    "addr:housenumber":"101a",
    "addr:postcode":"fy2 9hz",
    "addr:street":"Red Bank Road",
    "iso:country":"GB",
    "sg:address":"101a Red Bank Road",
    "sg:city":"Blackpool",
    "sg:classifiers":[
        {
            "category":"Shopping",
            "subcategory":"Optician",
            "type":"Retail Goods"
        },
        {
            "category":"Health Services",
            "subcategory":"Optometrist",
            "type":"Services"
        }
    ],
    "sg:phone":"+44 1253 353423",
    "sg:postcode":"FY2 9HZ",
    "sg:province":"Lancashire",
    "sg:tags":[
        "opthalmic"
    ],
    "wof:name":"JULIA WOODING",
    "wof:placetype":"venue"
},
  "geometry": {"coordinates":[-3.048899889,53.8503036499],"type":"Point"}
}