{
  "type": "Feature",
  "properties": {
    "addr:full":"29 Maes Cynbryd, Llanddulas Abergele Conwy LL22 8HF",
    "addr:housenumber":"29",
    "addr:postcode":"ll22 8hf",
    "addr:street":"Maes Cynbryd",
    "iso:country":"GB",
    "sg:address":"29 Maes Cynbryd, Llanddulas",
    "sg:city":"Abergele",
    "sg:classifiers":[
        {
            "category":"Taxi",
            "type":"Transportation"
        },
        {
            "category":"Military Area",
            "subcategory":"Air Force Base",
            "type":"Public Place"
        }
    ],
    "sg:phone":"+44 1745 832852",
    "sg:postcode":"LL22 8HF",
    "sg:province":"Conwy",
    "sg:tags":[
        "hire",
        "private"
    ],
    "wof:name":"Dulas Taxis",
    "wof:placetype":"venue"
},
  "geometry": {"coordinates":[-3.6426870823,53.2898979187],"type":"Point"}
}