{
  "type": "Feature",
  "properties": {
    "iso:country":"GB",
    "sg:address":"4 Wessex Gate",
    "sg:city":"Waterlooville",
    "sg:classifiers":[
        {
            "category":"Health Services",
            "subcategory":"Dentist",
            "type":"Services"
        }
    ],
    "sg:phone":"+44 23 9259 9188",
    "sg:postcode":"PO8 9LP",
    "sg:province":"Hampshire",
    "sg:tags":[
        "technician",
        "dental"
    ],
    "wof:name":"J S Dental Ceramics",
    "wof:placetype":"venue"
},
  "geometry": {"coordinates":[-0.998265,50.931152],"type":"Point"}
}