{
  "type": "Feature",
  "properties": {
    "iso:country":"GB",
    "sg:address":"11 Foxglove Bank",
    "sg:city":"Royston",
    "sg:classifiers":[
        {
            "category":"Organizations",
            "subcategory":"Community Association",
            "type":"Services"
        }
    ],
    "sg:postcode":"SG8 9TH",
    "sg:province":"Bedfordshire",
    "sg:tags":[
        "relation",
        "public"
    ],
    "wof:name":"Face to Face",
    "wof:placetype":"venue"
},
  "geometry": {"coordinates":[-0.009407,52.046036],"type":"Point"}
}