{
  "type": "Feature",
  "properties": {
    "addr:full":"Lonsdale Chambers, Lonsdale Street Stoke-on-trent Staffordshire ST4 4BT",
    "addr:postcode":"st4 4bt",
    "addr:street":"Lonsdale Street",
    "iso:country":"GB",
    "sg:address":"Lonsdale Chambers, Lonsdale Street",
    "sg:city":"Stoke-on-trent",
    "sg:classifiers":[
        {
            "category":"Professional",
            "subcategory":"Computer Services",
            "type":"Services"
        }
    ],
    "sg:phone":"+44 1782 747192",
    "sg:postcode":"ST4 4BT",
    "sg:province":"Staffordshire",
    "sg:tags":[
        "system",
        "software"
    ],
    "wof:name":"Premier P C Ltd.",
    "wof:placetype":"venue"
},
  "geometry": {"coordinates":[-2.1826200485,53.002910614],"type":"Point"}
}