{
  "type": "Feature",
  "properties": {
    "addr:full":"214 Main Road, West Winch King's Lynn Norfolk PE33 0NP",
    "addr:housenumber":"214",
    "addr:postcode":"pe33 0np",
    "addr:street":"Main Road;Lynn",
    "iso:country":"GB",
    "sg:address":"214 Main Road, West Winch",
    "sg:city":"King's Lynn",
    "sg:classifiers":[
        {
            "category":"Home & Garden",
            "subcategory":"Carpets & Floor Coverings",
            "type":"Retail Goods"
        },
        {
            "category":"Wholesale",
            "subcategory":"Home Furnishings",
            "type":"Manufacturing & Wholesale Goods"
        }
    ],
    "sg:phone":"+44 1553 840219",
    "sg:postcode":"PE33 0NP",
    "sg:province":"Norfolk",
    "sg:tags":[
        "retailer",
        "rug",
        "wsale"
    ],
    "wof:name":"Olympic Carpets",
    "wof:placetype":"venue"
},
  "geometry": {"coordinates":[0.414138,52.715736],"type":"Point"}
}