{
  "type": "Feature",
  "properties": {
    "addr:full":"King Street Spennymoor Durham DL16 6QG",
    "addr:postcode":"dl16 6qg",
    "addr:street":"King Street",
    "iso:country":"GB",
    "sg:address":"King Street",
    "sg:city":"Spennymoor",
    "sg:classifiers":[
        {
            "category":"Organizations",
            "subcategory":"Membership Organization",
            "type":"Services"
        }
    ],
    "sg:phone":"+44 1388 814270",
    "sg:postcode":"DL16 6QG",
    "sg:province":"Durham",
    "sg:tags":[
        "club"
    ],
    "wof:name":"Spennymoor Workmens Club",
    "wof:placetype":"venue"
},
  "geometry": {"coordinates":[-1.599674,54.703075],"type":"Point"}
}