{
  "type": "Feature",
  "properties": {
    "iso:country":"GB",
    "sg:address":"26 Great Cornbow",
    "sg:city":"Halesowen",
    "sg:classifiers":[
        {
            "category":"Professional",
            "subcategory":"Business Services",
            "type":"Services"
        }
    ],
    "sg:phone":"+44 121 680 4416",
    "sg:postcode":"B63 3AE",
    "sg:province":"West Midlands",
    "sg:tags":[
        "hospitality",
        "corporate"
    ],
    "wof:name":"A Partner To Murder",
    "wof:placetype":"venue"
},
  "geometry": {"coordinates":[-2.0497100353,52.4482574463],"type":"Point"}
}