{
  "type": "Feature",
  "properties": {
    "addr:full":"78 Hermitage Road, Whitwick Coalville Leicestershire LE67 5EG",
    "addr:housenumber":"78",
    "addr:postcode":"le67 5eg",
    "addr:street":"Hermitage Road",
    "iso:country":"GB",
    "sg:address":"78 Hermitage Road, Whitwick",
    "sg:city":"Coalville",
    "sg:classifiers":[
        {
            "category":"Building & Trades",
            "subcategory":"Construction",
            "type":"Services"
        }
    ],
    "sg:phone":"+44 1530 837615",
    "sg:postcode":"LE67 5EG",
    "sg:province":"Leicestershire",
    "sg:tags":[
        "builder"
    ],
    "wof:name":"Kevin Waring",
    "wof:placetype":"venue"
},
  "geometry": {"coordinates":[-1.363744,52.732964],"type":"Point"}
}