{
  "type": "Feature",
  "properties": {
    "addr:full":"30 Middleleaze Drive, Middleleaze Swindon Wiltshire SN5 5GN",
    "addr:housenumber":"30",
    "addr:postcode":"sn5 5gn",
    "addr:street":"Middleleaze Drive",
    "iso:country":"GB",
    "sg:address":"30 Middleleaze Drive, Middleleaze",
    "sg:city":"Swindon",
    "sg:classifiers":[
        {
            "category":"Social Services",
            "subcategory":"Job Training",
            "type":"Services"
        }
    ],
    "sg:phone":"+44 1793 874506",
    "sg:postcode":"SN5 5GN",
    "sg:province":"Wiltshire",
    "sg:tags":[
        "draughtsman",
        "drawing"
    ],
    "wof:name":"Longcraft Ltd.",
    "wof:placetype":"venue"
},
  "geometry": {"coordinates":[-1.846791,51.56868],"type":"Point"}
}