{
  "type": "Feature",
  "properties": {
    "addr:full":"Zoar Baptist Chapel, Darfield St Bradford West Yorkshire BD1 3RU",
    "addr:postcode":"bd1 3ru",
    "addr:street":"Darfield St",
    "iso:country":"GB",
    "sg:address":"Zoar Baptist Chapel, Darfield St",
    "sg:city":"Bradford",
    "sg:classifiers":[
        {
            "category":"Home & Garden",
            "subcategory":"Kitchen Supply",
            "type":"Retail Goods"
        }
    ],
    "sg:phone":"+44 1274 729140",
    "sg:postcode":"BD1 3RU",
    "sg:province":"West Yorkshire",
    "sg:tags":[
        "equipment",
        "catering"
    ],
    "wof:name":"Mill Engineering",
    "wof:placetype":"venue"
},
  "geometry": {"coordinates":[-1.7583060265,53.7957382202],"type":"Point"}
}