{
  "type": "Feature",
  "properties": {
    "iso:country":"GB",
    "sg:address":"14 High St",
    "sg:city":"Burton On Trent",
    "sg:classifiers":[
        {
            "category":"Shopping",
            "subcategory":"Clothing, Apparel, & Fashions",
            "type":"Retail Goods"
        }
    ],
    "sg:phone":"+44 1283 520544",
    "sg:postcode":"DE13 9LP",
    "sg:province":"Derbyshire",
    "sg:tags":[
        "ladieswear"
    ],
    "wof:name":"Clothes Shop The",
    "wof:placetype":"venue"
},
  "geometry": {"coordinates":[-1.684738,52.858078],"type":"Point"}
}