{
  "type": "Feature",
  "properties": {
    "iso:country":"GB",
    "sg:address":"518 London Road",
    "sg:city":"Thornton Heath",
    "sg:classifiers":[
        {
            "category":"Health Services",
            "subcategory":"Doctor",
            "type":"Services"
        },
        {
            "category":"Health Services",
            "subcategory":"Clinic",
            "type":"Services"
        }
    ],
    "sg:phone":"+44 20 8684 2190",
    "sg:postcode":"CR7 7HQ",
    "sg:province":"Surrey",
    "sg:tags":[
        "nh",
        "practitioners"
    ],
    "wof:name":"Croydon Health Authority",
    "wof:placetype":"venue"
},
  "geometry": {"coordinates":[-0.111385,51.38826],"type":"Point"}
}