{
  "type": "Feature",
  "properties": {
    "addr:full":"Warden, Shortwood View, Kingswood Bristol City of Bristol BS15 4DD",
    "addr:postcode":"bs15 4dd",
    "iso:country":"GB",
    "sg:address":"Warden, Shortwood View, Kingswood",
    "sg:city":"Bristol",
    "sg:classifiers":[
        {
            "category":"Social Services",
            "subcategory":"Adult Care",
            "type":"Services"
        }
    ],
    "sg:phone":"+44 117 960 6816",
    "sg:postcode":"BS15 4DD",
    "sg:province":"City of Bristol",
    "sg:tags":[
        "housing",
        "sheltered"
    ],
    "wof:name":"Shortwood View House",
    "wof:placetype":"venue"
},
  "geometry": {"coordinates":[-2.499019,51.462044],"type":"Point"}
}