{
  "type": "Feature",
  "properties": {
    "addr:full":"Meadow Lane, Alvaston Derby Derbyshire DE24 8RE",
    "addr:postcode":"de24 8re",
    "addr:street":"Meadow Lane",
    "iso:country":"GB",
    "sg:address":"Meadow Lane, Alvaston",
    "sg:city":"Derby",
    "sg:classifiers":[
        {
            "category":"Manufacturing",
            "subcategory":"Buildings",
            "type":"Manufacturing & Wholesale Goods"
        }
    ],
    "sg:phone":"+44 1332 572204",
    "sg:postcode":"DE24 8RE",
    "sg:province":"Derbyshire",
    "sg:tags":[
        "mobile",
        "home"
    ],
    "wof:name":"Alvaston Mobile Homes",
    "wof:placetype":"venue"
},
  "geometry": {"coordinates":[-1.4379019737,52.902381897],"type":"Point"}
}