{
  "type": "Feature",
  "properties": {
    "iso:country":"GB",
    "sg:address":"113 Victoria Road, Portslade",
    "sg:city":"Brighton",
    "sg:classifiers":[
        {
            "category":"Shopping",
            "subcategory":"Department Store",
            "type":"Retail Goods"
        },
        {
            "category":"Professional",
            "subcategory":"Printing & Photocopies",
            "type":"Services"
        }
    ],
    "sg:phone":"+44 1273 424529",
    "sg:postcode":"BN41 1XD",
    "sg:province":"East Sussex",
    "sg:tags":[
        "embroiderer"
    ],
    "wof:name":"The Dropped Stitch",
    "wof:placetype":"venue"
},
  "geometry": {"coordinates":[-0.212707,50.836788],"type":"Point"}
}