{
  "type": "Feature",
  "properties": {
    "addr:full":"20 Norton Grn La, Knowle Solihull Warwickshire B93 8PL",
    "addr:housenumber":"20",
    "addr:postcode":"b93 8pl",
    "addr:street":"Norton Grn La Knowle",
    "iso:country":"GB",
    "sg:address":"20 Norton Grn La, Knowle",
    "sg:city":"Solihull",
    "sg:classifiers":[
        {
            "category":"Autos & Motor Vehicles",
            "subcategory":"Automobile Sales",
            "type":"Retail Goods"
        }
    ],
    "sg:postcode":"B93 8PL",
    "sg:province":"Warwickshire",
    "sg:tags":[
        "car"
    ],
    "wof:name":"Green,Clive,",
    "wof:placetype":"venue"
},
  "geometry": {"coordinates":[-1.7370820045,52.3698539734],"type":"Point"}
}