{
  "type": "Feature",
  "properties": {
    "addr:full":"2 Westwood Road Leek Staffordshire ST13 8DH",
    "addr:housenumber":"2",
    "addr:postcode":"st13 8dh",
    "addr:street":"Westwood Road",
    "iso:country":"GB",
    "sg:address":"2 Westwood Road",
    "sg:city":"Leek",
    "sg:classifiers":[
        {
            "category":"Shopping",
            "subcategory":"Clothing, Apparel, & Fashions",
            "type":"Retail Goods"
        }
    ],
    "sg:phone":"+44 1538 385340",
    "sg:postcode":"ST13 8DH",
    "sg:province":"Staffordshire",
    "sg:tags":[
        "shop"
    ],
    "wof:name":"Leek Factory Shop",
    "wof:placetype":"venue"
},
  "geometry": {"coordinates":[-2.0330209732,53.1062583923],"type":"Point"}
}