{
  "type": "Feature",
  "properties": {
    "iso:country":"GB",
    "sg:address":"Blaencediw",
    "sg:city":"Whitland",
    "sg:classifiers":[
        {
            "category":"Farming",
            "subcategory":"Dairy Farm",
            "type":"Manufacturing & Wholesale Goods"
        },
        {
            "category":"Farming",
            "subcategory":"Livestock Farm",
            "type":"Manufacturing & Wholesale Goods"
        },
        {
            "category":"Farming",
            "subcategory":"Farm",
            "type":"Manufacturing & Wholesale Goods"
        }
    ],
    "sg:phone":"+44 1994 448212",
    "sg:postcode":"SA34 0LH",
    "sg:province":"Carmarthenshire",
    "sg:tags":[
        "mixed",
        "others",
        "crop",
        "farmer"
    ],
    "wof:name":"I M & E S Richards",
    "wof:placetype":"venue"
},
  "geometry": {"coordinates":[-4.612054,51.819256],"type":"Point"}
}