{
  "type": "Feature",
  "properties": {
    "addr:full":"31 Vale Road Poole Dorset BH14 9AT",
    "addr:housenumber":"31",
    "addr:postcode":"bh14 9at",
    "addr:street":"Vale Road",
    "iso:country":"GB",
    "sg:address":"31 Vale Road",
    "sg:city":"Poole",
    "sg:classifiers":[
        {
            "category":"Building & Trades",
            "subcategory":"Construction",
            "type":"Services"
        }
    ],
    "sg:phone":"+44 1202 721711",
    "sg:postcode":"BH14 9AT",
    "sg:province":"Dorset",
    "sg:tags":[
        "builder"
    ],
    "wof:name":"C R Fulton",
    "wof:placetype":"venue"
},
  "geometry": {"coordinates":[-1.9288879633,50.7271232605],"type":"Point"}
}