{
  "type": "Feature",
  "properties": {
    "addr:full":"127-129 Marlowes Hemel Hempstead Hertfordshire HP1 1BB",
    "addr:postcode":"127-129;hp1 1bb",
    "addr:street":"Marlowes;Hempstead",
    "iso:country":"GB",
    "sg:address":"127-129 Marlowes",
    "sg:city":"Hemel Hempstead",
    "sg:classifiers":[
        {
            "category":"Shopping",
            "subcategory":"Department Store",
            "type":"Retail Goods"
        },
        {
            "category":"Shopping",
            "subcategory":"Gifts & Souvenirs",
            "type":"Retail Goods"
        }
    ],
    "sg:phone":"+44 1442 252537",
    "sg:postcode":"HP1 1BB",
    "sg:province":"Hertfordshire",
    "sg:tags":[
        "shop"
    ],
    "wof:name":"Dan Dallal",
    "wof:placetype":"venue"
},
  "geometry": {"coordinates":[-0.472119,51.751877],"type":"Point"}
}