{
  "type": "Feature",
  "properties": {
    "addr:full":"Tamar Street Torpoint Cornwall PL11 2AW",
    "addr:postcode":"pl11 2aw",
    "addr:street":"Tamar Street",
    "iso:country":"GB",
    "sg:address":"Tamar Street",
    "sg:city":"Torpoint",
    "sg:classifiers":[
        {
            "category":"Fast Food",
            "type":"Food & Drink"
        }
    ],
    "sg:phone":"+44 1752 814481",
    "sg:postcode":"PL11 2AW",
    "sg:province":"Cornwall",
    "sg:tags":[
        "away",
        "take"
    ],
    "wof:name":"Wong's Chinese Restaurant",
    "wof:placetype":"venue"
},
  "geometry": {"coordinates":[-4.194419,50.375374],"type":"Point"}
}