{
  "type": "Feature",
  "properties": {
    "iso:country":"GB",
    "sg:address":"County Ground, New Road",
    "sg:city":"Worcester",
    "sg:classifiers":[
        {
            "category":"Sports & Exercise",
            "subcategory":"Bowling",
            "type":"Entertainment"
        },
        {
            "category":"Government",
            "subcategory":"Office",
            "type":"Public Place"
        }
    ],
    "sg:phone":"+44 1905 421458",
    "sg:postcode":"WR2 4QH",
    "sg:province":"Worcestershire",
    "sg:tags":[
        "local"
    ],
    "wof:name":"Cripplegate Park Bowling Green",
    "wof:placetype":"venue"
},
  "geometry": {"coordinates":[-2.22816,52.188492],"type":"Point"}
}