{
  "type": "Feature",
  "properties": {
    "addr:full":"Kindrogan, Enochdhu Blairgowrie Perth and Kinross PH10 7PG",
    "addr:postcode":"ph10 7pg",
    "iso:country":"GB",
    "sg:address":"Kindrogan, Enochdhu",
    "sg:city":"Blairgowrie",
    "sg:classifiers":[
        {
            "category":"Government",
            "subcategory":"Office",
            "type":"Public Place"
        }
    ],
    "sg:phone":"+44 1250 881286",
    "sg:postcode":"PH10 7PG",
    "sg:province":"Perth and Kinross",
    "sg:tags":[
        "education",
        "agency",
        "authority"
    ],
    "wof:name":"Kindrogan Field Centre",
    "wof:placetype":"venue"
},
  "geometry": {"coordinates":[-3.533914,56.747253],"type":"Point"}
}