{
  "type": "Feature",
  "properties": {
    "iso:country":"GB",
    "sg:address":"22 Beach Station Road",
    "sg:city":"Felixstowe",
    "sg:classifiers":[
        {
            "category":"Personal",
            "subcategory":"Beauty Salon",
            "type":"Services"
        },
        {
            "category":"Personal",
            "subcategory":"Barber",
            "type":"Services"
        }
    ],
    "sg:phone":"+44 1394 284794",
    "sg:postcode":"IP11 2DR",
    "sg:province":"Suffolk",
    "sg:tags":[
        "unisex",
        "men's",
        "gents",
        "hairdresser"
    ],
    "wof:name":"Barnet Fayre",
    "wof:placetype":"venue"
},
  "geometry": {"coordinates":[1.336255,51.952381],"type":"Point"}
}