{
  "type": "Feature",
  "properties": {
    "addr:full":"New School Road, Garnant Ammanford Carmarthenshire SA18 1LL",
    "addr:postcode":"sa18 1ll",
    "addr:street":"New School Road",
    "iso:country":"GB",
    "sg:address":"New School Road, Garnant",
    "sg:city":"Ammanford",
    "sg:classifiers":[
        {
            "category":"Education",
            "subcategory":"School",
            "type":"Public Place"
        }
    ],
    "sg:phone":"+44 1269 822581",
    "sg:postcode":"SA18 1LL",
    "sg:province":"Carmarthenshire",
    "sg:tags":[
        "local",
        "authority"
    ],
    "wof:name":"Garnant Primary School",
    "wof:placetype":"venue"
},
  "geometry": {"coordinates":[-3.897524,51.801086],"type":"Point"}
}