{
  "type": "Feature",
  "properties": {
    "addr:full":"85 Horsecroft Road Hemel Hempstead Hertfordshire HP1 1PX",
    "addr:housenumber":"85",
    "addr:postcode":"hp1 1px",
    "addr:street":"Horsecroft Road",
    "iso:country":"GB",
    "sg:address":"85 Horsecroft Road",
    "sg:city":"Hemel Hempstead",
    "sg:classifiers":[
        {
            "category":"Government",
            "subcategory":"Post Office",
            "type":"Public Place"
        }
    ],
    "sg:postcode":"HP1 1PX",
    "sg:province":"Hertfordshire",
    "wof:name":"Boxmoor Post Office",
    "wof:placetype":"venue"
},
  "geometry": {"coordinates":[-0.487393,51.74559],"type":"Point"}
}