{
  "type": "Feature",
  "properties": {
    "addr:full":"Units 6 & 7 119 Shortmead St Biggleswade Bedfordshire SG18 0BB",
    "addr:housenumber":"units 6 & 7",
    "addr:postcode":"119;sg18 0bb",
    "addr:street":"Shortmead St",
    "iso:country":"GB",
    "sg:address":"Units 6 & 7 119 Shortmead St",
    "sg:city":"Biggleswade",
    "sg:classifiers":[
        {
            "category":"Professional",
            "subcategory":"Testing Lab",
            "type":"Services"
        }
    ],
    "sg:phone":"+44 1767 601945",
    "sg:postcode":"SG18 0BB",
    "sg:province":"Bedfordshire",
    "sg:tags":[
        "mot"
    ],
    "wof:name":"Biggleswade Mot Testing Centre",
    "wof:placetype":"venue"
},
  "geometry": {"coordinates":[-0.268155992,52.0916671753],"type":"Point"}
}