{
  "type": "Feature",
  "properties": {
    "addr:full":"37b Market Square, St Neots Huntingdon Bedfordshire PE19 2AR",
    "addr:housenumber":"37b",
    "addr:postcode":"pe19 2ar",
    "addr:street":"Market Square",
    "iso:country":"GB",
    "sg:address":"37b Market Square, St Neots",
    "sg:city":"Huntingdon",
    "sg:classifiers":[
        {
            "category":"Professional",
            "subcategory":"Lawyer & Legal Services",
            "type":"Services"
        }
    ],
    "sg:phone":"+44 1480 474061",
    "sg:postcode":"PE19 2AR",
    "sg:province":"Bedfordshire",
    "sg:tags":[
        "solicitor"
    ],
    "wof:name":"Adlams",
    "wof:placetype":"venue"
},
  "geometry": {"coordinates":[-0.2716200054,52.2277297974],"type":"Point"}
}