{
  "type": "Feature",
  "properties": {
    "addr:full":"24 Orchard Dr Epping Essex CM16 7DJ",
    "addr:housenumber":"24",
    "addr:postcode":"cm16 7dj",
    "addr:street":"Orchard Dr",
    "iso:country":"GB",
    "sg:address":"24 Orchard Dr",
    "sg:city":"Epping",
    "sg:classifiers":[
        {
            "category":"Health Services",
            "subcategory":"Health Practitioner",
            "type":"Services"
        }
    ],
    "sg:phone":"+44 1992 812189",
    "sg:postcode":"CM16 7DJ",
    "sg:province":"Essex",
    "sg:tags":[
        "technique",
        "alexander"
    ],
    "wof:name":"Stephanie Smith",
    "wof:placetype":"venue"
},
  "geometry": {"coordinates":[0.099051,51.673466],"type":"Point"}
}