{
  "type": "Feature",
  "properties": {
    "iso:country":"GB",
    "sg:address":"333 Millbrook Road",
    "sg:city":"Southampton",
    "sg:classifiers":[
        {
            "category":"Autos & Motor Vehicles",
            "subcategory":"Automobile Sales",
            "type":"Retail Goods"
        }
    ],
    "sg:phone":"+44 23 8070 1441",
    "sg:postcode":"SO15 0HW",
    "sg:province":"Hampshire",
    "sg:tags":[
        "car"
    ],
    "wof:name":"A C S Car Trade Centre",
    "wof:placetype":"venue"
},
  "geometry": {"coordinates":[-1.4444390535,50.91355896],"type":"Point"}
}