{
  "type": "Feature",
  "properties": {
    "iso:country":"GB",
    "sg:address":"180 Maple Road",
    "sg:city":"London",
    "sg:classifiers":[
        {
            "category":"Shopping",
            "subcategory":"Gifts & Souvenirs",
            "type":"Retail Goods"
        }
    ],
    "sg:phone":"+44 20 8776 5687",
    "sg:postcode":"SE20 8JB",
    "sg:province":"Greater London",
    "sg:tags":[
        "poster",
        "card"
    ],
    "wof:name":"Greetings",
    "wof:placetype":"venue"
},
  "geometry": {"coordinates":[-0.055395,51.414406],"type":"Point"}
}