{
  "type": "Feature",
  "properties": {
    "iso:country":"GB",
    "sg:address":"21 Upper Priory Street, Grafton Street Industrial Estate",
    "sg:city":"Northampton",
    "sg:classifiers":[
        {
            "category":"Professional",
            "subcategory":"Business Services",
            "type":"Services"
        },
        {
            "category":"Government",
            "subcategory":"Post Office",
            "type":"Public Place"
        }
    ],
    "sg:phone":"+44 1604 622290",
    "sg:postcode":"NN1 2PT",
    "sg:province":"Northamptonshire",
    "sg:tags":[
        "delivery",
        "house",
        "distribution",
        "mailing",
        "mail"
    ],
    "wof:name":"Mailshot Services",
    "wof:placetype":"venue"
},
  "geometry": {"coordinates":[-0.9011020064,52.2432632446],"type":"Point"}
}