{
  "type": "Feature",
  "properties": {
    "addr:full":"64 Lichfield Grove Finchley Central Greater London N3 2JP",
    "addr:housenumber":"64",
    "addr:postcode":"n3 2jp",
    "addr:street":"Lichfield Grove",
    "iso:country":"GB",
    "sg:address":"64 Lichfield Grove",
    "sg:city":"Finchley Central",
    "sg:classifiers":[
        {
            "category":"Health Services",
            "subcategory":"Doctor",
            "type":"Services"
        }
    ],
    "sg:phone":"+44 20 8346 3123",
    "sg:postcode":"N3 2JP",
    "sg:province":"Greater London",
    "sg:tags":[
        "practitioners"
    ],
    "wof:name":"Drs Durden & Pelendrides",
    "wof:placetype":"venue"
},
  "geometry": {"coordinates":[-0.193106994,51.5994987488],"type":"Point"}
}