{
  "type": "Feature",
  "properties": {
    "addr:full":"1193 Uttoxeter Road Stoke-on-trent Staffordshire ST3 6HJ",
    "addr:housenumber":"1193",
    "addr:postcode":"st3 6hj",
    "addr:street":"Uttoxeter Road",
    "iso:country":"GB",
    "sg:address":"1193 Uttoxeter Road",
    "sg:city":"Stoke-on-trent",
    "sg:classifiers":[
        {
            "category":"Manufacturing",
            "subcategory":"Glass & Minerals",
            "type":"Manufacturing & Wholesale Goods"
        }
    ],
    "sg:phone":"+44 1782 392463",
    "sg:postcode":"ST3 6HJ",
    "sg:province":"Staffordshire",
    "sg:tags":[
        "mnfr",
        "glassware",
        "china"
    ],
    "wof:name":"Charles Rose Jewellery",
    "wof:placetype":"venue"
},
  "geometry": {"coordinates":[-2.1025400162,52.9774246216],"type":"Point"}
}