{
  "type": "Feature",
  "properties": {
    "addr:full":"1 Winston Rise, Four Marks Alton Hampshire GU34 5HW",
    "addr:housenumber":"1",
    "addr:postcode":"gu34 5hw",
    "addr:street":"Winston Rise",
    "iso:country":"GB",
    "sg:address":"1 Winston Rise, Four Marks",
    "sg:city":"Alton",
    "sg:classifiers":[
        {
            "category":"Real Estate",
            "subcategory":"Real Estate Services",
            "type":"Services"
        },
        {
            "category":"Building & Trades",
            "subcategory":"Equipment Rental",
            "type":"Services"
        }
    ],
    "sg:phone":"+44 1420 562327",
    "sg:postcode":"GU34 5HW",
    "sg:province":"Hampshire",
    "sg:tags":[
        "hire",
        "leasing",
        "plant",
        "machinery"
    ],
    "wof:name":"L G Plant Hire",
    "wof:placetype":"venue"
},
  "geometry": {"coordinates":[-1.0463600159,51.1126976013],"type":"Point"}
}