{
  "type": "Feature",
  "properties": {
    "iso:country":"GB",
    "sg:address":"36 Curzon Street",
    "sg:city":"Birmingham",
    "sg:classifiers":[
        {
            "category":"Manufacturing",
            "subcategory":"Lumber",
            "type":"Manufacturing & Wholesale Goods"
        }
    ],
    "sg:phone":"+44 121 359 5828",
    "sg:postcode":"B4 7XE",
    "sg:province":"West Midlands",
    "sg:tags":[
        "importer",
        "merchants",
        "agent",
        "timber"
    ],
    "wof:name":"Ryland-Jameson (Timber & Plywood) Ltd.",
    "wof:placetype":"venue"
},
  "geometry": {"coordinates":[-1.879945,52.483471],"type":"Point"}
}