{
  "type": "Feature",
  "properties": {
    "iso:country":"GB",
    "sg:address":"38 Leysfield Rd",
    "sg:city":"Shepherd's Bush",
    "sg:classifiers":[
        {
            "category":"Autos & Motor Vehicles",
            "subcategory":"Automobile Sales",
            "type":"Retail Goods"
        }
    ],
    "sg:phone":"+44 20 8749 8282",
    "sg:postcode":"W12 9JF",
    "sg:province":"Greater London",
    "sg:tags":[
        "car",
        "specialist",
        "sales",
        "classic"
    ],
    "wof:name":"Taylormead Engineering (N C Coachworks) Ltd",
    "wof:placetype":"venue"
},
  "geometry": {"coordinates":[-0.23767,51.501667],"type":"Point"}
}