{
  "type": "Feature",
  "properties": {
    "addr:full":"12-13 Conduit Street London Greater London W1S 2XQ",
    "addr:housenumber":"12-13",
    "addr:postcode":"w1s 2xq",
    "addr:street":"Conduit Street",
    "iso:country":"GB",
    "sg:address":"12-13 Conduit Street",
    "sg:city":"London",
    "sg:classifiers":[
        {
            "category":"Banks & Credit Unions",
            "subcategory":"Financial Services",
            "type":"Services"
        }
    ],
    "sg:postcode":"W1S 2XQ",
    "sg:province":"Greater London",
    "sg:tags":[
        "consultant"
    ],
    "wof:name":"City Limits Investments Ltd.",
    "wof:placetype":"venue"
},
  "geometry": {"coordinates":[-0.1417289972,51.5126075745],"type":"Point"}
}