{
  "type": "Feature",
  "properties": {
    "iso:country":"GB",
    "sg:address":"Oaklands Business Centre, 64-68 Elm Gro",
    "sg:city":"Worthing",
    "sg:classifiers":[
        {
            "category":"Professional",
            "type":"Services"
        }
    ],
    "sg:phone":"+44 1903 503297",
    "sg:postcode":"BN11 5LH",
    "sg:province":"West Sussex",
    "sg:tags":[
        "entertainer"
    ],
    "wof:name":"Andrew Beaucham Management & Promotions",
    "wof:placetype":"venue"
},
  "geometry": {"coordinates":[-0.3754239976,50.8136253357],"type":"Point"}
}