{
  "type": "Feature",
  "properties": {
    "addr:full":"Doctors Surgery, 60 Falcondale Rd Bristol City of Bristol BS9 3JY",
    "addr:housenumber":"60",
    "addr:postcode":"bs9 3jy",
    "addr:street":"Falcondale Rd",
    "iso:country":"GB",
    "sg:address":"Doctors Surgery, 60 Falcondale Rd",
    "sg:city":"Bristol",
    "sg:classifiers":[
        {
            "category":"Health Services",
            "subcategory":"Doctor",
            "type":"Services"
        }
    ],
    "sg:phone":"+44 117 962 3406",
    "sg:postcode":"BS9 3JY",
    "sg:province":"City of Bristol",
    "sg:tags":[
        "practitioners"
    ],
    "wof:name":"Cohen, M",
    "wof:placetype":"venue"
},
  "geometry": {"coordinates":[-2.6220989227,51.4930992126],"type":"Point"}
}