{
  "type": "Feature",
  "properties": {
    "addr:full":"27-31 Basil Street London Greater London SW3 1BB",
    "addr:housenumber":"27-31",
    "addr:postcode":"sw3 1bb",
    "addr:street":"Basil Street",
    "iso:country":"GB",
    "sg:address":"27-31 Basil Street",
    "sg:city":"London",
    "sg:classifiers":[
        {
            "category":"Restaurant",
            "type":"Food & Drink"
        }
    ],
    "sg:phone":"+44 20 7584 2345",
    "sg:postcode":"SW3 1BB",
    "sg:province":"Greater London",
    "sg:tags":[
        "french"
    ],
    "wof:name":"Cafe Rouge Ltd.",
    "wof:placetype":"venue"
},
  "geometry": {"coordinates":[-0.162111,51.498409],"type":"Point"}
}