{
  "type": "Feature",
  "properties": {
    "addr:full":"29b High Street Harpenden Hertfordshire AL5 2RU",
    "addr:housenumber":"29b",
    "addr:postcode":"al5 2ru",
    "addr:street":"High Street",
    "iso:country":"GB",
    "sg:address":"29b High Street",
    "sg:city":"Harpenden",
    "sg:classifiers":[
        {
            "category":"Autos & Motor Vehicles",
            "subcategory":"Automobile Sales",
            "type":"Retail Goods"
        }
    ],
    "sg:postcode":"AL5 2RU",
    "sg:province":"Hertfordshire",
    "sg:tags":[
        "car"
    ],
    "wof:name":"International Cars",
    "wof:placetype":"venue"
},
  "geometry": {"coordinates":[-0.356146,51.815968],"type":"Point"}
}