{
  "type": "Feature",
  "properties": {
    "addr:full":"Redbrink Crescent Barry The Vale of Glamorgan CF62 5TT",
    "addr:postcode":"cf62 5tt",
    "addr:street":"Redbrink Crescent;Vale",
    "iso:country":"GB",
    "sg:address":"Redbrink Crescent",
    "sg:city":"Barry",
    "sg:classifiers":[
        {
            "category":"Bars & Pubs",
            "type":"Food & Drink"
        }
    ],
    "sg:phone":"+44 1446 740662",
    "sg:postcode":"CF62 5TT",
    "sg:province":"The Vale of Glamorgan",
    "sg:tags":[
        "pubs",
        "inn"
    ],
    "wof:name":"The Marine Hotel",
    "wof:placetype":"venue"
},
  "geometry": {"coordinates":[-3.2669770718,51.3944969177],"type":"Point"}
}