{
  "type": "Feature",
  "properties": {
    "iso:country":"GB",
    "sg:address":"Bank Yard, Tabernacle Road",
    "sg:city":"Wotton-under-edge",
    "sg:classifiers":[
        {
            "category":"Home & Garden",
            "subcategory":"Hardware",
            "type":"Retail Goods"
        }
    ],
    "sg:phone":"+44 1453 844719",
    "sg:postcode":"GL12 7EB",
    "sg:province":"Gloucestershire",
    "sg:tags":[
        "compressor",
        "air"
    ],
    "wof:name":"Avon Air Tools",
    "wof:placetype":"venue"
},
  "geometry": {"coordinates":[-2.35565,51.640434],"type":"Point"}
}