{
  "type": "Feature",
  "properties": {
    "iso:country":"GB",
    "sg:address":"71 Nortoft Rd, Chalfont St Peter",
    "sg:city":"Gerrards Cross",
    "sg:classifiers":[
        {
            "category":"Building & Trades",
            "subcategory":"Landscaping Services",
            "type":"Services"
        }
    ],
    "sg:postcode":"SL9 0LB",
    "sg:province":"Buckinghamshire",
    "sg:tags":[
        "landscape",
        "contractor"
    ],
    "wof:name":"Cocker,Mark,",
    "wof:placetype":"venue"
},
  "geometry": {"coordinates":[-0.544607,51.61964],"type":"Point"}
}