{
  "type": "Feature",
  "properties": {
    "iso:country":"GB",
    "sg:address":"The Workshop, Smithcot Farm, Dauntsey",
    "sg:city":"Chippenham",
    "sg:classifiers":[
        {
            "category":"Wholesale",
            "subcategory":"Machinery & Supplies",
            "type":"Manufacturing & Wholesale Goods"
        }
    ],
    "sg:postcode":"SN15 4JL",
    "sg:province":"Wiltshire",
    "wof:name":"Cummins,John G,",
    "wof:placetype":"venue"
},
  "geometry": {"coordinates":[-2.01679,51.53754],"type":"Point"}
}