{
  "type": "Feature",
  "properties": {
    "iso:country":"GB",
    "sg:address":"Milton Keynes College, Leadenhall",
    "sg:city":"Milton Keynes",
    "sg:classifiers":[
        {
            "category":"Farming",
            "subcategory":"Nursery",
            "type":"Manufacturing & Wholesale Goods"
        }
    ],
    "sg:phone":"+44 1908 684420",
    "sg:postcode":"MK6 5LP",
    "sg:province":"Buckinghamshire",
    "sg:tags":[
        "creche"
    ],
    "wof:name":"Kids on the Move",
    "wof:placetype":"venue"
},
  "geometry": {"coordinates":[-0.754684,52.026997],"type":"Point"}
}