{
  "type": "Feature",
  "properties": {
    "addr:full":"157 Stowupland Road Stowmarket Suffolk IP14 5AP",
    "addr:housenumber":"157",
    "addr:postcode":"ip14 5ap",
    "addr:street":"Stowupland Road",
    "iso:country":"GB",
    "sg:address":"157 Stowupland Road",
    "sg:city":"Stowmarket",
    "sg:classifiers":[
        {
            "category":"Wholesale",
            "subcategory":"Books, Periodicals, & Newspapers",
            "type":"Manufacturing & Wholesale Goods"
        }
    ],
    "sg:phone":"+44 1449 672572",
    "sg:postcode":"IP14 5AP",
    "sg:province":"Suffolk",
    "sg:tags":[
        "publisher",
        "publishing"
    ],
    "wof:name":"Mansion House Publishing Co. Ltd.",
    "wof:placetype":"venue"
},
  "geometry": {"coordinates":[1.008425951,52.1926765442],"type":"Point"}
}