{
  "type": "Feature",
  "properties": {
    "addr:full":"6 Badgers Way Sturminster Newton Dorset DT10 1DW",
    "addr:housenumber":"6",
    "addr:postcode":"dt10 1dw",
    "addr:street":"Badgers Way",
    "iso:country":"GB",
    "sg:address":"6 Badgers Way",
    "sg:city":"Sturminster Newton",
    "sg:classifiers":[
        {
            "category":"Manufacturing",
            "subcategory":"Buildings",
            "type":"Manufacturing & Wholesale Goods"
        }
    ],
    "sg:phone":"+44 1258 473501",
    "sg:postcode":"DT10 1DW",
    "sg:province":"Dorset",
    "sg:tags":[
        "mobile",
        "home"
    ],
    "wof:name":"JOHN ROMANS PARK HOMES",
    "wof:placetype":"venue"
},
  "geometry": {"coordinates":[-2.3026230335,50.9332580566],"type":"Point"}
}