{
  "type": "Feature",
  "properties": {
    "iso:country":"GB",
    "sg:address":"226-228 Broomhill Road, Brislington",
    "sg:city":"Bristol",
    "sg:classifiers":[
        {
            "category":"Home & Garden",
            "subcategory":"Kitchen Supply",
            "type":"Retail Goods"
        }
    ],
    "sg:phone":"+44 117 977 9494",
    "sg:postcode":"BS4 5RG",
    "sg:province":"City of Bristol",
    "sg:tags":[
        "equipment",
        "bakery"
    ],
    "wof:name":"Modern Baking Systems (Bristol) Ltd.",
    "wof:placetype":"venue"
},
  "geometry": {"coordinates":[-2.536225,51.430786],"type":"Point"}
}