{
  "type": "Feature",
  "properties": {
    "iso:country":"GB",
    "sg:address":"Acres Barn, Tompkin Lane, Stanley",
    "sg:city":"Stoke-on-trent",
    "sg:classifiers":[
        {
            "category":"Farming",
            "subcategory":"Livestock Farm",
            "type":"Manufacturing & Wholesale Goods"
        }
    ],
    "sg:postcode":"ST9 9LY",
    "sg:province":"Staffordshire",
    "sg:tags":[
        "others"
    ],
    "wof:name":"P & A Rogers",
    "wof:placetype":"venue"
},
  "geometry": {"coordinates":[-2.105538,53.06879],"type":"Point"}
}