{
  "type": "Feature",
  "properties": {
    "iso:country":"GB",
    "sg:address":"Stuart House, 71 Elizabeth Street",
    "sg:city":"Corby",
    "sg:classifiers":[
        {
            "category":"Professional",
            "subcategory":"Lawyer & Legal Services",
            "type":"Services"
        }
    ],
    "sg:phone":"+44 1536 400000",
    "sg:postcode":"NN17 1SE",
    "sg:province":"Northamptonshire",
    "sg:tags":[
        "solicitor"
    ],
    "wof:name":"Wilson Browne",
    "wof:placetype":"venue"
},
  "geometry": {"coordinates":[-0.698989,52.487259],"type":"Point"}
}