{
  "type": "Feature",
  "properties": {
    "addr:full":"3 The Court Yard The Hayes, Southam Road Prestbury Cheltenham Gloucestershire GL52 3NQ",
    "addr:housenumber":"3",
    "addr:postcode":"gl52 3nq",
    "addr:street":"The Court Yard The;Southam Road",
    "iso:country":"GB",
    "sg:address":"3 The Court Yard The Hayes, Southam Road Prestbury",
    "sg:city":"Cheltenham",
    "sg:classifiers":[
        {
            "category":"Professional",
            "subcategory":"Engineering",
            "type":"Services"
        }
    ],
    "sg:phone":"+44 1242 255437",
    "sg:postcode":"GL52 3NQ",
    "sg:province":"Gloucestershire",
    "sg:tags":[
        "engineer",
        "mechanical"
    ],
    "wof:name":"Searchteam Ltd",
    "wof:placetype":"venue"
},
  "geometry": {"coordinates":[-2.035477,51.914501],"type":"Point"}
}