{
  "type": "Feature",
  "properties": {
    "addr:full":"2 The Mall, Breck Road Liverpool Merseyside L5 4QF",
    "addr:housenumber":"2",
    "addr:postcode":"l5 4qf",
    "addr:street":"The Mall Breck Road",
    "iso:country":"GB",
    "sg:address":"2 The Mall, Breck Road",
    "sg:city":"Liverpool",
    "sg:classifiers":[
        {
            "category":"Shopping",
            "subcategory":"Gifts & Souvenirs",
            "type":"Retail Goods"
        }
    ],
    "sg:phone":"+44 151 260 9600",
    "sg:postcode":"L5 4QF",
    "sg:province":"Merseyside",
    "sg:tags":[
        "poster",
        "card"
    ],
    "wof:name":"Cards",
    "wof:placetype":"venue"
},
  "geometry": {"coordinates":[-2.9659199715,53.4221496582],"type":"Point"}
}