{
  "type": "Feature",
  "properties": {
    "addr:full":"Studio 2001, Mile End Paisley Renfrewshire PA1 1JS",
    "addr:housenumber":"2001",
    "addr:postcode":"pa1 1js",
    "iso:country":"GB",
    "sg:address":"Studio 2001, Mile End",
    "sg:city":"Paisley",
    "sg:classifiers":[
        {
            "category":"Communications",
            "subcategory":"Newspaper",
            "type":"Services"
        }
    ],
    "sg:phone":"+44 141 561 0300",
    "sg:postcode":"PA1 1JS",
    "sg:province":"Renfrewshire",
    "sg:tags":[
        "magazine"
    ],
    "wof:name":"Connect Communications (Scotland) Ltd.",
    "wof:placetype":"venue"
},
  "geometry": {"coordinates":[-4.41488,55.84301],"type":"Point"}
}