{
  "type": "Feature",
  "properties": {
    "addr:full":"Castle Street Maesteg Bridgend CF34 9UN",
    "addr:postcode":"cf34 9un",
    "addr:street":"Castle Street",
    "iso:country":"GB",
    "sg:address":"Castle Street",
    "sg:city":"Maesteg",
    "sg:classifiers":[
        {
            "category":"Travel",
            "subcategory":"Travel Agent",
            "type":"Entertainment"
        },
        {
            "category":"Retail",
            "subcategory":"Auto Repair",
            "type":"Services"
        }
    ],
    "sg:phone":"+44 1656 730000",
    "sg:postcode":"CF34 9UN",
    "sg:province":"Bridgend",
    "sg:tags":[
        "modification",
        "garage",
        "related"
    ],
    "wof:name":"Fairfield Garage",
    "wof:placetype":"venue"
},
  "geometry": {"coordinates":[-3.6588969231,51.6102180481],"type":"Point"}
}