{
  "type": "Feature",
  "properties": {
    "iso:country":"GB",
    "sg:address":"18 Blackdown Rd",
    "sg:city":"Wellington",
    "sg:classifiers":[
        {
            "category":"Building & Trades",
            "subcategory":"Construction",
            "type":"Services"
        }
    ],
    "sg:phone":"+44 1823 667061",
    "sg:postcode":"TA21 9DG",
    "sg:province":"Devon",
    "sg:tags":[
        "roofing"
    ],
    "wof:name":"A-One Roofing Experts",
    "wof:placetype":"venue"
},
  "geometry": {"coordinates":[-3.244991,50.971027],"type":"Point"}
}