{
  "type": "Feature",
  "properties": {
    "addr:full":"Yew Tree Farm, Money Lane, Chadwich Bromsgrove Worcestershire B61 0QY",
    "addr:postcode":"b61 0qy",
    "addr:street":"Yew;Money Lane Chadwich",
    "iso:country":"GB",
    "sg:address":"Yew Tree Farm, Money Lane, Chadwich",
    "sg:city":"Bromsgrove",
    "sg:classifiers":[
        {
            "category":"Retail",
            "subcategory":"Animal Services",
            "type":"Services"
        }
    ],
    "sg:phone":"+44 121 453 2330",
    "sg:postcode":"B61 0QY",
    "sg:province":"Worcestershire",
    "sg:tags":[
        "breeder",
        "livestock"
    ],
    "wof:name":"S & B Wood",
    "wof:placetype":"venue"
},
  "geometry": {"coordinates":[-2.058112,52.336594],"type":"Point"}
}