{
  "type": "Feature",
  "properties": {
    "iso:country":"GB",
    "sg:address":"Parc Vean, 323 Babbacombe Rd",
    "sg:city":"Torquay",
    "sg:classifiers":[
        {
            "category":"Health Services",
            "subcategory":"Dentist",
            "type":"Services"
        }
    ],
    "sg:phone":"+44 1803 293627",
    "sg:postcode":"TQ1 3TB",
    "sg:province":"Devon",
    "wof:name":"D Roberts",
    "wof:placetype":"venue"
},
  "geometry": {"coordinates":[-3.50686,50.47366],"type":"Point"}
}