{
  "type": "Feature",
  "properties": {
    "iso:country":"GB",
    "sg:address":"Stoke Mandeville Hospital, Mandeville Road",
    "sg:city":"Aylesbury",
    "sg:classifiers":[
        {
            "category":"Health Services",
            "subcategory":"Hospital",
            "type":"Services"
        }
    ],
    "sg:phone":"+44 1296 315120",
    "sg:postcode":"HP21 8BD",
    "sg:province":"Buckinghamshire",
    "wof:name":"Stoke Mandeville Hospital",
    "wof:placetype":"venue"
},
  "geometry": {"coordinates":[-0.80971,51.803776],"type":"Point"}
}