{
  "type": "Feature",
  "properties": {
    "iso:country":"GB",
    "sg:address":"25 Phipp Street",
    "sg:city":"London",
    "sg:classifiers":[
        {
            "category":"Shopping",
            "subcategory":"Stationery & Office Supplies",
            "type":"Retail Goods"
        }
    ],
    "sg:phone":"+44 20 8739 3152",
    "sg:postcode":"EC2A 4NP",
    "sg:province":"Greater London",
    "sg:tags":[
        "printers'"
    ],
    "wof:name":"Target Litho Plate Making Co. Ltd.",
    "wof:placetype":"venue"
},
  "geometry": {"coordinates":[-0.0811270028,51.5246276855],"type":"Point"}
}