{
  "type": "Feature",
  "properties": {
    "addr:full":"596 Kings Road London Greater London SW6 2DX",
    "addr:housenumber":"596",
    "addr:postcode":"sw6 2dx",
    "addr:street":"Kings Road",
    "iso:country":"GB",
    "sg:address":"596 Kings Road",
    "sg:city":"London",
    "sg:classifiers":[
        {
            "category":"Shopping",
            "subcategory":"Antiques",
            "type":"Retail Goods"
        }
    ],
    "sg:phone":"+44 20 7731 2448",
    "sg:postcode":"SW6 2DX",
    "sg:province":"Greater London",
    "wof:name":"Pimpernel & Partners",
    "wof:placetype":"venue"
},
  "geometry": {"coordinates":[-0.189041,51.478523],"type":"Point"}
}