{
  "type": "Feature",
  "properties": {
    "addr:full":"Colney Lane, Colney Norwich Norfolk NR4 7UH",
    "addr:postcode":"nr4 7uh",
    "addr:street":"Colney Lane;Norwich Norfolk",
    "iso:country":"GB",
    "sg:address":"Colney Lane, Colney",
    "sg:city":"Norwich",
    "sg:classifiers":[
        {
            "category":"Government",
            "subcategory":"Post Office",
            "type":"Public Place"
        },
        {
            "category":"Organizations",
            "subcategory":"Professional Association",
            "type":"Services"
        }
    ],
    "sg:phone":"+44 1603 450000",
    "sg:postcode":"NR4 7UH",
    "sg:province":"Norfolk",
    "sg:tags":[
        "organisation",
        "soc",
        "institution",
        "research"
    ],
    "wof:name":"John Innes Centre Ltd",
    "wof:placetype":"venue"
},
  "geometry": {"coordinates":[1.22927,52.627056],"type":"Point"}
}