{
  "type": "Feature",
  "properties": {
    "addr:full":"The Spinney, Clay Hill Rye East Sussex TN31 6SQ",
    "addr:postcode":"tn31 6sq",
    "addr:street":"The",
    "iso:country":"GB",
    "sg:address":"The Spinney, Clay Hill",
    "sg:city":"Rye",
    "sg:classifiers":[
        {
            "category":"Military Area",
            "subcategory":"Air Force Base",
            "type":"Public Place"
        }
    ],
    "sg:postcode":"TN31 6SQ",
    "sg:province":"East Sussex",
    "sg:tags":[
        "taxi",
        "hire",
        "private"
    ],
    "wof:name":"John Healey",
    "wof:placetype":"venue"
},
  "geometry": {"coordinates":[0.735652,50.951729],"type":"Point"}
}