{
  "type": "Feature",
  "properties": {
    "iso:country":"GB",
    "sg:address":"12 Market St, Droylsden",
    "sg:city":"Manchester",
    "sg:classifiers":[
        {
            "category":"Shopping",
            "subcategory":"Party Supplies",
            "type":"Retail Goods"
        }
    ],
    "sg:postcode":"M43 6EA",
    "sg:province":"Greater Manchester",
    "sg:tags":[
        "novelty"
    ],
    "wof:name":"Style Flowers & Balloons",
    "wof:placetype":"venue"
},
  "geometry": {"coordinates":[-2.1467471123,53.4772262573],"type":"Point"}
}