{
  "type": "Feature",
  "properties": {
    "iso:country":"GB",
    "sg:address":"Rockingham Drive, Linford Wood",
    "sg:city":"Milton Keynes",
    "sg:classifiers":[
        {
            "category":"Professional",
            "subcategory":"Management & Consulting",
            "type":"Services"
        }
    ],
    "sg:phone":"+44 1908 608000",
    "sg:postcode":"MK14 6LY",
    "sg:province":"Buckinghamshire",
    "sg:tags":[
        "marketing",
        "consultant"
    ],
    "wof:name":"P & M M Ltd.",
    "wof:placetype":"venue"
},
  "geometry": {"coordinates":[-0.756804,52.055866],"type":"Point"}
}