{
  "type": "Feature",
  "properties": {
    "iso:country":"GB",
    "sg:address":"The Old Brickworks, Top Of The Bank, Thurstonland",
    "sg:city":"Huddersfield",
    "sg:classifiers":[
        {
            "category":"Building & Trades",
            "subcategory":"Construction",
            "type":"Services"
        }
    ],
    "sg:phone":"+44 1484 663541",
    "sg:postcode":"HD4 6XZ",
    "sg:province":"West Yorkshire",
    "sg:tags":[
        "builder"
    ],
    "wof:name":"D Parker (Builders) Ltd.",
    "wof:placetype":"venue"
},
  "geometry": {"coordinates":[-1.749458,53.591061],"type":"Point"}
}