{
  "type": "Feature",
  "properties": {
    "addr:full":"12 Medway Parade Greenford Greater London UB6 8HR",
    "addr:housenumber":"12",
    "addr:postcode":"ub6 8hr",
    "addr:street":"Medway Parade",
    "iso:country":"GB",
    "sg:address":"12 Medway Parade",
    "sg:city":"Greenford",
    "sg:classifiers":[
        {
            "category":"Food & Beverages",
            "subcategory":"Supermarket",
            "type":"Retail Goods"
        }
    ],
    "sg:phone":"+44 20 8991 9113",
    "sg:postcode":"UB6 8HR",
    "sg:province":"Greater London",
    "wof:name":"H Hammond",
    "wof:placetype":"venue"
},
  "geometry": {"coordinates":[-0.332785,51.534706],"type":"Point"}
}