{
  "type": "Feature",
  "properties": {
    "addr:full":"44-45 Four Seasons Centre Mansfield Nottinghamshire NG18 1SX",
    "addr:housenumber":"44-45",
    "addr:postcode":"ng18 1sx",
    "addr:street":"Four",
    "iso:country":"GB",
    "sg:address":"44-45 Four Seasons Centre",
    "sg:city":"Mansfield",
    "sg:classifiers":[
        {
            "category":"Food & Beverages",
            "subcategory":"Bakery",
            "type":"Retail Goods"
        }
    ],
    "sg:phone":"+44 1623 636415",
    "sg:postcode":"NG18 1SX",
    "sg:province":"Nottinghamshire",
    "sg:tags":[
        "baker"
    ],
    "wof:name":"The Bakers Oven",
    "wof:placetype":"venue"
},
  "geometry": {"coordinates":[-1.201743,53.144024],"type":"Point"}
}