{
  "type": "Feature",
  "properties": {
    "addr:full":"134 York Way London Greater London N1 0AX",
    "addr:housenumber":"134",
    "addr:postcode":"n1 0ax",
    "addr:street":"York Way",
    "iso:country":"GB",
    "sg:address":"134 York Way",
    "sg:city":"London",
    "sg:classifiers":[
        {
            "category":"Food & Beverages",
            "subcategory":"Liquor & Beverages",
            "type":"Retail Goods"
        }
    ],
    "sg:phone":"+44 20 7837 0584",
    "sg:postcode":"N1 0AX",
    "sg:province":"Greater London",
    "sg:tags":[
        "beer",
        "wine",
        "spirit",
        "wines"
    ],
    "wof:name":"Gueler Off Licence",
    "wof:placetype":"venue"
},
  "geometry": {"coordinates":[-0.1218179986,51.5366668701],"type":"Point"}
}