{
  "type": "Feature",
  "properties": {
    "iso:country":"GB",
    "sg:address":"3 Fairford Clo",
    "sg:city":"Haywards Heath",
    "sg:classifiers":[
        {
            "category":"Building & Trades",
            "subcategory":"Construction",
            "type":"Services"
        }
    ],
    "sg:phone":"+44 1444 451135",
    "sg:postcode":"RH16 3EF",
    "sg:province":"East Sussex",
    "sg:tags":[
        "tiling",
        "contractor"
    ],
    "wof:name":"J H Poten",
    "wof:placetype":"venue"
},
  "geometry": {"coordinates":[-0.0992330015,51.0009803772],"type":"Point"}
}