{
  "type": "Feature",
  "properties": {
    "addr:full":"199 Acton La London Greater London W4 5DA",
    "addr:housenumber":"199",
    "addr:postcode":"w4 5da",
    "addr:street":"Acton La",
    "iso:country":"GB",
    "sg:address":"199 Acton La",
    "sg:city":"London",
    "sg:classifiers":[
        {
            "category":"Government",
            "subcategory":"Customs House",
            "type":"Public Place"
        }
    ],
    "sg:postcode":"W4 5DA",
    "sg:province":"Greater London",
    "sg:tags":[
        "clearance"
    ],
    "wof:name":"Acton Archives",
    "wof:placetype":"venue"
},
  "geometry": {"coordinates":[-0.264841,51.500031],"type":"Point"}
}