{
  "type": "Feature",
  "properties": {
    "addr:full":"168 Evington Road Leicester Leicestershire LE2 1HL",
    "addr:housenumber":"168",
    "addr:postcode":"le2 1hl",
    "addr:street":"Evington Road",
    "iso:country":"GB",
    "sg:address":"168 Evington Road",
    "sg:city":"Leicester",
    "sg:classifiers":[
        {
            "category":"Shopping",
            "subcategory":"News",
            "type":"Retail Goods"
        }
    ],
    "sg:phone":"+44 116 273 9227",
    "sg:postcode":"LE2 1HL",
    "sg:province":"Leicestershire",
    "sg:tags":[
        "newsagent"
    ],
    "wof:name":"Forbuoys",
    "wof:placetype":"venue"
},
  "geometry": {"coordinates":[-1.107799,52.625381],"type":"Point"}
}