{
  "type": "Feature",
  "properties": {
    "iso:country":"GB",
    "sg:address":"120 London Road",
    "sg:city":"Portsmouth",
    "sg:classifiers":[
        {
            "category":"Home & Garden",
            "subcategory":"Carpets & Floor Coverings",
            "type":"Retail Goods"
        }
    ],
    "sg:phone":"+44 23 9261 9933",
    "sg:postcode":"PO2 0NB",
    "sg:province":"Hampshire",
    "sg:tags":[
        "carpets",
        "rug",
        "matting"
    ],
    "wof:name":"Charisma Carpets Ltd.",
    "wof:placetype":"venue"
},
  "geometry": {"coordinates":[-1.079599,50.817032],"type":"Point"}
}