{
  "type": "Feature",
  "properties": {
    "addr:full":"337 Southbourne Gro Westcliff-on-sea Essex SS0 0AH",
    "addr:housenumber":"337",
    "addr:postcode":"ss0 0ah",
    "addr:street":"Southbourne Gro",
    "iso:country":"GB",
    "sg:address":"337 Southbourne Gro",
    "sg:city":"Westcliff-on-sea",
    "sg:classifiers":[
        {
            "category":"Building & Trades",
            "subcategory":"Construction",
            "type":"Services"
        }
    ],
    "sg:phone":"+44 1702 305124",
    "sg:postcode":"SS0 0AH",
    "sg:province":"Essex",
    "sg:tags":[
        "roofing"
    ],
    "wof:name":"Atel Roofing",
    "wof:placetype":"venue"
},
  "geometry": {"coordinates":[0.679599,51.558044],"type":"Point"}
}