{
  "type": "Feature",
  "properties": {
    "iso:country":"GB",
    "sg:address":"36-40 Walsall Road",
    "sg:city":"Willenhall",
    "sg:classifiers":[
        {
            "category":"Wholesale",
            "subcategory":"Non-durable Goods",
            "type":"Manufacturing & Wholesale Goods"
        }
    ],
    "sg:phone":"+44 1902 368788",
    "sg:postcode":"WV13 2EE",
    "sg:province":"West Midlands",
    "sg:tags":[
        "carry",
        "cash"
    ],
    "wof:name":"Daner Ltd.",
    "wof:placetype":"venue"
},
  "geometry": {"coordinates":[-2.042901,52.585697],"type":"Point"}
}