{
  "type": "Feature",
  "properties": {
    "addr:full":"Batemans Accountants, Unit 19 Tolsons Mill Tamworth Staffordshire B78 3QB",
    "addr:housenumber":"unit 19",
    "addr:postcode":"b78 3qb",
    "addr:street":"Tolsons Mill",
    "iso:country":"GB",
    "sg:address":"Batemans Accountants, Unit 19 Tolsons Mill",
    "sg:city":"Tamworth",
    "sg:classifiers":[
        {
            "category":"Retail",
            "subcategory":"Auto Repair",
            "type":"Services"
        }
    ],
    "sg:postcode":"B78 3QB",
    "sg:province":"Staffordshire",
    "sg:tags":[
        "modification",
        "car",
        "classic"
    ],
    "wof:name":"Spridgebits Ltd",
    "wof:placetype":"venue"
},
  "geometry": {"coordinates":[-1.6984,52.612549],"type":"Point"}
}