{
  "type": "Feature",
  "properties": {
    "addr:full":"1 Royal Street London Greater London SE1 7LL",
    "addr:housenumber":"1",
    "addr:postcode":"se1 7ll",
    "addr:street":"Royal Street",
    "iso:country":"GB",
    "sg:address":"1 Royal Street",
    "sg:city":"London",
    "sg:classifiers":[
        {
            "category":"Organizations",
            "subcategory":"Non-profit Organization",
            "type":"Services"
        }
    ],
    "sg:phone":"+44 20 7582 9996",
    "sg:postcode":"SE1 7LL",
    "sg:province":"Greater London",
    "sg:tags":[
        "organisation",
        "voluntary",
        "charity"
    ],
    "wof:name":"Cicely Northcote Trust",
    "wof:placetype":"venue"
},
  "geometry": {"coordinates":[-0.116734,51.498878],"type":"Point"}
}