{
  "type": "Feature",
  "properties": {
    "addr:full":"Werneth Road, Woodley Stockport Cheshire SK6 1HR",
    "addr:postcode":"sk6 1hr",
    "addr:street":"Werneth Road",
    "iso:country":"GB",
    "sg:address":"Werneth Road, Woodley",
    "sg:city":"Stockport",
    "sg:classifiers":[
        {
            "category":"Education",
            "subcategory":"School",
            "type":"Public Place"
        }
    ],
    "sg:phone":"+44 161 430 6318",
    "sg:postcode":"SK6 1HR",
    "sg:province":"Cheshire",
    "sg:tags":[
        "local",
        "authority"
    ],
    "wof:name":"Greave Primary School",
    "wof:placetype":"venue"
},
  "geometry": {"coordinates":[-2.0975420475,53.4265708923],"type":"Point"}
}