{
  "type": "Feature",
  "properties": {
    "iso:country":"GB",
    "sg:address":"166-168 Wellesley Road, Methil",
    "sg:city":"Leven",
    "sg:classifiers":[
        {
            "category":"Parking",
            "type":"Transportation"
        }
    ],
    "sg:postcode":"KY8 3AQ",
    "sg:province":"Fife",
    "sg:tags":[
        "car",
        "valet"
    ],
    "wof:name":"Martin's Valet Services",
    "wof:placetype":"venue"
},
  "geometry": {"coordinates":[-3.012104,56.186718],"type":"Point"}
}