{
  "type": "Feature",
  "properties": {
    "addr:full":"35 Church Street Haverfordwest Pembrokeshire SA61 2EA",
    "addr:housenumber":"35",
    "addr:postcode":"sa61 2ea",
    "addr:street":"Church Street",
    "iso:country":"GB",
    "sg:address":"35 Church Street",
    "sg:city":"Haverfordwest",
    "sg:classifiers":[
        {
            "category":"Retail",
            "subcategory":"Repair Shop",
            "type":"Services"
        }
    ],
    "sg:postcode":"SA61 2EA",
    "sg:province":"Pembrokeshire",
    "sg:tags":[
        "radio",
        "television",
        "video"
    ],
    "wof:name":"Sound & Vision Services",
    "wof:placetype":"venue"
},
  "geometry": {"coordinates":[-4.971855,51.80241],"type":"Point"}
}