{
  "type": "Feature",
  "properties": {
    "iso:country":"GB",
    "sg:address":"2 Bishop Street",
    "sg:city":"Leicester",
    "sg:classifiers":[
        {
            "category":"Personal",
            "subcategory":"Beauty Salon",
            "type":"Services"
        }
    ],
    "sg:phone":"+44 116 255 8774",
    "sg:postcode":"LE1 6AF",
    "sg:province":"Leicestershire",
    "sg:tags":[
        "unisex",
        "hairdresser"
    ],
    "wof:name":"Mantini Beauty Clinic",
    "wof:placetype":"venue"
},
  "geometry": {"coordinates":[-1.130892992,52.6337356567],"type":"Point"}
}