{
  "type": "Feature",
  "properties": {
    "iso:country":"GB",
    "sg:address":"196 Norwich Road",
    "sg:city":"Wisbech",
    "sg:classifiers":[
        {
            "category":"Building & Trades",
            "subcategory":"Construction",
            "type":"Services"
        }
    ],
    "sg:phone":"+44 1945 584219",
    "sg:postcode":"PE13 3TB",
    "sg:province":"Cambridgeshire",
    "sg:tags":[
        "dry",
        "lining",
        "plasterers",
        "screeders"
    ],
    "wof:name":"Michael Ward Plastering & Artexing",
    "wof:placetype":"venue"
},
  "geometry": {"coordinates":[0.17368,52.665852],"type":"Point"}
}