{
  "type": "Feature",
  "properties": {
    "iso:country":"GB",
    "sg:address":"7 Stubbington Green",
    "sg:city":"Fareham",
    "sg:classifiers":[
        {
            "category":"Shopping",
            "subcategory":"Gifts & Souvenirs",
            "type":"Retail Goods"
        }
    ],
    "sg:phone":"+44 1329 664334",
    "sg:postcode":"PO14 2JG",
    "sg:province":"Hampshire",
    "sg:tags":[
        "shop"
    ],
    "wof:name":"Best Wishes",
    "wof:placetype":"venue"
},
  "geometry": {"coordinates":[-1.2142989635,50.825592041],"type":"Point"}
}