{
  "type": "Feature",
  "properties": {
    "iso:country":"GB",
    "sg:address":"Bourne Fields, Twyford",
    "sg:city":"Winchester",
    "sg:classifiers":[
        {
            "category":"Banks & Credit Unions",
            "subcategory":"Bureau De Change",
            "type":"Services"
        }
    ],
    "sg:phone":"+44 1962 714183",
    "sg:postcode":"SO21 1NY",
    "sg:province":"Hampshire",
    "sg:tags":[
        "town",
        "consultant",
        "planning"
    ],
    "wof:name":"Boxhill Consultants Ltd.",
    "wof:placetype":"venue"
},
  "geometry": {"coordinates":[-1.312739,51.02359],"type":"Point"}
}