{
  "type": "Feature",
  "properties": {
    "iso:country":"GB",
    "sg:address":"9-10 Market Square",
    "sg:city":"Biggleswade",
    "sg:classifiers":[
        {
            "category":"Shopping",
            "subcategory":"Pharmacy",
            "type":"Retail Goods"
        }
    ],
    "sg:phone":"+44 1767 313278",
    "sg:postcode":"SG18 8AS",
    "sg:province":"Bedfordshire",
    "sg:tags":[
        "pharmacist",
        "chemist"
    ],
    "wof:name":"Boots the Chemists",
    "wof:placetype":"venue"
},
  "geometry": {"coordinates":[-0.265004009,52.0864067078],"type":"Point"}
}