{
  "type": "Feature",
  "properties": {
    "addr:full":"18 Alderman Pl, Knightswood Glasgow Glasgow City G13 3YH",
    "addr:housenumber":"18",
    "addr:postcode":"g13 3yh",
    "addr:street":"Alderman Pl",
    "iso:country":"GB",
    "sg:address":"18 Alderman Pl, Knightswood",
    "sg:city":"Glasgow",
    "sg:classifiers":[
        {
            "category":"Arts & Performance",
            "subcategory":"Music",
            "type":"Entertainment"
        }
    ],
    "sg:postcode":"G13 3YH",
    "sg:province":"Glasgow City",
    "sg:tags":[
        "mobile",
        "disco"
    ],
    "wof:name":"Stevie,Gaston,",
    "wof:placetype":"venue"
},
  "geometry": {"coordinates":[-4.3469491005,55.8879508972],"type":"Point"}
}