{
  "type": "Feature",
  "properties": {
    "addr:full":"3 Heol Aradur, Danes Crt Cardiff Cardiff CF5 2RE",
    "addr:housenumber":"3",
    "addr:postcode":"cf5 2re",
    "addr:street":"Heol Aradur Danes Crt",
    "iso:country":"GB",
    "sg:address":"3 Heol Aradur, Danes Crt",
    "sg:city":"Cardiff",
    "sg:classifiers":[
        {
            "category":"Autos & Motor Vehicles",
            "subcategory":"Motorcycle Sales",
            "type":"Retail Goods"
        },
        {
            "category":"Retail",
            "subcategory":"Auto Rental",
            "type":"Services"
        },
        {
            "category":"Bus Charters",
            "type":"Transportation"
        }
    ],
    "sg:phone":"+44 29 2056 1531",
    "sg:postcode":"CF5 2RE",
    "sg:province":"Cardiff",
    "sg:tags":[
        "chauffeur",
        "driven",
        "hire",
        "coach",
        "car"
    ],
    "wof:name":"Wilson & Wilson Executive Car Service",
    "wof:placetype":"venue"
},
  "geometry": {"coordinates":[-3.24379,51.503811],"type":"Point"}
}