{
  "type": "Feature",
  "properties": {
    "addr:full":"25-26 The Forum, North Hykeham Lincoln Lincolnshire LN6 8HW",
    "addr:housenumber":"25-26",
    "addr:postcode":"ln6 8hw",
    "addr:street":"The Forum North",
    "iso:country":"GB",
    "sg:address":"25-26 The Forum, North Hykeham",
    "sg:city":"Lincoln",
    "sg:classifiers":[
        {
            "category":"Banks & Credit Unions",
            "subcategory":"Bank",
            "type":"Services"
        }
    ],
    "sg:phone":"+44 1522 500015",
    "sg:postcode":"LN6 8HW",
    "sg:province":"Lincolnshire",
    "sg:tags":[
        "financial",
        "institution"
    ],
    "wof:name":"Barclays Bank Plc",
    "wof:placetype":"venue"
},
  "geometry": {"coordinates":[-0.58044,53.18766],"type":"Point"}
}