{
  "type": "Feature",
  "properties": {
    "addr:full":"Mcclaren Court, Willow Court Moorgate Greater London EC2A 4QB",
    "addr:postcode":"ec2a 4qb",
    "addr:street":"Mcclaren Court Willow Court Moorgate",
    "iso:country":"GB",
    "sg:address":"Mcclaren Court, Willow Court",
    "sg:city":"Moorgate",
    "sg:classifiers":[
        {
            "category":"Professional",
            "subcategory":"Business Services",
            "type":"Services"
        }
    ],
    "sg:phone":"+44 20 7550 3000",
    "sg:postcode":"EC2A 4QB",
    "sg:province":"Greater London",
    "sg:tags":[
        "food",
        "import",
        "export",
        "agent"
    ],
    "wof:name":"Ewart McLaren Ltd",
    "wof:placetype":"venue"
},
  "geometry": {"coordinates":[-0.0835490003,51.5252685547],"type":"Point"}
}