{
  "type": "Feature",
  "properties": {
    "iso:country":"GB",
    "sg:address":"22 Ladypark",
    "sg:city":"Gateshead",
    "sg:classifiers":[
        {
            "category":"Recreation",
            "subcategory":"Water Park",
            "type":"Entertainment"
        },
        {
            "category":"Manufacturing",
            "subcategory":"Musical Instruments",
            "type":"Manufacturing & Wholesale Goods"
        }
    ],
    "sg:phone":"+44 191 482 4389",
    "sg:postcode":"NE11 0HD",
    "sg:province":"Tyne and Wear",
    "sg:tags":[
        "drum",
        "keg",
        "cask",
        "drums",
        "supplier",
        "barrel",
        "manufacturer"
    ],
    "wof:name":"Northern Tubs",
    "wof:placetype":"venue"
},
  "geometry": {"coordinates":[-1.622379,54.927269],"type":"Point"}
}