{
  "type": "Feature",
  "properties": {
    "addr:full":"12 Queen Street Colchester Essex CO1 2PJ",
    "addr:housenumber":"12",
    "addr:postcode":"co1 2pj",
    "addr:street":"Queen Street",
    "iso:country":"GB",
    "sg:address":"12 Queen Street",
    "sg:city":"Colchester",
    "sg:classifiers":[
        {
            "category":"Shopping",
            "subcategory":"Department Store",
            "type":"Retail Goods"
        },
        {
            "category":"Sports & Exercise",
            "subcategory":"Sports Center",
            "type":"Entertainment"
        },
        {
            "category":"Sports & Exercise",
            "subcategory":"Ski Resort",
            "type":"Entertainment"
        }
    ],
    "sg:phone":"+44 1206 761880",
    "sg:postcode":"CO1 2PJ",
    "sg:province":"Essex",
    "sg:tags":[
        "shop",
        "equipment"
    ],
    "sg:website":"http://-",
    "wof:name":"More Sports",
    "wof:placetype":"venue"
},
  "geometry": {"coordinates":[0.9034000039,51.887878418],"type":"Point"}
}