{
  "type": "Feature",
  "properties": {
    "iso:country":"GB",
    "sg:address":"4 The Square, Cranborne",
    "sg:city":"Wimborne",
    "sg:classifiers":[
        {
            "category":"Travel",
            "subcategory":"Hotels & Motels",
            "type":"Entertainment"
        },
        {
            "category":"Bars & Pubs",
            "type":"Food & Drink"
        }
    ],
    "sg:phone":"+44 1725 517456",
    "sg:postcode":"BH21 5PR",
    "sg:province":"Dorset",
    "sg:tags":[
        "house",
        "public",
        "guest",
        "activity"
    ],
    "wof:name":"Sheaf Of Arrows",
    "wof:placetype":"venue"
},
  "geometry": {"coordinates":[-1.922386,50.919247],"type":"Point"}
}