{
  "type": "Feature",
  "properties": {
    "addr:full":"Unit 2 Blackhouse Indust Est Peterhead Aberdeenshire AB42 1BW",
    "addr:housenumber":"unit 2",
    "addr:postcode":"ab42 1bw",
    "addr:street":"Indust",
    "iso:country":"GB",
    "sg:address":"Unit 2 Blackhouse Indust Est",
    "sg:city":"Peterhead",
    "sg:classifiers":[
        {
            "category":"Manufacturing",
            "subcategory":"Building Materials",
            "type":"Manufacturing & Wholesale Goods"
        }
    ],
    "sg:phone":"+44 1779 474499",
    "sg:postcode":"AB42 1BW",
    "sg:province":"Aberdeenshire",
    "sg:tags":[
        "merchant",
        "builder"
    ],
    "wof:name":"Graham Builders Merchants",
    "wof:placetype":"venue"
},
  "geometry": {"coordinates":[-1.7874319553,57.5151901245],"type":"Point"}
}