{
  "type": "Feature",
  "properties": {
    "addr:full":"9 Olliver Clo Halesowen West Midlands B62 0QB",
    "addr:housenumber":"9",
    "addr:postcode":"b62 0qb",
    "addr:street":"Olliver Clo",
    "iso:country":"GB",
    "sg:address":"9 Olliver Clo",
    "sg:city":"Halesowen",
    "sg:classifiers":[
        {
            "category":"Building & Trades",
            "subcategory":"Construction",
            "type":"Services"
        }
    ],
    "sg:phone":"+44 121 421 3373",
    "sg:postcode":"B62 0QB",
    "sg:province":"West Midlands",
    "sg:tags":[
        "flooring"
    ],
    "wof:name":"Lay-Kem Industrial Flooring",
    "wof:placetype":"venue"
},
  "geometry": {"coordinates":[-2.01584,52.445499],"type":"Point"}
}