{
  "type": "Feature",
  "properties": {
    "addr:full":"6 Faside Avenue Court, Wallyford, East Lothian Musselburgh City of Edinburgh EH21 8BT",
    "addr:housenumber":"6",
    "addr:postcode":"eh21 8bt",
    "addr:street":"Faside Avenue Court",
    "iso:country":"GB",
    "sg:address":"6 Faside Avenue Court, Wallyford, East Lothian",
    "sg:city":"Musselburgh",
    "sg:classifiers":[
        {
            "category":"Building & Trades",
            "subcategory":"Construction",
            "type":"Services"
        }
    ],
    "sg:phone":"+44 131 653 2194",
    "sg:postcode":"EH21 8BT",
    "sg:province":"City of Edinburgh",
    "sg:tags":[
        "roofing"
    ],
    "wof:name":"K & S Roofing",
    "wof:placetype":"venue"
},
  "geometry": {"coordinates":[-3.0145859718,55.9337272644],"type":"Point"}
}