{
  "type": "Feature",
  "properties": {
    "iso:country":"GB",
    "sg:address":"55-57 Lomond Road",
    "sg:city":"Manchester",
    "sg:classifiers":[
        {
            "category":"Shopping",
            "subcategory":"News",
            "type":"Retail Goods"
        },
        {
            "category":"Food & Beverages",
            "subcategory":"Groceries & Convenience Stores",
            "type":"Retail Goods"
        }
    ],
    "sg:phone":"+44 161 437 3348",
    "sg:postcode":"M22 5JB",
    "sg:province":"Greater Manchester",
    "sg:tags":[
        "newsagent"
    ],
    "wof:name":"Philip Bowden & Josephine",
    "wof:placetype":"venue"
},
  "geometry": {"coordinates":[-2.2462320328,53.3768043518],"type":"Point"}
}