{
  "type": "Feature",
  "properties": {
    "addr:full":"Suite 6, Challenge House, Sherwood Drive Milton Keynes Buckinghamshire MK3 6DP",
    "addr:housenumber":"suite 6 challenge house",
    "addr:postcode":"mk3 6dp",
    "addr:street":"Sherwood Drive",
    "iso:country":"GB",
    "sg:address":"Suite 6, Challenge House, Sherwood Drive",
    "sg:city":"Milton Keynes",
    "sg:classifiers":[
        {
            "category":"Professional",
            "subcategory":"Computer Services",
            "type":"Services"
        }
    ],
    "sg:phone":"+44 1908 625100",
    "sg:postcode":"MK3 6DP",
    "sg:province":"Buckinghamshire",
    "sg:tags":[
        "consultant"
    ],
    "wof:name":"Bloor Research Ltd.",
    "wof:placetype":"venue"
},
  "geometry": {"coordinates":[-0.7381759882,51.9985198975],"type":"Point"}
}