{
  "type": "Feature",
  "properties": {
    "addr:full":"19 Maple Way, Earl Shilton Leicester Leicestershire LE9 7HW",
    "addr:housenumber":"19",
    "addr:postcode":"le9 7hw",
    "addr:street":"Maple Way",
    "iso:country":"GB",
    "sg:address":"19 Maple Way, Earl Shilton",
    "sg:city":"Leicester",
    "sg:classifiers":[
        {
            "category":"Recreation",
            "subcategory":"Water Park",
            "type":"Entertainment"
        },
        {
            "category":"Sports & Exercise",
            "subcategory":"Sports Center",
            "type":"Entertainment"
        }
    ],
    "sg:phone":"+44 1455 846505",
    "sg:postcode":"LE9 7HW",
    "sg:province":"Leicestershire",
    "sg:tags":[
        "activity",
        "watersport"
    ],
    "wof:name":"Terrapin Wetsuits",
    "wof:placetype":"venue"
},
  "geometry": {"coordinates":[-1.3228540421,52.568145752],"type":"Point"}
}