{
  "type": "Feature",
  "properties": {
    "addr:full":"Rutland House, Hargreaves Road, Groundwell Industrial Estate Swindon Wiltshire SN25 5AZ",
    "addr:housenumber":"estate",
    "addr:postcode":"sn25 5az",
    "addr:street":"Hargreaves Road Groundwell Industrial",
    "iso:country":"GB",
    "sg:address":"Rutland House, Hargreaves Road, Groundwell Industrial Estate",
    "sg:city":"Swindon",
    "sg:classifiers":[
        {
            "category":"Professional",
            "subcategory":"Detective & Security Services",
            "type":"Services"
        }
    ],
    "sg:phone":"+44 1793 747700",
    "sg:postcode":"SN25 5AZ",
    "sg:province":"Wiltshire",
    "sg:tags":[
        "equipment"
    ],
    "wof:name":"Thorn Secure Science Ltd.",
    "wof:placetype":"venue"
},
  "geometry": {"coordinates":[-1.7739739418,51.5967483521],"type":"Point"}
}