{
  "type": "Feature",
  "properties": {
    "addr:full":"69 Britannia Road London Greater London SW6 2JR",
    "addr:housenumber":"69",
    "addr:postcode":"sw6 2jr",
    "addr:street":"Britannia Road",
    "iso:country":"GB",
    "sg:address":"69 Britannia Road",
    "sg:city":"London",
    "sg:classifiers":[
        {
            "category":"Organizations",
            "subcategory":"Membership Organization",
            "type":"Services"
        }
    ],
    "sg:phone":"+44 20 7736 2703",
    "sg:postcode":"SW6 2JR",
    "sg:province":"Greater London",
    "sg:tags":[
        "club"
    ],
    "wof:name":"Fulham Club & Institute Ltd.",
    "wof:placetype":"venue"
},
  "geometry": {"coordinates":[-0.191919,51.47974],"type":"Point"}
}