{
  "type": "Feature",
  "properties": {
    "addr:full":"5 Park Pl Truro Cornwall TR2 4EG",
    "addr:housenumber":"5",
    "addr:postcode":"tr2 4eg",
    "addr:street":"Park Pl",
    "iso:country":"GB",
    "sg:address":"5 Park Pl",
    "sg:city":"Truro",
    "sg:classifiers":[
        {
            "category":"Communications",
            "subcategory":"Newspaper",
            "type":"Services"
        }
    ],
    "sg:phone":"+44 1726 882480",
    "sg:postcode":"TR2 4EG",
    "sg:province":"Cornwall",
    "sg:tags":[
        "magazine"
    ],
    "wof:name":"Cornwall Review Newspaper For Tourism",
    "wof:placetype":"venue"
},
  "geometry": {"coordinates":[-4.9298000336,50.3200912476],"type":"Point"}
}