{
  "type": "Feature",
  "properties": {
    "addr:full":"5 Everest Road Christchurch Dorset BH23 3AY",
    "addr:housenumber":"5",
    "addr:postcode":"bh23 3ay",
    "addr:street":"Everest Road",
    "iso:country":"GB",
    "sg:address":"5 Everest Road",
    "sg:city":"Christchurch",
    "sg:classifiers":[
        {
            "category":"Manufacturing",
            "subcategory":"Petroleum Products",
            "type":"Manufacturing & Wholesale Goods"
        },
        {
            "category":"Building & Trades",
            "subcategory":"Construction",
            "type":"Services"
        }
    ],
    "sg:phone":"+44 1202 471771",
    "sg:postcode":"BH23 3AY",
    "sg:province":"Dorset",
    "sg:tags":[
        "double",
        "glazing",
        "installers"
    ],
    "wof:name":"Parkes Glass & Glazing",
    "wof:placetype":"venue"
},
  "geometry": {"coordinates":[-1.7582950592,50.742023468],"type":"Point"}
}