{
  "type": "Feature",
  "properties": {
    "iso:country":"GB",
    "sg:address":"Shelah Road",
    "sg:city":"Halesowen",
    "sg:classifiers":[
        {
            "category":"Social Services",
            "subcategory":"Adult Care",
            "type":"Services"
        }
    ],
    "sg:phone":"+44 121 550 9555",
    "sg:postcode":"B63 3XL",
    "sg:province":"West Midlands",
    "sg:tags":[
        "lubrication"
    ],
    "wof:name":"Hayley Lube",
    "wof:placetype":"venue"
},
  "geometry": {"coordinates":[-2.0574769974,52.4613342285],"type":"Point"}
}