{
  "type": "Feature",
  "properties": {
    "iso:country":"GB",
    "sg:address":"56 High Street, Bedmond",
    "sg:city":"Abbots Langley",
    "sg:classifiers":[
        {
            "category":"Autos & Motor Vehicles",
            "subcategory":"Fuel & Gas Station",
            "type":"Retail Goods"
        }
    ],
    "sg:phone":"+44 1923 261538",
    "sg:postcode":"WD5 0RH",
    "sg:province":"Hertfordshire",
    "sg:tags":[
        "petrol",
        "filling"
    ],
    "wof:name":"Q8 Bedmond",
    "wof:placetype":"venue"
},
  "geometry": {"coordinates":[-0.410399,51.721722],"type":"Point"}
}