{
  "type": "Feature",
  "properties": {
    "iso:country":"GB",
    "sg:address":"The Acres, Gills Lane, Rooksbridge",
    "sg:city":"Axbridge",
    "sg:classifiers":[
        {
            "category":"Shopping",
            "subcategory":"Pets & Pet Supplies",
            "type":"Retail Goods"
        }
    ],
    "sg:phone":"+44 1934 750743",
    "sg:postcode":"BS26 2TZ",
    "sg:province":"Somerset",
    "sg:tags":[
        "food"
    ],
    "wof:name":"Chiltern Reptiles",
    "wof:placetype":"venue"
},
  "geometry": {"coordinates":[-2.818409,51.288391],"type":"Point"}
}