{
  "type": "Feature",
  "properties": {
    "iso:country":"GB",
    "sg:address":"Unit 23 Melmerby Indstl Est, Melmerby",
    "sg:city":"Ripon",
    "sg:classifiers":[
        {
            "category":"Shopping",
            "subcategory":"Antiques",
            "type":"Retail Goods"
        }
    ],
    "sg:postcode":"HG4 5HQ",
    "sg:province":"North Yorkshire",
    "wof:name":"Kindon Antiques Ltd",
    "wof:placetype":"venue"
},
  "geometry": {"coordinates":[-1.4871350527,54.1862297058],"type":"Point"}
}