{
  "type": "Feature",
  "properties": {
    "iso:country":"GB",
    "sg:address":"Abbey Hall, Bretford Road, Brinklow",
    "sg:city":"Rugby",
    "sg:classifiers":[
        {
            "category":"Farming",
            "subcategory":"Farm",
            "type":"Manufacturing & Wholesale Goods"
        }
    ],
    "sg:postcode":"CV23 0NB",
    "sg:province":"Northamptonshire",
    "sg:tags":[
        "mixed",
        "crop"
    ],
    "wof:name":"M G & M Barnes",
    "wof:placetype":"venue"
},
  "geometry": {"coordinates":[-1.368624,52.391285],"type":"Point"}
}