{
  "type": "Feature",
  "properties": {
    "addr:full":"73 Letterston Rd Cardiff Caerphilly CF3 8PU",
    "addr:housenumber":"73",
    "addr:postcode":"cf3 8pu",
    "addr:street":"Letterston Rd",
    "iso:country":"GB",
    "sg:address":"73 Letterston Rd",
    "sg:city":"Cardiff",
    "sg:classifiers":[
        {
            "category":"Building & Trades",
            "subcategory":"Landscaping Services",
            "type":"Services"
        }
    ],
    "sg:phone":"+44 7774 117446",
    "sg:postcode":"CF3 8PU",
    "sg:province":"Caerphilly",
    "sg:tags":[
        "gardening"
    ],
    "wof:name":"All Seasons Garden Services",
    "wof:placetype":"venue"
},
  "geometry": {"coordinates":[-3.1152319908,51.515460968],"type":"Point"}
}