{
  "type": "Feature",
  "properties": {
    "addr:full":"3 St Swithuns Road, Kennington Oxford Oxfordshire OX1 5PT",
    "addr:housenumber":"3",
    "addr:postcode":"ox1 5pt",
    "addr:street":"St Swithuns Road",
    "iso:country":"GB",
    "sg:address":"3 St Swithuns Road, Kennington",
    "sg:city":"Oxford",
    "sg:classifiers":[
        {
            "category":"Building & Trades",
            "subcategory":"Construction",
            "type":"Services"
        }
    ],
    "sg:phone":"+44 1865 739661",
    "sg:postcode":"OX1 5PT",
    "sg:province":"Oxfordshire",
    "sg:tags":[
        "conversion",
        "property",
        "loft",
        "converter"
    ],
    "wof:name":"Apex Construction",
    "wof:placetype":"venue"
},
  "geometry": {"coordinates":[-1.2449419498,51.7123527527],"type":"Point"}
}