{
  "type": "Feature",
  "properties": {
    "addr:full":"6 Enderby Road Indust Est Leicester Leicestershire LE8 6HZ",
    "addr:housenumber":"6",
    "addr:postcode":"le8 6hz",
    "addr:street":"Enderby Road",
    "iso:country":"GB",
    "sg:address":"6 Enderby Road Indust Est",
    "sg:city":"Leicester",
    "sg:classifiers":[
        {
            "category":"Manufacturing",
            "subcategory":"Textiles",
            "type":"Manufacturing & Wholesale Goods"
        }
    ],
    "sg:phone":"+44 116 284 1166",
    "sg:postcode":"LE8 6HZ",
    "sg:province":"Leicestershire",
    "sg:tags":[
        "knitwear"
    ],
    "wof:name":"Leo Textile Printing Ltd",
    "wof:placetype":"venue"
},
  "geometry": {"coordinates":[-1.1720490456,52.5754089355],"type":"Point"}
}