{
  "type": "Feature",
  "properties": {
    "iso:country":"GB",
    "sg:address":"14 Station Road, New Barnet",
    "sg:city":"Barnet",
    "sg:classifiers":[
        {
            "category":"Sports & Exercise",
            "subcategory":"Sports Center",
            "type":"Entertainment"
        }
    ],
    "sg:phone":"+44 20 8449 2223",
    "sg:postcode":"EN5 1QW",
    "sg:province":"Hertfordshire",
    "sg:tags":[
        "shop",
        "good"
    ],
    "wof:name":"Right Sport Ltd.",
    "wof:placetype":"venue"
},
  "geometry": {"coordinates":[-0.176545,51.649342],"type":"Point"}
}