{
  "type": "Feature",
  "properties": {
    "iso:country":"GB",
    "sg:address":"16 Wickham Avenue",
    "sg:city":"Wetherby",
    "sg:classifiers":[
        {
            "category":"Freight",
            "type":"Transportation"
        }
    ],
    "sg:phone":"+44 1937 845080",
    "sg:postcode":"LS23 6NJ",
    "sg:province":"West Yorkshire",
    "sg:tags":[
        "haulage",
        "road"
    ],
    "wof:name":"William Wilson",
    "wof:placetype":"venue"
},
  "geometry": {"coordinates":[-1.3614139557,53.9041137695],"type":"Point"}
}