{
  "type": "Feature",
  "properties": {
    "addr:full":"11 Saxon Way Bourne Lincolnshire PE10 9QY",
    "addr:housenumber":"11",
    "addr:postcode":"pe10 9qy",
    "addr:street":"Saxon Way",
    "iso:country":"GB",
    "sg:address":"11 Saxon Way",
    "sg:city":"Bourne",
    "sg:classifiers":[
        {
            "category":"Building & Trades",
            "subcategory":"Construction",
            "type":"Services"
        }
    ],
    "sg:postcode":"PE10 9QY",
    "sg:province":"Lincolnshire",
    "sg:tags":[
        "decorator",
        "painter"
    ],
    "wof:name":"Goode Decorating",
    "wof:placetype":"venue"
},
  "geometry": {"coordinates":[-0.387398,52.770966],"type":"Point"}
}