{
  "type": "Feature",
  "properties": {
    "addr:full":"5 Wharfage, Iorobridge Telford Shropshire TF8 7AW",
    "addr:housenumber":"5",
    "addr:postcode":"tf8 7aw",
    "addr:street":"Wharfage Iorobridge",
    "iso:country":"GB",
    "sg:address":"5 Wharfage, Iorobridge",
    "sg:city":"Telford",
    "sg:classifiers":[
        {
            "category":"Professional",
            "subcategory":"Printing & Photocopies",
            "type":"Services"
        }
    ],
    "sg:phone":"+44 1952 433785",
    "sg:postcode":"TF8 7AW",
    "sg:province":"Shropshire",
    "sg:tags":[
        "printer"
    ],
    "wof:name":"Ness Print Ltd",
    "wof:placetype":"venue"
},
  "geometry": {"coordinates":[-2.493809,52.630283],"type":"Point"}
}