{
  "type": "Feature",
  "properties": {
    "iso:country":"GB",
    "sg:address":"139 London Road",
    "sg:city":"Edinburgh",
    "sg:classifiers":[
        {
            "category":"Cafe",
            "type":"Food & Drink"
        }
    ],
    "sg:postcode":"EH7 6AE",
    "sg:province":"City of Edinburgh",
    "sg:tags":[
        "tea",
        "room"
    ],
    "wof:name":"S L F Group",
    "wof:placetype":"venue"
},
  "geometry": {"coordinates":[-3.157859087,55.9558181763],"type":"Point"}
}