{
  "type": "Feature",
  "properties": {
    "addr:full":"Stanley Ho, High St Polegate East Sussex BN26 5TB",
    "addr:postcode":"bn26 5tb",
    "addr:street":"High St Polegate",
    "iso:country":"GB",
    "sg:address":"Stanley Ho, High St",
    "sg:city":"Polegate",
    "sg:classifiers":[
        {
            "category":"Personal",
            "type":"Services"
        }
    ],
    "sg:phone":"+44 1323 871122",
    "sg:postcode":"BN26 5TB",
    "sg:province":"East Sussex",
    "sg:tags":[
        "party",
        "organiser"
    ],
    "wof:name":"Harvey & May",
    "wof:placetype":"venue"
},
  "geometry": {"coordinates":[0.244123,50.821339],"type":"Point"}
}