{
  "type": "Feature",
  "properties": {
    "addr:full":"The Westminster South Chowdene, Chowdene Bank Gateshead Tyne and Wear NE9 6JE",
    "addr:postcode":"ne9 6je",
    "addr:street":"South",
    "iso:country":"GB",
    "sg:address":"The Westminster South Chowdene, Chowdene Bank",
    "sg:city":"Gateshead",
    "sg:classifiers":[
        {
            "category":"Health Services",
            "subcategory":"Nursing And Care Facility",
            "type":"Services"
        }
    ],
    "sg:phone":"+44 191 491 0861",
    "sg:postcode":"NE9 6JE",
    "sg:province":"Tyne and Wear",
    "sg:tags":[
        "home",
        "residential"
    ],
    "wof:name":"South Chowdene Nursing Home",
    "wof:placetype":"venue"
},
  "geometry": {"coordinates":[-1.59954,54.928982],"type":"Point"}
}