{
  "type": "Feature",
  "properties": {
    "addr:full":"70 Barton Hill Rd Torquay Devon TQ2 8JA",
    "addr:housenumber":"70",
    "addr:postcode":"tq2 8ja",
    "addr:street":"Barton Hill Rd",
    "iso:country":"GB",
    "sg:address":"70 Barton Hill Rd",
    "sg:city":"Torquay",
    "sg:classifiers":[
        {
            "category":"Professional",
            "subcategory":"Art Services",
            "type":"Services"
        }
    ],
    "sg:phone":"+44 1803 311685",
    "sg:postcode":"TQ2 8JA",
    "sg:province":"Devon",
    "sg:tags":[
        "photographer"
    ],
    "wof:name":"Sandercock Vic",
    "wof:placetype":"venue"
},
  "geometry": {"coordinates":[-3.540672,50.489143],"type":"Point"}
}