{
  "type": "Feature",
  "properties": {
    "iso:country":"GB",
    "sg:address":"Heritage House, Albion Drive, Thurnscoe",
    "sg:city":"Rotherham",
    "sg:classifiers":[
        {
            "category":"Professional",
            "subcategory":"Engineering",
            "type":"Services"
        }
    ],
    "sg:phone":"+44 1709 881703",
    "sg:postcode":"S63 0BA",
    "sg:province":"South Yorkshire",
    "wof:name":"Maan Engineering Ltd.",
    "wof:placetype":"venue"
},
  "geometry": {"coordinates":[-1.293104,53.545589],"type":"Point"}
}