{
  "type": "Feature",
  "properties": {
    "addr:full":"Whitelees Road Lanark South Lanarkshire ML11 7RX",
    "addr:postcode":"ml11 7rx",
    "addr:street":"Whitelees Road",
    "iso:country":"GB",
    "sg:address":"Whitelees Road",
    "sg:city":"Lanark",
    "sg:classifiers":[
        {
            "category":"Sports & Exercise",
            "subcategory":"Golf",
            "type":"Entertainment"
        }
    ],
    "sg:phone":"+44 1555 663219",
    "sg:postcode":"ML11 7RX",
    "sg:province":"South Lanarkshire",
    "sg:tags":[
        "club",
        "course",
        "equipment"
    ],
    "wof:name":"Lanark Golf Club",
    "wof:placetype":"venue"
},
  "geometry": {"coordinates":[-3.7366991043,55.7043762207],"type":"Point"}
}