{
  "type": "Feature",
  "properties": {
    "addr:full":"Farmhouse, Springs Farm, Coalpit Lane Rugeley Staffordshire WS15 1EW",
    "addr:postcode":"ws15 1ew",
    "addr:street":"Springs;Coalpit Lane",
    "iso:country":"GB",
    "sg:address":"Farmhouse, Springs Farm, Coalpit Lane",
    "sg:city":"Rugeley",
    "sg:classifiers":[
        {
            "category":"Building & Trades",
            "subcategory":"Construction",
            "type":"Services"
        }
    ],
    "sg:phone":"+44 1889 586152",
    "sg:postcode":"WS15 1EW",
    "sg:province":"Staffordshire",
    "sg:tags":[
        "platform",
        "work",
        "scaffolding"
    ],
    "wof:name":"Premier Scaffolding",
    "wof:placetype":"venue"
},
  "geometry": {"coordinates":[-1.9353519678,52.7575569153],"type":"Point"}
}