{
  "type": "Feature",
  "properties": {
    "iso:country":"GB",
    "sg:address":"34 Princes St",
    "sg:city":"Yeovil",
    "sg:classifiers":[
        {
            "category":"Shopping",
            "subcategory":"Department Store",
            "type":"Retail Goods"
        }
    ],
    "sg:postcode":"BA20 1EQ",
    "sg:province":"Somerset",
    "wof:name":"Warry,M L,",
    "wof:placetype":"venue"
},
  "geometry": {"coordinates":[-2.633557,50.942352],"type":"Point"}
}