{
  "type": "Feature",
  "properties": {
    "iso:country":"GB",
    "sg:address":"190a St Aidans Ave",
    "sg:city":"Blackburn",
    "sg:classifiers":[
        {
            "category":"Professional",
            "subcategory":"Business Services",
            "type":"Services"
        }
    ],
    "sg:postcode":"BB2 4EA",
    "sg:province":"Lancashire",
    "sg:tags":[
        "tile",
        "import",
        "export",
        "agent",
        "stockist"
    ],
    "wof:name":"Leaver,Fred,",
    "wof:placetype":"venue"
},
  "geometry": {"coordinates":[-2.5024089813,53.7336006165],"type":"Point"}
}