{
  "type": "Feature",
  "properties": {
    "iso:country":"GB",
    "sg:address":"Beaverhall House, 27 Beaverhall Rd",
    "sg:city":"Edinburgh",
    "sg:classifiers":[
        {
            "category":"Recreation",
            "type":"Entertainment"
        }
    ],
    "sg:phone":"+44 131 478 4400",
    "sg:postcode":"EH7 4JE",
    "sg:province":"City of Edinburgh",
    "sg:tags":[
        "corporate",
        "leisure"
    ],
    "wof:name":"RTE",
    "wof:placetype":"venue"
},
  "geometry": {"coordinates":[-3.196203,55.968159],"type":"Point"}
}