{
  "type": "Feature",
  "properties": {
    "addr:full":"11 Broomhouse Loan Edinburgh City of Edinburgh EH11 3TS",
    "addr:housenumber":"11",
    "addr:postcode":"eh11 3ts",
    "addr:street":"Broomhouse Loan",
    "iso:country":"GB",
    "sg:address":"11 Broomhouse Loan",
    "sg:city":"Edinburgh",
    "sg:classifiers":[
        {
            "category":"Building & Trades",
            "subcategory":"Construction",
            "type":"Services"
        }
    ],
    "sg:phone":"+44 131 443 4517",
    "sg:postcode":"EH11 3TS",
    "sg:province":"City of Edinburgh",
    "sg:tags":[
        "decorator",
        "painter"
    ],
    "wof:name":"Grant Russell",
    "wof:placetype":"venue"
},
  "geometry": {"coordinates":[-3.280905962,55.9254875183],"type":"Point"}
}