{
  "type": "Feature",
  "properties": {
    "iso:country":"GB",
    "sg:address":"6 Terrace Walk",
    "sg:city":"Bath",
    "sg:classifiers":[
        {
            "category":"Personal",
            "subcategory":"Beauty Salon",
            "type":"Services"
        }
    ],
    "sg:phone":"+44 1225 465141",
    "sg:postcode":"BA1 6LN",
    "sg:province":"Bath and North East Somerset",
    "sg:tags":[
        "unisex",
        "hairdresser"
    ],
    "wof:name":"Giuseppe Hair Stylist",
    "wof:placetype":"venue"
},
  "geometry": {"coordinates":[-2.357826,51.381317],"type":"Point"}
}