{
  "type": "Feature",
  "properties": {
    "addr:full":"39 Moulsham Street Chelmsford Essex CM2 0HY",
    "addr:housenumber":"39",
    "addr:postcode":"cm2 0hy",
    "addr:street":"Moulsham Street",
    "iso:country":"GB",
    "sg:address":"39 Moulsham Street",
    "sg:city":"Chelmsford",
    "sg:classifiers":[
        {
            "category":"Professional",
            "subcategory":"Computer Services",
            "type":"Services"
        }
    ],
    "sg:postcode":"CM2 0HY",
    "sg:province":"Essex",
    "sg:tags":[
        "system",
        "software"
    ],
    "wof:name":"Auriga Projects Ltd",
    "wof:placetype":"venue"
},
  "geometry": {"coordinates":[0.4721789956,51.729637146],"type":"Point"}
}