{
  "type": "Feature",
  "properties": {
    "addr:full":"64 Oxford Rd Dewsbury West Yorkshire WF13 4EH",
    "addr:housenumber":"64",
    "addr:postcode":"wf13 4eh",
    "addr:street":"Oxford Rd",
    "iso:country":"GB",
    "sg:address":"64 Oxford Rd",
    "sg:city":"Dewsbury",
    "sg:classifiers":[
        {
            "category":"Organizations",
            "subcategory":"Non-profit Organization",
            "type":"Services"
        }
    ],
    "sg:postcode":"WF13 4EH",
    "sg:province":"West Yorkshire",
    "sg:tags":[
        "organisation",
        "voluntary",
        "charity"
    ],
    "wof:name":"P.B.C. Support Network",
    "wof:placetype":"venue"
},
  "geometry": {"coordinates":[-1.65028,53.694683],"type":"Point"}
}