{
  "type": "Feature",
  "properties": {
    "addr:full":"8 The Wheatlands, Perton Wolverhampton Shropshire WV6 7XP",
    "addr:housenumber":"8",
    "addr:postcode":"wv6 7xp",
    "addr:street":"The",
    "iso:country":"GB",
    "sg:address":"8 The Wheatlands, Perton",
    "sg:city":"Wolverhampton",
    "sg:classifiers":[
        {
            "category":"Building & Trades",
            "subcategory":"Pest Control",
            "type":"Services"
        }
    ],
    "sg:phone":"+44 1902 744560",
    "sg:postcode":"WV6 7XP",
    "sg:province":"Shropshire",
    "sg:tags":[
        "vermin"
    ],
    "wof:name":"Comlete Hygiene Equipment",
    "wof:placetype":"venue"
},
  "geometry": {"coordinates":[-2.2123579979,52.5927314758],"type":"Point"}
}