{
  "type": "Feature",
  "properties": {
    "addr:full":"31 Viewforth Terr Kirkcaldy Fife KY1 3DW",
    "addr:housenumber":"31",
    "addr:postcode":"ky1 3dw",
    "addr:street":"Viewforth Terr",
    "iso:country":"GB",
    "sg:address":"31 Viewforth Terr",
    "sg:city":"Kirkcaldy",
    "sg:classifiers":[
        {
            "category":"Building & Trades",
            "subcategory":"Construction",
            "type":"Services"
        }
    ],
    "sg:postcode":"KY1 3DW",
    "sg:province":"Fife",
    "sg:tags":[
        "builder"
    ],
    "wof:name":"Rodger,K,",
    "wof:placetype":"venue"
},
  "geometry": {"coordinates":[-3.1349151134,56.1298675537],"type":"Point"}
}