{
  "type": "Feature",
  "properties": {
    "addr:full":"26 Blakesway Welwyn Hertfordshire AL6 9RE",
    "addr:housenumber":"26",
    "addr:postcode":"al6 9re",
    "addr:street":"Blakesway",
    "iso:country":"GB",
    "sg:address":"26 Blakesway",
    "sg:city":"Welwyn",
    "sg:classifiers":[
        {
            "category":"Freight",
            "type":"Transportation"
        }
    ],
    "sg:phone":"+44 1438 840305",
    "sg:postcode":"AL6 9RE",
    "sg:province":"Hertfordshire",
    "sg:tags":[
        "forwarders"
    ],
    "wof:name":"Oasis Air Freight Ltd.",
    "wof:placetype":"venue"
},
  "geometry": {"coordinates":[-0.215015,51.836845],"type":"Point"}
}