{
  "type": "Feature",
  "properties": {
    "addr:full":"24 Le Strange Terrace Hunstanton Norfolk PE36 5AJ",
    "addr:housenumber":"24",
    "addr:postcode":"pe36 5aj",
    "addr:street":"Le Strange Terrace",
    "iso:country":"GB",
    "sg:address":"24 Le Strange Terrace",
    "sg:city":"Hunstanton",
    "sg:classifiers":[
        {
            "category":"Food & Beverages",
            "subcategory":"Candy",
            "type":"Retail Goods"
        }
    ],
    "sg:phone":"+44 1485 533300",
    "sg:postcode":"PE36 5AJ",
    "sg:province":"Norfolk",
    "sg:tags":[
        "confectioner"
    ],
    "wof:name":"D Boldero",
    "wof:placetype":"venue"
},
  "geometry": {"coordinates":[0.487235,52.938545],"type":"Point"}
}