{
  "type": "Feature",
  "properties": {
    "addr:full":"27a Ladies Mile Road, Patcham Brighton East Sussex BN1 8QE",
    "addr:housenumber":"27a",
    "addr:postcode":"bn1 8qe",
    "addr:street":"Ladies Mile Road",
    "iso:country":"GB",
    "sg:address":"27a Ladies Mile Road, Patcham",
    "sg:city":"Brighton",
    "sg:classifiers":[
        {
            "category":"Home & Garden",
            "subcategory":"Hardware",
            "type":"Retail Goods"
        }
    ],
    "sg:phone":"+44 1273 556000",
    "sg:postcode":"BN1 8QE",
    "sg:province":"East Sussex",
    "sg:tags":[
        "equipment",
        "heating"
    ],
    "wof:name":"Alpha Heating",
    "wof:placetype":"venue"
},
  "geometry": {"coordinates":[-0.146033,50.863892],"type":"Point"}
}