{
  "type": "Feature",
  "properties": {
    "iso:country":"GB",
    "sg:address":"13 Market Square, Kirkby",
    "sg:city":"Liverpool",
    "sg:classifiers":[
        {
            "category":"Shopping",
            "subcategory":"Pharmacy",
            "type":"Retail Goods"
        }
    ],
    "sg:phone":"+44 151 546 6454",
    "sg:postcode":"L32 8RG",
    "sg:province":"Merseyside",
    "sg:tags":[
        "pharmacist",
        "chemist"
    ],
    "wof:name":"Tony's Pharmacy",
    "wof:placetype":"venue"
},
  "geometry": {"coordinates":[-2.885204,53.482327],"type":"Point"}
}