{
  "type": "Feature",
  "properties": {
    "iso:country":"GB",
    "sg:address":"13 Gerrard St",
    "sg:city":"West End",
    "sg:classifiers":[
        {
            "category":"Restaurant",
            "type":"Food & Drink"
        }
    ],
    "sg:phone":"+44 20 7437 6148",
    "sg:postcode":"W1V 7LJ",
    "sg:province":"Hampshire",
    "wof:name":"Far East Restaurant",
    "wof:placetype":"venue"
},
  "geometry": {"coordinates":[-0.1310649961,51.511932373],"type":"Point"}
}