{
  "type": "Feature",
  "properties": {
    "addr:full":"30-31 Newtown Shopping Centre Birmingham West Midlands B19 2SS",
    "addr:housenumber":"30-31",
    "addr:postcode":"b19 2ss",
    "addr:street":"Newtown Shopping",
    "iso:country":"GB",
    "sg:address":"30-31 Newtown Shopping Centre",
    "sg:city":"Birmingham",
    "sg:classifiers":[
        {
            "category":"Cinema",
            "subcategory":"Movie Rental",
            "type":"Entertainment"
        }
    ],
    "sg:postcode":"B19 2SS",
    "sg:province":"West Midlands",
    "sg:tags":[
        "video",
        "library"
    ],
    "wof:name":"Apollo Video",
    "wof:placetype":"venue"
},
  "geometry": {"coordinates":[-1.9118289948,52.4951553345],"type":"Point"}
}