{
  "type": "Feature",
  "properties": {
    "iso:country":"GB",
    "sg:address":"14 St Marys Row",
    "sg:city":"Birmingham",
    "sg:classifiers":[
        {
            "category":"Health Services",
            "subcategory":"Optometrist",
            "type":"Services"
        }
    ],
    "sg:phone":"+44 121 449 0845",
    "sg:postcode":"B13 8JG",
    "sg:province":"West Midlands",
    "sg:tags":[
        "optician"
    ],
    "wof:name":"Pabari Opticians",
    "wof:placetype":"venue"
},
  "geometry": {"coordinates":[-1.8876789808,52.4463043213],"type":"Point"}
}