{
  "type": "Feature",
  "properties": {
    "addr:full":"6 Burroughs Bank, Lightmoor Telford Shropshire TF4 3QS",
    "addr:housenumber":"6;lightmoor",
    "addr:postcode":"tf4 3qs",
    "addr:street":"Burroughs Bank",
    "iso:country":"GB",
    "sg:address":"6 Burroughs Bank, Lightmoor",
    "sg:city":"Telford",
    "sg:classifiers":[
        {
            "category":"Professional",
            "subcategory":"Management & Consulting",
            "type":"Services"
        }
    ],
    "sg:phone":"+44 1952 432508",
    "sg:postcode":"TF4 3QS",
    "sg:province":"Shropshire",
    "sg:tags":[
        "consultant",
        "business"
    ],
    "wof:name":"V J H Business Training & Consultants",
    "wof:placetype":"venue"
},
  "geometry": {"coordinates":[-2.4743111134,52.6449584961],"type":"Point"}
}