{
  "type": "Feature",
  "properties": {
    "iso:country":"GB",
    "sg:address":"9 Edinburgh Avenue",
    "sg:city":"Workington",
    "sg:classifiers":[
        {
            "category":"Wholesale",
            "subcategory":"Fruits & Vegetables",
            "type":"Manufacturing & Wholesale Goods"
        }
    ],
    "sg:phone":"+44 1900 605262",
    "sg:postcode":"CA14 3NY",
    "sg:province":"Cumbria",
    "wof:name":"M & F Fruit Wholesalers",
    "wof:placetype":"venue"
},
  "geometry": {"coordinates":[-3.550063,54.631546],"type":"Point"}
}