{
  "type": "Feature",
  "properties": {
    "iso:country":"GB",
    "sg:address":"41 The Coppice",
    "sg:city":"West Drayton",
    "sg:classifiers":[
        {
            "category":"Building & Trades",
            "subcategory":"Plumbing",
            "type":"Services"
        }
    ],
    "sg:phone":"+44 1895 463603",
    "sg:postcode":"UB7 8DX",
    "sg:province":"Greater London",
    "sg:tags":[
        "heating"
    ],
    "wof:name":"Ryan Kearney Plumbing & Heating Engineer",
    "wof:placetype":"venue"
},
  "geometry": {"coordinates":[-0.470221,51.5214],"type":"Point"}
}