{
  "type": "Feature",
  "properties": {
    "addr:full":"5 Station Road Rickmansworth Hertfordshire WD3 1QP",
    "addr:housenumber":"5",
    "addr:postcode":"wd3 1qp",
    "addr:street":"Station Road",
    "iso:country":"GB",
    "sg:address":"5 Station Road",
    "sg:city":"Rickmansworth",
    "sg:classifiers":[
        {
            "category":"Shopping",
            "subcategory":"Clothing, Apparel, & Fashions",
            "type":"Retail Goods"
        }
    ],
    "sg:postcode":"WD3 1QP",
    "sg:province":"Hertfordshire",
    "sg:tags":[
        "dresswear"
    ],
    "wof:name":"Secondgear",
    "wof:placetype":"venue"
},
  "geometry": {"coordinates":[-0.4720109999,51.639213562],"type":"Point"}
}