{
  "type": "Feature",
  "properties": {
    "addr:full":"Station Works, Conolley Keighley North Yorkshire BD20 8LN",
    "addr:postcode":"bd20 8ln",
    "addr:street":"Keighley",
    "iso:country":"GB",
    "sg:address":"Station Works, Conolley",
    "sg:city":"Keighley",
    "sg:classifiers":[
        {
            "category":"Taxi",
            "type":"Transportation"
        },
        {
            "category":"Military Area",
            "subcategory":"Air Force Base",
            "type":"Public Place"
        }
    ],
    "sg:phone":"+44 1535 630062",
    "sg:postcode":"BD20 8LN",
    "sg:province":"North Yorkshire",
    "sg:tags":[
        "mini",
        "hire",
        "private",
        "cab"
    ],
    "wof:name":"Airedale Private Hire",
    "wof:placetype":"venue"
},
  "geometry": {"coordinates":[-1.997303009,53.8976364136],"type":"Point"}
}