{
  "type": "Feature",
  "properties": {
    "addr:full":"67 Gloucester Rd Bristol City of Bristol BS7 8AD",
    "addr:housenumber":"67",
    "addr:postcode":"bs7 8ad",
    "addr:street":"Gloucester Rd",
    "iso:country":"GB",
    "sg:address":"67 Gloucester Rd",
    "sg:city":"Bristol",
    "sg:classifiers":[
        {
            "category":"Shopping",
            "subcategory":"Discount & Variety Stores",
            "type":"Retail Goods"
        }
    ],
    "sg:phone":"+44 117 924 1812",
    "sg:postcode":"BS7 8AD",
    "sg:province":"City of Bristol",
    "sg:tags":[
        "surplus"
    ],
    "wof:name":"G L Brown",
    "wof:placetype":"venue"
},
  "geometry": {"coordinates":[-2.593767,51.469685],"type":"Point"}
}