{
  "type": "Feature",
  "properties": {
    "iso:country":"GB",
    "sg:address":"114 Canterbury Street",
    "sg:city":"Gillingham",
    "sg:classifiers":[
        {
            "category":"Organizations",
            "subcategory":"Non-profit Organization",
            "type":"Services"
        }
    ],
    "sg:phone":"+44 1634 850878",
    "sg:postcode":"ME7 5UH",
    "sg:province":"Kent",
    "sg:tags":[
        "charitable",
        "organisation",
        "voluntary",
        "charity"
    ],
    "wof:name":"Kent Muslim Welfare Association",
    "wof:placetype":"venue"
},
  "geometry": {"coordinates":[0.544766,51.38435],"type":"Point"}
}