{
  "type": "Feature",
  "properties": {
    "addr:full":"Station Approach Newquay Cornwall TR7 2NG",
    "addr:postcode":"tr7 2ng",
    "addr:street":"Station Approach",
    "iso:country":"GB",
    "sg:address":"Station Approach",
    "sg:city":"Newquay",
    "sg:classifiers":[
        {
            "category":"Fast Food",
            "type":"Food & Drink"
        }
    ],
    "sg:phone":"+44 1637 872100",
    "sg:postcode":"TR7 2NG",
    "sg:province":"Cornwall",
    "sg:tags":[
        "away",
        "take"
    ],
    "wof:name":"Burger King",
    "wof:placetype":"venue"
},
  "geometry": {"coordinates":[-5.074864,50.415234],"type":"Point"}
}