{
  "type": "Feature",
  "properties": {
    "iso:country":"GB",
    "sg:address":"9 Beacon Hill Road",
    "sg:city":"Hindhead",
    "sg:classifiers":[
        {
            "category":"Education",
            "subcategory":"Music School",
            "type":"Public Place"
        }
    ],
    "sg:phone":"+44 1428 608866",
    "sg:postcode":"GU26 6NR",
    "sg:province":"Hampshire",
    "wof:name":"The Man in the Moon",
    "wof:placetype":"venue"
},
  "geometry": {"coordinates":[-0.753624022,51.1225090027],"type":"Point"}
}