{
  "type": "Feature",
  "properties": {
    "addr:full":"30 Church Road Liverpool Merseyside L13 2BA",
    "addr:housenumber":"30",
    "addr:postcode":"l13 2ba",
    "addr:street":"Church Road",
    "iso:country":"GB",
    "sg:address":"30 Church Road",
    "sg:city":"Liverpool",
    "sg:classifiers":[
        {
            "category":"Organizations",
            "subcategory":"Membership Organization",
            "type":"Services"
        }
    ],
    "sg:phone":"+44 151 228 0752",
    "sg:postcode":"L13 2BA",
    "sg:province":"Merseyside",
    "sg:tags":[
        "club"
    ],
    "wof:name":"St.Cuthberts Parochial Club",
    "wof:placetype":"venue"
},
  "geometry": {"coordinates":[-2.924145937,53.4136543274],"type":"Point"}
}