{
  "type": "Feature",
  "properties": {
    "iso:country":"GB",
    "sg:address":"Hude Cottage, Hude Lane",
    "sg:city":"Chelmsford",
    "sg:classifiers":[
        {
            "category":"Building & Trades",
            "subcategory":"Construction",
            "type":"Services"
        }
    ],
    "sg:postcode":"CM3 4LW",
    "sg:province":"Essex",
    "sg:tags":[
        "builder"
    ],
    "wof:name":"D E Hood",
    "wof:placetype":"venue"
},
  "geometry": {"coordinates":[0.59855,51.704079],"type":"Point"}
}