{
  "type": "Feature",
  "properties": {
    "addr:full":"7 The Brownings Edenbridge East Sussex TN8 6JF",
    "addr:housenumber":"7",
    "addr:postcode":"tn8 6jf",
    "iso:country":"GB",
    "sg:address":"7 The Brownings",
    "sg:city":"Edenbridge",
    "sg:classifiers":[
        {
            "category":"Organizations",
            "subcategory":"Non-profit Organization",
            "type":"Services"
        }
    ],
    "sg:postcode":"TN8 6JF",
    "sg:province":"East Sussex",
    "sg:tags":[
        "organisation",
        "voluntary",
        "charity"
    ],
    "wof:name":"The Cancer Research Campaign",
    "wof:placetype":"venue"
},
  "geometry": {"coordinates":[0.0441100001,51.2091407776],"type":"Point"}
}