{
  "type": "Feature",
  "properties": {
    "addr:full":"Norton Bridge Garage, Norton Bridge Enterprise Centre Stone Staffordshire ST15 0NS",
    "addr:postcode":"st15 0ns",
    "iso:country":"GB",
    "sg:address":"Norton Bridge Garage, Norton Bridge Enterprise Centre",
    "sg:city":"Stone",
    "sg:classifiers":[
        {
            "category":"Autos & Motor Vehicles",
            "subcategory":"Automobile Sales",
            "type":"Retail Goods"
        }
    ],
    "sg:postcode":"ST15 0NS",
    "sg:province":"Staffordshire",
    "sg:tags":[
        "car"
    ],
    "wof:name":"Prestige & Performance",
    "wof:placetype":"venue"
},
  "geometry": {"coordinates":[-2.197639,52.87151],"type":"Point"}
}