{
  "type": "Feature",
  "properties": {
    "addr:full":"2 West End, Barlestone Nuneaton Leicestershire CV13 0EJ",
    "addr:housenumber":"2",
    "addr:postcode":"cv13 0ej",
    "addr:street":"West End",
    "iso:country":"GB",
    "sg:address":"2 West End, Barlestone",
    "sg:city":"Nuneaton",
    "sg:classifiers":[
        {
            "category":"Banks & Credit Unions",
            "subcategory":"Financial Services",
            "type":"Services"
        }
    ],
    "sg:phone":"+44 1455 290213",
    "sg:postcode":"CV13 0EJ",
    "sg:province":"Leicestershire",
    "sg:tags":[
        "building",
        "society"
    ],
    "sg:website":"http://www.hrbs.co.uk",
    "wof:name":"Hinckley & Rugby Building Society",
    "wof:placetype":"venue"
},
  "geometry": {"coordinates":[-1.3690749407,52.6475143433],"type":"Point"}
}