{
  "type": "Feature",
  "properties": {
    "addr:full":"8 The Courtyard, 52 Horsemarket St Warrington Cheshire WA1 1XL",
    "addr:housenumber":"8;52",
    "addr:postcode":"wa1 1xl",
    "addr:street":"The Courtyard;Horsemarket St",
    "iso:country":"GB",
    "sg:address":"8 The Courtyard, 52 Horsemarket St",
    "sg:city":"Warrington",
    "sg:classifiers":[
        {
            "category":"Professional",
            "subcategory":"Management & Consulting",
            "type":"Services"
        }
    ],
    "sg:phone":"+44 1925 651566",
    "sg:postcode":"WA1 1XL",
    "sg:province":"Cheshire",
    "sg:tags":[
        "marketing",
        "consultant"
    ],
    "wof:name":"I.Q Promotions",
    "wof:placetype":"venue"
},
  "geometry": {"coordinates":[-2.59331,53.38966],"type":"Point"}
}