{
  "type": "Feature",
  "properties": {
    "addr:full":"Quarry Mills, Quarry Rd Godstone Surrey RH9 8DQ",
    "addr:postcode":"rh9 8dq",
    "addr:street":"Quarry Mills Quarry Rd",
    "iso:country":"GB",
    "sg:address":"Quarry Mills, Quarry Rd",
    "sg:city":"Godstone",
    "sg:classifiers":[
        {
            "category":"Retail",
            "subcategory":"Auto Repair",
            "type":"Services"
        }
    ],
    "sg:phone":"+44 1883 742036",
    "sg:postcode":"RH9 8DQ",
    "sg:province":"Surrey",
    "sg:tags":[
        "modification",
        "garage"
    ],
    "wof:name":"Weller Diagnostic Ltd",
    "wof:placetype":"venue"
},
  "geometry": {"coordinates":[-0.0669879988,51.2500801086],"type":"Point"}
}