{
  "type": "Feature",
  "properties": {
    "iso:country":"GB",
    "sg:address":"Forrest House, 13 North End",
    "sg:city":"Bedale",
    "sg:classifiers":[
        {
            "category":"Retail",
            "subcategory":"Veterinary Services",
            "type":"Services"
        }
    ],
    "sg:phone":"+44 1677 422124",
    "sg:postcode":"DL8 1AF",
    "sg:province":"North Yorkshire",
    "sg:tags":[
        "surgeon"
    ],
    "wof:name":"Grant Norrie & Almond",
    "wof:placetype":"venue"
},
  "geometry": {"coordinates":[-1.593467,54.290482],"type":"Point"}
}