{
  "type": "Feature",
  "properties": {
    "iso:country":"GB",
    "sg:address":"171 Waterloo Road",
    "sg:city":"Middlesbrough",
    "sg:classifiers":[
        {
            "category":"Food & Beverages",
            "subcategory":"Meat & Fish",
            "type":"Retail Goods"
        }
    ],
    "sg:phone":"+44 1642 248697",
    "sg:postcode":"TS1 3JG",
    "sg:province":"North Yorkshire",
    "sg:tags":[
        "butcher"
    ],
    "wof:name":"Alam & Sons",
    "wof:placetype":"venue"
},
  "geometry": {"coordinates":[-1.22817,54.56823],"type":"Point"}
}