{
  "type": "Feature",
  "properties": {
    "addr:full":"242 Hatch Road Brentwood Essex CM15 9QR",
    "addr:housenumber":"242",
    "addr:postcode":"cm15 9qr",
    "addr:street":"Hatch Road",
    "iso:country":"GB",
    "sg:address":"242 Hatch Road",
    "sg:city":"Brentwood",
    "sg:classifiers":[
        {
            "category":"Building & Trades",
            "subcategory":"Construction",
            "type":"Services"
        }
    ],
    "sg:postcode":"CM15 9QR",
    "sg:province":"Essex",
    "sg:tags":[
        "builder"
    ],
    "wof:name":"Giles & Co",
    "wof:placetype":"venue"
},
  "geometry": {"coordinates":[0.297268,51.639328],"type":"Point"}
}