{
  "type": "Feature",
  "properties": {
    "addr:full":"93 Victoria Road Scarborough North Yorkshire YO11 1SP",
    "addr:housenumber":"93",
    "addr:postcode":"yo11 1sp",
    "addr:street":"Victoria Road",
    "iso:country":"GB",
    "sg:address":"93 Victoria Road",
    "sg:city":"Scarborough",
    "sg:classifiers":[
        {
            "category":"Cafe",
            "type":"Food & Drink"
        }
    ],
    "sg:postcode":"YO11 1SP",
    "sg:province":"North Yorkshire",
    "sg:tags":[
        "tea",
        "room"
    ],
    "wof:name":"Davids",
    "wof:placetype":"venue"
},
  "geometry": {"coordinates":[-0.407338,54.280865],"type":"Point"}
}