{
  "type": "Feature",
  "properties": {
    "iso:country":"GB",
    "sg:address":"19 Sugden Road",
    "sg:city":"Thames Ditton",
    "sg:classifiers":[
        {
            "category":"Real Estate",
            "subcategory":"Real Estate Services",
            "type":"Services"
        },
        {
            "category":"Building & Trades",
            "subcategory":"Construction",
            "type":"Services"
        }
    ],
    "sg:phone":"+44 20 8398 7179",
    "sg:postcode":"KT7 0AB",
    "sg:province":"Surrey",
    "sg:tags":[
        "property",
        "decorator",
        "maintenance",
        "painter"
    ],
    "wof:name":"Concept Decorating",
    "wof:placetype":"venue"
},
  "geometry": {"coordinates":[-0.3268289864,51.38256073],"type":"Point"}
}