{
  "type": "Feature",
  "properties": {
    "addr:full":"Canterbury Street Gillingham Kent ME7 5LF",
    "addr:postcode":"me7 5lf",
    "addr:street":"Canterbury Street",
    "iso:country":"GB",
    "sg:address":"Canterbury Street",
    "sg:city":"Gillingham",
    "sg:classifiers":[
        {
            "category":"Home & Garden",
            "subcategory":"Hardware",
            "type":"Retail Goods"
        }
    ],
    "sg:phone":"+44 1634 579857",
    "sg:postcode":"ME7 5LF",
    "sg:province":"Kent",
    "sg:tags":[
        "equipment",
        "welding"
    ],
    "wof:name":"W & E Ltd.",
    "wof:placetype":"venue"
},
  "geometry": {"coordinates":[0.5445799828,51.3869781494],"type":"Point"}
}