{
  "type": "Feature",
  "properties": {
    "iso:country":"GB",
    "sg:address":"Durley Lane, Keynsham",
    "sg:city":"Bristol",
    "sg:classifiers":[
        {
            "category":"Retail",
            "subcategory":"Auto Repair",
            "type":"Services"
        }
    ],
    "sg:phone":"+44 117 986 7498",
    "sg:postcode":"BS31 2AJ",
    "sg:province":"City of Bristol",
    "sg:tags":[
        "body",
        "garage",
        "modification",
        "car"
    ],
    "wof:name":"Greenlane Bodyworks",
    "wof:placetype":"venue"
},
  "geometry": {"coordinates":[-2.510518,51.422989],"type":"Point"}
}