{
  "type": "Feature",
  "properties": {
    "addr:full":"11 Steele Road Isleworth Greater London TW7 7HL",
    "addr:housenumber":"11",
    "addr:postcode":"tw7 7hl",
    "addr:street":"Steele Road",
    "iso:country":"GB",
    "sg:address":"11 Steele Road",
    "sg:city":"Isleworth",
    "sg:classifiers":[
        {
            "category":"Building & Trades",
            "subcategory":"Construction",
            "type":"Services"
        }
    ],
    "sg:phone":"+44 20 8892 8768",
    "sg:postcode":"TW7 7HL",
    "sg:province":"Greater London",
    "sg:tags":[
        "joiner",
        "carpenter"
    ],
    "wof:name":"Quality Carpentry & Joinery Service (The)",
    "wof:placetype":"venue"
},
  "geometry": {"coordinates":[-0.3273299932,51.4641571045],"type":"Point"}
}