{
  "type": "Feature",
  "properties": {
    "addr:full":"Wrexham Library & Art Centre, Rhosddu Road Wrexham Wrexham LL11 1AU",
    "addr:postcode":"ll11 1au",
    "addr:street":"Rhosddu Road",
    "iso:country":"GB",
    "sg:address":"Wrexham Library & Art Centre, Rhosddu Road",
    "sg:city":"Wrexham",
    "sg:classifiers":[
        {
            "category":"Communications",
            "type":"Services"
        }
    ],
    "sg:phone":"+44 1978 221100",
    "sg:postcode":"LL11 1AU",
    "sg:province":"Wrexham",
    "sg:tags":[
        "broadcasting"
    ],
    "wof:name":"BBC Wales",
    "wof:placetype":"venue"
},
  "geometry": {"coordinates":[-2.99413,53.048161],"type":"Point"}
}