{
  "type": "Feature",
  "properties": {
    "addr:full":"Unit 11 Bromyard Road Indust Est Ledbury Gloucestershire HR8 1NS",
    "addr:housenumber":"unit 11",
    "addr:postcode":"hr8 1ns",
    "addr:street":"Bromyard Road",
    "iso:country":"GB",
    "sg:address":"Unit 11 Bromyard Road Indust Est",
    "sg:city":"Ledbury",
    "sg:classifiers":[
        {
            "category":"Professional",
            "subcategory":"Engineering",
            "type":"Services"
        }
    ],
    "sg:phone":"+44 1531 631525",
    "sg:postcode":"HR8 1NS",
    "sg:province":"Gloucestershire",
    "sg:tags":[
        "precision",
        "engineer"
    ],
    "wof:name":"D G Precision Engineering",
    "wof:placetype":"venue"
},
  "geometry": {"coordinates":[-2.427155,52.047565],"type":"Point"}
}