{
  "type": "Feature",
  "properties": {
    "addr:full":"1 Stanhope Street, Highgate Birmingham West Midlands B12 0UZ",
    "addr:housenumber":"1",
    "addr:postcode":"b12 0uz",
    "addr:street":"Stanhope Street Highgate",
    "iso:country":"GB",
    "sg:address":"1 Stanhope Street, Highgate",
    "sg:city":"Birmingham",
    "sg:classifiers":[
        {
            "category":"Professional",
            "subcategory":"Engineering",
            "type":"Services"
        }
    ],
    "sg:phone":"+44 121 772 2516",
    "sg:postcode":"B12 0UZ",
    "sg:province":"West Midlands",
    "sg:tags":[
        "precision",
        "engineer"
    ],
    "wof:name":"S Z N Pendle Automatics Ltd.",
    "wof:placetype":"venue"
},
  "geometry": {"coordinates":[-1.8862780333,52.4681510925],"type":"Point"}
}