{
  "type": "Feature",
  "properties": {
    "addr:full":"Unit 251c Dukes Way, Team Valley Trad Est Gateshead Tyne and Wear NE11 0PN",
    "addr:housenumber":"251c",
    "addr:postcode":"ne11 0pn",
    "addr:street":"Dukes Way;Est",
    "iso:country":"GB",
    "sg:address":"Unit 251c Dukes Way, Team Valley Trad Est",
    "sg:city":"Gateshead",
    "sg:classifiers":[
        {
            "category":"Building & Trades",
            "subcategory":"Plumbing",
            "type":"Services"
        },
        {
            "category":"Utilities",
            "subcategory":"Sewage",
            "type":"Services"
        }
    ],
    "sg:phone":"+44 191 491 5869",
    "sg:postcode":"NE11 0PN",
    "sg:province":"Tyne and Wear",
    "sg:tags":[
        "disposal",
        "clearance",
        "drain",
        "sewer"
    ],
    "wof:name":"D C S Environmental Ltd",
    "wof:placetype":"venue"
},
  "geometry": {"coordinates":[-1.6223789454,54.9272689819],"type":"Point"}
}