{
  "type": "Feature",
  "properties": {
    "addr:full":"Unit F The Factory, Dippenhall Farnham Hampshire GU10 5DW",
    "addr:postcode":"gu10 5dw",
    "addr:street":"Dippenhall;Hampshire",
    "iso:country":"GB",
    "sg:address":"Unit F The Factory, Dippenhall",
    "sg:city":"Farnham",
    "sg:classifiers":[
        {
            "category":"Banks & Credit Unions",
            "subcategory":"Financial Services",
            "type":"Services"
        }
    ],
    "sg:postcode":"GU10 5DW",
    "sg:province":"Hampshire",
    "sg:tags":[
        "adviser"
    ],
    "wof:name":"Wilson Harris & White",
    "wof:placetype":"venue"
},
  "geometry": {"coordinates":[-0.833979,51.213551],"type":"Point"}
}