{
  "type": "Feature",
  "properties": {
    "addr:full":"Unit8, Little Hyde Farm, Little Hyde Lane Ingatestone Essex CM4 0DU",
    "addr:postcode":"cm4 0du",
    "addr:street":"Little;Little Hyde Lane",
    "iso:country":"GB",
    "sg:address":"Unit8, Little Hyde Farm, Little Hyde Lane",
    "sg:city":"Ingatestone",
    "sg:classifiers":[
        {
            "category":"Manufacturing",
            "subcategory":"Signs",
            "type":"Manufacturing & Wholesale Goods"
        },
        {
            "category":"Organizations",
            "subcategory":"Community Association",
            "type":"Services"
        }
    ],
    "sg:phone":"+44 1277 355078",
    "sg:postcode":"CM4 0DU",
    "sg:province":"Essex",
    "sg:tags":[
        "manufacture",
        "emblem",
        "badge"
    ],
    "wof:name":"Premier Badges Ltd.",
    "wof:placetype":"venue"
},
  "geometry": {"coordinates":[0.383585006,51.669921875],"type":"Point"}
}