{
  "type": "Feature",
  "properties": {
    "addr:full":"Blenheim Road London Greater London SW20 9BA",
    "addr:postcode":"sw20 9ba",
    "addr:street":"Blenheim Road",
    "iso:country":"GB",
    "sg:address":"Blenheim Road",
    "sg:city":"London",
    "sg:classifiers":[
        {
            "category":"Social Services",
            "subcategory":"Retirement Home",
            "type":"Services"
        }
    ],
    "sg:postcode":"SW20 9BA",
    "sg:province":"Greater London",
    "sg:tags":[
        "residential",
        "care"
    ],
    "wof:name":"London Borough of Merton",
    "wof:placetype":"venue"
},
  "geometry": {"coordinates":[-0.230385,51.403034],"type":"Point"}
}