{
  "type": "Feature",
  "properties": {
    "addr:full":"28 Market Street Wymondham Norfolk NR18 0BB",
    "addr:housenumber":"28",
    "addr:postcode":"nr18 0bb",
    "addr:street":"Market Street",
    "iso:country":"GB",
    "sg:address":"28 Market Street",
    "sg:city":"Wymondham",
    "sg:classifiers":[
        {
            "category":"Travel",
            "subcategory":"Hotels & Motels",
            "type":"Entertainment"
        }
    ],
    "sg:phone":"+44 1953 606721",
    "sg:postcode":"NR18 0BB",
    "sg:province":"Norfolk",
    "wof:name":"The Wymondham Consort Hotel",
    "wof:placetype":"venue"
},
  "geometry": {"coordinates":[1.1120070219,52.5702590942],"type":"Point"}
}