{
  "type": "Feature",
  "properties": {
    "iso:country":"GB",
    "sg:address":"Unit 9 Bridge Business Park, Whetsted Road",
    "sg:city":"Tonbridge",
    "sg:classifiers":[
        {
            "category":"Home & Garden",
            "subcategory":"Hardware",
            "type":"Retail Goods"
        }
    ],
    "sg:phone":"+44 1892 835090",
    "sg:postcode":"TN12 6RS",
    "sg:province":"Kent",
    "sg:tags":[
        "retailer",
        "diy"
    ],
    "wof:name":"Anglefix",
    "wof:placetype":"venue"
},
  "geometry": {"coordinates":[0.35968,51.1847],"type":"Point"}
}