{
  "type": "Feature",
  "properties": {
    "iso:country":"GB",
    "sg:address":"225 Warwick Road",
    "sg:city":"Solihull",
    "sg:classifiers":[
        {
            "category":"Personal",
            "type":"Services"
        }
    ],
    "sg:postcode":"B92 7AL",
    "sg:province":"West Midlands",
    "sg:tags":[
        "wedding"
    ],
    "wof:name":"Lesley & Bobbie Cotton's",
    "wof:placetype":"venue"
},
  "geometry": {"coordinates":[-1.801839,52.434952],"type":"Point"}
}