{
  "type": "Feature",
  "properties": {
    "addr:full":"102 Loughborough Road Kirkcaldy Fife KY1 3DD",
    "addr:housenumber":"102",
    "addr:postcode":"ky1 3dd",
    "addr:street":"Loughborough Road",
    "iso:country":"GB",
    "sg:address":"102 Loughborough Road",
    "sg:city":"Kirkcaldy",
    "sg:classifiers":[
        {
            "category":"Education",
            "subcategory":"School",
            "type":"Public Place"
        }
    ],
    "sg:phone":"+44 1592 652244",
    "sg:postcode":"KY1 3DD",
    "sg:province":"Fife",
    "sg:tags":[
        "independent",
        "preparatory"
    ],
    "wof:name":"Sea View Private School",
    "wof:placetype":"venue"
},
  "geometry": {"coordinates":[-3.128438,56.12624],"type":"Point"}
}