{
  "type": "Feature",
  "properties": {
    "addr:full":"Research Info Unit, Caversham Park Reading Berkshire RG4 8TZ",
    "addr:housenumber":"unit",
    "addr:postcode":"rg4 8tz",
    "iso:country":"GB",
    "sg:address":"Research Info Unit, Caversham Park",
    "sg:city":"Reading",
    "sg:classifiers":[
        {
            "category":"Communications",
            "type":"Services"
        }
    ],
    "sg:phone":"+44 118 947 2742",
    "sg:postcode":"RG4 8TZ",
    "sg:province":"Berkshire",
    "sg:tags":[
        "broadcasting"
    ],
    "wof:name":"B B C Monitoring Unit",
    "wof:placetype":"venue"
},
  "geometry": {"coordinates":[-0.9676640034,51.4741744995],"type":"Point"}
}