{
  "type": "Feature",
  "properties": {
    "iso:country":"GB",
    "sg:address":"16 Fitzroy Street",
    "sg:city":"Newmarket",
    "sg:classifiers":[
        {
            "category":"Arts & Performance",
            "subcategory":"Theater",
            "type":"Entertainment"
        }
    ],
    "sg:phone":"+44 1638 663337",
    "sg:postcode":"CB8 0JW",
    "sg:province":"Cambridgeshire",
    "sg:tags":[
        "hall",
        "theatre",
        "concert"
    ],
    "wof:name":"Newmarket Operatic Musical & Dramatic Society",
    "wof:placetype":"venue"
},
  "geometry": {"coordinates":[0.400888,52.243683],"type":"Point"}
}