{
  "type": "Feature",
  "properties": {
    "addr:full":"21 Phelipps Rd, Corfe Mullen Wimborne Dorset BH21 3NN",
    "addr:housenumber":"21",
    "addr:postcode":"bh21 3nn",
    "addr:street":"Phelipps Rd",
    "iso:country":"GB",
    "sg:address":"21 Phelipps Rd, Corfe Mullen",
    "sg:city":"Wimborne",
    "sg:classifiers":[
        {
            "category":"Military Area",
            "subcategory":"Air Force Base",
            "type":"Public Place"
        }
    ],
    "sg:postcode":"BH21 3NN",
    "sg:province":"Dorset",
    "sg:tags":[
        "taxi",
        "hire",
        "private"
    ],
    "wof:name":"Hubbard,S,",
    "wof:placetype":"venue"
},
  "geometry": {"coordinates":[-2.0140988827,50.7737388611],"type":"Point"}
}