{
  "type": "Feature",
  "properties": {
    "iso:country":"GB",
    "sg:address":"153 Lady Margaret Road",
    "sg:city":"Southall",
    "sg:classifiers":[
        {
            "category":"Retail",
            "subcategory":"Driving School",
            "type":"Services"
        }
    ],
    "sg:phone":"+44 20 8571 1079",
    "sg:postcode":"UB1 2PS",
    "sg:province":"Greater London",
    "wof:name":"Raj School of Motoring",
    "wof:placetype":"venue"
},
  "geometry": {"coordinates":[-0.3756150007,51.5176086426],"type":"Point"}
}