{
  "type": "Feature",
  "properties": {
    "iso:country":"GB",
    "sg:address":"13 The Square",
    "sg:city":"Grantown-on-spey",
    "sg:classifiers":[
        {
            "category":"Travel",
            "subcategory":"Hotels & Motels",
            "type":"Entertainment"
        }
    ],
    "sg:phone":"+44 1479 872721",
    "sg:postcode":"PH26 3HG",
    "sg:province":"Highland",
    "wof:name":"Rosehall Hotel",
    "wof:placetype":"venue"
},
  "geometry": {"coordinates":[-3.607411,57.331684],"type":"Point"}
}