{
  "type": "Feature",
  "properties": {
    "iso:country":"GB",
    "sg:address":"52 Station Road",
    "sg:city":"Ilkeston",
    "sg:classifiers":[
        {
            "category":"Personal",
            "subcategory":"Beauty Salon",
            "type":"Services"
        }
    ],
    "sg:phone":"+44 115 932 5436",
    "sg:postcode":"DE7 5LE",
    "sg:province":"Derbyshire",
    "sg:tags":[
        "lady",
        "hairdresser"
    ],
    "wof:name":"Glynis Hair Design",
    "wof:placetype":"venue"
},
  "geometry": {"coordinates":[-1.304427,52.975662],"type":"Point"}
}