{
  "type": "Feature",
  "properties": {
    "iso:country":"GB",
    "sg:address":"Orme's Hey, 30 Church Walks",
    "sg:city":"Llandudno",
    "sg:classifiers":[
        {
            "category":"Travel",
            "subcategory":"Hotels & Motels",
            "type":"Entertainment"
        }
    ],
    "sg:phone":"+44 1492 593923",
    "sg:postcode":"LL30 2HL",
    "sg:province":"Conwy",
    "sg:tags":[
        "self",
        "catering"
    ],
    "wof:name":"B Powell",
    "wof:placetype":"venue"
},
  "geometry": {"coordinates":[-3.8380138874,53.3251457214],"type":"Point"}
}