{
  "type": "Feature",
  "properties": {
    "iso:country":"GB",
    "sg:address":"3 East Castle St",
    "sg:city":"Bridgnorth",
    "sg:classifiers":[
        {
            "category":"Professional",
            "subcategory":"Accounting & Tax Preparation",
            "type":"Services"
        }
    ],
    "sg:phone":"+44 1746 763129",
    "sg:postcode":"WV16 4AL",
    "sg:province":"Shropshire",
    "sg:tags":[
        "accountant"
    ],
    "wof:name":"Turner Peachey",
    "wof:placetype":"venue"
},
  "geometry": {"coordinates":[-2.419037,52.534107],"type":"Point"}
}