{
  "type": "Feature",
  "properties": {
    "addr:full":"Beccles Road, Thurlton Norwich Norfolk NR14 6RJ",
    "addr:postcode":"nr14 6rj",
    "addr:street":"Beccles Road",
    "iso:country":"GB",
    "sg:address":"Beccles Road, Thurlton",
    "sg:city":"Norwich",
    "sg:classifiers":[
        {
            "category":"Bars & Pubs",
            "type":"Food & Drink"
        }
    ],
    "sg:postcode":"NR14 6RJ",
    "sg:province":"Norfolk",
    "sg:tags":[
        "pubs",
        "inn"
    ],
    "wof:name":"Queens Head",
    "wof:placetype":"venue"
},
  "geometry": {"coordinates":[1.5572400093,52.5300254822],"type":"Point"}
}