{
  "type": "Feature",
  "properties": {
    "addr:full":"166-170 Wilderspool Causeway Warrington Cheshire WA4 6QA",
    "addr:housenumber":"166-170",
    "addr:postcode":"wa4 6qa",
    "addr:street":"Wilderspool Causeway",
    "iso:country":"GB",
    "sg:address":"166-170 Wilderspool Causeway",
    "sg:city":"Warrington",
    "sg:classifiers":[
        {
            "category":"Health Services",
            "subcategory":"Doctor",
            "type":"Services"
        }
    ],
    "sg:phone":"+44 1925 635024",
    "sg:postcode":"WA4 6QA",
    "sg:province":"Cheshire",
    "sg:tags":[
        "practitioners"
    ],
    "wof:name":"Desai, M I",
    "wof:placetype":"venue"
},
  "geometry": {"coordinates":[-2.5892400742,53.3803138733],"type":"Point"}
}