{
  "type": "Feature",
  "properties": {
    "iso:country":"GB",
    "sg:address":"Walnut Tree Farm, Birch Road",
    "sg:city":"Colchester",
    "sg:classifiers":[
        {
            "category":"Food & Beverages",
            "subcategory":"Candy",
            "type":"Retail Goods"
        }
    ],
    "sg:phone":"+44 1206 330240",
    "sg:postcode":"CO6 1DR",
    "sg:province":"Essex",
    "sg:tags":[
        "confectioner"
    ],
    "wof:name":"Linden Lady Chocolates Ltd.",
    "wof:placetype":"venue"
},
  "geometry": {"coordinates":[0.80764,51.860222],"type":"Point"}
}