{
  "type": "Feature",
  "properties": {
    "iso:country":"GB",
    "sg:address":"Hill Top, York Road, Barlby",
    "sg:city":"Selby",
    "sg:classifiers":[
        {
            "category":"Food & Beverages",
            "subcategory":"Farmers Market",
            "type":"Retail Goods"
        }
    ],
    "sg:phone":"+44 1757 700365",
    "sg:postcode":"YO8 5JQ",
    "sg:province":"East Riding of Yorkshire",
    "sg:tags":[
        "farm",
        "shop",
        "pyo"
    ],
    "wof:name":"Farm Shop",
    "wof:placetype":"venue"
},
  "geometry": {"coordinates":[-1.039334,53.801109],"type":"Point"}
}