{
  "type": "Feature",
  "properties": {
    "addr:full":"1568 Coventry Rd, Yardley Birmingham West Midlands B26 1AD",
    "addr:housenumber":"1568",
    "addr:postcode":"b26 1ad",
    "addr:street":"Coventry Rd",
    "iso:country":"GB",
    "sg:address":"1568 Coventry Rd, Yardley",
    "sg:city":"Birmingham",
    "sg:classifiers":[
        {
            "category":"Shopping",
            "subcategory":"Thrift Store",
            "type":"Retail Goods"
        },
        {
            "category":"Social Services",
            "subcategory":"Adult Care",
            "type":"Services"
        },
        {
            "category":"Organizations",
            "subcategory":"Non-profit Organization",
            "type":"Services"
        }
    ],
    "sg:phone":"+44 121 765 4817",
    "sg:postcode":"B26 1AD",
    "sg:province":"West Midlands",
    "sg:tags":[
        "shop",
        "voluntary",
        "centre",
        "organisation",
        "day",
        "charity"
    ],
    "wof:name":"Age Concern",
    "wof:placetype":"venue"
},
  "geometry": {"coordinates":[-1.8127629757,52.4620552063],"type":"Point"}
}