{
  "type": "Feature",
  "properties": {
    "iso:country":"GB",
    "sg:address":"7 Ransom Road, Tiptree",
    "sg:city":"Colchester",
    "sg:classifiers":[
        {
            "category":"Personal",
            "subcategory":"Sauna",
            "type":"Services"
        }
    ],
    "sg:phone":"+44 1621 819239",
    "sg:postcode":"CO5 0TL",
    "sg:province":"Essex",
    "sg:tags":[
        "equipment",
        "sunbed"
    ],
    "wof:name":"Cyrano Leisure",
    "wof:placetype":"venue"
},
  "geometry": {"coordinates":[0.744558,51.81509],"type":"Point"}
}