{
  "type": "Feature",
  "properties": {
    "iso:country":"GB",
    "sg:address":"1 Airlie St, Alyth",
    "sg:city":"Blairgowrie",
    "sg:classifiers":[
        {
            "category":"Food & Beverages",
            "subcategory":"Meat & Fish",
            "type":"Retail Goods"
        }
    ],
    "sg:phone":"+44 1828 632538",
    "sg:postcode":"PH11 8AH",
    "sg:province":"Angus",
    "sg:tags":[
        "chip"
    ],
    "wof:name":"Alyth Fish & Chip Shop",
    "wof:placetype":"venue"
},
  "geometry": {"coordinates":[-3.229992,56.62241],"type":"Point"}
}