{
  "type": "Feature",
  "properties": {
    "addr:full":"11 Lichfield Road, Rushall Walsall West Midlands WS4 1NP",
    "addr:housenumber":"11",
    "addr:postcode":"ws4 1np",
    "addr:street":"Lichfield Road",
    "iso:country":"GB",
    "sg:address":"11 Lichfield Road, Rushall",
    "sg:city":"Walsall",
    "sg:classifiers":[
        {
            "category":"Retail",
            "subcategory":"Driving School",
            "type":"Services"
        }
    ],
    "sg:phone":"+44 1922 612134",
    "sg:postcode":"WS4 1NP",
    "sg:province":"West Midlands",
    "wof:name":"Confidence School of Motoring",
    "wof:placetype":"venue"
},
  "geometry": {"coordinates":[-1.956747,52.610985],"type":"Point"}
}