{
  "type": "Feature",
  "properties": {
    "iso:country":"GB",
    "sg:address":"Northfiel Farm, St Abbs",
    "sg:city":"Eyemouth",
    "sg:classifiers":[
        {
            "category":"Cafe",
            "type":"Food & Drink"
        }
    ],
    "sg:postcode":"TD14 5QF",
    "sg:province":"Scottish Borders",
    "sg:tags":[
        "tea",
        "room"
    ],
    "wof:name":"The Head Start Coffee Shop",
    "wof:placetype":"venue"
},
  "geometry": {"coordinates":[-2.0951159,55.8731422424],"type":"Point"}
}