{
  "type": "Feature",
  "properties": {
    "addr:full":"5 Glebelands, Mersham Ashford Kent TN25 6PB",
    "addr:housenumber":"5;mersham",
    "addr:postcode":"tn25 6pb",
    "iso:country":"GB",
    "sg:address":"5 Glebelands, Mersham",
    "sg:city":"Ashford",
    "sg:classifiers":[
        {
            "category":"Building & Trades",
            "subcategory":"Construction",
            "type":"Services"
        }
    ],
    "sg:postcode":"TN25 6PB",
    "sg:province":"Kent",
    "sg:tags":[
        "decorator",
        "painter"
    ],
    "wof:name":"Southern Services",
    "wof:placetype":"venue"
},
  "geometry": {"coordinates":[0.98449,51.116428],"type":"Point"}
}