{
  "type": "Feature",
  "properties": {
    "iso:country":"GB",
    "sg:address":"6 Babmaes Street",
    "sg:city":"Westminster",
    "sg:classifiers":[
        {
            "category":"Banks & Credit Unions",
            "subcategory":"Financial Services",
            "type":"Services"
        }
    ],
    "sg:postcode":"SW1Y 6HD",
    "sg:province":"Greater London",
    "sg:tags":[
        "consultant"
    ],
    "wof:name":"Bayreel Ltd",
    "wof:placetype":"venue"
},
  "geometry": {"coordinates":[-0.135029003,51.5086631775],"type":"Point"}
}