{
  "type": "Feature",
  "properties": {
    "addr:full":"98 Godsey Lane Peterborough Cambridgeshire PE6 8HZ",
    "addr:housenumber":"98",
    "addr:postcode":"pe6 8hz",
    "addr:street":"Godsey Lane",
    "iso:country":"GB",
    "sg:address":"98 Godsey Lane",
    "sg:city":"Peterborough",
    "sg:classifiers":[
        {
            "category":"Communications",
            "subcategory":"Film & Video Production",
            "type":"Services"
        }
    ],
    "sg:postcode":"PE6 8HZ",
    "sg:province":"Cambridgeshire",
    "sg:tags":[
        "pr",
        "telemarketing"
    ],
    "wof:name":"Midas Marketing",
    "wof:placetype":"venue"
},
  "geometry": {"coordinates":[-0.3172490001,52.6835365295],"type":"Point"}
}