{
  "type": "Feature",
  "properties": {
    "iso:country":"GB",
    "sg:address":"83 Latham Avenue, Helsby",
    "sg:city":"Warrington",
    "sg:classifiers":[
        {
            "category":"Real Estate",
            "subcategory":"Architect",
            "type":"Services"
        }
    ],
    "sg:postcode":"WA6 0EA",
    "sg:province":"Cheshire",
    "wof:name":"Courtwick Engineering Ltd",
    "wof:placetype":"venue"
},
  "geometry": {"coordinates":[-2.77238,53.261269],"type":"Point"}
}