{
  "type": "Feature",
  "properties": {
    "addr:full":"Langdale Richmond North Yorkshire DL10 5PW",
    "addr:postcode":"dl10 5pw",
    "addr:street":"Yorkshire",
    "iso:country":"GB",
    "sg:address":"Langdale",
    "sg:city":"Richmond",
    "sg:classifiers":[
        {
            "category":"Personal",
            "subcategory":"Adult",
            "type":"Services"
        }
    ],
    "sg:phone":"+44 1325 718046",
    "sg:postcode":"DL10 5PW",
    "sg:province":"North Yorkshire",
    "sg:tags":[
        "equestrian"
    ],
    "wof:name":"Barnhouse Racing Stables",
    "wof:placetype":"venue"
},
  "geometry": {"coordinates":[-1.712299,54.443001],"type":"Point"}
}