{
  "type": "Feature",
  "properties": {
    "addr:full":"123-125 Edinburgh Ave Slough Berkshire SL1 4SS",
    "addr:housenumber":"123-125",
    "addr:postcode":"sl1 4ss",
    "addr:street":"Edinburgh Ave",
    "iso:country":"GB",
    "sg:address":"123-125 Edinburgh Ave",
    "sg:city":"Slough",
    "sg:classifiers":[
        {
            "category":"Manufacturing",
            "subcategory":"Signs",
            "type":"Manufacturing & Wholesale Goods"
        }
    ],
    "sg:phone":"+44 1753 824748",
    "sg:postcode":"SL1 4SS",
    "sg:province":"Berkshire",
    "sg:tags":[
        "writer"
    ],
    "wof:name":"Altype Signs",
    "wof:placetype":"venue"
},
  "geometry": {"coordinates":[-0.6288729906,51.5250091553],"type":"Point"}
}