{
  "type": "Feature",
  "properties": {
    "iso:country":"GB",
    "sg:address":"24 High St",
    "sg:city":"Wimbledon",
    "sg:classifiers":[
        {
            "category":"Real Estate",
            "subcategory":"Real Estate Agent",
            "type":"Services"
        }
    ],
    "sg:phone":"+44 20 8944 7744",
    "sg:postcode":"SW19 5DX",
    "sg:province":"Greater London",
    "wof:name":"Monckton & Co",
    "wof:placetype":"venue"
},
  "geometry": {"coordinates":[-0.2165900022,51.4245109558],"type":"Point"}
}