{
  "type": "Feature",
  "properties": {
    "addr:full":"129 Deansgate Bolton Lancashire BL1 1HA",
    "addr:housenumber":"129",
    "addr:postcode":"bl1 1ha",
    "addr:street":"Deansgate",
    "iso:country":"GB",
    "sg:address":"129 Deansgate",
    "sg:city":"Bolton",
    "sg:classifiers":[
        {
            "category":"Shopping",
            "subcategory":"Books",
            "type":"Retail Goods"
        }
    ],
    "sg:phone":"+44 1204 532384",
    "sg:postcode":"BL1 1HA",
    "sg:province":"Lancashire",
    "sg:tags":[
        "bookseller"
    ],
    "wof:name":"Wesley Owen Books & Music",
    "wof:placetype":"venue"
},
  "geometry": {"coordinates":[-2.4325621128,53.5789909363],"type":"Point"}
}