{
  "type": "Feature",
  "properties": {
    "iso:country":"GB",
    "sg:address":"150 Liverpool Road, Longton",
    "sg:city":"Preston",
    "sg:classifiers":[
        {
            "category":"Bars & Pubs",
            "type":"Food & Drink"
        }
    ],
    "sg:phone":"+44 1772 619719",
    "sg:postcode":"PR4 5AU",
    "sg:province":"Lancashire",
    "sg:tags":[
        "pubs",
        "inn"
    ],
    "wof:name":"Golden Ball",
    "wof:placetype":"venue"
},
  "geometry": {"coordinates":[-2.767271,53.732727],"type":"Point"}
}