{
  "type": "Feature",
  "properties": {
    "iso:country":"GB",
    "sg:address":"118 Chapel Lane",
    "sg:city":"Chorley",
    "sg:classifiers":[
        {
            "category":"Shopping",
            "subcategory":"Department Store",
            "type":"Retail Goods"
        }
    ],
    "sg:phone":"+44 1257 792647",
    "sg:postcode":"PR7 4PN",
    "sg:province":"Lancashire",
    "wof:name":"Chapel Lane Post Office",
    "wof:placetype":"venue"
},
  "geometry": {"coordinates":[-2.6545240879,53.624080658],"type":"Point"}
}