{
  "type": "Feature",
  "properties": {
    "iso:country":"GB",
    "sg:address":"Green Acres, Painswick Rd",
    "sg:city":"Gloucester",
    "sg:classifiers":[
        {
            "category":"Professional",
            "subcategory":"Engineering",
            "type":"Services"
        }
    ],
    "sg:phone":"+44 1452 863725",
    "sg:postcode":"GL3 4RP",
    "sg:province":"Gloucestershire",
    "sg:tags":[
        "consulting",
        "engineer"
    ],
    "wof:name":"Roberts Brian & Associates",
    "wof:placetype":"venue"
},
  "geometry": {"coordinates":[-2.15806,51.842533],"type":"Point"}
}