{
  "type": "Feature",
  "properties": {
    "iso:country":"GB",
    "sg:address":"2 Bramble Clo",
    "sg:city":"Tonbridge",
    "sg:classifiers":[
        {
            "category":"Professional",
            "subcategory":"Lawyer & Legal Services",
            "type":"Services"
        }
    ],
    "sg:phone":"+44 1732 833115",
    "sg:postcode":"TN11 9HG",
    "sg:province":"Kent",
    "sg:tags":[
        "advice",
        "counselling"
    ],
    "wof:name":"Rochelle Lewin",
    "wof:placetype":"venue"
},
  "geometry": {"coordinates":[0.253035,51.208557],"type":"Point"}
}