{
  "type": "Feature",
  "properties": {
    "iso:country":"GB",
    "sg:address":"Ingate Place",
    "sg:city":"London",
    "sg:classifiers":[
        {
            "category":"Professional",
            "type":"Services"
        }
    ],
    "sg:phone":"+44 20 7627 5085",
    "sg:postcode":"SW8 3NS",
    "sg:province":"Greater London",
    "sg:tags":[
        "interior",
        "furnishers",
        "designer"
    ],
    "wof:name":"Stratton-Norris Susanna Interior Designers",
    "wof:placetype":"venue"
},
  "geometry": {"coordinates":[-0.145299,51.474945],"type":"Point"}
}