{
  "type": "Feature",
  "properties": {
    "iso:country":"GB",
    "sg:address":"29a High East Street",
    "sg:city":"Dorchester",
    "sg:classifiers":[
        {
            "category":"Home & Garden",
            "subcategory":"Home Furnishings",
            "type":"Retail Goods"
        },
        {
            "category":"Building & Trades",
            "subcategory":"Landfill",
            "type":"Services"
        }
    ],
    "sg:phone":"+44 1305 261271",
    "sg:postcode":"DT1 1HF",
    "sg:province":"Dorset",
    "sg:tags":[
        "blind",
        "awning",
        "canopy",
        "blinds"
    ],
    "wof:name":"Discount Blind Centre",
    "wof:placetype":"venue"
},
  "geometry": {"coordinates":[-2.43526,50.715649],"type":"Point"}
}