{
  "type": "Feature",
  "properties": {
    "addr:full":"74 Deepdale Road Preston Lancashire PR1 5AR",
    "addr:housenumber":"74",
    "addr:postcode":"pr1 5ar",
    "addr:street":"Deepdale Road",
    "iso:country":"GB",
    "sg:address":"74 Deepdale Road",
    "sg:city":"Preston",
    "sg:classifiers":[
        {
            "category":"Health Services",
            "subcategory":"Dentist",
            "type":"Services"
        }
    ],
    "sg:phone":"+44 1772 555610",
    "sg:postcode":"PR1 5AR",
    "sg:province":"Lancashire",
    "wof:name":"M E Hamer",
    "wof:placetype":"venue"
},
  "geometry": {"coordinates":[-2.690529,53.763229],"type":"Point"}
}