{
  "type": "Feature",
  "properties": {
    "addr:full":"Bartholomews Cottage, School La Cheltenham Gloucestershire GL52 3NS",
    "addr:postcode":"gl52 3ns",
    "addr:street":"La",
    "iso:country":"GB",
    "sg:address":"Bartholomews Cottage, School La",
    "sg:city":"Cheltenham",
    "sg:classifiers":[
        {
            "category":"Health Services",
            "subcategory":"Doctor",
            "type":"Services"
        }
    ],
    "sg:phone":"+44 1242 524434",
    "sg:postcode":"GL52 3NS",
    "sg:province":"Gloucestershire",
    "sg:tags":[
        "practitioners"
    ],
    "wof:name":"Ellis, R H",
    "wof:placetype":"venue"
},
  "geometry": {"coordinates":[-2.04364,51.929562],"type":"Point"}
}