{
  "type": "Feature",
  "properties": {
    "iso:country":"GB",
    "sg:address":"31 Crayford High St",
    "sg:city":"Dartford",
    "sg:classifiers":[
        {
            "category":"Home & Garden",
            "subcategory":"Hardware",
            "type":"Retail Goods"
        }
    ],
    "sg:postcode":"DA1 4HH",
    "sg:province":"Kent",
    "sg:tags":[
        "retailer",
        "diy"
    ],
    "wof:name":"Weverley,Kenneth,",
    "wof:placetype":"venue"
},
  "geometry": {"coordinates":[0.1890020072,51.4492759705],"type":"Point"}
}