{
  "type": "Feature",
  "properties": {
    "addr:full":"Llanfihangel-talyllyllwyd Brecon Powys LD3 7TL",
    "addr:postcode":"ld3 7tl",
    "iso:country":"GB",
    "sg:address":"Llanfihangel-talyllyllwyd",
    "sg:city":"Brecon",
    "sg:classifiers":[
        {
            "category":"Government",
            "subcategory":"Post Office",
            "type":"Public Place"
        }
    ],
    "sg:phone":"+44 1874 658220",
    "sg:postcode":"LD3 7TL",
    "sg:province":"Powys",
    "wof:name":"Llanfihangel-Talyllyn Post Office",
    "wof:placetype":"venue"
},
  "geometry": {"coordinates":[-3.391142,51.949741],"type":"Point"}
}