{
  "type": "Feature",
  "properties": {
    "iso:country":"GB",
    "sg:address":"Technical House, Crowtrees Road, West Slaithwaite",
    "sg:city":"Huddersfield",
    "sg:classifiers":[
        {
            "category":"Professional",
            "subcategory":"Computer Services",
            "type":"Services"
        }
    ],
    "sg:postcode":"HD7 5XA",
    "sg:province":"West Yorkshire",
    "sg:tags":[
        "consultant"
    ],
    "wof:name":"R C S",
    "wof:placetype":"venue"
},
  "geometry": {"coordinates":[-1.911952,53.613602],"type":"Point"}
}