{
  "type": "Feature",
  "properties": {
    "addr:full":"Amber House, 11 Vance Business Park, Norwood Road Gateshead Tyne and Wear NE11 9NE",
    "addr:housenumber":"11",
    "addr:postcode":"ne11 9ne",
    "addr:street":"Vance Business Park Norwood Road",
    "iso:country":"GB",
    "sg:address":"Amber House, 11 Vance Business Park, Norwood Road",
    "sg:city":"Gateshead",
    "sg:classifiers":[
        {
            "category":"Professional",
            "subcategory":"Business Services",
            "type":"Services"
        }
    ],
    "sg:phone":"+44 191 492 2020",
    "sg:postcode":"NE11 9NE",
    "sg:province":"Tyne and Wear",
    "sg:tags":[
        "assessment",
        "quality"
    ],
    "wof:name":"Amberarch Ltd.",
    "wof:placetype":"venue"
},
  "geometry": {"coordinates":[-1.6332290173,54.9471893311],"type":"Point"}
}