{
  "type": "Feature",
  "properties": {
    "addr:full":"Phoenix House, 15-19 Norway Street, Portslade Brighton East Sussex BN41 1GN",
    "addr:housenumber":"15-19",
    "addr:postcode":"bn41 1gn",
    "addr:street":"Norway Street",
    "iso:country":"GB",
    "sg:address":"Phoenix House, 15-19 Norway Street, Portslade",
    "sg:city":"Brighton",
    "sg:classifiers":[
        {
            "category":"Social Services",
            "subcategory":"Job Training",
            "type":"Services"
        }
    ],
    "sg:postcode":"BN41 1GN",
    "sg:province":"East Sussex",
    "sg:tags":[
        "translator",
        "interpreter"
    ],
    "wof:name":"Phoenix Group Consulting Ltd.",
    "wof:placetype":"venue"
},
  "geometry": {"coordinates":[-0.2096579969,50.8341827393],"type":"Point"}
}