{
  "type": "Feature",
  "properties": {
    "addr:full":"Gartincaber Farm, Plean Stirling Falkirk FK7 8BA",
    "addr:postcode":"fk7 8ba",
    "iso:country":"GB",
    "sg:address":"Gartincaber Farm, Plean",
    "sg:city":"Stirling",
    "sg:classifiers":[
        {
            "category":"Retail",
            "subcategory":"Driving School",
            "type":"Services"
        }
    ],
    "sg:phone":"+44 1786 816400",
    "sg:postcode":"FK7 8BA",
    "sg:province":"Falkirk",
    "wof:name":"Swift School Of Motoring",
    "wof:placetype":"venue"
},
  "geometry": {"coordinates":[-3.8759388924,56.0651016235],"type":"Point"}
}