{
  "type": "Feature",
  "properties": {
    "addr:full":"7 Kinglake Rd Wallasey Merseyside CH44 8BS",
    "addr:housenumber":"7",
    "addr:postcode":"ch44 8bs",
    "addr:street":"Kinglake Rd",
    "iso:country":"GB",
    "sg:address":"7 Kinglake Rd",
    "sg:city":"Wallasey",
    "sg:classifiers":[
        {
            "category":"Wholesale",
            "subcategory":"Electrical",
            "type":"Manufacturing & Wholesale Goods"
        }
    ],
    "sg:phone":"+44 151 200 8498",
    "sg:postcode":"CH44 8BS",
    "sg:province":"Merseyside",
    "sg:tags":[
        "equipment",
        "refrigeration"
    ],
    "wof:name":"Phoenix Fire Security",
    "wof:placetype":"venue"
},
  "geometry": {"coordinates":[-3.0278029442,53.4203681946],"type":"Point"}
}