{
  "type": "Feature",
  "properties": {
    "iso:country":"GB",
    "sg:address":"29 Crosland Edge",
    "sg:city":"Huddersfield",
    "sg:classifiers":[
        {
            "category":"Building & Trades",
            "subcategory":"Construction",
            "type":"Services"
        }
    ],
    "sg:phone":"+44 1484 851776",
    "sg:postcode":"HD7 3RS",
    "sg:province":"West Yorkshire",
    "sg:tags":[
        "builder"
    ],
    "wof:name":"Liall Joinery",
    "wof:placetype":"venue"
},
  "geometry": {"coordinates":[-1.7826800346,53.6469497681],"type":"Point"}
}