{
  "type": "Feature",
  "properties": {
    "addr:full":"The Oval, 5 Claylands Place London Greater London SW8 1NL",
    "addr:housenumber":"5",
    "addr:postcode":"sw8 1nl",
    "addr:street":"Oval;Claylands Place",
    "iso:country":"GB",
    "sg:address":"The Oval, 5 Claylands Place",
    "sg:city":"London",
    "sg:classifiers":[
        {
            "category":"Real Estate",
            "subcategory":"Architect",
            "type":"Services"
        }
    ],
    "sg:phone":"+44 20 7587 1271",
    "sg:postcode":"SW8 1NL",
    "sg:province":"Greater London",
    "wof:name":"Best Harding Roels Partnership",
    "wof:placetype":"venue"
},
  "geometry": {"coordinates":[-0.114061,51.480942],"type":"Point"}
}