{
  "type": "Feature",
  "properties": {
    "addr:full":"8 Grosvenor House, Market Parade Gloucester Gloucestershire GL1 1SZ",
    "addr:housenumber":"8;house",
    "addr:postcode":"gl1 1sz",
    "addr:street":"Market Parade",
    "iso:country":"GB",
    "sg:address":"8 Grosvenor House, Market Parade",
    "sg:city":"Gloucester",
    "sg:classifiers":[
        {
            "category":"Real Estate",
            "subcategory":"Surveying",
            "type":"Services"
        }
    ],
    "sg:postcode":"GL1 1SZ",
    "sg:province":"Gloucestershire",
    "sg:tags":[
        "surveyor",
        "valuer"
    ],
    "wof:name":"Westwell Lambe",
    "wof:placetype":"venue"
},
  "geometry": {"coordinates":[-2.249624,51.863811],"type":"Point"}
}