{
  "type": "Feature",
  "properties": {
    "addr:full":"56 Sankey St Warrington Cheshire WA1 1SB",
    "addr:housenumber":"56",
    "addr:postcode":"wa1 1sb",
    "addr:street":"Sankey St",
    "iso:country":"GB",
    "sg:address":"56 Sankey St",
    "sg:city":"Warrington",
    "sg:classifiers":[
        {
            "category":"Bars & Pubs",
            "type":"Food & Drink"
        }
    ],
    "sg:phone":"+44 1925 638776",
    "sg:postcode":"WA1 1SB",
    "sg:province":"Cheshire",
    "sg:tags":[
        "pubs",
        "inn"
    ],
    "wof:name":"The White Hart",
    "wof:placetype":"venue"
},
  "geometry": {"coordinates":[-2.5963830948,53.3889694214],"type":"Point"}
}