{
  "type": "Feature",
  "properties": {
    "addr:full":"Unit 1 Meadow Works, Court Street Trowbridge Wiltshire BA14 8BR",
    "addr:housenumber":"unit 1",
    "addr:postcode":"ba14 8br",
    "addr:street":"Meadow Works Court Street",
    "iso:country":"GB",
    "sg:address":"Unit 1 Meadow Works, Court Street",
    "sg:city":"Trowbridge",
    "sg:classifiers":[
        {
            "category":"Professional",
            "subcategory":"Printing & Photocopies",
            "type":"Services"
        }
    ],
    "sg:postcode":"BA14 8BR",
    "sg:province":"Wiltshire",
    "sg:tags":[
        "printer"
    ],
    "wof:name":"Phoenix Screen Print",
    "wof:placetype":"venue"
},
  "geometry": {"coordinates":[-2.2083740234,51.3153419495],"type":"Point"}
}