{
  "type": "Feature",
  "properties": {
    "addr:full":"Maya Angelou Family Centre, Keston Road, Tottenham London Greater London N17 6PW",
    "addr:postcode":"n17 6pw",
    "addr:street":"Keston Road",
    "iso:country":"GB",
    "sg:address":"Maya Angelou Family Centre, Keston Road, Tottenham",
    "sg:city":"London",
    "sg:classifiers":[
        {
            "category":"Organizations",
            "subcategory":"Non-profit Organization",
            "type":"Services"
        }
    ],
    "sg:phone":"+44 20 8808 7882",
    "sg:postcode":"N17 6PW",
    "sg:province":"Greater London",
    "sg:tags":[
        "organisation",
        "voluntary",
        "charity"
    ],
    "wof:name":"N S P C C",
    "wof:placetype":"venue"
},
  "geometry": {"coordinates":[-0.08735,51.587811],"type":"Point"}
}