{
  "type": "Feature",
  "properties": {
    "addr:full":"22 Burghley Court, Great Holm Milton Keynes Buckinghamshire MK8 9EL",
    "addr:housenumber":"22",
    "addr:postcode":"mk8 9el",
    "addr:street":"Burghley Court",
    "iso:country":"GB",
    "sg:address":"22 Burghley Court, Great Holm",
    "sg:city":"Milton Keynes",
    "sg:classifiers":[
        {
            "category":"Retail",
            "subcategory":"Driving School",
            "type":"Services"
        }
    ],
    "sg:phone":"+44 1908 560868",
    "sg:postcode":"MK8 9EL",
    "sg:province":"Buckinghamshire",
    "wof:name":"Stanley Oakes School of Motoring",
    "wof:placetype":"venue"
},
  "geometry": {"coordinates":[-0.7967820168,52.0330886841],"type":"Point"}
}