{
  "type": "Feature",
  "properties": {
    "addr:full":"311 Brockley Road London Greater London SE4 2QZ",
    "addr:housenumber":"311",
    "addr:postcode":"se4 2qz",
    "addr:street":"Brockley Road",
    "iso:country":"GB",
    "sg:address":"311 Brockley Road",
    "sg:city":"London",
    "sg:classifiers":[
        {
            "category":"Shopping",
            "subcategory":"News",
            "type":"Retail Goods"
        }
    ],
    "sg:phone":"+44 20 8692 5518",
    "sg:postcode":"SE4 2QZ",
    "sg:province":"Greater London",
    "sg:tags":[
        "newsagent"
    ],
    "wof:name":"Sewel Newsagents",
    "wof:placetype":"venue"
},
  "geometry": {"coordinates":[-0.0337379985,51.4596595764],"type":"Point"}
}