{
  "type": "Feature",
  "properties": {
    "iso:country":"GB",
    "sg:address":"18-19 Thurlestone Pde, High St",
    "sg:city":"Shepperton",
    "sg:classifiers":[
        {
            "category":"Professional",
            "subcategory":"Printing & Photocopies",
            "type":"Services"
        }
    ],
    "sg:phone":"+44 1932 248600",
    "sg:postcode":"TW17 9AR",
    "sg:province":"Surrey",
    "sg:tags":[
        "duplicating",
        "copying"
    ],
    "wof:name":"Quick Print & Copy",
    "wof:placetype":"venue"
},
  "geometry": {"coordinates":[-0.448547,51.394321],"type":"Point"}
}