{
  "type": "Feature",
  "properties": {
    "addr:full":"I Shoreditch Road Taunton Somerset TA1 3BU",
    "addr:postcode":"ta1 3bu",
    "addr:street":"Shoreditch Road",
    "iso:country":"GB",
    "sg:address":"I Shoreditch Road",
    "sg:city":"Taunton",
    "sg:classifiers":[
        {
            "category":"Autos & Motor Vehicles",
            "subcategory":"Auto Supplies",
            "type":"Retail Goods"
        }
    ],
    "sg:phone":"+44 1823 275783",
    "sg:postcode":"TA1 3BU",
    "sg:province":"Somerset",
    "sg:tags":[
        "gearbox"
    ],
    "wof:name":"Jon Doble M O T Station",
    "wof:placetype":"venue"
},
  "geometry": {"coordinates":[-3.087651968,51.0042533875],"type":"Point"}
}