{
  "type": "Feature",
  "properties": {
    "addr:full":"37 Hale Road Altrincham Cheshire WA14 2EY",
    "addr:housenumber":"37",
    "addr:postcode":"wa14 2ey",
    "addr:street":"Hale Road",
    "iso:country":"GB",
    "sg:address":"37 Hale Road",
    "sg:city":"Altrincham",
    "sg:classifiers":[
        {
            "category":"Museum",
            "subcategory":"Art Museum",
            "type":"Entertainment"
        }
    ],
    "sg:phone":"+44 161 929 4867",
    "sg:postcode":"WA14 2EY",
    "sg:province":"Cheshire",
    "sg:tags":[
        "gallery"
    ],
    "wof:name":"Paint Stop Ltd.",
    "wof:placetype":"venue"
},
  "geometry": {"coordinates":[-2.348671,53.381691],"type":"Point"}
}