{
  "type": "Feature",
  "properties": {
    "addr:full":"Unit 4 230-240 Stoke Newington High St Stoke Newington Greater London N16 7HU",
    "addr:housenumber":"unit 4",
    "addr:postcode":"230-240;n16 7hu",
    "addr:street":"Stoke Newington High St",
    "iso:country":"GB",
    "sg:address":"Unit 4 230-240 Stoke Newington High St",
    "sg:city":"Stoke Newington",
    "sg:classifiers":[
        {
            "category":"Health Services",
            "subcategory":"Dentist",
            "type":"Services"
        }
    ],
    "sg:phone":"+44 20 7249 2939",
    "sg:postcode":"N16 7HU",
    "sg:province":"Greater London",
    "wof:name":"A S Shah",
    "wof:placetype":"venue"
},
  "geometry": {"coordinates":[-0.073279,51.563309],"type":"Point"}
}