{
  "type": "Feature",
  "properties": {
    "iso:country":"GB",
    "sg:address":"140 Braywick Road",
    "sg:city":"Maidenhead",
    "sg:classifiers":[
        {
            "category":"Professional",
            "subcategory":"Business Services",
            "type":"Services"
        }
    ],
    "sg:postcode":"SL6 1DJ",
    "sg:province":"Berkshire",
    "sg:tags":[
        "import",
        "export",
        "agent"
    ],
    "wof:name":"Amergate Ltd.",
    "wof:placetype":"venue"
},
  "geometry": {"coordinates":[-0.71387,51.506596],"type":"Point"}
}