{
  "type": "Feature",
  "properties": {
    "iso:country":"GB",
    "sg:address":"Medwyn House, Mountfield Road",
    "sg:city":"Lewes",
    "sg:classifiers":[
        {
            "category":"Professional",
            "subcategory":"Employment Agencies",
            "type":"Services"
        },
        {
            "category":"Government",
            "subcategory":"Office",
            "type":"Public Place"
        }
    ],
    "sg:phone":"+44 1273 368080",
    "sg:postcode":"BN7 2XS",
    "sg:province":"East Sussex",
    "sg:tags":[
        "consultant",
        "local"
    ],
    "wof:name":"Lewes Jobcentre",
    "wof:placetype":"venue"
},
  "geometry": {"coordinates":[0.011325,50.869518],"type":"Point"}
}