{
  "type": "Feature",
  "properties": {
    "addr:full":"10 Seafield Road Blackpool Lancashire FY1 2LS",
    "addr:housenumber":"10",
    "addr:postcode":"fy1 2ls",
    "addr:street":"Seafield Road",
    "iso:country":"GB",
    "sg:address":"10 Seafield Road",
    "sg:city":"Blackpool",
    "sg:classifiers":[
        {
            "category":"Building & Trades",
            "subcategory":"Landscaping Services",
            "type":"Services"
        }
    ],
    "sg:postcode":"FY1 2LS",
    "sg:province":"Lancashire",
    "sg:tags":[
        "preservation",
        "timber"
    ],
    "wof:name":"Paul Dyson Timber Treatment",
    "wof:placetype":"venue"
},
  "geometry": {"coordinates":[-3.0504539013,53.8319969177],"type":"Point"}
}