{
  "type": "Feature",
  "properties": {
    "addr:full":"13 Strutton Ground Westminster Greater London SW1P 2HY",
    "addr:housenumber":"13",
    "addr:postcode":"sw1p 2hy",
    "addr:street":"Strutton Ground",
    "iso:country":"GB",
    "sg:address":"13 Strutton Ground",
    "sg:city":"Westminster",
    "sg:classifiers":[
        {
            "category":"Professional",
            "subcategory":"Art Services",
            "type":"Services"
        }
    ],
    "sg:phone":"+44 20 7976 0648",
    "sg:postcode":"SW1P 2HY",
    "sg:province":"Greater London",
    "sg:tags":[
        "graphic",
        "designer"
    ],
    "wof:name":"Jig Jog Design",
    "wof:placetype":"venue"
},
  "geometry": {"coordinates":[-0.1336400062,51.4973144531],"type":"Point"}
}