{
  "type": "Feature",
  "properties": {
    "iso:country":"GB",
    "sg:address":"Acorn Business Centre, 30 Lawrence St",
    "sg:city":"York",
    "sg:classifiers":[
        {
            "category":"Professional",
            "subcategory":"Computer Services",
            "type":"Services"
        }
    ],
    "sg:postcode":"YO10 3BN",
    "sg:province":"North Yorkshire",
    "sg:tags":[
        "consultant"
    ],
    "wof:name":"Crocker,John,",
    "wof:placetype":"venue"
},
  "geometry": {"coordinates":[-1.06958,53.954781],"type":"Point"}
}