{
  "type": "Feature",
  "properties": {
    "addr:full":"32 Chalmers St Dunfermline Fife KY12 8DF",
    "addr:housenumber":"32",
    "addr:postcode":"ky12 8df",
    "addr:street":"Chalmers St",
    "iso:country":"GB",
    "sg:address":"32 Chalmers St",
    "sg:city":"Dunfermline",
    "sg:classifiers":[
        {
            "category":"Shopping",
            "subcategory":"Department Store",
            "type":"Retail Goods"
        }
    ],
    "sg:phone":"+44 1383 722381",
    "sg:postcode":"KY12 8DF",
    "sg:province":"Fife",
    "wof:name":"ORR Co Ltd",
    "wof:placetype":"venue"
},
  "geometry": {"coordinates":[-3.4662120342,56.0720214844],"type":"Point"}
}