{
  "type": "Feature",
  "properties": {
    "addr:full":"9 Steward St Whitechapel Greater London E1 6AJ",
    "addr:housenumber":"9",
    "addr:postcode":"e1 6aj",
    "addr:street":"Steward St",
    "iso:country":"GB",
    "sg:address":"9 Steward St",
    "sg:city":"Whitechapel",
    "sg:classifiers":[
        {
            "category":"Shopping",
            "subcategory":"Bicycles & Sporting Goods",
            "type":"Retail Goods"
        }
    ],
    "sg:phone":"+44 20 7375 3088",
    "sg:postcode":"E1 6AJ",
    "sg:province":"Greater London",
    "sg:tags":[
        "cycle",
        "accessory"
    ],
    "wof:name":"The Cycle Surgery",
    "wof:placetype":"venue"
},
  "geometry": {"coordinates":[-0.077342,51.51886],"type":"Point"}
}