{
  "type": "Feature",
  "properties": {
    "addr:full":"Unit 1, Robertson Street Glasgow East Ayrshire G78 1QW",
    "addr:housenumber":"unit 1",
    "addr:postcode":"g78 1qw",
    "addr:street":"Robertson Street",
    "iso:country":"GB",
    "sg:address":"Unit 1, Robertson Street",
    "sg:city":"Glasgow",
    "sg:classifiers":[
        {
            "category":"Building & Trades",
            "subcategory":"Construction",
            "type":"Services"
        }
    ],
    "sg:postcode":"G78 1QW",
    "sg:province":"East Ayrshire",
    "sg:tags":[
        "joiner",
        "carpenter"
    ],
    "wof:name":"Premier Quality Joiners",
    "wof:placetype":"venue"
},
  "geometry": {"coordinates":[-4.398607,55.800823],"type":"Point"}
}