{
  "type": "Feature",
  "properties": {
    "iso:country":"GB",
    "sg:address":"A9 Stanlaw Abbey Business Centre, Dover Drive",
    "sg:city":"Ellesmere Port",
    "sg:classifiers":[
        {
            "category":"Building & Trades",
            "subcategory":"Construction",
            "type":"Services"
        }
    ],
    "sg:phone":"+44 151 355 3340",
    "sg:postcode":"CH65 9BF",
    "sg:province":"Cheshire",
    "sg:tags":[
        "roofing",
        "builder"
    ],
    "wof:name":"Undercover Roofing & Cladding Ltd.",
    "wof:placetype":"venue"
},
  "geometry": {"coordinates":[-2.905574,53.277199],"type":"Point"}
}