{
  "type": "Feature",
  "properties": {
    "addr:full":"222 Eccles Old Road Salford Greater Manchester M6 8AL",
    "addr:housenumber":"222",
    "addr:postcode":"m6 8al",
    "addr:street":"Eccles Old Road",
    "iso:country":"GB",
    "sg:address":"222 Eccles Old Road",
    "sg:city":"Salford",
    "sg:classifiers":[
        {
            "category":"Organizations",
            "subcategory":"Non-profit Organization",
            "type":"Services"
        }
    ],
    "sg:phone":"+44 161 707 0222",
    "sg:postcode":"M6 8AL",
    "sg:province":"Greater Manchester",
    "sg:tags":[
        "organisation",
        "voluntary",
        "charity"
    ],
    "wof:name":"Barnardos Salford Families Project",
    "wof:placetype":"venue"
},
  "geometry": {"coordinates":[-2.3191649914,53.4893875122],"type":"Point"}
}