{
  "type": "Feature",
  "properties": {
    "iso:country":"GB",
    "sg:address":"46 Station Road, Tiptree",
    "sg:city":"Colchester",
    "sg:classifiers":[
        {
            "category":"Home & Garden",
            "subcategory":"Household Appliances",
            "type":"Retail Goods"
        }
    ],
    "sg:postcode":"CO5 0BB",
    "sg:province":"Essex",
    "sg:tags":[
        "electrical"
    ],
    "wof:name":"Anchor (Domestic Appliance) Services",
    "wof:placetype":"venue"
},
  "geometry": {"coordinates":[0.746168,51.807701],"type":"Point"}
}