{
  "type": "Feature",
  "properties": {
    "iso:country":"GB",
    "sg:address":"167 Larch Gro",
    "sg:city":"Newport",
    "sg:classifiers":[
        {
            "category":"Food & Beverages",
            "subcategory":"Fruits & Vegetables",
            "type":"Retail Goods"
        }
    ],
    "sg:phone":"+44 1633 855376",
    "sg:postcode":"NP20 6LA",
    "sg:province":"Newport",
    "sg:tags":[
        "greengrocer"
    ],
    "wof:name":"Malpas Fruit Basket",
    "wof:placetype":"venue"
},
  "geometry": {"coordinates":[-3.0055611134,51.6162986755],"type":"Point"}
}