{
  "type": "Feature",
  "properties": {
    "addr:full":"Units A & B Beaufort Yard, Beaufort Road Swansea Swansea SA6 8EY",
    "addr:postcode":"sa6 8ey",
    "addr:street":"Beaufort Road",
    "iso:country":"GB",
    "sg:address":"Units A & B Beaufort Yard, Beaufort Road",
    "sg:city":"Swansea",
    "sg:classifiers":[
        {
            "category":"Retail",
            "subcategory":"Auto Repair",
            "type":"Services"
        }
    ],
    "sg:phone":"+44 1792 799699",
    "sg:postcode":"SA6 8EY",
    "sg:province":"Swansea",
    "sg:tags":[
        "modification",
        "garage"
    ],
    "wof:name":"M G R Motor Services",
    "wof:placetype":"venue"
},
  "geometry": {"coordinates":[-3.9282999039,51.6513786316],"type":"Point"}
}