{
  "type": "Feature",
  "properties": {
    "iso:country":"GB",
    "sg:address":"97 Heol Llanishen Fach",
    "sg:city":"Cardiff",
    "sg:classifiers":[
        {
            "category":"Building & Trades",
            "subcategory":"Construction",
            "type":"Services"
        }
    ],
    "sg:phone":"+44 29 2061 8705",
    "sg:postcode":"CF14 6LB",
    "sg:province":"Cardiff",
    "sg:tags":[
        "builder"
    ],
    "wof:name":"Bricknell Conservation",
    "wof:placetype":"venue"
},
  "geometry": {"coordinates":[-3.210025,51.529636],"type":"Point"}
}