{
  "type": "Feature",
  "properties": {
    "addr:full":"Rushenden Rd Queenborough Kent ME11 5JD",
    "addr:postcode":"me11 5jd",
    "addr:street":"Rushenden Rd",
    "iso:country":"GB",
    "sg:address":"Rushenden Rd",
    "sg:city":"Queenborough",
    "sg:classifiers":[
        {
            "category":"Shopping",
            "subcategory":"Clothing, Apparel, & Fashions",
            "type":"Retail Goods"
        }
    ],
    "sg:phone":"+44 1795 580280",
    "sg:postcode":"ME11 5JD",
    "sg:province":"Kent",
    "sg:tags":[
        "workwear",
        "protective"
    ],
    "wof:name":"Stourmac Ltd",
    "wof:placetype":"venue"
},
  "geometry": {"coordinates":[0.7467380166,51.4136238098],"type":"Point"}
}