{
  "type": "Feature",
  "properties": {
    "addr:full":"11 Kingsway, Tealby Market Rasen Lincolnshire LN8 3YA",
    "addr:housenumber":"11",
    "addr:postcode":"ln8 3ya",
    "addr:street":"Kingsway",
    "iso:country":"GB",
    "sg:address":"11 Kingsway, Tealby",
    "sg:city":"Market Rasen",
    "sg:classifiers":[
        {
            "category":"Bars & Pubs",
            "type":"Food & Drink"
        }
    ],
    "sg:phone":"+44 1673 838347",
    "sg:postcode":"LN8 3YA",
    "sg:province":"Lincolnshire",
    "sg:tags":[
        "pubs",
        "inn"
    ],
    "wof:name":"The Kings Head Inn",
    "wof:placetype":"venue"
},
  "geometry": {"coordinates":[-0.3330680132,53.3867874146],"type":"Point"}
}