{
  "type": "Feature",
  "properties": {
    "addr:full":"1 Drumlanrig Square Hawick Cumbria TD9 0AS",
    "addr:housenumber":"1",
    "addr:postcode":"td9 0as",
    "addr:street":"Drumlanrig Square Hawick",
    "iso:country":"GB",
    "sg:address":"1 Drumlanrig Square",
    "sg:city":"Hawick",
    "sg:classifiers":[
        {
            "category":"Bars & Pubs",
            "type":"Food & Drink"
        }
    ],
    "sg:phone":"+44 1450 377836",
    "sg:postcode":"TD9 0AS",
    "sg:province":"Cumbria",
    "sg:tags":[
        "pubs",
        "inn"
    ],
    "wof:name":"Barclay's Bar",
    "wof:placetype":"venue"
},
  "geometry": {"coordinates":[-2.789959,55.420425],"type":"Point"}
}