{
  "type": "Feature",
  "properties": {
    "iso:country":"GB",
    "sg:address":"16 Lawns Road",
    "sg:city":"Wimborne",
    "sg:classifiers":[
        {
            "category":"Organizations",
            "subcategory":"Non-profit Organization",
            "type":"Services"
        }
    ],
    "sg:phone":"+44 1202 884336",
    "sg:postcode":"BH21 2JP",
    "sg:province":"Dorset",
    "sg:tags":[
        "charitable",
        "organisation",
        "voluntary",
        "charity"
    ],
    "wof:name":"Subud Wessex",
    "wof:placetype":"venue"
},
  "geometry": {"coordinates":[-1.9446920156,50.804813385],"type":"Point"}
}