{
  "type": "Feature",
  "properties": {
    "iso:country":"GB",
    "sg:address":"27 Main Street, Humberstone",
    "sg:city":"Leicester",
    "sg:classifiers":[
        {
            "category":"Home & Garden",
            "subcategory":"Building Materials",
            "type":"Retail Goods"
        }
    ],
    "sg:phone":"+44 116 276 2380",
    "sg:postcode":"LE5 1AE",
    "sg:province":"Leicestershire",
    "sg:tags":[
        "ironwork",
        "product",
        "production",
        "design",
        "diy",
        "iron",
        "wrought"
    ],
    "wof:name":"Nags Welding Shop",
    "wof:placetype":"venue"
},
  "geometry": {"coordinates":[-1.0759739876,52.6469612122],"type":"Point"}
}