{
  "type": "Feature",
  "properties": {
    "addr:full":"Unit 5 & 6 Vicarage Field Barking Essex IG11 8DG",
    "addr:housenumber":"unit 5 & 6",
    "addr:postcode":"ig11 8dg",
    "addr:street":"Vicarage Field",
    "iso:country":"GB",
    "sg:address":"Unit 5 & 6 Vicarage Field",
    "sg:city":"Barking",
    "sg:classifiers":[
        {
            "category":"Shopping",
            "subcategory":"Gifts & Souvenirs",
            "type":"Retail Goods"
        }
    ],
    "sg:phone":"+44 20 8591 9669",
    "sg:postcode":"IG11 8DG",
    "sg:province":"Essex",
    "sg:tags":[
        "poster",
        "card"
    ],
    "wof:name":"Clinton Cards Plc",
    "wof:placetype":"venue"
},
  "geometry": {"coordinates":[0.0812600031,51.5378417969],"type":"Point"}
}