{
  "type": "Feature",
  "properties": {
    "iso:country":"GB",
    "sg:address":"15 Queen Street",
    "sg:city":"Worksop",
    "sg:classifiers":[
        {
            "category":"Professional",
            "subcategory":"Accounting & Tax Preparation",
            "type":"Services"
        }
    ],
    "sg:phone":"+44 1909 472640",
    "sg:postcode":"S80 2AP",
    "sg:province":"Nottinghamshire",
    "sg:tags":[
        "accountant"
    ],
    "wof:name":"Harrison Shipley",
    "wof:placetype":"venue"
},
  "geometry": {"coordinates":[-1.122973,53.303623],"type":"Point"}
}