{
  "type": "Feature",
  "properties": {
    "addr:full":"1200 Ringwood Road Bournemouth Dorset BH11 9LQ",
    "addr:housenumber":"1200",
    "addr:postcode":"bh11 9lq",
    "addr:street":"Ringwood Road",
    "iso:country":"GB",
    "sg:address":"1200 Ringwood Road",
    "sg:city":"Bournemouth",
    "sg:classifiers":[
        {
            "category":"Home & Garden",
            "subcategory":"Garden Supply",
            "type":"Retail Goods"
        },
        {
            "category":"Manufacturing",
            "subcategory":"Pottery",
            "type":"Manufacturing & Wholesale Goods"
        }
    ],
    "sg:phone":"+44 1202 574991",
    "sg:postcode":"BH11 9LQ",
    "sg:province":"Dorset",
    "sg:tags":[
        "sales",
        "machinery"
    ],
    "wof:name":"WILLOW COTTAGE",
    "wof:placetype":"venue"
},
  "geometry": {"coordinates":[-1.910516,50.774586],"type":"Point"}
}