{
  "type": "Feature",
  "properties": {
    "addr:full":"Wayside House, Longton Road, Barlaston Stoke-on-trent Staffordshire ST12 9AR",
    "addr:postcode":"st12 9ar",
    "addr:street":"Longton Road",
    "iso:country":"GB",
    "sg:address":"Wayside House, Longton Road, Barlaston",
    "sg:city":"Stoke-on-trent",
    "sg:classifiers":[
        {
            "category":"Real Estate",
            "subcategory":"Real Estate Operator",
            "type":"Services"
        }
    ],
    "sg:postcode":"ST12 9AR",
    "sg:province":"Staffordshire",
    "sg:tags":[
        "letting",
        "agent"
    ],
    "wof:name":"Leemac Developments",
    "wof:placetype":"venue"
},
  "geometry": {"coordinates":[-2.153088,52.950222],"type":"Point"}
}