{
  "type": "Feature",
  "properties": {
    "addr:full":"23 North John St Liverpool Merseyside L2 5QU",
    "addr:housenumber":"23",
    "addr:postcode":"l2 5qu",
    "addr:street":"North John St",
    "iso:country":"GB",
    "sg:address":"23 North John St",
    "sg:city":"Liverpool",
    "sg:classifiers":[
        {
            "category":"Bars & Pubs",
            "type":"Food & Drink"
        }
    ],
    "sg:phone":"+44 151 236 2071",
    "sg:postcode":"L2 5QU",
    "sg:province":"Merseyside",
    "sg:tags":[
        "pubs",
        "inn"
    ],
    "wof:name":"Cains",
    "wof:placetype":"venue"
},
  "geometry": {"coordinates":[-2.988554,53.406406],"type":"Point"}
}