{
  "type": "Feature",
  "properties": {
    "addr:full":"Unit 61, Caxton Court, Garamonde Drive, Wymbush Milton Keynes Buckinghamshire MK8 8DD",
    "addr:housenumber":"unit 61",
    "addr:postcode":"mk8 8dd",
    "addr:street":"Caxton Court Garamonde Drive",
    "iso:country":"GB",
    "sg:address":"Unit 61, Caxton Court, Garamonde Drive, Wymbush",
    "sg:city":"Milton Keynes",
    "sg:classifiers":[
        {
            "category":"Organizations",
            "subcategory":"Membership Organization",
            "type":"Services"
        }
    ],
    "sg:phone":"+44 1908 569355",
    "sg:postcode":"MK8 8DD",
    "sg:province":"Buckinghamshire",
    "sg:tags":[
        "intercom",
        "system"
    ],
    "wof:name":"Benn Security",
    "wof:placetype":"venue"
},
  "geometry": {"coordinates":[-0.8007310033,52.0438995361],"type":"Point"}
}