{
  "type": "Feature",
  "properties": {
    "iso:country":"GB",
    "sg:address":"Broom House, Ashcombe",
    "sg:city":"Dawlish",
    "sg:classifiers":[
        {
            "category":"Building & Trades",
            "subcategory":"Construction",
            "type":"Services"
        }
    ],
    "sg:phone":"+44 1626 866637",
    "sg:postcode":"EX7 0QB",
    "sg:province":"Devon",
    "sg:tags":[
        "builder"
    ],
    "wof:name":"Terence Cole-greenwell",
    "wof:placetype":"venue"
},
  "geometry": {"coordinates":[-3.533079,50.605824],"type":"Point"}
}