{
  "type": "Feature",
  "properties": {
    "iso:country":"GB",
    "sg:address":"3 Angelica Road, Bisley",
    "sg:city":"Woking",
    "sg:classifiers":[
        {
            "category":"Building & Trades",
            "subcategory":"Plumbing",
            "type":"Services"
        }
    ],
    "sg:postcode":"GU24 9EY",
    "sg:province":"Surrey",
    "sg:tags":[
        "heating"
    ],
    "wof:name":"Moore & Easterling",
    "wof:placetype":"venue"
},
  "geometry": {"coordinates":[-0.631659,51.325207],"type":"Point"}
}