{
  "type": "Feature",
  "properties": {
    "addr:full":"24 The Business Village, Wexham Road Slough Berkshire SL2 5HF",
    "addr:housenumber":"24",
    "addr:postcode":"sl2 5hf",
    "addr:street":"The Business Village Wexham Road",
    "iso:country":"GB",
    "sg:address":"24 The Business Village, Wexham Road",
    "sg:city":"Slough",
    "sg:classifiers":[
        {
            "category":"Professional",
            "subcategory":"Advertising",
            "type":"Services"
        }
    ],
    "sg:phone":"+44 1753 554160",
    "sg:postcode":"SL2 5HF",
    "sg:province":"Berkshire",
    "sg:tags":[
        "mail",
        "direct"
    ],
    "wof:name":"R A P Marketing",
    "wof:placetype":"venue"
},
  "geometry": {"coordinates":[-0.5797299743,51.513999939],"type":"Point"}
}