{
  "type": "Feature",
  "properties": {
    "iso:country":"GB",
    "sg:address":"71 Bondway, Vauxhall",
    "sg:city":"London",
    "sg:classifiers":[
        {
            "category":"Professional",
            "subcategory":"Computer Services",
            "type":"Services"
        }
    ],
    "sg:phone":"+44 20 8878 0187",
    "sg:postcode":"SW8 1SQ",
    "sg:province":"Greater London",
    "sg:tags":[
        "consultant"
    ],
    "wof:name":"George Lovett",
    "wof:placetype":"venue"
},
  "geometry": {"coordinates":[-0.124663,51.48415],"type":"Point"}
}