{
  "type": "Feature",
  "properties": {
    "addr:full":"1 Nursery Lane, Hockwold Cum Wilton Thetford Norfolk IP26 4ND",
    "addr:housenumber":"1",
    "addr:postcode":"ip26 4nd",
    "addr:street":"Nursery Lane",
    "iso:country":"GB",
    "sg:address":"1 Nursery Lane, Hockwold Cum Wilton",
    "sg:city":"Thetford",
    "sg:classifiers":[
        {
            "category":"Real Estate",
            "subcategory":"Real Estate Agent",
            "type":"Services"
        }
    ],
    "sg:postcode":"IP26 4ND",
    "sg:province":"Norfolk",
    "wof:name":"The Little Snoring Property Co. Ltd.",
    "wof:placetype":"venue"
},
  "geometry": {"coordinates":[0.5562899709,52.4632110596],"type":"Point"}
}