{
  "type": "Feature",
  "properties": {
    "addr:full":"The Halfcroft, Syston Leicester Leicestershire LE7 1LD",
    "addr:postcode":"le7 1ld",
    "iso:country":"GB",
    "sg:address":"The Halfcroft, Syston",
    "sg:city":"Leicester",
    "sg:classifiers":[
        {
            "category":"Food & Beverages",
            "subcategory":"Supermarket",
            "type":"Retail Goods"
        }
    ],
    "sg:phone":"+44 116 260 7985",
    "sg:postcode":"LE7 1LD",
    "sg:province":"Leicestershire",
    "sg:tags":[
        "frozen"
    ],
    "wof:name":"Pukka Pies Ltd.",
    "wof:placetype":"venue"
},
  "geometry": {"coordinates":[-1.08294,52.701496],"type":"Point"}
}