{
  "type": "Feature",
  "properties": {
    "addr:full":"Upper Bryn, Bryn Lane Newtown Powys SY16 3LZ",
    "addr:postcode":"sy16 3lz",
    "addr:street":"Upper Bryn Bryn Lane",
    "iso:country":"GB",
    "sg:address":"Upper Bryn, Bryn Lane",
    "sg:city":"Newtown",
    "sg:classifiers":[
        {
            "category":"Farming",
            "subcategory":"Livestock Farm",
            "type":"Manufacturing & Wholesale Goods"
        }
    ],
    "sg:postcode":"SY16 3LZ",
    "sg:province":"Powys",
    "sg:tags":[
        "others"
    ],
    "wof:name":"G I Francis & Co.",
    "wof:placetype":"venue"
},
  "geometry": {"coordinates":[-3.314612,52.512775],"type":"Point"}
}