{
  "type": "Feature",
  "properties": {
    "addr:full":"Unit 1a The Vo Tec Centre, Hambridge Lane Newbury Berkshire RG14 5TN",
    "addr:housenumber":"unit 1a",
    "addr:postcode":"rg14 5tn",
    "addr:street":"The;Hambridge Lane",
    "iso:country":"GB",
    "sg:address":"Unit 1a The Vo Tec Centre, Hambridge Lane",
    "sg:city":"Newbury",
    "sg:classifiers":[
        {
            "category":"Real Estate",
            "subcategory":"Real Estate Services",
            "type":"Services"
        }
    ],
    "sg:postcode":"RG14 5TN",
    "sg:province":"Berkshire",
    "sg:tags":[
        "management",
        "facility"
    ],
    "wof:name":"Scion Group Ltd.",
    "wof:placetype":"venue"
},
  "geometry": {"coordinates":[-1.3258719444,51.405872345],"type":"Point"}
}