{
  "type": "Feature",
  "properties": {
    "addr:full":"George House, 30 Dudley Road Manchester Cheshire M16 8DE",
    "addr:housenumber":"30",
    "addr:postcode":"m16 8de",
    "addr:street":"Dudley Road",
    "iso:country":"GB",
    "sg:address":"George House, 30 Dudley Road",
    "sg:city":"Manchester",
    "sg:classifiers":[
        {
            "category":"Professional",
            "subcategory":"Advertising",
            "type":"Services"
        }
    ],
    "sg:postcode":"M16 8DE",
    "sg:province":"Cheshire",
    "sg:tags":[
        "agency"
    ],
    "wof:name":"The Humphries Co",
    "wof:placetype":"venue"
},
  "geometry": {"coordinates":[-2.259593,53.453236],"type":"Point"}
}