{
  "type": "Feature",
  "properties": {
    "addr:full":"3 Manor Row Bradford West Yorkshire BD1 4PB",
    "addr:housenumber":"3",
    "addr:postcode":"bd1 4pb",
    "addr:street":"Manor Row Bradford West",
    "iso:country":"GB",
    "sg:address":"3 Manor Row",
    "sg:city":"Bradford",
    "sg:classifiers":[
        {
            "category":"Real Estate",
            "subcategory":"Real Estate Agent",
            "type":"Services"
        }
    ],
    "sg:phone":"+44 1274 307910",
    "sg:postcode":"BD1 4PB",
    "sg:province":"West Yorkshire",
    "wof:name":"Starkeys Management Services Ltd.",
    "wof:placetype":"venue"
},
  "geometry": {"coordinates":[-1.7537959814,53.7965278625],"type":"Point"}
}