{
  "type": "Feature",
  "properties": {
    "addr:full":"Sawley Bridge Marina, Long Eaton Nottingham Derbyshire NG10 3AE",
    "addr:postcode":"ng10 3ae",
    "iso:country":"GB",
    "sg:address":"Sawley Bridge Marina, Long Eaton",
    "sg:city":"Nottingham",
    "sg:classifiers":[
        {
            "category":"Fast Food",
            "type":"Food & Drink"
        }
    ],
    "sg:postcode":"NG10 3AE",
    "sg:province":"Derbyshire",
    "sg:tags":[
        "away",
        "take"
    ],
    "wof:name":"Riverside (The)",
    "wof:placetype":"venue"
},
  "geometry": {"coordinates":[-1.309611,52.888577],"type":"Point"}
}