{
  "type": "Feature",
  "properties": {
    "iso:country":"GB",
    "sg:address":"25 Donnington Drive, Mudeford",
    "sg:city":"Christchurch",
    "sg:classifiers":[
        {
            "category":"Building & Trades",
            "subcategory":"Plumbing",
            "type":"Services"
        }
    ],
    "sg:postcode":"BH23 4SZ",
    "sg:province":"Dorset",
    "sg:tags":[
        "central",
        "heating"
    ],
    "wof:name":"Gaswarm Heating",
    "wof:placetype":"venue"
},
  "geometry": {"coordinates":[-1.734347,50.737354],"type":"Point"}
}