{
  "type": "Feature",
  "properties": {
    "addr:full":"Ty Gwyn Shop, 1 James Street New Tredegar Caerphilly NP24 6EW",
    "addr:housenumber":"1",
    "addr:postcode":"np24 6ew",
    "addr:street":"James Street",
    "iso:country":"GB",
    "sg:address":"Ty Gwyn Shop, 1 James Street",
    "sg:city":"New Tredegar",
    "sg:classifiers":[
        {
            "category":"Food & Beverages",
            "subcategory":"Bakery",
            "type":"Retail Goods"
        }
    ],
    "sg:phone":"+44 1443 832342",
    "sg:postcode":"NP24 6EW",
    "sg:province":"Caerphilly",
    "sg:tags":[
        "baker"
    ],
    "wof:name":"Village Bakery",
    "wof:placetype":"venue"
},
  "geometry": {"coordinates":[-3.2377490997,51.7186431885],"type":"Point"}
}