{
  "type": "Feature",
  "properties": {
    "addr:full":"304 St Marys Lane Upminster Essex RM14 3HL",
    "addr:housenumber":"304",
    "addr:postcode":"rm14 3hl",
    "addr:street":"St Marys Lane",
    "iso:country":"GB",
    "sg:address":"304 St Marys Lane",
    "sg:city":"Upminster",
    "sg:classifiers":[
        {
            "category":"Autos & Motor Vehicles",
            "subcategory":"Auto Supplies",
            "type":"Retail Goods"
        }
    ],
    "sg:phone":"+44 1708 223316",
    "sg:postcode":"RM14 3HL",
    "sg:province":"Essex",
    "sg:tags":[
        "towing",
        "eqpt",
        "trailer"
    ],
    "wof:name":"Towrite",
    "wof:placetype":"venue"
},
  "geometry": {"coordinates":[0.259301,51.557384],"type":"Point"}
}