{
  "type": "Feature",
  "properties": {
    "addr:full":"Unit 2 Linkway Retail Pk Cannock Staffordshire WS11 1TD",
    "addr:housenumber":"unit 2",
    "addr:postcode":"ws11 1td",
    "addr:street":"Linkway Retail Pk",
    "iso:country":"GB",
    "sg:address":"Unit 2 Linkway Retail Pk",
    "sg:city":"Cannock",
    "sg:classifiers":[
        {
            "category":"Shopping",
            "subcategory":"Department Store",
            "type":"Retail Goods"
        }
    ],
    "sg:postcode":"WS11 1TD",
    "sg:province":"Staffordshire",
    "wof:name":"Brewbaker (Midland) Ltd",
    "wof:placetype":"venue"
},
  "geometry": {"coordinates":[-2.0488839149,52.6791191101],"type":"Point"}
}