{
  "type": "Feature",
  "properties": {
    "addr:full":"48 Grasmere Rd Whitstable Kent CT5 3NA",
    "addr:housenumber":"48",
    "addr:postcode":"ct5 3na",
    "addr:street":"Grasmere Rd Whitstable",
    "iso:country":"GB",
    "sg:address":"48 Grasmere Rd",
    "sg:city":"Whitstable",
    "sg:classifiers":[
        {
            "category":"Building & Trades",
            "subcategory":"Plumbing",
            "type":"Services"
        }
    ],
    "sg:phone":"+44 1227 794729",
    "sg:postcode":"CT5 3NA",
    "sg:province":"Kent",
    "sg:tags":[
        "central",
        "heating"
    ],
    "wof:name":"Aldie Ltd",
    "wof:placetype":"venue"
},
  "geometry": {"coordinates":[1.0567430258,51.3515739441],"type":"Point"}
}