{
  "type": "Feature",
  "properties": {
    "iso:country":"GB",
    "sg:address":"3 The Villas",
    "sg:city":"Stanley",
    "sg:classifiers":[
        {
            "category":"Shopping",
            "subcategory":"Department Store",
            "type":"Retail Goods"
        },
        {
            "category":"Shopping",
            "type":"Retail Goods"
        }
    ],
    "sg:postcode":"DH9 8PA",
    "sg:province":"Durham",
    "sg:tags":[
        "household"
    ],
    "wof:name":"Harelaw Stores",
    "wof:placetype":"venue"
},
  "geometry": {"coordinates":[-1.750943,54.854351],"type":"Point"}
}