{
  "type": "Feature",
  "properties": {
    "addr:full":"Dove La, Long Eaton Nottingham Derbyshire NG10 4LP",
    "addr:postcode":"ng10 4lp",
    "addr:street":"Dove La Long",
    "iso:country":"GB",
    "sg:address":"Dove La, Long Eaton",
    "sg:city":"Nottingham",
    "sg:classifiers":[
        {
            "category":"Social Services",
            "subcategory":"Child Care",
            "type":"Services"
        }
    ],
    "sg:postcode":"NG10 4LP",
    "sg:province":"Derbyshire",
    "sg:tags":[
        "children's",
        "home"
    ],
    "wof:name":"Derbyshire County Council",
    "wof:placetype":"venue"
},
  "geometry": {"coordinates":[-1.2805219889,52.901096344],"type":"Point"}
}