{
  "type": "Feature",
  "properties": {
    "addr:full":"13 Prospect Place Watlington Buckinghamshire OX9 5AJ",
    "addr:housenumber":"13",
    "addr:postcode":"ox9 5aj",
    "addr:street":"Prospect Place",
    "iso:country":"GB",
    "sg:address":"13 Prospect Place",
    "sg:city":"Watlington",
    "sg:classifiers":[
        {
            "category":"Recreation",
            "type":"Entertainment"
        }
    ],
    "sg:phone":"+44 1491 614770",
    "sg:postcode":"OX9 5AJ",
    "sg:province":"Buckinghamshire",
    "sg:tags":[
        "corporate",
        "leisure"
    ],
    "wof:name":"Eventuality Corporate Events",
    "wof:placetype":"venue"
},
  "geometry": {"coordinates":[-1.005679965,51.6440811157],"type":"Point"}
}