{
  "type": "Feature",
  "properties": {
    "iso:country":"GB",
    "sg:address":"14 Birch Clo, Grassmoor",
    "sg:city":"Chesterfield",
    "sg:classifiers":[
        {
            "category":"Home & Garden",
            "subcategory":"Carpets & Floor Coverings",
            "type":"Retail Goods"
        }
    ],
    "sg:postcode":"S42 5YD",
    "sg:province":"Derbyshire",
    "sg:tags":[
        "cleaner",
        "upholstery"
    ],
    "wof:name":"Anne's Carpet & Upholstery Cleaning",
    "wof:placetype":"venue"
},
  "geometry": {"coordinates":[-1.3900330067,53.1987380981],"type":"Point"}
}