{
  "type": "Feature",
  "properties": {
    "addr:full":"23 Fleet Street London Greater London EC4Y 1AA",
    "addr:housenumber":"23",
    "addr:postcode":"ec4y 1aa",
    "addr:street":"Fleet Street",
    "iso:country":"GB",
    "sg:address":"23 Fleet Street",
    "sg:city":"London",
    "sg:classifiers":[
        {
            "category":"Cafe",
            "type":"Food & Drink"
        }
    ],
    "sg:postcode":"EC4Y 1AA",
    "sg:province":"Greater London",
    "sg:tags":[
        "tea",
        "room"
    ],
    "wof:name":"Costa Coffee",
    "wof:placetype":"venue"
},
  "geometry": {"coordinates":[-0.110587,51.51376],"type":"Point"}
}