{
  "type": "Feature",
  "properties": {
    "iso:country":"GB",
    "sg:address":"26 Quebec Street, Langley Park",
    "sg:city":"Durham",
    "sg:classifiers":[
        {
            "category":"Shopping",
            "subcategory":"Thrift Store",
            "type":"Retail Goods"
        }
    ],
    "sg:phone":"+44 191 373 2510",
    "sg:postcode":"DH7 9XA",
    "sg:province":"Durham",
    "sg:tags":[
        "shop",
        "charity"
    ],
    "wof:name":"St.Cuthberts Hospice",
    "wof:placetype":"venue"
},
  "geometry": {"coordinates":[-1.6720089912,54.7993240356],"type":"Point"}
}