{
  "type": "Feature",
  "properties": {
    "iso:country":"GB",
    "sg:address":"Old Pump House, Finkle Street, Wortley",
    "sg:city":"Sheffield",
    "sg:classifiers":[
        {
            "category":"Building & Trades",
            "subcategory":"Construction",
            "type":"Services"
        }
    ],
    "sg:postcode":"S35 7DH",
    "sg:province":"South Yorkshire",
    "sg:tags":[
        "builder"
    ],
    "wof:name":"T Barton & Co",
    "wof:placetype":"venue"
},
  "geometry": {"coordinates":[-1.55093503,53.489238739],"type":"Point"}
}