{
  "type": "Feature",
  "properties": {
    "addr:full":"12 Chapel Street, Eccles Manchester Greater Manchester M30 0RQ",
    "addr:housenumber":"12",
    "addr:postcode":"m30 0rq",
    "addr:street":"Chapel Street",
    "iso:country":"GB",
    "sg:address":"12 Chapel Street, Eccles",
    "sg:city":"Manchester",
    "sg:classifiers":[
        {
            "category":"Bars & Pubs",
            "type":"Food & Drink"
        }
    ],
    "sg:phone":"+44 161 789 4023",
    "sg:postcode":"M30 0RQ",
    "sg:province":"Greater Manchester",
    "sg:tags":[
        "pubs",
        "inn"
    ],
    "wof:name":"The Red Lion",
    "wof:placetype":"venue"
},
  "geometry": {"coordinates":[-2.3586909771,53.4818916321],"type":"Point"}
}