{
  "type": "Feature",
  "properties": {
    "addr:full":"1st Floor Sterling Ho, 67 Lawrence Rd Seven Sisters Greater London N15 4EE",
    "addr:housenumber":"67",
    "addr:postcode":"n15 4ee",
    "addr:street":"Lawrence Rd",
    "iso:country":"GB",
    "sg:address":"1st Floor Sterling Ho, 67 Lawrence Rd",
    "sg:city":"Seven Sisters",
    "sg:classifiers":[
        {
            "category":"Shopping",
            "subcategory":"Clothing, Apparel, & Fashions",
            "type":"Retail Goods"
        }
    ],
    "sg:phone":"+44 20 8809 1500",
    "sg:postcode":"N15 4EE",
    "sg:province":"Greater London",
    "sg:tags":[
        "clothing",
        "fabric"
    ],
    "wof:name":"Rimagold Ltd",
    "wof:placetype":"venue"
},
  "geometry": {"coordinates":[-0.07302,51.585442],"type":"Point"}
}