{
  "type": "Feature",
  "properties": {
    "addr:full":"8-9 Brunel Way, Stroudwater Business Park Stonehouse Gloucestershire GL10 3SX",
    "addr:housenumber":"8-9;business",
    "addr:postcode":"gl10 3sx",
    "addr:street":"Brunel Way;Park",
    "iso:country":"GB",
    "sg:address":"8-9 Brunel Way, Stroudwater Business Park",
    "sg:city":"Stonehouse",
    "sg:classifiers":[
        {
            "category":"Professional",
            "subcategory":"Engineering",
            "type":"Services"
        }
    ],
    "sg:phone":"+44 1453 827771",
    "sg:postcode":"GL10 3SX",
    "sg:province":"Gloucestershire",
    "sg:tags":[
        "precision",
        "engineer"
    ],
    "wof:name":"The Wire Erosion Co. Ltd.",
    "wof:placetype":"venue"
},
  "geometry": {"coordinates":[-2.29637,51.753071],"type":"Point"}
}