{
  "type": "Feature",
  "properties": {
    "iso:country":"GB",
    "sg:address":"Unit 10 Market Centre, Hayes Rd",
    "sg:city":"Southall",
    "sg:classifiers":[
        {
            "category":"Shopping",
            "subcategory":"Department Store",
            "type":"Retail Goods"
        }
    ],
    "sg:postcode":"UB2 5XJ",
    "sg:province":"Greater London",
    "wof:name":"W H Sports",
    "wof:placetype":"venue"
},
  "geometry": {"coordinates":[-0.40311,51.495941],"type":"Point"}
}