{
  "type": "Feature",
  "properties": {
    "iso:country":"GB",
    "sg:address":"Care Of Rollers, Saxon Street, Bletchley",
    "sg:city":"Milton Keynes",
    "sg:classifiers":[
        {
            "category":"Sports & Exercise",
            "subcategory":"Sports Center",
            "type":"Entertainment"
        }
    ],
    "sg:postcode":"MK1 1SR",
    "sg:province":"Buckinghamshire",
    "sg:tags":[
        "shop",
        "good"
    ],
    "wof:name":"The Skate Locker Ltd.",
    "wof:placetype":"venue"
},
  "geometry": {"coordinates":[-0.7277489901,52.0058555603],"type":"Point"}
}