{
  "type": "Feature",
  "properties": {
    "iso:country":"GB",
    "sg:address":"Upton Gro Stables, Upton",
    "sg:city":"Tetbury",
    "sg:classifiers":[
        {
            "category":"Farming",
            "subcategory":"Nursery",
            "type":"Manufacturing & Wholesale Goods"
        }
    ],
    "sg:postcode":"GL8 8LP",
    "sg:province":"Gloucestershire",
    "sg:tags":[
        "creche"
    ],
    "wof:name":"Oakley Court Nursery",
    "wof:placetype":"venue"
},
  "geometry": {"coordinates":[-2.1609759331,51.6378593445],"type":"Point"}
}