{
  "type": "Feature",
  "properties": {
    "addr:full":"28 High Street Laurencekirk Aberdeenshire AB30 1AB",
    "addr:housenumber":"28",
    "addr:postcode":"ab30 1ab",
    "addr:street":"High Street",
    "iso:country":"GB",
    "sg:address":"28 High Street",
    "sg:city":"Laurencekirk",
    "sg:classifiers":[
        {
            "category":"Food & Beverages",
            "subcategory":"Bakery",
            "type":"Retail Goods"
        }
    ],
    "sg:phone":"+44 1561 377344",
    "sg:postcode":"AB30 1AB",
    "sg:province":"Aberdeenshire",
    "sg:tags":[
        "baker"
    ],
    "wof:name":"Robertson of Stonehaven",
    "wof:placetype":"venue"
},
  "geometry": {"coordinates":[-2.464822,56.833961],"type":"Point"}
}