{
  "type": "Feature",
  "properties": {
    "iso:country":"GB",
    "sg:address":"Paignton Police Station, Southfield Road",
    "sg:city":"Paignton",
    "sg:classifiers":[
        {
            "category":"Professional",
            "subcategory":"Lawyer & Legal Services",
            "type":"Services"
        }
    ],
    "sg:phone":"+44 1803 665989",
    "sg:postcode":"TQ3 2SP",
    "sg:province":"Devon",
    "sg:tags":[
        "advice",
        "counselling"
    ],
    "wof:name":"Victim Support Torbay",
    "wof:placetype":"venue"
},
  "geometry": {"coordinates":[-3.567614,50.438568],"type":"Point"}
}