{
  "type": "Feature",
  "properties": {
    "addr:full":"Unit 303, 203 - 213 Mare Street London Greater London E8 3QE",
    "addr:housenumber":"303 203 213",
    "addr:postcode":"e8 3qe",
    "addr:street":"Mare Street",
    "iso:country":"GB",
    "sg:address":"Unit 303, 203 - 213 Mare Street",
    "sg:city":"London",
    "sg:classifiers":[
        {
            "category":"Communications",
            "subcategory":"News Services",
            "type":"Services"
        }
    ],
    "sg:phone":"+44 7850 895603",
    "sg:postcode":"E8 3QE",
    "sg:province":"Greater London",
    "sg:tags":[
        "illustrator"
    ],
    "wof:name":"Mark Preston Photography",
    "wof:placetype":"venue"
},
  "geometry": {"coordinates":[-0.05482,51.547241],"type":"Point"}
}