{
  "type": "Feature",
  "properties": {
    "addr:full":"2 Colin Park Rd Colindale Greater London NW9 6HS",
    "addr:housenumber":"2",
    "addr:postcode":"nw9 6hs",
    "addr:street":"Colin Park Rd",
    "iso:country":"GB",
    "sg:address":"2 Colin Park Rd",
    "sg:city":"Colindale",
    "sg:classifiers":[
        {
            "category":"Health Services",
            "subcategory":"Health Practitioner",
            "type":"Services"
        }
    ],
    "sg:phone":"+44 20 8200 9195",
    "sg:postcode":"NW9 6HS",
    "sg:province":"Greater London",
    "sg:tags":[
        "osteopath"
    ],
    "wof:name":"The Colindale Osteopathic Practice",
    "wof:placetype":"venue"
},
  "geometry": {"coordinates":[-0.2507050037,51.5889930725],"type":"Point"}
}