{
  "type": "Feature",
  "properties": {
    "iso:country":"GB",
    "sg:address":"1 Coombe Ave",
    "sg:city":"Croydon",
    "sg:classifiers":[
        {
            "category":"Professional",
            "subcategory":"Art Services",
            "type":"Services"
        }
    ],
    "sg:postcode":"CR0 5SD",
    "sg:province":"Surrey",
    "sg:tags":[
        "photographer"
    ],
    "wof:name":"Andrews,Jack,",
    "wof:placetype":"venue"
},
  "geometry": {"coordinates":[-0.085393,51.365116],"type":"Point"}
}