{
  "type": "Feature",
  "properties": {
    "iso:country":"GB",
    "sg:address":"47 Glanrafon Estate, Bontnewydd",
    "sg:city":"Caernarfon",
    "sg:classifiers":[
        {
            "category":"Building & Trades",
            "subcategory":"Construction",
            "type":"Services"
        }
    ],
    "sg:postcode":"LL55 2UW",
    "sg:province":"Gwynedd",
    "sg:tags":[
        "glazier",
        "decorator",
        "painter"
    ],
    "wof:name":"William Selwyn Williams",
    "wof:placetype":"venue"
},
  "geometry": {"coordinates":[-4.271972,53.11554],"type":"Point"}
}