{
  "type": "Feature",
  "properties": {
    "addr:full":"105a Brook Street Stourbridge Staffordshire DY8 3UX",
    "addr:housenumber":"105a",
    "addr:postcode":"dy8 3ux",
    "addr:street":"Brook Street",
    "iso:country":"GB",
    "sg:address":"105a Brook Street",
    "sg:city":"Stourbridge",
    "sg:classifiers":[
        {
            "category":"Wholesale",
            "subcategory":"Scrap",
            "type":"Manufacturing & Wholesale Goods"
        }
    ],
    "sg:postcode":"DY8 3UX",
    "sg:province":"Staffordshire",
    "sg:tags":[
        "waste",
        "metal"
    ],
    "wof:name":"A R Tanner (Metals) Ltd.",
    "wof:placetype":"venue"
},
  "geometry": {"coordinates":[-2.160452,52.454662],"type":"Point"}
}