{
  "type": "Feature",
  "properties": {
    "iso:country":"GB",
    "sg:address":"138 Westbrooke Rd",
    "sg:city":"Welling",
    "sg:classifiers":[
        {
            "category":"Social Services",
            "subcategory":"Job Training",
            "type":"Services"
        }
    ],
    "sg:postcode":"DA16 1QE",
    "sg:province":"Kent",
    "sg:tags":[
        "draughtsman",
        "drawing"
    ],
    "wof:name":"Hemhurst Technical Services Ltd",
    "wof:placetype":"venue"
},
  "geometry": {"coordinates":[0.113733,51.463802],"type":"Point"}
}