{
  "type": "Feature",
  "properties": {
    "addr:full":"27 Methuen Road Bournemouth Dorset BH8 8NB",
    "addr:housenumber":"27",
    "addr:postcode":"bh8 8nb",
    "addr:street":"Methuen Road",
    "iso:country":"GB",
    "sg:address":"27 Methuen Road",
    "sg:city":"Bournemouth",
    "sg:classifiers":[
        {
            "category":"Shopping",
            "subcategory":"Computers & Home Electronics",
            "type":"Retail Goods"
        }
    ],
    "sg:phone":"+44 1202 301486",
    "sg:postcode":"BH8 8NB",
    "sg:province":"Dorset",
    "sg:tags":[
        "consumables"
    ],
    "wof:name":"Laser Toner & Ink Jet Supplies",
    "wof:placetype":"venue"
},
  "geometry": {"coordinates":[-1.8601900339,50.7305335999],"type":"Point"}
}