{
  "type": "Feature",
  "properties": {
    "addr:full":"York House, York Place Knaresborough North Yorkshire HG5 0AD",
    "addr:postcode":"north;hg5 0ad",
    "addr:street":"York Place",
    "iso:country":"GB",
    "sg:address":"York House, York Place",
    "sg:city":"Knaresborough",
    "sg:classifiers":[
        {
            "category":"Real Estate",
            "subcategory":"Architect",
            "type":"Services"
        }
    ],
    "sg:phone":"+44 1423 867461",
    "sg:postcode":"HG5 0AD",
    "sg:province":"North Yorkshire",
    "wof:name":"Ferguson Sayell Partnership",
    "wof:placetype":"venue"
},
  "geometry": {"coordinates":[-1.462242,54.006397],"type":"Point"}
}