{
  "type": "Feature",
  "properties": {
    "addr:full":"103 High Street King's Lynn Norfolk PE30 1BW",
    "addr:housenumber":"103",
    "addr:postcode":"pe30 1bw",
    "addr:street":"High Street",
    "iso:country":"GB",
    "sg:address":"103 High Street",
    "sg:city":"King's Lynn",
    "sg:classifiers":[
        {
            "category":"Shopping",
            "subcategory":"Clothing, Apparel, & Fashions",
            "type":"Retail Goods"
        }
    ],
    "sg:phone":"+44 1553 771668",
    "sg:postcode":"PE30 1BW",
    "sg:province":"Norfolk",
    "sg:tags":[
        "menswear"
    ],
    "wof:name":"Gio's Clothing Co",
    "wof:placetype":"venue"
},
  "geometry": {"coordinates":[0.395422,52.753387],"type":"Point"}
}