{
  "type": "Feature",
  "properties": {
    "iso:country":"GB",
    "sg:address":"21a The Broadwalk, Pinner Road, North Harrow",
    "sg:city":"Harrow",
    "sg:classifiers":[
        {
            "category":"Education",
            "subcategory":"Special Training",
            "type":"Public Place"
        }
    ],
    "sg:phone":"+44 20 8424 0746",
    "sg:postcode":"HA2 6ED",
    "sg:province":"Greater London",
    "sg:tags":[
        "school",
        "language"
    ],
    "wof:name":"T C S School of English",
    "wof:placetype":"venue"
},
  "geometry": {"coordinates":[-0.36245,51.586842],"type":"Point"}
}