{
  "type": "Feature",
  "properties": {
    "addr:full":"1792 Pershore Road, Kings Norton Birmingham West Midlands B30 3AU",
    "addr:housenumber":"1792",
    "addr:postcode":"b30 3au",
    "addr:street":"Pershore Road",
    "iso:country":"GB",
    "sg:address":"1792 Pershore Road, Kings Norton",
    "sg:city":"Birmingham",
    "sg:classifiers":[
        {
            "category":"Cafe",
            "type":"Food & Drink"
        }
    ],
    "sg:phone":"+44 121 459 3206",
    "sg:postcode":"B30 3AU",
    "sg:province":"West Midlands",
    "sg:tags":[
        "tea",
        "snack",
        "bar",
        "room"
    ],
    "wof:name":"Golden Coin Cafe",
    "wof:placetype":"venue"
},
  "geometry": {"coordinates":[-1.925534,52.417732],"type":"Point"}
}