{
  "type": "Feature",
  "properties": {
    "iso:country":"GB",
    "sg:address":"232 Ashburton Ave",
    "sg:city":"Ilford",
    "sg:classifiers":[
        {
            "category":"Retail",
            "subcategory":"Repair Shop",
            "type":"Services"
        }
    ],
    "sg:postcode":"IG3 9EJ",
    "sg:province":"Essex",
    "sg:tags":[
        "maintenance"
    ],
    "wof:name":"Nicholls,Raymond,",
    "wof:placetype":"venue"
},
  "geometry": {"coordinates":[0.106046,51.552811],"type":"Point"}
}