{
  "type": "Feature",
  "properties": {
    "addr:full":"23 Fore Street, Tregony Truro Cornwall TR2 5RN",
    "addr:housenumber":"23",
    "addr:postcode":"tr2 5rn",
    "addr:street":"Fore Street",
    "iso:country":"GB",
    "sg:address":"23 Fore Street, Tregony",
    "sg:city":"Truro",
    "sg:classifiers":[
        {
            "category":"Health Services",
            "subcategory":"Nursing And Care Facility",
            "type":"Services"
        }
    ],
    "sg:phone":"+44 1872 530665",
    "sg:postcode":"TR2 5RN",
    "sg:province":"Cornwall",
    "sg:tags":[
        "home"
    ],
    "wof:name":"Penlee Nursing & Residential Home",
    "wof:placetype":"venue"
},
  "geometry": {"coordinates":[-4.9115829468,50.2684249878],"type":"Point"}
}