{
  "type": "Feature",
  "properties": {
    "iso:country":"GB",
    "sg:address":"17 Main Street",
    "sg:city":"Glasgow",
    "sg:classifiers":[
        {
            "category":"Food & Beverages",
            "subcategory":"Fruits & Vegetables",
            "type":"Retail Goods"
        }
    ],
    "sg:postcode":"G71 8RD",
    "sg:province":"Glasgow City",
    "sg:tags":[
        "greengrocer"
    ],
    "wof:name":"H & S Darroch",
    "wof:placetype":"venue"
},
  "geometry": {"coordinates":[-4.0666570663,55.8024597168],"type":"Point"}
}