{
  "type": "Feature",
  "properties": {
    "iso:country":"GB",
    "sg:address":"Fitzherbert Road, Farlington",
    "sg:city":"Portsmouth",
    "sg:classifiers":[
        {
            "category":"Manufacturing",
            "subcategory":"Building Materials",
            "type":"Manufacturing & Wholesale Goods"
        }
    ],
    "sg:phone":"+44 23 9237 3121",
    "sg:postcode":"PO6 1RJ",
    "sg:province":"Hampshire",
    "sg:tags":[
        "merchant",
        "builder"
    ],
    "wof:name":"Builder Centre",
    "wof:placetype":"venue"
},
  "geometry": {"coordinates":[-1.030622,50.843586],"type":"Point"}
}