{
  "type": "Feature",
  "properties": {
    "addr:full":"Unit 1 Bridgnorth Shropshire WV16 4QR",
    "addr:housenumber":"unit 1",
    "addr:postcode":"wv16 4qr",
    "iso:country":"GB",
    "sg:address":"Unit 1",
    "sg:city":"Bridgnorth",
    "sg:classifiers":[
        {
            "category":"Insurance",
            "subcategory":"Insurance Agent",
            "type":"Services"
        }
    ],
    "sg:phone":"+44 1746 763198",
    "sg:postcode":"WV16 4QR",
    "sg:province":"Shropshire",
    "wof:name":"National Farmers Union",
    "wof:placetype":"venue"
},
  "geometry": {"coordinates":[-2.443159,52.539619],"type":"Point"}
}