{
  "type": "Feature",
  "properties": {
    "addr:full":"89 Waterloo Road Blyth Northumberland NE24 1BU",
    "addr:housenumber":"89",
    "addr:postcode":"ne24 1bu",
    "addr:street":"Waterloo Road;Northumberland",
    "iso:country":"GB",
    "sg:address":"89 Waterloo Road",
    "sg:city":"Blyth",
    "sg:classifiers":[
        {
            "category":"Fast Food",
            "type":"Food & Drink"
        },
        {
            "category":"Restaurant",
            "type":"Food & Drink"
        }
    ],
    "sg:phone":"+44 1670 365567",
    "sg:postcode":"NE24 1BU",
    "sg:province":"Northumberland",
    "sg:tags":[
        "greek",
        "away",
        "-",
        "take"
    ],
    "wof:name":"THE GREEK EMPEROR",
    "wof:placetype":"venue"
},
  "geometry": {"coordinates":[-1.51224,55.126278],"type":"Point"}
}