{
  "type": "Feature",
  "properties": {
    "iso:country":"GB",
    "sg:address":"The Boulevard",
    "sg:city":"Welwyn Garden City",
    "sg:classifiers":[
        {
            "category":"Professional",
            "subcategory":"Computer Services",
            "type":"Services"
        }
    ],
    "sg:phone":"+44 1707 362200",
    "sg:postcode":"AL7 1LH",
    "sg:province":"Hertfordshire",
    "sg:tags":[
        "system",
        "software"
    ],
    "wof:name":"Sligos Payment Services Plc",
    "wof:placetype":"venue"
},
  "geometry": {"coordinates":[-0.190799,51.808434],"type":"Point"}
}