{
  "type": "Feature",
  "properties": {
    "addr:full":"18 Amhurst Wk London Greater London SE28 8RJ",
    "addr:housenumber":"18",
    "addr:postcode":"se28 8rj",
    "addr:street":"Amhurst Wk",
    "iso:country":"GB",
    "sg:address":"18 Amhurst Wk",
    "sg:city":"London",
    "sg:classifiers":[
        {
            "category":"Professional",
            "subcategory":"Management & Consulting",
            "type":"Services"
        }
    ],
    "sg:phone":"+44 20 8310 0430",
    "sg:postcode":"SE28 8RJ",
    "sg:province":"Greater London",
    "sg:tags":[
        "consultant",
        "business"
    ],
    "wof:name":"The Cooter-Ofori Partnership",
    "wof:placetype":"venue"
},
  "geometry": {"coordinates":[0.1067200005,51.5008621216],"type":"Point"}
}