{
  "type": "Feature",
  "properties": {
    "addr:full":"Brick Knowll Park, Ashley Road St Albans Hertfordshire AL1 5UG",
    "addr:postcode":"al1 5ug",
    "addr:street":"Ashley Road",
    "iso:country":"GB",
    "sg:address":"Brick Knowll Park, Ashley Road",
    "sg:city":"St Albans",
    "sg:classifiers":[
        {
            "category":"Autos & Motor Vehicles",
            "subcategory":"Automobile Sales",
            "type":"Retail Goods"
        }
    ],
    "sg:phone":"+44 1727 811144",
    "sg:postcode":"AL1 5UG",
    "sg:province":"Hertfordshire",
    "sg:tags":[
        "commercial"
    ],
    "wof:name":"C D Bramall St. Albans",
    "wof:placetype":"venue"
},
  "geometry": {"coordinates":[-0.302229,51.749161],"type":"Point"}
}