{
  "type": "Feature",
  "properties": {
    "addr:full":"Upper Richmond Road Post Office, 48 Upper Richmond London Greater London SW14 8DD",
    "addr:housenumber":"48",
    "addr:postcode":"sw14 8dd",
    "addr:street":"Upper Richmond Road;Upper Richmond",
    "iso:country":"GB",
    "sg:address":"Upper Richmond Road Post Office, 48 Upper Richmond",
    "sg:city":"London",
    "sg:classifiers":[
        {
            "category":"Shopping",
            "subcategory":"Used Merchandise",
            "type":"Retail Goods"
        }
    ],
    "sg:phone":"+44 20 8876 8700",
    "sg:postcode":"SW14 8DD",
    "sg:province":"Greater London",
    "sg:tags":[
        "shop",
        "second-hand"
    ],
    "wof:name":"The Post Office",
    "wof:placetype":"venue"
},
  "geometry": {"coordinates":[-0.2548840046,51.4651985168],"type":"Point"}
}