{
  "type": "Feature",
  "properties": {
    "iso:country":"GB",
    "sg:address":"3 Parc Teifi",
    "sg:city":"Cardigan",
    "sg:classifiers":[
        {
            "category":"Shopping",
            "subcategory":"Pets & Pet Supplies",
            "type":"Retail Goods"
        }
    ],
    "sg:phone":"+44 1239 614648",
    "sg:postcode":"SA43 1EW",
    "sg:province":"Ceredigion",
    "sg:tags":[
        "equestrian"
    ],
    "wof:name":"R G & M T Reynolds",
    "wof:placetype":"venue"
},
  "geometry": {"coordinates":[-4.648839,52.08498],"type":"Point"}
}