{
  "type": "Feature",
  "properties": {
    "addr:full":"174 Bowes Rd Friern Barnet Greater London N11 2JG",
    "addr:housenumber":"174",
    "addr:postcode":"n11 2jg",
    "addr:street":"Bowes Rd",
    "iso:country":"GB",
    "sg:address":"174 Bowes Rd",
    "sg:city":"Friern Barnet",
    "sg:classifiers":[
        {
            "category":"Place Of Worship",
            "type":"Public Place"
        }
    ],
    "sg:phone":"+44 20 8888 8765",
    "sg:postcode":"N11 2JG",
    "sg:province":"Greater London",
    "wof:name":"Jehovah's Witnesses",
    "wof:placetype":"venue"
},
  "geometry": {"coordinates":[-0.1272239983,51.614780426],"type":"Point"}
}