{
  "type": "Feature",
  "properties": {
    "iso:country":"GB",
    "sg:address":"Unit 2, Swaffield Industrial Estate, Hysopp Close",
    "sg:city":"Cannock",
    "sg:classifiers":[
        {
            "category":"Personal",
            "type":"Services"
        }
    ],
    "sg:phone":"+44 1543 573539",
    "sg:postcode":"WS11 2GA",
    "sg:province":"Staffordshire",
    "sg:tags":[
        "dressmaker"
    ],
    "wof:name":"Tyne Dancer",
    "wof:placetype":"venue"
},
  "geometry": {"coordinates":[-2.033145,52.690952],"type":"Point"}
}