{
  "type": "Feature",
  "properties": {
    "addr:full":"1st Floor Of Eyres Holywell Street Chesterfield Derbyshire S41 7SA",
    "addr:postcode":"s41 7sa",
    "addr:street":"Holywell Street",
    "iso:country":"GB",
    "sg:address":"1st Floor Of Eyres Holywell Street",
    "sg:city":"Chesterfield",
    "sg:classifiers":[
        {
            "category":"Professional",
            "subcategory":"Management & Consulting",
            "type":"Services"
        }
    ],
    "sg:phone":"+44 1246 203352",
    "sg:postcode":"S41 7SA",
    "sg:province":"Derbyshire",
    "sg:tags":[
        "consultant",
        "specialist"
    ],
    "wof:name":"Beauty Therapy by Debbie McInley",
    "wof:placetype":"venue"
},
  "geometry": {"coordinates":[-1.426149,53.238144],"type":"Point"}
}