{
  "type": "Feature",
  "properties": {
    "addr:full":"High Road, Needham Harleston Norfolk IP20 9LB",
    "addr:postcode":"ip20 9lb",
    "addr:street":"High Road;Harleston",
    "iso:country":"GB",
    "sg:address":"High Road, Needham",
    "sg:city":"Harleston",
    "sg:classifiers":[
        {
            "category":"Manufacturing",
            "subcategory":"Wood Products",
            "type":"Manufacturing & Wholesale Goods"
        }
    ],
    "sg:phone":"+44 1379 852873",
    "sg:postcode":"IP20 9LB",
    "sg:province":"Norfolk",
    "sg:tags":[
        "packaging",
        "crate",
        "pallets"
    ],
    "wof:name":"H L C (Wood Products) Ltd.",
    "wof:placetype":"venue"
},
  "geometry": {"coordinates":[1.2984149456,52.4014091492],"type":"Point"}
}