{
  "type": "Feature",
  "properties": {
    "addr:full":"1 Church Street, Bishop Middleham Ferryhill Durham DL17 9AF",
    "addr:housenumber":"1",
    "addr:postcode":"dl17 9af",
    "addr:street":"Church Street",
    "iso:country":"GB",
    "sg:address":"1 Church Street, Bishop Middleham",
    "sg:city":"Ferryhill",
    "sg:classifiers":[
        {
            "category":"Bars & Pubs",
            "type":"Food & Drink"
        }
    ],
    "sg:postcode":"DL17 9AF",
    "sg:province":"Durham",
    "sg:tags":[
        "pubs",
        "inn"
    ],
    "wof:name":"Dun Cow",
    "wof:placetype":"venue"
},
  "geometry": {"coordinates":[-1.4918789864,54.6770706177],"type":"Point"}
}