{
  "type": "Feature",
  "properties": {
    "addr:full":"82 Mornington Road Bolton Lancashire BL1 4EF",
    "addr:housenumber":"82",
    "addr:postcode":"bl1 4ef",
    "addr:street":"Mornington Road",
    "iso:country":"GB",
    "sg:address":"82 Mornington Road",
    "sg:city":"Bolton",
    "sg:classifiers":[
        {
            "category":"Shopping",
            "subcategory":"Florist",
            "type":"Retail Goods"
        }
    ],
    "sg:phone":"+44 1204 842352",
    "sg:postcode":"BL1 4EF",
    "sg:province":"Lancashire",
    "wof:name":"Sandra's Florist",
    "wof:placetype":"venue"
},
  "geometry": {"coordinates":[-2.4550259113,53.5824623108],"type":"Point"}
}