{
  "type": "Feature",
  "properties": {
    "iso:country":"GB",
    "sg:address":"17 The Cross",
    "sg:city":"Lymm",
    "sg:classifiers":[
        {
            "category":"Shopping",
            "subcategory":"Clothing, Apparel, & Fashions",
            "type":"Retail Goods"
        }
    ],
    "sg:phone":"+44 1925 756683",
    "sg:postcode":"WA13 0HR",
    "sg:province":"Cheshire",
    "sg:tags":[
        "shop"
    ],
    "wof:name":"Bee Chic",
    "wof:placetype":"venue"
},
  "geometry": {"coordinates":[-2.478315115,53.3809432983],"type":"Point"}
}