{
  "type": "Feature",
  "properties": {
    "addr:full":"71 Market St Holyhead Isle of Anglesey LL65 1UW",
    "addr:housenumber":"71",
    "addr:postcode":"ll65 1uw",
    "addr:street":"Market St",
    "iso:country":"GB",
    "sg:address":"71 Market St",
    "sg:city":"Holyhead",
    "sg:classifiers":[
        {
            "category":"Shopping",
            "type":"Retail Goods"
        }
    ],
    "sg:phone":"+44 1407 765849",
    "sg:postcode":"LL65 1UW",
    "sg:province":"Isle of Anglesey",
    "sg:tags":[
        "household",
        "store"
    ],
    "wof:name":"R.K.A Ltd",
    "wof:placetype":"venue"
},
  "geometry": {"coordinates":[-4.633669,53.309849],"type":"Point"}
}