{
  "type": "Feature",
  "properties": {
    "iso:country":"GB",
    "sg:address":"Rear Of 15 Queens Road",
    "sg:city":"Southend-on-sea",
    "sg:classifiers":[
        {
            "category":"Professional",
            "subcategory":"Printing & Photocopies",
            "type":"Services"
        }
    ],
    "sg:phone":"+44 1702 331454",
    "sg:postcode":"SS1 1LT",
    "sg:province":"Essex",
    "sg:tags":[
        "printer"
    ],
    "wof:name":"Derek M Holliday",
    "wof:placetype":"venue"
},
  "geometry": {"coordinates":[0.70516,51.540386],"type":"Point"}
}