{
  "type": "Feature",
  "properties": {
    "addr:full":"Main St York East Riding of Yorkshire YO6 1LA",
    "addr:postcode":"yo6 1la",
    "addr:street":"Main St",
    "iso:country":"GB",
    "sg:address":"Main St",
    "sg:city":"York",
    "sg:classifiers":[
        {
            "category":"Retail",
            "subcategory":"Veterinary Services",
            "type":"Services"
        }
    ],
    "sg:phone":"+44 1347 810794",
    "sg:postcode":"YO6 1LA",
    "sg:province":"East Riding of Yorkshire",
    "sg:tags":[
        "surgeon"
    ],
    "wof:name":"Four Dales Veterinary Practice",
    "wof:placetype":"venue"
},
  "geometry": {"coordinates":[-1.238199,54.084949],"type":"Point"}
}