{
  "type": "Feature",
  "properties": {
    "addr:full":"91 Nightingale Lane London Greater London SW12 8NX",
    "addr:housenumber":"91",
    "addr:postcode":"sw12 8nx",
    "addr:street":"Nightingale Lane",
    "iso:country":"GB",
    "sg:address":"91 Nightingale Lane",
    "sg:city":"London",
    "sg:classifiers":[
        {
            "category":"Shopping",
            "subcategory":"Baby Store",
            "type":"Retail Goods"
        }
    ],
    "sg:phone":"+44 20 8673 0275",
    "sg:postcode":"SW12 8NX",
    "sg:province":"Greater London",
    "sg:tags":[
        "babywear",
        "childrens"
    ],
    "wof:name":"Swallows & Amazons",
    "wof:placetype":"venue"
},
  "geometry": {"coordinates":[-0.1576759964,51.4502334595],"type":"Point"}
}