{
  "type": "Feature",
  "properties": {
    "addr:full":"52 Kirkgate, Silsden Keighley North Yorkshire BD20 0AL",
    "addr:housenumber":"52",
    "addr:postcode":"bd20 0al",
    "addr:street":"Kirkgate",
    "iso:country":"GB",
    "sg:address":"52 Kirkgate, Silsden",
    "sg:city":"Keighley",
    "sg:classifiers":[
        {
            "category":"Fast Food",
            "type":"Food & Drink"
        }
    ],
    "sg:phone":"+44 1535 652554",
    "sg:postcode":"BD20 0AL",
    "sg:province":"North Yorkshire",
    "sg:tags":[
        "away",
        "take"
    ],
    "wof:name":"Pizzaroma",
    "wof:placetype":"venue"
},
  "geometry": {"coordinates":[-1.937504,53.912827],"type":"Point"}
}