{
  "type": "Feature",
  "properties": {
    "addr:full":"14 Beresford Terrace Ayr South Ayrshire KA7 2EG",
    "addr:housenumber":"14",
    "addr:postcode":"ka7 2eg",
    "addr:street":"Beresford Terrace",
    "iso:country":"GB",
    "sg:address":"14 Beresford Terrace",
    "sg:city":"Ayr",
    "sg:classifiers":[
        {
            "category":"Real Estate",
            "subcategory":"Real Estate Agent",
            "type":"Services"
        }
    ],
    "sg:phone":"+44 1292 267504",
    "sg:postcode":"KA7 2EG",
    "sg:province":"South Ayrshire",
    "wof:name":"Seal",
    "wof:placetype":"venue"
},
  "geometry": {"coordinates":[-4.629406929,55.4577255249],"type":"Point"}
}