{
  "type": "Feature",
  "properties": {
    "addr:full":"47 High Street, Wickham Market Woodbridge Suffolk IP13 0HE",
    "addr:housenumber":"47",
    "addr:postcode":"ip13 0he",
    "addr:street":"High Street",
    "iso:country":"GB",
    "sg:address":"47 High Street, Wickham Market",
    "sg:city":"Woodbridge",
    "sg:classifiers":[
        {
            "category":"Utilities",
            "subcategory":"Refuse",
            "type":"Services"
        }
    ],
    "sg:postcode":"IP13 0HE",
    "sg:province":"Suffolk",
    "sg:tags":[
        "skip",
        "hire"
    ],
    "wof:name":"Betts Skips Ltd",
    "wof:placetype":"venue"
},
  "geometry": {"coordinates":[1.3633379936,52.1492652893],"type":"Point"}
}