{
  "type": "Feature",
  "properties": {
    "addr:full":"19 Long Chaulden Hemel Hempstead Hertfordshire HP1 2HT",
    "addr:housenumber":"19",
    "addr:postcode":"hp1 2ht",
    "addr:street":"Long Chaulden Hemel Hempstead",
    "iso:country":"GB",
    "sg:address":"19 Long Chaulden",
    "sg:city":"Hemel Hempstead",
    "sg:classifiers":[
        {
            "category":"Professional",
            "subcategory":"Engineering",
            "type":"Services"
        }
    ],
    "sg:postcode":"HP1 2HT",
    "sg:province":"Hertfordshire",
    "sg:tags":[
        "electronic",
        "engineer"
    ],
    "wof:name":"P M International",
    "wof:placetype":"venue"
},
  "geometry": {"coordinates":[-0.4984050095,51.748500824],"type":"Point"}
}