{
  "type": "Feature",
  "properties": {
    "iso:country":"GB",
    "sg:address":"14 Station Road",
    "sg:city":"Ilkeston",
    "sg:classifiers":[
        {
            "category":"Organizations",
            "subcategory":"Community Association",
            "type":"Services"
        },
        {
            "category":"Organizations",
            "subcategory":"Membership Organization",
            "type":"Services"
        }
    ],
    "sg:phone":"+44 115 932 3103",
    "sg:postcode":"DE7 5LD",
    "sg:province":"Derbyshire",
    "sg:tags":[
        "club",
        "social"
    ],
    "wof:name":"The Carlton Club",
    "wof:placetype":"venue"
},
  "geometry": {"coordinates":[-1.307424,52.975033],"type":"Point"}
}