{
  "type": "Feature",
  "properties": {
    "addr:full":"Unit 8, 14 Conlan Street London Greater London W10 5AR",
    "addr:housenumber":"unit;14",
    "addr:postcode":"w10 5ar",
    "addr:street":"Conlan Street",
    "iso:country":"GB",
    "sg:address":"Unit 8, 14 Conlan Street",
    "sg:city":"London",
    "sg:classifiers":[
        {
            "category":"Professional",
            "subcategory":"Art Services",
            "type":"Services"
        }
    ],
    "sg:postcode":"W10 5AR",
    "sg:province":"Greater London",
    "sg:tags":[
        "photographer"
    ],
    "wof:name":"Andrersen Photography",
    "wof:placetype":"venue"
},
  "geometry": {"coordinates":[-0.2107229978,51.5257377625],"type":"Point"}
}