{
  "type": "Feature",
  "properties": {
    "addr:full":"1 Wimbledon Place, Bradwell Common Milton Keynes Buckinghamshire MK13 8BQ",
    "addr:housenumber":"1",
    "addr:postcode":"mk13 8bq",
    "addr:street":"Wimbledon Place",
    "iso:country":"GB",
    "sg:address":"1 Wimbledon Place, Bradwell Common",
    "sg:city":"Milton Keynes",
    "sg:classifiers":[
        {
            "category":"Personal",
            "subcategory":"Beauty Salon",
            "type":"Services"
        }
    ],
    "sg:postcode":"MK13 8BQ",
    "sg:province":"Buckinghamshire",
    "sg:tags":[
        "unisex",
        "hairdresser"
    ],
    "wof:name":"The Looking Glass",
    "wof:placetype":"venue"
},
  "geometry": {"coordinates":[-0.769918,52.044373],"type":"Point"}
}