{
  "type": "Feature",
  "properties": {
    "addr:full":"Care Of Williams & Griffin Colchester Essex CO1 1PN",
    "addr:postcode":"co1 1pn",
    "iso:country":"GB",
    "sg:address":"Care Of Williams & Griffin",
    "sg:city":"Colchester",
    "sg:classifiers":[
        {
            "category":"Home & Garden",
            "subcategory":"Kitchen Supply",
            "type":"Retail Goods"
        }
    ],
    "sg:phone":"+44 1206 769666",
    "sg:postcode":"CO1 1PN",
    "sg:province":"Essex",
    "sg:tags":[
        "glassware",
        "china"
    ],
    "wof:name":"Waterford Wedgwood Retail Ltd.",
    "wof:placetype":"venue"
},
  "geometry": {"coordinates":[0.8973199725,51.8897590637],"type":"Point"}
}