{
  "type": "Feature",
  "properties": {
    "iso:country":"GB",
    "sg:address":"124 Norfolk St",
    "sg:city":"Glasgow",
    "sg:classifiers":[
        {
            "category":"Cinema",
            "subcategory":"Movie Rental",
            "type":"Entertainment"
        }
    ],
    "sg:phone":"+44 141 420 6631",
    "sg:postcode":"G5 9EQ",
    "sg:province":"Glasgow City",
    "sg:tags":[
        "video",
        "library"
    ],
    "wof:name":"Rox Video",
    "wof:placetype":"venue"
},
  "geometry": {"coordinates":[-4.257878,55.852695],"type":"Point"}
}