{
  "type": "Feature",
  "properties": {
    "addr:full":"Cudworth House, Patmore Estate South Lambeth Greater London SW8 4UT",
    "addr:housenumber":"cudworth",
    "addr:postcode":"sw8 4ut",
    "addr:street":"Patmore Estate",
    "iso:country":"GB",
    "sg:address":"Cudworth House, Patmore Estate",
    "sg:city":"South Lambeth",
    "sg:classifiers":[
        {
            "category":"Organizations",
            "subcategory":"Non-profit Organization",
            "type":"Services"
        }
    ],
    "sg:phone":"+44 20 7627 0660",
    "sg:postcode":"SW8 4UT",
    "sg:province":"Greater London",
    "sg:tags":[
        "organisation",
        "voluntary",
        "charity"
    ],
    "wof:name":"The Patmore Community Resource Project",
    "wof:placetype":"venue"
},
  "geometry": {"coordinates":[-0.1389600039,51.4748916626],"type":"Point"}
}