{
  "type": "Feature",
  "properties": {
    "addr:full":"Unit 4 Tenter Road, Moulton Park Industrial Estate Northampton Northamptonshire NN3 6PZ",
    "addr:housenumber":"unit 4;estate",
    "addr:postcode":"nn3 6pz",
    "addr:street":"Tenter Road",
    "iso:country":"GB",
    "sg:address":"Unit 4 Tenter Road, Moulton Park Industrial Estate",
    "sg:city":"Northampton",
    "sg:classifiers":[
        {
            "category":"Bus Stop",
            "subcategory":"None",
            "type":"Transportation"
        }
    ],
    "sg:phone":"+44 1604 494945",
    "sg:postcode":"NN3 6PZ",
    "sg:province":"Northamptonshire",
    "sg:tags":[
        "filter"
    ],
    "wof:name":"Pipercross Ltd.",
    "wof:placetype":"venue"
},
  "geometry": {"coordinates":[-0.876389,52.280033],"type":"Point"}
}