{
  "type": "Feature",
  "properties": {
    "iso:country":"GB",
    "sg:address":"Watling Street, Wedges Mill",
    "sg:city":"Cannock",
    "sg:classifiers":[
        {
            "category":"Professional",
            "subcategory":"Business Services",
            "type":"Services"
        }
    ],
    "sg:postcode":"WS11 1TE",
    "sg:province":"Staffordshire",
    "sg:tags":[
        "import",
        "export",
        "agent"
    ],
    "wof:name":"Wm Realisations Ltd.",
    "wof:placetype":"venue"
},
  "geometry": {"coordinates":[-2.0483620167,52.6794204712],"type":"Point"}
}