{
  "type": "Feature",
  "properties": {
    "addr:full":"Church St, Stapleford Nottingham Nottinghamshire NG9 8GA",
    "addr:postcode":"ng9 8ga",
    "addr:street":"Church St",
    "iso:country":"GB",
    "sg:address":"Church St, Stapleford",
    "sg:city":"Nottingham",
    "sg:classifiers":[
        {
            "category":"Bars & Pubs",
            "type":"Food & Drink"
        }
    ],
    "sg:phone":"+44 115 939 4927",
    "sg:postcode":"NG9 8GA",
    "sg:province":"Nottinghamshire",
    "sg:tags":[
        "pubs",
        "inn"
    ],
    "wof:name":"Old Cross",
    "wof:placetype":"venue"
},
  "geometry": {"coordinates":[-1.2734980583,52.929725647],"type":"Point"}
}