{
  "type": "Feature",
  "properties": {
    "addr:full":"5 Market Place London Greater London W1W 8AE",
    "addr:housenumber":"5",
    "addr:postcode":"w1w 8ae",
    "addr:street":"Market Place",
    "iso:country":"GB",
    "sg:address":"5 Market Place",
    "sg:city":"London",
    "sg:classifiers":[
        {
            "category":"Shopping",
            "subcategory":"Clothing, Apparel, & Fashions",
            "type":"Retail Goods"
        }
    ],
    "sg:postcode":"W1W 8AE",
    "sg:province":"Greater London",
    "sg:tags":[
        "clothing"
    ],
    "wof:name":"X T C Clothing Co. Ltd.",
    "wof:placetype":"venue"
},
  "geometry": {"coordinates":[-0.063974,51.492607],"type":"Point"}
}