{
  "type": "Feature",
  "properties": {
    "iso:country":"GB",
    "sg:address":"67 Mountbatten Clo",
    "sg:city":"West Bromwich",
    "sg:classifiers":[
        {
            "category":"Retail",
            "subcategory":"Driving School",
            "type":"Services"
        }
    ],
    "sg:phone":"+44 121 553 3481",
    "sg:postcode":"B70 6QN",
    "sg:province":"West Midlands",
    "wof:name":"Bowen Bros School Of Motoring",
    "wof:placetype":"venue"
},
  "geometry": {"coordinates":[-1.977931,52.512897],"type":"Point"}
}