{
  "type": "Feature",
  "properties": {
    "iso:country":"GB",
    "sg:address":"Under Lane, Chadderton",
    "sg:city":"Oldham",
    "sg:classifiers":[
        {
            "category":"Retail",
            "subcategory":"Auto Repair",
            "type":"Services"
        }
    ],
    "sg:phone":"+44 7775 970836",
    "sg:postcode":"OL9 7JQ",
    "sg:province":"Lancashire",
    "sg:tags":[
        "modification",
        "garage"
    ],
    "wof:name":"Gem Garage",
    "wof:placetype":"venue"
},
  "geometry": {"coordinates":[-2.143644,53.5242],"type":"Point"}
}