{
  "type": "Feature",
  "properties": {
    "iso:country":"GB",
    "sg:address":"Balcary, Shootersway",
    "sg:city":"Berkhamsted",
    "sg:classifiers":[
        {
            "category":"Organizations",
            "subcategory":"Labor Organization",
            "type":"Services"
        },
        {
            "category":"Professional",
            "subcategory":"Business Services",
            "type":"Services"
        }
    ],
    "sg:phone":"+44 1442 877800",
    "sg:postcode":"HP4 3NN",
    "sg:province":"Bedfordshire",
    "sg:tags":[
        "import",
        "export",
        "agent"
    ],
    "wof:name":"Goldhill Associates",
    "wof:placetype":"venue"
},
  "geometry": {"coordinates":[-0.564559,51.760414],"type":"Point"}
}