{
  "type": "Feature",
  "properties": {
    "addr:full":"5th Floor Pennine Ho, Russell St Leeds West Yorkshire LS1 5TR",
    "addr:housenumber":"5th floor",
    "addr:postcode":"ls1 5tr",
    "addr:street":"Pennine Ho Russell St",
    "iso:country":"GB",
    "sg:address":"5th Floor Pennine Ho, Russell St",
    "sg:city":"Leeds",
    "sg:classifiers":[
        {
            "category":"Communications",
            "subcategory":"Film & Video Production",
            "type":"Services"
        }
    ],
    "sg:postcode":"LS1 5TR",
    "sg:province":"West Yorkshire",
    "sg:tags":[
        "survey",
        "aerial",
        "photographer"
    ],
    "wof:name":"Dacebow Ltd",
    "wof:placetype":"venue"
},
  "geometry": {"coordinates":[-1.546587,53.794495],"type":"Point"}
}