{
  "type": "Feature",
  "properties": {
    "addr:full":"38a High Street Walton-on-thames Surrey KT12 1DE",
    "addr:housenumber":"38a",
    "addr:postcode":"kt12 1de",
    "addr:street":"High Street",
    "iso:country":"GB",
    "sg:address":"38a High Street",
    "sg:city":"Walton-on-thames",
    "sg:classifiers":[
        {
            "category":"Banks & Credit Unions",
            "subcategory":"Bank",
            "type":"Services"
        }
    ],
    "sg:phone":"+44 1932 241154",
    "sg:postcode":"KT12 1DE",
    "sg:province":"Surrey",
    "sg:tags":[
        "broker",
        "mortgage"
    ],
    "wof:name":"Acorn Mortgage & Independent Insurance Consultants Ltd.",
    "wof:placetype":"venue"
},
  "geometry": {"coordinates":[-0.41893,51.385258],"type":"Point"}
}