{
  "type": "Feature",
  "properties": {
    "iso:country":"GB",
    "sg:address":"122-124 George Street",
    "sg:city":"Oban",
    "sg:classifiers":[
        {
            "category":"Shopping",
            "subcategory":"Photographic Equipment",
            "type":"Retail Goods"
        }
    ],
    "sg:phone":"+44 1631 562917",
    "sg:postcode":"PA34 5NT",
    "sg:province":"Argyll and Bute",
    "sg:tags":[
        "supply"
    ],
    "wof:name":"Frank Walton",
    "wof:placetype":"venue"
},
  "geometry": {"coordinates":[-5.4729270935,56.4164123535],"type":"Point"}
}