{
  "type": "Feature",
  "properties": {
    "addr:full":"22 South Square Blackpool Lancashire FY3 8AJ",
    "addr:housenumber":"22",
    "addr:postcode":"fy3 8aj",
    "addr:street":"South Square",
    "iso:country":"GB",
    "sg:address":"22 South Square",
    "sg:city":"Blackpool",
    "sg:classifiers":[
        {
            "category":"Real Estate",
            "subcategory":"Real Estate Services",
            "type":"Services"
        },
        {
            "category":"Retail",
            "subcategory":"Repair Shop",
            "type":"Services"
        }
    ],
    "sg:phone":"+44 1253 395888",
    "sg:postcode":"FY3 8AJ",
    "sg:province":"Lancashire",
    "sg:tags":[
        "property",
        "maintenance"
    ],
    "wof:name":"N Berry",
    "wof:placetype":"venue"
},
  "geometry": {"coordinates":[-3.0361249447,53.8221321106],"type":"Point"}
}