{
  "type": "Feature",
  "properties": {
    "addr:full":"Unit 6 Raglan Enterprise Pk, Chepstow Rd Raglan Monmouthshire NP5 2EW",
    "addr:housenumber":"unit 6",
    "addr:postcode":"np5 2ew",
    "addr:street":"Chepstow Rd",
    "iso:country":"GB",
    "sg:address":"Unit 6 Raglan Enterprise Pk, Chepstow Rd",
    "sg:city":"Raglan",
    "sg:classifiers":[
        {
            "category":"Farming",
            "subcategory":"Farm",
            "type":"Manufacturing & Wholesale Goods"
        }
    ],
    "sg:postcode":"NP5 2EW",
    "sg:province":"Monmouthshire",
    "sg:tags":[
        "agricultural"
    ],
    "wof:name":"J & L Garden Equipment Specialists",
    "wof:placetype":"venue"
},
  "geometry": {"coordinates":[-2.852930069,51.7646484375],"type":"Point"}
}