{
  "type": "Feature",
  "properties": {
    "addr:full":"Down Ash Park, Sparkford Yeovil Dorset BA22 7LH",
    "addr:postcode":"ba22 7lh",
    "iso:country":"GB",
    "sg:address":"Down Ash Park, Sparkford",
    "sg:city":"Yeovil",
    "sg:classifiers":[
        {
            "category":"Farming",
            "subcategory":"Dairy Farm",
            "type":"Manufacturing & Wholesale Goods"
        }
    ],
    "sg:phone":"+44 1963 440425",
    "sg:postcode":"BA22 7LH",
    "sg:province":"Dorset",
    "sg:tags":[
        "farmer"
    ],
    "wof:name":"Down Ash Park Partnership",
    "wof:placetype":"venue"
},
  "geometry": {"coordinates":[-2.5644640923,51.0357704163],"type":"Point"}
}