{
  "type": "Feature",
  "properties": {
    "iso:country":"GB",
    "sg:address":"179 Heathhall Indust Est",
    "sg:city":"Dumfries",
    "sg:classifiers":[
        {
            "category":"Home & Garden",
            "subcategory":"Carpets & Floor Coverings",
            "type":"Retail Goods"
        }
    ],
    "sg:phone":"+44 1387 264071",
    "sg:postcode":"DG1 3PH",
    "sg:province":"Dumfries and Galloway",
    "sg:tags":[
        "carpets",
        "rug",
        "matting"
    ],
    "wof:name":"Heathhall Carpet Centre",
    "wof:placetype":"venue"
},
  "geometry": {"coordinates":[-3.5608639717,55.1372489929],"type":"Point"}
}