{
  "type": "Feature",
  "properties": {
    "addr:full":"8b London Rd Bexhill On Sea East Sussex TN39 3JU",
    "addr:housenumber":"8b",
    "addr:postcode":"tn39 3ju",
    "addr:street":"London Rd",
    "iso:country":"GB",
    "sg:address":"8b London Rd",
    "sg:city":"Bexhill On Sea",
    "sg:classifiers":[
        {
            "category":"Autos & Motor Vehicles",
            "subcategory":"Auto Supplies",
            "type":"Retail Goods"
        }
    ],
    "sg:phone":"+44 1424 211234",
    "sg:postcode":"TN39 3JU",
    "sg:province":"East Sussex",
    "sg:tags":[
        "component"
    ],
    "wof:name":"Edmunds Walker",
    "wof:placetype":"venue"
},
  "geometry": {"coordinates":[0.470166,50.841736],"type":"Point"}
}