{
  "type": "Feature",
  "properties": {
    "iso:country":"GB",
    "sg:address":"16 Park Grove",
    "sg:city":"Cardiff",
    "sg:classifiers":[
        {
            "category":"Banks & Credit Unions",
            "subcategory":"Investment Brokerage",
            "type":"Services"
        },
        {
            "category":"Banks & Credit Unions",
            "subcategory":"Financial Services",
            "type":"Services"
        }
    ],
    "sg:phone":"+44 29 2066 5588",
    "sg:postcode":"CF10 3BN",
    "sg:province":"Cardiff",
    "sg:tags":[
        "adviser",
        "independent"
    ],
    "wof:name":"Cavendish Financial Management Ltd",
    "wof:placetype":"venue"
},
  "geometry": {"coordinates":[-3.174835,51.486534],"type":"Point"}
}