{
  "type": "Feature",
  "properties": {
    "addr:full":"Unit B2, Wymeswold Industrial Park, Wymeswold Lane Loughborough Leicestershire LE12 5TY",
    "addr:postcode":"le12 5ty",
    "addr:street":"Industrial Park Wymeswold Lane",
    "iso:country":"GB",
    "sg:address":"Unit B2, Wymeswold Industrial Park, Wymeswold Lane",
    "sg:city":"Loughborough",
    "sg:classifiers":[
        {
            "category":"Home & Garden",
            "subcategory":"Furniture",
            "type":"Retail Goods"
        }
    ],
    "sg:phone":"+44 1509 881661",
    "sg:postcode":"LE12 5TY",
    "sg:province":"Leicestershire",
    "wof:name":"Bradgate Furniture Ltd.",
    "wof:placetype":"venue"
},
  "geometry": {"coordinates":[-1.1186740398,52.7931251526],"type":"Point"}
}