{
  "type": "Feature",
  "properties": {
    "iso:country":"GB",
    "sg:address":"79 Tintern Avenue, West Didsbury",
    "sg:city":"Manchester",
    "sg:classifiers":[
        {
            "category":"Professional",
            "subcategory":"Computer Services",
            "type":"Services"
        }
    ],
    "sg:postcode":"M20 2ND",
    "sg:province":"Greater Manchester",
    "sg:tags":[
        "system",
        "software"
    ],
    "wof:name":"Rigel Star Ltd.",
    "wof:placetype":"venue"
},
  "geometry": {"coordinates":[-2.2442879677,53.4268875122],"type":"Point"}
}