{
  "type": "Feature",
  "properties": {
    "iso:country":"GB",
    "sg:address":"60 Northgate",
    "sg:city":"Wakefield",
    "sg:classifiers":[
        {
            "category":"Bars & Pubs",
            "type":"Food & Drink"
        }
    ],
    "sg:phone":"+44 1924 299627",
    "sg:postcode":"WF1 3AP",
    "sg:province":"West Yorkshire",
    "sg:tags":[
        "pubs",
        "house",
        "inn",
        "public",
        "activity"
    ],
    "wof:name":"The Gates",
    "wof:placetype":"venue"
},
  "geometry": {"coordinates":[-1.4989390373,53.6840820312],"type":"Point"}
}