{
  "type": "Feature",
  "properties": {
    "addr:full":"The Croft Annex, Ewood Lane, Newdigate Dorking Surrey RH5 5AP",
    "addr:postcode":"rh5 5ap",
    "addr:street":"Ewood Lane",
    "iso:country":"GB",
    "sg:address":"The Croft Annex, Ewood Lane, Newdigate",
    "sg:city":"Dorking",
    "sg:classifiers":[
        {
            "category":"Shopping",
            "subcategory":"Books",
            "type":"Retail Goods"
        }
    ],
    "sg:phone":"+44 1306 631661",
    "sg:postcode":"RH5 5AP",
    "sg:province":"Surrey",
    "wof:name":"Jane Menday",
    "wof:placetype":"venue"
},
  "geometry": {"coordinates":[-0.2905510068,51.167591095],"type":"Point"}
}