{
  "type": "Feature",
  "properties": {
    "iso:country":"GB",
    "sg:address":"5 Alverton Street",
    "sg:city":"Penzance",
    "sg:classifiers":[
        {
            "category":"Restaurant",
            "type":"Food & Drink"
        }
    ],
    "sg:postcode":"TR18 2QW",
    "sg:province":"Cornwall",
    "wof:name":"Nick's Restaurant",
    "wof:placetype":"venue"
},
  "geometry": {"coordinates":[-5.538393,50.118397],"type":"Point"}
}