{
  "type": "Feature",
  "properties": {
    "iso:country":"GB",
    "sg:address":"1 Cross Street",
    "sg:city":"Macclesfield",
    "sg:classifiers":[
        {
            "category":"Personal",
            "subcategory":"Beauty Salon",
            "type":"Services"
        },
        {
            "category":"Personal",
            "subcategory":"Barber",
            "type":"Services"
        }
    ],
    "sg:phone":"+44 1625 428401",
    "sg:postcode":"SK11 7PG",
    "sg:province":"Cheshire",
    "sg:tags":[
        "unisex",
        "hairdresser"
    ],
    "wof:name":"Shapers",
    "wof:placetype":"venue"
},
  "geometry": {"coordinates":[-2.121517,53.252094],"type":"Point"}
}