{
  "type": "Feature",
  "properties": {
    "addr:full":"92 Mercer Cres Rossendale Lancashire BB4 4DX",
    "addr:housenumber":"92",
    "addr:postcode":"bb4 4dx",
    "addr:street":"Mercer Cres",
    "iso:country":"GB",
    "sg:address":"92 Mercer Cres",
    "sg:city":"Rossendale",
    "sg:classifiers":[
        {
            "category":"Building & Trades",
            "subcategory":"Plumbing",
            "type":"Services"
        }
    ],
    "sg:phone":"+44 1706 217219",
    "sg:postcode":"BB4 4DX",
    "sg:province":"Lancashire",
    "sg:tags":[
        "central",
        "heating"
    ],
    "wof:name":"Grahams Service & Repairs",
    "wof:placetype":"venue"
},
  "geometry": {"coordinates":[-2.333577,53.695057],"type":"Point"}
}