{
  "type": "Feature",
  "properties": {
    "iso:country":"GB",
    "sg:address":"White Wing Commons Old Rd, Shaldon",
    "sg:city":"Teignmouth",
    "sg:classifiers":[
        {
            "category":"Sports & Exercise",
            "subcategory":"Gym",
            "type":"Entertainment"
        }
    ],
    "sg:postcode":"TQ14 0EF",
    "sg:province":"Devon",
    "sg:tags":[
        "fitness",
        "health",
        "centre"
    ],
    "wof:name":"Slimming Magazine Club",
    "wof:placetype":"venue"
},
  "geometry": {"coordinates":[-3.511077,50.539448],"type":"Point"}
}