{
  "type": "Feature",
  "properties": {
    "addr:full":"70 Plover Road, Lindley Huddersfield West Yorkshire HD3 3HR",
    "addr:housenumber":"70",
    "addr:postcode":"hd3 3hr",
    "addr:street":"Plover Road;West",
    "iso:country":"GB",
    "sg:address":"70 Plover Road, Lindley",
    "sg:city":"Huddersfield",
    "sg:classifiers":[
        {
            "category":"Manufacturing",
            "subcategory":"Textiles",
            "type":"Manufacturing & Wholesale Goods"
        }
    ],
    "sg:phone":"+44 1484 653437",
    "sg:postcode":"HD3 3HR",
    "sg:province":"West Yorkshire",
    "sg:tags":[
        "dyer"
    ],
    "wof:name":"John Gladstone & Co. Ltd.",
    "wof:placetype":"venue"
},
  "geometry": {"coordinates":[-1.8236119747,53.656955719],"type":"Point"}
}