{
  "type": "Feature",
  "properties": {
    "addr:full":"3 Scott Place Saltcoats North Ayrshire KA21 5TA",
    "addr:housenumber":"3",
    "addr:postcode":"ka21 5ta",
    "addr:street":"Scott Place",
    "iso:country":"GB",
    "sg:address":"3 Scott Place",
    "sg:city":"Saltcoats",
    "sg:classifiers":[
        {
            "category":"Professional",
            "subcategory":"Business Services",
            "type":"Services"
        }
    ],
    "sg:phone":"+44 1294 465162",
    "sg:postcode":"KA21 5TA",
    "sg:province":"North Ayrshire",
    "sg:tags":[
        "assessment",
        "quality"
    ],
    "wof:name":"Harry Boyle Associates Ltd.",
    "wof:placetype":"venue"
},
  "geometry": {"coordinates":[-4.793034,55.640732],"type":"Point"}
}