{
  "type": "Feature",
  "properties": {
    "addr:full":"Garden Flat, 30 Camden Square London Greater London NW1 9XA",
    "addr:housenumber":"30",
    "addr:postcode":"nw1 9xa",
    "addr:street":"Camden Square",
    "iso:country":"GB",
    "sg:address":"Garden Flat, 30 Camden Square",
    "sg:city":"London",
    "sg:classifiers":[
        {
            "category":"Organizations",
            "subcategory":"Membership Organization",
            "type":"Services"
        }
    ],
    "sg:postcode":"NW1 9XA",
    "sg:province":"Greater London",
    "sg:tags":[
        "club"
    ],
    "wof:name":"Gemini Management Ltd",
    "wof:placetype":"venue"
},
  "geometry": {"coordinates":[-0.131219998,51.5448303223],"type":"Point"}
}