{
  "type": "Feature",
  "properties": {
    "addr:full":"1st Floor 1 Albion Place Sunderland Tyne and Wear SR1 3NG",
    "addr:postcode":"sr1 3ng",
    "addr:street":"Albion Place",
    "iso:country":"GB",
    "sg:address":"1st Floor 1 Albion Place",
    "sg:city":"Sunderland",
    "sg:classifiers":[
        {
            "category":"Professional",
            "subcategory":"Accounting & Tax Preparation",
            "type":"Services"
        }
    ],
    "sg:phone":"+44 191 387 1110",
    "sg:postcode":"SR1 3NG",
    "sg:province":"Tyne and Wear",
    "sg:tags":[
        "accountant"
    ],
    "wof:name":"Rainbow Straughan & Elliott",
    "wof:placetype":"venue"
},
  "geometry": {"coordinates":[-1.38629,54.90229],"type":"Point"}
}