{
  "type": "Feature",
  "properties": {
    "addr:full":"Robeck Road Ipswich Suffolk IP3 0HS",
    "addr:postcode":"ip3 0hs",
    "addr:street":"Robeck Road",
    "iso:country":"GB",
    "sg:address":"Robeck Road",
    "sg:city":"Ipswich",
    "sg:classifiers":[
        {
            "category":"Education",
            "subcategory":"School",
            "type":"Public Place"
        }
    ],
    "sg:phone":"+44 1473 727458",
    "sg:postcode":"IP3 0HS",
    "sg:province":"Suffolk",
    "sg:tags":[
        "local",
        "authority"
    ],
    "wof:name":"Orwell Junior School",
    "wof:placetype":"venue"
},
  "geometry": {"coordinates":[1.1668909788,52.0374794006],"type":"Point"}
}