{
  "type": "Feature",
  "properties": {
    "iso:country":"GB",
    "sg:address":"Thriplow House, Middle Street, Thriplow",
    "sg:city":"Royston",
    "sg:classifiers":[
        {
            "category":"Real Estate",
            "subcategory":"Architect",
            "type":"Services"
        }
    ],
    "sg:phone":"+44 1763 208887",
    "sg:postcode":"SG8 7RD",
    "sg:province":"Bedfordshire",
    "wof:name":"Michael Walton",
    "wof:placetype":"venue"
},
  "geometry": {"coordinates":[0.098302,52.099365],"type":"Point"}
}