{
  "type": "Feature",
  "properties": {
    "iso:country":"GB",
    "sg:address":"18 Holland Rd",
    "sg:city":"Wallasey",
    "sg:classifiers":[
        {
            "category":"Manufacturing",
            "subcategory":"Signs",
            "type":"Manufacturing & Wholesale Goods"
        }
    ],
    "sg:phone":"+44 151 639 9508",
    "sg:postcode":"L45 7RB",
    "sg:province":"Merseyside",
    "sg:tags":[
        "writer"
    ],
    "wof:name":"Chesters",
    "wof:placetype":"venue"
},
  "geometry": {"coordinates":[-3.036022,53.429516],"type":"Point"}
}