{
  "type": "Feature",
  "properties": {
    "iso:country":"GB",
    "sg:address":"62d Cricklewood Bdwy",
    "sg:city":"London",
    "sg:classifiers":[
        {
            "category":"Personal",
            "subcategory":"Beauty Salon",
            "type":"Services"
        }
    ],
    "sg:phone":"+44 20 8450 3670",
    "sg:postcode":"NW2 3EP",
    "sg:province":"Greater London",
    "sg:tags":[
        "unisex",
        "hairdresser"
    ],
    "wof:name":"Your Way",
    "wof:placetype":"venue"
},
  "geometry": {"coordinates":[-0.211595,51.553444],"type":"Point"}
}