{
  "type": "Feature",
  "properties": {
    "addr:full":"Powers Chambers, Bath Place Taunton Somerset TA1 4ER",
    "addr:postcode":"ta1 4er",
    "addr:street":"Bath Place",
    "iso:country":"GB",
    "sg:address":"Powers Chambers, Bath Place",
    "sg:city":"Taunton",
    "sg:classifiers":[
        {
            "category":"Government",
            "subcategory":"Office",
            "type":"Public Place"
        }
    ],
    "sg:phone":"+44 1823 321231",
    "sg:postcode":"TA1 4ER",
    "sg:province":"Somerset",
    "sg:tags":[
        "chamber",
        "commerce"
    ],
    "wof:name":"Somerset Chamber of Commerce & Industry Ltd.",
    "wof:placetype":"venue"
},
  "geometry": {"coordinates":[-3.1106989384,51.0104904175],"type":"Point"}
}