{
  "type": "Feature",
  "properties": {
    "iso:country":"GB",
    "sg:address":"12 Colmore Circus Queensway",
    "sg:city":"Birmingham",
    "sg:classifiers":[
        {
            "category":"Personal",
            "subcategory":"Beauty Salon",
            "type":"Services"
        }
    ],
    "sg:phone":"+44 121 236 6630",
    "sg:postcode":"B4 6AT",
    "sg:province":"West Midlands",
    "sg:tags":[
        "unisex",
        "hairdresser"
    ],
    "wof:name":"Raffles",
    "wof:placetype":"venue"
},
  "geometry": {"coordinates":[-1.896577,52.483837],"type":"Point"}
}