{
  "type": "Feature",
  "properties": {
    "addr:full":"19 Barton Close Shepperton Surrey TW17 9AQ",
    "addr:housenumber":"19",
    "addr:postcode":"tw17 9aq",
    "addr:street":"Barton Close",
    "iso:country":"GB",
    "sg:address":"19 Barton Close",
    "sg:city":"Shepperton",
    "sg:classifiers":[
        {
            "category":"Professional",
            "subcategory":"Engineering",
            "type":"Services"
        }
    ],
    "sg:phone":"+44 1932 223297",
    "sg:postcode":"TW17 9AQ",
    "sg:province":"Surrey",
    "sg:tags":[
        "contractor",
        "electrical",
        "engineer"
    ],
    "wof:name":"Electrical Contacts (Shepperton) Ltd.",
    "wof:placetype":"venue"
},
  "geometry": {"coordinates":[-0.450791,51.395828],"type":"Point"}
}