{
  "type": "Feature",
  "properties": {
    "addr:full":"8 Mynydd Newydd Road, Caereithin Swansea Swansea SA5 5AG",
    "addr:housenumber":"8",
    "addr:postcode":"sa5 5ag",
    "addr:street":"Mynydd Newydd Road Caereithin",
    "iso:country":"GB",
    "sg:address":"8 Mynydd Newydd Road, Caereithin",
    "sg:city":"Swansea",
    "sg:classifiers":[
        {
            "category":"Retail",
            "subcategory":"Storage",
            "type":"Services"
        }
    ],
    "sg:phone":"+44 1792 583278",
    "sg:postcode":"SA5 5AG",
    "sg:province":"Swansea",
    "sg:tags":[
        "household",
        "removal"
    ],
    "wof:name":"Paul Andrew Bennett",
    "wof:placetype":"venue"
},
  "geometry": {"coordinates":[-3.969203949,51.6508560181],"type":"Point"}
}