{
  "type": "Feature",
  "properties": {
    "addr:full":"Old Church Road, Cullen Buckie Moray AB56 4UZ",
    "addr:postcode":"ab56 4uz",
    "addr:street":"Old Church Road",
    "iso:country":"GB",
    "sg:address":"Old Church Road, Cullen",
    "sg:city":"Buckie",
    "sg:classifiers":[
        {
            "category":"Education",
            "subcategory":"School",
            "type":"Public Place"
        },
        {
            "category":"Government",
            "subcategory":"Office",
            "type":"Public Place"
        }
    ],
    "sg:phone":"+44 1542 840279",
    "sg:postcode":"AB56 4UZ",
    "sg:province":"Moray",
    "sg:tags":[
        "local",
        "authority"
    ],
    "wof:name":"Cullen Primary School",
    "wof:placetype":"venue"
},
  "geometry": {"coordinates":[-2.8181979656,57.690612793],"type":"Point"}
}