{
  "type": "Feature",
  "properties": {
    "addr:full":"32 Upr Dartrey Walk, Worlds End Est London Greater London SW10 0EN",
    "addr:housenumber":"32",
    "addr:postcode":"sw10 0en",
    "addr:street":"Upr Dartrey Walk Worlds End Est",
    "iso:country":"GB",
    "sg:address":"32 Upr Dartrey Walk, Worlds End Est",
    "sg:city":"London",
    "sg:classifiers":[
        {
            "category":"Communications",
            "subcategory":"Film & Video Production",
            "type":"Services"
        },
        {
            "category":"Professional",
            "subcategory":"Business Services",
            "type":"Services"
        }
    ],
    "sg:postcode":"SW10 0EN",
    "sg:province":"Greater London",
    "sg:tags":[
        "distributor",
        "tv",
        "studio"
    ],
    "wof:name":"Ciel Productions Ltd",
    "wof:placetype":"venue"
},
  "geometry": {"coordinates":[-0.1805399954,51.4811401367],"type":"Point"}
}