{
  "type": "Feature",
  "properties": {
    "addr:full":"29-30 Wulvesford Witham Essex CM8 1NL",
    "addr:housenumber":"29-30",
    "addr:postcode":"cm8 1nl",
    "addr:street":"Wulvesford Witham",
    "iso:country":"GB",
    "sg:address":"29-30 Wulvesford",
    "sg:city":"Witham",
    "sg:classifiers":[
        {
            "category":"Shopping",
            "subcategory":"Department Store",
            "type":"Retail Goods"
        }
    ],
    "sg:phone":"+44 1376 512798",
    "sg:postcode":"CM8 1NL",
    "sg:province":"Essex",
    "wof:name":"Londis Store",
    "wof:placetype":"venue"
},
  "geometry": {"coordinates":[0.6220999956,51.7920455933],"type":"Point"}
}