{
  "type": "Feature",
  "properties": {
    "addr:full":"Unit A223, Riverside Business Centre, Haldane Place London Greater London SW18 4UQ",
    "addr:postcode":"sw18 4uq",
    "addr:street":"Haldane Place",
    "iso:country":"GB",
    "sg:address":"Unit A223, Riverside Business Centre, Haldane Place",
    "sg:city":"London",
    "sg:classifiers":[
        {
            "category":"Professional",
            "type":"Services"
        }
    ],
    "sg:phone":"+44 20 8875 1311",
    "sg:postcode":"SW18 4UQ",
    "sg:province":"Greater London",
    "sg:tags":[
        "interior",
        "furnishers",
        "designer"
    ],
    "wof:name":"Yewberry Ltd.",
    "wof:placetype":"venue"
},
  "geometry": {"coordinates":[-0.1928499937,51.4459686279],"type":"Point"}
}