{
  "type": "Feature",
  "properties": {
    "addr:full":"42-44 Cambridge Road Barking Essex IG11 8NW",
    "addr:housenumber":"42-44",
    "addr:postcode":"ig11 8nw",
    "addr:street":"Cambridge Road",
    "iso:country":"GB",
    "sg:address":"42-44 Cambridge Road",
    "sg:city":"Barking",
    "sg:classifiers":[
        {
            "category":"Building & Trades",
            "subcategory":"Cleaning & Sanitation",
            "type":"Services"
        }
    ],
    "sg:phone":"+44 20 8591 4070",
    "sg:postcode":"IG11 8NW",
    "sg:province":"Essex",
    "sg:tags":[
        "commercial"
    ],
    "wof:name":"Superclean Services (City) Ltd.",
    "wof:placetype":"venue"
},
  "geometry": {"coordinates":[0.0784349963,51.5395812988],"type":"Point"}
}