{
  "type": "Feature",
  "properties": {
    "addr:full":"5 New Road, Gwaun Cae Gurwen Ammanford Carmarthenshire SA18 1UN",
    "addr:housenumber":"5",
    "addr:postcode":"sa18 1un",
    "addr:street":"New Road",
    "iso:country":"GB",
    "sg:address":"5 New Road, Gwaun Cae Gurwen",
    "sg:city":"Ammanford",
    "sg:classifiers":[
        {
            "category":"Community Center",
            "type":"Public Place"
        }
    ],
    "sg:phone":"+44 1269 825919",
    "sg:postcode":"SA18 1UN",
    "sg:province":"Carmarthenshire",
    "sg:tags":[
        "centre"
    ],
    "wof:name":"G C G Community Hall",
    "wof:placetype":"venue"
},
  "geometry": {"coordinates":[-3.865813,51.813251],"type":"Point"}
}