{
  "type": "Feature",
  "properties": {
    "addr:full":"Oak Farm Hall Road, Hopton Great Yarmouth Norfolk NR31 9AU",
    "addr:postcode":"nr31 9au",
    "addr:street":"Oak;Hall Road;Yarmouth",
    "iso:country":"GB",
    "sg:address":"Oak Farm Hall Road, Hopton",
    "sg:city":"Great Yarmouth",
    "sg:classifiers":[
        {
            "category":"Professional",
            "subcategory":"Engineering",
            "type":"Services"
        },
        {
            "category":"Building & Trades",
            "subcategory":"Electrical",
            "type":"Services"
        }
    ],
    "sg:phone":"+44 1502 730055",
    "sg:postcode":"NR31 9AU",
    "sg:province":"Norfolk",
    "sg:tags":[
        "engineer",
        "electrician",
        "contractor"
    ],
    "wof:name":"Bure Electrical",
    "wof:placetype":"venue"
},
  "geometry": {"coordinates":[1.72592,52.539349],"type":"Point"}
}