{
  "type": "Feature",
  "properties": {
    "iso:country":"GB",
    "sg:address":"79 Albany Rd",
    "sg:city":"Chatham",
    "sg:classifiers":[
        {
            "category":"Professional",
            "subcategory":"Testing Lab",
            "type":"Services"
        }
    ],
    "sg:postcode":"ME4 5DN",
    "sg:province":"Kent",
    "sg:tags":[
        "inspection",
        "calibration"
    ],
    "wof:name":"N D T Services",
    "wof:placetype":"venue"
},
  "geometry": {"coordinates":[0.5406939983,51.3716888428],"type":"Point"}
}