{
  "type": "Feature",
  "properties": {
    "addr:full":"Melbourne House, 509 Middleton Road, Chadderton Oldham Lancashire OL9 9SH",
    "addr:housenumber":"509",
    "addr:postcode":"ol9 9sh",
    "addr:street":"Middleton Road",
    "iso:country":"GB",
    "sg:address":"Melbourne House, 509 Middleton Road, Chadderton",
    "sg:city":"Oldham",
    "sg:classifiers":[
        {
            "category":"Building & Trades",
            "subcategory":"Construction",
            "type":"Services"
        }
    ],
    "sg:phone":"+44 161 626 7218",
    "sg:postcode":"OL9 9SH",
    "sg:province":"Lancashire",
    "sg:tags":[
        "builder"
    ],
    "wof:name":"Stonerand Ltd.",
    "wof:placetype":"venue"
},
  "geometry": {"coordinates":[-2.139799118,53.5447692871],"type":"Point"}
}