{
  "type": "Feature",
  "properties": {
    "addr:full":"24 Caledonian Road London Greater London N1 9DU",
    "addr:housenumber":"24",
    "addr:postcode":"n1 9du",
    "addr:street":"Caledonian Road",
    "iso:country":"GB",
    "sg:address":"24 Caledonian Road",
    "sg:city":"London",
    "sg:classifiers":[
        {
            "category":"Personal",
            "subcategory":"Barber",
            "type":"Services"
        }
    ],
    "sg:phone":"+44 20 7837 4701",
    "sg:postcode":"N1 9DU",
    "sg:province":"Greater London",
    "sg:tags":[
        "men's",
        "hairdresser"
    ],
    "wof:name":"Peter & Tony",
    "wof:placetype":"venue"
},
  "geometry": {"coordinates":[-0.1207759976,51.5315895081],"type":"Point"}
}