{
  "type": "Feature",
  "properties": {
    "iso:country":"GB",
    "sg:address":"153 Battersea Rise",
    "sg:city":"Battersea",
    "sg:classifiers":[
        {
            "category":"Professional",
            "subcategory":"Employment Agencies",
            "type":"Services"
        }
    ],
    "sg:phone":"+44 20 7924 2484",
    "sg:postcode":"SW11 1HP",
    "sg:province":"Greater London",
    "sg:tags":[
        "modelling"
    ],
    "wof:name":"Derek's Hands",
    "wof:placetype":"venue"
},
  "geometry": {"coordinates":[-0.172109,51.459572],"type":"Point"}
}