{
  "type": "Feature",
  "properties": {
    "addr:full":"1 The Precinct, Main Road, Church Village Pontypridd Rhondda, Cynon, Taff CF38 1SB",
    "addr:housenumber":"1",
    "addr:postcode":"cf38 1sb",
    "addr:street":"The Precinct Main Road Church",
    "iso:country":"GB",
    "sg:address":"1 The Precinct, Main Road, Church Village",
    "sg:city":"Pontypridd",
    "sg:classifiers":[
        {
            "category":"Food & Beverages",
            "subcategory":"Supermarket",
            "type":"Retail Goods"
        }
    ],
    "sg:phone":"+44 1443 205038",
    "sg:postcode":"CF38 1SB",
    "sg:province":"Rhondda, Cynon, Taff",
    "wof:name":"Somerfield Stores Ltd",
    "wof:placetype":"venue"
},
  "geometry": {"coordinates":[-3.3240339756,51.5644035339],"type":"Point"}
}