{
  "type": "Feature",
  "properties": {
    "iso:country":"GB",
    "sg:address":"Cruso Street",
    "sg:city":"Leek",
    "sg:classifiers":[
        {
            "category":"Retail",
            "subcategory":"Auto Repair",
            "type":"Services"
        }
    ],
    "sg:phone":"+44 1538 382618",
    "sg:postcode":"ST13 8BW",
    "sg:province":"Staffordshire",
    "sg:tags":[
        "body",
        "car"
    ],
    "wof:name":"John Lagan",
    "wof:placetype":"venue"
},
  "geometry": {"coordinates":[-2.031475,53.104733],"type":"Point"}
}