{
  "type": "Feature",
  "properties": {
    "addr:full":"20 Litchdon Street Barnstaple Devon EX32 8ND",
    "addr:housenumber":"20",
    "addr:postcode":"ex32 8nd",
    "addr:street":"Litchdon Street",
    "iso:country":"GB",
    "sg:address":"20 Litchdon Street",
    "sg:city":"Barnstaple",
    "sg:classifiers":[
        {
            "category":"Social Services",
            "subcategory":"Child Care",
            "type":"Services"
        }
    ],
    "sg:phone":"+44 1271 346655",
    "sg:postcode":"EX32 8ND",
    "sg:province":"Devon",
    "sg:tags":[
        "children's",
        "home"
    ],
    "wof:name":"Southern Child Care Ltd.",
    "wof:placetype":"venue"
},
  "geometry": {"coordinates":[-4.056819,51.077122],"type":"Point"}
}