{
  "type": "Feature",
  "properties": {
    "addr:full":"8 Long Lane, Ickenham Uxbridge Greater London UB10 8TB",
    "addr:housenumber":"8",
    "addr:postcode":"ub10 8tb",
    "addr:street":"Long Lane",
    "iso:country":"GB",
    "sg:address":"8 Long Lane, Ickenham",
    "sg:city":"Uxbridge",
    "sg:classifiers":[
        {
            "category":"Building & Trades",
            "subcategory":"Construction",
            "type":"Services"
        }
    ],
    "sg:phone":"+44 1895 633241",
    "sg:postcode":"UB10 8TB",
    "sg:province":"Greater London",
    "sg:tags":[
        "double",
        "window",
        "glazing",
        "installers",
        "replacement"
    ],
    "sg:website":"http://www.city2000.com",
    "wof:name":"Just Windows & Doors Ltd.",
    "wof:placetype":"venue"
},
  "geometry": {"coordinates":[-0.4441600144,51.5640907288],"type":"Point"}
}