{
  "type": "Feature",
  "properties": {
    "addr:full":"Cwmcreigiau Fach, Alltwalis Carmarthen Carmarthenshire SA32 7EG",
    "addr:postcode":"sa32 7eg",
    "addr:street":"Cwmcreigiau;Alltwalis;Carmarthenshire",
    "iso:country":"GB",
    "sg:address":"Cwmcreigiau Fach, Alltwalis",
    "sg:city":"Carmarthen",
    "sg:classifiers":[
        {
            "category":"Farming",
            "subcategory":"Livestock Farm",
            "type":"Manufacturing & Wholesale Goods"
        }
    ],
    "sg:postcode":"SA32 7EG",
    "sg:province":"Carmarthenshire",
    "sg:tags":[
        "others"
    ],
    "wof:name":"William E Evans",
    "wof:placetype":"venue"
},
  "geometry": {"coordinates":[-4.2638602257,51.9617156982],"type":"Point"}
}