{
  "type": "Feature",
  "properties": {
    "addr:full":"19 Rydal Avenue, Netherton Maryport Cumbria CA15 7LU",
    "addr:housenumber":"19",
    "addr:postcode":"ca15 7lu",
    "addr:street":"Rydal Avenue",
    "iso:country":"GB",
    "sg:address":"19 Rydal Avenue, Netherton",
    "sg:city":"Maryport",
    "sg:classifiers":[
        {
            "category":"Government",
            "subcategory":"Post Office",
            "type":"Public Place"
        }
    ],
    "sg:phone":"+44 1900 812618",
    "sg:postcode":"CA15 7LU",
    "sg:province":"Cumbria",
    "wof:name":"Craig & Sharpe",
    "wof:placetype":"venue"
},
  "geometry": {"coordinates":[-3.48781,54.710457],"type":"Point"}
}