{
  "type": "Feature",
  "properties": {
    "iso:country":"GB",
    "sg:address":"245-251 Lord Street",
    "sg:city":"Southport",
    "sg:classifiers":[
        {
            "category":"Shopping",
            "subcategory":"Comic Books",
            "type":"Retail Goods"
        }
    ],
    "sg:phone":"+44 1704 536664",
    "sg:postcode":"PR8 1NY",
    "sg:province":"Lancashire",
    "sg:tags":[
        "jeweller"
    ],
    "wof:name":"H Samuel",
    "wof:placetype":"venue"
},
  "geometry": {"coordinates":[-3.0064899921,53.6479301453],"type":"Point"}
}