{
  "type": "Feature",
  "properties": {
    "iso:country":"GB",
    "sg:address":"Pit Lane, Jamage Road Industrial Estate, Talke Pits",
    "sg:city":"Stoke-on-trent",
    "sg:classifiers":[
        {
            "category":"Home & Garden",
            "subcategory":"Hardware",
            "type":"Retail Goods"
        }
    ],
    "sg:phone":"+44 1782 771323",
    "sg:postcode":"ST7 1TT",
    "sg:province":"Cheshire",
    "sg:tags":[
        "retailer",
        "diy"
    ],
    "wof:name":"B & Q Diy Supercentre",
    "wof:placetype":"venue"
},
  "geometry": {"coordinates":[-2.264158,53.072388],"type":"Point"}
}