{
  "type": "Feature",
  "properties": {
    "iso:country":"GB",
    "sg:address":", Stone Berkeley",
    "sg:city":"Berkeley",
    "sg:classifiers":[
        {
            "category":"Education",
            "subcategory":"School",
            "type":"Public Place"
        }
    ],
    "sg:phone":"+44 1454 260309",
    "sg:postcode":"GL13 9JX",
    "sg:province":"Gloucestershire",
    "sg:tags":[
        "local",
        "authority"
    ],
    "wof:name":"Stone with Woodford C.of E. School",
    "wof:placetype":"venue"
},
  "geometry": {"coordinates":[-2.4595689774,51.6931877136],"type":"Point"}
}