{
  "type": "Feature",
  "properties": {
    "iso:country":"GB",
    "sg:address":"Greengarth, Main St, Hatfield Woodhouse",
    "sg:city":"Doncaster",
    "sg:classifiers":[
        {
            "category":"Home & Garden",
            "subcategory":"Furniture",
            "type":"Retail Goods"
        }
    ],
    "sg:phone":"+44 1302 845874",
    "sg:postcode":"DN7 6NE",
    "sg:province":"South Yorkshire",
    "wof:name":"John Reeves",
    "wof:placetype":"venue"
},
  "geometry": {"coordinates":[-0.9983450174,53.5780181885],"type":"Point"}
}