{
  "type": "Feature",
  "properties": {
    "iso:country":"GB",
    "sg:address":"Ffordd Gwynedd",
    "sg:city":"Bangor",
    "sg:classifiers":[
        {
            "category":"Cafe",
            "type":"Food & Drink"
        }
    ],
    "sg:postcode":"LL57 1DT",
    "sg:province":"Gwynedd",
    "sg:tags":[
        "tea",
        "room"
    ],
    "wof:name":"Gwenda Kotkowicz",
    "wof:placetype":"venue"
},
  "geometry": {"coordinates":[-4.127783,53.227646],"type":"Point"}
}