{
  "type": "Feature",
  "properties": {
    "addr:full":"63 Liverpool Road, Kidsgrove Stoke-on-trent Cheshire ST7 1EA",
    "addr:housenumber":"63",
    "addr:postcode":"st7 1ea",
    "addr:street":"Liverpool Road",
    "iso:country":"GB",
    "sg:address":"63 Liverpool Road, Kidsgrove",
    "sg:city":"Stoke-on-trent",
    "sg:classifiers":[
        {
            "category":"Recreation",
            "subcategory":"Amusement Park",
            "type":"Entertainment"
        }
    ],
    "sg:phone":"+44 1782 782051",
    "sg:postcode":"ST7 1EA",
    "sg:province":"Cheshire",
    "sg:tags":[
        "arcade"
    ],
    "wof:name":"Silver Coin",
    "wof:placetype":"venue"
},
  "geometry": {"coordinates":[-2.241379,53.086967],"type":"Point"}
}