{
  "type": "Feature",
  "properties": {
    "iso:country":"GB",
    "sg:address":"Caledonian Road",
    "sg:city":"Perth",
    "sg:classifiers":[
        {
            "category":"Health Services",
            "subcategory":"Doctor",
            "type":"Services"
        }
    ],
    "sg:phone":"+44 1738 628234",
    "sg:postcode":"PH2 8HH",
    "sg:province":"Perth and Kinross",
    "sg:tags":[
        "practitioners"
    ],
    "wof:name":"The Medical Centre",
    "wof:placetype":"venue"
},
  "geometry": {"coordinates":[-3.438874,56.395851],"type":"Point"}
}