{
  "type": "Feature",
  "properties": {
    "iso:country":"GB",
    "sg:address":"21 Whitegate Drive",
    "sg:city":"Blackpool",
    "sg:classifiers":[
        {
            "category":"Food & Beverages",
            "subcategory":"Fruits & Vegetables",
            "type":"Retail Goods"
        }
    ],
    "sg:phone":"+44 1253 302322",
    "sg:postcode":"FY3 9AA",
    "sg:province":"Lancashire",
    "sg:tags":[
        "greengrocer"
    ],
    "wof:name":"Hunt's Fruit & Veg",
    "wof:placetype":"venue"
},
  "geometry": {"coordinates":[-3.037805,53.817585],"type":"Point"}
}