{
  "type": "Feature",
  "properties": {
    "iso:country":"GB",
    "sg:address":"Stane Street, Slinfold",
    "sg:city":"Horsham",
    "sg:classifiers":[
        {
            "category":"Travel",
            "subcategory":"Hotels & Motels",
            "type":"Entertainment"
        }
    ],
    "sg:phone":"+44 1403 790764",
    "sg:postcode":"RH13 7QX",
    "sg:province":"West Sussex",
    "sg:tags":[
        "house",
        "guest"
    ],
    "wof:name":"Magpies",
    "wof:placetype":"venue"
},
  "geometry": {"coordinates":[-0.40533,51.070011],"type":"Point"}
}