{
  "type": "Feature",
  "properties": {
    "iso:country":"GB",
    "sg:address":"1 Hall Waveney Market",
    "sg:city":"Lowestoft",
    "sg:classifiers":[
        {
            "category":"Food & Beverages",
            "subcategory":"Meat & Fish",
            "type":"Retail Goods"
        }
    ],
    "sg:postcode":"NR32 1BY",
    "sg:province":"Suffolk",
    "sg:tags":[
        "merchant"
    ],
    "wof:name":"R & A Fish Merchants",
    "wof:placetype":"venue"
},
  "geometry": {"coordinates":[1.7533199787,52.4740180969],"type":"Point"}
}