{
  "type": "Feature",
  "properties": {
    "addr:full":"186 Manchester Road, Swinton Manchester Greater Manchester M27 4TS",
    "addr:housenumber":"186",
    "addr:postcode":"m27 4ts",
    "addr:street":"Manchester Road",
    "iso:country":"GB",
    "sg:address":"186 Manchester Road, Swinton",
    "sg:city":"Manchester",
    "sg:classifiers":[
        {
            "category":"Home & Garden",
            "subcategory":"Carpets & Floor Coverings",
            "type":"Retail Goods"
        }
    ],
    "sg:phone":"+44 161 794 9615",
    "sg:postcode":"M27 4TS",
    "sg:province":"Greater Manchester",
    "sg:tags":[
        "carpets",
        "retailer",
        "rug",
        "matting"
    ],
    "wof:name":"C C Carpets",
    "wof:placetype":"venue"
},
  "geometry": {"coordinates":[-2.331069,53.511639],"type":"Point"}
}