{
  "type": "Feature",
  "properties": {
    "addr:full":"Thornton House, Cemetry Road, Shelton Stoke-on-trent Staffordshire ST4 2DL",
    "addr:postcode":"st4 2dl",
    "addr:street":"Cemetry Road",
    "iso:country":"GB",
    "sg:address":"Thornton House, Cemetry Road, Shelton",
    "sg:city":"Stoke-on-trent",
    "sg:classifiers":[
        {
            "category":"Professional",
            "subcategory":"Computer Services",
            "type":"Services"
        }
    ],
    "sg:phone":"+44 1782 212939",
    "sg:postcode":"ST4 2DL",
    "sg:province":"Staffordshire",
    "sg:tags":[
        "system",
        "software"
    ],
    "wof:name":"Charmwood Computers Ltd.",
    "wof:placetype":"venue"
},
  "geometry": {"coordinates":[-2.1858229637,53.0142669678],"type":"Point"}
}