{
  "type": "Feature",
  "properties": {
    "addr:full":"39 High Street, Chipping Sodbury Bristol Gloucestershire BS37 6BA",
    "addr:housenumber":"39",
    "addr:postcode":"bs37 6ba",
    "addr:street":"High Street Chipping;Bristol",
    "iso:country":"GB",
    "sg:address":"39 High Street, Chipping Sodbury",
    "sg:city":"Bristol",
    "sg:classifiers":[
        {
            "category":"Banks & Credit Unions",
            "subcategory":"Financial Services",
            "type":"Services"
        }
    ],
    "sg:phone":"+44 1454 327788",
    "sg:postcode":"BS37 6BA",
    "sg:province":"Gloucestershire",
    "sg:tags":[
        "adviser"
    ],
    "wof:name":"Whitehead Group",
    "wof:placetype":"venue"
},
  "geometry": {"coordinates":[-2.394589901,51.5383872986],"type":"Point"}
}