{
  "type": "Feature",
  "properties": {
    "iso:country":"GB",
    "sg:address":"Townbridge House, St Thomas Street",
    "sg:city":"Weymouth",
    "sg:classifiers":[
        {
            "category":"Professional",
            "subcategory":"Employment Agencies",
            "type":"Services"
        }
    ],
    "sg:postcode":"DT4 8TF",
    "sg:province":"Dorset",
    "sg:tags":[
        "consultant"
    ],
    "wof:name":"Weymouth Jobcentre",
    "wof:placetype":"venue"
},
  "geometry": {"coordinates":[-2.455287,50.608128],"type":"Point"}
}