{
  "type": "Feature",
  "properties": {
    "addr:full":"258 High Rd Loughton Essex IG10 1RB",
    "addr:housenumber":"258",
    "addr:postcode":"ig10 1rb",
    "addr:street":"High Rd",
    "iso:country":"GB",
    "sg:address":"258 High Rd",
    "sg:city":"Loughton",
    "sg:classifiers":[
        {
            "category":"Restaurant",
            "type":"Food & Drink"
        }
    ],
    "sg:postcode":"IG10 1RB",
    "sg:province":"Essex",
    "wof:name":"Meze Restaurant",
    "wof:placetype":"venue"
},
  "geometry": {"coordinates":[0.056632,51.649261],"type":"Point"}
}