{
  "type": "Feature",
  "properties": {
    "iso:country":"GB",
    "sg:address":"Brigstock Road",
    "sg:city":"Thornton Heath",
    "sg:classifiers":[
        {
            "category":"Education",
            "subcategory":"Library",
            "type":"Public Place"
        },
        {
            "category":"Government",
            "subcategory":"Office",
            "type":"Public Place"
        }
    ],
    "sg:phone":"+44 20 8684 4432",
    "sg:postcode":"CR7 7JB",
    "sg:province":"Surrey",
    "sg:tags":[
        "book",
        "local"
    ],
    "wof:name":"Thornton Heath Library",
    "wof:placetype":"venue"
},
  "geometry": {"coordinates":[-0.098864,51.398663],"type":"Point"}
}