{
  "type": "Feature",
  "properties": {
    "iso:country":"GB",
    "sg:address":", Inwardleigh",
    "sg:city":"Okehampton",
    "sg:classifiers":[
        {
            "category":"Farming",
            "subcategory":"Farm",
            "type":"Manufacturing & Wholesale Goods"
        }
    ],
    "sg:phone":"+44 1837 55017",
    "sg:postcode":"EX20 3BY",
    "sg:province":"Devon",
    "sg:tags":[
        "egg",
        "producer"
    ],
    "wof:name":"Brook Farm",
    "wof:placetype":"venue"
},
  "geometry": {"coordinates":[-4.0432171822,50.7759208679],"type":"Point"}
}