{
  "type": "Feature",
  "properties": {
    "addr:full":"377-379 Rayners Lane Pinner Greater London HA5 5ER",
    "addr:housenumber":"377-379",
    "addr:postcode":"ha5 5er",
    "addr:street":"Rayners Lane",
    "iso:country":"GB",
    "sg:address":"377-379 Rayners Lane",
    "sg:city":"Pinner",
    "sg:classifiers":[
        {
            "category":"Home & Garden",
            "subcategory":"Hardware",
            "type":"Retail Goods"
        }
    ],
    "sg:phone":"+44 20 8866 9206",
    "sg:postcode":"HA5 5ER",
    "sg:province":"Greater London",
    "sg:tags":[
        "retailer",
        "diy"
    ],
    "wof:name":"Toolbox Diy Centre",
    "wof:placetype":"venue"
},
  "geometry": {"coordinates":[-0.371244,51.576351],"type":"Point"}
}