{
  "type": "Feature",
  "properties": {
    "addr:full":"75a Columbus Way, Walworth Industrial Estate Andover Hampshire SP10 3NP",
    "addr:housenumber":"75a;estate",
    "addr:postcode":"sp10 3np",
    "addr:street":"Columbus Way;Industrial",
    "iso:country":"GB",
    "sg:address":"75a Columbus Way, Walworth Industrial Estate",
    "sg:city":"Andover",
    "sg:classifiers":[
        {
            "category":"Retail",
            "subcategory":"Auto Repair",
            "type":"Services"
        }
    ],
    "sg:phone":"+44 1264 332919",
    "sg:postcode":"SP10 3NP",
    "sg:province":"Hampshire",
    "sg:tags":[
        "bodybuilder",
        "repairer"
    ],
    "wof:name":"J & J Conversions Ltd.",
    "wof:placetype":"venue"
},
  "geometry": {"coordinates":[-1.476779,51.206493],"type":"Point"}
}