{
  "type": "Feature",
  "properties": {
    "addr:full":"St Peters Avenue Sowerby Bridge West Yorkshire HX6 1DL",
    "addr:postcode":"hx6 1dl",
    "addr:street":"St Peters Avenue",
    "iso:country":"GB",
    "sg:address":"St Peters Avenue",
    "sg:city":"Sowerby Bridge",
    "sg:classifiers":[
        {
            "category":"Arena",
            "subcategory":"Sports Club",
            "type":"Entertainment"
        }
    ],
    "sg:phone":"+44 1422 834346",
    "sg:postcode":"HX6 1DL",
    "sg:province":"West Yorkshire",
    "wof:name":"Sowerby St.Peter's Cricket Club",
    "wof:placetype":"venue"
},
  "geometry": {"coordinates":[-1.922715,53.705673],"type":"Point"}
}