{
  "type": "Feature",
  "properties": {
    "addr:full":"141-143 Berridge Road Nottingham Nottinghamshire NG7 6HR",
    "addr:housenumber":"141-143",
    "addr:postcode":"ng7 6hr",
    "addr:street":"Berridge Road",
    "iso:country":"GB",
    "sg:address":"141-143 Berridge Road",
    "sg:city":"Nottingham",
    "sg:classifiers":[
        {
            "category":"Organizations",
            "subcategory":"Membership Organization",
            "type":"Services"
        }
    ],
    "sg:phone":"+44 115 942 0588",
    "sg:postcode":"NG7 6HR",
    "sg:province":"Nottinghamshire",
    "sg:tags":[
        "club"
    ],
    "wof:name":"Madrasah Karinia",
    "wof:placetype":"venue"
},
  "geometry": {"coordinates":[-1.16623,52.970097],"type":"Point"}
}