{
  "type": "Feature",
  "properties": {
    "addr:full":"Southside, Goudhurst Road Cranbrook Kent TN17 2PT",
    "addr:postcode":"tn17 2pt",
    "addr:street":"Goudhurst Road",
    "iso:country":"GB",
    "sg:address":"Southside, Goudhurst Road",
    "sg:city":"Cranbrook",
    "sg:classifiers":[
        {
            "category":"Retail",
            "subcategory":"Auto Repair",
            "type":"Services"
        }
    ],
    "sg:phone":"+44 1580 712418",
    "sg:postcode":"TN17 2PT",
    "sg:province":"Kent",
    "sg:tags":[
        "body",
        "car",
        "repairer"
    ],
    "sg:website":"http://www.brileyo.freeserve.co.uk",
    "wof:name":"Briley Coachworks",
    "wof:placetype":"venue"
},
  "geometry": {"coordinates":[0.5399349928,51.1106262207],"type":"Point"}
}