{
  "type": "Feature",
  "properties": {
    "addr:full":"25 Cave St Oxford Oxfordshire OX4 1DH",
    "addr:housenumber":"25",
    "addr:postcode":"ox4 1dh",
    "addr:street":"Cave St",
    "iso:country":"GB",
    "sg:address":"25 Cave St",
    "sg:city":"Oxford",
    "sg:classifiers":[
        {
            "category":"Real Estate",
            "subcategory":"Architect",
            "type":"Services"
        }
    ],
    "sg:phone":"+44 1865 248636",
    "sg:postcode":"OX4 1DH",
    "sg:province":"Oxfordshire",
    "wof:name":"Thomas Rayson Partnership",
    "wof:placetype":"venue"
},
  "geometry": {"coordinates":[-1.239858,51.752068],"type":"Point"}
}