{
  "type": "Feature",
  "properties": {
    "addr:full":"Queensgate Buss Ctr Inverness Highland IV1 1DW",
    "addr:postcode":"iv1 1dw",
    "addr:street":"Queensgate Buss Ctr",
    "iso:country":"GB",
    "sg:address":"Queensgate Buss Ctr",
    "sg:city":"Inverness",
    "sg:classifiers":[
        {
            "category":"Shopping",
            "subcategory":"Department Store",
            "type":"Retail Goods"
        }
    ],
    "sg:phone":"+44 1463 231777",
    "sg:postcode":"IV1 1DW",
    "sg:province":"Highland",
    "wof:name":"Carnaby Crafts",
    "wof:placetype":"venue"
},
  "geometry": {"coordinates":[-4.225563,57.47953],"type":"Point"}
}