{
  "type": "Feature",
  "properties": {
    "iso:country":"GB",
    "sg:address":"4 Glamis Place",
    "sg:city":"Perth",
    "sg:classifiers":[
        {
            "category":"Retail",
            "subcategory":"Driving School",
            "type":"Services"
        }
    ],
    "sg:phone":"+44 1738 637822",
    "sg:postcode":"PH2 0HP",
    "sg:province":"Perth and Kinross",
    "wof:name":"Impact School of Motoring",
    "wof:placetype":"venue"
},
  "geometry": {"coordinates":[-3.44789,56.387115],"type":"Point"}
}