{
  "type": "Feature",
  "properties": {
    "addr:full":"Rear Of 125 Catford Hill London Greater London SE6 4PR",
    "addr:postcode":"se6 4pr",
    "addr:street":"Catford Hill",
    "iso:country":"GB",
    "sg:address":"Rear Of 125 Catford Hill",
    "sg:city":"London",
    "sg:classifiers":[
        {
            "category":"Home & Garden",
            "subcategory":"Home Furnishings",
            "type":"Retail Goods"
        }
    ],
    "sg:phone":"+44 20 8690 3531",
    "sg:postcode":"SE6 4PR",
    "sg:province":"Greater London",
    "sg:tags":[
        "soft"
    ],
    "wof:name":"Cover to Cover",
    "wof:placetype":"venue"
},
  "geometry": {"coordinates":[-0.03181,51.439529],"type":"Point"}
}