{
  "type": "Feature",
  "properties": {
    "addr:full":"2 Station App Kenley Surrey CR8 5JD",
    "addr:housenumber":"2",
    "addr:postcode":"cr8 5jd",
    "iso:country":"GB",
    "sg:address":"2 Station App",
    "sg:city":"Kenley",
    "sg:classifiers":[
        {
            "category":"Fast Food",
            "type":"Food & Drink"
        }
    ],
    "sg:phone":"+44 20 8660 8088",
    "sg:postcode":"CR8 5JD",
    "sg:province":"Surrey",
    "sg:tags":[
        "away",
        "take"
    ],
    "wof:name":"Mandarin Chinese Takeaway",
    "wof:placetype":"venue"
},
  "geometry": {"coordinates":[-0.1011449993,51.3254547119],"type":"Point"}
}