{
  "type": "Feature",
  "properties": {
    "addr:full":"Eilean Iarmain, An T Eilean Isle Of Skye Highland IV43 8QR",
    "addr:postcode":"iv43 8qr",
    "addr:street":"An T Eilean Isle",
    "iso:country":"GB",
    "sg:address":"Eilean Iarmain, An T Eilean",
    "sg:city":"Isle Of Skye",
    "sg:classifiers":[
        {
            "category":"Food & Beverages",
            "subcategory":"Liquor & Beverages",
            "type":"Retail Goods"
        }
    ],
    "sg:phone":"+44 1471 833266",
    "sg:postcode":"IV43 8QR",
    "sg:province":"Highland",
    "sg:tags":[
        "beer",
        "spirit",
        "wines"
    ],
    "wof:name":"Gaelic Whiskies",
    "wof:placetype":"venue"
},
  "geometry": {"coordinates":[-5.7995700836,57.1455116272],"type":"Point"}
}