{
  "type": "Feature",
  "properties": {
    "addr:full":"6-7 High Street Hungerford Berkshire RG17 0DN",
    "addr:housenumber":"6-7",
    "addr:postcode":"rg17 0dn",
    "addr:street":"High Street",
    "iso:country":"GB",
    "sg:address":"6-7 High Street",
    "sg:city":"Hungerford",
    "sg:classifiers":[
        {
            "category":"Government",
            "subcategory":"Post Office",
            "type":"Public Place"
        }
    ],
    "sg:phone":"+44 1488 682801",
    "sg:postcode":"RG17 0DN",
    "sg:province":"Berkshire",
    "wof:name":"Hungerford Post Office",
    "wof:placetype":"venue"
},
  "geometry": {"coordinates":[-1.5149769783,51.4162139893],"type":"Point"}
}