{
  "type": "Feature",
  "properties": {
    "addr:full":"810 Holderness Rd Hull East Riding of Yorkshire HU9 3LP",
    "addr:housenumber":"810",
    "addr:postcode":"hu9 3lp",
    "addr:street":"Holderness Rd",
    "iso:country":"GB",
    "sg:address":"810 Holderness Rd",
    "sg:city":"Hull",
    "sg:classifiers":[
        {
            "category":"Health Services",
            "subcategory":"Dentist",
            "type":"Services"
        }
    ],
    "sg:phone":"+44 1482 783611",
    "sg:postcode":"HU9 3LP",
    "sg:province":"East Riding of Yorkshire",
    "wof:name":"East Hull Dental Centre The",
    "wof:placetype":"venue"
},
  "geometry": {"coordinates":[-0.286713,53.766815],"type":"Point"}
}