{
  "type": "Feature",
  "properties": {
    "addr:full":"501 Cleveland Street Birkenhead Merseyside CH41 8EF",
    "addr:housenumber":"501",
    "addr:postcode":"ch41 8ef",
    "addr:street":"Cleveland Street",
    "iso:country":"GB",
    "sg:address":"501 Cleveland Street",
    "sg:city":"Birkenhead",
    "sg:classifiers":[
        {
            "category":"Retail",
            "subcategory":"Auto Repair",
            "type":"Services"
        }
    ],
    "sg:postcode":"CH41 8EF",
    "sg:province":"Merseyside",
    "sg:tags":[
        "modification",
        "garage"
    ],
    "wof:name":"R G  Bate (Engineering) Ltd.",
    "wof:placetype":"venue"
},
  "geometry": {"coordinates":[-3.0396130085,53.4007835388],"type":"Point"}
}