{
  "type": "Feature",
  "properties": {
    "addr:full":"Main Rd, Sutton At Hone Dartford Dartford Kent DA4 9HQ",
    "addr:postcode":"da4 9hq",
    "addr:street":"Main Rd",
    "iso:country":"GB",
    "sg:address":"Main Rd, Sutton At Hone Dartford",
    "sg:city":"Dartford",
    "sg:classifiers":[
        {
            "category":"Government",
            "subcategory":"City Hall",
            "type":"Public Place"
        }
    ],
    "sg:phone":"+44 1322 864502",
    "sg:postcode":"DA4 9HQ",
    "sg:province":"Kent",
    "wof:name":"Sutton At Hone Village Hall",
    "wof:placetype":"venue"
},
  "geometry": {"coordinates":[0.2355950028,51.41147995],"type":"Point"}
}