{
  "type": "Feature",
  "properties": {
    "iso:country":"GB",
    "sg:address":"312 Broadmead Road",
    "sg:city":"Woodford Green",
    "sg:classifiers":[
        {
            "category":"Retail",
            "subcategory":"Event Space",
            "type":"Services"
        },
        {
            "category":"Building & Trades",
            "subcategory":"Electrical",
            "type":"Services"
        }
    ],
    "sg:phone":"+44 20 8504 9691",
    "sg:postcode":"IG8 8PG",
    "sg:province":"Essex",
    "sg:tags":[
        "product",
        "lighting",
        "sales"
    ],
    "wof:name":"FLUOREL LTD",
    "wof:placetype":"venue"
},
  "geometry": {"coordinates":[0.044756,51.60075],"type":"Point"}
}