{
  "type": "Feature",
  "properties": {
    "iso:country":"GB",
    "sg:address":"97 Lancaster Pl",
    "sg:city":"Walsall",
    "sg:classifiers":[
        {
            "category":"Building & Trades",
            "subcategory":"Construction",
            "type":"Services"
        }
    ],
    "sg:phone":"+44 1922 403150",
    "sg:postcode":"WS3 3NS",
    "sg:province":"Staffordshire",
    "sg:tags":[
        "guttering"
    ],
    "wof:name":"First Choice",
    "wof:placetype":"venue"
},
  "geometry": {"coordinates":[-1.997005,52.621624],"type":"Point"}
}