{
  "type": "Feature",
  "properties": {
    "addr:full":"62 Alexandra Road Enfield Greater London EN3 7SQ",
    "addr:housenumber":"62",
    "addr:postcode":"en3 7sq",
    "addr:street":"Alexandra Road",
    "iso:country":"GB",
    "sg:address":"62 Alexandra Road",
    "sg:city":"Enfield",
    "sg:classifiers":[
        {
            "category":"Professional",
            "subcategory":"Detective & Security Services",
            "type":"Services"
        }
    ],
    "sg:phone":"+44 20 8539 1544",
    "sg:postcode":"EN3 7SQ",
    "sg:province":"Greater London",
    "sg:tags":[
        "alarm",
        "burglar",
        "system"
    ],
    "wof:name":"Chubb Electronic Security Ltd.",
    "wof:placetype":"venue"
},
  "geometry": {"coordinates":[-0.036816,51.650761],"type":"Point"}
}