{
  "type": "Feature",
  "properties": {
    "addr:full":"Gledrid Industrial Park, Chirk Wrexham Wrexham LL14 5DG",
    "addr:postcode":"ll14 5dg",
    "iso:country":"GB",
    "sg:address":"Gledrid Industrial Park, Chirk",
    "sg:city":"Wrexham",
    "sg:classifiers":[
        {
            "category":"Professional",
            "subcategory":"Computer Services",
            "type":"Services"
        }
    ],
    "sg:phone":"+44 1978 363048",
    "sg:postcode":"LL14 5DG",
    "sg:province":"Wrexham",
    "sg:tags":[
        "system",
        "software"
    ],
    "wof:name":"Calfire Group Ltd.",
    "wof:placetype":"venue"
},
  "geometry": {"coordinates":[-3.0569889545,52.9329566956],"type":"Point"}
}