{
  "type": "Feature",
  "properties": {
    "addr:full":"Salaman House, 23a Hill Street Saffron Walden Cambridgeshire CB10 1EH",
    "addr:housenumber":"23a",
    "addr:postcode":"cb10 1eh",
    "addr:street":"Hill Street",
    "iso:country":"GB",
    "sg:address":"Salaman House, 23a Hill Street",
    "sg:city":"Saffron Walden",
    "sg:classifiers":[
        {
            "category":"Home & Garden",
            "subcategory":"Home Furnishings",
            "type":"Retail Goods"
        },
        {
            "category":"Home & Garden",
            "subcategory":"Building Materials",
            "type":"Retail Goods"
        },
        {
            "category":"Communications",
            "type":"Services"
        }
    ],
    "sg:phone":"+44 1799 522581",
    "sg:postcode":"CB10 1EH",
    "sg:province":"Cambridgeshire",
    "sg:tags":[
        "planner",
        "tv",
        "installers",
        "furnishers",
        "video",
        "radio",
        "kitchen"
    ],
    "wof:name":"Goddards Interiors",
    "wof:placetype":"venue"
},
  "geometry": {"coordinates":[0.242403999,52.0231323242],"type":"Point"}
}