{
  "type": "Feature",
  "properties": {
    "addr:full":"27 The Green, Ickwell Biggleswade Bedfordshire SG18 9EE",
    "addr:housenumber":"27",
    "addr:postcode":"sg18 9ee",
    "addr:street":"The Green Ickwell",
    "iso:country":"GB",
    "sg:address":"27 The Green, Ickwell",
    "sg:city":"Biggleswade",
    "sg:classifiers":[
        {
            "category":"Professional",
            "subcategory":"Advertising",
            "type":"Services"
        }
    ],
    "sg:phone":"+44 1767 626386",
    "sg:postcode":"SG18 9EE",
    "sg:province":"Bedfordshire",
    "wof:name":"S M Advertising",
    "wof:placetype":"venue"
},
  "geometry": {"coordinates":[-0.300176,52.09734],"type":"Point"}
}