{
  "type": "Feature",
  "properties": {
    "addr:full":"27 Oldham Rd Rochdale Lancashire OL16 1UA",
    "addr:housenumber":"27",
    "addr:postcode":"ol16 1ua",
    "addr:street":"Oldham Rd",
    "iso:country":"GB",
    "sg:address":"27 Oldham Rd",
    "sg:city":"Rochdale",
    "sg:classifiers":[
        {
            "category":"Fast Food",
            "type":"Food & Drink"
        }
    ],
    "sg:phone":"+44 1706 631876",
    "sg:postcode":"OL16 1UA",
    "sg:province":"Lancashire",
    "sg:tags":[
        "away",
        "take"
    ],
    "wof:name":"Eastern Delight",
    "wof:placetype":"venue"
},
  "geometry": {"coordinates":[-2.1527318954,53.6144561768],"type":"Point"}
}