{
  "type": "Feature",
  "properties": {
    "addr:full":"11 Harley Shute Rd St Leonards On Sea East Sussex TN38 8BP",
    "addr:housenumber":"11",
    "addr:postcode":"tn38 8bp",
    "addr:street":"Harley Shute Rd St",
    "iso:country":"GB",
    "sg:address":"11 Harley Shute Rd",
    "sg:city":"St Leonards On Sea",
    "sg:classifiers":[
        {
            "category":"Recreation",
            "subcategory":"Dog Park",
            "type":"Entertainment"
        }
    ],
    "sg:phone":"+44 1424 428104",
    "sg:postcode":"TN38 8BP",
    "sg:province":"East Sussex",
    "wof:name":"All Breeds Canine Groomer",
    "wof:placetype":"venue"
},
  "geometry": {"coordinates":[0.526599,50.851963],"type":"Point"}
}