{
  "type": "Feature",
  "properties": {
    "addr:full":"Longford St Surgery, Longford St Warrington Cheshire WA2 7QZ",
    "addr:postcode":"wa2 7qz",
    "addr:street":"Longford;Longford St",
    "iso:country":"GB",
    "sg:address":"Longford St Surgery, Longford St",
    "sg:city":"Warrington",
    "sg:classifiers":[
        {
            "category":"Health Services",
            "subcategory":"Doctor",
            "type":"Services"
        }
    ],
    "sg:phone":"+44 1925 255600",
    "sg:postcode":"WA2 7QZ",
    "sg:province":"Cheshire",
    "sg:tags":[
        "practitioners"
    ],
    "wof:name":"Drs O'Colmain Watson Sokhi Horton Walton & Carr",
    "wof:placetype":"venue"
},
  "geometry": {"coordinates":[-2.591254,53.399574],"type":"Point"}
}