{
  "type": "Feature",
  "properties": {
    "addr:full":"2 Claremont Rd Surbiton Surrey KT6 4QX",
    "addr:housenumber":"2",
    "addr:postcode":"kt6 4qx",
    "addr:street":"Claremont Rd",
    "iso:country":"GB",
    "sg:address":"2 Claremont Rd",
    "sg:city":"Surbiton",
    "sg:classifiers":[
        {
            "category":"Professional",
            "subcategory":"Computer Services",
            "type":"Services"
        }
    ],
    "sg:phone":"+44 1483 418948",
    "sg:postcode":"KT6 4QX",
    "sg:province":"Surrey",
    "sg:tags":[
        "consultant"
    ],
    "wof:name":"IT Benchmarking User Group",
    "wof:placetype":"venue"
},
  "geometry": {"coordinates":[-0.304197,51.393353],"type":"Point"}
}