{
  "type": "Feature",
  "properties": {
    "addr:full":"2 Court Road Gloucester Gloucestershire GL3 4EP",
    "addr:housenumber":"2",
    "addr:postcode":"gl3 4ep",
    "addr:street":"Court Road",
    "iso:country":"GB",
    "sg:address":"2 Court Road",
    "sg:city":"Gloucester",
    "sg:classifiers":[
        {
            "category":"Fast Food",
            "type":"Food & Drink"
        },
        {
            "category":"Food & Beverages",
            "subcategory":"Meat & Fish",
            "type":"Retail Goods"
        }
    ],
    "sg:phone":"+44 1452 863911",
    "sg:postcode":"GL3 4EP",
    "sg:province":"Gloucestershire",
    "sg:tags":[
        "chip",
        "away",
        "take"
    ],
    "wof:name":"Motty's",
    "wof:placetype":"venue"
},
  "geometry": {"coordinates":[-2.1591479778,51.8466072083],"type":"Point"}
}