{
  "type": "Feature",
  "properties": {
    "addr:full":"248 Kilmarnock Rd Glasgow Glasgow City G43 1TT",
    "addr:housenumber":"248",
    "addr:postcode":"g43 1tt",
    "addr:street":"Kilmarnock Rd",
    "iso:country":"GB",
    "sg:address":"248 Kilmarnock Rd",
    "sg:city":"Glasgow",
    "sg:classifiers":[
        {
            "category":"Shopping",
            "subcategory":"Bicycles & Sporting Goods",
            "type":"Retail Goods"
        }
    ],
    "sg:phone":"+44 141 632 7441",
    "sg:postcode":"G43 1TT",
    "sg:province":"Glasgow City",
    "sg:tags":[
        "cycle",
        "accessory"
    ],
    "wof:name":"Thomson Cycles",
    "wof:placetype":"venue"
},
  "geometry": {"coordinates":[-4.286064,55.82552],"type":"Point"}
}