{
  "type": "Feature",
  "properties": {
    "iso:country":"GB",
    "sg:address":"New Art Shop, Suffolk College, Rope Walk",
    "sg:city":"Ipswich",
    "sg:classifiers":[
        {
            "category":"Shopping",
            "subcategory":"Crafts & Fabrics",
            "type":"Retail Goods"
        }
    ],
    "sg:postcode":"IP4 1LT",
    "sg:province":"Suffolk",
    "sg:tags":[
        "material",
        "graphic",
        "art"
    ],
    "wof:name":"Hussey & Greaves Ltd",
    "wof:placetype":"venue"
},
  "geometry": {"coordinates":[1.1647800207,52.0547218323],"type":"Point"}
}