{
  "type": "Feature",
  "properties": {
    "iso:country":"GB",
    "sg:address":"52 Junction Road",
    "sg:city":"Burgess Hill",
    "sg:classifiers":[
        {
            "category":"Home & Garden",
            "subcategory":"Hardware",
            "type":"Retail Goods"
        },
        {
            "category":"Home & Garden",
            "subcategory":"Carpets & Floor Coverings",
            "type":"Retail Goods"
        }
    ],
    "sg:phone":"+44 1444 244491",
    "sg:postcode":"RH15 0JN",
    "sg:province":"East Sussex",
    "sg:tags":[
        "lawnmowers",
        "sales",
        "machinery"
    ],
    "wof:name":"Sussex Garden Machinery",
    "wof:placetype":"venue"
},
  "geometry": {"coordinates":[-0.120479,50.96323],"type":"Point"}
}