{
  "type": "Feature",
  "properties": {
    "addr:full":"Unit 9, Wollescote Factory Cntr Stourbridge West Midlands DY9 8TF",
    "addr:housenumber":"unit 9",
    "addr:postcode":"dy9 8tf",
    "iso:country":"GB",
    "sg:address":"Unit 9, Wollescote Factory Cntr",
    "sg:city":"Stourbridge",
    "sg:classifiers":[
        {
            "category":"Autos & Motor Vehicles",
            "subcategory":"Auto Supplies",
            "type":"Retail Goods"
        }
    ],
    "sg:postcode":"DY9 8TF",
    "sg:province":"West Midlands",
    "sg:tags":[
        "electric"
    ],
    "wof:name":"B L M Rewinds",
    "wof:placetype":"venue"
},
  "geometry": {"coordinates":[-2.1086199284,52.4545593262],"type":"Point"}
}