{
  "type": "Feature",
  "properties": {
    "iso:country":"GB",
    "sg:address":"15 Lint Brae, Stewarton",
    "sg:city":"Kilmarnock",
    "sg:classifiers":[
        {
            "category":"Professional",
            "subcategory":"Engineering",
            "type":"Services"
        }
    ],
    "sg:phone":"+44 1560 483147",
    "sg:postcode":"KA3 5PB",
    "sg:province":"East Ayrshire",
    "sg:tags":[
        "contractor",
        "electrical",
        "engineer"
    ],
    "wof:name":"J & K Electrical",
    "wof:placetype":"venue"
},
  "geometry": {"coordinates":[-4.50735,55.682358],"type":"Point"}
}