{
  "type": "Feature",
  "properties": {
    "iso:country":"GB",
    "sg:address":"80a Condor Gro",
    "sg:city":"Blackpool",
    "sg:classifiers":[
        {
            "category":"Building & Trades",
            "subcategory":"Construction",
            "type":"Services"
        }
    ],
    "sg:postcode":"FY1 5LT",
    "sg:province":"Lancashire",
    "sg:tags":[
        "decorator",
        "painter"
    ],
    "wof:name":"Darren Beckman",
    "wof:placetype":"venue"
},
  "geometry": {"coordinates":[-3.037694931,53.8082046509],"type":"Point"}
}