{
  "type": "Feature",
  "properties": {
    "addr:full":"6 Tower Hill Terrace London Greater London EC3N 4EE",
    "addr:housenumber":"6",
    "addr:postcode":"ec3n 4ee",
    "addr:street":"Tower Hill Terrace",
    "iso:country":"GB",
    "sg:address":"6 Tower Hill Terrace",
    "sg:city":"London",
    "sg:classifiers":[
        {
            "category":"Shopping",
            "subcategory":"Event Tickets",
            "type":"Retail Goods"
        }
    ],
    "sg:phone":"+44 20 7702 9878",
    "sg:postcode":"EC3N 4EE",
    "sg:province":"Greater London",
    "sg:tags":[
        "agency"
    ],
    "wof:name":"Ticket World",
    "wof:placetype":"venue"
},
  "geometry": {"coordinates":[-0.0737790018,51.5094108582],"type":"Point"}
}