{
  "type": "Feature",
  "properties": {
    "iso:country":"GB",
    "sg:address":"The Cedars, Farmfield Lane, Nash",
    "sg:city":"Newport",
    "sg:classifiers":[
        {
            "category":"Professional",
            "subcategory":"Detective & Security Services",
            "type":"Services"
        },
        {
            "category":"Building & Trades",
            "subcategory":"Electrical",
            "type":"Services"
        }
    ],
    "sg:phone":"+44 1633 272754",
    "sg:postcode":"NP18 2AR",
    "sg:province":"Monmouthshire",
    "sg:tags":[
        "burglar",
        "alarm",
        "electrician",
        "system",
        "contractor"
    ],
    "wof:name":"RHIWDERIN ELECTRICAL SERVICES",
    "wof:placetype":"venue"
},
  "geometry": {"coordinates":[-2.9468729496,51.54895401],"type":"Point"}
}