{
  "type": "Feature",
  "properties": {
    "addr:full":"Town Wall House, 4 Balkerne Hill Colchester Essex CO3 3AD",
    "addr:housenumber":"4",
    "addr:postcode":"co3 3ad",
    "addr:street":"House;Balkerne Hill Colchester",
    "iso:country":"GB",
    "sg:address":"Town Wall House, 4 Balkerne Hill",
    "sg:city":"Colchester",
    "sg:classifiers":[
        {
            "category":"Professional",
            "subcategory":"Business Services",
            "type":"Services"
        }
    ],
    "sg:phone":"+44 1621 828754",
    "sg:postcode":"CO3 3AD",
    "sg:province":"Essex",
    "sg:tags":[
        "holding"
    ],
    "wof:name":"Corporation Holdings Ltd",
    "wof:placetype":"venue"
},
  "geometry": {"coordinates":[0.89388,51.887901],"type":"Point"}
}