{
  "type": "Feature",
  "properties": {
    "addr:full":"Vine Cottage, Lower Slaughter Cheltenham Gloucestershire GL54 2HS",
    "addr:postcode":"gl54 2hs",
    "iso:country":"GB",
    "sg:address":"Vine Cottage, Lower Slaughter",
    "sg:city":"Cheltenham",
    "sg:classifiers":[
        {
            "category":"Professional",
            "subcategory":"Management & Consulting",
            "type":"Services"
        }
    ],
    "sg:postcode":"GL54 2HS",
    "sg:province":"Gloucestershire",
    "sg:tags":[
        "consultant",
        "business"
    ],
    "wof:name":"Plassey Ltd",
    "wof:placetype":"venue"
},
  "geometry": {"coordinates":[-1.7612589598,51.9014205933],"type":"Point"}
}