{
  "type": "Feature",
  "properties": {
    "addr:full":"10 Morkinshire Lane, Cotgrave Nottingham Nottinghamshire NG12 3HJ",
    "addr:housenumber":"10",
    "addr:postcode":"ng12 3hj",
    "addr:street":"Morkinshire Lane",
    "iso:country":"GB",
    "sg:address":"10 Morkinshire Lane, Cotgrave",
    "sg:city":"Nottingham",
    "sg:classifiers":[
        {
            "category":"Shopping",
            "subcategory":"Photographic Equipment",
            "type":"Retail Goods"
        }
    ],
    "sg:phone":"+44 115 989 3336",
    "sg:postcode":"NG12 3HJ",
    "sg:province":"Nottinghamshire",
    "wof:name":"Deborah Mears Photography",
    "wof:placetype":"venue"
},
  "geometry": {"coordinates":[-1.042425,52.913517],"type":"Point"}
}