{
  "type": "Feature",
  "properties": {
    "addr:full":"101a Meeting Street, Quorn Loughborough Leicestershire LE12 8AQ",
    "addr:housenumber":"101a",
    "addr:postcode":"le12 8aq",
    "addr:street":"Meeting Street",
    "iso:country":"GB",
    "sg:address":"101a Meeting Street, Quorn",
    "sg:city":"Loughborough",
    "sg:classifiers":[
        {
            "category":"Retail",
            "subcategory":"Funeral Services",
            "type":"Services"
        }
    ],
    "sg:phone":"+44 1509 415415",
    "sg:postcode":"LE12 8AQ",
    "sg:province":"Leicestershire",
    "wof:name":"G Gamble & Sons (Quorn) Ltd.",
    "wof:placetype":"venue"
},
  "geometry": {"coordinates":[-1.174961,52.741283],"type":"Point"}
}