{
  "type": "Feature",
  "properties": {
    "addr:full":"6 Warley Hill Brentwood Essex CM14 5EZ",
    "addr:housenumber":"6",
    "addr:postcode":"cm14 5ez",
    "addr:street":"Warley Hill",
    "iso:country":"GB",
    "sg:address":"6 Warley Hill",
    "sg:city":"Brentwood",
    "sg:classifiers":[
        {
            "category":"Food & Beverages",
            "subcategory":"Fruits & Vegetables",
            "type":"Retail Goods"
        }
    ],
    "sg:phone":"+44 1277 223336",
    "sg:postcode":"CM14 5EZ",
    "sg:province":"Essex",
    "sg:tags":[
        "greengrocer"
    ],
    "wof:name":"John Cooper",
    "wof:placetype":"venue"
},
  "geometry": {"coordinates":[0.29696,51.606499],"type":"Point"}
}