{
  "type": "Feature",
  "properties": {
    "addr:full":"Unit 1, South Bridge Road Northampton Northamptonshire NN4 8DD",
    "addr:housenumber":"unit 1",
    "addr:postcode":"nn4 8dd",
    "addr:street":"South Bridge Road",
    "iso:country":"GB",
    "sg:address":"Unit 1, South Bridge Road",
    "sg:city":"Northampton",
    "sg:classifiers":[
        {
            "category":"Manufacturing",
            "subcategory":"Metals",
            "type":"Manufacturing & Wholesale Goods"
        }
    ],
    "sg:phone":"+44 1604 767979",
    "sg:postcode":"NN4 8DD",
    "sg:province":"Northamptonshire",
    "sg:tags":[
        "work",
        "sheet"
    ],
    "wof:name":"G Burditt & Co. Ltd.",
    "wof:placetype":"venue"
},
  "geometry": {"coordinates":[-0.9076600075,52.2224197388],"type":"Point"}
}