{
  "type": "Feature",
  "properties": {
    "iso:country":"GB",
    "sg:address":"St Margarets Road, Ward End",
    "sg:city":"Birmingham",
    "sg:classifiers":[
        {
            "category":"Autos & Motor Vehicles",
            "subcategory":"Auto Supplies",
            "type":"Retail Goods"
        }
    ],
    "sg:phone":"+44 121 327 1815",
    "sg:postcode":"B8 2BA",
    "sg:province":"West Midlands",
    "sg:tags":[
        "tyre"
    ],
    "wof:name":"Chequered Flag",
    "wof:placetype":"venue"
},
  "geometry": {"coordinates":[-1.824,52.497814],"type":"Point"}
}