{
  "type": "Feature",
  "properties": {
    "iso:country":"GB",
    "sg:address":"Main St",
    "sg:city":"Thornhill",
    "sg:classifiers":[
        {
            "category":"Food & Beverages",
            "subcategory":"Supermarket",
            "type":"Retail Goods"
        }
    ],
    "sg:postcode":"DG3 4BP",
    "sg:province":"Dumfries and Galloway",
    "wof:name":"Rash,G & G,",
    "wof:placetype":"venue"
},
  "geometry": {"coordinates":[-3.814239,55.232555],"type":"Point"}
}