{
  "type": "Feature",
  "properties": {
    "iso:country":"GB",
    "sg:address":"6 Bullough St, Atherton",
    "sg:city":"Manchester",
    "sg:classifiers":[
        {
            "category":"Retail",
            "subcategory":"Funeral Services",
            "type":"Services"
        }
    ],
    "sg:phone":"+44 1942 882896",
    "sg:postcode":"M46 0DL",
    "sg:province":"Greater Manchester",
    "wof:name":"Family Funerals Trust Ltd",
    "wof:placetype":"venue"
},
  "geometry": {"coordinates":[-2.496162,53.522915],"type":"Point"}
}