{
  "type": "Feature",
  "properties": {
    "addr:full":"The Business Station, Castle Street Merthyr Tydfil Merthyr Tydfil CF47 8BB",
    "addr:postcode":"cf47 8bb",
    "addr:street":"Castle Street",
    "iso:country":"GB",
    "sg:address":"The Business Station, Castle Street",
    "sg:city":"Merthyr Tydfil",
    "sg:classifiers":[
        {
            "category":"Organizations",
            "subcategory":"Non-profit Organization",
            "type":"Services"
        }
    ],
    "sg:postcode":"CF47 8BB",
    "sg:province":"Merthyr Tydfil",
    "sg:tags":[
        "organisation",
        "voluntary",
        "charity"
    ],
    "wof:name":"Safer Merthyr Tydfil Ltd.",
    "wof:placetype":"venue"
},
  "geometry": {"coordinates":[-3.376464,51.750439],"type":"Point"}
}