{
  "type": "Feature",
  "properties": {
    "iso:country":"GB",
    "sg:address":"Rhiwgan",
    "sg:city":"Llanbrynmair",
    "sg:classifiers":[
        {
            "category":"Farming",
            "subcategory":"Farm",
            "type":"Manufacturing & Wholesale Goods"
        }
    ],
    "sg:phone":"+44 1650 521341",
    "sg:postcode":"SY19 7AP",
    "sg:province":"Powys",
    "sg:tags":[
        "mixed",
        "crop"
    ],
    "wof:name":"E W Roberts",
    "wof:placetype":"venue"
},
  "geometry": {"coordinates":[-3.636218,52.585739],"type":"Point"}
}