{
  "type": "Feature",
  "properties": {
    "addr:full":"Upper Orchard, Hoarwithy Hereford Herefordshire HR2 6QR",
    "addr:postcode":"hr2 6qr",
    "addr:street":"Upper",
    "iso:country":"GB",
    "sg:address":"Upper Orchard, Hoarwithy",
    "sg:city":"Hereford",
    "sg:classifiers":[
        {
            "category":"Food & Beverages",
            "subcategory":"Liquor & Beverages",
            "type":"Retail Goods"
        }
    ],
    "sg:phone":"+44 1432 840649",
    "sg:postcode":"HR2 6QR",
    "sg:province":"Herefordshire",
    "sg:tags":[
        "beer",
        "spirit",
        "wines"
    ],
    "wof:name":"Jon Hurley Wineweekends",
    "wof:placetype":"venue"
},
  "geometry": {"coordinates":[-2.662411,51.960346],"type":"Point"}
}