{
  "type": "Feature",
  "properties": {
    "addr:full":"16 Mount Pleasant Road Tonbridge Kent TN1 1QU",
    "addr:housenumber":"16",
    "addr:postcode":"tn1 1qu",
    "addr:street":"Mount Pleasant Road",
    "iso:country":"GB",
    "sg:address":"16 Mount Pleasant Road",
    "sg:city":"Tonbridge",
    "sg:classifiers":[
        {
            "category":"Professional",
            "subcategory":"Lawyer & Legal Services",
            "type":"Services"
        }
    ],
    "sg:phone":"+44 1892 539379",
    "sg:postcode":"TN1 1QU",
    "sg:province":"Kent",
    "sg:tags":[
        "solicitor"
    ],
    "wof:name":"Max Barford & Co.",
    "wof:placetype":"venue"
},
  "geometry": {"coordinates":[0.2432,51.216389],"type":"Point"}
}