{
  "type": "Feature",
  "properties": {
    "addr:full":"25 Barkhill Road Chester Cheshire CH3 5JQ",
    "addr:housenumber":"25",
    "addr:postcode":"ch3 5jq",
    "addr:street":"Barkhill Road",
    "iso:country":"GB",
    "sg:address":"25 Barkhill Road",
    "sg:city":"Chester",
    "sg:classifiers":[
        {
            "category":"Building & Trades",
            "subcategory":"Plumbing",
            "type":"Services"
        }
    ],
    "sg:phone":"+44 1244 340051",
    "sg:postcode":"CH3 5JQ",
    "sg:province":"Cheshire",
    "sg:tags":[
        "drain",
        "clearance",
        "sewer"
    ],
    "wof:name":"Geoffrey Powell",
    "wof:placetype":"venue"
},
  "geometry": {"coordinates":[-2.8627700806,53.1966781616],"type":"Point"}
}