{
  "type": "Feature",
  "properties": {
    "iso:country":"GB",
    "sg:address":"188 Foundry Lane",
    "sg:city":"Southampton",
    "sg:classifiers":[
        {
            "category":"Personal",
            "subcategory":"Beauty Salon",
            "type":"Services"
        }
    ],
    "sg:phone":"+44 23 8070 4426",
    "sg:postcode":"SO15 3LE",
    "sg:province":"Hampshire",
    "sg:tags":[
        "unisex",
        "hairdresser"
    ],
    "wof:name":"Origin",
    "wof:placetype":"venue"
},
  "geometry": {"coordinates":[-1.43281,50.916325],"type":"Point"}
}