{
  "type": "Feature",
  "properties": {
    "addr:full":"107 Sandwich Road, Whitfield Dover Kent CT16 3JP",
    "addr:housenumber":"107",
    "addr:postcode":"ct16 3jp",
    "addr:street":"Sandwich Road;Dover",
    "iso:country":"GB",
    "sg:address":"107 Sandwich Road, Whitfield",
    "sg:city":"Dover",
    "sg:classifiers":[
        {
            "category":"Social Services",
            "subcategory":"Retirement Home",
            "type":"Services"
        }
    ],
    "sg:phone":"+44 1304 820236",
    "sg:postcode":"CT16 3JP",
    "sg:province":"Kent",
    "sg:tags":[
        "residential",
        "care"
    ],
    "wof:name":"Whitfield Rest Home",
    "wof:placetype":"venue"
},
  "geometry": {"coordinates":[1.2901890278,51.1633758545],"type":"Point"}
}