{
  "type": "Feature",
  "properties": {
    "iso:country":"GB",
    "sg:address":"21 High Street, Highworth",
    "sg:city":"Swindon",
    "sg:classifiers":[
        {
            "category":"Retail",
            "subcategory":"Veterinary Services",
            "type":"Services"
        }
    ],
    "sg:phone":"+44 1793 765335",
    "sg:postcode":"SN6 7AG",
    "sg:province":"Gloucestershire",
    "sg:tags":[
        "surgeon"
    ],
    "wof:name":"Archway Veterinary Surgery",
    "wof:placetype":"venue"
},
  "geometry": {"coordinates":[-1.7103589773,51.6304473877],"type":"Point"}
}