{
  "type": "Feature",
  "properties": {
    "iso:country":"GB",
    "sg:address":"Meadow View, Churchend, Twyning",
    "sg:city":"Tewkesbury",
    "sg:classifiers":[
        {
            "category":"Building & Trades",
            "subcategory":"Construction",
            "type":"Services"
        }
    ],
    "sg:phone":"+44 1684 294474",
    "sg:postcode":"GL20 6DA",
    "sg:province":"Gloucestershire",
    "sg:tags":[
        "builder"
    ],
    "wof:name":"G R Williams",
    "wof:placetype":"venue"
},
  "geometry": {"coordinates":[-2.149463,51.992958],"type":"Point"}
}