{
  "type": "Feature",
  "properties": {
    "addr:full":"101 St Huberts Rd Blackburn Lancashire BB6 7AF",
    "addr:housenumber":"101",
    "addr:postcode":"bb6 7af",
    "addr:street":"St Huberts Rd",
    "iso:country":"GB",
    "sg:address":"101 St Huberts Rd",
    "sg:city":"Blackburn",
    "sg:classifiers":[
        {
            "category":"Food & Beverages",
            "subcategory":"Fruits & Vegetables",
            "type":"Retail Goods"
        }
    ],
    "sg:phone":"+44 1254 884735",
    "sg:postcode":"BB6 7AF",
    "sg:province":"Lancashire",
    "sg:tags":[
        "greengrocer"
    ],
    "wof:name":"N & A Harris",
    "wof:placetype":"venue"
},
  "geometry": {"coordinates":[-2.4047079086,53.7836151123],"type":"Point"}
}