{
  "type": "Feature",
  "properties": {
    "iso:country":"GB",
    "sg:address":"17 Market Place",
    "sg:city":"Southwell",
    "sg:classifiers":[
        {
            "category":"Real Estate",
            "subcategory":"Real Estate Agent",
            "type":"Services"
        }
    ],
    "sg:phone":"+44 1636 813971",
    "sg:postcode":"NG25 0HE",
    "sg:province":"Nottinghamshire",
    "wof:name":"Alasdair Morrison Chartered Surveyors",
    "wof:placetype":"venue"
},
  "geometry": {"coordinates":[-0.955291,53.077969],"type":"Point"}
}