{
  "type": "Feature",
  "properties": {
    "iso:country":"GB",
    "sg:address":"Hale Farm, Back Lane, Herriard",
    "sg:city":"Basingstoke",
    "sg:classifiers":[
        {
            "category":"Farming",
            "subcategory":"Farm",
            "type":"Manufacturing & Wholesale Goods"
        }
    ],
    "sg:phone":"+44 1256 381245",
    "sg:postcode":"RG25 2PS",
    "sg:province":"Hampshire",
    "sg:tags":[
        "mixed",
        "crop"
    ],
    "wof:name":"Jack Earwaker",
    "wof:placetype":"venue"
},
  "geometry": {"coordinates":[-1.044324,51.203754],"type":"Point"}
}