{
  "type": "Feature",
  "properties": {
    "addr:full":"152 High Street Deal Kent CT14 6BG",
    "addr:housenumber":"152",
    "addr:postcode":"ct14 6bg",
    "addr:street":"High Street Deal",
    "iso:country":"GB",
    "sg:address":"152 High Street",
    "sg:city":"Deal",
    "sg:classifiers":[
        {
            "category":"Education",
            "subcategory":"Library",
            "type":"Public Place"
        }
    ],
    "sg:phone":"+44 1304 375513",
    "sg:postcode":"CT14 6BG",
    "sg:province":"Kent",
    "sg:tags":[
        "reproduction",
        "furniture"
    ],
    "wof:name":"Ferriers House",
    "wof:placetype":"venue"
},
  "geometry": {"coordinates":[1.4027119875,51.2272262573],"type":"Point"}
}