{
  "type": "Feature",
  "properties": {
    "iso:country":"GB",
    "sg:address":"Glasshouse Farm, Gorsty Hill",
    "sg:city":"Uttoxeter",
    "sg:classifiers":[
        {
            "category":"Farming",
            "subcategory":"Livestock Farm",
            "type":"Manufacturing & Wholesale Goods"
        }
    ],
    "sg:phone":"+44 1889 562160",
    "sg:postcode":"ST14 8PH",
    "sg:province":"Derbyshire",
    "sg:tags":[
        "others"
    ],
    "wof:name":"J W Backhouse & Sons",
    "wof:placetype":"venue"
},
  "geometry": {"coordinates":[-1.85247,52.858532],"type":"Point"}
}