{
  "type": "Feature",
  "properties": {
    "addr:full":"70 High Street, Wickham Market Woodbridge Suffolk IP13 0QU",
    "addr:housenumber":"70",
    "addr:postcode":"ip13 0qu",
    "addr:street":"High Street",
    "iso:country":"GB",
    "sg:address":"70 High Street, Wickham Market",
    "sg:city":"Woodbridge",
    "sg:classifiers":[
        {
            "category":"Restaurant",
            "type":"Food & Drink"
        }
    ],
    "sg:phone":"+44 1728 747767",
    "sg:postcode":"IP13 0QU",
    "sg:province":"Suffolk",
    "sg:tags":[
        "indian",
        "-"
    ],
    "wof:name":"Bengal Tandoori Restaurant",
    "wof:placetype":"venue"
},
  "geometry": {"coordinates":[1.3631520271,52.15259552],"type":"Point"}
}