{
  "type": "Feature",
  "properties": {
    "addr:full":"3 Ellesmere Rd Morecambe Lancashire LA4 4JJ",
    "addr:housenumber":"3",
    "addr:postcode":"la4 4jj",
    "addr:street":"Ellesmere Rd",
    "iso:country":"GB",
    "sg:address":"3 Ellesmere Rd",
    "sg:city":"Morecambe",
    "sg:classifiers":[
        {
            "category":"Retail",
            "subcategory":"Auto Repair",
            "type":"Services"
        }
    ],
    "sg:phone":"+44 1524 416482",
    "sg:postcode":"LA4 4JJ",
    "sg:province":"Lancashire",
    "sg:tags":[
        "car",
        "upholsterer"
    ],
    "wof:name":"Total Valeting",
    "wof:placetype":"venue"
},
  "geometry": {"coordinates":[-2.8759539127,54.0659294128],"type":"Point"}
}