{
  "type": "Feature",
  "properties": {
    "iso:country":"GB",
    "sg:address":"Wallsgreen Road, Cardenden",
    "sg:city":"Lochgelly",
    "sg:classifiers":[
        {
            "category":"Health Services",
            "subcategory":"Doctor",
            "type":"Services"
        }
    ],
    "sg:phone":"+44 1592 722441",
    "sg:postcode":"KY5 0JE",
    "sg:province":"Fife",
    "sg:tags":[
        "practitioners"
    ],
    "wof:name":"M A RAHMAN",
    "wof:placetype":"venue"
},
  "geometry": {"coordinates":[-3.263912,56.147362],"type":"Point"}
}