{
  "type": "Feature",
  "properties": {
    "iso:country":"GB",
    "sg:address":"62 Godwin Street",
    "sg:city":"Bradford",
    "sg:classifiers":[
        {
            "category":"Home & Garden",
            "subcategory":"Furniture",
            "type":"Retail Goods"
        }
    ],
    "sg:phone":"+44 1274 390260",
    "sg:postcode":"BD1 2SD",
    "sg:province":"West Yorkshire",
    "wof:name":"Walmsleys Suite Superstore",
    "wof:placetype":"venue"
},
  "geometry": {"coordinates":[-1.756256,53.794529],"type":"Point"}
}