{
  "type": "Feature",
  "properties": {
    "addr:full":"164 Southampton Road, Titchfield Fareham Hampshire PO14 4PP",
    "addr:housenumber":"164",
    "addr:postcode":"po14 4pp",
    "addr:street":"Southampton Road",
    "iso:country":"GB",
    "sg:address":"164 Southampton Road, Titchfield",
    "sg:city":"Fareham",
    "sg:classifiers":[
        {
            "category":"Autos & Motor Vehicles",
            "subcategory":"Fuel & Gas Station",
            "type":"Retail Goods"
        }
    ],
    "sg:phone":"+44 1489 589056",
    "sg:postcode":"PO14 4PP",
    "sg:province":"Hampshire",
    "sg:tags":[
        "petrol",
        "filling"
    ],
    "wof:name":"Pie and Cafe",
    "wof:placetype":"venue"
},
  "geometry": {"coordinates":[-1.254439,50.862347],"type":"Point"}
}