{
  "type": "Feature",
  "properties": {
    "addr:full":"Broadcoombe South Croydon Surrey CR2 8HX",
    "addr:postcode":"cr2 8hx",
    "iso:country":"GB",
    "sg:address":"Broadcoombe",
    "sg:city":"South Croydon",
    "sg:classifiers":[
        {
            "category":"Organizations",
            "subcategory":"Community Association",
            "type":"Services"
        },
        {
            "category":"Organizations",
            "subcategory":"Membership Organization",
            "type":"Services"
        }
    ],
    "sg:phone":"+44 20 8657 1099",
    "sg:postcode":"CR2 8HX",
    "sg:province":"Surrey",
    "sg:tags":[
        "club",
        "social"
    ],
    "wof:name":"Croydon Irish Association",
    "wof:placetype":"venue"
},
  "geometry": {"coordinates":[-0.055482,51.352562],"type":"Point"}
}