{
  "type": "Feature",
  "properties": {
    "iso:country":"GB",
    "sg:address":"30 Wyldfield Gardens",
    "sg:city":"London",
    "sg:classifiers":[
        {
            "category":"Professional",
            "type":"Services"
        },
        {
            "category":"Professional",
            "subcategory":"Art Services",
            "type":"Services"
        }
    ],
    "sg:phone":"+44 20 8350 6352",
    "sg:postcode":"N9 9NY",
    "sg:province":"Greater London",
    "sg:tags":[
        "interior",
        "furnishers",
        "designer"
    ],
    "wof:name":"Calico Interior Decorators",
    "wof:placetype":"venue"
},
  "geometry": {"coordinates":[-0.068302,51.627453],"type":"Point"}
}