{
  "type": "Feature",
  "properties": {
    "iso:country":"GB",
    "sg:address":"110 High Street",
    "sg:city":"Bromsgrove",
    "sg:classifiers":[
        {
            "category":"Deli",
            "type":"Food & Drink"
        }
    ],
    "sg:phone":"+44 1527 872927",
    "sg:postcode":"B61 8HA",
    "sg:province":"Worcestershire",
    "sg:tags":[
        "delicatessen"
    ],
    "wof:name":"Rainscourt Ltd.",
    "wof:placetype":"venue"
},
  "geometry": {"coordinates":[-2.059867,52.335541],"type":"Point"}
}