{
  "type": "Feature",
  "properties": {
    "addr:full":"Ross Road Hereford Herefordshire HR2 8HY",
    "addr:postcode":"hr2 8hy",
    "addr:street":"Ross Road",
    "iso:country":"GB",
    "sg:address":"Ross Road",
    "sg:city":"Hereford",
    "sg:classifiers":[
        {
            "category":"Autos & Motor Vehicles",
            "subcategory":"Automobile Sales",
            "type":"Retail Goods"
        }
    ],
    "sg:postcode":"HR2 8HY",
    "sg:province":"Herefordshire",
    "sg:tags":[
        "car"
    ],
    "wof:name":"Gary John Thorn",
    "wof:placetype":"venue"
},
  "geometry": {"coordinates":[-2.7221689224,52.0305633545],"type":"Point"}
}