{
  "type": "Feature",
  "properties": {
    "addr:full":"67 Bourne Vale Bromley Kent BR2 7NW",
    "addr:housenumber":"67",
    "addr:postcode":"br2 7nw",
    "addr:street":"Bourne Vale",
    "iso:country":"GB",
    "sg:address":"67 Bourne Vale",
    "sg:city":"Bromley",
    "sg:classifiers":[
        {
            "category":"Building & Trades",
            "subcategory":"Construction",
            "type":"Services"
        }
    ],
    "sg:phone":"+44 20 8462 8505",
    "sg:postcode":"BR2 7NW",
    "sg:province":"Kent",
    "sg:tags":[
        "roofing"
    ],
    "wof:name":"Impala Roofing",
    "wof:placetype":"venue"
},
  "geometry": {"coordinates":[0.007014,51.37579],"type":"Point"}
}