{
  "type": "Feature",
  "properties": {
    "addr:full":"Unit 34a Chadkirk Indust Est, Vale Rd, Romiley Stockport Cheshire SK6 3LE",
    "addr:housenumber":"unit 34a",
    "addr:postcode":"sk6 3le",
    "addr:street":"Chadkirk Indust Est Vale Rd",
    "iso:country":"GB",
    "sg:address":"Unit 34a Chadkirk Indust Est, Vale Rd, Romiley",
    "sg:city":"Stockport",
    "sg:classifiers":[
        {
            "category":"Communications",
            "type":"Services"
        }
    ],
    "sg:postcode":"SK6 3LE",
    "sg:province":"Cheshire",
    "sg:tags":[
        "tv",
        "video",
        "radio"
    ],
    "wof:name":"Woollam,Paul,Kitchens & Bedrooms",
    "wof:placetype":"venue"
},
  "geometry": {"coordinates":[-2.0911839008,53.4138412476],"type":"Point"}
}