{
  "type": "Feature",
  "properties": {
    "addr:full":"211 Warbreck Moor Liverpool Merseyside L9 0HU",
    "addr:housenumber":"211",
    "addr:postcode":"l9 0hu",
    "addr:street":"Warbreck Moor",
    "iso:country":"GB",
    "sg:address":"211 Warbreck Moor",
    "sg:city":"Liverpool",
    "sg:classifiers":[
        {
            "category":"Food & Beverages",
            "subcategory":"Meat & Fish",
            "type":"Retail Goods"
        }
    ],
    "sg:phone":"+44 151 525 2634",
    "sg:postcode":"L9 0HU",
    "sg:province":"Merseyside",
    "sg:tags":[
        "butcher"
    ],
    "wof:name":"Dennis Boyles",
    "wof:placetype":"venue"
},
  "geometry": {"coordinates":[-2.955685,53.470318],"type":"Point"}
}