{
  "type": "Feature",
  "properties": {
    "iso:country":"GB",
    "sg:address":"Unit 52, Gravelly Industrial Park",
    "sg:city":"Birmingham",
    "sg:classifiers":[
        {
            "category":"Home & Garden",
            "subcategory":"Hardware",
            "type":"Retail Goods"
        }
    ],
    "sg:postcode":"B24 8TG",
    "sg:province":"West Midlands",
    "wof:name":"Ardia Uk Ltd.",
    "wof:placetype":"venue"
},
  "geometry": {"coordinates":[-1.8518340588,52.512966156],"type":"Point"}
}