{
  "type": "Feature",
  "properties": {
    "addr:full":"194 Upper Richmond Rd Putney Greater London SW15 2SH",
    "addr:housenumber":"194",
    "addr:postcode":"sw15 2sh",
    "addr:street":"Upper Richmond Rd",
    "iso:country":"GB",
    "sg:address":"194 Upper Richmond Rd",
    "sg:city":"Putney",
    "sg:classifiers":[
        {
            "category":"Real Estate",
            "subcategory":"Real Estate Agent",
            "type":"Services"
        }
    ],
    "sg:phone":"+44 20 8780 1100",
    "sg:postcode":"SW15 2SH",
    "sg:province":"Greater London",
    "wof:name":"Warren's",
    "wof:placetype":"venue"
},
  "geometry": {"coordinates":[-0.216625005,51.4608268738],"type":"Point"}
}