{
  "type": "Feature",
  "properties": {
    "iso:country":"GB",
    "sg:address":"2b High Street",
    "sg:city":"Haslemere",
    "sg:classifiers":[
        {
            "category":"Shopping",
            "subcategory":"Clothing, Apparel, & Fashions",
            "type":"Retail Goods"
        }
    ],
    "sg:phone":"+44 1428 654647",
    "sg:postcode":"GU27 2LY",
    "sg:province":"Hampshire",
    "sg:tags":[
        "shop"
    ],
    "wof:name":"M & R Clothing",
    "wof:placetype":"venue"
},
  "geometry": {"coordinates":[-0.709669,51.087502],"type":"Point"}
}