{
  "type": "Feature",
  "properties": {
    "iso:country":"GB",
    "sg:address":"2 The Peak",
    "sg:city":"Rowland's Castle",
    "sg:classifiers":[
        {
            "category":"Real Estate",
            "subcategory":"Surveying",
            "type":"Services"
        }
    ],
    "sg:postcode":"PO9 6AH",
    "sg:province":"Hampshire",
    "sg:tags":[
        "surveyor",
        "valuer"
    ],
    "wof:name":"Benjamin French",
    "wof:placetype":"venue"
},
  "geometry": {"coordinates":[-0.961941,50.89299],"type":"Point"}
}