{
  "type": "Feature",
  "properties": {
    "iso:country":"GB",
    "sg:address":"Venn Farm, Quethiock",
    "sg:city":"Liskeard",
    "sg:classifiers":[
        {
            "category":"Farming",
            "subcategory":"Farm",
            "type":"Manufacturing & Wholesale Goods"
        }
    ],
    "sg:postcode":"PL14 3SL",
    "sg:province":"Cornwall",
    "sg:tags":[
        "mixed",
        "crop"
    ],
    "wof:name":"O G Hoskin",
    "wof:placetype":"venue"
},
  "geometry": {"coordinates":[-4.378319,50.458977],"type":"Point"}
}