{
  "type": "Feature",
  "properties": {
    "iso:country":"GB",
    "sg:address":"Melrose, 143 Ashbourne Road, Turnditch",
    "sg:city":"Belper",
    "sg:classifiers":[
        {
            "category":"Building & Trades",
            "subcategory":"Construction",
            "type":"Services"
        }
    ],
    "sg:postcode":"DE56 2LH",
    "sg:province":"Derbyshire",
    "sg:tags":[
        "builder"
    ],
    "wof:name":"P J Allen & Son",
    "wof:placetype":"venue"
},
  "geometry": {"coordinates":[-1.5593789816,53.0159416199],"type":"Point"}
}