{
  "type": "Feature",
  "properties": {
    "iso:country":"GB",
    "sg:address":"Burr Street, Harwell",
    "sg:city":"Didcot",
    "sg:classifiers":[
        {
            "category":"Bars & Pubs",
            "type":"Food & Drink"
        },
        {
            "category":"Community Center",
            "subcategory":"Social",
            "type":"Public Place"
        }
    ],
    "sg:phone":"+44 1235 835212",
    "sg:postcode":"OX11 0DT",
    "sg:province":"Oxfordshire",
    "sg:tags":[
        "pubs",
        "house",
        "inn",
        "activity"
    ],
    "wof:name":"THE CRISPIN",
    "wof:placetype":"venue"
},
  "geometry": {"coordinates":[-1.289862,51.601433],"type":"Point"}
}