{
  "type": "Feature",
  "properties": {
    "iso:country":"GB",
    "sg:address":"Claxfield House, London Rd, Teynham",
    "sg:city":"Sittingbourne",
    "sg:classifiers":[
        {
            "category":"Wholesale",
            "subcategory":"Fruits & Vegetables",
            "type":"Manufacturing & Wholesale Goods"
        }
    ],
    "sg:phone":"+44 1795 522497",
    "sg:postcode":"ME9 9PR",
    "sg:province":"Kent",
    "wof:name":"Poggi & Co Ltd",
    "wof:placetype":"venue"
},
  "geometry": {"coordinates":[0.7759,51.333195],"type":"Point"}
}