{
  "type": "Feature",
  "properties": {
    "iso:country":"GB",
    "sg:address":"Newton Road, Bishops Teignton",
    "sg:city":"Teignmouth",
    "sg:classifiers":[
        {
            "category":"Home & Garden",
            "subcategory":"Garden Supply",
            "type":"Retail Goods"
        }
    ],
    "sg:phone":"+44 1626 776996",
    "sg:postcode":"TQ14 9PN",
    "sg:province":"Devon",
    "sg:tags":[
        "nursery",
        "centre"
    ],
    "wof:name":"Great Park Nurseries Ltd.",
    "wof:placetype":"venue"
},
  "geometry": {"coordinates":[-3.508514,50.547779],"type":"Point"}
}