{
  "type": "Feature",
  "properties": {
    "addr:full":"8 Nunns Court, Featherstone Pontefract West Yorkshire WF7 5PW",
    "addr:housenumber":"8",
    "addr:postcode":"wf7 5pw",
    "addr:street":"Nunns Court;West",
    "iso:country":"GB",
    "sg:address":"8 Nunns Court, Featherstone",
    "sg:city":"Pontefract",
    "sg:classifiers":[
        {
            "category":"Professional",
            "subcategory":"Art Services",
            "type":"Services"
        }
    ],
    "sg:postcode":"WF7 5PW",
    "sg:province":"West Yorkshire",
    "sg:tags":[
        "photographer"
    ],
    "wof:name":"Reflections Photography",
    "wof:placetype":"venue"
},
  "geometry": {"coordinates":[-1.3589459658,53.6698036194],"type":"Point"}
}