{
  "type": "Feature",
  "properties": {
    "addr:full":"Unit 1, 17 Ladbroke Close, Woodley Reading Berkshire RG5 4DX",
    "addr:housenumber":"unit;17",
    "addr:postcode":"rg5 4dx",
    "addr:street":"Ladbroke Close",
    "iso:country":"GB",
    "sg:address":"Unit 1, 17 Ladbroke Close, Woodley",
    "sg:city":"Reading",
    "sg:classifiers":[
        {
            "category":"Professional",
            "subcategory":"Engineering",
            "type":"Services"
        }
    ],
    "sg:phone":"+44 118 969 8800",
    "sg:postcode":"RG5 4DX",
    "sg:province":"Berkshire",
    "sg:tags":[
        "precision",
        "engineer"
    ],
    "wof:name":"Swaypoint Ltd.",
    "wof:placetype":"venue"
},
  "geometry": {"coordinates":[-0.8969150186,51.4505805969],"type":"Point"}
}