{
  "type": "Feature",
  "properties": {
    "addr:full":"Biteford, Woolsery Bideford Devon EX39 5QZ",
    "addr:postcode":"ex39 5qz",
    "iso:country":"GB",
    "sg:address":"Biteford, Woolsery",
    "sg:city":"Bideford",
    "sg:classifiers":[
        {
            "category":"Farming",
            "subcategory":"Livestock Farm",
            "type":"Manufacturing & Wholesale Goods"
        }
    ],
    "sg:postcode":"EX39 5QZ",
    "sg:province":"Devon",
    "sg:tags":[
        "others"
    ],
    "wof:name":"Biteford Farm",
    "wof:placetype":"venue"
},
  "geometry": {"coordinates":[-4.378394,50.965759],"type":"Point"}
}