{
  "type": "Feature",
  "properties": {
    "addr:full":"3-5 Grange Terrace, Stockton Road Sunderland Tyne and Wear SR2 7DG",
    "addr:housenumber":"3-5",
    "addr:postcode":"sr2 7dg",
    "addr:street":"Grange Terrace Stockton Road",
    "iso:country":"GB",
    "sg:address":"3-5 Grange Terrace, Stockton Road",
    "sg:city":"Sunderland",
    "sg:classifiers":[
        {
            "category":"Professional",
            "subcategory":"Accounting & Tax Preparation",
            "type":"Services"
        }
    ],
    "sg:phone":"+44 191 567 0304",
    "sg:postcode":"SR2 7DG",
    "sg:province":"Tyne and Wear",
    "sg:tags":[
        "accountant"
    ],
    "wof:name":"T T R Barnes Limited",
    "wof:placetype":"venue"
},
  "geometry": {"coordinates":[-1.383775,54.899899],"type":"Point"}
}