{
  "type": "Feature",
  "properties": {
    "addr:full":"Mill Bridge Hope Valley Derbyshire S33 8WR",
    "addr:postcode":"s33 8wr",
    "addr:street":"Mill Bridge",
    "iso:country":"GB",
    "sg:address":"Mill Bridge",
    "sg:city":"Hope Valley",
    "sg:classifiers":[
        {
            "category":"Manufacturing",
            "subcategory":"Electronics",
            "type":"Manufacturing & Wholesale Goods"
        }
    ],
    "sg:phone":"+44 1433 621555",
    "sg:postcode":"S33 8WR",
    "sg:province":"Derbyshire",
    "sg:tags":[
        "control",
        "component",
        "-",
        "electronic"
    ],
    "wof:name":"Wearnes Hollingsworth Ltd",
    "wof:placetype":"venue"
},
  "geometry": {"coordinates":[-1.7737640142,53.3445968628],"type":"Point"}
}