{
  "type": "Feature",
  "properties": {
    "iso:country":"GB",
    "sg:address":"Unit 2b, Walworth Enterprise Centre, Duke Close",
    "sg:city":"Andover",
    "sg:classifiers":[
        {
            "category":"Shopping",
            "subcategory":"Books",
            "type":"Retail Goods"
        }
    ],
    "sg:phone":"+44 1264 334748",
    "sg:postcode":"SP10 5AR",
    "sg:province":"Hampshire",
    "wof:name":"Intercept Ltd.",
    "wof:placetype":"venue"
},
  "geometry": {"coordinates":[-1.4767789841,51.2064933777],"type":"Point"}
}