{
  "type": "Feature",
  "properties": {
    "addr:full":"52-54 Union Street Torquay Devon TQ2 5PS",
    "addr:housenumber":"52-54",
    "addr:postcode":"tq2 5ps",
    "addr:street":"Union Street",
    "iso:country":"GB",
    "sg:address":"52-54 Union Street",
    "sg:city":"Torquay",
    "sg:classifiers":[
        {
            "category":"Shopping",
            "subcategory":"Clothing, Apparel, & Fashions",
            "type":"Retail Goods"
        }
    ],
    "sg:phone":"+44 1803 295044",
    "sg:postcode":"TQ2 5PS",
    "sg:province":"Devon",
    "sg:tags":[
        "menswear"
    ],
    "wof:name":"Burton Menswear",
    "wof:placetype":"venue"
},
  "geometry": {"coordinates":[-3.529523,50.466419],"type":"Point"}
}