{
  "type": "Feature",
  "properties": {
    "addr:full":"9 Rufus Close Ruislip Greater London HA4 0QU",
    "addr:housenumber":"9",
    "addr:postcode":"ha4 0qu",
    "addr:street":"Rufus Close",
    "iso:country":"GB",
    "sg:address":"9 Rufus Close",
    "sg:city":"Ruislip",
    "sg:classifiers":[
        {
            "category":"Real Estate",
            "subcategory":"Real Estate Operator",
            "type":"Services"
        }
    ],
    "sg:postcode":"HA4 0QU",
    "sg:province":"Greater London",
    "sg:tags":[
        "letting",
        "agent"
    ],
    "wof:name":"On Line Property Services",
    "wof:placetype":"venue"
},
  "geometry": {"coordinates":[-0.385079,51.563782],"type":"Point"}
}