{
  "type": "Feature",
  "properties": {
    "addr:full":"23 North Bridge Street Bathgate West Lothian EH48 4PS",
    "addr:housenumber":"23",
    "addr:postcode":"eh48 4ps",
    "addr:street":"North Bridge Street Bathgate",
    "iso:country":"GB",
    "sg:address":"23 North Bridge Street",
    "sg:city":"Bathgate",
    "sg:classifiers":[
        {
            "category":"Food & Beverages",
            "subcategory":"Bakery",
            "type":"Retail Goods"
        }
    ],
    "sg:phone":"+44 1506 632840",
    "sg:postcode":"EH48 4PS",
    "sg:province":"West Lothian",
    "sg:tags":[
        "baker"
    ],
    "wof:name":"Greggs",
    "wof:placetype":"venue"
},
  "geometry": {"coordinates":[-3.6434929371,55.9021072388],"type":"Point"}
}