{
  "type": "Feature",
  "properties": {
    "iso:country":"GB",
    "sg:address":"13 Derby Street",
    "sg:city":"Leek",
    "sg:classifiers":[
        {
            "category":"Shopping",
            "subcategory":"Pharmacy",
            "type":"Retail Goods"
        }
    ],
    "sg:phone":"+44 1538 382435",
    "sg:postcode":"ST13 6HN",
    "sg:province":"Staffordshire",
    "sg:tags":[
        "pharmacist",
        "chemist"
    ],
    "wof:name":"Boots the Chemist",
    "wof:placetype":"venue"
},
  "geometry": {"coordinates":[-2.024594,53.1059],"type":"Point"}
}