{
  "type": "Feature",
  "properties": {
    "addr:full":"8 Bridge Street Stranraer Dumfries and Galloway DG9 7HY",
    "addr:housenumber":"8",
    "addr:postcode":"dg9 7hy",
    "addr:street":"Bridge Street",
    "iso:country":"GB",
    "sg:address":"8 Bridge Street",
    "sg:city":"Stranraer",
    "sg:classifiers":[
        {
            "category":"Shopping",
            "subcategory":"Clothing, Apparel, & Fashions",
            "type":"Retail Goods"
        }
    ],
    "sg:phone":"+44 1776 703389",
    "sg:postcode":"DG9 7HY",
    "sg:province":"Dumfries and Galloway",
    "sg:tags":[
        "ladieswear"
    ],
    "wof:name":"The Cat Walk",
    "wof:placetype":"venue"
},
  "geometry": {"coordinates":[-5.027176857,54.9040222168],"type":"Point"}
}