{
  "type": "Feature",
  "properties": {
    "addr:full":"High Street, St Davids Haverfordwest Pembrokeshire SA62 6SB",
    "addr:postcode":"sa62 6sb",
    "addr:street":"High Street St",
    "iso:country":"GB",
    "sg:address":"High Street, St Davids",
    "sg:city":"Haverfordwest",
    "sg:classifiers":[
        {
            "category":"Travel",
            "subcategory":"Hotels & Motels",
            "type":"Entertainment"
        }
    ],
    "sg:phone":"+44 1437 720341",
    "sg:postcode":"SA62 6SB",
    "sg:province":"Pembrokeshire",
    "wof:name":"Grove Hotel",
    "wof:placetype":"venue"
},
  "geometry": {"coordinates":[-5.1966900826,51.8739852905],"type":"Point"}
}