{
  "type": "Feature",
  "properties": {
    "addr:full":"28 Tynwald Hill, Moortown Leeds North Yorkshire LS17 5ND",
    "addr:housenumber":"28",
    "addr:postcode":"ls17 5nd",
    "addr:street":"Tynwald Hill",
    "iso:country":"GB",
    "sg:address":"28 Tynwald Hill, Moortown",
    "sg:city":"Leeds",
    "sg:classifiers":[
        {
            "category":"Building & Trades",
            "subcategory":"Construction",
            "type":"Services"
        }
    ],
    "sg:phone":"+44 113 268 1451",
    "sg:postcode":"LS17 5ND",
    "sg:province":"North Yorkshire",
    "sg:tags":[
        "joiner",
        "carpenter"
    ],
    "wof:name":"Dmc Services",
    "wof:placetype":"venue"
},
  "geometry": {"coordinates":[-1.559872,53.844837],"type":"Point"}
}