{
  "type": "Feature",
  "properties": {
    "addr:full":"51 Derby Street Rochdale Lancashire OL11 1LU",
    "addr:housenumber":"51",
    "addr:postcode":"ol11 1lu",
    "addr:street":"Derby Street",
    "iso:country":"GB",
    "sg:address":"51 Derby Street",
    "sg:city":"Rochdale",
    "sg:classifiers":[
        {
            "category":"Retail",
            "subcategory":"Laundry & Dry Cleaning",
            "type":"Services"
        }
    ],
    "sg:phone":"+44 1706 353126",
    "sg:postcode":"OL11 1LU",
    "sg:province":"Lancashire",
    "sg:tags":[
        "alteration"
    ],
    "wof:name":"Mario Petito",
    "wof:placetype":"venue"
},
  "geometry": {"coordinates":[-2.151373,53.607281],"type":"Point"}
}