{
  "type": "Feature",
  "properties": {
    "addr:full":"82 College Road Bromley Kent BR1 3PE",
    "addr:housenumber":"82",
    "addr:postcode":"br1 3pe",
    "addr:street":"College Road",
    "iso:country":"GB",
    "sg:address":"82 College Road",
    "sg:city":"Bromley",
    "sg:classifiers":[
        {
            "category":"Food & Beverages",
            "subcategory":"Candy",
            "type":"Retail Goods"
        }
    ],
    "sg:phone":"+44 1825 769622",
    "sg:postcode":"BR1 3PE",
    "sg:province":"Kent",
    "sg:tags":[
        "confectioner"
    ],
    "wof:name":"Fishers",
    "wof:placetype":"venue"
},
  "geometry": {"coordinates":[0.0148,51.4118309021],"type":"Point"}
}