{
  "type": "Feature",
  "properties": {
    "iso:country":"GB",
    "sg:address":"7 Coulthurst Street, Ramsbottom",
    "sg:city":"Bury",
    "sg:classifiers":[
        {
            "category":"Home & Garden",
            "subcategory":"Home Furnishings",
            "type":"Retail Goods"
        }
    ],
    "sg:phone":"+44 1706 826420",
    "sg:postcode":"BL0 9ET",
    "sg:province":"Lancashire",
    "sg:tags":[
        "mantelpiece",
        "fireplace"
    ],
    "wof:name":"Victorian Cast Iron Furnishings",
    "wof:placetype":"venue"
},
  "geometry": {"coordinates":[-2.3243649006,53.6488113403],"type":"Point"}
}