{
  "type": "Feature",
  "properties": {
    "addr:full":"6 The Triangle Poole Dorset BH16 5PG",
    "addr:housenumber":"6",
    "addr:postcode":"bh16 5pg",
    "addr:street":"The Triangle",
    "iso:country":"GB",
    "sg:address":"6 The Triangle",
    "sg:city":"Poole",
    "sg:classifiers":[
        {
            "category":"Shopping",
            "subcategory":"Department Store",
            "type":"Retail Goods"
        },
        {
            "category":"Food & Beverages",
            "subcategory":"Groceries & Convenience Stores",
            "type":"Retail Goods"
        }
    ],
    "sg:phone":"+44 1202 622890",
    "sg:postcode":"BH16 5PG",
    "sg:province":"Dorset",
    "wof:name":"Triangle Stores",
    "wof:placetype":"venue"
},
  "geometry": {"coordinates":[-2.0299890041,50.7370185852],"type":"Point"}
}