{
  "type": "Feature",
  "properties": {
    "addr:full":"23 North Pde Bradford West Yorkshire BD1 3JL",
    "addr:housenumber":"23",
    "addr:postcode":"bd1 3jl",
    "addr:street":"North Pde",
    "iso:country":"GB",
    "sg:address":"23 North Pde",
    "sg:city":"Bradford",
    "sg:classifiers":[
        {
            "category":"Retail",
            "subcategory":"Laundry & Dry Cleaning",
            "type":"Services"
        }
    ],
    "sg:phone":"+44 1274 726666",
    "sg:postcode":"BD1 3JL",
    "sg:province":"West Yorkshire",
    "sg:tags":[
        "alteration"
    ],
    "wof:name":"Crockatt Cleaning",
    "wof:placetype":"venue"
},
  "geometry": {"coordinates":[-1.756427,53.796841],"type":"Point"}
}