{
  "type": "Feature",
  "properties": {
    "addr:full":"10 The College, Denby Ripley Derbyshire DE5 8NJ",
    "addr:housenumber":"10",
    "addr:postcode":"de5 8nj",
    "addr:street":"The",
    "iso:country":"GB",
    "sg:address":"10 The College, Denby",
    "sg:city":"Ripley",
    "sg:classifiers":[
        {
            "category":"Communications",
            "subcategory":"Film & Video Production",
            "type":"Services"
        }
    ],
    "sg:phone":"+44 1773 745805",
    "sg:postcode":"DE5 8NJ",
    "sg:province":"Derbyshire",
    "sg:tags":[
        "illustrator",
        "artist"
    ],
    "wof:name":"Tom Leighton Artist",
    "wof:placetype":"venue"
},
  "geometry": {"coordinates":[-1.412279,53.012726],"type":"Point"}
}