{
  "type": "Feature",
  "properties": {
    "iso:country":"GB",
    "sg:address":"Atkinson Road, Urmston",
    "sg:city":"Manchester",
    "sg:classifiers":[
        {
            "category":"Building & Trades",
            "subcategory":"Construction",
            "type":"Services"
        }
    ],
    "sg:phone":"+44 161 748 6201",
    "sg:postcode":"M41 9AD",
    "sg:province":"Cheshire",
    "sg:tags":[
        "builder"
    ],
    "wof:name":"P O'Connor (Builders) Ltd.",
    "wof:placetype":"venue"
},
  "geometry": {"coordinates":[-2.351434,53.447701],"type":"Point"}
}