{
  "type": "Feature",
  "properties": {
    "addr:full":"Unit 7 Palmerston Workshops, Palmerston Road Barry The Vale of Glamorgan CF63 2YZ",
    "addr:housenumber":"unit 7",
    "addr:postcode":"cf63 2yz",
    "addr:street":"Workshops Palmerston Road;Vale",
    "iso:country":"GB",
    "sg:address":"Unit 7 Palmerston Workshops, Palmerston Road",
    "sg:city":"Barry",
    "sg:classifiers":[
        {
            "category":"Wholesale",
            "subcategory":"Meat",
            "type":"Manufacturing & Wholesale Goods"
        }
    ],
    "sg:postcode":"CF63 2YZ",
    "sg:province":"The Vale of Glamorgan",
    "sg:tags":[
        "product"
    ],
    "wof:name":"Real Pie Co Ltd (The)",
    "wof:placetype":"venue"
},
  "geometry": {"coordinates":[-3.241604,51.412125],"type":"Point"}
}