{
  "type": "Feature",
  "properties": {
    "iso:country":"GB",
    "sg:address":"102 Palmerston St, Bollington",
    "sg:city":"Macclesfield",
    "sg:classifiers":[
        {
            "category":"Home & Garden",
            "subcategory":"Furniture",
            "type":"Retail Goods"
        }
    ],
    "sg:phone":"+44 1625 572524",
    "sg:postcode":"SK10 5PW",
    "sg:province":"Cheshire",
    "wof:name":"Bridgend Country Collection",
    "wof:placetype":"venue"
},
  "geometry": {"coordinates":[-2.0975348949,53.298122406],"type":"Point"}
}