{
  "type": "Feature",
  "properties": {
    "iso:country":"GB",
    "sg:address":"91 Moor La, Woodford",
    "sg:city":"Stockport",
    "sg:classifiers":[
        {
            "category":"Freight",
            "type":"Transportation"
        }
    ],
    "sg:phone":"+44 161 440 0228",
    "sg:postcode":"SK7 1PL",
    "sg:province":"Cheshire",
    "sg:tags":[
        "haulage",
        "road"
    ],
    "wof:name":"Rhino Transport Ltd",
    "wof:placetype":"venue"
},
  "geometry": {"coordinates":[-2.166039,53.346714],"type":"Point"}
}