{
  "type": "Feature",
  "properties": {
    "iso:country":"GB",
    "sg:address":"24 Faircross Parade, Longbridge Road",
    "sg:city":"Barking",
    "sg:classifiers":[
        {
            "category":"Recreation",
            "subcategory":"Dog Park",
            "type":"Entertainment"
        }
    ],
    "sg:phone":"+44 20 8591 7112",
    "sg:postcode":"IG11 8UW",
    "sg:province":"Essex",
    "wof:name":"The Pet Stop",
    "wof:placetype":"venue"
},
  "geometry": {"coordinates":[0.083397,51.542004],"type":"Point"}
}