{
  "type": "Feature",
  "properties": {
    "iso:country":"GB",
    "sg:address":"Unit 8 The Quadrant, Town Road",
    "sg:city":"Stoke-on-trent",
    "sg:classifiers":[
        {
            "category":"Personal",
            "subcategory":"Nail Salon",
            "type":"Services"
        }
    ],
    "sg:phone":"+44 1782 266255",
    "sg:postcode":"ST1 2QD",
    "sg:province":"Staffordshire",
    "sg:tags":[
        "solarium",
        "tanning"
    ],
    "wof:name":"The Pyramid Tanning Centre",
    "wof:placetype":"venue"
},
  "geometry": {"coordinates":[-2.1748020649,53.0285263062],"type":"Point"}
}