{
  "type": "Feature",
  "properties": {
    "addr:full":"Unit 22 Cam Centre, Wilbury Way Hitchin Hertfordshire SG4 0TW",
    "addr:housenumber":"unit 22",
    "addr:postcode":"sg4 0tw",
    "addr:street":"Cam Centre Wilbury Way",
    "iso:country":"GB",
    "sg:address":"Unit 22 Cam Centre, Wilbury Way",
    "sg:city":"Hitchin",
    "sg:classifiers":[
        {
            "category":"Military Area",
            "subcategory":"Air Force Base",
            "type":"Public Place"
        }
    ],
    "sg:phone":"+44 1462 420666",
    "sg:postcode":"SG4 0TW",
    "sg:province":"Hertfordshire",
    "sg:tags":[
        "water",
        "treatment"
    ],
    "wof:name":"Euraqua Ltd.",
    "wof:placetype":"venue"
},
  "geometry": {"coordinates":[-0.2641440034,51.9641914368],"type":"Point"}
}