{
  "type": "Feature",
  "properties": {
    "addr:full":"10 Broad O'th La, Shevington Wigan Lancashire WN6 8EA",
    "addr:housenumber":"10",
    "addr:postcode":"wn6 8ea",
    "addr:street":"Broad O'Th La Shevington",
    "iso:country":"GB",
    "sg:address":"10 Broad O'th La, Shevington",
    "sg:city":"Wigan",
    "sg:classifiers":[
        {
            "category":"Professional",
            "subcategory":"Management & Consulting",
            "type":"Services"
        }
    ],
    "sg:postcode":"WN6 8EA",
    "sg:province":"Lancashire",
    "sg:tags":[
        "consultant",
        "business"
    ],
    "wof:name":"Cromedale Resources Ltd",
    "wof:placetype":"venue"
},
  "geometry": {"coordinates":[-2.6930599213,53.5726394653],"type":"Point"}
}