{
  "type": "Feature",
  "properties": {
    "iso:country":"GB",
    "sg:address":"Sunwin House, 18-24 Furnival Gate",
    "sg:city":"Sheffield",
    "sg:classifiers":[
        {
            "category":"Shopping",
            "subcategory":"Department Store",
            "type":"Retail Goods"
        }
    ],
    "sg:phone":"+44 114 273 7058",
    "sg:postcode":"S1 3LE",
    "sg:province":"South Yorkshire",
    "wof:name":"Sunwin House",
    "wof:placetype":"venue"
},
  "geometry": {"coordinates":[-1.47251,53.378403],"type":"Point"}
}