{
  "type": "Feature",
  "properties": {
    "iso:country":"GB",
    "sg:address":"The France Shop, Digbeth Court, Digbeth Street",
    "sg:city":"Cheltenham",
    "sg:classifiers":[
        {
            "category":"Shopping",
            "subcategory":"Books",
            "type":"Retail Goods"
        }
    ],
    "sg:postcode":"GL54 1BN",
    "sg:province":"Gloucestershire",
    "sg:tags":[
        "bookseller"
    ],
    "wof:name":"France Magasin",
    "wof:placetype":"venue"
},
  "geometry": {"coordinates":[-1.721868,51.929626],"type":"Point"}
}