{
  "type": "Feature",
  "properties": {
    "addr:full":"8 Chalton Church Lane London Greater London SE7 7AQ",
    "addr:housenumber":"8",
    "addr:postcode":"se7 7aq",
    "addr:street":"Chalton Church Lane",
    "iso:country":"GB",
    "sg:address":"8 Chalton Church Lane",
    "sg:city":"London",
    "sg:classifiers":[
        {
            "category":"Banks & Credit Unions",
            "subcategory":"Bank",
            "type":"Services"
        }
    ],
    "sg:phone":"+44 20 8858 5106",
    "sg:postcode":"SE7 7AQ",
    "sg:province":"Greater London",
    "wof:name":"Barclays Bank Plc",
    "wof:placetype":"venue"
},
  "geometry": {"coordinates":[0.0315370001,51.4873085022],"type":"Point"}
}