{
  "type": "Feature",
  "properties": {
    "iso:country":"GB",
    "sg:address":"29 Heathfield, Stacey Bushes",
    "sg:city":"Milton Keynes",
    "sg:classifiers":[
        {
            "category":"Personal",
            "type":"Services"
        }
    ],
    "sg:phone":"+44 1908 220322",
    "sg:postcode":"MK12 6HR",
    "sg:province":"Buckinghamshire",
    "sg:tags":[
        "delivery"
    ],
    "wof:name":"Four Ways Parcel Service Ltd.",
    "wof:placetype":"venue"
},
  "geometry": {"coordinates":[-0.801383,52.049606],"type":"Point"}
}