{
  "type": "Feature",
  "properties": {
    "iso:country":"GB",
    "sg:address":"Unit 1 Holmer Trading Estate",
    "sg:city":"Hereford",
    "sg:classifiers":[
        {
            "category":"Retail",
            "subcategory":"Auto Repair",
            "type":"Services"
        }
    ],
    "sg:phone":"+44 1432 265200",
    "sg:postcode":"HR1 1JS",
    "sg:province":"Herefordshire",
    "sg:tags":[
        "body",
        "car",
        "repairer"
    ],
    "wof:name":"Cavanaghs Ltd.",
    "wof:placetype":"venue"
},
  "geometry": {"coordinates":[-2.7074599266,52.0714836121],"type":"Point"}
}