{
  "type": "Feature",
  "properties": {
    "iso:country":"GB",
    "sg:address":"Unit 12 Bilton Indust Est, Bilton Rd",
    "sg:city":"Basingstoke",
    "sg:classifiers":[
        {
            "category":"Professional",
            "subcategory":"Detective & Security Services",
            "type":"Services"
        }
    ],
    "sg:phone":"+44 1256 479417",
    "sg:postcode":"RG24 8NJ",
    "sg:province":"Hampshire",
    "sg:tags":[
        "equipment"
    ],
    "wof:name":"I T W Fastex Security & Closure Products",
    "wof:placetype":"venue"
},
  "geometry": {"coordinates":[-1.06787,51.28244],"type":"Point"}
}