{
  "type": "Feature",
  "properties": {
    "addr:full":"204 London Road, Hazel Gro Stockport Cheshire SK7 4DQ",
    "addr:housenumber":"204",
    "addr:postcode":"sk7 4dq",
    "addr:street":"London Road",
    "iso:country":"GB",
    "sg:address":"204 London Road, Hazel Gro",
    "sg:city":"Stockport",
    "sg:classifiers":[
        {
            "category":"Shopping",
            "subcategory":"Used Merchandise",
            "type":"Retail Goods"
        }
    ],
    "sg:phone":"+44 161 456 3534",
    "sg:postcode":"SK7 4DQ",
    "sg:province":"Cheshire",
    "sg:tags":[
        "shop",
        "second-hand"
    ],
    "wof:name":"Yu & Me Superstore",
    "wof:placetype":"venue"
},
  "geometry": {"coordinates":[-2.120718,53.37949],"type":"Point"}
}