{
  "type": "Feature",
  "properties": {
    "addr:full":"Queen Street Penzance Cornwall TR18 4BJ",
    "addr:postcode":"tr18 4bj",
    "addr:street":"Queen Street",
    "iso:country":"GB",
    "sg:address":"Queen Street",
    "sg:city":"Penzance",
    "sg:classifiers":[
        {
            "category":"Bars & Pubs",
            "type":"Food & Drink"
        }
    ],
    "sg:postcode":"TR18 4BJ",
    "sg:province":"Cornwall",
    "sg:tags":[
        "pubs",
        "inn"
    ],
    "wof:name":"Greenalls Group Plc (The)",
    "wof:placetype":"venue"
},
  "geometry": {"coordinates":[-5.536579,50.117649],"type":"Point"}
}