{
  "type": "Feature",
  "properties": {
    "iso:country":"GB",
    "sg:address":"82 Church Lane, Barton Under Needwood",
    "sg:city":"Burton-on-trent",
    "sg:classifiers":[
        {
            "category":"Professional",
            "subcategory":"Computer Services",
            "type":"Services"
        }
    ],
    "sg:postcode":"DE13 8HX",
    "sg:province":"Derbyshire",
    "sg:tags":[
        "consultant"
    ],
    "wof:name":"Needwood Business Systems",
    "wof:placetype":"venue"
},
  "geometry": {"coordinates":[-1.723394,52.763149],"type":"Point"}
}