{
  "type": "Feature",
  "properties": {
    "addr:full":"7 Air Street London Greater London W1B 5AD",
    "addr:housenumber":"7",
    "addr:postcode":"w1b 5ad",
    "addr:street":"Air Street",
    "iso:country":"GB",
    "sg:address":"7 Air Street",
    "sg:city":"London",
    "sg:classifiers":[
        {
            "category":"Banks & Credit Unions",
            "subcategory":"Financial Services",
            "type":"Services"
        },
        {
            "category":"Wholesale",
            "subcategory":"Books, Periodicals, & Newspapers",
            "type":"Manufacturing & Wholesale Goods"
        }
    ],
    "sg:phone":"+44 20 7439 3050",
    "sg:postcode":"W1B 5AD",
    "sg:province":"Greater London",
    "sg:tags":[
        "consultant",
        "publishing"
    ],
    "wof:name":"City Financial Communications Ltd.",
    "wof:placetype":"venue"
},
  "geometry": {"coordinates":[-0.1364070028,51.5099258423],"type":"Point"}
}