{
  "type": "Feature",
  "properties": {
    "addr:full":"Willows Road Salford Greater Manchester M5 2FQ",
    "addr:postcode":"m5 2fq",
    "addr:street":"Willows Road",
    "iso:country":"GB",
    "sg:address":"Willows Road",
    "sg:city":"Salford",
    "sg:classifiers":[
        {
            "category":"Arena",
            "subcategory":"Sports Club",
            "type":"Entertainment"
        }
    ],
    "sg:phone":"+44 161 736 6564",
    "sg:postcode":"M5 2FQ",
    "sg:province":"Greater Manchester",
    "wof:name":"Salford Rugby League Football Club",
    "wof:placetype":"venue"
},
  "geometry": {"coordinates":[-2.3093690872,53.4856948853],"type":"Point"}
}