{
  "type": "Feature",
  "properties": {
    "addr:full":"The Council House, Ventnor Road Cwmbran Monmouthshire NP44 3JY",
    "addr:postcode":"np44 3jy",
    "addr:street":"Ventnor Road",
    "iso:country":"GB",
    "sg:address":"The Council House, Ventnor Road",
    "sg:city":"Cwmbran",
    "sg:classifiers":[
        {
            "category":"Government",
            "subcategory":"Office",
            "type":"Public Place"
        }
    ],
    "sg:phone":"+44 1633 838456",
    "sg:postcode":"NP44 3JY",
    "sg:province":"Monmouthshire",
    "sg:tags":[
        "local"
    ],
    "wof:name":"Cwmbran Community Council",
    "wof:placetype":"venue"
},
  "geometry": {"coordinates":[-3.021337,51.64706],"type":"Point"}
}