{
  "type": "Feature",
  "properties": {
    "addr:full":"Bisley Green, Bisley Woking Surrey GU24 9EW",
    "addr:postcode":"gu24 9ew",
    "addr:street":"Bisley Green",
    "iso:country":"GB",
    "sg:address":"Bisley Green, Bisley",
    "sg:city":"Woking",
    "sg:classifiers":[
        {
            "category":"Retail",
            "subcategory":"Storage",
            "type":"Services"
        }
    ],
    "sg:postcode":"GU24 9EW",
    "sg:province":"Surrey",
    "sg:tags":[
        "household",
        "removal"
    ],
    "wof:name":"Bisley Removal Services",
    "wof:placetype":"venue"
},
  "geometry": {"coordinates":[-0.637119,51.324875],"type":"Point"}
}