{
  "type": "Feature",
  "properties": {
    "addr:full":"Beechwood Av Runcorn Cheshire WA7 3HB",
    "addr:postcode":"wa7 3hb",
    "addr:street":"Beechwood Av Runcorn Cheshire",
    "iso:country":"GB",
    "sg:address":"Beechwood Av",
    "sg:city":"Runcorn",
    "sg:classifiers":[
        {
            "category":"Place Of Worship",
            "type":"Public Place"
        }
    ],
    "sg:phone":"+44 1928 713101",
    "sg:postcode":"WA7 3HB",
    "sg:province":"Cheshire",
    "wof:name":"St Mark Shared Church",
    "wof:placetype":"venue"
},
  "geometry": {"coordinates":[-2.6905839443,53.3165168762],"type":"Point"}
}