{
  "type": "Feature",
  "properties": {
    "addr:full":"Church Street Settle North Yorkshire BD24 9JD",
    "addr:postcode":"bd24 9jd",
    "addr:street":"Church Street",
    "iso:country":"GB",
    "sg:address":"Church Street",
    "sg:city":"Settle",
    "sg:classifiers":[
        {
            "category":"Autos & Motor Vehicles",
            "subcategory":"Fuel & Gas Station",
            "type":"Retail Goods"
        },
        {
            "category":"Travel",
            "subcategory":"Hotels & Motels",
            "type":"Entertainment"
        }
    ],
    "sg:phone":"+44 1729 824719",
    "sg:postcode":"BD24 9JD",
    "sg:province":"North Yorkshire",
    "sg:tags":[
        "petrol",
        "house",
        "guest"
    ],
    "wof:name":"WHITEFRIARS COUNTRY GUEST HOUSE",
    "wof:placetype":"venue"
},
  "geometry": {"coordinates":[-2.2793440819,54.0710411072],"type":"Point"}
}