{
  "type": "Feature",
  "properties": {
    "addr:full":"185k Milton Park Abingdon Oxfordshire OX14 4SR",
    "addr:housenumber":"185k",
    "addr:postcode":"ox14 4sr",
    "addr:street":"Milton Park",
    "iso:country":"GB",
    "sg:address":"185k Milton Park",
    "sg:city":"Abingdon",
    "sg:classifiers":[
        {
            "category":"Real Estate",
            "subcategory":"Surveying",
            "type":"Services"
        }
    ],
    "sg:phone":"+44 1235 862826",
    "sg:postcode":"OX14 4SR",
    "sg:province":"Oxfordshire",
    "sg:tags":[
        "surveyor",
        "valuer"
    ],
    "wof:name":"Stiles Harold Williams Ltd.",
    "wof:placetype":"venue"
},
  "geometry": {"coordinates":[-1.3013240099,51.6222496033],"type":"Point"}
}