{
  "type": "Feature",
  "properties": {
    "addr:full":"2 North Grn, Coates Peterborough Cambridgeshire PE7 2BQ",
    "addr:housenumber":"2",
    "addr:postcode":"pe7 2bq",
    "addr:street":"North Grn Coates",
    "iso:country":"GB",
    "sg:address":"2 North Grn, Coates",
    "sg:city":"Peterborough",
    "sg:classifiers":[
        {
            "category":"Shopping",
            "subcategory":"Musical Instruments",
            "type":"Retail Goods"
        }
    ],
    "sg:postcode":"PE7 2BQ",
    "sg:province":"Cambridgeshire",
    "wof:name":"Simon Watkins",
    "wof:placetype":"venue"
},
  "geometry": {"coordinates":[-0.0767920017,52.5639572144],"type":"Point"}
}