{
  "type": "Feature",
  "properties": {
    "iso:country":"GB",
    "sg:address":"Tong St",
    "sg:city":"Bradford",
    "sg:classifiers":[
        {
            "category":"Retail",
            "subcategory":"Auto Repair",
            "type":"Services"
        }
    ],
    "sg:phone":"+44 1274 651073",
    "sg:postcode":"BD4 9RB",
    "sg:province":"West Yorkshire",
    "sg:tags":[
        "modification",
        "garage"
    ],
    "wof:name":"Fina Service Station",
    "wof:placetype":"venue"
},
  "geometry": {"coordinates":[-1.723994,53.772789],"type":"Point"}
}