{
  "type": "Feature",
  "properties": {
    "iso:country":"GB",
    "sg:address":"Gidding Grove Farm, Winwick Road, Great Gidding",
    "sg:city":"Huntingdon",
    "sg:classifiers":[
        {
            "category":"Farming",
            "subcategory":"Farm",
            "type":"Manufacturing & Wholesale Goods"
        }
    ],
    "sg:phone":"+44 1832 293407",
    "sg:postcode":"PE28 5PD",
    "sg:province":"Bedfordshire",
    "sg:tags":[
        "mixed",
        "crop"
    ],
    "wof:name":"D G Roughton",
    "wof:placetype":"venue"
},
  "geometry": {"coordinates":[-0.350759,52.434376],"type":"Point"}
}