{
  "type": "Feature",
  "properties": {
    "iso:country":"GB",
    "sg:address":"69 Springwood Ave, Garston",
    "sg:city":"Liverpool",
    "sg:classifiers":[
        {
            "category":"Building & Trades",
            "subcategory":"Cleaning & Sanitation",
            "type":"Services"
        }
    ],
    "sg:postcode":"L19 4TU",
    "sg:province":"Merseyside",
    "sg:tags":[
        "commercial"
    ],
    "wof:name":"Alpha Cleaning Services Ltd",
    "wof:placetype":"venue"
},
  "geometry": {"coordinates":[-2.887383,53.364376],"type":"Point"}
}