{
  "type": "Feature",
  "properties": {
    "iso:country":"GB",
    "sg:address":"Inch Rd",
    "sg:city":"Ellon",
    "sg:classifiers":[
        {
            "category":"Building & Trades",
            "subcategory":"Plumbing",
            "type":"Services"
        }
    ],
    "sg:phone":"+44 1358 789419",
    "sg:postcode":"AB41 0BN",
    "sg:province":"Aberdeenshire",
    "sg:tags":[
        "heating"
    ],
    "wof:name":"Gall William & Son Ltd",
    "wof:placetype":"venue"
},
  "geometry": {"coordinates":[-2.09522,57.386848],"type":"Point"}
}