{
  "type": "Feature",
  "properties": {
    "addr:full":"Park Lane Barnstaple Devon EX32 9AX",
    "addr:postcode":"ex32 9ax",
    "addr:street":"Park Lane",
    "iso:country":"GB",
    "sg:address":"Park Lane",
    "sg:city":"Barnstaple",
    "sg:classifiers":[
        {
            "category":"Education",
            "subcategory":"School",
            "type":"Public Place"
        }
    ],
    "sg:phone":"+44 1271 373131",
    "sg:postcode":"EX32 9AX",
    "sg:province":"Devon",
    "sg:tags":[
        "local",
        "authority"
    ],
    "wof:name":"The Park Community School",
    "wof:placetype":"venue"
},
  "geometry": {"coordinates":[-4.051963,51.072353],"type":"Point"}
}