{
  "type": "Feature",
  "properties": {
    "iso:country":"GB",
    "sg:address":"41 The Hyde",
    "sg:city":"Ware",
    "sg:classifiers":[
        {
            "category":"Building & Trades",
            "subcategory":"Construction",
            "type":"Services"
        }
    ],
    "sg:phone":"+44 1920 460052",
    "sg:postcode":"SG12 0ER",
    "sg:province":"Hertfordshire",
    "sg:tags":[
        "roofing"
    ],
    "wof:name":"Cakebread Roofing & Leadwork Specialist",
    "wof:placetype":"venue"
},
  "geometry": {"coordinates":[-0.049515,51.815739],"type":"Point"}
}