{
  "type": "Feature",
  "properties": {
    "iso:country":"GB",
    "sg:address":"94 Railway Rd",
    "sg:city":"Chorley",
    "sg:classifiers":[
        {
            "category":"Arts & Performance",
            "subcategory":"Music",
            "type":"Entertainment"
        }
    ],
    "sg:phone":"+44 1257 249655",
    "sg:postcode":"PR6 0HN",
    "sg:province":"Lancashire",
    "sg:tags":[
        "mobile",
        "disco"
    ],
    "wof:name":"S T V Roadshow",
    "wof:placetype":"venue"
},
  "geometry": {"coordinates":[-2.626303,53.658508],"type":"Point"}
}