{
  "type": "Feature",
  "properties": {
    "addr:full":"36 Renfrew Avenue, Eastham Wirral Cheshire L62 8DN",
    "addr:housenumber":"36",
    "addr:postcode":"l62 8dn",
    "addr:street":"Renfrew Avenue",
    "iso:country":"GB",
    "sg:address":"36 Renfrew Avenue, Eastham",
    "sg:city":"Wirral",
    "sg:classifiers":[
        {
            "category":"Retail",
            "subcategory":"Auto Repair",
            "type":"Services"
        }
    ],
    "sg:phone":"+44 151 327 1220",
    "sg:postcode":"L62 8DN",
    "sg:province":"Cheshire",
    "sg:tags":[
        "electrician"
    ],
    "wof:name":"R Chapple",
    "wof:placetype":"venue"
},
  "geometry": {"coordinates":[-2.9637598991,53.3181686401],"type":"Point"}
}