{
  "type": "Feature",
  "properties": {
    "addr:full":"98-100 Lower Addiscombe Rd Croydon Surrey CR9 6AE",
    "addr:housenumber":"98-100",
    "addr:postcode":"cr9 6ae",
    "addr:street":"Lower Addiscombe Rd",
    "iso:country":"GB",
    "sg:address":"98-100 Lower Addiscombe Rd",
    "sg:city":"Croydon",
    "sg:classifiers":[
        {
            "category":"Autos & Motor Vehicles",
            "subcategory":"Automobile Sales",
            "type":"Retail Goods"
        }
    ],
    "sg:phone":"+44 20 8654 8111",
    "sg:postcode":"CR9 6AE",
    "sg:province":"Surrey",
    "sg:tags":[
        "car"
    ],
    "wof:name":"Camden Rover",
    "wof:placetype":"venue"
},
  "geometry": {"coordinates":[-0.0653190017,51.383518219],"type":"Point"}
}