{
  "type": "Feature",
  "properties": {
    "addr:full":"Unit 5 Churchill Works, Highfield Street, Earl Shilton Leicester Leicestershire LE9 7HS",
    "addr:housenumber":"unit 5",
    "addr:postcode":"le9 7hs",
    "addr:street":"Churchill Works Highfield Street",
    "iso:country":"GB",
    "sg:address":"Unit 5 Churchill Works, Highfield Street, Earl Shilton",
    "sg:city":"Leicester",
    "sg:classifiers":[
        {
            "category":"Professional",
            "type":"Services"
        },
        {
            "category":"Personal",
            "subcategory":"Shoe Repair & Shine",
            "type":"Services"
        }
    ],
    "sg:phone":"+44 1455 841737",
    "sg:postcode":"LE9 7HS",
    "sg:province":"Leicestershire",
    "sg:tags":[
        "equipment",
        "fixture",
        "display",
        "maker"
    ],
    "wof:name":"Mark Ii Construction",
    "wof:placetype":"venue"
},
  "geometry": {"coordinates":[-1.3144949675,52.5757751465],"type":"Point"}
}