{
  "type": "Feature",
  "properties": {
    "addr:full":"Royale Leisure Park, Western Avenue, Acton London Greater London W3 7EE",
    "addr:postcode":"w3 7ee",
    "addr:street":"Park Western Avenue",
    "iso:country":"GB",
    "sg:address":"Royale Leisure Park, Western Avenue, Acton",
    "sg:city":"London",
    "sg:classifiers":[
        {
            "category":"Bars & Pubs",
            "subcategory":"Nightclub",
            "type":"Food & Drink"
        }
    ],
    "sg:phone":"+44 20 8896 3406",
    "sg:postcode":"W3 7EE",
    "sg:province":"Greater London",
    "sg:tags":[
        "club",
        "night"
    ],
    "wof:name":"Zenith Discotheque",
    "wof:placetype":"venue"
},
  "geometry": {"coordinates":[-0.2548600137,51.5144386292],"type":"Point"}
}