{
  "type": "Feature",
  "properties": {
    "addr:full":"396 Mentmore Terrace Hackney Greater London E8 3PN",
    "addr:housenumber":"396",
    "addr:postcode":"e8 3pn",
    "addr:street":"Mentmore Terrace",
    "iso:country":"GB",
    "sg:address":"396 Mentmore Terrace",
    "sg:city":"Hackney",
    "sg:classifiers":[
        {
            "category":"Retail",
            "subcategory":"Auto Repair",
            "type":"Services"
        }
    ],
    "sg:phone":"+44 20 8986 4934",
    "sg:postcode":"E8 3PN",
    "sg:province":"Greater London",
    "sg:tags":[
        "modification",
        "garage"
    ],
    "wof:name":"Lucky Brake Motors",
    "wof:placetype":"venue"
},
  "geometry": {"coordinates":[-0.057589,51.540852],"type":"Point"}
}