{
  "type": "Feature",
  "properties": {
    "iso:country":"GB",
    "sg:address":"396 Mentmore Terrace",
    "sg:city":"Hackney",
    "sg:classifiers":[
        {
            "category":"Retail",
            "subcategory":"Auto Repair",
            "type":"Services"
        }
    ],
    "sg:phone":"+44 20 8986 4934",
    "sg:postcode":"E8 3PN",
    "sg:province":"Greater London",
    "sg:tags":[
        "modification",
        "garage"
    ],
    "wof:name":"Lucky Brake Motors",
    "wof:placetype":"venue"
},
  "geometry": {"coordinates":[-0.057589,51.540852],"type":"Point"}
}