{
  "type": "Feature",
  "properties": {
    "addr:full":"31 Moor Street Congleton Cheshire CW12 1QH",
    "addr:housenumber":"31",
    "addr:postcode":"cw12 1qh",
    "addr:street":"Moor Street",
    "iso:country":"GB",
    "sg:address":"31 Moor Street",
    "sg:city":"Congleton",
    "sg:classifiers":[
        {
            "category":"Personal",
            "subcategory":"Beauty Salon",
            "type":"Services"
        }
    ],
    "sg:postcode":"CW12 1QH",
    "sg:province":"Cheshire",
    "sg:tags":[
        "unisex",
        "hairdresser"
    ],
    "wof:name":"Lesley Hairdressing",
    "wof:placetype":"venue"
},
  "geometry": {"coordinates":[-2.206274,53.163738],"type":"Point"}
}