{
  "type": "Feature",
  "properties": {
    "addr:full":"Manor Farm, Netton Salisbury Hampshire SP4 6AW",
    "addr:postcode":"sp4 6aw",
    "addr:street":"Manor;Netton",
    "iso:country":"GB",
    "sg:address":"Manor Farm, Netton",
    "sg:city":"Salisbury",
    "sg:classifiers":[
        {
            "category":"Home & Garden",
            "subcategory":"Garden Supply",
            "type":"Retail Goods"
        },
        {
            "category":"Farming",
            "subcategory":"Livestock Farm",
            "type":"Manufacturing & Wholesale Goods"
        }
    ],
    "sg:phone":"+44 1722 782230",
    "sg:postcode":"SP4 6AW",
    "sg:province":"Hampshire",
    "sg:tags":[
        "bulb",
        "grower",
        "others"
    ],
    "wof:name":"Wilson Baird & Partners",
    "wof:placetype":"venue"
},
  "geometry": {"coordinates":[-1.818642,51.132317],"type":"Point"}
}