{
  "type": "Feature",
  "properties": {
    "iso:country":"GB",
    "sg:address":"Springfield Cottage, Preston New Road",
    "sg:city":"Blackburn",
    "sg:classifiers":[
        {
            "category":"Health Services",
            "subcategory":"Nursing And Care Facility",
            "type":"Services"
        },
        {
            "category":"Social Services",
            "subcategory":"Retirement Home",
            "type":"Services"
        }
    ],
    "sg:phone":"+44 1254 264704",
    "sg:postcode":"BB2 6PS",
    "sg:province":"Lancashire",
    "sg:tags":[
        "residential"
    ],
    "wof:name":"Springfield Cottage Residential Home",
    "wof:placetype":"venue"
},
  "geometry": {"coordinates":[-2.49191,53.752167],"type":"Point"}
}