{
  "type": "Feature",
  "properties": {
    "addr:full":"21 Printing Office Street Doncaster South Yorkshire DN1 1TZ",
    "addr:postcode":"dn1 1tz",
    "addr:street":"Office Street",
    "iso:country":"GB",
    "sg:address":"21 Printing Office Street",
    "sg:city":"Doncaster",
    "sg:classifiers":[
        {
            "category":"Travel",
            "subcategory":"Travel Agent",
            "type":"Entertainment"
        }
    ],
    "sg:phone":"+44 1302 366934",
    "sg:postcode":"DN1 1TZ",
    "sg:province":"South Yorkshire",
    "sg:tags":[
        "agency",
        "activity"
    ],
    "wof:name":"ALLIED TRAVEL AGENCY",
    "wof:placetype":"venue"
},
  "geometry": {"coordinates":[-1.135235,53.52227],"type":"Point"}
}