{
  "type": "Feature",
  "properties": {
    "iso:country":"GB",
    "sg:address":"Heaton Chapel Post Office, 455 Manchester Road",
    "sg:city":"Stockport",
    "sg:classifiers":[
        {
            "category":"Government",
            "subcategory":"Post Office",
            "type":"Public Place"
        }
    ],
    "sg:phone":"+44 161 432 5504",
    "sg:postcode":"SK4 5DJ",
    "sg:province":"Cheshire",
    "wof:name":"Heaton Chapel Post Office",
    "wof:placetype":"venue"
},
  "geometry": {"coordinates":[-2.177883,53.429276],"type":"Point"}
}