{
  "type": "Feature",
  "properties": {
    "addr:full":"Tunnel Street Burnley Lancashire BB12 0NN",
    "addr:postcode":"bb12 0nn",
    "addr:street":"Tunnel Street",
    "iso:country":"GB",
    "sg:address":"Tunnel Street",
    "sg:city":"Burnley",
    "sg:classifiers":[
        {
            "category":"Organizations",
            "subcategory":"Community Association",
            "type":"Services"
        },
        {
            "category":"Organizations",
            "subcategory":"Membership Organization",
            "type":"Services"
        }
    ],
    "sg:phone":"+44 1282 421485",
    "sg:postcode":"BB12 0NN",
    "sg:province":"Lancashire",
    "sg:tags":[
        "club",
        "social"
    ],
    "wof:name":"Dickie Pink",
    "wof:placetype":"venue"
},
  "geometry": {"coordinates":[-2.263283968,53.7926139832],"type":"Point"}
}