{
  "type": "Feature",
  "properties": {
    "iso:country":"GB",
    "sg:address":"1 Doxey Road",
    "sg:city":"Stafford",
    "sg:classifiers":[
        {
            "category":"Bars & Pubs",
            "type":"Food & Drink"
        }
    ],
    "sg:phone":"+44 1785 247719",
    "sg:postcode":"ST16 2EW",
    "sg:province":"Staffordshire",
    "sg:tags":[
        "pubs",
        "inn"
    ],
    "wof:name":"Castle Tavern",
    "wof:placetype":"venue"
},
  "geometry": {"coordinates":[-2.124514,52.807369],"type":"Point"}
}