{
  "type": "Feature",
  "properties": {
    "addr:full":"Suite 2, 80a Blackheath Road London Greater London SE10 8DA",
    "addr:housenumber":"suite 2 80a",
    "addr:postcode":"se10 8da",
    "addr:street":"Blackheath Road",
    "iso:country":"GB",
    "sg:address":"Suite 2, 80a Blackheath Road",
    "sg:city":"London",
    "sg:classifiers":[
        {
            "category":"Organizations",
            "subcategory":"Non-profit Organization",
            "type":"Services"
        }
    ],
    "sg:postcode":"SE10 8DA",
    "sg:province":"Greater London",
    "sg:tags":[
        "organisation",
        "voluntary",
        "charity"
    ],
    "wof:name":"Civil Service Retirement Fellowship",
    "wof:placetype":"venue"
},
  "geometry": {"coordinates":[-0.0184080005,51.4731750488],"type":"Point"}
}