{
  "type": "Feature",
  "properties": {
    "addr:full":"14 Triangle Road, Hackney London Greater London E8 3RP",
    "addr:housenumber":"14",
    "addr:postcode":"e8 3rp",
    "addr:street":"Triangle Road",
    "iso:country":"GB",
    "sg:address":"14 Triangle Road, Hackney",
    "sg:city":"London",
    "sg:classifiers":[
        {
            "category":"Education",
            "subcategory":"Library",
            "type":"Public Place"
        }
    ],
    "sg:phone":"+44 20 7249 8348",
    "sg:postcode":"E8 3RP",
    "sg:province":"Greater London",
    "sg:tags":[
        "reproduction",
        "furniture"
    ],
    "wof:name":"J & J Hallett Ltd.",
    "wof:placetype":"venue"
},
  "geometry": {"coordinates":[-0.058699,51.538208],"type":"Point"}
}