{
  "type": "Feature",
  "properties": {
    "addr:full":"Canterbury Road Herne Bay Kent CT6 5TD",
    "addr:postcode":"ct6 5td",
    "addr:street":"Canterbury Road",
    "iso:country":"GB",
    "sg:address":"Canterbury Road",
    "sg:city":"Herne Bay",
    "sg:classifiers":[
        {
            "category":"Community Center",
            "type":"Public Place"
        },
        {
            "category":"Conference Center",
            "type":"Public Place"
        }
    ],
    "sg:phone":"+44 1227 373254",
    "sg:postcode":"CT6 5TD",
    "sg:province":"Kent",
    "sg:tags":[
        "facility",
        "room",
        "centre"
    ],
    "wof:name":"Herne Bay Court",
    "wof:placetype":"venue"
},
  "geometry": {"coordinates":[1.13434,51.372074],"type":"Point"}
}