{
  "type": "Feature",
  "properties": {
    "addr:full":"Rear Of 66-68 Edward St Burton On Trent Derbyshire DE14 2JD",
    "addr:housenumber":"rear of 66-68",
    "addr:postcode":"trent derbyshire de14 2jd",
    "addr:street":"Edward St",
    "iso:country":"GB",
    "sg:address":"Rear Of 66-68 Edward St",
    "sg:city":"Burton On Trent",
    "sg:classifiers":[
        {
            "category":"Retail",
            "subcategory":"Auto Repair",
            "type":"Services"
        }
    ],
    "sg:phone":"+44 1283 530031",
    "sg:postcode":"DE14 2JD",
    "sg:province":"Derbyshire",
    "sg:tags":[
        "modification",
        "garage"
    ],
    "wof:name":"Kenwell Auto Repairs",
    "wof:placetype":"venue"
},
  "geometry": {"coordinates":[-1.647701025,52.8043518066],"type":"Point"}
}