{
  "type": "Feature",
  "properties": {
    "iso:country":"GB",
    "sg:address":"347b Wakefield Road, Denby Dale",
    "sg:city":"Huddersfield",
    "sg:classifiers":[
        {
            "category":"Shopping",
            "subcategory":"Books",
            "type":"Retail Goods"
        }
    ],
    "sg:phone":"+44 1484 866413",
    "sg:postcode":"HD8 8RT",
    "sg:province":"South Yorkshire",
    "sg:tags":[
        "bookseller",
        "retailer"
    ],
    "wof:name":"Orchard Bookshop",
    "wof:placetype":"venue"
},
  "geometry": {"coordinates":[-1.6567729712,53.572681427],"type":"Point"}
}