{
  "type": "Feature",
  "properties": {
    "iso:country":"GB",
    "sg:address":"Unit 7 & 8 Curlew Park, Threemilestone Industrial Estate, Threemilestone",
    "sg:city":"Truro",
    "sg:classifiers":[
        {
            "category":"Shopping",
            "subcategory":"Computers & Home Electronics",
            "type":"Retail Goods"
        }
    ],
    "sg:phone":"+44 1872 272277",
    "sg:postcode":"TR4 9LG",
    "sg:province":"Cornwall",
    "sg:tags":[
        "electrical"
    ],
    "wof:name":"Newey & Eyre Ltd.",
    "wof:placetype":"venue"
},
  "geometry": {"coordinates":[-5.1220397949,50.2622909546],"type":"Point"}
}