{
  "type": "Feature",
  "properties": {
    "addr:full":"13-15 St Peters Street Ashton-under-lyne Greater Manchester OL6 7TG",
    "addr:housenumber":"13-15",
    "addr:postcode":"ol6 7tg",
    "addr:street":"St Peters Street",
    "iso:country":"GB",
    "sg:address":"13-15 St Peters Street",
    "sg:city":"Ashton-under-lyne",
    "sg:classifiers":[
        {
            "category":"Retail",
            "subcategory":"Auto Repair",
            "type":"Services"
        }
    ],
    "sg:phone":"+44 161 343 1017",
    "sg:postcode":"OL6 7TG",
    "sg:province":"Greater Manchester",
    "sg:tags":[
        "modification",
        "garage"
    ],
    "wof:name":"A P A Motors",
    "wof:placetype":"venue"
},
  "geometry": {"coordinates":[-2.10304,53.484924],"type":"Point"}
}