{
  "type": "Feature",
  "properties": {
    "iso:country":"GB",
    "sg:address":"295 Finchley Road",
    "sg:city":"London",
    "sg:classifiers":[
        {
            "category":"Shopping",
            "subcategory":"Bicycles & Sporting Goods",
            "type":"Retail Goods"
        }
    ],
    "sg:phone":"+44 20 7431 4900",
    "sg:postcode":"NW3 6DT",
    "sg:province":"Greater London",
    "sg:tags":[
        "shop",
        "cycle",
        "accessory"
    ],
    "wof:name":"The Cycle Surgery",
    "wof:placetype":"venue"
},
  "geometry": {"coordinates":[-0.181812,51.549541],"type":"Point"}
}