{
  "type": "Feature",
  "properties": {
    "iso:country":"GB",
    "sg:address":"71 Fore Street, Bovey Tracey",
    "sg:city":"Newton Abbot",
    "sg:classifiers":[
        {
            "category":"Retail",
            "subcategory":"Laundry & Dry Cleaning",
            "type":"Services"
        }
    ],
    "sg:phone":"+44 1626 833675",
    "sg:postcode":"TQ13 9AB",
    "sg:province":"Devon",
    "sg:tags":[
        "launderette"
    ],
    "wof:name":"The Dolly Tub",
    "wof:placetype":"venue"
},
  "geometry": {"coordinates":[-3.673486,50.594418],"type":"Point"}
}