{
  "type": "Feature",
  "properties": {
    "iso:country":"GB",
    "sg:address":"13 Treforthlan, Paynters Lane End",
    "sg:city":"Redruth",
    "sg:classifiers":[
        {
            "category":"Building & Trades",
            "subcategory":"Construction",
            "type":"Services"
        }
    ],
    "sg:phone":"+44 1209 842930",
    "sg:postcode":"TR16 4RN",
    "sg:province":"Cornwall",
    "sg:tags":[
        "decorator",
        "painter"
    ],
    "wof:name":"Trevor Harris",
    "wof:placetype":"venue"
},
  "geometry": {"coordinates":[-5.26621,50.24369],"type":"Point"}
}