{
  "type": "Feature",
  "properties": {
    "addr:full":"Oak Bank Mill, Hallam Road Nelson Lancashire BB9 8AJ",
    "addr:postcode":"bb9 8aj",
    "addr:street":"Hallam Road",
    "iso:country":"GB",
    "sg:address":"Oak Bank Mill, Hallam Road",
    "sg:city":"Nelson",
    "sg:classifiers":[
        {
            "category":"Retail",
            "subcategory":"Repair Shop",
            "type":"Services"
        }
    ],
    "sg:phone":"+44 1282 691631",
    "sg:postcode":"BB9 8AJ",
    "sg:province":"Lancashire",
    "sg:tags":[
        "upholstering",
        "upholsterer"
    ],
    "wof:name":"Buoyant Upholstery Ltd.",
    "wof:placetype":"venue"
},
  "geometry": {"coordinates":[-2.213340044,53.8359680176],"type":"Point"}
}