{
  "type": "Feature",
  "properties": {
    "addr:full":"Memorial Ground, Kernick Road Penryn Cornwall TR10 8NT",
    "addr:postcode":"tr10 8nt",
    "addr:street":"Kernick Road",
    "iso:country":"GB",
    "sg:address":"Memorial Ground, Kernick Road",
    "sg:city":"Penryn",
    "sg:classifiers":[
        {
            "category":"Arena",
            "subcategory":"Sports Club",
            "type":"Entertainment"
        }
    ],
    "sg:phone":"+44 1326 372239",
    "sg:postcode":"TR10 8NT",
    "sg:province":"Cornwall",
    "wof:name":"Penryn Rugby Football Club",
    "wof:placetype":"venue"
},
  "geometry": {"coordinates":[-5.104809,50.168575],"type":"Point"}
}