{
  "type": "Feature",
  "properties": {
    "iso:country":"GB",
    "sg:address":"The Yard, Kenardington",
    "sg:city":"Ashford",
    "sg:classifiers":[
        {
            "category":"Manufacturing",
            "subcategory":"Buildings",
            "type":"Manufacturing & Wholesale Goods"
        }
    ],
    "sg:phone":"+44 1233 733833",
    "sg:postcode":"TN26 2LX",
    "sg:province":"Kent",
    "sg:tags":[
        "portable"
    ],
    "wof:name":"Lowrie Bros",
    "wof:placetype":"venue"
},
  "geometry": {"coordinates":[0.7995560169,51.0501937866],"type":"Point"}
}