{
  "type": "Feature",
  "properties": {
    "addr:full":"Associated Press Building, 12 Norwich Street London Greater London EC4A 1BP",
    "addr:housenumber":"12",
    "addr:postcode":"ec4a 1bp",
    "addr:street":"Norwich Street",
    "iso:country":"GB",
    "sg:address":"Associated Press Building, 12 Norwich Street",
    "sg:city":"London",
    "sg:classifiers":[
        {
            "category":"Communications",
            "subcategory":"News Services",
            "type":"Services"
        }
    ],
    "sg:phone":"+44 20 7353 3692",
    "sg:postcode":"EC4A 1BP",
    "sg:province":"Greater London",
    "sg:tags":[
        "photo",
        "agency"
    ],
    "wof:name":"Associated Press Radio Office",
    "wof:placetype":"venue"
},
  "geometry": {"coordinates":[-0.1101950034,51.5166778564],"type":"Point"}
}