{
  "type": "Feature",
  "properties": {
    "addr:full":"Vicarage, High St Doncaster North Yorkshire DN6 9AD",
    "addr:postcode":"dn6 9ad",
    "addr:street":"High St",
    "iso:country":"GB",
    "sg:address":"Vicarage, High St",
    "sg:city":"Doncaster",
    "sg:classifiers":[
        {
            "category":"Place Of Worship",
            "type":"Public Place"
        }
    ],
    "sg:phone":"+44 1302 700286",
    "sg:postcode":"DN6 9AD",
    "sg:province":"North Yorkshire",
    "wof:name":"St Magdalene's C Of E Church",
    "wof:placetype":"venue"
},
  "geometry": {"coordinates":[-1.1789400578,53.62059021],"type":"Point"}
}