{
  "type": "Feature",
  "properties": {
    "iso:country":"GB",
    "sg:address":"Chamberlain Ho, 88 High St, Coleshill",
    "sg:city":"Birmingham",
    "sg:classifiers":[
        {
            "category":"Professional",
            "subcategory":"Engineering",
            "type":"Services"
        }
    ],
    "sg:phone":"+44 1675 465448",
    "sg:postcode":"B46 3BL",
    "sg:province":"Warwickshire",
    "sg:tags":[
        "engineer",
        "mechanical"
    ],
    "wof:name":"Brightside Y A Y Ltd",
    "wof:placetype":"venue"
},
  "geometry": {"coordinates":[-1.7068,52.498611],"type":"Point"}
}