{
  "type": "Feature",
  "properties": {
    "addr:full":"Kirstead Hall Norwich Norfolk NR15 1ER",
    "addr:postcode":"nr15 1er",
    "addr:street":"Norwich",
    "iso:country":"GB",
    "sg:address":"Kirstead Hall",
    "sg:city":"Norwich",
    "sg:classifiers":[
        {
            "category":"Shopping",
            "subcategory":"Antiques",
            "type":"Retail Goods"
        }
    ],
    "sg:phone":"+44 1508 558269",
    "sg:postcode":"NR15 1ER",
    "sg:province":"Norfolk",
    "wof:name":"Dermot Murphy",
    "wof:placetype":"venue"
},
  "geometry": {"coordinates":[1.381005,52.522686],"type":"Point"}
}