{
  "type": "Feature",
  "properties": {
    "addr:full":"39 West Church St Buckie Moray AB56 1BP",
    "addr:housenumber":"39",
    "addr:postcode":"ab56 1bp",
    "addr:street":"West Church St",
    "iso:country":"GB",
    "sg:address":"39 West Church St",
    "sg:city":"Buckie",
    "sg:classifiers":[
        {
            "category":"Shopping",
            "subcategory":"Used Merchandise",
            "type":"Retail Goods"
        }
    ],
    "sg:postcode":"AB56 1BP",
    "sg:province":"Moray",
    "sg:tags":[
        "shop",
        "second-hand"
    ],
    "wof:name":"Needful Things",
    "wof:placetype":"venue"
},
  "geometry": {"coordinates":[-2.9680309296,57.6753845215],"type":"Point"}
}