{
  "type": "Feature",
  "properties": {
    "addr:full":"Moats Tye Hall, Tannery Road, Combs Stowmarket Suffolk IP14 2EN",
    "addr:postcode":"ip14 2en",
    "addr:street":"Tannery Road",
    "iso:country":"GB",
    "sg:address":"Moats Tye Hall, Tannery Road, Combs",
    "sg:city":"Stowmarket",
    "sg:classifiers":[
        {
            "category":"Building & Trades",
            "subcategory":"Construction",
            "type":"Services"
        }
    ],
    "sg:postcode":"IP14 2EN",
    "sg:province":"Suffolk",
    "sg:tags":[
        "window",
        "replacement"
    ],
    "wof:name":"Amc Window Design Ltd",
    "wof:placetype":"venue"
},
  "geometry": {"coordinates":[0.9871510267,52.1694717407],"type":"Point"}
}