{
  "type": "Feature",
  "properties": {
    "addr:full":"47 Glebe Street Falkirk Falkirk FK1 1HX",
    "addr:housenumber":"47",
    "addr:postcode":"fk1 1hx",
    "addr:street":"Glebe Street",
    "iso:country":"GB",
    "sg:address":"47 Glebe Street",
    "sg:city":"Falkirk",
    "sg:classifiers":[
        {
            "category":"Shopping",
            "subcategory":"Gifts & Souvenirs",
            "type":"Retail Goods"
        }
    ],
    "sg:phone":"+44 1324 639366",
    "sg:postcode":"FK1 1HX",
    "sg:province":"Falkirk",
    "sg:tags":[
        "shop"
    ],
    "wof:name":"Bairns Shop",
    "wof:placetype":"venue"
},
  "geometry": {"coordinates":[-3.7859408855,56.0013046265],"type":"Point"}
}