{
  "type": "Feature",
  "properties": {
    "addr:full":"64 Weeping Cross Stafford Staffordshire ST17 0DL",
    "addr:housenumber":"64",
    "addr:postcode":"st17 0dl",
    "iso:country":"GB",
    "sg:address":"64 Weeping Cross",
    "sg:city":"Stafford",
    "sg:classifiers":[
        {
            "category":"Professional",
            "subcategory":"Management & Consulting",
            "type":"Services"
        }
    ],
    "sg:postcode":"ST17 0DL",
    "sg:province":"Staffordshire",
    "sg:tags":[
        "consultant",
        "training"
    ],
    "wof:name":"Speechcraft Consultancy",
    "wof:placetype":"venue"
},
  "geometry": {"coordinates":[-2.07455,52.788239],"type":"Point"}
}