{
  "type": "Feature",
  "properties": {
    "iso:country":"GB",
    "sg:address":"West Edge, Marsh Gibbon",
    "sg:city":"Bicester",
    "sg:classifiers":[
        {
            "category":"Bars & Pubs",
            "type":"Food & Drink"
        },
        {
            "category":"Community Center",
            "subcategory":"Social",
            "type":"Public Place"
        }
    ],
    "sg:phone":"+44 1869 277365",
    "sg:postcode":"OX27 0HA",
    "sg:province":"Buckinghamshire",
    "sg:tags":[
        "pubs",
        "house",
        "inn",
        "activity"
    ],
    "wof:name":"The Greyhound Inn",
    "wof:placetype":"venue"
},
  "geometry": {"coordinates":[-1.0583779812,51.9029045105],"type":"Point"}
}