{
  "type": "Feature",
  "properties": {
    "addr:full":"Upper Lumsdale Matlock Derbyshire DE4 5LB",
    "addr:postcode":"de4 5lb",
    "addr:street":"Upper Lumsdale",
    "iso:country":"GB",
    "sg:address":"Upper Lumsdale",
    "sg:city":"Matlock",
    "sg:classifiers":[
        {
            "category":"Bus Charters",
            "type":"Transportation"
        }
    ],
    "sg:phone":"+44 1629 582826",
    "sg:postcode":"DE4 5LB",
    "sg:province":"Derbyshire",
    "sg:tags":[
        "hire",
        "coach"
    ],
    "wof:name":"K V & G L Slack Ltd.",
    "wof:placetype":"venue"
},
  "geometry": {"coordinates":[-1.5405650139,53.1348304749],"type":"Point"}
}