{
  "type": "Feature",
  "properties": {
    "iso:country":"GB",
    "sg:address":"Unit 10 Bridgend Industrial Estate, Gartferry Road",
    "sg:city":"Glasgow",
    "sg:classifiers":[
        {
            "category":"Taxi",
            "type":"Transportation"
        },
        {
            "category":"Military Area",
            "subcategory":"Air Force Base",
            "type":"Public Place"
        }
    ],
    "sg:phone":"+44 1236 875666",
    "sg:postcode":"G69 0JT",
    "sg:province":"East Dunbartonshire",
    "sg:tags":[
        "mini",
        "hire",
        "private",
        "cab"
    ],
    "wof:name":"Stephen Goodwin",
    "wof:placetype":"venue"
},
  "geometry": {"coordinates":[-4.08125,55.91851],"type":"Point"}
}