{
  "type": "Feature",
  "properties": {
    "addr:full":"East Trafalgar Rd Newport Isle of Wight PO30 1RT",
    "addr:postcode":"po30 1rt",
    "addr:street":"East Trafalgar Rd",
    "iso:country":"GB",
    "sg:address":"East Trafalgar Rd",
    "sg:city":"Newport",
    "sg:classifiers":[
        {
            "category":"Manufacturing",
            "subcategory":"Lumber",
            "type":"Manufacturing & Wholesale Goods"
        }
    ],
    "sg:phone":"+44 1983 562360",
    "sg:postcode":"PO30 1RT",
    "sg:province":"Isle of Wight",
    "sg:tags":[
        "importer",
        "merchants",
        "agent",
        "timber"
    ],
    "wof:name":"Moreys Ltd",
    "wof:placetype":"venue"
},
  "geometry": {"coordinates":[-1.2897449732,50.7003669739],"type":"Point"}
}