{
  "type": "Feature",
  "properties": {
    "iso:country":"GB",
    "sg:address":"8-10 Castle St",
    "sg:city":"Rugby",
    "sg:classifiers":[
        {
            "category":"Shopping",
            "subcategory":"Clothing, Apparel, & Fashions",
            "type":"Retail Goods"
        }
    ],
    "sg:postcode":"CV21 2TP",
    "sg:province":"Warwickshire",
    "sg:tags":[
        "shop"
    ],
    "wof:name":"Millbrook Factory Outlets Ltd",
    "wof:placetype":"venue"
},
  "geometry": {"coordinates":[-1.2594250441,52.3729438782],"type":"Point"}
}