{
  "type": "Feature",
  "properties": {
    "iso:country":"GB",
    "sg:address":"46 High Street",
    "sg:city":"New Romney",
    "sg:classifiers":[
        {
            "category":"Professional",
            "subcategory":"Business Services",
            "type":"Services"
        }
    ],
    "sg:phone":"+44 1797 363116",
    "sg:postcode":"TN28 8BN",
    "sg:province":"Kent",
    "sg:tags":[
        "bookmaker"
    ],
    "wof:name":"Jeff Mabey Ltd.",
    "wof:placetype":"venue"
},
  "geometry": {"coordinates":[0.940214,50.985905],"type":"Point"}
}