{
  "type": "Feature",
  "properties": {
    "addr:full":"Bon Accord Centre George Street Aberdeen Aberdeen City AB25 1HZ",
    "addr:postcode":"ab25 1hz",
    "addr:street":"George Street",
    "iso:country":"GB",
    "sg:address":"Bon Accord Centre George Street",
    "sg:city":"Aberdeen",
    "sg:classifiers":[
        {
            "category":"Travel",
            "subcategory":"Travel Agent",
            "type":"Entertainment"
        }
    ],
    "sg:phone":"+44 1224 807100",
    "sg:postcode":"AB25 1HZ",
    "sg:province":"Aberdeen City",
    "wof:name":"Thomas Cook",
    "wof:placetype":"venue"
},
  "geometry": {"coordinates":[-2.1067891121,57.1538200378],"type":"Point"}
}