{
  "type": "Feature",
  "properties": {
    "addr:full":"Bardsey Place Newcastle-upon-tyne Tyne and Wear NE12 8NU",
    "addr:postcode":"ne12 8nu",
    "addr:street":"Bardsey Place",
    "iso:country":"GB",
    "sg:address":"Bardsey Place",
    "sg:city":"Newcastle-upon-tyne",
    "sg:classifiers":[
        {
            "category":"Education",
            "subcategory":"School",
            "type":"Public Place"
        }
    ],
    "sg:phone":"+44 191 200 7425",
    "sg:postcode":"NE12 8NU",
    "sg:province":"Tyne and Wear",
    "sg:tags":[
        "local",
        "authority"
    ],
    "wof:name":"St Stephen's R C Primary School",
    "wof:placetype":"venue"
},
  "geometry": {"coordinates":[-1.5849260092,55.0152015686],"type":"Point"}
}