{
  "type": "Feature",
  "properties": {
    "iso:country":"GB",
    "sg:address":"11 Firs Drive, Hedge End",
    "sg:city":"Southampton",
    "sg:classifiers":[
        {
            "category":"Social Services",
            "subcategory":"Adult Care",
            "type":"Services"
        }
    ],
    "sg:phone":"+44 1489 860990",
    "sg:postcode":"SO30 4QQ",
    "sg:province":"Hampshire",
    "sg:tags":[
        "domestic",
        "cleaning"
    ],
    "wof:name":"Selclene (Maida Vale) Ltd.",
    "wof:placetype":"venue"
},
  "geometry": {"coordinates":[-1.313732,50.909424],"type":"Point"}
}