{
  "type": "Feature",
  "properties": {
    "addr:full":"Wheelers Lane, Brockham Betchworth Surrey RH3 7HJ",
    "addr:postcode":"rh3 7hj",
    "addr:street":"Wheelers Lane;Betchworth",
    "iso:country":"GB",
    "sg:address":"Wheelers Lane, Brockham",
    "sg:city":"Betchworth",
    "sg:classifiers":[
        {
            "category":"Home & Garden",
            "subcategory":"Garden Supply",
            "type":"Retail Goods"
        }
    ],
    "sg:postcode":"RH3 7HJ",
    "sg:province":"Surrey",
    "sg:tags":[
        "planting",
        "tree",
        "shrub"
    ],
    "wof:name":"Wheelers La Nursery",
    "wof:placetype":"venue"
},
  "geometry": {"coordinates":[-0.284962,51.231209],"type":"Point"}
}