{
  "type": "Feature",
  "properties": {
    "addr:full":"Adswood Road, Cheadle Hulme Cheadle Cheshire SK8 5QY",
    "addr:postcode":"sk8 5qy",
    "addr:street":"Adswood Road",
    "iso:country":"GB",
    "sg:address":"Adswood Road, Cheadle Hulme",
    "sg:city":"Cheadle",
    "sg:classifiers":[
        {
            "category":"Home & Garden",
            "subcategory":"Building Materials",
            "type":"Retail Goods"
        }
    ],
    "sg:phone":"+44 161 485 8211",
    "sg:postcode":"SK8 5QY",
    "sg:province":"Cheshire",
    "sg:tags":[
        "brick"
    ],
    "wof:name":"The Brick Business Ltd.",
    "wof:placetype":"venue"
},
  "geometry": {"coordinates":[-2.1801838875,53.3868484497],"type":"Point"}
}