{
  "type": "Feature",
  "properties": {
    "addr:full":"First Floor, Osprey House, Broadway Manchester Greater Manchester M5 2UE",
    "addr:postcode":"m5 2ue",
    "addr:street":"Broadway",
    "iso:country":"GB",
    "sg:address":"First Floor, Osprey House, Broadway",
    "sg:city":"Manchester",
    "sg:classifiers":[
        {
            "category":"Banks & Credit Unions",
            "subcategory":"Financial Services",
            "type":"Services"
        }
    ],
    "sg:phone":"+44 161 848 8111",
    "sg:postcode":"M5 2UE",
    "sg:province":"Greater Manchester",
    "sg:tags":[
        "consultant"
    ],
    "wof:name":"Barclays Mercantile Business Finance Ltd.",
    "wof:placetype":"venue"
},
  "geometry": {"coordinates":[-2.2749300003,53.4775505066],"type":"Point"}
}