{
  "type": "Feature",
  "properties": {
    "iso:country":"GB",
    "sg:address":"204 Dean St, Telford Centre",
    "sg:city":"Telford",
    "sg:classifiers":[
        {
            "category":"Shopping",
            "subcategory":"Mobile Phones",
            "type":"Retail Goods"
        }
    ],
    "sg:phone":"+44 1952 293274",
    "sg:postcode":"TF3 4BT",
    "sg:province":"Shropshire",
    "wof:name":"BT Shop",
    "wof:placetype":"venue"
},
  "geometry": {"coordinates":[-2.441765,52.676662],"type":"Point"}
}