{
  "type": "Feature",
  "properties": {
    "addr:full":"11a Market Place Banbury Oxfordshire OX16 5UA",
    "addr:housenumber":"11a",
    "addr:postcode":"ox16 5ua",
    "addr:street":"Market Place",
    "iso:country":"GB",
    "sg:address":"11a Market Place",
    "sg:city":"Banbury",
    "sg:classifiers":[
        {
            "category":"Professional",
            "subcategory":"Lawyer & Legal Services",
            "type":"Services"
        }
    ],
    "sg:phone":"+44 1295 257328",
    "sg:postcode":"OX16 5UA",
    "sg:province":"Oxfordshire",
    "sg:tags":[
        "solicitor"
    ],
    "wof:name":"Leport & Co. (Solicitors)",
    "wof:placetype":"venue"
},
  "geometry": {"coordinates":[-1.335208,52.062031],"type":"Point"}
}