{
  "type": "Feature",
  "properties": {
    "addr:full":"Main St Burrelton Blairgowrie Angus PH13 9NT",
    "addr:postcode":"ph13 9nt",
    "addr:street":"Main St",
    "iso:country":"GB",
    "sg:address":"Main St Burrelton",
    "sg:city":"Blairgowrie",
    "sg:classifiers":[
        {
            "category":"Home & Garden",
            "subcategory":"Hardware",
            "type":"Retail Goods"
        }
    ],
    "sg:phone":"+44 1828 670229",
    "sg:postcode":"PH13 9NT",
    "sg:province":"Angus",
    "sg:tags":[
        "part",
        "accessory"
    ],
    "wof:name":"Marrs Motorcycles Ltd.",
    "wof:placetype":"venue"
},
  "geometry": {"coordinates":[-3.3024690151,56.5160331726],"type":"Point"}
}