{
  "type": "Feature",
  "properties": {
    "addr:full":"1 Waterloo Road Liverpool Merseyside L22 1RE",
    "addr:housenumber":"1",
    "addr:postcode":"l22 1re",
    "addr:street":"Waterloo Road",
    "iso:country":"GB",
    "sg:address":"1 Waterloo Road",
    "sg:city":"Liverpool",
    "sg:classifiers":[
        {
            "category":"Retail",
            "subcategory":"Auto Repair",
            "type":"Services"
        }
    ],
    "sg:phone":"+44 151 474 0011",
    "sg:postcode":"L22 1RE",
    "sg:province":"Merseyside",
    "sg:tags":[
        "modification",
        "garage"
    ],
    "wof:name":"Waterloo Motor Co",
    "wof:placetype":"venue"
},
  "geometry": {"coordinates":[-3.0240778923,53.4707260132],"type":"Point"}
}