{
  "type": "Feature",
  "properties": {
    "addr:full":"St Lawrence Hall, St Lawrence Hill, St Lawrence Southminster Essex CM0 7LN",
    "addr:postcode":"st;cm0 7ln",
    "addr:street":"St Lawrence Hill;Southminster",
    "iso:country":"GB",
    "sg:address":"St Lawrence Hall, St Lawrence Hill, St Lawrence",
    "sg:city":"Southminster",
    "sg:classifiers":[
        {
            "category":"Farming",
            "subcategory":"Crops",
            "type":"Manufacturing & Wholesale Goods"
        },
        {
            "category":"Banks & Credit Unions",
            "subcategory":"Investment Brokerage",
            "type":"Services"
        }
    ],
    "sg:phone":"+44 1621 779473",
    "sg:postcode":"CM0 7LN",
    "sg:province":"Essex",
    "sg:tags":[
        "arable",
        "contractor"
    ],
    "wof:name":"R Procter Farms Ltd",
    "wof:placetype":"venue"
},
  "geometry": {"coordinates":[0.8233850002,51.7195968628],"type":"Point"}
}