{
  "type": "Feature",
  "properties": {
    "iso:country":"GB",
    "sg:address":"235 Edgware Road, Colindale",
    "sg:city":"London",
    "sg:classifiers":[
        {
            "category":"Shopping",
            "subcategory":"Pharmacy",
            "type":"Retail Goods"
        }
    ],
    "sg:phone":"+44 20 8205 6937",
    "sg:postcode":"NW9 6LU",
    "sg:province":"Greater London",
    "sg:tags":[
        "pharmacist",
        "chemist"
    ],
    "wof:name":"V K Kumrai",
    "wof:placetype":"venue"
},
  "geometry": {"coordinates":[-0.256124,51.591095],"type":"Point"}
}