{
  "type": "Feature",
  "properties": {
    "iso:country":"GB",
    "sg:address":"288 Crow Lane",
    "sg:city":"Romford",
    "sg:classifiers":[
        {
            "category":"Retail",
            "subcategory":"Auto Repair",
            "type":"Services"
        }
    ],
    "sg:phone":"+44 1708 723001",
    "sg:postcode":"RM7 0HJ",
    "sg:province":"Essex",
    "sg:tags":[
        "body",
        "car"
    ],
    "wof:name":"V J Cross",
    "wof:placetype":"venue"
},
  "geometry": {"coordinates":[0.150122,51.569004],"type":"Point"}
}