{
  "type": "Feature",
  "properties": {
    "addr:full":"16 New Market Beccles Norfolk NR34 9HB",
    "addr:housenumber":"16",
    "addr:postcode":"nr34 9hb",
    "addr:street":"New Market",
    "iso:country":"GB",
    "sg:address":"16 New Market",
    "sg:city":"Beccles",
    "sg:classifiers":[
        {
            "category":"Shopping",
            "subcategory":"Pharmacy",
            "type":"Retail Goods"
        }
    ],
    "sg:phone":"+44 1502 712136",
    "sg:postcode":"NR34 9HB",
    "sg:province":"Norfolk",
    "sg:tags":[
        "store",
        "drug",
        "outlet"
    ],
    "wof:name":"Superdrug Stores Plc",
    "wof:placetype":"venue"
},
  "geometry": {"coordinates":[1.562683,52.457546],"type":"Point"}
}