{
  "type": "Feature",
  "properties": {
    "addr:full":"Great Square Braintree Essex CM7 7TX",
    "addr:postcode":"cm7 7tx",
    "addr:street":"Great Square",
    "iso:country":"GB",
    "sg:address":"Great Square",
    "sg:city":"Braintree",
    "sg:classifiers":[
        {
            "category":"Personal",
            "subcategory":"Barber",
            "type":"Services"
        }
    ],
    "sg:phone":"+44 1376 321048",
    "sg:postcode":"CM7 7TX",
    "sg:province":"Essex",
    "sg:tags":[
        "men's",
        "hairdresser"
    ],
    "wof:name":"Esquire",
    "wof:placetype":"venue"
},
  "geometry": {"coordinates":[0.5511050224,51.8785133362],"type":"Point"}
}