{
  "type": "Feature",
  "properties": {
    "iso:country":"GB",
    "sg:address":"66-68 Southchurch Avenue",
    "sg:city":"Southend-on-sea",
    "sg:classifiers":[
        {
            "category":"Restaurant",
            "type":"Food & Drink"
        }
    ],
    "sg:phone":"+44 1702 468412",
    "sg:postcode":"SS1 2RR",
    "sg:province":"Essex",
    "wof:name":"Mr Mings Garden Restaurant",
    "wof:placetype":"venue"
},
  "geometry": {"coordinates":[0.723845005,51.5363311768],"type":"Point"}
}