{
  "type": "Feature",
  "properties": {
    "addr:full":"Wcc Depot, Honington Shipston-on-stour Warwickshire CV36 5AD",
    "addr:postcode":"cv36 5ad",
    "iso:country":"GB",
    "sg:address":"Wcc Depot, Honington",
    "sg:city":"Shipston-on-stour",
    "sg:classifiers":[
        {
            "category":"Utilities",
            "subcategory":"Refuse",
            "type":"Services"
        }
    ],
    "sg:phone":"+44 1608 663560",
    "sg:postcode":"CV36 5AD",
    "sg:province":"Warwickshire",
    "sg:tags":[
        "disposal",
        "waste",
        "retail"
    ],
    "wof:name":"Shipston Household Waste Site",
    "wof:placetype":"venue"
},
  "geometry": {"coordinates":[-1.568624,52.028473],"type":"Point"}
}