{
  "type": "Feature",
  "properties": {
    "addr:full":"Moorview Crescent Newcastle-upon-tyne Tyne and Wear NE5 3HY",
    "addr:postcode":"ne5 3hy",
    "addr:street":"Moorview Crescent",
    "iso:country":"GB",
    "sg:address":"Moorview Crescent",
    "sg:city":"Newcastle-upon-tyne",
    "sg:classifiers":[
        {
            "category":"Education",
            "subcategory":"School",
            "type":"Public Place"
        }
    ],
    "sg:phone":"+44 191 286 9658",
    "sg:postcode":"NE5 3HY",
    "sg:province":"Tyne and Wear",
    "sg:tags":[
        "local",
        "authority"
    ],
    "wof:name":"Montagu Primary School",
    "wof:placetype":"venue"
},
  "geometry": {"coordinates":[-1.6566009521,54.9965171814],"type":"Point"}
}