{
  "type": "Feature",
  "properties": {
    "iso:country":"GB",
    "sg:address":"59 Eton Square, Eton",
    "sg:city":"Windsor",
    "sg:classifiers":[
        {
            "category":"Social Services",
            "subcategory":"Adult Care",
            "type":"Services"
        }
    ],
    "sg:phone":"+44 1753 833371",
    "sg:postcode":"SL4 6AL",
    "sg:province":"Berkshire",
    "sg:tags":[
        "day",
        "centre"
    ],
    "wof:name":"Charterist House Day Centre",
    "wof:placetype":"venue"
},
  "geometry": {"coordinates":[-0.6083419919,51.4877166748],"type":"Point"}
}