{
  "type": "Feature",
  "properties": {
    "iso:country":"GB",
    "sg:address":"61 Paddington St",
    "sg:city":"West End",
    "sg:classifiers":[
        {
            "category":"Professional",
            "subcategory":"Engineering",
            "type":"Services"
        }
    ],
    "sg:phone":"+44 20 7935 1638",
    "sg:postcode":"W1M 3RR",
    "sg:province":"Hampshire",
    "sg:tags":[
        "contractor",
        "electrical",
        "engineer"
    ],
    "wof:name":"Baldwin Electrical Co Lt",
    "wof:placetype":"venue"
},
  "geometry": {"coordinates":[-0.152437,51.520603],"type":"Point"}
}