{
  "type": "Feature",
  "properties": {
    "addr:full":"41 Mayflower St Plymouth Devon PL1 1QL",
    "addr:housenumber":"41",
    "addr:postcode":"pl1 1ql",
    "addr:street":"Mayflower St",
    "iso:country":"GB",
    "sg:address":"41 Mayflower St",
    "sg:city":"Plymouth",
    "sg:classifiers":[
        {
            "category":"Shopping",
            "subcategory":"Stationery & Office Supplies",
            "type":"Retail Goods"
        }
    ],
    "sg:phone":"+44 1752 668399",
    "sg:postcode":"PL1 1QL",
    "sg:province":"Devon",
    "wof:name":"Statprint Office Supplies",
    "wof:placetype":"venue"
},
  "geometry": {"coordinates":[-4.141904,50.373207],"type":"Point"}
}