{
  "type": "Feature",
  "properties": {
    "addr:full":"2 Rhyl St Fleetwood Lancashire FY7 6BB",
    "addr:housenumber":"2",
    "addr:postcode":"fy7 6bb",
    "addr:street":"Rhyl St",
    "iso:country":"GB",
    "sg:address":"2 Rhyl St",
    "sg:city":"Fleetwood",
    "sg:classifiers":[
        {
            "category":"Food & Beverages",
            "subcategory":"Meat & Fish",
            "type":"Retail Goods"
        }
    ],
    "sg:phone":"+44 1253 875832",
    "sg:postcode":"FY7 6BB",
    "sg:province":"Lancashire",
    "sg:tags":[
        "chip"
    ],
    "wof:name":"Hamptons Fish & Chips",
    "wof:placetype":"venue"
},
  "geometry": {"coordinates":[-3.012401,53.925373],"type":"Point"}
}