{
  "type": "Feature",
  "properties": {
    "addr:full":"6 Commerce Way Croydon Surrey CR0 4XA",
    "addr:housenumber":"6",
    "addr:postcode":"cr0 4xa",
    "addr:street":"Commerce Way",
    "iso:country":"GB",
    "sg:address":"6 Commerce Way",
    "sg:city":"Croydon",
    "sg:classifiers":[
        {
            "category":"Professional",
            "type":"Services"
        }
    ],
    "sg:phone":"+44 20 8256 0180",
    "sg:postcode":"CR0 4XA",
    "sg:province":"Surrey",
    "sg:tags":[
        "display",
        "maker"
    ],
    "wof:name":"Aztec Displays Ltd.",
    "wof:placetype":"venue"
},
  "geometry": {"coordinates":[-0.121089,51.37389],"type":"Point"}
}