{
  "type": "Feature",
  "properties": {
    "iso:country":"GB",
    "sg:address":"Unit 3 Daniels Indust Est, Bath Rd",
    "sg:city":"Stroud",
    "sg:classifiers":[
        {
            "category":"Professional",
            "subcategory":"Business Services",
            "type":"Services"
        }
    ],
    "sg:phone":"+44 1453 755800",
    "sg:postcode":"GL6 0JB",
    "sg:province":"Gloucestershire",
    "sg:tags":[
        "distribution"
    ],
    "wof:name":"Hillier Hipkins Ltd",
    "wof:placetype":"venue"
},
  "geometry": {"coordinates":[-2.2188100815,51.6924705505],"type":"Point"}
}