{
  "type": "Feature",
  "properties": {
    "iso:country":"GB",
    "sg:address":"Mid Suffolk Branch, Coddenham Road, 4 Fairfax Gardens",
    "sg:city":"Ipswich",
    "sg:classifiers":[
        {
            "category":"Organizations",
            "subcategory":"Non-profit Organization",
            "type":"Services"
        }
    ],
    "sg:postcode":"IP6 8AZ",
    "sg:province":"Suffolk",
    "sg:tags":[
        "organisation",
        "voluntary",
        "charity"
    ],
    "wof:name":"Alzheimer's Society",
    "wof:placetype":"venue"
},
  "geometry": {"coordinates":[1.0551799536,52.1518592834],"type":"Point"}
}