{
  "type": "Feature",
  "properties": {
    "addr:full":"12 Belle Vale Shopping Centre Liverpool Merseyside L25 2RF",
    "addr:housenumber":"12",
    "addr:postcode":"l25 2rf",
    "addr:street":"Belle Vale Shopping Centre",
    "iso:country":"GB",
    "sg:address":"12 Belle Vale Shopping Centre",
    "sg:city":"Liverpool",
    "sg:classifiers":[
        {
            "category":"Shopping",
            "subcategory":"Baby Store",
            "type":"Retail Goods"
        }
    ],
    "sg:postcode":"L25 2RF",
    "sg:province":"Merseyside",
    "sg:tags":[
        "babywear",
        "childrens"
    ],
    "wof:name":"Small World",
    "wof:placetype":"venue"
},
  "geometry": {"coordinates":[-2.861194,53.389744],"type":"Point"}
}