{
  "type": "Feature",
  "properties": {
    "addr:full":"14 Begbroke Lane, Begbroke Kidlington Buckinghamshire OX5 1RN",
    "addr:housenumber":"14",
    "addr:postcode":"ox5 1rn",
    "addr:street":"Begbroke Lane",
    "iso:country":"GB",
    "sg:address":"14 Begbroke Lane, Begbroke",
    "sg:city":"Kidlington",
    "sg:classifiers":[
        {
            "category":"Building & Trades",
            "subcategory":"Landscaping Services",
            "type":"Services"
        }
    ],
    "sg:phone":"+44 1865 371227",
    "sg:postcode":"OX5 1RN",
    "sg:province":"Buckinghamshire",
    "sg:tags":[
        "gardening"
    ],
    "wof:name":"Cherwell Garden Services",
    "wof:placetype":"venue"
},
  "geometry": {"coordinates":[-1.316285,51.824139],"type":"Point"}
}