{
  "type": "Feature",
  "properties": {
    "iso:country":"GB",
    "sg:address":"4 The Arcade, High Street",
    "sg:city":"Brentwood",
    "sg:classifiers":[
        {
            "category":"Shopping",
            "subcategory":"Florist",
            "type":"Retail Goods"
        }
    ],
    "sg:phone":"+44 1277 223783",
    "sg:postcode":"CM14 4AH",
    "sg:province":"Essex",
    "wof:name":"T & P Burrows Ltd.",
    "wof:placetype":"venue"
},
  "geometry": {"coordinates":[0.302834,51.620445],"type":"Point"}
}