{
  "type": "Feature",
  "properties": {
    "addr:full":"36 Gaol Lane Sudbury Essex CO10 1JL",
    "addr:housenumber":"36",
    "addr:postcode":"co10 1jl",
    "addr:street":"Gaol Lane",
    "iso:country":"GB",
    "sg:address":"36 Gaol Lane",
    "sg:city":"Sudbury",
    "sg:classifiers":[
        {
            "category":"Shopping",
            "subcategory":"Used Merchandise",
            "type":"Retail Goods"
        }
    ],
    "sg:postcode":"CO10 1JL",
    "sg:province":"Essex",
    "sg:tags":[
        "shop",
        "second-hand"
    ],
    "wof:name":"Arkwrights",
    "wof:placetype":"venue"
},
  "geometry": {"coordinates":[0.730745,52.039364],"type":"Point"}
}