{
  "type": "Feature",
  "properties": {
    "addr:full":"Middle Cragg Farm, Dolphinholme Lancaster Lancashire LA2 9AS",
    "addr:postcode":"la2 9as",
    "addr:street":"Middle Cragg;Dolphinholme",
    "iso:country":"GB",
    "sg:address":"Middle Cragg Farm, Dolphinholme",
    "sg:city":"Lancaster",
    "sg:classifiers":[
        {
            "category":"Farming",
            "subcategory":"Farm",
            "type":"Manufacturing & Wholesale Goods"
        }
    ],
    "sg:postcode":"LA2 9AS",
    "sg:province":"Lancashire",
    "sg:tags":[
        "mixed",
        "crop"
    ],
    "wof:name":"J Carter",
    "wof:placetype":"venue"
},
  "geometry": {"coordinates":[-2.739269,53.974571],"type":"Point"}
}