{
  "type": "Feature",
  "properties": {
    "addr:full":"The Dental Practice, 97 South Street Dorking Surrey RH4 2JU",
    "addr:housenumber":"97",
    "addr:postcode":"rh4 2ju",
    "addr:street":"South Street",
    "iso:country":"GB",
    "sg:address":"The Dental Practice, 97 South Street",
    "sg:city":"Dorking",
    "sg:classifiers":[
        {
            "category":"Health Services",
            "subcategory":"Health Practitioner",
            "type":"Services"
        }
    ],
    "sg:postcode":"RH4 2JU",
    "sg:province":"Surrey",
    "sg:tags":[
        "osteopath"
    ],
    "wof:name":"Samantha Taylor & Matthew Davies",
    "wof:placetype":"venue"
},
  "geometry": {"coordinates":[-0.3288139999,51.233341217],"type":"Point"}
}