{
  "type": "Feature",
  "properties": {
    "iso:country":"GB",
    "sg:address":"Front Street, Langtoft",
    "sg:city":"Driffield",
    "sg:classifiers":[
        {
            "category":"Farming",
            "subcategory":"Livestock Farm",
            "type":"Manufacturing & Wholesale Goods"
        }
    ],
    "sg:postcode":"YO25 3TF",
    "sg:province":"East Riding of Yorkshire",
    "sg:tags":[
        "others"
    ],
    "wof:name":"M Field",
    "wof:placetype":"venue"
},
  "geometry": {"coordinates":[-0.3434,54.135403],"type":"Point"}
}