{
  "type": "Feature",
  "properties": {
    "addr:full":"Rectory Farm, Thornton-le-clay York North Yorkshire YO60 7QA",
    "addr:postcode":"yo60 7qa",
    "addr:street":"Rectory",
    "iso:country":"GB",
    "sg:address":"Rectory Farm, Thornton-le-clay",
    "sg:city":"York",
    "sg:classifiers":[
        {
            "category":"Farming",
            "subcategory":"Livestock Farm",
            "type":"Manufacturing & Wholesale Goods"
        }
    ],
    "sg:phone":"+44 1904 468217",
    "sg:postcode":"YO60 7QA",
    "sg:province":"North Yorkshire",
    "sg:tags":[
        "others"
    ],
    "wof:name":"C T Fothergill & Sons",
    "wof:placetype":"venue"
},
  "geometry": {"coordinates":[-0.9545750022,54.0770111084],"type":"Point"}
}