{
  "type": "Feature",
  "properties": {
    "addr:full":"43-47 Petersham Road Richmond Greater London TW10 6UL",
    "addr:housenumber":"43-47",
    "addr:postcode":"tw10 6ul",
    "addr:street":"Petersham Road",
    "iso:country":"GB",
    "sg:address":"43-47 Petersham Road",
    "sg:city":"Richmond",
    "sg:classifiers":[
        {
            "category":"Travel",
            "subcategory":"Hotels & Motels",
            "type":"Entertainment"
        }
    ],
    "sg:phone":"+44 20 8940 0435",
    "sg:postcode":"TW10 6UL",
    "sg:province":"Greater London",
    "wof:name":"Hobart Hall Hotel",
    "wof:placetype":"venue"
},
  "geometry": {"coordinates":[-0.303762,51.456459],"type":"Point"}
}