{
  "type": "Feature",
  "properties": {
    "addr:full":"2 Queen St, Sandhurst Cranbrook East Sussex TN18 5HY",
    "addr:housenumber":"2",
    "addr:postcode":"tn18 5hy",
    "addr:street":"Queen St",
    "iso:country":"GB",
    "sg:address":"2 Queen St, Sandhurst",
    "sg:city":"Cranbrook",
    "sg:classifiers":[
        {
            "category":"Real Estate",
            "subcategory":"Real Estate Agent",
            "type":"Services"
        }
    ],
    "sg:phone":"+44 1580 850850",
    "sg:postcode":"TN18 5HY",
    "sg:province":"East Sussex",
    "wof:name":"Freeman Forman",
    "wof:placetype":"venue"
},
  "geometry": {"coordinates":[0.5635499954,51.0269546509],"type":"Point"}
}