{
  "type": "Feature",
  "properties": {
    "iso:country":"GB",
    "sg:address":"219 Knightsfield",
    "sg:city":"Welwyn Garden City",
    "sg:classifiers":[
        {
            "category":"Building & Trades",
            "subcategory":"Construction",
            "type":"Services"
        }
    ],
    "sg:postcode":"AL8 7QL",
    "sg:province":"Hertfordshire",
    "sg:tags":[
        "restoration",
        "refurbishment"
    ],
    "wof:name":"Dring,Peter,",
    "wof:placetype":"venue"
},
  "geometry": {"coordinates":[-0.205211,51.816704],"type":"Point"}
}