{
  "type": "Feature",
  "properties": {
    "addr:full":"28 Reading Road, Woodley Reading Berkshire RG5 3DB",
    "addr:housenumber":"28",
    "addr:postcode":"rg5 3db",
    "addr:street":"Reading Road",
    "iso:country":"GB",
    "sg:address":"28 Reading Road, Woodley",
    "sg:city":"Reading",
    "sg:classifiers":[
        {
            "category":"Professional",
            "subcategory":"Research",
            "type":"Services"
        }
    ],
    "sg:phone":"+44 118 969 3287",
    "sg:postcode":"RG5 3DB",
    "sg:province":"Berkshire",
    "sg:tags":[
        "organisation"
    ],
    "wof:name":"Mystery Shopper Services",
    "wof:placetype":"venue"
},
  "geometry": {"coordinates":[-0.906997,51.454739],"type":"Point"}
}