{
  "type": "Feature",
  "properties": {
    "addr:full":"9-11 Old Market Street Manchester Greater Manchester M9 8DT",
    "addr:housenumber":"9-11",
    "addr:postcode":"m9 8dt",
    "addr:street":"Old Market Street",
    "iso:country":"GB",
    "sg:address":"9-11 Old Market Street",
    "sg:city":"Manchester",
    "sg:classifiers":[
        {
            "category":"Autos & Motor Vehicles",
            "subcategory":"Auto Supplies",
            "type":"Retail Goods"
        }
    ],
    "sg:phone":"+44 161 721 4646",
    "sg:postcode":"M9 8DT",
    "sg:province":"Greater Manchester",
    "sg:tags":[
        "tyre"
    ],
    "wof:name":"Tyres-R-Us",
    "wof:placetype":"venue"
},
  "geometry": {"coordinates":[-2.218541,53.521427],"type":"Point"}
}