{
  "type": "Feature",
  "properties": {
    "addr:full":"Valley Mills Trading Estate, 344 Meanwood Rd Leeds West Yorkshire LS7 2JF",
    "addr:housenumber":"344",
    "addr:postcode":"ls7 2jf",
    "addr:street":"Meanwood Rd",
    "iso:country":"GB",
    "sg:address":"Valley Mills Trading Estate, 344 Meanwood Rd",
    "sg:city":"Leeds",
    "sg:classifiers":[
        {
            "category":"Building & Trades",
            "subcategory":"Electrical",
            "type":"Services"
        }
    ],
    "sg:phone":"+44 113 237 4258",
    "sg:postcode":"LS7 2JF",
    "sg:province":"West Yorkshire",
    "sg:tags":[
        "galvanising"
    ],
    "wof:name":"Meanwood Metal Finishing",
    "wof:placetype":"venue"
},
  "geometry": {"coordinates":[-1.54911,53.817421],"type":"Point"}
}