{
  "type": "Feature",
  "properties": {
    "addr:full":"St Marys Place Market Harborough Leicestershire LE16 7DR",
    "addr:postcode":"le16 7dr",
    "addr:street":"St Marys Place",
    "iso:country":"GB",
    "sg:address":"St Marys Place",
    "sg:city":"Market Harborough",
    "sg:classifiers":[
        {
            "category":"Sports & Exercise",
            "subcategory":"Sports Center",
            "type":"Entertainment"
        }
    ],
    "sg:phone":"+44 1858 461600",
    "sg:postcode":"LE16 7DR",
    "sg:province":"Leicestershire",
    "sg:tags":[
        "shop",
        "good"
    ],
    "wof:name":"Sportsworld (G B) Plc",
    "wof:placetype":"venue"
},
  "geometry": {"coordinates":[-0.9194210172,52.4777297974],"type":"Point"}
}