{
  "type": "Feature",
  "properties": {
    "iso:country":"GB",
    "sg:address":"41 Worsley Road, Swinton",
    "sg:city":"Manchester",
    "sg:classifiers":[
        {
            "category":"Food & Beverages",
            "subcategory":"Liquor & Beverages",
            "type":"Retail Goods"
        }
    ],
    "sg:phone":"+44 161 794 2819",
    "sg:postcode":"M27 5WN",
    "sg:province":"Greater Manchester",
    "sg:tags":[
        "beer",
        "wine",
        "spirit",
        "wines"
    ],
    "wof:name":"JOAN BUCKLEY",
    "wof:placetype":"venue"
},
  "geometry": {"coordinates":[-2.335712,53.507435],"type":"Point"}
}