{
  "type": "Feature",
  "properties": {
    "iso:country":"GB",
    "sg:address":"639 Nuthall Rd",
    "sg:city":"Nottingham",
    "sg:classifiers":[
        {
            "category":"Shopping",
            "subcategory":"Computers & Home Electronics",
            "type":"Retail Goods"
        }
    ],
    "sg:phone":"+44 115 913 5468",
    "sg:postcode":"NG8 6AF",
    "sg:province":"Nottinghamshire",
    "wof:name":"Echotech Game World",
    "wof:placetype":"venue"
},
  "geometry": {"coordinates":[-1.200195,52.984772],"type":"Point"}
}