{
  "type": "Feature",
  "properties": {
    "iso:country":"GB",
    "sg:address":"18 Harley St",
    "sg:city":"Glasgow",
    "sg:classifiers":[
        {
            "category":"Building & Trades",
            "subcategory":"Construction",
            "type":"Services"
        }
    ],
    "sg:phone":"+44 141 427 1222",
    "sg:postcode":"G31 1AH",
    "sg:province":"Glasgow City",
    "sg:tags":[
        "dry",
        "lining",
        "plasterers",
        "screeders"
    ],
    "wof:name":"David Mitchell",
    "wof:placetype":"venue"
},
  "geometry": {"coordinates":[-4.2175998688,55.8582687378],"type":"Point"}
}