{
  "type": "Feature",
  "properties": {
    "iso:country":"GB",
    "sg:address":"Bank Mill Wharf",
    "sg:city":"Berkhamsted",
    "sg:classifiers":[
        {
            "category":"Education",
            "subcategory":"Special Training",
            "type":"Public Place"
        }
    ],
    "sg:phone":"+44 1442 877172",
    "sg:postcode":"HP4 2NT",
    "sg:province":"Bedfordshire",
    "sg:tags":[
        "product",
        "centre"
    ],
    "wof:name":"Wild Track Business Solutions Ltd.",
    "wof:placetype":"venue"
},
  "geometry": {"coordinates":[-0.549546,51.757324],"type":"Point"}
}