{
  "type": "Feature",
  "properties": {
    "iso:country":"GB",
    "sg:address":"Edge Fold Industrial Estate, Plodder Lane, Farnworth",
    "sg:city":"Bolton",
    "sg:classifiers":[
        {
            "category":"Professional",
            "subcategory":"Business Services",
            "type":"Services"
        }
    ],
    "sg:phone":"+44 1204 665444",
    "sg:postcode":"BL4 0LR",
    "sg:province":"Lancashire",
    "sg:tags":[
        "distribution"
    ],
    "wof:name":"Waterline Ltd.",
    "wof:placetype":"venue"
},
  "geometry": {"coordinates":[-2.417426,53.556377],"type":"Point"}
}