{
  "type": "Feature",
  "properties": {
    "iso:country":"GB",
    "sg:address":"119 Lansdowne Way",
    "sg:city":"London",
    "sg:classifiers":[
        {
            "category":"Organizations",
            "subcategory":"Non-profit Organization",
            "type":"Services"
        }
    ],
    "sg:phone":"+44 20 7978 1683",
    "sg:postcode":"SW8 2NP",
    "sg:province":"Greater London",
    "sg:tags":[
        "charitable",
        "organisation",
        "voluntary",
        "charity"
    ],
    "wof:name":"Breslaff Centre",
    "wof:placetype":"venue"
},
  "geometry": {"coordinates":[-0.1301169991,51.4752807617],"type":"Point"}
}