{
  "type": "Feature",
  "properties": {
    "iso:country":"GB",
    "sg:address":"Unit 3 46 York St",
    "sg:city":"Luton",
    "sg:classifiers":[
        {
            "category":"Shopping",
            "subcategory":"Clothing, Apparel, & Fashions",
            "type":"Retail Goods"
        }
    ],
    "sg:phone":"+44 1582 413081",
    "sg:postcode":"LU2 0HA",
    "sg:province":"Bedfordshire",
    "sg:tags":[
        "clothing",
        "fabric"
    ],
    "wof:name":"W Finn & Co",
    "wof:placetype":"venue"
},
  "geometry": {"coordinates":[-0.409739,51.884781],"type":"Point"}
}