{
  "type": "Feature",
  "properties": {
    "iso:country":"GB",
    "sg:address":"52 Old Compton Street",
    "sg:city":"London",
    "sg:classifiers":[
        {
            "category":"Personal",
            "type":"Services"
        }
    ],
    "sg:phone":"+44 20 7437 2916",
    "sg:postcode":"W1D 4PB",
    "sg:province":"Greater London",
    "sg:tags":[
        "wedding"
    ],
    "wof:name":"Bomboniere Connection",
    "wof:placetype":"venue"
},
  "geometry": {"coordinates":[-0.132305,51.512932],"type":"Point"}
}