{
  "type": "Feature",
  "properties": {
    "iso:country":"GB",
    "sg:address":"56 Terminus Road",
    "sg:city":"Eastbourne",
    "sg:classifiers":[
        {
            "category":"Personal",
            "subcategory":"Beauty Salon",
            "type":"Services"
        }
    ],
    "sg:phone":"+44 1323 430070",
    "sg:postcode":"BN21 3LX",
    "sg:province":"East Sussex",
    "sg:tags":[
        "unisex",
        "hairdresser"
    ],
    "wof:name":"Graham Webb International",
    "wof:placetype":"venue"
},
  "geometry": {"coordinates":[0.281921,50.768738],"type":"Point"}
}