{
  "type": "Feature",
  "properties": {
    "iso:country":"GB",
    "sg:address":"Main Street, Sibford Ferris",
    "sg:city":"Banbury",
    "sg:classifiers":[
        {
            "category":"Shopping",
            "subcategory":"Department Store",
            "type":"Retail Goods"
        }
    ],
    "sg:phone":"+44 1295 788317",
    "sg:postcode":"OX15 5RG",
    "sg:province":"Oxfordshire",
    "wof:name":"Sibford Ferris Stores & Post Office",
    "wof:placetype":"venue"
},
  "geometry": {"coordinates":[-1.482974,52.031166],"type":"Point"}
}