{
  "type": "Feature",
  "properties": {
    "addr:full":"Elm Farm, Mill Road, Stratton Audley Bicester Buckinghamshire OX27 9BJ",
    "addr:postcode":"ox27 9bj",
    "addr:street":"Mill Road",
    "iso:country":"GB",
    "sg:address":"Elm Farm, Mill Road, Stratton Audley",
    "sg:city":"Bicester",
    "sg:classifiers":[
        {
            "category":"Farming",
            "subcategory":"Dairy Farm",
            "type":"Manufacturing & Wholesale Goods"
        }
    ],
    "sg:phone":"+44 1869 277204",
    "sg:postcode":"OX27 9BJ",
    "sg:province":"Buckinghamshire",
    "sg:tags":[
        "farmer"
    ],
    "wof:name":"Goss Bros",
    "wof:placetype":"venue"
},
  "geometry": {"coordinates":[-1.118543,51.931217],"type":"Point"}
}