{
  "type": "Feature",
  "properties": {
    "iso:country":"GB",
    "sg:address":"Beech Ho, Tydehams",
    "sg:city":"Newbury",
    "sg:classifiers":[
        {
            "category":"Banks & Credit Unions",
            "subcategory":"Financial Services",
            "type":"Services"
        }
    ],
    "sg:postcode":"RG14 6JT",
    "sg:province":"Berkshire",
    "sg:tags":[
        "claim",
        "assessor"
    ],
    "wof:name":"Claims Force Ltd",
    "wof:placetype":"venue"
},
  "geometry": {"coordinates":[-1.335369,51.385731],"type":"Point"}
}