{
  "type": "Feature",
  "properties": {
    "addr:full":"6 Eaglesham Rd Glasgow East Ayrshire G77 5BG",
    "addr:housenumber":"6",
    "addr:postcode":"g77 5bg",
    "addr:street":"Eaglesham Rd",
    "iso:country":"GB",
    "sg:address":"6 Eaglesham Rd",
    "sg:city":"Glasgow",
    "sg:classifiers":[
        {
            "category":"Government",
            "subcategory":"Post Office",
            "type":"Public Place"
        }
    ],
    "sg:postcode":"G77 5BG",
    "sg:province":"East Ayrshire",
    "sg:tags":[
        "organisation",
        "soc",
        "research"
    ],
    "wof:name":"Howat Graham Research",
    "wof:placetype":"venue"
},
  "geometry": {"coordinates":[-4.3323898315,55.7711334229],"type":"Point"}
}