{
  "type": "Feature",
  "properties": {
    "addr:full":"Halcyon, West Rd Bridport Dorset DT6 6AA",
    "addr:postcode":"dt6 6aa",
    "addr:street":"West Rd",
    "iso:country":"GB",
    "sg:address":"Halcyon, West Rd",
    "sg:city":"Bridport",
    "sg:classifiers":[
        {
            "category":"Building & Trades",
            "subcategory":"Construction",
            "type":"Services"
        }
    ],
    "sg:phone":"+44 1308 424630",
    "sg:postcode":"DT6 6AA",
    "sg:province":"Dorset",
    "sg:tags":[
        "builder"
    ],
    "wof:name":"Godfrey R Baker",
    "wof:placetype":"venue"
},
  "geometry": {"coordinates":[-2.758019,50.733566],"type":"Point"}
}