{
  "type": "Feature",
  "properties": {
    "addr:full":"52 Brankin Drive Darlington Durham DL1 4LQ",
    "addr:housenumber":"52",
    "addr:postcode":"dl1 4lq",
    "addr:street":"Brankin Drive",
    "iso:country":"GB",
    "sg:address":"52 Brankin Drive",
    "sg:city":"Darlington",
    "sg:classifiers":[
        {
            "category":"Retail",
            "subcategory":"Driving School",
            "type":"Services"
        }
    ],
    "sg:phone":"+44 1325 350193",
    "sg:postcode":"DL1 4LQ",
    "sg:province":"Durham",
    "wof:name":"Ray's Driving Lessons",
    "wof:placetype":"venue"
},
  "geometry": {"coordinates":[-1.5373760462,54.5126228333],"type":"Point"}
}