{
  "type": "Feature",
  "properties": {
    "addr:full":"Units 7 & 8 Greenline Business Park, Wellington St Burton On Trent Derbyshire DE14 2AS",
    "addr:housenumber":"units 7 & 8",
    "addr:postcode":"de14 2as",
    "addr:street":"Greenline Business Park;St",
    "iso:country":"GB",
    "sg:address":"Units 7 & 8 Greenline Business Park, Wellington St",
    "sg:city":"Burton On Trent",
    "sg:classifiers":[
        {
            "category":"Manufacturing",
            "subcategory":"Petroleum Products",
            "type":"Manufacturing & Wholesale Goods"
        }
    ],
    "sg:phone":"+44 1283 539123",
    "sg:postcode":"DE14 2AS",
    "sg:province":"Derbyshire",
    "sg:tags":[
        "double",
        "glazing"
    ],
    "wof:name":"Trent Windows & Conservatories",
    "wof:placetype":"venue"
},
  "geometry": {"coordinates":[-1.6476999521,52.8049888611],"type":"Point"}
}