{
  "type": "Feature",
  "properties": {
    "addr:full":"24 Carden Hill Brighton East Sussex BN1 8AB",
    "addr:housenumber":"24",
    "addr:postcode":"bn1 8ab",
    "addr:street":"Carden Hill",
    "iso:country":"GB",
    "sg:address":"24 Carden Hill",
    "sg:city":"Brighton",
    "sg:classifiers":[
        {
            "category":"Home & Garden",
            "subcategory":"Building Materials",
            "type":"Retail Goods"
        }
    ],
    "sg:postcode":"BN1 8AB",
    "sg:province":"East Sussex",
    "sg:tags":[
        "fencing"
    ],
    "wof:name":"Felsing Bros",
    "wof:placetype":"venue"
},
  "geometry": {"coordinates":[-0.132852003,50.8564796448],"type":"Point"}
}