{
  "type": "Feature",
  "properties": {
    "iso:country":"GB",
    "sg:address":"54 Fallodon Way",
    "sg:city":"Bristol",
    "sg:classifiers":[
        {
            "category":"Professional",
            "subcategory":"Printing & Photocopies",
            "type":"Services"
        }
    ],
    "sg:phone":"+44 117 962 9459",
    "sg:postcode":"BS9 4HR",
    "sg:province":"City of Bristol",
    "sg:tags":[
        "plate",
        "lithographic",
        "maker"
    ],
    "wof:name":"Safeguard Cheque Printers",
    "wof:placetype":"venue"
},
  "geometry": {"coordinates":[-2.601509,51.49073],"type":"Point"}
}