{
  "type": "Feature",
  "properties": {
    "iso:country":"GB",
    "sg:address":"Wood Street",
    "sg:city":"Barnet",
    "sg:classifiers":[
        {
            "category":"Bars & Pubs",
            "type":"Food & Drink"
        }
    ],
    "sg:phone":"+44 20 8449 6438",
    "sg:postcode":"EN5 4HY",
    "sg:province":"Hertfordshire",
    "sg:tags":[
        "pubs",
        "inn"
    ],
    "wof:name":"The Black Horse",
    "wof:placetype":"venue"
},
  "geometry": {"coordinates":[-0.203724,51.653004],"type":"Point"}
}