{
  "type": "Feature",
  "properties": {
    "addr:full":"New Close Works, Crabmill Lane York North Yorkshire YO61 3DG",
    "addr:postcode":"yo61 3dg",
    "addr:street":"New Close;Crabmill Lane",
    "iso:country":"GB",
    "sg:address":"New Close Works, Crabmill Lane",
    "sg:city":"York",
    "sg:classifiers":[
        {
            "category":"Professional",
            "subcategory":"Engineering",
            "type":"Services"
        }
    ],
    "sg:phone":"+44 1347 821657",
    "sg:postcode":"YO61 3DG",
    "sg:province":"North Yorkshire",
    "wof:name":"G Long",
    "wof:placetype":"venue"
},
  "geometry": {"coordinates":[-1.1933939457,54.1208267212],"type":"Point"}
}