{
  "type": "Feature",
  "properties": {
    "iso:country":"GB",
    "sg:address":"7 West Bank, Abbots Park",
    "sg:city":"Chester",
    "sg:classifiers":[
        {
            "category":"Professional",
            "subcategory":"Art Services",
            "type":"Services"
        }
    ],
    "sg:phone":"+44 1244 376665",
    "sg:postcode":"CH1 4BD",
    "sg:province":"Cheshire",
    "sg:tags":[
        "photographer"
    ],
    "wof:name":"D Turner",
    "wof:placetype":"venue"
},
  "geometry": {"coordinates":[-2.897237,53.204212],"type":"Point"}
}