{
  "type": "Feature",
  "properties": {
    "addr:full":"Preseli School, Preseli Crymych Pembrokeshire SA41 3QH",
    "addr:postcode":"sa41 3qh",
    "addr:street":"Preseli;Pembrokeshire",
    "iso:country":"GB",
    "sg:address":"Preseli School, Preseli",
    "sg:city":"Crymych",
    "sg:classifiers":[
        {
            "category":"Education",
            "subcategory":"University",
            "type":"Public Place"
        }
    ],
    "sg:phone":"+44 1239 831455",
    "sg:postcode":"SA41 3QH",
    "sg:province":"Pembrokeshire",
    "sg:tags":[
        "higher"
    ],
    "wof:name":"Preseli Community Education Centre",
    "wof:placetype":"venue"
},
  "geometry": {"coordinates":[-4.648454,51.971241],"type":"Point"}
}