{
  "type": "Feature",
  "properties": {
    "addr:full":"Fifth Avenue, Cliftonville Margate Kent CT9 2JJ",
    "addr:postcode":"ct9 2jj",
    "addr:street":"Fifth Avenue;Margate",
    "iso:country":"GB",
    "sg:address":"Fifth Avenue, Cliftonville",
    "sg:city":"Margate",
    "sg:classifiers":[
        {
            "category":"Travel",
            "subcategory":"Hotels & Motels",
            "type":"Entertainment"
        }
    ],
    "sg:phone":"+44 1843 221703",
    "sg:postcode":"CT9 2JJ",
    "sg:province":"Kent",
    "wof:name":"Walpole Bay Hotel",
    "wof:placetype":"venue"
},
  "geometry": {"coordinates":[1.4018599987,51.3907814026],"type":"Point"}
}