{
  "type": "Feature",
  "properties": {
    "iso:country":"GB",
    "sg:address":"33 Barnsley Rd, Penistone",
    "sg:city":"Sheffield",
    "sg:classifiers":[
        {
            "category":"Autos & Motor Vehicles",
            "subcategory":"Motorcycle Sales",
            "type":"Retail Goods"
        }
    ],
    "sg:phone":"+44 1226 765447",
    "sg:postcode":"S36 8AE",
    "sg:province":"South Yorkshire",
    "sg:tags":[
        "component"
    ],
    "wof:name":"S.R.A Services",
    "wof:placetype":"venue"
},
  "geometry": {"coordinates":[-1.6107039452,53.5348243713],"type":"Point"}
}