{
  "type": "Feature",
  "properties": {
    "iso:country":"GB",
    "sg:address":"Leven Road, Lundin Links",
    "sg:city":"Leven",
    "sg:classifiers":[
        {
            "category":"Travel",
            "subcategory":"Hotels & Motels",
            "type":"Entertainment"
        }
    ],
    "sg:phone":"+44 1333 320207",
    "sg:postcode":"KY8 6AP",
    "sg:province":"Fife",
    "wof:name":"The Lundin Links Hotel",
    "wof:placetype":"venue"
},
  "geometry": {"coordinates":[-2.963414,56.21212],"type":"Point"}
}