{
  "type": "Feature",
  "properties": {
    "addr:full":"8 The Schoolhouse, Second Avenue, Trafford Park Manchester Cheshire M17 1DZ",
    "addr:housenumber":"8",
    "addr:postcode":"m17 1dz",
    "addr:street":"The;Second Avenue Trafford",
    "iso:country":"GB",
    "sg:address":"8 The Schoolhouse, Second Avenue, Trafford Park",
    "sg:city":"Manchester",
    "sg:classifiers":[
        {
            "category":"Professional",
            "subcategory":"Art Services",
            "type":"Services"
        }
    ],
    "sg:phone":"+44 161 877 1131",
    "sg:postcode":"M17 1DZ",
    "sg:province":"Cheshire",
    "sg:tags":[
        "graphic",
        "designer"
    ],
    "wof:name":"Qudos Creative",
    "wof:placetype":"venue"
},
  "geometry": {"coordinates":[-2.308359,53.46814],"type":"Point"}
}