{
  "type": "Feature",
  "properties": {
    "iso:country":"GB",
    "sg:address":"3 The Cutting, Hampstead Norreys",
    "sg:city":"Thatcham",
    "sg:classifiers":[
        {
            "category":"Wholesale",
            "subcategory":"Vending Machines",
            "type":"Manufacturing & Wholesale Goods"
        }
    ],
    "sg:postcode":"RG18 0RR",
    "sg:province":"Berkshire",
    "wof:name":"Beacon Vending",
    "wof:placetype":"venue"
},
  "geometry": {"coordinates":[-1.241555,51.483898],"type":"Point"}
}