{
  "type": "Feature",
  "properties": {
    "iso:country":"GB",
    "sg:address":"108 High Street",
    "sg:city":"Lee-on-the-solent",
    "sg:classifiers":[
        {
            "category":"Shopping",
            "subcategory":"News",
            "type":"Retail Goods"
        }
    ],
    "sg:phone":"+44 23 9255 2110",
    "sg:postcode":"PO13 9DA",
    "sg:province":"Hampshire",
    "sg:tags":[
        "newsagent"
    ],
    "wof:name":"Lee News & Post Office",
    "wof:placetype":"venue"
},
  "geometry": {"coordinates":[-1.201738,50.801689],"type":"Point"}
}