{
  "type": "Feature",
  "properties": {
    "addr:full":"Brazennose House East, Lincoln Square Manchester Greater Manchester M2 5BP",
    "addr:postcode":"m2 5bp",
    "addr:street":"East",
    "iso:country":"GB",
    "sg:address":"Brazennose House East, Lincoln Square",
    "sg:city":"Manchester",
    "sg:classifiers":[
        {
            "category":"Professional",
            "subcategory":"Lawyer & Legal Services",
            "type":"Services"
        }
    ],
    "sg:phone":"+44 161 834 0201",
    "sg:postcode":"M2 5BP",
    "sg:province":"Greater Manchester",
    "sg:tags":[
        "patent",
        "agent"
    ],
    "wof:name":"Mewburn Ellis",
    "wof:placetype":"venue"
},
  "geometry": {"coordinates":[-2.2469499111,53.4799308777],"type":"Point"}
}