{
  "type": "Feature",
  "properties": {
    "iso:country":"GB",
    "sg:address":"60 Redhill Drive",
    "sg:city":"Brighton",
    "sg:classifiers":[
        {
            "category":"Professional",
            "subcategory":"Management & Consulting",
            "type":"Services"
        }
    ],
    "sg:postcode":"BN1 5FL",
    "sg:province":"East Sussex",
    "sg:tags":[
        "consultant",
        "business"
    ],
    "wof:name":"Myles Forrester Consulting Ltd",
    "wof:placetype":"venue"
},
  "geometry": {"coordinates":[-0.163373,50.856518],"type":"Point"}
}