{
  "type": "Feature",
  "properties": {
    "addr:full":"West Street East Grinstead East Sussex RH19 4EY",
    "addr:postcode":"rh19 4ey",
    "addr:street":"West Street",
    "iso:country":"GB",
    "sg:address":"West Street",
    "sg:city":"East Grinstead",
    "sg:classifiers":[
        {
            "category":"Shopping",
            "subcategory":"Thrift Store",
            "type":"Retail Goods"
        }
    ],
    "sg:phone":"+44 1342 316055",
    "sg:postcode":"RH19 4EY",
    "sg:province":"East Sussex",
    "sg:tags":[
        "shop",
        "charity"
    ],
    "wof:name":"The Red Cross Shop",
    "wof:placetype":"venue"
},
  "geometry": {"coordinates":[-0.0099,51.124161],"type":"Point"}
}