{
  "type": "Feature",
  "properties": {
    "iso:country":"GB",
    "sg:address":"Groves Farm, Sontley",
    "sg:city":"Wrexham",
    "sg:classifiers":[
        {
            "category":"Farming",
            "subcategory":"Livestock Farm",
            "type":"Manufacturing & Wholesale Goods"
        }
    ],
    "sg:phone":"+44 1978 820818",
    "sg:postcode":"LL13 0YB",
    "sg:province":"Wrexham",
    "sg:tags":[
        "others"
    ],
    "wof:name":"J H Morris",
    "wof:placetype":"venue"
},
  "geometry": {"coordinates":[-2.99952,53.015381],"type":"Point"}
}