{
  "type": "Feature",
  "properties": {
    "iso:country":"GB",
    "sg:address":"Jubilee Garage, North Road",
    "sg:city":"Egremont",
    "sg:classifiers":[
        {
            "category":"Retail",
            "subcategory":"Auto Repair",
            "type":"Services"
        }
    ],
    "sg:phone":"+44 1946 820245",
    "sg:postcode":"CA22 2PR",
    "sg:province":"Cumbria",
    "sg:tags":[
        "modification",
        "garage"
    ],
    "wof:name":"Jubilee Garage (Egremont) Ltd.",
    "wof:placetype":"venue"
},
  "geometry": {"coordinates":[-3.52831,54.482918],"type":"Point"}
}