{
  "type": "Feature",
  "properties": {
    "addr:full":"40 New Road Dagenham Essex RM9 6YS",
    "addr:housenumber":"40",
    "addr:postcode":"rm9 6ys",
    "addr:street":"New Road",
    "iso:country":"GB",
    "sg:address":"40 New Road",
    "sg:city":"Dagenham",
    "sg:classifiers":[
        {
            "category":"Travel",
            "subcategory":"Hotels & Motels",
            "type":"Entertainment"
        }
    ],
    "sg:phone":"+44 20 8593 6337",
    "sg:postcode":"RM9 6YS",
    "sg:province":"Essex",
    "sg:tags":[
        "house",
        "guest"
    ],
    "wof:name":"The New Inn Hotel",
    "wof:placetype":"venue"
},
  "geometry": {"coordinates":[0.15048,51.530861],"type":"Point"}
}