{
  "type": "Feature",
  "properties": {
    "iso:country":"GB",
    "sg:address":"2a Waun-y-groes Ave",
    "sg:city":"Cardiff",
    "sg:classifiers":[
        {
            "category":"Personal",
            "subcategory":"Beauty Salon",
            "type":"Services"
        },
        {
            "category":"Professional",
            "subcategory":"Management & Consulting",
            "type":"Services"
        }
    ],
    "sg:postcode":"CF14 4SY",
    "sg:province":"Cardiff",
    "sg:tags":[
        "unisex",
        "consultant",
        "specialist",
        "hairdresser"
    ],
    "wof:name":"Rosie Parkers Ltd",
    "wof:placetype":"venue"
},
  "geometry": {"coordinates":[-3.202392,51.522293],"type":"Point"}
}