{
  "type": "Feature",
  "properties": {
    "addr:full":"87a Rushey Grn London Greater London SE6 4AF",
    "addr:housenumber":"87a",
    "addr:postcode":"se6 4af",
    "addr:street":"Rushey Grn",
    "iso:country":"GB",
    "sg:address":"87a Rushey Grn",
    "sg:city":"London",
    "sg:classifiers":[
        {
            "category":"Organizations",
            "subcategory":"Religious Organization",
            "type":"Services"
        }
    ],
    "sg:phone":"+44 20 8244 8844",
    "sg:postcode":"SE6 4AF",
    "sg:province":"Greater London",
    "sg:tags":[
        "organisation"
    ],
    "wof:name":"St Peters Pilgrim",
    "wof:placetype":"venue"
},
  "geometry": {"coordinates":[-0.018569,51.446949],"type":"Point"}
}