{
  "type": "Feature",
  "properties": {
    "iso:country":"GB",
    "sg:address":"32 Albion Street",
    "sg:city":"Glasgow",
    "sg:classifiers":[
        {
            "category":"Real Estate",
            "subcategory":"Architect",
            "type":"Services"
        }
    ],
    "sg:phone":"+44 141 552 8977",
    "sg:postcode":"G1 1LH",
    "sg:province":"Glasgow City",
    "sg:tags":[
        "kilt",
        "accessory"
    ],
    "wof:name":"Bulloch Cowell & Co. Ltd.",
    "wof:placetype":"venue"
},
  "geometry": {"coordinates":[-4.244634,55.857349],"type":"Point"}
}