{
  "type": "Feature",
  "properties": {
    "addr:full":"18 Main Street, Great Dalby Melton Mowbray Leicestershire LE14 2ET",
    "addr:housenumber":"18",
    "addr:postcode":"le14 2et",
    "addr:street":"Main Street",
    "iso:country":"GB",
    "sg:address":"18 Main Street, Great Dalby",
    "sg:city":"Melton Mowbray",
    "sg:classifiers":[
        {
            "category":"Bars & Pubs",
            "type":"Food & Drink"
        }
    ],
    "sg:phone":"+44 1664 563147",
    "sg:postcode":"LE14 2ET",
    "sg:province":"Leicestershire",
    "sg:tags":[
        "pubs",
        "inn"
    ],
    "wof:name":"S H Ward & Co. Ltd.",
    "wof:placetype":"venue"
},
  "geometry": {"coordinates":[-0.881304,52.688221],"type":"Point"}
}