{
  "type": "Feature",
  "properties": {
    "addr:full":"8 Caversham Street London Greater London SW3 4AH",
    "addr:housenumber":"8",
    "addr:postcode":"sw3 4ah",
    "addr:street":"Caversham Street",
    "iso:country":"GB",
    "sg:address":"8 Caversham Street",
    "sg:city":"London",
    "sg:classifiers":[
        {
            "category":"Professional",
            "subcategory":"Management & Consulting",
            "type":"Services"
        }
    ],
    "sg:postcode":"SW3 4AH",
    "sg:province":"Greater London",
    "sg:tags":[
        "consultant",
        "business"
    ],
    "wof:name":"Michel Guillon Consultancy Limited",
    "wof:placetype":"venue"
},
  "geometry": {"coordinates":[-0.163135,51.486012],"type":"Point"}
}