{
  "type": "Feature",
  "properties": {
    "iso:country":"GB",
    "sg:address":"Unit 30 Parkengue, Kernick Industrial Estate",
    "sg:city":"Penryn",
    "sg:classifiers":[
        {
            "category":"Professional",
            "subcategory":"Business Services",
            "type":"Services"
        }
    ],
    "sg:phone":"+44 1326 373800",
    "sg:postcode":"TR10 9EP",
    "sg:province":"Cornwall",
    "sg:tags":[
        "distribution"
    ],
    "wof:name":"Books Etc",
    "wof:placetype":"venue"
},
  "geometry": {"coordinates":[-5.104809,50.168575],"type":"Point"}
}