{
  "type": "Feature",
  "properties": {
    "addr:full":"39 Atlas Wynd Yarm North Yorkshire TS15 9AD",
    "addr:housenumber":"39",
    "addr:postcode":"ts15 9ad",
    "addr:street":"Atlas Wynd",
    "iso:country":"GB",
    "sg:address":"39 Atlas Wynd",
    "sg:city":"Yarm",
    "sg:classifiers":[
        {
            "category":"Professional",
            "subcategory":"Management & Consulting",
            "type":"Services"
        }
    ],
    "sg:phone":"+44 1642 644758",
    "sg:postcode":"TS15 9AD",
    "sg:province":"North Yorkshire",
    "sg:tags":[
        "sport"
    ],
    "wof:name":"Premier Players",
    "wof:placetype":"venue"
},
  "geometry": {"coordinates":[-1.352643013,54.5079803467],"type":"Point"}
}