{
  "type": "Feature",
  "properties": {
    "iso:country":"GB",
    "sg:address":"21 Britannia Rd",
    "sg:city":"Sale",
    "sg:classifiers":[
        {
            "category":"Personal",
            "type":"Services"
        }
    ],
    "sg:postcode":"M33 2AA",
    "sg:province":"Cheshire",
    "sg:tags":[
        "wedding"
    ],
    "wof:name":"Charles,John,",
    "wof:placetype":"venue"
},
  "geometry": {"coordinates":[-2.3156590462,53.4276618958],"type":"Point"}
}