{
  "type": "Feature",
  "properties": {
    "addr:full":"136a Heathfield Rd, Handsworth Birmingham West Midlands B19 1HJ",
    "addr:housenumber":"136a",
    "addr:postcode":"b19 1hj",
    "addr:street":"Heathfield Rd",
    "iso:country":"GB",
    "sg:address":"136a Heathfield Rd, Handsworth",
    "sg:city":"Birmingham",
    "sg:classifiers":[
        {
            "category":"Shopping",
            "subcategory":"News",
            "type":"Retail Goods"
        }
    ],
    "sg:postcode":"B19 1HJ",
    "sg:province":"West Midlands",
    "sg:tags":[
        "newsagent"
    ],
    "wof:name":"Gulab Candy Bar",
    "wof:placetype":"venue"
},
  "geometry": {"coordinates":[-1.9095,52.506123],"type":"Point"}
}