{
  "type": "Feature",
  "properties": {
    "iso:country":"GB",
    "sg:address":"136a Heathfield Rd, Handsworth",
    "sg:city":"Birmingham",
    "sg:classifiers":[
        {
            "category":"Shopping",
            "subcategory":"News",
            "type":"Retail Goods"
        }
    ],
    "sg:postcode":"B19 1HJ",
    "sg:province":"West Midlands",
    "sg:tags":[
        "newsagent"
    ],
    "wof:name":"Gulab Candy Bar",
    "wof:placetype":"venue"
},
  "geometry": {"coordinates":[-1.9095,52.506123],"type":"Point"}
}