{
  "type": "Feature",
  "properties": {
    "addr:full":"1 Cliffe Bank, Swinton Mexborough South Yorkshire S64 8PQ",
    "addr:housenumber":"1",
    "addr:postcode":"s64 8pq",
    "addr:street":"Cliffe Bank",
    "iso:country":"GB",
    "sg:address":"1 Cliffe Bank, Swinton",
    "sg:city":"Mexborough",
    "sg:classifiers":[
        {
            "category":"Social Services",
            "subcategory":"Adult Care",
            "type":"Services"
        }
    ],
    "sg:phone":"+44 1709 586366",
    "sg:postcode":"S64 8PQ",
    "sg:province":"South Yorkshire",
    "sg:tags":[
        "housing",
        "sheltered"
    ],
    "wof:name":"Cliffe Bank Sheltered Housing",
    "wof:placetype":"venue"
},
  "geometry": {"coordinates":[-1.3110840321,53.4859733582],"type":"Point"}
}