{
  "type": "Feature",
  "properties": {
    "addr:full":"72 South Street St Andrews Fife KY16 9JT",
    "addr:housenumber":"72",
    "addr:postcode":"ky16 9jt",
    "addr:street":"South Street",
    "iso:country":"GB",
    "sg:address":"72 South Street",
    "sg:city":"St Andrews",
    "sg:classifiers":[
        {
            "category":"Shopping",
            "subcategory":"Department Store",
            "type":"Retail Goods"
        },
        {
            "category":"Home & Garden",
            "subcategory":"Carpets & Floor Coverings",
            "type":"Retail Goods"
        }
    ],
    "sg:phone":"+44 1334 476334",
    "sg:postcode":"KY16 9JT",
    "sg:province":"Fife",
    "sg:tags":[
        "design",
        "carpets",
        "oriental",
        "rug",
        "matting"
    ],
    "wof:name":"Renton Oriental Rugs",
    "wof:placetype":"venue"
},
  "geometry": {"coordinates":[-2.795355,56.339279],"type":"Point"}
}