{
  "type": "Feature",
  "properties": {
    "addr:full":"204 Great West Road Hounslow Greater London TW5 9AW",
    "addr:housenumber":"204",
    "addr:postcode":"tw5 9aw",
    "addr:street":"Great West Road",
    "iso:country":"GB",
    "sg:address":"204 Great West Road",
    "sg:city":"Hounslow",
    "sg:classifiers":[
        {
            "category":"Retail",
            "subcategory":"Laundry & Dry Cleaning",
            "type":"Services"
        }
    ],
    "sg:phone":"+44 20 8572 8456",
    "sg:postcode":"TW5 9AW",
    "sg:province":"Greater London",
    "sg:tags":[
        "launderette"
    ],
    "wof:name":"Washeteria",
    "wof:placetype":"venue"
},
  "geometry": {"coordinates":[-0.385391,51.476391],"type":"Point"}
}