{
  "type": "Feature",
  "properties": {
    "addr:full":"Brickfield Lane Ruthin Denbighshire LL15 2TN",
    "addr:postcode":"ll15 2tn",
    "addr:street":"Brickfield Lane",
    "iso:country":"GB",
    "sg:address":"Brickfield Lane",
    "sg:city":"Ruthin",
    "sg:classifiers":[
        {
            "category":"Home & Garden",
            "subcategory":"Building Materials",
            "type":"Retail Goods"
        }
    ],
    "sg:phone":"+44 1824 702157",
    "sg:postcode":"LL15 2TN",
    "sg:province":"Denbighshire",
    "sg:tags":[
        "gate",
        "door",
        "barrier"
    ],
    "wof:name":"Clifford Jones Timber Ltd.",
    "wof:placetype":"venue"
},
  "geometry": {"coordinates":[-3.304522,53.114017],"type":"Point"}
}