{
  "type": "Feature",
  "properties": {
    "addr:full":"54 Tillingbourne Rd, Shalford Guildford Surrey GU4 8EX",
    "addr:housenumber":"54",
    "addr:postcode":"gu4 8ex",
    "addr:street":"Tillingbourne Rd",
    "iso:country":"GB",
    "sg:address":"54 Tillingbourne Rd, Shalford",
    "sg:city":"Guildford",
    "sg:classifiers":[
        {
            "category":"Communications",
            "subcategory":"Film & Video Production",
            "type":"Services"
        }
    ],
    "sg:postcode":"GU4 8EX",
    "sg:province":"Surrey",
    "sg:tags":[
        "tv",
        "studio"
    ],
    "wof:name":"Simmons,Clive,",
    "wof:placetype":"venue"
},
  "geometry": {"coordinates":[-0.562841,51.215134],"type":"Point"}
}