{
  "type": "Feature",
  "properties": {
    "addr:full":"34 Crouch Hill London Greater London N4 4AU",
    "addr:housenumber":"34",
    "addr:postcode":"n4 4au",
    "addr:street":"Crouch Hill",
    "iso:country":"GB",
    "sg:address":"34 Crouch Hill",
    "sg:city":"London",
    "sg:classifiers":[
        {
            "category":"Personal",
            "type":"Services"
        },
        {
            "category":"Shopping",
            "subcategory":"Bridal",
            "type":"Retail Goods"
        }
    ],
    "sg:postcode":"N4 4AU",
    "sg:province":"Greater London",
    "sg:tags":[
        "shop",
        "gown",
        "wedding"
    ],
    "wof:name":"E & N C SOFIANOU",
    "wof:placetype":"venue"
},
  "geometry": {"coordinates":[-0.117854,51.571243],"type":"Point"}
}