{
  "type": "Feature",
  "properties": {
    "iso:country":"GB",
    "sg:address":"The Old Garage, Mill Road, Whitfield",
    "sg:city":"Brackley",
    "sg:classifiers":[
        {
            "category":"Communications",
            "type":"Services"
        }
    ],
    "sg:phone":"+44 1280 850114",
    "sg:postcode":"NN13 5TQ",
    "sg:province":"Buckinghamshire",
    "sg:tags":[
        "data",
        "network"
    ],
    "wof:name":"James Pates",
    "wof:placetype":"venue"
},
  "geometry": {"coordinates":[-1.069209,52.067169],"type":"Point"}
}