{
  "type": "Feature",
  "properties": {
    "iso:country":"GB",
    "sg:address":"717-719 Durham Road",
    "sg:city":"Gateshead",
    "sg:classifiers":[
        {
            "category":"Food & Beverages",
            "subcategory":"Meat & Fish",
            "type":"Retail Goods"
        }
    ],
    "sg:postcode":"NE9 6AP",
    "sg:province":"Tyne and Wear",
    "sg:tags":[
        "chip"
    ],
    "wof:name":"Khinda's Fish & Chips",
    "wof:placetype":"venue"
},
  "geometry": {"coordinates":[-1.5974550247,54.9310264587],"type":"Point"}
}