{
  "type": "Feature",
  "properties": {
    "addr:full":"Wroxham Road, Coltishall Norwich Norfolk NR12 7AF",
    "addr:postcode":"nr12 7af",
    "addr:street":"Wroxham Road;Norwich",
    "iso:country":"GB",
    "sg:address":"Wroxham Road, Coltishall",
    "sg:city":"Norwich",
    "sg:classifiers":[
        {
            "category":"Social Services",
            "subcategory":"Retirement Home",
            "type":"Services"
        }
    ],
    "sg:postcode":"NR12 7AF",
    "sg:province":"Norfolk",
    "sg:tags":[
        "rest"
    ],
    "wof:name":"Coltishall Hall",
    "wof:placetype":"venue"
},
  "geometry": {"coordinates":[1.3551299572,52.7278327942],"type":"Point"}
}