{
  "type": "Feature",
  "properties": {
    "iso:country":"GB",
    "sg:address":"Town House Rd, Costessey",
    "sg:city":"Norwich",
    "sg:classifiers":[
        {
            "category":"Bars & Pubs",
            "type":"Food & Drink"
        }
    ],
    "sg:postcode":"NR8 5BS",
    "sg:province":"Norfolk",
    "sg:tags":[
        "pubs",
        "inn"
    ],
    "wof:name":"De-la-Borda,P,",
    "wof:placetype":"venue"
},
  "geometry": {"coordinates":[1.211989,52.658924],"type":"Point"}
}