{
  "type": "Feature",
  "properties": {
    "iso:country":"GB",
    "sg:address":"Elmcross House, Broad Hinton",
    "sg:city":"Swindon",
    "sg:classifiers":[
        {
            "category":"Retail",
            "subcategory":"Animal Services",
            "type":"Services"
        },
        {
            "category":"Personal",
            "subcategory":"Adult",
            "type":"Services"
        }
    ],
    "sg:phone":"+44 1793 731481",
    "sg:postcode":"SN4 9PF",
    "sg:province":"Wiltshire",
    "sg:tags":[
        "trainer",
        "horse",
        "equestrian"
    ],
    "wof:name":"Jeffrey S King",
    "wof:placetype":"venue"
},
  "geometry": {"coordinates":[-1.8507150412,51.4882965088],"type":"Point"}
}