{
  "type": "Feature",
  "properties": {
    "iso:country":"GB",
    "sg:address":"109 Gloucester Place",
    "sg:city":"London",
    "sg:classifiers":[
        {
            "category":"Real Estate",
            "subcategory":"Developer",
            "type":"Services"
        }
    ],
    "sg:postcode":"W1U 6JW",
    "sg:province":"Greater London",
    "sg:tags":[
        "property"
    ],
    "wof:name":"Granada Developments Limited",
    "wof:placetype":"venue"
},
  "geometry": {"coordinates":[-0.159009,51.519001],"type":"Point"}
}