{
  "type": "Feature",
  "properties": {
    "iso:country":"GB",
    "sg:address":"The Pld Chapel, Bradford Street",
    "sg:city":"Tonbridge",
    "sg:classifiers":[
        {
            "category":"Organizations",
            "subcategory":"Non-profit Organization",
            "type":"Services"
        }
    ],
    "sg:phone":"+44 1732 364546",
    "sg:postcode":"TN9 1AW",
    "sg:province":"Kent",
    "sg:tags":[
        "organisation",
        "animal",
        "welfare"
    ],
    "wof:name":"Animal Abuse Injustice & Defence Society",
    "wof:placetype":"venue"
},
  "geometry": {"coordinates":[0.2763400078,51.1998291016],"type":"Point"}
}