{
  "type": "Feature",
  "properties": {
    "addr:full":"72 Newhaven Road Edinburgh City of Edinburgh EH6 5QG",
    "addr:housenumber":"72",
    "addr:postcode":"eh6 5qg",
    "addr:street":"Newhaven Road",
    "iso:country":"GB",
    "sg:address":"72 Newhaven Road",
    "sg:city":"Edinburgh",
    "sg:classifiers":[
        {
            "category":"Professional",
            "subcategory":"Detective & Security Services",
            "type":"Services"
        }
    ],
    "sg:postcode":"EH6 5QG",
    "sg:province":"City of Edinburgh",
    "sg:tags":[
        "locksmith"
    ],
    "wof:name":"Caledonian Lock & Safe (Edinburgh) Ltd.",
    "wof:placetype":"venue"
},
  "geometry": {"coordinates":[-3.1872580051,55.9712982178],"type":"Point"}
}