{
  "type": "Feature",
  "properties": {
    "addr:full":"Cromford Garage, 24 Water Lane, Cromford Matlock Derbyshire DE4 3QH",
    "addr:housenumber":"24",
    "addr:postcode":"de4 3qh",
    "addr:street":"Water Lane",
    "iso:country":"GB",
    "sg:address":"Cromford Garage, 24 Water Lane, Cromford",
    "sg:city":"Matlock",
    "sg:classifiers":[
        {
            "category":"Professional",
            "subcategory":"Testing Lab",
            "type":"Services"
        }
    ],
    "sg:phone":"+44 1629 823043",
    "sg:postcode":"DE4 3QH",
    "sg:province":"Derbyshire",
    "sg:tags":[
        "mot"
    ],
    "wof:name":"P Gould & Son",
    "wof:placetype":"venue"
},
  "geometry": {"coordinates":[-1.5482740402,53.1356163025],"type":"Point"}
}