{
  "type": "Feature",
  "properties": {
    "iso:country":"GB",
    "sg:address":"The Hall, 68a West St, Isleham",
    "sg:city":"Ely",
    "sg:classifiers":[
        {
            "category":"Communications",
            "subcategory":"Film & Video Production",
            "type":"Services"
        }
    ],
    "sg:phone":"+44 1638 780960",
    "sg:postcode":"CB7 5RA",
    "sg:province":"Cambridgeshire",
    "sg:tags":[
        "illustrator",
        "artist"
    ],
    "wof:name":"Jack Lewis",
    "wof:placetype":"venue"
},
  "geometry": {"coordinates":[0.409965,52.341454],"type":"Point"}
}