{
  "type": "Feature",
  "properties": {
    "iso:country":"GB",
    "sg:address":"55 Hove Rd",
    "sg:city":"Lytham St Annes",
    "sg:classifiers":[
        {
            "category":"Professional",
            "subcategory":"Management & Consulting",
            "type":"Services"
        }
    ],
    "sg:phone":"+44 1253 780222",
    "sg:postcode":"FY8 1XH",
    "sg:province":"Lancashire",
    "sg:tags":[
        "marketing",
        "consultant"
    ],
    "wof:name":"Business Board Ltd",
    "wof:placetype":"venue"
},
  "geometry": {"coordinates":[-3.0222198963,53.7530479431],"type":"Point"}
}