{
  "type": "Feature",
  "properties": {
    "iso:country":"GB",
    "sg:address":"39 Thornhill Road",
    "sg:city":"Halesowen",
    "sg:classifiers":[
        {
            "category":"Shopping",
            "subcategory":"News",
            "type":"Retail Goods"
        }
    ],
    "sg:phone":"+44 121 550 2138",
    "sg:postcode":"B63 1AU",
    "sg:province":"West Midlands",
    "sg:tags":[
        "newsagent"
    ],
    "wof:name":"Thornhill News & Grocery",
    "wof:placetype":"venue"
},
  "geometry": {"coordinates":[-2.0705940723,52.4473495483],"type":"Point"}
}