{
  "type": "Feature",
  "properties": {
    "addr:full":"29 Museum Street London Greater London WC1A 1LH",
    "addr:housenumber":"29",
    "addr:postcode":"wc1a 1lh",
    "addr:street":"Museum Street",
    "iso:country":"GB",
    "sg:address":"29 Museum Street",
    "sg:city":"London",
    "sg:classifiers":[
        {
            "category":"Professional",
            "subcategory":"Business Services",
            "type":"Services"
        }
    ],
    "sg:postcode":"WC1A 1LH",
    "sg:province":"Greater London",
    "sg:tags":[
        "distribution"
    ],
    "wof:name":"B.A.S. Distribution Limited",
    "wof:placetype":"venue"
},
  "geometry": {"coordinates":[-0.1258109957,51.517829895],"type":"Point"}
}