{
  "type": "Feature",
  "properties": {
    "iso:country":"GB",
    "sg:address":"2 London Road, Purbrook",
    "sg:city":"Waterlooville",
    "sg:classifiers":[
        {
            "category":"Taxi",
            "type":"Transportation"
        },
        {
            "category":"Bus Stop",
            "subcategory":"None",
            "type":"Transportation"
        },
        {
            "category":"Military Area",
            "subcategory":"Air Force Base",
            "type":"Public Place"
        }
    ],
    "sg:phone":"+44 23 9223 0250",
    "sg:postcode":"PO7 5LJ",
    "sg:province":"Hampshire",
    "sg:tags":[
        "mini",
        "hire",
        "cab",
        "private",
        "min"
    ],
    "wof:name":"Pete'S Cars Airlink",
    "wof:placetype":"venue"
},
  "geometry": {"coordinates":[-1.04567,50.866184],"type":"Point"}
}