{
  "type": "Feature",
  "properties": {
    "iso:country":"GB",
    "sg:address":", Uffington",
    "sg:city":"Shrewsbury",
    "sg:classifiers":[
        {
            "category":"Bars & Pubs",
            "type":"Food & Drink"
        }
    ],
    "sg:phone":"+44 1743 709232",
    "sg:postcode":"SY4 4SN",
    "sg:province":"Shropshire",
    "sg:tags":[
        "pubs",
        "inn"
    ],
    "wof:name":"Corbet Arms Hotel",
    "wof:placetype":"venue"
},
  "geometry": {"coordinates":[-2.699204,52.721344],"type":"Point"}
}