{
  "type": "Feature",
  "properties": {
    "addr:full":"285 Middlewood Road Sheffield South Yorkshire S6 1TG",
    "addr:housenumber":"285",
    "addr:postcode":"s6 1tg",
    "addr:street":"Middlewood Road",
    "iso:country":"GB",
    "sg:address":"285 Middlewood Road",
    "sg:city":"Sheffield",
    "sg:classifiers":[
        {
            "category":"Cafe",
            "type":"Food & Drink"
        }
    ],
    "sg:postcode":"S6 1TG",
    "sg:province":"South Yorkshire",
    "sg:tags":[
        "tea",
        "room"
    ],
    "wof:name":"Ovenfayre",
    "wof:placetype":"venue"
},
  "geometry": {"coordinates":[-1.50456,53.410679],"type":"Point"}
}