{
  "type": "Feature",
  "properties": {
    "addr:full":"Hotel Road, Watling Street Gillingham Kent ME8 6AA",
    "addr:postcode":"me8 6aa",
    "addr:street":"Hotel Road Watling Street",
    "iso:country":"GB",
    "sg:address":"Hotel Road, Watling Street",
    "sg:city":"Gillingham",
    "sg:classifiers":[
        {
            "category":"Education",
            "subcategory":"School",
            "type":"Public Place"
        }
    ],
    "sg:phone":"+44 1634 232589",
    "sg:postcode":"ME8 6AA",
    "sg:province":"Kent",
    "sg:tags":[
        "local",
        "authority"
    ],
    "wof:name":"Danecourt Special School",
    "wof:placetype":"venue"
},
  "geometry": {"coordinates":[0.571415,51.370602],"type":"Point"}
}