{
  "type": "Feature",
  "properties": {
    "iso:country":"GB",
    "sg:address":"51 St Giles Street",
    "sg:city":"Northampton",
    "sg:classifiers":[
        {
            "category":"Shopping",
            "subcategory":"Florist",
            "type":"Retail Goods"
        }
    ],
    "sg:phone":"+44 1604 633024",
    "sg:postcode":"NN1 1JF",
    "sg:province":"Northamptonshire",
    "wof:name":"Jack Haddon of Northampton",
    "wof:placetype":"venue"
},
  "geometry": {"coordinates":[-0.892109,52.237679],"type":"Point"}
}