{
  "type": "Feature",
  "properties": {
    "iso:country":"GB",
    "sg:address":"8 High St",
    "sg:city":"Stamford",
    "sg:classifiers":[
        {
            "category":"Personal",
            "subcategory":"Beauty Salon",
            "type":"Services"
        }
    ],
    "sg:phone":"+44 1780 752725",
    "sg:postcode":"PE9 2LF",
    "sg:province":"Cambridgeshire",
    "wof:name":"Cameo Health & Beauty Studio",
    "wof:placetype":"venue"
},
  "geometry": {"coordinates":[-0.479263,52.652233],"type":"Point"}
}