{
  "type": "Feature",
  "properties": {
    "iso:country":"GB",
    "sg:address":"Southcote Barn, Southend Lane",
    "sg:city":"Newent",
    "sg:classifiers":[
        {
            "category":"Professional",
            "subcategory":"Engineering",
            "type":"Services"
        }
    ],
    "sg:phone":"+44 1531 822988",
    "sg:postcode":"GL18 1JD",
    "sg:province":"Gloucestershire",
    "sg:tags":[
        "contractor",
        "electrical",
        "engineer"
    ],
    "wof:name":"Clark Electrical Contractors",
    "wof:placetype":"venue"
},
  "geometry": {"coordinates":[-2.406134,51.930828],"type":"Point"}
}