{
  "type": "Feature",
  "properties": {
    "iso:country":"GB",
    "sg:address":"5 Langbridge Business Centre, Langbridge",
    "sg:city":"Sandown",
    "sg:classifiers":[
        {
            "category":"Retail",
            "subcategory":"Auto Repair",
            "type":"Services"
        }
    ],
    "sg:phone":"+44 1983 865338",
    "sg:postcode":"PO36 0NP",
    "sg:province":"Isle of Wight",
    "sg:tags":[
        "modification",
        "garage"
    ],
    "wof:name":"Bartletts Service Station",
    "wof:placetype":"venue"
},
  "geometry": {"coordinates":[-1.150164,50.656013],"type":"Point"}
}