{
  "type": "Feature",
  "properties": {
    "addr:full":"159 Eastbank Street Southport Lancashire PR8 1EE",
    "addr:housenumber":"159",
    "addr:postcode":"pr8 1ee",
    "addr:street":"Eastbank Street",
    "iso:country":"GB",
    "sg:address":"159 Eastbank Street",
    "sg:city":"Southport",
    "sg:classifiers":[
        {
            "category":"Shopping",
            "subcategory":"Bicycles & Sporting Goods",
            "type":"Retail Goods"
        },
        {
            "category":"Sports & Exercise",
            "subcategory":"Sports Center",
            "type":"Entertainment"
        }
    ],
    "sg:phone":"+44 1704 546082",
    "sg:postcode":"PR8 1EE",
    "sg:province":"Lancashire",
    "sg:tags":[
        "shop",
        "retailer"
    ],
    "wof:name":"Natterjack Running Centre",
    "wof:placetype":"venue"
},
  "geometry": {"coordinates":[-3.0017340183,53.6427879333],"type":"Point"}
}