{
  "type": "Feature",
  "properties": {
    "iso:country":"GB",
    "sg:address":"138 Moorings Way",
    "sg:city":"Southsea",
    "sg:classifiers":[
        {
            "category":"Professional",
            "subcategory":"Accounting & Tax Preparation",
            "type":"Services"
        }
    ],
    "sg:phone":"+44 23 9261 0450",
    "sg:postcode":"PO4 8YL",
    "sg:province":"Hampshire",
    "sg:tags":[
        "accountant",
        "activity"
    ],
    "wof:name":"John Doyle Partnership",
    "wof:placetype":"venue"
},
  "geometry": {"coordinates":[-1.0457309484,50.8007125854],"type":"Point"}
}