{
  "type": "Feature",
  "properties": {
    "addr:full":"86 Holme Lane Sheffield South Yorkshire S6 4JW",
    "addr:housenumber":"86",
    "addr:postcode":"s6 4jw",
    "addr:street":"Holme Lane",
    "iso:country":"GB",
    "sg:address":"86 Holme Lane",
    "sg:city":"Sheffield",
    "sg:classifiers":[
        {
            "category":"Fast Food",
            "type":"Food & Drink"
        }
    ],
    "sg:phone":"+44 114 231 4311",
    "sg:postcode":"S6 4JW",
    "sg:province":"South Yorkshire",
    "sg:tags":[
        "away",
        "take"
    ],
    "wof:name":"Munchies",
    "wof:placetype":"venue"
},
  "geometry": {"coordinates":[-1.5044790506,53.4015083313],"type":"Point"}
}