{
  "type": "Feature",
  "properties": {
    "iso:country":"GB",
    "sg:address":"75 Etterby Street",
    "sg:city":"Carlisle",
    "sg:classifiers":[
        {
            "category":"Building & Trades",
            "subcategory":"Construction",
            "type":"Services"
        }
    ],
    "sg:phone":"+44 1228 529252",
    "sg:postcode":"CA3 9JD",
    "sg:province":"Cumbria",
    "sg:tags":[
        "heating",
        "contractor"
    ],
    "wof:name":"Ian Dockerty Heating & Plumbing",
    "wof:placetype":"venue"
},
  "geometry": {"coordinates":[-2.941607,54.905708],"type":"Point"}
}