{
  "type": "Feature",
  "properties": {
    "iso:country":"GB",
    "sg:address":"20 Cleveland Way, Shelley",
    "sg:city":"Huddersfield",
    "sg:classifiers":[
        {
            "category":"Professional",
            "subcategory":"Advertising",
            "type":"Services"
        }
    ],
    "sg:postcode":"HD8 8NQ",
    "sg:province":"South Yorkshire",
    "wof:name":"Localeyes",
    "wof:placetype":"venue"
},
  "geometry": {"coordinates":[-1.7011510134,53.5960922241],"type":"Point"}
}