{
  "type": "Feature",
  "properties": {
    "addr:full":"2b Woodhouse Lane Tamworth Staffordshire B77 3AE",
    "addr:housenumber":"2b",
    "addr:postcode":"b77 3ae",
    "addr:street":"Woodhouse Lane",
    "iso:country":"GB",
    "sg:address":"2b Woodhouse Lane",
    "sg:city":"Tamworth",
    "sg:classifiers":[
        {
            "category":"Travel",
            "subcategory":"Hostel",
            "type":"Entertainment"
        },
        {
            "category":"Organizations",
            "subcategory":"Community Association",
            "type":"Services"
        }
    ],
    "sg:postcode":"B77 3AE",
    "sg:province":"Staffordshire",
    "sg:tags":[
        "society",
        "housing"
    ],
    "wof:name":"The Old School House",
    "wof:placetype":"venue"
},
  "geometry": {"coordinates":[-1.657209,52.636395],"type":"Point"}
}