{
  "type": "Feature",
  "properties": {
    "addr:full":"34 Station Parade Barking Essex IG11 8DR",
    "addr:housenumber":"34",
    "addr:postcode":"ig11 8dr",
    "addr:street":"Station Parade",
    "iso:country":"GB",
    "sg:address":"34 Station Parade",
    "sg:city":"Barking",
    "sg:classifiers":[
        {
            "category":"Professional",
            "type":"Services"
        }
    ],
    "sg:phone":"+44 20 8591 5010",
    "sg:postcode":"IG11 8DR",
    "sg:province":"Essex",
    "sg:tags":[
        "interior",
        "furnishers",
        "designer"
    ],
    "wof:name":"Devon House Interiors Ltd.",
    "wof:placetype":"venue"
},
  "geometry": {"coordinates":[0.0806600004,51.5385780334],"type":"Point"}
}