{
  "type": "Feature",
  "properties": {
    "addr:full":"Tanrallt Farm, Nebo Amlwch Isle of Anglesey LL68 9NE",
    "addr:postcode":"ll68 9ne",
    "addr:street":"Amlwch",
    "iso:country":"GB",
    "sg:address":"Tanrallt Farm, Nebo",
    "sg:city":"Amlwch",
    "sg:classifiers":[
        {
            "category":"Farming",
            "subcategory":"Livestock Farm",
            "type":"Manufacturing & Wholesale Goods"
        }
    ],
    "sg:phone":"+44 1407 830391",
    "sg:postcode":"LL68 9NE",
    "sg:province":"Isle of Anglesey",
    "sg:tags":[
        "others"
    ],
    "wof:name":"J L Owen",
    "wof:placetype":"venue"
},
  "geometry": {"coordinates":[-4.3463768959,53.4091033936],"type":"Point"}
}