{
  "type": "Feature",
  "properties": {
    "iso:country":"GB",
    "sg:address":"Main Rd",
    "sg:city":"Nuneaton",
    "sg:classifiers":[
        {
            "category":"Travel",
            "subcategory":"Hotels & Motels",
            "type":"Entertainment"
        }
    ],
    "sg:phone":"+44 1827 880223",
    "sg:postcode":"CV13 6LB",
    "sg:province":"Leicestershire",
    "wof:name":"Millers Hotel Ltd (The)",
    "wof:placetype":"venue"
},
  "geometry": {"coordinates":[-1.464933,52.643471],"type":"Point"}
}