{
  "type": "Feature",
  "properties": {
    "addr:full":"The Centre, 255 Crewe Road Stoke-on-trent Cheshire ST7 2JJ",
    "addr:housenumber":"255",
    "addr:postcode":"st7 2jj",
    "addr:street":"Crewe Road",
    "iso:country":"GB",
    "sg:address":"The Centre, 255 Crewe Road",
    "sg:city":"Stoke-on-trent",
    "sg:classifiers":[
        {
            "category":"Home & Garden",
            "subcategory":"Home Furnishings",
            "type":"Retail Goods"
        }
    ],
    "sg:postcode":"ST7 2JJ",
    "sg:province":"Cheshire",
    "sg:tags":[
        "furnishers",
        "planner",
        "bedroom"
    ],
    "wof:name":"Cozy-Plan Ltd.",
    "wof:placetype":"venue"
},
  "geometry": {"coordinates":[-2.3278300762,53.0908889771],"type":"Point"}
}