{
  "type": "Feature",
  "properties": {
    "iso:country":"GB",
    "sg:address":"793 Southchurch Road",
    "sg:city":"Southend-on-sea",
    "sg:classifiers":[
        {
            "category":"Shopping",
            "subcategory":"Department Store",
            "type":"Retail Goods"
        },
        {
            "category":"Shopping",
            "subcategory":"Comic Books",
            "type":"Retail Goods"
        }
    ],
    "sg:postcode":"SS1 2PP",
    "sg:province":"Essex",
    "sg:tags":[
        "jeweller"
    ],
    "wof:name":"Jeffrey Klein",
    "wof:placetype":"venue"
},
  "geometry": {"coordinates":[0.737064,51.541512],"type":"Point"}
}