{
  "type": "Feature",
  "properties": {
    "addr:full":"207 Byerley Road Shildon Durham DL4 1HL",
    "addr:housenumber":"207",
    "addr:postcode":"dl4 1hl",
    "addr:street":"Byerley Road",
    "iso:country":"GB",
    "sg:address":"207 Byerley Road",
    "sg:city":"Shildon",
    "sg:classifiers":[
        {
            "category":"Bars & Pubs",
            "type":"Food & Drink"
        },
        {
            "category":"Communications",
            "subcategory":"Film & Video Production",
            "type":"Services"
        },
        {
            "category":"Community Center",
            "subcategory":"Social",
            "type":"Public Place"
        }
    ],
    "sg:phone":"+44 1388 772108",
    "sg:postcode":"DL4 1HL",
    "sg:province":"Durham",
    "sg:tags":[
        "illustrator",
        "artist",
        "house",
        "pubs",
        "inn",
        "activity"
    ],
    "wof:name":"The Locomotive",
    "wof:placetype":"venue"
},
  "geometry": {"coordinates":[-1.6482729912,54.6264381409],"type":"Point"}
}