{
  "type": "Feature",
  "properties": {
    "iso:country":"GB",
    "sg:address":"Eccles House, Main Road",
    "sg:city":"Edenbridge",
    "sg:classifiers":[
        {
            "category":"Home & Garden",
            "subcategory":"Carpets & Floor Coverings",
            "type":"Retail Goods"
        }
    ],
    "sg:phone":"+44 1732 866735",
    "sg:postcode":"TN8 6HZ",
    "sg:province":"East Sussex",
    "sg:tags":[
        "wall",
        "tie",
        "replacement"
    ],
    "wof:name":"Terence C Blake",
    "wof:placetype":"venue"
},
  "geometry": {"coordinates":[0.0563200004,51.2195510864],"type":"Point"}
}