{
  "type": "Feature",
  "properties": {
    "iso:country":"GB",
    "sg:address":"27 Berrow Road",
    "sg:city":"Burnham-on-sea",
    "sg:classifiers":[
        {
            "category":"Travel",
            "subcategory":"Hotels & Motels",
            "type":"Entertainment"
        }
    ],
    "sg:phone":"+44 1278 784214",
    "sg:postcode":"TA8 2EY",
    "sg:province":"Somerset",
    "wof:name":"The Pine Grange Hotel",
    "wof:placetype":"venue"
},
  "geometry": {"coordinates":[-2.997733,51.2439],"type":"Point"}
}