{
  "type": "Feature",
  "properties": {
    "addr:full":"28 Kingfisher Shopping Centre, Kingfisher Walk Redditch Warwickshire B97 4EY",
    "addr:housenumber":"28",
    "addr:postcode":"b97 4ey",
    "addr:street":"Kingfisher Shopping;Kingfisher Walk",
    "iso:country":"GB",
    "sg:address":"28 Kingfisher Shopping Centre, Kingfisher Walk",
    "sg:city":"Redditch",
    "sg:classifiers":[
        {
            "category":"Home & Garden",
            "subcategory":"Kitchen Supply",
            "type":"Retail Goods"
        }
    ],
    "sg:phone":"+44 1527 65478",
    "sg:postcode":"B97 4EY",
    "sg:province":"Warwickshire",
    "sg:tags":[
        "glassware",
        "china"
    ],
    "wof:name":"Pottery Plus",
    "wof:placetype":"venue"
},
  "geometry": {"coordinates":[-1.9412670135,52.30727005],"type":"Point"}
}