{
  "type": "Feature",
  "properties": {
    "iso:country":"GB",
    "sg:address":"5th Floor, 6-7 St. Cross St",
    "sg:city":"Clerkenwell",
    "sg:classifiers":[
        {
            "category":"Professional",
            "subcategory":"Research",
            "type":"Services"
        }
    ],
    "sg:phone":"+44 20 7208 4800",
    "sg:postcode":"EC1N 8UA",
    "sg:province":"Greater London",
    "sg:tags":[
        "organisation"
    ],
    "wof:name":"Broadcast Strategy",
    "wof:placetype":"venue"
},
  "geometry": {"coordinates":[-0.109192,51.520435],"type":"Point"}
}