{
  "type": "Feature",
  "properties": {
    "iso:country":"GB",
    "sg:address":"111 Broad Street",
    "sg:city":"Bromsgrove",
    "sg:classifiers":[
        {
            "category":"Professional",
            "subcategory":"Engineering",
            "type":"Services"
        }
    ],
    "sg:phone":"+44 1527 870261",
    "sg:postcode":"B61 8LR",
    "sg:province":"Worcestershire",
    "sg:tags":[
        "consulting",
        "engineer"
    ],
    "wof:name":"P K Engineering Services Ltd.",
    "wof:placetype":"venue"
},
  "geometry": {"coordinates":[-2.0657699108,52.3430862427],"type":"Point"}
}