{
  "type": "Feature",
  "properties": {
    "addr:full":"Birdhouse Lane, Downe Orpington Kent BR6 7LJ",
    "addr:postcode":"br6 7lj",
    "addr:street":"Birdhouse Lane",
    "iso:country":"GB",
    "sg:address":"Birdhouse Lane, Downe",
    "sg:city":"Orpington",
    "sg:classifiers":[
        {
            "category":"Recreation",
            "subcategory":"Campground",
            "type":"Entertainment"
        }
    ],
    "sg:phone":"+44 1959 572121",
    "sg:postcode":"BR6 7LJ",
    "sg:province":"Kent",
    "sg:tags":[
        "site",
        "camping"
    ],
    "wof:name":"Downe Scout Camp",
    "wof:placetype":"venue"
},
  "geometry": {"coordinates":[0.053909,51.33622],"type":"Point"}
}