{
  "type": "Feature",
  "properties": {
    "iso:country":"GB",
    "sg:address":"110 High Street",
    "sg:city":"Street",
    "sg:classifiers":[
        {
            "category":"Personal",
            "subcategory":"Barber",
            "type":"Services"
        }
    ],
    "sg:phone":"+44 1458 442353",
    "sg:postcode":"BA16 0EW",
    "sg:province":"Somerset",
    "sg:tags":[
        "men's",
        "gents",
        "hairdresser"
    ],
    "wof:name":"M T Howe",
    "wof:placetype":"venue"
},
  "geometry": {"coordinates":[-2.741625,51.126026],"type":"Point"}
}