{
  "type": "Feature",
  "properties": {
    "addr:full":"135 Chapel Street Leigh Lancashire WN7 2AL",
    "addr:housenumber":"135",
    "addr:postcode":"wn7 2al",
    "addr:street":"Chapel Street Leigh",
    "iso:country":"GB",
    "sg:address":"135 Chapel Street",
    "sg:city":"Leigh",
    "sg:classifiers":[
        {
            "category":"Personal",
            "subcategory":"Beauty Salon",
            "type":"Services"
        }
    ],
    "sg:phone":"+44 1942 671774",
    "sg:postcode":"WN7 2AL",
    "sg:province":"Lancashire",
    "sg:tags":[
        "unisex",
        "hairdresser"
    ],
    "wof:name":"Enigma Hair & Beauty",
    "wof:placetype":"venue"
},
  "geometry": {"coordinates":[-2.5047008991,53.4936523438],"type":"Point"}
}