{
  "type": "Feature",
  "properties": {
    "iso:country":"GB",
    "sg:address":"28 Ashley Gardens Park Gate, Amberstone",
    "sg:city":"Hailsham",
    "sg:classifiers":[
        {
            "category":"Building & Trades",
            "subcategory":"Landscaping Services",
            "type":"Services"
        },
        {
            "category":"Personal",
            "type":"Services"
        }
    ],
    "sg:phone":"+44 1323 844028",
    "sg:postcode":"BN27 1NQ",
    "sg:province":"East Sussex",
    "sg:tags":[
        "contractor",
        "landscape",
        "wedding"
    ],
    "wof:name":"Classique Drives & Gardens",
    "wof:placetype":"venue"
},
  "geometry": {"coordinates":[0.264876008,50.878452301],"type":"Point"}
}