{
  "type": "Feature",
  "properties": {
    "addr:full":"5 Alice Close Hove East Sussex BN3 1JH",
    "addr:housenumber":"5",
    "addr:postcode":"bn3 1jh",
    "addr:street":"Alice Close",
    "iso:country":"GB",
    "sg:address":"5 Alice Close",
    "sg:city":"Hove",
    "sg:classifiers":[
        {
            "category":"Shopping",
            "subcategory":"Clothing, Apparel, & Fashions",
            "type":"Retail Goods"
        }
    ],
    "sg:postcode":"BN3 1JH",
    "sg:province":"East Sussex",
    "sg:tags":[
        "tie",
        "neckwear"
    ],
    "wof:name":"G R Currey",
    "wof:placetype":"venue"
},
  "geometry": {"coordinates":[-0.162139,50.824604],"type":"Point"}
}