{
  "type": "Feature",
  "properties": {
    "iso:country":"GB",
    "sg:address":"4 Norfolk Street",
    "sg:city":"Cambridge",
    "sg:classifiers":[
        {
            "category":"Shopping",
            "subcategory":"Musical Instruments",
            "type":"Retail Goods"
        }
    ],
    "sg:phone":"+44 1223 364410",
    "sg:postcode":"CB1 2LF",
    "sg:province":"Cambridgeshire",
    "sg:tags":[
        "music",
        "sheet"
    ],
    "wof:name":"Drum & Guitar Centre",
    "wof:placetype":"venue"
},
  "geometry": {"coordinates":[0.136729,52.204704],"type":"Point"}
}