{
  "type": "Feature",
  "properties": {
    "iso:country":"GB",
    "sg:address":"321 Lower Broughton Rd",
    "sg:city":"Salford",
    "sg:classifiers":[
        {
            "category":"Cafe",
            "type":"Food & Drink"
        }
    ],
    "sg:postcode":"M7 2LH",
    "sg:province":"Greater Manchester",
    "sg:tags":[
        "tea",
        "room"
    ],
    "wof:name":"Foster,D K,&,R,",
    "wof:placetype":"venue"
},
  "geometry": {"coordinates":[-2.2700419426,53.4984436035],"type":"Point"}
}