{
  "type": "Feature",
  "properties": {
    "addr:full":"Labour Hall, Crab La Biggleswade Bedfordshire SG18 0LN",
    "addr:postcode":"sg18 0ln",
    "addr:street":"La Biggleswade Bedfordshire",
    "iso:country":"GB",
    "sg:address":"Labour Hall, Crab La",
    "sg:city":"Biggleswade",
    "sg:classifiers":[
        {
            "category":"Organizations",
            "subcategory":"Political Organization",
            "type":"Services"
        }
    ],
    "sg:phone":"+44 1767 318676",
    "sg:postcode":"SG18 0LN",
    "sg:province":"Bedfordshire",
    "sg:tags":[
        "party"
    ],
    "wof:name":"Labour Party The",
    "wof:placetype":"venue"
},
  "geometry": {"coordinates":[-0.261729,52.086975],"type":"Point"}
}