{
  "type": "Feature",
  "properties": {
    "addr:full":"5 Regent Road Blackpool Lancashire FY1 4LY",
    "addr:housenumber":"5",
    "addr:postcode":"fy1 4ly",
    "addr:street":"Regent Road",
    "iso:country":"GB",
    "sg:address":"5 Regent Road",
    "sg:city":"Blackpool",
    "sg:classifiers":[
        {
            "category":"Travel",
            "subcategory":"Hotels & Motels",
            "type":"Entertainment"
        },
        {
            "category":"Bars & Pubs",
            "subcategory":"Hookah Bar",
            "type":"Food & Drink"
        }
    ],
    "sg:phone":"+44 1253 625535",
    "sg:postcode":"FY1 4LY",
    "sg:province":"Lancashire",
    "sg:tags":[
        "self",
        "holiday",
        "catering"
    ],
    "wof:name":"ANNE TUPLIN",
    "wof:placetype":"venue"
},
  "geometry": {"coordinates":[-3.0463860035,53.8171653748],"type":"Point"}
}