{
  "type": "Feature",
  "properties": {
    "addr:full":"21 Raleigh Walk Crawley Surrey RH10 5NJ",
    "addr:housenumber":"21",
    "addr:postcode":"rh10 5nj",
    "addr:street":"Raleigh Walk",
    "iso:country":"GB",
    "sg:address":"21 Raleigh Walk",
    "sg:city":"Crawley",
    "sg:classifiers":[
        {
            "category":"Professional",
            "subcategory":"Computer Services",
            "type":"Services"
        }
    ],
    "sg:phone":"+44 1293 435447",
    "sg:postcode":"RH10 5NJ",
    "sg:province":"Surrey",
    "sg:tags":[
        "consultant"
    ],
    "wof:name":"Titan Analysis",
    "wof:placetype":"venue"
},
  "geometry": {"coordinates":[-0.1815859973,51.1050033569],"type":"Point"}
}