{
  "type": "Feature",
  "properties": {
    "addr:full":"Office Suite, 2nd Floor, Gun Ct, 70 Wapping La London Greater London E1 9LR",
    "addr:housenumber":"suite 2nd floor;70",
    "addr:postcode":"e1 9lr",
    "addr:street":"Gun Ct;La",
    "iso:country":"GB",
    "sg:address":"Office Suite, 2nd Floor, Gun Ct, 70 Wapping La",
    "sg:city":"London",
    "sg:classifiers":[
        {
            "category":"Manufacturing",
            "subcategory":"Tools & Machinery",
            "type":"Manufacturing & Wholesale Goods"
        }
    ],
    "sg:postcode":"E1 9LR",
    "sg:province":"Greater London",
    "sg:tags":[
        "society",
        "friendly"
    ],
    "wof:name":"Corporate Risk Management Ltd",
    "wof:placetype":"venue"
},
  "geometry": {"coordinates":[-0.0573600009,51.5179786682],"type":"Point"}
}