{
  "type": "Feature",
  "properties": {
    "addr:full":"Klondyke Garden Centre Chester-le-street Durham DH3 4HD",
    "addr:postcode":"dh3 4hd",
    "addr:street":"Chester-Le-Street",
    "iso:country":"GB",
    "sg:address":"Klondyke Garden Centre",
    "sg:city":"Chester-le-street",
    "sg:classifiers":[
        {
            "category":"Building & Trades",
            "subcategory":"Construction",
            "type":"Services"
        }
    ],
    "sg:phone":"+44 191 385 6667",
    "sg:postcode":"DH3 4HD",
    "sg:province":"Durham",
    "sg:tags":[
        "contractor",
        "paving",
        "driveway"
    ],
    "wof:name":"Colorcrete",
    "wof:placetype":"venue"
},
  "geometry": {"coordinates":[-1.53902,54.84763],"type":"Point"}
}