{
  "type": "Feature",
  "properties": {
    "addr:full":"298 Station Rd Harrow Greater London HA1 2DX",
    "addr:housenumber":"298",
    "addr:postcode":"ha1 2dx",
    "addr:street":"Station Rd",
    "iso:country":"GB",
    "sg:address":"298 Station Rd",
    "sg:city":"Harrow",
    "sg:classifiers":[
        {
            "category":"Shopping",
            "subcategory":"Clothing, Apparel, & Fashions",
            "type":"Retail Goods"
        }
    ],
    "sg:phone":"+44 20 8863 4117",
    "sg:postcode":"HA1 2DX",
    "sg:province":"Greater London",
    "sg:tags":[
        "menswear"
    ],
    "wof:name":"Mr Howard Menswear Ltd",
    "wof:placetype":"venue"
},
  "geometry": {"coordinates":[-0.3328790069,51.5816459656],"type":"Point"}
}