{
  "type": "Feature",
  "properties": {
    "iso:country":"GB",
    "sg:address":"181 Gravelly Lane",
    "sg:city":"Birmingham",
    "sg:classifiers":[
        {
            "category":"Shopping",
            "subcategory":"Antiques",
            "type":"Retail Goods"
        }
    ],
    "sg:phone":"+44 121 373 3876",
    "sg:postcode":"B23 5SG",
    "sg:province":"West Midlands",
    "wof:name":"Mara Cirjanic",
    "wof:placetype":"venue"
},
  "geometry": {"coordinates":[-1.841034,52.531242],"type":"Point"}
}