{
  "type": "Feature",
  "properties": {
    "iso:country":"GB",
    "sg:address":"2 Regent Street, Moulton",
    "sg:city":"Northwich",
    "sg:classifiers":[
        {
            "category":"Shopping",
            "subcategory":"Department Store",
            "type":"Retail Goods"
        },
        {
            "category":"Government",
            "subcategory":"Post Office",
            "type":"Public Place"
        }
    ],
    "sg:phone":"+44 1606 593212",
    "sg:postcode":"CW9 8NY",
    "sg:province":"Cheshire",
    "wof:name":"Moulton Post Office",
    "wof:placetype":"venue"
},
  "geometry": {"coordinates":[-2.5105938911,53.2344894409],"type":"Point"}
}