{
  "type": "Feature",
  "properties": {
    "addr:full":"97 Station Road Birchington Kent CT7 9RE",
    "addr:housenumber":"97",
    "addr:postcode":"ct7 9re",
    "addr:street":"Station Road",
    "iso:country":"GB",
    "sg:address":"97 Station Road",
    "sg:city":"Birchington",
    "sg:classifiers":[
        {
            "category":"Professional",
            "subcategory":"Art Services",
            "type":"Services"
        }
    ],
    "sg:phone":"+44 1843 841794",
    "sg:postcode":"CT7 9RE",
    "sg:province":"Kent",
    "sg:tags":[
        "photographer"
    ],
    "wof:name":"John Glanvill",
    "wof:placetype":"venue"
},
  "geometry": {"coordinates":[1.304074049,51.3762550354],"type":"Point"}
}