{
  "type": "Feature",
  "properties": {
    "iso:country":"GB",
    "sg:address":"The Friary",
    "sg:city":"Guildford",
    "sg:classifiers":[
        {
            "category":"Personal",
            "subcategory":"Beauty Salon",
            "type":"Services"
        },
        {
            "category":"Personal",
            "subcategory":"Barber",
            "type":"Services"
        }
    ],
    "sg:phone":"+44 1483 300534",
    "sg:postcode":"GU1 4YT",
    "sg:province":"Surrey",
    "sg:tags":[
        "unisex",
        "hairdresser"
    ],
    "wof:name":"Supercuts",
    "wof:placetype":"venue"
},
  "geometry": {"coordinates":[-0.570516,51.237087],"type":"Point"}
}