{
  "type": "Feature",
  "properties": {
    "iso:country":"GB",
    "sg:address":"Brywood House, Boulton Road",
    "sg:city":"Solihull",
    "sg:classifiers":[
        {
            "category":"Professional",
            "subcategory":"Engineering",
            "type":"Services"
        }
    ],
    "sg:phone":"+44 121 705 6365",
    "sg:postcode":"B91 2JU",
    "sg:province":"West Midlands",
    "wof:name":"S G Maintenance Services Ltd.",
    "wof:placetype":"venue"
},
  "geometry": {"coordinates":[-1.775639,52.427235],"type":"Point"}
}