{
  "type": "Feature",
  "properties": {
    "addr:full":"Sheldon Dr Wells Somerset BA5 2HF",
    "addr:postcode":"ba5 2hf",
    "addr:street":"Sheldon Dr",
    "iso:country":"GB",
    "sg:address":"Sheldon Dr",
    "sg:city":"Wells",
    "sg:classifiers":[
        {
            "category":"Social Services",
            "subcategory":"Adult Care",
            "type":"Services"
        }
    ],
    "sg:phone":"+44 1749 676668",
    "sg:postcode":"BA5 2HF",
    "sg:province":"Somerset",
    "sg:tags":[
        "housing",
        "sheltered"
    ],
    "wof:name":"Sheldon Drive Sheltered Housing",
    "wof:placetype":"venue"
},
  "geometry": {"coordinates":[-2.6559839249,51.2063827515],"type":"Point"}
}