{
  "type": "Feature",
  "properties": {
    "addr:full":"3 Foxden Witham Essex CM8 3HN",
    "addr:housenumber":"3",
    "addr:postcode":"cm8 3hn",
    "addr:street":"Foxden Witham",
    "iso:country":"GB",
    "sg:address":"3 Foxden",
    "sg:city":"Witham",
    "sg:classifiers":[
        {
            "category":"Wholesale",
            "subcategory":"Machinery & Supplies",
            "type":"Manufacturing & Wholesale Goods"
        }
    ],
    "sg:phone":"+44 1376 500617",
    "sg:postcode":"CM8 3HN",
    "sg:province":"Essex",
    "sg:tags":[
        "pump"
    ],
    "wof:name":"PRD Ltd",
    "wof:placetype":"venue"
},
  "geometry": {"coordinates":[0.667152,51.817921],"type":"Point"}
}