{
  "type": "Feature",
  "properties": {
    "iso:country":"GB",
    "sg:address":"5 Fox Street",
    "sg:city":"Treharris",
    "sg:classifiers":[
        {
            "category":"Food & Beverages",
            "subcategory":"Bakery",
            "type":"Retail Goods"
        }
    ],
    "sg:phone":"+44 1443 412929",
    "sg:postcode":"CF46 5ET",
    "sg:province":"Caerphilly",
    "sg:tags":[
        "confectionery"
    ],
    "wof:name":"L Hegedus",
    "wof:placetype":"venue"
},
  "geometry": {"coordinates":[-3.3042159081,51.665348053],"type":"Point"}
}