{
  "type": "Feature",
  "properties": {
    "addr:full":"Head Office, High St, Buckden Huntingdon Cambridgeshire PE18 9XA",
    "addr:postcode":"pe18 9xa",
    "addr:street":"High St",
    "iso:country":"GB",
    "sg:address":"Head Office, High St, Buckden",
    "sg:city":"Huntingdon",
    "sg:classifiers":[
        {
            "category":"Shopping",
            "subcategory":"Party Supplies",
            "type":"Retail Goods"
        }
    ],
    "sg:phone":"+44 1480 812481",
    "sg:postcode":"PE18 9XA",
    "sg:province":"Cambridgeshire",
    "sg:tags":[
        "plan",
        "agent"
    ],
    "wof:name":"House Of Chantilly",
    "wof:placetype":"venue"
},
  "geometry": {"coordinates":[-0.2545999885,52.2932014465],"type":"Point"}
}