{
  "type": "Feature",
  "properties": {
    "iso:country":"GB",
    "sg:address":"31 High Street, Kingswood",
    "sg:city":"Bristol",
    "sg:classifiers":[
        {
            "category":"Home & Garden",
            "subcategory":"Carpets & Floor Coverings",
            "type":"Retail Goods"
        }
    ],
    "sg:phone":"+44 117 960 2304",
    "sg:postcode":"BS15 4AA",
    "sg:province":"City of Bristol",
    "sg:tags":[
        "carpets",
        "rug",
        "matting"
    ],
    "wof:name":"Harris the Name Carpets the Game Ltd.",
    "wof:placetype":"venue"
},
  "geometry": {"coordinates":[-2.476667,51.460133],"type":"Point"}
}