{
  "type": "Feature",
  "properties": {
    "addr:full":"Roden House Nottingham Nottinghamshire NG3 1JH",
    "addr:postcode":"ng3 1jh",
    "iso:country":"GB",
    "sg:address":"Roden House",
    "sg:city":"Nottingham",
    "sg:classifiers":[
        {
            "category":"Professional",
            "type":"Services"
        }
    ],
    "sg:postcode":"NG3 1JH",
    "sg:province":"Nottinghamshire",
    "sg:tags":[
        "repair",
        "tech",
        "maintenance"
    ],
    "wof:name":"Carlton Technical Services",
    "wof:placetype":"venue"
},
  "geometry": {"coordinates":[-1.1359599829,52.9557800293],"type":"Point"}
}