{
  "type": "Feature",
  "properties": {
    "addr:full":"4 Elm Cotts Lincolns Hill, Chiddingfold Godalming Surrey GU8 4UL",
    "addr:housenumber":"4;cotts lincolns",
    "addr:postcode":"gu8 4ul",
    "addr:street":"Elm;Hill",
    "iso:country":"GB",
    "sg:address":"4 Elm Cotts Lincolns Hill, Chiddingfold",
    "sg:city":"Godalming",
    "sg:classifiers":[
        {
            "category":"Professional",
            "subcategory":"Engineering",
            "type":"Services"
        }
    ],
    "sg:postcode":"GU8 4UL",
    "sg:province":"Surrey",
    "sg:tags":[
        "contractor",
        "electrical",
        "engineer"
    ],
    "wof:name":"Robert Pullen Electrics",
    "wof:placetype":"venue"
},
  "geometry": {"coordinates":[-0.6277520061,51.1137619019],"type":"Point"}
}