{
  "type": "Feature",
  "properties": {
    "addr:full":"6 Fountain Court, New Leaze, Almondsbury Bristol Gloucestershire BS32 4LA",
    "addr:housenumber":"6",
    "addr:postcode":"bs32 4la",
    "addr:street":"Fountain Court",
    "iso:country":"GB",
    "sg:address":"6 Fountain Court, New Leaze, Almondsbury",
    "sg:city":"Bristol",
    "sg:classifiers":[
        {
            "category":"Professional",
            "subcategory":"Lawyer & Legal Services",
            "type":"Services"
        }
    ],
    "sg:phone":"+44 1454 201338",
    "sg:postcode":"BS32 4LA",
    "sg:province":"Gloucestershire",
    "sg:tags":[
        "solicitor"
    ],
    "wof:name":"Wards Solicitors",
    "wof:placetype":"venue"
},
  "geometry": {"coordinates":[-2.5646190643,51.5565261841],"type":"Point"}
}