{
  "type": "Feature",
  "properties": {
    "addr:full":"Armultra House, Hewett Road Great Yarmouth Norfolk NR31 0RB",
    "addr:postcode":"nr31 0rb",
    "addr:street":"Hewett Road",
    "iso:country":"GB",
    "sg:address":"Armultra House, Hewett Road",
    "sg:city":"Great Yarmouth",
    "sg:classifiers":[
        {
            "category":"Wholesale",
            "subcategory":"Electrical",
            "type":"Manufacturing & Wholesale Goods"
        },
        {
            "category":"Professional",
            "subcategory":"Business Services",
            "type":"Services"
        }
    ],
    "sg:phone":"+44 1493 652150",
    "sg:postcode":"NR31 0RB",
    "sg:province":"Norfolk",
    "sg:tags":[
        "equipment",
        "refrigeration",
        "manufacturer"
    ],
    "sg:website":"http://www.armultra.co.uk",
    "wof:name":"Armultra Ltd",
    "wof:placetype":"venue"
},
  "geometry": {"coordinates":[1.701791,52.591675],"type":"Point"}
}