{
  "type": "Feature",
  "properties": {
    "addr:full":"67 Tamworth Rd, Woodend Atherstone Leicestershire CV9 2QH",
    "addr:housenumber":"67",
    "addr:postcode":"cv9 2qh",
    "addr:street":"Tamworth Rd",
    "iso:country":"GB",
    "sg:address":"67 Tamworth Rd, Woodend",
    "sg:city":"Atherstone",
    "sg:classifiers":[
        {
            "category":"Taxi",
            "type":"Transportation"
        },
        {
            "category":"Military Area",
            "subcategory":"Air Force Base",
            "type":"Public Place"
        }
    ],
    "sg:phone":"+44 1827 874859",
    "sg:postcode":"CV9 2QH",
    "sg:province":"Leicestershire",
    "sg:tags":[
        "mini",
        "hire",
        "private",
        "cab"
    ],
    "wof:name":"Woodend Taxis",
    "wof:placetype":"venue"
},
  "geometry": {"coordinates":[-1.642514,52.581867],"type":"Point"}
}