{
  "type": "Feature",
  "properties": {
    "addr:full":"45 Peppard Road, Caversham Reading Berkshire RG4 8NR",
    "addr:housenumber":"45",
    "addr:postcode":"rg4 8nr",
    "addr:street":"Peppard Road",
    "iso:country":"GB",
    "sg:address":"45 Peppard Road, Caversham",
    "sg:city":"Reading",
    "sg:classifiers":[
        {
            "category":"Health Services",
            "subcategory":"Doctor",
            "type":"Services"
        }
    ],
    "sg:phone":"+44 118 946 2224",
    "sg:postcode":"RG4 8NR",
    "sg:province":"Berkshire",
    "sg:tags":[
        "practitioners"
    ],
    "wof:name":"Peppard Road Surgery",
    "wof:placetype":"venue"
},
  "geometry": {"coordinates":[-0.969497025,51.4715957642],"type":"Point"}
}