{
  "type": "Feature",
  "properties": {
    "addr:full":"64 Birnam Road London Greater London N4 3LQ",
    "addr:housenumber":"64",
    "addr:postcode":"n4 3lq",
    "addr:street":"Birnam Road",
    "iso:country":"GB",
    "sg:address":"64 Birnam Road",
    "sg:city":"London",
    "sg:classifiers":[
        {
            "category":"Professional",
            "subcategory":"Art Services",
            "type":"Services"
        }
    ],
    "sg:postcode":"N4 3LQ",
    "sg:province":"Greater London",
    "sg:tags":[
        "photographer"
    ],
    "wof:name":"Robert Aberman",
    "wof:placetype":"venue"
},
  "geometry": {"coordinates":[-0.116008997,51.5643386841],"type":"Point"}
}