{
  "type": "Feature",
  "properties": {
    "iso:country":"GB",
    "sg:address":"Beechhill Creca",
    "sg:city":"Annan",
    "sg:classifiers":[
        {
            "category":"Farming",
            "subcategory":"Livestock Farm",
            "type":"Manufacturing & Wholesale Goods"
        }
    ],
    "sg:phone":"+44 1461 500258",
    "sg:postcode":"DG12 6RP",
    "sg:province":"Dumfries and Galloway",
    "sg:tags":[
        "others"
    ],
    "wof:name":"C T Scott & Partners",
    "wof:placetype":"venue"
},
  "geometry": {"coordinates":[-3.256819,54.987034],"type":"Point"}
}