{
  "type": "Feature",
  "properties": {
    "iso:country":"GB",
    "sg:address":"36 Copt-elm Road, Charlton Kings",
    "sg:city":"Cheltenham",
    "sg:classifiers":[
        {
            "category":"Building & Trades",
            "subcategory":"Construction",
            "type":"Services"
        }
    ],
    "sg:postcode":"GL53 8AL",
    "sg:province":"Gloucestershire",
    "sg:tags":[
        "joiner",
        "carpenter"
    ],
    "wof:name":"Roy Peacey Carpenter & Joiner",
    "wof:placetype":"venue"
},
  "geometry": {"coordinates":[-2.053303,51.885208],"type":"Point"}
}