{
  "type": "Feature",
  "properties": {
    "addr:full":"Woodlyn, Castramont Road, Gatehouse Of Fleet Castle Douglas Dumfries and Galloway DG7 2JE",
    "addr:postcode":"dg7 2je",
    "addr:street":"Castramont Road Gatehouse",
    "iso:country":"GB",
    "sg:address":"Woodlyn, Castramont Road, Gatehouse Of Fleet",
    "sg:city":"Castle Douglas",
    "sg:classifiers":[
        {
            "category":"Organizations",
            "subcategory":"Community Association",
            "type":"Services"
        }
    ],
    "sg:phone":"+44 1557 814639",
    "sg:postcode":"DG7 2JE",
    "sg:province":"Dumfries and Galloway",
    "sg:tags":[
        "society",
        "housing"
    ],
    "wof:name":"Abbeyfield Stewrtry Society",
    "wof:placetype":"venue"
},
  "geometry": {"coordinates":[-4.186934,54.880909],"type":"Point"}
}