{
  "type": "Feature",
  "properties": {
    "iso:country":"GB",
    "sg:address":"26 Cheviot Rd",
    "sg:city":"Hornchurch",
    "sg:classifiers":[
        {
            "category":"Home & Garden",
            "subcategory":"Building Materials",
            "type":"Retail Goods"
        }
    ],
    "sg:postcode":"RM11 1LP",
    "sg:province":"Essex",
    "sg:tags":[
        "insulation",
        "installers"
    ],
    "wof:name":"Future Interiors",
    "wof:placetype":"venue"
},
  "geometry": {"coordinates":[0.1974910051,51.5662574768],"type":"Point"}
}