{
  "type": "Feature",
  "properties": {
    "addr:full":"Lasswade Road Edinburgh City of Edinburgh EH16 6UE",
    "addr:postcode":"eh16 6ue",
    "addr:street":"Lasswade Road",
    "iso:country":"GB",
    "sg:address":"Lasswade Road",
    "sg:city":"Edinburgh",
    "sg:classifiers":[
        {
            "category":"Health Services",
            "subcategory":"Hospital",
            "type":"Services"
        }
    ],
    "sg:phone":"+44 131 672 2958",
    "sg:postcode":"EH16 6UE",
    "sg:province":"City of Edinburgh",
    "wof:name":"Lothian Health Board",
    "wof:placetype":"venue"
},
  "geometry": {"coordinates":[-3.1594569683,55.9130783081],"type":"Point"}
}