{
  "type": "Feature",
  "properties": {
    "addr:full":"47 High Street, Stokesley Middlesbrough North Yorkshire TS9 5AD",
    "addr:housenumber":"47",
    "addr:postcode":"ts9 5ad",
    "addr:street":"High Street",
    "iso:country":"GB",
    "sg:address":"47 High Street, Stokesley",
    "sg:city":"Middlesbrough",
    "sg:classifiers":[
        {
            "category":"Shopping",
            "subcategory":"Gifts & Souvenirs",
            "type":"Retail Goods"
        }
    ],
    "sg:phone":"+44 1642 711683",
    "sg:postcode":"TS9 5AD",
    "sg:province":"North Yorkshire",
    "sg:tags":[
        "shop"
    ],
    "wof:name":"The Yorkshire Store",
    "wof:placetype":"venue"
},
  "geometry": {"coordinates":[-1.19284904,54.4695472717],"type":"Point"}
}