{
  "type": "Feature",
  "properties": {
    "iso:country":"GB",
    "sg:address":"3 Sunnyside Road",
    "sg:city":"Clevedon",
    "sg:classifiers":[
        {
            "category":"Education",
            "subcategory":"Preschool",
            "type":"Public Place"
        },
        {
            "category":"Government",
            "subcategory":"Office",
            "type":"Public Place"
        }
    ],
    "sg:phone":"+44 1275 874886",
    "sg:postcode":"BS21 7TA",
    "sg:province":"Somerset",
    "sg:tags":[
        "pre-school",
        "agency",
        "playgroups",
        "authority"
    ],
    "wof:name":"Sunnyside Pre School Playgroup",
    "wof:placetype":"venue"
},
  "geometry": {"coordinates":[-2.8579769135,51.4379348755],"type":"Point"}
}