{
  "type": "Feature",
  "properties": {
    "addr:full":"Cranborne Road, Furzehill Wimborne Dorset BH21 4HW",
    "addr:postcode":"bh21 4hw",
    "addr:street":"Cranborne Road Furzehill",
    "iso:country":"GB",
    "sg:address":"Cranborne Road, Furzehill",
    "sg:city":"Wimborne",
    "sg:classifiers":[
        {
            "category":"Recreation",
            "subcategory":"Campground",
            "type":"Entertainment"
        }
    ],
    "sg:postcode":"BH21 4HW",
    "sg:province":"Dorset",
    "sg:tags":[
        "site",
        "camping"
    ],
    "wof:name":"Wilksworth Farm Caravan Park",
    "wof:placetype":"venue"
},
  "geometry": {"coordinates":[-1.979794,50.818729],"type":"Point"}
}