{
  "type": "Feature",
  "properties": {
    "iso:country":"GB",
    "sg:address":"4 Nuttfield Clo",
    "sg:city":"Rickmansworth",
    "sg:classifiers":[
        {
            "category":"Building & Trades",
            "subcategory":"Plumbing",
            "type":"Services"
        }
    ],
    "sg:phone":"+44 1923 462172",
    "sg:postcode":"WD3 3AT",
    "sg:province":"Hertfordshire",
    "sg:tags":[
        "heating"
    ],
    "wof:name":"Turnkey",
    "wof:placetype":"venue"
},
  "geometry": {"coordinates":[-0.4403469861,51.6462211609],"type":"Point"}
}