{
  "type": "Feature",
  "properties": {
    "iso:country":"GB",
    "sg:address":"394 Main Rd, Dovercourt",
    "sg:city":"Harwich",
    "sg:classifiers":[
        {
            "category":"Autos & Motor Vehicles",
            "subcategory":"Fuel & Gas Station",
            "type":"Retail Goods"
        }
    ],
    "sg:phone":"+44 1255 553971",
    "sg:postcode":"CO12 4DJ",
    "sg:province":"Essex",
    "sg:tags":[
        "petrol",
        "filling"
    ],
    "wof:name":"Vines Service Station",
    "wof:placetype":"venue"
},
  "geometry": {"coordinates":[1.2734650373,51.935634613],"type":"Point"}
}