{
  "type": "Feature",
  "properties": {
    "addr:full":"James Hemphill Court, Lennoxtown Glasgow East Dunbartonshire G66 7EX",
    "addr:postcode":"g66 7ex",
    "addr:street":"Hemphill Court",
    "iso:country":"GB",
    "sg:address":"James Hemphill Court, Lennoxtown",
    "sg:city":"Glasgow",
    "sg:classifiers":[
        {
            "category":"Organizations",
            "subcategory":"Community Association",
            "type":"Services"
        }
    ],
    "sg:phone":"+44 1360 312321",
    "sg:postcode":"G66 7EX",
    "sg:province":"East Dunbartonshire",
    "sg:tags":[
        "co-operatives",
        "society",
        "housing",
        "trust"
    ],
    "wof:name":"Hanover (Scotland) Housing Association Ltd.",
    "wof:placetype":"venue"
},
  "geometry": {"coordinates":[-4.200329,55.974571],"type":"Point"}
}