{
  "type": "Feature",
  "properties": {
    "iso:country":"GB",
    "sg:address":"177a Queens Road",
    "sg:city":"Hastings",
    "sg:classifiers":[
        {
            "category":"Fast Food",
            "type":"Food & Drink"
        },
        {
            "category":"Restaurant",
            "type":"Food & Drink"
        }
    ],
    "sg:phone":"+44 1424 439493",
    "sg:postcode":"TN34 1RN",
    "sg:province":"East Sussex",
    "sg:tags":[
        "away",
        "indian",
        "take"
    ],
    "wof:name":"Shiplu Restaurant",
    "wof:placetype":"venue"
},
  "geometry": {"coordinates":[0.583227,50.859039],"type":"Point"}
}