{
  "type": "Feature",
  "properties": {
    "iso:country":"GB",
    "sg:address":"12 Cedar St",
    "sg:city":"Southport",
    "sg:classifiers":[
        {
            "category":"Manufacturing",
            "subcategory":"Signs",
            "type":"Manufacturing & Wholesale Goods"
        }
    ],
    "sg:phone":"+44 1704 537716",
    "sg:postcode":"PR8 6NG",
    "sg:province":"Lancashire",
    "sg:tags":[
        "writer"
    ],
    "wof:name":"Design Signs",
    "wof:placetype":"venue"
},
  "geometry": {"coordinates":[-2.991149,53.636433],"type":"Point"}
}