{
  "type": "Feature",
  "properties": {
    "addr:full":"54 Dalestorth Street Sutton-in-ashfield Nottinghamshire NG17 4EX",
    "addr:housenumber":"54",
    "addr:postcode":"ng17 4ex",
    "addr:street":"Dalestorth Street",
    "iso:country":"GB",
    "sg:address":"54 Dalestorth Street",
    "sg:city":"Sutton-in-ashfield",
    "sg:classifiers":[
        {
            "category":"Personal",
            "subcategory":"Beauty Salon",
            "type":"Services"
        }
    ],
    "sg:phone":"+44 1623 443618",
    "sg:postcode":"NG17 4EX",
    "sg:province":"Nottinghamshire",
    "sg:tags":[
        "unisex",
        "hairdresser"
    ],
    "wof:name":"Fayes Unisex Hair Salon",
    "wof:placetype":"venue"
},
  "geometry": {"coordinates":[-1.2526880503,53.1322937012],"type":"Point"}
}