{
  "type": "Feature",
  "properties": {
    "addr:full":"28 Sugden Rd Worthing West Sussex BN11 2JQ",
    "addr:housenumber":"28",
    "addr:postcode":"bn11 2jq",
    "addr:street":"Sugden Rd",
    "iso:country":"GB",
    "sg:address":"28 Sugden Rd",
    "sg:city":"Worthing",
    "sg:classifiers":[
        {
            "category":"Food & Beverages",
            "subcategory":"Supermarket",
            "type":"Retail Goods"
        }
    ],
    "sg:postcode":"BN11 2JQ",
    "sg:province":"West Sussex",
    "wof:name":"Lori's Mini Market",
    "wof:placetype":"venue"
},
  "geometry": {"coordinates":[-0.360185,50.817383],"type":"Point"}
}