{
  "type": "Feature",
  "properties": {
    "addr:full":"12 Carlton Avenue, Cheadle Hulme Cheadle Cheshire SK8 5EH",
    "addr:housenumber":"12",
    "addr:postcode":"sk8 5eh",
    "addr:street":"Carlton Avenue",
    "iso:country":"GB",
    "sg:address":"12 Carlton Avenue, Cheadle Hulme",
    "sg:city":"Cheadle",
    "sg:classifiers":[
        {
            "category":"Retail",
            "subcategory":"Repair Shop",
            "type":"Services"
        }
    ],
    "sg:postcode":"SK8 5EH",
    "sg:province":"Cheshire",
    "sg:tags":[
        "plant",
        "machinery"
    ],
    "wof:name":"Carlton Print Services",
    "wof:placetype":"venue"
},
  "geometry": {"coordinates":[-2.1973950863,53.3808097839],"type":"Point"}
}