{
  "type": "Feature",
  "properties": {
    "iso:country":"GB",
    "sg:address":"Croft Bank, Croft",
    "sg:city":"Skegness",
    "sg:classifiers":[
        {
            "category":"Restaurant",
            "type":"Food & Drink"
        }
    ],
    "sg:phone":"+44 1754 762890",
    "sg:postcode":"PE24 4AW",
    "sg:province":"Lincolnshire",
    "wof:name":"Cottage Restaurant",
    "wof:placetype":"venue"
},
  "geometry": {"coordinates":[0.297668,53.135414],"type":"Point"}
}