{
  "type": "Feature",
  "properties": {
    "iso:country":"GB",
    "sg:address":"Leigh Farm, Westerleigh",
    "sg:city":"Bristol",
    "sg:classifiers":[
        {
            "category":"Farming",
            "subcategory":"Farm",
            "type":"Manufacturing & Wholesale Goods"
        }
    ],
    "sg:phone":"+44 117 937 2440",
    "sg:postcode":"BS37 8RE",
    "sg:province":"Gloucestershire",
    "sg:tags":[
        "mixed",
        "crop"
    ],
    "wof:name":"F D & S M Humphris & Son",
    "wof:placetype":"venue"
},
  "geometry": {"coordinates":[-2.434194088,51.516834259],"type":"Point"}
}