{
  "type": "Feature",
  "properties": {
    "addr:full":"10 Guild Hall Arcade, Lancaster Road Preston Lancashire PR1 1HR",
    "addr:housenumber":"10",
    "addr:postcode":"pr1 1hr",
    "addr:street":"Guild Hall Arcade Lancaster Road",
    "iso:country":"GB",
    "sg:address":"10 Guild Hall Arcade, Lancaster Road",
    "sg:city":"Preston",
    "sg:classifiers":[
        {
            "category":"Deli",
            "type":"Food & Drink"
        }
    ],
    "sg:postcode":"PR1 1HR",
    "sg:province":"Lancashire",
    "sg:tags":[
        "delicatessen"
    ],
    "wof:name":"Cassandra's",
    "wof:placetype":"venue"
},
  "geometry": {"coordinates":[-2.7057290077,53.7579612732],"type":"Point"}
}