{
  "type": "Feature",
  "properties": {
    "addr:full":"Straight Road Romford Essex RM3 7JS",
    "addr:postcode":"rm3 7js",
    "addr:street":"Straight Road",
    "iso:country":"GB",
    "sg:address":"Straight Road",
    "sg:city":"Romford",
    "sg:classifiers":[
        {
            "category":"Education",
            "subcategory":"School",
            "type":"Public Place"
        }
    ],
    "sg:phone":"+44 1708 343170",
    "sg:postcode":"RM3 7JS",
    "sg:province":"Essex",
    "sg:tags":[
        "local",
        "authority"
    ],
    "wof:name":"St Ursula's R C Junior School",
    "wof:placetype":"venue"
},
  "geometry": {"coordinates":[0.2131440043,51.5938835144],"type":"Point"}
}