{
  "type": "Feature",
  "properties": {
    "addr:full":"28 Linver Road London Greater London SW6 3RB",
    "addr:housenumber":"28",
    "addr:postcode":"sw6 3rb",
    "addr:street":"Linver Road",
    "iso:country":"GB",
    "sg:address":"28 Linver Road",
    "sg:city":"London",
    "sg:classifiers":[
        {
            "category":"Real Estate",
            "subcategory":"Developer",
            "type":"Services"
        }
    ],
    "sg:postcode":"SW6 3RB",
    "sg:province":"Greater London",
    "sg:tags":[
        "property"
    ],
    "wof:name":"The Coxton Partnership",
    "wof:placetype":"venue"
},
  "geometry": {"coordinates":[-0.201748997,51.4724082947],"type":"Point"}
}