{
  "type": "Feature",
  "properties": {
    "iso:country":"GB",
    "sg:address":"Yew Tree Inn, Barfreestone",
    "sg:city":"Dover",
    "sg:classifiers":[
        {
            "category":"Bars & Pubs",
            "type":"Food & Drink"
        }
    ],
    "sg:postcode":"CT15 7JH",
    "sg:province":"Kent",
    "sg:tags":[
        "pubs",
        "inn"
    ],
    "wof:name":"Yew Tree Inn",
    "wof:placetype":"venue"
},
  "geometry": {"coordinates":[1.23981,51.205841],"type":"Point"}
}