{
  "type": "Feature",
  "properties": {
    "addr:full":"19 High Street, Carcroft Doncaster North Yorkshire DN6 8DN",
    "addr:housenumber":"19",
    "addr:postcode":"dn6 8dn",
    "addr:street":"High Street",
    "iso:country":"GB",
    "sg:address":"19 High Street, Carcroft",
    "sg:city":"Doncaster",
    "sg:classifiers":[
        {
            "category":"Government",
            "subcategory":"Post Office",
            "type":"Public Place"
        }
    ],
    "sg:phone":"+44 1302 723515",
    "sg:postcode":"DN6 8DN",
    "sg:province":"North Yorkshire",
    "wof:name":"Carcroft Post Office",
    "wof:placetype":"venue"
},
  "geometry": {"coordinates":[-1.1807370186,53.5829315186],"type":"Point"}
}