{
  "type": "Feature",
  "properties": {
    "addr:full":"158 Southerland Gro Milton Keynes Buckinghamshire MK3 7NX",
    "addr:housenumber":"158",
    "addr:postcode":"mk3 7nx",
    "addr:street":"Southerland Gro",
    "iso:country":"GB",
    "sg:address":"158 Southerland Gro",
    "sg:city":"Milton Keynes",
    "sg:classifiers":[
        {
            "category":"Home & Garden",
            "subcategory":"Carpets & Floor Coverings",
            "type":"Retail Goods"
        }
    ],
    "sg:phone":"+44 1908 366604",
    "sg:postcode":"MK3 7NX",
    "sg:province":"Buckinghamshire",
    "sg:tags":[
        "carpets",
        "rug",
        "matting"
    ],
    "wof:name":"Canaan Carpets",
    "wof:placetype":"venue"
},
  "geometry": {"coordinates":[-0.7551419735,52.0053024292],"type":"Point"}
}