{
  "type": "Feature",
  "properties": {
    "iso:country":"GB",
    "sg:address":"Personnel Services, Training & Development, Council Offices",
    "sg:city":"Cumnock",
    "sg:classifiers":[
        {
            "category":"Government",
            "subcategory":"Office",
            "type":"Public Place"
        }
    ],
    "sg:phone":"+44 1563 555284",
    "sg:postcode":"KA18 3JQ",
    "sg:province":"East Ayrshire",
    "sg:tags":[
        "local"
    ],
    "wof:name":"East Ayrshire Council",
    "wof:placetype":"venue"
},
  "geometry": {"coordinates":[-4.23265,55.467209],"type":"Point"}
}