{
  "type": "Feature",
  "properties": {
    "addr:full":"22 Station Road Wellington Devon TA21 8NJ",
    "addr:housenumber":"22",
    "addr:postcode":"ta21 8nj",
    "addr:street":"Station Road",
    "iso:country":"GB",
    "sg:address":"22 Station Road",
    "sg:city":"Wellington",
    "sg:classifiers":[
        {
            "category":"Shopping",
            "subcategory":"Department Store",
            "type":"Retail Goods"
        }
    ],
    "sg:phone":"+44 1823 662445",
    "sg:postcode":"TA21 8NJ",
    "sg:province":"Devon",
    "wof:name":"Keith's Food Store",
    "wof:placetype":"venue"
},
  "geometry": {"coordinates":[-3.2394111156,50.9835014343],"type":"Point"}
}