{
  "type": "Feature",
  "properties": {
    "iso:country":"GB",
    "sg:address":"3 Brook Court, Brook Street, Bishops Waltham",
    "sg:city":"Southampton",
    "sg:classifiers":[
        {
            "category":"Personal",
            "subcategory":"Beauty Salon",
            "type":"Services"
        }
    ],
    "sg:phone":"+44 1489 891299",
    "sg:postcode":"SO32 1AX",
    "sg:province":"Hampshire",
    "sg:tags":[
        "unisex",
        "hairdresser"
    ],
    "wof:name":"Barber Elles",
    "wof:placetype":"venue"
},
  "geometry": {"coordinates":[-1.2128230333,50.9548683167],"type":"Point"}
}