{
  "type": "Feature",
  "properties": {
    "addr:full":"Moorside Farm, Burnley Rd Accrington Lancashire BB5 5TZ",
    "addr:postcode":"bb5 5tz",
    "addr:street":"Burnley Rd",
    "iso:country":"GB",
    "sg:address":"Moorside Farm, Burnley Rd",
    "sg:city":"Accrington",
    "sg:classifiers":[
        {
            "category":"Retail",
            "subcategory":"Auto Repair",
            "type":"Services"
        }
    ],
    "sg:phone":"+44 1254 238498",
    "sg:postcode":"BB5 5TZ",
    "sg:province":"Lancashire",
    "sg:tags":[
        "modification",
        "garage",
        "related"
    ],
    "wof:name":"M Boothman",
    "wof:placetype":"venue"
},
  "geometry": {"coordinates":[-2.3706440926,53.7553291321],"type":"Point"}
}