{
  "type": "Feature",
  "properties": {
    "iso:country":"GB",
    "sg:address":"Hagley Hill Farm",
    "sg:city":"Stourbridge",
    "sg:classifiers":[
        {
            "category":"Farming",
            "subcategory":"Farm",
            "type":"Manufacturing & Wholesale Goods"
        }
    ],
    "sg:phone":"+44 121 236 1866",
    "sg:postcode":"DY9 9YE",
    "sg:province":"West Midlands",
    "sg:tags":[
        "mixed",
        "crop"
    ],
    "wof:name":"David Rose (Farms) Ltd.",
    "wof:placetype":"venue"
},
  "geometry": {"coordinates":[-2.115491,52.429482],"type":"Point"}
}