{
  "type": "Feature",
  "properties": {
    "iso:country":"GB",
    "sg:address":"Hassock Business Park, Northington Down",
    "sg:city":"Alresford",
    "sg:classifiers":[
        {
            "category":"Professional",
            "subcategory":"Business Services",
            "type":"Services"
        }
    ],
    "sg:postcode":"SO24 9UB",
    "sg:province":"Hampshire",
    "sg:tags":[
        "hospitality",
        "corporate"
    ],
    "wof:name":"Team Spirit",
    "wof:placetype":"venue"
},
  "geometry": {"coordinates":[-1.209784,51.133293],"type":"Point"}
}