{
  "type": "Feature",
  "properties": {
    "addr:full":"4 Goods Station Rd Tunbridge Wells Kent TN1 2BJ",
    "addr:housenumber":"4",
    "addr:postcode":"tn1 2bj",
    "addr:street":"Station Rd",
    "iso:country":"GB",
    "sg:address":"4 Goods Station Rd",
    "sg:city":"Tunbridge Wells",
    "sg:classifiers":[
        {
            "category":"Manufacturing",
            "subcategory":"Tools & Machinery",
            "type":"Manufacturing & Wholesale Goods"
        }
    ],
    "sg:postcode":"TN1 2BJ",
    "sg:province":"Kent",
    "wof:name":"Coffin,Martin,",
    "wof:placetype":"venue"
},
  "geometry": {"coordinates":[0.263736,51.135044],"type":"Point"}
}