{
  "type": "Feature",
  "properties": {
    "addr:full":"Crescent Works, Wilford Gro Nottingham Nottinghamshire NG2 2DT",
    "addr:postcode":"ng2 2dt",
    "addr:street":"Gro",
    "iso:country":"GB",
    "sg:address":"Crescent Works, Wilford Gro",
    "sg:city":"Nottingham",
    "sg:classifiers":[
        {
            "category":"Home & Garden",
            "subcategory":"Furniture",
            "type":"Retail Goods"
        }
    ],
    "sg:phone":"+44 115 952 8877",
    "sg:postcode":"NG2 2DT",
    "sg:province":"Nottinghamshire",
    "wof:name":"Carlton Bailey",
    "wof:placetype":"venue"
},
  "geometry": {"coordinates":[-1.1470390558,52.9410896301],"type":"Point"}
}