{
  "type": "Feature",
  "properties": {
    "addr:full":"Hillhead Farm, Chagford Newton Abbot Devon TQ13 8DY",
    "addr:postcode":"tq13 8dy",
    "iso:country":"GB",
    "sg:address":"Hillhead Farm, Chagford",
    "sg:city":"Newton Abbot",
    "sg:classifiers":[
        {
            "category":"Food & Beverages",
            "subcategory":"Specialty",
            "type":"Retail Goods"
        }
    ],
    "sg:postcode":"TQ13 8DY",
    "sg:province":"Devon",
    "sg:tags":[
        "organic"
    ],
    "wof:name":"Wild Beef",
    "wof:placetype":"venue"
},
  "geometry": {"coordinates":[-3.834256,50.677418],"type":"Point"}
}