{
  "type": "Feature",
  "properties": {
    "iso:country":"GB",
    "sg:address":"Broombank Rd, Chesterfield Trading Est",
    "sg:city":"Chesterfield",
    "sg:classifiers":[
        {
            "category":"Professional",
            "subcategory":"Engineering",
            "type":"Services"
        }
    ],
    "sg:phone":"+44 1246 452525",
    "sg:postcode":"S41 9QJ",
    "sg:province":"Derbyshire",
    "sg:tags":[
        "precision",
        "engineer"
    ],
    "wof:name":"Exacto-Bore (Engineers) Ltd",
    "wof:placetype":"venue"
},
  "geometry": {"coordinates":[-1.4430990219,53.2733840942],"type":"Point"}
}