{
  "type": "Feature",
  "properties": {
    "addr:full":"132 Elm Road Kingston-upon-thames Greater London KT2 6HU",
    "addr:housenumber":"132",
    "addr:postcode":"kt2 6hu",
    "addr:street":"Elm Road",
    "iso:country":"GB",
    "sg:address":"132 Elm Road",
    "sg:city":"Kingston-upon-thames",
    "sg:classifiers":[
        {
            "category":"Shopping",
            "subcategory":"Computers & Home Electronics",
            "type":"Retail Goods"
        }
    ],
    "sg:phone":"+44 20 8546 6831",
    "sg:postcode":"KT2 6HU",
    "sg:province":"Greater London",
    "sg:tags":[
        "equipment",
        "radio"
    ],
    "wof:name":"H M Communications",
    "wof:placetype":"venue"
},
  "geometry": {"coordinates":[-0.2938410044,51.4170417786],"type":"Point"}
}