{
  "type": "Feature",
  "properties": {
    "addr:full":"Little Bedford Street North Shields Tyne and Wear NE29 6NW",
    "addr:postcode":"ne29 6nw",
    "addr:street":"Little Bedford Street",
    "iso:country":"GB",
    "sg:address":"Little Bedford Street",
    "sg:city":"North Shields",
    "sg:classifiers":[
        {
            "category":"Shopping",
            "subcategory":"Clothing, Apparel, & Fashions",
            "type":"Retail Goods"
        }
    ],
    "sg:postcode":"NE29 6NW",
    "sg:province":"Tyne and Wear",
    "sg:tags":[
        "haberdasher"
    ],
    "wof:name":"Reeds",
    "wof:placetype":"venue"
},
  "geometry": {"coordinates":[-1.4458839893,55.0074768066],"type":"Point"}
}