{
  "type": "Feature",
  "properties": {
    "addr:full":"Unit 36, Ten Acres, Berry Hill Industrial Estate Droitwich Worcestershire WR9 9AE",
    "addr:housenumber":"unit 36",
    "addr:postcode":"wr9 9ae",
    "addr:street":"Ten Acres;Hill Industrial Estate",
    "iso:country":"GB",
    "sg:address":"Unit 36, Ten Acres, Berry Hill Industrial Estate",
    "sg:city":"Droitwich",
    "sg:classifiers":[
        {
            "category":"Manufacturing",
            "subcategory":"Petroleum Products",
            "type":"Manufacturing & Wholesale Goods"
        }
    ],
    "sg:phone":"+44 1905 774267",
    "sg:postcode":"WR9 9AE",
    "sg:province":"Worcestershire",
    "sg:tags":[
        "double",
        "glazing"
    ],
    "wof:name":"A W S Turner Fain Ltd.",
    "wof:placetype":"venue"
},
  "geometry": {"coordinates":[-2.1562490463,52.2755088806],"type":"Point"}
}