{
  "type": "Feature",
  "properties": {
    "addr:full":"5 Lucy Hall Drive, Baildon Shipley West Yorkshire BD17 5BG",
    "addr:housenumber":"5",
    "addr:postcode":"bd17 5bg",
    "addr:street":"Lucy Hall Drive Baildon",
    "iso:country":"GB",
    "sg:address":"5 Lucy Hall Drive, Baildon",
    "sg:city":"Shipley",
    "sg:classifiers":[
        {
            "category":"Retail",
            "subcategory":"Storage",
            "type":"Services"
        }
    ],
    "sg:phone":"+44 1274 598099",
    "sg:postcode":"BD17 5BG",
    "sg:province":"West Yorkshire",
    "sg:tags":[
        "household",
        "activity",
        "domestic",
        "removal"
    ],
    "wof:name":"A J Pellitt & Son",
    "wof:placetype":"venue"
},
  "geometry": {"coordinates":[-1.7927269936,53.8477287292],"type":"Point"}
}