{
  "type": "Feature",
  "properties": {
    "iso:country":"GB",
    "sg:address":"23 Beverley Avenue",
    "sg:city":"Bristol",
    "sg:classifiers":[
        {
            "category":"Building & Trades",
            "subcategory":"Construction",
            "type":"Services"
        }
    ],
    "sg:phone":"+44 117 949 2251",
    "sg:postcode":"BS16 6SX",
    "sg:province":"City of Bristol",
    "sg:tags":[
        "builder"
    ],
    "wof:name":"H K Construction",
    "wof:placetype":"venue"
},
  "geometry": {"coordinates":[-2.494948,51.500565],"type":"Point"}
}