{
  "type": "Feature",
  "properties": {
    "addr:full":"134 Dukes Road, Rutherglen Glasgow Glasgow City G73 5AF",
    "addr:housenumber":"134",
    "addr:postcode":"g73 5af",
    "addr:street":"Dukes Road",
    "iso:country":"GB",
    "sg:address":"134 Dukes Road, Rutherglen",
    "sg:city":"Glasgow",
    "sg:classifiers":[
        {
            "category":"Food & Beverages",
            "subcategory":"Liquor & Beverages",
            "type":"Retail Goods"
        }
    ],
    "sg:phone":"+44 141 647 6653",
    "sg:postcode":"G73 5AF",
    "sg:province":"Glasgow City",
    "sg:tags":[
        "beer",
        "wine",
        "spirit",
        "wines"
    ],
    "wof:name":"Supersave",
    "wof:placetype":"venue"
},
  "geometry": {"coordinates":[-4.1919322014,55.8184394836],"type":"Point"}
}