{
  "type": "Feature",
  "properties": {
    "addr:full":"25 London Road, Kirton Boston Lincolnshire PE20 1JE",
    "addr:housenumber":"25",
    "addr:postcode":"pe20 1je",
    "addr:street":"London Road",
    "iso:country":"GB",
    "sg:address":"25 London Road, Kirton",
    "sg:city":"Boston",
    "sg:classifiers":[
        {
            "category":"Personal",
            "subcategory":"Beauty Salon",
            "type":"Services"
        }
    ],
    "sg:phone":"+44 1205 722476",
    "sg:postcode":"PE20 1JE",
    "sg:province":"Lincolnshire",
    "sg:tags":[
        "unisex",
        "hairdresser"
    ],
    "wof:name":"The Hairstudio 2",
    "wof:placetype":"venue"
},
  "geometry": {"coordinates":[-0.0607400015,52.9273757935],"type":"Point"}
}