{
  "type": "Feature",
  "properties": {
    "iso:country":"GB",
    "sg:address":"20 Newbridge Road, Glen Parva",
    "sg:city":"Leicester",
    "sg:classifiers":[
        {
            "category":"Building & Trades",
            "subcategory":"Construction",
            "type":"Services"
        }
    ],
    "sg:phone":"+44 116 277 9070",
    "sg:postcode":"LE2 9TG",
    "sg:province":"Leicestershire",
    "sg:tags":[
        "builder"
    ],
    "wof:name":"M & D Grant",
    "wof:placetype":"venue"
},
  "geometry": {"coordinates":[-1.165927,52.581882],"type":"Point"}
}