{
  "type": "Feature",
  "properties": {
    "iso:country":"GB",
    "sg:address":"16 Helliwell Lane, Deepcar",
    "sg:city":"Sheffield",
    "sg:classifiers":[
        {
            "category":"Bars & Pubs",
            "type":"Food & Drink"
        },
        {
            "category":"Community Center",
            "subcategory":"Social",
            "type":"Public Place"
        }
    ],
    "sg:phone":"+44 114 288 4482",
    "sg:postcode":"S36 2QH",
    "sg:province":"South Yorkshire",
    "sg:tags":[
        "pubs",
        "house",
        "inn",
        "activity"
    ],
    "wof:name":"Pen Nook",
    "wof:placetype":"venue"
},
  "geometry": {"coordinates":[-1.5737190247,53.475566864],"type":"Point"}
}