{
  "type": "Feature",
  "properties": {
    "addr:full":"Studio 8 92 Lots Road, Chelsea London Greater London SW10 0QD",
    "addr:housenumber":"92",
    "addr:postcode":"sw10 0qd",
    "addr:street":"Lots Road",
    "iso:country":"GB",
    "sg:address":"Studio 8 92 Lots Road, Chelsea",
    "sg:city":"London",
    "sg:classifiers":[
        {
            "category":"Professional",
            "subcategory":"Advertising",
            "type":"Services"
        }
    ],
    "sg:postcode":"SW10 0QD",
    "sg:province":"Greater London",
    "sg:tags":[
        "agency"
    ],
    "wof:name":"M J F Advertising & Marketing Services Ltd.",
    "wof:placetype":"venue"
},
  "geometry": {"coordinates":[-0.18076,51.47871],"type":"Point"}
}