{
  "type": "Feature",
  "properties": {
    "addr:full":"Grassyards Rd Kilmarnock East Ayrshire KA3 7SH",
    "addr:postcode":"ka3 7sh",
    "addr:street":"Grassyards Rd",
    "iso:country":"GB",
    "sg:address":"Grassyards Rd",
    "sg:city":"Kilmarnock",
    "sg:classifiers":[
        {
            "category":"Place Of Worship",
            "type":"Public Place"
        },
        {
            "category":"Organizations",
            "subcategory":"Non-profit Organization",
            "type":"Services"
        }
    ],
    "sg:phone":"+44 1563 533587",
    "sg:postcode":"KA3 7SH",
    "sg:province":"East Ayrshire",
    "sg:tags":[
        "charitable",
        "organisation",
        "charity"
    ],
    "wof:name":"St Matthews R C Church",
    "wof:placetype":"venue"
},
  "geometry": {"coordinates":[-4.483812,55.610813],"type":"Point"}
}