{
  "type": "Feature",
  "properties": {
    "iso:country":"GB",
    "sg:address":"198 Wellesley Road, Methil",
    "sg:city":"Leven",
    "sg:classifiers":[
        {
            "category":"Professional",
            "subcategory":"Lawyer & Legal Services",
            "type":"Services"
        }
    ],
    "sg:phone":"+44 1333 424661",
    "sg:postcode":"KY8 3BW",
    "sg:province":"Fife",
    "sg:tags":[
        "solicitor"
    ],
    "wof:name":"Smith & Grant (Solicitors)",
    "wof:placetype":"venue"
},
  "geometry": {"coordinates":[-3.013479948,56.1859779358],"type":"Point"}
}