{
  "type": "Feature",
  "properties": {
    "iso:country":"GB",
    "sg:address":"46 Rokells",
    "sg:city":"Basildon",
    "sg:classifiers":[
        {
            "category":"Professional",
            "subcategory":"Business Services",
            "type":"Services"
        }
    ],
    "sg:phone":"+44 1268 533521",
    "sg:postcode":"SS14 2BD",
    "sg:province":"Essex",
    "sg:tags":[
        "accomodation"
    ],
    "wof:name":"Logrose Ltd.",
    "wof:placetype":"venue"
},
  "geometry": {"coordinates":[0.4570330083,51.5751686096],"type":"Point"}
}