{
  "type": "Feature",
  "properties": {
    "addr:full":"Park Road Haddington East Lothian EH41 4PT",
    "addr:postcode":"eh41 4pt",
    "addr:street":"Park Road",
    "iso:country":"GB",
    "sg:address":"Park Road",
    "sg:city":"Haddington",
    "sg:classifiers":[
        {
            "category":"Sports & Exercise",
            "subcategory":"Golf",
            "type":"Entertainment"
        }
    ],
    "sg:phone":"+44 1620 823627",
    "sg:postcode":"EH41 4PT",
    "sg:province":"East Lothian",
    "sg:tags":[
        "club",
        "course"
    ],
    "wof:name":"Haddington Golf Club",
    "wof:placetype":"venue"
},
  "geometry": {"coordinates":[-2.795572,55.953857],"type":"Point"}
}