{
  "type": "Feature",
  "properties": {
    "iso:country":"GB",
    "sg:address":"55 Cardiff Rd",
    "sg:city":"Cardiff",
    "sg:classifiers":[
        {
            "category":"Personal",
            "subcategory":"Beauty Salon",
            "type":"Services"
        }
    ],
    "sg:phone":"+44 29 2081 0424",
    "sg:postcode":"CF4 7RD",
    "sg:province":"Cardiff",
    "sg:tags":[
        "unisex",
        "hairdresser"
    ],
    "wof:name":"Headlines",
    "wof:placetype":"venue"
},
  "geometry": {"coordinates":[-3.267462,51.542465],"type":"Point"}
}