{
  "type": "Feature",
  "properties": {
    "iso:country":"GB",
    "sg:address":"Low Bracken Hill Farm, Bradley Road, Silsden",
    "sg:city":"Keighley",
    "sg:classifiers":[
        {
            "category":"Farming",
            "subcategory":"Livestock Farm",
            "type":"Manufacturing & Wholesale Goods"
        }
    ],
    "sg:phone":"+44 1535 652001",
    "sg:postcode":"BD20 9JN",
    "sg:province":"North Yorkshire",
    "sg:tags":[
        "others"
    ],
    "wof:name":"F & M Desort",
    "wof:placetype":"venue"
},
  "geometry": {"coordinates":[-1.99788,53.931355],"type":"Point"}
}