{
  "type": "Feature",
  "properties": {
    "addr:full":"New Farm, Coach Lane Sandown Isle of Wight PO36 0JG",
    "addr:postcode":"po36 0jg",
    "addr:street":"Coach Lane",
    "iso:country":"GB",
    "sg:address":"New Farm, Coach Lane",
    "sg:city":"Sandown",
    "sg:classifiers":[
        {
            "category":"Manufacturing",
            "subcategory":"Metals",
            "type":"Manufacturing & Wholesale Goods"
        }
    ],
    "sg:postcode":"PO36 0JG",
    "sg:province":"Isle of Wight",
    "wof:name":"I E P  Ltd.",
    "wof:placetype":"venue"
},
  "geometry": {"coordinates":[-1.1501640081,50.6560134888],"type":"Point"}
}