{
  "type": "Feature",
  "properties": {
    "iso:country":"GB",
    "sg:address":"14 Cranberry Clo",
    "sg:city":"St Helens",
    "sg:classifiers":[
        {
            "category":"Professional",
            "subcategory":"Engineering",
            "type":"Services"
        }
    ],
    "sg:phone":"+44 1744 22874",
    "sg:postcode":"WA10 2ND",
    "sg:province":"Merseyside",
    "sg:tags":[
        "contractor",
        "electrical",
        "engineer"
    ],
    "wof:name":"A & A Electrical",
    "wof:placetype":"venue"
},
  "geometry": {"coordinates":[-2.743727,53.458733],"type":"Point"}
}