{
  "type": "Feature",
  "properties": {
    "addr:full":"1 Spring Gardens, Station Road Dorking Surrey RH4 1EE",
    "addr:housenumber":"1",
    "addr:postcode":"rh4 1ee",
    "addr:street":"Spring Gardens Station Road",
    "iso:country":"GB",
    "sg:address":"1 Spring Gardens, Station Road",
    "sg:city":"Dorking",
    "sg:classifiers":[
        {
            "category":"Health Services",
            "subcategory":"Podiatrist",
            "type":"Services"
        }
    ],
    "sg:phone":"+44 1306 742900",
    "sg:postcode":"RH4 1EE",
    "sg:province":"Surrey",
    "sg:tags":[
        "podiatrists",
        "chiropodist"
    ],
    "wof:name":"F S & M Hill Chiropodists",
    "wof:placetype":"venue"
},
  "geometry": {"coordinates":[-0.3371840119,51.2323989868],"type":"Point"}
}