{
  "type": "Feature",
  "properties": {
    "iso:country":"GB",
    "sg:address":"St Saviours Hill, Polruan",
    "sg:city":"Fowey",
    "sg:classifiers":[
        {
            "category":"Education",
            "subcategory":"School",
            "type":"Public Place"
        }
    ],
    "sg:phone":"+44 1726 870402",
    "sg:postcode":"PL23 1PS",
    "sg:province":"Cornwall",
    "sg:tags":[
        "local",
        "authority"
    ],
    "wof:name":"Polruan Junior & Infants School",
    "wof:placetype":"venue"
},
  "geometry": {"coordinates":[-4.634682,50.327038],"type":"Point"}
}