{
  "type": "Feature",
  "properties": {
    "iso:country":"GB",
    "sg:address":"57a High Street, Guilden Morden",
    "sg:city":"Royston",
    "sg:classifiers":[
        {
            "category":"Banks & Credit Unions",
            "subcategory":"Financial Services",
            "type":"Services"
        }
    ],
    "sg:phone":"+44 1763 853400",
    "sg:postcode":"SG8 0JR",
    "sg:province":"Bedfordshire",
    "sg:tags":[
        "adviser"
    ],
    "wof:name":"The Maltings Partnership Ltd.",
    "wof:placetype":"venue"
},
  "geometry": {"coordinates":[-0.135989,52.075558],"type":"Point"}
}