{
  "type": "Feature",
  "properties": {
    "iso:country":"GB",
    "sg:address":"1 Cheam Rd",
    "sg:city":"Epsom",
    "sg:classifiers":[
        {
            "category":"Communications",
            "type":"Services"
        }
    ],
    "sg:phone":"+44 20 8224 2323",
    "sg:postcode":"KT17 1QL",
    "sg:province":"Surrey",
    "sg:tags":[
        "telecommunication"
    ],
    "wof:name":"Wellcomm",
    "wof:placetype":"venue"
},
  "geometry": {"coordinates":[-0.2444449961,51.3468666077],"type":"Point"}
}