{
  "type": "Feature",
  "properties": {
    "addr:full":"Unit 10 Cwntawe Business Park Swansea Neath Port Talbot SA8 4EZ",
    "addr:housenumber":"unit 10",
    "addr:postcode":"sa8 4ez",
    "addr:street":"Cwntawe Business Park",
    "iso:country":"GB",
    "sg:address":"Unit 10 Cwntawe Business Park",
    "sg:city":"Swansea",
    "sg:classifiers":[
        {
            "category":"Home & Garden",
            "subcategory":"Household Appliances",
            "type":"Retail Goods"
        }
    ],
    "sg:phone":"+44 1792 863380",
    "sg:postcode":"SA8 4EZ",
    "sg:province":"Neath Port Talbot",
    "sg:tags":[
        "refrigeration",
        "air conditioning"
    ],
    "wof:name":"A & A Services (Wales) Ltd",
    "wof:placetype":"venue"
},
  "geometry": {"coordinates":[-3.846143961,51.7211303711],"type":"Point"}
}