{
  "type": "Feature",
  "properties": {
    "iso:country":"GB",
    "sg:address":"37-41 Railway Street",
    "sg:city":"Chatham",
    "sg:classifiers":[
        {
            "category":"Professional",
            "subcategory":"Lawyer & Legal Services",
            "type":"Services"
        }
    ],
    "sg:phone":"+44 1634 811444",
    "sg:postcode":"ME4 4RP",
    "sg:province":"Kent",
    "sg:tags":[
        "solicitor"
    ],
    "wof:name":"Stephens & Son",
    "wof:placetype":"venue"
},
  "geometry": {"coordinates":[0.52257,51.38176],"type":"Point"}
}