{
  "type": "Feature",
  "properties": {
    "addr:full":"The Pavillion, Manchester Old Road, Middleton Manchester Greater Manchester M24 4DY",
    "addr:postcode":"m24 4dy",
    "addr:street":"Manchester Old Road",
    "iso:country":"GB",
    "sg:address":"The Pavillion, Manchester Old Road, Middleton",
    "sg:city":"Manchester",
    "sg:classifiers":[
        {
            "category":"Government",
            "subcategory":"City Hall",
            "type":"Public Place"
        }
    ],
    "sg:phone":"+44 161 643 2951",
    "sg:postcode":"M24 4DY",
    "sg:province":"Greater Manchester",
    "wof:name":"Middleton Masonic Club Ltd.",
    "wof:placetype":"venue"
},
  "geometry": {"coordinates":[-2.209112,53.545929],"type":"Point"}
}