{
  "type": "Feature",
  "properties": {
    "iso:country":"GB",
    "sg:address":"Common Farm, West Hill, Aspley Guise",
    "sg:city":"Milton Keynes",
    "sg:classifiers":[
        {
            "category":"Farming",
            "subcategory":"Crops",
            "type":"Manufacturing & Wholesale Goods"
        },
        {
            "category":"Farming",
            "subcategory":"Farm",
            "type":"Manufacturing & Wholesale Goods"
        }
    ],
    "sg:phone":"+44 1908 583333",
    "sg:postcode":"MK17 8DX",
    "sg:province":"Bedfordshire",
    "sg:tags":[
        "mixed",
        "arable"
    ],
    "wof:name":"H D Kilpin",
    "wof:placetype":"venue"
},
  "geometry": {"coordinates":[-0.6454610229,52.0093955994],"type":"Point"}
}