{
  "type": "Feature",
  "properties": {
    "iso:country":"GB",
    "sg:address":"39 Upper High St",
    "sg:city":"Wednesbury",
    "sg:classifiers":[
        {
            "category":"Shopping",
            "subcategory":"Music",
            "type":"Retail Goods"
        }
    ],
    "sg:phone":"+44 121 505 3608",
    "sg:postcode":"WS10 7HJ",
    "sg:province":"West Midlands",
    "sg:tags":[
        "record",
        "tape",
        "cd"
    ],
    "wof:name":"Back To Basics",
    "wof:placetype":"venue"
},
  "geometry": {"coordinates":[-2.0202639103,52.5534477234],"type":"Point"}
}