{
  "type": "Feature",
  "properties": {
    "iso:country":"GB",
    "sg:address":"27 Alexandra Road, Waterloo",
    "sg:city":"Liverpool",
    "sg:classifiers":[
        {
            "category":"Health Services",
            "subcategory":"Nursing And Care Facility",
            "type":"Services"
        }
    ],
    "sg:postcode":"L22 1RJ",
    "sg:province":"Merseyside",
    "sg:tags":[
        "home"
    ],
    "wof:name":"Gorsefield Rest Home",
    "wof:placetype":"venue"
},
  "geometry": {"coordinates":[-3.0217480659,53.4720497131],"type":"Point"}
}