{
  "type": "Feature",
  "properties": {
    "addr:full":"2 Finch Road Liverpool Merseyside L14 4AT",
    "addr:housenumber":"2",
    "addr:postcode":"l14 4at",
    "addr:street":"Finch Road",
    "iso:country":"GB",
    "sg:address":"2 Finch Road",
    "sg:city":"Liverpool",
    "sg:classifiers":[
        {
            "category":"Professional",
            "subcategory":"Management & Consulting",
            "type":"Services"
        },
        {
            "category":"Government",
            "subcategory":"Office",
            "type":"Public Place"
        }
    ],
    "sg:postcode":"L14 4AT",
    "sg:province":"Merseyside",
    "sg:tags":[
        "project",
        "gov",
        "community"
    ],
    "wof:name":"East Liverpool Economic & Community Trust Ltd.",
    "wof:placetype":"venue"
},
  "geometry": {"coordinates":[-2.872654,53.428669],"type":"Point"}
}