{
  "type": "Feature",
  "properties": {
    "iso:country":"GB",
    "sg:address":"109 High Street, Gorleston",
    "sg:city":"Great Yarmouth",
    "sg:classifiers":[
        {
            "category":"Shopping",
            "subcategory":"Discount & Variety Stores",
            "type":"Retail Goods"
        }
    ],
    "sg:phone":"+44 1493 664815",
    "sg:postcode":"NR31 6RE",
    "sg:province":"Norfolk",
    "sg:tags":[
        "shop",
        "model"
    ],
    "wof:name":"Anglia Model Centre",
    "wof:placetype":"venue"
},
  "geometry": {"coordinates":[1.728035,52.578968],"type":"Point"}
}