{
  "type": "Feature",
  "properties": {
    "addr:full":"29 Russet Way Hockley Essex SS5 5PJ",
    "addr:housenumber":"29",
    "addr:postcode":"ss5 5pj",
    "addr:street":"Russet Way Hockley",
    "iso:country":"GB",
    "sg:address":"29 Russet Way",
    "sg:city":"Hockley",
    "sg:classifiers":[
        {
            "category":"Retail",
            "subcategory":"Driving School",
            "type":"Services"
        }
    ],
    "sg:postcode":"SS5 5PJ",
    "sg:province":"Essex",
    "wof:name":"Alf Millard",
    "wof:placetype":"venue"
},
  "geometry": {"coordinates":[0.6635230184,51.6104850769],"type":"Point"}
}