{
  "type": "Feature",
  "properties": {
    "addr:full":"52 The Avenue Poole Dorset BH13 6LL",
    "addr:housenumber":"52",
    "addr:postcode":"bh13 6ll",
    "addr:street":"The Avenue",
    "iso:country":"GB",
    "sg:address":"52 The Avenue",
    "sg:city":"Poole",
    "sg:classifiers":[
        {
            "category":"Building & Trades",
            "subcategory":"Construction",
            "type":"Services"
        }
    ],
    "sg:phone":"+44 1202 764200",
    "sg:postcode":"BH13 6LL",
    "sg:province":"Dorset",
    "sg:tags":[
        "builder"
    ],
    "wof:name":"Park Builders",
    "wof:placetype":"venue"
},
  "geometry": {"coordinates":[-1.9096859694,50.7108535767],"type":"Point"}
}