{
  "type": "Feature",
  "properties": {
    "addr:full":"Artificial Limb & Appliance Centre, Raigmore Hospital Inverness Highland IV2 3UJ",
    "addr:postcode":"iv2 3uj",
    "iso:country":"GB",
    "sg:address":"Artificial Limb & Appliance Centre, Raigmore Hospital",
    "sg:city":"Inverness",
    "sg:classifiers":[
        {
            "category":"Social Services",
            "type":"Services"
        }
    ],
    "sg:phone":"+44 1463 710791",
    "sg:postcode":"IV2 3UJ",
    "sg:province":"Highland",
    "sg:tags":[
        "need",
        "disability",
        "special"
    ],
    "wof:name":"Steeper,Hugh,Ltd",
    "wof:placetype":"venue"
},
  "geometry": {"coordinates":[-4.1925,57.4739],"type":"Point"}
}