{
  "type": "Feature",
  "properties": {
    "addr:full":"202 Bolton Street, Ramsbottom Bury Lancashire BL0 9JE",
    "addr:housenumber":"202",
    "addr:postcode":"bl0 9je",
    "addr:street":"Bolton Street",
    "iso:country":"GB",
    "sg:address":"202 Bolton Street, Ramsbottom",
    "sg:city":"Bury",
    "sg:classifiers":[
        {
            "category":"Fast Food",
            "type":"Food & Drink"
        }
    ],
    "sg:phone":"+44 1706 826689",
    "sg:postcode":"BL0 9JE",
    "sg:province":"Lancashire",
    "sg:tags":[
        "away",
        "take"
    ],
    "wof:name":"Lucky Star",
    "wof:placetype":"venue"
},
  "geometry": {"coordinates":[-2.322133,53.643288],"type":"Point"}
}