{
  "type": "Feature",
  "properties": {
    "iso:country":"GB",
    "sg:address":"38 Church Rd",
    "sg:city":"Burgess Hill",
    "sg:classifiers":[
        {
            "category":"Organizations",
            "subcategory":"Non-profit Organization",
            "type":"Services"
        }
    ],
    "sg:phone":"+44 1444 250990",
    "sg:postcode":"RH15 9AE",
    "sg:province":"East Sussex",
    "sg:tags":[
        "organisation",
        "voluntary",
        "charity"
    ],
    "wof:name":"Dial Mid Sussex",
    "wof:placetype":"venue"
},
  "geometry": {"coordinates":[-0.129801,50.955395],"type":"Point"}
}