{
  "type": "Feature",
  "properties": {
    "iso:country":"GB",
    "sg:address":"19 High Street",
    "sg:city":"Oakham",
    "sg:classifiers":[
        {
            "category":"Professional",
            "subcategory":"Art Services",
            "type":"Services"
        }
    ],
    "sg:postcode":"LE15 6AH",
    "sg:province":"Leicestershire",
    "sg:tags":[
        "decorating",
        "painting"
    ],
    "wof:name":"Grimmer & Sons",
    "wof:placetype":"venue"
},
  "geometry": {"coordinates":[-0.72818,52.669739],"type":"Point"}
}