{
  "type": "Feature",
  "properties": {
    "iso:country":"GB",
    "sg:address":"120a Frimley Rd",
    "sg:city":"Camberley",
    "sg:classifiers":[
        {
            "category":"Home & Garden",
            "subcategory":"Garden Supply",
            "type":"Retail Goods"
        }
    ],
    "sg:phone":"+44 1276 686992",
    "sg:postcode":"GU15 2QN",
    "sg:province":"Berkshire",
    "sg:tags":[
        "nursery",
        "centre"
    ],
    "wof:name":"Arnott & Mason (Horticultural) Ltd",
    "wof:placetype":"venue"
},
  "geometry": {"coordinates":[-0.755252,51.327347],"type":"Point"}
}