{
  "type": "Feature",
  "properties": {
    "addr:full":"Babbacombe Ho, 2 Babbacombe Rd Bromley Kent BR1 3LW",
    "addr:housenumber":"2",
    "addr:postcode":"br1 3lw",
    "addr:street":"Babbacombe Rd",
    "iso:country":"GB",
    "sg:address":"Babbacombe Ho, 2 Babbacombe Rd",
    "sg:city":"Bromley",
    "sg:classifiers":[
        {
            "category":"Professional",
            "subcategory":"Lawyer & Legal Services",
            "type":"Services"
        }
    ],
    "sg:phone":"+44 20 8464 0249",
    "sg:postcode":"BR1 3LW",
    "sg:province":"Kent",
    "sg:tags":[
        "advice",
        "counselling"
    ],
    "wof:name":"Bromley Community Health Council",
    "wof:placetype":"venue"
},
  "geometry": {"coordinates":[0.014928,51.4057006836],"type":"Point"}
}