{
  "type": "Feature",
  "properties": {
    "iso:country":"GB",
    "sg:address":"Compton House, Harrier Wy, Sowton Industrial Estate",
    "sg:city":"Exeter",
    "sg:classifiers":[
        {
            "category":"Professional",
            "subcategory":"Engineering",
            "type":"Services"
        }
    ],
    "sg:phone":"+44 1392 440000",
    "sg:postcode":"EX2 7HU",
    "sg:province":"Devon",
    "sg:tags":[
        "design",
        "engineer"
    ],
    "wof:name":"Bgp-Reid Crowther Ltd.",
    "wof:placetype":"venue"
},
  "geometry": {"coordinates":[-3.4689540863,50.7161903381],"type":"Point"}
}