{
  "type": "Feature",
  "properties": {
    "iso:country":"GB",
    "sg:address":"The Studio",
    "sg:city":"Grimsby",
    "sg:classifiers":[
        {
            "category":"Communications",
            "subcategory":"Film & Video Production",
            "type":"Services"
        }
    ],
    "sg:postcode":"DN32 0RA",
    "sg:province":"Lincolnshire",
    "sg:tags":[
        "illustrator",
        "artist"
    ],
    "wof:name":"J F Parr",
    "wof:placetype":"venue"
},
  "geometry": {"coordinates":[-0.0870900005,53.5624694824],"type":"Point"}
}