{
  "type": "Feature",
  "properties": {
    "iso:country":"GB",
    "sg:address":"11 Horncastle Road",
    "sg:city":"Boston",
    "sg:classifiers":[
        {
            "category":"Shopping",
            "subcategory":"Bicycles & Sporting Goods",
            "type":"Retail Goods"
        },
        {
            "category":"Recreation",
            "subcategory":"Fishing",
            "type":"Entertainment"
        }
    ],
    "sg:phone":"+44 1205 353436",
    "sg:postcode":"PE21 9BN",
    "sg:province":"Lincolnshire",
    "sg:tags":[
        "equipment",
        "angling"
    ],
    "wof:name":"Boston Angling Centre",
    "wof:placetype":"venue"
},
  "geometry": {"coordinates":[-0.01876,52.982834],"type":"Point"}
}