{
  "type": "Feature",
  "properties": {
    "addr:full":"Penyparc, Llandefalle Brecon Powys LD3 0UN",
    "addr:postcode":"ld3 0un",
    "iso:country":"GB",
    "sg:address":"Penyparc, Llandefalle",
    "sg:city":"Brecon",
    "sg:classifiers":[
        {
            "category":"Banks & Credit Unions",
            "subcategory":"Financial Services",
            "type":"Services"
        }
    ],
    "sg:phone":"+44 1874 754507",
    "sg:postcode":"LD3 0UN",
    "sg:province":"Powys",
    "sg:tags":[
        "adviser"
    ],
    "wof:name":"Morgan Financial",
    "wof:placetype":"venue"
},
  "geometry": {"coordinates":[-3.2884030342,52.0112228394],"type":"Point"}
}