{
  "type": "Feature",
  "properties": {
    "iso:country":"GB",
    "sg:address":"15 Bridge Street",
    "sg:city":"Todmorden",
    "sg:classifiers":[
        {
            "category":"Shopping",
            "subcategory":"News",
            "type":"Retail Goods"
        }
    ],
    "sg:phone":"+44 1706 819889",
    "sg:postcode":"OL14 5AQ",
    "sg:province":"Lancashire",
    "sg:tags":[
        "newsagent"
    ],
    "wof:name":"Cryers Newscentre",
    "wof:placetype":"venue"
},
  "geometry": {"coordinates":[-2.097209,53.714096],"type":"Point"}
}