{
  "type": "Feature",
  "properties": {
    "iso:country":"GB",
    "sg:address":"2 New Street, Castle Bromwich",
    "sg:city":"Birmingham",
    "sg:classifiers":[
        {
            "category":"Communications",
            "subcategory":"Newspaper",
            "type":"Services"
        }
    ],
    "sg:phone":"+44 121 749 3400",
    "sg:postcode":"B36 9AP",
    "sg:province":"West Midlands",
    "sg:tags":[
        "magazine"
    ],
    "wof:name":"Midland Vision",
    "wof:placetype":"venue"
},
  "geometry": {"coordinates":[-1.782453,52.504776],"type":"Point"}
}