{
  "type": "Feature",
  "properties": {
    "addr:full":"130 High Street Uckfield East Sussex TN22 1QR",
    "addr:housenumber":"130",
    "addr:postcode":"tn22 1qr",
    "addr:street":"High Street",
    "iso:country":"GB",
    "sg:address":"130 High Street",
    "sg:city":"Uckfield",
    "sg:classifiers":[
        {
            "category":"Communications",
            "subcategory":"Newspaper",
            "type":"Services"
        }
    ],
    "sg:phone":"+44 870 162 9999",
    "sg:postcode":"TN22 1QR",
    "sg:province":"East Sussex",
    "sg:tags":[
        "magazine"
    ],
    "wof:name":"Friday-Ad Print Ltd.",
    "wof:placetype":"venue"
},
  "geometry": {"coordinates":[0.0964950025,50.9707374573],"type":"Point"}
}