{
  "type": "Feature",
  "properties": {
    "addr:full":"Office 18 Le Claire Enterprise, Centre Reading Berkshire RG7 5DP",
    "addr:housenumber":"18",
    "addr:postcode":"rg7 5dp",
    "iso:country":"GB",
    "sg:address":"Office 18 Le Claire Enterprise, Centre",
    "sg:city":"Reading",
    "sg:classifiers":[
        {
            "category":"Banks & Credit Unions",
            "subcategory":"Financial Services",
            "type":"Services"
        }
    ],
    "sg:postcode":"RG7 5DP",
    "sg:province":"Berkshire",
    "sg:tags":[
        "adviser"
    ],
    "wof:name":"Theale Financial Services",
    "wof:placetype":"venue"
},
  "geometry": {"coordinates":[-1.0861,51.434719],"type":"Point"}
}