{
  "type": "Feature",
  "properties": {
    "iso:country":"GB",
    "sg:address":"40 Great Charles Street, Queensway",
    "sg:city":"Birmingham",
    "sg:classifiers":[
        {
            "category":"Real Estate",
            "subcategory":"Real Estate Agent",
            "type":"Services"
        }
    ],
    "sg:phone":"+44 121 214 8900",
    "sg:postcode":"B3 2LX",
    "sg:province":"West Midlands",
    "wof:name":"P & O Properties Ltd.",
    "wof:placetype":"venue"
},
  "geometry": {"coordinates":[-1.9032440186,52.4822692871],"type":"Point"}
}