{
  "type": "Feature",
  "properties": {
    "addr:full":"23 St Georges Rd Enfield Greater London EN1 4TY",
    "addr:housenumber":"23",
    "addr:postcode":"en1 4ty",
    "addr:street":"St Georges Rd",
    "iso:country":"GB",
    "sg:address":"23 St Georges Rd",
    "sg:city":"Enfield",
    "sg:classifiers":[
        {
            "category":"Retail",
            "subcategory":"Auto Repair",
            "type":"Services"
        }
    ],
    "sg:phone":"+44 20 8367 5077",
    "sg:postcode":"EN1 4TY",
    "sg:province":"Greater London",
    "sg:tags":[
        "modification",
        "garage"
    ],
    "wof:name":"All Round Runabouts",
    "wof:placetype":"venue"
},
  "geometry": {"coordinates":[-0.0680669993,51.6666641235],"type":"Point"}
}