{
  "type": "Feature",
  "properties": {
    "addr:full":"51 Lexington Street London Greater London W1F 9AR",
    "addr:housenumber":"51",
    "addr:postcode":"w1f 9ar",
    "addr:street":"Lexington Street",
    "iso:country":"GB",
    "sg:address":"51 Lexington Street",
    "sg:city":"London",
    "sg:classifiers":[
        {
            "category":"Building & Trades",
            "subcategory":"Construction",
            "type":"Services"
        }
    ],
    "sg:phone":"+44 20 7437 1862",
    "sg:postcode":"W1F 9AR",
    "sg:province":"Greater London",
    "sg:tags":[
        "worker",
        "metal"
    ],
    "wof:name":"Bela Pasztor Art Metalwork",
    "wof:placetype":"venue"
},
  "geometry": {"coordinates":[-0.136624,51.513203],"type":"Point"}
}