{
  "type": "Feature",
  "properties": {
    "iso:country":"GB",
    "sg:address":"429a Herries Road",
    "sg:city":"Sheffield",
    "sg:classifiers":[
        {
            "category":"Personal",
            "subcategory":"Beauty Salon",
            "type":"Services"
        },
        {
            "category":"Personal",
            "subcategory":"Barber",
            "type":"Services"
        }
    ],
    "sg:phone":"+44 114 242 6171",
    "sg:postcode":"S5 7HF",
    "sg:province":"South Yorkshire",
    "sg:tags":[
        "unisex",
        "lady",
        "hairdresser"
    ],
    "wof:name":"Herries Hair Salon",
    "wof:placetype":"venue"
},
  "geometry": {"coordinates":[-1.473065,53.412975],"type":"Point"}
}