{
  "type": "Feature",
  "properties": {
    "addr:full":"Eden Park, East Rd Cupar Fife KY15 4RA",
    "addr:postcode":"ky15 4ra",
    "addr:street":"Eden;East Rd",
    "iso:country":"GB",
    "sg:address":"Eden Park, East Rd",
    "sg:city":"Cupar",
    "sg:classifiers":[
        {
            "category":"Community Center",
            "type":"Public Place"
        }
    ],
    "sg:phone":"+44 1334 654968",
    "sg:postcode":"KY15 4RA",
    "sg:province":"Fife",
    "sg:tags":[
        "recreation",
        "leisure",
        "centre"
    ],
    "wof:name":"Eden Park Leisure Centre",
    "wof:placetype":"venue"
},
  "geometry": {"coordinates":[-3.0117590427,56.3194961548],"type":"Point"}
}