{
  "type": "Feature",
  "properties": {
    "iso:country":"GB",
    "sg:address":"16 Colonels Wk",
    "sg:city":"Goole",
    "sg:classifiers":[
        {
            "category":"Food & Beverages",
            "subcategory":"Liquor & Beverages",
            "type":"Retail Goods"
        }
    ],
    "sg:phone":"+44 1405 764104",
    "sg:postcode":"DN14 6HJ",
    "sg:province":"East Riding of Yorkshire",
    "sg:tags":[
        "beer",
        "spirit",
        "wines"
    ],
    "wof:name":"Cash Stores",
    "wof:placetype":"venue"
},
  "geometry": {"coordinates":[-0.8715270162,53.7097053528],"type":"Point"}
}