{
  "type": "Feature",
  "properties": {
    "addr:full":"347 Preston Old Road Blackburn Lancashire BB2 5LJ",
    "addr:housenumber":"347",
    "addr:postcode":"bb2 5lj",
    "addr:street":"Preston Old Road",
    "iso:country":"GB",
    "sg:address":"347 Preston Old Road",
    "sg:city":"Blackburn",
    "sg:classifiers":[
        {
            "category":"Personal",
            "subcategory":"Beauty Salon",
            "type":"Services"
        }
    ],
    "sg:postcode":"BB2 5LJ",
    "sg:province":"Lancashire",
    "sg:tags":[
        "unisex",
        "hairdresser"
    ],
    "wof:name":"Crimpers Hair Design",
    "wof:placetype":"venue"
},
  "geometry": {"coordinates":[-2.5178480148,53.7349433899],"type":"Point"}
}