{
  "type": "Feature",
  "properties": {
    "addr:full":"50 Wilmington Close, Woodley Reading Berkshire RG5 4LR",
    "addr:housenumber":"50",
    "addr:postcode":"rg5 4lr",
    "addr:street":"Wilmington Close",
    "iso:country":"GB",
    "sg:address":"50 Wilmington Close, Woodley",
    "sg:city":"Reading",
    "sg:classifiers":[
        {
            "category":"Home & Garden",
            "subcategory":"Household Appliances",
            "type":"Retail Goods"
        },
        {
            "category":"Retail",
            "subcategory":"Repair Shop",
            "type":"Services"
        }
    ],
    "sg:phone":"+44 118 969 3863",
    "sg:postcode":"RG5 4LR",
    "sg:province":"Berkshire",
    "sg:tags":[
        "machine",
        "electrical",
        "washing"
    ],
    "wof:name":"Champion Domestic Services",
    "wof:placetype":"venue"
},
  "geometry": {"coordinates":[-0.898266,51.455757],"type":"Point"}
}