{
  "type": "Feature",
  "properties": {
    "iso:country":"GB",
    "sg:address":"5 Low Ousegate",
    "sg:city":"York",
    "sg:classifiers":[
        {
            "category":"Retail",
            "subcategory":"Laundry & Dry Cleaning",
            "type":"Services"
        }
    ],
    "sg:phone":"+44 1904 620252",
    "sg:postcode":"YO1 9QX",
    "sg:province":"North Yorkshire",
    "sg:tags":[
        "cleaner",
        "alteration"
    ],
    "wof:name":"Johnsons The Cleaners",
    "wof:placetype":"venue"
},
  "geometry": {"coordinates":[-1.083852,53.957336],"type":"Point"}
}