{
  "type": "Feature",
  "properties": {
    "addr:full":"Health Centre Burvill Street Lynton Devon EX35 6HA",
    "addr:postcode":"ex35 6ha",
    "addr:street":"Burvill Street",
    "iso:country":"GB",
    "sg:address":"Health Centre Burvill Street",
    "sg:city":"Lynton",
    "sg:classifiers":[
        {
            "category":"Health Services",
            "subcategory":"Doctor",
            "type":"Services"
        }
    ],
    "sg:phone":"+44 1598 753226",
    "sg:postcode":"EX35 6HA",
    "sg:province":"Devon",
    "sg:tags":[
        "practitioners"
    ],
    "wof:name":"R G Ferrar",
    "wof:placetype":"venue"
},
  "geometry": {"coordinates":[-3.8326990604,51.2261428833],"type":"Point"}
}