{
  "type": "Feature",
  "properties": {
    "addr:full":"Frongoch, Llanrhaeadr Ym Mochnant Oswestry Shropshire SY10 0BE",
    "addr:postcode":"sy10 0be",
    "iso:country":"GB",
    "sg:address":"Frongoch, Llanrhaeadr Ym Mochnant",
    "sg:city":"Oswestry",
    "sg:classifiers":[
        {
            "category":"Farming",
            "subcategory":"Livestock Farm",
            "type":"Manufacturing & Wholesale Goods"
        }
    ],
    "sg:phone":"+44 1691 780274",
    "sg:postcode":"SY10 0BE",
    "sg:province":"Shropshire",
    "sg:tags":[
        "others"
    ],
    "wof:name":"T E & G O Evans",
    "wof:placetype":"venue"
},
  "geometry": {"coordinates":[-3.3001699448,52.8196487427],"type":"Point"}
}