{
  "type": "Feature",
  "properties": {
    "iso:country":"GB",
    "sg:address":"31-39 Perry Vale",
    "sg:city":"London",
    "sg:classifiers":[
        {
            "category":"Professional",
            "subcategory":"Business Services",
            "type":"Services"
        }
    ],
    "sg:postcode":"SE23 2NE",
    "sg:province":"Greater London",
    "sg:tags":[
        "import",
        "export",
        "agent"
    ],
    "wof:name":"Forest Hill Gas Centre",
    "wof:placetype":"venue"
},
  "geometry": {"coordinates":[-0.052603,51.439056],"type":"Point"}
}