{
  "type": "Feature",
  "properties": {
    "addr:full":"Treetops, 5a Great Hinton Trowbridge Wiltshire BA14 6DA",
    "addr:housenumber":"5a",
    "addr:postcode":"ba14 6da",
    "addr:street":"Great",
    "iso:country":"GB",
    "sg:address":"Treetops, 5a Great Hinton",
    "sg:city":"Trowbridge",
    "sg:classifiers":[
        {
            "category":"Building & Trades",
            "subcategory":"Landscaping Services",
            "type":"Services"
        },
        {
            "category":"Freight",
            "type":"Transportation"
        }
    ],
    "sg:phone":"+44 1380 870412",
    "sg:postcode":"BA14 6DA",
    "sg:province":"Wiltshire",
    "sg:tags":[
        "haulage",
        "gardening",
        "road",
        "transport"
    ],
    "wof:name":"P D Noad & Co. (Agricultural Services) Ltd.",
    "wof:placetype":"venue"
},
  "geometry": {"coordinates":[-2.208374,51.315342],"type":"Point"}
}