{
  "type": "Feature",
  "properties": {
    "addr:full":"Washington Street Bury Lancashire BL9 5BZ",
    "addr:postcode":"bl9 5bz",
    "addr:street":"Washington Street",
    "iso:country":"GB",
    "sg:address":"Washington Street",
    "sg:city":"Bury",
    "sg:classifiers":[
        {
            "category":"Autos & Motor Vehicles",
            "subcategory":"Automobile Sales",
            "type":"Retail Goods"
        }
    ],
    "sg:phone":"+44 161 764 9969",
    "sg:postcode":"BL9 5BZ",
    "sg:province":"Lancashire",
    "sg:tags":[
        "commercial"
    ],
    "wof:name":"R S Commercials",
    "wof:placetype":"venue"
},
  "geometry": {"coordinates":[-2.3010540009,53.5897331238],"type":"Point"}
}