{
  "type": "Feature",
  "properties": {
    "addr:full":"Cross Lane, Dunston Gateshead Tyne and Wear NE11 9HQ",
    "addr:postcode":"ne11 9hq",
    "addr:street":"Cross Lane",
    "iso:country":"GB",
    "sg:address":"Cross Lane, Dunston",
    "sg:city":"Gateshead",
    "sg:classifiers":[
        {
            "category":"Manufacturing",
            "subcategory":"Chemicals & Compounds",
            "type":"Manufacturing & Wholesale Goods"
        }
    ],
    "sg:phone":"+44 191 493 2525",
    "sg:postcode":"NE11 9HQ",
    "sg:province":"Tyne and Wear",
    "sg:tags":[
        "pesticide"
    ],
    "wof:name":"Resinous Chemicals Ltd.",
    "wof:placetype":"venue"
},
  "geometry": {"coordinates":[-1.6488989592,54.9527626038],"type":"Point"}
}