{
  "type": "Feature",
  "properties": {
    "iso:country":"GB",
    "sg:address":"Adastral Road",
    "sg:city":"Poole",
    "sg:classifiers":[
        {
            "category":"Community Center",
            "type":"Public Place"
        }
    ],
    "sg:phone":"+44 1202 604224",
    "sg:postcode":"BH17 7PY",
    "sg:province":"Dorset",
    "sg:tags":[
        "recreation",
        "leisure",
        "centre"
    ],
    "wof:name":"Ashdown Leisure Centre",
    "wof:placetype":"venue"
},
  "geometry": {"coordinates":[-1.967669,50.741268],"type":"Point"}
}