{
  "type": "Feature",
  "properties": {
    "iso:country":"GB",
    "sg:address":"1c Talbot Road, Leyland",
    "sg:city":"Preston",
    "sg:classifiers":[
        {
            "category":"Professional",
            "subcategory":"Business Services",
            "type":"Services"
        }
    ],
    "sg:phone":"+44 1772 623234",
    "sg:postcode":"PR5 1ZJ",
    "sg:province":"Lancashire",
    "sg:tags":[
        "import",
        "export",
        "agent"
    ],
    "wof:name":"Automotive Export Ltd.",
    "wof:placetype":"venue"
},
  "geometry": {"coordinates":[-2.69349,53.695339],"type":"Point"}
}