{
  "type": "Feature",
  "properties": {
    "addr:full":"Lower Gages Farm, Rusper Road, Capel Dorking Surrey RH5 5HG",
    "addr:postcode":"rh5 5hg",
    "addr:street":"Lower Gages;Rusper Road",
    "iso:country":"GB",
    "sg:address":"Lower Gages Farm, Rusper Road, Capel",
    "sg:city":"Dorking",
    "sg:classifiers":[
        {
            "category":"Farming",
            "subcategory":"Livestock Farm",
            "type":"Manufacturing & Wholesale Goods"
        }
    ],
    "sg:postcode":"RH5 5HG",
    "sg:province":"Surrey",
    "sg:tags":[
        "others"
    ],
    "wof:name":"R & M V Mills",
    "wof:placetype":"venue"
},
  "geometry": {"coordinates":[-0.3231390119,51.1498146057],"type":"Point"}
}