{
  "type": "Feature",
  "properties": {
    "addr:full":"307a Forton Road Gosport Hampshire PO12 3HD",
    "addr:housenumber":"307a",
    "addr:postcode":"po12 3hd",
    "addr:street":"Forton Road",
    "iso:country":"GB",
    "sg:address":"307a Forton Road",
    "sg:city":"Gosport",
    "sg:classifiers":[
        {
            "category":"Shopping",
            "type":"Retail Goods"
        }
    ],
    "sg:phone":"+44 23 9252 9136",
    "sg:postcode":"PO12 3HD",
    "sg:province":"Hampshire",
    "sg:tags":[
        "part",
        "accessory"
    ],
    "wof:name":"Rallie - Round",
    "wof:placetype":"venue"
},
  "geometry": {"coordinates":[-1.14606,50.802902],"type":"Point"}
}