{
  "type": "Feature",
  "properties": {
    "iso:country":"GB",
    "sg:address":"Chislet, Marshside",
    "sg:city":"Canterbury",
    "sg:classifiers":[
        {
            "category":"Bars & Pubs",
            "type":"Food & Drink"
        }
    ],
    "sg:phone":"+44 1227 860206",
    "sg:postcode":"CT3 4EH",
    "sg:province":"Kent",
    "sg:tags":[
        "pubs",
        "inn"
    ],
    "wof:name":"The Hog & Donkey",
    "wof:placetype":"venue"
},
  "geometry": {"coordinates":[1.191424,51.33392],"type":"Point"}
}