{
  "type": "Feature",
  "properties": {
    "addr:full":"Unit 24d North Tyne Indstl Est, Whitley, Benton Newcastle-upon-tyne Tyne and Wear NE12 9SZ",
    "addr:housenumber":"24d",
    "addr:postcode":"ne12 9sz",
    "addr:street":"North Tyne Indstl Est",
    "iso:country":"GB",
    "sg:address":"Unit 24d North Tyne Indstl Est, Whitley, Benton",
    "sg:city":"Newcastle-upon-tyne",
    "sg:classifiers":[
        {
            "category":"Deli",
            "type":"Food & Drink"
        }
    ],
    "sg:postcode":"NE12 9SZ",
    "sg:province":"Tyne and Wear",
    "sg:tags":[
        "delivery",
        "sandwich"
    ],
    "wof:name":"Sparks,Steven,",
    "wof:placetype":"venue"
},
  "geometry": {"coordinates":[-1.52759,55.02713],"type":"Point"}
}