{
  "type": "Feature",
  "properties": {
    "iso:country":"GB",
    "sg:address":"Albany House, North Dock",
    "sg:city":"Llanelli",
    "sg:classifiers":[
        {
            "category":"Wholesale",
            "subcategory":"Chemicals & Plastics",
            "type":"Manufacturing & Wholesale Goods"
        },
        {
            "category":"Military Area",
            "subcategory":"Air Force Base",
            "type":"Public Place"
        }
    ],
    "sg:phone":"+44 1554 775236",
    "sg:postcode":"SA15 2LF",
    "sg:province":"Carmarthenshire",
    "sg:tags":[
        "water",
        "product",
        "allied",
        "treatment"
    ],
    "wof:name":"Albanyoak Ltd.",
    "wof:placetype":"venue"
},
  "geometry": {"coordinates":[-4.144494,51.669701],"type":"Point"}
}