{
  "type": "Feature",
  "properties": {
    "iso:country":"GB",
    "sg:address":"Hunter St",
    "sg:city":"Glasgow",
    "sg:classifiers":[
        {
            "category":"Shopping",
            "subcategory":"Stationery & Office Supplies",
            "type":"Retail Goods"
        }
    ],
    "sg:phone":"+44 1355 579957",
    "sg:postcode":"G74 4LZ",
    "sg:province":"South Lanarkshire",
    "sg:tags":[
        "envelope"
    ],
    "wof:name":"E K P S",
    "wof:placetype":"venue"
},
  "geometry": {"coordinates":[-4.175219,55.765366],"type":"Point"}
}