{
  "type": "Feature",
  "properties": {
    "iso:country":"GB",
    "sg:address":"4 Upperton Road",
    "sg:city":"Leicester",
    "sg:classifiers":[
        {
            "category":"Personal",
            "subcategory":"Tattoo Parlor",
            "type":"Services"
        }
    ],
    "sg:phone":"+44 116 254 1319",
    "sg:postcode":"LE3 0BG",
    "sg:province":"Leicestershire",
    "sg:tags":[
        "tattooing",
        "piercing",
        "artist"
    ],
    "wof:name":"Tattoo City",
    "wof:placetype":"venue"
},
  "geometry": {"coordinates":[-1.147818,52.62571],"type":"Point"}
}