{
  "type": "Feature",
  "properties": {
    "iso:country":"GB",
    "sg:address":"11 The Thoroughfare",
    "sg:city":"Woodbridge",
    "sg:classifiers":[
        {
            "category":"Shopping",
            "subcategory":"Department Store",
            "type":"Retail Goods"
        }
    ],
    "sg:phone":"+44 1394 382445",
    "sg:postcode":"IP12 1AA",
    "sg:province":"Suffolk",
    "sg:tags":[
        "departmental"
    ],
    "wof:name":"Woolworths plc",
    "wof:placetype":"venue"
},
  "geometry": {"coordinates":[1.330007,52.10532],"type":"Point"}
}