{
  "type": "Feature",
  "properties": {
    "addr:full":"Little Barksore Farm, Sheerness Road, Lower Halstow Sittingbourne Kent ME9 7ED",
    "addr:postcode":"me9 7ed",
    "addr:street":"Sheerness Road",
    "iso:country":"GB",
    "sg:address":"Little Barksore Farm, Sheerness Road, Lower Halstow",
    "sg:city":"Sittingbourne",
    "sg:classifiers":[
        {
            "category":"Farming",
            "subcategory":"Livestock Farm",
            "type":"Manufacturing & Wholesale Goods"
        }
    ],
    "sg:phone":"+44 1795 842460",
    "sg:postcode":"ME9 7ED",
    "sg:province":"Kent",
    "sg:tags":[
        "others"
    ],
    "wof:name":"J Goodhew & Sons",
    "wof:placetype":"venue"
},
  "geometry": {"coordinates":[0.6686099768,51.373790741],"type":"Point"}
}