{
  "type": "Feature",
  "properties": {
    "addr:full":"Harland House Woking Surrey GU21 6HW",
    "addr:postcode":"gu21 6hw",
    "iso:country":"GB",
    "sg:address":"Harland House",
    "sg:city":"Woking",
    "sg:classifiers":[
        {
            "category":"Real Estate",
            "subcategory":"Real Estate Agent",
            "type":"Services"
        }
    ],
    "sg:phone":"+44 1483 773773",
    "sg:postcode":"GU21 6HW",
    "sg:province":"Surrey",
    "wof:name":"Waterfall Durrant & Barclay Ltd.",
    "wof:placetype":"venue"
},
  "geometry": {"coordinates":[-0.55855,51.322075],"type":"Point"}
}