{
  "type": "Feature",
  "properties": {
    "iso:country":"GB",
    "sg:address":"33 High Street",
    "sg:city":"Dalbeattie",
    "sg:classifiers":[
        {
            "category":"Professional",
            "subcategory":"Lawyer & Legal Services",
            "type":"Services"
        }
    ],
    "sg:phone":"+44 1556 611247",
    "sg:postcode":"DG5 4AD",
    "sg:province":"Dumfries and Galloway",
    "sg:tags":[
        "solicitor"
    ],
    "sg:website":"http://www.ggblaw.co.uk",
    "wof:name":"Gillespie Gifford & Brown",
    "wof:placetype":"venue"
},
  "geometry": {"coordinates":[-3.821857,54.932796],"type":"Point"}
}