{
  "type": "Feature",
  "properties": {
    "iso:country":"GB",
    "sg:address":"Higher Honey Brook Farm, Cranborne Road, Furzehill",
    "sg:city":"Wimborne",
    "sg:classifiers":[
        {
            "category":"Building & Trades",
            "subcategory":"Landscaping Services",
            "type":"Services"
        }
    ],
    "sg:phone":"+44 1202 885464",
    "sg:postcode":"BH21 4HW",
    "sg:province":"Dorset",
    "sg:tags":[
        "gardening"
    ],
    "wof:name":"Honeybrook Services",
    "wof:placetype":"venue"
},
  "geometry": {"coordinates":[-1.979794,50.818729],"type":"Point"}
}