{
  "type": "Feature",
  "properties": {
    "addr:full":"180 Old Stone Road Stafford Staffordshire ST16 1NT",
    "addr:housenumber":"180",
    "addr:postcode":"st16 1nt",
    "addr:street":"Old Stone Road",
    "iso:country":"GB",
    "sg:address":"180 Old Stone Road",
    "sg:city":"Stafford",
    "sg:classifiers":[
        {
            "category":"Food & Beverages",
            "subcategory":"Bakery",
            "type":"Retail Goods"
        }
    ],
    "sg:postcode":"ST16 1NT",
    "sg:province":"Staffordshire",
    "sg:tags":[
        "baker"
    ],
    "wof:name":"George Low",
    "wof:placetype":"venue"
},
  "geometry": {"coordinates":[-2.126704,52.822147],"type":"Point"}
}