{
  "type": "Feature",
  "properties": {
    "addr:full":"48 Beaumont Street Southport Lancashire PR8 1LY",
    "addr:housenumber":"48",
    "addr:postcode":"pr8 1ly",
    "addr:street":"Beaumont Street",
    "iso:country":"GB",
    "sg:address":"48 Beaumont Street",
    "sg:city":"Southport",
    "sg:classifiers":[
        {
            "category":"Building & Trades",
            "subcategory":"Construction",
            "type":"Services"
        }
    ],
    "sg:phone":"+44 1704 534268",
    "sg:postcode":"PR8 1LY",
    "sg:province":"Lancashire",
    "sg:tags":[
        "roofing"
    ],
    "wof:name":"P & R Roofing Contractors",
    "wof:placetype":"venue"
},
  "geometry": {"coordinates":[-3.0105929375,53.6399650574],"type":"Point"}
}