{
  "type": "Feature",
  "properties": {
    "addr:full":"Flat 3 Harvest Lodge, 53-55 Penton Street London Greater London N1 9PY",
    "addr:housenumber":"53-55",
    "addr:postcode":"n1 9py",
    "addr:street":"Penton Street",
    "iso:country":"GB",
    "sg:address":"Flat 3 Harvest Lodge, 53-55 Penton Street",
    "sg:city":"London",
    "sg:classifiers":[
        {
            "category":"Real Estate",
            "subcategory":"Developer",
            "type":"Services"
        }
    ],
    "sg:postcode":"N1 9PY",
    "sg:province":"Greater London",
    "sg:tags":[
        "property"
    ],
    "wof:name":"Springbay Ltd",
    "wof:placetype":"venue"
},
  "geometry": {"coordinates":[-0.1119299978,51.5336608887],"type":"Point"}
}