{
  "type": "Feature",
  "properties": {
    "addr:full":"177 Grenville Road Plymouth Devon PL4 9QD",
    "addr:housenumber":"177",
    "addr:postcode":"pl4 9qd",
    "addr:street":"Grenville Road",
    "iso:country":"GB",
    "sg:address":"177 Grenville Road",
    "sg:city":"Plymouth",
    "sg:classifiers":[
        {
            "category":"Organizations",
            "subcategory":"Membership Organization",
            "type":"Services"
        }
    ],
    "sg:phone":"+44 1752 660564",
    "sg:postcode":"PL4 9QD",
    "sg:province":"Devon",
    "sg:tags":[
        "club"
    ],
    "wof:name":"The Friary Social Club",
    "wof:placetype":"venue"
},
  "geometry": {"coordinates":[-4.1178860664,50.3719673157],"type":"Point"}
}