{
  "type": "Feature",
  "properties": {
    "addr:full":"Workshop, Cambridge Road Weymouth Dorset DT4 9TJ",
    "addr:postcode":"dt4 9tj",
    "addr:street":"Cambridge Road",
    "iso:country":"GB",
    "sg:address":"Workshop, Cambridge Road",
    "sg:city":"Weymouth",
    "sg:classifiers":[
        {
            "category":"Professional",
            "subcategory":"Engineering",
            "type":"Services"
        }
    ],
    "sg:postcode":"DT4 9TJ",
    "sg:province":"Dorset",
    "sg:tags":[
        "precision",
        "engineer"
    ],
    "wof:name":"Granby Precision Engineering",
    "wof:placetype":"venue"
},
  "geometry": {"coordinates":[-2.491771,50.614971],"type":"Point"}
}