{
  "type": "Feature",
  "properties": {
    "addr:full":"21 Tudor Avenue Stanford-le-hope Essex SS17 8BX",
    "addr:housenumber":"21",
    "addr:postcode":"ss17 8bx",
    "addr:street":"Tudor Avenue Stanford-Le-Hope",
    "iso:country":"GB",
    "sg:address":"21 Tudor Avenue",
    "sg:city":"Stanford-le-hope",
    "sg:classifiers":[
        {
            "category":"Building & Trades",
            "subcategory":"Construction",
            "type":"Services"
        }
    ],
    "sg:phone":"+44 1375 675068",
    "sg:postcode":"SS17 8BX",
    "sg:province":"Essex",
    "sg:tags":[
        "builder"
    ],
    "wof:name":"G D Builders",
    "wof:placetype":"venue"
},
  "geometry": {"coordinates":[0.437753,51.529015],"type":"Point"}
}