{
  "type": "Feature",
  "properties": {
    "iso:country":"GB",
    "sg:address":"21 Tudor Avenue",
    "sg:city":"Stanford-le-hope",
    "sg:classifiers":[
        {
            "category":"Building & Trades",
            "subcategory":"Construction",
            "type":"Services"
        }
    ],
    "sg:phone":"+44 1375 675068",
    "sg:postcode":"SS17 8BX",
    "sg:province":"Essex",
    "sg:tags":[
        "builder"
    ],
    "wof:name":"G D Builders",
    "wof:placetype":"venue"
},
  "geometry": {"coordinates":[0.437753,51.529015],"type":"Point"}
}