{
  "type": "Feature",
  "properties": {
    "addr:full":"86 Old Fosse Rd Bath Somerset BA2 2SR",
    "addr:housenumber":"86",
    "addr:postcode":"ba2 2sr",
    "addr:street":"Old Fosse Rd",
    "iso:country":"GB",
    "sg:address":"86 Old Fosse Rd",
    "sg:city":"Bath",
    "sg:classifiers":[
        {
            "category":"Government",
            "subcategory":"Customs House",
            "type":"Public Place"
        }
    ],
    "sg:phone":"+44 1225 401218",
    "sg:postcode":"BA2 2SR",
    "sg:province":"Somerset",
    "sg:tags":[
        "clearance"
    ],
    "wof:name":"B & K House Clearance Specialists",
    "wof:placetype":"venue"
},
  "geometry": {"coordinates":[-2.3835530281,51.358127594],"type":"Point"}
}