{
  "type": "Feature",
  "properties": {
    "addr:full":"P O Box 7 Waterlooville Hampshire PO7 7EF",
    "addr:housenumber":"7",
    "addr:postcode":"po7 7ef",
    "addr:street":"P O Box",
    "iso:country":"GB",
    "sg:address":"P O Box 7",
    "sg:city":"Waterlooville",
    "sg:classifiers":[
        {
            "category":"Wholesale",
            "subcategory":"Toys & Hobbies",
            "type":"Manufacturing & Wholesale Goods"
        }
    ],
    "sg:phone":"+44 23 9226 8998",
    "sg:postcode":"PO7 7EF",
    "sg:province":"Hampshire",
    "sg:tags":[
        "game"
    ],
    "wof:name":"Toywise",
    "wof:placetype":"venue"
},
  "geometry": {"coordinates":[-1.0315589905,50.8800888062],"type":"Point"}
}