{
  "type": "Feature",
  "properties": {
    "addr:full":"33 Grange Rd West Birkenhead Merseyside CH41 4BY",
    "addr:housenumber":"33",
    "addr:postcode":"ch41 4by",
    "addr:street":"Grange Rd West",
    "iso:country":"GB",
    "sg:address":"33 Grange Rd West",
    "sg:city":"Birkenhead",
    "sg:classifiers":[
        {
            "category":"Building & Trades",
            "subcategory":"Cleaning & Sanitation",
            "type":"Services"
        }
    ],
    "sg:phone":"+44 151 647 4501",
    "sg:postcode":"CH41 4BY",
    "sg:province":"Merseyside",
    "sg:tags":[
        "polishing",
        "floor"
    ],
    "wof:name":"Evergreen Cleaning Concepts",
    "wof:placetype":"venue"
},
  "geometry": {"coordinates":[-3.034139,53.389061],"type":"Point"}
}