{
  "type": "Feature",
  "properties": {
    "iso:country":"GB",
    "sg:address":"The Court House, Lowther Terrace",
    "sg:city":"Penrith",
    "sg:classifiers":[
        {
            "category":"Government",
            "subcategory":"Court House",
            "type":"Public Place"
        }
    ],
    "sg:phone":"+44 1768 862535",
    "sg:postcode":"CA11 7QL",
    "sg:province":"Cumbria",
    "wof:name":"County Court",
    "wof:placetype":"venue"
},
  "geometry": {"coordinates":[-2.7532789707,54.6674804688],"type":"Point"}
}