{
  "type": "Feature",
  "properties": {
    "iso:country":"GB",
    "sg:address":"57 Inchbrook Road",
    "sg:city":"Kenilworth",
    "sg:classifiers":[
        {
            "category":"Professional",
            "type":"Services"
        }
    ],
    "sg:postcode":"CV8 2EW",
    "sg:province":"Warwickshire",
    "sg:tags":[
        "entertainer"
    ],
    "wof:name":"James Beavis",
    "wof:placetype":"venue"
},
  "geometry": {"coordinates":[-1.558866024,52.3555679321],"type":"Point"}
}