{
  "type": "Feature",
  "properties": {
    "addr:full":"78-80 Kingston Road Portsmouth Hampshire PO2 7PA",
    "addr:housenumber":"78-80",
    "addr:postcode":"hampshire po2 7pa",
    "addr:street":"Kingston Road",
    "iso:country":"GB",
    "sg:address":"78-80 Kingston Road",
    "sg:city":"Portsmouth",
    "sg:classifiers":[
        {
            "category":"Fast Food",
            "type":"Food & Drink"
        }
    ],
    "sg:phone":"+44 23 9267 0760",
    "sg:postcode":"PO2 7PA",
    "sg:province":"Hampshire",
    "sg:tags":[
        "away",
        "meal",
        "outlet",
        "take"
    ],
    "wof:name":"Pompey Kebab House",
    "wof:placetype":"venue"
},
  "geometry": {"coordinates":[-1.0772390366,50.8086891174],"type":"Point"}
}