{
  "type": "Feature",
  "properties": {
    "iso:country":"GB",
    "sg:address":"8 Charnwood Street",
    "sg:city":"Derby",
    "sg:classifiers":[
        {
            "category":"Professional",
            "subcategory":"Art Services",
            "type":"Services"
        }
    ],
    "sg:phone":"+44 1332 298088",
    "sg:postcode":"DE1 2GT",
    "sg:province":"Derbyshire",
    "sg:tags":[
        "consultant",
        "design"
    ],
    "wof:name":"S A M Design Consultants Ltd.",
    "wof:placetype":"venue"
},
  "geometry": {"coordinates":[-1.476143,52.915791],"type":"Point"}
}