{
  "type": "Feature",
  "properties": {
    "iso:country":"GB",
    "sg:address":"Newhailes Est, Newhailes Rd",
    "sg:city":"Musselburgh",
    "sg:classifiers":[
        {
            "category":"Manufacturing",
            "subcategory":"Petroleum Products",
            "type":"Manufacturing & Wholesale Goods"
        }
    ],
    "sg:phone":"+44 131 665 9820",
    "sg:postcode":"EH21 6SJ",
    "sg:province":"City of Edinburgh",
    "sg:tags":[
        "double",
        "glazing"
    ],
    "wof:name":"Premier Glazing (Edinburgh) Ltd",
    "wof:placetype":"venue"
},
  "geometry": {"coordinates":[-3.07647,55.945206],"type":"Point"}
}