{
  "type": "Feature",
  "properties": {
    "iso:country":"GB",
    "sg:address":"Regional Centre, 5 White Hart Lane",
    "sg:city":"Wellington",
    "sg:classifiers":[
        {
            "category":"Shopping",
            "subcategory":"Thrift Store",
            "type":"Retail Goods"
        }
    ],
    "sg:phone":"+44 1403 210585",
    "sg:postcode":"TA21 8HN",
    "sg:province":"Devon",
    "sg:tags":[
        "shop",
        "charity"
    ],
    "wof:name":"Imperial Cancer Research Fund",
    "wof:placetype":"venue"
},
  "geometry": {"coordinates":[-3.226639,50.979271],"type":"Point"}
}