{
  "type": "Feature",
  "properties": {
    "addr:full":"Esso Garage, A418-b4011 The Bicester Road Thame Buckinghamshire OX9 3SB",
    "addr:housenumber":"the",
    "addr:postcode":"ox9 3sb",
    "addr:street":"Bicester Road",
    "iso:country":"GB",
    "sg:address":"Esso Garage, A418-b4011 The Bicester Road",
    "sg:city":"Thame",
    "sg:classifiers":[
        {
            "category":"Autos & Motor Vehicles",
            "subcategory":"Fuel & Gas Station",
            "type":"Retail Goods"
        }
    ],
    "sg:phone":"+44 1844 218742",
    "sg:postcode":"OX9 3SB",
    "sg:province":"Buckinghamshire",
    "sg:tags":[
        "hr",
        "petrol"
    ],
    "wof:name":"Thame Service Area",
    "wof:placetype":"venue"
},
  "geometry": {"coordinates":[-0.9729539752,51.7591514587],"type":"Point"}
}