{
  "type": "Feature",
  "properties": {
    "addr:full":"55 Albert Park Road Malvern Herefordshire WR14 1RH",
    "addr:housenumber":"55",
    "addr:postcode":"wr14 1rh",
    "addr:street":"Albert Park Road",
    "iso:country":"GB",
    "sg:address":"55 Albert Park Road",
    "sg:city":"Malvern",
    "sg:classifiers":[
        {
            "category":"Food & Beverages",
            "subcategory":"Bakery",
            "type":"Retail Goods"
        }
    ],
    "sg:postcode":"WR14 1RH",
    "sg:province":"Herefordshire",
    "sg:tags":[
        "baker"
    ],
    "wof:name":"Orchard Bakery",
    "wof:placetype":"venue"
},
  "geometry": {"coordinates":[-2.329116106,52.1263694763],"type":"Point"}
}