{
  "type": "Feature",
  "properties": {
    "addr:full":"16 Manor Place Edinburgh City of Edinburgh EH3 7DS",
    "addr:housenumber":"16",
    "addr:postcode":"eh3 7ds",
    "addr:street":"Manor Place Edinburgh",
    "iso:country":"GB",
    "sg:address":"16 Manor Place",
    "sg:city":"Edinburgh",
    "sg:classifiers":[
        {
            "category":"Shopping",
            "subcategory":"Clothing, Apparel, & Fashions",
            "type":"Retail Goods"
        }
    ],
    "sg:phone":"+44 131 225 3984",
    "sg:postcode":"EH3 7DS",
    "sg:province":"City of Edinburgh",
    "sg:tags":[
        "shop"
    ],
    "wof:name":"Bennetton",
    "wof:placetype":"venue"
},
  "geometry": {"coordinates":[-3.214981,55.952438],"type":"Point"}
}