{
  "type": "Feature",
  "properties": {
    "addr:full":"16 Cone Terrace Chester-le-street Durham DH3 3QH",
    "addr:housenumber":"16",
    "addr:postcode":"dh3 3qh",
    "addr:street":"Cone Terrace",
    "iso:country":"GB",
    "sg:address":"16 Cone Terrace",
    "sg:city":"Chester-le-street",
    "sg:classifiers":[
        {
            "category":"Building & Trades",
            "subcategory":"Construction",
            "type":"Services"
        }
    ],
    "sg:phone":"+44 191 389 0542",
    "sg:postcode":"DH3 3QH",
    "sg:province":"Durham",
    "sg:tags":[
        "builder"
    ],
    "wof:name":"Melcon Building Contractors",
    "wof:placetype":"venue"
},
  "geometry": {"coordinates":[-1.5705239773,54.8574905396],"type":"Point"}
}