{
  "type": "Feature",
  "properties": {
    "addr:full":"The Honeypot, School Lane, Peasmarsh Rye East Sussex TN31 6UW",
    "addr:postcode":"tn31 6uw",
    "addr:street":"School Lane",
    "iso:country":"GB",
    "sg:address":"The Honeypot, School Lane, Peasmarsh",
    "sg:city":"Rye",
    "sg:classifiers":[
        {
            "category":"Professional",
            "subcategory":"Accounting & Tax Preparation",
            "type":"Services"
        }
    ],
    "sg:phone":"+44 1797 230091",
    "sg:postcode":"TN31 6UW",
    "sg:province":"East Sussex",
    "sg:tags":[
        "accountant"
    ],
    "wof:name":"Porterhouse Account Services",
    "wof:placetype":"venue"
},
  "geometry": {"coordinates":[0.67889,50.977589],"type":"Point"}
}