{
  "type": "Feature",
  "properties": {
    "addr:full":"12 Turf Hill Rd Camberley Berkshire GU15 4EQ",
    "addr:housenumber":"12",
    "addr:postcode":"gu15 4eq",
    "addr:street":"Turf Hill Rd",
    "iso:country":"GB",
    "sg:address":"12 Turf Hill Rd",
    "sg:city":"Camberley",
    "sg:classifiers":[
        {
            "category":"Building & Trades",
            "subcategory":"Construction",
            "type":"Services"
        }
    ],
    "sg:phone":"+44 1276 681600",
    "sg:postcode":"GU15 4EQ",
    "sg:province":"Berkshire",
    "sg:tags":[
        "builder"
    ],
    "wof:name":"P Bartrop",
    "wof:placetype":"venue"
},
  "geometry": {"coordinates":[-0.727446,51.346699],"type":"Point"}
}