{
  "type": "Feature",
  "properties": {
    "addr:full":"9 Heritage Park, Hatch Warren Basingstoke Hampshire RG22 4XT",
    "addr:housenumber":"9",
    "addr:postcode":"rg22 4xt",
    "addr:street":"Heritage Park",
    "iso:country":"GB",
    "sg:address":"9 Heritage Park, Hatch Warren",
    "sg:city":"Basingstoke",
    "sg:classifiers":[
        {
            "category":"Building & Trades",
            "subcategory":"Electrical",
            "type":"Services"
        },
        {
            "category":"Real Estate",
            "subcategory":"Architect",
            "type":"Services"
        }
    ],
    "sg:phone":"+44 1256 351801",
    "sg:postcode":"RG22 4XT",
    "sg:province":"Hampshire",
    "sg:tags":[
        "electrician",
        "contractor"
    ],
    "wof:name":"Brian Oates Electrical Engineering Services Ltd.",
    "wof:placetype":"venue"
},
  "geometry": {"coordinates":[-1.1315619946,51.2314872742],"type":"Point"}
}