{
  "type": "Feature",
  "properties": {
    "addr:full":"43 Tempsford Road Sandy Bedfordshire SG19 2AF",
    "addr:housenumber":"43",
    "addr:postcode":"sg19 2af",
    "addr:street":"Tempsford Road",
    "iso:country":"GB",
    "sg:address":"43 Tempsford Road",
    "sg:city":"Sandy",
    "sg:classifiers":[
        {
            "category":"Recreation",
            "subcategory":"Barbecue",
            "type":"Entertainment"
        }
    ],
    "sg:phone":"+44 1767 681694",
    "sg:postcode":"SG19 2AF",
    "sg:province":"Bedfordshire",
    "sg:tags":[
        "equipment",
        "retail"
    ],
    "wof:name":"Bedfordshire Barbeque Centre",
    "wof:placetype":"venue"
},
  "geometry": {"coordinates":[-0.301703,52.155727],"type":"Point"}
}