{
  "type": "Feature",
  "properties": {
    "iso:country":"GB",
    "sg:address":"76 Skipton Rd",
    "sg:city":"Colne",
    "sg:classifiers":[
        {
            "category":"Education",
            "subcategory":"Preschool",
            "type":"Public Place"
        }
    ],
    "sg:phone":"+44 1282 815269",
    "sg:postcode":"BB8 5EG",
    "sg:province":"Lancashire",
    "sg:tags":[
        "pre-school",
        "playgroups"
    ],
    "wof:name":"Craven Pre-School",
    "wof:placetype":"venue"
},
  "geometry": {"coordinates":[-2.1863689423,53.9198303223],"type":"Point"}
}