{
  "type": "Feature",
  "properties": {
    "iso:country":"GB",
    "sg:address":"6-7 Brindley Road, Reginald Road Industr",
    "sg:city":"St Helens",
    "sg:classifiers":[
        {
            "category":"Shopping",
            "subcategory":"Computers & Home Electronics",
            "type":"Retail Goods"
        }
    ],
    "sg:phone":"+44 1744 811120",
    "sg:postcode":"WA9 4HY",
    "sg:province":"Cheshire",
    "wof:name":"Geminites Ltd.",
    "wof:placetype":"venue"
},
  "geometry": {"coordinates":[-2.703046,53.429977],"type":"Point"}
}