{
  "type": "Feature",
  "properties": {
    "addr:full":"53 West Nile Street Glasgow Glasgow City G1 2QB",
    "addr:housenumber":"53",
    "addr:postcode":"g1 2qb",
    "addr:street":"West Nile Street",
    "iso:country":"GB",
    "sg:address":"53 West Nile Street",
    "sg:city":"Glasgow",
    "sg:classifiers":[
        {
            "category":"Shopping",
            "subcategory":"Gifts & Souvenirs",
            "type":"Retail Goods"
        }
    ],
    "sg:postcode":"G1 2QB",
    "sg:province":"Glasgow City",
    "sg:tags":[
        "giftware"
    ],
    "wof:name":"Images Scotland Ltd.",
    "wof:placetype":"venue"
},
  "geometry": {"coordinates":[-4.255161,55.862038],"type":"Point"}
}