{
  "type": "Feature",
  "properties": {
    "addr:full":"16 East Precinct, Charles Street Stoke-on-trent Staffordshire ST1 3AR",
    "addr:housenumber":"16",
    "addr:postcode":"st1 3ar",
    "addr:street":"East Precinct Charles Street",
    "iso:country":"GB",
    "sg:address":"16 East Precinct, Charles Street",
    "sg:city":"Stoke-on-trent",
    "sg:classifiers":[
        {
            "category":"Home & Garden",
            "subcategory":"Household Appliances",
            "type":"Retail Goods"
        }
    ],
    "sg:phone":"+44 1782 263019",
    "sg:postcode":"ST1 3AR",
    "sg:province":"Staffordshire",
    "sg:tags":[
        "electrical",
        "domestic"
    ],
    "wof:name":"Tandy",
    "wof:placetype":"venue"
},
  "geometry": {"coordinates":[-2.175069,53.029369],"type":"Point"}
}