{
  "type": "Feature",
  "properties": {
    "addr:full":"15 Enterprise Court, Lakes Road Braintree Essex CM7 3QS",
    "addr:housenumber":"15",
    "addr:postcode":"cm7 3qs",
    "addr:street":"Enterprise Court Lakes Road",
    "iso:country":"GB",
    "sg:address":"15 Enterprise Court, Lakes Road",
    "sg:city":"Braintree",
    "sg:classifiers":[
        {
            "category":"Manufacturing",
            "subcategory":"Electronics",
            "type":"Manufacturing & Wholesale Goods"
        }
    ],
    "sg:phone":"+44 1376 347415",
    "sg:postcode":"CM7 3QS",
    "sg:province":"Essex",
    "sg:tags":[
        "control",
        "component",
        "-",
        "electronic"
    ],
    "wof:name":"Dannell Electronics Ltd.",
    "wof:placetype":"venue"
},
  "geometry": {"coordinates":[0.563845,51.876579],"type":"Point"}
}