{
  "type": "Feature",
  "properties": {
    "addr:full":"Unit G, Prospect Business Centre, Dundee Technology Park Dundee Dundee City DD2 1TY",
    "addr:housenumber":"unit g",
    "addr:postcode":"dd2 1ty",
    "addr:street":"Prospect Business Centre;Technology Park",
    "iso:country":"GB",
    "sg:address":"Unit G, Prospect Business Centre, Dundee Technology Park",
    "sg:city":"Dundee",
    "sg:classifiers":[
        {
            "category":"Professional",
            "subcategory":"Computer Services",
            "type":"Services"
        }
    ],
    "sg:phone":"+44 1382 598450",
    "sg:postcode":"DD2 1TY",
    "sg:province":"Dundee City",
    "sg:tags":[
        "system",
        "software"
    ],
    "wof:name":"C2 Software Ltd.",
    "wof:placetype":"venue"
},
  "geometry": {"coordinates":[-3.0514359474,56.4621315002],"type":"Point"}
}