{
  "type": "Feature",
  "properties": {
    "iso:country":"GB",
    "sg:address":"53 Walton Vale, Aintree",
    "sg:city":"Liverpool",
    "sg:classifiers":[
        {
            "category":"Shopping",
            "subcategory":"Shoes",
            "type":"Retail Goods"
        }
    ],
    "sg:phone":"+44 151 525 8382",
    "sg:postcode":"L9 4RF",
    "sg:province":"Merseyside",
    "sg:tags":[
        "shop"
    ],
    "wof:name":"Timpson",
    "wof:placetype":"venue"
},
  "geometry": {"coordinates":[-2.959891,53.463116],"type":"Point"}
}