{
  "type": "Feature",
  "properties": {
    "iso:country":"GB",
    "sg:address":"Lion Way, Swansea Enterprise Park",
    "sg:city":"Swansea",
    "sg:classifiers":[
        {
            "category":"Home & Garden",
            "subcategory":"Home Furnishings",
            "type":"Retail Goods"
        },
        {
            "category":"Wholesale",
            "subcategory":"Home Furnishings",
            "type":"Manufacturing & Wholesale Goods"
        }
    ],
    "sg:phone":"+44 1792 701551",
    "sg:postcode":"SA7 9EH",
    "sg:province":"Neath Port Talbot",
    "sg:tags":[
        "merchant",
        "diy",
        "decorators'"
    ],
    "wof:name":"Crown Brolac Decorator Centre",
    "wof:placetype":"venue"
},
  "geometry": {"coordinates":[-3.910199,51.656834],"type":"Point"}
}