{
  "type": "Feature",
  "properties": {
    "addr:full":"32 St Mary's Walk Mirfield West Yorkshire WF14 0QB",
    "addr:housenumber":"32",
    "addr:postcode":"wf14 0qb",
    "addr:street":"St Mary'S Walk",
    "iso:country":"GB",
    "sg:address":"32 St Mary's Walk",
    "sg:city":"Mirfield",
    "sg:classifiers":[
        {
            "category":"Building & Trades",
            "subcategory":"Construction",
            "type":"Services"
        }
    ],
    "sg:postcode":"WF14 0QB",
    "sg:province":"West Yorkshire",
    "sg:tags":[
        "joiner",
        "carpenter"
    ],
    "wof:name":"Ashman Mark Joinery & Home Improvement Services",
    "wof:placetype":"venue"
},
  "geometry": {"coordinates":[-1.699416995,53.6707954407],"type":"Point"}
}