{
  "type": "Feature",
  "properties": {
    "iso:country":"GB",
    "sg:address":"55 Clyde Street",
    "sg:city":"Sheerness",
    "sg:classifiers":[
        {
            "category":"Bars & Pubs",
            "type":"Food & Drink"
        },
        {
            "category":"Community Center",
            "subcategory":"Social",
            "type":"Public Place"
        }
    ],
    "sg:postcode":"ME12 2QF",
    "sg:province":"Kent",
    "sg:tags":[
        "pubs",
        "house",
        "inn",
        "activity"
    ],
    "wof:name":"BLACKSMITHS ARMS",
    "wof:placetype":"venue"
},
  "geometry": {"coordinates":[0.771639,51.438126],"type":"Point"}
}