{
  "type": "Feature",
  "properties": {
    "iso:country":"GB",
    "sg:address":"14a Fountainhall Road",
    "sg:city":"Aberdeen",
    "sg:classifiers":[
        {
            "category":"Communications",
            "type":"Services"
        }
    ],
    "sg:phone":"+44 1224 648720",
    "sg:postcode":"AB12 5RL",
    "sg:province":"Aberdeen City",
    "sg:tags":[
        "audio-visual"
    ],
    "wof:name":"T V P Film & Multimedia Ltd.",
    "wof:placetype":"venue"
},
  "geometry": {"coordinates":[-2.1278250217,57.144733429],"type":"Point"}
}