{
  "type": "Feature",
  "properties": {
    "iso:country":"GB",
    "sg:address":"West Winds, Strachur",
    "sg:city":"Cairndow",
    "sg:classifiers":[
        {
            "category":"Manufacturing",
            "subcategory":"Lumber",
            "type":"Manufacturing & Wholesale Goods"
        }
    ],
    "sg:phone":"+44 1369 860334",
    "sg:postcode":"PA27 8BY",
    "sg:province":"Argyll and Bute",
    "sg:tags":[
        "importer",
        "merchants",
        "agent",
        "timber"
    ],
    "wof:name":"B S W Timber",
    "wof:placetype":"venue"
},
  "geometry": {"coordinates":[-5.0673789978,56.1663856506],"type":"Point"}
}