{
  "type": "Feature",
  "properties": {
    "iso:country":"GB",
    "sg:address":"8-10 West Street",
    "sg:city":"Dunstable",
    "sg:classifiers":[
        {
            "category":"Shopping",
            "subcategory":"Pharmacy",
            "type":"Retail Goods"
        }
    ],
    "sg:phone":"+44 1582 699854",
    "sg:postcode":"LU6 1SX",
    "sg:province":"Bedfordshire",
    "sg:tags":[
        "pharmacist",
        "chemist"
    ],
    "wof:name":"West Street Pharmacy",
    "wof:placetype":"venue"
},
  "geometry": {"coordinates":[-0.5216339827,51.8858604431],"type":"Point"}
}