{
  "type": "Feature",
  "properties": {
    "iso:country":"GB",
    "sg:address":"33 North View, Westbury Park",
    "sg:city":"Bristol",
    "sg:classifiers":[
        {
            "category":"Personal",
            "subcategory":"Beauty Salon",
            "type":"Services"
        }
    ],
    "sg:postcode":"BS6 7PT",
    "sg:province":"City of Bristol",
    "sg:tags":[
        "lady",
        "hairdresser"
    ],
    "wof:name":"Taylor Vivienne Exclusive Ladies Hairdressing",
    "wof:placetype":"venue"
},
  "geometry": {"coordinates":[-2.6139900684,51.4794387817],"type":"Point"}
}