{
  "type": "Feature",
  "properties": {
    "addr:full":"7 Hallams Yard Skipton Lancashire BD23 1JN",
    "addr:housenumber":"7",
    "addr:postcode":"bd23 1jn",
    "addr:street":"Hallams Yard",
    "iso:country":"GB",
    "sg:address":"7 Hallams Yard",
    "sg:city":"Skipton",
    "sg:classifiers":[
        {
            "category":"Home & Garden",
            "subcategory":"Carpets & Floor Coverings",
            "type":"Retail Goods"
        }
    ],
    "sg:phone":"+44 1756 791756",
    "sg:postcode":"BD23 1JN",
    "sg:province":"Lancashire",
    "sg:tags":[
        "carpets",
        "rug",
        "matting"
    ],
    "wof:name":"G & C Smith Carpets",
    "wof:placetype":"venue"
},
  "geometry": {"coordinates":[-2.017399,53.961449],"type":"Point"}
}