{
  "type": "Feature",
  "properties": {
    "addr:full":"Salterton Road, Littleham Exmouth Devon EX8 5BW",
    "addr:postcode":"ex8 5bw",
    "addr:street":"Salterton Road",
    "iso:country":"GB",
    "sg:address":"Salterton Road, Littleham",
    "sg:city":"Exmouth",
    "sg:classifiers":[
        {
            "category":"Farming",
            "subcategory":"Livestock Farm",
            "type":"Manufacturing & Wholesale Goods"
        }
    ],
    "sg:postcode":"EX8 5BW",
    "sg:province":"Devon",
    "sg:tags":[
        "others"
    ],
    "wof:name":"Liverton Farm",
    "wof:placetype":"venue"
},
  "geometry": {"coordinates":[-3.377969,50.629509],"type":"Point"}
}