{
  "type": "Feature",
  "properties": {
    "iso:country":"GB",
    "sg:address":"Rear Of 67 Barlborough Road, Clowne",
    "sg:city":"Chesterfield",
    "sg:classifiers":[
        {
            "category":"Retail",
            "subcategory":"Auto Rental",
            "type":"Services"
        }
    ],
    "sg:postcode":"S43 4QX",
    "sg:province":"Derbyshire",
    "sg:tags":[
        "car"
    ],
    "wof:name":"C M S Self Drive Hire",
    "wof:placetype":"venue"
},
  "geometry": {"coordinates":[-1.2885940075,53.2861557007],"type":"Point"}
}