{
  "type": "Feature",
  "properties": {
    "addr:full":"34 Everest Dr, Hoo Rochester Kent ME3 9AW",
    "addr:housenumber":"34",
    "addr:postcode":"me3 9aw",
    "addr:street":"Everest Dr",
    "iso:country":"GB",
    "sg:address":"34 Everest Dr, Hoo",
    "sg:city":"Rochester",
    "sg:classifiers":[
        {
            "category":"Retail",
            "subcategory":"Repair Shop",
            "type":"Services"
        }
    ],
    "sg:phone":"+44 1634 255103",
    "sg:postcode":"ME3 9AW",
    "sg:province":"Kent",
    "sg:tags":[
        "equipment",
        "catering"
    ],
    "wof:name":"Washbrook,Michael,",
    "wof:placetype":"venue"
},
  "geometry": {"coordinates":[0.561811,51.418655],"type":"Point"}
}