{
  "type": "Feature",
  "properties": {
    "addr:full":"Unit 6 Redhouse Industrial Estat, E Shieldhill Road Falkirk Falkirk FK2 0DT",
    "addr:housenumber":"unit 6",
    "addr:postcode":"fk2 0dt",
    "addr:street":"Redhouse Industrial Estat E Shieldhill Road",
    "iso:country":"GB",
    "sg:address":"Unit 6 Redhouse Industrial Estat, E Shieldhill Road",
    "sg:city":"Falkirk",
    "sg:classifiers":[
        {
            "category":"Farming",
            "subcategory":"Fish & Marine Products",
            "type":"Manufacturing & Wholesale Goods"
        }
    ],
    "sg:phone":"+44 1324 716616",
    "sg:postcode":"FK2 0DT",
    "sg:province":"Falkirk",
    "sg:tags":[
        "fishmonger"
    ],
    "wof:name":"Mary's Plaice",
    "wof:placetype":"venue"
},
  "geometry": {"coordinates":[-3.74174,55.980289],"type":"Point"}
}