{
  "type": "Feature",
  "properties": {
    "iso:country":"GB",
    "sg:address":"59a-b Clarence Street",
    "sg:city":"Kingston-upon-thames",
    "sg:classifiers":[
        {
            "category":"Shopping",
            "subcategory":"Clothing, Apparel, & Fashions",
            "type":"Retail Goods"
        }
    ],
    "sg:phone":"+44 20 8546 1465",
    "sg:postcode":"KT1 1RB",
    "sg:province":"Greater London",
    "sg:tags":[
        "shop"
    ],
    "wof:name":"River Island Clothing Co Ltd",
    "wof:placetype":"venue"
},
  "geometry": {"coordinates":[-0.3034189939,51.4109458923],"type":"Point"}
}