{
  "type": "Feature",
  "properties": {
    "iso:country":"GB",
    "sg:address":"Ashdale House, Lockwood Avenue",
    "sg:city":"Poulton-le-fylde",
    "sg:classifiers":[
        {
            "category":"Professional",
            "subcategory":"Engineering",
            "type":"Services"
        }
    ],
    "sg:phone":"+44 1253 894436",
    "sg:postcode":"FY6 7AB",
    "sg:province":"Lancashire",
    "sg:tags":[
        "contractor",
        "electrical",
        "engineer"
    ],
    "wof:name":"Environmental Project Services Ltd.",
    "wof:placetype":"venue"
},
  "geometry": {"coordinates":[-2.992899,53.849594],"type":"Point"}
}