{
  "type": "Feature",
  "properties": {
    "addr:full":"50 Stanley Road, Oldbury Birmingham West Midlands B68 0EQ",
    "addr:housenumber":"50",
    "addr:postcode":"b68 0eq",
    "addr:street":"Stanley Road",
    "iso:country":"GB",
    "sg:address":"50 Stanley Road, Oldbury",
    "sg:city":"Birmingham",
    "sg:classifiers":[
        {
            "category":"Professional",
            "type":"Services"
        }
    ],
    "sg:postcode":"B68 0EQ",
    "sg:province":"West Midlands",
    "sg:tags":[
        "reflexologists"
    ],
    "wof:name":"Shelley White",
    "wof:placetype":"venue"
},
  "geometry": {"coordinates":[-1.9950530529,52.4667816162],"type":"Point"}
}