{
  "type": "Feature",
  "properties": {
    "iso:country":"GB",
    "sg:address":"Church Farm",
    "sg:city":"Monmouth",
    "sg:classifiers":[
        {
            "category":"Farming",
            "subcategory":"Dairy Farm",
            "type":"Manufacturing & Wholesale Goods"
        }
    ],
    "sg:postcode":"NP25 4JP",
    "sg:province":"Gloucestershire",
    "wof:name":"Hubert E Quick",
    "wof:placetype":"venue"
},
  "geometry": {"coordinates":[-2.7246239185,51.7439193726],"type":"Point"}
}