{
  "type": "Feature",
  "properties": {
    "iso:country":"GB",
    "sg:address":"1675 Dunbarton Road",
    "sg:city":"Glasgow",
    "sg:classifiers":[
        {
            "category":"Professional",
            "subcategory":"Art Services",
            "type":"Services"
        },
        {
            "category":"Building & Trades",
            "subcategory":"Construction",
            "type":"Services"
        }
    ],
    "sg:phone":"+44 141 959 1252",
    "sg:postcode":"G14 9YB",
    "sg:province":"Glasgow City",
    "sg:tags":[
        "decorator",
        "painter"
    ],
    "wof:name":"Express Decor",
    "wof:placetype":"venue"
},
  "geometry": {"coordinates":[-4.358654,55.88187],"type":"Point"}
}