{
  "type": "Feature",
  "properties": {
    "iso:country":"GB",
    "sg:address":"Squirrel Cottage, Main St",
    "sg:city":"Evesham",
    "sg:classifiers":[
        {
            "category":"Professional",
            "subcategory":"Management & Consulting",
            "type":"Services"
        }
    ],
    "sg:phone":"+44 1789 772985",
    "sg:postcode":"WR11 5LD",
    "sg:province":"Gloucestershire",
    "sg:tags":[
        "consultant",
        "safety"
    ],
    "wof:name":"Safety Management Consultants",
    "wof:placetype":"venue"
},
  "geometry": {"coordinates":[-1.943969,52.106392],"type":"Point"}
}