{
  "type": "Feature",
  "properties": {
    "addr:full":"18 County Rd Liverpool Merseyside L4 3QH",
    "addr:housenumber":"18",
    "addr:postcode":"l4 3qh",
    "addr:street":"County Rd",
    "iso:country":"GB",
    "sg:address":"18 County Rd",
    "sg:city":"Liverpool",
    "sg:classifiers":[
        {
            "category":"Travel",
            "subcategory":"Travel Agent",
            "type":"Entertainment"
        }
    ],
    "sg:phone":"+44 151 524 2424",
    "sg:postcode":"L4 3QH",
    "sg:province":"Merseyside",
    "sg:tags":[
        "agency",
        "activity"
    ],
    "wof:name":"Co-op Travelcare",
    "wof:placetype":"venue"
},
  "geometry": {"coordinates":[-2.971295,53.438316],"type":"Point"}
}