{
  "type": "Feature",
  "properties": {
    "addr:full":"638 Aldridge Rd Birmingham West Midlands B44 8NQ",
    "addr:housenumber":"638",
    "addr:postcode":"b44 8nq",
    "addr:street":"Aldridge Rd",
    "iso:country":"GB",
    "sg:address":"638 Aldridge Rd",
    "sg:city":"Birmingham",
    "sg:classifiers":[
        {
            "category":"Manufacturing",
            "subcategory":"Tools & Machinery",
            "type":"Manufacturing & Wholesale Goods"
        },
        {
            "category":"Insurance",
            "subcategory":"Insurance Agent",
            "type":"Services"
        }
    ],
    "sg:phone":"+44 121 360 4106",
    "sg:postcode":"B44 8NQ",
    "sg:province":"West Midlands",
    "sg:tags":[
        "society",
        "friendly"
    ],
    "wof:name":"Cofield Insurance Services",
    "wof:placetype":"venue"
},
  "geometry": {"coordinates":[-1.8950819969,52.5385704041],"type":"Point"}
}