{
  "type": "Feature",
  "properties": {
    "addr:full":"312 Chester Road, Streetly Sutton Coldfield Staffordshire B74 3ED",
    "addr:housenumber":"312",
    "addr:postcode":"b74 3ed",
    "addr:street":"Chester Road",
    "iso:country":"GB",
    "sg:address":"312 Chester Road, Streetly",
    "sg:city":"Sutton Coldfield",
    "sg:classifiers":[
        {
            "category":"Manufacturing",
            "subcategory":"Food",
            "type":"Manufacturing & Wholesale Goods"
        },
        {
            "category":"Home & Garden",
            "subcategory":"Hardware",
            "type":"Retail Goods"
        }
    ],
    "sg:postcode":"B74 3ED",
    "sg:province":"Staffordshire",
    "sg:tags":[
        "mnfr",
        "mech",
        "drink",
        "heat",
        "exchanger",
        "soft"
    ],
    "wof:name":"Dunedin Spring Ltd",
    "wof:placetype":"venue"
},
  "geometry": {"coordinates":[-1.8875969648,52.5856018066],"type":"Point"}
}