{
  "type": "Feature",
  "properties": {
    "addr:full":"28a Gwennyth Street, Cathays Cardiff Cardiff CF24 4PH",
    "addr:housenumber":"28a",
    "addr:postcode":"cf24 4ph",
    "addr:street":"Gwennyth Street",
    "iso:country":"GB",
    "sg:address":"28a Gwennyth Street, Cathays",
    "sg:city":"Cardiff",
    "sg:classifiers":[
        {
            "category":"Retail",
            "subcategory":"Auto Repair",
            "type":"Services"
        }
    ],
    "sg:postcode":"CF24 4PH",
    "sg:province":"Cardiff",
    "sg:tags":[
        "modification",
        "garage"
    ],
    "wof:name":"Ferris Bros Motor Engineers",
    "wof:placetype":"venue"
},
  "geometry": {"coordinates":[-3.175962925,51.4978752136],"type":"Point"}
}