{
  "type": "Feature",
  "properties": {
    "addr:full":"26 St Marks Road Mitcham Greater London CR4 2LF",
    "addr:housenumber":"26",
    "addr:postcode":"cr4 2lf",
    "addr:street":"St Marks Road",
    "iso:country":"GB",
    "sg:address":"26 St Marks Road",
    "sg:city":"Mitcham",
    "sg:classifiers":[
        {
            "category":"Organizations",
            "subcategory":"Community Association",
            "type":"Services"
        },
        {
            "category":"Organizations",
            "subcategory":"Membership Organization",
            "type":"Services"
        }
    ],
    "sg:phone":"+44 20 8648 3222",
    "sg:postcode":"CR4 2LF",
    "sg:province":"Greater London",
    "sg:tags":[
        "club",
        "social"
    ],
    "wof:name":"The Royal British Legion",
    "wof:placetype":"venue"
},
  "geometry": {"coordinates":[-0.159995,51.406528],"type":"Point"}
}