{
  "type": "Feature",
  "properties": {
    "iso:country":"GB",
    "sg:address":"33 Lehar Close",
    "sg:city":"Basingstoke",
    "sg:classifiers":[
        {
            "category":"Retail",
            "subcategory":"Storage",
            "type":"Services"
        }
    ],
    "sg:phone":"+44 1256 475331",
    "sg:postcode":"RG22 4HT",
    "sg:province":"Hampshire",
    "sg:tags":[
        "household",
        "removal"
    ],
    "wof:name":"Dolton's Removals",
    "wof:placetype":"venue"
},
  "geometry": {"coordinates":[-1.116799,51.243656],"type":"Point"}
}