{
  "type": "Feature",
  "properties": {
    "addr:full":"16 Ledborough Wood Beaconsfield Buckinghamshire HP9 2DJ",
    "addr:housenumber":"16",
    "addr:postcode":"hp9 2dj",
    "addr:street":"Ledborough Wood",
    "iso:country":"GB",
    "sg:address":"16 Ledborough Wood",
    "sg:city":"Beaconsfield",
    "sg:classifiers":[
        {
            "category":"Social Services",
            "subcategory":"Job Training",
            "type":"Services"
        }
    ],
    "sg:phone":"+44 1494 681631",
    "sg:postcode":"HP9 2DJ",
    "sg:province":"Buckinghamshire",
    "sg:tags":[
        "translator",
        "interpreter"
    ],
    "wof:name":"VIETNAM TRAVEL",
    "wof:placetype":"venue"
},
  "geometry": {"coordinates":[-0.638919,51.615978],"type":"Point"}
}