{
  "type": "Feature",
  "properties": {
    "addr:full":"11 Park Parade Havant Hampshire PO9 5AA",
    "addr:housenumber":"11",
    "addr:postcode":"po9 5aa",
    "addr:street":"Park Parade",
    "iso:country":"GB",
    "sg:address":"11 Park Parade",
    "sg:city":"Havant",
    "sg:classifiers":[
        {
            "category":"Fast Food",
            "type":"Food & Drink"
        }
    ],
    "sg:phone":"+44 23 9247 2681",
    "sg:postcode":"PO9 5AA",
    "sg:province":"Hampshire",
    "sg:tags":[
        "away",
        "meal",
        "outlet",
        "take"
    ],
    "wof:name":"Leigh Park Kebab House",
    "wof:placetype":"venue"
},
  "geometry": {"coordinates":[-0.9860889912,50.8661384583],"type":"Point"}
}