{
  "type": "Feature",
  "properties": {
    "iso:country":"GB",
    "sg:address":"Worthington Way",
    "sg:city":"Wigan",
    "sg:classifiers":[
        {
            "category":"Food & Beverages",
            "subcategory":"Supermarket",
            "type":"Retail Goods"
        }
    ],
    "sg:phone":"+44 1942 321966",
    "sg:postcode":"WN3 6XE",
    "sg:province":"Lancashire",
    "wof:name":"Sainsburys J PLC",
    "wof:placetype":"venue"
},
  "geometry": {"coordinates":[-2.6538341045,53.5196113586],"type":"Point"}
}