{
  "type": "Feature",
  "properties": {
    "addr:full":"2100 The Crescent, Birmingham Business Park Birmingham West Midlands B37 7YE",
    "addr:housenumber":"2100",
    "addr:postcode":"b37 7ye",
    "addr:street":"The Crescent;Business Park",
    "iso:country":"GB",
    "sg:address":"2100 The Crescent, Birmingham Business Park",
    "sg:city":"Birmingham",
    "sg:classifiers":[
        {
            "category":"Retail",
            "subcategory":"Auto Repair",
            "type":"Services"
        }
    ],
    "sg:phone":"+44 121 717 0007",
    "sg:postcode":"B37 7YE",
    "sg:province":"West Midlands",
    "sg:tags":[
        "car",
        "servicing",
        "radiator"
    ],
    "wof:name":"Serck Marston",
    "wof:placetype":"venue"
},
  "geometry": {"coordinates":[-1.718,52.470783],"type":"Point"}
}