{
  "type": "Feature",
  "properties": {
    "iso:country":"GB",
    "sg:address":"Baltic Road",
    "sg:city":"Stockton-on-tees",
    "sg:classifiers":[
        {
            "category":"Organizations",
            "subcategory":"Membership Organization",
            "type":"Services"
        }
    ],
    "sg:phone":"+44 1642 676887",
    "sg:postcode":"TS18 2EZ",
    "sg:province":"Durham",
    "sg:tags":[
        "club"
    ],
    "wof:name":"The Cons Club",
    "wof:placetype":"venue"
},
  "geometry": {"coordinates":[-1.306884,54.569172],"type":"Point"}
}