{
  "type": "Feature",
  "properties": {
    "addr:full":"45 High Street Bristol City of Bristol BS1 2AZ",
    "addr:housenumber":"45",
    "addr:postcode":"bs1 2az",
    "addr:street":"High Street",
    "iso:country":"GB",
    "sg:address":"45 High Street",
    "sg:city":"Bristol",
    "sg:classifiers":[
        {
            "category":"Shopping",
            "subcategory":"News",
            "type":"Retail Goods"
        }
    ],
    "sg:phone":"+44 117 926 4836",
    "sg:postcode":"BS1 2AZ",
    "sg:province":"City of Bristol",
    "sg:tags":[
        "newsagent"
    ],
    "wof:name":"A & Z News",
    "wof:placetype":"venue"
},
  "geometry": {"coordinates":[-2.59289,51.454659],"type":"Point"}
}