{
  "type": "Feature",
  "properties": {
    "addr:full":"Grange Farm Avenue Felixstowe Suffolk IP11 2FB",
    "addr:postcode":"ip11 2fb",
    "addr:street":"Farm Avenue",
    "iso:country":"GB",
    "sg:address":"Grange Farm Avenue",
    "sg:city":"Felixstowe",
    "sg:classifiers":[
        {
            "category":"Health Services",
            "subcategory":"Doctor",
            "type":"Services"
        },
        {
            "category":"Health Services",
            "subcategory":"Clinic",
            "type":"Services"
        }
    ],
    "sg:phone":"+44 1394 670107",
    "sg:postcode":"IP11 2FB",
    "sg:province":"Suffolk",
    "sg:tags":[
        "practitioners",
        "private"
    ],
    "wof:name":"Haven Health",
    "wof:placetype":"venue"
},
  "geometry": {"coordinates":[1.329774,51.968697],"type":"Point"}
}