{
  "type": "Feature",
  "properties": {
    "addr:full":"30 Station Street Pudsey West Yorkshire LS28 8PR",
    "addr:housenumber":"30",
    "addr:postcode":"ls28 8pr",
    "addr:street":"Station Street",
    "iso:country":"GB",
    "sg:address":"30 Station Street",
    "sg:city":"Pudsey",
    "sg:classifiers":[
        {
            "category":"Bars & Pubs",
            "type":"Food & Drink"
        }
    ],
    "sg:phone":"+44 113 256 4085",
    "sg:postcode":"LS28 8PR",
    "sg:province":"West Yorkshire",
    "sg:tags":[
        "pubs",
        "inn"
    ],
    "wof:name":"Longman Leisure Ltd.",
    "wof:placetype":"venue"
},
  "geometry": {"coordinates":[-1.66896,53.790215],"type":"Point"}
}