{
  "type": "Feature",
  "properties": {
    "addr:full":"36 Thornhill Banbury Northamptonshire OX17 2JQ",
    "addr:housenumber":"36",
    "addr:postcode":"ox17 2jq",
    "addr:street":"Thornhill",
    "iso:country":"GB",
    "sg:address":"36 Thornhill",
    "sg:city":"Banbury",
    "sg:classifiers":[
        {
            "category":"Communications",
            "subcategory":"Film & Video Production",
            "type":"Services"
        }
    ],
    "sg:phone":"+44 1295 711661",
    "sg:postcode":"OX17 2JQ",
    "sg:province":"Northamptonshire",
    "sg:tags":[
        "pr",
        "telemarketing"
    ],
    "wof:name":"Impact Teleservices",
    "wof:placetype":"venue"
},
  "geometry": {"coordinates":[-1.2785439491,52.0899276733],"type":"Point"}
}