{
  "type": "Feature",
  "properties": {
    "addr:full":"62 Packhorse Road Gerrards Cross Buckinghamshire SL9 8EF",
    "addr:housenumber":"62",
    "addr:postcode":"sl9 8ef",
    "addr:street":"Packhorse Road",
    "iso:country":"GB",
    "sg:address":"62 Packhorse Road",
    "sg:city":"Gerrards Cross",
    "sg:classifiers":[
        {
            "category":"Real Estate",
            "subcategory":"Developer",
            "type":"Services"
        }
    ],
    "sg:phone":"+44 1753 893991",
    "sg:postcode":"SL9 8EF",
    "sg:province":"Buckinghamshire",
    "sg:tags":[
        "property"
    ],
    "wof:name":"Cathedral Homes (U K) Ltd.",
    "wof:placetype":"venue"
},
  "geometry": {"coordinates":[-0.551997,51.589035],"type":"Point"}
}