{
  "type": "Feature",
  "properties": {
    "addr:full":"25 Ditchling Rise, Beaconfields Workshops Brighton East Sussex BN1 4QL",
    "addr:housenumber":"25",
    "addr:postcode":"bn1 4ql",
    "addr:street":"Ditchling Rise",
    "iso:country":"GB",
    "sg:address":"25 Ditchling Rise, Beaconfields Workshops",
    "sg:city":"Brighton",
    "sg:classifiers":[
        {
            "category":"Shopping",
            "subcategory":"Antiques",
            "type":"Retail Goods"
        }
    ],
    "sg:phone":"+44 1273 628686",
    "sg:postcode":"BN1 4QL",
    "sg:province":"East Sussex",
    "wof:name":"The Hanoverian Workshop",
    "wof:placetype":"venue"
},
  "geometry": {"coordinates":[-0.1403030008,50.8354263306],"type":"Point"}
}