{
  "type": "Feature",
  "properties": {
    "addr:full":"286 Shooters Hill Road London Greater London SE18 4LT",
    "addr:housenumber":"286",
    "addr:postcode":"se18 4lt",
    "addr:street":"Shooters Hill Road",
    "iso:country":"GB",
    "sg:address":"286 Shooters Hill Road",
    "sg:city":"London",
    "sg:classifiers":[
        {
            "category":"Bars & Pubs",
            "type":"Food & Drink"
        }
    ],
    "sg:phone":"+44 20 8856 5518",
    "sg:postcode":"SE18 4LT",
    "sg:province":"Greater London",
    "sg:tags":[
        "pubs",
        "inn"
    ],
    "wof:name":"Fox under the Hill",
    "wof:placetype":"venue"
},
  "geometry": {"coordinates":[0.039171,51.473927],"type":"Point"}
}