{
  "type": "Feature",
  "properties": {
    "addr:full":"298 Norton Road Stockton-on-tees Durham TS20 2BX",
    "addr:housenumber":"298",
    "addr:postcode":"ts20 2bx",
    "addr:street":"Norton Road",
    "iso:country":"GB",
    "sg:address":"298 Norton Road",
    "sg:city":"Stockton-on-tees",
    "sg:classifiers":[
        {
            "category":"Real Estate",
            "subcategory":"Architect",
            "type":"Services"
        }
    ],
    "sg:phone":"+44 1642 888050",
    "sg:postcode":"TS20 2BX",
    "sg:province":"Durham",
    "sg:tags":[
        "architectural"
    ],
    "wof:name":"Cleveland Architectural Design",
    "wof:placetype":"venue"
},
  "geometry": {"coordinates":[-1.3109799623,54.5795249939],"type":"Point"}
}