{
  "type": "Feature",
  "properties": {
    "addr:full":"Longwood Gate Huddersfield West Yorkshire HD3 4UP",
    "addr:postcode":"hd3 4up",
    "addr:street":"Longwood Gate",
    "iso:country":"GB",
    "sg:address":"Longwood Gate",
    "sg:city":"Huddersfield",
    "sg:classifiers":[
        {
            "category":"Health Services",
            "subcategory":"Nursing And Care Facility",
            "type":"Services"
        }
    ],
    "sg:phone":"+44 1484 647276",
    "sg:postcode":"HD3 4UP",
    "sg:province":"West Yorkshire",
    "sg:tags":[
        "home"
    ],
    "wof:name":"Longwood Grange Nursing Home",
    "wof:placetype":"venue"
},
  "geometry": {"coordinates":[-1.8427330256,53.6505126953],"type":"Point"}
}