{
  "type": "Feature",
  "properties": {
    "addr:full":"Oakland House, Millhayes Road Stoke-on-trent Staffordshire ST8 7PR",
    "addr:postcode":"st8 7pr",
    "addr:street":"Millhayes Road",
    "iso:country":"GB",
    "sg:address":"Oakland House, Millhayes Road",
    "sg:city":"Stoke-on-trent",
    "sg:classifiers":[
        {
            "category":"Building & Trades",
            "subcategory":"Construction",
            "type":"Services"
        }
    ],
    "sg:postcode":"ST8 7PR",
    "sg:province":"Staffordshire",
    "sg:tags":[
        "valve"
    ],
    "wof:name":"Kee Valves Ltd.",
    "wof:placetype":"venue"
},
  "geometry": {"coordinates":[-2.164527,53.105251],"type":"Point"}
}