{
  "type": "Feature",
  "properties": {
    "addr:full":"Intergrated Care House, 67-69 St Johns Road Isleworth Greater London TW7 6NL",
    "addr:housenumber":"67-69",
    "addr:postcode":"tw7 6nl",
    "addr:street":"St Johns Road",
    "iso:country":"GB",
    "sg:address":"Intergrated Care House, 67-69 St Johns Road",
    "sg:city":"Isleworth",
    "sg:classifiers":[
        {
            "category":"Social Services",
            "subcategory":"Child Care",
            "type":"Services"
        },
        {
            "category":"Social Services",
            "subcategory":"Retirement Home",
            "type":"Services"
        }
    ],
    "sg:postcode":"TW7 6NL",
    "sg:province":"Greater London",
    "sg:tags":[
        "children's",
        "residential"
    ],
    "wof:name":"Integrated Care Ltd.",
    "wof:placetype":"venue"
},
  "geometry": {"coordinates":[-0.337112993,51.47240448],"type":"Point"}
}