{
  "type": "Feature",
  "properties": {
    "iso:country":"GB",
    "sg:address":"21 Carlton Street",
    "sg:city":"Castleford",
    "sg:classifiers":[
        {
            "category":"Home & Garden",
            "subcategory":"Home Furnishings",
            "type":"Retail Goods"
        }
    ],
    "sg:phone":"+44 1977 554532",
    "sg:postcode":"WF10 1AX",
    "sg:province":"West Yorkshire",
    "sg:tags":[
        "blind",
        "curtain",
        "fitting"
    ],
    "wof:name":"Louis Curtain House",
    "wof:placetype":"venue"
},
  "geometry": {"coordinates":[-1.349513,53.726547],"type":"Point"}
}