{
  "type": "Feature",
  "properties": {
    "addr:full":"2 The Hermitage, High Street Ascot Berkshire SL5 7HD",
    "addr:housenumber":"2",
    "addr:postcode":"sl5 7hd",
    "addr:street":"The Hermitage High Street",
    "iso:country":"GB",
    "sg:address":"2 The Hermitage, High Street",
    "sg:city":"Ascot",
    "sg:classifiers":[
        {
            "category":"Personal",
            "subcategory":"Beauty Salon",
            "type":"Services"
        }
    ],
    "sg:phone":"+44 1344 626026",
    "sg:postcode":"SL5 7HD",
    "sg:province":"Berkshire",
    "sg:tags":[
        "unisex",
        "hairdresser"
    ],
    "wof:name":"New Concept Hair Team Ltd.",
    "wof:placetype":"venue"
},
  "geometry": {"coordinates":[-0.6737939715,51.4106750488],"type":"Point"}
}