{
  "type": "Feature",
  "properties": {
    "addr:full":"98 Pontygwindy Rd Caerphilly Caerphilly CF83 3HA",
    "addr:housenumber":"98",
    "addr:postcode":"cf83 3ha",
    "addr:street":"Pontygwindy Rd",
    "iso:country":"GB",
    "sg:address":"98 Pontygwindy Rd",
    "sg:city":"Caerphilly",
    "sg:classifiers":[
        {
            "category":"Personal",
            "subcategory":"Beauty Salon",
            "type":"Services"
        }
    ],
    "sg:phone":"+44 29 2086 8207",
    "sg:postcode":"CF83 3HA",
    "sg:province":"Caerphilly",
    "sg:tags":[
        "unisex",
        "hairdresser"
    ],
    "wof:name":"Sculpture Hairdressing",
    "wof:placetype":"venue"
},
  "geometry": {"coordinates":[-3.2190029621,51.5819358826],"type":"Point"}
}