{
  "type": "Feature",
  "properties": {
    "addr:full":"5 Crookes Road, Broomhill Sheffield South Yorkshire S10 5BA",
    "addr:housenumber":"5",
    "addr:postcode":"s10 5ba",
    "addr:street":"Crookes Road",
    "iso:country":"GB",
    "sg:address":"5 Crookes Road, Broomhill",
    "sg:city":"Sheffield",
    "sg:classifiers":[
        {
            "category":"Fast Food",
            "type":"Food & Drink"
        }
    ],
    "sg:phone":"+44 114 266 3120",
    "sg:postcode":"S10 5BA",
    "sg:province":"South Yorkshire",
    "sg:tags":[
        "away",
        "take"
    ],
    "wof:name":"Kfc",
    "wof:placetype":"venue"
},
  "geometry": {"coordinates":[-1.501023,53.377853],"type":"Point"}
}