{
  "type": "Feature",
  "properties": {
    "addr:full":"26 Harley Ave, Bebington Wirral Merseyside CH63 5PZ",
    "addr:housenumber":"26",
    "addr:postcode":"ch63 5pz",
    "addr:street":"Harley Ave",
    "iso:country":"GB",
    "sg:address":"26 Harley Ave, Bebington",
    "sg:city":"Wirral",
    "sg:classifiers":[
        {
            "category":"Building & Trades",
            "subcategory":"Construction",
            "type":"Services"
        }
    ],
    "sg:phone":"+44 151 608 1391",
    "sg:postcode":"CH63 5PZ",
    "sg:province":"Merseyside",
    "sg:tags":[
        "flooring"
    ],
    "wof:name":"Wood J & Sons (Wirral)",
    "wof:placetype":"venue"
},
  "geometry": {"coordinates":[-3.0321750641,53.3654899597],"type":"Point"}
}