{
  "type": "Feature",
  "properties": {
    "addr:full":"5a Abercrombie Street Chesterfield Derbyshire S41 7LW",
    "addr:housenumber":"5a",
    "addr:postcode":"s41 7lw",
    "addr:street":"Abercrombie Street",
    "iso:country":"GB",
    "sg:address":"5a Abercrombie Street",
    "sg:city":"Chesterfield",
    "sg:classifiers":[
        {
            "category":"Organizations",
            "subcategory":"Membership Organization",
            "type":"Services"
        }
    ],
    "sg:phone":"+44 1246 208045",
    "sg:postcode":"S41 7LW",
    "sg:province":"Derbyshire",
    "sg:tags":[
        "club"
    ],
    "wof:name":"Chesterfield Operatic Society",
    "wof:placetype":"venue"
},
  "geometry": {"coordinates":[-1.428905,53.240932],"type":"Point"}
}