{
  "type": "Feature",
  "properties": {
    "addr:full":"2 Church Rd Aldershot Hampshire GU11 3PS",
    "addr:housenumber":"2",
    "addr:postcode":"gu11 3ps",
    "addr:street":"Church Rd",
    "iso:country":"GB",
    "sg:address":"2 Church Rd",
    "sg:city":"Aldershot",
    "sg:classifiers":[
        {
            "category":"Home & Garden",
            "subcategory":"Garden Supply",
            "type":"Retail Goods"
        }
    ],
    "sg:postcode":"GU11 3PS",
    "sg:province":"Hampshire",
    "sg:tags":[
        "nursery",
        "centre"
    ],
    "wof:name":"Bennett,Ian,",
    "wof:placetype":"venue"
},
  "geometry": {"coordinates":[-0.752259016,51.2393836975],"type":"Point"}
}