{
  "type": "Feature",
  "properties": {
    "iso:country":"GB",
    "sg:address":"Crown Street Surgery, 17 Crown St",
    "sg:city":"Mexborough",
    "sg:classifiers":[
        {
            "category":"Health Services",
            "subcategory":"Doctor",
            "type":"Services"
        }
    ],
    "sg:phone":"+44 1709 583862",
    "sg:postcode":"S64 8NB",
    "sg:province":"South Yorkshire",
    "sg:tags":[
        "practitioners"
    ],
    "wof:name":"Ford, J B",
    "wof:placetype":"venue"
},
  "geometry": {"coordinates":[-1.299808979,53.4953536987],"type":"Point"}
}