{
  "type": "Feature",
  "properties": {
    "addr:full":"The Coach Station, Sharp Street, Worsley Manchester Greater Manchester M28 3LX",
    "addr:postcode":"m28 3lx",
    "addr:street":"Sharp Street",
    "iso:country":"GB",
    "sg:address":"The Coach Station, Sharp Street, Worsley",
    "sg:city":"Manchester",
    "sg:classifiers":[
        {
            "category":"Bus Charters",
            "type":"Transportation"
        }
    ],
    "sg:phone":"+44 161 799 9800",
    "sg:postcode":"M28 3LX",
    "sg:province":"Greater Manchester",
    "sg:tags":[
        "hire",
        "coach"
    ],
    "wof:name":"Chester's Coaches Ltd",
    "wof:placetype":"venue"
},
  "geometry": {"coordinates":[-2.38663,53.5242],"type":"Point"}
}