{
  "type": "Feature",
  "properties": {
    "addr:full":"7 Tammy Hall Street, Off Wood Street Wakefield West Yorkshire WF1 2SX",
    "addr:housenumber":"7",
    "addr:postcode":"wf1 2sx",
    "addr:street":"Tammy Hall Street Off Wood Street",
    "iso:country":"GB",
    "sg:address":"7 Tammy Hall Street, Off Wood Street",
    "sg:city":"Wakefield",
    "sg:classifiers":[
        {
            "category":"Manufacturing",
            "subcategory":"Printing",
            "type":"Manufacturing & Wholesale Goods"
        }
    ],
    "sg:postcode":"WF1 2SX",
    "sg:province":"West Yorkshire",
    "sg:tags":[
        "bookbinder"
    ],
    "wof:name":"R-Craft Bookbinding & Conservation",
    "wof:placetype":"venue"
},
  "geometry": {"coordinates":[-1.5010750294,53.6836738586],"type":"Point"}
}