{
  "type": "Feature",
  "properties": {
    "iso:country":"GB",
    "sg:address":"Titchmarsh Lodge, Sudborough",
    "sg:city":"Kettering",
    "sg:classifiers":[
        {
            "category":"Personal",
            "subcategory":"Tanning Parlor",
            "type":"Services"
        }
    ],
    "sg:postcode":"NN14 3BU",
    "sg:province":"Northamptonshire",
    "sg:tags":[
        "sunbeds"
    ],
    "wof:name":"Fourseasons Sunbeds",
    "wof:placetype":"venue"
},
  "geometry": {"coordinates":[-0.5787990093,52.4299850464],"type":"Point"}
}