{
  "type": "Feature",
  "properties": {
    "addr:full":"The Fabric Cabin, Market Pavement Basildon Essex SS14 1BH",
    "addr:postcode":"ss14 1bh",
    "addr:street":"Market Pavement",
    "iso:country":"GB",
    "sg:address":"The Fabric Cabin, Market Pavement",
    "sg:city":"Basildon",
    "sg:classifiers":[
        {
            "category":"Home & Garden",
            "subcategory":"Home Furnishings",
            "type":"Retail Goods"
        }
    ],
    "sg:postcode":"SS14 1BH",
    "sg:province":"Essex",
    "sg:tags":[
        "blind",
        "curtain",
        "fitting"
    ],
    "wof:name":"Jeannette Byworth",
    "wof:placetype":"venue"
},
  "geometry": {"coordinates":[0.4575299919,51.5696792603],"type":"Point"}
}