{
  "type": "Feature",
  "properties": {
    "iso:country":"GB",
    "sg:address":"Unit 1, 38 Roman Ridge Rd",
    "sg:city":"Sheffield",
    "sg:classifiers":[
        {
            "category":"Shopping",
            "subcategory":"Beauty & Cosmetics",
            "type":"Retail Goods"
        }
    ],
    "sg:phone":"+44 114 261 1612",
    "sg:postcode":"S9 1GB",
    "sg:province":"South Yorkshire",
    "sg:tags":[
        "equipment",
        "supply",
        "hairdressing"
    ],
    "wof:name":"Sally Hair & Beauty Supplies",
    "wof:placetype":"venue"
},
  "geometry": {"coordinates":[-1.420656,53.417381],"type":"Point"}
}