{
  "type": "Feature",
  "properties": {
    "addr:full":"3 Dayton Drive, Darenth Industrial Park, Off Wallhouse Road Erith Kent DA8 2LE",
    "addr:housenumber":"3",
    "addr:postcode":"da8 2le",
    "addr:street":"Dayton Drive Darenth Industrial Park Off Wallhouse Road",
    "iso:country":"GB",
    "sg:address":"3 Dayton Drive, Darenth Industrial Park, Off Wallhouse Road",
    "sg:city":"Erith",
    "sg:classifiers":[
        {
            "category":"Manufacturing",
            "subcategory":"Paper Products",
            "type":"Manufacturing & Wholesale Goods"
        }
    ],
    "sg:phone":"+44 1322 350555",
    "sg:postcode":"DA8 2LE",
    "sg:province":"Kent",
    "sg:tags":[
        "merchant",
        "waste"
    ],
    "wof:name":"Capital Waste Paper Ltd",
    "wof:placetype":"venue"
},
  "geometry": {"coordinates":[0.2107560039,51.4798049927],"type":"Point"}
}