{
  "type": "Feature",
  "properties": {
    "addr:full":"186 Victoria Road West, Cleveleys Thornton-cleveleys Lancashire FY5 3NG",
    "addr:housenumber":"186",
    "addr:postcode":"fy5 3ng",
    "addr:street":"Victoria Road West Cleveleys Thornton-Cleveleys",
    "iso:country":"GB",
    "sg:address":"186 Victoria Road West, Cleveleys",
    "sg:city":"Thornton-cleveleys",
    "sg:classifiers":[
        {
            "category":"Professional",
            "type":"Services"
        }
    ],
    "sg:phone":"+44 1253 829522",
    "sg:postcode":"FY5 3NG",
    "sg:province":"Lancashire",
    "sg:tags":[
        "interior",
        "furnishers",
        "designer"
    ],
    "wof:name":"Gail Hunt Interior Designs",
    "wof:placetype":"venue"
},
  "geometry": {"coordinates":[-3.0358428955,53.8761405945],"type":"Point"}
}