{
  "type": "Feature",
  "properties": {
    "addr:full":"60 Fore Street Cullompton Devon EX15 1LB",
    "addr:housenumber":"60",
    "addr:postcode":"ex15 1lb",
    "addr:street":"Fore Street",
    "iso:country":"GB",
    "sg:address":"60 Fore Street",
    "sg:city":"Cullompton",
    "sg:classifiers":[
        {
            "category":"Personal",
            "subcategory":"Beauty Salon",
            "type":"Services"
        }
    ],
    "sg:phone":"+44 1884 33313",
    "sg:postcode":"EX15 1LB",
    "sg:province":"Devon",
    "sg:tags":[
        "unisex",
        "hairdresser"
    ],
    "wof:name":"Haircraft",
    "wof:placetype":"venue"
},
  "geometry": {"coordinates":[-3.3927719593,50.8554077148],"type":"Point"}
}