{
  "type": "Feature",
  "properties": {
    "addr:full":"Neville House, 55 Eden Street Kingston-upon-thames Greater London KT1 1BW",
    "addr:housenumber":"55",
    "addr:postcode":"kt1 1bw",
    "addr:street":"Eden Street",
    "iso:country":"GB",
    "sg:address":"Neville House, 55 Eden Street",
    "sg:city":"Kingston-upon-thames",
    "sg:classifiers":[
        {
            "category":"Real Estate",
            "subcategory":"Surveying",
            "type":"Services"
        }
    ],
    "sg:phone":"+44 20 8549 5988",
    "sg:postcode":"KT1 1BW",
    "sg:province":"Greater London",
    "sg:tags":[
        "surveyor",
        "quantity"
    ],
    "wof:name":"Naismiths",
    "wof:placetype":"venue"
},
  "geometry": {"coordinates":[-0.3022840023,51.410533905],"type":"Point"}
}