{
  "type": "Feature",
  "properties": {
    "iso:country":"GB",
    "sg:address":"75 Tregundy Rd",
    "sg:city":"Perranporth",
    "sg:classifiers":[
        {
            "category":"Personal",
            "type":"Services"
        }
    ],
    "sg:phone":"+44 1872 573504",
    "sg:postcode":"TR6 0LL",
    "sg:province":"Cornwall",
    "sg:tags":[
        "wedding"
    ],
    "wof:name":"Take One Video Productions",
    "wof:placetype":"venue"
},
  "geometry": {"coordinates":[-5.162181,50.342857],"type":"Point"}
}