{
  "type": "Feature",
  "properties": {
    "iso:country":"GB",
    "sg:address":"Howard Town Mills",
    "sg:city":"Glossop",
    "sg:classifiers":[
        {
            "category":"Shopping",
            "subcategory":"Clothing, Apparel, & Fashions",
            "type":"Retail Goods"
        }
    ],
    "sg:phone":"+44 1457 861122",
    "sg:postcode":"SK13 8LR",
    "sg:province":"Derbyshire",
    "sg:tags":[
        "lingerie"
    ],
    "wof:name":"Bentwood Lingerie Ltd.",
    "wof:placetype":"venue"
},
  "geometry": {"coordinates":[-1.9465700388,53.4433364868],"type":"Point"}
}