{
  "type": "Feature",
  "properties": {
    "addr:full":"Unit 10 Orbital Retail Centre Cannock Staffordshire WS11 3XB",
    "addr:housenumber":"unit 10;retail",
    "addr:postcode":"ws11 3xb",
    "addr:street":"Orbital",
    "iso:country":"GB",
    "sg:address":"Unit 10 Orbital Retail Centre",
    "sg:city":"Cannock",
    "sg:classifiers":[
        {
            "category":"Shopping",
            "subcategory":"Mobile Phones",
            "type":"Retail Goods"
        }
    ],
    "sg:phone":"+44 1543 500784",
    "sg:postcode":"WS11 3XB",
    "sg:province":"Staffordshire",
    "wof:name":"DX Communications Ltd",
    "wof:placetype":"venue"
},
  "geometry": {"coordinates":[-2.018152,52.677441],"type":"Point"}
}