{
  "type": "Feature",
  "properties": {
    "iso:country":"GB",
    "sg:address":"1a The Crescent, West Kirby",
    "sg:city":"Wirral",
    "sg:classifiers":[
        {
            "category":"Shopping",
            "subcategory":"Jewelry",
            "type":"Retail Goods"
        },
        {
            "category":"Shopping",
            "subcategory":"Comic Books",
            "type":"Retail Goods"
        }
    ],
    "sg:phone":"+44 151 625 8491",
    "sg:postcode":"CH48 4HL",
    "sg:province":"Merseyside",
    "sg:tags":[
        "jeweller",
        "sale",
        "jewellery"
    ],
    "wof:name":"Crescent Jewellers",
    "wof:placetype":"venue"
},
  "geometry": {"coordinates":[-3.1845459938,53.3724136353],"type":"Point"}
}