{
  "type": "Feature",
  "properties": {
    "addr:full":"14 Fenlake Business Centre, Fengate Peterborough Cambridgeshire PE1 5BQ",
    "addr:housenumber":"14",
    "addr:postcode":"pe1 5bq",
    "addr:street":"Fenlake Business Centre",
    "iso:country":"GB",
    "sg:address":"14 Fenlake Business Centre, Fengate",
    "sg:city":"Peterborough",
    "sg:classifiers":[
        {
            "category":"Home & Garden",
            "subcategory":"Home Furnishings",
            "type":"Retail Goods"
        },
        {
            "category":"Building & Trades",
            "subcategory":"Landfill",
            "type":"Services"
        }
    ],
    "sg:phone":"+44 1733 894570",
    "sg:postcode":"PE1 5BQ",
    "sg:province":"Cambridgeshire",
    "sg:tags":[
        "blind",
        "awning",
        "canopy",
        "blinds"
    ],
    "wof:name":"FINISHING TOUCH",
    "wof:placetype":"venue"
},
  "geometry": {"coordinates":[-0.2209589928,52.5749130249],"type":"Point"}
}