{
  "type": "Feature",
  "properties": {
    "iso:country":"GB",
    "sg:address":"Unit F6 Waterside Road, Hamilton Business Park",
    "sg:city":"Leicester",
    "sg:classifiers":[
        {
            "category":"Manufacturing",
            "subcategory":"Buildings",
            "type":"Manufacturing & Wholesale Goods"
        }
    ],
    "sg:phone":"+44 116 222 1133",
    "sg:postcode":"LE5 1TL",
    "sg:province":"Leicestershire",
    "sg:tags":[
        "system",
        "air conditioning"
    ],
    "wof:name":"A1 Alpha Building Services (Leicester) Ltd.",
    "wof:placetype":"venue"
},
  "geometry": {"coordinates":[-1.0782289505,52.6599159241],"type":"Point"}
}