{
  "type": "Feature",
  "properties": {
    "iso:country":"GB",
    "sg:address":"22 Birmingham Road",
    "sg:city":"Sutton Coldfield",
    "sg:classifiers":[
        {
            "category":"Home & Garden",
            "subcategory":"Furniture",
            "type":"Retail Goods"
        }
    ],
    "sg:postcode":"B72 1QG",
    "sg:province":"West Midlands",
    "wof:name":"Kingswood",
    "wof:placetype":"venue"
},
  "geometry": {"coordinates":[-1.827014,52.558327],"type":"Point"}
}