{
  "type": "Feature",
  "properties": {
    "iso:country":"GB",
    "sg:address":"273 Kings Road, Kingstanding",
    "sg:city":"Birmingham",
    "sg:classifiers":[
        {
            "category":"Shopping",
            "subcategory":"News",
            "type":"Retail Goods"
        }
    ],
    "sg:phone":"+44 121 354 1514",
    "sg:postcode":"B44 0TE",
    "sg:province":"West Midlands",
    "sg:tags":[
        "newsagent"
    ],
    "wof:name":"Dillons Newsagents Ltd.",
    "wof:placetype":"venue"
},
  "geometry": {"coordinates":[-1.874037,52.550915],"type":"Point"}
}