{
  "type": "Feature",
  "properties": {
    "addr:full":"140 Bank Street Coatbridge North Lanarkshire ML5 1ET",
    "addr:housenumber":"140",
    "addr:postcode":"ml5 1et",
    "addr:street":"Bank Street",
    "iso:country":"GB",
    "sg:address":"140 Bank Street",
    "sg:city":"Coatbridge",
    "sg:classifiers":[
        {
            "category":"Communications",
            "subcategory":"Film & Video Production",
            "type":"Services"
        }
    ],
    "sg:phone":"+44 1236 436401",
    "sg:postcode":"ML5 1ET",
    "sg:province":"North Lanarkshire",
    "sg:tags":[
        "tv"
    ],
    "wof:name":"Videoland",
    "wof:placetype":"venue"
},
  "geometry": {"coordinates":[-4.037951,55.859737],"type":"Point"}
}