{
  "type": "Feature",
  "properties": {
    "addr:full":"85 Clayton Street Newcastle-upon-tyne Tyne and Wear NE1 5PY",
    "addr:housenumber":"85",
    "addr:postcode":"ne1 5py",
    "addr:street":"Clayton Street",
    "iso:country":"GB",
    "sg:address":"85 Clayton Street",
    "sg:city":"Newcastle-upon-tyne",
    "sg:classifiers":[
        {
            "category":"Travel",
            "subcategory":"Travel Agent",
            "type":"Entertainment"
        }
    ],
    "sg:phone":"+44 191 230 2240",
    "sg:postcode":"NE1 5PY",
    "sg:province":"Tyne and Wear",
    "sg:tags":[
        "agency",
        "activity"
    ],
    "wof:name":"CALLERS-PEGASUS TRAVEL SERVICE LTD",
    "wof:placetype":"venue"
},
  "geometry": {"coordinates":[-1.6173269749,54.9713439941],"type":"Point"}
}