{
  "type": "Feature",
  "properties": {
    "iso:country":"GB",
    "sg:address":"3 Ambassador Ho, Wolseley Rd",
    "sg:city":"Harrow",
    "sg:classifiers":[
        {
            "category":"Building & Trades",
            "subcategory":"Construction",
            "type":"Services"
        }
    ],
    "sg:postcode":"HA3 5RT",
    "sg:province":"Greater London",
    "sg:tags":[
        "builder",
        "restoration",
        "refurbishment"
    ],
    "wof:name":"Brent Interiors Ltd",
    "wof:placetype":"venue"
},
  "geometry": {"coordinates":[-0.3361099958,51.5954704285],"type":"Point"}
}