{
  "type": "Feature",
  "properties": {
    "addr:full":"Fir Tree Farm, Swettenham Heath Congleton Cheshire CW12 2LW",
    "addr:postcode":"cw12 2lw",
    "iso:country":"GB",
    "sg:address":"Fir Tree Farm, Swettenham Heath",
    "sg:city":"Congleton",
    "sg:classifiers":[
        {
            "category":"Farming",
            "subcategory":"Livestock Farm",
            "type":"Manufacturing & Wholesale Goods"
        },
        {
            "category":"Farming",
            "subcategory":"Farm",
            "type":"Manufacturing & Wholesale Goods"
        }
    ],
    "sg:phone":"+44 1477 571286",
    "sg:postcode":"CW12 2LW",
    "sg:province":"Cheshire",
    "sg:tags":[
        "mixed",
        "others"
    ],
    "wof:name":"John M Dingle",
    "wof:placetype":"venue"
},
  "geometry": {"coordinates":[-2.296613,53.202648],"type":"Point"}
}