{
  "type": "Feature",
  "properties": {
    "iso:country":"GB",
    "sg:address":"Texa Bldgs, Main St",
    "sg:city":"Isle Of Mull",
    "sg:classifiers":[
        {
            "category":"Food & Beverages",
            "subcategory":"Meat & Fish",
            "type":"Retail Goods"
        }
    ],
    "sg:postcode":"PA75 6NT",
    "sg:province":"Argyll and Bute",
    "sg:tags":[
        "butcher"
    ],
    "wof:name":"Hughes,R & J,",
    "wof:placetype":"venue"
},
  "geometry": {"coordinates":[-6.0645051003,56.623210907],"type":"Point"}
}