{
  "type": "Feature",
  "properties": {
    "addr:full":"143a High Street, Norton Stockton-on-tees Durham TS20 1AA",
    "addr:housenumber":"143a",
    "addr:postcode":"ts20 1aa",
    "addr:street":"High Street",
    "iso:country":"GB",
    "sg:address":"143a High Street, Norton",
    "sg:city":"Stockton-on-tees",
    "sg:classifiers":[
        {
            "category":"Shopping",
            "subcategory":"Florist",
            "type":"Retail Goods"
        }
    ],
    "sg:postcode":"TS20 1AA",
    "sg:province":"Durham",
    "wof:name":"Jennifer Pinder Florists",
    "wof:placetype":"venue"
},
  "geometry": {"coordinates":[-1.3125599623,54.5915641785],"type":"Point"}
}