{
  "type": "Feature",
  "properties": {
    "iso:country":"GB",
    "sg:address":"8 Rowcroft, Stroud",
    "sg:city":"Gloucester",
    "sg:classifiers":[
        {
            "category":"Professional",
            "subcategory":"Business Services",
            "type":"Services"
        }
    ],
    "sg:phone":"+44 1453 752151",
    "sg:postcode":"GL5 3AZ",
    "sg:province":"Gloucestershire",
    "sg:tags":[
        "holding"
    ],
    "wof:name":"Capecroft Ltd.",
    "wof:placetype":"venue"
},
  "geometry": {"coordinates":[-2.219381,51.745243],"type":"Point"}
}