{
  "type": "Feature",
  "properties": {
    "iso:country":"GB",
    "sg:address":"Unit 1 38 Midland Road, Staple Hill",
    "sg:city":"Bristol",
    "sg:classifiers":[
        {
            "category":"Professional",
            "subcategory":"Business Services",
            "type":"Services"
        }
    ],
    "sg:phone":"+44 117 957 3355",
    "sg:postcode":"BS16 4NW",
    "sg:province":"City of Bristol",
    "sg:tags":[
        "planning",
        "design"
    ],
    "wof:name":"McFeggan Brown Ltd.",
    "wof:placetype":"venue"
},
  "geometry": {"coordinates":[-2.510329,51.478638],"type":"Point"}
}