{
  "type": "Feature",
  "properties": {
    "addr:full":"36 Pipers Row Wolverhampton West Midlands WV1 3JY",
    "addr:housenumber":"36",
    "addr:postcode":"wv1 3jy",
    "addr:street":"Pipers Row",
    "iso:country":"GB",
    "sg:address":"36 Pipers Row",
    "sg:city":"Wolverhampton",
    "sg:classifiers":[
        {
            "category":"Restaurant",
            "type":"Food & Drink"
        }
    ],
    "sg:phone":"+44 1902 772977",
    "sg:postcode":"WV1 3JY",
    "sg:province":"West Midlands",
    "sg:tags":[
        "american"
    ],
    "wof:name":"Luminar Plc",
    "wof:placetype":"venue"
},
  "geometry": {"coordinates":[-2.123112,52.585667],"type":"Point"}
}