{
  "type": "Feature",
  "properties": {
    "addr:full":"Pencroft Business Centre Farnham Hampshire GU10 5PX",
    "addr:postcode":"gu10 5px",
    "addr:street":"Farnham",
    "iso:country":"GB",
    "sg:address":"Pencroft Business Centre",
    "sg:city":"Farnham",
    "sg:classifiers":[
        {
            "category":"Social Services",
            "subcategory":"Job Training",
            "type":"Services"
        }
    ],
    "sg:phone":"+44 1252 852400",
    "sg:postcode":"GU10 5PX",
    "sg:province":"Hampshire",
    "sg:tags":[
        "draughtsman",
        "drawing"
    ],
    "wof:name":"Euro-cad",
    "wof:placetype":"venue"
},
  "geometry": {"coordinates":[-0.8008300066,51.2143211365],"type":"Point"}
}