{
  "type": "Feature",
  "properties": {
    "iso:country":"GB",
    "sg:address":"8 Honeycomb Close, Narborough",
    "sg:city":"Leicester",
    "sg:classifiers":[
        {
            "category":"Health Services",
            "subcategory":"Podiatrist",
            "type":"Services"
        }
    ],
    "sg:phone":"+44 116 286 4435",
    "sg:postcode":"LE19 3PS",
    "sg:province":"Leicestershire",
    "sg:tags":[
        "podiatrists",
        "chiropodist"
    ],
    "wof:name":"Rachael Mellor",
    "wof:placetype":"venue"
},
  "geometry": {"coordinates":[-1.2151960135,52.5761413574],"type":"Point"}
}