{
  "type": "Feature",
  "properties": {
    "iso:country":"GB",
    "sg:address":"4 Derwen Road",
    "sg:city":"Bridgend",
    "sg:classifiers":[
        {
            "category":"Home & Garden",
            "subcategory":"Household Appliances",
            "type":"Retail Goods"
        }
    ],
    "sg:phone":"+44 1656 669566",
    "sg:postcode":"CF31 1LH",
    "sg:province":"Bridgend",
    "sg:tags":[
        "electrical"
    ],
    "wof:name":"The Repair Shop Ltd.",
    "wof:placetype":"venue"
},
  "geometry": {"coordinates":[-3.576655,51.506531],"type":"Point"}
}