{
  "type": "Feature",
  "properties": {
    "addr:full":"Bankside, Old Town Hill, Lamberhurst Tunbridge Wells East Sussex TN3 8EN",
    "addr:postcode":"tn3 8en",
    "addr:street":"Bankside",
    "iso:country":"GB",
    "sg:address":"Bankside, Old Town Hill, Lamberhurst",
    "sg:city":"Tunbridge Wells",
    "sg:classifiers":[
        {
            "category":"Transit Center",
            "subcategory":"Passenger",
            "type":"Transportation"
        }
    ],
    "sg:phone":"+44 1892 890485",
    "sg:postcode":"TN3 8EN",
    "sg:province":"East Sussex",
    "sg:tags":[
        "boarding",
        "kennel",
        "catteries"
    ],
    "wof:name":"Moggs",
    "wof:placetype":"venue"
},
  "geometry": {"coordinates":[0.3910849988,51.0999031067],"type":"Point"}
}