{
  "type": "Feature",
  "properties": {
    "addr:full":"284 Sandbanks Road Poole Dorset BH14 8HU",
    "addr:housenumber":"284",
    "addr:postcode":"bh14 8hu",
    "addr:street":"Sandbanks Road",
    "iso:country":"GB",
    "sg:address":"284 Sandbanks Road",
    "sg:city":"Poole",
    "sg:classifiers":[
        {
            "category":"Recreation",
            "subcategory":"Water Park",
            "type":"Entertainment"
        },
        {
            "category":"Education",
            "subcategory":"School",
            "type":"Public Place"
        }
    ],
    "sg:phone":"+44 1202 700503",
    "sg:postcode":"BH14 8HU",
    "sg:province":"Dorset",
    "sg:tags":[
        "sport",
        "local",
        "authority"
    ],
    "wof:name":"Poole Harbour Boardsailing",
    "wof:placetype":"venue"
},
  "geometry": {"coordinates":[-1.9454090595,50.7080383301],"type":"Point"}
}