{
  "type": "Feature",
  "properties": {
    "addr:full":"106-108 Audley Road London Greater London NW4 3HG",
    "addr:housenumber":"106-108",
    "addr:postcode":"nw4 3hg",
    "addr:street":"Audley Road",
    "iso:country":"GB",
    "sg:address":"106-108 Audley Road",
    "sg:city":"London",
    "sg:classifiers":[
        {
            "category":"Shopping",
            "subcategory":"Comic Books",
            "type":"Retail Goods"
        },
        {
            "category":"Social Services",
            "subcategory":"Retirement Home",
            "type":"Services"
        }
    ],
    "sg:postcode":"NW4 3HG",
    "sg:province":"Greater London",
    "sg:tags":[
        "residential",
        "jeweller",
        "care"
    ],
    "wof:name":"A Young",
    "wof:placetype":"venue"
},
  "geometry": {"coordinates":[-0.2332559973,51.5809783936],"type":"Point"}
}