{
  "type": "Feature",
  "properties": {
    "iso:country":"GB",
    "sg:address":"175 St Neots Rd, Hardwick",
    "sg:city":"Cambridge",
    "sg:classifiers":[
        {
            "category":"Shopping",
            "subcategory":"Pets & Pet Supplies",
            "type":"Retail Goods"
        }
    ],
    "sg:phone":"+44 1954 212187",
    "sg:postcode":"CB3 7QJ",
    "sg:province":"Cambridgeshire",
    "wof:name":"Keep Reptiles",
    "wof:placetype":"venue"
},
  "geometry": {"coordinates":[0.010795,52.217701],"type":"Point"}
}