{
  "type": "Feature",
  "properties": {
    "addr:full":"52a Preston New Rd Blackburn Lancashire BB2 6AH",
    "addr:housenumber":"52a",
    "addr:postcode":"bb2 6ah",
    "addr:street":"Preston New Rd",
    "iso:country":"GB",
    "sg:address":"52a Preston New Rd",
    "sg:city":"Blackburn",
    "sg:classifiers":[
        {
            "category":"Professional",
            "subcategory":"Accounting & Tax Preparation",
            "type":"Services"
        }
    ],
    "sg:phone":"+44 1254 674222",
    "sg:postcode":"BB2 6AH",
    "sg:province":"Lancashire",
    "sg:tags":[
        "accountant"
    ],
    "wof:name":"Kidsons Impey",
    "wof:placetype":"venue"
},
  "geometry": {"coordinates":[-2.4892659187,53.7520523071],"type":"Point"}
}