{
  "type": "Feature",
  "properties": {
    "addr:full":"West End Lane London Greater London NW6 1XJ",
    "addr:postcode":"nw6 1xj",
    "addr:street":"West End Lane",
    "iso:country":"GB",
    "sg:address":"West End Lane",
    "sg:city":"London",
    "sg:classifiers":[
        {
            "category":"Food & Beverages",
            "subcategory":"Liquor & Beverages",
            "type":"Retail Goods"
        }
    ],
    "sg:phone":"+44 20 7794 9766",
    "sg:postcode":"NW6 1XJ",
    "sg:province":"Greater London",
    "sg:tags":[
        "beer",
        "spirit",
        "wines"
    ],
    "wof:name":"Oddbins Ltd.",
    "wof:placetype":"venue"
},
  "geometry": {"coordinates":[-0.19117,51.548569],"type":"Point"}
}