{
  "type": "Feature",
  "properties": {
    "iso:country":"GB",
    "sg:address":"24 Great King Street",
    "sg:city":"Edinburgh",
    "sg:classifiers":[
        {
            "category":"Professional",
            "subcategory":"Printing & Photocopies",
            "type":"Services"
        }
    ],
    "sg:phone":"+44 131 653 1308",
    "sg:postcode":"EH3 6QN",
    "sg:province":"City of Edinburgh",
    "sg:tags":[
        "printer"
    ],
    "wof:name":"Palm Printing Ltd.",
    "wof:placetype":"venue"
},
  "geometry": {"coordinates":[-3.198188,55.958191],"type":"Point"}
}