{
  "type": "Feature",
  "properties": {
    "addr:full":"The Cottage, Rheda Frizington Cumbria CA26 3TE",
    "addr:postcode":"ca26 3te",
    "iso:country":"GB",
    "sg:address":"The Cottage, Rheda",
    "sg:city":"Frizington",
    "sg:classifiers":[
        {
            "category":"Building & Trades",
            "subcategory":"Construction",
            "type":"Services"
        }
    ],
    "sg:phone":"+44 1946 810429",
    "sg:postcode":"CA26 3TE",
    "sg:province":"Cumbria",
    "sg:tags":[
        "joiner",
        "carpenter"
    ],
    "wof:name":"Fred Smithyes Graham",
    "wof:placetype":"venue"
},
  "geometry": {"coordinates":[-3.4941239357,54.541431427],"type":"Point"}
}