{
  "type": "Feature",
  "properties": {
    "addr:full":"1-1a St Martins Industrial Estate, Tat, Bank Road Oldbury West Midlands B69 4NP",
    "addr:housenumber":"1-1a",
    "addr:postcode":"b69 4np",
    "addr:street":"St Martins Industrial Estate Tat Bank Road",
    "iso:country":"GB",
    "sg:address":"1-1a St Martins Industrial Estate, Tat, Bank Road",
    "sg:city":"Oldbury",
    "sg:classifiers":[
        {
            "category":"Retail",
            "subcategory":"Event Space",
            "type":"Services"
        },
        {
            "category":"Shopping",
            "subcategory":"Computers & Home Electronics",
            "type":"Retail Goods"
        }
    ],
    "sg:phone":"+44 121 541 1315",
    "sg:postcode":"B69 4NP",
    "sg:province":"West Midlands",
    "sg:tags":[
        "product",
        "electrical",
        "sales"
    ],
    "wof:name":"Flameproof Electrical Enclosures Ltd.",
    "wof:placetype":"venue"
},
  "geometry": {"coordinates":[-2.015845,52.503777],"type":"Point"}
}