{
  "type": "Feature",
  "properties": {
    "iso:country":"GB",
    "sg:address":"Unit 2 Dragoon Court, Hillsborough Barracks",
    "sg:city":"Sheffield",
    "sg:classifiers":[
        {
            "category":"Professional",
            "subcategory":"Computer Services",
            "type":"Services"
        }
    ],
    "sg:phone":"+44 114 281 5000",
    "sg:postcode":"S6 2GZ",
    "sg:province":"South Yorkshire",
    "sg:tags":[
        "development",
        "system",
        "software"
    ],
    "wof:name":"Selima Software Ltd.",
    "wof:placetype":"venue"
},
  "geometry": {"coordinates":[-1.4951200485,53.4007606506],"type":"Point"}
}