{
  "type": "Feature",
  "properties": {
    "addr:full":"12-14 Cross Square Wakefield West Yorkshire WF1 1PH",
    "addr:housenumber":"12-14",
    "addr:postcode":"wf1 1ph",
    "addr:street":"Cross Square",
    "iso:country":"GB",
    "sg:address":"12-14 Cross Square",
    "sg:city":"Wakefield",
    "sg:classifiers":[
        {
            "category":"Shopping",
            "subcategory":"Clothing, Apparel, & Fashions",
            "type":"Retail Goods"
        }
    ],
    "sg:phone":"+44 1924 363086",
    "sg:postcode":"WF1 1PH",
    "sg:province":"West Yorkshire",
    "sg:tags":[
        "shop"
    ],
    "wof:name":"Kingswells Double Two",
    "wof:placetype":"venue"
},
  "geometry": {"coordinates":[-1.4979790449,53.6830863953],"type":"Point"}
}