{
  "type": "Feature",
  "properties": {
    "iso:country":"GB",
    "sg:address":"The Old Brewery, Priory Lane",
    "sg:city":"Burford",
    "sg:classifiers":[
        {
            "category":"Professional",
            "subcategory":"Accounting & Tax Preparation",
            "type":"Services"
        }
    ],
    "sg:postcode":"OX18 4SG",
    "sg:province":"Gloucestershire",
    "sg:tags":[
        "accountant"
    ],
    "wof:name":"Hillier & Co",
    "wof:placetype":"venue"
},
  "geometry": {"coordinates":[-1.6350229979,51.8023376465],"type":"Point"}
}