{
  "type": "Feature",
  "properties": {
    "iso:country":"GB",
    "sg:address":"Walmley Rd",
    "sg:city":"Sutton Coldfield",
    "sg:classifiers":[
        {
            "category":"Autos & Motor Vehicles",
            "subcategory":"Fuel & Gas Station",
            "type":"Retail Goods"
        }
    ],
    "sg:phone":"+44 121 351 4495",
    "sg:postcode":"B76 1NP",
    "sg:province":"Warwickshire",
    "sg:tags":[
        "petrol",
        "filling"
    ],
    "wof:name":"Walmley Road Service Station",
    "wof:placetype":"venue"
},
  "geometry": {"coordinates":[-1.801869,52.55843],"type":"Point"}
}