{
  "type": "Feature",
  "properties": {
    "iso:country":"GB",
    "sg:address":"3 Woodland Gro",
    "sg:city":"Weybridge",
    "sg:classifiers":[
        {
            "category":"Shopping",
            "subcategory":"Gifts & Souvenirs",
            "type":"Retail Goods"
        }
    ],
    "sg:phone":"+44 1932 855285",
    "sg:postcode":"KT13 9EF",
    "sg:province":"Surrey",
    "sg:tags":[
        "greeting",
        "card"
    ],
    "wof:name":"Cavendish Collection",
    "wof:placetype":"venue"
},
  "geometry": {"coordinates":[-0.4387,51.368603],"type":"Point"}
}