{
  "type": "Feature",
  "properties": {
    "iso:country":"GB",
    "sg:address":"13 Cotsworld Mews, 30 Battersea Square",
    "sg:city":"London",
    "sg:classifiers":[
        {
            "category":"Wholesale",
            "subcategory":"Books, Periodicals, & Newspapers",
            "type":"Manufacturing & Wholesale Goods"
        }
    ],
    "sg:phone":"+44 20 7738 1339",
    "sg:postcode":"SW11 3RA",
    "sg:province":"Greater London",
    "sg:tags":[
        "publishing"
    ],
    "wof:name":"Oyster Publishing",
    "wof:placetype":"venue"
},
  "geometry": {"coordinates":[-0.17496,51.47472],"type":"Point"}
}