{
  "type": "Feature",
  "properties": {
    "iso:country":"GB",
    "sg:address":"32 St Dunstans Rise, West Hunsbury",
    "sg:city":"Northampton",
    "sg:classifiers":[
        {
            "category":"Professional",
            "subcategory":"Secretarial Services",
            "type":"Services"
        }
    ],
    "sg:phone":"+44 1604 469933",
    "sg:postcode":"NN4 9XL",
    "sg:province":"Northamptonshire",
    "wof:name":"Advantage Northampton",
    "wof:placetype":"venue"
},
  "geometry": {"coordinates":[-0.929415,52.219898],"type":"Point"}
}