{
  "type": "Feature",
  "properties": {
    "addr:full":"39a High St Esher Surrey KT10 9RN",
    "addr:housenumber":"39a",
    "addr:postcode":"kt10 9rn",
    "addr:street":"High St",
    "iso:country":"GB",
    "sg:address":"39a High St",
    "sg:city":"Esher",
    "sg:classifiers":[
        {
            "category":"Real Estate",
            "subcategory":"Real Estate Operator",
            "type":"Services"
        }
    ],
    "sg:phone":"+44 70 7122 4497",
    "sg:postcode":"KT10 9RN",
    "sg:province":"Surrey",
    "sg:tags":[
        "letting",
        "agent"
    ],
    "wof:name":"Easy Let",
    "wof:placetype":"venue"
},
  "geometry": {"coordinates":[-0.3641270101,51.3701095581],"type":"Point"}
}