{
  "type": "Feature",
  "properties": {
    "addr:full":"Parkway King's Lynn Norfolk PE30 4QQ",
    "addr:postcode":"pe30 4qq",
    "addr:street":"Parkway",
    "iso:country":"GB",
    "sg:address":"Parkway",
    "sg:city":"King's Lynn",
    "sg:classifiers":[
        {
            "category":"Organizations",
            "subcategory":"Non-profit Organization",
            "type":"Services"
        }
    ],
    "sg:phone":"+44 1553 774531",
    "sg:postcode":"PE30 4QQ",
    "sg:province":"Norfolk",
    "sg:tags":[
        "charitable",
        "organisation",
        "voluntary",
        "charity"
    ],
    "wof:name":"St Raphael Club For The Handicapped",
    "wof:placetype":"venue"
},
  "geometry": {"coordinates":[0.4190700054,52.7524795532],"type":"Point"}
}