{
  "type": "Feature",
  "properties": {
    "addr:full":"2 Star Lane Coulsdon Surrey CR5 3RA",
    "addr:housenumber":"2",
    "addr:postcode":"cr5 3ra",
    "addr:street":"Star Lane",
    "iso:country":"GB",
    "sg:address":"2 Star Lane",
    "sg:city":"Coulsdon",
    "sg:classifiers":[
        {
            "category":"Shopping",
            "subcategory":"Photographic Equipment",
            "type":"Retail Goods"
        }
    ],
    "sg:phone":"+44 1737 551424",
    "sg:postcode":"CR5 3RA",
    "sg:province":"Surrey",
    "wof:name":"David Phipps",
    "wof:placetype":"venue"
},
  "geometry": {"coordinates":[-0.154248,51.293282],"type":"Point"}
}