{
  "type": "Feature",
  "properties": {
    "iso:country":"GB",
    "sg:address":"3 Stanch Hill Road, Sawtry",
    "sg:city":"Huntingdon",
    "sg:classifiers":[
        {
            "category":"Professional",
            "subcategory":"Detective & Security Services",
            "type":"Services"
        }
    ],
    "sg:phone":"+44 1487 831493",
    "sg:postcode":"PE28 5XG",
    "sg:province":"Bedfordshire",
    "sg:tags":[
        "agency"
    ],
    "wof:name":"Intercounty Investigations",
    "wof:placetype":"venue"
},
  "geometry": {"coordinates":[-0.2755660117,52.4334259033],"type":"Point"}
}