{
  "type": "Feature",
  "properties": {
    "iso:country":"GB",
    "sg:address":"Botley Road West End",
    "sg:city":"Southampton",
    "sg:classifiers":[
        {
            "category":"Autos & Motor Vehicles",
            "subcategory":"Fuel & Gas Station",
            "type":"Retail Goods"
        }
    ],
    "sg:phone":"+44 23 8046 5200",
    "sg:postcode":"SO30 3HA",
    "sg:province":"Hampshire",
    "sg:tags":[
        "petrol",
        "filling"
    ],
    "wof:name":"Texaco Ltd.",
    "wof:placetype":"venue"
},
  "geometry": {"coordinates":[-1.3048759699,50.9228057861],"type":"Point"}
}