{
  "type": "Feature",
  "properties": {
    "iso:country":"GB",
    "sg:address":"Blaen Y Gors Neath Rd, Ystradgynlais",
    "sg:city":"Swansea",
    "sg:classifiers":[
        {
            "category":"Autos & Motor Vehicles",
            "subcategory":"Automobile Sales",
            "type":"Retail Goods"
        }
    ],
    "sg:phone":"+44 1639 842810",
    "sg:postcode":"SA9 1PY",
    "sg:province":"Carmarthenshire",
    "sg:tags":[
        "commercial"
    ],
    "wof:name":"C Bradshaw",
    "wof:placetype":"venue"
},
  "geometry": {"coordinates":[-3.757261,51.777824],"type":"Point"}
}