{
  "type": "Feature",
  "properties": {
    "addr:full":"213 Victoria Park Road London Greater London E9 7HD",
    "addr:housenumber":"213",
    "addr:postcode":"e9 7hd",
    "addr:street":"Victoria Park Road",
    "iso:country":"GB",
    "sg:address":"213 Victoria Park Road",
    "sg:city":"London",
    "sg:classifiers":[
        {
            "category":"Real Estate",
            "subcategory":"Real Estate Agent",
            "type":"Services"
        }
    ],
    "sg:phone":"+44 20 8985 5800",
    "sg:postcode":"E9 7HD",
    "sg:province":"Greater London",
    "wof:name":"Sovereign House Estates",
    "wof:placetype":"venue"
},
  "geometry": {"coordinates":[-0.042506,51.53846],"type":"Point"}
}