{
  "type": "Feature",
  "properties": {
    "addr:full":"1 High St Northwich Cheshire CW8 3EX",
    "addr:housenumber":"1",
    "addr:postcode":"cw8 3ex",
    "addr:street":"High St",
    "iso:country":"GB",
    "sg:address":"1 High St",
    "sg:city":"Northwich",
    "sg:classifiers":[
        {
            "category":"Shopping",
            "subcategory":"Pharmacy",
            "type":"Retail Goods"
        }
    ],
    "sg:phone":"+44 1606 853122",
    "sg:postcode":"CW8 3EX",
    "sg:province":"Cheshire",
    "sg:tags":[
        "pharmacist",
        "chemist"
    ],
    "wof:name":"Peels Chemist",
    "wof:placetype":"venue"
},
  "geometry": {"coordinates":[-2.58062,53.262833],"type":"Point"}
}