{
  "type": "Feature",
  "properties": {
    "iso:country":"GB",
    "sg:address":"32 Central Drive, Romiley",
    "sg:city":"Stockport",
    "sg:classifiers":[
        {
            "category":"Retail",
            "subcategory":"Driving School",
            "type":"Services"
        }
    ],
    "sg:phone":"+44 161 494 7727",
    "sg:postcode":"SK6 4PH",
    "sg:province":"Cheshire",
    "wof:name":"M Smith School of Motoring",
    "wof:placetype":"venue"
},
  "geometry": {"coordinates":[-2.086744,53.416718],"type":"Point"}
}