{
  "type": "Feature",
  "properties": {
    "iso:country":"GB",
    "sg:address":"Edgware General Hospital Social Club, Burnt Oak Broadway",
    "sg:city":"Edgware",
    "sg:classifiers":[
        {
            "category":"Education",
            "subcategory":"Dance Studio",
            "type":"Public Place"
        }
    ],
    "sg:phone":"+44 20 8575 0716",
    "sg:postcode":"HA8 0AD",
    "sg:province":"Greater London",
    "sg:tags":[
        "school",
        "dancing"
    ],
    "wof:name":"Rock & Roll & Sulsa",
    "wof:placetype":"venue"
},
  "geometry": {"coordinates":[-0.2775639892,51.6120834351],"type":"Point"}
}