{
  "type": "Feature",
  "properties": {
    "iso:country":"GB",
    "sg:address":"8 Springfield Dr",
    "sg:city":"Thornton-cleveleys",
    "sg:classifiers":[
        {
            "category":"Building & Trades",
            "subcategory":"Construction",
            "type":"Services"
        }
    ],
    "sg:postcode":"FY5 4LN",
    "sg:province":"Lancashire",
    "sg:tags":[
        "builder"
    ],
    "wof:name":"Large,Graham Joseph,",
    "wof:placetype":"venue"
},
  "geometry": {"coordinates":[-3.012261,53.885361],"type":"Point"}
}