{
  "type": "Feature",
  "properties": {
    "addr:full":"Ingleby Lane, Easby, Great Ayton Middlesbrough North Yorkshire TS9 6LH",
    "addr:postcode":"ts9 6lh",
    "addr:street":"Ingleby Lane",
    "iso:country":"GB",
    "sg:address":"Ingleby Lane, Easby, Great Ayton",
    "sg:city":"Middlesbrough",
    "sg:classifiers":[
        {
            "category":"Sports & Exercise",
            "subcategory":"Skate Park",
            "type":"Entertainment"
        }
    ],
    "sg:postcode":"TS9 6LH",
    "sg:province":"North Yorkshire",
    "sg:tags":[
        "mushroom"
    ],
    "wof:name":"Monument Mushrooms",
    "wof:placetype":"venue"
},
  "geometry": {"coordinates":[-1.141065,54.489876],"type":"Point"}
}