{
  "type": "Feature",
  "properties": {
    "addr:full":"Cedar Way Wellingborough Northamptonshire NN8 4SL",
    "addr:postcode":"nn8 4sl",
    "addr:street":"Cedar Way",
    "iso:country":"GB",
    "sg:address":"Cedar Way",
    "sg:city":"Wellingborough",
    "sg:classifiers":[
        {
            "category":"Personal",
            "subcategory":"Beauty Salon",
            "type":"Services"
        }
    ],
    "sg:phone":"+44 1933 678900",
    "sg:postcode":"NN8 4SL",
    "sg:province":"Northamptonshire",
    "sg:tags":[
        "lady",
        "hairdresser"
    ],
    "wof:name":"Dianne's Salon",
    "wof:placetype":"venue"
},
  "geometry": {"coordinates":[-0.697799,52.313419],"type":"Point"}
}