{
  "type": "Feature",
  "properties": {
    "iso:country":"GB",
    "sg:address":"Scotia House, 3 Evans Street, Burslem",
    "sg:city":"Stoke-on-trent",
    "sg:classifiers":[
        {
            "category":"Shopping",
            "subcategory":"Crafts & Fabrics",
            "type":"Retail Goods"
        }
    ],
    "sg:phone":"+44 1782 816660",
    "sg:postcode":"ST6 4HP",
    "sg:province":"Staffordshire",
    "sg:tags":[
        "ceramic"
    ],
    "wof:name":"W Nicholas Mellor Ceramic Transfers",
    "wof:placetype":"venue"
},
  "geometry": {"coordinates":[-2.2010269165,53.0512390137],"type":"Point"}
}