{
  "type": "Feature",
  "properties": {
    "addr:full":"273 Main Rd Sidcup Kent DA14 6QL",
    "addr:housenumber":"273",
    "addr:postcode":"da14 6ql",
    "addr:street":"Main Rd",
    "iso:country":"GB",
    "sg:address":"273 Main Rd",
    "sg:city":"Sidcup",
    "sg:classifiers":[
        {
            "category":"Real Estate",
            "subcategory":"Real Estate Operator",
            "type":"Services"
        }
    ],
    "sg:postcode":"DA14 6QL",
    "sg:province":"Kent",
    "sg:tags":[
        "letting",
        "agent"
    ],
    "wof:name":"Central Management and Lettings Ltd",
    "wof:placetype":"venue"
},
  "geometry": {"coordinates":[0.086633,51.430153],"type":"Point"}
}