{
  "type": "Feature",
  "properties": {
    "iso:country":"GB",
    "sg:address":"Dykefoot",
    "sg:city":"West Calder",
    "sg:classifiers":[
        {
            "category":"Professional",
            "subcategory":"Lawyer & Legal Services",
            "type":"Services"
        }
    ],
    "sg:phone":"+44 1501 785385",
    "sg:postcode":"EH55 8LS",
    "sg:province":"South Lanarkshire",
    "sg:tags":[
        "solicitor"
    ],
    "wof:name":"G Jones",
    "wof:placetype":"venue"
},
  "geometry": {"coordinates":[-3.572372,55.851124],"type":"Point"}
}