{
  "type": "Feature",
  "properties": {
    "addr:full":"23 The Ridgeway Grimsby Lincolnshire DN34 5PH",
    "addr:housenumber":"23",
    "addr:postcode":"dn34 5ph",
    "addr:street":"The Ridgeway",
    "iso:country":"GB",
    "sg:address":"23 The Ridgeway",
    "sg:city":"Grimsby",
    "sg:classifiers":[
        {
            "category":"Building & Trades",
            "subcategory":"Construction",
            "type":"Services"
        }
    ],
    "sg:phone":"+44 1472 873224",
    "sg:postcode":"DN34 5PH",
    "sg:province":"Lincolnshire",
    "sg:tags":[
        "builder"
    ],
    "wof:name":"D R King Builders",
    "wof:placetype":"venue"
},
  "geometry": {"coordinates":[-0.1266359985,53.54945755],"type":"Point"}
}