{
  "type": "Feature",
  "properties": {
    "iso:country":"GB",
    "sg:address":"1a Adcroft Dr",
    "sg:city":"Trowbridge",
    "sg:classifiers":[
        {
            "category":"Professional",
            "subcategory":"Management & Consulting",
            "type":"Services"
        },
        {
            "category":"Building & Trades",
            "subcategory":"Construction",
            "type":"Services"
        }
    ],
    "sg:postcode":"BA14 8PU",
    "sg:province":"Wiltshire",
    "sg:tags":[
        "consultant",
        "business"
    ],
    "wof:name":"Stallard,N C,",
    "wof:placetype":"venue"
},
  "geometry": {"coordinates":[-2.208393,51.324749],"type":"Point"}
}