{
  "type": "Feature",
  "properties": {
    "addr:full":"3 Upper Hirst Huddersfield West Yorkshire HD3 3TG",
    "addr:housenumber":"3",
    "addr:postcode":"hd3 3tg",
    "addr:street":"Upper Hirst",
    "iso:country":"GB",
    "sg:address":"3 Upper Hirst",
    "sg:city":"Huddersfield",
    "sg:classifiers":[
        {
            "category":"Retail",
            "subcategory":"Driving School",
            "type":"Services"
        }
    ],
    "sg:phone":"+44 1484 645866",
    "sg:postcode":"HD3 3TG",
    "sg:province":"West Yorkshire",
    "wof:name":"Sally Jennings",
    "wof:placetype":"venue"
},
  "geometry": {"coordinates":[-1.857622,53.657398],"type":"Point"}
}