{
  "type": "Feature",
  "properties": {
    "addr:full":"Oxford Road Aylesbury Buckinghamshire HP19 8RJ",
    "addr:postcode":"hp19 8rj",
    "addr:street":"Oxford Road",
    "iso:country":"GB",
    "sg:address":"Oxford Road",
    "sg:city":"Aylesbury",
    "sg:classifiers":[
        {
            "category":"Government",
            "subcategory":"Office",
            "type":"Public Place"
        }
    ],
    "sg:phone":"+44 1296 482946",
    "sg:postcode":"HP19 8RJ",
    "sg:province":"Buckinghamshire",
    "sg:tags":[
        "armed",
        "reserve"
    ],
    "wof:name":"Territorial Army",
    "wof:placetype":"venue"
},
  "geometry": {"coordinates":[-0.819694,51.81752],"type":"Point"}
}