{
  "type": "Feature",
  "properties": {
    "addr:full":"3 Portobello High Street Edinburgh City of Edinburgh EH15 1DW",
    "addr:housenumber":"3",
    "addr:postcode":"eh15 1dw",
    "addr:street":"Portobello High Street",
    "iso:country":"GB",
    "sg:address":"3 Portobello High Street",
    "sg:city":"Edinburgh",
    "sg:classifiers":[
        {
            "category":"Autos & Motor Vehicles",
            "subcategory":"Automobile Sales",
            "type":"Retail Goods"
        }
    ],
    "sg:postcode":"EH15 1DW",
    "sg:province":"City of Edinburgh",
    "sg:tags":[
        "car"
    ],
    "wof:name":"Colorado Realisations (No  8) Ltd.",
    "wof:placetype":"venue"
},
  "geometry": {"coordinates":[-3.121844,55.957043],"type":"Point"}
}