{
  "type": "Feature",
  "properties": {
    "addr:full":"Greenbogue Torthorwald Dumfries Dumfries and Galloway DG1 3QG",
    "addr:postcode":"dg1 3qg",
    "iso:country":"GB",
    "sg:address":"Greenbogue Torthorwald",
    "sg:city":"Dumfries",
    "sg:classifiers":[
        {
            "category":"Shopping",
            "subcategory":"Department Store",
            "type":"Retail Goods"
        },
        {
            "category":"Recreation",
            "subcategory":"Fishing",
            "type":"Entertainment"
        }
    ],
    "sg:phone":"+44 1387 750247",
    "sg:postcode":"DG1 3QG",
    "sg:province":"Dumfries and Galloway",
    "sg:tags":[
        "angling"
    ],
    "wof:name":"Angler Craft",
    "wof:placetype":"venue"
},
  "geometry": {"coordinates":[-3.536164,55.092056],"type":"Point"}
}