{
  "type": "Feature",
  "properties": {
    "iso:country":"GB",
    "sg:address":"Town Ho, 63 High St",
    "sg:city":"Woking",
    "sg:classifiers":[
        {
            "category":"Professional",
            "subcategory":"Employment Agencies",
            "type":"Services"
        }
    ],
    "sg:phone":"+44 1276 855598",
    "sg:postcode":"GU24 8AF",
    "sg:province":"Surrey",
    "sg:tags":[
        "consultant"
    ],
    "wof:name":"Print Search & Selection",
    "wof:placetype":"venue"
},
  "geometry": {"coordinates":[-0.60373,51.346088],"type":"Point"}
}