{
  "type": "Feature",
  "properties": {
    "addr:full":"100 Welbeck Street Hull East Riding of Yorkshire HU5 3SG",
    "addr:housenumber":"100",
    "addr:postcode":"hu5 3sg",
    "addr:street":"Welbeck Street",
    "iso:country":"GB",
    "sg:address":"100 Welbeck Street",
    "sg:city":"Hull",
    "sg:classifiers":[
        {
            "category":"Building & Trades",
            "subcategory":"Construction",
            "type":"Services"
        }
    ],
    "sg:phone":"+44 1482 440667",
    "sg:postcode":"HU5 3SG",
    "sg:province":"East Riding of Yorkshire",
    "sg:tags":[
        "builder"
    ],
    "wof:name":"A J R Home & Property Maintenance Services",
    "wof:placetype":"venue"
},
  "geometry": {"coordinates":[-0.365071,53.75275],"type":"Point"}
}