{
  "type": "Feature",
  "properties": {
    "iso:country":"GB",
    "sg:address":"16 Roseveare Road",
    "sg:city":"Eastbourne",
    "sg:classifiers":[
        {
            "category":"Building & Trades",
            "subcategory":"Construction",
            "type":"Services"
        }
    ],
    "sg:postcode":"BN22 8RS",
    "sg:province":"East Sussex",
    "sg:tags":[
        "joiner",
        "carpenter"
    ],
    "wof:name":"Michael Hooker",
    "wof:placetype":"venue"
},
  "geometry": {"coordinates":[0.297228,50.785088],"type":"Point"}
}