{
  "type": "Feature",
  "properties": {
    "iso:country":"GB",
    "sg:address":"Church Road, Blaenavon",
    "sg:city":"Pontypool",
    "sg:classifiers":[
        {
            "category":"Health Services",
            "subcategory":"Nursing And Care Facility",
            "type":"Services"
        }
    ],
    "sg:phone":"+44 1495 792019",
    "sg:postcode":"NP4 9AE",
    "sg:province":"Monmouthshire",
    "sg:tags":[
        "home"
    ],
    "wof:name":"The Beeches Nursing Home",
    "wof:placetype":"venue"
},
  "geometry": {"coordinates":[-3.087084,51.773102],"type":"Point"}
}