{
  "type": "Feature",
  "properties": {
    "iso:country":"GB",
    "sg:address":"105 Church Street",
    "sg:city":"Highbridge",
    "sg:classifiers":[
        {
            "category":"Food & Beverages",
            "subcategory":"Meat & Fish",
            "type":"Retail Goods"
        }
    ],
    "sg:phone":"+44 1278 783567",
    "sg:postcode":"TA9 3HR",
    "sg:province":"Somerset",
    "sg:tags":[
        "chip"
    ],
    "wof:name":"Moore's Fish Saloon",
    "wof:placetype":"venue"
},
  "geometry": {"coordinates":[-2.975678,51.221111],"type":"Point"}
}