{
  "type": "Feature",
  "properties": {
    "addr:full":"17-39 Gibbins Road London Greater London E15 2HU",
    "addr:housenumber":"17-39",
    "addr:postcode":"e15 2hu",
    "addr:street":"Gibbins Road",
    "iso:country":"GB",
    "sg:address":"17-39 Gibbins Road",
    "sg:city":"London",
    "sg:classifiers":[
        {
            "category":"Home & Garden",
            "subcategory":"Home Furnishings",
            "type":"Retail Goods"
        }
    ],
    "sg:phone":"+44 20 8534 9000",
    "sg:postcode":"E15 2HU",
    "sg:province":"Greater London",
    "sg:tags":[
        "beds",
        "bedding",
        "blanket"
    ],
    "wof:name":"City Beds Ltd.",
    "wof:placetype":"venue"
},
  "geometry": {"coordinates":[-0.005622,51.538532],"type":"Point"}
}