{
  "type": "Feature",
  "properties": {
    "iso:country":"GB",
    "sg:address":"Look Weep Farm, Liverton",
    "sg:city":"Newton Abbot",
    "sg:classifiers":[
        {
            "category":"Retail",
            "subcategory":"Repair Shop",
            "type":"Services"
        }
    ],
    "sg:phone":"+44 1626 834412",
    "sg:postcode":"TQ12 6HT",
    "sg:province":"Devon",
    "sg:tags":[
        "radio",
        "television",
        "video"
    ],
    "wof:name":"Griffiths",
    "wof:placetype":"venue"
},
  "geometry": {"coordinates":[-3.686318,50.563866],"type":"Point"}
}