{
  "type": "Feature",
  "properties": {
    "iso:country":"GB",
    "sg:address":"Dodhead",
    "sg:city":"Burntisland",
    "sg:classifiers":[
        {
            "category":"Sports & Exercise",
            "subcategory":"Golf",
            "type":"Entertainment"
        }
    ],
    "sg:phone":"+44 1592 874093",
    "sg:postcode":"KY3 9LQ",
    "sg:province":"Fife",
    "sg:tags":[
        "club",
        "course"
    ],
    "wof:name":"Burntisland Golf House Club",
    "wof:placetype":"venue"
},
  "geometry": {"coordinates":[-3.2040390968,56.0723800659],"type":"Point"}
}