{
  "type": "Feature",
  "properties": {
    "iso:country":"GB",
    "sg:address":"Lakewood",
    "sg:city":"Chester",
    "sg:classifiers":[
        {
            "category":"Shopping",
            "subcategory":"Pharmacy",
            "type":"Retail Goods"
        }
    ],
    "sg:postcode":"CH4 9QW",
    "sg:province":"Cheshire",
    "sg:tags":[
        "medical"
    ],
    "wof:name":"Convatec Ltd.",
    "wof:placetype":"venue"
},
  "geometry": {"coordinates":[-2.905314,53.159306],"type":"Point"}
}