{
  "type": "Feature",
  "properties": {
    "addr:full":"32 Union St Greenock Inverclyde PA16 8DJ",
    "addr:housenumber":"32",
    "addr:postcode":"pa16 8dj",
    "addr:street":"Union St Greenock",
    "iso:country":"GB",
    "sg:address":"32 Union St",
    "sg:city":"Greenock",
    "sg:classifiers":[
        {
            "category":"Wholesale",
            "subcategory":"Construction Materials",
            "type":"Manufacturing & Wholesale Goods"
        }
    ],
    "sg:phone":"+44 1475 723737",
    "sg:postcode":"PA16 8DJ",
    "sg:province":"Inverclyde",
    "sg:tags":[
        "sawdust",
        "sawmills",
        "shaving"
    ],
    "wof:name":"Greenock Central Sawmills",
    "wof:placetype":"venue"
},
  "geometry": {"coordinates":[-4.769388,55.953449],"type":"Point"}
}