{
  "type": "Feature",
  "properties": {
    "addr:full":"Unit 27 Monument Industrial Park Oxford Oxfordshire OX44 7RW",
    "addr:housenumber":"unit 27",
    "addr:postcode":"ox44 7rw",
    "addr:street":"Monument Industrial Park",
    "iso:country":"GB",
    "sg:address":"Unit 27 Monument Industrial Park",
    "sg:city":"Oxford",
    "sg:classifiers":[
        {
            "category":"Shopping",
            "subcategory":"Books",
            "type":"Retail Goods"
        }
    ],
    "sg:phone":"+44 1865 400256",
    "sg:postcode":"OX44 7RW",
    "sg:province":"Oxfordshire",
    "sg:tags":[
        "bookseller"
    ],
    "wof:name":"Outdoorsmans Bookstore The",
    "wof:placetype":"venue"
},
  "geometry": {"coordinates":[-1.0649600029,51.6698188782],"type":"Point"}
}