{
  "type": "Feature",
  "properties": {
    "iso:country":"GB",
    "sg:address":"29 St Stephens Road",
    "sg:city":"Norwich",
    "sg:classifiers":[
        {
            "category":"Shopping",
            "subcategory":"News",
            "type":"Retail Goods"
        }
    ],
    "sg:postcode":"NR1 3SP",
    "sg:province":"Norfolk",
    "sg:tags":[
        "newsagent"
    ],
    "wof:name":"Charlie's News and Convenience Stores",
    "wof:placetype":"venue"
},
  "geometry": {"coordinates":[1.288645,52.623699],"type":"Point"}
}