{
  "type": "Feature",
  "properties": {
    "addr:full":"Pontefract Road, Normanton Industrial Estate Normanton West Yorkshire WF6 1RW",
    "addr:housenumber":"estate",
    "addr:postcode":"wf6 1rw",
    "addr:street":"Pontefract Road;Industrial;West",
    "iso:country":"GB",
    "sg:address":"Pontefract Road, Normanton Industrial Estate",
    "sg:city":"Normanton",
    "sg:classifiers":[
        {
            "category":"Freight",
            "type":"Transportation"
        }
    ],
    "sg:phone":"+44 1924 895444",
    "sg:postcode":"WF6 1RW",
    "sg:province":"West Yorkshire",
    "sg:tags":[
        "haulage",
        "road"
    ],
    "wof:name":"Swift Transport Services",
    "wof:placetype":"venue"
},
  "geometry": {"coordinates":[-1.400069,53.706524],"type":"Point"}
}