{
  "type": "Feature",
  "properties": {
    "iso:country":"GB",
    "sg:address":"56 Long Lane, Aston End",
    "sg:city":"Stevenage",
    "sg:classifiers":[
        {
            "category":"Bars & Pubs",
            "type":"Food & Drink"
        }
    ],
    "sg:phone":"+44 1438 880060",
    "sg:postcode":"SG2 7HD",
    "sg:province":"Hertfordshire",
    "sg:tags":[
        "pubs",
        "inn"
    ],
    "wof:name":"The Crown",
    "wof:placetype":"venue"
},
  "geometry": {"coordinates":[-0.150828,51.901844],"type":"Point"}
}