{
  "type": "Feature",
  "properties": {
    "addr:full":"17 Main Street, Whittington Lichfield Staffordshire WS14 9JR",
    "addr:housenumber":"17",
    "addr:postcode":"ws14 9jr",
    "addr:street":"Main Street",
    "iso:country":"GB",
    "sg:address":"17 Main Street, Whittington",
    "sg:city":"Lichfield",
    "sg:classifiers":[
        {
            "category":"Professional",
            "subcategory":"Engineering",
            "type":"Services"
        }
    ],
    "sg:phone":"+44 1543 255900",
    "sg:postcode":"WS14 9JR",
    "sg:province":"Staffordshire",
    "sg:tags":[
        "consulting",
        "engineer"
    ],
    "wof:name":"E P C",
    "wof:placetype":"venue"
},
  "geometry": {"coordinates":[-1.7626409531,52.6732292175],"type":"Point"}
}