{
  "type": "Feature",
  "properties": {
    "addr:full":"164-166 Hawthorne Road Bootle Merseyside L20 3AR",
    "addr:housenumber":"164-166",
    "addr:postcode":"l20 3ar",
    "addr:street":"Hawthorne Road",
    "iso:country":"GB",
    "sg:address":"164-166 Hawthorne Road",
    "sg:city":"Bootle",
    "sg:classifiers":[
        {
            "category":"Health Services",
            "subcategory":"Nursing And Care Facility",
            "type":"Services"
        }
    ],
    "sg:phone":"+44 151 933 3323",
    "sg:postcode":"L20 3AR",
    "sg:province":"Merseyside",
    "sg:tags":[
        "home",
        "residential"
    ],
    "wof:name":"STIRRUPVIEW LTD",
    "wof:placetype":"venue"
},
  "geometry": {"coordinates":[-2.98350811,53.4469146729],"type":"Point"}
}