{
  "type": "Feature",
  "properties": {
    "addr:full":"7 Station Rd, Flitwick Bedford Bedfordshire MK45 1JR",
    "addr:housenumber":"7",
    "addr:postcode":"mk45 1jr",
    "addr:street":"Station Rd",
    "iso:country":"GB",
    "sg:address":"7 Station Rd, Flitwick",
    "sg:city":"Bedford",
    "sg:classifiers":[
        {
            "category":"Shopping",
            "subcategory":"Crafts & Fabrics",
            "type":"Retail Goods"
        }
    ],
    "sg:postcode":"MK45 1JR",
    "sg:province":"Bedfordshire",
    "sg:tags":[
        "shop",
        "needlecraft",
        "wool"
    ],
    "wof:name":"Owen,Margaret,",
    "wof:placetype":"venue"
},
  "geometry": {"coordinates":[-0.4933579862,52.0028762817],"type":"Point"}
}