{
  "type": "Feature",
  "properties": {
    "addr:full":"2 The Broadway Winchester Hampshire SO23 9BE",
    "addr:housenumber":"2",
    "addr:postcode":"so23 9be",
    "addr:street":"The Broadway",
    "iso:country":"GB",
    "sg:address":"2 The Broadway",
    "sg:city":"Winchester",
    "sg:classifiers":[
        {
            "category":"Retail",
            "subcategory":"Funeral Services",
            "type":"Services"
        }
    ],
    "sg:phone":"+44 1962 843181",
    "sg:postcode":"SO23 9BE",
    "sg:province":"Hampshire",
    "wof:name":"B Mathews",
    "wof:placetype":"venue"
},
  "geometry": {"coordinates":[-1.3090649843,51.0614624023],"type":"Point"}
}