{
  "type": "Feature",
  "properties": {
    "iso:country":"GB",
    "sg:address":"77 London Road",
    "sg:city":"Cheltenham",
    "sg:classifiers":[
        {
            "category":"Bars & Pubs",
            "type":"Food & Drink"
        }
    ],
    "sg:phone":"+44 1242 701162",
    "sg:postcode":"GL52 6HF",
    "sg:province":"Gloucestershire",
    "sg:tags":[
        "pubs",
        "inn"
    ],
    "wof:name":"The Sunset Bar",
    "wof:placetype":"venue"
},
  "geometry": {"coordinates":[-2.065012,51.894085],"type":"Point"}
}