{
  "type": "Feature",
  "properties": {
    "addr:full":"8 Church Street Troon South Ayrshire KA10 6AU",
    "addr:housenumber":"8",
    "addr:postcode":"ka10 6au",
    "addr:street":"Church Street",
    "iso:country":"GB",
    "sg:address":"8 Church Street",
    "sg:city":"Troon",
    "sg:classifiers":[
        {
            "category":"Shopping",
            "subcategory":"Comic Books",
            "type":"Retail Goods"
        }
    ],
    "sg:postcode":"KA10 6AU",
    "sg:province":"South Ayrshire",
    "sg:tags":[
        "jeweller"
    ],
    "wof:name":"Siena Jewellery",
    "wof:placetype":"venue"
},
  "geometry": {"coordinates":[-4.662187,55.544491],"type":"Point"}
}