{
  "type": "Feature",
  "properties": {
    "iso:country":"GB",
    "sg:address":"San-marti, Skirlaugh Road, Old Ellerby",
    "sg:city":"Hull",
    "sg:classifiers":[
        {
            "category":"Building & Trades",
            "subcategory":"Cleaning & Sanitation",
            "type":"Services"
        }
    ],
    "sg:phone":"+44 1964 562482",
    "sg:postcode":"HU11 5AN",
    "sg:province":"East Riding of Yorkshire",
    "sg:tags":[
        "steam"
    ],
    "wof:name":"Perry Equipment",
    "wof:placetype":"venue"
},
  "geometry": {"coordinates":[-0.224549,53.822521],"type":"Point"}
}