{
  "type": "Feature",
  "properties": {
    "addr:full":"Warley Springs Garage, Burnley Road Halifax West Yorkshire HX2 7NB",
    "addr:postcode":"hx2 7nb",
    "addr:street":"Burnley Road",
    "iso:country":"GB",
    "sg:address":"Warley Springs Garage, Burnley Road",
    "sg:city":"Halifax",
    "sg:classifiers":[
        {
            "category":"Retail",
            "subcategory":"Auto Repair",
            "type":"Services"
        }
    ],
    "sg:phone":"+44 1422 831475",
    "sg:postcode":"HX2 7NB",
    "sg:province":"West Yorkshire",
    "sg:tags":[
        "modification",
        "garage"
    ],
    "wof:name":"H Horsfield & Son Wedding Cars",
    "wof:placetype":"venue"
},
  "geometry": {"coordinates":[-1.9050699472,53.7195587158],"type":"Point"}
}