{
  "type": "Feature",
  "properties": {
    "addr:full":"Unit 5/6, First Avenue, Westfield Industrial Estate Bath Somerset BA3 4BS",
    "addr:housenumber":"unit 5 / 6",
    "addr:postcode":"ba3 4bs",
    "addr:street":"First Avenue;Industrial Estate",
    "iso:country":"GB",
    "sg:address":"Unit 5/6, First Avenue, Westfield Industrial Estate",
    "sg:city":"Bath",
    "sg:classifiers":[
        {
            "category":"Professional",
            "subcategory":"Printing & Photocopies",
            "type":"Services"
        }
    ],
    "sg:phone":"+44 1761 416023",
    "sg:postcode":"BA3 4BS",
    "sg:province":"Somerset",
    "sg:tags":[
        "printer"
    ],
    "wof:name":"Tom Jukes Graphics Ltd.",
    "wof:placetype":"venue"
},
  "geometry": {"coordinates":[-2.4682900906,51.2801094055],"type":"Point"}
}