{
  "type": "Feature",
  "properties": {
    "addr:full":"Clutton Hill, Clutton Bristol Somerset BS39 5QH",
    "addr:postcode":"bs39 5qh",
    "addr:street":"Clutton Hill",
    "iso:country":"GB",
    "sg:address":"Clutton Hill, Clutton",
    "sg:city":"Bristol",
    "sg:classifiers":[
        {
            "category":"Transit Center",
            "subcategory":"Passenger",
            "type":"Transportation"
        }
    ],
    "sg:postcode":"BS39 5QH",
    "sg:province":"Somerset",
    "sg:tags":[
        "boarding",
        "kennel",
        "catteries"
    ],
    "wof:name":"Ashdene Boarding Kennels",
    "wof:placetype":"venue"
},
  "geometry": {"coordinates":[-2.5188291073,51.3364982605],"type":"Point"}
}