{
  "type": "Feature",
  "properties": {
    "addr:full":"10 Flint Close Andover Hampshire SP10 2UE",
    "addr:housenumber":"10",
    "addr:postcode":"sp10 2ue",
    "addr:street":"Flint Close",
    "iso:country":"GB",
    "sg:address":"10 Flint Close",
    "sg:city":"Andover",
    "sg:classifiers":[
        {
            "category":"Autos & Motor Vehicles",
            "subcategory":"Auto Supplies",
            "type":"Retail Goods"
        }
    ],
    "sg:phone":"+44 1264 366922",
    "sg:postcode":"SP10 2UE",
    "sg:province":"Hampshire",
    "sg:tags":[
        "tyre"
    ],
    "wof:name":"Integrated Tyres Ltd.",
    "wof:placetype":"venue"
},
  "geometry": {"coordinates":[-1.5000679493,51.2003326416],"type":"Point"}
}