{
  "type": "Feature",
  "properties": {
    "addr:full":"Waingate Head Farm Carlisle Cumbria CA6 6BG",
    "addr:postcode":"ca6 6bg",
    "addr:street":"Waingate",
    "iso:country":"GB",
    "sg:address":"Waingate Head Farm",
    "sg:city":"Carlisle",
    "sg:classifiers":[
        {
            "category":"Farming",
            "subcategory":"Dairy Farm",
            "type":"Manufacturing & Wholesale Goods"
        }
    ],
    "sg:postcode":"CA6 6BG",
    "sg:province":"Cumbria",
    "wof:name":"Michael J L Simpson",
    "wof:placetype":"venue"
},
  "geometry": {"coordinates":[-2.865240097,55.0124816895],"type":"Point"}
}