{
  "type": "Feature",
  "properties": {
    "iso:country":"GB",
    "sg:address":"44 Stafford Road",
    "sg:city":"Lichfield",
    "sg:classifiers":[
        {
            "category":"Personal",
            "subcategory":"Beauty Salon",
            "type":"Services"
        }
    ],
    "sg:phone":"+44 1543 264301",
    "sg:postcode":"WS13 7BZ",
    "sg:province":"Staffordshire",
    "sg:tags":[
        "unisex",
        "hairdresser"
    ],
    "wof:name":"Regency Salon",
    "wof:placetype":"venue"
},
  "geometry": {"coordinates":[-1.8468580246,52.6916923523],"type":"Point"}
}