{
  "type": "Feature",
  "properties": {
    "addr:full":"Ushaw College Durham Durham DH7 9RH",
    "addr:postcode":"dh7 9rh",
    "iso:country":"GB",
    "sg:address":"Ushaw College",
    "sg:city":"Durham",
    "sg:classifiers":[
        {
            "category":"Organizations",
            "subcategory":"Non-profit Organization",
            "type":"Services"
        }
    ],
    "sg:phone":"+44 191 373 4555",
    "sg:postcode":"DH7 9RH",
    "sg:province":"Durham",
    "sg:tags":[
        "organisation",
        "voluntary",
        "charity"
    ],
    "wof:name":"Durham Area Disability Leisure Group",
    "wof:placetype":"venue"
},
  "geometry": {"coordinates":[-1.66113,54.788422],"type":"Point"}
}