{
  "type": "Feature",
  "properties": {
    "addr:full":"The Street, Hemsby Great Yarmouth Norfolk NR29 4EU",
    "addr:postcode":"nr29 4eu",
    "addr:street":"The Street;Yarmouth",
    "iso:country":"GB",
    "sg:address":"The Street, Hemsby",
    "sg:city":"Great Yarmouth",
    "sg:classifiers":[
        {
            "category":"Food & Beverages",
            "subcategory":"Meat & Fish",
            "type":"Retail Goods"
        },
        {
            "category":"Food & Beverages",
            "subcategory":"Groceries & Convenience Stores",
            "type":"Retail Goods"
        }
    ],
    "sg:phone":"+44 1493 730397",
    "sg:postcode":"NR29 4EU",
    "sg:province":"Norfolk",
    "sg:tags":[
        "shop",
        "chip"
    ],
    "wof:name":"The Fish & Chip Shop",
    "wof:placetype":"venue"
},
  "geometry": {"coordinates":[1.661865,52.71909],"type":"Point"}
}