{
  "type": "Feature",
  "properties": {
    "iso:country":"GB",
    "sg:address":"42 Radburn Way",
    "sg:city":"Letchworth",
    "sg:classifiers":[
        {
            "category":"Taxi",
            "type":"Transportation"
        },
        {
            "category":"Military Area",
            "subcategory":"Air Force Base",
            "type":"Public Place"
        }
    ],
    "sg:phone":"+44 1462 483336",
    "sg:postcode":"SG6 2LG",
    "sg:province":"Hertfordshire",
    "sg:tags":[
        "mini",
        "hire",
        "private",
        "cab"
    ],
    "wof:name":"Arrows Taxis",
    "wof:placetype":"venue"
},
  "geometry": {"coordinates":[-0.213547,51.972858],"type":"Point"}
}