{
  "type": "Feature",
  "properties": {
    "addr:full":"50 Needingworth Road St Ives Cambridgeshire PE27 5JP",
    "addr:housenumber":"50",
    "addr:postcode":"pe27 5jp",
    "addr:street":"Needingworth Road",
    "iso:country":"GB",
    "sg:address":"50 Needingworth Road",
    "sg:city":"St Ives",
    "sg:classifiers":[
        {
            "category":"Professional",
            "type":"Services"
        }
    ],
    "sg:postcode":"PE27 5JP",
    "sg:province":"Cambridgeshire",
    "sg:tags":[
        "caterer"
    ],
    "wof:name":"Barlist",
    "wof:placetype":"venue"
},
  "geometry": {"coordinates":[-0.067934,52.325783],"type":"Point"}
}