{
  "type": "Feature",
  "properties": {
    "iso:country":"GB",
    "sg:address":"Unit 6 Fleet Walk, Fleet Street",
    "sg:city":"Torquay",
    "sg:classifiers":[
        {
            "category":"Shopping",
            "subcategory":"Clothing, Apparel, & Fashions",
            "type":"Retail Goods"
        }
    ],
    "sg:phone":"+44 1803 201049",
    "sg:postcode":"TQ2 5EH",
    "sg:province":"Devon",
    "sg:tags":[
        "shop"
    ],
    "wof:name":"Ann Harvey",
    "wof:placetype":"venue"
},
  "geometry": {"coordinates":[-3.526266098,50.4630393982],"type":"Point"}
}