{
  "type": "Feature",
  "properties": {
    "addr:full":"2 Beacon Road Broadstone Dorset BH18 9JN",
    "addr:housenumber":"2",
    "addr:postcode":"bh18 9jn",
    "addr:street":"Beacon Road",
    "iso:country":"GB",
    "sg:address":"2 Beacon Road",
    "sg:city":"Broadstone",
    "sg:classifiers":[
        {
            "category":"Manufacturing",
            "subcategory":"Petroleum Products",
            "type":"Manufacturing & Wholesale Goods"
        },
        {
            "category":"Building & Trades",
            "subcategory":"Construction",
            "type":"Services"
        }
    ],
    "sg:phone":"+44 1202 692986",
    "sg:postcode":"BH18 9JN",
    "sg:province":"Dorset",
    "sg:tags":[
        "double",
        "glazing",
        "installers"
    ],
    "wof:name":"Habgood & Bartlett Double Glazing",
    "wof:placetype":"venue"
},
  "geometry": {"coordinates":[-2.0122389793,50.7561721802],"type":"Point"}
}