{
  "type": "Feature",
  "properties": {
    "iso:country":"GB",
    "sg:address":"New Street, Huthwaite",
    "sg:city":"Sutton-in-ashfield",
    "sg:classifiers":[
        {
            "category":"Community Center",
            "type":"Public Place"
        }
    ],
    "sg:phone":"+44 1623 513147",
    "sg:postcode":"NG17 2LR",
    "sg:province":"Nottinghamshire",
    "sg:tags":[
        "recreation",
        "leisure",
        "centre"
    ],
    "wof:name":"Huthwaite Leisure Centre",
    "wof:placetype":"venue"
},
  "geometry": {"coordinates":[-1.3005690575,53.1300354004],"type":"Point"}
}