{
  "type": "Feature",
  "properties": {
    "iso:country":"GB",
    "sg:address":"20 Norwich Road",
    "sg:city":"Norwich",
    "sg:classifiers":[
        {
            "category":"Real Estate",
            "subcategory":"Surveying",
            "type":"Services"
        }
    ],
    "sg:postcode":"NR9 3DD",
    "sg:province":"Norfolk",
    "sg:tags":[
        "surveyor",
        "quantity"
    ],
    "wof:name":"W Harker Bousfield & Partners",
    "wof:placetype":"venue"
},
  "geometry": {"coordinates":[1.181345,52.59761],"type":"Point"}
}