{
  "type": "Feature",
  "properties": {
    "iso:country":"GB",
    "sg:address":"68 Grampian Way",
    "sg:city":"Slough",
    "sg:classifiers":[
        {
            "category":"Professional",
            "subcategory":"Engineering",
            "type":"Services"
        },
        {
            "category":"Building & Trades",
            "subcategory":"Electrical",
            "type":"Services"
        }
    ],
    "sg:phone":"+44 1753 548770",
    "sg:postcode":"SL3 8UG",
    "sg:province":"Berkshire",
    "sg:tags":[
        "engineer",
        "electrician",
        "contractor"
    ],
    "wof:name":"Welco Electrical Services Ltd",
    "wof:placetype":"venue"
},
  "geometry": {"coordinates":[-0.5416169763,51.4928665161],"type":"Point"}
}