{
  "type": "Feature",
  "properties": {
    "addr:full":"237 Monton Road, Monton, Eccles Manchester Greater Manchester M30 9QF",
    "addr:housenumber":"237",
    "addr:postcode":"m30 9qf",
    "addr:street":"Monton Road",
    "iso:country":"GB",
    "sg:address":"237 Monton Road, Monton, Eccles",
    "sg:city":"Manchester",
    "sg:classifiers":[
        {
            "category":"Home & Garden",
            "subcategory":"Carpets & Floor Coverings",
            "type":"Retail Goods"
        }
    ],
    "sg:phone":"+44 161 789 3683",
    "sg:postcode":"M30 9QF",
    "sg:province":"Greater Manchester",
    "sg:tags":[
        "carpets",
        "rug",
        "matting"
    ],
    "wof:name":"Brian K Bennett",
    "wof:placetype":"venue"
},
  "geometry": {"coordinates":[-2.352463007,53.4913024902],"type":"Point"}
}