{
  "type": "Feature",
  "properties": {
    "addr:full":"Hilltop Farm, Otley Road Skipton Lancashire BD23 1HB",
    "addr:postcode":"bd23 1hb",
    "addr:street":"Otley Road",
    "iso:country":"GB",
    "sg:address":"Hilltop Farm, Otley Road",
    "sg:city":"Skipton",
    "sg:classifiers":[
        {
            "category":"Sports & Exercise",
            "subcategory":"Tennis Court",
            "type":"Entertainment"
        }
    ],
    "sg:phone":"+44 1756 795888",
    "sg:postcode":"BD23 1HB",
    "sg:province":"Lancashire",
    "sg:tags":[
        "breakdown",
        "recovery"
    ],
    "wof:name":"P Shaw Recovery Services",
    "wof:placetype":"venue"
},
  "geometry": {"coordinates":[-2.018514,53.960201],"type":"Point"}
}