{
  "type": "Feature",
  "properties": {
    "addr:full":"10 Park Street Chatteris Cambridgeshire PE16 6AE",
    "addr:housenumber":"10",
    "addr:postcode":"pe16 6ae",
    "addr:street":"Park Street",
    "iso:country":"GB",
    "sg:address":"10 Park Street",
    "sg:city":"Chatteris",
    "sg:classifiers":[
        {
            "category":"Professional",
            "subcategory":"Lawyer & Legal Services",
            "type":"Services"
        }
    ],
    "sg:phone":"+44 1354 695885",
    "sg:postcode":"PE16 6AE",
    "sg:province":"Cambridgeshire",
    "sg:tags":[
        "solicitor"
    ],
    "wof:name":"Battersby James",
    "wof:placetype":"venue"
},
  "geometry": {"coordinates":[0.0488680005,52.4535446167],"type":"Point"}
}