{
  "type": "Feature",
  "properties": {
    "iso:country":"GB",
    "sg:address":"Knightsford House, Church Road",
    "sg:city":"Wolverhampton",
    "sg:classifiers":[
        {
            "category":"Shopping",
            "subcategory":"Pets & Pet Supplies",
            "type":"Retail Goods"
        }
    ],
    "sg:postcode":"WV5 9EX",
    "sg:province":"Shropshire",
    "sg:tags":[
        "equestrian"
    ],
    "wof:name":"Maslen Thomas",
    "wof:placetype":"venue"
},
  "geometry": {"coordinates":[-2.184359,52.535923],"type":"Point"}
}