{
  "type": "Feature",
  "properties": {
    "iso:country":"GB",
    "sg:address":"34 Langside Drive, Kilbarchan",
    "sg:city":"Johnstone",
    "sg:classifiers":[
        {
            "category":"Sports & Exercise",
            "subcategory":"Golf",
            "type":"Entertainment"
        }
    ],
    "sg:phone":"+44 1505 706767",
    "sg:postcode":"PA10 2EW",
    "sg:province":"Renfrewshire",
    "sg:tags":[
        "greeting",
        "card"
    ],
    "wof:name":"Signature Greetings Card Distributor",
    "wof:placetype":"venue"
},
  "geometry": {"coordinates":[-4.551305,55.833183],"type":"Point"}
}