{
  "type": "Feature",
  "properties": {
    "iso:country":"GB",
    "sg:address":"83a Holyhead Road",
    "sg:city":"Coventry",
    "sg:classifiers":[
        {
            "category":"Building & Trades",
            "subcategory":"Cleaning & Sanitation",
            "type":"Services"
        },
        {
            "category":"Home & Garden",
            "subcategory":"Carpets & Floor Coverings",
            "type":"Retail Goods"
        }
    ],
    "sg:phone":"+44 24 7622 5608",
    "sg:postcode":"CV1 3AA",
    "sg:province":"West Midlands",
    "sg:tags":[
        "cleaner",
        "upholstery"
    ],
    "wof:name":"Miracle Steam Cleaners",
    "wof:placetype":"venue"
},
  "geometry": {"coordinates":[-1.520955,52.410156],"type":"Point"}
}