{
  "type": "Feature",
  "properties": {
    "iso:country":"GB",
    "sg:address":"Aireworth Road",
    "sg:city":"Keighley",
    "sg:classifiers":[
        {
            "category":"Arena",
            "subcategory":"Sports Club",
            "type":"Entertainment"
        },
        {
            "category":"Arena",
            "subcategory":"Stadium",
            "type":"Entertainment"
        },
        {
            "category":"Government",
            "subcategory":"Office",
            "type":"Public Place"
        }
    ],
    "sg:phone":"+44 1535 609910",
    "sg:postcode":"BD21 4DB",
    "sg:province":"West Yorkshire",
    "sg:tags":[
        "local",
        "ground"
    ],
    "wof:name":"Marley Outdoor Activities Centre",
    "wof:placetype":"venue"
},
  "geometry": {"coordinates":[-1.8908890486,53.8750801086],"type":"Point"}
}