{
  "type": "Feature",
  "properties": {
    "addr:full":"29 Crawford St West End Greater London W1H 1PL",
    "addr:housenumber":"29",
    "addr:postcode":"w1h 1pl",
    "addr:street":"Crawford St",
    "iso:country":"GB",
    "sg:address":"29 Crawford St",
    "sg:city":"West End",
    "sg:classifiers":[
        {
            "category":"Organizations",
            "subcategory":"Non-profit Organization",
            "type":"Services"
        }
    ],
    "sg:phone":"+44 20 7724 0473",
    "sg:postcode":"W1H 1PL",
    "sg:province":"Greater London",
    "sg:tags":[
        "organisation",
        "voluntary",
        "charity"
    ],
    "wof:name":"Ability International",
    "wof:placetype":"venue"
},
  "geometry": {"coordinates":[-0.160945,51.519669],"type":"Point"}
}