{
  "type": "Feature",
  "properties": {
    "iso:country":"GB",
    "sg:address":"Cusson Road",
    "sg:city":"Liverpool",
    "sg:classifiers":[
        {
            "category":"Home & Garden",
            "subcategory":"Hardware",
            "type":"Retail Goods"
        }
    ],
    "sg:phone":"+44 151 549 1491",
    "sg:postcode":"L33 7UD",
    "sg:province":"Lancashire",
    "sg:tags":[
        "paint",
        "coating"
    ],
    "wof:name":"Product Release Europe Ltd.",
    "wof:placetype":"venue"
},
  "geometry": {"coordinates":[-2.864765,53.476398],"type":"Point"}
}