{
  "type": "Feature",
  "properties": {
    "addr:full":"5 Vaughan Street Llandudno Conwy LL30 1AB",
    "addr:housenumber":"5",
    "addr:postcode":"ll30 1ab",
    "addr:street":"Vaughan Street",
    "iso:country":"GB",
    "sg:address":"5 Vaughan Street",
    "sg:city":"Llandudno",
    "sg:classifiers":[
        {
            "category":"Professional",
            "subcategory":"Art Services",
            "type":"Services"
        }
    ],
    "sg:phone":"+44 1492 876547",
    "sg:postcode":"LL30 1AB",
    "sg:province":"Conwy",
    "sg:tags":[
        "photographer"
    ],
    "wof:name":"Baxter's Photography",
    "wof:placetype":"venue"
},
  "geometry": {"coordinates":[-3.825942,53.321003],"type":"Point"}
}