{
  "type": "Feature",
  "properties": {
    "addr:full":"Wheatsheaf Farm, Corton Denham Sherborne Dorset DT9 4LQ",
    "addr:postcode":"dt9 4lq",
    "iso:country":"GB",
    "sg:address":"Wheatsheaf Farm, Corton Denham",
    "sg:city":"Sherborne",
    "sg:classifiers":[
        {
            "category":"Farming",
            "subcategory":"Livestock Farm",
            "type":"Manufacturing & Wholesale Goods"
        }
    ],
    "sg:phone":"+44 1963 220318",
    "sg:postcode":"DT9 4LQ",
    "sg:province":"Dorset",
    "sg:tags":[
        "others"
    ],
    "wof:name":"Wheatsheaf Farm",
    "wof:placetype":"venue"
},
  "geometry": {"coordinates":[-2.521419,50.997807],"type":"Point"}
}