{
  "type": "Feature",
  "properties": {
    "addr:full":"Arch Villa, 23 High Street, Bozeat Wellingborough Bedfordshire NN29 7NF",
    "addr:housenumber":"23",
    "addr:postcode":"nn29 7nf",
    "addr:street":"Arch;High Street",
    "iso:country":"GB",
    "sg:address":"Arch Villa, 23 High Street, Bozeat",
    "sg:city":"Wellingborough",
    "sg:classifiers":[
        {
            "category":"Building & Trades",
            "subcategory":"Construction",
            "type":"Services"
        }
    ],
    "sg:phone":"+44 1933 664784",
    "sg:postcode":"NN29 7NF",
    "sg:province":"Bedfordshire",
    "sg:tags":[
        "builder"
    ],
    "wof:name":"Systems & Ceramics Ltd.",
    "wof:placetype":"venue"
},
  "geometry": {"coordinates":[-0.6760280132,52.2217483521],"type":"Point"}
}