{
  "type": "Feature",
  "properties": {
    "addr:full":"Times Ho, Station App Ruislip Greater London HA4 8LD",
    "addr:postcode":"ha4 8ld",
    "iso:country":"GB",
    "sg:address":"Times Ho, Station App",
    "sg:city":"Ruislip",
    "sg:classifiers":[
        {
            "category":"Travel",
            "subcategory":"Travel Agent",
            "type":"Entertainment"
        }
    ],
    "sg:postcode":"HA4 8LD",
    "sg:province":"Greater London",
    "wof:name":"Southmews Holidays",
    "wof:placetype":"venue"
},
  "geometry": {"coordinates":[-0.4214200079,51.5714607239],"type":"Point"}
}