{
  "type": "Feature",
  "properties": {
    "addr:full":"St Andrew's House, 1 Dreadnought Street, Greenwich London Greater London SE10 0PU",
    "addr:housenumber":"1",
    "addr:postcode":"se10 0pu",
    "addr:street":"Dreadnought Street",
    "iso:country":"GB",
    "sg:address":"St Andrew's House, 1 Dreadnought Street, Greenwich",
    "sg:city":"London",
    "sg:classifiers":[
        {
            "category":"Professional",
            "subcategory":"Engineering",
            "type":"Services"
        }
    ],
    "sg:phone":"+44 20 8858 9124",
    "sg:postcode":"SE10 0PU",
    "sg:province":"Greater London",
    "sg:tags":[
        "civil",
        "engineer"
    ],
    "wof:name":"O'Keefe Construction (Greenwich) Ltd.",
    "wof:placetype":"venue"
},
  "geometry": {"coordinates":[0.00514,51.4948501587],"type":"Point"}
}