{
  "type": "Feature",
  "properties": {
    "iso:country":"GB",
    "sg:address":"Priest Park Farm, Warwick Road, Chadwick End",
    "sg:city":"Solihull",
    "sg:classifiers":[
        {
            "category":"Farming",
            "subcategory":"Livestock Farm",
            "type":"Manufacturing & Wholesale Goods"
        }
    ],
    "sg:phone":"+44 1564 782372",
    "sg:postcode":"B93 0BU",
    "sg:province":"Warwickshire",
    "sg:tags":[
        "others"
    ],
    "wof:name":"C A G Cummins & Son",
    "wof:placetype":"venue"
},
  "geometry": {"coordinates":[-1.699089,52.356194],"type":"Point"}
}