{
  "type": "Feature",
  "properties": {
    "iso:country":"GB",
    "sg:address":"30-32 North St",
    "sg:city":"Hailsham",
    "sg:classifiers":[
        {
            "category":"Government",
            "subcategory":"Fire Station",
            "type":"Public Place"
        }
    ],
    "sg:postcode":"BN27 1DW",
    "sg:province":"East Sussex",
    "sg:tags":[
        "security"
    ],
    "wof:name":"Manchester Fire Group Ltd",
    "wof:placetype":"venue"
},
  "geometry": {"coordinates":[0.257623,50.863495],"type":"Point"}
}