{
  "type": "Feature",
  "properties": {
    "addr:full":"44-48 Corporation Street Coventry West Midlands CV1 1GF",
    "addr:housenumber":"44-48",
    "addr:postcode":"cv1 1gf",
    "addr:street":"Corporation Street",
    "iso:country":"GB",
    "sg:address":"44-48 Corporation Street",
    "sg:city":"Coventry",
    "sg:classifiers":[
        {
            "category":"Home & Garden",
            "subcategory":"Furniture",
            "type":"Retail Goods"
        }
    ],
    "sg:phone":"+44 24 7622 4200",
    "sg:postcode":"CV1 1GF",
    "sg:province":"West Midlands",
    "wof:name":"Durham Pine",
    "wof:placetype":"venue"
},
  "geometry": {"coordinates":[-1.514507,52.409248],"type":"Point"}
}