{
  "type": "Feature",
  "properties": {
    "addr:full":"401 Camp Hill Rd Nuneaton Leicestershire CV10 0JU",
    "addr:housenumber":"401",
    "addr:postcode":"cv10 0ju",
    "addr:street":"Camp Hill Rd",
    "iso:country":"GB",
    "sg:address":"401 Camp Hill Rd",
    "sg:city":"Nuneaton",
    "sg:classifiers":[
        {
            "category":"Building & Trades",
            "subcategory":"Construction",
            "type":"Services"
        }
    ],
    "sg:postcode":"CV10 0JU",
    "sg:province":"Leicestershire",
    "sg:tags":[
        "decorator",
        "painter"
    ],
    "wof:name":"Bigginhouse Ltd",
    "wof:placetype":"venue"
},
  "geometry": {"coordinates":[-1.499614954,52.5352783203],"type":"Point"}
}