{
  "type": "Feature",
  "properties": {
    "addr:full":"72 Pendine Clo Cardiff The Vale of Glamorgan CF62 9DE",
    "addr:housenumber":"72",
    "addr:postcode":"cf62 9de",
    "addr:street":"Pendine Clo;Vale",
    "iso:country":"GB",
    "sg:address":"72 Pendine Clo",
    "sg:city":"Cardiff",
    "sg:classifiers":[
        {
            "category":"Shopping",
            "subcategory":"Hobbies, Toys, & Games",
            "type":"Retail Goods"
        },
        {
            "category":"Wholesale",
            "subcategory":"Sporting Goods",
            "type":"Manufacturing & Wholesale Goods"
        }
    ],
    "sg:postcode":"CF62 9DE",
    "sg:province":"The Vale of Glamorgan",
    "sg:tags":[
        "wholesaler",
        "mnfrs",
        "toy",
        "cycle"
    ],
    "wof:name":"Ashman,Philip,",
    "wof:placetype":"venue"
},
  "geometry": {"coordinates":[-3.27047,51.42046],"type":"Point"}
}