{
  "type": "Feature",
  "properties": {
    "addr:full":"Papyrus Rd, Werrington Parkway, Werrington Peterborough Cambridgeshire PE4 5HG",
    "addr:postcode":"pe4 5hg",
    "addr:street":"Papyrus Rd;Parkway",
    "iso:country":"GB",
    "sg:address":"Papyrus Rd, Werrington Parkway, Werrington",
    "sg:city":"Peterborough",
    "sg:classifiers":[
        {
            "category":"Professional",
            "subcategory":"Engineering",
            "type":"Services"
        }
    ],
    "sg:phone":"+44 1733 292200",
    "sg:postcode":"PE4 5HG",
    "sg:province":"Cambridgeshire",
    "wof:name":"Brotherhood,Peter,Ltd",
    "wof:placetype":"venue"
},
  "geometry": {"coordinates":[-0.290536,52.618565],"type":"Point"}
}