{
  "type": "Feature",
  "properties": {
    "addr:full":"Kelso Avenue, Lesmahagow Lanark South Lanarkshire ML11 0BA",
    "addr:postcode":"ml11 0ba",
    "addr:street":"Kelso Avenue",
    "iso:country":"GB",
    "sg:address":"Kelso Avenue, Lesmahagow",
    "sg:city":"Lanark",
    "sg:classifiers":[
        {
            "category":"Organizations",
            "subcategory":"Membership Organization",
            "type":"Services"
        }
    ],
    "sg:phone":"+44 1555 893328",
    "sg:postcode":"ML11 0BA",
    "sg:province":"South Lanarkshire",
    "sg:tags":[
        "club"
    ],
    "wof:name":"Lesmahagow & District Miners Social Club",
    "wof:placetype":"venue"
},
  "geometry": {"coordinates":[-3.8865880966,55.6375961304],"type":"Point"}
}