{
  "type": "Feature",
  "properties": {
    "addr:full":"14 Stuart Street Sutton-in-ashfield Nottinghamshire NG17 5AQ",
    "addr:housenumber":"14",
    "addr:postcode":"ng17 5aq",
    "addr:street":"Stuart Street",
    "iso:country":"GB",
    "sg:address":"14 Stuart Street",
    "sg:city":"Sutton-in-ashfield",
    "sg:classifiers":[
        {
            "category":"Building & Trades",
            "subcategory":"Construction",
            "type":"Services"
        }
    ],
    "sg:phone":"+44 1623 552953",
    "sg:postcode":"NG17 5AQ",
    "sg:province":"Nottinghamshire",
    "sg:tags":[
        "builder"
    ],
    "wof:name":"R P L Builders",
    "wof:placetype":"venue"
},
  "geometry": {"coordinates":[-1.2668399811,53.118434906],"type":"Point"}
}