{
  "type": "Feature",
  "properties": {
    "addr:full":"212 High St North, East Ham London Greater London E6 2JA",
    "addr:housenumber":"212",
    "addr:postcode":"e6 2ja",
    "addr:street":"High St North",
    "iso:country":"GB",
    "sg:address":"212 High St North, East Ham",
    "sg:city":"London",
    "sg:classifiers":[
        {
            "category":"Shopping",
            "subcategory":"Gifts & Souvenirs",
            "type":"Retail Goods"
        }
    ],
    "sg:phone":"+44 20 8548 8466",
    "sg:postcode":"E6 2JA",
    "sg:province":"Greater London",
    "sg:tags":[
        "shop"
    ],
    "wof:name":"Shama's Centre",
    "wof:placetype":"venue"
},
  "geometry": {"coordinates":[0.0513699986,51.5392379761],"type":"Point"}
}