{
  "type": "Feature",
  "properties": {
    "iso:country":"GB",
    "sg:address":"Longridge, Long Ridge Road",
    "sg:city":"Blaydon-on-tyne",
    "sg:classifiers":[
        {
            "category":"Professional",
            "type":"Services"
        }
    ],
    "sg:postcode":"NE21 6JW",
    "sg:province":"Tyne and Wear",
    "sg:tags":[
        "entertainer"
    ],
    "wof:name":"The Mane Traditional Music Agency",
    "wof:placetype":"venue"
},
  "geometry": {"coordinates":[-1.7079429626,54.9630126953],"type":"Point"}
}