{
  "type": "Feature",
  "properties": {
    "iso:country":"GB",
    "sg:address":"Unit 2, Newtown Industrial Estate, Llantwit Fardre",
    "sg:city":"Pontypridd",
    "sg:classifiers":[
        {
            "category":"Building & Trades",
            "subcategory":"Construction",
            "type":"Services"
        }
    ],
    "sg:phone":"+44 1443 209799",
    "sg:postcode":"CF38 2EE",
    "sg:province":"Rhondda, Cynon, Taff",
    "sg:tags":[
        "builder"
    ],
    "wof:name":"Fortrade Ltd.",
    "wof:placetype":"venue"
},
  "geometry": {"coordinates":[-3.3301808834,51.5597877502],"type":"Point"}
}