{
  "type": "Feature",
  "properties": {
    "iso:country":"GB",
    "sg:address":"Creagorry",
    "sg:city":"Isle Of Benbecula",
    "sg:classifiers":[
        {
            "category":"Travel",
            "subcategory":"Hotels & Motels",
            "type":"Entertainment"
        }
    ],
    "sg:phone":"+44 1870 602024",
    "sg:postcode":"HS7 5PG",
    "sg:province":"Eilean Siar",
    "wof:name":"Creagorry Hotel",
    "wof:placetype":"venue"
},
  "geometry": {"coordinates":[-7.333119,57.410049],"type":"Point"}
}