{
  "type": "Feature",
  "properties": {
    "addr:full":"Woodgrove Surgery, 2 Doncaster Rd Rotherham South Yorkshire S63 7AL",
    "addr:housenumber":"2",
    "addr:postcode":"s63 7al",
    "addr:street":"Doncaster Rd",
    "iso:country":"GB",
    "sg:address":"Woodgrove Surgery, 2 Doncaster Rd",
    "sg:city":"Rotherham",
    "sg:classifiers":[
        {
            "category":"Health Services",
            "subcategory":"Doctor",
            "type":"Services"
        }
    ],
    "sg:phone":"+44 1709 763400",
    "sg:postcode":"S63 7AL",
    "sg:province":"South Yorkshire",
    "sg:tags":[
        "practitioners"
    ],
    "wof:name":"Phipps, K",
    "wof:placetype":"venue"
},
  "geometry": {"coordinates":[-1.33867,53.502579],"type":"Point"}
}