{
  "type": "Feature",
  "properties": {
    "addr:full":"3 Beddoes Court, Milford Street Saundersfoot Pembrokeshire SA69 9EW",
    "addr:housenumber":"3",
    "addr:postcode":"sa69 9ew",
    "addr:street":"Beddoes Court Milford Street",
    "iso:country":"GB",
    "sg:address":"3 Beddoes Court, Milford Street",
    "sg:city":"Saundersfoot",
    "sg:classifiers":[
        {
            "category":"Shopping",
            "subcategory":"Gifts & Souvenirs",
            "type":"Retail Goods"
        }
    ],
    "sg:phone":"+44 1834 814680",
    "sg:postcode":"SA69 9EW",
    "sg:province":"Pembrokeshire",
    "sg:tags":[
        "shop"
    ],
    "wof:name":"The Famous Pound Shop",
    "wof:placetype":"venue"
},
  "geometry": {"coordinates":[-4.699556,51.710205],"type":"Point"}
}