{
  "type": "Feature",
  "properties": {
    "addr:full":"25c Leconfield Rd Highbury Greater London N5 2RZ",
    "addr:housenumber":"25c",
    "addr:postcode":"n5 2rz",
    "addr:street":"Leconfield Rd",
    "iso:country":"GB",
    "sg:address":"25c Leconfield Rd",
    "sg:city":"Highbury",
    "sg:classifiers":[
        {
            "category":"Home & Garden",
            "subcategory":"Kitchen Supply",
            "type":"Retail Goods"
        }
    ],
    "sg:phone":"+44 20 7354 2234",
    "sg:postcode":"N5 2RZ",
    "sg:province":"Greater London",
    "sg:tags":[
        "equipment",
        "catering"
    ],
    "wof:name":"Mussy Catering",
    "wof:placetype":"venue"
},
  "geometry": {"coordinates":[-0.0891479999,51.5536499023],"type":"Point"}
}