{
  "type": "Feature",
  "properties": {
    "iso:country":"GB",
    "sg:address":"26 Lessness Road",
    "sg:city":"Morden",
    "sg:classifiers":[
        {
            "category":"Building & Trades",
            "subcategory":"Construction",
            "type":"Services"
        }
    ],
    "sg:phone":"+44 20 8715 7241",
    "sg:postcode":"SM4 6HP",
    "sg:province":"Surrey",
    "sg:tags":[
        "contractor",
        "paving",
        "driveway"
    ],
    "wof:name":"B B S",
    "wof:placetype":"venue"
},
  "geometry": {"coordinates":[-0.183022,51.39283],"type":"Point"}
}