{
  "type": "Feature",
  "properties": {
    "iso:country":"GB",
    "sg:address":"The Market Hall, The Brook",
    "sg:city":"Chatham",
    "sg:classifiers":[
        {
            "category":"Food & Beverages",
            "subcategory":"Supermarket",
            "type":"Retail Goods"
        }
    ],
    "sg:phone":"+44 1634 840817",
    "sg:postcode":"ME4 4NX",
    "sg:province":"Kent",
    "wof:name":"Coslo (Kent) Ltd.",
    "wof:placetype":"venue"
},
  "geometry": {"coordinates":[0.52601,51.385529],"type":"Point"}
}