{
  "type": "Feature",
  "properties": {
    "iso:country":"GB",
    "sg:address":"63-65 Crewe Road, Alsager",
    "sg:city":"Stoke-on-trent",
    "sg:classifiers":[
        {
            "category":"Shopping",
            "subcategory":"News",
            "type":"Retail Goods"
        }
    ],
    "sg:phone":"+44 1270 872493",
    "sg:postcode":"ST7 2EZ",
    "sg:province":"Cheshire",
    "sg:tags":[
        "newsagent"
    ],
    "wof:name":"Fryer's",
    "wof:placetype":"venue"
},
  "geometry": {"coordinates":[-2.310288,53.095833],"type":"Point"}
}