{
  "type": "Feature",
  "properties": {
    "iso:country":"GB",
    "sg:address":"Dallerie",
    "sg:city":"Crieff",
    "sg:classifiers":[
        {
            "category":"Professional",
            "subcategory":"Management & Consulting",
            "type":"Services"
        }
    ],
    "sg:phone":"+44 1738 551597",
    "sg:postcode":"PH7 4HR",
    "sg:province":"Perth and Kinross",
    "sg:tags":[
        "sport"
    ],
    "wof:name":"S M Morsehead",
    "wof:placetype":"venue"
},
  "geometry": {"coordinates":[-3.848789,56.372456],"type":"Point"}
}