{
  "type": "Feature",
  "properties": {
    "addr:full":"151-153 Greyhound Lane, Streatham Common Streatham Greater London SW16 5NJ",
    "addr:housenumber":"151-153",
    "addr:postcode":"streatham;london sw16 5nj",
    "addr:street":"Greyhound Lane;Common",
    "iso:country":"GB",
    "sg:address":"151-153 Greyhound Lane, Streatham Common",
    "sg:city":"Streatham",
    "sg:classifiers":[
        {
            "category":"Bars & Pubs",
            "type":"Food & Drink"
        }
    ],
    "sg:phone":"+44 20 8677 9962",
    "sg:postcode":"SW16 5NJ",
    "sg:province":"Greater London",
    "sg:tags":[
        "pubs",
        "inn"
    ],
    "wof:name":"The Greyhound",
    "wof:placetype":"venue"
},
  "geometry": {"coordinates":[-0.129448995,51.4216499329],"type":"Point"}
}