{
  "type": "Feature",
  "properties": {
    "iso:country":"GB",
    "sg:address":"West End Rd",
    "sg:city":"Broxbourne",
    "sg:classifiers":[
        {
            "category":"Home & Garden",
            "subcategory":"Garden Supply",
            "type":"Retail Goods"
        }
    ],
    "sg:postcode":"EN10 7QN",
    "sg:province":"Essex",
    "sg:tags":[
        "nursery",
        "centre"
    ],
    "wof:name":"Brookfield Nursery",
    "wof:placetype":"venue"
},
  "geometry": {"coordinates":[-0.06793,51.739269],"type":"Point"}
}