{
  "type": "Feature",
  "properties": {
    "iso:country":"GB",
    "sg:address":"105-107 Church Street",
    "sg:city":"Inverness",
    "sg:classifiers":[
        {
            "category":"Sports & Exercise",
            "subcategory":"Sports Center",
            "type":"Entertainment"
        }
    ],
    "sg:postcode":"IV1 1EY",
    "sg:province":"Highland",
    "sg:tags":[
        "shop",
        "good"
    ],
    "wof:name":"Coutts Sports",
    "wof:placetype":"venue"
},
  "geometry": {"coordinates":[-4.22822,57.479912],"type":"Point"}
}