{
  "type": "Feature",
  "properties": {
    "addr:full":"169 London Road, New Balderton Newark Nottinghamshire NG24 3AB",
    "addr:housenumber":"169",
    "addr:postcode":"ng24 3ab",
    "addr:street":"London Road New",
    "iso:country":"GB",
    "sg:address":"169 London Road, New Balderton",
    "sg:city":"Newark",
    "sg:classifiers":[
        {
            "category":"Military Area",
            "subcategory":"Air Force Base",
            "type":"Public Place"
        }
    ],
    "sg:phone":"+44 1636 677777",
    "sg:postcode":"NG24 3AB",
    "sg:province":"Nottinghamshire",
    "sg:tags":[
        "taxi",
        "hire",
        "private"
    ],
    "wof:name":"A B C Pete's Taxis",
    "wof:placetype":"venue"
},
  "geometry": {"coordinates":[-0.7855229974,53.0586433411],"type":"Point"}
}