{
  "type": "Feature",
  "properties": {
    "addr:full":"Unit 20 The Hopewell Business Centre, 105 Hopewell Dr Chatham Kent ME5 7NP",
    "addr:housenumber":"unit 20;105",
    "addr:postcode":"me5 7np",
    "addr:street":"The;Hopewell Dr",
    "iso:country":"GB",
    "sg:address":"Unit 20 The Hopewell Business Centre, 105 Hopewell Dr",
    "sg:city":"Chatham",
    "sg:classifiers":[
        {
            "category":"Retail",
            "subcategory":"Repair Shop",
            "type":"Services"
        }
    ],
    "sg:phone":"+44 1634 309444",
    "sg:postcode":"ME5 7NP",
    "sg:province":"Kent",
    "sg:tags":[
        "maintenance"
    ],
    "wof:name":"Empire Property Services Ltd",
    "wof:placetype":"venue"
},
  "geometry": {"coordinates":[0.54527,51.364109],"type":"Point"}
}