{
  "type": "Feature",
  "properties": {
    "iso:country":"GB",
    "sg:address":"179 Ferensway",
    "sg:city":"Hull",
    "sg:classifiers":[
        {
            "category":"Shopping",
            "subcategory":"Department Store",
            "type":"Retail Goods"
        }
    ],
    "sg:phone":"+44 1482 329199",
    "sg:postcode":"HU1 3UA",
    "sg:province":"East Riding of Yorkshire",
    "wof:name":"Model Shop",
    "wof:placetype":"venue"
},
  "geometry": {"coordinates":[-0.344316,53.743641],"type":"Point"}
}