{
  "type": "Feature",
  "properties": {
    "iso:country":"GB",
    "sg:address":"23 Meliden Road",
    "sg:city":"Prestatyn",
    "sg:classifiers":[
        {
            "category":"Shopping",
            "subcategory":"Clothing, Apparel, & Fashions",
            "type":"Retail Goods"
        }
    ],
    "sg:phone":"+44 1745 889449",
    "sg:postcode":"LL19 9SD",
    "sg:province":"Denbighshire",
    "sg:tags":[
        "dresswear"
    ],
    "wof:name":"Justins",
    "wof:placetype":"venue"
},
  "geometry": {"coordinates":[-3.401981,53.331017],"type":"Point"}
}