{
  "type": "Feature",
  "properties": {
    "iso:country":"GB",
    "sg:address":"405a Belchers Lane",
    "sg:city":"Birmingham",
    "sg:classifiers":[
        {
            "category":"Farming",
            "subcategory":"Nursery",
            "type":"Manufacturing & Wholesale Goods"
        },
        {
            "category":"Education",
            "subcategory":"Preschool",
            "type":"Public Place"
        }
    ],
    "sg:phone":"+44 121 773 1748",
    "sg:postcode":"B9 5SY",
    "sg:province":"West Midlands",
    "sg:tags":[
        "school",
        "creche"
    ],
    "wof:name":"Crossover Enterprises Ltd.",
    "wof:placetype":"venue"
},
  "geometry": {"coordinates":[-1.8341610432,52.4789237976],"type":"Point"}
}