{
  "type": "Feature",
  "properties": {
    "iso:country":"GB",
    "sg:address":"815 Huddersfield Road",
    "sg:city":"Dewsbury",
    "sg:classifiers":[
        {
            "category":"Bars & Pubs",
            "type":"Food & Drink"
        }
    ],
    "sg:phone":"+44 1924 498999",
    "sg:postcode":"WF13 3LR",
    "sg:province":"West Yorkshire",
    "sg:tags":[
        "pubs",
        "inn"
    ],
    "wof:name":"The Bulls Head",
    "wof:placetype":"venue"
},
  "geometry": {"coordinates":[-1.6704679728,53.676448822],"type":"Point"}
}