{
  "type": "Feature",
  "properties": {
    "iso:country":"GB",
    "sg:address":"32 West St",
    "sg:city":"Leominster",
    "sg:classifiers":[
        {
            "category":"Professional",
            "subcategory":"Printing & Photocopies",
            "type":"Services"
        }
    ],
    "sg:phone":"+44 1568 610868",
    "sg:postcode":"HR6 8EP",
    "sg:province":"Herefordshire",
    "sg:tags":[
        "duplicating",
        "copying"
    ],
    "wof:name":"Centre Print Retail",
    "wof:placetype":"venue"
},
  "geometry": {"coordinates":[-2.7405,52.22699],"type":"Point"}
}