{
  "type": "Feature",
  "properties": {
    "addr:full":"90 Victoria Road Swindon Wiltshire SN1 3BD",
    "addr:housenumber":"90",
    "addr:postcode":"sn1 3bd",
    "addr:street":"Victoria Road",
    "iso:country":"GB",
    "sg:address":"90 Victoria Road",
    "sg:city":"Swindon",
    "sg:classifiers":[
        {
            "category":"Restaurant",
            "type":"Food & Drink"
        }
    ],
    "sg:phone":"+44 1793 521114",
    "sg:postcode":"SN1 3BD",
    "sg:province":"Wiltshire",
    "sg:tags":[
        "indian"
    ],
    "wof:name":"Curry Garden Tandoori Restaurant",
    "wof:placetype":"venue"
},
  "geometry": {"coordinates":[-1.7770040035,51.5535545349],"type":"Point"}
}