{
  "type": "Feature",
  "properties": {
    "addr:full":"44a Caves Road St Leonards-on-sea East Sussex TN38 0BY",
    "addr:housenumber":"44a",
    "addr:postcode":"leonards-on-sea;tn38 0by",
    "addr:street":"Caves Road St",
    "iso:country":"GB",
    "sg:address":"44a Caves Road",
    "sg:city":"St Leonards-on-sea",
    "sg:classifiers":[
        {
            "category":"Retail",
            "subcategory":"Auto Repair",
            "type":"Services"
        }
    ],
    "sg:postcode":"TN38 0BY",
    "sg:province":"East Sussex",
    "sg:tags":[
        "modification",
        "garage"
    ],
    "wof:name":"Roy Page",
    "wof:placetype":"venue"
},
  "geometry": {"coordinates":[0.545801,50.851219],"type":"Point"}
}