{
  "type": "Feature",
  "properties": {
    "addr:full":"Camp Street Industrial Estate, Camp Street, Elton Bury Lancashire BL8 1FZ",
    "addr:housenumber":"estate",
    "addr:postcode":"bl8 1fz",
    "addr:street":"Camp Street Industrial;Camp Street",
    "iso:country":"GB",
    "sg:address":"Camp Street Industrial Estate, Camp Street, Elton",
    "sg:city":"Bury",
    "sg:classifiers":[
        {
            "category":"Building & Trades",
            "subcategory":"Construction",
            "type":"Services"
        }
    ],
    "sg:phone":"+44 161 761 7988",
    "sg:postcode":"BL8 1FZ",
    "sg:province":"Lancashire",
    "sg:tags":[
        "equipment"
    ],
    "wof:name":"G Mortimer Crane Hire Ltd.",
    "wof:placetype":"venue"
},
  "geometry": {"coordinates":[-2.3170940876,53.5971946716],"type":"Point"}
}