{
  "type": "Feature",
  "properties": {
    "addr:full":"2 Cheney Manor Rd Swindon Wiltshire SN2 2NS",
    "addr:housenumber":"2",
    "addr:postcode":"sn2 2ns",
    "addr:street":"Cheney Manor Rd",
    "iso:country":"GB",
    "sg:address":"2 Cheney Manor Rd",
    "sg:city":"Swindon",
    "sg:classifiers":[
        {
            "category":"Shopping",
            "subcategory":"News",
            "type":"Retail Goods"
        }
    ],
    "sg:phone":"+44 1793 521224",
    "sg:postcode":"SN2 2NS",
    "sg:province":"Wiltshire",
    "sg:tags":[
        "newsagent"
    ],
    "wof:name":"Baileys Corner Newsagents",
    "wof:placetype":"venue"
},
  "geometry": {"coordinates":[-1.801456,51.571205],"type":"Point"}
}