{
  "type": "Feature",
  "properties": {
    "iso:country":"GB",
    "sg:address":"44 Cheapside",
    "sg:city":"Barnsley",
    "sg:classifiers":[
        {
            "category":"Shopping",
            "subcategory":"Comic Books",
            "type":"Retail Goods"
        }
    ],
    "sg:phone":"+44 1226 733997",
    "sg:postcode":"S70 1RU",
    "sg:province":"South Yorkshire",
    "sg:tags":[
        "jeweller",
        "sale",
        "jewellery"
    ],
    "wof:name":"Warren James (Jewellers) Ltd.",
    "wof:placetype":"venue"
},
  "geometry": {"coordinates":[-1.479066,53.551544],"type":"Point"}
}