{
  "type": "Feature",
  "properties": {
    "iso:country":"GB",
    "sg:address":"Germoe Cross Roads, Germoe Lane, Germoe",
    "sg:city":"Penzance",
    "sg:classifiers":[
        {
            "category":"Education",
            "subcategory":"School",
            "type":"Public Place"
        }
    ],
    "sg:phone":"+44 1736 763310",
    "sg:postcode":"TR20 9QY",
    "sg:province":"Cornwall",
    "sg:tags":[
        "local",
        "authority"
    ],
    "wof:name":"Germoe County Primary School",
    "wof:placetype":"venue"
},
  "geometry": {"coordinates":[-5.382154,50.112789],"type":"Point"}
}