{
  "type": "Feature",
  "properties": {
    "addr:full":"Cherry Orchard House Pershore Worcestershire WR10 1EZ",
    "addr:postcode":"wr10 1ez",
    "addr:street":"Pershore",
    "iso:country":"GB",
    "sg:address":"Cherry Orchard House",
    "sg:city":"Pershore",
    "sg:classifiers":[
        {
            "category":"Organizations",
            "subcategory":"Non-profit Organization",
            "type":"Services"
        }
    ],
    "sg:phone":"+44 1386 561027",
    "sg:postcode":"WR10 1EZ",
    "sg:province":"Worcestershire",
    "sg:tags":[
        "organisation",
        "voluntary",
        "charity"
    ],
    "wof:name":"Womens Royal Voluntary Service Meals on Wheels Kit",
    "wof:placetype":"venue"
},
  "geometry": {"coordinates":[-2.0793390274,52.1137657166],"type":"Point"}
}