{
  "type": "Feature",
  "properties": {
    "addr:full":"Ashleigh House, Brushfor Dulverton Devon TA22 9AP",
    "addr:postcode":"ta22 9ap",
    "addr:street":"Brushfor",
    "iso:country":"GB",
    "sg:address":"Ashleigh House, Brushfor",
    "sg:city":"Dulverton",
    "sg:classifiers":[
        {
            "category":"Building & Trades",
            "subcategory":"Construction",
            "type":"Services"
        }
    ],
    "sg:phone":"+44 1398 323875",
    "sg:postcode":"TA22 9AP",
    "sg:province":"Devon",
    "sg:tags":[
        "builder"
    ],
    "wof:name":"R H J Lazarus",
    "wof:placetype":"venue"
},
  "geometry": {"coordinates":[-3.5504629612,51.0399169922],"type":"Point"}
}