{
  "type": "Feature",
  "properties": {
    "iso:country":"GB",
    "sg:address":"5 Argyle Street",
    "sg:city":"Bath",
    "sg:classifiers":[
        {
            "category":"Professional",
            "type":"Services"
        }
    ],
    "sg:postcode":"BA2 4BA",
    "sg:province":"Somerset",
    "sg:tags":[
        "caterer"
    ],
    "wof:name":"Milburns Restaurants Ltd.",
    "wof:placetype":"venue"
},
  "geometry": {"coordinates":[-2.357681,51.383278],"type":"Point"}
}