{
  "type": "Feature",
  "properties": {
    "iso:country":"GB",
    "sg:address":"Builders Yard, Duke Street, Hintelsham",
    "sg:city":"Ipswich",
    "sg:classifiers":[
        {
            "category":"Home & Garden",
            "subcategory":"Garden Supply",
            "type":"Retail Goods"
        }
    ],
    "sg:phone":"+44 1473 652048",
    "sg:postcode":"IP8 3QP",
    "sg:province":"Suffolk",
    "sg:tags":[
        "turfing"
    ],
    "wof:name":"Ipswich Turf Supply",
    "wof:placetype":"venue"
},
  "geometry": {"coordinates":[1.03045,52.042278],"type":"Point"}
}