{
  "type": "Feature",
  "properties": {
    "iso:country":"GB",
    "sg:address":"White Cottage, Bearwood Path",
    "sg:city":"Wokingham",
    "sg:classifiers":[
        {
            "category":"Professional",
            "subcategory":"Engineering",
            "type":"Services"
        }
    ],
    "sg:phone":"+44 1734 786740",
    "sg:postcode":"RG41 5EY",
    "sg:province":"Berkshire",
    "sg:tags":[
        "contractor",
        "electrical",
        "engineer"
    ],
    "wof:name":"J W H Bowden (electrical)",
    "wof:placetype":"venue"
},
  "geometry": {"coordinates":[-0.88823,51.431992],"type":"Point"}
}