{
  "type": "Feature",
  "properties": {
    "iso:country":"GB",
    "sg:address":"80 Grosvenor Road",
    "sg:city":"Tunbridge Wells",
    "sg:classifiers":[
        {
            "category":"Home & Garden",
            "subcategory":"Furniture",
            "type":"Retail Goods"
        }
    ],
    "sg:phone":"+44 1892 548337",
    "sg:postcode":"TN1 2AS",
    "sg:province":"Kent",
    "sg:tags":[
        "outlet"
    ],
    "wof:name":"Preferably Pine",
    "wof:placetype":"venue"
},
  "geometry": {"coordinates":[0.26228,51.136776],"type":"Point"}
}