{
  "type": "Feature",
  "properties": {
    "iso:country":"GB",
    "sg:address":"15 Wardieburn St West",
    "sg:city":"Edinburgh",
    "sg:classifiers":[
        {
            "category":"Social Services",
            "subcategory":"Adult Care",
            "type":"Services"
        }
    ],
    "sg:phone":"+44 131 552 8647",
    "sg:postcode":"EH5 2DA",
    "sg:province":"City of Edinburgh",
    "sg:tags":[
        "day",
        "centre"
    ],
    "wof:name":"Granton Day Centre",
    "wof:placetype":"venue"
},
  "geometry": {"coordinates":[-3.227704,55.976269],"type":"Point"}
}