{
  "type": "Feature",
  "properties": {
    "addr:full":"Anchor Lane, Ingoldmells Skegness Lincolnshire PE25 1LX",
    "addr:postcode":"pe25 1lx",
    "addr:street":"Anchor Lane",
    "iso:country":"GB",
    "sg:address":"Anchor Lane, Ingoldmells",
    "sg:city":"Skegness",
    "sg:classifiers":[
        {
            "category":"Recreation",
            "subcategory":"Amusement Park",
            "type":"Entertainment"
        }
    ],
    "sg:phone":"+44 1754 874027",
    "sg:postcode":"PE25 1LX",
    "sg:province":"Lincolnshire",
    "sg:tags":[
        "arcade"
    ],
    "wof:name":"Funtasia",
    "wof:placetype":"venue"
},
  "geometry": {"coordinates":[0.338576,53.199814],"type":"Point"}
}