{
  "type": "Feature",
  "properties": {
    "addr:full":"76 High Street, Talke Pits Stoke-on-trent Cheshire ST7 1PY",
    "addr:housenumber":"76",
    "addr:postcode":"st7 1py",
    "addr:street":"High Street",
    "iso:country":"GB",
    "sg:address":"76 High Street, Talke Pits",
    "sg:city":"Stoke-on-trent",
    "sg:classifiers":[
        {
            "category":"Manufacturing",
            "subcategory":"Petroleum Products",
            "type":"Manufacturing & Wholesale Goods"
        }
    ],
    "sg:phone":"+44 1782 777158",
    "sg:postcode":"ST7 1PY",
    "sg:province":"Cheshire",
    "sg:tags":[
        "double",
        "glazing"
    ],
    "wof:name":"North Staffs Windows & Conservatories",
    "wof:placetype":"venue"
},
  "geometry": {"coordinates":[-2.260265,53.071373],"type":"Point"}
}