{
  "type": "Feature",
  "properties": {
    "addr:full":"133 Broad Lane Coventry West Midlands CV5 7AL",
    "addr:housenumber":"133",
    "addr:postcode":"cv5 7al",
    "addr:street":"Broad Lane",
    "iso:country":"GB",
    "sg:address":"133 Broad Lane",
    "sg:city":"Coventry",
    "sg:classifiers":[
        {
            "category":"Professional",
            "subcategory":"Business Services",
            "type":"Services"
        },
        {
            "category":"Organizations",
            "subcategory":"Non-profit Organization",
            "type":"Services"
        }
    ],
    "sg:phone":"+44 24 7671 1444",
    "sg:postcode":"CV5 7AL",
    "sg:province":"West Midlands",
    "sg:tags":[
        "organisation",
        "agent",
        "charitable",
        "export",
        "import",
        "charity"
    ],
    "wof:name":"Developing Nations Children Foundation",
    "wof:placetype":"venue"
},
  "geometry": {"coordinates":[-1.558485,52.40675],"type":"Point"}
}