{
  "type": "Feature",
  "properties": {
    "addr:full":"Brae Croft, Muiresk Turriff Aberdeenshire AB53 4HE",
    "addr:postcode":"ab53 4he",
    "addr:street":"Brae;Muiresk",
    "iso:country":"GB",
    "sg:address":"Brae Croft, Muiresk",
    "sg:city":"Turriff",
    "sg:classifiers":[
        {
            "category":"Transit Center",
            "subcategory":"Freight",
            "type":"Transportation"
        }
    ],
    "sg:phone":"+44 1888 563544",
    "sg:postcode":"AB53 4HE",
    "sg:province":"Aberdeenshire",
    "sg:tags":[
        "shop",
        "craft",
        "centre"
    ],
    "wof:name":"David Russell Gurney",
    "wof:placetype":"venue"
},
  "geometry": {"coordinates":[-2.455229,57.539902],"type":"Point"}
}