{
  "type": "Feature",
  "properties": {
    "iso:country":"GB",
    "sg:address":"23 High St",
    "sg:city":"Market Drayton",
    "sg:classifiers":[
        {
            "category":"Home & Garden",
            "subcategory":"Home Furnishings",
            "type":"Retail Goods"
        }
    ],
    "sg:postcode":"TF9 1QF",
    "sg:province":"Shropshire",
    "sg:tags":[
        "blind",
        "curtain",
        "fitting"
    ],
    "wof:name":"Hallahan",
    "wof:placetype":"venue"
},
  "geometry": {"coordinates":[-2.483925,52.904049],"type":"Point"}
}