{
  "type": "Feature",
  "properties": {
    "iso:country":"GB",
    "sg:address":"2 Seabrook Drive",
    "sg:city":"West Wickham",
    "sg:classifiers":[
        {
            "category":"Shopping",
            "type":"Retail Goods"
        }
    ],
    "sg:postcode":"BR4 9AJ",
    "sg:province":"Kent",
    "sg:tags":[
        "equipment",
        "clothing",
        "safety"
    ],
    "wof:name":"Mipeg Ltd.",
    "wof:placetype":"venue"
},
  "geometry": {"coordinates":[-0.002698,51.373287],"type":"Point"}
}