{
  "type": "Feature",
  "properties": {
    "addr:full":"20 Deans Yard London Greater London SW1P 3PA",
    "addr:housenumber":"20",
    "addr:postcode":"sw1p 3pa",
    "addr:street":"Deans Yard",
    "iso:country":"GB",
    "sg:address":"20 Deans Yard",
    "sg:city":"London",
    "sg:classifiers":[
        {
            "category":"Museum",
            "subcategory":"Art Museum",
            "type":"Entertainment"
        }
    ],
    "sg:postcode":"SW1P 3PA",
    "sg:province":"Greater London",
    "sg:tags":[
        "gallery"
    ],
    "wof:name":"Westminster Abbey Museum",
    "wof:placetype":"venue"
},
  "geometry": {"coordinates":[-0.127994,51.500065],"type":"Point"}
}