{
  "type": "Feature",
  "properties": {
    "iso:country":"GB",
    "sg:address":"19 East Street",
    "sg:city":"Southampton",
    "sg:classifiers":[
        {
            "category":"Shopping",
            "subcategory":"Photographic Equipment",
            "type":"Retail Goods"
        }
    ],
    "sg:phone":"+44 23 8063 8753",
    "sg:postcode":"SO14 3HG",
    "sg:province":"Hampshire",
    "sg:tags":[
        "supply"
    ],
    "wof:name":"Jessop Photo Video Centre",
    "wof:placetype":"venue"
},
  "geometry": {"coordinates":[-1.4017699957,50.9018936157],"type":"Point"}
}