{
  "type": "Feature",
  "properties": {
    "iso:country":"GB",
    "sg:address":"278/286 High Street",
    "sg:city":"Slough",
    "sg:classifiers":[
        {
            "category":"Museum",
            "subcategory":"Art Museum",
            "type":"Entertainment"
        }
    ],
    "sg:postcode":"SL1 1NB",
    "sg:province":"Berkshire",
    "sg:tags":[
        "gallery"
    ],
    "wof:name":"Slough Museum",
    "wof:placetype":"venue"
},
  "geometry": {"coordinates":[-0.586361,51.507298],"type":"Point"}
}