{
  "type": "Feature",
  "properties": {
    "iso:country":"GB",
    "sg:address":"26 Ysguthan Road",
    "sg:city":"Port Talbot",
    "sg:classifiers":[
        {
            "category":"Personal",
            "subcategory":"Tattoo Parlor",
            "type":"Services"
        }
    ],
    "sg:postcode":"SA12 6LY",
    "sg:province":"Neath Port Talbot",
    "sg:tags":[
        "tattooing",
        "piercing"
    ],
    "wof:name":"Skin Deep Tatooing",
    "wof:placetype":"venue"
},
  "geometry": {"coordinates":[-3.794529,51.594261],"type":"Point"}
}