{
  "type": "Feature",
  "properties": {
    "addr:full":"Unit 3 97 Tindal Street Birmingham West Midlands B12 9TU",
    "addr:housenumber":"unit;97",
    "addr:postcode":"b12 9tu",
    "addr:street":"Tindal Street",
    "iso:country":"GB",
    "sg:address":"Unit 3 97 Tindal Street",
    "sg:city":"Birmingham",
    "sg:classifiers":[
        {
            "category":"Autos & Motor Vehicles",
            "subcategory":"Auto Supplies",
            "type":"Retail Goods"
        }
    ],
    "sg:postcode":"B12 9TU",
    "sg:province":"West Midlands",
    "sg:tags":[
        "car",
        "audio"
    ],
    "wof:name":"Mr Fixit",
    "wof:placetype":"venue"
},
  "geometry": {"coordinates":[-1.8893100023,52.454990387],"type":"Point"}
}