{
  "type": "Feature",
  "properties": {
    "iso:country":"GB",
    "sg:address":"5a Devon Ho, Hermon Hill",
    "sg:city":"London",
    "sg:classifiers":[
        {
            "category":"Shopping",
            "subcategory":"Department Store",
            "type":"Retail Goods"
        },
        {
            "category":"Shopping",
            "subcategory":"Musical Instruments",
            "type":"Retail Goods"
        },
        {
            "category":"Transit Center",
            "subcategory":"Freight",
            "type":"Transportation"
        }
    ],
    "sg:phone":"+44 20 8530 3808",
    "sg:postcode":"E11 2AW",
    "sg:province":"Greater London",
    "sg:tags":[
        "music",
        "piano",
        "sheet",
        "accessory"
    ],
    "wof:name":"Goring,Reg,",
    "wof:placetype":"venue"
},
  "geometry": {"coordinates":[0.02384,51.580399],"type":"Point"}
}