{
  "type": "Feature",
  "properties": {
    "iso:country":"GB",
    "sg:address":"227 Commercial Rd",
    "sg:city":"Portsmouth",
    "sg:classifiers":[
        {
            "category":"Bars & Pubs",
            "type":"Food & Drink"
        }
    ],
    "sg:phone":"+44 23 9285 2951",
    "sg:postcode":"PO1 4BJ",
    "sg:province":"Hampshire",
    "sg:tags":[
        "pubs",
        "inn"
    ],
    "wof:name":"Martha's",
    "wof:placetype":"venue"
},
  "geometry": {"coordinates":[-1.087841,50.80278],"type":"Point"}
}