{
  "type": "Feature",
  "properties": {
    "addr:full":"11 Churchill Lodge, Savill Row Woodford Green Essex IG8 0UE",
    "addr:housenumber":"11",
    "addr:postcode":"ig8 0ue",
    "addr:street":"Churchill Lodge Savill Row",
    "iso:country":"GB",
    "sg:address":"11 Churchill Lodge, Savill Row",
    "sg:city":"Woodford Green",
    "sg:classifiers":[
        {
            "category":"Banks & Credit Unions",
            "subcategory":"Financial Services",
            "type":"Services"
        }
    ],
    "sg:postcode":"IG8 0UE",
    "sg:province":"Essex",
    "sg:tags":[
        "consultant"
    ],
    "wof:name":"Winza Financial Dealers Ltd",
    "wof:placetype":"venue"
},
  "geometry": {"coordinates":[0.028982,51.604389],"type":"Point"}
}