{
  "type": "Feature",
  "properties": {
    "addr:full":"217-219 High Street Bradford West Yorkshire BD6 1QR",
    "addr:housenumber":"217-219",
    "addr:postcode":"bd6 1qr",
    "addr:street":"High Street",
    "iso:country":"GB",
    "sg:address":"217-219 High Street",
    "sg:city":"Bradford",
    "sg:classifiers":[
        {
            "category":"Cafe",
            "type":"Food & Drink"
        }
    ],
    "sg:phone":"+44 1274 770190",
    "sg:postcode":"BD6 1QR",
    "sg:province":"West Yorkshire",
    "sg:tags":[
        "tea",
        "room"
    ],
    "wof:name":"Cosy Corner Tea Shop",
    "wof:placetype":"venue"
},
  "geometry": {"coordinates":[-1.774443984,53.7667579651],"type":"Point"}
}