{
  "type": "Feature",
  "properties": {
    "addr:full":"30 Heathmoor Way Halifax West Yorkshire HX2 9LT",
    "addr:housenumber":"30",
    "addr:postcode":"hx2 9lt",
    "addr:street":"Heathmoor Way",
    "iso:country":"GB",
    "sg:address":"30 Heathmoor Way",
    "sg:city":"Halifax",
    "sg:classifiers":[
        {
            "category":"Building & Trades",
            "subcategory":"Construction",
            "type":"Services"
        }
    ],
    "sg:postcode":"HX2 9LT",
    "sg:province":"West Yorkshire",
    "sg:tags":[
        "builder"
    ],
    "wof:name":"Apex Property Services",
    "wof:placetype":"venue"
},
  "geometry": {"coordinates":[-1.896264,53.753529],"type":"Point"}
}