{
  "type": "Feature",
  "properties": {
    "addr:full":"158 Camden Street London Greater London NW1 9PA",
    "addr:housenumber":"158",
    "addr:postcode":"nw1 9pa",
    "addr:street":"Camden Street",
    "iso:country":"GB",
    "sg:address":"158 Camden Street",
    "sg:city":"London",
    "sg:classifiers":[
        {
            "category":"Shopping",
            "subcategory":"Antiques",
            "type":"Retail Goods"
        }
    ],
    "sg:phone":"+44 20 7267 4324",
    "sg:postcode":"NW1 9PA",
    "sg:province":"Greater London",
    "wof:name":"Art Furniture",
    "wof:placetype":"venue"
},
  "geometry": {"coordinates":[-0.140748,51.541821],"type":"Point"}
}