{
  "type": "Feature",
  "properties": {
    "iso:country":"GB",
    "sg:address":"107-115 Seven Sisters Road",
    "sg:city":"London",
    "sg:classifiers":[
        {
            "category":"Arena",
            "subcategory":"Sports Club",
            "type":"Entertainment"
        }
    ],
    "sg:postcode":"N7 7QG",
    "sg:province":"Greater London",
    "wof:name":"World Boxing Council",
    "wof:placetype":"venue"
},
  "geometry": {"coordinates":[-0.114229,51.560837],"type":"Point"}
}