{
  "type": "Feature",
  "properties": {
    "iso:country":"GB",
    "sg:address":"206 Victory Business Centre, Somers Road North",
    "sg:city":"Portsmouth",
    "sg:classifiers":[
        {
            "category":"Wholesale",
            "subcategory":"Books, Periodicals, & Newspapers",
            "type":"Manufacturing & Wholesale Goods"
        }
    ],
    "sg:phone":"+44 23 9278 3322",
    "sg:postcode":"PO1 1PJ",
    "sg:province":"Hampshire",
    "sg:tags":[
        "publishing"
    ],
    "wof:name":"Ideas Unlimited (Publishing)",
    "wof:placetype":"venue"
},
  "geometry": {"coordinates":[-1.087284,50.804008],"type":"Point"}
}