{
  "type": "Feature",
  "properties": {
    "iso:country":"GB",
    "sg:address":"Carlton House",
    "sg:city":"Cheltenham",
    "sg:classifiers":[
        {
            "category":"Insurance",
            "subcategory":"Insurance Agent",
            "type":"Services"
        }
    ],
    "sg:postcode":"GL53 7HQ",
    "sg:province":"Gloucestershire",
    "wof:name":"Hollands Insurance Services Ltd.",
    "wof:placetype":"venue"
},
  "geometry": {"coordinates":[-2.07365,51.897011],"type":"Point"}
}