{
  "type": "Feature",
  "properties": {
    "iso:country":"GB",
    "sg:address":"Northampton House, Poplar Road",
    "sg:city":"Solihull",
    "sg:classifiers":[
        {
            "category":"Professional",
            "subcategory":"Lawyer & Legal Services",
            "type":"Services"
        }
    ],
    "sg:phone":"+44 121 705 6868",
    "sg:postcode":"B91 3AP",
    "sg:province":"West Midlands",
    "sg:tags":[
        "solicitor"
    ],
    "wof:name":"CUNNINGTON SOLICITORS",
    "wof:placetype":"venue"
},
  "geometry": {"coordinates":[-1.779204011,52.4140815735],"type":"Point"}
}