{
  "type": "Feature",
  "properties": {
    "addr:full":"Unit 4b Bridge Mills, Rochdale Road, Edenfield Bury Lancashire BL0 0RE",
    "addr:housenumber":"unit 4b",
    "addr:postcode":"bl0 0re",
    "addr:street":"Bridge Mills Rochdale Road",
    "iso:country":"GB",
    "sg:address":"Unit 4b Bridge Mills, Rochdale Road, Edenfield",
    "sg:city":"Bury",
    "sg:classifiers":[
        {
            "category":"Sports & Exercise",
            "subcategory":"Tennis Court",
            "type":"Entertainment"
        }
    ],
    "sg:phone":"+44 1706 828166",
    "sg:postcode":"BL0 0RE",
    "sg:province":"Lancashire",
    "sg:tags":[
        "breakdown",
        "recovery"
    ],
    "wof:name":"Bridge Mills Recovery",
    "wof:placetype":"venue"
},
  "geometry": {"coordinates":[-2.3068540096,53.6656150818],"type":"Point"}
}