{
  "type": "Feature",
  "properties": {
    "iso:country":"GB",
    "sg:address":"Hook Rd",
    "sg:city":"Chessington",
    "sg:classifiers":[
        {
            "category":"Place Of Worship",
            "type":"Public Place"
        }
    ],
    "sg:phone":"+44 20 8391 2362",
    "sg:postcode":"KT9 1PF",
    "sg:province":"Surrey",
    "wof:name":"St Pauls Parish Office",
    "wof:placetype":"venue"
},
  "geometry": {"coordinates":[-0.3056499958,51.3710861206],"type":"Point"}
}