{
  "type": "Feature",
  "properties": {
    "iso:country":"GB",
    "sg:address":"Unit 1-2, Cowburn Street",
    "sg:city":"Heywood",
    "sg:classifiers":[
        {
            "category":"Retail",
            "subcategory":"Auto Repair",
            "type":"Services"
        }
    ],
    "sg:phone":"+44 1706 622459",
    "sg:postcode":"OL10 2AJ",
    "sg:province":"Lancashire",
    "sg:tags":[
        "modification",
        "garage"
    ],
    "wof:name":"L C Motors Engineers",
    "wof:placetype":"venue"
},
  "geometry": {"coordinates":[-2.211493969,53.5892753601],"type":"Point"}
}