{
  "type": "Feature",
  "properties": {
    "iso:country":"GB",
    "sg:address":"18a Main Road",
    "sg:city":"Windermere",
    "sg:classifiers":[
        {
            "category":"Professional",
            "subcategory":"Management & Consulting",
            "type":"Services"
        },
        {
            "category":"Professional",
            "subcategory":"Business Services",
            "type":"Services"
        }
    ],
    "sg:phone":"+44 15394 44001",
    "sg:postcode":"LA23 1DY",
    "sg:province":"Cumbria",
    "sg:tags":[
        "house",
        "public",
        "pub"
    ],
    "wof:name":"Drystone Inns Ltd",
    "wof:placetype":"venue"
},
  "geometry": {"coordinates":[-2.906506,54.37904],"type":"Point"}
}