{
  "type": "Feature",
  "properties": {
    "addr:full":"Lindleys Lane, Kirkby In Ashfield Nottingham Nottinghamshire NG17 8AA",
    "addr:postcode":"ng17 8aa",
    "addr:street":"Lindleys Lane;In Ashfield",
    "iso:country":"GB",
    "sg:address":"Lindleys Lane, Kirkby In Ashfield",
    "sg:city":"Nottingham",
    "sg:classifiers":[
        {
            "category":"Organizations",
            "subcategory":"Membership Organization",
            "type":"Services"
        }
    ],
    "sg:phone":"+44 1623 458920",
    "sg:postcode":"NG17 8AA",
    "sg:province":"Nottinghamshire",
    "sg:tags":[
        "club"
    ],
    "wof:name":"The Urban Social Club",
    "wof:placetype":"venue"
},
  "geometry": {"coordinates":[-1.2489329576,53.0983352661],"type":"Point"}
}