{
  "type": "Feature",
  "properties": {
    "addr:full":"The Loaning, Denholm Hawick Cumbria TD9 8NN",
    "addr:postcode":"td9 8nn",
    "addr:street":"The Loaning",
    "iso:country":"GB",
    "sg:address":"The Loaning, Denholm",
    "sg:city":"Hawick",
    "sg:classifiers":[
        {
            "category":"Retail",
            "subcategory":"Auto Repair",
            "type":"Services"
        }
    ],
    "sg:phone":"+44 1450 870231",
    "sg:postcode":"TD9 8NN",
    "sg:province":"Cumbria",
    "sg:tags":[
        "body",
        "car"
    ],
    "wof:name":"Border Coachcraft",
    "wof:placetype":"venue"
},
  "geometry": {"coordinates":[-2.6823561192,55.458152771],"type":"Point"}
}