{
  "type": "Feature",
  "properties": {
    "addr:full":"4 Pont Park, Berwick Hill, Ponteland Newcastle-upon-tyne Northumberland NE20 0JX",
    "addr:housenumber":"4",
    "addr:postcode":"ne20 0jx",
    "addr:street":"Pont Park;Northumberland",
    "iso:country":"GB",
    "sg:address":"4 Pont Park, Berwick Hill, Ponteland",
    "sg:city":"Newcastle-upon-tyne",
    "sg:classifiers":[
        {
            "category":"Professional",
            "subcategory":"Business Services",
            "type":"Services"
        },
        {
            "category":"Manufacturing",
            "subcategory":"Lumber",
            "type":"Manufacturing & Wholesale Goods"
        }
    ],
    "sg:phone":"+44 1661 820011",
    "sg:postcode":"NE20 0JX",
    "sg:province":"Northumberland",
    "sg:tags":[
        "merchant",
        "import",
        "export",
        "agent",
        "timber"
    ],
    "wof:name":"HOME & LEISURE INTERNATIONAL LTD",
    "wof:placetype":"venue"
},
  "geometry": {"coordinates":[-1.7281520367,55.0742835999],"type":"Point"}
}