{
  "type": "Feature",
  "properties": {
    "addr:full":"638 Fulham Road Fulham Greater London SW6 5RT",
    "addr:housenumber":"638",
    "addr:postcode":"sw6 5rt",
    "addr:street":"Fulham Road",
    "iso:country":"GB",
    "sg:address":"638 Fulham Road",
    "sg:city":"Fulham",
    "sg:classifiers":[
        {
            "category":"Fast Food",
            "type":"Food & Drink"
        }
    ],
    "sg:phone":"+44 20 7731 6802",
    "sg:postcode":"SW6 5RT",
    "sg:province":"Greater London",
    "sg:tags":[
        "away",
        "take"
    ],
    "wof:name":"Alan Williams",
    "wof:placetype":"venue"
},
  "geometry": {"coordinates":[-0.2047660053,51.4762496948],"type":"Point"}
}