{
  "type": "Feature",
  "properties": {
    "iso:country":"GB",
    "sg:address":"2 Franklin Close",
    "sg:city":"Wadebridge",
    "sg:classifiers":[
        {
            "category":"Professional",
            "subcategory":"Detective & Security Services",
            "type":"Services"
        }
    ],
    "sg:phone":"+44 1208 812770",
    "sg:postcode":"PL27 6BH",
    "sg:province":"Cornwall",
    "sg:tags":[
        "locksmith"
    ],
    "wof:name":"Bridge Locks",
    "wof:placetype":"venue"
},
  "geometry": {"coordinates":[-4.828110218,50.5195007324],"type":"Point"}
}