{
  "type": "Feature",
  "properties": {
    "iso:country":"GB",
    "sg:address":"125 Chelmer Road",
    "sg:city":"Witham",
    "sg:classifiers":[
        {
            "category":"Home & Garden",
            "subcategory":"Carpets & Floor Coverings",
            "type":"Retail Goods"
        }
    ],
    "sg:phone":"+44 1376 513007",
    "sg:postcode":"CM8 2ET",
    "sg:province":"Essex",
    "sg:tags":[
        "carpets",
        "rug",
        "matting"
    ],
    "wof:name":"Alan Jones",
    "wof:placetype":"venue"
},
  "geometry": {"coordinates":[0.629883,51.803799],"type":"Point"}
}