{
  "type": "Feature",
  "properties": {
    "addr:full":"T Saveker House, 101 Aldridge Road, Perrybarr Birmingham West Midlands B42 2TS",
    "addr:housenumber":"101",
    "addr:postcode":"b42 2ts",
    "addr:street":"T;Aldridge Road",
    "iso:country":"GB",
    "sg:address":"T Saveker House, 101 Aldridge Road, Perrybarr",
    "sg:city":"Birmingham",
    "sg:classifiers":[
        {
            "category":"Manufacturing",
            "subcategory":"Metals",
            "type":"Manufacturing & Wholesale Goods"
        },
        {
            "category":"Wholesale",
            "subcategory":"Furniture",
            "type":"Manufacturing & Wholesale Goods"
        }
    ],
    "sg:phone":"+44 121 331 1903",
    "sg:postcode":"B42 2TS",
    "sg:province":"West Midlands",
    "sg:tags":[
        "shop",
        "fitting",
        "pressworkers"
    ],
    "sg:website":"http://www.tsaveker.co.uk",
    "wof:name":"T Saveker Ltd",
    "wof:placetype":"venue"
},
  "geometry": {"coordinates":[-1.896469,52.520882],"type":"Point"}
}