{
  "type": "Feature",
  "properties": {
    "addr:full":"6 Lindsay Avenue Nottingham Nottinghamshire NG17 9DJ",
    "addr:housenumber":"6",
    "addr:postcode":"ng17 9dj",
    "addr:street":"Lindsay Avenue",
    "iso:country":"GB",
    "sg:address":"6 Lindsay Avenue",
    "sg:city":"Nottingham",
    "sg:classifiers":[
        {
            "category":"Retail",
            "subcategory":"Driving School",
            "type":"Services"
        }
    ],
    "sg:postcode":"NG17 9DJ",
    "sg:province":"Nottinghamshire",
    "wof:name":"Ann Scott",
    "wof:placetype":"venue"
},
  "geometry": {"coordinates":[-1.24337,53.083862],"type":"Point"}
}