{
  "type": "Feature",
  "properties": {
    "addr:full":"Unit 1 Church Farm, West Tytherley Salisbury Dorset SP5 1LP",
    "addr:housenumber":"unit 1;tytherley",
    "addr:postcode":"sp5 1lp",
    "addr:street":"Church Farm West",
    "iso:country":"GB",
    "sg:address":"Unit 1 Church Farm, West Tytherley",
    "sg:city":"Salisbury",
    "sg:classifiers":[
        {
            "category":"Building & Trades",
            "subcategory":"Equipment Rental",
            "type":"Services"
        }
    ],
    "sg:phone":"+44 1794 340562",
    "sg:postcode":"SP5 1LP",
    "sg:province":"Dorset",
    "sg:tags":[
        "plant",
        "machinery"
    ],
    "wof:name":"A G B Plant",
    "wof:placetype":"venue"
},
  "geometry": {"coordinates":[-1.682433,51.064548],"type":"Point"}
}