{
  "type": "Feature",
  "properties": {
    "addr:full":"7d Mayflower Way, Harleston Industrial Estate Harleston Norfolk IP20 9EB",
    "addr:housenumber":"7d",
    "addr:postcode":"ip20 9eb",
    "addr:street":"Mayflower Way;Industrial Estate",
    "iso:country":"GB",
    "sg:address":"7d Mayflower Way, Harleston Industrial Estate",
    "sg:city":"Harleston",
    "sg:classifiers":[
        {
            "category":"Building & Trades",
            "subcategory":"Construction",
            "type":"Services"
        }
    ],
    "sg:phone":"+44 1379 853084",
    "sg:postcode":"IP20 9EB",
    "sg:province":"Norfolk",
    "sg:tags":[
        "joinery"
    ],
    "wof:name":"John Archer & Richard Chapman",
    "wof:placetype":"venue"
},
  "geometry": {"coordinates":[1.305641,52.396259],"type":"Point"}
}