{
  "type": "Feature",
  "properties": {
    "addr:full":"33 East Midlands Airport, Castle Donington Derby Leicestershire DE74 2SL",
    "addr:housenumber":"33",
    "addr:postcode":"de74 2sl",
    "iso:country":"GB",
    "sg:address":"33 East Midlands Airport, Castle Donington",
    "sg:city":"Derby",
    "sg:classifiers":[
        {
            "category":"Professional",
            "subcategory":"Employment Agencies",
            "type":"Services"
        }
    ],
    "sg:phone":"+44 1332 812190",
    "sg:postcode":"DE74 2SL",
    "sg:province":"Leicestershire",
    "sg:tags":[
        "consultant"
    ],
    "wof:name":"Acetech Personnel Ltd.",
    "wof:placetype":"venue"
},
  "geometry": {"coordinates":[-1.3373839855,52.8448791504],"type":"Point"}
}