{
  "type": "Feature",
  "properties": {
    "addr:full":"Town End Bodmin Cornwall PL31 1LN",
    "addr:postcode":"pl31 1ln",
    "iso:country":"GB",
    "sg:address":"Town End",
    "sg:city":"Bodmin",
    "sg:classifiers":[
        {
            "category":"Shopping",
            "subcategory":"News",
            "type":"Retail Goods"
        }
    ],
    "sg:postcode":"PL31 1LN",
    "sg:province":"Cornwall",
    "sg:tags":[
        "newsagent"
    ],
    "wof:name":"Masters Newsagents",
    "wof:placetype":"venue"
},
  "geometry": {"coordinates":[-4.716369,50.471046],"type":"Point"}
}