{
  "type": "Feature",
  "properties": {
    "iso:country":"GB",
    "sg:address":"32 Cherry Garden Lane",
    "sg:city":"Folkestone",
    "sg:classifiers":[
        {
            "category":"Building & Trades",
            "subcategory":"Construction",
            "type":"Services"
        }
    ],
    "sg:phone":"+44 1303 277660",
    "sg:postcode":"CT19 4AD",
    "sg:province":"Kent",
    "sg:tags":[
        "heating",
        "contractor"
    ],
    "wof:name":"A Bartlett Plumbing & Heating",
    "wof:placetype":"venue"
},
  "geometry": {"coordinates":[1.1527570486,51.0905380249],"type":"Point"}
}