{
  "type": "Feature",
  "properties": {
    "addr:full":"100 Cold Harbour Lane Bushey Hertfordshire WD23 4NX",
    "addr:housenumber":"100",
    "addr:postcode":"wd23 4nx",
    "addr:street":"Cold Harbour Lane",
    "iso:country":"GB",
    "sg:address":"100 Cold Harbour Lane",
    "sg:city":"Bushey",
    "sg:classifiers":[
        {
            "category":"Building & Trades",
            "subcategory":"Construction",
            "type":"Services"
        }
    ],
    "sg:postcode":"WD23 4NX",
    "sg:province":"Hertfordshire",
    "sg:tags":[
        "builder"
    ],
    "wof:name":"G & S Edmands (Construction) Ltd.",
    "wof:placetype":"venue"
},
  "geometry": {"coordinates":[-0.353099,51.646622],"type":"Point"}
}