{
  "type": "Feature",
  "properties": {
    "addr:full":"Cellan Road, Cwmann Lampeter Carmarthenshire SA48 8HT",
    "addr:postcode":"sa48 8ht",
    "addr:street":"Cellan Road",
    "iso:country":"GB",
    "sg:address":"Cellan Road, Cwmann",
    "sg:city":"Lampeter",
    "sg:classifiers":[
        {
            "category":"Farming",
            "subcategory":"Livestock Farm",
            "type":"Manufacturing & Wholesale Goods"
        }
    ],
    "sg:phone":"+44 1570 422255",
    "sg:postcode":"SA48 8HT",
    "sg:province":"Carmarthenshire",
    "sg:tags":[
        "others"
    ],
    "wof:name":"S M & J A Jones",
    "wof:placetype":"venue"
},
  "geometry": {"coordinates":[-4.0388679504,52.1207542419],"type":"Point"}
}