{
  "type": "Feature",
  "properties": {
    "iso:country":"GB",
    "sg:address":"Unit 3a Marsh Road Industrial Estate",
    "sg:city":"Minehead",
    "sg:classifiers":[
        {
            "category":"Shopping",
            "subcategory":"Computers & Home Electronics",
            "type":"Retail Goods"
        }
    ],
    "sg:phone":"+44 1643 707505",
    "sg:postcode":"TA24 5BJ",
    "sg:province":"Somerset",
    "sg:tags":[
        "electrical"
    ],
    "wof:name":"Hickin Electrical Wholesale",
    "wof:placetype":"venue"
},
  "geometry": {"coordinates":[-3.479969,51.205406],"type":"Point"}
}