{
  "type": "Feature",
  "properties": {
    "iso:country":"GB",
    "sg:address":"Holme Park, Heathlands Road",
    "sg:city":"Wokingham",
    "sg:classifiers":[
        {
            "category":"Farming",
            "subcategory":"Poultry Farm",
            "type":"Manufacturing & Wholesale Goods"
        }
    ],
    "sg:phone":"+44 118 978 2911",
    "sg:postcode":"RG40 3AJ",
    "sg:province":"Berkshire",
    "sg:tags":[
        "breeder",
        "game"
    ],
    "wof:name":"Holme Park Game Hatcheries",
    "wof:placetype":"venue"
},
  "geometry": {"coordinates":[-0.8160939813,51.3969230652],"type":"Point"}
}