{
  "type": "Feature",
  "properties": {
    "addr:full":"44-48 Broad Street King's Lynn Norfolk PE30 1DP",
    "addr:housenumber":"44-48",
    "addr:postcode":"pe30 1dp",
    "addr:street":"Broad Street",
    "iso:country":"GB",
    "sg:address":"44-48 Broad Street",
    "sg:city":"King's Lynn",
    "sg:classifiers":[
        {
            "category":"Shopping",
            "subcategory":"Gifts & Souvenirs",
            "type":"Retail Goods"
        }
    ],
    "sg:phone":"+44 1553 692140",
    "sg:postcode":"PE30 1DP",
    "sg:province":"Norfolk",
    "sg:tags":[
        "poster",
        "card"
    ],
    "wof:name":"Cardfair Ltd.",
    "wof:placetype":"venue"
},
  "geometry": {"coordinates":[0.3975760043,52.7546920776],"type":"Point"}
}