{
  "type": "Feature",
  "properties": {
    "iso:country":"GB",
    "sg:address":"21 Chester Street",
    "sg:city":"Mold",
    "sg:classifiers":[
        {
            "category":"Banks & Credit Unions",
            "subcategory":"Financial Services",
            "type":"Services"
        }
    ],
    "sg:phone":"+44 1352 753353",
    "sg:postcode":"CH7 1EG",
    "sg:province":"Denbighshire",
    "sg:tags":[
        "adviser"
    ],
    "wof:name":"Investment & Estate Planning Services",
    "wof:placetype":"venue"
},
  "geometry": {"coordinates":[-3.138173,53.168125],"type":"Point"}
}