{
  "type": "Feature",
  "properties": {
    "iso:country":"GB",
    "sg:address":"High St, Chellbey",
    "sg:city":"Slough",
    "sg:classifiers":[
        {
            "category":"Professional",
            "subcategory":"Engineering",
            "type":"Services"
        }
    ],
    "sg:phone":"+44 1753 695993",
    "sg:postcode":"SL1 2RX",
    "sg:province":"Berkshire",
    "sg:tags":[
        "contractor",
        "electrical",
        "engineer"
    ],
    "wof:name":"Southern Electrical Contracting Ltd",
    "wof:placetype":"venue"
},
  "geometry": {"coordinates":[-0.607024,51.506481],"type":"Point"}
}