{
  "type": "Feature",
  "properties": {
    "addr:full":"6 Windsor Grove, Stoneclough, Radcliffe Manchester Greater Manchester M26 1HD",
    "addr:housenumber":"6",
    "addr:postcode":"m26 1hd",
    "addr:street":"Windsor Grove Stoneclough",
    "iso:country":"GB",
    "sg:address":"6 Windsor Grove, Stoneclough, Radcliffe",
    "sg:city":"Manchester",
    "sg:classifiers":[
        {
            "category":"Professional",
            "subcategory":"Engineering",
            "type":"Services"
        }
    ],
    "sg:phone":"+44 1204 431495",
    "sg:postcode":"M26 1HD",
    "sg:province":"Greater Manchester",
    "sg:tags":[
        "contractor",
        "electrical",
        "engineer"
    ],
    "wof:name":"Mike Thomas",
    "wof:placetype":"venue"
},
  "geometry": {"coordinates":[-2.3696670532,53.5451698303],"type":"Point"}
}