{
  "type": "Feature",
  "properties": {
    "addr:full":"P O Box 2465 London Greater London NW7 3QJ",
    "addr:housenumber":"p o;2465",
    "addr:postcode":"nw7 3qj",
    "iso:country":"GB",
    "sg:address":"P O Box 2465",
    "sg:city":"London",
    "sg:classifiers":[
        {
            "category":"Food & Beverages",
            "subcategory":"Specialty",
            "type":"Retail Goods"
        }
    ],
    "sg:postcode":"NW7 3QJ",
    "sg:province":"Greater London",
    "sg:tags":[
        "product",
        "health"
    ],
    "wof:name":"Top Quality Natural Food & Nuts",
    "wof:placetype":"venue"
},
  "geometry": {"coordinates":[-0.255358994,51.6208305359],"type":"Point"}
}