{
  "type": "Feature",
  "properties": {
    "addr:full":"Tanhouse Farm, Eaton Congleton Cheshire CW12 2ND",
    "addr:postcode":"cw12 2nd",
    "addr:street":"Eaton Congleton",
    "iso:country":"GB",
    "sg:address":"Tanhouse Farm, Eaton",
    "sg:city":"Congleton",
    "sg:classifiers":[
        {
            "category":"Sports & Exercise",
            "subcategory":"Stables",
            "type":"Entertainment"
        }
    ],
    "sg:phone":"+44 1260 299454",
    "sg:postcode":"CW12 2ND",
    "sg:province":"Cheshire",
    "sg:tags":[
        "equestrian",
        "centre",
        "livery",
        "schools",
        "riding",
        "education"
    ],
    "wof:name":"Dane Valley Equestrian Centre",
    "wof:placetype":"venue"
},
  "geometry": {"coordinates":[-2.1965680122,53.1873931885],"type":"Point"}
}