{
  "type": "Feature",
  "properties": {
    "addr:full":"Morrison Rd Hayes Greater London UB4 9JP",
    "addr:postcode":"ub4 9jp",
    "addr:street":"Morrison Rd",
    "iso:country":"GB",
    "sg:address":"Morrison Rd",
    "sg:city":"Hayes",
    "sg:classifiers":[
        {
            "category":"Place Of Worship",
            "type":"Public Place"
        }
    ],
    "sg:phone":"+44 20 8845 1919",
    "sg:postcode":"UB4 9JP",
    "sg:province":"Greater London",
    "wof:name":"St Raphael R C Church",
    "wof:placetype":"venue"
},
  "geometry": {"coordinates":[-0.407032,51.532753],"type":"Point"}
}