{
  "type": "Feature",
  "properties": {
    "addr:full":"Dry Howe, Selside Kendal Cumbria LA8 9JZ",
    "addr:postcode":"la8 9jz",
    "addr:street":"Selside Kendal",
    "iso:country":"GB",
    "sg:address":"Dry Howe, Selside",
    "sg:city":"Kendal",
    "sg:classifiers":[
        {
            "category":"Farming",
            "subcategory":"Livestock Farm",
            "type":"Manufacturing & Wholesale Goods"
        },
        {
            "category":"Farming",
            "subcategory":"Farm",
            "type":"Manufacturing & Wholesale Goods"
        }
    ],
    "sg:phone":"+44 1539 823269",
    "sg:postcode":"LA8 9JZ",
    "sg:province":"Cumbria",
    "sg:tags":[
        "mixed",
        "crop",
        "others"
    ],
    "wof:name":"J I & J Swift",
    "wof:placetype":"venue"
},
  "geometry": {"coordinates":[-2.7167870998,54.3852310181],"type":"Point"}
}