{
  "type": "Feature",
  "properties": {
    "addr:full":"4 Blea Clo Burnley Lancashire BB12 7TP",
    "addr:housenumber":"4",
    "addr:postcode":"bb12 7tp",
    "addr:street":"Blea Clo",
    "iso:country":"GB",
    "sg:address":"4 Blea Clo",
    "sg:city":"Burnley",
    "sg:classifiers":[
        {
            "category":"Professional",
            "subcategory":"Management & Consulting",
            "type":"Services"
        }
    ],
    "sg:phone":"+44 1282 456100",
    "sg:postcode":"BB12 7TP",
    "sg:province":"Lancashire",
    "sg:tags":[
        "consultant",
        "business"
    ],
    "wof:name":"David Wilkinson",
    "wof:placetype":"venue"
},
  "geometry": {"coordinates":[-2.2747991085,53.8005714417],"type":"Point"}
}