{
  "type": "Feature",
  "properties": {
    "addr:full":"40 Esplanade Whitley Bay Northumberland NE26 2AE",
    "addr:housenumber":"40",
    "addr:postcode":"ne26 2ae",
    "addr:street":"Esplanade",
    "iso:country":"GB",
    "sg:address":"40 Esplanade",
    "sg:city":"Whitley Bay",
    "sg:classifiers":[
        {
            "category":"Restaurant",
            "type":"Food & Drink"
        }
    ],
    "sg:phone":"+44 191 252 9483",
    "sg:postcode":"NE26 2AE",
    "sg:province":"Northumberland",
    "sg:tags":[
        "indian",
        "-"
    ],
    "wof:name":"Whitley Bay Tandoori",
    "wof:placetype":"venue"
},
  "geometry": {"coordinates":[-1.442054987,55.0421295166],"type":"Point"}
}