{
  "type": "Feature",
  "properties": {
    "iso:country":"GB",
    "sg:address":"90-92 Lothian Road",
    "sg:city":"Edinburgh",
    "sg:classifiers":[
        {
            "category":"Banks & Credit Unions",
            "subcategory":"Investment Brokerage",
            "type":"Services"
        }
    ],
    "sg:phone":"+44 131 228 3660",
    "sg:postcode":"EH3 9BE",
    "sg:province":"City of Edinburgh",
    "wof:name":"Save & Invest",
    "wof:placetype":"venue"
},
  "geometry": {"coordinates":[-3.206105,55.947281],"type":"Point"}
}