{
  "type": "Feature",
  "properties": {
    "addr:full":"Dorothy Terry House, Evesham Road Redditch Warwickshire B97 5EN",
    "addr:postcode":"b97 5en",
    "addr:street":"Evesham Road",
    "iso:country":"GB",
    "sg:address":"Dorothy Terry House, Evesham Road",
    "sg:city":"Redditch",
    "sg:classifiers":[
        {
            "category":"Health Services",
            "subcategory":"Nursing And Care Facility",
            "type":"Services"
        }
    ],
    "sg:phone":"+44 1527 541575",
    "sg:postcode":"B97 5EN",
    "sg:province":"Warwickshire",
    "sg:tags":[
        "home"
    ],
    "wof:name":"British Red Cross",
    "wof:placetype":"venue"
},
  "geometry": {"coordinates":[-1.9439840317,52.2853088379],"type":"Point"}
}