{
  "type": "Feature",
  "properties": {
    "addr:full":"Princes Road Wells Somerset BA5 1TE",
    "addr:postcode":"ba5 1te",
    "addr:street":"Princes Road",
    "iso:country":"GB",
    "sg:address":"Princes Road",
    "sg:city":"Wells",
    "sg:classifiers":[
        {
            "category":"Manufacturing",
            "subcategory":"Metals",
            "type":"Manufacturing & Wholesale Goods"
        },
        {
            "category":"Professional",
            "subcategory":"Printing & Photocopies",
            "type":"Services"
        }
    ],
    "sg:postcode":"BA5 1TE",
    "sg:province":"Somerset",
    "sg:tags":[
        "engraving",
        "heat",
        "-",
        "treatment"
    ],
    "wof:name":"Mr Snob",
    "wof:placetype":"venue"
},
  "geometry": {"coordinates":[-2.650869,51.206936],"type":"Point"}
}