{
  "type": "Feature",
  "properties": {
    "iso:country":"GB",
    "sg:address":"3 Dalgety Avenue",
    "sg:city":"Edinburgh",
    "sg:classifiers":[
        {
            "category":"Taxi",
            "type":"Transportation"
        }
    ],
    "sg:postcode":"EH7 5UF",
    "sg:province":"City of Edinburgh",
    "sg:tags":[
        "mini",
        "cab"
    ],
    "wof:name":"Marionville Private Hire",
    "wof:placetype":"venue"
},
  "geometry": {"coordinates":[-3.161856,55.957718],"type":"Point"}
}