{
  "type": "Feature",
  "properties": {
    "addr:full":"Grant Thornton Ho,, Kettering Venture Pk, Kettering Northamptonshire NN15 6XR",
    "addr:postcode":"nn15 6xr",
    "addr:street":"Venture Pk",
    "iso:country":"GB",
    "sg:address":"Grant Thornton Ho,, Kettering Venture Pk,",
    "sg:city":"Kettering",
    "sg:classifiers":[
        {
            "category":"Professional",
            "subcategory":"Engineering",
            "type":"Services"
        }
    ],
    "sg:postcode":"NN15 6XR",
    "sg:province":"Northamptonshire",
    "sg:tags":[
        "consulting",
        "engineer"
    ],
    "wof:name":"Connroll Ltd",
    "wof:placetype":"venue"
},
  "geometry": {"coordinates":[-0.7225040197,52.3782043457],"type":"Point"}
}