{
  "type": "Feature",
  "properties": {
    "iso:country":"GB",
    "sg:address":"48 Queens Road",
    "sg:city":"Reading",
    "sg:classifiers":[
        {
            "category":"Professional",
            "subcategory":"Lawyer & Legal Services",
            "type":"Services"
        }
    ],
    "sg:phone":"+44 118 956 8856",
    "sg:postcode":"RG1 4AU",
    "sg:province":"Berkshire",
    "sg:tags":[
        "barrister"
    ],
    "wof:name":"Wessex Chambers",
    "wof:placetype":"venue"
},
  "geometry": {"coordinates":[-0.9652500153,51.4531097412],"type":"Point"}
}