{
  "type": "Feature",
  "properties": {
    "iso:country":"GB",
    "sg:address":"77 Staplehill Road, Fishponds",
    "sg:city":"Bristol",
    "sg:classifiers":[
        {
            "category":"Recreation",
            "type":"Entertainment"
        }
    ],
    "sg:phone":"+44 1454 851134",
    "sg:postcode":"BS16 5AB",
    "sg:province":"City of Bristol",
    "sg:tags":[
        "outdoor",
        "pursuit"
    ],
    "wof:name":"Thornbury Paint Ball Fields",
    "wof:placetype":"venue"
},
  "geometry": {"coordinates":[-2.5235440731,51.4817733765],"type":"Point"}
}