{
  "type": "Feature",
  "properties": {
    "addr:full":"10-12 The Green Warlingham Kent CR6 9NA",
    "addr:housenumber":"10-12",
    "addr:postcode":"cr6 9na",
    "addr:street":"The Green",
    "iso:country":"GB",
    "sg:address":"10-12 The Green",
    "sg:city":"Warlingham",
    "sg:classifiers":[
        {
            "category":"Shopping",
            "subcategory":"News",
            "type":"Retail Goods"
        }
    ],
    "sg:phone":"+44 1883 624339",
    "sg:postcode":"CR6 9NA",
    "sg:province":"Kent",
    "sg:tags":[
        "newsagent"
    ],
    "wof:name":"Readychoice Ltd.",
    "wof:placetype":"venue"
},
  "geometry": {"coordinates":[-0.0565119982,51.3097305298],"type":"Point"}
}