{
  "type": "Feature",
  "properties": {
    "addr:full":"3 Madresfield Road Malvern Herefordshire WR14 2AP",
    "addr:housenumber":"3",
    "addr:postcode":"wr14 2ap",
    "addr:street":"Madresfield Road",
    "iso:country":"GB",
    "sg:address":"3 Madresfield Road",
    "sg:city":"Malvern",
    "sg:classifiers":[
        {
            "category":"Personal",
            "subcategory":"Beauty Salon",
            "type":"Services"
        }
    ],
    "sg:postcode":"WR14 2AP",
    "sg:province":"Herefordshire",
    "sg:tags":[
        "lady",
        "hairdresser"
    ],
    "wof:name":"Poppys Hairdressing",
    "wof:placetype":"venue"
},
  "geometry": {"coordinates":[-2.3186318874,52.112361908],"type":"Point"}
}