{
  "type": "Feature",
  "properties": {
    "addr:full":"42 Fleming Avenue, Sidford Sidmouth Devon EX10 9NZ",
    "addr:housenumber":"42",
    "addr:postcode":"ex10 9nz",
    "addr:street":"Fleming Avenue",
    "iso:country":"GB",
    "sg:address":"42 Fleming Avenue, Sidford",
    "sg:city":"Sidmouth",
    "sg:classifiers":[
        {
            "category":"Home & Garden",
            "subcategory":"Home Furnishings",
            "type":"Retail Goods"
        },
        {
            "category":"Home & Garden",
            "subcategory":"Carpets & Floor Coverings",
            "type":"Retail Goods"
        }
    ],
    "sg:phone":"+44 1395 513055",
    "sg:postcode":"EX10 9NZ",
    "sg:province":"Devon",
    "sg:tags":[
        "fitting",
        "rug",
        "matting",
        "carpets"
    ],
    "wof:name":"D S Clapp",
    "wof:placetype":"venue"
},
  "geometry": {"coordinates":[-3.229362011,50.701007843],"type":"Point"}
}