{
  "type": "Feature",
  "properties": {
    "iso:country":"GB",
    "sg:address":"14 Market Square",
    "sg:city":"Rushden",
    "sg:classifiers":[
        {
            "category":"Banks & Credit Unions",
            "subcategory":"Financial Services",
            "type":"Services"
        }
    ],
    "sg:phone":"+44 1933 358233",
    "sg:postcode":"NN10 8DJ",
    "sg:province":"Bedfordshire",
    "sg:tags":[
        "consultant"
    ],
    "wof:name":"Assured Future Financial Management",
    "wof:placetype":"venue"
},
  "geometry": {"coordinates":[-0.592844,52.306019],"type":"Point"}
}