{
  "type": "Feature",
  "properties": {
    "iso:country":"GB",
    "sg:address":"King Street",
    "sg:city":"Dumfries",
    "sg:classifiers":[
        {
            "category":"Community Center",
            "type":"Public Place"
        }
    ],
    "sg:phone":"+44 1387 251300",
    "sg:postcode":"DG2 9AN",
    "sg:province":"Dumfries and Galloway",
    "sg:tags":[
        "recreation",
        "leisure",
        "centre"
    ],
    "sg:website":"http://www.dumgul.gov.uk",
    "wof:name":"Dumfries Ice Bowl",
    "wof:placetype":"venue"
},
  "geometry": {"coordinates":[-3.620992,55.069504],"type":"Point"}
}