{
  "type": "Feature",
  "properties": {
    "addr:full":"Horsley House Gosforth Newcastle-upon-tyne Tyne and Wear NE3 3TZ",
    "addr:postcode":"ne3 3tz",
    "iso:country":"GB",
    "sg:address":"Horsley House Gosforth",
    "sg:city":"Newcastle-upon-tyne",
    "sg:classifiers":[
        {
            "category":"Professional",
            "subcategory":"Engineering",
            "type":"Services"
        }
    ],
    "sg:phone":"+44 191 213 4900",
    "sg:postcode":"NE3 3TZ",
    "sg:province":"Tyne and Wear",
    "sg:tags":[
        "civil",
        "consulting",
        "engineer"
    ],
    "wof:name":"Jacobs U K  Ltd.",
    "wof:placetype":"venue"
},
  "geometry": {"coordinates":[-1.606506,55.007973],"type":"Point"}
}