{
  "type": "Feature",
  "properties": {
    "addr:full":"19 Finkle Street Thirsk North Yorkshire YO7 1DA",
    "addr:housenumber":"19",
    "addr:postcode":"yo7 1da",
    "addr:street":"Finkle Street",
    "iso:country":"GB",
    "sg:address":"19 Finkle Street",
    "sg:city":"Thirsk",
    "sg:classifiers":[
        {
            "category":"Health Services",
            "subcategory":"Dentist",
            "type":"Services"
        }
    ],
    "sg:phone":"+44 1845 522602",
    "sg:postcode":"YO7 1DA",
    "sg:province":"North Yorkshire",
    "wof:name":"R H Firth & Associates",
    "wof:placetype":"venue"
},
  "geometry": {"coordinates":[-1.339124,54.233131],"type":"Point"}
}