{
  "type": "Feature",
  "properties": {
    "addr:full":"Gloucester Street Wotton-under-edge Gloucestershire GL12 7DN",
    "addr:postcode":"gl12 7dn",
    "addr:street":"Gloucester Street",
    "iso:country":"GB",
    "sg:address":"Gloucester Street",
    "sg:city":"Wotton-under-edge",
    "sg:classifiers":[
        {
            "category":"Retail",
            "subcategory":"Auto Repair",
            "type":"Services"
        }
    ],
    "sg:phone":"+44 1453 842240",
    "sg:postcode":"GL12 7DN",
    "sg:province":"Gloucestershire",
    "sg:tags":[
        "modification",
        "garage"
    ],
    "wof:name":"Wotton Motor Centre Ltd.",
    "wof:placetype":"venue"
},
  "geometry": {"coordinates":[-2.356507,51.639477],"type":"Point"}
}