{
  "type": "Feature",
  "properties": {
    "iso:country":"GB",
    "sg:address":"1c Mere Road",
    "sg:city":"Blackpool",
    "sg:classifiers":[
        {
            "category":"Fast Food",
            "type":"Food & Drink"
        }
    ],
    "sg:phone":"+44 1253 396011",
    "sg:postcode":"FY3 9AU",
    "sg:province":"Lancashire",
    "sg:tags":[
        "away",
        "take"
    ],
    "wof:name":"The Butty Mines",
    "wof:placetype":"venue"
},
  "geometry": {"coordinates":[-3.036291,53.816605],"type":"Point"}
}