{
  "type": "Feature",
  "properties": {
    "addr:full":"3 Marlborough Parade, Uxbridge Rd, Hillingdon Uxbridge Greater London UB10 0LR",
    "addr:housenumber":"3",
    "addr:postcode":"ub10 0lr",
    "addr:street":"Marlborough Parade Uxbridge Rd",
    "iso:country":"GB",
    "sg:address":"3 Marlborough Parade, Uxbridge Rd, Hillingdon",
    "sg:city":"Uxbridge",
    "sg:classifiers":[
        {
            "category":"Home & Garden",
            "subcategory":"Kitchen Supply",
            "type":"Retail Goods"
        }
    ],
    "sg:phone":"+44 1895 812813",
    "sg:postcode":"UB10 0LR",
    "sg:province":"Greater London",
    "sg:tags":[
        "equipment",
        "bakery"
    ],
    "wof:name":"Pattisserie De Paris",
    "wof:placetype":"venue"
},
  "geometry": {"coordinates":[-0.447399,51.530529],"type":"Point"}
}