{
  "type": "Feature",
  "properties": {
    "addr:full":"Risley Moss, Moss Gate, Birchwood Warrington Cheshire WA3 6QX",
    "addr:postcode":"wa3 6qx",
    "addr:street":"Moss Moss Gate",
    "iso:country":"GB",
    "sg:address":"Risley Moss, Moss Gate, Birchwood",
    "sg:city":"Warrington",
    "sg:classifiers":[
        {
            "category":"Professional",
            "subcategory":"Engineering",
            "type":"Services"
        }
    ],
    "sg:phone":"+44 1925 816217",
    "sg:postcode":"WA3 6QX",
    "sg:province":"Cheshire",
    "sg:tags":[
        "consulting",
        "engineer"
    ],
    "wof:name":"Cheshire County Council",
    "wof:placetype":"venue"
},
  "geometry": {"coordinates":[-2.5208990574,53.4224357605],"type":"Point"}
}