{
  "type": "Feature",
  "properties": {
    "addr:full":"18 Ranfurly Road Sutton Surrey SM1 3JB",
    "addr:housenumber":"18",
    "addr:postcode":"sm1 3jb",
    "addr:street":"Ranfurly Road",
    "iso:country":"GB",
    "sg:address":"18 Ranfurly Road",
    "sg:city":"Sutton",
    "sg:classifiers":[
        {
            "category":"Manufacturing",
            "subcategory":"Furniture",
            "type":"Manufacturing & Wholesale Goods"
        }
    ],
    "sg:postcode":"SM1 3JB",
    "sg:province":"Surrey",
    "sg:tags":[
        "polishing",
        "french"
    ],
    "wof:name":"Michael J Offord",
    "wof:placetype":"venue"
},
  "geometry": {"coordinates":[-0.1985729933,51.3774681091],"type":"Point"}
}