{
  "type": "Feature",
  "properties": {
    "addr:full":"Verulam House, Verulam Road St Albans Hertfordshire AL3 4DH",
    "addr:postcode":"al3 4dh",
    "addr:street":"Verulam Road",
    "iso:country":"GB",
    "sg:address":"Verulam House, Verulam Road",
    "sg:city":"St Albans",
    "sg:classifiers":[
        {
            "category":"Health Services",
            "subcategory":"Nursing And Care Facility",
            "type":"Services"
        }
    ],
    "sg:phone":"+44 1727 853991",
    "sg:postcode":"AL3 4DH",
    "sg:province":"Hertfordshire",
    "sg:tags":[
        "home"
    ],
    "wof:name":"Submorte Ltd.",
    "wof:placetype":"venue"
},
  "geometry": {"coordinates":[-0.3496739864,51.7565536499],"type":"Point"}
}