{
  "type": "Feature",
  "properties": {
    "iso:country":"GB",
    "sg:address":"1a Warren Road",
    "sg:city":"Guildford",
    "sg:classifiers":[
        {
            "category":"Utilities",
            "subcategory":"Telephone",
            "type":"Services"
        }
    ],
    "sg:phone":"+44 1483 456606",
    "sg:postcode":"GU1 3NS",
    "sg:province":"Surrey",
    "sg:tags":[
        "telecommunication"
    ],
    "wof:name":"Ash & Co",
    "wof:placetype":"venue"
},
  "geometry": {"coordinates":[-0.556292,51.236012],"type":"Point"}
}