{
  "type": "Feature",
  "properties": {
    "addr:full":"50 Dunkeld Street Aberfeldy Perth and Kinross PH15 2AF",
    "addr:housenumber":"50",
    "addr:postcode":"ph15 2af",
    "addr:street":"Dunkeld Street",
    "iso:country":"GB",
    "sg:address":"50 Dunkeld Street",
    "sg:city":"Aberfeldy",
    "sg:classifiers":[
        {
            "category":"Restaurant",
            "type":"Food & Drink"
        }
    ],
    "sg:phone":"+44 1887 829200",
    "sg:postcode":"PH15 2AF",
    "sg:province":"Perth and Kinross",
    "sg:tags":[
        "indian"
    ],
    "wof:name":"Chillies Restaurant",
    "wof:placetype":"venue"
},
  "geometry": {"coordinates":[-3.86239,56.620564],"type":"Point"}
}