{
  "type": "Feature",
  "properties": {
    "addr:full":"School Road Keith Moray AB55 5ES",
    "addr:postcode":"ab55 5es",
    "addr:street":"School Road",
    "iso:country":"GB",
    "sg:address":"School Road",
    "sg:city":"Keith",
    "sg:classifiers":[
        {
            "category":"Education",
            "subcategory":"School",
            "type":"Public Place"
        },
        {
            "category":"Government",
            "subcategory":"Office",
            "type":"Public Place"
        }
    ],
    "sg:phone":"+44 1542 882461",
    "sg:postcode":"AB55 5ES",
    "sg:province":"Moray",
    "sg:tags":[
        "local",
        "authority"
    ],
    "wof:name":"Keith Grammar School",
    "wof:placetype":"venue"
},
  "geometry": {"coordinates":[-2.9468090534,57.5446434021],"type":"Point"}
}