{
  "type": "Feature",
  "properties": {
    "iso:country":"GB",
    "sg:address":"205 Knightswood Road",
    "sg:city":"Glasgow",
    "sg:classifiers":[
        {
            "category":"Shopping",
            "subcategory":"Florist",
            "type":"Retail Goods"
        }
    ],
    "sg:phone":"+44 141 950 1302",
    "sg:postcode":"G13 2EX",
    "sg:province":"Glasgow City",
    "wof:name":"Elliots Fruit & Flowers",
    "wof:placetype":"venue"
},
  "geometry": {"coordinates":[-4.3417830467,55.8960723877],"type":"Point"}
}