{
  "type": "Feature",
  "properties": {
    "addr:full":"361a Hitchin Rd Luton Bedfordshire LU2 7SW",
    "addr:housenumber":"361a",
    "addr:postcode":"lu2 7sw",
    "addr:street":"Hitchin Rd",
    "iso:country":"GB",
    "sg:address":"361a Hitchin Rd",
    "sg:city":"Luton",
    "sg:classifiers":[
        {
            "category":"Autos & Motor Vehicles",
            "subcategory":"Fuel & Gas Station",
            "type":"Retail Goods"
        }
    ],
    "sg:postcode":"LU2 7SW",
    "sg:province":"Bedfordshire",
    "sg:tags":[
        "hr",
        "filling",
        "petrol"
    ],
    "wof:name":"King,Christopher,",
    "wof:placetype":"venue"
},
  "geometry": {"coordinates":[-0.40158,51.891968],"type":"Point"}
}