{
  "type": "Feature",
  "properties": {
    "iso:country":"GB",
    "sg:address":"108 Vicarage Wood",
    "sg:city":"Harlow",
    "sg:classifiers":[
        {
            "category":"Shopping",
            "subcategory":"Crafts & Fabrics",
            "type":"Retail Goods"
        }
    ],
    "sg:phone":"+44 1279 434782",
    "sg:postcode":"CM20 3HH",
    "sg:province":"Essex",
    "sg:tags":[
        "machine",
        "sewing",
        "knitting"
    ],
    "wof:name":"Alan Summers Sewing Machines",
    "wof:placetype":"venue"
},
  "geometry": {"coordinates":[0.1154450029,51.7725296021],"type":"Point"}
}