{
  "type": "Feature",
  "properties": {
    "addr:full":"Low Marishes Malton North Yorkshire YO17 6RJ",
    "addr:postcode":"yo17 6rj",
    "addr:street":"Marishes",
    "iso:country":"GB",
    "sg:address":"Low Marishes",
    "sg:city":"Malton",
    "sg:classifiers":[
        {
            "category":"Bars & Pubs",
            "type":"Food & Drink"
        }
    ],
    "sg:phone":"+44 1653 668247",
    "sg:postcode":"YO17 6RJ",
    "sg:province":"North Yorkshire",
    "sg:tags":[
        "pubs",
        "inn"
    ],
    "wof:name":"School House Inn",
    "wof:placetype":"venue"
},
  "geometry": {"coordinates":[-0.835818,54.159821],"type":"Point"}
}