{
  "type": "Feature",
  "properties": {
    "iso:country":"GB",
    "sg:address":"51 Falcon Road",
    "sg:city":"London",
    "sg:classifiers":[
        {
            "category":"Health Services",
            "subcategory":"Dentist",
            "type":"Services"
        }
    ],
    "sg:phone":"+44 20 7978 4432",
    "sg:postcode":"SW11 2PH",
    "sg:province":"Greater London",
    "wof:name":"Falcon Road Dental Practice",
    "wof:placetype":"venue"
},
  "geometry": {"coordinates":[-0.170642,51.46854],"type":"Point"}
}