{
  "type": "Feature",
  "properties": {
    "iso:country":"GB",
    "sg:address":"13 Deveronside Drive",
    "sg:city":"Turriff",
    "sg:classifiers":[
        {
            "category":"Professional",
            "subcategory":"Engineering",
            "type":"Services"
        }
    ],
    "sg:postcode":"AB53 4SP",
    "sg:province":"Aberdeenshire",
    "sg:tags":[
        "hydraulic",
        "engineer"
    ],
    "wof:name":"Eagle Engineering",
    "wof:placetype":"venue"
},
  "geometry": {"coordinates":[-2.473669,57.540043],"type":"Point"}
}