{
  "type": "Feature",
  "properties": {
    "addr:full":"High Holburn House London Greater London WC1R 4LR",
    "addr:postcode":"wc1r 4lr",
    "iso:country":"GB",
    "sg:address":"High Holburn House",
    "sg:city":"London",
    "sg:classifiers":[
        {
            "category":"Shopping",
            "subcategory":"Books",
            "type":"Retail Goods"
        }
    ],
    "sg:phone":"+44 20 7497 1422",
    "sg:postcode":"WC1R 4LR",
    "sg:province":"Greater London",
    "wof:name":"International Thomson Publishing",
    "wof:placetype":"venue"
},
  "geometry": {"coordinates":[-0.087914,51.50737],"type":"Point"}
}