{
  "type": "Feature",
  "properties": {
    "addr:full":"Railway Arch, 883 Rosendale Rd Herne Hill Greater London SE24 9EH",
    "addr:housenumber":"883",
    "addr:postcode":"se24 9eh",
    "addr:street":"Railway Arch;Rosendale Rd",
    "iso:country":"GB",
    "sg:address":"Railway Arch, 883 Rosendale Rd",
    "sg:city":"Herne Hill",
    "sg:classifiers":[
        {
            "category":"Home & Garden",
            "subcategory":"Hardware",
            "type":"Retail Goods"
        }
    ],
    "sg:phone":"+44 20 8678 9679",
    "sg:postcode":"SE24 9EH",
    "sg:province":"Greater London",
    "sg:tags":[
        "part",
        "accessory"
    ],
    "wof:name":"Craft",
    "wof:placetype":"venue"
},
  "geometry": {"coordinates":[-0.099584,51.455086],"type":"Point"}
}