{
  "type": "Feature",
  "properties": {
    "addr:full":"17 Lichfield Road Stafford Staffordshire ST17 4LJ",
    "addr:housenumber":"17",
    "addr:postcode":"st17 4lj",
    "addr:street":"Lichfield Road",
    "iso:country":"GB",
    "sg:address":"17 Lichfield Road",
    "sg:city":"Stafford",
    "sg:classifiers":[
        {
            "category":"Education",
            "subcategory":"Special Training",
            "type":"Public Place"
        }
    ],
    "sg:phone":"+44 1785 250585",
    "sg:postcode":"ST17 4LJ",
    "sg:province":"Staffordshire",
    "sg:tags":[
        "product",
        "centre"
    ],
    "wof:name":"S C Training",
    "wof:placetype":"venue"
},
  "geometry": {"coordinates":[-2.1104888916,52.801990509],"type":"Point"}
}