{
  "type": "Feature",
  "properties": {
    "addr:full":"46 Scot Lane, Aspull Wigan Lancashire WN2 1YX",
    "addr:housenumber":"46",
    "addr:postcode":"wn2 1yx",
    "addr:street":"Scot Lane",
    "iso:country":"GB",
    "sg:address":"46 Scot Lane, Aspull",
    "sg:city":"Wigan",
    "sg:classifiers":[
        {
            "category":"Shopping",
            "subcategory":"Florist",
            "type":"Retail Goods"
        }
    ],
    "sg:postcode":"WN2 1YX",
    "sg:province":"Lancashire",
    "wof:name":"Elizabeths",
    "wof:placetype":"venue"
},
  "geometry": {"coordinates":[-2.58425,53.569717],"type":"Point"}
}