{
  "type": "Feature",
  "properties": {
    "addr:full":"Rumbolds Hill Midhurst West Sussex GU29 9DB",
    "addr:postcode":"gu29 9db",
    "addr:street":"Rumbolds Hill",
    "iso:country":"GB",
    "sg:address":"Rumbolds Hill",
    "sg:city":"Midhurst",
    "sg:classifiers":[
        {
            "category":"Banks & Credit Unions",
            "subcategory":"Bank",
            "type":"Services"
        }
    ],
    "sg:phone":"+44 1730 812241",
    "sg:postcode":"GU29 9DB",
    "sg:province":"West Sussex",
    "wof:name":"NatWest",
    "wof:placetype":"venue"
},
  "geometry": {"coordinates":[-0.739039,50.986519],"type":"Point"}
}