{
  "type": "Feature",
  "properties": {
    "iso:country":"GB",
    "sg:address":"Salford Rd",
    "sg:city":"Lancaster",
    "sg:classifiers":[
        {
            "category":"Food & Beverages",
            "subcategory":"Fruits & Vegetables",
            "type":"Retail Goods"
        }
    ],
    "sg:phone":"+44 1524 752655",
    "sg:postcode":"LA2 0LL",
    "sg:province":"Lancashire",
    "sg:tags":[
        "greengrocer"
    ],
    "wof:name":"Elle Fruit & Veg",
    "wof:placetype":"venue"
},
  "geometry": {"coordinates":[-2.791643,53.992683],"type":"Point"}
}