{
  "type": "Feature",
  "properties": {
    "iso:country":"GB",
    "sg:address":"29 Ashcroft Road, Porthill",
    "sg:city":"Newcastle",
    "sg:classifiers":[
        {
            "category":"Building & Trades",
            "subcategory":"Construction",
            "type":"Services"
        }
    ],
    "sg:phone":"+44 1782 561650",
    "sg:postcode":"ST5 8EP",
    "sg:province":"Staffordshire",
    "sg:tags":[
        "decorator",
        "painter"
    ],
    "wof:name":"Dennis Scarlett",
    "wof:placetype":"venue"
},
  "geometry": {"coordinates":[-2.232378,53.036274],"type":"Point"}
}