{
  "type": "Feature",
  "properties": {
    "iso:country":"GB",
    "sg:address":"Norwich Road",
    "sg:city":"Wymondham",
    "sg:classifiers":[
        {
            "category":"Arena",
            "subcategory":"Sports Club",
            "type":"Entertainment"
        }
    ],
    "sg:phone":"+44 1953 602099",
    "sg:postcode":"NR18 0NT",
    "sg:province":"Norfolk",
    "wof:name":"Wymondham Dell Bowls Club",
    "wof:placetype":"venue"
},
  "geometry": {"coordinates":[1.135404,52.579895],"type":"Point"}
}