{
  "type": "Feature",
  "properties": {
    "addr:full":"Muster Green Haywards Heath East Sussex RH16 4AG",
    "addr:postcode":"rh16 4ag",
    "addr:street":"Muster Green",
    "iso:country":"GB",
    "sg:address":"Muster Green",
    "sg:city":"Haywards Heath",
    "sg:classifiers":[
        {
            "category":"Health Services",
            "subcategory":"Podiatrist",
            "type":"Services"
        }
    ],
    "sg:phone":"+44 1444 412863",
    "sg:postcode":"RH16 4AG",
    "sg:province":"East Sussex",
    "sg:tags":[
        "podiatrists",
        "chiropodist"
    ],
    "wof:name":"J Hughes",
    "wof:placetype":"venue"
},
  "geometry": {"coordinates":[-0.1080339998,51.0001182556],"type":"Point"}
}