{
  "type": "Feature",
  "properties": {
    "addr:full":"111 Lichfield Street, Hanley Stoke-on-trent Staffordshire ST1 3EA",
    "addr:housenumber":"111",
    "addr:postcode":"staffordshire st1 3ea",
    "addr:street":"Lichfield Street",
    "iso:country":"GB",
    "sg:address":"111 Lichfield Street, Hanley",
    "sg:city":"Stoke-on-trent",
    "sg:classifiers":[
        {
            "category":"Autos & Motor Vehicles",
            "subcategory":"Auto Supplies",
            "type":"Retail Goods"
        }
    ],
    "sg:phone":"+44 1782 214431",
    "sg:postcode":"ST1 3EA",
    "sg:province":"Staffordshire",
    "sg:tags":[
        "component"
    ],
    "wof:name":"L & H Brakes & Hoses (Hanley) Ltd.",
    "wof:placetype":"venue"
},
  "geometry": {"coordinates":[-2.1725199223,53.0216140747],"type":"Point"}
}