{
  "type": "Feature",
  "properties": {
    "addr:full":"Marketing Suite, California Dr, Wakefield Europort Castleford West Yorkshire WF10 5QW",
    "addr:postcode":"wf10 5qw",
    "addr:street":"California Dr;Europort Castleford West",
    "iso:country":"GB",
    "sg:address":"Marketing Suite, California Dr, Wakefield Europort",
    "sg:city":"Castleford",
    "sg:classifiers":[
        {
            "category":"Building & Trades",
            "subcategory":"Construction",
            "type":"Services"
        }
    ],
    "sg:phone":"+44 1924 364411",
    "sg:postcode":"WF10 5QW",
    "sg:province":"West Yorkshire",
    "sg:tags":[
        "builder"
    ],
    "wof:name":"Wakefield Europort",
    "wof:placetype":"venue"
},
  "geometry": {"coordinates":[-1.38185,53.71117],"type":"Point"}
}