{
  "type": "Feature",
  "properties": {
    "iso:country":"GB",
    "sg:address":"22 Sherbrooke Drive",
    "sg:city":"Glasgow",
    "sg:classifiers":[
        {
            "category":"Professional",
            "subcategory":"Management & Consulting",
            "type":"Services"
        }
    ],
    "sg:phone":"+44 141 427 6164",
    "sg:postcode":"G41 5AA",
    "sg:province":"Glasgow City",
    "sg:tags":[
        "consultant",
        "business"
    ],
    "wof:name":"Ian & Sylvia McKay",
    "wof:placetype":"venue"
},
  "geometry": {"coordinates":[-4.297252,55.844986],"type":"Point"}
}