{
  "type": "Feature",
  "properties": {
    "addr:full":"Maltmans Lane Gerrards Cross Buckinghamshire SL9 8RR",
    "addr:postcode":"sl9 8rr",
    "addr:street":"Maltmans Lane",
    "iso:country":"GB",
    "sg:address":"Maltmans Lane",
    "sg:city":"Gerrards Cross",
    "sg:classifiers":[
        {
            "category":"Education",
            "subcategory":"School",
            "type":"Public Place"
        }
    ],
    "sg:postcode":"SL9 8RR",
    "sg:province":"Buckinghamshire",
    "sg:tags":[
        "independent",
        "preparatory"
    ],
    "wof:name":"Maltmans Green School Trust Ltd.",
    "wof:placetype":"venue"
},
  "geometry": {"coordinates":[-0.567434,51.596859],"type":"Point"}
}