{
  "type": "Feature",
  "properties": {
    "iso:country":"GB",
    "sg:address":"67 Farm Way",
    "sg:city":"Worcester Park",
    "sg:classifiers":[
        {
            "category":"Professional",
            "subcategory":"Engineering",
            "type":"Services"
        }
    ],
    "sg:phone":"+44 20 8337 2315",
    "sg:postcode":"KT4 8SB",
    "sg:province":"Surrey",
    "sg:tags":[
        "contractor",
        "electrical",
        "engineer"
    ],
    "wof:name":"J S P Electrical Installations",
    "wof:placetype":"venue"
},
  "geometry": {"coordinates":[-0.22761,51.375576],"type":"Point"}
}