{
  "type": "Feature",
  "properties": {
    "addr:full":"Unit D3, Welland Ind Est Market Harborough Leicestershire LE16 7PS",
    "addr:housenumber":"d3",
    "addr:postcode":"le16 7ps",
    "addr:street":"Welland Ind Est",
    "iso:country":"GB",
    "sg:address":"Unit D3, Welland Ind Est",
    "sg:city":"Market Harborough",
    "sg:classifiers":[
        {
            "category":"Professional",
            "type":"Services"
        }
    ],
    "sg:phone":"+44 1858 410242",
    "sg:postcode":"LE16 7PS",
    "sg:province":"Leicestershire",
    "sg:tags":[
        "exhibition"
    ],
    "wof:name":"Omnis Exhibition & Display",
    "wof:placetype":"venue"
},
  "geometry": {"coordinates":[-0.96359,52.496284],"type":"Point"}
}