{
  "type": "Feature",
  "properties": {
    "iso:country":"GB",
    "sg:address":"745-747 Clarkston Road",
    "sg:city":"Glasgow",
    "sg:classifiers":[
        {
            "category":"Retail",
            "subcategory":"Funeral Services",
            "type":"Services"
        }
    ],
    "sg:phone":"+44 141 633 5033",
    "sg:postcode":"G44 3XA",
    "sg:province":"East Renfrewshire",
    "wof:name":"Laird & McMillan",
    "wof:placetype":"venue"
},
  "geometry": {"coordinates":[-4.2727251053,55.7996406555],"type":"Point"}
}