{
  "type": "Feature",
  "properties": {
    "addr:full":"10 Sandyford Pl Glasgow Glasgow City G3 7NB",
    "addr:housenumber":"10",
    "addr:postcode":"g3 7nb",
    "addr:street":"Sandyford Pl",
    "iso:country":"GB",
    "sg:address":"10 Sandyford Pl",
    "sg:city":"Glasgow",
    "sg:classifiers":[
        {
            "category":"Real Estate",
            "subcategory":"Surveying",
            "type":"Services"
        }
    ],
    "sg:phone":"+44 141 204 3234",
    "sg:postcode":"G3 7NB",
    "sg:province":"Glasgow City",
    "sg:tags":[
        "surveyor",
        "valuer"
    ],
    "wof:name":"William McVicar",
    "wof:placetype":"venue"
},
  "geometry": {"coordinates":[-4.276714,55.865753],"type":"Point"}
}