{
  "type": "Feature",
  "properties": {
    "addr:full":"Unit B North Rd, Bridgend Indust Est Bridgend Bridgend CF31 3TP",
    "addr:housenumber":"b",
    "addr:postcode":"cf31 3tp",
    "addr:street":"North Rd;Indust",
    "iso:country":"GB",
    "sg:address":"Unit B North Rd, Bridgend Indust Est",
    "sg:city":"Bridgend",
    "sg:classifiers":[
        {
            "category":"Government",
            "subcategory":"Post Office",
            "type":"Public Place"
        }
    ],
    "sg:phone":"+44 1656 664336",
    "sg:postcode":"CF31 3TP",
    "sg:province":"Bridgend",
    "sg:tags":[
        "messenger",
        "courier"
    ],
    "wof:name":"Midnite Express",
    "wof:placetype":"venue"
},
  "geometry": {"coordinates":[-3.5399138927,51.5031890869],"type":"Point"}
}