{
  "type": "Feature",
  "properties": {
    "addr:full":"33 Warren Close Cheltenham Gloucestershire GL51 3HW",
    "addr:housenumber":"33",
    "addr:postcode":"gl51 3hw",
    "addr:street":"Warren Close",
    "iso:country":"GB",
    "sg:address":"33 Warren Close",
    "sg:city":"Cheltenham",
    "sg:classifiers":[
        {
            "category":"Building & Trades",
            "subcategory":"Construction",
            "type":"Services"
        }
    ],
    "sg:phone":"+44 1242 576891",
    "sg:postcode":"GL51 3HW",
    "sg:province":"Gloucestershire",
    "sg:tags":[
        "builder"
    ],
    "wof:name":"J P Building",
    "wof:placetype":"venue"
},
  "geometry": {"coordinates":[-2.1065080166,51.8871040344],"type":"Point"}
}