{
  "type": "Feature",
  "properties": {
    "addr:full":"Moor Lane Trading Estate, Sherburn-in-elmet Leeds North Yorkshire LS25 6ES",
    "addr:postcode":"ls25 6es",
    "addr:street":"Moor Lane Trading Estate",
    "iso:country":"GB",
    "sg:address":"Moor Lane Trading Estate, Sherburn-in-elmet",
    "sg:city":"Leeds",
    "sg:classifiers":[
        {
            "category":"Manufacturing",
            "subcategory":"Rubber & Plastics",
            "type":"Manufacturing & Wholesale Goods"
        }
    ],
    "sg:phone":"+44 1977 882000",
    "sg:postcode":"LS25 6ES",
    "sg:province":"North Yorkshire",
    "sg:tags":[
        "product"
    ],
    "wof:name":"Constar International U K Ltd.",
    "wof:placetype":"venue"
},
  "geometry": {"coordinates":[-1.2410769463,53.7976036072],"type":"Point"}
}