{
  "type": "Feature",
  "properties": {
    "iso:country":"GB",
    "sg:address":"8 Saddle Close, Norton",
    "sg:city":"Malton",
    "sg:classifiers":[
        {
            "category":"Professional",
            "subcategory":"Engineering",
            "type":"Services"
        }
    ],
    "sg:postcode":"YO17 9JY",
    "sg:province":"North Yorkshire",
    "sg:tags":[
        "contractor",
        "electrical",
        "engineer"
    ],
    "wof:name":"A N Foster",
    "wof:placetype":"venue"
},
  "geometry": {"coordinates":[-0.78424,54.127483],"type":"Point"}
}