{
  "type": "Feature",
  "properties": {
    "iso:country":"GB",
    "sg:address":"44 Park Avenue",
    "sg:city":"Bedford",
    "sg:classifiers":[
        {
            "category":"Health Services",
            "subcategory":"Nursing And Care Facility",
            "type":"Services"
        }
    ],
    "sg:phone":"+44 1234 218571",
    "sg:postcode":"MK40 2NF",
    "sg:province":"Bedfordshire",
    "sg:tags":[
        "home"
    ],
    "wof:name":"Airedale Nursing Home",
    "wof:placetype":"venue"
},
  "geometry": {"coordinates":[-0.4577369988,52.1476593018],"type":"Point"}
}