{
  "type": "Feature",
  "properties": {
    "addr:full":"Care Of Sportlife, 1 High St Manchester Greater Manchester M28 3JH",
    "addr:housenumber":"1",
    "addr:postcode":"m28 3jh",
    "addr:street":"High St",
    "iso:country":"GB",
    "sg:address":"Care Of Sportlife, 1 High St",
    "sg:city":"Manchester",
    "sg:classifiers":[
        {
            "category":"Personal",
            "subcategory":"Beauty Salon",
            "type":"Services"
        }
    ],
    "sg:phone":"+44 161 702 8353",
    "sg:postcode":"M28 3JH",
    "sg:province":"Greater Manchester",
    "wof:name":"Beverley Dawn",
    "wof:placetype":"venue"
},
  "geometry": {"coordinates":[-2.4002,53.523769],"type":"Point"}
}