{
  "type": "Feature",
  "properties": {
    "addr:full":"21 Marine Drive, Rottingdean Brighton East Sussex BN2 7HJ",
    "addr:housenumber":"21",
    "addr:postcode":"bn2 7hj",
    "addr:street":"Marine Drive",
    "iso:country":"GB",
    "sg:address":"21 Marine Drive, Rottingdean",
    "sg:city":"Brighton",
    "sg:classifiers":[
        {
            "category":"Manufacturing",
            "subcategory":"Textiles",
            "type":"Manufacturing & Wholesale Goods"
        }
    ],
    "sg:phone":"+44 1323 891653",
    "sg:postcode":"BN2 7HJ",
    "sg:province":"East Sussex",
    "sg:tags":[
        "made-up"
    ],
    "wof:name":"Westwood-trafalgar Bed Makers",
    "wof:placetype":"venue"
},
  "geometry": {"coordinates":[-0.0591530018,50.8033866882],"type":"Point"}
}