{
  "type": "Feature",
  "properties": {
    "iso:country":"GB",
    "sg:address":"10 Merryvale Place, Giffnock",
    "sg:city":"Glasgow",
    "sg:classifiers":[
        {
            "category":"Fast Food",
            "type":"Food & Drink"
        }
    ],
    "sg:phone":"+44 141 633 1510",
    "sg:postcode":"G46 6AT",
    "sg:province":"East Renfrewshire",
    "sg:tags":[
        "delivery"
    ],
    "wof:name":"Armandos Pizza",
    "wof:placetype":"venue"
},
  "geometry": {"coordinates":[-4.291001,55.812603],"type":"Point"}
}