{
  "type": "Feature",
  "properties": {
    "addr:full":"263 Southmead Rd Bristol City of Bristol BS10 5EL",
    "addr:housenumber":"263",
    "addr:postcode":"bs10 5el",
    "addr:street":"Southmead Rd",
    "iso:country":"GB",
    "sg:address":"263 Southmead Rd",
    "sg:city":"Bristol",
    "sg:classifiers":[
        {
            "category":"Professional",
            "subcategory":"Computer Services",
            "type":"Services"
        }
    ],
    "sg:phone":"+44 117 904 7245",
    "sg:postcode":"BS10 5EL",
    "sg:province":"City of Bristol",
    "sg:tags":[
        "system",
        "software"
    ],
    "wof:name":"SDL IT Solutions",
    "wof:placetype":"venue"
},
  "geometry": {"coordinates":[-2.593528986,51.5001907349],"type":"Point"}
}