{
  "type": "Feature",
  "properties": {
    "addr:full":"Four Lanes End, Bickerstaffe Ormskirk Lancashire L39 0EZ",
    "addr:postcode":"l39 0ez",
    "addr:street":"Lanes End",
    "iso:country":"GB",
    "sg:address":"Four Lanes End, Bickerstaffe",
    "sg:city":"Ormskirk",
    "sg:classifiers":[
        {
            "category":"Restaurant",
            "type":"Food & Drink"
        }
    ],
    "sg:phone":"+44 1695 50481",
    "sg:postcode":"L39 0EZ",
    "sg:province":"Lancashire",
    "wof:name":"Moto Hospitality Ltd.",
    "wof:placetype":"venue"
},
  "geometry": {"coordinates":[-2.886300087,53.5662765503],"type":"Point"}
}