{
  "type": "Feature",
  "properties": {
    "iso:country":"GB",
    "sg:address":"Longbutts Lane, Gawsworth",
    "sg:city":"Macclesfield",
    "sg:classifiers":[
        {
            "category":"Education",
            "subcategory":"School",
            "type":"Public Place"
        }
    ],
    "sg:phone":"+44 1625 426547",
    "sg:postcode":"SK11 9QU",
    "sg:province":"Cheshire",
    "sg:tags":[
        "local",
        "authority"
    ],
    "wof:name":"Gawsworth County Primary School",
    "wof:placetype":"venue"
},
  "geometry": {"coordinates":[-2.165619,53.231998],"type":"Point"}
}