{
  "type": "Feature",
  "properties": {
    "iso:country":"GB",
    "sg:address":"1 Pitt Terrace",
    "sg:city":"Stirling",
    "sg:classifiers":[
        {
            "category":"Professional",
            "subcategory":"Lawyer & Legal Services",
            "type":"Services"
        }
    ],
    "sg:phone":"+44 1786 27765",
    "sg:postcode":"FK8 2EZ",
    "sg:province":"Stirling",
    "sg:tags":[
        "solicitor"
    ],
    "wof:name":"Paul Gebal & Co",
    "wof:placetype":"venue"
},
  "geometry": {"coordinates":[-3.9379088879,56.1146888733],"type":"Point"}
}