{
  "type": "Feature",
  "properties": {
    "addr:full":"Yewtree Cottage, Willersley Lane Matlock Derbyshire DE4 5JG",
    "addr:postcode":"de4 5jg",
    "addr:street":"Willersley Lane",
    "iso:country":"GB",
    "sg:address":"Yewtree Cottage, Willersley Lane",
    "sg:city":"Matlock",
    "sg:classifiers":[
        {
            "category":"Professional",
            "subcategory":"Art Services",
            "type":"Services"
        }
    ],
    "sg:postcode":"DE4 5JG",
    "sg:province":"Derbyshire",
    "sg:tags":[
        "glass",
        "engraver"
    ],
    "wof:name":"John Balcombe",
    "wof:placetype":"venue"
},
  "geometry": {"coordinates":[-1.548274,53.135616],"type":"Point"}
}