{
  "type": "Feature",
  "properties": {
    "iso:country":"GB",
    "sg:address":"21 Holmes Land Walk, Botley",
    "sg:city":"Southampton",
    "sg:classifiers":[
        {
            "category":"Professional",
            "subcategory":"Engineering",
            "type":"Services"
        }
    ],
    "sg:postcode":"SO30 2DZ",
    "sg:province":"Hampshire",
    "sg:tags":[
        "contractor",
        "electrical",
        "engineer"
    ],
    "wof:name":"Botley Electrical Services",
    "wof:placetype":"venue"
},
  "geometry": {"coordinates":[-1.276266,50.919167],"type":"Point"}
}