{
  "type": "Feature",
  "properties": {
    "iso:country":"GB",
    "sg:address":"25 Gladstone Road",
    "sg:city":"Scarborough",
    "sg:classifiers":[
        {
            "category":"Personal",
            "subcategory":"Beauty Salon",
            "type":"Services"
        }
    ],
    "sg:phone":"+44 1723 365803",
    "sg:postcode":"YO12 7BQ",
    "sg:province":"North Yorkshire",
    "sg:tags":[
        "unisex",
        "hairdresser"
    ],
    "wof:name":"Joanna's Hair Studio",
    "wof:placetype":"venue"
},
  "geometry": {"coordinates":[-0.410531,54.281773],"type":"Point"}
}