{
  "type": "Feature",
  "properties": {
    "iso:country":"GB",
    "sg:address":"Cross La",
    "sg:city":"Salford",
    "sg:classifiers":[
        {
            "category":"Place Of Worship",
            "type":"Public Place"
        }
    ],
    "sg:phone":"+44 161 736 9572",
    "sg:postcode":"M5 4AA",
    "sg:province":"Greater Manchester",
    "wof:name":"Salford Religious Centre For Spiritualism",
    "wof:placetype":"venue"
},
  "geometry": {"coordinates":[-2.2779240608,53.4851455688],"type":"Point"}
}