{
  "type": "Feature",
  "properties": {
    "iso:country":"GB",
    "sg:address":"22 Greenwood Street",
    "sg:city":"Altrincham",
    "sg:classifiers":[
        {
            "category":"Real Estate",
            "subcategory":"Surveying",
            "type":"Services"
        }
    ],
    "sg:phone":"+44 161 929 9901",
    "sg:postcode":"WA14 1RZ",
    "sg:province":"Cheshire",
    "sg:tags":[
        "surveyor",
        "valuer"
    ],
    "wof:name":"Robert S Cohen",
    "wof:placetype":"venue"
},
  "geometry": {"coordinates":[-2.352405,53.386456],"type":"Point"}
}