{
  "type": "Feature",
  "properties": {
    "addr:full":"Willow Lodge, Cambridge Road, Thundridge Ware Hertfordshire SG12 0SU",
    "addr:postcode":"sg12 0su",
    "addr:street":"Cambridge Road;Ware",
    "iso:country":"GB",
    "sg:address":"Willow Lodge, Cambridge Road, Thundridge",
    "sg:city":"Ware",
    "sg:classifiers":[
        {
            "category":"Professional",
            "subcategory":"Employment Agencies",
            "type":"Services"
        }
    ],
    "sg:phone":"+44 1920 467802",
    "sg:postcode":"SG12 0SU",
    "sg:province":"Hertfordshire",
    "sg:tags":[
        "pair",
        "au"
    ],
    "wof:name":"Ace Au Pair Agency",
    "wof:placetype":"venue"
},
  "geometry": {"coordinates":[-0.035127,51.816338],"type":"Point"}
}