{
  "type": "Feature",
  "properties": {
    "addr:full":"316 Upminster Road North Rainham Essex RM13 9RY",
    "addr:housenumber":"316",
    "addr:postcode":"rm13 9ry",
    "addr:street":"Upminster Road North",
    "iso:country":"GB",
    "sg:address":"316 Upminster Road North",
    "sg:city":"Rainham",
    "sg:classifiers":[
        {
            "category":"Education",
            "subcategory":"Music School",
            "type":"Public Place"
        }
    ],
    "sg:postcode":"RM13 9RY",
    "sg:province":"Essex",
    "sg:tags":[
        "teacher"
    ],
    "wof:name":"Frank Warby",
    "wof:placetype":"venue"
},
  "geometry": {"coordinates":[0.211042,51.521435],"type":"Point"}
}