{
  "type": "Feature",
  "properties": {
    "iso:country":"GB",
    "sg:address":"Parkway Pen-y-fan Industrial Estate, Croespenmaen Crumlin",
    "sg:city":"Newport",
    "sg:classifiers":[
        {
            "category":"Manufacturing",
            "subcategory":"Textiles",
            "type":"Manufacturing & Wholesale Goods"
        }
    ],
    "sg:phone":"+44 1495 246220",
    "sg:postcode":"NP11 3XG",
    "sg:province":"Blaenau Gwent",
    "sg:tags":[
        "mnfr",
        "rug",
        "carpet"
    ],
    "wof:name":"Carpets International (U K) Ltd.",
    "wof:placetype":"venue"
},
  "geometry": {"coordinates":[-3.164144,51.680424],"type":"Point"}
}