{
  "type": "Feature",
  "properties": {
    "iso:country":"GB",
    "sg:address":"Unit 6 Bankside Park Industrial Estate, 28 Thames Road",
    "sg:city":"Barking",
    "sg:classifiers":[
        {
            "category":"Professional",
            "subcategory":"Printing & Photocopies",
            "type":"Services"
        }
    ],
    "sg:postcode":"IG11 0HZ",
    "sg:province":"Essex",
    "sg:tags":[
        "computer",
        "tag",
        "label"
    ],
    "wof:name":"Essex Self Adhesive Labels",
    "wof:placetype":"venue"
},
  "geometry": {"coordinates":[0.0811149999,51.539100647],"type":"Point"}
}