{
  "type": "Feature",
  "properties": {
    "addr:full":"186 Derby La Liverpool Merseyside L13 6QQ",
    "addr:housenumber":"186",
    "addr:postcode":"l13 6qq",
    "addr:street":"Derby La",
    "iso:country":"GB",
    "sg:address":"186 Derby La",
    "sg:city":"Liverpool",
    "sg:classifiers":[
        {
            "category":"Food & Beverages",
            "subcategory":"Meat & Fish",
            "type":"Retail Goods"
        }
    ],
    "sg:phone":"+44 151 220 7683",
    "sg:postcode":"L13 6QQ",
    "sg:province":"Merseyside",
    "sg:tags":[
        "chip"
    ],
    "wof:name":"Wongs Fish & Chips",
    "wof:placetype":"venue"
},
  "geometry": {"coordinates":[-2.914294,53.420471],"type":"Point"}
}