{
  "type": "Feature",
  "properties": {
    "addr:full":"333 Athlon Road Wembley Greater London HA0 1EF",
    "addr:housenumber":"333",
    "addr:postcode":"ha0 1ef",
    "addr:street":"Athlon Road",
    "iso:country":"GB",
    "sg:address":"333 Athlon Road",
    "sg:city":"Wembley",
    "sg:classifiers":[
        {
            "category":"Home & Garden",
            "subcategory":"Home Furnishings",
            "type":"Retail Goods"
        }
    ],
    "sg:phone":"+44 20 8810 5432",
    "sg:postcode":"HA0 1EF",
    "sg:province":"Greater London",
    "sg:tags":[
        "blind",
        "curtain",
        "fitting"
    ],
    "wof:name":"Jago Products Ltd",
    "wof:placetype":"venue"
},
  "geometry": {"coordinates":[-0.3040120006,51.5371055603],"type":"Point"}
}