{
  "type": "Feature",
  "properties": {
    "addr:full":"648 Alexandra Parade Glasgow Glasgow City G31 3BU",
    "addr:housenumber":"648",
    "addr:postcode":"g31 3bu",
    "addr:street":"Alexandra Parade",
    "iso:country":"GB",
    "sg:address":"648 Alexandra Parade",
    "sg:city":"Glasgow",
    "sg:classifiers":[
        {
            "category":"Professional",
            "subcategory":"Lawyer & Legal Services",
            "type":"Services"
        }
    ],
    "sg:phone":"+44 141 554 8837",
    "sg:postcode":"G31 3BU",
    "sg:province":"Glasgow City",
    "sg:tags":[
        "solicitor"
    ],
    "wof:name":"B McConville & Co",
    "wof:placetype":"venue"
},
  "geometry": {"coordinates":[-4.2103390694,55.8630905151],"type":"Point"}
}