{
  "type": "Feature",
  "properties": {
    "addr:full":"Unit 2, Cavendish Place Ashton-under-lyne Greater Manchester OL6 7DQ",
    "addr:housenumber":"unit 2",
    "addr:postcode":"ol6 7dq",
    "addr:street":"Cavendish Place",
    "iso:country":"GB",
    "sg:address":"Unit 2, Cavendish Place",
    "sg:city":"Ashton-under-lyne",
    "sg:classifiers":[
        {
            "category":"Home & Garden",
            "subcategory":"Home Furnishings",
            "type":"Retail Goods"
        },
        {
            "category":"Home & Garden",
            "subcategory":"Carpets & Floor Coverings",
            "type":"Retail Goods"
        }
    ],
    "sg:phone":"+44 161 343 2752",
    "sg:postcode":"OL6 7DQ",
    "sg:province":"Greater Manchester",
    "sg:tags":[
        "fitting",
        "rug",
        "matting",
        "carpets"
    ],
    "wof:name":"Beechwood Carpets",
    "wof:placetype":"venue"
},
  "geometry": {"coordinates":[-2.101039,53.489567],"type":"Point"}
}