{
  "type": "Feature",
  "properties": {
    "addr:full":"The Orchard Bristol City of Bristol BS3 2JX",
    "addr:postcode":"bs3 2jx",
    "iso:country":"GB",
    "sg:address":"The Orchard",
    "sg:city":"Bristol",
    "sg:classifiers":[
        {
            "category":"Shopping",
            "subcategory":"Books",
            "type":"Retail Goods"
        }
    ],
    "sg:phone":"+44 117 944 6491",
    "sg:postcode":"BS3 2JX",
    "sg:province":"City of Bristol",
    "wof:name":"Bio Press Ltd.",
    "wof:placetype":"venue"
},
  "geometry": {"coordinates":[-2.5465869904,51.3697166443],"type":"Point"}
}