{
  "type": "Feature",
  "properties": {
    "iso:country":"GB",
    "sg:address":"622 Hyde Road",
    "sg:city":"Manchester",
    "sg:classifiers":[
        {
            "category":"Personal",
            "subcategory":"Beauty Salon",
            "type":"Services"
        }
    ],
    "sg:phone":"+44 161 223 2973",
    "sg:postcode":"M18 7EE",
    "sg:province":"Greater Manchester",
    "sg:tags":[
        "unisex",
        "hairdresser"
    ],
    "wof:name":"Helen's Hair Design",
    "wof:placetype":"venue"
},
  "geometry": {"coordinates":[-2.174309,53.456051],"type":"Point"}
}