{
  "type": "Feature",
  "properties": {
    "addr:full":"50 Calvert Drive Basildon Essex SS13 1TB",
    "addr:housenumber":"50",
    "addr:postcode":"ss13 1tb",
    "addr:street":"Calvert Drive",
    "iso:country":"GB",
    "sg:address":"50 Calvert Drive",
    "sg:city":"Basildon",
    "sg:classifiers":[
        {
            "category":"Home & Garden",
            "subcategory":"Building Materials",
            "type":"Retail Goods"
        }
    ],
    "sg:postcode":"SS13 1TB",
    "sg:province":"Essex",
    "sg:tags":[
        "shutter",
        "door"
    ],
    "wof:name":"Robert Jagger",
    "wof:placetype":"venue"
},
  "geometry": {"coordinates":[0.5150449872,51.5832824707],"type":"Point"}
}