{
  "type": "Feature",
  "properties": {
    "iso:country":"GB",
    "sg:address":"258 East End Rd",
    "sg:city":"East Finchley",
    "sg:classifiers":[
        {
            "category":"Manufacturing",
            "subcategory":"Building Materials",
            "type":"Manufacturing & Wholesale Goods"
        }
    ],
    "sg:phone":"+44 20 8883 0635",
    "sg:postcode":"N2 8AU",
    "sg:province":"Greater London",
    "sg:tags":[
        "mnfr",
        "maker",
        "cabinet"
    ],
    "wof:name":"Splinters Joinery",
    "wof:placetype":"venue"
},
  "geometry": {"coordinates":[-0.171799,51.594231],"type":"Point"}
}