{
  "type": "Feature",
  "properties": {
    "addr:full":"11 Panmure St Dundee Dundee City DD1 2BG",
    "addr:housenumber":"11",
    "addr:postcode":"dd1 2bg",
    "addr:street":"Panmure St",
    "iso:country":"GB",
    "sg:address":"11 Panmure St",
    "sg:city":"Dundee",
    "sg:classifiers":[
        {
            "category":"Professional",
            "subcategory":"Management & Consulting",
            "type":"Services"
        }
    ],
    "sg:phone":"+44 1382 205160",
    "sg:postcode":"DD1 2BG",
    "sg:province":"Dundee City",
    "sg:tags":[
        "consultant",
        "business"
    ],
    "wof:name":"Gordon & Henderson",
    "wof:placetype":"venue"
},
  "geometry": {"coordinates":[-2.970442,56.463123],"type":"Point"}
}