{
  "type": "Feature",
  "properties": {
    "addr:full":"2 Willow Close, Stoke Canon Exeter Devon EX5 4AB",
    "addr:housenumber":"2",
    "addr:postcode":"ex5 4ab",
    "addr:street":"Willow Close",
    "iso:country":"GB",
    "sg:address":"2 Willow Close, Stoke Canon",
    "sg:city":"Exeter",
    "sg:classifiers":[
        {
            "category":"Real Estate",
            "subcategory":"Architect",
            "type":"Services"
        }
    ],
    "sg:phone":"+44 1392 841335",
    "sg:postcode":"EX5 4AB",
    "sg:province":"Devon",
    "sg:tags":[
        "architectural"
    ],
    "wof:name":"John W Piper",
    "wof:placetype":"venue"
},
  "geometry": {"coordinates":[-3.5078959465,50.7713050842],"type":"Point"}
}