{
  "type": "Feature",
  "properties": {
    "iso:country":"GB",
    "sg:address":"69 Claude Rd",
    "sg:city":"Leyton",
    "sg:classifiers":[
        {
            "category":"Building & Trades",
            "subcategory":"Construction",
            "type":"Services"
        }
    ],
    "sg:phone":"+44 20 8539 0328",
    "sg:postcode":"E10 6NG",
    "sg:province":"Greater London",
    "sg:tags":[
        "builder"
    ],
    "wof:name":"P I P Service",
    "wof:placetype":"venue"
},
  "geometry": {"coordinates":[-0.005259,51.565887],"type":"Point"}
}