{
  "type": "Feature",
  "properties": {
    "iso:country":"GB",
    "sg:address":"128 Mount Street",
    "sg:city":"London",
    "sg:classifiers":[
        {
            "category":"Real Estate",
            "subcategory":"Developer",
            "type":"Services"
        }
    ],
    "sg:phone":"+44 20 7495 3599",
    "sg:postcode":"W1K 3NU",
    "sg:province":"Greater London",
    "sg:tags":[
        "property"
    ],
    "wof:name":"St.Anselm Development Co. Ltd.",
    "wof:placetype":"venue"
},
  "geometry": {"coordinates":[-0.147939,51.51022],"type":"Point"}
}