{
  "type": "Feature",
  "properties": {
    "iso:country":"GB",
    "sg:address":"30 Tynemouth Road",
    "sg:city":"Wallsend",
    "sg:classifiers":[
        {
            "category":"Professional",
            "subcategory":"Lawyer & Legal Services",
            "type":"Services"
        }
    ],
    "sg:phone":"+44 191 234 3434",
    "sg:postcode":"NE28 0LF",
    "sg:province":"Tyne and Wear",
    "sg:tags":[
        "solicitor"
    ],
    "wof:name":"Paul Dodds & Hindson",
    "wof:placetype":"venue"
},
  "geometry": {"coordinates":[-1.501638,54.996677],"type":"Point"}
}