{
  "type": "Feature",
  "properties": {
    "addr:full":"Highfield, Southstoke Road Reading Berkshire RG8 0PL",
    "addr:postcode":"rg8 0pl",
    "addr:street":"Southstoke Road",
    "iso:country":"GB",
    "sg:address":"Highfield, Southstoke Road",
    "sg:city":"Reading",
    "sg:classifiers":[
        {
            "category":"Building & Trades",
            "subcategory":"Plumbing",
            "type":"Services"
        }
    ],
    "sg:postcode":"RG8 0PL",
    "sg:province":"Berkshire",
    "sg:tags":[
        "heating"
    ],
    "wof:name":"Robert G Giles",
    "wof:placetype":"venue"
},
  "geometry": {"coordinates":[-1.0812939405,51.5353851318],"type":"Point"}
}