{
  "type": "Feature",
  "properties": {
    "addr:full":"Redriff, Ethelbert Road, Ashingdon Rochford Essex SS4 3JS",
    "addr:postcode":"ss4 3js",
    "addr:street":"Ethelbert Road",
    "iso:country":"GB",
    "sg:address":"Redriff, Ethelbert Road, Ashingdon",
    "sg:city":"Rochford",
    "sg:classifiers":[
        {
            "category":"Building & Trades",
            "subcategory":"Equipment Rental",
            "type":"Services"
        }
    ],
    "sg:phone":"+44 1702 204472",
    "sg:postcode":"SS4 3JS",
    "sg:province":"Essex",
    "sg:tags":[
        "hire",
        "catering"
    ],
    "wof:name":"Cottage Catering Hire Services",
    "wof:placetype":"venue"
},
  "geometry": {"coordinates":[0.6961699724,51.5986785889],"type":"Point"}
}