{
  "type": "Feature",
  "properties": {
    "iso:country":"GB",
    "sg:address":"Church Rd",
    "sg:city":"Smethwick",
    "sg:classifiers":[
        {
            "category":"Place Of Worship",
            "type":"Public Place"
        }
    ],
    "sg:phone":"+44 121 558 1763",
    "sg:postcode":"B67 6EE",
    "sg:province":"West Midlands",
    "wof:name":"Smethwick Old Church",
    "wof:placetype":"venue"
},
  "geometry": {"coordinates":[-1.9686640501,52.4853134155],"type":"Point"}
}