{
  "type": "Feature",
  "properties": {
    "addr:full":"3 Malham Gro York North Yorkshire YO31 0QG",
    "addr:housenumber":"3",
    "addr:postcode":"yo31 0qg",
    "addr:street":"Malham Gro",
    "iso:country":"GB",
    "sg:address":"3 Malham Gro",
    "sg:city":"York",
    "sg:classifiers":[
        {
            "category":"Shopping",
            "subcategory":"Clothing, Apparel, & Fashions",
            "type":"Retail Goods"
        }
    ],
    "sg:phone":"+44 1904 411011",
    "sg:postcode":"YO31 0QG",
    "sg:province":"North Yorkshire",
    "sg:tags":[
        "lingerie"
    ],
    "wof:name":"David Hughes",
    "wof:placetype":"venue"
},
  "geometry": {"coordinates":[-1.0469939709,53.9606819153],"type":"Point"}
}