{
  "type": "Feature",
  "properties": {
    "addr:full":"7 Buailbhan, Ballinluig Pitlochry Perth and Kinross PH9 0NH",
    "addr:housenumber":"7",
    "addr:postcode":"ph9 0nh",
    "addr:street":"Buailbhan Ballinluig",
    "iso:country":"GB",
    "sg:address":"7 Buailbhan, Ballinluig",
    "sg:city":"Pitlochry",
    "sg:classifiers":[
        {
            "category":"Building & Trades",
            "subcategory":"Construction",
            "type":"Services"
        }
    ],
    "sg:phone":"+44 1796 482439",
    "sg:postcode":"PH9 0NH",
    "sg:province":"Perth and Kinross",
    "sg:tags":[
        "decorator",
        "painter"
    ],
    "wof:name":"W Brown",
    "wof:placetype":"venue"
},
  "geometry": {"coordinates":[-3.6852591038,56.6445083618],"type":"Point"}
}