{
  "type": "Feature",
  "properties": {
    "iso:country":"GB",
    "sg:address":"17 Duncans Close",
    "sg:city":"Andover",
    "sg:classifiers":[
        {
            "category":"Building & Trades",
            "subcategory":"Cleaning & Sanitation",
            "type":"Services"
        }
    ],
    "sg:phone":"+44 1264 771115",
    "sg:postcode":"SP11 8EJ",
    "sg:province":"Hampshire",
    "sg:tags":[
        "cleaner",
        "window"
    ],
    "wof:name":"Cleanscene",
    "wof:placetype":"venue"
},
  "geometry": {"coordinates":[-1.5790029764,51.2196617126],"type":"Point"}
}