{
  "type": "Feature",
  "properties": {
    "addr:full":"Newhaven, Redmoor Bodmin Cornwall PL30 5AT",
    "addr:postcode":"pl30 5at",
    "addr:street":"Bodmin",
    "iso:country":"GB",
    "sg:address":"Newhaven, Redmoor",
    "sg:city":"Bodmin",
    "sg:classifiers":[
        {
            "category":"Autos & Motor Vehicles",
            "subcategory":"Automobile Sales",
            "type":"Retail Goods"
        }
    ],
    "sg:phone":"+44 1208 872584",
    "sg:postcode":"PL30 5AT",
    "sg:province":"Cornwall",
    "sg:tags":[
        "commercial",
        "van",
        "truck"
    ],
    "wof:name":"Marshalls Motors",
    "wof:placetype":"venue"
},
  "geometry": {"coordinates":[-4.703988,50.420387],"type":"Point"}
}