{
  "type": "Feature",
  "properties": {
    "addr:full":"Rob Royd Farm, Hound Hill, Worbrough Bridge Barnsley South Yorkshire S70 6TY",
    "addr:postcode":"s70 6ty",
    "addr:street":"Hound Hill Worbrough Bridge;Yorkshire",
    "iso:country":"GB",
    "sg:address":"Rob Royd Farm, Hound Hill, Worbrough Bridge",
    "sg:city":"Barnsley",
    "sg:classifiers":[
        {
            "category":"Farming",
            "subcategory":"Livestock Farm",
            "type":"Manufacturing & Wholesale Goods"
        }
    ],
    "sg:phone":"+44 1226 281746",
    "sg:postcode":"S70 6TY",
    "sg:province":"South Yorkshire",
    "sg:tags":[
        "others"
    ],
    "wof:name":"L T White",
    "wof:placetype":"venue"
},
  "geometry": {"coordinates":[-1.484738,53.553192],"type":"Point"}
}