{
  "type": "Feature",
  "properties": {
    "addr:full":"Unit4, 11 Market Street Alton Hampshire GU34 1HA",
    "addr:housenumber":"11",
    "addr:postcode":"gu34 1ha",
    "addr:street":"Unit4;Market Street",
    "iso:country":"GB",
    "sg:address":"Unit4, 11 Market Street",
    "sg:city":"Alton",
    "sg:classifiers":[
        {
            "category":"Shopping",
            "subcategory":"Gifts & Souvenirs",
            "type":"Retail Goods"
        },
        {
            "category":"Shopping",
            "subcategory":"Florist",
            "type":"Retail Goods"
        }
    ],
    "sg:phone":"+44 1420 544194",
    "sg:postcode":"GU34 1HA",
    "sg:province":"Hampshire",
    "sg:tags":[
        "shop"
    ],
    "wof:name":"The Botanic Gardens",
    "wof:placetype":"venue"
},
  "geometry": {"coordinates":[-0.976574,51.1488],"type":"Point"}
}