{
  "type": "Feature",
  "properties": {
    "iso:country":"GB",
    "sg:address":"Unit 2 Gallagher Industrial Estate, First Avenue, Forge Lane",
    "sg:city":"Birmingham",
    "sg:classifiers":[
        {
            "category":"Manufacturing",
            "subcategory":"Building Materials",
            "type":"Manufacturing & Wholesale Goods"
        }
    ],
    "sg:phone":"+44 121 313 2020",
    "sg:postcode":"B76 8BA",
    "sg:province":"Warwickshire",
    "sg:tags":[
        "merchant",
        "builder"
    ],
    "wof:name":"Selco Timber",
    "wof:placetype":"venue"
},
  "geometry": {"coordinates":[-1.7496700287,52.5489311218],"type":"Point"}
}