{
  "type": "Feature",
  "properties": {
    "addr:full":"10 Hempitts Road, Walton Street Somerset BA16 9QS",
    "addr:housenumber":"10",
    "addr:postcode":"ba16 9qs",
    "addr:street":"Hempitts Road Walton Street",
    "iso:country":"GB",
    "sg:address":"10 Hempitts Road, Walton",
    "sg:city":"Street",
    "sg:classifiers":[
        {
            "category":"Building & Trades",
            "subcategory":"Construction",
            "type":"Services"
        }
    ],
    "sg:postcode":"BA16 9QS",
    "sg:province":"Somerset",
    "sg:tags":[
        "joiner",
        "carpenter"
    ],
    "wof:name":"Willcox Carpentry & Joinery",
    "wof:placetype":"venue"
},
  "geometry": {"coordinates":[-2.7598390579,51.1241531372],"type":"Point"}
}