{
  "type": "Feature",
  "properties": {
    "iso:country":"GB",
    "sg:address":"10 Cavendish Circus",
    "sg:city":"Buxton",
    "sg:classifiers":[
        {
            "category":"Professional",
            "subcategory":"Art Services",
            "type":"Services"
        }
    ],
    "sg:postcode":"SK17 6AT",
    "sg:province":"Derbyshire",
    "sg:tags":[
        "framing"
    ],
    "wof:name":"Peak Gallery",
    "wof:placetype":"venue"
},
  "geometry": {"coordinates":[-1.914773941,53.2597312927],"type":"Point"}
}