{
  "type": "Feature",
  "properties": {
    "addr:full":"Crengate Industrial Estate Crewe Cheshire CW1 6YY",
    "addr:postcode":"cw1 6yy",
    "addr:street":"Crengate Industrial Estate",
    "iso:country":"GB",
    "sg:address":"Crengate Industrial Estate",
    "sg:city":"Crewe",
    "sg:classifiers":[
        {
            "category":"Autos & Motor Vehicles",
            "subcategory":"Automobile Sales",
            "type":"Retail Goods"
        },
        {
            "category":"Autos & Motor Vehicles",
            "subcategory":"Recreational Vehicle Sales",
            "type":"Retail Goods"
        }
    ],
    "sg:phone":"+44 1270 587711",
    "sg:postcode":"CW1 6YY",
    "sg:province":"Cheshire",
    "sg:tags":[
        "car",
        "used",
        "new"
    ],
    "sg:website":"http://www.gateway-peugeot.com",
    "wof:name":"Gateway Motor Co Ltd",
    "wof:placetype":"venue"
},
  "geometry": {"coordinates":[-2.4294440746,53.0880203247],"type":"Point"}
}