{
  "type": "Feature",
  "properties": {
    "iso:country":"GB",
    "sg:address":"17 Greenhill Business Centre, Coltswood Rd",
    "sg:city":"Coatbridge",
    "sg:classifiers":[
        {
            "category":"Professional",
            "subcategory":"Engineering",
            "type":"Services"
        }
    ],
    "sg:phone":"+44 1236 426000",
    "sg:postcode":"ML5 2AB",
    "sg:province":"North Lanarkshire",
    "sg:tags":[
        "consulting",
        "engineer"
    ],
    "wof:name":"Akem Ltd",
    "wof:placetype":"venue"
},
  "geometry": {"coordinates":[-4.036569,55.907612],"type":"Point"}
}