{
  "type": "Feature",
  "properties": {
    "addr:full":"7 Harold St, Smallthorne Stoke On Trent Staffordshire ST6 1SJ",
    "addr:housenumber":"7",
    "addr:postcode":"st6 1sj",
    "addr:street":"Harold St",
    "iso:country":"GB",
    "sg:address":"7 Harold St, Smallthorne",
    "sg:city":"Stoke On Trent",
    "sg:classifiers":[
        {
            "category":"Manufacturing",
            "subcategory":"Petroleum Products",
            "type":"Manufacturing & Wholesale Goods"
        }
    ],
    "sg:phone":"+44 1782 577394",
    "sg:postcode":"ST6 1SJ",
    "sg:province":"Staffordshire",
    "sg:tags":[
        "double",
        "glazing"
    ],
    "wof:name":"Smallthorne Glass & Joinery",
    "wof:placetype":"venue"
},
  "geometry": {"coordinates":[-2.174716,53.048012],"type":"Point"}
}