{
  "type": "Feature",
  "properties": {
    "iso:country":"GB",
    "sg:address":"33 Chadbury Rd",
    "sg:city":"Halesowen",
    "sg:classifiers":[
        {
            "category":"Building & Trades",
            "subcategory":"Construction",
            "type":"Services"
        }
    ],
    "sg:phone":"+44 121 550 3815",
    "sg:postcode":"B63 3HB",
    "sg:province":"West Midlands",
    "sg:tags":[
        "decorator",
        "painter"
    ],
    "wof:name":"J.A Rowe",
    "wof:placetype":"venue"
},
  "geometry": {"coordinates":[-2.041223,52.445957],"type":"Point"}
}