{
  "type": "Feature",
  "properties": {
    "addr:full":"St Richards Parsonage, Forge La Feltham Greater London TW13 6UN",
    "addr:postcode":"tw13 6un",
    "addr:street":"St;Parsonage Forge La Feltham",
    "iso:country":"GB",
    "sg:address":"St Richards Parsonage, Forge La",
    "sg:city":"Feltham",
    "sg:classifiers":[
        {
            "category":"Place Of Worship",
            "type":"Public Place"
        }
    ],
    "sg:phone":"+44 20 8898 0241",
    "sg:postcode":"TW13 6UN",
    "sg:province":"Greater London",
    "wof:name":"St Richard Of Chichester C Of E Church",
    "wof:placetype":"venue"
},
  "geometry": {"coordinates":[-0.4092040062,51.4470748901],"type":"Point"}
}