{
  "type": "Feature",
  "properties": {
    "addr:full":"190 Queensway Milton Keynes Buckinghamshire MK2 2ST",
    "addr:housenumber":"190",
    "addr:postcode":"mk2 2st",
    "addr:street":"Queensway",
    "iso:country":"GB",
    "sg:address":"190 Queensway",
    "sg:city":"Milton Keynes",
    "sg:classifiers":[
        {
            "category":"Real Estate",
            "subcategory":"Real Estate Agent",
            "type":"Services"
        }
    ],
    "sg:phone":"+44 1908 648666",
    "sg:postcode":"MK2 2ST",
    "sg:province":"Buckinghamshire",
    "wof:name":"Halifax Property Services",
    "wof:placetype":"venue"
},
  "geometry": {"coordinates":[-0.7270519733,51.9952392578],"type":"Point"}
}