{
  "type": "Feature",
  "properties": {
    "iso:country":"GB",
    "sg:address":"Granite Way",
    "sg:city":"Loughborough",
    "sg:classifiers":[
        {
            "category":"Retail",
            "subcategory":"Auto Rental",
            "type":"Services"
        }
    ],
    "sg:phone":"+44 1509 413487",
    "sg:postcode":"LE12 7TZ",
    "sg:province":"Leicestershire",
    "sg:tags":[
        "car"
    ],
    "wof:name":"T L S Vehicle Rental",
    "wof:placetype":"venue"
},
  "geometry": {"coordinates":[-1.145444,52.740341],"type":"Point"}
}