{
  "type": "Feature",
  "properties": {
    "iso:country":"GB",
    "sg:address":"16 Hazelmead",
    "sg:city":"Liskeard",
    "sg:classifiers":[
        {
            "category":"Banks & Credit Unions",
            "subcategory":"Financial Services",
            "type":"Services"
        }
    ],
    "sg:postcode":"PL14 4PY",
    "sg:province":"Cornwall",
    "sg:tags":[
        "adviser"
    ],
    "wof:name":"Barclay Chapman & Co",
    "wof:placetype":"venue"
},
  "geometry": {"coordinates":[-4.470991,50.450031],"type":"Point"}
}