{
  "type": "Feature",
  "properties": {
    "addr:full":"37 Peacocks Close, Cavendish Sudbury Essex CO10 8DA",
    "addr:housenumber":"37",
    "addr:postcode":"co10 8da",
    "addr:street":"Peacocks Close",
    "iso:country":"GB",
    "sg:address":"37 Peacocks Close, Cavendish",
    "sg:city":"Sudbury",
    "sg:classifiers":[
        {
            "category":"Social Services",
            "subcategory":"Job Training",
            "type":"Services"
        }
    ],
    "sg:postcode":"CO10 8DA",
    "sg:province":"Essex",
    "sg:tags":[
        "draughtsman",
        "drawing"
    ],
    "wof:name":"David Farley Engineering Design",
    "wof:placetype":"venue"
},
  "geometry": {"coordinates":[0.628562,52.09063],"type":"Point"}
}