{
  "type": "Feature",
  "properties": {
    "addr:full":"1 Beechengrove Pinner Greater London HA5 3AH",
    "addr:housenumber":"1",
    "addr:postcode":"ha5 3ah",
    "addr:street":"Beechengrove",
    "iso:country":"GB",
    "sg:address":"1 Beechengrove",
    "sg:city":"Pinner",
    "sg:classifiers":[
        {
            "category":"Health Services",
            "subcategory":"Health Practitioner",
            "type":"Services"
        }
    ],
    "sg:phone":"+44 20 8677 5329",
    "sg:postcode":"HA5 3AH",
    "sg:province":"Greater London",
    "sg:tags":[
        "physiotherapist"
    ],
    "wof:name":"J C Simmons",
    "wof:placetype":"venue"
},
  "geometry": {"coordinates":[-0.375659,51.594753],"type":"Point"}
}