{
  "type": "Feature",
  "properties": {
    "addr:full":"10 The Manor Godalming Surrey GU8 5JL",
    "addr:housenumber":"10",
    "addr:postcode":"gu8 5jl",
    "addr:street":"The Manor Godalming",
    "iso:country":"GB",
    "sg:address":"10 The Manor",
    "sg:city":"Godalming",
    "sg:classifiers":[
        {
            "category":"Retail",
            "subcategory":"Repair Shop",
            "type":"Services"
        }
    ],
    "sg:phone":"+44 1483 416982",
    "sg:postcode":"GU8 5JL",
    "sg:province":"Surrey",
    "sg:tags":[
        "furniture"
    ],
    "wof:name":"Milford J Osgood",
    "wof:placetype":"venue"
},
  "geometry": {"coordinates":[-0.6485649943,51.1710357666],"type":"Point"}
}