{
  "type": "Feature",
  "properties": {
    "iso:country":"GB",
    "sg:address":"65 Main Street",
    "sg:city":"Egremont",
    "sg:classifiers":[
        {
            "category":"Fast Food",
            "type":"Food & Drink"
        }
    ],
    "sg:phone":"+44 1946 820851",
    "sg:postcode":"CA22 2DB",
    "sg:province":"Cumbria",
    "sg:tags":[
        "away",
        "meal",
        "outlet",
        "take"
    ],
    "wof:name":"Wonder Kitchen",
    "wof:placetype":"venue"
},
  "geometry": {"coordinates":[-3.5285310745,54.4830322266],"type":"Point"}
}