{
  "type": "Feature",
  "properties": {
    "addr:full":"Tuition House, 27-37 St Georges Road London Greater London SW19 4EU",
    "addr:housenumber":"27-37",
    "addr:postcode":"sw19 4eu",
    "addr:street":"St Georges Road",
    "iso:country":"GB",
    "sg:address":"Tuition House, 27-37 St Georges Road",
    "sg:city":"London",
    "sg:classifiers":[
        {
            "category":"Real Estate",
            "subcategory":"Real Estate Operator",
            "type":"Services"
        }
    ],
    "sg:phone":"+44 20 8971 7600",
    "sg:postcode":"SW19 4EU",
    "sg:province":"Greater London",
    "sg:tags":[
        "letting",
        "agent"
    ],
    "wof:name":"Cotton Thompson Cole Chartered Surveyors",
    "wof:placetype":"venue"
},
  "geometry": {"coordinates":[-0.209221,51.420193],"type":"Point"}
}