{
  "type": "Feature",
  "properties": {
    "iso:country":"GB",
    "sg:address":"The Medical Centre, Vicarage Rd",
    "sg:city":"Derby",
    "sg:classifiers":[
        {
            "category":"Health Services",
            "subcategory":"Doctor",
            "type":"Services"
        }
    ],
    "sg:phone":"+44 1332 513283",
    "sg:postcode":"DE3 5EB",
    "sg:province":"Derbyshire",
    "sg:tags":[
        "practitioners"
    ],
    "wof:name":"Keeling, C",
    "wof:placetype":"venue"
},
  "geometry": {"coordinates":[-1.5503900051,52.9061088562],"type":"Point"}
}