{
  "type": "Feature",
  "properties": {
    "addr:full":"Horsedown, Littleton Drew Chippenham Gloucestershire SN14 7LN",
    "addr:postcode":"sn14 7ln",
    "addr:street":"Drew",
    "iso:country":"GB",
    "sg:address":"Horsedown, Littleton Drew",
    "sg:city":"Chippenham",
    "sg:classifiers":[
        {
            "category":"Transit Center",
            "subcategory":"Passenger",
            "type":"Transportation"
        }
    ],
    "sg:postcode":"SN14 7LN",
    "sg:province":"Gloucestershire",
    "sg:tags":[
        "boarding",
        "kennel",
        "catteries"
    ],
    "wof:name":"Horsedown Boarding Kennels",
    "wof:placetype":"venue"
},
  "geometry": {"coordinates":[-2.2454409599,51.521736145],"type":"Point"}
}