{
  "type": "Feature",
  "properties": {
    "addr:full":"Four Ashes Road Solihull Warwickshire B93 8NQ",
    "addr:postcode":"b93 8nq",
    "addr:street":"Ashes Road",
    "iso:country":"GB",
    "sg:address":"Four Ashes Road",
    "sg:city":"Solihull",
    "sg:classifiers":[
        {
            "category":"Sports & Exercise",
            "subcategory":"Golf",
            "type":"Entertainment"
        }
    ],
    "sg:phone":"+44 1564 778072",
    "sg:postcode":"B93 8NQ",
    "sg:province":"Warwickshire",
    "sg:tags":[
        "range",
        "driving"
    ],
    "wof:name":"Terry Matthews Golf Shops Ltd.",
    "wof:placetype":"venue"
},
  "geometry": {"coordinates":[-1.7646930218,52.3784980774],"type":"Point"}
}