{
  "type": "Feature",
  "properties": {
    "addr:full":"112-114 London Road Portsmouth Hampshire PO2 0LZ",
    "addr:housenumber":"112-114",
    "addr:postcode":"hampshire po2 0lz",
    "addr:street":"London Road",
    "iso:country":"GB",
    "sg:address":"112-114 London Road",
    "sg:city":"Portsmouth",
    "sg:classifiers":[
        {
            "category":"Real Estate",
            "subcategory":"Real Estate Agent",
            "type":"Services"
        }
    ],
    "sg:phone":"+44 23 9266 4096",
    "sg:postcode":"PO2 0LZ",
    "sg:province":"Hampshire",
    "wof:name":"Jeffries & Partners Ltd.",
    "wof:placetype":"venue"
},
  "geometry": {"coordinates":[-1.079404,50.81678],"type":"Point"}
}