{
  "type": "Feature",
  "properties": {
    "iso:country":"GB",
    "sg:address":"30 Littledean, Yate",
    "sg:city":"Bristol",
    "sg:classifiers":[
        {
            "category":"Arts & Performance",
            "subcategory":"Music",
            "type":"Entertainment"
        }
    ],
    "sg:postcode":"BS37 8UL",
    "sg:province":"Gloucestershire",
    "sg:tags":[
        "mobile",
        "disco"
    ],
    "wof:name":"Capricorn Disco",
    "wof:placetype":"venue"
},
  "geometry": {"coordinates":[-2.434194088,51.516834259],"type":"Point"}
}