{
  "type": "Feature",
  "properties": {
    "addr:full":"9 Clinton Hill, Dormansland Lingfield Surrey RH7 6QD",
    "addr:housenumber":"9",
    "addr:postcode":"rh7 6qd",
    "addr:street":"Clinton",
    "iso:country":"GB",
    "sg:address":"9 Clinton Hill, Dormansland",
    "sg:city":"Lingfield",
    "sg:classifiers":[
        {
            "category":"Professional",
            "subcategory":"Engineering",
            "type":"Services"
        }
    ],
    "sg:phone":"+44 1342 833496",
    "sg:postcode":"RH7 6QD",
    "sg:province":"Surrey",
    "sg:tags":[
        "contractor",
        "electrical",
        "engineer"
    ],
    "wof:name":"Hellier & Co.",
    "wof:placetype":"venue"
},
  "geometry": {"coordinates":[0.0071350001,51.1598548889],"type":"Point"}
}