{
  "type": "Feature",
  "properties": {
    "addr:full":"13 The Quadrant, Marshals Wick St Albans Hertfordshire AL4 9RB",
    "addr:housenumber":"13",
    "addr:postcode":"al4 9rb",
    "addr:street":"The Quadrant;Wick",
    "iso:country":"GB",
    "sg:address":"13 The Quadrant, Marshals Wick",
    "sg:city":"St Albans",
    "sg:classifiers":[
        {
            "category":"Shopping",
            "subcategory":"Gifts & Souvenirs",
            "type":"Retail Goods"
        }
    ],
    "sg:phone":"+44 1727 760760",
    "sg:postcode":"AL4 9RB",
    "sg:province":"Hertfordshire",
    "sg:tags":[
        "shop",
        "poster",
        "card"
    ],
    "wof:name":"Quadrant Cards Ltd",
    "wof:placetype":"venue"
},
  "geometry": {"coordinates":[-0.30784,51.764511],"type":"Point"}
}