{
  "type": "Feature",
  "properties": {
    "iso:country":"GB",
    "sg:address":"Cooks Lane, Milton Regis",
    "sg:city":"Sittingbourne",
    "sg:classifiers":[
        {
            "category":"Manufacturing",
            "subcategory":"Building Materials",
            "type":"Manufacturing & Wholesale Goods"
        }
    ],
    "sg:phone":"+44 1795 425191",
    "sg:postcode":"ME10 2QF",
    "sg:province":"Kent",
    "sg:tags":[
        "concrete",
        "product"
    ],
    "wof:name":"Milton Pipes Ltd",
    "wof:placetype":"venue"
},
  "geometry": {"coordinates":[0.7340580225,51.349937439],"type":"Point"}
}