{
  "type": "Feature",
  "properties": {
    "addr:full":"94 South Street Bishops Stortford Essex CM23 3BG",
    "addr:housenumber":"94",
    "addr:postcode":"cm23 3bg",
    "addr:street":"South Street",
    "iso:country":"GB",
    "sg:address":"94 South Street",
    "sg:city":"Bishops Stortford",
    "sg:classifiers":[
        {
            "category":"Arts & Performance",
            "subcategory":"Art Gallery",
            "type":"Entertainment"
        }
    ],
    "sg:postcode":"CM23 3BG",
    "sg:province":"Essex",
    "wof:name":"Visual Impression",
    "wof:placetype":"venue"
},
  "geometry": {"coordinates":[0.1605319977,51.8671379089],"type":"Point"}
}