{
  "type": "Feature",
  "properties": {
    "iso:country":"GB",
    "sg:address":"22 Manchester Rd",
    "sg:city":"Heywood",
    "sg:classifiers":[
        {
            "category":"Bars & Pubs",
            "type":"Food & Drink"
        }
    ],
    "sg:postcode":"OL10 2AH",
    "sg:province":"Lancashire",
    "sg:tags":[
        "pubs",
        "inn"
    ],
    "wof:name":"Joseph Holt Ltd",
    "wof:placetype":"venue"
},
  "geometry": {"coordinates":[-2.2107670307,53.5880889893],"type":"Point"}
}