{
  "type": "Feature",
  "properties": {
    "iso:country":"GB",
    "sg:address":"St.richards House, Victoria Square",
    "sg:city":"Droitwich",
    "sg:classifiers":[
        {
            "category":"Government",
            "subcategory":"Office",
            "type":"Public Place"
        }
    ],
    "sg:phone":"+44 1905 774258",
    "sg:postcode":"WR9 8DS",
    "sg:province":"Worcestershire",
    "sg:tags":[
        "local"
    ],
    "wof:name":"Droitwich Spa Town Council",
    "wof:placetype":"venue"
},
  "geometry": {"coordinates":[-2.150446,52.266949],"type":"Point"}
}