{
  "type": "Feature",
  "properties": {
    "addr:full":"17a Queensferry St Edinburgh City of Edinburgh EH2 4QW",
    "addr:housenumber":"17a",
    "addr:postcode":"eh2 4qw",
    "addr:street":"Queensferry St Edinburgh",
    "iso:country":"GB",
    "sg:address":"17a Queensferry St",
    "sg:city":"Edinburgh",
    "sg:classifiers":[
        {
            "category":"Fast Food",
            "type":"Food & Drink"
        }
    ],
    "sg:phone":"+44 131 225 3329",
    "sg:postcode":"EH2 4QW",
    "sg:province":"City of Edinburgh",
    "sg:tags":[
        "away",
        "take"
    ],
    "wof:name":"Simons Express",
    "wof:placetype":"venue"
},
  "geometry": {"coordinates":[-3.2096970081,55.9494895935],"type":"Point"}
}