{
  "type": "Feature",
  "properties": {
    "addr:full":"Ottinge Court Farm, Elham Canterbury Kent CT4 6XH",
    "addr:housenumber":"elham",
    "addr:postcode":"ct4 6xh",
    "addr:street":"Canterbury",
    "iso:country":"GB",
    "sg:address":"Ottinge Court Farm, Elham",
    "sg:city":"Canterbury",
    "sg:classifiers":[
        {
            "category":"Farming",
            "subcategory":"Livestock Farm",
            "type":"Manufacturing & Wholesale Goods"
        }
    ],
    "sg:phone":"+44 1303 862449",
    "sg:postcode":"CT4 6XH",
    "sg:province":"Kent",
    "sg:tags":[
        "others"
    ],
    "wof:name":"J D R Wilsom (W S) Farms",
    "wof:placetype":"venue"
},
  "geometry": {"coordinates":[1.104695,51.165668],"type":"Point"}
}