{
  "type": "Feature",
  "properties": {
    "addr:full":"36 Langford Road Stoke-on-trent Staffordshire ST2 9HA",
    "addr:housenumber":"36",
    "addr:postcode":"st2 9ha",
    "addr:street":"Langford Road",
    "iso:country":"GB",
    "sg:address":"36 Langford Road",
    "sg:city":"Stoke-on-trent",
    "sg:classifiers":[
        {
            "category":"Retail",
            "subcategory":"Driving School",
            "type":"Services"
        }
    ],
    "sg:phone":"+44 1782 205937",
    "sg:postcode":"ST2 9HA",
    "sg:province":"Staffordshire",
    "wof:name":"Jeff Barber School of Motoring",
    "wof:placetype":"venue"
},
  "geometry": {"coordinates":[-2.1346240044,53.023891449],"type":"Point"}
}