{
  "type": "Feature",
  "properties": {
    "addr:full":"The Mannor, Stoke D'abernon Cobham Surrey KT11 3PX",
    "addr:postcode":"kt11 3px",
    "iso:country":"GB",
    "sg:address":"The Mannor, Stoke D'abernon",
    "sg:city":"Cobham",
    "sg:classifiers":[
        {
            "category":"Education",
            "subcategory":"School",
            "type":"Public Place"
        }
    ],
    "sg:phone":"+44 1932 862749",
    "sg:postcode":"KT11 3PX",
    "sg:province":"Surrey",
    "sg:tags":[
        "independent",
        "preparatory"
    ],
    "wof:name":"Parkside School Trust",
    "wof:placetype":"venue"
},
  "geometry": {"coordinates":[-0.3796800077,51.3152694702],"type":"Point"}
}