{
  "type": "Feature",
  "properties": {
    "addr:full":"4a Market Square Sandy Bedfordshire SG19 1HU",
    "addr:housenumber":"4a",
    "addr:postcode":"sg19 1hu",
    "addr:street":"Market Square",
    "iso:country":"GB",
    "sg:address":"4a Market Square",
    "sg:city":"Sandy",
    "sg:classifiers":[
        {
            "category":"Food & Beverages",
            "subcategory":"Meat & Fish",
            "type":"Retail Goods"
        }
    ],
    "sg:phone":"+44 1767 683303",
    "sg:postcode":"SG19 1HU",
    "sg:province":"Bedfordshire",
    "sg:tags":[
        "chip"
    ],
    "wof:name":"The Chippy",
    "wof:placetype":"venue"
},
  "geometry": {"coordinates":[-0.2870410085,52.1293373108],"type":"Point"}
}