{
  "type": "Feature",
  "properties": {
    "addr:full":"413 St Leonards Rd Windsor Berkshire SL4 3DT",
    "addr:housenumber":"413",
    "addr:postcode":"sl4 3dt",
    "addr:street":"St Leonards Rd",
    "iso:country":"GB",
    "sg:address":"413 St Leonards Rd",
    "sg:city":"Windsor",
    "sg:classifiers":[
        {
            "category":"Utilities",
            "type":"Services"
        }
    ],
    "sg:phone":"+44 1753 831139",
    "sg:postcode":"SL4 3DT",
    "sg:province":"Berkshire",
    "sg:tags":[
        "internet"
    ],
    "wof:name":"Lextra Communications",
    "wof:placetype":"venue"
},
  "geometry": {"coordinates":[-0.6253889799,51.4714698792],"type":"Point"}
}