{
  "type": "Feature",
  "properties": {
    "addr:full":"125-126 New Street Birmingham West Midlands B2 4JH",
    "addr:housenumber":"125-126",
    "addr:postcode":"b2 4jh",
    "addr:street":"New Street",
    "iso:country":"GB",
    "sg:address":"125-126 New Street",
    "sg:city":"Birmingham",
    "sg:classifiers":[
        {
            "category":"Shopping",
            "subcategory":"Clothing, Apparel, & Fashions",
            "type":"Retail Goods"
        }
    ],
    "sg:phone":"+44 121 643 2770",
    "sg:postcode":"B2 4JH",
    "sg:province":"West Midlands",
    "sg:tags":[
        "lady",
        "fashionwear",
        "ladieswear"
    ],
    "wof:name":"Oasis Stores Ltd",
    "wof:placetype":"venue"
},
  "geometry": {"coordinates":[-1.8990670443,52.4791221619],"type":"Point"}
}