{
  "type": "Feature",
  "properties": {
    "iso:country":"GB",
    "sg:address":"Home Farm, Little Wyrley",
    "sg:city":"Walsall",
    "sg:classifiers":[
        {
            "category":"Farming",
            "subcategory":"Farm",
            "type":"Manufacturing & Wholesale Goods"
        }
    ],
    "sg:phone":"+44 1922 691285",
    "sg:postcode":"WS3 5AQ",
    "sg:province":"Staffordshire",
    "sg:tags":[
        "mixed",
        "crop"
    ],
    "wof:name":"E J Benton & Sons",
    "wof:placetype":"venue"
},
  "geometry": {"coordinates":[-1.9660240412,52.6374206543],"type":"Point"}
}