{
  "type": "Feature",
  "properties": {
    "iso:country":"GB",
    "sg:address":"Rushden Road",
    "sg:city":"Bedford",
    "sg:classifiers":[
        {
            "category":"Home & Garden",
            "subcategory":"Garden Supply",
            "type":"Retail Goods"
        }
    ],
    "sg:postcode":"MK44 1ND",
    "sg:province":"Bedfordshire",
    "sg:tags":[
        "nursery",
        "centre"
    ],
    "wof:name":"Ivy Lodge Nurseries",
    "wof:placetype":"venue"
},
  "geometry": {"coordinates":[-0.51368,52.194923],"type":"Point"}
}