{
  "type": "Feature",
  "properties": {
    "addr:full":"33 Violet Avenue, Edlington Doncaster South Yorkshire DN12 1NP",
    "addr:housenumber":"33",
    "addr:postcode":"dn12 1np",
    "addr:street":"Violet Avenue",
    "iso:country":"GB",
    "sg:address":"33 Violet Avenue, Edlington",
    "sg:city":"Doncaster",
    "sg:classifiers":[
        {
            "category":"Government",
            "subcategory":"Post Office",
            "type":"Public Place"
        }
    ],
    "sg:phone":"+44 1709 864186",
    "sg:postcode":"DN12 1NP",
    "sg:province":"South Yorkshire",
    "wof:name":"Hill Top P.O",
    "wof:placetype":"venue"
},
  "geometry": {"coordinates":[-1.1900689602,53.4820899963],"type":"Point"}
}