{
  "type": "Feature",
  "properties": {
    "addr:full":"Cottage, 35a, Elveden Thetford Norfolk IP24 3TJ",
    "addr:housenumber":"35a",
    "addr:postcode":"ip24 3tj",
    "addr:street":"Cottage",
    "iso:country":"GB",
    "sg:address":"Cottage, 35a, Elveden",
    "sg:city":"Thetford",
    "sg:classifiers":[
        {
            "category":"Organizations",
            "subcategory":"Non-profit Organization",
            "type":"Services"
        }
    ],
    "sg:phone":"+44 1842 890226",
    "sg:postcode":"IP24 3TJ",
    "sg:province":"Norfolk",
    "sg:tags":[
        "charitable",
        "organisation",
        "voluntary",
        "charity"
    ],
    "wof:name":"The Cancer Research Campaign",
    "wof:placetype":"venue"
},
  "geometry": {"coordinates":[0.72552,52.4053],"type":"Point"}
}