{
  "type": "Feature",
  "properties": {
    "addr:full":"15 Springwood Ave, West Bowling Bradford West Yorkshire BD5 8BY",
    "addr:housenumber":"15",
    "addr:postcode":"bd5 8by",
    "addr:street":"Springwood Ave",
    "iso:country":"GB",
    "sg:address":"15 Springwood Ave, West Bowling",
    "sg:city":"Bradford",
    "sg:classifiers":[
        {
            "category":"Professional",
            "subcategory":"Engineering",
            "type":"Services"
        }
    ],
    "sg:postcode":"BD5 8BY",
    "sg:province":"West Yorkshire",
    "sg:tags":[
        "contractor",
        "electrical",
        "engineer"
    ],
    "wof:name":"Smith,Mike,",
    "wof:placetype":"venue"
},
  "geometry": {"coordinates":[-1.7468819618,53.7760887146],"type":"Point"}
}