{
  "type": "Feature",
  "properties": {
    "iso:country":"GB",
    "sg:address":"Halton Lodge Avenue",
    "sg:city":"Runcorn",
    "sg:classifiers":[
        {
            "category":"Travel",
            "subcategory":"Hostel",
            "type":"Entertainment"
        }
    ],
    "sg:phone":"+44 1928 591680",
    "sg:postcode":"WA7 5YQ",
    "sg:province":"Cheshire",
    "wof:name":"Halton Ymca Foyer",
    "wof:placetype":"venue"
},
  "geometry": {"coordinates":[-2.7090189457,53.3304214478],"type":"Point"}
}