{
  "type": "Feature",
  "properties": {
    "addr:full":"The Towers, Howdale Rd Downham Market Cambridgeshire PE38 9AF",
    "addr:postcode":"pe38 9af",
    "addr:street":"Howdale Rd",
    "iso:country":"GB",
    "sg:address":"The Towers, Howdale Rd",
    "sg:city":"Downham Market",
    "sg:classifiers":[
        {
            "category":"Health Services",
            "subcategory":"Doctor",
            "type":"Services"
        }
    ],
    "sg:phone":"+44 1366 383405",
    "sg:postcode":"PE38 9AF",
    "sg:province":"Cambridgeshire",
    "sg:tags":[
        "practitioners"
    ],
    "wof:name":"Sconce, J",
    "wof:placetype":"venue"
},
  "geometry": {"coordinates":[0.38107,52.601746],"type":"Point"}
}