{
  "type": "Feature",
  "properties": {
    "iso:country":"GB",
    "sg:address":"10 Redcar Lane, Coalville East",
    "sg:city":"Redcar",
    "sg:classifiers":[
        {
            "category":"Travel",
            "subcategory":"Travel Agent",
            "type":"Entertainment"
        }
    ],
    "sg:phone":"+44 1642 488211",
    "sg:postcode":"TS10 3JF",
    "sg:province":"North Yorkshire",
    "wof:name":"Thyme Travel Ltd.",
    "wof:placetype":"venue"
},
  "geometry": {"coordinates":[-1.0600559711,54.6169128418],"type":"Point"}
}