{
  "type": "Feature",
  "properties": {
    "addr:full":"191 Hagley Road, Old Swinford Stourbridge Staffordshire DY8 2JJ",
    "addr:housenumber":"191",
    "addr:postcode":"dy8 2jj",
    "addr:street":"Hagley Road Old",
    "iso:country":"GB",
    "sg:address":"191 Hagley Road, Old Swinford",
    "sg:city":"Stourbridge",
    "sg:classifiers":[
        {
            "category":"Professional",
            "subcategory":"Engineering",
            "type":"Services"
        }
    ],
    "sg:phone":"+44 1384 397531",
    "sg:postcode":"DY8 2JJ",
    "sg:province":"Staffordshire",
    "sg:tags":[
        "engineer"
    ],
    "wof:name":"Swinford Engineering Ltd",
    "wof:placetype":"venue"
},
  "geometry": {"coordinates":[-2.1399490833,52.4459648132],"type":"Point"}
}