{
  "type": "Feature",
  "properties": {
    "addr:full":"Mill Cottage, Colmworth Bedford Bedfordshire MK44 2NU",
    "addr:postcode":"mk44 2nu",
    "iso:country":"GB",
    "sg:address":"Mill Cottage, Colmworth",
    "sg:city":"Bedford",
    "sg:classifiers":[
        {
            "category":"Building & Trades",
            "subcategory":"Construction",
            "type":"Services"
        }
    ],
    "sg:phone":"+44 1234 376264",
    "sg:postcode":"MK44 2NU",
    "sg:province":"Bedfordshire",
    "sg:tags":[
        "demolition",
        "contractor"
    ],
    "wof:name":"Prigmore & Son",
    "wof:placetype":"venue"
},
  "geometry": {"coordinates":[-0.385804,52.211391],"type":"Point"}
}