{
  "type": "Feature",
  "properties": {
    "addr:full":"7 Gower St Bloomsbury Greater London WC1E 6HA",
    "addr:housenumber":"7",
    "addr:postcode":"wc1e 6ha",
    "addr:street":"Gower St",
    "iso:country":"GB",
    "sg:address":"7 Gower St",
    "sg:city":"Bloomsbury",
    "sg:classifiers":[
        {
            "category":"Professional",
            "subcategory":"Management & Consulting",
            "type":"Services"
        }
    ],
    "sg:phone":"+44 20 7323 4283",
    "sg:postcode":"WC1E 6HA",
    "sg:province":"Greater London",
    "sg:tags":[
        "consultant",
        "business"
    ],
    "wof:name":"University Consultants Ltd",
    "wof:placetype":"venue"
},
  "geometry": {"coordinates":[-0.130095,51.519886],"type":"Point"}
}