{
  "type": "Feature",
  "properties": {
    "iso:country":"GB",
    "sg:address":"Unit 5 Royal London Estate, 31-35 West Road",
    "sg:city":"London",
    "sg:classifiers":[
        {
            "category":"Shopping",
            "type":"Retail Goods"
        }
    ],
    "sg:phone":"+44 20 8885 8623",
    "sg:postcode":"N17 0XL",
    "sg:province":"Greater London",
    "sg:tags":[
        "part",
        "accessory"
    ],
    "wof:name":"Euro Paint",
    "wof:placetype":"venue"
},
  "geometry": {"coordinates":[-0.0568300001,51.606048584],"type":"Point"}
}