{
  "type": "Feature",
  "properties": {
    "addr:full":"Station Road Knighton Shropshire LD7 1DT",
    "addr:postcode":"ld7 1dt",
    "addr:street":"Station Road",
    "iso:country":"GB",
    "sg:address":"Station Road",
    "sg:city":"Knighton",
    "sg:classifiers":[
        {
            "category":"Professional",
            "subcategory":"Accounting & Tax Preparation",
            "type":"Services"
        }
    ],
    "sg:phone":"+44 1547 520172",
    "sg:postcode":"LD7 1DT",
    "sg:province":"Shropshire",
    "sg:tags":[
        "accountant"
    ],
    "wof:name":"Whittingham Riddell",
    "wof:placetype":"venue"
},
  "geometry": {"coordinates":[-3.046574,52.344345],"type":"Point"}
}