{
  "type": "Feature",
  "properties": {
    "iso:country":"GB",
    "sg:address":"Burlington House, Burlington Arcade, Eldon Streety",
    "sg:city":"Barnsley",
    "sg:classifiers":[
        {
            "category":"Travel",
            "subcategory":"Travel Agent",
            "type":"Entertainment"
        }
    ],
    "sg:phone":"+44 1226 293566",
    "sg:postcode":"S70 1SZ",
    "sg:province":"South Yorkshire",
    "wof:name":"Skills Of Nottingham",
    "wof:placetype":"venue"
},
  "geometry": {"coordinates":[-1.4799389839,53.5528106689],"type":"Point"}
}