{
  "type": "Feature",
  "properties": {
    "iso:country":"GB",
    "sg:address":"65 Kingsland Road",
    "sg:city":"Worthing",
    "sg:classifiers":[
        {
            "category":"Personal",
            "subcategory":"Beauty Salon",
            "type":"Services"
        }
    ],
    "sg:phone":"+44 1903 234663",
    "sg:postcode":"BN14 9ED",
    "sg:province":"West Sussex",
    "sg:tags":[
        "unisex",
        "hairdresser"
    ],
    "wof:name":"Protocol",
    "wof:placetype":"venue"
},
  "geometry": {"coordinates":[-0.368606,50.829281],"type":"Point"}
}