{
  "type": "Feature",
  "properties": {
    "addr:full":"1 Grand Parade, 459 Upper Richmond Road West London Greater London SW14 7PR",
    "addr:housenumber":"1;459",
    "addr:postcode":"sw14 7pr",
    "addr:street":"Grand Parade;Upper Richmond Road West",
    "iso:country":"GB",
    "sg:address":"1 Grand Parade, 459 Upper Richmond Road West",
    "sg:city":"London",
    "sg:classifiers":[
        {
            "category":"Bars & Pubs",
            "subcategory":"Wine Bar",
            "type":"Food & Drink"
        }
    ],
    "sg:phone":"+44 20 8876 3543",
    "sg:postcode":"SW14 7PR",
    "sg:province":"Greater London",
    "wof:name":"Leonardo Wine Bar",
    "wof:placetype":"venue"
},
  "geometry": {"coordinates":[-0.2710070014,51.4640197754],"type":"Point"}
}