{
  "type": "Feature",
  "properties": {
    "iso:country":"GB",
    "sg:address":"183 Lawley Middleway",
    "sg:city":"Birmingham",
    "sg:classifiers":[
        {
            "category":"Autos & Motor Vehicles",
            "subcategory":"Automobile Sales",
            "type":"Retail Goods"
        }
    ],
    "sg:postcode":"B4 7XT",
    "sg:province":"West Midlands",
    "sg:tags":[
        "car"
    ],
    "wof:name":"Downing,Clive,",
    "wof:placetype":"venue"
},
  "geometry": {"coordinates":[-1.881976,52.48558],"type":"Point"}
}