{
  "type": "Feature",
  "properties": {
    "iso:country":"GB",
    "sg:address":"3a Chapel St",
    "sg:city":"Stafford",
    "sg:classifiers":[
        {
            "category":"Organizations",
            "subcategory":"Non-profit Organization",
            "type":"Services"
        }
    ],
    "sg:phone":"+44 1785 244550",
    "sg:postcode":"ST16 2BX",
    "sg:province":"Staffordshire",
    "sg:tags":[
        "organisation",
        "voluntary",
        "charity"
    ],
    "wof:name":"Home-Start",
    "wof:placetype":"venue"
},
  "geometry": {"coordinates":[-2.119353056,52.8075065613],"type":"Point"}
}