{
  "type": "Feature",
  "properties": {
    "iso:country":"GB",
    "sg:address":"Mono Lodge, Bridge St, Golborne",
    "sg:city":"Warrington",
    "sg:classifiers":[
        {
            "category":"Shopping",
            "subcategory":"Computers & Home Electronics",
            "type":"Retail Goods"
        }
    ],
    "sg:postcode":"WA3 3QA",
    "sg:province":"Cheshire",
    "sg:tags":[
        "equipment",
        "video",
        "cctv"
    ],
    "wof:name":"Technomark Ltd",
    "wof:placetype":"venue"
},
  "geometry": {"coordinates":[-2.5968389511,53.4766998291],"type":"Point"}
}