{
  "type": "Feature",
  "properties": {
    "iso:country":"GB",
    "sg:address":"Stirches Mains Farm House",
    "sg:city":"Hawick",
    "sg:classifiers":[
        {
            "category":"Farming",
            "subcategory":"Farm",
            "type":"Manufacturing & Wholesale Goods"
        }
    ],
    "sg:phone":"+44 1450 372441",
    "sg:postcode":"TD9 7NR",
    "sg:province":"Cumbria",
    "sg:tags":[
        "mixed",
        "crop"
    ],
    "wof:name":"R & E Mercer",
    "wof:placetype":"venue"
},
  "geometry": {"coordinates":[-2.808159,55.424702],"type":"Point"}
}