{
  "type": "Feature",
  "properties": {
    "addr:full":"Lenacre Street, Eastwell Ashford Kent TN26 1JD",
    "addr:postcode":"tn26 1jd",
    "addr:street":"Lenacre Street",
    "iso:country":"GB",
    "sg:address":"Lenacre Street, Eastwell",
    "sg:city":"Ashford",
    "sg:classifiers":[
        {
            "category":"Building & Trades",
            "subcategory":"Construction",
            "type":"Services"
        }
    ],
    "sg:phone":"+44 1233 611566",
    "sg:postcode":"TN26 1JD",
    "sg:province":"Kent",
    "sg:tags":[
        "restoration",
        "refurbishment"
    ],
    "wof:name":"Principal Interiors",
    "wof:placetype":"venue"
},
  "geometry": {"coordinates":[0.8750349879,51.1806259155],"type":"Point"}
}