{
  "type": "Feature",
  "properties": {
    "addr:full":"4 Jasmine Close Calne Wiltshire SN11 0QN",
    "addr:housenumber":"4",
    "addr:postcode":"sn11 0qn",
    "addr:street":"Jasmine Close",
    "iso:country":"GB",
    "sg:address":"4 Jasmine Close",
    "sg:city":"Calne",
    "sg:classifiers":[
        {
            "category":"Manufacturing",
            "subcategory":"Glass & Minerals",
            "type":"Manufacturing & Wholesale Goods"
        }
    ],
    "sg:phone":"+44 1249 817489",
    "sg:postcode":"SN11 0QN",
    "sg:province":"Wiltshire",
    "sg:tags":[
        "stained",
        "designer"
    ],
    "wof:name":"Peter.J Berry",
    "wof:placetype":"venue"
},
  "geometry": {"coordinates":[-2.001477,51.432034],"type":"Point"}
}