{
  "type": "Feature",
  "properties": {
    "iso:country":"GB",
    "sg:address":"Willowbridge La",
    "sg:city":"Castleford",
    "sg:classifiers":[
        {
            "category":"Freight",
            "type":"Transportation"
        }
    ],
    "sg:phone":"+44 1977 553341",
    "sg:postcode":"WF10 5NN",
    "sg:province":"West Yorkshire",
    "sg:tags":[
        "haulage",
        "road"
    ],
    "wof:name":"BOC Interbrand",
    "wof:placetype":"venue"
},
  "geometry": {"coordinates":[-1.376674,53.718445],"type":"Point"}
}