{
  "type": "Feature",
  "properties": {
    "addr:full":"243-245 Broadway Bexleyheath Kent DA6 8DB",
    "addr:housenumber":"243-245",
    "addr:postcode":"da6 8db",
    "addr:street":"Broadway",
    "iso:country":"GB",
    "sg:address":"243-245 Broadway",
    "sg:city":"Bexleyheath",
    "sg:classifiers":[
        {
            "category":"Social Services",
            "type":"Services"
        }
    ],
    "sg:phone":"+44 20 8298 1071",
    "sg:postcode":"DA6 8DB",
    "sg:province":"Kent",
    "sg:tags":[
        "helplines"
    ],
    "wof:name":"Aids H I V Testing for Bexley",
    "wof:placetype":"venue"
},
  "geometry": {"coordinates":[0.1381749958,51.4574050903],"type":"Point"}
}