{
  "type": "Feature",
  "properties": {
    "addr:full":"139 Westbourne Street Hove East Sussex BN3 5FB",
    "addr:housenumber":"139",
    "addr:postcode":"bn3 5fb",
    "addr:street":"Westbourne Street",
    "iso:country":"GB",
    "sg:address":"139 Westbourne Street",
    "sg:city":"Hove",
    "sg:classifiers":[
        {
            "category":"Retail",
            "subcategory":"Auto Repair",
            "type":"Services"
        }
    ],
    "sg:phone":"+44 1273 773934",
    "sg:postcode":"BN3 5FB",
    "sg:province":"East Sussex",
    "sg:tags":[
        "body",
        "car"
    ],
    "wof:name":"P & N Watts",
    "wof:placetype":"venue"
},
  "geometry": {"coordinates":[-0.1809740067,50.8345489502],"type":"Point"}
}