{
  "type": "Feature",
  "properties": {
    "iso:country":"GB",
    "sg:address":"82 St Peters Road",
    "sg:city":"Great Yarmouth",
    "sg:classifiers":[
        {
            "category":"Professional",
            "subcategory":"Detective & Security Services",
            "type":"Services"
        },
        {
            "category":"Building & Trades",
            "subcategory":"Locksmith",
            "type":"Services"
        }
    ],
    "sg:phone":"+44 1493 331342",
    "sg:postcode":"NR30 3AY",
    "sg:province":"Norfolk",
    "wof:name":"Yarmouth Lock Co.",
    "wof:placetype":"venue"
},
  "geometry": {"coordinates":[1.732011,52.602539],"type":"Point"}
}