{
  "type": "Feature",
  "properties": {
    "iso:country":"GB",
    "sg:address":"Springkerse Road",
    "sg:city":"Stirling",
    "sg:classifiers":[
        {
            "category":"Autos & Motor Vehicles",
            "subcategory":"Auto Supplies",
            "type":"Retail Goods"
        }
    ],
    "sg:phone":"+44 1786 471418",
    "sg:postcode":"FK7 7SN",
    "sg:province":"Falkirk",
    "sg:tags":[
        "tyre"
    ],
    "wof:name":"Motorway Tyres & Accessories Ltd",
    "wof:placetype":"venue"
},
  "geometry": {"coordinates":[-3.922835,56.114044],"type":"Point"}
}