{
  "type": "Feature",
  "properties": {
    "iso:country":"GB",
    "sg:address":"37a Hairst Street",
    "sg:city":"Renfrew",
    "sg:classifiers":[
        {
            "category":"Retail",
            "subcategory":"Repair Shop",
            "type":"Services"
        }
    ],
    "sg:phone":"+44 141 886 3397",
    "sg:postcode":"PA4 8QU",
    "sg:province":"Renfrewshire",
    "sg:tags":[
        "upholstering",
        "upholsterer"
    ],
    "wof:name":"Duncan McGregor of Renfrew",
    "wof:placetype":"venue"
},
  "geometry": {"coordinates":[-4.3879709244,55.8782310486],"type":"Point"}
}