{
  "type": "Feature",
  "properties": {
    "addr:full":"Parkdale House, Northgate Street Devizes Wiltshire SN10 1DE",
    "addr:postcode":"sn10 1de",
    "addr:street":"Northgate Street",
    "iso:country":"GB",
    "sg:address":"Parkdale House, Northgate Street",
    "sg:city":"Devizes",
    "sg:classifiers":[
        {
            "category":"Professional",
            "subcategory":"Detective & Security Services",
            "type":"Services"
        }
    ],
    "sg:phone":"+44 1380 724236",
    "sg:postcode":"SN10 1DE",
    "sg:province":"Wiltshire",
    "sg:tags":[
        "equipment"
    ],
    "wof:name":"Fass (Security) Ltd.",
    "wof:placetype":"venue"
},
  "geometry": {"coordinates":[-1.999739,51.354038],"type":"Point"}
}