{
  "type": "Feature",
  "properties": {
    "addr:full":"21 Alston Drive, Bradwell Abbey Milton Keynes Buckinghamshire MK13 9HA",
    "addr:housenumber":"21",
    "addr:postcode":"mk13 9ha",
    "addr:street":"Alston Drive",
    "iso:country":"GB",
    "sg:address":"21 Alston Drive, Bradwell Abbey",
    "sg:city":"Milton Keynes",
    "sg:classifiers":[
        {
            "category":"Shopping",
            "subcategory":"Stationery & Office Supplies",
            "type":"Retail Goods"
        }
    ],
    "sg:phone":"+44 1908 221860",
    "sg:postcode":"MK13 9HA",
    "sg:province":"Buckinghamshire",
    "sg:tags":[
        "equipment",
        "school"
    ],
    "wof:name":"Beecroft & Partners",
    "wof:placetype":"venue"
},
  "geometry": {"coordinates":[-0.798677,52.047703],"type":"Point"}
}