{
  "type": "Feature",
  "properties": {
    "iso:country":"GB",
    "sg:address":"Dinsdale Cotts",
    "sg:city":"Sunderland",
    "sg:classifiers":[
        {
            "category":"Organizations",
            "subcategory":"Membership Organization",
            "type":"Services"
        }
    ],
    "sg:phone":"+44 191 521 3437",
    "sg:postcode":"SR2 0RL",
    "sg:province":"Tyne and Wear",
    "sg:tags":[
        "club"
    ],
    "wof:name":"Ryhope St.Patricks Catholic Club",
    "wof:placetype":"venue"
},
  "geometry": {"coordinates":[-1.3669639826,54.8694000244],"type":"Point"}
}