{
  "type": "Feature",
  "properties": {
    "iso:country":"GB",
    "sg:address":"Unit 4 Casting House",
    "sg:city":"Letchworth",
    "sg:classifiers":[
        {
            "category":"Retail",
            "subcategory":"Auto Repair",
            "type":"Services"
        }
    ],
    "sg:phone":"+44 1462 620456",
    "sg:postcode":"SG6 1HX",
    "sg:province":"Hertfordshire",
    "sg:tags":[
        "body",
        "car"
    ],
    "wof:name":"The Bumper Centre Ltd.",
    "wof:placetype":"venue"
},
  "geometry": {"coordinates":[-0.217949,51.984936],"type":"Point"}
}