{
  "type": "Feature",
  "properties": {
    "iso:country":"GB",
    "sg:address":"Omega Court, 350 Cemetery Road",
    "sg:city":"Sheffield",
    "sg:classifiers":[
        {
            "category":"Professional",
            "subcategory":"Accounting & Tax Preparation",
            "type":"Services"
        }
    ],
    "sg:phone":"+44 114 267 1172",
    "sg:postcode":"S11 8FT",
    "sg:province":"Derbyshire",
    "sg:tags":[
        "accountant"
    ],
    "wof:name":"B K R Haines Watts",
    "wof:placetype":"venue"
},
  "geometry": {"coordinates":[-1.488448,53.367832],"type":"Point"}
}