{
  "type": "Feature",
  "properties": {
    "iso:country":"GB",
    "sg:address":"New Road, Tintwistle",
    "sg:city":"Glossop",
    "sg:classifiers":[
        {
            "category":"Organizations",
            "subcategory":"Political Organization",
            "type":"Services"
        }
    ],
    "sg:phone":"+44 1457 852966",
    "sg:postcode":"SK13 1JN",
    "sg:province":"Derbyshire",
    "sg:tags":[
        "party"
    ],
    "wof:name":"Tintwistle Conservative Club",
    "wof:placetype":"venue"
},
  "geometry": {"coordinates":[-1.96867,53.472118],"type":"Point"}
}