{
  "type": "Feature",
  "properties": {
    "iso:country":"GB",
    "sg:address":"Yokesford Hill",
    "sg:city":"Romsey",
    "sg:classifiers":[
        {
            "category":"Building & Trades",
            "subcategory":"Equipment Rental",
            "type":"Services"
        }
    ],
    "sg:phone":"+44 1794 368395",
    "sg:postcode":"SO51 0ZB",
    "sg:province":"Hampshire",
    "sg:tags":[
        "plant",
        "machinery"
    ],
    "wof:name":"A Plant",
    "wof:placetype":"venue"
},
  "geometry": {"coordinates":[-1.502095,51.015972],"type":"Point"}
}