{
  "type": "Feature",
  "properties": {
    "addr:full":"Care Of Kwiksave Birkenhead Merseyside CH41 9BG",
    "addr:postcode":"ch41 9bg",
    "iso:country":"GB",
    "sg:address":"Care Of Kwiksave",
    "sg:city":"Birkenhead",
    "sg:classifiers":[
        {
            "category":"Food & Beverages",
            "subcategory":"Fruits & Vegetables",
            "type":"Retail Goods"
        }
    ],
    "sg:postcode":"CH41 9BG",
    "sg:province":"Merseyside",
    "sg:tags":[
        "greengrocer"
    ],
    "wof:name":"Kwik Fruit (Chester) Ltd",
    "wof:placetype":"venue"
},
  "geometry": {"coordinates":[-3.025489,53.392567],"type":"Point"}
}