{
  "type": "Feature",
  "properties": {
    "addr:full":"6 Langdale Rd Liverpool Merseyside L15 3LB",
    "addr:housenumber":"6",
    "addr:postcode":"l15 3lb",
    "addr:street":"Langdale Rd",
    "iso:country":"GB",
    "sg:address":"6 Langdale Rd",
    "sg:city":"Liverpool",
    "sg:classifiers":[
        {
            "category":"Building & Trades",
            "subcategory":"Landscaping Services",
            "type":"Services"
        }
    ],
    "sg:phone":"+44 151 733 2311",
    "sg:postcode":"L15 3LB",
    "sg:province":"Merseyside",
    "sg:tags":[
        "forestry",
        "tree"
    ],
    "wof:name":"Tree Health Care",
    "wof:placetype":"venue"
},
  "geometry": {"coordinates":[-2.9295239449,53.3904953003],"type":"Point"}
}