{
  "type": "Feature",
  "properties": {
    "addr:full":"Galileo Close, Newnham Industrial Estate, Plymton Plymouth Devon PL7 4JW",
    "addr:postcode":"pl7 4jw",
    "addr:street":"Galileo Close;Industrial;Plymton",
    "iso:country":"GB",
    "sg:address":"Galileo Close, Newnham Industrial Estate, Plymton",
    "sg:city":"Plymouth",
    "sg:classifiers":[
        {
            "category":"Manufacturing",
            "subcategory":"Petroleum Products",
            "type":"Manufacturing & Wholesale Goods"
        }
    ],
    "sg:phone":"+44 1752 340123",
    "sg:postcode":"PL7 4JW",
    "sg:province":"Devon",
    "sg:tags":[
        "double",
        "glazing"
    ],
    "wof:name":"Doors & Windows Ltd.",
    "wof:placetype":"venue"
},
  "geometry": {"coordinates":[-4.048794,50.393829],"type":"Point"}
}