{
  "type": "Feature",
  "properties": {
    "addr:full":"27 Belsize Lane London Greater London NW3 5AS",
    "addr:housenumber":"27",
    "addr:postcode":"nw3 5as",
    "addr:street":"Belsize Lane",
    "iso:country":"GB",
    "sg:address":"27 Belsize Lane",
    "sg:city":"London",
    "sg:classifiers":[
        {
            "category":"Real Estate",
            "subcategory":"Real Estate Agent",
            "type":"Services"
        }
    ],
    "sg:phone":"+44 20 7794 0005",
    "sg:postcode":"NW3 5AS",
    "sg:province":"Greater London",
    "wof:name":"Heywood Estate Agents",
    "wof:placetype":"venue"
},
  "geometry": {"coordinates":[-0.171125,51.549412],"type":"Point"}
}