{
  "type": "Feature",
  "properties": {
    "iso:country":"GB",
    "sg:address":"2 Beam St",
    "sg:city":"Nantwich",
    "sg:classifiers":[
        {
            "category":"Professional",
            "subcategory":"Business Services",
            "type":"Services"
        }
    ],
    "sg:phone":"+44 1270 611844",
    "sg:postcode":"CW5 5LL",
    "sg:province":"Cheshire",
    "sg:tags":[
        "bookmaker"
    ],
    "wof:name":"H Penk",
    "wof:placetype":"venue"
},
  "geometry": {"coordinates":[-2.5228409767,53.0681343079],"type":"Point"}
}