{
  "type": "Feature",
  "properties": {
    "iso:country":"GB",
    "sg:address":"27 Finchdean Road",
    "sg:city":"Havant",
    "sg:classifiers":[
        {
            "category":"Utilities",
            "subcategory":"Refuse",
            "type":"Services"
        }
    ],
    "sg:phone":"+44 23 9287 6124",
    "sg:postcode":"PO9 4AA",
    "sg:province":"Hampshire",
    "sg:tags":[
        "disposal",
        "waste"
    ],
    "wof:name":"Cheap Rates",
    "wof:placetype":"venue"
},
  "geometry": {"coordinates":[-0.997618,50.865238],"type":"Point"}
}