{
  "type": "Feature",
  "properties": {
    "addr:full":"Caird Street Hamilton South Lanarkshire ML3 0AL",
    "addr:postcode":"ml3 0al",
    "addr:street":"Caird Street",
    "iso:country":"GB",
    "sg:address":"Caird Street",
    "sg:city":"Hamilton",
    "sg:classifiers":[
        {
            "category":"Health Services",
            "subcategory":"Clinic",
            "type":"Services"
        }
    ],
    "sg:phone":"+44 1698 285828",
    "sg:postcode":"ML3 0AL",
    "sg:province":"South Lanarkshire",
    "sg:tags":[
        "nh"
    ],
    "wof:name":"Beckford Lodge Clinic",
    "wof:placetype":"venue"
},
  "geometry": {"coordinates":[-4.0507788658,55.7825431824],"type":"Point"}
}