{
  "type": "Feature",
  "properties": {
    "addr:full":"47a Wrecclesham Rd Farnham Surrey GU9 8TY",
    "addr:housenumber":"47a",
    "addr:postcode":"gu9 8ty",
    "addr:street":"Wrecclesham Rd",
    "iso:country":"GB",
    "sg:address":"47a Wrecclesham Rd",
    "sg:city":"Farnham",
    "sg:classifiers":[
        {
            "category":"Retail",
            "subcategory":"Auto Repair",
            "type":"Services"
        }
    ],
    "sg:phone":"+44 1252 710875",
    "sg:postcode":"GU9 8TY",
    "sg:province":"Surrey",
    "sg:tags":[
        "modification",
        "garage"
    ],
    "wof:name":"Auto Services",
    "wof:placetype":"venue"
},
  "geometry": {"coordinates":[-0.8166149855,51.2036590576],"type":"Point"}
}