{
  "type": "Feature",
  "properties": {
    "addr:full":"540 Allerton Rd, Allerton Bradford West Yorkshire BD15 8DA",
    "addr:housenumber":"540",
    "addr:postcode":"bd15 8da",
    "addr:street":"Allerton Rd",
    "iso:country":"GB",
    "sg:address":"540 Allerton Rd, Allerton",
    "sg:city":"Bradford",
    "sg:classifiers":[
        {
            "category":"Military Area",
            "subcategory":"Air Force Base",
            "type":"Public Place"
        }
    ],
    "sg:phone":"+44 1274 495555",
    "sg:postcode":"BD15 8DA",
    "sg:province":"West Yorkshire",
    "sg:tags":[
        "taxi",
        "hire",
        "private"
    ],
    "wof:name":"Angel Cars",
    "wof:placetype":"venue"
},
  "geometry": {"coordinates":[-1.8343939781,53.8059082031],"type":"Point"}
}