{
  "type": "Feature",
  "properties": {
    "addr:full":"35 Hawley Street Margate Kent CT9 1QA",
    "addr:housenumber":"35",
    "addr:postcode":"ct9 1qa",
    "addr:street":"Hawley Street",
    "iso:country":"GB",
    "sg:address":"35 Hawley Street",
    "sg:city":"Margate",
    "sg:classifiers":[
        {
            "category":"Organizations",
            "subcategory":"Non-profit Organization",
            "type":"Services"
        }
    ],
    "sg:phone":"+44 1843 292896",
    "sg:postcode":"CT9 1QA",
    "sg:province":"Kent",
    "sg:tags":[
        "organisation",
        "voluntary",
        "charity"
    ],
    "wof:name":"Salvation Army Care & Share Shop",
    "wof:placetype":"venue"
},
  "geometry": {"coordinates":[1.383243,51.389465],"type":"Point"}
}