{
  "type": "Feature",
  "properties": {
    "addr:full":"Trowse Norwich Norfolk NR14 8TL",
    "addr:postcode":"nr14 8tl",
    "addr:street":"Norwich",
    "iso:country":"GB",
    "sg:address":"Trowse",
    "sg:city":"Norwich",
    "sg:classifiers":[
        {
            "category":"Social Services",
            "subcategory":"Adult Care",
            "type":"Services"
        }
    ],
    "sg:phone":"+44 1603 623145",
    "sg:postcode":"NR14 8TL",
    "sg:province":"Norfolk",
    "sg:tags":[
        "housing",
        "sheltered"
    ],
    "wof:name":"Norfolk County Council",
    "wof:placetype":"venue"
},
  "geometry": {"coordinates":[1.3186399937,52.6110916138],"type":"Point"}
}