{
  "type": "Feature",
  "properties": {
    "addr:full":"1st Floor 27 The Crescent, King Street Leicester Leicestershire LE1 6RX",
    "addr:housenumber":"27",
    "addr:postcode":"le1 6rx",
    "addr:street":"The Crescent King Street",
    "iso:country":"GB",
    "sg:address":"1st Floor 27 The Crescent, King Street",
    "sg:city":"Leicester",
    "sg:classifiers":[
        {
            "category":"Manufacturing",
            "subcategory":"Food",
            "type":"Manufacturing & Wholesale Goods"
        }
    ],
    "sg:phone":"+44 1476 590141",
    "sg:postcode":"LE1 6RX",
    "sg:province":"Leicestershire",
    "sg:tags":[
        "technologist"
    ],
    "wof:name":"Romano Gatland Ltd.",
    "wof:placetype":"venue"
},
  "geometry": {"coordinates":[-1.131286025,52.6293487549],"type":"Point"}
}