{
  "type": "Feature",
  "properties": {
    "addr:full":"Chapel Lane, Withington Macclesfield Cheshire SK11 9LP",
    "addr:postcode":"sk11 9lp",
    "addr:street":"Chapel Lane",
    "iso:country":"GB",
    "sg:address":"Chapel Lane, Withington",
    "sg:city":"Macclesfield",
    "sg:classifiers":[
        {
            "category":"Retail",
            "subcategory":"Auto Repair",
            "type":"Services"
        }
    ],
    "sg:phone":"+44 1477 571447",
    "sg:postcode":"SK11 9LP",
    "sg:province":"Cheshire",
    "sg:tags":[
        "body",
        "car",
        "repairer"
    ],
    "wof:name":"G & J Leese",
    "wof:placetype":"venue"
},
  "geometry": {"coordinates":[-2.261146,53.238377],"type":"Point"}
}