{
  "type": "Feature",
  "properties": {
    "iso:country":"GB",
    "sg:address":"4 Hackwood Cotts, Hackwood Road",
    "sg:city":"Basingstoke",
    "sg:classifiers":[
        {
            "category":"Travel",
            "subcategory":"Hotels & Motels",
            "type":"Entertainment"
        }
    ],
    "sg:postcode":"RG21 3BA",
    "sg:province":"Hampshire",
    "sg:tags":[
        "house",
        "guest"
    ],
    "wof:name":"Gemini Guest House",
    "wof:placetype":"venue"
},
  "geometry": {"coordinates":[-1.083089,51.262444],"type":"Point"}
}