{
  "type": "Feature",
  "properties": {
    "addr:full":"386 West End Road Ruislip Greater London HA4 6QY",
    "addr:housenumber":"386",
    "addr:postcode":"ha4 6qy",
    "addr:street":"West End Road",
    "iso:country":"GB",
    "sg:address":"386 West End Road",
    "sg:city":"Ruislip",
    "sg:classifiers":[
        {
            "category":"Bars & Pubs",
            "type":"Food & Drink"
        }
    ],
    "sg:phone":"+44 20 8845 0893",
    "sg:postcode":"HA4 6QY",
    "sg:province":"Greater London",
    "sg:tags":[
        "pubs",
        "inn"
    ],
    "wof:name":"The Tally Ho",
    "wof:placetype":"venue"
},
  "geometry": {"coordinates":[-0.4015179873,51.5509033203],"type":"Point"}
}