{
  "type": "Feature",
  "properties": {
    "iso:country":"GB",
    "sg:address":"9 College Hill",
    "sg:city":"Shrewsbury",
    "sg:classifiers":[
        {
            "category":"Real Estate",
            "subcategory":"Real Estate Agent",
            "type":"Services"
        }
    ],
    "sg:phone":"+44 1743 242470",
    "sg:postcode":"SY1 1LZ",
    "sg:province":"Shropshire",
    "wof:name":"Marshall & Marshall Ltd.",
    "wof:placetype":"venue"
},
  "geometry": {"coordinates":[-2.754849,52.706635],"type":"Point"}
}