{
  "type": "Feature",
  "properties": {
    "addr:full":"Scotswood Road Newcastle-upon-tyne Tyne and Wear NE4 7NN",
    "addr:postcode":"ne4 7nn",
    "addr:street":"Scotswood Road",
    "iso:country":"GB",
    "sg:address":"Scotswood Road",
    "sg:city":"Newcastle-upon-tyne",
    "sg:classifiers":[
        {
            "category":"Autos & Motor Vehicles",
            "subcategory":"Fuel & Gas Station",
            "type":"Retail Goods"
        }
    ],
    "sg:phone":"+44 191 273 8945",
    "sg:postcode":"NE4 7NN",
    "sg:province":"Tyne and Wear",
    "sg:tags":[
        "hr",
        "petrol"
    ],
    "wof:name":"Bp Service Station",
    "wof:placetype":"venue"
},
  "geometry": {"coordinates":[-1.621894002,54.9672050476],"type":"Point"}
}