{
  "type": "Feature",
  "properties": {
    "iso:country":"GB",
    "sg:address":"59 High Street",
    "sg:city":"Lincoln",
    "sg:classifiers":[
        {
            "category":"Autos & Motor Vehicles",
            "subcategory":"Automobile Sales",
            "type":"Retail Goods"
        }
    ],
    "sg:phone":"+44 1522 530006",
    "sg:postcode":"LN5 8AH",
    "sg:province":"Lincolnshire",
    "sg:tags":[
        "commercial"
    ],
    "wof:name":"Colin Richardson Car Sales",
    "wof:placetype":"venue"
},
  "geometry": {"coordinates":[-0.5455,53.218498],"type":"Point"}
}