{
  "type": "Feature",
  "properties": {
    "addr:full":"45a Regent Street Hinckley Leicestershire LE10 0BA",
    "addr:housenumber":"45a",
    "addr:postcode":"le10 0ba",
    "addr:street":"Regent Street",
    "iso:country":"GB",
    "sg:address":"45a Regent Street",
    "sg:city":"Hinckley",
    "sg:classifiers":[
        {
            "category":"Personal",
            "subcategory":"Beauty Salon",
            "type":"Services"
        }
    ],
    "sg:phone":"+44 1455 616484",
    "sg:postcode":"LE10 0BA",
    "sg:province":"Leicestershire",
    "sg:tags":[
        "unisex",
        "hairdresser"
    ],
    "wof:name":"Mayfair Hair Design",
    "wof:placetype":"venue"
},
  "geometry": {"coordinates":[-1.375131,52.540138],"type":"Point"}
}