{
  "type": "Feature",
  "properties": {
    "iso:country":"GB",
    "sg:address":"Unit 7 Kettles Yard, Langwith Road",
    "sg:city":"Mansfield",
    "sg:classifiers":[
        {
            "category":"Professional",
            "subcategory":"Testing Lab",
            "type":"Services"
        }
    ],
    "sg:phone":"+44 1623 746060",
    "sg:postcode":"NG20 9RN",
    "sg:province":"Derbyshire",
    "sg:tags":[
        "mot"
    ],
    "wof:name":"A & R Motor Repairs",
    "wof:placetype":"venue"
},
  "geometry": {"coordinates":[-1.208172,53.227638],"type":"Point"}
}