{
  "type": "Feature",
  "properties": {
    "addr:full":"138 Westoe Road South Shields Tyne and Wear NE33 3PF",
    "addr:housenumber":"138",
    "addr:postcode":"ne33 3pf",
    "addr:street":"Westoe Road",
    "iso:country":"GB",
    "sg:address":"138 Westoe Road",
    "sg:city":"South Shields",
    "sg:classifiers":[
        {
            "category":"Professional",
            "subcategory":"Accounting & Tax Preparation",
            "type":"Services"
        }
    ],
    "sg:postcode":"NE33 3PF",
    "sg:province":"Tyne and Wear",
    "sg:tags":[
        "accountant"
    ],
    "wof:name":"Nicholson Hall",
    "wof:placetype":"venue"
},
  "geometry": {"coordinates":[-1.4261310101,54.989780426],"type":"Point"}
}