{
  "type": "Feature",
  "properties": {
    "iso:country":"GB",
    "sg:address":"Kings Cliffe Road, Wansford",
    "sg:city":"Peterborough",
    "sg:classifiers":[
        {
            "category":"Utilities",
            "subcategory":"Fuel Oil & Lpg",
            "type":"Services"
        },
        {
            "category":"Wholesale",
            "subcategory":"Petroleum",
            "type":"Manufacturing & Wholesale Goods"
        }
    ],
    "sg:phone":"+44 1780 782987",
    "sg:postcode":"PE8 6NU",
    "sg:province":"Cambridgeshire",
    "sg:tags":[
        "distributor"
    ],
    "wof:name":"Tanks Unlimited",
    "wof:placetype":"venue"
},
  "geometry": {"coordinates":[-0.4170140028,52.5838508606],"type":"Point"}
}