{
  "type": "Feature",
  "properties": {
    "addr:full":"43 Montague Square, Clifton Way London Greater London SE15 2LR",
    "addr:housenumber":"43",
    "addr:postcode":"se15 2lr",
    "addr:street":"Montague Square Clifton Way",
    "iso:country":"GB",
    "sg:address":"43 Montague Square, Clifton Way",
    "sg:city":"London",
    "sg:classifiers":[
        {
            "category":"Real Estate",
            "subcategory":"Architect",
            "type":"Services"
        }
    ],
    "sg:postcode":"SE15 2LR",
    "sg:province":"Greater London",
    "wof:name":"Powerhouse Engineering Services Ltd.",
    "wof:placetype":"venue"
},
  "geometry": {"coordinates":[-0.052964,51.477482],"type":"Point"}
}