{
  "type": "Feature",
  "properties": {
    "iso:country":"GB",
    "sg:address":"Unit 16 Heron Road Estate, Sowton Industrial Estate",
    "sg:city":"Exeter",
    "sg:classifiers":[
        {
            "category":"Building & Trades",
            "subcategory":"Equipment Rental",
            "type":"Services"
        }
    ],
    "sg:phone":"+44 1392 444800",
    "sg:postcode":"EX2 7LL",
    "sg:province":"Devon",
    "sg:tags":[
        "plant",
        "machinery"
    ],
    "wof:name":"Beacon Plant Sales",
    "wof:placetype":"venue"
},
  "geometry": {"coordinates":[-3.473614,50.722782],"type":"Point"}
}