{
  "type": "Feature",
  "properties": {
    "addr:full":"108-110 Welling High Street Welling Kent DA16 1TJ",
    "addr:postcode":"108-110;da16 1tj",
    "addr:street":"Welling High Street",
    "iso:country":"GB",
    "sg:address":"108-110 Welling High Street",
    "sg:city":"Welling",
    "sg:classifiers":[
        {
            "category":"Food & Beverages",
            "subcategory":"Bakery",
            "type":"Retail Goods"
        }
    ],
    "sg:phone":"+44 20 8303 3777",
    "sg:postcode":"DA16 1TJ",
    "sg:province":"Kent",
    "sg:tags":[
        "baker"
    ],
    "wof:name":"C S Worth & Sons (Welling) Ltd.",
    "wof:placetype":"venue"
},
  "geometry": {"coordinates":[0.1091170013,51.4621238708],"type":"Point"}
}