{
  "type": "Feature",
  "properties": {
    "addr:full":"The Estate Office, Fairy Cross Bideford Devon EX39 5BX",
    "addr:postcode":"ex39 5bx",
    "addr:street":"Fairy Cross",
    "iso:country":"GB",
    "sg:address":"The Estate Office, Fairy Cross",
    "sg:city":"Bideford",
    "sg:classifiers":[
        {
            "category":"Travel",
            "subcategory":"Hotels & Motels",
            "type":"Entertainment"
        }
    ],
    "sg:phone":"+44 1237 451056",
    "sg:postcode":"EX39 5BX",
    "sg:province":"Devon",
    "sg:tags":[
        "self",
        "catering"
    ],
    "wof:name":"The Portledge Estate Ltd.",
    "wof:placetype":"venue"
},
  "geometry": {"coordinates":[-4.2743988037,50.9971199036],"type":"Point"}
}