{
  "type": "Feature",
  "properties": {
    "addr:full":"West Road Maidenhead Berkshire SL6 1PD",
    "addr:postcode":"sl6 1pd",
    "addr:street":"West Road",
    "iso:country":"GB",
    "sg:address":"West Road",
    "sg:city":"Maidenhead",
    "sg:classifiers":[
        {
            "category":"Farming",
            "subcategory":"Nursery",
            "type":"Manufacturing & Wholesale Goods"
        },
        {
            "category":"Education",
            "subcategory":"School",
            "type":"Public Place"
        }
    ],
    "sg:phone":"+44 1628 624918",
    "sg:postcode":"SL6 1PD",
    "sg:province":"Berkshire",
    "sg:tags":[
        "independent",
        "preparatory",
        "creche"
    ],
    "wof:name":"Highfield School Trust Ltd.",
    "wof:placetype":"venue"
},
  "geometry": {"coordinates":[-0.7282469869,51.5216140747],"type":"Point"}
}