{
  "type": "Feature",
  "properties": {
    "iso:country":"GB",
    "sg:address":"3 Orchard Way, Bubbenhall",
    "sg:city":"Coventry",
    "sg:classifiers":[
        {
            "category":"Professional",
            "subcategory":"Printing & Photocopies",
            "type":"Services"
        }
    ],
    "sg:postcode":"CV8 3JQ",
    "sg:province":"Warwickshire",
    "sg:tags":[
        "printer"
    ],
    "wof:name":"Prudhoe,G M,",
    "wof:placetype":"venue"
},
  "geometry": {"coordinates":[-1.465835,52.349503],"type":"Point"}
}