{
  "type": "Feature",
  "properties": {
    "addr:full":"103 Cambridge Road St Helens Merseyside WA10 4HF",
    "addr:housenumber":"103",
    "addr:postcode":"wa10 4hf",
    "addr:street":"Cambridge Road",
    "iso:country":"GB",
    "sg:address":"103 Cambridge Road",
    "sg:city":"St Helens",
    "sg:classifiers":[
        {
            "category":"Building & Trades",
            "subcategory":"Construction",
            "type":"Services"
        }
    ],
    "sg:phone":"+44 1744 24268",
    "sg:postcode":"WA10 4HF",
    "sg:province":"Merseyside",
    "sg:tags":[
        "decorator",
        "painter"
    ],
    "wof:name":"Chas A Critchley (General Contractors) Ltd.",
    "wof:placetype":"venue"
},
  "geometry": {"coordinates":[-2.7530388832,53.4539985657],"type":"Point"}
}