{
  "type": "Feature",
  "properties": {
    "addr:full":"The Pharmacy, 39 Heol Jwbili Port Talbot Neath Port Talbot SA12 9NR",
    "addr:housenumber":"39",
    "addr:postcode":"sa12 9nr",
    "addr:street":"Heol Jwbili Port Talbot",
    "iso:country":"GB",
    "sg:address":"The Pharmacy, 39 Heol Jwbili",
    "sg:city":"Port Talbot",
    "sg:classifiers":[
        {
            "category":"Shopping",
            "subcategory":"Pharmacy",
            "type":"Retail Goods"
        }
    ],
    "sg:postcode":"SA12 9NR",
    "sg:province":"Neath Port Talbot",
    "sg:tags":[
        "pharmacist",
        "chemist"
    ],
    "wof:name":"Adrian D Richards",
    "wof:placetype":"venue"
},
  "geometry": {"coordinates":[-3.8023691177,51.5913848877],"type":"Point"}
}