{
  "type": "Feature",
  "properties": {
    "iso:country":"GB",
    "sg:address":"21a Coventry Road, Coleshill",
    "sg:city":"Birmingham",
    "sg:classifiers":[
        {
            "category":"Building & Trades",
            "subcategory":"Construction",
            "type":"Services"
        }
    ],
    "sg:phone":"+44 1675 466991",
    "sg:postcode":"B46 3BB",
    "sg:province":"Warwickshire",
    "sg:tags":[
        "builder"
    ],
    "wof:name":"Heathley Homes Ltd.",
    "wof:placetype":"venue"
},
  "geometry": {"coordinates":[-1.704691,52.49424],"type":"Point"}
}