{
  "type": "Feature",
  "properties": {
    "addr:full":"74 Tanygroes Street Port Talbot Neath Port Talbot SA13 1EE",
    "addr:housenumber":"74",
    "addr:postcode":"sa13 1ee",
    "addr:street":"Tanygroes Street",
    "iso:country":"GB",
    "sg:address":"74 Tanygroes Street",
    "sg:city":"Port Talbot",
    "sg:classifiers":[
        {
            "category":"Shopping",
            "subcategory":"News",
            "type":"Retail Goods"
        }
    ],
    "sg:postcode":"SA13 1EE",
    "sg:province":"Neath Port Talbot",
    "sg:tags":[
        "newsagent"
    ],
    "wof:name":"M & A Gosby",
    "wof:placetype":"venue"
},
  "geometry": {"coordinates":[-3.774158,51.592186],"type":"Point"}
}