{
  "type": "Feature",
  "properties": {
    "addr:full":"Unit B22 Treforest Industrial Estate Pontypridd Caerphilly CF37 5TF",
    "addr:housenumber":"b22 treforest",
    "addr:postcode":"cf37 5tf",
    "addr:street":"Industrial Estate",
    "iso:country":"GB",
    "sg:address":"Unit B22 Treforest Industrial Estate",
    "sg:city":"Pontypridd",
    "sg:classifiers":[
        {
            "category":"Food & Beverages",
            "subcategory":"Bakery",
            "type":"Retail Goods"
        }
    ],
    "sg:phone":"+44 1443 843421",
    "sg:postcode":"CF37 5TF",
    "sg:province":"Caerphilly",
    "sg:tags":[
        "baker"
    ],
    "wof:name":"Greggs of Treforest",
    "wof:placetype":"venue"
},
  "geometry": {"coordinates":[-3.291999,51.571175],"type":"Point"}
}