{
  "type": "Feature",
  "properties": {
    "iso:country":"GB",
    "sg:address":"P.o Box 28",
    "sg:city":"Stourport On Severn",
    "sg:classifiers":[
        {
            "category":"Organizations",
            "subcategory":"Non-profit Organization",
            "type":"Services"
        }
    ],
    "sg:phone":"+44 1299 827802",
    "sg:postcode":"DY13 8AE",
    "sg:province":"Worcestershire",
    "sg:tags":[
        "organisation",
        "animal",
        "welfare"
    ],
    "wof:name":"Worcestershire Badger Society",
    "wof:placetype":"venue"
},
  "geometry": {"coordinates":[-2.281167,52.338997],"type":"Point"}
}