{
  "type": "Feature",
  "properties": {
    "iso:country":"GB",
    "sg:address":"310 Linthorpe Road",
    "sg:city":"Middlesbrough",
    "sg:classifiers":[
        {
            "category":"Fast Food",
            "type":"Food & Drink"
        }
    ],
    "sg:phone":"+44 1642 246855",
    "sg:postcode":"TS1 3QX",
    "sg:province":"North Yorkshire",
    "sg:tags":[
        "delivery"
    ],
    "wof:name":"Lacasa Pizzeria",
    "wof:placetype":"venue"
},
  "geometry": {"coordinates":[-1.239759,54.567307],"type":"Point"}
}