{
  "type": "Feature",
  "properties": {
    "iso:country":"GB",
    "sg:address":"49 Tenbury Road",
    "sg:city":"Birmingham",
    "sg:classifiers":[
        {
            "category":"Health Services",
            "subcategory":"Podiatrist",
            "type":"Services"
        }
    ],
    "sg:phone":"+44 121 444 2146",
    "sg:postcode":"B14 6AH",
    "sg:province":"West Midlands",
    "sg:tags":[
        "podiatrists",
        "chiropodist"
    ],
    "wof:name":"K G Harvey",
    "wof:placetype":"venue"
},
  "geometry": {"coordinates":[-1.897573,52.42664],"type":"Point"}
}