{
  "type": "Feature",
  "properties": {
    "iso:country":"GB",
    "sg:address":"17 Rathbone St",
    "sg:city":"London",
    "sg:classifiers":[
        {
            "category":"Wholesale",
            "subcategory":"Books, Periodicals, & Newspapers",
            "type":"Manufacturing & Wholesale Goods"
        }
    ],
    "sg:postcode":"W1T 1NA",
    "sg:province":"Greater London",
    "sg:tags":[
        "publishing"
    ],
    "wof:name":"Arberry Pink Ltd",
    "wof:placetype":"venue"
},
  "geometry": {"coordinates":[-0.135119,51.51799],"type":"Point"}
}