{
  "type": "Feature",
  "properties": {
    "addr:full":"Wilsthorpe Road, Long Eaton Nottingham Derbyshire NG10 3JX",
    "addr:postcode":"ng10 3jx",
    "addr:street":"Wilsthorpe Road",
    "iso:country":"GB",
    "sg:address":"Wilsthorpe Road, Long Eaton",
    "sg:city":"Nottingham",
    "sg:classifiers":[
        {
            "category":"Autos & Motor Vehicles",
            "subcategory":"Fuel & Gas Station",
            "type":"Retail Goods"
        }
    ],
    "sg:phone":"+44 115 973 3139",
    "sg:postcode":"NG10 3JX",
    "sg:province":"Derbyshire",
    "sg:tags":[
        "petrol",
        "filling"
    ],
    "wof:name":"Junction Service Station",
    "wof:placetype":"venue"
},
  "geometry": {"coordinates":[-1.2918339968,52.8952293396],"type":"Point"}
}