{
  "type": "Feature",
  "properties": {
    "addr:full":"57 Rusper Road Crawley West Sussex RH11 0HN",
    "addr:housenumber":"57",
    "addr:postcode":"rh11 0hn",
    "addr:street":"Rusper Road",
    "iso:country":"GB",
    "sg:address":"57 Rusper Road",
    "sg:city":"Crawley",
    "sg:classifiers":[
        {
            "category":"Building & Trades",
            "subcategory":"Construction",
            "type":"Services"
        }
    ],
    "sg:postcode":"RH11 0HN",
    "sg:province":"West Sussex",
    "sg:tags":[
        "builder"
    ],
    "wof:name":"Wrightway Builders",
    "wof:placetype":"venue"
},
  "geometry": {"coordinates":[-0.217663,51.121712],"type":"Point"}
}