{
  "type": "Feature",
  "properties": {
    "iso:country":"GB",
    "sg:address":"Sentinel House Ground Floor, 16-22 Sutton Court Road",
    "sg:city":"Sutton",
    "sg:classifiers":[
        {
            "category":"Professional",
            "subcategory":"Employment Agencies",
            "type":"Services"
        }
    ],
    "sg:postcode":"SM1 4SY",
    "sg:province":"Surrey",
    "sg:tags":[
        "consultant"
    ],
    "wof:name":"Pds Personnel Services Ltd",
    "wof:placetype":"venue"
},
  "geometry": {"coordinates":[-0.197558,51.361191],"type":"Point"}
}