{
  "type": "Feature",
  "properties": {
    "iso:country":"GB",
    "sg:address":"Unit 11/12 Brindley Business Par, K",
    "sg:city":"Cannock",
    "sg:classifiers":[
        {
            "category":"Professional",
            "subcategory":"Engineering",
            "type":"Services"
        }
    ],
    "sg:phone":"+44 1543 422616",
    "sg:postcode":"WS11 7GD",
    "sg:province":"Staffordshire",
    "sg:tags":[
        "contractor",
        "electrical",
        "engineer"
    ],
    "wof:name":"J C Electrical & Mechanical Services",
    "wof:placetype":"venue"
},
  "geometry": {"coordinates":[-2.0331449509,52.690952301],"type":"Point"}
}