{
  "type": "Feature",
  "properties": {
    "iso:country":"GB",
    "sg:address":"Abbey Lane, Kirkstead",
    "sg:city":"Woodhall Spa",
    "sg:classifiers":[
        {
            "category":"Home & Garden",
            "subcategory":"Garden Supply",
            "type":"Retail Goods"
        }
    ],
    "sg:postcode":"LN10 6UH",
    "sg:province":"Lincolnshire",
    "sg:tags":[
        "turfing"
    ],
    "wof:name":"Cannons Turf Ltd.",
    "wof:placetype":"venue"
},
  "geometry": {"coordinates":[-0.212844,53.152489],"type":"Point"}
}