{
  "type": "Feature",
  "properties": {
    "iso:country":"GB",
    "sg:address":"20 Endbutt Lane, Crosby",
    "sg:city":"Liverpool",
    "sg:classifiers":[
        {
            "category":"Professional",
            "subcategory":"Engineering",
            "type":"Services"
        }
    ],
    "sg:phone":"+44 151 924 2208",
    "sg:postcode":"L23 0TR",
    "sg:province":"Merseyside",
    "sg:tags":[
        "contractor",
        "electrical",
        "engineer"
    ],
    "wof:name":"John Goodwin Electrical Contracators",
    "wof:placetype":"venue"
},
  "geometry": {"coordinates":[-3.022664,53.488922],"type":"Point"}
}