{
  "type": "Feature",
  "properties": {
    "addr:full":"20 Borve, Skeabost Bridge Portree Highland IV51 9PE",
    "addr:housenumber":"20",
    "addr:postcode":"iv51 9pe",
    "addr:street":"Borve Skeabost Bridge Portree",
    "iso:country":"GB",
    "sg:address":"20 Borve, Skeabost Bridge",
    "sg:city":"Portree",
    "sg:classifiers":[
        {
            "category":"Building & Trades",
            "subcategory":"Construction",
            "type":"Services"
        }
    ],
    "sg:phone":"+44 1470 532301",
    "sg:postcode":"IV51 9PE",
    "sg:province":"Highland",
    "sg:tags":[
        "joiner",
        "carpenter"
    ],
    "wof:name":"A McDonald",
    "wof:placetype":"venue"
},
  "geometry": {"coordinates":[-6.1961350441,57.4127845764],"type":"Point"}
}