{
  "type": "Feature",
  "properties": {
    "iso:country":"GB",
    "sg:address":"27 Annette Street",
    "sg:city":"Glasgow",
    "sg:classifiers":[
        {
            "category":"Education",
            "subcategory":"School",
            "type":"Public Place"
        }
    ],
    "sg:phone":"+44 141 423 0192",
    "sg:postcode":"G42 8YB",
    "sg:province":"Glasgow City",
    "sg:tags":[
        "local",
        "authority"
    ],
    "wof:name":"Annette Street Primary School",
    "wof:placetype":"venue"
},
  "geometry": {"coordinates":[-4.26073,55.836262],"type":"Point"}
}