{
  "type": "Feature",
  "properties": {
    "addr:full":"112-114 Humberstone Road Leicester Leicestershire LE5 0AT",
    "addr:postcode":"112-114;le5 0at",
    "addr:street":"Humberstone Road",
    "iso:country":"GB",
    "sg:address":"112-114 Humberstone Road",
    "sg:city":"Leicester",
    "sg:classifiers":[
        {
            "category":"Shopping",
            "subcategory":"Stationery & Office Supplies",
            "type":"Retail Goods"
        }
    ],
    "sg:phone":"+44 116 251 8388",
    "sg:postcode":"LE5 0AT",
    "sg:province":"Leicestershire",
    "sg:tags":[
        "box",
        "carton"
    ],
    "wof:name":"R T V Packaging Ltd.",
    "wof:placetype":"venue"
},
  "geometry": {"coordinates":[-1.0843839645,52.6458396912],"type":"Point"}
}