{
  "type": "Feature",
  "properties": {
    "addr:full":"3 Priory Crescent, Binham Fakenham Norfolk NR21 0DB",
    "addr:housenumber":"3",
    "addr:postcode":"nr21 0db",
    "addr:street":"Priory Crescent",
    "iso:country":"GB",
    "sg:address":"3 Priory Crescent, Binham",
    "sg:city":"Fakenham",
    "sg:classifiers":[
        {
            "category":"Building & Trades",
            "subcategory":"Construction",
            "type":"Services"
        }
    ],
    "sg:phone":"+44 1328 830652",
    "sg:postcode":"NR21 0DB",
    "sg:province":"Norfolk",
    "sg:tags":[
        "builder"
    ],
    "wof:name":"Stanley A Hewitt",
    "wof:placetype":"venue"
},
  "geometry": {"coordinates":[0.947445,52.916195],"type":"Point"}
}