{
  "type": "Feature",
  "properties": {
    "addr:full":"40 Shoreham Dr Warrington Cheshire WA5 2HY",
    "addr:housenumber":"40",
    "addr:postcode":"wa5 2hy",
    "addr:street":"Shoreham Dr",
    "iso:country":"GB",
    "sg:address":"40 Shoreham Dr",
    "sg:city":"Warrington",
    "sg:classifiers":[
        {
            "category":"Building & Trades",
            "subcategory":"Construction",
            "type":"Services"
        }
    ],
    "sg:phone":"+44 1925 727814",
    "sg:postcode":"WA5 2HY",
    "sg:province":"Cheshire",
    "sg:tags":[
        "builder"
    ],
    "wof:name":"Wall Construction",
    "wof:placetype":"venue"
},
  "geometry": {"coordinates":[-2.643896,53.381165],"type":"Point"}
}