{
  "type": "Feature",
  "properties": {
    "iso:country":"GB",
    "sg:address":"Unit 2, Shaw Lane Industrial Estate",
    "sg:city":"Bromsgrove",
    "sg:classifiers":[
        {
            "category":"Government",
            "subcategory":"Post Office",
            "type":"Public Place"
        }
    ],
    "sg:postcode":"B60 4ED",
    "sg:province":"Worcestershire",
    "sg:tags":[
        "messenger",
        "courier"
    ],
    "wof:name":"Grabbit & Run (West Mids) Ltd",
    "wof:placetype":"venue"
},
  "geometry": {"coordinates":[-2.0874519348,52.2926826477],"type":"Point"}
}