{
  "type": "Feature",
  "properties": {
    "addr:full":"73-75 Market Street, Farnworth Bolton Lancashire BL4 7NS",
    "addr:housenumber":"73-75",
    "addr:postcode":"bl4 7ns",
    "addr:street":"Market Street",
    "iso:country":"GB",
    "sg:address":"73-75 Market Street, Farnworth",
    "sg:city":"Bolton",
    "sg:classifiers":[
        {
            "category":"Fast Food",
            "type":"Food & Drink"
        }
    ],
    "sg:phone":"+44 1204 862627",
    "sg:postcode":"BL4 7NS",
    "sg:province":"Lancashire",
    "sg:tags":[
        "away",
        "take"
    ],
    "wof:name":"Rancheros",
    "wof:placetype":"venue"
},
  "geometry": {"coordinates":[-2.394713,53.549835],"type":"Point"}
}