{
  "type": "Feature",
  "properties": {
    "iso:country":"GB",
    "sg:address":"3 Bowland Road",
    "sg:city":"Woodford Green",
    "sg:classifiers":[
        {
            "category":"Retail",
            "subcategory":"Storage",
            "type":"Services"
        }
    ],
    "sg:postcode":"IG8 7LX",
    "sg:province":"Essex",
    "sg:tags":[
        "household",
        "removal"
    ],
    "wof:name":"S Wallace",
    "wof:placetype":"venue"
},
  "geometry": {"coordinates":[0.0395909995,51.6090583801],"type":"Point"}
}