{
  "type": "Feature",
  "properties": {
    "iso:country":"GB",
    "sg:address":"Tor Hill Farm, Drewsteignton",
    "sg:city":"Exeter",
    "sg:classifiers":[
        {
            "category":"Farming",
            "subcategory":"Livestock Farm",
            "type":"Manufacturing & Wholesale Goods"
        }
    ],
    "sg:phone":"+44 1647 231590",
    "sg:postcode":"EX6 6RG",
    "sg:province":"Devon",
    "sg:tags":[
        "others"
    ],
    "wof:name":"John H Harrington",
    "wof:placetype":"venue"
},
  "geometry": {"coordinates":[-3.792148,50.703949],"type":"Point"}
}