{
  "type": "Feature",
  "properties": {
    "addr:full":"86-88 Lord Street, North Shore Blackpool Lancashire FY1 2DJ",
    "addr:housenumber":"86-88",
    "addr:postcode":"fy1 2dj",
    "addr:street":"Lord Street",
    "iso:country":"GB",
    "sg:address":"86-88 Lord Street, North Shore",
    "sg:city":"Blackpool",
    "sg:classifiers":[
        {
            "category":"Travel",
            "subcategory":"Hotels & Motels",
            "type":"Entertainment"
        }
    ],
    "sg:phone":"+44 1253 620524",
    "sg:postcode":"FY1 2DJ",
    "sg:province":"Lancashire",
    "wof:name":"Falkland",
    "wof:placetype":"venue"
},
  "geometry": {"coordinates":[-3.053769,53.824619],"type":"Point"}
}