{
  "type": "Feature",
  "properties": {
    "addr:full":"Pen-y-ffridd Farm, Cerrig Road Ruthin Denbighshire LL15 2LR",
    "addr:postcode":"ll15 2lr",
    "addr:street":"Cerrig Road",
    "iso:country":"GB",
    "sg:address":"Pen-y-ffridd Farm, Cerrig Road",
    "sg:city":"Ruthin",
    "sg:classifiers":[
        {
            "category":"Farming",
            "subcategory":"Livestock Farm",
            "type":"Manufacturing & Wholesale Goods"
        }
    ],
    "sg:phone":"+44 1824 750661",
    "sg:postcode":"LL15 2LR",
    "sg:province":"Denbighshire",
    "sg:tags":[
        "others"
    ],
    "wof:name":"Herbert Jones",
    "wof:placetype":"venue"
},
  "geometry": {"coordinates":[-3.3045220375,53.1140174866],"type":"Point"}
}