{
  "type": "Feature",
  "properties": {
    "iso:country":"GB",
    "sg:address":"Flat 2 7 Park Road",
    "sg:city":"Halifax",
    "sg:classifiers":[
        {
            "category":"Health Services",
            "subcategory":"Dentist",
            "type":"Services"
        }
    ],
    "sg:phone":"+44 1422 368059",
    "sg:postcode":"HX1 2TS",
    "sg:province":"West Yorkshire",
    "wof:name":"The Park Road Dental Practice",
    "wof:placetype":"venue"
},
  "geometry": {"coordinates":[-1.862224,53.721233],"type":"Point"}
}