{
  "type": "Feature",
  "properties": {
    "addr:full":"Homebase Store, London Road Biggleswade Bedfordshire SG18 8EB",
    "addr:postcode":"sg18 8eb",
    "addr:street":"London Road",
    "iso:country":"GB",
    "sg:address":"Homebase Store, London Road",
    "sg:city":"Biggleswade",
    "sg:classifiers":[
        {
            "category":"Education",
            "subcategory":"Music School",
            "type":"Public Place"
        }
    ],
    "sg:phone":"+44 1767 316596",
    "sg:postcode":"SG18 8EB",
    "sg:province":"Bedfordshire",
    "sg:tags":[
        "conservatory"
    ],
    "wof:name":"Portland Conservatories Ltd.",
    "wof:placetype":"venue"
},
  "geometry": {"coordinates":[-0.261729,52.086975],"type":"Point"}
}