{
  "type": "Feature",
  "properties": {
    "addr:full":"The Harbour Nairn Highland IV12 4PH",
    "addr:postcode":"iv12 4ph",
    "iso:country":"GB",
    "sg:address":"The Harbour",
    "sg:city":"Nairn",
    "sg:classifiers":[
        {
            "category":"Recreation",
            "subcategory":"Amusement Park",
            "type":"Entertainment"
        }
    ],
    "sg:phone":"+44 1667 454500",
    "sg:postcode":"IV12 4PH",
    "sg:province":"Highland",
    "sg:tags":[
        "arcade"
    ],
    "wof:name":"Sandancer Fun & Food",
    "wof:placetype":"venue"
},
  "geometry": {"coordinates":[-3.8767089844,57.5832138062],"type":"Point"}
}