{
  "type": "Feature",
  "properties": {
    "addr:full":"44 Heath Road, Holmewood Chesterfield Derbyshire S42 5RA",
    "addr:housenumber":"44",
    "addr:postcode":"s42 5ra",
    "addr:street":"Heath Road",
    "iso:country":"GB",
    "sg:address":"44 Heath Road, Holmewood",
    "sg:city":"Chesterfield",
    "sg:classifiers":[
        {
            "category":"Shopping",
            "subcategory":"Crafts & Fabrics",
            "type":"Retail Goods"
        }
    ],
    "sg:phone":"+44 1246 855155",
    "sg:postcode":"S42 5RA",
    "sg:province":"Derbyshire",
    "sg:tags":[
        "shop"
    ],
    "wof:name":"Economy Fabrics",
    "wof:placetype":"venue"
},
  "geometry": {"coordinates":[-1.354729,53.188175],"type":"Point"}
}