{
  "type": "Feature",
  "properties": {
    "iso:country":"GB",
    "sg:address":"149 Leckhampton Road",
    "sg:city":"Cheltenham",
    "sg:classifiers":[
        {
            "category":"Shopping",
            "subcategory":"News",
            "type":"Retail Goods"
        }
    ],
    "sg:phone":"+44 1242 242966",
    "sg:postcode":"GL53 0AD",
    "sg:province":"Gloucestershire",
    "sg:tags":[
        "newsagent"
    ],
    "wof:name":"Leckhampton Post Office",
    "wof:placetype":"venue"
},
  "geometry": {"coordinates":[-2.077129,51.877377],"type":"Point"}
}