{
  "type": "Feature",
  "properties": {
    "iso:country":"GB",
    "sg:address":"69 71 East Street",
    "sg:city":"Epsom",
    "sg:classifiers":[
        {
            "category":"Banks & Credit Unions",
            "subcategory":"Financial Services",
            "type":"Services"
        }
    ],
    "sg:postcode":"KT17 1BP",
    "sg:province":"Surrey",
    "sg:tags":[
        "consultant"
    ],
    "wof:name":"Scudos Ltd.",
    "wof:placetype":"venue"
},
  "geometry": {"coordinates":[-0.259932,51.336803],"type":"Point"}
}