{
  "type": "Feature",
  "properties": {
    "addr:full":"Unit 6a 280 Coleridge Rd Sheffield South Yorkshire S9 5DA",
    "addr:housenumber":"unit 6a 280",
    "addr:postcode":"s9 5da",
    "addr:street":"Coleridge Rd",
    "iso:country":"GB",
    "sg:address":"Unit 6a 280 Coleridge Rd",
    "sg:city":"Sheffield",
    "sg:classifiers":[
        {
            "category":"Building & Trades",
            "subcategory":"Cleaning & Sanitation",
            "type":"Services"
        }
    ],
    "sg:phone":"+44 114 249 4080",
    "sg:postcode":"S9 5DA",
    "sg:province":"South Yorkshire",
    "sg:tags":[
        "blast"
    ],
    "wof:name":"Allblast",
    "wof:placetype":"venue"
},
  "geometry": {"coordinates":[-1.4201500416,53.3969688416],"type":"Point"}
}