{
  "type": "Feature",
  "properties": {
    "iso:country":"GB",
    "sg:address":"Chapman Court, Charfleets Road, Charfleets Industrial Estate",
    "sg:city":"Canvey Island",
    "sg:classifiers":[
        {
            "category":"Professional",
            "subcategory":"Advertising",
            "type":"Services"
        }
    ],
    "sg:phone":"+44 1268 698230",
    "sg:postcode":"SS8 0PQ",
    "sg:province":"Essex",
    "wof:name":"The Voucher Co. Ltd.",
    "wof:placetype":"venue"
},
  "geometry": {"coordinates":[0.557592988,51.5218429565],"type":"Point"}
}