{
  "type": "Feature",
  "properties": {
    "iso:country":"GB",
    "sg:address":"96 Newhey Road, Milnrow",
    "sg:city":"Rochdale",
    "sg:classifiers":[
        {
            "category":"Professional",
            "type":"Services"
        },
        {
            "category":"Retail",
            "subcategory":"Laundry & Dry Cleaning",
            "type":"Services"
        }
    ],
    "sg:phone":"+44 1706 521527",
    "sg:postcode":"OL16 4JE",
    "sg:province":"Lancashire",
    "sg:tags":[
        "linen",
        "hire",
        "launderette"
    ],
    "wof:name":"Universal Laundry Services",
    "wof:placetype":"venue"
},
  "geometry": {"coordinates":[-2.104509,53.605442],"type":"Point"}
}