{
  "type": "Feature",
  "properties": {
    "iso:country":"GB",
    "sg:address":"Wisteria House, 28 Fulling Mill Lane",
    "sg:city":"Welwyn",
    "sg:classifiers":[
        {
            "category":"Professional",
            "subcategory":"Business Services",
            "type":"Services"
        }
    ],
    "sg:phone":"+44 870 240 4542",
    "sg:postcode":"AL6 9NS",
    "sg:province":"Hertfordshire",
    "sg:tags":[
        "trade"
    ],
    "wof:name":"Photo Marketing Association International (U K) Ltd.",
    "wof:placetype":"venue"
},
  "geometry": {"coordinates":[-0.220881,51.835075],"type":"Point"}
}