{
  "type": "Feature",
  "properties": {
    "addr:full":"European House, 30 Salisbury Street Wolverhampton Staffordshire WV3 0BG",
    "addr:housenumber":"30",
    "addr:postcode":"wv3 0bg",
    "addr:street":"Salisbury Street",
    "iso:country":"GB",
    "sg:address":"European House, 30 Salisbury Street",
    "sg:city":"Wolverhampton",
    "sg:classifiers":[
        {
            "category":"Home & Garden",
            "subcategory":"Hardware",
            "type":"Retail Goods"
        }
    ],
    "sg:postcode":"WV3 0BG",
    "sg:province":"Staffordshire",
    "sg:tags":[
        "paint"
    ],
    "wof:name":"Black Country Paints Ltd.",
    "wof:placetype":"venue"
},
  "geometry": {"coordinates":[-2.139369,52.580505],"type":"Point"}
}