{
  "type": "Feature",
  "properties": {
    "iso:country":"GB",
    "sg:address":"78 Chichester Road",
    "sg:city":"Portsmouth",
    "sg:classifiers":[
        {
            "category":"Bars & Pubs",
            "type":"Food & Drink"
        }
    ],
    "sg:phone":"+44 23 9266 9500",
    "sg:postcode":"PO2 0AH",
    "sg:province":"Hampshire",
    "sg:tags":[
        "pubs",
        "inn"
    ],
    "wof:name":"The Pelham Arms",
    "wof:placetype":"venue"
},
  "geometry": {"coordinates":[-1.076353,50.81366],"type":"Point"}
}