{
  "type": "Feature",
  "properties": {
    "addr:full":"5 Beauley Road, Southville Bristol City of Bristol BS3 1PX",
    "addr:housenumber":"5",
    "addr:postcode":"bs3 1px",
    "addr:street":"Beauley Road",
    "iso:country":"GB",
    "sg:address":"5 Beauley Road, Southville",
    "sg:city":"Bristol",
    "sg:classifiers":[
        {
            "category":"Organizations",
            "subcategory":"Membership Organization",
            "type":"Services"
        }
    ],
    "sg:postcode":"BS3 1PX",
    "sg:province":"City of Bristol",
    "sg:tags":[
        "club"
    ],
    "wof:name":"Develop Court Ltd",
    "wof:placetype":"venue"
},
  "geometry": {"coordinates":[-2.6085119247,51.445640564],"type":"Point"}
}