{
  "type": "Feature",
  "properties": {
    "iso:country":"GB",
    "sg:address":"Mo Ango, Hind Heath Lane",
    "sg:city":"Sandbach",
    "sg:classifiers":[
        {
            "category":"Building & Trades",
            "subcategory":"Construction",
            "type":"Services"
        }
    ],
    "sg:postcode":"CW11 3LH",
    "sg:province":"Cheshire",
    "sg:tags":[
        "builder"
    ],
    "wof:name":"G Ollerhead & Sons",
    "wof:placetype":"venue"
},
  "geometry": {"coordinates":[-2.387557,53.138435],"type":"Point"}
}