{
  "type": "Feature",
  "properties": {
    "addr:full":"Pinfold, Tenter Road Doncaster South Yorkshire DN4 9PW",
    "addr:postcode":"dn4 9pw",
    "addr:street":"Pinfold Tenter Road",
    "iso:country":"GB",
    "sg:address":"Pinfold, Tenter Road",
    "sg:city":"Doncaster",
    "sg:classifiers":[
        {
            "category":"Manufacturing",
            "subcategory":"Rubber & Plastics",
            "type":"Manufacturing & Wholesale Goods"
        }
    ],
    "sg:postcode":"DN4 9PW",
    "sg:province":"South Yorkshire",
    "sg:tags":[
        "product"
    ],
    "wof:name":"Plastic Granulating Services",
    "wof:placetype":"venue"
},
  "geometry": {"coordinates":[-1.1794999838,53.500919342],"type":"Point"}
}