{
  "type": "Feature",
  "properties": {
    "iso:country":"GB",
    "sg:address":"Cargo House, Prestwick International Airport",
    "sg:city":"Prestwick",
    "sg:classifiers":[
        {
            "category":"Government",
            "subcategory":"Customs House",
            "type":"Public Place"
        }
    ],
    "sg:phone":"+44 1292 478548",
    "sg:postcode":"KA9 2PX",
    "sg:province":"South Ayrshire",
    "sg:tags":[
        "excise"
    ],
    "wof:name":"Customs & Excise",
    "wof:placetype":"venue"
},
  "geometry": {"coordinates":[-4.604234,55.50877],"type":"Point"}
}