{
  "type": "Feature",
  "properties": {
    "addr:full":"58 Westbourne Terrace Bayswater Greater London W2 3UJ",
    "addr:housenumber":"58",
    "addr:postcode":"w2 3uj",
    "addr:street":"Westbourne Terrace",
    "iso:country":"GB",
    "sg:address":"58 Westbourne Terrace",
    "sg:city":"Bayswater",
    "sg:classifiers":[
        {
            "category":"Shopping",
            "subcategory":"Pharmacy",
            "type":"Retail Goods"
        }
    ],
    "sg:phone":"+44 20 7224 6429",
    "sg:postcode":"W2 3UJ",
    "sg:province":"Greater London",
    "sg:tags":[
        "medicine",
        "therapy"
    ],
    "wof:name":"Double 0 Seven International Massage",
    "wof:placetype":"venue"
},
  "geometry": {"coordinates":[-0.179079,51.515034],"type":"Point"}
}