{
  "type": "Feature",
  "properties": {
    "addr:full":"64 Wellington Chambers, Fort Street Ayr South Ayrshire KA7 1EH",
    "addr:housenumber":"64",
    "addr:postcode":"ka7 1eh",
    "addr:street":"Wellington Chambers Fort Street",
    "iso:country":"GB",
    "sg:address":"64 Wellington Chambers, Fort Street",
    "sg:city":"Ayr",
    "sg:classifiers":[
        {
            "category":"Health Services",
            "subcategory":"Dentist",
            "type":"Services"
        }
    ],
    "sg:postcode":"KA7 1EH",
    "sg:province":"South Ayrshire",
    "wof:name":"Mark I Fitzpatrick",
    "wof:placetype":"venue"
},
  "geometry": {"coordinates":[-4.6292819977,55.4428710938],"type":"Point"}
}