{
  "type": "Feature",
  "properties": {
    "addr:full":"44 Lower Addiscombe Road Croydon Surrey CR0 6AA",
    "addr:housenumber":"44",
    "addr:postcode":"cr0 6aa",
    "addr:street":"Lower Addiscombe Road",
    "iso:country":"GB",
    "sg:address":"44 Lower Addiscombe Road",
    "sg:city":"Croydon",
    "sg:classifiers":[
        {
            "category":"Personal",
            "subcategory":"Beauty Salon",
            "type":"Services"
        }
    ],
    "sg:phone":"+44 20 8686 3455",
    "sg:postcode":"CR0 6AA",
    "sg:province":"Surrey",
    "sg:tags":[
        "lady",
        "hairdresser"
    ],
    "wof:name":"Adalena",
    "wof:placetype":"venue"
},
  "geometry": {"coordinates":[-0.087514,51.380466],"type":"Point"}
}