{
  "type": "Feature",
  "properties": {
    "addr:full":"Rickley House, Corrigan Close, Bletchley Milton Keynes Buckinghamshire MK3 6BP",
    "addr:postcode":"mk3 6bp",
    "addr:street":"Corrigan Close",
    "iso:country":"GB",
    "sg:address":"Rickley House, Corrigan Close, Bletchley",
    "sg:city":"Milton Keynes",
    "sg:classifiers":[
        {
            "category":"Arts & Performance",
            "subcategory":"Music",
            "type":"Entertainment"
        }
    ],
    "sg:postcode":"MK3 6BP",
    "sg:province":"Buckinghamshire",
    "sg:tags":[
        "mobile",
        "disco"
    ],
    "wof:name":"M K's No 1 Disco",
    "wof:placetype":"venue"
},
  "geometry": {"coordinates":[-0.7473189831,51.9952812195],"type":"Point"}
}