{
  "type": "Feature",
  "properties": {
    "addr:full":"53 Trinity Road Bridlington East Riding of Yorkshire YO15 2HF",
    "addr:housenumber":"53",
    "addr:postcode":"yo15 2hf",
    "addr:street":"Trinity Road",
    "iso:country":"GB",
    "sg:address":"53 Trinity Road",
    "sg:city":"Bridlington",
    "sg:classifiers":[
        {
            "category":"Travel",
            "subcategory":"Hotels & Motels",
            "type":"Entertainment"
        }
    ],
    "sg:postcode":"YO15 2HF",
    "sg:province":"East Riding of Yorkshire",
    "sg:tags":[
        "self",
        "catering"
    ],
    "wof:name":"Glengarth Holiday Flats",
    "wof:placetype":"venue"
},
  "geometry": {"coordinates":[-0.186678,54.087425],"type":"Point"}
}