{
  "type": "Feature",
  "properties": {
    "addr:full":"24 Hour Live-in Home Care, 22 Glendinning Av Weymouth Dorset DT4 7QF",
    "addr:housenumber":"22",
    "addr:postcode":"dt4 7qf",
    "addr:street":"Glendinning Av",
    "iso:country":"GB",
    "sg:address":"24 Hour Live-in Home Care, 22 Glendinning Av",
    "sg:city":"Weymouth",
    "sg:classifiers":[
        {
            "category":"Social Services",
            "subcategory":"Retirement Home",
            "type":"Services"
        }
    ],
    "sg:phone":"+44 1305 775544",
    "sg:postcode":"DT4 7QF",
    "sg:province":"Dorset",
    "sg:tags":[
        "care"
    ],
    "wof:name":"Independent Living Organisation",
    "wof:placetype":"venue"
},
  "geometry": {"coordinates":[-2.4592061043,50.6099014282],"type":"Point"}
}