{
  "type": "Feature",
  "properties": {
    "addr:full":"Lea Valley Trading Est, Angel Rd Upper Edmonton Greater London N18 3HN",
    "addr:postcode":"n18 3hn",
    "addr:street":"Angel Rd",
    "iso:country":"GB",
    "sg:address":"Lea Valley Trading Est, Angel Rd",
    "sg:city":"Upper Edmonton",
    "sg:classifiers":[
        {
            "category":"Manufacturing",
            "subcategory":"Wood Products",
            "type":"Manufacturing & Wholesale Goods"
        }
    ],
    "sg:phone":"+44 20 8803 9708",
    "sg:postcode":"N18 3HN",
    "sg:province":"Greater London",
    "sg:tags":[
        "woodturning"
    ],
    "wof:name":"Lawrance-Lowings (Knightsbridge) Ltd",
    "wof:placetype":"venue"
},
  "geometry": {"coordinates":[-0.0423,51.61327],"type":"Point"}
}