{
  "type": "Feature",
  "properties": {
    "iso:country":"GB",
    "sg:address":"Craig Oloch Road",
    "sg:city":"Forfar",
    "sg:classifiers":[
        {
            "category":"Government",
            "subcategory":"Office",
            "type":"Public Place"
        },
        {
            "category":"Landmark",
            "subcategory":"Tourist Attraction",
            "type":"Public Place"
        }
    ],
    "sg:phone":"+44 1307 461118",
    "sg:postcode":"DD8 1BT",
    "sg:province":"Angus",
    "sg:tags":[
        "local",
        "interest"
    ],
    "wof:name":"Forfar Loch Country Park",
    "wof:placetype":"venue"
},
  "geometry": {"coordinates":[-2.895549,56.646046],"type":"Point"}
}