{
  "type": "Feature",
  "properties": {
    "addr:full":"519 Old York Road London Greater London SW18 1TF",
    "addr:housenumber":"519",
    "addr:postcode":"sw18 1tf",
    "addr:street":"Old York Road",
    "iso:country":"GB",
    "sg:address":"519 Old York Road",
    "sg:city":"London",
    "sg:classifiers":[
        {
            "category":"Food & Beverages",
            "subcategory":"Liquor & Beverages",
            "type":"Retail Goods"
        }
    ],
    "sg:postcode":"SW18 1TF",
    "sg:province":"Greater London",
    "sg:tags":[
        "beer",
        "spirit",
        "wines"
    ],
    "wof:name":"Cork Talk",
    "wof:placetype":"venue"
},
  "geometry": {"coordinates":[-0.1883359998,51.4602088928],"type":"Point"}
}