{
  "type": "Feature",
  "properties": {
    "iso:country":"GB",
    "sg:address":"Combe Royal Farm",
    "sg:city":"Kingsbridge",
    "sg:classifiers":[
        {
            "category":"Farming",
            "subcategory":"Dairy Farm",
            "type":"Manufacturing & Wholesale Goods"
        }
    ],
    "sg:postcode":"TQ7 4AD",
    "sg:province":"Devon",
    "wof:name":"J H White",
    "wof:placetype":"venue"
},
  "geometry": {"coordinates":[-3.9158101082,50.3143463135],"type":"Point"}
}