{
  "type": "Feature",
  "properties": {
    "iso:country":"GB",
    "sg:address":"139 Anerley Road",
    "sg:city":"London",
    "sg:classifiers":[
        {
            "category":"Food & Beverages",
            "subcategory":"Liquor & Beverages",
            "type":"Retail Goods"
        }
    ],
    "sg:phone":"+44 20 8778 8323",
    "sg:postcode":"SE20 8EF",
    "sg:province":"Greater London",
    "sg:tags":[
        "beer",
        "spirit",
        "wines"
    ],
    "wof:name":"Neeta's Off Licence",
    "wof:placetype":"venue"
},
  "geometry": {"coordinates":[-0.0658399984,51.4114303589],"type":"Point"}
}