{
  "type": "Feature",
  "properties": {
    "addr:full":"12 Glebe Street Dalkeith City of Edinburgh EH22 1JG",
    "addr:housenumber":"12",
    "addr:postcode":"eh22 1jg",
    "addr:street":"Glebe Street",
    "iso:country":"GB",
    "sg:address":"12 Glebe Street",
    "sg:city":"Dalkeith",
    "sg:classifiers":[
        {
            "category":"Shopping",
            "subcategory":"Bicycles & Sporting Goods",
            "type":"Retail Goods"
        }
    ],
    "sg:phone":"+44 131 654 2162",
    "sg:postcode":"EH22 1JG",
    "sg:province":"City of Edinburgh",
    "sg:tags":[
        "equipment",
        "camping"
    ],
    "wof:name":"Cammo-Badge Discount Military Surplus Co",
    "wof:placetype":"venue"
},
  "geometry": {"coordinates":[-3.0717461109,55.8951454163],"type":"Point"}
}