{
  "type": "Feature",
  "properties": {
    "addr:full":"The Timbers, Cutlers Close Bishops Stortford Essex CM23 4FW",
    "addr:postcode":"cm23 4fw",
    "addr:street":"Cutlers Close",
    "iso:country":"GB",
    "sg:address":"The Timbers, Cutlers Close",
    "sg:city":"Bishops Stortford",
    "sg:classifiers":[
        {
            "category":"Education",
            "subcategory":"Dance Studio",
            "type":"Public Place"
        }
    ],
    "sg:postcode":"CM23 4FW",
    "sg:province":"Essex",
    "sg:tags":[
        "school",
        "dancing"
    ],
    "wof:name":"Barrow Dance Studio",
    "wof:placetype":"venue"
},
  "geometry": {"coordinates":[0.161956,51.872356],"type":"Point"}
}