{
  "type": "Feature",
  "properties": {
    "addr:full":"10 Southgate Street Winchester Hampshire SO23 9EF",
    "addr:housenumber":"10",
    "addr:postcode":"so23 9ef",
    "addr:street":"Southgate Street",
    "iso:country":"GB",
    "sg:address":"10 Southgate Street",
    "sg:city":"Winchester",
    "sg:classifiers":[
        {
            "category":"Banks & Credit Unions",
            "subcategory":"Financial Services",
            "type":"Services"
        }
    ],
    "sg:phone":"+44 1962 852803",
    "sg:postcode":"SO23 9EF",
    "sg:province":"Hampshire",
    "sg:tags":[
        "adviser",
        "consultant"
    ],
    "wof:name":"Emjay Financial Services",
    "wof:placetype":"venue"
},
  "geometry": {"coordinates":[-1.31823,51.061108],"type":"Point"}
}