{
  "type": "Feature",
  "properties": {
    "addr:full":"The Studio, 85a Rowlands Road Worthing West Sussex BN11 3JX",
    "addr:housenumber":"85a",
    "addr:postcode":"bn11 3jx",
    "addr:street":"Rowlands Road",
    "iso:country":"GB",
    "sg:address":"The Studio, 85a Rowlands Road",
    "sg:city":"Worthing",
    "sg:classifiers":[
        {
            "category":"Professional",
            "subcategory":"Advertising",
            "type":"Services"
        },
        {
            "category":"Professional",
            "subcategory":"Art Services",
            "type":"Services"
        }
    ],
    "sg:phone":"+44 1903 209955",
    "sg:postcode":"BN11 3JX",
    "sg:province":"West Sussex",
    "sg:tags":[
        "graphic",
        "agency",
        "designer"
    ],
    "wof:name":"Carter & Partners (Worthing) Ltd.",
    "wof:placetype":"venue"
},
  "geometry": {"coordinates":[-0.375424,50.813625],"type":"Point"}
}