{
  "type": "Feature",
  "properties": {
    "addr:full":"Brackenborough Hall Louth Lincolnshire LN11 0NS",
    "addr:postcode":"ln11 0ns",
    "addr:street":"Louth",
    "iso:country":"GB",
    "sg:address":"Brackenborough Hall",
    "sg:city":"Louth",
    "sg:classifiers":[
        {
            "category":"Farming",
            "subcategory":"Livestock Farm",
            "type":"Manufacturing & Wholesale Goods"
        }
    ],
    "sg:postcode":"LN11 0NS",
    "sg:province":"Lincolnshire",
    "sg:tags":[
        "others"
    ],
    "wof:name":"C R H Bennett & Co.",
    "wof:placetype":"venue"
},
  "geometry": {"coordinates":[0.00635,53.390488],"type":"Point"}
}