{
  "type": "Feature",
  "properties": {
    "addr:full":"Broomhouse Farm, Broomhouse Lane Doncaster South Yorkshire DN12 1EW",
    "addr:postcode":"dn12 1ew",
    "addr:street":"Broomhouse Lane",
    "iso:country":"GB",
    "sg:address":"Broomhouse Farm, Broomhouse Lane",
    "sg:city":"Doncaster",
    "sg:classifiers":[
        {
            "category":"Freight",
            "type":"Transportation"
        }
    ],
    "sg:phone":"+44 1709 862548",
    "sg:postcode":"DN12 1EW",
    "sg:province":"South Yorkshire",
    "sg:tags":[
        "haulage",
        "road"
    ],
    "wof:name":"Roxy H G V",
    "wof:placetype":"venue"
},
  "geometry": {"coordinates":[-1.181608,53.483177],"type":"Point"}
}