{
  "type": "Feature",
  "properties": {
    "addr:full":"113 New Street, Blackrod Bolton Lancashire BL6 5AG",
    "addr:housenumber":"113",
    "addr:postcode":"bl6 5ag",
    "addr:street":"New Street",
    "iso:country":"GB",
    "sg:address":"113 New Street, Blackrod",
    "sg:city":"Bolton",
    "sg:classifiers":[
        {
            "category":"Shopping",
            "subcategory":"Florist",
            "type":"Retail Goods"
        }
    ],
    "sg:postcode":"BL6 5AG",
    "sg:province":"Lancashire",
    "wof:name":"Debbies Flowers",
    "wof:placetype":"venue"
},
  "geometry": {"coordinates":[-2.58020401,53.5923309326],"type":"Point"}
}