{
  "type": "Feature",
  "properties": {
    "addr:full":"47 Weston Road Stoke-on-trent Staffordshire ST3 6AB",
    "addr:housenumber":"47",
    "addr:postcode":"st3 6ab",
    "addr:street":"Weston Road",
    "iso:country":"GB",
    "sg:address":"47 Weston Road",
    "sg:city":"Stoke-on-trent",
    "sg:classifiers":[
        {
            "category":"Personal",
            "subcategory":"Beauty Salon",
            "type":"Services"
        }
    ],
    "sg:phone":"+44 1782 594042",
    "sg:postcode":"ST3 6AB",
    "sg:province":"Staffordshire",
    "sg:tags":[
        "unisex",
        "hairdresser"
    ],
    "wof:name":"The Beauty Box Hair Studio",
    "wof:placetype":"venue"
},
  "geometry": {"coordinates":[-2.103153944,52.9785842896],"type":"Point"}
}