{
  "type": "Feature",
  "properties": {
    "iso:country":"GB",
    "sg:address":"27 Eton Avenue",
    "sg:city":"London",
    "sg:classifiers":[
        {
            "category":"Personal",
            "subcategory":"Beauty Salon",
            "type":"Services"
        }
    ],
    "sg:phone":"+44 20 7435 9855",
    "sg:postcode":"N12 0BD",
    "sg:province":"Greater London",
    "sg:tags":[
        "unisex",
        "hairdresser"
    ],
    "wof:name":"H H  Coiffure Ltd.",
    "wof:placetype":"venue"
},
  "geometry": {"coordinates":[-0.176501,51.607929],"type":"Point"}
}