{
  "type": "Feature",
  "properties": {
    "iso:country":"GB",
    "sg:address":"17 Whitwell Common",
    "sg:city":"Worksop",
    "sg:classifiers":[
        {
            "category":"Shopping",
            "subcategory":"Computers & Home Electronics",
            "type":"Retail Goods"
        }
    ],
    "sg:phone":"+44 1709 720989",
    "sg:postcode":"S80 3LJ",
    "sg:province":"Nottinghamshire",
    "sg:tags":[
        "aerial",
        "television",
        "radio"
    ],
    "wof:name":"Frank Godfrey Ariel & Satellite Specialists",
    "wof:placetype":"venue"
},
  "geometry": {"coordinates":[-1.1231889725,53.3066101074],"type":"Point"}
}