{
  "type": "Feature",
  "properties": {
    "addr:full":"Unit 1 Beaufort Road, Swansea Industrial Estate Swansea Swansea SA6 8JG",
    "addr:housenumber":"unit 1;estate",
    "addr:postcode":"sa6 8jg",
    "addr:street":"Beaufort Road;Industrial",
    "iso:country":"GB",
    "sg:address":"Unit 1 Beaufort Road, Swansea Industrial Estate",
    "sg:city":"Swansea",
    "sg:classifiers":[
        {
            "category":"Shopping",
            "subcategory":"Bicycles & Sporting Goods",
            "type":"Retail Goods"
        }
    ],
    "sg:phone":"+44 1792 796893",
    "sg:postcode":"SA6 8JG",
    "sg:province":"Swansea",
    "sg:tags":[
        "equipment",
        "gym",
        "sport"
    ],
    "wof:name":"Escalade Uk Ltd.",
    "wof:placetype":"venue"
},
  "geometry": {"coordinates":[-3.923893,51.658905],"type":"Point"}
}