{
  "type": "Feature",
  "properties": {
    "iso:country":"GB",
    "sg:address":"122 Bromley Road",
    "sg:city":"London",
    "sg:classifiers":[
        {
            "category":"Professional",
            "subcategory":"Business Services",
            "type":"Services"
        },
        {
            "category":"Casinos & Gambling",
            "type":"Entertainment"
        }
    ],
    "sg:phone":"+44 20 8697 8636",
    "sg:postcode":"SE6 2UN",
    "sg:province":"Greater London",
    "sg:tags":[
        "turf",
        "accountant",
        "bookmaker"
    ],
    "wof:name":"College Racing (Beckenham) Ltd.",
    "wof:placetype":"venue"
},
  "geometry": {"coordinates":[-0.018908,51.437572],"type":"Point"}
}