{
  "type": "Feature",
  "properties": {
    "iso:country":"GB",
    "sg:address":"112 Watnall Rd, Hucknall",
    "sg:city":"Nottingham",
    "sg:classifiers":[
        {
            "category":"Health Services",
            "subcategory":"Doctor",
            "type":"Services"
        }
    ],
    "sg:phone":"+44 115 963 2184",
    "sg:postcode":"NG15 7JP",
    "sg:province":"Nottinghamshire",
    "sg:tags":[
        "practitioners"
    ],
    "wof:name":"A.R Rao",
    "wof:placetype":"venue"
},
  "geometry": {"coordinates":[-1.2051730156,53.0351905823],"type":"Point"}
}