{
  "type": "Feature",
  "properties": {
    "addr:full":"Polladras Carleen Helston Cornwall TR13 9NT",
    "addr:postcode":"tr13 9nt",
    "iso:country":"GB",
    "sg:address":"Polladras Carleen",
    "sg:city":"Helston",
    "sg:classifiers":[
        {
            "category":"Travel",
            "subcategory":"Hotels & Motels",
            "type":"Entertainment"
        }
    ],
    "sg:phone":"+44 1736 763334",
    "sg:postcode":"TR13 9NT",
    "sg:province":"Cornwall",
    "wof:name":"Nemus Ltd.",
    "wof:placetype":"venue"
},
  "geometry": {"coordinates":[-5.2669591904,50.1058197021],"type":"Point"}
}