{
  "type": "Feature",
  "properties": {
    "addr:full":"32 High Newham Court, Hardwick Stockton-on-tees Durham TS19 8PD",
    "addr:housenumber":"32",
    "addr:postcode":"ts19 8pd",
    "addr:street":"High Newham Court",
    "iso:country":"GB",
    "sg:address":"32 High Newham Court, Hardwick",
    "sg:city":"Stockton-on-tees",
    "sg:classifiers":[
        {
            "category":"Personal",
            "subcategory":"Beauty Salon",
            "type":"Services"
        }
    ],
    "sg:phone":"+44 1642 674883",
    "sg:postcode":"TS19 8PD",
    "sg:province":"Durham",
    "sg:tags":[
        "unisex",
        "hairdresser"
    ],
    "wof:name":"Strands Hair Design",
    "wof:placetype":"venue"
},
  "geometry": {"coordinates":[-1.3536549807,54.5830039978],"type":"Point"}
}