{
  "type": "Feature",
  "properties": {
    "iso:country":"GB",
    "sg:address":"Unit 74 Hornby Boulevard",
    "sg:city":"Bootle",
    "sg:classifiers":[
        {
            "category":"Home & Garden",
            "subcategory":"Building Materials",
            "type":"Retail Goods"
        }
    ],
    "sg:phone":"+44 151 922 0348",
    "sg:postcode":"L20 5DX",
    "sg:province":"Merseyside",
    "sg:tags":[
        "dust",
        "extraction",
        "system"
    ],
    "wof:name":"A G Ventilation Ltd.",
    "wof:placetype":"venue"
},
  "geometry": {"coordinates":[-2.9980590343,53.459400177],"type":"Point"}
}