{
  "type": "Feature",
  "properties": {
    "iso:country":"GB",
    "sg:address":"43 Lower Parade",
    "sg:city":"Sutton Coldfield",
    "sg:classifiers":[
        {
            "category":"Education",
            "subcategory":"University",
            "type":"Public Place"
        }
    ],
    "sg:phone":"+44 121 354 4471",
    "sg:postcode":"B72 1XX",
    "sg:province":"West Midlands",
    "sg:tags":[
        "adult"
    ],
    "wof:name":"Sutton Coldfield Adult Education Centre",
    "wof:placetype":"venue"
},
  "geometry": {"coordinates":[-1.823018,52.563225],"type":"Point"}
}