{
  "type": "Feature",
  "properties": {
    "iso:country":"GB",
    "sg:address":"Old Castle, Cross Gates",
    "sg:city":"Llandrindod Wells",
    "sg:classifiers":[
        {
            "category":"Farming",
            "subcategory":"Livestock Farm",
            "type":"Manufacturing & Wholesale Goods"
        },
        {
            "category":"Farming",
            "subcategory":"Farm",
            "type":"Manufacturing & Wholesale Goods"
        }
    ],
    "sg:phone":"+44 1597 851604",
    "sg:postcode":"LD1 5TT",
    "sg:province":"Powys",
    "sg:tags":[
        "mixed",
        "crop",
        "others"
    ],
    "wof:name":"J W Bufton",
    "wof:placetype":"venue"
},
  "geometry": {"coordinates":[-3.377029,52.24575],"type":"Point"}
}