{
  "type": "Feature",
  "properties": {
    "addr:full":"3 Bridge Road, Park Gate Southampton Hampshire SO31 7GD",
    "addr:housenumber":"3",
    "addr:postcode":"so31 7gd",
    "addr:street":"Bridge Road",
    "iso:country":"GB",
    "sg:address":"3 Bridge Road, Park Gate",
    "sg:city":"Southampton",
    "sg:classifiers":[
        {
            "category":"Bars & Pubs",
            "type":"Food & Drink"
        }
    ],
    "sg:phone":"+44 1489 572614",
    "sg:postcode":"SO31 7GD",
    "sg:province":"Hampshire",
    "sg:tags":[
        "pubs",
        "inn"
    ],
    "wof:name":"The Talisman",
    "wof:placetype":"venue"
},
  "geometry": {"coordinates":[-1.268251,50.871773],"type":"Point"}
}