{
  "type": "Feature",
  "properties": {
    "iso:country":"GB",
    "sg:address":"2 Witheyhate Avenue",
    "sg:city":"Staines",
    "sg:classifiers":[
        {
            "category":"Mining & Drilling",
            "type":"Manufacturing & Wholesale Goods"
        }
    ],
    "sg:phone":"+44 1784 456013",
    "sg:postcode":"TW18 2RA",
    "sg:province":"Berkshire",
    "sg:tags":[
        "contractor"
    ],
    "wof:name":"Diacore Concrete Cutting Ltd.",
    "wof:placetype":"venue"
},
  "geometry": {"coordinates":[-0.496529,51.41769],"type":"Point"}
}