{
  "type": "Feature",
  "properties": {
    "iso:country":"GB",
    "sg:address":"3 The Glen",
    "sg:city":"Southall",
    "sg:classifiers":[
        {
            "category":"Professional",
            "subcategory":"Accounting & Tax Preparation",
            "type":"Services"
        }
    ],
    "sg:phone":"+44 20 8843 0009",
    "sg:postcode":"UB2 5RS",
    "sg:province":"Greater London",
    "sg:tags":[
        "accountant"
    ],
    "wof:name":"A S T Chartered Accountants",
    "wof:placetype":"venue"
},
  "geometry": {"coordinates":[-0.3753969967,51.4929847717],"type":"Point"}
}