{
  "type": "Feature",
  "properties": {
    "iso:country":"GB",
    "sg:address":"25 North Park",
    "sg:city":"Mansfield",
    "sg:classifiers":[
        {
            "category":"Professional",
            "subcategory":"Engineering",
            "type":"Services"
        }
    ],
    "sg:phone":"+44 1623 429057",
    "sg:postcode":"NG18 4PB",
    "sg:province":"Nottinghamshire",
    "sg:tags":[
        "acoustic",
        "design",
        "engineer"
    ],
    "wof:name":"Alpha Installations Ltd.",
    "wof:placetype":"venue"
},
  "geometry": {"coordinates":[-1.16922,53.12648],"type":"Point"}
}