{
  "type": "Feature",
  "properties": {
    "iso:country":"GB",
    "sg:address":"1 The Mall, Ringwood Road, Burley",
    "sg:city":"Ringwood",
    "sg:classifiers":[
        {
            "category":"Real Estate",
            "subcategory":"Real Estate Agent",
            "type":"Services"
        }
    ],
    "sg:phone":"+44 1425 403600",
    "sg:postcode":"BH24 4AD",
    "sg:province":"Dorset",
    "wof:name":"Fells Gulliver Estate Agents",
    "wof:placetype":"venue"
},
  "geometry": {"coordinates":[-1.702023983,50.8268356323],"type":"Point"}
}