{
  "type": "Feature",
  "properties": {
    "iso:country":"GB",
    "sg:address":"Henfwlch Road",
    "sg:city":"Carmarthen",
    "sg:classifiers":[
        {
            "category":"Sports & Exercise",
            "subcategory":"Stables",
            "type":"Entertainment"
        }
    ],
    "sg:phone":"+44 1267 238409",
    "sg:postcode":"SA33 6AJ",
    "sg:province":"Carmarthenshire",
    "sg:tags":[
        "education",
        "equestrian"
    ],
    "wof:name":"Flying M Ranch",
    "wof:placetype":"venue"
},
  "geometry": {"coordinates":[-4.36802,51.872131],"type":"Point"}
}