{
  "type": "Feature",
  "properties": {
    "addr:full":"School Lane Lymington Hampshire SO41 5QE",
    "addr:postcode":"so41 5qe",
    "addr:street":"School Lane",
    "iso:country":"GB",
    "sg:address":"School Lane",
    "sg:city":"Lymington",
    "sg:classifiers":[
        {
            "category":"Home & Garden",
            "subcategory":"Garden Supply",
            "type":"Retail Goods"
        }
    ],
    "sg:postcode":"SO41 5QE",
    "sg:province":"Hampshire",
    "sg:tags":[
        "nursery",
        "centre"
    ],
    "wof:name":"Spinners Garden & Rare Plant Nursery",
    "wof:placetype":"venue"
},
  "geometry": {"coordinates":[-1.5402159691,50.7800331116],"type":"Point"}
}