{
  "type": "Feature",
  "properties": {
    "iso:country":"GB",
    "sg:address":"Cemetry Road",
    "sg:city":"Barnsley",
    "sg:classifiers":[
        {
            "category":"Autos & Motor Vehicles",
            "subcategory":"Auto Supplies",
            "type":"Retail Goods"
        }
    ],
    "sg:phone":"+44 1226 295171",
    "sg:postcode":"S70 1XR",
    "sg:province":"South Yorkshire",
    "sg:tags":[
        "tyre"
    ],
    "wof:name":"Malcolm'S Tyre & Exhaust Services",
    "wof:placetype":"venue"
},
  "geometry": {"coordinates":[-1.471019,53.546844],"type":"Point"}
}