{
  "type": "Feature",
  "properties": {
    "iso:country":"GB",
    "sg:address":"Combe Wood, Combe St Nicholas",
    "sg:city":"Chard",
    "sg:classifiers":[
        {
            "category":"Professional",
            "subcategory":"Engineering",
            "type":"Services"
        }
    ],
    "sg:phone":"+44 1460 67351",
    "sg:postcode":"TA20 3NL",
    "sg:province":"Devon",
    "sg:tags":[
        "precision",
        "engineer"
    ],
    "wof:name":"Colin Mear Engineering Ltd.",
    "wof:placetype":"venue"
},
  "geometry": {"coordinates":[-2.99484,50.895374],"type":"Point"}
}