{
  "type": "Feature",
  "properties": {
    "addr:full":"Vicarage Hill Redruth Cornwall TR16 5PJ",
    "addr:postcode":"tr16 5pj",
    "addr:street":"Vicarage Hill",
    "iso:country":"GB",
    "sg:address":"Vicarage Hill",
    "sg:city":"Redruth",
    "sg:classifiers":[
        {
            "category":"Food & Beverages",
            "subcategory":"Meat & Fish",
            "type":"Retail Goods"
        }
    ],
    "sg:phone":"+44 1209 820308",
    "sg:postcode":"TR16 5PJ",
    "sg:province":"Cornwall",
    "sg:tags":[
        "butcher"
    ],
    "wof:name":"B C Braddon",
    "wof:placetype":"venue"
},
  "geometry": {"coordinates":[-5.1797537804,50.2391853333],"type":"Point"}
}