{
  "type": "Feature",
  "properties": {
    "addr:full":"Botany Avenue Mansfield Nottinghamshire NG18 5NG",
    "addr:postcode":"ng18 5ng",
    "addr:street":"Botany Avenue",
    "iso:country":"GB",
    "sg:address":"Botany Avenue",
    "sg:city":"Mansfield",
    "sg:classifiers":[
        {
            "category":"Building & Trades",
            "subcategory":"Construction",
            "type":"Services"
        }
    ],
    "sg:phone":"+44 1623 652494",
    "sg:postcode":"NG18 5NG",
    "sg:province":"Nottinghamshire",
    "sg:tags":[
        "roofing"
    ],
    "wof:name":"R F W (Midlands) Ltd.",
    "wof:placetype":"venue"
},
  "geometry": {"coordinates":[-1.211729,53.144585],"type":"Point"}
}