{
  "type": "Feature",
  "properties": {
    "iso:country":"GB",
    "sg:address":"Brynheulog, Llanarthney",
    "sg:city":"Carmarthen",
    "sg:classifiers":[
        {
            "category":"Building & Trades",
            "subcategory":"Construction",
            "type":"Services"
        }
    ],
    "sg:postcode":"SA32 8JD",
    "sg:province":"Carmarthenshire",
    "sg:tags":[
        "builder",
        "repairer",
        "chimney"
    ],
    "wof:name":"Cico",
    "wof:placetype":"venue"
},
  "geometry": {"coordinates":[-4.129837,51.861176],"type":"Point"}
}