{
  "type": "Feature",
  "properties": {
    "addr:full":"7 Cryalls La Sittingbourne Kent ME10 1NU",
    "addr:housenumber":"7",
    "addr:postcode":"me10 1nu",
    "addr:street":"Cryalls La Sittingbourne",
    "iso:country":"GB",
    "sg:address":"7 Cryalls La",
    "sg:city":"Sittingbourne",
    "sg:classifiers":[
        {
            "category":"Building & Trades",
            "subcategory":"Plumbing",
            "type":"Services"
        }
    ],
    "sg:phone":"+44 1795 470977",
    "sg:postcode":"ME10 1NU",
    "sg:province":"Kent",
    "sg:tags":[
        "heating"
    ],
    "wof:name":"Ash Plumbing",
    "wof:placetype":"venue"
},
  "geometry": {"coordinates":[0.717433989,51.3428993225],"type":"Point"}
}