{
  "type": "Feature",
  "properties": {
    "addr:full":"31 Buccleuch Place Edinburgh City of Edinburgh EH8 9JT",
    "addr:housenumber":"31",
    "addr:postcode":"eh8 9jt",
    "addr:street":"Buccleuch Place Edinburgh",
    "iso:country":"GB",
    "sg:address":"31 Buccleuch Place",
    "sg:city":"Edinburgh",
    "sg:classifiers":[
        {
            "category":"Professional",
            "subcategory":"Business Services",
            "type":"Services"
        }
    ],
    "sg:phone":"+44 131 662 1321",
    "sg:postcode":"EH8 9JT",
    "sg:province":"City of Edinburgh",
    "sg:tags":[
        "import",
        "export",
        "agent"
    ],
    "wof:name":"The Institute For Study Abroad",
    "wof:placetype":"venue"
},
  "geometry": {"coordinates":[-3.184994,55.943275],"type":"Point"}
}