{
  "type": "Feature",
  "properties": {
    "addr:full":"53 Handsworth Road Sheffield South Yorkshire S9 4AA",
    "addr:housenumber":"53",
    "addr:postcode":"s9 4aa",
    "addr:street":"Handsworth Road",
    "iso:country":"GB",
    "sg:address":"53 Handsworth Road",
    "sg:city":"Sheffield",
    "sg:classifiers":[
        {
            "category":"Professional",
            "subcategory":"Engineering",
            "type":"Services"
        }
    ],
    "sg:phone":"+44 114 244 1310",
    "sg:postcode":"S9 4AA",
    "sg:province":"South Yorkshire",
    "sg:tags":[
        "precision",
        "engineer"
    ],
    "wof:name":"Handsworth Precision Tools",
    "wof:placetype":"venue"
},
  "geometry": {"coordinates":[-1.39865,53.380428],"type":"Point"}
}