{
  "type": "Feature",
  "properties": {
    "addr:full":"Unit 8, Carwhinny Mitchelston Drive, Mitchelston Industrial Estate Kirkcaldy Fife KY1 3NF",
    "addr:housenumber":"unit 8",
    "addr:postcode":"ky1 3nf",
    "addr:street":"Mitchelston Drive Mitchelston Industrial Estate",
    "iso:country":"GB",
    "sg:address":"Unit 8, Carwhinny Mitchelston Drive, Mitchelston Industrial Estate",
    "sg:city":"Kirkcaldy",
    "sg:classifiers":[
        {
            "category":"Building & Trades",
            "subcategory":"Electrical",
            "type":"Services"
        }
    ],
    "sg:phone":"+44 1592 597598",
    "sg:postcode":"KY1 3NF",
    "sg:province":"Fife",
    "sg:tags":[
        "consultant",
        "lighting"
    ],
    "wof:name":"Eness Lighting Systems",
    "wof:placetype":"venue"
},
  "geometry": {"coordinates":[-3.1420259476,56.1391334534],"type":"Point"}
}