{
  "type": "Feature",
  "properties": {
    "iso:country":"GB",
    "sg:address":"2 Chapel Rd",
    "sg:city":"Ilford",
    "sg:classifiers":[
        {
            "category":"Shopping",
            "subcategory":"News",
            "type":"Retail Goods"
        }
    ],
    "sg:postcode":"IG1 2AG",
    "sg:province":"Essex",
    "sg:tags":[
        "newsagent"
    ],
    "wof:name":"Arslan,Z,",
    "wof:placetype":"venue"
},
  "geometry": {"coordinates":[0.06999,51.557629],"type":"Point"}
}