{
  "type": "Feature",
  "properties": {
    "iso:country":"GB",
    "sg:address":"Dewsbury Road",
    "sg:city":"Ossett",
    "sg:classifiers":[
        {
            "category":"Food & Beverages",
            "subcategory":"Meat & Fish",
            "type":"Retail Goods"
        }
    ],
    "sg:phone":"+44 1924 281771",
    "sg:postcode":"WF5 9PE",
    "sg:province":"West Yorkshire",
    "sg:tags":[
        "chip"
    ],
    "wof:name":"Wards Fisheries",
    "wof:placetype":"venue"
},
  "geometry": {"coordinates":[-1.590844,53.691502],"type":"Point"}
}