{
  "type": "Feature",
  "properties": {
    "addr:full":"A303 Camel Hill, Queen Camel Yeovil Dorset BA22 7PH",
    "addr:postcode":"ba22 7ph",
    "addr:street":"Camel Hill Queen",
    "iso:country":"GB",
    "sg:address":"A303 Camel Hill, Queen Camel",
    "sg:city":"Yeovil",
    "sg:classifiers":[
        {
            "category":"Restaurant",
            "type":"Food & Drink"
        }
    ],
    "sg:phone":"+44 1935 850542",
    "sg:postcode":"BA22 7PH",
    "sg:province":"Dorset",
    "wof:name":"Little Chef",
    "wof:placetype":"venue"
},
  "geometry": {"coordinates":[-2.494081,51.03772],"type":"Point"}
}