{
  "type": "Feature",
  "properties": {
    "addr:full":"18a St Georges Road, Bletchley Milton Keynes Buckinghamshire MK3 5ES",
    "addr:housenumber":"18a",
    "addr:postcode":"mk3 5es",
    "addr:street":"St Georges Road",
    "iso:country":"GB",
    "sg:address":"18a St Georges Road, Bletchley",
    "sg:city":"Milton Keynes",
    "sg:classifiers":[
        {
            "category":"Social Services",
            "subcategory":"Child Care",
            "type":"Services"
        }
    ],
    "sg:phone":"+44 1908 374527",
    "sg:postcode":"MK3 5ES",
    "sg:province":"Buckinghamshire",
    "sg:tags":[
        "children's",
        "home"
    ],
    "wof:name":"St. Georges Road Childrens Home",
    "wof:placetype":"venue"
},
  "geometry": {"coordinates":[-0.7613809705,51.989112854],"type":"Point"}
}