{
  "type": "Feature",
  "properties": {
    "iso:country":"GB",
    "sg:address":"109 High St",
    "sg:city":"Ongar",
    "sg:classifiers":[
        {
            "category":"Communications",
            "type":"Services"
        }
    ],
    "sg:postcode":"CM5 9DX",
    "sg:province":"Essex",
    "sg:tags":[
        "tv",
        "video",
        "radio"
    ],
    "wof:name":"Scott,Edwin T,",
    "wof:placetype":"venue"
},
  "geometry": {"coordinates":[0.244604,51.702896],"type":"Point"}
}