{
  "type": "Feature",
  "properties": {
    "iso:country":"GB",
    "sg:address":"101 Cheriton Rd",
    "sg:city":"Folkestone",
    "sg:classifiers":[
        {
            "category":"Education",
            "subcategory":"University",
            "type":"Public Place"
        }
    ],
    "sg:postcode":"CT19 5HD",
    "sg:province":"Kent",
    "sg:tags":[
        "higher"
    ],
    "wof:name":"Big Red L Co (The)",
    "wof:placetype":"venue"
},
  "geometry": {"coordinates":[1.170192,51.083134],"type":"Point"}
}