{
  "type": "Feature",
  "properties": {
    "addr:full":"Ty'r Felin, Lower Mill Field Pontypool Monmouthshire NP4 0XE",
    "addr:postcode":"np4 0xe",
    "addr:street":"Felin Lower Mill Field",
    "iso:country":"GB",
    "sg:address":"Ty'r Felin, Lower Mill Field",
    "sg:city":"Pontypool",
    "sg:classifiers":[
        {
            "category":"Government",
            "subcategory":"Office",
            "type":"Public Place"
        }
    ],
    "sg:postcode":"NP4 0XE",
    "sg:province":"Monmouthshire",
    "sg:tags":[
        "inland",
        "revenue"
    ],
    "wof:name":"Board of Inland Revenue",
    "wof:placetype":"venue"
},
  "geometry": {"coordinates":[-3.02157,51.694759],"type":"Point"}
}