{
  "type": "Feature",
  "properties": {
    "addr:full":"Compass House, 30-36 East St Bromley Kent BR1 1QU",
    "addr:housenumber":"30-36",
    "addr:postcode":"br1 1qu",
    "addr:street":"East St",
    "iso:country":"GB",
    "sg:address":"Compass House, 30-36 East St",
    "sg:city":"Bromley",
    "sg:classifiers":[
        {
            "category":"Communications",
            "subcategory":"Newspaper",
            "type":"Services"
        }
    ],
    "sg:phone":"+44 20 8289 9191",
    "sg:postcode":"BR1 1QU",
    "sg:province":"Kent",
    "sg:tags":[
        "magazine"
    ],
    "wof:name":"Success Now",
    "wof:placetype":"venue"
},
  "geometry": {"coordinates":[0.016375,51.407085],"type":"Point"}
}