{
  "type": "Feature",
  "properties": {
    "addr:full":"250 Hawes La West Wickham Kent BR4 9AQ",
    "addr:housenumber":"250",
    "addr:postcode":"br4 9aq",
    "addr:street":"Hawes La West Wickham",
    "iso:country":"GB",
    "sg:address":"250 Hawes La",
    "sg:city":"West Wickham",
    "sg:classifiers":[
        {
            "category":"Building & Trades",
            "subcategory":"Construction",
            "type":"Services"
        }
    ],
    "sg:phone":"+44 20 8777 3282",
    "sg:postcode":"BR4 9AQ",
    "sg:province":"Kent",
    "sg:tags":[
        "builder"
    ],
    "wof:name":"Beerlings Ltd",
    "wof:placetype":"venue"
},
  "geometry": {"coordinates":[-0.002349,51.373238],"type":"Point"}
}