{
  "type": "Feature",
  "properties": {
    "iso:country":"GB",
    "sg:address":"74 King Street, Drighlington",
    "sg:city":"Bradford",
    "sg:classifiers":[
        {
            "category":"Autos & Motor Vehicles",
            "subcategory":"Automobile Sales",
            "type":"Retail Goods"
        },
        {
            "category":"Home & Garden",
            "subcategory":"Hardware",
            "type":"Retail Goods"
        }
    ],
    "sg:phone":"+44 113 285 3878",
    "sg:postcode":"BD11 1EL",
    "sg:province":"West Yorkshire",
    "sg:tags":[
        "lighting",
        "commercial",
        "retailer"
    ],
    "wof:name":"PETER DENNING COMMERCIALS",
    "wof:placetype":"venue"
},
  "geometry": {"coordinates":[-1.657028,53.754185],"type":"Point"}
}