{
  "type": "Feature",
  "properties": {
    "addr:full":"110 Yateley Ave, Great Barr Birmingham West Midlands B42 1JL",
    "addr:housenumber":"110",
    "addr:postcode":"b42 1jl",
    "addr:street":"Yateley Ave",
    "iso:country":"GB",
    "sg:address":"110 Yateley Ave, Great Barr",
    "sg:city":"Birmingham",
    "sg:classifiers":[
        {
            "category":"Building & Trades",
            "subcategory":"Cleaning & Sanitation",
            "type":"Services"
        }
    ],
    "sg:postcode":"B42 1JL",
    "sg:province":"West Midlands",
    "sg:tags":[
        "dry",
        "control",
        "damp",
        "rot"
    ],
    "wof:name":"Beechwood Timber Preservation",
    "wof:placetype":"venue"
},
  "geometry": {"coordinates":[-1.9222639799,52.5354385376],"type":"Point"}
}