{
  "type": "Feature",
  "properties": {
    "addr:full":"Albion Road, Sandhurst Camberley Berkshire GU47 9BP",
    "addr:postcode":"gu47 9bp",
    "addr:street":"Albion Road",
    "iso:country":"GB",
    "sg:address":"Albion Road, Sandhurst",
    "sg:city":"Camberley",
    "sg:classifiers":[
        {
            "category":"Education",
            "subcategory":"School",
            "type":"Public Place"
        }
    ],
    "sg:phone":"+44 1252 873069",
    "sg:postcode":"GU47 9BP",
    "sg:province":"Berkshire",
    "sg:tags":[
        "local",
        "authority"
    ],
    "wof:name":"Uplands County Primary School",
    "wof:placetype":"venue"
},
  "geometry": {"coordinates":[-0.797604,51.347229],"type":"Point"}
}