{
  "type": "Feature",
  "properties": {
    "addr:full":"109 Haigh Road, Aspull Wigan Lancashire WN2 1RP",
    "addr:housenumber":"109",
    "addr:postcode":"wn2 1rp",
    "addr:street":"Haigh Road Aspull",
    "iso:country":"GB",
    "sg:address":"109 Haigh Road, Aspull",
    "sg:city":"Wigan",
    "sg:classifiers":[
        {
            "category":"Parking",
            "type":"Transportation"
        }
    ],
    "sg:phone":"+44 1942 833261",
    "sg:postcode":"WN2 1RP",
    "sg:province":"Lancashire",
    "sg:tags":[
        "car",
        "valet"
    ],
    "wof:name":"Alf Sharples",
    "wof:placetype":"venue"
},
  "geometry": {"coordinates":[-2.5913150311,53.5733947754],"type":"Point"}
}