{
  "type": "Feature",
  "properties": {
    "addr:full":"Unit 1 Spring Lane South Malvern Herefordshire WR14 1AQ",
    "addr:housenumber":"unit 1",
    "addr:postcode":"wr14 1aq",
    "addr:street":"Spring Lane",
    "iso:country":"GB",
    "sg:address":"Unit 1 Spring Lane South",
    "sg:city":"Malvern",
    "sg:classifiers":[
        {
            "category":"Freight",
            "type":"Transportation"
        }
    ],
    "sg:postcode":"WR14 1AQ",
    "sg:province":"Herefordshire",
    "sg:tags":[
        "haulage",
        "road"
    ],
    "wof:name":"Miles Transport Services (Ledbury) Ltd.",
    "wof:placetype":"venue"
},
  "geometry": {"coordinates":[-2.3059079647,52.1253128052],"type":"Point"}
}