{
  "type": "Feature",
  "properties": {
    "addr:full":"The Walnuts, Trout Road West Drayton Greater London UB7 7RS",
    "addr:postcode":"ub7 7rs",
    "addr:street":"The Walnuts Trout Road",
    "iso:country":"GB",
    "sg:address":"The Walnuts, Trout Road",
    "sg:city":"West Drayton",
    "sg:classifiers":[
        {
            "category":"Retail",
            "subcategory":"Auto Repair",
            "type":"Services"
        }
    ],
    "sg:phone":"+44 1895 440615",
    "sg:postcode":"UB7 7RS",
    "sg:province":"Greater London",
    "sg:tags":[
        "body",
        "car"
    ],
    "wof:name":"Hillingdon Auto's",
    "wof:placetype":"venue"
},
  "geometry": {"coordinates":[-0.4739899933,51.5091171265],"type":"Point"}
}