{
  "type": "Feature",
  "properties": {
    "iso:country":"GB",
    "sg:address":"Unit 26 The Steadings Business C, Entre Maisemore",
    "sg:city":"Gloucester",
    "sg:classifiers":[
        {
            "category":"Building & Trades",
            "subcategory":"Construction",
            "type":"Services"
        }
    ],
    "sg:phone":"+44 1452 421234",
    "sg:postcode":"GL2 8EY",
    "sg:province":"Gloucestershire",
    "sg:tags":[
        "supplier",
        "installers",
        "cladding"
    ],
    "wof:name":"Gasell Profiles Ltd.",
    "wof:placetype":"venue"
},
  "geometry": {"coordinates":[-2.2745139599,51.8896713257],"type":"Point"}
}