{
  "type": "Feature",
  "properties": {
    "addr:full":"14 Cotman Court, Farquhar Road London Greater London SE19 1SN",
    "addr:housenumber":"14",
    "addr:postcode":"se19 1sn",
    "addr:street":"Cotman Court Farquhar Road",
    "iso:country":"GB",
    "sg:address":"14 Cotman Court, Farquhar Road",
    "sg:city":"London",
    "sg:classifiers":[
        {
            "category":"Communications",
            "subcategory":"Television Station",
            "type":"Services"
        }
    ],
    "sg:postcode":"SE19 1SN",
    "sg:province":"Greater London",
    "sg:tags":[
        "video"
    ],
    "wof:name":"Proline Ltd",
    "wof:placetype":"venue"
},
  "geometry": {"coordinates":[-0.0790399984,51.4232902527],"type":"Point"}
}