{
  "type": "Feature",
  "properties": {
    "iso:country":"GB",
    "sg:address":"114 Wymomdley Road",
    "sg:city":"Hitchin",
    "sg:classifiers":[
        {
            "category":"Professional",
            "subcategory":"Accounting & Tax Preparation",
            "type":"Services"
        }
    ],
    "sg:phone":"+44 1462 458591",
    "sg:postcode":"SG4 9PX",
    "sg:province":"Hertfordshire",
    "sg:tags":[
        "consultant"
    ],
    "wof:name":"Derek Hewson & Associates Ltd.",
    "wof:placetype":"venue"
},
  "geometry": {"coordinates":[-0.2568300068,51.9450836182],"type":"Point"}
}