{
  "type": "Feature",
  "properties": {
    "iso:country":"GB",
    "sg:address":"Ellerbeck Ho, Ellerbeck Way, Stokesley Industrial Stokesley",
    "sg:city":"Middlesbrough",
    "sg:classifiers":[
        {
            "category":"Professional",
            "subcategory":"Engineering",
            "type":"Services"
        }
    ],
    "sg:postcode":"TS9 5JZ",
    "sg:province":"North Yorkshire",
    "sg:tags":[
        "contractor",
        "electrical",
        "engineer"
    ],
    "wof:name":"A C Electrical & Data (U K) Ltd",
    "wof:placetype":"venue"
},
  "geometry": {"coordinates":[-1.18879,54.470703],"type":"Point"}
}