{
  "type": "Feature",
  "properties": {
    "iso:country":"GB",
    "sg:address":"54 Lowestoft Rd, Carlton Colville",
    "sg:city":"Lowestoft",
    "sg:classifiers":[
        {
            "category":"Home & Garden",
            "subcategory":"Building Materials",
            "type":"Retail Goods"
        }
    ],
    "sg:phone":"+44 1502 572144",
    "sg:postcode":"NR33 8JB",
    "sg:province":"Suffolk",
    "sg:tags":[
        "gate",
        "door",
        "barrier"
    ],
    "wof:name":"R & S Installations",
    "wof:placetype":"venue"
},
  "geometry": {"coordinates":[1.703499,52.452667],"type":"Point"}
}