{
  "type": "Feature",
  "properties": {
    "addr:full":"27 Victoria Grove Southsea Hampshire PO5 1NF",
    "addr:housenumber":"27",
    "addr:postcode":"po5 1nf",
    "addr:street":"Victoria Grove",
    "iso:country":"GB",
    "sg:address":"27 Victoria Grove",
    "sg:city":"Southsea",
    "sg:classifiers":[
        {
            "category":"Professional",
            "subcategory":"Engineering",
            "type":"Services"
        },
        {
            "category":"Building & Trades",
            "subcategory":"Construction",
            "type":"Services"
        }
    ],
    "sg:phone":"+44 23 9281 4285",
    "sg:postcode":"PO5 1NF",
    "sg:province":"Hampshire",
    "sg:tags":[
        "installers",
        "gas",
        "engineer"
    ],
    "wof:name":"Southsea Gas",
    "wof:placetype":"venue"
},
  "geometry": {"coordinates":[-1.0795789957,50.789100647],"type":"Point"}
}