{
  "type": "Feature",
  "properties": {
    "addr:full":"Stanley Green Road Poole Dorset BH15 3AA",
    "addr:postcode":"bh15 3aa",
    "addr:street":"Stanley Green Road",
    "iso:country":"GB",
    "sg:address":"Stanley Green Road",
    "sg:city":"Poole",
    "sg:classifiers":[
        {
            "category":"Education",
            "subcategory":"School",
            "type":"Public Place"
        }
    ],
    "sg:phone":"+44 1202 778181",
    "sg:postcode":"BH15 3AA",
    "sg:province":"Dorset",
    "sg:tags":[
        "local",
        "authority"
    ],
    "wof:name":"Stanley Green First School",
    "wof:placetype":"venue"
},
  "geometry": {"coordinates":[-1.9813539982,50.7356109619],"type":"Point"}
}