{
  "type": "Feature",
  "properties": {
    "iso:country":"GB",
    "sg:address":"Parton Road, Churchdown",
    "sg:city":"Gloucester",
    "sg:classifiers":[
        {
            "category":"Education",
            "subcategory":"Library",
            "type":"Public Place"
        },
        {
            "category":"Government",
            "subcategory":"Office",
            "type":"Public Place"
        }
    ],
    "sg:phone":"+44 1452 712504",
    "sg:postcode":"GL3 2AF",
    "sg:province":"Gloucestershire",
    "sg:tags":[
        "book",
        "local"
    ],
    "wof:name":"Churchdown Library",
    "wof:placetype":"venue"
},
  "geometry": {"coordinates":[-2.172489,51.876392],"type":"Point"}
}