{
  "type": "Feature",
  "properties": {
    "addr:full":"147 Birkbeck Road Sidcup Kent DA14 4DJ",
    "addr:housenumber":"147",
    "addr:postcode":"da14 4dj",
    "addr:street":"Birkbeck Road",
    "iso:country":"GB",
    "sg:address":"147 Birkbeck Road",
    "sg:city":"Sidcup",
    "sg:classifiers":[
        {
            "category":"Retail",
            "subcategory":"Auto Repair",
            "type":"Services"
        }
    ],
    "sg:phone":"+44 20 8308 0033",
    "sg:postcode":"DA14 4DJ",
    "sg:province":"Kent",
    "sg:tags":[
        "modification",
        "garage"
    ],
    "wof:name":"P D Q Car Services",
    "wof:placetype":"venue"
},
  "geometry": {"coordinates":[0.1058180034,51.4311065674],"type":"Point"}
}