{
  "type": "Feature",
  "properties": {
    "addr:full":"Unit 7 Greendykes Industrial Estate, Greendykes Industrial Estate Broxburn City of Edinburgh EH52 6PG",
    "addr:housenumber":"unit 7",
    "addr:postcode":"eh52 6pg",
    "addr:street":"Greendykes Industrial Estate Greendykes Industrial Estate",
    "iso:country":"GB",
    "sg:address":"Unit 7 Greendykes Industrial Estate, Greendykes Industrial Estate",
    "sg:city":"Broxburn",
    "sg:classifiers":[
        {
            "category":"Manufacturing",
            "subcategory":"Petroleum Products",
            "type":"Manufacturing & Wholesale Goods"
        },
        {
            "category":"Building & Trades",
            "subcategory":"Construction",
            "type":"Services"
        }
    ],
    "sg:phone":"+44 1506 854248",
    "sg:postcode":"EH52 6PG",
    "sg:province":"City of Edinburgh",
    "sg:tags":[
        "double",
        "glazing",
        "installers"
    ],
    "wof:name":"Illingworth Bros",
    "wof:placetype":"venue"
},
  "geometry": {"coordinates":[-3.4723889828,55.9402503967],"type":"Point"}
}