{
  "type": "Feature",
  "properties": {
    "iso:country":"GB",
    "sg:address":"5 Edinburgh Road",
    "sg:city":"Penicuik",
    "sg:classifiers":[
        {
            "category":"Fast Food",
            "type":"Food & Drink"
        }
    ],
    "sg:phone":"+44 1968 678666",
    "sg:postcode":"EH26 8NP",
    "sg:province":"Midlothian",
    "sg:tags":[
        "away",
        "take"
    ],
    "wof:name":"The Jade Palace",
    "wof:placetype":"venue"
},
  "geometry": {"coordinates":[-3.2206740379,55.8352165222],"type":"Point"}
}