{
  "type": "Feature",
  "properties": {
    "iso:country":"GB",
    "sg:address":"Unit 1, Brickfields Way",
    "sg:city":"Thetford",
    "sg:classifiers":[
        {
            "category":"Sports & Exercise",
            "subcategory":"Golf",
            "type":"Entertainment"
        }
    ],
    "sg:phone":"+44 1842 751151",
    "sg:postcode":"IP24 1HX",
    "sg:province":"Norfolk",
    "sg:tags":[
        "greeting",
        "card"
    ],
    "wof:name":"Cartel International Ltd",
    "wof:placetype":"venue"
},
  "geometry": {"coordinates":[0.7461090088,52.4242248535],"type":"Point"}
}