{
  "type": "Feature",
  "properties": {
    "iso:country":"GB",
    "sg:address":"Oak Farm, Church Road, Baginton",
    "sg:city":"Coventry",
    "sg:classifiers":[
        {
            "category":"Farming",
            "subcategory":"Livestock Farm",
            "type":"Manufacturing & Wholesale Goods"
        }
    ],
    "sg:postcode":"CV8 3AR",
    "sg:province":"Warwickshire",
    "sg:tags":[
        "others"
    ],
    "wof:name":"Marguerite P Russell",
    "wof:placetype":"venue"
},
  "geometry": {"coordinates":[-1.493049,52.371735],"type":"Point"}
}