{
  "type": "Feature",
  "properties": {
    "iso:country":"GB",
    "sg:address":"Woolverstone House, 61-62 Berners Street",
    "sg:city":"West End",
    "sg:classifiers":[
        {
            "category":"Professional",
            "subcategory":"Advertising",
            "type":"Services"
        }
    ],
    "sg:phone":"+44 20 7636 6130",
    "sg:postcode":"W1P 3AE",
    "sg:province":"Hampshire",
    "wof:name":"Eurobest",
    "wof:placetype":"venue"
},
  "geometry": {"coordinates":[-0.13899,51.50758],"type":"Point"}
}