{
  "type": "Feature",
  "properties": {
    "addr:full":"St James Square, Boroughbridge York North Yorkshire YO51 9AR",
    "addr:postcode":"yo51 9ar",
    "addr:street":"St James Square",
    "iso:country":"GB",
    "sg:address":"St James Square, Boroughbridge",
    "sg:city":"York",
    "sg:classifiers":[
        {
            "category":"Professional",
            "subcategory":"Lawyer & Legal Services",
            "type":"Services"
        }
    ],
    "sg:phone":"+44 1423 324323",
    "sg:postcode":"YO51 9AR",
    "sg:province":"North Yorkshire",
    "sg:tags":[
        "solicitor"
    ],
    "wof:name":"Beecroft Lane & Co",
    "wof:placetype":"venue"
},
  "geometry": {"coordinates":[-1.3949209452,54.0941963196],"type":"Point"}
}