{
  "type": "Feature",
  "properties": {
    "addr:full":"80 Upton Close, Barnwood Gloucester Gloucestershire GL4 3EZ",
    "addr:housenumber":"80",
    "addr:postcode":"gl4 3ez",
    "addr:street":"Upton Close",
    "iso:country":"GB",
    "sg:address":"80 Upton Close, Barnwood",
    "sg:city":"Gloucester",
    "sg:classifiers":[
        {
            "category":"Professional",
            "subcategory":"Management & Consulting",
            "type":"Services"
        },
        {
            "category":"Professional",
            "subcategory":"Computer Services",
            "type":"Services"
        }
    ],
    "sg:phone":"+44 1452 612844",
    "sg:postcode":"GL4 3EZ",
    "sg:province":"Gloucestershire",
    "sg:tags":[
        "consultant",
        "business",
        "information"
    ],
    "wof:name":"Decidecheck Ltd",
    "wof:placetype":"venue"
},
  "geometry": {"coordinates":[-2.1997580528,51.8536109924],"type":"Point"}
}