{
  "type": "Feature",
  "properties": {
    "iso:country":"GB",
    "sg:address":"Unit 1, Little End Road",
    "sg:city":"St Neots",
    "sg:classifiers":[
        {
            "category":"Manufacturing",
            "subcategory":"Electronics",
            "type":"Manufacturing & Wholesale Goods"
        }
    ],
    "sg:phone":"+44 1480 470400",
    "sg:postcode":"PE19 8JH",
    "sg:province":"Bedfordshire",
    "sg:tags":[
        "control",
        "component",
        "-",
        "electronic"
    ],
    "wof:name":"Driftgate 2000 Ltd.",
    "wof:placetype":"venue"
},
  "geometry": {"coordinates":[-0.2924520075,52.2132301331],"type":"Point"}
}