{
  "type": "Feature",
  "properties": {
    "addr:full":"28 Trevor St Rochdale Lancashire OL11 3HZ",
    "addr:housenumber":"28",
    "addr:postcode":"ol11 3hz",
    "addr:street":"Trevor St",
    "iso:country":"GB",
    "sg:address":"28 Trevor St",
    "sg:city":"Rochdale",
    "sg:classifiers":[
        {
            "category":"Building & Trades",
            "subcategory":"Construction",
            "type":"Services"
        }
    ],
    "sg:phone":"+44 1706 639133",
    "sg:postcode":"OL11 3HZ",
    "sg:province":"Lancashire",
    "sg:tags":[
        "dry",
        "lining",
        "plasterers",
        "screeders"
    ],
    "wof:name":"B Mercer",
    "wof:placetype":"venue"
},
  "geometry": {"coordinates":[-2.1836121082,53.5969161987],"type":"Point"}
}