{
  "type": "Feature",
  "properties": {
    "addr:full":"Lynhurst Halifax West Yorkshire HX3 7LF",
    "addr:postcode":"hx3 7lf",
    "addr:street":"Lynhurst;West",
    "iso:country":"GB",
    "sg:address":"Lynhurst",
    "sg:city":"Halifax",
    "sg:classifiers":[
        {
            "category":"Arts & Performance",
            "subcategory":"Music",
            "type":"Entertainment"
        }
    ],
    "sg:postcode":"HX3 7LF",
    "sg:province":"West Yorkshire",
    "sg:tags":[
        "mobile",
        "disco"
    ],
    "wof:name":"Tower Disco",
    "wof:placetype":"venue"
},
  "geometry": {"coordinates":[-1.8222700357,53.7460098267],"type":"Point"}
}