{
  "type": "Feature",
  "properties": {
    "iso:country":"GB",
    "sg:address":"Trevore Farm, Kerley, Chacewater",
    "sg:city":"Truro",
    "sg:classifiers":[
        {
            "category":"Home & Garden",
            "subcategory":"Garden Supply",
            "type":"Retail Goods"
        },
        {
            "category":"Farming",
            "subcategory":"Livestock Farm",
            "type":"Manufacturing & Wholesale Goods"
        }
    ],
    "sg:postcode":"TR4 8LG",
    "sg:province":"Cornwall",
    "sg:tags":[
        "bulb",
        "grower",
        "others"
    ],
    "wof:name":"E P Loader",
    "wof:placetype":"venue"
},
  "geometry": {"coordinates":[-5.160164,50.25626],"type":"Point"}
}