{
  "type": "Feature",
  "properties": {
    "iso:country":"GB",
    "sg:address":"26 Limeside Avenue, Rutherglen",
    "sg:city":"Glasgow",
    "sg:classifiers":[
        {
            "category":"Education",
            "subcategory":"Preschool",
            "type":"Public Place"
        }
    ],
    "sg:postcode":"G73 3PN",
    "sg:province":"Glasgow City",
    "sg:tags":[
        "pre-school",
        "playgroups"
    ],
    "wof:name":"Little Toffs Private Playgroup",
    "wof:placetype":"venue"
},
  "geometry": {"coordinates":[-4.203769207,55.822933197],"type":"Point"}
}