{
  "type": "Feature",
  "properties": {
    "iso:country":"GB",
    "sg:address":"52 East Meadway, Kitts Green",
    "sg:city":"Birmingham",
    "sg:classifiers":[
        {
            "category":"Home & Garden",
            "subcategory":"Home Furnishings",
            "type":"Retail Goods"
        }
    ],
    "sg:phone":"+44 121 789 7131",
    "sg:postcode":"B33 0AP",
    "sg:province":"West Midlands",
    "sg:tags":[
        "blind",
        "curtain",
        "fitting"
    ],
    "wof:name":"Helen Margaret Interiors",
    "wof:placetype":"venue"
},
  "geometry": {"coordinates":[-1.7700840235,52.4810562134],"type":"Point"}
}