{
  "type": "Feature",
  "properties": {
    "addr:full":"125 Wellington Road, Bollington Macclesfield Cheshire SK10 5HT",
    "addr:housenumber":"125",
    "addr:postcode":"sk10 5ht",
    "addr:street":"Wellington Road",
    "iso:country":"GB",
    "sg:address":"125 Wellington Road, Bollington",
    "sg:city":"Macclesfield",
    "sg:classifiers":[
        {
            "category":"Fast Food",
            "type":"Food & Drink"
        }
    ],
    "sg:phone":"+44 1625 574949",
    "sg:postcode":"SK10 5HT",
    "sg:province":"Cheshire",
    "sg:tags":[
        "away",
        "meal",
        "outlet",
        "take"
    ],
    "wof:name":"Fung Ling Chinese Takeaway",
    "wof:placetype":"venue"
},
  "geometry": {"coordinates":[-2.1104030609,53.2937583923],"type":"Point"}
}