{
  "type": "Feature",
  "properties": {
    "addr:full":"36 Chapel Street Billericay Essex CM12 9LU",
    "addr:housenumber":"36",
    "addr:postcode":"cm12 9lu",
    "addr:street":"Chapel Street",
    "iso:country":"GB",
    "sg:address":"36 Chapel Street",
    "sg:city":"Billericay",
    "sg:classifiers":[
        {
            "category":"Bars & Pubs",
            "type":"Food & Drink"
        }
    ],
    "sg:phone":"+44 1277 622873",
    "sg:postcode":"CM12 9LU",
    "sg:province":"Essex",
    "sg:tags":[
        "pubs",
        "inn"
    ],
    "wof:name":"Coach & Horses",
    "wof:placetype":"venue"
},
  "geometry": {"coordinates":[0.4183189869,51.6243667603],"type":"Point"}
}