{
  "type": "Feature",
  "properties": {
    "addr:full":"Troon Harbour, Harbour Road Troon South Ayrshire KA10 6DH",
    "addr:postcode":"ka10 6dh",
    "addr:street":"Troon Harbour Harbour Road",
    "iso:country":"GB",
    "sg:address":"Troon Harbour, Harbour Road",
    "sg:city":"Troon",
    "sg:classifiers":[
        {
            "category":"Harbor",
            "type":"Transportation"
        }
    ],
    "sg:phone":"+44 1292 313412",
    "sg:postcode":"KA10 6DH",
    "sg:province":"South Ayrshire",
    "sg:tags":[
        "dock",
        "ports",
        "harbour"
    ],
    "wof:name":"Associated British Ports",
    "wof:placetype":"venue"
},
  "geometry": {"coordinates":[-4.6537041664,55.5463142395],"type":"Point"}
}