{
  "type": "Feature",
  "properties": {
    "addr:full":"8 Midanbury Bdwy, Watts Hill Southampton Hampshire SO18 4QD",
    "addr:housenumber":"8",
    "addr:postcode":"so18 4qd",
    "addr:street":"Midanbury Bdwy Watts Hill",
    "iso:country":"GB",
    "sg:address":"8 Midanbury Bdwy, Watts Hill",
    "sg:city":"Southampton",
    "sg:classifiers":[
        {
            "category":"Food & Beverages",
            "subcategory":"Liquor & Beverages",
            "type":"Retail Goods"
        }
    ],
    "sg:postcode":"SO18 4QD",
    "sg:province":"Hampshire",
    "sg:tags":[
        "beer",
        "spirit",
        "wines"
    ],
    "wof:name":"Hall & Woodhouse Ltd.",
    "wof:placetype":"venue"
},
  "geometry": {"coordinates":[-1.36415,50.925919],"type":"Point"}
}