{
  "type": "Feature",
  "properties": {
    "addr:full":"104 Newmarket Street Norwich Norfolk NR2 2DP",
    "addr:housenumber":"104",
    "addr:postcode":"nr2 2dp",
    "addr:street":"Newmarket Street",
    "iso:country":"GB",
    "sg:address":"104 Newmarket Street",
    "sg:city":"Norwich",
    "sg:classifiers":[
        {
            "category":"Professional",
            "subcategory":"Art Services",
            "type":"Services"
        },
        {
            "category":"Building & Trades",
            "subcategory":"Construction",
            "type":"Services"
        }
    ],
    "sg:phone":"+44 1603 610246",
    "sg:postcode":"NR2 2DP",
    "sg:province":"Norfolk",
    "sg:tags":[
        "decorator",
        "painter"
    ],
    "wof:name":"Robert James Sturman",
    "wof:placetype":"venue"
},
  "geometry": {"coordinates":[1.281389,52.621494],"type":"Point"}
}