{
  "type": "Feature",
  "properties": {
    "iso:country":"GB",
    "sg:address":"88 Moorland Road, Burslem",
    "sg:city":"Stoke-on-trent",
    "sg:classifiers":[
        {
            "category":"Shopping",
            "subcategory":"Stationery & Office Supplies",
            "type":"Retail Goods"
        }
    ],
    "sg:phone":"+44 1782 822415",
    "sg:postcode":"ST6 1DY",
    "sg:province":"Staffordshire",
    "sg:tags":[
        "equipment"
    ],
    "wof:name":"Business Products",
    "wof:placetype":"venue"
},
  "geometry": {"coordinates":[-2.192382,53.046429],"type":"Point"}
}