{
  "type": "Feature",
  "properties": {
    "iso:country":"GB",
    "sg:address":"35 Tranquil Vale, Blackheath Village",
    "sg:city":"London",
    "sg:classifiers":[
        {
            "category":"Real Estate",
            "subcategory":"Developer",
            "type":"Services"
        }
    ],
    "sg:postcode":"SE3 0BU",
    "sg:province":"Greater London",
    "sg:tags":[
        "property"
    ],
    "wof:name":"Estmanco (Kinden) Ltd.",
    "wof:placetype":"venue"
},
  "geometry": {"coordinates":[0.0083720004,51.4663124084],"type":"Point"}
}