{
  "type": "Feature",
  "properties": {
    "iso:country":"GB",
    "sg:address":"31 Woodfield Close, Darfield",
    "sg:city":"Barnsley",
    "sg:classifiers":[
        {
            "category":"Social Services",
            "subcategory":"Adult Care",
            "type":"Services"
        },
        {
            "category":"Real Estate",
            "subcategory":"Real Estate Agent",
            "type":"Services"
        }
    ],
    "sg:phone":"+44 1226 756412",
    "sg:postcode":"S73 9EP",
    "sg:province":"South Yorkshire",
    "sg:tags":[
        "housing",
        "sheltered"
    ],
    "wof:name":"Woodfield",
    "wof:placetype":"venue"
},
  "geometry": {"coordinates":[-1.379776,53.536442],"type":"Point"}
}