{
  "type": "Feature",
  "properties": {
    "iso:country":"GB",
    "sg:address":"5 Merlin Close",
    "sg:city":"Stockport",
    "sg:classifiers":[
        {
            "category":"Retail",
            "subcategory":"Driving School",
            "type":"Services"
        }
    ],
    "sg:postcode":"SK2 5UH",
    "sg:province":"Cheshire",
    "wof:name":"Learners School of Motoring",
    "wof:placetype":"venue"
},
  "geometry": {"coordinates":[-2.101627,53.394539],"type":"Point"}
}