{
  "type": "Feature",
  "properties": {
    "addr:full":"The Old Barns Bedford Bedfordshire MK43 7JD",
    "addr:postcode":"mk43 7jd",
    "addr:street":"Bedfordshire",
    "iso:country":"GB",
    "sg:address":"The Old Barns",
    "sg:city":"Bedford",
    "sg:classifiers":[
        {
            "category":"Banks & Credit Unions",
            "subcategory":"Financial Services",
            "type":"Services"
        }
    ],
    "sg:phone":"+44 1582 765026",
    "sg:postcode":"MK43 7JD",
    "sg:province":"Bedfordshire",
    "sg:tags":[
        "consultant"
    ],
    "wof:name":"Randall Associates",
    "wof:placetype":"venue"
},
  "geometry": {"coordinates":[-0.546717,52.210361],"type":"Point"}
}