{
  "type": "Feature",
  "properties": {
    "addr:full":"1 Westbury Street Sunderland Tyne and Wear SR4 6EF",
    "addr:housenumber":"1",
    "addr:postcode":"sr4 6ef",
    "addr:street":"Westbury Street",
    "iso:country":"GB",
    "sg:address":"1 Westbury Street",
    "sg:city":"Sunderland",
    "sg:classifiers":[
        {
            "category":"Bars & Pubs",
            "type":"Food & Drink"
        }
    ],
    "sg:postcode":"SR4 6EF",
    "sg:province":"Tyne and Wear",
    "sg:tags":[
        "pubs",
        "inn"
    ],
    "wof:name":"The Railway Tavern",
    "wof:placetype":"venue"
},
  "geometry": {"coordinates":[-1.4007810354,54.9083900452],"type":"Point"}
}