{
  "type": "Feature",
  "properties": {
    "iso:country":"GB",
    "sg:address":"50 Weston Road, Long Ashton",
    "sg:city":"Bristol",
    "sg:classifiers":[
        {
            "category":"Food & Beverages",
            "subcategory":"Liquor & Beverages",
            "type":"Retail Goods"
        }
    ],
    "sg:phone":"+44 1275 392508",
    "sg:postcode":"BS41 9HH",
    "sg:province":"Somerset",
    "sg:tags":[
        "beer",
        "spirit",
        "wines"
    ],
    "wof:name":"The Little Tipple",
    "wof:placetype":"venue"
},
  "geometry": {"coordinates":[-2.6676709652,51.4286880493],"type":"Point"}
}