{
  "type": "Feature",
  "properties": {
    "addr:full":"2 St Peter Street Peterhead Aberdeenshire AB42 6QB",
    "addr:housenumber":"2",
    "addr:postcode":"ab42 6qb",
    "addr:street":"St Peter Street",
    "iso:country":"GB",
    "sg:address":"2 St Peter Street",
    "sg:city":"Peterhead",
    "sg:classifiers":[
        {
            "category":"Personal",
            "subcategory":"Beauty Salon",
            "type":"Services"
        }
    ],
    "sg:postcode":"AB42 6QB",
    "sg:province":"Aberdeenshire",
    "sg:tags":[
        "unisex",
        "hairdresser"
    ],
    "wof:name":"Quick Snip",
    "wof:placetype":"venue"
},
  "geometry": {"coordinates":[-1.7840280533,57.5053367615],"type":"Point"}
}