{
  "type": "Feature",
  "properties": {
    "addr:full":"231a Lavender Hill London Greater London SW11 1JR",
    "addr:housenumber":"231a",
    "addr:postcode":"sw11 1jr",
    "addr:street":"Lavender Hill",
    "iso:country":"GB",
    "sg:address":"231a Lavender Hill",
    "sg:city":"London",
    "sg:classifiers":[
        {
            "category":"Personal",
            "type":"Services"
        },
        {
            "category":"Professional",
            "subcategory":"Lawyer & Legal Services",
            "type":"Services"
        }
    ],
    "sg:phone":"+44 20 7223 1234",
    "sg:postcode":"SW11 1JR",
    "sg:province":"Greater London",
    "sg:tags":[
        "advice",
        "counselling"
    ],
    "wof:name":"Victim Support - Wandsworth",
    "wof:placetype":"venue"
},
  "geometry": {"coordinates":[-0.1622799933,51.4643135071],"type":"Point"}
}