{
  "type": "Feature",
  "properties": {
    "iso:country":"GB",
    "sg:address":"193 High Street, Henley In Arden",
    "sg:city":"Solihull",
    "sg:classifiers":[
        {
            "category":"Personal",
            "subcategory":"Beauty Salon",
            "type":"Services"
        },
        {
            "category":"Personal",
            "subcategory":"Barber",
            "type":"Services"
        }
    ],
    "sg:phone":"+44 1564 793905",
    "sg:postcode":"B95 5BA",
    "sg:province":"Warwickshire",
    "sg:tags":[
        "unisex",
        "hairdresser"
    ],
    "wof:name":"Structures Hair Design",
    "wof:placetype":"venue"
},
  "geometry": {"coordinates":[-1.78004,52.290428],"type":"Point"}
}