{
  "type": "Feature",
  "properties": {
    "addr:full":"Surrey Street Luton Bedfordshire LU1 3BZ",
    "addr:postcode":"lu1 3bz",
    "addr:street":"Surrey Street",
    "iso:country":"GB",
    "sg:address":"Surrey Street",
    "sg:city":"Luton",
    "sg:classifiers":[
        {
            "category":"Education",
            "subcategory":"School",
            "type":"Public Place"
        }
    ],
    "sg:phone":"+44 1582 729489",
    "sg:postcode":"LU1 3BZ",
    "sg:province":"Bedfordshire",
    "sg:tags":[
        "local",
        "authority"
    ],
    "wof:name":"Surrey Street Primary School",
    "wof:placetype":"venue"
},
  "geometry": {"coordinates":[-0.411699,51.874046],"type":"Point"}
}