{
  "type": "Feature",
  "properties": {
    "addr:full":"24 Byworth Close Bexhill-on-sea East Sussex TN39 4NX",
    "addr:housenumber":"24",
    "addr:postcode":"tn39 4nx",
    "addr:street":"Byworth Close",
    "iso:country":"GB",
    "sg:address":"24 Byworth Close",
    "sg:city":"Bexhill-on-sea",
    "sg:classifiers":[
        {
            "category":"Military Area",
            "subcategory":"Air Force Base",
            "type":"Public Place"
        }
    ],
    "sg:postcode":"TN39 4NX",
    "sg:province":"East Sussex",
    "sg:tags":[
        "taxi",
        "hire",
        "private"
    ],
    "wof:name":"A 2 B Cabs",
    "wof:placetype":"venue"
},
  "geometry": {"coordinates":[0.432215,50.85305],"type":"Point"}
}