{
  "type": "Feature",
  "properties": {
    "addr:full":"10d Hyde Road Paignton Devon TQ4 5BW",
    "addr:housenumber":"10d",
    "addr:postcode":"tq4 5bw",
    "addr:street":"Hyde Road",
    "iso:country":"GB",
    "sg:address":"10d Hyde Road",
    "sg:city":"Paignton",
    "sg:classifiers":[
        {
            "category":"Shopping",
            "subcategory":"Thrift Store",
            "type":"Retail Goods"
        }
    ],
    "sg:phone":"+44 1803 557831",
    "sg:postcode":"TQ4 5BW",
    "sg:province":"Devon",
    "sg:tags":[
        "shop",
        "charity"
    ],
    "wof:name":"Marie Curie Cancer Care",
    "wof:placetype":"venue"
},
  "geometry": {"coordinates":[-3.566941,50.437378],"type":"Point"}
}