{
  "type": "Feature",
  "properties": {
    "iso:country":"GB",
    "sg:address":"33a Oaks Road, Great Glen",
    "sg:city":"Leicester",
    "sg:classifiers":[
        {
            "category":"Retail",
            "subcategory":"Auto Repair",
            "type":"Services"
        }
    ],
    "sg:phone":"+44 116 259 2479",
    "sg:postcode":"LE8 9EF",
    "sg:province":"Leicestershire",
    "sg:tags":[
        "modification",
        "car",
        "vehicle",
        "commercial",
        "garage"
    ],
    "wof:name":"Hillside Garage Great Glen Ltd",
    "wof:placetype":"venue"
},
  "geometry": {"coordinates":[-1.030102,52.574909],"type":"Point"}
}