{
  "type": "Feature",
  "properties": {
    "iso:country":"GB",
    "sg:address":"69a New Street",
    "sg:city":"Birmingham",
    "sg:classifiers":[
        {
            "category":"Arts & Performance",
            "subcategory":"Art Gallery",
            "type":"Entertainment"
        }
    ],
    "sg:postcode":"B2 4DU",
    "sg:province":"West Midlands",
    "wof:name":"Royal Birmingham Society of Artists",
    "wof:placetype":"venue"
},
  "geometry": {"coordinates":[-1.901737,52.479507],"type":"Point"}
}