{
  "type": "Feature",
  "properties": {
    "addr:full":"5-6 Bondgate Darlington Durham DL3 7JB",
    "addr:housenumber":"5-6",
    "addr:postcode":"dl3 7jb",
    "addr:street":"Bondgate Darlington",
    "iso:country":"GB",
    "sg:address":"5-6 Bondgate",
    "sg:city":"Darlington",
    "sg:classifiers":[
        {
            "category":"Banks & Credit Unions",
            "subcategory":"Financial Services",
            "type":"Services"
        }
    ],
    "sg:phone":"+44 1325 550300",
    "sg:postcode":"DL3 7JB",
    "sg:province":"Durham",
    "sg:tags":[
        "building",
        "society"
    ],
    "wof:name":"Nationwide Building Society",
    "wof:placetype":"venue"
},
  "geometry": {"coordinates":[-1.5558730364,54.5261383057],"type":"Point"}
}