{
  "type": "Feature",
  "properties": {
    "iso:country":"GB",
    "sg:address":"21 Market St",
    "sg:city":"Leek",
    "sg:classifiers":[
        {
            "category":"Community Center",
            "subcategory":"Youth",
            "type":"Public Place"
        }
    ],
    "sg:phone":"+44 1538 382419",
    "sg:postcode":"ST13 6HX",
    "sg:province":"Staffordshire",
    "sg:tags":[
        "organisation",
        "centre"
    ],
    "wof:name":"Razz The Coffee Stop",
    "wof:placetype":"venue"
},
  "geometry": {"coordinates":[-2.023447,53.106434],"type":"Point"}
}