{
  "type": "Feature",
  "properties": {
    "addr:full":"7 Bell La, Hendon Hendon Greater London NW4 2BP",
    "addr:housenumber":"7",
    "addr:postcode":"nw4 2bp",
    "addr:street":"Bell La Hendon Hendon",
    "iso:country":"GB",
    "sg:address":"7 Bell La, Hendon",
    "sg:city":"Hendon",
    "sg:classifiers":[
        {
            "category":"Cafe",
            "type":"Food & Drink"
        }
    ],
    "sg:phone":"+44 20 8203 1365",
    "sg:postcode":"NW4 2BP",
    "sg:province":"Greater London",
    "sg:tags":[
        "tea",
        "room"
    ],
    "wof:name":"Bruno's",
    "wof:placetype":"venue"
},
  "geometry": {"coordinates":[-0.219306,51.586998],"type":"Point"}
}