{
  "type": "Feature",
  "properties": {
    "iso:country":"GB",
    "sg:address":"7 Bell La, Hendon",
    "sg:city":"Hendon",
    "sg:classifiers":[
        {
            "category":"Cafe",
            "type":"Food & Drink"
        }
    ],
    "sg:phone":"+44 20 8203 1365",
    "sg:postcode":"NW4 2BP",
    "sg:province":"Greater London",
    "sg:tags":[
        "tea",
        "room"
    ],
    "wof:name":"Bruno's",
    "wof:placetype":"venue"
},
  "geometry": {"coordinates":[-0.219306,51.586998],"type":"Point"}
}