{
  "type": "Feature",
  "properties": {
    "addr:full":"9 Hillside Drive Leek Staffordshire ST13 8JQ",
    "addr:housenumber":"9",
    "addr:postcode":"st13 8jq",
    "addr:street":"Hillside Drive",
    "iso:country":"GB",
    "sg:address":"9 Hillside Drive",
    "sg:city":"Leek",
    "sg:classifiers":[
        {
            "category":"Retail",
            "subcategory":"Driving School",
            "type":"Services"
        }
    ],
    "sg:phone":"+44 1538 386883",
    "sg:postcode":"ST13 8JQ",
    "sg:province":"Staffordshire",
    "wof:name":"Paul David Birchenough",
    "wof:placetype":"venue"
},
  "geometry": {"coordinates":[-2.041378,53.097954],"type":"Point"}
}