{
  "type": "Feature",
  "properties": {
    "iso:country":"GB",
    "sg:address":"33 Newerne Street",
    "sg:city":"Lydney",
    "sg:classifiers":[
        {
            "category":"Shopping",
            "subcategory":"Pharmacy",
            "type":"Retail Goods"
        }
    ],
    "sg:phone":"+44 1594 843443",
    "sg:postcode":"GL15 5RA",
    "sg:province":"Gloucestershire",
    "sg:tags":[
        "pharmacist",
        "chemist"
    ],
    "wof:name":"Beaufort Pharmacy",
    "wof:placetype":"venue"
},
  "geometry": {"coordinates":[-2.529373,51.7272],"type":"Point"}
}