{
  "type": "Feature",
  "properties": {
    "addr:full":"26 Milford Road Lymington Hampshire SO41 8DW",
    "addr:housenumber":"26",
    "addr:postcode":"so41 8dw",
    "addr:street":"Milford Road",
    "iso:country":"GB",
    "sg:address":"26 Milford Road",
    "sg:city":"Lymington",
    "sg:classifiers":[
        {
            "category":"Retail",
            "subcategory":"Laundry & Dry Cleaning",
            "type":"Services"
        }
    ],
    "sg:phone":"+44 1590 673804",
    "sg:postcode":"SO41 8DW",
    "sg:province":"Hampshire",
    "sg:tags":[
        "cleaner",
        "alteration"
    ],
    "wof:name":"Clockwork Yellow",
    "wof:placetype":"venue"
},
  "geometry": {"coordinates":[-1.5526889563,50.7518463135],"type":"Point"}
}