{
  "type": "Feature",
  "properties": {
    "iso:country":"GB",
    "sg:address":"Vicarage Road",
    "sg:city":"Oldbury",
    "sg:classifiers":[
        {
            "category":"Sports & Exercise",
            "subcategory":"Gym",
            "type":"Entertainment"
        }
    ],
    "sg:postcode":"B68 8HS",
    "sg:province":"West Midlands",
    "sg:tags":[
        "fitness",
        "health",
        "centre"
    ],
    "wof:name":"Langley Health & Fitness Suite",
    "wof:placetype":"venue"
},
  "geometry": {"coordinates":[-1.999959,52.494164],"type":"Point"}
}