{
  "type": "Feature",
  "properties": {
    "addr:full":"2 Grasmere Rd Worksop Nottinghamshire S81 0NH",
    "addr:housenumber":"2",
    "addr:postcode":"s81 0nh",
    "addr:street":"Grasmere Rd",
    "iso:country":"GB",
    "sg:address":"2 Grasmere Rd",
    "sg:city":"Worksop",
    "sg:classifiers":[
        {
            "category":"Shopping",
            "subcategory":"Department Store",
            "type":"Retail Goods"
        }
    ],
    "sg:phone":"+44 1909 489228",
    "sg:postcode":"S81 0NH",
    "sg:province":"Nottinghamshire",
    "wof:name":"GRASMERE STORES",
    "wof:placetype":"venue"
},
  "geometry": {"coordinates":[-1.1191519499,53.3255348206],"type":"Point"}
}