{
  "type": "Feature",
  "properties": {
    "addr:full":"Milland Road Neath Neath Port Talbot SA11 1NJ",
    "addr:postcode":"sa11 1nj",
    "addr:street":"Milland Road",
    "iso:country":"GB",
    "sg:address":"Milland Road",
    "sg:city":"Neath",
    "sg:classifiers":[
        {
            "category":"Autos & Motor Vehicles",
            "subcategory":"Automobile Sales",
            "type":"Retail Goods"
        },
        {
            "category":"Shopping",
            "type":"Retail Goods"
        }
    ],
    "sg:phone":"+44 1639 630402",
    "sg:postcode":"SA11 1NJ",
    "sg:province":"Neath Port Talbot",
    "sg:tags":[
        "car",
        "part",
        "accessory"
    ],
    "wof:name":"Mike Saunders Motors Ltd.",
    "wof:placetype":"venue"
},
  "geometry": {"coordinates":[-3.80918,51.661064],"type":"Point"}
}