{
  "type": "Feature",
  "properties": {
    "iso:country":"GB",
    "sg:address":"3 Francis Road",
    "sg:city":"Ashford",
    "sg:classifiers":[
        {
            "category":"Building & Trades",
            "subcategory":"Construction",
            "type":"Services"
        }
    ],
    "sg:phone":"+44 1233 627415",
    "sg:postcode":"TN23 7UP",
    "sg:province":"Kent",
    "sg:tags":[
        "builder"
    ],
    "wof:name":"D W Light",
    "wof:placetype":"venue"
},
  "geometry": {"coordinates":[0.868786,51.139908],"type":"Point"}
}