{
  "type": "Feature",
  "properties": {
    "addr:full":"31 Waldeck Rd Chiswick Greater London W4 3NL",
    "addr:housenumber":"31",
    "addr:postcode":"w4 3nl",
    "addr:street":"Waldeck Rd",
    "iso:country":"GB",
    "sg:address":"31 Waldeck Rd",
    "sg:city":"Chiswick",
    "sg:classifiers":[
        {
            "category":"Professional",
            "subcategory":"Art Services",
            "type":"Services"
        }
    ],
    "sg:phone":"+44 20 8995 0771",
    "sg:postcode":"W4 3NL",
    "sg:province":"Greater London",
    "sg:tags":[
        "photographer"
    ],
    "wof:name":"Charles Carr-Jones",
    "wof:placetype":"venue"
},
  "geometry": {"coordinates":[-0.283238,51.488037],"type":"Point"}
}