{
  "type": "Feature",
  "properties": {
    "addr:full":"Liverpool Street Newport Newport NP19 8DH",
    "addr:postcode":"np19 8dh",
    "addr:street":"Liverpool Street",
    "iso:country":"GB",
    "sg:address":"Liverpool Street",
    "sg:city":"Newport",
    "sg:classifiers":[
        {
            "category":"Personal",
            "subcategory":"Beauty Salon",
            "type":"Services"
        }
    ],
    "sg:phone":"+44 1633 251628",
    "sg:postcode":"NP19 8DH",
    "sg:province":"Newport",
    "sg:tags":[
        "lady",
        "hairdresser"
    ],
    "wof:name":"Pat's Salon",
    "wof:placetype":"venue"
},
  "geometry": {"coordinates":[-2.9825439453,51.5918312073],"type":"Point"}
}