{
  "type": "Feature",
  "properties": {
    "iso:country":"GB",
    "sg:address":"Stadium Rd, Bromborough",
    "sg:city":"Wirral",
    "sg:classifiers":[
        {
            "category":"Professional",
            "type":"Services"
        },
        {
            "category":"Professional",
            "subcategory":"Business Services",
            "type":"Services"
        }
    ],
    "sg:phone":"+44 151 343 4500",
    "sg:postcode":"CH62 3NU",
    "sg:province":"Cheshire",
    "sg:tags":[
        "distribution",
        "provider"
    ],
    "wof:name":"Wincanton Logistics Ltd",
    "wof:placetype":"venue"
},
  "geometry": {"coordinates":[-2.9750699997,53.3437042236],"type":"Point"}
}