{
  "type": "Feature",
  "properties": {
    "iso:country":"GB",
    "sg:address":"Kings Chalets Kings Park",
    "sg:city":"Canvey Island",
    "sg:classifiers":[
        {
            "category":"Cafe",
            "type":"Food & Drink"
        }
    ],
    "sg:phone":"+44 1268 511444",
    "sg:postcode":"SS8 8HE",
    "sg:province":"Essex",
    "sg:tags":[
        "tea",
        "room"
    ],
    "wof:name":"Roosters Chicken Bar",
    "wof:placetype":"venue"
},
  "geometry": {"coordinates":[0.59112,51.520374],"type":"Point"}
}