{
  "type": "Feature",
  "properties": {
    "addr:full":"1 Netherwood Place, Netherwood Road London Greater London W14 0BW",
    "addr:housenumber":"1",
    "addr:postcode":"w14 0bw",
    "addr:street":"Netherwood Place Netherwood Road",
    "iso:country":"GB",
    "sg:address":"1 Netherwood Place, Netherwood Road",
    "sg:city":"London",
    "sg:classifiers":[
        {
            "category":"Manufacturing",
            "subcategory":"Apparel",
            "type":"Manufacturing & Wholesale Goods"
        }
    ],
    "sg:phone":"+44 20 7602 6023",
    "sg:postcode":"W14 0BW",
    "sg:province":"Greater London",
    "sg:tags":[
        "garment",
        "designer"
    ],
    "wof:name":"Betty Jackson Ltd.",
    "wof:placetype":"venue"
},
  "geometry": {"coordinates":[-0.2216199934,51.5002403259],"type":"Point"}
}