{
  "type": "Feature",
  "properties": {
    "iso:country":"GB",
    "sg:address":"31 Well Street",
    "sg:city":"Moffat",
    "sg:classifiers":[
        {
            "category":"Personal",
            "subcategory":"Beauty Salon",
            "type":"Services"
        },
        {
            "category":"Personal",
            "subcategory":"Barber",
            "type":"Services"
        }
    ],
    "sg:phone":"+44 1683 220268",
    "sg:postcode":"DG10 9DP",
    "sg:province":"Dumfries and Galloway",
    "sg:tags":[
        "unisex",
        "hairdresser"
    ],
    "wof:name":"Shonagh's New Images Hairdressing",
    "wof:placetype":"venue"
},
  "geometry": {"coordinates":[-3.442365,55.333282],"type":"Point"}
}