{
  "type": "Feature",
  "properties": {
    "iso:country":"GB",
    "sg:address":"28 Fore Street",
    "sg:city":"Teignmouth",
    "sg:classifiers":[
        {
            "category":"Shopping",
            "subcategory":"Pets & Pet Supplies",
            "type":"Retail Goods"
        }
    ],
    "sg:phone":"+44 1626 779777",
    "sg:postcode":"TQ14 8DZ",
    "sg:province":"Devon",
    "wof:name":"J & P Pet Supplies",
    "wof:placetype":"venue"
},
  "geometry": {"coordinates":[-3.4972560406,50.5466804504],"type":"Point"}
}