{
  "type": "Feature",
  "properties": {
    "addr:full":"Bengarra, Manse Road Ellon Aberdeenshire AB41 7RT",
    "addr:postcode":"ab41 7rt",
    "addr:street":"Manse Road",
    "iso:country":"GB",
    "sg:address":"Bengarra, Manse Road",
    "sg:city":"Ellon",
    "sg:classifiers":[
        {
            "category":"Building & Trades",
            "subcategory":"Construction",
            "type":"Services"
        }
    ],
    "sg:phone":"+44 1651 842993",
    "sg:postcode":"AB41 7RT",
    "sg:province":"Aberdeenshire",
    "sg:tags":[
        "builder"
    ],
    "wof:name":"Barry Dawson",
    "wof:placetype":"venue"
},
  "geometry": {"coordinates":[-2.0728139877,57.3641357422],"type":"Point"}
}