{
  "type": "Feature",
  "properties": {
    "iso:country":"GB",
    "sg:address":"Cherrytree Works, Roundhay Rd",
    "sg:city":"Leicester",
    "sg:classifiers":[
        {
            "category":"Professional",
            "subcategory":"Engineering",
            "type":"Services"
        }
    ],
    "sg:phone":"+44 116 263 0331",
    "sg:postcode":"LE3 2BY",
    "sg:province":"Leicestershire",
    "sg:tags":[
        "electronic",
        "engineer"
    ],
    "wof:name":"Contrive Ltd",
    "wof:placetype":"venue"
},
  "geometry": {"coordinates":[-1.1589,52.61792],"type":"Point"}
}