{
  "type": "Feature",
  "properties": {
    "addr:full":"Kingsland Leominster Herefordshire HR6 9SF",
    "addr:postcode":"hr6 9sf",
    "addr:street":"Kingsland",
    "iso:country":"GB",
    "sg:address":"Kingsland",
    "sg:city":"Leominster",
    "sg:classifiers":[
        {
            "category":"Home & Garden",
            "subcategory":"Home Furnishings",
            "type":"Retail Goods"
        },
        {
            "category":"Manufacturing",
            "subcategory":"Furniture",
            "type":"Manufacturing & Wholesale Goods"
        }
    ],
    "sg:phone":"+44 1568 708206",
    "sg:postcode":"HR6 9SF",
    "sg:province":"Herefordshire",
    "sg:tags":[
        "manufacture",
        "mnfr",
        "patio"
    ],
    "sg:website":"http://www.kingslandstabling.com",
    "wof:name":"Kingsland Saw Mills Ltd.",
    "wof:placetype":"venue"
},
  "geometry": {"coordinates":[-2.8227090836,52.2519607544],"type":"Point"}
}