{
  "type": "Feature",
  "properties": {
    "addr:full":"29 Howbeck Lane, Clarborough Retford Nottinghamshire DN22 9LW",
    "addr:housenumber":"29",
    "addr:postcode":"dn22 9lw",
    "addr:street":"Howbeck Lane",
    "iso:country":"GB",
    "sg:address":"29 Howbeck Lane, Clarborough",
    "sg:city":"Retford",
    "sg:classifiers":[
        {
            "category":"Education",
            "subcategory":"University",
            "type":"Public Place"
        }
    ],
    "sg:phone":"+44 1777 703058",
    "sg:postcode":"DN22 9LW",
    "sg:province":"Nottinghamshire",
    "sg:tags":[
        "higher"
    ],
    "wof:name":"Byron Evans",
    "wof:placetype":"venue"
},
  "geometry": {"coordinates":[-0.8984280229,53.3442993164],"type":"Point"}
}