{
  "type": "Feature",
  "properties": {
    "iso:country":"GB",
    "sg:address":"Home Farm, Chester Rd, Millington",
    "sg:city":"Altrincham",
    "sg:classifiers":[
        {
            "category":"Professional",
            "subcategory":"Management & Consulting",
            "type":"Services"
        }
    ],
    "sg:phone":"+44 161 928 3035",
    "sg:postcode":"WA14 3RU",
    "sg:province":"Cheshire",
    "sg:tags":[
        "conservation"
    ],
    "wof:name":"National Trust (The)",
    "wof:placetype":"venue"
},
  "geometry": {"coordinates":[-2.400536,53.366577],"type":"Point"}
}