{
  "type": "Feature",
  "properties": {
    "addr:full":"Church Farm, Hardley Norwich Norfolk NR14 6BU",
    "addr:postcode":"nr14 6bu",
    "addr:street":"Hardley Norwich",
    "iso:country":"GB",
    "sg:address":"Church Farm, Hardley",
    "sg:city":"Norwich",
    "sg:classifiers":[
        {
            "category":"Home & Garden",
            "subcategory":"Garden Supply",
            "type":"Retail Goods"
        },
        {
            "category":"Banks & Credit Unions",
            "subcategory":"Investment Brokerage",
            "type":"Services"
        }
    ],
    "sg:phone":"+44 1508 520666",
    "sg:postcode":"NR14 6BU",
    "sg:province":"Norfolk",
    "sg:tags":[
        "bulb",
        "grower",
        "contractor"
    ],
    "wof:name":"P J Hagger",
    "wof:placetype":"venue"
},
  "geometry": {"coordinates":[1.48201,52.539955],"type":"Point"}
}