{
  "type": "Feature",
  "properties": {
    "addr:full":"278a Stamford St West Ashton-under-lyne Greater Manchester OL6 7NJ",
    "addr:housenumber":"278a",
    "addr:postcode":"ol6 7nj",
    "addr:street":"Stamford St",
    "iso:country":"GB",
    "sg:address":"278a Stamford St West",
    "sg:city":"Ashton-under-lyne",
    "sg:classifiers":[
        {
            "category":"Home & Garden",
            "subcategory":"Home Furnishings",
            "type":"Retail Goods"
        }
    ],
    "sg:postcode":"OL6 7NJ",
    "sg:province":"Greater Manchester",
    "sg:tags":[
        "blind",
        "curtain",
        "fitting"
    ],
    "wof:name":"Castleton Textiles Ltd.",
    "wof:placetype":"venue"
},
  "geometry": {"coordinates":[-2.1015040874,53.4851455688],"type":"Point"}
}