{
  "type": "Feature",
  "properties": {
    "addr:full":"129 Streatham Vale Streatham Greater London SW16 5SQ",
    "addr:housenumber":"129",
    "addr:postcode":"sw16 5sq",
    "addr:street":"Streatham Vale",
    "iso:country":"GB",
    "sg:address":"129 Streatham Vale",
    "sg:city":"Streatham",
    "sg:classifiers":[
        {
            "category":"Food & Beverages",
            "subcategory":"Fruits & Vegetables",
            "type":"Retail Goods"
        }
    ],
    "sg:phone":"+44 20 8764 6238",
    "sg:postcode":"SW16 5SQ",
    "sg:province":"Greater London",
    "sg:tags":[
        "greengrocer"
    ],
    "wof:name":"Centra Stores",
    "wof:placetype":"venue"
},
  "geometry": {"coordinates":[-0.140188,51.414711],"type":"Point"}
}