{
  "type": "Feature",
  "properties": {
    "addr:full":"10 New Street Petworth West Sussex GU28 0AS",
    "addr:housenumber":"10",
    "addr:postcode":"gu28 0as",
    "addr:street":"New Street",
    "iso:country":"GB",
    "sg:address":"10 New Street",
    "sg:city":"Petworth",
    "sg:classifiers":[
        {
            "category":"Shopping",
            "subcategory":"Antiques",
            "type":"Retail Goods"
        }
    ],
    "sg:phone":"+44 1798 344011",
    "sg:postcode":"GU28 0AS",
    "sg:province":"West Sussex",
    "wof:name":"Antiquated",
    "wof:placetype":"venue"
},
  "geometry": {"coordinates":[-0.609701,50.986034],"type":"Point"}
}