{
  "type": "Feature",
  "properties": {
    "addr:full":"Unit 4 Lansdowne Workshops, Lansdowne Mews, Charlton London Greater London SE7 8AZ",
    "addr:housenumber":"unit 4;workshops",
    "addr:postcode":"se7 8az",
    "addr:street":"Lansdowne Mews",
    "iso:country":"GB",
    "sg:address":"Unit 4 Lansdowne Workshops, Lansdowne Mews, Charlton",
    "sg:city":"London",
    "sg:classifiers":[
        {
            "category":"Shopping",
            "subcategory":"Stationery & Office Supplies",
            "type":"Retail Goods"
        }
    ],
    "sg:phone":"+44 20 8293 4900",
    "sg:postcode":"SE7 8AZ",
    "sg:province":"Greater London",
    "sg:tags":[
        "printers'"
    ],
    "wof:name":"Valley Printers Supplies Ltd.",
    "wof:placetype":"venue"
},
  "geometry": {"coordinates":[0.03791,51.485611],"type":"Point"}
}