{
  "type": "Feature",
  "properties": {
    "addr:full":"4 Chatterton Road Bromley Kent BR2 9QN",
    "addr:housenumber":"4",
    "addr:postcode":"br2 9qn",
    "addr:street":"Chatterton Road",
    "iso:country":"GB",
    "sg:address":"4 Chatterton Road",
    "sg:city":"Bromley",
    "sg:classifiers":[
        {
            "category":"Personal",
            "subcategory":"Beauty Salon",
            "type":"Services"
        }
    ],
    "sg:phone":"+44 20 8466 8408",
    "sg:postcode":"BR2 9QN",
    "sg:province":"Kent",
    "sg:tags":[
        "unisex",
        "hairdresser"
    ],
    "wof:name":"Nikkis",
    "wof:placetype":"venue"
},
  "geometry": {"coordinates":[0.0341060013,51.3933525085],"type":"Point"}
}