{
  "type": "Feature",
  "properties": {
    "iso:country":"GB",
    "sg:address":"Unit 3 Mackays Yard, Colonial Way",
    "sg:city":"Watford",
    "sg:classifiers":[
        {
            "category":"Freight",
            "type":"Transportation"
        }
    ],
    "sg:phone":"+44 1923 248118",
    "sg:postcode":"WD24 4FL",
    "sg:province":"Hertfordshire",
    "sg:tags":[
        "haulage",
        "road"
    ],
    "wof:name":"Stand & Deliver Transport Ltd.",
    "wof:placetype":"venue"
},
  "geometry": {"coordinates":[-0.39366,51.666561],"type":"Point"}
}