{
  "type": "Feature",
  "properties": {
    "addr:full":"1 Factory Street, Shepshed Loughborough Leicestershire LE12 9AQ",
    "addr:housenumber":"1",
    "addr:postcode":"le12 9aq",
    "addr:street":"Factory Street",
    "iso:country":"GB",
    "sg:address":"1 Factory Street, Shepshed",
    "sg:city":"Loughborough",
    "sg:classifiers":[
        {
            "category":"Home & Garden",
            "subcategory":"Household Appliances",
            "type":"Retail Goods"
        }
    ],
    "sg:postcode":"LE12 9AQ",
    "sg:province":"Leicestershire",
    "sg:tags":[
        "electrical"
    ],
    "wof:name":"Automatic Washing Machine Services",
    "wof:placetype":"venue"
},
  "geometry": {"coordinates":[-1.2951669693,52.7728004456],"type":"Point"}
}