{
  "type": "Feature",
  "properties": {
    "iso:country":"GB",
    "sg:address":"4 Parkside",
    "sg:city":"Ringwood",
    "sg:classifiers":[
        {
            "category":"Communications",
            "type":"Services"
        }
    ],
    "sg:phone":"+44 1425 482848",
    "sg:postcode":"BH24 3SQ",
    "sg:province":"Dorset",
    "sg:tags":[
        "data",
        "network"
    ],
    "wof:name":"Infusion Multimedia Ltd.",
    "wof:placetype":"venue"
},
  "geometry": {"coordinates":[-1.78671,50.840282],"type":"Point"}
}