{
  "type": "Feature",
  "properties": {
    "addr:full":"10b Jay Mews London Greater London SW7 2EP",
    "addr:housenumber":"10b",
    "addr:postcode":"sw7 2ep",
    "addr:street":"Jay Mews",
    "iso:country":"GB",
    "sg:address":"10b Jay Mews",
    "sg:city":"London",
    "sg:classifiers":[
        {
            "category":"Real Estate",
            "subcategory":"Surveying",
            "type":"Services"
        }
    ],
    "sg:phone":"+44 20 7225 0400",
    "sg:postcode":"SW7 2EP",
    "sg:province":"Greater London",
    "sg:tags":[
        "surveyor",
        "valuer"
    ],
    "wof:name":"Malcolm Marsdin & Co",
    "wof:placetype":"venue"
},
  "geometry": {"coordinates":[-0.1792290062,51.5008010864],"type":"Point"}
}