{
  "type": "Feature",
  "properties": {
    "addr:full":"High Street, Burwash Etchingham East Sussex TN19 7ES",
    "addr:postcode":"tn19 7es",
    "addr:street":"High Street",
    "iso:country":"GB",
    "sg:address":"High Street, Burwash",
    "sg:city":"Etchingham",
    "sg:classifiers":[
        {
            "category":"Shopping",
            "subcategory":"Antiques",
            "type":"Retail Goods"
        },
        {
            "category":"Shopping",
            "subcategory":"Books",
            "type":"Retail Goods"
        },
        {
            "category":"Government",
            "subcategory":"Customs House",
            "type":"Public Place"
        }
    ],
    "sg:phone":"+44 1435 882535",
    "sg:postcode":"TN19 7ES",
    "sg:province":"East Sussex",
    "sg:tags":[
        "clearance",
        "second-hand"
    ],
    "wof:name":"Chateaubriand Antiques Centre",
    "wof:placetype":"venue"
},
  "geometry": {"coordinates":[0.442966,51.009933],"type":"Point"}
}