{
  "type": "Feature",
  "properties": {
    "addr:full":"17 Burnside Street, Rothes Aberlour Moray AB38 7AA",
    "addr:housenumber":"17",
    "addr:postcode":"ab38 7aa",
    "addr:street":"Burnside Street",
    "iso:country":"GB",
    "sg:address":"17 Burnside Street, Rothes",
    "sg:city":"Aberlour",
    "sg:classifiers":[
        {
            "category":"Building & Trades",
            "subcategory":"Landscaping Services",
            "type":"Services"
        }
    ],
    "sg:phone":"+44 1340 831292",
    "sg:postcode":"AB38 7AA",
    "sg:province":"Moray",
    "sg:tags":[
        "forestry",
        "tree"
    ],
    "wof:name":"I D Grant & Co",
    "wof:placetype":"venue"
},
  "geometry": {"coordinates":[-3.210995,57.526627],"type":"Point"}
}