{
  "type": "Feature",
  "properties": {
    "addr:full":"Harts Boat Yard, Portsmouth Road Surbiton Surrey KT6 4HJ",
    "addr:postcode":"kt6 4hj",
    "addr:street":"Portsmouth Road",
    "iso:country":"GB",
    "sg:address":"Harts Boat Yard, Portsmouth Road",
    "sg:city":"Surbiton",
    "sg:classifiers":[
        {
            "category":"Autos & Motor Vehicles",
            "subcategory":"Boat Sales",
            "type":"Retail Goods"
        }
    ],
    "sg:phone":"+44 20 8399 4009",
    "sg:postcode":"KT6 4HJ",
    "sg:province":"Surrey",
    "sg:tags":[
        "repair",
        "builder"
    ],
    "wof:name":"Harts Boats",
    "wof:placetype":"venue"
},
  "geometry": {"coordinates":[-0.3069489896,51.3920593262],"type":"Point"}
}