{
  "type": "Feature",
  "properties": {
    "iso:country":"GB",
    "sg:address":"Grove Ho, Millers Clo",
    "sg:city":"Dorchester",
    "sg:classifiers":[
        {
            "category":"Government",
            "subcategory":"Office",
            "type":"Public Place"
        }
    ],
    "sg:phone":"+44 1305 264479",
    "sg:postcode":"DT1 1SS",
    "sg:province":"Dorset",
    "sg:tags":[
        "project",
        "gov",
        "community"
    ],
    "wof:name":"Dorset Community N H S Trust",
    "wof:placetype":"venue"
},
  "geometry": {"coordinates":[-2.441564,50.711906],"type":"Point"}
}