{
  "type": "Feature",
  "properties": {
    "addr:full":"Coney Avenue Barnstaple Devon EX32 8QJ",
    "addr:postcode":"ex32 8qj",
    "addr:street":"Coney Avenue",
    "iso:country":"GB",
    "sg:address":"Coney Avenue",
    "sg:city":"Barnstaple",
    "sg:classifiers":[
        {
            "category":"Autos & Motor Vehicles",
            "subcategory":"Automobile Sales",
            "type":"Retail Goods"
        }
    ],
    "sg:phone":"+44 1271 374555",
    "sg:postcode":"EX32 8QJ",
    "sg:province":"Devon",
    "sg:tags":[
        "car"
    ],
    "wof:name":"Prideaux",
    "wof:placetype":"venue"
},
  "geometry": {"coordinates":[-4.043943882,51.0732383728],"type":"Point"}
}