{
  "type": "Feature",
  "properties": {
    "iso:country":"GB",
    "sg:address":"105 New Road Side, Horsforth",
    "sg:city":"Leeds",
    "sg:classifiers":[
        {
            "category":"Professional",
            "subcategory":"Lawyer & Legal Services",
            "type":"Services"
        }
    ],
    "sg:phone":"+44 113 259 1188",
    "sg:postcode":"LS18 4QD",
    "sg:province":"West Yorkshire",
    "sg:tags":[
        "solicitor"
    ],
    "wof:name":"Richmond & Co",
    "wof:placetype":"venue"
},
  "geometry": {"coordinates":[-1.639522,53.834335],"type":"Point"}
}