{
  "type": "Feature",
  "properties": {
    "iso:country":"GB",
    "sg:address":"20 Park Place",
    "sg:city":"Stirling",
    "sg:classifiers":[
        {
            "category":"Health Services",
            "subcategory":"Health Practitioner",
            "type":"Services"
        }
    ],
    "sg:postcode":"FK7 9JR",
    "sg:province":"Falkirk",
    "sg:tags":[
        "physiotherapist"
    ],
    "wof:name":"Sheila W Cumming",
    "wof:placetype":"venue"
},
  "geometry": {"coordinates":[-3.952042,56.111938],"type":"Point"}
}