{
  "type": "Feature",
  "properties": {
    "addr:full":"1 Hazelhurst Fold, Worsley Manchester Greater Manchester M28 2JU",
    "addr:housenumber":"1",
    "addr:postcode":"m28 2ju",
    "addr:street":"Hazelhurst Fold",
    "iso:country":"GB",
    "sg:address":"1 Hazelhurst Fold, Worsley",
    "sg:city":"Manchester",
    "sg:classifiers":[
        {
            "category":"Organizations",
            "subcategory":"Community Association",
            "type":"Services"
        },
        {
            "category":"Organizations",
            "subcategory":"Membership Organization",
            "type":"Services"
        }
    ],
    "sg:phone":"+44 161 794 1735",
    "sg:postcode":"M28 2JU",
    "sg:province":"Greater Manchester",
    "sg:tags":[
        "club",
        "social"
    ],
    "wof:name":"Brackley Conservative Club",
    "wof:placetype":"venue"
},
  "geometry": {"coordinates":[-2.359919,53.508587],"type":"Point"}
}