{
  "type": "Feature",
  "properties": {
    "iso:country":"GB",
    "sg:address":"P O Box 40, Peasley Cross La, Peasley Cross",
    "sg:city":"St Helens",
    "sg:classifiers":[
        {
            "category":"Manufacturing",
            "subcategory":"Glass & Minerals",
            "type":"Manufacturing & Wholesale Goods"
        }
    ],
    "sg:phone":"+44 1744 22211",
    "sg:postcode":"WA9 3AN",
    "sg:province":"Cheshire",
    "sg:tags":[
        "product"
    ],
    "wof:name":"United Glass Ltd",
    "wof:placetype":"venue"
},
  "geometry": {"coordinates":[-2.71103,53.436001],"type":"Point"}
}