{
  "type": "Feature",
  "properties": {
    "iso:country":"GB",
    "sg:address":"345 Garratt Lane",
    "sg:city":"London",
    "sg:classifiers":[
        {
            "category":"Banks & Credit Unions",
            "subcategory":"Financial Services",
            "type":"Services"
        }
    ],
    "sg:postcode":"SW18 4DX",
    "sg:province":"Greater London",
    "sg:tags":[
        "consultant"
    ],
    "wof:name":"Carlton Tower Finance Ltd",
    "wof:placetype":"venue"
},
  "geometry": {"coordinates":[-0.18917,51.44603],"type":"Point"}
}