{
  "type": "Feature",
  "properties": {
    "iso:country":"GB",
    "sg:address":"57 Lovelace Avenue",
    "sg:city":"Bromley",
    "sg:classifiers":[
        {
            "category":"Professional",
            "subcategory":"Engineering",
            "type":"Services"
        }
    ],
    "sg:postcode":"BR2 8DG",
    "sg:province":"Kent",
    "sg:tags":[
        "contractor",
        "electrical",
        "engineer"
    ],
    "wof:name":"Abel Electrics & Plumbing",
    "wof:placetype":"venue"
},
  "geometry": {"coordinates":[0.059542,51.385685],"type":"Point"}
}