{
  "type": "Feature",
  "properties": {
    "addr:full":"70 Tredegar St Newport East Riding of Yorkshire NP1 6BW",
    "addr:housenumber":"70",
    "addr:postcode":"np1 6bw",
    "addr:street":"Tredegar St",
    "iso:country":"GB",
    "sg:address":"70 Tredegar St",
    "sg:city":"Newport",
    "sg:classifiers":[
        {
            "category":"Banks & Credit Unions",
            "subcategory":"Bank",
            "type":"Services"
        }
    ],
    "sg:phone":"+44 1633 612276",
    "sg:postcode":"NP1 6BW",
    "sg:province":"East Riding of Yorkshire",
    "wof:name":"NatWest",
    "wof:placetype":"venue"
},
  "geometry": {"coordinates":[-2.990473032,51.5809555054],"type":"Point"}
}