{
  "type": "Feature",
  "properties": {
    "addr:full":"8 Agents Row, Abernant Aberdare Neath Port Talbot CF44 0SW",
    "addr:housenumber":"8",
    "addr:postcode":"cf44 0sw",
    "addr:street":"Agents Row",
    "iso:country":"GB",
    "sg:address":"8 Agents Row, Abernant",
    "sg:city":"Aberdare",
    "sg:classifiers":[
        {
            "category":"Real Estate",
            "subcategory":"Real Estate Agent",
            "type":"Services"
        }
    ],
    "sg:postcode":"CF44 0SW",
    "sg:province":"Neath Port Talbot",
    "wof:name":"C P  Property Ltd.",
    "wof:placetype":"venue"
},
  "geometry": {"coordinates":[-3.429418087,51.7210464478],"type":"Point"}
}