{
  "type": "Feature",
  "properties": {
    "iso:country":"GB",
    "sg:address":"St.catherines Mill, Broad La",
    "sg:city":"Leeds",
    "sg:classifiers":[
        {
            "category":"Building & Trades",
            "subcategory":"Construction",
            "type":"Services"
        }
    ],
    "sg:phone":"+44 113 263 0895",
    "sg:postcode":"LS13 2TD",
    "sg:province":"West Yorkshire",
    "sg:tags":[
        "roofing"
    ],
    "wof:name":"Bramley Roofing",
    "wof:placetype":"venue"
},
  "geometry": {"coordinates":[-1.623052,53.818275],"type":"Point"}
}