{
  "type": "Feature",
  "properties": {
    "iso:country":"GB",
    "sg:address":"63a High Street",
    "sg:city":"Bridgnorth",
    "sg:classifiers":[
        {
            "category":"Real Estate",
            "subcategory":"Architect",
            "type":"Services"
        }
    ],
    "sg:phone":"+44 1746 765923",
    "sg:postcode":"WV16 4DX",
    "sg:province":"Shropshire",
    "wof:name":"Bolton Lomas Bradshaw",
    "wof:placetype":"venue"
},
  "geometry": {"coordinates":[-2.419525,52.535702],"type":"Point"}
}