{
  "type": "Feature",
  "properties": {
    "addr:full":"158 New Cavendish St West End Hampshire W1M 7FJ",
    "addr:housenumber":"158",
    "addr:postcode":"w1m 7fj",
    "addr:street":"New Cavendish St",
    "iso:country":"GB",
    "sg:address":"158 New Cavendish St",
    "sg:city":"West End",
    "sg:classifiers":[
        {
            "category":"Professional",
            "subcategory":"Management & Consulting",
            "type":"Services"
        }
    ],
    "sg:phone":"+44 20 7255 1988",
    "sg:postcode":"W1M 7FJ",
    "sg:province":"Hampshire",
    "sg:tags":[
        "marketing",
        "consultant"
    ],
    "wof:name":"Ramtor International",
    "wof:placetype":"venue"
},
  "geometry": {"coordinates":[-0.139495,51.520557],"type":"Point"}
}