{
  "type": "Feature",
  "properties": {
    "addr:full":"18 Cambridge Walks Southport Lancashire PR8 1EN",
    "addr:housenumber":"18",
    "addr:postcode":"pr8 1en",
    "addr:street":"Cambridge Walks",
    "iso:country":"GB",
    "sg:address":"18 Cambridge Walks",
    "sg:city":"Southport",
    "sg:classifiers":[
        {
            "category":"Personal",
            "type":"Services"
        }
    ],
    "sg:phone":"+44 1704 533173",
    "sg:postcode":"PR8 1EN",
    "sg:province":"Lancashire",
    "sg:tags":[
        "wedding"
    ],
    "wof:name":"Silks and Satins",
    "wof:placetype":"venue"
},
  "geometry": {"coordinates":[-3.011548996,53.6467895508],"type":"Point"}
}