{
  "type": "Feature",
  "properties": {
    "iso:country":"GB",
    "sg:address":"48 High Street",
    "sg:city":"Crawley",
    "sg:classifiers":[
        {
            "category":"Professional",
            "subcategory":"Employment Agencies",
            "type":"Services"
        }
    ],
    "sg:phone":"+44 1293 553371",
    "sg:postcode":"RH10 1BW",
    "sg:province":"Surrey",
    "sg:tags":[
        "consultant"
    ],
    "wof:name":"Plan Personnel",
    "wof:placetype":"venue"
},
  "geometry": {"coordinates":[-0.190322,51.113834],"type":"Point"}
}