{
  "type": "Feature",
  "properties": {
    "addr:full":"119 King Street Stoke-on-trent Staffordshire ST4 3NA",
    "addr:housenumber":"119",
    "addr:postcode":"st4 3na",
    "addr:street":"King Street",
    "iso:country":"GB",
    "sg:address":"119 King Street",
    "sg:city":"Stoke-on-trent",
    "sg:classifiers":[
        {
            "category":"Fast Food",
            "type":"Food & Drink"
        }
    ],
    "sg:phone":"+44 1782 594623",
    "sg:postcode":"ST4 3NA",
    "sg:province":"Staffordshire",
    "sg:tags":[
        "away",
        "take"
    ],
    "wof:name":"Happy House",
    "wof:placetype":"venue"
},
  "geometry": {"coordinates":[-2.153111,52.997322],"type":"Point"}
}