{
  "type": "Feature",
  "properties": {
    "iso:country":"GB",
    "sg:address":"Woodside Road",
    "sg:city":"Sidcup",
    "sg:classifiers":[
        {
            "category":"Education",
            "subcategory":"School",
            "type":"Public Place"
        }
    ],
    "sg:phone":"+44 20 8300 2368",
    "sg:postcode":"DA15 7JG",
    "sg:province":"Kent",
    "sg:tags":[
        "local",
        "authority"
    ],
    "wof:name":"Longlands Primary School",
    "wof:placetype":"venue"
},
  "geometry": {"coordinates":[0.091332,51.431885],"type":"Point"}
}