{
  "type": "Feature",
  "properties": {
    "addr:full":"23 Station Road Burry Port Carmarthenshire SA16 0LP",
    "addr:housenumber":"23",
    "addr:postcode":"sa16 0lp",
    "addr:street":"Station Road",
    "iso:country":"GB",
    "sg:address":"23 Station Road",
    "sg:city":"Burry Port",
    "sg:classifiers":[
        {
            "category":"Food & Beverages",
            "subcategory":"Groceries & Convenience Stores",
            "type":"Retail Goods"
        }
    ],
    "sg:phone":"+44 1554 832640",
    "sg:postcode":"SA16 0LP",
    "sg:province":"Carmarthenshire",
    "wof:name":"Burry Spar",
    "wof:placetype":"venue"
},
  "geometry": {"coordinates":[-4.246865,51.684311],"type":"Point"}
}