{
  "type": "Feature",
  "properties": {
    "iso:country":"GB",
    "sg:address":"Powis Pl",
    "sg:city":"Aberdeen",
    "sg:classifiers":[
        {
            "category":"Place Of Worship",
            "type":"Public Place"
        }
    ],
    "sg:phone":"+44 1224 624443",
    "sg:postcode":"AB25 3TT",
    "sg:province":"Aberdeen City",
    "wof:name":"St Stephens Church",
    "wof:placetype":"venue"
},
  "geometry": {"coordinates":[-2.115548,57.157799],"type":"Point"}
}