{
  "type": "Feature",
  "properties": {
    "iso:country":"GB",
    "sg:address":"Old Fire Station, Seven Sisters",
    "sg:city":"Neath",
    "sg:classifiers":[
        {
            "category":"Building & Trades",
            "subcategory":"Construction",
            "type":"Services"
        }
    ],
    "sg:phone":"+44 1639 701412",
    "sg:postcode":"SA10 9EB",
    "sg:province":"Neath Port Talbot",
    "sg:tags":[
        "contractor"
    ],
    "wof:name":"H & H Construction (Neath) Ltd.",
    "wof:placetype":"venue"
},
  "geometry": {"coordinates":[-3.7076489925,51.7684631348],"type":"Point"}
}