{
  "type": "Feature",
  "properties": {
    "iso:country":"GB",
    "sg:address":"147a Kilburn High Rd",
    "sg:city":"Kilburn",
    "sg:classifiers":[
        {
            "category":"Farming",
            "subcategory":"Fish & Marine Products",
            "type":"Manufacturing & Wholesale Goods"
        }
    ],
    "sg:phone":"+44 20 7624 0356",
    "sg:postcode":"NW6 7HT",
    "sg:province":"Greater London",
    "sg:tags":[
        "fishmonger"
    ],
    "wof:name":"B & J Fisheries",
    "wof:placetype":"venue"
},
  "geometry": {"coordinates":[-0.195898,51.539928],"type":"Point"}
}