{
  "type": "Feature",
  "properties": {
    "iso:country":"GB",
    "sg:address":"36 Coed Isaf Road",
    "sg:city":"Pontypridd",
    "sg:classifiers":[
        {
            "category":"Professional",
            "subcategory":"Printing & Photocopies",
            "type":"Services"
        }
    ],
    "sg:postcode":"CF37 1EL",
    "sg:province":"Caerphilly",
    "sg:tags":[
        "printer"
    ],
    "wof:name":"Acorn Business Forms",
    "wof:placetype":"venue"
},
  "geometry": {"coordinates":[-3.353433,51.599316],"type":"Point"}
}