{
  "type": "Feature",
  "properties": {
    "addr:full":"95 Danson Cres Welling Kent DA16 2AR",
    "addr:housenumber":"95",
    "addr:postcode":"da16 2ar",
    "addr:street":"Danson Cres Welling",
    "iso:country":"GB",
    "sg:address":"95 Danson Cres",
    "sg:city":"Welling",
    "sg:classifiers":[
        {
            "category":"Professional",
            "subcategory":"Art Services",
            "type":"Services"
        }
    ],
    "sg:postcode":"DA16 2AR",
    "sg:province":"Kent",
    "sg:tags":[
        "photographer"
    ],
    "wof:name":"Jones,Brian,",
    "wof:placetype":"venue"
},
  "geometry": {"coordinates":[0.1096649989,51.4585876465],"type":"Point"}
}