{
  "type": "Feature",
  "properties": {
    "addr:full":"5/7 New York Rd Leeds West Yorkshire LS2 7AJ",
    "addr:housenumber":"5 / 7",
    "addr:postcode":"ls2 7aj",
    "addr:street":"New York Rd",
    "iso:country":"GB",
    "sg:address":"5/7 New York Rd",
    "sg:city":"Leeds",
    "sg:classifiers":[
        {
            "category":"Real Estate",
            "subcategory":"Real Estate Agent",
            "type":"Services"
        }
    ],
    "sg:postcode":"LS2 7AJ",
    "sg:province":"West Yorkshire",
    "wof:name":"Shireavon Properties Ltd",
    "wof:placetype":"venue"
},
  "geometry": {"coordinates":[-1.538146019,53.8009986877],"type":"Point"}
}