{
  "type": "Feature",
  "properties": {
    "iso:country":"GB",
    "sg:address":"346 Shirley Road, Shirley",
    "sg:city":"Southampton",
    "sg:classifiers":[
        {
            "category":"Professional",
            "subcategory":"Detective & Security Services",
            "type":"Services"
        }
    ],
    "sg:phone":"+44 23 8078 8422",
    "sg:postcode":"SO15 3HJ",
    "sg:province":"Hampshire",
    "sg:tags":[
        "equipment",
        "installers"
    ],
    "wof:name":"Css Total Security Ltd.",
    "wof:placetype":"venue"
},
  "geometry": {"coordinates":[-1.427747,50.917755],"type":"Point"}
}