{
  "type": "Feature",
  "properties": {
    "addr:full":"26 George Street Altrincham Cheshire WA14 1RH",
    "addr:housenumber":"26",
    "addr:postcode":"wa14 1rh",
    "addr:street":"George Street",
    "iso:country":"GB",
    "sg:address":"26 George Street",
    "sg:city":"Altrincham",
    "sg:classifiers":[
        {
            "category":"Shopping",
            "subcategory":"Beauty & Cosmetics",
            "type":"Retail Goods"
        }
    ],
    "sg:postcode":"WA14 1RH",
    "sg:province":"Cheshire",
    "sg:tags":[
        "product"
    ],
    "wof:name":"Body Shop",
    "wof:placetype":"venue"
},
  "geometry": {"coordinates":[-2.350018,53.387314],"type":"Point"}
}