{
  "type": "Feature",
  "properties": {
    "iso:country":"GB",
    "sg:address":"Woodlands Mill, Luke Lane, Thongsbridge",
    "sg:city":"Huddersfield",
    "sg:classifiers":[
        {
            "category":"Manufacturing",
            "subcategory":"Paper Products",
            "type":"Manufacturing & Wholesale Goods"
        }
    ],
    "sg:phone":"+44 1484 683126",
    "sg:postcode":"HD9 7TB",
    "sg:province":"South Yorkshire",
    "sg:tags":[
        "mill",
        "pulp"
    ],
    "wof:name":"Moorland Wood Turning Co. Ltd.",
    "wof:placetype":"venue"
},
  "geometry": {"coordinates":[-1.771412015,53.5852355957],"type":"Point"}
}