{
  "type": "Feature",
  "properties": {
    "iso:country":"GB",
    "sg:address":"Unit D2, Valley Way",
    "sg:city":"Market Harborough",
    "sg:classifiers":[
        {
            "category":"Retail",
            "subcategory":"Auto Repair",
            "type":"Services"
        }
    ],
    "sg:phone":"+44 1858 433428",
    "sg:postcode":"LE16 7PS",
    "sg:province":"Leicestershire",
    "sg:tags":[
        "garage"
    ],
    "wof:name":"S.J Vaughan Garage Equipment Services",
    "wof:placetype":"venue"
},
  "geometry": {"coordinates":[-0.902598,52.482483],"type":"Point"}
}