{
  "type": "Feature",
  "properties": {
    "addr:full":"90 Barton Road Lancaster Lancashire LA1 4EL",
    "addr:housenumber":"90",
    "addr:postcode":"la1 4el",
    "addr:street":"Barton Road",
    "iso:country":"GB",
    "sg:address":"90 Barton Road",
    "sg:city":"Lancaster",
    "sg:classifiers":[
        {
            "category":"Health Services",
            "subcategory":"Health Practitioner",
            "type":"Services"
        }
    ],
    "sg:phone":"+44 1524 64706",
    "sg:postcode":"LA1 4EL",
    "sg:province":"Lancashire",
    "sg:tags":[
        "physiotherapist"
    ],
    "wof:name":"C Fisher M C S P S R P",
    "wof:placetype":"venue"
},
  "geometry": {"coordinates":[-2.793601,54.030491],"type":"Point"}
}