{
  "type": "Feature",
  "properties": {
    "iso:country":"GB",
    "sg:address":"25 Dublin St",
    "sg:city":"Liverpool",
    "sg:classifiers":[
        {
            "category":"Retail",
            "subcategory":"Auto Repair",
            "type":"Services"
        }
    ],
    "sg:phone":"+44 151 236 4079",
    "sg:postcode":"L3 7DT",
    "sg:province":"Merseyside",
    "sg:tags":[
        "modification",
        "garage"
    ],
    "wof:name":"Euroclutch",
    "wof:placetype":"venue"
},
  "geometry": {"coordinates":[-2.999533,53.419697],"type":"Point"}
}