{
  "type": "Feature",
  "properties": {
    "addr:full":"North End Farm, Longframlington Morpeth Northumberland NE65 8DZ",
    "addr:postcode":"ne65 8dz",
    "addr:street":"End",
    "iso:country":"GB",
    "sg:address":"North End Farm, Longframlington",
    "sg:city":"Morpeth",
    "sg:classifiers":[
        {
            "category":"Farming",
            "subcategory":"Livestock Farm",
            "type":"Manufacturing & Wholesale Goods"
        }
    ],
    "sg:postcode":"NE65 8DZ",
    "sg:province":"Northumberland",
    "sg:tags":[
        "others"
    ],
    "wof:name":"A E Thorne",
    "wof:placetype":"venue"
},
  "geometry": {"coordinates":[-1.794284,55.303215],"type":"Point"}
}