{
  "type": "Feature",
  "properties": {
    "addr:full":"St Christopher School, Barrington Road Letchworth Hertfordshire SG6 3JZ",
    "addr:postcode":"sg6 3jz",
    "addr:street":"St;Barrington Road",
    "iso:country":"GB",
    "sg:address":"St Christopher School, Barrington Road",
    "sg:city":"Letchworth",
    "sg:classifiers":[
        {
            "category":"Education",
            "subcategory":"School",
            "type":"Public Place"
        }
    ],
    "sg:phone":"+44 1462 679301",
    "sg:postcode":"SG6 3JZ",
    "sg:province":"Hertfordshire",
    "sg:tags":[
        "independent",
        "preparatory"
    ],
    "wof:name":"St.Christopher School Guilds Ltd.",
    "wof:placetype":"venue"
},
  "geometry": {"coordinates":[-0.222243,51.972549],"type":"Point"}
}