{
  "type": "Feature",
  "properties": {
    "iso:country":"GB",
    "sg:address":"The Cider House, Halmore Lane, Halmore",
    "sg:city":"Berkeley",
    "sg:classifiers":[
        {
            "category":"Building & Trades",
            "subcategory":"Construction",
            "type":"Services"
        }
    ],
    "sg:phone":"+44 1453 811589",
    "sg:postcode":"GL13 9HQ",
    "sg:province":"Gloucestershire",
    "sg:tags":[
        "builder"
    ],
    "wof:name":"R Williams Building & Groundworks Ltd.",
    "wof:placetype":"venue"
},
  "geometry": {"coordinates":[-2.4359140396,51.7147407532],"type":"Point"}
}