{
  "type": "Feature",
  "properties": {
    "iso:country":"GB",
    "sg:address":"27 Craigie Park",
    "sg:city":"Aberdeen",
    "sg:classifiers":[
        {
            "category":"Communications",
            "subcategory":"News Services",
            "type":"Services"
        }
    ],
    "sg:phone":"+44 1224 643519",
    "sg:postcode":"AB25 2SE",
    "sg:province":"Aberdeen City",
    "sg:tags":[
        "photo",
        "agency",
        "journalist"
    ],
    "wof:name":"Ann Malcolm",
    "wof:placetype":"venue"
},
  "geometry": {"coordinates":[-2.1225290298,57.1479492188],"type":"Point"}
}