{
  "type": "Feature",
  "properties": {
    "addr:full":"11 Vicarage Pl Walsall West Midlands WS1 3NA",
    "addr:housenumber":"11",
    "addr:postcode":"ws1 3na",
    "addr:street":"Vicarage Pl",
    "iso:country":"GB",
    "sg:address":"11 Vicarage Pl",
    "sg:city":"Walsall",
    "sg:classifiers":[
        {
            "category":"Professional",
            "subcategory":"Secretarial Services",
            "type":"Services"
        }
    ],
    "sg:phone":"+44 1922 451569",
    "sg:postcode":"WS1 3NA",
    "sg:province":"West Midlands",
    "wof:name":"First Service",
    "wof:placetype":"venue"
},
  "geometry": {"coordinates":[-1.983485,52.580811],"type":"Point"}
}