{
  "type": "Feature",
  "properties": {
    "iso:country":"GB",
    "sg:address":"6 Victoria Square",
    "sg:city":"Truro",
    "sg:classifiers":[
        {
            "category":"Home & Garden",
            "subcategory":"Hardware",
            "type":"Retail Goods"
        }
    ],
    "sg:phone":"+44 1872 274441",
    "sg:postcode":"TR1 2RT",
    "sg:province":"Cornwall",
    "wof:name":"Mallett & Son  Ltd.",
    "wof:placetype":"venue"
},
  "geometry": {"coordinates":[-5.053382,50.262924],"type":"Point"}
}