{
  "type": "Feature",
  "properties": {
    "addr:full":"Grove Works Brighouse West Yorkshire HD6 3NR",
    "addr:postcode":"hd6 3nr",
    "addr:street":"Brighouse West",
    "iso:country":"GB",
    "sg:address":"Grove Works",
    "sg:city":"Brighouse",
    "sg:classifiers":[
        {
            "category":"Home & Garden",
            "subcategory":"Building Materials",
            "type":"Retail Goods"
        }
    ],
    "sg:phone":"+44 1484 401540",
    "sg:postcode":"HD6 3NR",
    "sg:province":"West Yorkshire",
    "sg:tags":[
        "window",
        "frame"
    ],
    "wof:name":"U P V C Systems",
    "wof:placetype":"venue"
},
  "geometry": {"coordinates":[-1.7936389446,53.6918106079],"type":"Point"}
}