{
  "type": "Feature",
  "properties": {
    "addr:full":"26 Hollyshaw La Leeds West Yorkshire LS15 7BD",
    "addr:housenumber":"26",
    "addr:postcode":"ls15 7bd",
    "addr:street":"Hollyshaw La Leeds West",
    "iso:country":"GB",
    "sg:address":"26 Hollyshaw La",
    "sg:city":"Leeds",
    "sg:classifiers":[
        {
            "category":"Building & Trades",
            "subcategory":"Construction",
            "type":"Services"
        }
    ],
    "sg:postcode":"LS15 7BD",
    "sg:province":"West Yorkshire",
    "sg:tags":[
        "roofing"
    ],
    "wof:name":"Sutcliffe,John,",
    "wof:placetype":"venue"
},
  "geometry": {"coordinates":[-1.4497859478,53.7997589111],"type":"Point"}
}