{
  "type": "Feature",
  "properties": {
    "addr:full":"1 The Square, Chalfont Way Reading Berkshire RG6 5HJ",
    "addr:housenumber":"1",
    "addr:postcode":"rg6 5hj",
    "addr:street":"The Square Chalfont Way",
    "iso:country":"GB",
    "sg:address":"1 The Square, Chalfont Way",
    "sg:city":"Reading",
    "sg:classifiers":[
        {
            "category":"Autos & Motor Vehicles",
            "subcategory":"Fuel & Gas Station",
            "type":"Retail Goods"
        }
    ],
    "sg:postcode":"RG6 5HJ",
    "sg:province":"Berkshire",
    "sg:tags":[
        "hr",
        "petrol"
    ],
    "wof:name":"Fraser Garages Ltd",
    "wof:placetype":"venue"
},
  "geometry": {"coordinates":[-0.9344300032,51.4231910706],"type":"Point"}
}