{
  "type": "Feature",
  "properties": {
    "addr:full":"56 Pill Street Penarth The Vale of Glamorgan CF64 2JR",
    "addr:housenumber":"56",
    "addr:postcode":"cf64 2jr",
    "addr:street":"Pill Street;Vale",
    "iso:country":"GB",
    "sg:address":"56 Pill Street",
    "sg:city":"Penarth",
    "sg:classifiers":[
        {
            "category":"Building & Trades",
            "subcategory":"Construction",
            "type":"Services"
        }
    ],
    "sg:phone":"+44 29 2070 1777",
    "sg:postcode":"CF64 2JR",
    "sg:province":"The Vale of Glamorgan",
    "sg:tags":[
        "builder"
    ],
    "wof:name":"Peter Akers Builders",
    "wof:placetype":"venue"
},
  "geometry": {"coordinates":[-3.186985,51.444424],"type":"Point"}
}