{
  "type": "Feature",
  "properties": {
    "iso:country":"GB",
    "sg:address":"5 Central Circus",
    "sg:city":"Hendon",
    "sg:classifiers":[
        {
            "category":"Banks & Credit Unions",
            "subcategory":"Bank",
            "type":"Services"
        }
    ],
    "sg:phone":"+44 845 605 1605",
    "sg:postcode":"NW4 3LA",
    "sg:province":"Greater London",
    "sg:tags":[
        "financial",
        "institution"
    ],
    "sg:website":"http://www.natwest.co.uk",
    "wof:name":"Natwest",
    "wof:placetype":"venue"
},
  "geometry": {"coordinates":[-0.22766,51.582481],"type":"Point"}
}