{
  "type": "Feature",
  "properties": {
    "addr:full":"Four Winds, Hermitage Road Rochester Kent ME3 7ND",
    "addr:postcode":"me3 7nd",
    "addr:street":"Hermitage Road Rochester",
    "iso:country":"GB",
    "sg:address":"Four Winds, Hermitage Road",
    "sg:city":"Rochester",
    "sg:classifiers":[
        {
            "category":"Professional",
            "subcategory":"Engineering",
            "type":"Services"
        }
    ],
    "sg:postcode":"ME3 7ND",
    "sg:province":"Kent",
    "sg:tags":[
        "contractor",
        "electrical",
        "engineer"
    ],
    "wof:name":"Currie Electrical & Plumbing",
    "wof:placetype":"venue"
},
  "geometry": {"coordinates":[0.47974,51.417881],"type":"Point"}
}