{
  "type": "Feature",
  "properties": {
    "addr:full":"3 Old Rectory Court, Bicester Road, Middleton Stoney Bicester Oxfordshire OX25 4TD",
    "addr:housenumber":"3",
    "addr:postcode":"ox25 4td",
    "addr:street":"Old Rectory Court Bicester Road",
    "iso:country":"GB",
    "sg:address":"3 Old Rectory Court, Bicester Road, Middleton Stoney",
    "sg:city":"Bicester",
    "sg:classifiers":[
        {
            "category":"Building & Trades",
            "subcategory":"Construction",
            "type":"Services"
        }
    ],
    "sg:phone":"+44 1869 343556",
    "sg:postcode":"OX25 4TD",
    "sg:province":"Oxfordshire",
    "sg:tags":[
        "builder"
    ],
    "wof:name":"Bernard Sporn",
    "wof:placetype":"venue"
},
  "geometry": {"coordinates":[-1.2253680229,51.9076461792],"type":"Point"}
}