{
  "type": "Feature",
  "properties": {
    "iso:country":"GB",
    "sg:address":"16 Rhydypenau Road",
    "sg:city":"Cardiff",
    "sg:classifiers":[
        {
            "category":"Shopping",
            "subcategory":"Department Store",
            "type":"Retail Goods"
        }
    ],
    "sg:postcode":"CF23 6PT",
    "sg:province":"Cardiff",
    "wof:name":"A Giudice",
    "wof:placetype":"venue"
},
  "geometry": {"coordinates":[-3.1774361134,51.5207557678],"type":"Point"}
}