{
  "type": "Feature",
  "properties": {
    "addr:full":"23 Market Pl Manchester Greater Manchester M24 6AE",
    "addr:housenumber":"23",
    "addr:postcode":"m24 6ae",
    "addr:street":"Market Pl",
    "iso:country":"GB",
    "sg:address":"23 Market Pl",
    "sg:city":"Manchester",
    "sg:classifiers":[
        {
            "category":"Restaurant",
            "type":"Food & Drink"
        }
    ],
    "sg:phone":"+44 161 643 6106",
    "sg:postcode":"M24 6AE",
    "sg:province":"Greater Manchester",
    "wof:name":"Awaz",
    "wof:placetype":"venue"
},
  "geometry": {"coordinates":[-2.194872,53.551262],"type":"Point"}
}