{
  "type": "Feature",
  "properties": {
    "iso:country":"GB",
    "sg:address":"23 Market Pl",
    "sg:city":"Manchester",
    "sg:classifiers":[
        {
            "category":"Restaurant",
            "type":"Food & Drink"
        }
    ],
    "sg:phone":"+44 161 643 6106",
    "sg:postcode":"M24 6AE",
    "sg:province":"Greater Manchester",
    "wof:name":"Awaz",
    "wof:placetype":"venue"
},
  "geometry": {"coordinates":[-2.194872,53.551262],"type":"Point"}
}