{
  "type": "Feature",
  "properties": {
    "addr:full":"Cranmore Hall, East Cranmore Shepton Mallet Somerset BA4 4SF",
    "addr:postcode":"ba4 4sf",
    "addr:street":"East",
    "iso:country":"GB",
    "sg:address":"Cranmore Hall, East Cranmore",
    "sg:city":"Shepton Mallet",
    "sg:classifiers":[
        {
            "category":"Education",
            "subcategory":"School",
            "type":"Public Place"
        }
    ],
    "sg:phone":"+44 1749 880227",
    "sg:postcode":"BA4 4SF",
    "sg:province":"Somerset",
    "sg:tags":[
        "independent",
        "preparatory",
        "local",
        "authority"
    ],
    "wof:name":"All Hallows (Cranmore Hall) School Trust Ltd.",
    "wof:placetype":"venue"
},
  "geometry": {"coordinates":[-2.465502,51.189514],"type":"Point"}
}