{
  "type": "Feature",
  "properties": {
    "addr:full":"14 Kings Rd Rochdale Lancashire OL16 5HW",
    "addr:housenumber":"14",
    "addr:postcode":"ol16 5hw",
    "addr:street":"Kings Rd",
    "iso:country":"GB",
    "sg:address":"14 Kings Rd",
    "sg:city":"Rochdale",
    "sg:classifiers":[
        {
            "category":"Personal",
            "type":"Services"
        }
    ],
    "sg:postcode":"OL16 5HW",
    "sg:province":"Lancashire",
    "sg:tags":[
        "dressmaker"
    ],
    "wof:name":"Solo Original Designs",
    "wof:placetype":"venue"
},
  "geometry": {"coordinates":[-2.141888,53.605679],"type":"Point"}
}