{
  "type": "Feature",
  "properties": {
    "addr:full":"Unit 4, Heol Stanllyd Llanelli Carmarthenshire SA14 6RB",
    "addr:housenumber":"unit 4",
    "addr:postcode":"sa14 6rb",
    "addr:street":"Heol Stanllyd;Carmarthenshire",
    "iso:country":"GB",
    "sg:address":"Unit 4, Heol Stanllyd",
    "sg:city":"Llanelli",
    "sg:classifiers":[
        {
            "category":"Manufacturing",
            "subcategory":"Petroleum Products",
            "type":"Manufacturing & Wholesale Goods"
        }
    ],
    "sg:phone":"+44 1269 845377",
    "sg:postcode":"SA14 6RB",
    "sg:province":"Carmarthenshire",
    "sg:tags":[
        "double",
        "glazing"
    ],
    "wof:name":"Seal (U P V C Products) Ltd.",
    "wof:placetype":"venue"
},
  "geometry": {"coordinates":[-4.0828790665,51.7969245911],"type":"Point"}
}