{
  "type": "Feature",
  "properties": {
    "addr:full":"8 Kathleen Ferrier Crescent Basildon Essex SS15 5RA",
    "addr:housenumber":"8",
    "addr:postcode":"ss15 5ra",
    "addr:street":"Kathleen Ferrier Crescent",
    "iso:country":"GB",
    "sg:address":"8 Kathleen Ferrier Crescent",
    "sg:city":"Basildon",
    "sg:classifiers":[
        {
            "category":"Building & Trades",
            "subcategory":"Equipment Rental",
            "type":"Services"
        },
        {
            "category":"Building & Trades",
            "subcategory":"Construction",
            "type":"Services"
        }
    ],
    "sg:phone":"+44 1268 412092",
    "sg:postcode":"SS15 5RA",
    "sg:province":"Essex",
    "sg:tags":[
        "plant",
        "machinery"
    ],
    "wof:name":"Keith John Marshall",
    "wof:placetype":"venue"
},
  "geometry": {"coordinates":[0.4282380044,51.5817642212],"type":"Point"}
}