{
  "type": "Feature",
  "properties": {
    "addr:full":"Chester Rd, Little Budworth Tarporley Cheshire CW6 9EY",
    "addr:postcode":"cw6 9ey",
    "addr:street":"Chester Rd",
    "iso:country":"GB",
    "sg:address":"Chester Rd, Little Budworth",
    "sg:city":"Tarporley",
    "sg:classifiers":[
        {
            "category":"Bars & Pubs",
            "type":"Food & Drink"
        }
    ],
    "sg:phone":"+44 1829 760240",
    "sg:postcode":"CW6 9EY",
    "sg:province":"Cheshire",
    "sg:tags":[
        "pubs",
        "inn"
    ],
    "wof:name":"Shrewsbury Arms",
    "wof:placetype":"venue"
},
  "geometry": {"coordinates":[-2.6229009628,53.199256897],"type":"Point"}
}