{
  "type": "Feature",
  "properties": {
    "addr:full":"St Asaph Avenue North, Kinmel Bay Rhyl Conwy LL18 5EQ",
    "addr:postcode":"ll18 5eq",
    "addr:street":"St Asaph Avenue North",
    "iso:country":"GB",
    "sg:address":"St Asaph Avenue North, Kinmel Bay",
    "sg:city":"Rhyl",
    "sg:classifiers":[
        {
            "category":"Food & Beverages",
            "subcategory":"Supermarket",
            "type":"Retail Goods"
        }
    ],
    "sg:phone":"+44 1745 343466",
    "sg:postcode":"LL18 5EQ",
    "sg:province":"Conwy",
    "wof:name":"Asda Stores Ltd.",
    "wof:placetype":"venue"
},
  "geometry": {"coordinates":[-3.519778,53.310558],"type":"Point"}
}