{
  "type": "Feature",
  "properties": {
    "iso:country":"GB",
    "sg:address":"2 Vynes Farm, Trendlewood Way",
    "sg:city":"Bristol",
    "sg:classifiers":[
        {
            "category":"Building & Trades",
            "subcategory":"Construction",
            "type":"Services"
        }
    ],
    "sg:postcode":"BS48 1SX",
    "sg:province":"Somerset",
    "sg:tags":[
        "glazier",
        "decorator",
        "painter"
    ],
    "wof:name":"A B Ferrier",
    "wof:placetype":"venue"
},
  "geometry": {"coordinates":[-2.74476,51.433071],"type":"Point"}
}