{
  "type": "Feature",
  "properties": {
    "iso:country":"GB",
    "sg:address":"523 Katherine Road",
    "sg:city":"London",
    "sg:classifiers":[
        {
            "category":"Home & Garden",
            "subcategory":"Furniture",
            "type":"Retail Goods"
        }
    ],
    "sg:phone":"+44 20 8471 8812",
    "sg:postcode":"E7 8EB",
    "sg:province":"Greater London",
    "wof:name":"All Solid Pine Shop",
    "wof:placetype":"venue"
},
  "geometry": {"coordinates":[0.0362490006,51.5462417603],"type":"Point"}
}