{
  "type": "Feature",
  "properties": {
    "addr:full":"9 Earl Grey Street Mauchline East Ayrshire KA5 5AB",
    "addr:housenumber":"9",
    "addr:postcode":"ka5 5ab",
    "addr:street":"Earl Grey Street",
    "iso:country":"GB",
    "sg:address":"9 Earl Grey Street",
    "sg:city":"Mauchline",
    "sg:classifiers":[
        {
            "category":"Professional",
            "subcategory":"Lawyer & Legal Services",
            "type":"Services"
        }
    ],
    "sg:phone":"+44 1290 550249",
    "sg:postcode":"KA5 5AB",
    "sg:province":"East Ayrshire",
    "sg:tags":[
        "solicitor"
    ],
    "wof:name":"J D & S Macmillan",
    "wof:placetype":"venue"
},
  "geometry": {"coordinates":[-4.378685,55.515682],"type":"Point"}
}