{
  "type": "Feature",
  "properties": {
    "iso:country":"GB",
    "sg:address":"Halesfield",
    "sg:city":"Telford",
    "sg:classifiers":[
        {
            "category":"Home & Garden",
            "subcategory":"Hardware",
            "type":"Retail Goods"
        }
    ],
    "sg:phone":"+44 1952 582882",
    "sg:postcode":"TF7 4QT",
    "sg:province":"Shropshire",
    "sg:tags":[
        "device",
        "fixing",
        "fastener"
    ],
    "wof:name":"T R Fastenings",
    "wof:placetype":"venue"
},
  "geometry": {"coordinates":[-2.438294,52.63871],"type":"Point"}
}