{
  "type": "Feature",
  "properties": {
    "addr:full":"82-90 Kelvin Avenue, Hillington Industrial Estate Glasgow Glasgow City G52 4LT",
    "addr:housenumber":"82-90",
    "addr:postcode":"g52 4lt",
    "addr:street":"Kelvin Avenue;Industrial Estate",
    "iso:country":"GB",
    "sg:address":"82-90 Kelvin Avenue, Hillington Industrial Estate",
    "sg:city":"Glasgow",
    "sg:classifiers":[
        {
            "category":"Shopping",
            "subcategory":"Beauty & Cosmetics",
            "type":"Retail Goods"
        }
    ],
    "sg:phone":"+44 141 882 8300",
    "sg:postcode":"G52 4LT",
    "sg:province":"Glasgow City",
    "sg:tags":[
        "product"
    ],
    "wof:name":"Beauty Express",
    "wof:placetype":"venue"
},
  "geometry": {"coordinates":[-4.365028,55.861782],"type":"Point"}
}