{
  "type": "Feature",
  "properties": {
    "iso:country":"GB",
    "sg:address":"11 High Street, Eccleshall",
    "sg:city":"Stafford",
    "sg:classifiers":[
        {
            "category":"Food & Beverages",
            "subcategory":"Meat & Fish",
            "type":"Retail Goods"
        }
    ],
    "sg:phone":"+44 1785 850239",
    "sg:postcode":"ST21 6BZ",
    "sg:province":"Staffordshire",
    "sg:tags":[
        "butcher"
    ],
    "wof:name":"The Country Butchers",
    "wof:placetype":"venue"
},
  "geometry": {"coordinates":[-2.252233,52.859581],"type":"Point"}
}