{
  "type": "Feature",
  "properties": {
    "addr:full":"31 Beacon Gro Carshalton Surrey SM5 3BA",
    "addr:housenumber":"31",
    "addr:postcode":"sm5 3ba",
    "addr:street":"Beacon Gro",
    "iso:country":"GB",
    "sg:address":"31 Beacon Gro",
    "sg:city":"Carshalton",
    "sg:classifiers":[
        {
            "category":"Shopping",
            "subcategory":"Gifts & Souvenirs",
            "type":"Retail Goods"
        }
    ],
    "sg:phone":"+44 20 8715 0543",
    "sg:postcode":"SM5 3BA",
    "sg:province":"Surrey",
    "sg:tags":[
        "poster",
        "card"
    ],
    "wof:name":"Cheers",
    "wof:placetype":"venue"
},
  "geometry": {"coordinates":[-0.161094,51.365288],"type":"Point"}
}