{
  "type": "Feature",
  "properties": {
    "iso:country":"GB",
    "sg:address":"8 Gainsborough Court, Broadgate, Beeston",
    "sg:city":"Nottingham",
    "sg:classifiers":[
        {
            "category":"Retail",
            "subcategory":"Driving School",
            "type":"Services"
        }
    ],
    "sg:phone":"+44 115 922 9785",
    "sg:postcode":"NG9 2HZ",
    "sg:province":"Nottinghamshire",
    "wof:name":"J Underwood School of Motoring",
    "wof:placetype":"venue"
},
  "geometry": {"coordinates":[-1.20923,52.92971],"type":"Point"}
}