{
  "type": "Feature",
  "properties": {
    "iso:country":"GB",
    "sg:address":"45 Cowgate, Kirkintilloch",
    "sg:city":"Glasgow",
    "sg:classifiers":[
        {
            "category":"Banks & Credit Unions",
            "subcategory":"Bank",
            "type":"Services"
        }
    ],
    "sg:phone":"+44 845 765 4321",
    "sg:postcode":"G66 1HW",
    "sg:province":"East Dunbartonshire",
    "sg:tags":[
        "financial",
        "institution"
    ],
    "wof:name":"Abbey National Plc",
    "wof:placetype":"venue"
},
  "geometry": {"coordinates":[-4.1580839157,55.9406738281],"type":"Point"}
}