{
  "type": "Feature",
  "properties": {
    "addr:full":"81 Lakes Lane Newport Pagnell Buckinghamshire MK16 8HT",
    "addr:housenumber":"81",
    "addr:postcode":"mk16 8ht",
    "addr:street":"Lakes Lane",
    "iso:country":"GB",
    "sg:address":"81 Lakes Lane",
    "sg:city":"Newport Pagnell",
    "sg:classifiers":[
        {
            "category":"Building & Trades",
            "subcategory":"Construction",
            "type":"Services"
        }
    ],
    "sg:phone":"+44 1908 612398",
    "sg:postcode":"MK16 8HT",
    "sg:province":"Buckinghamshire",
    "sg:tags":[
        "builder"
    ],
    "wof:name":"Cummings Builders",
    "wof:placetype":"venue"
},
  "geometry": {"coordinates":[-0.7348939776,52.0875511169],"type":"Point"}
}