{
  "type": "Feature",
  "properties": {
    "iso:country":"GB",
    "sg:address":"10 Edensor Road",
    "sg:city":"Eastbourne",
    "sg:classifiers":[
        {
            "category":"Professional",
            "subcategory":"Computer Services",
            "type":"Services"
        }
    ],
    "sg:postcode":"BN20 7XR",
    "sg:province":"East Sussex",
    "sg:tags":[
        "system",
        "software"
    ],
    "wof:name":"Infoarch Ltd.",
    "wof:placetype":"venue"
},
  "geometry": {"coordinates":[0.2625330091,50.7525863647],"type":"Point"}
}