{
  "type": "Feature",
  "properties": {
    "addr:full":"207 Field Road, Bloxwich Walsall Staffordshire WS3 3NA",
    "addr:housenumber":"207",
    "addr:postcode":"ws3 3na",
    "addr:street":"Field Road",
    "iso:country":"GB",
    "sg:address":"207 Field Road, Bloxwich",
    "sg:city":"Walsall",
    "sg:classifiers":[
        {
            "category":"Building & Trades",
            "subcategory":"Construction",
            "type":"Services"
        }
    ],
    "sg:phone":"+44 1922 476084",
    "sg:postcode":"WS3 3NA",
    "sg:province":"Staffordshire",
    "sg:tags":[
        "builder"
    ],
    "wof:name":"Steventon E & Son",
    "wof:placetype":"venue"
},
  "geometry": {"coordinates":[-1.995535,52.621918],"type":"Point"}
}