{
  "type": "Feature",
  "properties": {
    "addr:full":"Laindon Ponds, Wash Road Basildon Essex SS15 4AZ",
    "addr:postcode":"ss15 4az",
    "addr:street":"Wash Road",
    "iso:country":"GB",
    "sg:address":"Laindon Ponds, Wash Road",
    "sg:city":"Basildon",
    "sg:classifiers":[
        {
            "category":"Professional",
            "subcategory":"Management & Consulting",
            "type":"Services"
        }
    ],
    "sg:postcode":"SS15 4AZ",
    "sg:province":"Essex",
    "sg:tags":[
        "consultant",
        "business"
    ],
    "wof:name":"Goldney Consultants Ltd.",
    "wof:placetype":"venue"
},
  "geometry": {"coordinates":[0.4445559978,51.5677947998],"type":"Point"}
}