{
  "type": "Feature",
  "properties": {
    "addr:full":"Boscombe House, 20 Station Street Ross-on-wye Gloucestershire HR9 7AG",
    "addr:housenumber":"20",
    "addr:postcode":"hr9 7ag",
    "addr:street":"Station Street",
    "iso:country":"GB",
    "sg:address":"Boscombe House, 20 Station Street",
    "sg:city":"Ross-on-wye",
    "sg:classifiers":[
        {
            "category":"Wholesale",
            "subcategory":"Books, Periodicals, & Newspapers",
            "type":"Manufacturing & Wholesale Goods"
        }
    ],
    "sg:phone":"+44 1989 769595",
    "sg:postcode":"HR9 7AG",
    "sg:province":"Gloucestershire",
    "sg:tags":[
        "maps",
        "globe",
        "chart",
        "pub"
    ],
    "wof:name":"Scenic Maps Ltd.",
    "wof:placetype":"venue"
},
  "geometry": {"coordinates":[-2.5799911022,51.9153556824],"type":"Point"}
}