{
  "type": "Feature",
  "properties": {
    "addr:full":"Bonnyview Road, Westheatheryfold Aberdeen Aberdeen City AB16 7FQ",
    "addr:postcode":"ab16 7fq",
    "addr:street":"Bonnyview Road Westheatheryfold",
    "iso:country":"GB",
    "sg:address":"Bonnyview Road, Westheatheryfold",
    "sg:city":"Aberdeen",
    "sg:classifiers":[
        {
            "category":"Sports & Exercise",
            "subcategory":"Golf",
            "type":"Entertainment"
        }
    ],
    "sg:phone":"+44 1224 715525",
    "sg:postcode":"AB16 7FQ",
    "sg:province":"Aberdeen City",
    "sg:tags":[
        "club",
        "course"
    ],
    "wof:name":"Auchmill Golf Club",
    "wof:placetype":"venue"
},
  "geometry": {"coordinates":[-2.172049,57.169285],"type":"Point"}
}