{
  "type": "Feature",
  "properties": {
    "addr:full":"83 Coles Avenue Poole Dorset BH15 4HJ",
    "addr:housenumber":"83",
    "addr:postcode":"bh15 4hj",
    "addr:street":"Coles Avenue",
    "iso:country":"GB",
    "sg:address":"83 Coles Avenue",
    "sg:city":"Poole",
    "sg:classifiers":[
        {
            "category":"Personal",
            "subcategory":"Beauty Salon",
            "type":"Services"
        }
    ],
    "sg:phone":"+44 1202 672252",
    "sg:postcode":"BH15 4HJ",
    "sg:province":"Dorset",
    "sg:tags":[
        "unisex",
        "hairdresser"
    ],
    "wof:name":"Mayze",
    "wof:placetype":"venue"
},
  "geometry": {"coordinates":[-2.0140841007,50.7148323059],"type":"Point"}
}