{
  "type": "Feature",
  "properties": {
    "addr:full":"64 Shelgate Rd, Battersea Battersea Greater London SW11 1BG",
    "addr:housenumber":"64",
    "addr:postcode":"sw11 1bg",
    "addr:street":"Shelgate Rd",
    "iso:country":"GB",
    "sg:address":"64 Shelgate Rd, Battersea",
    "sg:city":"Battersea",
    "sg:classifiers":[
        {
            "category":"Professional",
            "subcategory":"Engineering",
            "type":"Services"
        }
    ],
    "sg:phone":"+44 20 7978 7762",
    "sg:postcode":"SW11 1BG",
    "sg:province":"Greater London",
    "sg:tags":[
        "gas",
        "engineer"
    ],
    "wof:name":"Brendan Sloley",
    "wof:placetype":"venue"
},
  "geometry": {"coordinates":[-0.1643290073,51.4595870972],"type":"Point"}
}