{
  "type": "Feature",
  "properties": {
    "addr:full":"P O Box 69 York North Yorkshire YO1 6JY",
    "addr:housenumber":"box 69",
    "addr:postcode":"yo1 6jy",
    "addr:street":"P O;York",
    "iso:country":"GB",
    "sg:address":"P O Box 69",
    "sg:city":"York",
    "sg:classifiers":[
        {
            "category":"Professional",
            "subcategory":"Lawyer & Legal Services",
            "type":"Services"
        }
    ],
    "sg:phone":"+44 1904 686631",
    "sg:postcode":"YO1 6JY",
    "sg:province":"North Yorkshire",
    "sg:tags":[
        "solicitor"
    ],
    "wof:name":"Carrick Carr & Wright",
    "wof:placetype":"venue"
},
  "geometry": {"coordinates":[-1.0897500515,53.9567604065],"type":"Point"}
}