{
  "type": "Feature",
  "properties": {
    "addr:full":"70 St Helens Road Bolton Lancashire BL3 3NP",
    "addr:housenumber":"70",
    "addr:postcode":"bl3 3np",
    "addr:street":"St Helens Road",
    "iso:country":"GB",
    "sg:address":"70 St Helens Road",
    "sg:city":"Bolton",
    "sg:classifiers":[
        {
            "category":"Shopping",
            "subcategory":"Pharmacy",
            "type":"Retail Goods"
        }
    ],
    "sg:phone":"+44 1204 62289",
    "sg:postcode":"BL3 3NP",
    "sg:province":"Lancashire",
    "sg:tags":[
        "pharmacist",
        "chemist"
    ],
    "wof:name":"Asif Iqbal Pharmacy Ltd.",
    "wof:placetype":"venue"
},
  "geometry": {"coordinates":[-2.4480440617,53.5650253296],"type":"Point"}
}