{
  "type": "Feature",
  "properties": {
    "addr:full":"32 Station Road, Marston Green Birmingham West Midlands B37 7AU",
    "addr:housenumber":"32",
    "addr:postcode":"b37 7au",
    "addr:street":"Station Road",
    "iso:country":"GB",
    "sg:address":"32 Station Road, Marston Green",
    "sg:city":"Birmingham",
    "sg:classifiers":[
        {
            "category":"Autos & Motor Vehicles",
            "subcategory":"Automobile Sales",
            "type":"Retail Goods"
        }
    ],
    "sg:phone":"+44 121 770 7070",
    "sg:postcode":"B37 7AU",
    "sg:province":"West Midlands",
    "sg:tags":[
        "car"
    ],
    "wof:name":"Timberley Lane Motors",
    "wof:placetype":"venue"
},
  "geometry": {"coordinates":[-1.7520339489,52.4677009583],"type":"Point"}
}