{
  "type": "Feature",
  "properties": {
    "addr:full":"East Kilbride Rd Glasgow East Renfrewshire G76 8RS",
    "addr:postcode":"g76 8rs",
    "addr:street":"East Kilbride Rd",
    "iso:country":"GB",
    "sg:address":"East Kilbride Rd",
    "sg:city":"Glasgow",
    "sg:classifiers":[
        {
            "category":"Retail",
            "subcategory":"Auto Repair",
            "type":"Services"
        }
    ],
    "sg:phone":"+44 141 644 5700",
    "sg:postcode":"G76 8RS",
    "sg:province":"East Renfrewshire",
    "sg:tags":[
        "modification",
        "garage"
    ],
    "wof:name":"Auto Mobile-Technik Ltd",
    "wof:placetype":"venue"
},
  "geometry": {"coordinates":[-4.2541308403,55.7783851624],"type":"Point"}
}