{
  "type": "Feature",
  "properties": {
    "iso:country":"GB",
    "sg:address":"107 East Barnet Road, New Barnet",
    "sg:city":"Barnet",
    "sg:classifiers":[
        {
            "category":"Retail",
            "subcategory":"Veterinary Services",
            "type":"Services"
        }
    ],
    "sg:phone":"+44 20 8440 5742",
    "sg:postcode":"EN4 8RF",
    "sg:province":"Hertfordshire",
    "sg:tags":[
        "surgeon"
    ],
    "wof:name":"East Barnet Veterinary Surgery",
    "wof:placetype":"venue"
},
  "geometry": {"coordinates":[-0.168302,51.648205],"type":"Point"}
}