{
  "type": "Feature",
  "properties": {
    "addr:full":"28 Cambridge Road Cambridge Cambridgeshire CB2 4DG",
    "addr:housenumber":"28",
    "addr:postcode":"cb2 4dg",
    "addr:street":"Cambridge Road",
    "iso:country":"GB",
    "sg:address":"28 Cambridge Road",
    "sg:city":"Cambridge",
    "sg:classifiers":[
        {
            "category":"Retail",
            "subcategory":"Auto Repair",
            "type":"Services"
        }
    ],
    "sg:phone":"+44 1223 835809",
    "sg:postcode":"CB2 4DG",
    "sg:province":"Cambridgeshire",
    "sg:tags":[
        "modification",
        "garage"
    ],
    "wof:name":"D & L Motors",
    "wof:placetype":"venue"
},
  "geometry": {"coordinates":[0.167559,52.127598],"type":"Point"}
}