{
  "type": "Feature",
  "properties": {
    "addr:full":"Church Lane Surgery Taunton Somerset TA2 6RN",
    "addr:postcode":"ta2 6rn",
    "iso:country":"GB",
    "sg:address":"Church Lane Surgery",
    "sg:city":"Taunton",
    "sg:classifiers":[
        {
            "category":"Health Services",
            "subcategory":"Doctor",
            "type":"Services"
        }
    ],
    "sg:phone":"+44 1823 351301",
    "sg:postcode":"TA2 6RN",
    "sg:province":"Somerset",
    "sg:tags":[
        "practitioners"
    ],
    "wof:name":"Bilbrough, M",
    "wof:placetype":"venue"
},
  "geometry": {"coordinates":[-3.146811,51.026634],"type":"Point"}
}