{
  "type": "Feature",
  "properties": {
    "iso:country":"GB",
    "sg:address":"15 Chichester Park",
    "sg:city":"Westbury",
    "sg:classifiers":[
        {
            "category":"Building & Trades",
            "subcategory":"Construction",
            "type":"Services"
        }
    ],
    "sg:phone":"+44 1373 825573",
    "sg:postcode":"BA13 3AN",
    "sg:province":"Wiltshire",
    "sg:tags":[
        "roofing",
        "contracting"
    ],
    "wof:name":"S F Roofing",
    "wof:placetype":"venue"
},
  "geometry": {"coordinates":[-2.1865301132,51.2659378052],"type":"Point"}
}