{
  "type": "Feature",
  "properties": {
    "addr:full":"307 Shenley Road Borehamwood Hertfordshire WD6 1TH",
    "addr:housenumber":"307",
    "addr:postcode":"wd6 1th",
    "addr:street":"Shenley Road",
    "iso:country":"GB",
    "sg:address":"307 Shenley Road",
    "sg:city":"Borehamwood",
    "sg:classifiers":[
        {
            "category":"Military Area",
            "subcategory":"Air Force Base",
            "type":"Public Place"
        }
    ],
    "sg:phone":"+44 20 8953 1002",
    "sg:postcode":"WD6 1TH",
    "sg:province":"Hertfordshire",
    "sg:tags":[
        "taxi",
        "hire",
        "private"
    ],
    "wof:name":"R Stevens",
    "wof:placetype":"venue"
},
  "geometry": {"coordinates":[-0.2685210109,51.6606826782],"type":"Point"}
}