{
  "type": "Feature",
  "properties": {
    "addr:full":"48 Somerhill Road Welling Kent DA16 1PE",
    "addr:housenumber":"48",
    "addr:postcode":"da16 1pe",
    "addr:street":"Somerhill Road",
    "iso:country":"GB",
    "sg:address":"48 Somerhill Road",
    "sg:city":"Welling",
    "sg:classifiers":[
        {
            "category":"Professional",
            "subcategory":"Engineering",
            "type":"Services"
        }
    ],
    "sg:phone":"+44 20 8303 3813",
    "sg:postcode":"DA16 1PE",
    "sg:province":"Kent",
    "sg:tags":[
        "gas",
        "engineer"
    ],
    "wof:name":"Steve Taylor Technical Services",
    "wof:placetype":"venue"
},
  "geometry": {"coordinates":[0.1135130003,51.4660644531],"type":"Point"}
}