{
  "type": "Feature",
  "properties": {
    "addr:full":"Litton Ho, Saville Rd Indstl Est, Saville Rd Peterborough Cambridgeshire PE3 7PR",
    "addr:postcode":"pe3 7pr",
    "addr:street":"Saville Rd;Est Saville Rd",
    "iso:country":"GB",
    "sg:address":"Litton Ho, Saville Rd Indstl Est, Saville Rd",
    "sg:city":"Peterborough",
    "sg:classifiers":[
        {
            "category":"Communications",
            "type":"Services"
        }
    ],
    "sg:phone":"+44 1733 765228",
    "sg:postcode":"PE3 7PR",
    "sg:province":"Cambridgeshire",
    "sg:tags":[
        "telecommunication"
    ],
    "wof:name":"Miracall Systems Ltd",
    "wof:placetype":"venue"
},
  "geometry": {"coordinates":[-0.2500520051,52.5729866028],"type":"Point"}
}