{
  "type": "Feature",
  "properties": {
    "iso:country":"GB",
    "sg:address":"4 Holywell Hill",
    "sg:city":"St Albans",
    "sg:classifiers":[
        {
            "category":"Professional",
            "subcategory":"Management & Consulting",
            "type":"Services"
        }
    ],
    "sg:postcode":"AL1 1BZ",
    "sg:province":"Hertfordshire",
    "sg:tags":[
        "consultant",
        "business"
    ],
    "wof:name":"Jarvis & Harty",
    "wof:placetype":"venue"
},
  "geometry": {"coordinates":[-0.340103,51.750748],"type":"Point"}
}