{
  "type": "Feature",
  "properties": {
    "iso:country":"GB",
    "sg:address":"75 Belford Road",
    "sg:city":"Edinburgh",
    "sg:classifiers":[
        {
            "category":"Museum",
            "subcategory":"Art Museum",
            "type":"Entertainment"
        },
        {
            "category":"Museum",
            "type":"Entertainment"
        }
    ],
    "sg:phone":"+44 131 556 8921",
    "sg:postcode":"EH4 3DR",
    "sg:province":"City of Edinburgh",
    "sg:tags":[
        "gallery"
    ],
    "wof:name":"Scottish National Gallery Of Modern Art",
    "wof:placetype":"venue"
},
  "geometry": {"coordinates":[-3.2508440018,55.9580497742],"type":"Point"}
}