{
  "type": "Feature",
  "properties": {
    "addr:full":"Imperial Way, Worton Grange Reading Berkshire RG2 0TH",
    "addr:postcode":"rg2 0th",
    "addr:street":"Imperial Way",
    "iso:country":"GB",
    "sg:address":"Imperial Way, Worton Grange",
    "sg:city":"Reading",
    "sg:classifiers":[
        {
            "category":"Freight",
            "type":"Transportation"
        }
    ],
    "sg:phone":"+44 118 986 5865",
    "sg:postcode":"RG2 0TH",
    "sg:province":"Berkshire",
    "sg:tags":[
        "forwarders"
    ],
    "wof:name":"Kuehne & Nagel Ltd.",
    "wof:placetype":"venue"
},
  "geometry": {"coordinates":[-0.973104,51.419762],"type":"Point"}
}