{
  "type": "Feature",
  "properties": {
    "iso:country":"GB",
    "sg:address":"10 Friargate",
    "sg:city":"Derby",
    "sg:classifiers":[
        {
            "category":"Restaurant",
            "type":"Food & Drink"
        }
    ],
    "sg:phone":"+44 1332 344828",
    "sg:postcode":"DE1 1BU",
    "sg:province":"Derbyshire",
    "sg:tags":[
        "chinese"
    ],
    "wof:name":"Kam Hon Cantonese Restaurant",
    "wof:placetype":"venue"
},
  "geometry": {"coordinates":[-1.4872889519,52.9243431091],"type":"Point"}
}