{
  "type": "Feature",
  "properties": {
    "iso:country":"GB",
    "sg:address":"Rose Bower Service Station, Thirsk Road, Easingwold",
    "sg:city":"York",
    "sg:classifiers":[
        {
            "category":"Retail",
            "subcategory":"Auto Repair",
            "type":"Services"
        }
    ],
    "sg:phone":"+44 1347 821326",
    "sg:postcode":"YO61 3HN",
    "sg:province":"North Yorkshire",
    "sg:tags":[
        "modification",
        "garage"
    ],
    "wof:name":"Rose Bower Garage",
    "wof:placetype":"venue"
},
  "geometry": {"coordinates":[-1.19231,54.121414],"type":"Point"}
}