{
  "type": "Feature",
  "properties": {
    "iso:country":"GB",
    "sg:address":"Unit A1 Skyway, 14 Calder Way",
    "sg:city":"Slough",
    "sg:classifiers":[
        {
            "category":"Building & Trades",
            "subcategory":"Construction",
            "type":"Services"
        }
    ],
    "sg:phone":"+44 1895 238728",
    "sg:postcode":"SL3 0BJ",
    "sg:province":"Berkshire",
    "sg:tags":[
        "restoration",
        "refurbishment"
    ],
    "wof:name":"Ashley Range Ltd.",
    "wof:placetype":"venue"
},
  "geometry": {"coordinates":[-0.51565,51.477718],"type":"Point"}
}