{
  "type": "Feature",
  "properties": {
    "iso:country":"GB",
    "sg:address":"34 Admirals Ct",
    "sg:city":"Bridgwater",
    "sg:classifiers":[
        {
            "category":"Professional",
            "subcategory":"Printing & Photocopies",
            "type":"Services"
        }
    ],
    "sg:postcode":"TA6 3EX",
    "sg:province":"Somerset",
    "sg:tags":[
        "plate",
        "lithographic",
        "maker"
    ],
    "wof:name":"Pegasus Supplies",
    "wof:placetype":"venue"
},
  "geometry": {"coordinates":[-3.005364,51.131836],"type":"Point"}
}