{
  "type": "Feature",
  "properties": {
    "iso:country":"GB",
    "sg:address":"162 Bankfield Road",
    "sg:city":"Widnes",
    "sg:classifiers":[
        {
            "category":"Organizations",
            "subcategory":"Non-profit Organization",
            "type":"Services"
        }
    ],
    "sg:postcode":"WA8 7UJ",
    "sg:province":"Cheshire",
    "sg:tags":[
        "organisation",
        "voluntary",
        "charity"
    ],
    "wof:name":"Halton Rape Councelling & Revocery Line",
    "wof:placetype":"venue"
},
  "geometry": {"coordinates":[-2.7683570385,53.3728370667],"type":"Point"}
}