{
  "type": "Feature",
  "properties": {
    "addr:full":"47b Town Street Batley West Yorkshire WF17 7NA",
    "addr:housenumber":"47b",
    "addr:postcode":"wf17 7na",
    "addr:street":"Town Street",
    "iso:country":"GB",
    "sg:address":"47b Town Street",
    "sg:city":"Batley",
    "sg:classifiers":[
        {
            "category":"Home & Garden",
            "subcategory":"Home Furnishings",
            "type":"Retail Goods"
        }
    ],
    "sg:postcode":"WF17 7NA",
    "sg:province":"West Yorkshire",
    "sg:tags":[
        "blind",
        "curtain",
        "fitting"
    ],
    "wof:name":"Adiraf Designs",
    "wof:placetype":"venue"
},
  "geometry": {"coordinates":[-1.634507,53.701408],"type":"Point"}
}