{
  "type": "Feature",
  "properties": {
    "addr:full":"Sutton Lane, Sutton Scarsdale Chesterfield Derbyshire S44 5UP",
    "addr:postcode":"s44 5up",
    "addr:street":"Sutton Lane",
    "iso:country":"GB",
    "sg:address":"Sutton Lane, Sutton Scarsdale",
    "sg:city":"Chesterfield",
    "sg:classifiers":[
        {
            "category":"Manufacturing",
            "subcategory":"Wood Products",
            "type":"Manufacturing & Wholesale Goods"
        }
    ],
    "sg:postcode":"S44 5UP",
    "sg:province":"Derbyshire",
    "sg:tags":[
        "packaging",
        "crate",
        "pallets"
    ],
    "wof:name":"Derbyshire Packaging Systems Ltd.",
    "wof:placetype":"venue"
},
  "geometry": {"coordinates":[-1.3452789783,53.2158584595],"type":"Point"}
}