{
  "type": "Feature",
  "properties": {
    "addr:full":"6 Church Street Kidderminster Staffordshire DY10 2AD",
    "addr:housenumber":"6",
    "addr:postcode":"dy10 2ad",
    "addr:street":"Church Street",
    "iso:country":"GB",
    "sg:address":"6 Church Street",
    "sg:city":"Kidderminster",
    "sg:classifiers":[
        {
            "category":"Shopping",
            "subcategory":"Clothing, Apparel, & Fashions",
            "type":"Retail Goods"
        }
    ],
    "sg:postcode":"DY10 2AD",
    "sg:province":"Staffordshire",
    "sg:tags":[
        "clothing",
        "fabric"
    ],
    "wof:name":"Industrial Maintenance Supplies Ltd",
    "wof:placetype":"venue"
},
  "geometry": {"coordinates":[-2.249898,52.388874],"type":"Point"}
}