{
  "type": "Feature",
  "properties": {
    "addr:full":"Unit 8, Cardiff Business Park, Lambourne Crescent Cardiff Cardiff CF14 5GF",
    "addr:housenumber":"unit 8",
    "addr:postcode":"cf14 5gf",
    "addr:street":"Cardiff Business Park Lambourne Crescent",
    "iso:country":"GB",
    "sg:address":"Unit 8, Cardiff Business Park, Lambourne Crescent",
    "sg:city":"Cardiff",
    "sg:classifiers":[
        {
            "category":"Professional",
            "subcategory":"Engineering",
            "type":"Services"
        }
    ],
    "sg:phone":"+44 29 2076 1148",
    "sg:postcode":"CF14 5GF",
    "sg:province":"Cardiff",
    "sg:tags":[
        "electronic",
        "engineer"
    ],
    "wof:name":"Kathcal Ltd.",
    "wof:placetype":"venue"
},
  "geometry": {"coordinates":[-3.19173,51.522572],"type":"Point"}
}