{
  "type": "Feature",
  "properties": {
    "iso:country":"GB",
    "sg:address":"Talbot Street",
    "sg:city":"Sheffield",
    "sg:classifiers":[
        {
            "category":"Organizations",
            "subcategory":"Political Organization",
            "type":"Services"
        }
    ],
    "sg:phone":"+44 114 275 0744",
    "sg:postcode":"S2 2TG",
    "sg:province":"South Yorkshire",
    "sg:tags":[
        "party"
    ],
    "wof:name":"Sheffield District Labour Party",
    "wof:placetype":"venue"
},
  "geometry": {"coordinates":[-1.4572440386,53.3786087036],"type":"Point"}
}