{
  "type": "Feature",
  "properties": {
    "addr:full":"Coldharbour Lane Bristol City of Bristol BS16 1QY",
    "addr:postcode":"bs16 1qy",
    "addr:street":"Coldharbour Lane",
    "iso:country":"GB",
    "sg:address":"Coldharbour Lane",
    "sg:city":"Bristol",
    "sg:classifiers":[
        {
            "category":"Social Services",
            "subcategory":"Job Training",
            "type":"Services"
        },
        {
            "category":"Education",
            "subcategory":"University",
            "type":"Public Place"
        }
    ],
    "sg:phone":"+44 117 965 6261",
    "sg:postcode":"BS16 1QY",
    "sg:province":"City of Bristol",
    "sg:tags":[
        "translator",
        "interpreter",
        "school",
        "medical"
    ],
    "wof:name":"University of the West of England",
    "wof:placetype":"venue"
},
  "geometry": {"coordinates":[-2.544689,51.504356],"type":"Point"}
}