{
  "type": "Feature",
  "properties": {
    "addr:full":"72 Bunting Rd Northampton Northamptonshire NN2 6EE",
    "addr:housenumber":"72",
    "addr:postcode":"nn2 6ee",
    "addr:street":"Bunting Rd",
    "iso:country":"GB",
    "sg:address":"72 Bunting Rd",
    "sg:city":"Northampton",
    "sg:classifiers":[
        {
            "category":"Utilities",
            "subcategory":"Telephone",
            "type":"Services"
        }
    ],
    "sg:phone":"+44 1604 722233",
    "sg:postcode":"NN2 6EE",
    "sg:province":"Northamptonshire",
    "sg:tags":[
        "telecommunication"
    ],
    "wof:name":"Delapre Communications",
    "wof:placetype":"venue"
},
  "geometry": {"coordinates":[-0.89569,52.251255],"type":"Point"}
}