{
  "type": "Feature",
  "properties": {
    "addr:full":"46 High Street Hampton Greater London TW12 1PD",
    "addr:housenumber":"46",
    "addr:postcode":"tw12 1pd",
    "addr:street":"High Street",
    "iso:country":"GB",
    "sg:address":"46 High Street",
    "sg:city":"Hampton",
    "sg:classifiers":[
        {
            "category":"Professional",
            "subcategory":"Employment Agencies",
            "type":"Services"
        }
    ],
    "sg:phone":"+44 20 8614 5858",
    "sg:postcode":"TW12 1PD",
    "sg:province":"Greater London",
    "sg:tags":[
        "consultant"
    ],
    "wof:name":"Holt Medical Recruitment Ltd.",
    "wof:placetype":"venue"
},
  "geometry": {"coordinates":[-0.3565100133,51.425945282],"type":"Point"}
}