{
  "type": "Feature",
  "properties": {
    "iso:country":"GB",
    "sg:address":"Church Street",
    "sg:city":"Ambleside",
    "sg:classifiers":[
        {
            "category":"Shopping",
            "subcategory":"News",
            "type":"Retail Goods"
        }
    ],
    "sg:phone":"+44 15394 32656",
    "sg:postcode":"LA22 0BT",
    "sg:province":"Cumbria",
    "sg:tags":[
        "newsagent"
    ],
    "wof:name":"J & P M Stobbart",
    "wof:placetype":"venue"
},
  "geometry": {"coordinates":[-2.964012,54.430275],"type":"Point"}
}