{
  "type": "Feature",
  "properties": {
    "iso:country":"GB",
    "sg:address":"St Charles Hospital, Exmoor Street",
    "sg:city":"London",
    "sg:classifiers":[
        {
            "category":"Shopping",
            "subcategory":"Pharmacy",
            "type":"Retail Goods"
        }
    ],
    "sg:phone":"+44 20 8964 1206",
    "sg:postcode":"W10 6DZ",
    "sg:province":"Greater London",
    "sg:tags":[
        "medicine",
        "therapy"
    ],
    "wof:name":"The Langford Centre Ltd.",
    "wof:placetype":"venue"
},
  "geometry": {"coordinates":[-0.2173999995,51.5223808289],"type":"Point"}
}