{
  "type": "Feature",
  "properties": {
    "iso:country":"GB",
    "sg:address":"Bricklehampton Hall, Bricklehampton",
    "sg:city":"Pershore",
    "sg:classifiers":[
        {
            "category":"Health Services",
            "subcategory":"Nursing And Care Facility",
            "type":"Services"
        }
    ],
    "sg:postcode":"WR10 3HQ",
    "sg:province":"Worcestershire",
    "sg:tags":[
        "home"
    ],
    "wof:name":"Bricklehampton Hall Nursing Home",
    "wof:placetype":"venue"
},
  "geometry": {"coordinates":[-2.030684948,52.0783233643],"type":"Point"}
}