{
  "type": "Feature",
  "properties": {
    "iso:country":"GB",
    "sg:address":"4 Dallega Close",
    "sg:city":"Hayes",
    "sg:classifiers":[
        {
            "category":"Social Services",
            "subcategory":"Adult Care",
            "type":"Services"
        }
    ],
    "sg:phone":"+44 1895 436247",
    "sg:postcode":"UB3 1ED",
    "sg:province":"Greater London",
    "sg:tags":[
        "domestic",
        "cleaning"
    ],
    "wof:name":"The Housework Service",
    "wof:placetype":"venue"
},
  "geometry": {"coordinates":[-0.437842,51.515442],"type":"Point"}
}