{
  "type": "Feature",
  "properties": {
    "addr:full":"8 Market Street Aberdeen Aberdeen City AB11 5NX",
    "addr:housenumber":"8",
    "addr:postcode":"ab11 5nx",
    "addr:street":"Market Street",
    "iso:country":"GB",
    "sg:address":"8 Market Street",
    "sg:city":"Aberdeen",
    "sg:classifiers":[
        {
            "category":"Fast Food",
            "type":"Food & Drink"
        }
    ],
    "sg:postcode":"AB11 5NX",
    "sg:province":"Aberdeen City",
    "sg:tags":[
        "away",
        "take"
    ],
    "wof:name":"Arthur Hedden",
    "wof:placetype":"venue"
},
  "geometry": {"coordinates":[-2.097375,57.146774],"type":"Point"}
}