{
  "type": "Feature",
  "properties": {
    "addr:full":"239 Kenelm Rd Birmingham West Midlands B10 9AF",
    "addr:housenumber":"239",
    "addr:postcode":"b10 9af",
    "addr:street":"Kenelm Rd",
    "iso:country":"GB",
    "sg:address":"239 Kenelm Rd",
    "sg:city":"Birmingham",
    "sg:classifiers":[
        {
            "category":"Shopping",
            "subcategory":"Comic Books",
            "type":"Retail Goods"
        }
    ],
    "sg:postcode":"B10 9AF",
    "sg:province":"West Midlands",
    "sg:tags":[
        "jeweller"
    ],
    "wof:name":"Gulam Jewellers",
    "wof:placetype":"venue"
},
  "geometry": {"coordinates":[-1.84623,52.471428],"type":"Point"}
}