{
  "type": "Feature",
  "properties": {
    "addr:full":"132 Bellemoor Road, Shirley Southampton Hampshire SO15 7RA",
    "addr:housenumber":"132",
    "addr:postcode":"so15 7ra",
    "addr:street":"Bellemoor Road",
    "iso:country":"GB",
    "sg:address":"132 Bellemoor Road, Shirley",
    "sg:city":"Southampton",
    "sg:classifiers":[
        {
            "category":"Health Services",
            "subcategory":"Health Practitioner",
            "type":"Services"
        }
    ],
    "sg:postcode":"SO15 7RA",
    "sg:province":"Hampshire",
    "sg:tags":[
        "acupuncture"
    ],
    "wof:name":"Acupuncture & Physiotherapy Clinic",
    "wof:placetype":"venue"
},
  "geometry": {"coordinates":[-1.418341,50.927601],"type":"Point"}
}