{
  "type": "Feature",
  "properties": {
    "iso:country":"GB",
    "sg:address":"Unit 21, Pearson Industrial Estate",
    "sg:city":"Chesterfield",
    "sg:classifiers":[
        {
            "category":"Personal",
            "subcategory":"Tanning Parlor",
            "type":"Services"
        }
    ],
    "sg:postcode":"S41 9EY",
    "sg:province":"Derbyshire",
    "sg:tags":[
        "laser"
    ],
    "wof:name":"Evans Traffic Services",
    "wof:placetype":"venue"
},
  "geometry": {"coordinates":[-1.438769,53.267025],"type":"Point"}
}