{
  "type": "Feature",
  "properties": {
    "addr:full":"Brookfield Business Centre, Twentypence Rd, Cottenham Cambridge Cambridgeshire CB4 8PS",
    "addr:postcode":"cb4 8ps",
    "addr:street":"Twentypence Rd",
    "iso:country":"GB",
    "sg:address":"Brookfield Business Centre, Twentypence Rd, Cottenham",
    "sg:city":"Cambridge",
    "sg:classifiers":[
        {
            "category":"Wholesale",
            "subcategory":"Scrap",
            "type":"Manufacturing & Wholesale Goods"
        }
    ],
    "sg:phone":"+44 1954 250638",
    "sg:postcode":"CB4 8PS",
    "sg:province":"Cambridgeshire",
    "sg:tags":[
        "waste",
        "metal"
    ],
    "wof:name":"Malary Oils",
    "wof:placetype":"venue"
},
  "geometry": {"coordinates":[0.13964,52.300598],"type":"Point"}
}