{
  "type": "Feature",
  "properties": {
    "addr:full":"88 Sheen Road Richmond Greater London TW9 1UF",
    "addr:housenumber":"88",
    "addr:postcode":"tw9 1uf",
    "addr:street":"Sheen Road",
    "iso:country":"GB",
    "sg:address":"88 Sheen Road",
    "sg:city":"Richmond",
    "sg:classifiers":[
        {
            "category":"Shopping",
            "subcategory":"Antiques",
            "type":"Retail Goods"
        }
    ],
    "sg:phone":"+44 20 8332 0262",
    "sg:postcode":"TW9 1UF",
    "sg:province":"Greater London",
    "wof:name":"Marryat",
    "wof:placetype":"venue"
},
  "geometry": {"coordinates":[-0.296441,51.462029],"type":"Point"}
}