{
  "type": "Feature",
  "properties": {
    "iso:country":"GB",
    "sg:address":"Coton",
    "sg:city":"Whitchurch",
    "sg:classifiers":[
        {
            "category":"Retail",
            "subcategory":"Auto Repair",
            "type":"Services"
        }
    ],
    "sg:phone":"+44 1948 880900",
    "sg:postcode":"SY13 2RB",
    "sg:province":"Cheshire",
    "sg:tags":[
        "modification",
        "garage"
    ],
    "wof:name":"Coton Garages Ltd.",
    "wof:placetype":"venue"
},
  "geometry": {"coordinates":[-2.711648,52.896973],"type":"Point"}
}