{
  "type": "Feature",
  "properties": {
    "iso:country":"GB",
    "sg:address":"11 East Street",
    "sg:city":"Shoreham-by-sea",
    "sg:classifiers":[
        {
            "category":"Shopping",
            "subcategory":"Pharmacy",
            "type":"Retail Goods"
        }
    ],
    "sg:phone":"+44 1273 461951",
    "sg:postcode":"BN43 5ZE",
    "sg:province":"West Sussex",
    "sg:tags":[
        "pharmacist",
        "chemist"
    ],
    "wof:name":"Bakhai Pharmacy",
    "wof:placetype":"venue"
},
  "geometry": {"coordinates":[-0.274591,50.832096],"type":"Point"}
}