{
  "type": "Feature",
  "properties": {
    "iso:country":"GB",
    "sg:address":"9 Victoria Road West",
    "sg:city":"Thornton-cleveleys",
    "sg:classifiers":[
        {
            "category":"Restaurant",
            "type":"Food & Drink"
        }
    ],
    "sg:phone":"+44 1253 852959",
    "sg:postcode":"FY5 1BS",
    "sg:province":"Lancashire",
    "wof:name":"FRANCOS",
    "wof:placetype":"venue"
},
  "geometry": {"coordinates":[-3.045484,53.877834],"type":"Point"}
}