{
  "type": "Feature",
  "properties": {
    "iso:country":"GB",
    "sg:address":"19 Bristol Gardens",
    "sg:city":"Brighton",
    "sg:classifiers":[
        {
            "category":"Manufacturing",
            "subcategory":"Building Materials",
            "type":"Manufacturing & Wholesale Goods"
        }
    ],
    "sg:phone":"+44 1273 603357",
    "sg:postcode":"BN2 5JR",
    "sg:province":"East Sussex",
    "sg:tags":[
        "merchant",
        "builder"
    ],
    "wof:name":"Hall & Co Ltd",
    "wof:placetype":"venue"
},
  "geometry": {"coordinates":[-0.10947,50.818161],"type":"Point"}
}