{
  "type": "Feature",
  "properties": {
    "addr:full":"Dovecote House, Gaulby Road, Kings Norton Leicester Leicestershire LE7 9BA",
    "addr:postcode":"le7 9ba",
    "addr:street":"Gaulby Road",
    "iso:country":"GB",
    "sg:address":"Dovecote House, Gaulby Road, Kings Norton",
    "sg:city":"Leicester",
    "sg:classifiers":[
        {
            "category":"Recreation",
            "type":"Entertainment"
        }
    ],
    "sg:phone":"+44 116 259 6990",
    "sg:postcode":"LE7 9BA",
    "sg:province":"Leicestershire",
    "sg:tags":[
        "hot",
        "balloon",
        "air"
    ],
    "wof:name":"Balloon Flights Co",
    "wof:placetype":"venue"
},
  "geometry": {"coordinates":[-0.963052,52.590988],"type":"Point"}
}