{
  "type": "Feature",
  "properties": {
    "addr:full":"10 Lady Lawson Street Edinburgh City of Edinburgh EH3 9DS",
    "addr:housenumber":"10",
    "addr:postcode":"eh3 9ds",
    "addr:street":"Lady Lawson Street",
    "iso:country":"GB",
    "sg:address":"10 Lady Lawson Street",
    "sg:city":"Edinburgh",
    "sg:classifiers":[
        {
            "category":"Professional",
            "subcategory":"Art Services",
            "type":"Services"
        }
    ],
    "sg:phone":"+44 131 229 5546",
    "sg:postcode":"EH3 9DS",
    "sg:province":"City of Edinburgh",
    "sg:tags":[
        "framing"
    ],
    "wof:name":"Lawsons Picture Framers",
    "wof:placetype":"venue"
},
  "geometry": {"coordinates":[-3.202221,55.946541],"type":"Point"}
}