{
  "type": "Feature",
  "properties": {
    "addr:full":"Fife Road London Greater London N22 5EG",
    "addr:postcode":"n22 5eg",
    "addr:street":"Fife Road",
    "iso:country":"GB",
    "sg:address":"Fife Road",
    "sg:city":"London",
    "sg:classifiers":[
        {
            "category":"Home & Garden",
            "subcategory":"Building Materials",
            "type":"Retail Goods"
        }
    ],
    "sg:phone":"+44 20 8888 6265",
    "sg:postcode":"N22 5EG",
    "sg:province":"Greater London",
    "sg:tags":[
        "ironwork",
        "diy",
        "wrought"
    ],
    "wof:name":"Croot's Steel Products",
    "wof:placetype":"venue"
},
  "geometry": {"coordinates":[-0.096329,51.602627],"type":"Point"}
}