{
  "type": "Feature",
  "properties": {
    "addr:full":"108 North Western St Manchester Greater Manchester M12 6DY",
    "addr:housenumber":"108",
    "addr:postcode":"m12 6dy",
    "addr:street":"North Western St",
    "iso:country":"GB",
    "sg:address":"108 North Western St",
    "sg:city":"Manchester",
    "sg:classifiers":[
        {
            "category":"Home & Garden",
            "subcategory":"Hardware",
            "type":"Retail Goods"
        }
    ],
    "sg:phone":"+44 161 272 6680",
    "sg:postcode":"M12 6DY",
    "sg:province":"Greater Manchester",
    "sg:tags":[
        "product",
        "wire",
        "electrical"
    ],
    "wof:name":"Distant Orders Ltd",
    "wof:placetype":"venue"
},
  "geometry": {"coordinates":[-2.224003,53.475933],"type":"Point"}
}