{
  "type": "Feature",
  "properties": {
    "iso:country":"GB",
    "sg:address":"9 Greenfield Rd",
    "sg:city":"Carluke",
    "sg:classifiers":[
        {
            "category":"Professional",
            "subcategory":"Art Services",
            "type":"Services"
        }
    ],
    "sg:phone":"+44 1555 752250",
    "sg:postcode":"ML8 5DA",
    "sg:province":"South Lanarkshire",
    "sg:tags":[
        "photographer"
    ],
    "wof:name":"Photographic Digital Images",
    "wof:placetype":"venue"
},
  "geometry": {"coordinates":[-3.83947,55.74136],"type":"Point"}
}