{
  "type": "Feature",
  "properties": {
    "iso:country":"GB",
    "sg:address":"21 Charnwood Street",
    "sg:city":"Derby",
    "sg:classifiers":[
        {
            "category":"Travel",
            "subcategory":"Hotels & Motels",
            "type":"Entertainment"
        }
    ],
    "sg:phone":"+44 1332 344103",
    "sg:postcode":"DE1 2GU",
    "sg:province":"Derbyshire",
    "sg:tags":[
        "house",
        "guest"
    ],
    "wof:name":"Rose & Thistle",
    "wof:placetype":"venue"
},
  "geometry": {"coordinates":[-1.4767249823,52.9152908325],"type":"Point"}
}