{
  "type": "Feature",
  "properties": {
    "addr:full":"4 Glasgow Rd Paisley Renfrewshire PA1 3QA",
    "addr:housenumber":"4",
    "addr:postcode":"pa1 3qa",
    "addr:street":"Glasgow Rd",
    "iso:country":"GB",
    "sg:address":"4 Glasgow Rd",
    "sg:city":"Paisley",
    "sg:classifiers":[
        {
            "category":"Bars & Pubs",
            "type":"Food & Drink"
        }
    ],
    "sg:phone":"+44 141 889 7145",
    "sg:postcode":"PA1 3QA",
    "sg:province":"Renfrewshire",
    "sg:tags":[
        "pubs",
        "inn"
    ],
    "wof:name":"Kelburn Tavern",
    "wof:placetype":"venue"
},
  "geometry": {"coordinates":[-4.4159817696,55.8469200134],"type":"Point"}
}