{
  "type": "Feature",
  "properties": {
    "iso:country":"GB",
    "sg:address":"120 Sackville Road",
    "sg:city":"Sheffield",
    "sg:classifiers":[
        {
            "category":"Real Estate",
            "subcategory":"Real Estate Operator",
            "type":"Services"
        },
        {
            "category":"Real Estate",
            "subcategory":"Real Estate Agent",
            "type":"Services"
        }
    ],
    "sg:phone":"+44 114 268 4168",
    "sg:postcode":"S10 1GW",
    "sg:province":"South Yorkshire",
    "sg:tags":[
        "letting"
    ],
    "wof:name":"U K Accommodation Services",
    "wof:placetype":"venue"
},
  "geometry": {"coordinates":[-1.5079580545,53.3845901489],"type":"Point"}
}