{
  "type": "Feature",
  "properties": {
    "addr:full":"Premier House Horsham West Sussex RH13 5AD",
    "addr:postcode":"rh13 5ad",
    "iso:country":"GB",
    "sg:address":"Premier House",
    "sg:city":"Horsham",
    "sg:classifiers":[
        {
            "category":"Manufacturing",
            "subcategory":"Metals",
            "type":"Manufacturing & Wholesale Goods"
        },
        {
            "category":"Autos & Motor Vehicles",
            "subcategory":"Auto Supplies",
            "type":"Retail Goods"
        },
        {
            "category":"Banks & Credit Unions",
            "subcategory":"Bank",
            "type":"Services"
        },
        {
            "category":"Building & Trades",
            "subcategory":"Equipment Rental",
            "type":"Services"
        }
    ],
    "sg:phone":"+44 1403 213344",
    "sg:postcode":"RH13 5AD",
    "sg:province":"West Sussex",
    "sg:tags":[
        "car",
        "plant",
        "machinery",
        "accessory"
    ],
    "wof:name":"Premier Industrial (U K) Ltd.",
    "wof:placetype":"venue"
},
  "geometry": {"coordinates":[-0.3228200078,51.0603904724],"type":"Point"}
}