{
  "type": "Feature",
  "properties": {
    "iso:country":"GB",
    "sg:address":"44 Len Side Drive, Bearsted",
    "sg:city":"Maidstone",
    "sg:classifiers":[
        {
            "category":"Professional",
            "subcategory":"Computer Services",
            "type":"Services"
        }
    ],
    "sg:postcode":"ME15 8UE",
    "sg:province":"Kent",
    "sg:tags":[
        "system",
        "software"
    ],
    "wof:name":"Je Marc Contracting Ltd",
    "wof:placetype":"venue"
},
  "geometry": {"coordinates":[0.57005,51.261967],"type":"Point"}
}