{
  "type": "Feature",
  "properties": {
    "addr:full":"28 Sandgate St Peckham Greater London SE15 1LE",
    "addr:housenumber":"28",
    "addr:postcode":"se15 1le",
    "addr:street":"Sandgate St",
    "iso:country":"GB",
    "sg:address":"28 Sandgate St",
    "sg:city":"Peckham",
    "sg:classifiers":[
        {
            "category":"Professional",
            "subcategory":"Detective & Security Services",
            "type":"Services"
        }
    ],
    "sg:phone":"+44 20 7635 6852",
    "sg:postcode":"SE15 1LE",
    "sg:province":"Greater London",
    "wof:name":"Pinkerton Security Services Ltd",
    "wof:placetype":"venue"
},
  "geometry": {"coordinates":[-0.062886,51.484196],"type":"Point"}
}