{
  "type": "Feature",
  "properties": {
    "addr:full":"Unit 9b Headway Business Park, Denby Dale Road Wakefield West Yorkshire WF2 7AZ",
    "addr:housenumber":"unit 9b",
    "addr:postcode":"wf2 7az",
    "addr:street":"Denby Dale Road",
    "iso:country":"GB",
    "sg:address":"Unit 9b Headway Business Park, Denby Dale Road",
    "sg:city":"Wakefield",
    "sg:classifiers":[
        {
            "category":"Shopping",
            "subcategory":"Crafts & Fabrics",
            "type":"Retail Goods"
        }
    ],
    "sg:phone":"+44 1924 200433",
    "sg:postcode":"WF2 7AZ",
    "sg:province":"West Yorkshire",
    "sg:tags":[
        "yarn",
        "supply"
    ],
    "wof:name":"David Ward Yarn Finishers",
    "wof:placetype":"venue"
},
  "geometry": {"coordinates":[-1.5102740526,53.6799697876],"type":"Point"}
}