{
  "type": "Feature",
  "properties": {
    "iso:country":"GB",
    "sg:address":"1625 London Road",
    "sg:city":"Leigh-on-sea",
    "sg:classifiers":[
        {
            "category":"Autos & Motor Vehicles",
            "subcategory":"Automobile Sales",
            "type":"Retail Goods"
        }
    ],
    "sg:postcode":"SS9 2SQ",
    "sg:province":"Essex",
    "sg:tags":[
        "car"
    ],
    "wof:name":"Sydney David",
    "wof:placetype":"venue"
},
  "geometry": {"coordinates":[0.637168,51.547897],"type":"Point"}
}