{
  "type": "Feature",
  "properties": {
    "addr:full":"1 Market Hill Road, East Kilbride Glasgow South Lanarkshire G74 4AA",
    "addr:housenumber":"1",
    "addr:postcode":"g74 4aa",
    "addr:street":"Market Hill Road",
    "iso:country":"GB",
    "sg:address":"1 Market Hill Road, East Kilbride",
    "sg:city":"Glasgow",
    "sg:classifiers":[
        {
            "category":"Professional",
            "subcategory":"Management & Consulting",
            "type":"Services"
        },
        {
            "category":"Professional",
            "subcategory":"Employment Agencies",
            "type":"Services"
        }
    ],
    "sg:phone":"+44 1355 230099",
    "sg:postcode":"G74 4AA",
    "sg:province":"South Lanarkshire",
    "sg:tags":[
        "consultant",
        "business"
    ],
    "wof:name":"Concept Management Systems International Ltd.",
    "wof:placetype":"venue"
},
  "geometry": {"coordinates":[-4.177796,55.768864],"type":"Point"}
}