{
  "type": "Feature",
  "properties": {
    "iso:country":"GB",
    "sg:address":"53 Glebe Road",
    "sg:city":"Skelmersdale",
    "sg:classifiers":[
        {
            "category":"Manufacturing",
            "subcategory":"Metals",
            "type":"Manufacturing & Wholesale Goods"
        }
    ],
    "sg:phone":"+44 1695 557157",
    "sg:postcode":"WN8 9JP",
    "sg:province":"Lancashire",
    "sg:tags":[
        "steel",
        "fabricator",
        "erectors"
    ],
    "wof:name":"Qualfab Engineering Ltd.",
    "wof:placetype":"venue"
},
  "geometry": {"coordinates":[-2.779895,53.544815],"type":"Point"}
}