{
  "type": "Feature",
  "properties": {
    "addr:full":"Beauchamp Rd St Leonards On Sea East Sussex TN38 9JU",
    "addr:postcode":"tn38 9ju",
    "addr:street":"Beauchamp Rd St",
    "iso:country":"GB",
    "sg:address":"Beauchamp Rd",
    "sg:city":"St Leonards On Sea",
    "sg:classifiers":[
        {
            "category":"Education",
            "subcategory":"School",
            "type":"Public Place"
        }
    ],
    "sg:phone":"+44 1424 853466",
    "sg:postcode":"TN38 9JU",
    "sg:province":"East Sussex",
    "sg:tags":[
        "local",
        "authority"
    ],
    "wof:name":"Hollington Junior School",
    "wof:placetype":"venue"
},
  "geometry": {"coordinates":[0.5476210117,50.8759231567],"type":"Point"}
}