{
  "type": "Feature",
  "properties": {
    "addr:full":"Po Box 85 Ipswich Suffolk IP1 4PY",
    "addr:housenumber":"po box 85",
    "addr:postcode":"ip1 4py",
    "iso:country":"GB",
    "sg:address":"Po Box 85",
    "sg:city":"Ipswich",
    "sg:classifiers":[
        {
            "category":"Professional",
            "subcategory":"Lawyer & Legal Services",
            "type":"Services"
        }
    ],
    "sg:postcode":"IP1 4PY",
    "sg:province":"Suffolk",
    "sg:tags":[
        "advice",
        "counselling"
    ],
    "wof:name":"Ipswich Women's Aid Ltd.",
    "wof:placetype":"venue"
},
  "geometry": {"coordinates":[1.143788,52.057777],"type":"Point"}
}