{
  "type": "Feature",
  "properties": {
    "addr:full":"65-66 Borough Market Halifax West Yorkshire HX1 1BZ",
    "addr:housenumber":"65-66",
    "addr:postcode":"hx1 1bz",
    "addr:street":"Borough Market",
    "iso:country":"GB",
    "sg:address":"65-66 Borough Market",
    "sg:city":"Halifax",
    "sg:classifiers":[
        {
            "category":"Shopping",
            "subcategory":"Party Supplies",
            "type":"Retail Goods"
        }
    ],
    "sg:postcode":"HX1 1BZ",
    "sg:province":"West Yorkshire",
    "sg:tags":[
        "novelty"
    ],
    "wof:name":"Roys Big Balloon & Party Shop",
    "wof:placetype":"venue"
},
  "geometry": {"coordinates":[-1.8600950241,53.7223968506],"type":"Point"}
}