{
  "type": "Feature",
  "properties": {
    "addr:full":"Manor Farm, Worth, Wookey Wells Somerset BA5 1LW",
    "addr:housenumber":"worth wookey",
    "addr:postcode":"ba5 1lw",
    "addr:street":"Manor",
    "iso:country":"GB",
    "sg:address":"Manor Farm, Worth, Wookey",
    "sg:city":"Wells",
    "sg:classifiers":[
        {
            "category":"Professional",
            "type":"Services"
        },
        {
            "category":"Banks & Credit Unions",
            "subcategory":"Investment Brokerage",
            "type":"Services"
        }
    ],
    "sg:phone":"+44 1749 673428",
    "sg:postcode":"BA5 1LW",
    "sg:province":"Somerset",
    "sg:tags":[
        "farm",
        "agricultural",
        "contractor"
    ],
    "wof:name":"T S Stevens",
    "wof:placetype":"venue"
},
  "geometry": {"coordinates":[-2.6912670135,51.2068901062],"type":"Point"}
}