{
  "type": "Feature",
  "properties": {
    "addr:full":"Hanbury House, Park Street, Thaxted Dunmow Essex CM6 2NE",
    "addr:postcode":"cm6 2ne",
    "addr:street":"Park Street",
    "iso:country":"GB",
    "sg:address":"Hanbury House, Park Street, Thaxted",
    "sg:city":"Dunmow",
    "sg:classifiers":[
        {
            "category":"Building & Trades",
            "subcategory":"Equipment Rental",
            "type":"Services"
        },
        {
            "category":"Building & Trades",
            "subcategory":"Construction",
            "type":"Services"
        }
    ],
    "sg:phone":"+44 1371 830150",
    "sg:postcode":"CM6 2NE",
    "sg:province":"Essex",
    "sg:tags":[
        "plant",
        "machinery"
    ],
    "wof:name":"Robert Jones Plant Hire",
    "wof:placetype":"venue"
},
  "geometry": {"coordinates":[0.344675,51.952805],"type":"Point"}
}