{
  "type": "Feature",
  "properties": {
    "iso:country":"GB",
    "sg:address":"Holly Tree Farm, 232 Maldon Rd",
    "sg:city":"Colchester",
    "sg:classifiers":[
        {
            "category":"Farming",
            "subcategory":"Livestock Farm",
            "type":"Manufacturing & Wholesale Goods"
        }
    ],
    "sg:phone":"+44 1621 815295",
    "sg:postcode":"CO5 0PU",
    "sg:province":"Essex",
    "sg:tags":[
        "others"
    ],
    "wof:name":"H J Keyes & Sons",
    "wof:placetype":"venue"
},
  "geometry": {"coordinates":[0.72565,51.800049],"type":"Point"}
}