{
  "type": "Feature",
  "properties": {
    "iso:country":"GB",
    "sg:address":"2 Chadwick Street",
    "sg:city":"London",
    "sg:classifiers":[
        {
            "category":"Wholesale",
            "subcategory":"Books, Periodicals, & Newspapers",
            "type":"Manufacturing & Wholesale Goods"
        }
    ],
    "sg:postcode":"SW1P 2EP",
    "sg:province":"Greater London",
    "sg:tags":[
        "publishing"
    ],
    "wof:name":"David Davies Memorial Institute of International Studies",
    "wof:placetype":"venue"
},
  "geometry": {"coordinates":[-0.132295,51.496563],"type":"Point"}
}