{
  "type": "Feature",
  "properties": {
    "addr:full":"374 Upper Richmond Road West, East Sheen London Greater London SW14 7JU",
    "addr:housenumber":"374",
    "addr:postcode":"sw14 7ju",
    "addr:street":"Upper Richmond Road West",
    "iso:country":"GB",
    "sg:address":"374 Upper Richmond Road West, East Sheen",
    "sg:city":"London",
    "sg:classifiers":[
        {
            "category":"Fast Food",
            "type":"Food & Drink"
        }
    ],
    "sg:phone":"+44 20 8876 2531",
    "sg:postcode":"SW14 7JU",
    "sg:province":"Greater London",
    "sg:tags":[
        "away",
        "take"
    ],
    "wof:name":"All Noodle Bar",
    "wof:placetype":"venue"
},
  "geometry": {"coordinates":[-0.2744460106,51.464389801],"type":"Point"}
}