{
  "type": "Feature",
  "properties": {
    "addr:full":"19 Upper Walthamstow Road London Greater London E17 3QG",
    "addr:housenumber":"19",
    "addr:postcode":"e17 3qg",
    "addr:street":"Upper Walthamstow Road",
    "iso:country":"GB",
    "sg:address":"19 Upper Walthamstow Road",
    "sg:city":"London",
    "sg:classifiers":[
        {
            "category":"Social Services",
            "subcategory":"Retirement Home",
            "type":"Services"
        }
    ],
    "sg:phone":"+44 20 8520 0671",
    "sg:postcode":"E17 3QG",
    "sg:province":"Greater London",
    "sg:tags":[
        "rest"
    ],
    "wof:name":"Y & R Jooma",
    "wof:placetype":"venue"
},
  "geometry": {"coordinates":[0.000829,51.5875358582],"type":"Point"}
}