{
  "type": "Feature",
  "properties": {
    "addr:full":"1 Clifton View, East Mains Industrial Estate Broxburn City of Edinburgh EH52 5NE",
    "addr:housenumber":"1",
    "addr:postcode":"eh52 5ne",
    "addr:street":"Clifton View East Mains Industrial Estate",
    "iso:country":"GB",
    "sg:address":"1 Clifton View, East Mains Industrial Estate",
    "sg:city":"Broxburn",
    "sg:classifiers":[
        {
            "category":"Bakery",
            "type":"Food & Drink"
        }
    ],
    "sg:phone":"+44 1506 857575",
    "sg:postcode":"EH52 5NE",
    "sg:province":"City of Edinburgh",
    "sg:tags":[
        "cake",
        "maker"
    ],
    "wof:name":"Dunbar Decorations Ltd.",
    "wof:placetype":"venue"
},
  "geometry": {"coordinates":[-3.471884,55.934235],"type":"Point"}
}