{
  "type": "Feature",
  "properties": {
    "addr:full":"39-41 Victoria Road Aberdeen Aberdeen City AB11 9LS",
    "addr:housenumber":"39-41",
    "addr:postcode":"ab11 9ls",
    "addr:street":"Victoria Road",
    "iso:country":"GB",
    "sg:address":"39-41 Victoria Road",
    "sg:city":"Aberdeen",
    "sg:classifiers":[
        {
            "category":"Shopping",
            "subcategory":"News",
            "type":"Retail Goods"
        }
    ],
    "sg:phone":"+44 1224 876036",
    "sg:postcode":"AB11 9LS",
    "sg:province":"Aberdeen City",
    "sg:tags":[
        "newsagent"
    ],
    "wof:name":"Stewart Shops",
    "wof:placetype":"venue"
},
  "geometry": {"coordinates":[-2.088586092,57.1386528015],"type":"Point"}
}