{
  "type": "Feature",
  "properties": {
    "addr:full":"89 Essex St Newbury Berkshire RG14 6RA",
    "addr:housenumber":"89",
    "addr:postcode":"rg14 6ra",
    "addr:street":"Essex St",
    "iso:country":"GB",
    "sg:address":"89 Essex St",
    "sg:city":"Newbury",
    "sg:classifiers":[
        {
            "category":"Manufacturing",
            "subcategory":"Signs",
            "type":"Manufacturing & Wholesale Goods"
        }
    ],
    "sg:phone":"+44 1635 42697",
    "sg:postcode":"RG14 6RA",
    "sg:province":"Berkshire",
    "sg:tags":[
        "writer"
    ],
    "wof:name":"Tim Boyle",
    "wof:placetype":"venue"
},
  "geometry": {"coordinates":[-1.3499009609,51.3820762634],"type":"Point"}
}