{
  "type": "Feature",
  "properties": {
    "iso:country":"GB",
    "sg:address":"49 Newport Road",
    "sg:city":"Ventnor",
    "sg:classifiers":[
        {
            "category":"Personal",
            "subcategory":"Beauty Salon",
            "type":"Services"
        },
        {
            "category":"Personal",
            "subcategory":"Barber",
            "type":"Services"
        }
    ],
    "sg:phone":"+44 1983 852752",
    "sg:postcode":"PO38 1BB",
    "sg:province":"Isle of Wight",
    "sg:tags":[
        "unisex",
        "hairdresser"
    ],
    "wof:name":"Nicki Jane",
    "wof:placetype":"venue"
},
  "geometry": {"coordinates":[-1.216523,50.598213],"type":"Point"}
}