{
  "type": "Feature",
  "properties": {
    "iso:country":"GB",
    "sg:address":"Co-op Works, Norfolk St",
    "sg:city":"Peterborough",
    "sg:classifiers":[
        {
            "category":"Building & Trades",
            "subcategory":"Construction",
            "type":"Services"
        }
    ],
    "sg:phone":"+44 1733 558501",
    "sg:postcode":"PE1 2NP",
    "sg:province":"Cambridgeshire",
    "sg:tags":[
        "guttering"
    ],
    "wof:name":"Elite Home Improvements",
    "wof:placetype":"venue"
},
  "geometry": {"coordinates":[-0.24725,52.582901],"type":"Point"}
}