{
  "type": "Feature",
  "properties": {
    "iso:country":"GB",
    "sg:address":"58 Dalesford Rd, Acorn",
    "sg:city":"Aylesbury",
    "sg:classifiers":[
        {
            "category":"Building & Trades",
            "subcategory":"Construction",
            "type":"Services"
        }
    ],
    "sg:postcode":"HP21 9XD",
    "sg:province":"Buckinghamshire",
    "sg:tags":[
        "builder",
        "decorator",
        "painter"
    ],
    "wof:name":"Hale,G,W,T,",
    "wof:placetype":"venue"
},
  "geometry": {"coordinates":[-0.795122,51.798016],"type":"Point"}
}