{
  "type": "Feature",
  "properties": {
    "addr:full":"845london Road Thornton Heath Surrey CR7 6JH",
    "addr:postcode":"cr7 6jh",
    "addr:street":"845London Road",
    "iso:country":"GB",
    "sg:address":"845london Road",
    "sg:city":"Thornton Heath",
    "sg:classifiers":[
        {
            "category":"Autos & Motor Vehicles",
            "subcategory":"Automobile Sales",
            "type":"Retail Goods"
        },
        {
            "category":"Retail",
            "subcategory":"Auto Repair",
            "type":"Services"
        }
    ],
    "sg:postcode":"CR7 6JH",
    "sg:province":"Surrey",
    "sg:tags":[
        "body",
        "car"
    ],
    "wof:name":"Ancaster Group Ltd.",
    "wof:placetype":"venue"
},
  "geometry": {"coordinates":[-0.111749,51.394291],"type":"Point"}
}