{
  "type": "Feature",
  "properties": {
    "addr:full":"Austin Hall, County Offices Kendal Cumbria LA9 4RQ",
    "addr:postcode":"la9 4rq",
    "iso:country":"GB",
    "sg:address":"Austin Hall, County Offices",
    "sg:city":"Kendal",
    "sg:classifiers":[
        {
            "category":"Organizations",
            "subcategory":"Non-profit Organization",
            "type":"Services"
        }
    ],
    "sg:phone":"+44 1539 740928",
    "sg:postcode":"LA9 4RQ",
    "sg:province":"Cumbria",
    "sg:tags":[
        "organisation",
        "voluntary",
        "charity"
    ],
    "wof:name":"Childrens Play Council",
    "wof:placetype":"venue"
},
  "geometry": {"coordinates":[-2.7480840683,54.3240013123],"type":"Point"}
}