{
  "type": "Feature",
  "properties": {
    "addr:full":"George Street Colchester Essex CO1 1TS",
    "addr:postcode":"co1 1ts",
    "addr:street":"George Street",
    "iso:country":"GB",
    "sg:address":"George Street",
    "sg:city":"Colchester",
    "sg:classifiers":[
        {
            "category":"Social Services",
            "subcategory":"Adult Care",
            "type":"Services"
        }
    ],
    "sg:postcode":"CO1 1TS",
    "sg:province":"Essex",
    "sg:tags":[
        "day",
        "centre"
    ],
    "wof:name":"Castlegate Day Centre",
    "wof:placetype":"venue"
},
  "geometry": {"coordinates":[0.9015600085,51.8906059265],"type":"Point"}
}