{
  "type": "Feature",
  "properties": {
    "addr:full":"28 Lon Ffawydd Abergele Conwy LL22 7DU",
    "addr:housenumber":"28",
    "addr:postcode":"ll22 7du",
    "addr:street":"Lon Ffawydd",
    "iso:country":"GB",
    "sg:address":"28 Lon Ffawydd",
    "sg:city":"Abergele",
    "sg:classifiers":[
        {
            "category":"Building & Trades",
            "subcategory":"Construction",
            "type":"Services"
        }
    ],
    "sg:phone":"+44 1745 826432",
    "sg:postcode":"LL22 7DU",
    "sg:province":"Conwy",
    "sg:tags":[
        "builder"
    ],
    "wof:name":"Heaton Building Services",
    "wof:placetype":"venue"
},
  "geometry": {"coordinates":[-3.5883760452,53.2801017761],"type":"Point"}
}