{
  "type": "Feature",
  "properties": {
    "addr:full":"Unit 1, St. Nicholas Centre Sutton Surrey SM1 1AW",
    "addr:housenumber":"unit 1",
    "addr:postcode":"sm1 1aw",
    "addr:street":"St. Nicholas Centre Sutton",
    "iso:country":"GB",
    "sg:address":"Unit 1, St. Nicholas Centre",
    "sg:city":"Sutton",
    "sg:classifiers":[
        {
            "category":"Communications",
            "type":"Services"
        }
    ],
    "sg:phone":"+44 20 8770 1444",
    "sg:postcode":"SM1 1AW",
    "sg:province":"Surrey",
    "sg:tags":[
        "telecommunication"
    ],
    "wof:name":"The PocketPhone Shop",
    "wof:placetype":"venue"
},
  "geometry": {"coordinates":[-0.193554,51.362579],"type":"Point"}
}