{
  "type": "Feature",
  "properties": {
    "iso:country":"GB",
    "sg:address":"67-69 Moore Street",
    "sg:city":"Wolverhampton",
    "sg:classifiers":[
        {
            "category":"Wholesale",
            "subcategory":"Scrap",
            "type":"Manufacturing & Wholesale Goods"
        }
    ],
    "sg:phone":"+44 1902 453144",
    "sg:postcode":"WV1 2HE",
    "sg:province":"West Midlands",
    "sg:tags":[
        "waste",
        "metal"
    ],
    "wof:name":"Moore Street Metals",
    "wof:placetype":"venue"
},
  "geometry": {"coordinates":[-2.107848,52.582836],"type":"Point"}
}