{
  "type": "Feature",
  "properties": {
    "iso:country":"GB",
    "sg:address":"Little Barton Farm, Pilgrims Way",
    "sg:city":"Canterbury",
    "sg:classifiers":[
        {
            "category":"Farming",
            "subcategory":"Livestock Farm",
            "type":"Manufacturing & Wholesale Goods"
        },
        {
            "category":"Farming",
            "subcategory":"Farm",
            "type":"Manufacturing & Wholesale Goods"
        }
    ],
    "sg:phone":"+44 1227 463634",
    "sg:postcode":"CT1 1WN",
    "sg:province":"Kent",
    "sg:tags":[
        "mixed",
        "others"
    ],
    "wof:name":"S W Mount & Sons Ltd.",
    "wof:placetype":"venue"
},
  "geometry": {"coordinates":[1.1019259691,51.2779998779],"type":"Point"}
}