{
  "type": "Feature",
  "properties": {
    "iso:country":"GB",
    "sg:address":"102 High Street",
    "sg:city":"Nairn",
    "sg:classifiers":[
        {
            "category":"Restaurant",
            "type":"Food & Drink"
        }
    ],
    "sg:phone":"+44 1667 454211",
    "sg:postcode":"IV12 4DE",
    "sg:province":"Highland",
    "wof:name":"Highland Palace",
    "wof:placetype":"venue"
},
  "geometry": {"coordinates":[-3.8669331074,57.5858001709],"type":"Point"}
}