{
  "type": "Feature",
  "properties": {
    "iso:country":"GB",
    "sg:address":"2 Duke Street",
    "sg:city":"Chelmsford",
    "sg:classifiers":[
        {
            "category":"Real Estate",
            "subcategory":"Real Estate Agent",
            "type":"Services"
        }
    ],
    "sg:phone":"+44 1245 262266",
    "sg:postcode":"CM1 1HL",
    "sg:province":"Essex",
    "wof:name":"H William Brown",
    "wof:placetype":"venue"
},
  "geometry": {"coordinates":[0.471627,51.734997],"type":"Point"}
}