{
  "type": "Feature",
  "properties": {
    "iso:country":"GB",
    "sg:address":"14 Gorton Road",
    "sg:city":"Stockport",
    "sg:classifiers":[
        {
            "category":"Shopping",
            "subcategory":"Gifts & Souvenirs",
            "type":"Retail Goods"
        },
        {
            "category":"Shopping",
            "subcategory":"News",
            "type":"Retail Goods"
        }
    ],
    "sg:phone":"+44 161 432 8546",
    "sg:postcode":"SK5 6AE",
    "sg:province":"Cheshire",
    "sg:tags":[
        "poster",
        "newsagent",
        "card"
    ],
    "wof:name":"Nigel's News",
    "wof:placetype":"venue"
},
  "geometry": {"coordinates":[-2.1595380306,53.437713623],"type":"Point"}
}