{
  "type": "Feature",
  "properties": {
    "addr:full":"11 Woodburn Drive, Whitley Lodge Whitley Bay Northumberland NE26 3HS",
    "addr:housenumber":"11",
    "addr:postcode":"ne26 3hs",
    "addr:street":"Woodburn Drive",
    "iso:country":"GB",
    "sg:address":"11 Woodburn Drive, Whitley Lodge",
    "sg:city":"Whitley Bay",
    "sg:classifiers":[
        {
            "category":"Professional",
            "subcategory":"Computer Services",
            "type":"Services"
        }
    ],
    "sg:postcode":"NE26 3HS",
    "sg:province":"Northumberland",
    "sg:tags":[
        "consultant"
    ],
    "wof:name":"Daycool Ltd",
    "wof:placetype":"venue"
},
  "geometry": {"coordinates":[-1.465537,55.055035],"type":"Point"}
}