{
  "type": "Feature",
  "properties": {
    "iso:country":"GB",
    "sg:address":"11 Woodburn Drive, Whitley Lodge",
    "sg:city":"Whitley Bay",
    "sg:classifiers":[
        {
            "category":"Professional",
            "subcategory":"Computer Services",
            "type":"Services"
        }
    ],
    "sg:postcode":"NE26 3HS",
    "sg:province":"Northumberland",
    "sg:tags":[
        "consultant"
    ],
    "wof:name":"Daycool Ltd",
    "wof:placetype":"venue"
},
  "geometry": {"coordinates":[-1.465537,55.055035],"type":"Point"}
}