{
  "type": "Feature",
  "properties": {
    "addr:full":"Hall Lane, Branston Lincoln Lincolnshire LN4 1PZ",
    "addr:postcode":"ln4 1pz",
    "addr:street":"Hall Lane",
    "iso:country":"GB",
    "sg:address":"Hall Lane, Branston",
    "sg:city":"Lincoln",
    "sg:classifiers":[
        {
            "category":"Farming",
            "subcategory":"Farm",
            "type":"Manufacturing & Wholesale Goods"
        }
    ],
    "sg:phone":"+44 1522 520097",
    "sg:postcode":"LN4 1PZ",
    "sg:province":"Lincolnshire",
    "sg:tags":[
        "mixed",
        "crop"
    ],
    "wof:name":"Nelstrop Farms Ltd.",
    "wof:placetype":"venue"
},
  "geometry": {"coordinates":[-0.4707539976,53.1935005188],"type":"Point"}
}