{
  "type": "Feature",
  "properties": {
    "addr:full":"143 Billacombe Road Plymouth Devon PL9 7HB",
    "addr:housenumber":"143",
    "addr:postcode":"pl9 7hb",
    "addr:street":"Billacombe Road",
    "iso:country":"GB",
    "sg:address":"143 Billacombe Road",
    "sg:city":"Plymouth",
    "sg:classifiers":[
        {
            "category":"Home & Garden",
            "subcategory":"Carpets & Floor Coverings",
            "type":"Retail Goods"
        }
    ],
    "sg:phone":"+44 1752 482030",
    "sg:postcode":"PL9 7HB",
    "sg:province":"Devon",
    "sg:tags":[
        "carpets",
        "rug",
        "matting"
    ],
    "wof:name":"Andy Trim Carpet Fitting Service",
    "wof:placetype":"venue"
},
  "geometry": {"coordinates":[-4.08896,50.366272],"type":"Point"}
}