{
  "type": "Feature",
  "properties": {
    "iso:country":"GB",
    "sg:address":"Hawksworth Place, Town St, Hawksworth",
    "sg:city":"Nottingham",
    "sg:classifiers":[
        {
            "category":"Building & Trades",
            "subcategory":"Construction",
            "type":"Services"
        }
    ],
    "sg:phone":"+44 1949 851577",
    "sg:postcode":"NG13 9DB",
    "sg:province":"Leicestershire",
    "sg:tags":[
        "contractor"
    ],
    "wof:name":"Charter Hill Ltd",
    "wof:placetype":"venue"
},
  "geometry": {"coordinates":[-0.906255,52.968018],"type":"Point"}
}