{
  "type": "Feature",
  "properties": {
    "addr:full":"St Andrews House, 385 Hillington Road Glasgow Glasgow City G52 4BL",
    "addr:housenumber":"385",
    "addr:postcode":"g52 4bl",
    "addr:street":"Hillington Road",
    "iso:country":"GB",
    "sg:address":"St Andrews House, 385 Hillington Road",
    "sg:city":"Glasgow",
    "sg:classifiers":[
        {
            "category":"Manufacturing",
            "subcategory":"Glass & Minerals",
            "type":"Manufacturing & Wholesale Goods"
        }
    ],
    "sg:phone":"+44 141 303 4590",
    "sg:postcode":"G52 4BL",
    "sg:province":"Glasgow City",
    "sg:tags":[
        "chalk",
        "stone",
        "slate"
    ],
    "wof:name":"A M P (Quarrymasters) Ltd.",
    "wof:placetype":"venue"
},
  "geometry": {"coordinates":[-4.364249,55.85635],"type":"Point"}
}