{
  "type": "Feature",
  "properties": {
    "iso:country":"GB",
    "sg:address":"Langthornes, High Cross Lane",
    "sg:city":"Dunmow",
    "sg:classifiers":[
        {
            "category":"Home & Garden",
            "subcategory":"Garden Supply",
            "type":"Retail Goods"
        }
    ],
    "sg:phone":"+44 1371 872611",
    "sg:postcode":"CM6 1TD",
    "sg:province":"Essex",
    "sg:tags":[
        "nursery",
        "centre"
    ],
    "wof:name":"Langthornes Plantery",
    "wof:placetype":"venue"
},
  "geometry": {"coordinates":[0.364977,51.870613],"type":"Point"}
}