{
  "type": "Feature",
  "properties": {
    "iso:country":"GB",
    "sg:address":"Queensway House Business Centre, Queensway, East Middlesbrough Industrial Es",
    "sg:city":"Middlesbrough",
    "sg:classifiers":[
        {
            "category":"Shopping",
            "subcategory":"Computers & Home Electronics",
            "type":"Retail Goods"
        }
    ],
    "sg:phone":"+44 1642 252595",
    "sg:postcode":"TS3 8TF",
    "sg:province":"North Yorkshire",
    "sg:tags":[
        "equipment",
        "video",
        "cctv"
    ],
    "wof:name":"Crimewatch Systems Ltd.",
    "wof:placetype":"venue"
},
  "geometry": {"coordinates":[-1.195849,54.573792],"type":"Point"}
}