{
  "type": "Feature",
  "properties": {
    "addr:full":"275 North Circular Road London Greater London N13 5JH",
    "addr:housenumber":"275",
    "addr:postcode":"n13 5jh",
    "addr:street":"North Circular Road",
    "iso:country":"GB",
    "sg:address":"275 North Circular Road",
    "sg:city":"London",
    "sg:classifiers":[
        {
            "category":"Professional",
            "subcategory":"Art Services",
            "type":"Services"
        }
    ],
    "sg:postcode":"N13 5JH",
    "sg:province":"Greater London",
    "sg:tags":[
        "framing"
    ],
    "wof:name":"Aashiv Photo Frames",
    "wof:placetype":"venue"
},
  "geometry": {"coordinates":[-0.1030969992,51.6142654419],"type":"Point"}
}