{
  "type": "Feature",
  "properties": {
    "iso:country":"GB",
    "sg:address":"Beake Avenue",
    "sg:city":"Coventry",
    "sg:classifiers":[
        {
            "category":"Bars & Pubs",
            "type":"Food & Drink"
        }
    ],
    "sg:phone":"+44 24 7633 2601",
    "sg:postcode":"CV6 2HQ",
    "sg:province":"Warwickshire",
    "sg:tags":[
        "pubs",
        "house",
        "inn",
        "public",
        "activity"
    ],
    "wof:name":"The Craftsman",
    "wof:placetype":"venue"
},
  "geometry": {"coordinates":[-1.522984,52.439156],"type":"Point"}
}