{
  "type": "Feature",
  "properties": {
    "iso:country":"GB",
    "sg:address":"Surgery Bay Road",
    "sg:city":"Bracknell",
    "sg:classifiers":[
        {
            "category":"Health Services",
            "subcategory":"Podiatrist",
            "type":"Services"
        }
    ],
    "sg:phone":"+44 1344 423117",
    "sg:postcode":"RG12 2NR",
    "sg:province":"Berkshire",
    "sg:tags":[
        "podiatrists",
        "chiropodist"
    ],
    "wof:name":"Jack Golding",
    "wof:placetype":"venue"
},
  "geometry": {"coordinates":[-0.7345700264,51.4162712097],"type":"Point"}
}