{
  "type": "Feature",
  "properties": {
    "iso:country":"GB",
    "sg:address":"22 Bencroft, Cheshunt",
    "sg:city":"Waltham Cross",
    "sg:classifiers":[
        {
            "category":"Banks & Credit Unions",
            "subcategory":"Bureau De Change",
            "type":"Services"
        }
    ],
    "sg:phone":"+44 1992 308666",
    "sg:postcode":"EN7 6BE",
    "sg:province":"Greater London",
    "sg:tags":[
        "town",
        "consultant",
        "planning"
    ],
    "wof:name":"Phil Smith Associates",
    "wof:placetype":"venue"
},
  "geometry": {"coordinates":[-0.057664,51.719357],"type":"Point"}
}