{
  "type": "Feature",
  "properties": {
    "addr:full":"33 Fountain Street, Morley Leeds West Yorkshire LS27 9AE",
    "addr:housenumber":"33",
    "addr:postcode":"ls27 9ae",
    "addr:street":"Fountain Street",
    "iso:country":"GB",
    "sg:address":"33 Fountain Street, Morley",
    "sg:city":"Leeds",
    "sg:classifiers":[
        {
            "category":"Autos & Motor Vehicles",
            "subcategory":"Auto Supplies",
            "type":"Retail Goods"
        }
    ],
    "sg:phone":"+44 113 252 0108",
    "sg:postcode":"LS27 9AE",
    "sg:province":"West Yorkshire",
    "sg:tags":[
        "part",
        "motorcycle",
        "accessory"
    ],
    "wof:name":"Tee Bee",
    "wof:placetype":"venue"
},
  "geometry": {"coordinates":[-1.6023130417,53.7428436279],"type":"Point"}
}