{
  "type": "Feature",
  "properties": {
    "addr:full":"11 Osborne Avenue Newcastle-upon-tyne Tyne and Wear NE2 1JQ",
    "addr:housenumber":"11",
    "addr:postcode":"ne2 1jq",
    "addr:street":"Osborne Avenue",
    "iso:country":"GB",
    "sg:address":"11 Osborne Avenue",
    "sg:city":"Newcastle-upon-tyne",
    "sg:classifiers":[
        {
            "category":"Health Services",
            "subcategory":"Health Practitioner",
            "type":"Services"
        }
    ],
    "sg:phone":"+44 191 236 6935",
    "sg:postcode":"NE2 1JQ",
    "sg:province":"Tyne and Wear",
    "sg:tags":[
        "homoeopathic",
        "homeopathic"
    ],
    "wof:name":"Beth Maceoin",
    "wof:placetype":"venue"
},
  "geometry": {"coordinates":[-1.60453,54.988083],"type":"Point"}
}