{
  "type": "Feature",
  "properties": {
    "addr:full":"Woodside East Grinstead East Sussex RH19 4QL",
    "addr:postcode":"rh19 4ql",
    "iso:country":"GB",
    "sg:address":"Woodside",
    "sg:city":"East Grinstead",
    "sg:classifiers":[
        {
            "category":"Retail",
            "subcategory":"Auto Repair",
            "type":"Services"
        }
    ],
    "sg:postcode":"RH19 4QL",
    "sg:province":"East Sussex",
    "sg:tags":[
        "modification",
        "garage"
    ],
    "wof:name":"West Hoathley Garage",
    "wof:placetype":"venue"
},
  "geometry": {"coordinates":[-0.0075679999,51.1239814758],"type":"Point"}
}