{
  "type": "Feature",
  "properties": {
    "addr:full":"Unit 4 Allendale Centre Middlesbrough North Yorkshire TS7 9LF",
    "addr:housenumber":"unit 4",
    "addr:postcode":"ts7 9lf",
    "iso:country":"GB",
    "sg:address":"Unit 4 Allendale Centre",
    "sg:city":"Middlesbrough",
    "sg:classifiers":[
        {
            "category":"Food & Beverages",
            "subcategory":"Fruits & Vegetables",
            "type":"Retail Goods"
        }
    ],
    "sg:postcode":"TS7 9LF",
    "sg:province":"North Yorkshire",
    "sg:tags":[
        "greengrocer"
    ],
    "wof:name":"Grocer Jack's",
    "wof:placetype":"venue"
},
  "geometry": {"coordinates":[-1.1728210449,54.5435714722],"type":"Point"}
}