{
  "type": "Feature",
  "properties": {
    "iso:country":"GB",
    "sg:address":"Unit 1m Hillsborough Barracks, Hillsborough",
    "sg:city":"Sheffield",
    "sg:classifiers":[
        {
            "category":"Banks & Credit Unions",
            "subcategory":"Bank",
            "type":"Services"
        }
    ],
    "sg:phone":"+44 114 231 5558",
    "sg:postcode":"S6 2GY",
    "sg:province":"South Yorkshire",
    "sg:tags":[
        "broker",
        "mortgage"
    ],
    "wof:name":"Mortgage Service Ltd The",
    "wof:placetype":"venue"
},
  "geometry": {"coordinates":[-1.4947099686,53.4036483765],"type":"Point"}
}