{
  "type": "Feature",
  "properties": {
    "addr:full":"18 Market Pl Melton Mowbray Leicestershire LE13 1XD",
    "addr:housenumber":"18",
    "addr:postcode":"le13 1xd",
    "addr:street":"Market Pl",
    "iso:country":"GB",
    "sg:address":"18 Market Pl",
    "sg:city":"Melton Mowbray",
    "sg:classifiers":[
        {
            "category":"Health Services",
            "subcategory":"Optometrist",
            "type":"Services"
        }
    ],
    "sg:phone":"+44 1664 560037",
    "sg:postcode":"LE13 1XD",
    "sg:province":"Leicestershire",
    "sg:tags":[
        "optician"
    ],
    "wof:name":"Regal Optical Centre",
    "wof:placetype":"venue"
},
  "geometry": {"coordinates":[-0.8861489892,52.7643547058],"type":"Point"}
}