{
  "type": "Feature",
  "properties": {
    "addr:full":"347 Haydons Road London Greater London SW19 8LA",
    "addr:housenumber":"347",
    "addr:postcode":"sw19 8la",
    "addr:street":"Haydons Road",
    "iso:country":"GB",
    "sg:address":"347 Haydons Road",
    "sg:city":"London",
    "sg:classifiers":[
        {
            "category":"Shopping",
            "subcategory":"News",
            "type":"Retail Goods"
        }
    ],
    "sg:phone":"+44 20 8286 2821",
    "sg:postcode":"SW19 8LA",
    "sg:province":"Greater London",
    "sg:tags":[
        "newsagent"
    ],
    "wof:name":"Krishen Newsagents",
    "wof:placetype":"venue"
},
  "geometry": {"coordinates":[-0.190218,51.426548],"type":"Point"}
}