{
  "type": "Feature",
  "properties": {
    "addr:full":"Old Church Rd Coventry Warwickshire CV6 7DU",
    "addr:postcode":"cv6 7du",
    "addr:street":"Old Church Rd",
    "iso:country":"GB",
    "sg:address":"Old Church Rd",
    "sg:city":"Coventry",
    "sg:classifiers":[
        {
            "category":"Bars & Pubs",
            "type":"Food & Drink"
        }
    ],
    "sg:postcode":"CV6 7DU",
    "sg:province":"Warwickshire",
    "sg:tags":[
        "pubs",
        "inn"
    ],
    "wof:name":"McGreevy,R,",
    "wof:placetype":"venue"
},
  "geometry": {"coordinates":[-1.480436,52.438782],"type":"Point"}
}