{
  "type": "Feature",
  "properties": {
    "addr:full":"The Moorings, Heswall Wirral Merseyside CH60 9JU",
    "addr:postcode":"ch60 9ju",
    "addr:street":"The Moorings",
    "iso:country":"GB",
    "sg:address":"The Moorings, Heswall",
    "sg:city":"Wirral",
    "sg:classifiers":[
        {
            "category":"Autos & Motor Vehicles",
            "subcategory":"Boat Sales",
            "type":"Retail Goods"
        }
    ],
    "sg:phone":"+44 151 342 4307",
    "sg:postcode":"CH60 9JU",
    "sg:province":"Merseyside",
    "sg:tags":[
        "repair",
        "builder"
    ],
    "wof:name":"Lower Heswall Boatyard",
    "wof:placetype":"venue"
},
  "geometry": {"coordinates":[-3.1218860149,53.325553894],"type":"Point"}
}