{
  "type": "Feature",
  "properties": {
    "addr:full":", Coryton Stanford Le Hope Essex SS17 9LQ",
    "addr:postcode":"ss17 9lq",
    "iso:country":"GB",
    "sg:address":", Coryton",
    "sg:city":"Stanford Le Hope",
    "sg:classifiers":[
        {
            "category":"Utilities",
            "subcategory":"Fuel Oil & Lpg",
            "type":"Services"
        }
    ],
    "sg:phone":"+44 1375 360060",
    "sg:postcode":"SS17 9LQ",
    "sg:province":"Essex",
    "wof:name":"Charringtons",
    "wof:placetype":"venue"
},
  "geometry": {"coordinates":[0.41475,51.513645],"type":"Point"}
}