{
  "type": "Feature",
  "properties": {
    "iso:country":"GB",
    "sg:address":"2 Birtley Avenue, Blaydon",
    "sg:city":"Newcastle-upon-tyne",
    "sg:classifiers":[
        {
            "category":"Home & Garden",
            "subcategory":"Home Furnishings",
            "type":"Retail Goods"
        }
    ],
    "sg:phone":"+44 191 420 6923",
    "sg:postcode":"NE21 5NQ",
    "sg:province":"Tyne and Wear",
    "sg:tags":[
        "awning",
        "canopy",
        "blinds"
    ],
    "wof:name":"Hillary's Blinds",
    "wof:placetype":"venue"
},
  "geometry": {"coordinates":[-1.70368,54.957851],"type":"Point"}
}