{
  "type": "Feature",
  "properties": {
    "addr:full":"48b St Johns Road Tunbridge Wells Kent TN4 9NY",
    "addr:housenumber":"48b",
    "addr:postcode":"tn4 9ny",
    "addr:street":"St Johns Road",
    "iso:country":"GB",
    "sg:address":"48b St Johns Road",
    "sg:city":"Tunbridge Wells",
    "sg:classifiers":[
        {
            "category":"Personal",
            "subcategory":"Beauty Salon",
            "type":"Services"
        }
    ],
    "sg:phone":"+44 1892 532255",
    "sg:postcode":"TN4 9NY",
    "sg:province":"Kent",
    "sg:tags":[
        "unisex",
        "hairdresser"
    ],
    "wof:name":"The Head Office",
    "wof:placetype":"venue"
},
  "geometry": {"coordinates":[0.260541,51.140697],"type":"Point"}
}