{
  "type": "Feature",
  "properties": {
    "iso:country":"GB",
    "sg:address":"The Street",
    "sg:city":"Leek",
    "sg:classifiers":[
        {
            "category":"Autos & Motor Vehicles",
            "subcategory":"Recreational Vehicle Sales",
            "type":"Retail Goods"
        }
    ],
    "sg:phone":"+44 1782 538853",
    "sg:postcode":"ST2 7EF",
    "sg:province":"Staffordshire",
    "sg:tags":[
        "caravan"
    ],
    "wof:name":"Moorland Leisure Ltd.",
    "wof:placetype":"venue"
},
  "geometry": {"coordinates":[-2.1554,53.05035],"type":"Point"}
}