{
  "type": "Feature",
  "properties": {
    "iso:country":"GB",
    "sg:address":"266 Lozells Road, Lozells",
    "sg:city":"Birmingham",
    "sg:classifiers":[
        {
            "category":"Retail",
            "subcategory":"Repair Shop",
            "type":"Services"
        }
    ],
    "sg:phone":"+44 121 551 1792",
    "sg:postcode":"B19 1NP",
    "sg:province":"West Midlands",
    "sg:tags":[
        "radio",
        "television",
        "video"
    ],
    "wof:name":"Five Star T V",
    "wof:placetype":"venue"
},
  "geometry": {"coordinates":[-1.9156759977,52.5027732849],"type":"Point"}
}