{
  "type": "Feature",
  "properties": {
    "iso:country":"GB",
    "sg:address":"Unit 4, Block 19 Ridgeway, Donibristle Industrial Estate",
    "sg:city":"Dunfermline",
    "sg:classifiers":[
        {
            "category":"Professional",
            "subcategory":"Computer Services",
            "type":"Services"
        }
    ],
    "sg:phone":"+44 1383 825100",
    "sg:postcode":"KY11 9JW",
    "sg:province":"Fife",
    "sg:tags":[
        "system",
        "software"
    ],
    "wof:name":"Systems Solutions U K Ltd.",
    "wof:placetype":"venue"
},
  "geometry": {"coordinates":[-3.35458,56.042831],"type":"Point"}
}