{
  "type": "Feature",
  "properties": {
    "addr:full":"Borough Road Darlington Durham DL1 1SG",
    "addr:postcode":"dl1 1sg",
    "addr:street":"Borough Road",
    "iso:country":"GB",
    "sg:address":"Borough Road",
    "sg:city":"Darlington",
    "sg:classifiers":[
        {
            "category":"Home & Garden",
            "subcategory":"Carpets & Floor Coverings",
            "type":"Retail Goods"
        }
    ],
    "sg:phone":"+44 1325 364907",
    "sg:postcode":"DL1 1SG",
    "sg:province":"Durham",
    "sg:tags":[
        "carpets",
        "rug",
        "matting"
    ],
    "wof:name":"Hutchinson Carpets",
    "wof:placetype":"venue"
},
  "geometry": {"coordinates":[-1.5473409891,54.5278739929],"type":"Point"}
}