{
  "type": "Feature",
  "properties": {
    "iso:country":"GB",
    "sg:address":"20 Millerfield Place",
    "sg:city":"Edinburgh",
    "sg:classifiers":[
        {
            "category":"Organizations",
            "subcategory":"Non-profit Organization",
            "type":"Services"
        }
    ],
    "sg:phone":"+44 131 668 4949",
    "sg:postcode":"EH9 1LW",
    "sg:province":"City of Edinburgh",
    "sg:tags":[
        "organisation",
        "voluntary",
        "charity"
    ],
    "wof:name":"Task Trading Ltd.",
    "wof:placetype":"venue"
},
  "geometry": {"coordinates":[-3.188348,55.939301],"type":"Point"}
}