{
  "type": "Feature",
  "properties": {
    "addr:full":"Warwick House, Warwick Road Manchester Cheshire M16 0QQ",
    "addr:postcode":"m16 0qq",
    "addr:street":"Warwick Road",
    "iso:country":"GB",
    "sg:address":"Warwick House, Warwick Road",
    "sg:city":"Manchester",
    "sg:classifiers":[
        {
            "category":"Organizations",
            "subcategory":"Professional Association",
            "type":"Services"
        }
    ],
    "sg:phone":"+44 161 848 7760",
    "sg:postcode":"M16 0QQ",
    "sg:province":"Cheshire",
    "sg:tags":[
        "union",
        "trade"
    ],
    "wof:name":"National Union of Public Employees",
    "wof:placetype":"venue"
},
  "geometry": {"coordinates":[-2.273349,53.452888],"type":"Point"}
}