{
  "type": "Feature",
  "properties": {
    "iso:country":"GB",
    "sg:address":"Unit G5, Levenmouth Business Centre, Hawkslaw Trading Estate",
    "sg:city":"Leven",
    "sg:phone":"+44 1333 307011",
    "sg:postcode":"KY8 4LT",
    "sg:province":"Fife",
    "wof:name":"Metaflake Ltd.",
    "wof:placetype":"venue"
},
  "geometry": {"coordinates":[-2.998787,56.194401],"type":"Point"}
}