{
  "type": "Feature",
  "properties": {
    "iso:country":"GB",
    "sg:address":"Great Crosshall Street",
    "sg:city":"Liverpool",
    "sg:classifiers":[
        {
            "category":"Organizations",
            "subcategory":"Membership Organization",
            "type":"Services"
        }
    ],
    "sg:postcode":"L3 2AP",
    "sg:province":"Merseyside",
    "sg:tags":[
        "club"
    ],
    "wof:name":"Holy Cross Parochial Club",
    "wof:placetype":"venue"
},
  "geometry": {"coordinates":[-2.9832439423,53.4113731384],"type":"Point"}
}