{
  "type": "Feature",
  "properties": {
    "addr:full":"Repton Avenue Wembley Greater London HA0 3DW",
    "addr:postcode":"ha0 3dw",
    "addr:street":"Repton Avenue",
    "iso:country":"GB",
    "sg:address":"Repton Avenue",
    "sg:city":"Wembley",
    "sg:classifiers":[
        {
            "category":"Arena",
            "subcategory":"Sports Club",
            "type":"Entertainment"
        }
    ],
    "sg:phone":"+44 20 8902 4200",
    "sg:postcode":"HA0 3DW",
    "sg:province":"Greater London",
    "wof:name":"Wasps Rugby Football Club Ltd.",
    "wof:placetype":"venue"
},
  "geometry": {"coordinates":[-0.31257,51.557869],"type":"Point"}
}