{
  "type": "Feature",
  "properties": {
    "addr:full":"79-83 High Street, Clay Cross Chesterfield Derbyshire S45 9DZ",
    "addr:housenumber":"79-83",
    "addr:postcode":"s45 9dz",
    "addr:street":"High Street",
    "iso:country":"GB",
    "sg:address":"79-83 High Street, Clay Cross",
    "sg:city":"Chesterfield",
    "sg:classifiers":[
        {
            "category":"Shopping",
            "subcategory":"Used Merchandise",
            "type":"Retail Goods"
        }
    ],
    "sg:phone":"+44 1246 866201",
    "sg:postcode":"S45 9DZ",
    "sg:province":"Derbyshire",
    "sg:tags":[
        "shop",
        "second-hand"
    ],
    "wof:name":"Nice Price",
    "wof:placetype":"venue"
},
  "geometry": {"coordinates":[-1.4159690142,53.1659240723],"type":"Point"}
}