{
  "type": "Feature",
  "properties": {
    "addr:full":"14 Manor Park Parade London Greater London SE13 5PB",
    "addr:housenumber":"14",
    "addr:postcode":"se13 5pb",
    "addr:street":"Manor Park Parade",
    "iso:country":"GB",
    "sg:address":"14 Manor Park Parade",
    "sg:city":"London",
    "sg:classifiers":[
        {
            "category":"Food & Beverages",
            "subcategory":"Liquor & Beverages",
            "type":"Retail Goods"
        }
    ],
    "sg:phone":"+44 20 8852 4378",
    "sg:postcode":"SE13 5PB",
    "sg:province":"Greater London",
    "sg:tags":[
        "beer",
        "spirit",
        "wines"
    ],
    "wof:name":"Manor Park Wines",
    "wof:placetype":"venue"
},
  "geometry": {"coordinates":[-0.002282,51.458736],"type":"Point"}
}