{
  "type": "Feature",
  "properties": {
    "addr:full":"Liphill Bank Road, Burnlee Huddersfield South Yorkshire HD9 2LR",
    "addr:postcode":"hd9 2lr",
    "addr:street":"Bank Road Burnlee",
    "iso:country":"GB",
    "sg:address":"Liphill Bank Road, Burnlee",
    "sg:city":"Huddersfield",
    "sg:classifiers":[
        {
            "category":"Bars & Pubs",
            "type":"Food & Drink"
        },
        {
            "category":"Community Center",
            "subcategory":"Social",
            "type":"Public Place"
        }
    ],
    "sg:phone":"+44 1484 683713",
    "sg:postcode":"HD9 2LR",
    "sg:province":"South Yorkshire",
    "sg:tags":[
        "pubs",
        "house",
        "inn",
        "activity"
    ],
    "wof:name":"The Farmers Arms",
    "wof:placetype":"venue"
},
  "geometry": {"coordinates":[-1.8033299446,53.5668106079],"type":"Point"}
}