{
  "type": "Feature",
  "properties": {
    "addr:full":"Trearched Farm, Croesgoch Haverfordwest Pembrokeshire SA62 5JP",
    "addr:postcode":"sa62 5jp",
    "addr:street":"Croesgoch;Pembrokeshire",
    "iso:country":"GB",
    "sg:address":"Trearched Farm, Croesgoch",
    "sg:city":"Haverfordwest",
    "sg:classifiers":[
        {
            "category":"Farming",
            "subcategory":"Livestock Farm",
            "type":"Manufacturing & Wholesale Goods"
        }
    ],
    "sg:postcode":"SA62 5JP",
    "sg:province":"Pembrokeshire",
    "sg:tags":[
        "others"
    ],
    "wof:name":"J H P Jenkins",
    "wof:placetype":"venue"
},
  "geometry": {"coordinates":[-5.1608462334,51.9280433655],"type":"Point"}
}