{
  "type": "Feature",
  "properties": {
    "addr:full":"89 Westerleigh Rd Bristol Gloucestershire BS37 4BN",
    "addr:housenumber":"89",
    "addr:postcode":"bs37 4bn",
    "addr:street":"Westerleigh Rd",
    "iso:country":"GB",
    "sg:address":"89 Westerleigh Rd",
    "sg:city":"Bristol",
    "sg:classifiers":[
        {
            "category":"Food & Beverages",
            "subcategory":"Groceries & Convenience Stores",
            "type":"Retail Goods"
        }
    ],
    "sg:phone":"+44 1454 313863",
    "sg:postcode":"BS37 4BN",
    "sg:province":"Gloucestershire",
    "wof:name":"M & W Ltd",
    "wof:placetype":"venue"
},
  "geometry": {"coordinates":[-2.422519,51.537155],"type":"Point"}
}