{
  "type": "Feature",
  "properties": {
    "iso:country":"GB",
    "sg:address":"514 Plessey Road",
    "sg:city":"Blyth",
    "sg:classifiers":[
        {
            "category":"Shopping",
            "subcategory":"Pharmacy",
            "type":"Retail Goods"
        }
    ],
    "sg:phone":"+44 1670 366198",
    "sg:postcode":"NE24 4AA",
    "sg:province":"Northumberland",
    "sg:tags":[
        "pharmacist",
        "chemist"
    ],
    "wof:name":"David Baron (Blyth) Ltd.",
    "wof:placetype":"venue"
},
  "geometry": {"coordinates":[-1.5317150354,55.1117706299],"type":"Point"}
}