{
  "type": "Feature",
  "properties": {
    "addr:full":"Bradshaw Trading Estate, Greengate, Middleton Manchester Greater Manchester M24 1RB",
    "addr:postcode":"m24 1rb",
    "addr:street":"Trading Estate Greengate",
    "iso:country":"GB",
    "sg:address":"Bradshaw Trading Estate, Greengate, Middleton",
    "sg:city":"Manchester",
    "sg:classifiers":[
        {
            "category":"Food & Beverages",
            "subcategory":"Supermarket",
            "type":"Retail Goods"
        }
    ],
    "sg:phone":"+44 161 653 5050",
    "sg:postcode":"M24 1RB",
    "sg:province":"Greater Manchester",
    "sg:tags":[
        "frozen"
    ],
    "wof:name":"Davjon Food Ltd.",
    "wof:placetype":"venue"
},
  "geometry": {"coordinates":[-2.17498,53.532501],"type":"Point"}
}