{
  "type": "Feature",
  "properties": {
    "addr:full":"32 New House Lane, Northfleet Gravesend Kent DA11 7JW",
    "addr:housenumber":"32",
    "addr:postcode":"da11 7jw",
    "addr:street":"New House Lane",
    "iso:country":"GB",
    "sg:address":"32 New House Lane, Northfleet",
    "sg:city":"Gravesend",
    "sg:classifiers":[
        {
            "category":"Government",
            "subcategory":"Post Office",
            "type":"Public Place"
        }
    ],
    "sg:postcode":"DA11 7JW",
    "sg:province":"Kent",
    "sg:tags":[
        "messenger",
        "courier"
    ],
    "wof:name":"Paul Harlin",
    "wof:placetype":"venue"
},
  "geometry": {"coordinates":[0.356622,51.428207],"type":"Point"}
}