{
  "type": "Feature",
  "properties": {
    "addr:full":"1 Sharrow Place Northampton Northamptonshire NN3 5AJ",
    "addr:housenumber":"1",
    "addr:postcode":"nn3 5aj",
    "addr:street":"Sharrow Place",
    "iso:country":"GB",
    "sg:address":"1 Sharrow Place",
    "sg:city":"Northampton",
    "sg:classifiers":[
        {
            "category":"Professional",
            "subcategory":"Art Services",
            "type":"Services"
        }
    ],
    "sg:phone":"+44 1604 414100",
    "sg:postcode":"NN3 5AJ",
    "sg:province":"Northamptonshire",
    "sg:tags":[
        "photographer"
    ],
    "wof:name":"Alan Valentine",
    "wof:placetype":"venue"
},
  "geometry": {"coordinates":[-0.8061490059,52.2548179626],"type":"Point"}
}