{
  "type": "Feature",
  "properties": {
    "iso:country":"GB",
    "sg:address":"Lamb Lane",
    "sg:city":"Bridgwater",
    "sg:classifiers":[
        {
            "category":"Home & Garden",
            "subcategory":"Home Furnishings",
            "type":"Retail Goods"
        }
    ],
    "sg:phone":"+44 1278 455883",
    "sg:postcode":"TA6 3EL",
    "sg:province":"Somerset",
    "sg:tags":[
        "blind",
        "curtain",
        "fitting"
    ],
    "wof:name":"Sedgmoors Home Furnishing",
    "wof:placetype":"venue"
},
  "geometry": {"coordinates":[-3.006404,51.12764],"type":"Point"}
}