{
  "type": "Feature",
  "properties": {
    "addr:full":"London Rd Dartford Kent DA2 6AS",
    "addr:postcode":"da2 6as",
    "addr:street":"London Rd",
    "iso:country":"GB",
    "sg:address":"London Rd",
    "sg:city":"Dartford",
    "sg:classifiers":[
        {
            "category":"Manufacturing",
            "subcategory":"Metals",
            "type":"Manufacturing & Wholesale Goods"
        }
    ],
    "sg:phone":"+44 1322 229318",
    "sg:postcode":"DA2 6AS",
    "sg:province":"Kent",
    "sg:tags":[
        "steel",
        "fabricator",
        "erectors"
    ],
    "wof:name":"N & C Fabrications Ltd",
    "wof:placetype":"venue"
},
  "geometry": {"coordinates":[0.2489939928,51.4440917969],"type":"Point"}
}