{
  "type": "Feature",
  "properties": {
    "addr:full":"67 Pallatine Road, Didsbury Manchester Greater Manchester M20 3LJ",
    "addr:housenumber":"67",
    "addr:postcode":"m20 3lj",
    "addr:street":"Pallatine Road",
    "iso:country":"GB",
    "sg:address":"67 Pallatine Road, Didsbury",
    "sg:city":"Manchester",
    "sg:classifiers":[
        {
            "category":"Professional",
            "subcategory":"Computer Services",
            "type":"Services"
        }
    ],
    "sg:phone":"+44 161 446 2251",
    "sg:postcode":"M20 3LJ",
    "sg:province":"Greater Manchester",
    "sg:tags":[
        "system",
        "software"
    ],
    "wof:name":"Tiertex Ltd.",
    "wof:placetype":"venue"
},
  "geometry": {"coordinates":[-2.234049,53.427734],"type":"Point"}
}