{
  "type": "Feature",
  "properties": {
    "iso:country":"GB",
    "sg:address":"28 Gawsworth Drive",
    "sg:city":"Sandbach",
    "sg:classifiers":[
        {
            "category":"Wholesale",
            "subcategory":"Vending Machines",
            "type":"Manufacturing & Wholesale Goods"
        }
    ],
    "sg:postcode":"CW11 1DY",
    "sg:province":"Cheshire",
    "sg:tags":[
        "sale"
    ],
    "wof:name":"Mastervend Enterprises",
    "wof:placetype":"venue"
},
  "geometry": {"coordinates":[-2.3571770191,53.1506233215],"type":"Point"}
}