{
  "type": "Feature",
  "properties": {
    "addr:full":"Deptford Rd Gateshead Tyne and Wear NE8 3AJ",
    "addr:postcode":"ne8 3aj",
    "addr:street":"Deptford Rd",
    "iso:country":"GB",
    "sg:address":"Deptford Rd",
    "sg:city":"Gateshead",
    "sg:classifiers":[
        {
            "category":"Shopping",
            "subcategory":"Crafts & Fabrics",
            "type":"Retail Goods"
        }
    ],
    "sg:phone":"+44 191 477 0521",
    "sg:postcode":"NE8 3AJ",
    "sg:province":"Tyne and Wear",
    "sg:tags":[
        "machine",
        "sewing",
        "knitting"
    ],
    "wof:name":"Tyne Sew Ltd",
    "wof:placetype":"venue"
},
  "geometry": {"coordinates":[-1.5894750357,54.9678153992],"type":"Point"}
}