{
  "type": "Feature",
  "properties": {
    "addr:full":"48 Micklegate Selby East Riding of Yorkshire YO8 4EQ",
    "addr:housenumber":"48",
    "addr:postcode":"yo8 4eq",
    "addr:street":"Micklegate",
    "iso:country":"GB",
    "sg:address":"48 Micklegate",
    "sg:city":"Selby",
    "sg:classifiers":[
        {
            "category":"Shopping",
            "subcategory":"Computers & Home Electronics",
            "type":"Retail Goods"
        },
        {
            "category":"Professional",
            "subcategory":"Computer Services",
            "type":"Services"
        }
    ],
    "sg:phone":"+44 1757 702704",
    "sg:postcode":"YO8 4EQ",
    "sg:province":"East Riding of Yorkshire",
    "sg:tags":[
        "system",
        "software"
    ],
    "wof:name":"Advanced Digital Dynamics Ltd.",
    "wof:placetype":"venue"
},
  "geometry": {"coordinates":[-1.079589,53.786888],"type":"Point"}
}