{
  "type": "Feature",
  "properties": {
    "addr:full":"Albert Street Hebburn Tyne and Wear NE31 1DW",
    "addr:postcode":"ne31 1dw",
    "addr:street":"Albert Street",
    "iso:country":"GB",
    "sg:address":"Albert Street",
    "sg:city":"Hebburn",
    "sg:classifiers":[
        {
            "category":"Bars & Pubs",
            "type":"Food & Drink"
        },
        {
            "category":"Community Center",
            "subcategory":"Social",
            "type":"Public Place"
        }
    ],
    "sg:phone":"+44 191 428 2183",
    "sg:postcode":"NE31 1DW",
    "sg:province":"Tyne and Wear",
    "sg:tags":[
        "pubs",
        "house",
        "inn",
        "activity"
    ],
    "wof:name":"Wardles Bar",
    "wof:placetype":"venue"
},
  "geometry": {"coordinates":[-1.523094058,54.9788856506],"type":"Point"}
}