{
  "type": "Feature",
  "properties": {
    "iso:country":"GB",
    "sg:address":"74 Prestonfield, Milngavie Road",
    "sg:city":"Glasgow",
    "sg:classifiers":[
        {
            "category":"Building & Trades",
            "subcategory":"Cleaning & Sanitation",
            "type":"Services"
        }
    ],
    "sg:phone":"+44 141 956 3186",
    "sg:postcode":"G62 7PZ",
    "sg:province":"East Dunbartonshire",
    "sg:tags":[
        "dry",
        "control",
        "damp",
        "rot"
    ],
    "wof:name":"M & B Preservation & Maintenance Ltd.",
    "wof:placetype":"venue"
},
  "geometry": {"coordinates":[-4.332296,55.936924],"type":"Point"}
}