{
  "type": "Feature",
  "properties": {
    "addr:full":"Milton Business Park New Milton Hampshire BH25 6RQ",
    "addr:postcode":"bh25 6rq",
    "addr:street":"Park",
    "iso:country":"GB",
    "sg:address":"Milton Business Park",
    "sg:city":"New Milton",
    "sg:classifiers":[
        {
            "category":"Wholesale",
            "subcategory":"Furniture",
            "type":"Manufacturing & Wholesale Goods"
        }
    ],
    "sg:phone":"+44 1425 623282",
    "sg:postcode":"BH25 6RQ",
    "sg:province":"Hampshire",
    "sg:tags":[
        "shop",
        "fitting"
    ],
    "wof:name":"Harrison Display Systems Ltd.",
    "wof:placetype":"venue"
},
  "geometry": {"coordinates":[-1.6716519594,50.7576179504],"type":"Point"}
}