{
  "type": "Feature",
  "properties": {
    "addr:full":"111 New Lane, Burscough Ormskirk Lancashire L40 0RX",
    "addr:housenumber":"111",
    "addr:postcode":"l40 0rx",
    "addr:street":"New Lane",
    "iso:country":"GB",
    "sg:address":"111 New Lane, Burscough",
    "sg:city":"Ormskirk",
    "sg:classifiers":[
        {
            "category":"Sports & Exercise",
            "subcategory":"Race Track",
            "type":"Entertainment"
        }
    ],
    "sg:postcode":"L40 0RX",
    "sg:province":"Lancashire",
    "sg:tags":[
        "motor"
    ],
    "wof:name":"Aprilia Moto (U K) Ltd.",
    "wof:placetype":"venue"
},
  "geometry": {"coordinates":[-2.8671491146,53.6107826233],"type":"Point"}
}