{
  "type": "Feature",
  "properties": {
    "addr:full":"4 Ladbroke Gro London Greater London W11 3BG",
    "addr:housenumber":"4",
    "addr:postcode":"w11 3bg",
    "addr:street":"Ladbroke Gro",
    "iso:country":"GB",
    "sg:address":"4 Ladbroke Gro",
    "sg:city":"London",
    "sg:classifiers":[
        {
            "category":"Arts & Performance",
            "subcategory":"Art Gallery",
            "type":"Entertainment"
        }
    ],
    "sg:phone":"+44 20 7727 8333",
    "sg:postcode":"W11 3BG",
    "sg:province":"Greater London",
    "wof:name":"Aquarelle Gallery",
    "wof:placetype":"venue"
},
  "geometry": {"coordinates":[-0.2030889988,51.5080451965],"type":"Point"}
}