{
  "type": "Feature",
  "properties": {
    "addr:full":"4 Church Street London Greater London NW8 8ED",
    "addr:housenumber":"4",
    "addr:postcode":"nw8 8ed",
    "addr:street":"Church Street",
    "iso:country":"GB",
    "sg:address":"4 Church Street",
    "sg:city":"London",
    "sg:classifiers":[
        {
            "category":"Shopping",
            "subcategory":"Antiques",
            "type":"Retail Goods"
        }
    ],
    "sg:phone":"+44 20 7724 1278",
    "sg:postcode":"NW8 8ED",
    "sg:province":"Greater London",
    "wof:name":"Magus Antiques",
    "wof:placetype":"venue"
},
  "geometry": {"coordinates":[-0.1686590016,51.5247306824],"type":"Point"}
}