{
  "type": "Feature",
  "properties": {
    "addr:full":"Roundhouse Close, Fengate Peterborough Cambridgeshire PE1 5TA",
    "addr:postcode":"pe1 5ta",
    "addr:street":"Roundhouse Close",
    "iso:country":"GB",
    "sg:address":"Roundhouse Close, Fengate",
    "sg:city":"Peterborough",
    "sg:classifiers":[
        {
            "category":"Retail",
            "subcategory":"Auto Repair",
            "type":"Services"
        }
    ],
    "sg:phone":"+44 1733 344022",
    "sg:postcode":"PE1 5TA",
    "sg:province":"Cambridgeshire",
    "sg:tags":[
        "bodybuilder",
        "repairer"
    ],
    "wof:name":"Rouse & Beer Ltd",
    "wof:placetype":"venue"
},
  "geometry": {"coordinates":[-0.2209589928,52.5749130249],"type":"Point"}
}