{
  "type": "Feature",
  "properties": {
    "addr:full":"138 Southbury Road Enfield Greater London EN1 1YF",
    "addr:housenumber":"138",
    "addr:postcode":"en1 1yf",
    "addr:street":"Southbury Road",
    "iso:country":"GB",
    "sg:address":"138 Southbury Road",
    "sg:city":"Enfield",
    "sg:classifiers":[
        {
            "category":"Building & Trades",
            "subcategory":"Construction",
            "type":"Services"
        },
        {
            "category":"Military Area",
            "subcategory":"Air Force Base",
            "type":"Public Place"
        }
    ],
    "sg:phone":"+44 20 8367 5738",
    "sg:postcode":"EN1 1YF",
    "sg:province":"Greater London",
    "sg:tags":[
        "supplier",
        "plastering",
        "plaster",
        "related",
        "mnfrs"
    ],
    "wof:name":"Regency Plastercraft",
    "wof:placetype":"venue"
},
  "geometry": {"coordinates":[-0.0679309964,51.6512298584],"type":"Point"}
}