{
  "type": "Feature",
  "properties": {
    "iso:country":"GB",
    "sg:address":"Unit 6, Moorside Industrial Estate, Priestley Road",
    "sg:city":"Manchester",
    "sg:classifiers":[
        {
            "category":"Shopping",
            "subcategory":"Stationery & Office Supplies",
            "type":"Retail Goods"
        }
    ],
    "sg:phone":"+44 870 751 7744",
    "sg:postcode":"M20 5NJ",
    "sg:province":"Greater Manchester",
    "wof:name":"S R Berry (Office Supplies) Ltd.",
    "wof:placetype":"venue"
},
  "geometry": {"coordinates":[-2.22494,53.405769],"type":"Point"}
}