{
  "type": "Feature",
  "properties": {
    "iso:country":"GB",
    "sg:address":"19 High Street, Gorseinon",
    "sg:city":"Swansea",
    "sg:classifiers":[
        {
            "category":"Bus Charters",
            "type":"Transportation"
        },
        {
            "category":"Military Area",
            "subcategory":"Air Force Base",
            "type":"Public Place"
        }
    ],
    "sg:phone":"+44 1792 898888",
    "sg:postcode":"SA4 4BX",
    "sg:province":"Carmarthenshire",
    "sg:tags":[
        "taxi",
        "mini",
        "hire",
        "leasing",
        "private"
    ],
    "wof:name":"Swallow Cabs Ltd.",
    "wof:placetype":"venue"
},
  "geometry": {"coordinates":[-4.035417,51.668163],"type":"Point"}
}