{
  "type": "Feature",
  "properties": {
    "addr:full":"62 High Street, Lindfield Haywards Heath East Sussex RH16 2HL",
    "addr:housenumber":"62",
    "addr:postcode":"rh16 2hl",
    "addr:street":"High Street",
    "iso:country":"GB",
    "sg:address":"62 High Street, Lindfield",
    "sg:city":"Haywards Heath",
    "sg:classifiers":[
        {
            "category":"Home & Garden",
            "subcategory":"Carpets & Floor Coverings",
            "type":"Retail Goods"
        }
    ],
    "sg:phone":"+44 1444 483817",
    "sg:postcode":"RH16 2HL",
    "sg:province":"East Sussex",
    "sg:tags":[
        "oriental",
        "carpets",
        "design",
        "rug",
        "matting"
    ],
    "wof:name":"Lindfield Galleries",
    "wof:placetype":"venue"
},
  "geometry": {"coordinates":[-0.0808760002,51.0130462646],"type":"Point"}
}