{
  "type": "Feature",
  "properties": {
    "addr:full":"Bradley Senior Citizen Centre, Wilkinson Av Bilston West Midlands WV14 8PS",
    "addr:postcode":"wv14 8ps",
    "addr:street":"Av Bilston",
    "iso:country":"GB",
    "sg:address":"Bradley Senior Citizen Centre, Wilkinson Av",
    "sg:city":"Bilston",
    "sg:classifiers":[
        {
            "category":"Government",
            "subcategory":"Office",
            "type":"Public Place"
        }
    ],
    "sg:phone":"+44 1902 494573",
    "sg:postcode":"WV14 8PS",
    "sg:province":"West Midlands",
    "sg:tags":[
        "local"
    ],
    "wof:name":"Wolverhampton Borough Council",
    "wof:placetype":"venue"
},
  "geometry": {"coordinates":[-2.0743091106,52.542514801],"type":"Point"}
}