{
  "type": "Feature",
  "properties": {
    "iso:country":"GB",
    "sg:address":"20-22 Durham Lane, Eaglescliffe",
    "sg:city":"Stockton-on-tees",
    "sg:classifiers":[
        {
            "category":"Shopping",
            "subcategory":"Baby Store",
            "type":"Retail Goods"
        }
    ],
    "sg:postcode":"TS16 0EH",
    "sg:province":"Durham",
    "sg:tags":[
        "babywear",
        "childrens"
    ],
    "wof:name":"Trendy Tots",
    "wof:placetype":"venue"
},
  "geometry": {"coordinates":[-1.359768,54.521423],"type":"Point"}
}