{
  "type": "Feature",
  "properties": {
    "iso:country":"GB",
    "sg:address":"4 East Croft, Blagdon",
    "sg:city":"Bristol",
    "sg:classifiers":[
        {
            "category":"Retail",
            "subcategory":"Auto Repair",
            "type":"Services"
        }
    ],
    "sg:postcode":"BS40 7RT",
    "sg:province":"Somerset",
    "sg:tags":[
        "garage"
    ],
    "wof:name":"Dragon Garage Equipment Services",
    "wof:placetype":"venue"
},
  "geometry": {"coordinates":[-2.715264082,51.3258018494],"type":"Point"}
}