{
  "type": "Feature",
  "properties": {
    "iso:country":"GB",
    "sg:address":"8 Railway Street",
    "sg:city":"Beverley",
    "sg:classifiers":[
        {
            "category":"Building & Trades",
            "subcategory":"Landscaping Services",
            "type":"Services"
        }
    ],
    "sg:postcode":"HU17 0DX",
    "sg:province":"East Riding of Yorkshire",
    "sg:tags":[
        "horticultural",
        "consultant"
    ],
    "wof:name":"J E G  Johnstone",
    "wof:placetype":"venue"
},
  "geometry": {"coordinates":[-0.425595,53.841396],"type":"Point"}
}