{
  "type": "Feature",
  "properties": {
    "iso:country":"GB",
    "sg:address":"21 Bampton Street",
    "sg:city":"Tiverton",
    "sg:classifiers":[
        {
            "category":"Professional",
            "subcategory":"Management & Consulting",
            "type":"Services"
        }
    ],
    "sg:postcode":"EX16 6AA",
    "sg:province":"Devon",
    "sg:tags":[
        "consultant",
        "business"
    ],
    "wof:name":"Foxdown Consulting Ltd",
    "wof:placetype":"venue"
},
  "geometry": {"coordinates":[-3.486061,50.903797],"type":"Point"}
}