{
  "type": "Feature",
  "properties": {
    "addr:full":"Unit 18 Vandries St Liverpool Merseyside L3 7BJ",
    "addr:housenumber":"unit 18",
    "addr:postcode":"l3 7bj",
    "addr:street":"Vandries St",
    "iso:country":"GB",
    "sg:address":"Unit 18 Vandries St",
    "sg:city":"Liverpool",
    "sg:classifiers":[
        {
            "category":"Autos & Motor Vehicles",
            "subcategory":"Auto Supplies",
            "type":"Retail Goods"
        }
    ],
    "sg:phone":"+44 151 236 1977",
    "sg:postcode":"L3 7BJ",
    "sg:province":"Merseyside",
    "sg:tags":[
        "taxi",
        "equipment"
    ],
    "wof:name":"Argo Taximeters Ltd",
    "wof:placetype":"venue"
},
  "geometry": {"coordinates":[-2.998064,53.416824],"type":"Point"}
}