{
  "type": "Feature",
  "properties": {
    "iso:country":"GB",
    "sg:address":"508 Sutton Rd",
    "sg:city":"Southend On Sea",
    "sg:classifiers":[
        {
            "category":"Health Services",
            "subcategory":"Doctor",
            "type":"Services"
        }
    ],
    "sg:phone":"+44 1702 468301",
    "sg:postcode":"SS2 5PN",
    "sg:province":"Essex",
    "sg:tags":[
        "practitioners"
    ],
    "wof:name":"Pelta Bowring & Partners",
    "wof:placetype":"venue"
},
  "geometry": {"coordinates":[0.715459,51.552097],"type":"Point"}
}