{
  "type": "Feature",
  "properties": {
    "addr:full":"78 Leyland Lane Preston Lancashire PR25 1XB",
    "addr:housenumber":"78",
    "addr:postcode":"pr25 1xb",
    "addr:street":"Leyland Lane",
    "iso:country":"GB",
    "sg:address":"78 Leyland Lane",
    "sg:city":"Preston",
    "sg:classifiers":[
        {
            "category":"Personal",
            "subcategory":"Sauna",
            "type":"Services"
        }
    ],
    "sg:phone":"+44 1772 454550",
    "sg:postcode":"PR25 1XB",
    "sg:province":"Lancashire",
    "sg:tags":[
        "equipment",
        "sunbed"
    ],
    "wof:name":"No White Bits",
    "wof:placetype":"venue"
},
  "geometry": {"coordinates":[-2.7129659653,53.7457046509],"type":"Point"}
}