{
  "type": "Feature",
  "properties": {
    "iso:country":"GB",
    "sg:address":"74 Rowland Way, Hartwell Estate",
    "sg:city":"Aylesbury",
    "sg:classifiers":[
        {
            "category":"Professional",
            "subcategory":"Engineering",
            "type":"Services"
        }
    ],
    "sg:postcode":"HP19 7SW",
    "sg:province":"Buckinghamshire",
    "sg:tags":[
        "contractor",
        "electrical",
        "engineer"
    ],
    "wof:name":"B & B Electrical Contractors",
    "wof:placetype":"venue"
},
  "geometry": {"coordinates":[-0.832722,51.810871],"type":"Point"}
}