{
  "type": "Feature",
  "properties": {
    "iso:country":"GB",
    "sg:address":"Stevens & Stephens, First Floor 187 High Street",
    "sg:city":"Tonbridge",
    "sg:classifiers":[
        {
            "category":"Real Estate",
            "subcategory":"Developer",
            "type":"Services"
        }
    ],
    "sg:postcode":"TN9 1BX",
    "sg:province":"Kent",
    "sg:tags":[
        "property"
    ],
    "wof:name":"Hadlow Bakery Limited (The)",
    "wof:placetype":"venue"
},
  "geometry": {"coordinates":[0.276085,51.198673],"type":"Point"}
}