{
  "type": "Feature",
  "properties": {
    "addr:full":"First Floor Offices, 18 Baron Avenue Northampton Northamptonshire NN6 0JE",
    "addr:housenumber":"18",
    "addr:postcode":"nn6 0je",
    "addr:street":"Baron Avenue",
    "iso:country":"GB",
    "sg:address":"First Floor Offices, 18 Baron Avenue",
    "sg:city":"Northampton",
    "sg:classifiers":[
        {
            "category":"Building & Trades",
            "subcategory":"Cleaning & Sanitation",
            "type":"Services"
        },
        {
            "category":"Professional",
            "subcategory":"Business Services",
            "type":"Services"
        }
    ],
    "sg:phone":"+44 1604 811545",
    "sg:postcode":"NN6 0JE",
    "sg:province":"Northamptonshire",
    "sg:tags":[
        "shop",
        "contracting",
        "commercial"
    ],
    "wof:name":"Minster Cleaning Services Ltd",
    "wof:placetype":"venue"
},
  "geometry": {"coordinates":[-0.747510016,52.2714996338],"type":"Point"}
}