{
  "type": "Feature",
  "properties": {
    "iso:country":"GB",
    "sg:address":"32a High Street",
    "sg:city":"Bagshot",
    "sg:classifiers":[
        {
            "category":"Professional",
            "subcategory":"Management & Consulting",
            "type":"Services"
        }
    ],
    "sg:phone":"+44 1276 451416",
    "sg:postcode":"GU19 5AZ",
    "sg:province":"Berkshire",
    "sg:tags":[
        "consultant",
        "business"
    ],
    "wof:name":"The Windsor Consulting Group",
    "wof:placetype":"venue"
},
  "geometry": {"coordinates":[-0.6931899786,51.3610305786],"type":"Point"}
}