{
  "type": "Feature",
  "properties": {
    "addr:full":"Broadway Ho, 14 Mt Pleasant Rd Tunbridge Wells Kent TN1 1QU",
    "addr:housenumber":"14",
    "addr:postcode":"tn1 1qu",
    "addr:street":"Broadway;Mt Pleasant Rd",
    "iso:country":"GB",
    "sg:address":"Broadway Ho, 14 Mt Pleasant Rd",
    "sg:city":"Tunbridge Wells",
    "sg:classifiers":[
        {
            "category":"Professional",
            "subcategory":"Employment Agencies",
            "type":"Services"
        }
    ],
    "sg:phone":"+44 1892 618900",
    "sg:postcode":"TN1 1QU",
    "sg:province":"Kent",
    "sg:tags":[
        "consultant"
    ],
    "wof:name":"Aardvark Recruitment Ltd",
    "wof:placetype":"venue"
},
  "geometry": {"coordinates":[0.26355,51.133373],"type":"Point"}
}