{
  "type": "Feature",
  "properties": {
    "iso:country":"GB",
    "sg:address":"Unit F Newark Road North, Eastfield Industrial Estate",
    "sg:city":"Glenrothes",
    "sg:classifiers":[
        {
            "category":"Manufacturing",
            "subcategory":"Tobacco Products",
            "type":"Manufacturing & Wholesale Goods"
        },
        {
            "category":"Manufacturing",
            "subcategory":"Electronics",
            "type":"Manufacturing & Wholesale Goods"
        }
    ],
    "sg:phone":"+44 1592 772557",
    "sg:postcode":"KY7 4NT",
    "sg:province":"Fife",
    "sg:tags":[
        "manufacture",
        "mnfr",
        "distribution",
        "component",
        "electronic"
    ],
    "sg:website":"http://www.cgi.co.uk",
    "wof:name":"Compugraphics International Ltd",
    "wof:placetype":"venue"
},
  "geometry": {"coordinates":[-3.1424739361,56.1868896484],"type":"Point"}
}