{
  "type": "Feature",
  "properties": {
    "iso:country":"GB",
    "sg:address":"910 Woodborough Road, Mapperley Top",
    "sg:city":"Nottingham",
    "sg:classifiers":[
        {
            "category":"Health Services",
            "subcategory":"Podiatrist",
            "type":"Services"
        },
        {
            "category":"Health Services",
            "subcategory":"Chiropractor",
            "type":"Services"
        }
    ],
    "sg:phone":"+44 115 985 6560",
    "sg:postcode":"NG3 5QR",
    "sg:province":"Nottinghamshire",
    "sg:tags":[
        "podiatrists",
        "chiropodist"
    ],
    "wof:name":"STEVEN EPWORTH",
    "wof:placetype":"venue"
},
  "geometry": {"coordinates":[-1.124609,52.982288],"type":"Point"}
}