{
  "type": "Feature",
  "properties": {
    "addr:full":"13 - 13a West Street Dunstable Bedfordshire LU6 1SL",
    "addr:housenumber":"13 13a",
    "addr:postcode":"lu6 1sl",
    "addr:street":"West Street",
    "iso:country":"GB",
    "sg:address":"13 - 13a West Street",
    "sg:city":"Dunstable",
    "sg:classifiers":[
        {
            "category":"Communications",
            "subcategory":"Film & Video Production",
            "type":"Services"
        },
        {
            "category":"Communications",
            "type":"Services"
        }
    ],
    "sg:phone":"+44 1582 660247",
    "sg:postcode":"LU6 1SL",
    "sg:province":"Bedfordshire",
    "sg:tags":[
        "tv",
        "radio"
    ],
    "wof:name":"Square Deal Televsion Rental",
    "wof:placetype":"venue"
},
  "geometry": {"coordinates":[-0.521657,51.885628],"type":"Point"}
}