{
  "type": "Feature",
  "properties": {
    "addr:full":"Unit 4 Old Mine Yard, Allenheads Hexham Northumberland NE47 9HW",
    "addr:housenumber":"unit 4",
    "addr:postcode":"ne47 9hw",
    "addr:street":"Old Mine;Allenheads",
    "iso:country":"GB",
    "sg:address":"Unit 4 Old Mine Yard, Allenheads",
    "sg:city":"Hexham",
    "sg:classifiers":[
        {
            "category":"Shopping",
            "subcategory":"Antiques",
            "type":"Retail Goods"
        }
    ],
    "sg:postcode":"NE47 9HW",
    "sg:province":"Northumberland",
    "wof:name":"Allenheads Antique & Repair Restorations",
    "wof:placetype":"venue"
},
  "geometry": {"coordinates":[-2.2184200287,54.8024482727],"type":"Point"}
}