{
  "type": "Feature",
  "properties": {
    "iso:country":"GB",
    "sg:address":"Hill Ho, 7-9 Tetbury Hill",
    "sg:city":"Tetbury",
    "sg:classifiers":[
        {
            "category":"Sports & Exercise",
            "subcategory":"Bowling",
            "type":"Entertainment"
        }
    ],
    "sg:phone":"+44 1453 835792",
    "sg:postcode":"GL8 8LT",
    "sg:province":"Gloucestershire",
    "sg:tags":[
        "photography"
    ],
    "wof:name":"John Haseltine",
    "wof:placetype":"venue"
},
  "geometry": {"coordinates":[-2.1609759331,51.6378593445],"type":"Point"}
}