{
  "type": "Feature",
  "properties": {
    "iso:country":"GB",
    "sg:address":"2 Broad Street",
    "sg:city":"Ivybridge",
    "sg:classifiers":[
        {
            "category":"Home & Garden",
            "subcategory":"Hardware",
            "type":"Retail Goods"
        }
    ],
    "sg:phone":"+44 1548 830412",
    "sg:postcode":"PL21 0PS",
    "sg:province":"Devon",
    "wof:name":"R & H Pickles",
    "wof:placetype":"venue"
},
  "geometry": {"coordinates":[-3.886502,50.349163],"type":"Point"}
}