{
  "type": "Feature",
  "properties": {
    "addr:full":"6 Martingale Close, Cambridge Cambridge Cambridgeshire CB4 3TA",
    "addr:housenumber":"6",
    "addr:postcode":"cb4 3ta",
    "addr:street":"Martingale Close",
    "iso:country":"GB",
    "sg:address":"6 Martingale Close, Cambridge",
    "sg:city":"Cambridge",
    "sg:classifiers":[
        {
            "category":"Professional",
            "subcategory":"Accounting & Tax Preparation",
            "type":"Services"
        }
    ],
    "sg:postcode":"CB4 3TA",
    "sg:province":"Cambridgeshire",
    "sg:tags":[
        "accountant"
    ],
    "wof:name":"Cambridge Tax Practice Ltd (The)",
    "wof:placetype":"venue"
},
  "geometry": {"coordinates":[0.109243,52.227234],"type":"Point"}
}