{
  "type": "Feature",
  "properties": {
    "iso:country":"GB",
    "sg:address":"64 Westgate",
    "sg:city":"Bradford",
    "sg:classifiers":[
        {
            "category":"Health Services",
            "subcategory":"Optometrist",
            "type":"Services"
        }
    ],
    "sg:phone":"+44 1274 731569",
    "sg:postcode":"BD1 2QR",
    "sg:province":"West Yorkshire",
    "sg:tags":[
        "optician"
    ],
    "wof:name":"Lloyd & Robinson",
    "wof:placetype":"venue"
},
  "geometry": {"coordinates":[-1.757505,53.795403],"type":"Point"}
}