{
  "type": "Feature",
  "properties": {
    "iso:country":"GB",
    "sg:address":"Exmouth House, 3-11 Pine Street",
    "sg:city":"London",
    "sg:classifiers":[
        {
            "category":"Organizations",
            "subcategory":"Non-profit Organization",
            "type":"Services"
        }
    ],
    "sg:phone":"+44 20 7833 2577",
    "sg:postcode":"EC1R 0JH",
    "sg:province":"Greater London",
    "sg:tags":[
        "organisation",
        "voluntary",
        "charity"
    ],
    "wof:name":"Children's Express (U K)",
    "wof:placetype":"venue"
},
  "geometry": {"coordinates":[-0.10989,51.525345],"type":"Point"}
}