{
  "type": "Feature",
  "properties": {
    "addr:full":"54 Chapel Street Manchester Greater Manchester M3 7AA",
    "addr:housenumber":"54",
    "addr:postcode":"m3 7aa",
    "addr:street":"Chapel Street",
    "iso:country":"GB",
    "sg:address":"54 Chapel Street",
    "sg:city":"Manchester",
    "sg:classifiers":[
        {
            "category":"Professional",
            "subcategory":"Art Services",
            "type":"Services"
        }
    ],
    "sg:phone":"+44 161 834 5011",
    "sg:postcode":"M3 7AA",
    "sg:province":"Greater Manchester",
    "sg:tags":[
        "consultant",
        "design"
    ],
    "wof:name":"A Four Associates",
    "wof:placetype":"venue"
},
  "geometry": {"coordinates":[-2.2571,53.483898],"type":"Point"}
}