{
  "type": "Feature",
  "properties": {
    "addr:full":"100 Hockliffe Road Leighton Buzzard Bedfordshire LU7 3FN",
    "addr:housenumber":"100",
    "addr:postcode":"lu7 3fn",
    "addr:street":"Hockliffe Road",
    "iso:country":"GB",
    "sg:address":"100 Hockliffe Road",
    "sg:city":"Leighton Buzzard",
    "sg:classifiers":[
        {
            "category":"Home & Garden",
            "subcategory":"Household Appliances",
            "type":"Retail Goods"
        }
    ],
    "sg:postcode":"LU7 3FN",
    "sg:province":"Bedfordshire",
    "sg:tags":[
        "electrical"
    ],
    "wof:name":"Aston Refrigeration",
    "wof:placetype":"venue"
},
  "geometry": {"coordinates":[-0.649471,51.918262],"type":"Point"}
}