{
  "type": "Feature",
  "properties": {
    "addr:full":"15 Rayleigh Road Woodford Green Essex IG8 7HG",
    "addr:housenumber":"15",
    "addr:postcode":"ig8 7hg",
    "addr:street":"Rayleigh Road",
    "iso:country":"GB",
    "sg:address":"15 Rayleigh Road",
    "sg:city":"Woodford Green",
    "sg:classifiers":[
        {
            "category":"Personal",
            "type":"Services"
        }
    ],
    "sg:phone":"+44 20 8505 1553",
    "sg:postcode":"IG8 7HG",
    "sg:province":"Essex",
    "sg:tags":[
        "delivery"
    ],
    "wof:name":"Melton Transport Services",
    "wof:placetype":"venue"
},
  "geometry": {"coordinates":[0.0369199999,51.6050262451],"type":"Point"}
}