{
  "type": "Feature",
  "properties": {
    "addr:full":"Laltex House, Leigh Commerce Park, Green Fold Way Leigh Lancashire WN7 3XH",
    "addr:postcode":"wn7 3xh",
    "addr:street":"Commerce Park Green Fold Way Leigh",
    "iso:country":"GB",
    "sg:address":"Laltex House, Leigh Commerce Park, Green Fold Way",
    "sg:city":"Leigh",
    "sg:classifiers":[
        {
            "category":"Professional",
            "subcategory":"Business Services",
            "type":"Services"
        }
    ],
    "sg:phone":"+44 1942 687000",
    "sg:postcode":"WN7 3XH",
    "sg:province":"Lancashire",
    "sg:tags":[
        "import",
        "export",
        "agent"
    ],
    "wof:name":"Laltex & Co. Ltd.",
    "wof:placetype":"venue"
},
  "geometry": {"coordinates":[-2.5008990765,53.4833564758],"type":"Point"}
}