{
  "type": "Feature",
  "properties": {
    "addr:full":"St Alphage House London Greater London EC2Y 5HP",
    "addr:postcode":"ec2y 5hp",
    "iso:country":"GB",
    "sg:address":"St Alphage House",
    "sg:city":"London",
    "sg:classifiers":[
        {
            "category":"Professional",
            "subcategory":"Engineering",
            "type":"Services"
        }
    ],
    "sg:phone":"+44 20 7374 8333",
    "sg:postcode":"EC2Y 5HP",
    "sg:province":"Greater London",
    "sg:tags":[
        "design",
        "engineer"
    ],
    "wof:name":"C S A Consulting Engineers Ltd.",
    "wof:placetype":"venue"
},
  "geometry": {"coordinates":[-0.095619,51.517464],"type":"Point"}
}