{
  "type": "Feature",
  "properties": {
    "addr:full":"Morris Owen House, 43-45 Devizes Road Swindon Wiltshire SN1 4BG",
    "addr:housenumber":"43-45",
    "addr:postcode":"sn1 4bg",
    "addr:street":"Morris;Devizes Road",
    "iso:country":"GB",
    "sg:address":"Morris Owen House, 43-45 Devizes Road",
    "sg:city":"Swindon",
    "sg:classifiers":[
        {
            "category":"Professional",
            "subcategory":"Business Services",
            "type":"Services"
        }
    ],
    "sg:postcode":"SN1 4BG",
    "sg:province":"Wiltshire",
    "sg:tags":[
        "distribution"
    ],
    "wof:name":"Impact Pos Distribution Ltd",
    "wof:placetype":"venue"
},
  "geometry": {"coordinates":[-1.777241,51.550701],"type":"Point"}
}