{
  "type": "Feature",
  "properties": {
    "iso:country":"GB",
    "sg:address":"Unit 1, Whitehouse Farm, Rotherwick",
    "sg:city":"Hook",
    "sg:classifiers":[
        {
            "category":"Recreation",
            "subcategory":"Water Park",
            "type":"Entertainment"
        }
    ],
    "sg:phone":"+44 1256 765078",
    "sg:postcode":"RG27 9BZ",
    "sg:province":"Berkshire",
    "sg:tags":[
        "sport"
    ],
    "wof:name":"Challenger 10",
    "wof:placetype":"venue"
},
  "geometry": {"coordinates":[-0.9657189846,51.2813606262],"type":"Point"}
}