{
  "type": "Feature",
  "properties": {
    "addr:full":"2-3 West Street Horsham West Sussex RH12 1PB",
    "addr:housenumber":"2-3",
    "addr:postcode":"rh12 1pb",
    "addr:street":"West Street",
    "iso:country":"GB",
    "sg:address":"2-3 West Street",
    "sg:city":"Horsham",
    "sg:classifiers":[
        {
            "category":"Shopping",
            "subcategory":"Clothing, Apparel, & Fashions",
            "type":"Retail Goods"
        }
    ],
    "sg:phone":"+44 1403 261739",
    "sg:postcode":"RH12 1PB",
    "sg:province":"West Sussex",
    "sg:tags":[
        "shop"
    ],
    "wof:name":"The Edinburgh Woollen Mill Ltd.",
    "wof:placetype":"venue"
},
  "geometry": {"coordinates":[-0.3293879926,51.0623626709],"type":"Point"}
}