{
  "type": "Feature",
  "properties": {
    "iso:country":"GB",
    "sg:address":"53 Bellclough Road, Drolsden",
    "sg:city":"Manchester",
    "sg:classifiers":[
        {
            "category":"Military Area",
            "subcategory":"Air Force Base",
            "type":"Public Place"
        }
    ],
    "sg:phone":"+44 161 285 5411",
    "sg:postcode":"M43 7NS",
    "sg:province":"Greater Manchester",
    "sg:tags":[
        "taxi",
        "hire",
        "private"
    ],
    "wof:name":"J T Clare",
    "wof:placetype":"venue"
},
  "geometry": {"coordinates":[-2.144565,53.488289],"type":"Point"}
}