{
  "type": "Feature",
  "properties": {
    "iso:country":"GB",
    "sg:address":"114 Trafalgar Road",
    "sg:city":"London",
    "sg:classifiers":[
        {
            "category":"Bars & Pubs",
            "type":"Food & Drink"
        }
    ],
    "sg:postcode":"SE10 9UW",
    "sg:province":"Greater London",
    "sg:tags":[
        "pubs",
        "inn"
    ],
    "wof:name":"The Victoria",
    "wof:placetype":"venue"
},
  "geometry": {"coordinates":[0.00132,51.483913],"type":"Point"}
}