{
  "type": "Feature",
  "properties": {
    "addr:full":"Unit 3, Station Approach, Kidbrooke London Greater London SE3 9BA",
    "addr:housenumber":"unit 3",
    "addr:postcode":"se3 9ba",
    "addr:street":"Station Approach",
    "iso:country":"GB",
    "sg:address":"Unit 3, Station Approach, Kidbrooke",
    "sg:city":"London",
    "sg:classifiers":[
        {
            "category":"Taxi",
            "type":"Transportation"
        }
    ],
    "sg:postcode":"SE3 9BA",
    "sg:province":"Greater London",
    "sg:tags":[
        "mini",
        "cab"
    ],
    "wof:name":"Eagle Rapid Transit Co Ltd",
    "wof:placetype":"venue"
},
  "geometry": {"coordinates":[0.0269719996,51.4621009827],"type":"Point"}
}