{
  "type": "Feature",
  "properties": {
    "addr:full":"7 Market Place Wisbech Cambridgeshire PE13 1DT",
    "addr:housenumber":"7",
    "addr:postcode":"pe13 1dt",
    "addr:street":"Market Place",
    "iso:country":"GB",
    "sg:address":"7 Market Place",
    "sg:city":"Wisbech",
    "sg:classifiers":[
        {
            "category":"Travel",
            "subcategory":"Travel Agent",
            "type":"Entertainment"
        }
    ],
    "sg:phone":"+44 1945 466800",
    "sg:postcode":"PE13 1DT",
    "sg:province":"Cambridgeshire",
    "sg:tags":[
        "agency",
        "activity"
    ],
    "wof:name":"Galaxy Travel Ltd",
    "wof:placetype":"venue"
},
  "geometry": {"coordinates":[0.1614850014,52.6646537781],"type":"Point"}
}