{
  "type": "Feature",
  "properties": {
    "iso:country":"GB",
    "sg:address":"176 Dalling Road",
    "sg:city":"London",
    "sg:classifiers":[
        {
            "category":"Shopping",
            "subcategory":"Department Store",
            "type":"Retail Goods"
        }
    ],
    "sg:phone":"+44 20 8741 9738",
    "sg:postcode":"W6 0EU",
    "sg:province":"Greater London",
    "wof:name":"Graff Stores",
    "wof:placetype":"venue"
},
  "geometry": {"coordinates":[-0.234417,51.498566],"type":"Point"}
}