{
  "type": "Feature",
  "properties": {
    "addr:full":"19 Salem St Bradford West Yorkshire BD1 4QH",
    "addr:housenumber":"19",
    "addr:postcode":"bd1 4qh",
    "addr:street":"Salem St",
    "iso:country":"GB",
    "sg:address":"19 Salem St",
    "sg:city":"Bradford",
    "sg:classifiers":[
        {
            "category":"Real Estate",
            "subcategory":"Surveying",
            "type":"Services"
        }
    ],
    "sg:phone":"+44 1274 729792",
    "sg:postcode":"BD1 4QH",
    "sg:province":"West Yorkshire",
    "sg:tags":[
        "surveyor",
        "valuer"
    ],
    "wof:name":"Benjamin Bentley and Partners (Bradford)",
    "wof:placetype":"venue"
},
  "geometry": {"coordinates":[-1.7551549673,53.7979202271],"type":"Point"}
}