{
  "type": "Feature",
  "properties": {
    "addr:full":"218 Lower Rd, Bermondsey London Greater London SE8 5DJ",
    "addr:housenumber":"218",
    "addr:postcode":"se8 5dj",
    "addr:street":"Lower Rd",
    "iso:country":"GB",
    "sg:address":"218 Lower Rd, Bermondsey",
    "sg:city":"London",
    "sg:classifiers":[
        {
            "category":"Shopping",
            "subcategory":"Department Store",
            "type":"Retail Goods"
        }
    ],
    "sg:postcode":"SE8 5DJ",
    "sg:province":"Greater London",
    "wof:name":"Encore Carpets",
    "wof:placetype":"venue"
},
  "geometry": {"coordinates":[-0.044267,51.491302],"type":"Point"}
}