{
  "type": "Feature",
  "properties": {
    "addr:full":"Cefn, Buttington Welshpool Shropshire SY21 8TB",
    "addr:postcode":"sy21 8tb",
    "iso:country":"GB",
    "sg:address":"Cefn, Buttington",
    "sg:city":"Welshpool",
    "sg:classifiers":[
        {
            "category":"Education",
            "subcategory":"School",
            "type":"Public Place"
        },
        {
            "category":"Community Center",
            "type":"Public Place"
        },
        {
            "category":"Government",
            "subcategory":"Office",
            "type":"Public Place"
        }
    ],
    "sg:phone":"+44 1938 570283",
    "sg:postcode":"SY21 8TB",
    "sg:province":"Shropshire",
    "sg:tags":[
        "local",
        "authority",
        "centre"
    ],
    "wof:name":"Buttington Trewern County Primary School",
    "wof:placetype":"venue"
},
  "geometry": {"coordinates":[-3.111803,52.665314],"type":"Point"}
}