{
  "type": "Feature",
  "properties": {
    "addr:full":"King Edward Av Worthing West Sussex BN14 8DH",
    "addr:postcode":"bn14 8dh",
    "addr:street":"King;Av Worthing",
    "iso:country":"GB",
    "sg:address":"King Edward Av",
    "sg:city":"Worthing",
    "sg:classifiers":[
        {
            "category":"Wholesale",
            "subcategory":"Groceries",
            "type":"Manufacturing & Wholesale Goods"
        }
    ],
    "sg:phone":"+44 1494 555900",
    "sg:postcode":"BN14 8DH",
    "sg:province":"West Sussex",
    "sg:tags":[
        "food",
        "supplier",
        "drink"
    ],
    "wof:name":"3663",
    "wof:placetype":"venue"
},
  "geometry": {"coordinates":[-0.3600490093,50.8211593628],"type":"Point"}
}