{
  "type": "Feature",
  "properties": {
    "addr:full":"72 Forest Rd Worthing West Sussex BN14 9LY",
    "addr:housenumber":"72",
    "addr:postcode":"bn14 9ly",
    "addr:street":"Forest Rd",
    "iso:country":"GB",
    "sg:address":"72 Forest Rd",
    "sg:city":"Worthing",
    "sg:classifiers":[
        {
            "category":"Building & Trades",
            "subcategory":"Construction",
            "type":"Services"
        }
    ],
    "sg:phone":"+44 1903 522545",
    "sg:postcode":"BN14 9LY",
    "sg:province":"West Sussex",
    "sg:tags":[
        "roofing"
    ],
    "wof:name":"James Jackson",
    "wof:placetype":"venue"
},
  "geometry": {"coordinates":[-0.3731060028,50.8328895569],"type":"Point"}
}