{
  "type": "Feature",
  "properties": {
    "addr:full":"10 North Road, Yate Bristol Gloucestershire BS37 7PA",
    "addr:housenumber":"10",
    "addr:postcode":"bs37 7pa",
    "addr:street":"North Road Yate",
    "iso:country":"GB",
    "sg:address":"10 North Road, Yate",
    "sg:city":"Bristol",
    "sg:classifiers":[
        {
            "category":"Manufacturing",
            "subcategory":"Signs",
            "type":"Manufacturing & Wholesale Goods"
        }
    ],
    "sg:phone":"+44 1454 311475",
    "sg:postcode":"BS37 7PA",
    "sg:province":"Gloucestershire",
    "sg:tags":[
        "nameplate"
    ],
    "wof:name":"Altaroute Ltd.",
    "wof:placetype":"venue"
},
  "geometry": {"coordinates":[-2.4351890087,51.550491333],"type":"Point"}
}