{
  "type": "Feature",
  "properties": {
    "addr:full":"116 Corporation Street Birmingham West Midlands B4 6SX",
    "addr:housenumber":"116",
    "addr:postcode":"6sx",
    "addr:street":"Corporation Street",
    "iso:country":"GB",
    "sg:address":"116 Corporation Street",
    "sg:city":"Birmingham",
    "sg:classifiers":[
        {
            "category":"Shopping",
            "subcategory":"Hobbies, Toys, & Games",
            "type":"Retail Goods"
        }
    ],
    "sg:phone":"+44 121 236 7880",
    "sg:postcode":"B4 6SX",
    "sg:province":"West Midlands",
    "sg:tags":[
        "shop",
        "computer",
        "retailer"
    ],
    "wof:name":"Games Workshop Ltd.",
    "wof:placetype":"venue"
},
  "geometry": {"coordinates":[-1.8950109482,52.4814376831],"type":"Point"}
}