{
  "type": "Feature",
  "properties": {
    "iso:country":"GB",
    "sg:address":"63 Ferry Road",
    "sg:city":"Renfrew",
    "sg:classifiers":[
        {
            "category":"Recreation",
            "type":"Entertainment"
        }
    ],
    "sg:phone":"+44 141 886 7770",
    "sg:postcode":"PA4 8SH",
    "sg:province":"Renfrewshire",
    "sg:tags":[
        "snooker",
        "billiards",
        "pool"
    ],
    "wof:name":"The Inn-Off Snooker Club",
    "wof:placetype":"venue"
},
  "geometry": {"coordinates":[-4.383937,55.885204],"type":"Point"}
}