{
  "type": "Feature",
  "properties": {
    "addr:full":"Pied House, Garthmyl Montgomery Shropshire SY15 6SQ",
    "addr:postcode":"sy15 6sq",
    "iso:country":"GB",
    "sg:address":"Pied House, Garthmyl",
    "sg:city":"Montgomery",
    "sg:classifiers":[
        {
            "category":"Farming",
            "subcategory":"Dairy Farm",
            "type":"Manufacturing & Wholesale Goods"
        }
    ],
    "sg:phone":"+44 1686 640365",
    "sg:postcode":"SY15 6SQ",
    "sg:province":"Shropshire",
    "wof:name":"R A Jones",
    "wof:placetype":"venue"
},
  "geometry": {"coordinates":[-3.147599,52.55225],"type":"Point"}
}