{
  "type": "Feature",
  "properties": {
    "iso:country":"GB",
    "sg:address":"2 Arndale House, Durham Road, Birtley",
    "sg:city":"Chester-le-street",
    "sg:classifiers":[
        {
            "category":"Shopping",
            "subcategory":"Used Merchandise",
            "type":"Retail Goods"
        }
    ],
    "sg:phone":"+44 191 410 9891",
    "sg:postcode":"DH3 2PG",
    "sg:province":"Durham",
    "sg:tags":[
        "shop",
        "second-hand"
    ],
    "wof:name":"Allsorts",
    "wof:placetype":"venue"
},
  "geometry": {"coordinates":[-1.574964,54.859135],"type":"Point"}
}