{
  "type": "Feature",
  "properties": {
    "iso:country":"GB",
    "sg:address":"31 Walmgate",
    "sg:city":"York",
    "sg:classifiers":[
        {
            "category":"Travel",
            "subcategory":"Travel Agent",
            "type":"Entertainment"
        }
    ],
    "sg:phone":"+44 1904 622922",
    "sg:postcode":"YO1 9TX",
    "sg:province":"North Yorkshire",
    "sg:tags":[
        "agency",
        "activity"
    ],
    "wof:name":"DIRECT READER HOLIDAYS LTD",
    "wof:placetype":"venue"
},
  "geometry": {"coordinates":[-1.076455,53.957043],"type":"Point"}
}