{
  "type": "Feature",
  "properties": {
    "addr:full":"91 Drake Av Worcester Worcestershire WR2 5RS",
    "addr:housenumber":"91",
    "addr:postcode":"wr2 5rs",
    "addr:street":"Drake Av",
    "iso:country":"GB",
    "sg:address":"91 Drake Av",
    "sg:city":"Worcester",
    "sg:classifiers":[
        {
            "category":"Home & Garden",
            "subcategory":"Carpets & Floor Coverings",
            "type":"Retail Goods"
        }
    ],
    "sg:phone":"+44 1905 426572",
    "sg:postcode":"WR2 5RS",
    "sg:province":"Worcestershire",
    "sg:tags":[
        "carpets",
        "rug",
        "matting"
    ],
    "wof:name":"Adam Price",
    "wof:placetype":"venue"
},
  "geometry": {"coordinates":[-2.2510170937,52.1913146973],"type":"Point"}
}