{
  "type": "Feature",
  "properties": {
    "iso:country":"GB",
    "sg:address":"7 Leicester Road, Blaby",
    "sg:city":"Leicester",
    "sg:classifiers":[
        {
            "category":"Shopping",
            "subcategory":"Clothing, Apparel, & Fashions",
            "type":"Retail Goods"
        }
    ],
    "sg:phone":"+44 116 277 4618",
    "sg:postcode":"LE8 4GR",
    "sg:province":"Leicestershire",
    "sg:tags":[
        "menswear"
    ],
    "wof:name":"Kevin Sheffield",
    "wof:placetype":"venue"
},
  "geometry": {"coordinates":[-1.163126,52.576096],"type":"Point"}
}