{
  "type": "Feature",
  "properties": {
    "addr:full":"Chimneys Family Centre, 6 Locks Hill Brighton East Sussex BN41 2LB",
    "addr:housenumber":"6",
    "addr:postcode":"bn41 2lb",
    "addr:street":"Locks Hill",
    "iso:country":"GB",
    "sg:address":"Chimneys Family Centre, 6 Locks Hill",
    "sg:city":"Brighton",
    "sg:classifiers":[
        {
            "category":"Government",
            "subcategory":"Office",
            "type":"Public Place"
        }
    ],
    "sg:phone":"+44 1273 296527",
    "sg:postcode":"BN41 2LB",
    "sg:province":"East Sussex",
    "sg:tags":[
        "local"
    ],
    "wof:name":"Brighton & Hove Council",
    "wof:placetype":"venue"
},
  "geometry": {"coordinates":[-0.21724,50.839191],"type":"Point"}
}