{
  "type": "Feature",
  "properties": {
    "iso:country":"GB",
    "sg:address":"20 Green La",
    "sg:city":"Chichester",
    "sg:classifiers":[
        {
            "category":"Autos & Motor Vehicles",
            "subcategory":"Motorcycle Sales",
            "type":"Retail Goods"
        }
    ],
    "sg:phone":"+44 1243 607903",
    "sg:postcode":"PO20 0AQ",
    "sg:province":"West Sussex",
    "sg:tags":[
        "chauffeur",
        "driven",
        "car"
    ],
    "wof:name":"Senate Chauffeur Services",
    "wof:placetype":"venue"
},
  "geometry": {"coordinates":[-0.789786,50.727833],"type":"Point"}
}