{
  "type": "Feature",
  "properties": {
    "addr:full":"Unit 41 Britannia Way, Britannia Enterprise Park Lichfield Staffordshire WS14 9UY",
    "addr:housenumber":"unit 41",
    "addr:postcode":"ws14 9uy",
    "addr:street":"Britannia Way;Enterprise Park",
    "iso:country":"GB",
    "sg:address":"Unit 41 Britannia Way, Britannia Enterprise Park",
    "sg:city":"Lichfield",
    "sg:classifiers":[
        {
            "category":"Professional",
            "subcategory":"Accounting & Tax Preparation",
            "type":"Services"
        }
    ],
    "sg:phone":"+44 1543 419907",
    "sg:postcode":"WS14 9UY",
    "sg:province":"Staffordshire",
    "sg:tags":[
        "accountant"
    ],
    "wof:name":"Hewitt & Associates",
    "wof:placetype":"venue"
},
  "geometry": {"coordinates":[-1.8019720316,52.68542099],"type":"Point"}
}