{
  "type": "Feature",
  "properties": {
    "addr:full":"17 Kettlebrook Road, Shirley Solihull West Midlands B90 4YL",
    "addr:housenumber":"17",
    "addr:postcode":"b90 4yl",
    "addr:street":"Kettlebrook Road",
    "iso:country":"GB",
    "sg:address":"17 Kettlebrook Road, Shirley",
    "sg:city":"Solihull",
    "sg:classifiers":[
        {
            "category":"Manufacturing",
            "subcategory":"Petroleum Products",
            "type":"Manufacturing & Wholesale Goods"
        }
    ],
    "sg:phone":"+44 121 711 1416",
    "sg:postcode":"B90 4YL",
    "sg:province":"West Midlands",
    "sg:tags":[
        "double",
        "glazing"
    ],
    "wof:name":"Precision Window Installations",
    "wof:placetype":"venue"
},
  "geometry": {"coordinates":[-1.7819340229,52.390209198],"type":"Point"}
}