{
  "type": "Feature",
  "properties": {
    "iso:country":"GB",
    "sg:address":"77 Duke Street",
    "sg:city":"Whitehaven",
    "sg:classifiers":[
        {
            "category":"Organizations",
            "subcategory":"Non-profit Organization",
            "type":"Services"
        }
    ],
    "sg:phone":"+44 1946 592857",
    "sg:postcode":"CA28 7NW",
    "sg:province":"Cumbria",
    "sg:tags":[
        "organisation",
        "voluntary",
        "charity"
    ],
    "wof:name":"Anchor Trust",
    "wof:placetype":"venue"
},
  "geometry": {"coordinates":[-3.585867,54.548615],"type":"Point"}
}