{
  "type": "Feature",
  "properties": {
    "addr:full":"34 Europa Way, Martineau Lane Norwich Norfolk NR1 2EN",
    "addr:housenumber":"34",
    "addr:postcode":"nr1 2en",
    "addr:street":"Europa Way Martineau Lane",
    "iso:country":"GB",
    "sg:address":"34 Europa Way, Martineau Lane",
    "sg:city":"Norwich",
    "sg:classifiers":[
        {
            "category":"Professional",
            "subcategory":"Business Services",
            "type":"Services"
        }
    ],
    "sg:phone":"+44 1603 627182",
    "sg:postcode":"NR1 2EN",
    "sg:province":"Norfolk",
    "sg:tags":[
        "distribution"
    ],
    "wof:name":"White Arrow Supplies & Services Ltd.",
    "wof:placetype":"venue"
},
  "geometry": {"coordinates":[1.310462,52.614902],"type":"Point"}
}