{
  "type": "Feature",
  "properties": {
    "iso:country":"GB",
    "sg:address":"2 West Lodge, Station Approach",
    "sg:city":"West Byfleet",
    "sg:classifiers":[
        {
            "category":"Shopping",
            "subcategory":"Pharmacy",
            "type":"Retail Goods"
        }
    ],
    "sg:phone":"+44 1932 345004",
    "sg:postcode":"KT14 6NG",
    "sg:province":"Surrey",
    "sg:tags":[
        "pharmacist",
        "dispensing",
        "chemist"
    ],
    "wof:name":"Lloyds Pharmacy Ltd",
    "wof:placetype":"venue"
},
  "geometry": {"coordinates":[-0.496921,51.338421],"type":"Point"}
}