{
  "type": "Feature",
  "properties": {
    "addr:full":"22 Brookend Street Ross-on-wye Gloucestershire HR9 7EE",
    "addr:housenumber":"22",
    "addr:postcode":"hr9 7ee",
    "addr:street":"Brookend Street",
    "iso:country":"GB",
    "sg:address":"22 Brookend Street",
    "sg:city":"Ross-on-wye",
    "sg:classifiers":[
        {
            "category":"Retail",
            "subcategory":"Laundry & Dry Cleaning",
            "type":"Services"
        }
    ],
    "sg:postcode":"HR9 7EE",
    "sg:province":"Gloucestershire",
    "sg:tags":[
        "alteration"
    ],
    "wof:name":"W L & S W H Chan",
    "wof:placetype":"venue"
},
  "geometry": {"coordinates":[-2.5814011097,51.91664505],"type":"Point"}
}