{
  "type": "Feature",
  "properties": {
    "iso:country":"GB",
    "sg:address":"16 Pennine Way",
    "sg:city":"Ashby-de-la-zouch",
    "sg:classifiers":[
        {
            "category":"Wholesale",
            "subcategory":"Non-durable Goods",
            "type":"Manufacturing & Wholesale Goods"
        },
        {
            "category":"Home & Garden",
            "subcategory":"Kitchen Supply",
            "type":"Retail Goods"
        }
    ],
    "sg:phone":"+44 1530 411393",
    "sg:postcode":"LE65 1EW",
    "sg:province":"Derbyshire",
    "sg:tags":[
        "carry",
        "cash",
        "catering"
    ],
    "wof:name":"Central Bar & Catering Supplies",
    "wof:placetype":"venue"
},
  "geometry": {"coordinates":[-1.4692380428,52.7416114807],"type":"Point"}
}