{
  "type": "Feature",
  "properties": {
    "addr:full":"26-30 Malvern Road Worcester Worcestershire WR2 4LG",
    "addr:housenumber":"26-30",
    "addr:postcode":"wr2 4lg",
    "addr:street":"Malvern Road",
    "iso:country":"GB",
    "sg:address":"26-30 Malvern Road",
    "sg:city":"Worcester",
    "sg:classifiers":[
        {
            "category":"Recreation",
            "subcategory":"Fishing",
            "type":"Entertainment"
        }
    ],
    "sg:postcode":"WR2 4LG",
    "sg:province":"Worcestershire",
    "sg:tags":[
        "angling"
    ],
    "wof:name":"Ellen Reynolds",
    "wof:placetype":"venue"
},
  "geometry": {"coordinates":[-2.2362248898,52.1858825684],"type":"Point"}
}