{
  "type": "Feature",
  "properties": {
    "addr:full":"1 Kings Court, Water Lane Wilmslow Cheshire SK9 5AR",
    "addr:housenumber":"1",
    "addr:postcode":"sk9 5ar",
    "addr:street":"Kings Court Water Lane",
    "iso:country":"GB",
    "sg:address":"1 Kings Court, Water Lane",
    "sg:city":"Wilmslow",
    "sg:classifiers":[
        {
            "category":"Professional",
            "subcategory":"Employment Agencies",
            "type":"Services"
        }
    ],
    "sg:phone":"+44 1625 444200",
    "sg:postcode":"SK9 5AR",
    "sg:province":"Cheshire",
    "sg:tags":[
        "consultant"
    ],
    "wof:name":"Aristo Intelligent Recruitment",
    "wof:placetype":"venue"
},
  "geometry": {"coordinates":[-2.246018,53.335548],"type":"Point"}
}