{
  "type": "Feature",
  "properties": {
    "addr:full":"Elephant & Castle The Grn, Woodwalton Huntingdon Bedfordshire PE28 5YN",
    "addr:postcode":"pe28 5yn",
    "addr:street":"The",
    "iso:country":"GB",
    "sg:address":"Elephant & Castle The Grn, Woodwalton",
    "sg:city":"Huntingdon",
    "sg:classifiers":[
        {
            "category":"Manufacturing",
            "subcategory":"Metals",
            "type":"Manufacturing & Wholesale Goods"
        }
    ],
    "sg:phone":"+44 1487 773553",
    "sg:postcode":"PE28 5YN",
    "sg:province":"Bedfordshire",
    "sg:tags":[
        "steel",
        "fabricator",
        "erectors"
    ],
    "wof:name":"Ironstone (The)",
    "wof:placetype":"venue"
},
  "geometry": {"coordinates":[-0.21579,52.412472],"type":"Point"}
}