{
  "type": "Feature",
  "properties": {
    "iso:country":"GB",
    "sg:address":"Mosshill Industrial Estate",
    "sg:city":"Ayr",
    "sg:classifiers":[
        {
            "category":"Shopping",
            "subcategory":"Computers & Home Electronics",
            "type":"Retail Goods"
        }
    ],
    "sg:phone":"+44 141 814 8000",
    "sg:postcode":"KA6 6BE",
    "sg:province":"East Ayrshire",
    "wof:name":"Digital Equipment Scotland",
    "wof:placetype":"venue"
},
  "geometry": {"coordinates":[-4.5734400749,55.4246902466],"type":"Point"}
}