{
  "type": "Feature",
  "properties": {
    "addr:full":"Hyde Farm, Hyde Wareham Dorset BH20 7NX",
    "addr:postcode":"bh20 7nx",
    "iso:country":"GB",
    "sg:address":"Hyde Farm, Hyde",
    "sg:city":"Wareham",
    "sg:classifiers":[
        {
            "category":"Farming",
            "subcategory":"Livestock Farm",
            "type":"Manufacturing & Wholesale Goods"
        }
    ],
    "sg:phone":"+44 1929 471284",
    "sg:postcode":"BH20 7NX",
    "sg:province":"Dorset",
    "sg:tags":[
        "others"
    ],
    "wof:name":"Peter Ives Ltd.",
    "wof:placetype":"venue"
},
  "geometry": {"coordinates":[-2.181664,50.716805],"type":"Point"}
}