{
  "type": "Feature",
  "properties": {
    "iso:country":"GB",
    "sg:address":"24 Victoria Road",
    "sg:city":"Kirkcaldy",
    "sg:classifiers":[
        {
            "category":"Home & Garden",
            "subcategory":"Building Materials",
            "type":"Retail Goods"
        }
    ],
    "sg:phone":"+44 1592 643148",
    "sg:postcode":"KY1 1DX",
    "sg:province":"Fife",
    "sg:tags":[
        "furnishers",
        "bathroom",
        "planner"
    ],
    "wof:name":"Victoria Design",
    "wof:placetype":"venue"
},
  "geometry": {"coordinates":[-3.1585359573,56.1178016663],"type":"Point"}
}