{
  "type": "Feature",
  "properties": {
    "addr:full":"Oliver House, Hall Street Chelmsford Essex CM2 0HG",
    "addr:postcode":"cm2 0hg",
    "addr:street":"Hall Street",
    "iso:country":"GB",
    "sg:address":"Oliver House, Hall Street",
    "sg:city":"Chelmsford",
    "sg:classifiers":[
        {
            "category":"Manufacturing",
            "subcategory":"Tools & Machinery",
            "type":"Manufacturing & Wholesale Goods"
        }
    ],
    "sg:phone":"+44 1245 269695",
    "sg:postcode":"CM2 0HG",
    "sg:province":"Essex",
    "sg:tags":[
        "society",
        "friendly"
    ],
    "wof:name":"Crawford & Co. Adjusters (Uk) Ltd.",
    "wof:placetype":"venue"
},
  "geometry": {"coordinates":[0.473269999,51.7295646667],"type":"Point"}
}