{
  "type": "Feature",
  "properties": {
    "iso:country":"GB",
    "sg:address":"Edgar Ho, 12 Birmingham Rd",
    "sg:city":"Walsall",
    "sg:classifiers":[
        {
            "category":"Shopping",
            "subcategory":"Stationery & Office Supplies",
            "type":"Retail Goods"
        }
    ],
    "sg:phone":"+44 1922 723616",
    "sg:postcode":"WS1 2NA",
    "sg:province":"West Midlands",
    "wof:name":"Zip Office Products Ltd",
    "wof:placetype":"venue"
},
  "geometry": {"coordinates":[-1.976104,52.585289],"type":"Point"}
}