{
  "type": "Feature",
  "properties": {
    "addr:full":"Midlairgh Quarry, Daviot Inverness Highland IV2 7HX",
    "addr:postcode":"iv2 7hx",
    "addr:street":"Midlairgh;Daviot",
    "iso:country":"GB",
    "sg:address":"Midlairgh Quarry, Daviot",
    "sg:city":"Inverness",
    "sg:classifiers":[
        {
            "category":"Home & Garden",
            "subcategory":"Carpets & Floor Coverings",
            "type":"Retail Goods"
        }
    ],
    "sg:phone":"+44 1463 772058",
    "sg:postcode":"IV2 7HX",
    "sg:province":"Highland",
    "sg:tags":[
        "asphalt",
        "macadam"
    ],
    "wof:name":"Bardon Aggregates",
    "wof:placetype":"venue"
},
  "geometry": {"coordinates":[-4.14801,57.497669],"type":"Point"}
}