{
  "type": "Feature",
  "properties": {
    "iso:country":"GB",
    "sg:address":"73 High Street, Gilfach Goch",
    "sg:city":"Porth",
    "sg:classifiers":[
        {
            "category":"Organizations",
            "subcategory":"Community Association",
            "type":"Services"
        },
        {
            "category":"Organizations",
            "subcategory":"Membership Organization",
            "type":"Services"
        }
    ],
    "sg:phone":"+44 1443 672301",
    "sg:postcode":"CF39 8SR",
    "sg:province":"Bridgend",
    "sg:tags":[
        "club",
        "social"
    ],
    "wof:name":"Gilfach Goch R F C",
    "wof:placetype":"venue"
},
  "geometry": {"coordinates":[-3.471288,51.593716],"type":"Point"}
}