{
  "type": "Feature",
  "properties": {
    "iso:country":"GB",
    "sg:address":"2a Old Market Place",
    "sg:city":"Altrincham",
    "sg:classifiers":[
        {
            "category":"Organizations",
            "subcategory":"Non-profit Organization",
            "type":"Services"
        }
    ],
    "sg:phone":"+44 161 929 9255",
    "sg:postcode":"WA14 4NP",
    "sg:province":"Cheshire",
    "sg:tags":[
        "organisation",
        "voluntary",
        "charity"
    ],
    "wof:name":"Lubavitch (U K) Ltd.",
    "wof:placetype":"venue"
},
  "geometry": {"coordinates":[-2.350619,53.388809],"type":"Point"}
}