{
  "type": "Feature",
  "properties": {
    "addr:full":"Trenance Mill, Trenance St Austell Cornwall PL25 5LZ",
    "addr:postcode":"pl25 5lz",
    "addr:street":"Trenance",
    "iso:country":"GB",
    "sg:address":"Trenance Mill, Trenance",
    "sg:city":"St Austell",
    "sg:classifiers":[
        {
            "category":"Manufacturing",
            "subcategory":"Rubber & Plastics",
            "type":"Manufacturing & Wholesale Goods"
        }
    ],
    "sg:phone":"+44 1726 74771",
    "sg:postcode":"PL25 5LZ",
    "sg:province":"Cornwall",
    "sg:tags":[
        "supplier",
        "stockist"
    ],
    "wof:name":"Plastestrip (Profiles) Ltd.",
    "wof:placetype":"venue"
},
  "geometry": {"coordinates":[-4.792324,50.337421],"type":"Point"}
}