{
  "type": "Feature",
  "properties": {
    "iso:country":"GB",
    "sg:address":"Hazelwick Avenue",
    "sg:city":"Crawley",
    "sg:classifiers":[
        {
            "category":"Food & Beverages",
            "subcategory":"Supermarket",
            "type":"Retail Goods"
        }
    ],
    "sg:phone":"+44 1293 562652",
    "sg:postcode":"RH10 1GY",
    "sg:province":"Surrey",
    "wof:name":"Tesco Stores Ltd.",
    "wof:placetype":"venue"
},
  "geometry": {"coordinates":[-0.163282,51.118248],"type":"Point"}
}