{
  "type": "Feature",
  "properties": {
    "iso:country":"GB",
    "sg:address":"97b Christleton Road, Boughton",
    "sg:city":"Chester",
    "sg:classifiers":[
        {
            "category":"Shopping",
            "subcategory":"Computers & Home Electronics",
            "type":"Retail Goods"
        }
    ],
    "sg:phone":"+44 1244 346558",
    "sg:postcode":"CH3 5UQ",
    "sg:province":"Cheshire",
    "sg:tags":[
        "electrical"
    ],
    "wof:name":"Alec Ainley Electrical Wholesalers",
    "wof:placetype":"venue"
},
  "geometry": {"coordinates":[-2.867922,53.190895],"type":"Point"}
}