{
  "type": "Feature",
  "properties": {
    "iso:country":"GB",
    "sg:address":"Latimer Farm, West Kington",
    "sg:city":"Chippenham",
    "sg:classifiers":[
        {
            "category":"Farming",
            "subcategory":"Livestock Farm",
            "type":"Manufacturing & Wholesale Goods"
        }
    ],
    "sg:phone":"+44 1249 782481",
    "sg:postcode":"SN14 7JQ",
    "sg:province":"Gloucestershire",
    "sg:tags":[
        "others"
    ],
    "wof:name":"J J Charnaud",
    "wof:placetype":"venue"
},
  "geometry": {"coordinates":[-2.27272,51.495705],"type":"Point"}
}