{
  "type": "Feature",
  "properties": {
    "addr:full":"Unit 3 Woodston Gate, Shrewsbury Avenue Peterborough Cambridgeshire PE2 7LF",
    "addr:housenumber":"unit 3",
    "addr:postcode":"pe2 7lf",
    "addr:street":"Woodston Gate Shrewsbury Avenue",
    "iso:country":"GB",
    "sg:address":"Unit 3 Woodston Gate, Shrewsbury Avenue",
    "sg:city":"Peterborough",
    "sg:classifiers":[
        {
            "category":"Professional",
            "type":"Services"
        }
    ],
    "sg:postcode":"PE2 7LF",
    "sg:province":"Cambridgeshire",
    "sg:tags":[
        "repair",
        "tech",
        "maintenance"
    ],
    "wof:name":"Qwinstar Ltd.",
    "wof:placetype":"venue"
},
  "geometry": {"coordinates":[-0.2639339864,52.5560798645],"type":"Point"}
}