{
  "type": "Feature",
  "properties": {
    "addr:full":"Butts Farm, Stoke Street, Rodney Stoke Cheddar Somerset BS27 3UP",
    "addr:postcode":"bs27 3up",
    "addr:street":"Stoke Street",
    "iso:country":"GB",
    "sg:address":"Butts Farm, Stoke Street, Rodney Stoke",
    "sg:city":"Cheddar",
    "sg:classifiers":[
        {
            "category":"Farming",
            "subcategory":"Livestock Farm",
            "type":"Manufacturing & Wholesale Goods"
        }
    ],
    "sg:postcode":"BS27 3UP",
    "sg:province":"Somerset",
    "sg:tags":[
        "others"
    ],
    "wof:name":"E J Dudden",
    "wof:placetype":"venue"
},
  "geometry": {"coordinates":[-2.777659,51.279659],"type":"Point"}
}