{
  "type": "Feature",
  "properties": {
    "iso:country":"GB",
    "sg:address":"Gabriels Wharf, 56 Upper Ground",
    "sg:city":"London",
    "sg:classifiers":[
        {
            "category":"Personal",
            "subcategory":"Beauty Salon",
            "type":"Services"
        }
    ],
    "sg:phone":"+44 20 7928 4163",
    "sg:postcode":"SE1 9PP",
    "sg:province":"Greater London",
    "sg:tags":[
        "unisex",
        "hairdresser"
    ],
    "wof:name":"P C M Haircutters",
    "wof:placetype":"venue"
},
  "geometry": {"coordinates":[-0.11054,51.507118],"type":"Point"}
}