{
  "type": "Feature",
  "properties": {
    "iso:country":"GB",
    "sg:address":"Birch House, Fraser Road",
    "sg:city":"Erith",
    "sg:classifiers":[
        {
            "category":"Professional",
            "subcategory":"Engineering",
            "type":"Services"
        }
    ],
    "sg:phone":"+44 1322 440827",
    "sg:postcode":"DA8 1QX",
    "sg:province":"Kent",
    "sg:tags":[
        "precision",
        "engineer"
    ],
    "wof:name":"L & A Engineering",
    "wof:placetype":"venue"
},
  "geometry": {"coordinates":[0.166195,51.483097],"type":"Point"}
}