{
  "type": "Feature",
  "properties": {
    "addr:full":"73 Buchanan Road, Upper Arncott Bicester Oxfordshire OX25 1PE",
    "addr:housenumber":"73",
    "addr:postcode":"ox25 1pe",
    "addr:street":"Buchanan Road Upper Arncott",
    "iso:country":"GB",
    "sg:address":"73 Buchanan Road, Upper Arncott",
    "sg:city":"Bicester",
    "sg:classifiers":[
        {
            "category":"Personal",
            "type":"Services"
        },
        {
            "category":"Professional",
            "subcategory":"Business Services",
            "type":"Services"
        }
    ],
    "sg:phone":"+44 1869 245074",
    "sg:postcode":"OX25 1PE",
    "sg:province":"Oxfordshire",
    "sg:tags":[
        "delivery",
        "courier"
    ],
    "wof:name":"Arnolds Delivery Services",
    "wof:placetype":"venue"
},
  "geometry": {"coordinates":[-1.106516,51.852165],"type":"Point"}
}