{
  "type": "Feature",
  "properties": {
    "addr:full":"334 Aldridge Road, Streetly Sutton Coldfield Staffordshire B74 2DT",
    "addr:housenumber":"334",
    "addr:postcode":"b74 2dt",
    "addr:street":"Aldridge Road",
    "iso:country":"GB",
    "sg:address":"334 Aldridge Road, Streetly",
    "sg:city":"Sutton Coldfield",
    "sg:classifiers":[
        {
            "category":"Home & Garden",
            "subcategory":"Furniture",
            "type":"Retail Goods"
        }
    ],
    "sg:phone":"+44 121 352 1733",
    "sg:postcode":"B74 2DT",
    "sg:province":"Staffordshire",
    "sg:tags":[
        "outlet"
    ],
    "wof:name":"Streetly Furnishings Ltd",
    "wof:placetype":"venue"
},
  "geometry": {"coordinates":[-1.8900899887,52.568813324],"type":"Point"}
}