{
  "type": "Feature",
  "properties": {
    "addr:full":"220 St Georges Road Bolton Lancashire BL1 2PG",
    "addr:housenumber":"220",
    "addr:postcode":"bl1 2pg",
    "addr:street":"St Georges Road",
    "iso:country":"GB",
    "sg:address":"220 St Georges Road",
    "sg:city":"Bolton",
    "sg:classifiers":[
        {
            "category":"Banks & Credit Unions",
            "subcategory":"Financial Services",
            "type":"Services"
        }
    ],
    "sg:phone":"+44 1204 523760",
    "sg:postcode":"BL1 2PG",
    "sg:province":"Lancashire",
    "sg:tags":[
        "consultant"
    ],
    "wof:name":"P L Schofield Ltd.",
    "wof:placetype":"venue"
},
  "geometry": {"coordinates":[-2.4393460751,53.582359314],"type":"Point"}
}