{
  "type": "Feature",
  "properties": {
    "addr:full":"345 Linthorpe Road Middlesbrough North Yorkshire TS5 6AB",
    "addr:housenumber":"345",
    "addr:postcode":"ts5 6ab",
    "addr:street":"Linthorpe Road",
    "iso:country":"GB",
    "sg:address":"345 Linthorpe Road",
    "sg:city":"Middlesbrough",
    "sg:classifiers":[
        {
            "category":"Shopping",
            "subcategory":"News",
            "type":"Retail Goods"
        }
    ],
    "sg:phone":"+44 1642 851147",
    "sg:postcode":"TS5 6AB",
    "sg:province":"North Yorkshire",
    "sg:tags":[
        "newsagent"
    ],
    "wof:name":"Linthorpe Newsagents",
    "wof:placetype":"venue"
},
  "geometry": {"coordinates":[-1.241721034,54.5646209717],"type":"Point"}
}