{
  "type": "Feature",
  "properties": {
    "iso:country":"GB",
    "sg:address":"Archway Office, 307 City Road, Fenton",
    "sg:city":"Stoke-on-trent",
    "sg:classifiers":[
        {
            "category":"Professional",
            "subcategory":"Accounting & Tax Preparation",
            "type":"Services"
        }
    ],
    "sg:phone":"+44 1782 416036",
    "sg:postcode":"ST4 2QA",
    "sg:province":"Staffordshire",
    "sg:tags":[
        "accountant"
    ],
    "wof:name":"Bath & Co",
    "wof:placetype":"venue"
},
  "geometry": {"coordinates":[-2.16347,52.999439],"type":"Point"}
}