{
  "type": "Feature",
  "properties": {
    "addr:full":"31 Mansfield Road, Skegby Sutton-in-ashfield Nottinghamshire NG17 3ED",
    "addr:housenumber":"31",
    "addr:postcode":"ng17 3ed",
    "addr:street":"Mansfield Road",
    "iso:country":"GB",
    "sg:address":"31 Mansfield Road, Skegby",
    "sg:city":"Sutton-in-ashfield",
    "sg:classifiers":[
        {
            "category":"Health Services",
            "subcategory":"Doctor",
            "type":"Services"
        }
    ],
    "sg:phone":"+44 1623 440666",
    "sg:postcode":"NG17 3ED",
    "sg:province":"Nottinghamshire",
    "sg:tags":[
        "practitioners"
    ],
    "wof:name":"Hook Porter & Hook Drs",
    "wof:placetype":"venue"
},
  "geometry": {"coordinates":[-1.2699559927,53.1431541443],"type":"Point"}
}