{
  "type": "Feature",
  "properties": {
    "iso:country":"GB",
    "sg:address":"Greencroft",
    "sg:city":"Stanley",
    "sg:classifiers":[
        {
            "category":"Community Center",
            "type":"Public Place"
        }
    ],
    "sg:phone":"+44 1207 284981",
    "sg:postcode":"DH9 8PP",
    "sg:province":"Durham",
    "sg:tags":[
        "centre"
    ],
    "wof:name":"Annfield Plain & District Community Centre",
    "wof:placetype":"venue"
},
  "geometry": {"coordinates":[-1.74985,54.857719],"type":"Point"}
}