{
  "type": "Feature",
  "properties": {
    "addr:full":"11 Northolt Rd Harrow Greater London HA2 0LH",
    "addr:housenumber":"11",
    "addr:postcode":"ha2 0lh",
    "addr:street":"Northolt Rd",
    "iso:country":"GB",
    "sg:address":"11 Northolt Rd",
    "sg:city":"Harrow",
    "sg:classifiers":[
        {
            "category":"Food & Beverages",
            "subcategory":"Liquor & Beverages",
            "type":"Retail Goods"
        }
    ],
    "sg:phone":"+44 20 8422 0835",
    "sg:postcode":"HA2 0LH",
    "sg:province":"Greater London",
    "sg:tags":[
        "beer",
        "wine",
        "spirit",
        "wines"
    ],
    "wof:name":"Wine Seller",
    "wof:placetype":"venue"
},
  "geometry": {"coordinates":[-0.346919,51.569107],"type":"Point"}
}