{
  "type": "Feature",
  "properties": {
    "addr:full":"Cottage Farm, Abermule Montgomery Shropshire SY15 6JQ",
    "addr:postcode":"sy15 6jq",
    "iso:country":"GB",
    "sg:address":"Cottage Farm, Abermule",
    "sg:city":"Montgomery",
    "sg:classifiers":[
        {
            "category":"Farming",
            "subcategory":"Farm",
            "type":"Manufacturing & Wholesale Goods"
        }
    ],
    "sg:postcode":"SY15 6JQ",
    "sg:province":"Shropshire",
    "sg:tags":[
        "mixed",
        "crop"
    ],
    "wof:name":"E & P Jones & Son",
    "wof:placetype":"venue"
},
  "geometry": {"coordinates":[-3.146479,52.563564],"type":"Point"}
}