{
  "type": "Feature",
  "properties": {
    "iso:country":"GB",
    "sg:address":"40 New Bridge Street",
    "sg:city":"London",
    "sg:classifiers":[
        {
            "category":"Organizations",
            "subcategory":"Membership Organization",
            "type":"Services"
        }
    ],
    "sg:postcode":"EC4V 6BE",
    "sg:province":"Greater London",
    "sg:tags":[
        "club"
    ],
    "wof:name":"Royal 23 Crescent (Bath) Ltd.",
    "wof:placetype":"venue"
},
  "geometry": {"coordinates":[-0.1043590009,51.5137786865],"type":"Point"}
}