{
  "type": "Feature",
  "properties": {
    "addr:full":"5 Raymond Buildings Bloomsbury Greater London WC1R 5BP",
    "addr:housenumber":"5",
    "addr:postcode":"wc1r 5bp",
    "addr:street":"Raymond Buildings",
    "iso:country":"GB",
    "sg:address":"5 Raymond Buildings",
    "sg:city":"Bloomsbury",
    "sg:classifiers":[
        {
            "category":"Professional",
            "subcategory":"Lawyer & Legal Services",
            "type":"Services"
        }
    ],
    "sg:phone":"+44 20 7242 2902",
    "sg:postcode":"WC1R 5BP",
    "sg:province":"Greater London",
    "sg:tags":[
        "barrister"
    ],
    "wof:name":"Matthew Nicklin",
    "wof:placetype":"venue"
},
  "geometry": {"coordinates":[-0.1147840023,51.5199012756],"type":"Point"}
}