{
  "type": "Feature",
  "properties": {
    "iso:country":"GB",
    "sg:address":"11 Middle Way",
    "sg:city":"Oxford",
    "sg:classifiers":[
        {
            "category":"Organizations",
            "subcategory":"Non-profit Organization",
            "type":"Services"
        }
    ],
    "sg:phone":"+44 1865 556608",
    "sg:postcode":"OX2 7LH",
    "sg:province":"Oxfordshire",
    "sg:tags":[
        "organisation",
        "voluntary",
        "charity"
    ],
    "wof:name":"Womens Institutes",
    "wof:placetype":"venue"
},
  "geometry": {"coordinates":[-1.267649,51.778828],"type":"Point"}
}