{
  "type": "Feature",
  "properties": {
    "addr:full":"12 Grange Close, Linslade Leighton Buzzard Bedfordshire LU7 2PW",
    "addr:housenumber":"12",
    "addr:postcode":"lu7 2pw",
    "addr:street":"Grange Close",
    "iso:country":"GB",
    "sg:address":"12 Grange Close, Linslade",
    "sg:city":"Leighton Buzzard",
    "sg:classifiers":[
        {
            "category":"Manufacturing",
            "subcategory":"Petroleum Products",
            "type":"Manufacturing & Wholesale Goods"
        }
    ],
    "sg:phone":"+44 1525 376850",
    "sg:postcode":"LU7 2PW",
    "sg:province":"Bedfordshire",
    "sg:tags":[
        "double",
        "glazing"
    ],
    "wof:name":"Grange Windows",
    "wof:placetype":"venue"
},
  "geometry": {"coordinates":[-0.6800460219,51.9142456055],"type":"Point"}
}