{
  "type": "Feature",
  "properties": {
    "iso:country":"GB",
    "sg:address":"17 High Street",
    "sg:city":"Saxmundham",
    "sg:classifiers":[
        {
            "category":"Shopping",
            "subcategory":"Thrift Store",
            "type":"Retail Goods"
        }
    ],
    "sg:phone":"+44 1728 604100",
    "sg:postcode":"IP17 1DF",
    "sg:province":"Suffolk",
    "sg:tags":[
        "shop",
        "charity"
    ],
    "wof:name":"St Elizabeth Hospice",
    "wof:placetype":"venue"
},
  "geometry": {"coordinates":[1.492031,52.214439],"type":"Point"}
}