{
  "type": "Feature",
  "properties": {
    "iso:country":"GB",
    "sg:address":"Llanwrda Farm",
    "sg:city":"Llanwrda",
    "sg:classifiers":[
        {
            "category":"Farming",
            "subcategory":"Livestock Farm",
            "type":"Manufacturing & Wholesale Goods"
        }
    ],
    "sg:phone":"+44 1550 777383",
    "sg:postcode":"SA19 8AW",
    "sg:province":"Carmarthenshire",
    "sg:tags":[
        "others"
    ],
    "wof:name":"C R Powell",
    "wof:placetype":"venue"
},
  "geometry": {"coordinates":[-3.874174,51.96669],"type":"Point"}
}