{
  "type": "Feature",
  "properties": {
    "iso:country":"GB",
    "sg:address":"89 Banstead Road",
    "sg:city":"Carshalton",
    "sg:classifiers":[
        {
            "category":"Food & Beverages",
            "subcategory":"Fruits & Vegetables",
            "type":"Retail Goods"
        }
    ],
    "sg:phone":"+44 20 8642 3839",
    "sg:postcode":"SM5 3NP",
    "sg:province":"Surrey",
    "sg:tags":[
        "greengrocer"
    ],
    "wof:name":"Judd Fruiterers",
    "wof:placetype":"venue"
},
  "geometry": {"coordinates":[-0.173614,51.35677],"type":"Point"}
}