{
  "type": "Feature",
  "properties": {
    "addr:full":"101 Station Road Port Talbot Neath Port Talbot SA13 1NR",
    "addr:housenumber":"101",
    "addr:postcode":"sa13 1nr",
    "addr:street":"Station Road",
    "iso:country":"GB",
    "sg:address":"101 Station Road",
    "sg:city":"Port Talbot",
    "sg:classifiers":[
        {
            "category":"Shopping",
            "subcategory":"Thrift Store",
            "type":"Retail Goods"
        }
    ],
    "sg:phone":"+44 1639 892094",
    "sg:postcode":"SA13 1NR",
    "sg:province":"Neath Port Talbot",
    "sg:tags":[
        "shop",
        "charity"
    ],
    "wof:name":"People'S Dispensary For Sick Animals",
    "wof:placetype":"venue"
},
  "geometry": {"coordinates":[-3.7831130028,51.5955123901],"type":"Point"}
}