{
  "type": "Feature",
  "properties": {
    "iso:country":"GB",
    "sg:address":"Stubbing, Wingerworth",
    "sg:city":"Chesterfield",
    "sg:classifiers":[
        {
            "category":"Retail",
            "subcategory":"Auto Repair",
            "type":"Services"
        }
    ],
    "sg:phone":"+44 1246 590807",
    "sg:postcode":"S42 6QX",
    "sg:province":"Derbyshire",
    "sg:tags":[
        "body",
        "car"
    ],
    "wof:name":"Grayhart Ltd.",
    "wof:placetype":"venue"
},
  "geometry": {"coordinates":[-1.421591,53.205528],"type":"Point"}
}