{
  "type": "Feature",
  "properties": {
    "iso:country":"GB",
    "sg:address":"10 Withyside, Denby Dale",
    "sg:city":"Huddersfield",
    "sg:classifiers":[
        {
            "category":"Home & Garden",
            "subcategory":"Building Materials",
            "type":"Retail Goods"
        }
    ],
    "sg:phone":"+44 1484 865377",
    "sg:postcode":"HD8 8SF",
    "sg:province":"South Yorkshire",
    "sg:tags":[
        "fencing"
    ],
    "wof:name":"T W Wood & Sons",
    "wof:placetype":"venue"
},
  "geometry": {"coordinates":[-1.6497670412,53.5762825012],"type":"Point"}
}