{
  "type": "Feature",
  "properties": {
    "iso:country":"GB",
    "sg:address":"14 Main St, Thornton Curtis",
    "sg:city":"Ulceby",
    "sg:classifiers":[
        {
            "category":"Government",
            "subcategory":"Post Office",
            "type":"Public Place"
        }
    ],
    "sg:phone":"+44 1469 531212",
    "sg:postcode":"DN39 6XW",
    "sg:province":"Lincolnshire",
    "wof:name":"Thornton Curtis PO",
    "wof:placetype":"venue"
},
  "geometry": {"coordinates":[-0.355565995,53.6450576782],"type":"Point"}
}