{
  "type": "Feature",
  "properties": {
    "addr:full":"175-177 Sandown Road Shanklin Isle of Wight PO37 6HP",
    "addr:housenumber":"175-177",
    "addr:postcode":"po37 6hp",
    "addr:street":"Sandown Road",
    "iso:country":"GB",
    "sg:address":"175-177 Sandown Road",
    "sg:city":"Shanklin",
    "sg:classifiers":[
        {
            "category":"Retail",
            "subcategory":"Auto Repair",
            "type":"Services"
        }
    ],
    "sg:phone":"+44 1983 862204",
    "sg:postcode":"PO37 6HP",
    "sg:province":"Isle of Wight",
    "sg:tags":[
        "garage"
    ],
    "wof:name":"Shanklin Auto Express",
    "wof:placetype":"venue"
},
  "geometry": {"coordinates":[-1.1723790169,50.6382331848],"type":"Point"}
}