{
  "type": "Feature",
  "properties": {
    "addr:full":"20 Glasgow Road Edinburgh City of Edinburgh EH12 8HL",
    "addr:housenumber":"20",
    "addr:postcode":"eh12 8hl",
    "addr:street":"Glasgow Road",
    "iso:country":"GB",
    "sg:address":"20 Glasgow Road",
    "sg:city":"Edinburgh",
    "sg:classifiers":[
        {
            "category":"Fast Food",
            "type":"Food & Drink"
        }
    ],
    "sg:phone":"+44 131 316 4299",
    "sg:postcode":"EH12 8HL",
    "sg:province":"City of Edinburgh",
    "sg:tags":[
        "away",
        "take"
    ],
    "wof:name":"The Barbecue",
    "wof:placetype":"venue"
},
  "geometry": {"coordinates":[-3.294835,55.942661],"type":"Point"}
}