{
  "type": "Feature",
  "properties": {
    "addr:full":"37 London Road, Purbrook Waterlooville Hampshire PO7 5LF",
    "addr:housenumber":"37",
    "addr:postcode":"po7 5lf",
    "addr:street":"London Road",
    "iso:country":"GB",
    "sg:address":"37 London Road, Purbrook",
    "sg:city":"Waterlooville",
    "sg:classifiers":[
        {
            "category":"Building & Trades",
            "subcategory":"Plumbing",
            "type":"Services"
        },
        {
            "category":"Home & Garden",
            "subcategory":"Hardware",
            "type":"Retail Goods"
        }
    ],
    "sg:phone":"+44 23 9226 6662",
    "sg:postcode":"PO7 5LF",
    "sg:province":"Hampshire",
    "sg:tags":[
        "merchant",
        "plumber",
        "plumbers'"
    ],
    "wof:name":"Portsmouth Plumbing Supplies Ltd",
    "wof:placetype":"venue"
},
  "geometry": {"coordinates":[-1.044151,50.869053],"type":"Point"}
}