{
  "type": "Feature",
  "properties": {
    "addr:full":"74 Western Road Hove East Sussex BN3 2JQ",
    "addr:housenumber":"74",
    "addr:postcode":"bn3 2jq",
    "addr:street":"Western Road",
    "iso:country":"GB",
    "sg:address":"74 Western Road",
    "sg:city":"Hove",
    "sg:classifiers":[
        {
            "category":"Retail",
            "subcategory":"Laundry & Dry Cleaning",
            "type":"Services"
        }
    ],
    "sg:phone":"+44 1273 734893",
    "sg:postcode":"BN3 2JQ",
    "sg:province":"East Sussex",
    "sg:tags":[
        "home",
        "ironing"
    ],
    "wof:name":"The Ironing Shop",
    "wof:placetype":"venue"
},
  "geometry": {"coordinates":[-0.163943,50.826523],"type":"Point"}
}