{
  "type": "Feature",
  "properties": {
    "addr:full":"95 Ellesmere Street, Howley Warrington Cheshire WA1 2EJ",
    "addr:housenumber":"95",
    "addr:postcode":"wa1 2ej",
    "addr:street":"Ellesmere Street",
    "iso:country":"GB",
    "sg:address":"95 Ellesmere Street, Howley",
    "sg:city":"Warrington",
    "sg:classifiers":[
        {
            "category":"Retail",
            "subcategory":"Repair Shop",
            "type":"Services"
        }
    ],
    "sg:phone":"+44 1925 413145",
    "sg:postcode":"WA1 2EJ",
    "sg:province":"Cheshire",
    "sg:tags":[
        "upholsterer"
    ],
    "wof:name":"Geoff Gibson",
    "wof:placetype":"venue"
},
  "geometry": {"coordinates":[-2.583278,53.388954],"type":"Point"}
}