{
  "type": "Feature",
  "properties": {
    "addr:full":"3 Jevington Gardens Eastbourne East Sussex BN21 4HR",
    "addr:housenumber":"3",
    "addr:postcode":"bn21 4hr",
    "addr:street":"Jevington Gardens",
    "iso:country":"GB",
    "sg:address":"3 Jevington Gardens",
    "sg:city":"Eastbourne",
    "sg:classifiers":[
        {
            "category":"Travel",
            "subcategory":"Hotels & Motels",
            "type":"Entertainment"
        }
    ],
    "sg:phone":"+44 1323 410443",
    "sg:postcode":"BN21 4HR",
    "sg:province":"East Sussex",
    "wof:name":"Eastbourne Associated Hotels",
    "wof:placetype":"venue"
},
  "geometry": {"coordinates":[0.279817,50.761192],"type":"Point"}
}