{
  "type": "Feature",
  "properties": {
    "addr:full":"56a Kenmore Avenue Harrow Greater London HA3 8PL",
    "addr:housenumber":"56a",
    "addr:postcode":"ha3 8pl",
    "addr:street":"Kenmore Avenue",
    "iso:country":"GB",
    "sg:address":"56a Kenmore Avenue",
    "sg:city":"Harrow",
    "sg:classifiers":[
        {
            "category":"Communications",
            "type":"Services"
        }
    ],
    "sg:phone":"+44 20 8907 3455",
    "sg:postcode":"HA3 8PL",
    "sg:province":"Greater London",
    "sg:tags":[
        "telecommunication"
    ],
    "wof:name":"Netlink 2000 Ltd",
    "wof:placetype":"venue"
},
  "geometry": {"coordinates":[-0.320776,51.593021],"type":"Point"}
}