{
  "type": "Feature",
  "properties": {
    "iso:country":"GB",
    "sg:address":"37 The Millfields, Stonehouse",
    "sg:city":"Plymouth",
    "sg:classifiers":[
        {
            "category":"Professional",
            "subcategory":"Engineering",
            "type":"Services"
        }
    ],
    "sg:phone":"+44 1752 201135",
    "sg:postcode":"PL1 3JN",
    "sg:province":"Devon",
    "sg:tags":[
        "engineer",
        "structural"
    ],
    "wof:name":"Queste Structured Consulting Ltd.",
    "wof:placetype":"venue"
},
  "geometry": {"coordinates":[-4.1558728218,50.3674850464],"type":"Point"}
}