{
  "type": "Feature",
  "properties": {
    "addr:full":"54 Edinburgh Pl, Coronation Sq Cheltenham Gloucestershire GL51 7SA",
    "addr:housenumber":"54",
    "addr:postcode":"gl51 7sa",
    "addr:street":"Edinburgh Pl Coronation Sq",
    "iso:country":"GB",
    "sg:address":"54 Edinburgh Pl, Coronation Sq",
    "sg:city":"Cheltenham",
    "sg:classifiers":[
        {
            "category":"Shopping",
            "subcategory":"Department Store",
            "type":"Retail Goods"
        }
    ],
    "sg:postcode":"GL51 7SA",
    "sg:province":"Gloucestershire",
    "wof:name":"Emc Carpets",
    "wof:placetype":"venue"
},
  "geometry": {"coordinates":[-2.114829,51.90279],"type":"Point"}
}