{
  "type": "Feature",
  "properties": {
    "addr:full":"9 Moy Terrace Inverness Highland IV2 4EL",
    "addr:housenumber":"9",
    "addr:postcode":"iv2 4el",
    "addr:street":"Moy Terrace",
    "iso:country":"GB",
    "sg:address":"9 Moy Terrace",
    "sg:city":"Inverness",
    "sg:classifiers":[
        {
            "category":"Shopping",
            "subcategory":"Pharmacy",
            "type":"Retail Goods"
        }
    ],
    "sg:phone":"+44 1463 240789",
    "sg:postcode":"IV2 4EL",
    "sg:province":"Highland",
    "sg:tags":[
        "medicine",
        "therapy"
    ],
    "wof:name":"W McArthur",
    "wof:placetype":"venue"
},
  "geometry": {"coordinates":[-4.223752,57.457428],"type":"Point"}
}