{
  "type": "Feature",
  "properties": {
    "iso:country":"GB",
    "sg:address":"2 Fieldgate Close, Wootton Fields",
    "sg:city":"Northampton",
    "sg:classifiers":[
        {
            "category":"Shopping",
            "subcategory":"Stationery & Office Supplies",
            "type":"Retail Goods"
        }
    ],
    "sg:phone":"+44 7850 372177",
    "sg:postcode":"NN4 6EE",
    "sg:province":"Northamptonshire",
    "sg:tags":[
        "printers'"
    ],
    "wof:name":"Digital Print Ltd.",
    "wof:placetype":"venue"
},
  "geometry": {"coordinates":[-0.879581,52.201878],"type":"Point"}
}