{
  "type": "Feature",
  "properties": {
    "iso:country":"GB",
    "sg:address":"Lamb Inn Road, Racca Grn",
    "sg:city":"Knottingley",
    "sg:classifiers":[
        {
            "category":"Autos & Motor Vehicles",
            "subcategory":"Recreational Vehicle Sales",
            "type":"Retail Goods"
        }
    ],
    "sg:phone":"+44 1977 676028",
    "sg:postcode":"WF11 8AU",
    "sg:province":"North Yorkshire",
    "sg:tags":[
        "caravan"
    ],
    "wof:name":"Euro Motor Campers Ltd.",
    "wof:placetype":"venue"
},
  "geometry": {"coordinates":[-1.237904,53.707909],"type":"Point"}
}