{
  "type": "Feature",
  "properties": {
    "addr:full":"3 Gwel-an Nans, Probus Truro Cornwall TR2 4ND",
    "addr:housenumber":"3",
    "addr:postcode":"tr2 4nd",
    "addr:street":"Gwel-An Nans",
    "iso:country":"GB",
    "sg:address":"3 Gwel-an Nans, Probus",
    "sg:city":"Truro",
    "sg:classifiers":[
        {
            "category":"Professional",
            "subcategory":"Engineering",
            "type":"Services"
        }
    ],
    "sg:postcode":"TR2 4ND",
    "sg:province":"Cornwall",
    "sg:tags":[
        "contractor",
        "electrical",
        "engineer"
    ],
    "wof:name":"D G D Electrical Contractors",
    "wof:placetype":"venue"
},
  "geometry": {"coordinates":[-4.9554738998,50.2925796509],"type":"Point"}
}