{
  "type": "Feature",
  "properties": {
    "iso:country":"GB",
    "sg:address":"Unit 20 Forest Business Park, South Access Road",
    "sg:city":"London",
    "sg:classifiers":[
        {
            "category":"Manufacturing",
            "subcategory":"Metals",
            "type":"Manufacturing & Wholesale Goods"
        }
    ],
    "sg:postcode":"E17 8BA",
    "sg:province":"Greater London",
    "sg:tags":[
        "work",
        "sheet"
    ],
    "wof:name":"A Tatham & Sons Ltd.",
    "wof:placetype":"venue"
},
  "geometry": {"coordinates":[-0.04108,51.571899],"type":"Point"}
}