{
  "type": "Feature",
  "properties": {
    "addr:full":"39 Peel St Southampton Hampshire SO14 5QU",
    "addr:housenumber":"39",
    "addr:postcode":"so14 5qu",
    "addr:street":"Peel St",
    "iso:country":"GB",
    "sg:address":"39 Peel St",
    "sg:city":"Southampton",
    "sg:classifiers":[
        {
            "category":"Government",
            "subcategory":"Office",
            "type":"Public Place"
        }
    ],
    "sg:phone":"+44 23 8063 5522",
    "sg:postcode":"SO14 5QU",
    "sg:province":"Hampshire",
    "sg:tags":[
        "education",
        "agency",
        "authority"
    ],
    "wof:name":"The House By The School",
    "wof:placetype":"venue"
},
  "geometry": {"coordinates":[-1.388152,50.909184],"type":"Point"}
}