{
  "type": "Feature",
  "properties": {
    "addr:full":"396 Hillington Road Glasgow Glasgow City G52 4BL",
    "addr:housenumber":"396",
    "addr:postcode":"g52 4bl",
    "addr:street":"Hillington Road",
    "iso:country":"GB",
    "sg:address":"396 Hillington Road",
    "sg:city":"Glasgow",
    "sg:classifiers":[
        {
            "category":"Professional",
            "subcategory":"Engineering",
            "type":"Services"
        }
    ],
    "sg:phone":"+44 141 882 6211",
    "sg:postcode":"G52 4BL",
    "sg:province":"Glasgow City",
    "sg:tags":[
        "hydraulic",
        "engineer"
    ],
    "wof:name":"Eagle Engineering (U K) Ltd.",
    "wof:placetype":"venue"
},
  "geometry": {"coordinates":[-4.362123,55.857635],"type":"Point"}
}