{
  "type": "Feature",
  "properties": {
    "iso:country":"GB",
    "sg:address":"13 Victoria Street, Eastwood",
    "sg:city":"Nottingham",
    "sg:classifiers":[
        {
            "category":"Health Services",
            "subcategory":"Dentist",
            "type":"Services"
        }
    ],
    "sg:phone":"+44 1773 719993",
    "sg:postcode":"NG16 3AW",
    "sg:province":"Derbyshire",
    "wof:name":"John Whitbread",
    "wof:placetype":"venue"
},
  "geometry": {"coordinates":[-1.306793,53.018177],"type":"Point"}
}