{
  "type": "Feature",
  "properties": {
    "addr:full":"Plant Hill Road Manchester Greater Manchester M9 0WQ",
    "addr:postcode":"m9 0wq",
    "addr:street":"Plant Hill Road",
    "iso:country":"GB",
    "sg:address":"Plant Hill Road",
    "sg:city":"Manchester",
    "sg:classifiers":[
        {
            "category":"Education",
            "subcategory":"University",
            "type":"Public Place"
        }
    ],
    "sg:phone":"+44 161 795 6010",
    "sg:postcode":"M9 0WQ",
    "sg:province":"Greater Manchester",
    "sg:tags":[
        "adult"
    ],
    "wof:name":"Plant Hill Adult Education Centre",
    "wof:placetype":"venue"
},
  "geometry": {"coordinates":[-2.221164,53.533894],"type":"Point"}
}