{
  "type": "Feature",
  "properties": {
    "addr:full":"76 Polwarth Terrace Edinburgh City of Edinburgh EH11 1NJ",
    "addr:housenumber":"76",
    "addr:postcode":"eh11 1nj",
    "addr:street":"Polwarth Terrace",
    "iso:country":"GB",
    "sg:address":"76 Polwarth Terrace",
    "sg:city":"Edinburgh",
    "sg:classifiers":[
        {
            "category":"Professional",
            "subcategory":"Management & Consulting",
            "type":"Services"
        }
    ],
    "sg:phone":"+44 131 337 4759",
    "sg:postcode":"EH11 1NJ",
    "sg:province":"City of Edinburgh",
    "sg:tags":[
        "consultant",
        "business"
    ],
    "wof:name":"Scott Moffat Consulting International",
    "wof:placetype":"venue"
},
  "geometry": {"coordinates":[-3.216409,55.941124],"type":"Point"}
}