{
  "type": "Feature",
  "properties": {
    "addr:full":"217 High St Burntwood Staffordshire WS7 8XN",
    "addr:housenumber":"217",
    "addr:postcode":"ws7 8xn",
    "addr:street":"High St",
    "iso:country":"GB",
    "sg:address":"217 High St",
    "sg:city":"Burntwood",
    "sg:classifiers":[
        {
            "category":"Manufacturing",
            "subcategory":"Signs",
            "type":"Manufacturing & Wholesale Goods"
        }
    ],
    "sg:phone":"+44 1543 682924",
    "sg:postcode":"WS7 8XN",
    "sg:province":"Staffordshire",
    "sg:tags":[
        "nameplate"
    ],
    "wof:name":"Safety Consultant Services",
    "wof:placetype":"venue"
},
  "geometry": {"coordinates":[-1.933989,52.677792],"type":"Point"}
}