{
  "type": "Feature",
  "properties": {
    "addr:full":"12 Reddenhill Rd Torquay Devon TQ1 3RQ",
    "addr:housenumber":"12",
    "addr:postcode":"tq1 3rq",
    "addr:street":"Reddenhill Rd",
    "iso:country":"GB",
    "sg:address":"12 Reddenhill Rd",
    "sg:city":"Torquay",
    "sg:classifiers":[
        {
            "category":"Retail",
            "subcategory":"Event Space",
            "type":"Services"
        }
    ],
    "sg:phone":"+44 1803 409911",
    "sg:postcode":"TQ1 3RQ",
    "sg:province":"Devon",
    "sg:tags":[
        "exhibition",
        "organiser"
    ],
    "wof:name":"Invert Creations",
    "wof:placetype":"venue"
},
  "geometry": {"coordinates":[-3.519247,50.474087],"type":"Point"}
}