{
  "type": "Feature",
  "properties": {
    "iso:country":"GB",
    "sg:address":"West Midlands House, Gypsy Lane",
    "sg:city":"Willenhall",
    "sg:classifiers":[
        {
            "category":"Professional",
            "subcategory":"Printing & Photocopies",
            "type":"Services"
        }
    ],
    "sg:phone":"+44 121 609 7129",
    "sg:postcode":"WV13 2HA",
    "sg:province":"West Midlands",
    "sg:tags":[
        "computer",
        "tag",
        "label"
    ],
    "wof:name":"Infalabel Ltd.",
    "wof:placetype":"venue"
},
  "geometry": {"coordinates":[-2.047673,52.582958],"type":"Point"}
}