{
  "type": "Feature",
  "properties": {
    "iso:country":"GB",
    "sg:address":"35 Church La",
    "sg:city":"Bristol",
    "sg:classifiers":[
        {
            "category":"Health Services",
            "subcategory":"Nursing And Care Facility",
            "type":"Services"
        }
    ],
    "sg:phone":"+44 1275 464208",
    "sg:postcode":"BS48 3PH",
    "sg:province":"Somerset",
    "sg:tags":[
        "home"
    ],
    "wof:name":"Farleigh Combe Manor Nursing Home",
    "wof:placetype":"venue"
},
  "geometry": {"coordinates":[-2.724017,51.407501],"type":"Point"}
}