{
  "type": "Feature",
  "properties": {
    "iso:country":"GB",
    "sg:address":"99 Surpentine Road",
    "sg:city":"Kendal",
    "sg:classifiers":[
        {
            "category":"Shopping",
            "subcategory":"Gifts & Souvenirs",
            "type":"Retail Goods"
        }
    ],
    "sg:phone":"+44 1539 741122",
    "sg:postcode":"LA9 4PD",
    "sg:province":"Cumbria",
    "sg:tags":[
        "giftware"
    ],
    "wof:name":"Richard Lote Earth Sciences Ltd.",
    "wof:placetype":"venue"
},
  "geometry": {"coordinates":[-2.7519040108,54.3299102783],"type":"Point"}
}