{
  "type": "Feature",
  "properties": {
    "addr:full":"The Forge, Yarrow Valley Selkirk Scottish Borders TD7 5NE",
    "addr:postcode":"td7 5ne",
    "iso:country":"GB",
    "sg:address":"The Forge, Yarrow Valley",
    "sg:city":"Selkirk",
    "sg:classifiers":[
        {
            "category":"Professional",
            "subcategory":"Computer Services",
            "type":"Services"
        }
    ],
    "sg:phone":"+44 1750 20253",
    "sg:postcode":"TD7 5NE",
    "sg:province":"Scottish Borders",
    "sg:tags":[
        "system",
        "software"
    ],
    "wof:name":"Vouch Safe Ltd.",
    "wof:placetype":"venue"
},
  "geometry": {"coordinates":[-3.0181260109,55.5393981934],"type":"Point"}
}