{
  "type": "Feature",
  "properties": {
    "addr:full":"32 Parsons Street Banbury Oxfordshire OX16 5LY",
    "addr:housenumber":"32",
    "addr:postcode":"ox16 5ly",
    "addr:street":"Parsons Street",
    "iso:country":"GB",
    "sg:address":"32 Parsons Street",
    "sg:city":"Banbury",
    "sg:classifiers":[
        {
            "category":"Shopping",
            "subcategory":"News",
            "type":"Retail Goods"
        }
    ],
    "sg:phone":"+44 1295 262271",
    "sg:postcode":"OX16 5LY",
    "sg:province":"Oxfordshire",
    "sg:tags":[
        "newsagent"
    ],
    "wof:name":"Dillons Newsagents Ltd.",
    "wof:placetype":"venue"
},
  "geometry": {"coordinates":[-1.3393609524,52.0620727539],"type":"Point"}
}