{
  "type": "Feature",
  "properties": {
    "addr:full":"17a Coast Road Newcastle-upon-tyne Tyne and Wear NE7 7RN",
    "addr:housenumber":"17a",
    "addr:postcode":"ne7 7rn",
    "addr:street":"Coast Road",
    "iso:country":"GB",
    "sg:address":"17a Coast Road",
    "sg:city":"Newcastle-upon-tyne",
    "sg:classifiers":[
        {
            "category":"Shopping",
            "subcategory":"Bicycles & Sporting Goods",
            "type":"Retail Goods"
        }
    ],
    "sg:phone":"+44 191 266 6626",
    "sg:postcode":"NE7 7RN",
    "sg:province":"Tyne and Wear",
    "sg:tags":[
        "equipment",
        "leisure"
    ],
    "wof:name":"Aquanorth Vocational Training Ltd.",
    "wof:placetype":"venue"
},
  "geometry": {"coordinates":[-1.5786639452,54.9932098389],"type":"Point"}
}