{
  "type": "Feature",
  "properties": {
    "addr:full":"Stamford Hill Stoke Newington Greater London N16 5TU",
    "addr:postcode":"n16 5tu",
    "addr:street":"Stamford Hill",
    "iso:country":"GB",
    "sg:address":"Stamford Hill",
    "sg:city":"Stoke Newington",
    "sg:classifiers":[
        {
            "category":"Landmark",
            "subcategory":"Tourist Attraction",
            "type":"Public Place"
        }
    ],
    "sg:phone":"+44 20 7275 7557",
    "sg:postcode":"N16 5TU",
    "sg:province":"Greater London",
    "sg:tags":[
        "interest"
    ],
    "wof:name":"Abney Park Cemetery Trust",
    "wof:placetype":"venue"
},
  "geometry": {"coordinates":[-0.0728290007,51.5708503723],"type":"Point"}
}