{
  "type": "Feature",
  "properties": {
    "addr:full":"Brook Lodge, Church Road, Rawreth Wickford Essex SS11 8SG",
    "addr:postcode":"ss11 8sg",
    "addr:street":"Church Road",
    "iso:country":"GB",
    "sg:address":"Brook Lodge, Church Road, Rawreth",
    "sg:city":"Wickford",
    "sg:classifiers":[
        {
            "category":"Professional",
            "subcategory":"Engineering",
            "type":"Services"
        }
    ],
    "sg:phone":"+44 1268 733652",
    "sg:postcode":"SS11 8SG",
    "sg:province":"Essex",
    "sg:tags":[
        "design",
        "engineer"
    ],
    "wof:name":"Toolex Designs",
    "wof:placetype":"venue"
},
  "geometry": {"coordinates":[0.574755,51.611469],"type":"Point"}
}