{
  "type": "Feature",
  "properties": {
    "addr:full":"1-3 & 9 Farrington Street Chorley Lancashire PR7 1DY",
    "addr:housenumber":"1-3 & 9",
    "addr:postcode":"pr7 1dy",
    "addr:street":"Farrington Street",
    "iso:country":"GB",
    "sg:address":"1-3 & 9 Farrington Street",
    "sg:city":"Chorley",
    "sg:classifiers":[
        {
            "category":"Professional",
            "subcategory":"Lawyer & Legal Services",
            "type":"Services"
        }
    ],
    "sg:phone":"+44 1257 260600",
    "sg:postcode":"PR7 1DY",
    "sg:province":"Lancashire",
    "sg:tags":[
        "solicitor"
    ],
    "wof:name":"Forbes Solicitors",
    "wof:placetype":"venue"
},
  "geometry": {"coordinates":[-2.6339840889,53.6545219421],"type":"Point"}
}