{
  "type": "Feature",
  "properties": {
    "iso:country":"GB",
    "sg:address":"340 Hook Rise North",
    "sg:city":"Surbiton",
    "sg:classifiers":[
        {
            "category":"Fast Food",
            "type":"Food & Drink"
        }
    ],
    "sg:phone":"+44 20 8391 5911",
    "sg:postcode":"KT6 7LN",
    "sg:province":"Surrey",
    "sg:tags":[
        "away",
        "meal",
        "outlet",
        "take"
    ],
    "wof:name":"Khasturi Indian Takeaway",
    "wof:placetype":"venue"
},
  "geometry": {"coordinates":[-0.298554,51.374428],"type":"Point"}
}