{
  "type": "Feature",
  "properties": {
    "addr:full":"5 Turnpike Parade, Green Lanes London Greater London N15 3EA",
    "addr:housenumber":"5",
    "addr:postcode":"n15 3ea",
    "addr:street":"Turnpike Parade Green Lanes",
    "iso:country":"GB",
    "sg:address":"5 Turnpike Parade, Green Lanes",
    "sg:city":"London",
    "sg:classifiers":[
        {
            "category":"Professional",
            "subcategory":"Art Services",
            "type":"Services"
        }
    ],
    "sg:postcode":"N15 3EA",
    "sg:province":"Greater London",
    "sg:tags":[
        "photographer"
    ],
    "wof:name":"Diamond Photos",
    "wof:placetype":"venue"
},
  "geometry": {"coordinates":[-0.1009299979,51.5864906311],"type":"Point"}
}