{
  "type": "Feature",
  "properties": {
    "iso:country":"GB",
    "sg:address":"The Graiseley Centre, Pool Street",
    "sg:city":"Wolverhampton",
    "sg:classifiers":[
        {
            "category":"Government",
            "subcategory":"Office",
            "type":"Public Place"
        }
    ],
    "sg:phone":"+44 1902 714646",
    "sg:postcode":"WV2 4NE",
    "sg:province":"West Midlands",
    "sg:tags":[
        "local",
        "agency",
        "education",
        "authority"
    ],
    "wof:name":"W M E S T C",
    "wof:placetype":"venue"
},
  "geometry": {"coordinates":[-2.132600069,52.5761184692],"type":"Point"}
}