{
  "type": "Feature",
  "properties": {
    "addr:full":"12 Gilbert Place, Burscough Industrial Estate Ormskirk Lancashire L40 8JU",
    "addr:housenumber":"12",
    "addr:postcode":"l40 8ju",
    "addr:street":"Gilbert Place;Industrial",
    "iso:country":"GB",
    "sg:address":"12 Gilbert Place, Burscough Industrial Estate",
    "sg:city":"Ormskirk",
    "sg:classifiers":[
        {
            "category":"Wholesale",
            "subcategory":"Motor Vehicles",
            "type":"Manufacturing & Wholesale Goods"
        }
    ],
    "sg:phone":"+44 1704 893354",
    "sg:postcode":"L40 8JU",
    "sg:province":"Lancashire",
    "sg:tags":[
        "turbine"
    ],
    "wof:name":"Diesel Injection Repair Laytham",
    "wof:placetype":"venue"
},
  "geometry": {"coordinates":[-2.8660390377,53.6005859375],"type":"Point"}
}