{
  "type": "Feature",
  "properties": {
    "addr:full":"89 Above Bar Street Southampton Hampshire SO14 7FF",
    "addr:housenumber":"89",
    "addr:postcode":"so14 7ff",
    "addr:street":"Above Bar Street",
    "iso:country":"GB",
    "sg:address":"89 Above Bar Street",
    "sg:city":"Southampton",
    "sg:classifiers":[
        {
            "category":"Shopping",
            "subcategory":"Clothing, Apparel, & Fashions",
            "type":"Retail Goods"
        }
    ],
    "sg:phone":"+44 23 8063 5512",
    "sg:postcode":"SO14 7FF",
    "sg:province":"Hampshire",
    "sg:tags":[
        "shop"
    ],
    "wof:name":"Monsoon Accessorize Ltd.",
    "wof:placetype":"venue"
},
  "geometry": {"coordinates":[-1.4046759605,50.905872345],"type":"Point"}
}