{
  "type": "Feature",
  "properties": {
    "addr:full":"14 Bellevue Rd Southampton Hampshire SO15 2AY",
    "addr:housenumber":"14",
    "addr:postcode":"so15 2ay",
    "addr:street":"Bellevue Rd",
    "iso:country":"GB",
    "sg:address":"14 Bellevue Rd",
    "sg:city":"Southampton",
    "sg:classifiers":[
        {
            "category":"Education",
            "subcategory":"Music School",
            "type":"Public Place"
        },
        {
            "category":"Manufacturing",
            "subcategory":"Petroleum Products",
            "type":"Manufacturing & Wholesale Goods"
        }
    ],
    "sg:postcode":"SO15 2AY",
    "sg:province":"Hampshire",
    "sg:tags":[
        "conservatory",
        "glazing",
        "double"
    ],
    "wof:name":"Pay-Less Windows & Conservatories Ltd",
    "wof:placetype":"venue"
},
  "geometry": {"coordinates":[-1.4021110535,50.9123573303],"type":"Point"}
}