{
  "type": "Feature",
  "properties": {
    "addr:full":"192 West End Lane London Greater London NW6 1SG",
    "addr:housenumber":"192",
    "addr:postcode":"nw6 1sg",
    "addr:street":"West End Lane",
    "iso:country":"GB",
    "sg:address":"192 West End Lane",
    "sg:city":"London",
    "sg:classifiers":[
        {
            "category":"Real Estate",
            "subcategory":"Real Estate Agent",
            "type":"Services"
        }
    ],
    "sg:postcode":"NW6 1SG",
    "sg:province":"Greater London",
    "wof:name":"Massey Souray & Co",
    "wof:placetype":"venue"
},
  "geometry": {"coordinates":[-0.191282,51.549706],"type":"Point"}
}