{
  "type": "Feature",
  "properties": {
    "addr:full":"5 Tan-y-bryn Drive, Rhos On Sea Colwyn Bay Conwy LL28 4TY",
    "addr:housenumber":"5",
    "addr:postcode":"ll28 4ty",
    "addr:street":"Tan-Y-Bryn Drive",
    "iso:country":"GB",
    "sg:address":"5 Tan-y-bryn Drive, Rhos On Sea",
    "sg:city":"Colwyn Bay",
    "sg:classifiers":[
        {
            "category":"Professional",
            "subcategory":"Detective & Security Services",
            "type":"Services"
        }
    ],
    "sg:phone":"+44 1492 544666",
    "sg:postcode":"LL28 4TY",
    "sg:province":"Conwy",
    "wof:name":"Alarms Direct",
    "wof:placetype":"venue"
},
  "geometry": {"coordinates":[-3.7516789436,53.3080291748],"type":"Point"}
}