{
  "type": "Feature",
  "properties": {
    "iso:country":"GB",
    "sg:address":"Unit 22 Hackford Walk, 119-123 Hackford Road",
    "sg:city":"London",
    "sg:classifiers":[
        {
            "category":"Professional",
            "type":"Services"
        }
    ],
    "sg:phone":"+44 20 7793 1877",
    "sg:postcode":"SW9 0QT",
    "sg:province":"Greater London",
    "sg:tags":[
        "caterer"
    ],
    "wof:name":"Food Show Ltd.",
    "wof:placetype":"venue"
},
  "geometry": {"coordinates":[-0.11539,51.47374],"type":"Point"}
}