{
  "type": "Feature",
  "properties": {
    "addr:full":"13a Melville Street Edinburgh City of Edinburgh EH3 7PE",
    "addr:housenumber":"13a",
    "addr:postcode":"eh3 7pe",
    "addr:street":"Melville Street",
    "iso:country":"GB",
    "sg:address":"13a Melville Street",
    "sg:city":"Edinburgh",
    "sg:classifiers":[
        {
            "category":"Professional",
            "subcategory":"Management & Consulting",
            "type":"Services"
        }
    ],
    "sg:phone":"+44 131 220 3900",
    "sg:postcode":"EH3 7PE",
    "sg:province":"City of Edinburgh",
    "sg:tags":[
        "consultant",
        "business"
    ],
    "wof:name":"Ritchie & Co",
    "wof:placetype":"venue"
},
  "geometry": {"coordinates":[-3.211732,55.95092],"type":"Point"}
}