{
  "type": "Feature",
  "properties": {
    "addr:full":"1 Caudwell Close, Stoke Holy Cross Norwich Norfolk NR14 8NB",
    "addr:housenumber":"1",
    "addr:postcode":"nr14 8nb",
    "addr:street":"Caudwell Close",
    "iso:country":"GB",
    "sg:address":"1 Caudwell Close, Stoke Holy Cross",
    "sg:city":"Norwich",
    "sg:classifiers":[
        {
            "category":"Transit Center",
            "subcategory":"Freight",
            "type":"Transportation"
        }
    ],
    "sg:phone":"+44 1508 493185",
    "sg:postcode":"NR14 8NB",
    "sg:province":"Norfolk",
    "sg:tags":[
        "piano",
        "accessory"
    ],
    "wof:name":"L Bingham",
    "wof:placetype":"venue"
},
  "geometry": {"coordinates":[1.2977679968,52.5682601929],"type":"Point"}
}