{
  "type": "Feature",
  "properties": {
    "iso:country":"GB",
    "sg:address":"3 Court Road",
    "sg:city":"Bridgend",
    "sg:classifiers":[
        {
            "category":"Professional",
            "subcategory":"Lawyer & Legal Services",
            "type":"Services"
        }
    ],
    "sg:phone":"+44 1656 645921",
    "sg:postcode":"CF31 1BL",
    "sg:province":"Bridgend",
    "sg:tags":[
        "solicitor"
    ],
    "wof:name":"David Prosser & Co. Solicitors",
    "wof:placetype":"venue"
},
  "geometry": {"coordinates":[-3.5764329433,51.5062446594],"type":"Point"}
}