{
  "type": "Feature",
  "properties": {
    "addr:full":"65 The Village, Bebington Wirral Merseyside CH63 7PL",
    "addr:housenumber":"65",
    "addr:postcode":"ch63 7pl",
    "addr:street":"The Village",
    "iso:country":"GB",
    "sg:address":"65 The Village, Bebington",
    "sg:city":"Wirral",
    "sg:classifiers":[
        {
            "category":"Organizations",
            "subcategory":"Non-profit Organization",
            "type":"Services"
        }
    ],
    "sg:phone":"+44 151 644 1536",
    "sg:postcode":"CH63 7PL",
    "sg:province":"Merseyside",
    "sg:tags":[
        "organisation",
        "voluntary",
        "charity"
    ],
    "wof:name":"Village Care Services",
    "wof:placetype":"venue"
},
  "geometry": {"coordinates":[-3.005109,53.35207],"type":"Point"}
}