{
  "type": "Feature",
  "properties": {
    "iso:country":"GB",
    "sg:address":"12 William Clowes Street",
    "sg:city":"Stoke-on-trent",
    "sg:classifiers":[
        {
            "category":"Cafe",
            "type":"Food & Drink"
        }
    ],
    "sg:phone":"+44 1782 832336",
    "sg:postcode":"ST6 3AP",
    "sg:province":"Staffordshire",
    "sg:tags":[
        "tea",
        "room"
    ],
    "wof:name":"Sunshine Cafe",
    "wof:placetype":"venue"
},
  "geometry": {"coordinates":[-2.1983439922,53.0441169739],"type":"Point"}
}