{
  "type": "Feature",
  "properties": {
    "iso:country":"GB",
    "sg:address":"Old Farm, Dents Lane, Hartpury",
    "sg:city":"Gloucester",
    "sg:classifiers":[
        {
            "category":"Building & Trades",
            "subcategory":"Construction",
            "type":"Services"
        }
    ],
    "sg:postcode":"GL19 3BB",
    "sg:province":"Gloucestershire",
    "sg:tags":[
        "builder"
    ],
    "wof:name":"Paul Underwood Building Services",
    "wof:placetype":"venue"
},
  "geometry": {"coordinates":[-2.2933990955,51.9247932434],"type":"Point"}
}