{
  "type": "Feature",
  "properties": {
    "addr:full":"Swettenham Lane, Somerford Booths Congleton Cheshire CW12 2JX",
    "addr:postcode":"cw12 2jx",
    "addr:street":"Swettenham Lane",
    "iso:country":"GB",
    "sg:address":"Swettenham Lane, Somerford Booths",
    "sg:city":"Congleton",
    "sg:classifiers":[
        {
            "category":"Farming",
            "subcategory":"Dairy Farm",
            "type":"Manufacturing & Wholesale Goods"
        },
        {
            "category":"Farming",
            "subcategory":"Livestock Farm",
            "type":"Manufacturing & Wholesale Goods"
        }
    ],
    "sg:phone":"+44 1260 224264",
    "sg:postcode":"CW12 2JX",
    "sg:province":"Cheshire",
    "sg:tags":[
        "others",
        "farmer"
    ],
    "wof:name":"G & E Radley & Sons",
    "wof:placetype":"venue"
},
  "geometry": {"coordinates":[-2.2991280556,53.2019577026],"type":"Point"}
}