{
  "type": "Feature",
  "properties": {
    "addr:full":"1 Derwent Road, Farnworth Bolton Lancashire BL4 0QE",
    "addr:housenumber":"1",
    "addr:postcode":"bl4 0qe",
    "addr:street":"Derwent Road",
    "iso:country":"GB",
    "sg:address":"1 Derwent Road, Farnworth",
    "sg:city":"Bolton",
    "sg:classifiers":[
        {
            "category":"Professional",
            "subcategory":"Business Services",
            "type":"Services"
        }
    ],
    "sg:phone":"+44 1204 572731",
    "sg:postcode":"BL4 0QE",
    "sg:province":"Lancashire",
    "sg:tags":[
        "bookmaker"
    ],
    "wof:name":"Mick Dines (Bookmakers)",
    "wof:placetype":"venue"
},
  "geometry": {"coordinates":[-2.4287080765,53.5467567444],"type":"Point"}
}