{
  "type": "Feature",
  "properties": {
    "addr:full":"21 Leyden St Whitechapel Greater London E1 7LE",
    "addr:housenumber":"21",
    "addr:postcode":"e1 7le",
    "addr:street":"Leyden St",
    "iso:country":"GB",
    "sg:address":"21 Leyden St",
    "sg:city":"Whitechapel",
    "sg:classifiers":[
        {
            "category":"Manufacturing",
            "subcategory":"Textiles",
            "type":"Manufacturing & Wholesale Goods"
        }
    ],
    "sg:phone":"+44 20 7377 0996",
    "sg:postcode":"E1 7LE",
    "sg:province":"Greater London",
    "sg:tags":[
        "merchant",
        "agent"
    ],
    "wof:name":"Benny Textile Stores",
    "wof:placetype":"venue"
},
  "geometry": {"coordinates":[-0.0763019994,51.5170936584],"type":"Point"}
}