{
  "type": "Feature",
  "properties": {
    "addr:full":"2 Paradise Road Richmond Greater London TW9 1SE",
    "addr:housenumber":"2",
    "addr:postcode":"tw9 1se",
    "addr:street":"Paradise Road",
    "iso:country":"GB",
    "sg:address":"2 Paradise Road",
    "sg:city":"Richmond",
    "sg:classifiers":[
        {
            "category":"Banks & Credit Unions",
            "subcategory":"Investment Brokerage",
            "type":"Services"
        }
    ],
    "sg:phone":"+44 20 7461 4406",
    "sg:postcode":"TW9 1SE",
    "sg:province":"Greater London",
    "sg:tags":[
        "stockbroker"
    ],
    "wof:name":"Killik & Co.",
    "wof:placetype":"venue"
},
  "geometry": {"coordinates":[-0.302322,51.460167],"type":"Point"}
}