{
  "type": "Feature",
  "properties": {
    "addr:full":"Unit 15 Aberdare Business Pk, Robertstown Aberdare Neath Port Talbot CF44 8ER",
    "addr:housenumber":"unit 15",
    "addr:postcode":"cf44 8er",
    "addr:street":"Aberdare Business Pk Robertstown Aberdare",
    "iso:country":"GB",
    "sg:address":"Unit 15 Aberdare Business Pk, Robertstown",
    "sg:city":"Aberdare",
    "sg:classifiers":[
        {
            "category":"Home & Garden",
            "subcategory":"Home Furnishings",
            "type":"Retail Goods"
        }
    ],
    "sg:postcode":"CF44 8ER",
    "sg:province":"Neath Port Talbot",
    "sg:tags":[
        "homefurnishings"
    ],
    "wof:name":"Swish Timber Products Ltd",
    "wof:placetype":"venue"
},
  "geometry": {"coordinates":[-3.449409,51.721165],"type":"Point"}
}