{
  "type": "Feature",
  "properties": {
    "iso:country":"GB",
    "sg:address":"79 High St",
    "sg:city":"Rotherham",
    "sg:classifiers":[
        {
            "category":"Government",
            "subcategory":"Office",
            "type":"Public Place"
        }
    ],
    "sg:phone":"+44 1709 875665",
    "sg:postcode":"S63 7QB",
    "sg:province":"South Yorkshire",
    "sg:tags":[
        "mp",
        "meps"
    ],
    "wof:name":"Linda McAuan MEP",
    "wof:placetype":"venue"
},
  "geometry": {"coordinates":[-1.342423,53.502937],"type":"Point"}
}