{
  "type": "Feature",
  "properties": {
    "addr:full":"Hikers Way Drakes Dr, Long Crendon Aylesbury Buckinghamshire HP18 9RW",
    "addr:postcode":"hp18 9rw",
    "addr:street":"Hikers Way Drakes Dr",
    "iso:country":"GB",
    "sg:address":"Hikers Way Drakes Dr, Long Crendon",
    "sg:city":"Aylesbury",
    "sg:classifiers":[
        {
            "category":"Retail",
            "subcategory":"Auto Repair",
            "type":"Services"
        }
    ],
    "sg:postcode":"HP18 9RW",
    "sg:province":"Buckinghamshire",
    "sg:tags":[
        "bodybuilder",
        "repairer"
    ],
    "wof:name":"Hayesmoor Management Ltd",
    "wof:placetype":"venue"
},
  "geometry": {"coordinates":[-0.9795600176,51.7649879456],"type":"Point"}
}