{
  "type": "Feature",
  "properties": {
    "addr:full":"Woodsend Road South, Urmston Manchester Cheshire M41 6QB",
    "addr:postcode":"m41 6qb",
    "addr:street":"Woodsend Road South",
    "iso:country":"GB",
    "sg:address":"Woodsend Road South, Urmston",
    "sg:city":"Manchester",
    "sg:classifiers":[
        {
            "category":"Place Of Worship",
            "type":"Public Place"
        },
        {
            "category":"Education",
            "subcategory":"School",
            "type":"Public Place"
        }
    ],
    "sg:phone":"+44 161 748 3353",
    "sg:postcode":"M41 6QB",
    "sg:province":"Cheshire",
    "sg:tags":[
        "local",
        "authority"
    ],
    "wof:name":"St Monica's R C Primary School",
    "wof:placetype":"venue"
},
  "geometry": {"coordinates":[-2.3914289474,53.4482688904],"type":"Point"}
}