{
  "type": "Feature",
  "properties": {
    "addr:full":"47 Coniston Avenue Upminster Essex RM14 3XL",
    "addr:housenumber":"47",
    "addr:postcode":"rm14 3xl",
    "addr:street":"Coniston Avenue",
    "iso:country":"GB",
    "sg:address":"47 Coniston Avenue",
    "sg:city":"Upminster",
    "sg:classifiers":[
        {
            "category":"Home & Garden",
            "subcategory":"Carpets & Floor Coverings",
            "type":"Retail Goods"
        }
    ],
    "sg:phone":"+44 1708 222296",
    "sg:postcode":"RM14 3XL",
    "sg:province":"Essex",
    "sg:tags":[
        "cleaner",
        "upholstery"
    ],
    "wof:name":"Charles A Clarke",
    "wof:placetype":"venue"
},
  "geometry": {"coordinates":[0.253435,51.549133],"type":"Point"}
}