{
  "type": "Feature",
  "properties": {
    "iso:country":"GB",
    "sg:address":"Drummond Rd, Aston Fields Indstl Est",
    "sg:city":"Stafford",
    "sg:classifiers":[
        {
            "category":"Retail",
            "subcategory":"Auto Repair",
            "type":"Services"
        }
    ],
    "sg:postcode":"ST16 3DE",
    "sg:province":"Staffordshire",
    "sg:tags":[
        "modification",
        "garage"
    ],
    "wof:name":"Taylor,Geoff,",
    "wof:placetype":"venue"
},
  "geometry": {"coordinates":[-2.1142230034,52.8214836121],"type":"Point"}
}