{
  "type": "Feature",
  "properties": {
    "iso:country":"GB",
    "sg:address":"Kojac House, 39-43 Park Royal Road",
    "sg:city":"London",
    "sg:classifiers":[
        {
            "category":"Building & Trades",
            "subcategory":"Equipment Rental",
            "type":"Services"
        }
    ],
    "sg:phone":"+44 20 8961 2323",
    "sg:postcode":"NW10 7LQ",
    "sg:province":"Greater London",
    "sg:tags":[
        "supply"
    ],
    "wof:name":"Freebuck Ltd.",
    "wof:placetype":"venue"
},
  "geometry": {"coordinates":[-0.267875,51.527988],"type":"Point"}
}