{
  "type": "Feature",
  "properties": {
    "addr:full":"5 Rolle Street Exmouth Devon EX8 1HL",
    "addr:housenumber":"5",
    "addr:postcode":"ex8 1hl",
    "addr:street":"Rolle Street",
    "iso:country":"GB",
    "sg:address":"5 Rolle Street",
    "sg:city":"Exmouth",
    "sg:classifiers":[
        {
            "category":"Shopping",
            "subcategory":"Clothing, Apparel, & Fashions",
            "type":"Retail Goods"
        },
        {
            "category":"Shopping",
            "subcategory":"Gifts & Souvenirs",
            "type":"Retail Goods"
        }
    ],
    "sg:phone":"+44 1395 274769",
    "sg:postcode":"EX8 1HL",
    "sg:province":"Devon",
    "sg:tags":[
        "shop",
        "dress",
        "outlet",
        "fancy"
    ],
    "wof:name":"Aladdins Cave",
    "wof:placetype":"venue"
},
  "geometry": {"coordinates":[-3.413631916,50.6199455261],"type":"Point"}
}