{
  "type": "Feature",
  "properties": {
    "iso:country":"GB",
    "sg:address":"38 Rumbridge Street, Totton",
    "sg:city":"Southampton",
    "sg:classifiers":[
        {
            "category":"Professional",
            "subcategory":"Accounting & Tax Preparation",
            "type":"Services"
        }
    ],
    "sg:phone":"+44 23 8066 6699",
    "sg:postcode":"SO40 9DS",
    "sg:province":"Hampshire",
    "sg:tags":[
        "accountant"
    ],
    "wof:name":"R A Jones & Co.",
    "wof:placetype":"venue"
},
  "geometry": {"coordinates":[-1.486961,50.915257],"type":"Point"}
}