{
  "type": "Feature",
  "properties": {
    "addr:full":"7 Melfort Road Thornton Heath Surrey CR7 7RS",
    "addr:housenumber":"7",
    "addr:postcode":"cr7 7rs",
    "addr:street":"Melfort Road",
    "iso:country":"GB",
    "sg:address":"7 Melfort Road",
    "sg:city":"Thornton Heath",
    "sg:classifiers":[
        {
            "category":"Food & Beverages",
            "subcategory":"Meat & Fish",
            "type":"Retail Goods"
        }
    ],
    "sg:postcode":"CR7 7RS",
    "sg:province":"Surrey",
    "sg:tags":[
        "chip"
    ],
    "wof:name":"Houli,G,",
    "wof:placetype":"venue"
},
  "geometry": {"coordinates":[-0.1019600034,51.398349762],"type":"Point"}
}