{
  "type": "Feature",
  "properties": {
    "addr:full":"28 Lumley Close Washington Durham NE38 0HX",
    "addr:housenumber":"28",
    "addr:postcode":"ne38 0hx",
    "addr:street":"Lumley Close",
    "iso:country":"GB",
    "sg:address":"28 Lumley Close",
    "sg:city":"Washington",
    "sg:classifiers":[
        {
            "category":"Farming",
            "subcategory":"Farm",
            "type":"Manufacturing & Wholesale Goods"
        }
    ],
    "sg:phone":"+44 191 416 5845",
    "sg:postcode":"NE38 0HX",
    "sg:province":"Durham",
    "sg:tags":[
        "agricultural"
    ],
    "wof:name":"John H Ogilvie",
    "wof:placetype":"venue"
},
  "geometry": {"coordinates":[-1.540759,54.899387],"type":"Point"}
}