{
  "type": "Feature",
  "properties": {
    "addr:full":"39 High Street Carshalton Surrey SM1 3BB",
    "addr:housenumber":"39",
    "addr:postcode":"sm1 3bb",
    "addr:street":"High Street",
    "iso:country":"GB",
    "sg:address":"39 High Street",
    "sg:city":"Carshalton",
    "sg:classifiers":[
        {
            "category":"Professional",
            "subcategory":"Art Services",
            "type":"Services"
        }
    ],
    "sg:phone":"+44 20 8770 4956",
    "sg:postcode":"SM1 3BB",
    "sg:province":"Surrey",
    "sg:tags":[
        "consultant",
        "design"
    ],
    "wof:name":"Big Hand Studios",
    "wof:placetype":"venue"
},
  "geometry": {"coordinates":[-0.1594620049,51.3657798767],"type":"Point"}
}