{
  "type": "Feature",
  "properties": {
    "iso:country":"GB",
    "sg:address":"High Fell Farm, Hallbankgate",
    "sg:city":"Brampton",
    "sg:classifiers":[
        {
            "category":"Farming",
            "subcategory":"Livestock Farm",
            "type":"Manufacturing & Wholesale Goods"
        }
    ],
    "sg:postcode":"CA8 1LY",
    "sg:province":"Cumbria",
    "sg:tags":[
        "others"
    ],
    "wof:name":"Robert M Bell",
    "wof:placetype":"venue"
},
  "geometry": {"coordinates":[-2.7372810841,54.9422798157],"type":"Point"}
}