{
  "type": "Feature",
  "properties": {
    "iso:country":"GB",
    "sg:address":"2 City View",
    "sg:city":"Chester",
    "sg:classifiers":[
        {
            "category":"Professional",
            "subcategory":"Engineering",
            "type":"Services"
        }
    ],
    "sg:postcode":"CH4 7BX",
    "sg:province":"Cheshire",
    "sg:tags":[
        "contractor",
        "electrical",
        "engineer"
    ],
    "wof:name":"Omega Electrical Services",
    "wof:placetype":"venue"
},
  "geometry": {"coordinates":[-2.8845200539,53.1830291748],"type":"Point"}
}