{
  "type": "Feature",
  "properties": {
    "iso:country":"GB",
    "sg:address":"The Old Stockyard, Farleigh Road, Cliddesden",
    "sg:city":"Basingstoke",
    "sg:classifiers":[
        {
            "category":"Professional",
            "subcategory":"Printing & Photocopies",
            "type":"Services"
        }
    ],
    "sg:phone":"+44 1256 811519",
    "sg:postcode":"RG25 2JS",
    "sg:province":"Hampshire",
    "sg:tags":[
        "printer"
    ],
    "wof:name":"Datasharp Independent Solutions",
    "wof:placetype":"venue"
},
  "geometry": {"coordinates":[-1.093963027,51.236831665],"type":"Point"}
}