{
  "type": "Feature",
  "properties": {
    "addr:full":"Cressingham Road, Stretford Manchester Cheshire M32 9DL",
    "addr:postcode":"m32 9dl",
    "addr:street":"Cressingham Road",
    "iso:country":"GB",
    "sg:address":"Cressingham Road, Stretford",
    "sg:city":"Manchester",
    "sg:classifiers":[
        {
            "category":"Retail",
            "subcategory":"Repair Shop",
            "type":"Services"
        }
    ],
    "sg:phone":"+44 161 864 2608",
    "sg:postcode":"M32 9DL",
    "sg:province":"Cheshire",
    "sg:tags":[
        "radio",
        "television",
        "video"
    ],
    "wof:name":"S Collins Tv & Video Repairs",
    "wof:placetype":"venue"
},
  "geometry": {"coordinates":[-2.323899,53.448727],"type":"Point"}
}