{
  "type": "Feature",
  "properties": {
    "addr:full":"22 Lydgate Burnley Lancashire BB10 2DT",
    "addr:housenumber":"22",
    "addr:postcode":"bb10 2dt",
    "addr:street":"Lydgate",
    "iso:country":"GB",
    "sg:address":"22 Lydgate",
    "sg:city":"Burnley",
    "sg:classifiers":[
        {
            "category":"Manufacturing",
            "subcategory":"Textiles",
            "type":"Manufacturing & Wholesale Goods"
        },
        {
            "category":"Home & Garden",
            "subcategory":"Carpets & Floor Coverings",
            "type":"Retail Goods"
        }
    ],
    "sg:phone":"+44 1282 432646",
    "sg:postcode":"BB10 2DT",
    "sg:province":"Lancashire",
    "sg:tags":[
        "cleaner",
        "upholstery",
        "rug",
        "mnfr"
    ],
    "wof:name":"C & B Chem-Dry",
    "wof:placetype":"venue"
},
  "geometry": {"coordinates":[-2.2110569477,53.8087539673],"type":"Point"}
}