{
  "type": "Feature",
  "properties": {
    "iso:country":"GB",
    "sg:address":"8 Rowlands Crescent",
    "sg:city":"Solihull",
    "sg:classifiers":[
        {
            "category":"Building & Trades",
            "subcategory":"Construction",
            "type":"Services"
        }
    ],
    "sg:postcode":"B91 2JF",
    "sg:province":"West Midlands",
    "sg:tags":[
        "glazier"
    ],
    "wof:name":"Plumb,E T, & Sons",
    "wof:placetype":"venue"
},
  "geometry": {"coordinates":[-1.781929,52.4314],"type":"Point"}
}