{
  "type": "Feature",
  "properties": {
    "addr:full":"478 Pinkston Road Glasgow East Dunbartonshire G21 1HU",
    "addr:housenumber":"478",
    "addr:postcode":"g21 1hu",
    "addr:street":"Pinkston Road",
    "iso:country":"GB",
    "sg:address":"478 Pinkston Road",
    "sg:city":"Glasgow",
    "sg:classifiers":[
        {
            "category":"Retail",
            "subcategory":"Auto Repair",
            "type":"Services"
        }
    ],
    "sg:phone":"+44 141 332 4589",
    "sg:postcode":"G21 1HU",
    "sg:province":"East Dunbartonshire",
    "sg:tags":[
        "modification",
        "garage",
        "related"
    ],
    "wof:name":"M R M AUTOMOTIVES",
    "wof:placetype":"venue"
},
  "geometry": {"coordinates":[-4.2472081184,55.8761940002],"type":"Point"}
}