{
  "type": "Feature",
  "properties": {
    "addr:full":"303 Chichester Road, North Bersted Bognor Regis West Sussex PO21 5AL",
    "addr:housenumber":"303",
    "addr:postcode":"po21 5al",
    "addr:street":"Chichester Road North",
    "iso:country":"GB",
    "sg:address":"303 Chichester Road, North Bersted",
    "sg:city":"Bognor Regis",
    "sg:classifiers":[
        {
            "category":"Food & Beverages",
            "subcategory":"Liquor & Beverages",
            "type":"Retail Goods"
        }
    ],
    "sg:phone":"+44 1243 864407",
    "sg:postcode":"PO21 5AL",
    "sg:province":"West Sussex",
    "sg:tags":[
        "beer",
        "spirit",
        "wines"
    ],
    "wof:name":"Unwins Wine Merchants",
    "wof:placetype":"venue"
},
  "geometry": {"coordinates":[-0.6906239986,50.7974853516],"type":"Point"}
}