{
  "type": "Feature",
  "properties": {
    "iso:country":"GB",
    "sg:address":"Dove Cottage, 1 Hayes St",
    "sg:city":"Ware",
    "sg:classifiers":[
        {
            "category":"Building & Trades",
            "subcategory":"Plumbing",
            "type":"Services"
        }
    ],
    "sg:phone":"+44 1920 822942",
    "sg:postcode":"SG11 2RJ",
    "sg:province":"Hertfordshire",
    "sg:tags":[
        "central",
        "heating"
    ],
    "wof:name":"MacDonald Plumbing & Heating",
    "wof:placetype":"venue"
},
  "geometry": {"coordinates":[0.02381,51.91824],"type":"Point"}
}