{
  "type": "Feature",
  "properties": {
    "addr:full":"Unit 19/20, Ariane Tamworth Staffordshire B79 7XF",
    "addr:housenumber":"unit 19 / 20",
    "addr:postcode":"b79 7xf",
    "addr:street":"Ariane",
    "iso:country":"GB",
    "sg:address":"Unit 19/20, Ariane",
    "sg:city":"Tamworth",
    "sg:classifiers":[
        {
            "category":"Retail",
            "subcategory":"Repair Shop",
            "type":"Services"
        },
        {
            "category":"Home & Garden",
            "subcategory":"Carpets & Floor Coverings",
            "type":"Retail Goods"
        }
    ],
    "sg:phone":"+44 1827 63366",
    "sg:postcode":"B79 7XF",
    "sg:province":"Staffordshire",
    "sg:tags":[
        "carpets",
        "rug",
        "floorcoverings",
        "matting"
    ],
    "wof:name":"Lakin Carpet & Flooring Co. Ltd.",
    "wof:placetype":"venue"
},
  "geometry": {"coordinates":[-1.7176059484,52.644115448],"type":"Point"}
}