{
  "type": "Feature",
  "properties": {
    "addr:full":"115 Hope Street Glasgow Glasgow City G2 6LX",
    "addr:housenumber":"115",
    "addr:postcode":"g2 6lx",
    "addr:street":"Hope Street",
    "iso:country":"GB",
    "sg:address":"115 Hope Street",
    "sg:city":"Glasgow",
    "sg:classifiers":[
        {
            "category":"Travel",
            "subcategory":"Travel Agent",
            "type":"Entertainment"
        }
    ],
    "sg:phone":"+44 870 600 1060",
    "sg:postcode":"G2 6LX",
    "sg:province":"Glasgow City",
    "sg:tags":[
        "agency",
        "activity"
    ],
    "wof:name":"American Express Travel",
    "wof:placetype":"venue"
},
  "geometry": {"coordinates":[-4.258202,55.861446],"type":"Point"}
}