{
  "type": "Feature",
  "properties": {
    "iso:country":"GB",
    "sg:address":"Aldgate Hostel, 7 Dock St",
    "sg:city":"Whitechapel",
    "sg:classifiers":[
        {
            "category":"Organizations",
            "subcategory":"Community Association",
            "type":"Services"
        }
    ],
    "sg:phone":"+44 171 481 1326",
    "sg:postcode":"E1 8JN",
    "sg:province":"Greater London",
    "sg:tags":[
        "society",
        "housing"
    ],
    "wof:name":"Look Ahead Housing Association",
    "wof:placetype":"venue"
},
  "geometry": {"coordinates":[-0.0682599992,51.5105400085],"type":"Point"}
}