{
  "type": "Feature",
  "properties": {
    "addr:full":"24 Beckenham Rd Beckenham Kent BR3 4PF",
    "addr:housenumber":"24",
    "addr:postcode":"br3 4pf",
    "addr:street":"Beckenham Rd",
    "iso:country":"GB",
    "sg:address":"24 Beckenham Rd",
    "sg:city":"Beckenham",
    "sg:classifiers":[
        {
            "category":"Community Center",
            "type":"Public Place"
        }
    ],
    "sg:phone":"+44 20 8650 0233",
    "sg:postcode":"BR3 4PF",
    "sg:province":"Kent",
    "sg:tags":[
        "recreation",
        "leisure",
        "centre"
    ],
    "wof:name":"Walnut Leisure Centre",
    "wof:placetype":"venue"
},
  "geometry": {"coordinates":[-0.037678,51.408512],"type":"Point"}
}