{
  "type": "Feature",
  "properties": {
    "addr:full":"77 Upwell Street Sheffield South Yorkshire S4 8AN",
    "addr:housenumber":"77",
    "addr:postcode":"s4 8an",
    "addr:street":"Upwell Street",
    "iso:country":"GB",
    "sg:address":"77 Upwell Street",
    "sg:city":"Sheffield",
    "sg:classifiers":[
        {
            "category":"Retail",
            "subcategory":"Auto Repair",
            "type":"Services"
        }
    ],
    "sg:phone":"+44 114 243 2469",
    "sg:postcode":"S4 8AN",
    "sg:province":"South Yorkshire",
    "sg:tags":[
        "modification",
        "garage"
    ],
    "wof:name":"M B Services",
    "wof:placetype":"venue"
},
  "geometry": {"coordinates":[-1.436543,53.407093],"type":"Point"}
}