{
  "type": "Feature",
  "properties": {
    "addr:full":"Unit 13, Impress House, Mansell Rd Acton Greater London W3 7QH",
    "addr:housenumber":"unit 13 impress house",
    "addr:postcode":"w3 7qh",
    "addr:street":"Mansell Rd",
    "iso:country":"GB",
    "sg:address":"Unit 13, Impress House, Mansell Rd",
    "sg:city":"Acton",
    "sg:classifiers":[
        {
            "category":"Retail",
            "subcategory":"Storage",
            "type":"Services"
        }
    ],
    "sg:phone":"+44 20 8749 9110",
    "sg:postcode":"W3 7QH",
    "sg:province":"Greater London",
    "sg:tags":[
        "recording",
        "equipment"
    ],
    "wof:name":"Connex Pro Audio",
    "wof:placetype":"venue"
},
  "geometry": {"coordinates":[-0.2625440061,51.5062713623],"type":"Point"}
}