{
  "type": "Feature",
  "properties": {
    "addr:full":"The Courtyard, Matthews Green Farm, Matthews Green Road Wokingham Berkshire RG41 1JX",
    "addr:postcode":"rg41 1jx",
    "addr:street":"Matthews Green;Matthews Green Road",
    "iso:country":"GB",
    "sg:address":"The Courtyard, Matthews Green Farm, Matthews Green Road",
    "sg:city":"Wokingham",
    "sg:classifiers":[
        {
            "category":"Home & Garden",
            "subcategory":"Home Furnishings",
            "type":"Retail Goods"
        }
    ],
    "sg:phone":"+44 118 977 0220",
    "sg:postcode":"RG41 1JX",
    "sg:province":"Berkshire",
    "sg:tags":[
        "awning",
        "canopy",
        "blinds"
    ],
    "wof:name":"Apollo Blinds",
    "wof:placetype":"venue"
},
  "geometry": {"coordinates":[-0.84468,51.422009],"type":"Point"}
}