{
  "type": "Feature",
  "properties": {
    "addr:full":"New Clubhouse, The Fairstead, Shouldham King's Lynn Norfolk PE33 0DL",
    "addr:postcode":"pe33 0dl",
    "addr:street":"The;Lynn",
    "iso:country":"GB",
    "sg:address":"New Clubhouse, The Fairstead, Shouldham",
    "sg:city":"King's Lynn",
    "sg:classifiers":[
        {
            "category":"Arena",
            "subcategory":"Sports Club",
            "type":"Entertainment"
        }
    ],
    "sg:phone":"+44 1366 347550",
    "sg:postcode":"PE33 0DL",
    "sg:province":"Norfolk",
    "wof:name":"Shouldham Bowls Club",
    "wof:placetype":"venue"
},
  "geometry": {"coordinates":[0.4726800025,52.6567382812],"type":"Point"}
}