{
  "type": "Feature",
  "properties": {
    "addr:full":"Unit 1 Shortway, Thornbury Industrial Estate Bristol Gloucestershire BS35 3UT",
    "addr:housenumber":"unit 1",
    "addr:postcode":"bs35 3ut",
    "addr:street":"Shortway Thornbury Industrial Estate",
    "iso:country":"GB",
    "sg:address":"Unit 1 Shortway, Thornbury Industrial Estate",
    "sg:city":"Bristol",
    "sg:classifiers":[
        {
            "category":"Manufacturing",
            "subcategory":"Furniture",
            "type":"Manufacturing & Wholesale Goods"
        }
    ],
    "sg:phone":"+44 1454 419245",
    "sg:postcode":"BS35 3UT",
    "sg:province":"Gloucestershire",
    "sg:tags":[
        "mnfr",
        "garden",
        "patio"
    ],
    "wof:name":"Woodfurn",
    "wof:placetype":"venue"
},
  "geometry": {"coordinates":[-2.528434,51.592926],"type":"Point"}
}