{
  "type": "Feature",
  "properties": {
    "iso:country":"GB",
    "sg:address":"101a Flaxfield Road",
    "sg:city":"Basingstoke",
    "sg:classifiers":[
        {
            "category":"Professional",
            "subcategory":"Detective & Security Services",
            "type":"Services"
        }
    ],
    "sg:phone":"+44 1256 817170",
    "sg:postcode":"RG21 8SJ",
    "sg:province":"Hampshire",
    "wof:name":"Rentokil Security Services",
    "wof:placetype":"venue"
},
  "geometry": {"coordinates":[-1.0930739641,51.2639923096],"type":"Point"}
}