{
  "type": "Feature",
  "properties": {
    "addr:full":"50 Priory Road Tonbridge Kent TN9 2BL",
    "addr:housenumber":"50",
    "addr:postcode":"tn9 2bl",
    "addr:street":"Priory Road",
    "iso:country":"GB",
    "sg:address":"50 Priory Road",
    "sg:city":"Tonbridge",
    "sg:classifiers":[
        {
            "category":"Wholesale",
            "subcategory":"Scrap",
            "type":"Manufacturing & Wholesale Goods"
        },
        {
            "category":"Home & Garden",
            "subcategory":"Hardware",
            "type":"Retail Goods"
        }
    ],
    "sg:phone":"+44 1732 369368",
    "sg:postcode":"TN9 2BL",
    "sg:province":"Kent",
    "sg:tags":[
        "waste",
        "metal"
    ],
    "wof:name":"Strada",
    "wof:placetype":"venue"
},
  "geometry": {"coordinates":[0.275943011,51.1899795532],"type":"Point"}
}