{
  "type": "Feature",
  "properties": {
    "iso:country":"GB",
    "sg:address":"Orcop Hill, Orcop",
    "sg:city":"Hereford",
    "sg:classifiers":[
        {
            "category":"Bars & Pubs",
            "type":"Food & Drink"
        }
    ],
    "sg:phone":"+44 1981 540304",
    "sg:postcode":"HR2 8EP",
    "sg:province":"Herefordshire",
    "sg:tags":[
        "pubs",
        "inn"
    ],
    "wof:name":"The Fountain Inn",
    "wof:placetype":"venue"
},
  "geometry": {"coordinates":[-2.75933,51.946941],"type":"Point"}
}