{
  "type": "Feature",
  "properties": {
    "addr:full":"53 King St Bridlington East Riding of Yorkshire YO15 2DQ",
    "addr:housenumber":"53",
    "addr:postcode":"yo15 2dq",
    "addr:street":"King St",
    "iso:country":"GB",
    "sg:address":"53 King St",
    "sg:city":"Bridlington",
    "sg:classifiers":[
        {
            "category":"Shopping",
            "subcategory":"Florist",
            "type":"Retail Goods"
        }
    ],
    "sg:phone":"+44 1262 401626",
    "sg:postcode":"YO15 2DQ",
    "sg:province":"East Riding of Yorkshire",
    "wof:name":"Pattisons",
    "wof:placetype":"venue"
},
  "geometry": {"coordinates":[-0.187399,54.08749],"type":"Point"}
}