{
  "type": "Feature",
  "properties": {
    "iso:country":"GB",
    "sg:address":"The Ct Yd, Crown Ct",
    "sg:city":"Godalming",
    "sg:classifiers":[
        {
            "category":"Personal",
            "type":"Services"
        }
    ],
    "sg:postcode":"GU7 1DY",
    "sg:province":"Surrey",
    "sg:tags":[
        "wedding"
    ],
    "wof:name":"Cameron,Anna,",
    "wof:placetype":"venue"
},
  "geometry": {"coordinates":[-0.6183840036,51.1839561462],"type":"Point"}
}