{
  "type": "Feature",
  "properties": {
    "addr:full":"225 Lewisham Way London Greater London SE4 1UY",
    "addr:housenumber":"225",
    "addr:postcode":"se4 1uy",
    "addr:street":"Lewisham Way",
    "iso:country":"GB",
    "sg:address":"225 Lewisham Way",
    "sg:city":"London",
    "sg:classifiers":[
        {
            "category":"Retail",
            "subcategory":"Auto Repair",
            "type":"Services"
        }
    ],
    "sg:phone":"+44 20 8691 7128",
    "sg:postcode":"SE4 1UY",
    "sg:province":"Greater London",
    "sg:tags":[
        "modification",
        "garage"
    ],
    "wof:name":"A C S Auto Services",
    "wof:placetype":"venue"
},
  "geometry": {"coordinates":[-0.0283899996,51.4700584412],"type":"Point"}
}