{
  "type": "Feature",
  "properties": {
    "addr:full":"30 Market Pl Goole East Riding of Yorkshire DN14 7BL",
    "addr:housenumber":"30",
    "addr:postcode":"dn14 7bl",
    "addr:street":"Market Pl",
    "iso:country":"GB",
    "sg:address":"30 Market Pl",
    "sg:city":"Goole",
    "sg:classifiers":[
        {
            "category":"Food & Beverages",
            "subcategory":"Fruits & Vegetables",
            "type":"Retail Goods"
        }
    ],
    "sg:phone":"+44 1430 432374",
    "sg:postcode":"DN14 7BL",
    "sg:province":"East Riding of Yorkshire",
    "sg:tags":[
        "greengrocer"
    ],
    "wof:name":"Howden Fruit Shop The",
    "wof:placetype":"venue"
},
  "geometry": {"coordinates":[-0.8662649989,53.7454109192],"type":"Point"}
}