{
  "type": "Feature",
  "properties": {
    "iso:country":"GB",
    "sg:address":"Unit 1 Bonhay Business Centre, Tudor Street",
    "sg:city":"Exeter",
    "sg:classifiers":[
        {
            "category":"Home & Garden",
            "subcategory":"Furniture",
            "type":"Retail Goods"
        }
    ],
    "sg:phone":"+44 1392 498005",
    "sg:postcode":"EX4 3BR",
    "sg:province":"Devon",
    "wof:name":"Just Pine",
    "wof:placetype":"venue"
},
  "geometry": {"coordinates":[-3.53716,50.72007],"type":"Point"}
}