{
  "type": "Feature",
  "properties": {
    "addr:full":"79 Newton Rd, Mumbles Swansea Bridgend CF31 1DU",
    "addr:housenumber":"79",
    "addr:postcode":"cf31 1du",
    "addr:street":"Newton Rd",
    "iso:country":"GB",
    "sg:address":"79 Newton Rd, Mumbles",
    "sg:city":"Swansea",
    "sg:classifiers":[
        {
            "category":"Real Estate",
            "subcategory":"Real Estate Agent",
            "type":"Services"
        }
    ],
    "sg:phone":"+44 1656 647055",
    "sg:postcode":"CF31 1DU",
    "sg:province":"Bridgend",
    "wof:name":"Morgan Peter",
    "wof:placetype":"venue"
},
  "geometry": {"coordinates":[-3.5769999027,51.5056991577],"type":"Point"}
}