{
  "type": "Feature",
  "properties": {
    "iso:country":"GB",
    "sg:address":"Ash Street",
    "sg:city":"Bilston",
    "sg:classifiers":[
        {
            "category":"Retail",
            "subcategory":"Auto Repair",
            "type":"Services"
        }
    ],
    "sg:phone":"+44 1902 490327",
    "sg:postcode":"WV14 8UL",
    "sg:province":"West Midlands",
    "sg:tags":[
        "modification",
        "garage"
    ],
    "wof:name":"P J Auto's",
    "wof:placetype":"venue"
},
  "geometry": {"coordinates":[-2.0743570328,52.5560112],"type":"Point"}
}