{
  "type": "Feature",
  "properties": {
    "addr:full":"Unit 1 Gladstone Street, Langlemill Nottingham Derbyshire NG16 4EN",
    "addr:housenumber":"unit 1",
    "addr:postcode":"ng16 4en",
    "addr:street":"Gladstone Street",
    "iso:country":"GB",
    "sg:address":"Unit 1 Gladstone Street, Langlemill",
    "sg:city":"Nottingham",
    "sg:classifiers":[
        {
            "category":"Wholesale",
            "subcategory":"Construction Materials",
            "type":"Manufacturing & Wholesale Goods"
        }
    ],
    "sg:phone":"+44 1773 718355",
    "sg:postcode":"NG16 4EN",
    "sg:province":"Derbyshire",
    "sg:tags":[
        "supplier",
        "double",
        "glazing"
    ],
    "wof:name":"Trims R Us",
    "wof:placetype":"venue"
},
  "geometry": {"coordinates":[-1.328424,53.022579],"type":"Point"}
}