{
  "type": "Feature",
  "properties": {
    "addr:full":"230 Norwood Road Tulse Hill Greater London SE27 9AW",
    "addr:housenumber":"230",
    "addr:postcode":"se27 9aw",
    "addr:street":"Norwood Road",
    "iso:country":"GB",
    "sg:address":"230 Norwood Road",
    "sg:city":"Tulse Hill",
    "sg:classifiers":[
        {
            "category":"Fast Food",
            "type":"Food & Drink"
        }
    ],
    "sg:phone":"+44 20 8761 7881",
    "sg:postcode":"SE27 9AW",
    "sg:province":"Greater London",
    "sg:tags":[
        "away",
        "take"
    ],
    "wof:name":"Pizza Romantica",
    "wof:placetype":"venue"
},
  "geometry": {"coordinates":[-0.1060419977,51.4383087158],"type":"Point"}
}