{
  "type": "Feature",
  "properties": {
    "addr:full":"295 Tettenhall Road Wolverhampton Shropshire WV6 0LB",
    "addr:housenumber":"295",
    "addr:postcode":"wv6 0lb",
    "addr:street":"Tettenhall Road",
    "iso:country":"GB",
    "sg:address":"295 Tettenhall Road",
    "sg:city":"Wolverhampton",
    "sg:classifiers":[
        {
            "category":"Personal",
            "subcategory":"Beauty Salon",
            "type":"Services"
        }
    ],
    "sg:postcode":"WV6 0LB",
    "sg:province":"Shropshire",
    "wof:name":"Top to Toe Beauty Care",
    "wof:placetype":"venue"
},
  "geometry": {"coordinates":[-2.158634,52.59634],"type":"Point"}
}