{
  "type": "Feature",
  "properties": {
    "addr:full":"The Street Pulborough West Sussex RH20 2HE",
    "addr:postcode":"rh20 2he",
    "addr:street":"The Street",
    "iso:country":"GB",
    "sg:address":"The Street",
    "sg:city":"Pulborough",
    "sg:classifiers":[
        {
            "category":"Professional",
            "subcategory":"Testing Lab",
            "type":"Services"
        }
    ],
    "sg:phone":"+44 1798 812194",
    "sg:postcode":"RH20 2HE",
    "sg:province":"West Sussex",
    "sg:tags":[
        "mot"
    ],
    "wof:name":"Nutbourne Garage",
    "wof:placetype":"venue"
},
  "geometry": {"coordinates":[-0.4714039862,50.9576301575],"type":"Point"}
}