{
  "type": "Feature",
  "properties": {
    "iso:country":"GB",
    "sg:address":"76-78 City Road, Walton",
    "sg:city":"Liverpool",
    "sg:classifiers":[
        {
            "category":"Food & Beverages",
            "subcategory":"Groceries & Convenience Stores",
            "type":"Retail Goods"
        }
    ],
    "sg:phone":"+44 151 523 8822",
    "sg:postcode":"L4 5TE",
    "sg:province":"Merseyside",
    "wof:name":"Greenalls Food Store",
    "wof:placetype":"venue"
},
  "geometry": {"coordinates":[-2.965693,53.441765],"type":"Point"}
}