{
  "type": "Feature",
  "properties": {
    "addr:full":"17 Market Square Dover Kent CT16 1NX",
    "addr:housenumber":"17",
    "addr:postcode":"ct16 1nx",
    "addr:street":"Market Square Dover",
    "iso:country":"GB",
    "sg:address":"17 Market Square",
    "sg:city":"Dover",
    "sg:classifiers":[
        {
            "category":"Organizations",
            "subcategory":"Non-profit Organization",
            "type":"Services"
        }
    ],
    "sg:phone":"+44 1304 211976",
    "sg:postcode":"CT16 1NX",
    "sg:province":"Kent",
    "sg:tags":[
        "organisation",
        "voluntary",
        "charity"
    ],
    "wof:name":"Scope",
    "wof:placetype":"venue"
},
  "geometry": {"coordinates":[1.31338,51.125034],"type":"Point"}
}