{
  "type": "Feature",
  "properties": {
    "addr:full":"North Eggardon Farm, Powerstock Bridport Dorset DT6 3ST",
    "addr:postcode":"dt6 3st",
    "addr:street":"North",
    "iso:country":"GB",
    "sg:address":"North Eggardon Farm, Powerstock",
    "sg:city":"Bridport",
    "sg:classifiers":[
        {
            "category":"Building & Trades",
            "subcategory":"Construction",
            "type":"Services"
        }
    ],
    "sg:phone":"+44 1308 485251",
    "sg:postcode":"DT6 3ST",
    "sg:province":"Dorset",
    "sg:tags":[
        "conservation",
        "craft",
        "thatching"
    ],
    "wof:name":"John Bretherton",
    "wof:placetype":"venue"
},
  "geometry": {"coordinates":[-2.7580189705,50.7335662842],"type":"Point"}
}