{
  "type": "Feature",
  "properties": {
    "addr:full":"2 Pound Rd, East Peckham Tonbridge Kent TN12 5BE",
    "addr:housenumber":"2",
    "addr:postcode":"tn12 5be",
    "addr:street":"Pound Rd",
    "iso:country":"GB",
    "sg:address":"2 Pound Rd, East Peckham",
    "sg:city":"Tonbridge",
    "sg:classifiers":[
        {
            "category":"Bars & Pubs",
            "type":"Food & Drink"
        }
    ],
    "sg:phone":"+44 1622 871249",
    "sg:postcode":"TN12 5BE",
    "sg:province":"Kent",
    "sg:tags":[
        "pubs",
        "inn"
    ],
    "wof:name":"Merry Boys Inn",
    "wof:placetype":"venue"
},
  "geometry": {"coordinates":[0.3860810101,51.2125244141],"type":"Point"}
}