{
  "type": "Feature",
  "properties": {
    "iso:country":"GB",
    "sg:address":"Marine Terrace",
    "sg:city":"Penzance",
    "sg:classifiers":[
        {
            "category":"Travel",
            "subcategory":"Hotels & Motels",
            "type":"Entertainment"
        }
    ],
    "sg:postcode":"TR18 4DL",
    "sg:province":"Cornwall",
    "wof:name":"Lugger Inn Hotel",
    "wof:placetype":"venue"
},
  "geometry": {"coordinates":[-5.5366640091,50.114315033],"type":"Point"}
}