{
  "type": "Feature",
  "properties": {
    "addr:full":"The Jungle, Woodbridge Road, Tunstall Woodbridge Suffolk IP12 2JE",
    "addr:postcode":"ip12 2je",
    "addr:street":"Jungle Woodbridge Road",
    "iso:country":"GB",
    "sg:address":"The Jungle, Woodbridge Road, Tunstall",
    "sg:city":"Woodbridge",
    "sg:classifiers":[
        {
            "category":"Retail",
            "subcategory":"Auto Repair",
            "type":"Services"
        }
    ],
    "sg:phone":"+44 1728 688292",
    "sg:postcode":"IP12 2JE",
    "sg:province":"Suffolk",
    "sg:tags":[
        "body",
        "car",
        "repairer"
    ],
    "wof:name":"Peter Teager Cars",
    "wof:placetype":"venue"
},
  "geometry": {"coordinates":[1.4479000568,52.1436729431],"type":"Point"}
}