{
  "type": "Feature",
  "properties": {
    "addr:full":"325 Liverpool Road, Eccles Manchester Greater Manchester M30 8GF",
    "addr:housenumber":"325",
    "addr:postcode":"m30 8gf",
    "addr:street":"Liverpool Road",
    "iso:country":"GB",
    "sg:address":"325 Liverpool Road, Eccles",
    "sg:city":"Manchester",
    "sg:classifiers":[
        {
            "category":"Banks & Credit Unions",
            "subcategory":"Investment Brokerage",
            "type":"Services"
        },
        {
            "category":"Home & Garden",
            "subcategory":"Carpets & Floor Coverings",
            "type":"Retail Goods"
        }
    ],
    "sg:phone":"+44 161 789 2050",
    "sg:postcode":"M30 8GF",
    "sg:province":"Greater Manchester",
    "sg:tags":[
        "wall",
        "tie",
        "replacement"
    ],
    "wof:name":"D C Wall Tie & Damp Proofing Services",
    "wof:placetype":"venue"
},
  "geometry": {"coordinates":[-2.3600161076,53.480506897],"type":"Point"}
}