{
  "type": "Feature",
  "properties": {
    "addr:full":"742 High Rd, Leytonstone London Greater London E11 3AW",
    "addr:housenumber":"742",
    "addr:postcode":"e11 3aw",
    "addr:street":"High Rd",
    "iso:country":"GB",
    "sg:address":"742 High Rd, Leytonstone",
    "sg:city":"London",
    "sg:classifiers":[
        {
            "category":"Freight",
            "type":"Transportation"
        }
    ],
    "sg:phone":"+44 20 8989 2077",
    "sg:postcode":"E11 3AW",
    "sg:province":"Greater London",
    "sg:tags":[
        "forwarders"
    ],
    "wof:name":"Maritime Freight Services Ltd",
    "wof:placetype":"venue"
},
  "geometry": {"coordinates":[0.0142200002,51.5702896118],"type":"Point"}
}