{
  "type": "Feature",
  "properties": {
    "addr:full":"58 Dunbar Lane, Burghead Elgin Moray IV30 5XE",
    "addr:housenumber":"58",
    "addr:postcode":"iv30 5xe",
    "addr:street":"Dunbar Lane",
    "iso:country":"GB",
    "sg:address":"58 Dunbar Lane, Burghead",
    "sg:city":"Elgin",
    "sg:classifiers":[
        {
            "category":"Professional",
            "subcategory":"Art Services",
            "type":"Services"
        },
        {
            "category":"Building & Trades",
            "subcategory":"Construction",
            "type":"Services"
        }
    ],
    "sg:phone":"+44 1343 835553",
    "sg:postcode":"IV30 5XE",
    "sg:province":"Moray",
    "sg:tags":[
        "glazier",
        "decorator",
        "painter"
    ],
    "wof:name":"James C Duncan",
    "wof:placetype":"venue"
},
  "geometry": {"coordinates":[-3.3952291012,57.7003288269],"type":"Point"}
}