{
  "type": "Feature",
  "properties": {
    "addr:full":"22-28 Cockburn Street Edinburgh City of Edinburgh EH1 1NY",
    "addr:housenumber":"22-28",
    "addr:postcode":"eh1 1ny",
    "addr:street":"Cockburn Street",
    "iso:country":"GB",
    "sg:address":"22-28 Cockburn Street",
    "sg:city":"Edinburgh",
    "sg:classifiers":[
        {
            "category":"Museum",
            "subcategory":"Art Museum",
            "type":"Entertainment"
        },
        {
            "category":"Museum",
            "type":"Entertainment"
        }
    ],
    "sg:phone":"+44 131 220 1260",
    "sg:postcode":"EH1 1NY",
    "sg:province":"City of Edinburgh",
    "sg:tags":[
        "gallery"
    ],
    "wof:name":"Collective Gallery",
    "wof:placetype":"venue"
},
  "geometry": {"coordinates":[-3.1895949841,55.950592041],"type":"Point"}
}