{
  "type": "Feature",
  "properties": {
    "addr:full":"Unit 2 County La, Warfield Bracknell Berkshire RG42 3JP",
    "addr:housenumber":"unit 2",
    "addr:postcode":"rg42 3jp",
    "addr:street":"County La Warfield",
    "iso:country":"GB",
    "sg:address":"Unit 2 County La, Warfield",
    "sg:city":"Bracknell",
    "sg:classifiers":[
        {
            "category":"Shopping",
            "subcategory":"Thrift Store",
            "type":"Retail Goods"
        }
    ],
    "sg:phone":"+44 1344 421888",
    "sg:postcode":"RG42 3JP",
    "sg:province":"Berkshire",
    "sg:tags":[
        "shop",
        "charity"
    ],
    "wof:name":"St. Michaels Hospice (Trading) Ltd",
    "wof:placetype":"venue"
},
  "geometry": {"coordinates":[-0.735311,51.427792],"type":"Point"}
}