{
  "type": "Feature",
  "properties": {
    "iso:country":"GB",
    "sg:address":"Warwick Street, Prestwich",
    "sg:city":"Manchester",
    "sg:classifiers":[
        {
            "category":"Home & Garden",
            "subcategory":"Furniture",
            "type":"Retail Goods"
        }
    ],
    "sg:phone":"+44 161 773 8625",
    "sg:postcode":"M25 3HN",
    "sg:province":"Greater Manchester",
    "wof:name":"The Warehouse",
    "wof:placetype":"venue"
},
  "geometry": {"coordinates":[-2.2858440876,53.5322952271],"type":"Point"}
}