{
  "type": "Feature",
  "properties": {
    "addr:full":"2 Myrtle Walk Bingley West Yorkshire BD16 1AN",
    "addr:housenumber":"2",
    "addr:postcode":"bd16 1an",
    "addr:street":"Myrtle Walk",
    "iso:country":"GB",
    "sg:address":"2 Myrtle Walk",
    "sg:city":"Bingley",
    "sg:classifiers":[
        {
            "category":"Shopping",
            "subcategory":"Clothing, Apparel, & Fashions",
            "type":"Retail Goods"
        }
    ],
    "sg:phone":"+44 1274 551076",
    "sg:postcode":"BD16 1AN",
    "sg:province":"West Yorkshire",
    "sg:tags":[
        "ladieswear"
    ],
    "wof:name":"Bon Marche Ltd.",
    "wof:placetype":"venue"
},
  "geometry": {"coordinates":[-1.8353790045,53.843963623],"type":"Point"}
}