{
  "type": "Feature",
  "properties": {
    "iso:country":"GB",
    "sg:address":"26 Town End Street",
    "sg:city":"Godalming",
    "sg:classifiers":[
        {
            "category":"Building & Trades",
            "subcategory":"Construction",
            "type":"Services"
        }
    ],
    "sg:postcode":"GU7 1BH",
    "sg:province":"Surrey",
    "sg:tags":[
        "joiner",
        "carpenter"
    ],
    "wof:name":"Derek G Keen",
    "wof:placetype":"venue"
},
  "geometry": {"coordinates":[-0.610526979,51.1834754944],"type":"Point"}
}