{
  "type": "Feature",
  "properties": {
    "iso:country":"GB",
    "sg:address":"41 Cunningham Way",
    "sg:city":"Rugby",
    "sg:classifiers":[
        {
            "category":"Retail",
            "subcategory":"Driving School",
            "type":"Services"
        }
    ],
    "sg:phone":"+44 1788 816202",
    "sg:postcode":"CV22 7JD",
    "sg:province":"Warwickshire",
    "wof:name":"Nu-Way School Of Motoring",
    "wof:placetype":"venue"
},
  "geometry": {"coordinates":[-1.2936789989,52.3667907715],"type":"Point"}
}