{
  "type": "Feature",
  "properties": {
    "iso:country":"GB",
    "sg:address":"45 Gipsy Lane",
    "sg:city":"Leeds",
    "sg:classifiers":[
        {
            "category":"Transit Center",
            "subcategory":"Passenger",
            "type":"Transportation"
        },
        {
            "category":"Retail",
            "subcategory":"Pet Boarding",
            "type":"Services"
        }
    ],
    "sg:phone":"+44 113 270 8381",
    "sg:postcode":"LS11 5TT",
    "sg:province":"West Yorkshire",
    "sg:tags":[
        "kennel",
        "catteries"
    ],
    "wof:name":"Beeston Park Boarding Kennels & Cattery",
    "wof:placetype":"venue"
},
  "geometry": {"coordinates":[-1.557997,53.75684],"type":"Point"}
}