{
  "type": "Feature",
  "properties": {
    "addr:full":"13-14 Albion Road North Shields Tyne and Wear NE30 2RJ",
    "addr:housenumber":"13-14",
    "addr:postcode":"ne30 2rj",
    "addr:street":"Albion Road",
    "iso:country":"GB",
    "sg:address":"13-14 Albion Road",
    "sg:city":"North Shields",
    "sg:classifiers":[
        {
            "category":"Bars & Pubs",
            "type":"Food & Drink"
        }
    ],
    "sg:postcode":"NE30 2RJ",
    "sg:province":"Tyne and Wear",
    "sg:tags":[
        "pubs",
        "inn"
    ],
    "wof:name":"The Queens Head",
    "wof:placetype":"venue"
},
  "geometry": {"coordinates":[-1.448339,55.010769],"type":"Point"}
}