{
  "type": "Feature",
  "properties": {
    "addr:full":"49 Grecian St Salford Greater Manchester M7 2JW",
    "addr:housenumber":"49",
    "addr:postcode":"m7 2jw",
    "addr:street":"Grecian St",
    "iso:country":"GB",
    "sg:address":"49 Grecian St",
    "sg:city":"Salford",
    "sg:classifiers":[
        {
            "category":"Building & Trades",
            "subcategory":"Construction",
            "type":"Services"
        }
    ],
    "sg:phone":"+44 161 792 8087",
    "sg:postcode":"M7 2JW",
    "sg:province":"Greater Manchester",
    "sg:tags":[
        "builder"
    ],
    "wof:name":"Abacus Building Services",
    "wof:placetype":"venue"
},
  "geometry": {"coordinates":[-2.2673389912,53.4991531372],"type":"Point"}
}