{
  "type": "Feature",
  "properties": {
    "iso:country":"GB",
    "sg:address":"276 Preston Road",
    "sg:city":"Harrow",
    "sg:classifiers":[
        {
            "category":"Real Estate",
            "subcategory":"Real Estate Agent",
            "type":"Services"
        }
    ],
    "sg:phone":"+44 20 8904 8822",
    "sg:postcode":"HA3 0QA",
    "sg:province":"Greater London",
    "wof:name":"Procter Levy Ltd.",
    "wof:placetype":"venue"
},
  "geometry": {"coordinates":[-0.294433,51.572918],"type":"Point"}
}