{
  "type": "Feature",
  "properties": {
    "iso:country":"GB",
    "sg:address":"74 High Street",
    "sg:city":"Oakham",
    "sg:classifiers":[
        {
            "category":"Health Services",
            "subcategory":"Dentist",
            "type":"Services"
        }
    ],
    "sg:phone":"+44 1572 755260",
    "sg:postcode":"LE15 6AS",
    "sg:province":"Leicestershire",
    "wof:name":"J A GWYTHER",
    "wof:placetype":"venue"
},
  "geometry": {"coordinates":[-0.731022,52.669891],"type":"Point"}
}