{
  "type": "Feature",
  "properties": {
    "iso:country":"GB",
    "sg:address":"6 Fitzalan Square",
    "sg:city":"Sheffield",
    "sg:classifiers":[
        {
            "category":"Shopping",
            "subcategory":"News",
            "type":"Retail Goods"
        }
    ],
    "sg:phone":"+44 114 281 4728",
    "sg:postcode":"S1 2AZ",
    "sg:province":"South Yorkshire",
    "sg:tags":[
        "newsagent"
    ],
    "wof:name":"IFONTO PROPERTY DEVELOPMENT LTD",
    "wof:placetype":"venue"
},
  "geometry": {"coordinates":[-1.464419,53.382755],"type":"Point"}
}