{
  "type": "Feature",
  "properties": {
    "iso:country":"GB",
    "sg:address":"94 New Court Way, Ormskirk Business Park",
    "sg:city":"Ormskirk",
    "sg:classifiers":[
        {
            "category":"Shopping",
            "subcategory":"Stationery & Office Supplies",
            "type":"Retail Goods"
        }
    ],
    "sg:phone":"+44 1695 570005",
    "sg:postcode":"L39 2YT",
    "sg:province":"Lancashire",
    "wof:name":"West Lancs Office Products",
    "wof:placetype":"venue"
},
  "geometry": {"coordinates":[-2.8801529408,53.5707588196],"type":"Point"}
}