{
  "type": "Feature",
  "properties": {
    "iso:country":"GB",
    "sg:address":"1 Mermaid Court, Borough High St",
    "sg:city":"Southwark",
    "sg:classifiers":[
        {
            "category":"Shopping",
            "subcategory":"Pharmacy",
            "type":"Retail Goods"
        }
    ],
    "sg:phone":"+44 20 7403 7900",
    "sg:postcode":"SE1 1HR",
    "sg:province":"Greater London",
    "sg:tags":[
        "pharmaceutical"
    ],
    "wof:name":"Mermaid House",
    "wof:placetype":"venue"
},
  "geometry": {"coordinates":[-0.09189,51.502869],"type":"Point"}
}