{
  "type": "Feature",
  "properties": {
    "addr:full":"Beech Nut Studio, Bramble Lane Christchurch Dorset BH23 5NB",
    "addr:postcode":"bh23 5nb",
    "addr:street":"Bramble Lane",
    "iso:country":"GB",
    "sg:address":"Beech Nut Studio, Bramble Lane",
    "sg:city":"Christchurch",
    "sg:classifiers":[
        {
            "category":"Real Estate",
            "subcategory":"Architect",
            "type":"Services"
        }
    ],
    "sg:postcode":"BH23 5NB",
    "sg:province":"Dorset",
    "wof:name":"D U A Architechture",
    "wof:placetype":"venue"
},
  "geometry": {"coordinates":[-1.776564002,50.7340698242],"type":"Point"}
}