{
  "type": "Feature",
  "properties": {
    "addr:full":"The Museum Of Nottingham Life, Castle Blvd Nottingham Nottinghamshire NG7 1FB",
    "addr:postcode":"ng7 1fb",
    "addr:street":"Castle Blvd",
    "iso:country":"GB",
    "sg:address":"The Museum Of Nottingham Life, Castle Blvd",
    "sg:city":"Nottingham",
    "sg:classifiers":[
        {
            "category":"Museum",
            "subcategory":"Art Museum",
            "type":"Entertainment"
        }
    ],
    "sg:phone":"+44 115 915 3600",
    "sg:postcode":"NG7 1FB",
    "sg:province":"Nottinghamshire",
    "sg:tags":[
        "gallery"
    ],
    "wof:name":"Brewhouse Yard Museum",
    "wof:placetype":"venue"
},
  "geometry": {"coordinates":[-1.15083,52.948879],"type":"Point"}
}