{
  "type": "Feature",
  "properties": {
    "iso:country":"GB",
    "sg:address":"5 Coldbath Square",
    "sg:city":"London",
    "sg:classifiers":[
        {
            "category":"Professional",
            "subcategory":"Lawyer & Legal Services",
            "type":"Services"
        }
    ],
    "sg:phone":"+44 20 7689 8900",
    "sg:postcode":"EC1R 5HL",
    "sg:province":"Greater London",
    "sg:tags":[
        "solicitor"
    ],
    "wof:name":"Denniss Matthews",
    "wof:placetype":"venue"
},
  "geometry": {"coordinates":[-0.110379,51.524143],"type":"Point"}
}