{
  "type": "Feature",
  "properties": {
    "addr:full":"3 Horton Inn Cottages, Cranborne Rd Wimborne Dorset BH21 7HW",
    "addr:housenumber":"3",
    "addr:postcode":"bh21 7hw",
    "addr:street":"Horton;Cranborne Rd",
    "iso:country":"GB",
    "sg:address":"3 Horton Inn Cottages, Cranborne Rd",
    "sg:city":"Wimborne",
    "sg:classifiers":[
        {
            "category":"Retail",
            "subcategory":"Repair Shop",
            "type":"Services"
        }
    ],
    "sg:phone":"+44 1258 840288",
    "sg:postcode":"BH21 7HW",
    "sg:province":"Dorset",
    "sg:tags":[
        "upholsterer"
    ],
    "wof:name":"Original Sofas & Chairs",
    "wof:placetype":"venue"
},
  "geometry": {"coordinates":[-1.988709,50.802235],"type":"Point"}
}