{
  "type": "Feature",
  "properties": {
    "addr:full":"Durnaford Farm, Milton Abbot Tavistock Devon PL19 0NR",
    "addr:housenumber":"milton abbot tavistock",
    "addr:postcode":"pl19 0nr",
    "iso:country":"GB",
    "sg:address":"Durnaford Farm, Milton Abbot",
    "sg:city":"Tavistock",
    "sg:classifiers":[
        {
            "category":"Farming",
            "subcategory":"Livestock Farm",
            "type":"Manufacturing & Wholesale Goods"
        }
    ],
    "sg:phone":"+44 1822 870202",
    "sg:postcode":"PL19 0NR",
    "sg:province":"Devon",
    "sg:tags":[
        "others"
    ],
    "wof:name":"D Ball",
    "wof:placetype":"venue"
},
  "geometry": {"coordinates":[-4.144739,50.549934],"type":"Point"}
}