{
  "type": "Feature",
  "properties": {
    "addr:full":"434b Havant Road, Farlington Portsmouth Hampshire PO6 1AB",
    "addr:housenumber":"434b",
    "addr:postcode":"hampshire po6 1ab",
    "addr:street":"Havant Road",
    "iso:country":"GB",
    "sg:address":"434b Havant Road, Farlington",
    "sg:city":"Portsmouth",
    "sg:classifiers":[
        {
            "category":"Retail",
            "subcategory":"Auto Repair",
            "type":"Services"
        }
    ],
    "sg:phone":"+44 23 9232 6643",
    "sg:postcode":"PO6 1AB",
    "sg:province":"Hampshire",
    "sg:tags":[
        "modification",
        "garage",
        "related"
    ],
    "sg:website":"http://www.harringtonautos.com",
    "wof:name":"Harrington Autos",
    "wof:placetype":"venue"
},
  "geometry": {"coordinates":[-1.0301029682,50.8475265503],"type":"Point"}
}