{
  "type": "Feature",
  "properties": {
    "iso:country":"GB",
    "sg:address":"103-107 Queen Street, Morley",
    "sg:city":"Leeds",
    "sg:classifiers":[
        {
            "category":"Professional",
            "subcategory":"Employment Agencies",
            "type":"Services"
        }
    ],
    "sg:phone":"+44 113 259 7299",
    "sg:postcode":"LS27 8DW",
    "sg:province":"West Yorkshire",
    "sg:tags":[
        "consultant"
    ],
    "wof:name":"Personnel Evaluation Consultants",
    "wof:placetype":"venue"
},
  "geometry": {"coordinates":[-1.600346,53.744495],"type":"Point"}
}