{
  "type": "Feature",
  "properties": {
    "iso:country":"GB",
    "sg:address":"92 Foster Hill Road",
    "sg:city":"Bedford",
    "sg:classifiers":[
        {
            "category":"Food & Beverages",
            "subcategory":"Supermarket",
            "type":"Retail Goods"
        },
        {
            "category":"Food & Beverages",
            "subcategory":"Groceries & Convenience Stores",
            "type":"Retail Goods"
        }
    ],
    "sg:phone":"+44 1234 352481",
    "sg:postcode":"MK40 2EU",
    "sg:province":"Bedfordshire",
    "wof:name":"Narinda Randhawa & Sons",
    "wof:placetype":"venue"
},
  "geometry": {"coordinates":[-0.468759,52.143074],"type":"Point"}
}