{
  "type": "Feature",
  "properties": {
    "addr:full":"113 Eastcotes Coventry Warwickshire CV4 9AT",
    "addr:housenumber":"113",
    "addr:postcode":"cv4 9at",
    "addr:street":"Eastcotes",
    "iso:country":"GB",
    "sg:address":"113 Eastcotes",
    "sg:city":"Coventry",
    "sg:classifiers":[
        {
            "category":"Personal",
            "subcategory":"Beauty Salon",
            "type":"Services"
        }
    ],
    "sg:phone":"+44 24 7646 5827",
    "sg:postcode":"CV4 9AT",
    "sg:province":"Warwickshire",
    "sg:tags":[
        "ladies",
        "lady",
        "hairdresser"
    ],
    "wof:name":"Hazel Hair Studio",
    "wof:placetype":"venue"
},
  "geometry": {"coordinates":[-1.5623240471,52.4007949829],"type":"Point"}
}