{
  "type": "Feature",
  "properties": {
    "iso:country":"GB",
    "sg:address":"16 Dartmouth Park Hill",
    "sg:city":"London",
    "sg:classifiers":[
        {
            "category":"Home & Garden",
            "subcategory":"Home Furnishings",
            "type":"Retail Goods"
        }
    ],
    "sg:postcode":"NW5 1HL",
    "sg:province":"Greater London",
    "sg:tags":[
        "furnishers",
        "planner",
        "kitchen"
    ],
    "wof:name":"Kitchen Trade Warehouse Ltd.",
    "wof:placetype":"venue"
},
  "geometry": {"coordinates":[-0.13903,51.557983],"type":"Point"}
}