{
  "type": "Feature",
  "properties": {
    "iso:country":"GB",
    "sg:address":"36 Milford Road",
    "sg:city":"Lymington",
    "sg:classifiers":[
        {
            "category":"Cinema",
            "subcategory":"Movie Rental",
            "type":"Entertainment"
        }
    ],
    "sg:phone":"+44 1590 670101",
    "sg:postcode":"SO41 8DW",
    "sg:province":"Hampshire",
    "sg:tags":[
        "tv",
        "dvd",
        "video",
        "library"
    ],
    "sg:website":"http://www.visualvibes.com",
    "wof:name":"Visual Vibes",
    "wof:placetype":"venue"
},
  "geometry": {"coordinates":[-1.5526889563,50.7518463135],"type":"Point"}
}