{
  "type": "Feature",
  "properties": {
    "addr:full":"Staney Hill Offices, North Road, Lerwick Shetland Shetland Islands ZE1 0QW",
    "addr:postcode":"ze1 0qw",
    "addr:street":"Staney;North Road",
    "iso:country":"GB",
    "sg:address":"Staney Hill Offices, North Road, Lerwick",
    "sg:city":"Shetland",
    "sg:classifiers":[
        {
            "category":"Home & Garden",
            "subcategory":"Building Materials",
            "type":"Retail Goods"
        },
        {
            "category":"Building & Trades",
            "subcategory":"Construction",
            "type":"Services"
        }
    ],
    "sg:phone":"+44 1595 696508",
    "sg:postcode":"ZE1 0QW",
    "sg:province":"Shetland Islands",
    "sg:tags":[
        "insulation",
        "installers"
    ],
    "wof:name":"Shetland Heatwise Ltd",
    "wof:placetype":"venue"
},
  "geometry": {"coordinates":[-1.1628040075,60.1634368896],"type":"Point"}
}