{
  "type": "Feature",
  "properties": {
    "addr:full":"34 Canynge Square Bristol City of Bristol BS8 3LB",
    "addr:housenumber":"34",
    "addr:postcode":"bs8 3lb",
    "addr:street":"Canynge Square",
    "iso:country":"GB",
    "sg:address":"34 Canynge Square",
    "sg:city":"Bristol",
    "sg:classifiers":[
        {
            "category":"Professional",
            "subcategory":"Management & Consulting",
            "type":"Services"
        }
    ],
    "sg:postcode":"BS8 3LB",
    "sg:province":"City of Bristol",
    "sg:tags":[
        "consultant",
        "business"
    ],
    "wof:name":"Clifton Management Consultancy Ltd.",
    "wof:placetype":"venue"
},
  "geometry": {"coordinates":[-2.622466,51.459171],"type":"Point"}
}