{
  "type": "Feature",
  "properties": {
    "iso:country":"GB",
    "sg:address":"Madonna Villa, Oaks Road, Whitwick",
    "sg:city":"Coalville",
    "sg:classifiers":[
        {
            "category":"Education",
            "subcategory":"Special Training",
            "type":"Public Place"
        }
    ],
    "sg:postcode":"LE67 5UN",
    "sg:province":"Leicestershire",
    "sg:tags":[
        "product",
        "centre"
    ],
    "wof:name":"Keith Cook Training Services",
    "wof:placetype":"venue"
},
  "geometry": {"coordinates":[-1.354947,52.739853],"type":"Point"}
}