{
  "type": "Feature",
  "properties": {
    "addr:full":"16-17 Small St Bristol City of Bristol BS1 1DE",
    "addr:housenumber":"16-17",
    "addr:postcode":"bs1 1de",
    "addr:street":"Small St",
    "iso:country":"GB",
    "sg:address":"16-17 Small St",
    "sg:city":"Bristol",
    "sg:classifiers":[
        {
            "category":"Professional",
            "type":"Services"
        }
    ],
    "sg:phone":"+44 117 925 0624",
    "sg:postcode":"BS1 1DE",
    "sg:province":"City of Bristol",
    "sg:tags":[
        "caterer"
    ],
    "wof:name":"Fosters Dining Rooms Ltd",
    "wof:placetype":"venue"
},
  "geometry": {"coordinates":[-2.5948040485,51.4551544189],"type":"Point"}
}