{
  "type": "Feature",
  "properties": {
    "iso:country":"GB",
    "sg:address":"Crescent Grn",
    "sg:city":"Kendal",
    "sg:classifiers":[
        {
            "category":"Shopping",
            "subcategory":"Bicycles & Sporting Goods",
            "type":"Retail Goods"
        }
    ],
    "sg:phone":"+44 1539 724311",
    "sg:postcode":"LA9 6DR",
    "sg:province":"Cumbria",
    "sg:tags":[
        "riding",
        "saddlery",
        "wear"
    ],
    "wof:name":"W G Todd & Sons",
    "wof:placetype":"venue"
},
  "geometry": {"coordinates":[-2.7381,54.336552],"type":"Point"}
}