{
  "type": "Feature",
  "properties": {
    "addr:full":"The Banks, Staveley Kendal Cumbria LA8 9NE",
    "addr:postcode":"la8 9ne",
    "iso:country":"GB",
    "sg:address":"The Banks, Staveley",
    "sg:city":"Kendal",
    "sg:classifiers":[
        {
            "category":"Travel",
            "subcategory":"Hotels & Motels",
            "type":"Entertainment"
        }
    ],
    "sg:postcode":"LA8 9NE",
    "sg:province":"Cumbria",
    "wof:name":"Railway Hotel",
    "wof:placetype":"venue"
},
  "geometry": {"coordinates":[-2.819247,54.372185],"type":"Point"}
}