{
  "type": "Feature",
  "properties": {
    "iso:country":"GB",
    "sg:address":"6 Dawson Avenue",
    "sg:city":"Wigan",
    "sg:classifiers":[
        {
            "category":"Building & Trades",
            "subcategory":"Construction",
            "type":"Services"
        }
    ],
    "sg:phone":"+44 1942 247182",
    "sg:postcode":"WN6 8QN",
    "sg:province":"Lancashire",
    "sg:tags":[
        "builder"
    ],
    "wof:name":"Houghton & Son",
    "wof:placetype":"venue"
},
  "geometry": {"coordinates":[-2.644789,53.561249],"type":"Point"}
}