{
  "type": "Feature",
  "properties": {
    "addr:full":"343 Whessoe Road Darlington Durham DL3 0RW",
    "addr:housenumber":"343",
    "addr:postcode":"dl3 0rw",
    "addr:street":"Whessoe Road",
    "iso:country":"GB",
    "sg:address":"343 Whessoe Road",
    "sg:city":"Darlington",
    "sg:classifiers":[
        {
            "category":"Organizations",
            "subcategory":"Membership Organization",
            "type":"Services"
        }
    ],
    "sg:phone":"+44 1325 288458",
    "sg:postcode":"DL3 0RW",
    "sg:province":"Durham",
    "sg:tags":[
        "club"
    ],
    "wof:name":"Darlington Bridge Club",
    "wof:placetype":"venue"
},
  "geometry": {"coordinates":[-1.556368947,54.537651062],"type":"Point"}
}