{
  "type": "Feature",
  "properties": {
    "iso:country":"GB",
    "sg:address":"Rodbourne Rd",
    "sg:city":"Swindon",
    "sg:classifiers":[
        {
            "category":"Building & Trades",
            "subcategory":"Construction",
            "type":"Services"
        }
    ],
    "sg:phone":"+44 1793 874571",
    "sg:postcode":"SN2 2AG",
    "sg:province":"Wiltshire",
    "sg:tags":[
        "contractor",
        "paving",
        "driveway"
    ],
    "wof:name":"Patio Specialist",
    "wof:placetype":"venue"
},
  "geometry": {"coordinates":[-1.8013190031,51.5672798157],"type":"Point"}
}