{
  "type": "Feature",
  "properties": {
    "iso:country":"GB",
    "sg:address":"Eastfield Farm, Edwinstowe",
    "sg:city":"Mansfield",
    "sg:classifiers":[
        {
            "category":"Home & Garden",
            "subcategory":"Garden Supply",
            "type":"Retail Goods"
        },
        {
            "category":"Farming",
            "subcategory":"Livestock Farm",
            "type":"Manufacturing & Wholesale Goods"
        }
    ],
    "sg:postcode":"NG21 9JJ",
    "sg:province":"Nottinghamshire",
    "sg:tags":[
        "bulb",
        "grower",
        "others"
    ],
    "wof:name":"Peter F Wilson",
    "wof:placetype":"venue"
},
  "geometry": {"coordinates":[-1.068123,53.194969],"type":"Point"}
}