{
  "type": "Feature",
  "properties": {
    "iso:country":"GB",
    "sg:address":"Rear Of 8 Wyken Grange Rd",
    "sg:city":"Coventry",
    "sg:classifiers":[
        {
            "category":"Building & Trades",
            "subcategory":"Construction",
            "type":"Services"
        }
    ],
    "sg:postcode":"CV2 3BS",
    "sg:province":"Warwickshire",
    "sg:tags":[
        "builder"
    ],
    "wof:name":"First Choice Property Repairs",
    "wof:placetype":"venue"
},
  "geometry": {"coordinates":[-1.4648400545,52.4167900085],"type":"Point"}
}