{
  "type": "Feature",
  "properties": {
    "iso:country":"GB",
    "sg:address":"45 Eastbourne Gardens",
    "sg:city":"Whitley Bay",
    "sg:classifiers":[
        {
            "category":"Food & Beverages",
            "subcategory":"Bakery",
            "type":"Retail Goods"
        }
    ],
    "sg:phone":"+44 191 252 1883",
    "sg:postcode":"NE26 1PY",
    "sg:province":"Northumberland",
    "sg:tags":[
        "shop",
        "baker"
    ],
    "wof:name":"J Scott & Co",
    "wof:placetype":"venue"
},
  "geometry": {"coordinates":[-1.4536390305,55.0471916199],"type":"Point"}
}