{
  "type": "Feature",
  "properties": {
    "addr:full":"Crampmoor Farm, Crampmoor Lane, Crampmoor Romsey Hampshire SO51 9AJ",
    "addr:postcode":"so51 9aj",
    "addr:street":"Crampmoor Lane Crampmoor",
    "iso:country":"GB",
    "sg:address":"Crampmoor Farm, Crampmoor Lane, Crampmoor",
    "sg:city":"Romsey",
    "sg:classifiers":[
        {
            "category":"Farming",
            "subcategory":"Farm",
            "type":"Manufacturing & Wholesale Goods"
        }
    ],
    "sg:phone":"+44 1794 513815",
    "sg:postcode":"SO51 9AJ",
    "sg:province":"Hampshire",
    "sg:tags":[
        "hatchery"
    ],
    "wof:name":"Crampmoor Fish Farm",
    "wof:placetype":"venue"
},
  "geometry": {"coordinates":[-1.4614640474,50.9979896545],"type":"Point"}
}