{
  "type": "Feature",
  "properties": {
    "addr:full":"Red House, The Green, Frampton-on-severn Gloucester Gloucestershire GL2 7EP",
    "addr:postcode":"gl2 7ep",
    "addr:street":"The Green",
    "iso:country":"GB",
    "sg:address":"Red House, The Green, Frampton-on-severn",
    "sg:city":"Gloucester",
    "sg:classifiers":[
        {
            "category":"Professional",
            "type":"Services"
        }
    ],
    "sg:phone":"+44 1452 741391",
    "sg:postcode":"GL2 7EP",
    "sg:province":"Gloucestershire",
    "sg:tags":[
        "interior",
        "furnishers",
        "designer"
    ],
    "wof:name":"Angel Price",
    "wof:placetype":"venue"
},
  "geometry": {"coordinates":[-2.3622090816,51.7718887329],"type":"Point"}
}