{
  "type": "Feature",
  "properties": {
    "addr:full":"Nant Y Rhiw, Llanddoged Road Llanrwst Conwy LL26 0YU",
    "addr:postcode":"ll26 0yu",
    "addr:street":"Llanddoged Road",
    "iso:country":"GB",
    "sg:address":"Nant Y Rhiw, Llanddoged Road",
    "sg:city":"Llanrwst",
    "sg:classifiers":[
        {
            "category":"Shopping",
            "subcategory":"Pharmacy",
            "type":"Retail Goods"
        }
    ],
    "sg:phone":"+44 1492 640234",
    "sg:postcode":"LL26 0YU",
    "sg:province":"Conwy",
    "sg:tags":[
        "toiletry"
    ],
    "wof:name":"Snowdon Heather Perfumery Co.",
    "wof:placetype":"venue"
},
  "geometry": {"coordinates":[-3.7980830669,53.1459732056],"type":"Point"}
}