{
  "type": "Feature",
  "properties": {
    "iso:country":"GB",
    "sg:address":"19 Plashet Gro",
    "sg:city":"London",
    "sg:classifiers":[
        {
            "category":"Professional",
            "subcategory":"Lawyer & Legal Services",
            "type":"Services"
        }
    ],
    "sg:phone":"+44 20 8472 4462",
    "sg:postcode":"E6 1AD",
    "sg:province":"Greater London",
    "sg:tags":[
        "solicitor"
    ],
    "wof:name":"Aina Khan Partnership (Solicitors)",
    "wof:placetype":"venue"
},
  "geometry": {"coordinates":[0.035233,51.537411],"type":"Point"}
}