{
  "type": "Feature",
  "properties": {
    "addr:full":"79 Church Street Crowthorne Berkshire RG45 7EW",
    "addr:housenumber":"79",
    "addr:postcode":"rg45 7ew",
    "addr:street":"Church Street",
    "iso:country":"GB",
    "sg:address":"79 Church Street",
    "sg:city":"Crowthorne",
    "sg:classifiers":[
        {
            "category":"Shopping",
            "subcategory":"Clothing, Apparel, & Fashions",
            "type":"Retail Goods"
        }
    ],
    "sg:phone":"+44 1344 778883",
    "sg:postcode":"RG45 7EW",
    "sg:province":"Berkshire",
    "sg:tags":[
        "dresswear"
    ],
    "wof:name":"Healey Menswear",
    "wof:placetype":"venue"
},
  "geometry": {"coordinates":[-0.7953450084,51.3672103882],"type":"Point"}
}