{
  "type": "Feature",
  "properties": {
    "iso:country":"GB",
    "sg:address":"Park Farm, Herringswell",
    "sg:city":"Bury St Edmunds",
    "sg:classifiers":[
        {
            "category":"Farming",
            "subcategory":"Livestock Farm",
            "type":"Manufacturing & Wholesale Goods"
        },
        {
            "category":"Farming",
            "subcategory":"Farm",
            "type":"Manufacturing & Wholesale Goods"
        }
    ],
    "sg:phone":"+44 1638 750317",
    "sg:postcode":"IP28 6SR",
    "sg:province":"Cambridgeshire",
    "sg:tags":[
        "mixed",
        "others"
    ],
    "wof:name":"Upton Suffolk Farms",
    "wof:placetype":"venue"
},
  "geometry": {"coordinates":[0.51618,52.301159],"type":"Point"}
}