{
  "type": "Feature",
  "properties": {
    "addr:full":"11-17 Dudley Rd Stourbridge West Midlands DY9 8EX",
    "addr:housenumber":"11-17",
    "addr:postcode":"dy9 8ex",
    "addr:street":"Dudley Rd",
    "iso:country":"GB",
    "sg:address":"11-17 Dudley Rd",
    "sg:city":"Stourbridge",
    "sg:classifiers":[
        {
            "category":"Autos & Motor Vehicles",
            "subcategory":"Automobile Sales",
            "type":"Retail Goods"
        }
    ],
    "sg:postcode":"DY9 8EX",
    "sg:province":"West Midlands",
    "sg:tags":[
        "car"
    ],
    "wof:name":"Lye Car Sales",
    "wof:placetype":"venue"
},
  "geometry": {"coordinates":[-2.1176578999,52.458152771],"type":"Point"}
}