{
  "type": "Feature",
  "properties": {
    "addr:full":"51 Earlsdon Avenue Middlesbrough North Yorkshire TS5 8SZ",
    "addr:housenumber":"51",
    "addr:postcode":"ts5 8sz",
    "addr:street":"Earlsdon Avenue",
    "iso:country":"GB",
    "sg:address":"51 Earlsdon Avenue",
    "sg:city":"Middlesbrough",
    "sg:classifiers":[
        {
            "category":"Retail",
            "subcategory":"Driving School",
            "type":"Services"
        }
    ],
    "sg:phone":"+44 1642 827169",
    "sg:postcode":"TS5 8SZ",
    "sg:province":"North Yorkshire",
    "wof:name":"County School Of Motoring",
    "wof:placetype":"venue"
},
  "geometry": {"coordinates":[-1.2547290325,54.5359153748],"type":"Point"}
}