{
  "type": "Feature",
  "properties": {
    "addr:full":"113 Wennington Road Rainham Essex RM13 9TH",
    "addr:housenumber":"113",
    "addr:postcode":"rm13 9th",
    "addr:street":"Wennington Road",
    "iso:country":"GB",
    "sg:address":"113 Wennington Road",
    "sg:city":"Rainham",
    "sg:classifiers":[
        {
            "category":"Retail",
            "subcategory":"Auto Rental",
            "type":"Services"
        }
    ],
    "sg:phone":"+44 1708 556775",
    "sg:postcode":"RM13 9TH",
    "sg:province":"Essex",
    "sg:tags":[
        "car"
    ],
    "wof:name":"Wennington Car & Van Hire",
    "wof:placetype":"venue"
},
  "geometry": {"coordinates":[0.195004,51.516888],"type":"Point"}
}