{
  "type": "Feature",
  "properties": {
    "addr:full":"15 Baildon Walk Leeds West Yorkshire LS14 2BW",
    "addr:housenumber":"15",
    "addr:postcode":"ls14 2bw",
    "addr:street":"Baildon Walk",
    "iso:country":"GB",
    "sg:address":"15 Baildon Walk",
    "sg:city":"Leeds",
    "sg:classifiers":[
        {
            "category":"Building & Trades",
            "subcategory":"Construction",
            "type":"Services"
        }
    ],
    "sg:phone":"+44 113 265 3793",
    "sg:postcode":"LS14 2BW",
    "sg:province":"West Yorkshire",
    "sg:tags":[
        "guttering"
    ],
    "wof:name":"1st Call Safe Shield Builders",
    "wof:placetype":"venue"
},
  "geometry": {"coordinates":[-1.4540669918,53.8291015625],"type":"Point"}
}