{
  "type": "Feature",
  "properties": {
    "iso:country":"GB",
    "sg:address":"10b High Street, Market Weighton",
    "sg:city":"York",
    "sg:classifiers":[
        {
            "category":"Food & Beverages",
            "subcategory":"Meat & Fish",
            "type":"Retail Goods"
        }
    ],
    "sg:phone":"+44 1430 873999",
    "sg:postcode":"YO43 3AH",
    "sg:province":"East Riding of Yorkshire",
    "sg:tags":[
        "butcher"
    ],
    "wof:name":"Hagston Family Butchers",
    "wof:placetype":"venue"
},
  "geometry": {"coordinates":[-0.665374,53.864212],"type":"Point"}
}