{
  "type": "Feature",
  "properties": {
    "addr:full":"8 North Gardner Street Glasgow Glasgow City G11 5BT",
    "addr:housenumber":"8",
    "addr:postcode":"g11 5bt",
    "addr:street":"North Gardner Street",
    "iso:country":"GB",
    "sg:address":"8 North Gardner Street",
    "sg:city":"Glasgow",
    "sg:classifiers":[
        {
            "category":"Professional",
            "subcategory":"Business Services",
            "type":"Services"
        }
    ],
    "sg:phone":"+44 141 357 6922",
    "sg:postcode":"G11 5BT",
    "sg:province":"Glasgow City",
    "sg:tags":[
        "publishers'"
    ],
    "wof:name":"Check Point Editorial Ltd.",
    "wof:placetype":"venue"
},
  "geometry": {"coordinates":[-4.305576,55.874588],"type":"Point"}
}