{
  "type": "Feature",
  "properties": {
    "addr:full":"Unit 20 The Yorkshire Outlet Doncaster South Yorkshire DN4 5PH",
    "addr:housenumber":"unit 20",
    "addr:postcode":"dn4 5ph",
    "addr:street":"The;Doncaster South",
    "iso:country":"GB",
    "sg:address":"Unit 20 The Yorkshire Outlet",
    "sg:city":"Doncaster",
    "sg:classifiers":[
        {
            "category":"Shopping",
            "subcategory":"Clothing, Apparel, & Fashions",
            "type":"Retail Goods"
        }
    ],
    "sg:phone":"+44 1302 367082",
    "sg:postcode":"DN4 5PH",
    "sg:province":"South Yorkshire",
    "sg:tags":[
        "ladieswear"
    ],
    "wof:name":"Dorsub (Dpr) Ltd.",
    "wof:placetype":"venue"
},
  "geometry": {"coordinates":[-1.0948690176,53.5140838623],"type":"Point"}
}