{
  "type": "Feature",
  "properties": {
    "addr:full":"The Pavilion, Dudley Rd Walton On Thames Surrey KT12 2JY",
    "addr:postcode":"kt12 2jy",
    "addr:street":"Dudley Rd",
    "iso:country":"GB",
    "sg:address":"The Pavilion, Dudley Rd",
    "sg:city":"Walton On Thames",
    "sg:classifiers":[
        {
            "category":"Arena",
            "subcategory":"Sports Club",
            "type":"Entertainment"
        }
    ],
    "sg:phone":"+44 1932 224215",
    "sg:postcode":"KT12 2JY",
    "sg:province":"Surrey",
    "wof:name":"Thames Valley Skiff Club",
    "wof:placetype":"venue"
},
  "geometry": {"coordinates":[-0.4207040071,51.3843460083],"type":"Point"}
}