{
  "type": "Feature",
  "properties": {
    "addr:full":"7-8 Curran Rd Cardiff Cardiff CF1 5DF",
    "addr:housenumber":"7-8",
    "addr:postcode":"cf1 5df",
    "addr:street":"Curran Rd",
    "iso:country":"GB",
    "sg:address":"7-8 Curran Rd",
    "sg:city":"Cardiff",
    "sg:classifiers":[
        {
            "category":"Professional",
            "subcategory":"Engineering",
            "type":"Services"
        }
    ],
    "sg:phone":"+44 29 2066 6910",
    "sg:postcode":"CF1 5DF",
    "sg:province":"Cardiff",
    "sg:tags":[
        "engineer"
    ],
    "wof:name":"European Lubricant Supplies Ltd",
    "wof:placetype":"venue"
},
  "geometry": {"coordinates":[-3.1769180298,51.4717102051],"type":"Point"}
}