{
  "type": "Feature",
  "properties": {
    "addr:full":"Cymerau Farm, Aberllefenni Machynlleth Ceredigion SY20 9RZ",
    "addr:postcode":"sy20 9rz",
    "iso:country":"GB",
    "sg:address":"Cymerau Farm, Aberllefenni",
    "sg:city":"Machynlleth",
    "sg:classifiers":[
        {
            "category":"Farming",
            "subcategory":"Livestock Farm",
            "type":"Manufacturing & Wholesale Goods"
        }
    ],
    "sg:phone":"+44 1654 761684",
    "sg:postcode":"SY20 9RZ",
    "sg:province":"Ceredigion",
    "sg:tags":[
        "others"
    ],
    "wof:name":"E Jones & Sons",
    "wof:placetype":"venue"
},
  "geometry": {"coordinates":[-3.819908,52.673183],"type":"Point"}
}