{
  "type": "Feature",
  "properties": {
    "addr:full":"6 Llwynypia Road Tonypandy Rhondda, Cynon, Taff CF40 2EL",
    "addr:housenumber":"6",
    "addr:postcode":"cf40 2el",
    "addr:street":"Llwynypia Road;Cynon Taff",
    "iso:country":"GB",
    "sg:address":"6 Llwynypia Road",
    "sg:city":"Tonypandy",
    "sg:classifiers":[
        {
            "category":"Retail",
            "subcategory":"Repair Shop",
            "type":"Services"
        }
    ],
    "sg:phone":"+44 1443 430658",
    "sg:postcode":"CF40 2EL",
    "sg:province":"Rhondda, Cynon, Taff",
    "sg:tags":[
        "television",
        "good",
        "video",
        "servicing",
        "maintenance",
        "radio"
    ],
    "wof:name":"It's Magic",
    "wof:placetype":"venue"
},
  "geometry": {"coordinates":[-3.4573640823,51.6259841919],"type":"Point"}
}