{
  "type": "Feature",
  "properties": {
    "addr:full":"Fenview, Doddington March Cambridgeshire PE15 0SN",
    "addr:postcode":"pe15 0sn",
    "addr:street":"March",
    "iso:country":"GB",
    "sg:address":"Fenview, Doddington",
    "sg:city":"March",
    "sg:classifiers":[
        {
            "category":"Communications",
            "type":"Services"
        }
    ],
    "sg:postcode":"PE15 0SN",
    "sg:province":"Cambridgeshire",
    "sg:tags":[
        "system",
        "music",
        "public",
        "address"
    ],
    "wof:name":"Ace Communications",
    "wof:placetype":"venue"
},
  "geometry": {"coordinates":[0.0620899983,52.4968109131],"type":"Point"}
}