{
  "type": "Feature",
  "properties": {
    "iso:country":"GB",
    "sg:address":"47 High St, Rainham",
    "sg:city":"Gillingham",
    "sg:classifiers":[
        {
            "category":"Professional",
            "subcategory":"Art Services",
            "type":"Services"
        }
    ],
    "sg:postcode":"ME8 7HS",
    "sg:province":"Kent",
    "sg:tags":[
        "framing"
    ],
    "wof:name":"Art's Delight",
    "wof:placetype":"venue"
},
  "geometry": {"coordinates":[0.6062150002,51.3640594482],"type":"Point"}
}