{
  "type": "Feature",
  "properties": {
    "addr:full":"37 Bucklersbury Hitchin Bedfordshire SG5 1BG",
    "addr:housenumber":"37",
    "addr:postcode":"sg5 1bg",
    "addr:street":"Bucklersbury",
    "iso:country":"GB",
    "sg:address":"37 Bucklersbury",
    "sg:city":"Hitchin",
    "sg:classifiers":[
        {
            "category":"Personal",
            "subcategory":"Beauty Salon",
            "type":"Services"
        }
    ],
    "sg:postcode":"SG5 1BG",
    "sg:province":"Bedfordshire",
    "sg:tags":[
        "unisex",
        "hairdresser"
    ],
    "wof:name":"Headlands",
    "wof:placetype":"venue"
},
  "geometry": {"coordinates":[-0.279571,51.947025],"type":"Point"}
}