{
  "type": "Feature",
  "properties": {
    "addr:full":"Keighley Road, Illingworth Halifax West Yorkshire HX2 8BA",
    "addr:postcode":"hx2 8ba",
    "addr:street":"Keighley Road",
    "iso:country":"GB",
    "sg:address":"Keighley Road, Illingworth",
    "sg:city":"Halifax",
    "sg:classifiers":[
        {
            "category":"Organizations",
            "subcategory":"Membership Organization",
            "type":"Services"
        }
    ],
    "sg:phone":"+44 1422 249096",
    "sg:postcode":"HX2 8BA",
    "sg:province":"West Yorkshire",
    "sg:tags":[
        "club"
    ],
    "wof:name":"Illingworth Sports Club",
    "wof:placetype":"venue"
},
  "geometry": {"coordinates":[-1.8956739902,53.7642631531],"type":"Point"}
}