{
  "type": "Feature",
  "properties": {
    "iso:country":"GB",
    "sg:address":"277 North High Street",
    "sg:city":"Musselburgh",
    "sg:classifiers":[
        {
            "category":"Banks & Credit Unions",
            "subcategory":"Bank",
            "type":"Services"
        },
        {
            "category":"Banks & Credit Unions",
            "subcategory":"Financial Services",
            "type":"Services"
        }
    ],
    "sg:phone":"+44 131 665 7771",
    "sg:postcode":"EH21 6BQ",
    "sg:province":"City of Edinburgh",
    "sg:tags":[
        "agent",
        "tied",
        "institution"
    ],
    "wof:name":"RODDY LAWRIE",
    "wof:placetype":"venue"
},
  "geometry": {"coordinates":[-3.066259,55.944126],"type":"Point"}
}