{
  "type": "Feature",
  "properties": {
    "iso:country":"GB",
    "sg:address":"Unit 4 Stn Yd",
    "sg:city":"Burntisland",
    "sg:classifiers":[
        {
            "category":"Building & Trades",
            "subcategory":"Construction",
            "type":"Services"
        }
    ],
    "sg:postcode":"KY3 9TL",
    "sg:province":"Fife",
    "sg:tags":[
        "joiner",
        "carpenter"
    ],
    "wof:name":"Chip'n'dale",
    "wof:placetype":"venue"
},
  "geometry": {"coordinates":[-3.204039,56.07238],"type":"Point"}
}