{
  "type": "Feature",
  "properties": {
    "iso:country":"GB",
    "sg:address":"34 Bridge Street",
    "sg:city":"St Helens",
    "sg:classifiers":[
        {
            "category":"Professional",
            "subcategory":"Art Services",
            "type":"Services"
        }
    ],
    "sg:phone":"+44 1744 739660",
    "sg:postcode":"WA10 1NW",
    "sg:province":"Merseyside",
    "sg:tags":[
        "framing"
    ],
    "wof:name":"Rennies Arts & Crafts Ltd.",
    "wof:placetype":"venue"
},
  "geometry": {"coordinates":[-2.7383260727,53.4522018433],"type":"Point"}
}