{
  "type": "Feature",
  "properties": {
    "addr:full":"Speldhurst Nurseries, Langton Road Tunbridge Wells East Sussex TN3 0NR",
    "addr:housenumber":"speldhurst",
    "addr:postcode":"tn3 0nr",
    "addr:street":"Langton Road",
    "iso:country":"GB",
    "sg:address":"Speldhurst Nurseries, Langton Road",
    "sg:city":"Tunbridge Wells",
    "sg:classifiers":[
        {
            "category":"Home & Garden",
            "subcategory":"Garden Supply",
            "type":"Retail Goods"
        }
    ],
    "sg:phone":"+44 1892 862682",
    "sg:postcode":"TN3 0NR",
    "sg:province":"East Sussex",
    "sg:tags":[
        "nursery",
        "centre"
    ],
    "wof:name":"Vistas Ltd.",
    "wof:placetype":"venue"
},
  "geometry": {"coordinates":[0.220383,51.150982],"type":"Point"}
}