{
  "type": "Feature",
  "properties": {
    "addr:full":"2 St. Petrocs Meadow Padstow Cornwall PL28 8HB",
    "addr:housenumber":"2",
    "addr:postcode":"pl28 8hb",
    "addr:street":"St. Petrocs Meadow",
    "iso:country":"GB",
    "sg:address":"2 St. Petrocs Meadow",
    "sg:city":"Padstow",
    "sg:classifiers":[
        {
            "category":"Professional",
            "subcategory":"Engineering",
            "type":"Services"
        }
    ],
    "sg:postcode":"PL28 8HB",
    "sg:province":"Cornwall",
    "sg:tags":[
        "contractor",
        "electrical",
        "engineer"
    ],
    "wof:name":"Kitto,Ron,",
    "wof:placetype":"venue"
},
  "geometry": {"coordinates":[-4.947528,50.538521],"type":"Point"}
}