{
  "type": "Feature",
  "properties": {
    "iso:country":"GB",
    "sg:address":"7 The Oval",
    "sg:city":"Hereford",
    "sg:classifiers":[
        {
            "category":"Government",
            "subcategory":"Post Office",
            "type":"Public Place"
        }
    ],
    "sg:phone":"+44 1432 265231",
    "sg:postcode":"HR2 7HG",
    "sg:province":"Herefordshire",
    "wof:name":"Oval Post Office",
    "wof:placetype":"venue"
},
  "geometry": {"coordinates":[-2.730753,52.043209],"type":"Point"}
}