{
  "type": "Feature",
  "properties": {
    "addr:full":"72 Mansfield Road Bellshill North Lanarkshire ML4 3AQ",
    "addr:housenumber":"72",
    "addr:postcode":"ml4 3aq",
    "addr:street":"Mansfield Road",
    "iso:country":"GB",
    "sg:address":"72 Mansfield Road",
    "sg:city":"Bellshill",
    "sg:classifiers":[
        {
            "category":"Food & Beverages",
            "subcategory":"Fruits & Vegetables",
            "type":"Retail Goods"
        }
    ],
    "sg:phone":"+44 1698 747759",
    "sg:postcode":"ML4 3AQ",
    "sg:province":"North Lanarkshire",
    "sg:tags":[
        "greengrocer"
    ],
    "wof:name":"Shop & Save",
    "wof:placetype":"venue"
},
  "geometry": {"coordinates":[-4.0303769112,55.8138427734],"type":"Point"}
}