{
  "type": "Feature",
  "properties": {
    "addr:full":"12 Church Rd, Catshill Bromsgrove Worcestershire B61 0JY",
    "addr:housenumber":"12",
    "addr:postcode":"b61 0jy",
    "addr:street":"Church Rd Catshill",
    "iso:country":"GB",
    "sg:address":"12 Church Rd, Catshill",
    "sg:city":"Bromsgrove",
    "sg:classifiers":[
        {
            "category":"Farming",
            "subcategory":"Livestock Farm",
            "type":"Manufacturing & Wholesale Goods"
        }
    ],
    "sg:postcode":"B61 0JY",
    "sg:province":"Worcestershire",
    "sg:tags":[
        "breeder"
    ],
    "wof:name":"Blackmore,G E,",
    "wof:placetype":"venue"
},
  "geometry": {"coordinates":[-2.0635120869,52.3635826111],"type":"Point"}
}