{
  "type": "Feature",
  "properties": {
    "addr:full":"Unit 22, Barton Hill Trading Estate Bristol City of Bristol BS5 9RD",
    "addr:housenumber":"unit 22",
    "addr:postcode":"bs5 9rd",
    "addr:street":"Barton Hill Trading Estate",
    "iso:country":"GB",
    "sg:address":"Unit 22, Barton Hill Trading Estate",
    "sg:city":"Bristol",
    "sg:classifiers":[
        {
            "category":"Shopping",
            "type":"Retail Goods"
        }
    ],
    "sg:phone":"+44 117 955 3166",
    "sg:postcode":"BS5 9RD",
    "sg:province":"City of Bristol",
    "sg:tags":[
        "part",
        "accessory"
    ],
    "wof:name":"S P A (Bristol) Ltd.",
    "wof:placetype":"venue"
},
  "geometry": {"coordinates":[-2.563032,51.452675],"type":"Point"}
}