{
  "type": "Feature",
  "properties": {
    "addr:full":"2 Yateley Court, Hayes Lane Kenley Surrey CR8 5JS",
    "addr:housenumber":"2",
    "addr:postcode":"cr8 5js",
    "addr:street":"Yateley Court Hayes Lane",
    "iso:country":"GB",
    "sg:address":"2 Yateley Court, Hayes Lane",
    "sg:city":"Kenley",
    "sg:classifiers":[
        {
            "category":"Professional",
            "subcategory":"Engineering",
            "type":"Services"
        }
    ],
    "sg:postcode":"CR8 5JS",
    "sg:province":"Surrey",
    "sg:tags":[
        "consultant",
        "structural"
    ],
    "wof:name":"J F Davenport",
    "wof:placetype":"venue"
},
  "geometry": {"coordinates":[-0.1016670018,51.3255653381],"type":"Point"}
}