{
  "type": "Feature",
  "properties": {
    "addr:full":"96-98 Merseyway Stockport Cheshire SK1 1QN",
    "addr:housenumber":"96-98",
    "addr:postcode":"sk1 1qn",
    "addr:street":"Merseyway Stockport",
    "iso:country":"GB",
    "sg:address":"96-98 Merseyway",
    "sg:city":"Stockport",
    "sg:classifiers":[
        {
            "category":"Shopping",
            "subcategory":"Bicycles & Sporting Goods",
            "type":"Retail Goods"
        }
    ],
    "sg:phone":"+44 161 480 6831",
    "sg:postcode":"SK1 1QN",
    "sg:province":"Cheshire",
    "sg:tags":[
        "equipment",
        "camping"
    ],
    "wof:name":"Millets The Outdoor Store",
    "wof:placetype":"venue"
},
  "geometry": {"coordinates":[-2.159933,53.411232],"type":"Point"}
}