{
  "type": "Feature",
  "properties": {
    "addr:full":"114 Westmead Road Sutton Surrey SM1 4JH",
    "addr:housenumber":"114",
    "addr:postcode":"sm1 4jh",
    "addr:street":"Westmead Road",
    "iso:country":"GB",
    "sg:address":"114 Westmead Road",
    "sg:city":"Sutton",
    "sg:classifiers":[
        {
            "category":"Fast Food",
            "type":"Food & Drink"
        }
    ],
    "sg:phone":"+44 20 8770 3737",
    "sg:postcode":"SM1 4JH",
    "sg:province":"Surrey",
    "sg:tags":[
        "away",
        "take"
    ],
    "wof:name":"Barbecue Pit",
    "wof:placetype":"venue"
},
  "geometry": {"coordinates":[-0.1793490052,51.366230011],"type":"Point"}
}