{
  "type": "Feature",
  "properties": {
    "iso:country":"GB",
    "sg:address":"Kennel Lane",
    "sg:city":"Windlesham",
    "sg:classifiers":[
        {
            "category":"Arena",
            "subcategory":"Sports Club",
            "type":"Entertainment"
        }
    ],
    "sg:phone":"+44 1276 476174",
    "sg:postcode":"GU20 6AA",
    "sg:province":"Surrey",
    "wof:name":"Windlesham Bowls Club",
    "wof:placetype":"venue"
},
  "geometry": {"coordinates":[-0.660449,51.368755],"type":"Point"}
}