{
  "type": "Feature",
  "properties": {
    "addr:full":"6 Cirrus Square, Glebe Road Huntingdon Cambridgeshire PE29 7DF",
    "addr:housenumber":"6",
    "addr:postcode":"pe29 7df",
    "addr:street":"Cirrus Square Glebe Road",
    "iso:country":"GB",
    "sg:address":"6 Cirrus Square, Glebe Road",
    "sg:city":"Huntingdon",
    "sg:classifiers":[
        {
            "category":"Professional",
            "subcategory":"Printing & Photocopies",
            "type":"Services"
        }
    ],
    "sg:phone":"+44 1480 411311",
    "sg:postcode":"PE29 7DF",
    "sg:province":"Cambridgeshire",
    "sg:tags":[
        "embroiderer"
    ],
    "wof:name":"P & M Embroidery",
    "wof:placetype":"venue"
},
  "geometry": {"coordinates":[-0.189304,52.33514],"type":"Point"}
}