{
  "type": "Feature",
  "properties": {
    "addr:full":"34-36 Woodfield Road Blackpool Lancashire FY1 6AX",
    "addr:housenumber":"34-36",
    "addr:postcode":"fy1 6ax",
    "addr:street":"Woodfield Road",
    "iso:country":"GB",
    "sg:address":"34-36 Woodfield Road",
    "sg:city":"Blackpool",
    "sg:classifiers":[
        {
            "category":"Travel",
            "subcategory":"Hotels & Motels",
            "type":"Entertainment"
        }
    ],
    "sg:phone":"+44 1253 346929",
    "sg:postcode":"FY1 6AX",
    "sg:province":"Lancashire",
    "wof:name":"New Edmond Hotel",
    "wof:placetype":"venue"
},
  "geometry": {"coordinates":[-3.052852,53.803711],"type":"Point"}
}