{
  "type": "Feature",
  "properties": {
    "addr:full":"73 Chislehurst Rd Orpington Kent BR6 0DQ",
    "addr:housenumber":"73",
    "addr:postcode":"br6 0dq",
    "addr:street":"Chislehurst Rd",
    "iso:country":"GB",
    "sg:address":"73 Chislehurst Rd",
    "sg:city":"Orpington",
    "sg:classifiers":[
        {
            "category":"Building & Trades",
            "subcategory":"Construction",
            "type":"Services"
        }
    ],
    "sg:phone":"+44 1689 874840",
    "sg:postcode":"BR6 0DQ",
    "sg:province":"Kent",
    "sg:tags":[
        "builder"
    ],
    "wof:name":"Windsor E & Son",
    "wof:placetype":"venue"
},
  "geometry": {"coordinates":[0.100440003,51.3814048767],"type":"Point"}
}