{
  "type": "Feature",
  "properties": {
    "iso:country":"GB",
    "sg:address":"15 Salter Row",
    "sg:city":"Pontefract",
    "sg:classifiers":[
        {
            "category":"Shopping",
            "subcategory":"Catalog Store",
            "type":"Retail Goods"
        }
    ],
    "sg:phone":"+44 845 165 7035",
    "sg:postcode":"WF8 1BA",
    "sg:province":"North Yorkshire",
    "sg:tags":[
        "shop",
        "catalogue",
        "showroom"
    ],
    "sg:website":"http://www.argos.co.uk",
    "wof:name":"Argos Ltd",
    "wof:placetype":"venue"
},
  "geometry": {"coordinates":[-1.311792016,53.6919174194],"type":"Point"}
}