{
  "type": "Feature",
  "properties": {
    "iso:country":"GB",
    "sg:address":"Weymouth Street",
    "sg:city":"Leicester",
    "sg:classifiers":[
        {
            "category":"Community Center",
            "type":"Public Place"
        },
        {
            "category":"Organizations",
            "subcategory":"Community Association",
            "type":"Services"
        }
    ],
    "sg:phone":"+44 116 268 0147",
    "sg:postcode":"LE4 6FN",
    "sg:province":"Leicestershire",
    "sg:tags":[
        "associations",
        "centre",
        "housing",
        "co-operatives",
        "trust",
        "societies"
    ],
    "wof:name":"ST. ALBANS COMMUNITY CENTRE",
    "wof:placetype":"venue"
},
  "geometry": {"coordinates":[-1.117299,52.648205],"type":"Point"}
}