{
  "type": "Feature",
  "properties": {
    "addr:full":"Newlands Cottage, Millpool Bodmin Cornwall PL30 4HZ",
    "addr:postcode":"pl30 4hz",
    "addr:street":"Millpool",
    "iso:country":"GB",
    "sg:address":"Newlands Cottage, Millpool",
    "sg:city":"Bodmin",
    "sg:classifiers":[
        {
            "category":"Building & Trades",
            "subcategory":"Construction",
            "type":"Services"
        }
    ],
    "sg:phone":"+44 1208 821438",
    "sg:postcode":"PL30 4HZ",
    "sg:province":"Cornwall",
    "sg:tags":[
        "builder"
    ],
    "wof:name":"P & M Blendell",
    "wof:placetype":"venue"
},
  "geometry": {"coordinates":[-4.6529388428,50.5036735535],"type":"Point"}
}