{
  "type": "Feature",
  "properties": {
    "iso:country":"GB",
    "sg:address":"30a Macdonald Street",
    "sg:city":"Birmingham",
    "sg:classifiers":[
        {
            "category":"Retail",
            "subcategory":"Auto Repair",
            "type":"Services"
        }
    ],
    "sg:phone":"+44 121 622 4749",
    "sg:postcode":"B5 6TG",
    "sg:province":"West Midlands",
    "sg:tags":[
        "electrical",
        "centre"
    ],
    "wof:name":"Mark Mason",
    "wof:placetype":"venue"
},
  "geometry": {"coordinates":[-1.89168,52.4701],"type":"Point"}
}