{
  "type": "Feature",
  "properties": {
    "addr:full":"The Vicarage, Green Head Rd Cambridge Cambridgeshire CB5 0JT",
    "addr:postcode":"cb5 0jt",
    "addr:street":"Green Head Rd",
    "iso:country":"GB",
    "sg:address":"The Vicarage, Green Head Rd",
    "sg:city":"Cambridge",
    "sg:classifiers":[
        {
            "category":"Place Of Worship",
            "type":"Public Place"
        }
    ],
    "sg:phone":"+44 1638 741409",
    "sg:postcode":"CB5 0JT",
    "sg:province":"Cambridgeshire",
    "wof:name":"St Marys Swaffham Bulbeck",
    "wof:placetype":"venue"
},
  "geometry": {"coordinates":[0.294045,52.250778],"type":"Point"}
}