{
  "type": "Feature",
  "properties": {
    "addr:full":"Shannons Corner New Malden Surrey KT3 4LX",
    "addr:postcode":"kt3 4lx",
    "addr:street":"New",
    "iso:country":"GB",
    "sg:address":"Shannons Corner",
    "sg:city":"New Malden",
    "sg:classifiers":[
        {
            "category":"Home & Garden",
            "subcategory":"Furniture",
            "type":"Retail Goods"
        }
    ],
    "sg:phone":"+44 20 8949 5333",
    "sg:postcode":"KT3 4LX",
    "sg:province":"Surrey",
    "wof:name":"M F I Furniture Centres Ltd.",
    "wof:placetype":"venue"
},
  "geometry": {"coordinates":[-0.256194,51.401772],"type":"Point"}
}