{
  "type": "Feature",
  "properties": {
    "addr:full":"77 Main St Largs North Ayrshire KA30 8AG",
    "addr:housenumber":"77",
    "addr:postcode":"ka30 8ag",
    "addr:street":"Main St",
    "iso:country":"GB",
    "sg:address":"77 Main St",
    "sg:city":"Largs",
    "sg:classifiers":[
        {
            "category":"Shopping",
            "subcategory":"Tobacco",
            "type":"Retail Goods"
        }
    ],
    "sg:phone":"+44 1475 687195",
    "sg:postcode":"KA30 8AG",
    "sg:province":"North Ayrshire",
    "sg:tags":[
        "tobacconist"
    ],
    "wof:name":"William R Nisbet",
    "wof:placetype":"venue"
},
  "geometry": {"coordinates":[-4.8677458763,55.7937278748],"type":"Point"}
}