{
  "type": "Feature",
  "properties": {
    "addr:full":"579 Coach Rd Estate Washington Tyne and Wear NE37 2HR",
    "addr:housenumber":"579",
    "addr:postcode":"tyne and;ne37 2hr",
    "addr:street":"Coach Rd",
    "iso:country":"GB",
    "sg:address":"579 Coach Rd Estate",
    "sg:city":"Washington",
    "sg:classifiers":[
        {
            "category":"Shopping",
            "subcategory":"Hobbies, Toys, & Games",
            "type":"Retail Goods"
        }
    ],
    "sg:phone":"+44 191 417 5717",
    "sg:postcode":"NE37 2HR",
    "sg:province":"Tyne and Wear",
    "sg:tags":[
        "toy"
    ],
    "wof:name":"Riding High Rocking Horses",
    "wof:placetype":"venue"
},
  "geometry": {"coordinates":[-1.526698947,54.9205665588],"type":"Point"}
}