{
  "type": "Feature",
  "properties": {
    "addr:full":"Lantern Yard Guildford Surrey GU2 7NW",
    "addr:postcode":"gu2 7nw",
    "addr:street":"Lantern Yard",
    "iso:country":"GB",
    "sg:address":"Lantern Yard",
    "sg:city":"Guildford",
    "sg:classifiers":[
        {
            "category":"Professional",
            "subcategory":"Business Services",
            "type":"Services"
        }
    ],
    "sg:phone":"+44 1483 537125",
    "sg:postcode":"GU2 7NW",
    "sg:province":"Surrey",
    "sg:tags":[
        "import",
        "export",
        "agent"
    ],
    "wof:name":"Attias International Trading Co.",
    "wof:placetype":"venue"
},
  "geometry": {"coordinates":[-0.5851899981,51.2370491028],"type":"Point"}
}