{
  "type": "Feature",
  "properties": {
    "addr:full":"195 Garscube Road Glasgow Glasgow City G4 9QH",
    "addr:housenumber":"195",
    "addr:postcode":"g4 9qh",
    "addr:street":"Garscube Road",
    "iso:country":"GB",
    "sg:address":"195 Garscube Road",
    "sg:city":"Glasgow",
    "sg:classifiers":[
        {
            "category":"Education",
            "subcategory":"Special Training",
            "type":"Public Place"
        },
        {
            "category":"Education",
            "subcategory":"School",
            "type":"Public Place"
        }
    ],
    "sg:phone":"+44 141 332 6212",
    "sg:postcode":"G4 9QH",
    "sg:province":"Glasgow City",
    "wof:name":"Abercorn Secondary School",
    "wof:placetype":"venue"
},
  "geometry": {"coordinates":[-4.2610459328,55.871723175],"type":"Point"}
}