{
  "type": "Feature",
  "properties": {
    "iso:country":"GB",
    "sg:address":"3 Leeway Ct, Leeway Indust Est",
    "sg:city":"Newport",
    "sg:classifiers":[
        {
            "category":"Building & Trades",
            "subcategory":"Construction",
            "type":"Services"
        }
    ],
    "sg:phone":"+44 1633 290039",
    "sg:postcode":"NP9 0SJ",
    "sg:province":"East Riding of Yorkshire",
    "sg:tags":[
        "welder"
    ],
    "wof:name":"Stevens & Stevens",
    "wof:placetype":"venue"
},
  "geometry": {"coordinates":[-2.947336,51.572346],"type":"Point"}
}