{
  "type": "Feature",
  "properties": {
    "addr:full":"21 Ryelands House Hereford Herefordshire HR4 0LW",
    "addr:housenumber":"21",
    "addr:postcode":"hr4 0lw",
    "addr:street":"Ryelands House",
    "iso:country":"GB",
    "sg:address":"21 Ryelands House",
    "sg:city":"Hereford",
    "sg:classifiers":[
        {
            "category":"Landmark",
            "subcategory":"Tourist Attraction",
            "type":"Public Place"
        }
    ],
    "sg:phone":"+44 1432 354207",
    "sg:postcode":"HR4 0LW",
    "sg:province":"Herefordshire",
    "sg:tags":[
        "interest"
    ],
    "wof:name":"Museum of Cider Ltd.",
    "wof:placetype":"venue"
},
  "geometry": {"coordinates":[-2.7405600548,52.0619087219],"type":"Point"}
}