{
  "type": "Feature",
  "properties": {
    "iso:country":"GB",
    "sg:address":"78 Main Street",
    "sg:city":"Cockermouth",
    "sg:classifiers":[
        {
            "category":"Food & Beverages",
            "subcategory":"Bakery",
            "type":"Retail Goods"
        }
    ],
    "sg:phone":"+44 1900 822012",
    "sg:postcode":"CA13 9LU",
    "sg:province":"Cumbria",
    "sg:tags":[
        "baker"
    ],
    "wof:name":"Bells of Lazonby Ltd.",
    "wof:placetype":"venue"
},
  "geometry": {"coordinates":[-3.3663449287,54.6637573242],"type":"Point"}
}