{
  "type": "Feature",
  "properties": {
    "iso:country":"GB",
    "sg:address":"Unit 4 Progress Business Centre, Brookfield Drive",
    "sg:city":"Cannock",
    "sg:classifiers":[
        {
            "category":"Professional",
            "subcategory":"Engineering",
            "type":"Services"
        }
    ],
    "sg:phone":"+44 1543 469300",
    "sg:postcode":"WS11 3JN",
    "sg:province":"Staffordshire",
    "sg:tags":[
        "contractor",
        "electrical",
        "engineer"
    ],
    "wof:name":"Cannock Electrical Installations Ltd.",
    "wof:placetype":"venue"
},
  "geometry": {"coordinates":[-2.0248560905,52.6789321899],"type":"Point"}
}