{
  "type": "Feature",
  "properties": {
    "addr:full":"Mill Ho, Aylesbury Rd Thame Buckinghamshire OX9 3AT",
    "addr:postcode":"ox9 3at",
    "addr:street":"Aylesbury Rd",
    "iso:country":"GB",
    "sg:address":"Mill Ho, Aylesbury Rd",
    "sg:city":"Thame",
    "sg:classifiers":[
        {
            "category":"Real Estate",
            "subcategory":"Real Estate Agent",
            "type":"Services"
        }
    ],
    "sg:postcode":"OX9 3AT",
    "sg:province":"Buckinghamshire",
    "wof:name":"Intrepreneur Estates",
    "wof:placetype":"venue"
},
  "geometry": {"coordinates":[-0.9629359841,51.7611083984],"type":"Point"}
}