{
  "type": "Feature",
  "properties": {
    "addr:full":"Station Road, Darley Dale Matlock Derbyshire DE4 2EQ",
    "addr:postcode":"de4 2eq",
    "addr:street":"Station Road;Dale",
    "iso:country":"GB",
    "sg:address":"Station Road, Darley Dale",
    "sg:city":"Matlock",
    "sg:classifiers":[
        {
            "category":"Shopping",
            "subcategory":"News",
            "type":"Retail Goods"
        }
    ],
    "sg:phone":"+44 1629 734098",
    "sg:postcode":"DE4 2EQ",
    "sg:province":"Derbyshire",
    "sg:tags":[
        "newsagent"
    ],
    "wof:name":"Two Dales News Plus",
    "wof:placetype":"venue"
},
  "geometry": {"coordinates":[-1.6016340256,53.1641044617],"type":"Point"}
}