{
  "type": "Feature",
  "properties": {
    "addr:full":"Brierly Pl, New London Rd Chelmsford Essex CM2 0AP",
    "addr:postcode":"cm2 0ap",
    "addr:street":"Brierly Pl New London Rd",
    "iso:country":"GB",
    "sg:address":"Brierly Pl, New London Rd",
    "sg:city":"Chelmsford",
    "sg:classifiers":[
        {
            "category":"Professional",
            "subcategory":"Employment Agencies",
            "type":"Services"
        }
    ],
    "sg:phone":"+44 1245 211216",
    "sg:postcode":"CM2 0AP",
    "sg:province":"Essex",
    "sg:tags":[
        "consultant"
    ],
    "wof:name":"Careersin.Com Ltd",
    "wof:placetype":"venue"
},
  "geometry": {"coordinates":[0.470605,51.730389],"type":"Point"}
}