{
  "type": "Feature",
  "properties": {
    "iso:country":"GB",
    "sg:address":"9 The Steyne",
    "sg:city":"Bognor Regis",
    "sg:classifiers":[
        {
            "category":"Building & Trades",
            "subcategory":"Plumbing",
            "type":"Services"
        }
    ],
    "sg:postcode":"PO21 1TX",
    "sg:province":"West Sussex",
    "sg:tags":[
        "heating"
    ],
    "wof:name":"B & S Pool Care & Plumbing",
    "wof:placetype":"venue"
},
  "geometry": {"coordinates":[-0.6783069968,50.7814826965],"type":"Point"}
}