{
  "type": "Feature",
  "properties": {
    "addr:full":"5 Leroy Drive, Blackley Manchester Greater Manchester M9 7EW",
    "addr:housenumber":"5",
    "addr:postcode":"m9 7ew",
    "addr:street":"Leroy Drive",
    "iso:country":"GB",
    "sg:address":"5 Leroy Drive, Blackley",
    "sg:city":"Manchester",
    "sg:classifiers":[
        {
            "category":"Professional",
            "subcategory":"Engineering",
            "type":"Services"
        }
    ],
    "sg:postcode":"M9 7EW",
    "sg:province":"Greater Manchester",
    "sg:tags":[
        "civil",
        "engineer"
    ],
    "wof:name":"M & B O'Connor",
    "wof:placetype":"venue"
},
  "geometry": {"coordinates":[-2.2124109268,53.5231170654],"type":"Point"}
}