{
  "type": "Feature",
  "properties": {
    "addr:full":"Unit 3e Ashleigh Commercial Centre, 87 Westmoor St Charlton Greater London SE7 8NQ",
    "addr:housenumber":"3e;87",
    "addr:postcode":"se7 8nq",
    "addr:street":"Westmoor St",
    "iso:country":"GB",
    "sg:address":"Unit 3e Ashleigh Commercial Centre, 87 Westmoor St",
    "sg:city":"Charlton",
    "sg:classifiers":[
        {
            "category":"Retail",
            "subcategory":"Auto Repair",
            "type":"Services"
        }
    ],
    "sg:phone":"+44 20 8293 6432",
    "sg:postcode":"SE7 8NQ",
    "sg:province":"Greater London",
    "sg:tags":[
        "modification",
        "garage"
    ],
    "wof:name":"Charlton Auto Tune Ltd",
    "wof:placetype":"venue"
},
  "geometry": {"coordinates":[0.03799,51.492409],"type":"Point"}
}