{
  "type": "Feature",
  "properties": {
    "addr:full":"3a Great Wheatley Road Rayleigh Essex SS6 7AL",
    "addr:housenumber":"3a",
    "addr:postcode":"ss6 7al",
    "addr:street":"Great Wheatley Road Rayleigh",
    "iso:country":"GB",
    "sg:address":"3a Great Wheatley Road",
    "sg:city":"Rayleigh",
    "sg:classifiers":[
        {
            "category":"Health Services",
            "subcategory":"Nursing And Care Facility",
            "type":"Services"
        }
    ],
    "sg:phone":"+44 1268 777281",
    "sg:postcode":"SS6 7AL",
    "sg:province":"Essex",
    "sg:tags":[
        "home"
    ],
    "wof:name":"Great Wheatley",
    "wof:placetype":"venue"
},
  "geometry": {"coordinates":[0.5977119803,51.5813674927],"type":"Point"}
}