{
  "type": "Feature",
  "properties": {
    "iso:country":"GB",
    "sg:address":"Olleberrie Lane, Sarratt",
    "sg:city":"Rickmansworth",
    "sg:classifiers":[
        {
            "category":"Professional",
            "subcategory":"Art Services",
            "type":"Services"
        }
    ],
    "sg:phone":"+44 1923 266887",
    "sg:postcode":"WD3 4NU",
    "sg:province":"Hertfordshire",
    "sg:tags":[
        "model",
        "maker"
    ],
    "wof:name":"Banjo Inc Ltd.",
    "wof:placetype":"venue"
},
  "geometry": {"coordinates":[-0.511487,51.701393],"type":"Point"}
}