{
  "type": "Feature",
  "properties": {
    "addr:full":"Montpilier Farm, Margaretting Road Chelmsford Essex CM1 3PL",
    "addr:postcode":"cm1 3pl",
    "addr:street":"Margaretting Road",
    "iso:country":"GB",
    "sg:address":"Montpilier Farm, Margaretting Road",
    "sg:city":"Chelmsford",
    "sg:classifiers":[
        {
            "category":"Banks & Credit Unions",
            "subcategory":"Investment Brokerage",
            "type":"Services"
        },
        {
            "category":"Farming",
            "subcategory":"Farm",
            "type":"Manufacturing & Wholesale Goods"
        },
        {
            "category":"Recreation",
            "subcategory":"Campground",
            "type":"Entertainment"
        }
    ],
    "sg:phone":"+44 1245 422522",
    "sg:postcode":"CM1 3PL",
    "sg:province":"Essex",
    "sg:tags":[
        "camping",
        "site",
        "crop",
        "contractor",
        "mixed",
        "operator"
    ],
    "sg:website":"http://www.vcamping.co.uk",
    "wof:name":"A Green & Partners",
    "wof:placetype":"venue"
},
  "geometry": {"coordinates":[0.4169799984,51.7180786133],"type":"Point"}
}