{
  "type": "Feature",
  "properties": {
    "iso:country":"GB",
    "sg:address":"Bentley Road, Willesborough",
    "sg:city":"Ashford",
    "sg:classifiers":[
        {
            "category":"Health Services",
            "subcategory":"Doctor",
            "type":"Services"
        },
        {
            "category":"Health Services",
            "subcategory":"Clinic",
            "type":"Services"
        }
    ],
    "sg:phone":"+44 1233 621626",
    "sg:postcode":"TN24 0HZ",
    "sg:province":"Kent",
    "sg:tags":[
        "nh",
        "practitioners"
    ],
    "wof:name":"Willesborough Health Centre",
    "wof:placetype":"venue"
},
  "geometry": {"coordinates":[0.8983200192,51.1582603455],"type":"Point"}
}