{
  "type": "Feature",
  "properties": {
    "addr:full":"Camden Place Great Yarmouth Norfolk NR30 3HX",
    "addr:postcode":"nr30 3hx",
    "addr:street":"Camden Place",
    "iso:country":"GB",
    "sg:address":"Camden Place",
    "sg:city":"Great Yarmouth",
    "sg:classifiers":[
        {
            "category":"Retail",
            "subcategory":"Auto Repair",
            "type":"Services"
        }
    ],
    "sg:phone":"+44 1493 844345",
    "sg:postcode":"NR30 3HX",
    "sg:province":"Norfolk",
    "sg:tags":[
        "modification",
        "garage",
        "related"
    ],
    "wof:name":"Halls Garage",
    "wof:placetype":"venue"
},
  "geometry": {"coordinates":[1.7303409576,52.5991096497],"type":"Point"}
}