{
  "type": "Feature",
  "properties": {
    "addr:full":"D3c The Business Park, Pleasley Vale Mansfield Derbyshire NG19 8RL",
    "addr:postcode":"ng19 8rl",
    "iso:country":"GB",
    "sg:address":"D3c The Business Park, Pleasley Vale",
    "sg:city":"Mansfield",
    "sg:classifiers":[
        {
            "category":"Professional",
            "subcategory":"Management & Consulting",
            "type":"Services"
        }
    ],
    "sg:phone":"+44 1623 811394",
    "sg:postcode":"NG19 8RL",
    "sg:province":"Derbyshire",
    "sg:tags":[
        "consultant",
        "promotion",
        "sale"
    ],
    "wof:name":"Radical Marketing",
    "wof:placetype":"venue"
},
  "geometry": {"coordinates":[-1.2266299725,53.1788482666],"type":"Point"}
}