{
  "type": "Feature",
  "properties": {
    "addr:full":"16 St Georges Road London Greater London SW19 4DP",
    "addr:housenumber":"16",
    "addr:postcode":"sw19 4dp",
    "addr:street":"St Georges Road",
    "iso:country":"GB",
    "sg:address":"16 St Georges Road",
    "sg:city":"London",
    "sg:classifiers":[
        {
            "category":"Shopping",
            "subcategory":"Shoes",
            "type":"Retail Goods"
        }
    ],
    "sg:phone":"+44 20 8879 7681",
    "sg:postcode":"SW19 4DP",
    "sg:province":"Greater London",
    "wof:name":"Saddlers",
    "wof:placetype":"venue"
},
  "geometry": {"coordinates":[-0.2090869993,51.4206695557],"type":"Point"}
}