{
  "type": "Feature",
  "properties": {
    "iso:country":"GB",
    "sg:address":"126 Trafalgar Rd",
    "sg:city":"Brighton",
    "sg:classifiers":[
        {
            "category":"Building & Trades",
            "subcategory":"Construction",
            "type":"Services"
        }
    ],
    "sg:phone":"+44 1273 582134",
    "sg:postcode":"BN41 1GS",
    "sg:province":"East Sussex",
    "sg:tags":[
        "glazier"
    ],
    "wof:name":"Barnard & Hoad Glazing Contractors",
    "wof:placetype":"venue"
},
  "geometry": {"coordinates":[-0.217106998,50.8376541138],"type":"Point"}
}