{
  "type": "Feature",
  "properties": {
    "addr:full":"31 Low Catton Rd York East Riding of Yorkshire YO4 1DZ",
    "addr:housenumber":"31",
    "addr:postcode":"yo4 1dz",
    "addr:street":"Low Catton Rd",
    "iso:country":"GB",
    "sg:address":"31 Low Catton Rd",
    "sg:city":"York",
    "sg:classifiers":[
        {
            "category":"Personal",
            "type":"Services"
        }
    ],
    "sg:phone":"+44 1759 372217",
    "sg:postcode":"YO4 1DZ",
    "sg:province":"East Riding of Yorkshire",
    "sg:tags":[
        "delivery"
    ],
    "wof:name":"Brian Arundale",
    "wof:placetype":"venue"
},
  "geometry": {"coordinates":[-0.9165210128,53.987033844],"type":"Point"}
}