{
  "type": "Feature",
  "properties": {
    "addr:full":"West Quay Road Poole Dorset BH15 1HZ",
    "addr:postcode":"bh15 1hz",
    "addr:street":"West Quay Road",
    "iso:country":"GB",
    "sg:address":"West Quay Road",
    "sg:city":"Poole",
    "sg:classifiers":[
        {
            "category":"Organizations",
            "subcategory":"Non-profit Organization",
            "type":"Services"
        }
    ],
    "sg:postcode":"BH15 1HZ",
    "sg:province":"Dorset",
    "sg:tags":[
        "organisation",
        "voluntary",
        "charity"
    ],
    "wof:name":"R N L I (Enterprises) Ltd.",
    "wof:placetype":"venue"
},
  "geometry": {"coordinates":[-1.9867529869,50.7172737122],"type":"Point"}
}