{
  "type": "Feature",
  "properties": {
    "addr:full":"122a North Street Bristol City of Bristol BS16 5SE",
    "addr:housenumber":"122a",
    "addr:postcode":"bs16 5se",
    "addr:street":"North Street",
    "iso:country":"GB",
    "sg:address":"122a North Street",
    "sg:city":"Bristol",
    "sg:classifiers":[
        {
            "category":"Personal",
            "subcategory":"Barber",
            "type":"Services"
        }
    ],
    "sg:postcode":"BS16 5SE",
    "sg:province":"City of Bristol",
    "sg:tags":[
        "men's",
        "hairdresser"
    ],
    "wof:name":"Masters Barber Shop",
    "wof:placetype":"venue"
},
  "geometry": {"coordinates":[-2.503613,51.48782],"type":"Point"}
}