{
  "type": "Feature",
  "properties": {
    "addr:full":"Lodbourne Green Gillingham Dorset SP8 4EG",
    "addr:postcode":"sp8 4eg",
    "addr:street":"Green",
    "iso:country":"GB",
    "sg:address":"Lodbourne Green",
    "sg:city":"Gillingham",
    "sg:classifiers":[
        {
            "category":"Cinema",
            "subcategory":"Movie Rental",
            "type":"Entertainment"
        }
    ],
    "sg:phone":"+44 1747 822224",
    "sg:postcode":"SP8 4EG",
    "sg:province":"Dorset",
    "sg:tags":[
        "video",
        "library"
    ],
    "wof:name":"Top Entertainment",
    "wof:placetype":"venue"
},
  "geometry": {"coordinates":[-2.276382,51.042236],"type":"Point"}
}