{
  "type": "Feature",
  "properties": {
    "addr:full":"The Store, Inverurie Rd Aberdeen Aberdeen City AB21 9LJ",
    "addr:postcode":"ab21 9lj",
    "addr:street":"Inverurie Rd",
    "iso:country":"GB",
    "sg:address":"The Store, Inverurie Rd",
    "sg:city":"Aberdeen",
    "sg:classifiers":[
        {
            "category":"Fast Food",
            "type":"Food & Drink"
        }
    ],
    "sg:postcode":"AB21 9LJ",
    "sg:province":"Aberdeen City",
    "sg:tags":[
        "away",
        "take"
    ],
    "wof:name":"Chipper Plus (The)",
    "wof:placetype":"venue"
},
  "geometry": {"coordinates":[-2.171464,57.177074],"type":"Point"}
}