{
  "type": "Feature",
  "properties": {
    "iso:country":"GB",
    "sg:address":"Melbury Ho, 34 Southborough Rd Bickley",
    "sg:city":"Bromley",
    "sg:classifiers":[
        {
            "category":"Building & Trades",
            "subcategory":"Construction",
            "type":"Services"
        }
    ],
    "sg:postcode":"BR1 2BE",
    "sg:province":"Kent",
    "sg:tags":[
        "builder"
    ],
    "wof:name":"Ironfighters Structual Steelworks Ltd",
    "wof:placetype":"venue"
},
  "geometry": {"coordinates":[0.05328,51.4021],"type":"Point"}
}