{
  "type": "Feature",
  "properties": {
    "iso:country":"GB",
    "sg:address":"224 Cowley Road",
    "sg:city":"Oxford",
    "sg:classifiers":[
        {
            "category":"Food & Beverages",
            "subcategory":"Meat & Fish",
            "type":"Retail Goods"
        }
    ],
    "sg:phone":"+44 1865 248524",
    "sg:postcode":"OX4 1UH",
    "sg:province":"Oxfordshire",
    "sg:tags":[
        "butcher"
    ],
    "wof:name":"William H Alder",
    "wof:placetype":"venue"
},
  "geometry": {"coordinates":[-1.2331249714,51.7464523315],"type":"Point"}
}