{
  "type": "Feature",
  "properties": {
    "addr:full":"Wellington Ho, 96-98 High St Newmarket Cambridgeshire CB8 8JX",
    "addr:housenumber":"96-98",
    "addr:postcode":"cb8 8jx",
    "addr:street":"High St",
    "iso:country":"GB",
    "sg:address":"Wellington Ho, 96-98 High St",
    "sg:city":"Newmarket",
    "sg:classifiers":[
        {
            "category":"Professional",
            "subcategory":"Employment Agencies",
            "type":"Services"
        }
    ],
    "sg:phone":"+44 1638 664881",
    "sg:postcode":"CB8 8JX",
    "sg:province":"Cambridgeshire",
    "sg:tags":[
        "consultant"
    ],
    "wof:name":"Status Recruitment Ltd",
    "wof:placetype":"venue"
},
  "geometry": {"coordinates":[0.399165988,52.2498168945],"type":"Point"}
}