{
  "type": "Feature",
  "properties": {
    "addr:full":"Suite 30, The Orion Suite, Enterprise Way Newport Newport NP20 2AQ",
    "addr:postcode":"np20 2aq",
    "addr:street":"Suite 30 The;Enterprise Way",
    "iso:country":"GB",
    "sg:address":"Suite 30, The Orion Suite, Enterprise Way",
    "sg:city":"Newport",
    "sg:classifiers":[
        {
            "category":"Professional",
            "subcategory":"Management & Consulting",
            "type":"Services"
        }
    ],
    "sg:phone":"+44 1633 262559",
    "sg:postcode":"NP20 2AQ",
    "sg:province":"Newport",
    "sg:tags":[
        "consultant",
        "business"
    ],
    "wof:name":"Innovative Financial Solutions",
    "wof:placetype":"venue"
},
  "geometry": {"coordinates":[-2.9879601002,51.5784683228],"type":"Point"}
}