{
  "type": "Feature",
  "properties": {
    "addr:full":"Rosedene, Bicester Road, Near Westcott Aylesbury Buckinghamshire HP18 0JU",
    "addr:postcode":"hp18 0ju",
    "addr:street":"Bicester Road Near Westcott",
    "iso:country":"GB",
    "sg:address":"Rosedene, Bicester Road, Near Westcott",
    "sg:city":"Aylesbury",
    "sg:classifiers":[
        {
            "category":"Building & Trades",
            "subcategory":"Landscaping Services",
            "type":"Services"
        }
    ],
    "sg:postcode":"HP18 0JU",
    "sg:province":"Buckinghamshire",
    "sg:tags":[
        "gardening"
    ],
    "wof:name":"North Bucks Tree Surgery",
    "wof:placetype":"venue"
},
  "geometry": {"coordinates":[-0.957499,51.846924],"type":"Point"}
}