{
  "type": "Feature",
  "properties": {
    "addr:full":"574 Caerleon Road Newport Monmouthshire NP18 1QA",
    "addr:housenumber":"574",
    "addr:postcode":"np18 1qa",
    "addr:street":"Caerleon Road",
    "iso:country":"GB",
    "sg:address":"574 Caerleon Road",
    "sg:city":"Newport",
    "sg:classifiers":[
        {
            "category":"Government",
            "subcategory":"Post Office",
            "type":"Public Place"
        }
    ],
    "sg:phone":"+44 1633 613816",
    "sg:postcode":"NP18 1QA",
    "sg:province":"Monmouthshire",
    "sg:tags":[
        "messenger",
        "courier"
    ],
    "wof:name":"Terry Davies Carrier Services",
    "wof:placetype":"venue"
},
  "geometry": {"coordinates":[-2.962605,51.602116],"type":"Point"}
}