{
  "type": "Feature",
  "properties": {
    "addr:full":"306 Upper Shoreham Road Shoreham-by-sea West Sussex BN43 6BA",
    "addr:housenumber":"306",
    "addr:postcode":"bn43 6ba",
    "addr:street":"Upper Shoreham Road",
    "iso:country":"GB",
    "sg:address":"306 Upper Shoreham Road",
    "sg:city":"Shoreham-by-sea",
    "sg:classifiers":[
        {
            "category":"Building & Trades",
            "subcategory":"Plumbing",
            "type":"Services"
        }
    ],
    "sg:phone":"+44 1273 464677",
    "sg:postcode":"BN43 6BA",
    "sg:province":"West Sussex",
    "sg:tags":[
        "heating"
    ],
    "wof:name":"A M & P M Plumbing",
    "wof:placetype":"venue"
},
  "geometry": {"coordinates":[-0.268386,50.839787],"type":"Point"}
}