{
  "type": "Feature",
  "properties": {
    "addr:full":"Sevenoaks Cp School, Bradbourne Park Road Sevenoaks Kent TN13 3LB",
    "addr:postcode":"tn13 3lb",
    "addr:street":"Bradbourne Park Road",
    "iso:country":"GB",
    "sg:address":"Sevenoaks Cp School, Bradbourne Park Road",
    "sg:city":"Sevenoaks",
    "sg:classifiers":[
        {
            "category":"Farming",
            "subcategory":"Nursery",
            "type":"Manufacturing & Wholesale Goods"
        }
    ],
    "sg:postcode":"TN13 3LB",
    "sg:province":"Kent",
    "sg:tags":[
        "creche"
    ],
    "wof:name":"Co. Child Care Ltd.",
    "wof:placetype":"venue"
},
  "geometry": {"coordinates":[0.1929389983,51.270198822],"type":"Point"}
}