{
  "type": "Feature",
  "properties": {
    "addr:full":"Enertech House, 3 Dolly Lane Leeds West Yorkshire LS9 7TU",
    "addr:housenumber":"3",
    "addr:postcode":"ls9 7tu",
    "addr:street":"Dolly Lane",
    "iso:country":"GB",
    "sg:address":"Enertech House, 3 Dolly Lane",
    "sg:city":"Leeds",
    "sg:classifiers":[
        {
            "category":"Home & Garden",
            "subcategory":"Household Appliances",
            "type":"Retail Goods"
        }
    ],
    "sg:phone":"+44 113 246 8200",
    "sg:postcode":"LS9 7TU",
    "sg:province":"West Yorkshire",
    "sg:tags":[
        "spare",
        "heating"
    ],
    "wof:name":"Heating Replacement Parts & Controls",
    "wof:placetype":"venue"
},
  "geometry": {"coordinates":[-1.5260699987,53.8073883057],"type":"Point"}
}