{
  "type": "Feature",
  "properties": {
    "addr:full":"40 Park Rd Peterborough Cambridgeshire PE1 2TG",
    "addr:housenumber":"40",
    "addr:postcode":"pe1 2tg",
    "addr:street":"Park Rd",
    "iso:country":"GB",
    "sg:address":"40 Park Rd",
    "sg:city":"Peterborough",
    "sg:classifiers":[
        {
            "category":"Government",
            "subcategory":"Office",
            "type":"Public Place"
        }
    ],
    "sg:postcode":"PE1 2TG",
    "sg:province":"Cambridgeshire",
    "sg:tags":[
        "project",
        "gov",
        "community"
    ],
    "wof:name":"North West Community Health Council",
    "wof:placetype":"venue"
},
  "geometry": {"coordinates":[-0.242054,52.57621],"type":"Point"}
}