{
  "type": "Feature",
  "properties": {
    "addr:full":"The Mews, Arley Road, Appleton Thorne Warrington Cheshire WA4 4RA",
    "addr:postcode":"wa4 4ra",
    "addr:street":"Arley Road",
    "iso:country":"GB",
    "sg:address":"The Mews, Arley Road, Appleton Thorne",
    "sg:city":"Warrington",
    "sg:classifiers":[
        {
            "category":"Professional",
            "subcategory":"Detective & Security Services",
            "type":"Services"
        }
    ],
    "sg:phone":"+44 1565 770800",
    "sg:postcode":"WA4 4RA",
    "sg:province":"Cheshire",
    "wof:name":"Remguard Ltd.",
    "wof:placetype":"venue"
},
  "geometry": {"coordinates":[-2.5448019505,53.3508605957],"type":"Point"}
}