{
  "type": "Feature",
  "properties": {
    "iso:country":"GB",
    "sg:address":"4 Pratt St",
    "sg:city":"Kirkcaldy",
    "sg:classifiers":[
        {
            "category":"Professional",
            "subcategory":"Engineering",
            "type":"Services"
        }
    ],
    "sg:phone":"+44 1592 261385",
    "sg:postcode":"KY1 1SA",
    "sg:province":"Fife",
    "wof:name":"I M I Water Heating Ltd",
    "wof:placetype":"venue"
},
  "geometry": {"coordinates":[-3.166217,56.098904],"type":"Point"}
}