{
  "type": "Feature",
  "properties": {
    "addr:full":"Lambourne House 1a Taunton Road Bridgwater Somerset TA6 3LW",
    "addr:housenumber":"1a",
    "addr:postcode":"ta6 3lw",
    "addr:street":"Taunton Road",
    "iso:country":"GB",
    "sg:address":"Lambourne House 1a Taunton Road",
    "sg:city":"Bridgwater",
    "sg:classifiers":[
        {
            "category":"Building & Trades",
            "subcategory":"Cleaning & Sanitation",
            "type":"Services"
        }
    ],
    "sg:postcode":"TA6 3LW",
    "sg:province":"Somerset",
    "sg:tags":[
        "commercial"
    ],
    "wof:name":"South West Cleaning Services Ltd",
    "wof:placetype":"venue"
},
  "geometry": {"coordinates":[-3.001503,51.126446],"type":"Point"}
}