{
  "type": "Feature",
  "properties": {
    "addr:full":"East Street South Molton Devon EX36 3QA",
    "addr:postcode":"ex36 3qa",
    "addr:street":"East Street South",
    "iso:country":"GB",
    "sg:address":"East Street",
    "sg:city":"South Molton",
    "sg:classifiers":[
        {
            "category":"Retail",
            "subcategory":"Auto Repair",
            "type":"Services"
        }
    ],
    "sg:phone":"+44 1769 572451",
    "sg:postcode":"EX36 3QA",
    "sg:province":"Devon",
    "sg:tags":[
        "modification",
        "garage"
    ],
    "wof:name":"E Nicklesl",
    "wof:placetype":"venue"
},
  "geometry": {"coordinates":[-3.831154,51.01844],"type":"Point"}
}