{
  "type": "Feature",
  "properties": {
    "iso:country":"GB",
    "sg:address":"2 Upper Pownall St",
    "sg:city":"Liverpool",
    "sg:classifiers":[
        {
            "category":"Food & Beverages",
            "subcategory":"Supermarket",
            "type":"Retail Goods"
        }
    ],
    "sg:phone":"+44 151 709 8090",
    "sg:postcode":"L1 8EG",
    "sg:province":"Merseyside",
    "sg:tags":[
        "frozen"
    ],
    "wof:name":"Anglo Australian Rice",
    "wof:placetype":"venue"
},
  "geometry": {"coordinates":[-2.984514,53.399422],"type":"Point"}
}