{
  "type": "Feature",
  "properties": {
    "addr:full":"60 Parker Street London Greater London WC2B 5PZ",
    "addr:housenumber":"60",
    "addr:postcode":"wc2b 5pz",
    "addr:street":"Parker Street",
    "iso:country":"GB",
    "sg:address":"60 Parker Street",
    "sg:city":"London",
    "sg:classifiers":[
        {
            "category":"Professional",
            "subcategory":"Employment Agencies",
            "type":"Services"
        }
    ],
    "sg:phone":"+44 20 7404 0077",
    "sg:postcode":"WC2B 5PZ",
    "sg:province":"Greater London",
    "sg:tags":[
        "consultant"
    ],
    "wof:name":"Aquent Inc",
    "wof:placetype":"venue"
},
  "geometry": {"coordinates":[-0.120277,51.516323],"type":"Point"}
}