{
  "type": "Feature",
  "properties": {
    "addr:full":"Unit E, 21-23 Market Road, Plympton Plymouth Devon PL7 1QW",
    "addr:housenumber":"21-23",
    "addr:postcode":"pl7 1qw",
    "addr:street":"Market Road",
    "iso:country":"GB",
    "sg:address":"Unit E, 21-23 Market Road, Plympton",
    "sg:city":"Plymouth",
    "sg:classifiers":[
        {
            "category":"Manufacturing",
            "subcategory":"Petroleum Products",
            "type":"Manufacturing & Wholesale Goods"
        }
    ],
    "sg:phone":"+44 1752 339373",
    "sg:postcode":"PL7 1QW",
    "sg:province":"Devon",
    "sg:tags":[
        "double",
        "glazing"
    ],
    "wof:name":"Sunrise Windows",
    "wof:placetype":"venue"
},
  "geometry": {"coordinates":[-4.0598201752,50.3864707947],"type":"Point"}
}