{
  "type": "Feature",
  "properties": {
    "addr:full":"45 Hythe Road Swindon Wiltshire SN1 3NY",
    "addr:housenumber":"45",
    "addr:postcode":"sn1 3ny",
    "addr:street":"Hythe Road",
    "iso:country":"GB",
    "sg:address":"45 Hythe Road",
    "sg:city":"Swindon",
    "sg:classifiers":[
        {
            "category":"Real Estate",
            "subcategory":"Architect",
            "type":"Services"
        }
    ],
    "sg:phone":"+44 1793 613755",
    "sg:postcode":"SN1 3NY",
    "sg:province":"Wiltshire",
    "wof:name":"Atta Engineering Ltd.",
    "wof:placetype":"venue"
},
  "geometry": {"coordinates":[-1.7849270105,51.5538063049],"type":"Point"}
}