{
  "type": "Feature",
  "properties": {
    "iso:country":"GB",
    "sg:address":"Howard Park Drive",
    "sg:city":"Kilmarnock",
    "sg:classifiers":[
        {
            "category":"Organizations",
            "subcategory":"Membership Organization",
            "type":"Services"
        }
    ],
    "sg:phone":"+44 1563 523390",
    "sg:postcode":"KA1 1SF",
    "sg:province":"East Ayrshire",
    "sg:tags":[
        "club"
    ],
    "wof:name":"Howard Park Bowling Group",
    "wof:placetype":"venue"
},
  "geometry": {"coordinates":[-4.502741,55.602375],"type":"Point"}
}