{
  "type": "Feature",
  "properties": {
    "iso:country":"GB",
    "sg:address":"Low Wynds, Rampside",
    "sg:city":"Barrow-in-furness",
    "sg:classifiers":[
        {
            "category":"Real Estate",
            "subcategory":"Architect",
            "type":"Services"
        }
    ],
    "sg:postcode":"LA13 0QR",
    "sg:province":"Cumbria",
    "wof:name":"B Jackson Yacht Surveyor",
    "wof:placetype":"venue"
},
  "geometry": {"coordinates":[-3.193815,54.135853],"type":"Point"}
}