{
  "type": "Feature",
  "properties": {
    "addr:full":"47 West Main Street Broxburn City of Edinburgh EH52 5RL",
    "addr:housenumber":"47",
    "addr:postcode":"eh52 5rl",
    "addr:street":"West Main Street",
    "iso:country":"GB",
    "sg:address":"47 West Main Street",
    "sg:city":"Broxburn",
    "sg:classifiers":[
        {
            "category":"Social Services",
            "subcategory":"Retirement Home",
            "type":"Services"
        },
        {
            "category":"Government",
            "subcategory":"Office",
            "type":"Public Place"
        }
    ],
    "sg:phone":"+44 1506 854742",
    "sg:postcode":"EH52 5RL",
    "sg:province":"City of Edinburgh",
    "sg:tags":[
        "residential",
        "local",
        "care"
    ],
    "wof:name":"Strathbrock Lodge Residential Care",
    "wof:placetype":"venue"
},
  "geometry": {"coordinates":[-3.4751079082,55.9339103699],"type":"Point"}
}