{
  "type": "Feature",
  "properties": {
    "iso:country":"GB",
    "sg:address":"Church Road, Stotfold",
    "sg:city":"Hitchin",
    "sg:classifiers":[
        {
            "category":"Education",
            "subcategory":"School",
            "type":"Public Place"
        }
    ],
    "sg:phone":"+44 1462 730336",
    "sg:postcode":"SG5 4NE",
    "sg:province":"Bedfordshire",
    "sg:tags":[
        "local",
        "authority"
    ],
    "wof:name":"Roecroft Lower School",
    "wof:placetype":"venue"
},
  "geometry": {"coordinates":[-0.2308720052,52.0154685974],"type":"Point"}
}