{
  "type": "Feature",
  "properties": {
    "addr:full":"431 Hall Road Norwich Norfolk NR4 6ET",
    "addr:housenumber":"431",
    "addr:postcode":"nr4 6et",
    "addr:street":"Hall Road Norwich Norfolk",
    "iso:country":"GB",
    "sg:address":"431 Hall Road",
    "sg:city":"Norwich",
    "sg:classifiers":[
        {
            "category":"Manufacturing",
            "subcategory":"Rubber & Plastics",
            "type":"Manufacturing & Wholesale Goods"
        },
        {
            "category":"Professional",
            "type":"Services"
        }
    ],
    "sg:phone":"+44 1603 612655",
    "sg:postcode":"NR4 6ET",
    "sg:province":"Norfolk",
    "sg:tags":[
        "product",
        "exhibition"
    ],
    "wof:name":"Steroma International Ltd.",
    "wof:placetype":"venue"
},
  "geometry": {"coordinates":[1.2842760086,52.6030426025],"type":"Point"}
}