{
  "type": "Feature",
  "properties": {
    "iso:country":"GB",
    "sg:address":"20 Garden Road",
    "sg:city":"Walton-on-thames",
    "sg:classifiers":[
        {
            "category":"Building & Trades",
            "subcategory":"Landscaping Services",
            "type":"Services"
        }
    ],
    "sg:postcode":"KT12 2HG",
    "sg:province":"Surrey",
    "sg:tags":[
        "landscape",
        "contractor"
    ],
    "wof:name":"Grass Roots",
    "wof:placetype":"venue"
},
  "geometry": {"coordinates":[-0.4091889858,51.3912696838],"type":"Point"}
}