{
  "type": "Feature",
  "properties": {
    "addr:full":"Llanfrechfa Way, Llanyravon Cwmbran Monmouthshire NP44 8HT",
    "addr:postcode":"np44 8ht",
    "addr:street":"Llanfrechfa Way Llanyravon",
    "iso:country":"GB",
    "sg:address":"Llanfrechfa Way, Llanyravon",
    "sg:city":"Cwmbran",
    "sg:classifiers":[
        {
            "category":"Autos & Motor Vehicles",
            "subcategory":"Automobile Sales",
            "type":"Retail Goods"
        }
    ],
    "sg:phone":"+44 1633 874263",
    "sg:postcode":"NP44 8HT",
    "sg:province":"Monmouthshire",
    "sg:tags":[
        "car"
    ],
    "wof:name":"C B Cars",
    "wof:placetype":"venue"
},
  "geometry": {"coordinates":[-2.986614,51.637615],"type":"Point"}
}