{
  "type": "Feature",
  "properties": {
    "addr:full":"98 Lichfield St Tamworth Staffordshire B79 7QF",
    "addr:housenumber":"98",
    "addr:postcode":"b79 7qf",
    "addr:street":"Lichfield St",
    "iso:country":"GB",
    "sg:address":"98 Lichfield St",
    "sg:city":"Tamworth",
    "sg:classifiers":[
        {
            "category":"Utilities",
            "subcategory":"Natural Gas",
            "type":"Services"
        }
    ],
    "sg:phone":"+44 1827 54945",
    "sg:postcode":"B79 7QF",
    "sg:province":"Staffordshire",
    "sg:tags":[
        "control",
        "energy",
        "management",
        "system"
    ],
    "wof:name":"Era Solutions",
    "wof:placetype":"venue"
},
  "geometry": {"coordinates":[-1.7119319439,52.6353607178],"type":"Point"}
}