{
  "type": "Feature",
  "properties": {
    "iso:country":"GB",
    "sg:address":"Coniston Avenue",
    "sg:city":"Upminster",
    "sg:classifiers":[
        {
            "category":"Arena",
            "subcategory":"Sports Club",
            "type":"Entertainment"
        }
    ],
    "sg:phone":"+44 1708 220040",
    "sg:postcode":"RM14 3XR",
    "sg:province":"Essex",
    "wof:name":"Cranston Park Tennis Club",
    "wof:placetype":"venue"
},
  "geometry": {"coordinates":[0.25023,51.548946],"type":"Point"}
}