{
  "type": "Feature",
  "properties": {
    "addr:full":"Bridge Cottage, Old Romsey Road, Cadnam Southampton Hampshire SO40 2NP",
    "addr:postcode":"so40 2np",
    "addr:street":"Old Romsey Road",
    "iso:country":"GB",
    "sg:address":"Bridge Cottage, Old Romsey Road, Cadnam",
    "sg:city":"Southampton",
    "sg:classifiers":[
        {
            "category":"Building & Trades",
            "subcategory":"Construction",
            "type":"Services"
        }
    ],
    "sg:postcode":"SO40 2NP",
    "sg:province":"Hampshire",
    "sg:tags":[
        "conservation",
        "craft",
        "thatching"
    ],
    "wof:name":"Simon Sinkinson",
    "wof:placetype":"venue"
},
  "geometry": {"coordinates":[-1.5740740299,50.9192581177],"type":"Point"}
}