{
  "type": "Feature",
  "properties": {
    "iso:country":"GB",
    "sg:address":"130 Middleton Rd, Gorleston",
    "sg:city":"Great Yarmouth",
    "sg:classifiers":[
        {
            "category":"Health Services",
            "subcategory":"Dentist",
            "type":"Services"
        }
    ],
    "sg:phone":"+44 1493 665416",
    "sg:postcode":"NR31 7PN",
    "sg:province":"Norfolk",
    "wof:name":"Dunelm Dental Practice",
    "wof:placetype":"venue"
},
  "geometry": {"coordinates":[1.720183,52.570522],"type":"Point"}
}