{
  "type": "Feature",
  "properties": {
    "iso:country":"GB",
    "sg:address":"6 Grove Park West",
    "sg:city":"Colwyn Bay",
    "sg:classifiers":[
        {
            "category":"Retail",
            "subcategory":"Driving School",
            "type":"Services"
        }
    ],
    "sg:postcode":"LL29 7EH",
    "sg:province":"Conwy",
    "wof:name":"Ace Hourly School of Motoring",
    "wof:placetype":"venue"
},
  "geometry": {"coordinates":[-3.727507,53.292538],"type":"Point"}
}