{
  "type": "Feature",
  "properties": {
    "iso:country":"GB",
    "sg:address":"44 Brendon Avenue",
    "sg:city":"Weston-super-mare",
    "sg:classifiers":[
        {
            "category":"Professional",
            "subcategory":"Engineering",
            "type":"Services"
        }
    ],
    "sg:postcode":"BS23 2TS",
    "sg:province":"Somerset",
    "sg:tags":[
        "contractor",
        "electrical",
        "engineer"
    ],
    "wof:name":"J P Snelling",
    "wof:placetype":"venue"
},
  "geometry": {"coordinates":[-2.964946,51.354164],"type":"Point"}
}