{
  "type": "Feature",
  "properties": {
    "iso:country":"GB",
    "sg:address":"The Anchorage, Off Willis Road",
    "sg:city":"Gosport",
    "sg:classifiers":[
        {
            "category":"Organizations",
            "subcategory":"Non-profit Organization",
            "type":"Services"
        }
    ],
    "sg:phone":"+44 23 9258 4370",
    "sg:postcode":"PO12 1NA",
    "sg:province":"Hampshire",
    "sg:tags":[
        "organisation",
        "voluntary",
        "charity"
    ],
    "wof:name":"British Red Cross Society",
    "wof:placetype":"venue"
},
  "geometry": {"coordinates":[-1.1215339899,50.7943611145],"type":"Point"}
}