{
  "type": "Feature",
  "properties": {
    "iso:country":"GB",
    "sg:address":"22a Swan Street, Kingsclere",
    "sg:city":"Newbury",
    "sg:classifiers":[
        {
            "category":"Professional",
            "subcategory":"Employment Agencies",
            "type":"Services"
        }
    ],
    "sg:phone":"+44 118 981 1110",
    "sg:postcode":"RG20 5PJ",
    "sg:province":"Berkshire",
    "sg:tags":[
        "consultant"
    ],
    "wof:name":"Bond Recruitment & Business Consultants",
    "wof:placetype":"venue"
},
  "geometry": {"coordinates":[-1.248448,51.323643],"type":"Point"}
}