{
  "type": "Feature",
  "properties": {
    "iso:country":"GB",
    "sg:address":"66 Hamilton Road, Rutherglen",
    "sg:city":"Glasgow",
    "sg:classifiers":[
        {
            "category":"Shopping",
            "subcategory":"Gifts & Souvenirs",
            "type":"Retail Goods"
        }
    ],
    "sg:postcode":"G73 3DQ",
    "sg:province":"Glasgow City",
    "sg:tags":[
        "poster",
        "card"
    ],
    "wof:name":"Kelrys",
    "wof:placetype":"venue"
},
  "geometry": {"coordinates":[-4.2074489594,55.8270645142],"type":"Point"}
}