{
  "type": "Feature",
  "properties": {
    "addr:full":"119 King Street Plymouth Devon PL1 5JD",
    "addr:housenumber":"119",
    "addr:postcode":"pl1 5jd",
    "addr:street":"King Street",
    "iso:country":"GB",
    "sg:address":"119 King Street",
    "sg:city":"Plymouth",
    "sg:classifiers":[
        {
            "category":"Professional",
            "subcategory":"Business Services",
            "type":"Services"
        },
        {
            "category":"Shopping",
            "subcategory":"Discount & Variety Stores",
            "type":"Retail Goods"
        }
    ],
    "sg:postcode":"PL1 5JD",
    "sg:province":"Devon",
    "sg:tags":[
        "import",
        "export",
        "surplus",
        "agent"
    ],
    "wof:name":"H W Knight & Sons Surplus Stores",
    "wof:placetype":"venue"
},
  "geometry": {"coordinates":[-4.1516637802,50.3717727661],"type":"Point"}
}