{
  "type": "Feature",
  "properties": {
    "addr:full":"20 Norwood High Street London Greater London SE27 9NR",
    "addr:housenumber":"20",
    "addr:postcode":"se27 9nr",
    "addr:street":"Norwood High Street",
    "iso:country":"GB",
    "sg:address":"20 Norwood High Street",
    "sg:city":"London",
    "sg:classifiers":[
        {
            "category":"Bars & Pubs",
            "type":"Food & Drink"
        }
    ],
    "sg:phone":"+44 20 8670 3318",
    "sg:postcode":"SE27 9NR",
    "sg:province":"Greater London",
    "sg:tags":[
        "pubs",
        "inn"
    ],
    "wof:name":"Gipsy Queen",
    "wof:placetype":"venue"
},
  "geometry": {"coordinates":[-0.1023709998,51.4309844971],"type":"Point"}
}