{
  "type": "Feature",
  "properties": {
    "addr:full":"London Road, Addington West Malling Kent ME19 5PL",
    "addr:postcode":"me19 5pl",
    "addr:street":"London Road;West",
    "iso:country":"GB",
    "sg:address":"London Road, Addington",
    "sg:city":"West Malling",
    "sg:classifiers":[
        {
            "category":"Autos & Motor Vehicles",
            "subcategory":"Automobile Sales",
            "type":"Retail Goods"
        }
    ],
    "sg:phone":"+44 1732 873757",
    "sg:postcode":"ME19 5PL",
    "sg:province":"Kent",
    "sg:tags":[
        "commercial"
    ],
    "wof:name":"A R Pugh C0mmercials Ltd.",
    "wof:placetype":"venue"
},
  "geometry": {"coordinates":[0.400819,51.301338],"type":"Point"}
}