{
  "type": "Feature",
  "properties": {
    "addr:full":"European House 93 Wellington Rd Leeds West Yorkshire LS12 1DZ",
    "addr:housenumber":"93",
    "addr:postcode":"ls12 1dz",
    "addr:street":"Wellington Rd",
    "iso:country":"GB",
    "sg:address":"European House 93 Wellington Rd",
    "sg:city":"Leeds",
    "sg:classifiers":[
        {
            "category":"Professional",
            "subcategory":"Printing & Photocopies",
            "type":"Services"
        }
    ],
    "sg:postcode":"LS12 1DZ",
    "sg:province":"West Yorkshire",
    "sg:tags":[
        "printer"
    ],
    "wof:name":"New Horizon Printing Promotions Ltd",
    "wof:placetype":"venue"
},
  "geometry": {"coordinates":[-1.570387,53.791676],"type":"Point"}
}