{
  "type": "Feature",
  "properties": {
    "addr:full":"12 Market Street, Atherton Manchester Greater Manchester M46 0DN",
    "addr:housenumber":"12",
    "addr:postcode":"m46 0dn",
    "addr:street":"Market Street",
    "iso:country":"GB",
    "sg:address":"12 Market Street, Atherton",
    "sg:city":"Manchester",
    "sg:classifiers":[
        {
            "category":"Shopping",
            "subcategory":"Comic Books",
            "type":"Retail Goods"
        }
    ],
    "sg:phone":"+44 1942 888494",
    "sg:postcode":"M46 0DN",
    "sg:province":"Greater Manchester",
    "sg:tags":[
        "jeweller"
    ],
    "wof:name":"Terry's Jewellers",
    "wof:placetype":"venue"
},
  "geometry": {"coordinates":[-2.49088,53.523495],"type":"Point"}
}