{
  "type": "Feature",
  "properties": {
    "iso:country":"GB",
    "sg:address":"92 Limpsfield Road, Sanderstead",
    "sg:city":"South Croydon",
    "sg:classifiers":[
        {
            "category":"Food & Beverages",
            "subcategory":"Groceries & Convenience Stores",
            "type":"Retail Goods"
        }
    ],
    "sg:phone":"+44 20 8657 1995",
    "sg:postcode":"CR2 9EE",
    "sg:province":"Surrey",
    "wof:name":"Central Stores",
    "wof:placetype":"venue"
},
  "geometry": {"coordinates":[-0.0742139965,51.3292884827],"type":"Point"}
}