{
  "type": "Feature",
  "properties": {
    "addr:full":"Falcon Garage, Sparth Bottoms Rd Rochdale Lancashire OL11 4HT",
    "addr:postcode":"ol11 4ht",
    "addr:street":"Bottoms Rd",
    "iso:country":"GB",
    "sg:address":"Falcon Garage, Sparth Bottoms Rd",
    "sg:city":"Rochdale",
    "sg:classifiers":[
        {
            "category":"Bus Charters",
            "type":"Transportation"
        }
    ],
    "sg:phone":"+44 1706 648573",
    "sg:postcode":"OL11 4HT",
    "sg:province":"Lancashire",
    "sg:tags":[
        "hire",
        "coach"
    ],
    "wof:name":"Les Bywater & Sons Ltd",
    "wof:placetype":"venue"
},
  "geometry": {"coordinates":[-2.169494,53.611423],"type":"Point"}
}