{
  "type": "Feature",
  "properties": {
    "addr:full":"24 Henderson Street, Bridge Of Allan Stirling Clackmannanshire FK9 4HP",
    "addr:housenumber":"24",
    "addr:postcode":"fk9 4hp",
    "addr:street":"Henderson Street",
    "iso:country":"GB",
    "sg:address":"24 Henderson Street, Bridge Of Allan",
    "sg:city":"Stirling",
    "sg:classifiers":[
        {
            "category":"Travel",
            "subcategory":"Hotels & Motels",
            "type":"Entertainment"
        }
    ],
    "sg:phone":"+44 1786 833268",
    "sg:postcode":"FK9 4HP",
    "sg:province":"Clackmannanshire",
    "wof:name":"QUEEN'S HOTEL",
    "wof:placetype":"venue"
},
  "geometry": {"coordinates":[-3.949211,56.155373],"type":"Point"}
}