{
  "type": "Feature",
  "properties": {
    "addr:full":"Main St Penrith Cumbria CA10 3NL",
    "addr:postcode":"ca10 3nl",
    "addr:street":"Main St",
    "iso:country":"GB",
    "sg:address":"Main St",
    "sg:city":"Penrith",
    "sg:classifiers":[
        {
            "category":"Shopping",
            "subcategory":"Shoes",
            "type":"Retail Goods"
        }
    ],
    "sg:phone":"+44 1931 716333",
    "sg:postcode":"CA10 3NL",
    "sg:province":"Cumbria",
    "sg:tags":[
        "shop"
    ],
    "wof:name":"K Shoes",
    "wof:placetype":"venue"
},
  "geometry": {"coordinates":[-2.678798914,54.5348167419],"type":"Point"}
}