{
  "type": "Feature",
  "properties": {
    "iso:country":"GB",
    "sg:address":"Little Whaphams, Golden Sq",
    "sg:city":"Henfield",
    "sg:classifiers":[
        {
            "category":"Place Of Worship",
            "type":"Public Place"
        }
    ],
    "sg:phone":"+44 1273 493435",
    "sg:postcode":"BN5 9DP",
    "sg:province":"West Sussex",
    "wof:name":"Convent Of The Blessed Sacrament",
    "wof:placetype":"venue"
},
  "geometry": {"coordinates":[-0.2722890079,50.9314193726],"type":"Point"}
}