{
  "type": "Feature",
  "properties": {
    "addr:full":"44 Tranquil Vale London Greater London SE3 0BD",
    "addr:housenumber":"44",
    "addr:postcode":"se3 0bd",
    "addr:street":"Tranquil Vale",
    "iso:country":"GB",
    "sg:address":"44 Tranquil Vale",
    "sg:city":"London",
    "sg:classifiers":[
        {
            "category":"Bakery",
            "type":"Food & Drink"
        }
    ],
    "sg:postcode":"SE3 0BD",
    "sg:province":"Greater London",
    "sg:tags":[
        "cake",
        "maker"
    ],
    "wof:name":"Edible Creations",
    "wof:placetype":"venue"
},
  "geometry": {"coordinates":[0.0082820002,51.466468811],"type":"Point"}
}