{
  "type": "Feature",
  "properties": {
    "addr:full":"Civic Center Car Park, Exange Street Aylesbury Buckinghamshire HP20 1QY",
    "addr:postcode":"hp20 1qy",
    "addr:street":"Exange Street",
    "iso:country":"GB",
    "sg:address":"Civic Center Car Park, Exange Street",
    "sg:city":"Aylesbury",
    "sg:classifiers":[
        {
            "category":"Government",
            "subcategory":"Office",
            "type":"Public Place"
        },
        {
            "category":"Organizations",
            "subcategory":"Non-profit Organization",
            "type":"Services"
        }
    ],
    "sg:phone":"+44 1296 336725",
    "sg:postcode":"HP20 1QY",
    "sg:province":"Buckinghamshire",
    "sg:tags":[
        "organisation",
        "local",
        "voluntary",
        "charity"
    ],
    "wof:name":"Aylesbury Shopmobility",
    "wof:placetype":"venue"
},
  "geometry": {"coordinates":[-0.8118640184,51.8187789917],"type":"Point"}
}