{
  "type": "Feature",
  "properties": {
    "iso:country":"GB",
    "sg:address":"55 Market St",
    "sg:city":"Heywood",
    "sg:classifiers":[
        {
            "category":"Shopping",
            "subcategory":"Florist",
            "type":"Retail Goods"
        }
    ],
    "sg:postcode":"OL10 1HZ",
    "sg:province":"Lancashire",
    "wof:name":"Forget-Me-Not",
    "wof:placetype":"venue"
},
  "geometry": {"coordinates":[-2.2233099937,53.5937156677],"type":"Point"}
}