{
  "type": "Feature",
  "properties": {
    "addr:full":"7 Kenyon Road, Lomeshaye Estate Nelson Lancashire BB9 5SP",
    "addr:housenumber":"7",
    "addr:postcode":"bb9 5sp",
    "addr:street":"Kenyon Road Lomeshaye Estate",
    "iso:country":"GB",
    "sg:address":"7 Kenyon Road, Lomeshaye Estate",
    "sg:city":"Nelson",
    "sg:classifiers":[
        {
            "category":"Wholesale",
            "subcategory":"Office Equipment",
            "type":"Manufacturing & Wholesale Goods"
        },
        {
            "category":"Shopping",
            "subcategory":"Stationery & Office Supplies",
            "type":"Retail Goods"
        }
    ],
    "sg:phone":"+44 1282 615426",
    "sg:postcode":"BB9 5SP",
    "sg:province":"Lancashire",
    "sg:tags":[
        "supplier",
        "furniture"
    ],
    "wof:name":"Office Image Interiors Ltd",
    "wof:placetype":"venue"
},
  "geometry": {"coordinates":[-2.232071,53.83271],"type":"Point"}
}