{
  "type": "Feature",
  "properties": {
    "addr:full":"Stowupland Road Stowmarket Suffolk IP14 5AL",
    "addr:postcode":"ip14 5al",
    "addr:street":"Stowupland Road",
    "iso:country":"GB",
    "sg:address":"Stowupland Road",
    "sg:city":"Stowmarket",
    "sg:classifiers":[
        {
            "category":"Home & Garden",
            "subcategory":"Building Materials",
            "type":"Retail Goods"
        },
        {
            "category":"Manufacturing",
            "subcategory":"Building Materials",
            "type":"Manufacturing & Wholesale Goods"
        }
    ],
    "sg:phone":"+44 1449 613740",
    "sg:postcode":"IP14 5AL",
    "sg:province":"Suffolk",
    "sg:tags":[
        "merchant",
        "plaster",
        "ware",
        "builder"
    ],
    "wof:name":"M & D Precast",
    "wof:placetype":"venue"
},
  "geometry": {"coordinates":[1.0082880259,52.1925621033],"type":"Point"}
}