{
  "type": "Feature",
  "properties": {
    "iso:country":"GB",
    "sg:address":"27 Dark Lane, Backwell",
    "sg:city":"Bristol",
    "sg:classifiers":[
        {
            "category":"Real Estate",
            "subcategory":"Architect",
            "type":"Services"
        }
    ],
    "sg:phone":"+44 1275 462817",
    "sg:postcode":"BS48 3NT",
    "sg:province":"Somerset",
    "wof:name":"Richard S Westmacott",
    "wof:placetype":"venue"
},
  "geometry": {"coordinates":[-2.736648,51.412449],"type":"Point"}
}