{
  "type": "Feature",
  "properties": {
    "addr:full":"5 Mornington Villas Manningham La Bradford West Yorkshire BD8 7JX",
    "addr:housenumber":"5",
    "addr:postcode":"bd8 7jx",
    "addr:street":"Mornington Villas;La Bradford West",
    "iso:country":"GB",
    "sg:address":"5 Mornington Villas Manningham La",
    "sg:city":"Bradford",
    "sg:classifiers":[
        {
            "category":"Health Services",
            "subcategory":"Doctor",
            "type":"Services"
        }
    ],
    "sg:postcode":"BD8 7JX",
    "sg:province":"West Yorkshire",
    "sg:tags":[
        "practitioners"
    ],
    "wof:name":"F C Tring Dermatologist",
    "wof:placetype":"venue"
},
  "geometry": {"coordinates":[-1.7644040585,53.8051109314],"type":"Point"}
}