{
  "type": "Feature",
  "properties": {
    "iso:country":"GB",
    "sg:address":"47 Main Street",
    "sg:city":"Campbeltown",
    "sg:classifiers":[
        {
            "category":"Shopping",
            "subcategory":"Clothing, Apparel, & Fashions",
            "type":"Retail Goods"
        }
    ],
    "sg:postcode":"PA28 6AB",
    "sg:province":"Argyll and Bute",
    "sg:tags":[
        "shop"
    ],
    "wof:name":"Alexander P Taylor",
    "wof:placetype":"venue"
},
  "geometry": {"coordinates":[-5.6059751511,55.423614502],"type":"Point"}
}