{
  "type": "Feature",
  "properties": {
    "iso:country":"GB",
    "sg:address":"71-81 Harnall Lane West",
    "sg:city":"Coventry",
    "sg:classifiers":[
        {
            "category":"Place Of Worship",
            "type":"Public Place"
        }
    ],
    "sg:phone":"+44 24 7622 6057",
    "sg:postcode":"CV1 4FB",
    "sg:province":"West Midlands",
    "wof:name":"Gurdwara Guru Nanak Parkash",
    "wof:placetype":"venue"
},
  "geometry": {"coordinates":[-1.506619,52.415966],"type":"Point"}
}