{
  "type": "Feature",
  "properties": {
    "iso:country":"GB",
    "sg:address":"Chase House, Gilbert Street",
    "sg:city":"Alresford",
    "sg:classifiers":[
        {
            "category":"Travel",
            "subcategory":"Travel Agent",
            "type":"Entertainment"
        }
    ],
    "sg:phone":"+44 1962 773646",
    "sg:postcode":"SO24 0BY",
    "sg:province":"Hampshire",
    "wof:name":"Holland Rail",
    "wof:placetype":"venue"
},
  "geometry": {"coordinates":[-1.07548,51.08762],"type":"Point"}
}