{
  "type": "Feature",
  "properties": {
    "addr:full":"21-23 Station Clo Potters Bar Greater London EN6 1TT",
    "addr:housenumber":"21-23",
    "addr:postcode":"en6 1tt",
    "addr:street":"Station Clo",
    "iso:country":"GB",
    "sg:address":"21-23 Station Clo",
    "sg:city":"Potters Bar",
    "sg:classifiers":[
        {
            "category":"Manufacturing",
            "subcategory":"Electronics",
            "type":"Manufacturing & Wholesale Goods"
        }
    ],
    "sg:phone":"+44 1707 650882",
    "sg:postcode":"EN6 1TT",
    "sg:province":"Greater London",
    "sg:tags":[
        "control",
        "component",
        "-",
        "electronic"
    ],
    "wof:name":"Stocko (UK) Ltd",
    "wof:placetype":"venue"
},
  "geometry": {"coordinates":[-0.1941760033,51.699924469],"type":"Point"}
}