{
  "type": "Feature",
  "properties": {
    "addr:full":"92 Connaught Road, Brookwood Woking Surrey GU24 0HJ",
    "addr:housenumber":"92",
    "addr:postcode":"gu24 0hj",
    "addr:street":"Connaught Road",
    "iso:country":"GB",
    "sg:address":"92 Connaught Road, Brookwood",
    "sg:city":"Woking",
    "sg:classifiers":[
        {
            "category":"Organizations",
            "subcategory":"Membership Organization",
            "type":"Services"
        }
    ],
    "sg:postcode":"GU24 0HJ",
    "sg:province":"Surrey",
    "sg:tags":[
        "club"
    ],
    "wof:name":"Brookwood & District Club",
    "wof:placetype":"venue"
},
  "geometry": {"coordinates":[-0.635971,51.30442],"type":"Point"}
}