{
  "type": "Feature",
  "properties": {
    "addr:full":"65 High Street Shanklin Isle of Wight PO37 6JP",
    "addr:housenumber":"65",
    "addr:postcode":"po37 6jp",
    "addr:street":"High Street",
    "iso:country":"GB",
    "sg:address":"65 High Street",
    "sg:city":"Shanklin",
    "sg:classifiers":[
        {
            "category":"Professional",
            "subcategory":"Lawyer & Legal Services",
            "type":"Services"
        }
    ],
    "sg:phone":"+44 1983 862262",
    "sg:postcode":"PO37 6JP",
    "sg:province":"Isle of Wight",
    "sg:tags":[
        "solicitor"
    ],
    "wof:name":"R J R Solicitors",
    "wof:placetype":"venue"
},
  "geometry": {"coordinates":[-1.1798369884,50.6278152466],"type":"Point"}
}