{
  "type": "Feature",
  "properties": {
    "iso:country":"GB",
    "sg:address":"653 King Street",
    "sg:city":"Aberdeen",
    "sg:classifiers":[
        {
            "category":"Fast Food",
            "type":"Food & Drink"
        }
    ],
    "sg:phone":"+44 1224 481103",
    "sg:postcode":"AB24 1SB",
    "sg:province":"Aberdeen City",
    "sg:tags":[
        "away",
        "meal",
        "outlet",
        "take"
    ],
    "wof:name":"New Rainbow",
    "wof:placetype":"venue"
},
  "geometry": {"coordinates":[-2.096038,57.168888],"type":"Point"}
}