{
  "type": "Feature",
  "properties": {
    "addr:full":"10 Holland Units, Redstone Ind Est, Redstone Rd Boston Lincolnshire PE21 8EA",
    "addr:housenumber":"10;units",
    "addr:postcode":"pe21 8ea",
    "addr:street":"Holland;Redstone Rd",
    "iso:country":"GB",
    "sg:address":"10 Holland Units, Redstone Ind Est, Redstone Rd",
    "sg:city":"Boston",
    "sg:classifiers":[
        {
            "category":"Taxi",
            "type":"Transportation"
        }
    ],
    "sg:phone":"+44 1205 363630",
    "sg:postcode":"PE21 8EA",
    "sg:province":"Lincolnshire",
    "sg:tags":[
        "mini",
        "cab"
    ],
    "wof:name":"A.A Private Hire",
    "wof:placetype":"venue"
},
  "geometry": {"coordinates":[-0.0291239992,52.974697113],"type":"Point"}
}