{
  "type": "Feature",
  "properties": {
    "addr:full":"82a Promenade Cheltenham Gloucestershire GL50 1NB",
    "addr:housenumber":"82a",
    "addr:postcode":"gl50 1nb",
    "addr:street":"Promenade",
    "iso:country":"GB",
    "sg:address":"82a Promenade",
    "sg:city":"Cheltenham",
    "sg:classifiers":[
        {
            "category":"Shopping",
            "subcategory":"Clothing, Apparel, & Fashions",
            "type":"Retail Goods"
        }
    ],
    "sg:phone":"+44 1242 571716",
    "sg:postcode":"GL50 1NB",
    "sg:province":"Gloucestershire",
    "sg:tags":[
        "shop"
    ],
    "wof:name":"House of Faiman (Retail) Ltd",
    "wof:placetype":"venue"
},
  "geometry": {"coordinates":[-2.0771620274,51.8989181519],"type":"Point"}
}