{
  "type": "Feature",
  "properties": {
    "iso:country":"GB",
    "sg:address":"292 Hale Rd",
    "sg:city":"Altrincham",
    "sg:classifiers":[
        {
            "category":"Restaurant",
            "type":"Food & Drink"
        }
    ],
    "sg:phone":"+44 161 904 9090",
    "sg:postcode":"WA15 8SP",
    "sg:province":"Cheshire",
    "wof:name":"Deckers Restaurant",
    "wof:placetype":"venue"
},
  "geometry": {"coordinates":[-2.315039,53.369583],"type":"Point"}
}