{
  "type": "Feature",
  "properties": {
    "addr:full":"182 Gravelly Lane Birmingham West Midlands B23 5SN",
    "addr:housenumber":"182",
    "addr:postcode":"b23 5sn",
    "addr:street":"Gravelly Lane",
    "iso:country":"GB",
    "sg:address":"182 Gravelly Lane",
    "sg:city":"Birmingham",
    "sg:classifiers":[
        {
            "category":"Autos & Motor Vehicles",
            "subcategory":"Auto Supplies",
            "type":"Retail Goods"
        },
        {
            "category":"Shopping",
            "type":"Retail Goods"
        }
    ],
    "sg:phone":"+44 121 382 6545",
    "sg:postcode":"B23 5SN",
    "sg:province":"West Midlands",
    "sg:tags":[
        "car",
        "part",
        "accessory"
    ],
    "wof:name":"Square Deal Car Spares",
    "wof:placetype":"venue"
},
  "geometry": {"coordinates":[-1.841089,52.531769],"type":"Point"}
}