{
  "type": "Feature",
  "properties": {
    "addr:full":"Blenheim, Wayside Road Basingstoke Hampshire RG23 8BH",
    "addr:postcode":"rg23 8bh",
    "addr:street":"Wayside Road",
    "iso:country":"GB",
    "sg:address":"Blenheim, Wayside Road",
    "sg:city":"Basingstoke",
    "sg:classifiers":[
        {
            "category":"Health Services",
            "subcategory":"Doctor",
            "type":"Services"
        },
        {
            "category":"Health Services",
            "subcategory":"Clinic",
            "type":"Services"
        }
    ],
    "sg:phone":"+44 1256 464151",
    "sg:postcode":"RG23 8BH",
    "sg:province":"Hampshire",
    "sg:tags":[
        "nh",
        "practitioners"
    ],
    "wof:name":"S Bhole",
    "wof:placetype":"venue"
},
  "geometry": {"coordinates":[-1.1303800344,51.266040802],"type":"Point"}
}