{
  "type": "Feature",
  "properties": {
    "iso:country":"GB",
    "sg:address":"9 Victoria Road, Saltaire",
    "sg:city":"Shipley",
    "sg:classifiers":[
        {
            "category":"Shopping",
            "subcategory":"Books",
            "type":"Retail Goods"
        }
    ],
    "sg:phone":"+44 1274 530102",
    "sg:postcode":"BD18 3LA",
    "sg:province":"West Yorkshire",
    "sg:tags":[
        "second-hand"
    ],
    "wof:name":"The Bodhran Books",
    "wof:placetype":"venue"
},
  "geometry": {"coordinates":[-1.7899800539,53.8378295898],"type":"Point"}
}