{
  "type": "Feature",
  "properties": {
    "addr:full":"High Street, St Davids Haverfordwest Pembrokeshire SA62 6SB",
    "addr:postcode":"sa62 6sb",
    "addr:street":"High Street St",
    "iso:country":"GB",
    "sg:address":"High Street, St Davids",
    "sg:city":"Haverfordwest",
    "sg:classifiers":[
        {
            "category":"Retail",
            "subcategory":"Event Space",
            "type":"Services"
        }
    ],
    "sg:phone":"+44 1437 720704",
    "sg:postcode":"SA62 6SB",
    "sg:province":"Pembrokeshire",
    "sg:tags":[
        "timeshare",
        "accommodation"
    ],
    "wof:name":"St Davids Vacation Club",
    "wof:placetype":"venue"
},
  "geometry": {"coordinates":[-5.1966900826,51.8739852905],"type":"Point"}
}