{
  "type": "Feature",
  "properties": {
    "iso:country":"GB",
    "sg:address":"4 Struttons Avenue",
    "sg:city":"Gravesend",
    "sg:classifiers":[
        {
            "category":"Retail",
            "subcategory":"Driving School",
            "type":"Services"
        }
    ],
    "sg:phone":"+44 1474 365287",
    "sg:postcode":"DA11 7EJ",
    "sg:province":"Kent",
    "wof:name":"Red & White School of Motoring",
    "wof:placetype":"venue"
},
  "geometry": {"coordinates":[0.354018,51.428619],"type":"Point"}
}