{
  "type": "Feature",
  "properties": {
    "addr:full":"25 St Mary Road Braunton Devon EX33 1PF",
    "addr:housenumber":"25",
    "addr:postcode":"ex33 1pf",
    "addr:street":"St Mary Road",
    "iso:country":"GB",
    "sg:address":"25 St Mary Road",
    "sg:city":"Braunton",
    "sg:classifiers":[
        {
            "category":"Restaurant",
            "type":"Food & Drink"
        }
    ],
    "sg:phone":"+44 1271 890541",
    "sg:postcode":"EX33 1PF",
    "sg:province":"Devon",
    "sg:tags":[
        "-",
        "english"
    ],
    "wof:name":"Home House Restaurant",
    "wof:placetype":"venue"
},
  "geometry": {"coordinates":[-4.2216911316,51.1310501099],"type":"Point"}
}