{
  "type": "Feature",
  "properties": {
    "iso:country":"GB",
    "sg:address":"15 Clifton Moor Business Village, James Nicolson Link",
    "sg:city":"York",
    "sg:classifiers":[
        {
            "category":"Manufacturing",
            "subcategory":"Tools & Machinery",
            "type":"Manufacturing & Wholesale Goods"
        },
        {
            "category":"Insurance",
            "subcategory":"Insurance Agent",
            "type":"Services"
        }
    ],
    "sg:phone":"+44 1904 693888",
    "sg:postcode":"YO30 4XG",
    "sg:province":"North Yorkshire",
    "sg:tags":[
        "society",
        "friendly"
    ],
    "wof:name":"BUSINESS INSURANCE SERVICES LTD",
    "wof:placetype":"venue"
},
  "geometry": {"coordinates":[-1.100567,53.986629],"type":"Point"}
}