{
  "type": "Feature",
  "properties": {
    "addr:full":"Gateside Cupar Fife KY14 7ST",
    "addr:postcode":"ky14 7st",
    "iso:country":"GB",
    "sg:address":"Gateside",
    "sg:city":"Cupar",
    "sg:classifiers":[
        {
            "category":"Retail",
            "subcategory":"Auto Repair",
            "type":"Services"
        }
    ],
    "sg:phone":"+44 1337 860666",
    "sg:postcode":"KY14 7ST",
    "sg:province":"Fife",
    "sg:tags":[
        "modification",
        "garage",
        "related"
    ],
    "wof:name":"Mini Mart",
    "wof:placetype":"venue"
},
  "geometry": {"coordinates":[-3.246729,56.293419],"type":"Point"}
}