{
  "type": "Feature",
  "properties": {
    "iso:country":"GB",
    "sg:address":"40 Greenacre Close",
    "sg:city":"Swanley",
    "sg:classifiers":[
        {
            "category":"Building & Trades",
            "subcategory":"Construction",
            "type":"Services"
        }
    ],
    "sg:postcode":"BR8 8HT",
    "sg:province":"Kent",
    "sg:tags":[
        "builder"
    ],
    "wof:name":"D A Austwick",
    "wof:placetype":"venue"
},
  "geometry": {"coordinates":[0.169299,51.391651],"type":"Point"}
}