{
  "type": "Feature",
  "properties": {
    "iso:country":"GB",
    "sg:address":"24 Station Road, Little Eaton",
    "sg:city":"Derby",
    "sg:classifiers":[
        {
            "category":"Professional",
            "subcategory":"Engineering",
            "type":"Services"
        },
        {
            "category":"Building & Trades",
            "subcategory":"Construction",
            "type":"Services"
        }
    ],
    "sg:phone":"+44 1332 834814",
    "sg:postcode":"DE21 5DN",
    "sg:province":"Derbyshire",
    "sg:tags":[
        "civil",
        "engineer",
        "driveway",
        "paving",
        "contractor"
    ],
    "wof:name":"Albert Bond Tarmacadam",
    "wof:placetype":"venue"
},
  "geometry": {"coordinates":[-1.46228,52.968781],"type":"Point"}
}