{
  "type": "Feature",
  "properties": {
    "addr:full":"37 Friars Street Sudbury Essex CO10 2AG",
    "addr:housenumber":"37",
    "addr:postcode":"co10 2ag",
    "addr:street":"Friars Street",
    "iso:country":"GB",
    "sg:address":"37 Friars Street",
    "sg:city":"Sudbury",
    "sg:classifiers":[
        {
            "category":"Real Estate",
            "subcategory":"Surveying",
            "type":"Services"
        }
    ],
    "sg:phone":"+44 1787 377733",
    "sg:postcode":"CO10 2AG",
    "sg:province":"Essex",
    "sg:tags":[
        "building",
        "surveyor"
    ],
    "wof:name":"N J Wakefield",
    "wof:placetype":"venue"
},
  "geometry": {"coordinates":[0.7284960151,52.0365104675],"type":"Point"}
}