{
  "type": "Feature",
  "properties": {
    "addr:full":"18 High Street, Broom Alcester Warwickshire B50 4HJ",
    "addr:housenumber":"18",
    "addr:postcode":"b50 4hj",
    "addr:street":"High Street",
    "iso:country":"GB",
    "sg:address":"18 High Street, Broom",
    "sg:city":"Alcester",
    "sg:classifiers":[
        {
            "category":"Manufacturing",
            "subcategory":"Food",
            "type":"Manufacturing & Wholesale Goods"
        },
        {
            "category":"Government",
            "subcategory":"Office",
            "type":"Public Place"
        }
    ],
    "sg:postcode":"B50 4HJ",
    "sg:province":"Warwickshire",
    "sg:tags":[
        "technologist",
        "education",
        "agency",
        "authority"
    ],
    "wof:name":"Health Education Trust",
    "wof:placetype":"venue"
},
  "geometry": {"coordinates":[-1.8539390564,52.1656723022],"type":"Point"}
}