{
  "type": "Feature",
  "properties": {
    "addr:full":"Corbie Cottage, Glaziers Lane, Normandy Guildford Surrey GU3 2DG",
    "addr:postcode":"gu3 2dg",
    "addr:street":"Glaziers Lane",
    "iso:country":"GB",
    "sg:address":"Corbie Cottage, Glaziers Lane, Normandy",
    "sg:city":"Guildford",
    "sg:classifiers":[
        {
            "category":"Real Estate",
            "subcategory":"Surveying",
            "type":"Services"
        },
        {
            "category":"Real Estate",
            "subcategory":"Architect",
            "type":"Services"
        }
    ],
    "sg:postcode":"GU3 2DG",
    "sg:province":"Surrey",
    "sg:tags":[
        "surveyor",
        "quantity"
    ],
    "wof:name":"D B Winton Associates",
    "wof:placetype":"venue"
},
  "geometry": {"coordinates":[-0.666989,51.256756],"type":"Point"}
}