{
  "type": "Feature",
  "properties": {
    "iso:country":"GB",
    "sg:address":"251 High Street",
    "sg:city":"Beckenham",
    "sg:classifiers":[
        {
            "category":"Fast Food",
            "type":"Food & Drink"
        }
    ],
    "sg:phone":"+44 20 8650 0755",
    "sg:postcode":"BR3 1BN",
    "sg:province":"Kent",
    "sg:tags":[
        "away",
        "take"
    ],
    "wof:name":"Diamond House",
    "wof:placetype":"venue"
},
  "geometry": {"coordinates":[-0.031732,51.406693],"type":"Point"}
}