{
  "type": "Feature",
  "properties": {
    "addr:full":"48 Darnhall Cres Nottingham Nottinghamshire NG8 4PZ",
    "addr:housenumber":"48",
    "addr:postcode":"ng8 4pz",
    "addr:street":"Darnhall Cres",
    "iso:country":"GB",
    "sg:address":"48 Darnhall Cres",
    "sg:city":"Nottingham",
    "sg:classifiers":[
        {
            "category":"Retail",
            "subcategory":"Laundry & Dry Cleaning",
            "type":"Services"
        }
    ],
    "sg:phone":"+44 115 929 7957",
    "sg:postcode":"NG8 4PZ",
    "sg:province":"Nottinghamshire",
    "sg:tags":[
        "home",
        "ironing"
    ],
    "wof:name":"Lizs Laundry & Ironing Service",
    "wof:placetype":"venue"
},
  "geometry": {"coordinates":[-1.230736,52.964848],"type":"Point"}
}