{
  "type": "Feature",
  "properties": {
    "addr:full":"Kings Yard Fordingbridge Dorset SP6 1AB",
    "addr:postcode":"sp6 1ab",
    "addr:street":"Kings Yard",
    "iso:country":"GB",
    "sg:address":"Kings Yard",
    "sg:city":"Fordingbridge",
    "sg:classifiers":[
        {
            "category":"Sports & Exercise",
            "subcategory":"Gym",
            "type":"Entertainment"
        }
    ],
    "sg:postcode":"SP6 1AB",
    "sg:province":"Dorset",
    "sg:tags":[
        "fitness",
        "health",
        "centre"
    ],
    "wof:name":"Forest Health Hydro",
    "wof:placetype":"venue"
},
  "geometry": {"coordinates":[-1.7916519642,50.9268188477],"type":"Point"}
}