{
  "type": "Feature",
  "properties": {
    "iso:country":"GB",
    "sg:address":"Boslandew Hill, Paul",
    "sg:city":"Penzance",
    "sg:classifiers":[
        {
            "category":"Health Services",
            "subcategory":"Health Practitioner",
            "type":"Services"
        }
    ],
    "sg:phone":"+44 1736 731033",
    "sg:postcode":"TR19 6UD",
    "sg:province":"Cornwall",
    "sg:tags":[
        "physiotherapist"
    ],
    "wof:name":"Paul Physiotherapy Centre",
    "wof:placetype":"venue"
},
  "geometry": {"coordinates":[-5.5471282005,50.0896110535],"type":"Point"}
}