{
  "type": "Feature",
  "properties": {
    "addr:full":"Glenwood Moorhill Road, West End Southampton Hampshire SO30 3AX",
    "addr:postcode":"so30 3ax",
    "addr:street":"Moorhill Road",
    "iso:country":"GB",
    "sg:address":"Glenwood Moorhill Road, West End",
    "sg:city":"Southampton",
    "sg:classifiers":[
        {
            "category":"Utilities",
            "type":"Services"
        }
    ],
    "sg:postcode":"SO30 3AX",
    "sg:province":"Hampshire",
    "sg:tags":[
        "internet"
    ],
    "wof:name":"Web Pages Ltd",
    "wof:placetype":"venue"
},
  "geometry": {"coordinates":[-1.33324,50.92065],"type":"Point"}
}