{
  "type": "Feature",
  "properties": {
    "iso:country":"GB",
    "sg:address":"35 The Vintners, Temple Farm Indstl Est",
    "sg:city":"Southend-on-sea",
    "sg:classifiers":[
        {
            "category":"Manufacturing",
            "subcategory":"Chemicals & Compounds",
            "type":"Manufacturing & Wholesale Goods"
        }
    ],
    "sg:phone":"+44 1702 601061",
    "sg:postcode":"SS2 5RZ",
    "sg:province":"Essex",
    "wof:name":"Harrier Industrial Chemicals Ltd",
    "wof:placetype":"venue"
},
  "geometry": {"coordinates":[0.71059,51.562981],"type":"Point"}
}