{
  "type": "Feature",
  "properties": {
    "addr:full":"Wellesley Rd Ilford Essex IG1 4JT",
    "addr:postcode":"ig1 4jt",
    "addr:street":"Wellesley Rd",
    "iso:country":"GB",
    "sg:address":"Wellesley Rd",
    "sg:city":"Ilford",
    "sg:classifiers":[
        {
            "category":"Place Of Worship",
            "type":"Public Place"
        }
    ],
    "sg:phone":"+44 20 8554 9823",
    "sg:postcode":"IG1 4JT",
    "sg:province":"Essex",
    "wof:name":"Cranbrook Baptist Church",
    "wof:placetype":"venue"
},
  "geometry": {"coordinates":[0.0807240009,51.5672111511],"type":"Point"}
}