{
  "type": "Feature",
  "properties": {
    "addr:full":"32 Carters Avenue, Hamworthy Poole Dorset BH15 4JU",
    "addr:housenumber":"32",
    "addr:postcode":"bh15 4ju",
    "addr:street":"Carters Avenue",
    "iso:country":"GB",
    "sg:address":"32 Carters Avenue, Hamworthy",
    "sg:city":"Poole",
    "sg:classifiers":[
        {
            "category":"Utilities",
            "subcategory":"Fuel Oil & Lpg",
            "type":"Services"
        }
    ],
    "sg:postcode":"BH15 4JU",
    "sg:province":"Dorset",
    "sg:tags":[
        "coal",
        "smokeless"
    ],
    "wof:name":"Hooper Brothers",
    "wof:placetype":"venue"
},
  "geometry": {"coordinates":[-2.0177240372,50.7252960205],"type":"Point"}
}