{
  "type": "Feature",
  "properties": {
    "addr:full":"Doncaster Road, Wath-upon-dearne Rotherham South Yorkshire S63 7EU",
    "addr:postcode":"s63 7eu",
    "addr:street":"Doncaster Road Wath-Upon-Dearne",
    "iso:country":"GB",
    "sg:address":"Doncaster Road, Wath-upon-dearne",
    "sg:city":"Rotherham",
    "sg:classifiers":[
        {
            "category":"Manufacturing",
            "subcategory":"Lumber",
            "type":"Manufacturing & Wholesale Goods"
        }
    ],
    "sg:postcode":"S63 7EU",
    "sg:province":"South Yorkshire",
    "sg:tags":[
        "importer",
        "merchants",
        "agent",
        "timber"
    ],
    "wof:name":"Palmer Bros",
    "wof:placetype":"venue"
},
  "geometry": {"coordinates":[-1.3383270502,53.5025596619],"type":"Point"}
}