{
  "type": "Feature",
  "properties": {
    "iso:country":"GB",
    "sg:address":"Mardeena, Mortimers Avenue, Cliffe Woods",
    "sg:city":"Rochester",
    "sg:classifiers":[
        {
            "category":"Building & Trades",
            "subcategory":"Construction",
            "type":"Services"
        }
    ],
    "sg:postcode":"ME3 8JT",
    "sg:province":"Kent",
    "sg:tags":[
        "builder"
    ],
    "wof:name":"G Richardson",
    "wof:placetype":"venue"
},
  "geometry": {"coordinates":[0.495314,51.434223],"type":"Point"}
}