{
  "type": "Feature",
  "properties": {
    "iso:country":"GB",
    "sg:address":"The Skerries, Macclesfield Road",
    "sg:city":"Alderley Edge",
    "sg:classifiers":[
        {
            "category":"Banks & Credit Unions",
            "subcategory":"Financial Services",
            "type":"Services"
        },
        {
            "category":"Manufacturing",
            "subcategory":"Musical Instruments",
            "type":"Manufacturing & Wholesale Goods"
        }
    ],
    "sg:phone":"+44 1625 584439",
    "sg:postcode":"SK9 7BN",
    "sg:province":"Cheshire",
    "sg:tags":[
        "consultant",
        "agent",
        "manufacturer"
    ],
    "wof:name":"Hawkmar Ltd",
    "wof:placetype":"venue"
},
  "geometry": {"coordinates":[-2.236334,53.302807],"type":"Point"}
}