{
  "type": "Feature",
  "properties": {
    "iso:country":"GB",
    "sg:address":"Ransome Road",
    "sg:city":"Northampton",
    "sg:classifiers":[
        {
            "category":"Home & Garden",
            "subcategory":"Building Materials",
            "type":"Retail Goods"
        }
    ],
    "sg:phone":"+44 1604 762442",
    "sg:postcode":"NN4 8AA",
    "sg:province":"Northamptonshire",
    "sg:tags":[
        "ready",
        "mixed",
        "concrete"
    ],
    "wof:name":"Readymix Concrete(Transite)",
    "wof:placetype":"venue"
},
  "geometry": {"coordinates":[-0.895167,52.227966],"type":"Point"}
}