{
  "type": "Feature",
  "properties": {
    "iso:country":"GB",
    "sg:address":"Highfield Farm",
    "sg:city":"Bedale",
    "sg:classifiers":[
        {
            "category":"Farming",
            "subcategory":"Farm",
            "type":"Manufacturing & Wholesale Goods"
        }
    ],
    "sg:postcode":"DL8 2SQ",
    "sg:province":"North Yorkshire",
    "sg:tags":[
        "mixed",
        "crop"
    ],
    "wof:name":"J M Abel",
    "wof:placetype":"venue"
},
  "geometry": {"coordinates":[-1.592346,54.288811],"type":"Point"}
}