{
  "type": "Feature",
  "properties": {
    "addr:full":"123 Ock Street Abingdon Oxfordshire OX14 5DL",
    "addr:housenumber":"123",
    "addr:postcode":"ox14 5dl",
    "addr:street":"Ock Street",
    "iso:country":"GB",
    "sg:address":"123 Ock Street",
    "sg:city":"Abingdon",
    "sg:classifiers":[
        {
            "category":"Cinema",
            "subcategory":"Movie Rental",
            "type":"Entertainment"
        }
    ],
    "sg:phone":"+44 1235 550333",
    "sg:postcode":"OX14 5DL",
    "sg:province":"Oxfordshire",
    "sg:tags":[
        "video",
        "library"
    ],
    "wof:name":"MOVIES VIDEO RENTAL",
    "wof:placetype":"venue"
},
  "geometry": {"coordinates":[-1.290932,51.669453],"type":"Point"}
}