{
  "type": "Feature",
  "properties": {
    "addr:full":"81 Grosvenor Dr Loughton Essex IG10 2LA",
    "addr:housenumber":"81",
    "addr:postcode":"ig10 2la",
    "addr:street":"Grosvenor Dr",
    "iso:country":"GB",
    "sg:address":"81 Grosvenor Dr",
    "sg:city":"Loughton",
    "sg:classifiers":[
        {
            "category":"Wholesale",
            "subcategory":"Machinery & Supplies",
            "type":"Manufacturing & Wholesale Goods"
        }
    ],
    "sg:phone":"+44 20 8508 2857",
    "sg:postcode":"IG10 2LA",
    "sg:province":"Essex",
    "sg:tags":[
        "theatrical"
    ],
    "wof:name":"Camstage Auditorium Services",
    "wof:placetype":"venue"
},
  "geometry": {"coordinates":[0.0804079995,51.6600837708],"type":"Point"}
}