{
  "type": "Feature",
  "properties": {
    "iso:country":"GB",
    "sg:address":"10 Wesley Street",
    "sg:city":"Cleckheaton",
    "sg:classifiers":[
        {
            "category":"Professional",
            "type":"Services"
        }
    ],
    "sg:phone":"+44 1274 873282",
    "sg:postcode":"BD19 3PU",
    "sg:province":"West Yorkshire",
    "sg:tags":[
        "caterer"
    ],
    "wof:name":"Villa Caterers",
    "wof:placetype":"venue"
},
  "geometry": {"coordinates":[-1.7153589725,53.7284584045],"type":"Point"}
}