{
  "type": "Feature",
  "properties": {
    "addr:full":"65-67 Stamford Hill London Greater London N16 5TJ",
    "addr:housenumber":"65-67",
    "addr:postcode":"n16 5tj",
    "addr:street":"Stamford Hill",
    "iso:country":"GB",
    "sg:address":"65-67 Stamford Hill",
    "sg:city":"London",
    "sg:classifiers":[
        {
            "category":"Retail",
            "subcategory":"Auto Repair",
            "type":"Services"
        }
    ],
    "sg:phone":"+44 20 8800 0411",
    "sg:postcode":"N16 5TJ",
    "sg:province":"Greater London",
    "sg:tags":[
        "modification",
        "garage"
    ],
    "wof:name":"Triangle Stamford Hill Ltd.",
    "wof:placetype":"venue"
},
  "geometry": {"coordinates":[-0.0730800033,51.5701408386],"type":"Point"}
}