{
  "type": "Feature",
  "properties": {
    "addr:full":"139 Acklam Road Middlesbrough North Yorkshire TS5 5HR",
    "addr:housenumber":"139",
    "addr:postcode":"ts5 5hr",
    "addr:street":"Acklam Road",
    "iso:country":"GB",
    "sg:address":"139 Acklam Road",
    "sg:city":"Middlesbrough",
    "sg:classifiers":[
        {
            "category":"Social Services",
            "subcategory":"Job Training",
            "type":"Services"
        },
        {
            "category":"Real Estate",
            "subcategory":"Architect",
            "type":"Services"
        }
    ],
    "sg:phone":"+44 1642 814797",
    "sg:postcode":"TS5 5HR",
    "sg:province":"North Yorkshire",
    "sg:tags":[
        "draughtsman",
        "drawing"
    ],
    "wof:name":"N POULTER",
    "wof:placetype":"venue"
},
  "geometry": {"coordinates":[-1.2626650333,54.5521469116],"type":"Point"}
}