{
  "type": "Feature",
  "properties": {
    "addr:full":"20 Acacia Avenue, Birstall Leicester Leicestershire LE4 4HA",
    "addr:housenumber":"20",
    "addr:postcode":"le4 4ha",
    "addr:street":"Acacia Avenue",
    "iso:country":"GB",
    "sg:address":"20 Acacia Avenue, Birstall",
    "sg:city":"Leicester",
    "sg:classifiers":[
        {
            "category":"Home & Garden",
            "subcategory":"Kitchen Supply",
            "type":"Retail Goods"
        }
    ],
    "sg:phone":"+44 116 267 2674",
    "sg:postcode":"LE4 4HA",
    "sg:province":"Leicestershire",
    "sg:tags":[
        "equipment",
        "catering"
    ],
    "wof:name":"Andrew Wright",
    "wof:placetype":"venue"
},
  "geometry": {"coordinates":[-1.119408,52.684254],"type":"Point"}
}