{
  "type": "Feature",
  "properties": {
    "addr:full":"Factory Yard, Rear Of 176 Uxbridge Road London Greater London W7 3TB",
    "addr:housenumber":"rear;176",
    "addr:postcode":"w7 3tb",
    "addr:street":"Factory Yard;Uxbridge Road",
    "iso:country":"GB",
    "sg:address":"Factory Yard, Rear Of 176 Uxbridge Road",
    "sg:city":"London",
    "sg:classifiers":[
        {
            "category":"Retail",
            "subcategory":"Auto Repair",
            "type":"Services"
        }
    ],
    "sg:postcode":"W7 3TB",
    "sg:province":"Greater London",
    "sg:tags":[
        "modification",
        "garage"
    ],
    "wof:name":"Jump Start",
    "wof:placetype":"venue"
},
  "geometry": {"coordinates":[-0.341409,51.511539],"type":"Point"}
}