{
  "type": "Feature",
  "properties": {
    "iso:country":"GB",
    "sg:address":"Pandy, Grosmont",
    "sg:city":"Abergavenny",
    "sg:classifiers":[
        {
            "category":"Farming",
            "subcategory":"Farm",
            "type":"Manufacturing & Wholesale Goods"
        }
    ],
    "sg:phone":"+44 1981 240266",
    "sg:postcode":"NP7 8HG",
    "sg:province":"Herefordshire",
    "sg:tags":[
        "mixed",
        "crop"
    ],
    "wof:name":"D J & J E Watkins",
    "wof:placetype":"venue"
},
  "geometry": {"coordinates":[-2.868297,51.916309],"type":"Point"}
}