{
  "type": "Feature",
  "properties": {
    "addr:full":"Lower Milltown, Milltown Lostwithiel Cornwall PL22 0JL",
    "addr:postcode":"pl22 0jl",
    "addr:street":"Lower Milltown",
    "iso:country":"GB",
    "sg:address":"Lower Milltown, Milltown",
    "sg:city":"Lostwithiel",
    "sg:classifiers":[
        {
            "category":"Travel",
            "subcategory":"Travel Agent",
            "type":"Entertainment"
        }
    ],
    "sg:postcode":"PL22 0JL",
    "sg:province":"Cornwall",
    "wof:name":"Green Theme International Home Exchange Holidays",
    "wof:placetype":"venue"
},
  "geometry": {"coordinates":[-4.669903,50.408272],"type":"Point"}
}