{
  "type": "Feature",
  "properties": {
    "addr:full":"Outwood Surgery, 581a Leeds Rd Wakefield West Yorkshire WF1 2JL",
    "addr:housenumber":"581a",
    "addr:postcode":"wf1 2jl",
    "addr:street":"Leeds Rd",
    "iso:country":"GB",
    "sg:address":"Outwood Surgery, 581a Leeds Rd",
    "sg:city":"Wakefield",
    "sg:classifiers":[
        {
            "category":"Health Services",
            "subcategory":"Doctor",
            "type":"Services"
        }
    ],
    "sg:phone":"+44 1924 822626",
    "sg:postcode":"WF1 2JL",
    "sg:province":"West Yorkshire",
    "sg:tags":[
        "practitioners"
    ],
    "wof:name":"Jepson, A",
    "wof:placetype":"venue"
},
  "geometry": {"coordinates":[-1.5028300285,53.7092704773],"type":"Point"}
}