{
  "type": "Feature",
  "properties": {
    "iso:country":"GB",
    "sg:address":"107 Charterhall Grove",
    "sg:city":"Edinburgh",
    "sg:classifiers":[
        {
            "category":"Retail",
            "subcategory":"Auto Repair",
            "type":"Services"
        }
    ],
    "sg:phone":"+44 131 667 0602",
    "sg:postcode":"EH9 3HT",
    "sg:province":"City of Edinburgh",
    "sg:tags":[
        "modification",
        "garage",
        "related"
    ],
    "wof:name":"Scotroen Motors",
    "wof:placetype":"venue"
},
  "geometry": {"coordinates":[-3.1886959076,55.9269218445],"type":"Point"}
}