{
  "type": "Feature",
  "properties": {
    "addr:full":"17 Cliff Road Newquay Cornwall TR7 2NE",
    "addr:housenumber":"17",
    "addr:postcode":"tr7 2ne",
    "addr:street":"Cliff Road",
    "iso:country":"GB",
    "sg:address":"17 Cliff Road",
    "sg:city":"Newquay",
    "sg:classifiers":[
        {
            "category":"Recreation",
            "subcategory":"Water Park",
            "type":"Entertainment"
        },
        {
            "category":"Sports & Exercise",
            "subcategory":"Sports Center",
            "type":"Entertainment"
        }
    ],
    "sg:phone":"+44 1637 878880",
    "sg:postcode":"TR7 2NE",
    "sg:province":"Cornwall",
    "sg:tags":[
        "shop",
        "good"
    ],
    "wof:name":"Boardwalk Surf Ltd.",
    "wof:placetype":"venue"
},
  "geometry": {"coordinates":[-5.075882,50.415775],"type":"Point"}
}