{
  "type": "Feature",
  "properties": {
    "iso:country":"GB",
    "sg:address":"2 Soverign Pk, Clevland Way",
    "sg:city":"Hemel Hempstead",
    "sg:classifiers":[
        {
            "category":"Professional",
            "subcategory":"Detective & Security Services",
            "type":"Services"
        }
    ],
    "sg:postcode":"HP2 7DA",
    "sg:province":"Hertfordshire",
    "sg:tags":[
        "alarm",
        "burglar",
        "system"
    ],
    "wof:name":"Silver Crest Air Conditioning Ltd",
    "wof:placetype":"venue"
},
  "geometry": {"coordinates":[-0.4397189915,51.7683105469],"type":"Point"}
}