{
  "type": "Feature",
  "properties": {
    "addr:full":"98 Veronica Gardens Streatham Greater London SW16 5JS",
    "addr:housenumber":"98",
    "addr:postcode":"sw16 5js",
    "addr:street":"Veronica Gardens",
    "iso:country":"GB",
    "sg:address":"98 Veronica Gardens",
    "sg:city":"Streatham",
    "sg:classifiers":[
        {
            "category":"Sports & Exercise",
            "subcategory":"Tennis Court",
            "type":"Entertainment"
        }
    ],
    "sg:phone":"+44 20 8679 8118",
    "sg:postcode":"SW16 5JS",
    "sg:province":"Greater London",
    "sg:tags":[
        "breakdown",
        "recovery"
    ],
    "wof:name":"Natec",
    "wof:placetype":"venue"
},
  "geometry": {"coordinates":[-0.1430059969,51.4113235474],"type":"Point"}
}