{
  "type": "Feature",
  "properties": {
    "iso:country":"GB",
    "sg:address":"Winterstoke Road",
    "sg:city":"Weston-super-mare",
    "sg:classifiers":[
        {
            "category":"Professional",
            "subcategory":"Engineering",
            "type":"Services"
        }
    ],
    "sg:phone":"+44 1934 628547",
    "sg:postcode":"BS23 3YS",
    "sg:province":"Somerset",
    "wof:name":"R E Page",
    "wof:placetype":"venue"
},
  "geometry": {"coordinates":[-2.960849,51.340328],"type":"Point"}
}