{
  "type": "Feature",
  "properties": {
    "addr:full":"2 Rockleaze Avenue, Sneyd Park Bristol City of Bristol BS9 1NG",
    "addr:housenumber":"2",
    "addr:postcode":"bs9 1ng",
    "addr:street":"Rockleaze Avenue Sneyd Park",
    "iso:country":"GB",
    "sg:address":"2 Rockleaze Avenue, Sneyd Park",
    "sg:city":"Bristol",
    "sg:classifiers":[
        {
            "category":"Professional",
            "subcategory":"Management & Consulting",
            "type":"Services"
        }
    ],
    "sg:phone":"+44 117 962 6390",
    "sg:postcode":"BS9 1NG",
    "sg:province":"City of Bristol",
    "sg:tags":[
        "consultant",
        "training"
    ],
    "wof:name":"M-Power Training Ltd.",
    "wof:placetype":"venue"
},
  "geometry": {"coordinates":[-2.629645,51.473354],"type":"Point"}
}