{
  "type": "Feature",
  "properties": {
    "iso:country":"GB",
    "sg:address":"39 Christian Crescent",
    "sg:city":"Edinburgh",
    "sg:classifiers":[
        {
            "category":"Building & Trades",
            "subcategory":"Cleaning & Sanitation",
            "type":"Services"
        }
    ],
    "sg:phone":"+44 131 657 5266",
    "sg:postcode":"EH15 3AB",
    "sg:province":"City of Edinburgh",
    "sg:tags":[
        "commercial"
    ],
    "wof:name":"Classic Carpet Cleaners",
    "wof:placetype":"venue"
},
  "geometry": {"coordinates":[-3.1044750214,55.9457702637],"type":"Point"}
}