{
  "type": "Feature",
  "properties": {
    "iso:country":"GB",
    "sg:address":"135 Palatine Rd",
    "sg:city":"Manchester",
    "sg:classifiers":[
        {
            "category":"Health Services",
            "subcategory":"Doctor",
            "type":"Services"
        }
    ],
    "sg:phone":"+44 161 445 0126",
    "sg:postcode":"M20 3YA",
    "sg:province":"Greater Manchester",
    "sg:tags":[
        "practitioners"
    ],
    "wof:name":"Norburn, P S",
    "wof:placetype":"venue"
},
  "geometry": {"coordinates":[-2.235882,53.425793],"type":"Point"}
}