{
  "type": "Feature",
  "properties": {
    "addr:full":"18a Lichfield St Walsall West Midlands WS1 1TJ",
    "addr:housenumber":"18a",
    "addr:postcode":"ws1 1tj",
    "addr:street":"Lichfield St",
    "iso:country":"GB",
    "sg:address":"18a Lichfield St",
    "sg:city":"Walsall",
    "sg:classifiers":[
        {
            "category":"Real Estate",
            "subcategory":"Real Estate Agent",
            "type":"Services"
        }
    ],
    "sg:phone":"+44 1922 611800",
    "sg:postcode":"WS1 1TJ",
    "sg:province":"West Midlands",
    "wof:name":"Moore Group The",
    "wof:placetype":"venue"
},
  "geometry": {"coordinates":[-1.978131,52.586849],"type":"Point"}
}