{
  "type": "Feature",
  "properties": {
    "iso:country":"GB",
    "sg:address":"17 Gullymoss Place",
    "sg:city":"Westhill",
    "sg:classifiers":[
        {
            "category":"Professional",
            "subcategory":"Management & Consulting",
            "type":"Services"
        }
    ],
    "sg:phone":"+44 1224 743869",
    "sg:postcode":"AB32 6PP",
    "sg:province":"Aberdeen City",
    "sg:tags":[
        "consultant",
        "business"
    ],
    "wof:name":"L S 2000",
    "wof:placetype":"venue"
},
  "geometry": {"coordinates":[-2.302413,57.151154],"type":"Point"}
}