{
  "type": "Feature",
  "properties": {
    "addr:full":"101 Fore Street, St Marychurch Torquay Devon TQ1 4PZ",
    "addr:housenumber":"101",
    "addr:postcode":"tq1 4pz",
    "addr:street":"Fore Street",
    "iso:country":"GB",
    "sg:address":"101 Fore Street, St Marychurch",
    "sg:city":"Torquay",
    "sg:classifiers":[
        {
            "category":"Communications",
            "subcategory":"Film & Video Production",
            "type":"Services"
        }
    ],
    "sg:phone":"+44 1803 323303",
    "sg:postcode":"TQ1 4PZ",
    "sg:province":"Devon",
    "sg:tags":[
        "tv"
    ],
    "wof:name":"St Marychurch Tv & Video Centre",
    "wof:placetype":"venue"
},
  "geometry": {"coordinates":[-3.524782896,50.483997345],"type":"Point"}
}