{
  "type": "Feature",
  "properties": {
    "addr:full":"32 Quarry Park Road, Plymstock Plymouth Devon PL9 7BB",
    "addr:housenumber":"32",
    "addr:postcode":"pl9 7bb",
    "addr:street":"Quarry Park Road",
    "iso:country":"GB",
    "sg:address":"32 Quarry Park Road, Plymstock",
    "sg:city":"Plymouth",
    "sg:classifiers":[
        {
            "category":"Building & Trades",
            "subcategory":"Cleaning & Sanitation",
            "type":"Services"
        }
    ],
    "sg:phone":"+44 1752 406565",
    "sg:postcode":"PL9 7BB",
    "sg:province":"Devon",
    "sg:tags":[
        "sweep",
        "chimney"
    ],
    "wof:name":"Vivid Clean Sweep",
    "wof:placetype":"venue"
},
  "geometry": {"coordinates":[-4.097952,50.359444],"type":"Point"}
}