{
  "type": "Feature",
  "properties": {
    "addr:full":"9 Ashbrooke Park, Parkside Lane Leeds West Yorkshire LS11 5SF",
    "addr:housenumber":"9",
    "addr:postcode":"ls11 5sf",
    "addr:street":"Ashbrooke Park Parkside Lane",
    "iso:country":"GB",
    "sg:address":"9 Ashbrooke Park, Parkside Lane",
    "sg:city":"Leeds",
    "sg:classifiers":[
        {
            "category":"Communications",
            "type":"Services"
        }
    ],
    "sg:phone":"+44 113 272 0072",
    "sg:postcode":"LS11 5SF",
    "sg:province":"West Yorkshire",
    "sg:tags":[
        "telecommunication"
    ],
    "wof:name":"JWE Telecom",
    "wof:placetype":"venue"
},
  "geometry": {"coordinates":[-1.544154,53.771225],"type":"Point"}
}