{
  "type": "Feature",
  "properties": {
    "addr:full":"57 Shelton Street London Greater London WC2H 9HE",
    "addr:housenumber":"57",
    "addr:postcode":"wc2h 9he",
    "addr:street":"Shelton Street",
    "iso:country":"GB",
    "sg:address":"57 Shelton Street",
    "sg:city":"London",
    "sg:classifiers":[
        {
            "category":"Shopping",
            "subcategory":"Books",
            "type":"Retail Goods"
        }
    ],
    "sg:phone":"+44 20 7836 3954",
    "sg:postcode":"WC2H 9HE",
    "sg:province":"Greater London",
    "wof:name":"Imperial College Press Ltd.",
    "wof:placetype":"venue"
},
  "geometry": {"coordinates":[-0.1240470037,51.5146026611],"type":"Point"}
}