{
  "type": "Feature",
  "properties": {
    "iso:country":"GB",
    "sg:address":"Unit 10 Blacklands Way, Abingdon Business Park",
    "sg:city":"Abingdon",
    "sg:classifiers":[
        {
            "category":"Manufacturing",
            "subcategory":"Rubber & Plastics",
            "type":"Manufacturing & Wholesale Goods"
        },
        {
            "category":"Wholesale",
            "subcategory":"Chemicals & Plastics",
            "type":"Manufacturing & Wholesale Goods"
        }
    ],
    "sg:phone":"+44 1235 550011",
    "sg:postcode":"OX14 1RD",
    "sg:province":"Oxfordshire",
    "sg:tags":[
        "machine",
        "ind",
        "product",
        "manufacturer",
        "making"
    ],
    "sg:website":"http://www.motan.co.uk",
    "wof:name":"Motan Ltd.",
    "wof:placetype":"venue"
},
  "geometry": {"coordinates":[-1.303447,51.672333],"type":"Point"}
}