{
  "type": "Feature",
  "properties": {
    "iso:country":"GB",
    "sg:address":"91-93 London Road, Hazel Gro",
    "sg:city":"Stockport",
    "sg:classifiers":[
        {
            "category":"Home & Garden",
            "subcategory":"Household Appliances",
            "type":"Retail Goods"
        }
    ],
    "sg:postcode":"SK7 4AX",
    "sg:province":"Cheshire",
    "sg:tags":[
        "domestic",
        "centre"
    ],
    "wof:name":"Modern Aids Ltd.",
    "wof:placetype":"venue"
},
  "geometry": {"coordinates":[-2.124242,53.382141],"type":"Point"}
}