{
  "type": "Feature",
  "properties": {
    "addr:full":"Huntswood, The Butts, Enmore Grn Shaftesbury Dorset SP7 8LG",
    "addr:postcode":"sp7 8lg",
    "addr:street":"The Butts",
    "iso:country":"GB",
    "sg:address":"Huntswood, The Butts, Enmore Grn",
    "sg:city":"Shaftesbury",
    "sg:classifiers":[
        {
            "category":"Professional",
            "subcategory":"Engineering",
            "type":"Services"
        }
    ],
    "sg:phone":"+44 1747 854609",
    "sg:postcode":"SP7 8LG",
    "sg:province":"Dorset",
    "sg:tags":[
        "contractor",
        "electrical",
        "engineer"
    ],
    "wof:name":"Owen Brockway Electricians",
    "wof:placetype":"venue"
},
  "geometry": {"coordinates":[-2.187124,51.005764],"type":"Point"}
}