{
  "type": "Feature",
  "properties": {
    "iso:country":"GB",
    "sg:address":"32a Laughton Rd, Dinnington",
    "sg:city":"Sheffield",
    "sg:classifiers":[
        {
            "category":"Education",
            "subcategory":"Music School",
            "type":"Public Place"
        }
    ],
    "sg:postcode":"S25 2PS",
    "sg:province":"South Yorkshire",
    "sg:tags":[
        "conservatory"
    ],
    "wof:name":"Coldseal Ltd",
    "wof:placetype":"venue"
},
  "geometry": {"coordinates":[-1.209529,53.365307],"type":"Point"}
}