{
  "type": "Feature",
  "properties": {
    "addr:full":"729 Garrett Lane, Tooting London Greater London SW17 0PD",
    "addr:housenumber":"729",
    "addr:postcode":"sw17 0pd",
    "addr:street":"Garrett Lane",
    "iso:country":"GB",
    "sg:address":"729 Garrett Lane, Tooting",
    "sg:city":"London",
    "sg:classifiers":[
        {
            "category":"Shopping",
            "subcategory":"Antiques",
            "type":"Retail Goods"
        }
    ],
    "sg:postcode":"SW17 0PD",
    "sg:province":"Greater London",
    "wof:name":"Tracey Antiques",
    "wof:placetype":"venue"
},
  "geometry": {"coordinates":[-0.1851889938,51.4345703125],"type":"Point"}
}