{
  "type": "Feature",
  "properties": {
    "addr:full":"31c Old Park Lane Southport Lancashire PR9 7BQ",
    "addr:housenumber":"31c",
    "addr:postcode":"pr9 7bq",
    "addr:street":"Old Park Lane",
    "iso:country":"GB",
    "sg:address":"31c Old Park Lane",
    "sg:city":"Southport",
    "sg:classifiers":[
        {
            "category":"Retail",
            "subcategory":"Auto Repair",
            "type":"Services"
        }
    ],
    "sg:postcode":"PR9 7BQ",
    "sg:province":"Lancashire",
    "sg:tags":[
        "body",
        "car"
    ],
    "wof:name":"Cross & Watson (Southport) Ltd.",
    "wof:placetype":"venue"
},
  "geometry": {"coordinates":[-2.9673640728,53.6518173218],"type":"Point"}
}