{
  "type": "Feature",
  "properties": {
    "iso:country":"GB",
    "sg:address":"Bonnyhill Farm Dairy",
    "sg:city":"Bonnybridge",
    "sg:classifiers":[
        {
            "category":"Farming",
            "subcategory":"Dairy Farm",
            "type":"Manufacturing & Wholesale Goods"
        }
    ],
    "sg:phone":"+44 1324 812144",
    "sg:postcode":"FK4 2EP",
    "sg:province":"Falkirk",
    "sg:tags":[
        "farmer"
    ],
    "wof:name":"John Pollock & Sons",
    "wof:placetype":"venue"
},
  "geometry": {"coordinates":[-3.8700120449,55.9917602539],"type":"Point"}
}