{
  "type": "Feature",
  "properties": {
    "addr:full":"Old Church Road, Mawnan Smith Falmouth Cornwall TR11 5HU",
    "addr:postcode":"tr11 5hu",
    "addr:street":"Old Church Road",
    "iso:country":"GB",
    "sg:address":"Old Church Road, Mawnan Smith",
    "sg:city":"Falmouth",
    "sg:classifiers":[
        {
            "category":"Travel",
            "subcategory":"Hotels & Motels",
            "type":"Entertainment"
        }
    ],
    "sg:phone":"+44 1326 250340",
    "sg:postcode":"TR11 5HU",
    "sg:province":"Cornwall",
    "wof:name":"Nansidwell Hotel",
    "wof:placetype":"venue"
},
  "geometry": {"coordinates":[-5.110490799,50.1180458069],"type":"Point"}
}