{
  "type": "Feature",
  "properties": {
    "iso:country":"GB",
    "sg:address":"High Street, Partridge Grn",
    "sg:city":"Horsham",
    "sg:classifiers":[
        {
            "category":"Shopping",
            "subcategory":"News",
            "type":"Retail Goods"
        }
    ],
    "sg:phone":"+44 1403 710481",
    "sg:postcode":"RH13 8HU",
    "sg:province":"West Sussex",
    "sg:tags":[
        "newsagent"
    ],
    "wof:name":"P R Patel",
    "wof:placetype":"venue"
},
  "geometry": {"coordinates":[-0.3013040125,50.9606361389],"type":"Point"}
}