{
  "type": "Feature",
  "properties": {
    "addr:full":"55 Peel Rd Harrow Greater London HA3 7QX",
    "addr:housenumber":"55",
    "addr:postcode":"ha3 7qx",
    "addr:street":"Peel Rd",
    "iso:country":"GB",
    "sg:address":"55 Peel Rd",
    "sg:city":"Harrow",
    "sg:classifiers":[
        {
            "category":"Building & Trades",
            "subcategory":"Cleaning & Sanitation",
            "type":"Services"
        }
    ],
    "sg:phone":"+44 20 8863 8151",
    "sg:postcode":"HA3 7QX",
    "sg:province":"Greater London",
    "sg:tags":[
        "commercial"
    ],
    "wof:name":"Revac Cleaning Contractors",
    "wof:placetype":"venue"
},
  "geometry": {"coordinates":[-0.3317579925,51.5942382812],"type":"Point"}
}