{
  "type": "Feature",
  "properties": {
    "addr:full":"24 Savile Parade Halifax West Yorkshire HX1 2XJ",
    "addr:housenumber":"24",
    "addr:postcode":"hx1 2xj",
    "addr:street":"Savile Parade",
    "iso:country":"GB",
    "sg:address":"24 Savile Parade",
    "sg:city":"Halifax",
    "sg:classifiers":[
        {
            "category":"Manufacturing",
            "subcategory":"Rubber & Plastics",
            "type":"Manufacturing & Wholesale Goods"
        }
    ],
    "sg:phone":"+44 1422 346800",
    "sg:postcode":"HX1 2XJ",
    "sg:province":"West Yorkshire",
    "sg:tags":[
        "supplier",
        "stockist"
    ],
    "wof:name":"Evergreen Products",
    "wof:placetype":"venue"
},
  "geometry": {"coordinates":[-1.869818,53.713295],"type":"Point"}
}