{
  "type": "Feature",
  "properties": {
    "iso:country":"GB",
    "sg:address":"Unit C, Copyhold La",
    "sg:city":"Dorchester",
    "sg:classifiers":[
        {
            "category":"Autos & Motor Vehicles",
            "subcategory":"Automobile Sales",
            "type":"Retail Goods"
        }
    ],
    "sg:postcode":"DT2 9LT",
    "sg:province":"Dorset",
    "sg:tags":[
        "car"
    ],
    "wof:name":"4 X 4",
    "wof:placetype":"venue"
},
  "geometry": {"coordinates":[-2.542241,50.714188],"type":"Point"}
}