{
  "type": "Feature",
  "properties": {
    "addr:full":"Merrion, Clive Avenue Church Stretton Shropshire SY6 7BL",
    "addr:postcode":"sy6 7bl",
    "addr:street":"Clive Avenue",
    "iso:country":"GB",
    "sg:address":"Merrion, Clive Avenue",
    "sg:city":"Church Stretton",
    "sg:classifiers":[
        {
            "category":"Organizations",
            "subcategory":"Non-profit Organization",
            "type":"Services"
        }
    ],
    "sg:postcode":"SY6 7BL",
    "sg:province":"Shropshire",
    "sg:tags":[
        "organisation",
        "voluntary",
        "charity"
    ],
    "wof:name":"The Cancer Research Campaign",
    "wof:placetype":"venue"
},
  "geometry": {"coordinates":[-2.8003339767,52.5376548767],"type":"Point"}
}