{
  "type": "Feature",
  "properties": {
    "addr:full":"North Watford Youth & Community, Centre, Southwold Road Watford Hertfordshire WD24 7DP",
    "addr:postcode":"wd24 7dp",
    "addr:street":"Southwold Road",
    "iso:country":"GB",
    "sg:address":"North Watford Youth & Community, Centre, Southwold Road",
    "sg:city":"Watford",
    "sg:classifiers":[
        {
            "category":"Education",
            "subcategory":"Dance Studio",
            "type":"Public Place"
        }
    ],
    "sg:postcode":"WD24 7DP",
    "sg:province":"Hertfordshire",
    "sg:tags":[
        "school",
        "dancing"
    ],
    "wof:name":"Lorraine's School of Dance",
    "wof:placetype":"venue"
},
  "geometry": {"coordinates":[-0.3934200108,51.6747512817],"type":"Point"}
}