{
  "type": "Feature",
  "properties": {
    "iso:country":"GB",
    "sg:address":"26 Oswald Avenue",
    "sg:city":"Grangemouth",
    "sg:classifiers":[
        {
            "category":"Retail",
            "subcategory":"Auto Repair",
            "type":"Services"
        }
    ],
    "sg:phone":"+44 1324 483999",
    "sg:postcode":"FK3 9AF",
    "sg:province":"Falkirk",
    "sg:tags":[
        "modification",
        "garage"
    ],
    "wof:name":"Wilf's Ltd.",
    "wof:placetype":"venue"
},
  "geometry": {"coordinates":[-3.709911,56.01796],"type":"Point"}
}