{
  "type": "Feature",
  "properties": {
    "addr:full":"Flat 5, 25 Cheshire Rd Exmouth Devon EX8 4BW",
    "addr:housenumber":"25",
    "addr:postcode":"ex8 4bw",
    "addr:street":"Cheshire Rd",
    "iso:country":"GB",
    "sg:address":"Flat 5, 25 Cheshire Rd",
    "sg:city":"Exmouth",
    "sg:classifiers":[
        {
            "category":"Taxi",
            "type":"Transportation"
        }
    ],
    "sg:phone":"+44 1395 222067",
    "sg:postcode":"EX8 4BW",
    "sg:province":"Devon",
    "sg:tags":[
        "mini",
        "cab"
    ],
    "wof:name":"Steves Cars",
    "wof:placetype":"venue"
},
  "geometry": {"coordinates":[-3.4132890701,50.6194152832],"type":"Point"}
}