{
  "type": "Feature",
  "properties": {
    "iso:country":"GB",
    "sg:address":"3 East St",
    "sg:city":"Littlehampton",
    "sg:classifiers":[
        {
            "category":"Building & Trades",
            "subcategory":"Construction",
            "type":"Services"
        }
    ],
    "sg:phone":"+44 1903 734220",
    "sg:postcode":"BN17 6AU",
    "sg:province":"West Sussex",
    "sg:tags":[
        "paint",
        "household",
        "spraying"
    ],
    "wof:name":"Enterprising Hands",
    "wof:placetype":"venue"
},
  "geometry": {"coordinates":[-0.540844,50.809326],"type":"Point"}
}