{
  "type": "Feature",
  "properties": {
    "iso:country":"GB",
    "sg:address":"1a Alpin Road",
    "sg:city":"Dundee",
    "sg:classifiers":[
        {
            "category":"Farming",
            "subcategory":"Farm",
            "type":"Manufacturing & Wholesale Goods"
        },
        {
            "category":"Food & Beverages",
            "subcategory":"Groceries & Convenience Stores",
            "type":"Retail Goods"
        }
    ],
    "sg:postcode":"DD3 6HB",
    "sg:province":"Dundee City",
    "sg:tags":[
        "merchant",
        "egg",
        "producer"
    ],
    "wof:name":"J D FORREST",
    "wof:placetype":"venue"
},
  "geometry": {"coordinates":[-2.995072,56.472649],"type":"Point"}
}