{
  "type": "Feature",
  "properties": {
    "addr:full":"Lea Brook Farm, Collinge Fold Lane Rossendale Lancashire BB4 8JQ",
    "addr:postcode":"bb4 8jq",
    "addr:street":"Lea Brook Farm Collinge Fold Lane",
    "iso:country":"GB",
    "sg:address":"Lea Brook Farm, Collinge Fold Lane",
    "sg:city":"Rossendale",
    "sg:classifiers":[
        {
            "category":"Banks & Credit Unions",
            "subcategory":"Investment Brokerage",
            "type":"Services"
        }
    ],
    "sg:phone":"+44 1706 210412",
    "sg:postcode":"BB4 8JQ",
    "sg:province":"Lancashire",
    "sg:tags":[
        "contractor"
    ],
    "wof:name":"V & J Kempson",
    "wof:placetype":"venue"
},
  "geometry": {"coordinates":[-2.274824,53.708961],"type":"Point"}
}