{
  "type": "Feature",
  "properties": {
    "addr:full":"Tommy Taylors Lane Cheltenham Gloucestershire GL50 4RN",
    "addr:postcode":"gl50 4rn",
    "addr:street":"Taylors Lane",
    "iso:country":"GB",
    "sg:address":"Tommy Taylors Lane",
    "sg:city":"Cheltenham",
    "sg:classifiers":[
        {
            "category":"Community Center",
            "type":"Public Place"
        },
        {
            "category":"Arena",
            "subcategory":"Sports Club",
            "type":"Entertainment"
        }
    ],
    "sg:phone":"+44 1242 528764",
    "sg:postcode":"GL50 4RN",
    "sg:province":"Gloucestershire",
    "sg:tags":[
        "recreation",
        "ground",
        "leisure",
        "centre"
    ],
    "wof:name":"Cheltenham Recreation Centre",
    "wof:placetype":"venue"
},
  "geometry": {"coordinates":[-2.076179,51.915794],"type":"Point"}
}