{
  "type": "Feature",
  "properties": {
    "addr:full":"22 Gloucester Street Stroud Gloucestershire GL5 1QG",
    "addr:housenumber":"22",
    "addr:postcode":"gl5 1qg",
    "addr:street":"Gloucester Street",
    "iso:country":"GB",
    "sg:address":"22 Gloucester Street",
    "sg:city":"Stroud",
    "sg:classifiers":[
        {
            "category":"Restaurant",
            "type":"Food & Drink"
        }
    ],
    "sg:phone":"+44 1453 765430",
    "sg:postcode":"GL5 1QG",
    "sg:province":"Gloucestershire",
    "sg:tags":[
        "indian"
    ],
    "wof:name":"Exotikka",
    "wof:placetype":"venue"
},
  "geometry": {"coordinates":[-2.2174470425,51.7465667725],"type":"Point"}
}