{
  "type": "Feature",
  "properties": {
    "addr:full":"15-16 Hunters Lane Rugby Warwickshire CV21 1EA",
    "addr:housenumber":"15-16",
    "addr:postcode":"cv21 1ea",
    "addr:street":"Hunters Lane",
    "iso:country":"GB",
    "sg:address":"15-16 Hunters Lane",
    "sg:city":"Rugby",
    "sg:classifiers":[
        {
            "category":"Manufacturing",
            "subcategory":"Rubber & Plastics",
            "type":"Manufacturing & Wholesale Goods"
        }
    ],
    "sg:phone":"+44 1788 571316",
    "sg:postcode":"CV21 1EA",
    "sg:province":"Warwickshire",
    "sg:tags":[
        "injection",
        "moulding"
    ],
    "wof:name":"Hygrade Industrial Plastics Ltd.",
    "wof:placetype":"venue"
},
  "geometry": {"coordinates":[-1.245789,52.375381],"type":"Point"}
}