{
  "type": "Feature",
  "properties": {
    "addr:full":"9 Cemetery Lane Burnley Lancashire BB11 5DG",
    "addr:housenumber":"9",
    "addr:postcode":"bb11 5dg",
    "addr:street":"Cemetery Lane",
    "iso:country":"GB",
    "sg:address":"9 Cemetery Lane",
    "sg:city":"Burnley",
    "sg:classifiers":[
        {
            "category":"Building & Trades",
            "subcategory":"Construction",
            "type":"Services"
        }
    ],
    "sg:phone":"+44 1282 425858",
    "sg:postcode":"BB11 5DG",
    "sg:province":"Lancashire",
    "sg:tags":[
        "monumental",
        "mason"
    ],
    "wof:name":"H Stevenson & Sons Ltd.",
    "wof:placetype":"venue"
},
  "geometry": {"coordinates":[-2.2791609764,53.7830963135],"type":"Point"}
}