{
  "type": "Feature",
  "properties": {
    "iso:country":"GB",
    "sg:address":"22 Connaught Road",
    "sg:city":"Market Harborough",
    "sg:classifiers":[
        {
            "category":"Professional",
            "subcategory":"Business Services",
            "type":"Services"
        }
    ],
    "sg:phone":"+44 1858 465726",
    "sg:postcode":"LE16 7NG",
    "sg:province":"Leicestershire",
    "sg:tags":[
        "tile",
        "stockist"
    ],
    "wof:name":"Harborough Tiles Ltd.",
    "wof:placetype":"venue"
},
  "geometry": {"coordinates":[-0.915357,52.481071],"type":"Point"}
}