{
  "type": "Feature",
  "properties": {
    "addr:full":"5a Royal Exchange Square Glasgow Glasgow City G1 3AH",
    "addr:housenumber":"5a",
    "addr:postcode":"g1 3ah",
    "addr:street":"Royal Exchange Square",
    "iso:country":"GB",
    "sg:address":"5a Royal Exchange Square",
    "sg:city":"Glasgow",
    "sg:classifiers":[
        {
            "category":"Organizations",
            "subcategory":"Religious Organization",
            "type":"Services"
        }
    ],
    "sg:phone":"+44 141 226 3391",
    "sg:postcode":"G1 3AH",
    "sg:province":"Glasgow City",
    "sg:tags":[
        "organisation"
    ],
    "wof:name":"St Paul Multimedia",
    "wof:placetype":"venue"
},
  "geometry": {"coordinates":[-4.252254,55.859798],"type":"Point"}
}