{
  "type": "Feature",
  "properties": {
    "iso:country":"GB",
    "sg:address":"Daldorn Farm",
    "sg:city":"Doune",
    "sg:classifiers":[
        {
            "category":"Farming",
            "subcategory":"Farm",
            "type":"Manufacturing & Wholesale Goods"
        }
    ],
    "sg:phone":"+44 1786 841307",
    "sg:postcode":"FK16 6HH",
    "sg:province":"Stirling",
    "sg:tags":[
        "mixed",
        "crop"
    ],
    "wof:name":"T G Macgregor",
    "wof:placetype":"venue"
},
  "geometry": {"coordinates":[-4.053243,56.190117],"type":"Point"}
}