{
  "type": "Feature",
  "properties": {
    "iso:country":"GB",
    "sg:address":"22 Post Office Road",
    "sg:city":"Bournemouth",
    "sg:classifiers":[
        {
            "category":"Professional",
            "type":"Services"
        }
    ],
    "sg:postcode":"BH1 1BA",
    "sg:province":"Dorset",
    "sg:tags":[
        "caterer"
    ],
    "wof:name":"Campions",
    "wof:placetype":"venue"
},
  "geometry": {"coordinates":[-1.879056,50.720821],"type":"Point"}
}