{
  "type": "Feature",
  "properties": {
    "iso:country":"GB",
    "sg:address":"467 Rotherham Rd",
    "sg:city":"Barnsley",
    "sg:classifiers":[
        {
            "category":"Wholesale",
            "subcategory":"Home Furnishings",
            "type":"Manufacturing & Wholesale Goods"
        }
    ],
    "sg:phone":"+44 1226 205317",
    "sg:postcode":"S71 1XB",
    "sg:province":"South Yorkshire",
    "sg:tags":[
        "wsale",
        "rug",
        "carpet"
    ],
    "wof:name":"Wilshire Carpets",
    "wof:placetype":"venue"
},
  "geometry": {"coordinates":[-1.4701410532,53.5743713379],"type":"Point"}
}