{
  "type": "Feature",
  "properties": {
    "addr:full":"95 Crossefield Road, Cheadle Hulme Cheadle Cheshire SK8 5PD",
    "addr:housenumber":"95",
    "addr:postcode":"sk8 5pd",
    "addr:street":"Crossefield Road",
    "iso:country":"GB",
    "sg:address":"95 Crossefield Road, Cheadle Hulme",
    "sg:city":"Cheadle",
    "sg:classifiers":[
        {
            "category":"Community Center",
            "subcategory":"Youth",
            "type":"Public Place"
        }
    ],
    "sg:postcode":"SK8 5PD",
    "sg:province":"Cheshire",
    "sg:tags":[
        "organisation",
        "centre"
    ],
    "wof:name":"Cheadle & District Scout Council",
    "wof:placetype":"venue"
},
  "geometry": {"coordinates":[-2.188695,53.382618],"type":"Point"}
}