{
  "type": "Feature",
  "properties": {
    "iso:country":"GB",
    "sg:address":"2-4 Northgate St",
    "sg:city":"Ipswich",
    "sg:classifiers":[
        {
            "category":"Shopping",
            "subcategory":"Beauty & Cosmetics",
            "type":"Retail Goods"
        }
    ],
    "sg:phone":"+44 1473 254156",
    "sg:postcode":"IP1 3BZ",
    "sg:province":"Suffolk",
    "sg:tags":[
        "wig",
        "hairpiece"
    ],
    "wof:name":"Frobisher Hair Designs",
    "wof:placetype":"venue"
},
  "geometry": {"coordinates":[1.156444,52.057755],"type":"Point"}
}