{
  "type": "Feature",
  "properties": {
    "iso:country":"GB",
    "sg:address":"Unit 5 Meadow Rd",
    "sg:city":"Motherwell",
    "sg:classifiers":[
        {
            "category":"Wholesale",
            "subcategory":"Vending Machines",
            "type":"Manufacturing & Wholesale Goods"
        }
    ],
    "sg:postcode":"ML1 1QE",
    "sg:province":"North Lanarkshire",
    "sg:tags":[
        "sale"
    ],
    "wof:name":"Refrigerated Dispense Systems Ltd",
    "wof:placetype":"venue"
},
  "geometry": {"coordinates":[-3.979197,55.785023],"type":"Point"}
}