{
  "type": "Feature",
  "properties": {
    "iso:country":"GB",
    "sg:address":"Unit A4",
    "sg:city":"Gravesend",
    "sg:classifiers":[
        {
            "category":"Autos & Motor Vehicles",
            "subcategory":"Auto Supplies",
            "type":"Retail Goods"
        }
    ],
    "sg:phone":"+44 1474 561055",
    "sg:postcode":"DA11 0DL",
    "sg:province":"Kent",
    "sg:tags":[
        "windscreen"
    ],
    "wof:name":"Millennium Windscreens",
    "wof:placetype":"venue"
},
  "geometry": {"coordinates":[0.364606,51.432827],"type":"Point"}
}