{
  "type": "Feature",
  "properties": {
    "iso:country":"GB",
    "sg:address":"60 Newport Road",
    "sg:city":"Caldicot",
    "sg:classifiers":[
        {
            "category":"Restaurant",
            "type":"Food & Drink"
        }
    ],
    "sg:phone":"+44 1291 425122",
    "sg:postcode":"NP26 4BR",
    "sg:province":"Monmouthshire",
    "sg:tags":[
        "indian"
    ],
    "wof:name":"The Knight of Bengal",
    "wof:placetype":"venue"
},
  "geometry": {"coordinates":[-2.753024,51.590389],"type":"Point"}
}