{
  "type": "Feature",
  "properties": {
    "iso:country":"GB",
    "sg:address":"Heaton House, King Street",
    "sg:city":"Nairn",
    "sg:classifiers":[
        {
            "category":"Cafe",
            "type":"Food & Drink"
        }
    ],
    "sg:phone":"+44 1667 454740",
    "sg:postcode":"IV12 4BQ",
    "sg:province":"Highland",
    "sg:tags":[
        "tea",
        "room"
    ],
    "wof:name":"The Wooden Spoon Cafe",
    "wof:placetype":"venue"
},
  "geometry": {"coordinates":[-3.865606,57.587475],"type":"Point"}
}