{
  "type": "Feature",
  "properties": {
    "addr:full":"68 Cranbourne Park, Hedge End Southampton Hampshire SO30 0NY",
    "addr:housenumber":"68",
    "addr:postcode":"so30 0ny",
    "addr:street":"Cranbourne Park",
    "iso:country":"GB",
    "sg:address":"68 Cranbourne Park, Hedge End",
    "sg:city":"Southampton",
    "sg:classifiers":[
        {
            "category":"Retail",
            "subcategory":"Repair Shop",
            "type":"Services"
        }
    ],
    "sg:phone":"+44 1489 786956",
    "sg:postcode":"SO30 0NY",
    "sg:province":"Hampshire",
    "sg:tags":[
        "maintenance"
    ],
    "wof:name":"T G S Property Maintenance",
    "wof:placetype":"venue"
},
  "geometry": {"coordinates":[-1.3000400066,50.9038314819],"type":"Point"}
}