{
  "type": "Feature",
  "properties": {
    "iso:country":"GB",
    "sg:address":"22-36 St Andrews Road, Bordesley",
    "sg:city":"Birmingham",
    "sg:classifiers":[
        {
            "category":"Professional",
            "subcategory":"Engineering",
            "type":"Services"
        }
    ],
    "sg:phone":"+44 121 766 6020",
    "sg:postcode":"B9 4LN",
    "sg:province":"West Midlands",
    "sg:tags":[
        "civil",
        "engineer"
    ],
    "wof:name":"Glenpark Ltd.",
    "wof:placetype":"venue"
},
  "geometry": {"coordinates":[-1.874239,52.478539],"type":"Point"}
}