{
  "type": "Feature",
  "properties": {
    "addr:full":"13 Mesnes Street Wigan Lancashire WN1 1QP",
    "addr:housenumber":"13",
    "addr:postcode":"wn1 1qp",
    "addr:street":"Mesnes Street",
    "iso:country":"GB",
    "sg:address":"13 Mesnes Street",
    "sg:city":"Wigan",
    "sg:classifiers":[
        {
            "category":"Food & Beverages",
            "subcategory":"Bakery",
            "type":"Retail Goods"
        }
    ],
    "sg:phone":"+44 1942 707108",
    "sg:postcode":"WN1 1QP",
    "sg:province":"Lancashire",
    "sg:tags":[
        "baker"
    ],
    "wof:name":"Waterfield's (Leigh)",
    "wof:placetype":"venue"
},
  "geometry": {"coordinates":[-2.631874,53.549244],"type":"Point"}
}