{
  "type": "Feature",
  "properties": {
    "iso:country":"GB",
    "sg:address":"Bentinck Street Indust Estate",
    "sg:city":"Manchester",
    "sg:classifiers":[
        {
            "category":"Professional",
            "subcategory":"Art Services",
            "type":"Services"
        }
    ],
    "sg:phone":"+44 161 831 9058",
    "sg:postcode":"M15 4LN",
    "sg:province":"Cheshire",
    "sg:tags":[
        "consultant",
        "design"
    ],
    "wof:name":"Crawford Mcdermott Partnership",
    "wof:placetype":"venue"
},
  "geometry": {"coordinates":[-2.2616438866,53.4716796875],"type":"Point"}
}