{
  "type": "Feature",
  "properties": {
    "iso:country":"GB",
    "sg:address":"North Bridge Road",
    "sg:city":"Berkhamsted",
    "sg:classifiers":[
        {
            "category":"Manufacturing",
            "subcategory":"Metals",
            "type":"Manufacturing & Wholesale Goods"
        },
        {
            "category":"Wholesale",
            "subcategory":"Metals & Minerals",
            "type":"Manufacturing & Wholesale Goods"
        }
    ],
    "sg:phone":"+44 1442 876969",
    "sg:postcode":"HP4 1EH",
    "sg:province":"Bedfordshire",
    "sg:tags":[
        "fabricator",
        "work",
        "sheet"
    ],
    "wof:name":"R & R Sheet Metal Fabrications Ltd",
    "wof:placetype":"venue"
},
  "geometry": {"coordinates":[-0.580807,51.767838],"type":"Point"}
}