{
  "type": "Feature",
  "properties": {
    "addr:full":"71 Bridge Street Pinner Greater London HA5 3JH",
    "addr:housenumber":"71",
    "addr:postcode":"ha5 3jh",
    "addr:street":"Bridge Street",
    "iso:country":"GB",
    "sg:address":"71 Bridge Street",
    "sg:city":"Pinner",
    "sg:classifiers":[
        {
            "category":"Retail",
            "subcategory":"Auto Repair",
            "type":"Services"
        }
    ],
    "sg:phone":"+44 20 8429 0646",
    "sg:postcode":"HA5 3JH",
    "sg:province":"Greater London",
    "sg:tags":[
        "modification",
        "garage"
    ],
    "wof:name":"Taylor's Autos",
    "wof:placetype":"venue"
},
  "geometry": {"coordinates":[-0.38433,51.595093],"type":"Point"}
}