{
  "type": "Feature",
  "properties": {
    "addr:full":"Unit 1 County Workshops, Dockfield Road Shipley West Yorkshire BD17 7AR",
    "addr:housenumber":"unit 1 county",
    "addr:postcode":"bd17 7ar",
    "addr:street":"Dockfield Road",
    "iso:country":"GB",
    "sg:address":"Unit 1 County Workshops, Dockfield Road",
    "sg:city":"Shipley",
    "sg:classifiers":[
        {
            "category":"Manufacturing",
            "subcategory":"Metals",
            "type":"Manufacturing & Wholesale Goods"
        }
    ],
    "sg:phone":"+44 1274 532410",
    "sg:postcode":"BD17 7AR",
    "sg:province":"West Yorkshire",
    "sg:tags":[
        "product",
        "fabricated"
    ],
    "wof:name":"D & E Metal Fabrications",
    "wof:placetype":"venue"
},
  "geometry": {"coordinates":[-1.772899,53.837975],"type":"Point"}
}