{
  "type": "Feature",
  "properties": {
    "addr:full":"43 New Bdwy, Tarring Road Worthing West Sussex BN11 4ER",
    "addr:housenumber":"43",
    "addr:postcode":"bn11 4er",
    "addr:street":"New Bdwy Tarring Road",
    "iso:country":"GB",
    "sg:address":"43 New Bdwy, Tarring Road",
    "sg:city":"Worthing",
    "sg:classifiers":[
        {
            "category":"Shopping",
            "subcategory":"Mobile Phones",
            "type":"Retail Goods"
        }
    ],
    "sg:postcode":"BN11 4ER",
    "sg:province":"West Sussex",
    "wof:name":"The Orange Shop",
    "wof:placetype":"venue"
},
  "geometry": {"coordinates":[-0.3754239976,50.8136253357],"type":"Point"}
}