{
  "type": "Feature",
  "properties": {
    "addr:full":"Pendragon House, Trevillick Tintagel Cornwall PL34 0DN",
    "addr:postcode":"pl34 0dn",
    "addr:street":"Trevillick",
    "iso:country":"GB",
    "sg:address":"Pendragon House, Trevillick",
    "sg:city":"Tintagel",
    "sg:classifiers":[
        {
            "category":"Travel",
            "subcategory":"Hotels & Motels",
            "type":"Entertainment"
        }
    ],
    "sg:postcode":"PL34 0DN",
    "sg:province":"Cornwall",
    "sg:tags":[
        "self",
        "catering"
    ],
    "wof:name":"Cumbrae Holiday Agency",
    "wof:placetype":"venue"
},
  "geometry": {"coordinates":[-4.7446041107,50.6629219055],"type":"Point"}
}