{
  "type": "Feature",
  "properties": {
    "iso:country":"GB",
    "sg:address":"Railway Sidings",
    "sg:city":"Gravesend",
    "sg:classifiers":[
        {
            "category":"Retail",
            "subcategory":"Auto Repair",
            "type":"Services"
        }
    ],
    "sg:postcode":"DA13 0LT",
    "sg:province":"Kent",
    "sg:tags":[
        "modification",
        "garage"
    ],
    "wof:name":"Weeks,G,",
    "wof:placetype":"venue"
},
  "geometry": {"coordinates":[0.35641,51.362469],"type":"Point"}
}