{
  "type": "Feature",
  "properties": {
    "addr:full":"9 Agincourt Street Monmouth Gloucestershire NP25 3DZ",
    "addr:housenumber":"9",
    "addr:postcode":"np25 3dz",
    "addr:street":"Agincourt Street",
    "iso:country":"GB",
    "sg:address":"9 Agincourt Street",
    "sg:city":"Monmouth",
    "sg:classifiers":[
        {
            "category":"Professional",
            "subcategory":"Art Services",
            "type":"Services"
        }
    ],
    "sg:postcode":"NP25 3DZ",
    "sg:province":"Gloucestershire",
    "sg:tags":[
        "graphic",
        "designer"
    ],
    "wof:name":"Platform 1",
    "wof:placetype":"venue"
},
  "geometry": {"coordinates":[-2.7150709629,51.8115272522],"type":"Point"}
}