{
  "type": "Feature",
  "properties": {
    "addr:full":"75 The Grove London Greater London W5 5LL",
    "addr:housenumber":"75",
    "addr:postcode":"w5 5ll",
    "addr:street":"The Grove",
    "iso:country":"GB",
    "sg:address":"75 The Grove",
    "sg:city":"London",
    "sg:classifiers":[
        {
            "category":"Communications",
            "type":"Services"
        }
    ],
    "sg:phone":"+44 20 8579 2743",
    "sg:postcode":"W5 5LL",
    "sg:province":"Greater London",
    "sg:tags":[
        "audio-visual"
    ],
    "wof:name":"Vortex Communications Ltd.",
    "wof:placetype":"venue"
},
  "geometry": {"coordinates":[-0.3015429974,51.5110549927],"type":"Point"}
}