{
  "type": "Feature",
  "properties": {
    "addr:full":"13 Market Row Brixton Greater London SW9 8LD",
    "addr:housenumber":"13",
    "addr:postcode":"sw9 8ld",
    "addr:street":"Market Row",
    "iso:country":"GB",
    "sg:address":"13 Market Row",
    "sg:city":"Brixton",
    "sg:classifiers":[
        {
            "category":"Manufacturing",
            "subcategory":"Textiles",
            "type":"Manufacturing & Wholesale Goods"
        }
    ],
    "sg:phone":"+44 20 7274 6279",
    "sg:postcode":"SW9 8LD",
    "sg:province":"Greater London",
    "sg:tags":[
        "knitwear"
    ],
    "wof:name":"B O J Textiles",
    "wof:placetype":"venue"
},
  "geometry": {"coordinates":[-0.1136490032,51.4619789124],"type":"Point"}
}