{
  "type": "Feature",
  "properties": {
    "addr:full":"Institute Street Bolton Lancashire BL1 1PZ",
    "addr:postcode":"bl1 1pz",
    "addr:street":"Institute Street",
    "iso:country":"GB",
    "sg:address":"Institute Street",
    "sg:city":"Bolton",
    "sg:classifiers":[
        {
            "category":"Organizations",
            "subcategory":"Membership Organization",
            "type":"Services"
        }
    ],
    "sg:phone":"+44 1204 525711",
    "sg:postcode":"BL1 1PZ",
    "sg:province":"Lancashire",
    "sg:tags":[
        "club",
        "social"
    ],
    "wof:name":"Freemasons Hall",
    "wof:placetype":"venue"
},
  "geometry": {"coordinates":[-2.4241409302,53.5783500671],"type":"Point"}
}