{
  "type": "Feature",
  "properties": {
    "addr:full":"Langland Bay Road, Langland Swansea Swansea SA3 4QR",
    "addr:postcode":"sa3 4qr",
    "addr:street":"Langland Bay Road",
    "iso:country":"GB",
    "sg:address":"Langland Bay Road, Langland",
    "sg:city":"Swansea",
    "sg:classifiers":[
        {
            "category":"Sports & Exercise",
            "subcategory":"Golf",
            "type":"Entertainment"
        }
    ],
    "sg:phone":"+44 1792 366186",
    "sg:postcode":"SA3 4QR",
    "sg:province":"Swansea",
    "sg:tags":[
        "club",
        "course"
    ],
    "wof:name":"Langland Bay Golf Club Ltd.",
    "wof:placetype":"venue"
},
  "geometry": {"coordinates":[-4.0112299919,51.5717849731],"type":"Point"}
}