{
  "type": "Feature",
  "properties": {
    "addr:full":"11a Bridge Buildings, Ladybridge Rd Cheadle Cheshire SK8 5LL",
    "addr:housenumber":"11a",
    "addr:postcode":"sk8 5ll",
    "addr:street":"Bridge Buildings Ladybridge Rd Cheadle",
    "iso:country":"GB",
    "sg:address":"11a Bridge Buildings, Ladybridge Rd",
    "sg:city":"Cheadle",
    "sg:classifiers":[
        {
            "category":"Communications",
            "subcategory":"News Services",
            "type":"Services"
        }
    ],
    "sg:phone":"+44 161 485 8180",
    "sg:postcode":"SK8 5LL",
    "sg:province":"Cheshire",
    "sg:tags":[
        "journalist"
    ],
    "wof:name":"Chapman Press Agency",
    "wof:placetype":"venue"
},
  "geometry": {"coordinates":[-2.182105,53.385147],"type":"Point"}
}