{
  "type": "Feature",
  "properties": {
    "addr:full":"25 Broad Street Harleston Norfolk IP20 9AZ",
    "addr:housenumber":"25",
    "addr:postcode":"ip20 9az",
    "addr:street":"Broad Street",
    "iso:country":"GB",
    "sg:address":"25 Broad Street",
    "sg:city":"Harleston",
    "sg:classifiers":[
        {
            "category":"Building & Trades",
            "subcategory":"Construction",
            "type":"Services"
        }
    ],
    "sg:phone":"+44 1379 855209",
    "sg:postcode":"IP20 9AZ",
    "sg:province":"Norfolk",
    "sg:tags":[
        "builder"
    ],
    "wof:name":"Graham Johnson Builders",
    "wof:placetype":"venue"
},
  "geometry": {"coordinates":[1.3006160259,52.4030799866],"type":"Point"}
}