{
  "type": "Feature",
  "properties": {
    "addr:full":"38 Swan Rd Port Talbot Neath Port Talbot SA12 8LA",
    "addr:housenumber":"38",
    "addr:postcode":"sa12 8la",
    "addr:street":"Swan Rd",
    "iso:country":"GB",
    "sg:address":"38 Swan Rd",
    "sg:city":"Port Talbot",
    "sg:classifiers":[
        {
            "category":"Autos & Motor Vehicles",
            "subcategory":"Fuel & Gas Station",
            "type":"Retail Goods"
        }
    ],
    "sg:postcode":"SA12 8LA",
    "sg:province":"Neath Port Talbot",
    "sg:tags":[
        "petrol",
        "filling"
    ],
    "wof:name":"P M C Trading Ltd",
    "wof:placetype":"venue"
},
  "geometry": {"coordinates":[-3.8187088966,51.6250915527],"type":"Point"}
}