{
  "type": "Feature",
  "properties": {
    "addr:full":"Mill Ho Farm, Bardon Mill Hexham Northumberland NE47 7JA",
    "addr:postcode":"ne47 7ja",
    "iso:country":"GB",
    "sg:address":"Mill Ho Farm, Bardon Mill",
    "sg:city":"Hexham",
    "sg:classifiers":[
        {
            "category":"Farming",
            "subcategory":"Livestock Farm",
            "type":"Manufacturing & Wholesale Goods"
        }
    ],
    "sg:postcode":"NE47 7JA",
    "sg:province":"Northumberland",
    "sg:tags":[
        "others"
    ],
    "wof:name":"Yeats,A S,",
    "wof:placetype":"venue"
},
  "geometry": {"coordinates":[-2.3433868885,54.9764785767],"type":"Point"}
}