{
  "type": "Feature",
  "properties": {
    "iso:country":"GB",
    "sg:address":"Turner Road",
    "sg:city":"Worksop",
    "sg:classifiers":[
        {
            "category":"Autos & Motor Vehicles",
            "subcategory":"Automobile Sales",
            "type":"Retail Goods"
        }
    ],
    "sg:postcode":"S81 7AE",
    "sg:province":"Nottinghamshire",
    "sg:tags":[
        "car"
    ],
    "wof:name":"Stanilands",
    "wof:placetype":"venue"
},
  "geometry": {"coordinates":[-1.12688,53.313782],"type":"Point"}
}