{
  "type": "Feature",
  "properties": {
    "iso:country":"GB",
    "sg:address":"34 The Esplanade",
    "sg:city":"Weymouth",
    "sg:classifiers":[
        {
            "category":"Bars & Pubs",
            "type":"Food & Drink"
        },
        {
            "category":"Restaurant",
            "type":"Food & Drink"
        }
    ],
    "sg:phone":"+44 1305 778933",
    "sg:postcode":"DT4 8DJ",
    "sg:province":"Dorset",
    "sg:tags":[
        "-"
    ],
    "wof:name":"Ferry Inn",
    "wof:placetype":"venue"
},
  "geometry": {"coordinates":[-2.4524309635,50.6089820862],"type":"Point"}
}