{
  "type": "Feature",
  "properties": {
    "iso:country":"GB",
    "sg:address":"18 Osborn Road South",
    "sg:city":"Fareham",
    "sg:classifiers":[
        {
            "category":"Place Of Worship",
            "type":"Public Place"
        }
    ],
    "sg:phone":"+44 1329 221465",
    "sg:postcode":"PO16 7DG",
    "sg:province":"Hampshire",
    "wof:name":"Fareham United Reformed Church",
    "wof:placetype":"venue"
},
  "geometry": {"coordinates":[-1.182089,50.854622],"type":"Point"}
}