{
  "type": "Feature",
  "properties": {
    "addr:full":"Keyhaven Lymington Hampshire SO41 0TR",
    "addr:postcode":"so41 0tr",
    "addr:street":"Keyhaven;Hampshire",
    "iso:country":"GB",
    "sg:address":"Keyhaven",
    "sg:city":"Lymington",
    "sg:classifiers":[
        {
            "category":"Arena",
            "subcategory":"Sports Club",
            "type":"Entertainment"
        }
    ],
    "sg:phone":"+44 1590 642165",
    "sg:postcode":"SO41 0TR",
    "sg:province":"Hampshire",
    "wof:name":"Keyhaven Yacht Club",
    "wof:placetype":"venue"
},
  "geometry": {"coordinates":[-1.576809,50.723995],"type":"Point"}
}