{
  "type": "Feature",
  "properties": {
    "addr:full":"5 First Road Livingston West Lothian EH54 5DJ",
    "addr:housenumber":"5",
    "addr:postcode":"eh54 5dj",
    "addr:street":"First Road",
    "iso:country":"GB",
    "sg:address":"5 First Road",
    "sg:city":"Livingston",
    "sg:classifiers":[
        {
            "category":"Food & Beverages",
            "subcategory":"Bakery",
            "type":"Retail Goods"
        }
    ],
    "sg:phone":"+44 1506 443344",
    "sg:postcode":"EH54 5DJ",
    "sg:province":"West Lothian",
    "sg:tags":[
        "confectionery"
    ],
    "wof:name":"Patisserie Uk Ltd.",
    "wof:placetype":"venue"
},
  "geometry": {"coordinates":[-3.5098340511,55.8862457275],"type":"Point"}
}