{
  "type": "Feature",
  "properties": {
    "addr:full":"127 Trafalgar Road, Greenwich London Greater London SE10 9TX",
    "addr:housenumber":"127",
    "addr:postcode":"se10 9tx",
    "addr:street":"Trafalgar Road",
    "iso:country":"GB",
    "sg:address":"127 Trafalgar Road, Greenwich",
    "sg:city":"London",
    "sg:classifiers":[
        {
            "category":"Shopping",
            "subcategory":"Computers & Home Electronics",
            "type":"Retail Goods"
        }
    ],
    "sg:phone":"+44 20 8858 9160",
    "sg:postcode":"SE10 9TX",
    "sg:province":"Greater London",
    "sg:tags":[
        "equipment",
        "audio-visual"
    ],
    "wof:name":"Specialist Audio Visual Co.",
    "wof:placetype":"venue"
},
  "geometry": {"coordinates":[0.0030749999,51.484703064],"type":"Point"}
}