{
  "type": "Feature",
  "properties": {
    "addr:full":"Flat 1 Pond House, Weston Green Thames Ditton Surrey KT7 0JX",
    "addr:postcode":"kt7 0jx",
    "addr:street":"Weston Green",
    "iso:country":"GB",
    "sg:address":"Flat 1 Pond House, Weston Green",
    "sg:city":"Thames Ditton",
    "sg:classifiers":[
        {
            "category":"Education",
            "subcategory":"School",
            "type":"Public Place"
        }
    ],
    "sg:phone":"+44 1603 456660",
    "sg:postcode":"KT7 0JX",
    "sg:province":"Surrey",
    "sg:tags":[
        "local",
        "authority"
    ],
    "wof:name":"R & D Languages Ltd.",
    "wof:placetype":"venue"
},
  "geometry": {"coordinates":[-0.34649,51.382801],"type":"Point"}
}