{
  "type": "Feature",
  "properties": {
    "addr:full":"108-110 New Kings Road, Fulham London Greater London SW6 4LY",
    "addr:housenumber":"108-110",
    "addr:postcode":"sw6 4ly",
    "addr:street":"New Kings Road",
    "iso:country":"GB",
    "sg:address":"108-110 New Kings Road, Fulham",
    "sg:city":"London",
    "sg:classifiers":[
        {
            "category":"Bars & Pubs",
            "type":"Food & Drink"
        }
    ],
    "sg:phone":"+44 20 7731 2142",
    "sg:postcode":"SW6 4LY",
    "sg:province":"Greater London",
    "sg:tags":[
        "pubs",
        "inn"
    ],
    "wof:name":"Mixology Ltd",
    "wof:placetype":"venue"
},
  "geometry": {"coordinates":[-0.2040040046,51.47215271],"type":"Point"}
}