{
  "type": "Feature",
  "properties": {
    "addr:full":"Pilot Works, Alfred Street Bury Lancashire BL9 9EF",
    "addr:postcode":"bl9 9ef",
    "addr:street":"Alfred Street",
    "iso:country":"GB",
    "sg:address":"Pilot Works, Alfred Street",
    "sg:city":"Bury",
    "sg:classifiers":[
        {
            "category":"Shopping",
            "subcategory":"Luggage & Leather Goods",
            "type":"Retail Goods"
        }
    ],
    "sg:phone":"+44 161 764 5241",
    "sg:postcode":"BL9 9EF",
    "sg:province":"Lancashire",
    "wof:name":"Antler Ltd.",
    "wof:placetype":"venue"
},
  "geometry": {"coordinates":[-2.301054,53.589733],"type":"Point"}
}