{
  "type": "Feature",
  "properties": {
    "addr:full":"3 High Street, Chasetown Burntwood Staffordshire WS7 3XE",
    "addr:housenumber":"3",
    "addr:postcode":"ws7 3xe",
    "addr:street":"High Street",
    "iso:country":"GB",
    "sg:address":"3 High Street, Chasetown",
    "sg:city":"Burntwood",
    "sg:classifiers":[
        {
            "category":"Retail",
            "subcategory":"Funeral Services",
            "type":"Services"
        }
    ],
    "sg:postcode":"WS7 3XE",
    "sg:province":"Staffordshire",
    "wof:name":"John Short & Son",
    "wof:placetype":"venue"
},
  "geometry": {"coordinates":[-1.920019,52.67976],"type":"Point"}
}