{
  "type": "Feature",
  "properties": {
    "iso:country":"GB",
    "sg:address":"Unit 4, Optrex Business Park, Tylney Hall",
    "sg:city":"Hook",
    "sg:classifiers":[
        {
            "category":"Shopping",
            "subcategory":"Florist",
            "type":"Retail Goods"
        }
    ],
    "sg:phone":"+44 1256 763946",
    "sg:postcode":"RG27 9AY",
    "sg:province":"Berkshire",
    "wof:name":"Urban Planters (Reading)",
    "wof:placetype":"venue"
},
  "geometry": {"coordinates":[-0.9657189846,51.2813606262],"type":"Point"}
}