{
  "type": "Feature",
  "properties": {
    "addr:full":"The Old Ho, 4-5 Pelham Yard, High St Seaford East Sussex BN25 1PQ",
    "addr:housenumber":"4-5",
    "addr:postcode":"bn25 1pq",
    "addr:street":"Pelham Yard High St",
    "iso:country":"GB",
    "sg:address":"The Old Ho, 4-5 Pelham Yard, High St",
    "sg:city":"Seaford",
    "sg:classifiers":[
        {
            "category":"Professional",
            "type":"Services"
        }
    ],
    "sg:phone":"+44 1323 893795",
    "sg:postcode":"BN25 1PQ",
    "sg:province":"East Sussex",
    "sg:tags":[
        "auctioneer"
    ],
    "wof:name":"Pelham Yard Sale Room",
    "wof:placetype":"venue"
},
  "geometry": {"coordinates":[0.1014100015,50.7729148865],"type":"Point"}
}