{
  "type": "Feature",
  "properties": {
    "iso:country":"GB",
    "sg:address":"3 High Street",
    "sg:city":"Devizes",
    "sg:classifiers":[
        {
            "category":"Professional",
            "subcategory":"Engineering",
            "type":"Services"
        }
    ],
    "sg:phone":"+44 1380 721593",
    "sg:postcode":"SN10 1AU",
    "sg:province":"Wiltshire",
    "sg:tags":[
        "contractor",
        "electrical",
        "engineer"
    ],
    "wof:name":"Anderlecht Building Services Ltd.",
    "wof:placetype":"venue"
},
  "geometry": {"coordinates":[-1.993974,51.351154],"type":"Point"}
}