{
  "type": "Feature",
  "properties": {
    "iso:country":"GB",
    "sg:address":"Cairngorm House, Almondvale Blvd",
    "sg:city":"Livingston",
    "sg:classifiers":[
        {
            "category":"Insurance",
            "subcategory":"Insurance Agent",
            "type":"Services"
        }
    ],
    "sg:phone":"+44 1506 438822",
    "sg:postcode":"EH54 6QN",
    "sg:province":"West Lothian",
    "wof:name":"Royal Liver Assurance Ltd.",
    "wof:placetype":"venue"
},
  "geometry": {"coordinates":[-3.5115289688,55.8858833313],"type":"Point"}
}