{
  "type": "Feature",
  "properties": {
    "iso:country":"GB",
    "sg:address":"4 High Street, Flitwick",
    "sg:city":"Bedford",
    "sg:classifiers":[
        {
            "category":"Personal",
            "subcategory":"Barber",
            "type":"Services"
        }
    ],
    "sg:phone":"+44 1525 719290",
    "sg:postcode":"MK45 1DS",
    "sg:province":"Bedfordshire",
    "sg:tags":[
        "men's",
        "hairdresser"
    ],
    "wof:name":"The Barber",
    "wof:placetype":"venue"
},
  "geometry": {"coordinates":[-0.4942609966,52.0036392212],"type":"Point"}
}