{
  "type": "Feature",
  "properties": {
    "addr:full":"28 Sidmouth Street Devizes Wiltshire SN10 1LD",
    "addr:housenumber":"28",
    "addr:postcode":"sn10 1ld",
    "addr:street":"Sidmouth Street",
    "iso:country":"GB",
    "sg:address":"28 Sidmouth Street",
    "sg:city":"Devizes",
    "sg:classifiers":[
        {
            "category":"Professional",
            "subcategory":"Engineering",
            "type":"Services"
        },
        {
            "category":"Retail",
            "subcategory":"Driving School",
            "type":"Services"
        },
        {
            "category":"Shopping",
            "subcategory":"Florist",
            "type":"Retail Goods"
        }
    ],
    "sg:postcode":"SN10 1LD",
    "sg:province":"Wiltshire",
    "wof:name":"Bowsher Engineering",
    "wof:placetype":"venue"
},
  "geometry": {"coordinates":[-1.9914540052,51.3518409729],"type":"Point"}
}