{
  "type": "Feature",
  "properties": {
    "addr:full":"41a Great Underbank Stockport Cheshire SK1 1NE",
    "addr:housenumber":"41a",
    "addr:postcode":"sk1 1ne",
    "addr:street":"Great Underbank",
    "iso:country":"GB",
    "sg:address":"41a Great Underbank",
    "sg:city":"Stockport",
    "sg:classifiers":[
        {
            "category":"Professional",
            "subcategory":"Management & Consulting",
            "type":"Services"
        }
    ],
    "sg:phone":"+44 161 480 5387",
    "sg:postcode":"SK1 1NE",
    "sg:province":"Cheshire",
    "sg:tags":[
        "consultant",
        "business"
    ],
    "wof:name":"Hall,David,Partnership (Northern) Ltd",
    "wof:placetype":"venue"
},
  "geometry": {"coordinates":[-2.1585459709,53.4109153748],"type":"Point"}
}