{
  "type": "Feature",
  "properties": {
    "iso:country":"GB",
    "sg:address":"Marsden Park Golf Course, Townhouse Road",
    "sg:city":"Nelson",
    "sg:classifiers":[
        {
            "category":"Government",
            "subcategory":"Office",
            "type":"Public Place"
        }
    ],
    "sg:phone":"+44 1282 661912",
    "sg:postcode":"BB9 8DG",
    "sg:province":"Lancashire",
    "sg:tags":[
        "local"
    ],
    "wof:name":"Marsden Park Golf Shop",
    "wof:placetype":"venue"
},
  "geometry": {"coordinates":[-2.21334,53.835968],"type":"Point"}
}