{
  "type": "Feature",
  "properties": {
    "iso:country":"GB",
    "sg:address":"173 High Street",
    "sg:city":"Northallerton",
    "sg:classifiers":[
        {
            "category":"Banks & Credit Unions",
            "subcategory":"Financial Services",
            "type":"Services"
        }
    ],
    "sg:postcode":"DL7 8JZ",
    "sg:province":"North Yorkshire",
    "sg:tags":[
        "building",
        "society"
    ],
    "wof:name":"Skipton Building Society",
    "wof:placetype":"venue"
},
  "geometry": {"coordinates":[-1.433941,54.338234],"type":"Point"}
}