{
  "type": "Feature",
  "properties": {
    "addr:full":"49 Beaver Rd Ashford Kent TN23 7SE",
    "addr:housenumber":"49",
    "addr:postcode":"tn23 7se",
    "addr:street":"Beaver Rd",
    "iso:country":"GB",
    "sg:address":"49 Beaver Rd",
    "sg:city":"Ashford",
    "sg:classifiers":[
        {
            "category":"Shopping",
            "subcategory":"Pets & Pet Supplies",
            "type":"Retail Goods"
        }
    ],
    "sg:postcode":"TN23 7SE",
    "sg:province":"Kent",
    "wof:name":"Cumberland",
    "wof:placetype":"venue"
},
  "geometry": {"coordinates":[0.8709380031,51.1400337219],"type":"Point"}
}