{
  "type": "Feature",
  "properties": {
    "addr:full":"Pentland Industrial Estate Loanhead Midlothian EH20 9QH",
    "addr:postcode":"eh20 9qh",
    "addr:street":"Pentland Industrial Estate",
    "iso:country":"GB",
    "sg:address":"Pentland Industrial Estate",
    "sg:city":"Loanhead",
    "sg:classifiers":[
        {
            "category":"Retail",
            "subcategory":"Storage",
            "type":"Services"
        }
    ],
    "sg:phone":"+44 131 448 2222",
    "sg:postcode":"EH20 9QH",
    "sg:province":"Midlothian",
    "sg:tags":[
        "household",
        "removal"
    ],
    "wof:name":"Bishops Move (Edinburgh) Ltd.",
    "wof:placetype":"venue"
},
  "geometry": {"coordinates":[-3.1492199898,55.877696991],"type":"Point"}
}