{
  "type": "Feature",
  "properties": {
    "addr:full":"59-61 High Street, Wivenhoe Colchester Essex CO7 9AZ",
    "addr:housenumber":"59-61",
    "addr:postcode":"co7 9az",
    "addr:street":"High Street",
    "iso:country":"GB",
    "sg:address":"59-61 High Street, Wivenhoe",
    "sg:city":"Colchester",
    "sg:classifiers":[
        {
            "category":"Professional",
            "subcategory":"Computer Services",
            "type":"Services"
        }
    ],
    "sg:phone":"+44 1206 825403",
    "sg:postcode":"CO7 9AZ",
    "sg:province":"Essex",
    "sg:tags":[
        "consultant"
    ],
    "wof:name":"Wivenhoe Information Systems Ltd.",
    "wof:placetype":"venue"
},
  "geometry": {"coordinates":[0.959388,51.856354],"type":"Point"}
}