{
  "type": "Feature",
  "properties": {
    "addr:full":"28 Fairfax Crescent Halifax West Yorkshire HX3 9SQ",
    "addr:housenumber":"28",
    "addr:postcode":"hx3 9sq",
    "addr:street":"Fairfax Crescent",
    "iso:country":"GB",
    "sg:address":"28 Fairfax Crescent",
    "sg:city":"Halifax",
    "sg:classifiers":[
        {
            "category":"Communications",
            "type":"Services"
        }
    ],
    "sg:phone":"+44 1422 346237",
    "sg:postcode":"HX3 9SQ",
    "sg:province":"West Yorkshire",
    "sg:tags":[
        "audio-visual"
    ],
    "wof:name":"Julian Hadlow",
    "wof:placetype":"venue"
},
  "geometry": {"coordinates":[-1.8288199902,53.7127075195],"type":"Point"}
}