{
  "type": "Feature",
  "properties": {
    "addr:full":"46 Felton Road Barking Essex IG11 7XZ",
    "addr:housenumber":"46",
    "addr:postcode":"ig11 7xz",
    "addr:street":"Felton Road",
    "iso:country":"GB",
    "sg:address":"46 Felton Road",
    "sg:city":"Barking",
    "sg:classifiers":[
        {
            "category":"Professional",
            "subcategory":"Engineering",
            "type":"Services"
        }
    ],
    "sg:postcode":"IG11 7XZ",
    "sg:province":"Essex",
    "sg:tags":[
        "contractor",
        "electrical",
        "engineer"
    ],
    "wof:name":"D J Dowsett Electrical",
    "wof:placetype":"venue"
},
  "geometry": {"coordinates":[0.094482,51.531017],"type":"Point"}
}