{
  "type": "Feature",
  "properties": {
    "addr:full":"Oakfield Bungalow, Tamworth Road Ashby-de-la-zouch Derbyshire LE65 2PR",
    "addr:housenumber":"oakfield",
    "addr:postcode":"le65 2pr",
    "addr:street":"Tamworth Road",
    "iso:country":"GB",
    "sg:address":"Oakfield Bungalow, Tamworth Road",
    "sg:city":"Ashby-de-la-zouch",
    "sg:classifiers":[
        {
            "category":"Building & Trades",
            "subcategory":"Construction",
            "type":"Services"
        }
    ],
    "sg:phone":"+44 1530 560795",
    "sg:postcode":"LE65 2PR",
    "sg:province":"Derbyshire",
    "sg:tags":[
        "roofing",
        "contracting"
    ],
    "wof:name":"Abla Roofing",
    "wof:placetype":"venue"
},
  "geometry": {"coordinates":[-1.4748610258,52.7480926514],"type":"Point"}
}