{
  "type": "Feature",
  "properties": {
    "addr:full":"359 Holmlea Road Glasgow East Renfrewshire G44 4BP",
    "addr:housenumber":"359",
    "addr:postcode":"g44 4bp",
    "addr:street":"Holmlea Road",
    "iso:country":"GB",
    "sg:address":"359 Holmlea Road",
    "sg:city":"Glasgow",
    "sg:classifiers":[
        {
            "category":"Personal",
            "subcategory":"Beauty Salon",
            "type":"Services"
        }
    ],
    "sg:phone":"+44 141 637 1614",
    "sg:postcode":"G44 4BP",
    "sg:province":"East Renfrewshire",
    "sg:tags":[
        "unisex",
        "hairdresser"
    ],
    "wof:name":"Silki Salon",
    "wof:placetype":"venue"
},
  "geometry": {"coordinates":[-4.2612781525,55.8184928894],"type":"Point"}
}