{
  "type": "Feature",
  "properties": {
    "addr:full":"Vranch House School, Pinhoe Road Exeter Devon EX4 8AD",
    "addr:postcode":"ex4 8ad",
    "addr:street":"Pinhoe Road",
    "iso:country":"GB",
    "sg:address":"Vranch House School, Pinhoe Road",
    "sg:city":"Exeter",
    "sg:classifiers":[
        {
            "category":"Education",
            "subcategory":"School",
            "type":"Public Place"
        }
    ],
    "sg:phone":"+44 1392 468333",
    "sg:postcode":"EX4 8AD",
    "sg:province":"Devon",
    "sg:tags":[
        "independent",
        "preparatory"
    ],
    "wof:name":"Devon & Exeter Spastics Society Ltd",
    "wof:placetype":"venue"
},
  "geometry": {"coordinates":[-3.4728639126,50.7378463745],"type":"Point"}
}