{
  "type": "Feature",
  "properties": {
    "iso:country":"GB",
    "sg:address":"53 Lynn Road, Snettisham",
    "sg:city":"King's Lynn",
    "sg:classifiers":[
        {
            "category":"Health Services",
            "subcategory":"Nursing And Care Facility",
            "type":"Services"
        },
        {
            "category":"Social Services",
            "subcategory":"Retirement Home",
            "type":"Services"
        }
    ],
    "sg:phone":"+44 1485 540041",
    "sg:postcode":"PE31 7PT",
    "sg:province":"Norfolk",
    "sg:tags":[
        "residential"
    ],
    "wof:name":"The Close",
    "wof:placetype":"venue"
},
  "geometry": {"coordinates":[0.5027599931,52.8781585693],"type":"Point"}
}