{
  "type": "Feature",
  "properties": {
    "iso:country":"GB",
    "sg:address":"Beardmore Place, Clydebank Industrial Estate",
    "sg:city":"Clydebank",
    "sg:classifiers":[
        {
            "category":"Home & Garden",
            "subcategory":"Building Materials",
            "type":"Retail Goods"
        }
    ],
    "sg:postcode":"G81 4HS",
    "sg:province":"East Dunbartonshire",
    "sg:tags":[
        "window",
        "frame"
    ],
    "wof:name":"C B Metal Casements Ltd.",
    "wof:placetype":"venue"
},
  "geometry": {"coordinates":[-4.429961,55.90929],"type":"Point"}
}