{
  "type": "Feature",
  "properties": {
    "addr:full":"Church Road, Bookham Leatherhead Surrey KT23 3JT",
    "addr:postcode":"kt23 3jt",
    "addr:street":"Church Road",
    "iso:country":"GB",
    "sg:address":"Church Road, Bookham",
    "sg:city":"Leatherhead",
    "sg:classifiers":[
        {
            "category":"Food & Beverages",
            "subcategory":"Bakery",
            "type":"Retail Goods"
        }
    ],
    "sg:phone":"+44 1372 457354",
    "sg:postcode":"KT23 3JT",
    "sg:province":"Surrey",
    "sg:tags":[
        "baker"
    ],
    "wof:name":"Watson's Bakeries",
    "wof:placetype":"venue"
},
  "geometry": {"coordinates":[-0.378549,51.283787],"type":"Point"}
}