{
  "type": "Feature",
  "properties": {
    "addr:full":"Airplace Mills, Kirkstall Road Leeds West Yorkshire LS3 1JS",
    "addr:postcode":"ls3 1js",
    "addr:street":"Kirkstall Road",
    "iso:country":"GB",
    "sg:address":"Airplace Mills, Kirkstall Road",
    "sg:city":"Leeds",
    "sg:classifiers":[
        {
            "category":"Home & Garden",
            "subcategory":"Home Furnishings",
            "type":"Retail Goods"
        }
    ],
    "sg:phone":"+44 113 245 6472",
    "sg:postcode":"LS3 1JS",
    "sg:province":"West Yorkshire",
    "sg:tags":[
        "wall",
        "wallpaper",
        "covering"
    ],
    "wof:name":"Rewrap Ltd.",
    "wof:placetype":"venue"
},
  "geometry": {"coordinates":[-1.57053,53.803101],"type":"Point"}
}