{
  "type": "Feature",
  "properties": {
    "addr:full":"London Road Trading Estate, London Road Sittingbourne Kent ME10 1NQ",
    "addr:postcode":"me10 1nq",
    "addr:street":"London Road Trading Estate London Road",
    "iso:country":"GB",
    "sg:address":"London Road Trading Estate, London Road",
    "sg:city":"Sittingbourne",
    "sg:classifiers":[
        {
            "category":"Shopping",
            "subcategory":"Pets & Pet Supplies",
            "type":"Retail Goods"
        }
    ],
    "sg:phone":"+44 1795 423564",
    "sg:postcode":"ME10 1NQ",
    "sg:province":"Kent",
    "sg:tags":[
        "food"
    ],
    "wof:name":"Triogen Canine Foods",
    "wof:placetype":"venue"
},
  "geometry": {"coordinates":[0.7266200185,51.3415718079],"type":"Point"}
}