{
  "type": "Feature",
  "properties": {
    "addr:full":"Unit 2 Mill Court Slough Berkshire SL2 5DA",
    "addr:housenumber":"unit 2",
    "addr:postcode":"sl2 5da",
    "addr:street":"Mill Court",
    "iso:country":"GB",
    "sg:address":"Unit 2 Mill Court",
    "sg:city":"Slough",
    "sg:classifiers":[
        {
            "category":"Wholesale",
            "subcategory":"Medical Equipment & Supplies",
            "type":"Manufacturing & Wholesale Goods"
        }
    ],
    "sg:phone":"+44 1753 550855",
    "sg:postcode":"SL2 5DA",
    "sg:province":"Berkshire",
    "sg:tags":[
        "hospital"
    ],
    "wof:name":"Eclipsys",
    "wof:placetype":"venue"
},
  "geometry": {"coordinates":[-0.590109,51.513161],"type":"Point"}
}