{
  "type": "Feature",
  "properties": {
    "addr:full":"5 Osborne Way, Wigginton Tring Buckinghamshire HP23 6EN",
    "addr:housenumber":"5",
    "addr:postcode":"hp23 6en",
    "addr:street":"Osborne Way",
    "iso:country":"GB",
    "sg:address":"5 Osborne Way, Wigginton",
    "sg:city":"Tring",
    "sg:classifiers":[
        {
            "category":"Retail",
            "subcategory":"Auto Rental",
            "type":"Services"
        },
        {
            "category":"Autos & Motor Vehicles",
            "subcategory":"Motorcycle Sales",
            "type":"Retail Goods"
        }
    ],
    "sg:phone":"+44 1442 823263",
    "sg:postcode":"HP23 6EN",
    "sg:province":"Buckinghamshire",
    "sg:tags":[
        "chauffeur",
        "driven",
        "hire",
        "car"
    ],
    "wof:name":"Barrington Cars",
    "wof:placetype":"venue"
},
  "geometry": {"coordinates":[-0.644925,51.780853],"type":"Point"}
}