{
  "type": "Feature",
  "properties": {
    "iso:country":"GB",
    "sg:address":"22-24 New Market Street",
    "sg:city":"Ulverston",
    "sg:classifiers":[
        {
            "category":"Shopping",
            "subcategory":"Clothing, Apparel, & Fashions",
            "type":"Retail Goods"
        }
    ],
    "sg:postcode":"LA12 7LN",
    "sg:province":"Cumbria",
    "sg:tags":[
        "shop"
    ],
    "wof:name":"Top Gear",
    "wof:placetype":"venue"
},
  "geometry": {"coordinates":[-3.095264,54.19516],"type":"Point"}
}