{
  "type": "Feature",
  "properties": {
    "iso:country":"GB",
    "sg:address":"Sea Hill, Beer",
    "sg:city":"Seaton",
    "sg:classifiers":[
        {
            "category":"Farming",
            "subcategory":"Fish & Marine Products",
            "type":"Manufacturing & Wholesale Goods"
        },
        {
            "category":"Food & Beverages",
            "subcategory":"Meat & Fish",
            "type":"Retail Goods"
        }
    ],
    "sg:phone":"+44 1297 20297",
    "sg:postcode":"EX12 3NE",
    "sg:province":"Devon",
    "sg:tags":[
        "fishmonger",
        "related"
    ],
    "wof:name":"Beer Fisheries",
    "wof:placetype":"venue"
},
  "geometry": {"coordinates":[-3.091607,50.696907],"type":"Point"}
}