{
  "type": "Feature",
  "properties": {
    "iso:country":"GB",
    "sg:address":"West Pavington, Burrington",
    "sg:city":"Umberleigh",
    "sg:classifiers":[
        {
            "category":"Farming",
            "subcategory":"Livestock Farm",
            "type":"Manufacturing & Wholesale Goods"
        }
    ],
    "sg:phone":"+44 1769 520200",
    "sg:postcode":"EX37 9LJ",
    "sg:province":"Devon",
    "sg:tags":[
        "others"
    ],
    "wof:name":"G C Thomas",
    "wof:placetype":"venue"
},
  "geometry": {"coordinates":[-3.985345,50.995815],"type":"Point"}
}