{
  "type": "Feature",
  "properties": {
    "addr:full":"23 Elswick Road Newcastle-upon-tyne Tyne and Wear NE4 6ER",
    "addr:housenumber":"23",
    "addr:postcode":"ne4 6er",
    "addr:street":"Elswick Road",
    "iso:country":"GB",
    "sg:address":"23 Elswick Road",
    "sg:city":"Newcastle-upon-tyne",
    "sg:classifiers":[
        {
            "category":"Personal",
            "subcategory":"Beauty Salon",
            "type":"Services"
        }
    ],
    "sg:phone":"+44 191 273 4873",
    "sg:postcode":"NE4 6ER",
    "sg:province":"Tyne and Wear",
    "sg:tags":[
        "ladies",
        "lady",
        "hairdresser"
    ],
    "wof:name":"Barbara's Hair Fashion",
    "wof:placetype":"venue"
},
  "geometry": {"coordinates":[-1.630545,54.97121],"type":"Point"}
}