{
  "type": "Feature",
  "properties": {
    "addr:full":"1st Floor Talon House, Presley Way Milton Keynes Buckinghamshire MK8 0EE",
    "addr:postcode":"mk8 0ee",
    "addr:street":"Presley Way",
    "iso:country":"GB",
    "sg:address":"1st Floor Talon House, Presley Way",
    "sg:city":"Milton Keynes",
    "sg:classifiers":[
        {
            "category":"Banks & Credit Unions",
            "subcategory":"Financial Services",
            "type":"Services"
        }
    ],
    "sg:postcode":"MK8 0EE",
    "sg:province":"Buckinghamshire",
    "sg:tags":[
        "consultant"
    ],
    "wof:name":"G Financial Services Ltd.",
    "wof:placetype":"venue"
},
  "geometry": {"coordinates":[-0.801946,52.028996],"type":"Point"}
}