{
  "type": "Feature",
  "properties": {
    "addr:full":"5 Hart St Brentwood Essex CM14 4AX",
    "addr:housenumber":"5",
    "addr:postcode":"cm14 4ax",
    "addr:street":"Hart St",
    "iso:country":"GB",
    "sg:address":"5 Hart St",
    "sg:city":"Brentwood",
    "sg:classifiers":[
        {
            "category":"Professional",
            "subcategory":"Employment Agencies",
            "type":"Services"
        }
    ],
    "sg:phone":"+44 1277 234700",
    "sg:postcode":"CM14 4AX",
    "sg:province":"Essex",
    "sg:tags":[
        "consultant"
    ],
    "wof:name":"Hamiltons",
    "wof:placetype":"venue"
},
  "geometry": {"coordinates":[0.300289,51.61937],"type":"Point"}
}