{
  "type": "Feature",
  "properties": {
    "iso:country":"GB",
    "sg:address":"7th Floor, 26 Cross Street",
    "sg:city":"Manchester",
    "sg:classifiers":[
        {
            "category":"Professional",
            "subcategory":"Management & Consulting",
            "type":"Services"
        }
    ],
    "sg:phone":"+44 161 839 0990",
    "sg:postcode":"M2 7AF",
    "sg:province":"Greater Manchester",
    "sg:tags":[
        "consultant",
        "business"
    ],
    "wof:name":"David Rigby Associates Ltd.",
    "wof:placetype":"venue"
},
  "geometry": {"coordinates":[-2.2442190647,53.4822692871],"type":"Point"}
}