{
  "type": "Feature",
  "properties": {
    "addr:full":"Eden House, The Indsl Estate Edenbridge East Sussex TN8 6HF",
    "addr:postcode":"tn8 6hf",
    "addr:street":"The",
    "iso:country":"GB",
    "sg:address":"Eden House, The Indsl Estate",
    "sg:city":"Edenbridge",
    "sg:classifiers":[
        {
            "category":"Shopping",
            "subcategory":"Stationery & Office Supplies",
            "type":"Retail Goods"
        }
    ],
    "sg:phone":"+44 1732 865420",
    "sg:postcode":"TN8 6HF",
    "sg:province":"East Sussex",
    "sg:tags":[
        "equipment"
    ],
    "wof:name":"C H Workspace Ltd.",
    "wof:placetype":"venue"
},
  "geometry": {"coordinates":[0.0647469983,51.1973876953],"type":"Point"}
}