{
  "type": "Feature",
  "properties": {
    "addr:full":"43 Station Rd Chingford Greater London E4 7BJ",
    "addr:housenumber":"43",
    "addr:postcode":"e4 7bj",
    "addr:street":"Station Rd",
    "iso:country":"GB",
    "sg:address":"43 Station Rd",
    "sg:city":"Chingford",
    "sg:classifiers":[
        {
            "category":"Shopping",
            "subcategory":"Thrift Store",
            "type":"Retail Goods"
        },
        {
            "category":"Organizations",
            "subcategory":"Non-profit Organization",
            "type":"Services"
        }
    ],
    "sg:phone":"+44 20 8524 6923",
    "sg:postcode":"E4 7BJ",
    "sg:province":"Greater London",
    "sg:tags":[
        "shop",
        "organisation",
        "voluntary",
        "charity"
    ],
    "wof:name":"The Children's Society",
    "wof:placetype":"venue"
},
  "geometry": {"coordinates":[0.003759,51.631207],"type":"Point"}
}