{
  "type": "Feature",
  "properties": {
    "iso:country":"GB",
    "sg:address":"14 Newbiggin",
    "sg:city":"Malton",
    "sg:classifiers":[
        {
            "category":"Bars & Pubs",
            "type":"Food & Drink"
        }
    ],
    "sg:phone":"+44 1653 692236",
    "sg:postcode":"YO17 7JF",
    "sg:province":"North Yorkshire",
    "sg:tags":[
        "pubs",
        "inn"
    ],
    "wof:name":"Albion Pub Contracts Ltd.",
    "wof:placetype":"venue"
},
  "geometry": {"coordinates":[-0.798705,54.137161],"type":"Point"}
}