{
  "type": "Feature",
  "properties": {
    "addr:full":"Woodstock Chiropractic Clinic 24, Hensington Road, Hensington Road Woodstock Oxfordshire OX20 1JL",
    "addr:housenumber":"24",
    "addr:postcode":"ox20 1jl",
    "addr:street":"Hensington Road Hensington Road",
    "iso:country":"GB",
    "sg:address":"Woodstock Chiropractic Clinic 24, Hensington Road, Hensington Road",
    "sg:city":"Woodstock",
    "sg:classifiers":[
        {
            "category":"Health Services",
            "subcategory":"Chiropractor",
            "type":"Services"
        }
    ],
    "sg:postcode":"OX20 1JL",
    "sg:province":"Oxfordshire",
    "wof:name":"R D Molloy & Associates",
    "wof:placetype":"venue"
},
  "geometry": {"coordinates":[-1.355022,51.848461],"type":"Point"}
}