{
  "type": "Feature",
  "properties": {
    "iso:country":"GB",
    "sg:address":"303 Tottington Road",
    "sg:city":"Bury",
    "sg:classifiers":[
        {
            "category":"Travel",
            "subcategory":"Travel Agent",
            "type":"Entertainment"
        }
    ],
    "sg:phone":"+44 161 761 2100",
    "sg:postcode":"BL8 1ST",
    "sg:province":"Lancashire",
    "wof:name":"Budget Travel",
    "wof:placetype":"venue"
},
  "geometry": {"coordinates":[-2.319346,53.601696],"type":"Point"}
}