{
  "type": "Feature",
  "properties": {
    "addr:full":"Sarason House, Barnet Road Barnet Hertfordshire EN5 3JT",
    "addr:postcode":"en5 3jt",
    "addr:street":"Barnet Road",
    "iso:country":"GB",
    "sg:address":"Sarason House, Barnet Road",
    "sg:city":"Barnet",
    "sg:classifiers":[
        {
            "category":"Professional",
            "subcategory":"Engineering",
            "type":"Services"
        }
    ],
    "sg:postcode":"EN5 3JT",
    "sg:province":"Hertfordshire",
    "sg:tags":[
        "consulting",
        "structural",
        "engineer"
    ],
    "wof:name":"C J Cowie Associates",
    "wof:placetype":"venue"
},
  "geometry": {"coordinates":[-0.219474,51.652271],"type":"Point"}
}