{
  "type": "Feature",
  "properties": {
    "addr:full":"28 Rochester Rd Durham Durham DH1 5QD",
    "addr:housenumber":"28",
    "addr:postcode":"dh1 5qd",
    "addr:street":"Rochester Rd",
    "iso:country":"GB",
    "sg:address":"28 Rochester Rd",
    "sg:city":"Durham",
    "sg:classifiers":[
        {
            "category":"Building & Trades",
            "subcategory":"Construction",
            "type":"Services"
        }
    ],
    "sg:phone":"+44 191 383 0584",
    "sg:postcode":"DH1 5QD",
    "sg:province":"Durham",
    "sg:tags":[
        "builder"
    ],
    "wof:name":"Lawrie Chatterton",
    "wof:placetype":"venue"
},
  "geometry": {"coordinates":[-1.570159,54.802521],"type":"Point"}
}