{
  "type": "Feature",
  "properties": {
    "addr:full":"36 Front Street, Birstall Leicester Leicestershire LE4 4DP",
    "addr:housenumber":"36",
    "addr:postcode":"le4 4dp",
    "addr:street":"Front Street",
    "iso:country":"GB",
    "sg:address":"36 Front Street, Birstall",
    "sg:city":"Leicester",
    "sg:classifiers":[
        {
            "category":"Shopping",
            "subcategory":"Shoes",
            "type":"Retail Goods"
        }
    ],
    "sg:phone":"+44 116 267 7330",
    "sg:postcode":"LE4 4DP",
    "sg:province":"Leicestershire",
    "wof:name":"Birstall Shoe Repairs",
    "wof:placetype":"venue"
},
  "geometry": {"coordinates":[-1.118887,52.675671],"type":"Point"}
}