{
  "type": "Feature",
  "properties": {
    "addr:full":"Bluebrick Cott, Monwode Lea Birmingham Warwickshire B46 2NP",
    "addr:postcode":"b46 2np",
    "addr:street":"Lea",
    "iso:country":"GB",
    "sg:address":"Bluebrick Cott, Monwode Lea",
    "sg:city":"Birmingham",
    "sg:classifiers":[
        {
            "category":"Building & Trades",
            "subcategory":"Construction",
            "type":"Services"
        }
    ],
    "sg:phone":"+44 1675 481589",
    "sg:postcode":"B46 2NP",
    "sg:province":"Warwickshire",
    "sg:tags":[
        "flooring"
    ],
    "wof:name":"R.W Astell & Co.Ltd",
    "wof:placetype":"venue"
},
  "geometry": {"coordinates":[-1.6085000038,52.5218086243],"type":"Point"}
}