{
  "type": "Feature",
  "properties": {
    "iso:country":"GB",
    "sg:address":"41-43 Northgate",
    "sg:city":"Bridgwater",
    "sg:classifiers":[
        {
            "category":"Professional",
            "subcategory":"Lawyer & Legal Services",
            "type":"Services"
        },
        {
            "category":"Organizations",
            "subcategory":"Non-profit Organization",
            "type":"Services"
        }
    ],
    "sg:phone":"+44 1823 327453",
    "sg:postcode":"TA6 3HJ",
    "sg:province":"Somerset",
    "sg:tags":[
        "advice",
        "organisation",
        "voluntary",
        "counselling",
        "charity"
    ],
    "wof:name":"Advocacy Information Mediation Services",
    "wof:placetype":"venue"
},
  "geometry": {"coordinates":[-3.004799,51.130032],"type":"Point"}
}