{
  "type": "Feature",
  "properties": {
    "iso:country":"GB",
    "sg:address":"20 The Forum",
    "sg:city":"Stevenage",
    "sg:classifiers":[
        {
            "category":"Professional",
            "subcategory":"Employment Agencies",
            "type":"Services"
        }
    ],
    "sg:phone":"+44 1438 750649",
    "sg:postcode":"SG1 1EH",
    "sg:province":"Hertfordshire",
    "sg:tags":[
        "consultant"
    ],
    "wof:name":"Reed Employment",
    "wof:placetype":"venue"
},
  "geometry": {"coordinates":[-0.200331,51.904537],"type":"Point"}
}