{
  "type": "Feature",
  "properties": {
    "addr:full":"328 Yardley Road, Yardley Birmingham West Midlands B25 8LT",
    "addr:housenumber":"328",
    "addr:postcode":"b25 8lt",
    "addr:street":"Yardley Road",
    "iso:country":"GB",
    "sg:address":"328 Yardley Road, Yardley",
    "sg:city":"Birmingham",
    "sg:classifiers":[
        {
            "category":"Organizations",
            "subcategory":"Membership Organization",
            "type":"Services"
        }
    ],
    "sg:phone":"+44 121 706 0202",
    "sg:postcode":"B25 8LT",
    "sg:province":"West Midlands",
    "sg:tags":[
        "club"
    ],
    "wof:name":"Yardley Ex-Service Mens Club Ltd.",
    "wof:placetype":"venue"
},
  "geometry": {"coordinates":[-1.8167649508,52.460521698],"type":"Point"}
}