{
  "type": "Feature",
  "properties": {
    "addr:full":"202 Kings Road, Tyseley Birmingham West Midlands B11 2AP",
    "addr:housenumber":"202",
    "addr:postcode":"b11 2ap",
    "addr:street":"Kings Road",
    "iso:country":"GB",
    "sg:address":"202 Kings Road, Tyseley",
    "sg:city":"Birmingham",
    "sg:classifiers":[
        {
            "category":"Professional",
            "subcategory":"Engineering",
            "type":"Services"
        }
    ],
    "sg:postcode":"B11 2AP",
    "sg:province":"West Midlands",
    "sg:tags":[
        "civil",
        "engineer"
    ],
    "wof:name":"Borderdown Communications Ltd",
    "wof:placetype":"venue"
},
  "geometry": {"coordinates":[-1.8391070366,52.4584083557],"type":"Point"}
}