{
  "type": "Feature",
  "properties": {
    "addr:full":"115a Trafalgar Road London Greater London SE10 9TX",
    "addr:housenumber":"115a",
    "addr:postcode":"se10 9tx",
    "addr:street":"Trafalgar Road",
    "iso:country":"GB",
    "sg:address":"115a Trafalgar Road",
    "sg:city":"London",
    "sg:classifiers":[
        {
            "category":"Deli",
            "type":"Food & Drink"
        }
    ],
    "sg:phone":"+44 20 8858 1734",
    "sg:postcode":"SE10 9TX",
    "sg:province":"Greater London",
    "sg:tags":[
        "delicatessen"
    ],
    "wof:name":"The Cottage Pantry",
    "wof:placetype":"venue"
},
  "geometry": {"coordinates":[0.0019690001,51.4844017029],"type":"Point"}
}