{
  "type": "Feature",
  "properties": {
    "iso:country":"GB",
    "sg:address":"90a Cassland Road",
    "sg:city":"London",
    "sg:classifiers":[
        {
            "category":"Shopping",
            "subcategory":"Stationery & Office Supplies",
            "type":"Retail Goods"
        }
    ],
    "sg:phone":"+44 20 8986 7138",
    "sg:postcode":"E9 7AN",
    "sg:province":"Greater London",
    "sg:tags":[
        "equipment"
    ],
    "wof:name":"WOODS OFFICE FURNITURE",
    "wof:placetype":"venue"
},
  "geometry": {"coordinates":[-0.042881,51.54303],"type":"Point"}
}