{
  "type": "Feature",
  "properties": {
    "addr:full":"Aberdulais Falls, Aberdulais Neath Neath Port Talbot SA10 8EU",
    "addr:postcode":"sa10 8eu",
    "addr:street":"Aberdulais Falls",
    "iso:country":"GB",
    "sg:address":"Aberdulais Falls, Aberdulais",
    "sg:city":"Neath",
    "sg:classifiers":[
        {
            "category":"Landmark",
            "subcategory":"Tourist Attraction",
            "type":"Public Place"
        }
    ],
    "sg:phone":"+44 1639 636674",
    "sg:postcode":"SA10 8EU",
    "sg:province":"Neath Port Talbot",
    "sg:tags":[
        "interest"
    ],
    "wof:name":"The National Trust",
    "wof:placetype":"venue"
},
  "geometry": {"coordinates":[-3.7775900364,51.6808013916],"type":"Point"}
}