{
  "type": "Feature",
  "properties": {
    "iso:country":"GB",
    "sg:address":"67 High Street, Meadowhall Centre",
    "sg:city":"Sheffield",
    "sg:classifiers":[
        {
            "category":"Shopping",
            "subcategory":"Shoes",
            "type":"Retail Goods"
        }
    ],
    "sg:phone":"+44 114 256 8526",
    "sg:postcode":"S9 1EN",
    "sg:province":"South Yorkshire",
    "sg:tags":[
        "shop"
    ],
    "wof:name":"Dolcis",
    "wof:placetype":"venue"
},
  "geometry": {"coordinates":[-1.391479,53.41275],"type":"Point"}
}