{
  "type": "Feature",
  "properties": {
    "addr:full":"Sweet 1beatty House Admirals Way London Greater London E14 9UF",
    "addr:postcode":"e14 9uf",
    "addr:street":"Admirals Way",
    "iso:country":"GB",
    "sg:address":"Sweet 1beatty House Admirals Way",
    "sg:city":"London",
    "sg:classifiers":[
        {
            "category":"Professional",
            "subcategory":"Accounting & Tax Preparation",
            "type":"Services"
        }
    ],
    "sg:phone":"+44 20 7538 1882",
    "sg:postcode":"E14 9UF",
    "sg:province":"Greater London",
    "sg:tags":[
        "accountant"
    ],
    "wof:name":"Riverruns Ltd",
    "wof:placetype":"venue"
},
  "geometry": {"coordinates":[-0.0209500007,51.5016708374],"type":"Point"}
}