{
  "type": "Feature",
  "properties": {
    "addr:full":"11 Alexander Ct, Fleming Rd Corby Northamptonshire NN17 4SW",
    "addr:housenumber":"11",
    "addr:postcode":"nn17 4sw",
    "addr:street":"Alexander Ct Fleming Rd",
    "iso:country":"GB",
    "sg:address":"11 Alexander Ct, Fleming Rd",
    "sg:city":"Corby",
    "sg:classifiers":[
        {
            "category":"Professional",
            "subcategory":"Detective & Security Services",
            "type":"Services"
        }
    ],
    "sg:phone":"+44 1536 200722",
    "sg:postcode":"NN17 4SW",
    "sg:province":"Northamptonshire",
    "sg:tags":[
        "car"
    ],
    "wof:name":"S R S",
    "wof:placetype":"venue"
},
  "geometry": {"coordinates":[-0.6893159747,52.5075035095],"type":"Point"}
}