{
  "type": "Feature",
  "properties": {
    "addr:full":"89 Bacup Road Rossendale Lancashire BB4 7NW",
    "addr:housenumber":"89",
    "addr:postcode":"bb4 7nw",
    "addr:street":"Bacup Road",
    "iso:country":"GB",
    "sg:address":"89 Bacup Road",
    "sg:city":"Rossendale",
    "sg:classifiers":[
        {
            "category":"Personal",
            "subcategory":"Tattoo Parlor",
            "type":"Services"
        }
    ],
    "sg:phone":"+44 1706 831368",
    "sg:postcode":"BB4 7NW",
    "sg:province":"Lancashire",
    "sg:tags":[
        "tattooing",
        "piercing",
        "artist"
    ],
    "wof:name":"Fancy That Body Piercing Studio",
    "wof:placetype":"venue"
},
  "geometry": {"coordinates":[-2.2833468914,53.700843811],"type":"Point"}
}