{
  "type": "Feature",
  "properties": {
    "addr:full":"79 Scalford Rd Melton Mowbray Leicestershire LE13 1JZ",
    "addr:housenumber":"79",
    "addr:postcode":"le13 1jz",
    "addr:street":"Scalford Rd",
    "iso:country":"GB",
    "sg:address":"79 Scalford Rd",
    "sg:city":"Melton Mowbray",
    "sg:classifiers":[
        {
            "category":"Health Services",
            "subcategory":"Dentist",
            "type":"Services"
        }
    ],
    "sg:phone":"+44 1664 562209",
    "sg:postcode":"LE13 1JZ",
    "sg:province":"Leicestershire",
    "wof:name":"I Lusis",
    "wof:placetype":"venue"
},
  "geometry": {"coordinates":[-0.887904,52.770802],"type":"Point"}
}