{
  "type": "Feature",
  "properties": {
    "addr:full":"2 Tower Factory, Well Street, Finedon Wellingborough Northamptonshire NN9 5JP",
    "addr:housenumber":"2",
    "addr:postcode":"nn9 5jp",
    "addr:street":"Tower Factory Well Street",
    "iso:country":"GB",
    "sg:address":"2 Tower Factory, Well Street, Finedon",
    "sg:city":"Wellingborough",
    "sg:classifiers":[
        {
            "category":"Personal",
            "type":"Services"
        }
    ],
    "sg:phone":"+44 1933 682511",
    "sg:postcode":"NN9 5JP",
    "sg:province":"Northamptonshire",
    "sg:tags":[
        "wedding"
    ],
    "wof:name":"Anthony James",
    "wof:placetype":"venue"
},
  "geometry": {"coordinates":[-0.649276,52.340191],"type":"Point"}
}