{
  "type": "Feature",
  "properties": {
    "addr:full":"25 Midland Road Wellingborough Northamptonshire NN8 1HA",
    "addr:housenumber":"25",
    "addr:postcode":"nn8 1ha",
    "addr:street":"Midland Road",
    "iso:country":"GB",
    "sg:address":"25 Midland Road",
    "sg:city":"Wellingborough",
    "sg:classifiers":[
        {
            "category":"Restaurant",
            "type":"Food & Drink"
        }
    ],
    "sg:phone":"+44 1933 440440",
    "sg:postcode":"NN8 1HA",
    "sg:province":"Northamptonshire",
    "sg:tags":[
        "american",
        "-"
    ],
    "wof:name":"Chicago Nights Diner",
    "wof:placetype":"venue"
},
  "geometry": {"coordinates":[-0.6903290153,52.3016853333],"type":"Point"}
}