{
  "type": "Feature",
  "properties": {
    "iso:country":"GB",
    "sg:address":"Unit 34, Lydney Industrial Estate, Harbour Road",
    "sg:city":"Lydney",
    "sg:classifiers":[
        {
            "category":"Shopping",
            "subcategory":"Crafts & Fabrics",
            "type":"Retail Goods"
        }
    ],
    "sg:phone":"+44 1594 843494",
    "sg:postcode":"GL15 4EJ",
    "sg:province":"Gloucestershire",
    "sg:tags":[
        "boiler"
    ],
    "wof:name":"Kayanson Engineers Ltd.",
    "wof:placetype":"venue"
},
  "geometry": {"coordinates":[-2.517624,51.710091],"type":"Point"}
}