{
  "type": "Feature",
  "properties": {
    "iso:country":"GB",
    "sg:address":"West Bay",
    "sg:city":"Millport",
    "sg:classifiers":[
        {
            "category":"Social Services",
            "subcategory":"Retirement Home",
            "type":"Services"
        }
    ],
    "sg:phone":"+44 1475 530640",
    "sg:postcode":"KA28 0EZ",
    "sg:province":"North Ayrshire",
    "sg:tags":[
        "residential",
        "care"
    ],
    "wof:name":"The Towers Retirement Residence",
    "wof:placetype":"venue"
},
  "geometry": {"coordinates":[-4.9347839355,55.7513961792],"type":"Point"}
}