{
  "type": "Feature",
  "properties": {
    "iso:country":"GB",
    "sg:address":"Paxton House, 11 Woodside Crescent",
    "sg:city":"Glasgow",
    "sg:classifiers":[
        {
            "category":"Home & Garden",
            "subcategory":"Building Materials",
            "type":"Retail Goods"
        }
    ],
    "sg:phone":"+44 141 557 2717",
    "sg:postcode":"G3 7UL",
    "sg:province":"Glasgow City",
    "sg:tags":[
        "fencing"
    ],
    "wof:name":"Charterhill Ltd",
    "wof:placetype":"venue"
},
  "geometry": {"coordinates":[-4.272095,55.867493],"type":"Point"}
}