{
  "type": "Feature",
  "properties": {
    "addr:full":"Units 7-8 Portland Industrial Estate, Kingsway Luton Bedfordshire LU4 8HA",
    "addr:housenumber":"units 7-8;estate",
    "addr:postcode":"lu4 8ha",
    "addr:street":"Portland Industrial;Kingsway",
    "iso:country":"GB",
    "sg:address":"Units 7-8 Portland Industrial Estate, Kingsway",
    "sg:city":"Luton",
    "sg:classifiers":[
        {
            "category":"Manufacturing",
            "subcategory":"Petroleum Products",
            "type":"Manufacturing & Wholesale Goods"
        },
        {
            "category":"Manufacturing",
            "subcategory":"Building Materials",
            "type":"Manufacturing & Wholesale Goods"
        }
    ],
    "sg:phone":"+44 1582 401617",
    "sg:postcode":"LU4 8HA",
    "sg:province":"Bedfordshire",
    "sg:tags":[
        "double",
        "frame",
        "glazing",
        "window",
        "manufacturer"
    ],
    "wof:name":"Icknield Windows Ltd",
    "wof:placetype":"venue"
},
  "geometry": {"coordinates":[-0.4385499954,51.8861312866],"type":"Point"}
}