{
  "type": "Feature",
  "properties": {
    "addr:full":"21 Gerridge Street, Off Morley Street London Greater London SE1 7QG",
    "addr:housenumber":"21",
    "addr:postcode":"se1 7qg",
    "addr:street":"Gerridge Street Off Morley Street",
    "iso:country":"GB",
    "sg:address":"21 Gerridge Street, Off Morley Street",
    "sg:city":"London",
    "sg:classifiers":[
        {
            "category":"Personal",
            "subcategory":"Beauty Salon",
            "type":"Services"
        }
    ],
    "sg:postcode":"SE1 7QG",
    "sg:province":"Greater London",
    "sg:tags":[
        "lady",
        "hairdresser"
    ],
    "wof:name":"Maria's West End Hair Fashions",
    "wof:placetype":"venue"
},
  "geometry": {"coordinates":[-0.107638,51.498585],"type":"Point"}
}