{
  "type": "Feature",
  "properties": {
    "addr:full":"146 Hyde Road, Denton Manchester Greater Manchester M34 3DH",
    "addr:housenumber":"146",
    "addr:postcode":"m34 3dh",
    "addr:street":"Hyde Road",
    "iso:country":"GB",
    "sg:address":"146 Hyde Road, Denton",
    "sg:city":"Manchester",
    "sg:classifiers":[
        {
            "category":"Shopping",
            "subcategory":"News",
            "type":"Retail Goods"
        }
    ],
    "sg:phone":"+44 161 336 2890",
    "sg:postcode":"M34 3DH",
    "sg:province":"Greater Manchester",
    "sg:tags":[
        "newsagent"
    ],
    "wof:name":"R & P Whitehouse",
    "wof:placetype":"venue"
},
  "geometry": {"coordinates":[-2.1053540707,53.4563980103],"type":"Point"}
}