{
  "type": "Feature",
  "properties": {
    "iso:country":"GB",
    "sg:address":"216 Broadway",
    "sg:city":"Bexleyheath",
    "sg:classifiers":[
        {
            "category":"Shopping",
            "subcategory":"Mobile Phones",
            "type":"Retail Goods"
        }
    ],
    "sg:phone":"+44 20 8301 1121",
    "sg:postcode":"DA6 7AU",
    "sg:province":"Kent",
    "wof:name":"Fonelink One 2 One Shops",
    "wof:placetype":"venue"
},
  "geometry": {"coordinates":[0.1385139972,51.4575233459],"type":"Point"}
}