{
  "type": "Feature",
  "properties": {
    "addr:full":"1 Higher Lane, Langland Swansea Swansea SA3 4NS",
    "addr:housenumber":"1",
    "addr:postcode":"sa3 4ns",
    "addr:street":"Higher Lane",
    "iso:country":"GB",
    "sg:address":"1 Higher Lane, Langland",
    "sg:city":"Swansea",
    "sg:classifiers":[
        {
            "category":"Travel",
            "subcategory":"Hotels & Motels",
            "type":"Entertainment"
        }
    ],
    "sg:postcode":"SA3 4NS",
    "sg:province":"Swansea",
    "wof:name":"Hillcrest House Hotel",
    "wof:placetype":"venue"
},
  "geometry": {"coordinates":[-4.007596,51.571178],"type":"Point"}
}