{
  "type": "Feature",
  "properties": {
    "iso:country":"GB",
    "sg:address":"Dunnikier Way",
    "sg:city":"Kirkcaldy",
    "sg:classifiers":[
        {
            "category":"Education",
            "subcategory":"School",
            "type":"Public Place"
        },
        {
            "category":"Government",
            "subcategory":"Office",
            "type":"Public Place"
        }
    ],
    "sg:phone":"+44 1592 412711",
    "sg:postcode":"KY1 3LR",
    "sg:province":"Fife",
    "sg:tags":[
        "local",
        "authority"
    ],
    "wof:name":"Kirkcaldy High School",
    "wof:placetype":"venue"
},
  "geometry": {"coordinates":[-3.1356179714,56.1356735229],"type":"Point"}
}