{
  "type": "Feature",
  "properties": {
    "addr:full":"80 Denemoor Ct, Elmdene Rd Kenilworth Warwickshire CV8 2BX",
    "addr:housenumber":"80",
    "addr:postcode":"cv8 2bx",
    "addr:street":"Denemoor Ct Elmdene Rd",
    "iso:country":"GB",
    "sg:address":"80 Denemoor Ct, Elmdene Rd",
    "sg:city":"Kenilworth",
    "sg:classifiers":[
        {
            "category":"Professional",
            "subcategory":"Employment Agencies",
            "type":"Services"
        }
    ],
    "sg:phone":"+44 1926 850668",
    "sg:postcode":"CV8 2BX",
    "sg:province":"Warwickshire",
    "sg:tags":[
        "modelling"
    ],
    "wof:name":"Dry White Promotions",
    "wof:placetype":"venue"
},
  "geometry": {"coordinates":[-1.579441,52.342937],"type":"Point"}
}