{
  "type": "Feature",
  "properties": {
    "iso:country":"GB",
    "sg:address":"Church Road, Felmingham",
    "sg:city":"North Walsham",
    "sg:classifiers":[
        {
            "category":"Manufacturing",
            "subcategory":"Pottery",
            "type":"Manufacturing & Wholesale Goods"
        }
    ],
    "sg:phone":"+44 1692 403967",
    "sg:postcode":"NR28 0LQ",
    "sg:province":"Norfolk",
    "sg:tags":[
        "supplier",
        "manufacturer"
    ],
    "wof:name":"Belaugh Pottery",
    "wof:placetype":"venue"
},
  "geometry": {"coordinates":[1.35451,52.850529],"type":"Point"}
}