{
  "type": "Feature",
  "properties": {
    "iso:country":"GB",
    "sg:address":"22 Monks Mead, Bicknacre",
    "sg:city":"Chelmsford",
    "sg:classifiers":[
        {
            "category":"Shopping",
            "subcategory":"News",
            "type":"Retail Goods"
        }
    ],
    "sg:phone":"+44 1245 224602",
    "sg:postcode":"CM3 4EU",
    "sg:province":"Essex",
    "sg:tags":[
        "newsagent"
    ],
    "wof:name":"R B News",
    "wof:placetype":"venue"
},
  "geometry": {"coordinates":[0.585072,51.695286],"type":"Point"}
}