{
  "type": "Feature",
  "properties": {
    "addr:full":"47b Madeira Road, Holland On Sea Clacton-on-sea Essex CO15 5HZ",
    "addr:housenumber":"47b",
    "addr:postcode":"co15 5hz",
    "addr:street":"Madeira Road",
    "iso:country":"GB",
    "sg:address":"47b Madeira Road, Holland On Sea",
    "sg:city":"Clacton-on-sea",
    "sg:classifiers":[
        {
            "category":"Personal",
            "subcategory":"Beauty Salon",
            "type":"Services"
        }
    ],
    "sg:postcode":"CO15 5HZ",
    "sg:province":"Essex",
    "sg:tags":[
        "unisex",
        "hairdresser"
    ],
    "wof:name":"McAllister Hair Design",
    "wof:placetype":"venue"
},
  "geometry": {"coordinates":[1.183801055,51.7990608215],"type":"Point"}
}