{
  "type": "Feature",
  "properties": {
    "addr:full":"Greaves Way, Stanbridge Road Leighton Buzzard Bedfordshire LU7 4UB",
    "addr:postcode":"lu7 4ub",
    "addr:street":"Greaves Way Stanbridge Road",
    "iso:country":"GB",
    "sg:address":"Greaves Way, Stanbridge Road",
    "sg:city":"Leighton Buzzard",
    "sg:classifiers":[
        {
            "category":"Wholesale",
            "subcategory":"Construction Materials",
            "type":"Manufacturing & Wholesale Goods"
        }
    ],
    "sg:phone":"+44 1525 371110",
    "sg:postcode":"LU7 4UB",
    "sg:province":"Bedfordshire",
    "sg:tags":[
        "merchant",
        "glass"
    ],
    "wof:name":"Buzzard Glass",
    "wof:placetype":"venue"
},
  "geometry": {"coordinates":[-0.651574,51.913673],"type":"Point"}
}