{
  "type": "Feature",
  "properties": {
    "iso:country":"GB",
    "sg:address":"Ampthill Road",
    "sg:city":"Bedford",
    "sg:classifiers":[
        {
            "category":"Home & Garden",
            "subcategory":"Hardware",
            "type":"Retail Goods"
        }
    ],
    "sg:phone":"+44 1234 364621",
    "sg:postcode":"MK42 9ER",
    "sg:province":"Bedfordshire",
    "sg:tags":[
        "equipment",
        "central",
        "heating"
    ],
    "wof:name":"Danfoss Randall Ltd.",
    "wof:placetype":"venue"
},
  "geometry": {"coordinates":[-0.470514,52.127254],"type":"Point"}
}