{
  "type": "Feature",
  "properties": {
    "addr:full":"Holly Grove Farm, Verwood Rd Ringwood Dorset BH24 2DB",
    "addr:postcode":"bh24 2db",
    "addr:street":"Holly Grove;Verwood Rd",
    "iso:country":"GB",
    "sg:address":"Holly Grove Farm, Verwood Rd",
    "sg:city":"Ringwood",
    "sg:classifiers":[
        {
            "category":"Professional",
            "subcategory":"Engineering",
            "type":"Services"
        }
    ],
    "sg:phone":"+44 1425 461461",
    "sg:postcode":"BH24 2DB",
    "sg:province":"Dorset",
    "sg:tags":[
        "precision",
        "engineer"
    ],
    "wof:name":"Reed & Sons",
    "wof:placetype":"venue"
},
  "geometry": {"coordinates":[-1.845732,50.832539],"type":"Point"}
}