{
  "type": "Feature",
  "properties": {
    "addr:full":"45 Fernbank Drive, Armthorpe Doncaster South Yorkshire DN3 2HD",
    "addr:housenumber":"45",
    "addr:postcode":"dn3 2hd",
    "addr:street":"Fernbank Drive",
    "iso:country":"GB",
    "sg:address":"45 Fernbank Drive, Armthorpe",
    "sg:city":"Doncaster",
    "sg:classifiers":[
        {
            "category":"Building & Trades",
            "subcategory":"Construction",
            "type":"Services"
        }
    ],
    "sg:phone":"+44 1302 831711",
    "sg:postcode":"DN3 2HD",
    "sg:province":"South Yorkshire",
    "sg:tags":[
        "flooring"
    ],
    "wof:name":"D & J Dodson",
    "wof:placetype":"venue"
},
  "geometry": {"coordinates":[-1.052791,53.543343],"type":"Point"}
}