{
  "type": "Feature",
  "properties": {
    "iso:country":"GB",
    "sg:address":"25 Waterloo Road",
    "sg:city":"Sutton",
    "sg:classifiers":[
        {
            "category":"Building & Trades",
            "subcategory":"Construction",
            "type":"Services"
        }
    ],
    "sg:phone":"+44 20 8661 7098",
    "sg:postcode":"SM1 4LW",
    "sg:province":"Surrey",
    "sg:tags":[
        "contractor",
        "paving",
        "driveway"
    ],
    "wof:name":"Design Driveways",
    "wof:placetype":"venue"
},
  "geometry": {"coordinates":[-0.1816029996,51.3643226624],"type":"Point"}
}