{
  "type": "Feature",
  "properties": {
    "addr:full":"Unit 1/4 Old Station Close, Coalville Leicester Leicestershire LE67 3FH",
    "addr:housenumber":"unit 1 / 4",
    "addr:postcode":"le67 3fh",
    "addr:street":"Old Station Close",
    "iso:country":"GB",
    "sg:address":"Unit 1/4 Old Station Close, Coalville",
    "sg:city":"Leicester",
    "sg:classifiers":[
        {
            "category":"Communications",
            "subcategory":"Film & Video Production",
            "type":"Services"
        },
        {
            "category":"Organizations",
            "subcategory":"Membership Organization",
            "type":"Services"
        },
        {
            "category":"Food & Beverages",
            "subcategory":"Meat & Fish",
            "type":"Retail Goods"
        }
    ],
    "sg:phone":"+44 1530 830920",
    "sg:postcode":"LE67 3FH",
    "sg:province":"Leicestershire",
    "sg:tags":[
        "curers",
        "bacon",
        "ham",
        "butcher"
    ],
    "wof:name":"T S BLOOR & SONS LTD",
    "wof:placetype":"venue"
},
  "geometry": {"coordinates":[-1.3701210022,52.7255630493],"type":"Point"}
}