{
  "type": "Feature",
  "properties": {
    "addr:full":"Unit 1a Haven Industrial Estate, Pyewipe, Gilbey Road Grimsby Lincolnshire DN31 2SJ",
    "addr:housenumber":"unit 1a",
    "addr:postcode":"dn31 2sj",
    "addr:street":"Haven Industrial Estate Pyewipe Gilbey Road",
    "iso:country":"GB",
    "sg:address":"Unit 1a Haven Industrial Estate, Pyewipe, Gilbey Road",
    "sg:city":"Grimsby",
    "sg:classifiers":[
        {
            "category":"Manufacturing",
            "subcategory":"Metals",
            "type":"Manufacturing & Wholesale Goods"
        }
    ],
    "sg:phone":"+44 1472 340925",
    "sg:postcode":"DN31 2SJ",
    "sg:province":"Lincolnshire",
    "sg:tags":[
        "work",
        "sheet"
    ],
    "wof:name":"Fistco Engineering",
    "wof:placetype":"venue"
},
  "geometry": {"coordinates":[-0.1041899994,53.5789794922],"type":"Point"}
}