{
  "type": "Feature",
  "properties": {
    "addr:full":"Pottery Road, Off Coach Road Whitehaven Cumbria CA28 9BZ",
    "addr:postcode":"ca28 9bz",
    "addr:street":"Pottery Road Off Coach Road",
    "iso:country":"GB",
    "sg:address":"Pottery Road, Off Coach Road",
    "sg:city":"Whitehaven",
    "sg:classifiers":[
        {
            "category":"Professional",
            "subcategory":"Computer Services",
            "type":"Services"
        }
    ],
    "sg:postcode":"CA28 9BZ",
    "sg:province":"Cumbria",
    "sg:tags":[
        "system",
        "software"
    ],
    "wof:name":"Oakleaf Computers",
    "wof:placetype":"venue"
},
  "geometry": {"coordinates":[-3.5883889198,54.5406532288],"type":"Point"}
}