{
  "type": "Feature",
  "properties": {
    "iso:country":"GB",
    "sg:address":"7 Ashes La",
    "sg:city":"Oldham",
    "sg:classifiers":[
        {
            "category":"Building & Trades",
            "subcategory":"Construction",
            "type":"Services"
        }
    ],
    "sg:phone":"+44 161 652 2298",
    "sg:postcode":"OL4 4PF",
    "sg:province":"Lancashire",
    "sg:tags":[
        "decorator",
        "painter"
    ],
    "wof:name":"B Hallworth",
    "wof:placetype":"venue"
},
  "geometry": {"coordinates":[-2.065424,53.538513],"type":"Point"}
}