{
  "type": "Feature",
  "properties": {
    "iso:country":"GB",
    "sg:address":"Manor House",
    "sg:city":"Thirsk",
    "sg:classifiers":[
        {
            "category":"Home & Garden",
            "subcategory":"Garden Supply",
            "type":"Retail Goods"
        },
        {
            "category":"Farming",
            "subcategory":"Farm",
            "type":"Manufacturing & Wholesale Goods"
        }
    ],
    "sg:phone":"+44 1845 587207",
    "sg:postcode":"YO7 4DJ",
    "sg:province":"North Yorkshire",
    "sg:tags":[
        "mixed",
        "bulb",
        "crop",
        "grower"
    ],
    "wof:name":"R P Bell & Son",
    "wof:placetype":"venue"
},
  "geometry": {"coordinates":[-1.387161,54.218964],"type":"Point"}
}