{
  "type": "Feature",
  "properties": {
    "addr:full":"24 Rockingham Lane Sheffield South Yorkshire S1 4FW",
    "addr:housenumber":"24",
    "addr:postcode":"s1 4fw",
    "addr:street":"Rockingham Lane",
    "iso:country":"GB",
    "sg:address":"24 Rockingham Lane",
    "sg:city":"Sheffield",
    "sg:classifiers":[
        {
            "category":"Arts & Performance",
            "subcategory":"Theater",
            "type":"Entertainment"
        }
    ],
    "sg:phone":"+44 114 275 5328",
    "sg:postcode":"S1 4FW",
    "sg:province":"South Yorkshire",
    "sg:tags":[
        "theatre"
    ],
    "wof:name":"Compass Theatre Co",
    "wof:placetype":"venue"
},
  "geometry": {"coordinates":[-1.475001,53.380375],"type":"Point"}
}