{
  "type": "Feature",
  "properties": {
    "addr:full":"Unit 1 Eagle Wharf, 59 Lafone St London Greater London SE1 2LX",
    "addr:housenumber":"unit 1;59",
    "addr:postcode":"se1 2lx",
    "addr:street":"Eagle Wharf;Lafone St",
    "iso:country":"GB",
    "sg:address":"Unit 1 Eagle Wharf, 59 Lafone St",
    "sg:city":"London",
    "sg:classifiers":[
        {
            "category":"Manufacturing",
            "subcategory":"Tools & Machinery",
            "type":"Manufacturing & Wholesale Goods"
        }
    ],
    "sg:phone":"+44 20 7403 9550",
    "sg:postcode":"SE1 2LX",
    "sg:province":"Greater London",
    "sg:tags":[
        "society",
        "friendly"
    ],
    "wof:name":"Bishop,G N,",
    "wof:placetype":"venue"
},
  "geometry": {"coordinates":[-0.074500002,51.5035705566],"type":"Point"}
}