{
  "type": "Feature",
  "properties": {
    "iso:country":"GB",
    "sg:address":"26 Beaconhill Drive, St. Johns",
    "sg:city":"Worcester",
    "sg:classifiers":[
        {
            "category":"Retail",
            "subcategory":"Driving School",
            "type":"Services"
        }
    ],
    "sg:phone":"+44 1905 423879",
    "sg:postcode":"WR2 6DR",
    "sg:province":"Worcestershire",
    "wof:name":"Sarah's School Of Motoring",
    "wof:placetype":"venue"
},
  "geometry": {"coordinates":[-2.244102,52.209118],"type":"Point"}
}