{
  "type": "Feature",
  "properties": {
    "addr:full":"Intec 4 Basingstoke Hampshire RG24 8NE",
    "addr:housenumber":"4",
    "addr:postcode":"rg24 8ne",
    "addr:street":"Intec",
    "iso:country":"GB",
    "sg:address":"Intec 4",
    "sg:city":"Basingstoke",
    "sg:classifiers":[
        {
            "category":"Building & Trades",
            "subcategory":"Construction",
            "type":"Services"
        }
    ],
    "sg:phone":"+44 1256 331391",
    "sg:postcode":"RG24 8NE",
    "sg:province":"Hampshire",
    "sg:tags":[
        "contractor"
    ],
    "wof:name":"Intec Management Ltd.",
    "wof:placetype":"venue"
},
  "geometry": {"coordinates":[-1.064396,51.279987],"type":"Point"}
}