{
  "type": "Feature",
  "properties": {
    "iso:country":"GB",
    "sg:address":"227-229 Dickson Rd",
    "sg:city":"Blackpool",
    "sg:classifiers":[
        {
            "category":"Restaurant",
            "type":"Food & Drink"
        }
    ],
    "sg:phone":"+44 1253 296144",
    "sg:postcode":"FY1 2JH",
    "sg:province":"Lancashire",
    "sg:tags":[
        "indian",
        "-"
    ],
    "wof:name":"The Bombay Restaurant",
    "wof:placetype":"venue"
},
  "geometry": {"coordinates":[-3.053102,53.829655],"type":"Point"}
}