{
  "type": "Feature",
  "properties": {
    "iso:country":"GB",
    "sg:address":"58 High Street, Pavenham",
    "sg:city":"Bedford",
    "sg:classifiers":[
        {
            "category":"Shopping",
            "subcategory":"Musical Instruments",
            "type":"Retail Goods"
        }
    ],
    "sg:phone":"+44 1234 823609",
    "sg:postcode":"MK43 7PE",
    "sg:province":"Bedfordshire",
    "sg:tags":[
        "organ",
        "accessory"
    ],
    "wof:name":"R Shaftoe",
    "wof:placetype":"venue"
},
  "geometry": {"coordinates":[-0.608425,52.201504],"type":"Point"}
}