{
  "type": "Feature",
  "properties": {
    "iso:country":"GB",
    "sg:address":"5 Church Street",
    "sg:city":"Slough",
    "sg:classifiers":[
        {
            "category":"Bars & Pubs",
            "type":"Food & Drink"
        }
    ],
    "sg:phone":"+44 1753 520136",
    "sg:postcode":"SL1 1PQ",
    "sg:province":"Berkshire",
    "sg:tags":[
        "pubs",
        "inn"
    ],
    "wof:name":"K & P Donnelly",
    "wof:placetype":"venue"
},
  "geometry": {"coordinates":[-0.5930299759,51.5084648132],"type":"Point"}
}