{
  "type": "Feature",
  "properties": {
    "iso:country":"GB",
    "sg:address":"4 Marlborough Parade, Uxbridge Road",
    "sg:city":"Uxbridge",
    "sg:classifiers":[
        {
            "category":"Real Estate",
            "subcategory":"Real Estate Agent",
            "type":"Services"
        }
    ],
    "sg:phone":"+44 7711 704184",
    "sg:postcode":"UB10 0LR",
    "sg:province":"Greater London",
    "wof:name":"Thompson Viol",
    "wof:placetype":"venue"
},
  "geometry": {"coordinates":[-0.447039,51.53038],"type":"Point"}
}