{
  "type": "Feature",
  "properties": {
    "iso:country":"GB",
    "sg:address":"21 Clarefield Drive",
    "sg:city":"Maidenhead",
    "sg:classifiers":[
        {
            "category":"Professional",
            "subcategory":"Management & Consulting",
            "type":"Services"
        }
    ],
    "sg:postcode":"SL6 5DW",
    "sg:province":"Berkshire",
    "sg:tags":[
        "consultant",
        "business"
    ],
    "wof:name":"Birchwood Systems",
    "wof:placetype":"venue"
},
  "geometry": {"coordinates":[-0.754271,51.530941],"type":"Point"}
}