{
  "type": "Feature",
  "properties": {
    "addr:full":"Junction 6 Trading Estate, Forstal Road Maidstone Kent ME20 7XA",
    "addr:housenumber":"6",
    "addr:postcode":"me20 7xa",
    "addr:street":"Trading Estate Forstal Road",
    "iso:country":"GB",
    "sg:address":"Junction 6 Trading Estate, Forstal Road",
    "sg:city":"Maidstone",
    "sg:classifiers":[
        {
            "category":"Retail",
            "subcategory":"Auto Repair",
            "type":"Services"
        }
    ],
    "sg:phone":"+44 1622 717233",
    "sg:postcode":"ME20 7XA",
    "sg:province":"Kent",
    "sg:tags":[
        "body",
        "car"
    ],
    "wof:name":"Parkwood Specialist Coachworks Ltd.",
    "wof:placetype":"venue"
},
  "geometry": {"coordinates":[0.4696800113,51.2905082703],"type":"Point"}
}