{
  "type": "Feature",
  "properties": {
    "iso:country":"GB",
    "sg:address":"44 Homefield",
    "sg:city":"Bristol",
    "sg:classifiers":[
        {
            "category":"Shopping",
            "subcategory":"Department Store",
            "type":"Retail Goods"
        },
        {
            "category":"Home & Garden",
            "subcategory":"Carpets & Floor Coverings",
            "type":"Retail Goods"
        }
    ],
    "sg:postcode":"BS37 5US",
    "sg:province":"Gloucestershire",
    "sg:tags":[
        "carpets",
        "rug",
        "matting"
    ],
    "wof:name":"Sodbury Carpets",
    "wof:placetype":"venue"
},
  "geometry": {"coordinates":[-2.416749,51.548805],"type":"Point"}
}