{
  "type": "Feature",
  "properties": {
    "addr:full":"Old Stable, Annery Bideford Devon EX39 5JN",
    "addr:postcode":"ex39 5jn",
    "iso:country":"GB",
    "sg:address":"Old Stable, Annery",
    "sg:city":"Bideford",
    "sg:classifiers":[
        {
            "category":"Real Estate",
            "subcategory":"Architect",
            "type":"Services"
        }
    ],
    "sg:phone":"+44 1237 475978",
    "sg:postcode":"EX39 5JN",
    "sg:province":"Devon",
    "sg:tags":[
        "architectural"
    ],
    "wof:name":"D W Lott Architectural Consultant",
    "wof:placetype":"venue"
},
  "geometry": {"coordinates":[-4.204259,51.019249],"type":"Point"}
}