{
  "type": "Feature",
  "properties": {
    "addr:full":"13 West Terrace Redcar North Yorkshire TS10 1DS",
    "addr:housenumber":"13",
    "addr:postcode":"ts10 1ds",
    "addr:street":"West Terrace",
    "iso:country":"GB",
    "sg:address":"13 West Terrace",
    "sg:city":"Redcar",
    "sg:classifiers":[
        {
            "category":"Banks & Credit Unions",
            "subcategory":"Financial Services",
            "type":"Services"
        }
    ],
    "sg:phone":"+44 1642 483351",
    "sg:postcode":"TS10 1DS",
    "sg:province":"North Yorkshire",
    "sg:tags":[
        "building",
        "society"
    ],
    "wof:name":"Darlington Building Society",
    "wof:placetype":"venue"
},
  "geometry": {"coordinates":[-1.068876,54.619183],"type":"Point"}
}