{
  "type": "Feature",
  "properties": {
    "addr:full":"22 Melchett Crescent Northwich Cheshire CW9 7EP",
    "addr:housenumber":"22",
    "addr:postcode":"cw9 7ep",
    "addr:street":"Melchett Crescent",
    "iso:country":"GB",
    "sg:address":"22 Melchett Crescent",
    "sg:city":"Northwich",
    "sg:classifiers":[
        {
            "category":"Building & Trades",
            "subcategory":"Construction",
            "type":"Services"
        }
    ],
    "sg:phone":"+44 1606 43174",
    "sg:postcode":"CW9 7EP",
    "sg:province":"Cheshire",
    "sg:tags":[
        "contractor",
        "paving",
        "driveway"
    ],
    "wof:name":"Pave Tec",
    "wof:placetype":"venue"
},
  "geometry": {"coordinates":[-2.484847,53.253864],"type":"Point"}
}