{
  "type": "Feature",
  "properties": {
    "iso:country":"GB",
    "sg:address":"Throws Farm, Stebbing",
    "sg:city":"Dunmow",
    "sg:classifiers":[
        {
            "category":"Education",
            "subcategory":"Special Training",
            "type":"Public Place"
        }
    ],
    "sg:postcode":"CM6 3AQ",
    "sg:province":"Essex",
    "sg:tags":[
        "product",
        "centre"
    ],
    "wof:name":"Advanced Rework Technology",
    "wof:placetype":"venue"
},
  "geometry": {"coordinates":[0.404921,51.900589],"type":"Point"}
}