{
  "type": "Feature",
  "properties": {
    "addr:full":"59 Moss Way, Croxteth Liverpool Merseyside L11 0BL",
    "addr:housenumber":"59",
    "addr:postcode":"l11 0bl",
    "addr:street":"Moss Way",
    "iso:country":"GB",
    "sg:address":"59 Moss Way, Croxteth",
    "sg:city":"Liverpool",
    "sg:classifiers":[
        {
            "category":"Organizations",
            "subcategory":"Non-profit Organization",
            "type":"Services"
        }
    ],
    "sg:postcode":"L11 0BL",
    "sg:province":"Merseyside",
    "sg:tags":[
        "organisation",
        "voluntary",
        "charity"
    ],
    "wof:name":"Croxteth Tenants & Residents Association",
    "wof:placetype":"venue"
},
  "geometry": {"coordinates":[-2.896848,53.456779],"type":"Point"}
}