{
  "type": "Feature",
  "properties": {
    "iso:country":"GB",
    "sg:address":"25 Cadham Centre",
    "sg:city":"Glenrothes",
    "sg:classifiers":[
        {
            "category":"Real Estate",
            "subcategory":"Real Estate Services",
            "type":"Services"
        },
        {
            "category":"Retail",
            "subcategory":"Auto Rental",
            "type":"Services"
        }
    ],
    "sg:phone":"+44 1592 745760",
    "sg:postcode":"KY7 6RU",
    "sg:province":"Fife",
    "sg:tags":[
        "truck",
        "hire",
        "van",
        "plant",
        "leasing"
    ],
    "wof:name":"AB MANAGEMENT SERVICES LTD",
    "wof:placetype":"venue"
},
  "geometry": {"coordinates":[-3.1685490608,56.2079811096],"type":"Point"}
}