{
  "type": "Feature",
  "properties": {
    "addr:full":", Llangorse Brecon Powys LD3 7UB",
    "addr:postcode":"ld3 7ub",
    "iso:country":"GB",
    "sg:address":", Llangorse",
    "sg:city":"Brecon",
    "sg:classifiers":[
        {
            "category":"Bars & Pubs",
            "type":"Food & Drink"
        }
    ],
    "sg:phone":"+44 1874 658225",
    "sg:postcode":"LD3 7UB",
    "sg:province":"Powys",
    "sg:tags":[
        "pubs",
        "inn"
    ],
    "wof:name":"The Castle Inn",
    "wof:placetype":"venue"
},
  "geometry": {"coordinates":[-3.391142,51.949741],"type":"Point"}
}