{
  "type": "Feature",
  "properties": {
    "addr:full":"18-20 Park Street Slough Berkshire SL1 1PD",
    "addr:housenumber":"18-20",
    "addr:postcode":"sl1 1pd",
    "addr:street":"Park Street",
    "iso:country":"GB",
    "sg:address":"18-20 Park Street",
    "sg:city":"Slough",
    "sg:classifiers":[
        {
            "category":"Professional",
            "subcategory":"Business Services",
            "type":"Services"
        }
    ],
    "sg:phone":"+44 1753 517450",
    "sg:postcode":"SL1 1PD",
    "sg:province":"Berkshire",
    "sg:tags":[
        "import",
        "export",
        "agent"
    ],
    "wof:name":"International Marketing Corporation Ltd.",
    "wof:placetype":"venue"
},
  "geometry": {"coordinates":[-0.5914090276,51.5074615479],"type":"Point"}
}