{
  "type": "Feature",
  "properties": {
    "iso:country":"GB",
    "sg:address":"39 Market Square",
    "sg:city":"Crewkerne",
    "sg:classifiers":[
        {
            "category":"Travel",
            "subcategory":"Hotels & Motels",
            "type":"Entertainment"
        }
    ],
    "sg:phone":"+44 1460 73650",
    "sg:postcode":"TA18 7LP",
    "sg:province":"Dorset",
    "wof:name":"The George Hotel",
    "wof:placetype":"venue"
},
  "geometry": {"coordinates":[-2.795956,50.885361],"type":"Point"}
}