{
  "type": "Feature",
  "properties": {
    "iso:country":"GB",
    "sg:address":"32 Melcombe Avenue",
    "sg:city":"Weymouth",
    "sg:classifiers":[
        {
            "category":"Place Of Worship",
            "type":"Public Place"
        }
    ],
    "sg:phone":"+44 1305 780594",
    "sg:postcode":"DT4 7TH",
    "sg:province":"Dorset",
    "wof:name":"Christian Science Society",
    "wof:placetype":"venue"
},
  "geometry": {"coordinates":[-2.448165,50.623089],"type":"Point"}
}