{
  "type": "Feature",
  "properties": {
    "addr:full":"92 Eardley Road London Greater London SW16 6BL",
    "addr:housenumber":"92",
    "addr:postcode":"sw16 6bl",
    "addr:street":"Eardley Road",
    "iso:country":"GB",
    "sg:address":"92 Eardley Road",
    "sg:city":"London",
    "sg:classifiers":[
        {
            "category":"Building & Trades",
            "subcategory":"Construction",
            "type":"Services"
        }
    ],
    "sg:phone":"+44 20 8677 5741",
    "sg:postcode":"SW16 6BL",
    "sg:province":"Greater London",
    "sg:tags":[
        "builder"
    ],
    "wof:name":"Withglow Roofing & Repairs Ltd.",
    "wof:placetype":"venue"
},
  "geometry": {"coordinates":[-0.139404,51.42123],"type":"Point"}
}