{
  "type": "Feature",
  "properties": {
    "iso:country":"GB",
    "sg:address":"St James House, Horseley Fields",
    "sg:city":"Wolverhampton",
    "sg:classifiers":[
        {
            "category":"Retail",
            "subcategory":"Funeral Services",
            "type":"Services"
        }
    ],
    "sg:phone":"+44 1902 352251",
    "sg:postcode":"WV1 3DN",
    "sg:province":"West Midlands",
    "wof:name":"F Jennings & Sons Ltd.",
    "wof:placetype":"venue"
},
  "geometry": {"coordinates":[-2.120753,52.585613],"type":"Point"}
}