{
  "type": "Feature",
  "properties": {
    "addr:full":"42 Ansdell Road, South Shore Blackpool Lancashire FY1 6PY",
    "addr:housenumber":"42",
    "addr:postcode":"fy1 6py",
    "addr:street":"Ansdell Road",
    "iso:country":"GB",
    "sg:address":"42 Ansdell Road, South Shore",
    "sg:city":"Blackpool",
    "sg:classifiers":[
        {
            "category":"Shopping",
            "subcategory":"Used Merchandise",
            "type":"Retail Goods"
        }
    ],
    "sg:postcode":"FY1 6PY",
    "sg:province":"Lancashire",
    "sg:tags":[
        "shop",
        "second-hand"
    ],
    "wof:name":"A1 Domestics",
    "wof:placetype":"venue"
},
  "geometry": {"coordinates":[-3.0394980907,53.8033828735],"type":"Point"}
}