{
  "type": "Feature",
  "properties": {
    "addr:full":"5th Floor Cathedral Buildings, Dean Street Newcastle-upon-tyne Tyne and Wear NE1 1PG",
    "addr:housenumber":"5th floor cathedral buildings",
    "addr:postcode":"ne1 1pg",
    "addr:street":"Dean Street",
    "iso:country":"GB",
    "sg:address":"5th Floor Cathedral Buildings, Dean Street",
    "sg:city":"Newcastle-upon-tyne",
    "sg:classifiers":[
        {
            "category":"Real Estate",
            "subcategory":"Surveying",
            "type":"Services"
        }
    ],
    "sg:phone":"+44 191 261 2142",
    "sg:postcode":"NE1 1PG",
    "sg:province":"Tyne and Wear",
    "sg:tags":[
        "surveyor",
        "quantity"
    ],
    "wof:name":"Timothy J Brown",
    "wof:placetype":"venue"
},
  "geometry": {"coordinates":[-1.6123689413,54.9779167175],"type":"Point"}
}