{
  "type": "Feature",
  "properties": {
    "iso:country":"GB",
    "sg:address":"Liverpool Road, Kidsgrove",
    "sg:city":"Stoke-on-trent",
    "sg:classifiers":[
        {
            "category":"Food & Beverages",
            "subcategory":"Supermarket",
            "type":"Retail Goods"
        }
    ],
    "sg:phone":"+44 1782 782919",
    "sg:postcode":"ST7 4EQ",
    "sg:province":"Cheshire",
    "wof:name":"United Norwest Co-Operatives Ltd.",
    "wof:placetype":"venue"
},
  "geometry": {"coordinates":[-2.239414,53.086418],"type":"Point"}
}