{
  "type": "Feature",
  "properties": {
    "iso:country":"GB",
    "sg:address":"31 Monkgate",
    "sg:city":"York",
    "sg:classifiers":[
        {
            "category":"Health Services",
            "subcategory":"Clinic",
            "type":"Services"
        }
    ],
    "sg:phone":"+44 1904 630352",
    "sg:postcode":"YO3 7PB",
    "sg:province":"East Riding of Yorkshire",
    "sg:tags":[
        "planning",
        "family",
        "centre"
    ],
    "wof:name":"Family Planning Clinics",
    "wof:placetype":"venue"
},
  "geometry": {"coordinates":[-1.076693,53.96386],"type":"Point"}
}