{
  "type": "Feature",
  "properties": {
    "iso:country":"GB",
    "sg:address":"31a Howardsgate",
    "sg:city":"Welwyn Garden City",
    "sg:classifiers":[
        {
            "category":"Communications",
            "subcategory":"Newspaper",
            "type":"Services"
        }
    ],
    "sg:phone":"+44 1707 327551",
    "sg:postcode":"AL8 6AA",
    "sg:province":"Hertfordshire",
    "sg:tags":[
        "magazine"
    ],
    "wof:name":"The Welwyn & Hatfield Times",
    "wof:placetype":"venue"
},
  "geometry": {"coordinates":[-0.2057289928,51.8014297485],"type":"Point"}
}