{
  "type": "Feature",
  "properties": {
    "addr:full":"18c The Crescent, Littleport, Haddenham Ely Cambridgeshire CB6 1HS",
    "addr:housenumber":"18c",
    "addr:postcode":"cb6 1hs",
    "addr:street":"The Crescent",
    "iso:country":"GB",
    "sg:address":"18c The Crescent, Littleport, Haddenham",
    "sg:city":"Ely",
    "sg:classifiers":[
        {
            "category":"Home & Garden",
            "subcategory":"Carpets & Floor Coverings",
            "type":"Retail Goods"
        }
    ],
    "sg:phone":"+44 1353 861831",
    "sg:postcode":"CB6 1HS",
    "sg:province":"Cambridgeshire",
    "sg:tags":[
        "floorcoverings"
    ],
    "wof:name":"Storvite Ltd.",
    "wof:placetype":"venue"
},
  "geometry": {"coordinates":[0.301596,52.451061],"type":"Point"}
}