{
  "type": "Feature",
  "properties": {
    "addr:full":"1 Elder Road, Killearn Glasgow Argyll and Bute G63 9RX",
    "addr:housenumber":"1",
    "addr:postcode":"g63 9rx",
    "addr:street":"Elder Road",
    "iso:country":"GB",
    "sg:address":"1 Elder Road, Killearn",
    "sg:city":"Glasgow",
    "sg:classifiers":[
        {
            "category":"Organizations",
            "subcategory":"Non-profit Organization",
            "type":"Services"
        }
    ],
    "sg:phone":"+44 1360 550852",
    "sg:postcode":"G63 9RX",
    "sg:province":"Argyll and Bute",
    "sg:tags":[
        "organisation",
        "voluntary",
        "charity"
    ],
    "wof:name":"Crossroads (West Stirlingshire) Care Attendant Scheme",
    "wof:placetype":"venue"
},
  "geometry": {"coordinates":[-4.3698921204,56.0398254395],"type":"Point"}
}