{
  "type": "Feature",
  "properties": {
    "addr:full":"54 High Street Blackwood Caerphilly NP12 1HP",
    "addr:housenumber":"54",
    "addr:postcode":"np12 1hp",
    "addr:street":"High Street",
    "iso:country":"GB",
    "sg:address":"54 High Street",
    "sg:city":"Blackwood",
    "sg:classifiers":[
        {
            "category":"Home & Garden",
            "subcategory":"Carpets & Floor Coverings",
            "type":"Retail Goods"
        }
    ],
    "sg:postcode":"NP12 1HP",
    "sg:province":"Caerphilly",
    "sg:tags":[
        "carpets",
        "rug",
        "matting"
    ],
    "wof:name":"Wall to Wall Carpets",
    "wof:placetype":"venue"
},
  "geometry": {"coordinates":[-3.1959009171,51.6690826416],"type":"Point"}
}