{
  "type": "Feature",
  "properties": {
    "iso:country":"GB",
    "sg:address":"1 Northfield Industrial Estate, Beresford Avenue",
    "sg:city":"Wembley",
    "sg:classifiers":[
        {
            "category":"Shopping",
            "subcategory":"Bicycles & Sporting Goods",
            "type":"Retail Goods"
        }
    ],
    "sg:phone":"+44 20 8903 8177",
    "sg:postcode":"HA0 1XS",
    "sg:province":"Greater London",
    "sg:tags":[
        "dance",
        "balletwear"
    ],
    "wof:name":"Gamba of London Ltd.",
    "wof:placetype":"venue"
},
  "geometry": {"coordinates":[-0.3014,51.5439],"type":"Point"}
}