{
  "type": "Feature",
  "properties": {
    "iso:country":"GB",
    "sg:address":"Abbey House, 9 Cooper Street",
    "sg:city":"Manchester",
    "sg:classifiers":[
        {
            "category":"Cafe",
            "type":"Food & Drink"
        }
    ],
    "sg:phone":"+44 161 236 4234",
    "sg:postcode":"M2 2FW",
    "sg:province":"Greater Manchester",
    "sg:tags":[
        "tea",
        "room"
    ],
    "wof:name":"Great American Sandwich",
    "wof:placetype":"venue"
},
  "geometry": {"coordinates":[-2.2425289154,53.4793243408],"type":"Point"}
}