{
  "type": "Feature",
  "properties": {
    "iso:country":"GB",
    "sg:address":"6 Adams Row",
    "sg:city":"Southwell",
    "sg:classifiers":[
        {
            "category":"Utilities",
            "subcategory":"Natural Gas",
            "type":"Services"
        }
    ],
    "sg:phone":"+44 1636 814727",
    "sg:postcode":"NG25 0FF",
    "sg:province":"Nottinghamshire",
    "sg:tags":[
        "control",
        "energy",
        "management",
        "system"
    ],
    "wof:name":"Premier Heating Services",
    "wof:placetype":"venue"
},
  "geometry": {"coordinates":[-0.960379,53.080254],"type":"Point"}
}