{
  "type": "Feature",
  "properties": {
    "iso:country":"GB",
    "sg:address":"17 King Street",
    "sg:city":"Ulverston",
    "sg:classifiers":[
        {
            "category":"Shopping",
            "subcategory":"Shoes",
            "type":"Retail Goods"
        }
    ],
    "sg:phone":"+44 1229 583469",
    "sg:postcode":"LA12 7DZ",
    "sg:province":"Cumbria",
    "sg:tags":[
        "shop",
        "retailer",
        "footwear"
    ],
    "wof:name":"F Dickinson (Footwear) Ltd",
    "wof:placetype":"venue"
},
  "geometry": {"coordinates":[-3.0962040424,54.1966514587],"type":"Point"}
}