{
  "type": "Feature",
  "properties": {
    "iso:country":"GB",
    "sg:address":"327 Cluny Place",
    "sg:city":"Glenrothes",
    "sg:classifiers":[
        {
            "category":"Military Area",
            "subcategory":"Air Force Base",
            "type":"Public Place"
        }
    ],
    "sg:phone":"+44 1592 773333",
    "sg:postcode":"KY7 4QY",
    "sg:province":"Fife",
    "sg:tags":[
        "taxi",
        "hire",
        "private"
    ],
    "wof:name":"Alans Taxis",
    "wof:placetype":"venue"
},
  "geometry": {"coordinates":[-3.165162,56.1847],"type":"Point"}
}