{
  "type": "Feature",
  "properties": {
    "addr:full":"Unit 5 Block 1 Thorniebank Indu, Strial Estate, Nitshill Road Thorniebank Glasgow East Renfrewshire G46 8QG",
    "addr:housenumber":"unit 5 block",
    "addr:postcode":"g46 8qg",
    "addr:street":"Thorniebank;Nitshill Road",
    "iso:country":"GB",
    "sg:address":"Unit 5 Block 1 Thorniebank Indu, Strial Estate, Nitshill Road Thorniebank",
    "sg:city":"Glasgow",
    "sg:classifiers":[
        {
            "category":"Professional",
            "subcategory":"Testing Lab",
            "type":"Services"
        }
    ],
    "sg:phone":"+44 141 621 0777",
    "sg:postcode":"G46 8QG",
    "sg:province":"East Renfrewshire",
    "sg:tags":[
        "mot"
    ],
    "wof:name":"M S V  Motors",
    "wof:placetype":"venue"
},
  "geometry": {"coordinates":[-4.32444,55.801208],"type":"Point"}
}