{
  "type": "Feature",
  "properties": {
    "addr:full":"123 Oxford Street, Totterdown Bristol City of Bristol BS3 4RH",
    "addr:housenumber":"123",
    "addr:postcode":"bs3 4rh",
    "addr:street":"Oxford Street",
    "iso:country":"GB",
    "sg:address":"123 Oxford Street, Totterdown",
    "sg:city":"Bristol",
    "sg:classifiers":[
        {
            "category":"Food & Beverages",
            "subcategory":"Meat & Fish",
            "type":"Retail Goods"
        }
    ],
    "sg:phone":"+44 117 977 7298",
    "sg:postcode":"BS3 4RH",
    "sg:province":"City of Bristol",
    "sg:tags":[
        "chip"
    ],
    "wof:name":"Ocean Fish Bar",
    "wof:placetype":"venue"
},
  "geometry": {"coordinates":[-2.579243,51.442455],"type":"Point"}
}