{
  "type": "Feature",
  "properties": {
    "addr:full":"Penn Hill Avenue, Parkstone Poole Dorset BH14 9NB",
    "addr:postcode":"bh14 9nb",
    "addr:street":"Penn Hill Avenue",
    "iso:country":"GB",
    "sg:address":"Penn Hill Avenue, Parkstone",
    "sg:city":"Poole",
    "sg:classifiers":[
        {
            "category":"Shopping",
            "subcategory":"News",
            "type":"Retail Goods"
        }
    ],
    "sg:phone":"+44 1202 742860",
    "sg:postcode":"BH14 9NB",
    "sg:province":"Dorset",
    "sg:tags":[
        "newsagent"
    ],
    "wof:name":"Balfour News",
    "wof:placetype":"venue"
},
  "geometry": {"coordinates":[-1.9259829521,50.7233772278],"type":"Point"}
}