{
  "type": "Feature",
  "properties": {
    "addr:full":"34 Crescent Grn Kendal Cumbria LA9 6DR",
    "addr:housenumber":"34",
    "addr:postcode":"la9 6dr",
    "addr:street":"Crescent Grn",
    "iso:country":"GB",
    "sg:address":"34 Crescent Grn",
    "sg:city":"Kendal",
    "sg:classifiers":[
        {
            "category":"Home & Garden",
            "subcategory":"Building Materials",
            "type":"Retail Goods"
        },
        {
            "category":"Building & Trades",
            "subcategory":"Construction",
            "type":"Services"
        }
    ],
    "sg:postcode":"LA9 6DR",
    "sg:province":"Cumbria",
    "sg:tags":[
        "dry",
        "plasterers",
        "installers",
        "lining",
        "insulation",
        "screeders"
    ],
    "wof:name":"David Nicholson",
    "wof:placetype":"venue"
},
  "geometry": {"coordinates":[-2.736207,54.336578],"type":"Point"}
}