{
  "type": "Feature",
  "properties": {
    "addr:full":"Block F3, West Kent Cold Store, Rye Lane Sevenoaks Kent TN14 5HB",
    "addr:housenumber":"f3",
    "addr:postcode":"tn14 5hb",
    "addr:street":"West Kent Cold;Rye Lane",
    "iso:country":"GB",
    "sg:address":"Block F3, West Kent Cold Store, Rye Lane",
    "sg:city":"Sevenoaks",
    "sg:classifiers":[
        {
            "category":"Food & Beverages",
            "subcategory":"Meat & Fish",
            "type":"Retail Goods"
        }
    ],
    "sg:phone":"+44 1732 453922",
    "sg:postcode":"TN14 5HB",
    "sg:province":"Kent",
    "sg:tags":[
        "butcher"
    ],
    "wof:name":"Malpass Bros Ltd.",
    "wof:placetype":"venue"
},
  "geometry": {"coordinates":[0.17226,51.293911],"type":"Point"}
}