{
  "type": "Feature",
  "properties": {
    "iso:country":"GB",
    "sg:address":"Senior Dept, 3 Maresfield Gardens",
    "sg:city":"Hampstead",
    "sg:classifiers":[
        {
            "category":"Education",
            "subcategory":"School",
            "type":"Public Place"
        }
    ],
    "sg:phone":"+44 20 7435 2899",
    "sg:postcode":"NW3 5SS",
    "sg:province":"Greater London",
    "sg:tags":[
        "independent",
        "preparatory"
    ],
    "wof:name":"South Hampstead High School",
    "wof:placetype":"venue"
},
  "geometry": {"coordinates":[-0.17721,51.546139],"type":"Point"}
}