{
  "type": "Feature",
  "properties": {
    "iso:country":"GB",
    "sg:address":"24 Pelham Street",
    "sg:city":"Hastings",
    "sg:classifiers":[
        {
            "category":"Bars & Pubs",
            "type":"Food & Drink"
        }
    ],
    "sg:phone":"+44 1424 420193",
    "sg:postcode":"TN34 1PE",
    "sg:province":"East Sussex",
    "sg:tags":[
        "pubs",
        "inn"
    ],
    "wof:name":"The Carlisle",
    "wof:placetype":"venue"
},
  "geometry": {"coordinates":[0.58068,50.85511],"type":"Point"}
}