{
  "type": "Feature",
  "properties": {
    "addr:full":"Neasham Road, Middleton St George Darlington Durham DL2 1DW",
    "addr:postcode":"dl2 1dw",
    "addr:street":"Neasham Road Middleton",
    "iso:country":"GB",
    "sg:address":"Neasham Road, Middleton St George",
    "sg:city":"Darlington",
    "sg:classifiers":[
        {
            "category":"Sports & Exercise",
            "subcategory":"Golf",
            "type":"Entertainment"
        }
    ],
    "sg:phone":"+44 1325 332297",
    "sg:postcode":"DL2 1DW",
    "sg:province":"Durham",
    "sg:tags":[
        "club",
        "course"
    ],
    "wof:name":"Dinsdale Spa Golf Club Ltd The",
    "wof:placetype":"venue"
},
  "geometry": {"coordinates":[-1.5354239941,54.5075721741],"type":"Point"}
}