{
  "type": "Feature",
  "properties": {
    "addr:full":"18 Greenway, Whetstone Totteridge Greater London N20 8ED",
    "addr:housenumber":"18",
    "addr:postcode":"n20 8ed",
    "addr:street":"Greenway",
    "iso:country":"GB",
    "sg:address":"18 Greenway, Whetstone",
    "sg:city":"Totteridge",
    "sg:classifiers":[
        {
            "category":"Social Services",
            "subcategory":"Job Training",
            "type":"Services"
        },
        {
            "category":"Education",
            "subcategory":"Special Training",
            "type":"Public Place"
        }
    ],
    "sg:phone":"+44 20 8445 2223",
    "sg:postcode":"N20 8ED",
    "sg:province":"Greater London",
    "sg:tags":[
        "product",
        "centre"
    ],
    "wof:name":"InPractice Cpe Training Ltd",
    "wof:placetype":"venue"
},
  "geometry": {"coordinates":[-0.185462,51.62886],"type":"Point"}
}