{
  "type": "Feature",
  "properties": {
    "addr:full":"114 Leagrave Rd Luton Bedfordshire LU4 8HX",
    "addr:housenumber":"114",
    "addr:postcode":"lu4 8hx",
    "addr:street":"Leagrave Rd",
    "iso:country":"GB",
    "sg:address":"114 Leagrave Rd",
    "sg:city":"Luton",
    "sg:classifiers":[
        {
            "category":"Building & Trades",
            "subcategory":"Construction",
            "type":"Services"
        }
    ],
    "sg:phone":"+44 1582 454582",
    "sg:postcode":"LU4 8HX",
    "sg:province":"Bedfordshire",
    "sg:tags":[
        "paint",
        "household",
        "spraying"
    ],
    "wof:name":"Monoroma Enterprises",
    "wof:placetype":"venue"
},
  "geometry": {"coordinates":[-0.4316599965,51.8882369995],"type":"Point"}
}