{
  "type": "Feature",
  "properties": {
    "addr:full":"176 Hamstel Rd Southend On Sea Essex SS2 4PH",
    "addr:housenumber":"176",
    "addr:postcode":"ss2 4ph",
    "addr:street":"Hamstel Rd",
    "iso:country":"GB",
    "sg:address":"176 Hamstel Rd",
    "sg:city":"Southend On Sea",
    "sg:classifiers":[
        {
            "category":"Building & Trades",
            "subcategory":"Construction",
            "type":"Services"
        }
    ],
    "sg:phone":"+44 1702 613282",
    "sg:postcode":"SS2 4PH",
    "sg:province":"Essex",
    "sg:tags":[
        "builder"
    ],
    "wof:name":"Pagan Construction",
    "wof:placetype":"venue"
},
  "geometry": {"coordinates":[0.7369400263,51.5489997864],"type":"Point"}
}