{
  "type": "Feature",
  "properties": {
    "iso:country":"GB",
    "sg:address":"Syon House, Oak Hill, East Budleigh",
    "sg:city":"Budleigh Salterton",
    "sg:classifiers":[
        {
            "category":"Professional",
            "subcategory":"Business Services",
            "type":"Services"
        }
    ],
    "sg:phone":"+44 1395 445545",
    "sg:postcode":"EX9 7DP",
    "sg:province":"Devon",
    "sg:tags":[
        "import",
        "export",
        "agent"
    ],
    "wof:name":"Lamps & Components International Ltd.",
    "wof:placetype":"venue"
},
  "geometry": {"coordinates":[-3.316294,50.657471],"type":"Point"}
}