{
  "type": "Feature",
  "properties": {
    "addr:full":"Unit C St Benedicts Court Huntingdon Cambridgeshire PE29 3PN",
    "addr:housenumber":"unit",
    "addr:postcode":"pe29 3pn",
    "addr:street":"C St Benedicts Court",
    "iso:country":"GB",
    "sg:address":"Unit C St Benedicts Court",
    "sg:city":"Huntingdon",
    "sg:classifiers":[
        {
            "category":"Shopping",
            "subcategory":"Comic Books",
            "type":"Retail Goods"
        }
    ],
    "sg:phone":"+44 1480 456101",
    "sg:postcode":"PE29 3PN",
    "sg:province":"Cambridgeshire",
    "sg:tags":[
        "jeweller"
    ],
    "wof:name":"H Samuel",
    "wof:placetype":"venue"
},
  "geometry": {"coordinates":[-0.189304,52.33514],"type":"Point"}
}