{
  "type": "Feature",
  "properties": {
    "iso:country":"GB",
    "sg:address":"40 Roxborough Park",
    "sg:city":"Harrow",
    "sg:classifiers":[
        {
            "category":"Education",
            "subcategory":"University",
            "type":"Public Place"
        }
    ],
    "sg:postcode":"HA1 3AY",
    "sg:province":"Greater London",
    "sg:tags":[
        "higher"
    ],
    "wof:name":"Silvester Associates Ltd",
    "wof:placetype":"venue"
},
  "geometry": {"coordinates":[-0.340785,51.577942],"type":"Point"}
}