{
  "type": "Feature",
  "properties": {
    "addr:full":"116 Idle Road Bradford West Yorkshire BD2 4ND",
    "addr:housenumber":"116",
    "addr:postcode":"bd2 4nd",
    "addr:street":"Idle Road",
    "iso:country":"GB",
    "sg:address":"116 Idle Road",
    "sg:city":"Bradford",
    "sg:classifiers":[
        {
            "category":"Building & Trades",
            "subcategory":"Construction",
            "type":"Services"
        }
    ],
    "sg:postcode":"BD2 4ND",
    "sg:province":"West Yorkshire",
    "sg:tags":[
        "roofing"
    ],
    "wof:name":"Freear Services",
    "wof:placetype":"venue"
},
  "geometry": {"coordinates":[-1.7328959703,53.811504364],"type":"Point"}
}