{
  "type": "Feature",
  "properties": {
    "iso:country":"GB",
    "sg:address":"31 Hawkhill",
    "sg:city":"Dundee",
    "sg:classifiers":[
        {
            "category":"Professional",
            "subcategory":"Accounting & Tax Preparation",
            "type":"Services"
        }
    ],
    "sg:phone":"+44 1382 224197",
    "sg:postcode":"DD1 5DH",
    "sg:province":"Dundee City",
    "sg:tags":[
        "accountant"
    ],
    "wof:name":"Richard Han",
    "wof:placetype":"venue"
},
  "geometry": {"coordinates":[-2.98344,56.460236],"type":"Point"}
}