{
  "type": "Feature",
  "properties": {
    "iso:country":"GB",
    "sg:address":"12 Byron Street, Earl Shilton",
    "sg:city":"Leicester",
    "sg:classifiers":[
        {
            "category":"Building & Trades",
            "subcategory":"Plumbing",
            "type":"Services"
        }
    ],
    "sg:phone":"+44 1455 840370",
    "sg:postcode":"LE9 7FA",
    "sg:province":"Leicestershire",
    "sg:tags":[
        "heating"
    ],
    "wof:name":"J N Sharland",
    "wof:placetype":"venue"
},
  "geometry": {"coordinates":[-1.319572,52.572689],"type":"Point"}
}