{
  "type": "Feature",
  "properties": {
    "iso:country":"GB",
    "sg:address":"110 Dundry Lane, Dundry",
    "sg:city":"Bristol",
    "sg:classifiers":[
        {
            "category":"Education",
            "subcategory":"School",
            "type":"Public Place"
        },
        {
            "category":"Government",
            "subcategory":"Office",
            "type":"Public Place"
        }
    ],
    "sg:phone":"+44 117 964 7181",
    "sg:postcode":"BS41 8JE",
    "sg:province":"Somerset",
    "sg:tags":[
        "local",
        "authority"
    ],
    "wof:name":"Dundry C E V C Primary School",
    "wof:placetype":"venue"
},
  "geometry": {"coordinates":[-2.638543,51.39986],"type":"Point"}
}