{
  "type": "Feature",
  "properties": {
    "addr:full":"249 Ewell Road Surbiton Surrey KT6 7AA",
    "addr:housenumber":"249",
    "addr:postcode":"kt6 7aa",
    "addr:street":"Ewell Road",
    "iso:country":"GB",
    "sg:address":"249 Ewell Road",
    "sg:city":"Surbiton",
    "sg:classifiers":[
        {
            "category":"Retail",
            "subcategory":"Laundry & Dry Cleaning",
            "type":"Services"
        }
    ],
    "sg:phone":"+44 20 8390 8545",
    "sg:postcode":"KT6 7AA",
    "sg:province":"Surrey",
    "sg:tags":[
        "alteration"
    ],
    "wof:name":"Brodies Exclusive Dry Cleaners",
    "wof:placetype":"venue"
},
  "geometry": {"coordinates":[-0.295059,51.38512],"type":"Point"}
}