{
  "type": "Feature",
  "properties": {
    "addr:full":"8 Bakers Walk, Weston Turville Aylesbury Buckinghamshire HP22 5YP",
    "addr:housenumber":"8",
    "addr:postcode":"hp22 5yp",
    "addr:street":"Bakers Walk",
    "iso:country":"GB",
    "sg:address":"8 Bakers Walk, Weston Turville",
    "sg:city":"Aylesbury",
    "sg:classifiers":[
        {
            "category":"Building & Trades",
            "subcategory":"Landscaping Services",
            "type":"Services"
        }
    ],
    "sg:phone":"+44 1296 613066",
    "sg:postcode":"HP22 5YP",
    "sg:province":"Buckinghamshire",
    "sg:tags":[
        "landscape",
        "contractor"
    ],
    "wof:name":"Dennison & Greene",
    "wof:placetype":"venue"
},
  "geometry": {"coordinates":[-0.7553279996,51.7890052795],"type":"Point"}
}