{
  "type": "Feature",
  "properties": {
    "addr:full":"40 Northumberland Av Blackpool Lancashire FY2 9SA",
    "addr:housenumber":"40",
    "addr:postcode":"fy2 9sa",
    "addr:street":"Northumberland Av",
    "iso:country":"GB",
    "sg:address":"40 Northumberland Av",
    "sg:city":"Blackpool",
    "sg:classifiers":[
        {
            "category":"Retail",
            "subcategory":"Driving School",
            "type":"Services"
        }
    ],
    "sg:phone":"+44 1253 595318",
    "sg:postcode":"FY2 9SA",
    "sg:province":"Lancashire",
    "wof:name":"Drivacar",
    "wof:placetype":"venue"
},
  "geometry": {"coordinates":[-3.050844,53.837059],"type":"Point"}
}