{
  "type": "Feature",
  "properties": {
    "addr:full":"Dilke House, Malet St Bloomsbury Greater London WC1E 7JG",
    "addr:postcode":"wc1e 7jg",
    "addr:street":"Malet St",
    "iso:country":"GB",
    "sg:address":"Dilke House, Malet St",
    "sg:city":"Bloomsbury",
    "sg:classifiers":[
        {
            "category":"Organizations",
            "subcategory":"Professional Association",
            "type":"Services"
        }
    ],
    "sg:phone":"+44 20 7323 5550",
    "sg:postcode":"WC1E 7JG",
    "sg:province":"Greater London",
    "sg:tags":[
        "union",
        "trade"
    ],
    "wof:name":"Union of Shop Distributive & Allied Workers",
    "wof:placetype":"venue"
},
  "geometry": {"coordinates":[-0.1288789958,51.5201568604],"type":"Point"}
}