{
  "type": "Feature",
  "properties": {
    "addr:full":"17 Gander Green Lane Sutton Surrey SM1 2EG",
    "addr:housenumber":"17",
    "addr:postcode":"sm1 2eg",
    "addr:street":"Gander Green Lane",
    "iso:country":"GB",
    "sg:address":"17 Gander Green Lane",
    "sg:city":"Sutton",
    "sg:classifiers":[
        {
            "category":"Manufacturing",
            "subcategory":"Chemicals & Compounds",
            "type":"Manufacturing & Wholesale Goods"
        }
    ],
    "sg:phone":"+44 20 8642 8703",
    "sg:postcode":"SM1 2EG",
    "sg:province":"Surrey",
    "sg:tags":[
        "equipment",
        "plant"
    ],
    "wof:name":"Ichor Process Plant Ltd",
    "wof:placetype":"venue"
},
  "geometry": {"coordinates":[-0.2060090005,51.3609466553],"type":"Point"}
}