{
  "type": "Feature",
  "properties": {
    "addr:full":"27 Gilbert Way Braintree Essex CM7 6UD",
    "addr:housenumber":"27",
    "addr:postcode":"cm7 6ud",
    "addr:street":"Gilbert Way",
    "iso:country":"GB",
    "sg:address":"27 Gilbert Way",
    "sg:city":"Braintree",
    "sg:classifiers":[
        {
            "category":"Professional",
            "type":"Services"
        }
    ],
    "sg:phone":"+44 1787 238406",
    "sg:postcode":"CM7 6UD",
    "sg:province":"Essex",
    "sg:tags":[
        "entertainer"
    ],
    "wof:name":"Five Star Roadshow",
    "wof:placetype":"venue"
},
  "geometry": {"coordinates":[0.5740609765,51.8873825073],"type":"Point"}
}