{
  "type": "Feature",
  "properties": {
    "iso:country":"GB",
    "sg:address":"Moss Side, Formby",
    "sg:city":"Liverpool",
    "sg:classifiers":[
        {
            "category":"Building & Trades",
            "subcategory":"Landscaping Services",
            "type":"Services"
        }
    ],
    "sg:phone":"+44 1704 877964",
    "sg:postcode":"L14 0JS",
    "sg:province":"Merseyside",
    "sg:tags":[
        "pond",
        "aquarium"
    ],
    "wof:name":"Freshfield Water Gardens & Aquarium",
    "wof:placetype":"venue"
},
  "geometry": {"coordinates":[-2.87192,53.414715],"type":"Point"}
}