{
  "type": "Feature",
  "properties": {
    "iso:country":"GB",
    "sg:address":"Peartree Industrial Park, Crackley Way, Peartree Lane",
    "sg:city":"Dudley",
    "sg:classifiers":[
        {
            "category":"Manufacturing",
            "subcategory":"Motor Vehicles & Parts",
            "type":"Manufacturing & Wholesale Goods"
        }
    ],
    "sg:phone":"+44 1384 458809",
    "sg:postcode":"DY2 0UW",
    "sg:province":"West Midlands",
    "sg:tags":[
        "bearing"
    ],
    "wof:name":"Olympic Chevin",
    "wof:placetype":"venue"
},
  "geometry": {"coordinates":[-2.099779,52.497486],"type":"Point"}
}