{
  "type": "Feature",
  "properties": {
    "addr:full":"2 Bank Street Warrington Cheshire WA1 2AS",
    "addr:housenumber":"2",
    "addr:postcode":"wa1 2as",
    "addr:street":"Bank Street",
    "iso:country":"GB",
    "sg:address":"2 Bank Street",
    "sg:city":"Warrington",
    "sg:classifiers":[
        {
            "category":"Shopping",
            "subcategory":"Bicycles & Sporting Goods",
            "type":"Retail Goods"
        },
        {
            "category":"Sports & Exercise",
            "subcategory":"Sports Center",
            "type":"Entertainment"
        }
    ],
    "sg:phone":"+44 1925 245602",
    "sg:postcode":"WA1 2AS",
    "sg:province":"Cheshire",
    "sg:tags":[
        "shop",
        "sale"
    ],
    "sg:website":"http://www.jjb.co.uk",
    "wof:name":"J J B Sports Plc",
    "wof:placetype":"venue"
},
  "geometry": {"coordinates":[-2.589607954,53.3876686096],"type":"Point"}
}