{
  "type": "Feature",
  "properties": {
    "addr:full":"103 The Struet Brecon Powys LD3 7LT",
    "addr:housenumber":"103",
    "addr:postcode":"ld3 7lt",
    "addr:street":"The Struet",
    "iso:country":"GB",
    "sg:address":"103 The Struet",
    "sg:city":"Brecon",
    "sg:classifiers":[
        {
            "category":"Personal",
            "subcategory":"Beauty Salon",
            "type":"Services"
        }
    ],
    "sg:phone":"+44 1874 611486",
    "sg:postcode":"LD3 7LT",
    "sg:province":"Powys",
    "sg:tags":[
        "unisex",
        "hairdresser"
    ],
    "wof:name":"Curly Tops Hair Design",
    "wof:placetype":"venue"
},
  "geometry": {"coordinates":[-3.3248040676,51.9290313721],"type":"Point"}
}