{
  "type": "Feature",
  "properties": {
    "iso:country":"GB",
    "sg:address":"28 Egerton Gardens",
    "sg:city":"London",
    "sg:classifiers":[
        {
            "category":"Travel",
            "subcategory":"Hotels & Motels",
            "type":"Entertainment"
        }
    ],
    "sg:phone":"+44 20 7584 5533",
    "sg:postcode":"SW3 2BD",
    "sg:province":"Greater London",
    "wof:name":"The Franklin Hotel Ltd.",
    "wof:placetype":"venue"
},
  "geometry": {"coordinates":[-0.16803,51.494884],"type":"Point"}
}