{
  "type": "Feature",
  "properties": {
    "iso:country":"GB",
    "sg:address":"Brentwood Road",
    "sg:city":"Upminster",
    "sg:classifiers":[
        {
            "category":"Retail",
            "subcategory":"Auto Repair",
            "type":"Services"
        }
    ],
    "sg:postcode":"RM14 3SS",
    "sg:province":"Essex",
    "sg:tags":[
        "modification",
        "garage"
    ],
    "wof:name":"Bulphan Service Station",
    "wof:placetype":"venue"
},
  "geometry": {"coordinates":[0.3625819981,51.556476593],"type":"Point"}
}