{
  "type": "Feature",
  "properties": {
    "addr:full":"Ribchester House, Lancaster Road Preston Lancashire PR1 2QL",
    "addr:housenumber":"ribchester",
    "addr:postcode":"pr1 2ql",
    "addr:street":"Lancaster Road",
    "iso:country":"GB",
    "sg:address":"Ribchester House, Lancaster Road",
    "sg:city":"Preston",
    "sg:classifiers":[
        {
            "category":"Professional",
            "subcategory":"Lawyer & Legal Services",
            "type":"Services"
        }
    ],
    "sg:phone":"+44 1772 220022",
    "sg:postcode":"PR1 2QL",
    "sg:province":"Lancashire",
    "sg:tags":[
        "solicitor"
    ],
    "wof:name":"Forbes Solicitors",
    "wof:placetype":"venue"
},
  "geometry": {"coordinates":[-2.7004799843,53.7637481689],"type":"Point"}
}