{
  "type": "Feature",
  "properties": {
    "addr:full":"4 Kingscroft Rd Prestwick South Ayrshire KA9 1SA",
    "addr:housenumber":"4",
    "addr:postcode":"ka9 1sa",
    "addr:street":"Kingscroft Rd",
    "iso:country":"GB",
    "sg:address":"4 Kingscroft Rd",
    "sg:city":"Prestwick",
    "sg:classifiers":[
        {
            "category":"Manufacturing",
            "subcategory":"Rubber & Plastics",
            "type":"Manufacturing & Wholesale Goods"
        }
    ],
    "sg:phone":"+44 1292 671900",
    "sg:postcode":"KA9 1SA",
    "sg:province":"South Ayrshire",
    "sg:tags":[
        "product"
    ],
    "wof:name":"Kingscroft Logistics",
    "wof:placetype":"venue"
},
  "geometry": {"coordinates":[-4.6138892174,55.4947357178],"type":"Point"}
}