{
  "type": "Feature",
  "properties": {
    "iso:country":"GB",
    "sg:address":"250 Messingham Road",
    "sg:city":"Scunthorpe",
    "sg:classifiers":[
        {
            "category":"Building & Trades",
            "subcategory":"Construction",
            "type":"Services"
        }
    ],
    "sg:phone":"+44 1724 851833",
    "sg:postcode":"DN17 2QY",
    "sg:province":"Lincolnshire",
    "sg:tags":[
        "joiner",
        "carpenter"
    ],
    "wof:name":"Peter Fisher",
    "wof:placetype":"venue"
},
  "geometry": {"coordinates":[-0.657076,53.557323],"type":"Point"}
}