{
  "type": "Feature",
  "properties": {
    "addr:full":"West Leeds Industrial Park, Stanningley Road Leeds West Yorkshire LS13 4EL",
    "addr:postcode":"ls13 4el",
    "addr:street":"West Leeds Industrial Park Stanningley Road",
    "iso:country":"GB",
    "sg:address":"West Leeds Industrial Park, Stanningley Road",
    "sg:city":"Leeds",
    "sg:classifiers":[
        {
            "category":"Shopping",
            "subcategory":"Computers & Home Electronics",
            "type":"Retail Goods"
        }
    ],
    "sg:postcode":"LS13 4EL",
    "sg:province":"West Yorkshire",
    "sg:tags":[
        "sound",
        "equipment"
    ],
    "wof:name":"Elite Sound Communications",
    "wof:placetype":"venue"
},
  "geometry": {"coordinates":[-1.546587,53.794495],"type":"Point"}
}