{
  "type": "Feature",
  "properties": {
    "addr:full":"Middlewich Road, Byley Middlewich Cheshire CW10 9NT",
    "addr:postcode":"cw10 9nt",
    "addr:street":"Middlewich Road",
    "iso:country":"GB",
    "sg:address":"Middlewich Road, Byley",
    "sg:city":"Middlewich",
    "sg:classifiers":[
        {
            "category":"Military Area",
            "subcategory":"Air Force Base",
            "type":"Public Place"
        }
    ],
    "sg:phone":"+44 1606 834723",
    "sg:postcode":"CW10 9NT",
    "sg:province":"Cheshire",
    "sg:tags":[
        "water",
        "treatment"
    ],
    "wof:name":"Universal Mineral Supplies Ltd.",
    "wof:placetype":"venue"
},
  "geometry": {"coordinates":[-2.4531340599,53.1922988892],"type":"Point"}
}