{
  "type": "Feature",
  "properties": {
    "iso:country":"GB",
    "sg:address":"60-62 Bryn Street, Ashton-in-makerfieldbryn",
    "sg:city":"Wigan",
    "sg:classifiers":[
        {
            "category":"Insurance",
            "subcategory":"Insurance Agent",
            "type":"Services"
        }
    ],
    "sg:phone":"+44 1942 724008",
    "sg:postcode":"WN4 9AX",
    "sg:province":"Lancashire",
    "wof:name":"Ashton Insurance Services Ltd.",
    "wof:placetype":"venue"
},
  "geometry": {"coordinates":[-2.63887,53.487865],"type":"Point"}
}