{
  "type": "Feature",
  "properties": {
    "addr:full":"15 Main Street Driffield East Riding of Yorkshire YO25 8RL",
    "addr:housenumber":"15",
    "addr:postcode":"yo25 8rl",
    "addr:street":"Main Street",
    "iso:country":"GB",
    "sg:address":"15 Main Street",
    "sg:city":"Driffield",
    "sg:classifiers":[
        {
            "category":"Autos & Motor Vehicles",
            "subcategory":"Automobile Sales",
            "type":"Retail Goods"
        },
        {
            "category":"Retail",
            "subcategory":"Auto Repair",
            "type":"Services"
        }
    ],
    "sg:phone":"+44 1964 543603",
    "sg:postcode":"YO25 8RL",
    "sg:province":"East Riding of Yorkshire",
    "sg:tags":[
        "modification",
        "garage",
        "car"
    ],
    "wof:name":"Brandesburton Motor Co.",
    "wof:placetype":"venue"
},
  "geometry": {"coordinates":[-0.2801010013,53.9710845947],"type":"Point"}
}