{
  "type": "Feature",
  "properties": {
    "iso:country":"GB",
    "sg:address":"2 Reditch Road",
    "sg:city":"Studley",
    "sg:classifiers":[
        {
            "category":"Home & Garden",
            "subcategory":"Garden Supply",
            "type":"Retail Goods"
        },
        {
            "category":"Sports & Exercise",
            "subcategory":"Swimming Pool",
            "type":"Entertainment"
        }
    ],
    "sg:phone":"+44 1527 854519",
    "sg:postcode":"B80 7AX",
    "sg:province":"Warwickshire",
    "sg:tags":[
        "supplier",
        "equipment"
    ],
    "wof:name":"Planscapes Leisure Ltd.",
    "wof:placetype":"venue"
},
  "geometry": {"coordinates":[-1.895231,52.27467],"type":"Point"}
}