{
  "type": "Feature",
  "properties": {
    "iso:country":"GB",
    "sg:address":"Park Street",
    "sg:city":"Cambridge",
    "sg:classifiers":[
        {
            "category":"Bars & Pubs",
            "type":"Food & Drink"
        },
        {
            "category":"Community Center",
            "subcategory":"Social",
            "type":"Public Place"
        }
    ],
    "sg:phone":"+44 1223 352999",
    "sg:postcode":"CB5 8AS",
    "sg:province":"Cambridgeshire",
    "sg:tags":[
        "pubs",
        "house",
        "inn",
        "activity"
    ],
    "wof:name":"The Maypole",
    "wof:placetype":"venue"
},
  "geometry": {"coordinates":[0.119612,52.209415],"type":"Point"}
}