{
  "type": "Feature",
  "properties": {
    "iso:country":"GB",
    "sg:address":"Mansfield Rd",
    "sg:city":"Poole",
    "sg:classifiers":[
        {
            "category":"Health Services",
            "subcategory":"Clinic",
            "type":"Services"
        }
    ],
    "sg:phone":"+44 1202 731818",
    "sg:postcode":"BH14 0DJ",
    "sg:province":"Dorset",
    "sg:tags":[
        "planning",
        "family",
        "centre"
    ],
    "wof:name":"Parkstone Family Planning Clinic",
    "wof:placetype":"venue"
},
  "geometry": {"coordinates":[-1.942084,50.728306],"type":"Point"}
}