{
  "type": "Feature",
  "properties": {
    "addr:full":"Centric Ho, 390-391 Strand London Greater London WC2R 0LT",
    "addr:housenumber":"390-391",
    "addr:postcode":"wc2r 0lt",
    "addr:street":"Strand",
    "iso:country":"GB",
    "sg:address":"Centric Ho, 390-391 Strand",
    "sg:city":"London",
    "sg:classifiers":[
        {
            "category":"Professional",
            "subcategory":"Management & Consulting",
            "type":"Services"
        }
    ],
    "sg:postcode":"WC2R 0LT",
    "sg:province":"Greater London",
    "sg:tags":[
        "consultant",
        "business"
    ],
    "wof:name":"Centric Management Consultants Ltd",
    "wof:placetype":"venue"
},
  "geometry": {"coordinates":[-0.1215500012,51.5103683472],"type":"Point"}
}