{
  "type": "Feature",
  "properties": {
    "addr:full":"19 Ringway Industrial Estate, Besk Road Huddersfield West Yorkshire HD1 5DG",
    "addr:housenumber":"19",
    "addr:postcode":"hd1 5dg",
    "addr:street":"Ringway Industrial Estate Besk Road",
    "iso:country":"GB",
    "sg:address":"19 Ringway Industrial Estate, Besk Road",
    "sg:city":"Huddersfield",
    "sg:classifiers":[
        {
            "category":"Professional",
            "subcategory":"Engineering",
            "type":"Services"
        }
    ],
    "sg:phone":"+44 1484 426611",
    "sg:postcode":"HD1 5DG",
    "sg:province":"West Yorkshire",
    "sg:tags":[
        "engineer"
    ],
    "wof:name":"Premier Farnell Uk Ltd.",
    "wof:placetype":"venue"
},
  "geometry": {"coordinates":[-1.7826839685,53.6469535828],"type":"Point"}
}