{
  "type": "Feature",
  "properties": {
    "addr:full":"301 Walsall Road, Stone Cross West Bromwich West Midlands B71 3LN",
    "addr:housenumber":"301",
    "addr:postcode":"b71 3ln",
    "addr:street":"Walsall Road",
    "iso:country":"GB",
    "sg:address":"301 Walsall Road, Stone Cross",
    "sg:city":"West Bromwich",
    "sg:classifiers":[
        {
            "category":"Building & Trades",
            "subcategory":"Construction",
            "type":"Services"
        }
    ],
    "sg:phone":"+44 121 588 2675",
    "sg:postcode":"B71 3LN",
    "sg:province":"West Midlands",
    "sg:tags":[
        "decorator",
        "painter"
    ],
    "wof:name":"David Moore & Co Decorators",
    "wof:placetype":"venue"
},
  "geometry": {"coordinates":[-1.982518,52.545952],"type":"Point"}
}