{
  "type": "Feature",
  "properties": {
    "addr:full":"Peel St Stalybridge Greater Manchester SK15 1PT",
    "addr:postcode":"sk15 1pt",
    "addr:street":"Peel St",
    "iso:country":"GB",
    "sg:address":"Peel St",
    "sg:city":"Stalybridge",
    "sg:classifiers":[
        {
            "category":"Retail",
            "subcategory":"Auto Repair",
            "type":"Services"
        }
    ],
    "sg:phone":"+44 161 303 7665",
    "sg:postcode":"SK15 1PT",
    "sg:province":"Greater Manchester",
    "sg:tags":[
        "modification",
        "garage"
    ],
    "wof:name":"Bancroft Motor Services",
    "wof:placetype":"venue"
},
  "geometry": {"coordinates":[-2.067774,53.48045],"type":"Point"}
}