{
  "type": "Feature",
  "properties": {
    "iso:country":"GB",
    "sg:address":"9 Hill View",
    "sg:city":"Newport Pagnell",
    "sg:classifiers":[
        {
            "category":"Freight",
            "type":"Transportation"
        }
    ],
    "sg:phone":"+44 1908 613328",
    "sg:postcode":"MK16 8BE",
    "sg:province":"Buckinghamshire",
    "sg:tags":[
        "haulage",
        "road"
    ],
    "wof:name":"Specialist Cargo Services",
    "wof:placetype":"venue"
},
  "geometry": {"coordinates":[-0.7436239719,52.081237793],"type":"Point"}
}