{
  "type": "Feature",
  "properties": {
    "iso:country":"GB",
    "sg:address":"116 Rouncil Lane",
    "sg:city":"Kenilworth",
    "sg:classifiers":[
        {
            "category":"Bars & Pubs",
            "subcategory":"Sports Bar",
            "type":"Food & Drink"
        },
        {
            "category":"Professional",
            "type":"Services"
        }
    ],
    "sg:phone":"+44 1926 853611",
    "sg:postcode":"CV8 1FP",
    "sg:province":"Warwickshire",
    "sg:tags":[
        "reflexology",
        "therapist",
        "reflexologists"
    ],
    "wof:name":"Susan Sellen",
    "wof:placetype":"venue"
},
  "geometry": {"coordinates":[-1.583131,52.331924],"type":"Point"}
}