{
  "type": "Feature",
  "properties": {
    "addr:full":"1 Elbow St Manchester Greater Manchester M19 3PY",
    "addr:housenumber":"1",
    "addr:postcode":"m19 3py",
    "addr:street":"Elbow St",
    "iso:country":"GB",
    "sg:address":"1 Elbow St",
    "sg:city":"Manchester",
    "sg:classifiers":[
        {
            "category":"Taxi",
            "type":"Transportation"
        }
    ],
    "sg:postcode":"M19 3PY",
    "sg:province":"Greater Manchester",
    "sg:tags":[
        "mini",
        "cab"
    ],
    "wof:name":"Harolds Cars",
    "wof:placetype":"venue"
},
  "geometry": {"coordinates":[-2.191589,53.444855],"type":"Point"}
}