{
  "type": "Feature",
  "properties": {
    "addr:full":"12 Leafield Way Bradford West Yorkshire BD2 3RY",
    "addr:housenumber":"12",
    "addr:postcode":"bd2 3ry",
    "addr:street":"Leafield Way",
    "iso:country":"GB",
    "sg:address":"12 Leafield Way",
    "sg:city":"Bradford",
    "sg:classifiers":[
        {
            "category":"Building & Trades",
            "subcategory":"Construction",
            "type":"Services"
        }
    ],
    "sg:phone":"+44 1274 641753",
    "sg:postcode":"BD2 3RY",
    "sg:province":"West Yorkshire",
    "sg:tags":[
        "joiner",
        "carpenter"
    ],
    "wof:name":"Designs In Times",
    "wof:placetype":"venue"
},
  "geometry": {"coordinates":[-1.725356,53.815403],"type":"Point"}
}