{
  "type": "Feature",
  "properties": {
    "iso:country":"GB",
    "sg:address":"18 Clarence Grove Road",
    "sg:city":"Weston-super-mare",
    "sg:classifiers":[
        {
            "category":"Health Services",
            "subcategory":"Podiatrist",
            "type":"Services"
        }
    ],
    "sg:phone":"+44 1934 419136",
    "sg:postcode":"BS23 4AQ",
    "sg:province":"Somerset",
    "sg:tags":[
        "podiatrists",
        "chiropodist"
    ],
    "wof:name":"Yvonne V Sutton",
    "wof:placetype":"venue"
},
  "geometry": {"coordinates":[-2.975188,51.336178],"type":"Point"}
}