{
  "type": "Feature",
  "properties": {
    "addr:full":"Valley Farm, Brooke Rd, Shotesham Norwich Norfolk NR15 1XL",
    "addr:postcode":"nr15 1xl",
    "addr:street":"Valley;Brooke Rd",
    "iso:country":"GB",
    "sg:address":"Valley Farm, Brooke Rd, Shotesham",
    "sg:city":"Norwich",
    "sg:classifiers":[
        {
            "category":"Farming",
            "subcategory":"Farm",
            "type":"Manufacturing & Wholesale Goods"
        }
    ],
    "sg:postcode":"NR15 1XL",
    "sg:province":"Norfolk",
    "sg:tags":[
        "mixed",
        "crop"
    ],
    "wof:name":"Banham,A,& Son",
    "wof:placetype":"venue"
},
  "geometry": {"coordinates":[1.36928,52.541679],"type":"Point"}
}