{
  "type": "Feature",
  "properties": {
    "iso:country":"GB",
    "sg:address":"3 Gorringe Valley Rd, Lower Willingdon",
    "sg:city":"Eastbourne",
    "sg:classifiers":[
        {
            "category":"Taxi",
            "type":"Transportation"
        }
    ],
    "sg:phone":"+44 1323 484352",
    "sg:postcode":"BN20 9SX",
    "sg:province":"East Sussex",
    "sg:tags":[
        "mini",
        "cab"
    ],
    "wof:name":"Station Taxis",
    "wof:placetype":"venue"
},
  "geometry": {"coordinates":[0.2487280071,50.8059120178],"type":"Point"}
}