{
  "type": "Feature",
  "properties": {
    "addr:full":"P O Box 10640 London Greater London SW10 9FN",
    "addr:housenumber":"box 10640",
    "addr:postcode":"sw10 9fn",
    "iso:country":"GB",
    "sg:address":"P O Box 10640",
    "sg:city":"London",
    "sg:classifiers":[
        {
            "category":"Manufacturing",
            "subcategory":"Jewelry",
            "type":"Manufacturing & Wholesale Goods"
        }
    ],
    "sg:phone":"+44 20 7373 3369",
    "sg:postcode":"SW10 9FN",
    "sg:province":"Greater London",
    "sg:tags":[
        "design",
        "jewellery"
    ],
    "wof:name":"Coleman Douglas Pearls",
    "wof:placetype":"venue"
},
  "geometry": {"coordinates":[-0.1870590001,51.4856185913],"type":"Point"}
}