{
  "type": "Feature",
  "properties": {
    "addr:full":"Marina, 57a East Lane, Stainforth Doncaster South Yorkshire DN7 5DY",
    "addr:housenumber":"57a",
    "addr:postcode":"dn7 5dy",
    "addr:street":"Marina;East Lane",
    "iso:country":"GB",
    "sg:address":"Marina, 57a East Lane, Stainforth",
    "sg:city":"Doncaster",
    "sg:classifiers":[
        {
            "category":"Building & Trades",
            "subcategory":"Construction",
            "type":"Services"
        }
    ],
    "sg:phone":"+44 1302 841210",
    "sg:postcode":"DN7 5DY",
    "sg:province":"South Yorkshire",
    "sg:tags":[
        "builder"
    ],
    "wof:name":"Dm Building Services",
    "wof:placetype":"venue"
},
  "geometry": {"coordinates":[-1.030399,53.595074],"type":"Point"}
}