{
  "type": "Feature",
  "properties": {
    "addr:full":"191 Rugby Rd, Milverton Leamington Spa Warwickshire CV32 6DX",
    "addr:housenumber":"191",
    "addr:postcode":"cv32 6dx",
    "addr:street":"Rugby Rd",
    "iso:country":"GB",
    "sg:address":"191 Rugby Rd, Milverton",
    "sg:city":"Leamington Spa",
    "sg:classifiers":[
        {
            "category":"Professional",
            "subcategory":"Computer Services",
            "type":"Services"
        }
    ],
    "sg:postcode":"CV32 6DX",
    "sg:province":"Warwickshire",
    "sg:tags":[
        "system",
        "software"
    ],
    "wof:name":"Computers in Action Ltd",
    "wof:placetype":"venue"
},
  "geometry": {"coordinates":[-1.5497690439,52.2916412354],"type":"Point"}
}