{
  "type": "Feature",
  "properties": {
    "iso:country":"GB",
    "sg:address":"Tulya House, 67-69 High Street",
    "sg:city":"Bagshot",
    "sg:classifiers":[
        {
            "category":"Education",
            "subcategory":"School",
            "type":"Public Place"
        }
    ],
    "sg:phone":"+44 1491 641641",
    "sg:postcode":"GU19 5AH",
    "sg:province":"Berkshire",
    "sg:tags":[
        "local",
        "authority"
    ],
    "wof:name":"Group 5 Training Ltd.",
    "wof:placetype":"venue"
},
  "geometry": {"coordinates":[-0.6915789843,51.3622741699],"type":"Point"}
}