{
  "type": "Feature",
  "properties": {
    "addr:full":"9a Fore Street Wellington Devon TA21 8AA",
    "addr:housenumber":"9a",
    "addr:postcode":"ta21 8aa",
    "addr:street":"Fore Street",
    "iso:country":"GB",
    "sg:address":"9a Fore Street",
    "sg:city":"Wellington",
    "sg:classifiers":[
        {
            "category":"Food & Beverages",
            "subcategory":"Bakery",
            "type":"Retail Goods"
        }
    ],
    "sg:phone":"+44 1823 662549",
    "sg:postcode":"TA21 8AA",
    "sg:province":"Devon",
    "sg:tags":[
        "baker"
    ],
    "wof:name":"Three Cooks Ltd.",
    "wof:placetype":"venue"
},
  "geometry": {"coordinates":[-3.229437,50.977451],"type":"Point"}
}