{
  "type": "Feature",
  "properties": {
    "addr:full":"Braybon Av Brighton East Sussex BN1 8EA",
    "addr:postcode":"bn1 8ea",
    "addr:street":"Av Brighton",
    "iso:country":"GB",
    "sg:address":"Braybon Av",
    "sg:city":"Brighton",
    "sg:classifiers":[
        {
            "category":"Place Of Worship",
            "type":"Public Place"
        }
    ],
    "sg:phone":"+44 1273 563017",
    "sg:postcode":"BN1 8EA",
    "sg:province":"East Sussex",
    "wof:name":"St Thomas More R C Church",
    "wof:placetype":"venue"
},
  "geometry": {"coordinates":[-0.1428859979,50.85887146],"type":"Point"}
}