{
  "type": "Feature",
  "properties": {
    "addr:full":"North Devon Auction Rooms, New Road South Molton Devon EX36 4BH",
    "addr:postcode":"ex36 4bh",
    "addr:street":"North Devon;New Road South",
    "iso:country":"GB",
    "sg:address":"North Devon Auction Rooms, New Road",
    "sg:city":"South Molton",
    "sg:classifiers":[
        {
            "category":"Professional",
            "type":"Services"
        }
    ],
    "sg:phone":"+44 1769 574888",
    "sg:postcode":"EX36 4BH",
    "sg:province":"Devon",
    "sg:tags":[
        "auctioneer"
    ],
    "wof:name":"John D Fleming & Co",
    "wof:placetype":"venue"
},
  "geometry": {"coordinates":[-3.831824,51.017647],"type":"Point"}
}