{
  "type": "Feature",
  "properties": {
    "iso:country":"GB",
    "sg:address":"Mayfield Road",
    "sg:city":"Leicester",
    "sg:classifiers":[
        {
            "category":"Social Services",
            "type":"Services"
        },
        {
            "category":"Government",
            "subcategory":"Office",
            "type":"Public Place"
        }
    ],
    "sg:phone":"+44 116 254 8855",
    "sg:postcode":"LE2 1LR",
    "sg:province":"Leicestershire",
    "sg:tags":[
        "local",
        "ds"
    ],
    "wof:name":"Mayfield Children & Family Centre",
    "wof:placetype":"venue"
},
  "geometry": {"coordinates":[-1.1135519743,52.6245040894],"type":"Point"}
}