{
  "type": "Feature",
  "properties": {
    "addr:full":"58 Whelley Wigan Lancashire WN1 3PQ",
    "addr:housenumber":"58",
    "addr:postcode":"wn1 3pq",
    "addr:street":"Whelley Wigan",
    "iso:country":"GB",
    "sg:address":"58 Whelley",
    "sg:city":"Wigan",
    "sg:classifiers":[
        {
            "category":"Retail",
            "subcategory":"Repair Shop",
            "type":"Services"
        }
    ],
    "sg:phone":"+44 1942 214771",
    "sg:postcode":"WN1 3PQ",
    "sg:province":"Lancashire",
    "sg:tags":[
        "radio",
        "television",
        "video"
    ],
    "wof:name":"Trend Electrical",
    "wof:placetype":"venue"
},
  "geometry": {"coordinates":[-2.6172449589,53.5515975952],"type":"Point"}
}