{
  "type": "Feature",
  "properties": {
    "iso:country":"GB",
    "sg:address":"59 Station Road, Ainsdale",
    "sg:city":"Southport",
    "sg:classifiers":[
        {
            "category":"Food & Beverages",
            "subcategory":"Supermarket",
            "type":"Retail Goods"
        }
    ],
    "sg:phone":"+44 1704 578081",
    "sg:postcode":"PR8 3HH",
    "sg:province":"Lancashire",
    "wof:name":"Spar Stores",
    "wof:placetype":"venue"
},
  "geometry": {"coordinates":[-3.042064,53.602119],"type":"Point"}
}