{
  "type": "Feature",
  "properties": {
    "addr:full":"82 Trentham Road, Longton Stoke-on-trent Staffordshire ST3 4DY",
    "addr:housenumber":"82",
    "addr:postcode":"staffordshire st3 4dy",
    "addr:street":"Trentham Road",
    "iso:country":"GB",
    "sg:address":"82 Trentham Road, Longton",
    "sg:city":"Stoke-on-trent",
    "sg:classifiers":[
        {
            "category":"Personal",
            "subcategory":"Beauty Salon",
            "type":"Services"
        }
    ],
    "sg:postcode":"ST3 4DY",
    "sg:province":"Staffordshire",
    "sg:tags":[
        "unisex",
        "hairdresser"
    ],
    "wof:name":"The Salon",
    "wof:placetype":"venue"
},
  "geometry": {"coordinates":[-2.134792,52.981182],"type":"Point"}
}