{
  "type": "Feature",
  "properties": {
    "iso:country":"GB",
    "sg:address":"82 Trentham Road, Longton",
    "sg:city":"Stoke-on-trent",
    "sg:classifiers":[
        {
            "category":"Personal",
            "subcategory":"Beauty Salon",
            "type":"Services"
        }
    ],
    "sg:postcode":"ST3 4DY",
    "sg:province":"Staffordshire",
    "sg:tags":[
        "unisex",
        "hairdresser"
    ],
    "wof:name":"The Salon",
    "wof:placetype":"venue"
},
  "geometry": {"coordinates":[-2.134792,52.981182],"type":"Point"}
}