{
  "type": "Feature",
  "properties": {
    "iso:country":"GB",
    "sg:address":"Sterling House, Fairfax Street",
    "sg:city":"Bristol",
    "sg:classifiers":[
        {
            "category":"Organizations",
            "subcategory":"Non-profit Organization",
            "type":"Services"
        }
    ],
    "sg:phone":"+44 117 926 8115",
    "sg:postcode":"BS1 3HX",
    "sg:province":"City of Bristol",
    "sg:tags":[
        "organisation",
        "voluntary",
        "charity"
    ],
    "wof:name":"Shelter Housing Aid",
    "wof:placetype":"venue"
},
  "geometry": {"coordinates":[-2.589525,51.456257],"type":"Point"}
}