{
  "type": "Feature",
  "properties": {
    "addr:full":"178-180 Main St Carnforth Cumbria LA5 9PN",
    "addr:housenumber":"178-180",
    "addr:postcode":"la5 9pn",
    "addr:street":"Main St",
    "iso:country":"GB",
    "sg:address":"178-180 Main St",
    "sg:city":"Carnforth",
    "sg:classifiers":[
        {
            "category":"Food & Beverages",
            "subcategory":"Groceries & Convenience Stores",
            "type":"Retail Goods"
        }
    ],
    "sg:postcode":"LA5 9PN",
    "sg:province":"Cumbria",
    "wof:name":"Wellstead,A & M,",
    "wof:placetype":"venue"
},
  "geometry": {"coordinates":[-2.766513,54.146549],"type":"Point"}
}