{
  "type": "Feature",
  "properties": {
    "addr:full":"68 Murray Street Montrose Aberdeenshire DD10 8JY",
    "addr:housenumber":"68",
    "addr:postcode":"dd10 8jy",
    "addr:street":"Murray Street",
    "iso:country":"GB",
    "sg:address":"68 Murray Street",
    "sg:city":"Montrose",
    "sg:classifiers":[
        {
            "category":"Shopping",
            "subcategory":"Baby Store",
            "type":"Retail Goods"
        },
        {
            "category":"Shopping",
            "subcategory":"Gifts & Souvenirs",
            "type":"Retail Goods"
        },
        {
            "category":"Building & Trades",
            "subcategory":"Electrical",
            "type":"Services"
        }
    ],
    "sg:postcode":"DD10 8JY",
    "sg:province":"Aberdeenshire",
    "sg:tags":[
        "nursery",
        "giftware",
        "accessory",
        "lighting",
        "consultant"
    ],
    "wof:name":"Small World",
    "wof:placetype":"venue"
},
  "geometry": {"coordinates":[-2.4678709507,56.7147369385],"type":"Point"}
}