{
  "type": "Feature",
  "properties": {
    "iso:country":"GB",
    "sg:address":"17 Courtybella Terr",
    "sg:city":"Newport",
    "sg:classifiers":[
        {
            "category":"Utilities",
            "subcategory":"Fuel Oil & Lpg",
            "type":"Services"
        }
    ],
    "sg:phone":"+44 1633 262035",
    "sg:postcode":"NP9 2LA",
    "sg:province":"East Riding of Yorkshire",
    "sg:tags":[
        "coal",
        "smokeless"
    ],
    "wof:name":"Magnus Organ",
    "wof:placetype":"venue"
},
  "geometry": {"coordinates":[-2.989175,51.575603],"type":"Point"}
}