{
  "type": "Feature",
  "properties": {
    "iso:country":"GB",
    "sg:address":"Greaves Farm, Field Broughton",
    "sg:city":"Grange-over-sands",
    "sg:classifiers":[
        {
            "category":"Farming",
            "subcategory":"Crops",
            "type":"Manufacturing & Wholesale Goods"
        },
        {
            "category":"Farming",
            "subcategory":"Farm",
            "type":"Manufacturing & Wholesale Goods"
        }
    ],
    "sg:phone":"+44 15395 36429",
    "sg:postcode":"LA11 6HR",
    "sg:province":"Cumbria",
    "sg:tags":[
        "mixed",
        "arable"
    ],
    "wof:name":"J Stables & Sons",
    "wof:placetype":"venue"
},
  "geometry": {"coordinates":[-2.94147,54.228531],"type":"Point"}
}