{
  "type": "Feature",
  "properties": {
    "addr:full":"14 Glebe Rd Skelmersdale Lancashire WN8 9UD",
    "addr:housenumber":"14",
    "addr:postcode":"wn8 9ud",
    "addr:street":"Glebe Rd",
    "iso:country":"GB",
    "sg:address":"14 Glebe Rd",
    "sg:city":"Skelmersdale",
    "sg:classifiers":[
        {
            "category":"Manufacturing",
            "subcategory":"Wood Products",
            "type":"Manufacturing & Wholesale Goods"
        }
    ],
    "sg:phone":"+44 1695 722851",
    "sg:postcode":"WN8 9UD",
    "sg:province":"Lancashire",
    "sg:tags":[
        "packaging",
        "crate",
        "pallets"
    ],
    "wof:name":"Kaycee Group Of Companies",
    "wof:placetype":"venue"
},
  "geometry": {"coordinates":[-2.780808,53.545052],"type":"Point"}
}