{
  "type": "Feature",
  "properties": {
    "addr:full":"Hunters Moon, Hogspudding Lane, Newdigate Dorking Surrey RH5 5DS",
    "addr:postcode":"rh5 5ds",
    "addr:street":"Hogspudding Lane",
    "iso:country":"GB",
    "sg:address":"Hunters Moon, Hogspudding Lane, Newdigate",
    "sg:city":"Dorking",
    "sg:classifiers":[
        {
            "category":"Professional",
            "type":"Services"
        },
        {
            "category":"Government",
            "subcategory":"Post Office",
            "type":"Public Place"
        }
    ],
    "sg:phone":"+44 1306 631442",
    "sg:postcode":"RH5 5DS",
    "sg:province":"Surrey",
    "sg:tags":[
        "organisation",
        "writer",
        "soc",
        "research"
    ],
    "wof:name":"Anchor Consultancy",
    "wof:placetype":"venue"
},
  "geometry": {"coordinates":[-0.290551,51.167591],"type":"Point"}
}