{
  "type": "Feature",
  "properties": {
    "addr:full":"67 Golders Green Road London Greater London NW11 8EL",
    "addr:housenumber":"67",
    "addr:postcode":"nw11 8el",
    "addr:street":"Golders Green Road",
    "iso:country":"GB",
    "sg:address":"67 Golders Green Road",
    "sg:city":"London",
    "sg:classifiers":[
        {
            "category":"Shopping",
            "subcategory":"Clothing, Apparel, & Fashions",
            "type":"Retail Goods"
        }
    ],
    "sg:phone":"+44 20 8458 8247",
    "sg:postcode":"NW11 8EL",
    "sg:province":"Greater London",
    "sg:tags":[
        "shop"
    ],
    "wof:name":"Next",
    "wof:placetype":"venue"
},
  "geometry": {"coordinates":[-0.1988629997,51.5725517273],"type":"Point"}
}