{
  "type": "Feature",
  "properties": {
    "addr:full":"Buchan Station, Boddam Peterhead Aberdeenshire AB42 3AR",
    "addr:postcode":"ab42 3ar",
    "iso:country":"GB",
    "sg:address":"Buchan Station, Boddam",
    "sg:city":"Peterhead",
    "sg:classifiers":[
        {
            "category":"Organizations",
            "subcategory":"Non-profit Organization",
            "type":"Services"
        }
    ],
    "sg:phone":"+44 1779 472091",
    "sg:postcode":"AB42 3AR",
    "sg:province":"Aberdeenshire",
    "sg:tags":[
        "organisation",
        "voluntary",
        "charity"
    ],
    "wof:name":"Royal Air Force",
    "wof:placetype":"venue"
},
  "geometry": {"coordinates":[-1.7826039791,57.4727363586],"type":"Point"}
}