{
  "type": "Feature",
  "properties": {
    "iso:country":"GB",
    "sg:address":"26-28 Southampton Street",
    "sg:city":"Reading",
    "sg:classifiers":[
        {
            "category":"Real Estate",
            "subcategory":"Developer",
            "type":"Services"
        }
    ],
    "sg:phone":"+44 20 8958 5125",
    "sg:postcode":"RG1 2QL",
    "sg:province":"Berkshire",
    "sg:tags":[
        "property"
    ],
    "wof:name":"Fox Properties Ltd.",
    "wof:placetype":"venue"
},
  "geometry": {"coordinates":[-0.971378,51.451275],"type":"Point"}
}