{
  "type": "Feature",
  "properties": {
    "addr:full":"Service Resource Centre, 78 Boothferry Rd Goole East Riding of Yorkshire DN14 6AA",
    "addr:housenumber":"78",
    "addr:postcode":"dn14 6aa",
    "addr:street":"Boothferry Rd",
    "iso:country":"GB",
    "sg:address":"Service Resource Centre, 78 Boothferry Rd",
    "sg:city":"Goole",
    "sg:classifiers":[
        {
            "category":"Organizations",
            "subcategory":"Non-profit Organization",
            "type":"Services"
        }
    ],
    "sg:phone":"+44 1405 760792",
    "sg:postcode":"DN14 6AA",
    "sg:province":"East Riding of Yorkshire",
    "sg:tags":[
        "organisation",
        "voluntary",
        "charity"
    ],
    "wof:name":"British Red Cross",
    "wof:placetype":"venue"
},
  "geometry": {"coordinates":[-0.87572,53.70475],"type":"Point"}
}