{
  "type": "Feature",
  "properties": {
    "addr:full":"55 Vicar La Chesterfield Derbyshire S40 1PY",
    "addr:housenumber":"55",
    "addr:postcode":"s40 1py",
    "addr:street":"Vicar La Chesterfield",
    "iso:country":"GB",
    "sg:address":"55 Vicar La",
    "sg:city":"Chesterfield",
    "sg:classifiers":[
        {
            "category":"Professional",
            "subcategory":"Lawyer & Legal Services",
            "type":"Services"
        }
    ],
    "sg:phone":"+44 1246 232465",
    "sg:postcode":"S40 1PY",
    "sg:province":"Derbyshire",
    "sg:tags":[
        "advice",
        "counselling"
    ],
    "wof:name":"Chesterfield & District National Schizophrenia Fellowship",
    "wof:placetype":"venue"
},
  "geometry": {"coordinates":[-1.4261319637,53.2348709106],"type":"Point"}
}