{
  "type": "Feature",
  "properties": {
    "addr:full":"Meeks Building, Brethertons Row Wigan Lancashire WN1 1LL",
    "addr:postcode":"wn1 1ll",
    "addr:street":"Brethertons Row",
    "iso:country":"GB",
    "sg:address":"Meeks Building, Brethertons Row",
    "sg:city":"Wigan",
    "sg:classifiers":[
        {
            "category":"Health Services",
            "subcategory":"Clinic",
            "type":"Services"
        }
    ],
    "sg:phone":"+44 1942 829507",
    "sg:postcode":"WN1 1LL",
    "sg:province":"Lancashire",
    "sg:tags":[
        "misuse",
        "alcohol"
    ],
    "wof:name":"Wigan & Leigh Community Alcohol Team",
    "wof:placetype":"venue"
},
  "geometry": {"coordinates":[-2.633532,53.544155],"type":"Point"}
}