{
  "type": "Feature",
  "properties": {
    "addr:full":"16 Greenwich Centre Business Park, 53 Norman Road, Greenwich London Greater London SE10 9QF",
    "addr:housenumber":"16;53",
    "addr:postcode":"se10 9qf",
    "addr:street":"Greenwich Centre Business Park;Norman Road",
    "iso:country":"GB",
    "sg:address":"16 Greenwich Centre Business Park, 53 Norman Road, Greenwich",
    "sg:city":"London",
    "sg:classifiers":[
        {
            "category":"Shopping",
            "subcategory":"Clothing, Apparel, & Fashions",
            "type":"Retail Goods"
        }
    ],
    "sg:phone":"+44 20 8853 1103",
    "sg:postcode":"SE10 9QF",
    "sg:province":"Greater London",
    "sg:tags":[
        "t-shirt"
    ],
    "wof:name":"A B C Shirts Ltd.",
    "wof:placetype":"venue"
},
  "geometry": {"coordinates":[-0.017472,51.479317],"type":"Point"}
}