{
  "type": "Feature",
  "properties": {
    "addr:full":"Herbert Lodge Drybrook Gloucestershire GL17 9DG",
    "addr:postcode":"gl17 9dg",
    "addr:street":"Drybrook",
    "iso:country":"GB",
    "sg:address":"Herbert Lodge",
    "sg:city":"Drybrook",
    "sg:classifiers":[
        {
            "category":"Building & Trades",
            "subcategory":"Construction",
            "type":"Services"
        }
    ],
    "sg:phone":"+44 1594 542486",
    "sg:postcode":"GL17 9DG",
    "sg:province":"Gloucestershire",
    "sg:tags":[
        "builder"
    ],
    "wof:name":"John James (Builders) Ltd.",
    "wof:placetype":"venue"
},
  "geometry": {"coordinates":[-2.515754,51.855839],"type":"Point"}
}