{
  "type": "Feature",
  "properties": {
    "addr:full":"Units 1-2, Galt House, 31 Bank St Irvine North Ayrshire KA12 0LL",
    "addr:housenumber":"units 1-2;31",
    "addr:postcode":"ka12 0ll",
    "addr:street":"Galt;Bank St",
    "iso:country":"GB",
    "sg:address":"Units 1-2, Galt House, 31 Bank St",
    "sg:city":"Irvine",
    "sg:classifiers":[
        {
            "category":"Banks & Credit Unions",
            "subcategory":"Bank",
            "type":"Services"
        }
    ],
    "sg:phone":"+44 1294 275444",
    "sg:postcode":"KA12 0LL",
    "sg:province":"North Ayrshire",
    "sg:tags":[
        "broker",
        "mortgage"
    ],
    "wof:name":"The Mortgage Manager",
    "wof:placetype":"venue"
},
  "geometry": {"coordinates":[-4.6561670303,55.6187477112],"type":"Point"}
}