{
  "type": "Feature",
  "properties": {
    "iso:country":"GB",
    "sg:address":"28 Gold Street",
    "sg:city":"Tiverton",
    "sg:classifiers":[
        {
            "category":"Organizations",
            "subcategory":"Non-profit Organization",
            "type":"Services"
        }
    ],
    "sg:postcode":"EX16 6PY",
    "sg:province":"Devon",
    "sg:tags":[
        "organisation",
        "voluntary",
        "charity"
    ],
    "wof:name":"Tiverton Volunteer Centre",
    "wof:placetype":"venue"
},
  "geometry": {"coordinates":[-3.484912,50.903343],"type":"Point"}
}