{
  "type": "Feature",
  "properties": {
    "addr:full":"406 Manford Way Chigwell Essex IG7 4AS",
    "addr:housenumber":"406",
    "addr:postcode":"ig7 4as",
    "addr:street":"Manford Way",
    "iso:country":"GB",
    "sg:address":"406 Manford Way",
    "sg:city":"Chigwell",
    "sg:classifiers":[
        {
            "category":"Manufacturing",
            "subcategory":"Metals",
            "type":"Manufacturing & Wholesale Goods"
        }
    ],
    "sg:postcode":"IG7 4AS",
    "sg:province":"Essex",
    "sg:tags":[
        "work",
        "sheet"
    ],
    "wof:name":"Margerum,Anthony,",
    "wof:placetype":"venue"
},
  "geometry": {"coordinates":[0.1163109988,51.6145782471],"type":"Point"}
}