{
  "type": "Feature",
  "properties": {
    "addr:full":"9 Cambridge Road East Cowes Isle of Wight PO32 6AE",
    "addr:housenumber":"9",
    "addr:postcode":"po32 6ae",
    "addr:street":"Cambridge Road",
    "iso:country":"GB",
    "sg:address":"9 Cambridge Road",
    "sg:city":"East Cowes",
    "sg:classifiers":[
        {
            "category":"Building & Trades",
            "subcategory":"Construction",
            "type":"Services"
        }
    ],
    "sg:postcode":"PO32 6AE",
    "sg:province":"Isle of Wight",
    "sg:tags":[
        "builder"
    ],
    "wof:name":"K H Builders",
    "wof:placetype":"venue"
},
  "geometry": {"coordinates":[-1.2876080275,50.7625198364],"type":"Point"}
}