{
  "type": "Feature",
  "properties": {
    "addr:full":"291 Hale Lane Edgware Greater London HA8 7AX",
    "addr:housenumber":"291",
    "addr:postcode":"ha8 7ax",
    "addr:street":"Hale Lane",
    "iso:country":"GB",
    "sg:address":"291 Hale Lane",
    "sg:city":"Edgware",
    "sg:classifiers":[
        {
            "category":"Home & Garden",
            "subcategory":"Household Appliances",
            "type":"Retail Goods"
        },
        {
            "category":"Retail",
            "subcategory":"Repair Shop",
            "type":"Services"
        }
    ],
    "sg:phone":"+44 20 8958 3263",
    "sg:postcode":"HA8 7AX",
    "sg:province":"Greater London",
    "sg:tags":[
        "machine",
        "electrical",
        "washing"
    ],
    "wof:name":"M.A Wash-Vac Services",
    "wof:placetype":"venue"
},
  "geometry": {"coordinates":[-0.275179,51.616039],"type":"Point"}
}