{
  "type": "Feature",
  "properties": {
    "addr:full":"80 Glasgow Road Paisley Renfrewshire PA1 3PN",
    "addr:housenumber":"80",
    "addr:postcode":"pa1 3pn",
    "addr:street":"Glasgow Road",
    "iso:country":"GB",
    "sg:address":"80 Glasgow Road",
    "sg:city":"Paisley",
    "sg:classifiers":[
        {
            "category":"Restaurant",
            "type":"Food & Drink"
        }
    ],
    "sg:phone":"+44 141 887 2861",
    "sg:postcode":"PA1 3PN",
    "sg:province":"Renfrewshire",
    "sg:tags":[
        "indian"
    ],
    "wof:name":"Shezan Tandoori",
    "wof:placetype":"venue"
},
  "geometry": {"coordinates":[-4.405573,55.846588],"type":"Point"}
}