{
  "type": "Feature",
  "properties": {
    "iso:country":"GB",
    "sg:address":"Unit 2 11 Almar Road, Snettisham",
    "sg:city":"King's Lynn",
    "sg:classifiers":[
        {
            "category":"Personal",
            "subcategory":"Beauty Salon",
            "type":"Services"
        },
        {
            "category":"Personal",
            "subcategory":"Barber",
            "type":"Services"
        }
    ],
    "sg:phone":"+44 1485 543193",
    "sg:postcode":"PE31 7NY",
    "sg:province":"Norfolk",
    "sg:tags":[
        "unisex",
        "hairdresser"
    ],
    "wof:name":"Impressions Hair Salon",
    "wof:placetype":"venue"
},
  "geometry": {"coordinates":[0.50026,52.8797],"type":"Point"}
}