{
  "type": "Feature",
  "properties": {
    "iso:country":"GB",
    "sg:address":"26 The Lea",
    "sg:city":"Stoke-on-trent",
    "sg:classifiers":[
        {
            "category":"Cinema",
            "subcategory":"Movie Rental",
            "type":"Entertainment"
        }
    ],
    "sg:phone":"+44 1782 641636",
    "sg:postcode":"ST4 8DY",
    "sg:province":"Staffordshire",
    "sg:tags":[
        "video",
        "library"
    ],
    "wof:name":"Videopark",
    "wof:placetype":"venue"
},
  "geometry": {"coordinates":[-2.186656,52.968002],"type":"Point"}
}