{
  "type": "Feature",
  "properties": {
    "addr:full":"83b Tolpits Lane Watford Hertfordshire WD18 6NT",
    "addr:housenumber":"83b",
    "addr:postcode":"wd18 6nt",
    "addr:street":"Tolpits Lane",
    "iso:country":"GB",
    "sg:address":"83b Tolpits Lane",
    "sg:city":"Watford",
    "sg:classifiers":[
        {
            "category":"Health Services",
            "subcategory":"Doctor",
            "type":"Services"
        }
    ],
    "sg:phone":"+44 1923 243130",
    "sg:postcode":"WD18 6NT",
    "sg:province":"Hertfordshire",
    "sg:tags":[
        "practitioners"
    ],
    "wof:name":"Hollywell Surgery",
    "wof:placetype":"venue"
},
  "geometry": {"coordinates":[-0.416326,51.646156],"type":"Point"}
}