{
  "type": "Feature",
  "properties": {
    "iso:country":"GB",
    "sg:address":"87 High Street",
    "sg:city":"Burton-on-trent",
    "sg:classifiers":[
        {
            "category":"Shopping",
            "subcategory":"Comic Books",
            "type":"Retail Goods"
        }
    ],
    "sg:postcode":"DE14 1LJ",
    "sg:province":"Derbyshire",
    "sg:tags":[
        "jeweller"
    ],
    "wof:name":"Edward Peter Jewellery",
    "wof:placetype":"venue"
},
  "geometry": {"coordinates":[-1.629862,52.80254],"type":"Point"}
}