{
  "type": "Feature",
  "properties": {
    "addr:full":"Oaklands, 78 Church Road, Plymstock Plymouth Devon PL9 9AY",
    "addr:housenumber":"78",
    "addr:postcode":"pl9 9ay",
    "addr:street":"Church Road",
    "iso:country":"GB",
    "sg:address":"Oaklands, 78 Church Road, Plymstock",
    "sg:city":"Plymouth",
    "sg:classifiers":[
        {
            "category":"Social Services",
            "subcategory":"Retirement Home",
            "type":"Services"
        }
    ],
    "sg:phone":"+44 1752 481166",
    "sg:postcode":"PL9 9AY",
    "sg:province":"Devon",
    "sg:tags":[
        "residential",
        "care"
    ],
    "wof:name":"The Durnford Society",
    "wof:placetype":"venue"
},
  "geometry": {"coordinates":[-4.086291,50.355801],"type":"Point"}
}