{
  "type": "Feature",
  "properties": {
    "iso:country":"GB",
    "sg:address":"32 Monks Way",
    "sg:city":"Nottingham",
    "sg:classifiers":[
        {
            "category":"Shopping",
            "subcategory":"News",
            "type":"Retail Goods"
        }
    ],
    "sg:phone":"+44 115 981 2614",
    "sg:postcode":"NG11 7FH",
    "sg:province":"Nottinghamshire",
    "sg:tags":[
        "newsagent"
    ],
    "wof:name":"Monks Way Post Office",
    "wof:placetype":"venue"
},
  "geometry": {"coordinates":[-1.163559,52.914871],"type":"Point"}
}