{
  "type": "Feature",
  "properties": {
    "addr:full":"9 Gayfere Street, Westminster London Greater London SW1P 3HN",
    "addr:housenumber":"9",
    "addr:postcode":"sw1p 3hn",
    "addr:street":"Gayfere Street",
    "iso:country":"GB",
    "sg:address":"9 Gayfere Street, Westminster",
    "sg:city":"London",
    "sg:classifiers":[
        {
            "category":"Manufacturing",
            "subcategory":"Tools & Machinery",
            "type":"Manufacturing & Wholesale Goods"
        }
    ],
    "sg:phone":"+44 20 7222 4999",
    "sg:postcode":"SW1P 3HN",
    "sg:province":"Greater London",
    "sg:tags":[
        "society",
        "friendly"
    ],
    "wof:name":"Dentists Provident Society",
    "wof:placetype":"venue"
},
  "geometry": {"coordinates":[-0.127914995,51.4965553284],"type":"Point"}
}