{
  "type": "Feature",
  "properties": {
    "iso:country":"GB",
    "sg:address":"The Avenue",
    "sg:city":"London",
    "sg:classifiers":[
        {
            "category":"Community Center",
            "type":"Public Place"
        }
    ],
    "sg:postcode":"N10 2QL",
    "sg:province":"Greater London",
    "sg:tags":[
        "centre"
    ],
    "wof:name":"Cufos Community Centre",
    "wof:placetype":"venue"
},
  "geometry": {"coordinates":[-0.13586,51.597858],"type":"Point"}
}