{
  "type": "Feature",
  "properties": {
    "iso:country":"GB",
    "sg:address":"293 Salisbury Road, Totton",
    "sg:city":"Southampton",
    "sg:classifiers":[
        {
            "category":"Shopping",
            "subcategory":"Computers & Home Electronics",
            "type":"Retail Goods"
        }
    ],
    "sg:postcode":"SO40 3LZ",
    "sg:province":"Hampshire",
    "sg:tags":[
        "equipment",
        "radio"
    ],
    "wof:name":"Murphy Telecommunications",
    "wof:placetype":"venue"
},
  "geometry": {"coordinates":[-1.503509,50.930008],"type":"Point"}
}