{
  "type": "Feature",
  "properties": {
    "addr:full":"86 Bradley Road Luton Bedfordshire LU4 8SW",
    "addr:housenumber":"86",
    "addr:postcode":"lu4 8sw",
    "addr:street":"Bradley Road",
    "iso:country":"GB",
    "sg:address":"86 Bradley Road",
    "sg:city":"Luton",
    "sg:classifiers":[
        {
            "category":"Banks & Credit Unions",
            "subcategory":"Bureau De Change",
            "type":"Services"
        },
        {
            "category":"Food & Beverages",
            "subcategory":"Liquor & Beverages",
            "type":"Retail Goods"
        }
    ],
    "sg:phone":"+44 1582 571051",
    "sg:postcode":"LU4 8SW",
    "sg:province":"Bedfordshire",
    "sg:tags":[
        "beer",
        "wine",
        "spirit",
        "wines"
    ],
    "wof:name":"Bradley Stores",
    "wof:placetype":"venue"
},
  "geometry": {"coordinates":[-0.46553,51.888878],"type":"Point"}
}