{
  "type": "Feature",
  "properties": {
    "addr:full":"12 St. Andrews Rd, Headington Oxford Oxfordshire OX3 9DL",
    "addr:housenumber":"12",
    "addr:postcode":"ox3 9dl",
    "addr:street":"St. Andrews Rd",
    "iso:country":"GB",
    "sg:address":"12 St. Andrews Rd, Headington",
    "sg:city":"Oxford",
    "sg:classifiers":[
        {
            "category":"Bars & Pubs",
            "type":"Food & Drink"
        }
    ],
    "sg:phone":"+44 1865 761737",
    "sg:postcode":"OX3 9DL",
    "sg:province":"Oxfordshire",
    "sg:tags":[
        "pubs",
        "inn"
    ],
    "wof:name":"The White Hart",
    "wof:placetype":"venue"
},
  "geometry": {"coordinates":[-1.2121340036,51.7643165588],"type":"Point"}
}