{
  "type": "Feature",
  "properties": {
    "iso:country":"GB",
    "sg:address":"13 Peckham Park Rd",
    "sg:city":"Peckham",
    "sg:classifiers":[
        {
            "category":"Food & Beverages",
            "subcategory":"Meat & Fish",
            "type":"Retail Goods"
        }
    ],
    "sg:phone":"+44 20 7639 3718",
    "sg:postcode":"SE15 6TR",
    "sg:province":"Greater London",
    "sg:tags":[
        "butcher"
    ],
    "wof:name":"W Bunting",
    "wof:placetype":"venue"
},
  "geometry": {"coordinates":[-0.065421,51.482704],"type":"Point"}
}