{
  "type": "Feature",
  "properties": {
    "iso:country":"GB",
    "sg:address":"4a Ditchling Rd",
    "sg:city":"Brighton",
    "sg:classifiers":[
        {
            "category":"Professional",
            "subcategory":"Engineering",
            "type":"Services"
        }
    ],
    "sg:phone":"+44 1273 608150",
    "sg:postcode":"BN1 4SF",
    "sg:province":"East Sussex",
    "sg:tags":[
        "civil",
        "engineer"
    ],
    "wof:name":"McHugh Formwork Ltd",
    "wof:placetype":"venue"
},
  "geometry": {"coordinates":[-0.134129,50.831959],"type":"Point"}
}