{
  "type": "Feature",
  "properties": {
    "iso:country":"GB",
    "sg:address":"7 Ashcroft Road",
    "sg:city":"Cirencester",
    "sg:classifiers":[
        {
            "category":"Professional",
            "subcategory":"Employment Agencies",
            "type":"Services"
        }
    ],
    "sg:phone":"+44 1285 644466",
    "sg:postcode":"GL7 1RA",
    "sg:province":"Gloucestershire",
    "sg:tags":[
        "consultant"
    ],
    "wof:name":"Gemini Employment",
    "wof:placetype":"venue"
},
  "geometry": {"coordinates":[-1.967525959,51.7151412964],"type":"Point"}
}