{
  "type": "Feature",
  "properties": {
    "addr:full":"3 Halsey Drive Hemel Hempstead Hertfordshire HP1 3SE",
    "addr:housenumber":"3",
    "addr:postcode":"hp1 3se",
    "addr:street":"Halsey Drive",
    "iso:country":"GB",
    "sg:address":"3 Halsey Drive",
    "sg:city":"Hemel Hempstead",
    "sg:classifiers":[
        {
            "category":"Professional",
            "subcategory":"Lawyer & Legal Services",
            "type":"Services"
        },
        {
            "category":"Organizations",
            "subcategory":"Non-profit Organization",
            "type":"Services"
        }
    ],
    "sg:phone":"+44 1442 243402",
    "sg:postcode":"HP1 3SE",
    "sg:province":"Hertfordshire",
    "sg:tags":[
        "organisation",
        "mediation",
        "voluntary",
        "charity"
    ],
    "wof:name":"Mediation Dacorum",
    "wof:placetype":"venue"
},
  "geometry": {"coordinates":[-0.498037,51.764687],"type":"Point"}
}