{
  "type": "Feature",
  "properties": {
    "iso:country":"GB",
    "sg:address":"Stockport Road",
    "sg:city":"Hyde",
    "sg:classifiers":[
        {
            "category":"Bars & Pubs",
            "type":"Food & Drink"
        }
    ],
    "sg:phone":"+44 161 368 1590",
    "sg:postcode":"SK14 3QF",
    "sg:province":"Cheshire",
    "sg:tags":[
        "pubs",
        "inn"
    ],
    "wof:name":"The Chapman Arms",
    "wof:placetype":"venue"
},
  "geometry": {"coordinates":[-2.0320739746,53.4426193237],"type":"Point"}
}