{
  "type": "Feature",
  "properties": {
    "addr:full":"7 Strawberry Dale Harrogate North Yorkshire HG1 5EF",
    "addr:housenumber":"7",
    "addr:postcode":"hg1 5ef",
    "addr:street":"Strawberry Dale",
    "iso:country":"GB",
    "sg:address":"7 Strawberry Dale",
    "sg:city":"Harrogate",
    "sg:classifiers":[
        {
            "category":"Professional",
            "subcategory":"Art Services",
            "type":"Services"
        }
    ],
    "sg:postcode":"HG1 5EF",
    "sg:province":"North Yorkshire",
    "sg:tags":[
        "photographer"
    ],
    "wof:name":"Barbara Shepard",
    "wof:placetype":"venue"
},
  "geometry": {"coordinates":[-1.538763,53.9967],"type":"Point"}
}