{
  "type": "Feature",
  "properties": {
    "addr:full":"12 Chestnut Gro Wigan Lancashire WN4 8XN",
    "addr:housenumber":"12",
    "addr:postcode":"wn4 8xn",
    "addr:street":"Chestnut Gro",
    "iso:country":"GB",
    "sg:address":"12 Chestnut Gro",
    "sg:city":"Wigan",
    "sg:classifiers":[
        {
            "category":"Building & Trades",
            "subcategory":"Plumbing",
            "type":"Services"
        }
    ],
    "sg:phone":"+44 1942 725476",
    "sg:postcode":"WN4 8XN",
    "sg:province":"Lancashire",
    "sg:tags":[
        "heating"
    ],
    "wof:name":"Marshall",
    "wof:placetype":"venue"
},
  "geometry": {"coordinates":[-2.6202011108,53.4930763245],"type":"Point"}
}