{
  "type": "Feature",
  "properties": {
    "iso:country":"GB",
    "sg:address":"Unit 1, Derwent St",
    "sg:city":"Sheffield",
    "sg:classifiers":[
        {
            "category":"Shopping",
            "subcategory":"Pets & Pet Supplies",
            "type":"Retail Goods"
        }
    ],
    "sg:phone":"+44 114 272 2209",
    "sg:postcode":"S2 5BN",
    "sg:province":"South Yorkshire",
    "wof:name":"Direct Pet Supplies",
    "wof:placetype":"venue"
},
  "geometry": {"coordinates":[-1.448556,53.383995],"type":"Point"}
}