{
  "type": "Feature",
  "properties": {
    "iso:country":"GB",
    "sg:address":"Poplar Farm, West End, Nailsea",
    "sg:city":"Bristol",
    "sg:classifiers":[
        {
            "category":"Farming",
            "subcategory":"Livestock Farm",
            "type":"Manufacturing & Wholesale Goods"
        }
    ],
    "sg:phone":"+44 1275 854565",
    "sg:postcode":"BS48 4BY",
    "sg:province":"Somerset",
    "sg:tags":[
        "others"
    ],
    "wof:name":"B J Hobbs",
    "wof:placetype":"venue"
},
  "geometry": {"coordinates":[-2.78407,51.426868],"type":"Point"}
}