{
  "type": "Feature",
  "properties": {
    "iso:country":"GB",
    "sg:address":"P O Box 14 8 Nelson Rd",
    "sg:city":"Liverpool",
    "sg:classifiers":[
        {
            "category":"Organizations",
            "subcategory":"Non-profit Organization",
            "type":"Services"
        }
    ],
    "sg:phone":"+44 151 709 8252",
    "sg:postcode":"L69 7AA",
    "sg:province":"Merseyside",
    "sg:tags":[
        "organisation",
        "voluntary",
        "charity"
    ],
    "wof:name":"Wirral Community Trust",
    "wof:placetype":"venue"
},
  "geometry": {"coordinates":[-2.96429,53.403358],"type":"Point"}
}