{
  "type": "Feature",
  "properties": {
    "iso:country":"GB",
    "sg:address":"7 Twynyffald Road",
    "sg:city":"Blackwood",
    "sg:classifiers":[
        {
            "category":"Organizations",
            "subcategory":"Community Association",
            "type":"Services"
        },
        {
            "category":"Organizations",
            "subcategory":"Membership Organization",
            "type":"Services"
        }
    ],
    "sg:phone":"+44 1443 830246",
    "sg:postcode":"NP12 3HD",
    "sg:province":"Caerphilly",
    "sg:tags":[
        "club",
        "social"
    ],
    "wof:name":"Twynyffald Workmen's Social Club & Institute Ltd.",
    "wof:placetype":"venue"
},
  "geometry": {"coordinates":[-3.207908,51.67144],"type":"Point"}
}