{
  "type": "Feature",
  "properties": {
    "iso:country":"GB",
    "sg:address":"52 Prior Road",
    "sg:city":"Forfar",
    "sg:classifiers":[
        {
            "category":"Building & Trades",
            "subcategory":"Construction",
            "type":"Services"
        }
    ],
    "sg:postcode":"DD8 3DT",
    "sg:province":"Angus",
    "sg:tags":[
        "roofing",
        "contracting"
    ],
    "wof:name":"A C Bruce & Sons",
    "wof:placetype":"venue"
},
  "geometry": {"coordinates":[-2.876963,56.647411],"type":"Point"}
}