{
  "type": "Feature",
  "properties": {
    "addr:full":"6 Argyle Court, Argyle Street Inverness Highland IV2 3DR",
    "addr:housenumber":"6",
    "addr:postcode":"iv2 3dr",
    "addr:street":"Argyle Court Argyle Street",
    "iso:country":"GB",
    "sg:address":"6 Argyle Court, Argyle Street",
    "sg:city":"Inverness",
    "sg:classifiers":[
        {
            "category":"Organizations",
            "subcategory":"Community Association",
            "type":"Services"
        }
    ],
    "sg:phone":"+44 1463 232815",
    "sg:postcode":"IV2 3DR",
    "sg:province":"Highland",
    "sg:tags":[
        "co-operatives",
        "society",
        "housing",
        "trust"
    ],
    "sg:website":"http://www.hsha.org.uk",
    "wof:name":"Hanover Scotland Housing Association Ltd",
    "wof:placetype":"venue"
},
  "geometry": {"coordinates":[-4.2185988426,57.4748649597],"type":"Point"}
}