{
  "type": "Feature",
  "properties": {
    "addr:full":"Hartley Mill, Mill Lane, Hartley Wespall Hook Berkshire RG27 0BQ",
    "addr:postcode":"rg27 0bq",
    "addr:street":"Hartley;Mill Lane",
    "iso:country":"GB",
    "sg:address":"Hartley Mill, Mill Lane, Hartley Wespall",
    "sg:city":"Hook",
    "sg:classifiers":[
        {
            "category":"Professional",
            "subcategory":"Business Services",
            "type":"Services"
        }
    ],
    "sg:phone":"+44 114 230 6700",
    "sg:postcode":"RG27 0BQ",
    "sg:province":"Berkshire",
    "sg:tags":[
        "trade"
    ],
    "wof:name":"Amhsa",
    "wof:placetype":"venue"
},
  "geometry": {"coordinates":[-0.9995189905,51.318321228],"type":"Point"}
}