{
  "type": "Feature",
  "properties": {
    "iso:country":"GB",
    "sg:address":"27 The Drive, Harold Wood",
    "sg:city":"Romford",
    "sg:classifiers":[
        {
            "category":"Organizations",
            "subcategory":"Political Organization",
            "type":"Services"
        }
    ],
    "sg:phone":"+44 1708 348325",
    "sg:postcode":"RM3 0DU",
    "sg:province":"Essex",
    "sg:tags":[
        "party"
    ],
    "wof:name":"Hornchurch & Upminster Liberal Democrats",
    "wof:placetype":"venue"
},
  "geometry": {"coordinates":[0.229986,51.59433],"type":"Point"}
}