{
  "type": "Feature",
  "properties": {
    "addr:full":"16 St John Street Manchester Greater Manchester M3 4EA",
    "addr:housenumber":"16",
    "addr:postcode":"m3 4ea",
    "addr:street":"St John Street",
    "iso:country":"GB",
    "sg:address":"16 St John Street",
    "sg:city":"Manchester",
    "sg:classifiers":[
        {
            "category":"Health Services",
            "subcategory":"Doctor",
            "type":"Services"
        }
    ],
    "sg:phone":"+44 161 834 5151",
    "sg:postcode":"M3 4EA",
    "sg:province":"Greater Manchester",
    "sg:tags":[
        "surgeon"
    ],
    "wof:name":"Roger J Williams",
    "wof:placetype":"venue"
},
  "geometry": {"coordinates":[-2.251255,53.477871],"type":"Point"}
}