{
  "type": "Feature",
  "properties": {
    "addr:full":"Market Hall Hereford Herefordshire HR2 9DS",
    "addr:postcode":"hr2 9ds",
    "iso:country":"GB",
    "sg:address":"Market Hall",
    "sg:city":"Hereford",
    "sg:classifiers":[
        {
            "category":"Farming",
            "subcategory":"Fish & Marine Products",
            "type":"Manufacturing & Wholesale Goods"
        }
    ],
    "sg:phone":"+44 1432 274480",
    "sg:postcode":"HR2 9DS",
    "sg:province":"Herefordshire",
    "sg:tags":[
        "fishmonger"
    ],
    "wof:name":"D J Benjamin & Sons",
    "wof:placetype":"venue"
},
  "geometry": {"coordinates":[-2.825499,52.025909],"type":"Point"}
}