{
  "type": "Feature",
  "properties": {
    "addr:full":"Nithbank Dumfries Dumfries and Galloway DG1 2SA",
    "addr:postcode":"dg1 2sa",
    "addr:street":"Nithbank",
    "iso:country":"GB",
    "sg:address":"Nithbank",
    "sg:city":"Dumfries",
    "sg:classifiers":[
        {
            "category":"Health Services",
            "subcategory":"Hospital",
            "type":"Services"
        },
        {
            "category":"Sports & Exercise",
            "subcategory":"Playing Field",
            "type":"Entertainment"
        }
    ],
    "sg:phone":"+44 1387 267144",
    "sg:postcode":"DG1 2SA",
    "sg:province":"Dumfries and Galloway",
    "sg:tags":[
        "medical",
        "transportation",
        "ambulance"
    ],
    "wof:name":"Common Services Agency for the Scottish Health Service",
    "wof:placetype":"venue"
},
  "geometry": {"coordinates":[-3.616154,55.075233],"type":"Point"}
}