{
  "type": "Feature",
  "properties": {
    "addr:full":"104 Seymour Place London Greater London W1H 1NB",
    "addr:housenumber":"104",
    "addr:postcode":"w1h 1nb",
    "addr:street":"Seymour Place",
    "iso:country":"GB",
    "sg:address":"104 Seymour Place",
    "sg:city":"London",
    "sg:classifiers":[
        {
            "category":"Home & Garden",
            "subcategory":"Carpets & Floor Coverings",
            "type":"Retail Goods"
        }
    ],
    "sg:phone":"+44 20 7724 8333",
    "sg:postcode":"W1H 1NB",
    "sg:province":"Greater London",
    "sg:tags":[
        "carpets",
        "rug",
        "matting"
    ],
    "wof:name":"Beau Decor",
    "wof:placetype":"venue"
},
  "geometry": {"coordinates":[-0.162992,51.519539],"type":"Point"}
}