{
  "type": "Feature",
  "properties": {
    "iso:country":"GB",
    "sg:address":"5 Thonock Road",
    "sg:city":"Morecambe",
    "sg:classifiers":[
        {
            "category":"Professional",
            "subcategory":"Art Services",
            "type":"Services"
        },
        {
            "category":"Building & Trades",
            "subcategory":"Construction",
            "type":"Services"
        }
    ],
    "sg:phone":"+44 1524 415297",
    "sg:postcode":"LA4 4RG",
    "sg:province":"Lancashire",
    "sg:tags":[
        "decorator",
        "painter"
    ],
    "wof:name":"B Love & Son",
    "wof:placetype":"venue"
},
  "geometry": {"coordinates":[-2.847129,54.063084],"type":"Point"}
}