{
  "type": "Feature",
  "properties": {
    "addr:full":"Chesney Wold, Bleak Hall Milton Keynes Buckinghamshire MK6 1NE",
    "addr:postcode":"mk6 1ne",
    "iso:country":"GB",
    "sg:address":"Chesney Wold, Bleak Hall",
    "sg:city":"Milton Keynes",
    "sg:classifiers":[
        {
            "category":"Autos & Motor Vehicles",
            "subcategory":"Automobile Sales",
            "type":"Retail Goods"
        },
        {
            "category":"Retail",
            "subcategory":"Auto Rental",
            "type":"Services"
        }
    ],
    "sg:phone":"+44 1908 232040",
    "sg:postcode":"MK6 1NE",
    "sg:province":"Buckinghamshire",
    "sg:tags":[
        "car",
        "commercial"
    ],
    "wof:name":"Kenning Car & Van Rental",
    "wof:placetype":"venue"
},
  "geometry": {"coordinates":[-0.755519,52.023464],"type":"Point"}
}