{
  "type": "Feature",
  "properties": {
    "addr:full":"5 Fieldside Didcot Oxfordshire OX11 9HY",
    "addr:housenumber":"5",
    "addr:postcode":"ox11 9hy",
    "addr:street":"Fieldside Didcot",
    "iso:country":"GB",
    "sg:address":"5 Fieldside",
    "sg:city":"Didcot",
    "sg:classifiers":[
        {
            "category":"Home & Garden",
            "subcategory":"Building Materials",
            "type":"Retail Goods"
        }
    ],
    "sg:phone":"+44 1235 850768",
    "sg:postcode":"OX11 9HY",
    "sg:province":"Oxfordshire",
    "sg:tags":[
        "fencing"
    ],
    "wof:name":"Town & Country Fencing",
    "wof:placetype":"venue"
},
  "geometry": {"coordinates":[-1.259629,51.579659],"type":"Point"}
}