{
  "type": "Feature",
  "properties": {
    "iso:country":"GB",
    "sg:address":"59/61 Botanic Rd",
    "sg:city":"Southport",
    "sg:classifiers":[
        {
            "category":"Bars & Pubs",
            "type":"Food & Drink"
        }
    ],
    "sg:phone":"+44 1704 228192",
    "sg:postcode":"PR9 7NE",
    "sg:province":"Lancashire",
    "sg:tags":[
        "pubs",
        "inn"
    ],
    "wof:name":"Bold Arms Tetley Public House",
    "wof:placetype":"venue"
},
  "geometry": {"coordinates":[-2.9643030167,53.6590538025],"type":"Point"}
}