{
  "type": "Feature",
  "properties": {
    "addr:full":"Main Road, Canon's Town Hayle Cornwall TR27 6NA",
    "addr:postcode":"tr27 6na",
    "addr:street":"Main Road",
    "iso:country":"GB",
    "sg:address":"Main Road, Canon's Town",
    "sg:city":"Hayle",
    "sg:classifiers":[
        {
            "category":"Manufacturing",
            "subcategory":"Jewelry",
            "type":"Manufacturing & Wholesale Goods"
        }
    ],
    "sg:phone":"+44 1736 740414",
    "sg:postcode":"TR27 6NA",
    "sg:province":"Cornwall",
    "sg:tags":[
        "repair",
        "jewellery"
    ],
    "wof:name":"Cornish Dreams Jewellery Workshop",
    "wof:placetype":"venue"
},
  "geometry": {"coordinates":[-5.4573998451,50.1642799377],"type":"Point"}
}