{
  "type": "Feature",
  "properties": {
    "addr:full":"203 New Kings Road, Parsons Grn London Greater London SW6 4SR",
    "addr:housenumber":"203",
    "addr:postcode":"sw6 4sr",
    "addr:street":"New Kings Road;Grn",
    "iso:country":"GB",
    "sg:address":"203 New Kings Road, Parsons Grn",
    "sg:city":"London",
    "sg:classifiers":[
        {
            "category":"Shopping",
            "subcategory":"Clothing, Apparel, & Fashions",
            "type":"Retail Goods"
        }
    ],
    "sg:phone":"+44 20 7731 3308",
    "sg:postcode":"SW6 4SR",
    "sg:province":"Greater London",
    "sg:tags":[
        "shop"
    ],
    "wof:name":"The Salcombe Clothing Co",
    "wof:placetype":"venue"
},
  "geometry": {"coordinates":[-0.197642,51.473103],"type":"Point"}
}