{
  "type": "Feature",
  "properties": {
    "addr:full":"Landywood Grn, Cheslyn Hay Walsall Staffordshire WS6 7QX",
    "addr:postcode":"ws6 7qx",
    "addr:street":"Landywood Grn",
    "iso:country":"GB",
    "sg:address":"Landywood Grn, Cheslyn Hay",
    "sg:city":"Walsall",
    "sg:classifiers":[
        {
            "category":"Travel",
            "subcategory":"Travel Agent",
            "type":"Entertainment"
        },
        {
            "category":"Recreation",
            "subcategory":"Gun Range",
            "type":"Entertainment"
        }
    ],
    "sg:phone":"+44 1922 417977",
    "sg:postcode":"WS6 7QX",
    "sg:province":"Staffordshire",
    "sg:tags":[
        "operator",
        "tour"
    ],
    "wof:name":"Dave Parry Travel Ltd.",
    "wof:placetype":"venue"
},
  "geometry": {"coordinates":[-2.0252630711,52.6580924988],"type":"Point"}
}