{
  "type": "Feature",
  "properties": {
    "addr:full":"Clock Ho, Bittell Farm Rd Birmingham West Midlands B45 8BP",
    "addr:postcode":"b45 8bp",
    "addr:street":"Farm Rd",
    "iso:country":"GB",
    "sg:address":"Clock Ho, Bittell Farm Rd",
    "sg:city":"Birmingham",
    "sg:classifiers":[
        {
            "category":"Farming",
            "subcategory":"Livestock Farm",
            "type":"Manufacturing & Wholesale Goods"
        }
    ],
    "sg:phone":"+44 121 445 2775",
    "sg:postcode":"B45 8BP",
    "sg:province":"West Midlands",
    "sg:tags":[
        "others"
    ],
    "wof:name":"W J Kember",
    "wof:placetype":"venue"
},
  "geometry": {"coordinates":[-1.9737509489,52.3678245544],"type":"Point"}
}