{
  "type": "Feature",
  "properties": {
    "iso:country":"GB",
    "sg:address":"33 Haynes Park Court, Slewins Close",
    "sg:city":"Hornchurch",
    "sg:classifiers":[
        {
            "category":"Shopping",
            "type":"Retail Goods"
        }
    ],
    "sg:phone":"+44 1708 453000",
    "sg:postcode":"RM11 2DE",
    "sg:province":"Essex",
    "sg:tags":[
        "bag"
    ],
    "wof:name":"London Jute Association",
    "wof:placetype":"venue"
},
  "geometry": {"coordinates":[0.2203799933,51.5620994568],"type":"Point"}
}