{
  "type": "Feature",
  "properties": {
    "addr:full":"3 Kenwick Dr Manchester Greater Manchester M40 3RU",
    "addr:housenumber":"3",
    "addr:postcode":"m40 3ru",
    "addr:street":"Kenwick Dr",
    "iso:country":"GB",
    "sg:address":"3 Kenwick Dr",
    "sg:city":"Manchester",
    "sg:classifiers":[
        {
            "category":"Building & Trades",
            "subcategory":"Construction",
            "type":"Services"
        }
    ],
    "sg:postcode":"M40 3RU",
    "sg:province":"Greater Manchester",
    "sg:tags":[
        "builder"
    ],
    "wof:name":"Goulding Builders",
    "wof:placetype":"venue"
},
  "geometry": {"coordinates":[-2.1689488888,53.5170783997],"type":"Point"}
}