{
  "type": "Feature",
  "properties": {
    "addr:full":"Avon Street Bath Bath and North East Somerset BA1 1UN",
    "addr:postcode":"ba1 1un",
    "addr:street":"Avon Street",
    "iso:country":"GB",
    "sg:address":"Avon Street",
    "sg:city":"Bath",
    "sg:classifiers":[
        {
            "category":"Professional",
            "subcategory":"Printing & Photocopies",
            "type":"Services"
        }
    ],
    "sg:phone":"+44 1225 427116",
    "sg:postcode":"BA1 1UN",
    "sg:province":"Bath and North East Somerset",
    "sg:tags":[
        "printer"
    ],
    "wof:name":"Press to Print Ltd.",
    "wof:placetype":"venue"
},
  "geometry": {"coordinates":[-2.3633339405,51.3789291382],"type":"Point"}
}