{
  "type": "Feature",
  "properties": {
    "addr:full":"38 Anthill Close Waterlooville Hampshire PO7 6ND",
    "addr:housenumber":"38",
    "addr:postcode":"po7 6nd",
    "addr:street":"Anthill Close",
    "iso:country":"GB",
    "sg:address":"38 Anthill Close",
    "sg:city":"Waterlooville",
    "sg:classifiers":[
        {
            "category":"Professional",
            "subcategory":"Printing & Photocopies",
            "type":"Services"
        }
    ],
    "sg:phone":"+44 23 9259 5950",
    "sg:postcode":"PO7 6ND",
    "sg:province":"Hampshire",
    "sg:tags":[
        "printer"
    ],
    "wof:name":"B S E Ltd.",
    "wof:placetype":"venue"
},
  "geometry": {"coordinates":[-1.0855749846,50.9090042114],"type":"Point"}
}