{
  "type": "Feature",
  "properties": {
    "addr:full":"Unit 6 Hednesford Road Cannock Staffordshire WS12 5HL",
    "addr:housenumber":"unit 6",
    "addr:postcode":"ws12 5hl",
    "addr:street":"Hednesford Road",
    "iso:country":"GB",
    "sg:address":"Unit 6 Hednesford Road",
    "sg:city":"Cannock",
    "sg:classifiers":[
        {
            "category":"Retail",
            "subcategory":"Auto Repair",
            "type":"Services"
        }
    ],
    "sg:phone":"+44 1543 271453",
    "sg:postcode":"WS12 5HL",
    "sg:province":"Staffordshire",
    "sg:tags":[
        "modification",
        "garage"
    ],
    "wof:name":"G T B Services",
    "wof:placetype":"venue"
},
  "geometry": {"coordinates":[-1.988476038,52.6932983398],"type":"Point"}
}