{
  "type": "Feature",
  "properties": {
    "iso:country":"GB",
    "sg:address":"Hampstead Grn",
    "sg:city":"Rotherham",
    "sg:classifiers":[
        {
            "category":"Social Services",
            "subcategory":"Adult Care",
            "type":"Services"
        },
        {
            "category":"Government",
            "subcategory":"Office",
            "type":"Public Place"
        }
    ],
    "sg:phone":"+44 1709 555494",
    "sg:postcode":"S61 3QG",
    "sg:province":"South Yorkshire",
    "sg:tags":[
        "housing",
        "local",
        "sheltered"
    ],
    "wof:name":"Hampstead Green Sheltered Housing",
    "wof:placetype":"venue"
},
  "geometry": {"coordinates":[-1.395699,53.441498],"type":"Point"}
}