{
  "type": "Feature",
  "properties": {
    "addr:full":"73 Berkeley Avenue Greenford Greater London UB6 0NY",
    "addr:housenumber":"73",
    "addr:postcode":"ub6 0ny",
    "addr:street":"Berkeley Avenue",
    "iso:country":"GB",
    "sg:address":"73 Berkeley Avenue",
    "sg:city":"Greenford",
    "sg:classifiers":[
        {
            "category":"Home & Garden",
            "subcategory":"Home Furnishings",
            "type":"Retail Goods"
        }
    ],
    "sg:phone":"+44 20 8423 7392",
    "sg:postcode":"UB6 0NY",
    "sg:province":"Greater London",
    "sg:tags":[
        "blind",
        "curtain",
        "fitting"
    ],
    "wof:name":"Berkeley Drapes & Blinds",
    "wof:placetype":"venue"
},
  "geometry": {"coordinates":[-0.3363310099,51.5482978821],"type":"Point"}
}