{
  "type": "Feature",
  "properties": {
    "addr:full":"205 Gibraltar Street Sheffield South Yorkshire S3 8UA",
    "addr:housenumber":"205",
    "addr:postcode":"s3 8ua",
    "addr:street":"Gibraltar Street",
    "iso:country":"GB",
    "sg:address":"205 Gibraltar Street",
    "sg:city":"Sheffield",
    "sg:classifiers":[
        {
            "category":"Community Center",
            "type":"Public Place"
        }
    ],
    "sg:postcode":"S3 8UA",
    "sg:province":"South Yorkshire",
    "sg:tags":[
        "centre"
    ],
    "wof:name":"Somali Community Association",
    "wof:placetype":"venue"
},
  "geometry": {"coordinates":[-1.4721970558,53.3869895935],"type":"Point"}
}