{
  "type": "Feature",
  "properties": {
    "iso:country":"GB",
    "sg:address":"Blackmore House, Greendale",
    "sg:city":"Ilminster",
    "sg:classifiers":[
        {
            "category":"Building & Trades",
            "subcategory":"Construction",
            "type":"Services"
        }
    ],
    "sg:phone":"+44 1460 53952",
    "sg:postcode":"TA19 0EB",
    "sg:province":"Somerset",
    "sg:tags":[
        "joiner",
        "carpenter"
    ],
    "wof:name":"Trott Graham Carpentry & Building Services",
    "wof:placetype":"venue"
},
  "geometry": {"coordinates":[-2.917833,50.925945],"type":"Point"}
}