{
  "type": "Feature",
  "properties": {
    "addr:full":"Whitehill Depot, 1-6 Whitehill Rd Glenrothes Fife KY6 2RN",
    "addr:housenumber":"1-6",
    "addr:postcode":"ky6 2rn",
    "addr:street":"Whitehill Rd",
    "iso:country":"GB",
    "sg:address":"Whitehill Depot, 1-6 Whitehill Rd",
    "sg:city":"Glenrothes",
    "sg:classifiers":[
        {
            "category":"Government",
            "subcategory":"Office",
            "type":"Public Place"
        }
    ],
    "sg:phone":"+44 1592 772345",
    "sg:postcode":"KY6 2RN",
    "sg:province":"Fife",
    "sg:tags":[
        "local"
    ],
    "wof:name":"Fife Council",
    "wof:placetype":"venue"
},
  "geometry": {"coordinates":[-3.20209,56.183369],"type":"Point"}
}