{
  "type": "Feature",
  "properties": {
    "addr:full":"Holiday Homes, Gradwells Farm, Moor Road Preston Lancashire PR26 9HP",
    "addr:postcode":"pr26 9hp",
    "addr:street":"Moor Road",
    "iso:country":"GB",
    "sg:address":"Holiday Homes, Gradwells Farm, Moor Road",
    "sg:city":"Preston",
    "sg:classifiers":[
        {
            "category":"Organizations",
            "subcategory":"Non-profit Organization",
            "type":"Services"
        }
    ],
    "sg:phone":"+44 1772 600915",
    "sg:postcode":"PR26 9HP",
    "sg:province":"Lancashire",
    "sg:tags":[
        "organisation",
        "voluntary",
        "charity"
    ],
    "wof:name":"The Sons of Divine Providence",
    "wof:placetype":"venue"
},
  "geometry": {"coordinates":[-2.7572200298,53.6666107178],"type":"Point"}
}