{
  "type": "Feature",
  "properties": {
    "iso:country":"GB",
    "sg:address":"36 Matlock Crescent",
    "sg:city":"Sutton",
    "sg:classifiers":[
        {
            "category":"Professional",
            "subcategory":"Engineering",
            "type":"Services"
        },
        {
            "category":"Building & Trades",
            "subcategory":"Electrical",
            "type":"Services"
        }
    ],
    "sg:phone":"+44 20 8641 6158",
    "sg:postcode":"SM3 9SN",
    "sg:province":"Surrey",
    "sg:tags":[
        "engineer",
        "electrician",
        "contractor"
    ],
    "wof:name":"J B Sparkes",
    "wof:placetype":"venue"
},
  "geometry": {"coordinates":[-0.2147700042,51.3672409058],"type":"Point"}
}