{
  "type": "Feature",
  "properties": {
    "addr:full":"Site Data Ho, The Courtyard, Roman Way Birmingham Warwickshire B46 1HQ",
    "addr:postcode":"b46 1hq",
    "addr:street":"The Courtyard Roman Way",
    "iso:country":"GB",
    "sg:address":"Site Data Ho, The Courtyard, Roman Way",
    "sg:city":"Birmingham",
    "sg:classifiers":[
        {
            "category":"Real Estate",
            "subcategory":"Architect",
            "type":"Services"
        }
    ],
    "sg:phone":"+44 1675 462636",
    "sg:postcode":"B46 1HQ",
    "sg:province":"Warwickshire",
    "wof:name":"Fellows & Burt Associates Ltd",
    "wof:placetype":"venue"
},
  "geometry": {"coordinates":[-1.71449,52.51366],"type":"Point"}
}