{
  "type": "Feature",
  "properties": {
    "addr:full":"44 Torrington Crescent, Worle Weston-super-mare Somerset BS22 6NP",
    "addr:housenumber":"44",
    "addr:postcode":"bs22 6np",
    "addr:street":"Torrington Crescent",
    "iso:country":"GB",
    "sg:address":"44 Torrington Crescent, Worle",
    "sg:city":"Weston-super-mare",
    "sg:classifiers":[
        {
            "category":"Professional",
            "subcategory":"Engineering",
            "type":"Services"
        }
    ],
    "sg:postcode":"BS22 6NP",
    "sg:province":"Somerset",
    "sg:tags":[
        "contractor",
        "electrical",
        "engineer"
    ],
    "wof:name":"A V Potter-Burnell",
    "wof:placetype":"venue"
},
  "geometry": {"coordinates":[-2.9170939922,51.3625907898],"type":"Point"}
}