{
  "type": "Feature",
  "properties": {
    "iso:country":"GB",
    "sg:address":"12 Elms West",
    "sg:city":"Sunderland",
    "sg:classifiers":[
        {
            "category":"Professional",
            "subcategory":"Accounting & Tax Preparation",
            "type":"Services"
        }
    ],
    "sg:postcode":"SR2 7BY",
    "sg:province":"Tyne and Wear",
    "sg:tags":[
        "accountant"
    ],
    "wof:name":"Network Accounting Services",
    "wof:placetype":"venue"
},
  "geometry": {"coordinates":[-1.3837139606,54.897441864],"type":"Point"}
}