{
  "type": "Feature",
  "properties": {
    "addr:full":"Unit 26, Ddole Road Industrial Estate Llandrindod Wells Powys LD1 6DF",
    "addr:housenumber":"unit 26",
    "addr:postcode":"ld1 6df",
    "addr:street":"Ddole Road Industrial Estate",
    "iso:country":"GB",
    "sg:address":"Unit 26, Ddole Road Industrial Estate",
    "sg:city":"Llandrindod Wells",
    "sg:classifiers":[
        {
            "category":"Manufacturing",
            "subcategory":"Aerospace",
            "type":"Manufacturing & Wholesale Goods"
        },
        {
            "category":"Airport",
            "subcategory":"General Aviation",
            "type":"Transportation"
        }
    ],
    "sg:phone":"+44 1597 824420",
    "sg:postcode":"LD1 6DF",
    "sg:province":"Powys",
    "sg:tags":[
        "aircraft",
        "component",
        "supply"
    ],
    "wof:name":"Newton Propeller",
    "wof:placetype":"venue"
},
  "geometry": {"coordinates":[-3.3658390045,52.2908210754],"type":"Point"}
}