{
  "type": "Feature",
  "properties": {
    "iso:country":"GB",
    "sg:address":"36 Westby Road, Boscombe",
    "sg:city":"Bournemouth",
    "sg:classifiers":[
        {
            "category":"Travel",
            "subcategory":"Hotels & Motels",
            "type":"Entertainment"
        }
    ],
    "sg:postcode":"BH5 1HD",
    "sg:province":"Dorset",
    "wof:name":"Westby Hotel",
    "wof:placetype":"venue"
},
  "geometry": {"coordinates":[-1.837444,50.725578],"type":"Point"}
}