{
  "type": "Feature",
  "properties": {
    "iso:country":"GB",
    "sg:address":"87 Charltons",
    "sg:city":"Saltburn-by-the-sea",
    "sg:classifiers":[
        {
            "category":"Building & Trades",
            "subcategory":"Construction",
            "type":"Services"
        }
    ],
    "sg:phone":"+44 1287 610097",
    "sg:postcode":"TS12 3DA",
    "sg:province":"North Yorkshire",
    "sg:tags":[
        "dry",
        "lining",
        "plasterers",
        "screeders"
    ],
    "wof:name":"Altee Plasterers",
    "wof:placetype":"venue"
},
  "geometry": {"coordinates":[-0.9741889834,54.5823707581],"type":"Point"}
}