{
  "type": "Feature",
  "properties": {
    "iso:country":"GB",
    "sg:address":"21 The Street",
    "sg:city":"Ashtead",
    "sg:classifiers":[
        {
            "category":"Fast Food",
            "type":"Food & Drink"
        }
    ],
    "sg:phone":"+44 1372 276606",
    "sg:postcode":"KT21 1AA",
    "sg:province":"Surrey",
    "sg:tags":[
        "away",
        "take"
    ],
    "wof:name":"Burgerland the Big One",
    "wof:placetype":"venue"
},
  "geometry": {"coordinates":[-0.299539,51.309517],"type":"Point"}
}