{
  "type": "Feature",
  "properties": {
    "iso:country":"GB",
    "sg:address":"42 Eskdale Gardens",
    "sg:city":"Gateshead",
    "sg:classifiers":[
        {
            "category":"Social Services",
            "subcategory":"Child Care",
            "type":"Services"
        },
        {
            "category":"Health Services",
            "subcategory":"Nursing And Care Facility",
            "type":"Services"
        }
    ],
    "sg:phone":"+44 191 487 6620",
    "sg:postcode":"NE9 6NS",
    "sg:province":"Tyne and Wear",
    "sg:tags":[
        "home",
        "residential",
        "children's"
    ],
    "wof:name":"LYNDHURST CHILDREN'S HOME",
    "wof:placetype":"venue"
},
  "geometry": {"coordinates":[-1.59085,54.92926],"type":"Point"}
}