{
  "type": "Feature",
  "properties": {
    "addr:full":"18 Goldhawk Road London Greater London W12 8DH",
    "addr:housenumber":"18",
    "addr:postcode":"w12 8dh",
    "addr:street":"Goldhawk Road",
    "iso:country":"GB",
    "sg:address":"18 Goldhawk Road",
    "sg:city":"London",
    "sg:classifiers":[
        {
            "category":"Restaurant",
            "type":"Food & Drink"
        }
    ],
    "sg:phone":"+44 20 8743 1541",
    "sg:postcode":"W12 8DH",
    "sg:province":"Greater London",
    "sg:tags":[
        "mediterranean",
        "-"
    ],
    "wof:name":"Pasha",
    "wof:placetype":"venue"
},
  "geometry": {"coordinates":[-0.224603,51.502941],"type":"Point"}
}