{
  "type": "Feature",
  "properties": {
    "iso:country":"GB",
    "sg:address":"304 Birmingham Road",
    "sg:city":"Redditch",
    "sg:classifiers":[
        {
            "category":"Education",
            "subcategory":"Special Training",
            "type":"Public Place"
        }
    ],
    "sg:postcode":"B97 6RJ",
    "sg:province":"Warwickshire",
    "sg:tags":[
        "product",
        "centre"
    ],
    "wof:name":"Quantum Training",
    "wof:placetype":"venue"
},
  "geometry": {"coordinates":[-1.940718,52.324329],"type":"Point"}
}