{
  "type": "Feature",
  "properties": {
    "iso:country":"GB",
    "sg:address":"105 St Peters St",
    "sg:city":"St Albans",
    "sg:classifiers":[
        {
            "category":"Professional",
            "subcategory":"Management & Consulting",
            "type":"Services"
        }
    ],
    "sg:postcode":"AL1 3EJ",
    "sg:province":"Hertfordshire",
    "sg:tags":[
        "consultant",
        "business"
    ],
    "wof:name":"Dynargie (U K) Ltd",
    "wof:placetype":"venue"
},
  "geometry": {"coordinates":[-0.335842,51.755592],"type":"Point"}
}