{
  "type": "Feature",
  "properties": {
    "iso:country":"GB",
    "sg:address":"Wardleys View, Staynall La",
    "sg:city":"Poulton Le Fylde",
    "sg:classifiers":[
        {
            "category":"Food & Beverages",
            "subcategory":"Groceries & Convenience Stores",
            "type":"Retail Goods"
        }
    ],
    "sg:phone":"+44 1253 700318",
    "sg:postcode":"FY6 9DT",
    "sg:province":"Lancashire",
    "sg:tags":[
        "merchant",
        "potato"
    ],
    "wof:name":"R Singleton & Sons",
    "wof:placetype":"venue"
},
  "geometry": {"coordinates":[-2.994658947,53.8480796814],"type":"Point"}
}