{
  "type": "Feature",
  "properties": {
    "addr:full":"Cromwell House, Staffa Rd Leyton Greater London E10 7PY",
    "addr:postcode":"e10 7py",
    "addr:street":"Staffa Rd",
    "iso:country":"GB",
    "sg:address":"Cromwell House, Staffa Rd",
    "sg:city":"Leyton",
    "sg:classifiers":[
        {
            "category":"Professional",
            "subcategory":"Printing & Photocopies",
            "type":"Services"
        }
    ],
    "sg:phone":"+44 20 8556 3556",
    "sg:postcode":"E10 7PY",
    "sg:province":"Greater London",
    "sg:tags":[
        "printer"
    ],
    "wof:name":"Power Ltd",
    "wof:placetype":"venue"
},
  "geometry": {"coordinates":[-0.039404,51.568909],"type":"Point"}
}