{
  "type": "Feature",
  "properties": {
    "iso:country":"GB",
    "sg:address":"48 Brookley Road",
    "sg:city":"Brockenhurst",
    "sg:classifiers":[
        {
            "category":"Shopping",
            "subcategory":"Pharmacy",
            "type":"Retail Goods"
        }
    ],
    "sg:postcode":"SO42 7RA",
    "sg:province":"Hampshire",
    "sg:tags":[
        "medicine",
        "therapy"
    ],
    "wof:name":"Maria J Hayter",
    "wof:placetype":"venue"
},
  "geometry": {"coordinates":[-1.576437,50.819344],"type":"Point"}
}