{
  "type": "Feature",
  "properties": {
    "addr:full":"45 Springfield Road Blackpool Lancashire FY1 1PZ",
    "addr:housenumber":"45",
    "addr:postcode":"fy1 1pz",
    "addr:street":"Springfield Road",
    "iso:country":"GB",
    "sg:address":"45 Springfield Road",
    "sg:city":"Blackpool",
    "sg:classifiers":[
        {
            "category":"Professional",
            "subcategory":"Lawyer & Legal Services",
            "type":"Services"
        }
    ],
    "sg:phone":"+44 1253 293151",
    "sg:postcode":"FY1 1PZ",
    "sg:province":"Lancashire",
    "sg:tags":[
        "solicitor"
    ],
    "wof:name":"Atkinson Cave & Stuart",
    "wof:placetype":"venue"
},
  "geometry": {"coordinates":[-3.0527529716,53.8211517334],"type":"Point"}
}