{
  "type": "Feature",
  "properties": {
    "addr:full":"Sampson House Business Park, Berwick Lane, Hallen Bristol City of Bristol BS10 7RS",
    "addr:postcode":"bs10 7rs",
    "addr:street":"Business Park Berwick Lane",
    "iso:country":"GB",
    "sg:address":"Sampson House Business Park, Berwick Lane, Hallen",
    "sg:city":"Bristol",
    "sg:classifiers":[
        {
            "category":"Professional",
            "subcategory":"Business Services",
            "type":"Services"
        }
    ],
    "sg:phone":"+44 117 959 0746",
    "sg:postcode":"BS10 7RS",
    "sg:province":"City of Bristol",
    "sg:tags":[
        "import",
        "export",
        "agent"
    ],
    "wof:name":"Global Imports",
    "wof:placetype":"venue"
},
  "geometry": {"coordinates":[-2.6490790844,51.5171203613],"type":"Point"}
}