{
  "type": "Feature",
  "properties": {
    "addr:full":"388, 392 High Rd, Leyton Leyton Greater London E10 6QE",
    "addr:housenumber":"392",
    "addr:postcode":"e10 6qe",
    "addr:street":"High Rd",
    "iso:country":"GB",
    "sg:address":"388, 392 High Rd, Leyton",
    "sg:city":"Leyton",
    "sg:classifiers":[
        {
            "category":"Professional",
            "subcategory":"Lawyer & Legal Services",
            "type":"Services"
        }
    ],
    "sg:phone":"+44 20 8558 0551",
    "sg:postcode":"E10 6QE",
    "sg:province":"Greater London",
    "sg:tags":[
        "advice",
        "counselling"
    ],
    "wof:name":"East London Out Project",
    "wof:placetype":"venue"
},
  "geometry": {"coordinates":[-0.010604,51.563152],"type":"Point"}
}