{
  "type": "Feature",
  "properties": {
    "addr:full":"Balmoral Lodge Dental Practice Ferndown Dorset BH22 9RT",
    "addr:postcode":"bh22 9rt",
    "iso:country":"GB",
    "sg:address":"Balmoral Lodge Dental Practice",
    "sg:city":"Ferndown",
    "sg:classifiers":[
        {
            "category":"Health Services",
            "subcategory":"Dentist",
            "type":"Services"
        }
    ],
    "sg:phone":"+44 1202 871488",
    "sg:postcode":"BH22 9RT",
    "sg:province":"Dorset",
    "wof:name":"Balmoral Lodge Dental Practice",
    "wof:placetype":"venue"
},
  "geometry": {"coordinates":[-1.8893890381,50.8018302917],"type":"Point"}
}