{
  "type": "Feature",
  "properties": {
    "iso:country":"GB",
    "sg:address":"Unit 5 Sandfold Lane, Levenshulme",
    "sg:city":"Manchester",
    "sg:classifiers":[
        {
            "category":"Building & Trades",
            "subcategory":"Construction",
            "type":"Services"
        }
    ],
    "sg:postcode":"M19 3BJ",
    "sg:province":"Greater Manchester",
    "sg:tags":[
        "platform",
        "work",
        "scaffolding"
    ],
    "wof:name":"Sky Scaffolding Ltd.",
    "wof:placetype":"venue"
},
  "geometry": {"coordinates":[-2.176859,53.448105],"type":"Point"}
}