{
  "type": "Feature",
  "properties": {
    "addr:full":"Social Functions & Weddings, London Rd Clacton On Sea Essex CO16 9RN",
    "addr:postcode":"co16 9rn",
    "addr:street":"London Rd",
    "iso:country":"GB",
    "sg:address":"Social Functions & Weddings, London Rd",
    "sg:city":"Clacton On Sea",
    "sg:classifiers":[
        {
            "category":"Organizations",
            "subcategory":"Membership Organization",
            "type":"Services"
        }
    ],
    "sg:phone":"+44 1255 860880",
    "sg:postcode":"CO16 9RN",
    "sg:province":"Essex",
    "sg:tags":[
        "club"
    ],
    "wof:name":"Firs Caravan Park Club",
    "wof:placetype":"venue"
},
  "geometry": {"coordinates":[1.1419099569,51.8220901489],"type":"Point"}
}