{
  "type": "Feature",
  "properties": {
    "addr:full":"School Road, Longridge Bathgate North Lanarkshire EH47 8AG",
    "addr:postcode":"eh47 8ag",
    "addr:street":"School Road;Bathgate",
    "iso:country":"GB",
    "sg:address":"School Road, Longridge",
    "sg:city":"Bathgate",
    "sg:classifiers":[
        {
            "category":"Education",
            "subcategory":"School",
            "type":"Public Place"
        }
    ],
    "sg:phone":"+44 1501 770208",
    "sg:postcode":"EH47 8AG",
    "sg:province":"North Lanarkshire",
    "sg:tags":[
        "local",
        "authority"
    ],
    "wof:name":"Longridge Primary School",
    "wof:placetype":"venue"
},
  "geometry": {"coordinates":[-3.6778140068,55.8427696228],"type":"Point"}
}