{
  "type": "Feature",
  "properties": {
    "iso:country":"GB",
    "sg:address":"15 Moulins Road",
    "sg:city":"London",
    "sg:classifiers":[
        {
            "category":"Banks & Credit Unions",
            "subcategory":"Financial Services",
            "type":"Services"
        }
    ],
    "sg:postcode":"E9 7EL",
    "sg:province":"Greater London",
    "sg:tags":[
        "consultant"
    ],
    "wof:name":"Wagga Investments Ltd",
    "wof:placetype":"venue"
},
  "geometry": {"coordinates":[-0.047203,51.539612],"type":"Point"}
}