{
  "type": "Feature",
  "properties": {
    "addr:full":"Merton Bank Rd St Helens Cheshire WA9 1HY",
    "addr:postcode":"wa9 1hy",
    "addr:street":"Bank Rd",
    "iso:country":"GB",
    "sg:address":"Merton Bank Rd",
    "sg:city":"St Helens",
    "sg:classifiers":[
        {
            "category":"Utilities",
            "subcategory":"Natural Gas",
            "type":"Services"
        }
    ],
    "sg:phone":"+44 1744 27879",
    "sg:postcode":"WA9 1HY",
    "sg:province":"Cheshire",
    "sg:tags":[
        "supplier"
    ],
    "wof:name":"Suregrow Products",
    "wof:placetype":"venue"
},
  "geometry": {"coordinates":[-2.7190690041,53.4577102661],"type":"Point"}
}