{
  "type": "Feature",
  "properties": {
    "addr:full":"Unit 16 First Avenue, Drum Industrial Estate, Birtley Chester-le-street Durham DH2 1AG",
    "addr:housenumber":"unit 16",
    "addr:postcode":"dh2 1ag",
    "addr:street":"First Avenue;Industrial;Chester-Le-Street",
    "iso:country":"GB",
    "sg:address":"Unit 16 First Avenue, Drum Industrial Estate, Birtley",
    "sg:city":"Chester-le-street",
    "sg:classifiers":[
        {
            "category":"Building & Trades",
            "subcategory":"Construction",
            "type":"Services"
        }
    ],
    "sg:phone":"+44 191 410 7917",
    "sg:postcode":"DH2 1AG",
    "sg:province":"Durham",
    "sg:tags":[
        "platform",
        "work",
        "scaffolding"
    ],
    "wof:name":"Skyline Scaffolding Ltd.",
    "wof:placetype":"venue"
},
  "geometry": {"coordinates":[-1.5861589909,54.8764343262],"type":"Point"}
}