{
  "type": "Feature",
  "properties": {
    "addr:full":"Wilshamstead Post Office, 33 Cotton End Road, Wilstead Bedford Bedfordshire MK45 3BX",
    "addr:housenumber":"33",
    "addr:postcode":"mk45 3bx",
    "addr:street":"Cotton End Road",
    "iso:country":"GB",
    "sg:address":"Wilshamstead Post Office, 33 Cotton End Road, Wilstead",
    "sg:city":"Bedford",
    "sg:classifiers":[
        {
            "category":"Real Estate",
            "subcategory":"Real Estate Agent",
            "type":"Services"
        }
    ],
    "sg:postcode":"MK45 3BX",
    "sg:province":"Bedfordshire",
    "wof:name":"Grantlease Ltd",
    "wof:placetype":"venue"
},
  "geometry": {"coordinates":[-0.4177390039,52.0961914062],"type":"Point"}
}