{
  "type": "Feature",
  "properties": {
    "addr:full":"338 Limpsfield Rd South Croydon Surrey CR2 9BX",
    "addr:housenumber":"338",
    "addr:postcode":"cr2 9bx",
    "addr:street":"Limpsfield Rd",
    "iso:country":"GB",
    "sg:address":"338 Limpsfield Rd",
    "sg:city":"South Croydon",
    "sg:classifiers":[
        {
            "category":"Cinema",
            "subcategory":"Movie Rental",
            "type":"Entertainment"
        }
    ],
    "sg:phone":"+44 20 8657 3809",
    "sg:postcode":"CR2 9BX",
    "sg:province":"Surrey",
    "sg:tags":[
        "video",
        "library"
    ],
    "wof:name":"Videoscene",
    "wof:placetype":"venue"
},
  "geometry": {"coordinates":[-0.065181,51.319695],"type":"Point"}
}