{
  "type": "Feature",
  "properties": {
    "iso:country":"GB",
    "sg:address":"Kings House, 1 Stamford Street",
    "sg:city":"Altrincham",
    "sg:classifiers":[
        {
            "category":"Insurance",
            "subcategory":"Insurance Agent",
            "type":"Services"
        }
    ],
    "sg:postcode":"WA14 1EX",
    "sg:province":"Cheshire",
    "sg:tags":[
        "broker"
    ],
    "wof:name":"Seacombe Insurance Consultants",
    "wof:placetype":"venue"
},
  "geometry": {"coordinates":[-2.349452,53.388779],"type":"Point"}
}