{
  "type": "Feature",
  "properties": {
    "addr:full":"79 Trezaise Rd St Austell Cornwall PL26 8HG",
    "addr:housenumber":"79",
    "addr:postcode":"pl26 8hg",
    "addr:street":"Trezaise Rd",
    "iso:country":"GB",
    "sg:address":"79 Trezaise Rd",
    "sg:city":"St Austell",
    "sg:classifiers":[
        {
            "category":"Shopping",
            "subcategory":"Department Store",
            "type":"Retail Goods"
        }
    ],
    "sg:phone":"+44 1726 890313",
    "sg:postcode":"PL26 8HG",
    "sg:province":"Cornwall",
    "wof:name":"D R Thomas",
    "wof:placetype":"venue"
},
  "geometry": {"coordinates":[-4.830667,50.399288],"type":"Point"}
}