{
  "type": "Feature",
  "properties": {
    "addr:full":"Harley House Bolton Lancashire BL1 6AB",
    "addr:postcode":"bl1 6ab",
    "addr:street":"Bolton",
    "iso:country":"GB",
    "sg:address":"Harley House",
    "sg:city":"Bolton",
    "sg:classifiers":[
        {
            "category":"Professional",
            "type":"Services"
        }
    ],
    "sg:phone":"+44 1204 841185",
    "sg:postcode":"BL1 6AB",
    "sg:province":"Lancashire",
    "sg:tags":[
        "repair",
        "tech",
        "maintenance"
    ],
    "wof:name":"Dawson Computer Maintenance Ltd.",
    "wof:placetype":"venue"
},
  "geometry": {"coordinates":[-2.4265940189,53.578289032],"type":"Point"}
}