{
  "type": "Feature",
  "properties": {
    "iso:country":"GB",
    "sg:address":"107 Ebury Street",
    "sg:city":"London",
    "sg:classifiers":[
        {
            "category":"Travel",
            "subcategory":"Hotels & Motels",
            "type":"Entertainment"
        }
    ],
    "sg:phone":"+44 20 7730 1048",
    "sg:postcode":"SW1W 9QU",
    "sg:province":"Greater London",
    "wof:name":"Woodville House Hotel",
    "wof:placetype":"venue"
},
  "geometry": {"coordinates":[-0.149168998,51.4940032959],"type":"Point"}
}