{
  "type": "Feature",
  "properties": {
    "addr:full":"Unit 3 5 West Hill Milton Keynes Bedfordshire MK17 8DP",
    "addr:housenumber":"unit;5",
    "addr:postcode":"mk17 8dp",
    "addr:street":"West",
    "iso:country":"GB",
    "sg:address":"Unit 3 5 West Hill",
    "sg:city":"Milton Keynes",
    "sg:classifiers":[
        {
            "category":"Building & Trades",
            "subcategory":"Cleaning & Sanitation",
            "type":"Services"
        }
    ],
    "sg:phone":"+44 1908 587348",
    "sg:postcode":"MK17 8DP",
    "sg:province":"Bedfordshire",
    "sg:tags":[
        "commercial"
    ],
    "wof:name":"Stalden Security Services",
    "wof:placetype":"venue"
},
  "geometry": {"coordinates":[-0.628853,52.013481],"type":"Point"}
}