{
  "type": "Feature",
  "properties": {
    "addr:full":"The Mount, Burton Overy Leicester Leicestershire LE8 9DS",
    "addr:postcode":"le8 9ds",
    "iso:country":"GB",
    "sg:address":"The Mount, Burton Overy",
    "sg:city":"Leicester",
    "sg:classifiers":[
        {
            "category":"Farming",
            "subcategory":"Poultry Farm",
            "type":"Manufacturing & Wholesale Goods"
        },
        {
            "category":"Shopping",
            "type":"Retail Goods"
        }
    ],
    "sg:phone":"+44 116 259 3345",
    "sg:postcode":"LE8 9DS",
    "sg:province":"Leicestershire",
    "sg:tags":[
        "merchant",
        "related"
    ],
    "wof:name":"John Holman Agrihealth Ltd.",
    "wof:placetype":"venue"
},
  "geometry": {"coordinates":[-1.0024709702,52.5749664307],"type":"Point"}
}