{
  "type": "Feature",
  "properties": {
    "addr:full":"184 Lavender Hill London Greater London SW11 5TQ",
    "addr:housenumber":"184",
    "addr:postcode":"sw11 5tq",
    "addr:street":"Lavender Hill",
    "iso:country":"GB",
    "sg:address":"184 Lavender Hill",
    "sg:city":"London",
    "sg:classifiers":[
        {
            "category":"Restaurant",
            "type":"Food & Drink"
        }
    ],
    "sg:phone":"+44 20 7228 8947",
    "sg:postcode":"SW11 5TQ",
    "sg:province":"Greater London",
    "sg:tags":[
        "indian",
        "-"
    ],
    "wof:name":"M S Miah",
    "wof:placetype":"venue"
},
  "geometry": {"coordinates":[-0.163556993,51.4642791748],"type":"Point"}
}