{
  "type": "Feature",
  "properties": {
    "addr:full":"Fulwood Farm, Trull Taunton Devon TA3 7PE",
    "addr:housenumber":"trull",
    "addr:postcode":"ta3 7pe",
    "iso:country":"GB",
    "sg:address":"Fulwood Farm, Trull",
    "sg:city":"Taunton",
    "sg:classifiers":[
        {
            "category":"Farming",
            "subcategory":"Livestock Farm",
            "type":"Manufacturing & Wholesale Goods"
        }
    ],
    "sg:phone":"+44 1823 421337",
    "sg:postcode":"TA3 7PE",
    "sg:province":"Devon",
    "sg:tags":[
        "others"
    ],
    "wof:name":"L & D Spiller & Sons",
    "wof:placetype":"venue"
},
  "geometry": {"coordinates":[-3.1198570728,50.9940414429],"type":"Point"}
}