{
  "type": "Feature",
  "properties": {
    "addr:full":"Rear Of Mill Terrace, Mill Place, Shiney Row Houghton-le-spring Durham DH4 4JT",
    "addr:housenumber":"rear of",
    "addr:postcode":"dh4 4jt",
    "addr:street":"Mill Terrace Mill Place;Row",
    "iso:country":"GB",
    "sg:address":"Rear Of Mill Terrace, Mill Place, Shiney Row",
    "sg:city":"Houghton-le-spring",
    "sg:classifiers":[
        {
            "category":"Building & Trades",
            "subcategory":"Cleaning & Sanitation",
            "type":"Services"
        }
    ],
    "sg:phone":"+44 191 385 3333",
    "sg:postcode":"DH4 4JT",
    "sg:province":"Durham",
    "sg:tags":[
        "dry",
        "control",
        "damp",
        "rot"
    ],
    "wof:name":"Marsden Preservation Ltd.",
    "wof:placetype":"venue"
},
  "geometry": {"coordinates":[-1.497048974,54.8670845032],"type":"Point"}
}