{
  "type": "Feature",
  "properties": {
    "iso:country":"GB",
    "sg:address":"14 Earl Close",
    "sg:city":"High Wycombe",
    "sg:classifiers":[
        {
            "category":"Real Estate",
            "subcategory":"Architect",
            "type":"Services"
        }
    ],
    "sg:postcode":"HP13 5EH",
    "sg:province":"Buckinghamshire",
    "wof:name":"Linevast Limited",
    "wof:placetype":"venue"
},
  "geometry": {"coordinates":[-0.755019,51.640465],"type":"Point"}
}