{
  "type": "Feature",
  "properties": {
    "addr:full":"14 Earl Close High Wycombe Buckinghamshire HP13 5EH",
    "addr:housenumber":"14",
    "addr:postcode":"hp13 5eh",
    "addr:street":"Earl Close",
    "iso:country":"GB",
    "sg:address":"14 Earl Close",
    "sg:city":"High Wycombe",
    "sg:classifiers":[
        {
            "category":"Real Estate",
            "subcategory":"Architect",
            "type":"Services"
        }
    ],
    "sg:postcode":"HP13 5EH",
    "sg:province":"Buckinghamshire",
    "wof:name":"Linevast Limited",
    "wof:placetype":"venue"
},
  "geometry": {"coordinates":[-0.755019,51.640465],"type":"Point"}
}