{
  "type": "Feature",
  "properties": {
    "addr:full":"Unit 2, 94 Fleet Rd Fleet Hampshire GU51 4PA",
    "addr:housenumber":"unit;94",
    "addr:postcode":"gu51 4pa",
    "addr:street":"Fleet Rd",
    "iso:country":"GB",
    "sg:address":"Unit 2, 94 Fleet Rd",
    "sg:city":"Fleet",
    "sg:classifiers":[
        {
            "category":"Professional",
            "subcategory":"Employment Agencies",
            "type":"Services"
        }
    ],
    "sg:postcode":"GU51 4PA",
    "sg:province":"Hampshire",
    "sg:tags":[
        "consultant"
    ],
    "wof:name":"Hampshire County Council",
    "wof:placetype":"venue"
},
  "geometry": {"coordinates":[-0.8393959999,51.2836723328],"type":"Point"}
}