{
  "type": "Feature",
  "properties": {
    "addr:full":"Main Street, Grimston Melton Mowbray Leicestershire LE14 3BZ",
    "addr:postcode":"le14 3bz",
    "addr:street":"Main Street",
    "iso:country":"GB",
    "sg:address":"Main Street, Grimston",
    "sg:city":"Melton Mowbray",
    "sg:classifiers":[
        {
            "category":"Professional",
            "type":"Services"
        }
    ],
    "sg:phone":"+44 1664 813800",
    "sg:postcode":"LE14 3BZ",
    "sg:province":"Leicestershire",
    "sg:tags":[
        "caterer"
    ],
    "wof:name":"Coffee Heaven Ltd.",
    "wof:placetype":"venue"
},
  "geometry": {"coordinates":[-0.943407,52.764523],"type":"Point"}
}