{
  "type": "Feature",
  "properties": {
    "addr:full":"Moir Place, Alexandra Parade Dunoon Argyll and Bute PA23 8AD",
    "addr:postcode":"pa23 8ad",
    "addr:street":"Moir Place Alexandra Parade",
    "iso:country":"GB",
    "sg:address":"Moir Place, Alexandra Parade",
    "sg:city":"Dunoon",
    "sg:classifiers":[
        {
            "category":"Health Services",
            "subcategory":"Dentist",
            "type":"Services"
        }
    ],
    "sg:phone":"+44 1369 703381",
    "sg:postcode":"PA23 8AD",
    "sg:province":"Argyll and Bute",
    "wof:name":"Argyll & Clyde Health Board",
    "wof:placetype":"venue"
},
  "geometry": {"coordinates":[-4.9216980934,55.9523658752],"type":"Point"}
}