{
  "type": "Feature",
  "properties": {
    "addr:full":"101 Station Road, Whittington Moor Chesterfield Derbyshire S41 9AW",
    "addr:housenumber":"101",
    "addr:postcode":"s41 9aw",
    "addr:street":"Station Road",
    "iso:country":"GB",
    "sg:address":"101 Station Road, Whittington Moor",
    "sg:city":"Chesterfield",
    "sg:classifiers":[
        {
            "category":"Retail",
            "subcategory":"Repair Shop",
            "type":"Services"
        }
    ],
    "sg:phone":"+44 1246 454433",
    "sg:postcode":"S41 9AW",
    "sg:province":"Derbyshire",
    "sg:tags":[
        "radio",
        "television",
        "video"
    ],
    "wof:name":"Marriott's Tv & Video Service Centre",
    "wof:placetype":"venue"
},
  "geometry": {"coordinates":[-1.4288320541,53.2633552551],"type":"Point"}
}