{
  "type": "Feature",
  "properties": {
    "iso:country":"GB",
    "sg:address":"148 Melton High Street, Wath-on-dearne",
    "sg:city":"Rotherham",
    "sg:classifiers":[
        {
            "category":"Sports & Exercise",
            "subcategory":"Tennis Court",
            "type":"Entertainment"
        }
    ],
    "sg:phone":"+44 7836 528380",
    "sg:postcode":"S63 6RG",
    "sg:province":"South Yorkshire",
    "sg:tags":[
        "breakdown",
        "recovery"
    ],
    "wof:name":"Ian's Recovery",
    "wof:placetype":"venue"
},
  "geometry": {"coordinates":[-1.361499,53.503677],"type":"Point"}
}