{
  "type": "Feature",
  "properties": {
    "addr:full":"Hall Farm, Back Lane, Billingley Barnsley South Yorkshire S72 0JF",
    "addr:postcode":"s72 0jf",
    "addr:street":"Hall;Back Lane;Yorkshire",
    "iso:country":"GB",
    "sg:address":"Hall Farm, Back Lane, Billingley",
    "sg:city":"Barnsley",
    "sg:classifiers":[
        {
            "category":"Farming",
            "subcategory":"Livestock Farm",
            "type":"Manufacturing & Wholesale Goods"
        },
        {
            "category":"Farming",
            "subcategory":"Farm",
            "type":"Manufacturing & Wholesale Goods"
        }
    ],
    "sg:phone":"+44 1709 894262",
    "sg:postcode":"S72 0JF",
    "sg:province":"South Yorkshire",
    "sg:tags":[
        "mixed",
        "crop",
        "others"
    ],
    "wof:name":"C M Stenton & Son",
    "wof:placetype":"venue"
},
  "geometry": {"coordinates":[-1.3386499882,53.537399292],"type":"Point"}
}