{
  "type": "Feature",
  "properties": {
    "iso:country":"GB",
    "sg:address":"109 Western Rd",
    "sg:city":"Brighton",
    "sg:classifiers":[
        {
            "category":"Professional",
            "subcategory":"Computer Services",
            "type":"Services"
        }
    ],
    "sg:phone":"+44 1273 772882",
    "sg:postcode":"BN1 2AA",
    "sg:province":"East Sussex",
    "sg:tags":[
        "system",
        "software"
    ],
    "wof:name":"H & C Computers",
    "wof:placetype":"venue"
},
  "geometry": {"coordinates":[-0.154097,50.824989],"type":"Point"}
}