{
  "type": "Feature",
  "properties": {
    "addr:full":"Fairwater Medical Centre, Fairwater Sq Cwmbran Monmouthshire NP44 4TA",
    "addr:postcode":"np44 4ta",
    "addr:street":"Fairwater Sq",
    "iso:country":"GB",
    "sg:address":"Fairwater Medical Centre, Fairwater Sq",
    "sg:city":"Cwmbran",
    "sg:classifiers":[
        {
            "category":"Health Services",
            "subcategory":"Doctor",
            "type":"Services"
        }
    ],
    "sg:phone":"+44 1633 869544",
    "sg:postcode":"NP44 4TA",
    "sg:province":"Monmouthshire",
    "sg:tags":[
        "practitioners"
    ],
    "wof:name":"Nirmal, D L",
    "wof:placetype":"venue"
},
  "geometry": {"coordinates":[-3.045039,51.64415],"type":"Point"}
}