{
  "type": "Feature",
  "properties": {
    "addr:full":"210-212 Hagley Road Stourbridge Staffordshire DY8 2JU",
    "addr:housenumber":"210-212",
    "addr:postcode":"dy8 2ju",
    "addr:street":"Hagley Road",
    "iso:country":"GB",
    "sg:address":"210-212 Hagley Road",
    "sg:city":"Stourbridge",
    "sg:classifiers":[
        {
            "category":"Shopping",
            "subcategory":"Bicycles & Sporting Goods",
            "type":"Retail Goods"
        }
    ],
    "sg:postcode":"DY8 2JU",
    "sg:province":"Staffordshire",
    "sg:tags":[
        "cycle",
        "accessory"
    ],
    "wof:name":"Phillip Sherwood",
    "wof:placetype":"venue"
},
  "geometry": {"coordinates":[-2.1380300522,52.4435691833],"type":"Point"}
}