{
  "type": "Feature",
  "properties": {
    "addr:full":"56 Charlton Church Lane London Greater London SE7 7AB",
    "addr:housenumber":"56",
    "addr:postcode":"se7 7ab",
    "addr:street":"Charlton Church Lane",
    "iso:country":"GB",
    "sg:address":"56 Charlton Church Lane",
    "sg:city":"London",
    "sg:classifiers":[
        {
            "category":"Fast Food",
            "type":"Food & Drink"
        }
    ],
    "sg:phone":"+44 20 8853 1706",
    "sg:postcode":"SE7 7AB",
    "sg:province":"Greater London",
    "sg:tags":[
        "away",
        "meal",
        "outlet",
        "take"
    ],
    "wof:name":"New Manderin Palace",
    "wof:placetype":"venue"
},
  "geometry": {"coordinates":[0.032641001,51.4853096008],"type":"Point"}
}