{
  "type": "Feature",
  "properties": {
    "addr:full":"34 Stockingstone Road Luton Bedfordshire LU2 7NF",
    "addr:housenumber":"34",
    "addr:postcode":"lu2 7nf",
    "addr:street":"Stockingstone Road",
    "iso:country":"GB",
    "sg:address":"34 Stockingstone Road",
    "sg:city":"Luton",
    "sg:classifiers":[
        {
            "category":"Building & Trades",
            "subcategory":"Construction",
            "type":"Services"
        }
    ],
    "sg:phone":"+44 1582 20276",
    "sg:postcode":"LU2 7NF",
    "sg:province":"Bedfordshire",
    "sg:tags":[
        "joiner",
        "carpenter"
    ],
    "wof:name":"Trevor Thompson",
    "wof:placetype":"venue"
},
  "geometry": {"coordinates":[-0.404467,51.892426],"type":"Point"}
}