{
  "type": "Feature",
  "properties": {
    "addr:full":"37d Mildmay Gro North London Greater London N1 4RH",
    "addr:housenumber":"37d",
    "addr:postcode":"n1 4rh",
    "addr:street":"Mildmay Gro North",
    "iso:country":"GB",
    "sg:address":"37d Mildmay Gro North",
    "sg:city":"London",
    "sg:classifiers":[
        {
            "category":"Real Estate",
            "subcategory":"Architect",
            "type":"Services"
        }
    ],
    "sg:phone":"+44 20 7359 0288",
    "sg:postcode":"N1 4RH",
    "sg:province":"Greater London",
    "wof:name":"Benson & Forsyth",
    "wof:placetype":"venue"
},
  "geometry": {"coordinates":[-0.084262,51.54781],"type":"Point"}
}