{
  "type": "Feature",
  "properties": {
    "iso:country":"GB",
    "sg:address":"359 Blackpool Rd, Fulwood",
    "sg:city":"Preston",
    "sg:classifiers":[
        {
            "category":"Retail",
            "subcategory":"Auto Repair",
            "type":"Services"
        }
    ],
    "sg:phone":"+44 1772 251099",
    "sg:postcode":"PR2 3AB",
    "sg:province":"Lancashire",
    "sg:tags":[
        "modification",
        "garage"
    ],
    "wof:name":"National Tyres & Autocare",
    "wof:placetype":"venue"
},
  "geometry": {"coordinates":[-2.714391,53.773392],"type":"Point"}
}