{
  "type": "Feature",
  "properties": {
    "addr:full":"96 Kings Road Chelmsford Essex CM1 2BB",
    "addr:housenumber":"96",
    "addr:postcode":"cm1 2bb",
    "addr:street":"Kings Road",
    "iso:country":"GB",
    "sg:address":"96 Kings Road",
    "sg:city":"Chelmsford",
    "sg:classifiers":[
        {
            "category":"Shopping",
            "subcategory":"News",
            "type":"Retail Goods"
        }
    ],
    "sg:phone":"+44 1245 355634",
    "sg:postcode":"CM1 2BB",
    "sg:province":"Essex",
    "sg:tags":[
        "newsagent"
    ],
    "wof:name":"The Paper Shop",
    "wof:placetype":"venue"
},
  "geometry": {"coordinates":[0.4588670135,51.7445259094],"type":"Point"}
}