{
  "type": "Feature",
  "properties": {
    "addr:full":"62 Edgware Way Edgware Greater London HA8 8JS",
    "addr:housenumber":"62",
    "addr:postcode":"ha8 8js",
    "addr:street":"Edgware Way",
    "iso:country":"GB",
    "sg:address":"62 Edgware Way",
    "sg:city":"Edgware",
    "sg:classifiers":[
        {
            "category":"Shopping",
            "subcategory":"Books",
            "type":"Retail Goods"
        }
    ],
    "sg:phone":"+44 20 8958 7632",
    "sg:postcode":"HA8 8JS",
    "sg:province":"Greater London",
    "sg:tags":[
        "bookseller"
    ],
    "wof:name":"Carmel Gifts",
    "wof:placetype":"venue"
},
  "geometry": {"coordinates":[-0.299759,51.632664],"type":"Point"}
}