{
  "type": "Feature",
  "properties": {
    "iso:country":"GB",
    "sg:address":"Kettering Road, Islip Furnaces Industrial Estate, Islip",
    "sg:city":"Kettering",
    "sg:classifiers":[
        {
            "category":"Retail",
            "subcategory":"Auto Repair",
            "type":"Services"
        }
    ],
    "sg:postcode":"NN14 3JW",
    "sg:province":"Northamptonshire",
    "sg:tags":[
        "car",
        "specialist",
        "customizing"
    ],
    "wof:name":"Paul James Tyres",
    "wof:placetype":"venue"
},
  "geometry": {"coordinates":[-0.548992,52.395863],"type":"Point"}
}