{
  "type": "Feature",
  "properties": {
    "iso:country":"GB",
    "sg:address":"Clacton Road, Frating",
    "sg:city":"Colchester",
    "sg:classifiers":[
        {
            "category":"Retail",
            "subcategory":"Auto Rental",
            "type":"Services"
        }
    ],
    "sg:phone":"+44 1206 251525",
    "sg:postcode":"CO7 7QY",
    "sg:province":"Essex",
    "sg:tags":[
        "car"
    ],
    "wof:name":"Willhire Vehicle Rentals",
    "wof:placetype":"venue"
},
  "geometry": {"coordinates":[1.0220799446,51.8606834412],"type":"Point"}
}