{
  "type": "Feature",
  "properties": {
    "addr:full":"16 Stoneham Street, Coggeshall Colchester Essex CO6 1TT",
    "addr:housenumber":"16",
    "addr:postcode":"co6 1tt",
    "addr:street":"Stoneham Street",
    "iso:country":"GB",
    "sg:address":"16 Stoneham Street, Coggeshall",
    "sg:city":"Colchester",
    "sg:classifiers":[
        {
            "category":"Shopping",
            "subcategory":"Books",
            "type":"Retail Goods"
        }
    ],
    "sg:phone":"+44 1376 561730",
    "sg:postcode":"CO6 1TT",
    "sg:province":"Essex",
    "sg:tags":[
        "second-hand"
    ],
    "wof:name":"Elkin Mathews",
    "wof:placetype":"venue"
},
  "geometry": {"coordinates":[0.6862429976,51.8714141846],"type":"Point"}
}