{
  "type": "Feature",
  "properties": {
    "addr:full":"Southey Street Keswick Cumbria CA12 4HH",
    "addr:postcode":"ca12 4hh",
    "addr:street":"Southey Street",
    "iso:country":"GB",
    "sg:address":"Southey Street",
    "sg:city":"Keswick",
    "sg:classifiers":[
        {
            "category":"Shopping",
            "subcategory":"Pets & Pet Supplies",
            "type":"Retail Goods"
        }
    ],
    "sg:postcode":"CA12 4HH",
    "sg:province":"Cumbria",
    "wof:name":"Pet Needs",
    "wof:placetype":"venue"
},
  "geometry": {"coordinates":[-3.134223938,54.6004753113],"type":"Point"}
}