{
  "type": "Feature",
  "properties": {
    "addr:full":"205a Nantwich Road Crewe Cheshire CW2 6DD",
    "addr:housenumber":"205a",
    "addr:postcode":"cw2 6dd",
    "addr:street":"Nantwich Road",
    "iso:country":"GB",
    "sg:address":"205a Nantwich Road",
    "sg:city":"Crewe",
    "sg:classifiers":[
        {
            "category":"Professional",
            "subcategory":"Employment Agencies",
            "type":"Services"
        }
    ],
    "sg:phone":"+44 1270 250001",
    "sg:postcode":"CW2 6DD",
    "sg:province":"Cheshire",
    "sg:tags":[
        "consultant"
    ],
    "wof:name":"Driver Hire Crewe",
    "wof:placetype":"venue"
},
  "geometry": {"coordinates":[-2.445394,53.08757],"type":"Point"}
}