{
  "type": "Feature",
  "properties": {
    "addr:full":"6 Carlingnose Way, North Queensferry Inverkeithing Fife KY11 1EU",
    "addr:housenumber":"6",
    "addr:postcode":"ky11 1eu",
    "addr:street":"Carlingnose Way North;Inverkeithing",
    "iso:country":"GB",
    "sg:address":"6 Carlingnose Way, North Queensferry",
    "sg:city":"Inverkeithing",
    "sg:classifiers":[
        {
            "category":"Professional",
            "subcategory":"Accounting & Tax Preparation",
            "type":"Services"
        }
    ],
    "sg:phone":"+44 131 312 8772",
    "sg:postcode":"KY11 1EU",
    "sg:province":"Fife",
    "sg:tags":[
        "accountant"
    ],
    "wof:name":"Fraser Kerr & Co",
    "wof:placetype":"venue"
},
  "geometry": {"coordinates":[-3.397679,56.031132],"type":"Point"}
}