{
  "type": "Feature",
  "properties": {
    "iso:country":"GB",
    "sg:address":"The Old Workshop, Bratton Fleming",
    "sg:city":"Barnstaple",
    "sg:classifiers":[
        {
            "category":"Home & Garden",
            "subcategory":"Hardware",
            "type":"Retail Goods"
        }
    ],
    "sg:phone":"+44 1598 710892",
    "sg:postcode":"EX31 4SA",
    "sg:province":"Devon",
    "sg:tags":[
        "fixing",
        "nuts",
        "bolt"
    ],
    "wof:name":"E K P Supplies",
    "wof:placetype":"venue"
},
  "geometry": {"coordinates":[-3.939171,51.122311],"type":"Point"}
}