{
  "type": "Feature",
  "properties": {
    "addr:full":"31 Marsh Rd Cowes Isle of Wight PO31 8JQ",
    "addr:housenumber":"31",
    "addr:postcode":"po31 8jq",
    "addr:street":"Marsh Rd",
    "iso:country":"GB",
    "sg:address":"31 Marsh Rd",
    "sg:city":"Cowes",
    "sg:classifiers":[
        {
            "category":"Restaurant",
            "type":"Food & Drink"
        }
    ],
    "sg:phone":"+44 1983 281200",
    "sg:postcode":"PO31 8JQ",
    "sg:province":"Isle of Wight",
    "wof:name":"Sealights",
    "wof:placetype":"venue"
},
  "geometry": {"coordinates":[-1.3337550163,50.7543182373],"type":"Point"}
}