{
  "type": "Feature",
  "properties": {
    "addr:full":"Marles Farm, Awliscombe Honiton Devon EX14 3PJ",
    "addr:postcode":"ex14 3pj",
    "addr:street":"Awliscombe",
    "iso:country":"GB",
    "sg:address":"Marles Farm, Awliscombe",
    "sg:city":"Honiton",
    "sg:classifiers":[
        {
            "category":"Farming",
            "subcategory":"Livestock Farm",
            "type":"Manufacturing & Wholesale Goods"
        }
    ],
    "sg:phone":"+44 1404 42962",
    "sg:postcode":"EX14 3PJ",
    "sg:province":"Devon",
    "sg:tags":[
        "others"
    ],
    "wof:name":"A F Maynard & Son",
    "wof:placetype":"venue"
},
  "geometry": {"coordinates":[-3.2277860641,50.8072395325],"type":"Point"}
}