{
  "type": "Feature",
  "properties": {
    "addr:full":"15 Larch Clo Lymington Hampshire SO41 0GX",
    "addr:housenumber":"15",
    "addr:postcode":"so41 0gx",
    "addr:street":"Larch Clo",
    "iso:country":"GB",
    "sg:address":"15 Larch Clo",
    "sg:city":"Lymington",
    "sg:classifiers":[
        {
            "category":"Parking",
            "type":"Transportation"
        }
    ],
    "sg:phone":"+44 1425 620900",
    "sg:postcode":"SO41 0GX",
    "sg:province":"Hampshire",
    "sg:tags":[
        "car",
        "valet"
    ],
    "wof:name":"Milton Valeting",
    "wof:placetype":"venue"
},
  "geometry": {"coordinates":[-1.623914957,50.7582092285],"type":"Point"}
}