{
  "type": "Feature",
  "properties": {
    "addr:full":"Landsea House, Stuart Street, Cardiff Bay Cardiff Cardiff CF1 6BW",
    "addr:postcode":"cf1 6bw",
    "addr:street":"Stuart Street",
    "iso:country":"GB",
    "sg:address":"Landsea House, Stuart Street, Cardiff Bay",
    "sg:city":"Cardiff",
    "sg:classifiers":[
        {
            "category":"Food & Beverages",
            "subcategory":"Meat & Fish",
            "type":"Retail Goods"
        }
    ],
    "sg:phone":"+44 1222 463334",
    "sg:postcode":"CF1 6BW",
    "sg:province":"Cardiff",
    "sg:tags":[
        "chip"
    ],
    "wof:name":"Harry Ramsdens",
    "wof:placetype":"venue"
},
  "geometry": {"coordinates":[-3.16762,51.461342],"type":"Point"}
}