{
  "type": "Feature",
  "properties": {
    "iso:country":"GB",
    "sg:address":"Tartan Forge Town Lane, Wooburn Green High Wycombe",
    "sg:city":"High Wycombe",
    "sg:classifiers":[
        {
            "category":"Home & Garden",
            "subcategory":"Building Materials",
            "type":"Retail Goods"
        }
    ],
    "sg:phone":"+44 1628 520288",
    "sg:postcode":"HP10 0PJ",
    "sg:province":"Buckinghamshire",
    "sg:tags":[
        "ironwork",
        "diy",
        "wrought"
    ],
    "wof:name":"Dowlings Air Guns",
    "wof:placetype":"venue"
},
  "geometry": {"coordinates":[-0.683647,51.588245],"type":"Point"}
}