{
  "type": "Feature",
  "properties": {
    "iso:country":"GB",
    "sg:address":"Hatton Street, Adlington",
    "sg:city":"Chorley",
    "sg:classifiers":[
        {
            "category":"Building & Trades",
            "subcategory":"Construction",
            "type":"Services"
        }
    ],
    "sg:phone":"+44 1257 480222",
    "sg:postcode":"PR7 4HT",
    "sg:province":"Lancashire",
    "sg:tags":[
        "builder"
    ],
    "sg:website":"http://www.naylorwalkden.co.uk",
    "wof:name":"Naylor & Walkden Ltd.",
    "wof:placetype":"venue"
},
  "geometry": {"coordinates":[-2.606319,53.607899],"type":"Point"}
}