{
  "type": "Feature",
  "properties": {
    "addr:full":"Metropolitan House, Hagley Road Birmingham West Midlands B16 8TG",
    "addr:postcode":"b16 8tg",
    "addr:street":"Hagley Road",
    "iso:country":"GB",
    "sg:address":"Metropolitan House, Hagley Road",
    "sg:city":"Birmingham",
    "sg:classifiers":[
        {
            "category":"Banks & Credit Unions",
            "subcategory":"Financial Services",
            "type":"Services"
        }
    ],
    "sg:phone":"+44 121 456 3443",
    "sg:postcode":"B16 8TG",
    "sg:province":"West Midlands",
    "sg:tags":[
        "consultant"
    ],
    "wof:name":"R F S Ltd.",
    "wof:placetype":"venue"
},
  "geometry": {"coordinates":[-1.9203519821,52.4725608826],"type":"Point"}
}