{
  "type": "Feature",
  "properties": {
    "iso:country":"GB",
    "sg:address":"Pengam Road, Ystrad Mynach",
    "sg:city":"Hengoed",
    "sg:classifiers":[
        {
            "category":"Community Center",
            "type":"Public Place"
        }
    ],
    "sg:phone":"+44 1443 813982",
    "sg:postcode":"CF82 8AA",
    "sg:province":"Caerphilly",
    "sg:tags":[
        "recreation",
        "leisure",
        "centre"
    ],
    "wof:name":"Ystrad Mynach Sports Hall",
    "wof:placetype":"venue"
},
  "geometry": {"coordinates":[-3.239389,51.670345],"type":"Point"}
}