{
  "type": "Feature",
  "properties": {
    "iso:country":"GB",
    "sg:address":"47 Warrener Close",
    "sg:city":"Swindon",
    "sg:classifiers":[
        {
            "category":"Social Services",
            "subcategory":"Job Training",
            "type":"Services"
        }
    ],
    "sg:phone":"+44 1793 723748",
    "sg:postcode":"SN25 4AH",
    "sg:province":"Wiltshire",
    "sg:tags":[
        "translator",
        "interpreter"
    ],
    "wof:name":"Jens Puhle",
    "wof:placetype":"venue"
},
  "geometry": {"coordinates":[-1.7850550413,51.5997924805],"type":"Point"}
}