{
  "type": "Feature",
  "properties": {
    "iso:country":"GB",
    "sg:address":"Eagle Works, Hooton Street",
    "sg:city":"Nottingham",
    "sg:classifiers":[
        {
            "category":"Organizations",
            "subcategory":"Labor Organization",
            "type":"Services"
        },
        {
            "category":"Professional",
            "subcategory":"Business Services",
            "type":"Services"
        }
    ],
    "sg:phone":"+44 115 958 4990",
    "sg:postcode":"NG3 2NJ",
    "sg:province":"Nottinghamshire",
    "sg:tags":[
        "import",
        "export",
        "agent"
    ],
    "wof:name":"Microrama Import & Export",
    "wof:placetype":"venue"
},
  "geometry": {"coordinates":[-1.12473,52.95834],"type":"Point"}
}