{
  "type": "Feature",
  "properties": {
    "addr:full":"The Railway Station Alston Cumbria CA9 3JB",
    "addr:postcode":"ca9 3jb",
    "iso:country":"GB",
    "sg:address":"The Railway Station",
    "sg:city":"Alston",
    "sg:classifiers":[
        {
            "category":"Landmark",
            "subcategory":"Tourist Information",
            "type":"Public Place"
        }
    ],
    "sg:phone":"+44 1434 381696",
    "sg:postcode":"CA9 3JB",
    "sg:province":"Cumbria",
    "wof:name":"Tourist Information Centre",
    "wof:placetype":"venue"
},
  "geometry": {"coordinates":[-2.438751936,54.8123817444],"type":"Point"}
}