{
  "type": "Feature",
  "properties": {
    "addr:full":"3a Marker Place Bishop Auckland Durham DL14 7NJ",
    "addr:housenumber":"3a",
    "addr:postcode":"dl14 7nj",
    "addr:street":"Marker Place",
    "iso:country":"GB",
    "sg:address":"3a Marker Place",
    "sg:city":"Bishop Auckland",
    "sg:classifiers":[
        {
            "category":"Professional",
            "subcategory":"Employment Agencies",
            "type":"Services"
        }
    ],
    "sg:phone":"+44 1388 603468",
    "sg:postcode":"DL14 7NJ",
    "sg:province":"Durham",
    "sg:tags":[
        "career",
        "guidance"
    ],
    "wof:name":"Connections",
    "wof:placetype":"venue"
},
  "geometry": {"coordinates":[-1.6804939508,54.650100708],"type":"Point"}
}