{
  "type": "Feature",
  "properties": {
    "addr:full":"Coulby Dental Centre, The Parkway Centre Middlesbrough North Yorkshire TS8 0TJ",
    "addr:postcode":"ts8 0tj",
    "addr:street":"The Parkway",
    "iso:country":"GB",
    "sg:address":"Coulby Dental Centre, The Parkway Centre",
    "sg:city":"Middlesbrough",
    "sg:classifiers":[
        {
            "category":"Health Services",
            "subcategory":"Dentist",
            "type":"Services"
        }
    ],
    "sg:phone":"+44 1642 598888",
    "sg:postcode":"TS8 0TJ",
    "sg:province":"North Yorkshire",
    "wof:name":"N P Tucker",
    "wof:placetype":"venue"
},
  "geometry": {"coordinates":[-1.216442,54.519978],"type":"Point"}
}