{
  "type": "Feature",
  "properties": {
    "iso:country":"GB",
    "sg:address":"1-3 Wood St, St. Annes",
    "sg:city":"Lytham St. Annes",
    "sg:classifiers":[
        {
            "category":"Shopping",
            "subcategory":"Crafts & Fabrics",
            "type":"Retail Goods"
        }
    ],
    "sg:phone":"+44 1253 722559",
    "sg:postcode":"FY8 1QS",
    "sg:province":"Lancashire",
    "sg:tags":[
        "shop",
        "retailer"
    ],
    "wof:name":"Soper's",
    "wof:placetype":"venue"
},
  "geometry": {"coordinates":[-3.027902,53.750145],"type":"Point"}
}