{
  "type": "Feature",
  "properties": {
    "iso:country":"GB",
    "sg:address":"7 The Square",
    "sg:city":"Swanage",
    "sg:classifiers":[
        {
            "category":"Shopping",
            "subcategory":"Shoes",
            "type":"Retail Goods"
        }
    ],
    "sg:phone":"+44 1929 422505",
    "sg:postcode":"BH19 2LJ",
    "sg:province":"Dorset",
    "sg:tags":[
        "shop"
    ],
    "wof:name":"Caroline's Shoes",
    "wof:placetype":"venue"
},
  "geometry": {"coordinates":[-1.957385,50.607559],"type":"Point"}
}