{
  "type": "Feature",
  "properties": {
    "addr:full":"Knightingale House, 1-7 Fulham High Street London Greater London SW6 3JH",
    "addr:housenumber":"1-7",
    "addr:postcode":"sw6 3jh",
    "addr:street":"Fulham High Street",
    "iso:country":"GB",
    "sg:address":"Knightingale House, 1-7 Fulham High Street",
    "sg:city":"London",
    "sg:classifiers":[
        {
            "category":"Government",
            "subcategory":"Post Office",
            "type":"Public Place"
        }
    ],
    "sg:phone":"+44 20 7371 7047",
    "sg:postcode":"SW6 3JH",
    "sg:province":"Greater London",
    "sg:tags":[
        "window",
        "display",
        "dressing"
    ],
    "wof:name":"Borderline Graphics",
    "wof:placetype":"venue"
},
  "geometry": {"coordinates":[-0.210947,51.471401],"type":"Point"}
}