{
  "type": "Feature",
  "properties": {
    "iso:country":"GB",
    "sg:address":"Anglo House, Anglo Trading Estate",
    "sg:city":"Shepton Mallet",
    "sg:classifiers":[
        {
            "category":"Organizations",
            "subcategory":"Membership Organization",
            "type":"Services"
        }
    ],
    "sg:postcode":"BA4 5BY",
    "sg:province":"Somerset",
    "sg:tags":[
        "club"
    ],
    "wof:name":"1A St. Pauls Road Management Company Lim",
    "wof:placetype":"venue"
},
  "geometry": {"coordinates":[-2.546778,51.189732],"type":"Point"}
}