{
  "type": "Feature",
  "properties": {
    "addr:full":"4 Heriot Row Edinburgh City of Edinburgh EH3 6HU",
    "addr:housenumber":"4",
    "addr:postcode":"eh3 6hu",
    "addr:street":"Heriot Row",
    "iso:country":"GB",
    "sg:address":"4 Heriot Row",
    "sg:city":"Edinburgh",
    "sg:classifiers":[
        {
            "category":"Professional",
            "subcategory":"Lawyer & Legal Services",
            "type":"Services"
        }
    ],
    "sg:phone":"+44 131 557 4114",
    "sg:postcode":"EH3 6HU",
    "sg:province":"City of Edinburgh",
    "sg:tags":[
        "patent",
        "agent"
    ],
    "wof:name":"Rodime plc",
    "wof:placetype":"venue"
},
  "geometry": {"coordinates":[-3.199423,55.95594],"type":"Point"}
}