{
  "type": "Feature",
  "properties": {
    "addr:full":"5 Preston Road Weymouth Dorset DT3 6PU",
    "addr:housenumber":"5",
    "addr:postcode":"dt3 6pu",
    "addr:street":"Preston Road",
    "iso:country":"GB",
    "sg:address":"5 Preston Road",
    "sg:city":"Weymouth",
    "sg:classifiers":[
        {
            "category":"Shopping",
            "subcategory":"News",
            "type":"Retail Goods"
        }
    ],
    "sg:phone":"+44 1305 833155",
    "sg:postcode":"DT3 6PU",
    "sg:province":"Dorset",
    "sg:tags":[
        "newsagent"
    ],
    "wof:name":"H B Joy & Sons",
    "wof:placetype":"venue"
},
  "geometry": {"coordinates":[-2.4315950871,50.6333312988],"type":"Point"}
}