{
  "type": "Feature",
  "properties": {
    "iso:country":"GB",
    "sg:address":"1a-1b Unit, St Clare Business Park",
    "sg:city":"Hampton",
    "sg:classifiers":[
        {
            "category":"Communications",
            "type":"Services"
        }
    ],
    "sg:phone":"+44 20 8941 7975",
    "sg:postcode":"TW12 1PZ",
    "sg:province":"Greater London",
    "sg:tags":[
        "data",
        "network"
    ],
    "wof:name":"Cablefree Solutions Ltd.",
    "wof:placetype":"venue"
},
  "geometry": {"coordinates":[-0.362314,51.43071],"type":"Point"}
}