{
  "type": "Feature",
  "properties": {
    "iso:country":"GB",
    "sg:address":"Hollywell Leisure Park, Park Road",
    "sg:city":"Castleford",
    "sg:classifiers":[
        {
            "category":"Bars & Pubs",
            "type":"Food & Drink"
        }
    ],
    "sg:phone":"+44 1977 668383",
    "sg:postcode":"WF10 4RS",
    "sg:province":"West Yorkshire",
    "sg:tags":[
        "pubs",
        "inn"
    ],
    "wof:name":"Northern Leisure 2000 Ltd.",
    "wof:placetype":"venue"
},
  "geometry": {"coordinates":[-1.344208,53.721699],"type":"Point"}
}