{
  "type": "Feature",
  "properties": {
    "iso:country":"GB",
    "sg:address":"137 Mortimer Road",
    "sg:city":"London",
    "sg:classifiers":[
        {
            "category":"Manufacturing",
            "subcategory":"Apparel",
            "type":"Manufacturing & Wholesale Goods"
        }
    ],
    "sg:phone":"+44 20 8969 2009",
    "sg:postcode":"NW10 5TN",
    "sg:province":"Greater London",
    "sg:tags":[
        "garment",
        "designer",
        "clothing"
    ],
    "wof:name":"Conscious Clothing",
    "wof:placetype":"venue"
},
  "geometry": {"coordinates":[-0.2233240008,51.5309753418],"type":"Point"}
}