{
  "type": "Feature",
  "properties": {
    "addr:full":"Unit 5 Church Farm Business Park, Corston Bath Somerset BA2 9AP",
    "addr:housenumber":"unit 5",
    "addr:postcode":"ba2 9ap",
    "addr:street":"Church Farm Business Park",
    "iso:country":"GB",
    "sg:address":"Unit 5 Church Farm Business Park, Corston",
    "sg:city":"Bath",
    "sg:classifiers":[
        {
            "category":"Professional",
            "subcategory":"Accounting & Tax Preparation",
            "type":"Services"
        }
    ],
    "sg:postcode":"BA2 9AP",
    "sg:province":"Somerset",
    "sg:tags":[
        "accountant"
    ],
    "wof:name":"G M Richards & Co.",
    "wof:placetype":"venue"
},
  "geometry": {"coordinates":[-2.440088,51.387798],"type":"Point"}
}