{
  "type": "Feature",
  "properties": {
    "addr:full":"4-7 Arden Buildings, Station Road, Dorridge Solihull Warwickshire B93 8HH",
    "addr:housenumber":"4-7;buildings",
    "addr:postcode":"b93 8hh",
    "addr:street":"Arden;Station Road",
    "iso:country":"GB",
    "sg:address":"4-7 Arden Buildings, Station Road, Dorridge",
    "sg:city":"Solihull",
    "sg:classifiers":[
        {
            "category":"Food & Beverages",
            "subcategory":"Groceries & Convenience Stores",
            "type":"Retail Goods"
        }
    ],
    "sg:phone":"+44 1564 774973",
    "sg:postcode":"B93 8HH",
    "sg:province":"Warwickshire",
    "wof:name":"ONE STOP COMMUNITY STORES LTD",
    "wof:placetype":"venue"
},
  "geometry": {"coordinates":[-1.7541190386,52.3713645935],"type":"Point"}
}