{
  "type": "Feature",
  "properties": {
    "iso:country":"GB",
    "sg:address":"London Road",
    "sg:city":"Stanford-le-hope",
    "sg:classifiers":[
        {
            "category":"Sports & Exercise",
            "subcategory":"Golf",
            "type":"Entertainment"
        }
    ],
    "sg:phone":"+44 1375 673007",
    "sg:postcode":"SS17 0LX",
    "sg:province":"Essex",
    "sg:tags":[
        "club",
        "course",
        "equipment"
    ],
    "sg:website":"http://www.stcleresgolf.co.uk",
    "wof:name":"St Cleres Hall Golf Club",
    "wof:placetype":"venue"
},
  "geometry": {"coordinates":[0.4207000136,51.5141639709],"type":"Point"}
}