{
  "type": "Feature",
  "properties": {
    "addr:full":"Heol Don, Whitchurch Cardiff Cardiff CF4 2AU",
    "addr:postcode":"cf4 2au",
    "addr:street":"Heol Don Whitchurch",
    "iso:country":"GB",
    "sg:address":"Heol Don, Whitchurch",
    "sg:city":"Cardiff",
    "sg:classifiers":[
        {
            "category":"Government",
            "subcategory":"Office",
            "type":"Public Place"
        },
        {
            "category":"Organizations",
            "subcategory":"Non-profit Organization",
            "type":"Services"
        }
    ],
    "sg:phone":"+44 29 2052 1855",
    "sg:postcode":"CF4 2AU",
    "sg:province":"Cardiff",
    "sg:tags":[
        "organisation",
        "local",
        "voluntary",
        "charity"
    ],
    "wof:name":"Heol Don Resource Centre for the Elderly & Physica",
    "wof:placetype":"venue"
},
  "geometry": {"coordinates":[-3.2281699181,51.51197052],"type":"Point"}
}