{
  "type": "Feature",
  "properties": {
    "addr:full":"65 Pevensey Avenue London Greater London N11 2RB",
    "addr:housenumber":"65",
    "addr:postcode":"n11 2rb",
    "addr:street":"Pevensey Avenue",
    "iso:country":"GB",
    "sg:address":"65 Pevensey Avenue",
    "sg:city":"London",
    "sg:classifiers":[
        {
            "category":"Shopping",
            "subcategory":"Books",
            "type":"Retail Goods"
        }
    ],
    "sg:phone":"+44 20 8350 9677",
    "sg:postcode":"N11 2RB",
    "sg:province":"Greater London",
    "wof:name":"C D Press Ltd.",
    "wof:placetype":"venue"
},
  "geometry": {"coordinates":[-0.1285780072,51.6143226624],"type":"Point"}
}