{
  "type": "Feature",
  "properties": {
    "iso:country":"GB",
    "sg:address":"6 Eastville Cotts, Weston Road",
    "sg:city":"Portland",
    "sg:classifiers":[
        {
            "category":"Professional",
            "subcategory":"Engineering",
            "type":"Services"
        },
        {
            "category":"Building & Trades",
            "subcategory":"Plumbing",
            "type":"Services"
        }
    ],
    "sg:postcode":"DT5 2DD",
    "sg:province":"Dorset",
    "sg:tags":[
        "gas",
        "heating",
        "engineer"
    ],
    "wof:name":"Fred Cann",
    "wof:placetype":"venue"
},
  "geometry": {"coordinates":[-2.435969,50.546902],"type":"Point"}
}