{
  "type": "Feature",
  "properties": {
    "addr:full":"56 Ayres St Southwark Greater London SE1 1EU",
    "addr:housenumber":"56",
    "addr:postcode":"se1 1eu",
    "addr:street":"Ayres St",
    "iso:country":"GB",
    "sg:address":"56 Ayres St",
    "sg:city":"Southwark",
    "sg:classifiers":[
        {
            "category":"Professional",
            "subcategory":"Computer Services",
            "type":"Services"
        }
    ],
    "sg:phone":"+44 20 7378 3888",
    "sg:postcode":"SE1 1EU",
    "sg:province":"Greater London",
    "sg:tags":[
        "system",
        "software"
    ],
    "wof:name":"Quadranet",
    "wof:placetype":"venue"
},
  "geometry": {"coordinates":[-0.0948799998,51.5037384033],"type":"Point"}
}