{
  "type": "Feature",
  "properties": {
    "iso:country":"GB",
    "sg:address":"19 High St, Little Bytham",
    "sg:city":"Grantham",
    "sg:classifiers":[
        {
            "category":"Wholesale",
            "subcategory":"Office Equipment",
            "type":"Manufacturing & Wholesale Goods"
        }
    ],
    "sg:phone":"+44 1780 411019",
    "sg:postcode":"NG33 4QX",
    "sg:province":"Leicestershire",
    "wof:name":"Carter Parratt",
    "wof:placetype":"venue"
},
  "geometry": {"coordinates":[-0.5388470292,52.7545433044],"type":"Point"}
}