{
  "type": "Feature",
  "properties": {
    "addr:full":"190 Liverpool Road South Liverpool Lancashire L31 7DQ",
    "addr:housenumber":"190",
    "addr:postcode":"l31 7dq",
    "addr:street":"Liverpool Road South",
    "iso:country":"GB",
    "sg:address":"190 Liverpool Road South",
    "sg:city":"Liverpool",
    "sg:classifiers":[
        {
            "category":"Manufacturing",
            "subcategory":"Petroleum Products",
            "type":"Manufacturing & Wholesale Goods"
        }
    ],
    "sg:phone":"+44 151 531 0574",
    "sg:postcode":"L31 7DQ",
    "sg:province":"Lancashire",
    "sg:tags":[
        "double",
        "glazing"
    ],
    "wof:name":"Paul Roberts",
    "wof:placetype":"venue"
},
  "geometry": {"coordinates":[-2.948871,53.509464],"type":"Point"}
}