{
  "type": "Feature",
  "properties": {
    "iso:country":"GB",
    "sg:address":"Mayfield Surgery, 54 Trentham Rd, Longton",
    "sg:city":"Stoke On Trent",
    "sg:classifiers":[
        {
            "category":"Health Services",
            "subcategory":"Doctor",
            "type":"Services"
        }
    ],
    "sg:phone":"+44 1782 315654",
    "sg:postcode":"ST3 4DW",
    "sg:province":"Staffordshire",
    "sg:tags":[
        "practitioners"
    ],
    "wof:name":"McCarthy & Partners",
    "wof:placetype":"venue"
},
  "geometry": {"coordinates":[-2.13447,52.98296],"type":"Point"}
}