{
  "type": "Feature",
  "properties": {
    "addr:full":"16 Springfield Avenue Rugeley Staffordshire WS15 1DB",
    "addr:housenumber":"16",
    "addr:postcode":"ws15 1db",
    "addr:street":"Springfield Avenue",
    "iso:country":"GB",
    "sg:address":"16 Springfield Avenue",
    "sg:city":"Rugeley",
    "sg:classifiers":[
        {
            "category":"Building & Trades",
            "subcategory":"Cleaning & Sanitation",
            "type":"Services"
        }
    ],
    "sg:postcode":"WS15 1DB",
    "sg:province":"Staffordshire",
    "sg:tags":[
        "commercial"
    ],
    "wof:name":"Clearview Cleaning Services Ltd.",
    "wof:placetype":"venue"
},
  "geometry": {"coordinates":[-1.928402,52.75248],"type":"Point"}
}