{
  "type": "Feature",
  "properties": {
    "addr:full":"Mornington Rd Bingley West Yorkshire BD16 4JS",
    "addr:postcode":"bd16 4js",
    "addr:street":"Mornington Rd",
    "iso:country":"GB",
    "sg:address":"Mornington Rd",
    "sg:city":"Bingley",
    "sg:classifiers":[
        {
            "category":"Community Center",
            "subcategory":"Youth",
            "type":"Public Place"
        }
    ],
    "sg:phone":"+44 1274 511416",
    "sg:postcode":"BD16 4JS",
    "sg:province":"West Yorkshire",
    "sg:tags":[
        "organisation",
        "centre"
    ],
    "wof:name":"Bingley Central Youth Club",
    "wof:placetype":"venue"
},
  "geometry": {"coordinates":[-1.8322089911,53.8497200012],"type":"Point"}
}