{
  "type": "Feature",
  "properties": {
    "addr:full":"Offa Cottage, Heol Offa, Coed Poeth Wrexham Wrexham LL11 3NE",
    "addr:postcode":"ll11 3ne",
    "addr:street":"Heol Offa;Poeth",
    "iso:country":"GB",
    "sg:address":"Offa Cottage, Heol Offa, Coed Poeth",
    "sg:city":"Wrexham",
    "sg:classifiers":[
        {
            "category":"Freight",
            "type":"Transportation"
        }
    ],
    "sg:phone":"+44 1978 755917",
    "sg:postcode":"LL11 3NE",
    "sg:province":"Wrexham",
    "sg:tags":[
        "haulage",
        "road"
    ],
    "wof:name":"F W Evans",
    "wof:placetype":"venue"
},
  "geometry": {"coordinates":[-3.0573859215,53.0559844971],"type":"Point"}
}