{
  "type": "Feature",
  "properties": {
    "iso:country":"GB",
    "sg:address":"Hollington Farm, Woolton Hill",
    "sg:city":"Newbury",
    "sg:classifiers":[
        {
            "category":"Farming",
            "subcategory":"Livestock Farm",
            "type":"Manufacturing & Wholesale Goods"
        }
    ],
    "sg:phone":"+44 1635 253511",
    "sg:postcode":"RG20 9XN",
    "sg:province":"Berkshire",
    "sg:tags":[
        "others"
    ],
    "wof:name":"N J Perris",
    "wof:placetype":"venue"
},
  "geometry": {"coordinates":[-1.3843029737,51.353603363],"type":"Point"}
}