{
  "type": "Feature",
  "properties": {
    "iso:country":"GB",
    "sg:address":"8 South Park Avenue, Broadwalk, Darley Dale",
    "sg:city":"Matlock",
    "sg:classifiers":[
        {
            "category":"Freight",
            "type":"Transportation"
        }
    ],
    "sg:postcode":"DE4 2FY",
    "sg:province":"Derbyshire",
    "sg:tags":[
        "haulage",
        "road"
    ],
    "wof:name":"Frank Raymond Wayne",
    "wof:placetype":"venue"
},
  "geometry": {"coordinates":[-1.5963209867,53.1659622192],"type":"Point"}
}