{
  "type": "Feature",
  "properties": {
    "addr:full":"Leigh Fields, Main Rd Yarmouth Isle of Wight PO41 0UL",
    "addr:postcode":"po41 0ul",
    "addr:street":"Leigh Fields Main Rd",
    "iso:country":"GB",
    "sg:address":"Leigh Fields, Main Rd",
    "sg:city":"Yarmouth",
    "sg:classifiers":[
        {
            "category":"Professional",
            "subcategory":"Printing & Photocopies",
            "type":"Services"
        }
    ],
    "sg:phone":"+44 1983 531811",
    "sg:postcode":"PO41 0UL",
    "sg:province":"Isle of Wight",
    "sg:tags":[
        "printer"
    ],
    "wof:name":"Print-Im Press",
    "wof:placetype":"venue"
},
  "geometry": {"coordinates":[-1.496659,50.705009],"type":"Point"}
}