{
  "type": "Feature",
  "properties": {
    "addr:full":"7 Western Parade, Woodhatch Reigate Surrey RH2 8AU",
    "addr:housenumber":"7",
    "addr:postcode":"rh2 8au",
    "addr:street":"Western Parade Woodhatch",
    "iso:country":"GB",
    "sg:address":"7 Western Parade, Woodhatch",
    "sg:city":"Reigate",
    "sg:classifiers":[
        {
            "category":"Shopping",
            "subcategory":"Hobbies, Toys, & Games",
            "type":"Retail Goods"
        }
    ],
    "sg:postcode":"RH2 8AU",
    "sg:province":"Surrey",
    "sg:tags":[
        "shop",
        "toy"
    ],
    "wof:name":"Peter Basden",
    "wof:placetype":"venue"
},
  "geometry": {"coordinates":[-0.2000660002,51.2238502502],"type":"Point"}
}