{
  "type": "Feature",
  "properties": {
    "iso:country":"GB",
    "sg:address":"Madges Farm House, Chearsley Road, Long Crendon",
    "sg:city":"Aylesbury",
    "sg:classifiers":[
        {
            "category":"Professional",
            "type":"Services"
        }
    ],
    "sg:postcode":"HP18 9AW",
    "sg:province":"Buckinghamshire",
    "sg:tags":[
        "interior",
        "furnishers",
        "designer"
    ],
    "wof:name":"Thomas Interior Contracts Ltd.",
    "wof:placetype":"venue"
},
  "geometry": {"coordinates":[-0.995376,51.773502],"type":"Point"}
}