{
  "type": "Feature",
  "properties": {
    "addr:full":"8 Lendal York North Yorkshire YO1 2AA",
    "addr:housenumber":"8",
    "addr:postcode":"yo1 2aa",
    "addr:street":"Lendal",
    "iso:country":"GB",
    "sg:address":"8 Lendal",
    "sg:city":"York",
    "sg:classifiers":[
        {
            "category":"Health Services",
            "subcategory":"Nursing And Care Facility",
            "type":"Services"
        }
    ],
    "sg:phone":"+44 1904 656455",
    "sg:postcode":"YO1 2AA",
    "sg:province":"North Yorkshire",
    "sg:tags":[
        "agency"
    ],
    "wof:name":"Goldsborough Homecare & Nursing Services",
    "wof:placetype":"venue"
},
  "geometry": {"coordinates":[-1.0859600306,53.9604377747],"type":"Point"}
}