{
  "type": "Feature",
  "properties": {
    "iso:country":"GB",
    "sg:address":"367 Wimborne Rd",
    "sg:city":"Bournemouth",
    "sg:classifiers":[
        {
            "category":"Professional",
            "subcategory":"Lawyer & Legal Services",
            "type":"Services"
        }
    ],
    "sg:postcode":"BH9 2AQ",
    "sg:province":"Dorset",
    "sg:tags":[
        "patent",
        "agent"
    ],
    "wof:name":"Bailey,Marion,",
    "wof:placetype":"venue"
},
  "geometry": {"coordinates":[-1.879062,50.741447],"type":"Point"}
}