{
  "type": "Feature",
  "properties": {
    "iso:country":"GB",
    "sg:address":"14 St Bartholomews Close, Cam",
    "sg:city":"Dursley",
    "sg:classifiers":[
        {
            "category":"Farming",
            "subcategory":"Dairy Farm",
            "type":"Manufacturing & Wholesale Goods"
        }
    ],
    "sg:phone":"+44 1453 545829",
    "sg:postcode":"GL11 5UR",
    "sg:province":"Gloucestershire",
    "wof:name":"Daybreak Dairies",
    "wof:placetype":"venue"
},
  "geometry": {"coordinates":[-2.367455,51.70047],"type":"Point"}
}