{
  "type": "Feature",
  "properties": {
    "addr:full":"7 High Ousegate York North Yorkshire YO1 8RZ",
    "addr:housenumber":"7",
    "addr:postcode":"yo1 8rz",
    "addr:street":"High Ousegate",
    "iso:country":"GB",
    "sg:address":"7 High Ousegate",
    "sg:city":"York",
    "sg:classifiers":[
        {
            "category":"Banks & Credit Unions",
            "subcategory":"Bank",
            "type":"Services"
        }
    ],
    "sg:phone":"+44 845 765 4321",
    "sg:postcode":"YO1 8RZ",
    "sg:province":"North Yorkshire",
    "wof:name":"Abbey National Plc",
    "wof:placetype":"venue"
},
  "geometry": {"coordinates":[-1.0816149712,53.9581069946],"type":"Point"}
}