{
  "type": "Feature",
  "properties": {
    "iso:country":"GB",
    "sg:address":"8 Parkstone Way",
    "sg:city":"Doncaster",
    "sg:classifiers":[
        {
            "category":"Building & Trades",
            "subcategory":"Cleaning & Sanitation",
            "type":"Services"
        }
    ],
    "sg:phone":"+44 1302 363339",
    "sg:postcode":"DN2 5RQ",
    "sg:province":"South Yorkshire",
    "sg:tags":[
        "dry",
        "control",
        "damp",
        "rot"
    ],
    "wof:name":"South Yorkshire Damp Proof Specialists",
    "wof:placetype":"venue"
},
  "geometry": {"coordinates":[-1.0921430588,53.5422554016],"type":"Point"}
}