{
  "type": "Feature",
  "properties": {
    "addr:full":"Woodwater Lane Exeter Devon EX2 5AW",
    "addr:postcode":"ex2 5aw",
    "addr:street":"Woodwater Lane",
    "iso:country":"GB",
    "sg:address":"Woodwater Lane",
    "sg:city":"Exeter",
    "sg:classifiers":[
        {
            "category":"Education",
            "subcategory":"School",
            "type":"Public Place"
        }
    ],
    "sg:phone":"+44 1392 274147",
    "sg:postcode":"EX2 5AW",
    "sg:province":"Devon",
    "sg:tags":[
        "local",
        "authority"
    ],
    "wof:name":"Walter Daw First School",
    "wof:placetype":"venue"
},
  "geometry": {"coordinates":[-3.492664,50.717419],"type":"Point"}
}