{
  "type": "Feature",
  "properties": {
    "addr:full":"367 Stourbridge Road Kidderminster Staffordshire DY10 2QE",
    "addr:housenumber":"367",
    "addr:postcode":"dy10 2qe",
    "addr:street":"Stourbridge Road",
    "iso:country":"GB",
    "sg:address":"367 Stourbridge Road",
    "sg:city":"Kidderminster",
    "sg:classifiers":[
        {
            "category":"Professional",
            "subcategory":"Engineering",
            "type":"Services"
        }
    ],
    "sg:phone":"+44 1562 824318",
    "sg:postcode":"DY10 2QE",
    "sg:province":"Staffordshire",
    "sg:tags":[
        "contractor",
        "electrical",
        "engineer"
    ],
    "wof:name":"Wilcox Bros",
    "wof:placetype":"venue"
},
  "geometry": {"coordinates":[-2.2400178909,52.3974380493],"type":"Point"}
}