{
  "type": "Feature",
  "properties": {
    "iso:country":"GB",
    "sg:address":"156 Frimley Road",
    "sg:city":"Camberley",
    "sg:classifiers":[
        {
            "category":"Autos & Motor Vehicles",
            "subcategory":"Fuel & Gas Station",
            "type":"Retail Goods"
        }
    ],
    "sg:phone":"+44 1276 692700",
    "sg:postcode":"GU15 2QL",
    "sg:province":"Berkshire",
    "sg:tags":[
        "hr",
        "petrol"
    ],
    "wof:name":"Frimley Road Service Station",
    "wof:placetype":"venue"
},
  "geometry": {"coordinates":[-0.754691,51.3246],"type":"Point"}
}