{
  "type": "Feature",
  "properties": {
    "iso:country":"GB",
    "sg:address":"St Ives Rugby Club Alexandra Road",
    "sg:city":"St Ives",
    "sg:classifiers":[
        {
            "category":"Sports & Exercise",
            "subcategory":"Gym",
            "type":"Entertainment"
        }
    ],
    "sg:phone":"+44 1736 798077",
    "sg:postcode":"TR26 1ER",
    "sg:province":"Cornwall",
    "sg:tags":[
        "fitness",
        "health",
        "centre"
    ],
    "wof:name":"Evolution Gymnasium",
    "wof:placetype":"venue"
},
  "geometry": {"coordinates":[-5.4857401848,50.2103614807],"type":"Point"}
}