{
  "type": "Feature",
  "properties": {
    "iso:country":"GB",
    "sg:address":"20 Gerretts Close, Bishopston",
    "sg:city":"Swansea",
    "sg:classifiers":[
        {
            "category":"Professional",
            "subcategory":"Computer Services",
            "type":"Services"
        }
    ],
    "sg:phone":"+44 1792 234043",
    "sg:postcode":"SA3 3HF",
    "sg:province":"Swansea",
    "sg:tags":[
        "system",
        "software"
    ],
    "wof:name":"Papergraphics Ltd.",
    "wof:placetype":"venue"
},
  "geometry": {"coordinates":[-4.047489,51.577145],"type":"Point"}
}