{
  "type": "Feature",
  "properties": {
    "iso:country":"GB",
    "sg:address":"Unit A, Heath Place, Ashgrove Industrial Park",
    "sg:city":"Bognor Regis",
    "sg:classifiers":[
        {
            "category":"Wholesale",
            "subcategory":"Metals & Minerals",
            "type":"Manufacturing & Wholesale Goods"
        }
    ],
    "sg:phone":"+44 1243 861421",
    "sg:postcode":"PO22 9SL",
    "sg:province":"West Sussex",
    "sg:tags":[
        "aluminium",
        "non-ferrous",
        "stockholder"
    ],
    "sg:website":"http://www.kedek.co.uk",
    "wof:name":"Kedek Ltd.",
    "wof:placetype":"venue"
},
  "geometry": {"coordinates":[-0.67398,50.801788],"type":"Point"}
}