{
  "type": "Feature",
  "properties": {
    "iso:country":"GB",
    "sg:address":"Broom Leys Farm, Broom Leys Road",
    "sg:city":"Coalville",
    "sg:classifiers":[
        {
            "category":"Farming",
            "subcategory":"Livestock Farm",
            "type":"Manufacturing & Wholesale Goods"
        }
    ],
    "sg:phone":"+44 1530 812992",
    "sg:postcode":"LE67 4DD",
    "sg:province":"Leicestershire",
    "sg:tags":[
        "others"
    ],
    "wof:name":"J J & L A Jarvis",
    "wof:placetype":"venue"
},
  "geometry": {"coordinates":[-1.372306,52.718784],"type":"Point"}
}