{
  "type": "Feature",
  "properties": {
    "addr:full":"London Road, Riverhead Sevenoaks Kent TN13 2DN",
    "addr:postcode":"tn13 2dn",
    "addr:street":"London Road",
    "iso:country":"GB",
    "sg:address":"London Road, Riverhead",
    "sg:city":"Sevenoaks",
    "sg:classifiers":[
        {
            "category":"Professional",
            "subcategory":"Engineering",
            "type":"Services"
        }
    ],
    "sg:phone":"+44 1732 451200",
    "sg:postcode":"TN13 2DN",
    "sg:province":"Kent",
    "wof:name":"Riverhead Toolmakers",
    "wof:placetype":"venue"
},
  "geometry": {"coordinates":[0.16919,51.285702],"type":"Point"}
}