{
  "type": "Feature",
  "properties": {
    "iso:country":"GB",
    "sg:address":"Unit 37,the Parker Ce, Mansfield Rd",
    "sg:city":"Derby",
    "sg:classifiers":[
        {
            "category":"Home & Garden",
            "subcategory":"Hardware",
            "type":"Retail Goods"
        }
    ],
    "sg:phone":"+44 1332 293949",
    "sg:postcode":"DE21 4SZ",
    "sg:province":"Derbyshire",
    "sg:tags":[
        "fixing",
        "nuts",
        "bolt"
    ],
    "wof:name":"Threadwell Plc",
    "wof:placetype":"venue"
},
  "geometry": {"coordinates":[-1.4674500227,52.9367218018],"type":"Point"}
}