{
  "type": "Feature",
  "properties": {
    "addr:full":"Old Hall Joinery Works, Bradley Road, Silsden Keighley North Yorkshire BD20 9LS",
    "addr:postcode":"bd20 9ls",
    "addr:street":"Bradley Road",
    "iso:country":"GB",
    "sg:address":"Old Hall Joinery Works, Bradley Road, Silsden",
    "sg:city":"Keighley",
    "sg:classifiers":[
        {
            "category":"Manufacturing",
            "subcategory":"Wood Products",
            "type":"Manufacturing & Wholesale Goods"
        },
        {
            "category":"Building & Trades",
            "subcategory":"Construction",
            "type":"Services"
        }
    ],
    "sg:phone":"+44 1535 655569",
    "sg:postcode":"BD20 9LS",
    "sg:province":"North Yorkshire",
    "sg:tags":[
        "joinery",
        "shaving",
        "sawmill",
        "manufacturer"
    ],
    "wof:name":"D W Wright & Son",
    "wof:placetype":"venue"
},
  "geometry": {"coordinates":[-1.997879982,53.9313545227],"type":"Point"}
}