{
  "type": "Feature",
  "properties": {
    "iso:country":"GB",
    "sg:address":"18 Walberswick Street",
    "sg:city":"London",
    "sg:classifiers":[
        {
            "category":"Retail",
            "subcategory":"Portrait Studio",
            "type":"Services"
        },
        {
            "category":"Communications",
            "subcategory":"Newspaper",
            "type":"Services"
        }
    ],
    "sg:postcode":"SW8 1XG",
    "sg:province":"Greater London",
    "sg:tags":[
        "photographer",
        "magazine",
        "commercial"
    ],
    "wof:name":"South China Morning Post",
    "wof:placetype":"venue"
},
  "geometry": {"coordinates":[-0.1225429997,51.4783439636],"type":"Point"}
}