{
  "type": "Feature",
  "properties": {
    "addr:full":"9a Cromwell Rd Banbury Oxfordshire OX16 0HJ",
    "addr:housenumber":"9a",
    "addr:postcode":"ox16 0hj",
    "addr:street":"Cromwell Rd",
    "iso:country":"GB",
    "sg:address":"9a Cromwell Rd",
    "sg:city":"Banbury",
    "sg:classifiers":[
        {
            "category":"Professional",
            "subcategory":"Business Services",
            "type":"Services"
        }
    ],
    "sg:postcode":"OX16 0HJ",
    "sg:province":"Oxfordshire",
    "sg:tags":[
        "import",
        "export",
        "agent"
    ],
    "wof:name":"Dawkes,Edmund P,",
    "wof:placetype":"venue"
},
  "geometry": {"coordinates":[-1.3522609472,52.0660247803],"type":"Point"}
}