{
  "type": "Feature",
  "properties": {
    "addr:full":"Stafford Rd, Newtown Walsall Staffordshire WS6 6BA",
    "addr:postcode":"ws6 6ba",
    "addr:street":"Stafford Rd",
    "iso:country":"GB",
    "sg:address":"Stafford Rd, Newtown",
    "sg:city":"Walsall",
    "sg:classifiers":[
        {
            "category":"Autos & Motor Vehicles",
            "subcategory":"Automobile Sales",
            "type":"Retail Goods"
        }
    ],
    "sg:phone":"+44 1922 711727",
    "sg:postcode":"WS6 6BA",
    "sg:province":"Staffordshire",
    "sg:tags":[
        "car",
        "specialist",
        "sales",
        "classic"
    ],
    "wof:name":"Paul A Depper",
    "wof:placetype":"venue"
},
  "geometry": {"coordinates":[-2.0104720592,52.6353797913],"type":"Point"}
}