{
  "type": "Feature",
  "properties": {
    "iso:country":"GB",
    "sg:address":"6 Golden Square",
    "sg:city":"Duns",
    "sg:classifiers":[
        {
            "category":"Retail",
            "subcategory":"Veterinary Services",
            "type":"Services"
        }
    ],
    "sg:phone":"+44 1361 883266",
    "sg:postcode":"TD11 3AW",
    "sg:province":"East Lothian",
    "sg:tags":[
        "surgeon"
    ],
    "wof:name":"Ian S Peek",
    "wof:placetype":"venue"
},
  "geometry": {"coordinates":[-2.341107,55.775776],"type":"Point"}
}