{
  "type": "Feature",
  "properties": {
    "addr:full":"430 West Bromwich Rd Walsall West Midlands WS5 4NS",
    "addr:housenumber":"430",
    "addr:postcode":"ws5 4ns",
    "addr:street":"West Bromwich Rd",
    "iso:country":"GB",
    "sg:address":"430 West Bromwich Rd",
    "sg:city":"Walsall",
    "sg:classifiers":[
        {
            "category":"Food & Beverages",
            "subcategory":"Meat & Fish",
            "type":"Retail Goods"
        }
    ],
    "sg:phone":"+44 1922 628075",
    "sg:postcode":"WS5 4NS",
    "sg:province":"West Midlands",
    "sg:tags":[
        "butcher"
    ],
    "wof:name":"G B Moore",
    "wof:placetype":"venue"
},
  "geometry": {"coordinates":[-1.975627,52.561852],"type":"Point"}
}