{
  "type": "Feature",
  "properties": {
    "iso:country":"GB",
    "sg:address":"Herbrandston Hall, Herbrandston",
    "sg:city":"Milford Haven",
    "sg:classifiers":[
        {
            "category":"Farming",
            "subcategory":"Livestock Farm",
            "type":"Manufacturing & Wholesale Goods"
        }
    ],
    "sg:phone":"+44 1646 694305",
    "sg:postcode":"SA73 3SS",
    "sg:province":"Pembrokeshire",
    "sg:tags":[
        "others"
    ],
    "wof:name":"J A Davies & Sons",
    "wof:placetype":"venue"
},
  "geometry": {"coordinates":[-5.086663,51.727978],"type":"Point"}
}