{
  "type": "Feature",
  "properties": {
    "addr:full":"1 Clifton Place, Cliftonville Margate Kent CT9 2BJ",
    "addr:housenumber":"1",
    "addr:postcode":"ct9 2bj",
    "addr:street":"Clifton Place;Margate",
    "iso:country":"GB",
    "sg:address":"1 Clifton Place, Cliftonville",
    "sg:city":"Margate",
    "sg:classifiers":[
        {
            "category":"Wholesale",
            "subcategory":"Construction Materials",
            "type":"Manufacturing & Wholesale Goods"
        }
    ],
    "sg:phone":"+44 1843 223621",
    "sg:postcode":"CT9 2BJ",
    "sg:province":"Kent",
    "sg:tags":[
        "merchant",
        "glass"
    ],
    "wof:name":"R G S Deanhouse",
    "wof:placetype":"venue"
},
  "geometry": {"coordinates":[1.389658,51.389477],"type":"Point"}
}