{
  "type": "Feature",
  "properties": {
    "iso:country":"GB",
    "sg:address":"11 Rectory Gro",
    "sg:city":"Leigh-on-sea",
    "sg:classifiers":[
        {
            "category":"Cafe",
            "type":"Food & Drink"
        }
    ],
    "sg:phone":"+44 1702 474713",
    "sg:postcode":"SS9 2HA",
    "sg:province":"Essex",
    "sg:tags":[
        "tea",
        "room"
    ],
    "wof:name":"Muffets of Leigh",
    "wof:placetype":"venue"
},
  "geometry": {"coordinates":[0.653997,51.542496],"type":"Point"}
}