{
  "type": "Feature",
  "properties": {
    "addr:full":"12 Ringwood Avenue, Aldridge Walsall Staffordshire WS9 0HZ",
    "addr:housenumber":"12",
    "addr:postcode":"ws9 0hz",
    "addr:street":"Ringwood Avenue",
    "iso:country":"GB",
    "sg:address":"12 Ringwood Avenue, Aldridge",
    "sg:city":"Walsall",
    "sg:classifiers":[
        {
            "category":"Recreation",
            "subcategory":"Dog Park",
            "type":"Entertainment"
        },
        {
            "category":"Retail",
            "subcategory":"Animal Services",
            "type":"Services"
        }
    ],
    "sg:phone":"+44 1922 459903",
    "sg:postcode":"WS9 0HZ",
    "sg:province":"Staffordshire",
    "sg:tags":[
        "training"
    ],
    "wof:name":"South Staffs Dog Training",
    "wof:placetype":"venue"
},
  "geometry": {"coordinates":[-1.9195760489,52.6004943848],"type":"Point"}
}