{
  "type": "Feature",
  "properties": {
    "iso:country":"GB",
    "sg:address":"Granslet Farm, Northend",
    "sg:city":"Leamington Spa",
    "sg:classifiers":[
        {
            "category":"Farming",
            "subcategory":"Farm",
            "type":"Manufacturing & Wholesale Goods"
        }
    ],
    "sg:phone":"+44 1295 770854",
    "sg:postcode":"CV33 0BA",
    "sg:province":"Warwickshire",
    "sg:tags":[
        "mixed",
        "crop"
    ],
    "wof:name":"Benjamin M Pick",
    "wof:placetype":"venue"
},
  "geometry": {"coordinates":[-1.4292999506,52.1698112488],"type":"Point"}
}