{
  "type": "Feature",
  "properties": {
    "addr:full":"20 Dalton Square Lancaster Lancashire LA1 1PL",
    "addr:housenumber":"20",
    "addr:postcode":"la1 1pl",
    "addr:street":"Dalton Square",
    "iso:country":"GB",
    "sg:address":"20 Dalton Square",
    "sg:city":"Lancaster",
    "sg:classifiers":[
        {
            "category":"Personal",
            "subcategory":"Nail Salon",
            "type":"Services"
        }
    ],
    "sg:postcode":"LA1 1PL",
    "sg:province":"Lancashire",
    "sg:tags":[
        "solarium",
        "tanning"
    ],
    "wof:name":"The Tanning Centre",
    "wof:placetype":"venue"
},
  "geometry": {"coordinates":[-2.7982530594,54.0481643677],"type":"Point"}
}