{
  "type": "Feature",
  "properties": {
    "addr:full":"Cardigan Delivery Office, Finchs Square Cardigan Ceredigion SA43 1BS",
    "addr:postcode":"sa43 1bs",
    "addr:street":"Finchs Square",
    "iso:country":"GB",
    "sg:address":"Cardigan Delivery Office, Finchs Square",
    "sg:city":"Cardigan",
    "sg:classifiers":[
        {
            "category":"Personal",
            "type":"Services"
        }
    ],
    "sg:phone":"+44 1239 612677",
    "sg:postcode":"SA43 1BS",
    "sg:province":"Ceredigion",
    "sg:tags":[
        "delivery"
    ],
    "wof:name":"Royal Mail",
    "wof:placetype":"venue"
},
  "geometry": {"coordinates":[-4.655044,52.086868],"type":"Point"}
}