{
  "type": "Feature",
  "properties": {
    "addr:full":"25 Carnbrook Road London Greater London SE3 8AE",
    "addr:housenumber":"25",
    "addr:postcode":"se3 8ae",
    "addr:street":"Carnbrook Road",
    "iso:country":"GB",
    "sg:address":"25 Carnbrook Road",
    "sg:city":"London",
    "sg:classifiers":[
        {
            "category":"Community Center",
            "subcategory":"Youth",
            "type":"Public Place"
        }
    ],
    "sg:phone":"+44 20 8856 0800",
    "sg:postcode":"SE3 8AE",
    "sg:province":"Greater London",
    "sg:tags":[
        "organisation",
        "centre"
    ],
    "wof:name":"Orchards Youth Club (The )",
    "wof:placetype":"venue"
},
  "geometry": {"coordinates":[0.038502,51.463779],"type":"Point"}
}