{
  "type": "Feature",
  "properties": {
    "iso:country":"GB",
    "sg:address":"591 Staniforth Road",
    "sg:city":"Sheffield",
    "sg:classifiers":[
        {
            "category":"Retail",
            "subcategory":"Auto Repair",
            "type":"Services"
        }
    ],
    "sg:phone":"+44 114 244 4441",
    "sg:postcode":"S9 4RD",
    "sg:province":"South Yorkshire",
    "sg:tags":[
        "modification",
        "garage"
    ],
    "wof:name":"Sheffield Car Clinic",
    "wof:placetype":"venue"
},
  "geometry": {"coordinates":[-1.415850997,53.3871192932],"type":"Point"}
}