{
  "type": "Feature",
  "properties": {
    "iso:country":"GB",
    "sg:address":"Green Duer, Roman Landing, West Wittering",
    "sg:city":"Chichester",
    "sg:classifiers":[
        {
            "category":"Real Estate",
            "subcategory":"Surveying",
            "type":"Services"
        }
    ],
    "sg:postcode":"PO20 8AL",
    "sg:province":"West Sussex",
    "sg:tags":[
        "surveyor",
        "valuer"
    ],
    "wof:name":"Colin Kaye",
    "wof:placetype":"venue"
},
  "geometry": {"coordinates":[-0.893624,50.781296],"type":"Point"}
}