{
  "type": "Feature",
  "properties": {
    "addr:full":"28 Basil Street London Greater London SW3 1AS",
    "addr:housenumber":"28",
    "addr:postcode":"sw3 1as",
    "addr:street":"Basil Street",
    "iso:country":"GB",
    "sg:address":"28 Basil Street",
    "sg:city":"London",
    "sg:classifiers":[
        {
            "category":"Travel",
            "subcategory":"Hotels & Motels",
            "type":"Entertainment"
        }
    ],
    "sg:phone":"+44 20 7589 6286",
    "sg:postcode":"SW3 1AS",
    "sg:province":"Greater London",
    "wof:name":"L'Hotel",
    "wof:placetype":"venue"
},
  "geometry": {"coordinates":[-0.1607690006,51.5007286072],"type":"Point"}
}