{
  "type": "Feature",
  "properties": {
    "addr:full":"6 Brunswick Park Gardens London Greater London N11 1EJ",
    "addr:housenumber":"6",
    "addr:postcode":"n11 1ej",
    "addr:street":"Brunswick Park Gardens",
    "iso:country":"GB",
    "sg:address":"6 Brunswick Park Gardens",
    "sg:city":"London",
    "sg:classifiers":[
        {
            "category":"Retail",
            "subcategory":"Repair Shop",
            "type":"Services"
        }
    ],
    "sg:phone":"+44 20 8368 4721",
    "sg:postcode":"N11 1EJ",
    "sg:province":"Greater London",
    "sg:tags":[
        "maintenance"
    ],
    "wof:name":"Network Trades Services Ltd.",
    "wof:placetype":"venue"
},
  "geometry": {"coordinates":[-0.1496939957,51.6272163391],"type":"Point"}
}