{
  "type": "Feature",
  "properties": {
    "iso:country":"GB",
    "sg:address":"Unit 3b, Lion Barn Industrial",
    "sg:city":"Ipswich",
    "sg:classifiers":[
        {
            "category":"Manufacturing",
            "subcategory":"Metals",
            "type":"Manufacturing & Wholesale Goods"
        }
    ],
    "sg:postcode":"IP6 8NZ",
    "sg:province":"Suffolk",
    "sg:tags":[
        "work",
        "sheet"
    ],
    "wof:name":"Pro-Metal Manufacturing Ltd",
    "wof:placetype":"venue"
},
  "geometry": {"coordinates":[1.058934,52.149494],"type":"Point"}
}