{
  "type": "Feature",
  "properties": {
    "addr:full":"Lady Bray Farm, Kinsbourne Green Harpenden Hertfordshire AL5 3PZ",
    "addr:postcode":"al5 3pz",
    "addr:street":"Lady;Kinsbourne Green",
    "iso:country":"GB",
    "sg:address":"Lady Bray Farm, Kinsbourne Green",
    "sg:city":"Harpenden",
    "sg:classifiers":[
        {
            "category":"Real Estate",
            "subcategory":"Developer",
            "type":"Services"
        },
        {
            "category":"Building & Trades",
            "subcategory":"Construction",
            "type":"Services"
        }
    ],
    "sg:phone":"+44 1582 462246",
    "sg:postcode":"AL5 3PZ",
    "sg:province":"Hertfordshire",
    "sg:tags":[
        "residential",
        "builder",
        "property"
    ],
    "wof:name":"John Catton Homes Ltd.",
    "wof:placetype":"venue"
},
  "geometry": {"coordinates":[-0.3565590084,51.8162155151],"type":"Point"}
}