{
  "type": "Feature",
  "properties": {
    "addr:full":"72-74 New Road Side Leeds West Yorkshire LS18 4NG",
    "addr:housenumber":"72-74",
    "addr:postcode":"ls18 4ng",
    "addr:street":"New Road Side Leeds West",
    "iso:country":"GB",
    "sg:address":"72-74 New Road Side",
    "sg:city":"Leeds",
    "sg:classifiers":[
        {
            "category":"Home & Garden",
            "subcategory":"Hardware",
            "type":"Retail Goods"
        }
    ],
    "sg:postcode":"LS18 4NG",
    "sg:province":"West Yorkshire",
    "sg:tags":[
        "retailer",
        "lighting"
    ],
    "wof:name":"Electrical Replacement Parts",
    "wof:placetype":"venue"
},
  "geometry": {"coordinates":[-1.639379,53.83736],"type":"Point"}
}