{
  "type": "Feature",
  "properties": {
    "addr:full":"Ellabank, Buccleuch Street Hawick Cumbria TD9 0HW",
    "addr:postcode":"td9 0hw",
    "addr:street":"Buccleuch Street",
    "iso:country":"GB",
    "sg:address":"Ellabank, Buccleuch Street",
    "sg:city":"Hawick",
    "sg:classifiers":[
        {
            "category":"Building & Trades",
            "subcategory":"Construction",
            "type":"Services"
        }
    ],
    "sg:phone":"+44 1450 374189",
    "sg:postcode":"TD9 0HW",
    "sg:province":"Cumbria",
    "sg:tags":[
        "decorator",
        "painter"
    ],
    "wof:name":"J D Macleod",
    "wof:placetype":"venue"
},
  "geometry": {"coordinates":[-2.790538,55.421329],"type":"Point"}
}