{
  "type": "Feature",
  "properties": {
    "iso:country":"GB",
    "sg:address":"6 Burrow Street",
    "sg:city":"South Shields",
    "sg:classifiers":[
        {
            "category":"Real Estate",
            "subcategory":"Real Estate Agent",
            "type":"Services"
        }
    ],
    "sg:phone":"+44 191 427 6767",
    "sg:postcode":"NE33 1PP",
    "sg:province":"Tyne and Wear",
    "wof:name":"Andrew McLean",
    "wof:placetype":"venue"
},
  "geometry": {"coordinates":[-1.431796,54.997318],"type":"Point"}
}