{
  "type": "Feature",
  "properties": {
    "addr:full":"West Bank House School Street, Honeybourne, Evesham Gloucestershire WR11 7PL",
    "addr:postcode":"wr11 7pl",
    "addr:street":"West;School Street",
    "iso:country":"GB",
    "sg:address":"West Bank House School Street, Honeybourne,",
    "sg:city":"Evesham",
    "sg:classifiers":[
        {
            "category":"Communications",
            "type":"Services"
        }
    ],
    "sg:postcode":"WR11 7PL",
    "sg:province":"Gloucestershire",
    "sg:tags":[
        "audio-visual"
    ],
    "wof:name":"Ochreon Productions Ltd",
    "wof:placetype":"venue"
},
  "geometry": {"coordinates":[-1.8366730213,52.0923423767],"type":"Point"}
}