{
  "type": "Feature",
  "properties": {
    "addr:full":"93 Chesterfield Rd Sheffield Derbyshire S8 0RN",
    "addr:housenumber":"93",
    "addr:postcode":"s8 0rn",
    "addr:street":"Chesterfield Rd",
    "iso:country":"GB",
    "sg:address":"93 Chesterfield Rd",
    "sg:city":"Sheffield",
    "sg:classifiers":[
        {
            "category":"Professional",
            "subcategory":"Computer Services",
            "type":"Services"
        }
    ],
    "sg:phone":"+44 114 255 5545",
    "sg:postcode":"S8 0RN",
    "sg:province":"Derbyshire",
    "sg:tags":[
        "system",
        "software"
    ],
    "wof:name":"Activity Software",
    "wof:placetype":"venue"
},
  "geometry": {"coordinates":[-1.4760869741,53.3572883606],"type":"Point"}
}