{
  "type": "Feature",
  "properties": {
    "addr:full":"Universal Site, Commercial St Caerphilly Caerphilly CF83 4GY",
    "addr:postcode":"cf83 4gy",
    "addr:street":"Commercial St",
    "iso:country":"GB",
    "sg:address":"Universal Site, Commercial St",
    "sg:city":"Caerphilly",
    "sg:classifiers":[
        {
            "category":"Bus Charters",
            "type":"Transportation"
        }
    ],
    "sg:phone":"+44 29 2083 0434",
    "sg:postcode":"CF83 4GY",
    "sg:province":"Caerphilly",
    "sg:tags":[
        "hire",
        "coach"
    ],
    "wof:name":"Ferris Holidays & Coaches",
    "wof:placetype":"venue"
},
  "geometry": {"coordinates":[-3.217728,51.576588],"type":"Point"}
}