{
  "type": "Feature",
  "properties": {
    "iso:country":"GB",
    "sg:address":"88 Spruce Avenue",
    "sg:city":"Waterlooville",
    "sg:classifiers":[
        {
            "category":"Building & Trades",
            "subcategory":"Construction",
            "type":"Services"
        }
    ],
    "sg:postcode":"PO7 8HJ",
    "sg:province":"Hampshire",
    "sg:tags":[
        "bricklaying"
    ],
    "wof:name":"D M  Lloyd",
    "wof:placetype":"venue"
},
  "geometry": {"coordinates":[-1.017034,50.875786],"type":"Point"}
}