{
  "type": "Feature",
  "properties": {
    "addr:full":"116 Prestbury Drive Warminster Somerset BA12 9LE",
    "addr:housenumber":"116",
    "addr:postcode":"ba12 9le",
    "addr:street":"Prestbury Drive",
    "iso:country":"GB",
    "sg:address":"116 Prestbury Drive",
    "sg:city":"Warminster",
    "sg:classifiers":[
        {
            "category":"Wholesale",
            "subcategory":"Groceries",
            "type":"Manufacturing & Wholesale Goods"
        }
    ],
    "sg:phone":"+44 1985 211357",
    "sg:postcode":"BA12 9LE",
    "sg:province":"Somerset",
    "sg:tags":[
        "food",
        "supplier",
        "drink"
    ],
    "wof:name":"Heron Coffee & Vending Systems",
    "wof:placetype":"venue"
},
  "geometry": {"coordinates":[-2.1668300629,51.1974487305],"type":"Point"}
}