{
  "type": "Feature",
  "properties": {
    "addr:full":"70 Guernsey Gardens Wickford Essex SS11 7BB",
    "addr:housenumber":"70",
    "addr:postcode":"ss11 7bb",
    "addr:street":"Guernsey Gardens",
    "iso:country":"GB",
    "sg:address":"70 Guernsey Gardens",
    "sg:city":"Wickford",
    "sg:classifiers":[
        {
            "category":"Health Services",
            "subcategory":"Health Practitioner",
            "type":"Services"
        }
    ],
    "sg:phone":"+44 1268 458660",
    "sg:postcode":"SS11 7BB",
    "sg:province":"Essex",
    "sg:tags":[
        "osteopath"
    ],
    "wof:name":"B Calvert-Painter",
    "wof:placetype":"venue"
},
  "geometry": {"coordinates":[0.5195199847,51.6202507019],"type":"Point"}
}