{
  "type": "Feature",
  "properties": {
    "addr:full":"17-20 New Road Kidderminster Staffordshire DY10 1AF",
    "addr:housenumber":"17-20",
    "addr:postcode":"dy10 1af",
    "addr:street":"New Road",
    "iso:country":"GB",
    "sg:address":"17-20 New Road",
    "sg:city":"Kidderminster",
    "sg:classifiers":[
        {
            "category":"Home & Garden",
            "subcategory":"Hardware",
            "type":"Retail Goods"
        }
    ],
    "sg:postcode":"DY10 1AF",
    "sg:province":"Staffordshire",
    "wof:name":"M B M Garden Supplies",
    "wof:placetype":"venue"
},
  "geometry": {"coordinates":[-2.2475790977,52.3852500916],"type":"Point"}
}