{
  "type": "Feature",
  "properties": {
    "addr:full":"19 Harrow Road Leighton Buzzard Bedfordshire LU7 8UF",
    "addr:housenumber":"19",
    "addr:postcode":"lu7 8uf",
    "addr:street":"Harrow Road",
    "iso:country":"GB",
    "sg:address":"19 Harrow Road",
    "sg:city":"Leighton Buzzard",
    "sg:classifiers":[
        {
            "category":"Farming",
            "subcategory":"Farm",
            "type":"Manufacturing & Wholesale Goods"
        }
    ],
    "sg:phone":"+44 1525 376305",
    "sg:postcode":"LU7 8UF",
    "sg:province":"Bedfordshire",
    "sg:tags":[
        "agricultural"
    ],
    "wof:name":"Griffin Lighting",
    "wof:placetype":"venue"
},
  "geometry": {"coordinates":[-0.650352,51.912884],"type":"Point"}
}