{
  "type": "Feature",
  "properties": {
    "addr:full":"38 Church Street Runcorn Cheshire WA7 1LR",
    "addr:housenumber":"38",
    "addr:postcode":"wa7 1lr",
    "addr:street":"Church Street",
    "iso:country":"GB",
    "sg:address":"38 Church Street",
    "sg:city":"Runcorn",
    "sg:classifiers":[
        {
            "category":"Professional",
            "subcategory":"Employment Agencies",
            "type":"Services"
        }
    ],
    "sg:phone":"+44 1928 576644",
    "sg:postcode":"WA7 1LR",
    "sg:province":"Cheshire",
    "sg:tags":[
        "consultant"
    ],
    "wof:name":"M D A Work Services Ltd.",
    "wof:placetype":"venue"
},
  "geometry": {"coordinates":[-2.7328529358,53.3426551819],"type":"Point"}
}