{
  "type": "Feature",
  "properties": {
    "addr:full":"Dale Bridge Farmhouse, West Rasen Market Rasen Lincolnshire LN8 3NU",
    "addr:housenumber":"rasen",
    "addr:postcode":"ln8 3nu",
    "addr:street":"Dale;West",
    "iso:country":"GB",
    "sg:address":"Dale Bridge Farmhouse, West Rasen",
    "sg:city":"Market Rasen",
    "sg:classifiers":[
        {
            "category":"Manufacturing",
            "subcategory":"Motor Vehicles & Parts",
            "type":"Manufacturing & Wholesale Goods"
        }
    ],
    "sg:postcode":"LN8 3NU",
    "sg:province":"Lincolnshire",
    "sg:tags":[
        "engineer",
        "handling",
        "mechanical"
    ],
    "wof:name":"Mechanical Engineering Services Ltd.",
    "wof:placetype":"venue"
},
  "geometry": {"coordinates":[-0.3330680132,53.3867874146],"type":"Point"}
}