{
  "type": "Feature",
  "properties": {
    "addr:full":"347 Skircoat Green Rd Halifax West Yorkshire HX3 0LX",
    "addr:housenumber":"347",
    "addr:postcode":"hx3 0lx",
    "addr:street":"Skircoat Green Rd",
    "iso:country":"GB",
    "sg:address":"347 Skircoat Green Rd",
    "sg:city":"Halifax",
    "sg:classifiers":[
        {
            "category":"Food & Beverages",
            "subcategory":"Fruits & Vegetables",
            "type":"Retail Goods"
        }
    ],
    "sg:phone":"+44 1422 353571",
    "sg:postcode":"HX3 0LX",
    "sg:province":"West Yorkshire",
    "sg:tags":[
        "greengrocer"
    ],
    "wof:name":"Skircoat Greens",
    "wof:placetype":"venue"
},
  "geometry": {"coordinates":[-1.863083,53.70377],"type":"Point"}
}