{
  "type": "Feature",
  "properties": {
    "addr:full":"Double Row, Seaton Delaval Whitley Bay Northumberland NE25 0PR",
    "addr:postcode":"ne25 0pr",
    "addr:street":"Double Row",
    "iso:country":"GB",
    "sg:address":"Double Row, Seaton Delaval",
    "sg:city":"Whitley Bay",
    "sg:classifiers":[
        {
            "category":"Home & Garden",
            "subcategory":"Furniture",
            "type":"Retail Goods"
        }
    ],
    "sg:phone":"+44 191 237 1303",
    "sg:postcode":"NE25 0PR",
    "sg:province":"Northumberland",
    "wof:name":"Delcor Furniture Ltd.",
    "wof:placetype":"venue"
},
  "geometry": {"coordinates":[-1.5348379612,55.0779266357],"type":"Point"}
}