{
  "type": "Feature",
  "properties": {
    "iso:country":"GB",
    "sg:address":"1 Pickering",
    "sg:city":"Bracknell",
    "sg:classifiers":[
        {
            "category":"Building & Trades",
            "subcategory":"Construction",
            "type":"Services"
        }
    ],
    "sg:phone":"+44 20 8845 0300",
    "sg:postcode":"RG12 7EA",
    "sg:province":"Berkshire",
    "sg:tags":[
        "roofing"
    ],
    "wof:name":"Mark Harvey",
    "wof:placetype":"venue"
},
  "geometry": {"coordinates":[-0.759582,51.404968],"type":"Point"}
}