{
  "type": "Feature",
  "properties": {
    "addr:full":"Loppingdales, Gaunts End Bishops Stortford Essex CM22 6DR",
    "addr:postcode":"cm22 6dr",
    "addr:street":"Gaunts End",
    "iso:country":"GB",
    "sg:address":"Loppingdales, Gaunts End",
    "sg:city":"Bishops Stortford",
    "sg:classifiers":[
        {
            "category":"Building & Trades",
            "subcategory":"Equipment Rental",
            "type":"Services"
        }
    ],
    "sg:phone":"+44 1279 647272",
    "sg:postcode":"CM22 6DR",
    "sg:province":"Essex",
    "sg:tags":[
        "plant",
        "machinery"
    ],
    "wof:name":"E Corr Plant Hire",
    "wof:placetype":"venue"
},
  "geometry": {"coordinates":[0.16195,51.87233],"type":"Point"}
}