{
  "type": "Feature",
  "properties": {
    "addr:full":"55 Bute Street Luton Bedfordshire LU1 2EP",
    "addr:housenumber":"55",
    "addr:postcode":"lu1 2ep",
    "addr:street":"Bute Street",
    "iso:country":"GB",
    "sg:address":"55 Bute Street",
    "sg:city":"Luton",
    "sg:classifiers":[
        {
            "category":"Bars & Pubs",
            "type":"Food & Drink"
        }
    ],
    "sg:phone":"+44 1582 720688",
    "sg:postcode":"LU1 2EP",
    "sg:province":"Bedfordshire",
    "sg:tags":[
        "pubs",
        "inn"
    ],
    "wof:name":"The Coopers Arms",
    "wof:placetype":"venue"
},
  "geometry": {"coordinates":[-0.4151670039,51.8807182312],"type":"Point"}
}