{
  "type": "Feature",
  "properties": {
    "addr:full":"Unit 4-6 Kym Road, Bicton Industrial Park Huntingdon Bedfordshire PE28 0EY",
    "addr:housenumber":"unit 4-6",
    "addr:postcode":"pe28 0ey",
    "addr:street":"Kym Road",
    "iso:country":"GB",
    "sg:address":"Unit 4-6 Kym Road, Bicton Industrial Park",
    "sg:city":"Huntingdon",
    "sg:classifiers":[
        {
            "category":"Professional",
            "subcategory":"Printing & Photocopies",
            "type":"Services"
        }
    ],
    "sg:phone":"+44 1480 861429",
    "sg:postcode":"PE28 0EY",
    "sg:province":"Bedfordshire",
    "sg:tags":[
        "printer"
    ],
    "wof:name":"Lockwood Lithographics",
    "wof:placetype":"venue"
},
  "geometry": {"coordinates":[-0.380299,52.31152],"type":"Point"}
}