{
  "type": "Feature",
  "properties": {
    "addr:full":"35 Carnaby Street London Greater London W1F 7DP",
    "addr:housenumber":"35",
    "addr:postcode":"w1f 7dp",
    "addr:street":"Carnaby Street",
    "iso:country":"GB",
    "sg:address":"35 Carnaby Street",
    "sg:city":"London",
    "sg:classifiers":[
        {
            "category":"Shopping",
            "subcategory":"Gifts & Souvenirs",
            "type":"Retail Goods"
        }
    ],
    "sg:phone":"+44 20 7437 6009",
    "sg:postcode":"W1F 7DP",
    "sg:province":"Greater London",
    "sg:tags":[
        "shop"
    ],
    "wof:name":"Gear Giftware",
    "wof:placetype":"venue"
},
  "geometry": {"coordinates":[-0.139262,51.513489],"type":"Point"}
}