{
  "type": "Feature",
  "properties": {
    "iso:country":"GB",
    "sg:address":"P O Box 61, Minster On Sea",
    "sg:city":"Sheerness",
    "sg:classifiers":[
        {
            "category":"Organizations",
            "subcategory":"Community Association",
            "type":"Services"
        }
    ],
    "sg:postcode":"ME12 3AF",
    "sg:province":"Kent",
    "sg:tags":[
        "relation",
        "public"
    ],
    "wof:name":"Maximum Publicity Consultants",
    "wof:placetype":"venue"
},
  "geometry": {"coordinates":[0.764665,51.43885],"type":"Point"}
}