{
  "type": "Feature",
  "properties": {
    "addr:full":"27 Swift Gardens Southampton Hampshire SO19 9FQ",
    "addr:housenumber":"27",
    "addr:postcode":"so19 9fq",
    "addr:street":"Swift Gardens",
    "iso:country":"GB",
    "sg:address":"27 Swift Gardens",
    "sg:city":"Southampton",
    "sg:classifiers":[
        {
            "category":"Shopping",
            "subcategory":"Party Supplies",
            "type":"Retail Goods"
        }
    ],
    "sg:phone":"+44 23 8036 7401",
    "sg:postcode":"SO19 9FQ",
    "sg:province":"Hampshire",
    "sg:tags":[
        "inflatables",
        "bouncy",
        "castle"
    ],
    "wof:name":"Activity Times",
    "wof:placetype":"venue"
},
  "geometry": {"coordinates":[-1.377029,50.890999],"type":"Point"}
}