{
  "type": "Feature",
  "properties": {
    "iso:country":"GB",
    "sg:address":"37 Trinity Street",
    "sg:city":"Cambridge",
    "sg:classifiers":[
        {
            "category":"Shopping",
            "subcategory":"Clothing, Apparel, & Fashions",
            "type":"Retail Goods"
        }
    ],
    "sg:phone":"+44 1223 356734",
    "sg:postcode":"CB2 1TB",
    "sg:province":"Cambridgeshire",
    "sg:tags":[
        "equipment",
        "outdoor",
        "clothing",
        "wear",
        "leisure"
    ],
    "wof:name":"Rohan Designs Ltd",
    "wof:placetype":"venue"
},
  "geometry": {"coordinates":[0.1181999967,52.2064476013],"type":"Point"}
}