{
  "type": "Feature",
  "properties": {
    "addr:full":"93 Stechford Rd Birmingham West Midlands B34 6AB",
    "addr:housenumber":"93",
    "addr:postcode":"6ab",
    "addr:street":"Stechford Rd",
    "iso:country":"GB",
    "sg:address":"93 Stechford Rd",
    "sg:city":"Birmingham",
    "sg:classifiers":[
        {
            "category":"Utilities",
            "subcategory":"Fuel Oil & Lpg",
            "type":"Services"
        }
    ],
    "sg:phone":"+44 121 783 4215",
    "sg:postcode":"B34 6AB",
    "sg:province":"West Midlands",
    "wof:name":"W.J Fenner & Son",
    "wof:placetype":"venue"
},
  "geometry": {"coordinates":[-1.811585,52.491673],"type":"Point"}
}