{
  "type": "Feature",
  "properties": {
    "addr:full":"Rectory Lane Guisborough North Yorkshire TS14 7DJ",
    "addr:postcode":"ts14 7dj",
    "addr:street":"Rectory Lane",
    "iso:country":"GB",
    "sg:address":"Rectory Lane",
    "sg:city":"Guisborough",
    "sg:classifiers":[
        {
            "category":"Community Center",
            "type":"Public Place"
        }
    ],
    "sg:postcode":"TS14 7DJ",
    "sg:province":"North Yorkshire",
    "sg:tags":[
        "centre"
    ],
    "wof:name":"Guisborough Community Resource Centre",
    "wof:placetype":"venue"
},
  "geometry": {"coordinates":[-1.057124,54.532295],"type":"Point"}
}