{
  "type": "Feature",
  "properties": {
    "addr:full":"120 Sydney Street Glasgow Glasgow City G31 1JF",
    "addr:housenumber":"120",
    "addr:postcode":"g31 1jf",
    "addr:street":"Sydney Street",
    "iso:country":"GB",
    "sg:address":"120 Sydney Street",
    "sg:city":"Glasgow",
    "sg:classifiers":[
        {
            "category":"Manufacturing",
            "subcategory":"Apparel",
            "type":"Manufacturing & Wholesale Goods"
        }
    ],
    "sg:phone":"+44 141 554 5161",
    "sg:postcode":"G31 1JF",
    "sg:province":"Glasgow City",
    "sg:tags":[
        "garment",
        "designer"
    ],
    "wof:name":"F W Design",
    "wof:placetype":"venue"
},
  "geometry": {"coordinates":[-4.2299938202,55.8586730957],"type":"Point"}
}