{
  "type": "Feature",
  "properties": {
    "addr:full":"56a Westgate Hunstanton Norfolk PE36 5EL",
    "addr:housenumber":"56a",
    "addr:postcode":"pe36 5el",
    "addr:street":"Westgate",
    "iso:country":"GB",
    "sg:address":"56a Westgate",
    "sg:city":"Hunstanton",
    "sg:classifiers":[
        {
            "category":"Shopping",
            "subcategory":"Bicycles & Sporting Goods",
            "type":"Retail Goods"
        }
    ],
    "sg:phone":"+44 1485 532271",
    "sg:postcode":"PE36 5EL",
    "sg:province":"Norfolk",
    "sg:tags":[
        "riding",
        "saddlery",
        "wear"
    ],
    "wof:name":"The Saddle Room",
    "wof:placetype":"venue"
},
  "geometry": {"coordinates":[0.490299,52.938847],"type":"Point"}
}