{
  "type": "Feature",
  "properties": {
    "addr:full":"34 Broomsleigh Street London Greater London NW6 1QH",
    "addr:housenumber":"34",
    "addr:postcode":"nw6 1qh",
    "addr:street":"Broomsleigh Street",
    "iso:country":"GB",
    "sg:address":"34 Broomsleigh Street",
    "sg:city":"London",
    "sg:classifiers":[
        {
            "category":"Communications",
            "type":"Services"
        }
    ],
    "sg:postcode":"NW6 1QH",
    "sg:province":"Greater London",
    "sg:tags":[
        "broadcasting"
    ],
    "wof:name":"Track Record",
    "wof:placetype":"venue"
},
  "geometry": {"coordinates":[-0.198439,51.549889],"type":"Point"}
}