{
  "type": "Feature",
  "properties": {
    "addr:full":"63 Churchill Crescent Thame Buckinghamshire OX9 3JW",
    "addr:housenumber":"63",
    "addr:postcode":"ox9 3jw",
    "addr:street":"Churchill Crescent",
    "iso:country":"GB",
    "sg:address":"63 Churchill Crescent",
    "sg:city":"Thame",
    "sg:classifiers":[
        {
            "category":"Building & Trades",
            "subcategory":"Construction",
            "type":"Services"
        }
    ],
    "sg:phone":"+44 1844 216014",
    "sg:postcode":"OX9 3JW",
    "sg:province":"Buckinghamshire",
    "sg:tags":[
        "builder"
    ],
    "wof:name":"Christopher D Martin",
    "wof:placetype":"venue"
},
  "geometry": {"coordinates":[-0.966268,51.745934],"type":"Point"}
}