{
  "type": "Feature",
  "properties": {
    "addr:full":"7 Linden Gardens, Paddington London Greater London W2 4HA",
    "addr:housenumber":"7",
    "addr:postcode":"w2 4ha",
    "addr:street":"Linden Gardens",
    "iso:country":"GB",
    "sg:address":"7 Linden Gardens, Paddington",
    "sg:city":"London",
    "sg:classifiers":[
        {
            "category":"Recreation",
            "type":"Entertainment"
        }
    ],
    "sg:postcode":"W2 4HA",
    "sg:province":"Greater London",
    "sg:tags":[
        "corporate",
        "leisure"
    ],
    "wof:name":"Cybernetic Productions Ltd.",
    "wof:placetype":"venue"
},
  "geometry": {"coordinates":[-0.194054,51.509823],"type":"Point"}
}