{
  "type": "Feature",
  "properties": {
    "iso:country":"GB",
    "sg:address":"5 Whinbush Road, Barton Le Clay",
    "sg:city":"Hitchin",
    "sg:classifiers":[
        {
            "category":"Shopping",
            "subcategory":"Shoes",
            "type":"Retail Goods"
        }
    ],
    "sg:phone":"+44 1462 451452",
    "sg:postcode":"SG5 1PL",
    "sg:province":"Bedfordshire",
    "wof:name":"Hitchin Shoe Repairs Ltd.",
    "wof:placetype":"venue"
},
  "geometry": {"coordinates":[-0.274116993,51.9494132996],"type":"Point"}
}