{
  "type": "Feature",
  "properties": {
    "addr:full":"1-3 Albion St Derby Derbyshire DE1 2PR",
    "addr:housenumber":"1-3",
    "addr:postcode":"de1 2pr",
    "addr:street":"Albion St",
    "iso:country":"GB",
    "sg:address":"1-3 Albion St",
    "sg:city":"Derby",
    "sg:classifiers":[
        {
            "category":"Shopping",
            "subcategory":"Baby Store",
            "type":"Retail Goods"
        }
    ],
    "sg:postcode":"DE1 2PR",
    "sg:province":"Derbyshire",
    "sg:tags":[
        "nursery",
        "accessory"
    ],
    "wof:name":"Mothercare (U K) Ltd",
    "wof:placetype":"venue"
},
  "geometry": {"coordinates":[-1.4743059874,52.9212913513],"type":"Point"}
}