{
  "type": "Feature",
  "properties": {
    "iso:country":"GB",
    "sg:address":"18 Byron Drive",
    "sg:city":"Newport Pagnell",
    "sg:classifiers":[
        {
            "category":"Building & Trades",
            "subcategory":"Plumbing",
            "type":"Services"
        }
    ],
    "sg:phone":"+44 1908 615911",
    "sg:postcode":"MK16 8DX",
    "sg:province":"Buckinghamshire",
    "sg:tags":[
        "central",
        "installation",
        "heating",
        "servicing",
        "system"
    ],
    "wof:name":"K & J HEATING CONTRACTORS",
    "wof:placetype":"venue"
},
  "geometry": {"coordinates":[-0.74306,52.084843],"type":"Point"}
}