{
  "type": "Feature",
  "properties": {
    "iso:country":"GB",
    "sg:address":"The Elms, Worcester Rd, Hackmans Gate, Clent",
    "sg:city":"Stourbridge",
    "sg:classifiers":[
        {
            "category":"Professional",
            "subcategory":"Accounting & Tax Preparation",
            "type":"Services"
        }
    ],
    "sg:postcode":"DY9 0ER",
    "sg:province":"West Midlands",
    "sg:tags":[
        "accountant"
    ],
    "wof:name":"Herbert,Graham H,",
    "wof:placetype":"venue"
},
  "geometry": {"coordinates":[-2.1526319981,52.4074440002],"type":"Point"}
}