{
  "type": "Feature",
  "properties": {
    "addr:full":"74 Brookfield Road Aldershot Hampshire GU12 4UR",
    "addr:housenumber":"74",
    "addr:postcode":"gu12 4ur",
    "addr:street":"Brookfield Road",
    "iso:country":"GB",
    "sg:address":"74 Brookfield Road",
    "sg:city":"Aldershot",
    "sg:classifiers":[
        {
            "category":"Retail",
            "subcategory":"Driving School",
            "type":"Services"
        }
    ],
    "sg:postcode":"GU12 4UR",
    "sg:province":"Hampshire",
    "wof:name":"Regent School of Motoring",
    "wof:placetype":"venue"
},
  "geometry": {"coordinates":[-0.731469,51.252388],"type":"Point"}
}