{
  "type": "Feature",
  "properties": {
    "addr:full":"29 Gaskell Street, Stockton Heath Warrington Cheshire WA4 2UN",
    "addr:housenumber":"29",
    "addr:postcode":"wa4 2un",
    "addr:street":"Gaskell Street",
    "iso:country":"GB",
    "sg:address":"29 Gaskell Street, Stockton Heath",
    "sg:city":"Warrington",
    "sg:classifiers":[
        {
            "category":"Shopping",
            "subcategory":"Computers & Home Electronics",
            "type":"Retail Goods"
        }
    ],
    "sg:postcode":"WA4 2UN",
    "sg:province":"Cheshire",
    "sg:tags":[
        "hi-fi",
        "centre"
    ],
    "wof:name":"Chris Brooks Audio",
    "wof:placetype":"venue"
},
  "geometry": {"coordinates":[-2.580813,53.372372],"type":"Point"}
}