{
  "type": "Feature",
  "properties": {
    "addr:full":"19 Hartley Court Gardens Cranbrook Kent TN17 3QY",
    "addr:housenumber":"19",
    "addr:postcode":"tn17 3qy",
    "addr:street":"Hartley Court Gardens Cranbrook",
    "iso:country":"GB",
    "sg:address":"19 Hartley Court Gardens",
    "sg:city":"Cranbrook",
    "sg:classifiers":[
        {
            "category":"Professional",
            "subcategory":"Research",
            "type":"Services"
        }
    ],
    "sg:postcode":"TN17 3QY",
    "sg:province":"Kent",
    "sg:tags":[
        "market"
    ],
    "wof:name":"Graham Consultancy",
    "wof:placetype":"venue"
},
  "geometry": {"coordinates":[0.512657,51.087524],"type":"Point"}
}