{
  "type": "Feature",
  "properties": {
    "iso:country":"GB",
    "sg:address":"3 Imperial Square",
    "sg:city":"Cheltenham",
    "sg:classifiers":[
        {
            "category":"Professional",
            "subcategory":"Employment Agencies",
            "type":"Services"
        }
    ],
    "sg:phone":"+44 1242 521358",
    "sg:postcode":"GL50 1QB",
    "sg:province":"Gloucestershire",
    "sg:tags":[
        "consultant"
    ],
    "wof:name":"Datasource Computer Employment Ltd.",
    "wof:placetype":"venue"
},
  "geometry": {"coordinates":[-2.077596,51.897839],"type":"Point"}
}