{
  "type": "Feature",
  "properties": {
    "addr:full":"North Westminster Community Scho, Ol London Greater London W9 2EB",
    "addr:postcode":"w9 2eb",
    "addr:street":"North;Ol",
    "iso:country":"GB",
    "sg:address":"North Westminster Community Scho, Ol",
    "sg:city":"London",
    "sg:classifiers":[
        {
            "category":"Organizations",
            "subcategory":"Non-profit Organization",
            "type":"Services"
        }
    ],
    "sg:postcode":"W9 2EB",
    "sg:province":"Greater London",
    "sg:tags":[
        "organisation",
        "voluntary",
        "charity"
    ],
    "wof:name":"Divert Mentoring Project",
    "wof:placetype":"venue"
},
  "geometry": {"coordinates":[-0.1940799952,51.525100708],"type":"Point"}
}