{
  "type": "Feature",
  "properties": {
    "iso:country":"GB",
    "sg:address":"37a Regents Park Road",
    "sg:city":"Southampton",
    "sg:classifiers":[
        {
            "category":"Bars & Pubs",
            "type":"Food & Drink"
        },
        {
            "category":"Personal",
            "subcategory":"Barber",
            "type":"Services"
        }
    ],
    "sg:phone":"+44 23 8077 3439",
    "sg:postcode":"SO15 8PF",
    "sg:province":"Hampshire",
    "sg:tags":[
        "pubs",
        "inn",
        "gents",
        "hairdresser"
    ],
    "wof:name":"Regents Barber Shop",
    "wof:placetype":"venue"
},
  "geometry": {"coordinates":[-1.4429730177,50.9157905579],"type":"Point"}
}