{
  "type": "Feature",
  "properties": {
    "iso:country":"GB",
    "sg:address":"24 Tennant Place",
    "sg:city":"Newcastle",
    "sg:classifiers":[
        {
            "category":"Building & Trades",
            "subcategory":"Construction",
            "type":"Services"
        }
    ],
    "sg:phone":"+44 1782 636997",
    "sg:postcode":"ST5 8QP",
    "sg:province":"Staffordshire",
    "sg:tags":[
        "joiner",
        "carpenter"
    ],
    "wof:name":"B Stanway",
    "wof:placetype":"venue"
},
  "geometry": {"coordinates":[-2.2255809307,53.0401611328],"type":"Point"}
}