{
  "type": "Feature",
  "properties": {
    "addr:full":"Unit 6 Budbrooke Industrial Estate, Budbrooke Road Warwick Warwickshire CV34 5HG",
    "addr:housenumber":"unit 6",
    "addr:postcode":"cv34 5hg",
    "addr:street":"Budbrooke Industrial Estate Budbrooke Road",
    "iso:country":"GB",
    "sg:address":"Unit 6 Budbrooke Industrial Estate, Budbrooke Road",
    "sg:city":"Warwick",
    "sg:classifiers":[
        {
            "category":"Utilities",
            "subcategory":"Telephone",
            "type":"Services"
        }
    ],
    "sg:phone":"+44 1926 493322",
    "sg:postcode":"CV34 5HG",
    "sg:province":"Warwickshire",
    "sg:tags":[
        "telecommunication"
    ],
    "wof:name":"Vocom Ltd.",
    "wof:placetype":"venue"
},
  "geometry": {"coordinates":[-1.6057139635,52.2869110107],"type":"Point"}
}