{
  "type": "Feature",
  "properties": {
    "iso:country":"GB",
    "sg:address":"72 The Vennel",
    "sg:city":"Linlithgow",
    "sg:classifiers":[
        {
            "category":"Social Services",
            "subcategory":"Adult Care",
            "type":"Services"
        }
    ],
    "sg:phone":"+44 1506 847659",
    "sg:postcode":"EH49 7ET",
    "sg:province":"Falkirk",
    "sg:tags":[
        "domestic",
        "cleaning"
    ],
    "wof:name":"Spick 'N' Span",
    "wof:placetype":"venue"
},
  "geometry": {"coordinates":[-3.603464,55.976425],"type":"Point"}
}