{
  "type": "Feature",
  "properties": {
    "addr:full":"Unit 1-2 Amhurst Business Centre, Budbrooke Road Warwick Warwickshire CV34 5XH",
    "addr:housenumber":"unit 1-2",
    "addr:postcode":"cv34 5xh",
    "addr:street":"Amhurst Business Centre Budbrooke Road",
    "iso:country":"GB",
    "sg:address":"Unit 1-2 Amhurst Business Centre, Budbrooke Road",
    "sg:city":"Warwick",
    "sg:classifiers":[
        {
            "category":"Organizations",
            "subcategory":"Non-profit Organization",
            "type":"Services"
        }
    ],
    "sg:phone":"+44 1926 410938",
    "sg:postcode":"CV34 5XH",
    "sg:province":"Warwickshire",
    "sg:tags":[
        "organisation",
        "voluntary",
        "charity"
    ],
    "wof:name":"The Guide Dogs for the Blind Association",
    "wof:placetype":"venue"
},
  "geometry": {"coordinates":[-1.5910340548,52.28175354],"type":"Point"}
}