{
  "type": "Feature",
  "properties": {
    "addr:full":"The Coombe House, Streatley Reading Berkshire RG8 9QL",
    "addr:housenumber":"coombe house",
    "addr:postcode":"rg8 9ql",
    "iso:country":"GB",
    "sg:address":"The Coombe House, Streatley",
    "sg:city":"Reading",
    "sg:classifiers":[
        {
            "category":"Social Services",
            "subcategory":"Retirement Home",
            "type":"Services"
        }
    ],
    "sg:postcode":"RG8 9QL",
    "sg:province":"Berkshire",
    "sg:tags":[
        "residential",
        "care"
    ],
    "wof:name":"The Coombe House",
    "wof:placetype":"venue"
},
  "geometry": {"coordinates":[-1.1489150524,51.5230522156],"type":"Point"}
}