{
  "type": "Feature",
  "properties": {
    "iso:country":"GB",
    "sg:address":"Leamington Hastings",
    "sg:city":"Rugby",
    "sg:classifiers":[
        {
            "category":"Education",
            "subcategory":"School",
            "type":"Public Place"
        }
    ],
    "sg:phone":"+44 1926 632359",
    "sg:postcode":"CV23 8EA",
    "sg:province":"Northamptonshire",
    "sg:tags":[
        "local",
        "authority"
    ],
    "wof:name":"Leamington Hastings C of E Infant School",
    "wof:placetype":"venue"
},
  "geometry": {"coordinates":[-1.33997,52.300941],"type":"Point"}
}