{
  "type": "Feature",
  "properties": {
    "addr:full":"Kingswick Ho Ascot Berkshire SL5 7BH",
    "addr:postcode":"sl5 7bh",
    "iso:country":"GB",
    "sg:address":"Kingswick Ho",
    "sg:city":"Ascot",
    "sg:classifiers":[
        {
            "category":"Wholesale",
            "subcategory":"Motor Vehicles",
            "type":"Manufacturing & Wholesale Goods"
        }
    ],
    "sg:phone":"+44 1276 857172",
    "sg:postcode":"SL5 7BH",
    "sg:province":"Berkshire",
    "sg:tags":[
        "aircraft",
        "spare"
    ],
    "wof:name":"Eagle Air Spares Ltd",
    "wof:placetype":"venue"
},
  "geometry": {"coordinates":[-0.673794,51.410675],"type":"Point"}
}