{
  "type": "Feature",
  "properties": {
    "iso:country":"GB",
    "sg:address":"Unit 12 Easton Business Centre, Felix Rd",
    "sg:city":"Bristol",
    "sg:classifiers":[
        {
            "category":"Government",
            "subcategory":"Post Office",
            "type":"Public Place"
        }
    ],
    "sg:phone":"+44 117 941 5876",
    "sg:postcode":"BS5 0HE",
    "sg:province":"City of Bristol",
    "sg:tags":[
        "messenger",
        "courier"
    ],
    "wof:name":"Safe Transport",
    "wof:placetype":"venue"
},
  "geometry": {"coordinates":[-2.567759,51.462448],"type":"Point"}
}