{
  "type": "Feature",
  "properties": {
    "addr:full":"Ashington Welfare, Recreation Ground Ashington Northumberland NE63 9XG",
    "addr:postcode":"ne63 9xg",
    "addr:street":"Northumberland",
    "iso:country":"GB",
    "sg:address":"Ashington Welfare, Recreation Ground",
    "sg:city":"Ashington",
    "sg:classifiers":[
        {
            "category":"Arena",
            "subcategory":"Sports Club",
            "type":"Entertainment"
        }
    ],
    "sg:phone":"+44 1670 814123",
    "sg:postcode":"NE63 9XG",
    "sg:province":"Northumberland",
    "wof:name":"Ashington Rugby Club",
    "wof:placetype":"venue"
},
  "geometry": {"coordinates":[-1.567809,55.178928],"type":"Point"}
}