{
  "type": "Feature",
  "properties": {
    "addr:full":"17 Weston Rd Southend On Sea Essex SS1 1AS",
    "addr:housenumber":"17",
    "addr:postcode":"ss1 1as",
    "addr:street":"Weston Rd",
    "iso:country":"GB",
    "sg:address":"17 Weston Rd",
    "sg:city":"Southend On Sea",
    "sg:classifiers":[
        {
            "category":"Social Services",
            "type":"Services"
        }
    ],
    "sg:phone":"+44 1702 330464",
    "sg:postcode":"SS1 1AS",
    "sg:province":"Essex",
    "wof:name":"South East Essex Youth Justice Centre",
    "wof:placetype":"venue"
},
  "geometry": {"coordinates":[0.712298,51.536205],"type":"Point"}
}