{
  "type": "Feature",
  "properties": {
    "addr:full":"Fidelity Ho, Stocks La Chester Cheshire CH3 5TE",
    "addr:postcode":"ch3 5te",
    "addr:street":"Stocks",
    "iso:country":"GB",
    "sg:address":"Fidelity Ho, Stocks La",
    "sg:city":"Chester",
    "sg:classifiers":[
        {
            "category":"Real Estate",
            "subcategory":"Surveying",
            "type":"Services"
        }
    ],
    "sg:phone":"+44 1244 315570",
    "sg:postcode":"CH3 5TE",
    "sg:province":"Cheshire",
    "sg:tags":[
        "surveyor",
        "valuer"
    ],
    "wof:name":"Darlington & Associates",
    "wof:placetype":"venue"
},
  "geometry": {"coordinates":[-2.86618,53.188091],"type":"Point"}
}