{
  "type": "Feature",
  "properties": {
    "addr:full":"1 Vulcan Way, Swan La Camberley Hampshire GU17 8DB",
    "addr:housenumber":"1",
    "addr:postcode":"gu17 8db",
    "addr:street":"Vulcan Way",
    "iso:country":"GB",
    "sg:address":"1 Vulcan Way, Swan La",
    "sg:city":"Camberley",
    "sg:classifiers":[
        {
            "category":"Manufacturing",
            "subcategory":"Metals",
            "type":"Manufacturing & Wholesale Goods"
        }
    ],
    "sg:phone":"+44 1252 890621",
    "sg:postcode":"GU17 8DB",
    "sg:province":"Hampshire",
    "sg:tags":[
        "work",
        "sheet"
    ],
    "wof:name":"Tarbet Engineering Ltd",
    "wof:placetype":"venue"
},
  "geometry": {"coordinates":[-0.8116599917,51.3216018677],"type":"Point"}
}