{
  "type": "Feature",
  "properties": {
    "addr:full":"236-237 Record Street London Greater London SE15 1TL",
    "addr:postcode":"236-237;se15 1tl",
    "addr:street":"Record Street",
    "iso:country":"GB",
    "sg:address":"236-237 Record Street",
    "sg:city":"London",
    "sg:classifiers":[
        {
            "category":"Shopping",
            "subcategory":"Stationery & Office Supplies",
            "type":"Retail Goods"
        }
    ],
    "sg:phone":"+44 20 7732 9988",
    "sg:postcode":"SE15 1TL",
    "sg:province":"Greater London",
    "sg:tags":[
        "merchant",
        "paper"
    ],
    "wof:name":"Davies Harvey & Murrell Ltd.",
    "wof:placetype":"venue"
},
  "geometry": {"coordinates":[-0.05534,51.484592],"type":"Point"}
}