{
  "type": "Feature",
  "properties": {
    "addr:full":"78 Commercial St Newport East Riding of Yorkshire NP9 1LR",
    "addr:housenumber":"78",
    "addr:postcode":"np9 1lr",
    "addr:street":"Commercial St",
    "iso:country":"GB",
    "sg:address":"78 Commercial St",
    "sg:city":"Newport",
    "sg:classifiers":[
        {
            "category":"Bars & Pubs",
            "type":"Food & Drink"
        }
    ],
    "sg:phone":"+44 1633 660502",
    "sg:postcode":"NP9 1LR",
    "sg:province":"East Riding of Yorkshire",
    "sg:tags":[
        "pubs",
        "inn"
    ],
    "wof:name":"Welsh Prince The",
    "wof:placetype":"venue"
},
  "geometry": {"coordinates":[-2.992944,51.58371],"type":"Point"}
}