{
  "type": "Feature",
  "properties": {
    "addr:full":"67-69 High Street, Nailsea Bristol Somerset BS48 1AW",
    "addr:housenumber":"67-69",
    "addr:postcode":"bs48 1aw",
    "addr:street":"High Street",
    "iso:country":"GB",
    "sg:address":"67-69 High Street, Nailsea",
    "sg:city":"Bristol",
    "sg:classifiers":[
        {
            "category":"Professional",
            "subcategory":"Management & Consulting",
            "type":"Services"
        }
    ],
    "sg:postcode":"BS48 1AW",
    "sg:province":"Somerset",
    "sg:tags":[
        "consultant",
        "specialist"
    ],
    "wof:name":"Face Values Health & Beauty",
    "wof:placetype":"venue"
},
  "geometry": {"coordinates":[-2.7562999725,51.433506012],"type":"Point"}
}