{
  "type": "Feature",
  "properties": {
    "iso:country":"GB",
    "sg:address":"Bentgate House, Newhey Road",
    "sg:city":"Rochdale",
    "sg:classifiers":[
        {
            "category":"Manufacturing",
            "subcategory":"Glass & Minerals",
            "type":"Manufacturing & Wholesale Goods"
        }
    ],
    "sg:phone":"+44 1706 290390",
    "sg:postcode":"OL16 4JY",
    "sg:province":"Lancashire",
    "sg:tags":[
        "fibre",
        "material"
    ],
    "wof:name":"Glass Fibre Ltd.",
    "wof:placetype":"venue"
},
  "geometry": {"coordinates":[-2.098319,53.600143],"type":"Point"}
}