{
  "type": "Feature",
  "properties": {
    "addr:full":"7 High St Maidenhead Berkshire SL6 1JN",
    "addr:housenumber":"7",
    "addr:postcode":"sl6 1jn",
    "addr:street":"High St",
    "iso:country":"GB",
    "sg:address":"7 High St",
    "sg:city":"Maidenhead",
    "sg:classifiers":[
        {
            "category":"Banks & Credit Unions",
            "subcategory":"Investment Brokerage",
            "type":"Services"
        }
    ],
    "sg:phone":"+44 1628 778841",
    "sg:postcode":"SL6 1JN",
    "sg:province":"Berkshire",
    "sg:tags":[
        "overseas",
        "property",
        "agent"
    ],
    "wof:name":"Prime Property International",
    "wof:placetype":"venue"
},
  "geometry": {"coordinates":[-0.7172989845,51.5228881836],"type":"Point"}
}