{
  "type": "Feature",
  "properties": {
    "iso:country":"GB",
    "sg:address":"125 Collingwood Crescent",
    "sg:city":"Guildford",
    "sg:classifiers":[
        {
            "category":"Shopping",
            "subcategory":"Department Store",
            "type":"Retail Goods"
        },
        {
            "category":"Sports & Exercise",
            "subcategory":"Sports Center",
            "type":"Entertainment"
        }
    ],
    "sg:phone":"+44 1483 458555",
    "sg:postcode":"GU1 2PF",
    "sg:province":"Surrey",
    "sg:tags":[
        "shop"
    ],
    "wof:name":"Skate Asylum",
    "wof:placetype":"venue"
},
  "geometry": {"coordinates":[-0.54628,51.246071],"type":"Point"}
}