{
  "type": "Feature",
  "properties": {
    "iso:country":"GB",
    "sg:address":"14 Crow Lane West",
    "sg:city":"Newton-le-willows",
    "sg:classifiers":[
        {
            "category":"Wholesale",
            "subcategory":"Furniture",
            "type":"Manufacturing & Wholesale Goods"
        },
        {
            "category":"Home & Garden",
            "subcategory":"Kitchen Supply",
            "type":"Retail Goods"
        }
    ],
    "sg:phone":"+44 1925 292222",
    "sg:postcode":"WA12 9YG",
    "sg:province":"Cheshire",
    "sg:tags":[
        "shop",
        "fitting",
        "bar",
        "accessory"
    ],
    "wof:name":"Newton Bar Supplies",
    "wof:placetype":"venue"
},
  "geometry": {"coordinates":[-2.639009,53.456337],"type":"Point"}
}