{
  "type": "Feature",
  "properties": {
    "addr:full":"The Old Mill, Canterbury Rd, Lyminge Folkestone Kent CT18 8JW",
    "addr:postcode":"ct18 8jw",
    "addr:street":"Canterbury Rd",
    "iso:country":"GB",
    "sg:address":"The Old Mill, Canterbury Rd, Lyminge",
    "sg:city":"Folkestone",
    "sg:classifiers":[
        {
            "category":"Home & Garden",
            "subcategory":"Building Materials",
            "type":"Retail Goods"
        }
    ],
    "sg:phone":"+44 1303 862393",
    "sg:postcode":"CT18 8JW",
    "sg:province":"Kent",
    "sg:tags":[
        "window",
        "frame"
    ],
    "wof:name":"Sabre Windows",
    "wof:placetype":"venue"
},
  "geometry": {"coordinates":[1.0902,51.129047],"type":"Point"}
}