{
  "type": "Feature",
  "properties": {
    "iso:country":"GB",
    "sg:address":"5 Temple Terrace, Aspatria",
    "sg:city":"Wigton",
    "sg:classifiers":[
        {
            "category":"Building & Trades",
            "subcategory":"Construction",
            "type":"Services"
        }
    ],
    "sg:phone":"+44 16973 20365",
    "sg:postcode":"CA7 3BH",
    "sg:province":"Cumbria",
    "sg:tags":[
        "builder"
    ],
    "wof:name":"Storey & Baker",
    "wof:placetype":"venue"
},
  "geometry": {"coordinates":[-3.3200318813,54.7649688721],"type":"Point"}
}