{
  "type": "Feature",
  "properties": {
    "addr:full":"Blacksnape Road Darwen Lancashire BB3 3PN",
    "addr:postcode":"bb3 3pn",
    "addr:street":"Blacksnape Road",
    "iso:country":"GB",
    "sg:address":"Blacksnape Road",
    "sg:city":"Darwen",
    "sg:classifiers":[
        {
            "category":"Sports & Exercise",
            "subcategory":"Stables",
            "type":"Entertainment"
        }
    ],
    "sg:phone":"+44 1254 701557",
    "sg:postcode":"BB3 3PN",
    "sg:province":"Lancashire",
    "sg:tags":[
        "education",
        "equestrian"
    ],
    "wof:name":"Moorview Equestrian Centre",
    "wof:placetype":"venue"
},
  "geometry": {"coordinates":[-2.433095,53.683563],"type":"Point"}
}