{
  "type": "Feature",
  "properties": {
    "addr:full":"166 Buxton Rd Macclesfield Cheshire SK10 1NG",
    "addr:housenumber":"166",
    "addr:postcode":"sk10 1ng",
    "addr:street":"Buxton Rd",
    "iso:country":"GB",
    "sg:address":"166 Buxton Rd",
    "sg:city":"Macclesfield",
    "sg:classifiers":[
        {
            "category":"Recreation",
            "subcategory":"Fishing",
            "type":"Entertainment"
        }
    ],
    "sg:postcode":"SK10 1NG",
    "sg:province":"Cheshire",
    "sg:tags":[
        "equipment",
        "angling"
    ],
    "wof:name":"Shackley,Robert,",
    "wof:placetype":"venue"
},
  "geometry": {"coordinates":[-2.115277,53.258812],"type":"Point"}
}