{
  "type": "Feature",
  "properties": {
    "addr:full":"40a Hertford Road Enfield Greater London EN3 5AN",
    "addr:housenumber":"40a",
    "addr:postcode":"en3 5an",
    "addr:street":"Hertford Road",
    "iso:country":"GB",
    "sg:address":"40a Hertford Road",
    "sg:city":"Enfield",
    "sg:classifiers":[
        {
            "category":"Building & Trades",
            "subcategory":"Construction",
            "type":"Services"
        }
    ],
    "sg:phone":"+44 20 8804 7715",
    "sg:postcode":"EN3 5AN",
    "sg:province":"Greater London",
    "sg:tags":[
        "flooring"
    ],
    "wof:name":"CROUCHER FLOORING",
    "wof:placetype":"venue"
},
  "geometry": {"coordinates":[-0.0483549982,51.6528015137],"type":"Point"}
}