{
  "type": "Feature",
  "properties": {
    "addr:full":"14 New Conduit St King's Lynn Norfolk PE30 1DL",
    "addr:housenumber":"14",
    "addr:postcode":"pe30 1dl",
    "addr:street":"New Conduit St",
    "iso:country":"GB",
    "sg:address":"14 New Conduit St",
    "sg:city":"King's Lynn",
    "sg:classifiers":[
        {
            "category":"Retail",
            "subcategory":"Laundry & Dry Cleaning",
            "type":"Services"
        }
    ],
    "sg:phone":"+44 1553 775925",
    "sg:postcode":"PE30 1DL",
    "sg:province":"Norfolk",
    "sg:tags":[
        "alteration"
    ],
    "wof:name":"Johnsons The Cleaners",
    "wof:placetype":"venue"
},
  "geometry": {"coordinates":[0.396876,52.753559],"type":"Point"}
}