{
  "type": "Feature",
  "properties": {
    "iso:country":"GB",
    "sg:address":"82 Newtown Road",
    "sg:city":"Bedworth",
    "sg:classifiers":[
        {
            "category":"Personal",
            "subcategory":"Adult",
            "type":"Services"
        }
    ],
    "sg:phone":"+44 24 7631 7608",
    "sg:postcode":"CV12 8QS",
    "sg:province":"Warwickshire",
    "sg:tags":[
        "equestrian"
    ],
    "wof:name":"Smithy",
    "wof:placetype":"venue"
},
  "geometry": {"coordinates":[-1.48003,52.479584],"type":"Point"}
}