{
  "type": "Feature",
  "properties": {
    "iso:country":"GB",
    "sg:address":"475 Margate Road",
    "sg:city":"Broadstairs",
    "sg:classifiers":[
        {
            "category":"Community Center",
            "subcategory":"Youth",
            "type":"Public Place"
        }
    ],
    "sg:phone":"+44 1843 600610",
    "sg:postcode":"CT10 2QJ",
    "sg:province":"Kent",
    "sg:tags":[
        "children's",
        "activity"
    ],
    "wof:name":"Funtazia Adventure Centre",
    "wof:placetype":"venue"
},
  "geometry": {"coordinates":[1.395761,51.360058],"type":"Point"}
}