{
  "type": "Feature",
  "properties": {
    "addr:full":"13 King George Road Shoreham-by-sea West Sussex BN43 6YN",
    "addr:housenumber":"13",
    "addr:postcode":"bn43 6yn",
    "addr:street":"King George Road",
    "iso:country":"GB",
    "sg:address":"13 King George Road",
    "sg:city":"Shoreham-by-sea",
    "sg:classifiers":[
        {
            "category":"Building & Trades",
            "subcategory":"Construction",
            "type":"Services"
        }
    ],
    "sg:postcode":"BN43 6YN",
    "sg:province":"West Sussex",
    "sg:tags":[
        "roofing",
        "bricklaying"
    ],
    "wof:name":"Nigel Barnes",
    "wof:placetype":"venue"
},
  "geometry": {"coordinates":[-0.247499004,50.8399009705],"type":"Point"}
}