{
  "type": "Feature",
  "properties": {
    "addr:full":"1 Great Hay Drive, Sutton Hill Telford Shropshire TF7 4DT",
    "addr:housenumber":"1",
    "addr:postcode":"tf7 4dt",
    "addr:street":"Great Hay Drive",
    "iso:country":"GB",
    "sg:address":"1 Great Hay Drive, Sutton Hill",
    "sg:city":"Telford",
    "sg:classifiers":[
        {
            "category":"Manufacturing",
            "subcategory":"Metals",
            "type":"Manufacturing & Wholesale Goods"
        }
    ],
    "sg:postcode":"TF7 4DT",
    "sg:province":"Shropshire",
    "sg:tags":[
        "steel",
        "stockholder"
    ],
    "wof:name":"Wentworth Steel Services",
    "wof:placetype":"venue"
},
  "geometry": {"coordinates":[-2.4448339939,52.6270828247],"type":"Point"}
}