{
  "type": "Feature",
  "properties": {
    "iso:country":"GB",
    "sg:address":"Millfields, Coach St",
    "sg:city":"Skipton",
    "sg:classifiers":[
        {
            "category":"Health Services",
            "subcategory":"Doctor",
            "type":"Services"
        }
    ],
    "sg:phone":"+44 1756 799622",
    "sg:postcode":"BD23 1LQ",
    "sg:province":"Lancashire",
    "sg:tags":[
        "practitioners"
    ],
    "wof:name":"Clarke, J",
    "wof:placetype":"venue"
},
  "geometry": {"coordinates":[-2.0185139179,53.9602012634],"type":"Point"}
}