{
  "type": "Feature",
  "properties": {
    "iso:country":"GB",
    "sg:address":"Main Street",
    "sg:city":"Lochwinnoch",
    "sg:classifiers":[
        {
            "category":"Government",
            "subcategory":"City Hall",
            "type":"Public Place"
        },
        {
            "category":"Retail",
            "subcategory":"Event Space",
            "type":"Services"
        },
        {
            "category":"Government",
            "subcategory":"Office",
            "type":"Public Place"
        }
    ],
    "sg:phone":"+44 1505 842261",
    "sg:postcode":"PA12 4AJ",
    "sg:province":"Renfrewshire",
    "sg:tags":[
        "function",
        "hire",
        "local",
        "room"
    ],
    "wof:name":"McKillop Institute",
    "wof:placetype":"venue"
},
  "geometry": {"coordinates":[-4.622879,55.797619],"type":"Point"}
}