{
  "type": "Feature",
  "properties": {
    "addr:full":"114 Ashleigh Rd St Albans Hertfordshire AL1 5JR",
    "addr:housenumber":"114",
    "addr:postcode":"al1 5jr",
    "addr:street":"Ashleigh Rd",
    "iso:country":"GB",
    "sg:address":"114 Ashleigh Rd",
    "sg:city":"St Albans",
    "sg:classifiers":[
        {
            "category":"Autos & Motor Vehicles",
            "subcategory":"Auto Supplies",
            "type":"Retail Goods"
        }
    ],
    "sg:phone":"+44 1727 839936",
    "sg:postcode":"AL1 5JR",
    "sg:province":"Hertfordshire",
    "sg:tags":[
        "component"
    ],
    "wof:name":"Wheels Motor Factors Ltd",
    "wof:placetype":"venue"
},
  "geometry": {"coordinates":[-0.3377520144,51.7531890869],"type":"Point"}
}