{
  "type": "Feature",
  "properties": {
    "iso:country":"GB",
    "sg:address":"6 Worcester Roa",
    "sg:city":"Droitwich",
    "sg:classifiers":[
        {
            "category":"Restaurant",
            "type":"Food & Drink"
        }
    ],
    "sg:phone":"+44 1905 794799",
    "sg:postcode":"WR9 8AB",
    "sg:province":"Worcestershire",
    "wof:name":"Rossini Restaurant",
    "wof:placetype":"venue"
},
  "geometry": {"coordinates":[-2.1460549831,52.2680511475],"type":"Point"}
}