{
  "type": "Feature",
  "properties": {
    "iso:country":"GB",
    "sg:address":"Building 1, 10 Banbury Avenue Trading Estate",
    "sg:city":"Slough",
    "sg:classifiers":[
        {
            "category":"Home & Garden",
            "subcategory":"Hardware",
            "type":"Retail Goods"
        }
    ],
    "sg:postcode":"SL1 4LR",
    "sg:province":"Berkshire",
    "sg:tags":[
        "device",
        "fixing",
        "fastener"
    ],
    "wof:name":"New Zipper Co. Ltd.",
    "wof:placetype":"venue"
},
  "geometry": {"coordinates":[-0.6319289804,51.5255012512],"type":"Point"}
}