{
  "type": "Feature",
  "properties": {
    "iso:country":"GB",
    "sg:address":"Unit 6, 35 Catley Road, Darnall",
    "sg:city":"Sheffield",
    "sg:classifiers":[
        {
            "category":"Bus Charters",
            "type":"Transportation"
        }
    ],
    "sg:phone":"+44 114 244 8323",
    "sg:postcode":"S9 5JF",
    "sg:province":"South Yorkshire",
    "sg:tags":[
        "hire",
        "coach"
    ],
    "wof:name":"Burgin European (Coach Hirers) Ltd.",
    "wof:placetype":"venue"
},
  "geometry": {"coordinates":[-1.407137,53.388645],"type":"Point"}
}