{
  "type": "Feature",
  "properties": {
    "addr:full":"52 Beulah Road London Greater London E17 9LQ",
    "addr:housenumber":"52",
    "addr:postcode":"e17 9lq",
    "addr:street":"Beulah Road",
    "iso:country":"GB",
    "sg:address":"52 Beulah Road",
    "sg:city":"London",
    "sg:classifiers":[
        {
            "category":"Home & Garden",
            "subcategory":"Home Furnishings",
            "type":"Retail Goods"
        }
    ],
    "sg:postcode":"E17 9LQ",
    "sg:province":"Greater London",
    "sg:tags":[
        "blind",
        "curtain",
        "fitting"
    ],
    "wof:name":"Something Nice",
    "wof:placetype":"venue"
},
  "geometry": {"coordinates":[-0.010483,51.581455],"type":"Point"}
}