{
  "type": "Feature",
  "properties": {
    "addr:full":"Po Box 136 Northampton Northamptonshire NN1 1AT",
    "addr:housenumber":"po",
    "addr:postcode":"nn1 1at",
    "addr:street":"Box 136",
    "iso:country":"GB",
    "sg:address":"Po Box 136",
    "sg:city":"Northampton",
    "sg:classifiers":[
        {
            "category":"Government",
            "subcategory":"Office",
            "type":"Public Place"
        }
    ],
    "sg:postcode":"NN1 1AT",
    "sg:province":"Northamptonshire",
    "sg:tags":[
        "local"
    ],
    "wof:name":"Northamptonshire",
    "wof:placetype":"venue"
},
  "geometry": {"coordinates":[-0.897679,52.234859],"type":"Point"}
}