{
  "type": "Feature",
  "properties": {
    "addr:full":"Tercrosset Farm, West Hall Brampton Cumbria CA8 2EH",
    "addr:postcode":"ca8 2eh",
    "addr:street":"West Hall",
    "iso:country":"GB",
    "sg:address":"Tercrosset Farm, West Hall",
    "sg:city":"Brampton",
    "sg:postcode":"CA8 2EH",
    "sg:province":"Cumbria",
    "wof:name":"Thomas Crawford Whiteford",
    "wof:placetype":"venue"
},
  "geometry": {"coordinates":[-2.6785480976,55.001335144],"type":"Point"}
}