{
  "type": "Feature",
  "properties": {
    "iso:country":"GB",
    "sg:address":"The Leasowes, Fair Mile, Stoke Prior",
    "sg:city":"Leominster",
    "sg:classifiers":[
        {
            "category":"Wholesale",
            "subcategory":"Scrap",
            "type":"Manufacturing & Wholesale Goods"
        },
        {
            "category":"Wholesale",
            "subcategory":"Auto Parts",
            "type":"Manufacturing & Wholesale Goods"
        }
    ],
    "sg:phone":"+44 1568 760684",
    "sg:postcode":"HR6 0LR",
    "sg:province":"Herefordshire",
    "sg:tags":[
        "car",
        "breaker",
        "dismantlers"
    ],
    "sg:website":"http://www.p-tmoore.co.uk",
    "wof:name":"P & T Moore",
    "wof:placetype":"venue"
},
  "geometry": {"coordinates":[-2.7021501064,52.206161499],"type":"Point"}
}