{
  "type": "Feature",
  "properties": {
    "addr:full":"26 Darlingscote Road Shipston-on-stour Warwickshire CV36 4DR",
    "addr:housenumber":"26",
    "addr:postcode":"cv36 4dr",
    "addr:street":"Darlingscote Road",
    "iso:country":"GB",
    "sg:address":"26 Darlingscote Road",
    "sg:city":"Shipston-on-stour",
    "sg:classifiers":[
        {
            "category":"Health Services",
            "subcategory":"Podiatrist",
            "type":"Services"
        }
    ],
    "sg:phone":"+44 1608 661283",
    "sg:postcode":"CV36 4DR",
    "sg:province":"Warwickshire",
    "sg:tags":[
        "podiatrists",
        "chiropodist"
    ],
    "wof:name":"Margery J Bradley",
    "wof:placetype":"venue"
},
  "geometry": {"coordinates":[-1.6336740255,52.0673141479],"type":"Point"}
}