{
  "type": "Feature",
  "properties": {
    "addr:full":"21 Bempton Drive Ruislip Greater London HA4 9DB",
    "addr:housenumber":"21",
    "addr:postcode":"ha4 9db",
    "addr:street":"Bempton Drive",
    "iso:country":"GB",
    "sg:address":"21 Bempton Drive",
    "sg:city":"Ruislip",
    "sg:classifiers":[
        {
            "category":"Building & Trades",
            "subcategory":"Plumbing",
            "type":"Services"
        }
    ],
    "sg:phone":"+44 1895 639720",
    "sg:postcode":"HA4 9DB",
    "sg:province":"Greater London",
    "sg:tags":[
        "plumber",
        "heating"
    ],
    "wof:name":"J A Plumbing",
    "wof:placetype":"venue"
},
  "geometry": {"coordinates":[-0.405627,51.566486],"type":"Point"}
}