{
  "type": "Feature",
  "properties": {
    "addr:full":"44 Shambles St Barnsley South Yorkshire S70 2SH",
    "addr:housenumber":"44",
    "addr:postcode":"s70 2sh",
    "addr:street":"Shambles St;Yorkshire",
    "iso:country":"GB",
    "sg:address":"44 Shambles St",
    "sg:city":"Barnsley",
    "sg:classifiers":[
        {
            "category":"Real Estate",
            "subcategory":"Real Estate Agent",
            "type":"Services"
        }
    ],
    "sg:phone":"+44 1226 298541",
    "sg:postcode":"S70 2SH",
    "sg:province":"South Yorkshire",
    "wof:name":"Lewis Wadsworth",
    "wof:placetype":"venue"
},
  "geometry": {"coordinates":[-1.4853520393,53.5529899597],"type":"Point"}
}