{
  "type": "Feature",
  "properties": {
    "addr:full":"Grampound Road Truro Cornwall TR2 4HD",
    "addr:postcode":"tr2 4hd",
    "addr:street":"Grampound Road",
    "iso:country":"GB",
    "sg:address":"Grampound Road",
    "sg:city":"Truro",
    "sg:classifiers":[
        {
            "category":"Autos & Motor Vehicles",
            "subcategory":"Automobile Sales",
            "type":"Retail Goods"
        }
    ],
    "sg:postcode":"TR2 4HD",
    "sg:province":"Cornwall",
    "sg:tags":[
        "car"
    ],
    "wof:name":"Jim Broad Cars",
    "wof:placetype":"venue"
},
  "geometry": {"coordinates":[-4.8990340233,50.2982139587],"type":"Point"}
}