{
  "type": "Feature",
  "properties": {
    "iso:country":"GB",
    "sg:address":"1066 London Rd",
    "sg:city":"Thornton Heath",
    "sg:classifiers":[
        {
            "category":"Personal",
            "subcategory":"Beauty Salon",
            "type":"Services"
        }
    ],
    "sg:postcode":"CR7 7ND",
    "sg:province":"Surrey",
    "sg:tags":[
        "unisex",
        "hairdresser"
    ],
    "wof:name":"Remarque Hair & Beauty Salon",
    "wof:placetype":"venue"
},
  "geometry": {"coordinates":[-0.116899,51.399101],"type":"Point"}
}