{
  "type": "Feature",
  "properties": {
    "addr:full":"21 Picton Rd Liverpool Merseyside L15 4LD",
    "addr:housenumber":"21",
    "addr:postcode":"l15 4ld",
    "addr:street":"Picton Rd",
    "iso:country":"GB",
    "sg:address":"21 Picton Rd",
    "sg:city":"Liverpool",
    "sg:classifiers":[
        {
            "category":"Bars & Pubs",
            "subcategory":"Nightclub",
            "type":"Food & Drink"
        }
    ],
    "sg:phone":"+44 151 280 5138",
    "sg:postcode":"L15 4LD",
    "sg:province":"Merseyside",
    "sg:tags":[
        "club",
        "night"
    ],
    "wof:name":"Bar Oasis",
    "wof:placetype":"venue"
},
  "geometry": {"coordinates":[-2.9378929138,53.4028778076],"type":"Point"}
}