{
  "type": "Feature",
  "properties": {
    "iso:country":"GB",
    "sg:address":"Wood Lane",
    "sg:city":"Ellesmere",
    "sg:classifiers":[
        {
            "category":"Manufacturing",
            "subcategory":"Building Materials",
            "type":"Manufacturing & Wholesale Goods"
        }
    ],
    "sg:phone":"+44 1691 626262",
    "sg:postcode":"SY12 0HY",
    "sg:province":"Shropshire",
    "sg:tags":[
        "merchant",
        "builder"
    ],
    "wof:name":"T G Builders Merchants Ltd.",
    "wof:placetype":"venue"
},
  "geometry": {"coordinates":[-2.8967549801,52.9076843262],"type":"Point"}
}