{
  "type": "Feature",
  "properties": {
    "addr:full":"2-3 Central Buildings, Ealing London Greater London W5 2NT",
    "addr:housenumber":"2-3",
    "addr:postcode":"w5 2nt",
    "addr:street":"Central Buildings",
    "iso:country":"GB",
    "sg:address":"2-3 Central Buildings, Ealing",
    "sg:city":"London",
    "sg:classifiers":[
        {
            "category":"Bars & Pubs",
            "type":"Food & Drink"
        }
    ],
    "sg:phone":"+44 20 8567 4859",
    "sg:postcode":"W5 2NT",
    "sg:province":"Greater London",
    "sg:tags":[
        "pubs",
        "inn"
    ],
    "wof:name":"Chandlers",
    "wof:placetype":"venue"
},
  "geometry": {"coordinates":[-0.30241,51.51466],"type":"Point"}
}