{
  "type": "Feature",
  "properties": {
    "iso:country":"GB",
    "sg:address":"26 Depot St",
    "sg:city":"Derby",
    "sg:classifiers":[
        {
            "category":"Shopping",
            "subcategory":"Pets & Pet Supplies",
            "type":"Retail Goods"
        }
    ],
    "sg:phone":"+44 1332 361514",
    "sg:postcode":"DE23 8ET",
    "sg:province":"Derbyshire",
    "wof:name":"Pet Foods",
    "wof:placetype":"venue"
},
  "geometry": {"coordinates":[-1.476262,52.911278],"type":"Point"}
}