{
  "type": "Feature",
  "properties": {
    "addr:full":"Hook Lane, Shere Guildford Surrey GU5 9QQ",
    "addr:postcode":"gu5 9qq",
    "addr:street":"Hook Lane",
    "iso:country":"GB",
    "sg:address":"Hook Lane, Shere",
    "sg:city":"Guildford",
    "sg:classifiers":[
        {
            "category":"Retail",
            "subcategory":"Auto Repair",
            "type":"Services"
        }
    ],
    "sg:phone":"+44 1483 202850",
    "sg:postcode":"GU5 9QQ",
    "sg:province":"Surrey",
    "sg:tags":[
        "modification",
        "garage"
    ],
    "wof:name":"Technicraft",
    "wof:placetype":"venue"
},
  "geometry": {"coordinates":[-0.464705,51.220524],"type":"Point"}
}