{
  "type": "Feature",
  "properties": {
    "iso:country":"GB",
    "sg:address":"14 Riverlands, Astley Burf",
    "sg:city":"Stourport-on-severn",
    "sg:classifiers":[
        {
            "category":"Home & Garden",
            "subcategory":"Carpets & Floor Coverings",
            "type":"Retail Goods"
        }
    ],
    "sg:phone":"+44 1299 822738",
    "sg:postcode":"DY13 0RZ",
    "sg:province":"Worcestershire",
    "sg:tags":[
        "crane"
    ],
    "wof:name":"G R L Designs",
    "wof:placetype":"venue"
},
  "geometry": {"coordinates":[-2.281167,52.338997],"type":"Point"}
}