{
  "type": "Feature",
  "properties": {
    "addr:full":"Station Drive, Brierley Hill Brierley Hill West Midlands DY5 3JZ",
    "addr:postcode":"dy5 3jz",
    "addr:street":"Station Drive Brierley Hill Brierley Hill",
    "iso:country":"GB",
    "sg:address":"Station Drive, Brierley Hill",
    "sg:city":"Brierley Hill",
    "sg:classifiers":[
        {
            "category":"Communications",
            "subcategory":"News Services",
            "type":"Services"
        }
    ],
    "sg:phone":"+44 1384 261406",
    "sg:postcode":"DY5 3JZ",
    "sg:province":"West Midlands",
    "sg:tags":[
        "press"
    ],
    "wof:name":"Whorton & Reeves",
    "wof:placetype":"venue"
},
  "geometry": {"coordinates":[-2.136274,52.47316],"type":"Point"}
}