{
  "type": "Feature",
  "properties": {
    "addr:full":"13 Cheap St Sherborne Dorset DT9 3PU",
    "addr:housenumber":"13",
    "addr:postcode":"dt9 3pu",
    "addr:street":"Cheap St",
    "iso:country":"GB",
    "sg:address":"13 Cheap St",
    "sg:city":"Sherborne",
    "sg:classifiers":[
        {
            "category":"Shopping",
            "subcategory":"Department Store",
            "type":"Retail Goods"
        }
    ],
    "sg:postcode":"DT9 3PU",
    "sg:province":"Dorset",
    "wof:name":"Palmers Toy Shop",
    "wof:placetype":"venue"
},
  "geometry": {"coordinates":[-2.5164959431,50.9495048523],"type":"Point"}
}