{
  "type": "Feature",
  "properties": {
    "iso:country":"GB",
    "sg:address":"51 High Street",
    "sg:city":"Cheltenham",
    "sg:classifiers":[
        {
            "category":"Home & Garden",
            "subcategory":"Furniture",
            "type":"Retail Goods"
        }
    ],
    "sg:postcode":"GL50 1DX",
    "sg:province":"Gloucestershire",
    "wof:name":"New Rooms",
    "wof:placetype":"venue"
},
  "geometry": {"coordinates":[-2.070868,51.897877],"type":"Point"}
}