{
  "type": "Feature",
  "properties": {
    "iso:country":"GB",
    "sg:address":"Warden, Bishops Crescent",
    "sg:city":"Southampton",
    "sg:classifiers":[
        {
            "category":"Social Services",
            "subcategory":"Adult Care",
            "type":"Services"
        }
    ],
    "sg:phone":"+44 24 8044 5886",
    "sg:postcode":"SO19 2FH",
    "sg:province":"Hampshire",
    "sg:tags":[
        "housing",
        "sheltered"
    ],
    "wof:name":"Bishops Crescent Sheltered Housing",
    "wof:placetype":"venue"
},
  "geometry": {"coordinates":[-1.366834,50.903095],"type":"Point"}
}