{
  "type": "Feature",
  "properties": {
    "iso:country":"GB",
    "sg:address":"20-22 Queen Street",
    "sg:city":"London",
    "sg:classifiers":[
        {
            "category":"Real Estate",
            "subcategory":"Surveying",
            "type":"Services"
        }
    ],
    "sg:phone":"+44 20 7495 4321",
    "sg:postcode":"W1J 5PR",
    "sg:province":"Greater London",
    "sg:tags":[
        "surveyor",
        "valuer"
    ],
    "wof:name":"Wilkinson Williams Ltd.",
    "wof:placetype":"venue"
},
  "geometry": {"coordinates":[-0.1471969932,51.506980896],"type":"Point"}
}