{
  "type": "Feature",
  "properties": {
    "iso:country":"GB",
    "sg:address":"Office 8 Hinckley Business Cent, Re, Burbidge Road",
    "sg:city":"Hinckley",
    "sg:classifiers":[
        {
            "category":"Professional",
            "subcategory":"Management & Consulting",
            "type":"Services"
        }
    ],
    "sg:phone":"+44 1455 239988",
    "sg:postcode":"LE10 2TP",
    "sg:province":"Leicestershire",
    "sg:tags":[
        "consultant",
        "training"
    ],
    "wof:name":"Q S M Training",
    "wof:placetype":"venue"
},
  "geometry": {"coordinates":[-1.372754,52.542439],"type":"Point"}
}