{
  "type": "Feature",
  "properties": {
    "iso:country":"GB",
    "sg:address":"385 Upton Rd",
    "sg:city":"Birkenhead",
    "sg:classifiers":[
        {
            "category":"Personal",
            "subcategory":"Beauty Salon",
            "type":"Services"
        }
    ],
    "sg:phone":"+44 151 677 3001",
    "sg:postcode":"L43 9SE",
    "sg:province":"Merseyside",
    "sg:tags":[
        "unisex",
        "hairdresser"
    ],
    "wof:name":"Headhunters",
    "wof:placetype":"venue"
},
  "geometry": {"coordinates":[-3.0825090408,53.3877983093],"type":"Point"}
}