{
  "type": "Feature",
  "properties": {
    "addr:full":"110 Calabria Rd Highbury Greater London N5 1HT",
    "addr:housenumber":"110",
    "addr:postcode":"n5 1ht",
    "addr:street":"Calabria Rd",
    "iso:country":"GB",
    "sg:address":"110 Calabria Rd",
    "sg:city":"Highbury",
    "sg:classifiers":[
        {
            "category":"Communications",
            "subcategory":"Film & Video Production",
            "type":"Services"
        }
    ],
    "sg:phone":"+44 20 7226 0365",
    "sg:postcode":"N5 1HT",
    "sg:province":"Greater London",
    "sg:tags":[
        "tv",
        "studio"
    ],
    "wof:name":"Marjut Riminen Animation",
    "wof:placetype":"venue"
},
  "geometry": {"coordinates":[-0.0989700034,51.5491027832],"type":"Point"}
}