{
  "type": "Feature",
  "properties": {
    "iso:country":"GB",
    "sg:address":"2 Herndon Rd",
    "sg:city":"London",
    "sg:classifiers":[
        {
            "category":"Banks & Credit Unions",
            "subcategory":"Financial Services",
            "type":"Services"
        }
    ],
    "sg:postcode":"SW18 2DG",
    "sg:province":"Greater London",
    "sg:tags":[
        "consultant"
    ],
    "wof:name":"Kinesis Trading Systems Ltd",
    "wof:placetype":"venue"
},
  "geometry": {"coordinates":[-0.1873479933,51.4571685791],"type":"Point"}
}