{
  "type": "Feature",
  "properties": {
    "addr:full":"5 Ryder Court Corby Northamptonshire NN18 9NX",
    "addr:housenumber":"5",
    "addr:postcode":"nn18 9nx",
    "addr:street":"Ryder Court",
    "iso:country":"GB",
    "sg:address":"5 Ryder Court",
    "sg:city":"Corby",
    "sg:classifiers":[
        {
            "category":"Military Area",
            "subcategory":"Air Force Base",
            "type":"Public Place"
        }
    ],
    "sg:phone":"+44 1536 461441",
    "sg:postcode":"NN18 9NX",
    "sg:province":"Northamptonshire",
    "sg:tags":[
        "water",
        "treatment"
    ],
    "wof:name":"Hingerose Ltd.",
    "wof:placetype":"venue"
},
  "geometry": {"coordinates":[-0.735784,52.464771],"type":"Point"}
}