{
  "type": "Feature",
  "properties": {
    "iso:country":"GB",
    "sg:address":"3 Hartington Place",
    "sg:city":"Edinburgh",
    "sg:classifiers":[
        {
            "category":"Professional",
            "subcategory":"Accounting & Tax Preparation",
            "type":"Services"
        }
    ],
    "sg:phone":"+44 131 228 8052",
    "sg:postcode":"EH10 4LF",
    "sg:province":"City of Edinburgh",
    "sg:tags":[
        "accountant",
        "bookkeeping",
        "primarily",
        "activity"
    ],
    "wof:name":"Accounting Services For Scottish Solicitors",
    "wof:placetype":"venue"
},
  "geometry": {"coordinates":[-3.2105779648,55.9384841919],"type":"Point"}
}