{
  "type": "Feature",
  "properties": {
    "iso:country":"GB",
    "sg:address":"172 London Road",
    "sg:city":"Southend-on-sea",
    "sg:classifiers":[
        {
            "category":"Manufacturing",
            "subcategory":"Metals",
            "type":"Manufacturing & Wholesale Goods"
        }
    ],
    "sg:phone":"+44 1702 338727",
    "sg:postcode":"SS1 1PH",
    "sg:province":"Essex",
    "wof:name":"Hadleigh Jewellery Polishing",
    "wof:placetype":"venue"
},
  "geometry": {"coordinates":[0.7028909922,51.5399169922],"type":"Point"}
}