{
  "type": "Feature",
  "properties": {
    "iso:country":"GB",
    "sg:address":"8-10 Saughton Road North",
    "sg:city":"Edinburgh",
    "sg:classifiers":[
        {
            "category":"Building & Trades",
            "subcategory":"Construction",
            "type":"Services"
        }
    ],
    "sg:phone":"+44 131 334 1140",
    "sg:postcode":"EH12 7HG",
    "sg:province":"City of Edinburgh",
    "sg:tags":[
        "builder"
    ],
    "wof:name":"William T Thomson & Son (Edinburgh) Ltd",
    "wof:placetype":"venue"
},
  "geometry": {"coordinates":[-3.2819330692,55.9401779175],"type":"Point"}
}