{
  "type": "Feature",
  "properties": {
    "addr:full":"Blackwood Rd, Pontllanfraith Blackwood Caerphilly NP12 2BW",
    "addr:postcode":"np12 2bw",
    "addr:street":"Blackwood Rd",
    "iso:country":"GB",
    "sg:address":"Blackwood Rd, Pontllanfraith",
    "sg:city":"Blackwood",
    "sg:classifiers":[
        {
            "category":"Food & Beverages",
            "subcategory":"Bakery",
            "type":"Retail Goods"
        }
    ],
    "sg:phone":"+44 1495 223400",
    "sg:postcode":"NP12 2BW",
    "sg:province":"Caerphilly",
    "sg:tags":[
        "confectionery"
    ],
    "wof:name":"Iles Bros",
    "wof:placetype":"venue"
},
  "geometry": {"coordinates":[-3.1901199818,51.653629303],"type":"Point"}
}