{
  "type": "Feature",
  "properties": {
    "iso:country":"GB",
    "sg:address":"101 Boldon Lane",
    "sg:city":"South Shields",
    "sg:classifiers":[
        {
            "category":"Shopping",
            "subcategory":"Pets & Pet Supplies",
            "type":"Retail Goods"
        }
    ],
    "sg:postcode":"NE34 0AS",
    "sg:province":"Tyne and Wear",
    "wof:name":"Spraggon's Stores",
    "wof:placetype":"venue"
},
  "geometry": {"coordinates":[-1.439662,54.972927],"type":"Point"}
}