{
  "type": "Feature",
  "properties": {
    "addr:full":"3 Market Place Holt Norfolk NR25 6BE",
    "addr:housenumber":"3",
    "addr:postcode":"nr25 6be",
    "addr:street":"Market Place Holt",
    "iso:country":"GB",
    "sg:address":"3 Market Place",
    "sg:city":"Holt",
    "sg:classifiers":[
        {
            "category":"Real Estate",
            "subcategory":"Real Estate Agent",
            "type":"Services"
        }
    ],
    "sg:postcode":"NR25 6BE",
    "sg:province":"Norfolk",
    "wof:name":"John Marsh Ltd.",
    "wof:placetype":"venue"
},
  "geometry": {"coordinates":[1.0887349844,52.9060440063],"type":"Point"}
}