{
  "type": "Feature",
  "properties": {
    "iso:country":"GB",
    "sg:address":"12 Bank St",
    "sg:city":"Pontefract",
    "sg:classifiers":[
        {
            "category":"Communications",
            "subcategory":"Newspaper",
            "type":"Services"
        }
    ],
    "sg:phone":"+44 1977 737200",
    "sg:postcode":"WF9 4JX",
    "sg:province":"West Yorkshire",
    "sg:tags":[
        "magazine"
    ],
    "wof:name":"Pontefract & Castleford Express",
    "wof:placetype":"venue"
},
  "geometry": {"coordinates":[-1.317947,53.688572],"type":"Point"}
}