{
  "type": "Feature",
  "properties": {
    "addr:full":"19 Front Street, Concord Washington Tyne and Wear NE37 2BA",
    "addr:housenumber":"19",
    "addr:postcode":"ne37 2ba",
    "addr:street":"Front Street",
    "iso:country":"GB",
    "sg:address":"19 Front Street, Concord",
    "sg:city":"Washington",
    "sg:classifiers":[
        {
            "category":"Organizations",
            "subcategory":"Non-profit Organization",
            "type":"Services"
        }
    ],
    "sg:phone":"+44 191 416 3550",
    "sg:postcode":"NE37 2BA",
    "sg:province":"Tyne and Wear",
    "sg:tags":[
        "charitable",
        "organisation",
        "voluntary",
        "charity"
    ],
    "wof:name":"Wearside Women in Need",
    "wof:placetype":"venue"
},
  "geometry": {"coordinates":[-1.5174759626,54.9127388],"type":"Point"}
}