{
  "type": "Feature",
  "properties": {
    "iso:country":"GB",
    "sg:address":"St Leonards Road",
    "sg:city":"Forres",
    "sg:classifiers":[
        {
            "category":"Health Services",
            "subcategory":"Nursing And Care Facility",
            "type":"Services"
        }
    ],
    "sg:phone":"+44 1309 675500",
    "sg:postcode":"IV36 2RE",
    "sg:province":"Moray",
    "sg:tags":[
        "home"
    ],
    "wof:name":"Cathay Registered Nursing Home",
    "wof:placetype":"venue"
},
  "geometry": {"coordinates":[-3.600014,57.606541],"type":"Point"}
}