{
  "type": "Feature",
  "properties": {
    "addr:full":"20 Prospect Avenue, Frindsbury Rochester Kent ME2 3BZ",
    "addr:housenumber":"20",
    "addr:postcode":"me2 3bz",
    "addr:street":"Prospect Avenue",
    "iso:country":"GB",
    "sg:address":"20 Prospect Avenue, Frindsbury",
    "sg:city":"Rochester",
    "sg:classifiers":[
        {
            "category":"Sports & Exercise",
            "subcategory":"Tennis Court",
            "type":"Entertainment"
        }
    ],
    "sg:phone":"+44 1634 721071",
    "sg:postcode":"ME2 3BZ",
    "sg:province":"Kent",
    "sg:tags":[
        "breakdown",
        "recovery"
    ],
    "wof:name":"A Jones & Sons Recovery",
    "wof:placetype":"venue"
},
  "geometry": {"coordinates":[0.4983749986,51.4016418457],"type":"Point"}
}