{
  "type": "Feature",
  "properties": {
    "addr:full":"6 Churchfields Southend-on-sea Essex SS3 8TT",
    "addr:housenumber":"6",
    "addr:postcode":"ss3 8tt",
    "addr:street":"Churchfields",
    "iso:country":"GB",
    "sg:address":"6 Churchfields",
    "sg:city":"Southend-on-sea",
    "sg:classifiers":[
        {
            "category":"Professional",
            "type":"Services"
        }
    ],
    "sg:postcode":"SS3 8TT",
    "sg:province":"Essex",
    "sg:tags":[
        "services",
        "belt",
        "conveyor"
    ],
    "wof:name":"John S Raven",
    "wof:placetype":"venue"
},
  "geometry": {"coordinates":[0.7842490077,51.544002533],"type":"Point"}
}