{
  "type": "Feature",
  "properties": {
    "addr:full":"84 High Street, Wimbledon London Greater London SW19 5EQ",
    "addr:housenumber":"84",
    "addr:postcode":"sw19 5eq",
    "addr:street":"High Street",
    "iso:country":"GB",
    "sg:address":"84 High Street, Wimbledon",
    "sg:city":"London",
    "sg:classifiers":[
        {
            "category":"Food & Beverages",
            "subcategory":"Bakery",
            "type":"Retail Goods"
        }
    ],
    "sg:phone":"+44 20 8946 6027",
    "sg:postcode":"SW19 5EQ",
    "sg:province":"Greater London",
    "sg:tags":[
        "pizza"
    ],
    "wof:name":"Pizzaexpress (Restaurants) Ltd.",
    "wof:placetype":"venue"
},
  "geometry": {"coordinates":[-0.2171,51.42543],"type":"Point"}
}