{
  "type": "Feature",
  "properties": {
    "iso:country":"GB",
    "sg:address":"26 Humbleton Drive, Mackworth",
    "sg:city":"Derby",
    "sg:classifiers":[
        {
            "category":"Personal",
            "subcategory":"Beauty Salon",
            "type":"Services"
        },
        {
            "category":"Personal",
            "subcategory":"Barber",
            "type":"Services"
        }
    ],
    "sg:phone":"+44 1332 203700",
    "sg:postcode":"DE22 4AT",
    "sg:province":"Derbyshire",
    "sg:tags":[
        "unisex",
        "hairdresser"
    ],
    "wof:name":"J BRENNAN",
    "wof:placetype":"venue"
},
  "geometry": {"coordinates":[-1.5196379423,52.9236297607],"type":"Point"}
}