{
  "type": "Feature",
  "properties": {
    "iso:country":"GB",
    "sg:address":"13 Coldharbour Lane",
    "sg:city":"Hayes",
    "sg:classifiers":[
        {
            "category":"Shopping",
            "subcategory":"Bicycles & Sporting Goods",
            "type":"Retail Goods"
        }
    ],
    "sg:postcode":"UB3 3EA",
    "sg:province":"Greater London",
    "sg:tags":[
        "cycle",
        "accessory"
    ],
    "wof:name":"Hayes Cycle Centre",
    "wof:placetype":"venue"
},
  "geometry": {"coordinates":[-0.416939,51.507931],"type":"Point"}
}