{
  "type": "Feature",
  "properties": {
    "addr:full":"24 Queen Elizabeth Close Shefford Bedfordshire SG17 5LE",
    "addr:housenumber":"24",
    "addr:postcode":"sg17 5le",
    "addr:street":"Queen Elizabeth Close",
    "iso:country":"GB",
    "sg:address":"24 Queen Elizabeth Close",
    "sg:city":"Shefford",
    "sg:classifiers":[
        {
            "category":"Retail",
            "subcategory":"Driving School",
            "type":"Services"
        }
    ],
    "sg:phone":"+44 1462 815059",
    "sg:postcode":"SG17 5LE",
    "sg:province":"Bedfordshire",
    "wof:name":"Intercounty Driver Training",
    "wof:placetype":"venue"
},
  "geometry": {"coordinates":[-0.330277,52.033501],"type":"Point"}
}