{
  "type": "Feature",
  "properties": {
    "iso:country":"GB",
    "sg:address":"Chapel Street, Lye",
    "sg:city":"Stourbridge",
    "sg:classifiers":[
        {
            "category":"Bars & Pubs",
            "type":"Food & Drink"
        }
    ],
    "sg:phone":"+44 1384 894018",
    "sg:postcode":"DY9 8BT",
    "sg:province":"West Midlands",
    "sg:tags":[
        "pubs",
        "inn"
    ],
    "wof:name":"Old Bell Inn",
    "wof:placetype":"venue"
},
  "geometry": {"coordinates":[-2.1141090393,52.4565887451],"type":"Point"}
}