{
  "type": "Feature",
  "properties": {
    "addr:full":"Cemetery Lodge & Office, Lower House La Liverpool Merseyside L11 2SE",
    "addr:postcode":"l11 2se",
    "addr:street":"Lower House La",
    "iso:country":"GB",
    "sg:address":"Cemetery Lodge & Office, Lower House La",
    "sg:city":"Liverpool",
    "sg:classifiers":[
        {
            "category":"Retail",
            "subcategory":"Funeral Services",
            "type":"Services"
        }
    ],
    "sg:phone":"+44 151 546 2128",
    "sg:postcode":"L11 2SE",
    "sg:province":"Merseyside",
    "sg:tags":[
        "cemetery",
        "crematorium"
    ],
    "wof:name":"West Derby Cemetery",
    "wof:placetype":"venue"
},
  "geometry": {"coordinates":[-2.91445,53.450451],"type":"Point"}
}