{
  "type": "Feature",
  "properties": {
    "addr:full":"Unit 24, The Drummond Centre Croydon Surrey CR0 1UA",
    "addr:housenumber":"unit 24",
    "addr:postcode":"cr0 1ua",
    "addr:street":"The Drummond Centre",
    "iso:country":"GB",
    "sg:address":"Unit 24, The Drummond Centre",
    "sg:city":"Croydon",
    "sg:classifiers":[
        {
            "category":"Fast Food",
            "type":"Food & Drink"
        }
    ],
    "sg:phone":"+44 20 8686 2642",
    "sg:postcode":"CR0 1UA",
    "sg:province":"Surrey",
    "sg:tags":[
        "away",
        "take"
    ],
    "wof:name":"McDonald's",
    "wof:placetype":"venue"
},
  "geometry": {"coordinates":[-0.0997499973,51.3703918457],"type":"Point"}
}