{
  "type": "Feature",
  "properties": {
    "iso:country":"GB",
    "sg:address":"367 Forton Road",
    "sg:city":"Gosport",
    "sg:classifiers":[
        {
            "category":"Bars & Pubs",
            "type":"Food & Drink"
        }
    ],
    "sg:phone":"+44 23 9264 3738",
    "sg:postcode":"PO12 3HF",
    "sg:province":"Hampshire",
    "sg:tags":[
        "pubs",
        "inn"
    ],
    "wof:name":"John Warnes",
    "wof:placetype":"venue"
},
  "geometry": {"coordinates":[-1.148864,50.803501],"type":"Point"}
}