{
  "type": "Feature",
  "properties": {
    "iso:country":"GB",
    "sg:address":"162 Trafalgar Road",
    "sg:city":"London",
    "sg:classifiers":[
        {
            "category":"Building & Trades",
            "subcategory":"Plumbing",
            "type":"Services"
        }
    ],
    "sg:phone":"+44 20 8858 5538",
    "sg:postcode":"SE10 9TZ",
    "sg:province":"Greater London",
    "sg:tags":[
        "heating"
    ],
    "wof:name":"The M E T Furnace Construction Co. Ltd.",
    "wof:placetype":"venue"
},
  "geometry": {"coordinates":[0.003701,51.4847297668],"type":"Point"}
}