{
  "type": "Feature",
  "properties": {
    "iso:country":"GB",
    "sg:address":"Narborough Wood Park, Desford Road, Enderby",
    "sg:city":"Leicester",
    "sg:classifiers":[
        {
            "category":"Professional",
            "type":"Services"
        },
        {
            "category":"Professional",
            "subcategory":"Printing & Photocopies",
            "type":"Services"
        }
    ],
    "sg:phone":"+44 116 238 8115",
    "sg:postcode":"LE19 4XT",
    "sg:province":"Leicestershire",
    "sg:tags":[
        "directory",
        "printer",
        "pub"
    ],
    "wof:name":"SCRIBBLE",
    "wof:placetype":"venue"
},
  "geometry": {"coordinates":[-1.23223,52.60498],"type":"Point"}
}