{
  "type": "Feature",
  "properties": {
    "addr:full":"9-11 Bedford Street, Ampthill Bedford Bedfordshire MK45 2LU",
    "addr:housenumber":"9-11",
    "addr:postcode":"mk45 2lu",
    "addr:street":"Bedford Street",
    "iso:country":"GB",
    "sg:address":"9-11 Bedford Street, Ampthill",
    "sg:city":"Bedford",
    "sg:classifiers":[
        {
            "category":"Food & Beverages",
            "subcategory":"Supermarket",
            "type":"Retail Goods"
        }
    ],
    "sg:postcode":"MK45 2LU",
    "sg:province":"Bedfordshire",
    "wof:name":"Budgens Stores Ltd.",
    "wof:placetype":"venue"
},
  "geometry": {"coordinates":[-0.4934819937,52.0325775146],"type":"Point"}
}