{
  "type": "Feature",
  "properties": {
    "addr:full":"C/o British Airways, 156 Regent Street London Greater London W1B 5SN",
    "addr:housenumber":"156",
    "addr:postcode":"w1b 5sn",
    "addr:street":"C;Regent Street",
    "iso:country":"GB",
    "sg:address":"C/o British Airways, 156 Regent Street",
    "sg:city":"London",
    "sg:classifiers":[
        {
            "category":"Wholesale",
            "subcategory":"Books, Periodicals, & Newspapers",
            "type":"Manufacturing & Wholesale Goods"
        }
    ],
    "sg:phone":"+44 20 7434 4744",
    "sg:postcode":"W1B 5SN",
    "sg:province":"Greater London",
    "sg:tags":[
        "maps",
        "globe",
        "chart",
        "pub"
    ],
    "wof:name":"Edward Stanford",
    "wof:placetype":"venue"
},
  "geometry": {"coordinates":[-0.13996,51.512291],"type":"Point"}
}