{
  "type": "Feature",
  "properties": {
    "addr:full":"11 Hever Close Hockley Essex SS5 4XB",
    "addr:housenumber":"11",
    "addr:postcode":"ss5 4xb",
    "addr:street":"Hever Close",
    "iso:country":"GB",
    "sg:address":"11 Hever Close",
    "sg:city":"Hockley",
    "sg:classifiers":[
        {
            "category":"Professional",
            "subcategory":"Computer Services",
            "type":"Services"
        }
    ],
    "sg:phone":"+44 1702 200988",
    "sg:postcode":"SS5 4XB",
    "sg:province":"Essex",
    "sg:tags":[
        "system",
        "software"
    ],
    "wof:name":"Frontdelta Ltd.",
    "wof:placetype":"venue"
},
  "geometry": {"coordinates":[0.650234,51.602295],"type":"Point"}
}