{
  "type": "Feature",
  "properties": {
    "iso:country":"GB",
    "sg:address":"19 John Street",
    "sg:city":"London",
    "sg:classifiers":[
        {
            "category":"Organizations",
            "subcategory":"Professional Association",
            "type":"Services"
        }
    ],
    "sg:phone":"+44 20 7405 7473",
    "sg:postcode":"WC1N 2DL",
    "sg:province":"Greater London",
    "sg:tags":[
        "literary",
        "agent"
    ],
    "wof:name":"Sheil Land Foreign Rights",
    "wof:placetype":"venue"
},
  "geometry": {"coordinates":[-0.115573,51.522709],"type":"Point"}
}