{
  "type": "Feature",
  "properties": {
    "addr:full":"36-36a Unit, Phoebe Lane Industrial Estate Halifax West Yorkshire HX3 9EX",
    "addr:housenumber":"36-36a unit",
    "addr:postcode":"hx3 9ex",
    "addr:street":"Phoebe Lane Industrial Estate",
    "iso:country":"GB",
    "sg:address":"36-36a Unit, Phoebe Lane Industrial Estate",
    "sg:city":"Halifax",
    "sg:classifiers":[
        {
            "category":"Manufacturing",
            "subcategory":"Rubber & Plastics",
            "type":"Manufacturing & Wholesale Goods"
        },
        {
            "category":"Building & Trades",
            "subcategory":"Construction",
            "type":"Services"
        }
    ],
    "sg:postcode":"HX3 9EX",
    "sg:province":"West Yorkshire",
    "sg:tags":[
        "builder",
        "coating"
    ],
    "wof:name":"D & C Smith",
    "wof:placetype":"venue"
},
  "geometry": {"coordinates":[-1.8542040586,53.7104911804],"type":"Point"}
}