{
  "type": "Feature",
  "properties": {
    "addr:full":"Riverside Works, Frankland Lane Durham Durham DH1 5TA",
    "addr:postcode":"dh1 5ta",
    "addr:street":"Frankland Lane",
    "iso:country":"GB",
    "sg:address":"Riverside Works, Frankland Lane",
    "sg:city":"Durham",
    "sg:classifiers":[
        {
            "category":"Wholesale",
            "subcategory":"Scrap",
            "type":"Manufacturing & Wholesale Goods"
        }
    ],
    "sg:phone":"+44 191 384 7498",
    "sg:postcode":"DH1 5TA",
    "sg:province":"Durham",
    "sg:tags":[
        "breaker",
        "dismantlers"
    ],
    "wof:name":"Durham City Auto Salvage",
    "wof:placetype":"venue"
},
  "geometry": {"coordinates":[-1.574608,54.777534],"type":"Point"}
}