{
  "type": "Feature",
  "properties": {
    "addr:full":"Unit 3 Lister Gate Nottingham Nottinghamshire NG1 7DD",
    "addr:housenumber":"unit 3",
    "addr:postcode":"ng1 7dd",
    "addr:street":"Lister Gate",
    "iso:country":"GB",
    "sg:address":"Unit 3 Lister Gate",
    "sg:city":"Nottingham",
    "sg:classifiers":[
        {
            "category":"Home & Garden",
            "subcategory":"Household Appliances",
            "type":"Retail Goods"
        }
    ],
    "sg:phone":"+44 115 947 3719",
    "sg:postcode":"NG1 7DD",
    "sg:province":"Nottinghamshire",
    "sg:tags":[
        "electrical",
        "domestic"
    ],
    "wof:name":"Dixons",
    "wof:placetype":"venue"
},
  "geometry": {"coordinates":[-1.1487070322,52.9509506226],"type":"Point"}
}