{
  "type": "Feature",
  "properties": {
    "addr:full":"24 Main Street, Cosby Leicester Leicestershire LE9 1UU",
    "addr:housenumber":"24",
    "addr:postcode":"le9 1uu",
    "addr:street":"Main Street",
    "iso:country":"GB",
    "sg:address":"24 Main Street, Cosby",
    "sg:city":"Leicester",
    "sg:classifiers":[
        {
            "category":"Professional",
            "subcategory":"Art Services",
            "type":"Services"
        },
        {
            "category":"Building & Trades",
            "subcategory":"Construction",
            "type":"Services"
        }
    ],
    "sg:phone":"+44 116 286 3335",
    "sg:postcode":"LE9 1UU",
    "sg:province":"Leicestershire",
    "sg:tags":[
        "decorator",
        "painter"
    ],
    "wof:name":"DAVID STATHAM",
    "wof:placetype":"venue"
},
  "geometry": {"coordinates":[-1.193028,52.550758],"type":"Point"}
}