{
  "type": "Feature",
  "properties": {
    "addr:full":"Charnwood, Gregory Blvd Nottingham Nottinghamshire NG7 6NX",
    "addr:postcode":"ng7 6nx",
    "addr:street":"Gregory Blvd",
    "iso:country":"GB",
    "sg:address":"Charnwood, Gregory Blvd",
    "sg:city":"Nottingham",
    "sg:classifiers":[
        {
            "category":"Professional",
            "subcategory":"Engineering",
            "type":"Services"
        }
    ],
    "sg:phone":"+44 115 962 2721",
    "sg:postcode":"NG7 6NX",
    "sg:province":"Nottinghamshire",
    "sg:tags":[
        "engineer",
        "structural"
    ],
    "wof:name":"Allott & Lomax",
    "wof:placetype":"venue"
},
  "geometry": {"coordinates":[-1.16117,52.96711],"type":"Point"}
}