{
  "type": "Feature",
  "properties": {
    "iso:country":"GB",
    "sg:address":"Beech House, Ross Avenue",
    "sg:city":"Manchester",
    "sg:classifiers":[
        {
            "category":"Organizations",
            "subcategory":"Community Association",
            "type":"Services"
        },
        {
            "category":"Organizations",
            "subcategory":"Membership Organization",
            "type":"Services"
        }
    ],
    "sg:phone":"+44 161 224 4716",
    "sg:postcode":"M19 2HW",
    "sg:province":"Greater Manchester",
    "sg:tags":[
        "club",
        "social"
    ],
    "wof:name":"The Royal British Legion",
    "wof:placetype":"venue"
},
  "geometry": {"coordinates":[-2.19796,53.443241],"type":"Point"}
}