{
  "type": "Feature",
  "properties": {
    "addr:full":"21 Meadow Park Bridgwater Somerset TA6 7QE",
    "addr:housenumber":"21",
    "addr:postcode":"ta6 7qe",
    "addr:street":"Meadow Park",
    "iso:country":"GB",
    "sg:address":"21 Meadow Park",
    "sg:city":"Bridgwater",
    "sg:classifiers":[
        {
            "category":"Building & Trades",
            "subcategory":"Plumbing",
            "type":"Services"
        }
    ],
    "sg:postcode":"TA6 7QE",
    "sg:province":"Somerset",
    "sg:tags":[
        "central",
        "heating"
    ],
    "wof:name":"Plumb Heating",
    "wof:placetype":"venue"
},
  "geometry": {"coordinates":[-3.022704,51.12991],"type":"Point"}
}