{
  "type": "Feature",
  "properties": {
    "iso:country":"GB",
    "sg:address":"1359 London Road",
    "sg:city":"London",
    "sg:classifiers":[
        {
            "category":"Retail",
            "subcategory":"Laundry & Dry Cleaning",
            "type":"Services"
        }
    ],
    "sg:phone":"+44 20 8679 6500",
    "sg:postcode":"SW16 4BE",
    "sg:province":"Greater London",
    "sg:tags":[
        "alteration"
    ],
    "wof:name":"Norbury Express Dry Cleaners",
    "wof:placetype":"venue"
},
  "geometry": {"coordinates":[-0.121764,51.407761],"type":"Point"}
}