{
  "type": "Feature",
  "properties": {
    "addr:full":"11 The Parade, Blacon Chester Cheshire CH1 5HN",
    "addr:housenumber":"11",
    "addr:postcode":"ch1 5hn",
    "addr:street":"The Parade",
    "iso:country":"GB",
    "sg:address":"11 The Parade, Blacon",
    "sg:city":"Chester",
    "sg:classifiers":[
        {
            "category":"Food & Beverages",
            "subcategory":"Liquor & Beverages",
            "type":"Retail Goods"
        }
    ],
    "sg:phone":"+44 1244 372575",
    "sg:postcode":"CH1 5HN",
    "sg:province":"Cheshire",
    "sg:tags":[
        "beer",
        "spirit",
        "wines"
    ],
    "wof:name":"The Drinks Cabin",
    "wof:placetype":"venue"
},
  "geometry": {"coordinates":[-2.925037,53.20842],"type":"Point"}
}