{
  "type": "Feature",
  "properties": {
    "addr:full":"The Long Barn, 50 High Street Tring Buckinghamshire HP23 5AG",
    "addr:housenumber":"50",
    "addr:postcode":"hp23 5ag",
    "addr:street":"High Street",
    "iso:country":"GB",
    "sg:address":"The Long Barn, 50 High Street",
    "sg:city":"Tring",
    "sg:classifiers":[
        {
            "category":"Shopping",
            "subcategory":"Antiques",
            "type":"Retail Goods"
        }
    ],
    "sg:postcode":"HP23 5AG",
    "sg:province":"Buckinghamshire",
    "wof:name":"Farrelly Antiques",
    "wof:placetype":"venue"
},
  "geometry": {"coordinates":[-0.6639800072,51.7932701111],"type":"Point"}
}