{
  "type": "Feature",
  "properties": {
    "addr:full":"103 Stanley Road Bootle Merseyside L20 7DA",
    "addr:housenumber":"103",
    "addr:postcode":"l20 7da",
    "addr:street":"Stanley Road",
    "iso:country":"GB",
    "sg:address":"103 Stanley Road",
    "sg:city":"Bootle",
    "sg:classifiers":[
        {
            "category":"Fast Food",
            "type":"Food & Drink"
        }
    ],
    "sg:phone":"+44 151 284 2844",
    "sg:postcode":"L20 7DA",
    "sg:province":"Merseyside",
    "sg:tags":[
        "away",
        "take"
    ],
    "wof:name":"Taza Tandoori",
    "wof:placetype":"venue"
},
  "geometry": {"coordinates":[-2.9889960289,53.4444351196],"type":"Point"}
}