{
  "type": "Feature",
  "properties": {
    "addr:full":"Bilton House, St. James St Cheltenham Gloucestershire GL52 2SH",
    "addr:postcode":"gl52 2sh",
    "addr:street":"St. James St",
    "iso:country":"GB",
    "sg:address":"Bilton House, St. James St",
    "sg:city":"Cheltenham",
    "sg:classifiers":[
        {
            "category":"Retail",
            "subcategory":"Auto Repair",
            "type":"Services"
        }
    ],
    "sg:phone":"+44 1242 706987",
    "sg:postcode":"GL52 2SH",
    "sg:province":"Gloucestershire",
    "sg:tags":[
        "car",
        "upholsterer"
    ],
    "wof:name":"H.R.G Mobile Valeting & Steam Cleaning",
    "wof:placetype":"venue"
},
  "geometry": {"coordinates":[-2.070134,51.898342],"type":"Point"}
}