{
  "type": "Feature",
  "properties": {
    "addr:full":"50 Needingworth Road St Ives Cambridgeshire PE27 5JP",
    "addr:housenumber":"50",
    "addr:postcode":"pe27 5jp",
    "addr:street":"Needingworth Road",
    "iso:country":"GB",
    "sg:address":"50 Needingworth Road",
    "sg:city":"St Ives",
    "sg:classifiers":[
        {
            "category":"Travel",
            "subcategory":"Hotels & Motels",
            "type":"Entertainment"
        }
    ],
    "sg:phone":"+44 1480 463252",
    "sg:postcode":"PE27 5JP",
    "sg:province":"Cambridgeshire",
    "wof:name":"Olivers Lodge Hotel",
    "wof:placetype":"venue"
},
  "geometry": {"coordinates":[-0.067934,52.325783],"type":"Point"}
}