{
  "type": "Feature",
  "properties": {
    "addr:full":"125 Eastwood Road Nottingham Derbyshire NG16 2HQ",
    "addr:housenumber":"125",
    "addr:postcode":"ng16 2hq",
    "addr:street":"Eastwood Road",
    "iso:country":"GB",
    "sg:address":"125 Eastwood Road",
    "sg:city":"Nottingham",
    "sg:classifiers":[
        {
            "category":"Organizations",
            "subcategory":"Membership Organization",
            "type":"Services"
        }
    ],
    "sg:phone":"+44 115 938 2124",
    "sg:postcode":"NG16 2HQ",
    "sg:province":"Derbyshire",
    "sg:tags":[
        "club"
    ],
    "wof:name":"Kimberley Miners' Welfare Institute & Club",
    "wof:placetype":"venue"
},
  "geometry": {"coordinates":[-1.272063,53.000614],"type":"Point"}
}