{
  "type": "Feature",
  "properties": {
    "iso:country":"GB",
    "sg:address":"112a Gisburn Road, Barrowford",
    "sg:city":"Nelson",
    "sg:classifiers":[
        {
            "category":"Deli",
            "type":"Food & Drink"
        },
        {
            "category":"Food & Beverages",
            "subcategory":"Supermarket",
            "type":"Retail Goods"
        }
    ],
    "sg:phone":"+44 1282 613167",
    "sg:postcode":"BB9 6EW",
    "sg:province":"Lancashire",
    "sg:tags":[
        "delicatessen"
    ],
    "wof:name":"The Village Fayre",
    "wof:placetype":"venue"
},
  "geometry": {"coordinates":[-2.215534,53.852467],"type":"Point"}
}