{
  "type": "Feature",
  "properties": {
    "iso:country":"GB",
    "sg:address":"21a Daws Lane",
    "sg:city":"London",
    "sg:classifiers":[
        {
            "category":"Personal",
            "type":"Services"
        }
    ],
    "sg:postcode":"NW7 4SD",
    "sg:province":"Greater London",
    "sg:tags":[
        "tailor"
    ],
    "wof:name":"Handystitch",
    "wof:placetype":"venue"
},
  "geometry": {"coordinates":[-0.24224,51.616024],"type":"Point"}
}