{
  "type": "Feature",
  "properties": {
    "addr:full":"Flat 3 Ryecroft House, Hamilton Road, Wimbledon London Greater London SW19 1JE",
    "addr:postcode":"sw19 1je",
    "addr:street":"Hamilton Road",
    "iso:country":"GB",
    "sg:address":"Flat 3 Ryecroft House, Hamilton Road, Wimbledon",
    "sg:city":"London",
    "sg:classifiers":[
        {
            "category":"Government",
            "subcategory":"Post Office",
            "type":"Public Place"
        }
    ],
    "sg:postcode":"SW19 1JE",
    "sg:province":"Greater London",
    "sg:tags":[
        "messenger",
        "courier"
    ],
    "wof:name":"Abbey Mills Courier & Transport",
    "wof:placetype":"venue"
},
  "geometry": {"coordinates":[-0.191049993,51.4178199768],"type":"Point"}
}