{
  "type": "Feature",
  "properties": {
    "iso:country":"GB",
    "sg:address":"203-207 Woolwich Road",
    "sg:city":"London",
    "sg:classifiers":[
        {
            "category":"Education",
            "subcategory":"Library",
            "type":"Public Place"
        },
        {
            "category":"Government",
            "subcategory":"Office",
            "type":"Public Place"
        }
    ],
    "sg:phone":"+44 20 8858 6656",
    "sg:postcode":"SE10 0RL",
    "sg:province":"Greater London",
    "sg:tags":[
        "book",
        "local"
    ],
    "wof:name":"East Greenwich Library",
    "wof:placetype":"venue"
},
  "geometry": {"coordinates":[0.0163460001,51.4864501953],"type":"Point"}
}