{
  "type": "Feature",
  "properties": {
    "addr:full":"Po Box 925 Kingsbridge Devon TQ7 1WZ",
    "addr:housenumber":"po;925",
    "addr:postcode":"tq7 1wz",
    "addr:street":"Box",
    "iso:country":"GB",
    "sg:address":"Po Box 925",
    "sg:city":"Kingsbridge",
    "sg:classifiers":[
        {
            "category":"Building & Trades",
            "subcategory":"Equipment Rental",
            "type":"Services"
        }
    ],
    "sg:phone":"+44 1548 854577",
    "sg:postcode":"TQ7 1WZ",
    "sg:province":"Devon",
    "sg:tags":[
        "supply"
    ],
    "wof:name":"Rashleigh & Jones",
    "wof:placetype":"venue"
},
  "geometry": {"coordinates":[-3.776699,50.283379],"type":"Point"}
}