{
  "type": "Feature",
  "properties": {
    "iso:country":"GB",
    "sg:address":"28 Hornby Road",
    "sg:city":"Blackpool",
    "sg:classifiers":[
        {
            "category":"Travel",
            "subcategory":"Hotels & Motels",
            "type":"Entertainment"
        }
    ],
    "sg:phone":"+44 1253 625684",
    "sg:postcode":"FY1 4QG",
    "sg:province":"Lancashire",
    "wof:name":"Bel-Reve",
    "wof:placetype":"venue"
},
  "geometry": {"coordinates":[-3.050992,53.813957],"type":"Point"}
}