{
  "type": "Feature",
  "properties": {
    "addr:full":"25 Gadlys Road Aberdare Neath Port Talbot CF44 8AE",
    "addr:housenumber":"25",
    "addr:postcode":"cf44 8ae",
    "addr:street":"Gadlys Road",
    "iso:country":"GB",
    "sg:address":"25 Gadlys Road",
    "sg:city":"Aberdare",
    "sg:classifiers":[
        {
            "category":"Bars & Pubs",
            "type":"Food & Drink"
        },
        {
            "category":"Community Center",
            "subcategory":"Social",
            "type":"Public Place"
        }
    ],
    "sg:phone":"+44 1685 870702",
    "sg:postcode":"CF44 8AE",
    "sg:province":"Neath Port Talbot",
    "sg:tags":[
        "pubs",
        "house",
        "inn",
        "activity"
    ],
    "wof:name":"The Mackworth Arms",
    "wof:placetype":"venue"
},
  "geometry": {"coordinates":[-3.4510951042,51.7152557373],"type":"Point"}
}