{
  "type": "Feature",
  "properties": {
    "iso:country":"GB",
    "sg:address":"70 Birmingham Road, Rowley Regis",
    "sg:city":"Rowley Regis",
    "sg:classifiers":[
        {
            "category":"Banks & Credit Unions",
            "subcategory":"Bank",
            "type":"Services"
        }
    ],
    "sg:phone":"+44 121 480 6606",
    "sg:postcode":"B65 9BA",
    "sg:province":"West Midlands",
    "wof:name":"Barclays Bank Plc",
    "wof:placetype":"venue"
},
  "geometry": {"coordinates":[-2.0391,52.476215],"type":"Point"}
}