{
  "type": "Feature",
  "properties": {
    "iso:country":"GB",
    "sg:address":"Woodlands Road, Woodlands",
    "sg:city":"Doncaster",
    "sg:classifiers":[
        {
            "category":"Personal",
            "subcategory":"Beauty Salon",
            "type":"Services"
        }
    ],
    "sg:phone":"+44 1302 723265",
    "sg:postcode":"DN6 7JX",
    "sg:province":"North Yorkshire",
    "sg:tags":[
        "unisex",
        "hairdresser"
    ],
    "wof:name":"Dumvilles",
    "wof:placetype":"venue"
},
  "geometry": {"coordinates":[-1.187504,53.560936],"type":"Point"}
}