{
  "type": "Feature",
  "properties": {
    "iso:country":"GB",
    "sg:address":"78 Nook Lane",
    "sg:city":"Ashton-under-lyne",
    "sg:classifiers":[
        {
            "category":"Bars & Pubs",
            "type":"Food & Drink"
        },
        {
            "category":"Community Center",
            "subcategory":"Social",
            "type":"Public Place"
        }
    ],
    "sg:phone":"+44 161 330 8653",
    "sg:postcode":"OL6 9HJ",
    "sg:province":"Greater Manchester",
    "sg:tags":[
        "pubs",
        "house",
        "inn",
        "activity"
    ],
    "wof:name":"MARSTON THOMPSON & EVERSHED LTD",
    "wof:placetype":"venue"
},
  "geometry": {"coordinates":[-2.075589,53.503296],"type":"Point"}
}