{"geometry":{"type":"Point","coordinates":[0.097332,53.031929]},"type":"Feature","id":102560101,"bbox":[0.097332,53.031929,0.097332,53.031929],"properties":{"sg:province":"Lincolnshire","sg:tags":["operator","site","camping"],"geom:longitude":0.097332,"wof:breaches":[],"sg:href":"http://api.simplegeo.com/1.0/features/SG_2JNDzr7AK6EjCPdEDSpE9n_53.031929_0.097332@1300740015.json","sg:owner":"simplegeo","sg:postcode":"PE22 9LQ","geom:latitude":53.031929,"sg:classifiers":[{"category":"Recreation","type":"Entertainment","subcategory":"Campground"}],"sg:address":"The Cottage, Shaws Lane, Old Leake","sg:phone":"+44 1205 870121","wof:hierarchy":[{"venue_id":102560101,"country_id":85633159,"region_id":85684529}],"geom:area":0.000000,"sg:city":"Boston","wof:lastmodified":1438093190,"iso:country":"GB","wof:geomhash":"ed2271067bb5d34a613131f311512278","wof:name":"White Cat Caravan & Camping Park","wof:belongsto":[85633159,85684529],"src:geom":"simplegeo","wof:placetype":"venue","wof:supersedes":[],"wof:id":102560101,"wof:superseded_by":[],"wof:concordances":{"sg:id":"SG_2JNDzr7AK6EjCPdEDSpE9n_53.031929_0.097332@1300740015"},"wof:parent_id":85684529}}