{
  "type": "Feature",
  "properties": {
    "iso:country":"GB",
    "sg:address":"The Cottage, Shaws Lane, Old Leake",
    "sg:city":"Boston",
    "sg:classifiers":[
        {
            "category":"Recreation",
            "subcategory":"Campground",
            "type":"Entertainment"
        }
    ],
    "sg:href":"http://api.simplegeo.com/1.0/features/SG_2JNDzr7AK6EjCPdEDSpE9n_53.031929_0.097332@1300740015.json",
    "sg:phone":"+44 1205 870121",
    "sg:postcode":"PE22 9LQ",
    "sg:province":"Lincolnshire",
    "sg:tags":[
        "operator",
        "site",
        "camping"
    ],
    "wof:name":"White Cat Caravan & Camping Park",
    "wof:placetype":"venue"
},
  "geometry": {"coordinates":[0.097332,53.031929],"type":"Point"}
}