{
  "type": "Feature",
  "properties": {
    "iso:country":"GB",
    "sg:address":"12 Saunders Copse",
    "sg:city":"Woking",
    "sg:classifiers":[
        {
            "category":"Professional",
            "subcategory":"Testing Lab",
            "type":"Services"
        }
    ],
    "sg:phone":"+44 1483 761050",
    "sg:postcode":"GU22 0NS",
    "sg:province":"Surrey",
    "sg:tags":[
        "laboratory"
    ],
    "wof:name":"Positel Ltd.",
    "wof:placetype":"venue"
},
  "geometry": {"coordinates":[-0.583303,51.296669],"type":"Point"}
}