{
  "type": "Feature",
  "properties": {
    "addr:full":"72 New Bedford Road Luton Bedfordshire LU3 1BT",
    "addr:housenumber":"72",
    "addr:postcode":"lu3 1bt",
    "addr:street":"New Bedford Road",
    "iso:country":"GB",
    "sg:address":"72 New Bedford Road",
    "sg:city":"Luton",
    "sg:classifiers":[
        {
            "category":"Travel",
            "subcategory":"Hotels & Motels",
            "type":"Entertainment"
        }
    ],
    "sg:phone":"+44 1582 417643",
    "sg:postcode":"LU3 1BT",
    "sg:province":"Bedfordshire",
    "sg:website":"http://www.leasidehotel.co.uk",
    "wof:name":"Leaside Hotel",
    "wof:placetype":"venue"
},
  "geometry": {"coordinates":[-0.4196400046,51.883518219],"type":"Point"}
}