{
  "type": "Feature",
  "properties": {
    "addr:full":"Brookside, Rowe Bodmin Cornwall PL30 4LN",
    "addr:postcode":"pl30 4ln",
    "iso:country":"GB",
    "sg:address":"Brookside, Rowe",
    "sg:city":"Bodmin",
    "sg:classifiers":[
        {
            "category":"Arena",
            "subcategory":"Sports Club",
            "type":"Entertainment"
        }
    ],
    "sg:phone":"+44 1208 850137",
    "sg:postcode":"PL30 4LN",
    "sg:province":"Cornwall",
    "wof:name":"Gosen Golf Reservations",
    "wof:placetype":"venue"
},
  "geometry": {"coordinates":[-4.6599388123,50.5089607239],"type":"Point"}
}