{
  "type": "Feature",
  "properties": {
    "addr:full":"1st Floor 40a Belmont Road Erith Kent DA8 1LB",
    "addr:housenumber":"40a",
    "addr:postcode":"da8 1lb",
    "addr:street":"Floor;Belmont Road",
    "iso:country":"GB",
    "sg:address":"1st Floor 40a Belmont Road",
    "sg:city":"Erith",
    "sg:classifiers":[
        {
            "category":"Professional",
            "subcategory":"Employment Agencies",
            "type":"Services"
        }
    ],
    "sg:phone":"+44 1322 351877",
    "sg:postcode":"DA8 1LB",
    "sg:province":"Kent",
    "sg:tags":[
        "consultant"
    ],
    "wof:name":"Blue Arrow Personnel Services",
    "wof:placetype":"venue"
},
  "geometry": {"coordinates":[0.1562709957,51.4721565247],"type":"Point"}
}