{
  "type": "Feature",
  "properties": {
    "addr:full":"45 Lower Redland Road Bristol City of Bristol BS6 6TB",
    "addr:housenumber":"45",
    "addr:postcode":"bs6 6tb",
    "addr:street":"Lower Redland Road",
    "iso:country":"GB",
    "sg:address":"45 Lower Redland Road",
    "sg:city":"Bristol",
    "sg:classifiers":[
        {
            "category":"Manufacturing",
            "subcategory":"Pottery",
            "type":"Manufacturing & Wholesale Goods"
        }
    ],
    "sg:phone":"+44 117 973 2422",
    "sg:postcode":"BS6 6TB",
    "sg:province":"City of Bristol",
    "wof:name":"Redland Pottery",
    "wof:placetype":"venue"
},
  "geometry": {"coordinates":[-2.6117660999,51.4693946838],"type":"Point"}
}