{
  "type": "Feature",
  "properties": {
    "iso:country":"GB",
    "sg:address":"29 Woodcock Road",
    "sg:city":"Norwich",
    "sg:classifiers":[
        {
            "category":"Health Services",
            "subcategory":"Doctor",
            "type":"Services"
        }
    ],
    "sg:phone":"+44 1603 425989",
    "sg:postcode":"NR3 3UA",
    "sg:province":"Norfolk",
    "sg:tags":[
        "practitioners"
    ],
    "wof:name":"J C B Shutes",
    "wof:placetype":"venue"
},
  "geometry": {"coordinates":[1.280864,52.652397],"type":"Point"}
}