{
  "type": "Feature",
  "properties": {
    "addr:full":"46 Dorset Street London Greater London W1U 7NB",
    "addr:housenumber":"46",
    "addr:postcode":"w1u 7nb",
    "addr:street":"Dorset Street",
    "iso:country":"GB",
    "sg:address":"46 Dorset Street",
    "sg:city":"London",
    "sg:classifiers":[
        {
            "category":"Cafe",
            "type":"Food & Drink"
        }
    ],
    "sg:postcode":"W1U 7NB",
    "sg:province":"Greater London",
    "sg:tags":[
        "tea",
        "room"
    ],
    "wof:name":"Maison Francois Ltd.",
    "wof:placetype":"venue"
},
  "geometry": {"coordinates":[-0.1555619985,51.5195274353],"type":"Point"}
}