{
  "type": "Feature",
  "properties": {
    "addr:full":"Needham Road Stowmarket Suffolk IP14 2AJ",
    "addr:postcode":"ip14 2aj",
    "addr:street":"Needham Road",
    "iso:country":"GB",
    "sg:address":"Needham Road",
    "sg:city":"Stowmarket",
    "sg:classifiers":[
        {
            "category":"Travel",
            "subcategory":"Hotels & Motels",
            "type":"Entertainment"
        }
    ],
    "sg:phone":"+44 1449 612668",
    "sg:postcode":"IP14 2AJ",
    "sg:province":"Suffolk",
    "wof:name":"Cedars Hotel",
    "wof:placetype":"venue"
},
  "geometry": {"coordinates":[1.003082,52.179821],"type":"Point"}
}