{
  "type": "Feature",
  "properties": {
    "iso:country":"GB",
    "sg:address":"43 Teme Street",
    "sg:city":"Tenbury Wells",
    "sg:classifiers":[
        {
            "category":"Shopping",
            "subcategory":"Gifts & Souvenirs",
            "type":"Retail Goods"
        }
    ],
    "sg:phone":"+44 1584 810026",
    "sg:postcode":"WR15 8AE",
    "sg:province":"Herefordshire",
    "sg:tags":[
        "shop"
    ],
    "wof:name":"Harlequin Gift Shop",
    "wof:placetype":"venue"
},
  "geometry": {"coordinates":[-2.594404,52.312572],"type":"Point"}
}