{
  "type": "Feature",
  "properties": {
    "iso:country":"GB",
    "sg:address":"33 Kirtley Way, Broughton Astley",
    "sg:city":"Leicester",
    "sg:classifiers":[
        {
            "category":"Building & Trades",
            "subcategory":"Plumbing",
            "type":"Services"
        }
    ],
    "sg:phone":"+44 1455 283163",
    "sg:postcode":"LE9 6ND",
    "sg:province":"Leicestershire",
    "sg:tags":[
        "heating"
    ],
    "wof:name":"Ian Woolman Plumbing & Heating",
    "wof:placetype":"venue"
},
  "geometry": {"coordinates":[-1.215754,52.528034],"type":"Point"}
}