{
  "type": "Feature",
  "properties": {
    "addr:full":"42 Marine Street, Cwm Ebbw Vale Blaenau Gwent NP23 7ST",
    "addr:housenumber":"42",
    "addr:postcode":"np23 7st",
    "addr:street":"Marine Street",
    "iso:country":"GB",
    "sg:address":"42 Marine Street, Cwm",
    "sg:city":"Ebbw Vale",
    "sg:classifiers":[
        {
            "category":"Personal",
            "subcategory":"Beauty Salon",
            "type":"Services"
        },
        {
            "category":"Personal",
            "subcategory":"Barber",
            "type":"Services"
        }
    ],
    "sg:phone":"+44 1495 370701",
    "sg:postcode":"NP23 7ST",
    "sg:province":"Blaenau Gwent",
    "sg:tags":[
        "unisex",
        "hairdresser"
    ],
    "wof:name":"Images Salon",
    "wof:placetype":"venue"
},
  "geometry": {"coordinates":[-3.1821119785,51.7392807007],"type":"Point"}
}