{
  "type": "Feature",
  "properties": {
    "addr:full":"Leechmere Road Industrial Estate Sunderland Tyne and Wear SR2 9TT",
    "addr:housenumber":"estate",
    "addr:postcode":"sr2 9tt",
    "addr:street":"Leechmere Road Industrial",
    "iso:country":"GB",
    "sg:address":"Leechmere Road Industrial Estate",
    "sg:city":"Sunderland",
    "sg:classifiers":[
        {
            "category":"Food & Beverages",
            "subcategory":"Supermarket",
            "type":"Retail Goods"
        }
    ],
    "sg:phone":"+44 191 565 2222",
    "sg:postcode":"SR2 9TT",
    "sg:province":"Tyne and Wear",
    "wof:name":"Asda Stores",
    "wof:placetype":"venue"
},
  "geometry": {"coordinates":[-1.391644001,54.8866767883],"type":"Point"}
}