{
  "type": "Feature",
  "properties": {
    "addr:full":"18 Bracken Park Ayr South Ayrshire KA7 3XB",
    "addr:housenumber":"18",
    "addr:postcode":"ka7 3xb",
    "addr:street":"Bracken Park",
    "iso:country":"GB",
    "sg:address":"18 Bracken Park",
    "sg:city":"Ayr",
    "sg:classifiers":[
        {
            "category":"Arena",
            "subcategory":"Sports Club",
            "type":"Entertainment"
        }
    ],
    "sg:phone":"+44 1292 289885",
    "sg:postcode":"KA7 3XB",
    "sg:province":"South Ayrshire",
    "wof:name":"Kincaidston & Belmont Bowling Club",
    "wof:placetype":"venue"
},
  "geometry": {"coordinates":[-4.6071400642,55.4413604736],"type":"Point"}
}