{
  "type": "Feature",
  "properties": {
    "addr:full":"Downs Quarry, Kingston Rd, Langton Matravers Swanage Dorset BH19 3JP",
    "addr:postcode":"bh19 3jp",
    "addr:street":"Downs Quarry Kingston Rd",
    "iso:country":"GB",
    "sg:address":"Downs Quarry, Kingston Rd, Langton Matravers",
    "sg:city":"Swanage",
    "sg:classifiers":[
        {
            "category":"Building & Trades",
            "subcategory":"Equipment Rental",
            "type":"Services"
        }
    ],
    "sg:phone":"+44 1929 439476",
    "sg:postcode":"BH19 3JP",
    "sg:province":"Dorset",
    "sg:tags":[
        "plant",
        "machinery"
    ],
    "wof:name":"H & L Handling",
    "wof:placetype":"venue"
},
  "geometry": {"coordinates":[-1.991484,50.610146],"type":"Point"}
}