{
  "type": "Feature",
  "properties": {
    "iso:country":"GB",
    "sg:address":"Excelsior Wks, Bradford Rd, Riddlesden",
    "sg:city":"Keighley",
    "sg:classifiers":[
        {
            "category":"Autos & Motor Vehicles",
            "subcategory":"Automobile Sales",
            "type":"Retail Goods"
        }
    ],
    "sg:postcode":"BD21 4HA",
    "sg:province":"West Yorkshire",
    "sg:tags":[
        "car"
    ],
    "wof:name":"Carter,Steven,",
    "wof:placetype":"venue"
},
  "geometry": {"coordinates":[-1.88295,53.876801],"type":"Point"}
}