{
  "type": "Feature",
  "properties": {
    "addr:full":"Riddles Court, 322 Lawnmarket Edinburgh City of Edinburgh EH1 2PG",
    "addr:housenumber":"322",
    "addr:postcode":"eh1 2pg",
    "addr:street":"Lawnmarket Edinburgh",
    "iso:country":"GB",
    "sg:address":"Riddles Court, 322 Lawnmarket",
    "sg:city":"Edinburgh",
    "sg:classifiers":[
        {
            "category":"Education",
            "subcategory":"School",
            "type":"Public Place"
        },
        {
            "category":"Organizations",
            "subcategory":"Non-profit Organization",
            "type":"Services"
        }
    ],
    "sg:phone":"+44 131 226 3456",
    "sg:postcode":"EH1 2PG",
    "sg:province":"City of Edinburgh",
    "sg:tags":[
        "organisation",
        "location",
        "voluntary",
        "adult",
        "charity"
    ],
    "wof:name":"Workers Educational Association",
    "wof:placetype":"venue"
},
  "geometry": {"coordinates":[-3.194186,55.949123],"type":"Point"}
}