{
  "type": "Feature",
  "properties": {
    "iso:country":"GB",
    "sg:address":"26 Cleveland Street",
    "sg:city":"Wolverhampton",
    "sg:classifiers":[
        {
            "category":"Home & Garden",
            "subcategory":"Household Appliances",
            "type":"Retail Goods"
        }
    ],
    "sg:phone":"+44 1902 773573",
    "sg:postcode":"WV1 3HT",
    "sg:province":"West Midlands",
    "sg:tags":[
        "domestic",
        "centre"
    ],
    "wof:name":"A & F Trading Co.",
    "wof:placetype":"venue"
},
  "geometry": {"coordinates":[-2.1274049282,52.5828857422],"type":"Point"}
}