{
  "type": "Feature",
  "properties": {
    "iso:country":"GB",
    "sg:address":"138 Battersea High Street",
    "sg:city":"London",
    "sg:classifiers":[
        {
            "category":"Personal",
            "subcategory":"Beauty Salon",
            "type":"Services"
        }
    ],
    "sg:phone":"+44 20 7228 0241",
    "sg:postcode":"SW11 3JR",
    "sg:province":"Greater London",
    "sg:tags":[
        "unisex",
        "hairdresser"
    ],
    "wof:name":"Kay's",
    "wof:placetype":"venue"
},
  "geometry": {"coordinates":[-0.17247,51.470539],"type":"Point"}
}