{
  "type": "Feature",
  "properties": {
    "addr:full":"Ewing Ho, 130 Kings Rd Brentwood Essex CM14 4EQ",
    "addr:housenumber":"130",
    "addr:postcode":"cm14 4eq",
    "addr:street":"Kings Rd",
    "iso:country":"GB",
    "sg:address":"Ewing Ho, 130 Kings Rd",
    "sg:city":"Brentwood",
    "sg:classifiers":[
        {
            "category":"Insurance",
            "subcategory":"Insurance Agent",
            "type":"Services"
        }
    ],
    "sg:phone":"+44 1277 232535",
    "sg:postcode":"CM14 4EQ",
    "sg:province":"Essex",
    "wof:name":"United Kingdom Temperance & General Prov",
    "wof:placetype":"venue"
},
  "geometry": {"coordinates":[0.302834,51.620445],"type":"Point"}
}