{
  "type": "Feature",
  "properties": {
    "addr:full":"Woolram Wygate Spalding Lincolnshire PE11 1PB",
    "addr:postcode":"pe11 1pb",
    "addr:street":"Wygate Spalding",
    "iso:country":"GB",
    "sg:address":"Woolram Wygate",
    "sg:city":"Spalding",
    "sg:classifiers":[
        {
            "category":"Education",
            "subcategory":"School",
            "type":"Public Place"
        }
    ],
    "sg:phone":"+44 1476 585582",
    "sg:postcode":"PE11 1PB",
    "sg:province":"Lincolnshire",
    "sg:tags":[
        "foundation",
        "college"
    ],
    "wof:name":"Spalding Primary School",
    "wof:placetype":"venue"
},
  "geometry": {"coordinates":[-0.162351,52.795422],"type":"Point"}
}