{
  "type": "Feature",
  "properties": {
    "iso:country":"GB",
    "sg:address":"8 Bondgate Within",
    "sg:city":"Alnwick",
    "sg:classifiers":[
        {
            "category":"Building & Trades",
            "subcategory":"Construction",
            "type":"Services"
        }
    ],
    "sg:phone":"+44 1665 603617",
    "sg:postcode":"NE66 1TD",
    "sg:province":"Northumberland",
    "sg:tags":[
        "builder"
    ],
    "wof:name":"Tower Construction Ltd.",
    "wof:placetype":"venue"
},
  "geometry": {"coordinates":[-1.7050460577,55.4132728577],"type":"Point"}
}