{
  "type": "Feature",
  "properties": {
    "addr:full":"North Moel Y Garth, Groesllwyd, Guilsfield Welshpool Shropshire SY21 9BY",
    "addr:postcode":"sy21 9by",
    "addr:street":"North Moel Y Garth Groesllwyd Guilsfield",
    "iso:country":"GB",
    "sg:address":"North Moel Y Garth, Groesllwyd, Guilsfield",
    "sg:city":"Welshpool",
    "sg:classifiers":[
        {
            "category":"Farming",
            "subcategory":"Livestock Farm",
            "type":"Manufacturing & Wholesale Goods"
        }
    ],
    "sg:phone":"+44 1938 553229",
    "sg:postcode":"SY21 9BY",
    "sg:province":"Shropshire",
    "sg:tags":[
        "others"
    ],
    "wof:name":"G Thomas",
    "wof:placetype":"venue"
},
  "geometry": {"coordinates":[-3.155589,52.69669],"type":"Point"}
}