{
  "type": "Feature",
  "properties": {
    "iso:country":"GB",
    "sg:address":"Fair Meadow Close",
    "sg:city":"Milford Haven",
    "sg:classifiers":[
        {
            "category":"Building & Trades",
            "subcategory":"Landscaping Services",
            "type":"Services"
        }
    ],
    "sg:phone":"+44 1646 694564",
    "sg:postcode":"SA73 3TF",
    "sg:province":"Pembrokeshire",
    "sg:tags":[
        "horticultural",
        "consultant"
    ],
    "wof:name":"T C S",
    "wof:placetype":"venue"
},
  "geometry": {"coordinates":[-5.085759,51.729259],"type":"Point"}
}