{
  "type": "Feature",
  "properties": {
    "addr:full":"65 Norwood Road, Stretford Manchester Cheshire M32 8PN",
    "addr:housenumber":"65",
    "addr:postcode":"m32 8pn",
    "addr:street":"Norwood Road",
    "iso:country":"GB",
    "sg:address":"65 Norwood Road, Stretford",
    "sg:city":"Manchester",
    "sg:classifiers":[
        {
            "category":"Health Services",
            "subcategory":"Health Practitioner",
            "type":"Services"
        },
        {
            "category":"Shopping",
            "subcategory":"Pharmacy",
            "type":"Retail Goods"
        }
    ],
    "sg:phone":"+44 161 865 3193",
    "sg:postcode":"M32 8PN",
    "sg:province":"Cheshire",
    "sg:tags":[
        "medicine",
        "therapy",
        "hypnotherapists"
    ],
    "wof:name":"Fokkina Mcdonnell Associates",
    "wof:placetype":"venue"
},
  "geometry": {"coordinates":[-2.2982850075,53.4469299316],"type":"Point"}
}