{
  "type": "Feature",
  "properties": {
    "addr:full":"Lubbards Lodge, Hullbridge Road Rayleigh Essex SS6 9QG",
    "addr:postcode":"ss6 9qg",
    "addr:street":"Hullbridge Road Rayleigh",
    "iso:country":"GB",
    "sg:address":"Lubbards Lodge, Hullbridge Road",
    "sg:city":"Rayleigh",
    "sg:classifiers":[
        {
            "category":"Communications",
            "subcategory":"Film & Video Production",
            "type":"Services"
        }
    ],
    "sg:phone":"+44 1268 784599",
    "sg:postcode":"SS6 9QG",
    "sg:province":"Essex",
    "sg:tags":[
        "recording",
        "studio"
    ],
    "wof:name":"Mushroom Studios",
    "wof:placetype":"venue"
},
  "geometry": {"coordinates":[0.6087419987,51.6013832092],"type":"Point"}
}