{
  "type": "Feature",
  "properties": {
    "addr:full":"Park Side London Greater London NW2 6RJ",
    "addr:postcode":"nw2 6rj",
    "addr:street":"Park Side",
    "iso:country":"GB",
    "sg:address":"Park Side",
    "sg:city":"London",
    "sg:classifiers":[
        {
            "category":"Education",
            "subcategory":"School",
            "type":"Public Place"
        }
    ],
    "sg:phone":"+44 20 8450 4377",
    "sg:postcode":"NW2 6RJ",
    "sg:province":"Greater London",
    "sg:tags":[
        "local",
        "authority"
    ],
    "wof:name":"Avigdor Hirsch Torah Temimah Primary School",
    "wof:placetype":"venue"
},
  "geometry": {"coordinates":[-0.23324,51.559261],"type":"Point"}
}