{
  "type": "Feature",
  "properties": {
    "addr:full":"Bolebec Farm, Limbersey Lane Bedford Bedfordshire MK45 2DX",
    "addr:postcode":"mk45 2dx",
    "addr:street":"Limbersey Lane",
    "iso:country":"GB",
    "sg:address":"Bolebec Farm, Limbersey Lane",
    "sg:city":"Bedford",
    "sg:classifiers":[
        {
            "category":"Farming",
            "subcategory":"Dairy Farm",
            "type":"Manufacturing & Wholesale Goods"
        }
    ],
    "sg:phone":"+44 1525 404023",
    "sg:postcode":"MK45 2DX",
    "sg:province":"Bedfordshire",
    "wof:name":"John F Goodge",
    "wof:placetype":"venue"
},
  "geometry": {"coordinates":[-0.494994,52.027946],"type":"Point"}
}