{
  "type": "Feature",
  "properties": {
    "addr:full":"1 Constable Close, Cottenham Cambridge Cambridgeshire CB4 8RX",
    "addr:housenumber":"1",
    "addr:postcode":"cb4 8rx",
    "addr:street":"Constable Close",
    "iso:country":"GB",
    "sg:address":"1 Constable Close, Cottenham",
    "sg:city":"Cambridge",
    "sg:classifiers":[
        {
            "category":"Manufacturing",
            "subcategory":"Buildings",
            "type":"Manufacturing & Wholesale Goods"
        }
    ],
    "sg:postcode":"CB4 8RX",
    "sg:province":"Cambridgeshire",
    "sg:tags":[
        "mobile",
        "home"
    ],
    "wof:name":"Cottenham Park",
    "wof:placetype":"venue"
},
  "geometry": {"coordinates":[0.1272580028,52.2935752869],"type":"Point"}
}