{
  "type": "Feature",
  "properties": {
    "iso:country":"GB",
    "sg:address":"Ralph Street",
    "sg:city":"Pontypridd",
    "sg:classifiers":[
        {
            "category":"Bars & Pubs",
            "type":"Food & Drink"
        },
        {
            "category":"Community Center",
            "subcategory":"Social",
            "type":"Public Place"
        }
    ],
    "sg:phone":"+44 1443 402320",
    "sg:postcode":"CF37 4RS",
    "sg:province":"Caerphilly",
    "sg:tags":[
        "pubs",
        "house",
        "inn",
        "activity"
    ],
    "wof:name":"Central Hotel",
    "wof:placetype":"venue"
},
  "geometry": {"coordinates":[-3.3344240189,51.6083068848],"type":"Point"}
}