{
  "type": "Feature",
  "properties": {
    "addr:full":"149 Albany Road, Earlsdon Coventry West Midlands CV5 6ND",
    "addr:housenumber":"149",
    "addr:postcode":"cv5 6nd",
    "addr:street":"Albany Road Earlsdon",
    "iso:country":"GB",
    "sg:address":"149 Albany Road, Earlsdon",
    "sg:city":"Coventry",
    "sg:classifiers":[
        {
            "category":"Education",
            "subcategory":"School",
            "type":"Public Place"
        }
    ],
    "sg:postcode":"CV5 6ND",
    "sg:province":"West Midlands",
    "sg:tags":[
        "local",
        "authority"
    ],
    "wof:name":"Meridian Crew Training Ltd",
    "wof:placetype":"venue"
},
  "geometry": {"coordinates":[-1.527062,52.401119],"type":"Point"}
}