{
  "type": "Feature",
  "properties": {
    "iso:country":"GB",
    "sg:address":"31 Marshall Terrace",
    "sg:city":"Durham",
    "sg:classifiers":[
        {
            "category":"Personal",
            "subcategory":"Nail Salon",
            "type":"Services"
        }
    ],
    "sg:phone":"+44 191 384 7707",
    "sg:postcode":"DH1 2HX",
    "sg:province":"Durham",
    "sg:tags":[
        "solarium",
        "tanning"
    ],
    "wof:name":"Oasis Vertical Tanning Centre",
    "wof:placetype":"venue"
},
  "geometry": {"coordinates":[-1.542064,54.78157],"type":"Point"}
}