{
  "type": "Feature",
  "properties": {
    "addr:full":"17 Broad Street Warwick Warwickshire CV34 4LT",
    "addr:housenumber":"17",
    "addr:postcode":"cv34 4lt",
    "addr:street":"Broad Street",
    "iso:country":"GB",
    "sg:address":"17 Broad Street",
    "sg:city":"Warwick",
    "sg:classifiers":[
        {
            "category":"Building & Trades",
            "subcategory":"Landscaping Services",
            "type":"Services"
        }
    ],
    "sg:phone":"+44 1926 402558",
    "sg:postcode":"CV34 4LT",
    "sg:province":"Warwickshire",
    "sg:tags":[
        "landscape",
        "contractor"
    ],
    "wof:name":"Four Seasons",
    "wof:placetype":"venue"
},
  "geometry": {"coordinates":[-1.577186,52.285885],"type":"Point"}
}