{
  "type": "Feature",
  "properties": {
    "iso:country":"GB",
    "sg:address":"331-333 Finchley Road",
    "sg:city":"London",
    "sg:classifiers":[
        {
            "category":"Retail",
            "subcategory":"Auto Rental",
            "type":"Services"
        }
    ],
    "sg:phone":"+44 20 7431 6655",
    "sg:postcode":"NW3 6EP",
    "sg:province":"Greater London",
    "sg:tags":[
        "car"
    ],
    "wof:name":"Major Car Rental",
    "wof:placetype":"venue"
},
  "geometry": {"coordinates":[-0.183358,51.550438],"type":"Point"}
}