{
  "type": "Feature",
  "properties": {
    "addr:full":"Albany Park, Spout Lane Washington Tyne and Wear NE37 2BZ",
    "addr:postcode":"ne37 2bz",
    "addr:street":"Spout Lane",
    "iso:country":"GB",
    "sg:address":"Albany Park, Spout Lane",
    "sg:city":"Washington",
    "sg:classifiers":[
        {
            "category":"Arena",
            "subcategory":"Sports Club",
            "type":"Entertainment"
        }
    ],
    "sg:phone":"+44 191 417 7779",
    "sg:postcode":"NE37 2BZ",
    "sg:province":"Tyne and Wear",
    "wof:name":"Washington Association Football Club Ltd.",
    "wof:placetype":"venue"
},
  "geometry": {"coordinates":[-1.51986,54.90947],"type":"Point"}
}