{
  "type": "Feature",
  "properties": {
    "addr:full":"201 Henley Road Ipswich Suffolk IP1 4NX",
    "addr:housenumber":"201",
    "addr:postcode":"ip1 4nx",
    "addr:street":"Henley Road",
    "iso:country":"GB",
    "sg:address":"201 Henley Road",
    "sg:city":"Ipswich",
    "sg:classifiers":[
        {
            "category":"Real Estate",
            "subcategory":"Surveying",
            "type":"Services"
        }
    ],
    "sg:phone":"+44 1473 253375",
    "sg:postcode":"IP1 4NX",
    "sg:province":"Suffolk",
    "sg:tags":[
        "surveyor",
        "quantity"
    ],
    "wof:name":"John Trower & Partner",
    "wof:placetype":"venue"
},
  "geometry": {"coordinates":[1.1508530378,52.0781517029],"type":"Point"}
}