{
  "type": "Feature",
  "properties": {
    "iso:country":"GB",
    "sg:address":"Hardy Avenue, Brierfield",
    "sg:city":"Nelson",
    "sg:classifiers":[
        {
            "category":"Health Services",
            "subcategory":"Nursing And Care Facility",
            "type":"Services"
        }
    ],
    "sg:phone":"+44 1282 619313",
    "sg:postcode":"BB9 5RN",
    "sg:province":"Lancashire",
    "sg:tags":[
        "home",
        "residential"
    ],
    "wof:name":"ASHBOURNE HOMES (DEVELOPMENTS) LTD",
    "wof:placetype":"venue"
},
  "geometry": {"coordinates":[-2.2342839241,53.8236045837],"type":"Point"}
}