{
  "type": "Feature",
  "properties": {
    "iso:country":"GB",
    "sg:address":"Wallhouse Road",
    "sg:city":"Erith",
    "sg:classifiers":[
        {
            "category":"Real Estate",
            "subcategory":"Developer",
            "type":"Services"
        }
    ],
    "sg:phone":"+44 1322 331556",
    "sg:postcode":"DA8 2JZ",
    "sg:province":"Kent",
    "sg:tags":[
        "property"
    ],
    "wof:name":"Thameside Estates Ltd.",
    "wof:placetype":"venue"
},
  "geometry": {"coordinates":[0.198795,51.472542],"type":"Point"}
}