{
  "type": "Feature",
  "properties": {
    "iso:country":"GB",
    "sg:address":"62 St Martins La",
    "sg:city":"London",
    "sg:classifiers":[
        {
            "category":"Banks & Credit Unions",
            "subcategory":"Financial Services",
            "type":"Services"
        }
    ],
    "sg:postcode":"WC2N 4AB",
    "sg:province":"Greater London",
    "sg:tags":[
        "consultant"
    ],
    "wof:name":"International Capital Services Ltd",
    "wof:placetype":"venue"
},
  "geometry": {"coordinates":[-0.127013,51.511372],"type":"Point"}
}