{
  "type": "Feature",
  "properties": {
    "iso:country":"GB",
    "sg:address":"382 Denby Dale Road, Durkar",
    "sg:city":"Wakefield",
    "sg:classifiers":[
        {
            "category":"Home & Garden",
            "subcategory":"Garden Supply",
            "type":"Retail Goods"
        }
    ],
    "sg:phone":"+44 1924 298365",
    "sg:postcode":"WF4 3AZ",
    "sg:province":"West Yorkshire",
    "sg:tags":[
        "nursery",
        "centre"
    ],
    "sg:website":"http://www.plantworld91.fsnet.co.uk",
    "wof:name":"Hampsons Plant World Ltd",
    "wof:placetype":"venue"
},
  "geometry": {"coordinates":[-1.521296978,53.652633667],"type":"Point"}
}