{
  "type": "Feature",
  "properties": {
    "addr:full":"88 Market Street Chorley Lancashire PR7 2SF",
    "addr:housenumber":"88",
    "addr:postcode":"pr7 2sf",
    "addr:street":"Market Street",
    "iso:country":"GB",
    "sg:address":"88 Market Street",
    "sg:city":"Chorley",
    "sg:classifiers":[
        {
            "category":"Fast Food",
            "type":"Food & Drink"
        }
    ],
    "sg:phone":"+44 1257 266069",
    "sg:postcode":"PR7 2SF",
    "sg:province":"Lancashire",
    "sg:tags":[
        "away",
        "take"
    ],
    "wof:name":"The Crispy Cob",
    "wof:placetype":"venue"
},
  "geometry": {"coordinates":[-2.6321110725,53.651512146],"type":"Point"}
}