{
  "type": "Feature",
  "properties": {
    "iso:country":"GB",
    "sg:address":"31 Barclay Street",
    "sg:city":"Stonehaven",
    "sg:classifiers":[
        {
            "category":"Farming",
            "subcategory":"Fish & Marine Products",
            "type":"Manufacturing & Wholesale Goods"
        },
        {
            "category":"Food & Beverages",
            "subcategory":"Meat & Fish",
            "type":"Retail Goods"
        }
    ],
    "sg:phone":"+44 1569 764873",
    "sg:postcode":"AB39 2AX",
    "sg:province":"Aberdeenshire",
    "sg:tags":[
        "fishmonger",
        "related"
    ],
    "wof:name":"Creel Fishmongers The",
    "wof:placetype":"venue"
},
  "geometry": {"coordinates":[-2.224239,56.95998],"type":"Point"}
}