{
  "type": "Feature",
  "properties": {
    "addr:full":"Gwbert Cardigan Ceredigion SA43 1PR",
    "addr:postcode":"sa43 1pr",
    "addr:street":"Gwbert",
    "iso:country":"GB",
    "sg:address":"Gwbert",
    "sg:city":"Cardigan",
    "sg:classifiers":[
        {
            "category":"Sports & Exercise",
            "subcategory":"Golf",
            "type":"Entertainment"
        }
    ],
    "sg:phone":"+44 1239 621698",
    "sg:postcode":"SA43 1PR",
    "sg:province":"Ceredigion",
    "sg:tags":[
        "club",
        "course"
    ],
    "wof:name":"Cardigan Golf Club",
    "wof:placetype":"venue"
},
  "geometry": {"coordinates":[-4.655044,52.086868],"type":"Point"}
}