{
  "type": "Feature",
  "properties": {
    "iso:country":"GB",
    "sg:address":"10 Rosebery Avenue",
    "sg:city":"Clerkenwell",
    "sg:classifiers":[
        {
            "category":"Education",
            "subcategory":"Special Training",
            "type":"Public Place"
        }
    ],
    "sg:phone":"+44 20 7713 7639",
    "sg:postcode":"EC1R 4TD",
    "sg:province":"Greater London",
    "sg:tags":[
        "product",
        "centre"
    ],
    "wof:name":"QA Training",
    "wof:placetype":"venue"
},
  "geometry": {"coordinates":[-0.110924,51.524426],"type":"Point"}
}