{
  "type": "Feature",
  "properties": {
    "addr:full":"St Lukes Road Corby Northamptonshire NN18 8LY",
    "addr:postcode":"nn18 8ly",
    "addr:street":"St Lukes Road",
    "iso:country":"GB",
    "sg:address":"St Lukes Road",
    "sg:city":"Corby",
    "sg:classifiers":[
        {
            "category":"Autos & Motor Vehicles",
            "subcategory":"Auto Supplies",
            "type":"Retail Goods"
        }
    ],
    "sg:postcode":"NN18 8LY",
    "sg:province":"Northamptonshire",
    "sg:tags":[
        "component"
    ],
    "wof:name":"Central Auto Supplies",
    "wof:placetype":"venue"
},
  "geometry": {"coordinates":[-0.6846389771,52.4855499268],"type":"Point"}
}