{
  "type": "Feature",
  "properties": {
    "iso:country":"GB",
    "sg:address":"1 Windsor Road",
    "sg:city":"Penarth",
    "sg:classifiers":[
        {
            "category":"Bars & Pubs",
            "type":"Food & Drink"
        }
    ],
    "sg:phone":"+44 29 2070 2821",
    "sg:postcode":"CF64 1JF",
    "sg:province":"The Vale of Glamorgan",
    "sg:tags":[
        "pubs",
        "inn"
    ],
    "wof:name":"The Windsor",
    "wof:placetype":"venue"
},
  "geometry": {"coordinates":[-3.1733810902,51.4387016296],"type":"Point"}
}