{
  "type": "Feature",
  "properties": {
    "addr:full":"128 Church Street, Eccles Manchester Greater Manchester M30 0LS",
    "addr:housenumber":"128",
    "addr:postcode":"m30 0ls",
    "addr:street":"Church Street",
    "iso:country":"GB",
    "sg:address":"128 Church Street, Eccles",
    "sg:city":"Manchester",
    "sg:classifiers":[
        {
            "category":"Shopping",
            "subcategory":"News",
            "type":"Retail Goods"
        }
    ],
    "sg:phone":"+44 161 789 3381",
    "sg:postcode":"M30 0LS",
    "sg:province":"Greater Manchester",
    "sg:tags":[
        "newsagent"
    ],
    "wof:name":"Newscrew",
    "wof:placetype":"venue"
},
  "geometry": {"coordinates":[-2.3386459351,53.4831428528],"type":"Point"}
}