{
  "type": "Feature",
  "properties": {
    "addr:full":"14 Station Road Lutterworth Leicestershire LE17 4AP",
    "addr:housenumber":"14",
    "addr:postcode":"le17 4ap",
    "addr:street":"Station Road",
    "iso:country":"GB",
    "sg:address":"14 Station Road",
    "sg:city":"Lutterworth",
    "sg:classifiers":[
        {
            "category":"Fast Food",
            "type":"Food & Drink"
        }
    ],
    "sg:phone":"+44 1455 552686",
    "sg:postcode":"LE17 4AP",
    "sg:province":"Leicestershire",
    "sg:tags":[
        "away",
        "meal",
        "outlet",
        "take"
    ],
    "wof:name":"The New Sunar Gow",
    "wof:placetype":"venue"
},
  "geometry": {"coordinates":[-1.198288,52.455284],"type":"Point"}
}