{
  "type": "Feature",
  "properties": {
    "iso:country":"GB",
    "sg:address":"9 Church Close, Clapham",
    "sg:city":"Worthing",
    "sg:classifiers":[
        {
            "category":"Home & Garden",
            "subcategory":"Carpets & Floor Coverings",
            "type":"Retail Goods"
        }
    ],
    "sg:postcode":"BN13 3XP",
    "sg:province":"West Sussex",
    "sg:tags":[
        "cleaner",
        "upholstery"
    ],
    "wof:name":"Safeclean",
    "wof:placetype":"venue"
},
  "geometry": {"coordinates":[-0.445024997,50.8471221924],"type":"Point"}
}