{
  "type": "Feature",
  "properties": {
    "iso:country":"GB",
    "sg:address":"115 Bradford Road",
    "sg:city":"Huddersfield",
    "sg:classifiers":[
        {
            "category":"Shopping",
            "subcategory":"Computers & Home Electronics",
            "type":"Retail Goods"
        }
    ],
    "sg:phone":"+44 1484 420065",
    "sg:postcode":"HD1 6DZ",
    "sg:province":"West Yorkshire",
    "sg:tags":[
        "electrical"
    ],
    "wof:name":"Shop 4 Security",
    "wof:placetype":"venue"
},
  "geometry": {"coordinates":[-1.7824469805,53.6557693481],"type":"Point"}
}