{
  "type": "Feature",
  "properties": {
    "addr:full":"9 Morris Road Dalkeith City of Edinburgh EH22 4ST",
    "addr:housenumber":"9",
    "addr:postcode":"eh22 4st",
    "addr:street":"Morris Road",
    "iso:country":"GB",
    "sg:address":"9 Morris Road",
    "sg:city":"Dalkeith",
    "sg:classifiers":[
        {
            "category":"Professional",
            "subcategory":"Printing & Photocopies",
            "type":"Services"
        }
    ],
    "sg:phone":"+44 131 663 1292",
    "sg:postcode":"EH22 4ST",
    "sg:province":"City of Edinburgh",
    "sg:tags":[
        "printer"
    ],
    "wof:name":"Portobello Printers",
    "wof:placetype":"venue"
},
  "geometry": {"coordinates":[-3.0555579662,55.8725471497],"type":"Point"}
}