{
  "type": "Feature",
  "properties": {
    "addr:full":"Ambulance Station, Inverurie Hospital Inverurie Aberdeenshire AB51 3UL",
    "addr:postcode":"ab51 3ul",
    "iso:country":"GB",
    "sg:address":"Ambulance Station, Inverurie Hospital",
    "sg:city":"Inverurie",
    "sg:classifiers":[
        {
            "category":"Health Services",
            "subcategory":"Hospital",
            "type":"Services"
        }
    ],
    "sg:phone":"+44 1467 621566",
    "sg:postcode":"AB51 3UL",
    "sg:province":"Aberdeenshire",
    "sg:tags":[
        "ambulance"
    ],
    "wof:name":"Scottish Ambulance Service",
    "wof:placetype":"venue"
},
  "geometry": {"coordinates":[-2.389794,57.291119],"type":"Point"}
}