{
  "type": "Feature",
  "properties": {
    "iso:country":"GB",
    "sg:address":"Unit 8, Springvale Mill, Preston St, Springvale Middleton",
    "sg:city":"Manchester",
    "sg:classifiers":[
        {
            "category":"Building & Trades",
            "subcategory":"Construction",
            "type":"Services"
        }
    ],
    "sg:phone":"+44 161 643 1741",
    "sg:postcode":"M24 2HN",
    "sg:province":"Greater Manchester",
    "sg:tags":[
        "joinery"
    ],
    "wof:name":"Middleton Pallets",
    "wof:placetype":"venue"
},
  "geometry": {"coordinates":[-2.191324,53.5494],"type":"Point"}
}