{
  "type": "Feature",
  "properties": {
    "addr:full":"75 Lion Road Bexleyheath Kent DA6 8NW",
    "addr:housenumber":"75",
    "addr:postcode":"da6 8nw",
    "addr:street":"Lion Road",
    "iso:country":"GB",
    "sg:address":"75 Lion Road",
    "sg:city":"Bexleyheath",
    "sg:classifiers":[
        {
            "category":"Travel",
            "subcategory":"Hotels & Motels",
            "type":"Entertainment"
        }
    ],
    "sg:postcode":"DA6 8NW",
    "sg:province":"Kent",
    "sg:tags":[
        "house",
        "guest"
    ],
    "wof:name":"Brooklands Guest House",
    "wof:placetype":"venue"
},
  "geometry": {"coordinates":[0.1361500025,51.4558143616],"type":"Point"}
}