{
  "type": "Feature",
  "properties": {
    "addr:full":"72-74 Newington Rd Edinburgh City of Edinburgh EH9 1QN",
    "addr:housenumber":"72-74",
    "addr:postcode":"eh9 1qn",
    "addr:street":"Newington Rd",
    "iso:country":"GB",
    "sg:address":"72-74 Newington Rd",
    "sg:city":"Edinburgh",
    "sg:classifiers":[
        {
            "category":"Bars & Pubs",
            "type":"Food & Drink"
        }
    ],
    "sg:phone":"+44 131 668 1465",
    "sg:postcode":"EH9 1QN",
    "sg:province":"City of Edinburgh",
    "sg:tags":[
        "pubs",
        "inn"
    ],
    "wof:name":"Highlander The",
    "wof:placetype":"venue"
},
  "geometry": {"coordinates":[-3.188699,55.938049],"type":"Point"}
}