{
  "type": "Feature",
  "properties": {
    "addr:full":"Unit D, Level 1, The Wellgate Dundee Dundee City DD1 2DB",
    "addr:housenumber":"unit d level 1",
    "addr:postcode":"dd1 2db",
    "addr:street":"The Wellgate",
    "iso:country":"GB",
    "sg:address":"Unit D, Level 1, The Wellgate",
    "sg:city":"Dundee",
    "sg:classifiers":[
        {
            "category":"Shopping",
            "subcategory":"Books",
            "type":"Retail Goods"
        }
    ],
    "sg:phone":"+44 1382 204730",
    "sg:postcode":"DD1 2DB",
    "sg:province":"Dundee City",
    "sg:tags":[
        "bookseller",
        "retailer"
    ],
    "wof:name":"The Works",
    "wof:placetype":"venue"
},
  "geometry": {"coordinates":[-2.967609,56.461376],"type":"Point"}
}