{
  "type": "Feature",
  "properties": {
    "addr:full":"Colarado House, 300 Thames Valley Park Drive Reading Berkshire RG6 1RD",
    "addr:housenumber":"300",
    "addr:postcode":"rg6 1rd",
    "addr:street":"Thames Valley Park Drive",
    "iso:country":"GB",
    "sg:address":"Colarado House, 300 Thames Valley Park Drive",
    "sg:city":"Reading",
    "sg:classifiers":[
        {
            "category":"Professional",
            "subcategory":"Computer Services",
            "type":"Services"
        }
    ],
    "sg:phone":"+44 118 952 2000",
    "sg:postcode":"RG6 1RD",
    "sg:province":"Berkshire",
    "sg:tags":[
        "system",
        "software"
    ],
    "wof:name":"Peoplesoft (U K) Ltd.",
    "wof:placetype":"venue"
},
  "geometry": {"coordinates":[-0.933087,51.460403],"type":"Point"}
}