{
  "type": "Feature",
  "properties": {
    "iso:country":"GB",
    "sg:address":"Dorset Ho, 20-22 Christchurch Rd",
    "sg:city":"Bournemouth",
    "sg:classifiers":[
        {
            "category":"Community Center",
            "subcategory":"Youth",
            "type":"Public Place"
        }
    ],
    "sg:phone":"+44 1202 456206",
    "sg:postcode":"BH1 3NL",
    "sg:province":"Dorset",
    "sg:tags":[
        "organisation",
        "centre"
    ],
    "wof:name":"Bournemouth Youth Service",
    "wof:placetype":"venue"
},
  "geometry": {"coordinates":[-1.86232,50.72245],"type":"Point"}
}