{
  "type": "Feature",
  "properties": {
    "addr:full":"95 Bearwood Hill Road Burton-on-trent Derbyshire DE15 0JP",
    "addr:housenumber":"95",
    "addr:postcode":"de15 0jp",
    "addr:street":"Bearwood Hill Road",
    "iso:country":"GB",
    "sg:address":"95 Bearwood Hill Road",
    "sg:city":"Burton-on-trent",
    "sg:classifiers":[
        {
            "category":"Shopping",
            "subcategory":"News",
            "type":"Retail Goods"
        }
    ],
    "sg:phone":"+44 1283 563803",
    "sg:postcode":"DE15 0JP",
    "sg:province":"Derbyshire",
    "sg:tags":[
        "newsagent"
    ],
    "wof:name":"P & T News",
    "wof:placetype":"venue"
},
  "geometry": {"coordinates":[-1.607353,52.806728],"type":"Point"}
}