{
  "type": "Feature",
  "properties": {
    "addr:full":"Abbeyfield Road Nottingham Nottinghamshire NG7 2SZ",
    "addr:postcode":"ng7 2sz",
    "addr:street":"Abbeyfield Road",
    "iso:country":"GB",
    "sg:address":"Abbeyfield Road",
    "sg:city":"Nottingham",
    "sg:classifiers":[
        {
            "category":"Utilities",
            "subcategory":"Natural Gas",
            "type":"Services"
        }
    ],
    "sg:phone":"+44 115 986 1744",
    "sg:postcode":"NG7 2SZ",
    "sg:province":"Nottinghamshire",
    "sg:tags":[
        "supplier"
    ],
    "wof:name":"Nottingham Calor Centre",
    "wof:placetype":"venue"
},
  "geometry": {"coordinates":[-1.1742889881,52.9355354309],"type":"Point"}
}