{
  "type": "Feature",
  "properties": {
    "addr:full":"Richmond Street West Bromwich West Midlands B70 0DD",
    "addr:postcode":"b70 0dd",
    "addr:street":"Richmond Street",
    "iso:country":"GB",
    "sg:address":"Richmond Street",
    "sg:city":"West Bromwich",
    "sg:classifiers":[
        {
            "category":"Retail",
            "subcategory":"Storage",
            "type":"Services"
        }
    ],
    "sg:phone":"+44 121 520 3532",
    "sg:postcode":"B70 0DD",
    "sg:province":"West Midlands",
    "sg:tags":[
        "household",
        "removal",
        "operation",
        "facility"
    ],
    "wof:name":"We 'R' Storage Ltd",
    "wof:placetype":"venue"
},
  "geometry": {"coordinates":[-2.022062,52.531647],"type":"Point"}
}