{
  "type": "Feature",
  "properties": {
    "iso:country":"GB",
    "sg:address":"Station Road, Woolhampton",
    "sg:city":"Reading",
    "sg:classifiers":[
        {
            "category":"Real Estate",
            "subcategory":"Architect",
            "type":"Services"
        }
    ],
    "sg:phone":"+44 118 971 3363",
    "sg:postcode":"RG7 5SE",
    "sg:province":"Berkshire",
    "sg:tags":[
        "architectural"
    ],
    "wof:name":"Woolhampton Design Centre Ltd.",
    "wof:placetype":"venue"
},
  "geometry": {"coordinates":[-1.1790479422,51.3976287842],"type":"Point"}
}