{
  "type": "Feature",
  "properties": {
    "addr:full":"84 Chatham Road London Greater London SW11 6HG",
    "addr:housenumber":"84",
    "addr:postcode":"sw11 6hg",
    "addr:street":"Chatham Road",
    "iso:country":"GB",
    "sg:address":"84 Chatham Road",
    "sg:city":"London",
    "sg:classifiers":[
        {
            "category":"Utilities",
            "subcategory":"Fuel Oil & Lpg",
            "type":"Services"
        }
    ],
    "sg:phone":"+44 20 7738 9696",
    "sg:postcode":"SW11 6HG",
    "sg:province":"Greater London",
    "sg:tags":[
        "coal",
        "smokeless"
    ],
    "wof:name":"A G Hutchings & Sons",
    "wof:placetype":"venue"
},
  "geometry": {"coordinates":[-0.1638910025,51.4549331665],"type":"Point"}
}