{
  "type": "Feature",
  "properties": {
    "addr:full":"85 Leven Rd Stockton On Tees Durham TS20 1DB",
    "addr:housenumber":"85",
    "addr:postcode":"ts20 1db",
    "addr:street":"Leven Rd",
    "iso:country":"GB",
    "sg:address":"85 Leven Rd",
    "sg:city":"Stockton On Tees",
    "sg:classifiers":[
        {
            "category":"Personal",
            "type":"Services"
        }
    ],
    "sg:phone":"+44 1642 659326",
    "sg:postcode":"TS20 1DB",
    "sg:province":"Durham",
    "sg:tags":[
        "delivery"
    ],
    "wof:name":"Booths Express Deliveries",
    "wof:placetype":"venue"
},
  "geometry": {"coordinates":[-1.3172010183,54.5868606567],"type":"Point"}
}