{
  "type": "Feature",
  "properties": {
    "addr:full":"2 Wyedale Avenue Bristol City of Bristol BS9 2QQ",
    "addr:housenumber":"2",
    "addr:postcode":"bs9 2qq",
    "addr:street":"Wyedale Avenue",
    "iso:country":"GB",
    "sg:address":"2 Wyedale Avenue",
    "sg:city":"Bristol",
    "sg:classifiers":[
        {
            "category":"Education",
            "subcategory":"Dance Studio",
            "type":"Public Place"
        }
    ],
    "sg:phone":"+44 117 968 8078",
    "sg:postcode":"BS9 2QQ",
    "sg:province":"City of Bristol",
    "sg:tags":[
        "school",
        "dancing"
    ],
    "wof:name":"Annette Adams School of Dancing",
    "wof:placetype":"venue"
},
  "geometry": {"coordinates":[-2.645138979,51.4904518127],"type":"Point"}
}