{
  "type": "Feature",
  "properties": {
    "addr:full":"57-63 Princess St Manchester Greater Manchester M2 4EQ",
    "addr:housenumber":"57-63",
    "addr:postcode":"m2 4eq",
    "addr:street":"Princess St",
    "iso:country":"GB",
    "sg:address":"57-63 Princess St",
    "sg:city":"Manchester",
    "sg:classifiers":[
        {
            "category":"Restaurant",
            "type":"Food & Drink"
        }
    ],
    "sg:postcode":"M2 4EQ",
    "sg:province":"Greater Manchester",
    "wof:name":"Carol,Francis,",
    "wof:placetype":"venue"
},
  "geometry": {"coordinates":[-2.243252,53.47937],"type":"Point"}
}