{
  "type": "Feature",
  "properties": {
    "addr:full":"5 High Street Carluke South Lanarkshire ML8 4AL",
    "addr:housenumber":"5",
    "addr:postcode":"ml8 4al",
    "addr:street":"High Street",
    "iso:country":"GB",
    "sg:address":"5 High Street",
    "sg:city":"Carluke",
    "sg:classifiers":[
        {
            "category":"Bars & Pubs",
            "type":"Food & Drink"
        }
    ],
    "sg:phone":"+44 1555 772143",
    "sg:postcode":"ML8 4AL",
    "sg:province":"South Lanarkshire",
    "sg:tags":[
        "pubs",
        "inn"
    ],
    "wof:name":"The Wee Thackitt Inn",
    "wof:placetype":"venue"
},
  "geometry": {"coordinates":[-3.8401260376,55.7350502014],"type":"Point"}
}