{
  "type": "Feature",
  "properties": {
    "addr:full":"85 North Deeside Rd Aberdeen Aberdeen City AB12 3AX",
    "addr:housenumber":"85",
    "addr:postcode":"ab12 3ax",
    "addr:street":"North Deeside Rd",
    "iso:country":"GB",
    "sg:address":"85 North Deeside Rd",
    "sg:city":"Aberdeen",
    "sg:classifiers":[
        {
            "category":"Building & Trades",
            "subcategory":"Construction",
            "type":"Services"
        }
    ],
    "sg:phone":"+44 1224 868830",
    "sg:postcode":"AB12 3AX",
    "sg:province":"Aberdeen City",
    "sg:tags":[
        "builder"
    ],
    "wof:name":"Westburn Properties",
    "wof:placetype":"venue"
},
  "geometry": {"coordinates":[-2.0895290375,57.1068000793],"type":"Point"}
}