{
  "type": "Feature",
  "properties": {
    "addr:full":"44 Middle Field Barrow-in-furness Cumbria LA14 4BX",
    "addr:housenumber":"44",
    "addr:postcode":"la14 4bx",
    "addr:street":"Middle Field",
    "iso:country":"GB",
    "sg:address":"44 Middle Field",
    "sg:city":"Barrow-in-furness",
    "sg:classifiers":[
        {
            "category":"Food & Beverages",
            "subcategory":"Liquor & Beverages",
            "type":"Retail Goods"
        }
    ],
    "sg:postcode":"LA14 4BX",
    "sg:province":"Cumbria",
    "sg:tags":[
        "beer",
        "spirit",
        "wines"
    ],
    "wof:name":"Middlefield Off Licence",
    "wof:placetype":"venue"
},
  "geometry": {"coordinates":[-3.229629,54.141026],"type":"Point"}
}