{
  "type": "Feature",
  "properties": {
    "addr:full":"Carriage House, Little Broom Street, Highgate Birmingham West Midlands B12 0EU",
    "addr:postcode":"b12 0eu",
    "addr:street":"Little Broom Street Highgate",
    "iso:country":"GB",
    "sg:address":"Carriage House, Little Broom Street, Highgate",
    "sg:city":"Birmingham",
    "sg:classifiers":[
        {
            "category":"Building & Trades",
            "subcategory":"Construction",
            "type":"Services"
        }
    ],
    "sg:phone":"+44 121 766 6633",
    "sg:postcode":"B12 0EU",
    "sg:province":"West Midlands",
    "sg:tags":[
        "roofing",
        "contracting"
    ],
    "wof:name":"Construction Profiles Ltd",
    "wof:placetype":"venue"
},
  "geometry": {"coordinates":[-1.881149,52.469769],"type":"Point"}
}