{
  "type": "Feature",
  "properties": {
    "iso:country":"GB",
    "sg:address":"1 Upr Gladstone Rd",
    "sg:city":"Chesham",
    "sg:classifiers":[
        {
            "category":"Professional",
            "subcategory":"Accounting & Tax Preparation",
            "type":"Services"
        }
    ],
    "sg:postcode":"HP5 3AF",
    "sg:province":"Buckinghamshire",
    "sg:tags":[
        "accountant"
    ],
    "wof:name":"Badcock,Peter G,",
    "wof:placetype":"venue"
},
  "geometry": {"coordinates":[-0.608874,51.710377],"type":"Point"}
}