{
  "type": "Feature",
  "properties": {
    "addr:full":"Unit 8, Harpurhey District Centre, Conran Street Manchester Greater Manchester M9 1DH",
    "addr:housenumber":"unit 8",
    "addr:postcode":"m9 1dh",
    "addr:street":"District Centre Conran Street",
    "iso:country":"GB",
    "sg:address":"Unit 8, Harpurhey District Centre, Conran Street",
    "sg:city":"Manchester",
    "sg:classifiers":[
        {
            "category":"Shopping",
            "subcategory":"Pharmacy",
            "type":"Retail Goods"
        }
    ],
    "sg:phone":"+44 161 205 2164",
    "sg:postcode":"M9 1DH",
    "sg:province":"Greater Manchester",
    "sg:tags":[
        "pharmacist",
        "chemist"
    ],
    "wof:name":"Hills Pharmacy",
    "wof:placetype":"venue"
},
  "geometry": {"coordinates":[-2.21412,53.522308],"type":"Point"}
}