{
  "type": "Feature",
  "properties": {
    "addr:full":"Argent Road Queenborough Kent ME11 5JP",
    "addr:postcode":"me11 5jp",
    "addr:street":"Argent Road",
    "iso:country":"GB",
    "sg:address":"Argent Road",
    "sg:city":"Queenborough",
    "sg:classifiers":[
        {
            "category":"Home & Garden",
            "subcategory":"Garden Supply",
            "type":"Retail Goods"
        }
    ],
    "sg:phone":"+44 1795 580734",
    "sg:postcode":"ME11 5JP",
    "sg:province":"Kent",
    "sg:tags":[
        "ornament"
    ],
    "wof:name":"Danicraft Ltd.",
    "wof:placetype":"venue"
},
  "geometry": {"coordinates":[0.7485280037,51.4056587219],"type":"Point"}
}