{
  "type": "Feature",
  "properties": {
    "iso:country":"GB",
    "sg:address":"Queen Elizabeth Road",
    "sg:city":"Nuneaton",
    "sg:classifiers":[
        {
            "category":"Farming",
            "subcategory":"Nursery",
            "type":"Manufacturing & Wholesale Goods"
        }
    ],
    "sg:phone":"+44 24 7638 2040",
    "sg:postcode":"CV10 9AT",
    "sg:province":"Leicestershire",
    "sg:tags":[
        "creche"
    ],
    "wof:name":"Camp Hill Nursery School",
    "wof:placetype":"venue"
},
  "geometry": {"coordinates":[-1.511848,52.531376],"type":"Point"}
}