{
  "type": "Feature",
  "properties": {
    "iso:country":"GB",
    "sg:address":"10 Martin Hardie Way",
    "sg:city":"Tonbridge",
    "sg:classifiers":[
        {
            "category":"Food & Beverages",
            "subcategory":"Bakery",
            "type":"Retail Goods"
        }
    ],
    "sg:phone":"+44 1732 355968",
    "sg:postcode":"TN10 4AE",
    "sg:province":"Kent",
    "sg:tags":[
        "baker"
    ],
    "wof:name":"Clarks Bakery",
    "wof:placetype":"venue"
},
  "geometry": {"coordinates":[0.2940860093,51.2115402222],"type":"Point"}
}