{
  "type": "Feature",
  "properties": {
    "iso:country":"GB",
    "sg:address":"Blackhills Lane, Upper Killay",
    "sg:city":"Swansea",
    "sg:classifiers":[
        {
            "category":"Sports & Exercise",
            "subcategory":"Golf",
            "type":"Entertainment"
        }
    ],
    "sg:phone":"+44 1792 203648",
    "sg:postcode":"SA2 7JN",
    "sg:province":"Swansea",
    "sg:tags":[
        "club",
        "course"
    ],
    "wof:name":"Fairwood Park Golf Club",
    "wof:placetype":"venue"
},
  "geometry": {"coordinates":[-4.015322,51.618385],"type":"Point"}
}