{
  "type": "Feature",
  "properties": {
    "addr:full":"Glasgow Road, Milngavie Glasgow East Dunbartonshire G62 6HX",
    "addr:postcode":"g62 6hx",
    "addr:street":"Glasgow Road",
    "iso:country":"GB",
    "sg:address":"Glasgow Road, Milngavie",
    "sg:city":"Glasgow",
    "sg:classifiers":[
        {
            "category":"Farming",
            "subcategory":"Nursery",
            "type":"Manufacturing & Wholesale Goods"
        },
        {
            "category":"Social Services",
            "subcategory":"Child Care",
            "type":"Services"
        }
    ],
    "sg:phone":"+44 141 956 2891",
    "sg:postcode":"G62 6HX",
    "sg:province":"East Dunbartonshire",
    "sg:tags":[
        "creche"
    ],
    "wof:name":"Kilmartinny Nursery",
    "wof:placetype":"venue"
},
  "geometry": {"coordinates":[-4.317124,55.936829],"type":"Point"}
}