{
  "type": "Feature",
  "properties": {
    "addr:full":"Penblewyn Farm Narberth Carmarthenshire SA67 7NX",
    "addr:postcode":"sa67 7nx",
    "iso:country":"GB",
    "sg:address":"Penblewyn Farm",
    "sg:city":"Narberth",
    "sg:classifiers":[
        {
            "category":"Farming",
            "subcategory":"Farm",
            "type":"Manufacturing & Wholesale Goods"
        }
    ],
    "sg:phone":"+44 1834 861059",
    "sg:postcode":"SA67 7NX",
    "sg:province":"Carmarthenshire",
    "sg:tags":[
        "mixed",
        "crop"
    ],
    "wof:name":"C Hartt",
    "wof:placetype":"venue"
},
  "geometry": {"coordinates":[-4.744227,51.80117],"type":"Point"}
}