{
  "type": "Feature",
  "properties": {
    "addr:full":"95b Kingston Rd New Malden Surrey KT3 3PA",
    "addr:housenumber":"95b",
    "addr:postcode":"kt3 3pa",
    "addr:street":"Kingston Rd",
    "iso:country":"GB",
    "sg:address":"95b Kingston Rd",
    "sg:city":"New Malden",
    "sg:classifiers":[
        {
            "category":"Retail",
            "subcategory":"Auto Repair",
            "type":"Services"
        }
    ],
    "sg:phone":"+44 20 8949 6033",
    "sg:postcode":"KT3 3PA",
    "sg:province":"Surrey",
    "sg:tags":[
        "modification",
        "garage"
    ],
    "wof:name":"Lw Autos",
    "wof:placetype":"venue"
},
  "geometry": {"coordinates":[-0.263293,51.400223],"type":"Point"}
}