{
  "type": "Feature",
  "properties": {
    "iso:country":"GB",
    "sg:address":"Room 503 Trelawney House, Dock Road",
    "sg:city":"Felixstowe",
    "sg:classifiers":[
        {
            "category":"Freight",
            "type":"Transportation"
        }
    ],
    "sg:phone":"+44 1394 674468",
    "sg:postcode":"IP11 3GG",
    "sg:province":"Suffolk",
    "sg:tags":[
        "forwarders"
    ],
    "wof:name":"Imorex Shipping Services Ltd.",
    "wof:placetype":"venue"
},
  "geometry": {"coordinates":[1.327158,51.955593],"type":"Point"}
}