{
  "type": "Feature",
  "properties": {
    "addr:full":"2 Kings Drive Egremont Cumbria CA22 2LE",
    "addr:housenumber":"2",
    "addr:postcode":"ca22 2le",
    "addr:street":"Kings Drive",
    "iso:country":"GB",
    "sg:address":"2 Kings Drive",
    "sg:city":"Egremont",
    "sg:classifiers":[
        {
            "category":"Building & Trades",
            "subcategory":"Cleaning & Sanitation",
            "type":"Services"
        }
    ],
    "sg:postcode":"CA22 2LE",
    "sg:province":"Cumbria",
    "sg:tags":[
        "commercial"
    ],
    "wof:name":"Tracey's Industrial Cleaners",
    "wof:placetype":"venue"
},
  "geometry": {"coordinates":[-3.53604,54.475494],"type":"Point"}
}