{
  "type": "Feature",
  "properties": {
    "addr:full":"Unit 3 Richardson House, Sherwood Avenue Newark Nottinghamshire NG24 1QF",
    "addr:housenumber":"unit 3",
    "addr:postcode":"ng24 1qf",
    "addr:street":"Sherwood Avenue",
    "iso:country":"GB",
    "sg:address":"Unit 3 Richardson House, Sherwood Avenue",
    "sg:city":"Newark",
    "sg:classifiers":[
        {
            "category":"Organizations",
            "subcategory":"Non-profit Organization",
            "type":"Services"
        }
    ],
    "sg:phone":"+44 1636 612777",
    "sg:postcode":"NG24 1QF",
    "sg:province":"Nottinghamshire",
    "sg:tags":[
        "alarm",
        "system"
    ],
    "wof:name":"Trisec Ltd.",
    "wof:placetype":"venue"
},
  "geometry": {"coordinates":[-0.804403,53.073574],"type":"Point"}
}