{
  "type": "Feature",
  "properties": {
    "addr:full":"5 Terrace Walk Bath Bath and North East Somerset BA1 1LN",
    "addr:housenumber":"5",
    "addr:postcode":"ba1 1ln",
    "addr:street":"Terrace Walk",
    "iso:country":"GB",
    "sg:address":"5 Terrace Walk",
    "sg:city":"Bath",
    "sg:classifiers":[
        {
            "category":"Food & Beverages",
            "subcategory":"Liquor & Beverages",
            "type":"Retail Goods"
        }
    ],
    "sg:phone":"+44 1225 460280",
    "sg:postcode":"BA1 1LN",
    "sg:province":"Bath and North East Somerset",
    "sg:tags":[
        "beer",
        "wine",
        "spirit",
        "wines"
    ],
    "wof:name":"Threshers",
    "wof:placetype":"venue"
},
  "geometry": {"coordinates":[-2.3578488827,51.3812828064],"type":"Point"}
}