{
  "type": "Feature",
  "properties": {
    "iso:country":"GB",
    "sg:address":"The Surgery, Glebe Farm Ct",
    "sg:city":"Cheltenham",
    "sg:classifiers":[
        {
            "category":"Health Services",
            "subcategory":"Doctor",
            "type":"Services"
        }
    ],
    "sg:phone":"+44 1242 863333",
    "sg:postcode":"GL51 5EB",
    "sg:province":"Gloucestershire",
    "sg:tags":[
        "practitioners"
    ],
    "wof:name":"Watkins, D",
    "wof:placetype":"venue"
},
  "geometry": {"coordinates":[-2.07846,51.898048],"type":"Point"}
}