{
  "type": "Feature",
  "properties": {
    "iso:country":"GB",
    "sg:address":"Community Hall, Ilkeston Road",
    "sg:city":"Heanor",
    "sg:classifiers":[
        {
            "category":"Organizations",
            "subcategory":"Membership Organization",
            "type":"Services"
        }
    ],
    "sg:phone":"+44 1773 710939",
    "sg:postcode":"DE75 7AG",
    "sg:province":"Derbyshire",
    "sg:tags":[
        "club"
    ],
    "wof:name":"Stepping Stones (Amber Valley)",
    "wof:placetype":"venue"
},
  "geometry": {"coordinates":[-1.353434,53.013737],"type":"Point"}
}