{
  "type": "Feature",
  "properties": {
    "addr:full":"101 Wellington Road North Stockport Cheshire SK4 2LP",
    "addr:housenumber":"101",
    "addr:postcode":"sk4 2lp",
    "addr:street":"Wellington Road North",
    "iso:country":"GB",
    "sg:address":"101 Wellington Road North",
    "sg:city":"Stockport",
    "sg:classifiers":[
        {
            "category":"Retail",
            "subcategory":"Driving School",
            "type":"Services"
        },
        {
            "category":"Organizations",
            "subcategory":"Professional Association",
            "type":"Services"
        }
    ],
    "sg:phone":"+44 161 429 9669",
    "sg:postcode":"SK4 2LP",
    "sg:province":"Cheshire",
    "sg:tags":[
        "organisation",
        "motoring"
    ],
    "wof:name":"Motor Schools Association Of Great Britain Ltd",
    "wof:placetype":"venue"
},
  "geometry": {"coordinates":[-2.169601,53.416012],"type":"Point"}
}