{
  "type": "Feature",
  "properties": {
    "iso:country":"GB",
    "sg:address":"1 Great Shuttlesfield Cottages, Acrise",
    "sg:city":"Folkestone",
    "sg:classifiers":[
        {
            "category":"Building & Trades",
            "subcategory":"Construction",
            "type":"Services"
        }
    ],
    "sg:phone":"+44 1303 862986",
    "sg:postcode":"CT18 8JZ",
    "sg:province":"Kent",
    "sg:tags":[
        "roofing"
    ],
    "wof:name":"Town & Country Roofing Services",
    "wof:placetype":"venue"
},
  "geometry": {"coordinates":[1.14882,51.131893],"type":"Point"}
}