{
  "type": "Feature",
  "properties": {
    "addr:full":"16 Briar Ave Oldham Lancashire OL4 2PG",
    "addr:housenumber":"16",
    "addr:postcode":"ol4 2pg",
    "addr:street":"Briar Ave",
    "iso:country":"GB",
    "sg:address":"16 Briar Ave",
    "sg:city":"Oldham",
    "sg:classifiers":[
        {
            "category":"Building & Trades",
            "subcategory":"Construction",
            "type":"Services"
        }
    ],
    "sg:postcode":"OL4 2PG",
    "sg:province":"Lancashire",
    "sg:tags":[
        "dry",
        "lining",
        "plasterers",
        "screeders"
    ],
    "wof:name":"Baker,R A,",
    "wof:placetype":"venue"
},
  "geometry": {"coordinates":[-2.0796720982,53.5540313721],"type":"Point"}
}