{
  "type": "Feature",
  "properties": {
    "addr:full":"1a St. Nicholas St Colchester Essex CO1 1LB",
    "addr:housenumber":"1a",
    "addr:postcode":"co1 1lb",
    "addr:street":"St. Nicholas St",
    "iso:country":"GB",
    "sg:address":"1a St. Nicholas St",
    "sg:city":"Colchester",
    "sg:classifiers":[
        {
            "category":"Home & Garden",
            "subcategory":"Furniture",
            "type":"Retail Goods"
        }
    ],
    "sg:postcode":"CO1 1LB",
    "sg:province":"Essex",
    "wof:name":"Durham Pine",
    "wof:placetype":"venue"
},
  "geometry": {"coordinates":[0.902421,51.889408],"type":"Point"}
}