{
  "type": "Feature",
  "properties": {
    "addr:full":"97 Park Road Wallsend Tyne and Wear NE28 7LP",
    "addr:housenumber":"97",
    "addr:postcode":"ne28 7lp",
    "addr:street":"Park Road",
    "iso:country":"GB",
    "sg:address":"97 Park Road",
    "sg:city":"Wallsend",
    "sg:classifiers":[
        {
            "category":"Health Services",
            "subcategory":"Dentist",
            "type":"Services"
        }
    ],
    "sg:phone":"+44 191 262 4254",
    "sg:postcode":"NE28 7LP",
    "sg:province":"Tyne and Wear",
    "wof:name":"Park Dental Practice",
    "wof:placetype":"venue"
},
  "geometry": {"coordinates":[-1.5310490131,54.9920883179],"type":"Point"}
}