{
  "type": "Feature",
  "properties": {
    "iso:country":"GB",
    "sg:address":"Lancaster Boys Club, Dallas Road",
    "sg:city":"Lancaster",
    "sg:classifiers":[
        {
            "category":"Community Center",
            "subcategory":"Youth",
            "type":"Public Place"
        }
    ],
    "sg:phone":"+44 1524 849106",
    "sg:postcode":"LA1 1TP",
    "sg:province":"Lancashire",
    "sg:tags":[
        "organisation",
        "centre"
    ],
    "wof:name":"Dallas Road Kids Club",
    "wof:placetype":"venue"
},
  "geometry": {"coordinates":[-2.7990291119,54.0445365906],"type":"Point"}
}