{
  "type": "Feature",
  "properties": {
    "addr:full":"50 Grove Road Portland Dorset DT5 1DA",
    "addr:housenumber":"50",
    "addr:postcode":"dt5 1da",
    "addr:street":"Grove Road",
    "iso:country":"GB",
    "sg:address":"50 Grove Road",
    "sg:city":"Portland",
    "sg:classifiers":[
        {
            "category":"Bars & Pubs",
            "type":"Food & Drink"
        },
        {
            "category":"Community Center",
            "subcategory":"Social",
            "type":"Public Place"
        }
    ],
    "sg:phone":"+44 1305 820473",
    "sg:postcode":"DT5 1DA",
    "sg:province":"Dorset",
    "sg:tags":[
        "pubs",
        "house",
        "inn",
        "activity"
    ],
    "wof:name":"The Clifton Hotel",
    "wof:placetype":"venue"
},
  "geometry": {"coordinates":[-2.428659,50.551365],"type":"Point"}
}