{
  "type": "Feature",
  "properties": {
    "addr:full":"Craigs Farm Girvan South Ayrshire KA26 9RS",
    "addr:postcode":"ka26 9rs",
    "iso:country":"GB",
    "sg:address":"Craigs Farm",
    "sg:city":"Girvan",
    "sg:classifiers":[
        {
            "category":"Farming",
            "subcategory":"Livestock Farm",
            "type":"Manufacturing & Wholesale Goods"
        }
    ],
    "sg:phone":"+44 1465 811582",
    "sg:postcode":"KA26 9RS",
    "sg:province":"South Ayrshire",
    "sg:tags":[
        "others"
    ],
    "wof:name":"N Gillon",
    "wof:placetype":"venue"
},
  "geometry": {"coordinates":[-4.7827692032,55.2605895996],"type":"Point"}
}