{
  "type": "Feature",
  "properties": {
    "addr:full":"1 Birshaw Close, Oldham Road, Shaw Oldham Lancashire OL2 8SU",
    "addr:housenumber":"1",
    "addr:postcode":"ol2 8su",
    "addr:street":"Birshaw Close Oldham Road",
    "iso:country":"GB",
    "sg:address":"1 Birshaw Close, Oldham Road, Shaw",
    "sg:city":"Oldham",
    "sg:classifiers":[
        {
            "category":"Utilities",
            "subcategory":"Refuse",
            "type":"Services"
        }
    ],
    "sg:phone":"+44 1706 848961",
    "sg:postcode":"OL2 8SU",
    "sg:province":"Lancashire",
    "sg:tags":[
        "skip",
        "hire"
    ],
    "wof:name":"Shaw Mini Skips",
    "wof:placetype":"venue"
},
  "geometry": {"coordinates":[-2.098379,53.5695],"type":"Point"}
}