{
  "type": "Feature",
  "properties": {
    "addr:full":"Gibralter Business Park, Off Waterloo Rd Pudsey West Yorkshire LS28 8DF",
    "addr:postcode":"ls28 8df",
    "addr:street":"Waterloo Rd",
    "iso:country":"GB",
    "sg:address":"Gibralter Business Park, Off Waterloo Rd",
    "sg:city":"Pudsey",
    "sg:classifiers":[
        {
            "category":"Building & Trades",
            "subcategory":"Construction",
            "type":"Services"
        }
    ],
    "sg:phone":"+44 113 236 1379",
    "sg:postcode":"LS28 8DF",
    "sg:province":"West Yorkshire",
    "sg:tags":[
        "builder"
    ],
    "wof:name":"Northern Fair Traders Association",
    "wof:placetype":"venue"
},
  "geometry": {"coordinates":[-1.6562689543,53.7976837158],"type":"Point"}
}