{
  "type": "Feature",
  "properties": {
    "iso:country":"GB",
    "sg:address":"47 King Georges Avenue",
    "sg:city":"Coventry",
    "sg:classifiers":[
        {
            "category":"Building & Trades",
            "subcategory":"Plumbing",
            "type":"Services"
        },
        {
            "category":"Building & Trades",
            "subcategory":"Construction",
            "type":"Services"
        }
    ],
    "sg:phone":"+44 24 7668 6204",
    "sg:postcode":"CV6 6FE",
    "sg:province":"Warwickshire",
    "sg:tags":[
        "central",
        "installation",
        "system",
        "servicing",
        "heating"
    ],
    "wof:name":"Mann Builders",
    "wof:placetype":"venue"
},
  "geometry": {"coordinates":[-1.49386,52.439487],"type":"Point"}
}