{
  "type": "Feature",
  "properties": {
    "addr:full":"5 Prospect St, Caversham Reading Berkshire RG4 8JB",
    "addr:housenumber":"5",
    "addr:postcode":"rg4 8jb",
    "addr:street":"Prospect St",
    "iso:country":"GB",
    "sg:address":"5 Prospect St, Caversham",
    "sg:city":"Reading",
    "sg:classifiers":[
        {
            "category":"Restaurant",
            "type":"Food & Drink"
        }
    ],
    "sg:phone":"+44 118 946 3400",
    "sg:postcode":"RG4 8JB",
    "sg:province":"Berkshire",
    "wof:name":"The Fondue Pot",
    "wof:placetype":"venue"
},
  "geometry": {"coordinates":[-0.9724569917,51.4678344727],"type":"Point"}
}