{
  "type": "Feature",
  "properties": {
    "iso:country":"GB",
    "sg:address":"18 Museum St",
    "sg:city":"Ipswich",
    "sg:classifiers":[
        {
            "category":"Real Estate",
            "subcategory":"Surveying",
            "type":"Services"
        }
    ],
    "sg:phone":"+44 1473 219119",
    "sg:postcode":"IP1 1HX",
    "sg:province":"Suffolk",
    "sg:tags":[
        "surveyor",
        "land"
    ],
    "wof:name":"Survey Solutions",
    "wof:placetype":"venue"
},
  "geometry": {"coordinates":[1.150195,52.057705],"type":"Point"}
}