{
  "type": "Feature",
  "properties": {
    "iso:country":"GB",
    "sg:address":"5 Admirals Walk",
    "sg:city":"Chatham",
    "sg:classifiers":[
        {
            "category":"Food & Beverages",
            "subcategory":"Fruits & Vegetables",
            "type":"Retail Goods"
        }
    ],
    "sg:phone":"+44 1634 300999",
    "sg:postcode":"ME5 8NL",
    "sg:province":"Kent",
    "sg:tags":[
        "greengrocer"
    ],
    "wof:name":"Lordswood Fruiterers",
    "wof:placetype":"venue"
},
  "geometry": {"coordinates":[0.5359,51.341438],"type":"Point"}
}