{
  "type": "Feature",
  "properties": {
    "addr:full":"Four Season, Battenhall Avenue Worcester Worcestershire WR5 2HW",
    "addr:postcode":"wr5 2hw",
    "addr:street":"Battenhall Avenue",
    "iso:country":"GB",
    "sg:address":"Four Season, Battenhall Avenue",
    "sg:city":"Worcester",
    "sg:classifiers":[
        {
            "category":"Communications",
            "subcategory":"Film & Video Production",
            "type":"Services"
        }
    ],
    "sg:postcode":"WR5 2HW",
    "sg:province":"Worcestershire",
    "sg:tags":[
        "illustrator",
        "artist"
    ],
    "wof:name":"Powis Hayward Illustrators",
    "wof:placetype":"venue"
},
  "geometry": {"coordinates":[-2.2020299435,52.1793289185],"type":"Point"}
}