{
  "type": "Feature",
  "properties": {
    "iso:country":"GB",
    "sg:address":"35 Brookside, Barkby",
    "sg:city":"Leicester",
    "sg:classifiers":[
        {
            "category":"Bars & Pubs",
            "type":"Food & Drink"
        },
        {
            "category":"Community Center",
            "subcategory":"Social",
            "type":"Public Place"
        }
    ],
    "sg:phone":"+44 116 260 0092",
    "sg:postcode":"LE7 3QD",
    "sg:province":"Leicestershire",
    "sg:tags":[
        "pubs",
        "house",
        "inn",
        "activity"
    ],
    "wof:name":"The Brookside Inn",
    "wof:placetype":"venue"
},
  "geometry": {"coordinates":[-1.0541379452,52.6806297302],"type":"Point"}
}