{
  "type": "Feature",
  "properties": {
    "addr:full":"72 Oxford Road, Waterloo Liverpool Merseyside L22 7RF",
    "addr:housenumber":"72",
    "addr:postcode":"l22 7rf",
    "addr:street":"Oxford Road",
    "iso:country":"GB",
    "sg:address":"72 Oxford Road, Waterloo",
    "sg:city":"Liverpool",
    "sg:classifiers":[
        {
            "category":"Food & Beverages",
            "subcategory":"Liquor & Beverages",
            "type":"Retail Goods"
        }
    ],
    "sg:phone":"+44 151 920 3080",
    "sg:postcode":"L22 7RF",
    "sg:province":"Merseyside",
    "sg:tags":[
        "beer",
        "wine",
        "spirit",
        "wines"
    ],
    "wof:name":"Oxford Wines",
    "wof:placetype":"venue"
},
  "geometry": {"coordinates":[-3.0352869034,53.4796447754],"type":"Point"}
}