{
  "type": "Feature",
  "properties": {
    "addr:full":"109 Commercial Road Swindon Wiltshire SN1 5PL",
    "addr:housenumber":"109",
    "addr:postcode":"sn1 5pl",
    "addr:street":"Commercial Road",
    "iso:country":"GB",
    "sg:address":"109 Commercial Road",
    "sg:city":"Swindon",
    "sg:classifiers":[
        {
            "category":"Banks & Credit Unions",
            "subcategory":"Financial Services",
            "type":"Services"
        }
    ],
    "sg:phone":"+44 1793 495321",
    "sg:postcode":"SN1 5PL",
    "sg:province":"Wiltshire",
    "sg:tags":[
        "consultant"
    ],
    "wof:name":"The Associates",
    "wof:placetype":"venue"
},
  "geometry": {"coordinates":[-1.7836630344,51.5587921143],"type":"Point"}
}