{
  "type": "Feature",
  "properties": {
    "iso:country":"GB",
    "sg:address":"9 Birmingham Rd, Blakedown",
    "sg:city":"Kidderminster",
    "sg:classifiers":[
        {
            "category":"Bars & Pubs",
            "type":"Food & Drink"
        },
        {
            "category":"Community Center",
            "subcategory":"Social",
            "type":"Public Place"
        }
    ],
    "sg:phone":"+44 1562 700229",
    "sg:postcode":"DY10 3JD",
    "sg:province":"Staffordshire",
    "sg:tags":[
        "pubs",
        "house",
        "inn",
        "activity"
    ],
    "wof:name":"THE SWAN PUBLIC HOUSE",
    "wof:placetype":"venue"
},
  "geometry": {"coordinates":[-2.182649,52.40242],"type":"Point"}
}