{
  "type": "Feature",
  "properties": {
    "iso:country":"GB",
    "sg:address":"124 Himley Rd",
    "sg:city":"Tooting",
    "sg:classifiers":[
        {
            "category":"Retail",
            "subcategory":"Auto Repair",
            "type":"Services"
        }
    ],
    "sg:phone":"+44 20 8682 3083",
    "sg:postcode":"SW17 9AQ",
    "sg:province":"Greater London",
    "sg:tags":[
        "body",
        "car"
    ],
    "wof:name":"R P S Motors",
    "wof:placetype":"venue"
},
  "geometry": {"coordinates":[-0.1652559936,51.4230270386],"type":"Point"}
}