{
  "type": "Feature",
  "properties": {
    "iso:country":"GB",
    "sg:address":"4 Park Lane, Walney",
    "sg:city":"Barrow-in-furness",
    "sg:classifiers":[
        {
            "category":"Taxi",
            "type":"Transportation"
        },
        {
            "category":"Military Area",
            "subcategory":"Air Force Base",
            "type":"Public Place"
        }
    ],
    "sg:phone":"+44 1229 471307",
    "sg:postcode":"LA14 3JA",
    "sg:province":"Cumbria",
    "sg:tags":[
        "hire",
        "private"
    ],
    "wof:name":"Park Lane Travel",
    "wof:placetype":"venue"
},
  "geometry": {"coordinates":[-3.249159,54.106796],"type":"Point"}
}