{
  "type": "Feature",
  "properties": {
    "iso:country":"GB",
    "sg:address":"Po Box 1074",
    "sg:city":"Coulsdon",
    "sg:classifiers":[
        {
            "category":"Utilities",
            "type":"Services"
        }
    ],
    "sg:phone":"+44 1737 553456",
    "sg:postcode":"CR5 1ZW",
    "sg:province":"Surrey",
    "sg:tags":[
        "internet"
    ],
    "wof:name":"Jupiter Internet Ltd.",
    "wof:placetype":"venue"
},
  "geometry": {"coordinates":[-0.139179,51.318924],"type":"Point"}
}