{
  "type": "Feature",
  "properties": {
    "iso:country":"GB",
    "sg:address":"Unit 22, Voyagers Walk",
    "sg:city":"Manchester",
    "sg:classifiers":[
        {
            "category":"Arts & Performance",
            "subcategory":"Art Gallery",
            "type":"Entertainment"
        }
    ],
    "sg:phone":"+44 161 834 3370",
    "sg:postcode":"M4 3AT",
    "sg:province":"Greater Manchester",
    "wof:name":"The Original Art Shop",
    "wof:placetype":"venue"
},
  "geometry": {"coordinates":[-2.24281,53.482929],"type":"Point"}
}