{
  "type": "Feature",
  "properties": {
    "addr:full":"108 West Princes Street Helensburgh Argyll and Bute G84 8XD",
    "addr:housenumber":"108",
    "addr:postcode":"g84 8xd",
    "addr:street":"West Princes Street",
    "iso:country":"GB",
    "sg:address":"108 West Princes Street",
    "sg:city":"Helensburgh",
    "sg:classifiers":[
        {
            "category":"Health Services",
            "subcategory":"Optometrist",
            "type":"Services"
        }
    ],
    "sg:phone":"+44 1436 672111",
    "sg:postcode":"G84 8XD",
    "sg:province":"Argyll and Bute",
    "sg:tags":[
        "optician"
    ],
    "wof:name":"Cobb Optometrists",
    "wof:placetype":"venue"
},
  "geometry": {"coordinates":[-4.7386279106,56.0050354004],"type":"Point"}
}