{
  "type": "Feature",
  "properties": {
    "iso:country":"GB",
    "sg:address":"Newbegin",
    "sg:city":"Hornsea",
    "sg:classifiers":[
        {
            "category":"Personal",
            "subcategory":"Beauty Salon",
            "type":"Services"
        }
    ],
    "sg:phone":"+44 1964 536242",
    "sg:postcode":"HU18 1PB",
    "sg:province":"East Riding of Yorkshire",
    "sg:tags":[
        "lady",
        "hairdresser"
    ],
    "wof:name":"Total Concept",
    "wof:placetype":"venue"
},
  "geometry": {"coordinates":[-0.1672559977,53.912197113],"type":"Point"}
}