{
  "type": "Feature",
  "properties": {
    "addr:full":"23 Dean St Bangor Gwynedd LL57 1UP",
    "addr:housenumber":"23",
    "addr:postcode":"ll57 1up",
    "addr:street":"Dean St",
    "iso:country":"GB",
    "sg:address":"23 Dean St",
    "sg:city":"Bangor",
    "sg:classifiers":[
        {
            "category":"Personal",
            "subcategory":"Beauty Salon",
            "type":"Services"
        }
    ],
    "sg:phone":"+44 1248 355878",
    "sg:postcode":"LL57 1UP",
    "sg:province":"Gwynedd",
    "sg:tags":[
        "unisex",
        "hairdresser"
    ],
    "wof:name":"Style Review",
    "wof:placetype":"venue"
},
  "geometry": {"coordinates":[-4.125062,53.22987],"type":"Point"}
}