{
  "type": "Feature",
  "properties": {
    "iso:country":"GB",
    "sg:address":"1 Stud Farm, Halstead",
    "sg:city":"Sevenoaks",
    "sg:classifiers":[
        {
            "category":"Building & Trades",
            "subcategory":"Construction",
            "type":"Services"
        }
    ],
    "sg:postcode":"TN14 7HQ",
    "sg:province":"Kent",
    "sg:tags":[
        "contractor",
        "paving",
        "driveway"
    ],
    "wof:name":"J H Clark Paving",
    "wof:placetype":"venue"
},
  "geometry": {"coordinates":[0.133681,51.328606],"type":"Point"}
}