{
  "type": "Feature",
  "properties": {
    "addr:full":"Watling Street Cannock Staffordshire WS11 1SH",
    "addr:postcode":"ws11 1sh",
    "addr:street":"Watling Street",
    "iso:country":"GB",
    "sg:address":"Watling Street",
    "sg:city":"Cannock",
    "sg:classifiers":[
        {
            "category":"Building & Trades",
            "subcategory":"Landscaping Services",
            "type":"Services"
        }
    ],
    "sg:phone":"+44 1543 466423",
    "sg:postcode":"WS11 1SH",
    "sg:province":"Staffordshire",
    "sg:tags":[
        "pond",
        "aquarium"
    ],
    "wof:name":"Hatherton Aquatics",
    "wof:placetype":"venue"
},
  "geometry": {"coordinates":[-2.048362,52.67942],"type":"Point"}
}