{
  "type": "Feature",
  "properties": {
    "addr:full":"Cashmore Avenue Leamington Spa Warwickshire CV31 3EU",
    "addr:postcode":"cv31 3eu",
    "addr:street":"Cashmore Avenue",
    "iso:country":"GB",
    "sg:address":"Cashmore Avenue",
    "sg:city":"Leamington Spa",
    "sg:classifiers":[
        {
            "category":"Education",
            "subcategory":"School",
            "type":"Public Place"
        }
    ],
    "sg:phone":"+44 1926 425958",
    "sg:postcode":"CV31 3EU",
    "sg:province":"Warwickshire",
    "sg:tags":[
        "local",
        "authority"
    ],
    "wof:name":"St Patrick's R C Junior School",
    "wof:placetype":"venue"
},
  "geometry": {"coordinates":[-1.5364240408,52.2776412964],"type":"Point"}
}