{
  "type": "Feature",
  "properties": {
    "addr:full":"7 Queensway Halesowen West Midlands B63 4AA",
    "addr:housenumber":"7",
    "addr:postcode":"b63 4aa",
    "addr:street":"Queensway",
    "iso:country":"GB",
    "sg:address":"7 Queensway",
    "sg:city":"Halesowen",
    "sg:classifiers":[
        {
            "category":"Government",
            "subcategory":"Post Office",
            "type":"Public Place"
        }
    ],
    "sg:phone":"+44 845 722 3344",
    "sg:postcode":"B63 4AA",
    "sg:province":"West Midlands",
    "wof:name":"POST OFFICE LTD",
    "wof:placetype":"venue"
},
  "geometry": {"coordinates":[-2.0509951115,52.44972229],"type":"Point"}
}