{
  "type": "Feature",
  "properties": {
    "addr:full":"10-16 Tiller Rd, Docklands Poplar Greater London E14 8PX",
    "addr:housenumber":"10-16",
    "addr:postcode":"e14 8px",
    "addr:street":"Tiller Rd",
    "iso:country":"GB",
    "sg:address":"10-16 Tiller Rd, Docklands",
    "sg:city":"Poplar",
    "sg:classifiers":[
        {
            "category":"Professional",
            "subcategory":"Management & Consulting",
            "type":"Services"
        }
    ],
    "sg:phone":"+44 20 7345 5199",
    "sg:postcode":"E14 8PX",
    "sg:province":"Greater London",
    "sg:tags":[
        "marketing",
        "consultant"
    ],
    "wof:name":"Competitive Marketing Concepts",
    "wof:placetype":"venue"
},
  "geometry": {"coordinates":[-0.025553,51.496208],"type":"Point"}
}