{
  "type": "Feature",
  "properties": {
    "iso:country":"GB",
    "sg:address":"Redburn Road",
    "sg:city":"Newcastle-upon-tyne",
    "sg:classifiers":[
        {
            "category":"Building & Trades",
            "subcategory":"Construction",
            "type":"Services"
        }
    ],
    "sg:postcode":"NE5 1NB",
    "sg:province":"Tyne and Wear",
    "sg:tags":[
        "tiling",
        "contractor"
    ],
    "wof:name":"The Tiling Co. Ltd.",
    "wof:placetype":"venue"
},
  "geometry": {"coordinates":[-1.69357,55.003262],"type":"Point"}
}