{
  "type": "Feature",
  "properties": {
    "addr:full":"75 Kilmarnock Road Glasgow Glasgow City G41 3YR",
    "addr:housenumber":"75",
    "addr:postcode":"g41 3yr",
    "addr:street":"Kilmarnock Road",
    "iso:country":"GB",
    "sg:address":"75 Kilmarnock Road",
    "sg:city":"Glasgow",
    "sg:classifiers":[
        {
            "category":"Shopping",
            "subcategory":"Florist",
            "type":"Retail Goods"
        }
    ],
    "sg:phone":"+44 141 632 2660",
    "sg:postcode":"G41 3YR",
    "sg:province":"Glasgow City",
    "wof:name":"Billy's Florists",
    "wof:placetype":"venue"
},
  "geometry": {"coordinates":[-4.2831130028,55.8286323547],"type":"Point"}
}