{
  "type": "Feature",
  "properties": {
    "addr:full":"Trident House, 31a Dale Street Liverpool Merseyside L2 2HF",
    "addr:housenumber":"31a",
    "addr:postcode":"l2 2hf",
    "addr:street":"Dale Street",
    "iso:country":"GB",
    "sg:address":"Trident House, 31a Dale Street",
    "sg:city":"Liverpool",
    "sg:classifiers":[
        {
            "category":"Shopping",
            "subcategory":"Photographic Equipment",
            "type":"Retail Goods"
        }
    ],
    "sg:phone":"+44 151 236 2326",
    "sg:postcode":"L2 2HF",
    "sg:province":"Merseyside",
    "sg:tags":[
        "supply"
    ],
    "wof:name":"Photo-Optics Ltd.",
    "wof:placetype":"venue"
},
  "geometry": {"coordinates":[-2.988898,53.408028],"type":"Point"}
}