{
  "type": "Feature",
  "properties": {
    "addr:full":"Main Road, Meriden Coventry Warwickshire CV7 7NE",
    "addr:postcode":"cv7 7ne",
    "addr:street":"Main Road",
    "iso:country":"GB",
    "sg:address":"Main Road, Meriden",
    "sg:city":"Coventry",
    "sg:classifiers":[
        {
            "category":"Autos & Motor Vehicles",
            "subcategory":"Automobile Sales",
            "type":"Retail Goods"
        }
    ],
    "sg:postcode":"CV7 7NE",
    "sg:province":"Warwickshire",
    "sg:tags":[
        "commercial"
    ],
    "wof:name":"J D Paul Commercial Vehicles",
    "wof:placetype":"venue"
},
  "geometry": {"coordinates":[-1.6493389606,52.4375953674],"type":"Point"}
}