{
  "type": "Feature",
  "properties": {
    "iso:country":"GB",
    "sg:address":"19 Pratt Street",
    "sg:city":"Kirkcaldy",
    "sg:classifiers":[
        {
            "category":"Taxi",
            "type":"Transportation"
        },
        {
            "category":"Military Area",
            "subcategory":"Air Force Base",
            "type":"Public Place"
        }
    ],
    "sg:phone":"+44 1592 644000",
    "sg:postcode":"KY1 1RZ",
    "sg:province":"Fife",
    "sg:tags":[
        "hire",
        "private"
    ],
    "wof:name":"A A CABS",
    "wof:placetype":"venue"
},
  "geometry": {"coordinates":[-3.166785,56.099583],"type":"Point"}
}