{
  "type": "Feature",
  "properties": {
    "addr:full":"Kelmercourt House, 102 Sale Lane Manchester Greater Manchester M29 8PZ",
    "addr:housenumber":"102",
    "addr:postcode":"m29 8pz",
    "addr:street":"Sale Lane",
    "iso:country":"GB",
    "sg:address":"Kelmercourt House, 102 Sale Lane",
    "sg:city":"Manchester",
    "sg:classifiers":[
        {
            "category":"Building & Trades",
            "subcategory":"Plumbing",
            "type":"Services"
        }
    ],
    "sg:postcode":"M29 8PZ",
    "sg:province":"Greater Manchester",
    "sg:tags":[
        "central",
        "heating"
    ],
    "wof:name":"C H N Heating & Plumbing Services",
    "wof:placetype":"venue"
},
  "geometry": {"coordinates":[-2.4401390553,53.5142250061],"type":"Point"}
}