{
  "type": "Feature",
  "properties": {
    "iso:country":"GB",
    "sg:address":"27 Northwich Road, Weaverham",
    "sg:city":"Northwich",
    "sg:classifiers":[
        {
            "category":"Food & Beverages",
            "subcategory":"Bakery",
            "type":"Retail Goods"
        }
    ],
    "sg:phone":"+44 1606 852762",
    "sg:postcode":"CW8 3EU",
    "sg:province":"Cheshire",
    "sg:tags":[
        "baker"
    ],
    "wof:name":"Anne's Cake Shops",
    "wof:placetype":"venue"
},
  "geometry": {"coordinates":[-2.576968,53.262161],"type":"Point"}
}