{
  "type": "Feature",
  "properties": {
    "iso:country":"GB",
    "sg:address":"Vigo Place, Aldridge",
    "sg:city":"Walsall",
    "sg:classifiers":[
        {
            "category":"Professional",
            "subcategory":"Employment Agencies",
            "type":"Services"
        }
    ],
    "sg:phone":"+44 1922 744123",
    "sg:postcode":"WS9 8UG",
    "sg:province":"Staffordshire",
    "sg:tags":[
        "consultant"
    ],
    "wof:name":"Rosestaff",
    "wof:placetype":"venue"
},
  "geometry": {"coordinates":[-1.915706,52.603863],"type":"Point"}
}