{
  "type": "Feature",
  "properties": {
    "iso:country":"GB",
    "sg:address":"97 Macclesfield Road, Whaley Bridge",
    "sg:city":"High Peak",
    "sg:classifiers":[
        {
            "category":"Building & Trades",
            "subcategory":"Landscaping Services",
            "type":"Services"
        }
    ],
    "sg:postcode":"SK23 7DH",
    "sg:province":"Cheshire",
    "sg:tags":[
        "designer",
        "architect",
        "landscape"
    ],
    "wof:name":"Branching Out",
    "wof:placetype":"venue"
},
  "geometry": {"coordinates":[-1.9907079935,53.3226203918],"type":"Point"}
}