{
  "type": "Feature",
  "properties": {
    "iso:country":"GB",
    "sg:address":"51 Attlee Crescent",
    "sg:city":"Rugeley",
    "sg:classifiers":[
        {
            "category":"Health Services",
            "subcategory":"Nursing And Care Facility",
            "type":"Services"
        }
    ],
    "sg:phone":"+44 1889 576622",
    "sg:postcode":"WS15 1BP",
    "sg:province":"Staffordshire",
    "sg:tags":[
        "home"
    ],
    "wof:name":"Briar Hill House",
    "wof:placetype":"venue"
},
  "geometry": {"coordinates":[-1.931174,52.753567],"type":"Point"}
}