{
  "type": "Feature",
  "properties": {
    "addr:full":"318-320 Queenstown Road London Greater London SW8 4LT",
    "addr:housenumber":"318-320",
    "addr:postcode":"sw8 4lt",
    "addr:street":"Queenstown Road",
    "iso:country":"GB",
    "sg:address":"318-320 Queenstown Road",
    "sg:city":"London",
    "sg:classifiers":[
        {
            "category":"Organizations",
            "subcategory":"Non-profit Organization",
            "type":"Services"
        }
    ],
    "sg:phone":"+44 20 7627 1242",
    "sg:postcode":"SW8 4LT",
    "sg:province":"Greater London",
    "sg:tags":[
        "organisation",
        "voluntary",
        "charity"
    ],
    "wof:name":"Davies Alcohol Services",
    "wof:placetype":"venue"
},
  "geometry": {"coordinates":[-0.148499,51.47757],"type":"Point"}
}