{
  "type": "Feature",
  "properties": {
    "addr:full":"19 New Quebec Street, Marble Arch London Greater London W1H 7DG",
    "addr:housenumber":"19",
    "addr:postcode":"w1h 7dg",
    "addr:street":"New Quebec Street",
    "iso:country":"GB",
    "sg:address":"19 New Quebec Street, Marble Arch",
    "sg:city":"London",
    "sg:classifiers":[
        {
            "category":"Real Estate",
            "subcategory":"Developer",
            "type":"Services"
        }
    ],
    "sg:postcode":"W1H 7DG",
    "sg:province":"Greater London",
    "sg:tags":[
        "property"
    ],
    "wof:name":"Brooke Bennings Ltd.",
    "wof:placetype":"venue"
},
  "geometry": {"coordinates":[-0.158408,51.515347],"type":"Point"}
}