{
  "type": "Feature",
  "properties": {
    "addr:full":"57 High Street Arbroath Angus DD11 1AN",
    "addr:housenumber":"57",
    "addr:postcode":"dd11 1an",
    "addr:street":"High Street",
    "iso:country":"GB",
    "sg:address":"57 High Street",
    "sg:city":"Arbroath",
    "sg:classifiers":[
        {
            "category":"Bars & Pubs",
            "type":"Food & Drink"
        }
    ],
    "sg:phone":"+44 1241 870776",
    "sg:postcode":"DD11 1AN",
    "sg:province":"Angus",
    "sg:tags":[
        "pubs",
        "inn"
    ],
    "wof:name":"The Fisherman's Inn",
    "wof:placetype":"venue"
},
  "geometry": {"coordinates":[-2.5806701183,56.5577888489],"type":"Point"}
}