{
  "type": "Feature",
  "properties": {
    "iso:country":"GB",
    "sg:address":"Princes Avenue, Walderslade",
    "sg:city":"Chatham",
    "sg:classifiers":[
        {
            "category":"Food & Beverages",
            "subcategory":"Supermarket",
            "type":"Retail Goods"
        }
    ],
    "sg:phone":"+44 1634 867470",
    "sg:postcode":"ME5 8BA",
    "sg:province":"Kent",
    "wof:name":"Safeway Stores Ltd.",
    "wof:placetype":"venue"
},
  "geometry": {"coordinates":[0.5294089913,51.3441314697],"type":"Point"}
}