{
  "type": "Feature",
  "properties": {
    "addr:full":"Hawk Drive Bedford Bedfordshire MK41 7JA",
    "addr:postcode":"mk41 7ja",
    "addr:street":"Hawk Drive",
    "iso:country":"GB",
    "sg:address":"Hawk Drive",
    "sg:city":"Bedford",
    "sg:classifiers":[
        {
            "category":"Education",
            "subcategory":"School",
            "type":"Public Place"
        }
    ],
    "sg:postcode":"MK41 7JA",
    "sg:province":"Bedfordshire",
    "sg:tags":[
        "local",
        "authority"
    ],
    "wof:name":"Scott Lower School",
    "wof:placetype":"venue"
},
  "geometry": {"coordinates":[-0.465436995,52.156867981],"type":"Point"}
}