{
  "type": "Feature",
  "properties": {
    "iso:country":"GB",
    "sg:address":"Prime Cattle Sale Ring, Norwich Livestock Market, Hall Rd",
    "sg:city":"Norwich",
    "sg:classifiers":[
        {
            "category":"Professional",
            "type":"Services"
        }
    ],
    "sg:phone":"+44 1603 454393",
    "sg:postcode":"NR4 6DG",
    "sg:province":"Norfolk",
    "sg:tags":[
        "auctioneer"
    ],
    "wof:name":"Irelands-Saturday Only",
    "wof:placetype":"venue"
},
  "geometry": {"coordinates":[1.28541,52.602798],"type":"Point"}
}