{
  "type": "Feature",
  "properties": {
    "iso:country":"GB",
    "sg:address":"58a Wimpole St",
    "sg:city":"West End",
    "sg:classifiers":[
        {
            "category":"Health Services",
            "subcategory":"Doctor",
            "type":"Services"
        }
    ],
    "sg:phone":"+44 20 7935 3351",
    "sg:postcode":"W1M 7DE",
    "sg:province":"Hampshire",
    "sg:tags":[
        "practitioners"
    ],
    "wof:name":"Adrian Whiteson",
    "wof:placetype":"venue"
},
  "geometry": {"coordinates":[-0.148773,51.518967],"type":"Point"}
}