{
  "type": "Feature",
  "properties": {
    "iso:country":"GB",
    "sg:address":"9-11 St Cross Road",
    "sg:city":"Winchester",
    "sg:classifiers":[
        {
            "category":"Building & Trades",
            "subcategory":"Construction",
            "type":"Services"
        }
    ],
    "sg:phone":"+44 1962 853568",
    "sg:postcode":"SO23 9JB",
    "sg:province":"Hampshire",
    "sg:tags":[
        "builder"
    ],
    "wof:name":"Bendall Developments Ltd.",
    "wof:placetype":"venue"
},
  "geometry": {"coordinates":[-1.318347,51.060024],"type":"Point"}
}