{
  "type": "Feature",
  "properties": {
    "iso:country":"GB",
    "sg:address":"Trafalgar House, Grenville Place",
    "sg:city":"London",
    "sg:classifiers":[
        {
            "category":"Professional",
            "subcategory":"Accounting & Tax Preparation",
            "type":"Services"
        }
    ],
    "sg:phone":"+44 20 8444 2000",
    "sg:postcode":"NW7 3SA",
    "sg:province":"Greater London",
    "sg:tags":[
        "accountant"
    ],
    "wof:name":"Ian Skolnick & Co",
    "wof:placetype":"venue"
},
  "geometry": {"coordinates":[-0.2587,51.615711],"type":"Point"}
}