{
  "type": "Feature",
  "properties": {
    "iso:country":"GB",
    "sg:address":"7 Aspin Way, Darby Grn",
    "sg:city":"Camberley",
    "sg:classifiers":[
        {
            "category":"Building & Trades",
            "subcategory":"Construction",
            "type":"Services"
        }
    ],
    "sg:phone":"+44 1252 860300",
    "sg:postcode":"GU17 0BP",
    "sg:province":"Hampshire",
    "sg:tags":[
        "builder"
    ],
    "wof:name":"A & B Construction",
    "wof:placetype":"venue"
},
  "geometry": {"coordinates":[-0.7993909717,51.3339920044],"type":"Point"}
}