{
  "type": "Feature",
  "properties": {
    "addr:full":"4 Marlborough Parade, Beverley Road Maidstone Kent ME16 9JN",
    "addr:housenumber":"4",
    "addr:postcode":"me16 9jn",
    "addr:street":"Marlborough Parade Beverley Road",
    "iso:country":"GB",
    "sg:address":"4 Marlborough Parade, Beverley Road",
    "sg:city":"Maidstone",
    "sg:classifiers":[
        {
            "category":"Food & Beverages",
            "subcategory":"Liquor & Beverages",
            "type":"Retail Goods"
        }
    ],
    "sg:phone":"+44 1622 726034",
    "sg:postcode":"ME16 9JN",
    "sg:province":"Kent",
    "sg:tags":[
        "beer",
        "spirit",
        "wines"
    ],
    "wof:name":"Thresher",
    "wof:placetype":"venue"
},
  "geometry": {"coordinates":[0.4766199887,51.2667312622],"type":"Point"}
}