{
  "type": "Feature",
  "properties": {
    "iso:country":"GB",
    "sg:address":"166 High Street",
    "sg:city":"Scunthorpe",
    "sg:classifiers":[
        {
            "category":"Shopping",
            "subcategory":"Luggage & Leather Goods",
            "type":"Retail Goods"
        }
    ],
    "sg:phone":"+44 1724 844225",
    "sg:postcode":"DN15 6EH",
    "sg:province":"Lincolnshire",
    "sg:tags":[
        "shop",
        "leathergoods"
    ],
    "wof:name":"Gregory's (Leather) Ltd.",
    "wof:placetype":"venue"
},
  "geometry": {"coordinates":[-0.652011,53.591209],"type":"Point"}
}