{
  "type": "Feature",
  "properties": {
    "addr:full":"3 Chilcomb Burgess Hill East Sussex RH15 0DJ",
    "addr:housenumber":"3",
    "addr:postcode":"rh15 0dj",
    "addr:street":"Chilcomb",
    "iso:country":"GB",
    "sg:address":"3 Chilcomb",
    "sg:city":"Burgess Hill",
    "sg:classifiers":[
        {
            "category":"Recreation",
            "subcategory":"Amusement Park",
            "type":"Entertainment"
        }
    ],
    "sg:phone":"+44 1444 871282",
    "sg:postcode":"RH15 0DJ",
    "sg:province":"East Sussex",
    "sg:tags":[
        "arcade"
    ],
    "wof:name":"Rainbow Rides",
    "wof:placetype":"venue"
},
  "geometry": {"coordinates":[-0.1194109991,50.9476737976],"type":"Point"}
}