{
  "type": "Feature",
  "properties": {
    "addr:full":"Doctors Surgery, 66 Norse Walk Corby Northamptonshire NN18 9DG",
    "addr:housenumber":"66",
    "addr:postcode":"nn18 9dg",
    "addr:street":"Norse Walk",
    "iso:country":"GB",
    "sg:address":"Doctors Surgery, 66 Norse Walk",
    "sg:city":"Corby",
    "sg:classifiers":[
        {
            "category":"Health Services",
            "subcategory":"Doctor",
            "type":"Services"
        }
    ],
    "sg:phone":"+44 1536 743228",
    "sg:postcode":"NN18 9DG",
    "sg:province":"Northamptonshire",
    "sg:tags":[
        "practitioners"
    ],
    "wof:name":"B R Bhattacharya",
    "wof:placetype":"venue"
},
  "geometry": {"coordinates":[-0.73242,52.469898],"type":"Point"}
}