{
  "type": "Feature",
  "properties": {
    "addr:full":"22 Newport Street, Vauxhall London Greater London SE11 6AY",
    "addr:housenumber":"22",
    "addr:postcode":"se11 6ay",
    "addr:street":"Newport Street",
    "iso:country":"GB",
    "sg:address":"22 Newport Street, Vauxhall",
    "sg:city":"London",
    "sg:classifiers":[
        {
            "category":"Arts & Performance",
            "subcategory":"Art Gallery",
            "type":"Entertainment"
        }
    ],
    "sg:phone":"+44 20 7582 6465",
    "sg:postcode":"SE11 6AY",
    "sg:province":"Greater London",
    "sg:website":"http://www.beaconsfield.ltd.uk",
    "wof:name":"Beaconsfield Ltd",
    "wof:placetype":"venue"
},
  "geometry": {"coordinates":[-0.1181510016,51.4923057556],"type":"Point"}
}