{
  "type": "Feature",
  "properties": {
    "iso:country":"GB",
    "sg:address":"20 St Peters St",
    "sg:city":"Canterbury",
    "sg:classifiers":[
        {
            "category":"Shopping",
            "subcategory":"Department Store",
            "type":"Retail Goods"
        },
        {
            "category":"Shopping",
            "subcategory":"Comic Books",
            "type":"Retail Goods"
        }
    ],
    "sg:postcode":"CT1 2BQ",
    "sg:province":"Kent",
    "sg:tags":[
        "jeweller"
    ],
    "wof:name":"Wilson,R J,",
    "wof:placetype":"venue"
},
  "geometry": {"coordinates":[1.0768769979,51.2809944153],"type":"Point"}
}