{
  "type": "Feature",
  "properties": {
    "iso:country":"GB",
    "sg:address":"68 Liverpool Rd, Cadishead",
    "sg:city":"Manchester",
    "sg:classifiers":[
        {
            "category":"Retail",
            "subcategory":"Repair Shop",
            "type":"Services"
        }
    ],
    "sg:postcode":"M44 5AF",
    "sg:province":"Greater Manchester",
    "sg:tags":[
        "radio",
        "television",
        "video"
    ],
    "wof:name":"Williams,David,",
    "wof:placetype":"venue"
},
  "geometry": {"coordinates":[-2.434664,53.429779],"type":"Point"}
}