{
  "type": "Feature",
  "properties": {
    "addr:full":"1b Queen St Rushden Bedfordshire NN10 0AA",
    "addr:housenumber":"1b",
    "addr:postcode":"nn10 0aa",
    "addr:street":"Queen St",
    "iso:country":"GB",
    "sg:address":"1b Queen St",
    "sg:city":"Rushden",
    "sg:classifiers":[
        {
            "category":"Home & Garden",
            "subcategory":"Furniture",
            "type":"Retail Goods"
        }
    ],
    "sg:postcode":"NN10 0AA",
    "sg:province":"Bedfordshire",
    "wof:name":"Richard Phillips Furnishings",
    "wof:placetype":"venue"
},
  "geometry": {"coordinates":[-0.5980229974,52.2915649414],"type":"Point"}
}