{
  "type": "Feature",
  "properties": {
    "iso:country":"GB",
    "sg:address":"2 Pickwick Road",
    "sg:city":"Corsham",
    "sg:classifiers":[
        {
            "category":"Retail",
            "subcategory":"Auto Repair",
            "type":"Services"
        }
    ],
    "sg:postcode":"SN13 9BJ",
    "sg:province":"Wiltshire",
    "sg:tags":[
        "body",
        "car"
    ],
    "wof:name":"Delta Bodyworks",
    "wof:placetype":"venue"
},
  "geometry": {"coordinates":[-2.186475,51.431114],"type":"Point"}
}