{
  "type": "Feature",
  "properties": {
    "addr:full":"Berrington Hall, Berrington Leominster Herefordshire HR6 0DW",
    "addr:housenumber":"berrington;berrington",
    "addr:postcode":"hr6 0dw",
    "iso:country":"GB",
    "sg:address":"Berrington Hall, Berrington",
    "sg:city":"Leominster",
    "sg:classifiers":[
        {
            "category":"Landmark",
            "subcategory":"Tourist Attraction",
            "type":"Public Place"
        }
    ],
    "sg:phone":"+44 1568 615721",
    "sg:postcode":"HR6 0DW",
    "sg:province":"Herefordshire",
    "sg:tags":[
        "interest"
    ],
    "wof:name":"The National Trust",
    "wof:placetype":"venue"
},
  "geometry": {"coordinates":[-2.71948,52.269272],"type":"Point"}
}