{
  "type": "Feature",
  "properties": {
    "iso:country":"GB",
    "sg:address":"Rear Of 17-19 High Street, Nelson",
    "sg:city":"Treharris",
    "sg:classifiers":[
        {
            "category":"Manufacturing",
            "subcategory":"Metals",
            "type":"Manufacturing & Wholesale Goods"
        },
        {
            "category":"Building & Trades",
            "subcategory":"Construction",
            "type":"Services"
        }
    ],
    "sg:phone":"+44 1443 450522",
    "sg:postcode":"CF46 6EU",
    "sg:province":"Caerphilly",
    "sg:tags":[
        "steel",
        "fabricator",
        "builder",
        "erectors"
    ],
    "wof:name":"Graham Bridges Welding & Plating",
    "wof:placetype":"venue"
},
  "geometry": {"coordinates":[-3.284114,51.652679],"type":"Point"}
}