{
  "type": "Feature",
  "properties": {
    "addr:full":"135 Seaside Eastbourne East Sussex BN22 7NN",
    "addr:housenumber":"135",
    "addr:postcode":"bn22 7nn",
    "addr:street":"Seaside",
    "iso:country":"GB",
    "sg:address":"135 Seaside",
    "sg:city":"Eastbourne",
    "sg:classifiers":[
        {
            "category":"Shopping",
            "subcategory":"Department Store",
            "type":"Retail Goods"
        }
    ],
    "sg:postcode":"BN22 7NN",
    "sg:province":"East Sussex",
    "wof:name":"Nazmin Food Store",
    "wof:placetype":"venue"
},
  "geometry": {"coordinates":[0.2960709929,50.7737388611],"type":"Point"}
}