{
  "type": "Feature",
  "properties": {
    "addr:full":"Glasgow Airport, Abbotsinch Paisley Renfrewshire PA3 2ST",
    "iso:country":"GB",
    "sg:address":"Glasgow Airport, Abbotsinch",
    "sg:city":"Paisley",
    "sg:classifiers":[
        {
            "category":"Food & Beverages",
            "subcategory":"Candy",
            "type":"Retail Goods"
        }
    ],
    "sg:phone":"+44 141 840 1788",
    "sg:postcode":"PA3 2ST",
    "sg:province":"Renfrewshire",
    "sg:tags":[
        "confectioner"
    ],
    "wof:name":"Thorntons Plc",
    "wof:placetype":"venue"
},
  "geometry": {"coordinates":[-4.4334797859,55.8640785217],"type":"Point"}
}