{
  "type": "Feature",
  "properties": {
    "addr:full":"33 Park Drive Chester Cheshire CH2 3JR",
    "addr:housenumber":"33",
    "addr:postcode":"ch2 3jr",
    "addr:street":"Park Drive",
    "iso:country":"GB",
    "sg:address":"33 Park Drive",
    "sg:city":"Chester",
    "sg:classifiers":[
        {
            "category":"Building & Trades",
            "subcategory":"Landscaping Services",
            "type":"Services"
        }
    ],
    "sg:postcode":"CH2 3JR",
    "sg:province":"Cheshire",
    "sg:tags":[
        "landscape",
        "contractor"
    ],
    "wof:name":"Greenacre Landscape",
    "wof:placetype":"venue"
},
  "geometry": {"coordinates":[-2.8647549152,53.2023239136],"type":"Point"}
}