{
  "type": "Feature",
  "properties": {
    "iso:country":"GB",
    "sg:address":"Croft Hall, The Croft",
    "sg:city":"Hungerford",
    "sg:classifiers":[
        {
            "category":"Education",
            "subcategory":"Preschool",
            "type":"Public Place"
        }
    ],
    "sg:phone":"+44 1488 684561",
    "sg:postcode":"RG17 0HY",
    "sg:province":"Berkshire",
    "sg:tags":[
        "pre",
        "school",
        "playgroups",
        "pre-school"
    ],
    "wof:name":"Hungerford Playgroup",
    "wof:placetype":"venue"
},
  "geometry": {"coordinates":[-1.516156,51.413197],"type":"Point"}
}