{
  "type": "Feature",
  "properties": {
    "addr:full":"13 Eskbank Avenue, Patcham Brighton East Sussex BN1 8SL",
    "addr:housenumber":"13",
    "addr:postcode":"bn1 8sl",
    "addr:street":"Eskbank Avenue",
    "iso:country":"GB",
    "sg:address":"13 Eskbank Avenue, Patcham",
    "sg:city":"Brighton",
    "sg:classifiers":[
        {
            "category":"Recreation",
            "type":"Entertainment"
        }
    ],
    "sg:phone":"+44 1273 506955",
    "sg:postcode":"BN1 8SL",
    "sg:province":"East Sussex",
    "sg:tags":[
        "outdoor",
        "pursuit"
    ],
    "wof:name":"4TH Dimension",
    "wof:placetype":"venue"
},
  "geometry": {"coordinates":[-0.133587,50.868492],"type":"Point"}
}