{
  "type": "Feature",
  "properties": {
    "iso:country":"GB",
    "sg:address":"10 Pencroft Gro, Littleover",
    "sg:city":"Derby",
    "sg:classifiers":[
        {
            "category":"Building & Trades",
            "subcategory":"Construction",
            "type":"Services"
        }
    ],
    "sg:postcode":"DE23 2XN",
    "sg:province":"Derbyshire",
    "sg:tags":[
        "glazier",
        "decorator",
        "painter"
    ],
    "wof:name":"Edward Moran",
    "wof:placetype":"venue"
},
  "geometry": {"coordinates":[-1.50900805,52.885219574],"type":"Point"}
}