{
  "type": "Feature",
  "properties": {
    "addr:full":"5 Jubilee Drive Loughborough Leicestershire LE11 5XS",
    "addr:housenumber":"5",
    "addr:postcode":"le11 5xs",
    "addr:street":"Jubilee Drive",
    "iso:country":"GB",
    "sg:address":"5 Jubilee Drive",
    "sg:city":"Loughborough",
    "sg:classifiers":[
        {
            "category":"Professional",
            "type":"Services"
        },
        {
            "category":"Personal",
            "subcategory":"Shoe Repair & Shine",
            "type":"Services"
        }
    ],
    "sg:phone":"+44 1509 211111",
    "sg:postcode":"LE11 5XS",
    "sg:province":"Leicestershire",
    "sg:tags":[
        "equipment",
        "fixture",
        "display",
        "maker"
    ],
    "sg:website":"http://www.diam-int.com",
    "wof:name":"Diam International Ltd",
    "wof:placetype":"venue"
},
  "geometry": {"coordinates":[-1.212781,52.78286],"type":"Point"}
}