{
  "type": "Feature",
  "properties": {
    "iso:country":"GB",
    "sg:address":"32 Dale St",
    "sg:city":"Rochdale",
    "sg:classifiers":[
        {
            "category":"Home & Garden",
            "subcategory":"Home Furnishings",
            "type":"Retail Goods"
        }
    ],
    "sg:phone":"+44 1706 642016",
    "sg:postcode":"OL16 4HS",
    "sg:province":"Lancashire",
    "sg:tags":[
        "blind",
        "curtain",
        "fitting"
    ],
    "wof:name":"Lace & Drapes",
    "wof:placetype":"venue"
},
  "geometry": {"coordinates":[-2.111569,53.610428],"type":"Point"}
}