{
  "type": "Feature",
  "properties": {
    "iso:country":"GB",
    "sg:address":"Holbrook Hall Park",
    "sg:city":"Sudbury",
    "sg:classifiers":[
        {
            "category":"Health Services",
            "subcategory":"Nursing And Care Facility",
            "type":"Services"
        }
    ],
    "sg:phone":"+44 1787 248063",
    "sg:postcode":"CO10 0TH",
    "sg:province":"Essex",
    "sg:tags":[
        "home"
    ],
    "wof:name":"Holbrook Hall Nursing Home",
    "wof:placetype":"venue"
},
  "geometry": {"coordinates":[0.7343900204,52.0386047363],"type":"Point"}
}