{
  "type": "Feature",
  "properties": {
    "iso:country":"GB",
    "sg:address":"30-31 Carlton Business Centre, Carlton",
    "sg:city":"Nottingham",
    "sg:classifiers":[
        {
            "category":"Professional",
            "subcategory":"Computer Services",
            "type":"Services"
        }
    ],
    "sg:postcode":"NG4 3AA",
    "sg:province":"Nottinghamshire",
    "sg:tags":[
        "system",
        "software"
    ],
    "wof:name":"Diamond Technologies Group Ltd",
    "wof:placetype":"venue"
},
  "geometry": {"coordinates":[-1.0808000565,52.9665527344],"type":"Point"}
}