{
  "type": "Feature",
  "properties": {
    "addr:full":"10 Holmefield Road Ripon North Yorkshire HG4 1RZ",
    "addr:housenumber":"10",
    "addr:postcode":"hg4 1rz",
    "addr:street":"Holmefield Road",
    "iso:country":"GB",
    "sg:address":"10 Holmefield Road",
    "sg:city":"Ripon",
    "sg:classifiers":[
        {
            "category":"Professional",
            "subcategory":"Management & Consulting",
            "type":"Services"
        },
        {
            "category":"Sports & Exercise",
            "subcategory":"Sports Center",
            "type":"Entertainment"
        }
    ],
    "sg:phone":"+44 1765 607850",
    "sg:postcode":"HG4 1RZ",
    "sg:province":"North Yorkshire",
    "sg:tags":[
        "technician",
        "adviser",
        "safety",
        "consultant"
    ],
    "wof:name":"Cathedral Safety Services",
    "wof:placetype":"venue"
},
  "geometry": {"coordinates":[-1.524999,54.128658],"type":"Point"}
}