{
  "type": "Feature",
  "properties": {
    "addr:full":"Unit 3b Chesterbank Business Park, River Lane, Saltney Chester Cheshire CH4 8SL",
    "addr:housenumber":"unit 3b chesterbank",
    "addr:postcode":"ch4 8sl",
    "addr:street":"Business Park River Lane",
    "iso:country":"GB",
    "sg:address":"Unit 3b Chesterbank Business Park, River Lane, Saltney",
    "sg:city":"Chester",
    "sg:classifiers":[
        {
            "category":"Autos & Motor Vehicles",
            "subcategory":"Auto Supplies",
            "type":"Retail Goods"
        }
    ],
    "sg:phone":"+44 1244 683344",
    "sg:postcode":"CH4 8SL",
    "sg:province":"Cheshire",
    "sg:tags":[
        "windscreen"
    ],
    "wof:name":"Highway Windscreens",
    "wof:placetype":"venue"
},
  "geometry": {"coordinates":[-2.9283800125,53.1805000305],"type":"Point"}
}