{
  "type": "Feature",
  "properties": {
    "iso:country":"GB",
    "sg:address":"50 North Station Road",
    "sg:city":"Colchester",
    "sg:classifiers":[
        {
            "category":"Retail",
            "subcategory":"Laundry & Dry Cleaning",
            "type":"Services"
        }
    ],
    "sg:phone":"+44 1206 571877",
    "sg:postcode":"CO1 1RB",
    "sg:province":"Essex",
    "sg:tags":[
        "alteration"
    ],
    "wof:name":"Geoffrey David Hague-thomas",
    "wof:placetype":"venue"
},
  "geometry": {"coordinates":[0.8955050111,51.8959541321],"type":"Point"}
}