{
  "type": "Feature",
  "properties": {
    "addr:full":"39 Spalding Street Leicester Leicestershire LE5 4PH",
    "addr:housenumber":"39",
    "addr:postcode":"le5 4ph",
    "addr:street":"Spalding Street",
    "iso:country":"GB",
    "sg:address":"39 Spalding Street",
    "sg:city":"Leicester",
    "sg:classifiers":[
        {
            "category":"Shopping",
            "subcategory":"Clothing, Apparel, & Fashions",
            "type":"Retail Goods"
        }
    ],
    "sg:phone":"+44 116 276 3550",
    "sg:postcode":"LE5 4PH",
    "sg:province":"Leicestershire",
    "sg:tags":[
        "wear",
        "leisure"
    ],
    "wof:name":"D R Garments Ltd.",
    "wof:placetype":"venue"
},
  "geometry": {"coordinates":[-1.097705,52.637791],"type":"Point"}
}