{
  "type": "Feature",
  "properties": {
    "addr:full":"4 Vicarage Road, Edgbaston Birmingham West Midlands B15 3ES",
    "addr:housenumber":"4",
    "addr:postcode":"b15 3es",
    "addr:street":"Vicarage Road",
    "iso:country":"GB",
    "sg:address":"4 Vicarage Road, Edgbaston",
    "sg:city":"Birmingham",
    "sg:classifiers":[
        {
            "category":"Bus Charters",
            "type":"Transportation"
        },
        {
            "category":"Bus Stop",
            "subcategory":"None",
            "type":"Transportation"
        }
    ],
    "sg:phone":"+44 121 625 1122",
    "sg:postcode":"B15 3ES",
    "sg:province":"West Midlands",
    "sg:tags":[
        "operator",
        "coach"
    ],
    "wof:name":"National Express Ltd.",
    "wof:placetype":"venue"
},
  "geometry": {"coordinates":[-1.930886,52.471268],"type":"Point"}
}