{
  "type": "Feature",
  "properties": {
    "iso:country":"GB",
    "sg:address":"9 Little Ashfield",
    "sg:city":"Midhurst",
    "sg:classifiers":[
        {
            "category":"Building & Trades",
            "subcategory":"Construction",
            "type":"Services"
        }
    ],
    "sg:postcode":"GU29 9JP",
    "sg:province":"West Sussex",
    "sg:tags":[
        "roofing"
    ],
    "wof:name":"Repair Craft Construction",
    "wof:placetype":"venue"
},
  "geometry": {"coordinates":[-0.742294,50.986156],"type":"Point"}
}