{
  "type": "Feature",
  "properties": {
    "addr:full":"63 Southwood Road Farnborough Hampshire GU14 0JH",
    "addr:housenumber":"63",
    "addr:postcode":"gu14 0jh",
    "addr:street":"Southwood Road",
    "iso:country":"GB",
    "sg:address":"63 Southwood Road",
    "sg:city":"Farnborough",
    "sg:classifiers":[
        {
            "category":"Building & Trades",
            "subcategory":"Construction",
            "type":"Services"
        }
    ],
    "sg:phone":"+44 1252 377666",
    "sg:postcode":"GU14 0JH",
    "sg:province":"Hampshire",
    "sg:tags":[
        "builder"
    ],
    "wof:name":"Southwood Building Services",
    "wof:placetype":"venue"
},
  "geometry": {"coordinates":[-0.780696,51.293594],"type":"Point"}
}