{
  "type": "Feature",
  "properties": {
    "iso:country":"GB",
    "sg:address":"95 Victoria Rd",
    "sg:city":"Tipton",
    "sg:classifiers":[
        {
            "category":"Personal",
            "subcategory":"Beauty Salon",
            "type":"Services"
        }
    ],
    "sg:phone":"+44 121 530 1000",
    "sg:postcode":"DY4 8SW",
    "sg:province":"West Midlands",
    "sg:tags":[
        "unisex",
        "hairdresser"
    ],
    "wof:name":"Santoro's",
    "wof:placetype":"venue"
},
  "geometry": {"coordinates":[-2.057613,52.523895],"type":"Point"}
}