{
  "type": "Feature",
  "properties": {
    "addr:full":"Rugby Family Support Team, Rokeby Lions House, Holbrook Avenue Rugby Warwickshire CV21 2QQ",
    "addr:postcode":"cv21 2qq",
    "addr:street":"Holbrook Avenue",
    "iso:country":"GB",
    "sg:address":"Rugby Family Support Team, Rokeby Lions House, Holbrook Avenue",
    "sg:city":"Rugby",
    "sg:classifiers":[
        {
            "category":"Social Services",
            "type":"Services"
        }
    ],
    "sg:phone":"+44 1788 543886",
    "sg:postcode":"CV21 2QQ",
    "sg:province":"Warwickshire",
    "wof:name":"The Family Centre",
    "wof:placetype":"venue"
},
  "geometry": {"coordinates":[-1.2588080168,52.3766593933],"type":"Point"}
}