{
  "type": "Feature",
  "properties": {
    "addr:full":"Bryn Nefydd, Coppi Road Denbigh Conwy LL16 5AA",
    "addr:postcode":"ll16 5aa",
    "addr:street":"Coppi Road",
    "iso:country":"GB",
    "sg:address":"Bryn Nefydd, Coppi Road",
    "sg:city":"Denbigh",
    "sg:classifiers":[
        {
            "category":"Farming",
            "subcategory":"Dairy Farm",
            "type":"Manufacturing & Wholesale Goods"
        }
    ],
    "sg:phone":"+44 1745 812403",
    "sg:postcode":"LL16 5AA",
    "sg:province":"Conwy",
    "sg:tags":[
        "farmer"
    ],
    "wof:name":"A M JONES & SON",
    "wof:placetype":"venue"
},
  "geometry": {"coordinates":[-3.421149,53.183411],"type":"Point"}
}