{
  "type": "Feature",
  "properties": {
    "addr:full":"9 Meynell Cres Hackney Greater London E9 7AS",
    "addr:housenumber":"9",
    "addr:postcode":"e9 7as",
    "addr:street":"Meynell Cres",
    "iso:country":"GB",
    "sg:address":"9 Meynell Cres",
    "sg:city":"Hackney",
    "sg:classifiers":[
        {
            "category":"Professional",
            "subcategory":"Lawyer & Legal Services",
            "type":"Services"
        }
    ],
    "sg:phone":"+44 20 8985 7955",
    "sg:postcode":"E9 7AS",
    "sg:province":"Greater London",
    "sg:tags":[
        "advice",
        "counselling"
    ],
    "wof:name":"London Counselling Service (LCS)",
    "wof:placetype":"venue"
},
  "geometry": {"coordinates":[-0.0469439998,51.5413551331],"type":"Point"}
}