{
  "type": "Feature",
  "properties": {
    "addr:full":"Acle Bridge, Acle Norwich Norfolk NR13 3AS",
    "addr:postcode":"nr13 3as",
    "addr:street":"Acle Bridge;Norwich",
    "iso:country":"GB",
    "sg:address":"Acle Bridge, Acle",
    "sg:city":"Norwich",
    "sg:classifiers":[
        {
            "category":"Recreation",
            "subcategory":"Boat Charter",
            "type":"Entertainment"
        }
    ],
    "sg:phone":"+44 1493 750283",
    "sg:postcode":"NR13 3AS",
    "sg:province":"Norfolk",
    "sg:tags":[
        "excursion"
    ],
    "wof:name":"Horizon Craft",
    "wof:placetype":"venue"
},
  "geometry": {"coordinates":[1.535404,52.647289],"type":"Point"}
}