{
  "type": "Feature",
  "properties": {
    "iso:country":"GB",
    "sg:address":"50 High St",
    "sg:city":"Leicester",
    "sg:classifiers":[
        {
            "category":"Food & Beverages",
            "subcategory":"Groceries & Convenience Stores",
            "type":"Retail Goods"
        }
    ],
    "sg:phone":"+44 116 275 1098",
    "sg:postcode":"LE8 6LP",
    "sg:province":"Leicestershire",
    "wof:name":"Whetstone Convenience Store",
    "wof:placetype":"venue"
},
  "geometry": {"coordinates":[-1.179965,52.572754],"type":"Point"}
}