{
  "type": "Feature",
  "properties": {
    "iso:country":"GB",
    "sg:address":"Peppercorn House, 8 Huntingdon Street, St Neots",
    "sg:city":"Huntingdon",
    "sg:classifiers":[
        {
            "category":"Professional",
            "subcategory":"Engineering",
            "type":"Services"
        }
    ],
    "sg:phone":"+44 1480 404404",
    "sg:postcode":"PE19 1BH",
    "sg:province":"Bedfordshire",
    "sg:tags":[
        "civil",
        "engineer"
    ],
    "sg:website":"http://www.graham.co.uk",
    "wof:name":"Graham Construction Division",
    "wof:placetype":"venue"
},
  "geometry": {"coordinates":[-0.265662998,52.2286338806],"type":"Point"}
}