{
  "type": "Feature",
  "properties": {
    "iso:country":"GB",
    "sg:address":"66 Albert Road",
    "sg:city":"Manchester",
    "sg:classifiers":[
        {
            "category":"Building & Trades",
            "subcategory":"Landscaping Services",
            "type":"Services"
        }
    ],
    "sg:phone":"+44 161 225 4621",
    "sg:postcode":"M19 2AB",
    "sg:province":"Greater Manchester",
    "sg:tags":[
        "forestry",
        "tree"
    ],
    "wof:name":"Treecare",
    "wof:placetype":"venue"
},
  "geometry": {"coordinates":[-2.1969249249,53.4440841675],"type":"Point"}
}