{
  "type": "Feature",
  "properties": {
    "iso:country":"GB",
    "sg:address":"Walton Grange, Bosworth Rd",
    "sg:city":"Lutterworth",
    "sg:classifiers":[
        {
            "category":"Building & Trades",
            "subcategory":"Construction",
            "type":"Services"
        }
    ],
    "sg:phone":"+44 1858 881152",
    "sg:postcode":"LE17 5RW",
    "sg:province":"Leicestershire",
    "sg:tags":[
        "builder"
    ],
    "wof:name":"Paul Collins",
    "wof:placetype":"venue"
},
  "geometry": {"coordinates":[-1.0989700556,52.4895210266],"type":"Point"}
}