{
  "type": "Feature",
  "properties": {
    "addr:full":"25 Oxford Street Brighton East Sussex BN1 4LA",
    "addr:housenumber":"25",
    "addr:postcode":"bn1 4la",
    "addr:street":"Oxford Street",
    "iso:country":"GB",
    "sg:address":"25 Oxford Street",
    "sg:city":"Brighton",
    "sg:classifiers":[
        {
            "category":"Professional",
            "subcategory":"Lawyer & Legal Services",
            "type":"Services"
        }
    ],
    "sg:postcode":"BN1 4LA",
    "sg:province":"East Sussex",
    "sg:tags":[
        "solicitor"
    ],
    "wof:name":"Morris & Rogers",
    "wof:placetype":"venue"
},
  "geometry": {"coordinates":[-0.1344449967,50.8308906555],"type":"Point"}
}