{
  "type": "Feature",
  "properties": {
    "addr:full":"14 St Davids Way, St Davids Centre Cardiff Cardiff CF1 4DR",
    "addr:housenumber":"14",
    "addr:postcode":"cf1 4dr",
    "addr:street":"St Davids Way St;Cardiff",
    "iso:country":"GB",
    "sg:address":"14 St Davids Way, St Davids Centre",
    "sg:city":"Cardiff",
    "sg:classifiers":[
        {
            "category":"Shopping",
            "subcategory":"Gifts & Souvenirs",
            "type":"Retail Goods"
        }
    ],
    "sg:phone":"+44 29 2023 2820",
    "sg:postcode":"CF1 4DR",
    "sg:province":"Cardiff",
    "sg:tags":[
        "shop"
    ],
    "wof:name":"Past Times",
    "wof:placetype":"venue"
},
  "geometry": {"coordinates":[-3.180670023,51.4812583923],"type":"Point"}
}