{
  "type": "Feature",
  "properties": {
    "addr:full":"32 Kelmore Gro Bradford West Yorkshire BD6 2QZ",
    "addr:housenumber":"32",
    "addr:postcode":"bd6 2qz",
    "addr:street":"Kelmore Gro Bradford West",
    "iso:country":"GB",
    "sg:address":"32 Kelmore Gro",
    "sg:city":"Bradford",
    "sg:classifiers":[
        {
            "category":"Professional",
            "subcategory":"Lawyer & Legal Services",
            "type":"Services"
        }
    ],
    "sg:phone":"+44 1274 415933",
    "sg:postcode":"BD6 2QZ",
    "sg:province":"West Yorkshire",
    "sg:tags":[
        "patent",
        "agent"
    ],
    "wof:name":"Kelmar Site Training",
    "wof:placetype":"venue"
},
  "geometry": {"coordinates":[-1.7952309847,53.7572021484],"type":"Point"}
}