{
  "type": "Feature",
  "properties": {
    "addr:full":"66-68 John Street Porthcawl Bridgend CF36 3BD",
    "addr:housenumber":"66-68",
    "addr:postcode":"cf36 3bd",
    "addr:street":"John Street",
    "iso:country":"GB",
    "sg:address":"66-68 John Street",
    "sg:city":"Porthcawl",
    "sg:classifiers":[
        {
            "category":"Food & Beverages",
            "subcategory":"Supermarket",
            "type":"Retail Goods"
        }
    ],
    "sg:phone":"+44 1656 782745",
    "sg:postcode":"CF36 3BD",
    "sg:province":"Bridgend",
    "wof:name":"Spar",
    "wof:placetype":"venue"
},
  "geometry": {"coordinates":[-3.703944,51.478535],"type":"Point"}
}