{
  "type": "Feature",
  "properties": {
    "addr:full":"65 Chapel Hill Stansted Essex CM24 8AA",
    "addr:housenumber":"65",
    "addr:postcode":"cm24 8aa",
    "addr:street":"Chapel Hill Stansted",
    "iso:country":"GB",
    "sg:address":"65 Chapel Hill",
    "sg:city":"Stansted",
    "sg:classifiers":[
        {
            "category":"Government",
            "subcategory":"Post Office",
            "type":"Public Place"
        }
    ],
    "sg:phone":"+44 1279 813610",
    "sg:postcode":"CM24 8AA",
    "sg:province":"Essex",
    "wof:name":"D G Head",
    "wof:placetype":"venue"
},
  "geometry": {"coordinates":[0.1950840056,51.9029541016],"type":"Point"}
}