{
  "type": "Feature",
  "properties": {
    "addr:full":"52-64 Heath Rd Twickenham Greater London TW1 4BX",
    "addr:housenumber":"52-64",
    "addr:postcode":"tw1 4bx",
    "addr:street":"Heath Rd",
    "iso:country":"GB",
    "sg:address":"52-64 Heath Rd",
    "sg:city":"Twickenham",
    "sg:classifiers":[
        {
            "category":"Professional",
            "subcategory":"Advertising",
            "type":"Services"
        }
    ],
    "sg:postcode":"TW1 4BX",
    "sg:province":"Greater London",
    "wof:name":"Trans World Media (Northern) Ltd",
    "wof:placetype":"venue"
},
  "geometry": {"coordinates":[-0.332321,51.445358],"type":"Point"}
}