{
  "type": "Feature",
  "properties": {
    "iso:country":"GB",
    "sg:address":"23 Eld La",
    "sg:city":"Colchester",
    "sg:classifiers":[
        {
            "category":"Food & Beverages",
            "subcategory":"Candy",
            "type":"Retail Goods"
        }
    ],
    "sg:postcode":"CO1 1LS",
    "sg:province":"Essex",
    "sg:tags":[
        "confectioner"
    ],
    "wof:name":"Shop & Save",
    "wof:placetype":"venue"
},
  "geometry": {"coordinates":[0.9006800056,51.8878593445],"type":"Point"}
}