{
  "type": "Feature",
  "properties": {
    "iso:country":"GB",
    "sg:address":"5 School Road",
    "sg:city":"Liverpool",
    "sg:classifiers":[
        {
            "category":"Government",
            "subcategory":"Post Office",
            "type":"Public Place"
        }
    ],
    "sg:phone":"+44 151 929 2418",
    "sg:postcode":"L38 0BN",
    "sg:province":"Merseyside",
    "wof:name":"Hightown Post Office",
    "wof:placetype":"venue"
},
  "geometry": {"coordinates":[-3.058465004,53.5246810913],"type":"Point"}
}