{
  "type": "Feature",
  "properties": {
    "addr:full":"125 Grosvenor Rd Ashford Kent TN24 9PN",
    "addr:housenumber":"125",
    "addr:postcode":"tn24 9pn",
    "addr:street":"Grosvenor Rd",
    "iso:country":"GB",
    "sg:address":"125 Grosvenor Rd",
    "sg:city":"Ashford",
    "sg:classifiers":[
        {
            "category":"Building & Trades",
            "subcategory":"Construction",
            "type":"Services"
        }
    ],
    "sg:postcode":"TN24 9PN",
    "sg:province":"Kent",
    "sg:tags":[
        "builder"
    ],
    "wof:name":"Lenton Builders",
    "wof:placetype":"venue"
},
  "geometry": {"coordinates":[0.8835849762,51.1721458435],"type":"Point"}
}