{
  "type": "Feature",
  "properties": {
    "addr:full":"Dental Surgery, 1 Saville Rd Canning Town Greater London E16 2DS",
    "addr:housenumber":"1",
    "addr:postcode":"e16 2ds",
    "addr:street":"Saville Rd",
    "iso:country":"GB",
    "sg:address":"Dental Surgery, 1 Saville Rd",
    "sg:city":"Canning Town",
    "sg:classifiers":[
        {
            "category":"Health Services",
            "subcategory":"Dentist",
            "type":"Services"
        }
    ],
    "sg:phone":"+44 20 7511 2665",
    "sg:postcode":"E16 2DS",
    "sg:province":"Greater London",
    "wof:name":"D J J Vanderspuy",
    "wof:placetype":"venue"
},
  "geometry": {"coordinates":[0.0483499989,51.502281189],"type":"Point"}
}