{
  "type": "Feature",
  "properties": {
    "addr:full":"8 Castle St Farnham Surrey GU9 7HR",
    "addr:housenumber":"8",
    "addr:postcode":"gu9 7hr",
    "addr:street":"Castle St",
    "iso:country":"GB",
    "sg:address":"8 Castle St",
    "sg:city":"Farnham",
    "sg:classifiers":[
        {
            "category":"Health Services",
            "subcategory":"Nursing And Care Facility",
            "type":"Services"
        }
    ],
    "sg:phone":"+44 1252 714855",
    "sg:postcode":"GU9 7HR",
    "sg:province":"Surrey",
    "sg:tags":[
        "agency"
    ],
    "wof:name":"County Nurseline",
    "wof:placetype":"venue"
},
  "geometry": {"coordinates":[-0.799583,51.215416],"type":"Point"}
}