{
  "type": "Feature",
  "properties": {
    "iso:country":"GB",
    "sg:address":"15 Mary Rd",
    "sg:city":"Wells",
    "sg:classifiers":[
        {
            "category":"Shopping",
            "subcategory":"Pharmacy",
            "type":"Retail Goods"
        }
    ],
    "sg:phone":"+44 1749 674818",
    "sg:postcode":"BA5 2NF",
    "sg:province":"Somerset",
    "sg:tags":[
        "medicine",
        "therapy"
    ],
    "wof:name":"Lifestyle Health & Beauty",
    "wof:placetype":"venue"
},
  "geometry": {"coordinates":[-2.6569569111,51.2135543823],"type":"Point"}
}