{
  "type": "Feature",
  "properties": {
    "addr:full":"Park Works, Park Road, Mansfield Woodhouse Mansfield Derbyshire NG19 8EF",
    "addr:postcode":"ng19 8ef",
    "addr:street":"Park;Park Road",
    "iso:country":"GB",
    "sg:address":"Park Works, Park Road, Mansfield Woodhouse",
    "sg:city":"Mansfield",
    "sg:classifiers":[
        {
            "category":"Professional",
            "subcategory":"Accounting & Tax Preparation",
            "type":"Services"
        },
        {
            "category":"Home & Garden",
            "subcategory":"Garden Supply",
            "type":"Retail Goods"
        }
    ],
    "sg:phone":"+44 1623 644334",
    "sg:postcode":"NG19 8EF",
    "sg:province":"Derbyshire",
    "sg:tags":[
        "supplier",
        "herb",
        "retailer",
        "spice"
    ],
    "wof:name":"Phyto Products Ltd.",
    "wof:placetype":"venue"
},
  "geometry": {"coordinates":[-1.19513,53.165588],"type":"Point"}
}