{
  "type": "Feature",
  "properties": {
    "iso:country":"GB",
    "sg:address":"Unit 1/2 Clifton Metro, Whiteladies Road",
    "sg:city":"Bristol",
    "sg:classifiers":[
        {
            "category":"Cafe",
            "type":"Food & Drink"
        }
    ],
    "sg:phone":"+44 117 914 7797",
    "sg:postcode":"BS8 2NP",
    "sg:province":"City of Bristol",
    "sg:tags":[
        "tea",
        "room"
    ],
    "wof:name":"Metro Espresso",
    "wof:placetype":"venue"
},
  "geometry": {"coordinates":[-2.6100199223,51.4646987915],"type":"Point"}
}