{
  "type": "Feature",
  "properties": {
    "addr:full":"24 Pool Road Basingstoke Berkshire RG27 8RD",
    "addr:housenumber":"24",
    "addr:postcode":"rg27 8rd",
    "addr:street":"Pool Road",
    "iso:country":"GB",
    "sg:address":"24 Pool Road",
    "sg:city":"Basingstoke",
    "sg:classifiers":[
        {
            "category":"Professional",
            "subcategory":"Management & Consulting",
            "type":"Services"
        }
    ],
    "sg:phone":"+44 1252 844258",
    "sg:postcode":"RG27 8RD",
    "sg:province":"Berkshire",
    "sg:tags":[
        "consultant",
        "business"
    ],
    "wof:name":"Michael Jankowski",
    "wof:placetype":"venue"
},
  "geometry": {"coordinates":[-0.9084900022,51.3081207275],"type":"Point"}
}