{
  "type": "Feature",
  "properties": {
    "iso:country":"GB",
    "sg:address":"20a Murray Road",
    "sg:city":"Workington",
    "sg:classifiers":[
        {
            "category":"Personal",
            "subcategory":"Beauty Salon",
            "type":"Services"
        },
        {
            "category":"Personal",
            "subcategory":"Barber",
            "type":"Services"
        }
    ],
    "sg:phone":"+44 1900 62228",
    "sg:postcode":"CA14 2AD",
    "sg:province":"Cumbria",
    "sg:tags":[
        "unisex",
        "hairdresser"
    ],
    "wof:name":"Mode 1 Hairdressers",
    "wof:placetype":"venue"
},
  "geometry": {"coordinates":[-3.547559,54.643917],"type":"Point"}
}