{
  "type": "Feature",
  "properties": {
    "iso:country":"GB",
    "sg:address":"35 Elmer Road",
    "sg:city":"Bognor Regis",
    "sg:classifiers":[
        {
            "category":"Manufacturing",
            "subcategory":"Tools & Machinery",
            "type":"Manufacturing & Wholesale Goods"
        },
        {
            "category":"Insurance",
            "subcategory":"Insurance Agent",
            "type":"Services"
        }
    ],
    "sg:phone":"+44 1243 582293",
    "sg:postcode":"PO22 6DZ",
    "sg:province":"West Sussex",
    "sg:tags":[
        "society",
        "broker",
        "friendly"
    ],
    "wof:name":"Middleton Insurance Services",
    "wof:placetype":"venue"
},
  "geometry": {"coordinates":[-0.617689,50.79501],"type":"Point"}
}