{
  "type": "Feature",
  "properties": {
    "addr:full":"70 London Road Sittingbourne Kent ME9 9PP",
    "addr:housenumber":"70",
    "addr:postcode":"me9 9pp",
    "addr:street":"London Road",
    "iso:country":"GB",
    "sg:address":"70 London Road",
    "sg:city":"Sittingbourne",
    "sg:classifiers":[
        {
            "category":"Autos & Motor Vehicles",
            "subcategory":"Automobile Sales",
            "type":"Retail Goods"
        }
    ],
    "sg:phone":"+44 1795 425454",
    "sg:postcode":"ME9 9PP",
    "sg:province":"Kent",
    "sg:tags":[
        "car"
    ],
    "wof:name":"Specialist Cars of Sittingbourne",
    "wof:placetype":"venue"
},
  "geometry": {"coordinates":[0.799952,51.327629],"type":"Point"}
}