{
  "type": "Feature",
  "properties": {
    "iso:country":"GB",
    "sg:address":"Pennlands Farm, Collinswood Rd, Farnham Common",
    "sg:city":"Slough",
    "sg:classifiers":[
        {
            "category":"Professional",
            "subcategory":"Management & Consulting",
            "type":"Services"
        }
    ],
    "sg:postcode":"SL6 3LQ",
    "sg:province":"Berkshire",
    "sg:tags":[
        "consultant",
        "business"
    ],
    "wof:name":"Knowledge Based Development",
    "wof:placetype":"venue"
},
  "geometry": {"coordinates":[-0.72808,51.483292],"type":"Point"}
}