{
  "type": "Feature",
  "properties": {
    "addr:full":"London Road, Allostock Knutsford Cheshire WA16 9LU",
    "addr:postcode":"wa16 9lu",
    "addr:street":"London Road",
    "iso:country":"GB",
    "sg:address":"London Road, Allostock",
    "sg:city":"Knutsford",
    "sg:classifiers":[
        {
            "category":"Home & Garden",
            "subcategory":"Garden Supply",
            "type":"Retail Goods"
        }
    ],
    "sg:phone":"+44 1565 722567",
    "sg:postcode":"WA16 9LU",
    "sg:province":"Cheshire",
    "sg:tags":[
        "nursery",
        "centre"
    ],
    "wof:name":"Hills Garden Centre",
    "wof:placetype":"venue"
},
  "geometry": {"coordinates":[-2.383348,53.235809],"type":"Point"}
}