{
  "type": "Feature",
  "properties": {
    "addr:full":"Savoy Timber, 77 Renfrew Street Glasgow Glasgow City G2 3BY",
    "addr:housenumber":"77",
    "addr:postcode":"g2 3by",
    "addr:street":"Renfrew Street",
    "iso:country":"GB",
    "sg:address":"Savoy Timber, 77 Renfrew Street",
    "sg:city":"Glasgow",
    "sg:classifiers":[
        {
            "category":"Shopping",
            "subcategory":"Department Store",
            "type":"Retail Goods"
        }
    ],
    "sg:phone":"+44 141 333 9770",
    "sg:postcode":"G2 3BY",
    "sg:province":"Glasgow City",
    "wof:name":"Wine & Spirit Factors Ltd.",
    "wof:placetype":"venue"
},
  "geometry": {"coordinates":[-4.25804,55.8652],"type":"Point"}
}