{
  "type": "Feature",
  "properties": {
    "iso:country":"GB",
    "sg:address":"21 Rowantree Avenue, Baildon",
    "sg:city":"Shipley",
    "sg:classifiers":[
        {
            "category":"Sports & Exercise",
            "subcategory":"Stables",
            "type":"Entertainment"
        }
    ],
    "sg:phone":"+44 1274 597500",
    "sg:postcode":"BD17 5LQ",
    "sg:province":"West Yorkshire",
    "sg:tags":[
        "equestrian",
        "centre",
        "livery",
        "schools",
        "riding",
        "education"
    ],
    "wof:name":"Strathmore Equestrian Centre",
    "wof:placetype":"venue"
},
  "geometry": {"coordinates":[-1.778049,53.854279],"type":"Point"}
}