{
  "type": "Feature",
  "properties": {
    "addr:full":"394 Ladypool Road Birmingham West Midlands B12 8JZ",
    "addr:housenumber":"394",
    "addr:postcode":"b12 8jz",
    "addr:street":"Ladypool Road",
    "iso:country":"GB",
    "sg:address":"394 Ladypool Road",
    "sg:city":"Birmingham",
    "sg:classifiers":[
        {
            "category":"Communications",
            "subcategory":"Film & Video Production",
            "type":"Services"
        }
    ],
    "sg:phone":"+44 121 449 0606",
    "sg:postcode":"B12 8JZ",
    "sg:province":"West Midlands",
    "sg:tags":[
        "recording",
        "studio"
    ],
    "wof:name":"Frantic Recording Studios",
    "wof:placetype":"venue"
},
  "geometry": {"coordinates":[-1.878102,52.452847],"type":"Point"}
}