{
  "type": "Feature",
  "properties": {
    "addr:full":"Compound P, Navigation Way Loughborough Leicestershire LE11 0LP",
    "addr:postcode":"le11 0lp",
    "addr:street":"Navigation Way",
    "iso:country":"GB",
    "sg:address":"Compound P, Navigation Way",
    "sg:city":"Loughborough",
    "sg:classifiers":[
        {
            "category":"Home & Garden",
            "subcategory":"Building Materials",
            "type":"Retail Goods"
        }
    ],
    "sg:phone":"+44 1509 219998",
    "sg:postcode":"LE11 0LP",
    "sg:province":"Leicestershire",
    "sg:tags":[
        "roofing",
        "rafter",
        "beams"
    ],
    "wof:name":"D G Wilde",
    "wof:placetype":"venue"
},
  "geometry": {"coordinates":[-1.2234740257,52.7685241699],"type":"Point"}
}