{
  "type": "Feature",
  "properties": {
    "iso:country":"GB",
    "sg:address":"Bullocks Farm Lane, Wheeler End",
    "sg:city":"High Wycombe",
    "sg:classifiers":[
        {
            "category":"Bars & Pubs",
            "type":"Food & Drink"
        },
        {
            "category":"Community Center",
            "subcategory":"Social",
            "type":"Public Place"
        }
    ],
    "sg:phone":"+44 1494 883070",
    "sg:postcode":"HP14 3NH",
    "sg:province":"Buckinghamshire",
    "sg:tags":[
        "pubs",
        "house",
        "inn",
        "activity"
    ],
    "wof:name":"The Chequers",
    "wof:placetype":"venue"
},
  "geometry": {"coordinates":[-0.835199,51.623096],"type":"Point"}
}