{
  "type": "Feature",
  "properties": {
    "iso:country":"GB",
    "sg:address":"96 Pontmorlais",
    "sg:city":"Merthyr Tydfil",
    "sg:classifiers":[
        {
            "category":"Bars & Pubs",
            "type":"Food & Drink"
        }
    ],
    "sg:postcode":"CF47 8UH",
    "sg:province":"Merthyr Tydfil",
    "sg:tags":[
        "pubs",
        "inn"
    ],
    "wof:name":"The Anchor Inn",
    "wof:placetype":"venue"
},
  "geometry": {"coordinates":[-3.376464,51.750439],"type":"Point"}
}