{
  "type": "Feature",
  "properties": {
    "iso:country":"GB",
    "sg:address":"162 Coggeshall Road",
    "sg:city":"Braintree",
    "sg:classifiers":[
        {
            "category":"Personal",
            "type":"Services"
        }
    ],
    "sg:phone":"+44 1376 553311",
    "sg:postcode":"CM7 9ER",
    "sg:province":"Essex",
    "sg:tags":[
        "delivery"
    ],
    "wof:name":"B B A Express Courier",
    "wof:placetype":"venue"
},
  "geometry": {"coordinates":[0.560156,51.88018],"type":"Point"}
}