{
  "type": "Feature",
  "properties": {
    "addr:full":"Main St Mallaig Highland PH41 4QS",
    "addr:postcode":"ph41 4qs",
    "addr:street":"Main St",
    "iso:country":"GB",
    "sg:address":"Main St",
    "sg:city":"Mallaig",
    "sg:classifiers":[
        {
            "category":"Travel",
            "subcategory":"Hotels & Motels",
            "type":"Entertainment"
        }
    ],
    "sg:phone":"+44 1687 462988",
    "sg:postcode":"PH41 4QS",
    "sg:province":"Highland",
    "sg:tags":[
        "house",
        "guest"
    ],
    "wof:name":"Half Moon Bay",
    "wof:placetype":"venue"
},
  "geometry": {"coordinates":[-5.8291192055,57.0058250427],"type":"Point"}
}