{
  "type": "Feature",
  "properties": {
    "addr:full":"North Road, Bridgend Industrial Estate Bridgend Bridgend CF31 3TP",
    "addr:postcode":"cf31 3tp",
    "addr:street":"North Road;Industrial Estate",
    "iso:country":"GB",
    "sg:address":"North Road, Bridgend Industrial Estate",
    "sg:city":"Bridgend",
    "sg:classifiers":[
        {
            "category":"Manufacturing",
            "subcategory":"Metals",
            "type":"Manufacturing & Wholesale Goods"
        },
        {
            "category":"Manufacturing",
            "subcategory":"Tools & Machinery",
            "type":"Manufacturing & Wholesale Goods"
        }
    ],
    "sg:phone":"+44 1656 648488",
    "sg:postcode":"CF31 3TP",
    "sg:province":"Bridgend",
    "sg:tags":[
        "machine",
        "equipment",
        "welding",
        "manufacturer"
    ],
    "wof:name":"Vale Welding & Engineering Supplies Ltd",
    "wof:placetype":"venue"
},
  "geometry": {"coordinates":[-3.5395190716,51.5042686462],"type":"Point"}
}