{
  "type": "Feature",
  "properties": {
    "iso:country":"GB",
    "sg:address":"Tea Rooms Town Hall",
    "sg:city":"Ipswich",
    "sg:classifiers":[
        {
            "category":"Organizations",
            "subcategory":"Non-profit Organization",
            "type":"Services"
        }
    ],
    "sg:phone":"+44 1473 231080",
    "sg:postcode":"IP1 1DH",
    "sg:province":"Suffolk",
    "sg:tags":[
        "charitable",
        "organisation",
        "voluntary",
        "charity"
    ],
    "wof:name":"Age Concern in Suffolk",
    "wof:placetype":"venue"
},
  "geometry": {"coordinates":[1.143788,52.057777],"type":"Point"}
}