{
  "type": "Feature",
  "properties": {
    "iso:country":"GB",
    "sg:address":"30 Dover Road, Walmer",
    "sg:city":"Deal",
    "sg:classifiers":[
        {
            "category":"Shopping",
            "subcategory":"Antiques",
            "type":"Retail Goods"
        }
    ],
    "sg:phone":"+44 1304 374082",
    "sg:postcode":"CT14 7JW",
    "sg:province":"Kent",
    "wof:name":"R S B Antiques",
    "wof:placetype":"venue"
},
  "geometry": {"coordinates":[1.401716,51.211388],"type":"Point"}
}