{
  "type": "Feature",
  "properties": {
    "iso:country":"GB",
    "sg:address":"Cornwall Court, 19 Cornwall St",
    "sg:city":"Birmingham",
    "sg:classifiers":[
        {
            "category":"Banks & Credit Unions",
            "subcategory":"Bank",
            "type":"Services"
        }
    ],
    "sg:phone":"+44 121 200 5987",
    "sg:postcode":"B3 2DY",
    "sg:province":"West Midlands",
    "sg:tags":[
        "discounting",
        "invoice"
    ],
    "wof:name":"Euro Sales Finance plc",
    "wof:placetype":"venue"
},
  "geometry": {"coordinates":[-1.90126,52.483021],"type":"Point"}
}