{
  "type": "Feature",
  "properties": {
    "iso:country":"GB",
    "sg:address":"8 Fallow Walk",
    "sg:city":"Northampton",
    "sg:classifiers":[
        {
            "category":"Building & Trades",
            "subcategory":"Landscaping Services",
            "type":"Services"
        }
    ],
    "sg:phone":"+44 1604 844937",
    "sg:postcode":"NN2 8DE",
    "sg:province":"Northamptonshire",
    "sg:tags":[
        "gardening"
    ],
    "wof:name":"D Brown Gardens",
    "wof:placetype":"venue"
},
  "geometry": {"coordinates":[-0.9115660191,52.2753791809],"type":"Point"}
}