{
  "type": "Feature",
  "properties": {
    "addr:full":"Unit 41-42, Gate 8 Terminal 4 London Heathro Hounslow Greater London TW6 3XA",
    "addr:housenumber":"unit 41-42;8;4",
    "addr:postcode":"tw6 3xa",
    "addr:street":"Gate;Terminal",
    "iso:country":"GB",
    "sg:address":"Unit 41-42, Gate 8 Terminal 4 London Heathro",
    "sg:city":"Hounslow",
    "sg:classifiers":[
        {
            "category":"Home & Garden",
            "subcategory":"Household Appliances",
            "type":"Retail Goods"
        }
    ],
    "sg:phone":"+44 20 8754 1819",
    "sg:postcode":"TW6 3XA",
    "sg:province":"Greater London",
    "sg:tags":[
        "electrical",
        "domestic"
    ],
    "wof:name":"Dixons",
    "wof:placetype":"venue"
},
  "geometry": {"coordinates":[-0.36643,51.46698],"type":"Point"}
}