{
  "type": "Feature",
  "properties": {
    "iso:country":"GB",
    "sg:address":"Rignall Farm House, Handley Park",
    "sg:city":"Towcester",
    "sg:classifiers":[
        {
            "category":"Shopping",
            "subcategory":"Mobile Phones",
            "type":"Retail Goods"
        },
        {
            "category":"Communications",
            "type":"Services"
        }
    ],
    "sg:phone":"+44 1327 352162",
    "sg:postcode":"NN12 8PA",
    "sg:province":"Buckinghamshire",
    "sg:tags":[
        "telecommunication"
    ],
    "wof:name":"Connekt Cellular",
    "wof:placetype":"venue"
},
  "geometry": {"coordinates":[-0.987009,52.130508],"type":"Point"}
}