{
  "type": "Feature",
  "properties": {
    "iso:country":"GB",
    "sg:address":"British Moss Peat Works, Swinefleet",
    "sg:city":"Goole",
    "sg:classifiers":[
        {
            "category":"Building & Trades",
            "subcategory":"Landscaping Services",
            "type":"Services"
        }
    ],
    "sg:phone":"+44 1724 710666",
    "sg:postcode":"DN14 8DU",
    "sg:province":"East Riding of Yorkshire",
    "sg:tags":[
        "horticultural",
        "consultant"
    ],
    "wof:name":"Levington Horticultural",
    "wof:placetype":"venue"
},
  "geometry": {"coordinates":[-0.834054,53.690731],"type":"Point"}
}