{
  "type": "Feature",
  "properties": {
    "addr:full":"Wyre Street, Padiham Burnley Lancashire BB12 8DF",
    "addr:postcode":"bb12 8df",
    "addr:street":"Wyre Street",
    "iso:country":"GB",
    "sg:address":"Wyre Street, Padiham",
    "sg:city":"Burnley",
    "sg:classifiers":[
        {
            "category":"Retail",
            "subcategory":"Auto Repair",
            "type":"Services"
        }
    ],
    "sg:postcode":"BB12 8DF",
    "sg:province":"Lancashire",
    "sg:tags":[
        "body",
        "car"
    ],
    "wof:name":"N S J Commercials",
    "wof:placetype":"venue"
},
  "geometry": {"coordinates":[-2.3138840199,53.8011894226],"type":"Point"}
}