{
  "type": "Feature",
  "properties": {
    "iso:country":"GB",
    "sg:address":"P O Box 514",
    "sg:city":"Sheffield",
    "sg:classifiers":[
        {
            "category":"Professional",
            "subcategory":"Testing Lab",
            "type":"Services"
        }
    ],
    "sg:phone":"+44 114 225 0400",
    "sg:postcode":"S4 7QQ",
    "sg:province":"South Yorkshire",
    "sg:tags":[
        "inspection",
        "calibration"
    ],
    "wof:name":"Moore & Jackson",
    "wof:placetype":"venue"
},
  "geometry": {"coordinates":[-1.44325,53.39806],"type":"Point"}
}