{
  "type": "Feature",
  "properties": {
    "addr:full":"14 Lower Riding, Holtspur Beaconsfield Buckinghamshire HP9 1BQ",
    "addr:housenumber":"14",
    "addr:postcode":"hp9 1bq",
    "addr:street":"Lower Riding Holtspur",
    "iso:country":"GB",
    "sg:address":"14 Lower Riding, Holtspur",
    "sg:city":"Beaconsfield",
    "sg:classifiers":[
        {
            "category":"Building & Trades",
            "subcategory":"Construction",
            "type":"Services"
        }
    ],
    "sg:postcode":"HP9 1BQ",
    "sg:province":"Buckinghamshire",
    "sg:tags":[
        "builder"
    ],
    "wof:name":"Broadbent D Brickwork & Property Maintenance",
    "wof:placetype":"venue"
},
  "geometry": {"coordinates":[-0.6637380123,51.6059608459],"type":"Point"}
}