{
  "type": "Feature",
  "properties": {
    "iso:country":"GB",
    "sg:address":"51 Hesketh Lane, Tarleton",
    "sg:city":"Preston",
    "sg:classifiers":[
        {
            "category":"Retail",
            "subcategory":"Auto Repair",
            "type":"Services"
        }
    ],
    "sg:phone":"+44 1772 812618",
    "sg:postcode":"PR4 6AQ",
    "sg:province":"Lancashire",
    "sg:tags":[
        "modification",
        "garage",
        "related"
    ],
    "wof:name":"Steven Norris",
    "wof:placetype":"venue"
},
  "geometry": {"coordinates":[-2.831475,53.684105],"type":"Point"}
}