{
  "type": "Feature",
  "properties": {
    "addr:full":"1 Onslow Way, Pyrford Woking Surrey GU22 8QX",
    "addr:housenumber":"1",
    "addr:postcode":"gu22 8qx",
    "addr:street":"Onslow Way",
    "iso:country":"GB",
    "sg:address":"1 Onslow Way, Pyrford",
    "sg:city":"Woking",
    "sg:classifiers":[
        {
            "category":"Professional",
            "subcategory":"Art Services",
            "type":"Services"
        }
    ],
    "sg:phone":"+44 1932 347313",
    "sg:postcode":"GU22 8QX",
    "sg:province":"Surrey",
    "sg:tags":[
        "photographer"
    ],
    "wof:name":"Cliff Bolton",
    "wof:placetype":"venue"
},
  "geometry": {"coordinates":[-0.5131070018,51.3251609802],"type":"Point"}
}