{
  "type": "Feature",
  "properties": {
    "addr:full":"Burdon Lane Beaworthy Devon EX21 5LX",
    "addr:postcode":"ex21 5lx",
    "addr:street":"Burdon Lane",
    "iso:country":"GB",
    "sg:address":"Burdon Lane",
    "sg:city":"Beaworthy",
    "sg:classifiers":[
        {
            "category":"Health Services",
            "subcategory":"Nursing And Care Facility",
            "type":"Services"
        }
    ],
    "sg:postcode":"EX21 5LX",
    "sg:province":"Devon",
    "sg:tags":[
        "home"
    ],
    "wof:name":"Burdon Grange Nursing Home",
    "wof:placetype":"venue"
},
  "geometry": {"coordinates":[-4.1833848953,50.7753067017],"type":"Point"}
}