{
  "type": "Feature",
  "properties": {
    "iso:country":"GB",
    "sg:address":"Graisley Lane",
    "sg:city":"Wolverhampton",
    "sg:classifiers":[
        {
            "category":"Recreation",
            "type":"Entertainment"
        }
    ],
    "sg:phone":"+44 1902 861748",
    "sg:postcode":"WV11 1PD",
    "sg:province":"Staffordshire",
    "sg:tags":[
        "snooker",
        "billiards",
        "pool"
    ],
    "wof:name":"Graisley Lane Snooker Club",
    "wof:placetype":"venue"
},
  "geometry": {"coordinates":[-2.0891590118,52.6003494263],"type":"Point"}
}