{
  "type": "Feature",
  "properties": {
    "addr:full":"A 30 Salisbury Wiltshire SP3 5PH",
    "addr:housenumber":"30",
    "addr:postcode":"sp3 5ph",
    "addr:street":"A",
    "iso:country":"GB",
    "sg:address":"A 30",
    "sg:city":"Salisbury",
    "sg:classifiers":[
        {
            "category":"Retail",
            "subcategory":"Auto Repair",
            "type":"Services"
        }
    ],
    "sg:phone":"+44 1747 870080",
    "sg:postcode":"SP3 5PH",
    "sg:province":"Wiltshire",
    "sg:tags":[
        "modification",
        "garage"
    ],
    "wof:name":"Downside Garage",
    "wof:placetype":"venue"
},
  "geometry": {"coordinates":[-2.0537209511,51.0357780457],"type":"Point"}
}