{
  "type": "Feature",
  "properties": {
    "iso:country":"GB",
    "sg:address":"Workshop, Cleatham Hall, Kirton Lindsey",
    "sg:city":"Gainsborough",
    "sg:classifiers":[
        {
            "category":"Farming",
            "subcategory":"Farm",
            "type":"Manufacturing & Wholesale Goods"
        }
    ],
    "sg:phone":"+44 1724 762060",
    "sg:postcode":"DN21 4JS",
    "sg:province":"Lincolnshire",
    "sg:tags":[
        "mixed",
        "crop"
    ],
    "wof:name":"Ian Fowler & Co.",
    "wof:placetype":"venue"
},
  "geometry": {"coordinates":[-0.582832,53.500095],"type":"Point"}
}