{
  "type": "Feature",
  "properties": {
    "addr:full":"East Lodge, Jesmond Rd, Jesmond Newcastle Upon Tyne Tyne and Wear NE2 1NJ",
    "addr:postcode":"ne2 1nj",
    "addr:street":"Jesmond Rd",
    "iso:country":"GB",
    "sg:address":"East Lodge, Jesmond Rd, Jesmond",
    "sg:city":"Newcastle Upon Tyne",
    "sg:classifiers":[
        {
            "category":"Professional",
            "type":"Services"
        }
    ],
    "sg:phone":"+44 191 281 6251",
    "sg:postcode":"NE2 1NJ",
    "sg:province":"Tyne and Wear",
    "sg:tags":[
        "archaeologist"
    ],
    "wof:name":"Tyne & Wear Museums",
    "wof:placetype":"venue"
},
  "geometry": {"coordinates":[-1.60091,54.98399],"type":"Point"}
}