{
  "type": "Feature",
  "properties": {
    "iso:country":"GB",
    "sg:address":"23 Greenwich South Street",
    "sg:city":"London",
    "sg:classifiers":[
        {
            "category":"Shopping",
            "subcategory":"Antiques",
            "type":"Retail Goods"
        }
    ],
    "sg:phone":"+44 20 8293 5721",
    "sg:postcode":"SE10 8NW",
    "sg:province":"Greater London",
    "wof:name":"Creek Antiques",
    "wof:placetype":"venue"
},
  "geometry": {"coordinates":[-0.0121929999,51.4773139954],"type":"Point"}
}