{
  "type": "Feature",
  "properties": {
    "addr:full":"194 Shoreditch High Street Whitechapel Greater London E1 6LG",
    "addr:housenumber":"194",
    "addr:postcode":"e1 6lg",
    "addr:street":"Shoreditch High Street",
    "iso:country":"GB",
    "sg:address":"194 Shoreditch High Street",
    "sg:city":"Whitechapel",
    "sg:classifiers":[
        {
            "category":"Professional",
            "type":"Services"
        }
    ],
    "sg:phone":"+44 20 7247 8668",
    "sg:postcode":"E1 6LG",
    "sg:province":"Greater London",
    "sg:tags":[
        "repair",
        "tech",
        "maintenance"
    ],
    "wof:name":"Kaltec Systems",
    "wof:placetype":"venue"
},
  "geometry": {"coordinates":[-0.0777989998,51.5226097107],"type":"Point"}
}