{
  "type": "Feature",
  "properties": {
    "addr:full":"Hammerain House, Hooks Stone Avenue Harrogate North Yorkshire HG2 8ER",
    "addr:postcode":"hg2 8er",
    "addr:street":"Hooks Stone Avenue",
    "iso:country":"GB",
    "sg:address":"Hammerain House, Hooks Stone Avenue",
    "sg:city":"Harrogate",
    "sg:classifiers":[
        {
            "category":"Shopping",
            "subcategory":"Discount & Variety Stores",
            "type":"Retail Goods"
        }
    ],
    "sg:phone":"+44 1924 284286",
    "sg:postcode":"HG2 8ER",
    "sg:province":"North Yorkshire",
    "sg:tags":[
        "cleaning",
        "supply"
    ],
    "wof:name":"Bsl (Harrogate) Ltd.",
    "wof:placetype":"venue"
},
  "geometry": {"coordinates":[-1.5298240185,53.9777793884],"type":"Point"}
}