{
  "type": "Feature",
  "properties": {
    "iso:country":"GB",
    "sg:address":"Abbey Road Health Centre, 28a Abbey Rd",
    "sg:city":"Stratford",
    "sg:classifiers":[
        {
            "category":"Health Services",
            "subcategory":"Doctor",
            "type":"Services"
        }
    ],
    "sg:phone":"+44 20 8534 2515",
    "sg:postcode":"E15 3LG",
    "sg:province":"Greater London",
    "sg:tags":[
        "practitioners"
    ],
    "wof:name":"Yates, H",
    "wof:placetype":"venue"
},
  "geometry": {"coordinates":[0.0058900001,51.535030365],"type":"Point"}
}