{
  "type": "Feature",
  "properties": {
    "addr:full":"15 Little End Rd, St. Neots Huntingdon Bedfordshire PE19 3JH",
    "addr:housenumber":"15",
    "addr:postcode":"pe19 3jh",
    "addr:street":"Little End Rd",
    "iso:country":"GB",
    "sg:address":"15 Little End Rd, St. Neots",
    "sg:city":"Huntingdon",
    "sg:classifiers":[
        {
            "category":"Wholesale",
            "subcategory":"Medical Equipment & Supplies",
            "type":"Manufacturing & Wholesale Goods"
        }
    ],
    "sg:phone":"+44 1480 471972",
    "sg:postcode":"PE19 3JH",
    "sg:province":"Bedfordshire",
    "sg:tags":[
        "dental"
    ],
    "wof:name":"Rota-dent Ltd",
    "wof:placetype":"venue"
},
  "geometry": {"coordinates":[-0.27204,52.246269],"type":"Point"}
}