{
  "type": "Feature",
  "properties": {
    "iso:country":"GB",
    "sg:address":"2 Walsall Rd",
    "sg:city":"Willenhall",
    "sg:classifiers":[
        {
            "category":"Professional",
            "subcategory":"Engineering",
            "type":"Services"
        }
    ],
    "sg:phone":"+44 1902 603888",
    "sg:postcode":"WV13 2EH",
    "sg:province":"West Midlands",
    "sg:tags":[
        "civil",
        "engineer"
    ],
    "wof:name":"Lovat Europe Ltd",
    "wof:placetype":"venue"
},
  "geometry": {"coordinates":[-2.047036,52.584957],"type":"Point"}
}