{
  "type": "Feature",
  "properties": {
    "iso:country":"GB",
    "sg:address":"19 Church Road",
    "sg:city":"London",
    "sg:classifiers":[
        {
            "category":"Health Services",
            "subcategory":"Nursing And Care Facility",
            "type":"Services"
        },
        {
            "category":"Social Services",
            "subcategory":"Retirement Home",
            "type":"Services"
        }
    ],
    "sg:phone":"+44 20 8203 5368",
    "sg:postcode":"NW4 4EB",
    "sg:province":"Greater London",
    "sg:tags":[
        "residential"
    ],
    "wof:name":"Ella & Ridley Jacobs House",
    "wof:placetype":"venue"
},
  "geometry": {"coordinates":[-0.22572,51.589825],"type":"Point"}
}