{
  "type": "Feature",
  "properties": {
    "addr:full":"58 Woodside Ave Benfleet Essex SS7 4NY",
    "addr:housenumber":"58",
    "addr:postcode":"ss7 4ny",
    "addr:street":"Woodside Ave",
    "iso:country":"GB",
    "sg:address":"58 Woodside Ave",
    "sg:city":"Benfleet",
    "sg:classifiers":[
        {
            "category":"Building & Trades",
            "subcategory":"Landscaping Services",
            "type":"Services"
        }
    ],
    "sg:postcode":"SS7 4NY",
    "sg:province":"Essex",
    "sg:tags":[
        "forestry",
        "tree"
    ],
    "wof:name":"McCracken,P,",
    "wof:placetype":"venue"
},
  "geometry": {"coordinates":[0.5586739779,51.5764198303],"type":"Point"}
}