{
  "type": "Feature",
  "properties": {
    "addr:full":"Chapel La Northampton Buckinghamshire NN7 1BS",
    "addr:postcode":"nn7 1bs",
    "iso:country":"GB",
    "sg:address":"Chapel La",
    "sg:city":"Northampton",
    "sg:classifiers":[
        {
            "category":"Personal",
            "subcategory":"Beauty Salon",
            "type":"Services"
        }
    ],
    "sg:phone":"+44 1604 891431",
    "sg:postcode":"NN7 1BS",
    "sg:province":"Buckinghamshire",
    "sg:tags":[
        "lady",
        "hairdresser"
    ],
    "wof:name":"Lynda's Salon",
    "wof:placetype":"venue"
},
  "geometry": {"coordinates":[-0.7996240258,52.2207450867],"type":"Point"}
}