{
  "type": "Feature",
  "properties": {
    "iso:country":"GB",
    "sg:address":"46 Bath Street",
    "sg:city":"Glasgow",
    "sg:classifiers":[
        {
            "category":"Restaurant",
            "type":"Food & Drink"
        }
    ],
    "sg:phone":"+44 141 331 2391",
    "sg:postcode":"G2 1HG",
    "sg:province":"Glasgow City",
    "wof:name":"Garfunkel's Restaurant",
    "wof:placetype":"venue"
},
  "geometry": {"coordinates":[-4.255585,55.863834],"type":"Point"}
}