{
  "type": "Feature",
  "properties": {
    "iso:country":"GB",
    "sg:address":"Plymtree Manor, Plymtree",
    "sg:city":"Cullompton",
    "sg:classifiers":[
        {
            "category":"Food & Beverages",
            "subcategory":"Liquor & Beverages",
            "type":"Retail Goods"
        }
    ],
    "sg:phone":"+44 1884 277555",
    "sg:postcode":"EX15 2LE",
    "sg:province":"Devon",
    "sg:tags":[
        "beer",
        "wine",
        "spirit",
        "wines"
    ],
    "wof:name":"Peter Wylie Fine Wines",
    "wof:placetype":"venue"
},
  "geometry": {"coordinates":[-3.347823,50.817837],"type":"Point"}
}