{
  "type": "Feature",
  "properties": {
    "iso:country":"GB",
    "sg:address":"Westwood Garage, Margate Road",
    "sg:city":"Ramsgate",
    "sg:classifiers":[
        {
            "category":"Bus Charters",
            "type":"Transportation"
        }
    ],
    "sg:phone":"+44 1843 594681",
    "sg:postcode":"CT12 6SL",
    "sg:province":"Kent",
    "sg:tags":[
        "hire",
        "coach"
    ],
    "wof:name":"Stagecoach East Kent Ltd.",
    "wof:placetype":"venue"
},
  "geometry": {"coordinates":[1.39685,51.356991],"type":"Point"}
}