{
  "type": "Feature",
  "properties": {
    "addr:full":"30 Weston Zoyland Road Bridgwater Somerset TA6 5BN",
    "addr:housenumber":"30",
    "addr:postcode":"ta6 5bn",
    "addr:street":"Weston Zoyland Road",
    "iso:country":"GB",
    "sg:address":"30 Weston Zoyland Road",
    "sg:city":"Bridgwater",
    "sg:classifiers":[
        {
            "category":"Food & Beverages",
            "subcategory":"Meat & Fish",
            "type":"Retail Goods"
        }
    ],
    "sg:postcode":"TA6 5BN",
    "sg:province":"Somerset",
    "sg:tags":[
        "chip"
    ],
    "wof:name":"The Dolphin Fish Bar",
    "wof:placetype":"venue"
},
  "geometry": {"coordinates":[-2.988534,51.12632],"type":"Point"}
}