{
  "type": "Feature",
  "properties": {
    "addr:full":"53 St Margarets Road London Greater London W7 2HX",
    "addr:housenumber":"53",
    "addr:postcode":"w7 2hx",
    "addr:street":"St Margarets Road",
    "iso:country":"GB",
    "sg:address":"53 St Margarets Road",
    "sg:city":"London",
    "sg:classifiers":[
        {
            "category":"Professional",
            "subcategory":"Engineering",
            "type":"Services"
        }
    ],
    "sg:phone":"+44 20 8567 1293",
    "sg:postcode":"W7 2HX",
    "sg:province":"Greater London",
    "sg:tags":[
        "engineer",
        "mechanical"
    ],
    "wof:name":"D Wildy & Sons",
    "wof:placetype":"venue"
},
  "geometry": {"coordinates":[-0.338927,51.503201],"type":"Point"}
}