{
  "type": "Feature",
  "properties": {
    "iso:country":"GB",
    "sg:address":"17 Calver Gro",
    "sg:city":"Birmingham",
    "sg:classifiers":[
        {
            "category":"Building & Trades",
            "subcategory":"Construction",
            "type":"Services"
        }
    ],
    "sg:phone":"+44 121 325 0161",
    "sg:postcode":"B44 9BE",
    "sg:province":"West Midlands",
    "sg:tags":[
        "builder"
    ],
    "wof:name":"David Hodder Roofing & Building",
    "wof:placetype":"venue"
},
  "geometry": {"coordinates":[-1.901496,52.553131],"type":"Point"}
}