{
  "type": "Feature",
  "properties": {
    "addr:full":"2 Somerset Villas, Corseley Road, Groombridge Tunbridge Wells East Sussex TN3 9RR",
    "addr:housenumber":"2",
    "addr:postcode":"tn3 9rr",
    "addr:street":"Somerset Villas Corseley Road",
    "iso:country":"GB",
    "sg:address":"2 Somerset Villas, Corseley Road, Groombridge",
    "sg:city":"Tunbridge Wells",
    "sg:classifiers":[
        {
            "category":"Utilities",
            "subcategory":"Natural Gas",
            "type":"Services"
        }
    ],
    "sg:phone":"+44 1892 610303",
    "sg:postcode":"TN3 9RR",
    "sg:province":"East Sussex",
    "sg:tags":[
        "resurfacing",
        "bath"
    ],
    "wof:name":"Southern Bath Resurfacing",
    "wof:placetype":"venue"
},
  "geometry": {"coordinates":[0.178580001,51.1116256714],"type":"Point"}
}