{
  "type": "Feature",
  "properties": {
    "iso:country":"GB",
    "sg:address":"Corris Craft Centre",
    "sg:city":"Machynlleth",
    "sg:classifiers":[
        {
            "category":"Landmark",
            "subcategory":"Tourist Attraction",
            "type":"Public Place"
        }
    ],
    "sg:phone":"+44 1654 761584",
    "sg:postcode":"SY20 9RF",
    "sg:province":"Ceredigion",
    "sg:tags":[
        "interest"
    ],
    "wof:name":"Corris Caverns Ltd.",
    "wof:placetype":"venue"
},
  "geometry": {"coordinates":[-3.843345,52.652039],"type":"Point"}
}