{
  "type": "Feature",
  "properties": {
    "iso:country":"GB",
    "sg:address":"Starley Rd",
    "sg:city":"Coventry",
    "sg:classifiers":[
        {
            "category":"Personal",
            "subcategory":"Psychics & Astrologers",
            "type":"Services"
        }
    ],
    "sg:phone":"+44 24 7622 5121",
    "sg:postcode":"CV1 3JU",
    "sg:province":"West Midlands",
    "sg:tags":[
        "clairvoyant",
        "palmist"
    ],
    "wof:name":"Callie International Clairvoyant",
    "wof:placetype":"venue"
},
  "geometry": {"coordinates":[-1.517165,52.40559],"type":"Point"}
}