{
  "type": "Feature",
  "properties": {
    "addr:full":"4 Hawkenbury Clo Tunbridge Wells East Sussex TN2 5BL",
    "addr:housenumber":"4",
    "addr:postcode":"tn2 5bl",
    "addr:street":"Hawkenbury Clo",
    "iso:country":"GB",
    "sg:address":"4 Hawkenbury Clo",
    "sg:city":"Tunbridge Wells",
    "sg:classifiers":[
        {
            "category":"Building & Trades",
            "subcategory":"Construction",
            "type":"Services"
        }
    ],
    "sg:phone":"+44 1892 525072",
    "sg:postcode":"TN2 5BL",
    "sg:province":"East Sussex",
    "sg:tags":[
        "decorator",
        "painter"
    ],
    "wof:name":"J Winter",
    "wof:placetype":"venue"
},
  "geometry": {"coordinates":[0.2797699869,51.1240348816],"type":"Point"}
}