{
  "type": "Feature",
  "properties": {
    "iso:country":"GB",
    "sg:address":"2 Cosgrove Road, Old Stratford",
    "sg:city":"Milton Keynes",
    "sg:classifiers":[
        {
            "category":"Retail",
            "subcategory":"Auto Rental",
            "type":"Services"
        }
    ],
    "sg:phone":"+44 1908 262662",
    "sg:postcode":"MK19 6AF",
    "sg:province":"Buckinghamshire",
    "sg:tags":[
        "car",
        "hire",
        "truck"
    ],
    "wof:name":"Foxfield Securities Ltd.",
    "wof:placetype":"venue"
},
  "geometry": {"coordinates":[-0.864399,52.063354],"type":"Point"}
}