{
  "type": "Feature",
  "properties": {
    "iso:country":"GB",
    "sg:address":"88 Lincoln Road",
    "sg:city":"Peterborough",
    "sg:classifiers":[
        {
            "category":"Education",
            "subcategory":"University",
            "type":"Public Place"
        }
    ],
    "sg:postcode":"PE1 2SN",
    "sg:province":"Cambridgeshire",
    "sg:tags":[
        "higher"
    ],
    "wof:name":"Tammy Hair & Beauty Centre",
    "wof:placetype":"venue"
},
  "geometry": {"coordinates":[-0.243731007,52.5796890259],"type":"Point"}
}