{
  "type": "Feature",
  "properties": {
    "iso:country":"GB",
    "sg:address":"67 Cadzow Street",
    "sg:city":"Hamilton",
    "sg:classifiers":[
        {
            "category":"Banks & Credit Unions",
            "subcategory":"Bank",
            "type":"Services"
        }
    ],
    "sg:phone":"+44 1698 426642",
    "sg:postcode":"ML3 6DZ",
    "sg:province":"South Lanarkshire",
    "wof:name":"Clydesdale Bank Plc",
    "wof:placetype":"venue"
},
  "geometry": {"coordinates":[-4.036009,55.776596],"type":"Point"}
}