{
  "type": "Feature",
  "properties": {
    "addr:full":"Trouthall Nursery, Trouthall Lane, Plumley Knutsford Cheshire WA16 9RZ",
    "addr:postcode":"wa16 9rz",
    "addr:street":"Trouthall Lane",
    "iso:country":"GB",
    "sg:address":"Trouthall Nursery, Trouthall Lane, Plumley",
    "sg:city":"Knutsford",
    "sg:classifiers":[
        {
            "category":"Building & Trades",
            "subcategory":"Landscaping Services",
            "type":"Services"
        }
    ],
    "sg:phone":"+44 1565 723010",
    "sg:postcode":"WA16 9RZ",
    "sg:province":"Cheshire",
    "sg:tags":[
        "landscape",
        "contractor"
    ],
    "wof:name":"Hulse Landscapes",
    "wof:placetype":"venue"
},
  "geometry": {"coordinates":[-2.37624,53.304203],"type":"Point"}
}