{
  "type": "Feature",
  "properties": {
    "addr:full":"Park House Watford Hertfordshire WD18 8PH",
    "addr:postcode":"wd18 8ph",
    "iso:country":"GB",
    "sg:address":"Park House",
    "sg:city":"Watford",
    "sg:classifiers":[
        {
            "category":"Shopping",
            "subcategory":"Mobile Phones",
            "type":"Retail Goods"
        },
        {
            "category":"Real Estate",
            "subcategory":"Real Estate Agent",
            "type":"Services"
        }
    ],
    "sg:postcode":"WD18 8PH",
    "sg:province":"Hertfordshire",
    "wof:name":"Phones Direct",
    "wof:placetype":"venue"
},
  "geometry": {"coordinates":[-0.4258,51.64603],"type":"Point"}
}