{
  "type": "Feature",
  "properties": {
    "addr:full":"Law Hospital, Carluke Road Carluke South Lanarkshire ML8 5ER",
    "addr:postcode":"ml8 5er",
    "addr:street":"Carluke Road",
    "iso:country":"GB",
    "sg:address":"Law Hospital, Carluke Road",
    "sg:city":"Carluke",
    "sg:classifiers":[
        {
            "category":"Professional",
            "subcategory":"Testing Lab",
            "type":"Services"
        }
    ],
    "sg:phone":"+44 1698 351161",
    "sg:postcode":"ML8 5ER",
    "sg:province":"South Lanarkshire",
    "sg:tags":[
        "laboratory"
    ],
    "wof:name":"S A P U",
    "wof:placetype":"venue"
},
  "geometry": {"coordinates":[-3.837712,55.736324],"type":"Point"}
}