{
  "type": "Feature",
  "properties": {
    "addr:full":"5 Lynedoch St Glasgow Glasgow City G3 6EF",
    "addr:housenumber":"5",
    "addr:postcode":"g3 6ef",
    "addr:street":"Lynedoch St",
    "iso:country":"GB",
    "sg:address":"5 Lynedoch St",
    "sg:city":"Glasgow",
    "sg:classifiers":[
        {
            "category":"Professional",
            "subcategory":"Engineering",
            "type":"Services"
        }
    ],
    "sg:phone":"+44 141 332 8810",
    "sg:postcode":"G3 6EF",
    "sg:province":"Glasgow City",
    "sg:tags":[
        "underpinning",
        "foundation",
        "engineer"
    ],
    "wof:name":"Keller Group Ltd",
    "wof:placetype":"venue"
},
  "geometry": {"coordinates":[-4.2734069824,55.8684921265],"type":"Point"}
}