{
  "type": "Feature",
  "properties": {
    "addr:full":"3 East Street Rochford Essex SS4 1DB",
    "addr:housenumber":"3",
    "addr:postcode":"ss4 1db",
    "addr:street":"East Street",
    "iso:country":"GB",
    "sg:address":"3 East Street",
    "sg:city":"Rochford",
    "sg:classifiers":[
        {
            "category":"Shopping",
            "subcategory":"Department Store",
            "type":"Retail Goods"
        },
        {
            "category":"Shopping",
            "subcategory":"Hobbies, Toys, & Games",
            "type":"Retail Goods"
        }
    ],
    "sg:phone":"+44 1702 543541",
    "sg:postcode":"SS4 1DB",
    "sg:province":"Essex",
    "sg:tags":[
        "house",
        "dolls'",
        "doll"
    ],
    "wof:name":"The Rochford Dolls House",
    "wof:placetype":"venue"
},
  "geometry": {"coordinates":[0.693473,51.595291],"type":"Point"}
}