{
  "type": "Feature",
  "properties": {
    "iso:country":"GB",
    "sg:address":"Enquiries, 8-180 Redditch Road, Kings Norton",
    "sg:city":"Birmingham",
    "sg:classifiers":[
        {
            "category":"Retail",
            "subcategory":"Driving School",
            "type":"Services"
        }
    ],
    "sg:phone":"+44 121 459 5757",
    "sg:postcode":"B38 8QE",
    "sg:province":"West Midlands",
    "wof:name":"Aardvark Drivetrain",
    "wof:placetype":"venue"
},
  "geometry": {"coordinates":[-1.93716,52.40015],"type":"Point"}
}