{
  "type": "Feature",
  "properties": {
    "iso:country":"GB",
    "sg:address":"170 Bevington Road, Aston",
    "sg:city":"Birmingham",
    "sg:classifiers":[
        {
            "category":"Shopping",
            "subcategory":"Department Store",
            "type":"Retail Goods"
        }
    ],
    "sg:postcode":"B6 6HT",
    "sg:province":"West Midlands",
    "wof:name":"A R General Stores",
    "wof:placetype":"venue"
},
  "geometry": {"coordinates":[-1.8881089687,52.5045204163],"type":"Point"}
}