{
  "type": "Feature",
  "properties": {
    "iso:country":"GB",
    "sg:address":"Pinefield Indust Est",
    "sg:city":"Elgin",
    "sg:classifiers":[
        {
            "category":"Manufacturing",
            "subcategory":"Building Materials",
            "type":"Manufacturing & Wholesale Goods"
        }
    ],
    "sg:phone":"+44 1343 543181",
    "sg:postcode":"IV30 3AG",
    "sg:province":"Moray",
    "sg:tags":[
        "merchant",
        "builder"
    ],
    "wof:name":"W M Wilson & Co (Aberdeen) Ltd",
    "wof:placetype":"venue"
},
  "geometry": {"coordinates":[-3.32902,57.625462],"type":"Point"}
}