{
  "type": "Feature",
  "properties": {
    "addr:full":"Trinity House, Foxes Parade Waltham Abbey Essex EN9 1PH",
    "addr:postcode":"en9 1ph",
    "addr:street":"Foxes Parade",
    "iso:country":"GB",
    "sg:address":"Trinity House, Foxes Parade",
    "sg:city":"Waltham Abbey",
    "sg:classifiers":[
        {
            "category":"Wholesale",
            "subcategory":"Fruits & Vegetables",
            "type":"Manufacturing & Wholesale Goods"
        }
    ],
    "sg:postcode":"EN9 1PH",
    "sg:province":"Essex",
    "wof:name":"Bentop Trading Ltd.",
    "wof:placetype":"venue"
},
  "geometry": {"coordinates":[0.0014900001,51.6864204407],"type":"Point"}
}