{
  "type": "Feature",
  "properties": {
    "iso:country":"GB",
    "sg:address":"12 Gynn Avenue",
    "sg:city":"Blackpool",
    "sg:classifiers":[
        {
            "category":"Travel",
            "subcategory":"Hotels & Motels",
            "type":"Entertainment"
        }
    ],
    "sg:phone":"+44 1253 351714",
    "sg:postcode":"FY1 2LD",
    "sg:province":"Lancashire",
    "sg:tags":[
        "house",
        "guest"
    ],
    "wof:name":"Rossdene Hotel",
    "wof:placetype":"venue"
},
  "geometry": {"coordinates":[-3.0548799038,53.8314628601],"type":"Point"}
}