{
  "type": "Feature",
  "properties": {
    "iso:country":"GB",
    "sg:address":"44 Eastcote Av",
    "sg:city":"Harrow",
    "sg:classifiers":[
        {
            "category":"Building & Trades",
            "subcategory":"Construction",
            "type":"Services"
        }
    ],
    "sg:phone":"+44 20 8248 8484",
    "sg:postcode":"HA2 8AL",
    "sg:province":"Greater London",
    "sg:tags":[
        "roofing"
    ],
    "wof:name":"Capital Roofing",
    "wof:placetype":"venue"
},
  "geometry": {"coordinates":[-0.3567839861,51.5667686462],"type":"Point"}
}