{
  "type": "Feature",
  "properties": {
    "addr:full":"52 Newton Crescent Dunblane Perth and Kinross FK15 0DZ",
    "addr:housenumber":"52",
    "addr:postcode":"fk15 0dz",
    "addr:street":"Newton Crescent",
    "iso:country":"GB",
    "sg:address":"52 Newton Crescent",
    "sg:city":"Dunblane",
    "sg:classifiers":[
        {
            "category":"Real Estate",
            "subcategory":"Real Estate Services",
            "type":"Services"
        }
    ],
    "sg:postcode":"FK15 0DZ",
    "sg:province":"Perth and Kinross",
    "sg:tags":[
        "management",
        "facility"
    ],
    "wof:name":"F M Resolutions Ltd",
    "wof:placetype":"venue"
},
  "geometry": {"coordinates":[-3.9484620094,56.1913948059],"type":"Point"}
}