{
  "type": "Feature",
  "properties": {
    "addr:full":"204 Liverpool Road Widnes Cheshire WA8 7HY",
    "addr:housenumber":"204",
    "addr:postcode":"wa8 7hy",
    "addr:street":"Liverpool Road",
    "iso:country":"GB",
    "sg:address":"204 Liverpool Road",
    "sg:city":"Widnes",
    "sg:classifiers":[
        {
            "category":"Building & Trades",
            "subcategory":"Construction",
            "type":"Services"
        }
    ],
    "sg:phone":"+44 151 424 5303",
    "sg:postcode":"WA8 7HY",
    "sg:province":"Cheshire",
    "sg:tags":[
        "builder"
    ],
    "wof:name":"C & D Cambell",
    "wof:placetype":"venue"
},
  "geometry": {"coordinates":[-2.75378,53.371445],"type":"Point"}
}