{
  "type": "Feature",
  "properties": {
    "addr:full":"58 High Street Ilfracombe Devon EX34 9QB",
    "addr:housenumber":"58",
    "addr:postcode":"ex34 9qb",
    "addr:street":"High Street",
    "iso:country":"GB",
    "sg:address":"58 High Street",
    "sg:city":"Ilfracombe",
    "sg:classifiers":[
        {
            "category":"Health Services",
            "subcategory":"Podiatrist",
            "type":"Services"
        }
    ],
    "sg:phone":"+44 1271 865989",
    "sg:postcode":"EX34 9QB",
    "sg:province":"Devon",
    "sg:tags":[
        "podiatrists",
        "chiropodist"
    ],
    "wof:name":"Angeo",
    "wof:placetype":"venue"
},
  "geometry": {"coordinates":[-4.1253299713,51.2069854736],"type":"Point"}
}