{
  "type": "Feature",
  "properties": {
    "iso:country":"GB",
    "sg:address":"67 Elmcroft Avenue",
    "sg:city":"London",
    "sg:classifiers":[
        {
            "category":"Building & Trades",
            "subcategory":"Construction",
            "type":"Services"
        },
        {
            "category":"Government",
            "subcategory":"Post Office",
            "type":"Public Place"
        }
    ],
    "sg:phone":"+44 20 8491 0120",
    "sg:postcode":"E11 2BN",
    "sg:province":"Greater London",
    "sg:tags":[
        "builder"
    ],
    "wof:name":"OFFICE SCOPE",
    "wof:placetype":"venue"
},
  "geometry": {"coordinates":[0.02879,51.576031],"type":"Point"}
}