{
  "type": "Feature",
  "properties": {
    "addr:full":"Queen Sq Bristol Somerset BS48 3EL",
    "addr:postcode":"bs48 3el",
    "addr:street":"Queen Sq",
    "iso:country":"GB",
    "sg:address":"Queen Sq",
    "sg:city":"Bristol",
    "sg:classifiers":[
        {
            "category":"Place Of Worship",
            "type":"Public Place"
        }
    ],
    "sg:phone":"+44 1225 872275",
    "sg:postcode":"BS48 3EL",
    "sg:province":"Somerset",
    "wof:name":"St Marys C Of E Church",
    "wof:placetype":"venue"
},
  "geometry": {"coordinates":[-2.7241311073,51.4073867798],"type":"Point"}
}