{
  "type": "Feature",
  "properties": {
    "addr:full":"Nettle Tree Farm, Horton Heath, Horton Wimborne Dorset BH21 7JN",
    "addr:postcode":"bh21 7jn",
    "addr:street":"Nettle",
    "iso:country":"GB",
    "sg:address":"Nettle Tree Farm, Horton Heath, Horton",
    "sg:city":"Wimborne",
    "sg:classifiers":[
        {
            "category":"Building & Trades",
            "subcategory":"Landscaping Services",
            "type":"Services"
        }
    ],
    "sg:phone":"+44 1202 828800",
    "sg:postcode":"BH21 7JN",
    "sg:province":"Dorset",
    "sg:tags":[
        "designer",
        "landscape",
        "contractor"
    ],
    "sg:website":"http://www.banyardsltd.com",
    "wof:name":"Keith D Banyard",
    "wof:placetype":"venue"
},
  "geometry": {"coordinates":[-1.9598939419,50.8675842285],"type":"Point"}
}