{
  "type": "Feature",
  "properties": {
    "addr:full":"20 Queen St, Earlestown Newton Le Willows Cheshire WA12 9AX",
    "addr:housenumber":"20",
    "addr:postcode":"wa12 9ax",
    "addr:street":"Queen St;Newton Le Willows",
    "iso:country":"GB",
    "sg:address":"20 Queen St, Earlestown",
    "sg:city":"Newton Le Willows",
    "sg:classifiers":[
        {
            "category":"Manufacturing",
            "subcategory":"Wood Products",
            "type":"Manufacturing & Wholesale Goods"
        }
    ],
    "sg:phone":"+44 1925 224575",
    "sg:postcode":"WA12 9AX",
    "sg:province":"Cheshire",
    "sg:tags":[
        "maker",
        "cabinet"
    ],
    "wof:name":"Choice Home Improvement Centre",
    "wof:placetype":"venue"
},
  "geometry": {"coordinates":[-2.6391479969,53.4514312744],"type":"Point"}
}