{
  "type": "Feature",
  "properties": {
    "addr:full":"60 Hanover Gardens, Oval London Greater London SE11 5TN",
    "addr:housenumber":"60",
    "addr:postcode":"se11 5tn",
    "addr:street":"Hanover Gardens Oval",
    "iso:country":"GB",
    "sg:address":"60 Hanover Gardens, Oval",
    "sg:city":"London",
    "sg:classifiers":[
        {
            "category":"Shopping",
            "subcategory":"Department Store",
            "type":"Retail Goods"
        }
    ],
    "sg:postcode":"SE11 5TN",
    "sg:province":"Greater London",
    "wof:name":"Vip Management Ltd.",
    "wof:placetype":"venue"
},
  "geometry": {"coordinates":[-0.11413,51.481899],"type":"Point"}
}