{
  "type": "Feature",
  "properties": {
    "addr:full":"Park Lane House, 47 Broad Street Glasgow Glasgow City G40 2QW",
    "addr:housenumber":"47",
    "addr:postcode":"g40 2qw",
    "addr:street":"Broad Street",
    "iso:country":"GB",
    "sg:address":"Park Lane House, 47 Broad Street",
    "sg:city":"Glasgow",
    "sg:classifiers":[
        {
            "category":"Professional",
            "subcategory":"Detective & Security Services",
            "type":"Services"
        }
    ],
    "sg:postcode":"G40 2QW",
    "sg:province":"Glasgow City",
    "sg:tags":[
        "agency"
    ],
    "wof:name":"Saks Investigations",
    "wof:placetype":"venue"
},
  "geometry": {"coordinates":[-4.225472,55.850246],"type":"Point"}
}