{
  "type": "Feature",
  "properties": {
    "addr:full":"25 Boulton Road Stevenage Hertfordshire SG1 4PL",
    "addr:housenumber":"25",
    "addr:postcode":"sg1 4pl",
    "addr:street":"Boulton Road",
    "iso:country":"GB",
    "sg:address":"25 Boulton Road",
    "sg:city":"Stevenage",
    "sg:classifiers":[
        {
            "category":"Manufacturing",
            "subcategory":"Wood Products",
            "type":"Manufacturing & Wholesale Goods"
        },
        {
            "category":"Professional",
            "subcategory":"Computer Services",
            "type":"Services"
        }
    ],
    "sg:phone":"+44 1438 222232",
    "sg:postcode":"SG1 4PL",
    "sg:province":"Hertfordshire",
    "sg:tags":[
        "aided",
        "design",
        "maker",
        "cabinet"
    ],
    "wof:name":"Quantum Design Ltd.",
    "wof:placetype":"venue"
},
  "geometry": {"coordinates":[-0.168604,51.926437],"type":"Point"}
}