{
  "type": "Feature",
  "properties": {
    "addr:full":"Windtop, Upper Pavenhill, Purton Swindon Wiltshire SN5 4DQ",
    "addr:postcode":"sn5 4dq",
    "addr:street":"Upper Pavenhill",
    "iso:country":"GB",
    "sg:address":"Windtop, Upper Pavenhill, Purton",
    "sg:city":"Swindon",
    "sg:classifiers":[
        {
            "category":"Building & Trades",
            "subcategory":"Construction",
            "type":"Services"
        }
    ],
    "sg:phone":"+44 1793 771193",
    "sg:postcode":"SN5 4DQ",
    "sg:province":"Wiltshire",
    "sg:tags":[
        "builder"
    ],
    "wof:name":"J E Frost",
    "wof:placetype":"venue"
},
  "geometry": {"coordinates":[-1.8660390377,51.5903739929],"type":"Point"}
}