{
  "type": "Feature",
  "properties": {
    "iso:country":"GB",
    "sg:address":"165 High Street",
    "sg:city":"Rickmansworth",
    "sg:classifiers":[
        {
            "category":"Professional",
            "subcategory":"Business Services",
            "type":"Services"
        }
    ],
    "sg:phone":"+44 1923 710611",
    "sg:postcode":"WD3 1AY",
    "sg:province":"Hertfordshire",
    "sg:tags":[
        "assessment",
        "quality"
    ],
    "wof:name":"John Dickinson & Andrew Glanville",
    "wof:placetype":"venue"
},
  "geometry": {"coordinates":[-0.4722310007,51.6390190125],"type":"Point"}
}