{
  "type": "Feature",
  "properties": {
    "iso:country":"GB",
    "sg:address":"15 Bexhill Road",
    "sg:city":"St Leonards-on-sea",
    "sg:classifiers":[
        {
            "category":"Government",
            "subcategory":"Post Office",
            "type":"Public Place"
        }
    ],
    "sg:phone":"+44 1424 420791",
    "sg:postcode":"TN38 0AH",
    "sg:province":"East Sussex",
    "wof:name":"West St Leonards Sub Post Office",
    "wof:placetype":"venue"
},
  "geometry": {"coordinates":[0.537721,50.851162],"type":"Point"}
}