{
  "type": "Feature",
  "properties": {
    "addr:full":"1 Taymount Terrace Perth Perth and Kinross PH1 1NU",
    "addr:housenumber":"1",
    "addr:postcode":"ph1 1nu",
    "addr:street":"Taymount Terrace",
    "iso:country":"GB",
    "sg:address":"1 Taymount Terrace",
    "sg:city":"Perth",
    "sg:classifiers":[
        {
            "category":"Health Services",
            "subcategory":"Doctor",
            "type":"Services"
        }
    ],
    "sg:phone":"+44 1738 627117",
    "sg:postcode":"PH1 1NU",
    "sg:province":"Perth and Kinross",
    "sg:tags":[
        "practitioners"
    ],
    "wof:name":"J I Watson",
    "wof:placetype":"venue"
},
  "geometry": {"coordinates":[-3.4512600899,56.3957290649],"type":"Point"}
}