{
  "type": "Feature",
  "properties": {
    "addr:full":"64-65 North Road, St Andrews Bristol City of Bristol BS6 5AQ",
    "addr:housenumber":"64-65",
    "addr:postcode":"bs6 5aq",
    "addr:street":"North Road",
    "iso:country":"GB",
    "sg:address":"64-65 North Road, St Andrews",
    "sg:city":"Bristol",
    "sg:classifiers":[
        {
            "category":"Communications",
            "subcategory":"Newspaper",
            "type":"Services"
        }
    ],
    "sg:phone":"+44 117 942 8491",
    "sg:postcode":"BS6 5AQ",
    "sg:province":"City of Bristol",
    "sg:tags":[
        "magazine"
    ],
    "wof:name":"Greetlake Services Ltd.",
    "wof:placetype":"venue"
},
  "geometry": {"coordinates":[-2.5914690495,51.4717788696],"type":"Point"}
}