{
  "type": "Feature",
  "properties": {
    "addr:full":"Southwick Road, Wickham Fareham Hampshire PO17 6HT",
    "addr:postcode":"po17 6ht",
    "addr:street":"Southwick Road",
    "iso:country":"GB",
    "sg:address":"Southwick Road, Wickham",
    "sg:city":"Fareham",
    "sg:classifiers":[
        {
            "category":"Education",
            "subcategory":"School",
            "type":"Public Place"
        }
    ],
    "sg:phone":"+44 1329 833108",
    "sg:postcode":"PO17 6HT",
    "sg:province":"Hampshire",
    "sg:tags":[
        "independent",
        "preparatory"
    ],
    "wof:name":"Rookesbury Park Ltd.",
    "wof:placetype":"venue"
},
  "geometry": {"coordinates":[-1.1076129675,50.8699073792],"type":"Point"}
}