{
  "type": "Feature",
  "properties": {
    "addr:full":"Fordley Respite Centre, 15 Annitsford Drive, Dudley Cramlington Northumberland NE23 7AP",
    "addr:housenumber":"15",
    "addr:postcode":"ne23 7ap",
    "addr:street":"Annitsford Drive",
    "iso:country":"GB",
    "sg:address":"Fordley Respite Centre, 15 Annitsford Drive, Dudley",
    "sg:city":"Cramlington",
    "sg:classifiers":[
        {
            "category":"Organizations",
            "subcategory":"Non-profit Organization",
            "type":"Services"
        }
    ],
    "sg:phone":"+44 191 200 8001",
    "sg:postcode":"NE23 7AP",
    "sg:province":"Northumberland",
    "sg:tags":[
        "organisation",
        "voluntary",
        "charity"
    ],
    "wof:name":"Care in the Community",
    "wof:placetype":"venue"
},
  "geometry": {"coordinates":[-1.579019,55.063019],"type":"Point"}
}