{
  "type": "Feature",
  "properties": {
    "iso:country":"GB",
    "sg:address":"Gotechnic House",
    "sg:city":"Ashford",
    "sg:classifiers":[
        {
            "category":"Shopping",
            "subcategory":"Pets & Pet Supplies",
            "type":"Retail Goods"
        }
    ],
    "sg:phone":"+44 1784 880480",
    "sg:postcode":"TW15 2RP",
    "sg:province":"Greater London",
    "sg:tags":[
        "equestrian"
    ],
    "wof:name":"Horse Bitz",
    "wof:placetype":"venue"
},
  "geometry": {"coordinates":[-0.4624440074,51.432975769],"type":"Point"}
}