{
  "type": "Feature",
  "properties": {
    "addr:full":"Studio 2 George Leigh, Street School, George Leigh Street Manchester Greater Manchester M4 6AT",
    "addr:housenumber":"2",
    "addr:postcode":"m4 6at",
    "addr:street":"George Leigh;George Leigh Street",
    "iso:country":"GB",
    "sg:address":"Studio 2 George Leigh, Street School, George Leigh Street",
    "sg:city":"Manchester",
    "sg:classifiers":[
        {
            "category":"Professional",
            "subcategory":"Art Services",
            "type":"Services"
        }
    ],
    "sg:phone":"+44 161 236 1285",
    "sg:postcode":"M4 6AT",
    "sg:province":"Greater Manchester",
    "sg:tags":[
        "photographer"
    ],
    "wof:name":"Woollams & Woollams",
    "wof:placetype":"venue"
},
  "geometry": {"coordinates":[-2.2231600285,53.4843597412],"type":"Point"}
}