{
  "type": "Feature",
  "properties": {
    "iso:country":"GB",
    "sg:address":"Main Street, Chapelhall",
    "sg:city":"Airdrie",
    "sg:classifiers":[
        {
            "category":"Shopping",
            "subcategory":"Stationery & Office Supplies",
            "type":"Retail Goods"
        }
    ],
    "sg:phone":"+44 1236 756552",
    "sg:postcode":"ML6 8SF",
    "sg:province":"North Lanarkshire",
    "sg:tags":[
        "equipment",
        "educational",
        "school"
    ],
    "wof:name":"Technician Service Centre",
    "wof:placetype":"venue"
},
  "geometry": {"coordinates":[-3.950414,55.842033],"type":"Point"}
}