{
  "type": "Feature",
  "properties": {
    "addr:full":"Unit 1 Morecambe Lancashire LA3 3PS",
    "addr:housenumber":"unit 1",
    "addr:postcode":"la3 3ps",
    "iso:country":"GB",
    "sg:address":"Unit 1",
    "sg:city":"Morecambe",
    "sg:classifiers":[
        {
            "category":"Sports & Exercise",
            "subcategory":"Race Track",
            "type":"Entertainment"
        }
    ],
    "sg:phone":"+44 1524 62748",
    "sg:postcode":"LA3 3PS",
    "sg:province":"Lancashire",
    "sg:tags":[
        "motor"
    ],
    "wof:name":"L A D Motor Sports",
    "wof:placetype":"venue"
},
  "geometry": {"coordinates":[-2.8551490307,54.0434112549],"type":"Point"}
}