{
  "type": "Feature",
  "properties": {
    "addr:full":"Killellan Farm, Toward Dunoon Argyll and Bute PA23 7UJ",
    "addr:postcode":"pa23 7uj",
    "addr:street":"Toward",
    "iso:country":"GB",
    "sg:address":"Killellan Farm, Toward",
    "sg:city":"Dunoon",
    "sg:classifiers":[
        {
            "category":"Farming",
            "subcategory":"Livestock Farm",
            "type":"Manufacturing & Wholesale Goods"
        },
        {
            "category":"Farming",
            "subcategory":"Farm",
            "type":"Manufacturing & Wholesale Goods"
        }
    ],
    "sg:phone":"+44 1369 870239",
    "sg:postcode":"PA23 7UJ",
    "sg:province":"Argyll and Bute",
    "sg:tags":[
        "mixed",
        "crop",
        "others"
    ],
    "wof:name":"J & A Mitchell",
    "wof:placetype":"venue"
},
  "geometry": {"coordinates":[-4.9807090759,55.8685264587],"type":"Point"}
}