{
  "type": "Feature",
  "properties": {
    "iso:country":"GB",
    "sg:address":"Quadrangle Building, 13 Waterloo Road",
    "sg:city":"Liverpool",
    "sg:classifiers":[
        {
            "category":"Professional",
            "subcategory":"Printing & Photocopies",
            "type":"Services"
        }
    ],
    "sg:phone":"+44 151 236 2817",
    "sg:postcode":"L3 7BB",
    "sg:province":"Merseyside",
    "sg:tags":[
        "printer"
    ],
    "wof:name":"S & A Print Services",
    "wof:placetype":"venue"
},
  "geometry": {"coordinates":[-2.99897,53.412796],"type":"Point"}
}