{
  "type": "Feature",
  "properties": {
    "iso:country":"GB",
    "sg:address":"Regmar House, East Road",
    "sg:city":"London",
    "sg:classifiers":[
        {
            "category":"Shopping",
            "subcategory":"Clothing, Apparel, & Fashions",
            "type":"Retail Goods"
        }
    ],
    "sg:phone":"+44 20 7253 9001",
    "sg:postcode":"N1 6AB",
    "sg:province":"Greater London",
    "sg:tags":[
        "clothing",
        "fabric"
    ],
    "wof:name":"Reggie & Co. Ltd.",
    "wof:placetype":"venue"
},
  "geometry": {"coordinates":[-0.08684,51.529308],"type":"Point"}
}