{
  "type": "Feature",
  "properties": {
    "iso:country":"GB",
    "sg:address":"68 Stratford Rd",
    "sg:city":"Luton",
    "sg:classifiers":[
        {
            "category":"Communications",
            "type":"Services"
        }
    ],
    "sg:phone":"+44 1582 592607",
    "sg:postcode":"LU4 8NG",
    "sg:province":"Bedfordshire",
    "sg:tags":[
        "telecommunication"
    ],
    "wof:name":"Financial Data Services",
    "wof:placetype":"venue"
},
  "geometry": {"coordinates":[-0.4367209971,51.8909034729],"type":"Point"}
}