{
  "type": "Feature",
  "properties": {
    "addr:full":"Unit 1, Chapel Court, Barton Street Tewkesbury Gloucestershire GL20 5PY",
    "addr:housenumber":"unit 1",
    "addr:postcode":"gl20 5py",
    "addr:street":"Chapel Court Barton Street",
    "iso:country":"GB",
    "sg:address":"Unit 1, Chapel Court, Barton Street",
    "sg:city":"Tewkesbury",
    "sg:classifiers":[
        {
            "category":"Shopping",
            "subcategory":"Clothing, Apparel, & Fashions",
            "type":"Retail Goods"
        }
    ],
    "sg:phone":"+44 1684 290533",
    "sg:postcode":"GL20 5PY",
    "sg:province":"Gloucestershire",
    "sg:tags":[
        "menswear"
    ],
    "wof:name":"Peter Wormington",
    "wof:placetype":"venue"
},
  "geometry": {"coordinates":[-2.1535990238,51.9929542542],"type":"Point"}
}