{
  "type": "Feature",
  "properties": {
    "addr:full":"12 Marsden Avenue, Queniborough Leicester Leicestershire LE7 3FL",
    "addr:housenumber":"12",
    "addr:postcode":"le7 3fl",
    "addr:street":"Marsden Avenue",
    "iso:country":"GB",
    "sg:address":"12 Marsden Avenue, Queniborough",
    "sg:city":"Leicester",
    "sg:classifiers":[
        {
            "category":"Health Services",
            "subcategory":"Health Practitioner",
            "type":"Services"
        }
    ],
    "sg:postcode":"LE7 3FL",
    "sg:province":"Leicestershire",
    "sg:tags":[
        "physiotherapist"
    ],
    "wof:name":"Mark Geeson",
    "wof:placetype":"venue"
},
  "geometry": {"coordinates":[-1.0554900169,52.7061653137],"type":"Point"}
}