{
  "type": "Feature",
  "properties": {
    "addr:full":"2 Court Yard, Collinton Walk Dorchester Dorset DT1 1TZ",
    "addr:housenumber":"2",
    "addr:postcode":"dt1 1tz",
    "addr:street":"Court Yard Collinton Walk",
    "iso:country":"GB",
    "sg:address":"2 Court Yard, Collinton Walk",
    "sg:city":"Dorchester",
    "sg:classifiers":[
        {
            "category":"Shopping",
            "subcategory":"Pharmacy",
            "type":"Retail Goods"
        }
    ],
    "sg:postcode":"DT1 1TZ",
    "sg:province":"Dorset",
    "sg:tags":[
        "medicine",
        "therapy"
    ],
    "wof:name":"Beltain Consultancy",
    "wof:placetype":"venue"
},
  "geometry": {"coordinates":[-2.4415640831,50.7119064331],"type":"Point"}
}