{
  "type": "Feature",
  "properties": {
    "addr:full":"8 Springfield Terrace Port Talbot Neath Port Talbot SA12 8HN",
    "addr:housenumber":"8",
    "addr:postcode":"sa12 8hn",
    "addr:street":"Springfield Terrace",
    "iso:country":"GB",
    "sg:address":"8 Springfield Terrace",
    "sg:city":"Port Talbot",
    "sg:classifiers":[
        {
            "category":"Professional",
            "subcategory":"Accounting & Tax Preparation",
            "type":"Services"
        }
    ],
    "sg:phone":"+44 1639 899330",
    "sg:postcode":"SA12 8HN",
    "sg:province":"Neath Port Talbot",
    "sg:tags":[
        "accountant"
    ],
    "wof:name":"M.M McCarthy Business Accounting",
    "wof:placetype":"venue"
},
  "geometry": {"coordinates":[-3.786997,51.599323],"type":"Point"}
}