{
  "type": "Feature",
  "properties": {
    "iso:country":"GB",
    "sg:address":"Bury Road, Beyton",
    "sg:city":"Bury St Edmunds",
    "sg:classifiers":[
        {
            "category":"Bars & Pubs",
            "type":"Food & Drink"
        }
    ],
    "sg:phone":"+44 1359 270324",
    "sg:postcode":"IP30 9AB",
    "sg:province":"Suffolk",
    "sg:tags":[
        "pubs",
        "inn"
    ],
    "wof:name":"The White Horse",
    "wof:placetype":"venue"
},
  "geometry": {"coordinates":[0.82874,52.233841],"type":"Point"}
}