{
  "type": "Feature",
  "properties": {
    "addr:full":"Flotterton Hall, Flotterton Morpeth Northumberland NE65 7LF",
    "addr:postcode":"ne65 7lf",
    "addr:street":"Northumberland",
    "iso:country":"GB",
    "sg:address":"Flotterton Hall, Flotterton",
    "sg:city":"Morpeth",
    "sg:classifiers":[
        {
            "category":"Farming",
            "subcategory":"Livestock Farm",
            "type":"Manufacturing & Wholesale Goods"
        }
    ],
    "sg:phone":"+44 1669 640253",
    "sg:postcode":"NE65 7LF",
    "sg:province":"Northumberland",
    "sg:tags":[
        "others"
    ],
    "wof:name":"F & J Walton",
    "wof:placetype":"venue"
},
  "geometry": {"coordinates":[-2.003101,55.316422],"type":"Point"}
}