{
  "type": "Feature",
  "properties": {
    "addr:full":"245 High Street Waltham Cross Essex EN8 7BE",
    "addr:housenumber":"245",
    "addr:postcode":"en8 7be",
    "addr:street":"High Street",
    "iso:country":"GB",
    "sg:address":"245 High Street",
    "sg:city":"Waltham Cross",
    "sg:classifiers":[
        {
            "category":"Fast Food",
            "type":"Food & Drink"
        },
        {
            "category":"Food & Beverages",
            "subcategory":"Meat & Fish",
            "type":"Retail Goods"
        }
    ],
    "sg:phone":"+44 1992 623055",
    "sg:postcode":"EN8 7BE",
    "sg:province":"Essex",
    "sg:tags":[
        "chip",
        "away",
        "take"
    ],
    "wof:name":"Hodsons Quality Fish Bar",
    "wof:placetype":"venue"
},
  "geometry": {"coordinates":[-0.0342429988,51.6911277771],"type":"Point"}
}