{
  "type": "Feature",
  "properties": {
    "addr:full":"Harbour Lodge, Haven Road, Canford Cliffs Poole Dorset BH13 7LZ",
    "addr:postcode":"bh13 7lz",
    "addr:street":"Haven Road",
    "iso:country":"GB",
    "sg:address":"Harbour Lodge, Haven Road, Canford Cliffs",
    "sg:city":"Poole",
    "sg:classifiers":[
        {
            "category":"Health Services",
            "subcategory":"Clinic",
            "type":"Services"
        }
    ],
    "sg:phone":"+44 1202 700940",
    "sg:postcode":"BH13 7LZ",
    "sg:province":"Dorset",
    "sg:tags":[
        "aromatherapy"
    ],
    "wof:name":"Angela Chiu",
    "wof:placetype":"venue"
},
  "geometry": {"coordinates":[-1.9230949879,50.7049713135],"type":"Point"}
}