{
  "type": "Feature",
  "properties": {
    "addr:full":"Ash Church Road, Ash Aldershot Hampshire GU12 6LU",
    "addr:postcode":"gu12 6lu",
    "addr:street":"Church Road",
    "iso:country":"GB",
    "sg:address":"Ash Church Road, Ash",
    "sg:city":"Aldershot",
    "sg:classifiers":[
        {
            "category":"Place Of Worship",
            "type":"Public Place"
        }
    ],
    "sg:phone":"+44 1252 321422",
    "sg:postcode":"GU12 6LU",
    "sg:province":"Hampshire",
    "wof:name":"Holy Angels R C Church",
    "wof:placetype":"venue"
},
  "geometry": {"coordinates":[-0.716757,51.248871],"type":"Point"}
}