{
  "type": "Feature",
  "properties": {
    "iso:country":"GB",
    "sg:address":"19 Edgefield Road",
    "sg:city":"Loanhead",
    "sg:classifiers":[
        {
            "category":"Education",
            "subcategory":"School",
            "type":"Public Place"
        },
        {
            "category":"Government",
            "subcategory":"Office",
            "type":"Public Place"
        }
    ],
    "sg:phone":"+44 131 440 0453",
    "sg:postcode":"EH20 9DX",
    "sg:province":"Midlothian",
    "sg:tags":[
        "local",
        "authority"
    ],
    "wof:name":"St. Margaret's R C Primary School",
    "wof:placetype":"venue"
},
  "geometry": {"coordinates":[-3.151346,55.881584],"type":"Point"}
}