{
  "type": "Feature",
  "properties": {
    "addr:full":"41 North Road Shanklin Isle of Wight PO37 6DE",
    "addr:housenumber":"41",
    "addr:postcode":"po37 6de",
    "addr:street":"North Road",
    "iso:country":"GB",
    "sg:address":"41 North Road",
    "sg:city":"Shanklin",
    "sg:classifiers":[
        {
            "category":"Health Services",
            "subcategory":"Podiatrist",
            "type":"Services"
        }
    ],
    "sg:postcode":"PO37 6DE",
    "sg:province":"Isle of Wight",
    "sg:tags":[
        "podiatrists",
        "chiropodist"
    ],
    "wof:name":"Raymond Webb",
    "wof:placetype":"venue"
},
  "geometry": {"coordinates":[-1.175861,50.631783],"type":"Point"}
}