{
  "type": "Feature",
  "properties": {
    "addr:full":"33 Kingsgate, James Street Dunfermline Fife KY12 8QU",
    "addr:housenumber":"33",
    "addr:postcode":"ky12 8qu",
    "addr:street":"Kingsgate James Street",
    "iso:country":"GB",
    "sg:address":"33 Kingsgate, James Street",
    "sg:city":"Dunfermline",
    "sg:classifiers":[
        {
            "category":"Shopping",
            "subcategory":"Clothing, Apparel, & Fashions",
            "type":"Retail Goods"
        }
    ],
    "sg:phone":"+44 1383 730383",
    "sg:postcode":"KY12 8QU",
    "sg:province":"Fife",
    "sg:tags":[
        "menswear"
    ],
    "wof:name":"Burton Menswear",
    "wof:placetype":"venue"
},
  "geometry": {"coordinates":[-3.4613740444,56.0748443604],"type":"Point"}
}