{
  "type": "Feature",
  "properties": {
    "addr:full":"207 Talbot Road Blackpool Lancashire FY3 7AS",
    "addr:housenumber":"207",
    "addr:postcode":"fy3 7as",
    "addr:street":"Talbot Road",
    "iso:country":"GB",
    "sg:address":"207 Talbot Road",
    "sg:city":"Blackpool",
    "sg:classifiers":[
        {
            "category":"Building & Trades",
            "subcategory":"Construction",
            "type":"Services"
        }
    ],
    "sg:phone":"+44 1253 392481",
    "sg:postcode":"FY3 7AS",
    "sg:province":"Lancashire",
    "sg:tags":[
        "demolition",
        "contractor"
    ],
    "wof:name":"Fylde Demolition Contractors (Felton) Ltd.",
    "wof:placetype":"venue"
},
  "geometry": {"coordinates":[-3.0395650864,53.8258628845],"type":"Point"}
}