{
  "type": "Feature",
  "properties": {
    "addr:full":"72 Coggeshall Rd Braintree Essex CM7 9BY",
    "addr:housenumber":"72",
    "addr:postcode":"cm7 9by",
    "addr:street":"Coggeshall Rd",
    "iso:country":"GB",
    "sg:address":"72 Coggeshall Rd",
    "sg:city":"Braintree",
    "sg:classifiers":[
        {
            "category":"Home & Garden",
            "subcategory":"Hardware",
            "type":"Retail Goods"
        },
        {
            "category":"Shopping",
            "subcategory":"Pharmacy",
            "type":"Retail Goods"
        }
    ],
    "sg:postcode":"CM7 9BY",
    "sg:province":"Essex",
    "sg:tags":[
        "lighting",
        "pharmacist",
        "retailer",
        "chemist"
    ],
    "wof:name":"Borno Chemists Ltd",
    "wof:placetype":"venue"
},
  "geometry": {"coordinates":[0.553749,51.879875],"type":"Point"}
}