{
  "type": "Feature",
  "properties": {
    "iso:country":"GB",
    "sg:address":"Manor Park South",
    "sg:city":"Knutsford",
    "sg:classifiers":[
        {
            "category":"Health Services",
            "subcategory":"Nursing And Care Facility",
            "type":"Services"
        }
    ],
    "sg:phone":"+44 1565 633022",
    "sg:postcode":"WA16 8AQ",
    "sg:province":"Cheshire",
    "sg:tags":[
        "home"
    ],
    "wof:name":"Sharston House",
    "wof:placetype":"venue"
},
  "geometry": {"coordinates":[-2.359333992,53.303314209],"type":"Point"}
}