{
  "type": "Feature",
  "properties": {
    "addr:full":"10 High Street Stone Staffordshire ST15 8AW",
    "addr:housenumber":"10",
    "addr:postcode":"st15 8aw",
    "addr:street":"High Street",
    "iso:country":"GB",
    "sg:address":"10 High Street",
    "sg:city":"Stone",
    "sg:classifiers":[
        {
            "category":"Manufacturing",
            "subcategory":"Metals",
            "type":"Manufacturing & Wholesale Goods"
        },
        {
            "category":"Professional",
            "subcategory":"Engineering",
            "type":"Services"
        }
    ],
    "sg:phone":"+44 1785 814811",
    "sg:postcode":"ST15 8AW",
    "sg:province":"Staffordshire",
    "sg:tags":[
        "steel",
        "fabricator",
        "erectors"
    ],
    "wof:name":"D A D Munro Engineers & Contractors Ltd.",
    "wof:placetype":"venue"
},
  "geometry": {"coordinates":[-2.1460020542,52.901599884],"type":"Point"}
}