{
  "type": "Feature",
  "properties": {
    "addr:full":"33 Barry Avenue Bicester Oxfordshire OX26 2DZ",
    "addr:housenumber":"33",
    "addr:postcode":"ox26 2dz",
    "addr:street":"Barry Avenue",
    "iso:country":"GB",
    "sg:address":"33 Barry Avenue",
    "sg:city":"Bicester",
    "sg:classifiers":[
        {
            "category":"Real Estate",
            "subcategory":"Surveying",
            "type":"Services"
        }
    ],
    "sg:phone":"+44 1869 252815",
    "sg:postcode":"OX26 2DZ",
    "sg:province":"Oxfordshire",
    "sg:tags":[
        "surveyor",
        "quantity"
    ],
    "wof:name":"C R Mullins",
    "wof:placetype":"venue"
},
  "geometry": {"coordinates":[-1.1593580246,51.9049720764],"type":"Point"}
}