{
  "type": "Feature",
  "properties": {
    "iso:country":"GB",
    "sg:address":"Aireyholme Cottage, Aireyholme Lane, Great Ayton",
    "sg:city":"Middlesbrough",
    "sg:classifiers":[
        {
            "category":"Farming",
            "subcategory":"Farm",
            "type":"Manufacturing & Wholesale Goods"
        }
    ],
    "sg:phone":"+44 1642 722248",
    "sg:postcode":"TS9 6HP",
    "sg:province":"North Yorkshire",
    "sg:tags":[
        "mixed",
        "crop"
    ],
    "wof:name":"C H PHALP",
    "wof:placetype":"venue"
},
  "geometry": {"coordinates":[-1.11037,54.491859],"type":"Point"}
}