{
  "type": "Feature",
  "properties": {
    "iso:country":"GB",
    "sg:address":"Orchard House, Orchard Lane",
    "sg:city":"Bristol",
    "sg:classifiers":[
        {
            "category":"Organizations",
            "subcategory":"Non-profit Organization",
            "type":"Services"
        }
    ],
    "sg:phone":"+44 117 922 1556",
    "sg:postcode":"BS1 5DT",
    "sg:province":"City of Bristol",
    "sg:tags":[
        "organisation",
        "voluntary",
        "charity"
    ],
    "wof:name":"Association for Children With Life-Threatening Or Terminal Condition & Their Fam",
    "wof:placetype":"venue"
},
  "geometry": {"coordinates":[-2.599399,51.453815],"type":"Point"}
}