{
  "type": "Feature",
  "properties": {
    "addr:full":"Lower Whitworth Road Ilkeston Derbyshire DE7 4LT",
    "addr:postcode":"de7 4lt",
    "addr:street":"Lower Whitworth Road",
    "iso:country":"GB",
    "sg:address":"Lower Whitworth Road",
    "sg:city":"Ilkeston",
    "sg:classifiers":[
        {
            "category":"Education",
            "subcategory":"School",
            "type":"Public Place"
        }
    ],
    "sg:phone":"+44 115 932 4526",
    "sg:postcode":"DE7 4LT",
    "sg:province":"Derbyshire",
    "sg:tags":[
        "local",
        "authority"
    ],
    "wof:name":"Field House Infant School",
    "wof:placetype":"venue"
},
  "geometry": {"coordinates":[-1.3038970232,52.9625740051],"type":"Point"}
}