{
  "type": "Feature",
  "properties": {
    "addr:full":"7e Wards End Loughborough Leicestershire LE11 3HA",
    "addr:postcode":"le11 3ha",
    "addr:street":"7E",
    "iso:country":"GB",
    "sg:address":"7e Wards End",
    "sg:city":"Loughborough",
    "sg:classifiers":[
        {
            "category":"Military Area",
            "subcategory":"Air Force Base",
            "type":"Public Place"
        }
    ],
    "sg:phone":"+44 1509 217105",
    "sg:postcode":"LE11 3HA",
    "sg:province":"Leicestershire",
    "sg:tags":[
        "plate",
        "number"
    ],
    "wof:name":"Timian Registrations",
    "wof:placetype":"venue"
},
  "geometry": {"coordinates":[-1.2078859806,52.7691497803],"type":"Point"}
}