{
  "type": "Feature",
  "properties": {
    "iso:country":"GB",
    "sg:address":"14 Regent Avenue",
    "sg:city":"Macclesfield",
    "sg:classifiers":[
        {
            "category":"Building & Trades",
            "subcategory":"Construction",
            "type":"Services"
        }
    ],
    "sg:phone":"+44 1625 420434",
    "sg:postcode":"SK11 8JP",
    "sg:province":"Cheshire",
    "sg:tags":[
        "roofing"
    ],
    "wof:name":"Priory Roofing",
    "wof:placetype":"venue"
},
  "geometry": {"coordinates":[-2.1385900974,53.2531814575],"type":"Point"}
}