{
  "type": "Feature",
  "properties": {
    "addr:full":"21 Bishopthorpe Road York North Yorkshire YO23 1NA",
    "addr:housenumber":"21",
    "addr:postcode":"yo23 1na",
    "addr:street":"Bishopthorpe Road",
    "iso:country":"GB",
    "sg:address":"21 Bishopthorpe Road",
    "sg:city":"York",
    "sg:classifiers":[
        {
            "category":"Restaurant",
            "type":"Food & Drink"
        }
    ],
    "sg:phone":"+44 1904 628886",
    "sg:postcode":"YO23 1NA",
    "sg:province":"North Yorkshire",
    "wof:name":"F & W Restaurants Ltd.",
    "wof:placetype":"venue"
},
  "geometry": {"coordinates":[-1.085038,53.951706],"type":"Point"}
}