{
  "type": "Feature",
  "properties": {
    "iso:country":"GB",
    "sg:address":"Pascoe House, 54 Bute Street, Cardiff Bay",
    "sg:city":"Cardiff",
    "sg:classifiers":[
        {
            "category":"Professional",
            "subcategory":"Art Services",
            "type":"Services"
        }
    ],
    "sg:phone":"+44 29 2047 0070",
    "sg:postcode":"CF10 5AF",
    "sg:province":"Cardiff",
    "sg:tags":[
        "graphic",
        "designer"
    ],
    "wof:name":"Eclipse (Creative) Ltd.",
    "wof:placetype":"venue"
},
  "geometry": {"coordinates":[-3.165984,51.466164],"type":"Point"}
}