{
  "type": "Feature",
  "properties": {
    "iso:country":"GB",
    "sg:address":"Over Hacking Farm, Stonyhurst",
    "sg:city":"Clitheroe",
    "sg:classifiers":[
        {
            "category":"Farming",
            "subcategory":"Livestock Farm",
            "type":"Manufacturing & Wholesale Goods"
        }
    ],
    "sg:phone":"+44 1254 826258",
    "sg:postcode":"BB7 9PY",
    "sg:province":"Lancashire",
    "sg:tags":[
        "others"
    ],
    "wof:name":"J S Collinge",
    "wof:placetype":"venue"
},
  "geometry": {"coordinates":[-2.4654579163,53.848739624],"type":"Point"}
}