{
  "type": "Feature",
  "properties": {
    "addr:full":"42 Westbourne Gro London Greater London W2 5SH",
    "addr:housenumber":"42",
    "addr:postcode":"w2 5sh",
    "addr:street":"Westbourne Gro",
    "iso:country":"GB",
    "sg:address":"42 Westbourne Gro",
    "sg:city":"London",
    "sg:classifiers":[
        {
            "category":"Food & Beverages",
            "subcategory":"Specialty",
            "type":"Retail Goods"
        }
    ],
    "sg:postcode":"W2 5SH",
    "sg:province":"Greater London",
    "sg:tags":[
        "organic"
    ],
    "wof:name":"Planet Organic Ltd.",
    "wof:placetype":"venue"
},
  "geometry": {"coordinates":[-0.19176,51.518242],"type":"Point"}
}