{
  "type": "Feature",
  "properties": {
    "iso:country":"GB",
    "sg:address":"Unit 15-16 Two Gates Trading Estate",
    "sg:city":"Tamworth",
    "sg:classifiers":[
        {
            "category":"Manufacturing",
            "subcategory":"Petroleum Products",
            "type":"Manufacturing & Wholesale Goods"
        }
    ],
    "sg:phone":"+44 1827 283211",
    "sg:postcode":"B77 5AE",
    "sg:province":"Staffordshire",
    "sg:tags":[
        "lubricant"
    ],
    "wof:name":"Rods Oils (Tamworth) Ltd.",
    "wof:placetype":"venue"
},
  "geometry": {"coordinates":[-1.678599,52.610241],"type":"Point"}
}