{
  "type": "Feature",
  "properties": {
    "iso:country":"GB",
    "sg:address":"Melchester, Wavering Lane",
    "sg:city":"Gillingham",
    "sg:classifiers":[
        {
            "category":"Building & Trades",
            "subcategory":"Construction",
            "type":"Services"
        }
    ],
    "sg:phone":"+44 1747 823403",
    "sg:postcode":"SP8 4NR",
    "sg:province":"Dorset",
    "sg:tags":[
        "roofing"
    ],
    "wof:name":"S J Gray",
    "wof:placetype":"venue"
},
  "geometry": {"coordinates":[-2.27862,51.038097],"type":"Point"}
}