{
  "type": "Feature",
  "properties": {
    "iso:country":"GB",
    "sg:address":"72 Littledown Av",
    "sg:city":"Bournemouth",
    "sg:classifiers":[
        {
            "category":"Building & Trades",
            "subcategory":"Plumbing",
            "type":"Services"
        }
    ],
    "sg:phone":"+44 1202 396897",
    "sg:postcode":"BH7 7AS",
    "sg:province":"Dorset",
    "sg:tags":[
        "heating"
    ],
    "wof:name":"Stearns K",
    "wof:placetype":"venue"
},
  "geometry": {"coordinates":[-1.833208,50.738098],"type":"Point"}
}