{
  "type": "Feature",
  "properties": {
    "addr:full":"Furze Farm, Morwenstow Bude Cornwall EX23 9SL",
    "addr:postcode":"ex23 9sl",
    "addr:street":"Furze",
    "iso:country":"GB",
    "sg:address":"Furze Farm, Morwenstow",
    "sg:city":"Bude",
    "sg:classifiers":[
        {
            "category":"Farming",
            "subcategory":"Dairy Farm",
            "type":"Manufacturing & Wholesale Goods"
        }
    ],
    "sg:postcode":"EX23 9SL",
    "sg:province":"Cornwall",
    "wof:name":"W B & W J Wickett",
    "wof:placetype":"venue"
},
  "geometry": {"coordinates":[-4.553809,50.908798],"type":"Point"}
}