{
  "type": "Feature",
  "properties": {
    "addr:full":"26 Corn St Witney Oxfordshire OX28 6BL",
    "addr:housenumber":"26",
    "addr:postcode":"ox28 6bl",
    "addr:street":"Corn St",
    "iso:country":"GB",
    "sg:address":"26 Corn St",
    "sg:city":"Witney",
    "sg:classifiers":[
        {
            "category":"Banks & Credit Unions",
            "subcategory":"Bank",
            "type":"Services"
        }
    ],
    "sg:postcode":"OX28 6BL",
    "sg:province":"Oxfordshire",
    "sg:tags":[
        "broker",
        "mortgage"
    ],
    "wof:name":"Select Independent Mortgage Services Ltd",
    "wof:placetype":"venue"
},
  "geometry": {"coordinates":[-1.486929,51.783817],"type":"Point"}
}