{
  "type": "Feature",
  "properties": {
    "addr:full":"7 Streatham Vale London Greater London SW16 5SE",
    "addr:housenumber":"7",
    "addr:postcode":"sw16 5se",
    "addr:street":"Streatham Vale",
    "iso:country":"GB",
    "sg:address":"7 Streatham Vale",
    "sg:city":"London",
    "sg:classifiers":[
        {
            "category":"Shopping",
            "subcategory":"Used Merchandise",
            "type":"Retail Goods"
        }
    ],
    "sg:phone":"+44 20 8764 3197",
    "sg:postcode":"SW16 5SE",
    "sg:province":"Greater London",
    "sg:tags":[
        "shop",
        "second-hand"
    ],
    "wof:name":"The Wardrobe",
    "wof:placetype":"venue"
},
  "geometry": {"coordinates":[-0.1361140013,51.4176101685],"type":"Point"}
}