{
  "type": "Feature",
  "properties": {
    "iso:country":"GB",
    "sg:address":"Hams Road",
    "sg:city":"Lydney",
    "sg:classifiers":[
        {
            "category":"Fast Food",
            "type":"Food & Drink"
        }
    ],
    "sg:phone":"+44 1594 842117",
    "sg:postcode":"GL15 5PE",
    "sg:province":"Gloucestershire",
    "sg:tags":[
        "away",
        "take"
    ],
    "wof:name":"The Flamingo Cafe",
    "wof:placetype":"venue"
},
  "geometry": {"coordinates":[-2.527032,51.726696],"type":"Point"}
}