{
  "type": "Feature",
  "properties": {
    "addr:full":"65 North Lane, East Preston Littlehampton West Sussex BN16 1HN",
    "addr:housenumber":"65",
    "addr:postcode":"bn16 1hn",
    "addr:street":"North Lane",
    "iso:country":"GB",
    "sg:address":"65 North Lane, East Preston",
    "sg:city":"Littlehampton",
    "sg:classifiers":[
        {
            "category":"Professional",
            "subcategory":"Art Services",
            "type":"Services"
        }
    ],
    "sg:postcode":"BN16 1HN",
    "sg:province":"West Sussex",
    "sg:tags":[
        "picture",
        "restoration",
        "cleaning"
    ],
    "wof:name":"Adrienne Cordell",
    "wof:placetype":"venue"
},
  "geometry": {"coordinates":[-0.4746609926,50.8126945496],"type":"Point"}
}