{
  "type": "Feature",
  "properties": {
    "iso:country":"GB",
    "sg:address":"5 Lyme Road, Meir",
    "sg:city":"Stoke-on-trent",
    "sg:classifiers":[
        {
            "category":"Professional",
            "subcategory":"Detective & Security Services",
            "type":"Services"
        }
    ],
    "sg:postcode":"ST3 6DY",
    "sg:province":"Staffordshire",
    "wof:name":"Roderick Brewerton",
    "wof:placetype":"venue"
},
  "geometry": {"coordinates":[-2.095399,52.977993],"type":"Point"}
}