{
  "type": "Feature",
  "properties": {
    "addr:full":"72 Comrie Crescent Hamilton South Lanarkshire ML3 9PZ",
    "addr:housenumber":"72",
    "addr:postcode":"ml3 9pz",
    "addr:street":"Comrie Crescent",
    "iso:country":"GB",
    "sg:address":"72 Comrie Crescent",
    "sg:city":"Hamilton",
    "sg:classifiers":[
        {
            "category":"Personal",
            "subcategory":"Psychics & Astrologers",
            "type":"Services"
        }
    ],
    "sg:phone":"+44 1698 820977",
    "sg:postcode":"ML3 9PZ",
    "sg:province":"South Lanarkshire",
    "sg:tags":[
        "clairvoyant",
        "palmist"
    ],
    "wof:name":"Joan Frances",
    "wof:placetype":"venue"
},
  "geometry": {"coordinates":[-4.089519,55.774189],"type":"Point"}
}