{
  "type": "Feature",
  "properties": {
    "addr:full":"4 Willowbrae Road Edinburgh City of Edinburgh EH8 7DB",
    "addr:housenumber":"4",
    "addr:postcode":"eh8 7db",
    "addr:street":"Willowbrae Road",
    "iso:country":"GB",
    "sg:address":"4 Willowbrae Road",
    "sg:city":"Edinburgh",
    "sg:classifiers":[
        {
            "category":"Wholesale",
            "subcategory":"Fruits & Vegetables",
            "type":"Manufacturing & Wholesale Goods"
        }
    ],
    "sg:phone":"+44 131 620 7026",
    "sg:postcode":"EH8 7DB",
    "sg:province":"City of Edinburgh",
    "wof:name":"Multi Fresh",
    "wof:placetype":"venue"
},
  "geometry": {"coordinates":[-3.1492118835,55.9547462463],"type":"Point"}
}