{
  "type": "Feature",
  "properties": {
    "iso:country":"GB",
    "sg:address":"7 Fawkon Walk",
    "sg:city":"Hoddesdon",
    "sg:classifiers":[
        {
            "category":"Health Services",
            "subcategory":"Optometrist",
            "type":"Services"
        }
    ],
    "sg:phone":"+44 1992 469393",
    "sg:postcode":"EN11 8TJ",
    "sg:province":"Essex",
    "sg:tags":[
        "optician"
    ],
    "wof:name":"Scrivens Optications",
    "wof:placetype":"venue"
},
  "geometry": {"coordinates":[-0.013255,51.767841],"type":"Point"}
}