{
  "type": "Feature",
  "properties": {
    "addr:full":"Ramillies, 12 Victoria Road South Southsea Hampshire PO5 2BZ",
    "addr:housenumber":"12",
    "addr:postcode":"po5 2bz",
    "addr:street":"Ramillies;Victoria Road South",
    "iso:country":"GB",
    "sg:address":"Ramillies, 12 Victoria Road South",
    "sg:city":"Southsea",
    "sg:classifiers":[
        {
            "category":"Health Services",
            "subcategory":"Doctor",
            "type":"Services"
        }
    ],
    "sg:phone":"+44 23 9282 3857",
    "sg:postcode":"PO5 2BZ",
    "sg:province":"Hampshire",
    "sg:tags":[
        "practitioners"
    ],
    "wof:name":"Caiger, M",
    "wof:placetype":"venue"
},
  "geometry": {"coordinates":[-1.0881639719,50.7846641541],"type":"Point"}
}