{
  "type": "Feature",
  "properties": {
    "iso:country":"GB",
    "sg:address":"123 Exeter Street",
    "sg:city":"Salisbury",
    "sg:classifiers":[
        {
            "category":"Retail",
            "subcategory":"Veterinary Services",
            "type":"Services"
        }
    ],
    "sg:phone":"+44 1722 337117",
    "sg:postcode":"SP1 2SG",
    "sg:province":"Wiltshire",
    "sg:tags":[
        "surgeon"
    ],
    "wof:name":"The Vets",
    "wof:placetype":"venue"
},
  "geometry": {"coordinates":[-1.794106,51.063065],"type":"Point"}
}