{
  "type": "Feature",
  "properties": {
    "iso:country":"GB",
    "sg:address":"145 High St",
    "sg:city":"Oldbury",
    "sg:classifiers":[
        {
            "category":"Farming",
            "subcategory":"Fish & Marine Products",
            "type":"Manufacturing & Wholesale Goods"
        }
    ],
    "sg:postcode":"B65 0EA",
    "sg:province":"West Midlands",
    "sg:tags":[
        "fishmonger"
    ],
    "wof:name":"Adams,Mary,",
    "wof:placetype":"venue"
},
  "geometry": {"coordinates":[-2.042677,52.475796],"type":"Point"}
}