{
  "type": "Feature",
  "properties": {
    "addr:full":"2111 Coventry Rd Birmingham West Midlands B26 3EA",
    "addr:housenumber":"2111",
    "addr:postcode":"b26 3ea",
    "addr:street":"Coventry Rd",
    "iso:country":"GB",
    "sg:address":"2111 Coventry Rd",
    "sg:city":"Birmingham",
    "sg:classifiers":[
        {
            "category":"Wholesale",
            "subcategory":"Medical Equipment & Supplies",
            "type":"Manufacturing & Wholesale Goods"
        }
    ],
    "sg:phone":"+44 121 742 2444",
    "sg:postcode":"B26 3EA",
    "sg:province":"West Midlands",
    "sg:tags":[
        "hospital"
    ],
    "wof:name":"Nycomed (UK) Ltd",
    "wof:placetype":"venue"
},
  "geometry": {"coordinates":[-1.788007021,52.4529876709],"type":"Point"}
}