{
  "type": "Feature",
  "properties": {
    "iso:country":"GB",
    "sg:address":"13 Princess Drive, Highwoods",
    "sg:city":"Colchester",
    "sg:classifiers":[
        {
            "category":"Manufacturing",
            "subcategory":"Signs",
            "type":"Manufacturing & Wholesale Goods"
        }
    ],
    "sg:postcode":"CO4 9YT",
    "sg:province":"Essex",
    "sg:tags":[
        "writer"
    ],
    "wof:name":"Chris Benham Signwriting",
    "wof:placetype":"venue"
},
  "geometry": {"coordinates":[0.926045,51.914223],"type":"Point"}
}