{
  "type": "Feature",
  "properties": {
    "iso:country":"GB",
    "sg:address":"3 Charlston Court",
    "sg:city":"Inverness",
    "sg:classifiers":[
        {
            "category":"Personal",
            "subcategory":"Beauty Salon",
            "type":"Services"
        }
    ],
    "sg:phone":"+44 1463 241040",
    "sg:postcode":"IV3 6PB",
    "sg:province":"Highland",
    "sg:tags":[
        "lady",
        "hairdresser"
    ],
    "wof:name":"Hairwaves Salon",
    "wof:placetype":"venue"
},
  "geometry": {"coordinates":[-4.2356119156,57.4790153503],"type":"Point"}
}