{
  "type": "Feature",
  "properties": {
    "addr:full":"Coronation Rd, Cossall Industrial Estate Ilkeston Derbyshire DE7 5UB",
    "addr:postcode":"de7 5ub",
    "addr:street":"Coronation Rd;Industrial Estate",
    "iso:country":"GB",
    "sg:address":"Coronation Rd, Cossall Industrial Estate",
    "sg:city":"Ilkeston",
    "sg:classifiers":[
        {
            "category":"Wholesale",
            "subcategory":"Machinery & Supplies",
            "type":"Manufacturing & Wholesale Goods"
        }
    ],
    "sg:phone":"+44 115 932 8781",
    "sg:postcode":"DE7 5UB",
    "sg:province":"Derbyshire",
    "sg:tags":[
        "equipment",
        "handling",
        "lifting"
    ],
    "wof:name":"Lansing Linde Jewsbury's Ltd",
    "wof:placetype":"venue"
},
  "geometry": {"coordinates":[-1.3087199926,52.9697761536],"type":"Point"}
}