{
  "type": "Feature",
  "properties": {
    "iso:country":"GB",
    "sg:address":"80 Trent Road, Shaw",
    "sg:city":"Oldham",
    "sg:classifiers":[
        {
            "category":"Building & Trades",
            "subcategory":"Cleaning & Sanitation",
            "type":"Services"
        },
        {
            "category":"Home & Garden",
            "subcategory":"Carpets & Floor Coverings",
            "type":"Retail Goods"
        }
    ],
    "sg:phone":"+44 1706 841435",
    "sg:postcode":"OL2 7YL",
    "sg:province":"Lancashire",
    "sg:tags":[
        "cleaner",
        "upholstery"
    ],
    "wof:name":"Gray's Carpets & Blinds",
    "wof:placetype":"venue"
},
  "geometry": {"coordinates":[-2.101399,53.586178],"type":"Point"}
}