{
  "type": "Feature",
  "properties": {
    "addr:full":"Unit 14 Campbell Court, Campbell Road, Bramley Basingstoke Berkshire RG26 5EG",
    "addr:housenumber":"unit 14",
    "addr:postcode":"rg26 5eg",
    "addr:street":"Campbell Court Campbell Road",
    "iso:country":"GB",
    "sg:address":"Unit 14 Campbell Court, Campbell Road, Bramley",
    "sg:city":"Basingstoke",
    "sg:classifiers":[
        {
            "category":"Shopping",
            "subcategory":"Computers & Home Electronics",
            "type":"Retail Goods"
        },
        {
            "category":"Building & Trades",
            "subcategory":"Electrical",
            "type":"Services"
        }
    ],
    "sg:phone":"+44 870 774 9944",
    "sg:postcode":"RG26 5EG",
    "sg:province":"Berkshire",
    "sg:tags":[
        "equipment",
        "cctv",
        "video",
        "electrician",
        "contractor"
    ],
    "wof:name":"Videor Technical E Hartig Gmbh",
    "wof:placetype":"venue"
},
  "geometry": {"coordinates":[-1.0454479456,51.3245544434],"type":"Point"}
}