{
  "type": "Feature",
  "properties": {
    "iso:country":"GB",
    "sg:address":"6 Gloucester Street",
    "sg:city":"Bristol",
    "sg:classifiers":[
        {
            "category":"Banks & Credit Unions",
            "subcategory":"Financial Services",
            "type":"Services"
        }
    ],
    "sg:phone":"+44 117 951 2187",
    "sg:postcode":"BS5 6QE",
    "sg:province":"City of Bristol",
    "sg:tags":[
        "consultant"
    ],
    "wof:name":"Western Alcohol & Drugs Education Society",
    "wof:placetype":"venue"
},
  "geometry": {"coordinates":[-2.556072,51.47377],"type":"Point"}
}