{
  "type": "Feature",
  "properties": {
    "addr:full":"10 Bakers Yd, Bakers Row London Greater London EC1R 3DD",
    "addr:housenumber":"10",
    "addr:postcode":"ec1r 3dd",
    "addr:street":"Bakers Yd Bakers Row",
    "iso:country":"GB",
    "sg:address":"10 Bakers Yd, Bakers Row",
    "sg:city":"London",
    "sg:classifiers":[
        {
            "category":"Communications",
            "type":"Services"
        }
    ],
    "sg:phone":"+44 20 7278 2300",
    "sg:postcode":"EC1R 3DD",
    "sg:province":"Greater London",
    "sg:tags":[
        "audio-visual"
    ],
    "wof:name":"Clicks Group Ltd",
    "wof:placetype":"venue"
},
  "geometry": {"coordinates":[-0.110076,51.523399],"type":"Point"}
}