{
  "type": "Feature",
  "properties": {
    "iso:country":"GB",
    "sg:address":"Eco Factory, Off Valley Way, Llansamlet",
    "sg:city":"Swansea",
    "sg:classifiers":[
        {
            "category":"Shopping",
            "subcategory":"Beauty & Cosmetics",
            "type":"Retail Goods"
        }
    ],
    "sg:phone":"+44 1792 310306",
    "sg:postcode":"SA6 8QP",
    "sg:province":"Swansea",
    "sg:tags":[
        "product"
    ],
    "wof:name":"Montague Jeunesse",
    "wof:placetype":"venue"
},
  "geometry": {"coordinates":[-3.9128000736,51.6592216492],"type":"Point"}
}