{
  "type": "Feature",
  "properties": {
    "iso:country":"GB",
    "sg:address":"Sherwell House, 30 North Hill",
    "sg:city":"Plymouth",
    "sg:classifiers":[
        {
            "category":"Real Estate",
            "subcategory":"Real Estate Agent",
            "type":"Services"
        }
    ],
    "sg:phone":"+44 1752 670700",
    "sg:postcode":"PL4 8ET",
    "sg:province":"Devon",
    "wof:name":"Stratton Creber Commercial",
    "wof:placetype":"venue"
},
  "geometry": {"coordinates":[-4.136296,50.376614],"type":"Point"}
}