{
  "type": "Feature",
  "properties": {
    "addr:full":"24 Honeypot La Colindale Greater London NW9 9QL",
    "addr:housenumber":"24",
    "addr:postcode":"nw9 9ql",
    "addr:street":"Honeypot La Colindale",
    "iso:country":"GB",
    "sg:address":"24 Honeypot La",
    "sg:city":"Colindale",
    "sg:classifiers":[
        {
            "category":"Health Services",
            "subcategory":"Doctor",
            "type":"Services"
        }
    ],
    "sg:phone":"+44 20 8204 9644",
    "sg:postcode":"NW9 9QL",
    "sg:province":"Greater London",
    "sg:tags":[
        "practitioners"
    ],
    "wof:name":"Baruah, M",
    "wof:placetype":"venue"
},
  "geometry": {"coordinates":[-0.2822349966,51.5859832764],"type":"Point"}
}