{
  "type": "Feature",
  "properties": {
    "addr:full":"16 School Lane Luton Bedfordshire LU4 9QS",
    "addr:housenumber":"16",
    "addr:postcode":"lu4 9qs",
    "addr:street":"School Lane",
    "iso:country":"GB",
    "sg:address":"16 School Lane",
    "sg:city":"Luton",
    "sg:classifiers":[
        {
            "category":"Building & Trades",
            "subcategory":"Construction",
            "type":"Services"
        }
    ],
    "sg:phone":"+44 1582 565986",
    "sg:postcode":"LU4 9QS",
    "sg:province":"Bedfordshire",
    "sg:tags":[
        "decorator",
        "painter"
    ],
    "wof:name":"Re-dec",
    "wof:placetype":"venue"
},
  "geometry": {"coordinates":[-0.463339,51.901829],"type":"Point"}
}