{
  "type": "Feature",
  "properties": {
    "iso:country":"GB",
    "sg:address":"2 Spa Road",
    "sg:city":"Weymouth",
    "sg:classifiers":[
        {
            "category":"Fast Food",
            "type":"Food & Drink"
        }
    ],
    "sg:phone":"+44 1305 775577",
    "sg:postcode":"DT3 5EL",
    "sg:province":"Dorset",
    "sg:tags":[
        "away",
        "meal",
        "outlet",
        "take"
    ],
    "wof:name":"Golden Bridge",
    "wof:placetype":"venue"
},
  "geometry": {"coordinates":[-2.461425066,50.6294593811],"type":"Point"}
}