{
  "type": "Feature",
  "properties": {
    "iso:country":"GB",
    "sg:address":"46 Redlands Road",
    "sg:city":"Reading",
    "sg:classifiers":[
        {
            "category":"Travel",
            "subcategory":"Hotels & Motels",
            "type":"Entertainment"
        }
    ],
    "sg:phone":"+44 118 986 3792",
    "sg:postcode":"RG1 5HE",
    "sg:province":"Berkshire",
    "sg:tags":[
        "house",
        "guest"
    ],
    "wof:name":"Abadair House",
    "wof:placetype":"venue"
},
  "geometry": {"coordinates":[-0.9573330283,51.4457778931],"type":"Point"}
}