{
  "type": "Feature",
  "properties": {
    "addr:full":"Unit 4 Pioneer Garage, Regent Street Rochdale Lancashire OL12 0HQ",
    "addr:housenumber":"unit 4",
    "addr:postcode":"ol12 0hq",
    "addr:street":"Regent Street",
    "iso:country":"GB",
    "sg:address":"Unit 4 Pioneer Garage, Regent Street",
    "sg:city":"Rochdale",
    "sg:classifiers":[
        {
            "category":"Retail",
            "subcategory":"Auto Repair",
            "type":"Services"
        }
    ],
    "sg:phone":"+44 1706 861039",
    "sg:postcode":"OL12 0HQ",
    "sg:province":"Lancashire",
    "sg:tags":[
        "modification",
        "garage"
    ],
    "wof:name":"Supreme Motor Repairs",
    "wof:placetype":"venue"
},
  "geometry": {"coordinates":[-2.1627659798,53.6190071106],"type":"Point"}
}