{
  "type": "Feature",
  "properties": {
    "addr:full":"The Ark Business Centre, Gordon Road Loughborough Leicestershire LE11 1JP",
    "addr:postcode":"le11 1jp",
    "addr:street":"Gordon Road",
    "iso:country":"GB",
    "sg:address":"The Ark Business Centre, Gordon Road",
    "sg:city":"Loughborough",
    "sg:classifiers":[
        {
            "category":"Communications",
            "subcategory":"Newspaper",
            "type":"Services"
        }
    ],
    "sg:phone":"+44 1509 610060",
    "sg:postcode":"LE11 1JP",
    "sg:province":"Leicestershire",
    "sg:tags":[
        "magazine"
    ],
    "wof:name":"Leicester Mercury Group Ltd.",
    "wof:placetype":"venue"
},
  "geometry": {"coordinates":[-1.2234740257,52.7685241699],"type":"Point"}
}