{
  "type": "Feature",
  "properties": {
    "addr:full":"Kitts Merries Farm, The Frenches, East Wellow Romsey Hampshire SO51 6FE",
    "addr:housenumber":"the",
    "addr:postcode":"so51 6fe",
    "addr:street":"East",
    "iso:country":"GB",
    "sg:address":"Kitts Merries Farm, The Frenches, East Wellow",
    "sg:city":"Romsey",
    "sg:classifiers":[
        {
            "category":"Farming",
            "subcategory":"Farm",
            "type":"Manufacturing & Wholesale Goods"
        }
    ],
    "sg:phone":"+44 1794 513242",
    "sg:postcode":"SO51 6FE",
    "sg:province":"Hampshire",
    "sg:tags":[
        "egg",
        "producer"
    ],
    "wof:name":"A J Clayton",
    "wof:placetype":"venue"
},
  "geometry": {"coordinates":[-1.567429,50.981266],"type":"Point"}
}