{
  "type": "Feature",
  "properties": {
    "addr:full":"138-140 Leek Road, Endon Stoke-on-trent Staffordshire ST9 9EW",
    "addr:housenumber":"138-140",
    "addr:postcode":"st9 9ew",
    "addr:street":"Leek Road",
    "iso:country":"GB",
    "sg:address":"138-140 Leek Road, Endon",
    "sg:city":"Stoke-on-trent",
    "sg:classifiers":[
        {
            "category":"Retail",
            "subcategory":"Auto Rental",
            "type":"Services"
        }
    ],
    "sg:phone":"+44 1782 504892",
    "sg:postcode":"ST9 9EW",
    "sg:province":"Staffordshire",
    "sg:tags":[
        "car"
    ],
    "wof:name":"Economy Drive",
    "wof:placetype":"venue"
},
  "geometry": {"coordinates":[-2.11724,53.07048],"type":"Point"}
}