{
  "type": "Feature",
  "properties": {
    "addr:full":"Unit 8 St Mark's Works, Foundry Lane Leicester Leicestershire LE1 3WU",
    "addr:housenumber":"unit 8",
    "addr:postcode":"le1 3wu",
    "addr:street":"St;Foundry Lane",
    "iso:country":"GB",
    "sg:address":"Unit 8 St Mark's Works, Foundry Lane",
    "sg:city":"Leicester",
    "sg:classifiers":[
        {
            "category":"Professional",
            "subcategory":"Printing & Photocopies",
            "type":"Services"
        }
    ],
    "sg:phone":"+44 116 262 5800",
    "sg:postcode":"LE1 3WU",
    "sg:province":"Leicestershire",
    "sg:tags":[
        "process",
        "screen",
        "printer"
    ],
    "wof:name":"The Blade Graphics Ltd.",
    "wof:placetype":"venue"
},
  "geometry": {"coordinates":[-1.12939,52.643459],"type":"Point"}
}