{
  "type": "Feature",
  "properties": {
    "iso:country":"GB",
    "sg:address":"18 Bardsley Road, Elstree Industrial Estate",
    "sg:city":"Corby",
    "sg:classifiers":[
        {
            "category":"Military Area",
            "subcategory":"Air Force Base",
            "type":"Public Place"
        }
    ],
    "sg:phone":"+44 1536 202919",
    "sg:postcode":"NN17 4AR",
    "sg:province":"Northamptonshire",
    "sg:tags":[
        "taxi",
        "hire",
        "private"
    ],
    "wof:name":"A T O Taxis",
    "wof:placetype":"venue"
},
  "geometry": {"coordinates":[-0.703422,52.510387],"type":"Point"}
}