{
  "type": "Feature",
  "properties": {
    "addr:full":"11 Bell Alley Leighton Buzzard Bedfordshire LU7 1DG",
    "addr:housenumber":"11",
    "addr:postcode":"lu7 1dg",
    "addr:street":"Bell Alley",
    "iso:country":"GB",
    "sg:address":"11 Bell Alley",
    "sg:city":"Leighton Buzzard",
    "sg:classifiers":[
        {
            "category":"Personal",
            "subcategory":"Barber",
            "type":"Services"
        }
    ],
    "sg:phone":"+44 1525 850353",
    "sg:postcode":"LU7 1DG",
    "sg:province":"Bedfordshire",
    "sg:tags":[
        "men's",
        "gents",
        "hairdresser"
    ],
    "wof:name":"Snips",
    "wof:placetype":"venue"
},
  "geometry": {"coordinates":[-0.660904,51.916294],"type":"Point"}
}