{
  "type": "Feature",
  "properties": {
    "addr:full":"7a Coombe Road New Malden Surrey KT3 4PX",
    "addr:housenumber":"7a",
    "addr:postcode":"kt3 4px",
    "addr:street":"Coombe Road",
    "iso:country":"GB",
    "sg:address":"7a Coombe Road",
    "sg:city":"New Malden",
    "sg:classifiers":[
        {
            "category":"Real Estate",
            "subcategory":"Real Estate Services",
            "type":"Services"
        },
        {
            "category":"Real Estate",
            "subcategory":"Real Estate Agent",
            "type":"Services"
        }
    ],
    "sg:phone":"+44 20 8336 1566",
    "sg:postcode":"KT3 4PX",
    "sg:province":"Surrey",
    "sg:tags":[
        "management"
    ],
    "sg:website":"http://www.jins.co.uk",
    "wof:name":"Jin's Lettings Agency",
    "wof:placetype":"venue"
},
  "geometry": {"coordinates":[-0.2567679882,51.4041481018],"type":"Point"}
}