{
  "type": "Feature",
  "properties": {
    "addr:full":"Maltravers Road Sheffield South Yorkshire S2 5AD",
    "addr:postcode":"s2 5ad",
    "addr:street":"Maltravers Road",
    "iso:country":"GB",
    "sg:address":"Maltravers Road",
    "sg:city":"Sheffield",
    "sg:classifiers":[
        {
            "category":"Professional",
            "type":"Services"
        },
        {
            "category":"Professional",
            "subcategory":"Testing Lab",
            "type":"Services"
        }
    ],
    "sg:phone":"+44 114 272 7317",
    "sg:postcode":"S2 5AD",
    "sg:province":"South Yorkshire",
    "sg:tags":[
        "equipment",
        "inspection",
        "calibration"
    ],
    "sg:website":"http://www.ndt.ltd.uk",
    "wof:name":"N D T Ltd.",
    "wof:placetype":"venue"
},
  "geometry": {"coordinates":[-1.445969,53.382484],"type":"Point"}
}