{
  "type": "Feature",
  "properties": {
    "addr:full":"19-21 City Rd Dundee Dundee City DD2 2BL",
    "addr:housenumber":"19-21",
    "addr:postcode":"dd2 2bl",
    "addr:street":"City Rd",
    "iso:country":"GB",
    "sg:address":"19-21 City Rd",
    "sg:city":"Dundee",
    "sg:classifiers":[
        {
            "category":"Shopping",
            "type":"Retail Goods"
        }
    ],
    "sg:phone":"+44 1382 641957",
    "sg:postcode":"DD2 2BL",
    "sg:province":"Dundee City",
    "sg:tags":[
        "part",
        "accessory"
    ],
    "wof:name":"Listers Motor Services",
    "wof:placetype":"venue"
},
  "geometry": {"coordinates":[-2.9975829124,56.4638061523],"type":"Point"}
}