{
  "type": "Feature",
  "properties": {
    "iso:country":"GB",
    "sg:address":"Kirk Street, Markinch",
    "sg:city":"Glenrothes",
    "sg:classifiers":[
        {
            "category":"Bars & Pubs",
            "type":"Food & Drink"
        },
        {
            "category":"Community Center",
            "subcategory":"Social",
            "type":"Public Place"
        }
    ],
    "sg:phone":"+44 1592 612328",
    "sg:postcode":"KY7 6DU",
    "sg:province":"Fife",
    "sg:tags":[
        "pubs",
        "house",
        "inn",
        "activity"
    ],
    "wof:name":"The Galloway Hotel",
    "wof:placetype":"venue"
},
  "geometry": {"coordinates":[-3.134689,56.203732],"type":"Point"}
}