{
  "type": "Feature",
  "properties": {
    "iso:country":"GB",
    "sg:address":"Cedars, Boundary Meany Gate, Hesketh Bank",
    "sg:city":"Preston",
    "sg:classifiers":[
        {
            "category":"Building & Trades",
            "subcategory":"Construction",
            "type":"Services"
        }
    ],
    "sg:phone":"+44 1772 812792",
    "sg:postcode":"PR4 6AL",
    "sg:province":"Lancashire",
    "sg:tags":[
        "builder"
    ],
    "wof:name":"R S Bannister & Son Building Contractors",
    "wof:placetype":"venue"
},
  "geometry": {"coordinates":[-2.838865,53.6991],"type":"Point"}
}