{
  "type": "Feature",
  "properties": {
    "iso:country":"GB",
    "sg:address":"115 Marsh Road",
    "sg:city":"Rhyl",
    "sg:classifiers":[
        {
            "category":"Manufacturing",
            "subcategory":"Tools & Machinery",
            "type":"Manufacturing & Wholesale Goods"
        },
        {
            "category":"Utilities",
            "subcategory":"Natural Gas",
            "type":"Services"
        }
    ],
    "sg:phone":"+44 1745 350700",
    "sg:postcode":"LL18 2AB",
    "sg:province":"Conwy",
    "sg:tags":[
        "manufacture",
        "instrumentation",
        "industrial",
        "weather"
    ],
    "wof:name":"Vector Instruments",
    "wof:placetype":"venue"
},
  "geometry": {"coordinates":[-3.493728,53.314438],"type":"Point"}
}