{
  "type": "Feature",
  "properties": {
    "addr:full":"Unit 1, Riverside Industrial Estate Market Harborough Leicestershire LE16 7PT",
    "addr:housenumber":"unit 1",
    "addr:postcode":"le16 7pt",
    "addr:street":"Riverside Industrial",
    "iso:country":"GB",
    "sg:address":"Unit 1, Riverside Industrial Estate",
    "sg:city":"Market Harborough",
    "sg:classifiers":[
        {
            "category":"Bars & Pubs",
            "subcategory":"Nightclub",
            "type":"Food & Drink"
        }
    ],
    "sg:phone":"+44 1858 462643",
    "sg:postcode":"LE16 7PT",
    "sg:province":"Leicestershire",
    "sg:tags":[
        "club",
        "night"
    ],
    "wof:name":"Broadway Night Club Ltd.",
    "wof:placetype":"venue"
},
  "geometry": {"coordinates":[-0.903598,52.484043],"type":"Point"}
}