{
  "type": "Feature",
  "properties": {
    "addr:full":"Red Lion Quarry, Frome Road Bath Somerset BA2 2PP",
    "addr:postcode":"ba2 2pp",
    "addr:street":"Quarry Frome Road",
    "iso:country":"GB",
    "sg:address":"Red Lion Quarry, Frome Road",
    "sg:city":"Bath",
    "sg:classifiers":[
        {
            "category":"Retail",
            "subcategory":"Auto Repair",
            "type":"Services"
        }
    ],
    "sg:phone":"+44 1225 833582",
    "sg:postcode":"BA2 2PP",
    "sg:province":"Somerset",
    "sg:tags":[
        "modification",
        "garage"
    ],
    "wof:name":"Mike Doman",
    "wof:placetype":"venue"
},
  "geometry": {"coordinates":[-2.3773999214,51.3592300415],"type":"Point"}
}