{
  "type": "Feature",
  "properties": {
    "addr:full":"The Triangle, Rochford Way Frinton-on-sea Essex CO13 0AU",
    "addr:postcode":"co13 0au",
    "addr:street":"The Triangle Rochford Way",
    "iso:country":"GB",
    "sg:address":"The Triangle, Rochford Way",
    "sg:city":"Frinton-on-sea",
    "sg:classifiers":[
        {
            "category":"Community Center",
            "type":"Public Place"
        }
    ],
    "sg:phone":"+44 1255 678332",
    "sg:postcode":"CO13 0AU",
    "sg:province":"Essex",
    "sg:tags":[
        "centre"
    ],
    "wof:name":"Frinton Community Centre",
    "wof:placetype":"venue"
},
  "geometry": {"coordinates":[1.2419110537,51.8380317688],"type":"Point"}
}