{
  "type": "Feature",
  "properties": {
    "addr:full":"5 Farm Road Esher Surrey KT10 8AU",
    "addr:housenumber":"5",
    "addr:postcode":"kt10 8au",
    "addr:street":"Farm Road",
    "iso:country":"GB",
    "sg:address":"5 Farm Road",
    "sg:city":"Esher",
    "sg:classifiers":[
        {
            "category":"Professional",
            "type":"Services"
        }
    ],
    "sg:postcode":"KT10 8AU",
    "sg:province":"Surrey",
    "sg:tags":[
        "entertainer"
    ],
    "wof:name":"Klass Entertainment  &  Leisure Ltd",
    "wof:placetype":"venue"
},
  "geometry": {"coordinates":[-0.3703370094,51.380153656],"type":"Point"}
}