{
  "type": "Feature",
  "properties": {
    "iso:country":"GB",
    "sg:address":"4 Gelli Cotts, Cymmer",
    "sg:city":"Port Talbot",
    "sg:classifiers":[
        {
            "category":"Shopping",
            "subcategory":"Clothing, Apparel, & Fashions",
            "type":"Retail Goods"
        }
    ],
    "sg:postcode":"SA13 3NP",
    "sg:province":"Neath Port Talbot",
    "sg:tags":[
        "lingerie"
    ],
    "wof:name":"Jones,Patricia,",
    "wof:placetype":"venue"
},
  "geometry": {"coordinates":[-3.602868,51.653301],"type":"Point"}
}