{
  "type": "Feature",
  "properties": {
    "iso:country":"GB",
    "sg:address":"19 Broadmead Business Park, Broadmead Rd, Stewartby",
    "sg:city":"Bedford",
    "sg:classifiers":[
        {
            "category":"Building & Trades",
            "subcategory":"Construction",
            "type":"Services"
        }
    ],
    "sg:phone":"+44 1234 765004",
    "sg:postcode":"MK43 9NX",
    "sg:province":"Bedfordshire",
    "sg:tags":[
        "window",
        "replacement"
    ],
    "wof:name":"Unique Windows",
    "wof:placetype":"venue"
},
  "geometry": {"coordinates":[-0.506609,52.066891],"type":"Point"}
}