{
  "type": "Feature",
  "properties": {
    "addr:full":"Main Street, Weston On Trent Derby Derbyshire DE72 2BL",
    "addr:postcode":"de72 2bl",
    "addr:street":"Main Street",
    "iso:country":"GB",
    "sg:address":"Main Street, Weston On Trent",
    "sg:city":"Derby",
    "sg:classifiers":[
        {
            "category":"Education",
            "subcategory":"School",
            "type":"Public Place"
        }
    ],
    "sg:phone":"+44 1332 700488",
    "sg:postcode":"DE72 2BL",
    "sg:province":"Derbyshire",
    "sg:tags":[
        "local",
        "authority"
    ],
    "wof:name":"Weston on Trent Primary School",
    "wof:placetype":"venue"
},
  "geometry": {"coordinates":[-1.400304,52.849964],"type":"Point"}
}