{
  "type": "Feature",
  "properties": {
    "addr:full":"397 Harrogate Road Leeds North Yorkshire LS17 6JJ",
    "addr:housenumber":"397",
    "addr:postcode":"ls17 6jj",
    "addr:street":"Harrogate Road",
    "iso:country":"GB",
    "sg:address":"397 Harrogate Road",
    "sg:city":"Leeds",
    "sg:classifiers":[
        {
            "category":"Manufacturing",
            "subcategory":"Wood Products",
            "type":"Manufacturing & Wholesale Goods"
        }
    ],
    "sg:phone":"+44 113 240 5421",
    "sg:postcode":"LS17 6JJ",
    "sg:province":"North Yorkshire",
    "sg:tags":[
        "packaging",
        "crate",
        "pallets"
    ],
    "wof:name":"Barraclough Packaging Services Ltd.",
    "wof:placetype":"venue"
},
  "geometry": {"coordinates":[-1.5348149538,53.8471794128],"type":"Point"}
}