{
  "type": "Feature",
  "properties": {
    "addr:full":"Sherington Road Newport Pagnell Buckinghamshire MK16 8NL",
    "addr:postcode":"mk16 8nl",
    "addr:street":"Sherington Road",
    "iso:country":"GB",
    "sg:address":"Sherington Road",
    "sg:city":"Newport Pagnell",
    "sg:classifiers":[
        {
            "category":"Sports & Exercise",
            "subcategory":"Stables",
            "type":"Entertainment"
        }
    ],
    "sg:phone":"+44 1908 618423",
    "sg:postcode":"MK16 8NL",
    "sg:province":"Buckinghamshire",
    "sg:tags":[
        "equestrian",
        "centre",
        "livery",
        "schools",
        "riding",
        "education"
    ],
    "wof:name":"Riversmeet Stables",
    "wof:placetype":"venue"
},
  "geometry": {"coordinates":[-0.7166470289,52.093536377],"type":"Point"}
}