{
  "type": "Feature",
  "properties": {
    "addr:full":"Little Chart, Balcombe Road Horley Surrey RH6 9ES",
    "addr:housenumber":"chart",
    "addr:postcode":"rh6 9es",
    "addr:street":"Balcombe Road",
    "iso:country":"GB",
    "sg:address":"Little Chart, Balcombe Road",
    "sg:city":"Horley",
    "sg:classifiers":[
        {
            "category":"Retail",
            "subcategory":"Auto Repair",
            "type":"Services"
        }
    ],
    "sg:postcode":"RH6 9ES",
    "sg:province":"Surrey",
    "sg:tags":[
        "modification",
        "garage"
    ],
    "wof:name":"Oakdene Services",
    "wof:placetype":"venue"
},
  "geometry": {"coordinates":[-0.1692889929,51.175365448],"type":"Point"}
}