{
  "type": "Feature",
  "properties": {
    "iso:country":"GB",
    "sg:address":"55a Sotheron Road",
    "sg:city":"Watford",
    "sg:classifiers":[
        {
            "category":"Wholesale",
            "subcategory":"Machinery & Supplies",
            "type":"Manufacturing & Wholesale Goods"
        }
    ],
    "sg:postcode":"WD17 2QB",
    "sg:province":"Hertfordshire",
    "sg:tags":[
        "equipment",
        "pneumatic",
        "system"
    ],
    "wof:name":"Herts-Air",
    "wof:placetype":"venue"
},
  "geometry": {"coordinates":[-0.393954,51.660099],"type":"Point"}
}