{
  "type": "Feature",
  "properties": {
    "addr:full":"19 Cheam Common Road Worcester Park Surrey KT4 8TL",
    "addr:housenumber":"19",
    "addr:postcode":"kt4 8tl",
    "addr:street":"Cheam Common Road",
    "iso:country":"GB",
    "sg:address":"19 Cheam Common Road",
    "sg:city":"Worcester Park",
    "sg:classifiers":[
        {
            "category":"Shopping",
            "subcategory":"Musical Instruments",
            "type":"Retail Goods"
        }
    ],
    "sg:postcode":"KT4 8TL",
    "sg:province":"Surrey",
    "sg:tags":[
        "music",
        "sheet"
    ],
    "wof:name":"Baldreys Music Centre",
    "wof:placetype":"venue"
},
  "geometry": {"coordinates":[-0.2290789932,51.3714523315],"type":"Point"}
}