{
  "type": "Feature",
  "properties": {
    "iso:country":"GB",
    "sg:address":"The Ridgeway",
    "sg:city":"Enfield",
    "sg:classifiers":[
        {
            "category":"Bars & Pubs",
            "type":"Food & Drink"
        }
    ],
    "sg:phone":"+44 20 8363 3781",
    "sg:postcode":"EN2 8AP",
    "sg:province":"Greater London",
    "sg:tags":[
        "pubs",
        "inn"
    ],
    "wof:name":"The Robin Hood",
    "wof:placetype":"venue"
},
  "geometry": {"coordinates":[-0.1289200038,51.6772613525],"type":"Point"}
}