{
  "type": "Feature",
  "properties": {
    "addr:full":"23 Hillam Road Wallasey Merseyside CH45 8LD",
    "addr:housenumber":"23",
    "addr:postcode":"ch45 8ld",
    "addr:street":"Hillam Road",
    "iso:country":"GB",
    "sg:address":"23 Hillam Road",
    "sg:city":"Wallasey",
    "sg:classifiers":[
        {
            "category":"Professional",
            "subcategory":"Engineering",
            "type":"Services"
        }
    ],
    "sg:phone":"+44 151 630 3341",
    "sg:postcode":"CH45 8LD",
    "sg:province":"Merseyside",
    "sg:tags":[
        "contractor",
        "electrical",
        "engineer"
    ],
    "wof:name":"Britannia Electrical Contractors Ltd.",
    "wof:placetype":"venue"
},
  "geometry": {"coordinates":[-3.072139,53.42746],"type":"Point"}
}