{
  "type": "Feature",
  "properties": {
    "iso:country":"GB",
    "sg:address":"Snedshill Industrial Estate, Oakengates",
    "sg:city":"Telford",
    "sg:classifiers":[
        {
            "category":"Professional",
            "subcategory":"Engineering",
            "type":"Services"
        }
    ],
    "sg:phone":"+44 1952 614337",
    "sg:postcode":"TF2 9NH",
    "sg:province":"Shropshire",
    "sg:tags":[
        "precision",
        "engineer"
    ],
    "wof:name":"Apex Patterns",
    "wof:placetype":"venue"
},
  "geometry": {"coordinates":[-2.44074,52.686684],"type":"Point"}
}