{
  "type": "Feature",
  "properties": {
    "addr:full":"Moor St West Bromwich West Midlands B70 7AQ",
    "addr:postcode":"b70 7aq",
    "addr:street":"Moor St West",
    "iso:country":"GB",
    "sg:address":"Moor St",
    "sg:city":"West Bromwich",
    "sg:classifiers":[
        {
            "category":"Autos & Motor Vehicles",
            "subcategory":"Automobile Sales",
            "type":"Retail Goods"
        }
    ],
    "sg:phone":"+44 121 601 2221",
    "sg:postcode":"B70 7AQ",
    "sg:province":"West Midlands",
    "sg:tags":[
        "commercial"
    ],
    "wof:name":"First Cars",
    "wof:placetype":"venue"
},
  "geometry": {"coordinates":[-1.9992090464,52.515750885],"type":"Point"}
}