{
  "type": "Feature",
  "properties": {
    "addr:full":"1 Whitcombe Road Beaminster Dorset DT8 3NB",
    "addr:housenumber":"1",
    "addr:postcode":"dt8 3nb",
    "addr:street":"Whitcombe Road",
    "iso:country":"GB",
    "sg:address":"1 Whitcombe Road",
    "sg:city":"Beaminster",
    "sg:classifiers":[
        {
            "category":"Autos & Motor Vehicles",
            "subcategory":"Fuel & Gas Station",
            "type":"Retail Goods"
        }
    ],
    "sg:phone":"+44 1308 863032",
    "sg:postcode":"DT8 3NB",
    "sg:province":"Dorset",
    "sg:tags":[
        "petrol",
        "filling"
    ],
    "wof:name":"Gibbs Garage",
    "wof:placetype":"venue"
},
  "geometry": {"coordinates":[-2.7371389866,50.8077087402],"type":"Point"}
}