{
  "type": "Feature",
  "properties": {
    "addr:full":"2a Walker Place Shipley West Yorkshire BD18 1QE",
    "addr:housenumber":"2a",
    "addr:postcode":"bd18 1qe",
    "addr:street":"Walker Place",
    "iso:country":"GB",
    "sg:address":"2a Walker Place",
    "sg:city":"Shipley",
    "sg:classifiers":[
        {
            "category":"Taxi",
            "type":"Transportation"
        }
    ],
    "sg:phone":"+44 1274 589898",
    "sg:postcode":"BD18 1QE",
    "sg:province":"West Yorkshire",
    "sg:tags":[
        "mini",
        "cab"
    ],
    "wof:name":"Arrivals Cars",
    "wof:placetype":"venue"
},
  "geometry": {"coordinates":[-1.763409,53.837254],"type":"Point"}
}