{
  "type": "Feature",
  "properties": {
    "iso:country":"GB",
    "sg:address":"98 Hangingwater Road",
    "sg:city":"Sheffield",
    "sg:classifiers":[
        {
            "category":"Personal",
            "subcategory":"Beauty Salon",
            "type":"Services"
        }
    ],
    "sg:phone":"+44 114 230 8959",
    "sg:postcode":"S11 7ER",
    "sg:province":"Derbyshire",
    "sg:tags":[
        "unisex",
        "hairdresser"
    ],
    "wof:name":"Parklands Hair Studio",
    "wof:placetype":"venue"
},
  "geometry": {"coordinates":[-1.524873,53.367729],"type":"Point"}
}