{
  "type": "Feature",
  "properties": {
    "iso:country":"GB",
    "sg:address":"Front Street",
    "sg:city":"Morpeth",
    "sg:classifiers":[
        {
            "category":"Education",
            "subcategory":"Library",
            "type":"Public Place"
        }
    ],
    "sg:phone":"+44 1669 620428",
    "sg:postcode":"NE65 7TZ",
    "sg:province":"Northumberland",
    "sg:tags":[
        "book"
    ],
    "wof:name":"Rothbury Library",
    "wof:placetype":"venue"
},
  "geometry": {"coordinates":[-1.795856,55.304966],"type":"Point"}
}