{
  "type": "Feature",
  "properties": {
    "addr:full":"Barton House, Oake Taunton Devon TA4 1DR",
    "addr:postcode":"ta4 1dr",
    "addr:street":"Oake",
    "iso:country":"GB",
    "sg:address":"Barton House, Oake",
    "sg:city":"Taunton",
    "sg:classifiers":[
        {
            "category":"Utilities",
            "subcategory":"Sewage",
            "type":"Services"
        }
    ],
    "sg:phone":"+44 1823 353248",
    "sg:postcode":"TA4 1DR",
    "sg:province":"Devon",
    "sg:tags":[
        "disposal"
    ],
    "wof:name":"Gregory Coles Cleansing Services",
    "wof:placetype":"venue"
},
  "geometry": {"coordinates":[-3.208599,51.022289],"type":"Point"}
}