{
  "type": "Feature",
  "properties": {
    "addr:full":"5-7 Rectory Rd Grays Essex RM17 6BE",
    "addr:housenumber":"5-7",
    "addr:postcode":"rm17 6be",
    "addr:street":"Rectory Rd",
    "iso:country":"GB",
    "sg:address":"5-7 Rectory Rd",
    "sg:city":"Grays",
    "sg:classifiers":[
        {
            "category":"Professional",
            "type":"Services"
        }
    ],
    "sg:phone":"+44 1375 409931",
    "sg:postcode":"RM17 6BE",
    "sg:province":"Essex",
    "sg:tags":[
        "shopfitters"
    ],
    "wof:name":"Thurrock Builders and Shopfitters Ltd",
    "wof:placetype":"venue"
},
  "geometry": {"coordinates":[0.3410849869,51.4766464233],"type":"Point"}
}