{
  "type": "Feature",
  "properties": {
    "iso:country":"GB",
    "sg:address":"5 Willow Mt, Alverthorpe",
    "sg:city":"Wakefield",
    "sg:classifiers":[
        {
            "category":"Personal",
            "type":"Services"
        }
    ],
    "sg:postcode":"WF2 9TF",
    "sg:province":"West Yorkshire",
    "sg:tags":[
        "wedding"
    ],
    "wof:name":"Cowgill,Kirsten",
    "wof:placetype":"venue"
},
  "geometry": {"coordinates":[-1.510274,53.67997],"type":"Point"}
}