{
  "type": "Feature",
  "properties": {
    "addr:full":"Unit 1, Neville Rd Bradford West Yorkshire BD4 8QW",
    "addr:housenumber":"unit 1",
    "addr:postcode":"bd4 8qw",
    "addr:street":"Neville Rd",
    "iso:country":"GB",
    "sg:address":"Unit 1, Neville Rd",
    "sg:city":"Bradford",
    "sg:classifiers":[
        {
            "category":"Manufacturing",
            "subcategory":"Metals",
            "type":"Manufacturing & Wholesale Goods"
        }
    ],
    "sg:postcode":"BD4 8QW",
    "sg:province":"West Yorkshire",
    "sg:tags":[
        "steel",
        "fabricator",
        "erectors"
    ],
    "wof:name":"Jackson,Albert,",
    "wof:placetype":"venue"
},
  "geometry": {"coordinates":[-1.7288000584,53.7833938599],"type":"Point"}
}