{
  "type": "Feature",
  "properties": {
    "iso:country":"GB",
    "sg:address":"Sullens Farm, Sunnings La",
    "sg:city":"Upminster",
    "sg:classifiers":[
        {
            "category":"Professional",
            "subcategory":"Engineering",
            "type":"Services"
        }
    ],
    "sg:phone":"+44 1708 220297",
    "sg:postcode":"RM14 2DQ",
    "sg:province":"Essex",
    "sg:tags":[
        "contractor",
        "electrical",
        "engineer"
    ],
    "wof:name":"Sharaman Electrical Contractors",
    "wof:placetype":"venue"
},
  "geometry": {"coordinates":[0.24926,51.556339],"type":"Point"}
}