{
  "type": "Feature",
  "properties": {
    "addr:full":"11 Towne Rd Royston Bedfordshire SG8 9ES",
    "addr:housenumber":"11",
    "addr:postcode":"sg8 9es",
    "addr:street":"Towne Rd",
    "iso:country":"GB",
    "sg:address":"11 Towne Rd",
    "sg:city":"Royston",
    "sg:classifiers":[
        {
            "category":"Organizations",
            "subcategory":"Non-profit Organization",
            "type":"Services"
        }
    ],
    "sg:phone":"+44 1763 226091",
    "sg:postcode":"SG8 9ES",
    "sg:province":"Bedfordshire",
    "sg:tags":[
        "alarm",
        "system"
    ],
    "wof:name":"L M A Security Systems",
    "wof:placetype":"venue"
},
  "geometry": {"coordinates":[-0.019526,52.043396],"type":"Point"}
}