{
  "type": "Feature",
  "properties": {
    "iso:country":"GB",
    "sg:address":"Brittania Trade Park, Radway Road",
    "sg:city":"Swindon",
    "sg:classifiers":[
        {
            "category":"Retail",
            "subcategory":"Storage",
            "type":"Services"
        }
    ],
    "sg:phone":"+44 1285 652501",
    "sg:postcode":"SN3 4ND",
    "sg:province":"Wiltshire",
    "sg:tags":[
        "household",
        "removal"
    ],
    "wof:name":"Pickfords Removals",
    "wof:placetype":"venue"
},
  "geometry": {"coordinates":[-1.7562099695,51.5818214417],"type":"Point"}
}