{
  "type": "Feature",
  "properties": {
    "iso:country":"GB",
    "sg:address":"Unit 11 Badentoy Pl, Badentoy Indust Est",
    "sg:city":"Aberdeen",
    "sg:classifiers":[
        {
            "category":"Building & Trades",
            "subcategory":"Landscaping Services",
            "type":"Services"
        }
    ],
    "sg:phone":"+44 1224 322205",
    "sg:postcode":"AB12 4YF",
    "sg:province":"Aberdeen City",
    "sg:tags":[
        "landscape",
        "contractor"
    ],
    "wof:name":"Rentokil Tropical Plants",
    "wof:placetype":"venue"
},
  "geometry": {"coordinates":[-2.155347,57.069313],"type":"Point"}
}