{
  "type": "Feature",
  "properties": {
    "addr:full":"136 Harley Street London Greater London W1G 7JZ",
    "addr:housenumber":"136",
    "addr:postcode":"w1g 7jz",
    "addr:street":"Harley Street",
    "iso:country":"GB",
    "sg:address":"136 Harley Street",
    "sg:city":"London",
    "sg:classifiers":[
        {
            "category":"Health Services",
            "subcategory":"Health Practitioner",
            "type":"Services"
        }
    ],
    "sg:phone":"+44 20 7935 1230",
    "sg:postcode":"W1G 7JZ",
    "sg:province":"Greater London",
    "sg:tags":[
        "osteopath"
    ],
    "wof:name":"The Harvey Clinic",
    "wof:placetype":"venue"
},
  "geometry": {"coordinates":[-0.1484050006,51.5226821899],"type":"Point"}
}