{
  "type": "Feature",
  "properties": {
    "addr:full":"31 St Johns Road London Greater London SW11 1QN",
    "addr:housenumber":"31",
    "addr:postcode":"sw11 1qn",
    "addr:street":"St Johns Road",
    "iso:country":"GB",
    "sg:address":"31 St Johns Road",
    "sg:city":"London",
    "sg:classifiers":[
        {
            "category":"Shopping",
            "subcategory":"Clothing, Apparel, & Fashions",
            "type":"Retail Goods"
        }
    ],
    "sg:phone":"+44 20 7228 6113",
    "sg:postcode":"SW11 1QN",
    "sg:province":"Greater London",
    "sg:tags":[
        "menswear"
    ],
    "wof:name":"Capolito Roma",
    "wof:placetype":"venue"
},
  "geometry": {"coordinates":[-0.1674620062,51.4629173279],"type":"Point"}
}