{
  "type": "Feature",
  "properties": {
    "addr:full":"202 New London Road Chelmsford Essex CM2 9AB",
    "addr:housenumber":"202",
    "addr:postcode":"cm2 9ab",
    "addr:street":"New London Road",
    "iso:country":"GB",
    "sg:address":"202 New London Road",
    "sg:city":"Chelmsford",
    "sg:classifiers":[
        {
            "category":"Real Estate",
            "subcategory":"Real Estate Agent",
            "type":"Services"
        }
    ],
    "sg:phone":"+44 1245 350160",
    "sg:postcode":"CM2 9AB",
    "sg:province":"Essex",
    "wof:name":"Robert & Susan Dewar",
    "wof:placetype":"venue"
},
  "geometry": {"coordinates":[0.46182,51.724609],"type":"Point"}
}