{
  "type": "Feature",
  "properties": {
    "iso:country":"GB",
    "sg:address":"The Meads, Conham Vale",
    "sg:city":"Bristol",
    "sg:classifiers":[
        {
            "category":"Home & Garden",
            "subcategory":"Carpets & Floor Coverings",
            "type":"Retail Goods"
        }
    ],
    "sg:phone":"+44 117 954 0095",
    "sg:postcode":"BS15 3AU",
    "sg:province":"City of Bristol",
    "sg:tags":[
        "carpets",
        "rug",
        "matting"
    ],
    "wof:name":"S. Bellamy Quality Low Cost Carpets",
    "wof:placetype":"venue"
},
  "geometry": {"coordinates":[-2.510374,51.444763],"type":"Point"}
}