{
  "type": "Feature",
  "properties": {
    "addr:full":"365 Pleck Rd Walsall West Midlands WS2 9HD",
    "addr:housenumber":"365",
    "addr:postcode":"ws2 9hd",
    "addr:street":"Pleck Rd",
    "iso:country":"GB",
    "sg:address":"365 Pleck Rd",
    "sg:city":"Walsall",
    "sg:classifiers":[
        {
            "category":"Cafe",
            "type":"Food & Drink"
        }
    ],
    "sg:postcode":"WS2 9HD",
    "sg:province":"West Midlands",
    "sg:tags":[
        "tea",
        "room"
    ],
    "wof:name":"Derek's Cafe",
    "wof:placetype":"venue"
},
  "geometry": {"coordinates":[-2.001288,52.576313],"type":"Point"}
}