{
  "type": "Feature",
  "properties": {
    "iso:country":"GB",
    "sg:address":"Montpellier",
    "sg:city":"Gloucester",
    "sg:classifiers":[
        {
            "category":"Autos & Motor Vehicles",
            "subcategory":"Automobile Sales",
            "type":"Retail Goods"
        }
    ],
    "sg:phone":"+44 1452 522404",
    "sg:postcode":"GL1 1LF",
    "sg:province":"Gloucestershire",
    "sg:tags":[
        "car"
    ],
    "wof:name":"Gloucester Saab",
    "wof:placetype":"venue"
},
  "geometry": {"coordinates":[-2.2453689575,51.860534668],"type":"Point"}
}