{
  "type": "Feature",
  "properties": {
    "iso:country":"GB",
    "sg:address":"Tremont Road",
    "sg:city":"Llandrindod Wells",
    "sg:classifiers":[
        {
            "category":"Arts & Performance",
            "subcategory":"Theater",
            "type":"Entertainment"
        }
    ],
    "sg:phone":"+44 1597 824444",
    "sg:postcode":"LD1 5EB",
    "sg:province":"Powys",
    "sg:tags":[
        "hall",
        "theatre",
        "concert"
    ],
    "wof:name":"Theatr Powys",
    "wof:placetype":"venue"
},
  "geometry": {"coordinates":[-3.372854948,52.2531967163],"type":"Point"}
}