{
  "type": "Feature",
  "properties": {
    "addr:full":"Building 16, Champagne Whin Spring Lane Walton Wetherby North Yorkshire LS22 4DF",
    "addr:postcode":"ls22 4df",
    "addr:street":"Spring Lane",
    "iso:country":"GB",
    "sg:address":"Building 16, Champagne Whin Spring Lane Walton",
    "sg:city":"Wetherby",
    "sg:classifiers":[
        {
            "category":"Retail",
            "subcategory":"Auto Repair",
            "type":"Services"
        }
    ],
    "sg:phone":"+44 1937 844921",
    "sg:postcode":"LS22 4DF",
    "sg:province":"North Yorkshire",
    "sg:tags":[
        "body",
        "car"
    ],
    "wof:name":"R Stanger",
    "wof:placetype":"venue"
},
  "geometry": {"coordinates":[-1.3868039846,53.9279899597],"type":"Point"}
}