{
  "type": "Feature",
  "properties": {
    "iso:country":"GB",
    "sg:address":"345 Brighton Rd",
    "sg:city":"South Croydon",
    "sg:classifiers":[
        {
            "category":"Bars & Pubs",
            "type":"Food & Drink"
        }
    ],
    "sg:phone":"+44 20 8686 3792",
    "sg:postcode":"CR2 6ER",
    "sg:province":"Surrey",
    "sg:tags":[
        "pubs",
        "inn"
    ],
    "wof:name":"The Purley Arms",
    "wof:placetype":"venue"
},
  "geometry": {"coordinates":[-0.099792,51.350151],"type":"Point"}
}