{
  "type": "Feature",
  "properties": {
    "addr:full":"2 Essington Way Peterlee Durham SR8 5AZ",
    "addr:housenumber":"2",
    "addr:postcode":"sr8 5az",
    "addr:street":"Essington Way",
    "iso:country":"GB",
    "sg:address":"2 Essington Way",
    "sg:city":"Peterlee",
    "sg:classifiers":[
        {
            "category":"Shopping",
            "subcategory":"Discount & Variety Stores",
            "type":"Retail Goods"
        }
    ],
    "sg:phone":"+44 191 587 0210",
    "sg:postcode":"SR8 5AZ",
    "sg:province":"Durham",
    "sg:tags":[
        "centre"
    ],
    "wof:name":"Poundstretcher Ltd.",
    "wof:placetype":"venue"
},
  "geometry": {"coordinates":[-1.3429939747,54.7743339539],"type":"Point"}
}