{
  "type": "Feature",
  "properties": {
    "iso:country":"GB",
    "sg:address":"39 Newmarket Road, Fordham",
    "sg:city":"Ely",
    "sg:classifiers":[
        {
            "category":"Building & Trades",
            "subcategory":"Construction",
            "type":"Services"
        }
    ],
    "sg:phone":"+44 1638 720681",
    "sg:postcode":"CB7 5LL",
    "sg:province":"Cambridgeshire",
    "sg:tags":[
        "builder"
    ],
    "wof:name":"Lewin Smith & Co. Ltd.",
    "wof:placetype":"venue"
},
  "geometry": {"coordinates":[0.387249,52.300526],"type":"Point"}
}