{
  "type": "Feature",
  "properties": {
    "addr:full":"13 Church St Wetherby North Yorkshire LS22 6LP",
    "addr:housenumber":"13",
    "addr:postcode":"ls22 6lp",
    "addr:street":"Church St",
    "iso:country":"GB",
    "sg:address":"13 Church St",
    "sg:city":"Wetherby",
    "sg:classifiers":[
        {
            "category":"Professional",
            "subcategory":"Printing & Photocopies",
            "type":"Services"
        }
    ],
    "sg:postcode":"LS22 6LP",
    "sg:province":"North Yorkshire",
    "sg:tags":[
        "printer"
    ],
    "wof:name":"Cheek,A,",
    "wof:placetype":"venue"
},
  "geometry": {"coordinates":[-1.386727,53.929218],"type":"Point"}
}