{
  "type": "Feature",
  "properties": {
    "addr:full":"8 Inverleith Gdns Edinburgh City of Edinburgh EH3 5PU",
    "addr:housenumber":"8",
    "addr:postcode":"eh3 5pu",
    "addr:street":"Inverleith Gdns Edinburgh",
    "iso:country":"GB",
    "sg:address":"8 Inverleith Gdns",
    "sg:city":"Edinburgh",
    "sg:classifiers":[
        {
            "category":"Organizations",
            "subcategory":"Non-profit Organization",
            "type":"Services"
        }
    ],
    "sg:phone":"+44 131 551 4550",
    "sg:postcode":"EH3 5PU",
    "sg:province":"City of Edinburgh",
    "sg:tags":[
        "organisation",
        "voluntary",
        "charity"
    ],
    "wof:name":"M E Foundation (The)",
    "wof:placetype":"venue"
},
  "geometry": {"coordinates":[-3.2099909782,55.9708518982],"type":"Point"}
}