{
  "type": "Feature",
  "properties": {
    "iso:country":"GB",
    "sg:address":"124 Cornwall Avenue",
    "sg:city":"Blackpool",
    "sg:classifiers":[
        {
            "category":"Utilities",
            "subcategory":"Refuse",
            "type":"Services"
        }
    ],
    "sg:postcode":"FY2 9QR",
    "sg:province":"Lancashire",
    "sg:tags":[
        "disposal",
        "waste"
    ],
    "wof:name":"A Jet Pest",
    "wof:placetype":"venue"
},
  "geometry": {"coordinates":[-3.049173,53.840019],"type":"Point"}
}