{
  "type": "Feature",
  "properties": {
    "iso:country":"GB",
    "sg:address":"48 Gilmour Street, Eaglesham",
    "sg:city":"Glasgow",
    "sg:classifiers":[
        {
            "category":"Communications",
            "type":"Services"
        }
    ],
    "sg:phone":"+44 1355 302333",
    "sg:postcode":"G76 0LQ",
    "sg:province":"East Renfrewshire",
    "sg:tags":[
        "broadcasting"
    ],
    "wof:name":"Pencil of Light",
    "wof:placetype":"venue"
},
  "geometry": {"coordinates":[-4.271943,55.739845],"type":"Point"}
}