{
  "type": "Feature",
  "properties": {
    "iso:country":"GB",
    "sg:address":"Unit 12 Morebrook, South Mead Industrial Park",
    "sg:city":"Didcot",
    "sg:classifiers":[
        {
            "category":"Home & Garden",
            "subcategory":"Hardware",
            "type":"Retail Goods"
        },
        {
            "category":"Retail",
            "subcategory":"Auto Repair",
            "type":"Services"
        }
    ],
    "sg:phone":"+44 1235 512500",
    "sg:postcode":"OX11 7HP",
    "sg:province":"Oxfordshire",
    "sg:tags":[
        "hose",
        "sales",
        "fitting",
        "machinery",
        "tubing",
        "agricultural",
        "diy"
    ],
    "wof:name":"ACTION-SEALTITE LTD",
    "wof:placetype":"venue"
},
  "geometry": {"coordinates":[-1.232115,51.602383],"type":"Point"}
}