{
  "type": "Feature",
  "properties": {
    "addr:full":"53 Holmfield Road Blackpool Lancashire FY2 9RU",
    "addr:housenumber":"53",
    "addr:postcode":"fy2 9ru",
    "addr:street":"Holmfield Road",
    "iso:country":"GB",
    "sg:address":"53 Holmfield Road",
    "sg:city":"Blackpool",
    "sg:classifiers":[
        {
            "category":"Travel",
            "subcategory":"Hotels & Motels",
            "type":"Entertainment"
        }
    ],
    "sg:postcode":"FY2 9RU",
    "sg:province":"Lancashire",
    "wof:name":"The Lynton",
    "wof:placetype":"venue"
},
  "geometry": {"coordinates":[-3.052148,53.83646],"type":"Point"}
}