{
  "type": "Feature",
  "properties": {
    "iso:country":"GB",
    "sg:address":"Birkby Grange",
    "sg:city":"Huddersfield",
    "sg:classifiers":[
        {
            "category":"Manufacturing",
            "subcategory":"Building Materials",
            "type":"Manufacturing & Wholesale Goods"
        }
    ],
    "sg:phone":"+44 1422 306000",
    "sg:postcode":"HD2 2YA",
    "sg:province":"West Yorkshire",
    "sg:tags":[
        "concrete",
        "product"
    ],
    "wof:name":"Marshalls Hoveringham Ltd.",
    "wof:placetype":"venue"
},
  "geometry": {"coordinates":[-1.8110539913,53.662815094],"type":"Point"}
}