{
  "type": "Feature",
  "properties": {
    "addr:full":"The Old Warehouse Weybridge Surrey KT13 8DG",
    "addr:postcode":"kt13 8dg",
    "addr:street":"Weybridge",
    "iso:country":"GB",
    "sg:address":"The Old Warehouse",
    "sg:city":"Weybridge",
    "sg:classifiers":[
        {
            "category":"Organizations",
            "subcategory":"Membership Organization",
            "type":"Services"
        }
    ],
    "sg:phone":"+44 1932 870142",
    "sg:postcode":"KT13 8DG",
    "sg:province":"Surrey",
    "sg:tags":[
        "club"
    ],
    "wof:name":"Landa Asset Management Plc",
    "wof:placetype":"venue"
},
  "geometry": {"coordinates":[-0.4580650032,51.3727493286],"type":"Point"}
}