{
  "type": "Feature",
  "properties": {
    "addr:full":"Three Lane Ends Castleford West Yorkshire WF10 1QY",
    "addr:postcode":"wf10 1qy",
    "addr:street":"Three;Ends;West Yorkshire",
    "iso:country":"GB",
    "sg:address":"Three Lane Ends",
    "sg:city":"Castleford",
    "sg:classifiers":[
        {
            "category":"Food & Beverages",
            "subcategory":"Meat & Fish",
            "type":"Retail Goods"
        }
    ],
    "sg:phone":"+44 1977 510813",
    "sg:postcode":"WF10 1QY",
    "sg:province":"West Yorkshire",
    "sg:tags":[
        "butcher"
    ],
    "wof:name":"R Squire Family Butcher",
    "wof:placetype":"venue"
},
  "geometry": {"coordinates":[-1.3442080021,53.721698761],"type":"Point"}
}