{
  "type": "Feature",
  "properties": {
    "iso:country":"GB",
    "sg:address":"St Georges Quarry, Nant Du Road St George",
    "sg:city":"Abergele",
    "sg:classifiers":[
        {
            "category":"Home & Garden",
            "subcategory":"Building Materials",
            "type":"Retail Goods"
        }
    ],
    "sg:phone":"+44 1745 833172",
    "sg:postcode":"LL22 9BD",
    "sg:province":"Conwy",
    "sg:tags":[
        "ready",
        "mixed",
        "concrete"
    ],
    "wof:name":"Tilcon Ltd",
    "wof:placetype":"venue"
},
  "geometry": {"coordinates":[-3.557054,53.273575],"type":"Point"}
}