{
  "type": "Feature",
  "properties": {
    "addr:full":"10th Floor Alexandra House, 1 Alexandra Road Swansea Neath Port Talbot SA1 5ED",
    "addr:housenumber":"1",
    "addr:postcode":"sa1 5ed",
    "addr:street":"Alexandra Road",
    "iso:country":"GB",
    "sg:address":"10th Floor Alexandra House, 1 Alexandra Road",
    "sg:city":"Swansea",
    "sg:classifiers":[
        {
            "category":"Insurance",
            "subcategory":"Insurance Agent",
            "type":"Services"
        }
    ],
    "sg:phone":"+44 1792 495300",
    "sg:postcode":"SA1 5ED",
    "sg:province":"Neath Port Talbot",
    "wof:name":"Royal Insurance Life & Pensions",
    "wof:placetype":"venue"
},
  "geometry": {"coordinates":[-3.9420111179,51.6247291565],"type":"Point"}
}