{
  "type": "Feature",
  "properties": {
    "iso:country":"GB",
    "sg:address":"62 High St",
    "sg:city":"Lymington",
    "sg:classifiers":[
        {
            "category":"Manufacturing",
            "subcategory":"Tools & Machinery",
            "type":"Manufacturing & Wholesale Goods"
        }
    ],
    "sg:phone":"+44 1590 673717",
    "sg:postcode":"SO41 9AH",
    "sg:province":"Hampshire",
    "sg:tags":[
        "society",
        "friendly"
    ],
    "wof:name":"Bishops Financial Management",
    "wof:placetype":"venue"
},
  "geometry": {"coordinates":[-1.544015,50.757683],"type":"Point"}
}