{
  "type": "Feature",
  "properties": {
    "addr:full":"Preston New Rd Blackpool Lancashire FY4 4RE",
    "addr:postcode":"fy4 4re",
    "addr:street":"Preston New Rd",
    "iso:country":"GB",
    "sg:address":"Preston New Rd",
    "sg:city":"Blackpool",
    "sg:classifiers":[
        {
            "category":"Organizations",
            "subcategory":"Membership Organization",
            "type":"Services"
        }
    ],
    "sg:phone":"+44 1253 761021",
    "sg:postcode":"FY4 4RE",
    "sg:province":"Lancashire",
    "sg:tags":[
        "club"
    ],
    "wof:name":"Co-operative Sports Association",
    "wof:placetype":"venue"
},
  "geometry": {"coordinates":[-3.0229139328,53.8044395447],"type":"Point"}
}