{
  "type": "Feature",
  "properties": {
    "addr:full":"Unit 49, Padgets Lane, South Moons Moat Redditch Warwickshire B98 0RD",
    "addr:housenumber":"unit 49",
    "addr:postcode":"b98 0rd",
    "addr:street":"Padgets Lane South Moons",
    "iso:country":"GB",
    "sg:address":"Unit 49, Padgets Lane, South Moons Moat",
    "sg:city":"Redditch",
    "sg:classifiers":[
        {
            "category":"Shopping",
            "subcategory":"Discount & Variety Stores",
            "type":"Retail Goods"
        }
    ],
    "sg:phone":"+44 1527 524992",
    "sg:postcode":"B98 0RD",
    "sg:province":"Warwickshire",
    "sg:tags":[
        "cleaning",
        "supply"
    ],
    "wof:name":"A M Services",
    "wof:placetype":"venue"
},
  "geometry": {"coordinates":[-1.8988790512,52.3093185425],"type":"Point"}
}