{
  "type": "Feature",
  "properties": {
    "addr:full":"13-14 Market Place Penzance Cornwall TR18 2JB",
    "addr:housenumber":"13-14",
    "addr:postcode":"tr18 2jb",
    "addr:street":"Market Place",
    "iso:country":"GB",
    "sg:address":"13-14 Market Place",
    "sg:city":"Penzance",
    "sg:classifiers":[
        {
            "category":"Home & Garden",
            "subcategory":"Furniture",
            "type":"Retail Goods"
        }
    ],
    "sg:postcode":"TR18 2JB",
    "sg:province":"Cornwall",
    "wof:name":"J W Meek & Sons Ltd.",
    "wof:placetype":"venue"
},
  "geometry": {"coordinates":[-5.5368189812,50.1189422607],"type":"Point"}
}