{
  "type": "Feature",
  "properties": {
    "iso:country":"GB",
    "sg:address":"Loraine Way",
    "sg:city":"Ipswich",
    "sg:classifiers":[
        {
            "category":"Recreation",
            "subcategory":"Water Park",
            "type":"Entertainment"
        }
    ],
    "sg:phone":"+44 1473 830191",
    "sg:postcode":"IP8 4JS",
    "sg:province":"Suffolk",
    "sg:tags":[
        "sport"
    ],
    "wof:name":"Suffolk Waters Country Park",
    "wof:placetype":"venue"
},
  "geometry": {"coordinates":[1.093789,52.075001],"type":"Point"}
}