{
  "type": "Feature",
  "properties": {
    "addr:full":"56 Crabtree Lane Lancing West Sussex BN15 9PJ",
    "addr:housenumber":"56",
    "addr:postcode":"bn15 9pj",
    "addr:street":"Crabtree Lane",
    "iso:country":"GB",
    "sg:address":"56 Crabtree Lane",
    "sg:city":"Lancing",
    "sg:classifiers":[
        {
            "category":"Home & Garden",
            "subcategory":"Building Materials",
            "type":"Retail Goods"
        }
    ],
    "sg:postcode":"BN15 9PJ",
    "sg:province":"West Sussex",
    "sg:tags":[
        "garage",
        "door"
    ],
    "wof:name":"Garage Door Associates",
    "wof:placetype":"venue"
},
  "geometry": {"coordinates":[-0.321663,50.832005],"type":"Point"}
}