{
  "type": "Feature",
  "properties": {
    "iso:country":"GB",
    "sg:address":"33 Brook Street",
    "sg:city":"Brentwood",
    "sg:classifiers":[
        {
            "category":"Building & Trades",
            "subcategory":"Construction",
            "type":"Services"
        }
    ],
    "sg:phone":"+44 1277 217033",
    "sg:postcode":"CM14 5LZ",
    "sg:province":"Essex",
    "sg:tags":[
        "ceiling",
        "contractor"
    ],
    "wof:name":"R A Fisher",
    "wof:placetype":"venue"
},
  "geometry": {"coordinates":[0.273497,51.611664],"type":"Point"}
}