{
  "type": "Feature",
  "properties": {
    "addr:full":"2a Crompton Way, Segensworth West Fareham Hampshire PO15 5SS",
    "addr:housenumber":"2a",
    "addr:postcode":"po15 5ss",
    "addr:street":"Crompton Way",
    "iso:country":"GB",
    "sg:address":"2a Crompton Way, Segensworth West",
    "sg:city":"Fareham",
    "sg:classifiers":[
        {
            "category":"Shopping",
            "subcategory":"Bicycles & Sporting Goods",
            "type":"Retail Goods"
        }
    ],
    "sg:phone":"+44 1489 581696",
    "sg:postcode":"PO15 5SS",
    "sg:province":"Hampshire",
    "sg:tags":[
        "equipment",
        "marine",
        "supply"
    ],
    "wof:name":"Kayospruce Ltd.",
    "wof:placetype":"venue"
},
  "geometry": {"coordinates":[-1.2590910196,50.8710212708],"type":"Point"}
}