{
  "type": "Feature",
  "properties": {
    "iso:country":"GB",
    "sg:address":"Hanmar House, 34 Coal Clough Lane",
    "sg:city":"Burnley",
    "sg:classifiers":[
        {
            "category":"Organizations",
            "subcategory":"Non-profit Organization",
            "type":"Services"
        }
    ],
    "sg:phone":"+44 7770 578350",
    "sg:postcode":"BB11 4PG",
    "sg:province":"Lancashire",
    "sg:tags":[
        "fundraising",
        "charity"
    ],
    "wof:name":"Club Promotions (U K)",
    "wof:placetype":"venue"
},
  "geometry": {"coordinates":[-2.2585029602,53.786895752],"type":"Point"}
}