{
  "type": "Feature",
  "properties": {
    "iso:country":"GB",
    "sg:address":"Exeter House, King Street, Laugharne",
    "sg:city":"Carmarthen",
    "sg:classifiers":[
        {
            "category":"Government",
            "subcategory":"Post Office",
            "type":"Public Place"
        }
    ],
    "sg:phone":"+44 1994 427250",
    "sg:postcode":"SA33 4RY",
    "sg:province":"Carmarthenshire",
    "wof:name":"Laugharne Sub Post Office",
    "wof:placetype":"venue"
},
  "geometry": {"coordinates":[-4.462729,51.771809],"type":"Point"}
}