{
  "type": "Feature",
  "properties": {
    "addr:full":"The Friary Northampton Northamptonshire NN1 2ER",
    "addr:postcode":"nn1 2er",
    "addr:street":"The",
    "iso:country":"GB",
    "sg:address":"The Friary",
    "sg:city":"Northampton",
    "sg:classifiers":[
        {
            "category":"Shopping",
            "subcategory":"Comic Books",
            "type":"Retail Goods"
        }
    ],
    "sg:postcode":"NN1 2ER",
    "sg:province":"Northamptonshire",
    "sg:tags":[
        "jeweller"
    ],
    "wof:name":"Nolans Jewellers & Watchmakers Ltd",
    "wof:placetype":"venue"
},
  "geometry": {"coordinates":[-0.8952839971,52.2339401245],"type":"Point"}
}