{
  "type": "Feature",
  "properties": {
    "addr:full":"12 Low Street Banff Aberdeenshire AB45 1AS",
    "addr:housenumber":"12",
    "addr:postcode":"ab45 1as",
    "addr:street":"Low Street",
    "iso:country":"GB",
    "sg:address":"12 Low Street",
    "sg:city":"Banff",
    "sg:classifiers":[
        {
            "category":"Bars & Pubs",
            "type":"Food & Drink"
        }
    ],
    "sg:postcode":"AB45 1AS",
    "sg:province":"Aberdeenshire",
    "sg:tags":[
        "pubs",
        "inn"
    ],
    "wof:name":"The Aul Fife",
    "wof:placetype":"venue"
},
  "geometry": {"coordinates":[-2.521836,57.66354],"type":"Point"}
}