{
  "type": "Feature",
  "properties": {
    "iso:country":"GB",
    "sg:address":"Holme Farm, Lincoln Lane, Thorpe-on-the-hill",
    "sg:city":"Lincoln",
    "sg:classifiers":[
        {
            "category":"Farming",
            "subcategory":"Farm",
            "type":"Manufacturing & Wholesale Goods"
        }
    ],
    "sg:phone":"+44 1522 681012",
    "sg:postcode":"LN6 9BH",
    "sg:province":"Lincolnshire",
    "sg:tags":[
        "mixed",
        "crop"
    ],
    "wof:name":"T.C Richardson & Son",
    "wof:placetype":"venue"
},
  "geometry": {"coordinates":[-0.6420919895,53.1799278259],"type":"Point"}
}