{
  "type": "Feature",
  "properties": {
    "iso:country":"GB",
    "sg:address":"Unit 1, The Industrial Estate",
    "sg:city":"Witney",
    "sg:classifiers":[
        {
            "category":"Freight",
            "type":"Transportation"
        }
    ],
    "sg:phone":"+44 1865 881918",
    "sg:postcode":"OX29 5SL",
    "sg:province":"Oxfordshire",
    "sg:tags":[
        "haulage",
        "road"
    ],
    "wof:name":"Bury's Transport (Maxim) Ltd.",
    "wof:placetype":"venue"
},
  "geometry": {"coordinates":[-1.408849,51.74715],"type":"Point"}
}