{
  "type": "Feature",
  "properties": {
    "iso:country":"GB",
    "sg:address":"38 Church Rd",
    "sg:city":"Burgess Hill",
    "sg:classifiers":[
        {
            "category":"Real Estate",
            "subcategory":"Surveying",
            "type":"Services"
        }
    ],
    "sg:phone":"+44 1444 250820",
    "sg:postcode":"RH15 9AE",
    "sg:province":"East Sussex",
    "sg:tags":[
        "building",
        "surveyor"
    ],
    "wof:name":"Woudman Oakley",
    "wof:placetype":"venue"
},
  "geometry": {"coordinates":[-0.129801,50.955395],"type":"Point"}
}