{
  "type": "Feature",
  "properties": {
    "iso:country":"GB",
    "sg:address":"Unit 4, 5 Haviland Road, Ferndown Industrial Estate",
    "sg:city":"Wimborne",
    "sg:classifiers":[
        {
            "category":"Professional",
            "subcategory":"Printing & Photocopies",
            "type":"Services"
        }
    ],
    "sg:phone":"+44 1202 890333",
    "sg:postcode":"BH21 7RZ",
    "sg:province":"Dorset",
    "sg:tags":[
        "duplicating",
        "copying"
    ],
    "wof:name":"Rpm Digital Print Ltd.",
    "wof:placetype":"venue"
},
  "geometry": {"coordinates":[-1.915656,50.811668],"type":"Point"}
}