{
  "type": "Feature",
  "properties": {
    "iso:country":"GB",
    "sg:address":"35 Greenacre Park",
    "sg:city":"Leeds",
    "sg:classifiers":[
        {
            "category":"Retail",
            "subcategory":"Driving School",
            "type":"Services"
        }
    ],
    "sg:phone":"+44 113 250 1489",
    "sg:postcode":"LS19 6AR",
    "sg:province":"West Yorkshire",
    "wof:name":"Driving Tuition Rawdon",
    "wof:placetype":"venue"
},
  "geometry": {"coordinates":[-1.685263,53.857632],"type":"Point"}
}