{
  "type": "Feature",
  "properties": {
    "addr:full":"17 Station Road, Willington Bedford Bedfordshire MK44 3QH",
    "addr:housenumber":"17",
    "addr:postcode":"mk44 3qh",
    "addr:street":"Station Road",
    "iso:country":"GB",
    "sg:address":"17 Station Road, Willington",
    "sg:city":"Bedford",
    "sg:classifiers":[
        {
            "category":"Bars & Pubs",
            "type":"Food & Drink"
        }
    ],
    "sg:phone":"+44 1234 838308",
    "sg:postcode":"MK44 3QH",
    "sg:province":"Bedfordshire",
    "sg:tags":[
        "pubs",
        "inn"
    ],
    "wof:name":"The Crown Public House",
    "wof:placetype":"venue"
},
  "geometry": {"coordinates":[-0.321242,52.145462],"type":"Point"}
}