{
  "type": "Feature",
  "properties": {
    "addr:full":"Unit F3 Brighton Business Centre, Ditchling Rd Brighton East Sussex BN1 4ST",
    "addr:housenumber":"f3",
    "addr:postcode":"bn1 4st",
    "addr:street":"Brighton Business Centre Ditchling Rd",
    "iso:country":"GB",
    "sg:address":"Unit F3 Brighton Business Centre, Ditchling Rd",
    "sg:city":"Brighton",
    "sg:classifiers":[
        {
            "category":"Food & Beverages",
            "subcategory":"Liquor & Beverages",
            "type":"Retail Goods"
        }
    ],
    "sg:postcode":"BN1 4ST",
    "sg:province":"East Sussex",
    "sg:tags":[
        "drink",
        "soft"
    ],
    "wof:name":"Cabanas Soft Drinks",
    "wof:placetype":"venue"
},
  "geometry": {"coordinates":[-0.1342100054,50.8330802917],"type":"Point"}
}