{
  "type": "Feature",
  "properties": {
    "addr:full":"Units 1-2, Quarry Lane Chichester West Sussex PO19 2NY",
    "addr:housenumber":"units 1-2",
    "addr:postcode":"po19 2ny",
    "addr:street":"Quarry Lane",
    "iso:country":"GB",
    "sg:address":"Units 1-2, Quarry Lane",
    "sg:city":"Chichester",
    "sg:classifiers":[
        {
            "category":"Home & Garden",
            "subcategory":"Home Furnishings",
            "type":"Retail Goods"
        },
        {
            "category":"Home & Garden",
            "subcategory":"Hardware",
            "type":"Retail Goods"
        }
    ],
    "sg:phone":"+44 1243 532456",
    "sg:postcode":"PO19 2NY",
    "sg:province":"West Sussex",
    "sg:tags":[
        "merchant",
        "paint",
        "diy",
        "decorators'"
    ],
    "wof:name":"Dulux Decorating Centre",
    "wof:placetype":"venue"
},
  "geometry": {"coordinates":[-0.7754290104,50.8361663818],"type":"Point"}
}