{
  "type": "Feature",
  "properties": {
    "addr:full":"10 Market Street Maidstone Kent ME14 1QA",
    "addr:housenumber":"10",
    "addr:postcode":"me14 1qa",
    "addr:street":"Market Street",
    "iso:country":"GB",
    "sg:address":"10 Market Street",
    "sg:city":"Maidstone",
    "sg:classifiers":[
        {
            "category":"Autos & Motor Vehicles",
            "subcategory":"Automobile Sales",
            "type":"Retail Goods"
        }
    ],
    "sg:postcode":"ME14 1QA",
    "sg:province":"Kent",
    "sg:tags":[
        "car"
    ],
    "wof:name":"J Clements",
    "wof:placetype":"venue"
},
  "geometry": {"coordinates":[0.521688,51.273926],"type":"Point"}
}