{
  "type": "Feature",
  "properties": {
    "addr:full":"Unit 13, Point Pleasant Industrial Estate Wallsend Tyne and Wear NE28 6HA",
    "addr:housenumber":"unit 13",
    "addr:postcode":"ne28 6ha",
    "addr:street":"Estate",
    "iso:country":"GB",
    "sg:address":"Unit 13, Point Pleasant Industrial Estate",
    "sg:city":"Wallsend",
    "sg:classifiers":[
        {
            "category":"Social Services",
            "subcategory":"Adult Care",
            "type":"Services"
        }
    ],
    "sg:phone":"+44 191 200 7159",
    "sg:postcode":"NE28 6HA",
    "sg:province":"Tyne and Wear",
    "sg:tags":[
        "housing",
        "sheltered"
    ],
    "wof:name":"North Tyne Products",
    "wof:placetype":"venue"
},
  "geometry": {"coordinates":[-1.5072259903,54.992477417],"type":"Point"}
}