{
  "type": "Feature",
  "properties": {
    "iso:country":"GB",
    "sg:address":"Lacy House",
    "sg:city":"Hebden Bridge",
    "sg:classifiers":[
        {
            "category":"Building & Trades",
            "subcategory":"Landscaping Services",
            "type":"Services"
        }
    ],
    "sg:postcode":"HX7 6PN",
    "sg:province":"West Yorkshire",
    "sg:tags":[
        "forestry",
        "tree"
    ],
    "wof:name":"Treeline",
    "wof:placetype":"venue"
},
  "geometry": {"coordinates":[-2.014491,53.741226],"type":"Point"}
}