{
  "type": "Feature",
  "properties": {
    "addr:full":"Bradford Farm Uckfield East Sussex TN22 5QP",
    "addr:housenumber":"uckfield",
    "addr:postcode":"tn22 5qp",
    "iso:country":"GB",
    "sg:address":"Bradford Farm",
    "sg:city":"Uckfield",
    "sg:classifiers":[
        {
            "category":"Shopping",
            "subcategory":"Gifts & Souvenirs",
            "type":"Retail Goods"
        }
    ],
    "sg:phone":"+44 1825 841227",
    "sg:postcode":"TN22 5QP",
    "sg:province":"East Sussex",
    "sg:tags":[
        "ducting"
    ],
    "wof:name":"Bretvents Ltd.",
    "wof:placetype":"venue"
},
  "geometry": {"coordinates":[0.0951849967,50.9677696228],"type":"Point"}
}