{
  "type": "Feature",
  "properties": {
    "iso:country":"GB",
    "sg:address":"The White House, Rooks Hill, Underriver",
    "sg:city":"Sevenoaks",
    "sg:classifiers":[
        {
            "category":"Organizations",
            "subcategory":"Non-profit Organization",
            "type":"Services"
        }
    ],
    "sg:postcode":"TN15 0SL",
    "sg:province":"Kent",
    "sg:tags":[
        "organisation",
        "voluntary",
        "charity"
    ],
    "wof:name":"Amnesty International",
    "wof:placetype":"venue"
},
  "geometry": {"coordinates":[0.228619,51.248272],"type":"Point"}
}