{
  "type": "Feature",
  "properties": {
    "iso:country":"GB",
    "sg:address":"2 Drumpellier Place, Lochwinnoch Rd",
    "sg:city":"Kilmacolm",
    "sg:classifiers":[
        {
            "category":"Real Estate",
            "subcategory":"Real Estate Agent",
            "type":"Services"
        }
    ],
    "sg:phone":"+44 1505 874000",
    "sg:postcode":"PA13 4HE",
    "sg:province":"Inverclyde",
    "wof:name":"The Robb Agency",
    "wof:placetype":"venue"
},
  "geometry": {"coordinates":[-4.6334438324,55.8932762146],"type":"Point"}
}