{
  "type": "Feature",
  "properties": {
    "addr:full":"Unit 6 Ben Nevis Auction Mart, Torlundy Fort William Highland PH33 6SW",
    "addr:housenumber":"unit 6",
    "addr:postcode":"ph33 6sw",
    "addr:street":"Ben Nevis;Torlundy;William",
    "iso:country":"GB",
    "sg:address":"Unit 6 Ben Nevis Auction Mart, Torlundy",
    "sg:city":"Fort William",
    "sg:classifiers":[
        {
            "category":"Professional",
            "subcategory":"Secretarial Services",
            "type":"Services"
        }
    ],
    "sg:phone":"+44 1397 701039",
    "sg:postcode":"PH33 6SW",
    "sg:province":"Highland",
    "wof:name":"B O S S",
    "wof:placetype":"venue"
},
  "geometry": {"coordinates":[-5.097840786,56.8211631775],"type":"Point"}
}