{
  "type": "Feature",
  "properties": {
    "addr:full":"12 Moat La Walsall Staffordshire WS6 6DU",
    "addr:housenumber":"12",
    "addr:postcode":"ws6 6du",
    "addr:street":"Moat La",
    "iso:country":"GB",
    "sg:address":"12 Moat La",
    "sg:city":"Walsall",
    "sg:classifiers":[
        {
            "category":"Home & Garden",
            "subcategory":"Kitchen Supply",
            "type":"Retail Goods"
        }
    ],
    "sg:phone":"+44 1922 410040",
    "sg:postcode":"WS6 6DU",
    "sg:province":"Staffordshire",
    "sg:tags":[
        "equipment",
        "catering"
    ],
    "wof:name":"Midlands Icing Centre",
    "wof:placetype":"venue"
},
  "geometry": {"coordinates":[-2.013435,52.659794],"type":"Point"}
}