{
  "type": "Feature",
  "properties": {
    "addr:full":"Coopers Square Shopping Centre, 13-15 Swan Walk Burton-on-trent Derbyshire DE14 1DD",
    "addr:housenumber":"13-15",
    "addr:postcode":"de14 1dd",
    "addr:street":"Swan Walk",
    "iso:country":"GB",
    "sg:address":"Coopers Square Shopping Centre, 13-15 Swan Walk",
    "sg:city":"Burton-on-trent",
    "sg:classifiers":[
        {
            "category":"Home & Garden",
            "subcategory":"Household Appliances",
            "type":"Retail Goods"
        }
    ],
    "sg:phone":"+44 1283 546311",
    "sg:postcode":"DE14 1DD",
    "sg:province":"Derbyshire",
    "sg:tags":[
        "electrical",
        "domestic"
    ],
    "wof:name":"Dixons",
    "wof:placetype":"venue"
},
  "geometry": {"coordinates":[-1.63202,52.802601],"type":"Point"}
}