{
  "type": "Feature",
  "properties": {
    "addr:full":"17 Greys Road Henley-on-thames Berkshire RG9 1SB",
    "addr:housenumber":"17",
    "addr:postcode":"rg9 1sb",
    "addr:street":"Greys Road",
    "iso:country":"GB",
    "sg:address":"17 Greys Road",
    "sg:city":"Henley-on-thames",
    "sg:classifiers":[
        {
            "category":"Professional",
            "subcategory":"Advertising",
            "type":"Services"
        },
        {
            "category":"Professional",
            "subcategory":"Art Services",
            "type":"Services"
        }
    ],
    "sg:phone":"+44 1491 572626",
    "sg:postcode":"RG9 1SB",
    "sg:province":"Berkshire",
    "sg:tags":[
        "consultant",
        "agency",
        "design"
    ],
    "wof:name":"Paragon Perspectives",
    "wof:placetype":"venue"
},
  "geometry": {"coordinates":[-0.904539,51.535946],"type":"Point"}
}