{
  "type": "Feature",
  "properties": {
    "addr:full":"Chapel Road Worthing West Sussex BN11 1HU",
    "addr:postcode":"bn11 1hu",
    "addr:street":"Chapel Road",
    "iso:country":"GB",
    "sg:address":"Chapel Road",
    "sg:city":"Worthing",
    "sg:classifiers":[
        {
            "category":"Bars & Pubs",
            "type":"Food & Drink"
        }
    ],
    "sg:postcode":"BN11 1HU",
    "sg:province":"West Sussex",
    "sg:tags":[
        "pubs",
        "inn"
    ],
    "wof:name":"The Rivoli Hotel",
    "wof:placetype":"venue"
},
  "geometry": {"coordinates":[-0.3713989854,50.8146896362],"type":"Point"}
}