{
  "type": "Feature",
  "properties": {
    "iso:country":"GB",
    "sg:address":"1 Kirk Square",
    "sg:city":"Arbroath",
    "sg:classifiers":[
        {
            "category":"Military Area",
            "subcategory":"Air Force Base",
            "type":"Public Place"
        }
    ],
    "sg:phone":"+44 1241 431333",
    "sg:postcode":"DD11 1DX",
    "sg:province":"Angus",
    "sg:tags":[
        "taxi",
        "hire",
        "private"
    ],
    "wof:name":"Co Cabs",
    "wof:placetype":"venue"
},
  "geometry": {"coordinates":[-2.580316,56.559845],"type":"Point"}
}