{
  "type": "Feature",
  "properties": {
    "addr:full":"17 Stockwell Street Glasgow Glasgow City G1 4RZ",
    "addr:housenumber":"17",
    "addr:postcode":"g1 4rz",
    "addr:street":"Stockwell Street",
    "iso:country":"GB",
    "sg:address":"17 Stockwell Street",
    "sg:city":"Glasgow",
    "sg:classifiers":[
        {
            "category":"Professional",
            "subcategory":"Art Services",
            "type":"Services"
        }
    ],
    "sg:phone":"+44 141 554 4222",
    "sg:postcode":"G1 4RZ",
    "sg:province":"Glasgow City",
    "sg:tags":[
        "framing"
    ],
    "wof:name":"Picturemounts Ltd",
    "wof:placetype":"venue"
},
  "geometry": {"coordinates":[-4.2491898537,55.8573455811],"type":"Point"}
}