{
  "type": "Feature",
  "properties": {
    "addr:full":"Hailes Park Industrial Estate, Dumbryden Drive Edinburgh City of Edinburgh EH14 2QR",
    "addr:postcode":"eh14 2qr",
    "addr:street":"Hailes Park Industrial;Dumbryden Drive",
    "iso:country":"GB",
    "sg:address":"Hailes Park Industrial Estate, Dumbryden Drive",
    "sg:city":"Edinburgh",
    "sg:classifiers":[
        {
            "category":"Food & Beverages",
            "subcategory":"Specialty",
            "type":"Retail Goods"
        }
    ],
    "sg:phone":"+44 131 477 7055",
    "sg:postcode":"EH14 2QR",
    "sg:province":"City of Edinburgh",
    "sg:tags":[
        "product",
        "health"
    ],
    "wof:name":"Ryan's Wholefoods",
    "wof:placetype":"venue"
},
  "geometry": {"coordinates":[-3.2811989784,55.914855957],"type":"Point"}
}