{
  "type": "Feature",
  "properties": {
    "addr:full":"9 Bull Yard Coventry West Midlands CV1 1LH",
    "addr:housenumber":"9",
    "addr:postcode":"cv1 1lh",
    "addr:street":"Bull Yard",
    "iso:country":"GB",
    "sg:address":"9 Bull Yard",
    "sg:city":"Coventry",
    "sg:classifiers":[
        {
            "category":"Deli",
            "type":"Food & Drink"
        }
    ],
    "sg:phone":"+44 24 7625 6389",
    "sg:postcode":"CV1 1LH",
    "sg:province":"West Midlands",
    "sg:tags":[
        "delicatessen"
    ],
    "wof:name":"Brown Bag Deli",
    "wof:placetype":"venue"
},
  "geometry": {"coordinates":[-1.5126479864,52.4062576294],"type":"Point"}
}