{
  "type": "Feature",
  "properties": {
    "addr:full":"The Bourne, 22 Whiterose La Woking Surrey GU22 7JY",
    "addr:housenumber":"22",
    "addr:postcode":"gu22 7jy",
    "addr:street":"Whiterose La Woking",
    "iso:country":"GB",
    "sg:address":"The Bourne, 22 Whiterose La",
    "sg:city":"Woking",
    "sg:classifiers":[
        {
            "category":"Manufacturing",
            "subcategory":"Signs",
            "type":"Manufacturing & Wholesale Goods"
        }
    ],
    "sg:postcode":"GU22 7JY",
    "sg:province":"Surrey",
    "sg:tags":[
        "nameplate"
    ],
    "wof:name":"Impact Image",
    "wof:placetype":"venue"
},
  "geometry": {"coordinates":[-0.54994,51.311359],"type":"Point"}
}