{
  "type": "Feature",
  "properties": {
    "iso:country":"GB",
    "sg:address":"Tannery Drift",
    "sg:city":"Royston",
    "sg:classifiers":[
        {
            "category":"Education",
            "subcategory":"School",
            "type":"Public Place"
        }
    ],
    "sg:phone":"+44 1763 243297",
    "sg:postcode":"SG8 5DE",
    "sg:province":"Bedfordshire",
    "sg:tags":[
        "local",
        "authority"
    ],
    "wof:name":"Hertfordshire County Council",
    "wof:placetype":"venue"
},
  "geometry": {"coordinates":[-0.029589,52.051075],"type":"Point"}
}