{
  "type": "Feature",
  "properties": {
    "addr:full":"55 Blackfriars Road Salford Greater Manchester M3 7DB",
    "addr:housenumber":"55",
    "addr:postcode":"m3 7db",
    "addr:street":"Blackfriars Road",
    "iso:country":"GB",
    "sg:address":"55 Blackfriars Road",
    "sg:city":"Salford",
    "sg:classifiers":[
        {
            "category":"Travel",
            "subcategory":"Hotels & Motels",
            "type":"Entertainment"
        }
    ],
    "sg:phone":"+44 161 907 2277",
    "sg:postcode":"M3 7DB",
    "sg:province":"Greater Manchester",
    "wof:name":"Dolby Hotel (Manchester West) Ltd.",
    "wof:placetype":"venue"
},
  "geometry": {"coordinates":[-2.253907,53.486881],"type":"Point"}
}