{
  "type": "Feature",
  "properties": {
    "addr:full":"12 Sankey St Warrington Cheshire WA1 1TD",
    "addr:housenumber":"12",
    "addr:postcode":"wa1 1td",
    "addr:street":"Sankey St",
    "iso:country":"GB",
    "sg:address":"12 Sankey St",
    "sg:city":"Warrington",
    "sg:classifiers":[
        {
            "category":"Communications",
            "type":"Services"
        }
    ],
    "sg:phone":"+44 1925 634900",
    "sg:postcode":"WA1 1TD",
    "sg:province":"Cheshire",
    "sg:tags":[
        "telecommunication"
    ],
    "wof:name":"Orange Retail Shop",
    "wof:placetype":"venue"
},
  "geometry": {"coordinates":[-2.594465,53.389149],"type":"Point"}
}