{
  "type": "Feature",
  "properties": {
    "iso:country":"GB",
    "sg:address":"59 Trafalgar Street",
    "sg:city":"Sheffield",
    "sg:classifiers":[
        {
            "category":"Building & Trades",
            "subcategory":"Construction",
            "type":"Services"
        }
    ],
    "sg:phone":"+44 114 249 3376",
    "sg:postcode":"S1 4GN",
    "sg:province":"South Yorkshire",
    "sg:tags":[
        "joiner",
        "carpenter"
    ],
    "wof:name":"Terence McBride",
    "wof:placetype":"venue"
},
  "geometry": {"coordinates":[-1.475749,53.378605],"type":"Point"}
}