{
  "type": "Feature",
  "properties": {
    "iso:country":"GB",
    "sg:address":"89 Repton Rd, Hartshorne",
    "sg:city":"Swadlincote",
    "sg:classifiers":[
        {
            "category":"Home & Garden",
            "subcategory":"Building Materials",
            "type":"Retail Goods"
        }
    ],
    "sg:postcode":"DE11 7AE",
    "sg:province":"Derbyshire",
    "sg:tags":[
        "insulation",
        "installers"
    ],
    "wof:name":"Henchcliffe,Andrew Ian,",
    "wof:placetype":"venue"
},
  "geometry": {"coordinates":[-1.528429985,52.7882080078],"type":"Point"}
}