{
  "type": "Feature",
  "properties": {
    "iso:country":"GB",
    "sg:address":"Quarry Farm, Trough La",
    "sg:city":"Pontefract",
    "sg:classifiers":[
        {
            "category":"Shopping",
            "subcategory":"Pets & Pet Supplies",
            "type":"Retail Goods"
        }
    ],
    "sg:phone":"+44 1977 648421",
    "sg:postcode":"WF9 2SX",
    "sg:province":"West Yorkshire",
    "sg:tags":[
        "food"
    ],
    "wof:name":"Hilltop Feeds & Equestrian Supplies",
    "wof:placetype":"venue"
},
  "geometry": {"coordinates":[-1.2691,53.59655],"type":"Point"}
}