{
  "type": "Feature",
  "properties": {
    "addr:full":"16 Dobney Avenue, Queniborough Leicester Leicestershire LE7 3FF",
    "addr:housenumber":"16",
    "addr:postcode":"le7 3ff",
    "addr:street":"Dobney Avenue",
    "iso:country":"GB",
    "sg:address":"16 Dobney Avenue, Queniborough",
    "sg:city":"Leicester",
    "sg:classifiers":[
        {
            "category":"Professional",
            "subcategory":"Accounting & Tax Preparation",
            "type":"Services"
        }
    ],
    "sg:postcode":"LE7 3FF",
    "sg:province":"Leicestershire",
    "sg:tags":[
        "accountant"
    ],
    "wof:name":"A J S Accountancy Services Ltd.",
    "wof:placetype":"venue"
},
  "geometry": {"coordinates":[-1.0615249872,52.7065734863],"type":"Point"}
}