{
  "type": "Feature",
  "properties": {
    "addr:full":"16a Hospital Street Nantwich Cheshire CW5 5RJ",
    "addr:housenumber":"16a",
    "addr:postcode":"cw5 5rj",
    "addr:street":"Hospital Street",
    "iso:country":"GB",
    "sg:address":"16a Hospital Street",
    "sg:city":"Nantwich",
    "sg:classifiers":[
        {
            "category":"Shopping",
            "subcategory":"Baby Store",
            "type":"Retail Goods"
        }
    ],
    "sg:phone":"+44 1270 610667",
    "sg:postcode":"CW5 5RJ",
    "sg:province":"Cheshire",
    "sg:tags":[
        "babywear",
        "childrens"
    ],
    "wof:name":"Sarah'n'dippity",
    "wof:placetype":"venue"
},
  "geometry": {"coordinates":[-2.521294117,53.0663032532],"type":"Point"}
}