{
  "type": "Feature",
  "properties": {
    "addr:full":"Phoenix Yard, Alexandra Road Basingstoke Hampshire RG21 7RQ",
    "addr:postcode":"rg21 7rq",
    "addr:street":"Alexandra Road",
    "iso:country":"GB",
    "sg:address":"Phoenix Yard, Alexandra Road",
    "sg:city":"Basingstoke",
    "sg:classifiers":[
        {
            "category":"Professional",
            "subcategory":"Engineering",
            "type":"Services"
        }
    ],
    "sg:phone":"+44 1256 320875",
    "sg:postcode":"RG21 7RQ",
    "sg:province":"Hampshire",
    "sg:tags":[
        "gas",
        "engineer"
    ],
    "wof:name":"Horton Gas Services Ltd.",
    "wof:placetype":"venue"
},
  "geometry": {"coordinates":[-1.083088994,51.2624435425],"type":"Point"}
}