{
  "type": "Feature",
  "properties": {
    "addr:full":"152 Walkden Road Manchester Greater Manchester M28 7DP",
    "addr:housenumber":"152",
    "addr:postcode":"m28 7dp",
    "addr:street":"Walkden Road",
    "iso:country":"GB",
    "sg:address":"152 Walkden Road",
    "sg:city":"Manchester",
    "sg:classifiers":[
        {
            "category":"Manufacturing",
            "subcategory":"Buildings",
            "type":"Manufacturing & Wholesale Goods"
        }
    ],
    "sg:phone":"+44 161 703 8793",
    "sg:postcode":"M28 7DP",
    "sg:province":"Greater Manchester",
    "sg:tags":[
        "portable"
    ],
    "wof:name":"Swift Loos",
    "wof:placetype":"venue"
},
  "geometry": {"coordinates":[-2.3964939117,53.5187606812],"type":"Point"}
}