{
  "type": "Feature",
  "properties": {
    "addr:full":"25 Waterbeech Drive Southampton Hampshire SO30 4NH",
    "addr:housenumber":"25",
    "addr:postcode":"so30 4nh",
    "addr:street":"Waterbeech Drive",
    "iso:country":"GB",
    "sg:address":"25 Waterbeech Drive",
    "sg:city":"Southampton",
    "sg:classifiers":[
        {
            "category":"Home & Garden",
            "subcategory":"Building Materials",
            "type":"Retail Goods"
        }
    ],
    "sg:phone":"+44 1489 785093",
    "sg:postcode":"SO30 4NH",
    "sg:province":"Hampshire",
    "sg:tags":[
        "polythene",
        "plastic"
    ],
    "wof:name":"N K A Trading Co",
    "wof:placetype":"venue"
},
  "geometry": {"coordinates":[-1.301574,50.921761],"type":"Point"}
}