{
  "type": "Feature",
  "properties": {
    "iso:country":"GB",
    "sg:address":"Suite A Unit 7, Barnfield Road",
    "sg:city":"Swindon",
    "sg:classifiers":[
        {
            "category":"Building & Trades",
            "subcategory":"Construction",
            "type":"Services"
        }
    ],
    "sg:phone":"+44 1793 484044",
    "sg:postcode":"SN2 2DJ",
    "sg:province":"Wiltshire",
    "sg:tags":[
        "builder"
    ],
    "wof:name":"Custom Homes (Uk) Ltd.",
    "wof:placetype":"venue"
},
  "geometry": {"coordinates":[-1.8097100258,51.5680007935],"type":"Point"}
}