{
  "type": "Feature",
  "properties": {
    "addr:full":"Unit 1, Holsworth Park Shrewsbury Shropshire SY3 5HJ",
    "addr:housenumber":"unit 1",
    "addr:postcode":"sy3 5hj",
    "addr:street":"Holsworth Park",
    "iso:country":"GB",
    "sg:address":"Unit 1, Holsworth Park",
    "sg:city":"Shrewsbury",
    "sg:classifiers":[
        {
            "category":"Farming",
            "subcategory":"Nursery",
            "type":"Manufacturing & Wholesale Goods"
        }
    ],
    "sg:postcode":"SY3 5HJ",
    "sg:province":"Shropshire",
    "sg:tags":[
        "creche"
    ],
    "wof:name":"Earlyworld Nursery & Pre-School",
    "wof:placetype":"venue"
},
  "geometry": {"coordinates":[-2.797394,52.715405],"type":"Point"}
}