{
  "type": "Feature",
  "properties": {
    "addr:full":"105 Rownhams Rd Southampton Hampshire SO16 5EB",
    "addr:housenumber":"105",
    "addr:postcode":"so16 5eb",
    "addr:street":"Rownhams Rd",
    "iso:country":"GB",
    "sg:address":"105 Rownhams Rd",
    "sg:city":"Southampton",
    "sg:classifiers":[
        {
            "category":"Real Estate",
            "subcategory":"Real Estate Agent",
            "type":"Services"
        }
    ],
    "sg:postcode":"SO16 5EB",
    "sg:province":"Hampshire",
    "wof:name":"Scaiff & Co Property Management",
    "wof:placetype":"venue"
},
  "geometry": {"coordinates":[-1.4471969604,50.9361915588],"type":"Point"}
}