{
  "type": "Feature",
  "properties": {
    "addr:full":"Unit 12b, Seedhill Rd Paisley Renfrewshire PA1 1TJ",
    "addr:housenumber":"unit 12b",
    "addr:postcode":"pa1 1tj",
    "addr:street":"Seedhill Rd",
    "iso:country":"GB",
    "sg:address":"Unit 12b, Seedhill Rd",
    "sg:city":"Paisley",
    "sg:classifiers":[
        {
            "category":"Shopping",
            "subcategory":"Hobbies, Toys, & Games",
            "type":"Retail Goods"
        }
    ],
    "sg:phone":"+44 141 561 2394",
    "sg:postcode":"PA1 1TJ",
    "sg:province":"Renfrewshire",
    "sg:tags":[
        "toy"
    ],
    "wof:name":"Clyde Steamer Models",
    "wof:placetype":"venue"
},
  "geometry": {"coordinates":[-4.415611,55.843311],"type":"Point"}
}