{
  "type": "Feature",
  "properties": {
    "addr:full":"Frimley Business Park Camberley Hampshire GU16 7SR",
    "addr:postcode":"gu16 7sr",
    "iso:country":"GB",
    "sg:address":"Frimley Business Park",
    "sg:city":"Camberley",
    "sg:classifiers":[
        {
            "category":"Shopping",
            "subcategory":"Pharmacy",
            "type":"Retail Goods"
        }
    ],
    "sg:phone":"+44 1276 692255",
    "sg:postcode":"GU16 7SR",
    "sg:province":"Hampshire",
    "sg:tags":[
        "pharmaceutical"
    ],
    "wof:name":"Novartis Pharmaceuticals U K Ltd.",
    "wof:placetype":"venue"
},
  "geometry": {"coordinates":[-0.745279,51.313259],"type":"Point"}
}