{
  "type": "Feature",
  "properties": {
    "addr:full":"Usk Rd Newport Monmouthshire NP18 1LN",
    "addr:postcode":"np18 1ln",
    "addr:street":"Usk Rd",
    "iso:country":"GB",
    "sg:address":"Usk Rd",
    "sg:city":"Newport",
    "sg:classifiers":[
        {
            "category":"Home & Garden",
            "subcategory":"Garden Supply",
            "type":"Retail Goods"
        }
    ],
    "sg:postcode":"NP18 1LN",
    "sg:province":"Monmouthshire",
    "sg:tags":[
        "nursery",
        "centre"
    ],
    "wof:name":"Asquith,John,",
    "wof:placetype":"venue"
},
  "geometry": {"coordinates":[-2.9513390064,51.6154403687],"type":"Point"}
}