{
  "type": "Feature",
  "properties": {
    "addr:full":"Barge Leslice, Lower Mall, Hummerfield London Greater London W5 1JX",
    "addr:postcode":"w5 1jx",
    "addr:street":"Lower Mall",
    "iso:country":"GB",
    "sg:address":"Barge Leslice, Lower Mall, Hummerfield",
    "sg:city":"London",
    "sg:classifiers":[
        {
            "category":"Professional",
            "subcategory":"Printing & Photocopies",
            "type":"Services"
        }
    ],
    "sg:phone":"+44 20 8563 0995",
    "sg:postcode":"W5 1JX",
    "sg:province":"Greater London",
    "sg:tags":[
        "printer"
    ],
    "wof:name":"Dolphin T-Shirt Printers",
    "wof:placetype":"venue"
},
  "geometry": {"coordinates":[-0.30045,51.5261],"type":"Point"}
}