{
  "type": "Feature",
  "properties": {
    "addr:full":"11 Atholl Crescent Edinburgh City of Edinburgh EH3 8HE",
    "addr:housenumber":"11",
    "addr:postcode":"eh3 8he",
    "addr:street":"Atholl Crescent",
    "iso:country":"GB",
    "sg:address":"11 Atholl Crescent",
    "sg:city":"Edinburgh",
    "sg:classifiers":[
        {
            "category":"Professional",
            "subcategory":"Lawyer & Legal Services",
            "type":"Services"
        }
    ],
    "sg:phone":"+44 131 229 1212",
    "sg:postcode":"EH3 8HE",
    "sg:province":"City of Edinburgh",
    "sg:tags":[
        "solicitor"
    ],
    "wof:name":"Lindsays W S",
    "wof:placetype":"venue"
},
  "geometry": {"coordinates":[-3.2118570805,55.9479064941],"type":"Point"}
}