{
  "type": "Feature",
  "properties": {
    "addr:full":"47 Dean St West End Greater London W1D 5BE",
    "addr:housenumber":"47",
    "addr:postcode":"w1d 5be",
    "addr:street":"Dean St",
    "iso:country":"GB",
    "sg:address":"47 Dean St",
    "sg:city":"West End",
    "sg:classifiers":[
        {
            "category":"Shopping",
            "subcategory":"Stationery & Office Supplies",
            "type":"Retail Goods"
        }
    ],
    "sg:phone":"+44 20 7734 9995",
    "sg:postcode":"W1D 5BE",
    "sg:province":"Greater London",
    "sg:tags":[
        "item",
        "promotional"
    ],
    "wof:name":"M C S Promotional Merchandsing",
    "wof:placetype":"venue"
},
  "geometry": {"coordinates":[-0.131892,51.513081],"type":"Point"}
}