{
  "type": "Feature",
  "properties": {
    "iso:country":"GB",
    "sg:address":"Park Gate, 21 Tothill Street, Westminster",
    "sg:city":"London",
    "sg:classifiers":[
        {
            "category":"Professional",
            "subcategory":"Research",
            "type":"Services"
        }
    ],
    "sg:phone":"+44 20 7222 8033",
    "sg:postcode":"SW1H 9LL",
    "sg:province":"Greater London",
    "sg:tags":[
        "actuary"
    ],
    "wof:name":"Wyatt Financial Services Ltd.",
    "wof:placetype":"venue"
},
  "geometry": {"coordinates":[-0.1307930052,51.4998474121],"type":"Point"}
}