{
  "type": "Feature",
  "properties": {
    "addr:full":"7 Welford Road, Shirley Solihull West Midlands B90 3HX",
    "addr:housenumber":"7",
    "addr:postcode":"b90 3hx",
    "addr:street":"Welford Road",
    "iso:country":"GB",
    "sg:address":"7 Welford Road, Shirley",
    "sg:city":"Solihull",
    "sg:classifiers":[
        {
            "category":"Professional",
            "subcategory":"Lawyer & Legal Services",
            "type":"Services"
        }
    ],
    "sg:phone":"+44 121 744 2003",
    "sg:postcode":"B90 3HX",
    "sg:province":"West Midlands",
    "sg:tags":[
        "solicitor"
    ],
    "wof:name":"McCready & Co",
    "wof:placetype":"venue"
},
  "geometry": {"coordinates":[-1.8258349895,52.4135551453],"type":"Point"}
}