{
  "type": "Feature",
  "properties": {
    "addr:full":"Huntick Lodge, Huntick Road, Lytchett Matravers Poole Dorset BH16 6BB",
    "addr:postcode":"bh16 6bb",
    "addr:street":"Huntick Road",
    "iso:country":"GB",
    "sg:address":"Huntick Lodge, Huntick Road, Lytchett Matravers",
    "sg:city":"Poole",
    "sg:classifiers":[
        {
            "category":"Professional",
            "subcategory":"Art Services",
            "type":"Services"
        },
        {
            "category":"Building & Trades",
            "subcategory":"Construction",
            "type":"Services"
        }
    ],
    "sg:phone":"+44 1202 622374",
    "sg:postcode":"BH16 6BB",
    "sg:province":"Dorset",
    "sg:tags":[
        "decorator",
        "painter"
    ],
    "wof:name":"A FRANCE",
    "wof:placetype":"venue"
},
  "geometry": {"coordinates":[-2.077644,50.756245],"type":"Point"}
}