{
  "type": "Feature",
  "properties": {
    "addr:full":"Sandy Lane, Cottam Preston Lancashire PR4 0LE",
    "addr:postcode":"pr4 0le",
    "addr:street":"Sandy Lane",
    "iso:country":"GB",
    "sg:address":"Sandy Lane, Cottam",
    "sg:city":"Preston",
    "sg:classifiers":[
        {
            "category":"Farming",
            "subcategory":"Nursery",
            "type":"Manufacturing & Wholesale Goods"
        },
        {
            "category":"Education",
            "subcategory":"Preschool",
            "type":"Public Place"
        }
    ],
    "sg:phone":"+44 1772 728035",
    "sg:postcode":"PR4 0LE",
    "sg:province":"Lancashire",
    "sg:tags":[
        "school",
        "creche"
    ],
    "wof:name":"Cottam Nursery School",
    "wof:placetype":"venue"
},
  "geometry": {"coordinates":[-2.7593491077,53.78956604],"type":"Point"}
}