{
  "type": "Feature",
  "properties": {
    "addr:full":"Kiplin Hall Quarry, Kiplin Richmond North Yorkshire DL10 6AT",
    "addr:postcode":"dl10 6at",
    "addr:street":"Yorkshire",
    "iso:country":"GB",
    "sg:address":"Kiplin Hall Quarry, Kiplin",
    "sg:city":"Richmond",
    "sg:classifiers":[
        {
            "category":"Home & Garden",
            "subcategory":"Garden Supply",
            "type":"Retail Goods"
        }
    ],
    "sg:phone":"+44 1748 812115",
    "sg:postcode":"DL10 6AT",
    "sg:province":"North Yorkshire",
    "sg:tags":[
        "sand",
        "gravel"
    ],
    "wof:name":"Lafarge Aggregates Ltd.",
    "wof:placetype":"venue"
},
  "geometry": {"coordinates":[-1.565762043,54.3682403564],"type":"Point"}
}