{
  "type": "Feature",
  "properties": {
    "addr:full":"63 St Helens Park Rd Hastings East Sussex TN34 2JJ",
    "addr:housenumber":"63",
    "addr:postcode":"tn34 2jj",
    "addr:street":"St;Park Rd",
    "iso:country":"GB",
    "sg:address":"63 St Helens Park Rd",
    "sg:city":"Hastings",
    "sg:classifiers":[
        {
            "category":"Professional",
            "subcategory":"Lawyer & Legal Services",
            "type":"Services"
        }
    ],
    "sg:phone":"+44 1424 420140",
    "sg:postcode":"TN34 2JJ",
    "sg:province":"East Sussex",
    "sg:tags":[
        "advice",
        "counselling"
    ],
    "wof:name":"Joy Oakley",
    "wof:placetype":"venue"
},
  "geometry": {"coordinates":[0.5776169896,50.870098114],"type":"Point"}
}