{
  "type": "Feature",
  "properties": {
    "addr:full":"91 Vermont Street Glasgow Glasgow City G41 1LU",
    "addr:housenumber":"91",
    "addr:postcode":"g41 1lu",
    "addr:street":"Vermont Street",
    "iso:country":"GB",
    "sg:address":"91 Vermont Street",
    "sg:city":"Glasgow",
    "sg:classifiers":[
        {
            "category":"Building & Trades",
            "subcategory":"Construction",
            "type":"Services"
        }
    ],
    "sg:phone":"+44 141 249 1848",
    "sg:postcode":"G41 1LU",
    "sg:province":"Glasgow City",
    "sg:tags":[
        "builder"
    ],
    "wof:name":"Robert Gilchrist & Son Ltd.",
    "wof:placetype":"venue"
},
  "geometry": {"coordinates":[-4.2808408737,55.8488807678],"type":"Point"}
}