{
  "type": "Feature",
  "properties": {
    "addr:full":"12 Bryn Rd Wigan Lancashire WN4 0AA",
    "addr:housenumber":"12",
    "addr:postcode":"wn4 0aa",
    "addr:street":"Bryn Rd",
    "iso:country":"GB",
    "sg:address":"12 Bryn Rd",
    "sg:city":"Wigan",
    "sg:classifiers":[
        {
            "category":"Place Of Worship",
            "type":"Public Place"
        }
    ],
    "sg:phone":"+44 1942 727114",
    "sg:postcode":"WN4 0AA",
    "sg:province":"Lancashire",
    "wof:name":"St Peter C Of E Church",
    "wof:placetype":"venue"
},
  "geometry": {"coordinates":[-2.6447789669,53.5012893677],"type":"Point"}
}