{
  "type": "Feature",
  "properties": {
    "addr:full":"Sandstone, 9 Penkett Road Wallasey Merseyside CH45 7QF",
    "addr:housenumber":"9",
    "addr:postcode":"ch45 7qf",
    "addr:street":"Sandstone;Penkett Road",
    "iso:country":"GB",
    "sg:address":"Sandstone, 9 Penkett Road",
    "sg:city":"Wallasey",
    "sg:classifiers":[
        {
            "category":"Organizations",
            "subcategory":"Community Association",
            "type":"Services"
        }
    ],
    "sg:phone":"+44 151 691 1449",
    "sg:postcode":"CH45 7QF",
    "sg:province":"Merseyside",
    "sg:tags":[
        "co-operatives",
        "society",
        "housing",
        "trust"
    ],
    "wof:name":"Anchor Trust",
    "wof:placetype":"venue"
},
  "geometry": {"coordinates":[-3.03617,53.42543],"type":"Point"}
}