{
  "type": "Feature",
  "properties": {
    "addr:full":"66 Derby Road Bootle Merseyside L20 1AJ",
    "addr:housenumber":"66",
    "addr:postcode":"l20 1aj",
    "addr:street":"Derby Road",
    "iso:country":"GB",
    "sg:address":"66 Derby Road",
    "sg:city":"Bootle",
    "sg:classifiers":[
        {
            "category":"Manufacturing",
            "subcategory":"Buildings",
            "type":"Manufacturing & Wholesale Goods"
        }
    ],
    "sg:phone":"+44 151 922 8448",
    "sg:postcode":"L20 1AJ",
    "sg:province":"Merseyside",
    "sg:tags":[
        "portable"
    ],
    "wof:name":"Eagle Containers Ltd.",
    "wof:placetype":"venue"
},
  "geometry": {"coordinates":[-3.0012578964,53.4480171204],"type":"Point"}
}