{
  "type": "Feature",
  "properties": {
    "iso:country":"GB",
    "sg:address":"Green Shopping Centre, Berrymuir Road, Portlethen",
    "sg:city":"Aberdeen",
    "sg:classifiers":[
        {
            "category":"Food & Beverages",
            "subcategory":"Meat & Fish",
            "type":"Retail Goods"
        }
    ],
    "sg:phone":"+44 1224 783052",
    "sg:postcode":"AB1 4UF",
    "sg:province":"Aberdeen City",
    "sg:tags":[
        "chip"
    ],
    "wof:name":"Plaice Fish Bar & Pizzeria",
    "wof:placetype":"venue"
},
  "geometry": {"coordinates":[-2.13709,57.057941],"type":"Point"}
}