{
  "type": "Feature",
  "properties": {
    "addr:full":"33 Market Place, Tattershall Lincoln Lincolnshire LN4 4LJ",
    "addr:housenumber":"33",
    "addr:postcode":"ln4 4lj",
    "addr:street":"Market Place",
    "iso:country":"GB",
    "sg:address":"33 Market Place, Tattershall",
    "sg:city":"Lincoln",
    "sg:classifiers":[
        {
            "category":"Food & Beverages",
            "subcategory":"Supermarket",
            "type":"Retail Goods"
        }
    ],
    "sg:phone":"+44 1526 342251",
    "sg:postcode":"LN4 4LJ",
    "sg:province":"Lincolnshire",
    "wof:name":"Somerfield",
    "wof:placetype":"venue"
},
  "geometry": {"coordinates":[-0.1902389973,53.1046409607],"type":"Point"}
}