{
  "type": "Feature",
  "properties": {
    "addr:full":"4, Badbury Swindon Wiltshire SN4 0EU",
    "addr:housenumber":"4",
    "addr:postcode":"sn4 0eu",
    "addr:street":"Badbury Swindon",
    "iso:country":"GB",
    "sg:address":"4, Badbury",
    "sg:city":"Swindon",
    "sg:classifiers":[
        {
            "category":"Professional",
            "subcategory":"Computer Services",
            "type":"Services"
        }
    ],
    "sg:phone":"+44 1285 869100",
    "sg:postcode":"SN4 0EU",
    "sg:province":"Wiltshire",
    "sg:tags":[
        "system",
        "software"
    ],
    "wof:name":"Martcom Computer Solutions Ltd",
    "wof:placetype":"venue"
},
  "geometry": {"coordinates":[-1.7240890265,51.5261688232],"type":"Point"}
}