{
  "type": "Feature",
  "properties": {
    "iso:country":"GB",
    "sg:address":"Birmingham Road",
    "sg:city":"Walsall",
    "sg:classifiers":[
        {
            "category":"Travel",
            "subcategory":"Hotels & Motels",
            "type":"Entertainment"
        }
    ],
    "sg:postcode":"WS5 3AB",
    "sg:province":"West Midlands",
    "wof:name":"The Boundary",
    "wof:placetype":"venue"
},
  "geometry": {"coordinates":[-1.9579509497,52.5718421936],"type":"Point"}
}