{
  "type": "Feature",
  "properties": {
    "iso:country":"GB",
    "sg:address":"244 Nutgrove Road",
    "sg:city":"St Helens",
    "sg:classifiers":[
        {
            "category":"Military Area",
            "subcategory":"Air Force Base",
            "type":"Public Place"
        }
    ],
    "sg:postcode":"WA9 5JT",
    "sg:province":"Cheshire",
    "sg:tags":[
        "taxi",
        "hire",
        "private"
    ],
    "wof:name":"Star Taxis",
    "wof:placetype":"venue"
},
  "geometry": {"coordinates":[-2.7630040646,53.4303703308],"type":"Point"}
}