{
  "type": "Feature",
  "properties": {
    "iso:country":"GB",
    "sg:address":"Guild Street",
    "sg:city":"Stratford-upon-avon",
    "sg:classifiers":[
        {
            "category":"Autos & Motor Vehicles",
            "subcategory":"Auto Supplies",
            "type":"Retail Goods"
        }
    ],
    "sg:phone":"+44 1789 415855",
    "sg:postcode":"CV37 6YW",
    "sg:province":"Warwickshire",
    "sg:tags":[
        "exhaust",
        "absorber",
        "shock"
    ],
    "wof:name":"Kwik-Fit",
    "wof:placetype":"venue"
},
  "geometry": {"coordinates":[-1.7058340311,52.1937446594],"type":"Point"}
}