{
  "type": "Feature",
  "properties": {
    "iso:country":"GB",
    "sg:address":"56 Medeswell, Orton Malborne",
    "sg:city":"Peterborough",
    "sg:classifiers":[
        {
            "category":"Communications",
            "type":"Services"
        }
    ],
    "sg:phone":"+44 1733 236779",
    "sg:postcode":"PE2 5PA",
    "sg:province":"Cambridgeshire",
    "sg:tags":[
        "audio-visual"
    ],
    "wof:name":"Cine to Video",
    "wof:placetype":"venue"
},
  "geometry": {"coordinates":[-0.27332,52.54594],"type":"Point"}
}