{
  "type": "Feature",
  "properties": {
    "iso:country":"GB",
    "sg:address":"Buddle Arts Centre, Station Rd",
    "sg:city":"Wallsend",
    "sg:classifiers":[
        {
            "category":"Organizations",
            "subcategory":"Non-profit Organization",
            "type":"Services"
        }
    ],
    "sg:phone":"+44 191 200 7267",
    "sg:postcode":"NE28 8RH",
    "sg:province":"Tyne and Wear",
    "sg:tags":[
        "organisation",
        "voluntary",
        "charity"
    ],
    "wof:name":"Tyneside Disability Arts",
    "wof:placetype":"venue"
},
  "geometry": {"coordinates":[-1.53521,54.99424],"type":"Point"}
}