{
  "type": "Feature",
  "properties": {
    "addr:full":"182 Alma Road Bournemouth Dorset BH9 1AJ",
    "addr:housenumber":"182",
    "addr:postcode":"bh9 1aj",
    "addr:street":"Alma Road",
    "iso:country":"GB",
    "sg:address":"182 Alma Road",
    "sg:city":"Bournemouth",
    "sg:classifiers":[
        {
            "category":"Fast Food",
            "type":"Food & Drink"
        }
    ],
    "sg:postcode":"BH9 1AJ",
    "sg:province":"Dorset",
    "sg:tags":[
        "away",
        "take"
    ],
    "wof:name":"Sinbad Restaurant",
    "wof:placetype":"venue"
},
  "geometry": {"coordinates":[-1.8654010296,50.7371864319],"type":"Point"}
}