{
  "type": "Feature",
  "properties": {
    "iso:country":"GB",
    "sg:address":"Carter Lane, Queensbury",
    "sg:city":"Bradford",
    "sg:classifiers":[
        {
            "category":"Farming",
            "subcategory":"Livestock Farm",
            "type":"Manufacturing & Wholesale Goods"
        }
    ],
    "sg:phone":"+44 1274 882148",
    "sg:postcode":"BD13 1NJ",
    "sg:province":"West Yorkshire",
    "sg:tags":[
        "others"
    ],
    "wof:name":"Alan Webster",
    "wof:placetype":"venue"
},
  "geometry": {"coordinates":[-1.852412,53.775154],"type":"Point"}
}