{
  "type": "Feature",
  "properties": {
    "addr:full":"4 Vernon Road, Bredbury Stockport Cheshire SK6 2NU",
    "addr:housenumber":"4",
    "addr:postcode":"sk6 2nu",
    "addr:street":"Vernon Road",
    "iso:country":"GB",
    "sg:address":"4 Vernon Road, Bredbury",
    "sg:city":"Stockport",
    "sg:classifiers":[
        {
            "category":"Building & Trades",
            "subcategory":"Cleaning & Sanitation",
            "type":"Services"
        }
    ],
    "sg:postcode":"SK6 2NU",
    "sg:province":"Cheshire",
    "sg:tags":[
        "commercial"
    ],
    "wof:name":"Eric Patton",
    "wof:placetype":"venue"
},
  "geometry": {"coordinates":[-2.110054,53.420017],"type":"Point"}
}