{
  "type": "Feature",
  "properties": {
    "addr:full":"304-306 Ballards Lane London Greater London N12 0EY",
    "addr:postcode":"304-306;n12 0ey",
    "addr:street":"Ballards Lane",
    "iso:country":"GB",
    "sg:address":"304-306 Ballards Lane",
    "sg:city":"London",
    "sg:classifiers":[
        {
            "category":"Autos & Motor Vehicles",
            "subcategory":"Auto Supplies",
            "type":"Retail Goods"
        }
    ],
    "sg:phone":"+44 20 8446 7080",
    "sg:postcode":"N12 0EY",
    "sg:province":"Greater London",
    "sg:tags":[
        "tyre"
    ],
    "wof:name":"Northway Tyres",
    "wof:placetype":"venue"
},
  "geometry": {"coordinates":[-0.1785759926,51.6115150452],"type":"Point"}
}