{
  "type": "Feature",
  "properties": {
    "addr:full":"98 Monson Road Redhill Surrey RH1 2EY",
    "addr:housenumber":"98",
    "addr:postcode":"rh1 2ey",
    "addr:street":"Monson Road",
    "iso:country":"GB",
    "sg:address":"98 Monson Road",
    "sg:city":"Redhill",
    "sg:classifiers":[
        {
            "category":"Shopping",
            "subcategory":"News",
            "type":"Retail Goods"
        }
    ],
    "sg:postcode":"RH1 2EY",
    "sg:province":"Surrey",
    "sg:tags":[
        "newsagent"
    ],
    "wof:name":"MONSON ROAD GENERAL STORE",
    "wof:placetype":"venue"
},
  "geometry": {"coordinates":[-0.169791,51.252464],"type":"Point"}
}