{
  "type": "Feature",
  "properties": {
    "iso:country":"GB",
    "sg:address":"Head Office, 16 St Marys Gate",
    "sg:city":"Manchester",
    "sg:classifiers":[
        {
            "category":"Fast Food",
            "type":"Food & Drink"
        }
    ],
    "sg:phone":"+44 161 819 1201",
    "sg:postcode":"M1 1PX",
    "sg:province":"Greater Manchester",
    "sg:tags":[
        "away",
        "take"
    ],
    "wof:name":"Feed The 5 Thousand",
    "wof:placetype":"venue"
},
  "geometry": {"coordinates":[-2.2458000183,53.4830818176],"type":"Point"}
}