{
  "type": "Feature",
  "properties": {
    "iso:country":"GB",
    "sg:address":"Darwin House, Southernhay Gardens",
    "sg:city":"Exeter",
    "sg:classifiers":[
        {
            "category":"Building & Trades",
            "subcategory":"Landscaping Services",
            "type":"Services"
        }
    ],
    "sg:postcode":"EX1 1LA",
    "sg:province":"Devon",
    "sg:tags":[
        "horticultural",
        "consultant"
    ],
    "wof:name":"West Country Compost Ltd.",
    "wof:placetype":"venue"
},
  "geometry": {"coordinates":[-3.525998,50.72131],"type":"Point"}
}