{
  "type": "Feature",
  "properties": {
    "addr:full":"55 Moss La Preston Lancashire PR4 6AA",
    "addr:housenumber":"55",
    "addr:postcode":"pr4 6aa",
    "addr:street":"Moss La Preston",
    "iso:country":"GB",
    "sg:address":"55 Moss La",
    "sg:city":"Preston",
    "sg:classifiers":[
        {
            "category":"Home & Garden",
            "subcategory":"Garden Supply",
            "type":"Retail Goods"
        }
    ],
    "sg:phone":"+44 1772 814656",
    "sg:postcode":"PR4 6AA",
    "sg:province":"Lancashire",
    "sg:tags":[
        "nursery",
        "centre"
    ],
    "wof:name":"Hollybank Nurseries",
    "wof:placetype":"venue"
},
  "geometry": {"coordinates":[-2.84278,53.697086],"type":"Point"}
}