{
  "type": "Feature",
  "properties": {
    "addr:full":"20 Lansdowne Rd Aldershot Hampshire GU11 3ER",
    "addr:housenumber":"20",
    "addr:postcode":"gu11 3er",
    "addr:street":"Lansdowne Rd",
    "iso:country":"GB",
    "sg:address":"20 Lansdowne Rd",
    "sg:city":"Aldershot",
    "sg:classifiers":[
        {
            "category":"Professional",
            "subcategory":"Secretarial Services",
            "type":"Services"
        }
    ],
    "sg:phone":"+44 1252 660284",
    "sg:postcode":"GU11 3ER",
    "sg:province":"Hampshire",
    "wof:name":"The Write Step",
    "wof:placetype":"venue"
},
  "geometry": {"coordinates":[-0.7680100203,51.2458877563],"type":"Point"}
}