{
  "type": "Feature",
  "properties": {
    "addr:full":"9d Park Road Lytham St Annes Lancashire FY8 1QX",
    "addr:housenumber":"9d",
    "addr:postcode":"fy8 1qx",
    "addr:street":"Park Road",
    "iso:country":"GB",
    "sg:address":"9d Park Road",
    "sg:city":"Lytham St Annes",
    "sg:classifiers":[
        {
            "category":"Shopping",
            "subcategory":"Comic Books",
            "type":"Retail Goods"
        }
    ],
    "sg:phone":"+44 1253 721719",
    "sg:postcode":"FY8 1QX",
    "sg:province":"Lancashire",
    "sg:tags":[
        "jeweller"
    ],
    "wof:name":"Thompson Jewellers",
    "wof:placetype":"venue"
},
  "geometry": {"coordinates":[-3.029017,53.751282],"type":"Point"}
}