{
  "type": "Feature",
  "properties": {
    "addr:full":"Oak Lodge Farm, Leighams Rd Chelmsford Essex CM3 4HF",
    "addr:postcode":"cm3 4hf",
    "addr:street":"Leighams Rd",
    "iso:country":"GB",
    "sg:address":"Oak Lodge Farm, Leighams Rd",
    "sg:city":"Chelmsford",
    "sg:classifiers":[
        {
            "category":"Communications",
            "subcategory":"Film & Video Production",
            "type":"Services"
        }
    ],
    "sg:phone":"+44 1245 323382",
    "sg:postcode":"CM3 4HF",
    "sg:province":"Essex",
    "sg:tags":[
        "recording",
        "studio"
    ],
    "wof:name":"Diploma Studios Ltd",
    "wof:placetype":"venue"
},
  "geometry": {"coordinates":[0.555678,51.728619],"type":"Point"}
}