{
  "type": "Feature",
  "properties": {
    "addr:full":"Old Sarum Park Salisbury Hampshire SP4 6EB",
    "addr:postcode":"sp4 6eb",
    "iso:country":"GB",
    "sg:address":"Old Sarum Park",
    "sg:city":"Salisbury",
    "sg:classifiers":[
        {
            "category":"Autos & Motor Vehicles",
            "subcategory":"Automobile Sales",
            "type":"Retail Goods"
        }
    ],
    "sg:phone":"+44 1722 414400",
    "sg:postcode":"SP4 6EB",
    "sg:province":"Hampshire",
    "sg:tags":[
        "car"
    ],
    "wof:name":"Otton Brothers Ltd.",
    "wof:placetype":"venue"
},
  "geometry": {"coordinates":[-1.7969540358,51.0980911255],"type":"Point"}
}