{
  "type": "Feature",
  "properties": {
    "addr:full":"6/8 Maddox Street London Greater London W1S 1NR",
    "addr:housenumber":"6 / 8",
    "addr:postcode":"w1s 1nr",
    "addr:street":"Maddox Street",
    "iso:country":"GB",
    "sg:address":"6/8 Maddox Street",
    "sg:city":"London",
    "sg:classifiers":[
        {
            "category":"Real Estate",
            "subcategory":"Surveying",
            "type":"Services"
        }
    ],
    "sg:phone":"+44 20 7495 1971",
    "sg:postcode":"W1S 1NR",
    "sg:province":"Greater London",
    "sg:tags":[
        "surveyor",
        "valuer"
    ],
    "wof:name":"Mason & Partners Ltd.",
    "wof:placetype":"venue"
},
  "geometry": {"coordinates":[-0.1416539997,51.5136451721],"type":"Point"}
}