{
  "type": "Feature",
  "properties": {
    "addr:full":"211 Camberwell Road London Greater London SE5 0HG",
    "addr:housenumber":"211",
    "addr:postcode":"se5 0hg",
    "addr:street":"Camberwell Road",
    "iso:country":"GB",
    "sg:address":"211 Camberwell Road",
    "sg:city":"London",
    "sg:classifiers":[
        {
            "category":"Shopping",
            "subcategory":"News",
            "type":"Retail Goods"
        }
    ],
    "sg:phone":"+44 20 7703 6783",
    "sg:postcode":"SE5 0HG",
    "sg:province":"Greater London",
    "sg:tags":[
        "newsagent"
    ],
    "wof:name":"Amin News",
    "wof:placetype":"venue"
},
  "geometry": {"coordinates":[-0.101946,51.477856],"type":"Point"}
}