{
  "type": "Feature",
  "properties": {
    "iso:country":"GB",
    "sg:address":"36 North St",
    "sg:city":"Wareham",
    "sg:classifiers":[
        {
            "category":"Manufacturing",
            "subcategory":"Pottery",
            "type":"Manufacturing & Wholesale Goods"
        }
    ],
    "sg:phone":"+44 1929 552146",
    "sg:postcode":"BH20 4AW",
    "sg:province":"Dorset",
    "sg:tags":[
        "product",
        "clay"
    ],
    "wof:name":"E C C Ball Clays",
    "wof:placetype":"venue"
},
  "geometry": {"coordinates":[-2.1110599041,50.6883468628],"type":"Point"}
}