{
  "type": "Feature",
  "properties": {
    "iso:country":"GB",
    "sg:address":"36 Western Road",
    "sg:city":"Hove",
    "sg:classifiers":[
        {
            "category":"Shopping",
            "subcategory":"News",
            "type":"Retail Goods"
        }
    ],
    "sg:phone":"+44 1273 731467",
    "sg:postcode":"BN3 1AF",
    "sg:province":"East Sussex",
    "sg:tags":[
        "newsagent"
    ],
    "wof:name":"Jayambe Newsagents",
    "wof:placetype":"venue"
},
  "geometry": {"coordinates":[-0.159567,50.825657],"type":"Point"}
}