{
  "type": "Feature",
  "properties": {
    "iso:country":"GB",
    "sg:address":"36 Lilac Avenue",
    "sg:city":"Sutton Coldfield",
    "sg:classifiers":[
        {
            "category":"Building & Trades",
            "subcategory":"Electrical",
            "type":"Services"
        }
    ],
    "sg:phone":"+44 121 352 1039",
    "sg:postcode":"B74 3TF",
    "sg:province":"Staffordshire",
    "sg:tags":[
        "lighting"
    ],
    "wof:name":"Clear Vision Lighting Virtual Daylight Ltd",
    "wof:placetype":"venue"
},
  "geometry": {"coordinates":[-1.89404,52.575775],"type":"Point"}
}