{
  "type": "Feature",
  "properties": {
    "iso:country":"GB",
    "sg:address":"17 Parkhurst Road",
    "sg:city":"London",
    "sg:classifiers":[
        {
            "category":"Building & Trades",
            "subcategory":"Construction",
            "type":"Services"
        }
    ],
    "sg:postcode":"N17 9RB",
    "sg:province":"Greater London",
    "sg:tags":[
        "equipment"
    ],
    "wof:name":"Pipeprince Ltd",
    "wof:placetype":"venue"
},
  "geometry": {"coordinates":[-0.065953,51.595345],"type":"Point"}
}