{
  "type": "Feature",
  "properties": {
    "addr:full":"The Brighton Newcastle Staffordshire ST5 6JR",
    "addr:postcode":"st5 6jr",
    "iso:country":"GB",
    "sg:address":"The Brighton",
    "sg:city":"Newcastle",
    "sg:classifiers":[
        {
            "category":"Social Services",
            "subcategory":"Adult Care",
            "type":"Services"
        }
    ],
    "sg:phone":"+44 1782 622200",
    "sg:postcode":"ST5 6JR",
    "sg:province":"Staffordshire",
    "sg:tags":[
        "housing",
        "sheltered"
    ],
    "wof:name":"The Brighton Sheltered Housing",
    "wof:placetype":"venue"
},
  "geometry": {"coordinates":[-2.274439,53.017178],"type":"Point"}
}