{
  "type": "Feature",
  "properties": {
    "addr:full":"Woodlane House, Wood Lane Shipston-on-stour Warwickshire CV36 5HY",
    "addr:postcode":"cv36 5hy",
    "addr:street":"Wood Lane",
    "iso:country":"GB",
    "sg:address":"Woodlane House, Wood Lane",
    "sg:city":"Shipston-on-stour",
    "sg:classifiers":[
        {
            "category":"Real Estate",
            "subcategory":"Surveying",
            "type":"Services"
        }
    ],
    "sg:postcode":"CV36 5HY",
    "sg:province":"Warwickshire",
    "sg:tags":[
        "surveyor",
        "valuer"
    ],
    "wof:name":"J David Armitage",
    "wof:placetype":"venue"
},
  "geometry": {"coordinates":[-1.5771529675,52.0258369446],"type":"Point"}
}