{
  "type": "Feature",
  "properties": {
    "addr:full":"Alton Chesterfield Derbyshire S42 6AW",
    "addr:postcode":"s42 6aw",
    "iso:country":"GB",
    "sg:address":"Alton",
    "sg:city":"Chesterfield",
    "sg:classifiers":[
        {
            "category":"Sports & Exercise",
            "subcategory":"Stables",
            "type":"Entertainment"
        }
    ],
    "sg:phone":"+44 1246 590267",
    "sg:postcode":"S42 6AW",
    "sg:province":"Derbyshire",
    "sg:tags":[
        "education",
        "equestrian"
    ],
    "wof:name":"Alton Riding School",
    "wof:placetype":"venue"
},
  "geometry": {"coordinates":[-1.4578000307,53.1747894287],"type":"Point"}
}