{
  "type": "Feature",
  "properties": {
    "iso:country":"GB",
    "sg:address":"Stamford New Road",
    "sg:city":"Altrincham",
    "sg:classifiers":[
        {
            "category":"Shopping",
            "subcategory":"News",
            "type":"Retail Goods"
        }
    ],
    "sg:phone":"+44 161 926 9411",
    "sg:postcode":"WA14 1EN",
    "sg:province":"Cheshire",
    "sg:tags":[
        "newsagent"
    ],
    "wof:name":"H & R Patel",
    "wof:placetype":"venue"
},
  "geometry": {"coordinates":[-2.348254,53.387589],"type":"Point"}
}