{
  "type": "Feature",
  "properties": {
    "addr:full":"14b Bayhead St Stornoway Eilean Siar HS1 2DU",
    "addr:housenumber":"14b",
    "addr:postcode":"hs1 2du",
    "addr:street":"Bayhead St",
    "iso:country":"GB",
    "sg:address":"14b Bayhead St",
    "sg:city":"Stornoway",
    "sg:classifiers":[
        {
            "category":"Banks & Credit Unions",
            "subcategory":"Financial Services",
            "type":"Services"
        }
    ],
    "sg:phone":"+44 1851 701170",
    "sg:postcode":"HS1 2DU",
    "sg:province":"Eilean Siar",
    "sg:tags":[
        "adviser"
    ],
    "wof:name":"Island Mortgage & Insurance Services",
    "wof:placetype":"venue"
},
  "geometry": {"coordinates":[-6.380339,58.213451],"type":"Point"}
}