{
  "type": "Feature",
  "properties": {
    "addr:full":"55 Littlepark Avenue, Bedhampton Havant Hampshire PO9 3QU",
    "addr:housenumber":"55",
    "addr:postcode":"po9 3qu",
    "addr:street":"Littlepark Avenue",
    "iso:country":"GB",
    "sg:address":"55 Littlepark Avenue, Bedhampton",
    "sg:city":"Havant",
    "sg:classifiers":[
        {
            "category":"Professional",
            "subcategory":"Engineering",
            "type":"Services"
        }
    ],
    "sg:postcode":"PO9 3QU",
    "sg:province":"Hampshire",
    "sg:tags":[
        "contractor",
        "electrical",
        "engineer"
    ],
    "wof:name":"T F Batchelor",
    "wof:placetype":"venue"
},
  "geometry": {"coordinates":[-1.0091990232,50.8598518372],"type":"Point"}
}