{
  "type": "Feature",
  "properties": {
    "addr:full":"Unit G4 Weston Street Bolton Lancashire BL3 2AW",
    "addr:housenumber":"g4",
    "addr:postcode":"bl3 2aw",
    "addr:street":"Weston Street",
    "iso:country":"GB",
    "sg:address":"Unit G4 Weston Street",
    "sg:city":"Bolton",
    "sg:classifiers":[
        {
            "category":"Building & Trades",
            "subcategory":"Equipment Rental",
            "type":"Services"
        }
    ],
    "sg:postcode":"BL3 2AW",
    "sg:province":"Lancashire",
    "sg:tags":[
        "plant",
        "machinery"
    ],
    "wof:name":"Alan Cross",
    "wof:placetype":"venue"
},
  "geometry": {"coordinates":[-2.417979002,53.5669898987],"type":"Point"}
}