{
  "type": "Feature",
  "properties": {
    "iso:country":"GB",
    "sg:address":"Hallam St",
    "sg:city":"West Bromwich",
    "sg:classifiers":[
        {
            "category":"Place Of Worship",
            "type":"Public Place"
        }
    ],
    "sg:phone":"+44 121 588 2563",
    "sg:postcode":"B71 4HE",
    "sg:province":"West Midlands",
    "wof:name":"Hallam Street Methodist Church",
    "wof:placetype":"venue"
},
  "geometry": {"coordinates":[-1.9868140221,52.5294799805],"type":"Point"}
}