{
  "type": "Feature",
  "properties": {
    "iso:country":"GB",
    "sg:address":"Middle Shadymoor Farm, Dorrington",
    "sg:city":"Shrewsbury",
    "sg:classifiers":[
        {
            "category":"Farming",
            "subcategory":"Livestock Farm",
            "type":"Manufacturing & Wholesale Goods"
        }
    ],
    "sg:postcode":"SY5 7LB",
    "sg:province":"Shropshire",
    "sg:tags":[
        "others"
    ],
    "wof:name":"R E & R M Beedles",
    "wof:placetype":"venue"
},
  "geometry": {"coordinates":[-2.773399,52.622414],"type":"Point"}
}