{
  "type": "Feature",
  "properties": {
    "addr:full":"5 Albany Parade, High Street Brentford Greater London TW8 0JW",
    "addr:housenumber":"5",
    "addr:postcode":"tw8 0jw",
    "addr:street":"Albany Parade High Street",
    "iso:country":"GB",
    "sg:address":"5 Albany Parade, High Street",
    "sg:city":"Brentford",
    "sg:classifiers":[
        {
            "category":"Shopping",
            "subcategory":"Discount & Variety Stores",
            "type":"Retail Goods"
        }
    ],
    "sg:phone":"+44 20 8560 6856",
    "sg:postcode":"TW8 0JW",
    "sg:province":"Greater London",
    "sg:tags":[
        "shop",
        "model"
    ],
    "wof:name":"Brentford Radio Control Centre",
    "wof:placetype":"venue"
},
  "geometry": {"coordinates":[-0.302649,51.48531],"type":"Point"}
}