{
  "type": "Feature",
  "properties": {
    "addr:full":"The Veterinary Centre, City Road Truro Cornwall TR1 2JL",
    "addr:postcode":"tr1 2jl",
    "addr:street":"City Road",
    "iso:country":"GB",
    "sg:address":"The Veterinary Centre, City Road",
    "sg:city":"Truro",
    "sg:classifiers":[
        {
            "category":"Retail",
            "subcategory":"Veterinary Services",
            "type":"Services"
        }
    ],
    "sg:phone":"+44 1872 273959",
    "sg:postcode":"TR1 2JL",
    "sg:province":"Cornwall",
    "sg:tags":[
        "surgeon"
    ],
    "wof:name":"Dyson Kingdon & Leedham",
    "wof:placetype":"venue"
},
  "geometry": {"coordinates":[-5.0536308289,50.2652397156],"type":"Point"}
}