{
  "type": "Feature",
  "properties": {
    "addr:full":"27th Floor Portland Ho, Stag Pl Westminster Greater London SW1E 5AY",
    "addr:postcode":"sw1e 5ay",
    "addr:street":"Stag Pl",
    "iso:country":"GB",
    "sg:address":"27th Floor Portland Ho, Stag Pl",
    "sg:city":"Westminster",
    "sg:classifiers":[
        {
            "category":"Food & Beverages",
            "subcategory":"Supermarket",
            "type":"Retail Goods"
        }
    ],
    "sg:phone":"+44 20 7411 5500",
    "sg:postcode":"SW1E 5AY",
    "sg:province":"Greater London",
    "sg:tags":[
        "frozen"
    ],
    "wof:name":"Booker PLC",
    "wof:placetype":"venue"
},
  "geometry": {"coordinates":[-0.1417739987,51.4968605042],"type":"Point"}
}