{
  "type": "Feature",
  "properties": {
    "iso:country":"GB",
    "sg:address":"7a Somervell Street",
    "sg:city":"Glasgow",
    "sg:classifiers":[
        {
            "category":"Retail",
            "subcategory":"Auto Repair",
            "type":"Services"
        }
    ],
    "sg:phone":"+44 141 641 5678",
    "sg:postcode":"G72 7EB",
    "sg:province":"South Lanarkshire",
    "sg:tags":[
        "modification",
        "garage"
    ],
    "wof:name":"I Wills Motors",
    "wof:placetype":"venue"
},
  "geometry": {"coordinates":[-4.1741,55.820721],"type":"Point"}
}