{
  "type": "Feature",
  "properties": {
    "iso:country":"GB",
    "sg:address":"25 Oldfield Circus",
    "sg:city":"Northolt",
    "sg:classifiers":[
        {
            "category":"Personal",
            "subcategory":"Beauty Salon",
            "type":"Services"
        }
    ],
    "sg:phone":"+44 20 8864 2372",
    "sg:postcode":"UB5 4RR",
    "sg:province":"Greater London",
    "sg:tags":[
        "lady",
        "hairdresser"
    ],
    "wof:name":"Steve Sergio Gents Hairdressers",
    "wof:placetype":"venue"
},
  "geometry": {"coordinates":[-0.3505240083,51.5524291992],"type":"Point"}
}