{
  "type": "Feature",
  "properties": {
    "addr:full":"19 Upper Craigs Stirling Stirling FK8 2DG",
    "addr:housenumber":"19",
    "addr:postcode":"fk8 2dg",
    "addr:street":"Upper Craigs",
    "iso:country":"GB",
    "sg:address":"19 Upper Craigs",
    "sg:city":"Stirling",
    "sg:classifiers":[
        {
            "category":"Health Services",
            "subcategory":"Dentist",
            "type":"Services"
        }
    ],
    "sg:phone":"+44 1786 464294",
    "sg:postcode":"FK8 2DG",
    "sg:province":"Stirling",
    "sg:tags":[
        "technician",
        "dental"
    ],
    "wof:name":"Alex Paterson",
    "wof:placetype":"venue"
},
  "geometry": {"coordinates":[-3.936175108,56.1164512634],"type":"Point"}
}