{
  "type": "Feature",
  "properties": {
    "addr:full":"Appointments, Borough Road Wakefield West Yorkshire WF1 3SW",
    "addr:postcode":"wf1 3sw",
    "addr:street":"Borough Road",
    "iso:country":"GB",
    "sg:address":"Appointments, Borough Road",
    "sg:city":"Wakefield",
    "sg:classifiers":[
        {
            "category":"Health Services",
            "subcategory":"Doctor",
            "type":"Services"
        },
        {
            "category":"Health Services",
            "subcategory":"Clinic",
            "type":"Services"
        }
    ],
    "sg:postcode":"WF1 3SW",
    "sg:province":"West Yorkshire",
    "sg:tags":[
        "nh",
        "practitioners"
    ],
    "wof:name":"The New Southgate Surgery",
    "wof:placetype":"venue"
},
  "geometry": {"coordinates":[-1.49576,53.69968],"type":"Point"}
}