{
  "type": "Feature",
  "properties": {
    "addr:full":"56 Crouch End Hill Hornsey Greater London N8 8AA",
    "addr:housenumber":"56",
    "addr:postcode":"n8 8aa",
    "addr:street":"Crouch",
    "iso:country":"GB",
    "sg:address":"56 Crouch End Hill",
    "sg:city":"Hornsey",
    "sg:classifiers":[
        {
            "category":"Home & Garden",
            "subcategory":"Garden Supply",
            "type":"Retail Goods"
        }
    ],
    "sg:phone":"+44 20 8341 3353",
    "sg:postcode":"N8 8AA",
    "sg:province":"Greater London",
    "sg:tags":[
        "nursery",
        "centre"
    ],
    "wof:name":"Adams",
    "wof:placetype":"venue"
},
  "geometry": {"coordinates":[-0.123954,51.578403],"type":"Point"}
}