{
  "type": "Feature",
  "properties": {
    "iso:country":"GB",
    "sg:address":"2 Church Street",
    "sg:city":"Diss",
    "sg:classifiers":[
        {
            "category":"Personal",
            "subcategory":"Beauty Salon",
            "type":"Services"
        },
        {
            "category":"Personal",
            "subcategory":"Barber",
            "type":"Services"
        }
    ],
    "sg:phone":"+44 1379 642860",
    "sg:postcode":"IP22 4DD",
    "sg:province":"Norfolk",
    "sg:tags":[
        "unisex",
        "hairdresser"
    ],
    "wof:name":"Dolphin House Hair Design",
    "wof:placetype":"venue"
},
  "geometry": {"coordinates":[1.110248,52.377129],"type":"Point"}
}