{
  "type": "Feature",
  "properties": {
    "addr:full":"252-258 North End Rd Fulham Greater London SW6 1NN",
    "addr:housenumber":"252-258",
    "addr:postcode":"sw6 1nn",
    "addr:street":"North End Rd",
    "iso:country":"GB",
    "sg:address":"252-258 North End Rd",
    "sg:city":"Fulham",
    "sg:classifiers":[
        {
            "category":"Personal",
            "subcategory":"Beauty Salon",
            "type":"Services"
        }
    ],
    "sg:phone":"+44 20 7381 9942",
    "sg:postcode":"SW6 1NN",
    "sg:province":"Greater London",
    "wof:name":"Beauty Co",
    "wof:placetype":"venue"
},
  "geometry": {"coordinates":[-0.202047,51.484474],"type":"Point"}
}