{
  "type": "Feature",
  "properties": {
    "iso:country":"GB",
    "sg:address":"2 Derby Road",
    "sg:city":"Swadlincote",
    "sg:classifiers":[
        {
            "category":"Autos & Motor Vehicles",
            "subcategory":"Motorcycle Sales",
            "type":"Retail Goods"
        }
    ],
    "sg:phone":"+44 1283 212455",
    "sg:postcode":"DE11 8EB",
    "sg:province":"Derbyshire",
    "wof:name":"Granville Motor Cycles",
    "wof:placetype":"venue"
},
  "geometry": {"coordinates":[-1.550009,52.770187],"type":"Point"}
}