{
  "type": "Feature",
  "properties": {
    "iso:country":"GB",
    "sg:address":"Hilton La",
    "sg:city":"Walsall",
    "sg:classifiers":[
        {
            "category":"Place Of Worship",
            "type":"Public Place"
        }
    ],
    "sg:phone":"+44 1922 419032",
    "sg:postcode":"WS6 6DS",
    "sg:province":"Staffordshire",
    "wof:name":"St Andrews C of E Church",
    "wof:placetype":"venue"
},
  "geometry": {"coordinates":[-2.0165760517,52.6566162109],"type":"Point"}
}