{
  "type": "Feature",
  "properties": {
    "addr:full":"Unit 8 & 10 Glanyllyn, Taffs Well Cardiff Caerphilly CF15 7QA",
    "addr:housenumber":"unit 8 & 10",
    "addr:postcode":"cf15 7qa",
    "iso:country":"GB",
    "sg:address":"Unit 8 & 10 Glanyllyn, Taffs Well",
    "sg:city":"Cardiff",
    "sg:classifiers":[
        {
            "category":"Shopping",
            "subcategory":"Pharmacy",
            "type":"Retail Goods"
        }
    ],
    "sg:postcode":"CF15 7QA",
    "sg:province":"Caerphilly",
    "sg:tags":[
        "pharmacist",
        "chemist"
    ],
    "wof:name":"Macton (South Wales) Ltd.",
    "wof:placetype":"venue"
},
  "geometry": {"coordinates":[-3.2703199387,51.5474090576],"type":"Point"}
}