{
  "type": "Feature",
  "properties": {
    "addr:full":"Mendip House, 24 Woodborough Road Winscombe Somerset BS25 1AD",
    "addr:housenumber":"24",
    "addr:postcode":"bs25 1ad",
    "addr:street":"Woodborough Road",
    "iso:country":"GB",
    "sg:address":"Mendip House, 24 Woodborough Road",
    "sg:city":"Winscombe",
    "sg:classifiers":[
        {
            "category":"Health Services",
            "subcategory":"Nursing And Care Facility",
            "type":"Services"
        }
    ],
    "sg:postcode":"BS25 1AD",
    "sg:province":"Somerset",
    "sg:tags":[
        "agency"
    ],
    "wof:name":"Mendip Nursing Services",
    "wof:placetype":"venue"
},
  "geometry": {"coordinates":[-2.8326098919,51.3145179749],"type":"Point"}
}