{
  "type": "Feature",
  "properties": {
    "iso:country":"GB",
    "sg:address":"34 Peverel Road",
    "sg:city":"Cambridge",
    "sg:classifiers":[
        {
            "category":"Building & Trades",
            "subcategory":"Construction",
            "type":"Services"
        }
    ],
    "sg:postcode":"CB5 8RH",
    "sg:province":"Cambridgeshire",
    "sg:tags":[
        "builder"
    ],
    "wof:name":"Gary O'Dell",
    "wof:placetype":"venue"
},
  "geometry": {"coordinates":[0.1643850058,52.2086524963],"type":"Point"}
}