{
  "type": "Feature",
  "properties": {
    "iso:country":"GB",
    "sg:address":"Unit 5 Greenwood Court, Ramridge Road",
    "sg:city":"Luton",
    "sg:classifiers":[
        {
            "category":"Professional",
            "subcategory":"Engineering",
            "type":"Services"
        }
    ],
    "sg:phone":"+44 1582 728880",
    "sg:postcode":"LU2 0TN",
    "sg:province":"Bedfordshire",
    "sg:tags":[
        "precision",
        "engineer"
    ],
    "wof:name":"Sunrise Cnc Engineering Ltd.",
    "wof:placetype":"venue"
},
  "geometry": {"coordinates":[-0.400774,51.892361],"type":"Point"}
}