{
  "type": "Feature",
  "properties": {
    "iso:country":"GB",
    "sg:address":"8 Coventry Road",
    "sg:city":"Market Harborough",
    "sg:classifiers":[
        {
            "category":"Professional",
            "subcategory":"Employment Agencies",
            "type":"Services"
        }
    ],
    "sg:phone":"+44 1858 473900",
    "sg:postcode":"LE16 9BZ",
    "sg:province":"Leicestershire",
    "sg:tags":[
        "consultant"
    ],
    "wof:name":"Employment Service Jobcentre",
    "wof:placetype":"venue"
},
  "geometry": {"coordinates":[-0.921653986,52.4778862],"type":"Point"}
}