{
  "type": "Feature",
  "properties": {
    "iso:country":"GB",
    "sg:address":"43 Westow Street",
    "sg:city":"London",
    "sg:classifiers":[
        {
            "category":"Personal",
            "subcategory":"Beauty Salon",
            "type":"Services"
        }
    ],
    "sg:phone":"+44 20 8653 7342",
    "sg:postcode":"SE19 3RW",
    "sg:province":"Greater London",
    "sg:tags":[
        "lady",
        "hairdresser"
    ],
    "wof:name":"Way Ahead",
    "wof:placetype":"venue"
},
  "geometry": {"coordinates":[-0.0817449987,51.4176712036],"type":"Point"}
}