{
  "type": "Feature",
  "properties": {
    "addr:full":"Brewery Road Woking Surrey GU21 4LH",
    "addr:postcode":"gu21 4lh",
    "addr:street":"Brewery Road",
    "iso:country":"GB",
    "sg:address":"Brewery Road",
    "sg:city":"Woking",
    "sg:classifiers":[
        {
            "category":"Place Of Worship",
            "type":"Public Place"
        }
    ],
    "sg:phone":"+44 1483 730733",
    "sg:postcode":"GU21 4LH",
    "sg:province":"Surrey",
    "wof:name":"Trinity Methodist Church",
    "wof:placetype":"venue"
},
  "geometry": {"coordinates":[-0.5608969927,51.3217430115],"type":"Point"}
}