{
  "type": "Feature",
  "properties": {
    "iso:country":"GB",
    "sg:address":"12 Moretons Clo",
    "sg:city":"Peterborough",
    "sg:classifiers":[
        {
            "category":"Shopping",
            "subcategory":"Catalog Store",
            "type":"Retail Goods"
        }
    ],
    "sg:phone":"+44 1733 205630",
    "sg:postcode":"PE7 1XP",
    "sg:province":"Cambridgeshire",
    "sg:tags":[
        "mail",
        "order"
    ],
    "wof:name":"Stewies Of Whittlesey",
    "wof:placetype":"venue"
},
  "geometry": {"coordinates":[-0.1132140011,52.5614242554],"type":"Point"}
}