{
  "type": "Feature",
  "properties": {
    "addr:full":"443-453 Bromley Rd Bromley Kent BR1 4PH",
    "addr:housenumber":"443-453",
    "addr:postcode":"br1 4ph",
    "addr:street":"Bromley Rd",
    "iso:country":"GB",
    "sg:address":"443-453 Bromley Rd",
    "sg:city":"Bromley",
    "sg:classifiers":[
        {
            "category":"Food & Beverages",
            "subcategory":"Supermarket",
            "type":"Retail Goods"
        }
    ],
    "sg:phone":"+44 20 8698 3330",
    "sg:postcode":"BR1 4PH",
    "sg:province":"Kent",
    "wof:name":"South East Co-op",
    "wof:placetype":"venue"
},
  "geometry": {"coordinates":[-0.0046060001,51.4253959656],"type":"Point"}
}