{
  "type": "Feature",
  "properties": {
    "iso:country":"GB",
    "sg:address":"50 Woodlands Cres",
    "sg:city":"Johnstone",
    "sg:classifiers":[
        {
            "category":"Building & Trades",
            "subcategory":"Construction",
            "type":"Services"
        }
    ],
    "sg:phone":"+44 1505 382376",
    "sg:postcode":"PA5 0AZ",
    "sg:province":"Renfrewshire",
    "sg:tags":[
        "decorator",
        "painter"
    ],
    "wof:name":"McLaughlin Decorators",
    "wof:placetype":"venue"
},
  "geometry": {"coordinates":[-4.5222220421,55.8239822388],"type":"Point"}
}