{
  "type": "Feature",
  "properties": {
    "iso:country":"GB",
    "sg:address":"Brookburn Road",
    "sg:city":"Manchester",
    "sg:classifiers":[
        {
            "category":"Organizations",
            "subcategory":"Membership Organization",
            "type":"Services"
        }
    ],
    "sg:postcode":"M21 9ES",
    "sg:province":"Cheshire",
    "sg:tags":[
        "club"
    ],
    "wof:name":"John Marshall",
    "wof:placetype":"venue"
},
  "geometry": {"coordinates":[-2.2831470966,53.4371032715],"type":"Point"}
}