{
  "type": "Feature",
  "properties": {
    "addr:full":"Palmon House, 128 Oxford Road Reading Berkshire RG1 7NL",
    "addr:housenumber":"128",
    "addr:postcode":"rg1 7nl",
    "addr:street":"Oxford Road",
    "iso:country":"GB",
    "sg:address":"Palmon House, 128 Oxford Road",
    "sg:city":"Reading",
    "sg:classifiers":[
        {
            "category":"Professional",
            "subcategory":"Accounting & Tax Preparation",
            "type":"Services"
        }
    ],
    "sg:postcode":"RG1 7NL",
    "sg:province":"Berkshire",
    "sg:tags":[
        "accountant"
    ],
    "wof:name":"Paul Gupta",
    "wof:placetype":"venue"
},
  "geometry": {"coordinates":[-0.98439,51.455326],"type":"Point"}
}