{
  "type": "Feature",
  "properties": {
    "addr:full":"2 Muiryhall Street Coatbridge North Lanarkshire ML5 3NA",
    "addr:housenumber":"2",
    "addr:postcode":"ml5 3na",
    "addr:street":"Muiryhall Street",
    "iso:country":"GB",
    "sg:address":"2 Muiryhall Street",
    "sg:city":"Coatbridge",
    "sg:classifiers":[
        {
            "category":"Government",
            "subcategory":"Customs House",
            "type":"Public Place"
        }
    ],
    "sg:phone":"+44 1236 433360",
    "sg:postcode":"ML5 3NA",
    "sg:province":"North Lanarkshire",
    "sg:tags":[
        "excise"
    ],
    "wof:name":"Customs & Excise",
    "wof:placetype":"venue"
},
  "geometry": {"coordinates":[-4.024805069,55.8632011414],"type":"Point"}
}