{
  "type": "Feature",
  "properties": {
    "iso:country":"GB",
    "sg:address":"38 Sheen Lane, East Sheen",
    "sg:city":"London",
    "sg:classifiers":[
        {
            "category":"Food & Beverages",
            "subcategory":"Meat & Fish",
            "type":"Retail Goods"
        }
    ],
    "sg:phone":"+44 20 8878 2865",
    "sg:postcode":"SW14 8LW",
    "sg:province":"Greater London",
    "sg:tags":[
        "chip"
    ],
    "wof:name":"Cathay Ho",
    "wof:placetype":"venue"
},
  "geometry": {"coordinates":[-0.2670530081,51.4666481018],"type":"Point"}
}