{
  "type": "Feature",
  "properties": {
    "addr:full":"81 Faulding Way Grimsby Lincolnshire DN37 9SD",
    "addr:housenumber":"81",
    "addr:postcode":"dn37 9sd",
    "addr:street":"Faulding Way",
    "iso:country":"GB",
    "sg:address":"81 Faulding Way",
    "sg:city":"Grimsby",
    "sg:classifiers":[
        {
            "category":"Professional",
            "subcategory":"Engineering",
            "type":"Services"
        }
    ],
    "sg:postcode":"DN37 9SD",
    "sg:province":"Lincolnshire",
    "sg:tags":[
        "contractor",
        "electrical",
        "engineer"
    ],
    "wof:name":"Bullivant Electrical",
    "wof:placetype":"venue"
},
  "geometry": {"coordinates":[-0.1396179944,53.5667991638],"type":"Point"}
}