{
  "type": "Feature",
  "properties": {
    "iso:country":"GB",
    "sg:address":"Lathom Rd",
    "sg:city":"East Ham",
    "sg:classifiers":[
        {
            "category":"Education",
            "subcategory":"School",
            "type":"Public Place"
        }
    ],
    "sg:phone":"+44 20 8472 0386",
    "sg:postcode":"E6 2DF",
    "sg:province":"Greater London",
    "sg:tags":[
        "local",
        "authority"
    ],
    "wof:name":"Lathom Junior School",
    "wof:placetype":"venue"
},
  "geometry": {"coordinates":[0.05889,51.5387763977],"type":"Point"}
}