{
  "type": "Feature",
  "properties": {
    "addr:full":"33 Southampton Road Ringwood Dorset BH24 1HB",
    "addr:housenumber":"33",
    "addr:postcode":"bh24 1hb",
    "addr:street":"Southampton Road",
    "iso:country":"GB",
    "sg:address":"33 Southampton Road",
    "sg:city":"Ringwood",
    "sg:classifiers":[
        {
            "category":"Shopping",
            "subcategory":"Clothing, Apparel, & Fashions",
            "type":"Retail Goods"
        }
    ],
    "sg:postcode":"BH24 1HB",
    "sg:province":"Dorset",
    "sg:tags":[
        "workwear",
        "protective"
    ],
    "wof:name":"Escape",
    "wof:placetype":"venue"
},
  "geometry": {"coordinates":[-1.790675,50.846989],"type":"Point"}
}