{
  "type": "Feature",
  "properties": {
    "addr:full":"471 London Rd Northwich Cheshire CW9 8NA",
    "addr:housenumber":"471",
    "addr:postcode":"cw9 8na",
    "addr:street":"London Rd",
    "iso:country":"GB",
    "sg:address":"471 London Rd",
    "sg:city":"Northwich",
    "sg:classifiers":[
        {
            "category":"Wholesale",
            "subcategory":"Toys & Hobbies",
            "type":"Manufacturing & Wholesale Goods"
        }
    ],
    "sg:phone":"+44 1606 49494",
    "sg:postcode":"CW9 8NA",
    "sg:province":"Cheshire",
    "sg:tags":[
        "balloon",
        "novelty"
    ],
    "wof:name":"Cards & Things",
    "wof:placetype":"venue"
},
  "geometry": {"coordinates":[-2.5126390457,53.2414512634],"type":"Point"}
}