{
  "type": "Feature",
  "properties": {
    "iso:country":"GB",
    "sg:address":"Widney Manor Road",
    "sg:city":"Solihull",
    "sg:classifiers":[
        {
            "category":"Education",
            "subcategory":"University",
            "type":"Public Place"
        },
        {
            "category":"Education",
            "subcategory":"School",
            "type":"Public Place"
        }
    ],
    "sg:phone":"+44 121 704 2581",
    "sg:postcode":"B91 3WR",
    "sg:province":"West Midlands",
    "sg:tags":[
        "local",
        "college",
        "authority"
    ],
    "wof:name":"Solihull Sixth Form College",
    "wof:placetype":"venue"
},
  "geometry": {"coordinates":[-1.775806,52.403065],"type":"Point"}
}