{
  "type": "Feature",
  "properties": {
    "iso:country":"GB",
    "sg:address":"1 George Centre, North Pde",
    "sg:city":"Matlock",
    "sg:classifiers":[
        {
            "category":"Food & Beverages",
            "subcategory":"Bakery",
            "type":"Retail Goods"
        }
    ],
    "sg:phone":"+44 1629 57773",
    "sg:postcode":"DE4 3NS",
    "sg:province":"Derbyshire",
    "sg:tags":[
        "baker"
    ],
    "wof:name":"Cakes Galore",
    "wof:placetype":"venue"
},
  "geometry": {"coordinates":[-1.548274,53.135616],"type":"Point"}
}