{
  "type": "Feature",
  "properties": {
    "iso:country":"GB",
    "sg:address":"East Muirlands Road",
    "sg:city":"Arbroath",
    "sg:classifiers":[
        {
            "category":"Professional",
            "subcategory":"Printing & Photocopies",
            "type":"Services"
        }
    ],
    "sg:phone":"+44 1241 870603",
    "sg:postcode":"DD11 3ES",
    "sg:province":"Angus",
    "sg:tags":[
        "printer"
    ],
    "wof:name":"Premier Printer Works",
    "wof:placetype":"venue"
},
  "geometry": {"coordinates":[-2.6097159386,56.5661087036],"type":"Point"}
}