{
  "type": "Feature",
  "properties": {
    "addr:full":"97 Westheath Road Farnborough Hampshire GU14 8QZ",
    "addr:housenumber":"97",
    "addr:postcode":"gu14 8qz",
    "addr:street":"Westheath Road",
    "iso:country":"GB",
    "sg:address":"97 Westheath Road",
    "sg:city":"Farnborough",
    "sg:classifiers":[
        {
            "category":"Professional",
            "subcategory":"Engineering",
            "type":"Services"
        }
    ],
    "sg:postcode":"GU14 8QZ",
    "sg:province":"Hampshire",
    "sg:tags":[
        "contractor",
        "electrical",
        "engineer"
    ],
    "wof:name":"M B Mackenzie Electrical Services",
    "wof:placetype":"venue"
},
  "geometry": {"coordinates":[-0.7640339732,51.2979507446],"type":"Point"}
}