{
  "type": "Feature",
  "properties": {
    "addr:full":"James Smith House, 11-15 Marlborough Road Sheffield South Yorkshire S10 1DA",
    "addr:housenumber":"11-15",
    "addr:postcode":"s10 1da",
    "addr:street":"Marlborough Road",
    "iso:country":"GB",
    "sg:address":"James Smith House, 11-15 Marlborough Road",
    "sg:city":"Sheffield",
    "sg:classifiers":[
        {
            "category":"Organizations",
            "subcategory":"Community Association",
            "type":"Services"
        }
    ],
    "sg:phone":"+44 114 266 2827",
    "sg:postcode":"S10 1DA",
    "sg:province":"South Yorkshire",
    "sg:tags":[
        "co-operatives",
        "society",
        "housing",
        "trust"
    ],
    "wof:name":"Abbeyfield Sheffield Hallam Society",
    "wof:placetype":"venue"
},
  "geometry": {"coordinates":[-1.4977920055,53.381023407],"type":"Point"}
}