{
  "type": "Feature",
  "properties": {
    "iso:country":"GB",
    "sg:address":"New Market House, Market Street",
    "sg:city":"Newbury",
    "sg:classifiers":[
        {
            "category":"Professional",
            "subcategory":"Business Services",
            "type":"Services"
        }
    ],
    "sg:phone":"+44 1635 36560",
    "sg:postcode":"RG14 5DP",
    "sg:province":"Berkshire",
    "sg:tags":[
        "planning",
        "supervisor"
    ],
    "wof:name":"King & Evans Partnership",
    "wof:placetype":"venue"
},
  "geometry": {"coordinates":[-1.324834,51.398991],"type":"Point"}
}