{
  "type": "Feature",
  "properties": {
    "addr:full":"New Street, North Wingfield Chesterfield Derbyshire S42 5JW",
    "addr:postcode":"s42 5jw",
    "addr:street":"New Street North",
    "iso:country":"GB",
    "sg:address":"New Street, North Wingfield",
    "sg:city":"Chesterfield",
    "sg:classifiers":[
        {
            "category":"Organizations",
            "subcategory":"Membership Organization",
            "type":"Services"
        }
    ],
    "sg:phone":"+44 1246 855399",
    "sg:postcode":"S42 5JW",
    "sg:province":"Derbyshire",
    "sg:tags":[
        "club"
    ],
    "wof:name":"Hepthorne Lane Evergreen Club",
    "wof:placetype":"venue"
},
  "geometry": {"coordinates":[-1.393624,53.201164],"type":"Point"}
}