{
  "type": "Feature",
  "properties": {
    "iso:country":"GB",
    "sg:address":"1490-2 London Rd, Norbury",
    "sg:city":"London",
    "sg:classifiers":[
        {
            "category":"Manufacturing",
            "subcategory":"Tools & Machinery",
            "type":"Manufacturing & Wholesale Goods"
        }
    ],
    "sg:postcode":"SW16 4BT",
    "sg:province":"Greater London",
    "sg:tags":[
        "society",
        "friendly"
    ],
    "wof:name":"Pullen,Dennis,",
    "wof:placetype":"venue"
},
  "geometry": {"coordinates":[-0.104356,51.498169],"type":"Point"}
}