{
  "type": "Feature",
  "properties": {
    "addr:full":"Jordan House, Foster Business Centre Durham Durham DH1 5HL",
    "addr:postcode":"dh1 5hl",
    "addr:street":"Foster",
    "iso:country":"GB",
    "sg:address":"Jordan House, Foster Business Centre",
    "sg:city":"Durham",
    "sg:classifiers":[
        {
            "category":"Organizations",
            "subcategory":"Non-profit Organization",
            "type":"Services"
        }
    ],
    "sg:phone":"+44 191 383 0055",
    "sg:postcode":"DH1 5HL",
    "sg:province":"Durham",
    "sg:tags":[
        "charitable",
        "organisation",
        "voluntary",
        "charity"
    ],
    "wof:name":"County Durham Foundation",
    "wof:placetype":"venue"
},
  "geometry": {"coordinates":[-1.574608,54.777534],"type":"Point"}
}