{
  "type": "Feature",
  "properties": {
    "iso:country":"GB",
    "sg:address":"4 Baker Street",
    "sg:city":"Hull",
    "sg:classifiers":[
        {
            "category":"Professional",
            "subcategory":"Printing & Photocopies",
            "type":"Services"
        }
    ],
    "sg:phone":"+44 1482 323464",
    "sg:postcode":"HU2 8HS",
    "sg:province":"East Riding of Yorkshire",
    "sg:tags":[
        "rubber",
        "stamp"
    ],
    "wof:name":"Mark C Brown Ltd.",
    "wof:placetype":"venue"
},
  "geometry": {"coordinates":[-0.3436020017,53.7471809387],"type":"Point"}
}