{
  "type": "Feature",
  "properties": {
    "addr:full":"12 Hobbs Hill, Croyde Braunton Devon EX33 1LZ",
    "addr:housenumber":"12",
    "addr:postcode":"ex33 1lz",
    "addr:street":"Hobbs Hill Croyde",
    "iso:country":"GB",
    "sg:address":"12 Hobbs Hill, Croyde",
    "sg:city":"Braunton",
    "sg:classifiers":[
        {
            "category":"Bars & Pubs",
            "type":"Food & Drink"
        }
    ],
    "sg:postcode":"EX33 1LZ",
    "sg:province":"Devon",
    "sg:tags":[
        "pubs",
        "inn"
    ],
    "wof:name":"Billy Budds",
    "wof:placetype":"venue"
},
  "geometry": {"coordinates":[-4.2247428894,51.1300506592],"type":"Point"}
}