{
  "type": "Feature",
  "properties": {
    "iso:country":"GB",
    "sg:address":"71 Marsden Street",
    "sg:city":"London",
    "sg:classifiers":[
        {
            "category":"Retail",
            "subcategory":"Photofinishing",
            "type":"Services"
        }
    ],
    "sg:postcode":"NW5 3JA",
    "sg:province":"Greater London",
    "sg:tags":[
        "photographic",
        "processor"
    ],
    "wof:name":"E Toosy",
    "wof:placetype":"venue"
},
  "geometry": {"coordinates":[-0.1520210057,51.5470085144],"type":"Point"}
}