{
  "type": "Feature",
  "properties": {
    "iso:country":"GB",
    "sg:address":"Corner House Stores, Reepham",
    "sg:city":"Lincoln",
    "sg:classifiers":[
        {
            "category":"Food & Beverages",
            "subcategory":"Groceries & Convenience Stores",
            "type":"Retail Goods"
        }
    ],
    "sg:postcode":"LN3 4DN",
    "sg:province":"Lincolnshire",
    "wof:name":"C F& D A Spillings",
    "wof:placetype":"venue"
},
  "geometry": {"coordinates":[-0.439747,53.251911],"type":"Point"}
}