{
  "type": "Feature",
  "properties": {
    "addr:full":"7 Branch Road Batley West Yorkshire WF17 5RY",
    "addr:housenumber":"7",
    "addr:postcode":"wf17 5ry",
    "addr:street":"Branch Road",
    "iso:country":"GB",
    "sg:address":"7 Branch Road",
    "sg:city":"Batley",
    "sg:classifiers":[
        {
            "category":"Military Area",
            "subcategory":"Air Force Base",
            "type":"Public Place"
        }
    ],
    "sg:phone":"+44 1924 479988",
    "sg:postcode":"WF17 5RY",
    "sg:province":"West Yorkshire",
    "sg:tags":[
        "taxi",
        "hire",
        "private"
    ],
    "wof:name":"Prestige Taxis",
    "wof:placetype":"venue"
},
  "geometry": {"coordinates":[-1.634036,53.714714],"type":"Point"}
}