{
  "type": "Feature",
  "properties": {
    "iso:country":"GB",
    "sg:address":"Whitby Street",
    "sg:city":"Hartlepool",
    "sg:classifiers":[
        {
            "category":"Organizations",
            "subcategory":"Membership Organization",
            "type":"Services"
        }
    ],
    "sg:phone":"+44 1429 268826",
    "sg:postcode":"TS24 7AB",
    "sg:province":"Durham",
    "sg:tags":[
        "club"
    ],
    "wof:name":"Corporation Welfare Club",
    "wof:placetype":"venue"
},
  "geometry": {"coordinates":[-1.207329,54.685696],"type":"Point"}
}