{
  "type": "Feature",
  "properties": {
    "iso:country":"GB",
    "sg:address":"11 Woodford Avenue",
    "sg:city":"Ilford",
    "sg:classifiers":[
        {
            "category":"Real Estate",
            "subcategory":"Real Estate Agent",
            "type":"Services"
        }
    ],
    "sg:phone":"+44 20 8551 4018",
    "sg:postcode":"IG2 6UF",
    "sg:province":"Essex",
    "wof:name":"Spicer McColl Ltd.",
    "wof:placetype":"venue"
},
  "geometry": {"coordinates":[0.065749,51.576965],"type":"Point"}
}