{
  "type": "Feature",
  "properties": {
    "addr:full":"Unit 16 Longshot Lane Industrial Estate Bracknell Berkshire RG12 1RL",
    "addr:housenumber":"unit 16",
    "addr:postcode":"rg12 1rl",
    "addr:street":"Longshot Lane Industrial Estate",
    "iso:country":"GB",
    "sg:address":"Unit 16 Longshot Lane Industrial Estate",
    "sg:city":"Bracknell",
    "sg:classifiers":[
        {
            "category":"Professional",
            "subcategory":"Engineering",
            "type":"Services"
        }
    ],
    "sg:phone":"+44 1753 541511",
    "sg:postcode":"RG12 1RL",
    "sg:province":"Berkshire",
    "sg:tags":[
        "contractor",
        "electrical",
        "engineer"
    ],
    "wof:name":"Benville & Marsh Ltd.",
    "wof:placetype":"venue"
},
  "geometry": {"coordinates":[-0.7710379958,51.4166908264],"type":"Point"}
}