{
  "type": "Feature",
  "properties": {
    "addr:full":"6 Academy St Elgin Moray IV30 1LJ",
    "addr:housenumber":"6",
    "addr:postcode":"iv30 1lj",
    "addr:street":"Academy St",
    "iso:country":"GB",
    "sg:address":"6 Academy St",
    "sg:city":"Elgin",
    "sg:classifiers":[
        {
            "category":"Food & Beverages",
            "subcategory":"Groceries & Convenience Stores",
            "type":"Retail Goods"
        }
    ],
    "sg:phone":"+44 1343 547372",
    "sg:postcode":"IV30 1LJ",
    "sg:province":"Moray",
    "wof:name":"Spar",
    "wof:placetype":"venue"
},
  "geometry": {"coordinates":[-3.3139350414,57.6477928162],"type":"Point"}
}