{
  "type": "Feature",
  "properties": {
    "addr:full":"472 Station Road, Dorridge Solihull Warwickshire B93 8HE",
    "addr:housenumber":"472",
    "addr:postcode":"b93 8he",
    "addr:street":"Station Road",
    "iso:country":"GB",
    "sg:address":"472 Station Road, Dorridge",
    "sg:city":"Solihull",
    "sg:classifiers":[
        {
            "category":"Wholesale",
            "subcategory":"Construction Materials",
            "type":"Manufacturing & Wholesale Goods"
        },
        {
            "category":"Professional",
            "subcategory":"Business Services",
            "type":"Services"
        }
    ],
    "sg:phone":"+44 1564 776195",
    "sg:postcode":"B93 8HE",
    "sg:province":"Warwickshire",
    "sg:tags":[
        "tile",
        "wholesaler",
        "supplier",
        "stockist"
    ],
    "wof:name":"Shirley Tile Studio",
    "wof:placetype":"venue"
},
  "geometry": {"coordinates":[-1.7536159754,52.3732681274],"type":"Point"}
}