{
  "type": "Feature",
  "properties": {
    "iso:country":"GB",
    "sg:address":"Higher Woodford, Wrangway",
    "sg:city":"Wellington",
    "sg:classifiers":[
        {
            "category":"Retail",
            "subcategory":"Auto Rental",
            "type":"Services"
        },
        {
            "category":"Building & Trades",
            "subcategory":"Construction",
            "type":"Services"
        }
    ],
    "sg:phone":"+44 1823 662963",
    "sg:postcode":"TA21 9QF",
    "sg:province":"Devon",
    "sg:tags":[
        "roofing",
        "hire",
        "van"
    ],
    "wof:name":"R Wescott",
    "wof:placetype":"venue"
},
  "geometry": {"coordinates":[-3.2496080399,50.954498291],"type":"Point"}
}