{
  "type": "Feature",
  "properties": {
    "iso:country":"GB",
    "sg:address":"138 Kilburn High Rd",
    "sg:city":"Kilburn",
    "sg:classifiers":[
        {
            "category":"Retail",
            "subcategory":"Photofinishing",
            "type":"Services"
        }
    ],
    "sg:phone":"+44 20 7625 6208",
    "sg:postcode":"NW6 4JD",
    "sg:province":"Greater London",
    "sg:tags":[
        "photographic",
        "processor"
    ],
    "wof:name":"Colorama Free Film Photo Centres",
    "wof:placetype":"venue"
},
  "geometry": {"coordinates":[-0.195419,51.53973],"type":"Point"}
}