{
  "type": "Feature",
  "properties": {
    "addr:full":"Back Southgate Hornsea East Riding of Yorkshire HU18 1BA",
    "addr:postcode":"hu18 1ba",
    "addr:street":"Back Southgate",
    "iso:country":"GB",
    "sg:address":"Back Southgate",
    "sg:city":"Hornsea",
    "sg:classifiers":[
        {
            "category":"Organizations",
            "subcategory":"Membership Organization",
            "type":"Services"
        }
    ],
    "sg:phone":"+44 1964 534230",
    "sg:postcode":"HU18 1BA",
    "sg:province":"East Riding of Yorkshire",
    "sg:tags":[
        "club"
    ],
    "wof:name":"Hornsea Ex-Service Mens Club Ltd.",
    "wof:placetype":"venue"
},
  "geometry": {"coordinates":[-0.172474,53.909081],"type":"Point"}
}