{
  "type": "Feature",
  "properties": {
    "addr:full":"133 Charing Cross Rd Holborn Greater London WC2H 0EA",
    "addr:housenumber":"133",
    "addr:postcode":"wc2h 0ea",
    "addr:street":"Charing Cross Rd",
    "iso:country":"GB",
    "sg:address":"133 Charing Cross Rd",
    "sg:city":"Holborn",
    "sg:classifiers":[
        {
            "category":"Professional",
            "subcategory":"Art Services",
            "type":"Services"
        }
    ],
    "sg:phone":"+44 20 7434 1111",
    "sg:postcode":"WC2H 0EA",
    "sg:province":"Greater London",
    "sg:tags":[
        "picture",
        "restoration"
    ],
    "wof:name":"Athena Galleries",
    "wof:placetype":"venue"
},
  "geometry": {"coordinates":[-0.1302549988,51.5163230896],"type":"Point"}
}