{
  "type": "Feature",
  "properties": {
    "addr:full":"9/10 Bentinck Mews London Greater London W1U 2AL",
    "addr:housenumber":"9 / 10",
    "addr:postcode":"w1u 2al",
    "addr:street":"Bentinck Mews",
    "iso:country":"GB",
    "sg:address":"9/10 Bentinck Mews",
    "sg:city":"London",
    "sg:classifiers":[
        {
            "category":"Real Estate",
            "subcategory":"Real Estate Agent",
            "type":"Services"
        }
    ],
    "sg:postcode":"W1U 2AL",
    "sg:province":"Greater London",
    "wof:name":"Rowebond Properties Ltd",
    "wof:placetype":"venue"
},
  "geometry": {"coordinates":[-0.1499550045,51.5176048279],"type":"Point"}
}