{
  "type": "Feature",
  "properties": {
    "iso:country":"GB",
    "sg:address":"Stoke Mill, Mill Road, Sharnbrook",
    "sg:city":"Bedford",
    "sg:classifiers":[
        {
            "category":"Manufacturing",
            "subcategory":"Metals",
            "type":"Manufacturing & Wholesale Goods"
        }
    ],
    "sg:phone":"+44 1234 782550",
    "sg:postcode":"MK44 1NR",
    "sg:province":"Bedfordshire",
    "sg:tags":[
        "work",
        "sheet"
    ],
    "wof:name":"Sharnbrook Metal Fabrication",
    "wof:placetype":"venue"
},
  "geometry": {"coordinates":[-0.544024,52.225994],"type":"Point"}
}