{
  "type": "Feature",
  "properties": {
    "addr:full":"Perrins Farm, Beech Hill Rd Reading Berkshire RG7 2AL",
    "addr:postcode":"rg7 2al",
    "addr:street":"Beech Hill Rd",
    "iso:country":"GB",
    "sg:address":"Perrins Farm, Beech Hill Rd",
    "sg:city":"Reading",
    "sg:classifiers":[
        {
            "category":"Farming",
            "subcategory":"Farm",
            "type":"Manufacturing & Wholesale Goods"
        }
    ],
    "sg:phone":"+44 118 933 2469",
    "sg:postcode":"RG7 2AL",
    "sg:province":"Berkshire",
    "sg:tags":[
        "mixed",
        "crop"
    ],
    "wof:name":"Thompson & Cripps",
    "wof:placetype":"venue"
},
  "geometry": {"coordinates":[-1.01946,51.367142],"type":"Point"}
}