{
  "type": "Feature",
  "properties": {
    "addr:full":"12 Hallam Chase Sheffield South Yorkshire S10 5SW",
    "addr:housenumber":"12",
    "addr:postcode":"s10 5sw",
    "addr:street":"Hallam Chase",
    "iso:country":"GB",
    "sg:address":"12 Hallam Chase",
    "sg:city":"Sheffield",
    "sg:classifiers":[
        {
            "category":"Building & Trades",
            "subcategory":"Construction",
            "type":"Services"
        }
    ],
    "sg:postcode":"S10 5SW",
    "sg:province":"South Yorkshire",
    "sg:tags":[
        "worker",
        "metal"
    ],
    "wof:name":"Urban Style",
    "wof:placetype":"venue"
},
  "geometry": {"coordinates":[-1.5384889841,53.3754234314],"type":"Point"}
}