{
  "type": "Feature",
  "properties": {
    "iso:country":"GB",
    "sg:address":"92 West George Street",
    "sg:city":"Glasgow",
    "sg:classifiers":[
        {
            "category":"Bars & Pubs",
            "type":"Food & Drink"
        }
    ],
    "sg:phone":"+44 141 353 3003",
    "sg:postcode":"G2 1PH",
    "sg:province":"Glasgow City",
    "sg:tags":[
        "pubs",
        "inn"
    ],
    "wof:name":"Picture & Piano",
    "wof:placetype":"venue"
},
  "geometry": {"coordinates":[-4.2550721169,55.8622589111],"type":"Point"}
}