{
  "type": "Feature",
  "properties": {
    "addr:full":"35 Broadpool Green, Whickham Newcastle Upon Tyne Durham NE16 4RH",
    "addr:housenumber":"35",
    "addr:postcode":"ne16 4rh",
    "addr:street":"Broadpool Green Whickham",
    "iso:country":"GB",
    "sg:address":"35 Broadpool Green, Whickham",
    "sg:city":"Newcastle Upon Tyne",
    "sg:classifiers":[
        {
            "category":"Professional",
            "subcategory":"Computer Services",
            "type":"Services"
        }
    ],
    "sg:phone":"+44 191 488 3859",
    "sg:postcode":"NE16 4RH",
    "sg:province":"Durham",
    "sg:tags":[
        "system",
        "software"
    ],
    "wof:name":"Northumbria Information Services",
    "wof:placetype":"venue"
},
  "geometry": {"coordinates":[-1.6704640388,54.9421234131],"type":"Point"}
}