{
  "type": "Feature",
  "properties": {
    "addr:full":"106 Stoke Newington High Street London Greater London N16 7NY",
    "addr:housenumber":"106",
    "addr:postcode":"n16 7ny",
    "addr:street":"Stoke Newington High Street",
    "iso:country":"GB",
    "sg:address":"106 Stoke Newington High Street",
    "sg:city":"London",
    "sg:classifiers":[
        {
            "category":"Farming",
            "subcategory":"Nursery",
            "type":"Manufacturing & Wholesale Goods"
        },
        {
            "category":"Organizations",
            "subcategory":"Religious Organization",
            "type":"Services"
        }
    ],
    "sg:phone":"+44 20 7254 8028",
    "sg:postcode":"N16 7NY",
    "sg:province":"Greater London",
    "sg:tags":[
        "organisation",
        "creche"
    ],
    "wof:name":"Stoke Newington Pre-School",
    "wof:placetype":"venue"
},
  "geometry": {"coordinates":[-0.0738390014,51.5600166321],"type":"Point"}
}