{
  "type": "Feature",
  "properties": {
    "iso:country":"GB",
    "sg:address":"Gwbert On Sea",
    "sg:city":"Cardigan",
    "sg:classifiers":[
        {
            "category":"Travel",
            "subcategory":"Hotels & Motels",
            "type":"Entertainment"
        }
    ],
    "sg:phone":"+44 1239 613241",
    "sg:postcode":"SA43 1PP",
    "sg:province":"Ceredigion",
    "wof:name":"Cliff Hotel",
    "wof:placetype":"venue"
},
  "geometry": {"coordinates":[-4.655044,52.086868],"type":"Point"}
}