{
  "type": "Feature",
  "properties": {
    "addr:full":"73 Cunningham Road Doncaster South Yorkshire DN1 2BP",
    "addr:housenumber":"73",
    "addr:postcode":"dn1 2bp",
    "addr:street":"Cunningham Road",
    "iso:country":"GB",
    "sg:address":"73 Cunningham Road",
    "sg:city":"Doncaster",
    "sg:classifiers":[
        {
            "category":"Personal",
            "subcategory":"Beauty Salon",
            "type":"Services"
        }
    ],
    "sg:postcode":"DN1 2BP",
    "sg:province":"South Yorkshire",
    "sg:tags":[
        "unisex",
        "hairdresser"
    ],
    "wof:name":"Lynns Hairstylists",
    "wof:placetype":"venue"
},
  "geometry": {"coordinates":[-1.128738,53.517277],"type":"Point"}
}