{
  "type": "Feature",
  "properties": {
    "iso:country":"GB",
    "sg:address":"Dunkeld Road",
    "sg:city":"Perth",
    "sg:classifiers":[
        {
            "category":"Autos & Motor Vehicles",
            "subcategory":"Automobile Sales",
            "type":"Retail Goods"
        }
    ],
    "sg:phone":"+44 1738 633999",
    "sg:postcode":"PH1 3EA",
    "sg:province":"Perth and Kinross",
    "sg:tags":[
        "car"
    ],
    "wof:name":"Perth Nissan",
    "wof:placetype":"venue"
},
  "geometry": {"coordinates":[-3.456754,56.41349],"type":"Point"}
}