{
  "type": "Feature",
  "properties": {
    "addr:full":"Penny Street Blackburn Lancashire BB1 6HL",
    "addr:postcode":"bb1 6hl",
    "addr:street":"Penny Street",
    "iso:country":"GB",
    "sg:address":"Penny Street",
    "sg:city":"Blackburn",
    "sg:classifiers":[
        {
            "category":"Parking",
            "type":"Transportation"
        },
        {
            "category":"Parking",
            "subcategory":"Bicycle",
            "type":"Transportation"
        }
    ],
    "sg:phone":"+44 1254 674333",
    "sg:postcode":"BB1 6HL",
    "sg:province":"Lancashire",
    "sg:tags":[
        "car",
        "garaging",
        "park"
    ],
    "wof:name":"National Car Parks Ltd",
    "wof:placetype":"venue"
},
  "geometry": {"coordinates":[-2.478419,53.750359],"type":"Point"}
}