{
  "type": "Feature",
  "properties": {
    "addr:full":"26 North St Havant Hampshire PO9 1PR",
    "addr:housenumber":"26",
    "addr:postcode":"po9 1pr",
    "addr:street":"North St",
    "iso:country":"GB",
    "sg:address":"26 North St",
    "sg:city":"Havant",
    "sg:classifiers":[
        {
            "category":"Health Services",
            "subcategory":"Podiatrist",
            "type":"Services"
        }
    ],
    "sg:phone":"+44 23 9248 4184",
    "sg:postcode":"PO9 1PR",
    "sg:province":"Hampshire",
    "sg:tags":[
        "podiatrists",
        "chiropodist"
    ],
    "wof:name":"M Hunt",
    "wof:placetype":"venue"
},
  "geometry": {"coordinates":[-0.98113,50.852608],"type":"Point"}
}