{
  "type": "Feature",
  "properties": {
    "addr:full":"2 Falconwood Parade, The Green Welling Kent DA16 2PL",
    "addr:housenumber":"2",
    "addr:postcode":"da16 2pl",
    "addr:street":"Falconwood Parade The Green Welling",
    "iso:country":"GB",
    "sg:address":"2 Falconwood Parade, The Green",
    "sg:city":"Welling",
    "sg:classifiers":[
        {
            "category":"Health Services",
            "subcategory":"Doctor",
            "type":"Services"
        }
    ],
    "sg:phone":"+44 20 8304 7662",
    "sg:postcode":"DA16 2PL",
    "sg:province":"Kent",
    "sg:tags":[
        "practitioners"
    ],
    "wof:name":"The Surgery",
    "wof:placetype":"venue"
},
  "geometry": {"coordinates":[0.0947519988,51.4562835693],"type":"Point"}
}