{
  "type": "Feature",
  "properties": {
    "iso:country":"GB",
    "sg:address":"4 Farrington Ave, East Herrington",
    "sg:city":"Sunderland",
    "sg:classifiers":[
        {
            "category":"Manufacturing",
            "subcategory":"Petroleum Products",
            "type":"Manufacturing & Wholesale Goods"
        }
    ],
    "sg:postcode":"SR3 3LX",
    "sg:province":"Tyne and Wear",
    "sg:tags":[
        "double",
        "glazing"
    ],
    "wof:name":"Imray,Anthony,",
    "wof:placetype":"venue"
},
  "geometry": {"coordinates":[-1.43598,54.875259],"type":"Point"}
}