{
  "type": "Feature",
  "properties": {
    "addr:full":"North Road, Yate Bristol Gloucestershire BS37 7PR",
    "addr:postcode":"bs37 7pr",
    "addr:street":"North Road Yate",
    "iso:country":"GB",
    "sg:address":"North Road, Yate",
    "sg:city":"Bristol",
    "sg:classifiers":[
        {
            "category":"Manufacturing",
            "subcategory":"Tools & Machinery",
            "type":"Manufacturing & Wholesale Goods"
        }
    ],
    "sg:postcode":"BS37 7PR",
    "sg:province":"Gloucestershire",
    "sg:tags":[
        "design",
        "maker"
    ],
    "wof:name":"Brunel Pattern Making Co.",
    "wof:placetype":"venue"
},
  "geometry": {"coordinates":[-2.436896,51.558582],"type":"Point"}
}