{
  "type": "Feature",
  "properties": {
    "addr:full":"2a Yealand Drive, Scotforth Lancaster Lancashire LA1 4EW",
    "addr:housenumber":"2a",
    "addr:postcode":"la1 4ew",
    "addr:street":"Yealand Drive",
    "iso:country":"GB",
    "sg:address":"2a Yealand Drive, Scotforth",
    "sg:city":"Lancaster",
    "sg:classifiers":[
        {
            "category":"Building & Trades",
            "subcategory":"Construction",
            "type":"Services"
        }
    ],
    "sg:postcode":"LA1 4EW",
    "sg:province":"Lancashire",
    "sg:tags":[
        "builder"
    ],
    "wof:name":"Prestwood,J E,",
    "wof:placetype":"venue"
},
  "geometry": {"coordinates":[-2.794362,54.029186],"type":"Point"}
}