{
  "type": "Feature",
  "properties": {
    "addr:full":"Manor Farm, Handley Grn, Sixpenny Handley Salisbury Dorset SP5 5NU",
    "addr:postcode":"sp5 5nu",
    "addr:street":"Manor;Handley Grn;Dorset",
    "iso:country":"GB",
    "sg:address":"Manor Farm, Handley Grn, Sixpenny Handley",
    "sg:city":"Salisbury",
    "sg:classifiers":[
        {
            "category":"Farming",
            "subcategory":"Livestock Farm",
            "type":"Manufacturing & Wholesale Goods"
        }
    ],
    "sg:postcode":"SP5 5NU",
    "sg:province":"Dorset",
    "sg:tags":[
        "others"
    ],
    "wof:name":"P G & D M H Chick",
    "wof:placetype":"venue"
},
  "geometry": {"coordinates":[-2.0034739971,50.9532699585],"type":"Point"}
}