{
  "type": "Feature",
  "properties": {
    "addr:full":"7 The Campus Hemel Hempstead Hertfordshire HP2 7TN",
    "addr:housenumber":"7",
    "addr:postcode":"hp2 7tn",
    "iso:country":"GB",
    "sg:address":"7 The Campus",
    "sg:city":"Hemel Hempstead",
    "sg:classifiers":[
        {
            "category":"Military Area",
            "subcategory":"Air Force Base",
            "type":"Public Place"
        }
    ],
    "sg:phone":"+44 1442 232232",
    "sg:postcode":"HP2 7TN",
    "sg:province":"Hertfordshire",
    "sg:tags":[
        "taxi",
        "hire",
        "private"
    ],
    "wof:name":"Berkhampsted & District Cars",
    "wof:placetype":"venue"
},
  "geometry": {"coordinates":[-0.4363659918,51.7618217468],"type":"Point"}
}