{
  "type": "Feature",
  "properties": {
    "iso:country":"GB",
    "sg:address":"The Craft Centre Rother Valley C, Ountry Park",
    "sg:city":"Sheffield",
    "sg:classifiers":[
        {
            "category":"Shopping",
            "subcategory":"Department Store",
            "type":"Retail Goods"
        }
    ],
    "sg:phone":"+44 114 251 1396",
    "sg:postcode":"S26 5PE",
    "sg:province":"South Yorkshire",
    "wof:name":"Jencel Jewellery",
    "wof:placetype":"venue"
},
  "geometry": {"coordinates":[-1.296579957,53.341999054],"type":"Point"}
}