{
  "type": "Feature",
  "properties": {
    "addr:full":"4 Bridge Street Kington Herefordshire HR5 3DL",
    "addr:housenumber":"4",
    "addr:postcode":"hr5 3dl",
    "addr:street":"Bridge Street",
    "iso:country":"GB",
    "sg:address":"4 Bridge Street",
    "sg:city":"Kington",
    "sg:classifiers":[
        {
            "category":"Shopping",
            "subcategory":"Pets & Pet Supplies",
            "type":"Retail Goods"
        }
    ],
    "sg:phone":"+44 1544 230838",
    "sg:postcode":"HR5 3DL",
    "sg:province":"Herefordshire",
    "sg:tags":[
        "shop"
    ],
    "wof:name":"Kington Pet Supplies",
    "wof:placetype":"venue"
},
  "geometry": {"coordinates":[-3.0289759636,52.2034950256],"type":"Point"}
}