{
  "type": "Feature",
  "properties": {
    "addr:full":"437 North Road Darlington Durham DL1 3BN",
    "addr:housenumber":"437",
    "addr:postcode":"dl1 3bn",
    "addr:street":"North Road",
    "iso:country":"GB",
    "sg:address":"437 North Road",
    "sg:city":"Darlington",
    "sg:classifiers":[
        {
            "category":"Building & Trades",
            "subcategory":"Plumbing",
            "type":"Services"
        }
    ],
    "sg:phone":"+44 1325 354605",
    "sg:postcode":"DL1 3BN",
    "sg:province":"Durham",
    "sg:tags":[
        "central",
        "heating"
    ],
    "wof:name":"J Chapman & Son",
    "wof:placetype":"venue"
},
  "geometry": {"coordinates":[-1.54723,54.548992],"type":"Point"}
}