{
  "type": "Feature",
  "properties": {
    "addr:full":"86 Colman Road Norwich Norfolk NR4 7EH",
    "addr:housenumber":"86",
    "addr:postcode":"nr4 7eh",
    "addr:street":"Colman Road Norwich Norfolk",
    "iso:country":"GB",
    "sg:address":"86 Colman Road",
    "sg:city":"Norwich",
    "sg:classifiers":[
        {
            "category":"Fast Food",
            "type":"Food & Drink"
        }
    ],
    "sg:postcode":"NR4 7EH",
    "sg:province":"Norfolk",
    "sg:tags":[
        "away",
        "take"
    ],
    "wof:name":"Golden Dragon Chinese Takeaway",
    "wof:placetype":"venue"
},
  "geometry": {"coordinates":[1.262333,52.621922],"type":"Point"}
}