{
  "type": "Feature",
  "properties": {
    "addr:full":"10 Tiller Road London Greater London E14 8PX",
    "addr:housenumber":"10",
    "addr:postcode":"e14 8px",
    "addr:street":"Tiller Road",
    "iso:country":"GB",
    "sg:address":"10 Tiller Road",
    "sg:city":"London",
    "sg:classifiers":[
        {
            "category":"Professional",
            "subcategory":"Computer Services",
            "type":"Services"
        }
    ],
    "sg:phone":"+44 20 7345 5038",
    "sg:postcode":"E14 8PX",
    "sg:province":"Greater London",
    "sg:tags":[
        "development",
        "system",
        "software"
    ],
    "sg:website":"http://www.liss.co.uk",
    "wof:name":"Liss Systems Ltd",
    "wof:placetype":"venue"
},
  "geometry": {"coordinates":[-0.025553,51.496208],"type":"Point"}
}