{
  "type": "Feature",
  "properties": {
    "iso:country":"GB",
    "sg:address":"55 Pembury Street",
    "sg:city":"Sittingbourne",
    "sg:classifiers":[
        {
            "category":"Professional",
            "subcategory":"Printing & Photocopies",
            "type":"Services"
        }
    ],
    "sg:phone":"+44 1795 474681",
    "sg:postcode":"ME10 3EE",
    "sg:province":"Kent",
    "sg:tags":[
        "printer"
    ],
    "wof:name":"Wyvern Press",
    "wof:placetype":"venue"
},
  "geometry": {"coordinates":[0.732479,51.341114],"type":"Point"}
}