{
  "type": "Feature",
  "properties": {
    "addr:full":"21 Hazel Beck Bingley West Yorkshire BD16 1LZ",
    "addr:housenumber":"21",
    "addr:postcode":"bd16 1lz",
    "addr:street":"Hazel Beck",
    "iso:country":"GB",
    "sg:address":"21 Hazel Beck",
    "sg:city":"Bingley",
    "sg:classifiers":[
        {
            "category":"Professional",
            "subcategory":"Computer Services",
            "type":"Services"
        }
    ],
    "sg:postcode":"BD16 1LZ",
    "sg:province":"West Yorkshire",
    "sg:tags":[
        "consultant"
    ],
    "wof:name":"Pearson Computer Systems",
    "wof:placetype":"venue"
},
  "geometry": {"coordinates":[-1.831969,53.837086],"type":"Point"}
}