{
  "type": "Feature",
  "properties": {
    "addr:full":"9 Fenton Street Rochdale Lancashire OL11 3TH",
    "addr:housenumber":"9",
    "addr:postcode":"ol11 3th",
    "addr:street":"Fenton Street",
    "iso:country":"GB",
    "sg:address":"9 Fenton Street",
    "sg:city":"Rochdale",
    "sg:classifiers":[
        {
            "category":"Personal",
            "subcategory":"Beauty Salon",
            "type":"Services"
        }
    ],
    "sg:phone":"+44 1706 647074",
    "sg:postcode":"OL11 3TH",
    "sg:province":"Lancashire",
    "sg:tags":[
        "lady",
        "hairdresser"
    ],
    "wof:name":"Oyster Hair Stylist",
    "wof:placetype":"venue"
},
  "geometry": {"coordinates":[-2.161113,53.607609],"type":"Point"}
}