{
  "type": "Feature",
  "properties": {
    "addr:full":"Eastern Avenue West Romford Essex RM7 7PH",
    "addr:postcode":"rm7 7ph",
    "addr:street":"Eastern Avenue West",
    "iso:country":"GB",
    "sg:address":"Eastern Avenue West",
    "sg:city":"Romford",
    "sg:classifiers":[
        {
            "category":"Manufacturing",
            "subcategory":"Building Materials",
            "type":"Manufacturing & Wholesale Goods"
        }
    ],
    "sg:phone":"+44 1708 757162",
    "sg:postcode":"RM7 7PH",
    "sg:province":"Essex",
    "sg:tags":[
        "tile",
        "mnfrs"
    ],
    "wof:name":"Tile Depot",
    "wof:placetype":"venue"
},
  "geometry": {"coordinates":[0.1700730026,51.5843238831],"type":"Point"}
}