{
  "type": "Feature",
  "properties": {
    "iso:country":"GB",
    "sg:address":"77 Union Street",
    "sg:city":"Oldham",
    "sg:classifiers":[
        {
            "category":"Organizations",
            "subcategory":"Community Association",
            "type":"Services"
        }
    ],
    "sg:phone":"+44 161 621 4100",
    "sg:postcode":"OL1 1JZ",
    "sg:province":"Lancashire",
    "sg:tags":[
        "society",
        "housing"
    ],
    "wof:name":"West Pennine Housing Association Ltd.",
    "wof:placetype":"venue"
},
  "geometry": {"coordinates":[-2.113202,53.540157],"type":"Point"}
}