{
  "type": "Feature",
  "properties": {
    "iso:country":"GB",
    "sg:address":"Tighean Magrath, Main Street",
    "sg:city":"Golspie",
    "sg:classifiers":[
        {
            "category":"Professional",
            "subcategory":"Art Services",
            "type":"Services"
        },
        {
            "category":"Building & Trades",
            "subcategory":"Construction",
            "type":"Services"
        }
    ],
    "sg:phone":"+44 1408 633786",
    "sg:postcode":"KW10 6RA",
    "sg:province":"Highland",
    "sg:tags":[
        "glazier",
        "decorator",
        "painter"
    ],
    "wof:name":"W A Macrae",
    "wof:placetype":"venue"
},
  "geometry": {"coordinates":[-3.976449,57.973267],"type":"Point"}
}