{
  "type": "Feature",
  "properties": {
    "addr:full":"412 Barking Road London Greater London E6 2SA",
    "addr:housenumber":"412",
    "addr:postcode":"e6 2sa",
    "addr:street":"Barking Road",
    "iso:country":"GB",
    "sg:address":"412 Barking Road",
    "sg:city":"London",
    "sg:classifiers":[
        {
            "category":"Fast Food",
            "type":"Food & Drink"
        }
    ],
    "sg:postcode":"E6 2SA",
    "sg:province":"Greater London",
    "sg:tags":[
        "away",
        "take"
    ],
    "wof:name":"Four Seasons",
    "wof:placetype":"venue"
},
  "geometry": {"coordinates":[0.0613070019,51.5336914062],"type":"Point"}
}