{
  "type": "Feature",
  "properties": {
    "iso:country":"GB",
    "sg:address":"Unit A, 2 Waverley Place, Newtown St Boswells",
    "sg:city":"Melrose",
    "sg:classifiers":[
        {
            "category":"Building & Trades",
            "subcategory":"Cleaning & Sanitation",
            "type":"Services"
        }
    ],
    "sg:phone":"+44 1835 822835",
    "sg:postcode":"TD6 0RS",
    "sg:province":"Scottish Borders",
    "sg:tags":[
        "hygiene",
        "cleansing"
    ],
    "sg:website":"http://www.pantonmcleod.co.uk",
    "wof:name":"Panton Mcleod Ltd",
    "wof:placetype":"venue"
},
  "geometry": {"coordinates":[-2.67227,55.57896],"type":"Point"}
}