{
  "type": "Feature",
  "properties": {
    "addr:full":"2 Bishops Road, Fulham London Greater London SW6 7AB",
    "addr:housenumber":"2",
    "addr:postcode":"sw6 7ab",
    "addr:street":"Bishops Road",
    "iso:country":"GB",
    "sg:address":"2 Bishops Road, Fulham",
    "sg:city":"London",
    "sg:classifiers":[
        {
            "category":"Retail",
            "subcategory":"Auto Repair",
            "type":"Services"
        }
    ],
    "sg:phone":"+44 20 7385 1193",
    "sg:postcode":"SW6 7AB",
    "sg:province":"Greater London",
    "sg:tags":[
        "modification",
        "garage"
    ],
    "wof:name":"Triangle Garages (London) Ltd.",
    "wof:placetype":"venue"
},
  "geometry": {"coordinates":[-0.202674,51.47987],"type":"Point"}
}