{
  "type": "Feature",
  "properties": {
    "addr:full":"9-10 The Promenade, Edgwarebury Lane Edgware Greater London HA8 7LQ",
    "addr:housenumber":"9-10",
    "addr:postcode":"ha8 7lq",
    "addr:street":"The Promenade Edgwarebury Lane",
    "iso:country":"GB",
    "sg:address":"9-10 The Promenade, Edgwarebury Lane",
    "sg:city":"Edgware",
    "sg:classifiers":[
        {
            "category":"Banks & Credit Unions",
            "subcategory":"Financial Services",
            "type":"Services"
        }
    ],
    "sg:phone":"+44 20 8250 0800",
    "sg:postcode":"HA8 7LQ",
    "sg:province":"Greater London",
    "sg:tags":[
        "building",
        "society"
    ],
    "wof:name":"Nationwide Building Society",
    "wof:placetype":"venue"
},
  "geometry": {"coordinates":[-0.277564,51.612083],"type":"Point"}
}