{
  "type": "Feature",
  "properties": {
    "addr:full":"Garthspool Lerwick Shetland Islands ZE1 0NP",
    "addr:postcode":"ze1 0np",
    "addr:street":"Garthspool;Shetland",
    "iso:country":"GB",
    "sg:address":"Garthspool",
    "sg:city":"Lerwick",
    "sg:classifiers":[
        {
            "category":"Home & Garden",
            "subcategory":"Carpets & Floor Coverings",
            "type":"Retail Goods"
        }
    ],
    "sg:phone":"+44 1595 692252",
    "sg:postcode":"ZE1 0NP",
    "sg:province":"Shetland Islands",
    "sg:tags":[
        "textile",
        "floorcoverings"
    ],
    "wof:name":"Bargain Centre",
    "wof:placetype":"venue"
},
  "geometry": {"coordinates":[-1.1452239752,60.1518287659],"type":"Point"}
}