{
  "type": "Feature",
  "properties": {
    "addr:full":"27 Henfor Close Marazion Cornwall TR17 0BU",
    "addr:housenumber":"27",
    "addr:postcode":"tr17 0bu",
    "addr:street":"Henfor Close",
    "iso:country":"GB",
    "sg:address":"27 Henfor Close",
    "sg:city":"Marazion",
    "sg:classifiers":[
        {
            "category":"Home & Garden",
            "subcategory":"Household Appliances",
            "type":"Retail Goods"
        }
    ],
    "sg:postcode":"TR17 0BU",
    "sg:province":"Cornwall",
    "sg:tags":[
        "electrical"
    ],
    "wof:name":"Washday Blues",
    "wof:placetype":"venue"
},
  "geometry": {"coordinates":[-5.458296,50.124813],"type":"Point"}
}