{
  "type": "Feature",
  "properties": {
    "iso:country":"GB",
    "sg:address":"272 Montgomery St",
    "sg:city":"Birmingham",
    "sg:classifiers":[
        {
            "category":"Manufacturing",
            "subcategory":"Chemicals & Compounds",
            "type":"Manufacturing & Wholesale Goods"
        }
    ],
    "sg:phone":"+44 121 773 9633",
    "sg:postcode":"B11 1DS",
    "sg:province":"West Midlands",
    "wof:name":"Future 2000",
    "wof:placetype":"venue"
},
  "geometry": {"coordinates":[-1.8639370203,52.4637107849],"type":"Point"}
}