{
  "type": "Feature",
  "properties": {
    "addr:full":"Belmont Road Torquay Devon TQ1 1NG",
    "addr:postcode":"tq1 1ng",
    "addr:street":"Belmont Road",
    "iso:country":"GB",
    "sg:address":"Belmont Road",
    "sg:city":"Torquay",
    "sg:classifiers":[
        {
            "category":"Home & Garden",
            "subcategory":"Household Appliances",
            "type":"Retail Goods"
        }
    ],
    "sg:phone":"+44 1803 323909",
    "sg:postcode":"TQ1 1NG",
    "sg:province":"Devon",
    "sg:tags":[
        "electrical"
    ],
    "wof:name":"Marshall Domestics",
    "wof:placetype":"venue"
},
  "geometry": {"coordinates":[-3.521024,50.47393],"type":"Point"}
}