{
  "type": "Feature",
  "properties": {
    "iso:country":"GB",
    "sg:address":"18 Crowther Close",
    "sg:city":"Southampton",
    "sg:classifiers":[
        {
            "category":"Building & Trades",
            "subcategory":"Cleaning & Sanitation",
            "type":"Services"
        }
    ],
    "sg:phone":"+44 23 8057 7770",
    "sg:postcode":"SO19 1BX",
    "sg:province":"Hampshire",
    "sg:tags":[
        "industrial",
        "business",
        "removal"
    ],
    "wof:name":"J & J Removals",
    "wof:placetype":"venue"
},
  "geometry": {"coordinates":[-1.3420759439,50.9028320312],"type":"Point"}
}