{
  "type": "Feature",
  "properties": {
    "iso:country":"GB",
    "sg:address":"15 Easby Place",
    "sg:city":"Darlington",
    "sg:classifiers":[
        {
            "category":"Building & Trades",
            "subcategory":"Construction",
            "type":"Services"
        }
    ],
    "sg:phone":"+44 1325 243941",
    "sg:postcode":"DL3 9RT",
    "sg:province":"Durham",
    "sg:tags":[
        "decorator",
        "painter"
    ],
    "wof:name":"M.P.G. Decorating Services",
    "wof:placetype":"venue"
},
  "geometry": {"coordinates":[-1.5905330181,54.5383377075],"type":"Point"}
}