{
  "type": "Feature",
  "properties": {
    "addr:full":"Keswick Mill Lane, Keswick Norwich Norfolk NR4 6TP",
    "addr:postcode":"nr4 6tp",
    "addr:street":"Mill Lane",
    "iso:country":"GB",
    "sg:address":"Keswick Mill Lane, Keswick",
    "sg:city":"Norwich",
    "sg:classifiers":[
        {
            "category":"Shopping",
            "subcategory":"Crafts & Fabrics",
            "type":"Retail Goods"
        }
    ],
    "sg:postcode":"NR4 6TP",
    "sg:province":"Norfolk",
    "sg:tags":[
        "shop",
        "needlecraft",
        "wool"
    ],
    "wof:name":"Pearson Design",
    "wof:placetype":"venue"
},
  "geometry": {"coordinates":[1.265632987,52.5923233032],"type":"Point"}
}