{
  "type": "Feature",
  "properties": {
    "iso:country":"GB",
    "sg:address":"34a Bank Street",
    "sg:city":"Rossendale",
    "sg:classifiers":[
        {
            "category":"Social Services",
            "subcategory":"Retirement Home",
            "type":"Services"
        }
    ],
    "sg:phone":"+44 1706 830411",
    "sg:postcode":"BB4 8DY",
    "sg:province":"Lancashire",
    "sg:tags":[
        "care"
    ],
    "wof:name":"Castle Care",
    "wof:placetype":"venue"
},
  "geometry": {"coordinates":[-2.2856390476,53.7023353577],"type":"Point"}
}