{
  "type": "Feature",
  "properties": {
    "iso:country":"GB",
    "sg:address":"337-341 London Rd",
    "sg:city":"Westcliff On Sea",
    "sg:classifiers":[
        {
            "category":"Home & Garden",
            "subcategory":"Furniture",
            "type":"Retail Goods"
        }
    ],
    "sg:phone":"+44 1702 436951",
    "sg:postcode":"SS0 7HT",
    "sg:province":"Essex",
    "wof:name":"Westcliff Furniture Centre",
    "wof:placetype":"venue"
},
  "geometry": {"coordinates":[0.695135,51.542667],"type":"Point"}
}