{
  "type": "Feature",
  "properties": {
    "addr:full":"121 Dale Rd Buxton Derbyshire SK17 6PD",
    "addr:housenumber":"121",
    "addr:postcode":"sk17 6pd",
    "addr:street":"Dale Rd",
    "iso:country":"GB",
    "sg:address":"121 Dale Rd",
    "sg:city":"Buxton",
    "sg:classifiers":[
        {
            "category":"Health Services",
            "subcategory":"Health Practitioner",
            "type":"Services"
        }
    ],
    "sg:phone":"+44 1298 22606",
    "sg:postcode":"SK17 6PD",
    "sg:province":"Derbyshire",
    "sg:tags":[
        "homoeopathic"
    ],
    "wof:name":"L Chera MA, LSSHom, RSHom",
    "wof:placetype":"venue"
},
  "geometry": {"coordinates":[-1.905875,53.253929],"type":"Point"}
}