{
  "type": "Feature",
  "properties": {
    "iso:country":"GB",
    "sg:address":"95 Regent St, Kingswood",
    "sg:city":"Bristol",
    "sg:classifiers":[
        {
            "category":"Shopping",
            "subcategory":"Gifts & Souvenirs",
            "type":"Retail Goods"
        }
    ],
    "sg:postcode":"BS15 8HP",
    "sg:province":"City of Bristol",
    "sg:tags":[
        "poster",
        "card"
    ],
    "wof:name":"J & M Cards",
    "wof:placetype":"venue"
},
  "geometry": {"coordinates":[-2.5070838928,51.462677002],"type":"Point"}
}