{
  "type": "Feature",
  "properties": {
    "iso:country":"GB",
    "sg:address":"137 The Butts, Soham",
    "sg:city":"Ely",
    "sg:classifiers":[
        {
            "category":"Farming",
            "subcategory":"Livestock Farm",
            "type":"Manufacturing & Wholesale Goods"
        }
    ],
    "sg:phone":"+44 1353 720104",
    "sg:postcode":"CB7 5AW",
    "sg:province":"Cambridgeshire",
    "sg:tags":[
        "others"
    ],
    "wof:name":"R A G Robinson",
    "wof:placetype":"venue"
},
  "geometry": {"coordinates":[0.35694,52.317989],"type":"Point"}
}