{
  "type": "Feature",
  "properties": {
    "iso:country":"GB",
    "sg:address":"3 Middle Garth Drive, South Cave",
    "sg:city":"Brough",
    "sg:classifiers":[
        {
            "category":"Freight",
            "type":"Transportation"
        }
    ],
    "sg:postcode":"HU15 2AY",
    "sg:province":"East Riding of Yorkshire",
    "sg:tags":[
        "haulage",
        "road"
    ],
    "wof:name":"M & J Copeland",
    "wof:placetype":"venue"
},
  "geometry": {"coordinates":[-0.597658,53.77076],"type":"Point"}
}