{
  "type": "Feature",
  "properties": {
    "addr:full":"5 Higham Place, Newcastle Newcastle Upon Tyne Tyne and Wear NE1 8AF",
    "addr:housenumber":"5",
    "addr:postcode":"ne1 8af",
    "addr:street":"Higham Place",
    "iso:country":"GB",
    "sg:address":"5 Higham Place, Newcastle",
    "sg:city":"Newcastle Upon Tyne",
    "sg:classifiers":[
        {
            "category":"Shopping",
            "subcategory":"Books",
            "type":"Retail Goods"
        }
    ],
    "sg:phone":"+44 191 232 5301",
    "sg:postcode":"NE1 8AF",
    "sg:province":"Tyne and Wear",
    "sg:tags":[
        "bookseller"
    ],
    "wof:name":"C.L.C Bookshop",
    "wof:placetype":"venue"
},
  "geometry": {"coordinates":[-1.6087729931,54.9749488831],"type":"Point"}
}