{
  "type": "Feature",
  "properties": {
    "iso:country":"GB",
    "sg:address":"9 Woodhall Street, Chapelhall",
    "sg:city":"Airdrie",
    "sg:classifiers":[
        {
            "category":"Retail",
            "subcategory":"Auto Repair",
            "type":"Services"
        }
    ],
    "sg:phone":"+44 1236 762999",
    "sg:postcode":"ML6 8SQ",
    "sg:province":"North Lanarkshire",
    "sg:tags":[
        "modification",
        "garage"
    ],
    "wof:name":"Railway Garage",
    "wof:placetype":"venue"
},
  "geometry": {"coordinates":[-3.9502089024,55.8419647217],"type":"Point"}
}