{
  "type": "Feature",
  "properties": {
    "addr:full":"Crawley Road, Cranfield Bedford Bedfordshire MK43 0AA",
    "addr:postcode":"mk43 0aa",
    "addr:street":"Crawley Road",
    "iso:country":"GB",
    "sg:address":"Crawley Road, Cranfield",
    "sg:city":"Bedford",
    "sg:classifiers":[
        {
            "category":"Restaurant",
            "type":"Food & Drink"
        }
    ],
    "sg:phone":"+44 1234 750283",
    "sg:postcode":"MK43 0AA",
    "sg:province":"Bedfordshire",
    "wof:name":"The Leathern Bottel",
    "wof:placetype":"venue"
},
  "geometry": {"coordinates":[-0.599939,52.072948],"type":"Point"}
}