{
  "type": "Feature",
  "properties": {
    "iso:country":"GB",
    "sg:address":"15 Abbey Road",
    "sg:city":"Llandudno",
    "sg:classifiers":[
        {
            "category":"Travel",
            "subcategory":"Hotels & Motels",
            "type":"Entertainment"
        }
    ],
    "sg:phone":"+44 1492 878746",
    "sg:postcode":"LL30 2EE",
    "sg:province":"Conwy",
    "wof:name":"Epperstone Hotel",
    "wof:placetype":"venue"
},
  "geometry": {"coordinates":[-3.8370199203,53.3244094849],"type":"Point"}
}