{
  "type": "Feature",
  "properties": {
    "addr:full":"76 Market Street, Shirebrook Mansfield Derbyshire NG20 8AD",
    "addr:housenumber":"76",
    "addr:postcode":"ng20 8ad",
    "addr:street":"Market Street",
    "iso:country":"GB",
    "sg:address":"76 Market Street, Shirebrook",
    "sg:city":"Mansfield",
    "sg:classifiers":[
        {
            "category":"Real Estate",
            "subcategory":"Real Estate Agent",
            "type":"Services"
        }
    ],
    "sg:phone":"+44 1623 747956",
    "sg:postcode":"NG20 8AD",
    "sg:province":"Derbyshire",
    "wof:name":"Elliot Yates Estate Agents",
    "wof:placetype":"venue"
},
  "geometry": {"coordinates":[-1.2115980387,53.2028770447],"type":"Point"}
}