{
  "type": "Feature",
  "properties": {
    "iso:country":"GB",
    "sg:address":"Unit H, Hoyle Head Mills",
    "sg:city":"Dewsbury",
    "sg:classifiers":[
        {
            "category":"Professional",
            "subcategory":"Engineering",
            "type":"Services"
        }
    ],
    "sg:phone":"+44 1924 458253",
    "sg:postcode":"WF12 8JJ",
    "sg:province":"West Yorkshire",
    "sg:tags":[
        "contractor",
        "electrical",
        "engineer"
    ],
    "wof:name":"S & G Electrics",
    "wof:placetype":"venue"
},
  "geometry": {"coordinates":[-1.6129,53.686909],"type":"Point"}
}