{
  "type": "Feature",
  "properties": {
    "addr:full":"The Green, East Dene Eastbourne East Sussex BN20 0BY",
    "addr:postcode":"bn20 0by",
    "addr:street":"The Green East Dene",
    "iso:country":"GB",
    "sg:address":"The Green, East Dene",
    "sg:city":"Eastbourne",
    "sg:classifiers":[
        {
            "category":"Restaurant",
            "type":"Food & Drink"
        }
    ],
    "sg:phone":"+44 1323 422384",
    "sg:postcode":"BN20 0BY",
    "sg:province":"East Sussex",
    "wof:name":"Grimaldi",
    "wof:placetype":"venue"
},
  "geometry": {"coordinates":[0.2049600035,50.7585906982],"type":"Point"}
}