{
  "type": "Feature",
  "properties": {
    "iso:country":"GB",
    "sg:address":"72 Charles Street",
    "sg:city":"Leicester",
    "sg:classifiers":[
        {
            "category":"Professional",
            "subcategory":"Employment Agencies",
            "type":"Services"
        }
    ],
    "sg:phone":"+44 116 262 1528",
    "sg:postcode":"LE1 1FB",
    "sg:province":"Leicestershire",
    "sg:tags":[
        "consultant"
    ],
    "wof:name":"Apex St. Nicholas Job Club",
    "wof:placetype":"venue"
},
  "geometry": {"coordinates":[-1.129391,52.634731],"type":"Point"}
}