{
  "type": "Feature",
  "properties": {
    "addr:full":"96 Maxwell Street Glasgow Glasgow City G1 4EQ",
    "addr:housenumber":"96",
    "addr:postcode":"g1 4eq",
    "addr:street":"Maxwell Street",
    "iso:country":"GB",
    "sg:address":"96 Maxwell Street",
    "sg:city":"Glasgow",
    "sg:classifiers":[
        {
            "category":"Recreation",
            "subcategory":"Dance Hall",
            "type":"Entertainment"
        }
    ],
    "sg:phone":"+44 141 221 6511",
    "sg:postcode":"G1 4EQ",
    "sg:province":"Glasgow City",
    "sg:tags":[
        "disco"
    ],
    "wof:name":"Fury Murrys",
    "wof:placetype":"venue"
},
  "geometry": {"coordinates":[-4.2539749146,55.8560180664],"type":"Point"}
}