{
  "type": "Feature",
  "properties": {
    "addr:full":"Borough Hall, Royal Hill Greenwich Greater London SE10 8RT",
    "addr:postcode":"se10 8rt",
    "addr:street":"Royal Hill",
    "iso:country":"GB",
    "sg:address":"Borough Hall, Royal Hill",
    "sg:city":"Greenwich",
    "sg:classifiers":[
        {
            "category":"Communications",
            "subcategory":"Film & Video Production",
            "type":"Services"
        }
    ],
    "sg:phone":"+44 20 8858 0611",
    "sg:postcode":"SE10 8RT",
    "sg:province":"Greater London",
    "sg:tags":[
        "recording",
        "studio"
    ],
    "wof:name":"Bubblegum",
    "wof:placetype":"venue"
},
  "geometry": {"coordinates":[0.0024349999,51.4844665527],"type":"Point"}
}