{
  "type": "Feature",
  "properties": {
    "iso:country":"GB",
    "sg:address":"Unit 4, Chequetts Lane Industrial Estate",
    "sg:city":"Worcester",
    "sg:classifiers":[
        {
            "category":"Manufacturing",
            "subcategory":"Chemicals & Compounds",
            "type":"Manufacturing & Wholesale Goods"
        }
    ],
    "sg:postcode":"WR3 7JW",
    "sg:province":"Worcestershire",
    "wof:name":"Ropro",
    "wof:placetype":"venue"
},
  "geometry": {"coordinates":[-2.225267,52.216042],"type":"Point"}
}