{
  "type": "Feature",
  "properties": {
    "iso:country":"GB",
    "sg:address":"80 Main Street, Lumphinnans",
    "sg:city":"Cowdenbeath",
    "sg:classifiers":[
        {
            "category":"Fast Food",
            "type":"Food & Drink"
        }
    ],
    "sg:phone":"+44 1383 611383",
    "sg:postcode":"KY4 9HN",
    "sg:province":"Fife",
    "sg:tags":[
        "away",
        "meal",
        "outlet",
        "take"
    ],
    "wof:name":"PEKING CHINESE TAKE AWAY",
    "wof:placetype":"venue"
},
  "geometry": {"coordinates":[-3.334834,56.11919],"type":"Point"}
}