{
  "type": "Feature",
  "properties": {
    "addr:full":"8 Alan Road Witham Essex CM8 1PT",
    "addr:housenumber":"8",
    "addr:postcode":"cm8 1pt",
    "addr:street":"Alan Road",
    "iso:country":"GB",
    "sg:address":"8 Alan Road",
    "sg:city":"Witham",
    "sg:classifiers":[
        {
            "category":"Building & Trades",
            "subcategory":"Construction",
            "type":"Services"
        }
    ],
    "sg:postcode":"CM8 1PT",
    "sg:province":"Essex",
    "sg:tags":[
        "builder",
        "glazier"
    ],
    "wof:name":"S P C Builders Painters & Decorators",
    "wof:placetype":"venue"
},
  "geometry": {"coordinates":[0.6258590221,51.7954521179],"type":"Point"}
}