{
  "type": "Feature",
  "properties": {
    "iso:country":"GB",
    "sg:address":"Unit 4 Western Road",
    "sg:city":"Stratford-upon-avon",
    "sg:classifiers":[
        {
            "category":"Social Services",
            "subcategory":"Child Care",
            "type":"Services"
        },
        {
            "category":"Home & Garden",
            "subcategory":"Household Appliances",
            "type":"Retail Goods"
        },
        {
            "category":"Retail",
            "subcategory":"Repair Shop",
            "type":"Services"
        }
    ],
    "sg:phone":"+44 1789 269078",
    "sg:postcode":"CV37 0AH",
    "sg:province":"Warwickshire",
    "sg:tags":[
        "television",
        "video",
        "servicing",
        "maintenance",
        "electrical",
        "radio"
    ],
    "wof:name":"Avon Electronics",
    "wof:placetype":"venue"
},
  "geometry": {"coordinates":[-1.714044,52.196659],"type":"Point"}
}