{
  "type": "Feature",
  "properties": {
    "addr:full":"2/3 London Road Dover Kent CT17 0ST",
    "addr:housenumber":"2 / 3",
    "addr:postcode":"ct17 0st",
    "addr:street":"London Road",
    "iso:country":"GB",
    "sg:address":"2/3 London Road",
    "sg:city":"Dover",
    "sg:classifiers":[
        {
            "category":"Home & Garden",
            "subcategory":"Building Materials",
            "type":"Retail Goods"
        }
    ],
    "sg:phone":"+44 1304 202247",
    "sg:postcode":"CT17 0ST",
    "sg:province":"Kent",
    "sg:tags":[
        "furnishers",
        "bathroom",
        "planner"
    ],
    "wof:name":"M H K Baths & Kitchens",
    "wof:placetype":"venue"
},
  "geometry": {"coordinates":[1.3048349619,51.1307907104],"type":"Point"}
}