{
  "type": "Feature",
  "properties": {
    "addr:full":"Unit 108, Buspace Studios, Conlan Street London Greater London W10 5AP",
    "addr:housenumber":"108",
    "addr:postcode":"w10 5ap",
    "addr:street":"Conlan Street",
    "iso:country":"GB",
    "sg:address":"Unit 108, Buspace Studios, Conlan Street",
    "sg:city":"London",
    "sg:classifiers":[
        {
            "category":"Travel",
            "subcategory":"Travel Agent",
            "type":"Entertainment"
        },
        {
            "category":"Recreation",
            "subcategory":"Gun Range",
            "type":"Entertainment"
        }
    ],
    "sg:phone":"+44 20 7460 0077",
    "sg:postcode":"W10 5AP",
    "sg:province":"Greater London",
    "sg:tags":[
        "operator",
        "tour",
        "agency",
        "activity"
    ],
    "wof:name":"Tasting Places Ltd",
    "wof:placetype":"venue"
},
  "geometry": {"coordinates":[-0.2112500072,51.5254211426],"type":"Point"}
}