{
  "type": "Feature",
  "properties": {
    "iso:country":"GB",
    "sg:address":"4 George St",
    "sg:city":"Brighton",
    "sg:classifiers":[
        {
            "category":"Organizations",
            "subcategory":"Community Association",
            "type":"Services"
        }
    ],
    "sg:phone":"+44 1273 626228",
    "sg:postcode":"BN2 1RH",
    "sg:province":"East Sussex",
    "sg:tags":[
        "relation",
        "public"
    ],
    "wof:name":"Charisma Public Relations",
    "wof:placetype":"venue"
},
  "geometry": {"coordinates":[-0.134981,50.821133],"type":"Point"}
}