{
  "type": "Feature",
  "properties": {
    "iso:country":"GB",
    "sg:address":"30 Old Road",
    "sg:city":"Cheadle",
    "sg:classifiers":[
        {
            "category":"Professional",
            "subcategory":"Business Services",
            "type":"Services"
        }
    ],
    "sg:phone":"+44 161 428 8143",
    "sg:postcode":"SK8 2BP",
    "sg:province":"Cheshire",
    "sg:tags":[
        "distribution"
    ],
    "wof:name":"C L Davies Ltd.",
    "wof:placetype":"venue"
},
  "geometry": {"coordinates":[-2.20169,53.397415],"type":"Point"}
}