{
  "type": "Feature",
  "properties": {
    "iso:country":"GB",
    "sg:address":"45 Boulevard",
    "sg:city":"Weston Super Mare",
    "sg:classifiers":[
        {
            "category":"Professional",
            "subcategory":"Employment Agencies",
            "type":"Services"
        }
    ],
    "sg:phone":"+44 1934 644443",
    "sg:postcode":"BS23 1PG",
    "sg:province":"Somerset",
    "sg:tags":[
        "career",
        "guidance"
    ],
    "wof:name":"Learning Partnership West",
    "wof:placetype":"venue"
},
  "geometry": {"coordinates":[-2.97212,51.35054],"type":"Point"}
}