{
  "type": "Feature",
  "properties": {
    "addr:full":"Main Rd, Lumphanan Banchory Aberdeen City AB31 4PW",
    "addr:postcode":"ab31 4pw",
    "addr:street":"Main Rd",
    "iso:country":"GB",
    "sg:address":"Main Rd, Lumphanan",
    "sg:city":"Banchory",
    "sg:classifiers":[
        {
            "category":"Sports & Exercise",
            "subcategory":"Golf",
            "type":"Entertainment"
        }
    ],
    "sg:phone":"+44 1339 883480",
    "sg:postcode":"AB31 4PW",
    "sg:province":"Aberdeen City",
    "sg:tags":[
        "course",
        "club"
    ],
    "wof:name":"LUMPHANAN GOLF CLUB",
    "wof:placetype":"venue"
},
  "geometry": {"coordinates":[-2.6884539127,57.1280632019],"type":"Point"}
}