{
  "type": "Feature",
  "properties": {
    "iso:country":"GB",
    "sg:address":"95-97 High Street",
    "sg:city":"West Bromwich",
    "sg:classifiers":[
        {
            "category":"Shopping",
            "subcategory":"Crafts & Fabrics",
            "type":"Retail Goods"
        }
    ],
    "sg:phone":"+44 121 553 4765",
    "sg:postcode":"B70 6NZ",
    "sg:province":"West Midlands",
    "sg:tags":[
        "shop"
    ],
    "wof:name":"Tajinder Bedis",
    "wof:placetype":"venue"
},
  "geometry": {"coordinates":[-1.988269,52.515366],"type":"Point"}
}