{
  "type": "Feature",
  "properties": {
    "addr:full":"Reid Kerr College, Renfrew Road Paisley Renfrewshire PA3 4DR",
    "addr:postcode":"pa3 4dr",
    "addr:street":"Renfrew Road",
    "iso:country":"GB",
    "sg:address":"Reid Kerr College, Renfrew Road",
    "sg:city":"Paisley",
    "sg:classifiers":[
        {
            "category":"Education",
            "subcategory":"University",
            "type":"Public Place"
        }
    ],
    "sg:phone":"+44 141 581 2222",
    "sg:postcode":"PA3 4DR",
    "sg:province":"Renfrewshire",
    "sg:tags":[
        "higher"
    ],
    "wof:name":"Reid Kerr College Enterprises Ltd.",
    "wof:placetype":"venue"
},
  "geometry": {"coordinates":[-4.41887,55.8526],"type":"Point"}
}