{
  "type": "Feature",
  "properties": {
    "addr:full":"Station Road, Legbourne Louth Lincolnshire LN11 8LL",
    "addr:postcode":"ln11 8ll",
    "addr:street":"Station Road;Louth",
    "iso:country":"GB",
    "sg:address":"Station Road, Legbourne",
    "sg:city":"Louth",
    "sg:classifiers":[
        {
            "category":"Government",
            "subcategory":"Post Office",
            "type":"Public Place"
        }
    ],
    "sg:postcode":"LN11 8LL",
    "sg:province":"Lincolnshire",
    "wof:name":"Legbourne Post Office & Stores",
    "wof:placetype":"venue"
},
  "geometry": {"coordinates":[0.0535609983,53.3385734558],"type":"Point"}
}