{
  "type": "Feature",
  "properties": {
    "iso:country":"GB",
    "sg:address":"Station Road, Columbia",
    "sg:city":"Washington",
    "sg:classifiers":[
        {
            "category":"Education",
            "subcategory":"School",
            "type":"Public Place"
        },
        {
            "category":"Government",
            "subcategory":"Office",
            "type":"Public Place"
        }
    ],
    "sg:phone":"+44 191 219 3745",
    "sg:postcode":"NE38 7AR",
    "sg:province":"Durham",
    "sg:tags":[
        "local",
        "authority"
    ],
    "wof:name":"John F Kennedy Primary School",
    "wof:placetype":"venue"
},
  "geometry": {"coordinates":[-1.5317889452,54.8981437683],"type":"Point"}
}