{
  "type": "Feature",
  "properties": {
    "iso:country":"GB",
    "sg:address":"2 Fiddlers La",
    "sg:city":"Chester",
    "sg:classifiers":[
        {
            "category":"Food & Beverages",
            "subcategory":"Meat & Fish",
            "type":"Retail Goods"
        }
    ],
    "sg:phone":"+44 1244 881621",
    "sg:postcode":"CH1 6DH",
    "sg:province":"Cheshire",
    "sg:tags":[
        "chip"
    ],
    "wof:name":"Jady",
    "wof:placetype":"venue"
},
  "geometry": {"coordinates":[-2.938163,53.226864],"type":"Point"}
}