{
  "type": "Feature",
  "properties": {
    "iso:country":"GB",
    "sg:address":"359 Mile End Road",
    "sg:city":"London",
    "sg:classifiers":[
        {
            "category":"Professional",
            "subcategory":"Employment Agencies",
            "type":"Services"
        }
    ],
    "sg:phone":"+44 20 8981 4383",
    "sg:postcode":"E3 4QS",
    "sg:province":"Greater London",
    "sg:tags":[
        "consultant",
        "recruitment"
    ],
    "wof:name":"Globe Recruitment Ltd",
    "wof:placetype":"venue"
},
  "geometry": {"coordinates":[-0.036771,51.524479],"type":"Point"}
}