{
  "type": "Feature",
  "properties": {
    "addr:full":"Pant Y Rhedyn, Cynghordy Llandovery Carmarthenshire SA20 0LP",
    "addr:postcode":"sa20 0lp",
    "addr:street":"Pant Y Rhedyn Cynghordy",
    "iso:country":"GB",
    "sg:address":"Pant Y Rhedyn, Cynghordy",
    "sg:city":"Llandovery",
    "sg:classifiers":[
        {
            "category":"Farming",
            "subcategory":"Farm",
            "type":"Manufacturing & Wholesale Goods"
        }
    ],
    "sg:postcode":"SA20 0LP",
    "sg:province":"Carmarthenshire",
    "sg:tags":[
        "mixed",
        "crop"
    ],
    "wof:name":"W D & B F James",
    "wof:placetype":"venue"
},
  "geometry": {"coordinates":[-3.800155,51.994087],"type":"Point"}
}