{
  "type": "Feature",
  "properties": {
    "iso:country":"GB",
    "sg:address":"Homestead Farm, Back Lane, Holcot",
    "sg:city":"Northampton",
    "sg:classifiers":[
        {
            "category":"Arts & Performance",
            "subcategory":"Art Gallery",
            "type":"Entertainment"
        }
    ],
    "sg:phone":"+44 1604 781180",
    "sg:postcode":"NN6 9SL",
    "sg:province":"Northamptonshire",
    "wof:name":"Axel Haig Gallery",
    "wof:placetype":"venue"
},
  "geometry": {"coordinates":[-0.8376619816,52.3198242188],"type":"Point"}
}