{
  "type": "Feature",
  "properties": {
    "iso:country":"GB",
    "sg:address":"Taunton Chambers, Taunton Road",
    "sg:city":"Swanage",
    "sg:classifiers":[
        {
            "category":"Professional",
            "subcategory":"Lawyer & Legal Services",
            "type":"Services"
        }
    ],
    "sg:phone":"+44 1929 422233",
    "sg:postcode":"BH19 2BY",
    "sg:province":"Dorset",
    "sg:tags":[
        "solicitor"
    ],
    "wof:name":"BUCK EDMUND & CO",
    "wof:placetype":"venue"
},
  "geometry": {"coordinates":[-1.9640660286,50.6119842529],"type":"Point"}
}