{
  "type": "Feature",
  "properties": {
    "iso:country":"GB",
    "sg:address":"6 Lenziemill Road, Cumbernauld",
    "sg:city":"Glasgow",
    "sg:classifiers":[
        {
            "category":"Manufacturing",
            "subcategory":"Metals",
            "type":"Manufacturing & Wholesale Goods"
        }
    ],
    "sg:phone":"+44 1236 728007",
    "sg:postcode":"G67 2RL",
    "sg:province":"Falkirk",
    "sg:tags":[
        "steel",
        "fabricator",
        "erectors"
    ],
    "wof:name":"Gable Fabrications Ltd.",
    "wof:placetype":"venue"
},
  "geometry": {"coordinates":[-3.976015,55.941345],"type":"Point"}
}