{
  "type": "Feature",
  "properties": {
    "iso:country":"GB",
    "sg:address":"10 Acres Berry Hill Industrial Estate",
    "sg:city":"Droitwich",
    "sg:classifiers":[
        {
            "category":"Manufacturing",
            "subcategory":"Building Materials",
            "type":"Manufacturing & Wholesale Goods"
        }
    ],
    "sg:phone":"+44 1905 794986",
    "sg:postcode":"WR9 9BG",
    "sg:province":"Worcestershire",
    "sg:tags":[
        "extrusion"
    ],
    "wof:name":"Ultimate Rubber Co The",
    "wof:placetype":"venue"
},
  "geometry": {"coordinates":[-2.156488,52.268078],"type":"Point"}
}