{
  "type": "Feature",
  "properties": {
    "addr:full":"34 Digby Dr Melton Mowbray Leicestershire LE13 0RQ",
    "addr:housenumber":"34",
    "addr:postcode":"le13 0rq",
    "addr:street":"Digby Dr",
    "iso:country":"GB",
    "sg:address":"34 Digby Dr",
    "sg:city":"Melton Mowbray",
    "sg:classifiers":[
        {
            "category":"Retail",
            "subcategory":"Auto Repair",
            "type":"Services"
        }
    ],
    "sg:phone":"+44 1664 569116",
    "sg:postcode":"LE13 0RQ",
    "sg:province":"Leicestershire",
    "sg:tags":[
        "modification",
        "garage"
    ],
    "wof:name":"P G Motors",
    "wof:placetype":"venue"
},
  "geometry": {"coordinates":[-0.9079989791,52.7511711121],"type":"Point"}
}