{
  "type": "Feature",
  "properties": {
    "addr:full":"14-16 Foxcum Road, Abingdon Business Park Abingdon Oxfordshire OX14 1DZ",
    "addr:housenumber":"14-16",
    "addr:postcode":"ox14 1dz",
    "addr:street":"Foxcum Road;Business Park",
    "iso:country":"GB",
    "sg:address":"14-16 Foxcum Road, Abingdon Business Park",
    "sg:city":"Abingdon",
    "sg:classifiers":[
        {
            "category":"Professional",
            "subcategory":"Computer Services",
            "type":"Services"
        }
    ],
    "sg:phone":"+44 1235 845550",
    "sg:postcode":"OX14 1DZ",
    "sg:province":"Oxfordshire",
    "sg:tags":[
        "system",
        "software"
    ],
    "wof:name":"International Medical Multimedia Ltd.",
    "wof:placetype":"venue"
},
  "geometry": {"coordinates":[-1.2854889631,51.673324585],"type":"Point"}
}