{
  "type": "Feature",
  "properties": {
    "addr:full":"363 Holderness Road Hull East Riding of Yorkshire HU8 8RD",
    "addr:housenumber":"363",
    "addr:postcode":"hu8 8rd",
    "addr:street":"Holderness Road",
    "iso:country":"GB",
    "sg:address":"363 Holderness Road",
    "sg:city":"Hull",
    "sg:classifiers":[
        {
            "category":"Shopping",
            "subcategory":"Used Merchandise",
            "type":"Retail Goods"
        }
    ],
    "sg:postcode":"HU8 8RD",
    "sg:province":"East Riding of Yorkshire",
    "sg:tags":[
        "shop",
        "second-hand"
    ],
    "wof:name":"Floggits",
    "wof:placetype":"venue"
},
  "geometry": {"coordinates":[-0.308971,53.756748],"type":"Point"}
}