{
  "type": "Feature",
  "properties": {
    "addr:full":"7 Putney Hill Putney Greater London SW15 6BA",
    "addr:housenumber":"7",
    "addr:postcode":"sw15 6ba",
    "addr:street":"Putney Hill",
    "iso:country":"GB",
    "sg:address":"7 Putney Hill",
    "sg:city":"Putney",
    "sg:classifiers":[
        {
            "category":"Shopping",
            "subcategory":"Luggage & Leather Goods",
            "type":"Retail Goods"
        }
    ],
    "sg:phone":"+44 20 8788 8738",
    "sg:postcode":"SW15 6BA",
    "sg:province":"Greater London",
    "wof:name":"Alex Lyons Leather",
    "wof:placetype":"venue"
},
  "geometry": {"coordinates":[-0.217245,51.459934],"type":"Point"}
}