{
  "type": "Feature",
  "properties": {
    "addr:full":"West End Penryn Cornwall TR10 8HE",
    "addr:postcode":"tr10 8he",
    "iso:country":"GB",
    "sg:address":"West End",
    "sg:city":"Penryn",
    "sg:classifiers":[
        {
            "category":"Personal",
            "subcategory":"Beauty Salon",
            "type":"Services"
        }
    ],
    "sg:phone":"+44 1326 373557",
    "sg:postcode":"TR10 8HE",
    "sg:province":"Cornwall",
    "sg:tags":[
        "unisex",
        "hairdresser"
    ],
    "wof:name":"Robert's & Emilie",
    "wof:placetype":"venue"
},
  "geometry": {"coordinates":[-5.1048088074,50.1685752869],"type":"Point"}
}