{
  "type": "Feature",
  "properties": {
    "addr:full":"64-66 High St Barnet Hertfordshire EN5 5SJ",
    "addr:housenumber":"64-66",
    "addr:postcode":"en5 5sj",
    "addr:street":"High St",
    "iso:country":"GB",
    "sg:address":"64-66 High St",
    "sg:city":"Barnet",
    "sg:classifiers":[
        {
            "category":"Manufacturing",
            "subcategory":"Chemicals & Compounds",
            "type":"Manufacturing & Wholesale Goods"
        }
    ],
    "sg:phone":"+44 20 8441 4151",
    "sg:postcode":"EN5 5SJ",
    "sg:province":"Hertfordshire",
    "sg:tags":[
        "abrasive",
        "product",
        "cleaning"
    ],
    "wof:name":"Micro-Mash Cushioned Abrasives",
    "wof:placetype":"venue"
},
  "geometry": {"coordinates":[-0.199823007,51.6531257629],"type":"Point"}
}