{
  "type": "Feature",
  "properties": {
    "iso:country":"GB",
    "sg:address":"Tomich Road",
    "sg:city":"Invergordon",
    "sg:classifiers":[
        {
            "category":"Social Services",
            "subcategory":"Adult Care",
            "type":"Services"
        },
        {
            "category":"Government",
            "subcategory":"Office",
            "type":"Public Place"
        }
    ],
    "sg:phone":"+44 1349 854154",
    "sg:postcode":"IV18 0AX",
    "sg:province":"Highland",
    "sg:tags":[
        "local",
        "day",
        "centre"
    ],
    "wof:name":"Isobel Rhind Centre",
    "wof:placetype":"venue"
},
  "geometry": {"coordinates":[-4.164654,57.68969],"type":"Point"}
}