{
  "type": "Feature",
  "properties": {
    "addr:full":"512 Holloway Rd Holloway Greater London N7 6JD",
    "addr:housenumber":"512",
    "addr:postcode":"n7 6jd",
    "addr:street":"Holloway Rd",
    "iso:country":"GB",
    "sg:address":"512 Holloway Rd",
    "sg:city":"Holloway",
    "sg:classifiers":[
        {
            "category":"Cafe",
            "type":"Food & Drink"
        }
    ],
    "sg:phone":"+44 20 7281 7452",
    "sg:postcode":"N7 6JD",
    "sg:province":"Greater London",
    "sg:tags":[
        "tea",
        "room"
    ],
    "wof:name":"Amazon",
    "wof:placetype":"venue"
},
  "geometry": {"coordinates":[-0.121334,51.559139],"type":"Point"}
}