{
  "type": "Feature",
  "properties": {
    "addr:full":"40 Harley Street London Greater London W1G 9PP",
    "addr:housenumber":"40",
    "addr:postcode":"w1g 9pp",
    "addr:street":"Harley Street",
    "iso:country":"GB",
    "sg:address":"40 Harley Street",
    "sg:city":"London",
    "sg:classifiers":[
        {
            "category":"Health Services",
            "subcategory":"Dentist",
            "type":"Services"
        }
    ],
    "sg:phone":"+44 20 7637 7585",
    "sg:postcode":"W1G 9PP",
    "sg:province":"Greater London",
    "wof:name":"Declan Thompson",
    "wof:placetype":"venue"
},
  "geometry": {"coordinates":[-0.146466,51.518383],"type":"Point"}
}