{
  "type": "Feature",
  "properties": {
    "addr:full":"Ferrygate North Berwick East Lothian EH39 5DQ",
    "addr:postcode":"eh39 5dq",
    "addr:street":"Ferrygate North Berwick",
    "iso:country":"GB",
    "sg:address":"Ferrygate",
    "sg:city":"North Berwick",
    "sg:classifiers":[
        {
            "category":"Building & Trades",
            "subcategory":"Construction",
            "type":"Services"
        }
    ],
    "sg:phone":"+44 1620 895550",
    "sg:postcode":"EH39 5DQ",
    "sg:province":"East Lothian",
    "sg:tags":[
        "platform",
        "work",
        "scaffolding"
    ],
    "wof:name":"Lothian Scaffold Services Ltd.",
    "wof:placetype":"venue"
},
  "geometry": {"coordinates":[-2.75005,56.057465],"type":"Point"}
}