{
  "type": "Feature",
  "properties": {
    "iso:country":"GB",
    "sg:address":"34 Middlecott Close",
    "sg:city":"Boston",
    "sg:classifiers":[
        {
            "category":"Organizations",
            "subcategory":"Community Association",
            "type":"Services"
        },
        {
            "category":"Organizations",
            "subcategory":"Non-profit Organization",
            "type":"Services"
        }
    ],
    "sg:phone":"+44 1205 366434",
    "sg:postcode":"PE21 7RD",
    "sg:province":"Lincolnshire",
    "sg:tags":[
        "voluntary",
        "housing",
        "co-operatives",
        "society",
        "trust",
        "organisation",
        "charity"
    ],
    "wof:name":"Nacro Services",
    "wof:placetype":"venue"
},
  "geometry": {"coordinates":[-0.026007,52.965691],"type":"Point"}
}