{
  "type": "Feature",
  "properties": {
    "iso:country":"GB",
    "sg:address":"1-2 Wainman Rd",
    "sg:city":"Peterborough",
    "sg:classifiers":[
        {
            "category":"Wholesale",
            "subcategory":"Books, Periodicals, & Newspapers",
            "type":"Manufacturing & Wholesale Goods"
        }
    ],
    "sg:phone":"+44 1733 230761",
    "sg:postcode":"PE2 7BU",
    "sg:province":"Cambridgeshire",
    "sg:tags":[
        "publishing"
    ],
    "wof:name":"Anchor Books",
    "wof:placetype":"venue"
},
  "geometry": {"coordinates":[-0.264329,52.55397],"type":"Point"}
}