{
  "type": "Feature",
  "properties": {
    "addr:full":"Room 9 Building 305, World Freight Terminal, Manchester Airport Manchester Greater Manchester M90 5PY",
    "addr:housenumber":"9;305",
    "addr:postcode":"m90 5py",
    "iso:country":"GB",
    "sg:address":"Room 9 Building 305, World Freight Terminal, Manchester Airport",
    "sg:city":"Manchester",
    "sg:classifiers":[
        {
            "category":"Freight",
            "type":"Transportation"
        }
    ],
    "sg:phone":"+44 161 437 7800",
    "sg:postcode":"M90 5PY",
    "sg:province":"Greater Manchester",
    "sg:tags":[
        "forwarders"
    ],
    "wof:name":"Cargo World (North) Ltd.",
    "wof:placetype":"venue"
},
  "geometry": {"coordinates":[-2.289249897,53.3623580933],"type":"Point"}
}