{
  "type": "Feature",
  "properties": {
    "addr:full":"199 Coalway Road Wolverhampton Staffordshire WV3 7NG",
    "addr:housenumber":"199",
    "addr:postcode":"wv3 7ng",
    "addr:street":"Coalway Road",
    "iso:country":"GB",
    "sg:address":"199 Coalway Road",
    "sg:city":"Wolverhampton",
    "sg:classifiers":[
        {
            "category":"Shopping",
            "subcategory":"News",
            "type":"Retail Goods"
        }
    ],
    "sg:phone":"+44 1902 335778",
    "sg:postcode":"WV3 7NG",
    "sg:province":"Staffordshire",
    "sg:tags":[
        "newsagent"
    ],
    "wof:name":"Island Newsagents",
    "wof:placetype":"venue"
},
  "geometry": {"coordinates":[-2.149609,52.569061],"type":"Point"}
}