{
  "type": "Feature",
  "properties": {
    "iso:country":"GB",
    "sg:address":"Elmsworth Farm, Elmsworth Lane, Porchfield",
    "sg:city":"Newport",
    "sg:classifiers":[
        {
            "category":"Farming",
            "subcategory":"Livestock Farm",
            "type":"Manufacturing & Wholesale Goods"
        }
    ],
    "sg:postcode":"PO30 4LR",
    "sg:province":"Isle of Wight",
    "sg:tags":[
        "others"
    ],
    "wof:name":"George Ablitt",
    "wof:placetype":"venue"
},
  "geometry": {"coordinates":[-1.3687989712,50.7189445496],"type":"Point"}
}