{
  "type": "Feature",
  "properties": {
    "iso:country":"GB",
    "sg:address":"Dairy Farm, Camps Heath, Oulton",
    "sg:city":"Lowestoft",
    "sg:classifiers":[
        {
            "category":"Farming",
            "subcategory":"Livestock Farm",
            "type":"Manufacturing & Wholesale Goods"
        }
    ],
    "sg:phone":"+44 1502 565957",
    "sg:postcode":"NR32 5DW",
    "sg:province":"Suffolk",
    "sg:tags":[
        "others"
    ],
    "wof:name":"Burton,C,",
    "wof:placetype":"venue"
},
  "geometry": {"coordinates":[1.6973899603,52.4870109558],"type":"Point"}
}