{
  "type": "Feature",
  "properties": {
    "iso:country":"GB",
    "sg:address":"Hatchwood Place, Farnham Road, Odiham",
    "sg:city":"Basingstoke",
    "sg:classifiers":[
        {
            "category":"Communications",
            "type":"Services"
        }
    ],
    "sg:phone":"+44 1256 709200",
    "sg:postcode":"RG29 1AB",
    "sg:province":"Hampshire",
    "sg:tags":[
        "data",
        "network"
    ],
    "wof:name":"Telindus Ltd.",
    "wof:placetype":"venue"
},
  "geometry": {"coordinates":[-0.9477689862,51.2456665039],"type":"Point"}
}