{
  "type": "Feature",
  "properties": {
    "addr:full":"33 Marsden Drive Scunthorpe Lincolnshire DN15 8AL",
    "addr:housenumber":"33",
    "addr:postcode":"dn15 8al",
    "addr:street":"Marsden Drive",
    "iso:country":"GB",
    "sg:address":"33 Marsden Drive",
    "sg:city":"Scunthorpe",
    "sg:classifiers":[
        {
            "category":"Food & Beverages",
            "subcategory":"Groceries & Convenience Stores",
            "type":"Retail Goods"
        }
    ],
    "sg:phone":"+44 1724 278877",
    "sg:postcode":"DN15 8AL",
    "sg:province":"Lincolnshire",
    "wof:name":"Londis",
    "wof:placetype":"venue"
},
  "geometry": {"coordinates":[-0.67862,53.592926],"type":"Point"}
}