{
  "type": "Feature",
  "properties": {
    "iso:country":"GB",
    "sg:address":"645 Uxbridge Road",
    "sg:city":"Hayes",
    "sg:classifiers":[
        {
            "category":"Home & Garden",
            "subcategory":"Hardware",
            "type":"Retail Goods"
        }
    ],
    "sg:phone":"+44 20 8573 4471",
    "sg:postcode":"UB4 8HS",
    "sg:province":"Greater London",
    "sg:tags":[
        "tubing",
        "fitting",
        "hose",
        "diy"
    ],
    "wof:name":"West London Hose & Hydraulics Supplies",
    "wof:placetype":"venue"
},
  "geometry": {"coordinates":[-0.431811,51.524635],"type":"Point"}
}