{
  "type": "Feature",
  "properties": {
    "addr:full":"Pantyrhaidd, Cwm Cou Newcastle Emlyn Carmarthenshire SA38 9PZ",
    "addr:postcode":"sa38 9pz",
    "addr:street":"Cwm",
    "iso:country":"GB",
    "sg:address":"Pantyrhaidd, Cwm Cou",
    "sg:city":"Newcastle Emlyn",
    "sg:classifiers":[
        {
            "category":"Banks & Credit Unions",
            "subcategory":"Investment Brokerage",
            "type":"Services"
        }
    ],
    "sg:postcode":"SA38 9PZ",
    "sg:province":"Carmarthenshire",
    "sg:tags":[
        "contractor"
    ],
    "wof:name":"D R Owens",
    "wof:placetype":"venue"
},
  "geometry": {"coordinates":[-4.4679841995,52.0359191895],"type":"Point"}
}