{
  "type": "Feature",
  "properties": {
    "addr:full":"Unit 4, Pepper Road, Hazel Grove Stockport Cheshire SK7 5BW",
    "addr:housenumber":"unit 4",
    "addr:postcode":"sk7 5bw",
    "addr:street":"Pepper Road",
    "iso:country":"GB",
    "sg:address":"Unit 4, Pepper Road, Hazel Grove",
    "sg:city":"Stockport",
    "sg:classifiers":[
        {
            "category":"Food & Beverages",
            "subcategory":"Specialty",
            "type":"Retail Goods"
        }
    ],
    "sg:phone":"+44 161 483 1235",
    "sg:postcode":"SK7 5BW",
    "sg:province":"Cheshire",
    "sg:tags":[
        "product",
        "health"
    ],
    "wof:name":"Cedar Health Ltd.",
    "wof:placetype":"venue"
},
  "geometry": {"coordinates":[-2.137787,53.377171],"type":"Point"}
}