{
  "type": "Feature",
  "properties": {
    "iso:country":"GB",
    "sg:address":"Unit 10, Horwood Court, Bletchley",
    "sg:city":"Milton Keynes",
    "sg:classifiers":[
        {
            "category":"Building & Trades",
            "subcategory":"Construction",
            "type":"Services"
        }
    ],
    "sg:phone":"+44 1908 560011",
    "sg:postcode":"MK1 1RD",
    "sg:province":"Buckinghamshire",
    "sg:tags":[
        "furnace"
    ],
    "wof:name":"Milton House Services Ltd.",
    "wof:placetype":"venue"
},
  "geometry": {"coordinates":[-0.721066,52.001945],"type":"Point"}
}