{
  "type": "Feature",
  "properties": {
    "addr:full":"36 Oxford Rd Leicester Leicestershire LE2 1TN",
    "addr:housenumber":"36",
    "addr:postcode":"le2 1tn",
    "addr:street":"Oxford Rd",
    "iso:country":"GB",
    "sg:address":"36 Oxford Rd",
    "sg:city":"Leicester",
    "sg:classifiers":[
        {
            "category":"Shopping",
            "subcategory":"Computers & Home Electronics",
            "type":"Retail Goods"
        }
    ],
    "sg:postcode":"LE2 1TN",
    "sg:province":"Leicestershire",
    "sg:tags":[
        "electrical"
    ],
    "wof:name":"Electrical Surplus Supplies",
    "wof:placetype":"venue"
},
  "geometry": {"coordinates":[-1.118181,52.61747],"type":"Point"}
}