{
  "type": "Feature",
  "properties": {
    "addr:full":"Watchouse Road, Galleywood Chelmsford Essex CM2 8NH",
    "addr:postcode":"cm2 8nh",
    "addr:street":"Watchouse Road",
    "iso:country":"GB",
    "sg:address":"Watchouse Road, Galleywood",
    "sg:city":"Chelmsford",
    "sg:classifiers":[
        {
            "category":"Bars & Pubs",
            "type":"Food & Drink"
        }
    ],
    "sg:phone":"+44 1245 353034",
    "sg:postcode":"CM2 8NH",
    "sg:province":"Essex",
    "sg:tags":[
        "pubs",
        "inn"
    ],
    "wof:name":"The White Bear",
    "wof:placetype":"venue"
},
  "geometry": {"coordinates":[0.466357,51.69701],"type":"Point"}
}