{
  "type": "Feature",
  "properties": {
    "addr:full":"37a Hogarth Avenue Ashford Greater London TW15 1QB",
    "addr:housenumber":"37a",
    "addr:postcode":"tw15 1qb",
    "addr:street":"Hogarth Avenue",
    "iso:country":"GB",
    "sg:address":"37a Hogarth Avenue",
    "sg:city":"Ashford",
    "sg:classifiers":[
        {
            "category":"Building & Trades",
            "subcategory":"Landscaping Services",
            "type":"Services"
        }
    ],
    "sg:postcode":"TW15 1QB",
    "sg:province":"Greater London",
    "sg:tags":[
        "landscape",
        "contractor"
    ],
    "wof:name":"Colin Hay",
    "wof:placetype":"venue"
},
  "geometry": {"coordinates":[-0.443433,51.424995],"type":"Point"}
}