{
  "type": "Feature",
  "properties": {
    "addr:full":"Leahs Yard, Meadow Lane Alfreton Derbyshire DE55 7FH",
    "addr:postcode":"de55 7fh",
    "addr:street":"Meadow Lane",
    "iso:country":"GB",
    "sg:address":"Leahs Yard, Meadow Lane",
    "sg:city":"Alfreton",
    "sg:classifiers":[
        {
            "category":"Manufacturing",
            "subcategory":"Building Materials",
            "type":"Manufacturing & Wholesale Goods"
        }
    ],
    "sg:phone":"+44 1773 832653",
    "sg:postcode":"DE55 7FH",
    "sg:province":"Derbyshire",
    "sg:tags":[
        "merchant",
        "builder"
    ],
    "wof:name":"Builder Center",
    "wof:placetype":"venue"
},
  "geometry": {"coordinates":[-1.3850489855,53.097618103],"type":"Point"}
}