{
  "type": "Feature",
  "properties": {
    "iso:country":"GB",
    "sg:address":"23b Galloway Street",
    "sg:city":"Dumfries",
    "sg:classifiers":[
        {
            "category":"Personal",
            "subcategory":"Beauty Salon",
            "type":"Services"
        },
        {
            "category":"Personal",
            "subcategory":"Barber",
            "type":"Services"
        }
    ],
    "sg:phone":"+44 1387 263137",
    "sg:postcode":"DG2 7TL",
    "sg:province":"Dumfries and Galloway",
    "sg:tags":[
        "unisex",
        "hairdresser"
    ],
    "wof:name":"Eclipse Hair Salon",
    "wof:placetype":"venue"
},
  "geometry": {"coordinates":[-3.6195058823,55.0683250427],"type":"Point"}
}