{
  "type": "Feature",
  "properties": {
    "iso:country":"GB",
    "sg:address":"52 School Lane, Blean",
    "sg:city":"Canterbury",
    "sg:classifiers":[
        {
            "category":"Professional",
            "subcategory":"Art Services",
            "type":"Services"
        }
    ],
    "sg:postcode":"CT2 9JA",
    "sg:province":"Kent",
    "sg:tags":[
        "photographer"
    ],
    "wof:name":"Advantage P P S",
    "wof:placetype":"venue"
},
  "geometry": {"coordinates":[1.045073,51.30928],"type":"Point"}
}