{
  "type": "Feature",
  "properties": {
    "addr:full":"Mosshead, Kemnay Inverurie Aberdeenshire AB51 5PA",
    "addr:postcode":"ab51 5pa",
    "iso:country":"GB",
    "sg:address":"Mosshead, Kemnay",
    "sg:city":"Inverurie",
    "sg:classifiers":[
        {
            "category":"Farming",
            "subcategory":"Farm",
            "type":"Manufacturing & Wholesale Goods"
        }
    ],
    "sg:phone":"+44 1467 642267",
    "sg:postcode":"AB51 5PA",
    "sg:province":"Aberdeenshire",
    "sg:tags":[
        "mixed",
        "crop"
    ],
    "wof:name":"Alexander Cook & Son",
    "wof:placetype":"venue"
},
  "geometry": {"coordinates":[-2.4416160583,57.2333183289],"type":"Point"}
}