{
  "type": "Feature",
  "properties": {
    "iso:country":"GB",
    "sg:address":"121 London Road",
    "sg:city":"Knebworth",
    "sg:classifiers":[
        {
            "category":"Fast Food",
            "type":"Food & Drink"
        }
    ],
    "sg:postcode":"SG3 6EX",
    "sg:province":"Hertfordshire",
    "sg:tags":[
        "away",
        "take"
    ],
    "wof:name":"Topgift Limited",
    "wof:placetype":"venue"
},
  "geometry": {"coordinates":[-0.184109,51.853519],"type":"Point"}
}