{
  "type": "Feature",
  "properties": {
    "iso:country":"GB",
    "sg:address":"Windsmead, Bread Street, Ruscombe",
    "sg:city":"Stroud",
    "sg:classifiers":[
        {
            "category":"Manufacturing",
            "subcategory":"Aerospace",
            "type":"Manufacturing & Wholesale Goods"
        }
    ],
    "sg:postcode":"GL6 6EL",
    "sg:province":"Gloucestershire",
    "sg:tags":[
        "aircraft",
        "furnishing",
        "fitting"
    ],
    "wof:name":"Aerodynamics Ltd.",
    "wof:placetype":"venue"
},
  "geometry": {"coordinates":[-2.246113,51.762886],"type":"Point"}
}