{
  "type": "Feature",
  "properties": {
    "iso:country":"GB",
    "sg:address":"7 Wyvern Buildings, Grove Trading Estate",
    "sg:city":"Dorchester",
    "sg:classifiers":[
        {
            "category":"Personal",
            "type":"Services"
        },
        {
            "category":"Freight",
            "type":"Transportation"
        }
    ],
    "sg:phone":"+44 1305 251002",
    "sg:postcode":"DT1 1ST",
    "sg:province":"Dorset",
    "sg:tags":[
        "delivery",
        "haulage",
        "road"
    ],
    "wof:name":"Amtrak Express Parcels",
    "wof:placetype":"venue"
},
  "geometry": {"coordinates":[-2.441564,50.711906],"type":"Point"}
}