{
  "type": "Feature",
  "properties": {
    "addr:full":"White Hart Lane, Charter Alley Tadley Berkshire RG26 5QA",
    "addr:postcode":"rg26 5qa",
    "addr:street":"Lane Charter",
    "iso:country":"GB",
    "sg:address":"White Hart Lane, Charter Alley",
    "sg:city":"Tadley",
    "sg:classifiers":[
        {
            "category":"Bars & Pubs",
            "type":"Food & Drink"
        },
        {
            "category":"Community Center",
            "subcategory":"Social",
            "type":"Public Place"
        }
    ],
    "sg:phone":"+44 1256 850048",
    "sg:postcode":"RG26 5QA",
    "sg:province":"Berkshire",
    "sg:tags":[
        "pubs",
        "house",
        "inn",
        "activity"
    ],
    "wof:name":"The White Hart Inn",
    "wof:placetype":"venue"
},
  "geometry": {"coordinates":[-1.149135,51.315342],"type":"Point"}
}