{
  "type": "Feature",
  "properties": {
    "addr:full":"2 Tower Building, Lower Mills Road, Farnley Leeds West Yorkshire LS12 4UY",
    "addr:housenumber":"2",
    "addr:postcode":"ls12 4uy",
    "addr:street":"Lower Mills Road",
    "iso:country":"GB",
    "sg:address":"2 Tower Building, Lower Mills Road, Farnley",
    "sg:city":"Leeds",
    "sg:classifiers":[
        {
            "category":"Home & Garden",
            "subcategory":"Home Furnishings",
            "type":"Retail Goods"
        },
        {
            "category":"Home & Garden",
            "subcategory":"Carpets & Floor Coverings",
            "type":"Retail Goods"
        }
    ],
    "sg:phone":"+44 113 282 4134",
    "sg:postcode":"LS12 4UY",
    "sg:province":"West Yorkshire",
    "sg:tags":[
        "fitting",
        "rug",
        "matting",
        "carpets"
    ],
    "wof:name":"David E Elley",
    "wof:placetype":"venue"
},
  "geometry": {"coordinates":[-1.59734,53.7826],"type":"Point"}
}