{
  "type": "Feature",
  "properties": {
    "iso:country":"GB",
    "sg:address":"19 Church Street, Seal",
    "sg:city":"Sevenoaks",
    "sg:classifiers":[
        {
            "category":"Shopping",
            "subcategory":"Clothing, Apparel, & Fashions",
            "type":"Retail Goods"
        }
    ],
    "sg:phone":"+44 1732 762155",
    "sg:postcode":"TN15 0AR",
    "sg:province":"Kent",
    "sg:tags":[
        "dresswear"
    ],
    "wof:name":"Deja-Vu",
    "wof:placetype":"venue"
},
  "geometry": {"coordinates":[0.22195,51.28867],"type":"Point"}
}