{
  "type": "Feature",
  "properties": {
    "addr:full":"57 Welland Vale Road Leicester Leicestershire LE5 6PX",
    "addr:housenumber":"57",
    "addr:postcode":"le5 6px",
    "addr:street":"Welland Vale Road",
    "iso:country":"GB",
    "sg:address":"57 Welland Vale Road",
    "sg:city":"Leicester",
    "sg:classifiers":[
        {
            "category":"Retail",
            "subcategory":"Repair Shop",
            "type":"Services"
        }
    ],
    "sg:postcode":"LE5 6PX",
    "sg:province":"Leicestershire",
    "sg:tags":[
        "radio",
        "television",
        "video"
    ],
    "wof:name":"T V Pages & Video Services",
    "wof:placetype":"venue"
},
  "geometry": {"coordinates":[-1.0574519634,52.6287307739],"type":"Point"}
}