{
  "type": "Feature",
  "properties": {
    "addr:full":"Back Beamish Street Stanley Durham DH9 8AH",
    "addr:postcode":"dh9 8ah",
    "addr:street":"Beamish Street",
    "iso:country":"GB",
    "sg:address":"Back Beamish Street",
    "sg:city":"Stanley",
    "sg:classifiers":[
        {
            "category":"Ice Cream",
            "type":"Food & Drink"
        }
    ],
    "sg:phone":"+44 1207 232208",
    "sg:postcode":"DH9 8AH",
    "sg:province":"Durham",
    "sg:tags":[
        "shop",
        "mobile",
        "parlour"
    ],
    "wof:name":"Roma Ices",
    "wof:placetype":"venue"
},
  "geometry": {"coordinates":[-1.6981240511,54.8718833923],"type":"Point"}
}