{
  "type": "Feature",
  "properties": {
    "iso:country":"GB",
    "sg:address":"Botley Mills, Botley",
    "sg:city":"Southampton",
    "sg:classifiers":[
        {
            "category":"Shopping",
            "subcategory":"Jewelry",
            "type":"Retail Goods"
        }
    ],
    "sg:phone":"+44 1489 796669",
    "sg:postcode":"SO30 2GB",
    "sg:province":"Hampshire",
    "sg:tags":[
        "gold",
        "silversmith"
    ],
    "wof:name":"James W Potter & Sons",
    "wof:placetype":"venue"
},
  "geometry": {"coordinates":[-1.270219,50.914333],"type":"Point"}
}