{
  "type": "Feature",
  "properties": {
    "addr:full":"15 Suffolk Parade Cheltenham Gloucestershire GL50 2AE",
    "addr:housenumber":"15",
    "addr:postcode":"gl50 2ae",
    "addr:street":"Suffolk Parade",
    "iso:country":"GB",
    "sg:address":"15 Suffolk Parade",
    "sg:city":"Cheltenham",
    "sg:classifiers":[
        {
            "category":"Food & Beverages",
            "subcategory":"Liquor & Beverages",
            "type":"Retail Goods"
        }
    ],
    "sg:postcode":"GL50 2AE",
    "sg:province":"Gloucestershire",
    "sg:tags":[
        "beer",
        "spirit",
        "wines"
    ],
    "wof:name":"Rose Tree Wines Ltd.",
    "wof:placetype":"venue"
},
  "geometry": {"coordinates":[-2.080046,51.892494],"type":"Point"}
}