{
  "type": "Feature",
  "properties": {
    "iso:country":"GB",
    "sg:address":"78 Swan Street, Sileby",
    "sg:city":"Loughborough",
    "sg:classifiers":[
        {
            "category":"Manufacturing",
            "subcategory":"Tools & Machinery",
            "type":"Manufacturing & Wholesale Goods"
        },
        {
            "category":"Insurance",
            "subcategory":"Insurance Agent",
            "type":"Services"
        }
    ],
    "sg:phone":"+44 1509 814264",
    "sg:postcode":"LE12 7NW",
    "sg:province":"Leicestershire",
    "sg:tags":[
        "society",
        "friendly"
    ],
    "wof:name":"Wartburg Insurance Services",
    "wof:placetype":"venue"
},
  "geometry": {"coordinates":[-1.0837090015,52.7517700195],"type":"Point"}
}