{
  "type": "Feature",
  "properties": {
    "iso:country":"GB",
    "sg:address":"The Pheasantry Vicarage Hill",
    "sg:city":"Westerham",
    "sg:classifiers":[
        {
            "category":"Shopping",
            "subcategory":"Pharmacy",
            "type":"Retail Goods"
        }
    ],
    "sg:phone":"+44 1959 565926",
    "sg:postcode":"TN16 1AY",
    "sg:province":"Kent",
    "sg:tags":[
        "medicine",
        "therapy"
    ],
    "wof:name":"Body Stress Release Centre",
    "wof:placetype":"venue"
},
  "geometry": {"coordinates":[0.071265,51.267075],"type":"Point"}
}