{
  "type": "Feature",
  "properties": {
    "addr:full":"Waterside, Halfway Bridge Petworth West Sussex GU28 9BP",
    "addr:housenumber":"petworth",
    "addr:postcode":"gu28 9bp",
    "iso:country":"GB",
    "sg:address":"Waterside, Halfway Bridge",
    "sg:city":"Petworth",
    "sg:classifiers":[
        {
            "category":"Education",
            "subcategory":"Junior College",
            "type":"Public Place"
        }
    ],
    "sg:phone":"+44 1798 861782",
    "sg:postcode":"GU28 9BP",
    "sg:province":"West Sussex",
    "sg:tags":[
        "educational",
        "resource"
    ],
    "wof:name":"Watermeadow Educational Art Supplies",
    "wof:placetype":"venue"
},
  "geometry": {"coordinates":[-0.6078540087,50.9861068726],"type":"Point"}
}