{
  "type": "Feature",
  "properties": {
    "iso:country":"GB",
    "sg:address":"Unit 31, Hainge Road Tividale",
    "sg:city":"Oldbury",
    "sg:classifiers":[
        {
            "category":"Home & Garden",
            "subcategory":"Hardware",
            "type":"Retail Goods"
        }
    ],
    "sg:phone":"+44 121 520 7772",
    "sg:postcode":"B69 2PA",
    "sg:province":"West Midlands",
    "sg:tags":[
        "paint"
    ],
    "wof:name":"Armour Industrial Coatings Ltd.",
    "wof:placetype":"venue"
},
  "geometry": {"coordinates":[-2.043004,52.513641],"type":"Point"}
}