{
  "type": "Feature",
  "properties": {
    "addr:full":"The Catacombs Stables Market, Chalk Farm Rd Camden Greater London NW1 8AH",
    "addr:postcode":"nw1 8ah",
    "addr:street":"Chalk Farm Rd",
    "iso:country":"GB",
    "sg:address":"The Catacombs Stables Market, Chalk Farm Rd",
    "sg:city":"Camden",
    "sg:classifiers":[
        {
            "category":"Building & Trades",
            "subcategory":"Construction",
            "type":"Services"
        }
    ],
    "sg:phone":"+44 20 7284 1088",
    "sg:postcode":"NW1 8AH",
    "sg:province":"Greater London",
    "sg:tags":[
        "tiling",
        "contractor"
    ],
    "wof:name":"Shale Mosaic",
    "wof:placetype":"venue"
},
  "geometry": {"coordinates":[-0.1480499953,51.5422401428],"type":"Point"}
}