{
  "type": "Feature",
  "properties": {
    "iso:country":"GB",
    "sg:address":"206 Rayleigh Rd",
    "sg:city":"Brentwood",
    "sg:classifiers":[
        {
            "category":"Shopping",
            "subcategory":"Florist",
            "type":"Retail Goods"
        }
    ],
    "sg:phone":"+44 1277 261744",
    "sg:postcode":"CM13 1PN",
    "sg:province":"Essex",
    "wof:name":"Karens",
    "wof:placetype":"venue"
},
  "geometry": {"coordinates":[0.355965,51.633347],"type":"Point"}
}