{
  "type": "Feature",
  "properties": {
    "iso:country":"GB",
    "sg:address":"34 East Street",
    "sg:city":"Faversham",
    "sg:classifiers":[
        {
            "category":"Professional",
            "subcategory":"Detective & Security Services",
            "type":"Services"
        }
    ],
    "sg:phone":"+44 1795 535535",
    "sg:postcode":"ME13 8AS",
    "sg:province":"Kent",
    "wof:name":"Longhurst Securities Ltd.",
    "wof:placetype":"venue"
},
  "geometry": {"coordinates":[0.895857,51.314655],"type":"Point"}
}