{
  "type": "Feature",
  "properties": {
    "iso:country":"GB",
    "sg:address":"15 Kirkgate",
    "sg:city":"Shipley",
    "sg:classifiers":[
        {
            "category":"Food & Beverages",
            "subcategory":"Meat & Fish",
            "type":"Retail Goods"
        }
    ],
    "sg:phone":"+44 1274 532226",
    "sg:postcode":"BD18 3QW",
    "sg:province":"West Yorkshire",
    "sg:tags":[
        "chip"
    ],
    "wof:name":"Eglefin",
    "wof:placetype":"venue"
},
  "geometry": {"coordinates":[-1.777438,53.834167],"type":"Point"}
}