{
  "type": "Feature",
  "properties": {
    "addr:full":"8-10 Fore St Brixham Devon TQ5 8DS",
    "addr:housenumber":"8-10",
    "addr:postcode":"tq5 8ds",
    "addr:street":"Fore St",
    "iso:country":"GB",
    "sg:address":"8-10 Fore St",
    "sg:city":"Brixham",
    "sg:classifiers":[
        {
            "category":"Food & Beverages",
            "subcategory":"Fruits & Vegetables",
            "type":"Retail Goods"
        }
    ],
    "sg:postcode":"TQ5 8DS",
    "sg:province":"Devon",
    "sg:tags":[
        "greengrocer"
    ],
    "wof:name":"Jaycock,Margaret,",
    "wof:placetype":"venue"
},
  "geometry": {"coordinates":[-3.5153119564,50.394367218],"type":"Point"}
}