{
  "type": "Feature",
  "properties": {
    "iso:country":"GB",
    "sg:address":"518 Mather Avenue",
    "sg:city":"Liverpool",
    "sg:classifiers":[
        {
            "category":"Food & Beverages",
            "subcategory":"Meat & Fish",
            "type":"Retail Goods"
        }
    ],
    "sg:phone":"+44 151 427 4027",
    "sg:postcode":"L19 4UG",
    "sg:province":"Merseyside",
    "sg:tags":[
        "butcher"
    ],
    "wof:name":"Diane McStraw",
    "wof:placetype":"venue"
},
  "geometry": {"coordinates":[-2.8930540085,53.3662796021],"type":"Point"}
}