{
  "type": "Feature",
  "properties": {
    "addr:full":"The Mow Cottage, Chobham Road, Lower Knaphill Woking Surrey GU21 2JB",
    "addr:postcode":"gu21 2jb",
    "addr:street":"Chobham Road Lower",
    "iso:country":"GB",
    "sg:address":"The Mow Cottage, Chobham Road, Lower Knaphill",
    "sg:city":"Woking",
    "sg:classifiers":[
        {
            "category":"Professional",
            "subcategory":"Management & Consulting",
            "type":"Services"
        }
    ],
    "sg:phone":"+44 1483 472260",
    "sg:postcode":"GU21 2JB",
    "sg:province":"Surrey",
    "sg:tags":[
        "consultant",
        "specialist"
    ],
    "wof:name":"Gill White",
    "wof:placetype":"venue"
},
  "geometry": {"coordinates":[-0.615927,51.318832],"type":"Point"}
}