{
  "type": "Feature",
  "properties": {
    "iso:country":"GB",
    "sg:address":"9 Downham Road South, Heswall",
    "sg:city":"Wirral",
    "sg:classifiers":[
        {
            "category":"Professional",
            "subcategory":"Accounting & Tax Preparation",
            "type":"Services"
        }
    ],
    "sg:phone":"+44 151 342 6669",
    "sg:postcode":"CH60 5RG",
    "sg:province":"Merseyside",
    "sg:tags":[
        "payroll"
    ],
    "wof:name":"Heswall Business Services",
    "wof:placetype":"venue"
},
  "geometry": {"coordinates":[-3.0938038826,53.3290252686],"type":"Point"}
}