{
  "type": "Feature",
  "properties": {
    "iso:country":"GB",
    "sg:address":"29a Water La",
    "sg:city":"Wilmslow",
    "sg:classifiers":[
        {
            "category":"Professional",
            "subcategory":"Engineering",
            "type":"Services"
        }
    ],
    "sg:postcode":"SK9 5AR",
    "sg:province":"Cheshire",
    "sg:tags":[
        "consultant",
        "structural"
    ],
    "wof:name":"Seymour,Harry,& Associates Ltd",
    "wof:placetype":"venue"
},
  "geometry": {"coordinates":[-2.234958,53.326103],"type":"Point"}
}