{
  "type": "Feature",
  "properties": {
    "addr:full":"Harplaw Farm, Brisbane Glen Road Largs North Ayrshire KA30 8SH",
    "addr:postcode":"ka30 8sh",
    "addr:street":"Brisbane Glen Road",
    "iso:country":"GB",
    "sg:address":"Harplaw Farm, Brisbane Glen Road",
    "sg:city":"Largs",
    "sg:classifiers":[
        {
            "category":"Farming",
            "subcategory":"Livestock Farm",
            "type":"Manufacturing & Wholesale Goods"
        }
    ],
    "sg:phone":"+44 1475 673167",
    "sg:postcode":"KA30 8SH",
    "sg:province":"North Ayrshire",
    "sg:tags":[
        "others"
    ],
    "wof:name":"J & W Mcnicol",
    "wof:placetype":"venue"
},
  "geometry": {"coordinates":[-4.861438,55.80423],"type":"Point"}
}