{
  "type": "Feature",
  "properties": {
    "addr:full":"Ceader House, Ceader Road Camberley Hampshire GU16 7HZ",
    "addr:postcode":"gu16 7hz",
    "addr:street":"Ceader Road",
    "iso:country":"GB",
    "sg:address":"Ceader House, Ceader Road",
    "sg:city":"Camberley",
    "sg:classifiers":[
        {
            "category":"Social Services",
            "subcategory":"Job Training",
            "type":"Services"
        }
    ],
    "sg:phone":"+44 1276 62121",
    "sg:postcode":"GU16 7HZ",
    "sg:province":"Hampshire",
    "sg:tags":[
        "draughtsman",
        "drawing"
    ],
    "wof:name":"Herron Associates",
    "wof:placetype":"venue"
},
  "geometry": {"coordinates":[-0.7437630296,51.3135719299],"type":"Point"}
}