{
  "type": "Feature",
  "properties": {
    "addr:full":"8 West Street Chipping Norton Gloucestershire OX7 5AA",
    "addr:housenumber":"8",
    "addr:postcode":"ox7 5aa",
    "addr:street":"West Street",
    "iso:country":"GB",
    "sg:address":"8 West Street",
    "sg:city":"Chipping Norton",
    "sg:classifiers":[
        {
            "category":"Shopping",
            "subcategory":"Books",
            "type":"Retail Goods"
        }
    ],
    "sg:phone":"+44 1608 641033",
    "sg:postcode":"OX7 5AA",
    "sg:province":"Gloucestershire",
    "sg:tags":[
        "bookseller"
    ],
    "wof:name":"The Bookshop",
    "wof:placetype":"venue"
},
  "geometry": {"coordinates":[-1.5457010269,51.940372467],"type":"Point"}
}