{
  "type": "Feature",
  "properties": {
    "iso:country":"GB",
    "sg:address":"13-15 North Marine Road",
    "sg:city":"Scarborough",
    "sg:classifiers":[
        {
            "category":"Home & Garden",
            "subcategory":"Furniture",
            "type":"Retail Goods"
        }
    ],
    "sg:phone":"+44 1723 361351",
    "sg:postcode":"YO12 7EY",
    "sg:province":"North Yorkshire",
    "wof:name":"Rymer Schorah Furnishing Ltd.",
    "wof:placetype":"venue"
},
  "geometry": {"coordinates":[-0.401226,54.286846],"type":"Point"}
}