{
  "type": "Feature",
  "properties": {
    "addr:full":"Chilwell Retail Park, Beeston Nottingham Nottinghamshire NG9 6DS",
    "addr:postcode":"ng9 6ds",
    "addr:street":"Park",
    "iso:country":"GB",
    "sg:address":"Chilwell Retail Park, Beeston",
    "sg:city":"Nottingham",
    "sg:classifiers":[
        {
            "category":"Farming",
            "subcategory":"Fish & Marine Products",
            "type":"Manufacturing & Wholesale Goods"
        }
    ],
    "sg:phone":"+44 115 946 4200",
    "sg:postcode":"NG9 6DS",
    "sg:province":"Nottinghamshire",
    "sg:tags":[
        "fishmonger"
    ],
    "wof:name":"Steers Butchers",
    "wof:placetype":"venue"
},
  "geometry": {"coordinates":[-1.243619,52.903976],"type":"Point"}
}