{
  "type": "Feature",
  "properties": {
    "addr:full":"1 Gatley Drive Guildford Surrey GU4 7JJ",
    "addr:housenumber":"1",
    "addr:postcode":"gu4 7jj",
    "addr:street":"Gatley Drive",
    "iso:country":"GB",
    "sg:address":"1 Gatley Drive",
    "sg:city":"Guildford",
    "sg:classifiers":[
        {
            "category":"Professional",
            "subcategory":"Lawyer & Legal Services",
            "type":"Services"
        }
    ],
    "sg:phone":"+44 1483 539431",
    "sg:postcode":"GU4 7JJ",
    "sg:province":"Surrey",
    "wof:name":"G P A Consultancy Services",
    "wof:placetype":"venue"
},
  "geometry": {"coordinates":[-0.5551260114,51.2553367615],"type":"Point"}
}