{
  "type": "Feature",
  "properties": {
    "addr:full":"26 High Street, Kippax Leeds North Yorkshire LS25 7AB",
    "addr:housenumber":"26",
    "addr:postcode":"ls25 7ab",
    "addr:street":"High Street",
    "iso:country":"GB",
    "sg:address":"26 High Street, Kippax",
    "sg:city":"Leeds",
    "sg:classifiers":[
        {
            "category":"Sports & Exercise",
            "subcategory":"Gym",
            "type":"Entertainment"
        },
        {
            "category":"Education",
            "subcategory":"Dance Studio",
            "type":"Public Place"
        }
    ],
    "sg:phone":"+44 113 286 1200",
    "sg:postcode":"LS25 7AB",
    "sg:province":"North Yorkshire",
    "sg:tags":[
        "body",
        "toning",
        "fitness",
        "health",
        "centre"
    ],
    "wof:name":"Tone 'N' Shape",
    "wof:placetype":"venue"
},
  "geometry": {"coordinates":[-1.368661046,53.7665405273],"type":"Point"}
}