{
  "type": "Feature",
  "properties": {
    "iso:country":"GB",
    "sg:address":"Crossfields Croft",
    "sg:city":"Turriff",
    "sg:classifiers":[
        {
            "category":"Freight",
            "type":"Transportation"
        }
    ],
    "sg:phone":"+44 1888 551254",
    "sg:postcode":"AB53 5PG",
    "sg:province":"Aberdeenshire",
    "sg:tags":[
        "haulage",
        "transport",
        "road"
    ],
    "wof:name":"ALFRED G CHEYNE",
    "wof:placetype":"venue"
},
  "geometry": {"coordinates":[-2.455229,57.539902],"type":"Point"}
}