{
  "type": "Feature",
  "properties": {
    "iso:country":"GB",
    "sg:address":"Islip House, Mildred Avenue",
    "sg:city":"Borehamwood",
    "sg:classifiers":[
        {
            "category":"Professional",
            "subcategory":"Engineering",
            "type":"Services"
        }
    ],
    "sg:postcode":"WD6 2DH",
    "sg:province":"Hertfordshire",
    "sg:tags":[
        "gas",
        "engineer"
    ],
    "wof:name":"R J Green (Heating)",
    "wof:placetype":"venue"
},
  "geometry": {"coordinates":[-0.272734,51.654675],"type":"Point"}
}