{
  "type": "Feature",
  "properties": {
    "addr:full":"6 Leigh Rd Eastleigh Hampshire SO50 9FH",
    "addr:housenumber":"6",
    "addr:postcode":"so50 9fh",
    "addr:street":"Leigh Rd",
    "iso:country":"GB",
    "sg:address":"6 Leigh Rd",
    "sg:city":"Eastleigh",
    "sg:classifiers":[
        {
            "category":"Real Estate",
            "subcategory":"Real Estate Agent",
            "type":"Services"
        }
    ],
    "sg:phone":"+44 23 8061 1661",
    "sg:postcode":"SO50 9FH",
    "sg:province":"Hampshire",
    "wof:name":"Mann & Co",
    "wof:placetype":"venue"
},
  "geometry": {"coordinates":[-1.351171,50.96941],"type":"Point"}
}