{
  "type": "Feature",
  "properties": {
    "iso:country":"GB",
    "sg:address":"15 Pinfold Street",
    "sg:city":"Wednesbury",
    "sg:classifiers":[
        {
            "category":"Food & Beverages",
            "subcategory":"Meat & Fish",
            "type":"Retail Goods"
        }
    ],
    "sg:phone":"+44 121 526 6784",
    "sg:postcode":"WS10 8SY",
    "sg:province":"West Midlands",
    "sg:tags":[
        "chip"
    ],
    "wof:name":"New Rainbow Fish Bar",
    "wof:placetype":"venue"
},
  "geometry": {"coordinates":[-2.036494,52.566139],"type":"Point"}
}