{
  "type": "Feature",
  "properties": {
    "addr:full":"Unit 3, Braehead Industrial Estate Renfrew Renfrewshire PA4 8XJ",
    "addr:housenumber":"unit 3",
    "addr:postcode":"pa4 8xj",
    "addr:street":"Industrial Estate",
    "iso:country":"GB",
    "sg:address":"Unit 3, Braehead Industrial Estate",
    "sg:city":"Renfrew",
    "sg:classifiers":[
        {
            "category":"Retail",
            "subcategory":"Auto Repair",
            "type":"Services"
        }
    ],
    "sg:phone":"+44 141 886 1804",
    "sg:postcode":"PA4 8XJ",
    "sg:province":"Renfrewshire",
    "sg:tags":[
        "modification",
        "garage"
    ],
    "wof:name":"John Clark Motor Engineers",
    "wof:placetype":"venue"
},
  "geometry": {"coordinates":[-4.3720898628,55.8736991882],"type":"Point"}
}