{
  "type": "Feature",
  "properties": {
    "iso:country":"GB",
    "sg:address":"47a Marchmont Street, Bloomsbury",
    "sg:city":"London",
    "sg:classifiers":[
        {
            "category":"Organizations",
            "subcategory":"Community Association",
            "type":"Services"
        }
    ],
    "sg:phone":"+44 20 7833 3759",
    "sg:postcode":"WC1N 1AP",
    "sg:province":"Greater London",
    "sg:tags":[
        "relation",
        "public"
    ],
    "wof:name":"Bloomsbury Communications Ltd.",
    "wof:placetype":"venue"
},
  "geometry": {"coordinates":[-0.125191,51.524677],"type":"Point"}
}