{
  "type": "Feature",
  "properties": {
    "iso:country":"GB",
    "sg:address":"Stanbridge Farm",
    "sg:city":"Petersfield",
    "sg:classifiers":[
        {
            "category":"Farming",
            "subcategory":"Dairy Farm",
            "type":"Manufacturing & Wholesale Goods"
        }
    ],
    "sg:phone":"+44 1730 231658",
    "sg:postcode":"GU31 5RB",
    "sg:province":"Hampshire",
    "sg:tags":[
        "farmer"
    ],
    "wof:name":"Caines Farm Partnership",
    "wof:placetype":"venue"
},
  "geometry": {"coordinates":[-0.8848720193,50.9873695374],"type":"Point"}
}