{
  "type": "Feature",
  "properties": {
    "addr:full":"12 Hamont Road Grimsby Lincolnshire DN32 8JS",
    "addr:housenumber":"12",
    "addr:postcode":"dn32 8js",
    "addr:street":"Hamont Road",
    "iso:country":"GB",
    "sg:address":"12 Hamont Road",
    "sg:city":"Grimsby",
    "sg:classifiers":[
        {
            "category":"Real Estate",
            "subcategory":"Real Estate Agent",
            "type":"Services"
        }
    ],
    "sg:postcode":"DN32 8JS",
    "sg:province":"Lincolnshire",
    "wof:name":"S B  Cabling & Maintenance Ltd.",
    "wof:placetype":"venue"
},
  "geometry": {"coordinates":[-0.054034,53.562325],"type":"Point"}
}