{
  "type": "Feature",
  "properties": {
    "iso:country":"GB",
    "sg:address":"27b Marchmont Road",
    "sg:city":"Edinburgh",
    "sg:classifiers":[
        {
            "category":"Health Services",
            "subcategory":"Optometrist",
            "type":"Services"
        },
        {
            "category":"Shopping",
            "subcategory":"Optician",
            "type":"Retail Goods"
        }
    ],
    "sg:phone":"+44 131 229 8043",
    "sg:postcode":"EH9 1HY",
    "sg:province":"City of Edinburgh",
    "sg:tags":[
        "ophthalmic"
    ],
    "wof:name":"Lyndsay Brown Opticians",
    "wof:placetype":"venue"
},
  "geometry": {"coordinates":[-3.194686,55.938484],"type":"Point"}
}