{
  "type": "Feature",
  "properties": {
    "addr:full":"Unit 1c Maple Cross Indust Estate, Denham Way Rickmansworth Hertfordshire WD3 2AS",
    "addr:housenumber":"unit 1c",
    "addr:postcode":"wd3 2as",
    "addr:street":"Maple;Indust;Denham Way",
    "iso:country":"GB",
    "sg:address":"Unit 1c Maple Cross Indust Estate, Denham Way",
    "sg:city":"Rickmansworth",
    "sg:classifiers":[
        {
            "category":"Government",
            "subcategory":"Post Office",
            "type":"Public Place"
        }
    ],
    "sg:phone":"+44 1923 712163",
    "sg:postcode":"WD3 2AS",
    "sg:province":"Hertfordshire",
    "sg:tags":[
        "messenger",
        "courier"
    ],
    "wof:name":"Delcol Couriers",
    "wof:placetype":"venue"
},
  "geometry": {"coordinates":[-0.4682750106,51.6414375305],"type":"Point"}
}