{
  "type": "Feature",
  "properties": {
    "iso:country":"GB",
    "sg:address":"2 London Wall Buildings",
    "sg:city":"Moorgate",
    "sg:classifiers":[
        {
            "category":"Professional",
            "subcategory":"Employment Agencies",
            "type":"Services"
        }
    ],
    "sg:phone":"+44 20 7448 5018",
    "sg:postcode":"EC2M 5UU",
    "sg:province":"Greater London",
    "sg:tags":[
        "consultant"
    ],
    "wof:name":"Ph.D. Recruitment",
    "wof:placetype":"venue"
},
  "geometry": {"coordinates":[-0.104356,51.498169],"type":"Point"}
}