{
  "type": "Feature",
  "properties": {
    "iso:country":"GB",
    "sg:address":"Po Box 8",
    "sg:city":"Benfleet",
    "sg:classifiers":[
        {
            "category":"Professional",
            "subcategory":"Employment Agencies",
            "type":"Services"
        }
    ],
    "sg:phone":"+44 1702 559144",
    "sg:postcode":"SS7 2LB",
    "sg:province":"Essex",
    "sg:tags":[
        "modelling"
    ],
    "wof:name":"Finesse",
    "wof:placetype":"venue"
},
  "geometry": {"coordinates":[0.614075,51.551311],"type":"Point"}
}