{
  "type": "Feature",
  "properties": {
    "addr:full":"6 Ibson Road Nelson Lancashire BB9 7LP",
    "addr:housenumber":"6",
    "addr:postcode":"bb9 7lp",
    "addr:street":"Ibson Road",
    "iso:country":"GB",
    "sg:address":"6 Ibson Road",
    "sg:city":"Nelson",
    "sg:classifiers":[
        {
            "category":"Taxi",
            "type":"Transportation"
        },
        {
            "category":"Military Area",
            "subcategory":"Air Force Base",
            "type":"Public Place"
        }
    ],
    "sg:phone":"+44 1282 616616",
    "sg:postcode":"BB9 7LP",
    "sg:province":"Lancashire",
    "sg:tags":[
        "mini",
        "hire",
        "private",
        "cab"
    ],
    "wof:name":"Ace Cars",
    "wof:placetype":"venue"
},
  "geometry": {"coordinates":[-2.2144858837,53.8354415894],"type":"Point"}
}