{
  "type": "Feature",
  "properties": {
    "addr:full":"Unit 3, Union Rd North Shields Tyne and Wear NE30 1HR",
    "addr:housenumber":"unit 3",
    "addr:postcode":"ne30 1hr",
    "addr:street":"Union Rd",
    "iso:country":"GB",
    "sg:address":"Unit 3, Union Rd",
    "sg:city":"North Shields",
    "sg:classifiers":[
        {
            "category":"Manufacturing",
            "subcategory":"Metals",
            "type":"Manufacturing & Wholesale Goods"
        }
    ],
    "sg:phone":"+44 191 257 7791",
    "sg:postcode":"NE30 1HR",
    "sg:province":"Tyne and Wear",
    "sg:tags":[
        "work",
        "sheet"
    ],
    "wof:name":"Rodman & Russell Ltd",
    "wof:placetype":"venue"
},
  "geometry": {"coordinates":[-1.43485,55.009972],"type":"Point"}
}