{
  "type": "Feature",
  "properties": {
    "addr:full":"Brookhill Hall Farm, Brookhill Lane, Pinxton Nottingham Derbyshire NG16 6JU",
    "addr:postcode":"ng16 6ju",
    "addr:street":"Brookhill Lane",
    "iso:country":"GB",
    "sg:address":"Brookhill Hall Farm, Brookhill Lane, Pinxton",
    "sg:city":"Nottingham",
    "sg:classifiers":[
        {
            "category":"Farming",
            "subcategory":"Livestock Farm",
            "type":"Manufacturing & Wholesale Goods"
        }
    ],
    "sg:phone":"+44 1773 810402",
    "sg:postcode":"NG16 6JU",
    "sg:province":"Derbyshire",
    "sg:tags":[
        "others"
    ],
    "wof:name":"G Bacon & Sons",
    "wof:placetype":"venue"
},
  "geometry": {"coordinates":[-1.317955,53.095806],"type":"Point"}
}