{
  "type": "Feature",
  "properties": {
    "addr:full":"Units 11 & 12, Northwestern Commercial Centre, Broadfield Lane London Greater London NW1 9YS",
    "addr:housenumber":"units 11 & 12",
    "addr:postcode":"nw1 9ys",
    "addr:street":"Broadfield Lane",
    "iso:country":"GB",
    "sg:address":"Units 11 & 12, Northwestern Commercial Centre, Broadfield Lane",
    "sg:city":"London",
    "sg:classifiers":[
        {
            "category":"Wholesale",
            "subcategory":"Photographic Equipment",
            "type":"Manufacturing & Wholesale Goods"
        }
    ],
    "sg:postcode":"NW1 9YS",
    "sg:province":"Greater London",
    "sg:tags":[
        "w'sale"
    ],
    "wof:name":"Direct Lighting",
    "wof:placetype":"venue"
},
  "geometry": {"coordinates":[-0.1261499971,51.5416984558],"type":"Point"}
}