{
  "type": "Feature",
  "properties": {
    "addr:full":"4 Church Road, Whitchurch Cardiff Cardiff CF14 2DZ",
    "addr:housenumber":"4",
    "addr:postcode":"cf14 2dz",
    "addr:street":"Church Road",
    "iso:country":"GB",
    "sg:address":"4 Church Road, Whitchurch",
    "sg:city":"Cardiff",
    "sg:classifiers":[
        {
            "category":"Health Services",
            "subcategory":"Doctor",
            "type":"Services"
        }
    ],
    "sg:phone":"+44 29 2052 2355",
    "sg:postcode":"CF14 2DZ",
    "sg:province":"Cardiff",
    "sg:tags":[
        "practitioners"
    ],
    "wof:name":"Birshfields Surgery",
    "wof:placetype":"venue"
},
  "geometry": {"coordinates":[-3.221708,51.512573],"type":"Point"}
}