{
  "type": "Feature",
  "properties": {
    "iso:country":"GB",
    "sg:address":"Unit 12 Acacia Close",
    "sg:city":"Leighton Buzzard",
    "sg:classifiers":[
        {
            "category":"Shopping",
            "subcategory":"Computers & Home Electronics",
            "type":"Retail Goods"
        }
    ],
    "sg:phone":"+44 1525 371544",
    "sg:postcode":"LU7 8QE",
    "sg:province":"Bedfordshire",
    "sg:tags":[
        "sound",
        "equipment",
        "system"
    ],
    "wof:name":"Prisms Sound & Lighting",
    "wof:placetype":"venue"
},
  "geometry": {"coordinates":[-0.6344310045,51.9148254395],"type":"Point"}
}