{
  "type": "Feature",
  "properties": {
    "iso:country":"GB",
    "sg:address":"Beetwell Street",
    "sg:city":"Chesterfield",
    "sg:classifiers":[
        {
            "category":"Organizations",
            "subcategory":"Professional Association",
            "type":"Services"
        }
    ],
    "sg:phone":"+44 1246 211658",
    "sg:postcode":"S40 1QJ",
    "sg:province":"Derbyshire",
    "sg:tags":[
        "union",
        "trade"
    ],
    "wof:name":"Derbyshire County Unison",
    "wof:placetype":"venue"
},
  "geometry": {"coordinates":[-1.4263130426,53.2341995239],"type":"Point"}
}