{
  "type": "Feature",
  "properties": {
    "iso:country":"GB",
    "sg:address":"24 Abbey Walk, Scawsby",
    "sg:city":"Doncaster",
    "sg:classifiers":[
        {
            "category":"Professional",
            "type":"Services"
        }
    ],
    "sg:phone":"+44 1302 782064",
    "sg:postcode":"DN5 8NP",
    "sg:province":"South Yorkshire",
    "sg:tags":[
        "auctioneer"
    ],
    "wof:name":"T & R Murray",
    "wof:placetype":"venue"
},
  "geometry": {"coordinates":[-1.170678,53.534061],"type":"Point"}
}