{
  "type": "Feature",
  "properties": {
    "addr:full":"296 Beacon Road Loughborough Leicestershire LE11 2RD",
    "addr:housenumber":"296",
    "addr:postcode":"le11 2rd",
    "addr:street":"Beacon Road",
    "iso:country":"GB",
    "sg:address":"296 Beacon Road",
    "sg:city":"Loughborough",
    "sg:classifiers":[
        {
            "category":"Building & Trades",
            "subcategory":"Construction",
            "type":"Services"
        }
    ],
    "sg:phone":"+44 1509 215291",
    "sg:postcode":"LE11 2RD",
    "sg:province":"Leicestershire",
    "sg:tags":[
        "builder"
    ],
    "wof:name":"P Millward Builders",
    "wof:placetype":"venue"
},
  "geometry": {"coordinates":[-1.219289,52.755699],"type":"Point"}
}