{
  "type": "Feature",
  "properties": {
    "iso:country":"GB",
    "sg:address":"35 Dickens Drive, Old Stratford",
    "sg:city":"Milton Keynes",
    "sg:classifiers":[
        {
            "category":"Home & Garden",
            "subcategory":"Household Appliances",
            "type":"Retail Goods"
        }
    ],
    "sg:phone":"+44 1908 564979",
    "sg:postcode":"MK19 6NW",
    "sg:province":"Buckinghamshire",
    "sg:tags":[
        "repairs",
        "electrical",
        "domestic",
        "servicing"
    ],
    "wof:name":"Aston Domestic Service",
    "wof:placetype":"venue"
},
  "geometry": {"coordinates":[-0.8693410158,52.060344696],"type":"Point"}
}