{
  "type": "Feature",
  "properties": {
    "addr:full":"Grange Farm, Pilcox Hall Lane, Tendring Clacton-on-sea Essex CO16 0DJ",
    "addr:postcode":"co16 0dj",
    "addr:street":"Pilcox Hall Lane",
    "iso:country":"GB",
    "sg:address":"Grange Farm, Pilcox Hall Lane, Tendring",
    "sg:city":"Clacton-on-sea",
    "sg:classifiers":[
        {
            "category":"Farming",
            "subcategory":"Livestock Farm",
            "type":"Manufacturing & Wholesale Goods"
        },
        {
            "category":"Retail",
            "subcategory":"Animal Services",
            "type":"Services"
        }
    ],
    "sg:phone":"+44 1255 831090",
    "sg:postcode":"CO16 0DJ",
    "sg:province":"Essex",
    "sg:tags":[
        "breeder",
        "others"
    ],
    "wof:name":"Alan W Black",
    "wof:placetype":"venue"
},
  "geometry": {"coordinates":[1.1169749498,51.8748397827],"type":"Point"}
}