{
  "type": "Feature",
  "properties": {
    "iso:country":"GB",
    "sg:address":"186 West St",
    "sg:city":"Fareham",
    "sg:classifiers":[
        {
            "category":"Insurance",
            "subcategory":"Insurance Agent",
            "type":"Services"
        }
    ],
    "sg:phone":"+44 1329 235841",
    "sg:postcode":"PO16 0HP",
    "sg:province":"Hampshire",
    "sg:tags":[
        "broker"
    ],
    "wof:name":"Curran,P,Ltd",
    "wof:placetype":"venue"
},
  "geometry": {"coordinates":[-1.185625,50.852421],"type":"Point"}
}