{
  "type": "Feature",
  "properties": {
    "iso:country":"GB",
    "sg:address":"The Vicarage, 55 Princess St",
    "sg:city":"Wrexham",
    "sg:classifiers":[
        {
            "category":"Place Of Worship",
            "type":"Public Place"
        }
    ],
    "sg:phone":"+44 1978 266145",
    "sg:postcode":"LL13 7US",
    "sg:province":"Wrexham",
    "wof:name":"All Saints Church In Wales",
    "wof:placetype":"venue"
},
  "geometry": {"coordinates":[-2.997129,53.041954],"type":"Point"}
}