{
  "type": "Feature",
  "properties": {
    "addr:full":"Greenford Road Greenford Greater London UB6 9AY",
    "addr:postcode":"ub6 9ay",
    "addr:street":"Greenford Road",
    "iso:country":"GB",
    "sg:address":"Greenford Road",
    "sg:city":"Greenford",
    "sg:classifiers":[
        {
            "category":"Bars & Pubs",
            "type":"Food & Drink"
        }
    ],
    "sg:postcode":"UB6 9AY",
    "sg:province":"Greater London",
    "sg:tags":[
        "pubs",
        "inn"
    ],
    "wof:name":"Courage Ltd.",
    "wof:placetype":"venue"
},
  "geometry": {"coordinates":[-0.352512,51.526943],"type":"Point"}
}