{
  "type": "Feature",
  "properties": {
    "addr:full":"30 Canham Close, Kimpton Hitchin Hertfordshire SG4 8SD",
    "addr:housenumber":"30",
    "addr:postcode":"kimpton;sg4 8sd",
    "addr:street":"Canham Close",
    "iso:country":"GB",
    "sg:address":"30 Canham Close, Kimpton",
    "sg:city":"Hitchin",
    "sg:classifiers":[
        {
            "category":"Manufacturing",
            "subcategory":"Building Materials",
            "type":"Manufacturing & Wholesale Goods"
        }
    ],
    "sg:phone":"+44 1438 833095",
    "sg:postcode":"SG4 8SD",
    "sg:province":"Hertfordshire",
    "sg:tags":[
        "tarmac",
        "asphalt"
    ],
    "wof:name":"Home Counties Surfacing",
    "wof:placetype":"venue"
},
  "geometry": {"coordinates":[-0.2943120003,51.8516120911],"type":"Point"}
}