{
  "type": "Feature",
  "properties": {
    "iso:country":"GB",
    "sg:address":"31 Chorley New Road",
    "sg:city":"Bolton",
    "sg:classifiers":[
        {
            "category":"Real Estate",
            "subcategory":"Architect",
            "type":"Services"
        }
    ],
    "sg:phone":"+44 1204 364666",
    "sg:postcode":"BL1 4QR",
    "sg:province":"Lancashire",
    "wof:name":"McH Investments Ltd.",
    "wof:placetype":"venue"
},
  "geometry": {"coordinates":[-2.441724,53.582012],"type":"Point"}
}