{
  "type": "Feature",
  "properties": {
    "addr:full":"7 Laurel Clo Bridport Dorset DT6 5RQ",
    "addr:housenumber":"7",
    "addr:postcode":"dt6 5rq",
    "addr:street":"Laurel Clo",
    "iso:country":"GB",
    "sg:address":"7 Laurel Clo",
    "sg:city":"Bridport",
    "sg:classifiers":[
        {
            "category":"Farming",
            "subcategory":"Fish & Marine Products",
            "type":"Manufacturing & Wholesale Goods"
        }
    ],
    "sg:phone":"+44 1308 425048",
    "sg:postcode":"DT6 5RQ",
    "sg:province":"Dorset",
    "sg:tags":[
        "fishmonger"
    ],
    "wof:name":"R M Brown",
    "wof:placetype":"venue"
},
  "geometry": {"coordinates":[-2.769,50.741257],"type":"Point"}
}