{
  "type": "Feature",
  "properties": {
    "addr:full":"52 Crewe Rd, Alsager Stoke-on-trent Cheshire ST7 2ET",
    "addr:housenumber":"52",
    "addr:postcode":"st7 2et",
    "addr:street":"Crewe Rd",
    "iso:country":"GB",
    "sg:address":"52 Crewe Rd, Alsager",
    "sg:city":"Stoke-on-trent",
    "sg:classifiers":[
        {
            "category":"Professional",
            "subcategory":"Business Services",
            "type":"Services"
        }
    ],
    "sg:postcode":"ST7 2ET",
    "sg:province":"Cheshire",
    "sg:tags":[
        "import",
        "export",
        "agent"
    ],
    "wof:name":"Congleton District for Voluntary Service",
    "wof:placetype":"venue"
},
  "geometry": {"coordinates":[-2.309219,53.095608],"type":"Point"}
}