{
  "type": "Feature",
  "properties": {
    "addr:full":"18 Croydon Ho, Croydon St Leeds West Yorkshire LS11 9RT",
    "addr:housenumber":"18",
    "addr:postcode":"ls11 9rt",
    "addr:street":"Croydon Ho Croydon St",
    "iso:country":"GB",
    "sg:address":"18 Croydon Ho, Croydon St",
    "sg:city":"Leeds",
    "sg:classifiers":[
        {
            "category":"Banks & Credit Unions",
            "subcategory":"Investment Brokerage",
            "type":"Services"
        }
    ],
    "sg:phone":"+44 113 243 8067",
    "sg:postcode":"LS11 9RT",
    "sg:province":"West Yorkshire",
    "sg:tags":[
        "agent"
    ],
    "wof:name":"Gillyn Sales Ltd",
    "wof:placetype":"venue"
},
  "geometry": {"coordinates":[-1.5653820038,53.7882194519],"type":"Point"}
}