{
  "type": "Feature",
  "properties": {
    "addr:full":"First Floor, 112-114 Brent Street London Greater London NW4 2DT",
    "addr:housenumber":"112-114",
    "addr:postcode":"nw4 2dt",
    "addr:street":"Brent Street",
    "iso:country":"GB",
    "sg:address":"First Floor, 112-114 Brent Street",
    "sg:city":"London",
    "sg:classifiers":[
        {
            "category":"Banks & Credit Unions",
            "subcategory":"Financial Services",
            "type":"Services"
        }
    ],
    "sg:phone":"+44 20 8202 5667",
    "sg:postcode":"NW4 2DT",
    "sg:province":"Greater London",
    "sg:tags":[
        "adviser"
    ],
    "wof:name":"Anthony Sigler (Life & Pensions) Ltd.",
    "wof:placetype":"venue"
},
  "geometry": {"coordinates":[-0.219939,51.585949],"type":"Point"}
}