{
  "type": "Feature",
  "properties": {
    "iso:country":"GB",
    "sg:address":"Maunby Demesne, Maunby",
    "sg:city":"Thirsk",
    "sg:classifiers":[
        {
            "category":"Home & Garden",
            "subcategory":"Garden Supply",
            "type":"Retail Goods"
        }
    ],
    "sg:phone":"+44 1609 779797",
    "sg:postcode":"YO7 4HQ",
    "sg:province":"North Yorkshire",
    "sg:tags":[
        "bulb",
        "grower"
    ],
    "wof:name":"J & J Burgess",
    "wof:placetype":"venue"
},
  "geometry": {"coordinates":[-1.4580340385,54.2743034363],"type":"Point"}
}