{
  "type": "Feature",
  "properties": {
    "iso:country":"GB",
    "sg:address":"2 Lower Grn, Dane End",
    "sg:city":"Ware",
    "sg:classifiers":[
        {
            "category":"Banks & Credit Unions",
            "subcategory":"Investment Brokerage",
            "type":"Services"
        }
    ],
    "sg:phone":"+44 1920 830652",
    "sg:postcode":"SG12 0PJ",
    "sg:province":"Hertfordshire",
    "sg:tags":[
        "contractor"
    ],
    "wof:name":"Stanley Dodson K",
    "wof:placetype":"venue"
},
  "geometry": {"coordinates":[-0.035127,51.816338],"type":"Point"}
}