{
  "type": "Feature",
  "properties": {
    "addr:full":"11 Church Hill Epping Essex CM16 4RA",
    "addr:housenumber":"11",
    "addr:postcode":"cm16 4ra",
    "addr:street":"Church Hill",
    "iso:country":"GB",
    "sg:address":"11 Church Hill",
    "sg:city":"Epping",
    "sg:classifiers":[
        {
            "category":"Place Of Worship",
            "type":"Public Place"
        }
    ],
    "sg:phone":"+44 1992 572516",
    "sg:postcode":"CM16 4RA",
    "sg:province":"Essex",
    "wof:name":"Church Of The Immaculate Conception R C Church",
    "wof:placetype":"venue"
},
  "geometry": {"coordinates":[0.115445,51.702518],"type":"Point"}
}