{
  "type": "Feature",
  "properties": {
    "addr:full":"Vicarage Road Ambleside Cumbria LA22 9DH",
    "addr:postcode":"la22 9dh",
    "addr:street":"Vicarage Road",
    "iso:country":"GB",
    "sg:address":"Vicarage Road",
    "sg:city":"Ambleside",
    "sg:classifiers":[
        {
            "category":"Travel",
            "subcategory":"Hotels & Motels",
            "type":"Entertainment"
        }
    ],
    "sg:phone":"+44 15394 33364",
    "sg:postcode":"LA22 9DH",
    "sg:province":"Cumbria",
    "sg:tags":[
        "house",
        "guest"
    ],
    "wof:name":"Old Vicarage",
    "wof:placetype":"venue"
},
  "geometry": {"coordinates":[-2.9654769897,54.4311752319],"type":"Point"}
}