{
  "type": "Feature",
  "properties": {
    "addr:full":"9 High Street Whitstable Kent CT5 1AP",
    "addr:housenumber":"9",
    "addr:postcode":"ct5 1ap",
    "addr:street":"High Street",
    "iso:country":"GB",
    "sg:address":"9 High Street",
    "sg:city":"Whitstable",
    "sg:classifiers":[
        {
            "category":"Shopping",
            "subcategory":"Clothing, Apparel, & Fashions",
            "type":"Retail Goods"
        }
    ],
    "sg:phone":"+44 1227 272681",
    "sg:postcode":"CT5 1AP",
    "sg:province":"Kent",
    "sg:tags":[
        "menswear"
    ],
    "wof:name":"Hatchards Outfitters",
    "wof:placetype":"venue"
},
  "geometry": {"coordinates":[1.024425,51.359947],"type":"Point"}
}