{
  "type": "Feature",
  "properties": {
    "addr:full":"395-397 Sheffield Road Chesterfield Derbyshire S41 8LS",
    "addr:housenumber":"395-397",
    "addr:postcode":"s41 8ls",
    "addr:street":"Sheffield Road",
    "iso:country":"GB",
    "sg:address":"395-397 Sheffield Road",
    "sg:city":"Chesterfield",
    "sg:classifiers":[
        {
            "category":"Cafe",
            "type":"Food & Drink"
        }
    ],
    "sg:phone":"+44 1246 451651",
    "sg:postcode":"S41 8LS",
    "sg:province":"Derbyshire",
    "sg:tags":[
        "tea",
        "room"
    ],
    "wof:name":"Phyll's Grill",
    "wof:placetype":"venue"
},
  "geometry": {"coordinates":[-1.427791,53.257732],"type":"Point"}
}