{
  "type": "Feature",
  "properties": {
    "addr:full":"221-223 Elliott Street, Tyldesley Manchester Greater Manchester M29 8DG",
    "addr:housenumber":"221-223",
    "addr:postcode":"m29 8dg",
    "addr:street":"Elliott Street",
    "iso:country":"GB",
    "sg:address":"221-223 Elliott Street, Tyldesley",
    "sg:city":"Manchester",
    "sg:classifiers":[
        {
            "category":"Retail",
            "subcategory":"Repair Shop",
            "type":"Services"
        }
    ],
    "sg:phone":"+44 1942 878213",
    "sg:postcode":"M29 8DG",
    "sg:province":"Greater Manchester",
    "sg:tags":[
        "upholsterer"
    ],
    "wof:name":"M A & C Taylor",
    "wof:placetype":"venue"
},
  "geometry": {"coordinates":[-2.464572,53.514217],"type":"Point"}
}