{
  "type": "Feature",
  "properties": {
    "addr:full":"23 Poole Road Bournemouth Dorset BH4 9DF",
    "addr:housenumber":"23",
    "addr:postcode":"bh4 9df",
    "addr:street":"Poole Road",
    "iso:country":"GB",
    "sg:address":"23 Poole Road",
    "sg:city":"Bournemouth",
    "sg:classifiers":[
        {
            "category":"Health Services",
            "subcategory":"Dentist",
            "type":"Services"
        }
    ],
    "sg:phone":"+44 1202 769216",
    "sg:postcode":"BH4 9DF",
    "sg:province":"Dorset",
    "wof:name":"M A Bloor",
    "wof:placetype":"venue"
},
  "geometry": {"coordinates":[-1.895494,50.72126],"type":"Point"}
}