{
  "type": "Feature",
  "properties": {
    "iso:country":"GB",
    "sg:address":"Hardys Yard, 2 Vale Rd",
    "sg:city":"Gravesend",
    "sg:classifiers":[
        {
            "category":"Autos & Motor Vehicles",
            "subcategory":"Automobile Sales",
            "type":"Retail Goods"
        }
    ],
    "sg:phone":"+44 1474 567824",
    "sg:postcode":"DA11 8BW",
    "sg:province":"Kent",
    "sg:tags":[
        "commercial"
    ],
    "wof:name":"Kent Number One Truck Centre",
    "wof:placetype":"venue"
},
  "geometry": {"coordinates":[0.364606,51.432827],"type":"Point"}
}