{
  "type": "Feature",
  "properties": {
    "iso:country":"GB",
    "sg:address":"322 Bridgwater Drive",
    "sg:city":"Westcliff-on-sea",
    "sg:classifiers":[
        {
            "category":"Personal",
            "subcategory":"Beauty Salon",
            "type":"Services"
        }
    ],
    "sg:phone":"+44 1702 524773",
    "sg:postcode":"SS0 0EZ",
    "sg:province":"Essex",
    "sg:tags":[
        "unisex",
        "hairdresser"
    ],
    "wof:name":"Brenda Hair Fashion",
    "wof:placetype":"venue"
},
  "geometry": {"coordinates":[0.665912,51.562317],"type":"Point"}
}