{
  "type": "Feature",
  "properties": {
    "addr:full":"Ross-on-wye Community Hospital, Alton Street Ross-on-wye Gloucestershire HR9 5AD",
    "addr:postcode":"hr9 5ad",
    "addr:street":"Alton Street",
    "iso:country":"GB",
    "sg:address":"Ross-on-wye Community Hospital, Alton Street",
    "sg:city":"Ross-on-wye",
    "sg:classifiers":[
        {
            "category":"Health Services",
            "subcategory":"Optometrist",
            "type":"Services"
        },
        {
            "category":"Shopping",
            "subcategory":"Optician",
            "type":"Retail Goods"
        }
    ],
    "sg:phone":"+44 1989 567244",
    "sg:postcode":"HR9 5AD",
    "sg:province":"Gloucestershire",
    "sg:tags":[
        "ophthalmic"
    ],
    "wof:name":"Scotts Opticians Ltd",
    "wof:placetype":"venue"
},
  "geometry": {"coordinates":[-2.5817329884,51.9164810181],"type":"Point"}
}