{
  "type": "Feature",
  "properties": {
    "addr:full":"Bessemer Ho, 59 Carlisle Street East Sheffield South Yorkshire S4 7QN",
    "addr:housenumber":"59",
    "addr:postcode":"s4 7qn",
    "addr:street":"Carlisle Street East",
    "iso:country":"GB",
    "sg:address":"Bessemer Ho, 59 Carlisle Street East",
    "sg:city":"Sheffield",
    "sg:classifiers":[
        {
            "category":"Organizations",
            "subcategory":"Non-profit Organization",
            "type":"Services"
        }
    ],
    "sg:phone":"+44 114 275 1212",
    "sg:postcode":"S4 7QN",
    "sg:province":"South Yorkshire",
    "sg:tags":[
        "organisation",
        "voluntary",
        "charity"
    ],
    "wof:name":"Agewell In Sheffield",
    "wof:placetype":"venue"
},
  "geometry": {"coordinates":[-1.44932,53.395309],"type":"Point"}
}