{
  "type": "Feature",
  "properties": {
    "addr:full":"6 Stewton Lane Louth Lincolnshire LN11 8RZ",
    "addr:housenumber":"6",
    "addr:postcode":"ln11 8rz",
    "addr:street":"Stewton Lane Louth",
    "iso:country":"GB",
    "sg:address":"6 Stewton Lane",
    "sg:city":"Louth",
    "sg:classifiers":[
        {
            "category":"Manufacturing",
            "subcategory":"Wood Products",
            "type":"Manufacturing & Wholesale Goods"
        }
    ],
    "sg:phone":"+44 1507 617800",
    "sg:postcode":"LN11 8RZ",
    "sg:province":"Lincolnshire",
    "sg:tags":[
        "packaging",
        "crate",
        "pallets"
    ],
    "wof:name":"Britton Security Products",
    "wof:placetype":"venue"
},
  "geometry": {"coordinates":[0.007216,53.360958],"type":"Point"}
}