{
  "type": "Feature",
  "properties": {
    "addr:full":"Doctors Surgery, 2 Scarsdale Villas London Greater London W8 6PR",
    "addr:housenumber":"2",
    "addr:postcode":"w8 6pr",
    "addr:street":"Scarsdale Villas",
    "iso:country":"GB",
    "sg:address":"Doctors Surgery, 2 Scarsdale Villas",
    "sg:city":"London",
    "sg:classifiers":[
        {
            "category":"Health Services",
            "subcategory":"Doctor",
            "type":"Services"
        }
    ],
    "sg:phone":"+44 20 7937 3343",
    "sg:postcode":"W8 6PR",
    "sg:province":"Greater London",
    "sg:tags":[
        "practitioners"
    ],
    "wof:name":"M H Malhas",
    "wof:placetype":"venue"
},
  "geometry": {"coordinates":[-0.1927700043,51.4978103638],"type":"Point"}
}