{
  "type": "Feature",
  "properties": {
    "iso:country":"GB",
    "sg:address":"63 Victoria Road",
    "sg:city":"Aldershot",
    "sg:classifiers":[
        {
            "category":"Organizations",
            "subcategory":"Non-profit Organization",
            "type":"Services"
        }
    ],
    "sg:phone":"+44 1252 312364",
    "sg:postcode":"GU11 1SJ",
    "sg:province":"Hampshire",
    "sg:tags":[
        "organisation",
        "voluntary",
        "charity"
    ],
    "wof:name":"Emmaus Projects Ltd.",
    "wof:placetype":"venue"
},
  "geometry": {"coordinates":[-0.759773,51.248016],"type":"Point"}
}