{
  "type": "Feature",
  "properties": {
    "iso:country":"GB",
    "sg:address":"Cardiff Business Technology Centre, Unit 101",
    "sg:city":"Cardiff",
    "sg:classifiers":[
        {
            "category":"Professional",
            "subcategory":"Research",
            "type":"Services"
        }
    ],
    "sg:phone":"+44 29 2038 8058",
    "sg:postcode":"CF24 4AG",
    "sg:province":"Cardiff",
    "sg:tags":[
        "organisation"
    ],
    "wof:name":"Magnetic Suspensions (Research & Development) Ltd.",
    "wof:placetype":"venue"
},
  "geometry": {"coordinates":[-3.17438,51.48682],"type":"Point"}
}