{
  "type": "Feature",
  "properties": {
    "iso:country":"GB",
    "sg:address":"Unit -6, Park Farm",
    "sg:city":"Saffron Walden",
    "sg:classifiers":[
        {
            "category":"Manufacturing",
            "subcategory":"Glass & Minerals",
            "type":"Manufacturing & Wholesale Goods"
        },
        {
            "category":"Building & Trades",
            "subcategory":"Construction",
            "type":"Services"
        }
    ],
    "sg:phone":"+44 1799 530655",
    "sg:postcode":"CB10 1RN",
    "sg:province":"Cambridgeshire",
    "sg:tags":[
        "glazier",
        "glassworker"
    ],
    "wof:name":"Fine Glass Finishers Ltd.",
    "wof:placetype":"venue"
},
  "geometry": {"coordinates":[0.2383950055,52.0230293274],"type":"Point"}
}