{
  "type": "Feature",
  "properties": {
    "addr:full":"Albion Road, New Mills High Peak Cheshire SK22 3EX",
    "addr:postcode":"sk22 3ex",
    "addr:street":"Albion Road",
    "iso:country":"GB",
    "sg:address":"Albion Road, New Mills",
    "sg:city":"High Peak",
    "sg:classifiers":[
        {
            "category":"Retail",
            "subcategory":"Auto Repair",
            "type":"Services"
        }
    ],
    "sg:phone":"+44 1663 741414",
    "sg:postcode":"SK22 3EX",
    "sg:province":"Cheshire",
    "sg:tags":[
        "body",
        "car"
    ],
    "wof:name":"High Peak Accident Management & Repair Centre",
    "wof:placetype":"venue"
},
  "geometry": {"coordinates":[-2.0021839142,53.3655662537],"type":"Point"}
}