{
  "type": "Feature",
  "properties": {
    "iso:country":"GB",
    "sg:address":"Argyll Road",
    "sg:city":"Perth",
    "sg:classifiers":[
        {
            "category":"Bars & Pubs",
            "type":"Food & Drink"
        }
    ],
    "sg:phone":"+44 1738 449500",
    "sg:postcode":"PH1 3BZ",
    "sg:province":"Perth and Kinross",
    "sg:tags":[
        "pubs",
        "inn"
    ],
    "wof:name":"Mallard Bar",
    "wof:placetype":"venue"
},
  "geometry": {"coordinates":[-3.4553089142,56.4143753052],"type":"Point"}
}