{
  "type": "Feature",
  "properties": {
    "iso:country":"GB",
    "sg:address":"The Corner House, Church Hill, Wickham",
    "sg:city":"Newbury",
    "sg:classifiers":[
        {
            "category":"Professional",
            "subcategory":"Art Services",
            "type":"Services"
        }
    ],
    "sg:phone":"+44 1488 608344",
    "sg:postcode":"RG20 8HD",
    "sg:province":"Berkshire",
    "sg:tags":[
        "graphic",
        "designer"
    ],
    "wof:name":"Brian Vincent Roll",
    "wof:placetype":"venue"
},
  "geometry": {"coordinates":[-1.435945,51.437675],"type":"Point"}
}