{
  "type": "Feature",
  "properties": {
    "iso:country":"GB",
    "sg:address":"Kingbeare, North Hill",
    "sg:city":"Launceston",
    "sg:classifiers":[
        {
            "category":"Farming",
            "subcategory":"Livestock Farm",
            "type":"Manufacturing & Wholesale Goods"
        },
        {
            "category":"Farming",
            "subcategory":"Farm",
            "type":"Manufacturing & Wholesale Goods"
        }
    ],
    "sg:postcode":"PL15 7NT",
    "sg:province":"Cornwall",
    "sg:tags":[
        "mixed",
        "crop",
        "others"
    ],
    "wof:name":"R B M & L M Budge",
    "wof:placetype":"venue"
},
  "geometry": {"coordinates":[-4.441444,50.563454],"type":"Point"}
}