{
  "type": "Feature",
  "properties": {
    "iso:country":"GB",
    "sg:address":"20 Gleneagle Mews, Streatham",
    "sg:city":"London",
    "sg:classifiers":[
        {
            "category":"Retail",
            "subcategory":"Auto Repair",
            "type":"Services"
        }
    ],
    "sg:phone":"+44 20 8769 8916",
    "sg:postcode":"SW16 6AE",
    "sg:province":"Greater London",
    "sg:tags":[
        "modification",
        "garage"
    ],
    "wof:name":"Gleneagle Motors",
    "wof:placetype":"venue"
},
  "geometry": {"coordinates":[-0.132109,51.426899],"type":"Point"}
}