{
  "type": "Feature",
  "properties": {
    "addr:full":"Unit 2 Busk Ro Oldham Lancashire OL9 6QZ",
    "addr:housenumber":"unit 2",
    "addr:postcode":"ol9 6qz",
    "iso:country":"GB",
    "sg:address":"Unit 2 Busk Ro",
    "sg:city":"Oldham",
    "sg:classifiers":[
        {
            "category":"Retail",
            "subcategory":"Auto Repair",
            "type":"Services"
        }
    ],
    "sg:postcode":"OL9 6QZ",
    "sg:province":"Lancashire",
    "sg:tags":[
        "body",
        "car"
    ],
    "wof:name":"Anderson,Jeff,",
    "wof:placetype":"venue"
},
  "geometry": {"coordinates":[-2.1316840649,53.5479507446],"type":"Point"}
}