{
  "type": "Feature",
  "properties": {
    "addr:full":"269 Holmlea Rd, Cathcart Glasgow East Renfrewshire G44 4BU",
    "addr:housenumber":"269",
    "addr:postcode":"g44 4bu",
    "addr:street":"Holmlea Rd",
    "iso:country":"GB",
    "sg:address":"269 Holmlea Rd, Cathcart",
    "sg:city":"Glasgow",
    "sg:classifiers":[
        {
            "category":"Health Services",
            "subcategory":"Nursing And Care Facility",
            "type":"Services"
        }
    ],
    "sg:phone":"+44 141 637 5835",
    "sg:postcode":"G44 4BU",
    "sg:province":"East Renfrewshire",
    "sg:tags":[
        "home"
    ],
    "wof:name":"The Caring Force",
    "wof:placetype":"venue"
},
  "geometry": {"coordinates":[-4.2604718208,55.8197669983],"type":"Point"}
}