{
  "type": "Feature",
  "properties": {
    "iso:country":"GB",
    "sg:address":"Woodview, Vicaridge Road, Waresley",
    "sg:city":"Sandy",
    "sg:classifiers":[
        {
            "category":"Freight",
            "type":"Transportation"
        }
    ],
    "sg:phone":"+44 1767 650115",
    "sg:postcode":"SG19 3DA",
    "sg:province":"Bedfordshire",
    "sg:tags":[
        "haulage",
        "road"
    ],
    "wof:name":"R N Griffin",
    "wof:placetype":"venue"
},
  "geometry": {"coordinates":[-0.17394,52.175282],"type":"Point"}
}