{
  "type": "Feature",
  "properties": {
    "addr:full":"The Old Garage, Middleton Lane, Middleton Tamworth Staffordshire B78 2BN",
    "addr:postcode":"b78 2bn",
    "addr:street":"Middleton Lane",
    "iso:country":"GB",
    "sg:address":"The Old Garage, Middleton Lane, Middleton",
    "sg:city":"Tamworth",
    "sg:classifiers":[
        {
            "category":"Sports & Exercise",
            "subcategory":"Tennis Court",
            "type":"Entertainment"
        }
    ],
    "sg:phone":"+44 121 329 3555",
    "sg:postcode":"B78 2BN",
    "sg:province":"Staffordshire",
    "sg:tags":[
        "breakdown",
        "recovery"
    ],
    "wof:name":"S P W  Auto Services Ltd.",
    "wof:placetype":"venue"
},
  "geometry": {"coordinates":[-1.7393989563,52.5823936462],"type":"Point"}
}