{
  "type": "Feature",
  "properties": {
    "iso:country":"GB",
    "sg:address":"10 Vine St",
    "sg:city":"Grantham",
    "sg:classifiers":[
        {
            "category":"Shopping",
            "subcategory":"Florist",
            "type":"Retail Goods"
        }
    ],
    "sg:phone":"+44 1476 564680",
    "sg:postcode":"NG31 6RQ",
    "sg:province":"Lincolnshire",
    "wof:name":"Willoughbys Florists",
    "wof:placetype":"venue"
},
  "geometry": {"coordinates":[-0.642145,52.91396],"type":"Point"}
}