{
  "type": "Feature",
  "properties": {
    "addr:full":"26 Park Road Lytham St Annes Lancashire FY8 1PA",
    "addr:housenumber":"26",
    "addr:postcode":"fy8 1pa",
    "addr:street":"Park Road",
    "iso:country":"GB",
    "sg:address":"26 Park Road",
    "sg:city":"Lytham St Annes",
    "sg:classifiers":[
        {
            "category":"Real Estate",
            "subcategory":"Real Estate Agent",
            "type":"Services"
        }
    ],
    "sg:postcode":"FY8 1PA",
    "sg:province":"Lancashire",
    "wof:name":"Bardsley",
    "wof:placetype":"venue"
},
  "geometry": {"coordinates":[-3.028795,53.750931],"type":"Point"}
}