{
  "type": "Feature",
  "properties": {
    "addr:full":"Whitefield Mill, Victoria Street Nelson Lancashire BB9 7HL",
    "addr:postcode":"bb9 7hl",
    "addr:street":"Whitefield;Victoria Street",
    "iso:country":"GB",
    "sg:address":"Whitefield Mill, Victoria Street",
    "sg:city":"Nelson",
    "sg:classifiers":[
        {
            "category":"Shopping",
            "subcategory":"Discount & Variety Stores",
            "type":"Retail Goods"
        }
    ],
    "sg:phone":"+44 1282 63997",
    "sg:postcode":"BB9 7HL",
    "sg:province":"Lancashire",
    "sg:tags":[
        "cleaning",
        "supply"
    ],
    "wof:name":"Ashworth Bros",
    "wof:placetype":"venue"
},
  "geometry": {"coordinates":[-2.21334,53.835968],"type":"Point"}
}