{
  "type": "Feature",
  "properties": {
    "addr:full":"Langmuir Way, Baillieston Glasgow East Dunbartonshire G69 7RW",
    "addr:postcode":"g69 7rw",
    "addr:street":"Langmuir Way",
    "iso:country":"GB",
    "sg:address":"Langmuir Way, Baillieston",
    "sg:city":"Glasgow",
    "sg:classifiers":[
        {
            "category":"Utilities",
            "subcategory":"Refuse",
            "type":"Services"
        }
    ],
    "sg:phone":"+44 141 771 3871",
    "sg:postcode":"G69 7RW",
    "sg:province":"East Dunbartonshire",
    "sg:tags":[
        "disposal",
        "waste"
    ],
    "wof:name":"Viridor Enviroscot Ltd.",
    "wof:placetype":"venue"
},
  "geometry": {"coordinates":[-4.0711131096,55.8524093628],"type":"Point"}
}