{
  "type": "Feature",
  "properties": {
    "addr:full":"Radway Road Swindon Wiltshire SN3 4ND",
    "addr:postcode":"sn3 4nd",
    "addr:street":"Radway Road",
    "iso:country":"GB",
    "sg:address":"Radway Road",
    "sg:city":"Swindon",
    "sg:classifiers":[
        {
            "category":"Retail",
            "subcategory":"Auto Rental",
            "type":"Services"
        },
        {
            "category":"Professional",
            "subcategory":"Employment Agencies",
            "type":"Services"
        }
    ],
    "sg:phone":"+44 1793 831515",
    "sg:postcode":"SN3 4ND",
    "sg:province":"Wiltshire",
    "sg:tags":[
        "recr",
        "driver",
        "hire",
        "van",
        "truck"
    ],
    "wof:name":"Revelan Group",
    "wof:placetype":"venue"
},
  "geometry": {"coordinates":[-1.7576309443,51.5823822021],"type":"Point"}
}