{
  "type": "Feature",
  "properties": {
    "iso:country":"GB",
    "sg:address":"47 Ringstead Rd",
    "sg:city":"Sutton",
    "sg:classifiers":[
        {
            "category":"Professional",
            "subcategory":"Engineering",
            "type":"Services"
        }
    ],
    "sg:phone":"+44 20 8643 8351",
    "sg:postcode":"SM1 4SJ",
    "sg:province":"Surrey",
    "sg:tags":[
        "contractor",
        "electrical",
        "engineer"
    ],
    "wof:name":"Renewdale",
    "wof:placetype":"venue"
},
  "geometry": {"coordinates":[-0.177923,51.365906],"type":"Point"}
}