{
  "type": "Feature",
  "properties": {
    "iso:country":"GB",
    "sg:address":"101 Grimsby Rd",
    "sg:city":"Cleethorpes",
    "sg:classifiers":[
        {
            "category":"Shopping",
            "type":"Retail Goods"
        }
    ],
    "sg:postcode":"DN35 7DD",
    "sg:province":"Lincolnshire",
    "sg:tags":[
        "merchant"
    ],
    "wof:name":"Barnbrook,David,",
    "wof:placetype":"venue"
},
  "geometry": {"coordinates":[-0.051609,53.570229],"type":"Point"}
}