{
  "type": "Feature",
  "properties": {
    "addr:full":"Bishopsfauld Farm, Comrie Crieff Perth and Kinross PH6 2JS",
    "addr:postcode":"ph6 2js",
    "iso:country":"GB",
    "sg:address":"Bishopsfauld Farm, Comrie",
    "sg:city":"Crieff",
    "sg:classifiers":[
        {
            "category":"Shopping",
            "subcategory":"Party Supplies",
            "type":"Retail Goods"
        },
        {
            "category":"Farming",
            "subcategory":"Livestock Farm",
            "type":"Manufacturing & Wholesale Goods"
        }
    ],
    "sg:postcode":"PH6 2JS",
    "sg:province":"Perth and Kinross",
    "sg:tags":[
        "inflatables",
        "bouncy",
        "castle",
        "others"
    ],
    "wof:name":"J McCrae & Sons",
    "wof:placetype":"venue"
},
  "geometry": {"coordinates":[-3.985064,56.370964],"type":"Point"}
}