{
  "type": "Feature",
  "properties": {
    "iso:country":"GB",
    "sg:address":"Ymca, Eirw Rd",
    "sg:city":"Porth",
    "sg:classifiers":[
        {
            "category":"Personal",
            "subcategory":"Beauty Salon",
            "type":"Services"
        }
    ],
    "sg:postcode":"CF39 9LT",
    "sg:province":"Bridgend",
    "sg:tags":[
        "unisex",
        "hairdresser"
    ],
    "wof:name":"Thomas,Michael,",
    "wof:placetype":"venue"
},
  "geometry": {"coordinates":[-3.4109508991,51.614982605],"type":"Point"}
}