{
  "type": "Feature",
  "properties": {
    "iso:country":"GB",
    "sg:address":"Consortium House, 7 Cheap Street",
    "sg:city":"Newbury",
    "sg:classifiers":[
        {
            "category":"Education",
            "subcategory":"Special Training",
            "type":"Public Place"
        }
    ],
    "sg:phone":"+44 1635 35975",
    "sg:postcode":"RG14 5DD",
    "sg:province":"Berkshire",
    "sg:tags":[
        "product",
        "centre"
    ],
    "wof:name":"West Berkshire Training Consortium Ltd",
    "wof:placetype":"venue"
},
  "geometry": {"coordinates":[-1.321569,51.398525],"type":"Point"}
}