{
  "type": "Feature",
  "properties": {
    "addr:full":"552 Durham Road Gateshead Tyne and Wear NE9 6HX",
    "addr:housenumber":"552",
    "addr:postcode":"ne9 6hx",
    "addr:street":"Durham Road",
    "iso:country":"GB",
    "sg:address":"552 Durham Road",
    "sg:city":"Gateshead",
    "sg:classifiers":[
        {
            "category":"Professional",
            "subcategory":"Employment Agencies",
            "type":"Services"
        }
    ],
    "sg:phone":"+44 191 420 1000",
    "sg:postcode":"NE9 6HX",
    "sg:province":"Tyne and Wear",
    "sg:tags":[
        "consultant"
    ],
    "wof:name":"Team Valley Recruitment Ltd.",
    "wof:placetype":"venue"
},
  "geometry": {"coordinates":[-1.599718,54.935516],"type":"Point"}
}