{
  "type": "Feature",
  "properties": {
    "iso:country":"GB",
    "sg:address":"81 Prospect Street",
    "sg:city":"Hull",
    "sg:classifiers":[
        {
            "category":"Shopping",
            "subcategory":"Optician",
            "type":"Retail Goods"
        }
    ],
    "sg:phone":"+44 1482 224687",
    "sg:postcode":"HU2 8PE",
    "sg:province":"East Riding of Yorkshire",
    "wof:name":"Crown Optical Centre",
    "wof:placetype":"venue"
},
  "geometry": {"coordinates":[-0.344693,53.747379],"type":"Point"}
}