{
  "type": "Feature",
  "properties": {
    "iso:country":"GB",
    "sg:address":"18 New Road",
    "sg:city":"London",
    "sg:classifiers":[
        {
            "category":"Fast Food",
            "type":"Food & Drink"
        }
    ],
    "sg:postcode":"E1 2AX",
    "sg:province":"Greater London",
    "sg:tags":[
        "away",
        "take"
    ],
    "wof:name":"High Society Restaurants Ltd",
    "wof:placetype":"venue"
},
  "geometry": {"coordinates":[-0.061912,51.515709],"type":"Point"}
}