{
  "type": "Feature",
  "properties": {
    "iso:country":"GB",
    "sg:address":"6 Copperhill St",
    "sg:city":"Aberdovey",
    "sg:classifiers":[
        {
            "category":"Professional",
            "subcategory":"Lawyer & Legal Services",
            "type":"Services"
        }
    ],
    "sg:phone":"+44 1654 767254",
    "sg:postcode":"LL35 0HA",
    "sg:province":"Gwynedd",
    "sg:tags":[
        "solicitor"
    ],
    "wof:name":"Henry Evans Roberts & Co",
    "wof:placetype":"venue"
},
  "geometry": {"coordinates":[-4.045044,52.544224],"type":"Point"}
}