{
  "type": "Feature",
  "properties": {
    "addr:full":"Richford Gate Primary Care Centre Hammersmith Greater London W6 7HY",
    "addr:postcode":"w6 7hy",
    "addr:street":"Richford",
    "iso:country":"GB",
    "sg:address":"Richford Gate Primary Care Centre",
    "sg:city":"Hammersmith",
    "sg:classifiers":[
        {
            "category":"Health Services",
            "subcategory":"Clinic",
            "type":"Services"
        }
    ],
    "sg:phone":"+44 20 8846 7539",
    "sg:postcode":"W6 7HY",
    "sg:province":"Greater London",
    "sg:tags":[
        "aromatherapy"
    ],
    "wof:name":"Mellennium Complementary Health Clinic",
    "wof:placetype":"venue"
},
  "geometry": {"coordinates":[-0.227108,51.499996],"type":"Point"}
}