{
  "type": "Feature",
  "properties": {
    "iso:country":"GB",
    "sg:address":"Baslow Rd",
    "sg:city":"Sheffield",
    "sg:classifiers":[
        {
            "category":"Autos & Motor Vehicles",
            "subcategory":"Automobile Sales",
            "type":"Retail Goods"
        }
    ],
    "sg:phone":"+44 114 236 7888",
    "sg:postcode":"S17 4AE",
    "sg:province":"Derbyshire",
    "sg:tags":[
        "car"
    ],
    "wof:name":"John Holland",
    "wof:placetype":"venue"
},
  "geometry": {"coordinates":[-1.52554,53.319664],"type":"Point"}
}