{
  "type": "Feature",
  "properties": {
    "iso:country":"GB",
    "sg:address":"Park Street",
    "sg:city":"Ammanford",
    "sg:classifiers":[
        {
            "category":"Food & Beverages",
            "subcategory":"Supermarket",
            "type":"Retail Goods"
        }
    ],
    "sg:phone":"+44 1269 815400",
    "sg:postcode":"SA18 2LR",
    "sg:province":"Carmarthenshire",
    "wof:name":"Tesco Stores Ltd.",
    "wof:placetype":"venue"
},
  "geometry": {"coordinates":[-3.984129,51.789398],"type":"Point"}
}