{
  "type": "Feature",
  "properties": {
    "addr:full":"40-42 Charterhouse Street London Greater London EC1M 6EQ",
    "addr:housenumber":"40-42",
    "addr:postcode":"ec1m 6eq",
    "addr:street":"Charterhouse Street",
    "iso:country":"GB",
    "sg:address":"40-42 Charterhouse Street",
    "sg:city":"London",
    "sg:classifiers":[
        {
            "category":"Professional",
            "subcategory":"Advertising",
            "type":"Services"
        }
    ],
    "sg:phone":"+44 20 7454 1919",
    "sg:postcode":"EC1M 6EQ",
    "sg:province":"Greater London",
    "wof:name":"Buckley Deane Wakefield Plc",
    "wof:placetype":"venue"
},
  "geometry": {"coordinates":[-0.100543,51.5201],"type":"Point"}
}