{
  "type": "Feature",
  "properties": {
    "addr:full":"Littlebrook Manorway Dartford Kent DA1 5EA",
    "addr:postcode":"da1 5ea",
    "addr:street":"Manorway",
    "iso:country":"GB",
    "sg:address":"Littlebrook Manorway",
    "sg:city":"Dartford",
    "sg:classifiers":[
        {
            "category":"Education",
            "subcategory":"School",
            "type":"Public Place"
        }
    ],
    "sg:phone":"+44 1322 225173",
    "sg:postcode":"DA1 5EA",
    "sg:province":"Kent",
    "sg:tags":[
        "local",
        "authority"
    ],
    "wof:name":"St Anselm's R C Primary School",
    "wof:placetype":"venue"
},
  "geometry": {"coordinates":[0.237819,51.452724],"type":"Point"}
}