{
  "type": "Feature",
  "properties": {
    "iso:country":"GB",
    "sg:address":"Tanzaro Ho, Ardwick Green North",
    "sg:city":"Manchester",
    "sg:classifiers":[
        {
            "category":"Organizations",
            "subcategory":"Community Association",
            "type":"Services"
        }
    ],
    "sg:phone":"+44 161 272 8881",
    "sg:postcode":"M12 6FZ",
    "sg:province":"Greater Manchester",
    "sg:tags":[
        "relation",
        "public"
    ],
    "wof:name":"Merchant & Co",
    "wof:placetype":"venue"
},
  "geometry": {"coordinates":[-2.222435,53.469074],"type":"Point"}
}