{
  "type": "Feature",
  "properties": {
    "addr:full":"34 Valley Rd, Bredbury Stockport Cheshire SK6 2DZ",
    "addr:housenumber":"34",
    "addr:postcode":"sk6 2dz",
    "addr:street":"Valley Rd",
    "iso:country":"GB",
    "sg:address":"34 Valley Rd, Bredbury",
    "sg:city":"Stockport",
    "sg:classifiers":[
        {
            "category":"Health Services",
            "subcategory":"Health Practitioner",
            "type":"Services"
        }
    ],
    "sg:phone":"+44 161 406 7683",
    "sg:postcode":"SK6 2DZ",
    "sg:province":"Cheshire",
    "sg:tags":[
        "therapist",
        "speech"
    ],
    "wof:name":"Chikara Training for Reiki",
    "wof:placetype":"venue"
},
  "geometry": {"coordinates":[-2.1263868809,53.4211349487],"type":"Point"}
}