{
  "type": "Feature",
  "properties": {
    "iso:country":"GB",
    "sg:address":"27 West End",
    "sg:city":"Witney",
    "sg:classifiers":[
        {
            "category":"Shopping",
            "subcategory":"Party Supplies",
            "type":"Retail Goods"
        }
    ],
    "sg:postcode":"OX28 1NQ",
    "sg:province":"Oxfordshire",
    "sg:tags":[
        "marquees",
        "floor",
        "tent"
    ],
    "wof:name":"B H K Rentals",
    "wof:placetype":"venue"
},
  "geometry": {"coordinates":[-1.481737,51.791267],"type":"Point"}
}