{
  "type": "Feature",
  "properties": {
    "addr:full":"Westminster Council Ho, Room 18 97 Marylebone Rd London Greater London NW1 5PT",
    "addr:housenumber":"97",
    "addr:postcode":"nw1 5pt",
    "addr:street":"Marylebone Rd",
    "iso:country":"GB",
    "sg:address":"Westminster Council Ho, Room 18 97 Marylebone Rd",
    "sg:city":"London",
    "sg:classifiers":[
        {
            "category":"Government",
            "subcategory":"Office",
            "type":"Public Place"
        }
    ],
    "sg:postcode":"NW1 5PT",
    "sg:province":"Greater London",
    "sg:tags":[
        "local"
    ],
    "wof:name":"Westminster City Council",
    "wof:placetype":"venue"
},
  "geometry": {"coordinates":[-0.1599600017,51.5211601257],"type":"Point"}
}