{
  "type": "Feature",
  "properties": {
    "addr:full":"39 Netherford Road, Clapham London Greater London SW4 6AF",
    "addr:housenumber":"39",
    "addr:postcode":"sw4 6af",
    "addr:street":"Netherford Road",
    "iso:country":"GB",
    "sg:address":"39 Netherford Road, Clapham",
    "sg:city":"London",
    "sg:classifiers":[
        {
            "category":"Professional",
            "subcategory":"Management & Consulting",
            "type":"Services"
        }
    ],
    "sg:postcode":"SW4 6AF",
    "sg:province":"Greater London",
    "sg:tags":[
        "consultant",
        "business"
    ],
    "wof:name":"Anemone Dealers Ltd.",
    "wof:placetype":"venue"
},
  "geometry": {"coordinates":[-0.139798,51.469372],"type":"Point"}
}