{
  "type": "Feature",
  "properties": {
    "iso:country":"GB",
    "sg:address":"Duke Street",
    "sg:city":"Denny",
    "sg:classifiers":[
        {
            "category":"Personal",
            "type":"Services"
        }
    ],
    "sg:phone":"+44 1324 822809",
    "sg:postcode":"FK6 6DA",
    "sg:province":"Falkirk",
    "sg:tags":[
        "delivery"
    ],
    "wof:name":"Royal Mail",
    "wof:placetype":"venue"
},
  "geometry": {"coordinates":[-3.909694,56.023159],"type":"Point"}
}