{
  "type": "Feature",
  "properties": {
    "iso:country":"GB",
    "sg:address":"The Mill, Marsh Fold Lane",
    "sg:city":"Bolton",
    "sg:classifiers":[
        {
            "category":"Wholesale",
            "subcategory":"Scrap",
            "type":"Manufacturing & Wholesale Goods"
        }
    ],
    "sg:phone":"+44 1204 847697",
    "sg:postcode":"BL1 4HG",
    "sg:province":"Lancashire",
    "sg:tags":[
        "breaker",
        "dismantlers"
    ],
    "wof:name":"Bournemouth Auto Spares Co",
    "wof:placetype":"venue"
},
  "geometry": {"coordinates":[-2.451709,53.583149],"type":"Point"}
}