{
  "type": "Feature",
  "properties": {
    "addr:full":"337 Ashby Road Coalville Leicestershire LE67 3LH",
    "addr:housenumber":"337",
    "addr:postcode":"le67 3lh",
    "addr:street":"Ashby Road",
    "iso:country":"GB",
    "sg:address":"337 Ashby Road",
    "sg:city":"Coalville",
    "sg:classifiers":[
        {
            "category":"Home & Garden",
            "subcategory":"Hardware",
            "type":"Retail Goods"
        }
    ],
    "sg:postcode":"LE67 3LH",
    "sg:province":"Leicestershire",
    "sg:tags":[
        "lawnmowers",
        "machinery"
    ],
    "wof:name":"Gibsons Lawnmower Services",
    "wof:placetype":"venue"
},
  "geometry": {"coordinates":[-1.395185,52.731468],"type":"Point"}
}