{
  "type": "Feature",
  "properties": {
    "addr:full":"Tinklers Lane Chorley Lancashire PR6 0QG",
    "addr:postcode":"pr6 0qg",
    "addr:street":"Tinklers Lane",
    "iso:country":"GB",
    "sg:address":"Tinklers Lane",
    "sg:city":"Chorley",
    "sg:classifiers":[
        {
            "category":"Autos & Motor Vehicles",
            "subcategory":"Automobile Sales",
            "type":"Retail Goods"
        }
    ],
    "sg:phone":"+44 1257 265360",
    "sg:postcode":"PR6 0QG",
    "sg:province":"Lancashire",
    "sg:tags":[
        "car"
    ],
    "wof:name":"Motoron Service Centre",
    "wof:placetype":"venue"
},
  "geometry": {"coordinates":[-2.61642,53.649429],"type":"Point"}
}