{
  "type": "Feature",
  "properties": {
    "addr:full":"14 Bardolph Road Richmond Greater London TW9 2LH",
    "addr:housenumber":"14",
    "addr:postcode":"tw9 2lh",
    "addr:street":"Bardolph Road",
    "iso:country":"GB",
    "sg:address":"14 Bardolph Road",
    "sg:city":"Richmond",
    "sg:classifiers":[
        {
            "category":"Building & Trades",
            "subcategory":"Pest Control",
            "type":"Services"
        },
        {
            "category":"Building & Trades",
            "subcategory":"Construction",
            "type":"Services"
        }
    ],
    "sg:phone":"+44 20 8948 6321",
    "sg:postcode":"TW9 2LH",
    "sg:province":"Greater London",
    "sg:tags":[
        "painting",
        "decorator",
        "painter",
        "contractor"
    ],
    "wof:name":"F A Clover & Son Ltd.",
    "wof:placetype":"venue"
},
  "geometry": {"coordinates":[-0.2898640037,51.4664611816],"type":"Point"}
}