{
  "type": "Feature",
  "properties": {
    "iso:country":"GB",
    "sg:address":"Moorside Farm, Tushingham",
    "sg:city":"Whitchurch",
    "sg:classifiers":[
        {
            "category":"Shopping",
            "subcategory":"Party Supplies",
            "type":"Retail Goods"
        }
    ],
    "sg:phone":"+44 1948 665142",
    "sg:postcode":"SY13 4QN",
    "sg:province":"Cheshire",
    "sg:tags":[
        "marquees",
        "floor",
        "tent"
    ],
    "wof:name":"4 Seasons Marquee Hire",
    "wof:placetype":"venue"
},
  "geometry": {"coordinates":[-2.685209,52.970558],"type":"Point"}
}