{
  "type": "Feature",
  "properties": {
    "iso:country":"GB",
    "sg:address":"Alston Old Hall, Alston Lane, Alston",
    "sg:city":"Preston",
    "sg:classifiers":[
        {
            "category":"Education",
            "subcategory":"University",
            "type":"Public Place"
        }
    ],
    "sg:phone":"+44 1772 784661",
    "sg:postcode":"PR3 3BN",
    "sg:province":"Lancashire",
    "sg:tags":[
        "adult"
    ],
    "wof:name":"Alston Properties Ltd.",
    "wof:placetype":"venue"
},
  "geometry": {"coordinates":[-2.6085939407,53.8128509521],"type":"Point"}
}