{
  "type": "Feature",
  "properties": {
    "iso:country":"GB",
    "sg:address":"41 Hesketh Avenue",
    "sg:city":"Blackpool",
    "sg:classifiers":[
        {
            "category":"Travel",
            "subcategory":"Hotels & Motels",
            "type":"Entertainment"
        }
    ],
    "sg:phone":"+44 1253 500678",
    "sg:postcode":"FY2 9JX",
    "sg:province":"Lancashire",
    "sg:tags":[
        "house",
        "guest"
    ],
    "wof:name":"Mauretania Guest House",
    "wof:placetype":"venue"
},
  "geometry": {"coordinates":[-3.051224,53.848961],"type":"Point"}
}