{
  "type": "Feature",
  "properties": {
    "addr:full":"Unit 3 Tesco Superstore, Ropes Drive, Kesgrave Ipswich Suffolk IP5 2FU",
    "addr:housenumber":"unit 3",
    "addr:postcode":"ip5 2fu",
    "addr:street":"Ropes Drive",
    "iso:country":"GB",
    "sg:address":"Unit 3 Tesco Superstore, Ropes Drive, Kesgrave",
    "sg:city":"Ipswich",
    "sg:classifiers":[
        {
            "category":"Retail",
            "subcategory":"Laundry & Dry Cleaning",
            "type":"Services"
        }
    ],
    "sg:phone":"+44 1473 625657",
    "sg:postcode":"IP5 2FU",
    "sg:province":"Suffolk",
    "sg:tags":[
        "alteration"
    ],
    "wof:name":"Prim Dry Cleaners",
    "wof:placetype":"venue"
},
  "geometry": {"coordinates":[1.240535,52.066456],"type":"Point"}
}