{
  "type": "Feature",
  "properties": {
    "iso:country":"GB",
    "sg:address":"3 Bruce Court",
    "sg:city":"Hawick",
    "sg:classifiers":[
        {
            "category":"Military Area",
            "subcategory":"Air Force Base",
            "type":"Public Place"
        }
    ],
    "sg:postcode":"TD9 7ER",
    "sg:province":"Cumbria",
    "sg:tags":[
        "taxi",
        "hire",
        "private"
    ],
    "wof:name":"D Grant Wilson",
    "wof:placetype":"venue"
},
  "geometry": {"coordinates":[-2.791171,55.428261],"type":"Point"}
}