{
  "type": "Feature",
  "properties": {
    "addr:full":"78c Manor St Braintree Essex CM7 3HP",
    "addr:housenumber":"78c",
    "addr:postcode":"cm7 3hp",
    "addr:street":"Manor St",
    "iso:country":"GB",
    "sg:address":"78c Manor St",
    "sg:city":"Braintree",
    "sg:classifiers":[
        {
            "category":"Shopping",
            "subcategory":"Computers & Home Electronics",
            "type":"Retail Goods"
        }
    ],
    "sg:phone":"+44 1376 349314",
    "sg:postcode":"CM7 3HP",
    "sg:province":"Essex",
    "wof:name":"Skyline Computers",
    "wof:placetype":"venue"
},
  "geometry": {"coordinates":[0.5579410195,51.8779754639],"type":"Point"}
}