{
  "type": "Feature",
  "properties": {
    "addr:full":"Course Hill, Templeton Narberth Carmarthenshire SA67 8SR",
    "addr:postcode":"sa67 8sr",
    "addr:street":"Course Hill",
    "iso:country":"GB",
    "sg:address":"Course Hill, Templeton",
    "sg:city":"Narberth",
    "sg:classifiers":[
        {
            "category":"Retail",
            "subcategory":"Auto Repair",
            "type":"Services"
        }
    ],
    "sg:postcode":"SA67 8SR",
    "sg:province":"Carmarthenshire",
    "sg:tags":[
        "modification",
        "garage"
    ],
    "wof:name":"Haydn Edwards",
    "wof:placetype":"venue"
},
  "geometry": {"coordinates":[-4.736469,51.771584],"type":"Point"}
}