{
  "type": "Feature",
  "properties": {
    "addr:full":"Unit 6 Castle Mills Northgate Cleckheaton West Yorkshire BD19 3JB",
    "addr:housenumber":"unit 6",
    "addr:postcode":"bd19 3jb",
    "addr:street":"Castle Mills Northgate",
    "iso:country":"GB",
    "sg:address":"Unit 6 Castle Mills Northgate",
    "sg:city":"Cleckheaton",
    "sg:classifiers":[
        {
            "category":"Home & Garden",
            "subcategory":"Hardware",
            "type":"Retail Goods"
        }
    ],
    "sg:phone":"+44 1274 871445",
    "sg:postcode":"BD19 3JB",
    "sg:province":"West Yorkshire",
    "sg:tags":[
        "device",
        "fixing",
        "fastener"
    ],
    "wof:name":"The Stapling Centre Ltd.",
    "wof:placetype":"venue"
},
  "geometry": {"coordinates":[-1.7118890285,53.7251701355],"type":"Point"}
}