{
  "type": "Feature",
  "properties": {
    "addr:full":"Rosslyn Street Brora Highland KW9 6NY",
    "addr:postcode":"kw9 6ny",
    "addr:street":"Rosslyn Street",
    "iso:country":"GB",
    "sg:address":"Rosslyn Street",
    "sg:city":"Brora",
    "sg:classifiers":[
        {
            "category":"Cafe",
            "type":"Food & Drink"
        }
    ],
    "sg:phone":"+44 1408 621467",
    "sg:postcode":"KW9 6NY",
    "sg:province":"Highland",
    "sg:tags":[
        "tea",
        "snack",
        "bar",
        "room"
    ],
    "wof:name":"Fountain Cafe",
    "wof:placetype":"venue"
},
  "geometry": {"coordinates":[-3.857825,58.010838],"type":"Point"}
}