{
  "type": "Feature",
  "properties": {
    "iso:country":"GB",
    "sg:address":"Beacon Road, Woodhouse Eaves",
    "sg:city":"Loughborough",
    "sg:classifiers":[
        {
            "category":"Landmark",
            "subcategory":"Tourist Attraction",
            "type":"Public Place"
        }
    ],
    "sg:phone":"+44 1509 890048",
    "sg:postcode":"LE12 8SP",
    "sg:province":"Leicestershire",
    "sg:tags":[
        "interest"
    ],
    "wof:name":"Beacon Hill & Broombriggs Farm Country Park",
    "wof:placetype":"venue"
},
  "geometry": {"coordinates":[-1.223539,52.727024],"type":"Point"}
}