{
  "type": "Feature",
  "properties": {
    "addr:full":"1642 High St Solihull Warwickshire B93 0NA",
    "addr:housenumber":"1642",
    "addr:postcode":"b93 0na",
    "addr:street":"High St",
    "iso:country":"GB",
    "sg:address":"1642 High St",
    "sg:city":"Solihull",
    "sg:classifiers":[
        {
            "category":"Home & Garden",
            "subcategory":"Home Furnishings",
            "type":"Retail Goods"
        }
    ],
    "sg:postcode":"B93 0NA",
    "sg:province":"Warwickshire",
    "sg:tags":[
        "blind",
        "curtain",
        "fitting"
    ],
    "wof:name":"Studio Four Est 1971",
    "wof:placetype":"venue"
},
  "geometry": {"coordinates":[-1.7349129915,52.3885879517],"type":"Point"}
}