{
  "type": "Feature",
  "properties": {
    "iso:country":"GB",
    "sg:address":"51 Hare Crescent",
    "sg:city":"Watford",
    "sg:classifiers":[
        {
            "category":"Building & Trades",
            "subcategory":"Construction",
            "type":"Services"
        }
    ],
    "sg:postcode":"WD25 7EE",
    "sg:province":"Hertfordshire",
    "sg:tags":[
        "decorator",
        "painter"
    ],
    "wof:name":"Tony Martin",
    "wof:placetype":"venue"
},
  "geometry": {"coordinates":[-0.404493,51.697453],"type":"Point"}
}