{
  "type": "Feature",
  "properties": {
    "addr:full":"22 The Lanes, Oasis, Meadowhall Centre Sheffield South Yorkshire S9 1EP",
    "addr:housenumber":"22",
    "addr:postcode":"s9 1ep",
    "addr:street":"The",
    "iso:country":"GB",
    "sg:address":"22 The Lanes, Oasis, Meadowhall Centre",
    "sg:city":"Sheffield",
    "sg:classifiers":[
        {
            "category":"Shopping",
            "subcategory":"Gifts & Souvenirs",
            "type":"Retail Goods"
        }
    ],
    "sg:phone":"+44 114 256 9816",
    "sg:postcode":"S9 1EP",
    "sg:province":"South Yorkshire",
    "sg:tags":[
        "shop"
    ],
    "wof:name":"Funky Monkey",
    "wof:placetype":"venue"
},
  "geometry": {"coordinates":[-1.41245,53.413029],"type":"Point"}
}