{
  "type": "Feature",
  "properties": {
    "addr:full":"4 Churchill Road, Barton Le Clay Bedford Bedfordshire MK45 4NH",
    "addr:housenumber":"4",
    "addr:postcode":"mk45 4nh",
    "addr:street":"Churchill Road;Le Clay",
    "iso:country":"GB",
    "sg:address":"4 Churchill Road, Barton Le Clay",
    "sg:city":"Bedford",
    "sg:classifiers":[
        {
            "category":"Communications",
            "type":"Services"
        }
    ],
    "sg:phone":"+44 1582 882900",
    "sg:postcode":"MK45 4NH",
    "sg:province":"Bedfordshire",
    "sg:tags":[
        "telecommunication"
    ],
    "wof:name":"Adafone",
    "wof:placetype":"venue"
},
  "geometry": {"coordinates":[-0.425605,51.970306],"type":"Point"}
}