{
  "type": "Feature",
  "properties": {
    "iso:country":"GB",
    "sg:address":"Mill St",
    "sg:city":"Bedworth",
    "sg:classifiers":[
        {
            "category":"Food & Beverages",
            "subcategory":"Supermarket",
            "type":"Retail Goods"
        }
    ],
    "sg:phone":"+44 24 7664 3888",
    "sg:postcode":"CV12 8JY",
    "sg:province":"Warwickshire",
    "wof:name":"Food Giant",
    "wof:placetype":"venue"
},
  "geometry": {"coordinates":[-1.475489,52.480206],"type":"Point"}
}