{
  "type": "Feature",
  "properties": {
    "iso:country":"GB",
    "sg:address":"5 Old Compton Street",
    "sg:city":"London",
    "sg:classifiers":[
        {
            "category":"Organizations",
            "subcategory":"Non-profit Organization",
            "type":"Services"
        }
    ],
    "sg:phone":"+44 20 7434 0538",
    "sg:postcode":"W1D 5JE",
    "sg:province":"Greater London",
    "sg:tags":[
        "organisation",
        "voluntary",
        "charity"
    ],
    "wof:name":"Cheung's Clansman Association",
    "wof:placetype":"venue"
},
  "geometry": {"coordinates":[-0.1297529936,51.5136146545],"type":"Point"}
}