{
  "type": "Feature",
  "properties": {
    "addr:full":"250 Upper Richmond Road West London Greater London SW14 8AG",
    "addr:housenumber":"250",
    "addr:postcode":"sw14 8ag",
    "addr:street":"Upper Richmond Road West",
    "iso:country":"GB",
    "sg:address":"250 Upper Richmond Road West",
    "sg:city":"London",
    "sg:classifiers":[
        {
            "category":"Shopping",
            "subcategory":"News",
            "type":"Retail Goods"
        }
    ],
    "sg:phone":"+44 20 8876 3015",
    "sg:postcode":"SW14 8AG",
    "sg:province":"Greater London",
    "sg:tags":[
        "newsagent"
    ],
    "wof:name":"Smart News",
    "wof:placetype":"venue"
},
  "geometry": {"coordinates":[-0.2665190101,51.4648933411],"type":"Point"}
}