{
  "type": "Feature",
  "properties": {
    "iso:country":"GB",
    "sg:address":"11",
    "sg:city":"Ringwood",
    "sg:classifiers":[
        {
            "category":"Communications",
            "type":"Services"
        }
    ],
    "sg:postcode":"WF9 4HZ",
    "sg:province":"West Yorkshire",
    "sg:tags":[
        "data",
        "network"
    ],
    "wof:name":"Highdata Ltd",
    "wof:placetype":"venue"
},
  "geometry": {"coordinates":[-1.353399,53.61195],"type":"Point"}
}