{
  "type": "Feature",
  "properties": {
    "addr:full":"Millpit Farm, Croppers Lane, Freiston Boston Lincolnshire PE22 0QN",
    "addr:postcode":"pe22 0qn",
    "addr:street":"Croppers Lane",
    "iso:country":"GB",
    "sg:address":"Millpit Farm, Croppers Lane, Freiston",
    "sg:city":"Boston",
    "sg:classifiers":[
        {
            "category":"Farming",
            "subcategory":"Livestock Farm",
            "type":"Manufacturing & Wholesale Goods"
        },
        {
            "category":"Farming",
            "subcategory":"Farm",
            "type":"Manufacturing & Wholesale Goods"
        }
    ],
    "sg:phone":"+44 1205 760355",
    "sg:postcode":"PE22 0QN",
    "sg:province":"Lincolnshire",
    "sg:tags":[
        "mixed",
        "others"
    ],
    "wof:name":"A W & F HARDY",
    "wof:placetype":"venue"
},
  "geometry": {"coordinates":[0.04558,52.976391],"type":"Point"}
}