{
  "type": "Feature",
  "properties": {
    "addr:full":"24 Dunkeld Road Perth Perth and Kinross PH1 5RW",
    "addr:housenumber":"24",
    "addr:postcode":"ph1 5rw",
    "addr:street":"Dunkeld Road",
    "iso:country":"GB",
    "sg:address":"24 Dunkeld Road",
    "sg:city":"Perth",
    "sg:classifiers":[
        {
            "category":"Travel",
            "subcategory":"Hotels & Motels",
            "type":"Entertainment"
        }
    ],
    "sg:phone":"+44 1738 624717",
    "sg:postcode":"PH1 5RW",
    "sg:province":"Perth and Kinross",
    "sg:tags":[
        "house",
        "guest"
    ],
    "wof:name":"The Gables",
    "wof:placetype":"venue"
},
  "geometry": {"coordinates":[-3.4414789677,56.4026794434],"type":"Point"}
}