{
  "type": "Feature",
  "properties": {
    "iso:country":"GB",
    "sg:address":"7 Green Road",
    "sg:city":"Reading",
    "sg:classifiers":[
        {
            "category":"Professional",
            "subcategory":"Art Services",
            "type":"Services"
        }
    ],
    "sg:phone":"+44 118 966 5452",
    "sg:postcode":"RG6 7BS",
    "sg:province":"Berkshire",
    "sg:tags":[
        "photographer"
    ],
    "wof:name":"Derek Botherel Photography",
    "wof:placetype":"venue"
},
  "geometry": {"coordinates":[-0.9355180264,51.4460792542],"type":"Point"}
}