{
  "type": "Feature",
  "properties": {
    "addr:full":"24 Leven Street Glasgow Glasgow City G41 2JE",
    "addr:housenumber":"24",
    "addr:postcode":"g41 2je",
    "addr:street":"Leven Street",
    "iso:country":"GB",
    "sg:address":"24 Leven Street",
    "sg:city":"Glasgow",
    "sg:classifiers":[
        {
            "category":"Shopping",
            "subcategory":"Computers & Home Electronics",
            "type":"Retail Goods"
        }
    ],
    "sg:phone":"+44 141 429 0029",
    "sg:postcode":"G41 2JE",
    "sg:province":"Glasgow City",
    "sg:tags":[
        "aerial",
        "television",
        "radio"
    ],
    "wof:name":"Antex Aerials",
    "wof:placetype":"venue"
},
  "geometry": {"coordinates":[-4.274479,55.839863],"type":"Point"}
}