{
  "type": "Feature",
  "properties": {
    "addr:full":"Bank Top Station, Bank Top Darlington Durham DL1 4AA",
    "addr:postcode":"dl1 4aa",
    "addr:street":"Bank Top",
    "iso:country":"GB",
    "sg:address":"Bank Top Station, Bank Top",
    "sg:city":"Darlington",
    "sg:classifiers":[
        {
            "category":"Fast Food",
            "type":"Food & Drink"
        }
    ],
    "sg:phone":"+44 1325 281500",
    "sg:postcode":"DL1 4AA",
    "sg:province":"Durham",
    "sg:tags":[
        "away",
        "take"
    ],
    "wof:name":"Travellers Fare Ltd",
    "wof:placetype":"venue"
},
  "geometry": {"coordinates":[-1.548894,54.524502],"type":"Point"}
}