{
  "type": "Feature",
  "properties": {
    "addr:full":"78 St Annes Rd Willenhall West Midlands WV13 1ED",
    "addr:housenumber":"78",
    "addr:postcode":"wv13 1ed",
    "addr:street":"St Annes Rd",
    "iso:country":"GB",
    "sg:address":"78 St Annes Rd",
    "sg:city":"Willenhall",
    "sg:classifiers":[
        {
            "category":"Food & Beverages",
            "subcategory":"Supermarket",
            "type":"Retail Goods"
        }
    ],
    "sg:phone":"+44 1902 605707",
    "sg:postcode":"WV13 1ED",
    "sg:province":"West Midlands",
    "wof:name":"Lucys Bath",
    "wof:placetype":"venue"
},
  "geometry": {"coordinates":[-2.0508000851,52.5920219421],"type":"Point"}
}