{
  "type": "Feature",
  "properties": {
    "addr:full":"12 Orton Road Leicester Leicestershire LE4 2AS",
    "addr:housenumber":"12",
    "addr:postcode":"le4 2as",
    "addr:street":"Orton Road",
    "iso:country":"GB",
    "sg:address":"12 Orton Road",
    "sg:city":"Leicester",
    "sg:classifiers":[
        {
            "category":"Building & Trades",
            "subcategory":"Construction",
            "type":"Services"
        }
    ],
    "sg:phone":"+44 116 266 0666",
    "sg:postcode":"LE4 2AS",
    "sg:province":"Leicestershire",
    "sg:tags":[
        "dry",
        "lining",
        "plasterers",
        "screeders"
    ],
    "wof:name":"C Pallett",
    "wof:placetype":"venue"
},
  "geometry": {"coordinates":[-1.1345119476,52.6583213806],"type":"Point"}
}