{
  "type": "Feature",
  "properties": {
    "iso:country":"GB",
    "sg:address":"148 Cranbrook Road",
    "sg:city":"Ilford",
    "sg:classifiers":[
        {
            "category":"Food & Beverages",
            "subcategory":"Liquor & Beverages",
            "type":"Retail Goods"
        }
    ],
    "sg:phone":"+44 20 8554 2580",
    "sg:postcode":"IG1 4LZ",
    "sg:province":"Essex",
    "sg:tags":[
        "beer",
        "spirit",
        "wines"
    ],
    "wof:name":"Thresher Wine Shop",
    "wof:placetype":"venue"
},
  "geometry": {"coordinates":[0.067978,51.56266],"type":"Point"}
}