{
  "type": "Feature",
  "properties": {
    "addr:full":"4 Station Cottage Elgin Moray IV30 3UP",
    "addr:housenumber":"4",
    "addr:postcode":"iv30 3up",
    "addr:street":"Elgin",
    "iso:country":"GB",
    "sg:address":"4 Station Cottage",
    "sg:city":"Elgin",
    "sg:classifiers":[
        {
            "category":"Professional",
            "subcategory":"Engineering",
            "type":"Services"
        }
    ],
    "sg:phone":"+44 1343 850621",
    "sg:postcode":"IV30 3UP",
    "sg:province":"Moray",
    "sg:tags":[
        "contractor",
        "electrical",
        "engineer"
    ],
    "wof:name":"James Duggie M & Sons",
    "wof:placetype":"venue"
},
  "geometry": {"coordinates":[-3.32902,57.625462],"type":"Point"}
}