{
  "type": "Feature",
  "properties": {
    "addr:full":"3-5 South Street Woolacombe Devon EX34 7BB",
    "addr:housenumber":"3-5",
    "addr:postcode":"ex34 7bb",
    "addr:street":"South Street",
    "iso:country":"GB",
    "sg:address":"3-5 South Street",
    "sg:city":"Woolacombe",
    "sg:classifiers":[
        {
            "category":"Retail",
            "subcategory":"Repair Shop",
            "type":"Services"
        },
        {
            "category":"Shopping",
            "subcategory":"Luggage & Leather Goods",
            "type":"Retail Goods"
        }
    ],
    "sg:phone":"+44 1271 870560",
    "sg:postcode":"EX34 7BB",
    "sg:province":"Devon",
    "sg:tags":[
        "leathergoods"
    ],
    "wof:name":"Bobbins",
    "wof:placetype":"venue"
},
  "geometry": {"coordinates":[-4.2044057846,51.171333313],"type":"Point"}
}