{
  "type": "Feature",
  "properties": {
    "iso:country":"GB",
    "sg:address":"Pratt Street",
    "sg:city":"Kirkcaldy",
    "sg:classifiers":[
        {
            "category":"Travel",
            "subcategory":"Hotels & Motels",
            "type":"Entertainment"
        }
    ],
    "sg:postcode":"KY1 1RZ",
    "sg:province":"Fife",
    "sg:tags":[
        "house",
        "guest"
    ],
    "wof:name":"The Watch House At Crail",
    "wof:placetype":"venue"
},
  "geometry": {"coordinates":[-3.168687,56.103203],"type":"Point"}
}