{
  "type": "Feature",
  "properties": {
    "iso:country":"GB",
    "sg:address":"22 Hatch Lane, Old Basing",
    "sg:city":"Basingstoke",
    "sg:classifiers":[
        {
            "category":"Professional",
            "subcategory":"Accounting & Tax Preparation",
            "type":"Services"
        }
    ],
    "sg:phone":"+44 1243 830409",
    "sg:postcode":"RG24 7EA",
    "sg:province":"Hampshire",
    "sg:tags":[
        "accountant"
    ],
    "wof:name":"Martin Fahy & Co.",
    "wof:placetype":"venue"
},
  "geometry": {"coordinates":[-1.042794,51.267929],"type":"Point"}
}