{
  "type": "Feature",
  "properties": {
    "addr:full":"Sion Hill Bristol City of Bristol BS8 4BB",
    "addr:postcode":"bs8 4bb",
    "addr:street":"Sion Hill",
    "iso:country":"GB",
    "sg:address":"Sion Hill",
    "sg:city":"Bristol",
    "sg:classifiers":[
        {
            "category":"Travel",
            "subcategory":"Hotels & Motels",
            "type":"Entertainment"
        }
    ],
    "sg:phone":"+44 117 973 9251",
    "sg:postcode":"BS8 4BB",
    "sg:province":"City of Bristol",
    "wof:name":"Woods,D,",
    "wof:placetype":"venue"
},
  "geometry": {"coordinates":[-2.6253380775,51.4540328979],"type":"Point"}
}