{
  "type": "Feature",
  "properties": {
    "addr:full":"Hills Lane Biggleswade Bedfordshire SG18 9AY",
    "addr:postcode":"sg18 9ay",
    "addr:street":"Hills Lane",
    "iso:country":"GB",
    "sg:address":"Hills Lane",
    "sg:city":"Biggleswade",
    "sg:classifiers":[
        {
            "category":"Sports & Exercise",
            "subcategory":"Golf",
            "type":"Entertainment"
        }
    ],
    "sg:phone":"+44 1767 318040",
    "sg:postcode":"SG18 9AY",
    "sg:province":"Bedfordshire",
    "sg:tags":[
        "equipment"
    ],
    "wof:name":"American Golf Discount Centre",
    "wof:placetype":"venue"
},
  "geometry": {"coordinates":[-0.2902660072,52.0913543701],"type":"Point"}
}