{
  "type": "Feature",
  "properties": {
    "iso:country":"GB",
    "sg:address":"Chestnut House, Stonegate, Weston",
    "sg:city":"Spalding",
    "sg:classifiers":[
        {
            "category":"Food & Beverages",
            "subcategory":"Groceries & Convenience Stores",
            "type":"Retail Goods"
        }
    ],
    "sg:postcode":"PE12 6HR",
    "sg:province":"Cambridgeshire",
    "sg:tags":[
        "merchant",
        "potato"
    ],
    "wof:name":"M C D Produce Ltd.",
    "wof:placetype":"venue"
},
  "geometry": {"coordinates":[-0.086939,52.806347],"type":"Point"}
}