{
  "type": "Feature",
  "properties": {
    "addr:full":"14the Rows, The High Harlow Essex CM20 1BX",
    "addr:postcode":"cm20 1bx",
    "iso:country":"GB",
    "sg:address":"14the Rows, The High",
    "sg:city":"Harlow",
    "sg:classifiers":[
        {
            "category":"Bars & Pubs",
            "subcategory":"Nightclub",
            "type":"Food & Drink"
        }
    ],
    "sg:postcode":"CM20 1BX",
    "sg:province":"Essex",
    "sg:tags":[
        "club",
        "night"
    ],
    "wof:name":"Hexapoint Ltd.",
    "wof:placetype":"venue"
},
  "geometry": {"coordinates":[0.09343,51.771095],"type":"Point"}
}