{
  "type": "Feature",
  "properties": {
    "addr:full":"9 Chartist Tower, Upper Dock Street Newport Newport NP20 1DW",
    "addr:housenumber":"9",
    "addr:postcode":"np20 1dw",
    "addr:street":"Chartist Tower Upper Dock Street",
    "iso:country":"GB",
    "sg:address":"9 Chartist Tower, Upper Dock Street",
    "sg:city":"Newport",
    "sg:classifiers":[
        {
            "category":"Travel",
            "subcategory":"Travel Agent",
            "type":"Entertainment"
        }
    ],
    "sg:postcode":"NP20 1DW",
    "sg:province":"Newport",
    "wof:name":"Air Ticket Centre",
    "wof:placetype":"venue"
},
  "geometry": {"coordinates":[-2.9954900742,51.5872383118],"type":"Point"}
}