{
  "type": "Feature",
  "properties": {
    "iso:country":"GB",
    "sg:address":"5th Floor, 29 Bressenden Pl",
    "sg:city":"London",
    "sg:classifiers":[
        {
            "category":"Wholesale",
            "subcategory":"Books, Periodicals, & Newspapers",
            "type":"Manufacturing & Wholesale Goods"
        }
    ],
    "sg:phone":"+44 20 7233 7233",
    "sg:postcode":"SW1E 5DR",
    "sg:province":"Greater London",
    "sg:tags":[
        "publishing"
    ],
    "wof:name":"Intapress Ltd",
    "wof:placetype":"venue"
},
  "geometry": {"coordinates":[-0.142059,51.497391],"type":"Point"}
}