{
  "type": "Feature",
  "properties": {
    "iso:country":"GB",
    "sg:address":"Old Fire Station, East Street",
    "sg:city":"Olney",
    "sg:classifiers":[
        {
            "category":"Professional",
            "subcategory":"Art Services",
            "type":"Services"
        }
    ],
    "sg:phone":"+44 1234 711577",
    "sg:postcode":"MK46 4DH",
    "sg:province":"Buckinghamshire",
    "sg:tags":[
        "carver",
        "sculptor"
    ],
    "wof:name":"W A Slaney & Son",
    "wof:placetype":"venue"
},
  "geometry": {"coordinates":[-0.701844,52.153469],"type":"Point"}
}