{
  "type": "Feature",
  "properties": {
    "iso:country":"GB",
    "sg:address":"4 The Parade, Southfields",
    "sg:city":"Letchworth",
    "sg:classifiers":[
        {
            "category":"Government",
            "subcategory":"Post Office",
            "type":"Public Place"
        }
    ],
    "sg:phone":"+44 1462 686629",
    "sg:postcode":"SG6 4NB",
    "sg:province":"Hertfordshire",
    "wof:name":"Southfield Sub Post Office",
    "wof:placetype":"venue"
},
  "geometry": {"coordinates":[-0.2281820029,51.982257843],"type":"Point"}
}