{
  "type": "Feature",
  "properties": {
    "addr:full":"45 Turkey Rd Bexhill-on-sea East Sussex TN39 5HB",
    "addr:housenumber":"45",
    "addr:postcode":"tn39 5hb",
    "addr:street":"Turkey Rd",
    "iso:country":"GB",
    "sg:address":"45 Turkey Rd",
    "sg:city":"Bexhill-on-sea",
    "sg:classifiers":[
        {
            "category":"Shopping",
            "subcategory":"Antiques",
            "type":"Retail Goods"
        }
    ],
    "sg:postcode":"TN39 5HB",
    "sg:province":"East Sussex",
    "wof:name":"The Old Minthouse Antiques",
    "wof:placetype":"venue"
},
  "geometry": {"coordinates":[0.464958,50.85693],"type":"Point"}
}