{
  "type": "Feature",
  "properties": {
    "addr:full":"43 Stonelaw Road, Rutherglen Glasgow Glasgow City G73 3TN",
    "addr:housenumber":"43",
    "addr:postcode":"g73 3tn",
    "addr:street":"Stonelaw Road",
    "iso:country":"GB",
    "sg:address":"43 Stonelaw Road, Rutherglen",
    "sg:city":"Glasgow",
    "sg:classifiers":[
        {
            "category":"Fast Food",
            "type":"Food & Drink"
        }
    ],
    "sg:postcode":"G73 3TN",
    "sg:province":"Glasgow City",
    "sg:tags":[
        "away",
        "take"
    ],
    "wof:name":"Little Spice",
    "wof:placetype":"venue"
},
  "geometry": {"coordinates":[-4.2101888657,55.8269462585],"type":"Point"}
}