{
  "type": "Feature",
  "properties": {
    "iso:country":"GB",
    "sg:address":"Eastbury Avenue",
    "sg:city":"Northwood",
    "sg:classifiers":[
        {
            "category":"Health Services",
            "subcategory":"Nursing And Care Facility",
            "type":"Services"
        },
        {
            "category":"Social Services",
            "subcategory":"Retirement Home",
            "type":"Services"
        }
    ],
    "sg:phone":"+44 1923 824585",
    "sg:postcode":"HA6 3LN",
    "sg:province":"Greater London",
    "sg:tags":[
        "residential",
        "rest"
    ],
    "wof:name":"Pocklington House",
    "wof:placetype":"venue"
},
  "geometry": {"coordinates":[-0.420721,51.616657],"type":"Point"}
}