{
  "type": "Feature",
  "properties": {
    "addr:full":"Rear Of 135 Birmingham Road, Shenstone Wood End Lichfield Staffordshire WS14 0LP",
    "addr:postcode":"ws14 0lp",
    "addr:street":"Birmingham Road",
    "iso:country":"GB",
    "sg:address":"Rear Of 135 Birmingham Road, Shenstone Wood End",
    "sg:city":"Lichfield",
    "sg:classifiers":[
        {
            "category":"Professional",
            "subcategory":"Engineering",
            "type":"Services"
        },
        {
            "category":"Real Estate",
            "subcategory":"Architect",
            "type":"Services"
        }
    ],
    "sg:phone":"+44 1543 480606",
    "sg:postcode":"WS14 0LP",
    "sg:province":"Staffordshire",
    "wof:name":"Todd Auto Engineering Services",
    "wof:placetype":"venue"
},
  "geometry": {"coordinates":[-1.8403099775,52.6407814026],"type":"Point"}
}