{
  "type": "Feature",
  "properties": {
    "addr:full":"Exhibition Way, Pinhoe Exeter Devon EX4 8HX",
    "addr:postcode":"ex4 8hx",
    "addr:street":"Exhibition Way",
    "iso:country":"GB",
    "sg:address":"Exhibition Way, Pinhoe",
    "sg:city":"Exeter",
    "sg:classifiers":[
        {
            "category":"Retail",
            "subcategory":"Auto Repair",
            "type":"Services"
        }
    ],
    "sg:phone":"+44 1392 466335",
    "sg:postcode":"EX4 8HX",
    "sg:province":"Devon",
    "sg:tags":[
        "body",
        "car"
    ],
    "wof:name":"Exway Coachworks Ltd.",
    "wof:placetype":"venue"
},
  "geometry": {"coordinates":[-3.4830970764,50.7368774414],"type":"Point"}
}