{
  "type": "Feature",
  "properties": {
    "iso:country":"GB",
    "sg:address":"Pigeon Cote Industrial Park",
    "sg:city":"York",
    "sg:classifiers":[
        {
            "category":"Farming",
            "subcategory":"Farm",
            "type":"Manufacturing & Wholesale Goods"
        }
    ],
    "sg:phone":"+44 1904 610504",
    "sg:postcode":"YO32 9JS",
    "sg:province":"North Yorkshire",
    "sg:tags":[
        "agricultural"
    ],
    "wof:name":"Geda Uk Ltd",
    "wof:placetype":"venue"
},
  "geometry": {"coordinates":[-1.0466660261,53.9831085205],"type":"Point"}
}