{
  "type": "Feature",
  "properties": {
    "iso:country":"GB",
    "sg:address":"19 Chittys Walk, Worplesdon",
    "sg:city":"Guildford",
    "sg:classifiers":[
        {
            "category":"Home & Garden",
            "subcategory":"Kitchen Supply",
            "type":"Retail Goods"
        }
    ],
    "sg:postcode":"GU3 3HW",
    "sg:province":"Surrey",
    "sg:tags":[
        "equipment",
        "catering"
    ],
    "wof:name":"C.K.W. Services",
    "wof:placetype":"venue"
},
  "geometry": {"coordinates":[-0.599981,51.260601],"type":"Point"}
}