{
  "type": "Feature",
  "properties": {
    "addr:full":"Ardwell Lane, Greenleys Milton Keynes Buckinghamshire MK12 6AT",
    "addr:postcode":"mk12 6at",
    "addr:street":"Ardwell Lane",
    "iso:country":"GB",
    "sg:address":"Ardwell Lane, Greenleys",
    "sg:city":"Milton Keynes",
    "sg:classifiers":[
        {
            "category":"Education",
            "subcategory":"School",
            "type":"Public Place"
        }
    ],
    "sg:phone":"+44 1908 314698",
    "sg:postcode":"MK12 6AT",
    "sg:province":"Buckinghamshire",
    "sg:tags":[
        "local",
        "authority"
    ],
    "wof:name":"Greenleys First School",
    "wof:placetype":"venue"
},
  "geometry": {"coordinates":[-0.825483,52.055466],"type":"Point"}
}