{
  "type": "Feature",
  "properties": {
    "iso:country":"GB",
    "sg:address":"1 Durham Road, Ealing",
    "sg:city":"London",
    "sg:classifiers":[
        {
            "category":"Building & Trades",
            "subcategory":"Construction",
            "type":"Services"
        }
    ],
    "sg:postcode":"W5 4JR",
    "sg:province":"Greater London",
    "sg:tags":[
        "builder"
    ],
    "wof:name":"Albany Building Contractors",
    "wof:placetype":"venue"
},
  "geometry": {"coordinates":[-0.305826,51.499065],"type":"Point"}
}