{
  "type": "Feature",
  "properties": {
    "iso:country":"GB",
    "sg:address":"32 Hatherleigh Gardens",
    "sg:city":"Bognor Regis",
    "sg:classifiers":[
        {
            "category":"Manufacturing",
            "subcategory":"Petroleum Products",
            "type":"Manufacturing & Wholesale Goods"
        }
    ],
    "sg:phone":"+44 1243 842380",
    "sg:postcode":"PO21 5HZ",
    "sg:province":"West Sussex",
    "sg:tags":[
        "double",
        "glazing"
    ],
    "wof:name":"Swan Windows",
    "wof:placetype":"venue"
},
  "geometry": {"coordinates":[-0.6892579794,50.7955932617],"type":"Point"}
}