{
  "type": "Feature",
  "properties": {
    "iso:country":"GB",
    "sg:address":"12 Steeple Close, Cleobury Mortimer",
    "sg:city":"Kidderminster",
    "sg:classifiers":[
        {
            "category":"Banks & Credit Unions",
            "subcategory":"Investment Brokerage",
            "type":"Services"
        }
    ],
    "sg:postcode":"DY14 8PD",
    "sg:province":"Shropshire",
    "sg:tags":[
        "contractor"
    ],
    "wof:name":"Anthony C Skellern",
    "wof:placetype":"venue"
},
  "geometry": {"coordinates":[-2.4828939438,52.3800010681],"type":"Point"}
}