{
  "type": "Feature",
  "properties": {
    "iso:country":"GB",
    "sg:address":"Unit 1, Beacon Rd",
    "sg:city":"Poulton-le-fylde",
    "sg:classifiers":[
        {
            "category":"Professional",
            "subcategory":"Art Services",
            "type":"Services"
        }
    ],
    "sg:phone":"+44 1253 892989",
    "sg:postcode":"FY6 8JE",
    "sg:province":"Lancashire",
    "sg:tags":[
        "consultant",
        "design"
    ],
    "wof:name":"Entertainment Design & Scenographic Stud",
    "wof:placetype":"venue"
},
  "geometry": {"coordinates":[-2.971694,53.843475],"type":"Point"}
}