{
  "type": "Feature",
  "properties": {
    "iso:country":"GB",
    "sg:address":"3 Brunswick Street",
    "sg:city":"Carlisle",
    "sg:classifiers":[
        {
            "category":"Building & Trades",
            "subcategory":"Construction",
            "type":"Services"
        }
    ],
    "sg:phone":"+44 1576 203982",
    "sg:postcode":"CA1 1PB",
    "sg:province":"Cumbria",
    "sg:tags":[
        "joinery"
    ],
    "wof:name":"Bexley Woodcraft Ltd.",
    "wof:placetype":"venue"
},
  "geometry": {"coordinates":[-2.929221,54.893166],"type":"Point"}
}