{
  "type": "Feature",
  "properties": {
    "addr:full":"2 Thornlaw Road, West Norwood London Greater London SE27 0SA",
    "addr:housenumber":"2",
    "addr:postcode":"se27 0sa",
    "addr:street":"Thornlaw Road",
    "iso:country":"GB",
    "sg:address":"2 Thornlaw Road, West Norwood",
    "sg:city":"London",
    "sg:classifiers":[
        {
            "category":"Place Of Worship",
            "type":"Public Place"
        }
    ],
    "sg:phone":"+44 20 8766 7732",
    "sg:postcode":"SE27 0SA",
    "sg:province":"Greater London",
    "wof:name":"Trinity baptist Church",
    "wof:placetype":"venue"
},
  "geometry": {"coordinates":[-0.104744,51.429604],"type":"Point"}
}