{
  "type": "Feature",
  "properties": {
    "addr:full":"Fleets Farm, East Witton Leyburn North Yorkshire DL8 4SR",
    "addr:housenumber":"witton",
    "addr:postcode":"dl8 4sr",
    "iso:country":"GB",
    "sg:address":"Fleets Farm, East Witton",
    "sg:city":"Leyburn",
    "sg:classifiers":[
        {
            "category":"Farming",
            "subcategory":"Farm",
            "type":"Manufacturing & Wholesale Goods"
        }
    ],
    "sg:phone":"+44 1969 623512",
    "sg:postcode":"DL8 4SR",
    "sg:province":"North Yorkshire",
    "sg:tags":[
        "mixed",
        "crop"
    ],
    "wof:name":"Wensleydale Weaners",
    "wof:placetype":"venue"
},
  "geometry": {"coordinates":[-1.77926898,54.2696495056],"type":"Point"}
}