{
  "type": "Feature",
  "properties": {
    "addr:full":"Unit 17 Wingate Rd, Fort Brockhurst Industrial Estate Gosport Hampshire PO12 4DP",
    "addr:housenumber":"unit 17",
    "addr:postcode":"po12 4dp",
    "addr:street":"Wingate Rd;Industrial Estate",
    "iso:country":"GB",
    "sg:address":"Unit 17 Wingate Rd, Fort Brockhurst Industrial Estate",
    "sg:city":"Gosport",
    "sg:classifiers":[
        {
            "category":"Shopping",
            "subcategory":"Party Supplies",
            "type":"Retail Goods"
        }
    ],
    "sg:phone":"+44 23 9251 0587",
    "sg:postcode":"PO12 4DP",
    "sg:province":"Hampshire",
    "sg:tags":[
        "equipment",
        "disco"
    ],
    "wof:name":"Transit Sound & Light",
    "wof:placetype":"venue"
},
  "geometry": {"coordinates":[-1.152971983,50.816028595],"type":"Point"}
}