{
  "type": "Feature",
  "properties": {
    "iso:country":"GB",
    "sg:address":"168 Severne Rd, Acocks Green",
    "sg:city":"Birmingham",
    "sg:classifiers":[
        {
            "category":"Personal",
            "type":"Services"
        }
    ],
    "sg:postcode":"B27 7HR",
    "sg:province":"West Midlands",
    "sg:tags":[
        "wedding"
    ],
    "wof:name":"McLarity,A,",
    "wof:placetype":"venue"
},
  "geometry": {"coordinates":[-1.822433,52.432671],"type":"Point"}
}