{
  "type": "Feature",
  "properties": {
    "addr:full":"Billingsgate Market, Trafalgar Way London Greater London E14 5ST",
    "addr:postcode":"e14 5st",
    "addr:street":"Billingsgate;Trafalgar Way",
    "iso:country":"GB",
    "sg:address":"Billingsgate Market, Trafalgar Way",
    "sg:city":"London",
    "sg:classifiers":[
        {
            "category":"Food & Beverages",
            "subcategory":"Groceries & Convenience Stores",
            "type":"Retail Goods"
        }
    ],
    "sg:phone":"+44 20 7515 3075",
    "sg:postcode":"E14 5ST",
    "sg:province":"Greater London",
    "sg:tags":[
        "frozen",
        "ice"
    ],
    "wof:name":"Billingsgate Coldstores Ltd.",
    "wof:placetype":"venue"
},
  "geometry": {"coordinates":[-0.0147700002,51.5065803528],"type":"Point"}
}