{
  "type": "Feature",
  "properties": {
    "iso:country":"GB",
    "sg:address":"The Square, Church Street, Woodbury",
    "sg:city":"Exeter",
    "sg:classifiers":[
        {
            "category":"Shopping",
            "subcategory":"Used Merchandise",
            "type":"Retail Goods"
        }
    ],
    "sg:postcode":"EX5 1LL",
    "sg:province":"Devon",
    "sg:tags":[
        "shop",
        "second-hand"
    ],
    "wof:name":"Pink Cottage Antiques",
    "wof:placetype":"venue"
},
  "geometry": {"coordinates":[-3.40239,50.673195],"type":"Point"}
}