{
  "type": "Feature",
  "properties": {
    "iso:country":"GB",
    "sg:address":"Cheltenham Road",
    "sg:city":"Bristol",
    "sg:classifiers":[
        {
            "category":"Education",
            "subcategory":"School",
            "type":"Public Place"
        }
    ],
    "sg:postcode":"BS6 5RD",
    "sg:province":"City of Bristol",
    "sg:tags":[
        "independent",
        "preparatory"
    ],
    "wof:name":"Colston's Girls School",
    "wof:placetype":"venue"
},
  "geometry": {"coordinates":[-2.593334,51.469372],"type":"Point"}
}