{
  "type": "Feature",
  "properties": {
    "addr:full":"310 Shirley Road, Shirley Southampton Hampshire SO15 3HL",
    "addr:housenumber":"310",
    "addr:postcode":"so15 3hl",
    "addr:street":"Shirley Road",
    "iso:country":"GB",
    "sg:address":"310 Shirley Road, Shirley",
    "sg:city":"Southampton",
    "sg:classifiers":[
        {
            "category":"Real Estate",
            "subcategory":"Real Estate Agent",
            "type":"Services"
        }
    ],
    "sg:postcode":"SO15 3HL",
    "sg:province":"Hampshire",
    "wof:name":"N Oglesby",
    "wof:placetype":"venue"
},
  "geometry": {"coordinates":[-1.426935,50.917034],"type":"Point"}
}