{
  "type": "Feature",
  "properties": {
    "iso:country":"GB",
    "sg:address":"36 Romney Av",
    "sg:city":"Bristol",
    "sg:classifiers":[
        {
            "category":"Building & Trades",
            "subcategory":"Construction",
            "type":"Services"
        }
    ],
    "sg:phone":"+44 117 935 4279",
    "sg:postcode":"BS7 9TN",
    "sg:province":"City of Bristol",
    "sg:tags":[
        "builder"
    ],
    "wof:name":"Robbins Scaffolding",
    "wof:placetype":"venue"
},
  "geometry": {"coordinates":[-2.5705990791,51.4826622009],"type":"Point"}
}