{
  "type": "Feature",
  "properties": {
    "iso:country":"GB",
    "sg:address":"Warriston Crescent",
    "sg:city":"Edinburgh",
    "sg:classifiers":[
        {
            "category":"Arena",
            "subcategory":"Sports Club",
            "type":"Entertainment"
        }
    ],
    "sg:phone":"+44 131 556 5575",
    "sg:postcode":"EH3 5LA",
    "sg:province":"City of Edinburgh",
    "wof:name":"Northern Bowling Club",
    "wof:placetype":"venue"
},
  "geometry": {"coordinates":[-3.199942112,55.9642906189],"type":"Point"}
}