{
  "type": "Feature",
  "properties": {
    "iso:country":"GB",
    "sg:address":"24 Cobden Pl",
    "sg:city":"Canterbury",
    "sg:classifiers":[
        {
            "category":"Autos & Motor Vehicles",
            "subcategory":"Automobile Sales",
            "type":"Retail Goods"
        }
    ],
    "sg:postcode":"CT1 2DU",
    "sg:province":"Kent",
    "sg:tags":[
        "car"
    ],
    "wof:name":"Rogers,M,",
    "wof:placetype":"venue"
},
  "geometry": {"coordinates":[1.0823869705,51.2818069458],"type":"Point"}
}