{
  "type": "Feature",
  "properties": {
    "addr:full":"The Old Village Cobblers Shop, Warbrook Lane, Eversley Hook Berkshire RG27 0QH",
    "addr:postcode":"rg27 0qh",
    "addr:street":"Warbrook Lane",
    "iso:country":"GB",
    "sg:address":"The Old Village Cobblers Shop, Warbrook Lane, Eversley",
    "sg:city":"Hook",
    "sg:classifiers":[
        {
            "category":"Wholesale",
            "subcategory":"Machinery & Supplies",
            "type":"Manufacturing & Wholesale Goods"
        }
    ],
    "sg:postcode":"RG27 0QH",
    "sg:province":"Berkshire",
    "sg:tags":[
        "control",
        "instrument",
        "industrial",
        "-"
    ],
    "wof:name":"Probes Plus Ltd.",
    "wof:placetype":"venue"
},
  "geometry": {"coordinates":[-0.888039,51.351688],"type":"Point"}
}