{
  "type": "Feature",
  "properties": {
    "iso:country":"GB",
    "sg:address":"New Road, Alton",
    "sg:city":"Stoke-on-trent",
    "sg:classifiers":[
        {
            "category":"Bars & Pubs",
            "type":"Food & Drink"
        }
    ],
    "sg:phone":"+44 1538 702218",
    "sg:postcode":"ST10 4AF",
    "sg:province":"Staffordshire",
    "sg:tags":[
        "pubs",
        "inn"
    ],
    "wof:name":"The Lord Shrewsbury",
    "wof:placetype":"venue"
},
  "geometry": {"coordinates":[-1.894116,52.978699],"type":"Point"}
}