{
  "type": "Feature",
  "properties": {
    "iso:country":"GB",
    "sg:address":"Unit 5 Leighcliffe Bldgs, Maple Ave",
    "sg:city":"Leigh-on-sea",
    "sg:classifiers":[
        {
            "category":"Professional",
            "subcategory":"Printing & Photocopies",
            "type":"Services"
        }
    ],
    "sg:postcode":"SS9 1PR",
    "sg:province":"Essex",
    "sg:tags":[
        "printer"
    ],
    "wof:name":"Booth,Alan,",
    "wof:placetype":"venue"
},
  "geometry": {"coordinates":[0.6509950161,51.5484809875],"type":"Point"}
}