{
  "type": "Feature",
  "properties": {
    "addr:full":"259 Whitechapel Rd London Greater London E1 1DB",
    "addr:housenumber":"259",
    "addr:postcode":"e1 1db",
    "addr:street":"Whitechapel Rd",
    "iso:country":"GB",
    "sg:address":"259 Whitechapel Rd",
    "sg:city":"London",
    "sg:classifiers":[
        {
            "category":"Travel",
            "subcategory":"Travel Agent",
            "type":"Entertainment"
        }
    ],
    "sg:postcode":"E1 1DB",
    "sg:province":"Greater London",
    "wof:name":"Tamim Travels",
    "wof:placetype":"venue"
},
  "geometry": {"coordinates":[-0.060321,51.51915],"type":"Point"}
}