{
  "type": "Feature",
  "properties": {
    "addr:full":"74 Fairfield Road Buxton Derbyshire SK17 7DR",
    "addr:housenumber":"74",
    "addr:postcode":"sk17 7dr",
    "addr:street":"Fairfield Road",
    "iso:country":"GB",
    "sg:address":"74 Fairfield Road",
    "sg:city":"Buxton",
    "sg:classifiers":[
        {
            "category":"Professional",
            "subcategory":"Advertising",
            "type":"Services"
        }
    ],
    "sg:phone":"+44 1298 73270",
    "sg:postcode":"SK17 7DR",
    "sg:province":"Derbyshire",
    "sg:tags":[
        "agency"
    ],
    "wof:name":"The Marketing Practice",
    "wof:placetype":"venue"
},
  "geometry": {"coordinates":[-1.9039490223,53.2626647949],"type":"Point"}
}