{
  "type": "Feature",
  "properties": {
    "iso:country":"GB",
    "sg:address":"7 Marklay Drive",
    "sg:city":"Chelmsford",
    "sg:classifiers":[
        {
            "category":"Professional",
            "subcategory":"Engineering",
            "type":"Services"
        }
    ],
    "sg:postcode":"CM3 5NP",
    "sg:province":"Essex",
    "sg:tags":[
        "contractor",
        "electrical",
        "engineer"
    ],
    "wof:name":"Delco Electrical Contractors",
    "wof:placetype":"venue"
},
  "geometry": {"coordinates":[0.606645,51.646858],"type":"Point"}
}