{
  "type": "Feature",
  "properties": {
    "iso:country":"GB",
    "sg:address":"19 Sterling Way",
    "sg:city":"Nuneaton",
    "sg:classifiers":[
        {
            "category":"Building & Trades",
            "subcategory":"Construction",
            "type":"Services"
        }
    ],
    "sg:postcode":"CV11 4YA",
    "sg:province":"Leicestershire",
    "sg:tags":[
        "builder"
    ],
    "wof:name":"K L B Contracts",
    "wof:placetype":"venue"
},
  "geometry": {"coordinates":[-1.450414,52.503136],"type":"Point"}
}