{
  "type": "Feature",
  "properties": {
    "addr:full":"156 Cheltenham Road Bristol City of Bristol BS6 5RL",
    "addr:housenumber":"156",
    "addr:postcode":"bs6 5rl",
    "addr:street":"Cheltenham Road",
    "iso:country":"GB",
    "sg:address":"156 Cheltenham Road",
    "sg:city":"Bristol",
    "sg:classifiers":[
        {
            "category":"Autos & Motor Vehicles",
            "subcategory":"Automobile Sales",
            "type":"Retail Goods"
        }
    ],
    "sg:postcode":"BS6 5RL",
    "sg:province":"City of Bristol",
    "sg:tags":[
        "car"
    ],
    "wof:name":"Dovercourt Bristol",
    "wof:placetype":"venue"
},
  "geometry": {"coordinates":[-2.59012,51.465309],"type":"Point"}
}