{
  "type": "Feature",
  "properties": {
    "addr:full":"Flat 7 Mountford House, Glover Street West Bromwich West Midlands B70 6DS",
    "addr:postcode":"b70 6ds",
    "addr:street":"Glover Street",
    "iso:country":"GB",
    "sg:address":"Flat 7 Mountford House, Glover Street",
    "sg:city":"West Bromwich",
    "sg:classifiers":[
        {
            "category":"Building & Trades",
            "subcategory":"Plumbing",
            "type":"Services"
        }
    ],
    "sg:phone":"+44 121 525 6734",
    "sg:postcode":"B70 6DS",
    "sg:province":"West Midlands",
    "sg:tags":[
        "plumber",
        "heating"
    ],
    "wof:name":"Anytime Plumbing Maintenance",
    "wof:placetype":"venue"
},
  "geometry": {"coordinates":[-1.9902240038,52.5186233521],"type":"Point"}
}