{
  "type": "Feature",
  "properties": {
    "iso:country":"GB",
    "sg:address":"82 Rosemary Road",
    "sg:city":"Clacton-on-sea",
    "sg:classifiers":[
        {
            "category":"Travel",
            "subcategory":"Travel Agent",
            "type":"Entertainment"
        }
    ],
    "sg:phone":"+44 1255 224228",
    "sg:postcode":"CO15 1TG",
    "sg:province":"Essex",
    "wof:name":"C W Travel U K Ltd.",
    "wof:placetype":"venue"
},
  "geometry": {"coordinates":[1.151178956,51.7901535034],"type":"Point"}
}