{
  "type": "Feature",
  "properties": {
    "addr:full":"5 Beech Croft Road, Summertown Oxford Oxfordshire OX2 7AY",
    "addr:housenumber":"5",
    "addr:postcode":"ox2 7ay",
    "addr:street":"Beech Croft Road",
    "iso:country":"GB",
    "sg:address":"5 Beech Croft Road, Summertown",
    "sg:city":"Oxford",
    "sg:classifiers":[
        {
            "category":"Professional",
            "subcategory":"Accounting & Tax Preparation",
            "type":"Services"
        }
    ],
    "sg:postcode":"OX2 7AY",
    "sg:province":"Oxfordshire",
    "sg:tags":[
        "accountant"
    ],
    "wof:name":"Unitemp Accounting Ltd",
    "wof:placetype":"venue"
},
  "geometry": {"coordinates":[-1.2644710541,51.7744407654],"type":"Point"}
}