{
  "type": "Feature",
  "properties": {
    "addr:full":"103 Rousay Drive, Summer Hill Aberdeen Aberdeen City AB15 6LT",
    "addr:housenumber":"103",
    "addr:postcode":"ab15 6lt",
    "addr:street":"Rousay Drive",
    "iso:country":"GB",
    "sg:address":"103 Rousay Drive, Summer Hill",
    "sg:city":"Aberdeen",
    "sg:classifiers":[
        {
            "category":"Shopping",
            "subcategory":"Florist",
            "type":"Retail Goods"
        }
    ],
    "sg:phone":"+44 1224 322434",
    "sg:postcode":"AB15 6LT",
    "sg:province":"Aberdeen City",
    "wof:name":"Everglade Garden Centre Ltd.",
    "wof:placetype":"venue"
},
  "geometry": {"coordinates":[-2.1721799374,57.1502304077],"type":"Point"}
}