{
  "type": "Feature",
  "properties": {
    "iso:country":"GB",
    "sg:address":"35-37 Gateside Street",
    "sg:city":"Hamilton",
    "sg:classifiers":[
        {
            "category":"Bars & Pubs",
            "type":"Food & Drink"
        }
    ],
    "sg:phone":"+44 1698 286889",
    "sg:postcode":"ML3 7JG",
    "sg:province":"South Lanarkshire",
    "sg:tags":[
        "pubs",
        "inn"
    ],
    "wof:name":"The Woodside Bar",
    "wof:placetype":"venue"
},
  "geometry": {"coordinates":[-4.037957,55.771439],"type":"Point"}
}