{
  "type": "Feature",
  "properties": {
    "addr:full":"Unit G, Centure House, Bone Lane Newbury Berkshire RG14 5SH",
    "addr:housenumber":"unit g",
    "addr:postcode":"rg14 5sh",
    "addr:street":"Bone Lane",
    "iso:country":"GB",
    "sg:address":"Unit G, Centure House, Bone Lane",
    "sg:city":"Newbury",
    "sg:classifiers":[
        {
            "category":"Shopping",
            "subcategory":"Optical Goods",
            "type":"Retail Goods"
        }
    ],
    "sg:phone":"+44 1635 277277",
    "sg:postcode":"RG14 5SH",
    "sg:province":"Berkshire",
    "sg:tags":[
        "medical"
    ],
    "wof:name":"Marcolin (U K) Ltd.",
    "wof:placetype":"venue"
},
  "geometry": {"coordinates":[-1.3098189831,51.4016494751],"type":"Point"}
}