{
  "type": "Feature",
  "properties": {
    "iso:country":"GB",
    "sg:address":"Archwood Farm, Johnstonebridge",
    "sg:city":"Lockerbie",
    "sg:classifiers":[
        {
            "category":"Farming",
            "subcategory":"Livestock Farm",
            "type":"Manufacturing & Wholesale Goods"
        },
        {
            "category":"Farming",
            "subcategory":"Farm",
            "type":"Manufacturing & Wholesale Goods"
        }
    ],
    "sg:postcode":"DG11 1EP",
    "sg:province":"Dumfries and Galloway",
    "sg:tags":[
        "breeder",
        "mixed",
        "crop"
    ],
    "wof:name":"R Wilson",
    "wof:placetype":"venue"
},
  "geometry": {"coordinates":[-3.415924,55.218204],"type":"Point"}
}