{
  "type": "Feature",
  "properties": {
    "iso:country":"GB",
    "sg:address":"Unit 2 Times Square",
    "sg:city":"Sutton",
    "sg:classifiers":[
        {
            "category":"Shopping",
            "subcategory":"Jewelry",
            "type":"Retail Goods"
        },
        {
            "category":"Shopping",
            "subcategory":"Comic Books",
            "type":"Retail Goods"
        }
    ],
    "sg:phone":"+44 20 8642 1598",
    "sg:postcode":"SM1 1LF",
    "sg:province":"Surrey",
    "sg:tags":[
        "jeweller",
        "sale",
        "jewellery"
    ],
    "wof:name":"Ernest Jones Ltd",
    "wof:placetype":"venue"
},
  "geometry": {"coordinates":[-0.192759,51.362785],"type":"Point"}
}