{
  "type": "Feature",
  "properties": {
    "addr:full":"118 Lower Lichfield Street Willenhall West Midlands WV13 1PU",
    "addr:housenumber":"118",
    "addr:postcode":"wv13 1pu",
    "addr:street":"Lower Lichfield Street",
    "iso:country":"GB",
    "sg:address":"118 Lower Lichfield Street",
    "sg:city":"Willenhall",
    "sg:classifiers":[
        {
            "category":"Home & Garden",
            "subcategory":"Home Furnishings",
            "type":"Retail Goods"
        }
    ],
    "sg:phone":"+44 1902 607114",
    "sg:postcode":"WV13 1PU",
    "sg:province":"West Midlands",
    "sg:tags":[
        "awning",
        "canopy",
        "blinds"
    ],
    "wof:name":"R B Blinds",
    "wof:placetype":"venue"
},
  "geometry": {"coordinates":[-2.052955,52.584667],"type":"Point"}
}