{
  "type": "Feature",
  "properties": {
    "addr:full":"32 Hanover Street Liverpool Merseyside L1 4LN",
    "addr:housenumber":"32",
    "addr:postcode":"l1 4ln",
    "addr:street":"Hanover Street",
    "iso:country":"GB",
    "sg:address":"32 Hanover Street",
    "sg:city":"Liverpool",
    "sg:classifiers":[
        {
            "category":"Building & Trades",
            "subcategory":"Landscaping Services",
            "type":"Services"
        }
    ],
    "sg:phone":"+44 151 709 4759",
    "sg:postcode":"L1 4LN",
    "sg:province":"Merseyside",
    "sg:tags":[
        "contractor"
    ],
    "wof:name":"Donaldson Edwards Partnership Ltd.",
    "wof:placetype":"venue"
},
  "geometry": {"coordinates":[-2.982222,53.404198],"type":"Point"}
}