{
  "type": "Feature",
  "properties": {
    "addr:full":"21 Cannon Street Louth Lincolnshire LN11 9NL",
    "addr:housenumber":"21",
    "addr:postcode":"ln11 9nl",
    "addr:street":"Cannon Street Louth",
    "iso:country":"GB",
    "sg:address":"21 Cannon Street",
    "sg:city":"Louth",
    "sg:classifiers":[
        {
            "category":"Manufacturing",
            "subcategory":"Wood Products",
            "type":"Manufacturing & Wholesale Goods"
        },
        {
            "category":"Building & Trades",
            "subcategory":"Construction",
            "type":"Services"
        }
    ],
    "sg:phone":"+44 1507 600006",
    "sg:postcode":"LN11 9NL",
    "sg:province":"Lincolnshire",
    "sg:tags":[
        "installers",
        "planner",
        "maker",
        "kitchen",
        "cabinet"
    ],
    "wof:name":"Studio 21 Interiors",
    "wof:placetype":"venue"
},
  "geometry": {"coordinates":[-0.005428,53.367432],"type":"Point"}
}