{
  "type": "Feature",
  "properties": {
    "addr:full":"59 Briarfield Avenue Widnes Cheshire WA8 8JZ",
    "addr:housenumber":"59",
    "addr:postcode":"wa8 8jz",
    "addr:street":"Briarfield Avenue",
    "iso:country":"GB",
    "sg:address":"59 Briarfield Avenue",
    "sg:city":"Widnes",
    "sg:classifiers":[
        {
            "category":"Freight",
            "type":"Transportation"
        }
    ],
    "sg:postcode":"WA8 8JZ",
    "sg:province":"Cheshire",
    "sg:tags":[
        "haulage",
        "road"
    ],
    "wof:name":"C & M Transport",
    "wof:placetype":"venue"
},
  "geometry": {"coordinates":[-2.7804710865,53.3690757751],"type":"Point"}
}