{
  "type": "Feature",
  "properties": {
    "addr:full":"76 Earl St Northampton Northamptonshire NN1 3AX",
    "addr:housenumber":"76",
    "addr:postcode":"nn1 3ax",
    "addr:street":"Earl St",
    "iso:country":"GB",
    "sg:address":"76 Earl St",
    "sg:city":"Northampton",
    "sg:classifiers":[
        {
            "category":"Restaurant",
            "type":"Food & Drink"
        }
    ],
    "sg:postcode":"NN1 3AX",
    "sg:province":"Northamptonshire",
    "sg:tags":[
        "indian"
    ],
    "wof:name":"Balti King Restaurant",
    "wof:placetype":"venue"
},
  "geometry": {"coordinates":[-0.891312,52.242481],"type":"Point"}
}