{
  "type": "Feature",
  "properties": {
    "iso:country":"GB",
    "sg:address":"408 Farnham Road",
    "sg:city":"Slough",
    "sg:classifiers":[
        {
            "category":"Shopping",
            "subcategory":"Crafts & Fabrics",
            "type":"Retail Goods"
        }
    ],
    "sg:postcode":"SL2 1JA",
    "sg:province":"Berkshire",
    "sg:tags":[
        "shop"
    ],
    "wof:name":"A Nisar",
    "wof:placetype":"venue"
},
  "geometry": {"coordinates":[-0.616738975,51.5292053223],"type":"Point"}
}