{
  "type": "Feature",
  "properties": {
    "iso:country":"GB",
    "sg:address":"198 Lavernock Rd",
    "sg:city":"Penarth",
    "sg:classifiers":[
        {
            "category":"Home & Garden",
            "subcategory":"Kitchen Supply",
            "type":"Retail Goods"
        }
    ],
    "sg:phone":"+44 29 2070 5335",
    "sg:postcode":"CF64 5UP",
    "sg:province":"The Vale of Glamorgan",
    "sg:tags":[
        "equipment",
        "catering"
    ],
    "wof:name":"ETC",
    "wof:placetype":"venue"
},
  "geometry": {"coordinates":[-3.1797280312,51.418056488],"type":"Point"}
}