{
  "type": "Feature",
  "properties": {
    "iso:country":"GB",
    "sg:address":"Second Floor, 69 Harley St",
    "sg:city":"London",
    "sg:classifiers":[
        {
            "category":"Banks & Credit Unions",
            "subcategory":"Financial Services",
            "type":"Services"
        }
    ],
    "sg:phone":"+44 20 7487 5582",
    "sg:postcode":"W1G 8QZ",
    "sg:province":"Greater London",
    "sg:tags":[
        "consultant"
    ],
    "wof:name":"N W Management Services Ltd",
    "wof:placetype":"venue"
},
  "geometry": {"coordinates":[-0.14743,51.519711],"type":"Point"}
}