{
  "type": "Feature",
  "properties": {
    "addr:full":"63 London Road St Albans Hertfordshire AL1 1LJ",
    "addr:housenumber":"63",
    "addr:postcode":"al1 1lj",
    "addr:street":"London Road",
    "iso:country":"GB",
    "sg:address":"63 London Road",
    "sg:city":"St Albans",
    "sg:classifiers":[
        {
            "category":"Professional",
            "subcategory":"Lawyer & Legal Services",
            "type":"Services"
        }
    ],
    "sg:phone":"+44 1707 257400",
    "sg:postcode":"AL1 1LJ",
    "sg:province":"Hertfordshire",
    "sg:tags":[
        "advice",
        "counselling"
    ],
    "wof:name":"Hertfordshire Mediation Service",
    "wof:placetype":"venue"
},
  "geometry": {"coordinates":[-0.3342190087,51.749256134],"type":"Point"}
}