{
  "type": "Feature",
  "properties": {
    "iso:country":"GB",
    "sg:address":"32 Southridge",
    "sg:city":"Billericay",
    "sg:classifiers":[
        {
            "category":"Professional",
            "subcategory":"Business Services",
            "type":"Services"
        }
    ],
    "sg:postcode":"CM11 2ER",
    "sg:province":"Essex",
    "sg:tags":[
        "distribution"
    ],
    "wof:name":"Broadway Products",
    "wof:placetype":"venue"
},
  "geometry": {"coordinates":[0.4732249975,51.6032409668],"type":"Point"}
}