{
  "type": "Feature",
  "properties": {
    "iso:country":"GB",
    "sg:address":"41 Ravensbourne Drive, Woodley",
    "sg:city":"Reading",
    "sg:classifiers":[
        {
            "category":"Professional",
            "subcategory":"Accounting & Tax Preparation",
            "type":"Services"
        }
    ],
    "sg:phone":"+44 118 969 9025",
    "sg:postcode":"RG5 4LH",
    "sg:province":"Berkshire",
    "sg:tags":[
        "accountant"
    ],
    "wof:name":"M B Bookkeeping Services",
    "wof:placetype":"venue"
},
  "geometry": {"coordinates":[-0.902246,51.459045],"type":"Point"}
}