{
  "type": "Feature",
  "properties": {
    "iso:country":"GB",
    "sg:address":"Foxbar Dental Practice, 4 Lochaline Avenue",
    "sg:city":"Paisley",
    "sg:classifiers":[
        {
            "category":"Health Services",
            "subcategory":"Dentist",
            "type":"Services"
        }
    ],
    "sg:phone":"+44 1505 813818",
    "sg:postcode":"PA2 9ET",
    "sg:province":"East Renfrewshire",
    "wof:name":"Peter H. Feechan B.D.S",
    "wof:placetype":"venue"
},
  "geometry": {"coordinates":[-4.45318,55.83316],"type":"Point"}
}