{
  "type": "Feature",
  "properties": {
    "iso:country":"GB",
    "sg:address":"34 Queen Street",
    "sg:city":"Neath",
    "sg:classifiers":[
        {
            "category":"Shopping",
            "subcategory":"Shoes",
            "type":"Retail Goods"
        }
    ],
    "sg:postcode":"SA11 1DL",
    "sg:province":"Neath Port Talbot",
    "wof:name":"Robs Heel Bar",
    "wof:placetype":"venue"
},
  "geometry": {"coordinates":[-3.804414,51.661766],"type":"Point"}
}