{
  "type": "Feature",
  "properties": {
    "addr:full":"43 Grand Avenue, Southbourne Bournemouth Dorset BH6 3SY",
    "addr:housenumber":"43",
    "addr:postcode":"bh6 3sy",
    "addr:street":"Grand Avenue",
    "iso:country":"GB",
    "sg:address":"43 Grand Avenue, Southbourne",
    "sg:city":"Bournemouth",
    "sg:classifiers":[
        {
            "category":"Travel",
            "subcategory":"Hotels & Motels",
            "type":"Entertainment"
        }
    ],
    "sg:phone":"+44 1202 425370",
    "sg:postcode":"BH6 3SY",
    "sg:province":"Dorset",
    "wof:name":"The Willowdene",
    "wof:placetype":"venue"
},
  "geometry": {"coordinates":[-1.8152250051,50.7235984802],"type":"Point"}
}