{
  "type": "Feature",
  "properties": {
    "addr:full":"31 Golds Nursery Business Park, Jenkins Drive, Elsenham Bishop's Stortford Essex CM22 6JX",
    "addr:housenumber":"31",
    "addr:postcode":"cm22 6jx",
    "addr:street":"Business Park Jenkins Drive;Bishop'S",
    "iso:country":"GB",
    "sg:address":"31 Golds Nursery Business Park, Jenkins Drive, Elsenham",
    "sg:city":"Bishop's Stortford",
    "sg:classifiers":[
        {
            "category":"Military Area",
            "subcategory":"Air Force Base",
            "type":"Public Place"
        }
    ],
    "sg:phone":"+44 1279 815754",
    "sg:postcode":"CM22 6JX",
    "sg:province":"Essex",
    "sg:tags":[
        "engine",
        "aircraft"
    ],
    "wof:name":"Spray Avia International Ltd",
    "wof:placetype":"venue"
},
  "geometry": {"coordinates":[0.2259799987,51.9212188721],"type":"Point"}
}