{
  "type": "Feature",
  "properties": {
    "iso:country":"GB",
    "sg:address":"5 Astoria Parade, Streatham High Rd",
    "sg:city":"Streatham",
    "sg:classifiers":[
        {
            "category":"Restaurant",
            "type":"Food & Drink"
        }
    ],
    "sg:phone":"+44 20 8769 2755",
    "sg:postcode":"SW16 1PR",
    "sg:province":"Greater London",
    "wof:name":"Astoria Restaurant",
    "wof:placetype":"venue"
},
  "geometry": {"coordinates":[-0.1274600029,51.436542511],"type":"Point"}
}