{
  "type": "Feature",
  "properties": {
    "addr:full":"Cobtree Hall, Mote Park, Willington St Maidstone Kent ME15 8EB",
    "addr:postcode":"me15 8eb",
    "addr:street":"Willington St",
    "iso:country":"GB",
    "sg:address":"Cobtree Hall, Mote Park, Willington St",
    "sg:city":"Maidstone",
    "sg:classifiers":[
        {
            "category":"Organizations",
            "subcategory":"Non-profit Organization",
            "type":"Services"
        }
    ],
    "sg:phone":"+44 1622 670464",
    "sg:postcode":"ME15 8EB",
    "sg:province":"Kent",
    "sg:tags":[
        "organisation",
        "voluntary",
        "charity"
    ],
    "wof:name":"Maidstone Society For Mentally Handicapped Children & Adults",
    "wof:placetype":"venue"
},
  "geometry": {"coordinates":[0.55444,51.25869],"type":"Point"}
}