{
  "type": "Feature",
  "properties": {
    "addr:full":"Marks Farm, The Broadway Dunmow Essex CM6 3BQ",
    "addr:postcode":"cm6 3bq",
    "addr:street":"The Broadway",
    "iso:country":"GB",
    "sg:address":"Marks Farm, The Broadway",
    "sg:city":"Dunmow",
    "sg:classifiers":[
        {
            "category":"Organizations",
            "subcategory":"Non-profit Organization",
            "type":"Services"
        }
    ],
    "sg:phone":"+44 1371 872102",
    "sg:postcode":"CM6 3BQ",
    "sg:province":"Essex",
    "sg:tags":[
        "organisation",
        "animal",
        "welfare"
    ],
    "wof:name":"Fenelon Moloney",
    "wof:placetype":"venue"
},
  "geometry": {"coordinates":[0.3787620068,51.889919281],"type":"Point"}
}