{
  "type": "Feature",
  "properties": {
    "addr:full":"Kwik Save Ivybridge Devon PL21 9PS",
    "addr:postcode":"pl21 9ps",
    "iso:country":"GB",
    "sg:address":"Kwik Save",
    "sg:city":"Ivybridge",
    "sg:classifiers":[
        {
            "category":"Food & Beverages",
            "subcategory":"Fruits & Vegetables",
            "type":"Retail Goods"
        }
    ],
    "sg:postcode":"PL21 9PS",
    "sg:province":"Devon",
    "sg:tags":[
        "greengrocer"
    ],
    "wof:name":"Pip Rind & Core Ltd",
    "wof:placetype":"venue"
},
  "geometry": {"coordinates":[-3.9290390015,50.3872642517],"type":"Point"}
}