{
  "type": "Feature",
  "properties": {
    "addr:full":"Ashville Road Gloucester Gloucestershire GL2 5EU",
    "addr:postcode":"gl2 5eu",
    "addr:street":"Ashville Road",
    "iso:country":"GB",
    "sg:address":"Ashville Road",
    "sg:city":"Gloucester",
    "sg:classifiers":[
        {
            "category":"Manufacturing",
            "subcategory":"Glass & Minerals",
            "type":"Manufacturing & Wholesale Goods"
        }
    ],
    "sg:phone":"+44 1452 422866",
    "sg:postcode":"GL2 5EU",
    "sg:province":"Gloucestershire",
    "sg:tags":[
        "fibre",
        "material"
    ],
    "wof:name":"Freeman Distribution",
    "wof:placetype":"venue"
},
  "geometry": {"coordinates":[-2.262289,51.845493],"type":"Point"}
}