{
  "type": "Feature",
  "properties": {
    "addr:full":"Lemon Mills, Bradley Lane Newton Abbot Devon TQ12 1TB",
    "addr:postcode":"tq12 1tb",
    "addr:street":"Lemon;Bradley Lane",
    "iso:country":"GB",
    "sg:address":"Lemon Mills, Bradley Lane",
    "sg:city":"Newton Abbot",
    "sg:classifiers":[
        {
            "category":"Manufacturing",
            "subcategory":"Glass & Minerals",
            "type":"Manufacturing & Wholesale Goods"
        }
    ],
    "sg:postcode":"TQ12 1TB",
    "sg:province":"Devon",
    "sg:tags":[
        "fibre",
        "moulding"
    ],
    "wof:name":"Jacqueline Mayler",
    "wof:placetype":"venue"
},
  "geometry": {"coordinates":[-3.6076591015,50.5288696289],"type":"Point"}
}