{
  "type": "Feature",
  "properties": {
    "addr:full":"Domestic Street Leeds West Yorkshire LS11 9PL",
    "addr:postcode":"ls11 9pl",
    "addr:street":"Domestic Street",
    "iso:country":"GB",
    "sg:address":"Domestic Street",
    "sg:city":"Leeds",
    "sg:classifiers":[
        {
            "category":"Retail",
            "subcategory":"Auto Rental",
            "type":"Services"
        }
    ],
    "sg:phone":"+44 113 244 1531",
    "sg:postcode":"LS11 9PL",
    "sg:province":"West Yorkshire",
    "sg:tags":[
        "car",
        "vehicle"
    ],
    "sg:website":"http://www.salfordvanhire.com",
    "wof:name":"Salford Car & Van Hire",
    "wof:placetype":"venue"
},
  "geometry": {"coordinates":[-1.5613540411,53.7865180969],"type":"Point"}
}