{
  "type": "Feature",
  "properties": {
    "iso:country":"GB",
    "sg:address":"21 Prospect Rd, Long Ditton",
    "sg:city":"Surbiton",
    "sg:classifiers":[
        {
            "category":"Retail",
            "subcategory":"Storage",
            "type":"Services"
        }
    ],
    "sg:postcode":"KT6 5PY",
    "sg:province":"Surrey",
    "sg:tags":[
        "household",
        "removal"
    ],
    "wof:name":"Jayce Moves",
    "wof:placetype":"venue"
},
  "geometry": {"coordinates":[-0.318017,51.390739],"type":"Point"}
}