{
  "type": "Feature",
  "properties": {
    "addr:full":"5 Blackheath Hill London Greater London SE10 8PB",
    "addr:housenumber":"5",
    "addr:postcode":"se10 8pb",
    "addr:street":"Blackheath Hill",
    "iso:country":"GB",
    "sg:address":"5 Blackheath Hill",
    "sg:city":"London",
    "sg:classifiers":[
        {
            "category":"Personal",
            "subcategory":"Beauty Salon",
            "type":"Services"
        },
        {
            "category":"Personal",
            "subcategory":"Barber",
            "type":"Services"
        }
    ],
    "sg:phone":"+44 20 8692 1005",
    "sg:postcode":"SE10 8PB",
    "sg:province":"Greater London",
    "sg:tags":[
        "unisex",
        "hairdresser"
    ],
    "wof:name":"Creed Hairdressing",
    "wof:placetype":"venue"
},
  "geometry": {"coordinates":[-0.0147540001,51.4731712341],"type":"Point"}
}