{
  "type": "Feature",
  "properties": {
    "addr:full":"29 Balaam St Plaistow Greater London E13 8EB",
    "addr:housenumber":"29",
    "addr:postcode":"e13 8eb",
    "addr:street":"Balaam St",
    "iso:country":"GB",
    "sg:address":"29 Balaam St",
    "sg:city":"Plaistow",
    "sg:classifiers":[
        {
            "category":"Fast Food",
            "type":"Food & Drink"
        }
    ],
    "sg:phone":"+44 20 7511 8588",
    "sg:postcode":"E13 8EB",
    "sg:province":"Greater London",
    "sg:tags":[
        "away",
        "take"
    ],
    "wof:name":"Purbash",
    "wof:placetype":"venue"
},
  "geometry": {"coordinates":[0.022382,51.523167],"type":"Point"}
}