{
  "type": "Feature",
  "properties": {
    "iso:country":"GB",
    "sg:address":"82 Raddlebarn Road, Selly Oak",
    "sg:city":"Birmingham",
    "sg:classifiers":[
        {
            "category":"Real Estate",
            "subcategory":"Real Estate Agent",
            "type":"Services"
        }
    ],
    "sg:postcode":"B29 6HH",
    "sg:province":"West Midlands",
    "wof:name":"Oakwood Property Services",
    "wof:placetype":"venue"
},
  "geometry": {"coordinates":[-1.929369,52.436878],"type":"Point"}
}