{
  "type": "Feature",
  "properties": {
    "iso:country":"GB",
    "sg:address":"Wood Lane",
    "sg:city":"Bradford",
    "sg:classifiers":[
        {
            "category":"Government",
            "subcategory":"Office",
            "type":"Public Place"
        }
    ],
    "sg:phone":"+44 1274 633109",
    "sg:postcode":"BD2 1JX",
    "sg:province":"West Yorkshire",
    "sg:tags":[
        "education",
        "agency",
        "authority"
    ],
    "wof:name":"Greenwood Youth & Community Centre",
    "wof:placetype":"venue"
},
  "geometry": {"coordinates":[-1.745034,53.822266],"type":"Point"}
}