{
  "type": "Feature",
  "properties": {
    "addr:full":"40 Osborn Street London Greater London E1 6TD",
    "addr:housenumber":"40",
    "addr:postcode":"e1 6td",
    "addr:street":"Osborn Street",
    "iso:country":"GB",
    "sg:address":"40 Osborn Street",
    "sg:city":"London",
    "sg:classifiers":[
        {
            "category":"Cafe",
            "type":"Food & Drink"
        }
    ],
    "sg:phone":"+44 20 7247 6413",
    "sg:postcode":"E1 6TD",
    "sg:province":"Greater London",
    "sg:tags":[
        "tea",
        "snack",
        "bar",
        "room"
    ],
    "wof:name":"S Woznicki",
    "wof:placetype":"venue"
},
  "geometry": {"coordinates":[-0.070178,51.517162],"type":"Point"}
}