{
  "type": "Feature",
  "properties": {
    "iso:country":"GB",
    "sg:address":"Cross Street Retail Park, Long Eaton",
    "sg:city":"Nottingham",
    "sg:classifiers":[
        {
            "category":"Manufacturing",
            "subcategory":"Textiles",
            "type":"Manufacturing & Wholesale Goods"
        }
    ],
    "sg:phone":"+44 115 972 4444",
    "sg:postcode":"NG10 1HD",
    "sg:province":"Derbyshire",
    "sg:tags":[
        "made-up"
    ],
    "wof:name":"Sleepers Bed Centre",
    "wof:placetype":"venue"
},
  "geometry": {"coordinates":[-1.267479,52.896965],"type":"Point"}
}