{
  "type": "Feature",
  "properties": {
    "addr:full":"St Ives Road, Somersham Huntingdon Bedfordshire PE28 3ET",
    "addr:postcode":"pe28 3et",
    "addr:street":"St Ives Road",
    "iso:country":"GB",
    "sg:address":"St Ives Road, Somersham",
    "sg:city":"Huntingdon",
    "sg:classifiers":[
        {
            "category":"Bars & Pubs",
            "type":"Food & Drink"
        },
        {
            "category":"Community Center",
            "subcategory":"Social",
            "type":"Public Place"
        }
    ],
    "sg:phone":"+44 1487 840328",
    "sg:postcode":"PE28 3ET",
    "sg:province":"Bedfordshire",
    "sg:tags":[
        "pubs",
        "house",
        "inn",
        "activity"
    ],
    "wof:name":"The Windmill",
    "wof:placetype":"venue"
},
  "geometry": {"coordinates":[-0.0939209983,52.3759078979],"type":"Point"}
}