{
  "type": "Feature",
  "properties": {
    "iso:country":"GB",
    "sg:address":"5b Baillie Street",
    "sg:city":"Rochdale",
    "sg:classifiers":[
        {
            "category":"Shopping",
            "subcategory":"Thrift Store",
            "type":"Retail Goods"
        }
    ],
    "sg:postcode":"OL16 1JJ",
    "sg:province":"Lancashire",
    "sg:tags":[
        "shop",
        "charity"
    ],
    "wof:name":"Oxfam",
    "wof:placetype":"venue"
},
  "geometry": {"coordinates":[-2.1560790539,53.6179199219],"type":"Point"}
}