{
  "type": "Feature",
  "properties": {
    "addr:full":"451 Green Lanes London Greater London N13 4BS",
    "addr:housenumber":"451",
    "addr:postcode":"n13 4bs",
    "addr:street":"Green Lanes",
    "iso:country":"GB",
    "sg:address":"451 Green Lanes",
    "sg:city":"London",
    "sg:classifiers":[
        {
            "category":"Health Services",
            "subcategory":"Nursing And Care Facility",
            "type":"Services"
        },
        {
            "category":"Social Services",
            "subcategory":"Retirement Home",
            "type":"Services"
        }
    ],
    "sg:phone":"+44 20 8447 8298",
    "sg:postcode":"N13 4BS",
    "sg:province":"Greater London",
    "sg:tags":[
        "residential"
    ],
    "wof:name":"The Worshipful Co. of Skinners",
    "wof:placetype":"venue"
},
  "geometry": {"coordinates":[-0.1056509987,51.6219711304],"type":"Point"}
}