{
  "type": "Feature",
  "properties": {
    "addr:full":"Forest Ride, Back Lane, Bucks Horn Oak Farnham Hampshire GU10 4LW",
    "addr:housenumber":"farnham",
    "addr:postcode":"gu10 4lw",
    "addr:street":"Back Lane;Horn Oak",
    "iso:country":"GB",
    "sg:address":"Forest Ride, Back Lane, Bucks Horn Oak",
    "sg:city":"Farnham",
    "sg:classifiers":[
        {
            "category":"Professional",
            "subcategory":"Management & Consulting",
            "type":"Services"
        }
    ],
    "sg:postcode":"GU10 4LW",
    "sg:province":"Hampshire",
    "sg:tags":[
        "consultant",
        "business"
    ],
    "wof:name":"Farm Cost Services",
    "wof:placetype":"venue"
},
  "geometry": {"coordinates":[-0.828749001,51.1842308044],"type":"Point"}
}