{
  "type": "Feature",
  "properties": {
    "addr:full":"27a St. Johns Rd Wembley Greater London HA9 7HU",
    "addr:housenumber":"27a",
    "addr:postcode":"ha9 7hu",
    "addr:street":"St. Johns Rd",
    "iso:country":"GB",
    "sg:address":"27a St. Johns Rd",
    "sg:city":"Wembley",
    "sg:classifiers":[
        {
            "category":"Banks & Credit Unions",
            "subcategory":"Financial Services",
            "type":"Services"
        }
    ],
    "sg:phone":"+44 20 8795 2004",
    "sg:postcode":"HA9 7HU",
    "sg:province":"Greater London",
    "sg:tags":[
        "agent",
        "tied"
    ],
    "wof:name":"Hari Financial Services",
    "wof:placetype":"venue"
},
  "geometry": {"coordinates":[-0.2966029942,51.553527832],"type":"Point"}
}