{
  "type": "Feature",
  "properties": {
    "iso:country":"GB",
    "sg:address":"Green Acres Farm, Duns Tew Road, Middle Barton",
    "sg:city":"Oxford",
    "sg:classifiers":[
        {
            "category":"Manufacturing",
            "subcategory":"Metals",
            "type":"Manufacturing & Wholesale Goods"
        }
    ],
    "sg:phone":"+44 1869 347014",
    "sg:postcode":"OX7 7DG",
    "sg:province":"Gloucestershire",
    "sg:tags":[
        "steel",
        "fabricator",
        "erectors"
    ],
    "wof:name":"T W Fabrications",
    "wof:placetype":"venue"
},
  "geometry": {"coordinates":[-1.3437999487,51.9384498596],"type":"Point"}
}