{
  "type": "Feature",
  "properties": {
    "addr:full":"48 Brunswick St Cardiff Cardiff CF5 1LJ",
    "addr:housenumber":"48",
    "addr:postcode":"cf5 1lj",
    "addr:street":"Brunswick St",
    "iso:country":"GB",
    "sg:address":"48 Brunswick St",
    "sg:city":"Cardiff",
    "sg:classifiers":[
        {
            "category":"Home & Garden",
            "subcategory":"Carpets & Floor Coverings",
            "type":"Retail Goods"
        }
    ],
    "sg:phone":"+44 29 2025 7639",
    "sg:postcode":"CF5 1LJ",
    "sg:province":"Cardiff",
    "sg:tags":[
        "wall",
        "tie",
        "replacement"
    ],
    "wof:name":"B & S General Builders",
    "wof:placetype":"venue"
},
  "geometry": {"coordinates":[-3.20631,51.481194],"type":"Point"}
}