{
  "type": "Feature",
  "properties": {
    "iso:country":"GB",
    "sg:address":"24 High Street, Kippax",
    "sg:city":"Leeds",
    "sg:classifiers":[
        {
            "category":"Personal",
            "subcategory":"Beauty Salon",
            "type":"Services"
        },
        {
            "category":"Personal",
            "subcategory":"Barber",
            "type":"Services"
        }
    ],
    "sg:phone":"+44 113 286 1244",
    "sg:postcode":"LS25 7AB",
    "sg:province":"North Yorkshire",
    "sg:tags":[
        "unisex",
        "hairdresser"
    ],
    "wof:name":"Kevins",
    "wof:placetype":"venue"
},
  "geometry": {"coordinates":[-1.3686360121,53.7665405273],"type":"Point"}
}