{
  "type": "Feature",
  "properties": {
    "iso:country":"GB",
    "sg:address":"82 English Street",
    "sg:city":"Carlisle",
    "sg:classifiers":[
        {
            "category":"Sports & Exercise",
            "subcategory":"Sports Center",
            "type":"Entertainment"
        }
    ],
    "sg:phone":"+44 1228 27478",
    "sg:postcode":"CA3 8HP",
    "sg:province":"Cumbria",
    "sg:tags":[
        "shop",
        "good"
    ],
    "wof:name":"Sports Division Ltd.",
    "wof:placetype":"venue"
},
  "geometry": {"coordinates":[-2.934969,54.892952],"type":"Point"}
}