{
  "type": "Feature",
  "properties": {
    "addr:full":"Ferndale Garden Centre, Berse Rd Wrexham Wrexham LL11 2BH",
    "addr:postcode":"ll11 2bh",
    "addr:street":"Berse Rd",
    "iso:country":"GB",
    "sg:address":"Ferndale Garden Centre, Berse Rd",
    "sg:city":"Wrexham",
    "sg:classifiers":[
        {
            "category":"Cafe",
            "type":"Food & Drink"
        }
    ],
    "sg:phone":"+44 1978 754812",
    "sg:postcode":"LL11 2BH",
    "sg:province":"Wrexham",
    "sg:tags":[
        "tea",
        "room"
    ],
    "wof:name":"Cottage Pantry The",
    "wof:placetype":"venue"
},
  "geometry": {"coordinates":[-3.0105199814,53.0528411865],"type":"Point"}
}