{
  "type": "Feature",
  "properties": {
    "iso:country":"GB",
    "sg:address":"Plas Mostyn Mawr, Pentre Fron Road, Coedpoeth",
    "sg:city":"Wrexham",
    "sg:classifiers":[
        {
            "category":"Farming",
            "subcategory":"Livestock Farm",
            "type":"Manufacturing & Wholesale Goods"
        }
    ],
    "sg:phone":"+44 1978 755755",
    "sg:postcode":"LL11 3BU",
    "sg:province":"Wrexham",
    "sg:tags":[
        "others"
    ],
    "wof:name":"P Harrison & Partners",
    "wof:placetype":"venue"
},
  "geometry": {"coordinates":[-3.070304,53.053265],"type":"Point"}
}