{
  "type": "Feature",
  "properties": {
    "addr:full":"147 Queen Street Newton Abbot Devon TQ12 2BN",
    "addr:housenumber":"147",
    "addr:postcode":"tq12 2bn",
    "addr:street":"Queen Street",
    "iso:country":"GB",
    "sg:address":"147 Queen Street",
    "sg:city":"Newton Abbot",
    "sg:classifiers":[
        {
            "category":"Manufacturing",
            "subcategory":"Rubber & Plastics",
            "type":"Manufacturing & Wholesale Goods"
        }
    ],
    "sg:postcode":"TQ12 2BN",
    "sg:province":"Devon",
    "sg:tags":[
        "product",
        "foam"
    ],
    "wof:name":"The Foam Shop",
    "wof:placetype":"venue"
},
  "geometry": {"coordinates":[-3.601734,50.530842],"type":"Point"}
}