{
  "type": "Feature",
  "properties": {
    "addr:full":"23 Penhevad St, Grangetown Cardiff Cardiff CF11 7LS",
    "addr:housenumber":"23",
    "addr:postcode":"cf11 7ls",
    "addr:street":"Penhevad St",
    "iso:country":"GB",
    "sg:address":"23 Penhevad St, Grangetown",
    "sg:city":"Cardiff",
    "sg:classifiers":[
        {
            "category":"Manufacturing",
            "subcategory":"Building Materials",
            "type":"Manufacturing & Wholesale Goods"
        }
    ],
    "sg:phone":"+44 29 2064 5775",
    "sg:postcode":"CF11 7LS",
    "sg:province":"Cardiff",
    "sg:tags":[
        "tile",
        "mnfrs"
    ],
    "wof:name":"AT Ceramics",
    "wof:placetype":"venue"
},
  "geometry": {"coordinates":[-3.1867558956,51.4675216675],"type":"Point"}
}