{
  "type": "Feature",
  "properties": {
    "iso:country":"GB",
    "sg:address":"4 Castle Vale, Shopping Centre",
    "sg:city":"Birmingham",
    "sg:classifiers":[
        {
            "category":"Government",
            "subcategory":"Post Office",
            "type":"Public Place"
        }
    ],
    "sg:phone":"+44 121 747 0550",
    "sg:postcode":"B35 6DX",
    "sg:province":"West Midlands",
    "wof:name":"Castle Vale Post Office & Newagents",
    "wof:placetype":"venue"
},
  "geometry": {"coordinates":[-1.796849966,52.5173110962],"type":"Point"}
}