{
  "type": "Feature",
  "properties": {
    "addr:full":"Harbour Band Arena, Behind Midland Hotel Morecambe Lancashire LA4 4BZ",
    "addr:postcode":"la4 4bz",
    "addr:street":"Behind",
    "iso:country":"GB",
    "sg:address":"Harbour Band Arena, Behind Midland Hotel",
    "sg:city":"Morecambe",
    "sg:classifiers":[
        {
            "category":"Community Center",
            "type":"Public Place"
        },
        {
            "category":"Organizations",
            "subcategory":"Membership Organization",
            "type":"Services"
        }
    ],
    "sg:phone":"+44 1524 424190",
    "sg:postcode":"LA4 4BZ",
    "sg:province":"Lancashire",
    "sg:tags":[
        "club",
        "recreation",
        "leisure",
        "centre"
    ],
    "wof:name":"Arena Leisure",
    "wof:placetype":"venue"
},
  "geometry": {"coordinates":[-2.854494,54.070129],"type":"Point"}
}