{
  "type": "Feature",
  "properties": {
    "iso:country":"GB",
    "sg:address":"Sandlands Gr",
    "sg:city":"Tadworth",
    "sg:classifiers":[
        {
            "category":"Government",
            "subcategory":"Police Station",
            "type":"Public Place"
        }
    ],
    "sg:phone":"+44 1737 812202",
    "sg:postcode":"KT20 7UY",
    "sg:province":"Surrey",
    "sg:tags":[
        "support"
    ],
    "wof:name":"Transport Police Training College",
    "wof:placetype":"venue"
},
  "geometry": {"coordinates":[-0.2484270036,51.285900116],"type":"Point"}
}