{
  "type": "Feature",
  "properties": {
    "iso:country":"GB",
    "sg:address":"Wle, C/o Roec, Middleton",
    "sg:city":"Swansea",
    "sg:classifiers":[
        {
            "category":"Community Center",
            "type":"Public Place"
        }
    ],
    "sg:phone":"+44 1792 390567",
    "sg:postcode":"SA3 1PJ",
    "sg:province":"Swansea",
    "sg:tags":[
        "recreation",
        "leisure",
        "centre"
    ],
    "wof:name":"Welsh Leisure Activities",
    "wof:placetype":"venue"
},
  "geometry": {"coordinates":[-4.27845,51.567081],"type":"Point"}
}