{
  "type": "Feature",
  "properties": {
    "iso:country":"GB",
    "sg:address":"52 Northumberland Avenue",
    "sg:city":"Stamford",
    "sg:classifiers":[
        {
            "category":"Arts & Performance",
            "subcategory":"Music",
            "type":"Entertainment"
        }
    ],
    "sg:phone":"+44 1780 751683",
    "sg:postcode":"PE9 1EA",
    "sg:province":"Cambridgeshire",
    "sg:tags":[
        "mobile",
        "disco"
    ],
    "wof:name":"Stars Karaoke Disco",
    "wof:placetype":"venue"
},
  "geometry": {"coordinates":[-0.48694,52.65604],"type":"Point"}
}