{
  "type": "Feature",
  "properties": {
    "iso:country":"GB",
    "sg:address":"79 Armstrong Rise, Charlton",
    "sg:city":"Andover",
    "sg:classifiers":[
        {
            "category":"Building & Trades",
            "subcategory":"Construction",
            "type":"Services"
        }
    ],
    "sg:postcode":"SP10 4EB",
    "sg:province":"Hampshire",
    "sg:tags":[
        "roofing"
    ],
    "wof:name":"Malcolm Peacock",
    "wof:placetype":"venue"
},
  "geometry": {"coordinates":[-1.496751,51.222839],"type":"Point"}
}