{
  "type": "Feature",
  "properties": {
    "addr:full":"Upper Litton, Whitton Knighton Shropshire LD7 1NP",
    "addr:postcode":"ld7 1np",
    "addr:street":"Upper Litton",
    "iso:country":"GB",
    "sg:address":"Upper Litton, Whitton",
    "sg:city":"Knighton",
    "sg:classifiers":[
        {
            "category":"Professional",
            "subcategory":"Art Services",
            "type":"Services"
        }
    ],
    "sg:phone":"+44 1547 560417",
    "sg:postcode":"LD7 1NP",
    "sg:province":"Shropshire",
    "sg:tags":[
        "consultant",
        "design"
    ],
    "wof:name":"Joanna M Griffiths",
    "wof:placetype":"venue"
},
  "geometry": {"coordinates":[-3.04771,52.343067],"type":"Point"}
}