{
  "type": "Feature",
  "properties": {
    "iso:country":"GB",
    "sg:address":"126 Preston Road",
    "sg:city":"Chorley",
    "sg:classifiers":[
        {
            "category":"Health Services",
            "subcategory":"Health Practitioner",
            "type":"Services"
        }
    ],
    "sg:postcode":"PR6 7AU",
    "sg:province":"Lancashire",
    "sg:tags":[
        "physiotherapist"
    ],
    "wof:name":"Chorley Physiotherapy",
    "wof:placetype":"venue"
},
  "geometry": {"coordinates":[-2.632097,53.667164],"type":"Point"}
}