{
  "type": "Feature",
  "properties": {
    "addr:full":"Kirk Wynd Blairgowrie Perth and Kinross PH10 6HN",
    "addr:postcode":"ph10 6hn",
    "addr:street":"Kirk Wynd",
    "iso:country":"GB",
    "sg:address":"Kirk Wynd",
    "sg:city":"Blairgowrie",
    "sg:classifiers":[
        {
            "category":"Health Services",
            "subcategory":"Nursing And Care Facility",
            "type":"Services"
        },
        {
            "category":"Social Services",
            "subcategory":"Retirement Home",
            "type":"Services"
        }
    ],
    "sg:phone":"+44 1250 872853",
    "sg:postcode":"PH10 6HN",
    "sg:province":"Perth and Kinross",
    "sg:tags":[
        "residential"
    ],
    "wof:name":"Stormont Lodge Residential Home",
    "wof:placetype":"venue"
},
  "geometry": {"coordinates":[-3.3403279781,56.5950431824],"type":"Point"}
}