{
  "type": "Feature",
  "properties": {
    "addr:full":"M G House, Franchise Street Kidderminster Staffordshire DY11 6RE",
    "addr:postcode":"dy11 6re",
    "addr:street":"M;Franchise Street",
    "iso:country":"GB",
    "sg:address":"M G House, Franchise Street",
    "sg:city":"Kidderminster",
    "sg:classifiers":[
        {
            "category":"Shopping",
            "subcategory":"Clothing, Apparel, & Fashions",
            "type":"Retail Goods"
        }
    ],
    "sg:phone":"+44 1562 744735",
    "sg:postcode":"DY11 6RE",
    "sg:province":"Staffordshire",
    "sg:tags":[
        "sportswear"
    ],
    "wof:name":"M G Sportswear Ltd.",
    "wof:placetype":"venue"
},
  "geometry": {"coordinates":[-2.2601399422,52.3844490051],"type":"Point"}
}