{
  "type": "Feature",
  "properties": {
    "addr:full":"6 Tylehurst Gardens Ilford Essex IG1 2QL",
    "addr:housenumber":"6",
    "addr:postcode":"ig1 2ql",
    "addr:street":"Tylehurst Gardens",
    "iso:country":"GB",
    "sg:address":"6 Tylehurst Gardens",
    "sg:city":"Ilford",
    "sg:classifiers":[
        {
            "category":"Shopping",
            "subcategory":"Musical Instruments",
            "type":"Retail Goods"
        },
        {
            "category":"Retail",
            "subcategory":"Repair Shop",
            "type":"Services"
        }
    ],
    "sg:phone":"+44 20 8478 8242",
    "sg:postcode":"IG1 2QL",
    "sg:province":"Essex",
    "sg:tags":[
        "restoration"
    ],
    "wof:name":"Electronic Maintenance Services",
    "wof:placetype":"venue"
},
  "geometry": {"coordinates":[0.0778080001,51.5495223999],"type":"Point"}
}