{
  "type": "Feature",
  "properties": {
    "iso:country":"GB",
    "sg:address":"87 - 89 Lampton Road",
    "sg:city":"Hounslow",
    "sg:classifiers":[
        {
            "category":"Travel",
            "subcategory":"Hotels & Motels",
            "type":"Entertainment"
        }
    ],
    "sg:phone":"+44 20 8572 5107",
    "sg:postcode":"TW3 4DP",
    "sg:province":"Greater London",
    "sg:tags":[
        "house",
        "guest"
    ],
    "wof:name":"Civic Guest House",
    "wof:placetype":"venue"
},
  "geometry": {"coordinates":[-0.366206,51.473381],"type":"Point"}
}