{
  "type": "Feature",
  "properties": {
    "iso:country":"GB",
    "sg:address":"Rhoin Farm",
    "sg:city":"Campbeltown",
    "sg:classifiers":[
        {
            "category":"Farming",
            "subcategory":"Livestock Farm",
            "type":"Manufacturing & Wholesale Goods"
        }
    ],
    "sg:postcode":"PA28 6NT",
    "sg:province":"Argyll and Bute",
    "sg:tags":[
        "others"
    ],
    "wof:name":"M & C Ralston",
    "wof:placetype":"venue"
},
  "geometry": {"coordinates":[-5.610239,55.431419],"type":"Point"}
}