{
  "type": "Feature",
  "properties": {
    "addr:full":"1 Lincoln Street Barrow-in-furness Cumbria LA14 5HS",
    "addr:housenumber":"1",
    "addr:postcode":"la14 5hs",
    "addr:street":"Lincoln Street",
    "iso:country":"GB",
    "sg:address":"1 Lincoln Street",
    "sg:city":"Barrow-in-furness",
    "sg:classifiers":[
        {
            "category":"Sports & Exercise",
            "subcategory":"Golf",
            "type":"Entertainment"
        }
    ],
    "sg:postcode":"LA14 5HS",
    "sg:province":"Cumbria",
    "sg:tags":[
        "equipment"
    ],
    "wof:name":"Lakeland Golf Shop",
    "wof:placetype":"venue"
},
  "geometry": {"coordinates":[-3.22165,54.120949],"type":"Point"}
}