{
  "type": "Feature",
  "properties": {
    "iso:country":"GB",
    "sg:address":"Forge Garage Annexe, The High Street, Rotherfield",
    "sg:city":"Crowborough",
    "sg:classifiers":[
        {
            "category":"Retail",
            "subcategory":"Auto Repair",
            "type":"Services"
        }
    ],
    "sg:phone":"+44 1892 853004",
    "sg:postcode":"TN6 3LN",
    "sg:province":"East Sussex",
    "sg:tags":[
        "modification",
        "garage",
        "related"
    ],
    "wof:name":"Rotherfield Gearboxes",
    "wof:placetype":"venue"
},
  "geometry": {"coordinates":[0.2191720009,51.0442657471],"type":"Point"}
}