{
  "type": "Feature",
  "properties": {
    "iso:country":"GB",
    "sg:address":"9 Moor Croft",
    "sg:city":"Bingley",
    "sg:classifiers":[
        {
            "category":"Real Estate",
            "subcategory":"Real Estate Agent",
            "type":"Services"
        }
    ],
    "sg:phone":"+44 1274 551881",
    "sg:postcode":"BD16 3DR",
    "sg:province":"West Yorkshire",
    "sg:tags":[
        "trademark"
    ],
    "wof:name":"Meridian Marketing",
    "wof:placetype":"venue"
},
  "geometry": {"coordinates":[-1.818772,53.857906],"type":"Point"}
}