{
  "type": "Feature",
  "properties": {
    "addr:full":"Main St, Iden Rye East Sussex TN31 7PT",
    "addr:postcode":"tn31 7pt",
    "addr:street":"Main St",
    "iso:country":"GB",
    "sg:address":"Main St, Iden",
    "sg:city":"Rye",
    "sg:classifiers":[
        {
            "category":"Bars & Pubs",
            "type":"Food & Drink"
        }
    ],
    "sg:postcode":"TN31 7PT",
    "sg:province":"East Sussex",
    "sg:tags":[
        "pubs",
        "inn"
    ],
    "wof:name":"Pithie,Barbara,",
    "wof:placetype":"venue"
},
  "geometry": {"coordinates":[0.730905,50.982143],"type":"Point"}
}