{
  "type": "Feature",
  "properties": {
    "addr:full":"2 Dallas Road, Sydenham London Greater London SE26 6JP",
    "addr:housenumber":"2",
    "addr:postcode":"se26 6jp",
    "addr:street":"Dallas Road",
    "iso:country":"GB",
    "sg:address":"2 Dallas Road, Sydenham",
    "sg:city":"London",
    "sg:classifiers":[
        {
            "category":"Professional",
            "subcategory":"Computer Services",
            "type":"Services"
        }
    ],
    "sg:postcode":"SE26 6JP",
    "sg:province":"Greater London",
    "sg:tags":[
        "system",
        "software"
    ],
    "wof:name":"Xpert Technology Ltd",
    "wof:placetype":"venue"
},
  "geometry": {"coordinates":[-0.063461,51.430954],"type":"Point"}
}