{
  "type": "Feature",
  "properties": {
    "addr:full":"Po Box 14 Bridgend Industrial E, State Bridgend Bridgend CF31 3DZ",
    "addr:housenumber":"po box 14",
    "addr:postcode":"cf31 3dz",
    "addr:street":"Bridgend Industrial E State",
    "iso:country":"GB",
    "sg:address":"Po Box 14 Bridgend Industrial E, State",
    "sg:city":"Bridgend",
    "sg:classifiers":[
        {
            "category":"Building & Trades",
            "subcategory":"Construction",
            "type":"Services"
        }
    ],
    "sg:phone":"+44 1656 653541",
    "sg:postcode":"CF31 3DZ",
    "sg:province":"Bridgend",
    "sg:tags":[
        "builder"
    ],
    "wof:name":"Gee Walker & Slater (South Wales) Ltd.",
    "wof:placetype":"venue"
},
  "geometry": {"coordinates":[-3.539914,51.503189],"type":"Point"}
}