{
  "type": "Feature",
  "properties": {
    "addr:full":"Unit 2, Hadnock Road Monmouth Gloucestershire NP25 3NQ",
    "addr:housenumber":"unit 2",
    "addr:postcode":"np25 3nq",
    "addr:street":"Hadnock Road",
    "iso:country":"GB",
    "sg:address":"Unit 2, Hadnock Road",
    "sg:city":"Monmouth",
    "sg:classifiers":[
        {
            "category":"Building & Trades",
            "subcategory":"Plumbing",
            "type":"Services"
        }
    ],
    "sg:phone":"+44 1600 712500",
    "sg:postcode":"NP25 3NQ",
    "sg:province":"Gloucestershire",
    "sg:tags":[
        "merchant",
        "plumbers'"
    ],
    "wof:name":"First Call Plumbing Supplies Ltd.",
    "wof:placetype":"venue"
},
  "geometry": {"coordinates":[-2.6916320324,51.820514679],"type":"Point"}
}