{
  "type": "Feature",
  "properties": {
    "iso:country":"GB",
    "sg:address":"Station App",
    "sg:city":"West Drayton",
    "sg:classifiers":[
        {
            "category":"Building & Trades",
            "subcategory":"Equipment Rental",
            "type":"Services"
        }
    ],
    "sg:phone":"+44 1895 446444",
    "sg:postcode":"UB7 9DZ",
    "sg:province":"Greater London",
    "sg:tags":[
        "plant",
        "machinery"
    ],
    "wof:name":"T D G Plc",
    "wof:placetype":"venue"
},
  "geometry": {"coordinates":[-0.466945,51.503735],"type":"Point"}
}