{
  "type": "Feature",
  "properties": {
    "addr:full":"16 Kings Road Lee-on-the-solent Hampshire PO13 9NU",
    "addr:housenumber":"16",
    "addr:postcode":"po13 9nu",
    "addr:street":"Kings Road",
    "iso:country":"GB",
    "sg:address":"16 Kings Road",
    "sg:city":"Lee-on-the-solent",
    "sg:classifiers":[
        {
            "category":"Travel",
            "subcategory":"Hotels & Motels",
            "type":"Entertainment"
        }
    ],
    "sg:postcode":"PO13 9NU",
    "sg:province":"Hampshire",
    "sg:tags":[
        "house",
        "guest"
    ],
    "wof:name":"Kings Lodge Guest House",
    "wof:placetype":"venue"
},
  "geometry": {"coordinates":[-1.2046819925,50.806476593],"type":"Point"}
}