{
  "type": "Feature",
  "properties": {
    "addr:full":"89 Monmouth Close, Chandlers Ford Southampton Hampshire SO53 4SZ",
    "addr:housenumber":"89",
    "addr:postcode":"so53 4sz",
    "addr:street":"Monmouth Close Chandlers",
    "iso:country":"GB",
    "sg:address":"89 Monmouth Close, Chandlers Ford",
    "sg:city":"Southampton",
    "sg:classifiers":[
        {
            "category":"Professional",
            "subcategory":"Lawyer & Legal Services",
            "type":"Services"
        }
    ],
    "sg:phone":"+44 23 8026 5814",
    "sg:postcode":"SO53 4SZ",
    "sg:province":"Hampshire",
    "sg:tags":[
        "writing"
    ],
    "wof:name":"Wills on Wheels",
    "wof:placetype":"venue"
},
  "geometry": {"coordinates":[-1.389622,50.983845],"type":"Point"}
}