{
  "type": "Feature",
  "properties": {
    "addr:full":"Uphempston Cottage, Littlehempston Totnes Devon TQ9 6LP",
    "addr:postcode":"tq9 6lp",
    "iso:country":"GB",
    "sg:address":"Uphempston Cottage, Littlehempston",
    "sg:city":"Totnes",
    "sg:classifiers":[
        {
            "category":"Building & Trades",
            "subcategory":"Construction",
            "type":"Services"
        }
    ],
    "sg:phone":"+44 1803 867618",
    "sg:postcode":"TQ9 6LP",
    "sg:province":"Devon",
    "sg:tags":[
        "roofing"
    ],
    "wof:name":"South Hams Roofing Ltd.",
    "wof:placetype":"venue"
},
  "geometry": {"coordinates":[-3.6667239666,50.4508705139],"type":"Point"}
}