{
  "type": "Feature",
  "properties": {
    "addr:full":"113 Old Church Road London Greater London E4 6ST",
    "addr:housenumber":"113",
    "addr:postcode":"e4 6st",
    "addr:street":"Old Church Road",
    "iso:country":"GB",
    "sg:address":"113 Old Church Road",
    "sg:city":"London",
    "sg:classifiers":[
        {
            "category":"Personal",
            "subcategory":"Beauty Salon",
            "type":"Services"
        }
    ],
    "sg:phone":"+44 20 8529 0006",
    "sg:postcode":"E4 6ST",
    "sg:province":"Greater London",
    "sg:tags":[
        "unisex",
        "hairdresser"
    ],
    "wof:name":"K Christche",
    "wof:placetype":"venue"
},
  "geometry": {"coordinates":[-0.0169459991,51.6198348999],"type":"Point"}
}