{
  "type": "Feature",
  "properties": {
    "iso:country":"GB",
    "sg:address":"One Two Three Wallpapers",
    "sg:city":"Leek",
    "sg:classifiers":[
        {
            "category":"Home & Garden",
            "subcategory":"Home Furnishings",
            "type":"Retail Goods"
        }
    ],
    "sg:phone":"+44 1538 371626",
    "sg:postcode":"ST13 5NS",
    "sg:province":"Staffordshire",
    "sg:tags":[
        "wall",
        "wallpaper",
        "covering"
    ],
    "wof:name":"Anna Marie & Dave Ladd",
    "wof:placetype":"venue"
},
  "geometry": {"coordinates":[-2.020884,53.106476],"type":"Point"}
}