{
  "type": "Feature",
  "properties": {
    "iso:country":"GB",
    "sg:address":"Estate House, 201 High Road",
    "sg:city":"Chigwell",
    "sg:classifiers":[
        {
            "category":"Food & Beverages",
            "subcategory":"Specialty",
            "type":"Retail Goods"
        }
    ],
    "sg:postcode":"IG7 6PS",
    "sg:province":"Essex",
    "sg:tags":[
        "product",
        "health"
    ],
    "wof:name":"Life Plus Ltd.",
    "wof:placetype":"venue"
},
  "geometry": {"coordinates":[0.074576,51.618523],"type":"Point"}
}