{
  "type": "Feature",
  "properties": {
    "iso:country":"GB",
    "sg:address":"42 Regent St",
    "sg:city":"Shanklin",
    "sg:classifiers":[
        {
            "category":"Government",
            "subcategory":"Post Office",
            "type":"Public Place"
        }
    ],
    "sg:phone":"+44 1983 862364",
    "sg:postcode":"PO37 7AA",
    "sg:province":"Isle of Wight",
    "wof:name":"Southern Vectis Post Office",
    "wof:placetype":"venue"
},
  "geometry": {"coordinates":[-1.178579,50.63084],"type":"Point"}
}