{
  "type": "Feature",
  "properties": {
    "iso:country":"GB",
    "sg:address":"Lynton Lodge, Beaufort Avenue",
    "sg:city":"Sale",
    "sg:classifiers":[
        {
            "category":"Education",
            "subcategory":"Music School",
            "type":"Public Place"
        }
    ],
    "sg:postcode":"M33 3WL",
    "sg:province":"Cheshire",
    "sg:tags":[
        "teacher"
    ],
    "wof:name":"Owen Wynne",
    "wof:placetype":"venue"
},
  "geometry": {"coordinates":[-2.320417,53.425949],"type":"Point"}
}