{
  "type": "Feature",
  "properties": {
    "addr:full":"102 Walton Drive, Terriers High Wycombe Buckinghamshire HP13 6TY",
    "addr:housenumber":"102",
    "addr:postcode":"hp13 6ty",
    "addr:street":"Walton Drive",
    "iso:country":"GB",
    "sg:address":"102 Walton Drive, Terriers",
    "sg:city":"High Wycombe",
    "sg:classifiers":[
        {
            "category":"Professional",
            "subcategory":"Engineering",
            "type":"Services"
        }
    ],
    "sg:phone":"+44 1494 442284",
    "sg:postcode":"HP13 6TY",
    "sg:province":"Buckinghamshire",
    "sg:tags":[
        "contractor",
        "electrical",
        "engineer"
    ],
    "wof:name":"N G Electrical",
    "wof:placetype":"venue"
},
  "geometry": {"coordinates":[-0.730941,51.640537],"type":"Point"}
}