{
  "type": "Feature",
  "properties": {
    "iso:country":"GB",
    "sg:address":"Montague Farm, Kirdford Road, Wisborough Grn",
    "sg:city":"Billingshurst",
    "sg:classifiers":[
        {
            "category":"Farming",
            "subcategory":"Livestock Farm",
            "type":"Manufacturing & Wholesale Goods"
        }
    ],
    "sg:phone":"+44 1403 700265",
    "sg:postcode":"RH14 0DD",
    "sg:province":"West Sussex",
    "sg:tags":[
        "others"
    ],
    "wof:name":"Richard J Stickland",
    "wof:placetype":"venue"
},
  "geometry": {"coordinates":[-0.5526239872,51.0324287415],"type":"Point"}
}