{
  "type": "Feature",
  "properties": {
    "addr:full":"29 Eglise Road Warlingham Kent CR6 9SE",
    "addr:housenumber":"29",
    "addr:postcode":"cr6 9se",
    "addr:street":"Eglise Road",
    "iso:country":"GB",
    "sg:address":"29 Eglise Road",
    "sg:city":"Warlingham",
    "sg:classifiers":[
        {
            "category":"Health Services",
            "subcategory":"Clinic",
            "type":"Services"
        },
        {
            "category":"Building & Trades",
            "subcategory":"Electrical",
            "type":"Services"
        }
    ],
    "sg:phone":"+44 1883 625584",
    "sg:postcode":"CR6 9SE",
    "sg:province":"Kent",
    "sg:tags":[
        "aromatherapy",
        "electrician",
        "contractor"
    ],
    "wof:name":"Ros Barrett",
    "wof:placetype":"venue"
},
  "geometry": {"coordinates":[-0.046432,51.309719],"type":"Point"}
}