{
  "type": "Feature",
  "properties": {
    "iso:country":"GB",
    "sg:address":"The Grange, Earthcott Green",
    "sg:city":"Bristol",
    "sg:classifiers":[
        {
            "category":"Professional",
            "subcategory":"Accounting & Tax Preparation",
            "type":"Services"
        }
    ],
    "sg:phone":"+44 1454 418974",
    "sg:postcode":"BS35 3TA",
    "sg:province":"Gloucestershire",
    "sg:tags":[
        "accountant"
    ],
    "wof:name":"Taylor & Co.",
    "wof:placetype":"venue"
},
  "geometry": {"coordinates":[-2.526344,51.589973],"type":"Point"}
}