{
  "type": "Feature",
  "properties": {
    "addr:full":"10 Maltravers St Holborn Greater London WC2R 3EE",
    "addr:housenumber":"10",
    "addr:postcode":"wc2r 3ee",
    "addr:street":"Maltravers St",
    "iso:country":"GB",
    "sg:address":"10 Maltravers St",
    "sg:city":"Holborn",
    "sg:classifiers":[
        {
            "category":"Utilities",
            "type":"Services"
        }
    ],
    "sg:phone":"+44 20 7836 8700",
    "sg:postcode":"WC2R 3EE",
    "sg:province":"Greater London",
    "sg:tags":[
        "internet"
    ],
    "wof:name":"Internet Telephone",
    "wof:placetype":"venue"
},
  "geometry": {"coordinates":[-0.1137650013,51.5120162964],"type":"Point"}
}