{
  "type": "Feature",
  "properties": {
    "iso:country":"GB",
    "sg:address":"61 Wath Road",
    "sg:city":"Mexborough",
    "sg:classifiers":[
        {
            "category":"Professional",
            "subcategory":"Art Services",
            "type":"Services"
        }
    ],
    "sg:phone":"+44 1709 590962",
    "sg:postcode":"S64 9QZ",
    "sg:province":"South Yorkshire",
    "sg:tags":[
        "photographer"
    ],
    "wof:name":"Roman Photographics",
    "wof:placetype":"venue"
},
  "geometry": {"coordinates":[-1.300317,53.495293],"type":"Point"}
}