{
  "type": "Feature",
  "properties": {
    "iso:country":"GB",
    "sg:address":"Hemington Lodge Road, Great Gidding",
    "sg:city":"Huntingdon",
    "sg:classifiers":[
        {
            "category":"Building & Trades",
            "subcategory":"Equipment Rental",
            "type":"Services"
        }
    ],
    "sg:phone":"+44 1832 293680",
    "sg:postcode":"PE28 5QZ",
    "sg:province":"Bedfordshire",
    "sg:tags":[
        "plant",
        "machinery"
    ],
    "wof:name":"Stanmore Plant Hire Ltd.",
    "wof:placetype":"venue"
},
  "geometry": {"coordinates":[-0.356404,52.444649],"type":"Point"}
}