{
  "type": "Feature",
  "properties": {
    "addr:full":"36 Bridge Street Morpeth Northumberland NE61 1NL",
    "addr:housenumber":"36",
    "addr:postcode":"ne61 1nl",
    "addr:street":"Bridge Street",
    "iso:country":"GB",
    "sg:address":"36 Bridge Street",
    "sg:city":"Morpeth",
    "sg:classifiers":[
        {
            "category":"Communications",
            "subcategory":"Newspaper",
            "type":"Services"
        }
    ],
    "sg:phone":"+44 1670 517362",
    "sg:postcode":"NE61 1NL",
    "sg:province":"Northumberland",
    "sg:tags":[
        "magazine"
    ],
    "wof:name":"Herald & Post",
    "wof:placetype":"venue"
},
  "geometry": {"coordinates":[-1.6884150505,55.1672172546],"type":"Point"}
}