{
  "type": "Feature",
  "properties": {
    "iso:country":"GB",
    "sg:address":"108a Christchurch Road",
    "sg:city":"Ringwood",
    "sg:classifiers":[
        {
            "category":"Autos & Motor Vehicles",
            "subcategory":"Automobile Sales",
            "type":"Retail Goods"
        }
    ],
    "sg:phone":"+44 1425 473956",
    "sg:postcode":"BH24 1DR",
    "sg:province":"Dorset",
    "sg:tags":[
        "car"
    ],
    "wof:name":"Hanham Motor Ringwood",
    "wof:placetype":"venue"
},
  "geometry": {"coordinates":[-1.7872649431,50.8428077698],"type":"Point"}
}