{
  "type": "Feature",
  "properties": {
    "addr:full":"3 Winnett Street London Greater London W1D 6JY",
    "addr:housenumber":"3",
    "addr:postcode":"w1d 6jy",
    "addr:street":"Winnett Street",
    "iso:country":"GB",
    "sg:address":"3 Winnett Street",
    "sg:city":"London",
    "sg:classifiers":[
        {
            "category":"Cafe",
            "type":"Food & Drink"
        }
    ],
    "sg:phone":"+44 20 7437 5045",
    "sg:postcode":"W1D 6JY",
    "sg:province":"Greater London",
    "sg:tags":[
        "tea",
        "room"
    ],
    "wof:name":"Il Panino Italiano",
    "wof:placetype":"venue"
},
  "geometry": {"coordinates":[-0.13332,51.512299],"type":"Point"}
}