{
  "type": "Feature",
  "properties": {
    "iso:country":"GB",
    "sg:address":"Unit 6 Rear Of 39 St Davids Rd North",
    "sg:city":"Lytham St Annes",
    "sg:classifiers":[
        {
            "category":"Retail",
            "subcategory":"Auto Repair",
            "type":"Services"
        }
    ],
    "sg:phone":"+44 1253 782947",
    "sg:postcode":"FY8 2BL",
    "sg:province":"Lancashire",
    "sg:tags":[
        "body",
        "car"
    ],
    "wof:name":"Bodyshop Accident Damage Specialists",
    "wof:placetype":"venue"
},
  "geometry": {"coordinates":[-2.991574,53.749516],"type":"Point"}
}