{
  "type": "Feature",
  "properties": {
    "iso:country":"GB",
    "sg:address":"137 High Street",
    "sg:city":"Bangor",
    "sg:classifiers":[
        {
            "category":"Professional",
            "subcategory":"Accounting & Tax Preparation",
            "type":"Services"
        }
    ],
    "sg:postcode":"LL57 1PR",
    "sg:province":"Gwynedd",
    "sg:tags":[
        "accountant"
    ],
    "wof:name":"Thomas R Knowles & Williams",
    "wof:placetype":"venue"
},
  "geometry": {"coordinates":[-4.1145119667,53.2309417725],"type":"Point"}
}