{
  "type": "Feature",
  "properties": {
    "addr:full":"Fairfield Works, 95 Wesy Wycombe Road High Wycombe Buckinghamshire HP11 2LR",
    "addr:housenumber":"95",
    "addr:postcode":"hp11 2lr",
    "addr:street":"Wesy Wycombe Road",
    "iso:country":"GB",
    "sg:address":"Fairfield Works, 95 Wesy Wycombe Road",
    "sg:city":"High Wycombe",
    "sg:classifiers":[
        {
            "category":"Home & Garden",
            "subcategory":"Hardware",
            "type":"Retail Goods"
        }
    ],
    "sg:phone":"+44 1494 530854",
    "sg:postcode":"HP11 2LR",
    "sg:province":"Buckinghamshire",
    "sg:tags":[
        "paint",
        "coating"
    ],
    "wof:name":"Sprayblast Fabrications Ltd.",
    "wof:placetype":"venue"
},
  "geometry": {"coordinates":[-0.76268,51.634331],"type":"Point"}
}