{
  "type": "Feature",
  "properties": {
    "addr:full":"2 Tynemouth Rd, Howdon Wallsend Tyne and Wear NE28 0AA",
    "addr:housenumber":"2",
    "addr:postcode":"ne28 0aa",
    "addr:street":"Tynemouth Rd",
    "iso:country":"GB",
    "sg:address":"2 Tynemouth Rd, Howdon",
    "sg:city":"Wallsend",
    "sg:classifiers":[
        {
            "category":"Professional",
            "type":"Services"
        }
    ],
    "sg:phone":"+44 191 287 1165",
    "sg:postcode":"NE28 0AA",
    "sg:province":"Tyne and Wear",
    "sg:tags":[
        "entertainer"
    ],
    "wof:name":"Double Deckers Magic",
    "wof:placetype":"venue"
},
  "geometry": {"coordinates":[-1.5033940077,54.9961738586],"type":"Point"}
}