{
  "type": "Feature",
  "properties": {
    "iso:country":"GB",
    "sg:address":"9 Patchy Park",
    "sg:city":"Larkhall",
    "sg:classifiers":[
        {
            "category":"Food & Beverages",
            "subcategory":"Meat & Fish",
            "type":"Retail Goods"
        }
    ],
    "sg:postcode":"ML9 1NL",
    "sg:province":"South Lanarkshire",
    "sg:tags":[
        "butcher"
    ],
    "wof:name":"John Ritchie & Sons",
    "wof:placetype":"venue"
},
  "geometry": {"coordinates":[-3.9716300964,55.7265129089],"type":"Point"}
}