{
  "type": "Feature",
  "properties": {
    "addr:full":"Beaconsfield St, Long Eaton Nottingham Derbyshire NG10 1AY",
    "addr:postcode":"ng10 1ay",
    "addr:street":"Beaconsfield St",
    "iso:country":"GB",
    "sg:address":"Beaconsfield St, Long Eaton",
    "sg:city":"Nottingham",
    "sg:classifiers":[
        {
            "category":"Autos & Motor Vehicles",
            "subcategory":"Automobile Sales",
            "type":"Retail Goods"
        }
    ],
    "sg:phone":"+44 115 946 5557",
    "sg:postcode":"NG10 1AY",
    "sg:province":"Derbyshire",
    "sg:tags":[
        "car"
    ],
    "wof:name":"Beaconsfield Vehicle Sales and Hire Ltd",
    "wof:placetype":"venue"
},
  "geometry": {"coordinates":[-1.2704290152,52.8964767456],"type":"Point"}
}