{
  "type": "Feature",
  "properties": {
    "iso:country":"GB",
    "sg:address":"Tregarthen Nurseries, Mylor",
    "sg:city":"Falmouth",
    "sg:classifiers":[
        {
            "category":"Community Center",
            "type":"Public Place"
        }
    ],
    "sg:phone":"+44 1872 865961",
    "sg:postcode":"TR11 5UL",
    "sg:province":"Cornwall",
    "sg:tags":[
        "nursery",
        "centre"
    ],
    "wof:name":"W Harcourt Williams (Falmouth) Ltd.",
    "wof:placetype":"venue"
},
  "geometry": {"coordinates":[-5.080033,50.152206],"type":"Point"}
}