{
  "type": "Feature",
  "properties": {
    "addr:full":"55 Edgwick Road Coventry Warwickshire CV6 5FP",
    "addr:housenumber":"55",
    "addr:postcode":"cv6 5fp",
    "addr:street":"Edgwick Road",
    "iso:country":"GB",
    "sg:address":"55 Edgwick Road",
    "sg:city":"Coventry",
    "sg:classifiers":[
        {
            "category":"Building & Trades",
            "subcategory":"Construction",
            "type":"Services"
        }
    ],
    "sg:phone":"+44 24 7668 7167",
    "sg:postcode":"CV6 5FP",
    "sg:province":"Warwickshire",
    "sg:tags":[
        "decorator",
        "painter"
    ],
    "wof:name":"Zenith Contractors Ltd.",
    "wof:placetype":"venue"
},
  "geometry": {"coordinates":[-1.490742,52.428528],"type":"Point"}
}