{
  "type": "Feature",
  "properties": {
    "addr:full":"17 Brunswick Sq Gloucester Gloucestershire GL1 1UG",
    "addr:housenumber":"17",
    "addr:postcode":"gl1 1ug",
    "addr:street":"Brunswick Sq",
    "iso:country":"GB",
    "sg:address":"17 Brunswick Sq",
    "sg:city":"Gloucester",
    "sg:classifiers":[
        {
            "category":"Real Estate",
            "subcategory":"Surveying",
            "type":"Services"
        }
    ],
    "sg:phone":"+44 1452 504284",
    "sg:postcode":"GL1 1UG",
    "sg:province":"Gloucestershire",
    "sg:tags":[
        "surveyor",
        "quantity"
    ],
    "wof:name":"Rose Blizzard & Associates",
    "wof:placetype":"venue"
},
  "geometry": {"coordinates":[-2.248274,51.861382],"type":"Point"}
}