{
  "type": "Feature",
  "properties": {
    "addr:full":"Chelsea Lane Inverurie Aberdeenshire AB51 3QQ",
    "addr:postcode":"ab51 3qq",
    "addr:street":"Chelsea Lane",
    "iso:country":"GB",
    "sg:address":"Chelsea Lane",
    "sg:city":"Inverurie",
    "sg:classifiers":[
        {
            "category":"Health Services",
            "subcategory":"Clinic",
            "type":"Services"
        }
    ],
    "sg:phone":"+44 1467 624888",
    "sg:postcode":"AB51 3QQ",
    "sg:province":"Aberdeenshire",
    "sg:tags":[
        "aromatherapy"
    ],
    "wof:name":"R Thompson",
    "wof:placetype":"venue"
},
  "geometry": {"coordinates":[-2.3769040108,57.2842750549],"type":"Point"}
}