{
  "type": "Feature",
  "properties": {
    "addr:full":"Great North Road, Wideopen Newcastle-upon-tyne Northumberland NE13 6PL",
    "addr:postcode":"ne13 6pl",
    "addr:street":"Great North Road",
    "iso:country":"GB",
    "sg:address":"Great North Road, Wideopen",
    "sg:city":"Newcastle-upon-tyne",
    "sg:classifiers":[
        {
            "category":"Social Services",
            "subcategory":"Retirement Home",
            "type":"Services"
        }
    ],
    "sg:phone":"+44 191 217 0090",
    "sg:postcode":"NE13 6PL",
    "sg:province":"Northumberland",
    "sg:tags":[
        "residential",
        "care"
    ],
    "wof:name":"Gosforth Park Care Homes Ltd.",
    "wof:placetype":"venue"
},
  "geometry": {"coordinates":[-1.6239290237,55.0482139587],"type":"Point"}
}