{
  "type": "Feature",
  "properties": {
    "addr:full":"Church End, Markyate St Albans Hertfordshire AL3 8PY",
    "addr:postcode":"al3 8py",
    "addr:street":"End Markyate",
    "iso:country":"GB",
    "sg:address":"Church End, Markyate",
    "sg:city":"St Albans",
    "sg:classifiers":[
        {
            "category":"Retail",
            "subcategory":"Auto Repair",
            "type":"Services"
        }
    ],
    "sg:phone":"+44 1582 841246",
    "sg:postcode":"AL3 8PY",
    "sg:province":"Hertfordshire",
    "sg:tags":[
        "modification",
        "garage",
        "electrician"
    ],
    "wof:name":"L R Gawley",
    "wof:placetype":"venue"
},
  "geometry": {"coordinates":[-0.4609740078,51.8363990784],"type":"Point"}
}