{
  "type": "Feature",
  "properties": {
    "iso:country":"GB",
    "sg:address":"23 Hall Park Hill",
    "sg:city":"Berkhamsted",
    "sg:classifiers":[
        {
            "category":"Banks & Credit Unions",
            "subcategory":"Financial Services",
            "type":"Services"
        },
        {
            "category":"Organizations",
            "subcategory":"Membership Organization",
            "type":"Services"
        }
    ],
    "sg:phone":"+44 1442 862077",
    "sg:postcode":"HP4 2NH",
    "sg:province":"Bedfordshire",
    "sg:tags":[
        "cashing",
        "club",
        "operation",
        "cheque"
    ],
    "wof:name":"de Havilland Moth Club Ltd.",
    "wof:placetype":"venue"
},
  "geometry": {"coordinates":[-0.549159,51.75296],"type":"Point"}
}