{
  "type": "Feature",
  "properties": {
    "iso:country":"GB",
    "sg:address":"Fuller St, Fairstead",
    "sg:city":"Chelmsford",
    "sg:classifiers":[
        {
            "category":"Bars & Pubs",
            "type":"Food & Drink"
        }
    ],
    "sg:postcode":"CM3 2BB",
    "sg:province":"Essex",
    "sg:tags":[
        "pubs",
        "inn"
    ],
    "wof:name":"Potts,V S,",
    "wof:placetype":"venue"
},
  "geometry": {"coordinates":[0.535233,51.814724],"type":"Point"}
}