{
  "type": "Feature",
  "properties": {
    "addr:full":"18 Seven Kings Road Ilford Essex IG3 8DF",
    "addr:housenumber":"18",
    "addr:postcode":"ig3 8df",
    "addr:street":"Seven Kings Road",
    "iso:country":"GB",
    "sg:address":"18 Seven Kings Road",
    "sg:city":"Ilford",
    "sg:classifiers":[
        {
            "category":"Professional",
            "subcategory":"Advertising",
            "type":"Services"
        },
        {
            "category":"Manufacturing",
            "subcategory":"Signs",
            "type":"Manufacturing & Wholesale Goods"
        }
    ],
    "sg:phone":"+44 20 8598 8769",
    "sg:postcode":"IG3 8DF",
    "sg:province":"Essex",
    "sg:tags":[
        "writer",
        "signwriters"
    ],
    "wof:name":"A J S Signs",
    "wof:placetype":"venue"
},
  "geometry": {"coordinates":[0.0984930024,51.5622406006],"type":"Point"}
}