{
  "type": "Feature",
  "properties": {
    "addr:full":"5 Hawth Way Seaford East Sussex BN25 2NG",
    "addr:housenumber":"5",
    "addr:postcode":"bn25 2ng",
    "addr:street":"Hawth Way",
    "iso:country":"GB",
    "sg:address":"5 Hawth Way",
    "sg:city":"Seaford",
    "sg:classifiers":[
        {
            "category":"Building & Trades",
            "subcategory":"Construction",
            "type":"Services"
        }
    ],
    "sg:postcode":"BN25 2NG",
    "sg:province":"East Sussex",
    "sg:tags":[
        "builder"
    ],
    "wof:name":"Seaford Pointing Specialists",
    "wof:placetype":"venue"
},
  "geometry": {"coordinates":[0.0854929984,50.7813835144],"type":"Point"}
}