{
  "type": "Feature",
  "properties": {
    "addr:full":"4 Cowper Road Carpark Dereham Norfolk NR19 2BX",
    "addr:housenumber":"4",
    "addr:postcode":"nr19 2bx",
    "addr:street":"Cowper Road;Dereham",
    "iso:country":"GB",
    "sg:address":"4 Cowper Road Carpark",
    "sg:city":"Dereham",
    "sg:classifiers":[
        {
            "category":"Health Services",
            "subcategory":"Podiatrist",
            "type":"Services"
        }
    ],
    "sg:postcode":"NR19 2BX",
    "sg:province":"Norfolk",
    "sg:tags":[
        "podiatrists",
        "chiropodist"
    ],
    "wof:name":"Frank Nicholls",
    "wof:placetype":"venue"
},
  "geometry": {"coordinates":[0.9439640045,52.6818771362],"type":"Point"}
}