{
  "type": "Feature",
  "properties": {
    "iso:country":"GB",
    "sg:address":"133 Snargate Street",
    "sg:city":"Dover",
    "sg:classifiers":[
        {
            "category":"Shopping",
            "subcategory":"Bicycles & Sporting Goods",
            "type":"Retail Goods"
        }
    ],
    "sg:phone":"+44 1304 206295",
    "sg:postcode":"CT17 9DA",
    "sg:province":"Kent",
    "sg:tags":[
        "equipment",
        "marine",
        "supply"
    ],
    "wof:name":"Sharp & Enright",
    "wof:placetype":"venue"
},
  "geometry": {"coordinates":[1.3103480339,51.1214942932],"type":"Point"}
}