{
  "type": "Feature",
  "properties": {
    "iso:country":"GB",
    "sg:address":"Mill Lane",
    "sg:city":"Lincoln",
    "sg:classifiers":[
        {
            "category":"Retail",
            "subcategory":"Auto Repair",
            "type":"Services"
        }
    ],
    "sg:phone":"+44 1522 520943",
    "sg:postcode":"LN5 7QN",
    "sg:province":"Lincolnshire",
    "sg:tags":[
        "modification",
        "garage"
    ],
    "wof:name":"Barry Carter Motor Services",
    "wof:placetype":"venue"
},
  "geometry": {"coordinates":[-0.5468789935,53.2209701538],"type":"Point"}
}