{
  "type": "Feature",
  "properties": {
    "addr:full":"135 East High Street Forfar Angus DD8 2EQ",
    "addr:housenumber":"135",
    "addr:postcode":"dd8 2eq",
    "addr:street":"East High Street",
    "iso:country":"GB",
    "sg:address":"135 East High Street",
    "sg:city":"Forfar",
    "sg:classifiers":[
        {
            "category":"Bars & Pubs",
            "type":"Food & Drink"
        }
    ],
    "sg:phone":"+44 1307 463334",
    "sg:postcode":"DD8 2EQ",
    "sg:province":"Angus",
    "sg:tags":[
        "pubs",
        "inn"
    ],
    "wof:name":"Flower of Scotland",
    "wof:placetype":"venue"
},
  "geometry": {"coordinates":[-2.8833930492,56.6455535889],"type":"Point"}
}