{
  "type": "Feature",
  "properties": {
    "addr:full":"7 Princess Road Colwyn Bay Conwy LL29 9PS",
    "addr:housenumber":"7",
    "addr:postcode":"ll29 9ps",
    "addr:street":"Princess Road",
    "iso:country":"GB",
    "sg:address":"7 Princess Road",
    "sg:city":"Colwyn Bay",
    "sg:classifiers":[
        {
            "category":"Building & Trades",
            "subcategory":"Plumbing",
            "type":"Services"
        }
    ],
    "sg:postcode":"LL29 9PS",
    "sg:province":"Conwy",
    "sg:tags":[
        "central",
        "heating"
    ],
    "wof:name":"Stevens,John A,",
    "wof:placetype":"venue"
},
  "geometry": {"coordinates":[-3.6976969242,53.2893943787],"type":"Point"}
}