{
  "type": "Feature",
  "properties": {
    "iso:country":"GB",
    "sg:address":"42 Yorkshire Street",
    "sg:city":"Rochdale",
    "sg:classifiers":[
        {
            "category":"Travel",
            "subcategory":"Travel Agent",
            "type":"Entertainment"
        }
    ],
    "sg:phone":"+44 1706 358888",
    "sg:postcode":"OL16 1JN",
    "sg:province":"Lancashire",
    "sg:tags":[
        "agency",
        "activity"
    ],
    "wof:name":"Jmch Services Ltd.",
    "wof:placetype":"venue"
},
  "geometry": {"coordinates":[-2.1572289467,53.618221283],"type":"Point"}
}