{
  "type": "Feature",
  "properties": {
    "addr:full":"4 Bertram Road Bradford West Yorkshire BD8 7LN",
    "addr:housenumber":"4",
    "addr:postcode":"bd8 7ln",
    "addr:street":"Bertram Road",
    "iso:country":"GB",
    "sg:address":"4 Bertram Road",
    "sg:city":"Bradford",
    "sg:classifiers":[
        {
            "category":"Health Services",
            "subcategory":"Doctor",
            "type":"Services"
        }
    ],
    "sg:phone":"+44 1274 493345",
    "sg:postcode":"BD8 7LN",
    "sg:province":"West Yorkshire",
    "sg:tags":[
        "practitioners"
    ],
    "wof:name":"Bradford District Health Authority",
    "wof:placetype":"venue"
},
  "geometry": {"coordinates":[-1.7686049938,53.8068275452],"type":"Point"}
}