{
  "type": "Feature",
  "properties": {
    "iso:country":"GB",
    "sg:address":"Swinton Bridge Industrial Estate",
    "sg:city":"Mexborough",
    "sg:classifiers":[
        {
            "category":"Building & Trades",
            "subcategory":"Construction",
            "type":"Services"
        }
    ],
    "sg:phone":"+44 1709 588909",
    "sg:postcode":"S64 8BH",
    "sg:province":"South Yorkshire",
    "sg:tags":[
        "roofing"
    ],
    "wof:name":"Valley Projects Ltd.",
    "wof:placetype":"venue"
},
  "geometry": {"coordinates":[-1.317869,53.487766],"type":"Point"}
}