{
  "type": "Feature",
  "properties": {
    "iso:country":"GB",
    "sg:address":"6 St Annes Square",
    "sg:city":"Barmouth",
    "sg:classifiers":[
        {
            "category":"Food & Beverages",
            "subcategory":"Meat & Fish",
            "type":"Retail Goods"
        }
    ],
    "sg:postcode":"LL42 1DL",
    "sg:province":"Gwynedd",
    "sg:tags":[
        "butcher"
    ],
    "wof:name":"Peter Grundy Butchers",
    "wof:placetype":"venue"
},
  "geometry": {"coordinates":[-4.054729,52.722519],"type":"Point"}
}