{
  "type": "Feature",
  "properties": {
    "addr:full":"Velfrey Road Whitland Carmarthenshire SA34 0QX",
    "addr:postcode":"sa34 0qx",
    "addr:street":"Velfrey Road",
    "iso:country":"GB",
    "sg:address":"Velfrey Road",
    "sg:city":"Whitland",
    "sg:classifiers":[
        {
            "category":"Social Services",
            "subcategory":"Retirement Home",
            "type":"Services"
        }
    ],
    "sg:phone":"+44 1994 240232",
    "sg:postcode":"SA34 0QX",
    "sg:province":"Carmarthenshire",
    "sg:tags":[
        "residential",
        "care"
    ],
    "wof:name":"Waungron Mansion Residential Home",
    "wof:placetype":"venue"
},
  "geometry": {"coordinates":[-4.620835,51.812527],"type":"Point"}
}