{
  "type": "Feature",
  "properties": {
    "iso:country":"GB",
    "sg:address":"67 Longridge Avenue, Saltdean",
    "sg:city":"Brighton",
    "sg:classifiers":[
        {
            "category":"Bars & Pubs",
            "type":"Food & Drink"
        }
    ],
    "sg:phone":"+44 1273 302564",
    "sg:postcode":"BN2 8LG",
    "sg:province":"East Sussex",
    "sg:tags":[
        "pubs",
        "inn"
    ],
    "wof:name":"Gullens",
    "wof:placetype":"venue"
},
  "geometry": {"coordinates":[-0.036595,50.801334],"type":"Point"}
}