{
  "type": "Feature",
  "properties": {
    "addr:full":"Building 62, Pesnett Trading Estate, Kingswinford Brierley Hill Staffordshire DY6 7XT",
    "addr:postcode":"dy6 7xt",
    "iso:country":"GB",
    "sg:address":"Building 62, Pesnett Trading Estate, Kingswinford",
    "sg:city":"Brierley Hill",
    "sg:classifiers":[
        {
            "category":"Shopping",
            "subcategory":"Clothing, Apparel, & Fashions",
            "type":"Retail Goods"
        }
    ],
    "sg:phone":"+44 1384 401071",
    "sg:postcode":"DY6 7XT",
    "sg:province":"Staffordshire",
    "sg:tags":[
        "clothing",
        "fabric"
    ],
    "wof:name":"John Matthews Clothing Ltd.",
    "wof:placetype":"venue"
},
  "geometry": {"coordinates":[-2.1536099911,52.5043106079],"type":"Point"}
}