{
  "type": "Feature",
  "properties": {
    "addr:full":"Cobdown Sports Club, Station Road, Ditton Aylesford Kent ME20 6AU",
    "addr:postcode":"me20 6au",
    "addr:street":"Station Road;Aylesford",
    "iso:country":"GB",
    "sg:address":"Cobdown Sports Club, Station Road, Ditton",
    "sg:city":"Aylesford",
    "sg:classifiers":[
        {
            "category":"Shopping",
            "subcategory":"Pharmacy",
            "type":"Retail Goods"
        }
    ],
    "sg:phone":"+44 1622 719799",
    "sg:postcode":"ME20 6AU",
    "sg:province":"Kent",
    "sg:tags":[
        "medicine",
        "therapy"
    ],
    "wof:name":"Hands on Health",
    "wof:placetype":"venue"
},
  "geometry": {"coordinates":[0.453373,51.299339],"type":"Point"}
}