{
  "type": "Feature",
  "properties": {
    "addr:full":"30-36 Upper York Street, St Pauls Bristol City of Bristol BS2 8QL",
    "addr:housenumber":"30-36",
    "addr:postcode":"bs2 8ql",
    "addr:street":"Upper York Street",
    "iso:country":"GB",
    "sg:address":"30-36 Upper York Street, St Pauls",
    "sg:city":"Bristol",
    "sg:classifiers":[
        {
            "category":"Communications",
            "subcategory":"Film & Video Production",
            "type":"Services"
        }
    ],
    "sg:phone":"+44 117 924 9494",
    "sg:postcode":"BS2 8QL",
    "sg:province":"City of Bristol",
    "sg:tags":[
        "curers",
        "bacon",
        "ham"
    ],
    "wof:name":"H H Brain Ltd.",
    "wof:placetype":"venue"
},
  "geometry": {"coordinates":[-2.589542,51.461784],"type":"Point"}
}