{
  "type": "Feature",
  "properties": {
    "addr:full":"18 & 22 High Street, Ardersier Inverness Highland IV2 7QB",
    "addr:housenumber":"18 & 22",
    "addr:postcode":"iv2 7qb",
    "addr:street":"High Street;Inverness",
    "iso:country":"GB",
    "sg:address":"18 & 22 High Street, Ardersier",
    "sg:city":"Inverness",
    "sg:classifiers":[
        {
            "category":"Community Center",
            "subcategory":"Social",
            "type":"Public Place"
        }
    ],
    "sg:postcode":"IV2 7QB",
    "sg:province":"Highland",
    "sg:tags":[
        "furnishers",
        "contract"
    ],
    "wof:name":"Roderick McPherson Furnishing Interiorss",
    "wof:placetype":"venue"
},
  "geometry": {"coordinates":[-4.038616,57.57151],"type":"Point"}
}