{
  "type": "Feature",
  "properties": {
    "iso:country":"GB",
    "sg:address":"5a Factory Rd, Upton Indstl Est, Upton",
    "sg:city":"Poole",
    "sg:classifiers":[
        {
            "category":"Manufacturing",
            "subcategory":"Signs",
            "type":"Manufacturing & Wholesale Goods"
        }
    ],
    "sg:postcode":"BH16 5SL",
    "sg:province":"Dorset",
    "sg:tags":[
        "writer"
    ],
    "wof:name":"Roper,Robert C,",
    "wof:placetype":"venue"
},
  "geometry": {"coordinates":[-2.024181,50.735832],"type":"Point"}
}