{
  "type": "Feature",
  "properties": {
    "addr:full":"Forge Close Bromley Kent BR2 7LL",
    "addr:postcode":"br2 7ll",
    "addr:street":"Forge Close",
    "iso:country":"GB",
    "sg:address":"Forge Close",
    "sg:city":"Bromley",
    "sg:classifiers":[
        {
            "category":"Health Services",
            "subcategory":"Doctor",
            "type":"Services"
        },
        {
            "category":"Health Services",
            "subcategory":"Clinic",
            "type":"Services"
        }
    ],
    "sg:phone":"+44 20 8462 1601",
    "sg:postcode":"BR2 7LL",
    "sg:province":"Kent",
    "sg:tags":[
        "nh",
        "practitioners"
    ],
    "wof:name":"The Surgery",
    "wof:placetype":"venue"
},
  "geometry": {"coordinates":[0.016221,51.377106],"type":"Point"}
}