{
  "type": "Feature",
  "properties": {
    "addr:full":"3 Station Buildings, Fife Road Kingston Upon Thames Greater London KT1 1SW",
    "addr:housenumber":"3",
    "addr:postcode":"kt1 1sw",
    "addr:street":"Station Buildings Fife Road",
    "iso:country":"GB",
    "sg:address":"3 Station Buildings, Fife Road",
    "sg:city":"Kingston Upon Thames",
    "sg:classifiers":[
        {
            "category":"Professional",
            "subcategory":"Computer Services",
            "type":"Services"
        }
    ],
    "sg:phone":"+44 20 8546 7880",
    "sg:postcode":"KT1 1SW",
    "sg:province":"Greater London",
    "sg:tags":[
        "system",
        "software"
    ],
    "wof:name":"Morgan Computer Co",
    "wof:placetype":"venue"
},
  "geometry": {"coordinates":[-0.30112,51.412071],"type":"Point"}
}