{
  "type": "Feature",
  "properties": {
    "addr:full":"31 The Avenue Kilburn Greater London NW6 7NR",
    "addr:housenumber":"31",
    "addr:postcode":"nw6 7nr",
    "addr:street":"The Avenue",
    "iso:country":"GB",
    "sg:address":"31 The Avenue",
    "sg:city":"Kilburn",
    "sg:classifiers":[
        {
            "category":"Health Services",
            "subcategory":"Health Practitioner",
            "type":"Services"
        }
    ],
    "sg:phone":"+44 20 8451 2530",
    "sg:postcode":"NW6 7NR",
    "sg:province":"Greater London",
    "sg:tags":[
        "acupuncture"
    ],
    "wof:name":"Michelle Cowie",
    "wof:placetype":"venue"
},
  "geometry": {"coordinates":[-0.2119449973,51.5407104492],"type":"Point"}
}