{
  "type": "Feature",
  "properties": {
    "addr:full":"129 Coed Camlas, New Inn Pontypool Monmouthshire NP4 8RP",
    "addr:housenumber":"129",
    "addr:postcode":"np4 8rp",
    "addr:street":"Coed Camlas",
    "iso:country":"GB",
    "sg:address":"129 Coed Camlas, New Inn",
    "sg:city":"Pontypool",
    "sg:classifiers":[
        {
            "category":"Building & Trades",
            "subcategory":"Construction",
            "type":"Services"
        }
    ],
    "sg:postcode":"NP4 8RP",
    "sg:province":"Monmouthshire",
    "sg:tags":[
        "roofing"
    ],
    "wof:name":"Aberclad Ltd.",
    "wof:placetype":"venue"
},
  "geometry": {"coordinates":[-3.04319,51.703087],"type":"Point"}
}