{
  "type": "Feature",
  "properties": {
    "iso:country":"GB",
    "sg:address":"65 Farm Fields",
    "sg:city":"South Croydon",
    "sg:classifiers":[
        {
            "category":"Building & Trades",
            "subcategory":"Landscaping Services",
            "type":"Services"
        },
        {
            "category":"Professional",
            "subcategory":"Management & Consulting",
            "type":"Services"
        }
    ],
    "sg:postcode":"CR2 0HR",
    "sg:province":"Surrey",
    "sg:tags":[
        "consultant",
        "training"
    ],
    "wof:name":"Michael Mitchell",
    "wof:placetype":"venue"
},
  "geometry": {"coordinates":[-0.080687,51.340569],"type":"Point"}
}