{
  "type": "Feature",
  "properties": {
    "addr:full":"Cameron Buildings Bromley Common Bromley Kent BR2 8HA",
    "addr:postcode":"br2 8ha",
    "addr:street":"Cameron;Bromley Common",
    "iso:country":"GB",
    "sg:address":"Cameron Buildings Bromley Common",
    "sg:city":"Bromley",
    "sg:classifiers":[
        {
            "category":"Professional",
            "subcategory":"Accounting & Tax Preparation",
            "type":"Services"
        }
    ],
    "sg:phone":"+44 20 8462 9238",
    "sg:postcode":"BR2 8HA",
    "sg:province":"Kent",
    "sg:tags":[
        "accountant"
    ],
    "wof:name":"Atkins & Co",
    "wof:placetype":"venue"
},
  "geometry": {"coordinates":[0.03573,51.388351],"type":"Point"}
}