{
  "type": "Feature",
  "properties": {
    "addr:full":"17 Meadow Drive, Credenhill Hereford Herefordshire HR4 7EF",
    "addr:housenumber":"17",
    "addr:postcode":"hr4 7ef",
    "addr:street":"Meadow Drive",
    "iso:country":"GB",
    "sg:address":"17 Meadow Drive, Credenhill",
    "sg:city":"Hereford",
    "sg:classifiers":[
        {
            "category":"Food & Beverages",
            "subcategory":"Bakery",
            "type":"Retail Goods"
        }
    ],
    "sg:phone":"+44 1432 761829",
    "sg:postcode":"HR4 7EF",
    "sg:province":"Herefordshire",
    "sg:tags":[
        "baker"
    ],
    "wof:name":"The Bakers Dozen",
    "wof:placetype":"venue"
},
  "geometry": {"coordinates":[-2.80583,52.084061],"type":"Point"}
}