{
  "type": "Feature",
  "properties": {
    "iso:country":"GB",
    "sg:address":"275 Wallasey Village",
    "sg:city":"Wallasey",
    "sg:classifiers":[
        {
            "category":"Home & Garden",
            "subcategory":"Hardware",
            "type":"Retail Goods"
        }
    ],
    "sg:phone":"+44 151 637 2227",
    "sg:postcode":"CH45 3LR",
    "sg:province":"Merseyside",
    "sg:tags":[
        "retailer",
        "diy"
    ],
    "wof:name":"Village D I Y",
    "wof:placetype":"venue"
},
  "geometry": {"coordinates":[-3.067766,53.427498],"type":"Point"}
}