{
  "type": "Feature",
  "properties": {
    "addr:full":"Ivyhouse Lane Bilston West Midlands WV14 9JH",
    "addr:postcode":"wv14 9jh",
    "addr:street":"Ivyhouse Lane",
    "iso:country":"GB",
    "sg:address":"Ivyhouse Lane",
    "sg:city":"Bilston",
    "sg:classifiers":[
        {
            "category":"Fast Food",
            "type":"Food & Drink"
        }
    ],
    "sg:phone":"+44 1902 885807",
    "sg:postcode":"WV14 9JH",
    "sg:province":"West Midlands",
    "sg:tags":[
        "away",
        "take"
    ],
    "wof:name":"McDonalds Restaurants Ltd.",
    "wof:placetype":"venue"
},
  "geometry": {"coordinates":[-2.088404,52.543686],"type":"Point"}
}