{
  "type": "Feature",
  "properties": {
    "addr:full":"88 St Georges Road, Forest Gate London Greater London E7 8HY",
    "addr:housenumber":"88",
    "addr:postcode":"e7 8hy",
    "addr:street":"St Georges Road",
    "iso:country":"GB",
    "sg:address":"88 St Georges Road, Forest Gate",
    "sg:city":"London",
    "sg:classifiers":[
        {
            "category":"Building & Trades",
            "subcategory":"Pest Control",
            "type":"Services"
        }
    ],
    "sg:postcode":"E7 8HY",
    "sg:province":"Greater London",
    "sg:tags":[
        "fastener"
    ],
    "wof:name":"Euro Buckles",
    "wof:placetype":"venue"
},
  "geometry": {"coordinates":[0.029929,51.541843],"type":"Point"}
}