{
  "type": "Feature",
  "properties": {
    "addr:full":"30a High Street, Stony Stratford Milton Keynes Buckinghamshire MK11 1AF",
    "addr:housenumber":"30a",
    "addr:postcode":"mk11 1af",
    "addr:street":"High Street",
    "iso:country":"GB",
    "sg:address":"30a High Street, Stony Stratford",
    "sg:city":"Milton Keynes",
    "sg:classifiers":[
        {
            "category":"Real Estate",
            "subcategory":"Developer",
            "type":"Services"
        }
    ],
    "sg:phone":"+44 1908 556600",
    "sg:postcode":"MK11 1AF",
    "sg:province":"Buckinghamshire",
    "sg:tags":[
        "property"
    ],
    "wof:name":"Rushmere Properties Ltd.",
    "wof:placetype":"venue"
},
  "geometry": {"coordinates":[-0.852083,52.056641],"type":"Point"}
}