{
  "type": "Feature",
  "properties": {
    "addr:full":"386 Neasden Lane North London Greater London NW10 0BT",
    "addr:housenumber":"386",
    "addr:postcode":"nw10 0bt",
    "addr:street":"Neasden Lane North",
    "iso:country":"GB",
    "sg:address":"386 Neasden Lane North",
    "sg:city":"London",
    "sg:classifiers":[
        {
            "category":"Manufacturing",
            "subcategory":"Signs",
            "type":"Manufacturing & Wholesale Goods"
        },
        {
            "category":"Communications",
            "type":"Services"
        }
    ],
    "sg:phone":"+44 20 8450 4241",
    "sg:postcode":"NW10 0BT",
    "sg:province":"Greater London",
    "sg:tags":[
        "tv",
        "radio",
        "video",
        "nameplate"
    ],
    "wof:name":"Media",
    "wof:placetype":"venue"
},
  "geometry": {"coordinates":[-0.254519999,51.5612068176],"type":"Point"}
}