{
  "type": "Feature",
  "properties": {
    "iso:country":"GB",
    "sg:address":"Sutton Road, Langley",
    "sg:city":"Maidstone",
    "sg:classifiers":[
        {
            "category":"Shopping",
            "subcategory":"Bicycles & Sporting Goods",
            "type":"Retail Goods"
        }
    ],
    "sg:postcode":"ME17 3NF",
    "sg:province":"Kent",
    "sg:tags":[
        "riding",
        "saddlery",
        "wear"
    ],
    "wof:name":"Birchalls the Riding Shop",
    "wof:placetype":"venue"
},
  "geometry": {"coordinates":[0.585466,51.231976],"type":"Point"}
}