{
  "type": "Feature",
  "properties": {
    "addr:full":"Keens Farm, Coakers Lane, Debach Woodbridge Suffolk IP13 6BX",
    "addr:postcode":"ip13 6bx",
    "addr:street":"Coakers Lane",
    "iso:country":"GB",
    "sg:address":"Keens Farm, Coakers Lane, Debach",
    "sg:city":"Woodbridge",
    "sg:classifiers":[
        {
            "category":"Farming",
            "subcategory":"Livestock Farm",
            "type":"Manufacturing & Wholesale Goods"
        }
    ],
    "sg:phone":"+44 1473 737874",
    "sg:postcode":"IP13 6BX",
    "sg:province":"Suffolk",
    "sg:tags":[
        "others"
    ],
    "wof:name":"J C Pirkis & Son",
    "wof:placetype":"venue"
},
  "geometry": {"coordinates":[1.275315,52.142654],"type":"Point"}
}