{
  "type": "Feature",
  "properties": {
    "addr:full":"20 Treloggan Lane Newquay Cornwall TR7 2JN",
    "addr:housenumber":"20",
    "addr:postcode":"tr7 2jn",
    "addr:street":"Treloggan Lane",
    "iso:country":"GB",
    "sg:address":"20 Treloggan Lane",
    "sg:city":"Newquay",
    "sg:classifiers":[
        {
            "category":"Building & Trades",
            "subcategory":"Cleaning & Sanitation",
            "type":"Services"
        },
        {
            "category":"Home & Garden",
            "subcategory":"Carpets & Floor Coverings",
            "type":"Retail Goods"
        }
    ],
    "sg:phone":"+44 1637 878835",
    "sg:postcode":"TR7 2JN",
    "sg:province":"Cornwall",
    "sg:tags":[
        "cleaner",
        "upholstery"
    ],
    "wof:name":"Newquay Cleaning Services",
    "wof:placetype":"venue"
},
  "geometry": {"coordinates":[-5.067215,50.406849],"type":"Point"}
}