{
  "type": "Feature",
  "properties": {
    "addr:full":"Oak Tree House, Langhurst Wood Road Horsham West Sussex RH12 4QD",
    "addr:postcode":"rh12 4qd",
    "addr:street":"Langhurst Wood Road",
    "iso:country":"GB",
    "sg:address":"Oak Tree House, Langhurst Wood Road",
    "sg:city":"Horsham",
    "sg:classifiers":[
        {
            "category":"Building & Trades",
            "subcategory":"Construction",
            "type":"Services"
        }
    ],
    "sg:phone":"+44 1403 256512",
    "sg:postcode":"RH12 4QD",
    "sg:province":"West Sussex",
    "sg:tags":[
        "builder"
    ],
    "wof:name":"D C Construction",
    "wof:placetype":"venue"
},
  "geometry": {"coordinates":[-0.314728,51.110069],"type":"Point"}
}