{
  "type": "Feature",
  "properties": {
    "addr:full":"P O Box 165 Reading Berkshire RG6 4LD",
    "addr:housenumber":"165",
    "addr:postcode":"rg6 4ld",
    "addr:street":"P O Box",
    "iso:country":"GB",
    "sg:address":"P O Box 165",
    "sg:city":"Reading",
    "sg:classifiers":[
        {
            "category":"Professional",
            "subcategory":"Management & Consulting",
            "type":"Services"
        }
    ],
    "sg:phone":"+44 118 941 0471",
    "sg:postcode":"RG6 4LD",
    "sg:province":"Berkshire",
    "sg:tags":[
        "conservation"
    ],
    "wof:name":"Berkshire Conservation Volunteers",
    "wof:placetype":"venue"
},
  "geometry": {"coordinates":[-0.922389,51.42458],"type":"Point"}
}