{
  "type": "Feature",
  "properties": {
    "addr:full":"Lichfield Buildings, Middlemore Lane West Walsall Staffordshire WS9 8BG",
    "addr:postcode":"ws9 8bg",
    "addr:street":"Middlemore Lane West",
    "iso:country":"GB",
    "sg:address":"Lichfield Buildings, Middlemore Lane West",
    "sg:city":"Walsall",
    "sg:classifiers":[
        {
            "category":"Utilities",
            "type":"Services"
        }
    ],
    "sg:phone":"+44 1922 745525",
    "sg:postcode":"WS9 8BG",
    "sg:province":"Staffordshire",
    "sg:tags":[
        "internet"
    ],
    "wof:name":"Internet Marketing & Consultancy",
    "wof:placetype":"venue"
},
  "geometry": {"coordinates":[-1.943588,52.601982],"type":"Point"}
}