{
  "type": "Feature",
  "properties": {
    "addr:full":"Birdingbury Fields Farm, Collingham Lane, Stockton Rugby Northamptonshire CV23 8HL",
    "addr:postcode":"cv23 8hl",
    "addr:street":"Birdingbury Fields Farm Collingham Lane",
    "iso:country":"GB",
    "sg:address":"Birdingbury Fields Farm, Collingham Lane, Stockton",
    "sg:city":"Rugby",
    "sg:classifiers":[
        {
            "category":"Farming",
            "subcategory":"Dairy Farm",
            "type":"Manufacturing & Wholesale Goods"
        }
    ],
    "sg:postcode":"CV23 8HL",
    "sg:province":"Northamptonshire",
    "wof:name":"G M & Sons Bostock",
    "wof:placetype":"venue"
},
  "geometry": {"coordinates":[-1.368103981,52.3116493225],"type":"Point"}
}