{
  "type": "Feature",
  "properties": {
    "addr:full":"245 Amhurst Road London Greater London N16 7UN",
    "addr:housenumber":"245",
    "addr:postcode":"n16 7un",
    "addr:street":"Amhurst Road",
    "iso:country":"GB",
    "sg:address":"245 Amhurst Road",
    "sg:city":"London",
    "sg:classifiers":[
        {
            "category":"Wholesale",
            "subcategory":"Construction Materials",
            "type":"Manufacturing & Wholesale Goods"
        },
        {
            "category":"Building & Trades",
            "subcategory":"Construction",
            "type":"Services"
        }
    ],
    "sg:phone":"+44 20 7254 1132",
    "sg:postcode":"N16 7UN",
    "sg:province":"Greater London",
    "sg:tags":[
        "merchant",
        "glass",
        "glazier"
    ],
    "wof:name":"Ward Glass",
    "wof:placetype":"venue"
},
  "geometry": {"coordinates":[-0.0687929988,51.5548171997],"type":"Point"}
}