{
  "type": "Feature",
  "properties": {
    "addr:full":"397 Topsham Road Exeter Devon EX2 6HD",
    "addr:housenumber":"397",
    "addr:postcode":"ex2 6hd",
    "addr:street":"Topsham Road",
    "iso:country":"GB",
    "sg:address":"397 Topsham Road",
    "sg:city":"Exeter",
    "sg:classifiers":[
        {
            "category":"Professional",
            "subcategory":"Accounting & Tax Preparation",
            "type":"Services"
        }
    ],
    "sg:phone":"+44 1392 877706",
    "sg:postcode":"EX2 6HD",
    "sg:province":"Devon",
    "sg:tags":[
        "accountant"
    ],
    "wof:name":"Stephen J Bright",
    "wof:placetype":"venue"
},
  "geometry": {"coordinates":[-3.502899,50.7057],"type":"Point"}
}