{
  "type": "Feature",
  "properties": {
    "iso:country":"GB",
    "sg:address":"Arch Lane, Garswood, Ashton-in-makerfieldlane",
    "sg:city":"Wigan",
    "sg:classifiers":[
        {
            "category":"Home & Garden",
            "subcategory":"Building Materials",
            "type":"Retail Goods"
        }
    ],
    "sg:phone":"+44 1744 892446",
    "sg:postcode":"WN4 0XL",
    "sg:province":"Lancashire",
    "sg:tags":[
        "roofing"
    ],
    "wof:name":"Pre Seal (Boards) Ltd.",
    "wof:placetype":"venue"
},
  "geometry": {"coordinates":[-2.6883189678,53.487159729],"type":"Point"}
}