{
  "type": "Feature",
  "properties": {
    "addr:full":"2c Albert Street Derby Derbyshire DE1 2DS",
    "addr:housenumber":"2c",
    "addr:postcode":"de1 2ds",
    "addr:street":"Albert Street",
    "iso:country":"GB",
    "sg:address":"2c Albert Street",
    "sg:city":"Derby",
    "sg:classifiers":[
        {
            "category":"Shopping",
            "subcategory":"Thrift Store",
            "type":"Retail Goods"
        },
        {
            "category":"Organizations",
            "subcategory":"Non-profit Organization",
            "type":"Services"
        }
    ],
    "sg:phone":"+44 1332 345641",
    "sg:postcode":"DE1 2DS",
    "sg:province":"Derbyshire",
    "sg:tags":[
        "shop",
        "charitable",
        "organisation",
        "charity"
    ],
    "wof:name":"OXFAM",
    "wof:placetype":"venue"
},
  "geometry": {"coordinates":[-1.4753090143,52.9218788147],"type":"Point"}
}