{
  "type": "Feature",
  "properties": {
    "addr:full":"46 Thornhill Park Road Southampton Hampshire SO18 5TP",
    "addr:housenumber":"46",
    "addr:postcode":"so18 5tp",
    "addr:street":"Thornhill Park Road",
    "iso:country":"GB",
    "sg:address":"46 Thornhill Park Road",
    "sg:city":"Southampton",
    "sg:classifiers":[
        {
            "category":"Fast Food",
            "type":"Food & Drink"
        }
    ],
    "sg:postcode":"SO18 5TP",
    "sg:province":"Hampshire",
    "sg:tags":[
        "away",
        "take"
    ],
    "wof:name":"Subhan A",
    "wof:placetype":"venue"
},
  "geometry": {"coordinates":[-1.336648941,50.9145126343],"type":"Point"}
}