{
  "type": "Feature",
  "properties": {
    "iso:country":"GB",
    "sg:address":"Ivy Cottage Church Lane, Wolverton, Tadley",
    "sg:city":"Basingstoke",
    "sg:classifiers":[
        {
            "category":"Utilities",
            "subcategory":"Fuel Oil & Lpg",
            "type":"Services"
        }
    ],
    "sg:postcode":"RG26 5RU",
    "sg:province":"Berkshire",
    "sg:tags":[
        "coal",
        "smokeless"
    ],
    "wof:name":"C S Mortimer & Son",
    "wof:placetype":"venue"
},
  "geometry": {"coordinates":[-1.2056939602,51.3206062317],"type":"Point"}
}