{
  "type": "Feature",
  "properties": {
    "addr:full":"69 High Street, Market Deeping Peterborough Cambridgeshire PE6 8ED",
    "addr:housenumber":"69",
    "addr:postcode":"pe6 8ed",
    "addr:street":"High Street;Peterborough",
    "iso:country":"GB",
    "sg:address":"69 High Street, Market Deeping",
    "sg:city":"Peterborough",
    "sg:classifiers":[
        {
            "category":"Food & Beverages",
            "subcategory":"Dairy",
            "type":"Retail Goods"
        }
    ],
    "sg:postcode":"PE6 8ED",
    "sg:province":"Cambridgeshire",
    "sg:tags":[
        "produce"
    ],
    "wof:name":"H & M E Beeby",
    "wof:placetype":"venue"
},
  "geometry": {"coordinates":[-0.312431,52.674328],"type":"Point"}
}