{
  "type": "Feature",
  "properties": {
    "addr:full":"17 Old Row, Burton Upon Stather Scunthorpe Lincolnshire DN15 9DL",
    "addr:housenumber":"17",
    "addr:postcode":"dn15 9dl",
    "addr:street":"Old Row",
    "iso:country":"GB",
    "sg:address":"17 Old Row, Burton Upon Stather",
    "sg:city":"Scunthorpe",
    "sg:classifiers":[
        {
            "category":"Professional",
            "type":"Services"
        }
    ],
    "sg:phone":"+44 1724 720754",
    "sg:postcode":"DN15 9DL",
    "sg:province":"Lincolnshire",
    "sg:tags":[
        "repair",
        "tech",
        "maintenance"
    ],
    "wof:name":"Net-worx",
    "wof:placetype":"venue"
},
  "geometry": {"coordinates":[-0.6913660169,53.6533737183],"type":"Point"}
}