{
  "type": "Feature",
  "properties": {
    "iso:country":"GB",
    "sg:address":"5 Kenwood Gardens",
    "sg:city":"Ilford",
    "sg:classifiers":[
        {
            "category":"Building & Trades",
            "subcategory":"Construction",
            "type":"Services"
        }
    ],
    "sg:postcode":"IG2 6YH",
    "sg:province":"Essex",
    "sg:tags":[
        "roofing"
    ],
    "wof:name":"K B S Roofing",
    "wof:placetype":"venue"
},
  "geometry": {"coordinates":[0.067587,51.581429],"type":"Point"}
}