{
  "type": "Feature",
  "properties": {
    "iso:country":"GB",
    "sg:address":"14 Otley Road",
    "sg:city":"Shipley",
    "sg:classifiers":[
        {
            "category":"Shopping",
            "type":"Retail Goods"
        }
    ],
    "sg:phone":"+44 1274 595728",
    "sg:postcode":"BD17 7SE",
    "sg:province":"West Yorkshire",
    "sg:tags":[
        "med",
        "scientific",
        "apparatus"
    ],
    "wof:name":"Don Whitley Scientific Ltd.",
    "wof:placetype":"venue"
},
  "geometry": {"coordinates":[-1.7742760181,53.83568573],"type":"Point"}
}