{
  "type": "Feature",
  "properties": {
    "addr:full":"1 Monica Road, Braunstone Leicester Leicestershire LE3 2PR",
    "addr:housenumber":"1",
    "addr:postcode":"le3 2pr",
    "addr:street":"Monica Road",
    "iso:country":"GB",
    "sg:address":"1 Monica Road, Braunstone",
    "sg:city":"Leicester",
    "sg:classifiers":[
        {
            "category":"Shopping",
            "subcategory":"Pharmacy",
            "type":"Retail Goods"
        }
    ],
    "sg:phone":"+44 116 289 5826",
    "sg:postcode":"LE3 2PR",
    "sg:province":"Leicestershire",
    "sg:tags":[
        "pharmacist",
        "chemist"
    ],
    "wof:name":"Sonichem Pharmacy",
    "wof:placetype":"venue"
},
  "geometry": {"coordinates":[-1.1751840115,52.6065139771],"type":"Point"}
}