{
  "type": "Feature",
  "properties": {
    "iso:country":"GB",
    "sg:address":"Priory Park Lodge, Aberford",
    "sg:city":"Leeds",
    "sg:classifiers":[
        {
            "category":"Real Estate",
            "subcategory":"Architect",
            "type":"Services"
        }
    ],
    "sg:phone":"+44 113 281 2020",
    "sg:postcode":"LS25 3DF",
    "sg:province":"North Yorkshire",
    "sg:website":"http://www.humphreysteal.com",
    "wof:name":"The Humphreys Teal Partnership",
    "wof:placetype":"venue"
},
  "geometry": {"coordinates":[-1.343052,53.829151],"type":"Point"}
}