{
  "type": "Feature",
  "properties": {
    "addr:full":"8a Lune Street Preston Lancashire PR1 2NL",
    "addr:housenumber":"8a",
    "addr:postcode":"pr1 2nl",
    "addr:street":"Lune Street",
    "iso:country":"GB",
    "sg:address":"8a Lune Street",
    "sg:city":"Preston",
    "sg:classifiers":[
        {
            "category":"Shopping",
            "subcategory":"Clothing, Apparel, & Fashions",
            "type":"Retail Goods"
        }
    ],
    "sg:phone":"+44 1772 823400",
    "sg:postcode":"PR1 2NL",
    "sg:province":"Lancashire",
    "sg:tags":[
        "shop",
        "menswear"
    ],
    "wof:name":"Mr Jethwa Menswear",
    "wof:placetype":"venue"
},
  "geometry": {"coordinates":[-2.703269,53.758526],"type":"Point"}
}