{
  "type": "Feature",
  "properties": {
    "iso:country":"GB",
    "sg:address":"Church End, Lyneham",
    "sg:city":"Chippenham",
    "sg:classifiers":[
        {
            "category":"Cinema",
            "subcategory":"Movie Rental",
            "type":"Entertainment"
        }
    ],
    "sg:phone":"+44 1249 890304",
    "sg:postcode":"SN15 4DQ",
    "sg:province":"Wiltshire",
    "sg:tags":[
        "video",
        "library"
    ],
    "wof:name":"Videos Plus",
    "wof:placetype":"venue"
},
  "geometry": {"coordinates":[-1.96827,51.507179],"type":"Point"}
}