{
  "type": "Feature",
  "properties": {
    "addr:full":"114 Green Lane Walsall West Midlands WS2 8HX",
    "addr:housenumber":"114",
    "addr:postcode":"ws2 8hx",
    "addr:street":"Green Lane",
    "iso:country":"GB",
    "sg:address":"114 Green Lane",
    "sg:city":"Walsall",
    "sg:classifiers":[
        {
            "category":"Personal",
            "subcategory":"Beauty Salon",
            "type":"Services"
        }
    ],
    "sg:postcode":"WS2 8HX",
    "sg:province":"West Midlands",
    "sg:tags":[
        "unisex",
        "hairdresser"
    ],
    "wof:name":"Crowning Glory Hair Design",
    "wof:placetype":"venue"
},
  "geometry": {"coordinates":[-1.989886,52.591225],"type":"Point"}
}