{
  "type": "Feature",
  "properties": {
    "addr:full":"Elmbridge Ct, Cheltenham Rd Gloucester Gloucestershire GL3 1AG",
    "addr:postcode":"gl3 1ag",
    "addr:street":"Elmbridge Ct Cheltenham Rd",
    "iso:country":"GB",
    "sg:address":"Elmbridge Ct, Cheltenham Rd",
    "sg:city":"Gloucester",
    "sg:classifiers":[
        {
            "category":"Government",
            "subcategory":"Office",
            "type":"Public Place"
        }
    ],
    "sg:phone":"+44 1452 316400",
    "sg:postcode":"GL3 1AG",
    "sg:province":"Gloucestershire",
    "sg:tags":[
        "central"
    ],
    "wof:name":"Agriculture Fisheries & Food Ministry Of",
    "wof:placetype":"venue"
},
  "geometry": {"coordinates":[-2.20181,51.884289],"type":"Point"}
}