{
  "type": "Feature",
  "properties": {
    "iso:country":"GB",
    "sg:address":"122 Potter St",
    "sg:city":"Worksop",
    "sg:classifiers":[
        {
            "category":"Retail",
            "subcategory":"Auto Repair",
            "type":"Services"
        }
    ],
    "sg:postcode":"S80 2HP",
    "sg:province":"Nottinghamshire",
    "sg:tags":[
        "modification",
        "garage"
    ],
    "wof:name":"Lamb,Martin William,",
    "wof:placetype":"venue"
},
  "geometry": {"coordinates":[-1.1173789501,53.3026008606],"type":"Point"}
}