{
  "type": "Feature",
  "properties": {
    "iso:country":"GB",
    "sg:address":"9 Page Moss Parade, Huyton",
    "sg:city":"Liverpool",
    "sg:classifiers":[
        {
            "category":"Food & Beverages",
            "subcategory":"Liquor & Beverages",
            "type":"Retail Goods"
        }
    ],
    "sg:phone":"+44 151 480 5300",
    "sg:postcode":"L36 2PA",
    "sg:province":"Merseyside",
    "sg:tags":[
        "beer",
        "wine",
        "spirit",
        "wines"
    ],
    "wof:name":"BARGAIN BOOZE LTD",
    "wof:placetype":"venue"
},
  "geometry": {"coordinates":[-2.862198,53.421253],"type":"Point"}
}