{
  "type": "Feature",
  "properties": {
    "iso:country":"GB",
    "sg:address":"74 The Parade, Oadby",
    "sg:city":"Leicester",
    "sg:classifiers":[
        {
            "category":"Insurance",
            "subcategory":"Insurance Agent",
            "type":"Services"
        }
    ],
    "sg:phone":"+44 116 271 0011",
    "sg:postcode":"LE2 5BF",
    "sg:province":"Leicestershire",
    "sg:tags":[
        "broker"
    ],
    "sg:website":"http://www.cjbott.com",
    "wof:name":"C J Bott Insurance Brokers Ltd.",
    "wof:placetype":"venue"
},
  "geometry": {"coordinates":[-1.084011,52.599781],"type":"Point"}
}