{
  "type": "Feature",
  "properties": {
    "addr:full":"Unit 1 & 2 Black Lake Indust Est West Bromwich West Midlands B70 0NS",
    "addr:housenumber":"unit 1 & 2",
    "addr:postcode":"b70 0ns",
    "addr:street":"Black Lake Indust Est",
    "iso:country":"GB",
    "sg:address":"Unit 1 & 2 Black Lake Indust Est",
    "sg:city":"West Bromwich",
    "sg:classifiers":[
        {
            "category":"Building & Trades",
            "subcategory":"Construction",
            "type":"Services"
        }
    ],
    "sg:phone":"+44 121 525 8438",
    "sg:postcode":"B70 0NS",
    "sg:province":"West Midlands",
    "sg:tags":[
        "decorator",
        "painter"
    ],
    "wof:name":"E N G Industrial Services",
    "wof:placetype":"venue"
},
  "geometry": {"coordinates":[-2.0095760822,52.5323829651],"type":"Point"}
}