{
  "type": "Feature",
  "properties": {
    "addr:full":"26-28 Water La Watford Hertfordshire WD1 2NJ",
    "addr:housenumber":"26-28",
    "addr:postcode":"wd1 2nj",
    "addr:street":"Water La",
    "iso:country":"GB",
    "sg:address":"26-28 Water La",
    "sg:city":"Watford",
    "sg:classifiers":[
        {
            "category":"Professional",
            "type":"Services"
        }
    ],
    "sg:phone":"+44 1923 445545",
    "sg:postcode":"WD1 2NJ",
    "sg:province":"Hertfordshire",
    "sg:tags":[
        "auctioneer"
    ],
    "wof:name":"Old Harlequin Sales",
    "wof:placetype":"venue"
},
  "geometry": {"coordinates":[-0.3908289969,51.6537017822],"type":"Point"}
}