{
  "type": "Feature",
  "properties": {
    "addr:full":"110 Lower Marsh London Greater London SE1 7AE",
    "addr:housenumber":"110",
    "addr:postcode":"se1 7ae",
    "addr:street":"Lower Marsh",
    "iso:country":"GB",
    "sg:address":"110 Lower Marsh",
    "sg:city":"London",
    "sg:classifiers":[
        {
            "category":"Shopping",
            "subcategory":"Shoes",
            "type":"Retail Goods"
        }
    ],
    "sg:phone":"+44 20 7928 7923",
    "sg:postcode":"SE1 7AE",
    "sg:province":"Greater London",
    "wof:name":"Waterloo Shoe Repairs",
    "wof:placetype":"venue"
},
  "geometry": {"coordinates":[-0.1127720028,51.5009994507],"type":"Point"}
}