{
  "type": "Feature",
  "properties": {
    "addr:full":"89 Bridgend Road Maesteg Bridgend CF34 0NA",
    "addr:housenumber":"89",
    "addr:postcode":"cf34 0na",
    "addr:street":"Bridgend Road",
    "iso:country":"GB",
    "sg:address":"89 Bridgend Road",
    "sg:city":"Maesteg",
    "sg:classifiers":[
        {
            "category":"Food & Beverages",
            "subcategory":"Liquor & Beverages",
            "type":"Retail Goods"
        }
    ],
    "sg:phone":"+44 1656 732294",
    "sg:postcode":"CF34 0NA",
    "sg:province":"Bridgend",
    "sg:tags":[
        "beer",
        "wine",
        "spirit",
        "wines"
    ],
    "wof:name":"Garth Supply Stores",
    "wof:placetype":"venue"
},
  "geometry": {"coordinates":[-3.6414830685,51.6021766663],"type":"Point"}
}