{
  "type": "Feature",
  "properties": {
    "addr:full":"Mount Pleasant Cambridge Cambridgeshire CB3 0BL",
    "addr:postcode":"cb3 0bl",
    "addr:street":"Mount Pleasant",
    "iso:country":"GB",
    "sg:address":"Mount Pleasant",
    "sg:city":"Cambridge",
    "sg:classifiers":[
        {
            "category":"Insurance",
            "subcategory":"Life Insurance",
            "type":"Services"
        }
    ],
    "sg:phone":"+44 1223 326300",
    "sg:postcode":"CB3 0BL",
    "sg:province":"Cambridgeshire",
    "sg:tags":[
        "assurance"
    ],
    "wof:name":"Equitable Life Assurance Society The",
    "wof:placetype":"venue"
},
  "geometry": {"coordinates":[0.11073,52.213203],"type":"Point"}
}