{
  "type": "Feature",
  "properties": {
    "addr:full":"46 High Street, Auchtermuchty Cupar Fife KY14 7AP",
    "addr:housenumber":"46",
    "addr:postcode":"ky14 7ap",
    "addr:street":"High Street",
    "iso:country":"GB",
    "sg:address":"46 High Street, Auchtermuchty",
    "sg:city":"Cupar",
    "sg:classifiers":[
        {
            "category":"Food & Beverages",
            "subcategory":"Meat & Fish",
            "type":"Retail Goods"
        }
    ],
    "sg:postcode":"KY14 7AP",
    "sg:province":"Fife",
    "sg:tags":[
        "butcher"
    ],
    "wof:name":"Andrew Anderson",
    "wof:placetype":"venue"
},
  "geometry": {"coordinates":[-3.270558,56.277824],"type":"Point"}
}