{
  "type": "Feature",
  "properties": {
    "addr:full":"61 Pall Mall London Greater London SW1Y 5HZ",
    "addr:housenumber":"61",
    "addr:postcode":"sw1y 5hz",
    "addr:street":"Pall Mall",
    "iso:country":"GB",
    "sg:address":"61 Pall Mall",
    "sg:city":"London",
    "sg:classifiers":[
        {
            "category":"Organizations",
            "subcategory":"Membership Organization",
            "type":"Services"
        }
    ],
    "sg:phone":"+44 20 7930 7319",
    "sg:postcode":"SW1Y 5HZ",
    "sg:province":"Greater London",
    "sg:tags":[
        "club"
    ],
    "wof:name":"The European Foundation",
    "wof:placetype":"venue"
},
  "geometry": {"coordinates":[-0.1376120001,51.5054130554],"type":"Point"}
}