{
  "type": "Feature",
  "properties": {
    "iso:country":"GB",
    "sg:address":"7 Harbord Road, Overstrand",
    "sg:city":"Cromer",
    "sg:classifiers":[
        {
            "category":"Building & Trades",
            "subcategory":"Plumbing",
            "type":"Services"
        }
    ],
    "sg:phone":"+44 1263 579235",
    "sg:postcode":"NR27 0PL",
    "sg:province":"Norfolk",
    "sg:tags":[
        "plumber",
        "heating"
    ],
    "wof:name":"A Pointer",
    "wof:placetype":"venue"
},
  "geometry": {"coordinates":[1.309436,52.920933],"type":"Point"}
}