{
  "type": "Feature",
  "properties": {
    "addr:full":"Little End, Eaton Socon St Neots Bedfordshire PE19 8JH",
    "addr:postcode":"pe19 8jh",
    "addr:street":"Little End;Socon",
    "iso:country":"GB",
    "sg:address":"Little End, Eaton Socon",
    "sg:city":"St Neots",
    "sg:classifiers":[
        {
            "category":"Food & Beverages",
            "subcategory":"Specialty",
            "type":"Retail Goods"
        }
    ],
    "sg:phone":"+44 1480 224610",
    "sg:postcode":"PE19 8JH",
    "sg:province":"Bedfordshire",
    "sg:tags":[
        "product",
        "health"
    ],
    "wof:name":"Life Plus Europe Ltd.",
    "wof:placetype":"venue"
},
  "geometry": {"coordinates":[-0.2893750072,52.2174720764],"type":"Point"}
}