{
  "type": "Feature",
  "properties": {
    "iso:country":"GB",
    "sg:address":"Trading Standards, Perceton Ho, Perceton",
    "sg:city":"Irvine",
    "sg:classifiers":[
        {
            "category":"Government",
            "subcategory":"Office",
            "type":"Public Place"
        }
    ],
    "sg:phone":"+44 1294 225163",
    "sg:postcode":"KA11 2AL",
    "sg:province":"East Ayrshire",
    "sg:tags":[
        "local"
    ],
    "wof:name":"North Ayrshire Council",
    "wof:placetype":"venue"
},
  "geometry": {"coordinates":[-4.616721,55.626987],"type":"Point"}
}