{
  "type": "Feature",
  "properties": {
    "iso:country":"GB",
    "sg:address":"4 Stonefield Road, Blantyre",
    "sg:city":"Glasgow",
    "sg:classifiers":[
        {
            "category":"Farming",
            "subcategory":"Livestock Farm",
            "type":"Manufacturing & Wholesale Goods"
        }
    ],
    "sg:phone":"+44 1698 829008",
    "sg:postcode":"G72 9PQ",
    "sg:province":"South Lanarkshire",
    "sg:tags":[
        "breeder"
    ],
    "wof:name":"Ruth Gormley",
    "wof:placetype":"venue"
},
  "geometry": {"coordinates":[-4.0960621834,55.7943840027],"type":"Point"}
}