{
  "type": "Feature",
  "properties": {
    "addr:full":"The Old Vicarage, Barton Street, Aylesby Grimsby Lincolnshire DN37 7LQ",
    "addr:postcode":"dn37 7lq",
    "addr:street":"Barton Street",
    "iso:country":"GB",
    "sg:address":"The Old Vicarage, Barton Street, Aylesby",
    "sg:city":"Grimsby",
    "sg:classifiers":[
        {
            "category":"Freight",
            "type":"Transportation"
        }
    ],
    "sg:phone":"+44 1469 553677",
    "sg:postcode":"DN37 7LQ",
    "sg:province":"Lincolnshire",
    "sg:tags":[
        "forwarders"
    ],
    "wof:name":"Yeoman International Transport Ltd.",
    "wof:placetype":"venue"
},
  "geometry": {"coordinates":[-0.1849859953,53.5517272949],"type":"Point"}
}