{
  "type": "Feature",
  "properties": {
    "iso:country":"GB",
    "sg:address":"Unit 11, Broomers Hill Park",
    "sg:city":"Pulborough",
    "sg:classifiers":[
        {
            "category":"Home & Garden",
            "subcategory":"Hardware",
            "type":"Retail Goods"
        }
    ],
    "sg:phone":"+44 1798 875628",
    "sg:postcode":"RH20 2RY",
    "sg:province":"West Sussex",
    "sg:tags":[
        "fixing",
        "nuts",
        "bolt"
    ],
    "wof:name":"Connect-2",
    "wof:placetype":"venue"
},
  "geometry": {"coordinates":[-0.488889,50.963799],"type":"Point"}
}