{
  "type": "Feature",
  "properties": {
    "addr:full":"94 Albany Road Cardiff Cardiff CF24 3RT",
    "addr:housenumber":"94",
    "addr:postcode":"cf24 3rt",
    "addr:street":"Albany Road",
    "iso:country":"GB",
    "sg:address":"94 Albany Road",
    "sg:city":"Cardiff",
    "sg:classifiers":[
        {
            "category":"Banks & Credit Unions",
            "subcategory":"Bank",
            "type":"Services"
        }
    ],
    "sg:phone":"+44 845 740 4404",
    "sg:postcode":"CF24 3RT",
    "sg:province":"Cardiff",
    "wof:name":"H S B C Bank",
    "wof:placetype":"venue"
},
  "geometry": {"coordinates":[-3.1658608913,51.4939689636],"type":"Point"}
}