{
  "type": "Feature",
  "properties": {
    "addr:full":"2 Beaconsfield Street Carlisle Cumbria CA2 4AL",
    "addr:housenumber":"2",
    "addr:postcode":"ca2 4al",
    "addr:street":"Beaconsfield Street",
    "iso:country":"GB",
    "sg:address":"2 Beaconsfield Street",
    "sg:city":"Carlisle",
    "sg:classifiers":[
        {
            "category":"Personal",
            "subcategory":"Beauty Salon",
            "type":"Services"
        }
    ],
    "sg:phone":"+44 1228 818488",
    "sg:postcode":"CA2 4AL",
    "sg:province":"Cumbria",
    "sg:tags":[
        "unisex",
        "hairdresser"
    ],
    "wof:name":"Rootz Hair Design",
    "wof:placetype":"venue"
},
  "geometry": {"coordinates":[-2.9289178848,54.882434845],"type":"Point"}
}