{
  "type": "Feature",
  "properties": {
    "iso:country":"GB",
    "sg:address":"Long La",
    "sg:city":"Southampton",
    "sg:classifiers":[
        {
            "category":"Place Of Worship",
            "type":"Public Place"
        }
    ],
    "sg:phone":"+44 23 8086 4076",
    "sg:postcode":"SO40 4WR",
    "sg:province":"Hampshire",
    "wof:name":"Marchwood Gospel Church The",
    "wof:placetype":"venue"
},
  "geometry": {"coordinates":[-1.457928,50.888237],"type":"Point"}
}