{
  "type": "Feature",
  "properties": {
    "addr:full":"Unit 11 Jasmin Rd Lincoln Lincolnshire LN6 0QQ",
    "addr:housenumber":"unit 11",
    "addr:postcode":"ln6 0qq",
    "addr:street":"Jasmin Rd",
    "iso:country":"GB",
    "sg:address":"Unit 11 Jasmin Rd",
    "sg:city":"Lincoln",
    "sg:classifiers":[
        {
            "category":"Building & Trades",
            "subcategory":"Cleaning & Sanitation",
            "type":"Services"
        }
    ],
    "sg:phone":"+44 1522 691071",
    "sg:postcode":"LN6 0QQ",
    "sg:province":"Lincolnshire",
    "sg:tags":[
        "commercial"
    ],
    "wof:name":"New Broom Sweeps Clean",
    "wof:placetype":"venue"
},
  "geometry": {"coordinates":[-0.6087740064,53.2186813354],"type":"Point"}
}