{
  "type": "Feature",
  "properties": {
    "iso:country":"GB",
    "sg:address":"90a Edwin Road, Rainham",
    "sg:city":"Gillingham",
    "sg:classifiers":[
        {
            "category":"Professional",
            "subcategory":"Lawyer & Legal Services",
            "type":"Services"
        }
    ],
    "sg:phone":"+44 1634 264264",
    "sg:postcode":"ME8 0AE",
    "sg:province":"Kent",
    "sg:tags":[
        "solicitor"
    ],
    "wof:name":"Stuart Fuller",
    "wof:placetype":"venue"
},
  "geometry": {"coordinates":[0.583681,51.363422],"type":"Point"}
}