{
  "type": "Feature",
  "properties": {
    "addr:full":"Provender Way, Weavering Maidstone Kent ME14 5TZ",
    "addr:postcode":"me14 5tz",
    "addr:street":"Provender Way",
    "iso:country":"GB",
    "sg:address":"Provender Way, Weavering",
    "sg:city":"Maidstone",
    "sg:classifiers":[
        {
            "category":"Education",
            "subcategory":"School",
            "type":"Public Place"
        }
    ],
    "sg:phone":"+44 1622 735916",
    "sg:postcode":"ME14 5TZ",
    "sg:province":"Kent",
    "sg:tags":[
        "local",
        "authority"
    ],
    "wof:name":"St Johns C Of E Primary School",
    "wof:placetype":"venue"
},
  "geometry": {"coordinates":[0.5527449846,51.2736206055],"type":"Point"}
}