{
  "type": "Feature",
  "properties": {
    "iso:country":"GB",
    "sg:address":"19 Somers Road",
    "sg:city":"Rugby",
    "sg:classifiers":[
        {
            "category":"Wholesale",
            "subcategory":"Motor Vehicles",
            "type":"Manufacturing & Wholesale Goods"
        }
    ],
    "sg:phone":"+44 1788 536087",
    "sg:postcode":"CV22 7DG",
    "sg:province":"Warwickshire",
    "sg:tags":[
        "turbine"
    ],
    "wof:name":"Cresta Turbines Ltd.",
    "wof:placetype":"venue"
},
  "geometry": {"coordinates":[-1.286892,52.372684],"type":"Point"}
}