{
  "type": "Feature",
  "properties": {
    "iso:country":"GB",
    "sg:address":"37 Eastside",
    "sg:city":"Glasgow",
    "sg:classifiers":[
        {
            "category":"Autos & Motor Vehicles",
            "subcategory":"Automobile Sales",
            "type":"Retail Goods"
        }
    ],
    "sg:phone":"+44 141 776 6771",
    "sg:postcode":"G66 1QA",
    "sg:province":"East Dunbartonshire",
    "sg:tags":[
        "car"
    ],
    "wof:name":"Kirkintilloch Car Sales",
    "wof:placetype":"venue"
},
  "geometry": {"coordinates":[-4.1532888412,55.9420013428],"type":"Point"}
}