{
  "type": "Feature",
  "properties": {
    "iso:country":"GB",
    "sg:address":"17b M'tongue Avenue, Bosham",
    "sg:city":"Chichester",
    "sg:classifiers":[
        {
            "category":"Professional",
            "subcategory":"Lawyer & Legal Services",
            "type":"Services"
        }
    ],
    "sg:phone":"+44 1243 576056",
    "sg:postcode":"PO18 8LB",
    "sg:province":"West Sussex",
    "sg:tags":[
        "solicitor"
    ],
    "wof:name":"Greg Challenor",
    "wof:placetype":"venue"
},
  "geometry": {"coordinates":[-0.8451,50.841228],"type":"Point"}
}