{
  "type": "Feature",
  "properties": {
    "addr:full":"The Red House, 84 High Street Buntingford Hertfordshire SG9 9AJ",
    "addr:housenumber":"84",
    "addr:postcode":"sg9 9aj",
    "addr:street":"High Street",
    "iso:country":"GB",
    "sg:address":"The Red House, 84 High Street",
    "sg:city":"Buntingford",
    "sg:classifiers":[
        {
            "category":"Utilities",
            "type":"Services"
        }
    ],
    "sg:phone":"+44 1763 273379",
    "sg:postcode":"SG9 9AJ",
    "sg:province":"Hertfordshire",
    "sg:tags":[
        "internet"
    ],
    "wof:name":"Diafade Ltd.",
    "wof:placetype":"venue"
},
  "geometry": {"coordinates":[-0.0209240001,51.949886322],"type":"Point"}
}