{
  "type": "Feature",
  "properties": {
    "addr:full":"32 Martin Square, Larkfield Aylesford Kent ME20 6QJ",
    "addr:housenumber":"32",
    "addr:postcode":"me20 6qj",
    "addr:street":"Martin Square",
    "iso:country":"GB",
    "sg:address":"32 Martin Square, Larkfield",
    "sg:city":"Aylesford",
    "sg:classifiers":[
        {
            "category":"Cinema",
            "subcategory":"Movie Rental",
            "type":"Entertainment"
        }
    ],
    "sg:phone":"+44 1732 846481",
    "sg:postcode":"ME20 6QJ",
    "sg:province":"Kent",
    "sg:tags":[
        "video",
        "library"
    ],
    "wof:name":"Pinderview Ltd.",
    "wof:placetype":"venue"
},
  "geometry": {"coordinates":[0.440779,51.300022],"type":"Point"}
}