{
  "type": "Feature",
  "properties": {
    "iso:country":"GB",
    "sg:address":"76 Curzon Avenue, Birstall",
    "sg:city":"Leicester",
    "sg:classifiers":[
        {
            "category":"Professional",
            "subcategory":"Art Services",
            "type":"Services"
        },
        {
            "category":"Building & Trades",
            "subcategory":"Construction",
            "type":"Services"
        }
    ],
    "sg:phone":"+44 116 267 5570",
    "sg:postcode":"LE4 4AD",
    "sg:province":"Leicestershire",
    "sg:tags":[
        "decorator",
        "painter"
    ],
    "wof:name":"Raymond John Townsend",
    "wof:placetype":"venue"
},
  "geometry": {"coordinates":[-1.1242439747,52.6704177856],"type":"Point"}
}