{
  "type": "Feature",
  "properties": {
    "iso:country":"GB",
    "sg:address":"10 Lower Fore Street",
    "sg:city":"Saltash",
    "sg:classifiers":[
        {
            "category":"Professional",
            "subcategory":"Art Services",
            "type":"Services"
        }
    ],
    "sg:phone":"+44 1752 841165",
    "sg:postcode":"PL12 6JX",
    "sg:province":"Cornwall",
    "sg:tags":[
        "framing"
    ],
    "wof:name":"Framers Corner",
    "wof:placetype":"venue"
},
  "geometry": {"coordinates":[-4.208589077,50.4082260132],"type":"Point"}
}