{
  "type": "Feature",
  "properties": {
    "iso:country":"GB",
    "sg:address":"1 New Village, Dudley Wood",
    "sg:city":"Dudley",
    "sg:classifiers":[
        {
            "category":"Professional",
            "subcategory":"Engineering",
            "type":"Services"
        }
    ],
    "sg:postcode":"DY2 0DR",
    "sg:province":"West Midlands",
    "wof:name":"T A G Repitition Ltd",
    "wof:placetype":"venue"
},
  "geometry": {"coordinates":[-2.089152,52.475578],"type":"Point"}
}