{
  "type": "Feature",
  "properties": {
    "iso:country":"GB",
    "sg:address":"Unit F, Blaby Industrial Park, Winchester Avenue",
    "sg:city":"Leicester",
    "sg:classifiers":[
        {
            "category":"Professional",
            "subcategory":"Engineering",
            "type":"Services"
        }
    ],
    "sg:phone":"+44 116 277 3607",
    "sg:postcode":"LE8 4GZ",
    "sg:province":"Leicestershire",
    "wof:name":"A T M Engineering Ltd.",
    "wof:placetype":"venue"
},
  "geometry": {"coordinates":[-1.164713,52.573448],"type":"Point"}
}