{
  "type": "Feature",
  "properties": {
    "iso:country":"GB",
    "sg:address":"South Row, Redwick, Magor",
    "sg:city":"Caldicot",
    "sg:classifiers":[
        {
            "category":"Bars & Pubs",
            "type":"Food & Drink"
        }
    ],
    "sg:phone":"+44 1633 880501",
    "sg:postcode":"NP26 3DU",
    "sg:province":"Monmouthshire",
    "sg:tags":[
        "pubs",
        "inn"
    ],
    "wof:name":"The Rose Inn",
    "wof:placetype":"venue"
},
  "geometry": {"coordinates":[-2.7480449677,51.5859565735],"type":"Point"}
}