{
  "type": "Feature",
  "properties": {
    "iso:country":"GB",
    "sg:address":"Hesmonds Farm, East Hoathly",
    "sg:city":"Lewes",
    "sg:classifiers":[
        {
            "category":"Farming",
            "subcategory":"Farm",
            "type":"Manufacturing & Wholesale Goods"
        }
    ],
    "sg:postcode":"BN8 6QH",
    "sg:province":"East Sussex",
    "sg:tags":[
        "mixed",
        "crop"
    ],
    "wof:name":"D W Gibson",
    "wof:placetype":"venue"
},
  "geometry": {"coordinates":[0.165229,50.925571],"type":"Point"}
}