{
  "type": "Feature",
  "properties": {
    "iso:country":"GB",
    "sg:address":"32 Howe Street",
    "sg:city":"Edinburgh",
    "sg:classifiers":[
        {
            "category":"Professional",
            "type":"Services"
        }
    ],
    "sg:phone":"+44 131 226 3903",
    "sg:postcode":"EH3 6TH",
    "sg:province":"City of Edinburgh",
    "sg:tags":[
        "caterer"
    ],
    "wof:name":"Stefan C's",
    "wof:placetype":"venue"
},
  "geometry": {"coordinates":[-3.202688,55.956562],"type":"Point"}
}