{
  "type": "Feature",
  "properties": {
    "addr:full":"Penmynydd Post Office, Penmynydd Llanfairpwllgwyngyll Isle of Anglesey LL61 6PG",
    "addr:postcode":"ll61 6pg",
    "addr:street":"Llanfairpwllgwyngyll",
    "iso:country":"GB",
    "sg:address":"Penmynydd Post Office, Penmynydd",
    "sg:city":"Llanfairpwllgwyngyll",
    "sg:classifiers":[
        {
            "category":"Government",
            "subcategory":"Post Office",
            "type":"Public Place"
        }
    ],
    "sg:postcode":"LL61 6PG",
    "sg:province":"Isle of Anglesey",
    "wof:name":"Penmynydd Post Office",
    "wof:placetype":"venue"
},
  "geometry": {"coordinates":[-4.2356419563,53.246181488],"type":"Point"}
}