{
  "type": "Feature",
  "properties": {
    "iso:country":"GB",
    "sg:address":"Boundary House, Salisbury Road",
    "sg:city":"Romsey",
    "sg:classifiers":[
        {
            "category":"Manufacturing",
            "subcategory":"Textiles",
            "type":"Manufacturing & Wholesale Goods"
        }
    ],
    "sg:postcode":"SO51 6FQ",
    "sg:province":"Hampshire",
    "sg:tags":[
        "knitwear"
    ],
    "wof:name":"Island Knitwear",
    "wof:placetype":"venue"
},
  "geometry": {"coordinates":[-1.535036,50.941341],"type":"Point"}
}