{
  "type": "Feature",
  "properties": {
    "addr:full":"29 Walters Road Swansea Neath Port Talbot SA1 5NN",
    "addr:housenumber":"29",
    "addr:postcode":"sa1 5nn",
    "addr:street":"Walters Road",
    "iso:country":"GB",
    "sg:address":"29 Walters Road",
    "sg:city":"Swansea",
    "sg:classifiers":[
        {
            "category":"Organizations",
            "subcategory":"Membership Organization",
            "type":"Services"
        }
    ],
    "sg:phone":"+44 1792 411132",
    "sg:postcode":"SA1 5NN",
    "sg:province":"Neath Port Talbot",
    "sg:tags":[
        "club",
        "social"
    ],
    "wof:name":"Royal Welsh Fusiliers Club",
    "wof:placetype":"venue"
},
  "geometry": {"coordinates":[-3.955842,51.619453],"type":"Point"}
}