{
  "type": "Feature",
  "properties": {
    "addr:full":"Eves Corner, Danbury Chelmsford Essex CM3 4QQ",
    "addr:postcode":"cm3 4qq",
    "iso:country":"GB",
    "sg:address":"Eves Corner, Danbury",
    "sg:city":"Chelmsford",
    "sg:classifiers":[
        {
            "category":"Real Estate",
            "subcategory":"Real Estate Agent",
            "type":"Services"
        }
    ],
    "sg:phone":"+44 1245 225896",
    "sg:postcode":"CM3 4QQ",
    "sg:province":"Essex",
    "wof:name":"Danbury Estate Agents",
    "wof:placetype":"venue"
},
  "geometry": {"coordinates":[0.5807800293,51.7163963318],"type":"Point"}
}