{
  "type": "Feature",
  "properties": {
    "addr:full":"9-11 Evan Street Stonehaven Aberdeenshire AB39 2EQ",
    "addr:housenumber":"9-11",
    "addr:postcode":"ab39 2eq",
    "addr:street":"Evan Street",
    "iso:country":"GB",
    "sg:address":"9-11 Evan Street",
    "sg:city":"Stonehaven",
    "sg:classifiers":[
        {
            "category":"Shopping",
            "subcategory":"News",
            "type":"Retail Goods"
        }
    ],
    "sg:phone":"+44 1569 762244",
    "sg:postcode":"AB39 2EQ",
    "sg:province":"Aberdeenshire",
    "sg:tags":[
        "newsagent"
    ],
    "wof:name":"David Waldie",
    "wof:placetype":"venue"
},
  "geometry": {"coordinates":[-2.209724,56.963867],"type":"Point"}
}