{
  "type": "Feature",
  "properties": {
    "addr:full":"9 The Rise Uxbridge Greater London UB10 0JL",
    "addr:housenumber":"9",
    "addr:postcode":"ub10 0jl",
    "addr:street":"The Rise",
    "iso:country":"GB",
    "sg:address":"9 The Rise",
    "sg:city":"Uxbridge",
    "sg:classifiers":[
        {
            "category":"Building & Trades",
            "subcategory":"Construction",
            "type":"Services"
        }
    ],
    "sg:phone":"+44 1895 230969",
    "sg:postcode":"UB10 0JL",
    "sg:province":"Greater London",
    "sg:tags":[
        "builder"
    ],
    "wof:name":"Kevin Cotterill",
    "wof:placetype":"venue"
},
  "geometry": {"coordinates":[-0.46124,51.536629],"type":"Point"}
}