{
  "type": "Feature",
  "properties": {
    "addr:full":"152 Furrlongs Newport Isle of Wight PO30 2BD",
    "addr:housenumber":"152",
    "addr:postcode":"po30 2bd",
    "addr:street":"Furrlongs",
    "iso:country":"GB",
    "sg:address":"152 Furrlongs",
    "sg:city":"Newport",
    "sg:classifiers":[
        {
            "category":"Building & Trades",
            "subcategory":"Construction",
            "type":"Services"
        }
    ],
    "sg:phone":"+44 1983 525340",
    "sg:postcode":"PO30 2BD",
    "sg:province":"Isle of Wight",
    "sg:tags":[
        "builder"
    ],
    "wof:name":"J Jolliffe",
    "wof:placetype":"venue"
},
  "geometry": {"coordinates":[-1.2804609537,50.6999473572],"type":"Point"}
}