{
  "type": "Feature",
  "properties": {
    "addr:full":"Aerodrome, Watnall Road, Hucknall Nottingham Derbyshire NG16 6EQ",
    "addr:postcode":"ng16 6eq",
    "addr:street":"Watnall Road",
    "iso:country":"GB",
    "sg:address":"Aerodrome, Watnall Road, Hucknall",
    "sg:city":"Nottingham",
    "sg:classifiers":[
        {
            "category":"Retail",
            "subcategory":"Auto Repair",
            "type":"Services"
        }
    ],
    "sg:phone":"+44 115 968 0070",
    "sg:postcode":"NG16 6EQ",
    "sg:province":"Derbyshire",
    "sg:tags":[
        "car",
        "specialist",
        "customizing"
    ],
    "wof:name":"Brivon Tyres",
    "wof:placetype":"venue"
},
  "geometry": {"coordinates":[-1.2989799976,53.0723686218],"type":"Point"}
}