{
  "type": "Feature",
  "properties": {
    "addr:full":"1b East Way, Lee Mill Industrial Estate Ivybridge Devon PL21 9PE",
    "addr:housenumber":"1b",
    "addr:postcode":"pl21 9pe",
    "addr:street":"East Way Lee Mill Industrial Estate",
    "iso:country":"GB",
    "sg:address":"1b East Way, Lee Mill Industrial Estate",
    "sg:city":"Ivybridge",
    "sg:classifiers":[
        {
            "category":"Manufacturing",
            "subcategory":"Building Materials",
            "type":"Manufacturing & Wholesale Goods"
        }
    ],
    "sg:phone":"+44 1752 690133",
    "sg:postcode":"PL21 9PE",
    "sg:province":"Devon",
    "sg:tags":[
        "stonemason"
    ],
    "wof:name":"Westcountry Stonemasons Ltd.",
    "wof:placetype":"venue"
},
  "geometry": {"coordinates":[-3.9493610859,50.3867835999],"type":"Point"}
}