{
  "type": "Feature",
  "properties": {
    "addr:full":"9 Derby Road Chesterfield Derbyshire S40 2EF",
    "addr:housenumber":"9",
    "addr:postcode":"s40 2ef",
    "addr:street":"Derby Road",
    "iso:country":"GB",
    "sg:address":"9 Derby Road",
    "sg:city":"Chesterfield",
    "sg:classifiers":[
        {
            "category":"Professional",
            "type":"Services"
        }
    ],
    "sg:postcode":"S40 2EF",
    "sg:province":"Derbyshire",
    "sg:tags":[
        "caterer"
    ],
    "wof:name":"Gorgers",
    "wof:placetype":"venue"
},
  "geometry": {"coordinates":[-1.4250320196,53.2268753052],"type":"Point"}
}