{
  "type": "Feature",
  "properties": {
    "addr:full":"H26 The Avenue, Team Valley Gateshead Tyne and Wear NE11 0NJ",
    "addr:postcode":"ne11 0nj",
    "addr:street":"The Avenue",
    "iso:country":"GB",
    "sg:address":"H26 The Avenue, Team Valley",
    "sg:city":"Gateshead",
    "sg:classifiers":[
        {
            "category":"Wholesale",
            "subcategory":"Books, Periodicals, & Newspapers",
            "type":"Manufacturing & Wholesale Goods"
        }
    ],
    "sg:phone":"+44 191 482 0696",
    "sg:postcode":"NE11 0NJ",
    "sg:province":"Tyne and Wear",
    "sg:tags":[
        "maps",
        "globe",
        "chart",
        "pub"
    ],
    "wof:name":"Give Way Ltd.",
    "wof:placetype":"venue"
},
  "geometry": {"coordinates":[-1.60847,54.925652],"type":"Point"}
}