{
  "type": "Feature",
  "properties": {
    "addr:full":"114 Westbourne Grove Yeovil Somerset BA20 2DQ",
    "addr:housenumber":"114",
    "addr:postcode":"ba20 2dq",
    "addr:street":"Westbourne Grove",
    "iso:country":"GB",
    "sg:address":"114 Westbourne Grove",
    "sg:city":"Yeovil",
    "sg:classifiers":[
        {
            "category":"Arts & Performance",
            "subcategory":"Music",
            "type":"Entertainment"
        }
    ],
    "sg:phone":"+44 1935 428893",
    "sg:postcode":"BA20 2DQ",
    "sg:province":"Somerset",
    "sg:tags":[
        "mobile",
        "disco"
    ],
    "wof:name":"Pro-j-discos County Sounds",
    "wof:placetype":"venue"
},
  "geometry": {"coordinates":[-2.6558470726,50.9427566528],"type":"Point"}
}