{
  "type": "Feature",
  "properties": {
    "iso:country":"GB",
    "sg:address":"Sunflower House, Gull Road",
    "sg:city":"Wisbech",
    "sg:classifiers":[
        {
            "category":"Sports & Exercise",
            "subcategory":"Skate Park",
            "type":"Entertainment"
        }
    ],
    "sg:postcode":"PE13 4ER",
    "sg:province":"Cambridgeshire",
    "sg:tags":[
        "mushroom"
    ],
    "wof:name":"G B Mushrooms Ltd.",
    "wof:placetype":"venue"
},
  "geometry": {"coordinates":[0.0566749983,52.6120452881],"type":"Point"}
}