{
  "type": "Feature",
  "properties": {
    "iso:country":"GB",
    "sg:address":"13 Fields Road",
    "sg:city":"Crewe",
    "sg:classifiers":[
        {
            "category":"Building & Trades",
            "subcategory":"Construction",
            "type":"Services"
        }
    ],
    "sg:postcode":"CW1 5ST",
    "sg:province":"Cheshire",
    "sg:tags":[
        "builder"
    ],
    "wof:name":"I A Birchall Builder & Contractor",
    "wof:placetype":"venue"
},
  "geometry": {"coordinates":[-2.39335,53.096348],"type":"Point"}
}