{
  "type": "Feature",
  "properties": {
    "addr:full":"80 Main Street Cockermouth Cumbria CA13 9LU",
    "addr:housenumber":"80",
    "addr:postcode":"ca13 9lu",
    "addr:street":"Main Street",
    "iso:country":"GB",
    "sg:address":"80 Main Street",
    "sg:city":"Cockermouth",
    "sg:classifiers":[
        {
            "category":"Shopping",
            "subcategory":"Clothing, Apparel, & Fashions",
            "type":"Retail Goods"
        }
    ],
    "sg:phone":"+44 1900 825338",
    "sg:postcode":"CA13 9LU",
    "sg:province":"Cumbria",
    "sg:tags":[
        "shop"
    ],
    "wof:name":"Annabelles",
    "wof:placetype":"venue"
},
  "geometry": {"coordinates":[-3.3664610386,54.6637496948],"type":"Point"}
}