{
  "type": "Feature",
  "properties": {
    "addr:full":"313-315 Cortis Road London Greater London SW15 6XG",
    "addr:housenumber":"313-315",
    "addr:postcode":"sw15 6xg",
    "addr:street":"Cortis Road",
    "iso:country":"GB",
    "sg:address":"313-315 Cortis Road",
    "sg:city":"London",
    "sg:classifiers":[
        {
            "category":"Health Services",
            "subcategory":"Clinic",
            "type":"Services"
        }
    ],
    "sg:postcode":"SW15 6XG",
    "sg:province":"Greater London",
    "sg:tags":[
        "nh"
    ],
    "wof:name":"South West London & St.Georges Mental He",
    "wof:placetype":"venue"
},
  "geometry": {"coordinates":[-0.22798,51.45586],"type":"Point"}
}