{
  "type": "Feature",
  "properties": {
    "addr:full":"102 Kechill Gardens Bromley Kent BR2 7NB",
    "addr:housenumber":"102",
    "addr:postcode":"br2 7nb",
    "addr:street":"Kechill Gardens",
    "iso:country":"GB",
    "sg:address":"102 Kechill Gardens",
    "sg:city":"Bromley",
    "sg:classifiers":[
        {
            "category":"Professional",
            "subcategory":"Engineering",
            "type":"Services"
        }
    ],
    "sg:phone":"+44 20 8462 3269",
    "sg:postcode":"BR2 7NB",
    "sg:province":"Kent",
    "sg:tags":[
        "contractor",
        "electrical",
        "engineer"
    ],
    "wof:name":"Powerpoint Electrical Services",
    "wof:placetype":"venue"
},
  "geometry": {"coordinates":[0.016265,51.384548],"type":"Point"}
}