{
  "type": "Feature",
  "properties": {
    "iso:country":"GB",
    "sg:address":"19 Holmside Pl",
    "sg:city":"Newcastle Upon Tyne",
    "sg:classifiers":[
        {
            "category":"Shopping",
            "subcategory":"Computers & Home Electronics",
            "type":"Retail Goods"
        }
    ],
    "sg:phone":"+44 191 224 3800",
    "sg:postcode":"NE6 5AJ",
    "sg:province":"Tyne and Wear",
    "sg:tags":[
        "sound",
        "equipment"
    ],
    "wof:name":"Stuk Sound",
    "wof:placetype":"venue"
},
  "geometry": {"coordinates":[-1.5851399899,54.9813613892],"type":"Point"}
}