{
  "type": "Feature",
  "properties": {
    "addr:full":"Jesse Road Narberth Carmarthenshire SA67 7DH",
    "addr:postcode":"sa67 7dh",
    "addr:street":"Jesse Road",
    "iso:country":"GB",
    "sg:address":"Jesse Road",
    "sg:city":"Narberth",
    "sg:classifiers":[
        {
            "category":"Building & Trades",
            "subcategory":"Construction",
            "type":"Services"
        }
    ],
    "sg:phone":"+44 1834 860950",
    "sg:postcode":"SA67 7DH",
    "sg:province":"Carmarthenshire",
    "sg:tags":[
        "glazier"
    ],
    "wof:name":"Narberth Glassworks",
    "wof:placetype":"venue"
},
  "geometry": {"coordinates":[-4.733654,51.800999],"type":"Point"}
}