{
  "type": "Feature",
  "properties": {
    "iso:country":"GB",
    "sg:address":"80 Elterwater Drive, Gamston",
    "sg:city":"Nottingham",
    "sg:classifiers":[
        {
            "category":"Shopping",
            "subcategory":"Crafts & Fabrics",
            "type":"Retail Goods"
        }
    ],
    "sg:postcode":"NG2 6PX",
    "sg:province":"Nottinghamshire",
    "sg:tags":[
        "machine",
        "sewing",
        "knitting"
    ],
    "wof:name":"Rush Machine Co.",
    "wof:placetype":"venue"
},
  "geometry": {"coordinates":[-1.103908,52.927097],"type":"Point"}
}