{
  "type": "Feature",
  "properties": {
    "addr:full":"90 Warwick Park Tunbridge Wells East Sussex TN2 5EN",
    "addr:housenumber":"90",
    "addr:postcode":"tn2 5en",
    "addr:street":"Warwick Park;Wells",
    "iso:country":"GB",
    "sg:address":"90 Warwick Park",
    "sg:city":"Tunbridge Wells",
    "sg:classifiers":[
        {
            "category":"Social Services",
            "subcategory":"Retirement Home",
            "type":"Services"
        }
    ],
    "sg:phone":"+44 1892 527814",
    "sg:postcode":"TN2 5EN",
    "sg:province":"East Sussex",
    "sg:tags":[
        "rest"
    ],
    "wof:name":"Cedars Rest Home",
    "wof:placetype":"venue"
},
  "geometry": {"coordinates":[0.267794013,51.1205635071],"type":"Point"}
}