{
  "type": "Feature",
  "properties": {
    "addr:full":"Conference Office, Loring Management Centre, St James New Cross Greater London SE14 6AD",
    "addr:postcode":"se14 6ad",
    "addr:street":"St;Cross",
    "iso:country":"GB",
    "sg:address":"Conference Office, Loring Management Centre, St James",
    "sg:city":"New Cross",
    "sg:classifiers":[
        {
            "category":"Conference Center",
            "type":"Public Place"
        }
    ],
    "sg:phone":"+44 20 7919 7132",
    "sg:postcode":"SE14 6AD",
    "sg:province":"Greater London",
    "wof:name":"Goldsmiths College University Of London",
    "wof:placetype":"venue"
},
  "geometry": {"coordinates":[-0.03872,51.474998],"type":"Point"}
}