{
  "type": "Feature",
  "properties": {
    "addr:full":"23 Fairywell Rd Altrincham Cheshire WA15 6XA",
    "addr:housenumber":"23",
    "addr:postcode":"wa15 6xa",
    "addr:street":"Fairywell Rd",
    "iso:country":"GB",
    "sg:address":"23 Fairywell Rd",
    "sg:city":"Altrincham",
    "sg:classifiers":[
        {
            "category":"Shopping",
            "subcategory":"Used Merchandise",
            "type":"Retail Goods"
        }
    ],
    "sg:phone":"+44 161 969 0753",
    "sg:postcode":"WA15 6XA",
    "sg:province":"Cheshire",
    "sg:tags":[
        "furniture"
    ],
    "wof:name":"Julia Wade",
    "wof:placetype":"venue"
},
  "geometry": {"coordinates":[-2.3179910183,53.4008483887],"type":"Point"}
}