{
  "type": "Feature",
  "properties": {
    "iso:country":"GB",
    "sg:address":"Flat 3, The Gainsborough",
    "sg:city":"Bournemouth",
    "sg:classifiers":[
        {
            "category":"Communications",
            "subcategory":"Film & Video Production",
            "type":"Services"
        }
    ],
    "sg:phone":"+44 7747 182077",
    "sg:postcode":"BH2 5HT",
    "sg:province":"Dorset",
    "sg:tags":[
        "illustrator",
        "artist"
    ],
    "wof:name":"SaQui Design",
    "wof:placetype":"venue"
},
  "geometry": {"coordinates":[-1.8860989809,50.7177886963],"type":"Point"}
}