{
  "type": "Feature",
  "properties": {
    "addr:full":"149a Fog Lane Manchester Greater Manchester M20 6FJ",
    "addr:housenumber":"149a",
    "addr:postcode":"m20 6fj",
    "addr:street":"Fog Lane",
    "iso:country":"GB",
    "sg:address":"149a Fog Lane",
    "sg:city":"Manchester",
    "sg:classifiers":[
        {
            "category":"Personal",
            "subcategory":"Beauty Salon",
            "type":"Services"
        }
    ],
    "sg:phone":"+44 161 445 0201",
    "sg:postcode":"M20 6FJ",
    "sg:province":"Greater Manchester",
    "sg:tags":[
        "unisex",
        "hairdresser"
    ],
    "wof:name":"John Yates Hair & Beauty",
    "wof:placetype":"venue"
},
  "geometry": {"coordinates":[-2.2184169292,53.4217071533],"type":"Point"}
}