{
  "type": "Feature",
  "properties": {
    "addr:full":"Po Box 66 Redcote House, Nightingale Avenue Leatherhead Surrey KT24 6YB",
    "addr:housenumber":"po box 66 redcote house",
    "addr:postcode":"kt24 6yb",
    "addr:street":"Nightingale Avenue",
    "iso:country":"GB",
    "sg:address":"Po Box 66 Redcote House, Nightingale Avenue",
    "sg:city":"Leatherhead",
    "sg:classifiers":[
        {
            "category":"Banks & Credit Unions",
            "subcategory":"Financial Services",
            "type":"Services"
        }
    ],
    "sg:postcode":"KT24 6YB",
    "sg:province":"Surrey",
    "sg:tags":[
        "adviser"
    ],
    "wof:name":"Russell Brewer Investments Ltd",
    "wof:placetype":"venue"
},
  "geometry": {"coordinates":[-0.44637,51.274139],"type":"Point"}
}