{
  "type": "Feature",
  "properties": {
    "addr:full":"9 Stroud Green Rd London Greater London N4 2DQ",
    "addr:housenumber":"9",
    "addr:postcode":"n4 2dq",
    "addr:street":"Stroud Green Rd",
    "iso:country":"GB",
    "sg:address":"9 Stroud Green Rd",
    "sg:city":"London",
    "sg:classifiers":[
        {
            "category":"Personal",
            "subcategory":"Beauty Salon",
            "type":"Services"
        }
    ],
    "sg:phone":"+44 20 7263 2483",
    "sg:postcode":"N4 2DQ",
    "sg:province":"Greater London",
    "sg:tags":[
        "unisex",
        "hairdresser"
    ],
    "wof:name":"Aquarius",
    "wof:placetype":"venue"
},
  "geometry": {"coordinates":[-0.1053479984,51.5648231506],"type":"Point"}
}