{
  "type": "Feature",
  "properties": {
    "addr:full":"13 Kingsteignton Road Newton Abbot Devon TQ12 2PQ",
    "addr:housenumber":"13",
    "addr:postcode":"tq12 2pq",
    "addr:street":"Kingsteignton Road",
    "iso:country":"GB",
    "sg:address":"13 Kingsteignton Road",
    "sg:city":"Newton Abbot",
    "sg:classifiers":[
        {
            "category":"Personal",
            "subcategory":"Beauty Salon",
            "type":"Services"
        }
    ],
    "sg:phone":"+44 1626 365310",
    "sg:postcode":"TQ12 2PQ",
    "sg:province":"Devon",
    "sg:tags":[
        "unisex",
        "hairdresser"
    ],
    "wof:name":"Daroma Hair Stylists",
    "wof:placetype":"venue"
},
  "geometry": {"coordinates":[-3.608698,50.532059],"type":"Point"}
}