{
  "type": "Feature",
  "properties": {
    "addr:full":"4 Shelley Gro, Droylsden Manchester Greater Manchester M43 7YG",
    "addr:housenumber":"4",
    "addr:postcode":"m43 7yg",
    "addr:street":"Shelley Gro",
    "iso:country":"GB",
    "sg:address":"4 Shelley Gro, Droylsden",
    "sg:city":"Manchester",
    "sg:classifiers":[
        {
            "category":"Building & Trades",
            "subcategory":"Construction",
            "type":"Services"
        }
    ],
    "sg:postcode":"M43 7YG",
    "sg:province":"Greater Manchester",
    "sg:tags":[
        "platform",
        "work",
        "scaffolding"
    ],
    "wof:name":"D J B Scaffolding",
    "wof:placetype":"venue"
},
  "geometry": {"coordinates":[-2.14960289,53.4837112427],"type":"Point"}
}