{
  "type": "Feature",
  "properties": {
    "addr:full":"767 Old Lode La Solihull West Midlands B92 8JE",
    "addr:housenumber":"767",
    "addr:postcode":"b92 8je",
    "addr:street":"Old Lode La Solihull",
    "iso:country":"GB",
    "sg:address":"767 Old Lode La",
    "sg:city":"Solihull",
    "sg:classifiers":[
        {
            "category":"Sports & Exercise",
            "subcategory":"Tennis Court",
            "type":"Entertainment"
        }
    ],
    "sg:postcode":"B92 8JE",
    "sg:province":"West Midlands",
    "sg:tags":[
        "breakdown",
        "recovery"
    ],
    "wof:name":"West Midlands Recovery",
    "wof:placetype":"venue"
},
  "geometry": {"coordinates":[-1.778646946,52.4484062195],"type":"Point"}
}