{
  "type": "Feature",
  "properties": {
    "addr:full":"36 High Street, Tarring Worthing West Sussex BN14 7NR",
    "addr:housenumber":"36",
    "addr:postcode":"bn14 7nr",
    "addr:street":"High Street",
    "iso:country":"GB",
    "sg:address":"36 High Street, Tarring",
    "sg:city":"Worthing",
    "sg:classifiers":[
        {
            "category":"Professional",
            "subcategory":"Accounting & Tax Preparation",
            "type":"Services"
        }
    ],
    "sg:phone":"+44 1903 213262",
    "sg:postcode":"BN14 7NR",
    "sg:province":"West Sussex",
    "sg:tags":[
        "accountant"
    ],
    "wof:name":"Calder & Co",
    "wof:placetype":"venue"
},
  "geometry": {"coordinates":[-0.392401,50.825878],"type":"Point"}
}