{
  "type": "Feature",
  "properties": {
    "iso:country":"GB",
    "sg:address":"4 Clyde Ct",
    "sg:city":"Sunderland",
    "sg:classifiers":[
        {
            "category":"Social Services",
            "type":"Services"
        }
    ],
    "sg:phone":"+44 191 565 3805",
    "sg:postcode":"SR3 2JB",
    "sg:province":"Tyne and Wear",
    "sg:tags":[
        "need",
        "disability",
        "special"
    ],
    "wof:name":"M J D Installations",
    "wof:placetype":"venue"
},
  "geometry": {"coordinates":[-1.40981,54.86869],"type":"Point"}
}