{
  "type": "Feature",
  "properties": {
    "addr:full":"4 Roscoe Street Liverpool Merseyside L1 2SX",
    "addr:housenumber":"4",
    "addr:postcode":"l1 2sx",
    "addr:street":"Roscoe Street",
    "iso:country":"GB",
    "sg:address":"4 Roscoe Street",
    "sg:city":"Liverpool",
    "sg:classifiers":[
        {
            "category":"Real Estate",
            "subcategory":"Architect",
            "type":"Services"
        }
    ],
    "sg:phone":"+44 151 709 3800",
    "sg:postcode":"L1 2SX",
    "sg:province":"Merseyside",
    "wof:name":"O'MAHONY FOZARD",
    "wof:placetype":"venue"
},
  "geometry": {"coordinates":[-2.974132061,53.4025840759],"type":"Point"}
}