{
  "type": "Feature",
  "properties": {
    "iso:country":"GB",
    "sg:address":"15 Cootham Green",
    "sg:city":"Pulborough",
    "sg:classifiers":[
        {
            "category":"Military Area",
            "subcategory":"Air Force Base",
            "type":"Public Place"
        }
    ],
    "sg:phone":"+44 1903 741112",
    "sg:postcode":"RH20 4JW",
    "sg:province":"West Sussex",
    "sg:tags":[
        "supplier",
        "mnfrs",
        "plaster"
    ],
    "wof:name":"UK Interior Finishes Ltd",
    "wof:placetype":"venue"
},
  "geometry": {"coordinates":[-0.471498996,50.9205093384],"type":"Point"}
}