{
  "type": "Feature",
  "properties": {
    "iso:country":"GB",
    "sg:address":"Unit 2, St Andrews Park",
    "sg:city":"Wells",
    "sg:classifiers":[
        {
            "category":"Taxi",
            "type":"Transportation"
        },
        {
            "category":"Military Area",
            "subcategory":"Air Force Base",
            "type":"Public Place"
        }
    ],
    "sg:phone":"+44 1749 670200",
    "sg:postcode":"BA5 1TE",
    "sg:province":"Somerset",
    "sg:tags":[
        "hire",
        "private"
    ],
    "wof:name":"A Taxis",
    "wof:placetype":"venue"
},
  "geometry": {"coordinates":[-2.63764,51.211803],"type":"Point"}
}