{
  "type": "Feature",
  "properties": {
    "iso:country":"GB",
    "sg:address":"16 Evelyn Street",
    "sg:city":"London",
    "sg:classifiers":[
        {
            "category":"Building & Trades",
            "subcategory":"Cleaning & Sanitation",
            "type":"Services"
        }
    ],
    "sg:phone":"+44 20 7232 2232",
    "sg:postcode":"SE8 5DQ",
    "sg:province":"Greater London",
    "sg:tags":[
        "industrial",
        "business",
        "removal"
    ],
    "wof:name":"Rentacrate",
    "wof:placetype":"venue"
},
  "geometry": {"coordinates":[-0.042259,51.490089],"type":"Point"}
}