{
  "type": "Feature",
  "properties": {
    "addr:full":"204 Elgar Road South Reading Berkshire RG2 0DD",
    "addr:housenumber":"204",
    "addr:postcode":"rg2 0dd",
    "addr:street":"Elgar Road South",
    "iso:country":"GB",
    "sg:address":"204 Elgar Road South",
    "sg:city":"Reading",
    "sg:classifiers":[
        {
            "category":"Home & Garden",
            "subcategory":"Home Furnishings",
            "type":"Retail Goods"
        }
    ],
    "sg:postcode":"RG2 0DD",
    "sg:province":"Berkshire",
    "sg:tags":[
        "furnishers",
        "planner",
        "kitchen"
    ],
    "wof:name":"New View Designs",
    "wof:placetype":"venue"
},
  "geometry": {"coordinates":[-0.972547,51.444347],"type":"Point"}
}