{
  "type": "Feature",
  "properties": {
    "addr:full":"79 Waterloo Road London Greater London SE1 8UD",
    "addr:housenumber":"79",
    "addr:postcode":"se1 8ud",
    "addr:street":"Waterloo Road",
    "iso:country":"GB",
    "sg:address":"79 Waterloo Road",
    "sg:city":"London",
    "sg:classifiers":[
        {
            "category":"Restaurant",
            "type":"Food & Drink"
        }
    ],
    "sg:phone":"+44 20 7928 3856",
    "sg:postcode":"SE1 8UD",
    "sg:province":"Greater London",
    "sg:tags":[
        "indian"
    ],
    "wof:name":"Thames Tandoori Restaurant Ltd.",
    "wof:placetype":"venue"
},
  "geometry": {"coordinates":[-0.111763,51.503723],"type":"Point"}
}