{
  "type": "Feature",
  "properties": {
    "addr:full":"Timber Hill Road Caterham Surrey CR3 6LD",
    "addr:postcode":"cr3 6ld",
    "addr:street":"Hill Road",
    "iso:country":"GB",
    "sg:address":"Timber Hill Road",
    "sg:city":"Caterham",
    "sg:classifiers":[
        {
            "category":"Education",
            "subcategory":"Special Training",
            "type":"Public Place"
        }
    ],
    "sg:phone":"+44 1883 342351",
    "sg:postcode":"CR3 6LD",
    "sg:province":"Surrey",
    "sg:tags":[
        "aid",
        "first"
    ],
    "wof:name":"St.John Ambulance",
    "wof:placetype":"venue"
},
  "geometry": {"coordinates":[-0.0749349967,51.2819404602],"type":"Point"}
}