{
  "type": "Feature",
  "properties": {
    "addr:full":"6th Floor, 20 Barlderton Street London Greater London W1K 6TL",
    "addr:housenumber":"6th floor 20",
    "addr:postcode":"w1k 6tl",
    "addr:street":"Barlderton Street",
    "iso:country":"GB",
    "sg:address":"6th Floor, 20 Barlderton Street",
    "sg:city":"London",
    "sg:classifiers":[
        {
            "category":"Shopping",
            "subcategory":"Mobile Phones",
            "type":"Retail Goods"
        }
    ],
    "sg:phone":"+44 20 7399 3366",
    "sg:postcode":"W1K 6TL",
    "sg:province":"Greater London",
    "wof:name":"Amitel Ltd.",
    "wof:placetype":"venue"
},
  "geometry": {"coordinates":[-0.15233,51.513779],"type":"Point"}
}