{
  "type": "Feature",
  "properties": {
    "addr:full":"4 Eastgate Street Gloucester Gloucestershire GL1 1PA",
    "addr:housenumber":"4",
    "addr:postcode":"gl1 1pa",
    "addr:street":"Eastgate Street",
    "iso:country":"GB",
    "sg:address":"4 Eastgate Street",
    "sg:city":"Gloucester",
    "sg:classifiers":[
        {
            "category":"Shopping",
            "subcategory":"Clothing, Apparel, & Fashions",
            "type":"Retail Goods"
        }
    ],
    "sg:postcode":"GL1 1PA",
    "sg:province":"Gloucestershire",
    "sg:tags":[
        "menswear"
    ],
    "wof:name":"Moss Bros Group Plc",
    "wof:placetype":"venue"
},
  "geometry": {"coordinates":[-2.2440240383,51.8641471863],"type":"Point"}
}