{
  "type": "Feature",
  "properties": {
    "addr:full":"113 Roman Road, Birstall Leicester Leicestershire LE4 4BF",
    "addr:housenumber":"113",
    "addr:postcode":"le4 4bf",
    "addr:street":"Roman Road",
    "iso:country":"GB",
    "sg:address":"113 Roman Road, Birstall",
    "sg:city":"Leicester",
    "sg:classifiers":[
        {
            "category":"Professional",
            "subcategory":"Engineering",
            "type":"Services"
        },
        {
            "category":"Building & Trades",
            "subcategory":"Electrical",
            "type":"Services"
        }
    ],
    "sg:phone":"+44 116 267 1862",
    "sg:postcode":"LE4 4BF",
    "sg:province":"Leicestershire",
    "sg:tags":[
        "engineer",
        "electrician",
        "contractor"
    ],
    "wof:name":"County Electrical Installations",
    "wof:placetype":"venue"
},
  "geometry": {"coordinates":[-1.126445055,52.67237854],"type":"Point"}
}