{
  "type": "Feature",
  "properties": {
    "iso:country":"GB",
    "sg:address":"6 Woodseats Rd",
    "sg:city":"Sheffield",
    "sg:classifiers":[
        {
            "category":"Professional",
            "subcategory":"Printing & Photocopies",
            "type":"Services"
        }
    ],
    "sg:postcode":"S8 0PD",
    "sg:province":"Derbyshire",
    "sg:tags":[
        "printer"
    ],
    "wof:name":"Bromley,Tony,",
    "wof:placetype":"venue"
},
  "geometry": {"coordinates":[-1.4859819412,53.3520965576],"type":"Point"}
}