{
  "type": "Feature",
  "properties": {
    "iso:country":"GB",
    "sg:address":"2 Whitegate Hill, Caistor",
    "sg:city":"Lincoln",
    "sg:classifiers":[
        {
            "category":"Building & Trades",
            "subcategory":"Construction",
            "type":"Services"
        }
    ],
    "sg:postcode":"LN7 6SW",
    "sg:province":"Lincolnshire",
    "sg:tags":[
        "heating",
        "contractor"
    ],
    "wof:name":"Phil Ingle",
    "wof:placetype":"venue"
},
  "geometry": {"coordinates":[-0.3127909899,53.494392395],"type":"Point"}
}