{
  "type": "Feature",
  "properties": {
    "iso:country":"GB",
    "sg:address":"11 Broad Street",
    "sg:city":"Teddington",
    "sg:classifiers":[
        {
            "category":"Professional",
            "type":"Services"
        }
    ],
    "sg:phone":"+44 20 8977 9222",
    "sg:postcode":"TW11 8RA",
    "sg:province":"Greater London",
    "sg:tags":[
        "repair",
        "tech",
        "maintenance"
    ],
    "wof:name":"Excan Computer Maintenance & Supplies Lt",
    "wof:placetype":"venue"
},
  "geometry": {"coordinates":[-0.339475,51.426315],"type":"Point"}
}