{
  "type": "Feature",
  "properties": {
    "addr:full":"59 Kelvin Avenue, Hillington Industrial Estate Glasgow Glasgow City G52 4LR",
    "addr:housenumber":"59",
    "addr:postcode":"g52 4lr",
    "addr:street":"Kelvin Avenue;Industrial Estate",
    "iso:country":"GB",
    "sg:address":"59 Kelvin Avenue, Hillington Industrial Estate",
    "sg:city":"Glasgow",
    "sg:classifiers":[
        {
            "category":"Professional",
            "subcategory":"Accounting & Tax Preparation",
            "type":"Services"
        }
    ],
    "sg:phone":"+44 141 883 4797",
    "sg:postcode":"G52 4LR",
    "sg:province":"Glasgow City",
    "sg:tags":[
        "herb",
        "spice"
    ],
    "wof:name":"Spicemanns Ltd.",
    "wof:placetype":"venue"
},
  "geometry": {"coordinates":[-4.367719,55.862953],"type":"Point"}
}