{
  "type": "Feature",
  "properties": {
    "addr:full":"Amco House, 30 Norfolk St Sunderland Tyne and Wear SR1 1EE",
    "addr:housenumber":"30",
    "addr:postcode":"sr1 1ee",
    "addr:street":"Norfolk St",
    "iso:country":"GB",
    "sg:address":"Amco House, 30 Norfolk St",
    "sg:city":"Sunderland",
    "sg:classifiers":[
        {
            "category":"Professional",
            "subcategory":"Computer Services",
            "type":"Services"
        }
    ],
    "sg:phone":"+44 191 567 4310",
    "sg:postcode":"SR1 1EE",
    "sg:province":"Tyne and Wear",
    "sg:tags":[
        "system",
        "software"
    ],
    "wof:name":"Amco Computer Services",
    "wof:placetype":"venue"
},
  "geometry": {"coordinates":[-1.377022028,54.9056091309],"type":"Point"}
}