{
  "type": "Feature",
  "properties": {
    "iso:country":"GB",
    "sg:address":"4-5 Gerrard St",
    "sg:city":"London",
    "sg:classifiers":[
        {
            "category":"Restaurant",
            "type":"Food & Drink"
        }
    ],
    "sg:postcode":"W1D 5PP",
    "sg:province":"Greater London",
    "sg:tags":[
        "chinese"
    ],
    "wof:name":"Lok Ho Fook",
    "wof:placetype":"venue"
},
  "geometry": {"coordinates":[-0.1304890066,51.5121574402],"type":"Point"}
}