{
  "type": "Feature",
  "properties": {
    "addr:full":"Wareham Road, Rednal Birmingham West Midlands B45 0JS",
    "addr:postcode":"b45 0js",
    "addr:street":"Wareham Road",
    "iso:country":"GB",
    "sg:address":"Wareham Road, Rednal",
    "sg:city":"Birmingham",
    "sg:classifiers":[
        {
            "category":"Bars & Pubs",
            "type":"Food & Drink"
        }
    ],
    "sg:postcode":"B45 0JS",
    "sg:province":"West Midlands",
    "sg:tags":[
        "pubs",
        "inn"
    ],
    "wof:name":"The Bugle Horn",
    "wof:placetype":"venue"
},
  "geometry": {"coordinates":[-2.004799,52.408131],"type":"Point"}
}