{
  "type": "Feature",
  "properties": {
    "addr:full":"21 Towler Street Peterborough Cambridgeshire PE1 2TX",
    "addr:housenumber":"21",
    "addr:postcode":"pe1 2tx",
    "addr:street":"Towler Street",
    "iso:country":"GB",
    "sg:address":"21 Towler Street",
    "sg:city":"Peterborough",
    "sg:classifiers":[
        {
            "category":"Travel",
            "subcategory":"Hostel",
            "type":"Entertainment"
        }
    ],
    "sg:phone":"+44 1733 342876",
    "sg:postcode":"PE1 2TX",
    "sg:province":"Cambridgeshire",
    "wof:name":"Towler Street Hostel",
    "wof:placetype":"venue"
},
  "geometry": {"coordinates":[-0.242221,52.579704],"type":"Point"}
}