{
  "type": "Feature",
  "properties": {
    "iso:country":"GB",
    "sg:address":"56 Harrogate Road",
    "sg:city":"Leeds",
    "sg:classifiers":[
        {
            "category":"Home & Garden",
            "subcategory":"Home Furnishings",
            "type":"Retail Goods"
        },
        {
            "category":"Home & Garden",
            "subcategory":"Furniture",
            "type":"Retail Goods"
        }
    ],
    "sg:phone":"+44 113 237 4801",
    "sg:postcode":"LS7 4LA",
    "sg:province":"West Yorkshire",
    "sg:tags":[
        "pine"
    ],
    "wof:name":"Rustic Pine",
    "wof:placetype":"venue"
},
  "geometry": {"coordinates":[-1.535195,53.8265],"type":"Point"}
}