{
  "type": "Feature",
  "properties": {
    "iso:country":"GB",
    "sg:address":"Club House, Links Road",
    "sg:city":"Weymouth",
    "sg:classifiers":[
        {
            "category":"Sports & Exercise",
            "subcategory":"Golf",
            "type":"Entertainment"
        }
    ],
    "sg:phone":"+44 1305 773981",
    "sg:postcode":"DT4 0PF",
    "sg:province":"Dorset",
    "sg:tags":[
        "club",
        "course",
        "equipment"
    ],
    "wof:name":"Weymouth Golf Club Ltd.",
    "wof:placetype":"venue"
},
  "geometry": {"coordinates":[-2.470014,50.616119],"type":"Point"}
}