{
  "type": "Feature",
  "properties": {
    "addr:full":"The Causeway Industrial Estate, 7 Galliford Road Maldon Essex CM9 4XD",
    "addr:housenumber":"7",
    "addr:postcode":"cm9 4xd",
    "addr:street":"The Causeway Industrial Estate;Galliford Road",
    "iso:country":"GB",
    "sg:address":"The Causeway Industrial Estate, 7 Galliford Road",
    "sg:city":"Maldon",
    "sg:classifiers":[
        {
            "category":"Autos & Motor Vehicles",
            "subcategory":"Auto Supplies",
            "type":"Retail Goods"
        }
    ],
    "sg:phone":"+44 1621 843770",
    "sg:postcode":"CM9 4XD",
    "sg:province":"Essex",
    "sg:tags":[
        "car",
        "accessory"
    ],
    "wof:name":"Wolfrace Wheels (Uk) Ltd.",
    "wof:placetype":"venue"
},
  "geometry": {"coordinates":[0.675249,51.731377],"type":"Point"}
}