{
  "type": "Feature",
  "properties": {
    "addr:full":"Millstone Cottage, 73 Buchanan Rd, Arncott,bicester Oxford Oxfordshire OX25 1TE",
    "addr:housenumber":"73",
    "addr:postcode":"ox25 1te",
    "addr:street":"Buchanan Rd",
    "iso:country":"GB",
    "sg:address":"Millstone Cottage, 73 Buchanan Rd, Arncott,bicester",
    "sg:city":"Oxford",
    "sg:classifiers":[
        {
            "category":"Wholesale",
            "subcategory":"Non-durable Goods",
            "type":"Manufacturing & Wholesale Goods"
        }
    ],
    "sg:postcode":"OX25 1TE",
    "sg:province":"Oxfordshire",
    "sg:tags":[
        "carry",
        "cash"
    ],
    "wof:name":"Arnold,Colin B,",
    "wof:placetype":"venue"
},
  "geometry": {"coordinates":[-1.0920540094,51.850566864],"type":"Point"}
}