{
  "type": "Feature",
  "properties": {
    "iso:country":"GB",
    "sg:address":"57 Cowley Road",
    "sg:city":"Blackpool",
    "sg:classifiers":[
        {
            "category":"Wholesale",
            "subcategory":"Scrap",
            "type":"Manufacturing & Wholesale Goods"
        }
    ],
    "sg:phone":"+44 1253 769764",
    "sg:postcode":"FY4 4NE",
    "sg:province":"Lancashire",
    "sg:tags":[
        "breaker",
        "dismantlers"
    ],
    "wof:name":"C I Motors",
    "wof:placetype":"venue"
},
  "geometry": {"coordinates":[-3.020912,53.797215],"type":"Point"}
}