{
  "type": "Feature",
  "properties": {
    "iso:country":"GB",
    "sg:address":"3 Stoke Newington Road",
    "sg:city":"London",
    "sg:classifiers":[
        {
            "category":"Food & Beverages",
            "subcategory":"Meat & Fish",
            "type":"Retail Goods"
        }
    ],
    "sg:phone":"+44 20 7923 2382",
    "sg:postcode":"N16 8BH",
    "sg:province":"Greater London",
    "sg:tags":[
        "butcher"
    ],
    "wof:name":"Binboga Butchers",
    "wof:placetype":"venue"
},
  "geometry": {"coordinates":[-0.074849,51.553421],"type":"Point"}
}