{
  "type": "Feature",
  "properties": {
    "iso:country":"GB",
    "sg:address":"Daleston Court, Southey Hill Trading Estate",
    "sg:city":"Keswick",
    "sg:classifiers":[
        {
            "category":"Autos & Motor Vehicles",
            "subcategory":"Auto Supplies",
            "type":"Retail Goods"
        }
    ],
    "sg:phone":"+44 17687 75842",
    "sg:postcode":"CA12 5LG",
    "sg:province":"Cumbria",
    "sg:tags":[
        "tyre"
    ],
    "wof:name":"Goodfellow & Sons",
    "wof:placetype":"venue"
},
  "geometry": {"coordinates":[-3.1345090866,54.6009178162],"type":"Point"}
}