{
  "type": "Feature",
  "properties": {
    "iso:country":"GB",
    "sg:address":"Greenman Tower, 332 Goswell Rd",
    "sg:city":"Clerkenwell",
    "sg:classifiers":[
        {
            "category":"Retail",
            "subcategory":"Event Space",
            "type":"Services"
        }
    ],
    "sg:phone":"+44 20 7713 0001",
    "sg:postcode":"EC1V 7LQ",
    "sg:province":"Greater London",
    "sg:tags":[
        "exhibition",
        "organiser"
    ],
    "wof:name":"Jobspec",
    "wof:placetype":"venue"
},
  "geometry": {"coordinates":[-0.10352,51.530602],"type":"Point"}
}