{
  "type": "Feature",
  "properties": {
    "addr:full":"118 Flixton Road, Urmston Manchester Cheshire M41 5AL",
    "addr:housenumber":"118",
    "addr:postcode":"m41 5al",
    "addr:street":"Flixton Road",
    "iso:country":"GB",
    "sg:address":"118 Flixton Road, Urmston",
    "sg:city":"Manchester",
    "sg:classifiers":[
        {
            "category":"Education",
            "subcategory":"College",
            "type":"Public Place"
        }
    ],
    "sg:postcode":"M41 5AL",
    "sg:province":"Cheshire",
    "sg:tags":[
        "school"
    ],
    "wof:name":"Togs & Clogs",
    "wof:placetype":"venue"
},
  "geometry": {"coordinates":[-2.361046,53.448139],"type":"Point"}
}