{
  "type": "Feature",
  "properties": {
    "iso:country":"GB",
    "sg:address":"Pexhill Rd, Henbury",
    "sg:city":"Macclesfield",
    "sg:classifiers":[
        {
            "category":"Farming",
            "subcategory":"Farm",
            "type":"Manufacturing & Wholesale Goods"
        }
    ],
    "sg:postcode":"SK11 9PY",
    "sg:province":"Cheshire",
    "sg:tags":[
        "mixed",
        "crop"
    ],
    "wof:name":"Pexhill Farm",
    "wof:placetype":"venue"
},
  "geometry": {"coordinates":[-2.1685950756,53.2538108826],"type":"Point"}
}