{
  "type": "Feature",
  "properties": {
    "addr:full":"27 Ranfurly Road Bridge Of Weir Inverclyde PA11 3EL",
    "addr:housenumber":"27",
    "addr:postcode":"pa11 3el",
    "addr:street":"Ranfurly Road",
    "iso:country":"GB",
    "sg:address":"27 Ranfurly Road",
    "sg:city":"Bridge Of Weir",
    "sg:classifiers":[
        {
            "category":"Home & Garden",
            "subcategory":"Home Furnishings",
            "type":"Retail Goods"
        }
    ],
    "sg:postcode":"PA11 3EL",
    "sg:province":"Inverclyde",
    "sg:tags":[
        "furnishers",
        "planner",
        "kitchen"
    ],
    "wof:name":"D K Ross Kitchen Design",
    "wof:placetype":"venue"
},
  "geometry": {"coordinates":[-4.582529068,55.8567199707],"type":"Point"}
}