{
  "type": "Feature",
  "properties": {
    "iso:country":"GB",
    "sg:address":"2 Ruskin Avenue",
    "sg:city":"Middlesbrough",
    "sg:classifiers":[
        {
            "category":"Building & Trades",
            "subcategory":"Construction",
            "type":"Services"
        }
    ],
    "sg:postcode":"TS5 8PJ",
    "sg:province":"North Yorkshire",
    "sg:tags":[
        "builder"
    ],
    "wof:name":"I D Vickers",
    "wof:placetype":"venue"
},
  "geometry": {"coordinates":[-1.259635,54.544575],"type":"Point"}
}