{
  "type": "Feature",
  "properties": {
    "addr:full":"34 Acorn Units, Ellough Indust Est, Ellough Rd Beccles Norfolk NR34 7TD",
    "addr:housenumber":"34",
    "addr:postcode":"nr34 7td",
    "addr:street":"Acorn Units;Indust Est Ellough Rd",
    "iso:country":"GB",
    "sg:address":"34 Acorn Units, Ellough Indust Est, Ellough Rd",
    "sg:city":"Beccles",
    "sg:classifiers":[
        {
            "category":"Home & Garden",
            "subcategory":"Home Furnishings",
            "type":"Retail Goods"
        }
    ],
    "sg:phone":"+44 1502 518812",
    "sg:postcode":"NR34 7TD",
    "sg:province":"Norfolk",
    "sg:tags":[
        "awning",
        "canopy",
        "blinds"
    ],
    "wof:name":"Siesta Blinds",
    "wof:placetype":"venue"
},
  "geometry": {"coordinates":[1.592325,52.426609],"type":"Point"}
}