{
  "type": "Feature",
  "properties": {
    "addr:full":"Unit 2a Borough Road, Buckingham Road Industrial Estate Brackley Buckinghamshire NN13 7BE",
    "addr:housenumber":"unit 2a",
    "addr:postcode":"nn13 7be",
    "addr:street":"Borough Road Buckingham Road Industrial Estate Brackley",
    "iso:country":"GB",
    "sg:address":"Unit 2a Borough Road, Buckingham Road Industrial Estate",
    "sg:city":"Brackley",
    "sg:classifiers":[
        {
            "category":"Home & Garden",
            "subcategory":"Carpets & Floor Coverings",
            "type":"Retail Goods"
        }
    ],
    "sg:postcode":"NN13 7BE",
    "sg:province":"Buckinghamshire",
    "sg:tags":[
        "carpets",
        "rug",
        "matting"
    ],
    "wof:name":"Listbasic Ltd.",
    "wof:placetype":"venue"
},
  "geometry": {"coordinates":[-1.141674,52.023457],"type":"Point"}
}