{
  "type": "Feature",
  "properties": {
    "iso:country":"GB",
    "sg:address":"The Hook Farm, Hook Bank, Hanley Castle",
    "sg:city":"Worcester",
    "sg:classifiers":[
        {
            "category":"Farming",
            "subcategory":"Livestock Farm",
            "type":"Manufacturing & Wholesale Goods"
        }
    ],
    "sg:phone":"+44 1684 592303",
    "sg:postcode":"WR8 0BA",
    "sg:province":"Gloucestershire",
    "sg:tags":[
        "others"
    ],
    "wof:name":"J D & H M Roberts",
    "wof:placetype":"venue"
},
  "geometry": {"coordinates":[-2.233494,52.076782],"type":"Point"}
}