{
  "type": "Feature",
  "properties": {
    "addr:full":"West Avenue, Gosforth Newcastle Upon Tyne Tyne and Wear NE3 4ES",
    "addr:postcode":"ne3 4es",
    "addr:street":"West Avenue",
    "iso:country":"GB",
    "sg:address":"West Avenue, Gosforth",
    "sg:city":"Newcastle Upon Tyne",
    "sg:classifiers":[
        {
            "category":"Place Of Worship",
            "type":"Public Place"
        }
    ],
    "sg:phone":"+44 191 285 6130",
    "sg:postcode":"NE3 4ES",
    "sg:province":"Tyne and Wear",
    "wof:name":"West Avenue Methodist Church",
    "wof:placetype":"venue"
},
  "geometry": {"coordinates":[-1.6236690283,55.00440979],"type":"Point"}
}