{
  "type": "Feature",
  "properties": {
    "addr:full":"Bideford Medical Centre, Abbotsham Rd Bideford Devon EX39 3AF",
    "addr:postcode":"ex39 3af",
    "addr:street":"Abbotsham Rd",
    "iso:country":"GB",
    "sg:address":"Bideford Medical Centre, Abbotsham Rd",
    "sg:city":"Bideford",
    "sg:classifiers":[
        {
            "category":"Health Services",
            "subcategory":"Doctor",
            "type":"Services"
        }
    ],
    "sg:phone":"+44 1237 476363",
    "sg:postcode":"EX39 3AF",
    "sg:province":"Devon",
    "sg:tags":[
        "practitioners"
    ],
    "wof:name":"Ford, R",
    "wof:placetype":"venue"
},
  "geometry": {"coordinates":[-4.2042589188,51.0192489624],"type":"Point"}
}