{
  "type": "Feature",
  "properties": {
    "addr:full":"48 Stanhope Street London Greater London NW1 3EX",
    "addr:housenumber":"48",
    "addr:postcode":"nw1 3ex",
    "addr:street":"Stanhope Street",
    "iso:country":"GB",
    "sg:address":"48 Stanhope Street",
    "sg:city":"London",
    "sg:classifiers":[
        {
            "category":"Bars & Pubs",
            "type":"Food & Drink"
        }
    ],
    "sg:postcode":"NW1 3EX",
    "sg:province":"Greater London",
    "sg:tags":[
        "pubs",
        "inn"
    ],
    "wof:name":"Cap'n Cutlers",
    "wof:placetype":"venue"
},
  "geometry": {"coordinates":[-0.140668,51.526176],"type":"Point"}
}