{
  "type": "Feature",
  "properties": {
    "iso:country":"GB",
    "sg:address":"11 Victoria Road",
    "sg:city":"Dartmouth",
    "sg:classifiers":[
        {
            "category":"Shopping",
            "subcategory":"Clothing, Apparel, & Fashions",
            "type":"Retail Goods"
        },
        {
            "category":"Professional",
            "subcategory":"Management & Consulting",
            "type":"Services"
        }
    ],
    "sg:phone":"+44 1803 834006",
    "sg:postcode":"TQ6 9RT",
    "sg:province":"Devon",
    "sg:tags":[
        "consultant",
        "direct",
        "leisure",
        "sale",
        "wear",
        "promotion"
    ],
    "wof:name":"Imago Trading Co.",
    "wof:placetype":"venue"
},
  "geometry": {"coordinates":[-3.5799839497,50.3514785767],"type":"Point"}
}