{
  "type": "Feature",
  "properties": {
    "addr:full":"15 St.thomas's Rd Chorley Lancashire PR7 1HP",
    "addr:housenumber":"15",
    "addr:postcode":"pr7 1hp",
    "addr:street":"St.Thomas'S Rd",
    "iso:country":"GB",
    "sg:address":"15 St.thomas's Rd",
    "sg:city":"Chorley",
    "sg:classifiers":[
        {
            "category":"Bars & Pubs",
            "type":"Food & Drink"
        }
    ],
    "sg:phone":"+44 1257 232065",
    "sg:postcode":"PR7 1HP",
    "sg:province":"Lancashire",
    "sg:tags":[
        "pubs",
        "inn"
    ],
    "wof:name":"Rose & Crown",
    "wof:placetype":"venue"
},
  "geometry": {"coordinates":[-2.633641,53.653667],"type":"Point"}
}