{
  "type": "Feature",
  "properties": {
    "addr:full":"Glen Nevis Fort William Highland PH33 6PF",
    "addr:postcode":"ph33 6pf",
    "addr:street":"Glen Nevis;William",
    "iso:country":"GB",
    "sg:address":"Glen Nevis",
    "sg:city":"Fort William",
    "sg:classifiers":[
        {
            "category":"Government",
            "subcategory":"Office",
            "type":"Public Place"
        },
        {
            "category":"Landmark",
            "subcategory":"Tourist Attraction",
            "type":"Public Place"
        }
    ],
    "sg:phone":"+44 1397 705922",
    "sg:postcode":"PH33 6PF",
    "sg:province":"Highland",
    "sg:tags":[
        "local",
        "interest"
    ],
    "wof:name":"Lonad Nibheis Visitor Centre",
    "wof:placetype":"venue"
},
  "geometry": {"coordinates":[-5.09146,56.82135],"type":"Point"}
}