{
  "type": "Feature",
  "properties": {
    "iso:country":"GB",
    "sg:address":"20 Cowbridge Road West",
    "sg:city":"Cardiff",
    "sg:classifiers":[
        {
            "category":"Professional",
            "subcategory":"Lawyer & Legal Services",
            "type":"Services"
        }
    ],
    "sg:postcode":"CF5 5BS",
    "sg:province":"Cardiff",
    "sg:tags":[
        "solicitor"
    ],
    "wof:name":"Colin Jones",
    "wof:placetype":"venue"
},
  "geometry": {"coordinates":[-3.233734,51.483147],"type":"Point"}
}