{
  "type": "Feature",
  "properties": {
    "addr:full":"Botanic Gardens Southport Lancashire PR9 7NB",
    "addr:postcode":"pr9 7nb",
    "iso:country":"GB",
    "sg:address":"Botanic Gardens",
    "sg:city":"Southport",
    "sg:classifiers":[
        {
            "category":"Cafe",
            "type":"Food & Drink"
        }
    ],
    "sg:phone":"+44 1704 228535",
    "sg:postcode":"PR9 7NB",
    "sg:province":"Lancashire",
    "sg:tags":[
        "tea",
        "room"
    ],
    "wof:name":"HESKETH PARK GIFT SHOP",
    "wof:placetype":"venue"
},
  "geometry": {"coordinates":[-2.9623639584,53.6596641541],"type":"Point"}
}