{
  "type": "Feature",
  "properties": {
    "addr:full":"Unit 13-14, Woods Browning Industrial Estate, Respryn Road Bodmin Cornwall PL31 1DQ",
    "addr:housenumber":"unit 13-14",
    "addr:postcode":"pl31 1dq",
    "addr:street":"Woods Browning Industrial;Respryn Road",
    "iso:country":"GB",
    "sg:address":"Unit 13-14, Woods Browning Industrial Estate, Respryn Road",
    "sg:city":"Bodmin",
    "sg:classifiers":[
        {
            "category":"Organizations",
            "subcategory":"Non-profit Organization",
            "type":"Services"
        }
    ],
    "sg:phone":"+44 1208 78663",
    "sg:postcode":"PL31 1DQ",
    "sg:province":"Cornwall",
    "sg:tags":[
        "organisation",
        "voluntary",
        "charity"
    ],
    "wof:name":"Pentreath Ltd.",
    "wof:placetype":"venue"
},
  "geometry": {"coordinates":[-4.7163691521,50.4710464478],"type":"Point"}
}