{
  "type": "Feature",
  "properties": {
    "addr:full":"41 Wilmslow Rd Manchester Greater Manchester M14 5TB",
    "addr:housenumber":"41",
    "addr:postcode":"m14 5tb",
    "addr:street":"Wilmslow Rd",
    "iso:country":"GB",
    "sg:address":"41 Wilmslow Rd",
    "sg:city":"Manchester",
    "sg:classifiers":[
        {
            "category":"Shopping",
            "subcategory":"Clothing, Apparel, & Fashions",
            "type":"Retail Goods"
        }
    ],
    "sg:postcode":"M14 5TB",
    "sg:province":"Greater Manchester",
    "sg:tags":[
        "shop"
    ],
    "wof:name":"Bombay Looks",
    "wof:placetype":"venue"
},
  "geometry": {"coordinates":[-2.222544,53.452286],"type":"Point"}
}