{
  "type": "Feature",
  "properties": {
    "addr:full":"4 Chenies Parade, Chalfont Station Road Amersham Buckinghamshire HP7 9PH",
    "addr:housenumber":"4",
    "addr:postcode":"hp7 9ph",
    "addr:street":"Chenies Parade;Station Road",
    "iso:country":"GB",
    "sg:address":"4 Chenies Parade, Chalfont Station Road",
    "sg:city":"Amersham",
    "sg:classifiers":[
        {
            "category":"Shopping",
            "subcategory":"Clothing, Apparel, & Fashions",
            "type":"Retail Goods"
        }
    ],
    "sg:postcode":"HP7 9PH",
    "sg:province":"Buckinghamshire",
    "sg:tags":[
        "menswear"
    ],
    "wof:name":"Marlyn Menswear",
    "wof:placetype":"venue"
},
  "geometry": {"coordinates":[-0.5630099773,51.6672058105],"type":"Point"}
}