{
  "type": "Feature",
  "properties": {
    "addr:full":"215 Whitton Road Twickenham Greater London TW2 7QZ",
    "addr:housenumber":"215",
    "addr:postcode":"tw2 7qz",
    "addr:street":"Whitton Road",
    "iso:country":"GB",
    "sg:address":"215 Whitton Road",
    "sg:city":"Twickenham",
    "sg:classifiers":[
        {
            "category":"Retail",
            "subcategory":"Auto Rental",
            "type":"Services"
        },
        {
            "category":"Autos & Motor Vehicles",
            "subcategory":"Motorcycle Sales",
            "type":"Retail Goods"
        }
    ],
    "sg:phone":"+44 20 8891 1093",
    "sg:postcode":"TW2 7QZ",
    "sg:province":"Greater London",
    "sg:tags":[
        "chauffeur",
        "driven",
        "hire",
        "car"
    ],
    "wof:name":"Wedding Carriage",
    "wof:placetype":"venue"
},
  "geometry": {"coordinates":[-0.3432149887,51.4538764954],"type":"Point"}
}