{
  "type": "Feature",
  "properties": {
    "iso:country":"GB",
    "sg:address":"130-134 Main Street",
    "sg:city":"Largs",
    "sg:classifiers":[
        {
            "category":"Fast Food",
            "type":"Food & Drink"
        }
    ],
    "sg:phone":"+44 1475 689993",
    "sg:postcode":"KA30 8JN",
    "sg:province":"North Ayrshire",
    "sg:tags":[
        "away",
        "take"
    ],
    "wof:name":"The Barbecue King",
    "wof:placetype":"venue"
},
  "geometry": {"coordinates":[-4.866152,55.793144],"type":"Point"}
}