{
  "type": "Feature",
  "properties": {
    "addr:full":"St Peters School Shop, Clifton York North Yorkshire YO30 6AB",
    "addr:postcode":"yo30 6ab",
    "iso:country":"GB",
    "sg:address":"St Peters School Shop, Clifton",
    "sg:city":"York",
    "sg:classifiers":[
        {
            "category":"Education",
            "subcategory":"College",
            "type":"Public Place"
        }
    ],
    "sg:postcode":"YO30 6AB",
    "sg:province":"North Yorkshire",
    "sg:tags":[
        "school"
    ],
    "wof:name":"St Peters School Shop",
    "wof:placetype":"venue"
},
  "geometry": {"coordinates":[-1.0904489756,53.9684524536],"type":"Point"}
}