{
  "type": "Feature",
  "properties": {
    "iso:country":"GB",
    "sg:address":"10 Ramsbury Close",
    "sg:city":"Bracknell",
    "sg:classifiers":[
        {
            "category":"Professional",
            "subcategory":"Engineering",
            "type":"Services"
        }
    ],
    "sg:phone":"+44 118 944 2404",
    "sg:postcode":"RG12 8GE",
    "sg:province":"Berkshire",
    "sg:tags":[
        "contractor",
        "electrical",
        "engineer"
    ],
    "wof:name":"K.E.B Engineering",
    "wof:placetype":"venue"
},
  "geometry": {"coordinates":[-0.776367,51.397972],"type":"Point"}
}