{
  "type": "Feature",
  "properties": {
    "iso:country":"GB",
    "sg:address":"Colliery Yard, Doncaster Road, Armthorpe",
    "sg:city":"Doncaster",
    "sg:classifiers":[
        {
            "category":"Organizations",
            "subcategory":"Membership Organization",
            "type":"Services"
        }
    ],
    "sg:phone":"+44 1302 831609",
    "sg:postcode":"DN3 2BW",
    "sg:province":"South Yorkshire",
    "sg:tags":[
        "club"
    ],
    "wof:name":"Markham Main Officals Club",
    "wof:placetype":"venue"
},
  "geometry": {"coordinates":[-1.0587099791,53.5438690186],"type":"Point"}
}