{
  "type": "Feature",
  "properties": {
    "iso:country":"GB",
    "sg:address":"Abbey Road",
    "sg:city":"Llangollen",
    "sg:classifiers":[
        {
            "category":"Government",
            "subcategory":"Office",
            "type":"Public Place"
        },
        {
            "category":"Landmark",
            "subcategory":"Tourist Attraction",
            "type":"Public Place"
        }
    ],
    "sg:phone":"+44 1978 860111",
    "sg:postcode":"LL20 8SW",
    "sg:province":"Denbighshire",
    "sg:tags":[
        "local",
        "interest"
    ],
    "wof:name":"Royal International Pavillion",
    "wof:placetype":"venue"
},
  "geometry": {"coordinates":[-3.175249,52.972416],"type":"Point"}
}