{
  "type": "Feature",
  "properties": {
    "iso:country":"GB",
    "sg:address":"Unit 26 Indust Est, Station Rd",
    "sg:city":"Horsham",
    "sg:classifiers":[
        {
            "category":"Freight",
            "type":"Transportation"
        }
    ],
    "sg:phone":"+44 1403 732911",
    "sg:postcode":"RH13 7UD",
    "sg:province":"West Sussex",
    "sg:tags":[
        "overseas",
        "shipping",
        "removal"
    ],
    "wof:name":"E E C Distribution",
    "wof:placetype":"venue"
},
  "geometry": {"coordinates":[-0.3291,51.065182],"type":"Point"}
}