{
  "type": "Feature",
  "properties": {
    "iso:country":"GB",
    "sg:address":"Training, Llys Ebwy, Alexandra Street",
    "sg:city":"Ebbw Vale",
    "sg:classifiers":[
        {
            "category":"Education",
            "subcategory":"Special Training",
            "type":"Public Place"
        }
    ],
    "sg:phone":"+44 1495 307617",
    "sg:postcode":"NP23 6LL",
    "sg:province":"Blaenau Gwent",
    "sg:tags":[
        "product",
        "centre"
    ],
    "wof:name":"Age Concern England (National Council of",
    "wof:placetype":"venue"
},
  "geometry": {"coordinates":[-3.214686,51.797028],"type":"Point"}
}