{
  "type": "Feature",
  "properties": {
    "addr:full":"Spencer Street, Heaton Newcastle-upon-tyne Tyne and Wear NE6 5BY",
    "addr:postcode":"ne6 5by",
    "addr:street":"Spencer Street",
    "iso:country":"GB",
    "sg:address":"Spencer Street, Heaton",
    "sg:city":"Newcastle-upon-tyne",
    "sg:classifiers":[
        {
            "category":"Train Station",
            "subcategory":"Rail",
            "type":"Transportation"
        }
    ],
    "sg:phone":"+44 1680 812314",
    "sg:postcode":"NE6 5BY",
    "sg:province":"Tyne and Wear",
    "sg:tags":[
        "railway"
    ],
    "wof:name":"Deltic 9000 Locomotives Ltd.",
    "wof:placetype":"venue"
},
  "geometry": {"coordinates":[-1.5753940344,54.9853401184],"type":"Point"}
}