{
  "type": "Feature",
  "properties": {
    "addr:full":"7 Owl Close South Croydon Surrey CR2 8ST",
    "addr:housenumber":"7",
    "addr:postcode":"cr2 8st",
    "addr:street":"Owl Close",
    "iso:country":"GB",
    "sg:address":"7 Owl Close",
    "sg:city":"South Croydon",
    "sg:classifiers":[
        {
            "category":"Professional",
            "subcategory":"Computer Services",
            "type":"Services"
        }
    ],
    "sg:postcode":"CR2 8ST",
    "sg:province":"Surrey",
    "sg:tags":[
        "system",
        "software"
    ],
    "wof:name":"Microcode Ltd.",
    "wof:placetype":"venue"
},
  "geometry": {"coordinates":[-0.049812,51.342812],"type":"Point"}
}