{
  "type": "Feature",
  "properties": {
    "addr:full":"Shillingstone Drive Bournemouth Dorset BH9 3LR",
    "addr:postcode":"bh9 3lr",
    "addr:street":"Shillingstone Drive",
    "iso:country":"GB",
    "sg:address":"Shillingstone Drive",
    "sg:city":"Bournemouth",
    "sg:classifiers":[
        {
            "category":"Food & Beverages",
            "subcategory":"Groceries & Convenience Stores",
            "type":"Retail Goods"
        }
    ],
    "sg:phone":"+44 1202 512991",
    "sg:postcode":"BH9 3LR",
    "sg:province":"Dorset",
    "wof:name":"One Stop",
    "wof:placetype":"venue"
},
  "geometry": {"coordinates":[-1.862300992,50.7614631653],"type":"Point"}
}