{
  "type": "Feature",
  "properties": {
    "addr:full":"Chartershall Farm, Chartershall Stirling Falkirk FK7 8HF",
    "addr:postcode":"fk7 8hf",
    "addr:street":"Chartershall",
    "iso:country":"GB",
    "sg:address":"Chartershall Farm, Chartershall",
    "sg:city":"Stirling",
    "sg:classifiers":[
        {
            "category":"Farming",
            "subcategory":"Crops",
            "type":"Manufacturing & Wholesale Goods"
        },
        {
            "category":"Farming",
            "subcategory":"Farm",
            "type":"Manufacturing & Wholesale Goods"
        }
    ],
    "sg:phone":"+44 1786 815799",
    "sg:postcode":"FK7 8HF",
    "sg:province":"Falkirk",
    "sg:tags":[
        "mixed",
        "arable"
    ],
    "wof:name":"A & M Wilson",
    "wof:placetype":"venue"
},
  "geometry": {"coordinates":[-3.9420540333,56.0900840759],"type":"Point"}
}