{
  "type": "Feature",
  "properties": {
    "addr:full":"Lennox House, 9 Lennox Street Bognor Regis West Sussex PO21 1LZ",
    "addr:housenumber":"9",
    "addr:postcode":"po21 1lz",
    "addr:street":"Lennox Street",
    "iso:country":"GB",
    "sg:address":"Lennox House, 9 Lennox Street",
    "sg:city":"Bognor Regis",
    "sg:classifiers":[
        {
            "category":"Professional",
            "subcategory":"Lawyer & Legal Services",
            "type":"Services"
        }
    ],
    "sg:postcode":"PO21 1LZ",
    "sg:province":"West Sussex",
    "sg:tags":[
        "solicitor"
    ],
    "wof:name":"Hobson & Rodgers",
    "wof:placetype":"venue"
},
  "geometry": {"coordinates":[-0.6746799946,50.7827110291],"type":"Point"}
}