{
  "type": "Feature",
  "properties": {
    "iso:country":"GB",
    "sg:address":"Sewing Machine Unit, 24 Church Street",
    "sg:city":"Eyemouth",
    "sg:classifiers":[
        {
            "category":"Shopping",
            "subcategory":"Crafts & Fabrics",
            "type":"Retail Goods"
        }
    ],
    "sg:phone":"+44 1890 750349",
    "sg:postcode":"TD14 5DH",
    "sg:province":"Scottish Borders",
    "sg:tags":[
        "machine",
        "sewing",
        "knitting"
    ],
    "wof:name":"A Coates Sewing Machines",
    "wof:placetype":"venue"
},
  "geometry": {"coordinates":[-2.095116,55.873142],"type":"Point"}
}