{
  "type": "Feature",
  "properties": {
    "iso:country":"GB",
    "sg:address":"23 Station Approach, Hayes",
    "sg:city":"Beckenham",
    "sg:classifiers":[
        {
            "category":"Real Estate",
            "subcategory":"Real Estate Agent",
            "type":"Services"
        }
    ],
    "sg:phone":"+44 20 8462 0222",
    "sg:postcode":"BR2 7EQ",
    "sg:province":"Kent",
    "wof:name":"Rachfern Properties Ltd.",
    "wof:placetype":"venue"
},
  "geometry": {"coordinates":[0.018035,51.379955],"type":"Point"}
}