{
  "type": "Feature",
  "properties": {
    "addr:full":"Pool Road, Chase Town Walsall Staffordshire WS7 8QW",
    "addr:postcode":"ws7 8qw",
    "addr:street":"Pool Road",
    "iso:country":"GB",
    "sg:address":"Pool Road, Chase Town",
    "sg:city":"Walsall",
    "sg:classifiers":[
        {
            "category":"Arena",
            "subcategory":"Sports Club",
            "type":"Entertainment"
        }
    ],
    "sg:phone":"+44 1543 686390",
    "sg:postcode":"WS7 8QW",
    "sg:province":"Staffordshire",
    "wof:name":"The Chase Sailing Club",
    "wof:placetype":"venue"
},
  "geometry": {"coordinates":[-1.9346790314,52.6686935425],"type":"Point"}
}