{
  "type": "Feature",
  "properties": {
    "iso:country":"GB",
    "sg:address":"Carlin How",
    "sg:city":"Saltburn-by-the-sea",
    "sg:classifiers":[
        {
            "category":"Wholesale",
            "subcategory":"Scrap",
            "type":"Manufacturing & Wholesale Goods"
        }
    ],
    "sg:phone":"+44 1287 640397",
    "sg:postcode":"TS13 4AQ",
    "sg:province":"North Yorkshire",
    "sg:tags":[
        "breaker",
        "dismantlers"
    ],
    "wof:name":"Garbutt Bros",
    "wof:placetype":"venue"
},
  "geometry": {"coordinates":[-0.9049,54.562679],"type":"Point"}
}