{
  "type": "Feature",
  "properties": {
    "iso:country":"GB",
    "sg:address":"Unit 5b Imperial Centre, Lion Way Enterprise Pk, Llansamlet",
    "sg:city":"Swansea",
    "sg:classifiers":[
        {
            "category":"Communications",
            "type":"Services"
        }
    ],
    "sg:phone":"+44 1792 790004",
    "sg:postcode":"SA6 8QN",
    "sg:province":"Swansea",
    "sg:tags":[
        "tv",
        "video",
        "radio"
    ],
    "wof:name":"Imperial Kitchens & Bedrooms Ltd",
    "wof:placetype":"venue"
},
  "geometry": {"coordinates":[-3.9179201126,51.6576385498],"type":"Point"}
}