{
  "type": "Feature",
  "properties": {
    "addr:full":"74a Holmes Road, Kentish Town London Greater London NW5 3AT",
    "addr:housenumber":"74a",
    "addr:postcode":"nw5 3at",
    "addr:street":"Holmes Road",
    "iso:country":"GB",
    "sg:address":"74a Holmes Road, Kentish Town",
    "sg:city":"London",
    "sg:classifiers":[
        {
            "category":"Retail",
            "subcategory":"Auto Repair",
            "type":"Services"
        }
    ],
    "sg:phone":"+44 20 7916 9331",
    "sg:postcode":"NW5 3AT",
    "sg:province":"Greater London",
    "sg:tags":[
        "body",
        "car"
    ],
    "wof:name":"M A Motors",
    "wof:placetype":"venue"
},
  "geometry": {"coordinates":[-0.14463,51.550011],"type":"Point"}
}