{
  "type": "Feature",
  "properties": {
    "iso:country":"GB",
    "sg:address":"The Gallery, 4 Knutsford Road, Row Of Trees",
    "sg:city":"Alderley Edge",
    "sg:classifiers":[
        {
            "category":"Professional",
            "subcategory":"Art Services",
            "type":"Services"
        }
    ],
    "sg:phone":"+44 1625 582014",
    "sg:postcode":"SK9 7SD",
    "sg:province":"Cheshire",
    "sg:tags":[
        "photographer"
    ],
    "wof:name":"John O'Connor Photography",
    "wof:placetype":"venue"
},
  "geometry": {"coordinates":[-2.236334,53.302807],"type":"Point"}
}