{
  "type": "Feature",
  "properties": {
    "iso:country":"GB",
    "sg:address":"15 Forge Lane, Bassaleg",
    "sg:city":"Newport",
    "sg:classifiers":[
        {
            "category":"Social Services",
            "subcategory":"Child Care",
            "type":"Services"
        }
    ],
    "sg:postcode":"NP10 8NF",
    "sg:province":"Caerphilly",
    "sg:tags":[
        "agency",
        "nanny"
    ],
    "wof:name":"Formative Years Nursery Nurse & Nanny Agency",
    "wof:placetype":"venue"
},
  "geometry": {"coordinates":[-3.0428171158,51.5735015869],"type":"Point"}
}