{
  "type": "Feature",
  "properties": {
    "addr:full":"Transport House, 54 North Bondgate Bishop Auckland Durham DL14 7PG",
    "addr:housenumber":"54",
    "addr:postcode":"dl14 7pg",
    "addr:street":"North Bondgate;Auckland",
    "iso:country":"GB",
    "sg:address":"Transport House, 54 North Bondgate",
    "sg:city":"Bishop Auckland",
    "sg:classifiers":[
        {
            "category":"Travel",
            "subcategory":"Travel Agent",
            "type":"Entertainment"
        }
    ],
    "sg:phone":"+44 1388 450000",
    "sg:postcode":"DL14 7PG",
    "sg:province":"Durham",
    "wof:name":"O K Motor Services Ltd.",
    "wof:placetype":"venue"
},
  "geometry": {"coordinates":[-1.6749420166,54.6660041809],"type":"Point"}
}