{
  "type": "Feature",
  "properties": {
    "iso:country":"GB",
    "sg:address":"Whiteley Rd, Norwood",
    "sg:city":"Upper Norwood",
    "sg:classifiers":[
        {
            "category":"Place Of Worship",
            "type":"Public Place"
        }
    ],
    "sg:phone":"+44 20 8670 5376",
    "sg:postcode":"SE19 1JT",
    "sg:province":"Greater London",
    "wof:name":"Kingdom Hall of Jehovah's Witnesses",
    "wof:placetype":"venue"
},
  "geometry": {"coordinates":[-0.089676,51.424477],"type":"Point"}
}