{
  "type": "Feature",
  "properties": {
    "addr:full":"London Road, Silk Willoughby Sleaford Lincolnshire NG34 8NZ",
    "addr:postcode":"ng34 8nz",
    "addr:street":"London Road",
    "iso:country":"GB",
    "sg:address":"London Road, Silk Willoughby",
    "sg:city":"Sleaford",
    "sg:classifiers":[
        {
            "category":"Government",
            "subcategory":"Post Office",
            "type":"Public Place"
        }
    ],
    "sg:phone":"+44 1529 307896",
    "sg:postcode":"NG34 8NZ",
    "sg:province":"Lincolnshire",
    "wof:name":"Silk Willoughby Post Office",
    "wof:placetype":"venue"
},
  "geometry": {"coordinates":[-0.4243740141,52.9834518433],"type":"Point"}
}