{
  "type": "Feature",
  "properties": {
    "iso:country":"GB",
    "sg:address":"113-117 Bournemouth Road",
    "sg:city":"Poole",
    "sg:classifiers":[
        {
            "category":"Autos & Motor Vehicles",
            "subcategory":"Fuel & Gas Station",
            "type":"Retail Goods"
        }
    ],
    "sg:postcode":"BH14 9HR",
    "sg:province":"Dorset",
    "sg:tags":[
        "petrol",
        "filling"
    ],
    "wof:name":"Churchill Service Station",
    "wof:placetype":"venue"
},
  "geometry": {"coordinates":[-1.9383579493,50.7247886658],"type":"Point"}
}