{
  "type": "Feature",
  "properties": {
    "addr:full":"6 Queens Terr Aberdeen Aberdeen City AB10 1XL",
    "addr:housenumber":"6",
    "addr:postcode":"ab10 1xl",
    "addr:street":"Queens Terr",
    "iso:country":"GB",
    "sg:address":"6 Queens Terr",
    "sg:city":"Aberdeen",
    "sg:classifiers":[
        {
            "category":"Professional",
            "subcategory":"Computer Services",
            "type":"Services"
        }
    ],
    "sg:phone":"+44 1224 646676",
    "sg:postcode":"AB10 1XL",
    "sg:province":"Aberdeen City",
    "sg:tags":[
        "system",
        "software"
    ],
    "wof:name":"Techscan International Ltd",
    "wof:placetype":"venue"
},
  "geometry": {"coordinates":[-2.1204769611,57.1435203552],"type":"Point"}
}