{
  "type": "Feature",
  "properties": {
    "iso:country":"GB",
    "sg:address":"9 Malvern Crescent",
    "sg:city":"Liverpool",
    "sg:classifiers":[
        {
            "category":"Professional",
            "subcategory":"Printing & Photocopies",
            "type":"Services"
        },
        {
            "category":"Building & Trades",
            "subcategory":"Locksmith",
            "type":"Services"
        }
    ],
    "sg:phone":"+44 151 480 9058",
    "sg:postcode":"L14 6TP",
    "sg:province":"Merseyside",
    "sg:tags":[
        "engraving"
    ],
    "wof:name":"North West Locks",
    "wof:placetype":"venue"
},
  "geometry": {"coordinates":[-2.875155,53.410763],"type":"Point"}
}