{
  "type": "Feature",
  "properties": {
    "addr:full":"11 Hartnup Street Maidstone Kent ME16 8LR",
    "addr:housenumber":"11",
    "addr:postcode":"me16 8lr",
    "addr:street":"Hartnup Street",
    "iso:country":"GB",
    "sg:address":"11 Hartnup Street",
    "sg:city":"Maidstone",
    "sg:classifiers":[
        {
            "category":"Building & Trades",
            "subcategory":"Construction",
            "type":"Services"
        }
    ],
    "sg:postcode":"ME16 8LR",
    "sg:province":"Kent",
    "sg:tags":[
        "contractor",
        "paving",
        "driveway"
    ],
    "wof:name":"The Posh Paving Co.",
    "wof:placetype":"venue"
},
  "geometry": {"coordinates":[0.4956749976,51.2672767639],"type":"Point"}
}