{
  "type": "Feature",
  "properties": {
    "iso:country":"GB",
    "sg:address":"Connect House, Omni Business Park",
    "sg:city":"Harlow",
    "sg:classifiers":[
        {
            "category":"Shopping",
            "subcategory":"Computers & Home Electronics",
            "type":"Retail Goods"
        }
    ],
    "sg:postcode":"CM19 5FT",
    "sg:province":"Essex",
    "wof:name":"Notebook Express Ltd.",
    "wof:placetype":"venue"
},
  "geometry": {"coordinates":[0.0629089996,51.7698554993],"type":"Point"}
}