{
  "type": "Feature",
  "properties": {
    "iso:country":"GB",
    "sg:address":"16a Osborne Road",
    "sg:city":"Southport",
    "sg:classifiers":[
        {
            "category":"Professional",
            "subcategory":"Art Services",
            "type":"Services"
        }
    ],
    "sg:postcode":"PR8 2RJ",
    "sg:province":"Lancashire",
    "sg:tags":[
        "graphic",
        "designer"
    ],
    "wof:name":"Artyfac (Creative Services) Ltd.",
    "wof:placetype":"venue"
},
  "geometry": {"coordinates":[-3.044169,53.60519],"type":"Point"}
}