{
  "type": "Feature",
  "properties": {
    "iso:country":"GB",
    "sg:address":"132-134 Brigstock Rd",
    "sg:city":"Thornton Heath",
    "sg:classifiers":[
        {
            "category":"Autos & Motor Vehicles",
            "subcategory":"Automobile Sales",
            "type":"Retail Goods"
        }
    ],
    "sg:phone":"+44 20 8664 8737",
    "sg:postcode":"CR7 7JB",
    "sg:province":"Surrey",
    "sg:tags":[
        "car"
    ],
    "wof:name":"C A Revelles",
    "wof:placetype":"venue"
},
  "geometry": {"coordinates":[-0.103851,51.397518],"type":"Point"}
}