{
  "type": "Feature",
  "properties": {
    "iso:country":"GB",
    "sg:address":"Gloucester Avenue Sheltered Housing, 22 Gloucester Av",
    "sg:city":"Keighley",
    "sg:classifiers":[
        {
            "category":"Government",
            "subcategory":"Office",
            "type":"Public Place"
        }
    ],
    "sg:phone":"+44 1535 652288",
    "sg:postcode":"BD20 0BY",
    "sg:province":"North Yorkshire",
    "sg:tags":[
        "local"
    ],
    "wof:name":"Bradford Metropolitan District Council",
    "wof:placetype":"venue"
},
  "geometry": {"coordinates":[-1.94726,53.913879],"type":"Point"}
}