{
  "type": "Feature",
  "properties": {
    "addr:full":"24 Glamis Clo Burton On Trent Derbyshire DE13 0HX",
    "addr:housenumber":"24",
    "addr:postcode":"de13 0hx",
    "addr:street":"Glamis Clo",
    "iso:country":"GB",
    "sg:address":"24 Glamis Clo",
    "sg:city":"Burton On Trent",
    "sg:classifiers":[
        {
            "category":"Social Services",
            "subcategory":"Job Training",
            "type":"Services"
        }
    ],
    "sg:phone":"+44 1283 533090",
    "sg:postcode":"DE13 0HX",
    "sg:province":"Derbyshire",
    "sg:tags":[
        "draughtsman",
        "drawing"
    ],
    "wof:name":"HFE Cad Services",
    "wof:placetype":"venue"
},
  "geometry": {"coordinates":[-1.6329430342,52.8290367126],"type":"Point"}
}