{
  "type": "Feature",
  "properties": {
    "iso:country":"GB",
    "sg:address":"Mount Pleasant Cottage, Mount Pleasant Lane",
    "sg:city":"Swanage",
    "sg:classifiers":[
        {
            "category":"Building & Trades",
            "subcategory":"Construction",
            "type":"Services"
        }
    ],
    "sg:phone":"+44 1929 424297",
    "sg:postcode":"BH19 2PN",
    "sg:province":"Dorset",
    "sg:tags":[
        "builder"
    ],
    "wof:name":"Ian D Saunder",
    "wof:placetype":"venue"
},
  "geometry": {"coordinates":[-1.957924,50.607971],"type":"Point"}
}