{
  "type": "Feature",
  "properties": {
    "addr:full":"1 Strathclyde Business Centre, 544 Scotland St West Glasgow Glasgow City G41 1BZ",
    "addr:housenumber":"1;544",
    "addr:postcode":"g41 1bz",
    "addr:street":"Strathclyde Business;Scotland St",
    "iso:country":"GB",
    "sg:address":"1 Strathclyde Business Centre, 544 Scotland St West",
    "sg:city":"Glasgow",
    "sg:classifiers":[
        {
            "category":"Wholesale",
            "subcategory":"Construction Materials",
            "type":"Manufacturing & Wholesale Goods"
        }
    ],
    "sg:postcode":"G41 1BZ",
    "sg:province":"Glasgow City",
    "sg:tags":[
        "lift"
    ],
    "wof:name":"M G R Scotland Ltd",
    "wof:placetype":"venue"
},
  "geometry": {"coordinates":[-4.2845897675,55.8502998352],"type":"Point"}
}