{
  "type": "Feature",
  "properties": {
    "addr:full":"Clifton Nursery Epping Road, Roydon Harlow Essex CM19 5DW",
    "addr:postcode":"cm19 5dw",
    "addr:street":"Epping Road",
    "iso:country":"GB",
    "sg:address":"Clifton Nursery Epping Road, Roydon",
    "sg:city":"Harlow",
    "sg:classifiers":[
        {
            "category":"Wholesale",
            "subcategory":"Fruits & Vegetables",
            "type":"Manufacturing & Wholesale Goods"
        }
    ],
    "sg:postcode":"CM19 5DW",
    "sg:province":"Essex",
    "wof:name":"B H Ebeling & Son",
    "wof:placetype":"venue"
},
  "geometry": {"coordinates":[0.038872,51.769241],"type":"Point"}
}