{
  "type": "Feature",
  "properties": {
    "addr:full":"50 Kings Crescent, Edlington Doncaster South Yorkshire DN12 1BD",
    "addr:housenumber":"50",
    "addr:postcode":"dn12 1bd",
    "addr:street":"Kings Crescent",
    "iso:country":"GB",
    "sg:address":"50 Kings Crescent, Edlington",
    "sg:city":"Doncaster",
    "sg:classifiers":[
        {
            "category":"Food & Beverages",
            "subcategory":"Meat & Fish",
            "type":"Retail Goods"
        },
        {
            "category":"Food & Beverages",
            "subcategory":"Groceries & Convenience Stores",
            "type":"Retail Goods"
        }
    ],
    "sg:phone":"+44 1709 770117",
    "sg:postcode":"DN12 1BD",
    "sg:province":"South Yorkshire",
    "sg:tags":[
        "shop",
        "chip"
    ],
    "wof:name":"Petes Plaice",
    "wof:placetype":"venue"
},
  "geometry": {"coordinates":[-1.1255149841,53.5274047852],"type":"Point"}
}