{
  "type": "Feature",
  "properties": {
    "addr:full":"14-14a Beulah Road, Rhiwbina Cardiff Cardiff CF14 6LX",
    "addr:housenumber":"14-14a",
    "addr:postcode":"cf14 6lx",
    "addr:street":"Beulah Road",
    "iso:country":"GB",
    "sg:address":"14-14a Beulah Road, Rhiwbina",
    "sg:city":"Cardiff",
    "sg:classifiers":[
        {
            "category":"Shopping",
            "subcategory":"Florist",
            "type":"Retail Goods"
        }
    ],
    "sg:phone":"+44 29 2062 7587",
    "sg:postcode":"CF14 6LX",
    "sg:province":"Cardiff",
    "wof:name":"Flower Lodge",
    "wof:placetype":"venue"
},
  "geometry": {"coordinates":[-3.21099,51.52232],"type":"Point"}
}