{
  "type": "Feature",
  "properties": {
    "addr:full":"131 Castle Road Bedford Bedfordshire MK40 3RF",
    "addr:housenumber":"131",
    "addr:postcode":"mk40 3rf",
    "addr:street":"Castle Road",
    "iso:country":"GB",
    "sg:address":"131 Castle Road",
    "sg:city":"Bedford",
    "sg:classifiers":[
        {
            "category":"Fast Food",
            "type":"Food & Drink"
        }
    ],
    "sg:phone":"+44 1234 212538",
    "sg:postcode":"MK40 3RF",
    "sg:province":"Bedfordshire",
    "sg:tags":[
        "away",
        "take"
    ],
    "wof:name":"Lees Chinese Take Away",
    "wof:placetype":"venue"
},
  "geometry": {"coordinates":[-0.4531689882,52.1370201111],"type":"Point"}
}