{
  "type": "Feature",
  "properties": {
    "addr:full":"Park Lane West Tipton West Midlands DY4 8LH",
    "addr:postcode":"dy4 8lh",
    "addr:street":"Park Lane West Tipton",
    "iso:country":"GB",
    "sg:address":"Park Lane West",
    "sg:city":"Tipton",
    "sg:classifiers":[
        {
            "category":"Building & Trades",
            "subcategory":"Plumbing",
            "type":"Services"
        }
    ],
    "sg:phone":"+44 121 521 2806",
    "sg:postcode":"DY4 8LH",
    "sg:province":"West Midlands",
    "sg:tags":[
        "heating"
    ],
    "wof:name":"Home Service Warranty Ltd.",
    "wof:placetype":"venue"
},
  "geometry": {"coordinates":[-2.067139,52.52467],"type":"Point"}
}