{
  "type": "Feature",
  "properties": {
    "iso:country":"GB",
    "sg:address":"83-87 Causewayend",
    "sg:city":"Aberdeen",
    "sg:classifiers":[
        {
            "category":"Manufacturing",
            "subcategory":"Petroleum Products",
            "type":"Manufacturing & Wholesale Goods"
        },
        {
            "category":"Building & Trades",
            "subcategory":"Construction",
            "type":"Services"
        }
    ],
    "sg:phone":"+44 1224 854600",
    "sg:postcode":"AB25 3TQ",
    "sg:province":"Aberdeen City",
    "sg:tags":[
        "double",
        "glazing",
        "installers"
    ],
    "wof:name":"Aberdeen Window & Door Systems Ltd.",
    "wof:placetype":"venue"
},
  "geometry": {"coordinates":[-2.101778,57.154564],"type":"Point"}
}