{
  "type": "Feature",
  "properties": {
    "iso:country":"GB",
    "sg:address":"Whitethorn Cottage, Tot Hill, Headley",
    "sg:city":"Epsom",
    "sg:classifiers":[
        {
            "category":"Professional",
            "subcategory":"Art Services",
            "type":"Services"
        },
        {
            "category":"Building & Trades",
            "subcategory":"Construction",
            "type":"Services"
        }
    ],
    "sg:phone":"+44 1372 377586",
    "sg:postcode":"KT18 6PY",
    "sg:province":"Surrey",
    "sg:tags":[
        "decorator",
        "painter"
    ],
    "wof:name":"A T Borer",
    "wof:placetype":"venue"
},
  "geometry": {"coordinates":[-0.2789700031,51.2756462097],"type":"Point"}
}