{
  "type": "Feature",
  "properties": {
    "addr:full":"2 Upper Green East Mitcham Greater London CR4 2PA",
    "addr:housenumber":"2",
    "addr:postcode":"cr4 2pa",
    "addr:street":"Upper;East",
    "iso:country":"GB",
    "sg:address":"2 Upper Green East",
    "sg:city":"Mitcham",
    "sg:classifiers":[
        {
            "category":"Food & Beverages",
            "subcategory":"Fruits & Vegetables",
            "type":"Retail Goods"
        }
    ],
    "sg:phone":"+44 20 8646 1286",
    "sg:postcode":"CR4 2PA",
    "sg:province":"Greater London",
    "sg:tags":[
        "greengrocer"
    ],
    "wof:name":"Roberts Greengrocers",
    "wof:placetype":"venue"
},
  "geometry": {"coordinates":[-0.1629620045,51.4049263],"type":"Point"}
}