{
  "type": "Feature",
  "properties": {
    "addr:full":"Unit 1 & 39 Anglesey Business Pa, Rk Littleworth Ro Cannock Staffordshire WS12 5NR",
    "addr:housenumber":"unit 1 & 39;business",
    "addr:postcode":"ws12 5nr",
    "addr:street":"Anglesey",
    "iso:country":"GB",
    "sg:address":"Unit 1 & 39 Anglesey Business Pa, Rk Littleworth Ro",
    "sg:city":"Cannock",
    "sg:classifiers":[
        {
            "category":"Wholesale",
            "subcategory":"Construction Materials",
            "type":"Manufacturing & Wholesale Goods"
        }
    ],
    "sg:phone":"+44 1543 871787",
    "sg:postcode":"WS12 5NR",
    "sg:province":"Staffordshire",
    "sg:tags":[
        "refractory"
    ],
    "wof:name":"Fuel Conservation Services Ltd.",
    "wof:placetype":"venue"
},
  "geometry": {"coordinates":[-1.98385,52.7043],"type":"Point"}
}