{
  "type": "Feature",
  "properties": {
    "addr:full":"Struan, Barhill Road Buckie Moray AB56 1DU",
    "addr:postcode":"ab56 1du",
    "addr:street":"Barhill Road",
    "iso:country":"GB",
    "sg:address":"Struan, Barhill Road",
    "sg:city":"Buckie",
    "sg:classifiers":[
        {
            "category":"Farming",
            "subcategory":"Fish & Marine Products",
            "type":"Manufacturing & Wholesale Goods"
        }
    ],
    "sg:postcode":"AB56 1DU",
    "sg:province":"Moray",
    "sg:tags":[
        "fisherman"
    ],
    "wof:name":"Struan Ltd.",
    "wof:placetype":"venue"
},
  "geometry": {"coordinates":[-2.9652240276,57.676700592],"type":"Point"}
}