{
  "type": "Feature",
  "properties": {
    "addr:full":"19 Ravendale Street North Scunthorpe Lincolnshire DN15 6NJ",
    "addr:housenumber":"19",
    "addr:postcode":"dn15 6nj",
    "addr:street":"Ravendale Street North",
    "iso:country":"GB",
    "sg:address":"19 Ravendale Street North",
    "sg:city":"Scunthorpe",
    "sg:classifiers":[
        {
            "category":"Shopping",
            "subcategory":"Jewelry",
            "type":"Retail Goods"
        },
        {
            "category":"Shopping",
            "subcategory":"Comic Books",
            "type":"Retail Goods"
        }
    ],
    "sg:phone":"+44 1724 855403",
    "sg:postcode":"DN15 6NJ",
    "sg:province":"Lincolnshire",
    "sg:tags":[
        "jeweller",
        "sale",
        "jewellery"
    ],
    "wof:name":"Leggott's Jewellers",
    "wof:placetype":"venue"
},
  "geometry": {"coordinates":[-0.648532,53.590668],"type":"Point"}
}