{
  "type": "Feature",
  "properties": {
    "addr:full":"Msp Business Centre, Fourth Way Wembley Greater London HA9 0HQ",
    "addr:postcode":"ha9 0hq",
    "addr:street":"Fourth Way",
    "iso:country":"GB",
    "sg:address":"Msp Business Centre, Fourth Way",
    "sg:city":"Wembley",
    "sg:classifiers":[
        {
            "category":"Professional",
            "subcategory":"Business Services",
            "type":"Services"
        }
    ],
    "sg:phone":"+44 20 8900 1001",
    "sg:postcode":"HA9 0HQ",
    "sg:province":"Greater London",
    "sg:tags":[
        "answering"
    ],
    "wof:name":"Metro Office Services",
    "wof:placetype":"venue"
},
  "geometry": {"coordinates":[-0.2955389917,51.5529632568],"type":"Point"}
}