{
  "type": "Feature",
  "properties": {
    "addr:full":"5 Blunt Road South Croydon Surrey CR2 7PA",
    "addr:housenumber":"5",
    "addr:postcode":"cr2 7pa",
    "addr:street":"Blunt Road",
    "iso:country":"GB",
    "sg:address":"5 Blunt Road",
    "sg:city":"South Croydon",
    "sg:classifiers":[
        {
            "category":"Farming",
            "subcategory":"Nursery",
            "type":"Manufacturing & Wholesale Goods"
        }
    ],
    "sg:postcode":"CR2 7PA",
    "sg:province":"Surrey",
    "sg:tags":[
        "creche"
    ],
    "wof:name":"Early Learners",
    "wof:placetype":"venue"
},
  "geometry": {"coordinates":[-0.0939129964,51.3628692627],"type":"Point"}
}