{
  "type": "Feature",
  "properties": {
    "iso:country":"GB",
    "sg:address":"1178 Maryhill Road",
    "sg:city":"Glasgow",
    "sg:classifiers":[
        {
            "category":"Food & Beverages",
            "subcategory":"Meat & Fish",
            "type":"Retail Goods"
        }
    ],
    "sg:phone":"+44 141 945 4740",
    "sg:postcode":"G20 9TA",
    "sg:province":"Glasgow City",
    "sg:tags":[
        "chip"
    ],
    "wof:name":"Harry's",
    "wof:placetype":"venue"
},
  "geometry": {"coordinates":[-4.284639,55.886822],"type":"Point"}
}