{
  "type": "Feature",
  "properties": {
    "iso:country":"GB",
    "sg:address":"Roost Hill Farm, Bradnop",
    "sg:city":"Leek",
    "sg:classifiers":[
        {
            "category":"Farming",
            "subcategory":"Dairy Farm",
            "type":"Manufacturing & Wholesale Goods"
        }
    ],
    "sg:phone":"+44 1538 373550",
    "sg:postcode":"ST13 7NA",
    "sg:province":"Staffordshire",
    "wof:name":"Malcolm Thomas Needham",
    "wof:placetype":"venue"
},
  "geometry": {"coordinates":[-1.987409,53.092167],"type":"Point"}
}