{
  "type": "Feature",
  "properties": {
    "iso:country":"GB",
    "sg:address":"12 Dolphin Mews, Dolphin Yard  Holywell Hill",
    "sg:city":"St Albans",
    "sg:classifiers":[
        {
            "category":"Professional",
            "subcategory":"Accounting & Tax Preparation",
            "type":"Services"
        }
    ],
    "sg:postcode":"AL1 1EX",
    "sg:province":"Hertfordshire",
    "sg:tags":[
        "accountant"
    ],
    "wof:name":"Crosscraft Enterprises Ltd",
    "wof:placetype":"venue"
},
  "geometry": {"coordinates":[-0.337752,51.753189],"type":"Point"}
}