{
  "type": "Feature",
  "properties": {
    "addr:full":"45 Station Road Birchington Kent CT7 9DJ",
    "addr:housenumber":"45",
    "addr:postcode":"ct7 9dj",
    "addr:street":"Station Road",
    "iso:country":"GB",
    "sg:address":"45 Station Road",
    "sg:city":"Birchington",
    "sg:classifiers":[
        {
            "category":"Shopping",
            "subcategory":"Gifts & Souvenirs",
            "type":"Retail Goods"
        }
    ],
    "sg:postcode":"CT7 9DJ",
    "sg:province":"Kent",
    "sg:tags":[
        "poster",
        "card"
    ],
    "wof:name":"House of Cards",
    "wof:placetype":"venue"
},
  "geometry": {"coordinates":[1.305456,51.375092],"type":"Point"}
}