{
  "type": "Feature",
  "properties": {
    "iso:country":"GB",
    "sg:address":"2 Worrall Street",
    "sg:city":"Salford",
    "sg:classifiers":[
        {
            "category":"Building & Trades",
            "subcategory":"Construction",
            "type":"Services"
        }
    ],
    "sg:phone":"+44 161 872 1355",
    "sg:postcode":"M5 4TH",
    "sg:province":"Greater Manchester",
    "sg:tags":[
        "equipment"
    ],
    "wof:name":"Ainscough Group Ltd.",
    "wof:placetype":"venue"
},
  "geometry": {"coordinates":[-2.268911,53.471889],"type":"Point"}
}