{
  "type": "Feature",
  "properties": {
    "addr:full":"The Garage, Wyndham Avenue Margate Kent CT9 2PR",
    "addr:postcode":"ct9 2pr",
    "addr:street":"Avenue Margate",
    "iso:country":"GB",
    "sg:address":"The Garage, Wyndham Avenue",
    "sg:city":"Margate",
    "sg:classifiers":[
        {
            "category":"Retail",
            "subcategory":"Auto Repair",
            "type":"Services"
        }
    ],
    "sg:phone":"+44 1843 299267",
    "sg:postcode":"CT9 2PR",
    "sg:province":"Kent",
    "sg:tags":[
        "modification",
        "garage"
    ],
    "wof:name":"G J Frape Bmw Specialists",
    "wof:placetype":"venue"
},
  "geometry": {"coordinates":[1.379247,51.386662],"type":"Point"}
}