{
  "type": "Feature",
  "properties": {
    "addr:full":"Woodside Terr Glasgow Glasgow City G3 7UY",
    "addr:postcode":"g3 7uy",
    "addr:street":"Terr",
    "iso:country":"GB",
    "sg:address":"Woodside Terr",
    "sg:city":"Glasgow",
    "sg:classifiers":[
        {
            "category":"Train Station",
            "subcategory":"Light Rail",
            "type":"Transportation"
        }
    ],
    "sg:postcode":"G3 7UY",
    "sg:province":"Glasgow City",
    "sg:tags":[
        "distributor",
        "mnfrs",
        "lime"
    ],
    "wof:name":"Scott Bennett Associates Ltd",
    "wof:placetype":"venue"
},
  "geometry": {"coordinates":[-4.27338,55.867691],"type":"Point"}
}