{
  "type": "Feature",
  "properties": {
    "addr:full":"1a Urquhart St Aberdeen Aberdeen City AB24 5PL",
    "addr:housenumber":"1a",
    "addr:postcode":"ab24 5pl",
    "addr:street":"Urquhart St",
    "iso:country":"GB",
    "sg:address":"1a Urquhart St",
    "sg:city":"Aberdeen",
    "sg:classifiers":[
        {
            "category":"Building & Trades",
            "subcategory":"Construction",
            "type":"Services"
        }
    ],
    "sg:phone":"+44 1224 624157",
    "sg:postcode":"AB24 5PL",
    "sg:province":"Aberdeen City",
    "sg:tags":[
        "decorator",
        "painter"
    ],
    "wof:name":"Andecor Decorating Services",
    "wof:placetype":"venue"
},
  "geometry": {"coordinates":[-2.091255,57.154961],"type":"Point"}
}