{
  "type": "Feature",
  "properties": {
    "addr:full":"21a North La, Headingley Leeds West Yorkshire LS6 3HW",
    "addr:housenumber":"21a",
    "addr:postcode":"ls6 3hw",
    "addr:street":"North La Headingley",
    "iso:country":"GB",
    "sg:address":"21a North La, Headingley",
    "sg:city":"Leeds",
    "sg:classifiers":[
        {
            "category":"Professional",
            "subcategory":"Business Services",
            "type":"Services"
        }
    ],
    "sg:postcode":"LS6 3HW",
    "sg:province":"West Yorkshire",
    "sg:tags":[
        "import",
        "export",
        "agent"
    ],
    "wof:name":"Shortall,A,",
    "wof:placetype":"venue"
},
  "geometry": {"coordinates":[-1.581079,53.819851],"type":"Point"}
}