{
  "type": "Feature",
  "properties": {
    "iso:country":"GB",
    "sg:address":", Tresillian",
    "sg:city":"Truro",
    "sg:classifiers":[
        {
            "category":"Professional",
            "subcategory":"Engineering",
            "type":"Services"
        }
    ],
    "sg:phone":"+44 1872 520351",
    "sg:postcode":"TR2 4BA",
    "sg:province":"Cornwall",
    "sg:tags":[
        "contractor",
        "electrical",
        "engineer"
    ],
    "wof:name":"P.A Ellis & Son",
    "wof:placetype":"venue"
},
  "geometry": {"coordinates":[-4.9462790489,50.2929000854],"type":"Point"}
}