{
  "type": "Feature",
  "properties": {
    "addr:full":"444 Chiswick High Road London Greater London W4 5TT",
    "addr:housenumber":"444",
    "addr:postcode":"w4 5tt",
    "addr:street":"Chiswick High Road",
    "iso:country":"GB",
    "sg:address":"444 Chiswick High Road",
    "sg:city":"London",
    "sg:classifiers":[
        {
            "category":"Arts & Performance",
            "subcategory":"Arts Center",
            "type":"Entertainment"
        }
    ],
    "sg:phone":"+44 20 8994 4100",
    "sg:postcode":"W4 5TT",
    "sg:province":"Greater London",
    "sg:tags":[
        "centre"
    ],
    "wof:name":"Art for Fun",
    "wof:placetype":"venue"
},
  "geometry": {"coordinates":[-0.267063,51.492867],"type":"Point"}
}