{
  "type": "Feature",
  "properties": {
    "iso:country":"GB",
    "sg:address":"77 Eridge Rd",
    "sg:city":"Eastbourne",
    "sg:classifiers":[
        {
            "category":"Building & Trades",
            "subcategory":"Plumbing",
            "type":"Services"
        }
    ],
    "sg:postcode":"BN21 2TS",
    "sg:province":"East Sussex",
    "sg:tags":[
        "heating"
    ],
    "wof:name":"Attridge,David,",
    "wof:placetype":"venue"
},
  "geometry": {"coordinates":[0.2646889985,50.7877006531],"type":"Point"}
}