{
  "type": "Feature",
  "properties": {
    "iso:country":"GB",
    "sg:address":"62 High Street",
    "sg:city":"Barnet",
    "sg:classifiers":[
        {
            "category":"Professional",
            "subcategory":"Business Services",
            "type":"Services"
        }
    ],
    "sg:phone":"+44 20 8440 5051",
    "sg:postcode":"EN5 5SJ",
    "sg:province":"Hertfordshire",
    "sg:tags":[
        "bookmaker"
    ],
    "wof:name":"Coverdale Racing",
    "wof:placetype":"venue"
},
  "geometry": {"coordinates":[-0.1997189969,51.653087616],"type":"Point"}
}