{
  "type": "Feature",
  "properties": {
    "addr:full":"Warton House, 150 High Street, Stratford London Greater London E15 2NE",
    "addr:housenumber":"150",
    "addr:postcode":"e15 2ne",
    "addr:street":"High Street",
    "iso:country":"GB",
    "sg:address":"Warton House, 150 High Street, Stratford",
    "sg:city":"London",
    "sg:classifiers":[
        {
            "category":"Freight",
            "type":"Transportation"
        }
    ],
    "sg:phone":"+44 20 8534 8899",
    "sg:postcode":"E15 2NE",
    "sg:province":"Greater London",
    "sg:tags":[
        "overseas",
        "shipping",
        "removal"
    ],
    "wof:name":"W H L Group Ltd.",
    "wof:placetype":"venue"
},
  "geometry": {"coordinates":[-0.00625,51.534962],"type":"Point"}
}