{
  "type": "Feature",
  "properties": {
    "addr:full":"10 Clarence Rd Shanklin Isle of Wight PO37 7BH",
    "addr:housenumber":"10",
    "addr:postcode":"po37 7bh",
    "addr:street":"Clarence Rd",
    "iso:country":"GB",
    "sg:address":"10 Clarence Rd",
    "sg:city":"Shanklin",
    "sg:classifiers":[
        {
            "category":"Travel",
            "subcategory":"Hotels & Motels",
            "type":"Entertainment"
        }
    ],
    "sg:postcode":"PO37 7BH",
    "sg:province":"Isle of Wight",
    "wof:name":"Norton,B,",
    "wof:placetype":"venue"
},
  "geometry": {"coordinates":[-1.175564,50.635204],"type":"Point"}
}