{
  "type": "Feature",
  "properties": {
    "addr:full":"4 Temple Farm Indust Est, The Candlemakers Southend On Sea Essex SS2 5RX",
    "addr:housenumber":"4",
    "addr:postcode":"ss2 5rx",
    "addr:street":"Temple Farm Indust Est The;Southend;Sea",
    "iso:country":"GB",
    "sg:address":"4 Temple Farm Indust Est, The Candlemakers",
    "sg:city":"Southend On Sea",
    "sg:classifiers":[
        {
            "category":"Shopping",
            "subcategory":"Computers & Home Electronics",
            "type":"Retail Goods"
        }
    ],
    "sg:phone":"+44 1702 420645",
    "sg:postcode":"SS2 5RX",
    "sg:province":"Essex",
    "sg:tags":[
        "equipment",
        "audio-visual"
    ],
    "wof:name":"Leaf Ltd",
    "wof:placetype":"venue"
},
  "geometry": {"coordinates":[0.71178,51.56345],"type":"Point"}
}