{
  "type": "Feature",
  "properties": {
    "addr:full":"Stone House Farm, Church Lane Stafford Staffordshire ST18 0DB",
    "addr:postcode":"st18 0db",
    "addr:street":"Church Lane",
    "iso:country":"GB",
    "sg:address":"Stone House Farm, Church Lane",
    "sg:city":"Stafford",
    "sg:classifiers":[
        {
            "category":"Farming",
            "subcategory":"Livestock Farm",
            "type":"Manufacturing & Wholesale Goods"
        },
        {
            "category":"Farming",
            "subcategory":"Farm",
            "type":"Manufacturing & Wholesale Goods"
        }
    ],
    "sg:postcode":"ST18 0DB",
    "sg:province":"Staffordshire",
    "sg:tags":[
        "mixed",
        "crop",
        "others"
    ],
    "wof:name":"John Thomas Haynes",
    "wof:placetype":"venue"
},
  "geometry": {"coordinates":[-2.0318710804,52.853351593],"type":"Point"}
}