{
  "type": "Feature",
  "properties": {
    "iso:country":"GB",
    "sg:address":"41 Longwools, Broadsands",
    "sg:city":"Paignton",
    "sg:classifiers":[
        {
            "category":"Building & Trades",
            "subcategory":"Construction",
            "type":"Services"
        }
    ],
    "sg:postcode":"TQ4 6HU",
    "sg:province":"Devon",
    "sg:tags":[
        "roofing"
    ],
    "wof:name":"Goodrington Roofing",
    "wof:placetype":"venue"
},
  "geometry": {"coordinates":[-3.5564339161,50.403465271],"type":"Point"}
}