{
  "type": "Feature",
  "properties": {
    "iso:country":"GB",
    "sg:address":"645 Romford Rd",
    "sg:city":"Manor Park",
    "sg:classifiers":[
        {
            "category":"Food & Beverages",
            "subcategory":"Meat & Fish",
            "type":"Retail Goods"
        }
    ],
    "sg:phone":"+44 20 8553 0128",
    "sg:postcode":"E12 5AD",
    "sg:province":"Greater London",
    "sg:tags":[
        "chip"
    ],
    "wof:name":"Muss Fish Bar",
    "wof:placetype":"venue"
},
  "geometry": {"coordinates":[0.045459,51.550011],"type":"Point"}
}