{
  "type": "Feature",
  "properties": {
    "addr:full":"447 Foxhall Road Ipswich Suffolk IP3 8LL",
    "addr:housenumber":"447",
    "addr:postcode":"ip3 8ll",
    "addr:street":"Foxhall Road",
    "iso:country":"GB",
    "sg:address":"447 Foxhall Road",
    "sg:city":"Ipswich",
    "sg:classifiers":[
        {
            "category":"Wholesale",
            "subcategory":"Chemicals & Plastics",
            "type":"Manufacturing & Wholesale Goods"
        }
    ],
    "sg:postcode":"IP3 8LL",
    "sg:province":"Suffolk",
    "sg:tags":[
        "retail",
        "freezer",
        "refrigerator"
    ],
    "wof:name":"Derwent Refrigeration",
    "wof:placetype":"venue"
},
  "geometry": {"coordinates":[1.191036,52.05191],"type":"Point"}
}