{
  "type": "Feature",
  "properties": {
    "addr:full":"12 Beech Road Oakham Leicestershire LE15 6DG",
    "addr:housenumber":"12",
    "addr:postcode":"le15 6dg",
    "addr:street":"Beech Road",
    "iso:country":"GB",
    "sg:address":"12 Beech Road",
    "sg:city":"Oakham",
    "sg:classifiers":[
        {
            "category":"Building & Trades",
            "subcategory":"Construction",
            "type":"Services"
        }
    ],
    "sg:phone":"+44 1572 723873",
    "sg:postcode":"LE15 6DG",
    "sg:province":"Leicestershire",
    "sg:tags":[
        "joinery",
        "joiner",
        "carpenter",
        "carpentry"
    ],
    "wof:name":"M A Duncan",
    "wof:placetype":"venue"
},
  "geometry": {"coordinates":[-0.7205849886,52.6738243103],"type":"Point"}
}