{
  "type": "Feature",
  "properties": {
    "iso:country":"GB",
    "sg:address":"39 Bayhall Road",
    "sg:city":"Tunbridge Wells",
    "sg:classifiers":[
        {
            "category":"Professional",
            "subcategory":"Detective & Security Services",
            "type":"Services"
        },
        {
            "category":"Building & Trades",
            "subcategory":"Locksmith",
            "type":"Services"
        }
    ],
    "sg:phone":"+44 1892 530587",
    "sg:postcode":"TN2 4UG",
    "sg:province":"East Sussex",
    "wof:name":"Clubb Security",
    "wof:placetype":"venue"
},
  "geometry": {"coordinates":[0.2775540054,51.1295661926],"type":"Point"}
}