{
  "type": "Feature",
  "properties": {
    "addr:full":"295 Fenwick Rd Glasgow East Renfrewshire G46 6UH",
    "addr:housenumber":"295",
    "addr:postcode":"g46 6uh",
    "addr:street":"Fenwick Rd",
    "iso:country":"GB",
    "sg:address":"295 Fenwick Rd",
    "sg:city":"Glasgow",
    "sg:classifiers":[
        {
            "category":"Health Services",
            "subcategory":"Clinic",
            "type":"Services"
        }
    ],
    "sg:phone":"+44 141 638 4445",
    "sg:postcode":"G46 6UH",
    "sg:province":"East Renfrewshire",
    "sg:tags":[
        "private"
    ],
    "wof:name":"BUPA",
    "wof:placetype":"venue"
},
  "geometry": {"coordinates":[-4.298637867,55.7969665527],"type":"Point"}
}