{
  "type": "Feature",
  "properties": {
    "addr:full":"12 Artillery Row London Greater London SW1P 1RZ",
    "addr:housenumber":"12",
    "addr:postcode":"sw1p 1rz",
    "addr:street":"Artillery Row",
    "iso:country":"GB",
    "sg:address":"12 Artillery Row",
    "sg:city":"London",
    "sg:classifiers":[
        {
            "category":"Deli",
            "type":"Food & Drink"
        }
    ],
    "sg:postcode":"SW1P 1RZ",
    "sg:province":"Greater London",
    "sg:tags":[
        "delivery",
        "sandwich"
    ],
    "wof:name":"Level 20 Ltd",
    "wof:placetype":"venue"
},
  "geometry": {"coordinates":[-0.135759,51.496574],"type":"Point"}
}