{
  "type": "Feature",
  "properties": {
    "addr:full":"Cambridge House, (annexe) Hospital Road Aldershot Hampshire GU11 2BF",
    "addr:postcode":"gu11 2bf",
    "addr:street":"Hospital Road",
    "iso:country":"GB",
    "sg:address":"Cambridge House, (annexe) Hospital Road",
    "sg:city":"Aldershot",
    "sg:classifiers":[
        {
            "category":"Building & Trades",
            "subcategory":"Construction",
            "type":"Services"
        }
    ],
    "sg:phone":"+44 1252 330939",
    "sg:postcode":"GU11 2BF",
    "sg:province":"Hampshire",
    "sg:tags":[
        "flooring"
    ],
    "wof:name":"Tudor Bros (Flooring) Ltd.",
    "wof:placetype":"venue"
},
  "geometry": {"coordinates":[-0.765021,51.254612],"type":"Point"}
}