{
  "type": "Feature",
  "properties": {
    "iso:country":"GB",
    "sg:address":"24 Church Street, Coxhoe",
    "sg:city":"Durham",
    "sg:classifiers":[
        {
            "category":"Insurance",
            "subcategory":"Insurance Agent",
            "type":"Services"
        }
    ],
    "sg:phone":"+44 191 377 3177",
    "sg:postcode":"DH6 4HE",
    "sg:province":"Durham",
    "sg:tags":[
        "broker"
    ],
    "wof:name":"A W C Insurance Services",
    "wof:placetype":"venue"
},
  "geometry": {"coordinates":[-1.477979,54.731411],"type":"Point"}
}