{
  "type": "Feature",
  "properties": {
    "iso:country":"GB",
    "sg:address":"Thrums, 11 Farquhar St, Hopeman",
    "sg:city":"Elgin",
    "sg:classifiers":[
        {
            "category":"Arts & Performance",
            "subcategory":"Theater",
            "type":"Entertainment"
        }
    ],
    "sg:postcode":"IV30 5SN",
    "sg:province":"Moray",
    "sg:tags":[
        "theatre"
    ],
    "wof:name":"Out of the Darkness Theatre Co",
    "wof:placetype":"venue"
},
  "geometry": {"coordinates":[-3.4300639629,57.7056312561],"type":"Point"}
}