{
  "type": "Feature",
  "properties": {
    "addr:full":"12 Southern Terrace Plymouth Devon PL4 7LS",
    "addr:housenumber":"12",
    "addr:postcode":"pl4 7ls",
    "addr:street":"Southern Terrace",
    "iso:country":"GB",
    "sg:address":"12 Southern Terrace",
    "sg:city":"Plymouth",
    "sg:classifiers":[
        {
            "category":"Building & Trades",
            "subcategory":"Construction",
            "type":"Services"
        }
    ],
    "sg:phone":"+44 1752 265413",
    "sg:postcode":"PL4 7LS",
    "sg:province":"Devon",
    "sg:tags":[
        "builder"
    ],
    "wof:name":"Findlay Brian",
    "wof:placetype":"venue"
},
  "geometry": {"coordinates":[-4.129307,50.380146],"type":"Point"}
}