{
  "type": "Feature",
  "properties": {
    "addr:full":"89 Trentham Rd Stoke-on-trent Staffordshire ST3 4EE",
    "addr:housenumber":"89",
    "addr:postcode":"st3 4ee",
    "addr:street":"Trentham Rd",
    "iso:country":"GB",
    "sg:address":"89 Trentham Rd",
    "sg:city":"Stoke-on-trent",
    "sg:classifiers":[
        {
            "category":"Shopping",
            "subcategory":"Clothing, Apparel, & Fashions",
            "type":"Retail Goods"
        }
    ],
    "sg:postcode":"ST3 4EE",
    "sg:province":"Staffordshire",
    "sg:tags":[
        "clothing",
        "fabric"
    ],
    "wof:name":"Philippe,Liz,",
    "wof:placetype":"venue"
},
  "geometry": {"coordinates":[-2.136116,52.979668],"type":"Point"}
}