{
  "type": "Feature",
  "properties": {
    "iso:country":"GB",
    "sg:address":"141 London Road, Southborough",
    "sg:city":"Tunbridge Wells",
    "sg:classifiers":[
        {
            "category":"Bars & Pubs",
            "type":"Food & Drink"
        }
    ],
    "sg:postcode":"TN4 0NA",
    "sg:province":"Kent",
    "sg:tags":[
        "pubs",
        "inn"
    ],
    "wof:name":"S Law",
    "wof:placetype":"venue"
},
  "geometry": {"coordinates":[0.2601290047,51.1558113098],"type":"Point"}
}