{
  "type": "Feature",
  "properties": {
    "addr:full":"36 Blatchington Rd Hove East Sussex BN3 3YN",
    "addr:housenumber":"36",
    "addr:postcode":"bn3 3yn",
    "addr:street":"Blatchington Rd",
    "iso:country":"GB",
    "sg:address":"36 Blatchington Rd",
    "sg:city":"Hove",
    "sg:classifiers":[
        {
            "category":"Organizations",
            "subcategory":"Non-profit Organization",
            "type":"Services"
        }
    ],
    "sg:phone":"+44 1273 707141",
    "sg:postcode":"BN3 3YN",
    "sg:province":"East Sussex",
    "sg:tags":[
        "organisation",
        "voluntary",
        "charity"
    ],
    "wof:name":"Age Concern Charity Shop",
    "wof:placetype":"venue"
},
  "geometry": {"coordinates":[-0.1757739931,50.8314361572],"type":"Point"}
}