{
  "type": "Feature",
  "properties": {
    "addr:full":"1 Longfield Street London Greater London SW18 5RD",
    "addr:housenumber":"1",
    "addr:postcode":"sw18 5rd",
    "addr:street":"Longfield Street",
    "iso:country":"GB",
    "sg:address":"1 Longfield Street",
    "sg:city":"London",
    "sg:classifiers":[
        {
            "category":"Retail",
            "subcategory":"Auto Repair",
            "type":"Services"
        }
    ],
    "sg:phone":"+44 20 8874 0646",
    "sg:postcode":"SW18 5RD",
    "sg:province":"Greater London",
    "sg:tags":[
        "modification",
        "garage"
    ],
    "wof:name":"J & M Auto Services",
    "wof:placetype":"venue"
},
  "geometry": {"coordinates":[-0.1994629949,51.4477081299],"type":"Point"}
}