{
  "type": "Feature",
  "properties": {
    "addr:full":"2 Tregonwell Road Minehead Somerset TA24 5DT",
    "addr:housenumber":"2",
    "addr:postcode":"ta24 5dt",
    "addr:street":"Tregonwell Road",
    "iso:country":"GB",
    "sg:address":"2 Tregonwell Road",
    "sg:city":"Minehead",
    "sg:classifiers":[
        {
            "category":"Health Services",
            "subcategory":"Nursing And Care Facility",
            "type":"Services"
        }
    ],
    "sg:postcode":"TA24 5DT",
    "sg:province":"Somerset",
    "sg:tags":[
        "home"
    ],
    "wof:name":"Glenlyn Residential Home",
    "wof:placetype":"venue"
},
  "geometry": {"coordinates":[-3.4719450474,51.2057647705],"type":"Point"}
}