{
  "type": "Feature",
  "properties": {
    "addr:full":"1 Buchanan St Largs North Ayrshire KA30 8PP",
    "addr:housenumber":"1",
    "addr:postcode":"ka30 8pp",
    "addr:street":"Buchanan St",
    "iso:country":"GB",
    "sg:address":"1 Buchanan St",
    "sg:city":"Largs",
    "sg:classifiers":[
        {
            "category":"Health Services",
            "subcategory":"Health Practitioner",
            "type":"Services"
        }
    ],
    "sg:phone":"+44 1475 674611",
    "sg:postcode":"KA30 8PP",
    "sg:province":"North Ayrshire",
    "sg:tags":[
        "physiotherapist"
    ],
    "wof:name":"Auld E R Mrs",
    "wof:placetype":"venue"
},
  "geometry": {"coordinates":[-4.873631,55.804535],"type":"Point"}
}