{
  "type": "Feature",
  "properties": {
    "iso:country":"GB",
    "sg:address":"Essex Works, Tallon Road, Hutton Industrial Estate",
    "sg:city":"Brentwood",
    "sg:classifiers":[
        {
            "category":"Manufacturing",
            "subcategory":"Lumber",
            "type":"Manufacturing & Wholesale Goods"
        }
    ],
    "sg:phone":"+44 1277 211557",
    "sg:postcode":"CM13 1TG",
    "sg:province":"Essex",
    "sg:tags":[
        "importer",
        "merchants",
        "agent",
        "timber"
    ],
    "wof:name":"Vickers Timber Co. Ltd.",
    "wof:placetype":"venue"
},
  "geometry": {"coordinates":[0.3558380008,51.6332130432],"type":"Point"}
}