{
  "type": "Feature",
  "properties": {
    "iso:country":"GB",
    "sg:address":"10 The Alhambra Shopping Centre, Cheapside",
    "sg:city":"Barnsley",
    "sg:classifiers":[
        {
            "category":"Shopping",
            "subcategory":"Clothing, Apparel, & Fashions",
            "type":"Retail Goods"
        }
    ],
    "sg:phone":"+44 1226 779111",
    "sg:postcode":"S70 1SB",
    "sg:province":"South Yorkshire",
    "sg:tags":[
        "ladieswear"
    ],
    "wof:name":"Select",
    "wof:placetype":"venue"
},
  "geometry": {"coordinates":[-1.4847379923,53.5531921387],"type":"Point"}
}