{
  "type": "Feature",
  "properties": {
    "iso:country":"GB",
    "sg:address":"Station Farm, Station Road, Sturton",
    "sg:city":"Brigg",
    "sg:classifiers":[
        {
            "category":"Farming",
            "subcategory":"Livestock Farm",
            "type":"Manufacturing & Wholesale Goods"
        }
    ],
    "sg:phone":"+44 1652 654258",
    "sg:postcode":"DN20 9DP",
    "sg:province":"Lincolnshire",
    "sg:tags":[
        "others"
    ],
    "wof:name":"J W Richardson",
    "wof:placetype":"venue"
},
  "geometry": {"coordinates":[-0.5386490226,53.5313148499],"type":"Point"}
}