{
  "type": "Feature",
  "properties": {
    "addr:full":"Hawkins Rd Colchester Essex CO2 8JT",
    "addr:postcode":"co2 8jt",
    "addr:street":"Hawkins Rd",
    "iso:country":"GB",
    "sg:address":"Hawkins Rd",
    "sg:city":"Colchester",
    "sg:classifiers":[
        {
            "category":"Professional",
            "subcategory":"Printing & Photocopies",
            "type":"Services"
        }
    ],
    "sg:phone":"+44 1206 795461",
    "sg:postcode":"CO2 8JT",
    "sg:province":"Essex",
    "sg:tags":[
        "printer"
    ],
    "wof:name":"Spottiswoode Ballantyne Printers Ltd",
    "wof:placetype":"venue"
},
  "geometry": {"coordinates":[0.9277870059,51.8832130432],"type":"Point"}
}