{
  "type": "Feature",
  "properties": {
    "addr:full":"Ham Farm Kingsbridge Devon TQ7 4RX",
    "addr:housenumber":"kingsbridge",
    "addr:postcode":"tq7 4rx",
    "addr:street":"Devon",
    "iso:country":"GB",
    "sg:address":"Ham Farm",
    "sg:city":"Kingsbridge",
    "sg:classifiers":[
        {
            "category":"Manufacturing",
            "subcategory":"Wood Products",
            "type":"Manufacturing & Wholesale Goods"
        }
    ],
    "sg:phone":"+44 1548 550861",
    "sg:postcode":"TQ7 4RX",
    "sg:province":"Devon",
    "sg:tags":[
        "craftsman"
    ],
    "wof:name":"C Hahn",
    "wof:placetype":"venue"
},
  "geometry": {"coordinates":[-3.9158101082,50.3143463135],"type":"Point"}
}