{
  "type": "Feature",
  "properties": {
    "iso:country":"GB",
    "sg:address":"79 Gordon Road, Ealing",
    "sg:city":"London",
    "sg:classifiers":[
        {
            "category":"Organizations",
            "subcategory":"Non-profit Organization",
            "type":"Services"
        }
    ],
    "sg:phone":"+44 20 8998 5148",
    "sg:postcode":"W5 2AL",
    "sg:province":"Greater London",
    "sg:tags":[
        "organisation",
        "voluntary",
        "charity"
    ],
    "wof:name":"The Ivy Club",
    "wof:placetype":"venue"
},
  "geometry": {"coordinates":[-0.312834,51.514591],"type":"Point"}
}