{
  "type": "Feature",
  "properties": {
    "addr:full":"195 Queensferry Rd Dunfermline Fife KY11 2LQ",
    "addr:housenumber":"195",
    "addr:postcode":"ky11 2lq",
    "addr:street":"Queensferry Rd",
    "iso:country":"GB",
    "sg:address":"195 Queensferry Rd",
    "sg:city":"Dunfermline",
    "sg:classifiers":[
        {
            "category":"Health Services",
            "subcategory":"Doctor",
            "type":"Services"
        }
    ],
    "sg:phone":"+44 1383 414874",
    "sg:postcode":"KY11 2LQ",
    "sg:province":"Fife",
    "sg:tags":[
        "practitioners"
    ],
    "wof:name":"Firth, C",
    "wof:placetype":"venue"
},
  "geometry": {"coordinates":[-3.4248449802,56.0430335999],"type":"Point"}
}