{
  "type": "Feature",
  "properties": {
    "addr:full":"Highfield Ho, Stratford Rd, Hall Grn Birmingham West Midlands B28 9HA",
    "addr:postcode":"b28 9ha",
    "addr:street":"Stratford Rd Hall Grn",
    "iso:country":"GB",
    "sg:address":"Highfield Ho, Stratford Rd, Hall Grn",
    "sg:city":"Birmingham",
    "sg:classifiers":[
        {
            "category":"Professional",
            "subcategory":"Detective & Security Services",
            "type":"Services"
        }
    ],
    "sg:postcode":"B28 9HA",
    "sg:province":"West Midlands",
    "sg:tags":[
        "agency"
    ],
    "wof:name":"B D I Specialist Surveillance & Investig",
    "wof:placetype":"venue"
},
  "geometry": {"coordinates":[-1.8424040079,52.428478241],"type":"Point"}
}