{
  "type": "Feature",
  "properties": {
    "iso:country":"GB",
    "sg:address":"Unit 6 Kirklea Farm, Badgworth",
    "sg:city":"Axbridge",
    "sg:classifiers":[
        {
            "category":"Manufacturing",
            "subcategory":"Textiles",
            "type":"Manufacturing & Wholesale Goods"
        }
    ],
    "sg:phone":"+44 1934 733515",
    "sg:postcode":"BS26 2QH",
    "sg:province":"Somerset",
    "sg:tags":[
        "designer"
    ],
    "wof:name":"Lucy Simpson",
    "wof:placetype":"venue"
},
  "geometry": {"coordinates":[-2.8184089661,51.2883911133],"type":"Point"}
}