{
  "type": "Feature",
  "properties": {
    "addr:full":"84 Bradford Road, Guiseley Leeds West Yorkshire LS20 8HT",
    "addr:housenumber":"84",
    "addr:postcode":"ls20 8ht",
    "addr:street":"Bradford Road",
    "iso:country":"GB",
    "sg:address":"84 Bradford Road, Guiseley",
    "sg:city":"Leeds",
    "sg:classifiers":[
        {
            "category":"Autos & Motor Vehicles",
            "subcategory":"Automobile Sales",
            "type":"Retail Goods"
        }
    ],
    "sg:postcode":"LS20 8HT",
    "sg:province":"West Yorkshire",
    "sg:tags":[
        "car"
    ],
    "wof:name":"Facia Five",
    "wof:placetype":"venue"
},
  "geometry": {"coordinates":[-1.72289,53.870373],"type":"Point"}
}