{
  "type": "Feature",
  "properties": {
    "iso:country":"GB",
    "sg:address":"14 Freemen Street",
    "sg:city":"Stafford",
    "sg:classifiers":[
        {
            "category":"Personal",
            "subcategory":"Beauty Salon",
            "type":"Services"
        }
    ],
    "sg:postcode":"ST16 3HY",
    "sg:province":"Staffordshire",
    "sg:tags":[
        "unisex",
        "hairdresser"
    ],
    "wof:name":"Trendz",
    "wof:placetype":"venue"
},
  "geometry": {"coordinates":[-2.113654,52.81596],"type":"Point"}
}