{
  "type": "Feature",
  "properties": {
    "addr:full":"Montasser, Coopers Lane Wantage Berkshire OX12 8HQ",
    "addr:postcode":"ox12 8hq",
    "addr:street":"Montasser Coopers Lane",
    "iso:country":"GB",
    "sg:address":"Montasser, Coopers Lane",
    "sg:city":"Wantage",
    "sg:classifiers":[
        {
            "category":"Retail",
            "subcategory":"Auto Repair",
            "type":"Services"
        }
    ],
    "sg:postcode":"OX12 8HQ",
    "sg:province":"Berkshire",
    "sg:tags":[
        "modification",
        "garage"
    ],
    "wof:name":"T W Mobile Autoservice",
    "wof:placetype":"venue"
},
  "geometry": {"coordinates":[-1.4236390591,51.5917472839],"type":"Point"}
}