{
  "type": "Feature",
  "properties": {
    "addr:full":"46 High St Honiton Devon EX14 8PJ",
    "addr:housenumber":"46",
    "addr:postcode":"ex14 8pj",
    "addr:street":"High St",
    "iso:country":"GB",
    "sg:address":"46 High St",
    "sg:city":"Honiton",
    "sg:classifiers":[
        {
            "category":"Shopping",
            "subcategory":"Antiques",
            "type":"Retail Goods"
        }
    ],
    "sg:phone":"+44 1404 46009",
    "sg:postcode":"EX14 8PJ",
    "sg:province":"Devon",
    "wof:name":"Maya Antiques",
    "wof:placetype":"venue"
},
  "geometry": {"coordinates":[-3.186271,50.800358],"type":"Point"}
}