{
  "type": "Feature",
  "properties": {
    "iso:country":"GB",
    "sg:address":"Seymour Ho, Green La",
    "sg:city":"Walsall",
    "sg:classifiers":[
        {
            "category":"Shopping",
            "subcategory":"Crafts & Fabrics",
            "type":"Retail Goods"
        }
    ],
    "sg:postcode":"WS2 8HE",
    "sg:province":"West Midlands",
    "sg:tags":[
        "shop"
    ],
    "wof:name":"B & S Textiles",
    "wof:placetype":"venue"
},
  "geometry": {"coordinates":[-1.98659,52.58709],"type":"Point"}
}