{
  "type": "Feature",
  "properties": {
    "addr:full":"Orchard House, High Common, Barsham Beccles Norfolk NR34 8HW",
    "addr:postcode":"nr34 8hw",
    "addr:street":"High Common",
    "iso:country":"GB",
    "sg:address":"Orchard House, High Common, Barsham",
    "sg:city":"Beccles",
    "sg:classifiers":[
        {
            "category":"Food & Beverages",
            "subcategory":"Specialty",
            "type":"Retail Goods"
        }
    ],
    "sg:phone":"+44 1502 715637",
    "sg:postcode":"NR34 8HW",
    "sg:province":"Norfolk",
    "sg:tags":[
        "product",
        "health"
    ],
    "wof:name":"Barleycorn Wholefoods",
    "wof:placetype":"venue"
},
  "geometry": {"coordinates":[1.52632,52.450439],"type":"Point"}
}