{
  "type": "Feature",
  "properties": {
    "addr:full":"Park Garage, Park Terrace, Deganwy Conwy Conwy LL31 9UL",
    "addr:postcode":"ll31 9ul",
    "addr:street":"Park;Deganwy",
    "iso:country":"GB",
    "sg:address":"Park Garage, Park Terrace, Deganwy",
    "sg:city":"Conwy",
    "sg:classifiers":[
        {
            "category":"Manufacturing",
            "subcategory":"Wood Products",
            "type":"Manufacturing & Wholesale Goods"
        }
    ],
    "sg:phone":"+44 1492 580870",
    "sg:postcode":"LL31 9UL",
    "sg:province":"Conwy",
    "sg:tags":[
        "packaging",
        "crate",
        "pallets"
    ],
    "wof:name":"Precision Packaging",
    "wof:placetype":"venue"
},
  "geometry": {"coordinates":[-3.8358290195,53.2969818115],"type":"Point"}
}