{
  "type": "Feature",
  "properties": {
    "iso:country":"GB",
    "sg:address":"17 Summerwood Lane, Halsall",
    "sg:city":"Ormskirk",
    "sg:classifiers":[
        {
            "category":"Professional",
            "subcategory":"Advertising",
            "type":"Services"
        }
    ],
    "sg:phone":"+44 1704 841921",
    "sg:postcode":"L39 8TH",
    "sg:province":"Lancashire",
    "sg:tags":[
        "agency"
    ],
    "wof:name":"Catch",
    "wof:placetype":"venue"
},
  "geometry": {"coordinates":[-2.947497,53.583958],"type":"Point"}
}