{
  "type": "Feature",
  "properties": {
    "addr:full":"21a Mill Street Wantage Berkshire OX12 9AB",
    "addr:housenumber":"21a",
    "addr:postcode":"ox12 9ab",
    "addr:street":"Mill Street",
    "iso:country":"GB",
    "sg:address":"21a Mill Street",
    "sg:city":"Wantage",
    "sg:classifiers":[
        {
            "category":"Shopping",
            "subcategory":"Optician",
            "type":"Retail Goods"
        }
    ],
    "sg:phone":"+44 1235 764488",
    "sg:postcode":"OX12 9AB",
    "sg:province":"Berkshire",
    "wof:name":"Robert Stanley",
    "wof:placetype":"venue"
},
  "geometry": {"coordinates":[-1.427858,51.589348],"type":"Point"}
}