{
  "type": "Feature",
  "properties": {
    "addr:full":"Grn Ore Filling Station Wells Somerset BA5 3ER",
    "addr:postcode":"ba5 3er",
    "addr:street":"Grn",
    "iso:country":"GB",
    "sg:address":"Grn Ore Filling Station",
    "sg:city":"Wells",
    "sg:classifiers":[
        {
            "category":"Autos & Motor Vehicles",
            "subcategory":"Automobile Sales",
            "type":"Retail Goods"
        },
        {
            "category":"Retail",
            "subcategory":"Auto Repair",
            "type":"Services"
        }
    ],
    "sg:postcode":"BA5 3ER",
    "sg:province":"Somerset",
    "sg:tags":[
        "specialist",
        "classic",
        "car",
        "sales",
        "garage",
        "modification"
    ],
    "wof:name":"Deane Engineering",
    "wof:placetype":"venue"
},
  "geometry": {"coordinates":[-2.645954,51.211349],"type":"Point"}
}