{
  "type": "Feature",
  "properties": {
    "iso:country":"GB",
    "sg:address":"95 Richmond Road",
    "sg:city":"Kingston-upon-thames",
    "sg:classifiers":[
        {
            "category":"Health Services",
            "subcategory":"Doctor",
            "type":"Services"
        }
    ],
    "sg:phone":"+44 844 499 6611",
    "sg:postcode":"KT2 5BT",
    "sg:province":"Greater London",
    "sg:tags":[
        "practitioners"
    ],
    "wof:name":"Richmond Road Medical Centre",
    "wof:placetype":"venue"
},
  "geometry": {"coordinates":[-0.301643014,51.4172019958],"type":"Point"}
}