{
  "type": "Feature",
  "properties": {
    "iso:country":"GB",
    "sg:address":"The Circle",
    "sg:city":"Swindon",
    "sg:classifiers":[
        {
            "category":"Education",
            "subcategory":"Library",
            "type":"Public Place"
        },
        {
            "category":"Government",
            "subcategory":"Office",
            "type":"Public Place"
        }
    ],
    "sg:phone":"+44 1793 616271",
    "sg:postcode":"SN2 1QZ",
    "sg:province":"Wiltshire",
    "sg:tags":[
        "book",
        "local"
    ],
    "wof:name":"Pinehurst Library",
    "wof:placetype":"venue"
},
  "geometry": {"coordinates":[-1.7806270123,51.5834732056],"type":"Point"}
}