{
  "type": "Feature",
  "properties": {
    "iso:country":"GB",
    "sg:address":"Unit 2, Athron Ind Est",
    "sg:city":"Doncaster",
    "sg:classifiers":[
        {
            "category":"Retail",
            "subcategory":"Auto Repair",
            "type":"Services"
        }
    ],
    "sg:phone":"+44 1302 361111",
    "sg:postcode":"DN1 2NU",
    "sg:province":"South Yorkshire",
    "sg:tags":[
        "car",
        "upholsterer"
    ],
    "wof:name":"Eurovaleting Ltd",
    "wof:placetype":"venue"
},
  "geometry": {"coordinates":[-1.126654,53.528534],"type":"Point"}
}