{
  "type": "Feature",
  "properties": {
    "addr:full":"136 Frankby Road, West Kirby Wirral Merseyside CH48 9UX",
    "addr:housenumber":"136",
    "addr:postcode":"ch48 9ux",
    "addr:street":"Frankby Road",
    "iso:country":"GB",
    "sg:address":"136 Frankby Road, West Kirby",
    "sg:city":"Wirral",
    "sg:classifiers":[
        {
            "category":"Food & Beverages",
            "subcategory":"Groceries & Convenience Stores",
            "type":"Retail Goods"
        }
    ],
    "sg:phone":"+44 151 625 1966",
    "sg:postcode":"CH48 9UX",
    "sg:province":"Merseyside",
    "wof:name":"Ian Herbert",
    "wof:placetype":"venue"
},
  "geometry": {"coordinates":[-3.1542229652,53.3732147217],"type":"Point"}
}