{
  "type": "Feature",
  "properties": {
    "iso:country":"GB",
    "sg:address":"148 Milton Road",
    "sg:city":"Weston-super-mare",
    "sg:classifiers":[
        {
            "category":"Travel",
            "subcategory":"Hotels & Motels",
            "type":"Entertainment"
        }
    ],
    "sg:phone":"+44 1934 627793",
    "sg:postcode":"BS23 2UZ",
    "sg:province":"Somerset",
    "wof:name":"Wychwood Hotel",
    "wof:placetype":"venue"
},
  "geometry": {"coordinates":[-2.956665,51.35136],"type":"Point"}
}