{
  "type": "Feature",
  "properties": {
    "addr:full":"32 Quay Street Ammanford Carmarthenshire SA18 3EN",
    "addr:housenumber":"32",
    "addr:postcode":"sa18 3en",
    "addr:street":"Quay Street",
    "iso:country":"GB",
    "sg:address":"32 Quay Street",
    "sg:city":"Ammanford",
    "sg:classifiers":[
        {
            "category":"Fast Food",
            "type":"Food & Drink"
        }
    ],
    "sg:phone":"+44 1269 596688",
    "sg:postcode":"SA18 3EN",
    "sg:province":"Carmarthenshire",
    "sg:tags":[
        "away",
        "take"
    ],
    "wof:name":"Shaan Tandoori Takeaway",
    "wof:placetype":"venue"
},
  "geometry": {"coordinates":[-3.986977,51.791363],"type":"Point"}
}