{
  "type": "Feature",
  "properties": {
    "addr:full":"21 Gold Tops Newport Newport NP20 4PG",
    "addr:housenumber":"21",
    "addr:postcode":"np20 4pg",
    "addr:street":"Gold Tops",
    "iso:country":"GB",
    "sg:address":"21 Gold Tops",
    "sg:city":"Newport",
    "sg:classifiers":[
        {
            "category":"Retail",
            "subcategory":"Auto Repair",
            "type":"Services"
        }
    ],
    "sg:phone":"+44 1291 424282",
    "sg:postcode":"NP20 4PG",
    "sg:province":"Newport",
    "sg:tags":[
        "body",
        "car",
        "related",
        "garage"
    ],
    "wof:name":"Caldicot Fleet Maintenance Ltd.",
    "wof:placetype":"venue"
},
  "geometry": {"coordinates":[-3.0020949841,51.5899734497],"type":"Point"}
}