{
  "type": "Feature",
  "properties": {
    "addr:full":"13 Bedwlwyn Road, Ystrad Mynach Hengoed Shropshire CF8 7AA",
    "addr:housenumber":"13",
    "addr:postcode":"cf8 7aa",
    "addr:street":"Bedwlwyn Road",
    "iso:country":"GB",
    "sg:address":"13 Bedwlwyn Road, Ystrad Mynach",
    "sg:city":"Hengoed",
    "sg:classifiers":[
        {
            "category":"Autos & Motor Vehicles",
            "subcategory":"Auto Supplies",
            "type":"Retail Goods"
        },
        {
            "category":"Shopping",
            "type":"Retail Goods"
        }
    ],
    "sg:phone":"+44 1443 813017",
    "sg:postcode":"CF8 7AA",
    "sg:province":"Shropshire",
    "sg:tags":[
        "car",
        "part",
        "accessory",
        "audio"
    ],
    "wof:name":"Motor World Ltd.",
    "wof:placetype":"venue"
},
  "geometry": {"coordinates":[-3.2260699272,51.6450881958],"type":"Point"}
}