{
  "type": "Feature",
  "properties": {
    "addr:full":"130 Crouch Hill Hornsey Greater London N8 9DY",
    "addr:housenumber":"130",
    "addr:postcode":"n8 9dy",
    "addr:street":"Crouch Hill",
    "iso:country":"GB",
    "sg:address":"130 Crouch Hill",
    "sg:city":"Hornsey",
    "sg:classifiers":[
        {
            "category":"Restaurant",
            "type":"Food & Drink"
        }
    ],
    "sg:phone":"+44 20 8340 5635",
    "sg:postcode":"N8 9DY",
    "sg:province":"Greater London",
    "wof:name":"World Cafe",
    "wof:placetype":"venue"
},
  "geometry": {"coordinates":[-0.127039,51.57457],"type":"Point"}
}