{
  "type": "Feature",
  "properties": {
    "addr:full":"129 Elwick Road Hartlepool Durham TS26 9BQ",
    "addr:housenumber":"129",
    "addr:postcode":"ts26 9bq",
    "addr:street":"Elwick Road",
    "iso:country":"GB",
    "sg:address":"129 Elwick Road",
    "sg:city":"Hartlepool",
    "sg:classifiers":[
        {
            "category":"Food & Beverages",
            "subcategory":"Liquor & Beverages",
            "type":"Retail Goods"
        }
    ],
    "sg:phone":"+44 1429 860108",
    "sg:postcode":"TS26 9BQ",
    "sg:province":"Durham",
    "sg:tags":[
        "beer",
        "wine",
        "spirit",
        "wines"
    ],
    "wof:name":"Victoria Wine",
    "wof:placetype":"venue"
},
  "geometry": {"coordinates":[-1.2231,54.679241],"type":"Point"}
}