{
  "type": "Feature",
  "properties": {
    "iso:country":"GB",
    "sg:address":"173 St Andrews Rd",
    "sg:city":"Coulsdon",
    "sg:classifiers":[
        {
            "category":"Building & Trades",
            "subcategory":"Construction",
            "type":"Services"
        }
    ],
    "sg:phone":"+44 20 8668 6301",
    "sg:postcode":"CR5 3HN",
    "sg:province":"Surrey",
    "sg:tags":[
        "heating",
        "contractor"
    ],
    "wof:name":"K R Mitchell",
    "wof:placetype":"venue"
},
  "geometry": {"coordinates":[-0.156758,51.318832],"type":"Point"}
}