{
  "type": "Feature",
  "properties": {
    "addr:full":"26 Wordsworth Crescent, North Prospect Plymouth Devon PL2 2JH",
    "addr:housenumber":"26",
    "addr:postcode":"pl2 2jh",
    "addr:street":"Wordsworth Crescent",
    "iso:country":"GB",
    "sg:address":"26 Wordsworth Crescent, North Prospect",
    "sg:city":"Plymouth",
    "sg:classifiers":[
        {
            "category":"Building & Trades",
            "subcategory":"Landscaping Services",
            "type":"Services"
        }
    ],
    "sg:phone":"+44 1752 362041",
    "sg:postcode":"PL2 2JH",
    "sg:province":"Devon",
    "sg:tags":[
        "gardening"
    ],
    "wof:name":"Garden Services",
    "wof:placetype":"venue"
},
  "geometry": {"coordinates":[-4.1740131378,50.3927383423],"type":"Point"}
}