{
  "type": "Feature",
  "properties": {
    "addr:full":"19 Hillfoot Street Glasgow Glasgow City G31 2LD",
    "addr:housenumber":"19",
    "addr:postcode":"g31 2ld",
    "addr:street":"Hillfoot Street",
    "iso:country":"GB",
    "sg:address":"19 Hillfoot Street",
    "sg:city":"Glasgow",
    "sg:classifiers":[
        {
            "category":"Recreation",
            "subcategory":"Amusement Park",
            "type":"Entertainment"
        },
        {
            "category":"Casinos & Gambling",
            "type":"Entertainment"
        }
    ],
    "sg:phone":"+44 141 554 5396",
    "sg:postcode":"G31 2LD",
    "sg:province":"Glasgow City",
    "sg:tags":[
        "turf",
        "accountant",
        "bookmaker",
        "arcade"
    ],
    "wof:name":"Prize Bingo",
    "wof:placetype":"venue"
},
  "geometry": {"coordinates":[-4.2208781242,55.8585777283],"type":"Point"}
}