{
  "type": "Feature",
  "properties": {
    "addr:full":"Unit 3 Viewpark Shopping Centre, Old Edinburgh Road Glasgow Glasgow City G71 6LB",
    "addr:housenumber":"unit 3",
    "addr:postcode":"g71 6lb",
    "addr:street":"Viewpark Shopping;Old Edinburgh Road",
    "iso:country":"GB",
    "sg:address":"Unit 3 Viewpark Shopping Centre, Old Edinburgh Road",
    "sg:city":"Glasgow",
    "sg:classifiers":[
        {
            "category":"Retail",
            "subcategory":"Veterinary Services",
            "type":"Services"
        }
    ],
    "sg:phone":"+44 1698 327122",
    "sg:postcode":"G71 6LB",
    "sg:province":"Glasgow City",
    "sg:tags":[
        "surgeon"
    ],
    "wof:name":"Iain Inglis",
    "wof:placetype":"venue"
},
  "geometry": {"coordinates":[-4.05287,55.824459],"type":"Point"}
}