{
  "type": "Feature",
  "properties": {
    "addr:full":"58 George St Hove East Sussex BN3 3YD",
    "addr:housenumber":"58",
    "addr:postcode":"bn3 3yd",
    "addr:street":"George St",
    "iso:country":"GB",
    "sg:address":"58 George St",
    "sg:city":"Hove",
    "sg:classifiers":[
        {
            "category":"Shopping",
            "subcategory":"Stationery & Office Supplies",
            "type":"Retail Goods"
        }
    ],
    "sg:phone":"+44 1273 820561",
    "sg:postcode":"BN3 3YD",
    "sg:province":"East Sussex",
    "wof:name":"Bubbles",
    "wof:placetype":"venue"
},
  "geometry": {"coordinates":[-0.1728390008,50.8310012817],"type":"Point"}
}