{
  "type": "Feature",
  "properties": {
    "addr:full":"158 Bispham Rd Blackpool Lancashire FY2 0LA",
    "addr:housenumber":"158",
    "addr:postcode":"fy2 0la",
    "addr:street":"Bispham Rd",
    "iso:country":"GB",
    "sg:address":"158 Bispham Rd",
    "sg:city":"Blackpool",
    "sg:classifiers":[
        {
            "category":"Personal",
            "subcategory":"Beauty Salon",
            "type":"Services"
        }
    ],
    "sg:phone":"+44 1253 593240",
    "sg:postcode":"FY2 0LA",
    "sg:province":"Lancashire",
    "sg:tags":[
        "unisex",
        "hairdresser"
    ],
    "wof:name":"Jean's Coiffure",
    "wof:placetype":"venue"
},
  "geometry": {"coordinates":[-3.0329151154,53.8437614441],"type":"Point"}
}