{
  "type": "Feature",
  "properties": {
    "addr:full":"3a Chapel Street Wrexham Wrexham LL13 7DD",
    "addr:housenumber":"3a",
    "addr:postcode":"ll13 7dd",
    "addr:street":"Chapel Street",
    "iso:country":"GB",
    "sg:address":"3a Chapel Street",
    "sg:city":"Wrexham",
    "sg:classifiers":[
        {
            "category":"Real Estate",
            "subcategory":"Architect",
            "type":"Services"
        }
    ],
    "sg:phone":"+44 1978 357887",
    "sg:postcode":"LL13 7DD",
    "sg:province":"Wrexham",
    "wof:name":"Lawray Ltd",
    "wof:placetype":"venue"
},
  "geometry": {"coordinates":[-2.995085001,53.0430793762],"type":"Point"}
}