{
  "type": "Feature",
  "properties": {
    "addr:full":"Manchester Science Park, Synergy House, Guildhall Close Manchester Cheshire M15 6SY",
    "addr:postcode":"m15 6sy",
    "addr:street":"Park;Guildhall Close",
    "iso:country":"GB",
    "sg:address":"Manchester Science Park, Synergy House, Guildhall Close",
    "sg:city":"Manchester",
    "sg:classifiers":[
        {
            "category":"Social Services",
            "type":"Services"
        }
    ],
    "sg:phone":"+44 161 232 7665",
    "sg:postcode":"M15 6SY",
    "sg:province":"Cheshire",
    "sg:tags":[
        "disability"
    ],
    "wof:name":"Ossur (U K) Ltd.",
    "wof:placetype":"venue"
},
  "geometry": {"coordinates":[-2.240659,53.466572],"type":"Point"}
}