{
  "type": "Feature",
  "properties": {
    "addr:full":"Darroch Annex, 7 Gillespie Street Edinburgh City of Edinburgh EH3 9NH",
    "addr:postcode":"eh3 9nh",
    "addr:street":"Gillespie Street",
    "iso:country":"GB",
    "sg:address":"Darroch Annex, 7 Gillespie Street",
    "sg:city":"Edinburgh",
    "sg:classifiers":[
        {
            "category":"Organizations",
            "subcategory":"Non-profit Organization",
            "type":"Services"
        }
    ],
    "sg:phone":"+44 131 221 1915",
    "sg:postcode":"EH3 9NH",
    "sg:province":"City of Edinburgh",
    "sg:tags":[
        "charitable",
        "organisation",
        "voluntary",
        "charity"
    ],
    "wof:name":"Nari Kallyan Shangho",
    "wof:placetype":"venue"
},
  "geometry": {"coordinates":[-3.2072401047,55.940990448],"type":"Point"}
}