{
  "type": "Feature",
  "properties": {
    "addr:full":"Rhos Y Gaer Terr Holyhead Isle of Anglesey LL65 2HW",
    "addr:postcode":"ll65 2hw",
    "addr:street":"Rhos Y Gaer Terr",
    "iso:country":"GB",
    "sg:address":"Rhos Y Gaer Terr",
    "sg:city":"Holyhead",
    "sg:classifiers":[
        {
            "category":"Bars & Pubs",
            "type":"Food & Drink"
        }
    ],
    "sg:phone":"+44 1407 762710",
    "sg:postcode":"LL65 2HW",
    "sg:province":"Isle of Anglesey",
    "sg:tags":[
        "pubs",
        "inn"
    ],
    "wof:name":"Holland Inn The",
    "wof:placetype":"venue"
},
  "geometry": {"coordinates":[-4.6307139397,53.3063697815],"type":"Point"}
}