{
  "type": "Feature",
  "properties": {
    "iso:country":"GB",
    "sg:address":"Pastures Farm, Rawcliffe",
    "sg:city":"Goole",
    "sg:classifiers":[
        {
            "category":"Farming",
            "subcategory":"Farm",
            "type":"Manufacturing & Wholesale Goods"
        }
    ],
    "sg:postcode":"DN14 8SH",
    "sg:province":"East Riding of Yorkshire",
    "sg:tags":[
        "mixed",
        "crop"
    ],
    "wof:name":"David W Thornton",
    "wof:placetype":"venue"
},
  "geometry": {"coordinates":[-0.9627460241,53.6993980408],"type":"Point"}
}