{
  "type": "Feature",
  "properties": {
    "iso:country":"GB",
    "sg:address":"170 High Street",
    "sg:city":"Macclesfield",
    "sg:classifiers":[
        {
            "category":"Shopping",
            "subcategory":"News",
            "type":"Retail Goods"
        }
    ],
    "sg:phone":"+44 1625 424117",
    "sg:postcode":"SK11 7QE",
    "sg:province":"Cheshire",
    "sg:tags":[
        "newsagent"
    ],
    "wof:name":"A & N News",
    "wof:placetype":"venue"
},
  "geometry": {"coordinates":[-2.122723,53.250477],"type":"Point"}
}