{
  "type": "Feature",
  "properties": {
    "addr:full":"5 Greenway Terrace, Kingston St Mary Taunton Somerset TA2 8JJ",
    "addr:housenumber":"5",
    "addr:postcode":"ta2 8jj",
    "addr:street":"Greenway Terrace;St Mary",
    "iso:country":"GB",
    "sg:address":"5 Greenway Terrace, Kingston St Mary",
    "sg:city":"Taunton",
    "sg:classifiers":[
        {
            "category":"Retail",
            "subcategory":"Driving School",
            "type":"Services"
        }
    ],
    "sg:phone":"+44 1823 451786",
    "sg:postcode":"TA2 8JJ",
    "sg:province":"Somerset",
    "wof:name":"TRUCKBUS TRAINING",
    "wof:placetype":"venue"
},
  "geometry": {"coordinates":[-3.118619,51.060703],"type":"Point"}
}