{
  "type": "Feature",
  "properties": {
    "iso:country":"GB",
    "sg:address":"11-13 Ringwood Road",
    "sg:city":"Verwood",
    "sg:classifiers":[
        {
            "category":"Food & Beverages",
            "subcategory":"Bakery",
            "type":"Retail Goods"
        }
    ],
    "sg:postcode":"BH31 7AA",
    "sg:province":"Dorset",
    "sg:tags":[
        "baker"
    ],
    "wof:name":"Belinda's Bakery",
    "wof:placetype":"venue"
},
  "geometry": {"coordinates":[-1.8783379793,50.8817405701],"type":"Point"}
}