{
  "type": "Feature",
  "properties": {
    "iso:country":"GB",
    "sg:address":"69 Mount Road",
    "sg:city":"Hastings",
    "sg:classifiers":[
        {
            "category":"Shopping",
            "subcategory":"Pets & Pet Supplies",
            "type":"Retail Goods"
        }
    ],
    "sg:postcode":"TN35 5LA",
    "sg:province":"East Sussex",
    "wof:name":"Mount Road Aquaria & Pet Supplies",
    "wof:placetype":"venue"
},
  "geometry": {"coordinates":[0.6021310091,50.8681983948],"type":"Point"}
}