{
  "type": "Feature",
  "properties": {
    "addr:full":"16 Harwill Rise Leeds West Yorkshire LS27 7QN",
    "addr:housenumber":"16",
    "addr:postcode":"ls27 7qn",
    "addr:street":"Harwill Rise",
    "iso:country":"GB",
    "sg:address":"16 Harwill Rise",
    "sg:city":"Leeds",
    "sg:classifiers":[
        {
            "category":"Building & Trades",
            "subcategory":"Construction",
            "type":"Services"
        }
    ],
    "sg:postcode":"LS27 7QN",
    "sg:province":"West Yorkshire",
    "sg:tags":[
        "builder"
    ],
    "wof:name":"Barry's Building Services",
    "wof:placetype":"venue"
},
  "geometry": {"coordinates":[-1.587146,53.758759],"type":"Point"}
}