{
  "type": "Feature",
  "properties": {
    "iso:country":"GB",
    "sg:address":"Summer Lane",
    "sg:city":"Banwell",
    "sg:classifiers":[
        {
            "category":"Transit Center",
            "subcategory":"Passenger",
            "type":"Transportation"
        },
        {
            "category":"Farming",
            "subcategory":"Livestock Farm",
            "type":"Manufacturing & Wholesale Goods"
        }
    ],
    "sg:phone":"+44 1934 822758",
    "sg:postcode":"BS29 6LR",
    "sg:province":"Somerset",
    "sg:tags":[
        "boarding",
        "catteries",
        "kennel",
        "others"
    ],
    "wof:name":"Amantra Kennels & Cattery",
    "wof:placetype":"venue"
},
  "geometry": {"coordinates":[-2.864942,51.327827],"type":"Point"}
}