{
  "type": "Feature",
  "properties": {
    "iso:country":"GB",
    "sg:address":"1 Thanet St",
    "sg:city":"Bloomsbury",
    "sg:classifiers":[
        {
            "category":"Professional",
            "subcategory":"Employment Agencies",
            "type":"Services"
        }
    ],
    "sg:phone":"+44 20 7388 4498",
    "sg:postcode":"WC1H 9ES",
    "sg:province":"Greater London",
    "sg:tags":[
        "consular"
    ],
    "wof:name":"Action Visas",
    "wof:placetype":"venue"
},
  "geometry": {"coordinates":[-0.12525,51.527],"type":"Point"}
}