{
  "type": "Feature",
  "properties": {
    "addr:full":"Thistledown, Park Lane, Appleton Oxford Oxfordshire OX13 5JT",
    "addr:postcode":"ox13 5jt",
    "addr:street":"Thistledown Park Lane",
    "iso:country":"GB",
    "sg:address":"Thistledown, Park Lane, Appleton",
    "sg:city":"Oxford",
    "sg:classifiers":[
        {
            "category":"Organizations",
            "subcategory":"Non-profit Organization",
            "type":"Services"
        }
    ],
    "sg:phone":"+44 1865 862416",
    "sg:postcode":"OX13 5JT",
    "sg:province":"Oxfordshire",
    "sg:tags":[
        "charitable",
        "organisation",
        "voluntary",
        "charity"
    ],
    "wof:name":"THE STROKE ASSOCIATION",
    "wof:placetype":"venue"
},
  "geometry": {"coordinates":[-1.2594890594,51.7562065125],"type":"Point"}
}