{
  "type": "Feature",
  "properties": {
    "iso:country":"GB",
    "sg:address":"Highgate Lodge, Ridgeway",
    "sg:city":"Whitstable",
    "sg:classifiers":[
        {
            "category":"Health Services",
            "subcategory":"Nursing And Care Facility",
            "type":"Services"
        }
    ],
    "sg:phone":"+44 1227 792281",
    "sg:postcode":"CT5 3JT",
    "sg:province":"Kent",
    "sg:tags":[
        "home"
    ],
    "wof:name":"Highgate Nursing Home",
    "wof:placetype":"venue"
},
  "geometry": {"coordinates":[1.0540629625,51.3574981689],"type":"Point"}
}