{
  "type": "Feature",
  "properties": {
    "iso:country":"GB",
    "sg:address":"Beacons View Transport Depot, Rhigos Road, Hirwaun",
    "sg:city":"Aberdare",
    "sg:classifiers":[
        {
            "category":"Freight",
            "type":"Transportation"
        }
    ],
    "sg:phone":"+44 1685 811864",
    "sg:postcode":"CF44 9UD",
    "sg:province":"Neath Port Talbot",
    "sg:tags":[
        "haulage",
        "road"
    ],
    "wof:name":"Maldwyn Davies Transport",
    "wof:placetype":"venue"
},
  "geometry": {"coordinates":[-3.508034,51.736446],"type":"Point"}
}