{
  "type": "Feature",
  "properties": {
    "addr:full":"St Peters Street Canterbury Kent CT1 2BQ",
    "addr:postcode":"ct1 2bq",
    "addr:street":"St Peters Street",
    "iso:country":"GB",
    "sg:address":"St Peters Street",
    "sg:city":"Canterbury",
    "sg:classifiers":[
        {
            "category":"Professional",
            "subcategory":"Business Services",
            "type":"Services"
        }
    ],
    "sg:phone":"+44 1227 462655",
    "sg:postcode":"CT1 2BQ",
    "sg:province":"Kent",
    "sg:tags":[
        "operator",
        "market"
    ],
    "wof:name":"Indoor Market",
    "wof:placetype":"venue"
},
  "geometry": {"coordinates":[1.0774550438,51.2804908752],"type":"Point"}
}