{
  "type": "Feature",
  "properties": {
    "addr:full":"Penrhyn Bach, Aberdaron Pwllheli Gwynedd LL53 8BY",
    "addr:postcode":"ll53 8by",
    "iso:country":"GB",
    "sg:address":"Penrhyn Bach, Aberdaron",
    "sg:city":"Pwllheli",
    "sg:classifiers":[
        {
            "category":"Restaurant",
            "type":"Food & Drink"
        }
    ],
    "sg:postcode":"LL53 8BY",
    "sg:province":"Gwynedd",
    "wof:name":"Pen Bryn Bach Restaurant",
    "wof:placetype":"venue"
},
  "geometry": {"coordinates":[-4.711589,52.804684],"type":"Point"}
}