{
  "type": "Feature",
  "properties": {
    "addr:full":"174 Broadway Bexleyheath Kent DA6 7BT",
    "addr:housenumber":"174",
    "addr:postcode":"da6 7bt",
    "addr:street":"Broadway",
    "iso:country":"GB",
    "sg:address":"174 Broadway",
    "sg:city":"Bexleyheath",
    "sg:classifiers":[
        {
            "category":"Autos & Motor Vehicles",
            "subcategory":"Auto Supplies",
            "type":"Retail Goods"
        },
        {
            "category":"Shopping Center",
            "type":"Public Place"
        }
    ],
    "sg:phone":"+44 20 8301 5911",
    "sg:postcode":"DA6 7BT",
    "sg:province":"Kent",
    "sg:tags":[
        "clutch",
        "replacement",
        "brake",
        "centre"
    ],
    "wof:name":"Lee Clutch Centre",
    "wof:placetype":"venue"
},
  "geometry": {"coordinates":[0.141117,51.457268],"type":"Point"}
}