{
  "type": "Feature",
  "properties": {
    "addr:full":"12 Marshall Crescent, Morley Leeds West Yorkshire LS27 0HB",
    "addr:housenumber":"12",
    "addr:postcode":"ls27 0hb",
    "addr:street":"Marshall Crescent",
    "iso:country":"GB",
    "sg:address":"12 Marshall Crescent, Morley",
    "sg:city":"Leeds",
    "sg:classifiers":[
        {
            "category":"Education",
            "subcategory":"Music School",
            "type":"Public Place"
        },
        {
            "category":"Education",
            "subcategory":"School",
            "type":"Public Place"
        }
    ],
    "sg:phone":"+44 113 253 9806",
    "sg:postcode":"LS27 0HB",
    "sg:province":"West Yorkshire",
    "sg:tags":[
        "local",
        "teacher",
        "authority"
    ],
    "wof:name":"Atkins Piano Tuition F T C L  A L C M",
    "wof:placetype":"venue"
},
  "geometry": {"coordinates":[-1.5977400541,53.7371101379],"type":"Point"}
}