{
  "type": "Feature",
  "properties": {
    "addr:full":"Llansteffan Carmarthen Carmarthenshire SA33 5JY",
    "addr:postcode":"sa33 5jy",
    "addr:street":"Llansteffan;Carmarthenshire",
    "iso:country":"GB",
    "sg:address":"Llansteffan",
    "sg:city":"Carmarthen",
    "sg:classifiers":[
        {
            "category":"Food & Beverages",
            "subcategory":"Groceries & Convenience Stores",
            "type":"Retail Goods"
        }
    ],
    "sg:phone":"+44 1267 241201",
    "sg:postcode":"SA33 5JY",
    "sg:province":"Carmarthenshire",
    "wof:name":"D B Thomas",
    "wof:placetype":"venue"
},
  "geometry": {"coordinates":[-4.3907399178,51.7724189758],"type":"Point"}
}