{
  "type": "Feature",
  "properties": {
    "addr:full":"22 Millbank Clo, High Grn Sheffield South Yorkshire S35 4NS",
    "addr:housenumber":"22;clo",
    "addr:postcode":"s35 4ns",
    "addr:street":"Millbank;High Grn",
    "iso:country":"GB",
    "sg:address":"22 Millbank Clo, High Grn",
    "sg:city":"Sheffield",
    "sg:classifiers":[
        {
            "category":"Building & Trades",
            "subcategory":"Plumbing",
            "type":"Services"
        }
    ],
    "sg:postcode":"S35 4NS",
    "sg:province":"South Yorkshire",
    "sg:tags":[
        "heating"
    ],
    "wof:name":"Hutchinson,Stephen,",
    "wof:placetype":"venue"
},
  "geometry": {"coordinates":[-1.49198,53.467041],"type":"Point"}
}