{
  "type": "Feature",
  "properties": {
    "iso:country":"GB",
    "sg:address":"2 Cross Lane, Braunston",
    "sg:city":"Daventry",
    "sg:classifiers":[
        {
            "category":"Real Estate",
            "subcategory":"Surveying",
            "type":"Services"
        }
    ],
    "sg:phone":"+44 1788 891721",
    "sg:postcode":"NN11 7HH",
    "sg:province":"Northamptonshire",
    "sg:tags":[
        "surveyor",
        "land"
    ],
    "wof:name":"Subsight Surveys Ltd.",
    "wof:placetype":"venue"
},
  "geometry": {"coordinates":[-1.208084,52.29118],"type":"Point"}
}