{
  "type": "Feature",
  "properties": {
    "addr:full":"12 Edinburgh Road South Queensferry City of Edinburgh EH30 9HR",
    "addr:housenumber":"12",
    "addr:postcode":"eh30 9hr",
    "addr:street":"Edinburgh Road",
    "iso:country":"GB",
    "sg:address":"12 Edinburgh Road",
    "sg:city":"South Queensferry",
    "sg:classifiers":[
        {
            "category":"Food & Beverages",
            "subcategory":"Meat & Fish",
            "type":"Retail Goods"
        },
        {
            "category":"Food & Beverages",
            "subcategory":"Groceries & Convenience Stores",
            "type":"Retail Goods"
        }
    ],
    "sg:phone":"+44 131 331 4432",
    "sg:postcode":"EH30 9HR",
    "sg:province":"City of Edinburgh",
    "sg:tags":[
        "shop",
        "chip"
    ],
    "wof:name":"The Ferry Fish Bar",
    "wof:placetype":"venue"
},
  "geometry": {"coordinates":[-3.388883,55.989773],"type":"Point"}
}