{
  "type": "Feature",
  "properties": {
    "iso:country":"GB",
    "sg:address":"Care Of Carpet World",
    "sg:city":"Nottingham",
    "sg:classifiers":[
        {
            "category":"Home & Garden",
            "subcategory":"Home Furnishings",
            "type":"Retail Goods"
        }
    ],
    "sg:phone":"+44 115 920 3852",
    "sg:postcode":"NG5 3GG",
    "sg:province":"Nottinghamshire",
    "sg:tags":[
        "beds",
        "bedding",
        "blanket"
    ],
    "wof:name":"Bensons Bed Centre Northern",
    "wof:placetype":"venue"
},
  "geometry": {"coordinates":[-1.13829,52.99453],"type":"Point"}
}