{
  "type": "Feature",
  "properties": {
    "addr:full":"32 Brook Street West End Greater London W1K 5DL",
    "addr:housenumber":"32",
    "addr:postcode":"w1k 5dl",
    "addr:street":"Brook Street",
    "iso:country":"GB",
    "sg:address":"32 Brook Street",
    "sg:city":"West End",
    "sg:classifiers":[
        {
            "category":"Professional",
            "subcategory":"Employment Agencies",
            "type":"Services"
        }
    ],
    "sg:phone":"+44 20 7470 0057",
    "sg:postcode":"W1K 5DL",
    "sg:province":"Greater London",
    "sg:tags":[
        "consultant"
    ],
    "wof:name":"Arlington Consultants Group",
    "wof:placetype":"venue"
},
  "geometry": {"coordinates":[-0.14648,51.51313],"type":"Point"}
}