{
  "type": "Feature",
  "properties": {
    "iso:country":"GB",
    "sg:address":"218 Bow Common Lane, Bow",
    "sg:city":"London",
    "sg:classifiers":[
        {
            "category":"Manufacturing",
            "subcategory":"Building Materials",
            "type":"Manufacturing & Wholesale Goods"
        }
    ],
    "sg:phone":"+44 20 8980 2213",
    "sg:postcode":"E3 4HH",
    "sg:province":"Greater London",
    "sg:tags":[
        "merchant",
        "builder"
    ],
    "wof:name":"Lazdan Builders Merchants Ltd",
    "wof:placetype":"venue"
},
  "geometry": {"coordinates":[-0.033274,51.521858],"type":"Point"}
}