{
  "type": "Feature",
  "properties": {
    "addr:full":"98 Shenley Hill Radlett Hertfordshire WD7 7BE",
    "addr:housenumber":"98",
    "addr:postcode":"wd7 7be",
    "addr:street":"Shenley Hill Radlett",
    "iso:country":"GB",
    "sg:address":"98 Shenley Hill",
    "sg:city":"Radlett",
    "sg:classifiers":[
        {
            "category":"Organizations",
            "subcategory":"Political Organization",
            "type":"Services"
        }
    ],
    "sg:phone":"+44 1923 857601",
    "sg:postcode":"WD7 7BE",
    "sg:province":"Hertfordshire",
    "sg:tags":[
        "party"
    ],
    "wof:name":"The Labour Party",
    "wof:placetype":"venue"
},
  "geometry": {"coordinates":[-0.3076089919,51.6866416931],"type":"Point"}
}