{
  "type": "Feature",
  "properties": {
    "iso:country":"GB",
    "sg:address":"17 West Cliff Road",
    "sg:city":"Bournemouth",
    "sg:classifiers":[
        {
            "category":"Travel",
            "subcategory":"Hotels & Motels",
            "type":"Entertainment"
        }
    ],
    "sg:phone":"+44 1202 553900",
    "sg:postcode":"BH2 5EX",
    "sg:province":"Dorset",
    "wof:name":"Chequers Hotel",
    "wof:placetype":"venue"
},
  "geometry": {"coordinates":[-1.889449,50.716423],"type":"Point"}
}