{
  "type": "Feature",
  "properties": {
    "addr:full":"49 Eskin Street Keswick Cumbria CA12 4DG",
    "addr:housenumber":"49",
    "addr:postcode":"ca12 4dg",
    "addr:street":"Eskin Street",
    "iso:country":"GB",
    "sg:address":"49 Eskin Street",
    "sg:city":"Keswick",
    "sg:classifiers":[
        {
            "category":"Wholesale",
            "subcategory":"Fruits & Vegetables",
            "type":"Manufacturing & Wholesale Goods"
        }
    ],
    "sg:phone":"+44 17687 71116",
    "sg:postcode":"CA12 4DG",
    "sg:province":"Cumbria",
    "wof:name":"THE FRENCH GARDEN LTD",
    "wof:placetype":"venue"
},
  "geometry": {"coordinates":[-3.1315710545,54.6000022888],"type":"Point"}
}