{
  "type": "Feature",
  "properties": {
    "iso:country":"GB",
    "sg:address":"53 Homefield Avenue, Arnold",
    "sg:city":"Nottingham",
    "sg:classifiers":[
        {
            "category":"Building & Trades",
            "subcategory":"Plumbing",
            "type":"Services"
        }
    ],
    "sg:phone":"+44 115 926 4125",
    "sg:postcode":"NG5 8FZ",
    "sg:province":"Nottinghamshire",
    "sg:tags":[
        "heating"
    ],
    "wof:name":"T F Plumbing & Heating",
    "wof:placetype":"venue"
},
  "geometry": {"coordinates":[-1.114689,53.01297],"type":"Point"}
}