{
  "type": "Feature",
  "properties": {
    "addr:full":"Flat 16 Chadswell, Cromer Street London Greater London WC1H 8LD",
    "addr:housenumber":"flat 16 chadswell",
    "addr:postcode":"wc1h 8ld",
    "addr:street":"Cromer Street",
    "iso:country":"GB",
    "sg:address":"Flat 16 Chadswell, Cromer Street",
    "sg:city":"London",
    "sg:classifiers":[
        {
            "category":"Professional",
            "type":"Services"
        }
    ],
    "sg:phone":"+44 20 7813 9852",
    "sg:postcode":"WC1H 8LD",
    "sg:province":"Greater London",
    "sg:tags":[
        "repair",
        "tech",
        "maintenance"
    ],
    "wof:name":"Accurate Computer Services",
    "wof:placetype":"venue"
},
  "geometry": {"coordinates":[-0.1220299974,51.5275688171],"type":"Point"}
}