{
  "type": "Feature",
  "properties": {
    "addr:full":"79 Marsh Road, Terrington St Clement King's Lynn Lincolnshire PE34 4LA",
    "addr:housenumber":"79",
    "addr:postcode":"pe34 4la",
    "addr:street":"Marsh Road",
    "iso:country":"GB",
    "sg:address":"79 Marsh Road, Terrington St Clement",
    "sg:city":"King's Lynn",
    "sg:classifiers":[
        {
            "category":"Building & Trades",
            "subcategory":"Cleaning & Sanitation",
            "type":"Services"
        },
        {
            "category":"Home & Garden",
            "subcategory":"Carpets & Floor Coverings",
            "type":"Retail Goods"
        }
    ],
    "sg:phone":"+44 1553 829514",
    "sg:postcode":"PE34 4LA",
    "sg:province":"Lincolnshire",
    "sg:tags":[
        "cleaner",
        "upholstery"
    ],
    "wof:name":"P & I CHEM-DRY",
    "wof:placetype":"venue"
},
  "geometry": {"coordinates":[0.3193700016,52.7622909546],"type":"Point"}
}