{
  "type": "Feature",
  "properties": {
    "addr:full":"152 Winchester Road Southampton Hampshire SO16 6UE",
    "addr:housenumber":"152",
    "addr:postcode":"so16 6ue",
    "addr:street":"Winchester Road",
    "iso:country":"GB",
    "sg:address":"152 Winchester Road",
    "sg:city":"Southampton",
    "sg:classifiers":[
        {
            "category":"Social Services",
            "subcategory":"Retirement Home",
            "type":"Services"
        }
    ],
    "sg:phone":"+44 23 8078 0116",
    "sg:postcode":"SO16 6UE",
    "sg:province":"Hampshire",
    "sg:tags":[
        "residential",
        "care"
    ],
    "wof:name":"Oakfield House",
    "wof:placetype":"venue"
},
  "geometry": {"coordinates":[-1.4329149723,50.9274177551],"type":"Point"}
}