{
  "type": "Feature",
  "properties": {
    "addr:full":"17a Coggeshall Rd Braintree Essex CM7 9DB",
    "addr:housenumber":"17a",
    "addr:postcode":"cm7 9db",
    "addr:street":"Coggeshall Rd",
    "iso:country":"GB",
    "sg:address":"17a Coggeshall Rd",
    "sg:city":"Braintree",
    "sg:classifiers":[
        {
            "category":"Health Services",
            "subcategory":"Clinic",
            "type":"Services"
        }
    ],
    "sg:phone":"+44 1376 308200",
    "sg:postcode":"CM7 9DB",
    "sg:province":"Essex",
    "sg:tags":[
        "private"
    ],
    "wof:name":"Braintree Clinic",
    "wof:placetype":"venue"
},
  "geometry": {"coordinates":[0.555339,51.880268],"type":"Point"}
}