{
  "type": "Feature",
  "properties": {
    "addr:full":"Out Elmstead La Canterbury Kent CT4 6PH",
    "addr:postcode":"ct4 6ph",
    "addr:street":"La Canterbury",
    "iso:country":"GB",
    "sg:address":"Out Elmstead La",
    "sg:city":"Canterbury",
    "sg:classifiers":[
        {
            "category":"Social Services",
            "subcategory":"Retirement Home",
            "type":"Services"
        }
    ],
    "sg:phone":"+44 1227 831676",
    "sg:postcode":"CT4 6PH",
    "sg:province":"Kent",
    "sg:tags":[
        "residential",
        "care"
    ],
    "wof:name":"Elmstone Court",
    "wof:placetype":"venue"
},
  "geometry": {"coordinates":[1.156582,51.215569],"type":"Point"}
}