{
  "type": "Feature",
  "properties": {
    "addr:full":"71-73 Bridge Street Row Chester Cheshire CH1 1NW",
    "addr:housenumber":"71-73",
    "addr:postcode":"ch1 1nw",
    "addr:street":"Bridge Street Row",
    "iso:country":"GB",
    "sg:address":"71-73 Bridge Street Row",
    "sg:city":"Chester",
    "sg:classifiers":[
        {
            "category":"Home & Garden",
            "subcategory":"Furniture",
            "type":"Retail Goods"
        }
    ],
    "sg:phone":"+44 1244 343234",
    "sg:postcode":"CH1 1NW",
    "sg:province":"Cheshire",
    "wof:name":"Just Sew Furnishings",
    "wof:placetype":"venue"
},
  "geometry": {"coordinates":[-2.891019,53.188721],"type":"Point"}
}