{
  "type": "Feature",
  "properties": {
    "addr:full":"Pound Lane, Mannings Heath Horsham West Sussex RH13 6JJ",
    "addr:postcode":"rh13 6jj",
    "addr:street":"Pound Lane",
    "iso:country":"GB",
    "sg:address":"Pound Lane, Mannings Heath",
    "sg:city":"Horsham",
    "sg:classifiers":[
        {
            "category":"Shopping",
            "subcategory":"Department Store",
            "type":"Retail Goods"
        },
        {
            "category":"Food & Beverages",
            "subcategory":"Groceries & Convenience Stores",
            "type":"Retail Goods"
        }
    ],
    "sg:phone":"+44 1403 255015",
    "sg:postcode":"RH13 6JJ",
    "sg:province":"West Sussex",
    "wof:name":"The Village Store",
    "wof:placetype":"venue"
},
  "geometry": {"coordinates":[-0.284191,51.045219],"type":"Point"}
}