{
  "type": "Feature",
  "properties": {
    "addr:full":"25 Pleasant Terrace Penzance Cornwall TR19 7JG",
    "addr:housenumber":"25",
    "addr:postcode":"tr19 7jg",
    "addr:street":"Pleasant Terrace",
    "iso:country":"GB",
    "sg:address":"25 Pleasant Terrace",
    "sg:city":"Penzance",
    "sg:classifiers":[
        {
            "category":"Professional",
            "subcategory":"Accounting & Tax Preparation",
            "type":"Services"
        }
    ],
    "sg:phone":"+44 1736 787509",
    "sg:postcode":"TR19 7JG",
    "sg:province":"Cornwall",
    "sg:tags":[
        "accountant"
    ],
    "wof:name":"Peter Devine & Co",
    "wof:placetype":"venue"
},
  "geometry": {"coordinates":[-5.686019,50.123741],"type":"Point"}
}