{
  "type": "Feature",
  "properties": {
    "iso:country":"GB",
    "sg:address":"Chirk",
    "sg:city":"Wrexham",
    "sg:classifiers":[
        {
            "category":"Sports & Exercise",
            "subcategory":"Golf",
            "type":"Entertainment"
        }
    ],
    "sg:phone":"+44 1691 774407",
    "sg:postcode":"LL14 5AD",
    "sg:province":"Wrexham",
    "sg:tags":[
        "club",
        "course"
    ],
    "wof:name":"Chirk Golf & Country Club",
    "wof:placetype":"venue"
},
  "geometry": {"coordinates":[-3.07646,52.94455],"type":"Point"}
}