{
  "type": "Feature",
  "properties": {
    "iso:country":"GB",
    "sg:address":"1 Pevensey Road",
    "sg:city":"Eastbourne",
    "sg:classifiers":[
        {
            "category":"Fast Food",
            "type":"Food & Drink"
        },
        {
            "category":"Cafe",
            "type":"Food & Drink"
        }
    ],
    "sg:postcode":"BN21 3HJ",
    "sg:province":"East Sussex",
    "sg:tags":[
        "tea",
        "away",
        "room",
        "take"
    ],
    "wof:name":"Badgers Set",
    "wof:placetype":"venue"
},
  "geometry": {"coordinates":[0.288426,50.768173],"type":"Point"}
}