{
  "type": "Feature",
  "properties": {
    "iso:country":"GB",
    "sg:address":"113 High Street, Great Ayton",
    "sg:city":"Middlesbrough",
    "sg:classifiers":[
        {
            "category":"Shopping",
            "subcategory":"Gifts & Souvenirs",
            "type":"Retail Goods"
        }
    ],
    "sg:phone":"+44 1642 722823",
    "sg:postcode":"TS9 6BW",
    "sg:province":"North Yorkshire",
    "sg:tags":[
        "shop"
    ],
    "wof:name":"The Premier Collection",
    "wof:placetype":"venue"
},
  "geometry": {"coordinates":[-1.133811,54.488373],"type":"Point"}
}