{
  "type": "Feature",
  "properties": {
    "addr:full":"3 Union Street, Broadmead Bristol City of Bristol BS1 2DD",
    "addr:housenumber":"3",
    "addr:postcode":"bs1 2dd",
    "addr:street":"Union Street",
    "iso:country":"GB",
    "sg:address":"3 Union Street, Broadmead",
    "sg:city":"Bristol",
    "sg:classifiers":[
        {
            "category":"Travel",
            "subcategory":"Travel Agent",
            "type":"Entertainment"
        }
    ],
    "sg:phone":"+44 117 925 1000",
    "sg:postcode":"BS1 2DD",
    "sg:province":"City of Bristol",
    "wof:name":"Bakers Dolphin Travel",
    "wof:placetype":"venue"
},
  "geometry": {"coordinates":[-2.5908589363,51.4557723999],"type":"Point"}
}