{
  "type": "Feature",
  "properties": {
    "addr:full":"Jay Farm, Myers Road, Potton Sandy Bedfordshire SG19 2RG",
    "addr:postcode":"sg19 2rg",
    "addr:street":"Myers Road",
    "iso:country":"GB",
    "sg:address":"Jay Farm, Myers Road, Potton",
    "sg:city":"Sandy",
    "sg:classifiers":[
        {
            "category":"Farming",
            "subcategory":"Livestock Farm",
            "type":"Manufacturing & Wholesale Goods"
        }
    ],
    "sg:phone":"+44 1767 261149",
    "sg:postcode":"SG19 2RG",
    "sg:province":"Bedfordshire",
    "sg:tags":[
        "others"
    ],
    "wof:name":"Katherine Hope",
    "wof:placetype":"venue"
},
  "geometry": {"coordinates":[-0.2161410004,52.1265907288],"type":"Point"}
}