{
  "type": "Feature",
  "properties": {
    "addr:full":"9 Queen St Ulverston Cumbria LA12 7AF",
    "addr:housenumber":"9",
    "addr:postcode":"la12 7af",
    "addr:street":"Queen St",
    "iso:country":"GB",
    "sg:address":"9 Queen St",
    "sg:city":"Ulverston",
    "sg:classifiers":[
        {
            "category":"Farming",
            "subcategory":"Fish & Marine Products",
            "type":"Manufacturing & Wholesale Goods"
        },
        {
            "category":"Food & Beverages",
            "subcategory":"Meat & Fish",
            "type":"Retail Goods"
        }
    ],
    "sg:postcode":"LA12 7AF",
    "sg:province":"Cumbria",
    "sg:tags":[
        "fishmonger",
        "butcher"
    ],
    "wof:name":"Winder,Peter,",
    "wof:placetype":"venue"
},
  "geometry": {"coordinates":[-3.096331,54.195621],"type":"Point"}
}