{
  "type": "Feature",
  "properties": {
    "addr:full":"Beveley Road, Oakengates Telford Shropshire TF2 6AT",
    "addr:postcode":"tf2 6at",
    "addr:street":"Beveley Road",
    "iso:country":"GB",
    "sg:address":"Beveley Road, Oakengates",
    "sg:city":"Telford",
    "sg:classifiers":[
        {
            "category":"Manufacturing",
            "subcategory":"Motor Vehicles & Parts",
            "type":"Manufacturing & Wholesale Goods"
        }
    ],
    "sg:phone":"+44 1952 610157",
    "sg:postcode":"TF2 6AT",
    "sg:province":"Shropshire",
    "sg:tags":[
        "bearing"
    ],
    "wof:name":"Shropshire Bearing Services",
    "wof:placetype":"venue"
},
  "geometry": {"coordinates":[-2.462704,52.695423],"type":"Point"}
}