{
  "type": "Feature",
  "properties": {
    "addr:full":"44 Coldean Lane Brighton East Sussex BN1 9GE",
    "addr:housenumber":"44",
    "addr:postcode":"bn1 9ge",
    "addr:street":"Coldean Lane",
    "iso:country":"GB",
    "sg:address":"44 Coldean Lane",
    "sg:city":"Brighton",
    "sg:classifiers":[
        {
            "category":"Building & Trades",
            "subcategory":"Construction",
            "type":"Services"
        }
    ],
    "sg:phone":"+44 1273 278542",
    "sg:postcode":"BN1 9GE",
    "sg:province":"East Sussex",
    "sg:tags":[
        "door",
        "replacement"
    ],
    "wof:name":"Elite Garage Doors",
    "wof:placetype":"venue"
},
  "geometry": {"coordinates":[-0.10792,50.861107],"type":"Point"}
}