{
  "type": "Feature",
  "properties": {
    "addr:full":"Tyler Way, Swalecliffe Whitstable Kent CT5 2RX",
    "addr:postcode":"ct5 2rx",
    "addr:street":"Tyler Way",
    "iso:country":"GB",
    "sg:address":"Tyler Way, Swalecliffe",
    "sg:city":"Whitstable",
    "sg:classifiers":[
        {
            "category":"Manufacturing",
            "subcategory":"Rubber & Plastics",
            "type":"Manufacturing & Wholesale Goods"
        }
    ],
    "sg:phone":"+44 1227 813200",
    "sg:postcode":"CT5 2RX",
    "sg:province":"Kent",
    "sg:tags":[
        "raw",
        "material"
    ],
    "sg:website":"http://www.hellyar.co.uk",
    "wof:name":"John Hellyar & Co. Ltd.",
    "wof:placetype":"venue"
},
  "geometry": {"coordinates":[1.06091,51.360291],"type":"Point"}
}