{
  "type": "Feature",
  "properties": {
    "addr:full":"Unit 311b, 130 Pershore Rd Birmingham West Midlands B5 6ND",
    "addr:housenumber":"311b 130;b5",
    "addr:postcode":"6nd",
    "addr:street":"Pershore Rd",
    "iso:country":"GB",
    "sg:address":"Unit 311b, 130 Pershore Rd",
    "sg:city":"Birmingham",
    "sg:classifiers":[
        {
            "category":"Building & Trades",
            "subcategory":"Electrical",
            "type":"Services"
        }
    ],
    "sg:phone":"+44 121 683 0052",
    "sg:postcode":"B5 6ND",
    "sg:province":"West Midlands",
    "sg:tags":[
        "lighting"
    ],
    "wof:name":"Golden Design",
    "wof:placetype":"venue"
},
  "geometry": {"coordinates":[-1.893729,52.472748],"type":"Point"}
}