{
  "type": "Feature",
  "properties": {
    "iso:country":"GB",
    "sg:address":"Unit 311b, 130 Pershore Rd",
    "sg:city":"Birmingham",
    "sg:classifiers":[
        {
            "category":"Building & Trades",
            "subcategory":"Electrical",
            "type":"Services"
        }
    ],
    "sg:phone":"+44 121 683 0052",
    "sg:postcode":"B5 6ND",
    "sg:province":"West Midlands",
    "sg:tags":[
        "lighting"
    ],
    "wof:name":"Golden Design",
    "wof:placetype":"venue"
},
  "geometry": {"coordinates":[-1.893729,52.472748],"type":"Point"}
}