{
  "type": "Feature",
  "properties": {
    "iso:country":"GB",
    "sg:address":"49 Kenilworth Avenue",
    "sg:city":"Wimbledon",
    "sg:classifiers":[
        {
            "category":"Shopping",
            "subcategory":"Photographic Equipment",
            "type":"Retail Goods"
        }
    ],
    "sg:phone":"+44 20 8947 5784",
    "sg:postcode":"SW19 7LP",
    "sg:province":"Greater London",
    "wof:name":"S Lloyd",
    "wof:placetype":"venue"
},
  "geometry": {"coordinates":[-0.199985,51.429291],"type":"Point"}
}