{
  "type": "Feature",
  "properties": {
    "addr:full":"49 Kenilworth Avenue Wimbledon Greater London SW19 7LP",
    "addr:housenumber":"49",
    "addr:postcode":"sw19 7lp",
    "addr:street":"Kenilworth Avenue",
    "iso:country":"GB",
    "sg:address":"49 Kenilworth Avenue",
    "sg:city":"Wimbledon",
    "sg:classifiers":[
        {
            "category":"Shopping",
            "subcategory":"Photographic Equipment",
            "type":"Retail Goods"
        }
    ],
    "sg:phone":"+44 20 8947 5784",
    "sg:postcode":"SW19 7LP",
    "sg:province":"Greater London",
    "wof:name":"S Lloyd",
    "wof:placetype":"venue"
},
  "geometry": {"coordinates":[-0.199985,51.429291],"type":"Point"}
}