{
  "type": "Feature",
  "properties": {
    "addr:full":"151 Wakefield Road, Scissett Huddersfield South Yorkshire HD8 9HR",
    "addr:housenumber":"151",
    "addr:postcode":"hd8 9hr",
    "addr:street":"Wakefield Road",
    "iso:country":"GB",
    "sg:address":"151 Wakefield Road, Scissett",
    "sg:city":"Huddersfield",
    "sg:classifiers":[
        {
            "category":"Food & Beverages",
            "subcategory":"Liquor & Beverages",
            "type":"Retail Goods"
        }
    ],
    "sg:phone":"+44 1484 861098",
    "sg:postcode":"HD8 9HR",
    "sg:province":"South Yorkshire",
    "sg:tags":[
        "beer",
        "spirit",
        "wines"
    ],
    "wof:name":"Alpine Stores",
    "wof:placetype":"venue"
},
  "geometry": {"coordinates":[-1.6237930059,53.59034729],"type":"Point"}
}