{
  "type": "Feature",
  "properties": {
    "iso:country":"GB",
    "sg:address":"17 Main Street, Lowdham",
    "sg:city":"Nottingham",
    "sg:classifiers":[
        {
            "category":"Shopping",
            "subcategory":"Department Store",
            "type":"Retail Goods"
        },
        {
            "category":"Food & Beverages",
            "subcategory":"Groceries & Convenience Stores",
            "type":"Retail Goods"
        }
    ],
    "sg:phone":"+44 115 966 3055",
    "sg:postcode":"NG14 7AB",
    "sg:province":"Nottinghamshire",
    "wof:name":"Lowdham Stores",
    "wof:placetype":"venue"
},
  "geometry": {"coordinates":[-0.987595,52.991154],"type":"Point"}
}