{
  "type": "Feature",
  "properties": {
    "addr:full":"Spring Gardens Worcester Worcestershire WR1 2BS",
    "addr:postcode":"wr1 2bs",
    "addr:street":"Spring Gardens",
    "iso:country":"GB",
    "sg:address":"Spring Gardens",
    "sg:city":"Worcester",
    "sg:classifiers":[
        {
            "category":"Health Services",
            "subcategory":"Doctor",
            "type":"Services"
        }
    ],
    "sg:phone":"+44 1905 681681",
    "sg:postcode":"WR1 2BS",
    "sg:province":"Worcestershire",
    "sg:tags":[
        "practitioners"
    ],
    "wof:name":"Allen, P A",
    "wof:placetype":"venue"
},
  "geometry": {"coordinates":[-2.2159938812,52.1921005249],"type":"Point"}
}