{
  "type": "Feature",
  "properties": {
    "addr:full":"34 Woodhead Park Haltwhistle Northumberland NE49 9DD",
    "addr:housenumber":"34",
    "addr:postcode":"ne49 9dd",
    "addr:street":"Woodhead Park;Northumberland",
    "iso:country":"GB",
    "sg:address":"34 Woodhead Park",
    "sg:city":"Haltwhistle",
    "sg:classifiers":[
        {
            "category":"Military Area",
            "subcategory":"Air Force Base",
            "type":"Public Place"
        }
    ],
    "sg:phone":"+44 1434 321064",
    "sg:postcode":"NE49 9DD",
    "sg:province":"Northumberland",
    "sg:tags":[
        "taxi",
        "hire",
        "private"
    ],
    "wof:name":"Sproul Taxis",
    "wof:placetype":"venue"
},
  "geometry": {"coordinates":[-2.4673650265,54.9730186462],"type":"Point"}
}