{
  "type": "Feature",
  "properties": {
    "addr:full":"13 New Street Stourport-on-severn Worcestershire DY13 8UW",
    "addr:housenumber":"13",
    "addr:postcode":"dy13 8uw",
    "addr:street":"New Street",
    "iso:country":"GB",
    "sg:address":"13 New Street",
    "sg:city":"Stourport-on-severn",
    "sg:classifiers":[
        {
            "category":"Health Services",
            "subcategory":"Podiatrist",
            "type":"Services"
        }
    ],
    "sg:phone":"+44 1299 878058",
    "sg:postcode":"DY13 8UW",
    "sg:province":"Worcestershire",
    "sg:tags":[
        "podiatrists",
        "chiropodist"
    ],
    "wof:name":"P J Jones",
    "wof:placetype":"venue"
},
  "geometry": {"coordinates":[-2.2813830376,52.339630127],"type":"Point"}
}