{
  "type": "Feature",
  "properties": {
    "addr:full":"Nantycwnstabl Ffostrasol Llandysul Carmarthenshire SA44 4TR",
    "addr:postcode":"sa44 4tr",
    "iso:country":"GB",
    "sg:address":"Nantycwnstabl Ffostrasol",
    "sg:city":"Llandysul",
    "sg:classifiers":[
        {
            "category":"Farming",
            "subcategory":"Dairy Farm",
            "type":"Manufacturing & Wholesale Goods"
        }
    ],
    "sg:phone":"+44 1545 590282",
    "sg:postcode":"SA44 4TR",
    "sg:province":"Carmarthenshire",
    "wof:name":"M A Thomas",
    "wof:placetype":"venue"
},
  "geometry": {"coordinates":[-4.3078169823,52.0444793701],"type":"Point"}
}