{
  "type": "Feature",
  "properties": {
    "addr:full":"Ockends Gardens Centre, Duke Street Littlehampton West Sussex BN17 6EU",
    "addr:postcode":"bn17 6eu",
    "addr:street":"Ockends;Duke Street",
    "iso:country":"GB",
    "sg:address":"Ockends Gardens Centre, Duke Street",
    "sg:city":"Littlehampton",
    "sg:classifiers":[
        {
            "category":"Building & Trades",
            "subcategory":"Landscaping Services",
            "type":"Services"
        },
        {
            "category":"Farming",
            "subcategory":"Livestock Farm",
            "type":"Manufacturing & Wholesale Goods"
        }
    ],
    "sg:phone":"+44 1903 733137",
    "sg:postcode":"BN17 6EU",
    "sg:province":"West Sussex",
    "sg:tags":[
        "pond",
        "aquarium",
        "others"
    ],
    "wof:name":"Keith Viney",
    "wof:placetype":"venue"
},
  "geometry": {"coordinates":[-0.538959,50.82103],"type":"Point"}
}