{
  "type": "Feature",
  "properties": {
    "addr:full":"50 Dundee Road Perth Perth and Kinross PH2 7BA",
    "addr:housenumber":"50",
    "addr:postcode":"ph2 7ba",
    "addr:street":"Dundee Road",
    "iso:country":"GB",
    "sg:address":"50 Dundee Road",
    "sg:city":"Perth",
    "sg:classifiers":[
        {
            "category":"Travel",
            "subcategory":"Hotels & Motels",
            "type":"Entertainment"
        }
    ],
    "sg:postcode":"PH2 7BA",
    "sg:province":"Perth and Kinross",
    "wof:name":"Georgina & Remigio Zane",
    "wof:placetype":"venue"
},
  "geometry": {"coordinates":[-3.418713,56.390701],"type":"Point"}
}