{
  "type": "Feature",
  "properties": {
    "iso:country":"GB",
    "sg:address":"Lauriston Place",
    "sg:city":"Edinburgh",
    "sg:classifiers":[
        {
            "category":"Education",
            "subcategory":"School",
            "type":"Public Place"
        }
    ],
    "sg:phone":"+44 131 229 7263",
    "sg:postcode":"EH3 9EQ",
    "sg:province":"City of Edinburgh",
    "sg:tags":[
        "independent",
        "preparatory"
    ],
    "wof:name":"George Heriots Trust",
    "wof:placetype":"venue"
},
  "geometry": {"coordinates":[-3.198394,55.944904],"type":"Point"}
}