{
  "type": "Feature",
  "properties": {
    "addr:full":"124 Fore St Exeter Devon EX4 3JQ",
    "addr:housenumber":"124",
    "addr:postcode":"ex4 3jq",
    "addr:street":"Fore St",
    "iso:country":"GB",
    "sg:address":"124 Fore St",
    "sg:city":"Exeter",
    "sg:classifiers":[
        {
            "category":"Shopping",
            "subcategory":"Books",
            "type":"Retail Goods"
        }
    ],
    "sg:postcode":"EX4 3JQ",
    "sg:province":"Devon",
    "sg:tags":[
        "bookseller"
    ],
    "wof:name":"Steel,Alan J,",
    "wof:placetype":"venue"
},
  "geometry": {"coordinates":[-3.535132885,50.7203865051],"type":"Point"}
}