{
  "type": "Feature",
  "properties": {
    "addr:full":"184 Kings Ash Rd Paignton Devon TQ3 3XL",
    "addr:housenumber":"184",
    "addr:postcode":"tq3 3xl",
    "addr:street":"Kings Ash Rd",
    "iso:country":"GB",
    "sg:address":"184 Kings Ash Rd",
    "sg:city":"Paignton",
    "sg:classifiers":[
        {
            "category":"Autos & Motor Vehicles",
            "subcategory":"Auto Supplies",
            "type":"Retail Goods"
        }
    ],
    "sg:phone":"+44 1803 552340",
    "sg:postcode":"TQ3 3XL",
    "sg:province":"Devon",
    "sg:tags":[
        "windscreen"
    ],
    "wof:name":"A.J Windscreen Repairs",
    "wof:placetype":"venue"
},
  "geometry": {"coordinates":[-3.58899,50.436619],"type":"Point"}
}