{
  "type": "Feature",
  "properties": {
    "addr:full":"134 Temple Avenue Dagenham Essex RM8 1NB",
    "addr:housenumber":"134",
    "addr:postcode":"rm8 1nb",
    "addr:street":"Temple Avenue",
    "iso:country":"GB",
    "sg:address":"134 Temple Avenue",
    "sg:city":"Dagenham",
    "sg:classifiers":[
        {
            "category":"Health Services",
            "subcategory":"Health Practitioner",
            "type":"Services"
        }
    ],
    "sg:postcode":"RM8 1NB",
    "sg:province":"Essex",
    "sg:tags":[
        "hypnotherapists"
    ],
    "wof:name":"Beacon Tree Hypnotherapy",
    "wof:placetype":"venue"
},
  "geometry": {"coordinates":[0.1495340019,51.5660057068],"type":"Point"}
}