{
  "type": "Feature",
  "properties": {
    "iso:country":"GB",
    "sg:address":"12 Harvey Drive",
    "sg:city":"Sittingbourne",
    "sg:classifiers":[
        {
            "category":"Organizations",
            "subcategory":"Non-profit Organization",
            "type":"Services"
        }
    ],
    "sg:phone":"+44 1795 424170",
    "sg:postcode":"ME10 4UR",
    "sg:province":"Kent",
    "sg:tags":[
        "organisation",
        "voluntary",
        "charity"
    ],
    "wof:name":"The Salvation Army",
    "wof:placetype":"venue"
},
  "geometry": {"coordinates":[0.7440090179,51.3316841125],"type":"Point"}
}