{
  "type": "Feature",
  "properties": {
    "addr:full":"Lovell Rd Bedford Bedfordshire MK42 0LR",
    "addr:postcode":"mk42 0lr",
    "addr:street":"Lovell Rd",
    "iso:country":"GB",
    "sg:address":"Lovell Rd",
    "sg:city":"Bedford",
    "sg:classifiers":[
        {
            "category":"Professional",
            "subcategory":"Detective & Security Services",
            "type":"Services"
        }
    ],
    "sg:phone":"+44 1234 270197",
    "sg:postcode":"MK42 0LR",
    "sg:province":"Bedfordshire",
    "sg:tags":[
        "agency"
    ],
    "wof:name":"Trackdown Investigations",
    "wof:placetype":"venue"
},
  "geometry": {"coordinates":[-0.4435139894,52.1249542236],"type":"Point"}
}