{
  "type": "Feature",
  "properties": {
    "addr:full":"Office 10 Tannery House, Tannery Road Carlisle Cumbria CA1 2SS",
    "addr:housenumber":"10",
    "addr:postcode":"ca1 2ss",
    "addr:street":"Tannery House Tannery Road",
    "iso:country":"GB",
    "sg:address":"Office 10 Tannery House, Tannery Road",
    "sg:city":"Carlisle",
    "sg:classifiers":[
        {
            "category":"Real Estate",
            "subcategory":"Surveying",
            "type":"Services"
        },
        {
            "category":"Real Estate",
            "subcategory":"Architect",
            "type":"Services"
        }
    ],
    "sg:phone":"+44 1228 515633",
    "sg:postcode":"CA1 2SS",
    "sg:province":"Cumbria",
    "sg:tags":[
        "surveyor",
        "quantity"
    ],
    "wof:name":"Currie Associates",
    "wof:placetype":"venue"
},
  "geometry": {"coordinates":[-2.9155499935,54.8823013306],"type":"Point"}
}