{
  "type": "Feature",
  "properties": {
    "addr:full":"21 Ely Place, Holborn Works London Greater London EC1N 6TD",
    "addr:housenumber":"21",
    "addr:postcode":"ec1n 6td",
    "addr:street":"Ely Place Holborn Works",
    "iso:country":"GB",
    "sg:address":"21 Ely Place, Holborn Works",
    "sg:city":"London",
    "sg:classifiers":[
        {
            "category":"Professional",
            "subcategory":"Lawyer & Legal Services",
            "type":"Services"
        }
    ],
    "sg:phone":"+44 20 7353 4433",
    "sg:postcode":"EC1N 6TD",
    "sg:province":"Greater London",
    "sg:tags":[
        "solicitor"
    ],
    "wof:name":"Camillins",
    "wof:placetype":"venue"
},
  "geometry": {"coordinates":[-0.1067849994,51.5189933777],"type":"Point"}
}