{
  "type": "Feature",
  "properties": {
    "iso:country":"GB",
    "sg:address":"33 High Street",
    "sg:city":"Budleigh Salterton",
    "sg:classifiers":[
        {
            "category":"Shopping",
            "subcategory":"Shoes",
            "type":"Retail Goods"
        }
    ],
    "sg:postcode":"EX9 6LD",
    "sg:province":"Devon",
    "sg:tags":[
        "shop"
    ],
    "wof:name":"Creedy & Sons",
    "wof:placetype":"venue"
},
  "geometry": {"coordinates":[-3.326937,50.629353],"type":"Point"}
}