{
  "type": "Feature",
  "properties": {
    "addr:full":"Alverthorpe Road Wakefield West Yorkshire WF2 9PP",
    "addr:postcode":"wf2 9pp",
    "addr:street":"Alverthorpe Road",
    "iso:country":"GB",
    "sg:address":"Alverthorpe Road",
    "sg:city":"Wakefield",
    "sg:classifiers":[
        {
            "category":"Bars & Pubs",
            "type":"Food & Drink"
        }
    ],
    "sg:postcode":"WF2 9PP",
    "sg:province":"West Yorkshire",
    "sg:tags":[
        "pubs",
        "inn"
    ],
    "wof:name":"Scarborough Arms",
    "wof:placetype":"venue"
},
  "geometry": {"coordinates":[-1.5125590563,53.6794281006],"type":"Point"}
}