{
  "type": "Feature",
  "properties": {
    "addr:full":"57 John Finnie St, Kilmarnock East Ayrshire KA1 1BH",
    "addr:housenumber":"57",
    "addr:postcode":"ka1 1bh",
    "addr:street":"John Finnie St",
    "iso:country":"GB",
    "sg:address":"57 John Finnie St,",
    "sg:city":"Kilmarnock",
    "sg:classifiers":[
        {
            "category":"Banks & Credit Unions",
            "subcategory":"Financial Services",
            "type":"Services"
        }
    ],
    "sg:postcode":"KA1 1BH",
    "sg:province":"East Ayrshire",
    "sg:tags":[
        "consultant"
    ],
    "wof:name":"Hannah,Dunlop, J",
    "wof:placetype":"venue"
},
  "geometry": {"coordinates":[-4.4997639656,55.6088600159],"type":"Point"}
}