{
  "type": "Feature",
  "properties": {
    "iso:country":"GB",
    "sg:address":"Church Street, Wolverton",
    "sg:city":"Milton Keynes",
    "sg:classifiers":[
        {
            "category":"Education",
            "subcategory":"School",
            "type":"Public Place"
        }
    ],
    "sg:phone":"+44 1908 314358",
    "sg:postcode":"MK12 5JW",
    "sg:province":"Buckinghamshire",
    "sg:tags":[
        "local",
        "authority"
    ],
    "wof:name":"Wyvern County First Nursery Class",
    "wof:placetype":"venue"
},
  "geometry": {"coordinates":[-0.811659,52.062115],"type":"Point"}
}