{
  "type": "Feature",
  "properties": {
    "addr:full":"7 Wood Ride, Petts Wood Orpington Kent BR5 1PZ",
    "addr:housenumber":"7",
    "addr:postcode":"br5 1pz",
    "addr:street":"Wood Ride;Wood Orpington",
    "iso:country":"GB",
    "sg:address":"7 Wood Ride, Petts Wood",
    "sg:city":"Orpington",
    "sg:classifiers":[
        {
            "category":"Organizations",
            "subcategory":"Non-profit Organization",
            "type":"Services"
        }
    ],
    "sg:phone":"+44 1689 823558",
    "sg:postcode":"BR5 1PZ",
    "sg:province":"Kent",
    "sg:tags":[
        "organisation",
        "voluntary",
        "charity"
    ],
    "wof:name":"National Osteoporosis Society Bromley Support Group",
    "wof:placetype":"venue"
},
  "geometry": {"coordinates":[0.0866990015,51.3926925659],"type":"Point"}
}