{
  "type": "Feature",
  "properties": {
    "addr:full":"16 Hospital St Nantwich Cheshire CW5 5RJ",
    "addr:housenumber":"16",
    "addr:postcode":"cw5 5rj",
    "addr:street":"Hospital St",
    "iso:country":"GB",
    "sg:address":"16 Hospital St",
    "sg:city":"Nantwich",
    "sg:classifiers":[
        {
            "category":"Health Services",
            "subcategory":"Optometrist",
            "type":"Services"
        }
    ],
    "sg:phone":"+44 1270 625282",
    "sg:postcode":"CW5 5RJ",
    "sg:province":"Cheshire",
    "sg:tags":[
        "optician"
    ],
    "wof:name":"Emlyn Owen Limited",
    "wof:placetype":"venue"
},
  "geometry": {"coordinates":[-2.521294117,53.0663032532],"type":"Point"}
}