{
  "type": "Feature",
  "properties": {
    "addr:full":"Rose Cottage, Lower Road, Cookham Rise Maidenhead Berkshire SL6 9EH",
    "addr:postcode":"rise;sl6 9eh",
    "addr:street":"Lower Road",
    "iso:country":"GB",
    "sg:address":"Rose Cottage, Lower Road, Cookham Rise",
    "sg:city":"Maidenhead",
    "sg:classifiers":[
        {
            "category":"Food & Beverages",
            "subcategory":"Meat & Fish",
            "type":"Retail Goods"
        }
    ],
    "sg:phone":"+44 1628 521128",
    "sg:postcode":"SL6 9EH",
    "sg:province":"Berkshire",
    "sg:tags":[
        "butcher"
    ],
    "wof:name":"Macey",
    "wof:placetype":"venue"
},
  "geometry": {"coordinates":[-0.707164,51.557995],"type":"Point"}
}