{
  "type": "Feature",
  "properties": {
    "addr:full":"8 Whitefield Road, Llandaff North Cardiff Cardiff CF14 2JG",
    "addr:housenumber":"8",
    "addr:postcode":"cf14 2jg",
    "addr:street":"Whitefield Road",
    "iso:country":"GB",
    "sg:address":"8 Whitefield Road, Llandaff North",
    "sg:city":"Cardiff",
    "sg:classifiers":[
        {
            "category":"Professional",
            "subcategory":"Engineering",
            "type":"Services"
        }
    ],
    "sg:postcode":"CF14 2JG",
    "sg:province":"Cardiff",
    "sg:tags":[
        "contractor",
        "electrical",
        "engineer"
    ],
    "wof:name":"Clarke Roger & Co.",
    "wof:placetype":"venue"
},
  "geometry": {"coordinates":[-3.222479105,51.5003051758],"type":"Point"}
}