{
  "type": "Feature",
  "properties": {
    "addr:full":"Snaygill Industrial Estate, Keighley Road Skipton Lancashire BD23 2QR",
    "addr:postcode":"bd23 2qr",
    "addr:street":"Snaygill Industrial Estate Keighley Road",
    "iso:country":"GB",
    "sg:address":"Snaygill Industrial Estate, Keighley Road",
    "sg:city":"Skipton",
    "sg:classifiers":[
        {
            "category":"Retail",
            "subcategory":"Auto Repair",
            "type":"Services"
        }
    ],
    "sg:phone":"+44 1756 799009",
    "sg:postcode":"BD23 2QR",
    "sg:province":"Lancashire",
    "sg:tags":[
        "modification",
        "garage",
        "related"
    ],
    "wof:name":"Kenneth Brown Bulk Liquids Ltd.",
    "wof:placetype":"venue"
},
  "geometry": {"coordinates":[-2.0141789913,53.9458885193],"type":"Point"}
}