{
  "type": "Feature",
  "properties": {
    "iso:country":"GB",
    "sg:address":"2 South Parade",
    "sg:city":"Whitley Bay",
    "sg:classifiers":[
        {
            "category":"Bars & Pubs",
            "type":"Food & Drink"
        },
        {
            "category":"Community Center",
            "subcategory":"Social",
            "type":"Public Place"
        }
    ],
    "sg:phone":"+44 191 251 1255",
    "sg:postcode":"NE26 2RG",
    "sg:province":"Northumberland",
    "sg:tags":[
        "pubs",
        "house",
        "inn",
        "activity"
    ],
    "wof:name":"Fitzgeralds",
    "wof:placetype":"venue"
},
  "geometry": {"coordinates":[-1.444061,55.042633],"type":"Point"}
}