{
  "type": "Feature",
  "properties": {
    "iso:country":"GB",
    "sg:address":"88 Christchurch Road",
    "sg:city":"Ringwood",
    "sg:classifiers":[
        {
            "category":"Building & Trades",
            "subcategory":"Construction",
            "type":"Services"
        }
    ],
    "sg:phone":"+44 1425 472701",
    "sg:postcode":"BH24 1DR",
    "sg:province":"Dorset",
    "sg:tags":[
        "builder"
    ],
    "wof:name":"Allum Bros",
    "wof:placetype":"venue"
},
  "geometry": {"coordinates":[-1.7878149748,50.8432731628],"type":"Point"}
}