{
  "type": "Feature",
  "properties": {
    "iso:country":"GB",
    "sg:address":"Unit 4 Green Indust Est, Station Rd",
    "sg:city":"Cannock",
    "sg:classifiers":[
        {
            "category":"Professional",
            "type":"Services"
        }
    ],
    "sg:phone":"+44 1543 878323",
    "sg:postcode":"WS12 4EG",
    "sg:province":"Staffordshire",
    "sg:tags":[
        "exhibition"
    ],
    "wof:name":"A & R",
    "wof:placetype":"venue"
},
  "geometry": {"coordinates":[-2.0187699795,52.7295188904],"type":"Point"}
}