{
  "type": "Feature",
  "properties": {
    "iso:country":"GB",
    "sg:address":"38 Britain St",
    "sg:city":"Dunstable",
    "sg:classifiers":[
        {
            "category":"Professional",
            "subcategory":"Secretarial Services",
            "type":"Services"
        }
    ],
    "sg:postcode":"LU5 4JA",
    "sg:province":"Bedfordshire",
    "wof:name":"Grimmer,Linda,",
    "wof:placetype":"venue"
},
  "geometry": {"coordinates":[-0.513719,51.884861],"type":"Point"}
}