{
  "type": "Feature",
  "properties": {
    "addr:full":"209 Kings Road, Kingstanding Birmingham West Midlands B44 0SB",
    "addr:housenumber":"209",
    "addr:postcode":"b44 0sb",
    "addr:street":"Kings Road",
    "iso:country":"GB",
    "sg:address":"209 Kings Road, Kingstanding",
    "sg:city":"Birmingham",
    "sg:classifiers":[
        {
            "category":"Building & Trades",
            "subcategory":"Construction",
            "type":"Services"
        }
    ],
    "sg:phone":"+44 121 354 1007",
    "sg:postcode":"B44 0SB",
    "sg:province":"West Midlands",
    "sg:tags":[
        "dry",
        "plastering",
        "plasterers",
        "lining",
        "related",
        "screeders"
    ],
    "wof:name":"Stephen Amos",
    "wof:placetype":"venue"
},
  "geometry": {"coordinates":[-1.870451,52.550148],"type":"Point"}
}