{
  "type": "Feature",
  "properties": {
    "iso:country":"GB",
    "sg:address":"Brettenham House, Lancaster Place",
    "sg:city":"London",
    "sg:classifiers":[
        {
            "category":"Professional",
            "subcategory":"Accounting & Tax Preparation",
            "type":"Services"
        }
    ],
    "sg:phone":"+44 20 7836 9671",
    "sg:postcode":"WC2E 7EW",
    "sg:province":"Greater London",
    "sg:tags":[
        "accountant",
        "chartered"
    ],
    "wof:name":"Midgley Snelling & Co",
    "wof:placetype":"venue"
},
  "geometry": {"coordinates":[-0.118900001,51.5105018616],"type":"Point"}
}