{
  "type": "Feature",
  "properties": {
    "iso:country":"GB",
    "sg:address":"Unit 1 Warren Street",
    "sg:city":"Stockport",
    "sg:classifiers":[
        {
            "category":"Shopping",
            "subcategory":"Baby Store",
            "type":"Retail Goods"
        }
    ],
    "sg:phone":"+44 161 429 7233",
    "sg:postcode":"SK1 1UD",
    "sg:province":"Cheshire",
    "sg:tags":[
        "babywear",
        "childrens"
    ],
    "wof:name":"Adams Childrenswear Ltd.",
    "wof:placetype":"venue"
},
  "geometry": {"coordinates":[-2.157007,53.412678],"type":"Point"}
}