{
  "type": "Feature",
  "properties": {
    "addr:full":"Sycamore Trading Estate, Squires Gate Lane Blackpool Lancashire FY4 3RL",
    "addr:housenumber":"estate",
    "addr:postcode":"fy4 3rl",
    "addr:street":"Squires Gate Lane",
    "iso:country":"GB",
    "sg:address":"Sycamore Trading Estate, Squires Gate Lane",
    "sg:city":"Blackpool",
    "sg:classifiers":[
        {
            "category":"Military Area",
            "subcategory":"Air Force Base",
            "type":"Public Place"
        }
    ],
    "sg:phone":"+44 1253 474444",
    "sg:postcode":"FY4 3RL",
    "sg:province":"Lancashire",
    "sg:tags":[
        "water",
        "treatment"
    ],
    "wof:name":"Gledhill (Water Storage) Ltd.",
    "wof:placetype":"venue"
},
  "geometry": {"coordinates":[-3.02303,53.779911],"type":"Point"}
}