{
  "type": "Feature",
  "properties": {
    "iso:country":"GB",
    "sg:address":"7 Claremont Road, Claygate",
    "sg:city":"Esher",
    "sg:classifiers":[
        {
            "category":"Professional",
            "subcategory":"Management & Consulting",
            "type":"Services"
        }
    ],
    "sg:phone":"+44 1932 895353",
    "sg:postcode":"KT10 0PL",
    "sg:province":"Surrey",
    "sg:tags":[
        "consultant",
        "business"
    ],
    "wof:name":"Davies Associates",
    "wof:placetype":"venue"
},
  "geometry": {"coordinates":[-0.3459179997,51.3572349548],"type":"Point"}
}