{
  "type": "Feature",
  "properties": {
    "addr:full":"4 Hoggan Way Alva Clackmannanshire FK12 5GG",
    "addr:housenumber":"4",
    "addr:postcode":"fk12 5gg",
    "addr:street":"Hoggan Way",
    "iso:country":"GB",
    "sg:address":"4 Hoggan Way",
    "sg:city":"Alva",
    "sg:classifiers":[
        {
            "category":"Building & Trades",
            "subcategory":"Construction",
            "type":"Services"
        }
    ],
    "sg:phone":"+44 1259 760213",
    "sg:postcode":"FK12 5GG",
    "sg:province":"Clackmannanshire",
    "sg:tags":[
        "joiner",
        "carpenter"
    ],
    "wof:name":"McCormack Alan Joiner & Building Contractor",
    "wof:placetype":"venue"
},
  "geometry": {"coordinates":[-3.8044810295,56.1512336731],"type":"Point"}
}