{
  "type": "Feature",
  "properties": {
    "iso:country":"GB",
    "sg:address":"Woodside Leisure Park, North Orbital Rd, Garston",
    "sg:city":"Watford",
    "sg:classifiers":[
        {
            "category":"Restaurant",
            "type":"Food & Drink"
        }
    ],
    "sg:phone":"+44 1923 662690",
    "sg:postcode":"WD2 6NB",
    "sg:province":"Hertfordshire",
    "wof:name":"Frankie & Bennys Restaurant",
    "wof:placetype":"venue"
},
  "geometry": {"coordinates":[-0.3824,51.68996],"type":"Point"}
}