{
  "type": "Feature",
  "properties": {
    "iso:country":"GB",
    "sg:address":"31 Ellerbeck, Wilnecote",
    "sg:city":"Tamworth",
    "sg:classifiers":[
        {
            "category":"Personal",
            "subcategory":"Beauty Salon",
            "type":"Services"
        }
    ],
    "sg:phone":"+44 1827 892303",
    "sg:postcode":"B77 4JA",
    "sg:province":"Staffordshire",
    "sg:tags":[
        "unisex",
        "hairdresser"
    ],
    "wof:name":"Chrissy John",
    "wof:placetype":"venue"
},
  "geometry": {"coordinates":[-1.6500799656,52.6171607971],"type":"Point"}
}