{
  "type": "Feature",
  "properties": {
    "iso:country":"GB",
    "sg:address":"Clubhouse, Milking Nook Drove",
    "sg:city":"Bourne",
    "sg:classifiers":[
        {
            "category":"Arena",
            "subcategory":"Sports Club",
            "type":"Entertainment"
        }
    ],
    "sg:phone":"+44 1778 393346",
    "sg:postcode":"PE10 0AX",
    "sg:province":"Lincolnshire",
    "sg:tags":[
        "ground"
    ],
    "wof:name":"Bourne Rugby Union Football Club",
    "wof:placetype":"venue"
},
  "geometry": {"coordinates":[-0.338134,52.769974],"type":"Point"}
}