{
  "type": "Feature",
  "properties": {
    "addr:full":"20 Station Road, Steeton Keighley North Yorkshire BD20 6RL",
    "addr:housenumber":"20",
    "addr:postcode":"bd20 6rl",
    "addr:street":"Station Road",
    "iso:country":"GB",
    "sg:address":"20 Station Road, Steeton",
    "sg:city":"Keighley",
    "sg:classifiers":[
        {
            "category":"Farming",
            "subcategory":"Fish & Marine Products",
            "type":"Manufacturing & Wholesale Goods"
        },
        {
            "category":"Food & Beverages",
            "subcategory":"Meat & Fish",
            "type":"Retail Goods"
        }
    ],
    "sg:phone":"+44 1535 655135",
    "sg:postcode":"BD20 6RL",
    "sg:province":"North Yorkshire",
    "sg:tags":[
        "fishmonger",
        "butcher"
    ],
    "wof:name":"RICHARD H CHAMLEY",
    "wof:placetype":"venue"
},
  "geometry": {"coordinates":[-1.947678,53.896294],"type":"Point"}
}