{
  "type": "Feature",
  "properties": {
    "addr:full":"5 The Street, Surlingham Norwich Norfolk NR14 7AJ",
    "addr:housenumber":"5",
    "addr:postcode":"nr14 7aj",
    "addr:street":"The Street;Norwich",
    "iso:country":"GB",
    "sg:address":"5 The Street, Surlingham",
    "sg:city":"Norwich",
    "sg:classifiers":[
        {
            "category":"Social Services",
            "subcategory":"Job Training",
            "type":"Services"
        }
    ],
    "sg:postcode":"NR14 7AJ",
    "sg:province":"Norfolk",
    "sg:tags":[
        "translator",
        "interpreter"
    ],
    "wof:name":"Gerlinde King",
    "wof:placetype":"venue"
},
  "geometry": {"coordinates":[1.3415349722,52.5755996704],"type":"Point"}
}