{
  "type": "Feature",
  "properties": {
    "addr:full":"Rothesay Court, Furnace Rd, Longton Stoke On Trent Staffordshire ST3 4LY",
    "addr:postcode":"st3 4ly",
    "addr:street":"Rothesay Court Furnace Rd",
    "iso:country":"GB",
    "sg:address":"Rothesay Court, Furnace Rd, Longton",
    "sg:city":"Stoke On Trent",
    "sg:classifiers":[
        {
            "category":"Health Services",
            "subcategory":"Nursing And Care Facility",
            "type":"Services"
        }
    ],
    "sg:phone":"+44 1782 314348",
    "sg:postcode":"ST3 4LY",
    "sg:province":"Staffordshire",
    "sg:tags":[
        "home"
    ],
    "wof:name":"The Beth Johnson Housing Group",
    "wof:placetype":"venue"
},
  "geometry": {"coordinates":[-2.122304,52.97963],"type":"Point"}
}