{
  "type": "Feature",
  "properties": {
    "iso:country":"GB",
    "sg:address":"County Hall, Colliton Park",
    "sg:city":"Dorchester",
    "sg:classifiers":[
        {
            "category":"Professional",
            "subcategory":"Computer Services",
            "type":"Services"
        }
    ],
    "sg:phone":"+44 1305 224936",
    "sg:postcode":"DT1 1XJ",
    "sg:province":"Dorset",
    "sg:tags":[
        "information"
    ],
    "wof:name":"Homesearch",
    "wof:placetype":"venue"
},
  "geometry": {"coordinates":[-2.441564,50.711906],"type":"Point"}
}