{
  "type": "Feature",
  "properties": {
    "addr:full":"16 Angle Terrace Wallsend Tyne and Wear NE28 7BQ",
    "addr:housenumber":"16",
    "addr:postcode":"ne28 7bq",
    "addr:street":"Angle Terrace",
    "iso:country":"GB",
    "sg:address":"16 Angle Terrace",
    "sg:city":"Wallsend",
    "sg:classifiers":[
        {
            "category":"Shopping",
            "subcategory":"News",
            "type":"Retail Goods"
        }
    ],
    "sg:phone":"+44 191 263 1750",
    "sg:postcode":"NE28 7BQ",
    "sg:province":"Tyne and Wear",
    "sg:tags":[
        "newsagent"
    ],
    "wof:name":"DIANE'S NEWSAGENCY",
    "wof:placetype":"venue"
},
  "geometry": {"coordinates":[-1.508496,54.996735],"type":"Point"}
}