{
  "type": "Feature",
  "properties": {
    "addr:full":"195 Portland Rd Seven Sisters Greater London N15 4SZ",
    "addr:housenumber":"195",
    "addr:postcode":"n15 4sz",
    "addr:street":"Portland Rd",
    "iso:country":"GB",
    "sg:address":"195 Portland Rd",
    "sg:city":"Seven Sisters",
    "sg:classifiers":[
        {
            "category":"Building & Trades",
            "subcategory":"Construction",
            "type":"Services"
        }
    ],
    "sg:phone":"+44 20 8800 4070",
    "sg:postcode":"N15 4SZ",
    "sg:province":"Greater London",
    "sg:tags":[
        "builder"
    ],
    "wof:name":"H B C Services",
    "wof:placetype":"venue"
},
  "geometry": {"coordinates":[-0.074364,51.585049],"type":"Point"}
}