{
  "type": "Feature",
  "properties": {
    "addr:full":"520 Church Road, Yardley Birmingham West Midlands B33 8HT",
    "addr:housenumber":"520",
    "addr:postcode":"b33 8ht",
    "addr:street":"Church Road",
    "iso:country":"GB",
    "sg:address":"520 Church Road, Yardley",
    "sg:city":"Birmingham",
    "sg:classifiers":[
        {
            "category":"Home & Garden",
            "subcategory":"Building Materials",
            "type":"Retail Goods"
        }
    ],
    "sg:phone":"+44 121 783 2242",
    "sg:postcode":"B33 8HT",
    "sg:province":"West Midlands",
    "sg:tags":[
        "insulation",
        "installers"
    ],
    "wof:name":"E & T Insulation",
    "wof:placetype":"venue"
},
  "geometry": {"coordinates":[-1.801644,52.476883],"type":"Point"}
}