{
  "type": "Feature",
  "properties": {
    "iso:country":"GB",
    "sg:address":"182 Market Street",
    "sg:city":"Aberdeen",
    "sg:classifiers":[
        {
            "category":"Real Estate",
            "subcategory":"Surveying",
            "type":"Services"
        }
    ],
    "sg:phone":"+44 1224 212324",
    "sg:postcode":"AB11 5PQ",
    "sg:province":"Aberdeen City",
    "sg:tags":[
        "surveyor",
        "land",
        "valuer"
    ],
    "wof:name":"N B Surveys Ltd.",
    "wof:placetype":"venue"
},
  "geometry": {"coordinates":[-2.092551,57.14257],"type":"Point"}
}