{
  "type": "Feature",
  "properties": {
    "iso:country":"GB",
    "sg:address":"200 Bellingham Road",
    "sg:city":"London",
    "sg:classifiers":[
        {
            "category":"Building & Trades",
            "subcategory":"Construction",
            "type":"Services"
        }
    ],
    "sg:phone":"+44 20 8461 3527",
    "sg:postcode":"SE6 1EJ",
    "sg:province":"Greater London",
    "sg:tags":[
        "builder"
    ],
    "wof:name":"Malcolm Tyler",
    "wof:placetype":"venue"
},
  "geometry": {"coordinates":[-0.0062529999,51.4355010986],"type":"Point"}
}