{
  "type": "Feature",
  "properties": {
    "addr:full":"High Street, St Margarets At Cliffe Dover Kent CT15 6AU",
    "addr:postcode":"ct15 6au",
    "addr:street":"High Street",
    "iso:country":"GB",
    "sg:address":"High Street, St Margarets At Cliffe",
    "sg:city":"Dover",
    "sg:classifiers":[
        {
            "category":"Bars & Pubs",
            "type":"Food & Drink"
        }
    ],
    "sg:phone":"+44 1304 853404",
    "sg:postcode":"CT15 6AU",
    "sg:province":"Kent",
    "sg:tags":[
        "pubs",
        "inn"
    ],
    "wof:name":"Peter Killin",
    "wof:placetype":"venue"
},
  "geometry": {"coordinates":[1.3703049421,51.1550750732],"type":"Point"}
}