{
  "type": "Feature",
  "properties": {
    "addr:full":"150 Curtain Rd Moorgate Greater London EC2A 3AR",
    "addr:housenumber":"150",
    "addr:postcode":"ec2a 3ar",
    "addr:street":"Curtain Rd",
    "iso:country":"GB",
    "sg:address":"150 Curtain Rd",
    "sg:city":"Moorgate",
    "sg:classifiers":[
        {
            "category":"Professional",
            "subcategory":"Printing & Photocopies",
            "type":"Services"
        }
    ],
    "sg:phone":"+44 20 7729 0243",
    "sg:postcode":"EC2A 3AR",
    "sg:province":"Greater London",
    "sg:tags":[
        "printer"
    ],
    "wof:name":"Call Print",
    "wof:placetype":"venue"
},
  "geometry": {"coordinates":[-0.080211997,51.52684021],"type":"Point"}
}