{
  "type": "Feature",
  "properties": {
    "addr:full":"Mill, 6 Mabgate Mills, Mabgate Leeds West Yorkshire LS9 7DZ",
    "addr:housenumber":"6",
    "addr:postcode":"ls9 7dz",
    "addr:street":"Mabgate Mills Mabgate Leeds West",
    "iso:country":"GB",
    "sg:address":"Mill, 6 Mabgate Mills, Mabgate",
    "sg:city":"Leeds",
    "sg:classifiers":[
        {
            "category":"Professional",
            "subcategory":"Art Services",
            "type":"Services"
        }
    ],
    "sg:phone":"+44 113 244 0900",
    "sg:postcode":"LS9 7DZ",
    "sg:province":"West Yorkshire",
    "sg:tags":[
        "photographer"
    ],
    "wof:name":"Douglas Unwin Advertising Photography",
    "wof:placetype":"venue"
},
  "geometry": {"coordinates":[-1.5307199955,53.8019714355],"type":"Point"}
}