{
  "type": "Feature",
  "properties": {
    "addr:full":"10 Church Road, Waterloo Liverpool Merseyside L22 5NB",
    "addr:housenumber":"10",
    "addr:postcode":"l22 5nb",
    "addr:street":"Church Road",
    "iso:country":"GB",
    "sg:address":"10 Church Road, Waterloo",
    "sg:city":"Liverpool",
    "sg:classifiers":[
        {
            "category":"Health Services",
            "subcategory":"Nursing And Care Facility",
            "type":"Services"
        },
        {
            "category":"Organizations",
            "subcategory":"Community Association",
            "type":"Services"
        }
    ],
    "sg:phone":"+44 151 920 7300",
    "sg:postcode":"L22 5NB",
    "sg:province":"Merseyside",
    "sg:tags":[
        "co-operatives",
        "society",
        "housing",
        "trust",
        "home"
    ],
    "wof:name":"Crosby Housing Association",
    "wof:placetype":"venue"
},
  "geometry": {"coordinates":[-3.0261740685,53.473941803],"type":"Point"}
}