{
  "type": "Feature",
  "properties": {
    "addr:full":"Trinity Farm Wellington Devon TA21 8BG",
    "addr:housenumber":"wellington",
    "addr:postcode":"ta21 8bg",
    "iso:country":"GB",
    "sg:address":"Trinity Farm",
    "sg:city":"Wellington",
    "sg:classifiers":[
        {
            "category":"Farming",
            "subcategory":"Livestock Farm",
            "type":"Manufacturing & Wholesale Goods"
        }
    ],
    "sg:phone":"+44 1823 662035",
    "sg:postcode":"TA21 8BG",
    "sg:province":"Devon",
    "sg:tags":[
        "breeder"
    ],
    "wof:name":"Linda Jean Hoare",
    "wof:placetype":"venue"
},
  "geometry": {"coordinates":[-3.226639,50.979271],"type":"Point"}
}