{
  "type": "Feature",
  "properties": {
    "iso:country":"GB",
    "sg:address":"Montagu Road",
    "sg:city":"London",
    "sg:classifiers":[
        {
            "category":"Bars & Pubs",
            "type":"Food & Drink"
        },
        {
            "category":"Community Center",
            "subcategory":"Social",
            "type":"Public Place"
        }
    ],
    "sg:phone":"+44 20 8803 7658",
    "sg:postcode":"N9 0ER",
    "sg:province":"Greater London",
    "sg:tags":[
        "pubs",
        "house",
        "inn",
        "activity"
    ],
    "wof:name":"The Cart Overthrown",
    "wof:placetype":"venue"
},
  "geometry": {"coordinates":[-0.046484,51.625633],"type":"Point"}
}