{
  "type": "Feature",
  "properties": {
    "iso:country":"GB",
    "sg:address":"2 Abbey Cres",
    "sg:city":"Torquay",
    "sg:classifiers":[
        {
            "category":"Cafe",
            "type":"Food & Drink"
        }
    ],
    "sg:phone":"+44 1803 293093",
    "sg:postcode":"TQ2 5HB",
    "sg:province":"Devon",
    "sg:tags":[
        "tea",
        "room"
    ],
    "wof:name":"Sea Bank",
    "wof:placetype":"venue"
},
  "geometry": {"coordinates":[-3.527459,50.465069],"type":"Point"}
}