{
  "type": "Feature",
  "properties": {
    "addr:full":"V G House, Park Street Stalybridge Greater Manchester SK15 2BT",
    "addr:postcode":"sk15 2bt",
    "addr:street":"V;Park Street",
    "iso:country":"GB",
    "sg:address":"V G House, Park Street",
    "sg:city":"Stalybridge",
    "sg:classifiers":[
        {
            "category":"Professional",
            "subcategory":"Engineering",
            "type":"Services"
        }
    ],
    "sg:phone":"+44 161 304 8488",
    "sg:postcode":"SK15 2BT",
    "sg:province":"Greater Manchester",
    "sg:tags":[
        "precision",
        "engineer"
    ],
    "wof:name":"Crossland Precision Tools",
    "wof:placetype":"venue"
},
  "geometry": {"coordinates":[-2.053168,53.4813],"type":"Point"}
}