{
  "type": "Feature",
  "properties": {
    "addr:full":"318 Romford Road, Forest Gate London Greater London E7 8BD",
    "addr:housenumber":"318",
    "addr:postcode":"e7 8bd",
    "addr:street":"Romford Road",
    "iso:country":"GB",
    "sg:address":"318 Romford Road, Forest Gate",
    "sg:city":"London",
    "sg:classifiers":[
        {
            "category":"Real Estate",
            "subcategory":"Real Estate Operator",
            "type":"Services"
        }
    ],
    "sg:phone":"+44 20 8519 9915",
    "sg:postcode":"E7 8BD",
    "sg:province":"Greater London",
    "sg:tags":[
        "letting",
        "agent"
    ],
    "wof:name":"Advance Lettings",
    "wof:placetype":"venue"
},
  "geometry": {"coordinates":[0.026789,51.546436],"type":"Point"}
}