{
  "type": "Feature",
  "properties": {
    "addr:full":"Suite C1 Ground Floor Cecil Cour, T London Road Enfield Greater London EN2 6DN",
    "addr:housenumber":"ground floor",
    "addr:postcode":"en2 6dn",
    "addr:street":"Cecil Cour T London Road",
    "iso:country":"GB",
    "sg:address":"Suite C1 Ground Floor Cecil Cour, T London Road",
    "sg:city":"Enfield",
    "sg:classifiers":[
        {
            "category":"Wholesale",
            "subcategory":"Books, Periodicals, & Newspapers",
            "type":"Manufacturing & Wholesale Goods"
        }
    ],
    "sg:phone":"+44 20 8367 1296",
    "sg:postcode":"EN2 6DN",
    "sg:province":"Greater London",
    "sg:tags":[
        "publishing"
    ],
    "wof:name":"Bloomsbury House Ltd.",
    "wof:placetype":"venue"
},
  "geometry": {"coordinates":[-0.0876490027,51.6531066895],"type":"Point"}
}