{
  "type": "Feature",
  "properties": {
    "addr:full":"Silverwood, Dalmurinzi Road, Bieldside Aberdeen Aberdeen City AB15 9EB",
    "addr:postcode":"ab15 9eb",
    "addr:street":"Road",
    "iso:country":"GB",
    "sg:address":"Silverwood, Dalmurinzi Road, Bieldside",
    "sg:city":"Aberdeen",
    "sg:classifiers":[
        {
            "category":"Professional",
            "subcategory":"Employment Agencies",
            "type":"Services"
        }
    ],
    "sg:phone":"+44 1224 825835",
    "sg:postcode":"AB15 9EB",
    "sg:province":"Aberdeen City",
    "sg:tags":[
        "factoring"
    ],
    "wof:name":"The Property Management Co. (Aberdeen) Ltd.",
    "wof:placetype":"venue"
},
  "geometry": {"coordinates":[-2.1978039742,57.1125411987],"type":"Point"}
}