{
  "type": "Feature",
  "properties": {
    "addr:full":"St Georges Way Peckham Greater London SE15 6PU",
    "addr:postcode":"se15 6pu",
    "addr:street":"St Georges Way",
    "iso:country":"GB",
    "sg:address":"St Georges Way",
    "sg:city":"Peckham",
    "sg:classifiers":[
        {
            "category":"Community Center",
            "type":"Public Place"
        }
    ],
    "sg:phone":"+44 20 7252 4514",
    "sg:postcode":"SE15 6PU",
    "sg:province":"Greater London",
    "sg:tags":[
        "centre"
    ],
    "wof:name":"Gloucester Grove Community Centre Association",
    "wof:placetype":"venue"
},
  "geometry": {"coordinates":[-0.07487,51.482124],"type":"Point"}
}