{
  "type": "Feature",
  "properties": {
    "addr:full":"136 Easter Road Edinburgh City of Edinburgh EH7 5RJ",
    "addr:housenumber":"136",
    "addr:postcode":"eh7 5rj",
    "addr:street":"Easter Road",
    "iso:country":"GB",
    "sg:address":"136 Easter Road",
    "sg:city":"Edinburgh",
    "sg:classifiers":[
        {
            "category":"Personal",
            "subcategory":"Barber",
            "type":"Services"
        }
    ],
    "sg:phone":"+44 131 478 7005",
    "sg:postcode":"EH7 5RJ",
    "sg:province":"City of Edinburgh",
    "sg:tags":[
        "men's",
        "hairdresser"
    ],
    "wof:name":"Barber",
    "wof:placetype":"venue"
},
  "geometry": {"coordinates":[-3.171336,55.959911],"type":"Point"}
}