{
  "type": "Feature",
  "properties": {
    "addr:full":"88-90 Kirk Brae Edinburgh City of Edinburgh EH16 6JA",
    "addr:housenumber":"88-90",
    "addr:postcode":"eh16 6ja",
    "addr:street":"Kirk Brae",
    "iso:country":"GB",
    "sg:address":"88-90 Kirk Brae",
    "sg:city":"Edinburgh",
    "sg:classifiers":[
        {
            "category":"Bars & Pubs",
            "type":"Food & Drink"
        }
    ],
    "sg:phone":"+44 131 672 0901",
    "sg:postcode":"EH16 6JA",
    "sg:province":"City of Edinburgh",
    "sg:tags":[
        "pubs",
        "inn"
    ],
    "wof:name":"Liberton Inn",
    "wof:placetype":"venue"
},
  "geometry": {"coordinates":[-3.162039,55.914639],"type":"Point"}
}