{
  "type": "Feature",
  "properties": {
    "addr:full":"27a Peckham High Street London Greater London SE15 5EB",
    "addr:housenumber":"27a",
    "addr:postcode":"se15 5eb",
    "addr:street":"Peckham High Street",
    "iso:country":"GB",
    "sg:address":"27a Peckham High Street",
    "sg:city":"London",
    "sg:classifiers":[
        {
            "category":"Freight",
            "type":"Transportation"
        }
    ],
    "sg:phone":"+44 20 7701 6147",
    "sg:postcode":"SE15 5EB",
    "sg:province":"Greater London",
    "sg:tags":[
        "forwarders"
    ],
    "wof:name":"Sulima",
    "wof:placetype":"venue"
},
  "geometry": {"coordinates":[-0.071886,51.473618],"type":"Point"}
}