{
  "type": "Feature",
  "properties": {
    "addr:full":"1 Library Road Ferndown Dorset BH22 9JP",
    "addr:housenumber":"1",
    "addr:postcode":"bh22 9jp",
    "addr:street":"Library Road",
    "iso:country":"GB",
    "sg:address":"1 Library Road",
    "sg:city":"Ferndown",
    "sg:classifiers":[
        {
            "category":"Manufacturing",
            "subcategory":"Building Materials",
            "type":"Manufacturing & Wholesale Goods"
        }
    ],
    "sg:phone":"+44 1202 855999",
    "sg:postcode":"BH22 9JP",
    "sg:province":"Dorset",
    "sg:tags":[
        "shutter",
        "supp",
        "door"
    ],
    "wof:name":"Fix A Door Ltd.",
    "wof:placetype":"venue"
},
  "geometry": {"coordinates":[-1.8918060064,50.8034324646],"type":"Point"}
}