{
  "type": "Feature",
  "properties": {
    "iso:country":"GB",
    "sg:address":"52 Lord Street",
    "sg:city":"Manchester",
    "sg:classifiers":[
        {
            "category":"Manufacturing",
            "subcategory":"Textiles",
            "type":"Manufacturing & Wholesale Goods"
        }
    ],
    "sg:phone":"+44 161 834 3340",
    "sg:postcode":"M3 1HN",
    "sg:province":"Greater Manchester",
    "sg:tags":[
        "merchant",
        "agent"
    ],
    "wof:name":"Rubitex",
    "wof:placetype":"venue"
},
  "geometry": {"coordinates":[-2.2426230907,53.4921913147],"type":"Point"}
}