{
  "type": "Feature",
  "properties": {
    "iso:country":"GB",
    "sg:address":"264 Addington Road, Irthlingborough",
    "sg:city":"Wellingborough",
    "sg:classifiers":[
        {
            "category":"Shopping",
            "subcategory":"News",
            "type":"Retail Goods"
        },
        {
            "category":"Food & Beverages",
            "subcategory":"Supermarket",
            "type":"Retail Goods"
        }
    ],
    "sg:phone":"+44 1933 651693",
    "sg:postcode":"NN9 5UT",
    "sg:province":"Northamptonshire",
    "sg:tags":[
        "newsagent"
    ],
    "wof:name":"Addington Road Post Office",
    "wof:placetype":"venue"
},
  "geometry": {"coordinates":[-0.6010389924,52.3372306824],"type":"Point"}
}