{
  "type": "Feature",
  "properties": {
    "addr:full":"College Farm, North End, Meldreth Royston Bedfordshire SG8 6NT",
    "addr:postcode":"sg8 6nt",
    "iso:country":"GB",
    "sg:address":"College Farm, North End, Meldreth",
    "sg:city":"Royston",
    "sg:classifiers":[
        {
            "category":"Shopping",
            "type":"Retail Goods"
        }
    ],
    "sg:phone":"+44 1763 262649",
    "sg:postcode":"SG8 6NT",
    "sg:province":"Bedfordshire",
    "sg:tags":[
        "equipment",
        "clothing",
        "safety"
    ],
    "wof:name":"Sure-Safe Ltd.",
    "wof:placetype":"venue"
},
  "geometry": {"coordinates":[0.006943,52.1006584167],"type":"Point"}
}