{
  "type": "Feature",
  "properties": {
    "addr:full":"129-135 Breck Road, Anfield Liverpool Merseyside L4 2QZ",
    "addr:housenumber":"129-135",
    "addr:postcode":"l4 2qz",
    "addr:street":"Breck Road Anfield",
    "iso:country":"GB",
    "sg:address":"129-135 Breck Road, Anfield",
    "sg:city":"Liverpool",
    "sg:classifiers":[
        {
            "category":"Home & Garden",
            "subcategory":"Home Furnishings",
            "type":"Retail Goods"
        },
        {
            "category":"Building & Trades",
            "subcategory":"Construction",
            "type":"Services"
        }
    ],
    "sg:phone":"+44 151 263 0660",
    "sg:postcode":"L4 2QZ",
    "sg:province":"Merseyside",
    "sg:tags":[
        "mantelpiece",
        "fireplace"
    ],
    "wof:name":"Quality Fireplaces",
    "wof:placetype":"venue"
},
  "geometry": {"coordinates":[-2.953481,53.425137],"type":"Point"}
}