{
  "type": "Feature",
  "properties": {
    "addr:full":"8 The Lanes Shopping Centre, Birmingham Road Sutton Coldfield West Midlands B72 1YG",
    "addr:housenumber":"8",
    "addr:postcode":"b72 1yg",
    "addr:street":"The Lanes Shopping Centre Birmingham Road",
    "iso:country":"GB",
    "sg:address":"8 The Lanes Shopping Centre, Birmingham Road",
    "sg:city":"Sutton Coldfield",
    "sg:classifiers":[
        {
            "category":"Shopping",
            "subcategory":"Optician",
            "type":"Retail Goods"
        }
    ],
    "sg:phone":"+44 121 350 5872",
    "sg:postcode":"B72 1YG",
    "sg:province":"West Midlands",
    "wof:name":"Lad & Turner Optical Practice",
    "wof:placetype":"venue"
},
  "geometry": {"coordinates":[-1.82757,52.537251],"type":"Point"}
}