{
  "type": "Feature",
  "properties": {
    "iso:country":"GB",
    "sg:address":"329 Ashley Road",
    "sg:city":"Poole",
    "sg:classifiers":[
        {
            "category":"Personal",
            "subcategory":"Beauty Salon",
            "type":"Services"
        }
    ],
    "sg:postcode":"BH14 0AP",
    "sg:province":"Dorset",
    "sg:tags":[
        "unisex",
        "hairdresser"
    ],
    "wof:name":"Hollywood Hair Design",
    "wof:placetype":"venue"
},
  "geometry": {"coordinates":[-1.9399859905,50.7287368774],"type":"Point"}
}