{
  "type": "Feature",
  "properties": {
    "addr:full":"67 Woodhedge Drive Nottingham Nottinghamshire NG3 6LW",
    "addr:housenumber":"67",
    "addr:postcode":"ng3 6lw",
    "addr:street":"Woodhedge Drive",
    "iso:country":"GB",
    "sg:address":"67 Woodhedge Drive",
    "sg:city":"Nottingham",
    "sg:classifiers":[
        {
            "category":"Building & Trades",
            "subcategory":"Plumbing",
            "type":"Services"
        }
    ],
    "sg:postcode":"NG3 6LW",
    "sg:province":"Nottinghamshire",
    "sg:tags":[
        "heating"
    ],
    "wof:name":"Williams Edward Plumbing & Heating Engineer",
    "wof:placetype":"venue"
},
  "geometry": {"coordinates":[-1.121241,52.971127],"type":"Point"}
}