{
  "type": "Feature",
  "properties": {
    "iso:country":"GB",
    "sg:address":"Agriculture House, 14 Prickwillow Road",
    "sg:city":"Ely",
    "sg:classifiers":[
        {
            "category":"Insurance",
            "subcategory":"Insurance Agent",
            "type":"Services"
        }
    ],
    "sg:phone":"+44 1353 662454",
    "sg:postcode":"CB7 4NS",
    "sg:province":"Cambridgeshire",
    "wof:name":"National Farmers Union",
    "wof:placetype":"venue"
},
  "geometry": {"coordinates":[0.2694140077,52.4012832642],"type":"Point"}
}