{
  "type": "Feature",
  "properties": {
    "iso:country":"GB",
    "sg:address":"33 College St",
    "sg:city":"Ammanford",
    "sg:classifiers":[
        {
            "category":"Social Services",
            "type":"Services"
        }
    ],
    "sg:phone":"+44 1269 596883",
    "sg:postcode":"SA18 3AB",
    "sg:province":"Carmarthenshire",
    "wof:name":"Dinefwr Childcare Team",
    "wof:placetype":"venue"
},
  "geometry": {"coordinates":[-3.989953,51.794289],"type":"Point"}
}