{
  "type": "Feature",
  "properties": {
    "addr:full":"Po Box 39 Stockton-on-tees Durham TS18 2DB",
    "addr:housenumber":"po box 39",
    "addr:postcode":"ts18 2db",
    "iso:country":"GB",
    "sg:address":"Po Box 39",
    "sg:city":"Stockton-on-tees",
    "sg:classifiers":[
        {
            "category":"Professional",
            "subcategory":"Business Services",
            "type":"Services"
        }
    ],
    "sg:phone":"+44 1642 613161",
    "sg:postcode":"TS18 2DB",
    "sg:province":"Durham",
    "sg:tags":[
        "distribution"
    ],
    "wof:name":"A H E D Ltd.",
    "wof:placetype":"venue"
},
  "geometry": {"coordinates":[-1.274499,54.573956],"type":"Point"}
}