{
  "type": "Feature",
  "properties": {
    "addr:full":"183 Cowick Street Exeter Devon EX4 1AA",
    "addr:housenumber":"183",
    "addr:postcode":"ex4 1aa",
    "addr:street":"Cowick Street",
    "iso:country":"GB",
    "sg:address":"183 Cowick Street",
    "sg:city":"Exeter",
    "sg:classifiers":[
        {
            "category":"Personal",
            "subcategory":"Beauty Salon",
            "type":"Services"
        }
    ],
    "sg:phone":"+44 1392 279941",
    "sg:postcode":"EX4 1AA",
    "sg:province":"Devon",
    "sg:tags":[
        "unisex",
        "hairdresser"
    ],
    "wof:name":"Nutters",
    "wof:placetype":"venue"
},
  "geometry": {"coordinates":[-3.538271,50.718044],"type":"Point"}
}