{
  "type": "Feature",
  "properties": {
    "addr:full":"Riverside Farm, Thorney Langport Somerset TA10 0DR",
    "addr:housenumber":"thorney langport",
    "addr:postcode":"ta10 0dr",
    "iso:country":"GB",
    "sg:address":"Riverside Farm, Thorney",
    "sg:city":"Langport",
    "sg:classifiers":[
        {
            "category":"Communications",
            "subcategory":"Newspaper",
            "type":"Services"
        }
    ],
    "sg:phone":"+44 1458 253536",
    "sg:postcode":"TA10 0DR",
    "sg:province":"Somerset",
    "sg:tags":[
        "magazine"
    ],
    "wof:name":"Business Money Ltd.",
    "wof:placetype":"venue"
},
  "geometry": {"coordinates":[-2.8181209564,51.0016593933],"type":"Point"}
}