{
  "type": "Feature",
  "properties": {
    "addr:full":"11d Carcroft Enterprise Park, Carcroft Doncaster North Yorkshire DN6 8DD",
    "addr:housenumber":"11d",
    "addr:postcode":"dn6 8dd",
    "addr:street":"Carcroft Enterprise Park",
    "iso:country":"GB",
    "sg:address":"11d Carcroft Enterprise Park, Carcroft",
    "sg:city":"Doncaster",
    "sg:classifiers":[
        {
            "category":"Manufacturing",
            "subcategory":"Tools & Machinery",
            "type":"Manufacturing & Wholesale Goods"
        },
        {
            "category":"Government",
            "subcategory":"Post Office",
            "type":"Public Place"
        },
        {
            "category":"Military Area",
            "subcategory":"Air Force Base",
            "type":"Public Place"
        }
    ],
    "sg:phone":"+44 1302 722215",
    "sg:postcode":"DN6 8DD",
    "sg:province":"North Yorkshire",
    "sg:tags":[
        "manufacture",
        "powertools",
        "cutting",
        "laser",
        "supply"
    ],
    "wof:name":"DONCASTER LASER LOGISTICS LTD",
    "wof:placetype":"venue"
},
  "geometry": {"coordinates":[-1.1778080463,53.5803909302],"type":"Point"}
}