{
  "type": "Feature",
  "properties": {
    "addr:full":"Care Of Homebase, Kingsway Derby Derbyshire DE3 3NF",
    "addr:postcode":"de3 3nf",
    "addr:street":"Kingsway",
    "iso:country":"GB",
    "sg:address":"Care Of Homebase, Kingsway",
    "sg:city":"Derby",
    "sg:classifiers":[
        {
            "category":"Home & Garden",
            "subcategory":"Furniture",
            "type":"Retail Goods"
        }
    ],
    "sg:phone":"+44 1332 291260",
    "sg:postcode":"DE3 3NF",
    "sg:province":"Derbyshire",
    "wof:name":"Laura Ashley",
    "wof:placetype":"venue"
},
  "geometry": {"coordinates":[-1.5145699978,52.9308013916],"type":"Point"}
}