{
  "type": "Feature",
  "properties": {
    "iso:country":"GB",
    "sg:address":"Jorvik House, Outgang Lane, Osbaldwick",
    "sg:city":"York",
    "sg:classifiers":[
        {
            "category":"Utilities",
            "subcategory":"Telephone",
            "type":"Services"
        }
    ],
    "sg:phone":"+44 1904 438438",
    "sg:postcode":"YO19 5UP",
    "sg:province":"North Yorkshire",
    "sg:tags":[
        "telecommunication"
    ],
    "wof:name":"B S C Filters Ltd.",
    "wof:placetype":"venue"
},
  "geometry": {"coordinates":[-1.028754,53.961933],"type":"Point"}
}