{
  "type": "Feature",
  "properties": {
    "addr:full":"12 Pump Clo Northolt Greater London UB5 6UG",
    "addr:housenumber":"12",
    "addr:postcode":"ub5 6ug",
    "addr:street":"Pump Clo",
    "iso:country":"GB",
    "sg:address":"12 Pump Clo",
    "sg:city":"Northolt",
    "sg:classifiers":[
        {
            "category":"Bus Charters",
            "type":"Transportation"
        }
    ],
    "sg:phone":"+44 20 8841 5898",
    "sg:postcode":"UB5 6UG",
    "sg:province":"Greater London",
    "sg:tags":[
        "mini",
        "hire",
        "leasing"
    ],
    "wof:name":"A Mint Minicoaches",
    "wof:placetype":"venue"
},
  "geometry": {"coordinates":[-0.3680799901,51.5364723206],"type":"Point"}
}