{
  "type": "Feature",
  "properties": {
    "addr:full":"59 Westbourne Gro, Bayswater London Greater London W2 4UA",
    "addr:housenumber":"59",
    "addr:postcode":"w2 4ua",
    "addr:street":"Westbourne Gro",
    "iso:country":"GB",
    "sg:address":"59 Westbourne Gro, Bayswater",
    "sg:city":"London",
    "sg:classifiers":[
        {
            "category":"Professional",
            "subcategory":"Computer Services",
            "type":"Services"
        }
    ],
    "sg:phone":"+44 20 7727 5892",
    "sg:postcode":"W2 4UA",
    "sg:province":"Greater London",
    "sg:tags":[
        "system",
        "software"
    ],
    "wof:name":"Wama Computer Services Ltd.",
    "wof:placetype":"venue"
},
  "geometry": {"coordinates":[-0.19088,51.5154],"type":"Point"}
}