{
  "type": "Feature",
  "properties": {
    "iso:country":"GB",
    "sg:address":"24 Richmond Drive",
    "sg:city":"Nottingham",
    "sg:classifiers":[
        {
            "category":"Health Services",
            "subcategory":"Doctor",
            "type":"Services"
        }
    ],
    "sg:phone":"+44 115 962 1043",
    "sg:postcode":"NG3 5EL",
    "sg:province":"Nottinghamshire",
    "sg:tags":[
        "practitioners"
    ],
    "wof:name":"R.J Lemberger F.R.C.S",
    "wof:placetype":"venue"
},
  "geometry": {"coordinates":[-1.1410039663,52.9776344299],"type":"Point"}
}