{
  "type": "Feature",
  "properties": {
    "iso:country":"GB",
    "sg:address":"Dyffryn Trading Estate",
    "sg:city":"Denbigh",
    "sg:classifiers":[
        {
            "category":"Autos & Motor Vehicles",
            "subcategory":"Automobile Sales",
            "type":"Retail Goods"
        }
    ],
    "sg:phone":"+44 1745 812307",
    "sg:postcode":"LL16 5SU",
    "sg:province":"Conwy",
    "sg:tags":[
        "commercial"
    ],
    "wof:name":"L J Watkins (North Wales) Ltd.",
    "wof:placetype":"venue"
},
  "geometry": {"coordinates":[-3.4211490154,53.1834106445],"type":"Point"}
}