{
  "type": "Feature",
  "properties": {
    "iso:country":"GB",
    "sg:address":"9 Forge Court",
    "sg:city":"Yateley",
    "sg:classifiers":[
        {
            "category":"Professional",
            "subcategory":"Computer Services",
            "type":"Services"
        }
    ],
    "sg:phone":"+44 1252 890633",
    "sg:postcode":"GU46 7RX",
    "sg:province":"Hampshire",
    "sg:tags":[
        "consultant"
    ],
    "wof:name":"Nexsys Consultants Ltd.",
    "wof:placetype":"venue"
},
  "geometry": {"coordinates":[-0.827109,51.342319],"type":"Point"}
}