{
  "type": "Feature",
  "properties": {
    "iso:country":"GB",
    "sg:address":"155 Chingford Road",
    "sg:city":"London",
    "sg:classifiers":[
        {
            "category":"Retail",
            "subcategory":"Auto Rental",
            "type":"Services"
        }
    ],
    "sg:phone":"+44 20 8527 6040",
    "sg:postcode":"E17 4PN",
    "sg:province":"Greater London",
    "sg:tags":[
        "car"
    ],
    "wof:name":"Mayes Self Drive",
    "wof:placetype":"venue"
},
  "geometry": {"coordinates":[-0.017719,51.593838],"type":"Point"}
}