{
  "type": "Feature",
  "properties": {
    "addr:full":"12 Cesson Close, Chipping Sodbury Bristol Gloucestershire BS37 6NJ",
    "addr:housenumber":"12",
    "addr:postcode":"bs37 6nj",
    "addr:street":"Cesson Close;Sodbury",
    "iso:country":"GB",
    "sg:address":"12 Cesson Close, Chipping Sodbury",
    "sg:city":"Bristol",
    "sg:classifiers":[
        {
            "category":"Utilities",
            "subcategory":"Natural Gas",
            "type":"Services"
        }
    ],
    "sg:phone":"+44 1454 858777",
    "sg:postcode":"BS37 6NJ",
    "sg:province":"Gloucestershire",
    "sg:tags":[
        "control",
        "energy",
        "management",
        "system"
    ],
    "wof:name":"Plumbtech",
    "wof:placetype":"venue"
},
  "geometry": {"coordinates":[-2.383995,51.535484],"type":"Point"}
}