{
  "type": "Feature",
  "properties": {
    "addr:full":"16 Velsheda Court, Hythe Marina Village Southampton Hampshire SO45 6DW",
    "addr:housenumber":"16",
    "addr:postcode":"so45 6dw",
    "addr:street":"Velsheda Court",
    "iso:country":"GB",
    "sg:address":"16 Velsheda Court, Hythe Marina Village",
    "sg:city":"Southampton",
    "sg:classifiers":[
        {
            "category":"Shopping",
            "subcategory":"Beauty & Cosmetics",
            "type":"Retail Goods"
        }
    ],
    "sg:postcode":"SO45 6DW",
    "sg:province":"Hampshire",
    "sg:tags":[
        "product"
    ],
    "wof:name":"Mary Kay Cosmetics",
    "wof:placetype":"venue"
},
  "geometry": {"coordinates":[-1.399304986,50.8739814758],"type":"Point"}
}