{
  "type": "Feature",
  "properties": {
    "iso:country":"GB",
    "sg:address":"Eynsford Cottage, Wotton Rd",
    "sg:city":"Bristol",
    "sg:classifiers":[
        {
            "category":"Building & Trades",
            "subcategory":"Landscaping Services",
            "type":"Services"
        }
    ],
    "sg:phone":"+44 1454 228247",
    "sg:postcode":"BS37 9UZ",
    "sg:province":"Gloucestershire",
    "sg:tags":[
        "forestry",
        "tree"
    ],
    "wof:name":"Chris Wright",
    "wof:placetype":"venue"
},
  "geometry": {"coordinates":[-2.4605100155,51.5495910645],"type":"Point"}
}