{
  "type": "Feature",
  "properties": {
    "iso:country":"GB",
    "sg:address":"26-28 Goodmays Road",
    "sg:city":"Ilford",
    "sg:classifiers":[
        {
            "category":"Manufacturing",
            "subcategory":"Petroleum Products",
            "type":"Manufacturing & Wholesale Goods"
        }
    ],
    "sg:postcode":"IG3 9UN",
    "sg:province":"Essex",
    "sg:tags":[
        "double",
        "glazing"
    ],
    "wof:name":"Crystal Windows & Doors Ltd.",
    "wof:placetype":"venue"
},
  "geometry": {"coordinates":[0.110275,51.566216],"type":"Point"}
}