{
  "type": "Feature",
  "properties": {
    "iso:country":"GB",
    "sg:address":"Colliery Rd",
    "sg:city":"Durham",
    "sg:classifiers":[
        {
            "category":"Autos & Motor Vehicles",
            "subcategory":"Automobile Sales",
            "type":"Retail Goods"
        }
    ],
    "sg:phone":"+44 191 375 0365",
    "sg:postcode":"DH7 7AU",
    "sg:province":"Durham",
    "sg:tags":[
        "car"
    ],
    "wof:name":"B & S Motor Co",
    "wof:placetype":"venue"
},
  "geometry": {"coordinates":[-1.628255,54.784973],"type":"Point"}
}