{
  "type": "Feature",
  "properties": {
    "iso:country":"GB",
    "sg:address":"21 Coleridge Road",
    "sg:city":"Oldham",
    "sg:classifiers":[
        {
            "category":"Health Services",
            "subcategory":"Health Practitioner",
            "type":"Services"
        }
    ],
    "sg:phone":"+44 7813 815697",
    "sg:postcode":"OL1 4RH",
    "sg:province":"Lancashire",
    "sg:tags":[
        "hypnotherapists"
    ],
    "wof:name":"ALAN SMITH",
    "wof:placetype":"venue"
},
  "geometry": {"coordinates":[-2.076751,53.567242],"type":"Point"}
}