{
  "type": "Feature",
  "properties": {
    "addr:full":"22 Main Avenue, Morepark Northwood Greater London HA6 2HJ",
    "addr:housenumber":"22",
    "addr:postcode":"ha6 2hj",
    "addr:street":"Main Avenue Morepark",
    "iso:country":"GB",
    "sg:address":"22 Main Avenue, Morepark",
    "sg:city":"Northwood",
    "sg:classifiers":[
        {
            "category":"Food & Beverages",
            "subcategory":"Supermarket",
            "type":"Retail Goods"
        }
    ],
    "sg:phone":"+44 1923 825312",
    "sg:postcode":"HA6 2HJ",
    "sg:province":"Greater London",
    "wof:name":"Moor Park Fine Food",
    "wof:placetype":"venue"
},
  "geometry": {"coordinates":[-0.434435,51.629509],"type":"Point"}
}