{
  "type": "Feature",
  "properties": {
    "iso:country":"GB",
    "sg:address":"27 St Michaels Hill",
    "sg:city":"Bristol",
    "sg:classifiers":[
        {
            "category":"Restaurant",
            "type":"Food & Drink"
        }
    ],
    "sg:postcode":"BS2 8DZ",
    "sg:province":"City of Bristol",
    "wof:name":"Anthem Restaurant",
    "wof:placetype":"venue"
},
  "geometry": {"coordinates":[-2.5986089706,51.4573898315],"type":"Point"}
}