{
  "type": "Feature",
  "properties": {
    "iso:country":"GB",
    "sg:address":"248 South Coast Road",
    "sg:city":"Peacehaven",
    "sg:classifiers":[
        {
            "category":"Manufacturing",
            "subcategory":"Petroleum Products",
            "type":"Manufacturing & Wholesale Goods"
        }
    ],
    "sg:phone":"+44 1273 580875",
    "sg:postcode":"BN10 7NP",
    "sg:province":"East Sussex",
    "sg:tags":[
        "double",
        "glazing"
    ],
    "wof:name":"N E Windows",
    "wof:placetype":"venue"
},
  "geometry": {"coordinates":[-0.003743,50.791988],"type":"Point"}
}