{
  "type": "Feature",
  "properties": {
    "addr:full":"39 Nicholas Avenue Sunderland Tyne and Wear SR6 7DG",
    "addr:housenumber":"39",
    "addr:postcode":"sr6 7dg",
    "addr:street":"Nicholas Avenue",
    "iso:country":"GB",
    "sg:address":"39 Nicholas Avenue",
    "sg:city":"Sunderland",
    "sg:classifiers":[
        {
            "category":"Real Estate",
            "subcategory":"Developer",
            "type":"Services"
        }
    ],
    "sg:phone":"+44 191 529 3658",
    "sg:postcode":"SR6 7DG",
    "sg:province":"Tyne and Wear",
    "sg:tags":[
        "property"
    ],
    "wof:name":"Ambridge Properties Ltd.",
    "wof:placetype":"venue"
},
  "geometry": {"coordinates":[-1.3630440235,54.9466209412],"type":"Point"}
}