{
  "type": "Feature",
  "properties": {
    "iso:country":"GB",
    "sg:address":"32 Reighton Avenue",
    "sg:city":"York",
    "sg:classifiers":[
        {
            "category":"Retail",
            "subcategory":"Auto Repair",
            "type":"Services"
        }
    ],
    "sg:postcode":"YO30 5QN",
    "sg:province":"North Yorkshire",
    "sg:tags":[
        "modification",
        "garage"
    ],
    "wof:name":"Jim Power",
    "wof:placetype":"venue"
},
  "geometry": {"coordinates":[-1.1027710438,53.97864151],"type":"Point"}
}