{
  "type": "Feature",
  "properties": {
    "iso:country":"GB",
    "sg:address":"Balmoral House, 51 Atherton Road, Hindley",
    "sg:city":"Wigan",
    "sg:classifiers":[
        {
            "category":"Health Services",
            "subcategory":"Dentist",
            "type":"Services"
        }
    ],
    "sg:phone":"+44 1942 258888",
    "sg:postcode":"WN2 3EA",
    "sg:province":"Lancashire",
    "wof:name":"P Mcgeary",
    "wof:placetype":"venue"
},
  "geometry": {"coordinates":[-2.578982,53.532555],"type":"Point"}
}