{
  "type": "Feature",
  "properties": {
    "addr:full":"397 Nuttall Road Nottingham Nottinghamshire NG8 5DB",
    "addr:housenumber":"397",
    "addr:postcode":"ng8 5db",
    "addr:street":"Nuttall Road",
    "iso:country":"GB",
    "sg:address":"397 Nuttall Road",
    "sg:city":"Nottingham",
    "sg:classifiers":[
        {
            "category":"Shopping",
            "subcategory":"Florist",
            "type":"Retail Goods"
        }
    ],
    "sg:phone":"+44 115 978 3110",
    "sg:postcode":"NG8 5DB",
    "sg:province":"Nottinghamshire",
    "wof:name":"Marianne",
    "wof:placetype":"venue"
},
  "geometry": {"coordinates":[-1.190144,52.976997],"type":"Point"}
}