{
  "type": "Feature",
  "properties": {
    "iso:country":"GB",
    "sg:address":"The Ridings",
    "sg:city":"Stevenage",
    "sg:classifiers":[
        {
            "category":"Education",
            "subcategory":"Preschool",
            "type":"Public Place"
        }
    ],
    "sg:phone":"+44 1438 353443",
    "sg:postcode":"SG2 9UA",
    "sg:province":"Hertfordshire",
    "sg:tags":[
        "pre-school",
        "playgroups"
    ],
    "wof:name":"Triangle Playgroup",
    "wof:placetype":"venue"
},
  "geometry": {"coordinates":[-0.175204,51.895424],"type":"Point"}
}