{
  "type": "Feature",
  "properties": {
    "addr:full":"38 London Rd Sittingbourne Kent ME10 1NJ",
    "addr:housenumber":"38",
    "addr:postcode":"me10 1nj",
    "addr:street":"London Rd",
    "iso:country":"GB",
    "sg:address":"38 London Rd",
    "sg:city":"Sittingbourne",
    "sg:classifiers":[
        {
            "category":"Restaurant",
            "type":"Food & Drink"
        }
    ],
    "sg:phone":"+44 1795 437096",
    "sg:postcode":"ME10 1NJ",
    "sg:province":"Kent",
    "sg:tags":[
        "thai"
    ],
    "wof:name":"Thai Garden Restaurant",
    "wof:placetype":"venue"
},
  "geometry": {"coordinates":[0.7239030004,51.3421478271],"type":"Point"}
}