{
  "type": "Feature",
  "properties": {
    "addr:full":"Hanson Clo Manchester Greater Manchester M24 2HD",
    "addr:postcode":"m24 2hd",
    "iso:country":"GB",
    "sg:address":"Hanson Clo",
    "sg:city":"Manchester",
    "sg:classifiers":[
        {
            "category":"Manufacturing",
            "subcategory":"Lumber",
            "type":"Manufacturing & Wholesale Goods"
        }
    ],
    "sg:phone":"+44 161 643 3973",
    "sg:postcode":"M24 2HD",
    "sg:province":"Greater Manchester",
    "sg:tags":[
        "importer",
        "merchants",
        "agent",
        "timber"
    ],
    "wof:name":"T J Guinan (Timber Merchants) Ltd",
    "wof:placetype":"venue"
},
  "geometry": {"coordinates":[-2.18946,53.551804],"type":"Point"}
}