{
  "type": "Feature",
  "properties": {
    "iso:country":"GB",
    "sg:address":"194 Cambridge Road",
    "sg:city":"Kingston-upon-thames",
    "sg:classifiers":[
        {
            "category":"Taxi",
            "type":"Transportation"
        }
    ],
    "sg:phone":"+44 20 8546 6843",
    "sg:postcode":"KT1 3LF",
    "sg:province":"Greater London",
    "sg:tags":[
        "mini",
        "cab"
    ],
    "wof:name":"Kingston Car Service",
    "wof:placetype":"venue"
},
  "geometry": {"coordinates":[-0.2842180133,51.4076042175],"type":"Point"}
}