{
  "type": "Feature",
  "properties": {
    "iso:country":"GB",
    "sg:address":"South Foreshore",
    "sg:city":"South Shields",
    "sg:classifiers":[
        {
            "category":"Bars & Pubs",
            "type":"Food & Drink"
        }
    ],
    "sg:phone":"+44 191 427 5504",
    "sg:postcode":"NE33 2JH",
    "sg:province":"Tyne and Wear",
    "sg:tags":[
        "pubs",
        "inn"
    ],
    "wof:name":"The Waters Edge",
    "wof:placetype":"venue"
},
  "geometry": {"coordinates":[-1.4305189848,54.9964637756],"type":"Point"}
}