{
  "type": "Feature",
  "properties": {
    "iso:country":"GB",
    "sg:address":"4 Old Blacksmiths Yd, Sadler Gate",
    "sg:city":"Derby",
    "sg:classifiers":[
        {
            "category":"Cafe",
            "type":"Food & Drink"
        }
    ],
    "sg:postcode":"DE1 3PD",
    "sg:province":"Derbyshire",
    "sg:tags":[
        "tea",
        "room"
    ],
    "wof:name":"Cafe Sol",
    "wof:placetype":"venue"
},
  "geometry": {"coordinates":[-1.483684,52.925171],"type":"Point"}
}