{
  "type": "Feature",
  "properties": {
    "iso:country":"GB",
    "sg:address":"1 Cleveland House, Hackford Rd, Oval",
    "sg:city":"Brixton",
    "sg:classifiers":[
        {
            "category":"Personal",
            "type":"Services"
        }
    ],
    "sg:phone":"+44 20 7582 3420",
    "sg:postcode":"SW9 0ET",
    "sg:province":"Greater London",
    "sg:tags":[
        "dressmaker"
    ],
    "wof:name":"Jeanne Laine",
    "wof:placetype":"venue"
},
  "geometry": {"coordinates":[-0.11445,51.477558],"type":"Point"}
}