{
  "type": "Feature",
  "properties": {
    "addr:full":"19 Front Street, Annfield Plain Stanley Durham DH9 7SY",
    "addr:housenumber":"19",
    "addr:postcode":"dh9 7sy",
    "addr:street":"Front Street;Plain",
    "iso:country":"GB",
    "sg:address":"19 Front Street, Annfield Plain",
    "sg:city":"Stanley",
    "sg:classifiers":[
        {
            "category":"Fast Food",
            "type":"Food & Drink"
        }
    ],
    "sg:phone":"+44 1207 239999",
    "sg:postcode":"DH9 7SY",
    "sg:province":"Durham",
    "sg:tags":[
        "away",
        "take"
    ],
    "wof:name":"Osmany Curry Out",
    "wof:placetype":"venue"
},
  "geometry": {"coordinates":[-1.690338,54.872379],"type":"Point"}
}