{
  "type": "Feature",
  "properties": {
    "addr:full":"Alms House, Thorpeness Leiston Suffolk IP16 4LY",
    "addr:postcode":"ip16 4ly",
    "addr:street":"Thorpeness",
    "iso:country":"GB",
    "sg:address":"Alms House, Thorpeness",
    "sg:city":"Leiston",
    "sg:classifiers":[
        {
            "category":"Organizations",
            "subcategory":"Community Association",
            "type":"Services"
        }
    ],
    "sg:phone":"+44 1728 452107",
    "sg:postcode":"IP16 4LY",
    "sg:province":"Suffolk",
    "sg:tags":[
        "society",
        "housing"
    ],
    "wof:name":"The Margaret Ogilvie Alms Houses",
    "wof:placetype":"venue"
},
  "geometry": {"coordinates":[1.5748339891,52.2048721313],"type":"Point"}
}