{
  "type": "Feature",
  "properties": {
    "addr:full":"1 Northaw Road West, Northaw Potters Bar Greater London EN6 4NW",
    "addr:housenumber":"1",
    "addr:postcode":"en6 4nw",
    "addr:street":"Northaw Road West",
    "iso:country":"GB",
    "sg:address":"1 Northaw Road West, Northaw",
    "sg:city":"Potters Bar",
    "sg:classifiers":[
        {
            "category":"Bars & Pubs",
            "type":"Food & Drink"
        }
    ],
    "sg:postcode":"EN6 4NW",
    "sg:province":"Greater London",
    "sg:tags":[
        "pubs",
        "inn"
    ],
    "wof:name":"The Two Brewers",
    "wof:placetype":"venue"
},
  "geometry": {"coordinates":[-0.150228,51.704533],"type":"Point"}
}