{
  "type": "Feature",
  "properties": {
    "addr:full":"52 High Street Staines Berkshire TW18 4DY",
    "addr:housenumber":"52",
    "addr:postcode":"tw18 4dy",
    "addr:street":"High Street",
    "iso:country":"GB",
    "sg:address":"52 High Street",
    "sg:city":"Staines",
    "sg:classifiers":[
        {
            "category":"Shopping",
            "subcategory":"Mobile Phones",
            "type":"Retail Goods"
        }
    ],
    "sg:phone":"+44 1784 466161",
    "sg:postcode":"TW18 4DY",
    "sg:province":"Berkshire",
    "wof:name":"N A G At Rymans",
    "wof:placetype":"venue"
},
  "geometry": {"coordinates":[-0.511503,51.434086],"type":"Point"}
}