{
  "type": "Feature",
  "properties": {
    "iso:country":"GB",
    "sg:address":"82 West Street, Portchester",
    "sg:city":"Fareham",
    "sg:classifiers":[
        {
            "category":"Building & Trades",
            "subcategory":"Construction",
            "type":"Services"
        }
    ],
    "sg:phone":"+44 7751 065433",
    "sg:postcode":"PO16 9UN",
    "sg:province":"Hampshire",
    "sg:tags":[
        "ceiling",
        "contractor"
    ],
    "wof:name":"A E Martin",
    "wof:placetype":"venue"
},
  "geometry": {"coordinates":[-1.128887,50.845806],"type":"Point"}
}