{
  "type": "Feature",
  "properties": {
    "addr:full":"5 De Winton Street Tonypandy Rhondda, Cynon, Taff CF40 2QZ",
    "addr:housenumber":"5",
    "addr:postcode":"cf40 2qz",
    "addr:street":"De Winton Street;Cynon Taff",
    "iso:country":"GB",
    "sg:address":"5 De Winton Street",
    "sg:city":"Tonypandy",
    "sg:classifiers":[
        {
            "category":"Cafe",
            "type":"Food & Drink"
        }
    ],
    "sg:phone":"+44 1443 432357",
    "sg:postcode":"CF40 2QZ",
    "sg:province":"Rhondda, Cynon, Taff",
    "sg:tags":[
        "tea",
        "snack",
        "bar",
        "room"
    ],
    "wof:name":"Lounge Cafe",
    "wof:placetype":"venue"
},
  "geometry": {"coordinates":[-3.457151,51.624458],"type":"Point"}
}