{
  "type": "Feature",
  "properties": {
    "addr:full":"Unit 10-11, Huntingdon Bsns Centre, 14 Stukeley Road Huntingdon Cambridgeshire PE29 6HF",
    "addr:housenumber":"unit 10-11;14",
    "addr:postcode":"pe29 6hf",
    "addr:street":"Stukeley Road",
    "iso:country":"GB",
    "sg:address":"Unit 10-11, Huntingdon Bsns Centre, 14 Stukeley Road",
    "sg:city":"Huntingdon",
    "sg:classifiers":[
        {
            "category":"Organizations",
            "subcategory":"Membership Organization",
            "type":"Services"
        },
        {
            "category":"Home & Garden",
            "subcategory":"Building Materials",
            "type":"Retail Goods"
        },
        {
            "category":"Home & Garden",
            "subcategory":"Carpets & Floor Coverings",
            "type":"Retail Goods"
        }
    ],
    "sg:phone":"+44 1480 413566",
    "sg:postcode":"PE29 6HF",
    "sg:province":"Cambridgeshire",
    "sg:tags":[
        "club",
        "rubber",
        "product",
        "manufacturer",
        "plastic"
    ],
    "wof:name":"Howgate & Lane Ltd",
    "wof:placetype":"venue"
},
  "geometry": {"coordinates":[-0.1893039942,52.3351402283],"type":"Point"}
}