{
  "type": "Feature",
  "properties": {
    "addr:full":"Unit 9, Carrwood Road Barnsley South Yorkshire S71 5AS",
    "addr:housenumber":"unit 9",
    "addr:postcode":"s71 5as",
    "addr:street":"Carrwood Road;Yorkshire",
    "iso:country":"GB",
    "sg:address":"Unit 9, Carrwood Road",
    "sg:city":"Barnsley",
    "sg:classifiers":[
        {
            "category":"Manufacturing",
            "subcategory":"Petroleum Products",
            "type":"Manufacturing & Wholesale Goods"
        }
    ],
    "sg:phone":"+44 1226 770774",
    "sg:postcode":"S71 5AS",
    "sg:province":"South Yorkshire",
    "sg:tags":[
        "double",
        "glazing"
    ],
    "wof:name":"B C Profiles",
    "wof:placetype":"venue"
},
  "geometry": {"coordinates":[-1.441574,53.549595],"type":"Point"}
}