{
  "type": "Feature",
  "properties": {
    "iso:country":"GB",
    "sg:address":"2 Allerton Buildings, Battery Green Rd",
    "sg:city":"Lowestoft",
    "sg:classifiers":[
        {
            "category":"Home & Garden",
            "subcategory":"Home Furnishings",
            "type":"Retail Goods"
        }
    ],
    "sg:phone":"+44 1502 567789",
    "sg:postcode":"NR32 1DH",
    "sg:province":"Suffolk",
    "sg:tags":[
        "furnishers",
        "planner",
        "kitchen"
    ],
    "wof:name":"J.N Kitchens & Bedrooms",
    "wof:placetype":"venue"
},
  "geometry": {"coordinates":[1.7535500526,52.4748306274],"type":"Point"}
}