{
  "type": "Feature",
  "properties": {
    "addr:full":"98a Plumstead High Street London Greater London SE18 1SL",
    "addr:housenumber":"98a",
    "addr:postcode":"se18 1sl",
    "addr:street":"High Street",
    "iso:country":"GB",
    "sg:address":"98a Plumstead High Street",
    "sg:city":"London",
    "sg:classifiers":[
        {
            "category":"Building & Trades",
            "subcategory":"Construction",
            "type":"Services"
        }
    ],
    "sg:postcode":"SE18 1SL",
    "sg:province":"Greater London",
    "sg:tags":[
        "builder"
    ],
    "wof:name":"The Thames Builders",
    "wof:placetype":"venue"
},
  "geometry": {"coordinates":[0.088621,51.488602],"type":"Point"}
}