{
  "type": "Feature",
  "properties": {
    "addr:full":"2 Turnpike Close Dunstable Bedfordshire LU6 3NG",
    "addr:housenumber":"2",
    "addr:postcode":"lu6 3ng",
    "addr:street":"Turnpike Close",
    "iso:country":"GB",
    "sg:address":"2 Turnpike Close",
    "sg:city":"Dunstable",
    "sg:classifiers":[
        {
            "category":"Building & Trades",
            "subcategory":"Landscaping Services",
            "type":"Services"
        }
    ],
    "sg:phone":"+44 1582 667615",
    "sg:postcode":"LU6 3NG",
    "sg:province":"Bedfordshire",
    "sg:tags":[
        "landscape",
        "contractor"
    ],
    "sg:website":"http://www.countrysidelandscapes.co.uk",
    "wof:name":"Countryside Garden Services",
    "wof:placetype":"venue"
},
  "geometry": {"coordinates":[-0.5128859878,51.8776130676],"type":"Point"}
}