{
  "type": "Feature",
  "properties": {
    "addr:full":"Windyridge Court, Milton Road, Drayton Abingdon Oxfordshire OX14 4EZ",
    "addr:postcode":"ox14 4ez",
    "addr:street":"Windyridge Court Milton Road",
    "iso:country":"GB",
    "sg:address":"Windyridge Court, Milton Road, Drayton",
    "sg:city":"Abingdon",
    "sg:classifiers":[
        {
            "category":"Shopping",
            "subcategory":"Florist",
            "type":"Retail Goods"
        }
    ],
    "sg:postcode":"OX14 4EZ",
    "sg:province":"Oxfordshire",
    "wof:name":"Wendy Madley Flowers",
    "wof:placetype":"venue"
},
  "geometry": {"coordinates":[-1.296563983,51.64270401],"type":"Point"}
}