{
  "type": "Feature",
  "properties": {
    "addr:full":"112 Shirland Road London Greater London W9 2EP",
    "addr:housenumber":"112",
    "addr:postcode":"w9 2ep",
    "addr:street":"Shirland Road",
    "iso:country":"GB",
    "sg:address":"112 Shirland Road",
    "sg:city":"London",
    "sg:classifiers":[
        {
            "category":"Taxi",
            "type":"Transportation"
        }
    ],
    "sg:postcode":"W9 2EP",
    "sg:province":"Greater London",
    "sg:tags":[
        "mini",
        "cab"
    ],
    "wof:name":"Royal Car Service",
    "wof:placetype":"venue"
},
  "geometry": {"coordinates":[-0.1933040023,51.5262489319],"type":"Point"}
}