{
  "type": "Feature",
  "properties": {
    "addr:full":"York House, York Terrace Chester Cheshire CH1 3LR",
    "addr:postcode":"ch1 3lr",
    "addr:street":"York Terrace",
    "iso:country":"GB",
    "sg:address":"York House, York Terrace",
    "sg:city":"Chester",
    "sg:classifiers":[
        {
            "category":"Travel",
            "subcategory":"Hotels & Motels",
            "type":"Entertainment"
        }
    ],
    "sg:phone":"+44 1244 345700",
    "sg:postcode":"CH1 3LR",
    "sg:province":"Cheshire",
    "sg:tags":[
        "self",
        "catering"
    ],
    "wof:name":"Sykes Cottages",
    "wof:placetype":"venue"
},
  "geometry": {"coordinates":[-2.8850190639,53.192905426],"type":"Point"}
}