{
  "type": "Feature",
  "properties": {
    "addr:full":"Unit 1 Market Street, Clay Cross Chesterfield Derbyshire S45 9JE",
    "addr:housenumber":"unit 1",
    "addr:postcode":"s45 9je",
    "addr:street":"Market Street",
    "iso:country":"GB",
    "sg:address":"Unit 1 Market Street, Clay Cross",
    "sg:city":"Chesterfield",
    "sg:classifiers":[
        {
            "category":"Travel",
            "subcategory":"Travel Agent",
            "type":"Entertainment"
        }
    ],
    "sg:phone":"+44 1246 250025",
    "sg:postcode":"S45 9JE",
    "sg:province":"Derbyshire",
    "wof:name":"Co-Op Travel Ltd.",
    "wof:placetype":"venue"
},
  "geometry": {"coordinates":[-1.4039139748,53.1706314087],"type":"Point"}
}