{
  "type": "Feature",
  "properties": {
    "addr:full":"Woolage Farm, Woolage Grn Canterbury Kent CT4 6SG",
    "addr:postcode":"ct4 6sg",
    "addr:street":"Woolage Grn",
    "iso:country":"GB",
    "sg:address":"Woolage Farm, Woolage Grn",
    "sg:city":"Canterbury",
    "sg:classifiers":[
        {
            "category":"Home & Garden",
            "subcategory":"Garden Supply",
            "type":"Retail Goods"
        }
    ],
    "sg:postcode":"CT4 6SG",
    "sg:province":"Kent",
    "sg:tags":[
        "bulb",
        "grower"
    ],
    "wof:name":"W A Groombridge & Sons",
    "wof:placetype":"venue"
},
  "geometry": {"coordinates":[1.2026200294,51.1999511719],"type":"Point"}
}