{
  "type": "Feature",
  "properties": {
    "addr:full":"19 Haig Road Bury Lancashire BL8 2ND",
    "addr:housenumber":"19",
    "addr:postcode":"bl8 2nd",
    "addr:street":"Haig Road",
    "iso:country":"GB",
    "sg:address":"19 Haig Road",
    "sg:city":"Bury",
    "sg:classifiers":[
        {
            "category":"Health Services",
            "subcategory":"Clinic",
            "type":"Services"
        }
    ],
    "sg:phone":"+44 161 797 9096",
    "sg:postcode":"BL8 2ND",
    "sg:province":"Lancashire",
    "sg:tags":[
        "aromatherapy"
    ],
    "wof:name":"Anne Whittaker Clinical Aromatherapist",
    "wof:placetype":"venue"
},
  "geometry": {"coordinates":[-2.321118,53.589535],"type":"Point"}
}