{
  "type": "Feature",
  "properties": {
    "iso:country":"GB",
    "sg:address":"Hempstead Valley Shopping Ctr, Unit 29/39",
    "sg:city":"Gillingham",
    "sg:classifiers":[
        {
            "category":"Shopping",
            "subcategory":"Clothing, Apparel, & Fashions",
            "type":"Retail Goods"
        }
    ],
    "sg:phone":"+44 1634 376118",
    "sg:postcode":"ME7 3PB",
    "sg:province":"Kent",
    "sg:tags":[
        "menswear"
    ],
    "wof:name":"Burton Menswear Ltd",
    "wof:placetype":"venue"
},
  "geometry": {"coordinates":[0.57106,51.351429],"type":"Point"}
}