{
  "type": "Feature",
  "properties": {
    "addr:full":"7 Elizabeth Place Dorchester Dorset DT1 2JL",
    "addr:housenumber":"7",
    "addr:postcode":"dt1 2jl",
    "addr:street":"Elizabeth Place",
    "iso:country":"GB",
    "sg:address":"7 Elizabeth Place",
    "sg:city":"Dorchester",
    "sg:classifiers":[
        {
            "category":"Professional",
            "subcategory":"Engineering",
            "type":"Services"
        }
    ],
    "sg:phone":"+44 1305 266798",
    "sg:postcode":"DT1 2JL",
    "sg:province":"Dorset",
    "sg:tags":[
        "contractor",
        "electrical",
        "engineer"
    ],
    "wof:name":"Peter Nother",
    "wof:placetype":"venue"
},
  "geometry": {"coordinates":[-2.454368,50.711216],"type":"Point"}
}