{
  "type": "Feature",
  "properties": {
    "addr:full":"43-45 Bonchurch Road Brighton East Sussex BN2 3PJ",
    "addr:housenumber":"43-45",
    "addr:postcode":"bn2 3pj",
    "addr:street":"Bonchurch Road",
    "iso:country":"GB",
    "sg:address":"43-45 Bonchurch Road",
    "sg:city":"Brighton",
    "sg:classifiers":[
        {
            "category":"Transit Center",
            "subcategory":"Freight",
            "type":"Transportation"
        }
    ],
    "sg:phone":"+44 1273 601989",
    "sg:postcode":"BN2 3PJ",
    "sg:province":"East Sussex",
    "sg:tags":[
        "piano",
        "accessory"
    ],
    "wof:name":"Brighton Piano Warehouse",
    "wof:placetype":"venue"
},
  "geometry": {"coordinates":[-0.122675,50.832867],"type":"Point"}
}