{
  "type": "Feature",
  "properties": {
    "addr:full":"Saxon Works, Olive Rd Hove East Sussex BN3 5LE",
    "addr:postcode":"bn3 5le",
    "addr:street":"Olive Rd",
    "iso:country":"GB",
    "sg:address":"Saxon Works, Olive Rd",
    "sg:city":"Hove",
    "sg:classifiers":[
        {
            "category":"Retail",
            "subcategory":"Auto Repair",
            "type":"Services"
        }
    ],
    "sg:phone":"+44 1273 707444",
    "sg:postcode":"BN3 5LE",
    "sg:province":"East Sussex",
    "sg:tags":[
        "modification",
        "garage"
    ],
    "wof:name":"Motor Services Ltd",
    "wof:placetype":"venue"
},
  "geometry": {"coordinates":[-0.182449,50.838943],"type":"Point"}
}