{
  "type": "Feature",
  "properties": {
    "iso:country":"GB",
    "sg:address":"65 Prescott Lane",
    "sg:city":"Wigan",
    "sg:classifiers":[
        {
            "category":"Food & Beverages",
            "subcategory":"Meat & Fish",
            "type":"Retail Goods"
        }
    ],
    "sg:phone":"+44 1942 703523",
    "sg:postcode":"WN5 0HT",
    "sg:province":"Lancashire",
    "sg:tags":[
        "butcher"
    ],
    "wof:name":"S & J Baxter",
    "wof:placetype":"venue"
},
  "geometry": {"coordinates":[-2.684289,53.548645],"type":"Point"}
}