{
  "type": "Feature",
  "properties": {
    "iso:country":"GB",
    "sg:address":"Yoxall Road, Kings Bromley",
    "sg:city":"Burton-on-trent",
    "sg:classifiers":[
        {
            "category":"Home & Garden",
            "subcategory":"Garden Supply",
            "type":"Retail Goods"
        }
    ],
    "sg:postcode":"DE13 7JJ",
    "sg:province":"Derbyshire",
    "sg:tags":[
        "planting",
        "tree",
        "shrub"
    ],
    "wof:name":"P D Nurseries",
    "wof:placetype":"venue"
},
  "geometry": {"coordinates":[-1.821409,52.750286],"type":"Point"}
}