{
  "type": "Feature",
  "properties": {
    "iso:country":"GB",
    "sg:address":"6 New Street, Bridge Of Allan",
    "sg:city":"Stirling",
    "sg:classifiers":[
        {
            "category":"Bars & Pubs",
            "type":"Food & Drink"
        },
        {
            "category":"Community Center",
            "subcategory":"Social",
            "type":"Public Place"
        }
    ],
    "sg:phone":"+44 1786 833281",
    "sg:postcode":"FK9 4NZ",
    "sg:province":"Clackmannanshire",
    "sg:tags":[
        "pubs",
        "house",
        "inn",
        "activity"
    ],
    "wof:name":"Rising Sun",
    "wof:placetype":"venue"
},
  "geometry": {"coordinates":[-3.950268,56.155457],"type":"Point"}
}