{
  "type": "Feature",
  "properties": {
    "addr:full":"15 Weston Rd Southend-on-sea Essex SS1 1AS",
    "addr:housenumber":"15",
    "addr:postcode":"ss1 1as",
    "addr:street":"Weston Rd",
    "iso:country":"GB",
    "sg:address":"15 Weston Rd",
    "sg:city":"Southend-on-sea",
    "sg:classifiers":[
        {
            "category":"Sports & Exercise",
            "subcategory":"Gym",
            "type":"Entertainment"
        }
    ],
    "sg:postcode":"SS1 1AS",
    "sg:province":"Essex",
    "sg:tags":[
        "fitness",
        "health",
        "centre"
    ],
    "wof:name":"Rarity,Denise,",
    "wof:placetype":"venue"
},
  "geometry": {"coordinates":[0.712473,51.536224],"type":"Point"}
}