{
  "type": "Feature",
  "properties": {
    "iso:country":"GB",
    "sg:address":"Unit B2 Barwell Business Park",
    "sg:city":"Chessington",
    "sg:classifiers":[
        {
            "category":"Retail",
            "subcategory":"Auto Repair",
            "type":"Services"
        }
    ],
    "sg:phone":"+44 20 8391 0121",
    "sg:postcode":"KT9 2NY",
    "sg:province":"Surrey",
    "sg:tags":[
        "engine",
        "car",
        "specialist"
    ],
    "wof:name":"S B Development",
    "wof:placetype":"venue"
},
  "geometry": {"coordinates":[-0.3123289943,51.3527832031],"type":"Point"}
}