{
  "type": "Feature",
  "properties": {
    "addr:full":"Lancer Square, Kensington Church St Kensington Greater London W8 4EH",
    "addr:postcode":"w8 4eh",
    "addr:street":"Lancer Square Kensington Church St",
    "iso:country":"GB",
    "sg:address":"Lancer Square, Kensington Church St",
    "sg:city":"Kensington",
    "sg:classifiers":[
        {
            "category":"Organizations",
            "subcategory":"Community Association",
            "type":"Services"
        }
    ],
    "sg:phone":"+44 20 7937 8088",
    "sg:postcode":"W8 4EH",
    "sg:province":"Greater London",
    "sg:tags":[
        "relation",
        "public"
    ],
    "wof:name":"Redchip Communications International Ltd",
    "wof:placetype":"venue"
},
  "geometry": {"coordinates":[-0.191379,51.503536],"type":"Point"}
}