{
  "type": "Feature",
  "properties": {
    "addr:full":"510 Brixton Rd Brixton Greater London SW9 8EN",
    "addr:housenumber":"510",
    "addr:postcode":"sw9 8en",
    "addr:street":"Brixton Rd",
    "iso:country":"GB",
    "sg:address":"510 Brixton Rd",
    "sg:city":"Brixton",
    "sg:classifiers":[
        {
            "category":"Shopping",
            "subcategory":"Clothing, Apparel, & Fashions",
            "type":"Retail Goods"
        }
    ],
    "sg:phone":"+44 20 7924 0322",
    "sg:postcode":"SW9 8EN",
    "sg:province":"Greater London",
    "sg:tags":[
        "shop"
    ],
    "wof:name":"Fashion Avenue",
    "wof:placetype":"venue"
},
  "geometry": {"coordinates":[-0.1156489998,51.4617347717],"type":"Point"}
}