{
  "type": "Feature",
  "properties": {
    "iso:country":"GB",
    "sg:address":"Toots Edge Oakley Rd, Caversham Heights",
    "sg:city":"Reading",
    "sg:classifiers":[
        {
            "category":"Organizations",
            "subcategory":"Community Association",
            "type":"Services"
        }
    ],
    "sg:phone":"+44 118 948 4646",
    "sg:postcode":"RG4 7RL",
    "sg:province":"Berkshire",
    "sg:tags":[
        "relation",
        "public"
    ],
    "wof:name":"Nickolls Public Relations",
    "wof:placetype":"venue"
},
  "geometry": {"coordinates":[-0.9822199941,51.4749107361],"type":"Point"}
}