{
  "type": "Feature",
  "properties": {
    "iso:country":"GB",
    "sg:address":"92 Briggate",
    "sg:city":"Leeds",
    "sg:classifiers":[
        {
            "category":"Restaurant",
            "type":"Food & Drink"
        }
    ],
    "sg:phone":"+44 113 242 8220",
    "sg:postcode":"LS1 6NP",
    "sg:province":"West Yorkshire",
    "wof:name":"Wendys (UK) Ltd",
    "wof:placetype":"venue"
},
  "geometry": {"coordinates":[-1.541856,53.798992],"type":"Point"}
}