{
  "type": "Feature",
  "properties": {
    "addr:full":"Bramling Road, Bramling Canterbury Kent CT3 1NA",
    "addr:postcode":"ct3 1na",
    "addr:street":"Bramling Road Bramling",
    "iso:country":"GB",
    "sg:address":"Bramling Road, Bramling",
    "sg:city":"Canterbury",
    "sg:classifiers":[
        {
            "category":"Autos & Motor Vehicles",
            "subcategory":"Fuel & Gas Station",
            "type":"Retail Goods"
        }
    ],
    "sg:phone":"+44 1227 720967",
    "sg:postcode":"CT3 1NA",
    "sg:province":"Kent",
    "sg:tags":[
        "petrol",
        "filling"
    ],
    "wof:name":"Casino Filling Station",
    "wof:placetype":"venue"
},
  "geometry": {"coordinates":[1.1783800125,51.256855011],"type":"Point"}
}