{
  "type": "Feature",
  "properties": {
    "addr:full":"4 Ridgeway, Hutton Brentwood Essex CM13 2LS",
    "addr:housenumber":"4",
    "addr:postcode":"cm13 2ls",
    "addr:street":"Ridgeway Hutton",
    "iso:country":"GB",
    "sg:address":"4 Ridgeway, Hutton",
    "sg:city":"Brentwood",
    "sg:classifiers":[
        {
            "category":"Building & Trades",
            "subcategory":"Construction",
            "type":"Services"
        }
    ],
    "sg:phone":"+44 1277 233919",
    "sg:postcode":"CM13 2LS",
    "sg:province":"Essex",
    "sg:tags":[
        "builder"
    ],
    "wof:name":"Ridgemount Construction Ltd.",
    "wof:placetype":"venue"
},
  "geometry": {"coordinates":[0.342076987,51.6231918335],"type":"Point"}
}