{
  "type": "Feature",
  "properties": {
    "iso:country":"GB",
    "sg:address":"26 Main Street",
    "sg:city":"Kelty",
    "sg:classifiers":[
        {
            "category":"Fast Food",
            "type":"Food & Drink"
        }
    ],
    "sg:postcode":"KY4 0AA",
    "sg:province":"Fife",
    "sg:tags":[
        "away",
        "take"
    ],
    "wof:name":"Four Seasons Take Away",
    "wof:placetype":"venue"
},
  "geometry": {"coordinates":[-3.379775,56.133495],"type":"Point"}
}