{
  "type": "Feature",
  "properties": {
    "addr:full":"89 Rice Lane, Walton Liverpool Merseyside L9 1AD",
    "addr:housenumber":"89",
    "addr:postcode":"l9 1ad",
    "addr:street":"Rice Lane",
    "iso:country":"GB",
    "sg:address":"89 Rice Lane, Walton",
    "sg:city":"Liverpool",
    "sg:classifiers":[
        {
            "category":"Community Center",
            "type":"Public Place"
        }
    ],
    "sg:phone":"+44 151 530 1065",
    "sg:postcode":"L9 1AD",
    "sg:province":"Merseyside",
    "sg:tags":[
        "centre"
    ],
    "wof:name":"Rice Lane Community Association Ltd.",
    "wof:placetype":"venue"
},
  "geometry": {"coordinates":[-2.96638,53.449631],"type":"Point"}
}