{
  "type": "Feature",
  "properties": {
    "iso:country":"GB",
    "sg:address":"South Street",
    "sg:city":"Crewkerne",
    "sg:classifiers":[
        {
            "category":"Manufacturing",
            "subcategory":"Buildings",
            "type":"Manufacturing & Wholesale Goods"
        }
    ],
    "sg:phone":"+44 1460 72873",
    "sg:postcode":"TA18 8DA",
    "sg:province":"Dorset",
    "sg:tags":[
        "portable"
    ],
    "wof:name":"R J Wey & Sons",
    "wof:placetype":"venue"
},
  "geometry": {"coordinates":[-2.794939,50.882923],"type":"Point"}
}