{
  "type": "Feature",
  "properties": {
    "addr:full":"Hartridge Farm Road Newport Monmouthshire NP18 2LN",
    "addr:postcode":"np18 2ln",
    "addr:street":"Farm Road",
    "iso:country":"GB",
    "sg:address":"Hartridge Farm Road",
    "sg:city":"Newport",
    "sg:classifiers":[
        {
            "category":"Education",
            "subcategory":"School",
            "type":"Public Place"
        }
    ],
    "sg:phone":"+44 1633 290270",
    "sg:postcode":"NP18 2LN",
    "sg:province":"Monmouthshire",
    "sg:tags":[
        "local",
        "authority"
    ],
    "wof:name":"Ysgol Gymraeg Casnewydd",
    "wof:placetype":"venue"
},
  "geometry": {"coordinates":[-2.9361701012,51.5849227905],"type":"Point"}
}