{
  "type": "Feature",
  "properties": {
    "addr:full":"Long House Farm, Delph Lane, Barnacre Preston Lancashire PR3 1UN",
    "addr:postcode":"pr3 1un",
    "addr:street":"Delph Lane",
    "iso:country":"GB",
    "sg:address":"Long House Farm, Delph Lane, Barnacre",
    "sg:city":"Preston",
    "sg:classifiers":[
        {
            "category":"Farming",
            "subcategory":"Dairy Farm",
            "type":"Manufacturing & Wholesale Goods"
        }
    ],
    "sg:phone":"+44 1995 602322",
    "sg:postcode":"PR3 1UN",
    "sg:province":"Lancashire",
    "sg:tags":[
        "farmer"
    ],
    "wof:name":"Clifford John Dennison",
    "wof:placetype":"venue"
},
  "geometry": {"coordinates":[-2.745642,53.915112],"type":"Point"}
}