{
  "type": "Feature",
  "properties": {
    "iso:country":"GB",
    "sg:address":"Shuttlewood Road, Bolsover",
    "sg:city":"Chesterfield",
    "sg:classifiers":[
        {
            "category":"Autos & Motor Vehicles",
            "subcategory":"Automobile Sales",
            "type":"Retail Goods"
        }
    ],
    "sg:phone":"+44 1246 822893",
    "sg:postcode":"S44 6PA",
    "sg:province":"Derbyshire",
    "sg:tags":[
        "commercial"
    ],
    "wof:name":"Trade 'N' Save",
    "wof:placetype":"venue"
},
  "geometry": {"coordinates":[-1.293583,53.237869],"type":"Point"}
}