{
  "type": "Feature",
  "properties": {
    "addr:full":"1 Pinfold Street Macclesfield Cheshire SK11 6HA",
    "addr:housenumber":"1",
    "addr:postcode":"sk11 6ha",
    "addr:street":"Pinfold Street",
    "iso:country":"GB",
    "sg:address":"1 Pinfold Street",
    "sg:city":"Macclesfield",
    "sg:classifiers":[
        {
            "category":"Personal",
            "subcategory":"Beauty Salon",
            "type":"Services"
        }
    ],
    "sg:phone":"+44 1625 434337",
    "sg:postcode":"SK11 6HA",
    "sg:province":"Cheshire",
    "sg:tags":[
        "lady",
        "hairdresser"
    ],
    "wof:name":"Haircraft",
    "wof:placetype":"venue"
},
  "geometry": {"coordinates":[-2.132028,53.260197],"type":"Point"}
}