{
  "type": "Feature",
  "properties": {
    "addr:full":"35 High Street, Dawley Telford Shropshire TF4 2EX",
    "addr:housenumber":"35",
    "addr:postcode":"tf4 2ex",
    "addr:street":"High Street",
    "iso:country":"GB",
    "sg:address":"35 High Street, Dawley",
    "sg:city":"Telford",
    "sg:classifiers":[
        {
            "category":"Banks & Credit Unions",
            "subcategory":"Bank",
            "type":"Services"
        }
    ],
    "sg:phone":"+44 1952 282528",
    "sg:postcode":"TF4 2EX",
    "sg:province":"Shropshire",
    "wof:name":"Farestone Credit",
    "wof:placetype":"venue"
},
  "geometry": {"coordinates":[-2.467784,52.664032],"type":"Point"}
}