{
  "type": "Feature",
  "properties": {
    "iso:country":"GB",
    "sg:address":"Foxes Riding School",
    "sg:city":"Ellesmere Port",
    "sg:classifiers":[
        {
            "category":"Home & Garden",
            "subcategory":"Home Furnishings",
            "type":"Retail Goods"
        }
    ],
    "sg:postcode":"CH66 8PF",
    "sg:province":"Cheshire",
    "sg:tags":[
        "homefurnishings"
    ],
    "wof:name":"Cheshire County Furniture",
    "wof:placetype":"venue"
},
  "geometry": {"coordinates":[-2.98502,53.273991],"type":"Point"}
}