{
  "type": "Feature",
  "properties": {
    "addr:full":"83 Croydon Road Caterham Surrey CR3 6PD",
    "addr:housenumber":"83",
    "addr:postcode":"cr3 6pd",
    "addr:street":"Croydon Road",
    "iso:country":"GB",
    "sg:address":"83 Croydon Road",
    "sg:city":"Caterham",
    "sg:classifiers":[
        {
            "category":"Manufacturing",
            "subcategory":"Buildings",
            "type":"Manufacturing & Wholesale Goods"
        }
    ],
    "sg:phone":"+44 1883 341710",
    "sg:postcode":"CR3 6PD",
    "sg:province":"Surrey",
    "sg:tags":[
        "system",
        "air conditioning"
    ],
    "wof:name":"Hitecsa U K Ltd.",
    "wof:placetype":"venue"
},
  "geometry": {"coordinates":[-0.079104,51.286057],"type":"Point"}
}