{
  "type": "Feature",
  "properties": {
    "addr:full":"8 Malvern Ct, Hook Rd Surbiton Surrey KT6 5AB",
    "addr:housenumber":"8",
    "addr:postcode":"kt6 5ab",
    "addr:street":"Malvern Ct Hook Rd",
    "iso:country":"GB",
    "sg:address":"8 Malvern Ct, Hook Rd",
    "sg:city":"Surbiton",
    "sg:classifiers":[
        {
            "category":"Health Services",
            "subcategory":"Health Practitioner",
            "type":"Services"
        }
    ],
    "sg:phone":"+44 20 8390 7015",
    "sg:postcode":"KT6 5AB",
    "sg:province":"Surrey",
    "sg:tags":[
        "hypnotherapists"
    ],
    "wof:name":"Josephine Blyth",
    "wof:placetype":"venue"
},
  "geometry": {"coordinates":[-0.306949,51.392059],"type":"Point"}
}