{
  "type": "Feature",
  "properties": {
    "iso:country":"GB",
    "sg:address":"88 Swinside Drive",
    "sg:city":"Durham",
    "sg:classifiers":[
        {
            "category":"Professional",
            "subcategory":"Art Services",
            "type":"Services"
        },
        {
            "category":"Building & Trades",
            "subcategory":"Construction",
            "type":"Services"
        }
    ],
    "sg:postcode":"DH1 1AF",
    "sg:province":"Durham",
    "sg:tags":[
        "decorator",
        "painter"
    ],
    "wof:name":"NEVILLE BROWN",
    "wof:placetype":"venue"
},
  "geometry": {"coordinates":[-1.528384,54.792042],"type":"Point"}
}