{
  "type": "Feature",
  "properties": {
    "addr:full":"Unit 1, Chester Road Borehamwood Hertfordshire WD6 1NA",
    "addr:housenumber":"unit 1",
    "addr:postcode":"wd6 1na",
    "addr:street":"Chester Road",
    "iso:country":"GB",
    "sg:address":"Unit 1, Chester Road",
    "sg:city":"Borehamwood",
    "sg:classifiers":[
        {
            "category":"Manufacturing",
            "subcategory":"Textiles",
            "type":"Manufacturing & Wholesale Goods"
        }
    ],
    "sg:phone":"+44 20 8207 6699",
    "sg:postcode":"WD6 1NA",
    "sg:province":"Hertfordshire",
    "sg:tags":[
        "merchant",
        "agent"
    ],
    "wof:name":"Furnishing Fabric Agencies",
    "wof:placetype":"venue"
},
  "geometry": {"coordinates":[-0.258804,51.657799],"type":"Point"}
}