{
  "type": "Feature",
  "properties": {
    "iso:country":"GB",
    "sg:address":"Town Street",
    "sg:city":"Pudsey",
    "sg:classifiers":[
        {
            "category":"Autos & Motor Vehicles",
            "subcategory":"Fuel & Gas Station",
            "type":"Retail Goods"
        }
    ],
    "sg:phone":"+44 113 256 2057",
    "sg:postcode":"LS28 6HQ",
    "sg:province":"West Yorkshire",
    "sg:tags":[
        "hr",
        "petrol"
    ],
    "wof:name":"Europa Filling Station",
    "wof:placetype":"venue"
},
  "geometry": {"coordinates":[-1.659892,53.807858],"type":"Point"}
}