{
  "type": "Feature",
  "properties": {
    "addr:full":"22 Chesterton Road Cambridge Cambridgeshire CB4 3AX",
    "addr:housenumber":"22",
    "addr:postcode":"cb4 3ax",
    "addr:street":"Chesterton Road",
    "iso:country":"GB",
    "sg:address":"22 Chesterton Road",
    "sg:city":"Cambridge",
    "sg:classifiers":[
        {
            "category":"Fast Food",
            "type":"Food & Drink"
        },
        {
            "category":"Restaurant",
            "type":"Food & Drink"
        }
    ],
    "sg:phone":"+44 1223 351880",
    "sg:postcode":"CB4 3AX",
    "sg:province":"Cambridgeshire",
    "sg:tags":[
        "away",
        "-",
        "take",
        "french"
    ],
    "wof:name":"Restaurant Twenty Two",
    "wof:placetype":"venue"
},
  "geometry": {"coordinates":[0.1242740005,52.2139358521],"type":"Point"}
}