{
  "type": "Feature",
  "properties": {
    "iso:country":"GB",
    "sg:address":"44 South Parade",
    "sg:city":"Whitley Bay",
    "sg:classifiers":[
        {
            "category":"Travel",
            "subcategory":"Hotels & Motels",
            "type":"Entertainment"
        }
    ],
    "sg:postcode":"NE26 2RQ",
    "sg:province":"Northumberland",
    "wof:name":"The Waverley",
    "wof:placetype":"venue"
},
  "geometry": {"coordinates":[-1.442512,55.043922],"type":"Point"}
}