{
  "type": "Feature",
  "properties": {
    "iso:country":"GB",
    "sg:address":"811 High Road, Goodmayes",
    "sg:city":"Ilford",
    "sg:classifiers":[
        {
            "category":"Food & Beverages",
            "subcategory":"Fruits & Vegetables",
            "type":"Retail Goods"
        }
    ],
    "sg:phone":"+44 20 8597 1700",
    "sg:postcode":"IG3 8TD",
    "sg:province":"Essex",
    "sg:tags":[
        "greengrocer"
    ],
    "wof:name":"Fruit Busters",
    "wof:placetype":"venue"
},
  "geometry": {"coordinates":[0.108307,51.566418],"type":"Point"}
}