{
  "type": "Feature",
  "properties": {
    "iso:country":"GB",
    "sg:address":"Divisional Headquarters, B Division, 40 Harpenden Road",
    "sg:city":"St Albans",
    "sg:classifiers":[
        {
            "category":"Government",
            "subcategory":"Fire Station",
            "type":"Public Place"
        }
    ],
    "sg:phone":"+44 1727 865821",
    "sg:postcode":"AL3 5AG",
    "sg:province":"Hertfordshire",
    "wof:name":"Hertfordshire Fire & Rescue Service",
    "wof:placetype":"venue"
},
  "geometry": {"coordinates":[-0.33443,51.762321],"type":"Point"}
}