{
  "type": "Feature",
  "properties": {
    "iso:country":"GB",
    "sg:address":"Unit 4, Golborne Enterprise Park",
    "sg:city":"Warrington",
    "sg:classifiers":[
        {
            "category":"Professional",
            "subcategory":"Engineering",
            "type":"Services"
        }
    ],
    "sg:postcode":"WA3 3DR",
    "sg:province":"Cheshire",
    "sg:tags":[
        "consulting",
        "engineer"
    ],
    "wof:name":"Coulthard Subsea Ltd.",
    "wof:placetype":"venue"
},
  "geometry": {"coordinates":[-2.5963330269,53.4787368774],"type":"Point"}
}