{
  "type": "Feature",
  "properties": {
    "iso:country":"GB",
    "sg:address":"53 Borough High St",
    "sg:city":"Southwark",
    "sg:classifiers":[
        {
            "category":"Cafe",
            "type":"Food & Drink"
        }
    ],
    "sg:phone":"+44 20 7407 2002",
    "sg:postcode":"SE1 1NE",
    "sg:province":"Greater London",
    "sg:tags":[
        "tea",
        "room"
    ],
    "wof:name":"Conti's",
    "wof:placetype":"venue"
},
  "geometry": {"coordinates":[-0.089459002,51.5052108765],"type":"Point"}
}