{
  "type": "Feature",
  "properties": {
    "addr:full":"30 Main Street Berwick-upon-tweed Northumberland TD15 1QY",
    "addr:housenumber":"30",
    "addr:postcode":"td15 1qy",
    "addr:street":"Main Street;Northumberland",
    "iso:country":"GB",
    "sg:address":"30 Main Street",
    "sg:city":"Berwick-upon-tweed",
    "sg:classifiers":[
        {
            "category":"Bus Charters",
            "type":"Transportation"
        }
    ],
    "sg:phone":"+44 1289 308719",
    "sg:postcode":"TD15 1QY",
    "sg:province":"Northumberland",
    "sg:tags":[
        "coach"
    ],
    "wof:name":"Cross-Country Connexions Ltd.",
    "wof:placetype":"venue"
},
  "geometry": {"coordinates":[-2.010525,55.766541],"type":"Point"}
}