{
  "type": "Feature",
  "properties": {
    "addr:full":"63 Ightham Road Erith Kent DA8 1LU",
    "addr:housenumber":"63",
    "addr:postcode":"da8 1lu",
    "addr:street":"Ightham Road",
    "iso:country":"GB",
    "sg:address":"63 Ightham Road",
    "sg:city":"Erith",
    "sg:classifiers":[
        {
            "category":"Freight",
            "type":"Transportation"
        }
    ],
    "sg:phone":"+44 1322 434876",
    "sg:postcode":"DA8 1LU",
    "sg:province":"Kent",
    "sg:tags":[
        "haulage",
        "road"
    ],
    "wof:name":"Tovin Services",
    "wof:placetype":"venue"
},
  "geometry": {"coordinates":[0.1501300037,51.4749984741],"type":"Point"}
}