{
  "type": "Feature",
  "properties": {
    "iso:country":"GB",
    "sg:address":"64 Saville Street",
    "sg:city":"North Shields",
    "sg:classifiers":[
        {
            "category":"Retail",
            "subcategory":"Repair Shop",
            "type":"Services"
        }
    ],
    "sg:postcode":"NE30 1AZ",
    "sg:province":"Tyne and Wear",
    "sg:tags":[
        "upholsterer"
    ],
    "wof:name":"Consort Upholstery",
    "wof:placetype":"venue"
},
  "geometry": {"coordinates":[-1.443116,55.008701],"type":"Point"}
}