{
  "type": "Feature",
  "properties": {
    "iso:country":"GB",
    "sg:address":"Middlemass Hey, Netherley",
    "sg:city":"Liverpool",
    "sg:classifiers":[
        {
            "category":"Health Services",
            "subcategory":"Nursing And Care Facility",
            "type":"Services"
        }
    ],
    "sg:phone":"+44 151 498 4776",
    "sg:postcode":"L27 7AR",
    "sg:province":"Merseyside",
    "sg:tags":[
        "home"
    ],
    "wof:name":"Garden Lodge Nursing Home",
    "wof:placetype":"venue"
},
  "geometry": {"coordinates":[-2.839504,53.387932],"type":"Point"}
}