{
  "type": "Feature",
  "properties": {
    "addr:full":"16b Grasmere Road Blackpool Lancashire FY1 5HT",
    "addr:housenumber":"16b",
    "addr:postcode":"fy1 5ht",
    "addr:street":"Grasmere Road",
    "iso:country":"GB",
    "sg:address":"16b Grasmere Road",
    "sg:city":"Blackpool",
    "sg:classifiers":[
        {
            "category":"Shopping",
            "subcategory":"Department Store",
            "type":"Retail Goods"
        }
    ],
    "sg:phone":"+44 1253 296452",
    "sg:postcode":"FY1 5HT",
    "sg:province":"Lancashire",
    "wof:name":"Grasmere Cycles",
    "wof:placetype":"venue"
},
  "geometry": {"coordinates":[-3.0447618961,53.8090667725],"type":"Point"}
}