{
  "type": "Feature",
  "properties": {
    "addr:full":"4 Princess Way Camberley Berkshire GU15 3SP",
    "addr:housenumber":"4",
    "addr:postcode":"gu15 3sp",
    "addr:street":"Princess Way",
    "iso:country":"GB",
    "sg:address":"4 Princess Way",
    "sg:city":"Camberley",
    "sg:classifiers":[
        {
            "category":"Health Services",
            "subcategory":"Optometrist",
            "type":"Services"
        }
    ],
    "sg:phone":"+44 1276 65003",
    "sg:postcode":"GU15 3SP",
    "sg:province":"Berkshire",
    "sg:tags":[
        "optician"
    ],
    "wof:name":"Leightons Opticians",
    "wof:placetype":"venue"
},
  "geometry": {"coordinates":[-0.7442700267,51.3376617432],"type":"Point"}
}