{
  "type": "Feature",
  "properties": {
    "iso:country":"GB",
    "sg:address":"Rivulet House, Canterbury Road",
    "sg:city":"Folkestone",
    "sg:classifiers":[
        {
            "category":"Organizations",
            "subcategory":"Community Association",
            "type":"Services"
        }
    ],
    "sg:postcode":"CT18 8HT",
    "sg:province":"Kent",
    "sg:tags":[
        "society",
        "housing"
    ],
    "wof:name":"Abbeyfield Lyminge Society Ltd(The)",
    "wof:placetype":"venue"
},
  "geometry": {"coordinates":[1.094515,51.113354],"type":"Point"}
}