{
  "type": "Feature",
  "properties": {
    "iso:country":"GB",
    "sg:address":"163 Vicarage Road",
    "sg:city":"Oldbury",
    "sg:classifiers":[
        {
            "category":"Manufacturing",
            "subcategory":"Tools & Machinery",
            "type":"Manufacturing & Wholesale Goods"
        },
        {
            "category":"Insurance",
            "subcategory":"Insurance Agent",
            "type":"Services"
        }
    ],
    "sg:phone":"+44 121 552 5000",
    "sg:postcode":"B68 8JB",
    "sg:province":"West Midlands",
    "sg:tags":[
        "society",
        "friendly"
    ],
    "wof:name":"Sovereign Insurance Services (Langley) Ltd.",
    "wof:placetype":"venue"
},
  "geometry": {"coordinates":[-1.99989,52.49427],"type":"Point"}
}