{
  "type": "Feature",
  "properties": {
    "addr:full":"Cock Horse, Chatsworth Drive Banbury Oxfordshire OX16 9YJ",
    "addr:postcode":"ox16 9yj",
    "addr:street":"Chatsworth Drive",
    "iso:country":"GB",
    "sg:address":"Cock Horse, Chatsworth Drive",
    "sg:city":"Banbury",
    "sg:classifiers":[
        {
            "category":"Arts & Performance",
            "subcategory":"Art Gallery",
            "type":"Entertainment"
        },
        {
            "category":"Autos & Motor Vehicles",
            "subcategory":"Motorcycle Sales",
            "type":"Retail Goods"
        }
    ],
    "sg:postcode":"OX16 9YJ",
    "sg:province":"Oxfordshire",
    "sg:tags":[
        "chauffeur",
        "car",
        "driven"
    ],
    "wof:name":"T I W Limousines",
    "wof:placetype":"venue"
},
  "geometry": {"coordinates":[-1.325764,52.048584],"type":"Point"}
}