{
  "type": "Feature",
  "properties": {
    "addr:full":"9 Berries Mt Bude Cornwall EX23 8AP",
    "addr:housenumber":"9",
    "addr:postcode":"ex23 8ap",
    "addr:street":"Berries Mt",
    "iso:country":"GB",
    "sg:address":"9 Berries Mt",
    "sg:city":"Bude",
    "sg:classifiers":[
        {
            "category":"Building & Trades",
            "subcategory":"Construction",
            "type":"Services"
        }
    ],
    "sg:phone":"+44 1288 354849",
    "sg:postcode":"EX23 8AP",
    "sg:province":"Cornwall",
    "sg:tags":[
        "joiner",
        "carpenter"
    ],
    "wof:name":"M Williams",
    "wof:placetype":"venue"
},
  "geometry": {"coordinates":[-4.5396208763,50.8233718872],"type":"Point"}
}