{
  "type": "Feature",
  "properties": {
    "addr:full":"10 Sutton Grove Sutton Surrey SM1 4LT",
    "addr:housenumber":"10",
    "addr:postcode":"sm1 4lt",
    "addr:street":"Sutton Grove",
    "iso:country":"GB",
    "sg:address":"10 Sutton Grove",
    "sg:city":"Sutton",
    "sg:classifiers":[
        {
            "category":"Professional",
            "subcategory":"Research",
            "type":"Services"
        }
    ],
    "sg:phone":"+44 70 9204 3128",
    "sg:postcode":"SM1 4LT",
    "sg:province":"Surrey",
    "sg:tags":[
        "market"
    ],
    "wof:name":"PBd Marketing Communications",
    "wof:placetype":"venue"
},
  "geometry": {"coordinates":[-0.1801580042,51.3633918762],"type":"Point"}
}