{
  "type": "Feature",
  "properties": {
    "iso:country":"GB",
    "sg:address":"North End Way",
    "sg:city":"London",
    "sg:classifiers":[
        {
            "category":"Restaurant",
            "type":"Food & Drink"
        }
    ],
    "sg:phone":"+44 20 7435 8885",
    "sg:postcode":"NW3 7ES",
    "sg:province":"Greater London",
    "wof:name":"Jack Straws Castle",
    "wof:placetype":"venue"
},
  "geometry": {"coordinates":[-0.1801099926,51.5627288818],"type":"Point"}
}