{
  "type": "Feature",
  "properties": {
    "addr:full":"Sawtry Way, Wyton Huntingdon Bedfordshire PE28 2DY",
    "addr:postcode":"pe28 2dy",
    "addr:street":"Sawtry Way",
    "iso:country":"GB",
    "sg:address":"Sawtry Way, Wyton",
    "sg:city":"Huntingdon",
    "sg:classifiers":[
        {
            "category":"Recreation",
            "subcategory":"Go Karts",
            "type":"Entertainment"
        }
    ],
    "sg:phone":"+44 1480 455132",
    "sg:postcode":"PE28 2DY",
    "sg:province":"Bedfordshire",
    "sg:tags":[
        "karting"
    ],
    "wof:name":"Upland Go-karting",
    "wof:placetype":"venue"
},
  "geometry": {"coordinates":[-0.131229,52.336124],"type":"Point"}
}