{
  "type": "Feature",
  "properties": {
    "iso:country":"GB",
    "sg:address":"4 Tinsley Cotts, Campains La, Deeping St. Nicholas",
    "sg:city":"Spalding",
    "sg:classifiers":[
        {
            "category":"Military Area",
            "subcategory":"Air Force Base",
            "type":"Public Place"
        }
    ],
    "sg:postcode":"PE11 3EX",
    "sg:province":"Lincolnshire",
    "sg:tags":[
        "taxi",
        "hire",
        "private"
    ],
    "wof:name":"Town & Country Taxis",
    "wof:placetype":"venue"
},
  "geometry": {"coordinates":[-0.1996500045,52.7328109741],"type":"Point"}
}