{
  "type": "Feature",
  "properties": {
    "addr:full":"51 School Lane, Walton Wakefield West Yorkshire WF2 6NR",
    "addr:housenumber":"51",
    "addr:postcode":"wf2 6nr",
    "addr:street":"School Lane;West",
    "iso:country":"GB",
    "sg:address":"51 School Lane, Walton",
    "sg:city":"Wakefield",
    "sg:classifiers":[
        {
            "category":"Education",
            "subcategory":"Library",
            "type":"Public Place"
        },
        {
            "category":"Government",
            "subcategory":"Office",
            "type":"Public Place"
        }
    ],
    "sg:phone":"+44 1924 303340",
    "sg:postcode":"WF2 6NR",
    "sg:province":"West Yorkshire",
    "sg:tags":[
        "book",
        "local"
    ],
    "wof:name":"Walton Library",
    "wof:placetype":"venue"
},
  "geometry": {"coordinates":[-1.4653010368,53.6489105225],"type":"Point"}
}