{
  "type": "Feature",
  "properties": {
    "iso:country":"GB",
    "sg:address":"11 Bridge Road, Litherland",
    "sg:city":"Liverpool",
    "sg:classifiers":[
        {
            "category":"Bars & Pubs",
            "type":"Food & Drink"
        }
    ],
    "sg:phone":"+44 151 949 1164",
    "sg:postcode":"L21 6PG",
    "sg:province":"Merseyside",
    "sg:tags":[
        "pubs",
        "inn"
    ],
    "wof:name":"Railway Hotel",
    "wof:placetype":"venue"
},
  "geometry": {"coordinates":[-3.005156,53.466896],"type":"Point"}
}