{
  "type": "Feature",
  "properties": {
    "addr:full":"58 Neville Rd Darlington Durham DL3 8NE",
    "addr:housenumber":"58",
    "addr:postcode":"dl3 8ne",
    "addr:street":"Neville Rd",
    "iso:country":"GB",
    "sg:address":"58 Neville Rd",
    "sg:city":"Darlington",
    "sg:classifiers":[
        {
            "category":"Building & Trades",
            "subcategory":"Construction",
            "type":"Services"
        }
    ],
    "sg:phone":"+44 7889 609285",
    "sg:postcode":"DL3 8NE",
    "sg:province":"Durham",
    "sg:tags":[
        "joiner",
        "carpenter"
    ],
    "wof:name":"J.Hughes Construction",
    "wof:placetype":"venue"
},
  "geometry": {"coordinates":[-1.575153,54.525131],"type":"Point"}
}