{
  "type": "Feature",
  "properties": {
    "iso:country":"GB",
    "sg:address":"Forth House 70 High Street, Waddesdon",
    "sg:city":"Aylesbury",
    "sg:classifiers":[
        {
            "category":"Professional",
            "subcategory":"Computer Services",
            "type":"Services"
        }
    ],
    "sg:phone":"+44 1296 652525",
    "sg:postcode":"HP18 0LB",
    "sg:province":"Buckinghamshire",
    "sg:tags":[
        "system",
        "software"
    ],
    "wof:name":"Zonal Retail Data Systems Ltd.",
    "wof:placetype":"venue"
},
  "geometry": {"coordinates":[-0.922787,51.845879],"type":"Point"}
}