{
  "type": "Feature",
  "properties": {
    "addr:full":"19 Finch Drive Braintree Essex CM7 2SF",
    "addr:housenumber":"19",
    "addr:postcode":"cm7 2sf",
    "addr:street":"Finch Drive",
    "iso:country":"GB",
    "sg:address":"19 Finch Drive",
    "sg:city":"Braintree",
    "sg:classifiers":[
        {
            "category":"Professional",
            "subcategory":"Business Services",
            "type":"Services"
        },
        {
            "category":"Manufacturing",
            "subcategory":"Electronics",
            "type":"Manufacturing & Wholesale Goods"
        },
        {
            "category":"Military Area",
            "subcategory":"Air Force Base",
            "type":"Public Place"
        }
    ],
    "sg:phone":"+44 1376 348115",
    "sg:postcode":"CM7 2SF",
    "sg:province":"Essex",
    "sg:tags":[
        "manufacture",
        "mnfr",
        "component",
        "agent",
        "equipment",
        "export",
        "import",
        "electronic"
    ],
    "sg:website":"http://www.kemtron.co.uk",
    "wof:name":"Kemtron Ltd",
    "wof:placetype":"venue"
},
  "geometry": {"coordinates":[0.538024,51.887043],"type":"Point"}
}