{
  "type": "Feature",
  "properties": {
    "addr:full":"Portland Ho, Longbrook St Exeter Devon EX4 6AB",
    "addr:postcode":"ex4 6ab",
    "addr:street":"Longbrook St",
    "iso:country":"GB",
    "sg:address":"Portland Ho, Longbrook St",
    "sg:city":"Exeter",
    "sg:classifiers":[
        {
            "category":"Professional",
            "subcategory":"Management & Consulting",
            "type":"Services"
        }
    ],
    "sg:phone":"+44 1392 499000",
    "sg:postcode":"EX4 6AB",
    "sg:province":"Devon",
    "sg:tags":[
        "consultant",
        "training"
    ],
    "wof:name":"Liaise International Training Ltd",
    "wof:placetype":"venue"
},
  "geometry": {"coordinates":[-3.5271599293,50.7270584106],"type":"Point"}
}