{
  "type": "Feature",
  "properties": {
    "addr:full":"Unit 61 Bridport Dorset DT6 3RR",
    "addr:housenumber":"unit 61",
    "addr:postcode":"dt6 3rr",
    "iso:country":"GB",
    "sg:address":"Unit 61",
    "sg:city":"Bridport",
    "sg:classifiers":[
        {
            "category":"Recreation",
            "subcategory":"Fishing",
            "type":"Entertainment"
        }
    ],
    "sg:phone":"+44 1308 427885",
    "sg:postcode":"DT6 3RR",
    "sg:province":"Dorset",
    "sg:tags":[
        "equipment",
        "angling"
    ],
    "wof:name":"Roderick Barr",
    "wof:placetype":"venue"
},
  "geometry": {"coordinates":[-2.7373890877,50.7455482483],"type":"Point"}
}