{
  "type": "Feature",
  "properties": {
    "iso:country":"GB",
    "sg:address":"1 East Bay, North Queensferry",
    "sg:city":"Inverkeithing",
    "sg:classifiers":[
        {
            "category":"Education",
            "subcategory":"Special Training",
            "type":"Public Place"
        }
    ],
    "sg:phone":"+44 1384 410051",
    "sg:postcode":"KY11 1JX",
    "sg:province":"Fife",
    "sg:tags":[
        "product",
        "centre"
    ],
    "wof:name":"Stick & Carrot Sales Training Ltd.",
    "wof:placetype":"venue"
},
  "geometry": {"coordinates":[-3.3976790905,56.0311317444],"type":"Point"}
}