{
  "type": "Feature",
  "properties": {
    "addr:full":"3 St Barnabas Road Cambridge Cambridgeshire CB1 2BU",
    "addr:housenumber":"3",
    "addr:postcode":"cb1 2bu",
    "addr:street":"St Barnabas Road",
    "iso:country":"GB",
    "sg:address":"3 St Barnabas Road",
    "sg:city":"Cambridge",
    "sg:classifiers":[
        {
            "category":"Real Estate",
            "subcategory":"Real Estate Operator",
            "type":"Services"
        },
        {
            "category":"Real Estate",
            "subcategory":"Real Estate Agent",
            "type":"Services"
        }
    ],
    "sg:postcode":"CB1 2BU",
    "sg:province":"Cambridgeshire",
    "sg:tags":[
        "property",
        "leasing"
    ],
    "wof:name":"MAYWOOD PROPERTIES LTD",
    "wof:placetype":"venue"
},
  "geometry": {"coordinates":[0.136048004,52.1972885132],"type":"Point"}
}