{
  "type": "Feature",
  "properties": {
    "addr:full":"Plot 16b Kingsmill Way, Hermitage Lane Industrial Estate Mansfield Nottinghamshire NG18 5ER",
    "addr:housenumber":"plot 16b;estate",
    "addr:postcode":"ng18 5er",
    "addr:street":"Kingsmill Way Hermitage Lane Industrial",
    "iso:country":"GB",
    "sg:address":"Plot 16b Kingsmill Way, Hermitage Lane Industrial Estate",
    "sg:city":"Mansfield",
    "sg:classifiers":[
        {
            "category":"Wholesale",
            "subcategory":"Furniture",
            "type":"Manufacturing & Wholesale Goods"
        }
    ],
    "sg:phone":"+44 1623 631356",
    "sg:postcode":"NG18 5ER",
    "sg:province":"Nottinghamshire",
    "sg:tags":[
        "shop",
        "fitting"
    ],
    "wof:name":"Stag Shopfronts Ltd.",
    "wof:placetype":"venue"
},
  "geometry": {"coordinates":[-1.2017430067,53.1440238953],"type":"Point"}
}