{
  "type": "Feature",
  "properties": {
    "addr:full":"Cradlehall Cottage Inverness Highland IV1 2NH",
    "addr:housenumber":"inverness",
    "addr:postcode":"iv1 2nh",
    "addr:street":"Highland",
    "iso:country":"GB",
    "sg:address":"Cradlehall Cottage",
    "sg:city":"Inverness",
    "sg:classifiers":[
        {
            "category":"Health Services",
            "subcategory":"Health Practitioner",
            "type":"Services"
        }
    ],
    "sg:phone":"+44 1463 238327",
    "sg:postcode":"IV1 2NH",
    "sg:province":"Highland",
    "sg:tags":[
        "herbalist"
    ],
    "wof:name":"Alison Fraser",
    "wof:placetype":"venue"
},
  "geometry": {"coordinates":[-4.1643490791,57.4726486206],"type":"Point"}
}