{
  "type": "Feature",
  "properties": {
    "addr:full":"The Mill House, 1 West Street, Coggeshall Colchester Essex CO6 1NN",
    "addr:housenumber":"1",
    "addr:postcode":"co6 1nn",
    "addr:street":"West Street",
    "iso:country":"GB",
    "sg:address":"The Mill House, 1 West Street, Coggeshall",
    "sg:city":"Colchester",
    "sg:classifiers":[
        {
            "category":"Real Estate",
            "subcategory":"Architect",
            "type":"Services"
        }
    ],
    "sg:phone":"+44 1376 562828",
    "sg:postcode":"CO6 1NN",
    "sg:province":"Essex",
    "wof:name":"Melville Dunbar Associates (U K) Ltd.",
    "wof:placetype":"venue"
},
  "geometry": {"coordinates":[0.6833059788,51.8705596924],"type":"Point"}
}