{
  "type": "Feature",
  "properties": {
    "addr:full":"Unit 20 Spedding Road, Fenton Industrial Estate Stoke-on-trent Staffordshire ST4 2ST",
    "addr:housenumber":"unit 20",
    "addr:postcode":"st4 2st",
    "addr:street":"Spedding Road;Industrial Estate",
    "iso:country":"GB",
    "sg:address":"Unit 20 Spedding Road, Fenton Industrial Estate",
    "sg:city":"Stoke-on-trent",
    "sg:classifiers":[
        {
            "category":"Building & Trades",
            "subcategory":"Cleaning & Sanitation",
            "type":"Services"
        },
        {
            "category":"Manufacturing",
            "subcategory":"Building Materials",
            "type":"Manufacturing & Wholesale Goods"
        }
    ],
    "sg:phone":"+44 1782 849111",
    "sg:postcode":"ST4 2ST",
    "sg:province":"Staffordshire",
    "sg:tags":[
        "shutter",
        "supp",
        "door",
        "manufacturer"
    ],
    "wof:name":"Doors for Industry Ltd.",
    "wof:placetype":"venue"
},
  "geometry": {"coordinates":[-2.1556940079,53.0106887817],"type":"Point"}
}