{
  "type": "Feature",
  "properties": {
    "addr:full":"39 Acre Lane, Heswall Wirral Merseyside CH60 1UN",
    "addr:housenumber":"39",
    "addr:postcode":"ch60 1un",
    "addr:street":"Acre Lane",
    "iso:country":"GB",
    "sg:address":"39 Acre Lane, Heswall",
    "sg:city":"Wirral",
    "sg:classifiers":[
        {
            "category":"Utilities",
            "subcategory":"Fuel Oil & Lpg",
            "type":"Services"
        }
    ],
    "sg:phone":"+44 151 342 9001",
    "sg:postcode":"CH60 1UN",
    "sg:province":"Merseyside",
    "sg:tags":[
        "distributor"
    ],
    "wof:name":"Dieselcard Ltd.",
    "wof:placetype":"venue"
},
  "geometry": {"coordinates":[-3.0757739544,53.3292541504],"type":"Point"}
}