{
  "type": "Feature",
  "properties": {
    "iso:country":"GB",
    "sg:address":"Laurel Bank, Motherby",
    "sg:city":"Penrith",
    "sg:classifiers":[
        {
            "category":"Professional",
            "subcategory":"Business Services",
            "type":"Services"
        }
    ],
    "sg:postcode":"CA11 0RL",
    "sg:province":"Cumbria",
    "sg:tags":[
        "hospitality",
        "corporate"
    ],
    "wof:name":"Silver Band Falconry",
    "wof:placetype":"venue"
},
  "geometry": {"coordinates":[-2.886222,54.648048],"type":"Point"}
}