{
  "type": "Feature",
  "properties": {
    "addr:full":"Unit 1, 202 Pershore Road South Birmingham West Midlands B30 3EU",
    "addr:housenumber":"unit 1 202",
    "addr:postcode":"b30 3eu",
    "addr:street":"Pershore Road South",
    "iso:country":"GB",
    "sg:address":"Unit 1, 202 Pershore Road South",
    "sg:city":"Birmingham",
    "sg:classifiers":[
        {
            "category":"Building & Trades",
            "subcategory":"Construction",
            "type":"Services"
        }
    ],
    "sg:postcode":"B30 3EU",
    "sg:province":"West Midlands",
    "sg:tags":[
        "glass",
        "replacement"
    ],
    "wof:name":"National Glass",
    "wof:placetype":"venue"
},
  "geometry": {"coordinates":[-1.928808,52.410728],"type":"Point"}
}