{
  "type": "Feature",
  "properties": {
    "iso:country":"GB",
    "sg:address":"199 Dudley Rd, Edgbaston",
    "sg:city":"Birmingham",
    "sg:classifiers":[
        {
            "category":"Taxi",
            "type":"Transportation"
        }
    ],
    "sg:phone":"+44 121 455 8888",
    "sg:postcode":"B18 7QY",
    "sg:province":"West Midlands",
    "sg:tags":[
        "mini",
        "cab"
    ],
    "wof:name":"Yellow Cars",
    "wof:placetype":"venue"
},
  "geometry": {"coordinates":[-1.9371789694,52.4865989685],"type":"Point"}
}