{
  "type": "Feature",
  "properties": {
    "addr:full":"17 Graveney Close, Cliffe Rochester Kent ME3 8LB",
    "addr:housenumber":"17",
    "addr:postcode":"me3 8lb",
    "addr:street":"Graveney Close",
    "iso:country":"GB",
    "sg:address":"17 Graveney Close, Cliffe",
    "sg:city":"Rochester",
    "sg:classifiers":[
        {
            "category":"Building & Trades",
            "subcategory":"Construction",
            "type":"Services"
        }
    ],
    "sg:postcode":"ME3 8LB",
    "sg:province":"Kent",
    "sg:tags":[
        "builder"
    ],
    "wof:name":"R A Jack",
    "wof:placetype":"venue"
},
  "geometry": {"coordinates":[0.503167,51.430058],"type":"Point"}
}