{
  "type": "Feature",
  "properties": {
    "iso:country":"GB",
    "sg:address":"162 High St",
    "sg:city":"Epping",
    "sg:classifiers":[
        {
            "category":"Shopping",
            "subcategory":"Pawn Shop",
            "type":"Retail Goods"
        }
    ],
    "sg:phone":"+44 1992 573628",
    "sg:postcode":"CM16 4AQ",
    "sg:province":"Essex",
    "sg:tags":[
        "pawnbroker"
    ],
    "wof:name":"Bowmans Of Epping Ltd",
    "wof:placetype":"venue"
},
  "geometry": {"coordinates":[0.111281,51.69873],"type":"Point"}
}