{
  "type": "Feature",
  "properties": {
    "iso:country":"GB",
    "sg:address":"223 Halliwell Rd",
    "sg:city":"Bolton",
    "sg:classifiers":[
        {
            "category":"Professional",
            "subcategory":"Engineering",
            "type":"Services"
        },
        {
            "category":"Building & Trades",
            "subcategory":"Plumbing",
            "type":"Services"
        },
        {
            "category":"Building & Trades",
            "subcategory":"Construction",
            "type":"Services"
        }
    ],
    "sg:phone":"+44 1204 303726",
    "sg:postcode":"BL1 3NT",
    "sg:province":"Lancashire",
    "sg:tags":[
        "builder",
        "gas",
        "heating",
        "engineer"
    ],
    "wof:name":"B M (Bolton) Ltd",
    "wof:placetype":"venue"
},
  "geometry": {"coordinates":[-2.436459,53.591827],"type":"Point"}
}