{
  "type": "Feature",
  "properties": {
    "iso:country":"GB",
    "sg:address":"12 Churchill Way",
    "sg:city":"Cardiff",
    "sg:classifiers":[
        {
            "category":"Personal",
            "subcategory":"Beauty Salon",
            "type":"Services"
        }
    ],
    "sg:phone":"+44 29 2038 7220",
    "sg:postcode":"CF1 4DX",
    "sg:province":"Cardiff",
    "sg:tags":[
        "unisex",
        "hairdresser"
    ],
    "wof:name":"Lazarou Bros",
    "wof:placetype":"venue"
},
  "geometry": {"coordinates":[-3.1731350422,51.4818077087],"type":"Point"}
}