{
  "type": "Feature",
  "properties": {
    "iso:country":"GB",
    "sg:address":"42 Stirling Close, Yate",
    "sg:city":"Bristol",
    "sg:classifiers":[
        {
            "category":"Building & Trades",
            "subcategory":"Construction",
            "type":"Services"
        }
    ],
    "sg:phone":"+44 1454 329672",
    "sg:postcode":"BS37 5UJ",
    "sg:province":"Gloucestershire",
    "sg:tags":[
        "builder"
    ],
    "wof:name":"Cdm Upholstery",
    "wof:placetype":"venue"
},
  "geometry": {"coordinates":[-2.419415,51.550797],"type":"Point"}
}