{
  "type": "Feature",
  "properties": {
    "addr:full":"The Grange, Butterwick Road Scunthorpe Lincolnshire DN17 3PP",
    "addr:postcode":"dn17 3pp",
    "addr:street":"Butterwick Road",
    "iso:country":"GB",
    "sg:address":"The Grange, Butterwick Road",
    "sg:city":"Scunthorpe",
    "sg:classifiers":[
        {
            "category":"Building & Trades",
            "subcategory":"Construction",
            "type":"Services"
        }
    ],
    "sg:phone":"+44 1724 762851",
    "sg:postcode":"DN17 3PP",
    "sg:province":"Lincolnshire",
    "sg:tags":[
        "builder"
    ],
    "wof:name":"R W Price Ltd.",
    "wof:placetype":"venue"
},
  "geometry": {"coordinates":[-0.716423,53.536072],"type":"Point"}
}