{
  "type": "Feature",
  "properties": {
    "addr:full":"33 Chiswick High Road, Chiswick London Greater London W4 4HS",
    "addr:housenumber":"33",
    "addr:postcode":"w4 4hs",
    "addr:street":"Chiswick High Road",
    "iso:country":"GB",
    "sg:address":"33 Chiswick High Road, Chiswick",
    "sg:city":"London",
    "sg:classifiers":[
        {
            "category":"Arts & Performance",
            "subcategory":"Theater",
            "type":"Entertainment"
        }
    ],
    "sg:phone":"+44 20 8994 4969",
    "sg:postcode":"W4 4HS",
    "sg:province":"Greater London",
    "sg:tags":[
        "theatre"
    ],
    "wof:name":"Salamander Theatre",
    "wof:placetype":"venue"
},
  "geometry": {"coordinates":[-0.247003004,51.4934501648],"type":"Point"}
}