{
  "type": "Feature",
  "properties": {
    "addr:full":"68 St Matthews Drive, Sutton Bridge Spalding Cambridgeshire PE12 9RJ",
    "addr:housenumber":"68",
    "addr:postcode":"pe12 9rj",
    "addr:street":"St Matthews Drive",
    "iso:country":"GB",
    "sg:address":"68 St Matthews Drive, Sutton Bridge",
    "sg:city":"Spalding",
    "sg:classifiers":[
        {
            "category":"Social Services",
            "subcategory":"Adult Care",
            "type":"Services"
        },
        {
            "category":"Government",
            "subcategory":"Office",
            "type":"Public Place"
        }
    ],
    "sg:phone":"+44 1406 350641",
    "sg:postcode":"PE12 9RJ",
    "sg:province":"Cambridgeshire",
    "sg:tags":[
        "housing",
        "local",
        "sheltered"
    ],
    "wof:name":"St Matthews Drive Sheltered Housing",
    "wof:placetype":"venue"
},
  "geometry": {"coordinates":[0.188034,52.772179],"type":"Point"}
}