{
  "type": "Feature",
  "properties": {
    "addr:full":"Cemetery Lodge, Alexandra Road Mold Denbighshire CH7 1HJ",
    "addr:postcode":"ch7 1hj",
    "addr:street":"Alexandra Road",
    "iso:country":"GB",
    "sg:address":"Cemetery Lodge, Alexandra Road",
    "sg:city":"Mold",
    "sg:classifiers":[
        {
            "category":"Retail",
            "subcategory":"Funeral Services",
            "type":"Services"
        }
    ],
    "sg:phone":"+44 1352 753820",
    "sg:postcode":"CH7 1HJ",
    "sg:province":"Denbighshire",
    "sg:tags":[
        "cemetery",
        "crematorium"
    ],
    "wof:name":"Mold Town Cemetery",
    "wof:placetype":"venue"
},
  "geometry": {"coordinates":[-3.1399838924,53.1638679504],"type":"Point"}
}