{
  "type": "Feature",
  "properties": {
    "addr:full":"Linburn House, 342 Kilburn High Road Kilburn Greater London NW6 2QJ",
    "addr:housenumber":"342",
    "addr:postcode":"nw6 2qj",
    "addr:street":"Kilburn High Road",
    "iso:country":"GB",
    "sg:address":"Linburn House, 342 Kilburn High Road",
    "sg:city":"Kilburn",
    "sg:classifiers":[
        {
            "category":"Taxi",
            "type":"Transportation"
        }
    ],
    "sg:postcode":"NW6 2QJ",
    "sg:province":"Greater London",
    "sg:tags":[
        "mini",
        "cab"
    ],
    "wof:name":"Capital Cars Express",
    "wof:placetype":"venue"
},
  "geometry": {"coordinates":[-0.202435,51.545929],"type":"Point"}
}