{
  "type": "Feature",
  "properties": {
    "iso:country":"GB",
    "sg:address":"10 Ashfield Road",
    "sg:city":"Chorley",
    "sg:classifiers":[
        {
            "category":"Professional",
            "subcategory":"Lawyer & Legal Services",
            "type":"Services"
        }
    ],
    "sg:phone":"+44 1257 272222",
    "sg:postcode":"PR7 1LJ",
    "sg:province":"Lancashire",
    "sg:tags":[
        "solicitor"
    ],
    "wof:name":"Stanley H Cross & Co",
    "wof:placetype":"venue"
},
  "geometry": {"coordinates":[-2.637751,53.653175],"type":"Point"}
}