{
  "type": "Feature",
  "properties": {
    "addr:full":"36 Point Street Stornoway Eilean Siar HS1 2XF",
    "addr:housenumber":"36",
    "addr:postcode":"hs1 2xf",
    "addr:street":"Point Street",
    "iso:country":"GB",
    "sg:address":"36 Point Street",
    "sg:city":"Stornoway",
    "sg:classifiers":[
        {
            "category":"Shopping",
            "subcategory":"Department Store",
            "type":"Retail Goods"
        },
        {
            "category":"Shopping",
            "subcategory":"Gifts & Souvenirs",
            "type":"Retail Goods"
        }
    ],
    "sg:phone":"+44 1851 702202",
    "sg:postcode":"HS1 2XF",
    "sg:province":"Eilean Siar",
    "sg:tags":[
        "shop"
    ],
    "wof:name":"This 'N' That",
    "wof:placetype":"venue"
},
  "geometry": {"coordinates":[-6.388449192,58.2090759277],"type":"Point"}
}