{
  "type": "Feature",
  "properties": {
    "addr:full":"4 Oaks House Sutton Coldfield Staffordshire B74 2TZ",
    "addr:postcode":"b74 2tz",
    "addr:street":"4",
    "iso:country":"GB",
    "sg:address":"4 Oaks House",
    "sg:city":"Sutton Coldfield",
    "sg:classifiers":[
        {
            "category":"Professional",
            "subcategory":"Computer Services",
            "type":"Services"
        }
    ],
    "sg:phone":"+44 121 308 6888",
    "sg:postcode":"B74 2TZ",
    "sg:province":"Staffordshire",
    "sg:tags":[
        "system",
        "software"
    ],
    "wof:name":"Ordina U K Ltd.",
    "wof:placetype":"venue"
},
  "geometry": {"coordinates":[-1.8292399645,52.5786399841],"type":"Point"}
}