{
  "type": "Feature",
  "properties": {
    "iso:country":"GB",
    "sg:address":"Sidmouth Road",
    "sg:city":"Exeter",
    "sg:classifiers":[
        {
            "category":"Wholesale",
            "subcategory":"Machinery & Supplies",
            "type":"Manufacturing & Wholesale Goods"
        },
        {
            "category":"Building & Trades",
            "subcategory":"Equipment Rental",
            "type":"Services"
        }
    ],
    "sg:phone":"+44 1395 232007",
    "sg:postcode":"EX5 1DR",
    "sg:province":"Devon",
    "sg:tags":[
        "plant",
        "industrial",
        "commercial"
    ],
    "wof:name":"Finning",
    "wof:placetype":"venue"
},
  "geometry": {"coordinates":[-3.45589,50.709255],"type":"Point"}
}