{
  "type": "Feature",
  "properties": {
    "addr:full":"Unit 5e Bear Brand Complex, Alison Road Liverpool Merseyside L25 7SF",
    "addr:housenumber":"5e",
    "addr:postcode":"l25 7sf",
    "addr:street":"Bear Brand;Alison Road",
    "iso:country":"GB",
    "sg:address":"Unit 5e Bear Brand Complex, Alison Road",
    "sg:city":"Liverpool",
    "sg:classifiers":[
        {
            "category":"Home & Garden",
            "subcategory":"Carpets & Floor Coverings",
            "type":"Retail Goods"
        }
    ],
    "sg:phone":"+44 151 421 0031",
    "sg:postcode":"L25 7SF",
    "sg:province":"Merseyside",
    "sg:tags":[
        "rubber",
        "plastic"
    ],
    "wof:name":"John Dodwell",
    "wof:placetype":"venue"
},
  "geometry": {"coordinates":[-2.87036,53.373878],"type":"Point"}
}