{
  "type": "Feature",
  "properties": {
    "addr:full":"9 Brunswick Rd Shoreham By Sea West Sussex BN43 5WA",
    "addr:housenumber":"9",
    "addr:postcode":"bn43 5wa",
    "addr:street":"Brunswick Rd",
    "iso:country":"GB",
    "sg:address":"9 Brunswick Rd",
    "sg:city":"Shoreham By Sea",
    "sg:classifiers":[
        {
            "category":"Manufacturing",
            "subcategory":"Jewelry",
            "type":"Manufacturing & Wholesale Goods"
        }
    ],
    "sg:phone":"+44 1273 464904",
    "sg:postcode":"BN43 5WA",
    "sg:province":"West Sussex",
    "sg:tags":[
        "repair",
        "jewellery"
    ],
    "wof:name":"Stephen English",
    "wof:placetype":"venue"
},
  "geometry": {"coordinates":[-0.272739,50.833813],"type":"Point"}
}