{
  "type": "Feature",
  "properties": {
    "addr:full":"7a Church Street Christchurch Dorset BH23 1BW",
    "addr:housenumber":"7a",
    "addr:postcode":"bh23 1bw",
    "addr:street":"Church Street",
    "iso:country":"GB",
    "sg:address":"7a Church Street",
    "sg:city":"Christchurch",
    "sg:classifiers":[
        {
            "category":"Shopping",
            "subcategory":"Clothing, Apparel, & Fashions",
            "type":"Retail Goods"
        }
    ],
    "sg:phone":"+44 1202 483295",
    "sg:postcode":"BH23 1BW",
    "sg:province":"Dorset",
    "sg:tags":[
        "shop"
    ],
    "wof:name":"The Ladies Shop",
    "wof:placetype":"venue"
},
  "geometry": {"coordinates":[-1.7754839659,50.7334632874],"type":"Point"}
}