{
  "type": "Feature",
  "properties": {
    "iso:country":"GB",
    "sg:address":"27 Prince St",
    "sg:city":"Walsall",
    "sg:classifiers":[
        {
            "category":"Shopping",
            "subcategory":"Computers & Home Electronics",
            "type":"Retail Goods"
        }
    ],
    "sg:phone":"+44 1922 644611",
    "sg:postcode":"WS2 9JJ",
    "sg:province":"West Midlands",
    "sg:tags":[
        "aerial",
        "television",
        "radio"
    ],
    "wof:name":"Walsall Aerials",
    "wof:placetype":"venue"
},
  "geometry": {"coordinates":[-1.996934,52.574436],"type":"Point"}
}