{
  "type": "Feature",
  "properties": {
    "iso:country":"GB",
    "sg:address":"2 Lower Hall Drive",
    "sg:city":"Liversedge",
    "sg:classifiers":[
        {
            "category":"Building & Trades",
            "subcategory":"Construction",
            "type":"Services"
        }
    ],
    "sg:phone":"+44 1924 404129",
    "sg:postcode":"WF15 6PB",
    "sg:province":"West Yorkshire",
    "sg:tags":[
        "joiner",
        "carpenter"
    ],
    "wof:name":"R P Joinery",
    "wof:placetype":"venue"
},
  "geometry": {"coordinates":[-1.70272,53.710762],"type":"Point"}
}