{
  "type": "Feature",
  "properties": {
    "addr:full":"159b Wadham Road London Greater London E17 4HU",
    "addr:housenumber":"159b",
    "addr:postcode":"e17 4hu",
    "addr:street":"Wadham Road",
    "iso:country":"GB",
    "sg:address":"159b Wadham Road",
    "sg:city":"London",
    "sg:classifiers":[
        {
            "category":"Food & Beverages",
            "subcategory":"Bakery",
            "type":"Retail Goods"
        }
    ],
    "sg:postcode":"E17 4HU",
    "sg:province":"Greater London",
    "sg:tags":[
        "baker"
    ],
    "wof:name":"Tea Time Cakes",
    "wof:placetype":"venue"
},
  "geometry": {"coordinates":[-0.007421,51.600887],"type":"Point"}
}