{
  "type": "Feature",
  "properties": {
    "addr:full":"Unit 525, Thorp Arch Trading Estate, Thorp Arch Wetherby West Yorkshire LS23 7BJ",
    "addr:housenumber":"525",
    "addr:postcode":"ls23 7bj",
    "addr:street":"Thorp Arch Trading Estate;Arch",
    "iso:country":"GB",
    "sg:address":"Unit 525, Thorp Arch Trading Estate, Thorp Arch",
    "sg:city":"Wetherby",
    "sg:classifiers":[
        {
            "category":"Professional",
            "subcategory":"Printing & Photocopies",
            "type":"Services"
        }
    ],
    "sg:phone":"+44 1937 849998",
    "sg:postcode":"LS23 7BJ",
    "sg:province":"West Yorkshire",
    "sg:tags":[
        "typesetter"
    ],
    "wof:name":"A & C Overseas Trading Ltd",
    "wof:placetype":"venue"
},
  "geometry": {"coordinates":[-1.342299,53.907715],"type":"Point"}
}