{
  "type": "Feature",
  "properties": {
    "addr:full":"Unit 4 Harbour Road Inverness Highland IV1 1SY",
    "addr:housenumber":"unit 4",
    "addr:postcode":"iv1 1sy",
    "addr:street":"Harbour Road",
    "iso:country":"GB",
    "sg:address":"Unit 4 Harbour Road",
    "sg:city":"Inverness",
    "sg:classifiers":[
        {
            "category":"Retail",
            "subcategory":"Auto Repair",
            "type":"Services"
        }
    ],
    "sg:phone":"+44 1463 712220",
    "sg:postcode":"IV1 1SY",
    "sg:province":"Highland",
    "sg:tags":[
        "modification",
        "garage"
    ],
    "wof:name":"Auto Services",
    "wof:placetype":"venue"
},
  "geometry": {"coordinates":[-4.227230072,57.4860076904],"type":"Point"}
}