{
  "type": "Feature",
  "properties": {
    "addr:full":"74 Nolton St Bridgend Bridgend CF31 3BP",
    "addr:housenumber":"74",
    "addr:postcode":"cf31 3bp",
    "addr:street":"Nolton St",
    "iso:country":"GB",
    "sg:address":"74 Nolton St",
    "sg:city":"Bridgend",
    "sg:classifiers":[
        {
            "category":"Home & Garden",
            "subcategory":"Furniture",
            "type":"Retail Goods"
        }
    ],
    "sg:phone":"+44 1656 662649",
    "sg:postcode":"CF31 3BP",
    "sg:province":"Bridgend",
    "wof:name":"Pine Centre The",
    "wof:placetype":"venue"
},
  "geometry": {"coordinates":[-3.5767951012,51.5033149719],"type":"Point"}
}