{
  "type": "Feature",
  "properties": {
    "addr:full":"Brookleaze, Stockwood Vale, Keynsham Bristol City of Bristol BS31 2AL",
    "addr:postcode":"bs31 2al",
    "addr:street":"Stockwood Vale",
    "iso:country":"GB",
    "sg:address":"Brookleaze, Stockwood Vale, Keynsham",
    "sg:city":"Bristol",
    "sg:classifiers":[
        {
            "category":"Retail",
            "subcategory":"Auto Repair",
            "type":"Services"
        }
    ],
    "sg:phone":"+44 117 986 9065",
    "sg:postcode":"BS31 2AL",
    "sg:province":"City of Bristol",
    "sg:tags":[
        "modification",
        "garage"
    ],
    "wof:name":"Vale Engineering",
    "wof:placetype":"venue"
},
  "geometry": {"coordinates":[-2.51138,51.418331],"type":"Point"}
}