{
  "type": "Feature",
  "properties": {
    "iso:country":"GB",
    "sg:address":"Mill Lane",
    "sg:city":"Lymm",
    "sg:classifiers":[
        {
            "category":"Restaurant",
            "type":"Food & Drink"
        }
    ],
    "sg:phone":"+44 1925 753657",
    "sg:postcode":"WA13 9SD",
    "sg:province":"Cheshire",
    "wof:name":"Laboheme",
    "wof:placetype":"venue"
},
  "geometry": {"coordinates":[-2.449048996,53.3923568726],"type":"Point"}
}