{
  "type": "Feature",
  "properties": {
    "iso:country":"GB",
    "sg:address":"84 The Gro",
    "sg:city":"West Wickham",
    "sg:classifiers":[
        {
            "category":"Social Services",
            "subcategory":"Job Training",
            "type":"Services"
        },
        {
            "category":"Professional",
            "subcategory":"Art Services",
            "type":"Services"
        }
    ],
    "sg:postcode":"BR4 9JT",
    "sg:province":"Kent",
    "sg:tags":[
        "translator",
        "photographer",
        "interpreter"
    ],
    "wof:name":"Linter,Graham,",
    "wof:placetype":"venue"
},
  "geometry": {"coordinates":[-0.0182980001,51.3719291687],"type":"Point"}
}