{
  "type": "Feature",
  "properties": {
    "addr:full":"96 Leigh Road Leigh-on-sea Essex SS9 1BU",
    "addr:housenumber":"96",
    "addr:postcode":"ss9 1bu",
    "addr:street":"Leigh Road",
    "iso:country":"GB",
    "sg:address":"96 Leigh Road",
    "sg:city":"Leigh-on-sea",
    "sg:classifiers":[
        {
            "category":"Shopping",
            "subcategory":"Antiques",
            "type":"Retail Goods"
        }
    ],
    "sg:postcode":"SS9 1BU",
    "sg:province":"Essex",
    "wof:name":"Magpie Antiques",
    "wof:placetype":"venue"
},
  "geometry": {"coordinates":[0.666942,51.543308],"type":"Point"}
}