{
  "type": "Feature",
  "properties": {
    "addr:full":"Unit 22, Vaulcan House, Vaulcan Rd Leicester Leicestershire LE5 3EF",
    "addr:housenumber":"unit 22",
    "addr:postcode":"le5 3ef",
    "addr:street":"Vaulcan Rd",
    "iso:country":"GB",
    "sg:address":"Unit 22, Vaulcan House, Vaulcan Rd",
    "sg:city":"Leicester",
    "sg:classifiers":[
        {
            "category":"Wholesale",
            "subcategory":"Machinery & Supplies",
            "type":"Manufacturing & Wholesale Goods"
        }
    ],
    "sg:postcode":"LE5 3EF",
    "sg:province":"Leicestershire",
    "sg:tags":[
        "hydraulic"
    ],
    "wof:name":"Eagle Industrial Supplies Ltd",
    "wof:placetype":"venue"
},
  "geometry": {"coordinates":[-1.1145190001,52.6386985779],"type":"Point"}
}