{
  "type": "Feature",
  "properties": {
    "addr:full":"77 Frederick Pl Woolwich Greater London SE18 7BH",
    "addr:housenumber":"77",
    "addr:postcode":"se18 7bh",
    "addr:street":"Frederick Pl",
    "iso:country":"GB",
    "sg:address":"77 Frederick Pl",
    "sg:city":"Woolwich",
    "sg:classifiers":[
        {
            "category":"Manufacturing",
            "subcategory":"Petroleum Products",
            "type":"Manufacturing & Wholesale Goods"
        }
    ],
    "sg:phone":"+44 20 8317 8862",
    "sg:postcode":"SE18 7BH",
    "sg:province":"Greater London",
    "sg:tags":[
        "double",
        "glazing"
    ],
    "wof:name":"R M V Builders & Double Glazing",
    "wof:placetype":"venue"
},
  "geometry": {"coordinates":[0.0710280016,51.4852905273],"type":"Point"}
}