{
  "type": "Feature",
  "properties": {
    "iso:country":"GB",
    "sg:address":"46 Kepler Road",
    "sg:city":"Clapham",
    "sg:classifiers":[
        {
            "category":"Taxi",
            "type":"Transportation"
        }
    ],
    "sg:phone":"+44 20 7274 4641",
    "sg:postcode":"SW4 7PQ",
    "sg:province":"Greater London",
    "sg:tags":[
        "mini",
        "cab"
    ],
    "wof:name":"Womens Safe Transport",
    "wof:placetype":"venue"
},
  "geometry": {"coordinates":[-0.125608,51.461292],"type":"Point"}
}