{
  "type": "Feature",
  "properties": {
    "addr:full":"5 Edington Square Witney Oxfordshire OX28 5YT",
    "addr:housenumber":"5",
    "addr:postcode":"ox28 5yt",
    "addr:street":"Edington Square",
    "iso:country":"GB",
    "sg:address":"5 Edington Square",
    "sg:city":"Witney",
    "sg:classifiers":[
        {
            "category":"Farming",
            "subcategory":"Nursery",
            "type":"Manufacturing & Wholesale Goods"
        }
    ],
    "sg:phone":"+44 1993 708822",
    "sg:postcode":"OX28 5YT",
    "sg:province":"Oxfordshire",
    "sg:tags":[
        "creche"
    ],
    "wof:name":"Stepping Stones",
    "wof:placetype":"venue"
},
  "geometry": {"coordinates":[-1.508944,51.786476],"type":"Point"}
}