{
  "type": "Feature",
  "properties": {
    "iso:country":"GB",
    "sg:address":"Chapel Walk, Frederick Street, Catcliffe",
    "sg:city":"Rotherham",
    "sg:classifiers":[
        {
            "category":"Social Services",
            "subcategory":"Adult Care",
            "type":"Services"
        }
    ],
    "sg:phone":"+44 1709 369588",
    "sg:postcode":"S60 5TT",
    "sg:province":"South Yorkshire",
    "sg:tags":[
        "housing",
        "sheltered"
    ],
    "wof:name":"Chapel Walk Sheltered Housing",
    "wof:placetype":"venue"
},
  "geometry": {"coordinates":[-1.361244,53.392403],"type":"Point"}
}