{
  "type": "Feature",
  "properties": {
    "addr:full":"Long Lane, Walton Liverpool Merseyside L9 6AD",
    "addr:postcode":"l9 6ad",
    "addr:street":"Long Lane",
    "iso:country":"GB",
    "sg:address":"Long Lane, Walton",
    "sg:city":"Liverpool",
    "sg:classifiers":[
        {
            "category":"Autos & Motor Vehicles",
            "subcategory":"Automobile Sales",
            "type":"Retail Goods"
        }
    ],
    "sg:postcode":"L9 6AD",
    "sg:province":"Merseyside",
    "sg:tags":[
        "car"
    ],
    "wof:name":"Mike's Autos",
    "wof:placetype":"venue"
},
  "geometry": {"coordinates":[-2.922549,53.456291],"type":"Point"}
}