{
  "type": "Feature",
  "properties": {
    "addr:full":"Unit 10 Summerson Road, Bleek Hall Milton Keynes Buckinghamshire MK6 1LE",
    "addr:housenumber":"unit 10",
    "addr:postcode":"mk6 1le",
    "addr:street":"Summerson Road Bleek",
    "iso:country":"GB",
    "sg:address":"Unit 10 Summerson Road, Bleek Hall",
    "sg:city":"Milton Keynes",
    "sg:classifiers":[
        {
            "category":"Home & Garden",
            "subcategory":"Building Materials",
            "type":"Retail Goods"
        }
    ],
    "sg:phone":"+44 1908 378661",
    "sg:postcode":"MK6 1LE",
    "sg:province":"Buckinghamshire",
    "sg:tags":[
        "garage",
        "door"
    ],
    "wof:name":"John Briars",
    "wof:placetype":"venue"
},
  "geometry": {"coordinates":[-0.747974,52.018185],"type":"Point"}
}