{
  "type": "Feature",
  "properties": {
    "addr:full":"125a Lavender Hill London Greater London SW11 5QJ",
    "addr:housenumber":"125a",
    "addr:postcode":"sw11 5qj",
    "addr:street":"Lavender Hill",
    "iso:country":"GB",
    "sg:address":"125a Lavender Hill",
    "sg:city":"London",
    "sg:classifiers":[
        {
            "category":"Home & Garden",
            "subcategory":"Household Appliances",
            "type":"Retail Goods"
        }
    ],
    "sg:phone":"+44 20 7228 3605",
    "sg:postcode":"SW11 5QJ",
    "sg:province":"Greater London",
    "sg:tags":[
        "cleaner",
        "domestic",
        "vacuum"
    ],
    "wof:name":"Western (Distributors) Ltd",
    "wof:placetype":"venue"
},
  "geometry": {"coordinates":[-0.1565269977,51.4653701782],"type":"Point"}
}