{
  "type": "Feature",
  "properties": {
    "iso:country":"GB",
    "sg:address":"64 Long St",
    "sg:city":"Atherstone",
    "sg:classifiers":[
        {
            "category":"Shopping",
            "subcategory":"Optician",
            "type":"Retail Goods"
        }
    ],
    "sg:postcode":"CV9 1AU",
    "sg:province":"Leicestershire",
    "wof:name":"D & L Opticians",
    "wof:placetype":"venue"
},
  "geometry": {"coordinates":[-1.5478769541,52.5778656006],"type":"Point"}
}