{
  "type": "Feature",
  "properties": {
    "addr:full":"350 Kings Rd Chelsea Greater London SW3 5UU",
    "addr:housenumber":"350",
    "addr:postcode":"sw3 5uu",
    "addr:street":"Kings Rd",
    "iso:country":"GB",
    "sg:address":"350 Kings Rd",
    "sg:city":"Chelsea",
    "sg:classifiers":[
        {
            "category":"Food & Beverages",
            "subcategory":"Groceries & Convenience Stores",
            "type":"Retail Goods"
        }
    ],
    "sg:phone":"+44 20 7352 2876",
    "sg:postcode":"SW3 5UU",
    "sg:province":"Greater London",
    "wof:name":"Spar",
    "wof:placetype":"venue"
},
  "geometry": {"coordinates":[-0.175741002,51.4845199585],"type":"Point"}
}