{
  "type": "Feature",
  "properties": {
    "iso:country":"GB",
    "sg:address":"33 Bingham Avenue",
    "sg:city":"Poole",
    "sg:classifiers":[
        {
            "category":"Professional",
            "subcategory":"Management & Consulting",
            "type":"Services"
        }
    ],
    "sg:postcode":"BH14 8ND",
    "sg:province":"Dorset",
    "sg:tags":[
        "consultant",
        "business"
    ],
    "wof:name":"M B A Consultants",
    "wof:placetype":"venue"
},
  "geometry": {"coordinates":[-1.936874032,50.7070655823],"type":"Point"}
}