{
  "type": "Feature",
  "properties": {
    "addr:full":"Three Day Market, Ainsworth Street Blackburn Lancashire BB1 6AF",
    "addr:postcode":"bb1 6af",
    "addr:street":"Ainsworth Street",
    "iso:country":"GB",
    "sg:address":"Three Day Market, Ainsworth Street",
    "sg:city":"Blackburn",
    "sg:classifiers":[
        {
            "category":"Shopping",
            "subcategory":"Luggage & Leather Goods",
            "type":"Retail Goods"
        }
    ],
    "sg:phone":"+44 1254 278280",
    "sg:postcode":"BB1 6AF",
    "sg:province":"Lancashire",
    "wof:name":"Blackburn Bag & Baggage Co.",
    "wof:placetype":"venue"
},
  "geometry": {"coordinates":[-2.480399,53.748516],"type":"Point"}
}