{
  "type": "Feature",
  "properties": {
    "iso:country":"GB",
    "sg:address":"48 Cavendish Avenue",
    "sg:city":"Cambridge",
    "sg:classifiers":[
        {
            "category":"Retail",
            "subcategory":"Storage",
            "type":"Services"
        }
    ],
    "sg:phone":"+44 1223 242506",
    "sg:postcode":"CB1 7UT",
    "sg:province":"Cambridgeshire",
    "sg:tags":[
        "household",
        "removal"
    ],
    "wof:name":"Philip Richardson",
    "wof:placetype":"venue"
},
  "geometry": {"coordinates":[0.146576,52.185188],"type":"Point"}
}