{
  "type": "Feature",
  "properties": {
    "addr:full":"18 High Street Halstead Essex CO9 2AP",
    "addr:housenumber":"18",
    "addr:postcode":"co9 2ap",
    "addr:street":"High Street",
    "iso:country":"GB",
    "sg:address":"18 High Street",
    "sg:city":"Halstead",
    "sg:classifiers":[
        {
            "category":"Personal",
            "subcategory":"Beauty Salon",
            "type":"Services"
        }
    ],
    "sg:postcode":"CO9 2AP",
    "sg:province":"Essex",
    "sg:tags":[
        "unisex",
        "hairdresser"
    ],
    "wof:name":"Karl L Lindekam",
    "wof:placetype":"venue"
},
  "geometry": {"coordinates":[0.637812,51.94495],"type":"Point"}
}