{
  "type": "Feature",
  "properties": {
    "iso:country":"GB",
    "sg:address":"18 Bovingdon Road",
    "sg:city":"London",
    "sg:classifiers":[
        {
            "category":"Food & Beverages",
            "subcategory":"Liquor & Beverages",
            "type":"Retail Goods"
        },
        {
            "category":"Wholesale",
            "subcategory":"Electrical",
            "type":"Manufacturing & Wholesale Goods"
        }
    ],
    "sg:phone":"+44 20 7736 4953",
    "sg:postcode":"SW6 2AP",
    "sg:province":"Greater London",
    "sg:tags":[
        "equipment",
        "beer",
        "refrigeration",
        "spirit",
        "wines"
    ],
    "wof:name":"Montclare & Co",
    "wof:placetype":"venue"
},
  "geometry": {"coordinates":[-0.190601,51.474693],"type":"Point"}
}