{
  "type": "Feature",
  "properties": {
    "addr:full":"Soughbridge Mill, Colne Road, Earby Barnoldswick Lancashire BB18 6RT",
    "addr:postcode":"bb18 6rt",
    "addr:street":"Colne Road",
    "iso:country":"GB",
    "sg:address":"Soughbridge Mill, Colne Road, Earby",
    "sg:city":"Barnoldswick",
    "sg:classifiers":[
        {
            "category":"Retail",
            "subcategory":"Auto Repair",
            "type":"Services"
        }
    ],
    "sg:postcode":"BB18 6RT",
    "sg:province":"Lancashire",
    "sg:tags":[
        "car",
        "servicing",
        "radiator"
    ],
    "wof:name":"Walkers Radiators Ltd.",
    "wof:placetype":"venue"
},
  "geometry": {"coordinates":[-2.146198988,53.9144859314],"type":"Point"}
}