{
  "type": "Feature",
  "properties": {
    "addr:full":"2a India Street Edinburgh City of Edinburgh EH3 6EZ",
    "addr:housenumber":"2a",
    "addr:postcode":"eh3 6ez",
    "addr:street":"India Street",
    "iso:country":"GB",
    "sg:address":"2a India Street",
    "sg:city":"Edinburgh",
    "sg:classifiers":[
        {
            "category":"Professional",
            "subcategory":"Secretarial Services",
            "type":"Services"
        }
    ],
    "sg:postcode":"EH3 6EZ",
    "sg:province":"City of Edinburgh",
    "wof:name":"Qualitype",
    "wof:placetype":"venue"
},
  "geometry": {"coordinates":[-3.205455,55.95488],"type":"Point"}
}