{
  "type": "Feature",
  "properties": {
    "addr:full":"34 Applefield Amersham Buckinghamshire HP7 9NF",
    "addr:housenumber":"34",
    "addr:postcode":"hp7 9nf",
    "addr:street":"Applefield Amersham",
    "iso:country":"GB",
    "sg:address":"34 Applefield",
    "sg:city":"Amersham",
    "sg:classifiers":[
        {
            "category":"Professional",
            "subcategory":"Accounting & Tax Preparation",
            "type":"Services"
        }
    ],
    "sg:postcode":"HP7 9NF",
    "sg:province":"Buckinghamshire",
    "sg:tags":[
        "accountant"
    ],
    "wof:name":"J M C Accounting Services",
    "wof:placetype":"venue"
},
  "geometry": {"coordinates":[-0.565287,51.667374],"type":"Point"}
}