{
  "type": "Feature",
  "properties": {
    "iso:country":"GB",
    "sg:address":"148 Nyetimber Lane",
    "sg:city":"Bognor Regis",
    "sg:classifiers":[
        {
            "category":"Banks & Credit Unions",
            "subcategory":"Financial Services",
            "type":"Services"
        }
    ],
    "sg:phone":"+44 1243 266903",
    "sg:postcode":"PO21 3HX",
    "sg:province":"West Sussex",
    "sg:tags":[
        "adviser",
        "independent"
    ],
    "wof:name":"D M Associates",
    "wof:placetype":"venue"
},
  "geometry": {"coordinates":[-0.7261250019,50.779586792],"type":"Point"}
}