{
  "type": "Feature",
  "properties": {
    "iso:country":"GB",
    "sg:address":"10 Abbeyhills Road",
    "sg:city":"Oldham",
    "sg:classifiers":[
        {
            "category":"Health Services",
            "subcategory":"Optometrist",
            "type":"Services"
        }
    ],
    "sg:phone":"+44 161 624 8053",
    "sg:postcode":"OL8 2BS",
    "sg:province":"Lancashire",
    "sg:tags":[
        "optician"
    ],
    "wof:name":"A Harris & Partners",
    "wof:placetype":"venue"
},
  "geometry": {"coordinates":[-2.096889,53.534157],"type":"Point"}
}