{
  "type": "Feature",
  "properties": {
    "iso:country":"GB",
    "sg:address":"Tile Hill Lane",
    "sg:city":"Coventry",
    "sg:classifiers":[
        {
            "category":"Manufacturing",
            "subcategory":"Petroleum Products",
            "type":"Manufacturing & Wholesale Goods"
        }
    ],
    "sg:postcode":"CV4 9DG",
    "sg:province":"Warwickshire",
    "sg:tags":[
        "double",
        "glazing"
    ],
    "wof:name":"Abbey Windows",
    "wof:placetype":"venue"
},
  "geometry": {"coordinates":[-1.562067,52.404114],"type":"Point"}
}