{
  "type": "Feature",
  "properties": {
    "addr:full":"61-63 Hollow Way, Cowley Oxford Oxfordshire OX4 2ND",
    "addr:housenumber":"61-63",
    "addr:postcode":"ox4 2nd",
    "addr:street":"Hollow Way",
    "iso:country":"GB",
    "sg:address":"61-63 Hollow Way, Cowley",
    "sg:city":"Oxford",
    "sg:classifiers":[
        {
            "category":"Food & Beverages",
            "subcategory":"Groceries & Convenience Stores",
            "type":"Retail Goods"
        }
    ],
    "sg:phone":"+44 1865 777049",
    "sg:postcode":"OX4 2ND",
    "sg:province":"Oxfordshire",
    "wof:name":"Hollow Way Stores",
    "wof:placetype":"venue"
},
  "geometry": {"coordinates":[-1.208985,51.736099],"type":"Point"}
}