{
  "type": "Feature",
  "properties": {
    "addr:full":"44 Turnham Green Terrace, Chiswick London Greater London W4 1QP",
    "addr:housenumber":"44",
    "addr:postcode":"w4 1qp",
    "addr:street":"Turnham Green Terrace",
    "iso:country":"GB",
    "sg:address":"44 Turnham Green Terrace, Chiswick",
    "sg:city":"London",
    "sg:classifiers":[
        {
            "category":"Food & Beverages",
            "subcategory":"Meat & Fish",
            "type":"Retail Goods"
        }
    ],
    "sg:phone":"+44 20 8994 2646",
    "sg:postcode":"W4 1QP",
    "sg:province":"Greater London",
    "sg:tags":[
        "butcher"
    ],
    "wof:name":"Macken Bros Ltd.",
    "wof:placetype":"venue"
},
  "geometry": {"coordinates":[-0.255118,51.493702],"type":"Point"}
}