{
  "type": "Feature",
  "properties": {
    "iso:country":"GB",
    "sg:address":"76 St Johns Road, Lostock",
    "sg:city":"Bolton",
    "sg:classifiers":[
        {
            "category":"Taxi",
            "type":"Transportation"
        }
    ],
    "sg:postcode":"BL6 4HA",
    "sg:province":"Lancashire",
    "sg:tags":[
        "mini",
        "cab"
    ],
    "wof:name":"A-Z Taxis",
    "wof:placetype":"venue"
},
  "geometry": {"coordinates":[-2.5032610893,53.5636672974],"type":"Point"}
}