{
  "type": "Feature",
  "properties": {
    "addr:full":"170 High Street London Greater London NW10 4ST",
    "addr:housenumber":"170",
    "addr:postcode":"nw10 4st",
    "addr:street":"High Street",
    "iso:country":"GB",
    "sg:address":"170 High Street",
    "sg:city":"London",
    "sg:classifiers":[
        {
            "category":"Home & Garden",
            "subcategory":"Household Appliances",
            "type":"Retail Goods"
        },
        {
            "category":"Building & Trades",
            "subcategory":"Plumbing",
            "type":"Services"
        },
        {
            "category":"Banks & Credit Unions",
            "subcategory":"Financial Services",
            "type":"Services"
        }
    ],
    "sg:phone":"+44 20 8459 2101",
    "sg:postcode":"NW10 4ST",
    "sg:province":"Greater London",
    "sg:tags":[
        "adviser",
        "plumber",
        "electrical"
    ],
    "wof:name":"Imaco",
    "wof:placetype":"venue"
},
  "geometry": {"coordinates":[-0.2434120029,51.5349273682],"type":"Point"}
}