{
  "type": "Feature",
  "properties": {
    "addr:full":"Factory1 Hetton Lyons Industrial Estate, Hetton-le-hole Houghton-le-spring Durham DH5 0RG",
    "addr:housenumber":"hetton",
    "addr:postcode":"dh5 0rg",
    "addr:street":"Lyons Industrial Estate",
    "iso:country":"GB",
    "sg:address":"Factory1 Hetton Lyons Industrial Estate, Hetton-le-hole",
    "sg:city":"Houghton-le-spring",
    "sg:classifiers":[
        {
            "category":"Food & Beverages",
            "subcategory":"Supermarket",
            "type":"Retail Goods"
        }
    ],
    "sg:phone":"+44 191 517 0944",
    "sg:postcode":"DH5 0RG",
    "sg:province":"Durham",
    "sg:tags":[
        "frozen"
    ],
    "wof:name":"Blendex Food Ingredients Ltd.",
    "wof:placetype":"venue"
},
  "geometry": {"coordinates":[-1.4686470032,54.8388786316],"type":"Point"}
}