{
  "type": "Feature",
  "properties": {
    "addr:full":"34 Worple Road Isleworth Greater London TW7 7AP",
    "addr:housenumber":"34",
    "addr:postcode":"tw7 7ap",
    "addr:street":"Worple Road",
    "iso:country":"GB",
    "sg:address":"34 Worple Road",
    "sg:city":"Isleworth",
    "sg:classifiers":[
        {
            "category":"Professional",
            "subcategory":"Accounting & Tax Preparation",
            "type":"Services"
        }
    ],
    "sg:phone":"+44 20 8847 4953",
    "sg:postcode":"TW7 7AP",
    "sg:province":"Greater London",
    "sg:tags":[
        "accountant"
    ],
    "wof:name":"K S Business Services",
    "wof:placetype":"venue"
},
  "geometry": {"coordinates":[-0.3272849917,51.4651451111],"type":"Point"}
}