{
  "type": "Feature",
  "properties": {
    "addr:full":"Doctors Surgery, 179 Dorchester Rd Weymouth Dorset DT4 7LE",
    "addr:housenumber":"179",
    "addr:postcode":"dt4 7le",
    "addr:street":"Dorchester Rd",
    "iso:country":"GB",
    "sg:address":"Doctors Surgery, 179 Dorchester Rd",
    "sg:city":"Weymouth",
    "sg:classifiers":[
        {
            "category":"Health Services",
            "subcategory":"Doctor",
            "type":"Services"
        }
    ],
    "sg:phone":"+44 1305 766472",
    "sg:postcode":"DT4 7LE",
    "sg:province":"Dorset",
    "sg:tags":[
        "practitioners"
    ],
    "wof:name":"Davies, F M",
    "wof:placetype":"venue"
},
  "geometry": {"coordinates":[-2.4592061043,50.6099014282],"type":"Point"}
}