{
  "type": "Feature",
  "properties": {
    "addr:full":"5 Tay Walk, Cumbernauld Glasgow Falkirk G67 1BU",
    "addr:housenumber":"5",
    "addr:postcode":"g67 1bu",
    "addr:street":"Tay Walk",
    "iso:country":"GB",
    "sg:address":"5 Tay Walk, Cumbernauld",
    "sg:city":"Glasgow",
    "sg:classifiers":[
        {
            "category":"Banks & Credit Unions",
            "subcategory":"Bank",
            "type":"Services"
        }
    ],
    "sg:phone":"+44 845 782 6909",
    "sg:postcode":"G67 1BU",
    "sg:province":"Falkirk",
    "sg:tags":[
        "financial",
        "institution"
    ],
    "wof:name":"Clydesdale Bank Plc",
    "wof:placetype":"venue"
},
  "geometry": {"coordinates":[-3.9907701015,55.9469108582],"type":"Point"}
}