{
  "type": "Feature",
  "properties": {
    "iso:country":"GB",
    "sg:address":"112 Downs Wa, East Preston",
    "sg:city":"Littlehampton",
    "sg:classifiers":[
        {
            "category":"Home & Garden",
            "subcategory":"Carpets & Floor Coverings",
            "type":"Retail Goods"
        }
    ],
    "sg:phone":"+44 1903 850228",
    "sg:postcode":"BN16 1AF",
    "sg:province":"West Sussex",
    "sg:tags":[
        "carpets",
        "rug",
        "matting"
    ],
    "wof:name":"Roundstone Carpets Ltd",
    "wof:placetype":"venue"
},
  "geometry": {"coordinates":[-0.4775570035,50.8168983459],"type":"Point"}
}