{
  "type": "Feature",
  "properties": {
    "iso:country":"GB",
    "sg:address":"1 Cronin Rd, Weldon South Ind Est",
    "sg:city":"Corby",
    "sg:classifiers":[
        {
            "category":"Manufacturing",
            "subcategory":"Building Materials",
            "type":"Manufacturing & Wholesale Goods"
        }
    ],
    "sg:phone":"+44 1536 403337",
    "sg:postcode":"NN18 8AQ",
    "sg:province":"Northamptonshire",
    "sg:tags":[
        "tile",
        "mnfrs"
    ],
    "wof:name":"Corby Ceramic Tile Centre",
    "wof:placetype":"venue"
},
  "geometry": {"coordinates":[-0.6558820009,52.4939041138],"type":"Point"}
}