{
  "type": "Feature",
  "properties": {
    "addr:full":"36 Bear Lane London Greater London SE1 0UH",
    "addr:housenumber":"36",
    "addr:postcode":"se1 0uh",
    "addr:street":"Bear Lane",
    "iso:country":"GB",
    "sg:address":"36 Bear Lane",
    "sg:city":"London",
    "sg:classifiers":[
        {
            "category":"Shopping",
            "subcategory":"Jewelry",
            "type":"Retail Goods"
        }
    ],
    "sg:postcode":"SE1 0UH",
    "sg:province":"Greater London",
    "sg:tags":[
        "gold",
        "silversmith"
    ],
    "wof:name":"Grant Macdonald (Silversmiths) Ltd.",
    "wof:placetype":"venue"
},
  "geometry": {"coordinates":[-0.1023100019,51.5055618286],"type":"Point"}
}