{
  "type": "Feature",
  "properties": {
    "addr:full":"60 High Street Brentford Greater London TW8 0AH",
    "addr:housenumber":"60",
    "addr:postcode":"tw8 0ah",
    "addr:street":"High Street",
    "iso:country":"GB",
    "sg:address":"60 High Street",
    "sg:city":"Brentford",
    "sg:classifiers":[
        {
            "category":"Professional",
            "subcategory":"Engineering",
            "type":"Services"
        }
    ],
    "sg:phone":"+44 20 8568 6494",
    "sg:postcode":"TW8 0AH",
    "sg:province":"Greater London",
    "sg:tags":[
        "consultant",
        "structural"
    ],
    "wof:name":"John Elworthy & Associates",
    "wof:placetype":"venue"
},
  "geometry": {"coordinates":[-0.301231,51.484966],"type":"Point"}
}