{
  "type": "Feature",
  "properties": {
    "addr:full":"6 Gorleston Street London Greater London W14 8XS",
    "addr:housenumber":"6",
    "addr:postcode":"w14 8xs",
    "addr:street":"Gorleston Street",
    "iso:country":"GB",
    "sg:address":"6 Gorleston Street",
    "sg:city":"London",
    "sg:classifiers":[
        {
            "category":"Communications",
            "type":"Services"
        }
    ],
    "sg:phone":"+44 20 7603 4567",
    "sg:postcode":"W14 8XS",
    "sg:province":"Greater London",
    "sg:tags":[
        "audio-visual"
    ],
    "wof:name":"Diverse Group Ltd.",
    "wof:placetype":"venue"
},
  "geometry": {"coordinates":[-0.209704,51.494186],"type":"Point"}
}