{
  "type": "Feature",
  "properties": {
    "addr:full":"11 West Street Bognor Regis West Sussex PO21 1UE",
    "addr:housenumber":"11",
    "addr:postcode":"po21 1ue",
    "addr:street":"West Street",
    "iso:country":"GB",
    "sg:address":"11 West Street",
    "sg:city":"Bognor Regis",
    "sg:classifiers":[
        {
            "category":"Food & Beverages",
            "subcategory":"Fruits & Vegetables",
            "type":"Retail Goods"
        }
    ],
    "sg:phone":"+44 1243 821948",
    "sg:postcode":"PO21 1UE",
    "sg:province":"West Sussex",
    "sg:tags":[
        "greengrocer"
    ],
    "wof:name":"The Garden Shop",
    "wof:placetype":"venue"
},
  "geometry": {"coordinates":[-0.678636,50.782494],"type":"Point"}
}