{
  "type": "Feature",
  "properties": {
    "addr:full":"31-33 Church Street St Helens Merseyside WA10 1AX",
    "addr:housenumber":"31-33",
    "addr:postcode":"wa10 1ax",
    "addr:street":"Church Street",
    "iso:country":"GB",
    "sg:address":"31-33 Church Street",
    "sg:city":"St Helens",
    "sg:classifiers":[
        {
            "category":"Fast Food",
            "type":"Food & Drink"
        }
    ],
    "sg:phone":"+44 1744 451020",
    "sg:postcode":"WA10 1AX",
    "sg:province":"Merseyside",
    "sg:tags":[
        "away",
        "take"
    ],
    "wof:name":"McDonalds Restaurants Ltd.",
    "wof:placetype":"venue"
},
  "geometry": {"coordinates":[-2.7359828949,53.4523353577],"type":"Point"}
}