{
  "type": "Feature",
  "properties": {
    "iso:country":"GB",
    "sg:address":"7 Silver Lane",
    "sg:city":"Stamford",
    "sg:classifiers":[
        {
            "category":"Sports & Exercise",
            "subcategory":"Sports Center",
            "type":"Entertainment"
        }
    ],
    "sg:postcode":"PE9 2BT",
    "sg:province":"Cambridgeshire",
    "sg:tags":[
        "shop",
        "good"
    ],
    "wof:name":"Sporting Image",
    "wof:placetype":"venue"
},
  "geometry": {"coordinates":[-0.4898349941,52.6540489197],"type":"Point"}
}