{
  "type": "Feature",
  "properties": {
    "iso:country":"GB",
    "sg:address":"The Bungalow, Old Forge Lane, Maisemore",
    "sg:city":"Gloucester",
    "sg:classifiers":[
        {
            "category":"Education",
            "subcategory":"Special Training",
            "type":"Public Place"
        }
    ],
    "sg:phone":"+44 1452 310113",
    "sg:postcode":"GL2 8HN",
    "sg:province":"Gloucestershire",
    "sg:tags":[
        "product",
        "centre"
    ],
    "wof:name":"C M S Training",
    "wof:placetype":"venue"
},
  "geometry": {"coordinates":[-2.274514,51.889671],"type":"Point"}
}