{
  "type": "Feature",
  "properties": {
    "iso:country":"GB",
    "sg:address":"Unit 33, First Floor, Milmead Business C, Mill Mead Rd",
    "sg:city":"London",
    "sg:classifiers":[
        {
            "category":"Manufacturing",
            "subcategory":"Apparel",
            "type":"Manufacturing & Wholesale Goods"
        }
    ],
    "sg:postcode":"N17 9QU",
    "sg:province":"Greater London",
    "sg:tags":[
        "garment",
        "designer"
    ],
    "wof:name":"Front Page Patterns",
    "wof:placetype":"venue"
},
  "geometry": {"coordinates":[-0.0573,51.59251],"type":"Point"}
}