{
  "type": "Feature",
  "properties": {
    "iso:country":"GB",
    "sg:address":"68 Whitburn Street",
    "sg:city":"Bridgnorth",
    "sg:classifiers":[
        {
            "category":"Shopping",
            "subcategory":"Pets & Pet Supplies",
            "type":"Retail Goods"
        }
    ],
    "sg:phone":"+44 1746 764031",
    "sg:postcode":"WV16 4QP",
    "sg:province":"Shropshire",
    "wof:name":"Bridgnorth Pet Shop",
    "wof:placetype":"venue"
},
  "geometry": {"coordinates":[-2.423004,52.53582],"type":"Point"}
}