{
  "type": "Feature",
  "properties": {
    "iso:country":"GB",
    "sg:address":"219 New Kings Road",
    "sg:city":"London",
    "sg:classifiers":[
        {
            "category":"Farming",
            "subcategory":"Nursery",
            "type":"Manufacturing & Wholesale Goods"
        }
    ],
    "sg:phone":"+44 20 7610 9900",
    "sg:postcode":"SW6 4XE",
    "sg:province":"Greater London",
    "sg:tags":[
        "creche"
    ],
    "wof:name":"Ivy House Baby & Toddler Nursery",
    "wof:placetype":"venue"
},
  "geometry": {"coordinates":[-0.198643,51.472794],"type":"Point"}
}