{
  "type": "Feature",
  "properties": {
    "addr:full":"26 North Grove Drive, Oakwood Leeds West Yorkshire LS8 2NJ",
    "addr:housenumber":"26",
    "addr:postcode":"ls8 2nj",
    "addr:street":"North Grove Drive",
    "iso:country":"GB",
    "sg:address":"26 North Grove Drive, Oakwood",
    "sg:city":"Leeds",
    "sg:classifiers":[
        {
            "category":"Education",
            "subcategory":"School",
            "type":"Public Place"
        }
    ],
    "sg:postcode":"LS8 2NJ",
    "sg:province":"West Yorkshire",
    "sg:tags":[
        "local",
        "authority"
    ],
    "wof:name":"Tbs Training",
    "wof:placetype":"venue"
},
  "geometry": {"coordinates":[-1.491668,53.825119],"type":"Point"}
}