{
  "type": "Feature",
  "properties": {
    "addr:full":"10 Brewers Lane Richmond Greater London TW9 1HH",
    "addr:housenumber":"10",
    "addr:postcode":"tw9 1hh",
    "addr:street":"Brewers Lane",
    "iso:country":"GB",
    "sg:address":"10 Brewers Lane",
    "sg:city":"Richmond",
    "sg:classifiers":[
        {
            "category":"Bars & Pubs",
            "subcategory":"Wine Bar",
            "type":"Food & Drink"
        }
    ],
    "sg:phone":"+44 20 8940 0427",
    "sg:postcode":"TW9 1HH",
    "sg:province":"Greater London",
    "wof:name":"The So Bar",
    "wof:placetype":"venue"
},
  "geometry": {"coordinates":[-0.305064,51.460903],"type":"Point"}
}