{
  "type": "Feature",
  "properties": {
    "addr:full":"Lower Skircoat Green Halifax West Yorkshire HX3 0TG",
    "addr:postcode":"hx3 0tg",
    "addr:street":"Lower Skircoat Green",
    "iso:country":"GB",
    "sg:address":"Lower Skircoat Green",
    "sg:city":"Halifax",
    "sg:classifiers":[
        {
            "category":"Freight",
            "type":"Transportation"
        }
    ],
    "sg:phone":"+44 1422 364653",
    "sg:postcode":"HX3 0TG",
    "sg:province":"West Yorkshire",
    "sg:tags":[
        "haulage",
        "road"
    ],
    "wof:name":"Ralph Douglas",
    "wof:placetype":"venue"
},
  "geometry": {"coordinates":[-1.8643939495,53.7009010315],"type":"Point"}
}