{
  "type": "Feature",
  "properties": {
    "addr:full":"Suite 7 Buckingham Row, Brick Lane Wigan Lancashire WN1 1XB",
    "addr:housenumber":"suite 7",
    "addr:postcode":"wn1 1xb",
    "addr:street":"Buckingham Row Brick Lane",
    "iso:country":"GB",
    "sg:address":"Suite 7 Buckingham Row, Brick Lane",
    "sg:city":"Wigan",
    "sg:classifiers":[
        {
            "category":"Professional",
            "subcategory":"Computer Services",
            "type":"Services"
        }
    ],
    "sg:phone":"+44 1942 239631",
    "sg:postcode":"WN1 1XB",
    "sg:province":"Lancashire",
    "sg:tags":[
        "information"
    ],
    "wof:name":"Wigan & Leigh Community Health Council",
    "wof:placetype":"venue"
},
  "geometry": {"coordinates":[-2.633532,53.544155],"type":"Point"}
}