{
  "type": "Feature",
  "properties": {
    "iso:country":"GB",
    "sg:address":"14 Carden Pl",
    "sg:city":"Aberdeen",
    "sg:classifiers":[
        {
            "category":"Utilities",
            "type":"Services"
        }
    ],
    "sg:postcode":"AB10 1UR",
    "sg:province":"Aberdeen City",
    "sg:tags":[
        "internet"
    ],
    "wof:name":"Empire Web Design",
    "wof:placetype":"venue"
},
  "geometry": {"coordinates":[-2.11932,57.144817],"type":"Point"}
}