{
  "type": "Feature",
  "properties": {
    "iso:country":"GB",
    "sg:address":"Care Of Home Store Furnishings, Gorseinon Road, Gorseinon",
    "sg:city":"Swansea",
    "sg:classifiers":[
        {
            "category":"Home & Garden",
            "subcategory":"Home Furnishings",
            "type":"Retail Goods"
        }
    ],
    "sg:phone":"+44 1792 899110",
    "sg:postcode":"SA4 9GG",
    "sg:province":"Carmarthenshire",
    "sg:tags":[
        "beds",
        "bedding",
        "blanket"
    ],
    "wof:name":"B & S Price",
    "wof:placetype":"venue"
},
  "geometry": {"coordinates":[-4.0179800987,51.6675415039],"type":"Point"}
}