{
  "type": "Feature",
  "properties": {
    "iso:country":"GB",
    "sg:address":"36 Broadway",
    "sg:city":"Sheerness",
    "sg:classifiers":[
        {
            "category":"Real Estate",
            "subcategory":"Real Estate Agent",
            "type":"Services"
        }
    ],
    "sg:phone":"+44 1795 583100",
    "sg:postcode":"ME12 1TP",
    "sg:province":"Kent",
    "wof:name":"Broadway Estates",
    "wof:placetype":"venue"
},
  "geometry": {"coordinates":[0.7656059861,51.4403648376],"type":"Point"}
}