{
  "type": "Feature",
  "properties": {
    "iso:country":"GB",
    "sg:address":"90 High Street, Burwell",
    "sg:city":"Cambridge",
    "sg:classifiers":[
        {
            "category":"Farming",
            "subcategory":"Nursery",
            "type":"Manufacturing & Wholesale Goods"
        }
    ],
    "sg:postcode":"CB5 0HD",
    "sg:province":"Cambridgeshire",
    "sg:tags":[
        "creche"
    ],
    "wof:name":"Red House Day Nursery",
    "wof:placetype":"venue"
},
  "geometry": {"coordinates":[0.327825,52.274731],"type":"Point"}
}