{
  "type": "Feature",
  "properties": {
    "addr:full":"19 Eccleston Sq London Greater London SW1V 1NS",
    "addr:housenumber":"19",
    "addr:postcode":"sw1v 1ns",
    "addr:street":"Eccleston Sq",
    "iso:country":"GB",
    "sg:address":"19 Eccleston Sq",
    "sg:city":"London",
    "sg:classifiers":[
        {
            "category":"Professional",
            "subcategory":"Business Services",
            "type":"Services"
        }
    ],
    "sg:postcode":"SW1V 1NS",
    "sg:province":"Greater London",
    "sg:tags":[
        "import",
        "export",
        "agent"
    ],
    "wof:name":"Mapp Fashions",
    "wof:placetype":"venue"
},
  "geometry": {"coordinates":[-0.1443260014,51.4926528931],"type":"Point"}
}