{
  "type": "Feature",
  "properties": {
    "addr:full":"20 Stanshawe Crescent Bristol Gloucestershire BS37 4EB",
    "addr:housenumber":"20",
    "addr:postcode":"bs37 4eb",
    "addr:street":"Stanshawe Crescent",
    "iso:country":"GB",
    "sg:address":"20 Stanshawe Crescent",
    "sg:city":"Bristol",
    "sg:classifiers":[
        {
            "category":"Organizations",
            "subcategory":"Non-profit Organization",
            "type":"Services"
        }
    ],
    "sg:phone":"+44 1454 880840",
    "sg:postcode":"BS37 4EB",
    "sg:province":"Gloucestershire",
    "sg:tags":[
        "organisation",
        "voluntary",
        "charity"
    ],
    "wof:name":"Severn Ambulance Medical Services",
    "wof:placetype":"venue"
},
  "geometry": {"coordinates":[-2.415568,51.537411],"type":"Point"}
}