{
  "type": "Feature",
  "properties": {
    "addr:full":"Goosemoor Farm, Warfield Lane, Cowthorpe Wetherby North Yorkshire LS22 5EU",
    "addr:postcode":"ls22 5eu",
    "addr:street":"Warfield Lane",
    "iso:country":"GB",
    "sg:address":"Goosemoor Farm, Warfield Lane, Cowthorpe",
    "sg:city":"Wetherby",
    "sg:classifiers":[
        {
            "category":"Farming",
            "subcategory":"Livestock Farm",
            "type":"Manufacturing & Wholesale Goods"
        },
        {
            "category":"Retail",
            "subcategory":"Animal Services",
            "type":"Services"
        }
    ],
    "sg:phone":"+44 1423 359397",
    "sg:postcode":"LS22 5EU",
    "sg:province":"North Yorkshire",
    "sg:tags":[
        "trainer",
        "clipping",
        "horse",
        "dog",
        "others",
        "grooming"
    ],
    "wof:name":"R Bastiman",
    "wof:placetype":"venue"
},
  "geometry": {"coordinates":[-1.3504300117,53.9668083191],"type":"Point"}
}