{
  "type": "Feature",
  "properties": {
    "addr:full":"Windmill Hill London Greater London NW3 6RT",
    "addr:postcode":"nw3 6rt",
    "iso:country":"GB",
    "sg:address":"Windmill Hill",
    "sg:city":"London",
    "sg:classifiers":[
        {
            "category":"Landmark",
            "subcategory":"Historic",
            "type":"Public Place"
        },
        {
            "category":"Landmark",
            "subcategory":"Tourist Attraction",
            "type":"Public Place"
        }
    ],
    "sg:phone":"+44 20 7435 3471",
    "sg:postcode":"NW3 6RT",
    "sg:province":"Greater London",
    "sg:tags":[
        "house",
        "garden",
        "interest"
    ],
    "sg:website":"http://www.nationaltrust.org.uk",
    "wof:name":"Fenton House",
    "wof:placetype":"venue"
},
  "geometry": {"coordinates":[-0.180509,51.558857],"type":"Point"}
}