{
  "type": "Feature",
  "properties": {
    "addr:full":"38 Kings Way, South Woodham Ferrers Chelmsford Essex CM3 5QH",
    "addr:housenumber":"38",
    "addr:postcode":"cm3 5qh",
    "addr:street":"Kings Way",
    "iso:country":"GB",
    "sg:address":"38 Kings Way, South Woodham Ferrers",
    "sg:city":"Chelmsford",
    "sg:classifiers":[
        {
            "category":"Professional",
            "subcategory":"Lawyer & Legal Services",
            "type":"Services"
        }
    ],
    "sg:phone":"+44 1245 325036",
    "sg:postcode":"CM3 5QH",
    "sg:province":"Essex",
    "sg:tags":[
        "solicitor"
    ],
    "wof:name":"STEVEN ALBAN JOHN KIMPTON",
    "wof:placetype":"venue"
},
  "geometry": {"coordinates":[0.60572,51.651955],"type":"Point"}
}