{
  "type": "Feature",
  "properties": {
    "addr:full":"10 Weaverham Road Stockton-on-tees Durham TS20 1QJ",
    "addr:housenumber":"10",
    "addr:postcode":"ts20 1qj",
    "addr:street":"Weaverham Road",
    "iso:country":"GB",
    "sg:address":"10 Weaverham Road",
    "sg:city":"Stockton-on-tees",
    "sg:classifiers":[
        {
            "category":"Retail",
            "subcategory":"Driving School",
            "type":"Services"
        }
    ],
    "sg:phone":"+44 1642 555239",
    "sg:postcode":"TS20 1QJ",
    "sg:province":"Durham",
    "wof:name":"G J School of Motoring",
    "wof:placetype":"venue"
},
  "geometry": {"coordinates":[-1.325761,54.585735],"type":"Point"}
}