{
  "type": "Feature",
  "properties": {
    "addr:full":"Padgbury La Congleton Cheshire CW12 4LR",
    "addr:postcode":"cw12 4lr",
    "addr:street":"La Congleton",
    "iso:country":"GB",
    "sg:address":"Padgbury La",
    "sg:city":"Congleton",
    "sg:classifiers":[
        {
            "category":"Bars & Pubs",
            "type":"Food & Drink"
        }
    ],
    "sg:phone":"+44 1260 273575",
    "sg:postcode":"CW12 4LR",
    "sg:province":"Cheshire",
    "sg:tags":[
        "pubs",
        "inn"
    ],
    "wof:name":"Punch Retail Ltd",
    "wof:placetype":"venue"
},
  "geometry": {"coordinates":[-2.244797945,53.1629257202],"type":"Point"}
}