{
  "type": "Feature",
  "properties": {
    "iso:country":"GB",
    "sg:address":"8 Victoria Street, Englefield Grn",
    "sg:city":"Egham",
    "sg:classifiers":[
        {
            "category":"Shopping",
            "subcategory":"Books",
            "type":"Retail Goods"
        },
        {
            "category":"Shopping",
            "subcategory":"Used Merchandise",
            "type":"Retail Goods"
        }
    ],
    "sg:phone":"+44 1784 438025",
    "sg:postcode":"TW20 0QY",
    "sg:province":"Surrey",
    "sg:tags":[
        "second-hand",
        "secondhand"
    ],
    "wof:name":"Blacklocks Books",
    "wof:placetype":"venue"
},
  "geometry": {"coordinates":[-0.569377,51.429249],"type":"Point"}
}