{
  "type": "Feature",
  "properties": {
    "addr:full":"1 Hackwood Close, Barlaston Stoke-on-trent Staffordshire ST12 9BE",
    "addr:housenumber":"1",
    "addr:postcode":"st12 9be",
    "addr:street":"Hackwood Close",
    "iso:country":"GB",
    "sg:address":"1 Hackwood Close, Barlaston",
    "sg:city":"Stoke-on-trent",
    "sg:classifiers":[
        {
            "category":"Building & Trades",
            "subcategory":"Landscaping Services",
            "type":"Services"
        }
    ],
    "sg:postcode":"ST12 9BE",
    "sg:province":"Staffordshire",
    "sg:tags":[
        "forestry",
        "tree"
    ],
    "wof:name":"Cedar Point Tree Surgeons",
    "wof:placetype":"venue"
},
  "geometry": {"coordinates":[-2.156722,52.955402],"type":"Point"}
}