{
  "type": "Feature",
  "properties": {
    "iso:country":"GB",
    "sg:address":"10 Strichen Rd",
    "sg:city":"Fraserburgh",
    "sg:classifiers":[
        {
            "category":"Building & Trades",
            "subcategory":"Plumbing",
            "type":"Services"
        }
    ],
    "sg:phone":"+44 1346 518598",
    "sg:postcode":"AB43 9SA",
    "sg:province":"Aberdeenshire",
    "sg:tags":[
        "heating"
    ],
    "wof:name":"J Whyte",
    "wof:placetype":"venue"
},
  "geometry": {"coordinates":[-2.0104370117,57.6848602295],"type":"Point"}
}