{
  "type": "Feature",
  "properties": {
    "addr:full":"Church Square, St Osyth Clacton-on-sea Essex CO16 8NU",
    "addr:postcode":"co16 8nu",
    "addr:street":"Church Square",
    "iso:country":"GB",
    "sg:address":"Church Square, St Osyth",
    "sg:city":"Clacton-on-sea",
    "sg:classifiers":[
        {
            "category":"Health Services",
            "subcategory":"Doctor",
            "type":"Services"
        },
        {
            "category":"Health Services",
            "subcategory":"Clinic",
            "type":"Services"
        }
    ],
    "sg:phone":"+44 1255 820309",
    "sg:postcode":"CO16 8NU",
    "sg:province":"Essex",
    "sg:tags":[
        "nh",
        "practitioners"
    ],
    "wof:name":"ST JAMES'S SURGERY",
    "wof:placetype":"venue"
},
  "geometry": {"coordinates":[1.07696,51.79887],"type":"Point"}
}