{
  "type": "Feature",
  "properties": {
    "addr:full":"33 St Annes Gardens Hengoed Caerphilly CF82 7QQ",
    "addr:housenumber":"33",
    "addr:postcode":"cf82 7qq",
    "addr:street":"St Annes Gardens",
    "iso:country":"GB",
    "sg:address":"33 St Annes Gardens",
    "sg:city":"Hengoed",
    "sg:classifiers":[
        {
            "category":"Retail",
            "subcategory":"Driving School",
            "type":"Services"
        }
    ],
    "sg:phone":"+44 1443 815286",
    "sg:postcode":"CF82 7QQ",
    "sg:province":"Caerphilly",
    "wof:name":"Top Gear School Driving",
    "wof:placetype":"venue"
},
  "geometry": {"coordinates":[-3.218444109,51.6434135437],"type":"Point"}
}