{
  "type": "Feature",
  "properties": {
    "addr:full":"27 Marsh Road Middlesbrough North Yorkshire TS1 5LA",
    "addr:housenumber":"27",
    "addr:postcode":"ts1 5la",
    "addr:street":"Marsh Road",
    "iso:country":"GB",
    "sg:address":"27 Marsh Road",
    "sg:city":"Middlesbrough",
    "sg:classifiers":[
        {
            "category":"Autos & Motor Vehicles",
            "subcategory":"Motorcycle Sales",
            "type":"Retail Goods"
        }
    ],
    "sg:phone":"+44 1642 218914",
    "sg:postcode":"TS1 5LA",
    "sg:province":"North Yorkshire",
    "sg:tags":[
        "component"
    ],
    "wof:name":"David Larry",
    "wof:placetype":"venue"
},
  "geometry": {"coordinates":[-1.2424340248,54.578868866],"type":"Point"}
}