{
  "type": "Feature",
  "properties": {
    "addr:full":"44 Frith Street London Greater London W1D 4SB",
    "addr:housenumber":"44",
    "addr:postcode":"w1d 4sb",
    "addr:street":"Frith Street",
    "iso:country":"GB",
    "sg:address":"44 Frith Street",
    "sg:city":"London",
    "sg:classifiers":[
        {
            "category":"Restaurant",
            "type":"Food & Drink"
        }
    ],
    "sg:phone":"+44 20 7437 8261",
    "sg:postcode":"W1D 4SB",
    "sg:province":"Greater London",
    "sg:tags":[
        "indian"
    ],
    "wof:name":"The Delhi Brasserie",
    "wof:placetype":"venue"
},
  "geometry": {"coordinates":[-0.1315409988,51.51329422],"type":"Point"}
}