{
  "type": "Feature",
  "properties": {
    "addr:full":"72 Anson Drive, Leegomery Telford Shropshire TF1 6XP",
    "addr:housenumber":"72",
    "addr:postcode":"tf1 6xp",
    "addr:street":"Anson Drive",
    "iso:country":"GB",
    "sg:address":"72 Anson Drive, Leegomery",
    "sg:city":"Telford",
    "sg:classifiers":[
        {
            "category":"Military Area",
            "subcategory":"Air Force Base",
            "type":"Public Place"
        }
    ],
    "sg:postcode":"TF1 6XP",
    "sg:province":"Shropshire",
    "sg:tags":[
        "taxi",
        "hire",
        "private"
    ],
    "wof:name":"P B Radio Cars",
    "wof:placetype":"venue"
},
  "geometry": {"coordinates":[-2.4960389137,52.7123336792],"type":"Point"}
}