{
  "type": "Feature",
  "properties": {
    "addr:full":"4 Loxley Road Stratford-upon-avon Warwickshire CV37 7DP",
    "addr:housenumber":"4",
    "addr:postcode":"cv37 7dp",
    "addr:street":"Loxley Road",
    "iso:country":"GB",
    "sg:address":"4 Loxley Road",
    "sg:city":"Stratford-upon-avon",
    "sg:classifiers":[
        {
            "category":"Health Services",
            "subcategory":"Health Practitioner",
            "type":"Services"
        }
    ],
    "sg:phone":"+44 1789 293766",
    "sg:postcode":"CV37 7DP",
    "sg:province":"Warwickshire",
    "sg:tags":[
        "homoeopathic",
        "homeopathic"
    ],
    "wof:name":"Celia Scott",
    "wof:placetype":"venue"
},
  "geometry": {"coordinates":[-1.6946270466,52.1919250488],"type":"Point"}
}