{
  "type": "Feature",
  "properties": {
    "addr:full":"The Kingsway Shopping Precint Bristol City of Bristol BS5 8NS",
    "addr:postcode":"bs5 8ns",
    "addr:street":"The Kingsway",
    "iso:country":"GB",
    "sg:address":"The Kingsway Shopping Precint",
    "sg:city":"Bristol",
    "sg:classifiers":[
        {
            "category":"Food & Beverages",
            "subcategory":"Meat & Fish",
            "type":"Retail Goods"
        }
    ],
    "sg:phone":"+44 117 961 6626",
    "sg:postcode":"BS5 8NS",
    "sg:province":"City of Bristol",
    "sg:tags":[
        "chip"
    ],
    "wof:name":"Farrows Fish and Chips",
    "wof:placetype":"venue"
},
  "geometry": {"coordinates":[-2.5209441185,51.4586181641],"type":"Point"}
}