{
  "type": "Feature",
  "properties": {
    "iso:country":"GB",
    "sg:address":"24-26 Church Road",
    "sg:city":"Stanmore",
    "sg:classifiers":[
        {
            "category":"Professional",
            "subcategory":"Lawyer & Legal Services",
            "type":"Services"
        }
    ],
    "sg:phone":"+44 20 8954 7474",
    "sg:postcode":"HA7 4AW",
    "sg:province":"Greater London",
    "sg:tags":[
        "solicitor"
    ],
    "wof:name":"Levine Mellins & Klarfield",
    "wof:placetype":"venue"
},
  "geometry": {"coordinates":[-0.3129909933,51.6169319153],"type":"Point"}
}