{
  "type": "Feature",
  "properties": {
    "addr:full":"Mainline House, The Parade, Crawford Road Hatfield Hertfordshire AL10 0PG",
    "addr:postcode":"al10 0pg",
    "addr:street":"The Parade Crawford Road",
    "iso:country":"GB",
    "sg:address":"Mainline House, The Parade, Crawford Road",
    "sg:city":"Hatfield",
    "sg:classifiers":[
        {
            "category":"Professional",
            "subcategory":"Engineering",
            "type":"Services"
        }
    ],
    "sg:phone":"+44 1707 270288",
    "sg:postcode":"AL10 0PG",
    "sg:province":"Hertfordshire",
    "sg:tags":[
        "contractor",
        "electrical",
        "engineer"
    ],
    "wof:name":"Mainline",
    "wof:placetype":"venue"
},
  "geometry": {"coordinates":[-0.2339649945,51.7610282898],"type":"Point"}
}