{
  "type": "Feature",
  "properties": {
    "iso:country":"GB",
    "sg:address":"5 Appold Street, Broadwalk House",
    "sg:city":"London",
    "sg:classifiers":[
        {
            "category":"Professional",
            "subcategory":"Lawyer & Legal Services",
            "type":"Services"
        }
    ],
    "sg:phone":"+44 20 7638 1111",
    "sg:postcode":"EC2A 2HA",
    "sg:province":"Greater London",
    "sg:tags":[
        "solicitor"
    ],
    "wof:name":"Ashursts Ltd.",
    "wof:placetype":"venue"
},
  "geometry": {"coordinates":[-0.08328,51.521278],"type":"Point"}
}