{
  "type": "Feature",
  "properties": {
    "addr:full":"37-38 Dunkerque Mall, Hill Street Shopping Centre Middlesbrough North Yorkshire TS1 1TA",
    "addr:housenumber":"37-38",
    "addr:postcode":"ts1 1ta",
    "addr:street":"Dunkerque Mall Hill Street",
    "iso:country":"GB",
    "sg:address":"37-38 Dunkerque Mall, Hill Street Shopping Centre",
    "sg:city":"Middlesbrough",
    "sg:classifiers":[
        {
            "category":"Shopping",
            "subcategory":"Clothing, Apparel, & Fashions",
            "type":"Retail Goods"
        }
    ],
    "sg:phone":"+44 1642 232519",
    "sg:postcode":"TS1 1TA",
    "sg:province":"North Yorkshire",
    "sg:tags":[
        "lingerie",
        "hosiery"
    ],
    "wof:name":"Frills & Things",
    "wof:placetype":"venue"
},
  "geometry": {"coordinates":[-1.239560008,54.5771713257],"type":"Point"}
}