{
  "type": "Feature",
  "properties": {
    "addr:full":"Gate Farm, Park Road, Kiddington Woodstock Oxfordshire OX20 1DB",
    "addr:postcode":"ox20 1db",
    "addr:street":"Gate;Park Road",
    "iso:country":"GB",
    "sg:address":"Gate Farm, Park Road, Kiddington",
    "sg:city":"Woodstock",
    "sg:classifiers":[
        {
            "category":"Communications",
            "type":"Services"
        }
    ],
    "sg:phone":"+44 1608 677777",
    "sg:postcode":"OX20 1DB",
    "sg:province":"Oxfordshire",
    "sg:tags":[
        "broadcasting"
    ],
    "wof:name":"Taylor Made Learning Ltd.",
    "wof:placetype":"venue"
},
  "geometry": {"coordinates":[-1.3550219536,51.8484611511],"type":"Point"}
}