{
  "type": "Feature",
  "properties": {
    "iso:country":"GB",
    "sg:address":"Water Street",
    "sg:city":"Rochdale",
    "sg:classifiers":[
        {
            "category":"Autos & Motor Vehicles",
            "subcategory":"Automobile Sales",
            "type":"Retail Goods"
        }
    ],
    "sg:postcode":"OL16 1TL",
    "sg:province":"Lancashire",
    "sg:tags":[
        "car"
    ],
    "wof:name":"Lythgoe Mazda",
    "wof:placetype":"venue"
},
  "geometry": {"coordinates":[-2.151598,53.616631],"type":"Point"}
}