{
  "type": "Feature",
  "properties": {
    "addr:full":"2 School Road, Rowledge Farnham Hampshire GU10 4BW",
    "addr:housenumber":"2",
    "addr:postcode":"gu10 4bw",
    "addr:street":"School Road Rowledge",
    "iso:country":"GB",
    "sg:address":"2 School Road, Rowledge",
    "sg:city":"Farnham",
    "sg:classifiers":[
        {
            "category":"Communications",
            "subcategory":"Film & Video Production",
            "type":"Services"
        }
    ],
    "sg:postcode":"GU10 4BW",
    "sg:province":"Hampshire",
    "sg:tags":[
        "illustrator",
        "artist"
    ],
    "wof:name":"Caroline Jayne Church",
    "wof:placetype":"venue"
},
  "geometry": {"coordinates":[-0.826339,51.183102],"type":"Point"}
}