{
  "type": "Feature",
  "properties": {
    "iso:country":"GB",
    "sg:address":"22-24 Dennis Road",
    "sg:city":"East Molesey",
    "sg:classifiers":[
        {
            "category":"Professional",
            "subcategory":"Testing Lab",
            "type":"Services"
        }
    ],
    "sg:phone":"+44 20 8979 6752",
    "sg:postcode":"KT8 9ED",
    "sg:province":"Greater London",
    "sg:tags":[
        "mot"
    ],
    "wof:name":"Dennis Road Motors",
    "wof:placetype":"venue"
},
  "geometry": {"coordinates":[-0.3597669899,51.4025917053],"type":"Point"}
}