{
  "type": "Feature",
  "properties": {
    "addr:full":"Units 5 & 6, 109 Maybank Road, South Woodford London Greater London E18 1EJ",
    "addr:housenumber":"units 5 & 6",
    "addr:postcode":"109;e18 1ej",
    "addr:street":"Maybank Road",
    "iso:country":"GB",
    "sg:address":"Units 5 & 6, 109 Maybank Road, South Woodford",
    "sg:city":"London",
    "sg:classifiers":[
        {
            "category":"Home & Garden",
            "subcategory":"Building Materials",
            "type":"Retail Goods"
        }
    ],
    "sg:phone":"+44 20 8505 1124",
    "sg:postcode":"E18 1EJ",
    "sg:province":"Greater London",
    "sg:tags":[
        "shutter",
        "door"
    ],
    "wof:name":"Contact Roller Shutters",
    "wof:placetype":"venue"
},
  "geometry": {"coordinates":[0.033069,51.595737],"type":"Point"}
}