{
  "type": "Feature",
  "properties": {
    "iso:country":"GB",
    "sg:address":"116 Featherstone La",
    "sg:city":"Pontefract",
    "sg:classifiers":[
        {
            "category":"Food & Beverages",
            "subcategory":"Liquor & Beverages",
            "type":"Retail Goods"
        }
    ],
    "sg:phone":"+44 1977 708021",
    "sg:postcode":"WF7 6LR",
    "sg:province":"West Yorkshire",
    "sg:tags":[
        "beer",
        "spirit",
        "wines"
    ],
    "wof:name":"M Gill",
    "wof:placetype":"venue"
},
  "geometry": {"coordinates":[-1.3537939787,53.6854515076],"type":"Point"}
}