{
  "type": "Feature",
  "properties": {
    "addr:full":"18 Pasture Cres Wirral Merseyside CH46 8SZ",
    "addr:housenumber":"18",
    "addr:postcode":"ch46 8sz",
    "addr:street":"Pasture Cres",
    "iso:country":"GB",
    "sg:address":"18 Pasture Cres",
    "sg:city":"Wirral",
    "sg:classifiers":[
        {
            "category":"Transit Center",
            "subcategory":"Passenger",
            "type":"Transportation"
        }
    ],
    "sg:phone":"+44 151 678 9261",
    "sg:postcode":"CH46 8SZ",
    "sg:province":"Merseyside",
    "sg:tags":[
        "airport"
    ],
    "wof:name":"Rapid Airport Services",
    "wof:placetype":"venue"
},
  "geometry": {"coordinates":[-3.111358,53.406361],"type":"Point"}
}