{
  "type": "Feature",
  "properties": {
    "addr:full":"Treinney Farm, Trewen Pipers Pool Launceston Cornwall PL15 8QF",
    "addr:housenumber":"trewen",
    "addr:postcode":"pl15 8qf",
    "iso:country":"GB",
    "sg:address":"Treinney Farm, Trewen Pipers Pool",
    "sg:city":"Launceston",
    "sg:classifiers":[
        {
            "category":"Professional",
            "subcategory":"Computer Services",
            "type":"Services"
        }
    ],
    "sg:phone":"+44 1566 86130",
    "sg:postcode":"PL15 8QF",
    "sg:province":"Cornwall",
    "sg:tags":[
        "consultant"
    ],
    "wof:name":"Angledata Consultants Ltd.",
    "wof:placetype":"venue"
},
  "geometry": {"coordinates":[-4.363344,50.636707],"type":"Point"}
}