{
  "type": "Feature",
  "properties": {
    "addr:full":"57 Dickinson Rd, Wombourne Wolverhampton Shropshire WV5 0NH",
    "addr:housenumber":"57",
    "addr:postcode":"wv5 0nh",
    "addr:street":"Dickinson Rd",
    "iso:country":"GB",
    "sg:address":"57 Dickinson Rd, Wombourne",
    "sg:city":"Wolverhampton",
    "sg:classifiers":[
        {
            "category":"Manufacturing",
            "subcategory":"Signs",
            "type":"Manufacturing & Wholesale Goods"
        }
    ],
    "sg:phone":"+44 1902 895296",
    "sg:postcode":"WV5 0NH",
    "sg:province":"Shropshire",
    "sg:tags":[
        "commercial",
        "maker"
    ],
    "wof:name":"Action Signs",
    "wof:placetype":"venue"
},
  "geometry": {"coordinates":[-2.191057,52.524872],"type":"Point"}
}