{
  "type": "Feature",
  "properties": {
    "iso:country":"GB",
    "sg:address":"Corporation Road",
    "sg:city":"Middlesbrough",
    "sg:classifiers":[
        {
            "category":"Bars & Pubs",
            "subcategory":"Nightclub",
            "type":"Food & Drink"
        }
    ],
    "sg:phone":"+44 1642 253553",
    "sg:postcode":"TS1 2RT",
    "sg:province":"North Yorkshire",
    "sg:tags":[
        "club",
        "night"
    ],
    "wof:name":"Empire Club",
    "wof:placetype":"venue"
},
  "geometry": {"coordinates":[-1.229209,54.575867],"type":"Point"}
}