{
  "type": "Feature",
  "properties": {
    "addr:full":"65 Whittington Hill Chesterfield Derbyshire S41 9EZ",
    "addr:housenumber":"65",
    "addr:postcode":"s41 9ez",
    "addr:street":"Whittington Hill",
    "iso:country":"GB",
    "sg:address":"65 Whittington Hill",
    "sg:city":"Chesterfield",
    "sg:classifiers":[
        {
            "category":"Food & Beverages",
            "subcategory":"Liquor & Beverages",
            "type":"Retail Goods"
        }
    ],
    "sg:phone":"+44 1246 450677",
    "sg:postcode":"S41 9EZ",
    "sg:province":"Derbyshire",
    "sg:tags":[
        "beer",
        "spirit",
        "wines"
    ],
    "wof:name":"Maan's Stores",
    "wof:placetype":"venue"
},
  "geometry": {"coordinates":[-1.427089,53.265671],"type":"Point"}
}