{
  "type": "Feature",
  "properties": {
    "addr:full":"Riverside Estate, Brundel Norwich Norfolk NR13 5PS",
    "addr:postcode":"nr13 5ps",
    "addr:street":"Riverside;Norwich",
    "iso:country":"GB",
    "sg:address":"Riverside Estate, Brundel",
    "sg:city":"Norwich",
    "sg:classifiers":[
        {
            "category":"Autos & Motor Vehicles",
            "subcategory":"Boat Sales",
            "type":"Retail Goods"
        }
    ],
    "sg:phone":"+44 1603 713265",
    "sg:postcode":"NR13 5PS",
    "sg:province":"Norfolk",
    "sg:tags":[
        "repair",
        "builder"
    ],
    "wof:name":"Alphacraft (Hire Services) Ltd.",
    "wof:placetype":"venue"
},
  "geometry": {"coordinates":[1.2948999405,52.6224937439],"type":"Point"}
}