{
  "type": "Feature",
  "properties": {
    "addr:full":"24 Crystal Road Blackpool Lancashire FY1 6BS",
    "addr:housenumber":"24",
    "addr:postcode":"fy1 6bs",
    "addr:street":"Crystal Road",
    "iso:country":"GB",
    "sg:address":"24 Crystal Road",
    "sg:city":"Blackpool",
    "sg:classifiers":[
        {
            "category":"Travel",
            "subcategory":"Hotels & Motels",
            "type":"Entertainment"
        }
    ],
    "sg:phone":"+44 1253 345636",
    "sg:postcode":"FY1 6BS",
    "sg:province":"Lancashire",
    "sg:tags":[
        "house",
        "guest"
    ],
    "wof:name":"Camelot House",
    "wof:placetype":"venue"
},
  "geometry": {"coordinates":[-3.053308,53.802319],"type":"Point"}
}