{
  "type": "Feature",
  "properties": {
    "iso:country":"GB",
    "sg:address":"1 Yew St",
    "sg:city":"Salford",
    "sg:classifiers":[
        {
            "category":"Home & Garden",
            "subcategory":"Furniture",
            "type":"Retail Goods"
        }
    ],
    "sg:phone":"+44 161 708 9171",
    "sg:postcode":"M7 2HL",
    "sg:province":"Greater Manchester",
    "wof:name":"MLB Multiskill Ltd",
    "wof:placetype":"venue"
},
  "geometry": {"coordinates":[-2.2674589157,53.5020599365],"type":"Point"}
}