{
  "type": "Feature",
  "properties": {
    "addr:full":"49 Station Road Harrow Greater London HA1 2TY",
    "addr:housenumber":"49",
    "addr:postcode":"ha1 2ty",
    "addr:street":"Station Road",
    "iso:country":"GB",
    "sg:address":"49 Station Road",
    "sg:city":"Harrow",
    "sg:classifiers":[
        {
            "category":"Professional",
            "subcategory":"Employment Agencies",
            "type":"Services"
        }
    ],
    "sg:phone":"+44 20 8424 2222",
    "sg:postcode":"HA1 2TY",
    "sg:province":"Greater London",
    "sg:tags":[
        "consultant",
        "recruitment"
    ],
    "wof:name":"Gem Appointments Ltd",
    "wof:placetype":"venue"
},
  "geometry": {"coordinates":[-0.332249,51.587532],"type":"Point"}
}