{
  "type": "Feature",
  "properties": {
    "addr:full":"Carlton House, 18 Albert Square Manchester Greater Manchester M2 5PE",
    "addr:housenumber":"18",
    "addr:postcode":"m2 5pe",
    "addr:street":"Albert Square",
    "iso:country":"GB",
    "sg:address":"Carlton House, 18 Albert Square",
    "sg:city":"Manchester",
    "sg:classifiers":[
        {
            "category":"Banks & Credit Unions",
            "subcategory":"Investment Brokerage",
            "type":"Services"
        }
    ],
    "sg:phone":"+44 161 839 3131",
    "sg:postcode":"M2 5PE",
    "sg:province":"Greater Manchester",
    "wof:name":"3 I Plc",
    "wof:placetype":"venue"
},
  "geometry": {"coordinates":[-2.2454400063,53.4788093567],"type":"Point"}
}