{
  "type": "Feature",
  "properties": {
    "iso:country":"GB",
    "sg:address":"10 Wellington Rd",
    "sg:city":"Wirral",
    "sg:classifiers":[
        {
            "category":"Place Of Worship",
            "type":"Public Place"
        }
    ],
    "sg:phone":"+44 151 645 1304",
    "sg:postcode":"CH63 7NF",
    "sg:province":"Merseyside",
    "wof:name":"Lower Bebington Methodist Church",
    "wof:placetype":"venue"
},
  "geometry": {"coordinates":[-3.006446,53.355114],"type":"Point"}
}