{
  "type": "Feature",
  "properties": {
    "addr:full":"Queens Road Hastings East Sussex TN34 1QP",
    "addr:postcode":"tn34 1qp",
    "addr:street":"Queens Road",
    "iso:country":"GB",
    "sg:address":"Queens Road",
    "sg:city":"Hastings",
    "sg:classifiers":[
        {
            "category":"Cafe",
            "type":"Food & Drink"
        },
        {
            "category":"Commercial Area",
            "type":"Public Place"
        }
    ],
    "sg:phone":"+44 1424 718049",
    "sg:postcode":"TN34 1QP",
    "sg:province":"East Sussex",
    "sg:tags":[
        "shop",
        "tea",
        "room",
        "centre"
    ],
    "wof:name":"Priory Meadow Shopping Centre",
    "wof:placetype":"venue"
},
  "geometry": {"coordinates":[0.5823299885,50.8574142456],"type":"Point"}
}