{
  "type": "Feature",
  "properties": {
    "addr:full":"26 Westgate Halifax West Yorkshire HX1 1DJ",
    "addr:housenumber":"26",
    "addr:postcode":"hx1 1dj",
    "addr:street":"Westgate Halifax West",
    "iso:country":"GB",
    "sg:address":"26 Westgate",
    "sg:city":"Halifax",
    "sg:classifiers":[
        {
            "category":"Personal",
            "subcategory":"Beauty Salon",
            "type":"Services"
        }
    ],
    "sg:phone":"+44 1422 354291",
    "sg:postcode":"HX1 1DJ",
    "sg:province":"West Yorkshire",
    "sg:tags":[
        "unisex",
        "hairdresser"
    ],
    "wof:name":"The Crop Shop",
    "wof:placetype":"venue"
},
  "geometry": {"coordinates":[-1.8584779501,53.7216644287],"type":"Point"}
}