{
  "type": "Feature",
  "properties": {
    "iso:country":"GB",
    "sg:address":"138  Crawford Rd",
    "sg:city":"Hatfield",
    "sg:classifiers":[
        {
            "category":"Freight",
            "type":"Transportation"
        }
    ],
    "sg:postcode":"AL10 0PA",
    "sg:province":"Hertfordshire",
    "sg:tags":[
        "haulage",
        "road"
    ],
    "wof:name":"Allinsons,T,Transport",
    "wof:placetype":"venue"
},
  "geometry": {"coordinates":[-0.224593997,51.7685241699],"type":"Point"}
}