{
  "type": "Feature",
  "properties": {
    "iso:country":"GB",
    "sg:address":"37 Rawson Market",
    "sg:city":"Bradford",
    "sg:classifiers":[
        {
            "category":"Food & Beverages",
            "subcategory":"Meat & Fish",
            "type":"Retail Goods"
        }
    ],
    "sg:phone":"+44 1274 734199",
    "sg:postcode":"BD1 3QF",
    "sg:province":"West Yorkshire",
    "sg:tags":[
        "butcher"
    ],
    "wof:name":"Doveshire Meat Supplies",
    "wof:placetype":"venue"
},
  "geometry": {"coordinates":[-1.756039,53.796181],"type":"Point"}
}