{
  "type": "Feature",
  "properties": {
    "iso:country":"GB",
    "sg:address":"99 High St",
    "sg:city":"Forres",
    "sg:classifiers":[
        {
            "category":"Shopping",
            "subcategory":"Pharmacy",
            "type":"Retail Goods"
        }
    ],
    "sg:phone":"+44 1309 672614",
    "sg:postcode":"IV36 0AA",
    "sg:province":"Moray",
    "sg:tags":[
        "pharmacist",
        "chemist"
    ],
    "wof:name":"Ian Noble",
    "wof:placetype":"venue"
},
  "geometry": {"coordinates":[-3.6304500103,57.6073989868],"type":"Point"}
}