{
  "type": "Feature",
  "properties": {
    "addr:full":"109 Gilstead Lane Bingley West Yorkshire BD16 3LH",
    "addr:housenumber":"109",
    "addr:postcode":"bd16 3lh",
    "addr:street":"Gilstead Lane",
    "iso:country":"GB",
    "sg:address":"109 Gilstead Lane",
    "sg:city":"Bingley",
    "sg:classifiers":[
        {
            "category":"Professional",
            "subcategory":"Management & Consulting",
            "type":"Services"
        }
    ],
    "sg:phone":"+44 1274 561001",
    "sg:postcode":"BD16 3LH",
    "sg:province":"West Yorkshire",
    "sg:tags":[
        "consultant",
        "training"
    ],
    "wof:name":"H B Training Consultancy",
    "wof:placetype":"venue"
},
  "geometry": {"coordinates":[-1.8166769743,53.8502655029],"type":"Point"}
}