{
  "type": "Feature",
  "properties": {
    "addr:full":"Craft Centre Cottage, Haining Drive, Tweedbank Galashiels Scottish Borders TD1 3RJ",
    "addr:postcode":"td1 3rj",
    "addr:street":"Haining Drive Tweedbank",
    "iso:country":"GB",
    "sg:address":"Craft Centre Cottage, Haining Drive, Tweedbank",
    "sg:city":"Galashiels",
    "sg:classifiers":[
        {
            "category":"Shopping",
            "subcategory":"Hobbies, Toys, & Games",
            "type":"Retail Goods"
        }
    ],
    "sg:postcode":"TD1 3RJ",
    "sg:province":"Scottish Borders",
    "sg:tags":[
        "collectors'",
        "item"
    ],
    "wof:name":"Border Bruins",
    "wof:placetype":"venue"
},
  "geometry": {"coordinates":[-2.802979,55.612156],"type":"Point"}
}