{
  "type": "Feature",
  "properties": {
    "addr:full":"Wentworth Place, Keats Gro London Greater London NW3 2RR",
    "addr:postcode":"nw3 2rr",
    "addr:street":"Wentworth Place",
    "iso:country":"GB",
    "sg:address":"Wentworth Place, Keats Gro",
    "sg:city":"London",
    "sg:classifiers":[
        {
            "category":"Museum",
            "subcategory":"Art Museum",
            "type":"Entertainment"
        },
        {
            "category":"Museum",
            "type":"Entertainment"
        }
    ],
    "sg:phone":"+44 20 7435 2062",
    "sg:postcode":"NW3 2RR",
    "sg:province":"Greater London",
    "sg:tags":[
        "gallery"
    ],
    "wof:name":"Keats House Museum",
    "wof:placetype":"venue"
},
  "geometry": {"coordinates":[-0.1666100025,51.5558586121],"type":"Point"}
}