{
  "type": "Feature",
  "properties": {
    "addr:full":"107a Richmond Road Gillingham Kent ME7 1LS",
    "addr:housenumber":"107a",
    "addr:postcode":"me7 1ls",
    "addr:street":"Richmond Road",
    "iso:country":"GB",
    "sg:address":"107a Richmond Road",
    "sg:city":"Gillingham",
    "sg:classifiers":[
        {
            "category":"Manufacturing",
            "subcategory":"Metals",
            "type":"Manufacturing & Wholesale Goods"
        }
    ],
    "sg:phone":"+44 1634 280537",
    "sg:postcode":"ME7 1LS",
    "sg:province":"Kent",
    "sg:tags":[
        "work",
        "sheet"
    ],
    "wof:name":"Medway Precision Sheet Metal Ltd.",
    "wof:placetype":"venue"
},
  "geometry": {"coordinates":[0.550680995,51.393863678],"type":"Point"}
}