{
  "type": "Feature",
  "properties": {
    "addr:full":"2 Church Street Helston Cornwall TR13 8TG",
    "addr:housenumber":"2",
    "addr:postcode":"tr13 8tg",
    "addr:street":"Church Street",
    "iso:country":"GB",
    "sg:address":"2 Church Street",
    "sg:city":"Helston",
    "sg:classifiers":[
        {
            "category":"Shopping",
            "subcategory":"Clothing, Apparel, & Fashions",
            "type":"Retail Goods"
        }
    ],
    "sg:phone":"+44 1326 572586",
    "sg:postcode":"TR13 8TG",
    "sg:province":"Cornwall",
    "sg:tags":[
        "shop"
    ],
    "wof:name":"Togs Boutique",
    "wof:placetype":"venue"
},
  "geometry": {"coordinates":[-5.274717,50.10096],"type":"Point"}
}