{
  "type": "Feature",
  "properties": {
    "addr:full":"41 Henshaw Street Oldham Lancashire OL1 1NH",
    "addr:housenumber":"41",
    "addr:postcode":"ol1 1nh",
    "addr:street":"Henshaw Street",
    "iso:country":"GB",
    "sg:address":"41 Henshaw Street",
    "sg:city":"Oldham",
    "sg:classifiers":[
        {
            "category":"Shopping",
            "subcategory":"Tobacco",
            "type":"Retail Goods"
        },
        {
            "category":"Retail",
            "subcategory":"Event Space",
            "type":"Services"
        },
        {
            "category":"Food & Beverages",
            "subcategory":"Groceries & Convenience Stores",
            "type":"Retail Goods"
        }
    ],
    "sg:phone":"+44 161 678 8900",
    "sg:postcode":"OL1 1NH",
    "sg:province":"Lancashire",
    "sg:tags":[
        "product",
        "tobacconist",
        "sale"
    ],
    "wof:name":"Cunningham's",
    "wof:placetype":"venue"
},
  "geometry": {"coordinates":[-2.115188,53.543388],"type":"Point"}
}