{
  "type": "Feature",
  "properties": {
    "addr:full":"37 Hallgarth Gateshead Tyne and Wear NE10 8XJ",
    "addr:housenumber":"37",
    "addr:postcode":"ne10 8xj",
    "addr:street":"Hallgarth",
    "iso:country":"GB",
    "sg:address":"37 Hallgarth",
    "sg:city":"Gateshead",
    "sg:classifiers":[
        {
            "category":"Social Services",
            "subcategory":"Child Care",
            "type":"Services"
        },
        {
            "category":"Government",
            "subcategory":"Office",
            "type":"Public Place"
        }
    ],
    "sg:phone":"+44 191 469 2747",
    "sg:postcode":"NE10 8XJ",
    "sg:province":"Tyne and Wear",
    "sg:tags":[
        "home",
        "local",
        "children's"
    ],
    "wof:name":"Felling Children's Home",
    "wof:placetype":"venue"
},
  "geometry": {"coordinates":[-1.542359,54.944084],"type":"Point"}
}