{
  "type": "Feature",
  "properties": {
    "addr:full":"Clump Farm, Desford Road, Thurlaston Leicester Leicestershire LE9 7TE",
    "addr:postcode":"le9 7te",
    "addr:street":"Desford Road",
    "iso:country":"GB",
    "sg:address":"Clump Farm, Desford Road, Thurlaston",
    "sg:city":"Leicester",
    "sg:classifiers":[
        {
            "category":"Farming",
            "subcategory":"Livestock Farm",
            "type":"Manufacturing & Wholesale Goods"
        }
    ],
    "sg:phone":"+44 1455 888330",
    "sg:postcode":"LE9 7TE",
    "sg:province":"Leicestershire",
    "sg:tags":[
        "others"
    ],
    "wof:name":"Robert J Summers",
    "wof:placetype":"venue"
},
  "geometry": {"coordinates":[-1.259144,52.587101],"type":"Point"}
}