{
  "type": "Feature",
  "properties": {
    "iso:country":"GB",
    "sg:address":"Rolston Road",
    "sg:city":"Hornsea",
    "sg:classifiers":[
        {
            "category":"Social Services",
            "subcategory":"Retirement Home",
            "type":"Services"
        }
    ],
    "sg:phone":"+44 1964 534651",
    "sg:postcode":"HU18 1XP",
    "sg:province":"East Riding of Yorkshire",
    "sg:tags":[
        "residential",
        "care"
    ],
    "wof:name":"Willow Garth Residential Care Home",
    "wof:placetype":"venue"
},
  "geometry": {"coordinates":[-0.170054,53.903801],"type":"Point"}
}