{
  "type": "Feature",
  "properties": {
    "addr:full":"381 Pollokshaws Road Glasgow Glasgow City G41 1QZ",
    "addr:housenumber":"381",
    "addr:postcode":"g41 1qz",
    "addr:street":"Pollokshaws Road",
    "iso:country":"GB",
    "sg:address":"381 Pollokshaws Road",
    "sg:city":"Glasgow",
    "sg:classifiers":[
        {
            "category":"Autos & Motor Vehicles",
            "subcategory":"Auto Supplies",
            "type":"Retail Goods"
        }
    ],
    "sg:phone":"+44 141 423 2954",
    "sg:postcode":"G41 1QZ",
    "sg:province":"Glasgow City",
    "sg:tags":[
        "exhaust",
        "absorber",
        "shock"
    ],
    "wof:name":"Kwik-Fit",
    "wof:placetype":"venue"
},
  "geometry": {"coordinates":[-4.2640419006,55.8422012329],"type":"Point"}
}