{
  "type": "Feature",
  "properties": {
    "addr:full":"Boundary Road Norwich Norfolk NR6 5JB",
    "addr:postcode":"nr6 5jb",
    "addr:street":"Boundary Road Norwich Norfolk",
    "iso:country":"GB",
    "sg:address":"Boundary Road",
    "sg:city":"Norwich",
    "sg:classifiers":[
        {
            "category":"Fast Food",
            "type":"Food & Drink"
        }
    ],
    "sg:phone":"+44 1603 787457",
    "sg:postcode":"NR6 5JB",
    "sg:province":"Norfolk",
    "sg:tags":[
        "away",
        "take"
    ],
    "wof:name":"McDonalds",
    "wof:placetype":"venue"
},
  "geometry": {"coordinates":[1.2759150267,52.6561546326],"type":"Point"}
}