{
  "type": "Feature",
  "properties": {
    "addr:full":"Wellow Manor Stud Romsey Hampshire SO51 6DR",
    "addr:postcode":"so51 6dr",
    "iso:country":"GB",
    "sg:address":"Wellow Manor Stud",
    "sg:city":"Romsey",
    "sg:classifiers":[
        {
            "category":"Professional",
            "subcategory":"Engineering",
            "type":"Services"
        }
    ],
    "sg:phone":"+44 1794 322012",
    "sg:postcode":"SO51 6DR",
    "sg:province":"Hampshire",
    "sg:tags":[
        "contractor",
        "electrical",
        "engineer"
    ],
    "wof:name":"Mockett & Merritt Electrical Ltd",
    "wof:placetype":"venue"
},
  "geometry": {"coordinates":[-1.583621,50.992142],"type":"Point"}
}