{
  "type": "Feature",
  "properties": {
    "addr:full":"Little Laver Road, Matching Grn Harlow Essex CM17 0QB",
    "addr:postcode":"cm17 0qb",
    "addr:street":"Little Laver Road",
    "iso:country":"GB",
    "sg:address":"Little Laver Road, Matching Grn",
    "sg:city":"Harlow",
    "sg:classifiers":[
        {
            "category":"Education",
            "subcategory":"School",
            "type":"Public Place"
        }
    ],
    "sg:phone":"+44 1279 731225",
    "sg:postcode":"CM17 0QB",
    "sg:province":"Essex",
    "sg:tags":[
        "local",
        "authority"
    ],
    "wof:name":"Matching Green C Of E Primary School",
    "wof:placetype":"venue"
},
  "geometry": {"coordinates":[0.2175049931,51.7880401611],"type":"Point"}
}