{
  "type": "Feature",
  "properties": {
    "addr:full":"320 Coleford Road, Darnall Sheffield South Yorkshire S9 5PH",
    "addr:housenumber":"320",
    "addr:postcode":"s9 5ph",
    "addr:street":"Coleford Road",
    "iso:country":"GB",
    "sg:address":"320 Coleford Road, Darnall",
    "sg:city":"Sheffield",
    "sg:classifiers":[
        {
            "category":"Freight",
            "type":"Transportation"
        }
    ],
    "sg:phone":"+44 114 261 7442",
    "sg:postcode":"S9 5PH",
    "sg:province":"South Yorkshire",
    "sg:tags":[
        "haulage",
        "road"
    ],
    "wof:name":"B & A Metals",
    "wof:placetype":"venue"
},
  "geometry": {"coordinates":[-1.410153985,53.3878593445],"type":"Point"}
}