{
  "type": "Feature",
  "properties": {
    "addr:full":"197 Hendon Way London Greater London NW2 1JJ",
    "addr:housenumber":"197",
    "addr:postcode":"nw2 1jj",
    "addr:street":"Hendon Way",
    "iso:country":"GB",
    "sg:address":"197 Hendon Way",
    "sg:city":"London",
    "sg:classifiers":[
        {
            "category":"Professional",
            "subcategory":"Business Services",
            "type":"Services"
        }
    ],
    "sg:phone":"+44 20 8455 6924",
    "sg:postcode":"NW2 1JJ",
    "sg:province":"Greater London",
    "sg:tags":[
        "import",
        "export",
        "agent"
    ],
    "wof:name":"Lightstream Ltd.",
    "wof:placetype":"venue"
},
  "geometry": {"coordinates":[-0.2124329954,51.5730667114],"type":"Point"}
}