{
  "type": "Feature",
  "properties": {
    "addr:full":"Avonbridge Wharf, Bridgefoot Stratford-upon-avon Warwickshire CV37 6YY",
    "addr:postcode":"cv37 6yy",
    "addr:street":"Avonbridge",
    "iso:country":"GB",
    "sg:address":"Avonbridge Wharf, Bridgefoot",
    "sg:city":"Stratford-upon-avon",
    "sg:classifiers":[
        {
            "category":"Bars & Pubs",
            "type":"Food & Drink"
        },
        {
            "category":"Landmark",
            "subcategory":"Tourist Attraction",
            "type":"Public Place"
        }
    ],
    "sg:phone":"+44 1789 404600",
    "sg:postcode":"CV37 6YY",
    "sg:province":"Warwickshire",
    "sg:tags":[
        "house",
        "interest",
        "activity"
    ],
    "sg:website":"http://www.coxsyard.co.uk",
    "wof:name":"Cox'S Yard",
    "wof:placetype":"venue"
},
  "geometry": {"coordinates":[-1.702974,52.192612],"type":"Point"}
}