{
  "type": "Feature",
  "properties": {
    "addr:full":"Dickens Road, Old Wolverton Milton Keynes Buckinghamshire MK12 5QQ",
    "addr:postcode":"mk12 5qq",
    "addr:street":"Dickens Road Old",
    "iso:country":"GB",
    "sg:address":"Dickens Road, Old Wolverton",
    "sg:city":"Milton Keynes",
    "sg:classifiers":[
        {
            "category":"Professional",
            "subcategory":"Testing Lab",
            "type":"Services"
        }
    ],
    "sg:phone":"+44 1908 316345",
    "sg:postcode":"MK12 5QQ",
    "sg:province":"Buckinghamshire",
    "sg:tags":[
        "inspection",
        "calibration"
    ],
    "wof:name":"Sonatest Nde Plc",
    "wof:placetype":"venue"
},
  "geometry": {"coordinates":[-0.815298,52.067127],"type":"Point"}
}