{
  "type": "Feature",
  "properties": {
    "addr:full":"9 The Square, Alvechurch Birmingham Worcestershire B48 7LA",
    "addr:housenumber":"9",
    "addr:postcode":"b48 7la",
    "addr:street":"The Square Alvechurch",
    "iso:country":"GB",
    "sg:address":"9 The Square, Alvechurch",
    "sg:city":"Birmingham",
    "sg:classifiers":[
        {
            "category":"Shopping",
            "subcategory":"Pharmacy",
            "type":"Retail Goods"
        }
    ],
    "sg:phone":"+44 121 445 2771",
    "sg:postcode":"B48 7LA",
    "sg:province":"Worcestershire",
    "sg:tags":[
        "pharmacist",
        "dispensing",
        "chemist"
    ],
    "wof:name":"Lloyds Pharmacy Ltd",
    "wof:placetype":"venue"
},
  "geometry": {"coordinates":[-1.959197998,52.3516769409],"type":"Point"}
}