{
  "type": "Feature",
  "properties": {
    "iso:country":"GB",
    "sg:address":"235 Percy Road",
    "sg:city":"Birmingham",
    "sg:classifiers":[
        {
            "category":"Professional",
            "subcategory":"Art Services",
            "type":"Services"
        }
    ],
    "sg:postcode":"B11 3LG",
    "sg:province":"West Midlands",
    "sg:tags":[
        "graphic",
        "designer"
    ],
    "wof:name":"Ropra Design",
    "wof:placetype":"venue"
},
  "geometry": {"coordinates":[-1.858815,52.449642],"type":"Point"}
}