{
  "type": "Feature",
  "properties": {
    "addr:full":"Beacon Ho, Commercial Rd Penryn Cornwall TR10 8AR",
    "addr:postcode":"tr10 8ar",
    "addr:street":"Commercial Rd",
    "iso:country":"GB",
    "sg:address":"Beacon Ho, Commercial Rd",
    "sg:city":"Penryn",
    "sg:classifiers":[
        {
            "category":"Home & Garden",
            "subcategory":"Carpets & Floor Coverings",
            "type":"Retail Goods"
        }
    ],
    "sg:postcode":"TR10 8AR",
    "sg:province":"Cornwall",
    "sg:tags":[
        "carpets",
        "rug",
        "matting"
    ],
    "wof:name":"Chrissy's Mobile Ltd",
    "wof:placetype":"venue"
},
  "geometry": {"coordinates":[-5.099298,50.168224],"type":"Point"}
}