{
  "type": "Feature",
  "properties": {
    "addr:full":"16 Barnes High Street, Barnes London Greater London SW13 9LW",
    "addr:housenumber":"16",
    "addr:postcode":"sw13 9lw",
    "addr:street":"Barnes High Street",
    "iso:country":"GB",
    "sg:address":"16 Barnes High Street, Barnes",
    "sg:city":"London",
    "sg:classifiers":[
        {
            "category":"Coffee & Tea",
            "type":"Food & Drink"
        }
    ],
    "sg:phone":"+44 20 8878 2468",
    "sg:postcode":"SW13 9LW",
    "sg:province":"Greater London",
    "wof:name":"Villa Fern",
    "wof:placetype":"venue"
},
  "geometry": {"coordinates":[-0.248955,51.473534],"type":"Point"}
}