{
  "type": "Feature",
  "properties": {
    "iso:country":"GB",
    "sg:address":"Sinclair, Lon Garreg Fawr",
    "sg:city":"Holyhead",
    "sg:classifiers":[
        {
            "category":"Health Services",
            "subcategory":"Podiatrist",
            "type":"Services"
        }
    ],
    "sg:phone":"+44 1407 860029",
    "sg:postcode":"LL65 2YL",
    "sg:province":"Isle of Anglesey",
    "sg:tags":[
        "podiatrists",
        "chiropodist"
    ],
    "wof:name":"Ivor Shaw",
    "wof:placetype":"venue"
},
  "geometry": {"coordinates":[-4.630714,53.30637],"type":"Point"}
}