{
  "type": "Feature",
  "properties": {
    "addr:full":"13 Buckton Vale Road, Carrbrook Stalybridge Greater Manchester SK15 3LW",
    "addr:housenumber":"13",
    "addr:postcode":"sk15 3lw",
    "addr:street":"Buckton Vale Road Carrbrook",
    "iso:country":"GB",
    "sg:address":"13 Buckton Vale Road, Carrbrook",
    "sg:city":"Stalybridge",
    "sg:classifiers":[
        {
            "category":"Personal",
            "subcategory":"Beauty Salon",
            "type":"Services"
        }
    ],
    "sg:phone":"+44 1457 835600",
    "sg:postcode":"SK15 3LW",
    "sg:province":"Greater Manchester",
    "sg:tags":[
        "unisex",
        "hairdresser"
    ],
    "wof:name":"Biba Hair Studio",
    "wof:placetype":"venue"
},
  "geometry": {"coordinates":[-2.026484,53.503899],"type":"Point"}
}