{
  "type": "Feature",
  "properties": {
    "iso:country":"GB",
    "sg:address":"31 Sydney St",
    "sg:city":"Brighton",
    "sg:classifiers":[
        {
            "category":"Manufacturing",
            "subcategory":"Textiles",
            "type":"Manufacturing & Wholesale Goods"
        }
    ],
    "sg:postcode":"BN1 4EP",
    "sg:province":"East Sussex",
    "sg:tags":[
        "merchant",
        "agent"
    ],
    "wof:name":"Seargent,David,",
    "wof:placetype":"venue"
},
  "geometry": {"coordinates":[-0.1374929994,50.8277015686],"type":"Point"}
}