{
  "type": "Feature",
  "properties": {
    "addr:full":"361 High Rd Harrow Greater London HA3 5EQ",
    "addr:housenumber":"361",
    "addr:postcode":"ha3 5eq",
    "addr:street":"High Rd",
    "iso:country":"GB",
    "sg:address":"361 High Rd",
    "sg:city":"Harrow",
    "sg:classifiers":[
        {
            "category":"Shopping",
            "subcategory":"Tobacco",
            "type":"Retail Goods"
        },
        {
            "category":"Retail",
            "subcategory":"Event Space",
            "type":"Services"
        }
    ],
    "sg:phone":"+44 20 8427 3074",
    "sg:postcode":"HA3 5EQ",
    "sg:province":"Greater London",
    "sg:tags":[
        "product",
        "tobacconist",
        "sale"
    ],
    "wof:name":"Freeway",
    "wof:placetype":"venue"
},
  "geometry": {"coordinates":[-0.339841,51.604271],"type":"Point"}
}