{
  "type": "Feature",
  "properties": {
    "addr:full":"1a Turners Road South Luton Bedfordshire LU2 0PH",
    "addr:housenumber":"1a",
    "addr:postcode":"lu2 0ph",
    "addr:street":"Turners Road South",
    "iso:country":"GB",
    "sg:address":"1a Turners Road South",
    "sg:city":"Luton",
    "sg:classifiers":[
        {
            "category":"Professional",
            "subcategory":"Detective & Security Services",
            "type":"Services"
        },
        {
            "category":"Home & Garden",
            "subcategory":"Building Materials",
            "type":"Retail Goods"
        }
    ],
    "sg:phone":"+44 1582 455188",
    "sg:postcode":"LU2 0PH",
    "sg:province":"Bedfordshire",
    "sg:tags":[
        "hinge",
        "locksmith"
    ],
    "wof:name":"Makesafe",
    "wof:placetype":"venue"
},
  "geometry": {"coordinates":[-0.402031,51.890472],"type":"Point"}
}