{
  "type": "Feature",
  "properties": {
    "addr:full":"22 Wood End Gardens Northolt Greater London UB5 4QJ",
    "addr:housenumber":"22",
    "addr:postcode":"ub5 4qj",
    "addr:street":"Wood End Gardens",
    "iso:country":"GB",
    "sg:address":"22 Wood End Gardens",
    "sg:city":"Northolt",
    "sg:classifiers":[
        {
            "category":"Shopping",
            "subcategory":"Department Store",
            "type":"Retail Goods"
        }
    ],
    "sg:phone":"+44 20 8422 2053",
    "sg:postcode":"UB5 4QJ",
    "sg:province":"Greater London",
    "wof:name":"Chocolate Box",
    "wof:placetype":"venue"
},
  "geometry": {"coordinates":[-0.3473570049,51.557636261],"type":"Point"}
}