{
  "type": "Feature",
  "properties": {
    "addr:full":"82 Rosemary Hill Road Sutton Coldfield Staffordshire B74 4HJ",
    "addr:housenumber":"82",
    "addr:postcode":"b74 4hj",
    "addr:street":"Rosemary Hill Road",
    "iso:country":"GB",
    "sg:address":"82 Rosemary Hill Road",
    "sg:city":"Sutton Coldfield",
    "sg:classifiers":[
        {
            "category":"Professional",
            "subcategory":"Management & Consulting",
            "type":"Services"
        }
    ],
    "sg:phone":"+44 121 580 9080",
    "sg:postcode":"B74 4HJ",
    "sg:province":"Staffordshire",
    "sg:tags":[
        "marketing",
        "consultant"
    ],
    "wof:name":"John Slade",
    "wof:placetype":"venue"
},
  "geometry": {"coordinates":[-1.860814,52.593983],"type":"Point"}
}