{
  "type": "Feature",
  "properties": {
    "iso:country":"GB",
    "sg:address":"Springvale Nursery, Mcgillivary Avenue",
    "sg:city":"Saltcoats",
    "sg:classifiers":[
        {
            "category":"Building & Trades",
            "subcategory":"Plumbing",
            "type":"Services"
        }
    ],
    "sg:phone":"+44 1294 465348",
    "sg:postcode":"KA21 6BN",
    "sg:province":"North Ayrshire",
    "sg:tags":[
        "heating"
    ],
    "wof:name":"J Bain Plumbers",
    "wof:placetype":"venue"
},
  "geometry": {"coordinates":[-4.7875790596,55.6434402466],"type":"Point"}
}