{
  "type": "Feature",
  "properties": {
    "addr:full":", Temple Sowerby Penrith Cumbria CA10 1RZ",
    "addr:postcode":"ca10 1rz",
    "iso:country":"GB",
    "sg:address":", Temple Sowerby",
    "sg:city":"Penrith",
    "sg:classifiers":[
        {
            "category":"Government",
            "subcategory":"Post Office",
            "type":"Public Place"
        }
    ],
    "sg:phone":"+44 17683 61319",
    "sg:postcode":"CA10 1RZ",
    "sg:province":"Cumbria",
    "wof:name":"Temple Sowerby P.O",
    "wof:placetype":"venue"
},
  "geometry": {"coordinates":[-2.6034,54.6367],"type":"Point"}
}