{
  "type": "Feature",
  "properties": {
    "addr:full":"Unit 3, Lemar Trad Est Birmingham West Midlands B30 2XH",
    "addr:housenumber":"unit 3",
    "addr:postcode":"b30 2xh",
    "addr:street":"Trad Est",
    "iso:country":"GB",
    "sg:address":"Unit 3, Lemar Trad Est",
    "sg:city":"Birmingham",
    "sg:classifiers":[
        {
            "category":"Retail",
            "subcategory":"Auto Repair",
            "type":"Services"
        }
    ],
    "sg:postcode":"B30 2XH",
    "sg:province":"West Midlands",
    "sg:tags":[
        "body",
        "car"
    ],
    "wof:name":"T T S Motors Ltd",
    "wof:placetype":"venue"
},
  "geometry": {"coordinates":[-1.91457,52.43697],"type":"Point"}
}