{
  "type": "Feature",
  "properties": {
    "addr:full":"11 Pound Barton, Sutton Veny Warminster Somerset BA12 7BT",
    "addr:housenumber":"11;barton;veny",
    "addr:postcode":"ba12 7bt",
    "addr:street":"Pound",
    "iso:country":"GB",
    "sg:address":"11 Pound Barton, Sutton Veny",
    "sg:city":"Warminster",
    "sg:classifiers":[
        {
            "category":"Home & Garden",
            "subcategory":"Home Furnishings",
            "type":"Retail Goods"
        },
        {
            "category":"Home & Garden",
            "subcategory":"Building Materials",
            "type":"Retail Goods"
        }
    ],
    "sg:phone":"+44 1985 840104",
    "sg:postcode":"BA12 7BT",
    "sg:province":"Somerset",
    "sg:tags":[
        "installers",
        "planner",
        "kitchen",
        "furnishers"
    ],
    "wof:name":"Airey & Guy",
    "wof:placetype":"venue"
},
  "geometry": {"coordinates":[-2.147459,51.17878],"type":"Point"}
}