{
  "type": "Feature",
  "properties": {
    "iso:country":"GB",
    "sg:address":"70 Priory Oak, Brackla",
    "sg:city":"Bridgend",
    "sg:classifiers":[
        {
            "category":"Building & Trades",
            "subcategory":"Construction",
            "type":"Services"
        }
    ],
    "sg:phone":"+44 1656 767091",
    "sg:postcode":"CF31 2HZ",
    "sg:province":"Bridgend",
    "sg:tags":[
        "roofing",
        "monumental",
        "mason"
    ],
    "wof:name":"Edwards Memorials",
    "wof:placetype":"venue"
},
  "geometry": {"coordinates":[-3.551775,51.504124],"type":"Point"}
}