{
  "type": "Feature",
  "properties": {
    "addr:full":"97 Highbury Rd Bristol City of Bristol BS4 3DP",
    "addr:housenumber":"97",
    "addr:postcode":"bs4 3dp",
    "addr:street":"Highbury Rd",
    "iso:country":"GB",
    "sg:address":"97 Highbury Rd",
    "sg:city":"Bristol",
    "sg:classifiers":[
        {
            "category":"Building & Trades",
            "subcategory":"Construction",
            "type":"Services"
        }
    ],
    "sg:phone":"+44 117 985 9923",
    "sg:postcode":"BS4 3DP",
    "sg:province":"City of Bristol",
    "sg:tags":[
        "builder"
    ],
    "wof:name":"Price Preservation",
    "wof:placetype":"venue"
},
  "geometry": {"coordinates":[-2.6031019688,51.4334526062],"type":"Point"}
}