{
  "type": "Feature",
  "properties": {
    "iso:country":"GB",
    "sg:address":"18 Waverley Road",
    "sg:city":"Innerleithen",
    "sg:classifiers":[
        {
            "category":"Shopping",
            "subcategory":"Baby Store",
            "type":"Retail Goods"
        }
    ],
    "sg:phone":"+44 1896 831661",
    "sg:postcode":"EH44 6QH",
    "sg:province":"Scottish Borders",
    "sg:tags":[
        "babywear",
        "childrens"
    ],
    "wof:name":"Janets Cut & Sew",
    "wof:placetype":"venue"
},
  "geometry": {"coordinates":[-3.062859,55.618671],"type":"Point"}
}