{
  "type": "Feature",
  "properties": {
    "iso:country":"GB",
    "sg:address":"22 Pudding Chare",
    "sg:city":"Newcastle Upon Tyne",
    "sg:classifiers":[
        {
            "category":"Restaurant",
            "type":"Food & Drink"
        }
    ],
    "sg:phone":"+44 191 261 1931",
    "sg:postcode":"NE1 1UE",
    "sg:province":"Tyne and Wear",
    "sg:tags":[
        "american"
    ],
    "wof:name":"Buffalo's American Diner",
    "wof:placetype":"venue"
},
  "geometry": {"coordinates":[-1.6139940023,54.9706840515],"type":"Point"}
}