{
  "type": "Feature",
  "properties": {
    "iso:country":"GB",
    "sg:address":"33 Barony Terrace",
    "sg:city":"Edinburgh",
    "sg:classifiers":[
        {
            "category":"Professional",
            "subcategory":"Engineering",
            "type":"Services"
        }
    ],
    "sg:phone":"+44 131 538 7887",
    "sg:postcode":"EH12 8RF",
    "sg:province":"City of Edinburgh",
    "sg:tags":[
        "contractor",
        "electrical",
        "engineer"
    ],
    "wof:name":"Brent Anderson",
    "wof:placetype":"venue"
},
  "geometry": {"coordinates":[-3.303785,55.951839],"type":"Point"}
}