{
  "type": "Feature",
  "properties": {
    "iso:country":"GB",
    "sg:address":"Unit 25 Dalziel Workspace, Mason St",
    "sg:city":"Motherwell",
    "sg:classifiers":[
        {
            "category":"Professional",
            "subcategory":"Management & Consulting",
            "type":"Services"
        }
    ],
    "sg:phone":"+44 1698 260880",
    "sg:postcode":"ML1 1YE",
    "sg:province":"North Lanarkshire",
    "sg:tags":[
        "marketing",
        "consultant"
    ],
    "wof:name":"M S Consultancy",
    "wof:placetype":"venue"
},
  "geometry": {"coordinates":[-3.989529,55.790562],"type":"Point"}
}