{
  "type": "Feature",
  "properties": {
    "iso:country":"GB",
    "sg:address":"4 Lammas Gate, 82 Meadrow",
    "sg:city":"Godalming",
    "sg:classifiers":[
        {
            "category":"Home & Garden",
            "subcategory":"Hardware",
            "type":"Retail Goods"
        }
    ],
    "sg:phone":"+44 1483 239000",
    "sg:postcode":"GU7 3HS",
    "sg:province":"Surrey",
    "sg:tags":[
        "device",
        "fixing",
        "fastener"
    ],
    "wof:name":"S E P Industrial Holdings Plc",
    "wof:placetype":"venue"
},
  "geometry": {"coordinates":[-0.603569,51.198761],"type":"Point"}
}