{
  "type": "Feature",
  "properties": {
    "iso:country":"GB",
    "sg:address":"14 Bank House, St Mary's Gate",
    "sg:city":"Manchester",
    "sg:classifiers":[
        {
            "category":"Wholesale",
            "subcategory":"Stationery",
            "type":"Manufacturing & Wholesale Goods"
        },
        {
            "category":"Shopping",
            "subcategory":"Crafts & Fabrics",
            "type":"Retail Goods"
        }
    ],
    "sg:phone":"+44 161 839 1500",
    "sg:postcode":"M1 1PX",
    "sg:province":"Greater Manchester",
    "sg:tags":[
        "supplier",
        "material",
        "art"
    ],
    "wof:name":"Paperchase Products Ltd",
    "wof:placetype":"venue"
},
  "geometry": {"coordinates":[-2.3472878933,53.4978103638],"type":"Point"}
}