{
  "type": "Feature",
  "properties": {
    "iso:country":"GB",
    "sg:address":"Dean Road",
    "sg:city":"South Shields",
    "sg:classifiers":[
        {
            "category":"Health Services",
            "subcategory":"Hospital",
            "type":"Services"
        }
    ],
    "sg:phone":"+44 191 451 6455",
    "sg:postcode":"NE33 5LG",
    "sg:province":"Tyne and Wear",
    "wof:name":"Deans Hospital",
    "wof:placetype":"venue"
},
  "geometry": {"coordinates":[-1.43689,54.983559],"type":"Point"}
}