{
  "type": "Feature",
  "properties": {
    "iso:country":"GB",
    "sg:address":"Greystone Yard, Nottinghill Way, Lower Weare",
    "sg:city":"Axbridge",
    "sg:classifiers":[
        {
            "category":"Home & Garden",
            "subcategory":"Building Materials",
            "type":"Retail Goods"
        }
    ],
    "sg:phone":"+44 1934 733380",
    "sg:postcode":"BS26 2JU",
    "sg:province":"Somerset",
    "sg:tags":[
        "fencing"
    ],
    "wof:name":"Pearman Fencing",
    "wof:placetype":"venue"
},
  "geometry": {"coordinates":[-2.818409,51.288391],"type":"Point"}
}