{
  "type": "Feature",
  "properties": {
    "iso:country":"GB",
    "sg:address":"67-69 Stamford Road",
    "sg:city":"Kettering",
    "sg:classifiers":[
        {
            "category":"Shopping",
            "type":"Retail Goods"
        }
    ],
    "sg:phone":"+44 1536 522930",
    "sg:postcode":"NN16 8XZ",
    "sg:province":"Northamptonshire",
    "sg:tags":[
        "part",
        "accessory"
    ],
    "wof:name":"Autofactors",
    "wof:placetype":"venue"
},
  "geometry": {"coordinates":[-0.7151989937,52.4032173157],"type":"Point"}
}