{
  "type": "Feature",
  "properties": {
    "iso:country":"GB",
    "sg:address":"177 Danford Lane",
    "sg:city":"Solihull",
    "sg:classifiers":[
        {
            "category":"Building & Trades",
            "subcategory":"Construction",
            "type":"Services"
        }
    ],
    "sg:phone":"+44 121 744 0809",
    "sg:postcode":"B91 1QR",
    "sg:province":"West Midlands",
    "sg:tags":[
        "roofing"
    ],
    "wof:name":"All Types Roofing",
    "wof:placetype":"venue"
},
  "geometry": {"coordinates":[-1.80811,52.412998],"type":"Point"}
}