{
  "type": "Feature",
  "properties": {
    "addr:full":"14 Mollison Drive Wallington Surrey SM6 9BY",
    "addr:housenumber":"14",
    "addr:postcode":"sm6 9by",
    "addr:street":"Mollison Drive",
    "iso:country":"GB",
    "sg:address":"14 Mollison Drive",
    "sg:city":"Wallington",
    "sg:classifiers":[
        {
            "category":"Home & Garden",
            "subcategory":"Kitchen Supply",
            "type":"Retail Goods"
        }
    ],
    "sg:phone":"+44 20 8401 6980",
    "sg:postcode":"SM6 9BY",
    "sg:province":"Surrey",
    "sg:tags":[
        "equipment",
        "catering"
    ],
    "wof:name":"G M-Autoflow",
    "wof:placetype":"venue"
},
  "geometry": {"coordinates":[-0.1293839961,51.3589706421],"type":"Point"}
}