{
  "type": "Feature",
  "properties": {
    "addr:full":"26 The Pavilion, High Street Waltham Cross Essex EN8 7BY",
    "addr:housenumber":"26",
    "addr:postcode":"en8 7by",
    "addr:street":"The;High Street",
    "iso:country":"GB",
    "sg:address":"26 The Pavilion, High Street",
    "sg:city":"Waltham Cross",
    "sg:classifiers":[
        {
            "category":"Shopping",
            "subcategory":"Pharmacy",
            "type":"Retail Goods"
        }
    ],
    "sg:phone":"+44 1992 717821",
    "sg:postcode":"EN8 7BY",
    "sg:province":"Essex",
    "sg:tags":[
        "pharmacist",
        "store",
        "drug",
        "chemist"
    ],
    "wof:name":"Niti Pharmacy",
    "wof:placetype":"venue"
},
  "geometry": {"coordinates":[-0.0338140018,51.6905097961],"type":"Point"}
}