{
  "type": "Feature",
  "properties": {
    "iso:country":"GB",
    "sg:address":"293 Heysham Rd",
    "sg:city":"Morecambe",
    "sg:classifiers":[
        {
            "category":"Food & Beverages",
            "subcategory":"Liquor & Beverages",
            "type":"Retail Goods"
        }
    ],
    "sg:postcode":"LA3 1PY",
    "sg:province":"Lancashire",
    "sg:tags":[
        "beer",
        "spirit",
        "wines"
    ],
    "wof:name":"Patel,A,",
    "wof:placetype":"venue"
},
  "geometry": {"coordinates":[-2.891317,54.054306],"type":"Point"}
}