{
  "type": "Feature",
  "properties": {
    "addr:full":"36 Howard Avenue Bexley Kent DA5 3BE",
    "addr:housenumber":"36",
    "addr:postcode":"da5 3be",
    "addr:street":"Howard Avenue",
    "iso:country":"GB",
    "sg:address":"36 Howard Avenue",
    "sg:city":"Bexley",
    "sg:classifiers":[
        {
            "category":"Professional",
            "subcategory":"Art Services",
            "type":"Services"
        },
        {
            "category":"Building & Trades",
            "subcategory":"Construction",
            "type":"Services"
        }
    ],
    "sg:phone":"+44 20 8301 0241",
    "sg:postcode":"DA5 3BE",
    "sg:province":"Kent",
    "sg:tags":[
        "decorator",
        "painter"
    ],
    "wof:name":"Penningtons",
    "wof:placetype":"venue"
},
  "geometry": {"coordinates":[0.1193509996,51.4406547546],"type":"Point"}
}