{
  "type": "Feature",
  "properties": {
    "iso:country":"GB",
    "sg:address":"Ammondale, Spa Road",
    "sg:city":"Llandrindod Wells",
    "sg:classifiers":[
        {
            "category":"Fast Food",
            "type":"Food & Drink"
        },
        {
            "category":"Cafe",
            "type":"Food & Drink"
        }
    ],
    "sg:postcode":"LD1 5EY",
    "sg:province":"Powys",
    "sg:tags":[
        "tea",
        "away",
        "room",
        "take"
    ],
    "wof:name":"Upstairs Downstairs",
    "wof:placetype":"venue"
},
  "geometry": {"coordinates":[-3.377029,52.24575],"type":"Point"}
}