{
  "type": "Feature",
  "properties": {
    "iso:country":"GB",
    "sg:address":"2 Bull Yard",
    "sg:city":"Southwell",
    "sg:classifiers":[
        {
            "category":"Farming",
            "subcategory":"Livestock Farm",
            "type":"Manufacturing & Wholesale Goods"
        },
        {
            "category":"Food & Beverages",
            "subcategory":"Fruits & Vegetables",
            "type":"Retail Goods"
        }
    ],
    "sg:phone":"+44 1636 812046",
    "sg:postcode":"NG25 0EH",
    "sg:province":"Nottinghamshire",
    "sg:tags":[
        "breeder",
        "greengrocer"
    ],
    "wof:name":"D A Stone",
    "wof:placetype":"venue"
},
  "geometry": {"coordinates":[-0.955641,53.078743],"type":"Point"}
}