{
  "type": "Feature",
  "properties": {
    "iso:country":"GB",
    "sg:address":"218 High Road",
    "sg:city":"Ilford",
    "sg:classifiers":[
        {
            "category":"Retail",
            "subcategory":"Driving School",
            "type":"Services"
        }
    ],
    "sg:phone":"+44 20 8478 7454",
    "sg:postcode":"IG1 1EQ",
    "sg:province":"Essex",
    "wof:name":"The British School of Motoring Ltd.",
    "wof:placetype":"venue"
},
  "geometry": {"coordinates":[0.077284,51.559658],"type":"Point"}
}