{
  "type": "Feature",
  "properties": {
    "addr:full":"27 White Hill Ct, Broad St Chesham Buckinghamshire HP5 3DY",
    "addr:housenumber":"27",
    "addr:postcode":"hp5 3dy",
    "addr:street":"White Hill Ct Broad St",
    "iso:country":"GB",
    "sg:address":"27 White Hill Ct, Broad St",
    "sg:city":"Chesham",
    "sg:classifiers":[
        {
            "category":"Professional",
            "type":"Services"
        }
    ],
    "sg:postcode":"HP5 3DY",
    "sg:province":"Buckinghamshire",
    "sg:tags":[
        "entertainer"
    ],
    "wof:name":"Peterson,Thomas,",
    "wof:placetype":"venue"
},
  "geometry": {"coordinates":[-0.6093329787,51.7105369568],"type":"Point"}
}