{
  "type": "Feature",
  "properties": {
    "addr:full":"The Travel Shop Northwick Park, Hospital Watford Road Harrow Greater London HA1 3UJ",
    "addr:postcode":"ha1 3uj",
    "addr:street":"Watford Road",
    "iso:country":"GB",
    "sg:address":"The Travel Shop Northwick Park, Hospital Watford Road",
    "sg:city":"Harrow",
    "sg:classifiers":[
        {
            "category":"Travel",
            "subcategory":"Travel Agent",
            "type":"Entertainment"
        }
    ],
    "sg:phone":"+44 20 8423 1242",
    "sg:postcode":"HA1 3UJ",
    "sg:province":"Greater London",
    "wof:name":"Ickenham Travel Group Plc",
    "wof:placetype":"venue"
},
  "geometry": {"coordinates":[-0.3360820115,51.5787849426],"type":"Point"}
}