{
  "type": "Feature",
  "properties": {
    "iso:country":"GB",
    "sg:address":"314 Margate Rd",
    "sg:city":"Ramsgate",
    "sg:classifiers":[
        {
            "category":"Autos & Motor Vehicles",
            "subcategory":"Motorcycle Sales",
            "type":"Retail Goods"
        }
    ],
    "sg:phone":"+44 1843 599190",
    "sg:postcode":"CT12 6AN",
    "sg:province":"Kent",
    "sg:tags":[
        "chauffeur",
        "driven",
        "car"
    ],
    "wof:name":"Occasions",
    "wof:placetype":"venue"
},
  "geometry": {"coordinates":[1.4028459787,51.351764679],"type":"Point"}
}