{
  "type": "Feature",
  "properties": {
    "iso:country":"GB",
    "sg:address":"7 Deep Acres",
    "sg:city":"High Wycombe",
    "sg:classifiers":[
        {
            "category":"Real Estate",
            "subcategory":"Surveying",
            "type":"Services"
        }
    ],
    "sg:postcode":"HP6 5NX",
    "sg:province":"Buckinghamshire",
    "sg:tags":[
        "surveyor",
        "valuer"
    ],
    "wof:name":"John Graham & Co",
    "wof:placetype":"venue"
},
  "geometry": {"coordinates":[-0.6107590199,51.6845817566],"type":"Point"}
}