{
  "type": "Feature",
  "properties": {
    "iso:country":"GB",
    "sg:address":"119 Groveley Road",
    "sg:city":"Sunbury-on-thames",
    "sg:classifiers":[
        {
            "category":"Professional",
            "subcategory":"Computer Services",
            "type":"Services"
        }
    ],
    "sg:phone":"+44 20 8893 2959",
    "sg:postcode":"TW16 7JZ",
    "sg:province":"Surrey",
    "sg:tags":[
        "system",
        "software"
    ],
    "wof:name":"Unimart Computers Ltd.",
    "wof:placetype":"venue"
},
  "geometry": {"coordinates":[-0.421373,51.429188],"type":"Point"}
}