{
  "type": "Feature",
  "properties": {
    "addr:full":"17 Highcroft Crescent Huddersfield West Yorkshire HD5 8NF",
    "addr:housenumber":"17",
    "addr:postcode":"hd5 8nf",
    "addr:street":"Highcroft Crescent",
    "iso:country":"GB",
    "sg:address":"17 Highcroft Crescent",
    "sg:city":"Huddersfield",
    "sg:classifiers":[
        {
            "category":"Retail",
            "subcategory":"Storage",
            "type":"Services"
        }
    ],
    "sg:phone":"+44 1484 538917",
    "sg:postcode":"HD5 8NF",
    "sg:province":"West Yorkshire",
    "sg:tags":[
        "household",
        "activity",
        "domestic",
        "removal"
    ],
    "wof:name":"Bellwoods Removals",
    "wof:placetype":"venue"
},
  "geometry": {"coordinates":[-1.750213027,53.6343536377],"type":"Point"}
}