{
  "type": "Feature",
  "properties": {
    "iso:country":"GB",
    "sg:address":"282 Plumstead High Street",
    "sg:city":"London",
    "sg:classifiers":[
        {
            "category":"Bars & Pubs",
            "type":"Food & Drink"
        }
    ],
    "sg:phone":"+44 20 8854 2795",
    "sg:postcode":"SE18 1JT",
    "sg:province":"Greater London",
    "sg:tags":[
        "pubs",
        "inn"
    ],
    "wof:name":"Plume of Feathers",
    "wof:placetype":"venue"
},
  "geometry": {"coordinates":[0.099413,51.485756],"type":"Point"}
}