{
  "type": "Feature",
  "properties": {
    "addr:full":"18 Academy Street Coatbridge North Lanarkshire ML5 3AU",
    "addr:housenumber":"18",
    "addr:postcode":"ml5 3au",
    "addr:street":"Academy Street",
    "iso:country":"GB",
    "sg:address":"18 Academy Street",
    "sg:city":"Coatbridge",
    "sg:classifiers":[
        {
            "category":"Professional",
            "subcategory":"Lawyer & Legal Services",
            "type":"Services"
        }
    ],
    "sg:phone":"+44 1236 600600",
    "sg:postcode":"ML5 3AU",
    "sg:province":"North Lanarkshire",
    "sg:tags":[
        "solicitor"
    ],
    "wof:name":"Trainor Alston",
    "wof:placetype":"venue"
},
  "geometry": {"coordinates":[-4.027972,55.863724],"type":"Point"}
}