{
  "type": "Feature",
  "properties": {
    "iso:country":"GB",
    "sg:address":"16 Greasbrough Road, Parkgate",
    "sg:city":"Rotherham",
    "sg:classifiers":[
        {
            "category":"Personal",
            "subcategory":"Beauty Salon",
            "type":"Services"
        }
    ],
    "sg:phone":"+44 1709 525948",
    "sg:postcode":"S62 6HN",
    "sg:province":"South Yorkshire",
    "sg:tags":[
        "unisex",
        "hairdresser"
    ],
    "wof:name":"Rifters",
    "wof:placetype":"venue"
},
  "geometry": {"coordinates":[-1.344709,53.45253],"type":"Point"}
}