{
  "type": "Feature",
  "properties": {
    "addr:full":"54 Derwent Close, Brownsover Rugby Warwickshire CV21 1JX",
    "addr:housenumber":"54",
    "addr:postcode":"cv21 1jx",
    "addr:street":"Derwent Close",
    "iso:country":"GB",
    "sg:address":"54 Derwent Close, Brownsover",
    "sg:city":"Rugby",
    "sg:classifiers":[
        {
            "category":"Health Services",
            "subcategory":"Podiatrist",
            "type":"Services"
        }
    ],
    "sg:phone":"+44 1788 567890",
    "sg:postcode":"CV21 1JX",
    "sg:province":"Warwickshire",
    "sg:tags":[
        "podiatrists",
        "chiropodist"
    ],
    "wof:name":"J.E Elliott",
    "wof:placetype":"venue"
},
  "geometry": {"coordinates":[-1.248111,52.388165],"type":"Point"}
}