{
  "type": "Feature",
  "properties": {
    "addr:full":"Unit 13-16, 54-60 Hoyland Road Sheffield South Yorkshire S3 8AB",
    "addr:housenumber":"unit 13-16",
    "addr:postcode":"54-60;s3 8ab",
    "addr:street":"Hoyland Road",
    "iso:country":"GB",
    "sg:address":"Unit 13-16, 54-60 Hoyland Road",
    "sg:city":"Sheffield",
    "sg:classifiers":[
        {
            "category":"Professional",
            "subcategory":"Printing & Photocopies",
            "type":"Services"
        }
    ],
    "sg:phone":"+44 114 275 8680",
    "sg:postcode":"S3 8AB",
    "sg:province":"South Yorkshire",
    "sg:tags":[
        "printer"
    ],
    "wof:name":"P F M Promotions Ltd.",
    "wof:placetype":"venue"
},
  "geometry": {"coordinates":[-1.48552,53.396839],"type":"Point"}
}