{
  "type": "Feature",
  "properties": {
    "addr:full":"2 Ridgemount Street London Greater London WC1E 7AA",
    "addr:housenumber":"2",
    "addr:postcode":"wc1e 7aa",
    "addr:street":"Ridgemount Street",
    "iso:country":"GB",
    "sg:address":"2 Ridgemount Street",
    "sg:city":"London",
    "sg:classifiers":[
        {
            "category":"Banks & Credit Unions",
            "subcategory":"Financial Services",
            "type":"Services"
        }
    ],
    "sg:postcode":"WC1E 7AA",
    "sg:province":"Greater London",
    "sg:tags":[
        "consultant"
    ],
    "wof:name":"The Esop Centre Ltd.",
    "wof:placetype":"venue"
},
  "geometry": {"coordinates":[-0.1310250014,51.5204086304],"type":"Point"}
}