{
  "type": "Feature",
  "properties": {
    "addr:full":"Eardley House, 4 Uxbridge St, Kensington Kensington Greater London W8 7SY",
    "addr:housenumber":"4",
    "addr:postcode":"w8 7sy",
    "addr:street":"Uxbridge St",
    "iso:country":"GB",
    "sg:address":"Eardley House, 4 Uxbridge St, Kensington",
    "sg:city":"Kensington",
    "sg:classifiers":[
        {
            "category":"Manufacturing",
            "subcategory":"Electronics",
            "type":"Manufacturing & Wholesale Goods"
        }
    ],
    "sg:phone":"+44 20 7792 8188",
    "sg:postcode":"W8 7SY",
    "sg:province":"Greater London",
    "sg:tags":[
        "mnfr",
        "component",
        "electronic"
    ],
    "wof:name":"Neutrik Ltd",
    "wof:placetype":"venue"
},
  "geometry": {"coordinates":[-0.1993660033,51.508266449],"type":"Point"}
}