{
  "type": "Feature",
  "properties": {
    "iso:country":"GB",
    "sg:address":"Horsepond Meadow Industrial Estate",
    "sg:city":"South Molton",
    "sg:classifiers":[
        {
            "category":"Bus Stop",
            "subcategory":"None",
            "type":"Transportation"
        }
    ],
    "sg:phone":"+44 1769 574574",
    "sg:postcode":"EX36 4EJ",
    "sg:province":"Devon",
    "sg:tags":[
        "gasket"
    ],
    "wof:name":"Bluemay Weston",
    "wof:placetype":"venue"
},
  "geometry": {"coordinates":[-3.836599,51.013554],"type":"Point"}
}