{
  "type": "Feature",
  "properties": {
    "addr:full":"23 Dalby Road Melton Mowbray Leicestershire LE13 0BG",
    "addr:housenumber":"23",
    "addr:postcode":"le13 0bg",
    "addr:street":"Dalby Road",
    "iso:country":"GB",
    "sg:address":"23 Dalby Road",
    "sg:city":"Melton Mowbray",
    "sg:classifiers":[
        {
            "category":"Health Services",
            "subcategory":"Clinic",
            "type":"Services"
        }
    ],
    "sg:postcode":"LE13 0BG",
    "sg:province":"Leicestershire",
    "sg:tags":[
        "aromatherapy"
    ],
    "wof:name":"Shirley Franklin Aromatherapy",
    "wof:placetype":"venue"
},
  "geometry": {"coordinates":[-0.8905400038,52.7617683411],"type":"Point"}
}