{
  "type": "Feature",
  "properties": {
    "iso:country":"GB",
    "sg:address":"Brooklyn Farm, North Hill, Horndon-on-the-hill",
    "sg:city":"Stanford-le-hope",
    "sg:classifiers":[
        {
            "category":"Freight",
            "type":"Transportation"
        }
    ],
    "sg:phone":"+44 1375 640104",
    "sg:postcode":"SS17 8QA",
    "sg:province":"Essex",
    "sg:tags":[
        "haulage",
        "transport",
        "road"
    ],
    "wof:name":"Kartic Freight Services",
    "wof:placetype":"venue"
},
  "geometry": {"coordinates":[0.40201,51.526279],"type":"Point"}
}