{
  "type": "Feature",
  "properties": {
    "addr:full":"50 High Street Beauly Highland IV4 7BX",
    "addr:housenumber":"50",
    "addr:postcode":"iv4 7bx",
    "addr:street":"High Street",
    "iso:country":"GB",
    "sg:address":"50 High Street",
    "sg:city":"Beauly",
    "sg:classifiers":[
        {
            "category":"Shopping",
            "subcategory":"Crafts & Fabrics",
            "type":"Retail Goods"
        },
        {
            "category":"Manufacturing",
            "subcategory":"Textiles",
            "type":"Manufacturing & Wholesale Goods"
        }
    ],
    "sg:phone":"+44 1463 783017",
    "sg:postcode":"IV4 7BX",
    "sg:province":"Highland",
    "sg:tags":[
        "knitwear",
        "producer"
    ],
    "wof:name":"LYNDA USHER",
    "wof:placetype":"venue"
},
  "geometry": {"coordinates":[-4.459616,57.484089],"type":"Point"}
}