{
  "type": "Feature",
  "properties": {
    "iso:country":"GB",
    "sg:address":"36 Moss Street",
    "sg:city":"Paisley",
    "sg:classifiers":[
        {
            "category":"Shopping",
            "subcategory":"Bicycles & Sporting Goods",
            "type":"Retail Goods"
        },
        {
            "category":"Wholesale",
            "subcategory":"Sporting Goods",
            "type":"Manufacturing & Wholesale Goods"
        }
    ],
    "sg:phone":"+44 141 887 5536",
    "sg:postcode":"PA1 1BA",
    "sg:province":"Renfrewshire",
    "sg:tags":[
        "supplier",
        "equipment",
        "camping"
    ],
    "sg:website":"http://www.summits.co.uk",
    "wof:name":"Summits Ltd",
    "wof:placetype":"venue"
},
  "geometry": {"coordinates":[-4.425468,55.847111],"type":"Point"}
}