{
  "type": "Feature",
  "properties": {
    "iso:country":"GB",
    "sg:address":"27 Ledger Drive",
    "sg:city":"Addlestone",
    "sg:classifiers":[
        {
            "category":"Real Estate",
            "subcategory":"Real Estate Services",
            "type":"Services"
        },
        {
            "category":"Retail",
            "subcategory":"Repair Shop",
            "type":"Services"
        }
    ],
    "sg:phone":"+44 1252 343726",
    "sg:postcode":"KT15 1AT",
    "sg:province":"Surrey",
    "sg:tags":[
        "property",
        "maintenance"
    ],
    "wof:name":"Oatlands Property Services",
    "wof:placetype":"venue"
},
  "geometry": {"coordinates":[-0.513994,51.365376],"type":"Point"}
}