{
  "type": "Feature",
  "properties": {
    "iso:country":"GB",
    "sg:address":"68 High Street",
    "sg:city":"Fordingbridge",
    "sg:classifiers":[
        {
            "category":"Travel",
            "subcategory":"Hotels & Motels",
            "type":"Entertainment"
        }
    ],
    "sg:phone":"+44 1425 652776",
    "sg:postcode":"SP6 1AX",
    "sg:province":"Dorset",
    "wof:name":"Inntrepreneur Retail Ltd.",
    "wof:placetype":"venue"
},
  "geometry": {"coordinates":[-1.7924339771,50.926700592],"type":"Point"}
}