{
  "type": "Feature",
  "properties": {
    "iso:country":"GB",
    "sg:address":"14 Queens Road, Walthamstow",
    "sg:city":"London",
    "sg:classifiers":[
        {
            "category":"Professional",
            "subcategory":"Lawyer & Legal Services",
            "type":"Services"
        }
    ],
    "sg:phone":"+44 20 8521 3328",
    "sg:postcode":"E17 8PX",
    "sg:province":"Greater London",
    "sg:tags":[
        "solicitor"
    ],
    "wof:name":"Khans Solicitors",
    "wof:placetype":"venue"
},
  "geometry": {"coordinates":[-0.0207940005,51.5794258118],"type":"Point"}
}