{
  "type": "Feature",
  "properties": {
    "addr:full":"70 Cornwall St Plymouth Devon PL1 1LR",
    "addr:housenumber":"70",
    "addr:postcode":"pl1 1lr",
    "addr:street":"Cornwall St",
    "iso:country":"GB",
    "sg:address":"70 Cornwall St",
    "sg:city":"Plymouth",
    "sg:classifiers":[
        {
            "category":"Health Services",
            "subcategory":"Optometrist",
            "type":"Services"
        }
    ],
    "sg:phone":"+44 1752 223873",
    "sg:postcode":"PL1 1LR",
    "sg:province":"Devon",
    "sg:tags":[
        "optician"
    ],
    "wof:name":"Keith Wills Optitians",
    "wof:placetype":"venue"
},
  "geometry": {"coordinates":[-4.1438450813,50.3724555969],"type":"Point"}
}