{
  "type": "Feature",
  "properties": {
    "addr:full":"Linden Lea, 7 New Barn La Alton Hampshire GU34 2RU",
    "addr:housenumber":"7",
    "addr:postcode":"gu34 2ru",
    "addr:street":"New Barn La Alton",
    "iso:country":"GB",
    "sg:address":"Linden Lea, 7 New Barn La",
    "sg:city":"Alton",
    "sg:classifiers":[
        {
            "category":"Health Services",
            "subcategory":"Podiatrist",
            "type":"Services"
        }
    ],
    "sg:phone":"+44 1420 80325",
    "sg:postcode":"GU34 2RU",
    "sg:province":"Hampshire",
    "sg:tags":[
        "podiatrists",
        "chiropodist"
    ],
    "wof:name":"A E Y Spear",
    "wof:placetype":"venue"
},
  "geometry": {"coordinates":[-0.974329,51.14756],"type":"Point"}
}