{
  "type": "Feature",
  "properties": {
    "addr:full":"Gibbs House Ascot Berkshire SL5 7NT",
    "addr:postcode":"sl5 7nt",
    "iso:country":"GB",
    "sg:address":"Gibbs House",
    "sg:city":"Ascot",
    "sg:classifiers":[
        {
            "category":"Shopping",
            "subcategory":"Bicycles & Sporting Goods",
            "type":"Retail Goods"
        }
    ],
    "sg:phone":"+44 1344 893288",
    "sg:postcode":"SL5 7NT",
    "sg:province":"Berkshire",
    "sg:tags":[
        "water",
        "cooler"
    ],
    "wof:name":"Water Bearers",
    "wof:placetype":"venue"
},
  "geometry": {"coordinates":[-0.673794,51.410675],"type":"Point"}
}