{
  "type": "Feature",
  "properties": {
    "addr:full":"18 Hastings St Plymouth Devon PL1 5BA",
    "addr:housenumber":"18",
    "addr:postcode":"pl1 5ba",
    "addr:street":"Hastings St",
    "iso:country":"GB",
    "sg:address":"18 Hastings St",
    "sg:city":"Plymouth",
    "sg:classifiers":[
        {
            "category":"Professional",
            "subcategory":"Lawyer & Legal Services",
            "type":"Services"
        }
    ],
    "sg:phone":"+44 1752 671078",
    "sg:postcode":"PL1 5BA",
    "sg:province":"Devon",
    "sg:tags":[
        "advice",
        "counselling"
    ],
    "wof:name":"Plymouth Mediation",
    "wof:placetype":"venue"
},
  "geometry": {"coordinates":[-4.148429,50.374062],"type":"Point"}
}