{
  "type": "Feature",
  "properties": {
    "addr:full":"23 Market Street Ashby-de-la-zouch Derbyshire LE65 1AF",
    "addr:housenumber":"23",
    "addr:postcode":"le65 1af",
    "addr:street":"Market Street",
    "iso:country":"GB",
    "sg:address":"23 Market Street",
    "sg:city":"Ashby-de-la-zouch",
    "sg:classifiers":[
        {
            "category":"Shopping",
            "subcategory":"Thrift Store",
            "type":"Retail Goods"
        },
        {
            "category":"Organizations",
            "subcategory":"Non-profit Organization",
            "type":"Services"
        }
    ],
    "sg:phone":"+44 1530 411144",
    "sg:postcode":"LE65 1AF",
    "sg:province":"Derbyshire",
    "sg:tags":[
        "shop",
        "charitable",
        "organisation",
        "charity"
    ],
    "wof:name":"OXFAM",
    "wof:placetype":"venue"
},
  "geometry": {"coordinates":[-1.473344,52.746651],"type":"Point"}
}