{
  "type": "Feature",
  "properties": {
    "iso:country":"GB",
    "sg:address":"Unit 10 Mini Park, Leeds Road",
    "sg:city":"Huddersfield",
    "sg:classifiers":[
        {
            "category":"Sports & Exercise",
            "subcategory":"Golf",
            "type":"Entertainment"
        }
    ],
    "sg:phone":"+44 1484 427338",
    "sg:postcode":"HD1 6PA",
    "sg:province":"West Yorkshire",
    "sg:tags":[
        "equipment"
    ],
    "wof:name":"Direct Golf U K Ltd.",
    "wof:placetype":"venue"
},
  "geometry": {"coordinates":[-1.782684,53.646954],"type":"Point"}
}