{
  "type": "Feature",
  "properties": {
    "addr:full":"11 Church Road, Gosforth Newcastle-upon-tyne Tyne and Wear NE3 1TX",
    "addr:housenumber":"11",
    "addr:postcode":"ne3 1tx",
    "addr:street":"Church Road",
    "iso:country":"GB",
    "sg:address":"11 Church Road, Gosforth",
    "sg:city":"Newcastle-upon-tyne",
    "sg:classifiers":[
        {
            "category":"Retail",
            "subcategory":"Laundry & Dry Cleaning",
            "type":"Services"
        }
    ],
    "sg:phone":"+44 191 284 4611",
    "sg:postcode":"NE3 1TX",
    "sg:province":"Tyne and Wear",
    "sg:tags":[
        "cleaner",
        "alteration"
    ],
    "wof:name":"Westinghouse Dry Cleaners",
    "wof:placetype":"venue"
},
  "geometry": {"coordinates":[-1.618887,55.007313],"type":"Point"}
}