{
  "type": "Feature",
  "properties": {
    "addr:full":"Sixth Cross Road Twickenham Greater London TW2 5PA",
    "addr:postcode":"tw2 5pa",
    "addr:street":"Cross Road",
    "iso:country":"GB",
    "sg:address":"Sixth Cross Road",
    "sg:city":"Twickenham",
    "sg:classifiers":[
        {
            "category":"Home & Garden",
            "subcategory":"Garden Supply",
            "type":"Retail Goods"
        }
    ],
    "sg:postcode":"TW2 5PA",
    "sg:province":"Greater London",
    "sg:tags":[
        "nursery",
        "centre"
    ],
    "wof:name":"D J Squire & Co. Ltd.",
    "wof:placetype":"venue"
},
  "geometry": {"coordinates":[-0.357682,51.437328],"type":"Point"}
}