{
  "type": "Feature",
  "properties": {
    "iso:country":"GB",
    "sg:address":"Alexander House, Excelsior Road",
    "sg:city":"Cardiff",
    "sg:classifiers":[
        {
            "category":"Professional",
            "subcategory":"Art Services",
            "type":"Services"
        }
    ],
    "sg:phone":"+44 29 2061 8822",
    "sg:postcode":"CF14 3TD",
    "sg:province":"Cardiff",
    "sg:tags":[
        "graphic",
        "designer"
    ],
    "wof:name":"Elgan Davies",
    "wof:placetype":"venue"
},
  "geometry": {"coordinates":[-3.20275,51.500172],"type":"Point"}
}