{
  "type": "Feature",
  "properties": {
    "iso:country":"GB",
    "sg:address":"14 Brook Street",
    "sg:city":"Watlington",
    "sg:classifiers":[
        {
            "category":"Utilities",
            "subcategory":"Natural Gas",
            "type":"Services"
        }
    ],
    "sg:phone":"+44 1491 612765",
    "sg:postcode":"OX49 5JH",
    "sg:province":"Oxfordshire",
    "sg:tags":[
        "resurfacing",
        "bath"
    ],
    "wof:name":"Vitreous New Surface",
    "wof:placetype":"venue"
},
  "geometry": {"coordinates":[-1.009546,51.644489],"type":"Point"}
}