{
  "type": "Feature",
  "properties": {
    "addr:full":"7 Tilgate Parade, Tilgate Crawley Surrey RH10 5EQ",
    "addr:housenumber":"7",
    "addr:postcode":"rh10 5eq",
    "addr:street":"Tilgate Parade Tilgate",
    "iso:country":"GB",
    "sg:address":"7 Tilgate Parade, Tilgate",
    "sg:city":"Crawley",
    "sg:classifiers":[
        {
            "category":"Shopping",
            "subcategory":"Pets & Pet Supplies",
            "type":"Retail Goods"
        }
    ],
    "sg:phone":"+44 1293 526094",
    "sg:postcode":"RH10 5EQ",
    "sg:province":"Surrey",
    "wof:name":"Our Pets",
    "wof:placetype":"venue"
},
  "geometry": {"coordinates":[-0.180826,51.102062],"type":"Point"}
}