{
  "type": "Feature",
  "properties": {
    "iso:country":"GB",
    "sg:address":"131 Golden Hill Lane",
    "sg:city":"Preston",
    "sg:classifiers":[
        {
            "category":"Food & Beverages",
            "subcategory":"Meat & Fish",
            "type":"Retail Goods"
        }
    ],
    "sg:phone":"+44 1772 421006",
    "sg:postcode":"PR25 3XJ",
    "sg:province":"Lancashire",
    "sg:tags":[
        "butcher"
    ],
    "wof:name":"Thomas Higham",
    "wof:placetype":"venue"
},
  "geometry": {"coordinates":[-2.7000699043,53.6981697083],"type":"Point"}
}