{
  "type": "Feature",
  "properties": {
    "iso:country":"GB",
    "sg:address":"Summerfield, Chertsey Road, Chobham",
    "sg:city":"Woking",
    "sg:classifiers":[
        {
            "category":"Farming",
            "subcategory":"Nursery",
            "type":"Manufacturing & Wholesale Goods"
        },
        {
            "category":"Social Services",
            "subcategory":"Child Care",
            "type":"Services"
        }
    ],
    "sg:phone":"+44 1276 856556",
    "sg:postcode":"GU24 8HF",
    "sg:province":"Surrey",
    "sg:tags":[
        "childcare",
        "creche"
    ],
    "wof:name":"Summerfield House Day Nursery Ltd.",
    "wof:placetype":"venue"
},
  "geometry": {"coordinates":[-0.60618,51.353657],"type":"Point"}
}