{
  "type": "Feature",
  "properties": {
    "iso:country":"GB",
    "sg:address":"174 Bedfont La",
    "sg:city":"Feltham",
    "sg:classifiers":[
        {
            "category":"Retail",
            "subcategory":"Auto Repair",
            "type":"Services"
        }
    ],
    "sg:phone":"+44 20 8893 1962",
    "sg:postcode":"TW14 9NJ",
    "sg:province":"Greater London",
    "sg:tags":[
        "modification",
        "garage"
    ],
    "wof:name":"Motortec",
    "wof:placetype":"venue"
},
  "geometry": {"coordinates":[-0.4177649915,51.4499053955],"type":"Point"}
}