{
  "type": "Feature",
  "properties": {
    "iso:country":"GB",
    "sg:address":"Unit 11k, Shrub Hill",
    "sg:city":"Worcester",
    "sg:classifiers":[
        {
            "category":"Organizations",
            "subcategory":"Community Association",
            "type":"Services"
        }
    ],
    "sg:phone":"+44 1905 745200",
    "sg:postcode":"WR4 9EL",
    "sg:province":"Worcestershire",
    "sg:tags":[
        "emblem",
        "badge"
    ],
    "wof:name":"Persona",
    "wof:placetype":"venue"
},
  "geometry": {"coordinates":[-2.210565,52.194458],"type":"Point"}
}