{
  "type": "Feature",
  "properties": {
    "addr:full":"262 Lewisham High St Lewisham Greater London SE13 6JX",
    "addr:housenumber":"262",
    "addr:postcode":"se13 6jx",
    "addr:street":"Lewisham High St",
    "iso:country":"GB",
    "sg:address":"262 Lewisham High St",
    "sg:city":"Lewisham",
    "sg:classifiers":[
        {
            "category":"Personal",
            "subcategory":"Beauty Salon",
            "type":"Services"
        }
    ],
    "sg:phone":"+44 20 8690 7110",
    "sg:postcode":"SE13 6JX",
    "sg:province":"Greater London",
    "wof:name":"Florida Nails",
    "wof:placetype":"venue"
},
  "geometry": {"coordinates":[-0.0133130001,51.457988739],"type":"Point"}
}