{
  "type": "Feature",
  "properties": {
    "addr:full":"Lindley Moor Road Huddersfield West Yorkshire HD3 3RW",
    "addr:postcode":"hd3 3rw",
    "addr:street":"Lindley Moor Road",
    "iso:country":"GB",
    "sg:address":"Lindley Moor Road",
    "sg:city":"Huddersfield",
    "sg:classifiers":[
        {
            "category":"Military Area",
            "subcategory":"Coast Guard Base",
            "type":"Public Place"
        },
        {
            "category":"Home & Garden",
            "subcategory":"Building Materials",
            "type":"Retail Goods"
        }
    ],
    "sg:phone":"+44 1422 314100",
    "sg:postcode":"HD3 3RW",
    "sg:province":"West Yorkshire",
    "sg:tags":[
        "window",
        "frame",
        "manufacturer"
    ],
    "wof:name":"John Fredericks Plastics Ltd",
    "wof:placetype":"venue"
},
  "geometry": {"coordinates":[-1.8225189447,53.659526825],"type":"Point"}
}