{
  "type": "Feature",
  "properties": {
    "addr:full":"60 Skircoat Moor Road Halifax West Yorkshire HX3 0HA",
    "addr:housenumber":"60",
    "addr:postcode":"hx3 0ha",
    "addr:street":"Skircoat Moor Road",
    "iso:country":"GB",
    "sg:address":"60 Skircoat Moor Road",
    "sg:city":"Halifax",
    "sg:classifiers":[
        {
            "category":"Professional",
            "type":"Services"
        }
    ],
    "sg:phone":"+44 1422 350980",
    "sg:postcode":"HX3 0HA",
    "sg:province":"West Yorkshire",
    "sg:tags":[
        "entertainer"
    ],
    "wof:name":"Colonel Custard Childrens Entertainer",
    "wof:placetype":"venue"
},
  "geometry": {"coordinates":[-1.8804140091,53.7121124268],"type":"Point"}
}