{
  "type": "Feature",
  "properties": {
    "addr:full":"3 Queen Street Ashford Kent TN23 1RF",
    "addr:housenumber":"3",
    "addr:postcode":"tn23 1rf",
    "addr:street":"Queen Street",
    "iso:country":"GB",
    "sg:address":"3 Queen Street",
    "sg:city":"Ashford",
    "sg:classifiers":[
        {
            "category":"Professional",
            "subcategory":"Accounting & Tax Preparation",
            "type":"Services"
        }
    ],
    "sg:phone":"+44 1233 633336",
    "sg:postcode":"TN23 1RF",
    "sg:province":"Kent",
    "sg:tags":[
        "accountant",
        "activity"
    ],
    "sg:website":"http://www.mmpaudit.co.uk",
    "wof:name":"Michael Martin Partnership Ltd",
    "wof:placetype":"venue"
},
  "geometry": {"coordinates":[0.871184,51.147339],"type":"Point"}
}