{
  "type": "Feature",
  "properties": {
    "iso:country":"GB",
    "sg:address":"28 Doreen Avenue",
    "sg:city":"Wirral",
    "sg:classifiers":[
        {
            "category":"Professional",
            "subcategory":"Engineering",
            "type":"Services"
        }
    ],
    "sg:phone":"+44 151 678 2745",
    "sg:postcode":"CH46 6DN",
    "sg:province":"Merseyside",
    "sg:tags":[
        "gas",
        "engineer"
    ],
    "wof:name":"Cain Services",
    "wof:placetype":"venue"
},
  "geometry": {"coordinates":[-3.118794,53.400024],"type":"Point"}
}