{
  "type": "Feature",
  "properties": {
    "addr:full":"176 Hamilton Road Felixstowe Suffolk IP11 7DU",
    "addr:housenumber":"176",
    "addr:postcode":"ip11 7du",
    "addr:street":"Hamilton Road",
    "iso:country":"GB",
    "sg:address":"176 Hamilton Road",
    "sg:city":"Felixstowe",
    "sg:classifiers":[
        {
            "category":"Professional",
            "subcategory":"Lawyer & Legal Services",
            "type":"Services"
        }
    ],
    "sg:phone":"+44 1394 277941",
    "sg:postcode":"IP11 7DU",
    "sg:province":"Suffolk",
    "sg:tags":[
        "solicitor"
    ],
    "sg:website":"http://www.fairstep.co.uk",
    "wof:name":"Fairweather Stephenson Company",
    "wof:placetype":"venue"
},
  "geometry": {"coordinates":[1.353122,51.966873],"type":"Point"}
}