{
  "type": "Feature",
  "properties": {
    "addr:full":"24 Haze Lane, North Hykeham Lincoln Lincolnshire LN6 9SR",
    "addr:housenumber":"24",
    "addr:postcode":"ln6 9sr",
    "addr:street":"Haze Lane",
    "iso:country":"GB",
    "sg:address":"24 Haze Lane, North Hykeham",
    "sg:city":"Lincoln",
    "sg:classifiers":[
        {
            "category":"Autos & Motor Vehicles",
            "subcategory":"Auto Supplies",
            "type":"Retail Goods"
        },
        {
            "category":"Retail",
            "subcategory":"Auto Repair",
            "type":"Services"
        }
    ],
    "sg:phone":"+44 1522 500679",
    "sg:postcode":"LN6 9SR",
    "sg:province":"Lincolnshire",
    "sg:tags":[
        "car",
        "specialist",
        "tyre",
        "customizing"
    ],
    "wof:name":"The Tyreman",
    "wof:placetype":"venue"
},
  "geometry": {"coordinates":[-0.6040189862,53.1839103699],"type":"Point"}
}