{
  "type": "Feature",
  "properties": {
    "iso:country":"GB",
    "sg:address":"58 Broadgate",
    "sg:city":"Coventry",
    "sg:classifiers":[
        {
            "category":"Food & Beverages",
            "subcategory":"Specialty",
            "type":"Retail Goods"
        }
    ],
    "sg:phone":"+44 24 7622 1336",
    "sg:postcode":"CV1 1NF",
    "sg:province":"West Midlands",
    "sg:tags":[
        "retailer",
        "product",
        "health"
    ],
    "wof:name":"HEALTH & DIET CENTRES LTD",
    "wof:placetype":"venue"
},
  "geometry": {"coordinates":[-1.5103089809,52.4085083008],"type":"Point"}
}