{
  "type": "Feature",
  "properties": {
    "addr:full":"5 Stuart Road Harrow Greater London HA3 7RF",
    "addr:housenumber":"5",
    "addr:postcode":"ha3 7rf",
    "addr:street":"Stuart Road",
    "iso:country":"GB",
    "sg:address":"5 Stuart Road",
    "sg:city":"Harrow",
    "sg:classifiers":[
        {
            "category":"Food & Beverages",
            "subcategory":"Groceries & Convenience Stores",
            "type":"Retail Goods"
        }
    ],
    "sg:phone":"+44 20 8427 0884",
    "sg:postcode":"HA3 7RF",
    "sg:province":"Greater London",
    "wof:name":"Stop & Shop",
    "wof:placetype":"venue"
},
  "geometry": {"coordinates":[-0.3288950026,51.5951881409],"type":"Point"}
}