{
  "type": "Feature",
  "properties": {
    "iso:country":"GB",
    "sg:address":"15 Holly Avenue, Breaston",
    "sg:city":"Derby",
    "sg:classifiers":[
        {
            "category":"Bars & Pubs",
            "subcategory":"Sports Bar",
            "type":"Food & Drink"
        },
        {
            "category":"Professional",
            "type":"Services"
        }
    ],
    "sg:phone":"+44 1332 873748",
    "sg:postcode":"DE72 3BG",
    "sg:province":"Derbyshire",
    "sg:tags":[
        "reflexology",
        "therapist",
        "reflexologists"
    ],
    "wof:name":"Patricia Mary Peebles",
    "wof:placetype":"venue"
},
  "geometry": {"coordinates":[-1.30569,52.903408],"type":"Point"}
}