{
  "type": "Feature",
  "properties": {
    "addr:full":"30 Saville Rd Chiswick Greater London W4 5HG",
    "addr:housenumber":"30",
    "addr:postcode":"w4 5hg",
    "addr:street":"Saville Rd",
    "iso:country":"GB",
    "sg:address":"30 Saville Rd",
    "sg:city":"Chiswick",
    "sg:classifiers":[
        {
            "category":"Building & Trades",
            "subcategory":"Landscaping Services",
            "type":"Services"
        }
    ],
    "sg:phone":"+44 20 8995 7225",
    "sg:postcode":"W4 5HG",
    "sg:province":"Greater London",
    "sg:tags":[
        "consultant"
    ],
    "wof:name":"Asgow Ltd",
    "wof:placetype":"venue"
},
  "geometry": {"coordinates":[-0.2628970146,51.4991950989],"type":"Point"}
}