{
  "type": "Feature",
  "properties": {
    "addr:full":"Reckleford Yeovil Somerset BA20 1JF",
    "addr:postcode":"ba20 1jf",
    "iso:country":"GB",
    "sg:address":"Reckleford",
    "sg:city":"Yeovil",
    "sg:classifiers":[
        {
            "category":"Government",
            "subcategory":"Fire Station",
            "type":"Public Place"
        }
    ],
    "sg:phone":"+44 1935 474646",
    "sg:postcode":"BA20 1JF",
    "sg:province":"Somerset",
    "wof:name":"Somerset County Fire Brigade",
    "wof:placetype":"venue"
},
  "geometry": {"coordinates":[-2.625309,50.943184],"type":"Point"}
}