{
  "type": "Feature",
  "properties": {
    "addr:full":"The Moathouse, Melbourn Science Park Royston Bedfordshire SG8 6EJ",
    "addr:postcode":"sg8 6ej",
    "addr:street":"Science Park",
    "iso:country":"GB",
    "sg:address":"The Moathouse, Melbourn Science Park",
    "sg:city":"Royston",
    "sg:classifiers":[
        {
            "category":"Professional",
            "subcategory":"Art Services",
            "type":"Services"
        }
    ],
    "sg:phone":"+44 70 0044 3327",
    "sg:postcode":"SG8 6EJ",
    "sg:province":"Bedfordshire",
    "sg:tags":[
        "graphic",
        "designer"
    ],
    "wof:name":"Red Electric Design",
    "wof:placetype":"venue"
},
  "geometry": {"coordinates":[0.011957,52.087051],"type":"Point"}
}