{
  "type": "Feature",
  "properties": {
    "addr:full":"191 Wakefield Road, Scissett Huddersfield South Yorkshire HD8 9JL",
    "addr:housenumber":"191",
    "addr:postcode":"hd8 9jl",
    "addr:street":"Wakefield Road",
    "iso:country":"GB",
    "sg:address":"191 Wakefield Road, Scissett",
    "sg:city":"Huddersfield",
    "sg:classifiers":[
        {
            "category":"Restaurant",
            "type":"Food & Drink"
        }
    ],
    "sg:postcode":"HD8 9JL",
    "sg:province":"South Yorkshire",
    "wof:name":"Bistro Bolare",
    "wof:placetype":"venue"
},
  "geometry": {"coordinates":[-1.6273449659,53.5877037048],"type":"Point"}
}