{
  "type": "Feature",
  "properties": {
    "addr:full":"Unit 5 Burley Hill Trading Estate Leeds West Yorkshire LS4 2PU",
    "addr:housenumber":"unit 5",
    "addr:postcode":"ls4 2pu",
    "addr:street":"Burley Hill Trading Estate",
    "iso:country":"GB",
    "sg:address":"Unit 5 Burley Hill Trading Estate",
    "sg:city":"Leeds",
    "sg:classifiers":[
        {
            "category":"Professional",
            "subcategory":"Printing & Photocopies",
            "type":"Services"
        }
    ],
    "sg:phone":"+44 113 230 7373",
    "sg:postcode":"LS4 2PU",
    "sg:province":"West Yorkshire",
    "sg:tags":[
        "printer"
    ],
    "wof:name":"Kall-Kwik Printing",
    "wof:placetype":"venue"
},
  "geometry": {"coordinates":[-1.576419,53.804031],"type":"Point"}
}