{
  "type": "Feature",
  "properties": {
    "iso:country":"GB",
    "sg:address":"Elstree Aerodrome",
    "sg:city":"Borehamwood",
    "sg:classifiers":[
        {
            "category":"Government",
            "subcategory":"Post Office",
            "type":"Public Place"
        }
    ],
    "sg:phone":"+44 20 8207 5161",
    "sg:postcode":"WD6 3AW",
    "sg:province":"Hertfordshire",
    "sg:tags":[
        "messenger",
        "courier"
    ],
    "wof:name":"Pickup",
    "wof:placetype":"venue"
},
  "geometry": {"coordinates":[-0.3239800036,51.6542015076],"type":"Point"}
}