{
  "type": "Feature",
  "properties": {
    "iso:country":"GB",
    "sg:address":"127 Fulham Palace Road",
    "sg:city":"London",
    "sg:classifiers":[
        {
            "category":"Retail",
            "subcategory":"Funeral Services",
            "type":"Services"
        }
    ],
    "sg:phone":"+44 20 8748 3185",
    "sg:postcode":"W6 8JA",
    "sg:province":"Greater London",
    "sg:tags":[
        "director"
    ],
    "wof:name":"Glenhaven Funeral Service Ltd.",
    "wof:placetype":"venue"
},
  "geometry": {"coordinates":[-0.222172,51.487812],"type":"Point"}
}