{
  "type": "Feature",
  "properties": {
    "addr:full":"2a Church Road Birmingham West Midlands B13 9AG",
    "addr:housenumber":"2a",
    "addr:postcode":"b13 9ag",
    "addr:street":"Church Road",
    "iso:country":"GB",
    "sg:address":"2a Church Road",
    "sg:city":"Birmingham",
    "sg:classifiers":[
        {
            "category":"Shopping",
            "subcategory":"Pharmacy",
            "type":"Retail Goods"
        }
    ],
    "sg:phone":"+44 121 449 2719",
    "sg:postcode":"B13 9AG",
    "sg:province":"West Midlands",
    "sg:tags":[
        "pharmacist",
        "chemist"
    ],
    "wof:name":"Fakir Chemists",
    "wof:placetype":"venue"
},
  "geometry": {"coordinates":[-1.879088,52.451633],"type":"Point"}
}