{
  "type": "Feature",
  "properties": {
    "addr:full":"Rears Of 20 Bradford Road, Guiseley Leeds West Yorkshire LS20 8AH",
    "addr:housenumber":"20",
    "addr:postcode":"ls20 8ah",
    "addr:street":"Bradford Road",
    "iso:country":"GB",
    "sg:address":"Rears Of 20 Bradford Road, Guiseley",
    "sg:city":"Leeds",
    "sg:classifiers":[
        {
            "category":"Building & Trades",
            "subcategory":"Construction",
            "type":"Services"
        }
    ],
    "sg:phone":"+44 1943 870872",
    "sg:postcode":"LS20 8AH",
    "sg:province":"West Yorkshire",
    "sg:tags":[
        "joiner",
        "carpenter"
    ],
    "wof:name":"Moores Bros",
    "wof:placetype":"venue"
},
  "geometry": {"coordinates":[-1.7104940414,53.8719558716],"type":"Point"}
}