{
  "type": "Feature",
  "properties": {
    "iso:country":"GB",
    "sg:address":"19a Briggate",
    "sg:city":"Shipley",
    "sg:classifiers":[
        {
            "category":"Building & Trades",
            "subcategory":"Construction",
            "type":"Services"
        }
    ],
    "sg:phone":"+44 1274 582220",
    "sg:postcode":"BD17 7BP",
    "sg:province":"West Yorkshire",
    "sg:tags":[
        "builder"
    ],
    "wof:name":"Channon Construction Ltd.",
    "wof:placetype":"venue"
},
  "geometry": {"coordinates":[-1.7745000124,53.8348350525],"type":"Point"}
}