{
  "type": "Feature",
  "properties": {
    "addr:full":"31 Bridge Street Mold Denbighshire CH7 1LW",
    "addr:housenumber":"31",
    "addr:postcode":"ch7 1lw",
    "addr:street":"Bridge Street",
    "iso:country":"GB",
    "sg:address":"31 Bridge Street",
    "sg:city":"Mold",
    "sg:classifiers":[
        {
            "category":"Professional",
            "subcategory":"Employment Agencies",
            "type":"Services"
        }
    ],
    "sg:postcode":"CH7 1LW",
    "sg:province":"Denbighshire",
    "sg:tags":[
        "consultant"
    ],
    "wof:name":"Celtic Recruitment",
    "wof:placetype":"venue"
},
  "geometry": {"coordinates":[-3.1365199089,53.1710700989],"type":"Point"}
}