{
  "type": "Feature",
  "properties": {
    "addr:full":"38 Young St Manchester Greater Manchester M3 3FT",
    "addr:housenumber":"38",
    "addr:postcode":"m3 3ft",
    "addr:street":"Young St",
    "iso:country":"GB",
    "sg:address":"38 Young St",
    "sg:city":"Manchester",
    "sg:classifiers":[
        {
            "category":"Professional",
            "subcategory":"Lawyer & Legal Services",
            "type":"Services"
        }
    ],
    "sg:phone":"+44 161 833 0489",
    "sg:postcode":"M3 3FT",
    "sg:province":"Greater Manchester",
    "sg:tags":[
        "barrister"
    ],
    "wof:name":"Ian Huffer",
    "wof:placetype":"venue"
},
  "geometry": {"coordinates":[-2.253971,53.479389],"type":"Point"}
}