{
  "type": "Feature",
  "properties": {
    "iso:country":"GB",
    "sg:address":"49 Providence Lane, Long Ashton",
    "sg:city":"Bristol",
    "sg:classifiers":[
        {
            "category":"Professional",
            "subcategory":"Business Services",
            "type":"Services"
        }
    ],
    "sg:postcode":"BS41 9DL",
    "sg:province":"Somerset",
    "sg:tags":[
        "holding"
    ],
    "wof:name":"Perdure (Holdings) Ltd.",
    "wof:placetype":"venue"
},
  "geometry": {"coordinates":[-2.6651849747,51.432258606],"type":"Point"}
}