{
  "type": "Feature",
  "properties": {
    "addr:full":"18 Bird Street Lichfield Staffordshire WS13 6PR",
    "addr:housenumber":"18",
    "addr:postcode":"ws13 6pr",
    "addr:street":"Bird Street",
    "iso:country":"GB",
    "sg:address":"18 Bird Street",
    "sg:city":"Lichfield",
    "sg:classifiers":[
        {
            "category":"Shopping",
            "subcategory":"Florist",
            "type":"Retail Goods"
        }
    ],
    "sg:postcode":"WS13 6PR",
    "sg:province":"Staffordshire",
    "wof:name":"The J &C Ivison Lichfield Florist",
    "wof:placetype":"venue"
},
  "geometry": {"coordinates":[-1.830556035,52.6833000183],"type":"Point"}
}