{
  "type": "Feature",
  "properties": {
    "addr:full":"35 Main Street, Kinglassie Lochgelly Fife KY5 0XA",
    "addr:housenumber":"35",
    "addr:postcode":"ky5 0xa",
    "addr:street":"Main Street;Lochgelly",
    "iso:country":"GB",
    "sg:address":"35 Main Street, Kinglassie",
    "sg:city":"Lochgelly",
    "sg:classifiers":[
        {
            "category":"Recreation",
            "subcategory":"Amusement Park",
            "type":"Entertainment"
        },
        {
            "category":"Fast Food",
            "type":"Food & Drink"
        }
    ],
    "sg:phone":"+44 1592 882394",
    "sg:postcode":"KY5 0XA",
    "sg:province":"Fife",
    "sg:tags":[
        "away",
        "take",
        "arcade"
    ],
    "wof:name":"The Cafe",
    "wof:placetype":"venue"
},
  "geometry": {"coordinates":[-3.265319109,56.148223877],"type":"Point"}
}