{
  "type": "Feature",
  "properties": {
    "iso:country":"GB",
    "sg:address":"St John's Innovation Centre Cowley Road",
    "sg:city":"Cambridge",
    "sg:classifiers":[
        {
            "category":"Professional",
            "subcategory":"Computer Services",
            "type":"Services"
        }
    ],
    "sg:postcode":"CB4 0WS",
    "sg:tags":[
        "testing",
        "automated-testing",
        "cross-browser-testing",
        "functional-testing",
        "web-applications"
    ],
    "sg:website":"http://go-test.it/",
    "wof:name":"Go Test It",
    "wof:placetype":"venue"
},
  "geometry": {"coordinates":[0.1987426,52.1963733],"type":"Point"}
}