{
  "type": "Feature",
  "properties": {
    "addr:full":"Seasalter Road, Graveney Faversham Kent ME13 9DU",
    "addr:postcode":"me13 9du",
    "addr:street":"Seasalter Road",
    "iso:country":"GB",
    "sg:address":"Seasalter Road, Graveney",
    "sg:city":"Faversham",
    "sg:classifiers":[
        {
            "category":"Education",
            "subcategory":"School",
            "type":"Public Place"
        }
    ],
    "sg:phone":"+44 1795 532005",
    "sg:postcode":"ME13 9DU",
    "sg:province":"Kent",
    "sg:tags":[
        "local",
        "authority"
    ],
    "wof:name":"Graveney School",
    "wof:placetype":"venue"
},
  "geometry": {"coordinates":[0.9419230223,51.3225250244],"type":"Point"}
}