{
  "type": "Feature",
  "properties": {
    "addr:full":"78 Queen Street, Great Harwood Blackburn Lancashire BB6 7AL",
    "addr:housenumber":"78",
    "addr:postcode":"bb6 7al",
    "addr:street":"Queen Street",
    "iso:country":"GB",
    "sg:address":"78 Queen Street, Great Harwood",
    "sg:city":"Blackburn",
    "sg:classifiers":[
        {
            "category":"Fast Food",
            "type":"Food & Drink"
        }
    ],
    "sg:phone":"+44 1254 888990",
    "sg:postcode":"BB6 7AL",
    "sg:province":"Lancashire",
    "sg:tags":[
        "away",
        "meal",
        "outlet",
        "take"
    ],
    "wof:name":"Yang Sing",
    "wof:placetype":"venue"
},
  "geometry": {"coordinates":[-2.403840065,53.7861404419],"type":"Point"}
}