{
  "type": "Feature",
  "properties": {
    "addr:full":"Edward Street Westbury Wiltshire BA13 3BD",
    "addr:postcode":"ba13 3bd",
    "addr:street":"Edward Street",
    "iso:country":"GB",
    "sg:address":"Edward Street",
    "sg:city":"Westbury",
    "sg:classifiers":[
        {
            "category":"Retail",
            "subcategory":"Auto Repair",
            "type":"Services"
        }
    ],
    "sg:phone":"+44 1373 827229",
    "sg:postcode":"BA13 3BD",
    "sg:province":"Wiltshire",
    "sg:tags":[
        "modification",
        "garage"
    ],
    "wof:name":"Kendricks Motors",
    "wof:placetype":"venue"
},
  "geometry": {"coordinates":[-2.1839189529,51.2621192932],"type":"Point"}
}