{
  "type": "Feature",
  "properties": {
    "iso:country":"GB",
    "sg:address":"31b High Street",
    "sg:city":"Oakham",
    "sg:classifiers":[
        {
            "category":"Fast Food",
            "type":"Food & Drink"
        }
    ],
    "sg:postcode":"LE15 6AH",
    "sg:province":"Leicestershire",
    "sg:tags":[
        "away",
        "take"
    ],
    "wof:name":"Hoagies",
    "wof:placetype":"venue"
},
  "geometry": {"coordinates":[-0.728716,52.669781],"type":"Point"}
}