{
  "type": "Feature",
  "properties": {
    "addr:full":"77 Westgate Southwell Nottinghamshire NG25 0LD",
    "addr:housenumber":"77",
    "addr:postcode":"ng25 0ld",
    "addr:street":"Westgate Southwell",
    "iso:country":"GB",
    "sg:address":"77 Westgate",
    "sg:city":"Southwell",
    "sg:classifiers":[
        {
            "category":"Health Services",
            "subcategory":"Dentist",
            "type":"Services"
        }
    ],
    "sg:phone":"+44 1636 813291",
    "sg:postcode":"NG25 0LD",
    "sg:province":"Nottinghamshire",
    "wof:name":"Dental Care Centres",
    "wof:placetype":"venue"
},
  "geometry": {"coordinates":[-0.961395,53.074852],"type":"Point"}
}