{
  "type": "Feature",
  "properties": {
    "addr:full":"6 High Street Purley Surrey CR8 2AA",
    "addr:housenumber":"6",
    "addr:postcode":"cr8 2aa",
    "addr:street":"High Street",
    "iso:country":"GB",
    "sg:address":"6 High Street",
    "sg:city":"Purley",
    "sg:classifiers":[
        {
            "category":"Personal",
            "subcategory":"Beauty Salon",
            "type":"Services"
        }
    ],
    "sg:phone":"+44 20 8668 3087",
    "sg:postcode":"CR8 2AA",
    "sg:province":"Surrey",
    "sg:tags":[
        "unisex",
        "hairdresser"
    ],
    "wof:name":"H Q Hair Salon",
    "wof:placetype":"venue"
},
  "geometry": {"coordinates":[-0.1153889969,51.337802887],"type":"Point"}
}