{
  "type": "Feature",
  "properties": {
    "addr:full":"26 Chiffinch Gardens, Northfleet Gravesend Kent DA11 8SL",
    "addr:housenumber":"26",
    "addr:postcode":"da11 8sl",
    "addr:street":"Chiffinch Gardens",
    "iso:country":"GB",
    "sg:address":"26 Chiffinch Gardens, Northfleet",
    "sg:city":"Gravesend",
    "sg:classifiers":[
        {
            "category":"Home & Garden",
            "subcategory":"Household Appliances",
            "type":"Retail Goods"
        },
        {
            "category":"Communications",
            "type":"Services"
        }
    ],
    "sg:postcode":"DA11 8SL",
    "sg:province":"Kent",
    "sg:tags":[
        "tv",
        "domestic",
        "microwave",
        "video",
        "oven",
        "radio"
    ],
    "wof:name":"Microspeed Services",
    "wof:placetype":"venue"
},
  "geometry": {"coordinates":[0.346494,51.427361],"type":"Point"}
}