{
  "type": "Feature",
  "properties": {
    "addr:full":"Victoria Gardens, Victoria St Windermere Cumbria LA23 1AB",
    "addr:postcode":"la23 1ab",
    "addr:street":"Victoria Gardens Victoria St",
    "iso:country":"GB",
    "sg:address":"Victoria Gardens, Victoria St",
    "sg:city":"Windermere",
    "sg:classifiers":[
        {
            "category":"Travel",
            "subcategory":"Hotels & Motels",
            "type":"Entertainment"
        }
    ],
    "sg:phone":"+44 15394 88772",
    "sg:postcode":"LA23 1AB",
    "sg:province":"Cumbria",
    "sg:tags":[
        "self",
        "catering"
    ],
    "wof:name":"Cumbrian Cottages",
    "wof:placetype":"venue"
},
  "geometry": {"coordinates":[-2.9054689407,54.379940033],"type":"Point"}
}