{
  "type": "Feature",
  "properties": {
    "addr:full":"The Pavillion, Moorfield Road Widnes Cheshire WA8 0JU",
    "addr:postcode":"wa8 0ju",
    "addr:street":"Moorfield Road",
    "iso:country":"GB",
    "sg:address":"The Pavillion, Moorfield Road",
    "sg:city":"Widnes",
    "sg:classifiers":[
        {
            "category":"Arena",
            "subcategory":"Sports Club",
            "type":"Entertainment"
        }
    ],
    "sg:phone":"+44 151 424 5009",
    "sg:postcode":"WA8 0JU",
    "sg:province":"Cheshire",
    "wof:name":"Moorfield Sports & Social Club",
    "wof:placetype":"venue"
},
  "geometry": {"coordinates":[-2.733244,53.374031],"type":"Point"}
}