{
  "type": "Feature",
  "properties": {
    "iso:country":"GB",
    "sg:address":"87 Chester Avenue",
    "sg:city":"Dukinfield",
    "sg:classifiers":[
        {
            "category":"Manufacturing",
            "subcategory":"Paper Products",
            "type":"Manufacturing & Wholesale Goods"
        }
    ],
    "sg:postcode":"SK16 5BW",
    "sg:province":"Greater Manchester",
    "sg:tags":[
        "cardboard"
    ],
    "wof:name":"Kaw Decorating",
    "wof:placetype":"venue"
},
  "geometry": {"coordinates":[-2.070982933,53.4728469849],"type":"Point"}
}