{
  "type": "Feature",
  "properties": {
    "addr:full":"11 Alhambra Terrace, Fishburn Stockton On Tees Durham TS21 4BU",
    "addr:housenumber":"11",
    "addr:postcode":"ts21 4bu",
    "addr:street":"Alhambra Terrace;On",
    "iso:country":"GB",
    "sg:address":"11 Alhambra Terrace, Fishburn",
    "sg:city":"Stockton On Tees",
    "sg:classifiers":[
        {
            "category":"Professional",
            "subcategory":"Engineering",
            "type":"Services"
        }
    ],
    "sg:phone":"+44 1740 622959",
    "sg:postcode":"TS21 4BU",
    "sg:province":"Durham",
    "sg:tags":[
        "contractor",
        "electrical",
        "engineer"
    ],
    "wof:name":"Andrew J Lyon",
    "wof:placetype":"venue"
},
  "geometry": {"coordinates":[-1.4370900393,54.6818809509],"type":"Point"}
}