{
  "type": "Feature",
  "properties": {
    "iso:country":"GB",
    "sg:address":"Care Of Asda, Carberry Rd, Mitchelston Indust Est",
    "sg:city":"Kirkcaldy",
    "sg:classifiers":[
        {
            "category":"Retail",
            "subcategory":"Laundry & Dry Cleaning",
            "type":"Services"
        }
    ],
    "sg:phone":"+44 1592 655041",
    "sg:postcode":"KY1 3NG",
    "sg:province":"Fife",
    "sg:tags":[
        "alteration"
    ],
    "wof:name":"Johnson Cleaners UK Ltd",
    "wof:placetype":"venue"
},
  "geometry": {"coordinates":[-3.1420259476,56.1391334534],"type":"Point"}
}