{
  "type": "Feature",
  "properties": {
    "iso:country":"GB",
    "sg:address":"12 Colville Mews",
    "sg:city":"London",
    "sg:classifiers":[
        {
            "category":"Shopping",
            "subcategory":"Books",
            "type":"Retail Goods"
        }
    ],
    "sg:postcode":"W11 2DA",
    "sg:province":"Greater London",
    "wof:name":"Endeavour Group",
    "wof:placetype":"venue"
},
  "geometry": {"coordinates":[-0.2031079978,51.5159721375],"type":"Point"}
}