{
  "type": "Feature",
  "properties": {
    "addr:full":"2/4 The Courtyard Glastonbury Somerset BA6 9DU",
    "addr:housenumber":"2 / 4",
    "addr:postcode":"ba6 9du",
    "addr:street":"The Courtyard",
    "iso:country":"GB",
    "sg:address":"2/4 The Courtyard",
    "sg:city":"Glastonbury",
    "sg:classifiers":[
        {
            "category":"Organizations",
            "subcategory":"Non-profit Organization",
            "type":"Services"
        }
    ],
    "sg:phone":"+44 1458 833933",
    "sg:postcode":"BA6 9DU",
    "sg:province":"Somerset",
    "sg:tags":[
        "organisation",
        "voluntary",
        "charity"
    ],
    "wof:name":"Isle of Avalon Foundation Ltd.",
    "wof:placetype":"venue"
},
  "geometry": {"coordinates":[-2.717009,51.147591],"type":"Point"}
}