{
  "type": "Feature",
  "properties": {
    "iso:country":"GB",
    "sg:address":"Unit 2 Saville Street",
    "sg:city":"Macclesfield",
    "sg:classifiers":[
        {
            "category":"Retail",
            "subcategory":"Auto Repair",
            "type":"Services"
        }
    ],
    "sg:phone":"+44 1625 502223",
    "sg:postcode":"SK11 7LQ",
    "sg:province":"Cheshire",
    "sg:tags":[
        "modification",
        "garage"
    ],
    "wof:name":"Autospeed",
    "wof:placetype":"venue"
},
  "geometry": {"coordinates":[-2.116024,53.254116],"type":"Point"}
}