{
  "type": "Feature",
  "properties": {
    "addr:full":"Units 2-3 Ployters Road, Southern Way, Staple Tye Harlow Essex CM18 7NS",
    "addr:housenumber":"units 2-3",
    "addr:postcode":"cm18 7ns",
    "addr:street":"Ployters Road Southern Way",
    "iso:country":"GB",
    "sg:address":"Units 2-3 Ployters Road, Southern Way, Staple Tye",
    "sg:city":"Harlow",
    "sg:classifiers":[
        {
            "category":"Shopping",
            "subcategory":"Discount & Variety Stores",
            "type":"Retail Goods"
        }
    ],
    "sg:phone":"+44 1279 641097",
    "sg:postcode":"CM18 7NS",
    "sg:province":"Essex",
    "sg:tags":[
        "shop",
        "model"
    ],
    "wof:name":"Helger Racing Ltd.",
    "wof:placetype":"venue"
},
  "geometry": {"coordinates":[0.0882499963,51.7509918213],"type":"Point"}
}