{
  "type": "Feature",
  "properties": {
    "addr:full":"New Elton Business Park, 238 Green La Eltham Greater London SE9 3TL",
    "addr:housenumber":"238",
    "addr:postcode":"se9 3tl",
    "addr:street":"Green La Eltham",
    "iso:country":"GB",
    "sg:address":"New Elton Business Park, 238 Green La",
    "sg:city":"Eltham",
    "sg:classifiers":[
        {
            "category":"Professional",
            "subcategory":"Accounting & Tax Preparation",
            "type":"Services"
        }
    ],
    "sg:phone":"+44 20 8850 5059",
    "sg:postcode":"SE9 3TL",
    "sg:province":"Greater London",
    "sg:tags":[
        "accountant"
    ],
    "wof:name":"Data Business Services",
    "wof:placetype":"venue"
},
  "geometry": {"coordinates":[0.063928,51.432339],"type":"Point"}
}