{
  "type": "Feature",
  "properties": {
    "addr:full":"P O Box 962 Malmesbury Wiltshire SN16 9ZS",
    "addr:housenumber":"962",
    "addr:postcode":"sn16 9zs",
    "addr:street":"P O Box",
    "iso:country":"GB",
    "sg:address":"P O Box 962",
    "sg:city":"Malmesbury",
    "sg:classifiers":[
        {
            "category":"Professional",
            "type":"Services"
        }
    ],
    "sg:phone":"+44 1666 577777",
    "sg:postcode":"SN16 9ZS",
    "sg:province":"Wiltshire",
    "sg:tags":[
        "relocation"
    ],
    "wof:name":"Migration Direct Services",
    "wof:placetype":"venue"
},
  "geometry": {"coordinates":[-2.057446003,51.6033782959],"type":"Point"}
}