{
  "type": "Feature",
  "properties": {
    "addr:full":"Bay Road Gillingham Dorset SP8 4EW",
    "addr:postcode":"sp8 4ew",
    "addr:street":"Bay Road",
    "iso:country":"GB",
    "sg:address":"Bay Road",
    "sg:city":"Gillingham",
    "sg:classifiers":[
        {
            "category":"Building & Trades",
            "subcategory":"Construction",
            "type":"Services"
        }
    ],
    "sg:postcode":"SP8 4EW",
    "sg:province":"Dorset",
    "sg:tags":[
        "builder"
    ],
    "wof:name":"R G Evans Building Contractor",
    "wof:placetype":"venue"
},
  "geometry": {"coordinates":[-2.274039,51.04195],"type":"Point"}
}