{
  "type": "Feature",
  "properties": {
    "addr:full":"9 Honey Hill, Gamlingay Sandy Bedfordshire SG19 3JU",
    "addr:housenumber":"9",
    "addr:postcode":"sg19 3ju",
    "addr:street":"Honey Hill",
    "iso:country":"GB",
    "sg:address":"9 Honey Hill, Gamlingay",
    "sg:city":"Sandy",
    "sg:classifiers":[
        {
            "category":"Professional",
            "subcategory":"Computer Services",
            "type":"Services"
        }
    ],
    "sg:phone":"+44 1767 650429",
    "sg:postcode":"SG19 3JU",
    "sg:province":"Bedfordshire",
    "sg:tags":[
        "system",
        "software"
    ],
    "wof:name":"Drampure Ltd.",
    "wof:placetype":"venue"
},
  "geometry": {"coordinates":[-0.191935,52.150848],"type":"Point"}
}