{
  "type": "Feature",
  "properties": {
    "addr:full":"13 Tor View Avenue Glastonbury Somerset BA6 8AE",
    "addr:housenumber":"13",
    "addr:postcode":"ba6 8ae",
    "addr:street":"Tor View Avenue",
    "iso:country":"GB",
    "sg:address":"13 Tor View Avenue",
    "sg:city":"Glastonbury",
    "sg:classifiers":[
        {
            "category":"Farming",
            "subcategory":"Livestock Farm",
            "type":"Manufacturing & Wholesale Goods"
        }
    ],
    "sg:phone":"+44 1458 832862",
    "sg:postcode":"BA6 8AE",
    "sg:province":"Somerset",
    "sg:tags":[
        "others"
    ],
    "wof:name":"L S Davies & Partners",
    "wof:placetype":"venue"
},
  "geometry": {"coordinates":[-2.7180669308,51.1423149109],"type":"Point"}
}