{
  "type": "Feature",
  "properties": {
    "addr:full":"Stream Lane Edgware Greater London HA8 7YA",
    "addr:postcode":"ha8 7ya",
    "addr:street":"Stream Lane",
    "iso:country":"GB",
    "sg:address":"Stream Lane",
    "sg:city":"Edgware",
    "sg:classifiers":[
        {
            "category":"Place Of Worship",
            "type":"Public Place"
        },
        {
            "category":"Community Center",
            "type":"Public Place"
        }
    ],
    "sg:phone":"+44 20 8905 4096",
    "sg:postcode":"HA8 7YA",
    "sg:province":"Greater London",
    "sg:tags":[
        "centre"
    ],
    "wof:name":"Edgware Masorti Synagogue",
    "wof:placetype":"venue"
},
  "geometry": {"coordinates":[-0.2750689983,51.6149139404],"type":"Point"}
}