{
  "type": "Feature",
  "properties": {
    "addr:full":"Northernhay House, Northernhay Place Exeter Devon EX4 3RY",
    "addr:postcode":"ex4 3ry",
    "addr:street":"Northernhay Place",
    "iso:country":"GB",
    "sg:address":"Northernhay House, Northernhay Place",
    "sg:city":"Exeter",
    "sg:classifiers":[
        {
            "category":"Professional",
            "subcategory":"Employment Agencies",
            "type":"Services"
        }
    ],
    "sg:phone":"+44 1392 423030",
    "sg:postcode":"EX4 3RY",
    "sg:province":"Devon",
    "sg:tags":[
        "consultant"
    ],
    "wof:name":"Action for Employment Ltd.",
    "wof:placetype":"venue"
},
  "geometry": {"coordinates":[-3.528314,50.726055],"type":"Point"}
}