{
  "type": "Feature",
  "properties": {
    "addr:full":"Tanyard Farm, Dodworth Barnsley South Yorkshire S75 3SA",
    "addr:postcode":"s75 3sa",
    "addr:street":"Dodworth;Yorkshire",
    "iso:country":"GB",
    "sg:address":"Tanyard Farm, Dodworth",
    "sg:city":"Barnsley",
    "sg:classifiers":[
        {
            "category":"Banks & Credit Unions",
            "subcategory":"Investment Brokerage",
            "type":"Services"
        }
    ],
    "sg:phone":"+44 1226 203337",
    "sg:postcode":"S75 3SA",
    "sg:province":"South Yorkshire",
    "sg:tags":[
        "contractor"
    ],
    "wof:name":"J C White & Son",
    "wof:placetype":"venue"
},
  "geometry": {"coordinates":[-1.5205689669,53.5404548645],"type":"Point"}
}