{
  "type": "Feature",
  "properties": {
    "iso:country":"GB",
    "sg:address":"1 Chadwick Street",
    "sg:city":"London",
    "sg:classifiers":[
        {
            "category":"Community Center",
            "type":"Public Place"
        }
    ],
    "sg:phone":"+44 20 7976 7646",
    "sg:postcode":"SW1P 2EP",
    "sg:province":"Greater London",
    "sg:tags":[
        "recreation",
        "leisure",
        "centre"
    ],
    "wof:name":"Chadwick Street Recreation Centre",
    "wof:placetype":"venue"
},
  "geometry": {"coordinates":[-0.131748,51.496059],"type":"Point"}
}