{
  "type": "Feature",
  "properties": {
    "iso:country":"GB",
    "sg:address":"16 Kingshill Drive",
    "sg:city":"Birmingham",
    "sg:classifiers":[
        {
            "category":"Manufacturing",
            "subcategory":"Glass & Minerals",
            "type":"Manufacturing & Wholesale Goods"
        },
        {
            "category":"Manufacturing",
            "subcategory":"Building Materials",
            "type":"Manufacturing & Wholesale Goods"
        }
    ],
    "sg:phone":"+44 121 459 2442",
    "sg:postcode":"B38 8SA",
    "sg:province":"West Midlands",
    "sg:tags":[
        "supplier",
        "specialist",
        "marble",
        "granite",
        "mnfr"
    ],
    "wof:name":"K & L Marble Masons",
    "wof:placetype":"venue"
},
  "geometry": {"coordinates":[-1.9334009886,52.4070472717],"type":"Point"}
}