{
  "type": "Feature",
  "properties": {
    "addr:full":"Savacentre, Eastgate Shopping Centre Basildon Essex SS14 1JH",
    "addr:postcode":"ss14 1jh",
    "addr:street":"Eastgate Shopping Centre",
    "iso:country":"GB",
    "sg:address":"Savacentre, Eastgate Shopping Centre",
    "sg:city":"Basildon",
    "sg:classifiers":[
        {
            "category":"Shopping",
            "subcategory":"Hobbies, Toys, & Games",
            "type":"Retail Goods"
        }
    ],
    "sg:postcode":"SS14 1JH",
    "sg:province":"Essex",
    "sg:tags":[
        "computer"
    ],
    "wof:name":"Guy Patey",
    "wof:placetype":"venue"
},
  "geometry": {"coordinates":[0.46354,51.569221],"type":"Point"}
}