{
  "type": "Feature",
  "properties": {
    "addr:full":"314 Church Street London Greater London N9 9HJ",
    "addr:housenumber":"314",
    "addr:postcode":"n9 9hj",
    "addr:street":"Church Street",
    "iso:country":"GB",
    "sg:address":"314 Church Street",
    "sg:city":"London",
    "sg:classifiers":[
        {
            "category":"Building & Trades",
            "subcategory":"Landscaping Services",
            "type":"Services"
        }
    ],
    "sg:phone":"+44 20 8807 1486",
    "sg:postcode":"N9 9HJ",
    "sg:province":"Greater London",
    "sg:tags":[
        "gardening"
    ],
    "wof:name":"Dave Lee & Sons Landscapes",
    "wof:placetype":"venue"
},
  "geometry": {"coordinates":[-0.0773049966,51.6291656494],"type":"Point"}
}