{
  "type": "Feature",
  "properties": {
    "addr:full":"19 The Broadway Newbury Berkshire RG14 1AS",
    "addr:housenumber":"19",
    "addr:postcode":"rg14 1as",
    "addr:street":"The Broadway",
    "iso:country":"GB",
    "sg:address":"19 The Broadway",
    "sg:city":"Newbury",
    "sg:classifiers":[
        {
            "category":"Restaurant",
            "type":"Food & Drink"
        },
        {
            "category":"Community Center",
            "subcategory":"Social",
            "type":"Public Place"
        }
    ],
    "sg:phone":"+44 1635 36502",
    "sg:postcode":"RG14 1AS",
    "sg:province":"Berkshire",
    "sg:tags":[
        "house",
        "activity"
    ],
    "wof:name":"Richard & Skinner Simon Hayman",
    "wof:placetype":"venue"
},
  "geometry": {"coordinates":[-1.3245819807,51.402381897],"type":"Point"}
}