{
  "type": "Feature",
  "properties": {
    "addr:full":"Albion Pencader Carmarthenshire SA39 9ES",
    "addr:postcode":"sa39 9es",
    "iso:country":"GB",
    "sg:address":"Albion",
    "sg:city":"Pencader",
    "sg:classifiers":[
        {
            "category":"Government",
            "subcategory":"Post Office",
            "type":"Public Place"
        }
    ],
    "sg:phone":"+44 1559 384270",
    "sg:postcode":"SA39 9ES",
    "sg:province":"Carmarthenshire",
    "wof:name":"Pencader Post Office & Albion Stores",
    "wof:placetype":"venue"
},
  "geometry": {"coordinates":[-4.265864,52.000229],"type":"Point"}
}