{
  "type": "Feature",
  "properties": {
    "addr:full":"Unit 2h, Brown Lees Road Industrial Estate, Forge Way Stoke-on-trent Staffordshire ST8 7DN",
    "addr:housenumber":"2h",
    "addr:postcode":"st8 7dn",
    "addr:street":"Brown Lees Road Industrial Estate Forge Way",
    "iso:country":"GB",
    "sg:address":"Unit 2h, Brown Lees Road Industrial Estate, Forge Way",
    "sg:city":"Stoke-on-trent",
    "sg:classifiers":[
        {
            "category":"Manufacturing",
            "subcategory":"Metals",
            "type":"Manufacturing & Wholesale Goods"
        }
    ],
    "sg:phone":"+44 1782 511732",
    "sg:postcode":"ST8 7DN",
    "sg:province":"Staffordshire",
    "sg:tags":[
        "steel",
        "fabricator",
        "erectors"
    ],
    "wof:name":"J Copestake & Sons",
    "wof:placetype":"venue"
},
  "geometry": {"coordinates":[-2.1809339523,53.0974159241],"type":"Point"}
}