{
  "type": "Feature",
  "properties": {
    "addr:full":"Kingsway Ho, 103 Kingsway Holborn Greater London WC2B 6QX",
    "addr:housenumber":"103",
    "addr:postcode":"wc2b 6qx",
    "addr:street":"Kingsway;Kingsway",
    "iso:country":"GB",
    "sg:address":"Kingsway Ho, 103 Kingsway",
    "sg:city":"Holborn",
    "sg:classifiers":[
        {
            "category":"Professional",
            "subcategory":"Employment Agencies",
            "type":"Services"
        }
    ],
    "sg:phone":"+44 20 7430 2349",
    "sg:postcode":"WC2B 6QX",
    "sg:province":"Greater London",
    "sg:tags":[
        "consultant"
    ],
    "wof:name":"Hays Richard Owen",
    "wof:placetype":"venue"
},
  "geometry": {"coordinates":[-0.119719,51.516495],"type":"Point"}
}