{
  "type": "Feature",
  "properties": {
    "addr:full":"Unit W4, New House Business Park, New House Road Grangemouth Falkirk FK3 8LL",
    "addr:housenumber":"w4",
    "addr:postcode":"fk3 8ll",
    "addr:street":"Business Park New House Road",
    "iso:country":"GB",
    "sg:address":"Unit W4, New House Business Park, New House Road",
    "sg:city":"Grangemouth",
    "sg:classifiers":[
        {
            "category":"Health Services",
            "subcategory":"Dentist",
            "type":"Services"
        }
    ],
    "sg:phone":"+44 1324 482126",
    "sg:postcode":"FK3 8LL",
    "sg:province":"Falkirk",
    "sg:tags":[
        "technician",
        "dental"
    ],
    "wof:name":"John Anderson",
    "wof:placetype":"venue"
},
  "geometry": {"coordinates":[-3.727298975,56.0127296448],"type":"Point"}
}