{
  "type": "Feature",
  "properties": {
    "iso:country":"GB",
    "sg:address":"8 Avery Hill Road",
    "sg:city":"London",
    "sg:classifiers":[
        {
            "category":"Utilities",
            "subcategory":"Natural Gas",
            "type":"Services"
        }
    ],
    "sg:phone":"+44 20 8850 1458",
    "sg:postcode":"SE9 2BD",
    "sg:province":"Greater London",
    "sg:tags":[
        "supplier"
    ],
    "wof:name":"Cyclone Stripper Ltd.",
    "wof:placetype":"venue"
},
  "geometry": {"coordinates":[0.0726049989,51.437625885],"type":"Point"}
}