{
  "type": "Feature",
  "properties": {
    "iso:country":"GB",
    "sg:address":"183 Mitcham Lane",
    "sg:city":"Streatham",
    "sg:classifiers":[
        {
            "category":"Building & Trades",
            "subcategory":"Construction",
            "type":"Services"
        }
    ],
    "sg:phone":"+44 20 8677 5115",
    "sg:postcode":"SW16 6PN",
    "sg:province":"Greater London",
    "sg:tags":[
        "builder"
    ],
    "wof:name":"Remdec Emergency Services",
    "wof:placetype":"venue"
},
  "geometry": {"coordinates":[-0.144491002,51.4217376709],"type":"Point"}
}