{
  "type": "Feature",
  "properties": {
    "addr:full":"77a Central Hill Upper Norwood Greater London SE19 1BS",
    "addr:housenumber":"77a",
    "addr:postcode":"se19 1bs",
    "addr:street":"Central Hill",
    "iso:country":"GB",
    "sg:address":"77a Central Hill",
    "sg:city":"Upper Norwood",
    "sg:classifiers":[
        {
            "category":"Banks & Credit Unions",
            "subcategory":"Bank",
            "type":"Services"
        }
    ],
    "sg:phone":"+44 20 7738 0888",
    "sg:postcode":"SE19 1BS",
    "sg:province":"Greater London",
    "wof:name":"NatWest",
    "wof:placetype":"venue"
},
  "geometry": {"coordinates":[-0.088184,51.419788],"type":"Point"}
}