{
  "type": "Feature",
  "properties": {
    "addr:full":"13 Church Street Ebbw Vale Blaenau Gwent NP23 6BE",
    "addr:housenumber":"13",
    "addr:postcode":"np23 6be",
    "addr:street":"Church Street",
    "iso:country":"GB",
    "sg:address":"13 Church Street",
    "sg:city":"Ebbw Vale",
    "sg:classifiers":[
        {
            "category":"Home & Garden",
            "subcategory":"Building Materials",
            "type":"Retail Goods"
        }
    ],
    "sg:postcode":"NP23 6BE",
    "sg:province":"Blaenau Gwent",
    "sg:tags":[
        "brick"
    ],
    "wof:name":"Style Retail Ltd",
    "wof:placetype":"venue"
},
  "geometry": {"coordinates":[-3.2074460983,51.77394104],"type":"Point"}
}