{
  "type": "Feature",
  "properties": {
    "iso:country":"GB",
    "sg:address":"2 Norfolk Road",
    "sg:city":"Maidenhead",
    "sg:classifiers":[
        {
            "category":"Restaurant",
            "type":"Food & Drink"
        }
    ],
    "sg:phone":"+44 1628 621710",
    "sg:postcode":"SL6 7EE",
    "sg:province":"Berkshire",
    "wof:name":"MORRISON'S BAR & RESTAURANT LTD",
    "wof:placetype":"venue"
},
  "geometry": {"coordinates":[-0.722978,51.526562],"type":"Point"}
}