{
  "type": "Feature",
  "properties": {
    "iso:country":"GB",
    "sg:address":"19 Newarke St",
    "sg:city":"Leicester",
    "sg:classifiers":[
        {
            "category":"Professional",
            "type":"Services"
        }
    ],
    "sg:phone":"+44 116 255 3336",
    "sg:postcode":"LE1 5SN",
    "sg:province":"Leicestershire",
    "sg:tags":[
        "interior",
        "furnishers",
        "designer"
    ],
    "wof:name":"Stirling Interiors",
    "wof:placetype":"venue"
},
  "geometry": {"coordinates":[-1.1353030205,52.6319961548],"type":"Point"}
}