{
  "type": "Feature",
  "properties": {
    "iso:country":"GB",
    "sg:address":"16 High St, Winterbourne",
    "sg:city":"Bristol",
    "sg:classifiers":[
        {
            "category":"Shopping",
            "subcategory":"Thrift Store",
            "type":"Retail Goods"
        }
    ],
    "sg:phone":"+44 1454 776859",
    "sg:postcode":"BS36 1JN",
    "sg:province":"Gloucestershire",
    "sg:tags":[
        "shop",
        "charity"
    ],
    "wof:name":"Break",
    "wof:placetype":"venue"
},
  "geometry": {"coordinates":[-2.508881,51.523853],"type":"Point"}
}