{
  "type": "Feature",
  "properties": {
    "iso:country":"GB",
    "sg:address":"Half Moon Lane",
    "sg:city":"Alford",
    "sg:classifiers":[
        {
            "category":"Retail",
            "subcategory":"Auto Repair",
            "type":"Services"
        }
    ],
    "sg:phone":"+44 1507 463435",
    "sg:postcode":"LN13 9ES",
    "sg:province":"Lincolnshire",
    "sg:tags":[
        "modification",
        "garage"
    ],
    "wof:name":"Sid Inckles Garage",
    "wof:placetype":"venue"
},
  "geometry": {"coordinates":[0.176865,53.260357],"type":"Point"}
}