{
  "type": "Feature",
  "properties": {
    "iso:country":"GB",
    "sg:address":"21a High Street",
    "sg:city":"Ely",
    "sg:classifiers":[
        {
            "category":"Personal",
            "subcategory":"Shoe Repair & Shine",
            "type":"Services"
        },
        {
            "category":"Shopping",
            "subcategory":"Shoes",
            "type":"Retail Goods"
        }
    ],
    "sg:phone":"+44 1353 669907",
    "sg:postcode":"CB7 4LQ",
    "sg:province":"Cambridgeshire",
    "wof:name":"Well Heeled",
    "wof:placetype":"venue"
},
  "geometry": {"coordinates":[0.2641789913,52.3995018005],"type":"Point"}
}