{
  "type": "Feature",
  "properties": {
    "iso:country":"GB",
    "sg:address":"111a Great Western Road",
    "sg:city":"Aberdeen",
    "sg:classifiers":[
        {
            "category":"Building & Trades",
            "subcategory":"Construction",
            "type":"Services"
        }
    ],
    "sg:postcode":"AB10 6PT",
    "sg:province":"Aberdeen City",
    "sg:tags":[
        "roofing"
    ],
    "wof:name":"Aberdeen Roofline Products",
    "wof:placetype":"venue"
},
  "geometry": {"coordinates":[-2.11802,57.138573],"type":"Point"}
}