{
  "type": "Feature",
  "properties": {
    "addr:full":"4 East Reach Taunton Somerset TA1 3EN",
    "addr:housenumber":"4",
    "addr:postcode":"ta1 3en",
    "addr:street":"East Reach",
    "iso:country":"GB",
    "sg:address":"4 East Reach",
    "sg:city":"Taunton",
    "sg:classifiers":[
        {
            "category":"Shopping",
            "subcategory":"Mobile Phones",
            "type":"Retail Goods"
        }
    ],
    "sg:phone":"+44 1823 321300",
    "sg:postcode":"TA1 3EN",
    "sg:province":"Somerset",
    "wof:name":"Airwaves Communications (1996) Ltd",
    "wof:placetype":"venue"
},
  "geometry": {"coordinates":[-3.0964720249,51.0151367188],"type":"Point"}
}