{
  "type": "Feature",
  "properties": {
    "iso:country":"GB",
    "sg:address":"158 Burchells Green Road",
    "sg:city":"Bristol",
    "sg:classifiers":[
        {
            "category":"Bars & Pubs",
            "type":"Food & Drink"
        }
    ],
    "sg:phone":"+44 117 949 7741",
    "sg:postcode":"BS15 1DY",
    "sg:province":"City of Bristol",
    "sg:tags":[
        "pubs",
        "inn"
    ],
    "wof:name":"The Lamb & Lark",
    "wof:placetype":"venue"
},
  "geometry": {"coordinates":[-2.5245580673,51.4663658142],"type":"Point"}
}