{
  "type": "Feature",
  "properties": {
    "iso:country":"GB",
    "sg:address":"Saucer Farm Main Street, Aslockton",
    "sg:city":"Nottingham",
    "sg:classifiers":[
        {
            "category":"Professional",
            "subcategory":"Printing & Photocopies",
            "type":"Services"
        }
    ],
    "sg:phone":"+44 1949 851611",
    "sg:postcode":"NG13 9AL",
    "sg:province":"Leicestershire",
    "sg:tags":[
        "computer",
        "tag",
        "label"
    ],
    "wof:name":"Aspect Print Services Ltd.",
    "wof:placetype":"venue"
},
  "geometry": {"coordinates":[-0.8972049952,52.9524536133],"type":"Point"}
}