{
  "type": "Feature",
  "properties": {
    "iso:country":"GB",
    "sg:address":"19 Dunstable Street, Ampthill",
    "sg:city":"Bedford",
    "sg:classifiers":[
        {
            "category":"Health Services",
            "subcategory":"Dentist",
            "type":"Services"
        }
    ],
    "sg:phone":"+44 1525 403205",
    "sg:postcode":"MK45 2NJ",
    "sg:province":"Bedfordshire",
    "wof:name":"Dental Surgery",
    "wof:placetype":"venue"
},
  "geometry": {"coordinates":[-0.4948439896,52.0277328491],"type":"Point"}
}