{
  "type": "Feature",
  "properties": {
    "iso:country":"GB",
    "sg:address":"Precision House, Ring Road",
    "sg:city":"Leeds",
    "sg:classifiers":[
        {
            "category":"Professional",
            "subcategory":"Printing & Photocopies",
            "type":"Services"
        }
    ],
    "sg:phone":"+44 113 232 3773",
    "sg:postcode":"LS14 1NH",
    "sg:province":"West Yorkshire",
    "sg:tags":[
        "plate",
        "lithographic",
        "maker"
    ],
    "wof:name":"Colour Concept",
    "wof:placetype":"venue"
},
  "geometry": {"coordinates":[-1.5566300154,53.7986717224],"type":"Point"}
}