{
  "type": "Feature",
  "properties": {
    "addr:full":"27 Byrom Street Manchester Greater Manchester M3 4PF",
    "addr:housenumber":"27",
    "addr:postcode":"m3 4pf",
    "addr:street":"Byrom Street",
    "iso:country":"GB",
    "sg:address":"27 Byrom Street",
    "sg:city":"Manchester",
    "sg:classifiers":[
        {
            "category":"Health Services",
            "subcategory":"Doctor",
            "type":"Services"
        }
    ],
    "sg:phone":"+44 161 834 9141",
    "sg:postcode":"M3 4PF",
    "sg:province":"Greater Manchester",
    "sg:tags":[
        "practitioners"
    ],
    "wof:name":"Cheadle M R Associates",
    "wof:placetype":"venue"
},
  "geometry": {"coordinates":[-2.2520749569,53.4776992798],"type":"Point"}
}