{
  "type": "Feature",
  "properties": {
    "addr:full":"Home Farm, Coach Road, Butterley Ripley Derbyshire DE5 3QU",
    "addr:postcode":"de5 3qu",
    "addr:street":"Coach Road",
    "iso:country":"GB",
    "sg:address":"Home Farm, Coach Road, Butterley",
    "sg:city":"Ripley",
    "sg:classifiers":[
        {
            "category":"Real Estate",
            "subcategory":"Developer",
            "type":"Services"
        },
        {
            "category":"Building & Trades",
            "subcategory":"Construction",
            "type":"Services"
        }
    ],
    "sg:phone":"+44 1773 744148",
    "sg:postcode":"DE5 3QU",
    "sg:province":"Derbyshire",
    "sg:tags":[
        "builder",
        "property"
    ],
    "wof:name":"John Dobb Development Co Ltd",
    "wof:placetype":"venue"
},
  "geometry": {"coordinates":[-1.407668,53.050701],"type":"Point"}
}