{
  "type": "Feature",
  "properties": {
    "addr:full":"Hawks Road Gateshead Tyne and Wear NE8 3BL",
    "addr:postcode":"ne8 3bl",
    "addr:street":"Hawks Road",
    "iso:country":"GB",
    "sg:address":"Hawks Road",
    "sg:city":"Gateshead",
    "sg:classifiers":[
        {
            "category":"Food & Beverages",
            "subcategory":"Meat & Fish",
            "type":"Retail Goods"
        }
    ],
    "sg:phone":"+44 191 477 7577",
    "sg:postcode":"NE8 3BL",
    "sg:province":"Tyne and Wear",
    "sg:tags":[
        "chip"
    ],
    "wof:name":"Billy Bunters",
    "wof:placetype":"venue"
},
  "geometry": {"coordinates":[-1.593491,54.968346],"type":"Point"}
}