{
  "type": "Feature",
  "properties": {
    "addr:full":"Pipers Cottage, The Street Arundel West Sussex BN18 0PY",
    "addr:postcode":"bn18 0py",
    "addr:street":"The Street",
    "iso:country":"GB",
    "sg:address":"Pipers Cottage, The Street",
    "sg:city":"Arundel",
    "sg:classifiers":[
        {
            "category":"Professional",
            "type":"Services"
        }
    ],
    "sg:phone":"+44 1243 545700",
    "sg:postcode":"BN18 0PY",
    "sg:province":"West Sussex",
    "sg:tags":[
        "interior",
        "furnishers",
        "designer"
    ],
    "wof:name":"African Cloth Co",
    "wof:placetype":"venue"
},
  "geometry": {"coordinates":[-0.554589,50.854836],"type":"Point"}
}