{
  "type": "Feature",
  "properties": {
    "iso:country":"GB",
    "sg:address":"33 Shaftsbury Av",
    "sg:city":"Doncaster",
    "sg:classifiers":[
        {
            "category":"Professional",
            "subcategory":"Computer Services",
            "type":"Services"
        }
    ],
    "sg:phone":"+44 1302 728176",
    "sg:postcode":"DN6 7TB",
    "sg:province":"North Yorkshire",
    "sg:tags":[
        "system",
        "software"
    ],
    "wof:name":"Elite IT",
    "wof:placetype":"venue"
},
  "geometry": {"coordinates":[-1.2049080133,53.5694465637],"type":"Point"}
}