{
  "type": "Feature",
  "properties": {
    "iso:country":"GB",
    "sg:address":"25 Morrison Avenue, Maltby",
    "sg:city":"Rotherham",
    "sg:classifiers":[
        {
            "category":"Building & Trades",
            "subcategory":"Cleaning & Sanitation",
            "type":"Services"
        }
    ],
    "sg:phone":"+44 1709 815100",
    "sg:postcode":"S66 7EY",
    "sg:province":"South Yorkshire",
    "sg:tags":[
        "sweep",
        "chimney"
    ],
    "wof:name":"R Stubbs",
    "wof:placetype":"venue"
},
  "geometry": {"coordinates":[-1.2026610374,53.4301681519],"type":"Point"}
}