{
  "type": "Feature",
  "properties": {
    "iso:country":"GB",
    "sg:address":"Unit 4, 54-58 Greenfield Rd",
    "sg:city":"London",
    "sg:classifiers":[
        {
            "category":"Wholesale",
            "subcategory":"Apparel",
            "type":"Manufacturing & Wholesale Goods"
        }
    ],
    "sg:postcode":"E1 1EJ",
    "sg:province":"Greater London",
    "sg:tags":[
        "w'sale",
        "ladieswear"
    ],
    "wof:name":"City Smart Ltd",
    "wof:placetype":"venue"
},
  "geometry": {"coordinates":[-0.064935,51.515163],"type":"Point"}
}