{
  "type": "Feature",
  "properties": {
    "iso:country":"GB",
    "sg:address":"71-73 Bramford Road",
    "sg:city":"Ipswich",
    "sg:classifiers":[
        {
            "category":"Personal",
            "subcategory":"Beauty Salon",
            "type":"Services"
        },
        {
            "category":"Personal",
            "subcategory":"Barber",
            "type":"Services"
        }
    ],
    "sg:phone":"+44 1473 219510",
    "sg:postcode":"IP1 2LT",
    "sg:province":"Suffolk",
    "sg:tags":[
        "unisex",
        "hairdresser"
    ],
    "wof:name":"Adam & Eve",
    "wof:placetype":"venue"
},
  "geometry": {"coordinates":[1.140179,52.062256],"type":"Point"}
}