{
  "type": "Feature",
  "properties": {
    "addr:full":"36 Church Rd Ferndown Dorset BH22 9EU",
    "addr:housenumber":"36",
    "addr:postcode":"bh22 9eu",
    "addr:street":"Church Rd",
    "iso:country":"GB",
    "sg:address":"36 Church Rd",
    "sg:city":"Ferndown",
    "sg:classifiers":[
        {
            "category":"Home & Garden",
            "subcategory":"Building Materials",
            "type":"Retail Goods"
        }
    ],
    "sg:postcode":"BH22 9EU",
    "sg:province":"Dorset",
    "sg:tags":[
        "insulation",
        "installers"
    ],
    "wof:name":"Birchmore,Ian,",
    "wof:placetype":"venue"
},
  "geometry": {"coordinates":[-1.895789,50.802105],"type":"Point"}
}