{
  "type": "Feature",
  "properties": {
    "addr:full":"Unit F11, Northfleet Ind Est, Lower Rd Gravesend Kent DA11 9SW",
    "addr:housenumber":"f11",
    "addr:postcode":"da11 9sw",
    "addr:street":"Lower Rd",
    "iso:country":"GB",
    "sg:address":"Unit F11, Northfleet Ind Est, Lower Rd",
    "sg:city":"Gravesend",
    "sg:classifiers":[
        {
            "category":"Building & Trades",
            "subcategory":"Construction",
            "type":"Services"
        }
    ],
    "sg:phone":"+44 1322 385158",
    "sg:postcode":"DA11 9SW",
    "sg:province":"Kent",
    "sg:tags":[
        "dry",
        "lining",
        "plasterers",
        "screeders"
    ],
    "wof:name":"Now Fine",
    "wof:placetype":"venue"
},
  "geometry": {"coordinates":[0.364606,51.432827],"type":"Point"}
}