{
  "type": "Feature",
  "properties": {
    "addr:full":"12 Whitbread Clo Eastbourne East Sussex BN23 8HF",
    "addr:housenumber":"12",
    "addr:postcode":"bn23 8hf",
    "addr:street":"Whitbread Clo",
    "iso:country":"GB",
    "sg:address":"12 Whitbread Clo",
    "sg:city":"Eastbourne",
    "sg:classifiers":[
        {
            "category":"Home & Garden",
            "subcategory":"Building Materials",
            "type":"Retail Goods"
        }
    ],
    "sg:postcode":"BN23 8HF",
    "sg:province":"East Sussex",
    "sg:tags":[
        "fencing"
    ],
    "wof:name":"Higson,R D,",
    "wof:placetype":"venue"
},
  "geometry": {"coordinates":[0.295918,50.811691],"type":"Point"}
}