{
  "type": "Feature",
  "properties": {
    "addr:full":"Unit 32 Hillhouse Community Workshop, Argyle Cres Hamilton South Lanarkshire ML3 9BQ",
    "addr:housenumber":"unit 32",
    "addr:postcode":"ml3 9bq",
    "addr:street":"Argyle Cres",
    "iso:country":"GB",
    "sg:address":"Unit 32 Hillhouse Community Workshop, Argyle Cres",
    "sg:city":"Hamilton",
    "sg:classifiers":[
        {
            "category":"Building & Trades",
            "subcategory":"Construction",
            "type":"Services"
        }
    ],
    "sg:phone":"+44 1698 285050",
    "sg:postcode":"ML3 9BQ",
    "sg:province":"South Lanarkshire",
    "sg:tags":[
        "heating",
        "contractor"
    ],
    "wof:name":"Scotcare Heating",
    "wof:placetype":"venue"
},
  "geometry": {"coordinates":[-4.076338768,55.773311615],"type":"Point"}
}