{
  "type": "Feature",
  "properties": {
    "iso:country":"GB",
    "sg:address":"Market Place",
    "sg:city":"Hartlepool",
    "sg:classifiers":[
        {
            "category":"Bus Charters",
            "type":"Transportation"
        }
    ],
    "sg:phone":"+44 1429 267082",
    "sg:postcode":"TS24 7DS",
    "sg:province":"Durham",
    "sg:tags":[
        "coach"
    ],
    "wof:name":"Hartlepool Transport Ltd.",
    "wof:placetype":"venue"
},
  "geometry": {"coordinates":[-1.2141189575,54.6854057312],"type":"Point"}
}