{
  "type": "Feature",
  "properties": {
    "iso:country":"GB",
    "sg:address":"2a Union Street",
    "sg:city":"Newton Abbot",
    "sg:classifiers":[
        {
            "category":"Shopping",
            "subcategory":"Florist",
            "type":"Retail Goods"
        }
    ],
    "sg:phone":"+44 1626 366359",
    "sg:postcode":"TQ12 2JS",
    "sg:province":"Devon",
    "wof:name":"Bouquets Florists",
    "wof:placetype":"venue"
},
  "geometry": {"coordinates":[-3.610201,50.530167],"type":"Point"}
}