{
  "type": "Feature",
  "properties": {
    "addr:full":"2a Lake Industrial Way Sandown Isle of Wight PO36 9PL",
    "addr:housenumber":"2a",
    "addr:postcode":"po36 9pl",
    "addr:street":"Lake Industrial Way",
    "iso:country":"GB",
    "sg:address":"2a Lake Industrial Way",
    "sg:city":"Sandown",
    "sg:classifiers":[
        {
            "category":"Building & Trades",
            "subcategory":"Construction",
            "type":"Services"
        }
    ],
    "sg:postcode":"PO36 9PL",
    "sg:province":"Isle of Wight",
    "sg:tags":[
        "contractor",
        "pool",
        "swimming"
    ],
    "wof:name":"Swimming Pool Air Systems",
    "wof:placetype":"venue"
},
  "geometry": {"coordinates":[-1.162262,50.650146],"type":"Point"}
}