{
  "type": "Feature",
  "properties": {
    "addr:full":"31 Victoria Rd Keighley West Yorkshire BD21 1HD",
    "addr:housenumber":"31",
    "addr:postcode":"bd21 1hd",
    "addr:street":"Victoria Rd",
    "iso:country":"GB",
    "sg:address":"31 Victoria Rd",
    "sg:city":"Keighley",
    "sg:classifiers":[
        {
            "category":"Travel",
            "subcategory":"Travel Agent",
            "type":"Entertainment"
        }
    ],
    "sg:postcode":"BD21 1HD",
    "sg:province":"West Yorkshire",
    "wof:name":"Al Ziarath",
    "wof:placetype":"venue"
},
  "geometry": {"coordinates":[-1.9136799574,53.8600387573],"type":"Point"}
}