{
  "type": "Feature",
  "properties": {
    "addr:full":"8 Vaughan Road Torquay Devon TQ2 5EQ",
    "addr:housenumber":"8",
    "addr:postcode":"tq2 5eq",
    "addr:street":"Vaughan Road",
    "iso:country":"GB",
    "sg:address":"8 Vaughan Road",
    "sg:city":"Torquay",
    "sg:classifiers":[
        {
            "category":"Restaurant",
            "type":"Food & Drink"
        }
    ],
    "sg:phone":"+44 1803 292255",
    "sg:postcode":"TQ2 5EQ",
    "sg:province":"Devon",
    "wof:name":"Marina Restaurant",
    "wof:placetype":"venue"
},
  "geometry": {"coordinates":[-3.5264749527,50.4610748291],"type":"Point"}
}