{
  "type": "Feature",
  "properties": {
    "iso:country":"GB",
    "sg:address":"New Park St",
    "sg:city":"Devizes",
    "sg:classifiers":[
        {
            "category":"Travel",
            "subcategory":"Hotels & Motels",
            "type":"Entertainment"
        }
    ],
    "sg:phone":"+44 1380 729300",
    "sg:postcode":"SN10 1DS",
    "sg:province":"Wiltshire",
    "wof:name":"The Castle Hotel",
    "wof:placetype":"venue"
},
  "geometry": {"coordinates":[-1.9957139492,51.3541488647],"type":"Point"}
}