{
  "type": "Feature",
  "properties": {
    "addr:full":"Unit 19, Whitemoor Court Nottingham Nottinghamshire NG8 5BY",
    "addr:housenumber":"unit 19",
    "addr:postcode":"ng8 5by",
    "addr:street":"Whitemoor Court",
    "iso:country":"GB",
    "sg:address":"Unit 19, Whitemoor Court",
    "sg:city":"Nottingham",
    "sg:classifiers":[
        {
            "category":"Wholesale",
            "subcategory":"Machinery & Supplies",
            "type":"Manufacturing & Wholesale Goods"
        }
    ],
    "sg:phone":"+44 115 929 9746",
    "sg:postcode":"NG8 5BY",
    "sg:province":"Nottinghamshire",
    "sg:tags":[
        "pump"
    ],
    "wof:name":"B & H Industrial Pumps",
    "wof:placetype":"venue"
},
  "geometry": {"coordinates":[-1.181978941,52.9706687927],"type":"Point"}
}