{
  "type": "Feature",
  "properties": {
    "addr:full":"30 Arthur Road St Albans Hertfordshire AL1 4SZ",
    "addr:housenumber":"30",
    "addr:postcode":"al1 4sz",
    "addr:street":"Arthur Road",
    "iso:country":"GB",
    "sg:address":"30 Arthur Road",
    "sg:city":"St Albans",
    "sg:classifiers":[
        {
            "category":"Building & Trades",
            "subcategory":"Construction",
            "type":"Services"
        }
    ],
    "sg:phone":"+44 1727 859656",
    "sg:postcode":"AL1 4SZ",
    "sg:province":"Hertfordshire",
    "sg:tags":[
        "dry",
        "plastering",
        "plasterers",
        "lining",
        "related",
        "screeders"
    ],
    "wof:name":"David Jay",
    "wof:placetype":"venue"
},
  "geometry": {"coordinates":[-0.310951,51.752434],"type":"Point"}
}