{
  "type": "Feature",
  "properties": {
    "iso:country":"GB",
    "sg:address":"53 Thorntree Road, Stockton",
    "sg:city":"Stockton-on-tees",
    "sg:classifiers":[
        {
            "category":"Shopping",
            "subcategory":"News",
            "type":"Retail Goods"
        }
    ],
    "sg:phone":"+44 1642 673829",
    "sg:postcode":"TS17 8LJ",
    "sg:province":"Durham",
    "sg:tags":[
        "newsagent"
    ],
    "wof:name":"Forbuoys",
    "wof:placetype":"venue"
},
  "geometry": {"coordinates":[-1.298826,54.545742],"type":"Point"}
}