{
  "type": "Feature",
  "properties": {
    "iso:country":"GB",
    "sg:address":"Hilmarton",
    "sg:city":"Calne",
    "sg:classifiers":[
        {
            "category":"Retail",
            "subcategory":"Auto Repair",
            "type":"Services"
        }
    ],
    "sg:phone":"+44 1249 760259",
    "sg:postcode":"SN11 8SD",
    "sg:province":"Wiltshire",
    "sg:tags":[
        "modification",
        "garage"
    ],
    "wof:name":"Hilmarton Garage",
    "wof:placetype":"venue"
},
  "geometry": {"coordinates":[-1.9735200405,51.4776115417],"type":"Point"}
}