{
  "type": "Feature",
  "properties": {
    "iso:country":"GB",
    "sg:address":"Unit 3 School Street, Methley Road",
    "sg:city":"Castleford",
    "sg:classifiers":[
        {
            "category":"Communications",
            "subcategory":"Film & Video Production",
            "type":"Services"
        }
    ],
    "sg:phone":"+44 1977 668138",
    "sg:postcode":"WF10 1LX",
    "sg:province":"West Yorkshire",
    "sg:tags":[
        "tv"
    ],
    "wof:name":"Tele View Direct",
    "wof:placetype":"venue"
},
  "geometry": {"coordinates":[-1.3645540476,53.7264900208],"type":"Point"}
}