{
  "type": "Feature",
  "properties": {
    "iso:country":"GB",
    "sg:address":"30 Castle Street",
    "sg:city":"Clitheroe",
    "sg:classifiers":[
        {
            "category":"Shopping",
            "subcategory":"Optical Goods",
            "type":"Retail Goods"
        },
        {
            "category":"Shopping",
            "subcategory":"Photographic Equipment",
            "type":"Retail Goods"
        }
    ],
    "sg:phone":"+44 1200 444744",
    "sg:postcode":"BB7 2BX",
    "sg:province":"Lancashire",
    "sg:tags":[
        "supply"
    ],
    "wof:name":"U K Digital Ltd.",
    "wof:placetype":"venue"
},
  "geometry": {"coordinates":[-2.3914179802,53.8721733093],"type":"Point"}
}