{
  "type": "Feature",
  "properties": {
    "iso:country":"GB",
    "sg:address":"13 Pembroke Street",
    "sg:city":"Cambridge",
    "sg:classifiers":[
        {
            "category":"Cafe",
            "type":"Food & Drink"
        }
    ],
    "sg:phone":"+44 1223 460923",
    "sg:postcode":"CB2 3QY",
    "sg:province":"Cambridgeshire",
    "sg:tags":[
        "tea",
        "snack",
        "bar",
        "room"
    ],
    "wof:name":"Trockel Ulmann & Freunde",
    "wof:placetype":"venue"
},
  "geometry": {"coordinates":[0.119078,52.202415],"type":"Point"}
}