{
  "type": "Feature",
  "properties": {
    "addr:full":"211 Whiteladies Road Bristol City of Bristol BS8 2XS",
    "addr:housenumber":"211",
    "addr:postcode":"bs8 2xs",
    "addr:street":"Whiteladies Road",
    "iso:country":"GB",
    "sg:address":"211 Whiteladies Road",
    "sg:city":"Bristol",
    "sg:classifiers":[
        {
            "category":"Fast Food",
            "type":"Food & Drink"
        }
    ],
    "sg:phone":"+44 117 973 3823",
    "sg:postcode":"BS8 2XS",
    "sg:province":"City of Bristol",
    "sg:tags":[
        "away",
        "take"
    ],
    "wof:name":"Clifton Tandoori Restaurant",
    "wof:placetype":"venue"
},
  "geometry": {"coordinates":[-2.6144900322,51.4700622559],"type":"Point"}
}