{
  "type": "Feature",
  "properties": {
    "addr:full":"Hortus Road Southall Greater London UB2 4AJ",
    "addr:postcode":"ub2 4aj",
    "addr:street":"Hortus Road",
    "iso:country":"GB",
    "sg:address":"Hortus Road",
    "sg:city":"Southall",
    "sg:classifiers":[
        {
            "category":"Retail",
            "subcategory":"Auto Repair",
            "type":"Services"
        }
    ],
    "sg:postcode":"UB2 4AJ",
    "sg:province":"Greater London",
    "sg:tags":[
        "body",
        "car"
    ],
    "wof:name":"Bodytec",
    "wof:placetype":"venue"
},
  "geometry": {"coordinates":[-0.3782539964,51.5045204163],"type":"Point"}
}