{
  "type": "Feature",
  "properties": {
    "addr:full":"Hillview Cottage, Summerfield Earlston Scottish Borders TD4 6ET",
    "addr:postcode":"td4 6et",
    "addr:street":"Summerfield",
    "iso:country":"GB",
    "sg:address":"Hillview Cottage, Summerfield",
    "sg:city":"Earlston",
    "sg:classifiers":[
        {
            "category":"Home & Garden",
            "subcategory":"Home Furnishings",
            "type":"Retail Goods"
        }
    ],
    "sg:postcode":"TD4 6ET",
    "sg:province":"Scottish Borders",
    "sg:tags":[
        "blind",
        "curtain",
        "fitting"
    ],
    "wof:name":"Curtain Track",
    "wof:placetype":"venue"
},
  "geometry": {"coordinates":[-2.6756188869,55.6385498047],"type":"Point"}
}