{
  "type": "Feature",
  "properties": {
    "addr:full":"12 Willow Street London Greater London EC2A 4BH",
    "addr:housenumber":"12",
    "addr:postcode":"ec2a 4bh",
    "addr:street":"Willow Street",
    "iso:country":"GB",
    "sg:address":"12 Willow Street",
    "sg:city":"London",
    "sg:classifiers":[
        {
            "category":"Professional",
            "subcategory":"Business Services",
            "type":"Services"
        }
    ],
    "sg:postcode":"EC2A 4BH",
    "sg:province":"Greater London",
    "sg:tags":[
        "distribution"
    ],
    "wof:name":"Britain & Overseas Trading (Bristles) Ltd.",
    "wof:placetype":"venue"
},
  "geometry": {"coordinates":[-0.08257,51.525284],"type":"Point"}
}