{
  "type": "Feature",
  "properties": {
    "iso:country":"GB",
    "sg:address":"Red Tiles, Church Hill, Merstham",
    "sg:city":"Redhill",
    "sg:classifiers":[
        {
            "category":"Banks & Credit Unions",
            "subcategory":"Bureau De Change",
            "type":"Services"
        }
    ],
    "sg:phone":"+44 1737 644064",
    "sg:postcode":"RH1 3BL",
    "sg:province":"Surrey",
    "sg:tags":[
        "town",
        "consultant",
        "planning"
    ],
    "wof:name":"Richard A Humphreys",
    "wof:placetype":"venue"
},
  "geometry": {"coordinates":[-0.152545,51.264359],"type":"Point"}
}