{
  "type": "Feature",
  "properties": {
    "iso:country":"GB",
    "sg:address":"14 Scott St",
    "sg:city":"Keighley",
    "sg:classifiers":[
        {
            "category":"Professional",
            "subcategory":"Lawyer & Legal Services",
            "type":"Services"
        }
    ],
    "sg:phone":"+44 1535 611092",
    "sg:postcode":"BD21 2JJ",
    "sg:province":"West Yorkshire",
    "sg:tags":[
        "advice",
        "counselling"
    ],
    "wof:name":"Bradford Mental Health Advocacy Group",
    "wof:placetype":"venue"
},
  "geometry": {"coordinates":[-1.910401,53.868031],"type":"Point"}
}