{
  "type": "Feature",
  "properties": {
    "iso:country":"GB",
    "sg:address":"131 Green Lane",
    "sg:city":"Derby",
    "sg:classifiers":[
        {
            "category":"Building & Trades",
            "subcategory":"Construction",
            "type":"Services"
        }
    ],
    "sg:phone":"+44 1332 201811",
    "sg:postcode":"DE1 1RZ",
    "sg:province":"Derbyshire",
    "sg:tags":[
        "builder",
        "heating",
        "contractor"
    ],
    "wof:name":"Premier Engineering Services Ltd.",
    "wof:placetype":"venue"
},
  "geometry": {"coordinates":[-1.4779759645,52.9180603027],"type":"Point"}
}