{
  "type": "Feature",
  "properties": {
    "addr:full":"75 Hyde End Road, Shinfield Reading Berkshire RG2 9EP",
    "addr:housenumber":"75",
    "addr:postcode":"rg2 9ep",
    "addr:street":"Hyde End Road",
    "iso:country":"GB",
    "sg:address":"75 Hyde End Road, Shinfield",
    "sg:city":"Reading",
    "sg:classifiers":[
        {
            "category":"Wholesale",
            "subcategory":"Sporting Goods",
            "type":"Manufacturing & Wholesale Goods"
        }
    ],
    "sg:phone":"+44 118 988 2802",
    "sg:postcode":"RG2 9EP",
    "sg:province":"Berkshire",
    "sg:tags":[
        "mnfr",
        "sport",
        "equipment"
    ],
    "wof:name":"Forum Sport International Ltd.",
    "wof:placetype":"venue"
},
  "geometry": {"coordinates":[-0.946839,51.403339],"type":"Point"}
}