{
  "type": "Feature",
  "properties": {
    "addr:full":"Dudbridge Road, Dudbridge Stroud Gloucestershire GL5 3HF",
    "addr:postcode":"gl5 3hf",
    "addr:street":"Dudbridge Road",
    "iso:country":"GB",
    "sg:address":"Dudbridge Road, Dudbridge",
    "sg:city":"Stroud",
    "sg:classifiers":[
        {
            "category":"Autos & Motor Vehicles",
            "subcategory":"Fuel & Gas Station",
            "type":"Retail Goods"
        }
    ],
    "sg:phone":"+44 1453 762345",
    "sg:postcode":"GL5 3HF",
    "sg:province":"Gloucestershire",
    "sg:tags":[
        "petrol",
        "filling"
    ],
    "wof:name":"Dudbridge Garage",
    "wof:placetype":"venue"
},
  "geometry": {"coordinates":[-2.2394089699,51.7430953979],"type":"Point"}
}