{
  "type": "Feature",
  "properties": {
    "addr:full":"1 Alcombe House, 5 Holden Avenue North Finchley Greater London N12 8HY",
    "addr:housenumber":"1;5",
    "addr:postcode":"n12 8hy",
    "addr:street":"Holden Avenue",
    "iso:country":"GB",
    "sg:address":"1 Alcombe House, 5 Holden Avenue",
    "sg:city":"North Finchley",
    "sg:classifiers":[
        {
            "category":"Travel",
            "subcategory":"Travel Agent",
            "type":"Entertainment"
        }
    ],
    "sg:postcode":"N12 8HY",
    "sg:province":"Greater London",
    "wof:name":"N S T Travel & Trading Co",
    "wof:placetype":"venue"
},
  "geometry": {"coordinates":[-0.184584,51.61705],"type":"Point"}
}