{
  "type": "Feature",
  "properties": {
    "addr:full":"Ollerton Road, Arnold Nottingham Nottinghamshire NG5 8PR",
    "addr:postcode":"ng5 8pr",
    "addr:street":"Ollerton Road",
    "iso:country":"GB",
    "sg:address":"Ollerton Road, Arnold",
    "sg:city":"Nottingham",
    "sg:classifiers":[
        {
            "category":"Wholesale",
            "subcategory":"Scrap",
            "type":"Manufacturing & Wholesale Goods"
        },
        {
            "category":"Utilities",
            "subcategory":"Recycling",
            "type":"Services"
        }
    ],
    "sg:postcode":"NG5 8PR",
    "sg:province":"Nottinghamshire",
    "sg:tags":[
        "waste",
        "metal"
    ],
    "wof:name":"BURNTSTUMP RECYCLING CENTRE",
    "wof:placetype":"venue"
},
  "geometry": {"coordinates":[-1.1288609505,53.0452575684],"type":"Point"}
}