{
  "type": "Feature",
  "properties": {
    "iso:country":"GB",
    "sg:address":"Upper Mantle Close, Bridge Street, Clay Cross",
    "sg:city":"Chesterfield",
    "sg:classifiers":[
        {
            "category":"Retail",
            "subcategory":"Auto Repair",
            "type":"Services"
        }
    ],
    "sg:phone":"+44 1246 250022",
    "sg:postcode":"S45 9NU",
    "sg:province":"Derbyshire",
    "sg:tags":[
        "bodybuilder",
        "repairer"
    ],
    "wof:name":"Pampas Motor Caravans Ltd.",
    "wof:placetype":"venue"
},
  "geometry": {"coordinates":[-1.412287,53.170467],"type":"Point"}
}