{
  "type": "Feature",
  "properties": {
    "iso:country":"GB",
    "sg:address":"15 Castle St",
    "sg:city":"High Wycombe",
    "sg:classifiers":[
        {
            "category":"Shopping",
            "subcategory":"Photographic Equipment",
            "type":"Retail Goods"
        }
    ],
    "sg:phone":"+44 1494 441941",
    "sg:postcode":"HP13 6RU",
    "sg:province":"Buckinghamshire",
    "sg:tags":[
        "supply"
    ],
    "wof:name":"Wycombe Cameras & Video",
    "wof:placetype":"venue"
},
  "geometry": {"coordinates":[-0.749042,51.630173],"type":"Point"}
}