{
  "type": "Feature",
  "properties": {
    "iso:country":"GB",
    "sg:address":"38 Church Street",
    "sg:city":"Ashbourne",
    "sg:classifiers":[
        {
            "category":"Shopping",
            "subcategory":"Antiques",
            "type":"Retail Goods"
        }
    ],
    "sg:phone":"+44 1335 300061",
    "sg:postcode":"DE6 1AJ",
    "sg:province":"Derbyshire",
    "wof:name":"M G Bassett",
    "wof:placetype":"venue"
},
  "geometry": {"coordinates":[-1.7358620167,53.0160675049],"type":"Point"}
}