{
  "type": "Feature",
  "properties": {
    "iso:country":"GB",
    "sg:address":"7 Bellview Rd",
    "sg:city":"Bournemouth",
    "sg:classifiers":[
        {
            "category":"Professional",
            "subcategory":"Lawyer & Legal Services",
            "type":"Services"
        }
    ],
    "sg:phone":"+44 1202 422842",
    "sg:postcode":"BH6 3DA",
    "sg:province":"Dorset",
    "sg:tags":[
        "advice",
        "counselling"
    ],
    "wof:name":"Sue Squires",
    "wof:placetype":"venue"
},
  "geometry": {"coordinates":[-1.80755,50.72374],"type":"Point"}
}