{
  "type": "Feature",
  "properties": {
    "iso:country":"GB",
    "sg:address":"Daisy Bank Garage, Unit 3 Daisy Bank La",
    "sg:city":"Northwich",
    "sg:classifiers":[
        {
            "category":"Military Area",
            "subcategory":"Air Force Base",
            "type":"Public Place"
        }
    ],
    "sg:phone":"+44 1606 77701",
    "sg:postcode":"CW9 6AA",
    "sg:province":"Cheshire",
    "sg:tags":[
        "taxi",
        "hire",
        "private"
    ],
    "wof:name":"Anderton Travel Ltd",
    "wof:placetype":"venue"
},
  "geometry": {"coordinates":[-2.5271289349,53.327747345],"type":"Point"}
}