{
  "type": "Feature",
  "properties": {
    "iso:country":"GB",
    "sg:address":"Whitegate Farm, Salters Lode",
    "sg:city":"Downham Market",
    "sg:classifiers":[
        {
            "category":"Personal",
            "subcategory":"Skin Care",
            "type":"Services"
        },
        {
            "category":"Utilities",
            "subcategory":"Natural Gas",
            "type":"Services"
        }
    ],
    "sg:phone":"+44 1366 388056",
    "sg:postcode":"PE38 0AY",
    "sg:province":"Cambridgeshire",
    "sg:tags":[
        "petrol",
        "repair",
        "pump",
        "maintenance"
    ],
    "wof:name":"Fuel Pump Installations",
    "wof:placetype":"venue"
},
  "geometry": {"coordinates":[0.33813,52.590157],"type":"Point"}
}