{
  "type": "Feature",
  "properties": {
    "addr:full":"Unit 5 Carrwood Road, Sheepbridge Industrial Estate Chesterfield Derbyshire S41 9QB",
    "addr:housenumber":"unit 5;estate",
    "addr:postcode":"s41 9qb",
    "addr:street":"Carrwood Road Sheepbridge Industrial",
    "iso:country":"GB",
    "sg:address":"Unit 5 Carrwood Road, Sheepbridge Industrial Estate",
    "sg:city":"Chesterfield",
    "sg:classifiers":[
        {
            "category":"Retail",
            "subcategory":"Auto Repair",
            "type":"Services"
        }
    ],
    "sg:phone":"+44 1246 454486",
    "sg:postcode":"S41 9QB",
    "sg:province":"Derbyshire",
    "sg:tags":[
        "modification",
        "garage"
    ],
    "wof:name":"Phoenix Motor Co.",
    "wof:placetype":"venue"
},
  "geometry": {"coordinates":[-1.4623659849,53.2757263184],"type":"Point"}
}