{
  "type": "Feature",
  "properties": {
    "addr:full":", Rattery South Brent Devon TQ10 9LD",
    "addr:postcode":"tq10 9ld",
    "iso:country":"GB",
    "sg:address":", Rattery",
    "sg:city":"South Brent",
    "sg:classifiers":[
        {
            "category":"Government",
            "subcategory":"Post Office",
            "type":"Public Place"
        }
    ],
    "sg:phone":"+44 1364 643293",
    "sg:postcode":"TQ10 9LD",
    "sg:province":"Devon",
    "wof:name":"Rattery P.O",
    "wof:placetype":"venue"
},
  "geometry": {"coordinates":[-3.8213889599,50.4227714539],"type":"Point"}
}