{
  "type": "Feature",
  "properties": {
    "addr:full":"28 Cumberland Rd Bexhill On Sea East Sussex TN39 5BU",
    "addr:housenumber":"28",
    "addr:postcode":"tn39 5bu",
    "addr:street":"Cumberland Rd",
    "iso:country":"GB",
    "sg:address":"28 Cumberland Rd",
    "sg:city":"Bexhill On Sea",
    "sg:classifiers":[
        {
            "category":"Retail",
            "subcategory":"Storage",
            "type":"Services"
        }
    ],
    "sg:phone":"+44 1424 224289",
    "sg:postcode":"TN39 5BU",
    "sg:province":"East Sussex",
    "sg:tags":[
        "household",
        "removal"
    ],
    "wof:name":"John Wyatt",
    "wof:placetype":"venue"
},
  "geometry": {"coordinates":[0.468141,50.857784],"type":"Point"}
}