{
  "type": "Feature",
  "properties": {
    "addr:full":"8 Millfield Ho, Mill Wynd Haddington East Lothian EH41 4DB",
    "addr:housenumber":"8",
    "addr:postcode":"eh41 4db",
    "addr:street":"Millfield Ho Mill Wynd",
    "iso:country":"GB",
    "sg:address":"8 Millfield Ho, Mill Wynd",
    "sg:city":"Haddington",
    "sg:classifiers":[
        {
            "category":"Building & Trades",
            "subcategory":"Construction",
            "type":"Services"
        }
    ],
    "sg:postcode":"EH41 4DB",
    "sg:province":"East Lothian",
    "sg:tags":[
        "builder"
    ],
    "wof:name":"Millfield Construction Ltd",
    "wof:placetype":"venue"
},
  "geometry": {"coordinates":[-2.776574,55.955471],"type":"Point"}
}