{
  "type": "Feature",
  "properties": {
    "addr:full":"17 Belgrave Blvd Leicester Leicestershire LE4 2JD",
    "addr:housenumber":"17",
    "addr:postcode":"le4 2jd",
    "addr:street":"Belgrave Blvd",
    "iso:country":"GB",
    "sg:address":"17 Belgrave Blvd",
    "sg:city":"Leicester",
    "sg:classifiers":[
        {
            "category":"Food & Beverages",
            "subcategory":"Meat & Fish",
            "type":"Retail Goods"
        }
    ],
    "sg:phone":"+44 116 235 4675",
    "sg:postcode":"LE4 2JD",
    "sg:province":"Leicestershire",
    "sg:tags":[
        "chip"
    ],
    "wof:name":"The Belgrave Fish Bar",
    "wof:placetype":"venue"
},
  "geometry": {"coordinates":[-1.137962,52.666016],"type":"Point"}
}