{
  "type": "Feature",
  "properties": {
    "addr:full":"30 Leys Rd Torquay Devon TQ2 6ED",
    "addr:housenumber":"30",
    "addr:postcode":"tq2 6ed",
    "addr:street":"Leys Rd",
    "iso:country":"GB",
    "sg:address":"30 Leys Rd",
    "sg:city":"Torquay",
    "sg:classifiers":[
        {
            "category":"Building & Trades",
            "subcategory":"Construction",
            "type":"Services"
        }
    ],
    "sg:phone":"+44 1803 606143",
    "sg:postcode":"TQ2 6ED",
    "sg:province":"Devon",
    "sg:tags":[
        "decorator",
        "painter"
    ],
    "wof:name":"Brown & Spencer",
    "wof:placetype":"venue"
},
  "geometry": {"coordinates":[-3.552912,50.467632],"type":"Point"}
}