{
  "type": "Feature",
  "properties": {
    "addr:full":"108-110 John Street Market Bradford West Yorkshire BD1 3ST",
    "addr:housenumber":"108-110",
    "addr:postcode":"bd1 3st",
    "addr:street":"John Street;Bradford West",
    "iso:country":"GB",
    "sg:address":"108-110 John Street Market",
    "sg:city":"Bradford",
    "sg:classifiers":[
        {
            "category":"Shopping",
            "subcategory":"Clothing, Apparel, & Fashions",
            "type":"Retail Goods"
        }
    ],
    "sg:phone":"+44 1274 721801",
    "sg:postcode":"BD1 3ST",
    "sg:province":"West Yorkshire",
    "sg:tags":[
        "haberdasher"
    ],
    "wof:name":"Jack Smith",
    "wof:placetype":"venue"
},
  "geometry": {"coordinates":[-1.756979,53.79599],"type":"Point"}
}