{
  "type": "Feature",
  "properties": {
    "iso:country":"GB",
    "sg:address":"Brook Road",
    "sg:city":"Trowbridge",
    "sg:classifiers":[
        {
            "category":"Place Of Worship",
            "type":"Public Place"
        }
    ],
    "sg:phone":"+44 1225 777097",
    "sg:postcode":"BA14 9DL",
    "sg:province":"Wiltshire",
    "wof:name":"Church Of Jesus Christ Of Latter-Day Saints The Trowbridge",
    "wof:placetype":"venue"
},
  "geometry": {"coordinates":[-2.2226350307,51.3208351135],"type":"Point"}
}