{
  "type": "Feature",
  "properties": {
    "iso:country":"GB",
    "sg:address":"4 Fore Street",
    "sg:city":"Trowbridge",
    "sg:classifiers":[
        {
            "category":"Real Estate",
            "subcategory":"Real Estate Agent",
            "type":"Services"
        }
    ],
    "sg:phone":"+44 1225 754391",
    "sg:postcode":"BA14 8HD",
    "sg:province":"Wiltshire",
    "wof:name":"CONNELL ESTATE AGENTS",
    "wof:placetype":"venue"
},
  "geometry": {"coordinates":[-2.209891,51.321121],"type":"Point"}
}