{
  "type": "Feature",
  "properties": {
    "iso:country":"GB",
    "sg:address":"23 Medway Parade",
    "sg:city":"Greenford",
    "sg:classifiers":[
        {
            "category":"Sports & Exercise",
            "subcategory":"Playing Field",
            "type":"Entertainment"
        }
    ],
    "sg:phone":"+44 20 8998 3969",
    "sg:postcode":"UB6 8HN",
    "sg:province":"Greater London",
    "sg:tags":[
        "sanitary",
        "hygiene",
        "appliance"
    ],
    "wof:name":"Prestige Bathrooms",
    "wof:placetype":"venue"
},
  "geometry": {"coordinates":[-0.333405,51.534573],"type":"Point"}
}