{
  "type": "Feature",
  "properties": {
    "addr:full":"16 Berkshire Drive Exeter Devon EX4 1NF",
    "addr:housenumber":"16",
    "addr:postcode":"ex4 1nf",
    "addr:street":"Berkshire Drive",
    "iso:country":"GB",
    "sg:address":"16 Berkshire Drive",
    "sg:city":"Exeter",
    "sg:classifiers":[
        {
            "category":"Professional",
            "subcategory":"Engineering",
            "type":"Services"
        }
    ],
    "sg:phone":"+44 1392 491550",
    "sg:postcode":"EX4 1NF",
    "sg:province":"Devon",
    "sg:tags":[
        "gas",
        "engineer"
    ],
    "wof:name":"All Gas Services",
    "wof:placetype":"venue"
},
  "geometry": {"coordinates":[-3.556415081,50.7156600952],"type":"Point"}
}