{
  "type": "Feature",
  "properties": {
    "iso:country":"GB",
    "sg:address":"Saxon House, 17lewis Road",
    "sg:city":"Sutton",
    "sg:classifiers":[
        {
            "category":"Banks & Credit Unions",
            "subcategory":"Financial Services",
            "type":"Services"
        }
    ],
    "sg:phone":"+44 20 8661 9292",
    "sg:postcode":"SM1 4BR",
    "sg:province":"Surrey",
    "sg:tags":[
        "consultant"
    ],
    "wof:name":"Rodis Securities Ltd.",
    "wof:placetype":"venue"
},
  "geometry": {"coordinates":[-0.1975580007,51.3611907959],"type":"Point"}
}