{
  "type": "Feature",
  "properties": {
    "addr:full":"8-10 Blackwood Street, Barrhead Glasgow East Ayrshire G78 1JX",
    "addr:housenumber":"8-10",
    "addr:postcode":"g78 1jx",
    "addr:street":"Blackwood Street",
    "iso:country":"GB",
    "sg:address":"8-10 Blackwood Street, Barrhead",
    "sg:city":"Glasgow",
    "sg:classifiers":[
        {
            "category":"Food & Beverages",
            "subcategory":"Supermarket",
            "type":"Retail Goods"
        }
    ],
    "sg:phone":"+44 141 881 5900",
    "sg:postcode":"G78 1JX",
    "sg:province":"East Ayrshire",
    "wof:name":"R B Gardners",
    "wof:placetype":"venue"
},
  "geometry": {"coordinates":[-4.4015312195,55.7972869873],"type":"Point"}
}