{
  "type": "Feature",
  "properties": {
    "iso:country":"GB",
    "sg:address":"124 Hollingbury Park Ave",
    "sg:city":"Brighton",
    "sg:classifiers":[
        {
            "category":"Building & Trades",
            "subcategory":"Construction",
            "type":"Services"
        }
    ],
    "sg:phone":"+44 1273 505816",
    "sg:postcode":"BN1 7JP",
    "sg:province":"East Sussex",
    "sg:tags":[
        "builder"
    ],
    "wof:name":"Fiveways",
    "wof:placetype":"venue"
},
  "geometry": {"coordinates":[-0.134153,50.846409],"type":"Point"}
}