{
  "type": "Feature",
  "properties": {
    "iso:country":"GB",
    "sg:address":"16a Endell Street",
    "sg:city":"London",
    "sg:classifiers":[
        {
            "category":"Restaurant",
            "type":"Food & Drink"
        }
    ],
    "sg:phone":"+44 20 7379 5108",
    "sg:postcode":"WC2H 9BD",
    "sg:province":"Greater London",
    "sg:tags":[
        "italian"
    ],
    "wof:name":"la Quercia D'Oro",
    "wof:placetype":"venue"
},
  "geometry": {"coordinates":[-0.124239,51.514465],"type":"Point"}
}