{
  "type": "Feature",
  "properties": {
    "addr:full":"3 Cox Avenue Bournemouth Dorset BH9 3LY",
    "addr:housenumber":"3",
    "addr:postcode":"bh9 3ly",
    "addr:street":"Cox Avenue",
    "iso:country":"GB",
    "sg:address":"3 Cox Avenue",
    "sg:city":"Bournemouth",
    "sg:classifiers":[
        {
            "category":"Social Services",
            "subcategory":"Child Care",
            "type":"Services"
        }
    ],
    "sg:postcode":"BH9 3LY",
    "sg:province":"Dorset",
    "sg:tags":[
        "baby",
        "sitter"
    ],
    "wof:name":"Guardian Angels Baby Sitting Services",
    "wof:placetype":"venue"
},
  "geometry": {"coordinates":[-1.8668370247,50.7586860657],"type":"Point"}
}