{
  "type": "Feature",
  "properties": {
    "addr:full":"Unit 3 Abbey Trading Estate, Bell Green Lane London Greater London SE26 5TW",
    "addr:housenumber":"unit 3;estate",
    "addr:postcode":"se26 5tw",
    "addr:street":"Trading;Bell Green Lane",
    "iso:country":"GB",
    "sg:address":"Unit 3 Abbey Trading Estate, Bell Green Lane",
    "sg:city":"London",
    "sg:classifiers":[
        {
            "category":"Wholesale",
            "subcategory":"Vending Machines",
            "type":"Manufacturing & Wholesale Goods"
        }
    ],
    "sg:phone":"+44 20 8776 8688",
    "sg:postcode":"SE26 5TW",
    "sg:province":"Greater London",
    "wof:name":"Q Cup Drinks Service",
    "wof:placetype":"venue"
},
  "geometry": {"coordinates":[-0.037899,51.424557],"type":"Point"}
}