{
  "type": "Feature",
  "properties": {
    "addr:full":"50/51 Nechells Park Road Birmingham West Midlands B7 5PR",
    "addr:housenumber":"50 / 51",
    "addr:postcode":"b7 5pr",
    "addr:street":"Nechells Park Road",
    "iso:country":"GB",
    "sg:address":"50/51 Nechells Park Road",
    "sg:city":"Birmingham",
    "sg:classifiers":[
        {
            "category":"Home & Garden",
            "subcategory":"Home Furnishings",
            "type":"Retail Goods"
        },
        {
            "category":"Home & Garden",
            "subcategory":"Furniture",
            "type":"Retail Goods"
        }
    ],
    "sg:phone":"+44 121 327 0902",
    "sg:postcode":"B7 5PR",
    "sg:province":"West Midlands",
    "sg:tags":[
        "soft",
        "sale"
    ],
    "wof:name":"Bullivant S Drapery Stores Ltd.",
    "wof:placetype":"venue"
},
  "geometry": {"coordinates":[-1.8683960438,52.4978981018],"type":"Point"}
}