{
  "type": "Feature",
  "properties": {
    "iso:country":"GB",
    "sg:address":"Unit 2a, Riverside Business Park",
    "sg:city":"Northampton",
    "sg:classifiers":[
        {
            "category":"Autos & Motor Vehicles",
            "subcategory":"Automobile Sales",
            "type":"Retail Goods"
        }
    ],
    "sg:phone":"+44 1604 786000",
    "sg:postcode":"NN3 9HU",
    "sg:province":"Northamptonshire",
    "sg:tags":[
        "car"
    ],
    "wof:name":"Daewoo Motor Show",
    "wof:placetype":"venue"
},
  "geometry": {"coordinates":[-0.83981,52.241039],"type":"Point"}
}