{
  "type": "Feature",
  "properties": {
    "iso:country":"GB",
    "sg:address":"41 Bondgate Without",
    "sg:city":"Alnwick",
    "sg:classifiers":[
        {
            "category":"Home & Garden",
            "subcategory":"Home Furnishings",
            "type":"Retail Goods"
        }
    ],
    "sg:phone":"+44 1665 510025",
    "sg:postcode":"NE66 1PR",
    "sg:province":"Northumberland",
    "sg:tags":[
        "homefurnishings"
    ],
    "wof:name":"Harlay Design",
    "wof:placetype":"venue"
},
  "geometry": {"coordinates":[-1.702942,55.412178],"type":"Point"}
}