{
  "type": "Feature",
  "properties": {
    "addr:full":"32 High Street Market Harborough Leicestershire LE16 7NL",
    "addr:housenumber":"32",
    "addr:postcode":"le16 7nl",
    "addr:street":"High Street",
    "iso:country":"GB",
    "sg:address":"32 High Street",
    "sg:city":"Market Harborough",
    "sg:classifiers":[
        {
            "category":"Manufacturing",
            "subcategory":"Tools & Machinery",
            "type":"Manufacturing & Wholesale Goods"
        }
    ],
    "sg:phone":"+44 1858 467507",
    "sg:postcode":"LE16 7NL",
    "sg:province":"Leicestershire",
    "sg:tags":[
        "society",
        "friendly"
    ],
    "wof:name":"I M S Insurance Service",
    "wof:placetype":"venue"
},
  "geometry": {"coordinates":[-0.9221950173,52.4786567688],"type":"Point"}
}