{
  "type": "Feature",
  "properties": {
    "addr:full":"2 Bakers Lane Lichfield Staffordshire WS13 6NF",
    "addr:housenumber":"2",
    "addr:postcode":"ws13 6nf",
    "addr:street":"Bakers Lane",
    "iso:country":"GB",
    "sg:address":"2 Bakers Lane",
    "sg:city":"Lichfield",
    "sg:classifiers":[
        {
            "category":"Shopping",
            "subcategory":"Optician",
            "type":"Retail Goods"
        }
    ],
    "sg:phone":"+44 1543 252086",
    "sg:postcode":"WS13 6NF",
    "sg:province":"Staffordshire",
    "wof:name":"Dollond & Aitchison",
    "wof:placetype":"venue"
},
  "geometry": {"coordinates":[-1.8257410526,52.682975769],"type":"Point"}
}