{
  "type": "Feature",
  "properties": {
    "addr:full":"33 Butcher Row Salisbury Wiltshire SP1 1EP",
    "addr:housenumber":"33",
    "addr:postcode":"sp1 1ep",
    "addr:street":"Butcher Row",
    "iso:country":"GB",
    "sg:address":"33 Butcher Row",
    "sg:city":"Salisbury",
    "sg:classifiers":[
        {
            "category":"Shopping",
            "subcategory":"Comic Books",
            "type":"Retail Goods"
        }
    ],
    "sg:phone":"+44 1722 324875",
    "sg:postcode":"SP1 1EP",
    "sg:province":"Wiltshire",
    "sg:tags":[
        "jeweller"
    ],
    "wof:name":"Goldsmiths",
    "wof:placetype":"venue"
},
  "geometry": {"coordinates":[-1.795514,51.068764],"type":"Point"}
}