{
  "type": "Feature",
  "properties": {
    "addr:full":"4 Sandringham Place, Ashwood Park Stourbridge Staffordshire DY8 5HP",
    "addr:housenumber":"4",
    "addr:postcode":"dy8 5hp",
    "addr:street":"Sandringham Place",
    "iso:country":"GB",
    "sg:address":"4 Sandringham Place, Ashwood Park",
    "sg:city":"Stourbridge",
    "sg:classifiers":[
        {
            "category":"Shopping",
            "subcategory":"Baby Store",
            "type":"Retail Goods"
        }
    ],
    "sg:phone":"+44 1384 296415",
    "sg:postcode":"DY8 5HP",
    "sg:province":"Staffordshire",
    "sg:tags":[
        "babywear",
        "childrens"
    ],
    "wof:name":"Tots & Teens",
    "wof:placetype":"venue"
},
  "geometry": {"coordinates":[-2.168897,52.476974],"type":"Point"}
}