{
  "type": "Feature",
  "properties": {
    "addr:full":"175 Bow Road London Greater London E3 2SG",
    "addr:housenumber":"175",
    "addr:postcode":"e3 2sg",
    "addr:street":"Bow Road",
    "iso:country":"GB",
    "sg:address":"175 Bow Road",
    "sg:city":"London",
    "sg:classifiers":[
        {
            "category":"Professional",
            "subcategory":"Detective & Security Services",
            "type":"Services"
        }
    ],
    "sg:phone":"+44 20 8981 3269",
    "sg:postcode":"E3 2SG",
    "sg:province":"Greater London",
    "sg:tags":[
        "alarm",
        "burglar",
        "system"
    ],
    "wof:name":"HERRING READER SECURITY",
    "wof:placetype":"venue"
},
  "geometry": {"coordinates":[-0.0230889991,51.5275802612],"type":"Point"}
}