{
  "type": "Feature",
  "properties": {
    "iso:country":"GB",
    "sg:address":"Unit 41l Winpenny Road",
    "sg:city":"Newcastle",
    "sg:classifiers":[
        {
            "category":"Shopping",
            "subcategory":"Crafts & Fabrics",
            "type":"Retail Goods"
        }
    ],
    "sg:postcode":"ST5 7RH",
    "sg:province":"Staffordshire",
    "sg:tags":[
        "ceramic"
    ],
    "wof:name":"P & P China",
    "wof:placetype":"venue"
},
  "geometry": {"coordinates":[-2.239329,53.04734],"type":"Point"}
}