{
  "type": "Feature",
  "properties": {
    "addr:full":"29 Lynnwood Road, East Didsbury Manchester Greater Manchester M19 1RL",
    "addr:housenumber":"29",
    "addr:postcode":"m19 1rl",
    "addr:street":"Lynnwood Road",
    "iso:country":"GB",
    "sg:address":"29 Lynnwood Road, East Didsbury",
    "sg:city":"Manchester",
    "sg:classifiers":[
        {
            "category":"Building & Trades",
            "subcategory":"Construction",
            "type":"Services"
        }
    ],
    "sg:phone":"+44 161 432 9517",
    "sg:postcode":"M19 1RL",
    "sg:province":"Greater Manchester",
    "sg:tags":[
        "joiner",
        "carpenter"
    ],
    "wof:name":"Lynnwood Joinery",
    "wof:placetype":"venue"
},
  "geometry": {"coordinates":[-2.217,53.41264],"type":"Point"}
}