{
  "type": "Feature",
  "properties": {
    "addr:full":"Victoria Road Port Talbot Neath Port Talbot SA12 6QG",
    "addr:postcode":"sa12 6qg",
    "addr:street":"Victoria Road",
    "iso:country":"GB",
    "sg:address":"Victoria Road",
    "sg:city":"Port Talbot",
    "sg:classifiers":[
        {
            "category":"Travel",
            "subcategory":"Hotels & Motels",
            "type":"Entertainment"
        }
    ],
    "sg:phone":"+44 1639 871582",
    "sg:postcode":"SA12 6QG",
    "sg:province":"Neath Port Talbot",
    "wof:name":"Vivian Park Hotel Ltd",
    "wof:placetype":"venue"
},
  "geometry": {"coordinates":[-3.800124,51.592564],"type":"Point"}
}