{
  "type": "Feature",
  "properties": {
    "addr:full":"1 Mill Lane, Warmsworth Doncaster South Yorkshire DN4 9RG",
    "addr:housenumber":"1",
    "addr:postcode":"dn4 9rg",
    "addr:street":"Mill Lane",
    "iso:country":"GB",
    "sg:address":"1 Mill Lane, Warmsworth",
    "sg:city":"Doncaster",
    "sg:classifiers":[
        {
            "category":"Shopping",
            "subcategory":"News",
            "type":"Retail Goods"
        }
    ],
    "sg:phone":"+44 1302 857772",
    "sg:postcode":"DN4 9RG",
    "sg:province":"South Yorkshire",
    "sg:tags":[
        "newsagent"
    ],
    "wof:name":"FARMHOUSE FOOD & WINE",
    "wof:placetype":"venue"
},
  "geometry": {"coordinates":[-1.1831120253,53.4984474182],"type":"Point"}
}