{
  "type": "Feature",
  "properties": {
    "addr:full":"Park Hill Farm, Coxhoe Durham Durham DH6 4JP",
    "addr:postcode":"dh6 4jp",
    "addr:street":"Park Hill",
    "iso:country":"GB",
    "sg:address":"Park Hill Farm, Coxhoe",
    "sg:city":"Durham",
    "sg:classifiers":[
        {
            "category":"Farming",
            "subcategory":"Livestock Farm",
            "type":"Manufacturing & Wholesale Goods"
        }
    ],
    "sg:phone":"+44 191 377 0365",
    "sg:postcode":"DH6 4JP",
    "sg:province":"Durham",
    "sg:tags":[
        "others"
    ],
    "wof:name":"Robert Oxley",
    "wof:placetype":"venue"
},
  "geometry": {"coordinates":[-1.515199,54.725189],"type":"Point"}
}