{
  "type": "Feature",
  "properties": {
    "addr:full":"39 Beechtree Avenue Coventry Warwickshire CV4 9FE",
    "addr:housenumber":"39",
    "addr:postcode":"cv4 9fe",
    "addr:street":"Beechtree Avenue",
    "iso:country":"GB",
    "sg:address":"39 Beechtree Avenue",
    "sg:city":"Coventry",
    "sg:classifiers":[
        {
            "category":"Food & Beverages",
            "subcategory":"Meat & Fish",
            "type":"Retail Goods"
        }
    ],
    "sg:postcode":"CV4 9FE",
    "sg:province":"Warwickshire",
    "sg:tags":[
        "chip"
    ],
    "wof:name":"Beechtree Chip Shop",
    "wof:placetype":"venue"
},
  "geometry": {"coordinates":[-1.5658229589,52.4058227539],"type":"Point"}
}