{
  "type": "Feature",
  "properties": {
    "iso:country":"GB",
    "sg:address":"Weighbridge Office, A5 Watling St, Clifton Upon Dunsmore",
    "sg:city":"Rugby",
    "sg:classifiers":[
        {
            "category":"Building & Trades",
            "subcategory":"Construction",
            "type":"Services"
        }
    ],
    "sg:phone":"+44 1788 860066",
    "sg:postcode":"CV23 0AJ",
    "sg:province":"Northamptonshire",
    "sg:tags":[
        "valve"
    ],
    "wof:name":"E T Valve Supply Co Ltd",
    "wof:placetype":"venue"
},
  "geometry": {"coordinates":[-1.222132,52.382793],"type":"Point"}
}