{
  "type": "Feature",
  "properties": {
    "iso:country":"GB",
    "sg:address":"63 Jenner Cres",
    "sg:city":"Northampton",
    "sg:classifiers":[
        {
            "category":"Shopping",
            "subcategory":"Antiques",
            "type":"Retail Goods"
        }
    ],
    "sg:phone":"+44 1604 842705",
    "sg:postcode":"NN2 8NB",
    "sg:province":"Northamptonshire",
    "wof:name":"Peter Cooksley",
    "wof:placetype":"venue"
},
  "geometry": {"coordinates":[-0.9046999812,52.2716674805],"type":"Point"}
}