{
  "type": "Feature",
  "properties": {
    "iso:country":"GB",
    "sg:address":"73 Ferncroft Avenue, Eastcote",
    "sg:city":"Ruislip",
    "sg:classifiers":[
        {
            "category":"Professional",
            "subcategory":"Engineering",
            "type":"Services"
        }
    ],
    "sg:postcode":"HA4 9JE",
    "sg:province":"Greater London",
    "sg:tags":[
        "contractor",
        "electrical",
        "engineer"
    ],
    "wof:name":"A J M Electrical Contractor",
    "wof:placetype":"venue"
},
  "geometry": {"coordinates":[-0.396886,51.569988],"type":"Point"}
}