{
  "type": "Feature",
  "properties": {
    "iso:country":"GB",
    "sg:address":"Avondale Dr",
    "sg:city":"Hayes",
    "sg:classifiers":[
        {
            "category":"Health Services",
            "subcategory":"Clinic",
            "type":"Services"
        }
    ],
    "sg:phone":"+44 20 8573 2634",
    "sg:postcode":"UB3 3NR",
    "sg:province":"Greater London",
    "sg:tags":[
        "nh"
    ],
    "wof:name":"Minet Clinic",
    "wof:placetype":"venue"
},
  "geometry": {"coordinates":[-0.409322,51.511166],"type":"Point"}
}