{
  "type": "Feature",
  "properties": {
    "addr:full":"Greycaine Road Watford Hertfordshire WD2 4QA",
    "addr:postcode":"wd2 4qa",
    "addr:street":"Greycaine Road",
    "iso:country":"GB",
    "sg:address":"Greycaine Road",
    "sg:city":"Watford",
    "sg:classifiers":[
        {
            "category":"Wholesale",
            "subcategory":"Machinery & Supplies",
            "type":"Manufacturing & Wholesale Goods"
        }
    ],
    "sg:phone":"+44 1923 492000",
    "sg:postcode":"WD2 4QA",
    "sg:province":"Hertfordshire",
    "sg:tags":[
        "hydraulic"
    ],
    "wof:name":"Parker-Hannifin Plc",
    "wof:placetype":"venue"
},
  "geometry": {"coordinates":[-0.3881309927,51.6768302917],"type":"Point"}
}