{
  "type": "Feature",
  "properties": {
    "iso:country":"GB",
    "sg:address":"8 Buckminster Road",
    "sg:city":"Leicester",
    "sg:classifiers":[
        {
            "category":"Utilities",
            "type":"Services"
        }
    ],
    "sg:postcode":"LE3 9AR",
    "sg:province":"Leicestershire",
    "sg:tags":[
        "internet"
    ],
    "wof:name":"Grosvenor Computer Consultants Ltd.",
    "wof:placetype":"venue"
},
  "geometry": {"coordinates":[-1.1491960287,52.6445083618],"type":"Point"}
}