{
  "type": "Feature",
  "properties": {
    "addr:full":"The Cottage, Three Horseshoes Hereford Herefordshire HR2 9AS",
    "addr:postcode":"hr2 9as",
    "iso:country":"GB",
    "sg:address":"The Cottage, Three Horseshoes",
    "sg:city":"Hereford",
    "sg:classifiers":[
        {
            "category":"Professional",
            "subcategory":"Accounting & Tax Preparation",
            "type":"Services"
        }
    ],
    "sg:phone":"+44 1981 570790",
    "sg:postcode":"HR2 9AS",
    "sg:province":"Herefordshire",
    "sg:tags":[
        "accountant"
    ],
    "wof:name":"P & J Cowell",
    "wof:placetype":"venue"
},
  "geometry": {"coordinates":[-2.801839,52.035194],"type":"Point"}
}