{
  "type": "Feature",
  "properties": {
    "iso:country":"GB",
    "sg:address":"3 Links View",
    "sg:city":"Halesowen",
    "sg:classifiers":[
        {
            "category":"Wholesale",
            "subcategory":"Machinery & Supplies",
            "type":"Manufacturing & Wholesale Goods"
        }
    ],
    "sg:phone":"+44 121 602 1078",
    "sg:postcode":"B62 8SS",
    "sg:province":"West Midlands",
    "sg:tags":[
        "control",
        "instrument",
        "industrial",
        "-"
    ],
    "wof:name":"Uvex Ltd",
    "wof:placetype":"venue"
},
  "geometry": {"coordinates":[-2.03318,52.449432],"type":"Point"}
}