{
  "type": "Feature",
  "properties": {
    "addr:full":"82 Longmoor La Nottingham Derbyshire NG10 5JP",
    "addr:housenumber":"82",
    "addr:postcode":"ng10 5jp",
    "addr:street":"Longmoor La",
    "iso:country":"GB",
    "sg:address":"82 Longmoor La",
    "sg:city":"Nottingham",
    "sg:classifiers":[
        {
            "category":"Shopping",
            "subcategory":"Department Store",
            "type":"Retail Goods"
        }
    ],
    "sg:postcode":"NG10 5JP",
    "sg:province":"Derbyshire",
    "wof:name":"Longmoor Lane Off Licence",
    "wof:placetype":"venue"
},
  "geometry": {"coordinates":[-1.288999,52.918411],"type":"Point"}
}