{
  "type": "Feature",
  "properties": {
    "addr:full":"Benllech Tyn-y-gongl Isle of Anglesey LL74 8TL",
    "addr:postcode":"ll74 8tl",
    "iso:country":"GB",
    "sg:address":"Benllech",
    "sg:city":"Tyn-y-gongl",
    "sg:classifiers":[
        {
            "category":"Personal",
            "subcategory":"Beauty Salon",
            "type":"Services"
        },
        {
            "category":"Personal",
            "subcategory":"Barber",
            "type":"Services"
        }
    ],
    "sg:phone":"+44 1248 852676",
    "sg:postcode":"LL74 8TL",
    "sg:province":"Isle of Anglesey",
    "sg:tags":[
        "unisex",
        "hairdresser"
    ],
    "wof:name":"Nikki Hair Fashions",
    "wof:placetype":"venue"
},
  "geometry": {"coordinates":[-4.233452,53.321613],"type":"Point"}
}