{
  "type": "Feature",
  "properties": {
    "addr:full":"Edenthorpe, Grove Road Rotherham South Yorkshire S60 2ER",
    "addr:postcode":"s60 2er",
    "addr:street":"Edenthorpe Grove Road",
    "iso:country":"GB",
    "sg:address":"Edenthorpe, Grove Road",
    "sg:city":"Rotherham",
    "sg:classifiers":[
        {
            "category":"Professional",
            "subcategory":"Accounting & Tax Preparation",
            "type":"Services"
        }
    ],
    "sg:phone":"+44 1709 820360",
    "sg:postcode":"S60 2ER",
    "sg:province":"South Yorkshire",
    "sg:tags":[
        "accountant"
    ],
    "wof:name":"M A Jarvis & Co.",
    "wof:placetype":"venue"
},
  "geometry": {"coordinates":[-1.354243,53.429874],"type":"Point"}
}