{
  "type": "Feature",
  "properties": {
    "addr:full":"Unit 4b-5 Boundary Bank, Boundary Bank Lane Kendal Cumbria LA9 5RR",
    "addr:housenumber":"unit 4b-5",
    "addr:postcode":"la9 5rr",
    "addr:street":"Boundary Bank Boundary Bank Lane",
    "iso:country":"GB",
    "sg:address":"Unit 4b-5 Boundary Bank, Boundary Bank Lane",
    "sg:city":"Kendal",
    "sg:phone":"+44 1539 735300",
    "sg:postcode":"LA9 5RR",
    "sg:province":"Cumbria",
    "wof:name":"Gordon Engineering",
    "wof:placetype":"venue"
},
  "geometry": {"coordinates":[-2.7480840683,54.3240013123],"type":"Point"}
}