{
  "type": "Feature",
  "properties": {
    "addr:full":"2 Lendal York North Yorkshire YO1 8AA",
    "addr:housenumber":"2",
    "addr:postcode":"yo1 8aa",
    "addr:street":"Lendal",
    "iso:country":"GB",
    "sg:address":"2 Lendal",
    "sg:city":"York",
    "sg:classifiers":[
        {
            "category":"Shopping",
            "subcategory":"Comic Books",
            "type":"Retail Goods"
        }
    ],
    "sg:phone":"+44 1904 620006",
    "sg:postcode":"YO1 8AA",
    "sg:province":"North Yorkshire",
    "sg:tags":[
        "jeweller"
    ],
    "wof:name":"Topaz Antique Jewellers",
    "wof:placetype":"venue"
},
  "geometry": {"coordinates":[-1.086238,53.960587],"type":"Point"}
}