{
  "type": "Feature",
  "properties": {
    "addr:full":"Crews Hole Road Bristol City of Bristol BS5 8GG",
    "addr:postcode":"bs5 8gg",
    "addr:street":"Hole Road",
    "iso:country":"GB",
    "sg:address":"Crews Hole Road",
    "sg:city":"Bristol",
    "sg:classifiers":[
        {
            "category":"Health Services",
            "subcategory":"Nursing And Care Facility",
            "type":"Services"
        }
    ],
    "sg:phone":"+44 117 955 5758",
    "sg:postcode":"BS5 8GG",
    "sg:province":"City of Bristol",
    "sg:tags":[
        "home"
    ],
    "wof:name":"Riversway Nursing Home",
    "wof:placetype":"venue"
},
  "geometry": {"coordinates":[-2.535884,51.452961],"type":"Point"}
}