{
  "type": "Feature",
  "properties": {
    "iso:country":"GB",
    "sg:address":"Moorland Road",
    "sg:city":"Cardiff",
    "sg:classifiers":[
        {
            "category":"Social Services",
            "subcategory":"Adult Care",
            "type":"Services"
        },
        {
            "category":"Organizations",
            "subcategory":"Community Association",
            "type":"Services"
        }
    ],
    "sg:phone":"+44 29 2046 2594",
    "sg:postcode":"CF24 2LG",
    "sg:province":"Cardiff",
    "sg:tags":[
        "associations",
        "centre",
        "housing",
        "co-operatives",
        "trust",
        "day",
        "societies"
    ],
    "wof:name":"MOORLAND ROAD DAY CENTRE",
    "wof:placetype":"venue"
},
  "geometry": {"coordinates":[-3.1481039524,51.4888534546],"type":"Point"}
}