{
  "type": "Feature",
  "properties": {
    "addr:full":"11 St Mary's Street Newport Shropshire TF10 7AF",
    "addr:housenumber":"11",
    "addr:postcode":"tf10 7af",
    "addr:street":"St Mary'S Street",
    "iso:country":"GB",
    "sg:address":"11 St Mary's Street",
    "sg:city":"Newport",
    "sg:classifiers":[
        {
            "category":"Shopping",
            "subcategory":"Clothing, Apparel, & Fashions",
            "type":"Retail Goods"
        }
    ],
    "sg:phone":"+44 1952 814121",
    "sg:postcode":"TF10 7AF",
    "sg:province":"Shropshire",
    "sg:tags":[
        "lingerie",
        "hosiery"
    ],
    "wof:name":"Cheryls",
    "wof:placetype":"venue"
},
  "geometry": {"coordinates":[-2.37828,52.769138],"type":"Point"}
}