{
  "type": "Feature",
  "properties": {
    "iso:country":"GB",
    "sg:address":"Membury Road",
    "sg:city":"Axminster",
    "sg:classifiers":[
        {
            "category":"Farming",
            "subcategory":"Livestock Farm",
            "type":"Manufacturing & Wholesale Goods"
        }
    ],
    "sg:postcode":"EX13 7JG",
    "sg:province":"Devon",
    "sg:tags":[
        "others"
    ],
    "wof:name":"Michael J Rowe",
    "wof:placetype":"venue"
},
  "geometry": {"coordinates":[-3.028536,50.821358],"type":"Point"}
}