{
  "type": "Feature",
  "properties": {
    "addr:full":"Unit 1c Mill Green Industrial Es Haywards Heath East Sussex RH16 1XQ",
    "addr:housenumber":"unit 1c",
    "addr:postcode":"rh16 1xq",
    "addr:street":"Mill Green",
    "iso:country":"GB",
    "sg:address":"Unit 1c Mill Green Industrial Es",
    "sg:city":"Haywards Heath",
    "sg:classifiers":[
        {
            "category":"Manufacturing",
            "subcategory":"Metals",
            "type":"Manufacturing & Wholesale Goods"
        },
        {
            "category":"Building & Trades",
            "subcategory":"Cleaning & Sanitation",
            "type":"Services"
        }
    ],
    "sg:phone":"+44 1444 458855",
    "sg:postcode":"RH16 1XQ",
    "sg:province":"East Sussex",
    "sg:tags":[
        "fabricator",
        "aluminium",
        "door",
        "manufacturer"
    ],
    "sg:website":"http://www.burfield.co.uk",
    "wof:name":"Burfield Ltd",
    "wof:placetype":"venue"
},
  "geometry": {"coordinates":[-0.1020469964,50.9966583252],"type":"Point"}
}