{
  "type": "Feature",
  "properties": {
    "addr:full":"16 Windlesham Road Shoreham-by-sea West Sussex BN43 5AE",
    "addr:housenumber":"16",
    "addr:postcode":"bn43 5ae",
    "addr:street":"Windlesham Road",
    "iso:country":"GB",
    "sg:address":"16 Windlesham Road",
    "sg:city":"Shoreham-by-sea",
    "sg:classifiers":[
        {
            "category":"Building & Trades",
            "subcategory":"Landscaping Services",
            "type":"Services"
        }
    ],
    "sg:postcode":"BN43 5AE",
    "sg:province":"West Sussex",
    "sg:tags":[
        "gardening"
    ],
    "wof:name":"Garden & Homecraft",
    "wof:placetype":"venue"
},
  "geometry": {"coordinates":[-0.273111,50.839188],"type":"Point"}
}