{
  "type": "Feature",
  "properties": {
    "addr:full":"Unit 5 & 8 Brasenose Industrial Estate, St Johns Rd Bootle Merseyside L20 8BH",
    "addr:housenumber":"unit 5 & 8",
    "addr:postcode":"l20 8bh",
    "addr:street":"Brasenose Industrial Estate St Johns Rd",
    "iso:country":"GB",
    "sg:address":"Unit 5 & 8 Brasenose Industrial Estate, St Johns Rd",
    "sg:city":"Bootle",
    "sg:classifiers":[
        {
            "category":"Autos & Motor Vehicles",
            "subcategory":"Boat Sales",
            "type":"Retail Goods"
        },
        {
            "category":"Retail",
            "subcategory":"Auto Repair",
            "type":"Services"
        }
    ],
    "sg:phone":"+44 151 933 9983",
    "sg:postcode":"L20 8BH",
    "sg:province":"Merseyside",
    "sg:tags":[
        "engine",
        "car",
        "rebuilders",
        "specialist"
    ],
    "wof:name":"Regal Motors",
    "wof:placetype":"venue"
},
  "geometry": {"coordinates":[-2.99174,53.43956],"type":"Point"}
}