{
  "type": "Feature",
  "properties": {
    "addr:full":"29 Greetlands Road Sunderland Tyne and Wear SR2 9EB",
    "addr:housenumber":"29",
    "addr:postcode":"sr2 9eb",
    "addr:street":"Greetlands Road",
    "iso:country":"GB",
    "sg:address":"29 Greetlands Road",
    "sg:city":"Sunderland",
    "sg:classifiers":[
        {
            "category":"Professional",
            "subcategory":"Engineering",
            "type":"Services"
        }
    ],
    "sg:postcode":"SR2 9EB",
    "sg:province":"Tyne and Wear",
    "sg:tags":[
        "contractor",
        "electrical",
        "engineer"
    ],
    "wof:name":"Gerard Harrison",
    "wof:placetype":"venue"
},
  "geometry": {"coordinates":[-1.3870279789,54.8875274658],"type":"Point"}
}