{
  "type": "Feature",
  "properties": {
    "addr:full":"262 Nithsdale Road Glasgow Glasgow City G41 5AN",
    "addr:housenumber":"262",
    "addr:postcode":"g41 5an",
    "addr:street":"Nithsdale Road",
    "iso:country":"GB",
    "sg:address":"262 Nithsdale Road",
    "sg:city":"Glasgow",
    "sg:classifiers":[
        {
            "category":"Health Services",
            "subcategory":"Nursing And Care Facility",
            "type":"Services"
        },
        {
            "category":"Organizations",
            "subcategory":"Community Association",
            "type":"Services"
        }
    ],
    "sg:phone":"+44 141 427 2362",
    "sg:postcode":"G41 5AN",
    "sg:province":"Glasgow City",
    "sg:tags":[
        "residential",
        "housing",
        "society"
    ],
    "wof:name":"Abbeyfield Glasgow Society Ltd.",
    "wof:placetype":"venue"
},
  "geometry": {"coordinates":[-4.30492,55.844818],"type":"Point"}
}