{
  "type": "Feature",
  "properties": {
    "addr:full":"9 Hurricane Way Norwich Norfolk NR6 6EZ",
    "addr:housenumber":"9",
    "addr:postcode":"nr6 6ez",
    "addr:street":"Hurricane Way",
    "iso:country":"GB",
    "sg:address":"9 Hurricane Way",
    "sg:city":"Norwich",
    "sg:classifiers":[
        {
            "category":"Wholesale",
            "subcategory":"Furniture",
            "type":"Manufacturing & Wholesale Goods"
        },
        {
            "category":"Wholesale",
            "subcategory":"Home Furnishings",
            "type":"Manufacturing & Wholesale Goods"
        }
    ],
    "sg:phone":"+44 1603 400126",
    "sg:postcode":"NR6 6EZ",
    "sg:province":"Norfolk",
    "sg:tags":[
        "shop",
        "installers",
        "fitting",
        "fixture"
    ],
    "wof:name":"Profile Technical Engineering",
    "wof:placetype":"venue"
},
  "geometry": {"coordinates":[1.288685,52.668171],"type":"Point"}
}