{
  "type": "Feature",
  "properties": {
    "addr:full":"Brookside Avenue, Brookside Telford Shropshire TF3 1LB",
    "addr:postcode":"tf3 1lb",
    "addr:street":"Brookside Avenue",
    "iso:country":"GB",
    "sg:address":"Brookside Avenue, Brookside",
    "sg:city":"Telford",
    "sg:classifiers":[
        {
            "category":"Education",
            "subcategory":"Special Training",
            "type":"Public Place"
        }
    ],
    "sg:phone":"+44 1952 417010",
    "sg:postcode":"TF3 1LB",
    "sg:province":"Shropshire",
    "sg:tags":[
        "school"
    ],
    "wof:name":"The Bridge School",
    "wof:placetype":"venue"
},
  "geometry": {"coordinates":[-2.449723,52.648273],"type":"Point"}
}