{
  "type": "Feature",
  "properties": {
    "addr:full":"31 Hoop Lane London Greater London NW11 8BS",
    "addr:housenumber":"31",
    "addr:postcode":"nw11 8bs",
    "addr:street":"Hoop Lane",
    "iso:country":"GB",
    "sg:address":"31 Hoop Lane",
    "sg:city":"London",
    "sg:classifiers":[
        {
            "category":"Farming",
            "subcategory":"Nursery",
            "type":"Manufacturing & Wholesale Goods"
        }
    ],
    "sg:phone":"+44 20 8209 0813",
    "sg:postcode":"NW11 8BS",
    "sg:province":"Greater London",
    "sg:tags":[
        "creche"
    ],
    "wof:name":"Hoop Lane Montessori School",
    "wof:placetype":"venue"
},
  "geometry": {"coordinates":[-0.197575,51.575436],"type":"Point"}
}