{
  "type": "Feature",
  "properties": {
    "addr:full":"65 East Barnet Rd, New Barnet Barnet Hertfordshire EN4 8RN",
    "addr:housenumber":"65",
    "addr:postcode":"en4 8rn",
    "addr:street":"East Barnet Rd",
    "iso:country":"GB",
    "sg:address":"65 East Barnet Rd, New Barnet",
    "sg:city":"Barnet",
    "sg:classifiers":[
        {
            "category":"Autos & Motor Vehicles",
            "subcategory":"Fuel & Gas Station",
            "type":"Retail Goods"
        }
    ],
    "sg:phone":"+44 20 8275 5850",
    "sg:postcode":"EN4 8RN",
    "sg:province":"Hertfordshire",
    "sg:tags":[
        "petrol",
        "filling"
    ],
    "wof:name":"Total Convenience Stores",
    "wof:placetype":"venue"
},
  "geometry": {"coordinates":[-0.170314,51.649471],"type":"Point"}
}