{
  "type": "Feature",
  "properties": {
    "addr:full":"127 Portland Road, Wyke Regis Weymouth Dorset DT4 9BQ",
    "addr:housenumber":"127",
    "addr:postcode":"dt4 9bq",
    "addr:street":"Portland Road",
    "iso:country":"GB",
    "sg:address":"127 Portland Road, Wyke Regis",
    "sg:city":"Weymouth",
    "sg:classifiers":[
        {
            "category":"Building & Trades",
            "subcategory":"Construction",
            "type":"Services"
        }
    ],
    "sg:phone":"+44 1305 779456",
    "sg:postcode":"DT4 9BQ",
    "sg:province":"Dorset",
    "sg:tags":[
        "dry",
        "lining",
        "plasterers",
        "screeders"
    ],
    "wof:name":"John Mark Entwistle",
    "wof:placetype":"venue"
},
  "geometry": {"coordinates":[-2.4736759663,50.5910682678],"type":"Point"}
}