{
  "type": "Feature",
  "properties": {
    "iso:country":"GB",
    "sg:address":"The Nut, Coombe Rd",
    "sg:city":"Dorchester",
    "sg:classifiers":[
        {
            "category":"Wholesale",
            "subcategory":"Construction Materials",
            "type":"Manufacturing & Wholesale Goods"
        }
    ],
    "sg:phone":"+44 1305 889324",
    "sg:postcode":"DT2 9HD",
    "sg:province":"Dorset",
    "sg:tags":[
        "sawdust",
        "sawmills",
        "shaving"
    ],
    "wof:name":"Losconbe Timber (Mobile)",
    "wof:placetype":"venue"
},
  "geometry": {"coordinates":[-2.54713,50.703999],"type":"Point"}
}