{
  "type": "Feature",
  "properties": {
    "addr:full":"26-29 Stanley Gardens London Greater London W11 2NQ",
    "addr:housenumber":"26-29",
    "addr:postcode":"w11 2nq",
    "addr:street":"Stanley Gardens",
    "iso:country":"GB",
    "sg:address":"26-29 Stanley Gardens",
    "sg:city":"London",
    "sg:classifiers":[
        {
            "category":"Social Services",
            "subcategory":"Adult Care",
            "type":"Services"
        },
        {
            "category":"Social Services",
            "subcategory":"Retirement Home",
            "type":"Services"
        }
    ],
    "sg:phone":"+44 20 7727 1232",
    "sg:postcode":"W11 2NQ",
    "sg:province":"Greater London",
    "sg:tags":[
        "accomodation",
        "housing",
        "sheltered"
    ],
    "wof:name":"Women's Pioneer Housing",
    "wof:placetype":"venue"
},
  "geometry": {"coordinates":[-0.2038,51.512127],"type":"Point"}
}