{
  "type": "Feature",
  "properties": {
    "addr:full":"5 Rodney Place Bristol City of Bristol BS8 4HY",
    "addr:housenumber":"5",
    "addr:postcode":"bs8 4hy",
    "addr:street":"Rodney Place",
    "iso:country":"GB",
    "sg:address":"5 Rodney Place",
    "sg:city":"Bristol",
    "sg:classifiers":[
        {
            "category":"Professional",
            "subcategory":"Lawyer & Legal Services",
            "type":"Services"
        }
    ],
    "sg:phone":"+44 117 973 2950",
    "sg:postcode":"BS8 4HY",
    "sg:province":"City of Bristol",
    "sg:tags":[
        "solicitor"
    ],
    "wof:name":"Williams Mann",
    "wof:placetype":"venue"
},
  "geometry": {"coordinates":[-2.619958,51.455627],"type":"Point"}
}