{
  "type": "Feature",
  "properties": {
    "addr:full":"Lombard St Petworth West Sussex GU28 0AH",
    "addr:postcode":"gu28 0ah",
    "addr:street":"Lombard St",
    "iso:country":"GB",
    "sg:address":"Lombard St",
    "sg:city":"Petworth",
    "sg:classifiers":[
        {
            "category":"Shopping",
            "subcategory":"Antiques",
            "type":"Retail Goods"
        },
        {
            "category":"Shopping",
            "subcategory":"Used Merchandise",
            "type":"Retail Goods"
        }
    ],
    "sg:postcode":"GU28 0AH",
    "sg:province":"West Sussex",
    "sg:tags":[
        "shop",
        "second-hand"
    ],
    "wof:name":"Embling-Evans,Kevin,",
    "wof:placetype":"venue"
},
  "geometry": {"coordinates":[-0.609775,50.986961],"type":"Point"}
}