{
  "type": "Feature",
  "properties": {
    "addr:full":"Richmond Road, Stechford Birmingham West Midlands B33 8TN",
    "addr:postcode":"b33 8tn",
    "addr:street":"Richmond Road",
    "iso:country":"GB",
    "sg:address":"Richmond Road, Stechford",
    "sg:city":"Birmingham",
    "sg:classifiers":[
        {
            "category":"Retail",
            "subcategory":"Event Space",
            "type":"Services"
        }
    ],
    "sg:phone":"+44 121 783 2900",
    "sg:postcode":"B33 8TN",
    "sg:province":"West Midlands",
    "sg:tags":[
        "function",
        "room"
    ],
    "wof:name":"The Stechford Masonic Hall Co. Ltd.",
    "wof:placetype":"venue"
},
  "geometry": {"coordinates":[-1.809209,52.4823],"type":"Point"}
}