{
  "type": "Feature",
  "properties": {
    "addr:full":"186 South Street Liverpool Merseyside L8 3TW",
    "addr:housenumber":"186",
    "addr:postcode":"l8 3tw",
    "addr:street":"South Street",
    "iso:country":"GB",
    "sg:address":"186 South Street",
    "sg:city":"Liverpool",
    "sg:classifiers":[
        {
            "category":"Retail",
            "subcategory":"Auto Repair",
            "type":"Services"
        }
    ],
    "sg:postcode":"L8 3TW",
    "sg:province":"Merseyside",
    "sg:tags":[
        "body",
        "car",
        "related",
        "garage"
    ],
    "wof:name":"SOUTH MOTORS",
    "wof:placetype":"venue"
},
  "geometry": {"coordinates":[-2.956128,53.389381],"type":"Point"}
}