{
  "type": "Feature",
  "properties": {
    "addr:full":"85 Church Street London Greater London NW8 8EU",
    "addr:housenumber":"85",
    "addr:postcode":"nw8 8eu",
    "addr:street":"Church Street",
    "iso:country":"GB",
    "sg:address":"85 Church Street",
    "sg:city":"London",
    "sg:classifiers":[
        {
            "category":"Shopping",
            "subcategory":"Pharmacy",
            "type":"Retail Goods"
        }
    ],
    "sg:phone":"+44 20 7723 1944",
    "sg:postcode":"NW8 8EU",
    "sg:province":"Greater London",
    "sg:tags":[
        "pharmacist",
        "chemist"
    ],
    "wof:name":"Mornicrest Ltd.",
    "wof:placetype":"venue"
},
  "geometry": {"coordinates":[-0.1707679927,51.5229072571],"type":"Point"}
}