{
  "type": "Feature",
  "properties": {
    "addr:full":"Garbetts, 42 Gregory Ave Ryde Isle of Wight PO33 1PZ",
    "addr:housenumber":"42",
    "addr:postcode":"po33 1pz",
    "addr:street":"Garbetts;Gregory Ave",
    "iso:country":"GB",
    "sg:address":"Garbetts, 42 Gregory Ave",
    "sg:city":"Ryde",
    "sg:classifiers":[
        {
            "category":"Professional",
            "subcategory":"Accounting & Tax Preparation",
            "type":"Services"
        }
    ],
    "sg:postcode":"PO33 1PZ",
    "sg:province":"Isle of Wight",
    "sg:tags":[
        "accountant"
    ],
    "wof:name":"Garbetts Ltd",
    "wof:placetype":"venue"
},
  "geometry": {"coordinates":[-1.1255099773,50.7160797119],"type":"Point"}
}