{
  "type": "Feature",
  "properties": {
    "addr:full":"19 Packmores Road London Greater London SE9 2NB",
    "addr:housenumber":"19",
    "addr:postcode":"se9 2nb",
    "addr:street":"Packmores Road",
    "iso:country":"GB",
    "sg:address":"19 Packmores Road",
    "sg:city":"London",
    "sg:classifiers":[
        {
            "category":"Professional",
            "subcategory":"Accounting & Tax Preparation",
            "type":"Services"
        }
    ],
    "sg:postcode":"SE9 2NB",
    "sg:province":"Greater London",
    "sg:tags":[
        "accountant"
    ],
    "wof:name":"G M C Accountancy Services",
    "wof:placetype":"venue"
},
  "geometry": {"coordinates":[0.085024,51.451855],"type":"Point"}
}