{
  "type": "Feature",
  "properties": {
    "addr:full":"203 Kilburn High Road Kilburn Greater London NW6 7HY",
    "addr:housenumber":"203",
    "addr:postcode":"nw6 7hy",
    "addr:street":"Kilburn High Road",
    "iso:country":"GB",
    "sg:address":"203 Kilburn High Road",
    "sg:city":"Kilburn",
    "sg:classifiers":[
        {
            "category":"Professional",
            "subcategory":"Lawyer & Legal Services",
            "type":"Services"
        }
    ],
    "sg:phone":"+44 20 7328 4357",
    "sg:postcode":"NW6 7HY",
    "sg:province":"Greater London",
    "sg:tags":[
        "solicitor"
    ],
    "wof:name":"Jack Bernstein",
    "wof:placetype":"venue"
},
  "geometry": {"coordinates":[-0.197956,51.541691],"type":"Point"}
}