{
  "type": "Feature",
  "properties": {
    "addr:full":"Clover Street Rochdale Lancashire OL12 6TP",
    "addr:postcode":"ol12 6tp",
    "addr:street":"Clover Street",
    "iso:country":"GB",
    "sg:address":"Clover Street",
    "sg:city":"Rochdale",
    "sg:classifiers":[
        {
            "category":"Place Of Worship",
            "type":"Public Place"
        },
        {
            "category":"Organizations",
            "subcategory":"Non-profit Organization",
            "type":"Services"
        }
    ],
    "sg:phone":"+44 1706 648461",
    "sg:postcode":"OL12 6TP",
    "sg:province":"Lancashire",
    "sg:tags":[
        "charitable",
        "organisation",
        "charity"
    ],
    "wof:name":"Unitarian Church",
    "wof:placetype":"venue"
},
  "geometry": {"coordinates":[-2.1625189781,53.6187133789],"type":"Point"}
}