{
  "type": "Feature",
  "properties": {
    "iso:country":"GB",
    "sg:address":"22a Westway",
    "sg:city":"Caterham",
    "sg:classifiers":[
        {
            "category":"Building & Trades",
            "subcategory":"Landscaping Services",
            "type":"Services"
        }
    ],
    "sg:phone":"+44 1883 347988",
    "sg:postcode":"CR3 5TP",
    "sg:province":"Surrey",
    "sg:tags":[
        "gardening"
    ],
    "wof:name":"Swift Construction",
    "wof:placetype":"venue"
},
  "geometry": {"coordinates":[-0.096088,51.287907],"type":"Point"}
}