{
  "type": "Feature",
  "properties": {
    "addr:full":"3 Burns Drive Wemyss Bay Inverclyde PA18 6BY",
    "addr:housenumber":"3",
    "addr:postcode":"pa18 6by",
    "addr:street":"Burns Drive Wemyss Bay",
    "iso:country":"GB",
    "sg:address":"3 Burns Drive",
    "sg:city":"Wemyss Bay",
    "sg:classifiers":[
        {
            "category":"Home & Garden",
            "subcategory":"Carpets & Floor Coverings",
            "type":"Retail Goods"
        }
    ],
    "sg:postcode":"PA18 6BY",
    "sg:province":"Inverclyde",
    "sg:tags":[
        "cleaner",
        "upholstery"
    ],
    "wof:name":"Rainbow International",
    "wof:placetype":"venue"
},
  "geometry": {"coordinates":[-4.8885188103,55.8913002014],"type":"Point"}
}