{
  "type": "Feature",
  "properties": {
    "addr:full":"44 Bridge End London Greater London E17 4ES",
    "addr:housenumber":"44",
    "addr:postcode":"e17 4es",
    "addr:street":"Bridge End",
    "iso:country":"GB",
    "sg:address":"44 Bridge End",
    "sg:city":"London",
    "sg:classifiers":[
        {
            "category":"Arts & Performance",
            "subcategory":"Music",
            "type":"Entertainment"
        }
    ],
    "sg:phone":"+44 20 8527 8891",
    "sg:postcode":"E17 4ES",
    "sg:province":"Greater London",
    "sg:tags":[
        "mobile",
        "disco"
    ],
    "wof:name":"Razzamatazz",
    "wof:placetype":"venue"
},
  "geometry": {"coordinates":[-0.005676,51.598843],"type":"Point"}
}