{
  "type": "Feature",
  "properties": {
    "addr:full":"2 Glamorgan Street Cardiff Cardiff CF5 1QS",
    "addr:housenumber":"2",
    "addr:postcode":"cf5 1qs",
    "addr:street":"Glamorgan Street",
    "iso:country":"GB",
    "sg:address":"2 Glamorgan Street",
    "sg:city":"Cardiff",
    "sg:classifiers":[
        {
            "category":"Personal",
            "subcategory":"Beauty Salon",
            "type":"Services"
        }
    ],
    "sg:phone":"+44 29 2023 0472",
    "sg:postcode":"CF5 1QS",
    "sg:province":"Cardiff",
    "sg:tags":[
        "ladies",
        "lady",
        "hairdresser"
    ],
    "wof:name":"Cut & Curl",
    "wof:placetype":"venue"
},
  "geometry": {"coordinates":[-3.2050390244,51.4827346802],"type":"Point"}
}