{
  "type": "Feature",
  "properties": {
    "addr:full":"64 Cleveleys Ave Thornton-cleveleys Lancashire FY5 2DJ",
    "addr:housenumber":"64",
    "addr:postcode":"fy5 2dj",
    "addr:street":"Cleveleys Ave",
    "iso:country":"GB",
    "sg:address":"64 Cleveleys Ave",
    "sg:city":"Thornton-cleveleys",
    "sg:classifiers":[
        {
            "category":"Professional",
            "subcategory":"Management & Consulting",
            "type":"Services"
        }
    ],
    "sg:postcode":"FY5 2DJ",
    "sg:province":"Lancashire",
    "sg:tags":[
        "fire",
        "consultant",
        "protection"
    ],
    "wof:name":"Crowe,Graham,",
    "wof:placetype":"venue"
},
  "geometry": {"coordinates":[-3.037008,53.881611],"type":"Point"}
}