{
  "type": "Feature",
  "properties": {
    "addr:full":"Park Corner Farm Upminster Essex RM14 2XU",
    "addr:postcode":"rm14 2xu",
    "addr:street":"Upminster",
    "iso:country":"GB",
    "sg:address":"Park Corner Farm",
    "sg:city":"Upminster",
    "sg:classifiers":[
        {
            "category":"Building & Trades",
            "subcategory":"Construction",
            "type":"Services"
        }
    ],
    "sg:phone":"+44 1708 640640",
    "sg:postcode":"RM14 2XU",
    "sg:province":"Essex",
    "sg:tags":[
        "glazier"
    ],
    "wof:name":"Graham Samuel Harris Ltd.",
    "wof:placetype":"venue"
},
  "geometry": {"coordinates":[0.2492599934,51.5563392639],"type":"Point"}
}