{
  "type": "Feature",
  "properties": {
    "iso:country":"GB",
    "sg:address":"14 Westgate",
    "sg:city":"Skelmersdale",
    "sg:classifiers":[
        {
            "category":"Utilities",
            "subcategory":"Telephone",
            "type":"Services"
        }
    ],
    "sg:phone":"+44 1695 557788",
    "sg:postcode":"WN8 8LP",
    "sg:province":"Lancashire",
    "sg:tags":[
        "telecommunication"
    ],
    "wof:name":"Duct Line Systems Ltd",
    "wof:placetype":"venue"
},
  "geometry": {"coordinates":[-2.8046250343,53.5460395813],"type":"Point"}
}