{
  "type": "Feature",
  "properties": {
    "iso:country":"GB",
    "sg:address":"Manston Lodge, Hampstead Drive, Great Moor",
    "sg:city":"Stockport",
    "sg:classifiers":[
        {
            "category":"Organizations",
            "subcategory":"Community Association",
            "type":"Services"
        }
    ],
    "sg:phone":"+44 161 456 3186",
    "sg:postcode":"SK2 7QL",
    "sg:province":"Cheshire",
    "sg:tags":[
        "co-operatives",
        "society",
        "housing",
        "trust"
    ],
    "wof:name":"Johnnie Johnson Housing Trust Ltd",
    "wof:placetype":"venue"
},
  "geometry": {"coordinates":[-2.13625,53.391769],"type":"Point"}
}