{
  "type": "Feature",
  "properties": {
    "iso:country":"GB",
    "sg:address":"Harby Lodge, 13 Pelham Rd, Sherwood Rise",
    "sg:city":"Nottingham",
    "sg:classifiers":[
        {
            "category":"Organizations",
            "subcategory":"Non-profit Organization",
            "type":"Services"
        }
    ],
    "sg:phone":"+44 115 993 2800",
    "sg:postcode":"NG5 1AP",
    "sg:province":"Nottinghamshire",
    "sg:tags":[
        "organisation",
        "voluntary",
        "charity"
    ],
    "wof:name":"Macedon",
    "wof:placetype":"venue"
},
  "geometry": {"coordinates":[-1.158914,52.971554],"type":"Point"}
}