{
  "type": "Feature",
  "properties": {
    "iso:country":"GB",
    "sg:address":"Mersey House, 220 Stockport Road, Cheadle Heath",
    "sg:city":"Stockport",
    "sg:classifiers":[
        {
            "category":"Wholesale",
            "subcategory":"Electrical",
            "type":"Manufacturing & Wholesale Goods"
        }
    ],
    "sg:phone":"+44 161 428 9225",
    "sg:postcode":"SK3 0LX",
    "sg:province":"Cheshire",
    "sg:tags":[
        "equipment",
        "refrigeration"
    ],
    "wof:name":"Norpe U K Ltd.",
    "wof:placetype":"venue"
},
  "geometry": {"coordinates":[-2.192306,53.401558],"type":"Point"}
}