{
  "type": "Feature",
  "properties": {
    "addr:full":"37-38 St Marys St Preston Lancashire PR1 5LN",
    "addr:housenumber":"37-38",
    "addr:postcode":"pr1 5ln",
    "addr:street":"St Marys St",
    "iso:country":"GB",
    "sg:address":"37-38 St Marys St",
    "sg:city":"Preston",
    "sg:classifiers":[
        {
            "category":"Professional",
            "subcategory":"Management & Consulting",
            "type":"Services"
        },
        {
            "category":"Education",
            "subcategory":"Special Training",
            "type":"Public Place"
        }
    ],
    "sg:phone":"+44 1772 905970",
    "sg:postcode":"PR1 5LN",
    "sg:province":"Lancashire",
    "sg:tags":[
        "consultant",
        "product",
        "centre"
    ],
    "wof:name":"A A I Training (U K) Ltd",
    "wof:placetype":"venue"
},
  "geometry": {"coordinates":[-2.685821,53.76144],"type":"Point"}
}