{
  "type": "Feature",
  "properties": {
    "iso:country":"GB",
    "sg:address":"Milburn Ho, Milburn Rd",
    "sg:city":"Ashington",
    "sg:classifiers":[
        {
            "category":"Retail",
            "subcategory":"Funeral Services",
            "type":"Services"
        }
    ],
    "sg:phone":"+44 1670 816464",
    "sg:postcode":"NE63 0PQ",
    "sg:province":"Northumberland",
    "wof:name":"T Shields & Sons",
    "wof:placetype":"venue"
},
  "geometry": {"coordinates":[-1.565344,55.179436],"type":"Point"}
}