{
  "type": "Feature",
  "properties": {
    "addr:full":"112 Brackley Square Woodford Green Essex IG8 7LS",
    "addr:housenumber":"112",
    "addr:postcode":"ig8 7ls",
    "addr:street":"Brackley Square",
    "iso:country":"GB",
    "sg:address":"112 Brackley Square",
    "sg:city":"Woodford Green",
    "sg:classifiers":[
        {
            "category":"Health Services",
            "subcategory":"Clinic",
            "type":"Services"
        }
    ],
    "sg:phone":"+44 20 8559 1310",
    "sg:postcode":"IG8 7LS",
    "sg:province":"Essex",
    "sg:tags":[
        "injury",
        "sport"
    ],
    "wof:name":"Proteus Sports Therapy",
    "wof:placetype":"venue"
},
  "geometry": {"coordinates":[0.0434099995,51.6037406921],"type":"Point"}
}