{
  "type": "Feature",
  "properties": {
    "iso:country":"GB",
    "sg:address":"27 Mill Street",
    "sg:city":"Alloa",
    "sg:classifiers":[
        {
            "category":"Personal",
            "subcategory":"Beauty Salon",
            "type":"Services"
        }
    ],
    "sg:phone":"+44 1259 723991",
    "sg:postcode":"FK10 1DT",
    "sg:province":"Clackmannanshire",
    "sg:tags":[
        "unisex",
        "hairdresser"
    ],
    "wof:name":"Morgans Hairdressing",
    "wof:placetype":"venue"
},
  "geometry": {"coordinates":[-3.7916920185,56.1149673462],"type":"Point"}
}