{
  "type": "Feature",
  "properties": {
    "iso:country":"GB",
    "sg:address":"23 Brocks Drive, Fairlands, Worplesdon",
    "sg:city":"Guildford",
    "sg:classifiers":[
        {
            "category":"Building & Trades",
            "subcategory":"Plumbing",
            "type":"Services"
        }
    ],
    "sg:phone":"+44 1483 233110",
    "sg:postcode":"GU3 3ND",
    "sg:province":"Surrey",
    "sg:tags":[
        "plumber",
        "heating"
    ],
    "wof:name":"Alan Nakiewycz",
    "wof:placetype":"venue"
},
  "geometry": {"coordinates":[-0.621157,51.2616],"type":"Point"}
}