{
  "type": "Feature",
  "properties": {
    "iso:country":"GB",
    "sg:address":"16 Elmsley Road",
    "sg:city":"Liverpool",
    "sg:classifiers":[
        {
            "category":"Farming",
            "subcategory":"Nursery",
            "type":"Manufacturing & Wholesale Goods"
        },
        {
            "category":"Education",
            "subcategory":"Preschool",
            "type":"Public Place"
        }
    ],
    "sg:phone":"+44 151 724 4500",
    "sg:postcode":"L18 8BB",
    "sg:province":"Merseyside",
    "sg:tags":[
        "school",
        "creche"
    ],
    "wof:name":"Monkton Nursery School",
    "wof:placetype":"venue"
},
  "geometry": {"coordinates":[-2.917425,53.380173],"type":"Point"}
}