{
  "type": "Feature",
  "properties": {
    "iso:country":"GB",
    "sg:address":"9 Frankwell",
    "sg:city":"Shrewsbury",
    "sg:classifiers":[
        {
            "category":"Shopping",
            "subcategory":"Antiques",
            "type":"Retail Goods"
        }
    ],
    "sg:postcode":"SY3 8JY",
    "sg:province":"Shropshire",
    "wof:name":"Quayside Antiques",
    "wof:placetype":"venue"
},
  "geometry": {"coordinates":[-2.75986,52.711044],"type":"Point"}
}