{
  "type": "Feature",
  "properties": {
    "iso:country":"GB",
    "sg:address":"189 Penarth Road",
    "sg:city":"Cardiff",
    "sg:classifiers":[
        {
            "category":"Fast Food",
            "type":"Food & Drink"
        }
    ],
    "sg:phone":"+44 29 2038 3340",
    "sg:postcode":"CF11 6FR",
    "sg:province":"Cardiff",
    "sg:tags":[
        "away",
        "take"
    ],
    "wof:name":"The Sorrento Restaurant",
    "wof:placetype":"venue"
},
  "geometry": {"coordinates":[-3.1859788895,51.4702606201],"type":"Point"}
}