{
  "type": "Feature",
  "properties": {
    "addr:full":"Unit 3 Ashton-under-lyne Greater Manchester OL6 6UG",
    "addr:housenumber":"unit 3",
    "addr:postcode":"ol6 6ug",
    "iso:country":"GB",
    "sg:address":"Unit 3",
    "sg:city":"Ashton-under-lyne",
    "sg:classifiers":[
        {
            "category":"Shopping",
            "subcategory":"Stationery & Office Supplies",
            "type":"Retail Goods"
        }
    ],
    "sg:postcode":"OL6 6UG",
    "sg:province":"Greater Manchester",
    "sg:tags":[
        "printers'"
    ],
    "wof:name":"Imperial Cutting Formes Ltd.",
    "wof:placetype":"venue"
},
  "geometry": {"coordinates":[-2.084929,53.48782],"type":"Point"}
}