{
  "type": "Feature",
  "properties": {
    "iso:country":"GB",
    "sg:address":"Four Oaks Farm, Aston Juxta Mondrum",
    "sg:city":"Nantwich",
    "sg:classifiers":[
        {
            "category":"Communications",
            "type":"Services"
        }
    ],
    "sg:phone":"+44 1270 522588",
    "sg:postcode":"CW5 6DT",
    "sg:province":"Cheshire",
    "sg:tags":[
        "telecommunication"
    ],
    "wof:name":"Perfect Personal Numbers",
    "wof:placetype":"venue"
},
  "geometry": {"coordinates":[-2.533205,53.105629],"type":"Point"}
}