{
  "type": "Feature",
  "properties": {
    "addr:full":"17 Laurieston Park Glenrothes Fife KY7 6YJ",
    "addr:housenumber":"17",
    "addr:postcode":"ky7 6yj",
    "addr:street":"Laurieston Park Glenrothes",
    "iso:country":"GB",
    "sg:address":"17 Laurieston Park",
    "sg:city":"Glenrothes",
    "sg:classifiers":[
        {
            "category":"Home & Garden",
            "subcategory":"Household Appliances",
            "type":"Retail Goods"
        }
    ],
    "sg:phone":"+44 1592 561408",
    "sg:postcode":"KY7 6YJ",
    "sg:province":"Fife",
    "sg:tags":[
        "electrical"
    ],
    "wof:name":"Methven & Methven",
    "wof:placetype":"venue"
},
  "geometry": {"coordinates":[-3.159296,56.216587],"type":"Point"}
}