{
  "type": "Feature",
  "properties": {
    "iso:country":"GB",
    "sg:address":"Alexander Industrial Estate, Broad Lanes",
    "sg:city":"Bilston",
    "sg:classifiers":[
        {
            "category":"Building & Trades",
            "subcategory":"Construction",
            "type":"Services"
        }
    ],
    "sg:phone":"+44 1902 402000",
    "sg:postcode":"WV14 0RQ",
    "sg:province":"West Midlands",
    "sg:tags":[
        "fork",
        "lift",
        "truck"
    ],
    "wof:name":"Centro Forklift Co. Ltd.",
    "wof:placetype":"venue"
},
  "geometry": {"coordinates":[-2.07449,52.566635],"type":"Point"}
}