{
  "type": "Feature",
  "properties": {
    "iso:country":"GB",
    "sg:address":"587 Etruria Rd",
    "sg:city":"Stoke On Trent",
    "sg:classifiers":[
        {
            "category":"Health Services",
            "subcategory":"Dentist",
            "type":"Services"
        }
    ],
    "sg:phone":"+44 1782 614905",
    "sg:postcode":"ST4 6HL",
    "sg:province":"Staffordshire",
    "wof:name":"A P White",
    "wof:placetype":"venue"
},
  "geometry": {"coordinates":[-2.214029,53.015739],"type":"Point"}
}