{
  "type": "Feature",
  "properties": {
    "iso:country":"GB",
    "sg:address":"62 Colinton, Mains Crescent",
    "sg:city":"Edinburgh",
    "sg:classifiers":[
        {
            "category":"Home & Garden",
            "subcategory":"Household Appliances",
            "type":"Retail Goods"
        }
    ],
    "sg:postcode":"EH13 9DS",
    "sg:province":"City of Edinburgh",
    "sg:tags":[
        "electrical"
    ],
    "wof:name":"Appliance Care",
    "wof:placetype":"venue"
},
  "geometry": {"coordinates":[-3.230722,55.908749],"type":"Point"}
}