{
  "type": "Feature",
  "properties": {
    "addr:full":"51a Westgate, Almondbury Huddersfield West Yorkshire HD5 8XF",
    "addr:housenumber":"51a",
    "addr:postcode":"hd5 8xf",
    "addr:street":"Westgate;West",
    "iso:country":"GB",
    "sg:address":"51a Westgate, Almondbury",
    "sg:city":"Huddersfield",
    "sg:classifiers":[
        {
            "category":"Professional",
            "subcategory":"Management & Consulting",
            "type":"Services"
        },
        {
            "category":"Organizations",
            "subcategory":"Community Association",
            "type":"Services"
        }
    ],
    "sg:phone":"+44 1484 426000",
    "sg:postcode":"HD5 8XF",
    "sg:province":"West Yorkshire",
    "sg:tags":[
        "consultant",
        "relation",
        "public",
        "business"
    ],
    "wof:name":"L A P Public Relations",
    "wof:placetype":"venue"
},
  "geometry": {"coordinates":[-1.747595,53.631062],"type":"Point"}
}