{
  "type": "Feature",
  "properties": {
    "iso:country":"GB",
    "sg:address":"36 The Street, Beck Row",
    "sg:city":"Bury St Edmunds",
    "sg:classifiers":[
        {
            "category":"Education",
            "subcategory":"School",
            "type":"Public Place"
        }
    ],
    "sg:phone":"+44 1638 713001",
    "sg:postcode":"IP28 8AE",
    "sg:province":"Cambridgeshire",
    "sg:tags":[
        "local",
        "authority"
    ],
    "wof:name":"Beck Row Primary School",
    "wof:placetype":"venue"
},
  "geometry": {"coordinates":[0.508518,52.365566],"type":"Point"}
}