{
  "type": "Feature",
  "properties": {
    "addr:full":"84 Itchen Avenue Eastleigh Hampshire SO50 8NH",
    "addr:housenumber":"84",
    "addr:postcode":"so50 8nh",
    "addr:street":"Itchen Avenue",
    "iso:country":"GB",
    "sg:address":"84 Itchen Avenue",
    "sg:city":"Eastleigh",
    "sg:classifiers":[
        {
            "category":"Building & Trades",
            "subcategory":"Construction",
            "type":"Services"
        }
    ],
    "sg:postcode":"SO50 8NH",
    "sg:province":"Hampshire",
    "sg:tags":[
        "builder"
    ],
    "wof:name":"S P Saunders",
    "wof:placetype":"venue"
},
  "geometry": {"coordinates":[-1.317103,50.965904],"type":"Point"}
}