{
  "type": "Feature",
  "properties": {
    "addr:full":"16 Atlas Way Sheffield South Yorkshire S4 7QQ",
    "addr:housenumber":"16",
    "addr:postcode":"s4 7qq",
    "addr:street":"Atlas Way",
    "iso:country":"GB",
    "sg:address":"16 Atlas Way",
    "sg:city":"Sheffield",
    "sg:classifiers":[
        {
            "category":"Manufacturing",
            "subcategory":"Metals",
            "type":"Manufacturing & Wholesale Goods"
        }
    ],
    "sg:phone":"+44 114 244 7400",
    "sg:postcode":"S4 7QQ",
    "sg:province":"South Yorkshire",
    "sg:tags":[
        "steel",
        "stockholder"
    ],
    "wof:name":"George Ibbotson (Steels) Ltd.",
    "wof:placetype":"venue"
},
  "geometry": {"coordinates":[-1.444877,53.397053],"type":"Point"}
}