{
  "type": "Feature",
  "properties": {
    "addr:full":"Glan-yr-afon Surgery, Shop Row Tredegar Blaenau Gwent NP2 4LB",
    "addr:postcode":"np2 4lb",
    "addr:street":"Row",
    "iso:country":"GB",
    "sg:address":"Glan-yr-afon Surgery, Shop Row",
    "sg:city":"Tredegar",
    "sg:classifiers":[
        {
            "category":"Health Services",
            "subcategory":"Doctor",
            "type":"Services"
        }
    ],
    "sg:phone":"+44 1495 722630",
    "sg:postcode":"NP2 4LB",
    "sg:province":"Blaenau Gwent",
    "sg:tags":[
        "practitioners"
    ],
    "wof:name":"Sinha, S",
    "wof:placetype":"venue"
},
  "geometry": {"coordinates":[-3.242413044,51.7709007263],"type":"Point"}
}