{
  "type": "Feature",
  "properties": {
    "iso:country":"GB",
    "sg:address":"13 Wilton Rd",
    "sg:city":"Birmingham",
    "sg:classifiers":[
        {
            "category":"Place Of Worship",
            "type":"Public Place"
        }
    ],
    "sg:phone":"+44 121 523 9129",
    "sg:postcode":"B20 3RX",
    "sg:province":"West Midlands",
    "wof:name":"United Reformed Church",
    "wof:placetype":"venue"
},
  "geometry": {"coordinates":[-1.9141340256,52.5127868652],"type":"Point"}
}