{
  "type": "Feature",
  "properties": {
    "addr:full":"96 St Bartholomews Rd Nottingham Nottinghamshire NG3 3ED",
    "addr:housenumber":"96",
    "addr:postcode":"ng3 3ed",
    "addr:street":"St Bartholomews Rd",
    "iso:country":"GB",
    "sg:address":"96 St Bartholomews Rd",
    "sg:city":"Nottingham",
    "sg:classifiers":[
        {
            "category":"Shopping",
            "subcategory":"News",
            "type":"Retail Goods"
        }
    ],
    "sg:phone":"+44 115 950 5463",
    "sg:postcode":"NG3 3ED",
    "sg:province":"Nottinghamshire",
    "sg:tags":[
        "newsagent"
    ],
    "wof:name":"Thorneywood Rise Sub Post Office",
    "wof:placetype":"venue"
},
  "geometry": {"coordinates":[-1.12608,52.964424],"type":"Point"}
}