{
  "type": "Feature",
  "properties": {
    "addr:full":"58 West End Road, Bitterne Southampton Hampshire SO18 6TG",
    "addr:housenumber":"58",
    "addr:postcode":"so18 6tg",
    "addr:street":"West End Road",
    "iso:country":"GB",
    "sg:address":"58 West End Road, Bitterne",
    "sg:city":"Southampton",
    "sg:classifiers":[
        {
            "category":"Building & Trades",
            "subcategory":"Construction",
            "type":"Services"
        }
    ],
    "sg:phone":"+44 23 8044 9292",
    "sg:postcode":"SO18 6TG",
    "sg:province":"Hampshire",
    "sg:tags":[
        "builder"
    ],
    "wof:name":"Lloyd & Jenkins",
    "wof:placetype":"venue"
},
  "geometry": {"coordinates":[-1.3476200104,50.9220161438],"type":"Point"}
}