{
  "type": "Feature",
  "properties": {
    "iso:country":"GB",
    "sg:address":"Millennium House, Euxton Lane, Euxton",
    "sg:city":"Chorley",
    "sg:classifiers":[
        {
            "category":"Professional",
            "subcategory":"Engineering",
            "type":"Services"
        }
    ],
    "sg:phone":"+44 1257 264441",
    "sg:postcode":"PR7 6AE",
    "sg:province":"Lancashire",
    "sg:tags":[
        "civil",
        "engineer"
    ],
    "wof:name":"John Reilly",
    "wof:placetype":"venue"
},
  "geometry": {"coordinates":[-2.6758608818,53.6690940857],"type":"Point"}
}