{
  "type": "Feature",
  "properties": {
    "iso:country":"GB",
    "sg:address":"40 Cowick Street",
    "sg:city":"Exeter",
    "sg:classifiers":[
        {
            "category":"Shopping",
            "subcategory":"Shoes",
            "type":"Retail Goods"
        }
    ],
    "sg:phone":"+44 1803 327543",
    "sg:postcode":"EX4 1AL",
    "sg:province":"Devon",
    "sg:tags":[
        "shop"
    ],
    "wof:name":"Discount Shoes",
    "wof:placetype":"venue"
},
  "geometry": {"coordinates":[-3.541326,50.716248],"type":"Point"}
}