{
  "type": "Feature",
  "properties": {
    "addr:full":"Janspar, Loveny Road, St Neot Liskeard Cornwall PL14 6NL",
    "addr:postcode":"pl14 6nl",
    "addr:street":"Loveny Road St Neot",
    "iso:country":"GB",
    "sg:address":"Janspar, Loveny Road, St Neot",
    "sg:city":"Liskeard",
    "sg:classifiers":[
        {
            "category":"Building & Trades",
            "subcategory":"Construction",
            "type":"Services"
        }
    ],
    "sg:phone":"+44 1579 320485",
    "sg:postcode":"PL14 6NL",
    "sg:province":"Cornwall",
    "sg:tags":[
        "builder"
    ],
    "wof:name":"W J Burrows Builder",
    "wof:placetype":"venue"
},
  "geometry": {"coordinates":[-4.556019783,50.4812202454],"type":"Point"}
}