{
  "type": "Feature",
  "properties": {
    "iso:country":"GB",
    "sg:address":"7 Stringers Avenue",
    "sg:city":"Guildford",
    "sg:classifiers":[
        {
            "category":"Retail",
            "subcategory":"Repair Shop",
            "type":"Services"
        }
    ],
    "sg:phone":"+44 1483 569146",
    "sg:postcode":"GU4 7NW",
    "sg:province":"Surrey",
    "sg:tags":[
        "radio",
        "television",
        "video"
    ],
    "wof:name":"Colstar Electronics",
    "wof:placetype":"venue"
},
  "geometry": {"coordinates":[-0.5758479834,51.268245697],"type":"Point"}
}