{
  "type": "Feature",
  "properties": {
    "addr:full":"1 Chatsworth Pl, Oxshott Leatherhead Surrey KT22 0SS",
    "addr:housenumber":"1",
    "addr:postcode":"kt22 0ss",
    "addr:street":"Chatsworth Pl",
    "iso:country":"GB",
    "sg:address":"1 Chatsworth Pl, Oxshott",
    "sg:city":"Leatherhead",
    "sg:classifiers":[
        {
            "category":"Real Estate",
            "subcategory":"Architect",
            "type":"Services"
        }
    ],
    "sg:postcode":"KT22 0SS",
    "sg:province":"Surrey",
    "wof:name":"Rubin,John M,",
    "wof:placetype":"venue"
},
  "geometry": {"coordinates":[-0.3569990098,51.3353118896],"type":"Point"}
}