{
  "type": "Feature",
  "properties": {
    "addr:full":"Treveth, Prideaux Road, St Blazey Par Cornwall PL24 2SR",
    "addr:postcode":"pl24 2sr",
    "addr:street":"Prideaux Road St",
    "iso:country":"GB",
    "sg:address":"Treveth, Prideaux Road, St Blazey",
    "sg:city":"Par",
    "sg:classifiers":[
        {
            "category":"Building & Trades",
            "subcategory":"Construction",
            "type":"Services"
        }
    ],
    "sg:postcode":"PL24 2SR",
    "sg:province":"Cornwall",
    "sg:tags":[
        "builder"
    ],
    "wof:name":"Roger A Swiggs",
    "wof:placetype":"venue"
},
  "geometry": {"coordinates":[-4.716859,50.364792],"type":"Point"}
}