{
  "type": "Feature",
  "properties": {
    "iso:country":"GB",
    "sg:address":"86 Brindley Rd, Astmoor Ind Est",
    "sg:city":"Runcorn",
    "sg:classifiers":[
        {
            "category":"Real Estate",
            "subcategory":"Real Estate Operator",
            "type":"Services"
        },
        {
            "category":"Home & Garden",
            "subcategory":"Home Furnishings",
            "type":"Retail Goods"
        }
    ],
    "sg:phone":"+44 1928 560527",
    "sg:postcode":"WA7 1PF",
    "sg:province":"Cheshire",
    "sg:tags":[
        "steel",
        "stainless",
        "fitting",
        "pipe",
        "stockholder"
    ],
    "wof:name":"Pharm-tech Ltd",
    "wof:placetype":"venue"
},
  "geometry": {"coordinates":[-2.6968998909,53.3438873291],"type":"Point"}
}