{
  "type": "Feature",
  "properties": {
    "addr:full":"2 Seabrook Road King's Langley Hertfordshire WD4 8NU",
    "addr:housenumber":"2",
    "addr:postcode":"wd4 8nu",
    "addr:street":"Seabrook Road",
    "iso:country":"GB",
    "sg:address":"2 Seabrook Road",
    "sg:city":"King's Langley",
    "sg:classifiers":[
        {
            "category":"Building & Trades",
            "subcategory":"Construction",
            "type":"Services"
        }
    ],
    "sg:phone":"+44 1923 263437",
    "sg:postcode":"WD4 8NU",
    "sg:province":"Hertfordshire",
    "sg:tags":[
        "builder"
    ],
    "wof:name":"Clark Building Services",
    "wof:placetype":"venue"
},
  "geometry": {"coordinates":[-0.4251919985,51.7200012207],"type":"Point"}
}