{
  "type": "Feature",
  "properties": {
    "addr:full":"St. Marys Works, Uttoxeter Rd Stoke On Trent Staffordshire ST3 1QR",
    "addr:postcode":"st3 1qr",
    "addr:street":"Uttoxeter Rd",
    "iso:country":"GB",
    "sg:address":"St. Marys Works, Uttoxeter Rd",
    "sg:city":"Stoke On Trent",
    "sg:classifiers":[
        {
            "category":"Manufacturing",
            "subcategory":"Building Materials",
            "type":"Manufacturing & Wholesale Goods"
        }
    ],
    "sg:phone":"+44 1782 291124",
    "sg:postcode":"ST3 1QR",
    "sg:province":"Staffordshire",
    "sg:tags":[
        "tile",
        "mnfrs"
    ],
    "wof:name":"The Royal Doulton Company",
    "wof:placetype":"venue"
},
  "geometry": {"coordinates":[-2.1292901039,52.9896316528],"type":"Point"}
}