{
  "type": "Feature",
  "properties": {
    "addr:full":"Unit 8/11, Exchange Industrial Estate, Cross Street Cannock Staffordshire WS11 3BW",
    "addr:housenumber":"unit 8 / 11",
    "addr:postcode":"ws11 3bw",
    "addr:street":"Exchange Industrial Estate Cross Street",
    "iso:country":"GB",
    "sg:address":"Unit 8/11, Exchange Industrial Estate, Cross Street",
    "sg:city":"Cannock",
    "sg:classifiers":[
        {
            "category":"Home & Garden",
            "subcategory":"Building Materials",
            "type":"Retail Goods"
        }
    ],
    "sg:phone":"+44 1543 574146",
    "sg:postcode":"WS11 3BW",
    "sg:province":"Staffordshire",
    "sg:tags":[
        "insulation",
        "installers"
    ],
    "wof:name":"Star Installation (Contractors) Ltd.",
    "wof:placetype":"venue"
},
  "geometry": {"coordinates":[-2.028067,52.674156],"type":"Point"}
}