{
  "type": "Feature",
  "properties": {
    "addr:full":"Witcombe Place Cheltenham Gloucestershire GL52 2SP",
    "addr:postcode":"gl52 2sp",
    "addr:street":"Witcombe Place",
    "iso:country":"GB",
    "sg:address":"Witcombe Place",
    "sg:city":"Cheltenham",
    "sg:classifiers":[
        {
            "category":"Retail",
            "subcategory":"Storage",
            "type":"Services"
        },
        {
            "category":"Shopping",
            "subcategory":"Used Merchandise",
            "type":"Retail Goods"
        }
    ],
    "sg:postcode":"GL52 2SP",
    "sg:province":"Gloucestershire",
    "sg:tags":[
        "shop",
        "household",
        "second-hand",
        "removal"
    ],
    "wof:name":"A1 Removals",
    "wof:placetype":"venue"
},
  "geometry": {"coordinates":[-2.069034,51.897995],"type":"Point"}
}