{
  "type": "Feature",
  "properties": {
    "addr:full":"77 Church Way, Iffley Oxford Oxfordshire OX4 4EF",
    "addr:housenumber":"77",
    "addr:postcode":"ox4 4ef",
    "addr:street":"Church Way",
    "iso:country":"GB",
    "sg:address":"77 Church Way, Iffley",
    "sg:city":"Oxford",
    "sg:classifiers":[
        {
            "category":"Shopping",
            "subcategory":"Department Store",
            "type":"Retail Goods"
        },
        {
            "category":"Food & Beverages",
            "subcategory":"Supermarket",
            "type":"Retail Goods"
        },
        {
            "category":"Government",
            "subcategory":"Post Office",
            "type":"Public Place"
        }
    ],
    "sg:postcode":"OX4 4EF",
    "sg:province":"Oxfordshire",
    "wof:name":"H ROOM",
    "wof:placetype":"venue"
},
  "geometry": {"coordinates":[-1.2375190258,51.730091095],"type":"Point"}
}