{
  "type": "Feature",
  "properties": {
    "iso:country":"GB",
    "sg:address":"65c Park Avenue",
    "sg:city":"Enfield",
    "sg:classifiers":[
        {
            "category":"Social Services",
            "subcategory":"Child Care",
            "type":"Services"
        },
        {
            "category":"Social Services",
            "subcategory":"Adult Care",
            "type":"Services"
        },
        {
            "category":"Government",
            "subcategory":"Office",
            "type":"Public Place"
        }
    ],
    "sg:phone":"+44 20 8360 1195",
    "sg:postcode":"EN1 2HH",
    "sg:province":"Greater London",
    "sg:tags":[
        "local",
        "day",
        "centre"
    ],
    "wof:name":"ENFIELD (LONDON BOROUGH OF)",
    "wof:placetype":"venue"
},
  "geometry": {"coordinates":[-0.077744,51.640797],"type":"Point"}
}