{
  "type": "Feature",
  "properties": {
    "addr:full":"Beach Road Norwich Norfolk NR12 0HS",
    "addr:postcode":"nr12 0hs",
    "addr:street":"Beach Road Norwich",
    "iso:country":"GB",
    "sg:address":"Beach Road",
    "sg:city":"Norwich",
    "sg:classifiers":[
        {
            "category":"Travel",
            "subcategory":"Hotels & Motels",
            "type":"Entertainment"
        }
    ],
    "sg:phone":"+44 1692 650302",
    "sg:postcode":"NR12 0HS",
    "sg:province":"Norfolk",
    "wof:name":"Seacroft Private Hotel",
    "wof:placetype":"venue"
},
  "geometry": {"coordinates":[1.477305,52.854012],"type":"Point"}
}