{
  "type": "Feature",
  "properties": {
    "addr:full":"121 Mortlake High Street London Greater London SW14 8SN",
    "addr:housenumber":"121",
    "addr:postcode":"sw14 8sn",
    "addr:street":"Mortlake High Street",
    "iso:country":"GB",
    "sg:address":"121 Mortlake High Street",
    "sg:city":"London",
    "sg:classifiers":[
        {
            "category":"Communications",
            "type":"Services"
        }
    ],
    "sg:phone":"+44 20 8878 3344",
    "sg:postcode":"SW14 8SN",
    "sg:province":"Greater London",
    "sg:tags":[
        "audio-visual"
    ],
    "wof:name":"Realisation Productions Ltd.",
    "wof:placetype":"venue"
},
  "geometry": {"coordinates":[-0.257795006,51.4702415466],"type":"Point"}
}