{
  "type": "Feature",
  "properties": {
    "addr:full":"Laystalls, Cross Hayes Malmesbury Wiltshire SN16 9BE",
    "addr:postcode":"sn16 9be",
    "addr:street":"Laystalls Cross",
    "iso:country":"GB",
    "sg:address":"Laystalls, Cross Hayes",
    "sg:city":"Malmesbury",
    "sg:classifiers":[
        {
            "category":"Professional",
            "subcategory":"Business Services",
            "type":"Services"
        },
        {
            "category":"Banks & Credit Unions",
            "subcategory":"Financial Services",
            "type":"Services"
        }
    ],
    "sg:postcode":"SN16 9BE",
    "sg:province":"Wiltshire",
    "sg:tags":[
        "adviser",
        "accomodation"
    ],
    "wof:name":"The Investment Centre",
    "wof:placetype":"venue"
},
  "geometry": {"coordinates":[-2.097419,51.582245],"type":"Point"}
}