{
  "type": "Feature",
  "properties": {
    "addr:full":"2 Parsonage Business Park Horsham West Sussex RH12 4AL",
    "addr:housenumber":"2",
    "addr:postcode":"rh12 4al",
    "addr:street":"Parsonage Business Park",
    "iso:country":"GB",
    "sg:address":"2 Parsonage Business Park",
    "sg:city":"Horsham",
    "sg:classifiers":[
        {
            "category":"Shopping",
            "subcategory":"Stationery & Office Supplies",
            "type":"Retail Goods"
        }
    ],
    "sg:phone":"+44 1403 211515",
    "sg:postcode":"RH12 4AL",
    "sg:province":"West Sussex",
    "wof:name":"Corporate Express",
    "wof:placetype":"venue"
},
  "geometry": {"coordinates":[-0.313224,51.074036],"type":"Point"}
}