{
  "type": "Feature",
  "properties": {
    "addr:full":"31 Whitehorse Street Baldock Bedfordshire SG7 6QF",
    "addr:housenumber":"31",
    "addr:postcode":"sg7 6qf",
    "addr:street":"Whitehorse Street",
    "iso:country":"GB",
    "sg:address":"31 Whitehorse Street",
    "sg:city":"Baldock",
    "sg:classifiers":[
        {
            "category":"Professional",
            "type":"Services"
        }
    ],
    "sg:postcode":"SG7 6QF",
    "sg:province":"Bedfordshire",
    "sg:tags":[
        "interior",
        "furnishers",
        "designer"
    ],
    "wof:name":"Florin Interiors",
    "wof:placetype":"venue"
},
  "geometry": {"coordinates":[-0.187155,51.990974],"type":"Point"}
}