{
  "type": "Feature",
  "properties": {
    "iso:country":"GB",
    "sg:address":"21 Chestergate",
    "sg:city":"Macclesfield",
    "sg:classifiers":[
        {
            "category":"Shopping",
            "subcategory":"Crafts & Fabrics",
            "type":"Retail Goods"
        }
    ],
    "sg:phone":"+44 1625 428757",
    "sg:postcode":"SK11 6BY",
    "sg:province":"Cheshire",
    "sg:tags":[
        "supplier"
    ],
    "wof:name":"Foam 4 U",
    "wof:placetype":"venue"
},
  "geometry": {"coordinates":[-2.1269450188,53.2569961548],"type":"Point"}
}