{
  "type": "Feature",
  "properties": {
    "addr:full":"1a Cambridge Avenue Kilburn Greater London NW6 5AA",
    "addr:housenumber":"1a",
    "addr:postcode":"nw6 5aa",
    "addr:street":"Cambridge Avenue",
    "iso:country":"GB",
    "sg:address":"1a Cambridge Avenue",
    "sg:city":"Kilburn",
    "sg:classifiers":[
        {
            "category":"Professional",
            "subcategory":"Computer Services",
            "type":"Services"
        }
    ],
    "sg:phone":"+44 20 7328 0294",
    "sg:postcode":"NW6 5AA",
    "sg:province":"Greater London",
    "sg:tags":[
        "system",
        "software"
    ],
    "wof:name":"Image Focus Services",
    "wof:placetype":"venue"
},
  "geometry": {"coordinates":[-0.1930149943,51.5360336304],"type":"Point"}
}