{
  "type": "Feature",
  "properties": {
    "addr:full":"Oakwood Court, Amberley Close Haywards Heath East Sussex RH16 4BG",
    "addr:postcode":"rh16 4bg",
    "addr:street":"Oakwood Court Amberley Close",
    "iso:country":"GB",
    "sg:address":"Oakwood Court, Amberley Close",
    "sg:city":"Haywards Heath",
    "sg:classifiers":[
        {
            "category":"Health Services",
            "subcategory":"Nursing And Care Facility",
            "type":"Services"
        },
        {
            "category":"Social Services",
            "subcategory":"Retirement Home",
            "type":"Services"
        }
    ],
    "sg:phone":"+44 1444 458872",
    "sg:postcode":"RH16 4BG",
    "sg:province":"East Sussex",
    "sg:tags":[
        "residential"
    ],
    "wof:name":"Oakwood Court Residential Care Home",
    "wof:placetype":"venue"
},
  "geometry": {"coordinates":[-0.110639,50.997849],"type":"Point"}
}