{
  "type": "Feature",
  "properties": {
    "addr:full":"50 Penrith Gdns Plymouth Devon PL6 8UX",
    "addr:housenumber":"50",
    "addr:postcode":"pl6 8ux",
    "addr:street":"Penrith Gdns",
    "iso:country":"GB",
    "sg:address":"50 Penrith Gdns",
    "sg:city":"Plymouth",
    "sg:classifiers":[
        {
            "category":"Building & Trades",
            "subcategory":"Construction",
            "type":"Services"
        }
    ],
    "sg:postcode":"PL6 8UX",
    "sg:province":"Devon",
    "sg:tags":[
        "builder"
    ],
    "wof:name":"Rawden Removals",
    "wof:placetype":"venue"
},
  "geometry": {"coordinates":[-4.10372,50.413464],"type":"Point"}
}