{
  "type": "Feature",
  "properties": {
    "iso:country":"GB",
    "sg:address":"Spring Farm, Stackyard Green",
    "sg:city":"Ipswich",
    "sg:classifiers":[
        {
            "category":"Social Services",
            "subcategory":"Retirement Home",
            "type":"Services"
        }
    ],
    "sg:phone":"+44 1449 741591",
    "sg:postcode":"IP7 7BD",
    "sg:province":"Suffolk",
    "sg:tags":[
        "care"
    ],
    "wof:name":"R J Parker",
    "wof:placetype":"venue"
},
  "geometry": {"coordinates":[0.8662199974,52.0752182007],"type":"Point"}
}