{
  "type": "Feature",
  "properties": {
    "iso:country":"GB",
    "sg:address":"17 Osborn Street",
    "sg:city":"London",
    "sg:classifiers":[
        {
            "category":"Building & Trades",
            "subcategory":"Construction",
            "type":"Services"
        }
    ],
    "sg:phone":"+44 20 7247 0163",
    "sg:postcode":"E1 6TD",
    "sg:province":"Greater London",
    "sg:tags":[
        "monumental",
        "mason"
    ],
    "wof:name":"A Elfes Ltd.",
    "wof:placetype":"venue"
},
  "geometry": {"coordinates":[-0.070306,51.51667],"type":"Point"}
}