{
  "type": "Feature",
  "properties": {
    "addr:full":"432 Park Road North Birkenhead Merseyside L41 0DA",
    "addr:housenumber":"432",
    "addr:postcode":"l41 0da",
    "addr:street":"Park Road North",
    "iso:country":"GB",
    "sg:address":"432 Park Road North",
    "sg:city":"Birkenhead",
    "sg:classifiers":[
        {
            "category":"Building & Trades",
            "subcategory":"Plumbing",
            "type":"Services"
        }
    ],
    "sg:phone":"+44 151 653 4234",
    "sg:postcode":"L41 0DA",
    "sg:province":"Merseyside",
    "sg:tags":[
        "heating"
    ],
    "wof:name":"H E Reynolds",
    "wof:placetype":"venue"
},
  "geometry": {"coordinates":[-3.0525519848,53.3968887329],"type":"Point"}
}