{
  "type": "Feature",
  "properties": {
    "iso:country":"GB",
    "sg:address":"Mill Farm, Mill Lane, Barthomley",
    "sg:city":"Crewe",
    "sg:classifiers":[
        {
            "category":"Farming",
            "subcategory":"Livestock Farm",
            "type":"Manufacturing & Wholesale Goods"
        }
    ],
    "sg:phone":"+44 1270 876447",
    "sg:postcode":"CW2 5NX",
    "sg:province":"Cheshire",
    "sg:tags":[
        "others"
    ],
    "wof:name":"T N Lawson",
    "wof:placetype":"venue"
},
  "geometry": {"coordinates":[-2.349229,53.068604],"type":"Point"}
}