{
  "type": "Feature",
  "properties": {
    "addr:full":"81 Mason Avenue, Swallownest Sheffield South Yorkshire S26 3UF",
    "addr:housenumber":"81",
    "addr:postcode":"s26 3uf",
    "addr:street":"Mason Avenue",
    "iso:country":"GB",
    "sg:address":"81 Mason Avenue, Swallownest",
    "sg:city":"Sheffield",
    "sg:classifiers":[
        {
            "category":"Military Area",
            "subcategory":"Air Force Base",
            "type":"Public Place"
        }
    ],
    "sg:postcode":"S26 3UF",
    "sg:province":"South Yorkshire",
    "sg:tags":[
        "taxi",
        "hire",
        "private"
    ],
    "wof:name":"A A A Taxis",
    "wof:placetype":"venue"
},
  "geometry": {"coordinates":[-1.315881,53.370655],"type":"Point"}
}