{
  "type": "Feature",
  "properties": {
    "iso:country":"GB",
    "sg:address":"91 Aylestone Road",
    "sg:city":"Leicester",
    "sg:classifiers":[
        {
            "category":"Shopping",
            "subcategory":"News",
            "type":"Retail Goods"
        }
    ],
    "sg:postcode":"LE2 7LN",
    "sg:province":"Leicestershire",
    "sg:tags":[
        "newsagent"
    ],
    "wof:name":"Dooleys News",
    "wof:placetype":"venue"
},
  "geometry": {"coordinates":[-1.13488,52.623398],"type":"Point"}
}