{
  "type": "Feature",
  "properties": {
    "iso:country":"GB",
    "sg:address":"Lakeside Works",
    "sg:city":"Newhaven",
    "sg:classifiers":[
        {
            "category":"Retail",
            "subcategory":"Auto Repair",
            "type":"Services"
        }
    ],
    "sg:phone":"+44 1273 514042",
    "sg:postcode":"BN9 0HS",
    "sg:province":"East Sussex",
    "sg:tags":[
        "modification",
        "garage"
    ],
    "wof:name":"Pollards Garage",
    "wof:placetype":"venue"
},
  "geometry": {"coordinates":[0.046175,50.795036],"type":"Point"}
}