{
  "type": "Feature",
  "properties": {
    "addr:full":"Maes Y Milwr Carmarthen Carmarthenshire SA33 4EJ",
    "addr:postcode":"sa33 4ej",
    "addr:street":"Maes Y Milwr",
    "iso:country":"GB",
    "sg:address":"Maes Y Milwr",
    "sg:city":"Carmarthen",
    "sg:classifiers":[
        {
            "category":"Building & Trades",
            "subcategory":"Plumbing",
            "type":"Services"
        }
    ],
    "sg:postcode":"SA33 4EJ",
    "sg:province":"Carmarthenshire",
    "sg:tags":[
        "heating"
    ],
    "wof:name":"G P Phillips Plumbing & Heating",
    "wof:placetype":"venue"
},
  "geometry": {"coordinates":[-4.4975700378,51.8107185364],"type":"Point"}
}