{
  "type": "Feature",
  "properties": {
    "addr:full":"100 Park Road Westcliff-on-sea Essex SS0 7PQ",
    "addr:housenumber":"100",
    "addr:postcode":"ss0 7pq",
    "addr:street":"Park Road",
    "iso:country":"GB",
    "sg:address":"100 Park Road",
    "sg:city":"Westcliff-on-sea",
    "sg:classifiers":[
        {
            "category":"Wholesale",
            "subcategory":"Books, Periodicals, & Newspapers",
            "type":"Manufacturing & Wholesale Goods"
        }
    ],
    "sg:postcode":"SS0 7PQ",
    "sg:province":"Essex",
    "sg:tags":[
        "maps",
        "globe",
        "chart",
        "pub"
    ],
    "wof:name":"Colourlink London Ltd.",
    "wof:placetype":"venue"
},
  "geometry": {"coordinates":[0.704417,51.54018],"type":"Point"}
}