{
  "type": "Feature",
  "properties": {
    "addr:full":"Swallowcliffe Salisbury Wiltshire SP3 5NU",
    "addr:postcode":"sp3 5nu",
    "iso:country":"GB",
    "sg:address":"Swallowcliffe",
    "sg:city":"Salisbury",
    "sg:classifiers":[
        {
            "category":"Farming",
            "subcategory":"Livestock Farm",
            "type":"Manufacturing & Wholesale Goods"
        }
    ],
    "sg:postcode":"SP3 5NU",
    "sg:province":"Wiltshire",
    "sg:tags":[
        "others"
    ],
    "wof:name":"D E J Parsons",
    "wof:placetype":"venue"
},
  "geometry": {"coordinates":[-2.05406,51.043652],"type":"Point"}
}