{
  "type": "Feature",
  "properties": {
    "addr:full":"24 Bath Street Abingdon Oxfordshire OX14 3QH",
    "addr:housenumber":"24",
    "addr:postcode":"ox14 3qh",
    "addr:street":"Bath Street",
    "iso:country":"GB",
    "sg:address":"24 Bath Street",
    "sg:city":"Abingdon",
    "sg:classifiers":[
        {
            "category":"Professional",
            "subcategory":"Computer Services",
            "type":"Services"
        }
    ],
    "sg:postcode":"OX14 3QH",
    "sg:province":"Oxfordshire",
    "sg:tags":[
        "system",
        "software"
    ],
    "wof:name":"Industrial and Commercial Computers Limi",
    "wof:placetype":"venue"
},
  "geometry": {"coordinates":[-1.2838180065,51.6709213257],"type":"Point"}
}