{
  "type": "Feature",
  "properties": {
    "addr:full":"20 Sterling Road Sittingbourne Kent ME10 1SL",
    "addr:housenumber":"20",
    "addr:postcode":"me10 1sl",
    "addr:street":"Sterling Road",
    "iso:country":"GB",
    "sg:address":"20 Sterling Road",
    "sg:city":"Sittingbourne",
    "sg:classifiers":[
        {
            "category":"Arts & Performance",
            "subcategory":"Music",
            "type":"Entertainment"
        }
    ],
    "sg:postcode":"ME10 1SL",
    "sg:province":"Kent",
    "sg:tags":[
        "mobile",
        "disco"
    ],
    "wof:name":"Solid Gold Entertainments",
    "wof:placetype":"venue"
},
  "geometry": {"coordinates":[0.7219589949,51.3310775757],"type":"Point"}
}