{
  "type": "Feature",
  "properties": {
    "addr:full":"Ovenden Road, Ovenden Halifax West Yorkshire HX3 5QG",
    "addr:postcode":"hx3 5qg",
    "addr:street":"Ovenden Road",
    "iso:country":"GB",
    "sg:address":"Ovenden Road, Ovenden",
    "sg:city":"Halifax",
    "sg:classifiers":[
        {
            "category":"Social Services",
            "subcategory":"Retirement Home",
            "type":"Services"
        }
    ],
    "sg:phone":"+44 1422 362487",
    "sg:postcode":"HX3 5QG",
    "sg:province":"West Yorkshire",
    "sg:tags":[
        "rest"
    ],
    "wof:name":"Ovenden House Rest Home",
    "wof:placetype":"venue"
},
  "geometry": {"coordinates":[-1.8754849434,53.7390975952],"type":"Point"}
}