{
  "type": "Feature",
  "properties": {
    "iso:country":"GB",
    "sg:address":"3 Walkers Cottage, Copthall Green",
    "sg:city":"Waltham Abbey",
    "sg:classifiers":[
        {
            "category":"Retail",
            "subcategory":"Repair Shop",
            "type":"Services"
        }
    ],
    "sg:phone":"+44 1992 715626",
    "sg:postcode":"EN9 3TA",
    "sg:province":"Essex",
    "sg:tags":[
        "maintenance"
    ],
    "wof:name":"Harvey Rose Ltd.",
    "wof:placetype":"venue"
},
  "geometry": {"coordinates":[0.0014900001,51.6864204407],"type":"Point"}
}