{
  "type": "Feature",
  "properties": {
    "addr:full":"Knole Road Bournemouth Dorset BH1 4DH",
    "addr:postcode":"bh1 4dh",
    "addr:street":"Knole Road",
    "iso:country":"GB",
    "sg:address":"Knole Road",
    "sg:city":"Bournemouth",
    "sg:classifiers":[
        {
            "category":"Government",
            "subcategory":"City Hall",
            "type":"Public Place"
        },
        {
            "category":"Organizations",
            "subcategory":"Membership Organization",
            "type":"Services"
        }
    ],
    "sg:phone":"+44 1202 393344",
    "sg:postcode":"BH1 4DH",
    "sg:province":"Dorset",
    "sg:tags":[
        "club"
    ],
    "wof:name":"Winshill Burton-on-Trent Freemasons Hall Ltd.",
    "wof:placetype":"venue"
},
  "geometry": {"coordinates":[-1.850489,50.727852],"type":"Point"}
}