{
  "type": "Feature",
  "properties": {
    "addr:full":"405-407 Holloway Road London Greater London N7 6HP",
    "addr:housenumber":"405-407",
    "addr:postcode":"n7 6hp",
    "addr:street":"Holloway Road",
    "iso:country":"GB",
    "sg:address":"405-407 Holloway Road",
    "sg:city":"London",
    "sg:classifiers":[
        {
            "category":"Health Services",
            "subcategory":"Clinic",
            "type":"Services"
        },
        {
            "category":"Health Services",
            "subcategory":"Dentist",
            "type":"Services"
        }
    ],
    "sg:phone":"+44 20 7700 7005",
    "sg:postcode":"N7 6HP",
    "sg:province":"Greater London",
    "sg:tags":[
        "nh"
    ],
    "wof:name":"Holloway Dental Centre",
    "wof:placetype":"venue"
},
  "geometry": {"coordinates":[-0.1199510023,51.5578956604],"type":"Point"}
}