{
  "type": "Feature",
  "properties": {
    "iso:country":"GB",
    "sg:address":"Unit 5, Trumpers Way, Hanwell",
    "sg:city":"Hanwell",
    "sg:classifiers":[
        {
            "category":"Retail",
            "subcategory":"Auto Repair",
            "type":"Services"
        }
    ],
    "sg:phone":"+44 20 8571 4488",
    "sg:postcode":"W7 2QA",
    "sg:province":"Greater London",
    "sg:tags":[
        "modification",
        "garage"
    ],
    "wof:name":"Clocktower Garage",
    "wof:placetype":"venue"
},
  "geometry": {"coordinates":[-0.336928,51.501373],"type":"Point"}
}