{
  "type": "Feature",
  "properties": {
    "addr:full":"21 The Precinct, London Road, Holmes Chapel Crewe Cheshire CW4 7AP",
    "addr:housenumber":"21",
    "addr:postcode":"cw4 7ap",
    "addr:street":"The Precinct London Road",
    "iso:country":"GB",
    "sg:address":"21 The Precinct, London Road, Holmes Chapel",
    "sg:city":"Crewe",
    "sg:classifiers":[
        {
            "category":"Real Estate",
            "subcategory":"Real Estate Agent",
            "type":"Services"
        }
    ],
    "sg:phone":"+44 1477 533575",
    "sg:postcode":"CW4 7AP",
    "sg:province":"Cheshire",
    "wof:name":"Reeds Rains Ltd.",
    "wof:placetype":"venue"
},
  "geometry": {"coordinates":[-2.35713,53.200748],"type":"Point"}
}