{
  "type": "Feature",
  "properties": {
    "iso:country":"GB",
    "sg:address":"58 Branston Street",
    "sg:city":"Birmingham",
    "sg:classifiers":[
        {
            "category":"Personal",
            "subcategory":"Sauna",
            "type":"Services"
        }
    ],
    "sg:phone":"+44 121 236 8122",
    "sg:postcode":"B18 6BP",
    "sg:province":"West Midlands",
    "wof:name":"58",
    "wof:placetype":"venue"
},
  "geometry": {"coordinates":[-1.9106849432,52.4895973206],"type":"Point"}
}