{
  "type": "Feature",
  "properties": {
    "addr:full":"158 Buckingham Road Aylesbury Buckinghamshire HP19 9QN",
    "addr:housenumber":"158",
    "addr:postcode":"hp19 9qn",
    "addr:street":"Buckingham Road",
    "iso:country":"GB",
    "sg:address":"158 Buckingham Road",
    "sg:city":"Aylesbury",
    "sg:classifiers":[
        {
            "category":"Food & Beverages",
            "subcategory":"Liquor & Beverages",
            "type":"Retail Goods"
        }
    ],
    "sg:phone":"+44 1296 436705",
    "sg:postcode":"HP19 9QN",
    "sg:province":"Buckinghamshire",
    "sg:tags":[
        "beer",
        "spirit",
        "wines"
    ],
    "wof:name":"Mac Wines",
    "wof:placetype":"venue"
},
  "geometry": {"coordinates":[-0.814841,51.827175],"type":"Point"}
}