{
  "type": "Feature",
  "properties": {
    "addr:full":"1 Ermin Street, Blundson Swindon Wiltshire SN26 8EF",
    "addr:housenumber":"1",
    "addr:postcode":"sn26 8ef",
    "addr:street":"Ermin Street",
    "iso:country":"GB",
    "sg:address":"1 Ermin Street, Blundson",
    "sg:city":"Swindon",
    "sg:classifiers":[
        {
            "category":"Professional",
            "subcategory":"Computer Services",
            "type":"Services"
        }
    ],
    "sg:phone":"+44 1793 729309",
    "sg:postcode":"SN26 8EF",
    "sg:province":"Wiltshire",
    "sg:tags":[
        "consultant"
    ],
    "wof:name":"O B S Y S",
    "wof:placetype":"venue"
},
  "geometry": {"coordinates":[-1.78835,51.609089],"type":"Point"}
}