{
  "type": "Feature",
  "properties": {
    "addr:full":"66 Lower Road Harrow Greater London HA2 0DH",
    "addr:housenumber":"66",
    "addr:postcode":"ha2 0dh",
    "addr:street":"Lower Road",
    "iso:country":"GB",
    "sg:address":"66 Lower Road",
    "sg:city":"Harrow",
    "sg:classifiers":[
        {
            "category":"Organizations",
            "subcategory":"Non-profit Organization",
            "type":"Services"
        }
    ],
    "sg:phone":"+44 20 8422 4535",
    "sg:postcode":"HA2 0DH",
    "sg:province":"Greater London",
    "sg:tags":[
        "organisation",
        "voluntary",
        "charity"
    ],
    "wof:name":"Advocacy Voice",
    "wof:placetype":"venue"
},
  "geometry": {"coordinates":[-0.346767,51.570007],"type":"Point"}
}