{
  "type": "Feature",
  "properties": {
    "iso:country":"GB",
    "sg:address":"17 Woodfield Road",
    "sg:city":"Doncaster",
    "sg:classifiers":[
        {
            "category":"Personal",
            "subcategory":"Beauty Salon",
            "type":"Services"
        }
    ],
    "sg:postcode":"DN4 8EP",
    "sg:province":"South Yorkshire",
    "sg:tags":[
        "unisex",
        "hairdresser"
    ],
    "wof:name":"Curl Up N'dye",
    "wof:placetype":"venue"
},
  "geometry": {"coordinates":[-1.152113,53.502956],"type":"Point"}
}