{
  "type": "Feature",
  "properties": {
    "iso:country":"GB",
    "sg:address":"Radnor Building, Radnor Park Industrial Estate",
    "sg:city":"Congleton",
    "sg:classifiers":[
        {
            "category":"Shopping",
            "subcategory":"Pharmacy",
            "type":"Retail Goods"
        }
    ],
    "sg:phone":"+44 1260 298398",
    "sg:postcode":"CW12 4XP",
    "sg:province":"Cheshire",
    "sg:tags":[
        "medical"
    ],
    "wof:name":"First Aid U K Ltd.",
    "wof:placetype":"venue"
},
  "geometry": {"coordinates":[-2.231193,53.165829],"type":"Point"}
}