{
  "type": "Feature",
  "properties": {
    "iso:country":"GB",
    "sg:address":"89 Littlehampton Road",
    "sg:city":"Worthing",
    "sg:classifiers":[
        {
            "category":"Building & Trades",
            "subcategory":"Construction",
            "type":"Services"
        }
    ],
    "sg:phone":"+44 1903 260630",
    "sg:postcode":"BN13 1QP",
    "sg:province":"West Sussex",
    "sg:tags":[
        "dry",
        "lining",
        "plasterers",
        "screeders"
    ],
    "wof:name":"Burtenshaw Plastering Services",
    "wof:placetype":"venue"
},
  "geometry": {"coordinates":[-0.4008930027,50.8293495178],"type":"Point"}
}