{
  "type": "Feature",
  "properties": {
    "addr:full":"20-22 Greenhill St Bedford Bedfordshire MK40 1LX",
    "addr:housenumber":"20-22",
    "addr:postcode":"mk40 1lx",
    "addr:street":"Greenhill St",
    "iso:country":"GB",
    "sg:address":"20-22 Greenhill St",
    "sg:city":"Bedford",
    "sg:classifiers":[
        {
            "category":"Home & Garden",
            "subcategory":"Home Furnishings",
            "type":"Retail Goods"
        }
    ],
    "sg:phone":"+44 1234 353465",
    "sg:postcode":"MK40 1LX",
    "sg:province":"Bedfordshire",
    "sg:tags":[
        "wall",
        "wallpaper",
        "covering"
    ],
    "wof:name":"Homestyle",
    "wof:placetype":"venue"
},
  "geometry": {"coordinates":[-0.470769,52.137882],"type":"Point"}
}