{
  "type": "Feature",
  "properties": {
    "addr:full":"198 Finney Lane, Heald Grn Cheadle Cheshire SK8 3QA",
    "addr:housenumber":"198",
    "addr:postcode":"sk8 3qa",
    "addr:street":"Finney Lane",
    "iso:country":"GB",
    "sg:address":"198 Finney Lane, Heald Grn",
    "sg:city":"Cheadle",
    "sg:classifiers":[
        {
            "category":"Real Estate",
            "subcategory":"Real Estate Agent",
            "type":"Services"
        }
    ],
    "sg:phone":"+44 161 437 1338",
    "sg:postcode":"SK8 3QA",
    "sg:province":"Cheshire",
    "wof:name":"Main & Main (Developments) Ltd.",
    "wof:placetype":"venue"
},
  "geometry": {"coordinates":[-2.2311449051,53.3699836731],"type":"Point"}
}