{
  "type": "Feature",
  "properties": {
    "iso:country":"GB",
    "sg:address":"761 Alum Rock Road, Ward End",
    "sg:city":"Birmingham",
    "sg:classifiers":[
        {
            "category":"Professional",
            "subcategory":"Employment Agencies",
            "type":"Services"
        }
    ],
    "sg:postcode":"B8 3PX",
    "sg:province":"West Midlands",
    "sg:tags":[
        "cv"
    ],
    "wof:name":"Kennneth Harris",
    "wof:placetype":"venue"
},
  "geometry": {"coordinates":[-1.83067,52.488594],"type":"Point"}
}