{
  "type": "Feature",
  "properties": {
    "iso:country":"GB",
    "sg:address":"18 Gosforth Close",
    "sg:city":"Sandy",
    "sg:classifiers":[
        {
            "category":"Professional",
            "subcategory":"Engineering",
            "type":"Services"
        }
    ],
    "sg:phone":"+44 1767 681392",
    "sg:postcode":"SG19 1RB",
    "sg:province":"Bedfordshire",
    "sg:tags":[
        "ge",
        "engineer",
        "mechanical"
    ],
    "wof:name":"M & E Services",
    "wof:placetype":"venue"
},
  "geometry": {"coordinates":[-0.2839339972,52.1428565979],"type":"Point"}
}