{
  "type": "Feature",
  "properties": {
    "addr:full":"Unit 5, Claylands Road Industrial Estate Southampton Hampshire SO32 1BH",
    "addr:housenumber":"unit 5",
    "addr:postcode":"so32 1bh",
    "addr:street":"Claylands Road Industrial Estate",
    "iso:country":"GB",
    "sg:address":"Unit 5, Claylands Road Industrial Estate",
    "sg:city":"Southampton",
    "sg:classifiers":[
        {
            "category":"Professional",
            "subcategory":"Engineering",
            "type":"Services"
        }
    ],
    "sg:phone":"+44 1489 891853",
    "sg:postcode":"SO32 1BH",
    "sg:province":"Hampshire",
    "sg:tags":[
        "acoustic",
        "engineer"
    ],
    "wof:name":"Proscon Environmental Ltd.",
    "wof:placetype":"venue"
},
  "geometry": {"coordinates":[-1.2214750051,50.9577522278],"type":"Point"}
}