{
  "type": "Feature",
  "properties": {
    "iso:country":"GB",
    "sg:address":"50 High Street, Gorseinon",
    "sg:city":"Swansea",
    "sg:classifiers":[
        {
            "category":"Social Services",
            "subcategory":"Retirement Home",
            "type":"Services"
        }
    ],
    "sg:phone":"+44 1792 892005",
    "sg:postcode":"SA4 4BR",
    "sg:province":"Carmarthenshire",
    "sg:tags":[
        "care"
    ],
    "wof:name":"Care-About (Wales) Ltd.",
    "wof:placetype":"venue"
},
  "geometry": {"coordinates":[-4.038405,51.668903],"type":"Point"}
}