{
  "type": "Feature",
  "properties": {
    "addr:full":"Southways, Dockacres Carnforth Cumbria LA6 1HP",
    "addr:postcode":"la6 1hp",
    "addr:street":"Carnforth",
    "iso:country":"GB",
    "sg:address":"Southways, Dockacres",
    "sg:city":"Carnforth",
    "sg:classifiers":[
        {
            "category":"Military Area",
            "subcategory":"Army Base",
            "type":"Public Place"
        }
    ],
    "sg:phone":"+44 1524 732992",
    "sg:postcode":"LA6 1HP",
    "sg:province":"Cumbria",
    "sg:tags":[
        "transportation",
        "livestock"
    ],
    "wof:name":"A Thompson Haulage",
    "wof:placetype":"venue"
},
  "geometry": {"coordinates":[-2.7478399277,54.1505699158],"type":"Point"}
}