{
  "type": "Feature",
  "properties": {
    "addr:full":"190 Quay Road Bridlington East Riding of Yorkshire YO16 4JF",
    "addr:housenumber":"190",
    "addr:postcode":"yo16 4jf",
    "addr:street":"Quay Road",
    "iso:country":"GB",
    "sg:address":"190 Quay Road",
    "sg:city":"Bridlington",
    "sg:classifiers":[
        {
            "category":"Home & Garden",
            "subcategory":"Furniture",
            "type":"Retail Goods"
        }
    ],
    "sg:phone":"+44 1262 400282",
    "sg:postcode":"YO16 4JF",
    "sg:province":"East Riding of Yorkshire",
    "wof:name":"Castle Interiors",
    "wof:placetype":"venue"
},
  "geometry": {"coordinates":[-0.202568993,54.0877685547],"type":"Point"}
}