{
  "type": "Feature",
  "properties": {
    "iso:country":"GB",
    "sg:address":"Swan Square, Llanfairtalhaiarn",
    "sg:city":"Abergele",
    "sg:classifiers":[
        {
            "category":"Fast Food",
            "type":"Food & Drink"
        }
    ],
    "sg:phone":"+44 1745 720205",
    "sg:postcode":"LL22 8RY",
    "sg:province":"Conwy",
    "sg:tags":[
        "away",
        "take"
    ],
    "wof:name":"Robinsons Brewery",
    "wof:placetype":"venue"
},
  "geometry": {"coordinates":[-3.6056449413,53.2186546326],"type":"Point"}
}