{
  "type": "Feature",
  "properties": {
    "addr:full":"Pacific Ho, 70 Wellington St Glasgow Glasgow City G2 6SB",
    "addr:housenumber":"70",
    "addr:postcode":"g2 6sb",
    "addr:street":"Wellington St",
    "iso:country":"GB",
    "sg:address":"Pacific Ho, 70 Wellington St",
    "sg:city":"Glasgow",
    "sg:classifiers":[
        {
            "category":"Real Estate",
            "subcategory":"Developer",
            "type":"Services"
        }
    ],
    "sg:postcode":"G2 6SB",
    "sg:province":"Glasgow City",
    "sg:tags":[
        "property"
    ],
    "wof:name":"Lawfield Investments Ltd",
    "wof:placetype":"venue"
},
  "geometry": {"coordinates":[-4.2602,55.859909],"type":"Point"}
}