{
  "type": "Feature",
  "properties": {
    "iso:country":"GB",
    "sg:address":"Unit 1 Hirwaun Industrial Estate, Hirwaun",
    "sg:city":"Aberdare",
    "sg:classifiers":[
        {
            "category":"Building & Trades",
            "subcategory":"Construction",
            "type":"Services"
        }
    ],
    "sg:phone":"+44 1685 811919",
    "sg:postcode":"CF44 9UP",
    "sg:province":"Neath Port Talbot",
    "sg:tags":[
        "ceiling",
        "contractor"
    ],
    "wof:name":"S A S International Ltd.",
    "wof:placetype":"venue"
},
  "geometry": {"coordinates":[-3.549364,51.744064],"type":"Point"}
}