{
  "type": "Feature",
  "properties": {
    "addr:full":"25 Union Road Inverness Highland IV2 3JY",
    "addr:housenumber":"25",
    "addr:postcode":"iv2 3jy",
    "addr:street":"Union Road",
    "iso:country":"GB",
    "sg:address":"25 Union Road",
    "sg:city":"Inverness",
    "sg:classifiers":[
        {
            "category":"Professional",
            "subcategory":"Computer Services",
            "type":"Services"
        }
    ],
    "sg:postcode":"IV2 3JY",
    "sg:province":"Highland",
    "sg:tags":[
        "system",
        "software"
    ],
    "wof:name":"E&I Systems",
    "wof:placetype":"venue"
},
  "geometry": {"coordinates":[-4.215313,57.476768],"type":"Point"}
}