{
  "type": "Feature",
  "properties": {
    "addr:full":"Meadow Croft, Wrockwardine Telford Shropshire TF6 5DG",
    "addr:postcode":"tf6 5dg",
    "addr:street":"Meadow",
    "iso:country":"GB",
    "sg:address":"Meadow Croft, Wrockwardine",
    "sg:city":"Telford",
    "sg:classifiers":[
        {
            "category":"Professional",
            "subcategory":"Management & Consulting",
            "type":"Services"
        }
    ],
    "sg:phone":"+44 1952 255444",
    "sg:postcode":"TF6 5DG",
    "sg:province":"Shropshire",
    "sg:tags":[
        "consultant"
    ],
    "wof:name":"Bowen Analysis",
    "wof:placetype":"venue"
},
  "geometry": {"coordinates":[-2.556119,52.703365],"type":"Point"}
}