{
  "type": "Feature",
  "properties": {
    "addr:full":"12 Farnborough Road Farnborough Hampshire GU14 6AY",
    "addr:housenumber":"12",
    "addr:postcode":"gu14 6ay",
    "addr:street":"Farnborough Road",
    "iso:country":"GB",
    "sg:address":"12 Farnborough Road",
    "sg:city":"Farnborough",
    "sg:classifiers":[
        {
            "category":"Government",
            "subcategory":"Post Office",
            "type":"Public Place"
        }
    ],
    "sg:phone":"+44 1252 541313",
    "sg:postcode":"GU14 6AY",
    "sg:province":"Hampshire",
    "sg:tags":[
        "messenger",
        "courier"
    ],
    "wof:name":"Arrow Despatch Ltd.",
    "wof:placetype":"venue"
},
  "geometry": {"coordinates":[-0.754661,51.277866],"type":"Point"}
}