{
  "type": "Feature",
  "properties": {
    "addr:full":"Freeman Ho, 63 Croxteth Dr St Helens Lancashire WA11 8LA",
    "addr:housenumber":"63",
    "addr:postcode":"wa11 8la",
    "addr:street":"Croxteth Dr",
    "iso:country":"GB",
    "sg:address":"Freeman Ho, 63 Croxteth Dr",
    "sg:city":"St Helens",
    "sg:classifiers":[
        {
            "category":"Shopping",
            "subcategory":"Computers & Home Electronics",
            "type":"Retail Goods"
        }
    ],
    "sg:phone":"+44 1744 885675",
    "sg:postcode":"WA11 8LA",
    "sg:province":"Lancashire",
    "sg:tags":[
        "electrical"
    ],
    "wof:name":"Freeman Enterprises Limited",
    "wof:placetype":"venue"
},
  "geometry": {"coordinates":[-2.7859,53.503948],"type":"Point"}
}