{
  "type": "Feature",
  "properties": {
    "addr:full":"579 Marton Road Middlesbrough North Yorkshire TS4 3SD",
    "addr:housenumber":"579",
    "addr:postcode":"ts4 3sd",
    "addr:street":"Marton Road",
    "iso:country":"GB",
    "sg:address":"579 Marton Road",
    "sg:city":"Middlesbrough",
    "sg:classifiers":[
        {
            "category":"Manufacturing",
            "subcategory":"Metals",
            "type":"Manufacturing & Wholesale Goods"
        }
    ],
    "sg:phone":"+44 1642 465195",
    "sg:postcode":"TS4 3SD",
    "sg:province":"North Yorkshire",
    "sg:tags":[
        "steel",
        "fabricator",
        "erectors"
    ],
    "wof:name":"Weldtech Fabrications",
    "wof:placetype":"venue"
},
  "geometry": {"coordinates":[-1.214806,54.545559],"type":"Point"}
}