{
  "type": "Feature",
  "properties": {
    "addr:full":"26 Foxholes Rd, Southbourne Bournemouth Dorset BH6 3AT",
    "addr:housenumber":"26",
    "addr:postcode":"bh6 3at",
    "addr:street":"Foxholes Rd",
    "iso:country":"GB",
    "sg:address":"26 Foxholes Rd, Southbourne",
    "sg:city":"Bournemouth",
    "sg:classifiers":[
        {
            "category":"Travel",
            "subcategory":"Hotels & Motels",
            "type":"Entertainment"
        }
    ],
    "sg:postcode":"BH6 3AT",
    "sg:province":"Dorset",
    "sg:tags":[
        "house",
        "guest"
    ],
    "wof:name":"Edgewood Guest House",
    "wof:placetype":"venue"
},
  "geometry": {"coordinates":[-1.796232,50.724113],"type":"Point"}
}