{
  "type": "Feature",
  "properties": {
    "iso:country":"GB",
    "sg:address":"Glendale House",
    "sg:city":"Salford",
    "sg:classifiers":[
        {
            "category":"Wholesale",
            "subcategory":"Non-durable Goods",
            "type":"Manufacturing & Wholesale Goods"
        },
        {
            "category":"Community Center",
            "subcategory":"Social",
            "type":"Public Place"
        }
    ],
    "sg:phone":"+44 161 736 8652",
    "sg:postcode":"M6 6LX",
    "sg:province":"Greater Manchester",
    "sg:tags":[
        "centre",
        "frozen",
        "cash",
        "freezer",
        "food",
        "carry"
    ],
    "wof:name":"Glendale Frozen Foods Ltd.",
    "wof:placetype":"venue"
},
  "geometry": {"coordinates":[-2.284299,53.489731],"type":"Point"}
}