{
  "type": "Feature",
  "properties": {
    "addr:full":"15-25 Caledonia Street London Greater London N1 9DZ",
    "addr:housenumber":"15-25",
    "addr:postcode":"n1 9dz",
    "addr:street":"Caledonia Street",
    "iso:country":"GB",
    "sg:address":"15-25 Caledonia Street",
    "sg:city":"London",
    "sg:classifiers":[
        {
            "category":"Retail",
            "subcategory":"Auto Rental",
            "type":"Services"
        }
    ],
    "sg:phone":"+44 20 7387 2276",
    "sg:postcode":"N1 9DZ",
    "sg:province":"Greater London",
    "sg:tags":[
        "car"
    ],
    "wof:name":"Europcar (U K) Ltd.",
    "wof:placetype":"venue"
},
  "geometry": {"coordinates":[-0.1211360022,51.5315361023],"type":"Point"}
}