{
  "type": "Feature",
  "properties": {
    "addr:full":"1 Crays Parade, Main Road Orpington Kent BR5 3HG",
    "addr:housenumber":"1",
    "addr:postcode":"br5 3hg",
    "addr:street":"Crays Parade Main Road",
    "iso:country":"GB",
    "sg:address":"1 Crays Parade, Main Road",
    "sg:city":"Orpington",
    "sg:classifiers":[
        {
            "category":"Fast Food",
            "type":"Food & Drink"
        }
    ],
    "sg:phone":"+44 1689 821816",
    "sg:postcode":"BR5 3HG",
    "sg:province":"Kent",
    "sg:tags":[
        "away",
        "take"
    ],
    "wof:name":"Phoenix Chinese Take Away",
    "wof:placetype":"venue"
},
  "geometry": {"coordinates":[0.11696,51.401169],"type":"Point"}
}