{
  "type": "Feature",
  "properties": {
    "addr:full":"1 Hoyles Road Wellington Devon TA21 9AH",
    "addr:housenumber":"1",
    "addr:postcode":"ta21 9ah",
    "addr:street":"Hoyles Road",
    "iso:country":"GB",
    "sg:address":"1 Hoyles Road",
    "sg:city":"Wellington",
    "sg:classifiers":[
        {
            "category":"Building & Trades",
            "subcategory":"Landscaping Services",
            "type":"Services"
        }
    ],
    "sg:phone":"+44 1823 664859",
    "sg:postcode":"TA21 9AH",
    "sg:province":"Devon",
    "sg:tags":[
        "landscape",
        "contractor"
    ],
    "wof:name":"Wellington Landscapes & Plant Hire",
    "wof:placetype":"venue"
},
  "geometry": {"coordinates":[-3.2227630615,50.9720726013],"type":"Point"}
}