{
  "type": "Feature",
  "properties": {
    "addr:full":"Forstal, Hernhill Faversham Kent ME13 9JG",
    "addr:postcode":"me13 9jg",
    "iso:country":"GB",
    "sg:address":"Forstal, Hernhill",
    "sg:city":"Faversham",
    "sg:classifiers":[
        {
            "category":"Community Center",
            "type":"Public Place"
        }
    ],
    "sg:phone":"+44 1227 751195",
    "sg:postcode":"ME13 9JG",
    "sg:province":"Kent",
    "sg:tags":[
        "centre"
    ],
    "wof:name":"Dawes Community Centre",
    "wof:placetype":"venue"
},
  "geometry": {"coordinates":[0.9613299966,51.3082084656],"type":"Point"}
}