{
  "type": "Feature",
  "properties": {
    "addr:full":"16 High Street, Doddington March Cambridgeshire PE15 0TF",
    "addr:housenumber":"16",
    "addr:postcode":"pe15 0tf",
    "addr:street":"High Street",
    "iso:country":"GB",
    "sg:address":"16 High Street, Doddington",
    "sg:city":"March",
    "sg:classifiers":[
        {
            "category":"Social Services",
            "subcategory":"Job Training",
            "type":"Services"
        },
        {
            "category":"Manufacturing",
            "subcategory":"Watercraft",
            "type":"Manufacturing & Wholesale Goods"
        }
    ],
    "sg:postcode":"PE15 0TF",
    "sg:province":"Cambridgeshire",
    "sg:tags":[
        "boatbuilder",
        "engineering",
        "marine"
    ],
    "wof:name":"LONGSHORE INTERNATIONAL",
    "wof:placetype":"venue"
},
  "geometry": {"coordinates":[-0.025564,52.4952735901],"type":"Point"}
}