{
  "type": "Feature",
  "properties": {
    "iso:country":"GB",
    "sg:address":"Herdman Street",
    "sg:city":"Crewe",
    "sg:classifiers":[
        {
            "category":"Government",
            "subcategory":"Office",
            "type":"Public Place"
        }
    ],
    "sg:phone":"+44 1270 257796",
    "sg:postcode":"CW2 7AP",
    "sg:province":"Cheshire",
    "sg:tags":[
        "central"
    ],
    "wof:name":"Abbeyfield House",
    "wof:placetype":"venue"
},
  "geometry": {"coordinates":[-2.437649,53.090389],"type":"Point"}
}