{
  "type": "Feature",
  "properties": {
    "addr:full":"2nd Floor, Suite 9, Widmore Road Bromley Kent BR1 1RP",
    "addr:housenumber":"2nd floor suite 9",
    "addr:postcode":"br1 1rp",
    "addr:street":"Widmore Road",
    "iso:country":"GB",
    "sg:address":"2nd Floor, Suite 9, Widmore Road",
    "sg:city":"Bromley",
    "sg:classifiers":[
        {
            "category":"Building & Trades",
            "subcategory":"Cleaning & Sanitation",
            "type":"Services"
        }
    ],
    "sg:postcode":"BR1 1RP",
    "sg:province":"Kent",
    "sg:tags":[
        "commercial"
    ],
    "wof:name":"Complete Property Services",
    "wof:placetype":"venue"
},
  "geometry": {"coordinates":[0.0177699998,51.4061965942],"type":"Point"}
}