{
  "type": "Feature",
  "properties": {
    "addr:full":"18 Lloyd St Manchester Greater Manchester M2 5WA",
    "addr:housenumber":"18",
    "addr:postcode":"m2 5wa",
    "addr:street":"Lloyd St",
    "iso:country":"GB",
    "sg:address":"18 Lloyd St",
    "sg:city":"Manchester",
    "sg:classifiers":[
        {
            "category":"Professional",
            "subcategory":"Lawyer & Legal Services",
            "type":"Services"
        }
    ],
    "sg:phone":"+44 161 832 3371",
    "sg:postcode":"M2 5WA",
    "sg:province":"Greater Manchester",
    "sg:tags":[
        "barrister"
    ],
    "wof:name":"Llyod House Chambers",
    "wof:placetype":"venue"
},
  "geometry": {"coordinates":[-2.2459509373,53.4790687561],"type":"Point"}
}