{
  "type": "Feature",
  "properties": {
    "iso:country":"GB",
    "sg:address":"Unit 7/8 Chelmsley Wood, Market Hall, Greenwood Way",
    "sg:city":"Birmingham",
    "sg:classifiers":[
        {
            "category":"Food & Beverages",
            "subcategory":"Meat & Fish",
            "type":"Retail Goods"
        }
    ],
    "sg:phone":"+44 121 788 0421",
    "sg:postcode":"B37 5TL",
    "sg:province":"West Midlands",
    "sg:tags":[
        "butcher"
    ],
    "wof:name":"P J Meats",
    "wof:placetype":"venue"
},
  "geometry": {"coordinates":[-1.747366,52.482452],"type":"Point"}
}