{
  "type": "Feature",
  "properties": {
    "iso:country":"GB",
    "sg:address":"Ashness Farm, Borrowdale",
    "sg:city":"Keswick",
    "sg:classifiers":[
        {
            "category":"Recreation",
            "subcategory":"Campground",
            "type":"Entertainment"
        }
    ],
    "sg:phone":"+44 17687 77361",
    "sg:postcode":"CA12 5UN",
    "sg:province":"Cumbria",
    "sg:tags":[
        "site",
        "camping"
    ],
    "wof:name":"Ashness Farm",
    "wof:placetype":"venue"
},
  "geometry": {"coordinates":[-3.1389639378,54.6017303467],"type":"Point"}
}