{
  "type": "Feature",
  "properties": {
    "addr:full":"32 Cartmell Rd Sheffield Derbyshire S8 0NJ",
    "addr:housenumber":"32",
    "addr:postcode":"s8 0nj",
    "addr:street":"Cartmell Rd",
    "iso:country":"GB",
    "sg:address":"32 Cartmell Rd",
    "sg:city":"Sheffield",
    "sg:classifiers":[
        {
            "category":"Utilities",
            "type":"Services"
        }
    ],
    "sg:postcode":"S8 0NJ",
    "sg:province":"Derbyshire",
    "sg:tags":[
        "internet"
    ],
    "wof:name":"Byte-site UK",
    "wof:placetype":"venue"
},
  "geometry": {"coordinates":[-1.484818,53.349369],"type":"Point"}
}