{
  "type": "Feature",
  "properties": {
    "addr:full":"49 Liverpool Rd Stoke On Trent Cheshire ST7 1EA",
    "addr:housenumber":"49",
    "addr:postcode":"st7 1ea",
    "addr:street":"Liverpool Rd",
    "iso:country":"GB",
    "sg:address":"49 Liverpool Rd",
    "sg:city":"Stoke On Trent",
    "sg:classifiers":[
        {
            "category":"Wholesale",
            "subcategory":"Toys & Hobbies",
            "type":"Manufacturing & Wholesale Goods"
        }
    ],
    "sg:phone":"+44 1782 783301",
    "sg:postcode":"ST7 1EA",
    "sg:province":"Cheshire",
    "sg:tags":[
        "balloon",
        "novelty"
    ],
    "wof:name":"Rainbow Cards & Balloons",
    "wof:placetype":"venue"
},
  "geometry": {"coordinates":[-2.241902,53.087051],"type":"Point"}
}