{
  "type": "Feature",
  "properties": {
    "iso:country":"GB",
    "sg:address":"179 High Street",
    "sg:city":"Northallerton",
    "sg:classifiers":[
        {
            "category":"Shopping",
            "subcategory":"Comic Books",
            "type":"Retail Goods"
        }
    ],
    "sg:phone":"+44 1609 776875",
    "sg:postcode":"DL7 8JZ",
    "sg:province":"North Yorkshire",
    "sg:tags":[
        "jeweller"
    ],
    "wof:name":"Swans Jewellers",
    "wof:placetype":"venue"
},
  "geometry": {"coordinates":[-1.434025,54.338539],"type":"Point"}
}