{
  "type": "Feature",
  "properties": {
    "iso:country":"GB",
    "sg:address":"1a Beverley Road",
    "sg:city":"Worcester Park",
    "sg:classifiers":[
        {
            "category":"Professional",
            "subcategory":"Engineering",
            "type":"Services"
        }
    ],
    "sg:phone":"+44 20 8669 1526",
    "sg:postcode":"KT4 8LX",
    "sg:province":"Surrey",
    "wof:name":"Rogerson & Good Ltd",
    "wof:placetype":"venue"
},
  "geometry": {"coordinates":[-0.2313620001,51.3761787415],"type":"Point"}
}