{
  "type": "Feature",
  "properties": {
    "iso:country":"GB",
    "sg:address":"290 Whitegate Drive",
    "sg:city":"Blackpool",
    "sg:classifiers":[
        {
            "category":"Education",
            "subcategory":"School",
            "type":"Public Place"
        }
    ],
    "sg:phone":"+44 1253 699379",
    "sg:postcode":"FY3 9PH",
    "sg:province":"Lancashire",
    "sg:tags":[
        "private",
        "tuition"
    ],
    "wof:name":"Lindow (Education & Training) Ltd.",
    "wof:placetype":"venue"
},
  "geometry": {"coordinates":[-3.027673,53.80492],"type":"Point"}
}