{
  "type": "Feature",
  "properties": {
    "iso:country":"GB",
    "sg:address":"177a Stourbridge Road",
    "sg:city":"Halesowen",
    "sg:classifiers":[
        {
            "category":"Health Services",
            "subcategory":"Optometrist",
            "type":"Services"
        },
        {
            "category":"Shopping",
            "subcategory":"Optician",
            "type":"Retail Goods"
        }
    ],
    "sg:phone":"+44 121 585 6044",
    "sg:postcode":"B63 3UD",
    "sg:province":"West Midlands",
    "sg:tags":[
        "ophthalmic"
    ],
    "wof:name":"L G Ellis",
    "wof:placetype":"venue"
},
  "geometry": {"coordinates":[-2.061819,52.453213],"type":"Point"}
}