{
  "type": "Feature",
  "properties": {
    "addr:full":"20 Highfields Rd Burntwood Staffordshire WS7 8QU",
    "addr:housenumber":"20",
    "addr:postcode":"ws7 8qu",
    "addr:street":"Highfields Rd",
    "iso:country":"GB",
    "sg:address":"20 Highfields Rd",
    "sg:city":"Burntwood",
    "sg:classifiers":[
        {
            "category":"Home & Garden",
            "subcategory":"Home Furnishings",
            "type":"Retail Goods"
        }
    ],
    "sg:phone":"+44 1543 676402",
    "sg:postcode":"WS7 8QU",
    "sg:province":"Staffordshire",
    "sg:tags":[
        "blind",
        "curtain",
        "fitting"
    ],
    "wof:name":"M Pugh",
    "wof:placetype":"venue"
},
  "geometry": {"coordinates":[-1.9332309961,52.6689872742],"type":"Point"}
}