{
  "type": "Feature",
  "properties": {
    "iso:country":"GB",
    "sg:address":"Shepherds, Old Church Rd, East Hanningfield",
    "sg:city":"Chelmsford",
    "sg:classifiers":[
        {
            "category":"Real Estate",
            "subcategory":"Architect",
            "type":"Services"
        }
    ],
    "sg:phone":"+44 1245 400663",
    "sg:postcode":"CM3 8BG",
    "sg:province":"Essex",
    "sg:tags":[
        "technologist",
        "architectural"
    ],
    "wof:name":"David C Rackham M.B.I.A.T F.F.B",
    "wof:placetype":"venue"
},
  "geometry": {"coordinates":[0.553,51.675297],"type":"Point"}
}