{
  "type": "Feature",
  "properties": {
    "iso:country":"GB",
    "sg:address":"25 Branchalmuir Crescent, Newmains",
    "sg:city":"Wishaw",
    "sg:classifiers":[
        {
            "category":"Health Services",
            "subcategory":"Health Practitioner",
            "type":"Services"
        }
    ],
    "sg:phone":"+44 1698 381779",
    "sg:postcode":"ML2 9DY",
    "sg:province":"North Lanarkshire",
    "sg:tags":[
        "physiotherapist"
    ],
    "wof:name":"Golden Hands",
    "wof:placetype":"venue"
},
  "geometry": {"coordinates":[-3.887401,55.787884],"type":"Point"}
}