{
  "type": "Feature",
  "properties": {
    "iso:country":"GB",
    "sg:address":"26 Clarendon Road",
    "sg:city":"Ashford",
    "sg:classifiers":[
        {
            "category":"Professional",
            "subcategory":"Art Services",
            "type":"Services"
        }
    ],
    "sg:postcode":"TW15 2QE",
    "sg:province":"Greater London",
    "sg:tags":[
        "graphic",
        "designer"
    ],
    "wof:name":"Richard Crawford Graphic Design",
    "wof:placetype":"venue"
},
  "geometry": {"coordinates":[-0.466775,51.434772],"type":"Point"}
}