{
  "type": "Feature",
  "properties": {
    "iso:country":"GB",
    "sg:address":"5 Oxhey Crescent, Biddulph",
    "sg:city":"Stoke-on-trent",
    "sg:classifiers":[
        {
            "category":"Retail",
            "subcategory":"Driving School",
            "type":"Services"
        }
    ],
    "sg:phone":"+44 1782 512300",
    "sg:postcode":"ST8 7EY",
    "sg:province":"Staffordshire",
    "wof:name":"A Proctor",
    "wof:placetype":"venue"
},
  "geometry": {"coordinates":[-2.16744,53.12328],"type":"Point"}
}