{
  "type": "Feature",
  "properties": {
    "iso:country":"GB",
    "sg:address":"216 Lord St",
    "sg:city":"Fleetwood",
    "sg:classifiers":[
        {
            "category":"Organizations",
            "subcategory":"Political Organization",
            "type":"Services"
        }
    ],
    "sg:phone":"+44 1253 877346",
    "sg:postcode":"FY7 6SW",
    "sg:province":"Lancashire",
    "sg:tags":[
        "party"
    ],
    "wof:name":"Blackpool North & Fleetwood Labour Party",
    "wof:placetype":"venue"
},
  "geometry": {"coordinates":[-3.016763,53.920254],"type":"Point"}
}