{
  "type": "Feature",
  "properties": {
    "addr:full":"The Forge Hungerford Berkshire RG17 0EF",
    "addr:postcode":"rg17 0ef",
    "iso:country":"GB",
    "sg:address":"The Forge",
    "sg:city":"Hungerford",
    "sg:classifiers":[
        {
            "category":"Home & Garden",
            "subcategory":"Home Furnishings",
            "type":"Retail Goods"
        }
    ],
    "sg:phone":"+44 1488 682066",
    "sg:postcode":"RG17 0EF",
    "sg:province":"Berkshire",
    "sg:tags":[
        "furnishers",
        "planner",
        "kitchen"
    ],
    "wof:name":"John Lewis of Hungerford",
    "wof:placetype":"venue"
},
  "geometry": {"coordinates":[-1.512806,51.417439],"type":"Point"}
}