{
  "type": "Feature",
  "properties": {
    "iso:country":"GB",
    "sg:address":"49 Bridge Street",
    "sg:city":"Llangefni",
    "sg:classifiers":[
        {
            "category":"Organizations",
            "subcategory":"Membership Organization",
            "type":"Services"
        },
        {
            "category":"Organizations",
            "subcategory":"Political Organization",
            "type":"Services"
        }
    ],
    "sg:phone":"+44 1248 750223",
    "sg:postcode":"LL77 7PN",
    "sg:province":"Gwynedd",
    "sg:tags":[
        "club",
        "party"
    ],
    "wof:name":"Ynys Mon Conservative Association",
    "wof:placetype":"venue"
},
  "geometry": {"coordinates":[-4.309575,53.255753],"type":"Point"}
}