{
  "type": "Feature",
  "properties": {
    "iso:country":"GB",
    "sg:address":"Capper House, Ditton Rd",
    "sg:city":"Widnes",
    "sg:classifiers":[
        {
            "category":"Professional",
            "subcategory":"Engineering",
            "type":"Services"
        }
    ],
    "sg:phone":"+44 151 424 5960",
    "sg:postcode":"WA8 0PQ",
    "sg:province":"Cheshire",
    "sg:tags":[
        "engineer"
    ],
    "wof:name":"Lamdec Projects",
    "wof:placetype":"venue"
},
  "geometry": {"coordinates":[-2.741869,53.35918],"type":"Point"}
}