{
  "type": "Feature",
  "properties": {
    "iso:country":"GB",
    "sg:address":"Gibralter Island Road, Old Mill Business Park",
    "sg:city":"Leeds",
    "sg:classifiers":[
        {
            "category":"Manufacturing",
            "subcategory":"Tools & Machinery",
            "type":"Manufacturing & Wholesale Goods"
        }
    ],
    "sg:phone":"+44 113 277 7730",
    "sg:postcode":"LS10 1RJ",
    "sg:province":"West Yorkshire",
    "wof:name":"Cromwell Tools (Leeds)",
    "wof:placetype":"venue"
},
  "geometry": {"coordinates":[-1.5190440416,53.779548645],"type":"Point"}
}