{
  "type": "Feature",
  "properties": {
    "addr:full":"Unit F9-f11, Cumberland Trading Estate Loughborough Leicestershire LE11 0DE",
    "addr:housenumber":"f9-f11",
    "addr:postcode":"le11 0de",
    "addr:street":"Trading Estate",
    "iso:country":"GB",
    "sg:address":"Unit F9-f11, Cumberland Trading Estate",
    "sg:city":"Loughborough",
    "sg:classifiers":[
        {
            "category":"Shopping",
            "type":"Retail Goods"
        }
    ],
    "sg:phone":"+44 1509 236677",
    "sg:postcode":"LE11 0DE",
    "sg:province":"Leicestershire",
    "sg:tags":[
        "merchant"
    ],
    "wof:name":"Farm Supplies",
    "wof:placetype":"venue"
},
  "geometry": {"coordinates":[-1.2234740257,52.7685241699],"type":"Point"}
}