{
  "type": "Feature",
  "properties": {
    "addr:full":"4 Church St Reigate Surrey RH2 0AN",
    "addr:housenumber":"4",
    "addr:postcode":"rh2 0an",
    "addr:street":"Church St",
    "iso:country":"GB",
    "sg:address":"4 Church St",
    "sg:city":"Reigate",
    "sg:classifiers":[
        {
            "category":"Real Estate",
            "subcategory":"Real Estate Agent",
            "type":"Services"
        }
    ],
    "sg:phone":"+44 1737 249277",
    "sg:postcode":"RH2 0AN",
    "sg:province":"Surrey",
    "wof:name":"Halifax Property Services",
    "wof:placetype":"venue"
},
  "geometry": {"coordinates":[-0.2049490064,51.2377281189],"type":"Point"}
}