{
  "type": "Feature",
  "properties": {
    "addr:full":"Castle Street Mall, Grosvenor Centre Macclesfield Cheshire SK11 6AX",
    "addr:postcode":"sk11 6ax",
    "addr:street":"Castle Street Mall Grosvenor Centre",
    "iso:country":"GB",
    "sg:address":"Castle Street Mall, Grosvenor Centre",
    "sg:city":"Macclesfield",
    "sg:classifiers":[
        {
            "category":"Professional",
            "subcategory":"Business Services",
            "type":"Services"
        }
    ],
    "sg:phone":"+44 1625 427785",
    "sg:postcode":"SK11 6AX",
    "sg:province":"Cheshire",
    "sg:tags":[
        "operator",
        "market"
    ],
    "wof:name":"Macclesfield Indoor Market",
    "wof:placetype":"venue"
},
  "geometry": {"coordinates":[-2.127102,53.259666],"type":"Point"}
}