{
  "type": "Feature",
  "properties": {
    "addr:full":"Unit 8, Princeton Mews Kingston-upon-thames Greater London KT2 6PT",
    "addr:housenumber":"unit 8",
    "addr:postcode":"kingston-upon-thames;kt2 6pt",
    "addr:street":"Princeton Mews",
    "iso:country":"GB",
    "sg:address":"Unit 8, Princeton Mews",
    "sg:city":"Kingston-upon-thames",
    "sg:classifiers":[
        {
            "category":"Professional",
            "subcategory":"Printing & Photocopies",
            "type":"Services"
        }
    ],
    "sg:postcode":"KT2 6PT",
    "sg:province":"Greater London",
    "sg:tags":[
        "top",
        "publishing",
        "desk"
    ],
    "wof:name":"Core Publishing Ltd.",
    "wof:placetype":"venue"
},
  "geometry": {"coordinates":[-0.289104,51.412659],"type":"Point"}
}