{
  "type": "Feature",
  "properties": {
    "addr:full":"16 Dawson Pl Bayswater Greater London W2 4TJ",
    "addr:housenumber":"16",
    "addr:postcode":"w2 4tj",
    "addr:street":"Dawson Pl",
    "iso:country":"GB",
    "sg:address":"16 Dawson Pl",
    "sg:city":"Bayswater",
    "sg:classifiers":[
        {
            "category":"Organizations",
            "subcategory":"Religious Organization",
            "type":"Services"
        }
    ],
    "sg:phone":"+44 20 7229 7059",
    "sg:postcode":"W2 4TJ",
    "sg:province":"Greater London",
    "sg:tags":[
        "organisation"
    ],
    "wof:name":"Verona Fathers The",
    "wof:placetype":"venue"
},
  "geometry": {"coordinates":[-0.196096,51.512291],"type":"Point"}
}