{
  "type": "Feature",
  "properties": {
    "addr:full":"21-22 Great Sutton St Clerkenwell Greater London EC1V 0DY",
    "addr:housenumber":"21-22",
    "addr:postcode":"ec1v 0dy",
    "addr:street":"Great Sutton St",
    "iso:country":"GB",
    "sg:address":"21-22 Great Sutton St",
    "sg:city":"Clerkenwell",
    "sg:classifiers":[
        {
            "category":"Professional",
            "subcategory":"Art Services",
            "type":"Services"
        }
    ],
    "sg:phone":"+44 20 7490 4440",
    "sg:postcode":"EC1V 0DY",
    "sg:province":"Greater London",
    "sg:tags":[
        "graphic",
        "designer"
    ],
    "wof:name":"Complete Group",
    "wof:placetype":"venue"
},
  "geometry": {"coordinates":[-0.100658,51.523216],"type":"Point"}
}