{
  "type": "Feature",
  "properties": {
    "iso:country":"GB",
    "sg:address":"2 Higher Mkt St",
    "sg:city":"Bolton",
    "sg:classifiers":[
        {
            "category":"Home & Garden",
            "subcategory":"Household Appliances",
            "type":"Retail Goods"
        }
    ],
    "sg:postcode":"BL4 9AJ",
    "sg:province":"Lancashire",
    "sg:tags":[
        "domestic",
        "centre"
    ],
    "wof:name":"Sellars,L G,",
    "wof:placetype":"venue"
},
  "geometry": {"coordinates":[-2.392239,53.547112],"type":"Point"}
}