{
  "type": "Feature",
  "properties": {
    "iso:country":"GB",
    "sg:address":"14 Muirton Rd",
    "sg:city":"Stirling",
    "sg:classifiers":[
        {
            "category":"Retail",
            "subcategory":"Car Wash",
            "type":"Services"
        },
        {
            "category":"Retail",
            "subcategory":"Auto Repair",
            "type":"Services"
        }
    ],
    "sg:phone":"+44 1786 479479",
    "sg:postcode":"FK7 7LJ",
    "sg:province":"Falkirk",
    "sg:tags":[
        "specialist",
        "sunroof",
        "customizing"
    ],
    "wof:name":"A K Mobile Sunroofs",
    "wof:placetype":"venue"
},
  "geometry": {"coordinates":[-3.9056420326,56.1088027954],"type":"Point"}
}