{
  "type": "Feature",
  "properties": {
    "addr:full":"35 Chapel Road Worthing West Sussex BN11 3DE",
    "addr:housenumber":"35",
    "addr:postcode":"bn11 3de",
    "addr:street":"Chapel Road",
    "iso:country":"GB",
    "sg:address":"35 Chapel Road",
    "sg:city":"Worthing",
    "sg:classifiers":[
        {
            "category":"Communications",
            "subcategory":"Newspaper",
            "type":"Services"
        }
    ],
    "sg:phone":"+44 1903 213311",
    "sg:postcode":"BN11 3DE",
    "sg:province":"West Sussex",
    "sg:tags":[
        "magazine"
    ],
    "wof:name":"The Evening Argus",
    "wof:placetype":"venue"
},
  "geometry": {"coordinates":[-0.3705160022,50.8123626709],"type":"Point"}
}