{
  "type": "Feature",
  "properties": {
    "addr:full":"Unit 7/9 Titan Business Centre, Spartan Close, Tachbrook Park Warwick Warwickshire CV34 6RR",
    "addr:housenumber":"unit 7 / 9",
    "addr:postcode":"cv34 6rr",
    "addr:street":"Spartan Close Tachbrook Park",
    "iso:country":"GB",
    "sg:address":"Unit 7/9 Titan Business Centre, Spartan Close, Tachbrook Park",
    "sg:city":"Warwick",
    "sg:classifiers":[
        {
            "category":"Manufacturing",
            "subcategory":"Signs",
            "type":"Manufacturing & Wholesale Goods"
        }
    ],
    "sg:phone":"+44 1926 452600",
    "sg:postcode":"CV34 6RR",
    "sg:province":"Warwickshire",
    "sg:tags":[
        "nameplate"
    ],
    "wof:name":"Gemco Signs",
    "wof:placetype":"venue"
},
  "geometry": {"coordinates":[-1.545272,52.27655],"type":"Point"}
}