{
  "type": "Feature",
  "properties": {
    "iso:country":"GB",
    "sg:address":"7 Brewery Lane",
    "sg:city":"Dundee",
    "sg:classifiers":[
        {
            "category":"Utilities",
            "subcategory":"Fuel Oil & Lpg",
            "type":"Services"
        }
    ],
    "sg:phone":"+44 1382 228778",
    "sg:postcode":"DD1 5QW",
    "sg:province":"Dundee City",
    "sg:tags":[
        "merchant",
        "coal",
        "smokeless"
    ],
    "wof:name":"TOM MARTIN & SONS",
    "wof:placetype":"venue"
},
  "geometry": {"coordinates":[-2.9890089035,56.4623985291],"type":"Point"}
}