{
  "type": "Feature",
  "properties": {
    "iso:country":"GB",
    "sg:address":"Carpenters Road, St Helens",
    "sg:city":"Ryde",
    "sg:classifiers":[
        {
            "category":"Manufacturing",
            "subcategory":"Metals",
            "type":"Manufacturing & Wholesale Goods"
        },
        {
            "category":"Building & Trades",
            "subcategory":"Construction",
            "type":"Services"
        }
    ],
    "sg:phone":"+44 1983 872965",
    "sg:postcode":"PO33 1YW",
    "sg:province":"Isle of Wight",
    "sg:tags":[
        "steel",
        "fabricator",
        "erectors",
        "welding"
    ],
    "wof:name":"A & R Welding",
    "wof:placetype":"venue"
},
  "geometry": {"coordinates":[-1.1163719893,50.6968154907],"type":"Point"}
}