{
  "type": "Feature",
  "properties": {
    "addr:full":"11 Edenvale Terrace, Springfield Cupar Fife KY15 5SB",
    "addr:housenumber":"11",
    "addr:postcode":"ky15 5sb",
    "addr:street":"Edenvale Terrace",
    "iso:country":"GB",
    "sg:address":"11 Edenvale Terrace, Springfield",
    "sg:city":"Cupar",
    "sg:classifiers":[
        {
            "category":"Shopping",
            "subcategory":"News",
            "type":"Retail Goods"
        }
    ],
    "sg:phone":"+44 1334 652283",
    "sg:postcode":"KY15 5SB",
    "sg:province":"Fife",
    "sg:tags":[
        "newsagent"
    ],
    "wof:name":"Springfield Stores",
    "wof:placetype":"venue"
},
  "geometry": {"coordinates":[-3.0355870724,56.3077163696],"type":"Point"}
}