{
  "type": "Feature",
  "properties": {
    "addr:full":"Sheriff Court House, Low Street Banff Aberdeenshire AB45 1AU",
    "addr:postcode":"ab45 1au",
    "addr:street":"Sheriff;Low Street",
    "iso:country":"GB",
    "sg:address":"Sheriff Court House, Low Street",
    "sg:city":"Banff",
    "sg:classifiers":[
        {
            "category":"Government",
            "subcategory":"Court House",
            "type":"Public Place"
        }
    ],
    "sg:phone":"+44 1261 812140",
    "sg:postcode":"AB45 1AU",
    "sg:province":"Aberdeenshire",
    "wof:name":"Sheriff Clerks Office",
    "wof:placetype":"venue"
},
  "geometry": {"coordinates":[-2.521859,57.664677],"type":"Point"}
}