{
  "type": "Feature",
  "properties": {
    "addr:full":"14 High Street Sheringham Norfolk NR26 8JR",
    "addr:housenumber":"14",
    "addr:postcode":"nr26 8jr",
    "addr:street":"High Street",
    "iso:country":"GB",
    "sg:address":"14 High Street",
    "sg:city":"Sheringham",
    "sg:classifiers":[
        {
            "category":"Food & Beverages",
            "subcategory":"Candy",
            "type":"Retail Goods"
        }
    ],
    "sg:postcode":"NR26 8JR",
    "sg:province":"Norfolk",
    "sg:tags":[
        "confectioner"
    ],
    "wof:name":"The Sweet Shop",
    "wof:placetype":"venue"
},
  "geometry": {"coordinates":[1.212073,52.94474],"type":"Point"}
}