{
  "type": "Feature",
  "properties": {
    "addr:full":"Old Bank Chambers, 2 Old Bank Street Manchester Greater Manchester M2 7PF",
    "addr:housenumber":"2",
    "addr:postcode":"m2 7pf",
    "addr:street":"Old Bank Street",
    "iso:country":"GB",
    "sg:address":"Old Bank Chambers, 2 Old Bank Street",
    "sg:city":"Manchester",
    "sg:classifiers":[
        {
            "category":"Real Estate",
            "subcategory":"Architect",
            "type":"Services"
        }
    ],
    "sg:phone":"+44 161 833 9345",
    "sg:postcode":"M2 7PF",
    "sg:province":"Greater Manchester",
    "wof:name":"Warburton Associates Design & Management Ltd.",
    "wof:placetype":"venue"
},
  "geometry": {"coordinates":[-2.2450499535,53.4821510315],"type":"Point"}
}