{
  "type": "Feature",
  "properties": {
    "iso:country":"GB",
    "sg:address":"69 The Parade, Kingshurst",
    "sg:city":"Birmingham",
    "sg:classifiers":[
        {
            "category":"Government",
            "subcategory":"Post Office",
            "type":"Public Place"
        }
    ],
    "sg:phone":"+44 121 770 3024",
    "sg:postcode":"B37 6BB",
    "sg:province":"West Midlands",
    "wof:name":"Kingshurst Sub Post Office",
    "wof:placetype":"venue"
},
  "geometry": {"coordinates":[-1.7502089739,52.4935035706],"type":"Point"}
}