{
  "type": "Feature",
  "properties": {
    "iso:country":"GB",
    "sg:address":"220 Oakbrook Road",
    "sg:city":"Sheffield",
    "sg:classifiers":[
        {
            "category":"Restaurant",
            "type":"Food & Drink"
        }
    ],
    "sg:phone":"+44 114 230 4819",
    "sg:postcode":"S11 7ED",
    "sg:province":"Derbyshire",
    "wof:name":"Rafters Restaurant",
    "wof:placetype":"venue"
},
  "geometry": {"coordinates":[-1.524757,53.368412],"type":"Point"}
}