{
  "type": "Feature",
  "properties": {
    "addr:full":"75 Redshank Lane Warrington Cheshire WA3 6RA",
    "addr:housenumber":"75",
    "addr:postcode":"wa3 6ra",
    "addr:street":"Redshank Lane",
    "iso:country":"GB",
    "sg:address":"75 Redshank Lane",
    "sg:city":"Warrington",
    "sg:classifiers":[
        {
            "category":"Building & Trades",
            "subcategory":"Plumbing",
            "type":"Services"
        }
    ],
    "sg:phone":"+44 1925 824718",
    "sg:postcode":"WA3 6RA",
    "sg:province":"Cheshire",
    "sg:tags":[
        "central",
        "heating"
    ],
    "wof:name":"B G Gas",
    "wof:placetype":"venue"
},
  "geometry": {"coordinates":[-2.5163259506,53.4207572937],"type":"Point"}
}