{
  "type": "Feature",
  "properties": {
    "iso:country":"GB",
    "sg:address":"91 Garstang Road",
    "sg:city":"Preston",
    "sg:classifiers":[
        {
            "category":"Professional",
            "subcategory":"Art Services",
            "type":"Services"
        }
    ],
    "sg:postcode":"PR1 1LD",
    "sg:province":"Lancashire",
    "sg:tags":[
        "graphic",
        "designer"
    ],
    "wof:name":"Forepoint Ltd.",
    "wof:placetype":"venue"
},
  "geometry": {"coordinates":[-2.7066309452,53.773109436],"type":"Point"}
}