{
  "type": "Feature",
  "properties": {
    "addr:full":"56 Doods Park Road Reigate Surrey RH2 0QD",
    "addr:housenumber":"56",
    "addr:postcode":"rh2 0qd",
    "addr:street":"Doods Park Road",
    "iso:country":"GB",
    "sg:address":"56 Doods Park Road",
    "sg:city":"Reigate",
    "sg:classifiers":[
        {
            "category":"Home & Garden",
            "subcategory":"Building Materials",
            "type":"Retail Goods"
        },
        {
            "category":"Building & Trades",
            "subcategory":"Construction",
            "type":"Services"
        }
    ],
    "sg:postcode":"RH2 0QD",
    "sg:province":"Surrey",
    "sg:tags":[
        "fencing",
        "contractor"
    ],
    "wof:name":"Cliff Fencing Co.",
    "wof:placetype":"venue"
},
  "geometry": {"coordinates":[-0.193803,51.239826],"type":"Point"}
}