{
  "type": "Feature",
  "properties": {
    "addr:full":"Unit 18 North Ellen Street Dundee Dundee City DD3 7DH",
    "addr:housenumber":"unit 18",
    "addr:postcode":"dd3 7dh",
    "addr:street":"North Ellen Street",
    "iso:country":"GB",
    "sg:address":"Unit 18 North Ellen Street",
    "sg:city":"Dundee",
    "sg:classifiers":[
        {
            "category":"Social Services",
            "subcategory":"Adult Care",
            "type":"Services"
        },
        {
            "category":"Wholesale",
            "subcategory":"Home Furnishings",
            "type":"Manufacturing & Wholesale Goods"
        }
    ],
    "sg:phone":"+44 1382 202657",
    "sg:postcode":"DD3 7DH",
    "sg:province":"Dundee City",
    "sg:tags":[
        "merchant",
        "decorator",
        "decorators'"
    ],
    "wof:name":"G B Decorators Merchants",
    "wof:placetype":"venue"
},
  "geometry": {"coordinates":[-2.9692139626,56.4705963135],"type":"Point"}
}