{
  "type": "Feature",
  "properties": {
    "iso:country":"GB",
    "sg:address":"39 Gilmour Rd",
    "sg:city":"Edinburgh",
    "sg:classifiers":[
        {
            "category":"Professional",
            "subcategory":"Management & Consulting",
            "type":"Services"
        }
    ],
    "sg:phone":"+44 131 667 2277",
    "sg:postcode":"EH16 5NS",
    "sg:province":"City of Edinburgh",
    "sg:tags":[
        "consultant",
        "business"
    ],
    "wof:name":"Brenda White Associates",
    "wof:placetype":"venue"
},
  "geometry": {"coordinates":[-3.165689,55.936321],"type":"Point"}
}