{
  "type": "Feature",
  "properties": {
    "addr:full":"2 Carlisle Avenue, Rufford Park Leeds West Yorkshire LS19 7RA",
    "addr:housenumber":"2",
    "addr:postcode":"ls19 7ra",
    "addr:street":"Carlisle Avenue",
    "iso:country":"GB",
    "sg:address":"2 Carlisle Avenue, Rufford Park",
    "sg:city":"Leeds",
    "sg:classifiers":[
        {
            "category":"Building & Trades",
            "subcategory":"Construction",
            "type":"Services"
        }
    ],
    "sg:postcode":"LS19 7RA",
    "sg:province":"West Yorkshire",
    "sg:tags":[
        "builder"
    ],
    "wof:name":"D C & E A Smith",
    "wof:placetype":"venue"
},
  "geometry": {"coordinates":[-1.67872,53.860706],"type":"Point"}
}