{
  "type": "Feature",
  "properties": {
    "iso:country":"GB",
    "sg:address":"24 Walnut Way, Hyde Heath",
    "sg:city":"Amersham",
    "sg:classifiers":[
        {
            "category":"Social Services",
            "subcategory":"Job Training",
            "type":"Services"
        },
        {
            "category":"Education",
            "subcategory":"Special Training",
            "type":"Public Place"
        }
    ],
    "sg:postcode":"HP6 5SB",
    "sg:province":"Buckinghamshire",
    "sg:tags":[
        "translator",
        "interpreter",
        "school",
        "language"
    ],
    "wof:name":"Language Link U K",
    "wof:placetype":"venue"
},
  "geometry": {"coordinates":[-0.648297,51.69017],"type":"Point"}
}