{
  "type": "Feature",
  "properties": {
    "addr:full":"Isington Rd, Isington Alton Hampshire GU34 4PP",
    "addr:postcode":"gu34 4pp",
    "addr:street":"Isington Rd",
    "iso:country":"GB",
    "sg:address":"Isington Rd, Isington",
    "sg:city":"Alton",
    "sg:classifiers":[
        {
            "category":"Home & Garden",
            "subcategory":"Home Furnishings",
            "type":"Retail Goods"
        }
    ],
    "sg:phone":"+44 1420 520445",
    "sg:postcode":"GU34 4PP",
    "sg:province":"Hampshire",
    "sg:tags":[
        "homefurnishings"
    ],
    "wof:name":"Tim Ram Design",
    "wof:placetype":"venue"
},
  "geometry": {"coordinates":[-0.8931589723,51.177154541],"type":"Point"}
}