{
  "type": "Feature",
  "properties": {
    "addr:full":"Panatta House, 71 Kingsway North, Teamvalley Trading Estate Gateshead Tyne and Wear NE11 0JH",
    "addr:housenumber":"71",
    "addr:postcode":"ne11 0jh",
    "addr:street":"Kingsway North Teamvalley Trading Estate",
    "iso:country":"GB",
    "sg:address":"Panatta House, 71 Kingsway North, Teamvalley Trading Estate",
    "sg:city":"Gateshead",
    "sg:classifiers":[
        {
            "category":"Sports & Exercise",
            "subcategory":"Gym",
            "type":"Entertainment"
        }
    ],
    "sg:phone":"+44 191 487 4874",
    "sg:postcode":"NE11 0JH",
    "sg:province":"Tyne and Wear",
    "sg:tags":[
        "fitness",
        "health",
        "centre"
    ],
    "wof:name":"Kingsway Leisure Clubs Group Ltd.",
    "wof:placetype":"venue"
},
  "geometry": {"coordinates":[-1.62169,54.938438],"type":"Point"}
}