{
  "type": "Feature",
  "properties": {
    "iso:country":"GB",
    "sg:address":"6 Arundel Court",
    "sg:city":"Arundel",
    "sg:classifiers":[
        {
            "category":"Professional",
            "subcategory":"Detective & Security Services",
            "type":"Services"
        }
    ],
    "sg:postcode":"BN43 6LR",
    "sg:province":"West Sussex",
    "wof:name":"Panther Private Security Ltd",
    "wof:placetype":"venue"
},
  "geometry": {"coordinates":[-0.250169009,50.8375511169],"type":"Point"}
}