{
  "type": "Feature",
  "properties": {
    "iso:country":"GB",
    "sg:address":"288 Upper Richmond Road",
    "sg:city":"London",
    "sg:classifiers":[
        {
            "category":"Shopping",
            "subcategory":"Thrift Store",
            "type":"Retail Goods"
        }
    ],
    "sg:phone":"+44 20 8788 5763",
    "sg:postcode":"SW15 6TH",
    "sg:province":"Greater London",
    "sg:tags":[
        "shop",
        "charity"
    ],
    "wof:name":"The Charity Shop",
    "wof:placetype":"venue"
},
  "geometry": {"coordinates":[-0.22109,51.462006],"type":"Point"}
}