{
  "type": "Feature",
  "properties": {
    "addr:full":"1 Holdenhurst Road Bournemouth Dorset BH8 8EH",
    "addr:housenumber":"1",
    "addr:postcode":"bh8 8eh",
    "addr:street":"Holdenhurst Road",
    "iso:country":"GB",
    "sg:address":"1 Holdenhurst Road",
    "sg:city":"Bournemouth",
    "sg:classifiers":[
        {
            "category":"Professional",
            "subcategory":"Employment Agencies",
            "type":"Services"
        }
    ],
    "sg:phone":"+44 1202 296888",
    "sg:postcode":"BH8 8EH",
    "sg:province":"Dorset",
    "sg:tags":[
        "consultant"
    ],
    "wof:name":"M B C (Motherwell Bridge)",
    "wof:placetype":"venue"
},
  "geometry": {"coordinates":[-1.866184,50.722469],"type":"Point"}
}