{
  "type": "Feature",
  "properties": {
    "addr:full":"99 Wood St Walthamstow Greater London E17 3LL",
    "addr:housenumber":"99",
    "addr:postcode":"e17 3ll",
    "addr:street":"Wood St",
    "iso:country":"GB",
    "sg:address":"99 Wood St",
    "sg:city":"Walthamstow",
    "sg:classifiers":[
        {
            "category":"Retail",
            "subcategory":"Funeral Services",
            "type":"Services"
        }
    ],
    "sg:phone":"+44 20 8520 4166",
    "sg:postcode":"E17 3LL",
    "sg:province":"Greater London",
    "wof:name":"George White & Son",
    "wof:placetype":"venue"
},
  "geometry": {"coordinates":[-0.004038,51.588726],"type":"Point"}
}