{
  "type": "Feature",
  "properties": {
    "addr:full":"300 Barton St Gloucester Gloucestershire GL1 4JJ",
    "addr:housenumber":"300",
    "addr:postcode":"gl1 4jj",
    "addr:street":"Barton St",
    "iso:country":"GB",
    "sg:address":"300 Barton St",
    "sg:city":"Gloucester",
    "sg:classifiers":[
        {
            "category":"Shopping",
            "subcategory":"Used Merchandise",
            "type":"Retail Goods"
        }
    ],
    "sg:phone":"+44 1452 304396",
    "sg:postcode":"GL1 4JJ",
    "sg:province":"Gloucestershire",
    "sg:tags":[
        "shop",
        "second-hand"
    ],
    "wof:name":"Second Time Around",
    "wof:placetype":"venue"
},
  "geometry": {"coordinates":[-2.2315909863,51.8566818237],"type":"Point"}
}