{
  "type": "Feature",
  "properties": {
    "iso:country":"GB",
    "sg:address":"5-6 Tower Quays, Tower Rd",
    "sg:city":"Birkenhead",
    "sg:classifiers":[
        {
            "category":"Professional",
            "subcategory":"Engineering",
            "type":"Services"
        }
    ],
    "sg:phone":"+44 151 647 7133",
    "sg:postcode":"L41 1BP",
    "sg:province":"Merseyside",
    "sg:tags":[
        "civil",
        "engineer"
    ],
    "wof:name":"F R C Ltd",
    "wof:placetype":"venue"
},
  "geometry": {"coordinates":[-3.02549,53.392559],"type":"Point"}
}