{
  "type": "Feature",
  "properties": {
    "iso:country":"GB",
    "sg:address":"5 Market Square",
    "sg:city":"Rugeley",
    "sg:classifiers":[
        {
            "category":"Professional",
            "subcategory":"Computer Services",
            "type":"Services"
        }
    ],
    "sg:phone":"+44 1889 579002",
    "sg:postcode":"WS15 2BL",
    "sg:province":"Staffordshire",
    "sg:tags":[
        "system",
        "software"
    ],
    "wof:name":"C T I",
    "wof:placetype":"venue"
},
  "geometry": {"coordinates":[-1.934448,52.761169],"type":"Point"}
}