{
  "type": "Feature",
  "properties": {
    "iso:country":"GB",
    "sg:address":"Toseland Road, Graveley",
    "sg:city":"Huntingdon",
    "sg:classifiers":[
        {
            "category":"Retail",
            "subcategory":"Auto Repair",
            "type":"Services"
        }
    ],
    "sg:phone":"+44 1480 831821",
    "sg:postcode":"PE19 6PS",
    "sg:province":"Bedfordshire",
    "sg:tags":[
        "bodybuilder",
        "repairer"
    ],
    "wof:name":"Advantage Contracts Ltd.",
    "wof:placetype":"venue"
},
  "geometry": {"coordinates":[-0.177025,52.258476],"type":"Point"}
}