{
  "type": "Feature",
  "properties": {
    "iso:country":"GB",
    "sg:address":"Mulberry Farm, Ashfield Road, Elmswell",
    "sg:city":"Bury St Edmunds",
    "sg:classifiers":[
        {
            "category":"Retail",
            "subcategory":"Repair Shop",
            "type":"Services"
        }
    ],
    "sg:postcode":"IP30 9HG",
    "sg:province":"Suffolk",
    "sg:tags":[
        "furniture"
    ],
    "wof:name":"Woodside Restoration Services",
    "wof:placetype":"venue"
},
  "geometry": {"coordinates":[0.91154,52.23711],"type":"Point"}
}