{
  "type": "Feature",
  "properties": {
    "addr:full":"117 Streetsbrook Rd Solihull West Midlands B90 3PF",
    "addr:housenumber":"117",
    "addr:postcode":"b90 3pf",
    "addr:street":"Streetsbrook Rd",
    "iso:country":"GB",
    "sg:address":"117 Streetsbrook Rd",
    "sg:city":"Solihull",
    "sg:classifiers":[
        {
            "category":"Building & Trades",
            "subcategory":"Construction",
            "type":"Services"
        }
    ],
    "sg:phone":"+44 121 744 1727",
    "sg:postcode":"B90 3PF",
    "sg:province":"West Midlands",
    "sg:tags":[
        "monumental",
        "mason"
    ],
    "wof:name":"Bannocks",
    "wof:placetype":"venue"
},
  "geometry": {"coordinates":[-1.820417,52.420818],"type":"Point"}
}