{
  "type": "Feature",
  "properties": {
    "iso:country":"GB",
    "sg:address":"23 Briarwood Avenue",
    "sg:city":"Bradford",
    "sg:classifiers":[
        {
            "category":"Building & Trades",
            "subcategory":"Cleaning & Sanitation",
            "type":"Services"
        }
    ],
    "sg:postcode":"BD6 1RX",
    "sg:province":"West Yorkshire",
    "sg:tags":[
        "commercial"
    ],
    "wof:name":"Multi Clean Services",
    "wof:placetype":"venue"
},
  "geometry": {"coordinates":[-1.7767499685,53.7699775696],"type":"Point"}
}