{
  "type": "Feature",
  "properties": {
    "addr:full":"14 Tomlinson Drive Wokingham Berkshire RG40 3NZ",
    "addr:housenumber":"14",
    "addr:postcode":"rg40 3nz",
    "addr:street":"Tomlinson Drive",
    "iso:country":"GB",
    "sg:address":"14 Tomlinson Drive",
    "sg:city":"Wokingham",
    "sg:classifiers":[
        {
            "category":"Real Estate",
            "subcategory":"Architect",
            "type":"Services"
        }
    ],
    "sg:postcode":"RG40 3NZ",
    "sg:province":"Berkshire",
    "sg:tags":[
        "architectural"
    ],
    "wof:name":"Harrall Design Associates",
    "wof:placetype":"venue"
},
  "geometry": {"coordinates":[-0.8448650241,51.3791465759],"type":"Point"}
}