{
  "type": "Feature",
  "properties": {
    "iso:country":"GB",
    "sg:address":"5 Valmont Road, Sherwood",
    "sg:city":"Nottingham",
    "sg:classifiers":[
        {
            "category":"Professional",
            "subcategory":"Computer Services",
            "type":"Services"
        }
    ],
    "sg:phone":"+44 115 985 8330",
    "sg:postcode":"NG5 1GA",
    "sg:province":"Nottinghamshire",
    "sg:tags":[
        "system",
        "software"
    ],
    "wof:name":"Glasscalc Ltd.",
    "wof:placetype":"venue"
},
  "geometry": {"coordinates":[-1.159774,52.985947],"type":"Point"}
}