{
  "type": "Feature",
  "properties": {
    "addr:full":"1 Burley Rd Leeds West Yorkshire LS3 1JZ",
    "addr:housenumber":"1",
    "addr:postcode":"ls3 1jz",
    "addr:street":"Burley Rd",
    "iso:country":"GB",
    "sg:address":"1 Burley Rd",
    "sg:city":"Leeds",
    "sg:classifiers":[
        {
            "category":"Building & Trades",
            "subcategory":"Construction",
            "type":"Services"
        }
    ],
    "sg:phone":"+44 113 246 1178",
    "sg:postcode":"LS3 1JZ",
    "sg:province":"West Yorkshire",
    "sg:tags":[
        "joinery"
    ],
    "wof:name":"Leeds Woodware Products Ltd",
    "wof:placetype":"venue"
},
  "geometry": {"coordinates":[-1.559194,53.800163],"type":"Point"}
}