{
  "type": "Feature",
  "properties": {
    "addr:full":"90 Polsloe Road Exeter Devon EX1 2HW",
    "addr:housenumber":"90",
    "addr:postcode":"ex1 2hw",
    "addr:street":"Polsloe Road",
    "iso:country":"GB",
    "sg:address":"90 Polsloe Road",
    "sg:city":"Exeter",
    "sg:classifiers":[
        {
            "category":"Social Services",
            "type":"Services"
        },
        {
            "category":"Social Services",
            "subcategory":"Child Care",
            "type":"Services"
        },
        {
            "category":"Government",
            "subcategory":"Office",
            "type":"Public Place"
        }
    ],
    "sg:phone":"+44 1392 423441",
    "sg:postcode":"EX1 2HW",
    "sg:province":"Devon",
    "sg:tags":[
        "local",
        "day",
        "centre"
    ],
    "wof:name":"Fairbanks Family Centre",
    "wof:placetype":"venue"
},
  "geometry": {"coordinates":[-3.514242,50.72963],"type":"Point"}
}