{
  "type": "Feature",
  "properties": {
    "iso:country":"GB",
    "sg:address":"145 Victoria Street",
    "sg:city":"St. Albans",
    "sg:classifiers":[
        {
            "category":"Manufacturing",
            "subcategory":"Tools & Machinery",
            "type":"Manufacturing & Wholesale Goods"
        }
    ],
    "sg:phone":"+44 1727 869298",
    "sg:postcode":"AL1 3TA",
    "sg:province":"Hertfordshire",
    "sg:tags":[
        "society",
        "friendly"
    ],
    "wof:name":"Trevor Callican",
    "wof:placetype":"venue"
},
  "geometry": {"coordinates":[-0.32885,51.750553],"type":"Point"}
}