{
  "type": "Feature",
  "properties": {
    "iso:country":"GB",
    "sg:address":"46 Thirlmere Avenue, Tilehurst",
    "sg:city":"Reading",
    "sg:classifiers":[
        {
            "category":"Parking",
            "type":"Transportation"
        }
    ],
    "sg:phone":"+44 118 942 6750",
    "sg:postcode":"RG30 6XN",
    "sg:province":"Berkshire",
    "sg:tags":[
        "car",
        "valet"
    ],
    "wof:name":"Kleen N Sheen",
    "wof:placetype":"venue"
},
  "geometry": {"coordinates":[-1.026846,51.466583],"type":"Point"}
}