{
  "type": "Feature",
  "properties": {
    "addr:full":"Unit2, The Old Malthouse, Norton Fitzwarren Taunton Somerset TA2 6RN",
    "addr:postcode":"ta2 6rn",
    "addr:street":"Norton Fitzwarren",
    "iso:country":"GB",
    "sg:address":"Unit2, The Old Malthouse, Norton Fitzwarren",
    "sg:city":"Taunton",
    "sg:classifiers":[
        {
            "category":"Building & Trades",
            "subcategory":"Construction",
            "type":"Services"
        }
    ],
    "sg:phone":"+44 1823 278269",
    "sg:postcode":"TA2 6RN",
    "sg:province":"Somerset",
    "sg:tags":[
        "joinery",
        "joiner",
        "carpenter",
        "carpentry"
    ],
    "wof:name":"Wyatt Joinery",
    "wof:placetype":"venue"
},
  "geometry": {"coordinates":[-3.14595,51.026958],"type":"Point"}
}