{
  "type": "Feature",
  "properties": {
    "addr:full":"14 West Street Alresford Hampshire SO24 9AT",
    "addr:housenumber":"14",
    "addr:postcode":"so24 9at",
    "addr:street":"West Street",
    "iso:country":"GB",
    "sg:address":"14 West Street",
    "sg:city":"Alresford",
    "sg:classifiers":[
        {
            "category":"Shopping",
            "subcategory":"Florist",
            "type":"Retail Goods"
        }
    ],
    "sg:phone":"+44 1962 735097",
    "sg:postcode":"SO24 9AT",
    "sg:province":"Hampshire",
    "wof:name":"Floral Design",
    "wof:placetype":"venue"
},
  "geometry": {"coordinates":[-1.1626009941,51.0904541016],"type":"Point"}
}