{
  "type": "Feature",
  "properties": {
    "addr:full":"Unit 12, The Market Place Blackwood Caerphilly NP12 1AU",
    "addr:housenumber":"unit 12",
    "addr:postcode":"np12 1au",
    "addr:street":"The Market Place",
    "iso:country":"GB",
    "sg:address":"Unit 12, The Market Place",
    "sg:city":"Blackwood",
    "sg:classifiers":[
        {
            "category":"Community Center",
            "subcategory":"Social",
            "type":"Public Place"
        }
    ],
    "sg:phone":"+44 1495 224479",
    "sg:postcode":"NP12 1AU",
    "sg:province":"Caerphilly",
    "sg:tags":[
        "frozen",
        "food",
        "freezer",
        "centre"
    ],
    "wof:name":"Iceland Foods Plc",
    "wof:placetype":"venue"
},
  "geometry": {"coordinates":[-3.1956489086,51.666595459],"type":"Point"}
}