{
  "type": "Feature",
  "properties": {
    "addr:full":"12-13 New Wharf Road London Greater London N1 9RT",
    "addr:housenumber":"12-13",
    "addr:postcode":"n1 9rt",
    "addr:street":"New Wharf Road",
    "iso:country":"GB",
    "sg:address":"12-13 New Wharf Road",
    "sg:city":"London",
    "sg:classifiers":[
        {
            "category":"Museum",
            "subcategory":"Art Museum",
            "type":"Entertainment"
        },
        {
            "category":"Museum",
            "type":"Entertainment"
        }
    ],
    "sg:phone":"+44 20 7713 0836",
    "sg:postcode":"N1 9RT",
    "sg:province":"Greater London",
    "sg:tags":[
        "gallery"
    ],
    "wof:name":"London Canal Museum",
    "wof:placetype":"venue"
},
  "geometry": {"coordinates":[-0.1201319993,51.5338821411],"type":"Point"}
}