{
  "type": "Feature",
  "properties": {
    "iso:country":"GB",
    "sg:address":"13 Gordon Street, Hopeman",
    "sg:city":"Elgin",
    "sg:classifiers":[
        {
            "category":"Building & Trades",
            "subcategory":"Construction",
            "type":"Services"
        }
    ],
    "sg:phone":"+44 1343 830035",
    "sg:postcode":"IV30 5SF",
    "sg:province":"Moray",
    "sg:tags":[
        "joiner",
        "carpenter"
    ],
    "wof:name":"J & J JOINERS",
    "wof:placetype":"venue"
},
  "geometry": {"coordinates":[-3.438373,57.70726],"type":"Point"}
}