{
  "type": "Feature",
  "properties": {
    "addr:full":"94 Banks Road, West Kirby Wirral Merseyside CH48 0RE",
    "addr:housenumber":"94",
    "addr:postcode":"ch48 0re",
    "addr:street":"Banks Road",
    "iso:country":"GB",
    "sg:address":"94 Banks Road, West Kirby",
    "sg:city":"Wirral",
    "sg:classifiers":[
        {
            "category":"Retail",
            "subcategory":"Laundry & Dry Cleaning",
            "type":"Services"
        }
    ],
    "sg:phone":"+44 151 625 2358",
    "sg:postcode":"CH48 0RE",
    "sg:province":"Merseyside",
    "sg:tags":[
        "alteration"
    ],
    "wof:name":"Macleans",
    "wof:placetype":"venue"
},
  "geometry": {"coordinates":[-3.184034,53.369892],"type":"Point"}
}