{
  "type": "Feature",
  "properties": {
    "addr:full":"Buck Farm, Buck Hill Braintree Essex CM77 8LA",
    "addr:postcode":"cm77 8la",
    "addr:street":"Buck",
    "iso:country":"GB",
    "sg:address":"Buck Farm, Buck Hill",
    "sg:city":"Braintree",
    "sg:classifiers":[
        {
            "category":"Professional",
            "subcategory":"Business Services",
            "type":"Services"
        }
    ],
    "sg:postcode":"CM77 8LA",
    "sg:province":"Essex",
    "sg:tags":[
        "import",
        "export",
        "agent"
    ],
    "wof:name":"Braintree Exports Ltd.",
    "wof:placetype":"venue"
},
  "geometry": {"coordinates":[0.5532420278,51.8777580261],"type":"Point"}
}