{
  "type": "Feature",
  "properties": {
    "addr:full":"Po Box 166 Northwood Greater London HA6 2FL",
    "addr:housenumber":"po",
    "addr:postcode":"ha6 2fl",
    "addr:street":"Box 166",
    "iso:country":"GB",
    "sg:address":"Po Box 166",
    "sg:city":"Northwood",
    "sg:classifiers":[
        {
            "category":"Wholesale",
            "subcategory":"Music Publishers",
            "type":"Manufacturing & Wholesale Goods"
        },
        {
            "category":"Wholesale",
            "subcategory":"Books, Periodicals, & Newspapers",
            "type":"Manufacturing & Wholesale Goods"
        }
    ],
    "sg:phone":"+44 1923 841645",
    "sg:postcode":"HA6 2FL",
    "sg:province":"Greater London",
    "sg:tags":[
        "publishing"
    ],
    "wof:name":"R W M Music",
    "wof:placetype":"venue"
},
  "geometry": {"coordinates":[-0.424186,51.611542],"type":"Point"}
}