{
  "type": "Feature",
  "properties": {
    "addr:full":"5 Market Square Horsham West Sussex RH12 1EU",
    "addr:housenumber":"5",
    "addr:postcode":"rh12 1eu",
    "addr:street":"Market Square",
    "iso:country":"GB",
    "sg:address":"5 Market Square",
    "sg:city":"Horsham",
    "sg:classifiers":[
        {
            "category":"Retail",
            "subcategory":"Funeral Services",
            "type":"Services"
        }
    ],
    "sg:postcode":"RH12 1EU",
    "sg:province":"West Sussex",
    "wof:name":"C & P Freeman",
    "wof:placetype":"venue"
},
  "geometry": {"coordinates":[-0.328911,51.061363],"type":"Point"}
}