{
  "type": "Feature",
  "properties": {
    "iso:country":"GB",
    "sg:address":"108 Main Street",
    "sg:city":"Ayr",
    "sg:classifiers":[
        {
            "category":"Shopping",
            "subcategory":"Florist",
            "type":"Retail Goods"
        }
    ],
    "sg:postcode":"KA8 8EF",
    "sg:province":"South Ayrshire",
    "wof:name":"Occasions",
    "wof:placetype":"venue"
},
  "geometry": {"coordinates":[-4.629644,55.468273],"type":"Point"}
}