{
  "type": "Feature",
  "properties": {
    "iso:country":"GB",
    "sg:address":"P O Box 94",
    "sg:city":"Whitley Bay",
    "sg:classifiers":[
        {
            "category":"Personal",
            "type":"Services"
        }
    ],
    "sg:phone":"+44 191 297 2080",
    "sg:postcode":"NE26 3YS",
    "sg:province":"Northumberland",
    "sg:tags":[
        "dating",
        "friendship",
        "agency"
    ],
    "wof:name":"Would Like to Meet Introductions",
    "wof:placetype":"venue"
},
  "geometry": {"coordinates":[-1.4494719505,55.0485420227],"type":"Point"}
}