{
  "type": "Feature",
  "properties": {
    "addr:full":"P O Box 94 Whitley Bay Northumberland NE26 3YS",
    "addr:housenumber":"box 94",
    "addr:postcode":"ne26 3ys",
    "addr:street":"P O",
    "iso:country":"GB",
    "sg:address":"P O Box 94",
    "sg:city":"Whitley Bay",
    "sg:classifiers":[
        {
            "category":"Personal",
            "type":"Services"
        }
    ],
    "sg:phone":"+44 191 297 2080",
    "sg:postcode":"NE26 3YS",
    "sg:province":"Northumberland",
    "sg:tags":[
        "dating",
        "friendship",
        "agency"
    ],
    "wof:name":"Would Like to Meet Introductions",
    "wof:placetype":"venue"
},
  "geometry": {"coordinates":[-1.4494719505,55.0485420227],"type":"Point"}
}