{
  "type": "Feature",
  "properties": {
    "addr:full":"Unit 4 Suffolk House, 127-129 Great Suffolk Street London Greater London SE1 1PP",
    "addr:housenumber":"unit 4;127-129",
    "addr:postcode":"se1 1pp",
    "addr:street":"Suffolk;Great Suffolk Street",
    "iso:country":"GB",
    "sg:address":"Unit 4 Suffolk House, 127-129 Great Suffolk Street",
    "sg:city":"London",
    "sg:classifiers":[
        {
            "category":"Farming",
            "subcategory":"Fish & Marine Products",
            "type":"Manufacturing & Wholesale Goods"
        }
    ],
    "sg:phone":"+44 20 7407 0247",
    "sg:postcode":"SE1 1PP",
    "sg:province":"Greater London",
    "sg:tags":[
        "fishmonger"
    ],
    "wof:name":"Aberdeen Sea Products Ltd.",
    "wof:placetype":"venue"
},
  "geometry": {"coordinates":[-0.0968400016,51.5004081726],"type":"Point"}
}