{
  "type": "Feature",
  "properties": {
    "addr:full":"Cobbs Hill Farm Caravan Park, Watermill Lane Bexhill-on-sea East Sussex TN39 5JA",
    "addr:postcode":"tn39 5ja",
    "addr:street":"Watermill Lane",
    "iso:country":"GB",
    "sg:address":"Cobbs Hill Farm Caravan Park, Watermill Lane",
    "sg:city":"Bexhill-on-sea",
    "sg:classifiers":[
        {
            "category":"Recreation",
            "subcategory":"Campground",
            "type":"Entertainment"
        }
    ],
    "sg:phone":"+44 1424 213460",
    "sg:postcode":"TN39 5JA",
    "sg:province":"East Sussex",
    "sg:tags":[
        "caravan",
        "park"
    ],
    "wof:name":"Cobbs Hill Farm Caravan Park",
    "wof:placetype":"venue"
},
  "geometry": {"coordinates":[0.46571,50.860214],"type":"Point"}
}