{
  "type": "Feature",
  "properties": {
    "iso:country":"GB",
    "sg:address":"23 St Andrews Meadow",
    "sg:city":"Harlow",
    "sg:classifiers":[
        {
            "category":"Building & Trades",
            "subcategory":"Construction",
            "type":"Services"
        }
    ],
    "sg:phone":"+44 1279 420334",
    "sg:postcode":"CM18 6BL",
    "sg:province":"Essex",
    "sg:tags":[
        "builder"
    ],
    "wof:name":"Terry Andrews",
    "wof:placetype":"venue"
},
  "geometry": {"coordinates":[0.109615,51.764301],"type":"Point"}
}