{
  "type": "Feature",
  "properties": {
    "addr:full":"23 Offham Slope London Greater London N12 7BZ",
    "addr:housenumber":"23",
    "addr:postcode":"n12 7bz",
    "addr:street":"Offham",
    "iso:country":"GB",
    "sg:address":"23 Offham Slope",
    "sg:city":"London",
    "sg:classifiers":[
        {
            "category":"Professional",
            "subcategory":"Lawyer & Legal Services",
            "type":"Services"
        }
    ],
    "sg:phone":"+44 20 8445 4069",
    "sg:postcode":"N12 7BZ",
    "sg:province":"Greater London",
    "sg:tags":[
        "solicitor"
    ],
    "wof:name":"Kaura & Co",
    "wof:placetype":"venue"
},
  "geometry": {"coordinates":[-0.1984229982,51.6154937744],"type":"Point"}
}