{
  "type": "Feature",
  "properties": {
    "iso:country":"GB",
    "sg:address":"Holmwood, Mayfield Avenue, New Haw",
    "sg:city":"Addlestone",
    "sg:classifiers":[
        {
            "category":"Building & Trades",
            "subcategory":"Cleaning & Sanitation",
            "type":"Services"
        }
    ],
    "sg:phone":"+44 1932 342134",
    "sg:postcode":"KT15 3AG",
    "sg:province":"Surrey",
    "sg:tags":[
        "sweep",
        "chimney"
    ],
    "wof:name":"F H FRANKLIN",
    "wof:placetype":"venue"
},
  "geometry": {"coordinates":[-0.485241,51.356892],"type":"Point"}
}