{
  "type": "Feature",
  "properties": {
    "iso:country":"GB",
    "sg:address":"The Court, Kirket La",
    "sg:city":"Wirral",
    "sg:classifiers":[
        {
            "category":"Social Services",
            "subcategory":"Adult Care",
            "type":"Services"
        }
    ],
    "sg:phone":"+44 151 645 8704",
    "sg:postcode":"CH63 3HX",
    "sg:province":"Merseyside",
    "sg:tags":[
        "housing",
        "sheltered"
    ],
    "wof:name":"Bebington Old Peoples Housing Association Ltd",
    "wof:placetype":"venue"
},
  "geometry": {"coordinates":[-3.005859,53.347923],"type":"Point"}
}