{
  "type": "Feature",
  "properties": {
    "addr:full":"Temeside Ludlow Herefordshire SY8 1JW",
    "addr:postcode":"sy8 1jw",
    "addr:street":"Temeside",
    "iso:country":"GB",
    "sg:address":"Temeside",
    "sg:city":"Ludlow",
    "sg:classifiers":[
        {
            "category":"Building & Trades",
            "subcategory":"Construction",
            "type":"Services"
        }
    ],
    "sg:phone":"+44 1584 872161",
    "sg:postcode":"SY8 1JW",
    "sg:province":"Herefordshire",
    "sg:tags":[
        "builder"
    ],
    "wof:name":"Treasure & Son Ltd.",
    "wof:placetype":"venue"
},
  "geometry": {"coordinates":[-2.70948,52.364891],"type":"Point"}
}