{
  "type": "Feature",
  "properties": {
    "addr:full":"C/o Jpc Financial Ltd, Dukes Court, Duke Street Woking Surrey GU21 5BH",
    "addr:postcode":"gu21 5bh",
    "addr:street":"C / O Jpc;Dukes;Duke Street",
    "iso:country":"GB",
    "sg:address":"C/o Jpc Financial Ltd, Dukes Court, Duke Street",
    "sg:city":"Woking",
    "sg:classifiers":[
        {
            "category":"Professional",
            "subcategory":"Computer Services",
            "type":"Services"
        }
    ],
    "sg:postcode":"GU21 5BH",
    "sg:province":"Surrey",
    "sg:tags":[
        "system",
        "software"
    ],
    "wof:name":"Keyedit Programming Ltd",
    "wof:placetype":"venue"
},
  "geometry": {"coordinates":[-0.5550640225,51.3205757141],"type":"Point"}
}