{
  "type": "Feature",
  "properties": {
    "addr:full":"43 Rooke St Newport Isle of Wight PO30 5PR",
    "addr:housenumber":"43",
    "addr:postcode":"po30 5pr",
    "addr:street":"Rooke St",
    "iso:country":"GB",
    "sg:address":"43 Rooke St",
    "sg:city":"Newport",
    "sg:classifiers":[
        {
            "category":"Retail",
            "subcategory":"Repair Shop",
            "type":"Services"
        }
    ],
    "sg:phone":"+44 7976 668870",
    "sg:postcode":"PO30 5PR",
    "sg:province":"Isle of Wight",
    "sg:tags":[
        "radio",
        "television",
        "video"
    ],
    "wof:name":"MS Electronic Servicing",
    "wof:placetype":"venue"
},
  "geometry": {"coordinates":[-1.3079440594,50.7174911499],"type":"Point"}
}