{
  "type": "Feature",
  "properties": {
    "addr:full":"53 Sussex Way London Greater London N7 6RT",
    "addr:housenumber":"53",
    "addr:postcode":"n7 6rt",
    "addr:street":"Sussex Way",
    "iso:country":"GB",
    "sg:address":"53 Sussex Way",
    "sg:city":"London",
    "sg:classifiers":[
        {
            "category":"Professional",
            "subcategory":"Computer Services",
            "type":"Services"
        }
    ],
    "sg:postcode":"N7 6RT",
    "sg:province":"Greater London",
    "sg:tags":[
        "consultant"
    ],
    "wof:name":"Fer Da Lance Support Ltd.",
    "wof:placetype":"venue"
},
  "geometry": {"coordinates":[-0.1170490012,51.5611305237],"type":"Point"}
}