{
  "type": "Feature",
  "properties": {
    "iso:country":"GB",
    "sg:address":"23 Bridge Street",
    "sg:city":"Aberdeen",
    "sg:classifiers":[
        {
            "category":"Personal",
            "subcategory":"Nail Salon",
            "type":"Services"
        }
    ],
    "sg:phone":"+44 1224 590404",
    "sg:postcode":"AB11 6JL",
    "sg:province":"Aberdeen City",
    "sg:tags":[
        "solarium",
        "tanning"
    ],
    "wof:name":"The Sun Shop",
    "wof:placetype":"venue"
},
  "geometry": {"coordinates":[-2.1012721062,57.1449279785],"type":"Point"}
}