{
  "type": "Feature",
  "properties": {
    "iso:country":"GB",
    "sg:address":"482 Fairfax Drive",
    "sg:city":"Westcliff-on-sea",
    "sg:classifiers":[
        {
            "category":"Shopping",
            "subcategory":"Crafts & Fabrics",
            "type":"Retail Goods"
        }
    ],
    "sg:postcode":"SS0 9RN",
    "sg:province":"Essex",
    "sg:tags":[
        "shop",
        "needlecraft",
        "wool"
    ],
    "wof:name":"Cotton & Things",
    "wof:placetype":"venue"
},
  "geometry": {"coordinates":[0.6811670065,51.5509376526],"type":"Point"}
}