{
  "type": "Feature",
  "properties": {
    "iso:country":"GB",
    "sg:address":"Armstrong Street",
    "sg:city":"Grimsby",
    "sg:classifiers":[
        {
            "category":"Autos & Motor Vehicles",
            "subcategory":"Auto Supplies",
            "type":"Retail Goods"
        }
    ],
    "sg:phone":"+44 1472 359096",
    "sg:postcode":"DN31 3AA",
    "sg:province":"Lincolnshire",
    "sg:tags":[
        "component"
    ],
    "wof:name":"Brown Bros",
    "wof:placetype":"venue"
},
  "geometry": {"coordinates":[-0.092734,53.572487],"type":"Point"}
}