{
  "type": "Feature",
  "properties": {
    "addr:full":"133 Sunrise Avenue Chelmsford Essex CM1 4JW",
    "addr:housenumber":"133",
    "addr:postcode":"cm1 4jw",
    "addr:street":"Sunrise Avenue",
    "iso:country":"GB",
    "sg:address":"133 Sunrise Avenue",
    "sg:city":"Chelmsford",
    "sg:classifiers":[
        {
            "category":"Shopping",
            "subcategory":"Pharmacy",
            "type":"Retail Goods"
        }
    ],
    "sg:phone":"+44 1245 281350",
    "sg:postcode":"CM1 4JW",
    "sg:province":"Essex",
    "sg:tags":[
        "pharmacist",
        "chemist"
    ],
    "wof:name":"Chemys Chemist",
    "wof:placetype":"venue"
},
  "geometry": {"coordinates":[0.463537991,51.7476463318],"type":"Point"}
}