{
  "type": "Feature",
  "properties": {
    "addr:full":"34 Waltham Crescent Nuneaton Leicestershire CV10 9JG",
    "addr:housenumber":"34",
    "addr:postcode":"cv10 9jg",
    "addr:street":"Waltham Crescent",
    "iso:country":"GB",
    "sg:address":"34 Waltham Crescent",
    "sg:city":"Nuneaton",
    "sg:classifiers":[
        {
            "category":"Professional",
            "subcategory":"Management & Consulting",
            "type":"Services"
        }
    ],
    "sg:postcode":"CV10 9JG",
    "sg:province":"Leicestershire",
    "sg:tags":[
        "consultant",
        "business"
    ],
    "wof:name":"R B Consulting Nuneaton Ltd.",
    "wof:placetype":"venue"
},
  "geometry": {"coordinates":[-1.516644,52.525345],"type":"Point"}
}