{
  "type": "Feature",
  "properties": {
    "iso:country":"GB",
    "sg:address":"Roman Road",
    "sg:city":"Chelmsford",
    "sg:classifiers":[
        {
            "category":"Place Of Worship",
            "type":"Public Place"
        }
    ],
    "sg:phone":"+44 1277 650626",
    "sg:postcode":"CM2 0HB",
    "sg:province":"Essex",
    "wof:name":"Chelmsford Seventh-day Adventist Church",
    "wof:placetype":"venue"
},
  "geometry": {"coordinates":[0.4720749855,51.7277641296],"type":"Point"}
}