{
  "type": "Feature",
  "properties": {
    "addr:full":"21 Down Way Northolt Greater London UB5 6PG",
    "addr:housenumber":"21",
    "addr:postcode":"ub5 6pg",
    "addr:street":"Down Way",
    "iso:country":"GB",
    "sg:address":"21 Down Way",
    "sg:city":"Northolt",
    "sg:classifiers":[
        {
            "category":"Food & Beverages",
            "subcategory":"Liquor & Beverages",
            "type":"Retail Goods"
        }
    ],
    "sg:postcode":"UB5 6PG",
    "sg:province":"Greater London",
    "sg:tags":[
        "beer",
        "spirit",
        "wines"
    ],
    "wof:name":"Blake,Stephen,",
    "wof:placetype":"venue"
},
  "geometry": {"coordinates":[-0.4056609869,51.5350799561],"type":"Point"}
}