{
  "type": "Feature",
  "properties": {
    "addr:full":"Highbridge Medical Centre, Pepperall Rd Highbridge Somerset TA9 3YA",
    "addr:postcode":"ta9 3ya",
    "addr:street":"Pepperall Rd",
    "iso:country":"GB",
    "sg:address":"Highbridge Medical Centre, Pepperall Rd",
    "sg:city":"Highbridge",
    "sg:classifiers":[
        {
            "category":"Health Services",
            "subcategory":"Doctor",
            "type":"Services"
        }
    ],
    "sg:phone":"+44 1278 783220",
    "sg:postcode":"TA9 3YA",
    "sg:province":"Somerset",
    "sg:tags":[
        "practitioners"
    ],
    "wof:name":"Clapham, C M",
    "wof:placetype":"venue"
},
  "geometry": {"coordinates":[-2.9749140739,51.2223243713],"type":"Point"}
}