{
  "type": "Feature",
  "properties": {
    "addr:full":"Remo House, 310-312 Regent Street London Greater London W1B 3AX",
    "addr:housenumber":"310-312",
    "addr:postcode":"w1b 3ax",
    "addr:street":"Regent Street",
    "iso:country":"GB",
    "sg:address":"Remo House, 310-312 Regent Street",
    "sg:city":"London",
    "sg:classifiers":[
        {
            "category":"Wholesale",
            "subcategory":"Machinery & Supplies",
            "type":"Manufacturing & Wholesale Goods"
        }
    ],
    "sg:phone":"+44 20 7637 7531",
    "sg:postcode":"W1B 3AX",
    "sg:province":"Greater London",
    "sg:tags":[
        "pump"
    ],
    "wof:name":"Weir Pumps Ltd.",
    "wof:placetype":"venue"
},
  "geometry": {"coordinates":[-0.142419,51.516804],"type":"Point"}
}