{
  "type": "Feature",
  "properties": {
    "addr:full":"3 East Road Kirkwall Orkney Islands KW15 1HZ",
    "addr:housenumber":"3",
    "addr:postcode":"kw15 1hz",
    "addr:street":"East Road",
    "iso:country":"GB",
    "sg:address":"3 East Road",
    "sg:city":"Kirkwall",
    "sg:classifiers":[
        {
            "category":"Professional",
            "subcategory":"Accounting & Tax Preparation",
            "type":"Services"
        }
    ],
    "sg:phone":"+44 1856 872804",
    "sg:postcode":"KW15 1HZ",
    "sg:province":"Orkney Islands",
    "sg:tags":[
        "accountant"
    ],
    "wof:name":"Orcadia",
    "wof:placetype":"venue"
},
  "geometry": {"coordinates":[-2.955692,58.983856],"type":"Point"}
}