{
  "type": "Feature",
  "properties": {
    "addr:full":"154 Clerkenwell Road London Greater London EC1R 5AD",
    "addr:housenumber":"154",
    "addr:postcode":"ec1r 5ad",
    "addr:street":"Clerkenwell Road",
    "iso:country":"GB",
    "sg:address":"154 Clerkenwell Road",
    "sg:city":"London",
    "sg:classifiers":[
        {
            "category":"Professional",
            "subcategory":"Business Services",
            "type":"Services"
        }
    ],
    "sg:phone":"+44 20 7837 8600",
    "sg:postcode":"EC1R 5AD",
    "sg:province":"Greater London",
    "sg:tags":[
        "trade"
    ],
    "wof:name":"Accounting Technician (Publications) Ltd.",
    "wof:placetype":"venue"
},
  "geometry": {"coordinates":[-0.110249,51.522018],"type":"Point"}
}