{
  "type": "Feature",
  "properties": {
    "iso:country":"GB",
    "sg:address":"Herts House, 63 Ely Road, Little Port",
    "sg:city":"Ely",
    "sg:classifiers":[
        {
            "category":"Retail",
            "subcategory":"Storage",
            "type":"Services"
        }
    ],
    "sg:phone":"+44 1353 863100",
    "sg:postcode":"CB6 1HJ",
    "sg:province":"Cambridgeshire",
    "sg:tags":[
        "household",
        "removal"
    ],
    "wof:name":"Hertfordshire Storage Systems Ltd.",
    "wof:placetype":"venue"
},
  "geometry": {"coordinates":[0.298643,52.447384],"type":"Point"}
}