{
  "type": "Feature",
  "properties": {
    "iso:country":"GB",
    "sg:address":"Warbrook House, Warbrook Lane, Eversley",
    "sg:city":"Hook",
    "sg:classifiers":[
        {
            "category":"Professional",
            "type":"Services"
        },
        {
            "category":"Conference Center",
            "type":"Public Place"
        }
    ],
    "sg:phone":"+44 118 973 2174",
    "sg:postcode":"RG27 0PL",
    "sg:province":"Berkshire",
    "sg:tags":[
        "related"
    ],
    "wof:name":"Inital Style Conferences Ltd",
    "wof:placetype":"venue"
},
  "geometry": {"coordinates":[-0.891938,51.351875],"type":"Point"}
}