{
  "type": "Feature",
  "properties": {
    "iso:country":"GB",
    "sg:address":"20 Westgate",
    "sg:city":"Ripon",
    "sg:classifiers":[
        {
            "category":"Personal",
            "subcategory":"Barber",
            "type":"Services"
        }
    ],
    "sg:phone":"+44 1765 602850",
    "sg:postcode":"HG4 2BQ",
    "sg:province":"North Yorkshire",
    "sg:tags":[
        "men's",
        "gents",
        "hairdresser"
    ],
    "wof:name":"Paul's",
    "wof:placetype":"venue"
},
  "geometry": {"coordinates":[-1.525992,54.136322],"type":"Point"}
}