{
  "type": "Feature",
  "properties": {
    "addr:full":"55 Richmond Road, St George Bristol City of Bristol BS5 8EL",
    "addr:housenumber":"55",
    "addr:postcode":"bs5 8el",
    "addr:street":"Richmond Road",
    "iso:country":"GB",
    "sg:address":"55 Richmond Road, St George",
    "sg:city":"Bristol",
    "sg:classifiers":[
        {
            "category":"Autos & Motor Vehicles",
            "subcategory":"Motorcycle Sales",
            "type":"Retail Goods"
        }
    ],
    "sg:phone":"+44 117 939 7750",
    "sg:postcode":"BS5 8EL",
    "sg:province":"City of Bristol",
    "wof:name":"Bikecare",
    "wof:placetype":"venue"
},
  "geometry": {"coordinates":[-2.5468740463,51.4596443176],"type":"Point"}
}