{
  "type": "Feature",
  "properties": {
    "iso:country":"GB",
    "sg:address":"Worth Road",
    "sg:city":"Crawley",
    "sg:classifiers":[
        {
            "category":"Community Center",
            "type":"Public Place"
        }
    ],
    "sg:phone":"+44 1293 616479",
    "sg:postcode":"RH11 0ED",
    "sg:province":"West Sussex",
    "sg:tags":[
        "centre"
    ],
    "wof:name":"Pound Hill Community Centre",
    "wof:placetype":"venue"
},
  "geometry": {"coordinates":[-0.157869,51.118961],"type":"Point"}
}