{
  "type": "Feature",
  "properties": {
    "iso:country":"GB",
    "sg:address":"18 Chevalier Road",
    "sg:city":"Dover",
    "sg:classifiers":[
        {
            "category":"Building & Trades",
            "subcategory":"Construction",
            "type":"Services"
        }
    ],
    "sg:phone":"+44 1304 209462",
    "sg:postcode":"CT17 9PG",
    "sg:province":"Kent",
    "sg:tags":[
        "glazier"
    ],
    "wof:name":"Neil Law Glazing",
    "wof:placetype":"venue"
},
  "geometry": {"coordinates":[1.2914789915,51.1244773865],"type":"Point"}
}