{
  "type": "Feature",
  "properties": {
    "addr:full":"9 The Nook, Anstey Leicester Leicestershire LE7 7AZ",
    "addr:housenumber":"9",
    "addr:postcode":"le7 7az",
    "addr:street":"The Nook",
    "iso:country":"GB",
    "sg:address":"9 The Nook, Anstey",
    "sg:city":"Leicester",
    "sg:classifiers":[
        {
            "category":"Health Services",
            "subcategory":"Optometrist",
            "type":"Services"
        }
    ],
    "sg:phone":"+44 116 234 0434",
    "sg:postcode":"LE7 7AZ",
    "sg:province":"Leicestershire",
    "sg:tags":[
        "optician"
    ],
    "wof:name":"Opticare",
    "wof:placetype":"venue"
},
  "geometry": {"coordinates":[-1.1835589409,52.6738357544],"type":"Point"}
}