{
  "type": "Feature",
  "properties": {
    "addr:full":"School La Bedford Bedfordshire MK43 0UY",
    "addr:postcode":"mk43 0uy",
    "addr:street":"La Bedford Bedfordshire",
    "iso:country":"GB",
    "sg:address":"School La",
    "sg:city":"Bedford",
    "sg:classifiers":[
        {
            "category":"Place Of Worship",
            "type":"Public Place"
        }
    ],
    "sg:phone":"+44 1908 583169",
    "sg:postcode":"MK43 0UY",
    "sg:province":"Bedfordshire",
    "wof:name":"St James C Of E Church",
    "wof:placetype":"venue"
},
  "geometry": {"coordinates":[-0.608935,52.015354],"type":"Point"}
}