{
  "type": "Feature",
  "properties": {
    "addr:full":"208 Moor St West Bromwich West Midlands B70 7AR",
    "addr:housenumber":"208",
    "addr:postcode":"b70 7ar",
    "addr:street":"Moor St West",
    "iso:country":"GB",
    "sg:address":"208 Moor St",
    "sg:city":"West Bromwich",
    "sg:classifiers":[
        {
            "category":"Health Services",
            "subcategory":"Optometrist",
            "type":"Services"
        }
    ],
    "sg:postcode":"B70 7AR",
    "sg:province":"West Midlands",
    "sg:tags":[
        "optician"
    ],
    "wof:name":"Ashby Opticians",
    "wof:placetype":"venue"
},
  "geometry": {"coordinates":[-1.9985660315,52.5160369873],"type":"Point"}
}