{
  "type": "Feature",
  "properties": {
    "addr:full":"2 Dalling Rd Hammersmith Greater London W6 0JB",
    "addr:housenumber":"2",
    "addr:postcode":"w6 0jb",
    "addr:street":"Dalling Rd",
    "iso:country":"GB",
    "sg:address":"2 Dalling Rd",
    "sg:city":"Hammersmith",
    "sg:classifiers":[
        {
            "category":"Arts & Performance",
            "subcategory":"Arts Center",
            "type":"Entertainment"
        }
    ],
    "sg:phone":"+44 20 8563 9495",
    "sg:postcode":"W6 0JB",
    "sg:province":"Greater London",
    "sg:tags":[
        "centre"
    ],
    "wof:name":"Artwise",
    "wof:placetype":"venue"
},
  "geometry": {"coordinates":[-0.234736,51.49305],"type":"Point"}
}