{
  "type": "Feature",
  "properties": {
    "iso:country":"GB",
    "sg:address":"Rose Farm, Ashfield",
    "sg:city":"Stowmarket",
    "sg:classifiers":[
        {
            "category":"Manufacturing",
            "subcategory":"Wood Products",
            "type":"Manufacturing & Wholesale Goods"
        },
        {
            "category":"Manufacturing",
            "subcategory":"Paper Products",
            "type":"Manufacturing & Wholesale Goods"
        }
    ],
    "sg:phone":"+44 1728 685402",
    "sg:postcode":"IP14 6LU",
    "sg:province":"Suffolk",
    "sg:tags":[
        "encapsulation",
        "cardboard",
        "lamination"
    ],
    "wof:name":"Langley Lamination & Encapsulation Service",
    "wof:placetype":"venue"
},
  "geometry": {"coordinates":[1.234820962,52.2184791565],"type":"Point"}
}