{
  "type": "Feature",
  "properties": {
    "addr:full":"15 Kings Rd Brighton East Sussex BN1 1NE",
    "addr:housenumber":"15",
    "addr:postcode":"bn1 1ne",
    "addr:street":"Kings Rd",
    "iso:country":"GB",
    "sg:address":"15 Kings Rd",
    "sg:city":"Brighton",
    "sg:classifiers":[
        {
            "category":"Bars & Pubs",
            "type":"Food & Drink"
        }
    ],
    "sg:postcode":"BN1 1NE",
    "sg:province":"East Sussex",
    "sg:tags":[
        "pubs",
        "inn"
    ],
    "wof:name":"Zenon's Nightclub",
    "wof:placetype":"venue"
},
  "geometry": {"coordinates":[-0.1395449936,50.8200531006],"type":"Point"}
}