{
  "type": "Feature",
  "properties": {
    "addr:full":"169 Norwich Road Wisbech Cambridgeshire PE13 3TA",
    "addr:housenumber":"169",
    "addr:postcode":"pe13 3ta",
    "addr:street":"Norwich Road",
    "iso:country":"GB",
    "sg:address":"169 Norwich Road",
    "sg:city":"Wisbech",
    "sg:classifiers":[
        {
            "category":"Social Services",
            "subcategory":"Retirement Home",
            "type":"Services"
        }
    ],
    "sg:postcode":"PE13 3TA",
    "sg:province":"Cambridgeshire",
    "sg:tags":[
        "residential",
        "care"
    ],
    "wof:name":"Chestnuts Residential Home for the Elderly",
    "wof:placetype":"venue"
},
  "geometry": {"coordinates":[0.171147,52.665455],"type":"Point"}
}