{
  "type": "Feature",
  "properties": {
    "addr:full":"1147-1149 Alcester Road South Birmingham West Midlands B14 5TP",
    "addr:housenumber":"1147-1149",
    "addr:postcode":"b14 5tp",
    "addr:street":"Alcester Road South",
    "iso:country":"GB",
    "sg:address":"1147-1149 Alcester Road South",
    "sg:city":"Birmingham",
    "sg:classifiers":[
        {
            "category":"Food & Beverages",
            "subcategory":"Supermarket",
            "type":"Retail Goods"
        }
    ],
    "sg:phone":"+44 121 430 8258",
    "sg:postcode":"B14 5TP",
    "sg:province":"West Midlands",
    "wof:name":"Hollywood Self Service Stores",
    "wof:placetype":"venue"
},
  "geometry": {"coordinates":[-1.883763,52.401234],"type":"Point"}
}