{
  "type": "Feature",
  "properties": {
    "addr:full":"Woolshops, Tudor Building Halifax West Yorkshire HX1 1RU",
    "addr:postcode":"hx1 1ru",
    "iso:country":"GB",
    "sg:address":"Woolshops, Tudor Building",
    "sg:city":"Halifax",
    "sg:classifiers":[
        {
            "category":"Retail",
            "subcategory":"Photofinishing",
            "type":"Services"
        }
    ],
    "sg:phone":"+44 1422 346424",
    "sg:postcode":"HX1 1RU",
    "sg:province":"West Yorkshire",
    "sg:tags":[
        "photographic",
        "processor"
    ],
    "wof:name":"Foto Processing",
    "wof:placetype":"venue"
},
  "geometry": {"coordinates":[-1.8622239828,53.7212333679],"type":"Point"}
}