{
  "type": "Feature",
  "properties": {
    "iso:country":"GB",
    "sg:address":"6 Glenavon Road, Maypole",
    "sg:city":"Birmingham",
    "sg:classifiers":[
        {
            "category":"Professional",
            "subcategory":"Testing Lab",
            "type":"Services"
        }
    ],
    "sg:phone":"+44 1564 826800",
    "sg:postcode":"B14 5BL",
    "sg:province":"West Midlands",
    "sg:tags":[
        "mot"
    ],
    "wof:name":"Bournville Garage",
    "wof:placetype":"venue"
},
  "geometry": {"coordinates":[-1.878879,52.408283],"type":"Point"}
}