{
  "type": "Feature",
  "properties": {
    "addr:full":"207a Park Rd Kingston-upon-thames Greater London KT2 5JY",
    "addr:housenumber":"207a",
    "addr:postcode":"kt2 5jy",
    "addr:street":"Park Rd",
    "iso:country":"GB",
    "sg:address":"207a Park Rd",
    "sg:city":"Kingston-upon-thames",
    "sg:classifiers":[
        {
            "category":"Real Estate",
            "subcategory":"Architect",
            "type":"Services"
        }
    ],
    "sg:postcode":"KT2 5JY",
    "sg:province":"Greater London",
    "wof:name":"Pringle,Alan,",
    "wof:placetype":"venue"
},
  "geometry": {"coordinates":[-0.2897030115,51.4210014343],"type":"Point"}
}