{
  "type": "Feature",
  "properties": {
    "iso:country":"GB",
    "sg:address":"Dental Surgery, Portland Square",
    "sg:city":"Sutton In Ashfield",
    "sg:classifiers":[
        {
            "category":"Health Services",
            "subcategory":"Dentist",
            "type":"Services"
        }
    ],
    "sg:phone":"+44 1623 557786",
    "sg:postcode":"NG17 1BA",
    "sg:province":"Nottinghamshire",
    "wof:name":"Hunter-spoke & Richardson",
    "wof:placetype":"venue"
},
  "geometry": {"coordinates":[-1.2770889997,53.1218414307],"type":"Point"}
}