{
  "type": "Feature",
  "properties": {
    "iso:country":"GB",
    "sg:address":"37 Winfield Gro, Newdigate",
    "sg:city":"Dorking",
    "sg:classifiers":[
        {
            "category":"Building & Trades",
            "subcategory":"Pest Control",
            "type":"Services"
        }
    ],
    "sg:phone":"+44 1306 631656",
    "sg:postcode":"RH5 5AX",
    "sg:province":"Surrey",
    "sg:tags":[
        "vermin"
    ],
    "wof:name":"Abee Pest Control",
    "wof:placetype":"venue"
},
  "geometry": {"coordinates":[-0.29081,51.165577],"type":"Point"}
}