{
  "type": "Feature",
  "properties": {
    "addr:full":"Unit 23/24, Slingsby Close Nuneaton Leicestershire CV11 6RP",
    "addr:housenumber":"unit 23 / 24",
    "addr:postcode":"cv11 6rp",
    "addr:street":"Slingsby Close",
    "iso:country":"GB",
    "sg:address":"Unit 23/24, Slingsby Close",
    "sg:city":"Nuneaton",
    "sg:classifiers":[
        {
            "category":"Professional",
            "subcategory":"Engineering",
            "type":"Services"
        }
    ],
    "sg:phone":"+44 24 7635 2622",
    "sg:postcode":"CV11 6RP",
    "sg:province":"Leicestershire",
    "sg:tags":[
        "precision",
        "engineer"
    ],
    "wof:name":"Jay-Jay Engineering (Coventry) Ltd.",
    "wof:placetype":"venue"
},
  "geometry": {"coordinates":[-1.4481090307,52.514881134],"type":"Point"}
}