{
  "type": "Feature",
  "properties": {
    "addr:full":"25 Monks Hall Rd Northampton Northamptonshire NN1 4LZ",
    "addr:housenumber":"25",
    "addr:postcode":"nn1 4lz",
    "addr:street":"Monks Hall Rd",
    "iso:country":"GB",
    "sg:address":"25 Monks Hall Rd",
    "sg:city":"Northampton",
    "sg:classifiers":[
        {
            "category":"Building & Trades",
            "subcategory":"Construction",
            "type":"Services"
        }
    ],
    "sg:phone":"+44 1604 630400",
    "sg:postcode":"NN1 4LZ",
    "sg:province":"Northamptonshire",
    "sg:tags":[
        "builder"
    ],
    "wof:name":"Patton Bros",
    "wof:placetype":"venue"
},
  "geometry": {"coordinates":[-0.874119,52.244328],"type":"Point"}
}