{
  "type": "Feature",
  "properties": {
    "addr:full":"Bath Road Melksham Wiltshire SN12 6LP",
    "addr:postcode":"sn12 6lp",
    "addr:street":"Bath Road",
    "iso:country":"GB",
    "sg:address":"Bath Road",
    "sg:city":"Melksham",
    "sg:classifiers":[
        {
            "category":"Food & Beverages",
            "subcategory":"Supermarket",
            "type":"Retail Goods"
        }
    ],
    "sg:phone":"+44 1225 707435",
    "sg:postcode":"SN12 6LP",
    "sg:province":"Wiltshire",
    "wof:name":"Somerfield",
    "wof:placetype":"venue"
},
  "geometry": {"coordinates":[-2.1396288872,51.3762893677],"type":"Point"}
}