{
  "type": "Feature",
  "properties": {
    "addr:full":"29 Church Street Inverkeithing Fife KY11 1LG",
    "addr:housenumber":"29",
    "addr:postcode":"ky11 1lg",
    "addr:street":"Church Street",
    "iso:country":"GB",
    "sg:address":"29 Church Street",
    "sg:city":"Inverkeithing",
    "sg:classifiers":[
        {
            "category":"Professional",
            "subcategory":"Business Services",
            "type":"Services"
        }
    ],
    "sg:phone":"+44 1383 411348",
    "sg:postcode":"KY11 1LG",
    "sg:province":"Fife",
    "sg:tags":[
        "import",
        "export",
        "agent"
    ],
    "wof:name":"Inverkeithing Trophy & Engraving Centre",
    "wof:placetype":"venue"
},
  "geometry": {"coordinates":[-3.3965570927,56.0330352783],"type":"Point"}
}