{
  "type": "Feature",
  "properties": {
    "addr:full":"171 Holyhead Road, Wellington Telford Shropshire TF1 2DP",
    "addr:housenumber":"171",
    "addr:postcode":"tf1 2dp",
    "addr:street":"Holyhead Road",
    "iso:country":"GB",
    "sg:address":"171 Holyhead Road, Wellington",
    "sg:city":"Telford",
    "sg:classifiers":[
        {
            "category":"Professional",
            "subcategory":"Art Services",
            "type":"Services"
        }
    ],
    "sg:phone":"+44 1952 222757",
    "sg:postcode":"TF1 2DP",
    "sg:province":"Shropshire",
    "sg:tags":[
        "graphic",
        "designer"
    ],
    "wof:name":"Strata Design",
    "wof:placetype":"venue"
},
  "geometry": {"coordinates":[-2.511182,52.695271],"type":"Point"}
}