{
  "type": "Feature",
  "properties": {
    "addr:full":"50 Parliament Street Harrogate North Yorkshire HG1 2RL",
    "addr:housenumber":"50",
    "addr:postcode":"hg1 2rl",
    "addr:street":"Parliament Street",
    "iso:country":"GB",
    "sg:address":"50 Parliament Street",
    "sg:city":"Harrogate",
    "sg:classifiers":[
        {
            "category":"Shopping",
            "subcategory":"Clothing, Apparel, & Fashions",
            "type":"Retail Goods"
        }
    ],
    "sg:phone":"+44 1423 523861",
    "sg:postcode":"HG1 2RL",
    "sg:province":"North Yorkshire",
    "sg:tags":[
        "ladieswear"
    ],
    "wof:name":"Liola (London) Ltd.",
    "wof:placetype":"venue"
},
  "geometry": {"coordinates":[-1.5436799526,53.9946327209],"type":"Point"}
}