{
  "type": "Feature",
  "properties": {
    "addr:full":"14 North Mall London Greater London N9 0EH",
    "addr:housenumber":"14",
    "addr:postcode":"n9 0eh",
    "addr:street":"North Mall",
    "iso:country":"GB",
    "sg:address":"14 North Mall",
    "sg:city":"London",
    "sg:classifiers":[
        {
            "category":"Retail",
            "subcategory":"Repair Shop",
            "type":"Services"
        }
    ],
    "sg:phone":"+44 20 8803 9031",
    "sg:postcode":"N9 0EH",
    "sg:province":"Greater London",
    "sg:tags":[
        "clocks",
        "watch"
    ],
    "wof:name":"M Barber",
    "wof:placetype":"venue"
},
  "geometry": {"coordinates":[-0.05697,51.624649],"type":"Point"}
}