{
  "type": "Feature",
  "properties": {
    "addr:full":"159 North Street Brighton East Sussex BN1 1EA",
    "addr:housenumber":"159",
    "addr:postcode":"bn1 1ea",
    "addr:street":"North Street",
    "iso:country":"GB",
    "sg:address":"159 North Street",
    "sg:city":"Brighton",
    "sg:classifiers":[
        {
            "category":"Shopping",
            "subcategory":"News",
            "type":"Retail Goods"
        }
    ],
    "sg:phone":"+44 1273 325024",
    "sg:postcode":"BN1 1EA",
    "sg:province":"East Sussex",
    "sg:tags":[
        "newsagent"
    ],
    "wof:name":"Allsorts",
    "wof:placetype":"venue"
},
  "geometry": {"coordinates":[-0.1403079927,50.8229942322],"type":"Point"}
}