{
  "type": "Feature",
  "properties": {
    "iso:country":"GB",
    "sg:address":"School Green, Shinfield",
    "sg:city":"Reading",
    "sg:classifiers":[
        {
            "category":"Autos & Motor Vehicles",
            "subcategory":"Auto Supplies",
            "type":"Retail Goods"
        }
    ],
    "sg:phone":"+44 118 988 6888",
    "sg:postcode":"RG2 9EB",
    "sg:province":"Berkshire",
    "sg:tags":[
        "tyre"
    ],
    "wof:name":"Humphries TyrePlus Autoservice",
    "wof:placetype":"venue"
},
  "geometry": {"coordinates":[-0.945945,51.405014],"type":"Point"}
}