{
  "type": "Feature",
  "properties": {
    "addr:full":"20 Sun Dale Drive Crewe Cheshire CW2 8UB",
    "addr:housenumber":"20",
    "addr:postcode":"cw2 8ub",
    "addr:street":"Sun Dale Drive",
    "iso:country":"GB",
    "sg:address":"20 Sun Dale Drive",
    "sg:city":"Crewe",
    "sg:classifiers":[
        {
            "category":"Wholesale",
            "subcategory":"Scrap",
            "type":"Manufacturing & Wholesale Goods"
        }
    ],
    "sg:phone":"+44 1270 212323",
    "sg:postcode":"CW2 8UB",
    "sg:province":"Cheshire",
    "sg:tags":[
        "breaker",
        "dismantlers"
    ],
    "wof:name":"Barlow Bros",
    "wof:placetype":"venue"
},
  "geometry": {"coordinates":[-2.4805159569,53.0968132019],"type":"Point"}
}