{
  "type": "Feature",
  "properties": {
    "iso:country":"GB",
    "sg:address":"1 Lower Cock Rd",
    "sg:city":"Bristol",
    "sg:classifiers":[
        {
            "category":"Shopping",
            "subcategory":"Party Supplies",
            "type":"Retail Goods"
        }
    ],
    "sg:phone":"+44 117 985 0091",
    "sg:postcode":"BS15 9RT",
    "sg:province":"City of Bristol",
    "sg:tags":[
        "inflatables",
        "bouncy",
        "castle"
    ],
    "wof:name":"Bounce Away",
    "wof:placetype":"venue"
},
  "geometry": {"coordinates":[-2.492017,51.456467],"type":"Point"}
}