{
  "type": "Feature",
  "properties": {
    "addr:full":"78 Infirmary Road Sheffield South Yorkshire S6 3DD",
    "addr:housenumber":"78",
    "addr:postcode":"s6 3dd",
    "addr:street":"Infirmary Road",
    "iso:country":"GB",
    "sg:address":"78 Infirmary Road",
    "sg:city":"Sheffield",
    "sg:classifiers":[
        {
            "category":"Personal",
            "subcategory":"Beauty Salon",
            "type":"Services"
        }
    ],
    "sg:phone":"+44 114 272 3739",
    "sg:postcode":"S6 3DD",
    "sg:province":"South Yorkshire",
    "sg:tags":[
        "unisex",
        "hairdresser"
    ],
    "wof:name":"Betty Tigers",
    "wof:placetype":"venue"
},
  "geometry": {"coordinates":[-1.4816570282,53.3906364441],"type":"Point"}
}