{
  "type": "Feature",
  "properties": {
    "iso:country":"GB",
    "sg:address":"Merlins Mill, Toadsmoor Rd, Brimscombe",
    "sg:city":"Stroud",
    "sg:classifiers":[
        {
            "category":"Retail",
            "subcategory":"Auto Repair",
            "type":"Services"
        }
    ],
    "sg:phone":"+44 1453 731121",
    "sg:postcode":"GL5 2UG",
    "sg:province":"Gloucestershire",
    "sg:tags":[
        "modification",
        "car",
        "classic"
    ],
    "wof:name":"Graham Millard",
    "wof:placetype":"venue"
},
  "geometry": {"coordinates":[-2.1810429096,51.7192459106],"type":"Point"}
}