{
  "type": "Feature",
  "properties": {
    "iso:country":"GB",
    "sg:address":"47 Byron Street",
    "sg:city":"Dundee",
    "sg:classifiers":[
        {
            "category":"Professional",
            "subcategory":"Engineering",
            "type":"Services"
        },
        {
            "category":"Building & Trades",
            "subcategory":"Electrical",
            "type":"Services"
        }
    ],
    "sg:phone":"+44 1382 508524",
    "sg:postcode":"DD3 6QT",
    "sg:province":"Dundee City",
    "sg:tags":[
        "engineer",
        "electrician",
        "contractor"
    ],
    "wof:name":"Bruce Jamieson",
    "wof:placetype":"venue"
},
  "geometry": {"coordinates":[-2.985721,56.472778],"type":"Point"}
}