{
  "type": "Feature",
  "properties": {
    "iso:country":"GB",
    "sg:address":"Poynton Water, Mill Lane, Totley Rise",
    "sg:city":"Sheffield",
    "sg:classifiers":[
        {
            "category":"Home & Garden",
            "subcategory":"Household Appliances",
            "type":"Retail Goods"
        }
    ],
    "sg:phone":"+44 114 262 0111",
    "sg:postcode":"S17 4HQ",
    "sg:province":"Derbyshire",
    "sg:tags":[
        "cleaner",
        "vacuum"
    ],
    "wof:name":"The Industrial Vacuum Co.",
    "wof:placetype":"venue"
},
  "geometry": {"coordinates":[-1.522146,53.319557],"type":"Point"}
}