{
  "type": "Feature",
  "properties": {
    "iso:country":"GB",
    "sg:address":"37 Broad Street",
    "sg:city":"Hereford",
    "sg:classifiers":[
        {
            "category":"Professional",
            "subcategory":"Art Services",
            "type":"Services"
        }
    ],
    "sg:postcode":"HR4 9AR",
    "sg:province":"Herefordshire",
    "sg:tags":[
        "framing"
    ],
    "wof:name":"Hereford Framing Centre",
    "wof:placetype":"venue"
},
  "geometry": {"coordinates":[-2.7177009583,52.0555038452],"type":"Point"}
}