{
  "type": "Feature",
  "properties": {
    "addr:full":"44 Towerfield Road, Shoeburyness Southend-on-sea Essex SS3 9QT",
    "addr:housenumber":"44",
    "addr:postcode":"ss3 9qt",
    "addr:street":"Towerfield Road",
    "iso:country":"GB",
    "sg:address":"44 Towerfield Road, Shoeburyness",
    "sg:city":"Southend-on-sea",
    "sg:classifiers":[
        {
            "category":"Shopping",
            "type":"Retail Goods"
        }
    ],
    "sg:phone":"+44 1702 296230",
    "sg:postcode":"SS3 9QT",
    "sg:province":"Essex",
    "sg:tags":[
        "part",
        "accessory"
    ],
    "wof:name":"U K Salvage",
    "wof:placetype":"venue"
},
  "geometry": {"coordinates":[0.78442,51.533813],"type":"Point"}
}