{
  "type": "Feature",
  "properties": {
    "addr:full":"Hillcrest, 5 Main Road Stamford Cambridgeshire PE9 4SN",
    "addr:housenumber":"5",
    "addr:postcode":"pe9 4sn",
    "addr:street":"Main Road",
    "iso:country":"GB",
    "sg:address":"Hillcrest, 5 Main Road",
    "sg:city":"Stamford",
    "sg:classifiers":[
        {
            "category":"Building & Trades",
            "subcategory":"Construction",
            "type":"Services"
        }
    ],
    "sg:postcode":"PE9 4SN",
    "sg:province":"Cambridgeshire",
    "sg:tags":[
        "joiner",
        "carpenter"
    ],
    "wof:name":"Glynn Woolf",
    "wof:placetype":"venue"
},
  "geometry": {"coordinates":[-0.4802899957,52.6520843506],"type":"Point"}
}