{
  "type": "Feature",
  "properties": {
    "iso:country":"GB",
    "sg:address":"268 Moston La",
    "sg:city":"Manchester",
    "sg:classifiers":[
        {
            "category":"Recreation",
            "subcategory":"Amusement Park",
            "type":"Entertainment"
        }
    ],
    "sg:phone":"+44 161 203 4128",
    "sg:postcode":"M40 9WF",
    "sg:province":"Greater Manchester",
    "sg:tags":[
        "arcade"
    ],
    "wof:name":"S Seldon",
    "wof:placetype":"venue"
},
  "geometry": {"coordinates":[-2.199158,53.513851],"type":"Point"}
}