{
  "type": "Feature",
  "properties": {
    "addr:full":"Common Sidings Pontyclun Bridgend CF72 8LS",
    "addr:postcode":"cf72 8ls",
    "addr:street":"Common;Pontyclun",
    "iso:country":"GB",
    "sg:address":"Common Sidings",
    "sg:city":"Pontyclun",
    "sg:classifiers":[
        {
            "category":"Autos & Motor Vehicles",
            "subcategory":"Auto Supplies",
            "type":"Retail Goods"
        }
    ],
    "sg:phone":"+44 1443 238392",
    "sg:postcode":"CF72 8LS",
    "sg:province":"Bridgend",
    "sg:tags":[
        "tyre"
    ],
    "wof:name":"Llantrisant Tyre Service",
    "wof:placetype":"venue"
},
  "geometry": {"coordinates":[-3.375424,51.544224],"type":"Point"}
}