{
  "type": "Feature",
  "properties": {
    "addr:full":"62 The Avenue Watford Hertfordshire WD17 4NX",
    "addr:housenumber":"62",
    "addr:postcode":"wd17 4nx",
    "addr:street":"The Avenue",
    "iso:country":"GB",
    "sg:address":"62 The Avenue",
    "sg:city":"Watford",
    "sg:classifiers":[
        {
            "category":"Professional",
            "subcategory":"Management & Consulting",
            "type":"Services"
        }
    ],
    "sg:postcode":"WD17 4NX",
    "sg:province":"Hertfordshire",
    "sg:tags":[
        "fire",
        "consultant",
        "protection"
    ],
    "wof:name":"Risk Control Services",
    "wof:placetype":"venue"
},
  "geometry": {"coordinates":[-0.406881,51.663029],"type":"Point"}
}