{
  "type": "Feature",
  "properties": {
    "iso:country":"GB",
    "sg:address":"38 Pentwyn, Baglan Road",
    "sg:city":"Port Talbot",
    "sg:classifiers":[
        {
            "category":"Professional",
            "subcategory":"Engineering",
            "type":"Services"
        },
        {
            "category":"Farming",
            "subcategory":"Livestock Farm",
            "type":"Manufacturing & Wholesale Goods"
        }
    ],
    "sg:phone":"+44 1639 821031",
    "sg:postcode":"SA12 8EA",
    "sg:province":"Neath Port Talbot",
    "sg:tags":[
        "engineer",
        "others",
        "electrical",
        "contractor"
    ],
    "wof:name":"Williams Bros",
    "wof:placetype":"venue"
},
  "geometry": {"coordinates":[-3.801427,51.612434],"type":"Point"}
}