{
  "type": "Feature",
  "properties": {
    "iso:country":"GB",
    "sg:address":"Studio 3 Dunlin Rise, Merrow Park",
    "sg:city":"Guildford",
    "sg:classifiers":[
        {
            "category":"Building & Trades",
            "subcategory":"Construction",
            "type":"Services"
        }
    ],
    "sg:phone":"+44 1483 451931",
    "sg:postcode":"GU4 7DX",
    "sg:province":"Surrey",
    "sg:tags":[
        "restoration",
        "refurbishment"
    ],
    "wof:name":"Richard Hewson Interior Contracts Ltd.",
    "wof:placetype":"venue"
},
  "geometry": {"coordinates":[-0.5286,51.25069],"type":"Point"}
}