{
  "type": "Feature",
  "properties": {
    "iso:country":"GB",
    "sg:address":"Newtonmore Road",
    "sg:city":"Kingussie",
    "sg:classifiers":[
        {
            "category":"Retail",
            "subcategory":"Auto Repair",
            "type":"Services"
        }
    ],
    "sg:phone":"+44 1540 661478",
    "sg:postcode":"PH21 1HF",
    "sg:province":"Highland",
    "sg:tags":[
        "modification",
        "garage"
    ],
    "wof:name":"West End Garage",
    "wof:placetype":"venue"
},
  "geometry": {"coordinates":[-4.052814,57.079868],"type":"Point"}
}