{
  "type": "Feature",
  "properties": {
    "addr:full":"C/o Gee Aggar & Co, 15 Sudbury Court Harrow Greater London HA1 3SD",
    "addr:housenumber":"/ o;15",
    "addr:postcode":"ha1 3sd",
    "addr:street":"C;Sudbury Court",
    "iso:country":"GB",
    "sg:address":"C/o Gee Aggar & Co, 15 Sudbury Court",
    "sg:city":"Harrow",
    "sg:classifiers":[
        {
            "category":"Retail",
            "subcategory":"Storage",
            "type":"Services"
        }
    ],
    "sg:postcode":"HA1 3SD",
    "sg:province":"Greater London",
    "sg:tags":[
        "household",
        "removal"
    ],
    "wof:name":"Dateco (U.K.) Ltd.",
    "wof:placetype":"venue"
},
  "geometry": {"coordinates":[-0.3280819952,51.5626220703],"type":"Point"}
}