{
  "type": "Feature",
  "properties": {
    "addr:full":"30 Fray's Close West Drayton Greater London UB7 7PF",
    "addr:housenumber":"30",
    "addr:postcode":"ub7 7pf",
    "addr:street":"Fray'S Close",
    "iso:country":"GB",
    "sg:address":"30 Fray's Close",
    "sg:city":"West Drayton",
    "sg:classifiers":[
        {
            "category":"Manufacturing",
            "subcategory":"Signs",
            "type":"Manufacturing & Wholesale Goods"
        }
    ],
    "sg:phone":"+44 1895 445658",
    "sg:postcode":"UB7 7PF",
    "sg:province":"Greater London",
    "sg:tags":[
        "writer"
    ],
    "wof:name":"Anderson Young",
    "wof:placetype":"venue"
},
  "geometry": {"coordinates":[-0.48098,51.502869],"type":"Point"}
}