{
  "type": "Feature",
  "properties": {
    "addr:full":"Lower Rectory Farm, Snarestone Road, Appleby Magna Swadlincote Derbyshire DE12 7AJ",
    "addr:postcode":"de12 7aj",
    "addr:street":"Rectory Farm Snarestone Road",
    "iso:country":"GB",
    "sg:address":"Lower Rectory Farm, Snarestone Road, Appleby Magna",
    "sg:city":"Swadlincote",
    "sg:classifiers":[
        {
            "category":"Retail",
            "subcategory":"Auto Repair",
            "type":"Services"
        }
    ],
    "sg:postcode":"DE12 7AJ",
    "sg:province":"Derbyshire",
    "sg:tags":[
        "car",
        "upholsterer"
    ],
    "wof:name":"Mosstrim",
    "wof:placetype":"venue"
},
  "geometry": {"coordinates":[-1.5351339579,52.6868896484],"type":"Point"}
}