{
  "type": "Feature",
  "properties": {
    "iso:country":"GB",
    "sg:address":"1 Wilson St",
    "sg:city":"Workington",
    "sg:classifiers":[
        {
            "category":"Professional",
            "subcategory":"Lawyer & Legal Services",
            "type":"Services"
        }
    ],
    "sg:postcode":"CA14 4AZ",
    "sg:province":"Cumbria",
    "sg:tags":[
        "solicitor"
    ],
    "wof:name":"Earle,Rowland,",
    "wof:placetype":"venue"
},
  "geometry": {"coordinates":[-3.542456,54.643398],"type":"Point"}
}