{
  "type": "Feature",
  "properties": {
    "addr:full":"Michael House, 35-37 Chiswell Street London Greater London EC1Y 4SE",
    "addr:housenumber":"35-37",
    "addr:postcode":"ec1y 4se",
    "addr:street":"Chiswell Street",
    "iso:country":"GB",
    "sg:address":"Michael House, 35-37 Chiswell Street",
    "sg:city":"London",
    "sg:classifiers":[
        {
            "category":"Banks & Credit Unions",
            "subcategory":"Financial Services",
            "type":"Services"
        }
    ],
    "sg:phone":"+44 20 7256 8000",
    "sg:postcode":"EC1Y 4SE",
    "sg:province":"Greater London",
    "sg:tags":[
        "adviser"
    ],
    "wof:name":"Capital Strategies Ltd.",
    "wof:placetype":"venue"
},
  "geometry": {"coordinates":[-0.09082,51.520985],"type":"Point"}
}