{
  "type": "Feature",
  "properties": {
    "iso:country":"GB",
    "sg:address":"481 Christchurch Road",
    "sg:city":"Bournemouth",
    "sg:classifiers":[
        {
            "category":"Travel",
            "subcategory":"Travel Agent",
            "type":"Entertainment"
        }
    ],
    "sg:phone":"+44 1202 304165",
    "sg:postcode":"BH1 4AD",
    "sg:province":"Dorset",
    "sg:tags":[
        "hotel",
        "agency",
        "booking"
    ],
    "wof:name":"Janet & Gordon Anstee Ltd.",
    "wof:placetype":"venue"
},
  "geometry": {"coordinates":[-1.8445299864,50.7250900269],"type":"Point"}
}