{
  "type": "Feature",
  "properties": {
    "addr:full":"112 Riverside Dr Mitcham Greater London CR4 4BW",
    "addr:housenumber":"112",
    "addr:postcode":"cr4 4bw",
    "addr:street":"Riverside Dr",
    "iso:country":"GB",
    "sg:address":"112 Riverside Dr",
    "sg:city":"Mitcham",
    "sg:classifiers":[
        {
            "category":"Social Services",
            "subcategory":"Retirement Home",
            "type":"Services"
        }
    ],
    "sg:phone":"+44 20 8640 0943",
    "sg:postcode":"CR4 4BW",
    "sg:province":"Greater London",
    "sg:tags":[
        "residential",
        "care"
    ],
    "wof:name":"Meadow House Residential Unit",
    "wof:placetype":"venue"
},
  "geometry": {"coordinates":[-0.169089,51.395889],"type":"Point"}
}