{
  "type": "Feature",
  "properties": {
    "iso:country":"GB",
    "sg:address":"Flanshaw Way, Flanshaw",
    "sg:city":"Wakefield",
    "sg:classifiers":[
        {
            "category":"Shopping",
            "subcategory":"Computers & Home Electronics",
            "type":"Retail Goods"
        }
    ],
    "sg:phone":"+44 1924 375611",
    "sg:postcode":"WF2 9LP",
    "sg:province":"West Yorkshire",
    "sg:tags":[
        "electrical"
    ],
    "wof:name":"Jack Hinton (Electrical) Ltd.",
    "wof:placetype":"venue"
},
  "geometry": {"coordinates":[-1.510274,53.67997],"type":"Point"}
}