{
  "type": "Feature",
  "properties": {
    "addr:full":"4 Scots Gate, Checkendon Reading Berkshire RG8 0TJ",
    "addr:housenumber":"4",
    "addr:postcode":"rg8 0tj",
    "addr:street":"Scots Gate",
    "iso:country":"GB",
    "sg:address":"4 Scots Gate, Checkendon",
    "sg:city":"Reading",
    "sg:classifiers":[
        {
            "category":"Retail",
            "subcategory":"Repair Shop",
            "type":"Services"
        }
    ],
    "sg:postcode":"RG8 0TJ",
    "sg:province":"Berkshire",
    "sg:tags":[
        "maintenance"
    ],
    "wof:name":"Norman Bollon",
    "wof:placetype":"venue"
},
  "geometry": {"coordinates":[-1.039394,51.546207],"type":"Point"}
}