{
  "type": "Feature",
  "properties": {
    "addr:full":"108 High Street, Staple Hill Bristol City of Bristol BS16 5NR",
    "addr:housenumber":"108",
    "addr:postcode":"bs16 5nr",
    "addr:street":"High Street",
    "iso:country":"GB",
    "sg:address":"108 High Street, Staple Hill",
    "sg:city":"Bristol",
    "sg:classifiers":[
        {
            "category":"Professional",
            "subcategory":"Management & Consulting",
            "type":"Services"
        }
    ],
    "sg:phone":"+44 117 970 1265",
    "sg:postcode":"BS16 5NR",
    "sg:province":"City of Bristol",
    "sg:tags":[
        "consultant",
        "business"
    ],
    "wof:name":"Practice Track Ltd.",
    "wof:placetype":"venue"
},
  "geometry": {"coordinates":[-2.515334,51.481468],"type":"Point"}
}