{
  "type": "Feature",
  "properties": {
    "iso:country":"GB",
    "sg:address":"52-53 Attwood Street, Lye",
    "sg:city":"Stourbridge",
    "sg:classifiers":[
        {
            "category":"Wholesale",
            "subcategory":"Scrap",
            "type":"Manufacturing & Wholesale Goods"
        }
    ],
    "sg:postcode":"DY9 8RU",
    "sg:province":"West Midlands",
    "sg:tags":[
        "waste",
        "metal"
    ],
    "wof:name":"D & W Metals",
    "wof:placetype":"venue"
},
  "geometry": {"coordinates":[-2.1047790051,52.4572181702],"type":"Point"}
}