{
  "type": "Feature",
  "properties": {
    "addr:full":"Dickens Avenue Great Yarmouth Norfolk NR30 3DT",
    "addr:postcode":"nr30 3dt",
    "addr:street":"Dickens Avenue",
    "iso:country":"GB",
    "sg:address":"Dickens Avenue",
    "sg:city":"Great Yarmouth",
    "sg:classifiers":[
        {
            "category":"Education",
            "subcategory":"School",
            "type":"Public Place"
        }
    ],
    "sg:phone":"+44 1493 855304",
    "sg:postcode":"NR30 3DT",
    "sg:province":"Norfolk",
    "sg:tags":[
        "local",
        "authority"
    ],
    "wof:name":"NORFOLK COUNTY COUNCIL",
    "wof:placetype":"venue"
},
  "geometry": {"coordinates":[1.7321150303,52.5952911377],"type":"Point"}
}