{
  "type": "Feature",
  "properties": {
    "iso:country":"GB",
    "sg:address":"23a Market Street",
    "sg:city":"Alton",
    "sg:classifiers":[
        {
            "category":"Home & Garden",
            "subcategory":"Home Furnishings",
            "type":"Retail Goods"
        }
    ],
    "sg:postcode":"GU34 1HA",
    "sg:province":"Hampshire",
    "sg:tags":[
        "beds",
        "bedding",
        "blanket"
    ],
    "wof:name":"Tiffany Textiles Ltd.",
    "wof:placetype":"venue"
},
  "geometry": {"coordinates":[-0.977209,51.148853],"type":"Point"}
}