{
  "type": "Feature",
  "properties": {
    "addr:full":"Grange Farm, Pertenhall Bedford Bedfordshire MK44 2SR",
    "addr:postcode":"mk44 2sr",
    "iso:country":"GB",
    "sg:address":"Grange Farm, Pertenhall",
    "sg:city":"Bedford",
    "sg:classifiers":[
        {
            "category":"Farming",
            "subcategory":"Livestock Farm",
            "type":"Manufacturing & Wholesale Goods"
        }
    ],
    "sg:phone":"+44 1480 860330",
    "sg:postcode":"MK44 2SR",
    "sg:province":"Bedfordshire",
    "sg:tags":[
        "others"
    ],
    "wof:name":"J M Shelton",
    "wof:placetype":"venue"
},
  "geometry": {"coordinates":[-0.413934,52.279301],"type":"Point"}
}