{
  "type": "Feature",
  "properties": {
    "addr:full":"19 Main Street, Uddingston Glasgow Glasgow City G71 7ES",
    "addr:housenumber":"19",
    "addr:postcode":"g71 7es",
    "addr:street":"Main Street",
    "iso:country":"GB",
    "sg:address":"19 Main Street, Uddingston",
    "sg:city":"Glasgow",
    "sg:classifiers":[
        {
            "category":"Health Services",
            "subcategory":"Optometrist",
            "type":"Services"
        }
    ],
    "sg:phone":"+44 1698 813318",
    "sg:postcode":"G71 7ES",
    "sg:province":"Glasgow City",
    "sg:tags":[
        "optician"
    ],
    "wof:name":"Jones & Hoyland",
    "wof:placetype":"venue"
},
  "geometry": {"coordinates":[-4.0821490288,55.818107605],"type":"Point"}
}