{
  "type": "Feature",
  "properties": {
    "iso:country":"GB",
    "sg:address":"Durham Indoor Market",
    "sg:city":"Durham",
    "sg:classifiers":[
        {
            "category":"Shopping",
            "subcategory":"Department Store",
            "type":"Retail Goods"
        },
        {
            "category":"Shopping",
            "subcategory":"Crafts & Fabrics",
            "type":"Retail Goods"
        }
    ],
    "sg:phone":"+44 191 386 7007",
    "sg:postcode":"DH1 3NJ",
    "sg:province":"Durham",
    "sg:tags":[
        "shop"
    ],
    "wof:name":"Walker Fabrics",
    "wof:placetype":"venue"
},
  "geometry": {"coordinates":[-1.5746079683,54.7775344849],"type":"Point"}
}