{
  "type": "Feature",
  "properties": {
    "addr:full":"5 The Grove Birmingham Warwickshire B46 3ET",
    "addr:housenumber":"5",
    "addr:postcode":"b46 3et",
    "addr:street":"The Grove",
    "iso:country":"GB",
    "sg:address":"5 The Grove",
    "sg:city":"Birmingham",
    "sg:classifiers":[
        {
            "category":"Professional",
            "subcategory":"Accounting & Tax Preparation",
            "type":"Services"
        }
    ],
    "sg:phone":"+44 1675 466789",
    "sg:postcode":"B46 3ET",
    "sg:province":"Warwickshire",
    "sg:tags":[
        "accountant"
    ],
    "wof:name":"Polar Summit Accounting Services",
    "wof:placetype":"venue"
},
  "geometry": {"coordinates":[-1.707529,52.48782],"type":"Point"}
}