{
  "type": "Feature",
  "properties": {
    "addr:full":"Craighead Cromarty Highland IV11 8XY",
    "addr:postcode":"iv11 8xy",
    "iso:country":"GB",
    "sg:address":"Craighead",
    "sg:city":"Cromarty",
    "sg:classifiers":[
        {
            "category":"Farming",
            "subcategory":"Livestock Farm",
            "type":"Manufacturing & Wholesale Goods"
        }
    ],
    "sg:phone":"+44 1381 620857",
    "sg:postcode":"IV11 8XY",
    "sg:province":"Highland",
    "sg:tags":[
        "others"
    ],
    "wof:name":"Agricultural Investment Syndicates Ltd.",
    "wof:placetype":"venue"
},
  "geometry": {"coordinates":[-4.0352888107,57.681224823],"type":"Point"}
}