{
  "type": "Feature",
  "properties": {
    "addr:full":"Smallmead Gate, Pingewood Reading Berkshire RG30 3UR",
    "addr:postcode":"rg30 3ur",
    "addr:street":"Smallmead Gate Pingewood",
    "iso:country":"GB",
    "sg:address":"Smallmead Gate, Pingewood",
    "sg:city":"Reading",
    "sg:classifiers":[
        {
            "category":"Professional",
            "type":"Services"
        },
        {
            "category":"Professional",
            "subcategory":"Employment Agencies",
            "type":"Services"
        }
    ],
    "sg:phone":"+44 118 975 4575",
    "sg:postcode":"RG30 3UR",
    "sg:province":"Berkshire",
    "sg:tags":[
        "consultant",
        "hire",
        "driver"
    ],
    "wof:name":"A S A P Driving & Industrial Services Ltd.",
    "wof:placetype":"venue"
},
  "geometry": {"coordinates":[-0.998919,51.424904],"type":"Point"}
}