{
  "type": "Feature",
  "properties": {
    "addr:full":"6 Winchester Road Bexleyheath Kent DA7 4TX",
    "addr:housenumber":"6",
    "addr:postcode":"da7 4tx",
    "addr:street":"Winchester Road",
    "iso:country":"GB",
    "sg:address":"6 Winchester Road",
    "sg:city":"Bexleyheath",
    "sg:classifiers":[
        {
            "category":"Building & Trades",
            "subcategory":"Construction",
            "type":"Services"
        }
    ],
    "sg:phone":"+44 20 8304 0189",
    "sg:postcode":"DA7 4TX",
    "sg:province":"Kent",
    "sg:tags":[
        "builder"
    ],
    "wof:name":"F & H Building Contractors",
    "wof:placetype":"venue"
},
  "geometry": {"coordinates":[0.1255680025,51.4664344788],"type":"Point"}
}