{
  "type": "Feature",
  "properties": {
    "addr:full":"6 Forestside Gardens Ringwood Dorset BH24 1SZ",
    "addr:housenumber":"6",
    "addr:postcode":"bh24 1sz",
    "addr:street":"Forestside Gardens",
    "iso:country":"GB",
    "sg:address":"6 Forestside Gardens",
    "sg:city":"Ringwood",
    "sg:classifiers":[
        {
            "category":"Professional",
            "subcategory":"Art Services",
            "type":"Services"
        }
    ],
    "sg:postcode":"BH24 1SZ",
    "sg:province":"Dorset",
    "sg:tags":[
        "photographer"
    ],
    "wof:name":"Forestside Photography",
    "wof:placetype":"venue"
},
  "geometry": {"coordinates":[-1.7696629763,50.8570899963],"type":"Point"}
}