{
  "type": "Feature",
  "properties": {
    "iso:country":"GB",
    "sg:address":"Batching Tower, Tumbling La",
    "sg:city":"Barnsley",
    "sg:classifiers":[
        {
            "category":"Home & Garden",
            "subcategory":"Building Materials",
            "type":"Retail Goods"
        }
    ],
    "sg:phone":"+44 1226 710565",
    "sg:postcode":"S71 5SA",
    "sg:province":"South Yorkshire",
    "sg:tags":[
        "ready",
        "mixed",
        "concrete"
    ],
    "wof:name":"Tarmac Topmix Ltd",
    "wof:placetype":"venue"
},
  "geometry": {"coordinates":[-1.43066,53.571739],"type":"Point"}
}