{
  "type": "Feature",
  "properties": {
    "addr:full":"51 Muirhouse Gardens Edinburgh City of Edinburgh EH4 4TD",
    "addr:housenumber":"51",
    "addr:postcode":"eh4 4td",
    "addr:street":"Muirhouse Gardens",
    "iso:country":"GB",
    "sg:address":"51 Muirhouse Gardens",
    "sg:city":"Edinburgh",
    "sg:classifiers":[
        {
            "category":"Food & Beverages",
            "subcategory":"Fruits & Vegetables",
            "type":"Retail Goods"
        }
    ],
    "sg:phone":"+44 131 538 7225",
    "sg:postcode":"EH4 4TD",
    "sg:province":"City of Edinburgh",
    "sg:tags":[
        "greengrocer"
    ],
    "wof:name":"El-Mexicano",
    "wof:placetype":"venue"
},
  "geometry": {"coordinates":[-3.2625229359,55.9720878601],"type":"Point"}
}