{
  "type": "Feature",
  "properties": {
    "addr:full":"109 Oxford Street Oldham Lancashire OL9 7SJ",
    "addr:housenumber":"109",
    "addr:postcode":"ol9 7sj",
    "addr:street":"Oxford Street",
    "iso:country":"GB",
    "sg:address":"109 Oxford Street",
    "sg:city":"Oldham",
    "sg:classifiers":[
        {
            "category":"Shopping",
            "subcategory":"Pharmacy",
            "type":"Retail Goods"
        }
    ],
    "sg:phone":"+44 161 624 1229",
    "sg:postcode":"OL9 7SJ",
    "sg:province":"Lancashire",
    "sg:tags":[
        "pharmacist",
        "chemist"
    ],
    "wof:name":"Oxford Street Pharmacy",
    "wof:placetype":"venue"
},
  "geometry": {"coordinates":[-2.136315,53.533768],"type":"Point"}
}