{
  "type": "Feature",
  "properties": {
    "addr:full":"The Abbey Clinic, 6a Albert Road Belvedere Kent DA17 5LJ",
    "addr:housenumber":"6a",
    "addr:postcode":"da17 5lj",
    "addr:street":"Albert Road",
    "iso:country":"GB",
    "sg:address":"The Abbey Clinic, 6a Albert Road",
    "sg:city":"Belvedere",
    "sg:classifiers":[
        {
            "category":"Health Services",
            "subcategory":"Health Practitioner",
            "type":"Services"
        }
    ],
    "sg:postcode":"DA17 5LJ",
    "sg:province":"Kent",
    "sg:tags":[
        "osteopath"
    ],
    "wof:name":"John R Roberts",
    "wof:placetype":"venue"
},
  "geometry": {"coordinates":[0.1525660008,51.4884223938],"type":"Point"}
}