{
  "type": "Feature",
  "properties": {
    "addr:full":"50 School Lane Rochdale Lancashire OL16 1QP",
    "addr:housenumber":"50",
    "addr:postcode":"ol16 1qp",
    "addr:street":"School Lane",
    "iso:country":"GB",
    "sg:address":"50 School Lane",
    "sg:city":"Rochdale",
    "sg:classifiers":[
        {
            "category":"Manufacturing",
            "subcategory":"Signs",
            "type":"Manufacturing & Wholesale Goods"
        }
    ],
    "sg:phone":"+44 1706 646401",
    "sg:postcode":"OL16 1QP",
    "sg:province":"Lancashire",
    "sg:tags":[
        "supplier",
        "nameplate"
    ],
    "wof:name":"S A Signs",
    "wof:placetype":"venue"
},
  "geometry": {"coordinates":[-2.1546449661,53.6143798828],"type":"Point"}
}