{
  "type": "Feature",
  "properties": {
    "iso:country":"GB",
    "sg:address":"5 Seymour Court, Manor Park",
    "sg:city":"Runcorn",
    "sg:classifiers":[
        {
            "category":"Wholesale",
            "subcategory":"Machinery & Supplies",
            "type":"Manufacturing & Wholesale Goods"
        }
    ],
    "sg:phone":"+44 1928 594400",
    "sg:postcode":"WA7 1UZ",
    "sg:province":"Cheshire",
    "wof:name":"Valtra Tractors (U K) Ltd.",
    "wof:placetype":"venue"
},
  "geometry": {"coordinates":[-2.674039,53.347481],"type":"Point"}
}