{
  "type": "Feature",
  "properties": {
    "addr:full":"27 Augusta Street Llandudno Conwy LL30 2AE",
    "addr:postcode":"ll30 2ae",
    "addr:street":"27 Augusta Street",
    "iso:country":"GB",
    "sg:address":"27 Augusta Street",
    "sg:city":"Llandudno",
    "sg:classifiers":[
        {
            "category":"Professional",
            "subcategory":"Lawyer & Legal Services",
            "type":"Services"
        }
    ],
    "sg:phone":"+44 1492 874774",
    "sg:postcode":"LL30 2AE",
    "sg:province":"Conwy",
    "sg:tags":[
        "solicitor"
    ],
    "wof:name":"J W Hughes & Co",
    "wof:placetype":"venue"
},
  "geometry": {"coordinates":[-3.8279969692,53.3217926025],"type":"Point"}
}