{
  "type": "Feature",
  "properties": {
    "addr:full":"52 London Rd Sevenoaks Kent TN13 1AS",
    "addr:housenumber":"52",
    "addr:postcode":"tn13 1as",
    "addr:street":"London Rd",
    "iso:country":"GB",
    "sg:address":"52 London Rd",
    "sg:city":"Sevenoaks",
    "sg:classifiers":[
        {
            "category":"Military Area",
            "subcategory":"Air Force Base",
            "type":"Public Place"
        }
    ],
    "sg:phone":"+44 1732 452089",
    "sg:postcode":"TN13 1AS",
    "sg:province":"Kent",
    "sg:tags":[
        "taxi",
        "hire",
        "private"
    ],
    "wof:name":"Victor Hire Taxis",
    "wof:placetype":"venue"
},
  "geometry": {"coordinates":[0.1907690018,51.2720222473],"type":"Point"}
}