{
  "type": "Feature",
  "properties": {
    "addr:full":"29 High Street, Milton Under Wychwood Chipping Norton Gloucestershire OX7 6LD",
    "addr:housenumber":"29",
    "addr:postcode":"ox7 6ld",
    "addr:street":"High Street;Under Wychwood",
    "iso:country":"GB",
    "sg:address":"29 High Street, Milton Under Wychwood",
    "sg:city":"Chipping Norton",
    "sg:classifiers":[
        {
            "category":"Education",
            "subcategory":"Library",
            "type":"Public Place"
        }
    ],
    "sg:phone":"+44 1993 830281",
    "sg:postcode":"OX7 6LD",
    "sg:province":"Gloucestershire",
    "sg:tags":[
        "book"
    ],
    "wof:name":"Milton under Wychwood Library",
    "wof:placetype":"venue"
},
  "geometry": {"coordinates":[-1.557421,51.86729],"type":"Point"}
}