{
  "type": "Feature",
  "properties": {
    "iso:country":"GB",
    "sg:address":"244 Warrington Road, Ince",
    "sg:city":"Wigan",
    "sg:classifiers":[
        {
            "category":"Building & Trades",
            "subcategory":"Construction",
            "type":"Services"
        }
    ],
    "sg:phone":"+44 1942 861311",
    "sg:postcode":"WN3 4NH",
    "sg:province":"Lancashire",
    "sg:tags":[
        "roofing"
    ],
    "wof:name":"D Shawcross Ltd.",
    "wof:placetype":"venue"
},
  "geometry": {"coordinates":[-2.616007,53.531582],"type":"Point"}
}