{
  "type": "Feature",
  "properties": {
    "iso:country":"GB",
    "sg:address":"2 Chapel Street",
    "sg:city":"Dewsbury",
    "sg:classifiers":[
        {
            "category":"Place Of Worship",
            "type":"Public Place"
        }
    ],
    "sg:phone":"+44 1924 461427",
    "sg:postcode":"WF12 9NQ",
    "sg:province":"West Yorkshire",
    "wof:name":"Saviletown Muslim Jamaat",
    "wof:placetype":"venue"
},
  "geometry": {"coordinates":[-1.627299,53.664471],"type":"Point"}
}