{
  "type": "Feature",
  "properties": {
    "iso:country":"GB",
    "sg:address":"241 Otley Road, West Park",
    "sg:city":"Leeds",
    "sg:classifiers":[
        {
            "category":"Shopping",
            "subcategory":"Pharmacy",
            "type":"Retail Goods"
        }
    ],
    "sg:phone":"+44 113 275 7727",
    "sg:postcode":"LS16 5LQ",
    "sg:province":"West Yorkshire",
    "sg:tags":[
        "medicine",
        "therapy"
    ],
    "wof:name":"Brahma Kumaris Meditation Centre",
    "wof:placetype":"venue"
},
  "geometry": {"coordinates":[-1.5915579796,53.8325920105],"type":"Point"}
}