{
  "type": "Feature",
  "properties": {
    "addr:full":"Higher Rew Farm Kingsbridge Devon TQ7 3DW",
    "addr:housenumber":"kingsbridge",
    "addr:postcode":"tq7 3dw",
    "addr:street":"Devon",
    "iso:country":"GB",
    "sg:address":"Higher Rew Farm",
    "sg:city":"Kingsbridge",
    "sg:classifiers":[
        {
            "category":"Travel",
            "subcategory":"Hotels & Motels",
            "type":"Entertainment"
        }
    ],
    "sg:phone":"+44 1548 843681",
    "sg:postcode":"TQ7 3DW",
    "sg:province":"Devon",
    "sg:tags":[
        "self",
        "catering"
    ],
    "wof:name":"Higher Rew Farm Cottage",
    "wof:placetype":"venue"
},
  "geometry": {"coordinates":[-3.777618885,50.2831039429],"type":"Point"}
}