{
  "type": "Feature",
  "properties": {
    "addr:full":"127 Daycott Avenue, Kenton Harrow Greater London HA3 0DA",
    "addr:housenumber":"127",
    "addr:postcode":"ha3 0da",
    "addr:street":"Daycott Avenue",
    "iso:country":"GB",
    "sg:address":"127 Daycott Avenue, Kenton",
    "sg:city":"Harrow",
    "sg:classifiers":[
        {
            "category":"Manufacturing",
            "subcategory":"Tools & Machinery",
            "type":"Manufacturing & Wholesale Goods"
        }
    ],
    "sg:phone":"+44 20 8907 8695",
    "sg:postcode":"HA3 0DA",
    "sg:province":"Greater London",
    "sg:tags":[
        "design",
        "maker"
    ],
    "wof:name":"Greenspan Designs",
    "wof:placetype":"venue"
},
  "geometry": {"coordinates":[-0.30712,51.576939],"type":"Point"}
}