{
  "type": "Feature",
  "properties": {
    "addr:full":"106 Radnor Avenue Welling Kent DA16 2BY",
    "addr:housenumber":"106",
    "addr:postcode":"da16 2by",
    "addr:street":"Radnor Avenue Welling",
    "iso:country":"GB",
    "sg:address":"106 Radnor Avenue",
    "sg:city":"Welling",
    "sg:classifiers":[
        {
            "category":"Building & Trades",
            "subcategory":"Construction",
            "type":"Services"
        }
    ],
    "sg:phone":"+44 20 8301 2446",
    "sg:postcode":"DA16 2BY",
    "sg:province":"Kent",
    "sg:tags":[
        "joiner",
        "carpenter"
    ],
    "wof:name":"John Spooner",
    "wof:placetype":"venue"
},
  "geometry": {"coordinates":[0.109252,51.453766],"type":"Point"}
}