{
  "type": "Feature",
  "properties": {
    "iso:country":"GB",
    "sg:address":"Rosebank Farm, Runcorn Road, Barnton",
    "sg:city":"Northwich",
    "sg:classifiers":[
        {
            "category":"Farming",
            "subcategory":"Livestock Farm",
            "type":"Manufacturing & Wholesale Goods"
        }
    ],
    "sg:phone":"+44 1606 74004",
    "sg:postcode":"CW8 4QD",
    "sg:province":"Cheshire",
    "sg:tags":[
        "others"
    ],
    "wof:name":"R Butterworth",
    "wof:placetype":"venue"
},
  "geometry": {"coordinates":[-2.5498259068,53.2706985474],"type":"Point"}
}