{
  "type": "Feature",
  "properties": {
    "addr:full":"10a Lythalls Lane Coventry Warwickshire CV6 6FJ",
    "addr:housenumber":"10a",
    "addr:postcode":"cv6 6fj",
    "addr:street":"Lythalls Lane",
    "iso:country":"GB",
    "sg:address":"10a Lythalls Lane",
    "sg:city":"Coventry",
    "sg:classifiers":[
        {
            "category":"Autos & Motor Vehicles",
            "subcategory":"Auto Supplies",
            "type":"Retail Goods"
        }
    ],
    "sg:phone":"+44 24 7663 8616",
    "sg:postcode":"CV6 6FJ",
    "sg:province":"Warwickshire",
    "sg:tags":[
        "electric"
    ],
    "wof:name":"M B K Motor Rewinds Ltd.",
    "wof:placetype":"venue"
},
  "geometry": {"coordinates":[-1.49515,52.437229],"type":"Point"}
}