{
  "type": "Feature",
  "properties": {
    "iso:country":"GB",
    "sg:address":"103 Canalot Production Studios, 222 Kensal Rd",
    "sg:city":"Ladbroke Grove",
    "sg:classifiers":[
        {
            "category":"Retail",
            "subcategory":"Event Space",
            "type":"Services"
        }
    ],
    "sg:phone":"+44 20 7792 9333",
    "sg:postcode":"W11 4XG",
    "sg:province":"Greater London",
    "sg:tags":[
        "exhibition",
        "organiser"
    ],
    "wof:name":"Project Green",
    "wof:placetype":"venue"
},
  "geometry": {"coordinates":[-0.21153,51.509979248],"type":"Point"}
}