{
  "type": "Feature",
  "properties": {
    "addr:full":"413 Warrington Road Warrington Cheshire WA3 5SW",
    "addr:housenumber":"413",
    "addr:postcode":"wa3 5sw",
    "addr:street":"Warrington Road",
    "iso:country":"GB",
    "sg:address":"413 Warrington Road",
    "sg:city":"Warrington",
    "sg:classifiers":[
        {
            "category":"Autos & Motor Vehicles",
            "subcategory":"Fuel & Gas Station",
            "type":"Retail Goods"
        }
    ],
    "sg:phone":"+44 1925 763398",
    "sg:postcode":"WA3 5SW",
    "sg:province":"Cheshire",
    "sg:tags":[
        "petrol",
        "filling"
    ],
    "wof:name":"Culcheth Service Station",
    "wof:placetype":"venue"
},
  "geometry": {"coordinates":[-2.5129170418,53.4526634216],"type":"Point"}
}