{
  "type": "Feature",
  "properties": {
    "iso:country":"GB",
    "sg:address":"6 Linden Place",
    "sg:city":"Loanhead",
    "sg:classifiers":[
        {
            "category":"Building & Trades",
            "subcategory":"Plumbing",
            "type":"Services"
        }
    ],
    "sg:phone":"+44 131 440 3228",
    "sg:postcode":"EH20 9RY",
    "sg:province":"Midlothian",
    "sg:tags":[
        "heating"
    ],
    "wof:name":"Mbm Plumbing",
    "wof:placetype":"venue"
},
  "geometry": {"coordinates":[-3.143513,55.877895],"type":"Point"}
}