{
  "type": "Feature",
  "properties": {
    "iso:country":"GB",
    "sg:address":"Hutton Industrial Estate, Wash Road",
    "sg:city":"Brentwood",
    "sg:classifiers":[
        {
            "category":"Utilities",
            "subcategory":"Natural Gas",
            "type":"Services"
        }
    ],
    "sg:postcode":"CM13 1TA",
    "sg:province":"Essex",
    "sg:tags":[
        "consultant",
        "air conditioning"
    ],
    "wof:name":"Curair Consulting Engineers",
    "wof:placetype":"venue"
},
  "geometry": {"coordinates":[0.35773,51.63868],"type":"Point"}
}