{
  "type": "Feature",
  "properties": {
    "iso:country":"GB",
    "sg:address":"5 Whitby Parade, Whitby Road",
    "sg:city":"Ruislip",
    "sg:classifiers":[
        {
            "category":"Home & Garden",
            "subcategory":"Household Appliances",
            "type":"Retail Goods"
        },
        {
            "category":"Retail",
            "subcategory":"Event Space",
            "type":"Services"
        }
    ],
    "sg:phone":"+44 20 8866 0196",
    "sg:postcode":"HA4 9EA",
    "sg:province":"Greater London",
    "sg:tags":[
        "product",
        "electrical",
        "sales"
    ],
    "wof:name":"STEADY'S",
    "wof:placetype":"venue"
},
  "geometry": {"coordinates":[-0.40452,51.564243],"type":"Point"}
}