{
  "type": "Feature",
  "properties": {
    "iso:country":"GB",
    "sg:address":"The Vicarage",
    "sg:city":"Torquay",
    "sg:classifiers":[
        {
            "category":"Place Of Worship",
            "type":"Public Place"
        }
    ],
    "sg:phone":"+44 1803 607957",
    "sg:postcode":"TQ2 6QW",
    "sg:province":"Devon",
    "wof:name":"Cockington Parish Church",
    "wof:placetype":"venue"
},
  "geometry": {"coordinates":[-3.5467090607,50.4662017822],"type":"Point"}
}