{
  "type": "Feature",
  "properties": {
    "iso:country":"GB",
    "sg:address":"16 Helena Close, Portslade",
    "sg:city":"Brighton",
    "sg:classifiers":[
        {
            "category":"Banks & Credit Unions",
            "subcategory":"Financial Services",
            "type":"Services"
        }
    ],
    "sg:phone":"+44 1273 422424",
    "sg:postcode":"BN41 2DQ",
    "sg:province":"East Sussex",
    "sg:tags":[
        "consultant"
    ],
    "wof:name":"Darion Finance & Marketing",
    "wof:placetype":"venue"
},
  "geometry": {"coordinates":[-0.2099490017,50.8445205688],"type":"Point"}
}