{
  "type": "Feature",
  "properties": {
    "iso:country":"GB",
    "sg:address":"38 Belvedere Road",
    "sg:city":"Taunton",
    "sg:classifiers":[
        {
            "category":"Professional",
            "subcategory":"Lawyer & Legal Services",
            "type":"Services"
        }
    ],
    "sg:postcode":"TA1 1HD",
    "sg:province":"Somerset",
    "sg:tags":[
        "advice",
        "counselling"
    ],
    "wof:name":"Somerset Psychodynamic Counselling Centr",
    "wof:placetype":"venue"
},
  "geometry": {"coordinates":[-3.105549,51.021301],"type":"Point"}
}