{
  "type": "Feature",
  "properties": {
    "addr:full":"Irvinehill Farm, Stewarton Kilmarnock East Ayrshire KA3 3EL",
    "addr:postcode":"ka3 3el",
    "addr:street":"East",
    "iso:country":"GB",
    "sg:address":"Irvinehill Farm, Stewarton",
    "sg:city":"Kilmarnock",
    "sg:classifiers":[
        {
            "category":"Professional",
            "subcategory":"Printing & Photocopies",
            "type":"Services"
        }
    ],
    "sg:postcode":"KA3 3EL",
    "sg:province":"East Ayrshire",
    "sg:tags":[
        "printer"
    ],
    "wof:name":"Gilmour Print",
    "wof:placetype":"venue"
},
  "geometry": {"coordinates":[-4.5808401108,55.6719512939],"type":"Point"}
}