{
  "type": "Feature",
  "properties": {
    "addr:full":"32 Jubilee Drive Loughborough Leicestershire LE11 5XS",
    "addr:housenumber":"32",
    "addr:postcode":"le11 5xs",
    "addr:street":"Jubilee Drive",
    "iso:country":"GB",
    "sg:address":"32 Jubilee Drive",
    "sg:city":"Loughborough",
    "sg:classifiers":[
        {
            "category":"Wholesale",
            "subcategory":"Office Equipment",
            "type":"Manufacturing & Wholesale Goods"
        },
        {
            "category":"Shopping",
            "subcategory":"Stationery & Office Supplies",
            "type":"Retail Goods"
        }
    ],
    "sg:phone":"+44 1509 214489",
    "sg:postcode":"LE11 5XS",
    "sg:province":"Leicestershire",
    "sg:tags":[
        "supplier",
        "furniture"
    ],
    "wof:name":"Wells & Blackwell Ltd",
    "wof:placetype":"venue"
},
  "geometry": {"coordinates":[-1.213934,52.78109],"type":"Point"}
}