{
  "type": "Feature",
  "properties": {
    "addr:full":"94a Willow Street Oswestry Shropshire SY11 1AL",
    "addr:housenumber":"94a",
    "addr:postcode":"sy11 1al",
    "addr:street":"Willow Street",
    "iso:country":"GB",
    "sg:address":"94a Willow Street",
    "sg:city":"Oswestry",
    "sg:classifiers":[
        {
            "category":"Autos & Motor Vehicles",
            "subcategory":"Auto Supplies",
            "type":"Retail Goods"
        }
    ],
    "sg:phone":"+44 1691 652159",
    "sg:postcode":"SY11 1AL",
    "sg:province":"Shropshire",
    "sg:tags":[
        "tyre"
    ],
    "wof:name":"National Tyres and Autocare",
    "wof:placetype":"venue"
},
  "geometry": {"coordinates":[-3.05886,52.861774],"type":"Point"}
}