{
  "type": "Feature",
  "properties": {
    "iso:country":"GB",
    "sg:address":"Banks Road",
    "sg:city":"Wirral",
    "sg:classifiers":[
        {
            "category":"Retail",
            "subcategory":"Auto Repair",
            "type":"Services"
        }
    ],
    "sg:phone":"+44 151 625 5041",
    "sg:postcode":"CH48 3HU",
    "sg:province":"Merseyside",
    "sg:tags":[
        "modification",
        "garage"
    ],
    "wof:name":"Hydro Service Station",
    "wof:placetype":"venue"
},
  "geometry": {"coordinates":[-3.1823439598,53.3672103882],"type":"Point"}
}