{
  "type": "Feature",
  "properties": {
    "addr:full":"Bridge St Bakewell Derbyshire DE45 1FY",
    "addr:postcode":"de45 1fy",
    "addr:street":"Bridge St",
    "iso:country":"GB",
    "sg:address":"Bridge St",
    "sg:city":"Bakewell",
    "sg:classifiers":[
        {
            "category":"Personal",
            "type":"Services"
        }
    ],
    "sg:phone":"+44 1629 812978",
    "sg:postcode":"DE45 1FY",
    "sg:province":"Derbyshire",
    "sg:tags":[
        "delivery"
    ],
    "wof:name":"Royal Mail",
    "wof:placetype":"venue"
},
  "geometry": {"coordinates":[-1.672339,53.214729],"type":"Point"}
}