{
  "type": "Feature",
  "properties": {
    "iso:country":"GB",
    "sg:address":"Woodend Colliery, Armadale",
    "sg:city":"Bathgate",
    "sg:classifiers":[
        {
            "category":"Utilities",
            "subcategory":"Fuel Oil & Lpg",
            "type":"Services"
        }
    ],
    "sg:phone":"+44 1501 730231",
    "sg:postcode":"EH48 3AP",
    "sg:province":"West Lothian",
    "wof:name":"Anglo Solid Fuel (Scotland)",
    "wof:placetype":"venue"
},
  "geometry": {"coordinates":[-3.709956,55.901894],"type":"Point"}
}