{
  "type": "Feature",
  "properties": {
    "addr:full":"Babcombe Farm, Chudleigh Newton Abbot Devon TQ13 0AG",
    "addr:postcode":"tq13 0ag",
    "iso:country":"GB",
    "sg:address":"Babcombe Farm, Chudleigh",
    "sg:city":"Newton Abbot",
    "sg:classifiers":[
        {
            "category":"Home & Garden",
            "subcategory":"Hardware",
            "type":"Retail Goods"
        }
    ],
    "sg:phone":"+44 1626 852322",
    "sg:postcode":"TQ13 0AG",
    "sg:province":"Devon",
    "sg:tags":[
        "part",
        "accessory"
    ],
    "wof:name":"G & J Hollis",
    "wof:placetype":"venue"
},
  "geometry": {"coordinates":[-3.6016008854,50.6042289734],"type":"Point"}
}