{
  "type": "Feature",
  "properties": {
    "addr:full":"14-15 Irving Street London Greater London WC2H 7AF",
    "addr:housenumber":"14-15",
    "addr:postcode":"wc2h 7af",
    "addr:street":"Irving Street",
    "iso:country":"GB",
    "sg:address":"14-15 Irving Street",
    "sg:city":"London",
    "sg:classifiers":[
        {
            "category":"Restaurant",
            "type":"Food & Drink"
        }
    ],
    "sg:postcode":"WC2H 7AF",
    "sg:province":"Greater London",
    "sg:tags":[
        "indian"
    ],
    "wof:name":"Akash Indian Restaurant",
    "wof:placetype":"venue"
},
  "geometry": {"coordinates":[-0.1289020032,51.5097770691],"type":"Point"}
}