{
  "type": "Feature",
  "properties": {
    "addr:full":"Fardre Court Pontypridd Rhondda, Cynon, Taff CF38 1AE",
    "addr:postcode":"cf38 1ae",
    "addr:street":"Fardre Court;Cynon Taff",
    "iso:country":"GB",
    "sg:address":"Fardre Court",
    "sg:city":"Pontypridd",
    "sg:classifiers":[
        {
            "category":"Social Services",
            "type":"Services"
        }
    ],
    "sg:phone":"+44 1443 206553",
    "sg:postcode":"CF38 1AE",
    "sg:province":"Rhondda, Cynon, Taff",
    "wof:name":"Silverbrook Resource Centre",
    "wof:placetype":"venue"
},
  "geometry": {"coordinates":[-3.3230369091,51.5696182251],"type":"Point"}
}