{
  "type": "Feature",
  "properties": {
    "addr:full":"Yarborough Congregation Hall, 156 Cromwell Rd Grimsby Lincolnshire DN31 2BA",
    "addr:housenumber":"156",
    "addr:postcode":"dn31 2ba",
    "addr:street":"Cromwell Rd",
    "iso:country":"GB",
    "sg:address":"Yarborough Congregation Hall, 156 Cromwell Rd",
    "sg:city":"Grimsby",
    "sg:classifiers":[
        {
            "category":"Organizations",
            "subcategory":"Religious Organization",
            "type":"Services"
        }
    ],
    "sg:phone":"+44 1472 241516",
    "sg:postcode":"DN31 2BA",
    "sg:province":"Lincolnshire",
    "sg:tags":[
        "organisation"
    ],
    "wof:name":"Jehovah's Witnesses",
    "wof:placetype":"venue"
},
  "geometry": {"coordinates":[-0.10236,53.56599],"type":"Point"}
}