{
  "type": "Feature",
  "properties": {
    "iso:country":"GB",
    "sg:address":"Unit 1 Butts Farm Courtyard, The Butts",
    "sg:city":"Cirencester",
    "sg:classifiers":[
        {
            "category":"Wholesale",
            "subcategory":"Machinery & Supplies",
            "type":"Manufacturing & Wholesale Goods"
        }
    ],
    "sg:postcode":"GL7 5HY",
    "sg:province":"Gloucestershire",
    "wof:name":"M J S International Ltd.",
    "wof:placetype":"venue"
},
  "geometry": {"coordinates":[-1.953541,51.718548],"type":"Point"}
}