{
  "type": "Feature",
  "properties": {
    "iso:country":"GB",
    "sg:address":"100 Oulton Road",
    "sg:city":"Lowestoft",
    "sg:classifiers":[
        {
            "category":"Autos & Motor Vehicles",
            "subcategory":"Fuel & Gas Station",
            "type":"Retail Goods"
        }
    ],
    "sg:phone":"+44 1502 501500",
    "sg:postcode":"NR32 4QR",
    "sg:province":"Suffolk",
    "sg:tags":[
        "petrol",
        "filling"
    ],
    "wof:name":"College Farm Service Station",
    "wof:placetype":"venue"
},
  "geometry": {"coordinates":[1.732805,52.486927],"type":"Point"}
}