{
  "type": "Feature",
  "properties": {
    "addr:full":"21 Priory Street Lewes East Sussex BN7 1HH",
    "addr:housenumber":"21",
    "addr:postcode":"bn7 1hh",
    "addr:street":"Priory Street",
    "iso:country":"GB",
    "sg:address":"21 Priory Street",
    "sg:city":"Lewes",
    "sg:classifiers":[
        {
            "category":"Government",
            "subcategory":"Post Office",
            "type":"Public Place"
        }
    ],
    "sg:phone":"+44 1273 474974",
    "sg:postcode":"BN7 1HH",
    "sg:province":"East Sussex",
    "wof:name":"Southover Post Office",
    "wof:placetype":"venue"
},
  "geometry": {"coordinates":[0.008912,50.869553],"type":"Point"}
}