{
  "type": "Feature",
  "properties": {
    "addr:full":"Meltham Rd, Lockwood Huddersfield West Yorkshire HD4 7BG",
    "addr:postcode":"hd4 7bg",
    "addr:street":"Meltham Rd;West",
    "iso:country":"GB",
    "sg:address":"Meltham Rd, Lockwood",
    "sg:city":"Huddersfield",
    "sg:classifiers":[
        {
            "category":"Arena",
            "subcategory":"Sports Club",
            "type":"Entertainment"
        }
    ],
    "sg:postcode":"HD4 7BG",
    "sg:province":"West Yorkshire",
    "wof:name":"Woodfield Park Police Sports Ground",
    "wof:placetype":"venue"
},
  "geometry": {"coordinates":[-1.806453,53.625172],"type":"Point"}
}