{
  "type": "Feature",
  "properties": {
    "addr:full":"28 High Street Leighton Buzzard Bedfordshire LU7 1EA",
    "addr:housenumber":"28",
    "addr:postcode":"lu7 1ea",
    "addr:street":"High Street",
    "iso:country":"GB",
    "sg:address":"28 High Street",
    "sg:city":"Leighton Buzzard",
    "sg:classifiers":[
        {
            "category":"Travel",
            "subcategory":"Travel Agent",
            "type":"Entertainment"
        }
    ],
    "sg:phone":"+44 1525 851306",
    "sg:postcode":"LU7 1EA",
    "sg:province":"Bedfordshire",
    "wof:name":"Co-Op Travelcare",
    "wof:placetype":"venue"
},
  "geometry": {"coordinates":[-0.6632300019,51.9159622192],"type":"Point"}
}