{
  "type": "Feature",
  "properties": {
    "addr:full":"858 Chester Road, Stretford Manchester Cheshire M32 0QJ",
    "addr:housenumber":"858",
    "addr:postcode":"m32 0qj",
    "addr:street":"Chester Road",
    "iso:country":"GB",
    "sg:address":"858 Chester Road, Stretford",
    "sg:city":"Manchester",
    "sg:classifiers":[
        {
            "category":"Health Services",
            "subcategory":"Dentist",
            "type":"Services"
        }
    ],
    "sg:phone":"+44 161 864 3250",
    "sg:postcode":"M32 0QJ",
    "sg:province":"Cheshire",
    "wof:name":"The Dental Team",
    "wof:placetype":"venue"
},
  "geometry": {"coordinates":[-2.297389,53.455654],"type":"Point"}
}