{
  "type": "Feature",
  "properties": {
    "iso:country":"GB",
    "sg:address":"8 The Forum",
    "sg:city":"Wallsend",
    "sg:classifiers":[
        {
            "category":"Transit Center",
            "subcategory":"Freight",
            "type":"Transportation"
        },
        {
            "category":"Commercial Area",
            "type":"Public Place"
        },
        {
            "category":"Real Estate",
            "subcategory":"Real Estate Agent",
            "type":"Services"
        },
        {
            "category":"Organizations",
            "subcategory":"Membership Organization",
            "type":"Services"
        }
    ],
    "sg:phone":"+44 191 263 5095",
    "sg:postcode":"NE28 8JR",
    "sg:province":"Tyne and Wear",
    "sg:tags":[
        "shop",
        "shopping",
        "centre"
    ],
    "wof:name":"In Shops Centres Ltd.",
    "wof:placetype":"venue"
},
  "geometry": {"coordinates":[-1.545512,54.999081],"type":"Point"}
}