{
  "type": "Feature",
  "properties": {
    "iso:country":"GB",
    "sg:address":"107 Rainsford Road",
    "sg:city":"Chelmsford",
    "sg:classifiers":[
        {
            "category":"Retail",
            "subcategory":"Auto Rental",
            "type":"Services"
        }
    ],
    "sg:postcode":"CM1 2PF",
    "sg:province":"Essex",
    "sg:tags":[
        "car"
    ],
    "wof:name":"Budget Rent A Car",
    "wof:placetype":"venue"
},
  "geometry": {"coordinates":[0.4583170116,51.7392692566],"type":"Point"}
}