{
  "type": "Feature",
  "properties": {
    "iso:country":"GB",
    "sg:address":"Robert Beard Youth Centre, Annexe High Street",
    "sg:city":"Hornchurch",
    "sg:classifiers":[
        {
            "category":"Organizations",
            "subcategory":"Membership Organization",
            "type":"Services"
        }
    ],
    "sg:phone":"+44 1277 811739",
    "sg:postcode":"RM11 3XU",
    "sg:province":"Essex",
    "sg:tags":[
        "club"
    ],
    "wof:name":"Havering 18 Plus Group",
    "wof:placetype":"venue"
},
  "geometry": {"coordinates":[0.2203799933,51.5620994568],"type":"Point"}
}