{
  "type": "Feature",
  "properties": {
    "iso:country":"GB",
    "sg:address":"98a Louise Road",
    "sg:city":"Northampton",
    "sg:classifiers":[
        {
            "category":"Personal",
            "type":"Services"
        }
    ],
    "sg:phone":"+44 1604 604308",
    "sg:postcode":"NN1 3RR",
    "sg:province":"Northamptonshire",
    "sg:tags":[
        "tailor"
    ],
    "wof:name":"Etriel Tailors",
    "wof:placetype":"venue"
},
  "geometry": {"coordinates":[-0.896686,52.245071],"type":"Point"}
}