{
  "type": "Feature",
  "properties": {
    "iso:country":"GB",
    "sg:address":"10 York Road",
    "sg:city":"Whitley Bay",
    "sg:classifiers":[
        {
            "category":"Retail",
            "subcategory":"Repair Shop",
            "type":"Services"
        }
    ],
    "sg:postcode":"NE26 1AB",
    "sg:province":"Northumberland",
    "sg:tags":[
        "upholsterer"
    ],
    "wof:name":"New Life Interiors",
    "wof:placetype":"venue"
},
  "geometry": {"coordinates":[-1.4451429844,55.0428123474],"type":"Point"}
}