{
  "type": "Feature",
  "properties": {
    "addr:full":"The Old Chapel, Fangfoss York East Riding of Yorkshire YO41 5QP",
    "addr:postcode":"yo41 5qp",
    "iso:country":"GB",
    "sg:address":"The Old Chapel, Fangfoss",
    "sg:city":"York",
    "sg:classifiers":[
        {
            "category":"Home & Garden",
            "subcategory":"Home Furnishings",
            "type":"Retail Goods"
        }
    ],
    "sg:postcode":"YO41 5QP",
    "sg:province":"East Riding of Yorkshire",
    "sg:tags":[
        "beds",
        "bedding",
        "blanket"
    ],
    "wof:name":"Harry Postill Beds",
    "wof:placetype":"venue"
},
  "geometry": {"coordinates":[-0.8353139758,53.9696807861],"type":"Point"}
}