{
  "type": "Feature",
  "properties": {
    "addr:full":"Princess St, Off Liverpool Rd Wigan Lancashire WN2 3HJ",
    "addr:postcode":"wn2 3hj",
    "addr:street":"Princess St Off Liverpool Rd",
    "iso:country":"GB",
    "sg:address":"Princess St, Off Liverpool Rd",
    "sg:city":"Wigan",
    "sg:classifiers":[
        {
            "category":"Education",
            "subcategory":"Special Training",
            "type":"Public Place"
        }
    ],
    "sg:phone":"+44 1942 255585",
    "sg:postcode":"WN2 3HJ",
    "sg:province":"Lancashire",
    "sg:tags":[
        "school"
    ],
    "wof:name":"Borsdane Brook School",
    "wof:placetype":"venue"
},
  "geometry": {"coordinates":[-2.583824,53.531849],"type":"Point"}
}