{
  "type": "Feature",
  "properties": {
    "addr:full":"Satellite Ho 160 Blackswarth Rd Bristol City of Bristol BS5 8AG",
    "addr:housenumber":"160",
    "addr:postcode":"bs5 8ag",
    "addr:street":"Blackswarth Rd",
    "iso:country":"GB",
    "sg:address":"Satellite Ho 160 Blackswarth Rd",
    "sg:city":"Bristol",
    "sg:classifiers":[
        {
            "category":"Professional",
            "subcategory":"Art Services",
            "type":"Services"
        }
    ],
    "sg:postcode":"BS5 8AG",
    "sg:province":"City of Bristol",
    "sg:tags":[
        "graphic",
        "designer"
    ],
    "wof:name":"Murphy,Julian,Design",
    "wof:placetype":"venue"
},
  "geometry": {"coordinates":[-2.55083,51.45475],"type":"Point"}
}