{
  "type": "Feature",
  "properties": {
    "addr:full":"80 Derby Lodge, Wicklow St Bloomsbury Greater London WC1X 9LF",
    "addr:housenumber":"80",
    "addr:postcode":"wc1x 9lf",
    "addr:street":"Derby Lodge Wicklow St",
    "iso:country":"GB",
    "sg:address":"80 Derby Lodge, Wicklow St",
    "sg:city":"Bloomsbury",
    "sg:classifiers":[
        {
            "category":"Professional",
            "subcategory":"Employment Agencies",
            "type":"Services"
        }
    ],
    "sg:phone":"+44 20 7430 0628",
    "sg:postcode":"WC1X 9LF",
    "sg:province":"Greater London",
    "sg:tags":[
        "consultant"
    ],
    "wof:name":"Innconnection Management Selection Ltd",
    "wof:placetype":"venue"
},
  "geometry": {"coordinates":[-0.1180939972,51.5295829773],"type":"Point"}
}