{
  "type": "Feature",
  "properties": {
    "addr:full":"128 Derby Lane Liverpool Merseyside L13 3DW",
    "addr:housenumber":"128",
    "addr:postcode":"l13 3dw",
    "addr:street":"Derby Lane",
    "iso:country":"GB",
    "sg:address":"128 Derby Lane",
    "sg:city":"Liverpool",
    "sg:classifiers":[
        {
            "category":"Personal",
            "subcategory":"Beauty Salon",
            "type":"Services"
        }
    ],
    "sg:postcode":"L13 3DW",
    "sg:province":"Merseyside",
    "sg:tags":[
        "unisex",
        "hairdresser"
    ],
    "wof:name":"Nouveaux Hair Dressing",
    "wof:placetype":"venue"
},
  "geometry": {"coordinates":[-2.915247,53.417938],"type":"Point"}
}