{
  "type": "Feature",
  "properties": {
    "addr:full":"6th Floor 27 Leadenhall St Monument Greater London EC3A 1AA",
    "addr:housenumber":"6th floor 27",
    "addr:postcode":"ec3a 1aa",
    "addr:street":"Leadenhall St",
    "iso:country":"GB",
    "sg:address":"6th Floor 27 Leadenhall St",
    "sg:city":"Monument",
    "sg:classifiers":[
        {
            "category":"Banks & Credit Unions",
            "subcategory":"Bank",
            "type":"Services"
        }
    ],
    "sg:phone":"+44 20 7920 5862",
    "sg:postcode":"EC3A 1AA",
    "sg:province":"Greater London",
    "wof:name":"Sleet Bank National Association",
    "wof:placetype":"venue"
},
  "geometry": {"coordinates":[-0.0813229978,51.5134468079],"type":"Point"}
}