{
  "type": "Feature",
  "properties": {
    "iso:country":"GB",
    "sg:address":"10 London Road",
    "sg:city":"Worcester",
    "sg:classifiers":[
        {
            "category":"Manufacturing",
            "subcategory":"Metals",
            "type":"Manufacturing & Wholesale Goods"
        }
    ],
    "sg:phone":"+44 1905 764077",
    "sg:postcode":"WR5 2DL",
    "sg:province":"Worcestershire",
    "wof:name":"Peter Robinson Customising",
    "wof:placetype":"venue"
},
  "geometry": {"coordinates":[-2.2155,52.186329],"type":"Point"}
}