{
  "type": "Feature",
  "properties": {
    "addr:full":"Brook St Loughborough Leicestershire LE12 9RG",
    "addr:postcode":"le12 9rg",
    "addr:street":"Brook St",
    "iso:country":"GB",
    "sg:address":"Brook St",
    "sg:city":"Loughborough",
    "sg:classifiers":[
        {
            "category":"Building & Trades",
            "subcategory":"Construction",
            "type":"Services"
        }
    ],
    "sg:phone":"+44 1509 508131",
    "sg:postcode":"LE12 9RG",
    "sg:province":"Leicestershire",
    "sg:tags":[
        "valve"
    ],
    "wof:name":"Kenway Ltd",
    "wof:placetype":"venue"
},
  "geometry": {"coordinates":[-1.288422,52.77668],"type":"Point"}
}