{
  "type": "Feature",
  "properties": {
    "addr:full":"1 Castleman Ct, Station Rd Ferndown Dorset BH22 0JY",
    "addr:housenumber":"1",
    "addr:postcode":"bh22 0jy",
    "addr:street":"Castleman Ct Station Rd",
    "iso:country":"GB",
    "sg:address":"1 Castleman Ct, Station Rd",
    "sg:city":"Ferndown",
    "sg:classifiers":[
        {
            "category":"Social Services",
            "subcategory":"Adult Care",
            "type":"Services"
        },
        {
            "category":"Social Services",
            "subcategory":"Retirement Home",
            "type":"Services"
        }
    ],
    "sg:phone":"+44 1202 897290",
    "sg:postcode":"BH22 0JY",
    "sg:province":"Dorset",
    "sg:tags":[
        "housing",
        "sheltered",
        "accommodation"
    ],
    "wof:name":"Castleman Court",
    "wof:placetype":"venue"
},
  "geometry": {"coordinates":[-1.8894690275,50.8268318176],"type":"Point"}
}