{
  "type": "Feature",
  "properties": {
    "iso:country":"GB",
    "sg:address":"Unit 12, George Shopping Centre",
    "sg:city":"Grantham",
    "sg:classifiers":[
        {
            "category":"Food & Beverages",
            "subcategory":"Candy",
            "type":"Retail Goods"
        }
    ],
    "sg:postcode":"NG31 6RH",
    "sg:province":"Lincolnshire",
    "sg:tags":[
        "confectioner"
    ],
    "wof:name":"The Chocshop",
    "wof:placetype":"venue"
},
  "geometry": {"coordinates":[-0.638289,52.911961],"type":"Point"}
}