{
  "type": "Feature",
  "properties": {
    "addr:full":"Grave Church House, 25-35 Castle Way Southampton Hampshire SO14 2BW",
    "addr:housenumber":"25-35",
    "addr:postcode":"so14 2bw",
    "addr:street":"Castle Way",
    "iso:country":"GB",
    "sg:address":"Grave Church House, 25-35 Castle Way",
    "sg:city":"Southampton",
    "sg:classifiers":[
        {
            "category":"Banks & Credit Unions",
            "subcategory":"Bank",
            "type":"Services"
        }
    ],
    "sg:phone":"+44 23 8033 9057",
    "sg:postcode":"SO14 2BW",
    "sg:province":"Hampshire",
    "wof:name":"T S B Commercial Services",
    "wof:placetype":"venue"
},
  "geometry": {"coordinates":[-1.4046829939,50.900554657],"type":"Point"}
}