{
  "type": "Feature",
  "properties": {
    "iso:country":"GB",
    "sg:address":"Community Central Hall, 304 Maryhill Road",
    "sg:city":"Glasgow",
    "sg:classifiers":[
        {
            "category":"Organizations",
            "subcategory":"Non-profit Organization",
            "type":"Services"
        }
    ],
    "sg:phone":"+44 141 579 0008",
    "sg:postcode":"G20 7YE",
    "sg:province":"Glasgow City",
    "sg:tags":[
        "charitable",
        "organisation",
        "voluntary",
        "charity"
    ],
    "wof:name":"Crossroads Glasgow West Care Attendant Scheme",
    "wof:placetype":"venue"
},
  "geometry": {"coordinates":[-4.27078,55.876709],"type":"Point"}
}