{
  "type": "Feature",
  "properties": {
    "addr:full":"Lochmaddy, Isle Of North Uist Lochmaddy Eilean Siar HS6 5AE",
    "addr:postcode":"hs6 5ae",
    "addr:street":"Lochmaddy",
    "iso:country":"GB",
    "sg:address":"Lochmaddy, Isle Of North Uist",
    "sg:city":"Lochmaddy",
    "sg:classifiers":[
        {
            "category":"Social Services",
            "type":"Services"
        },
        {
            "category":"Government",
            "subcategory":"Office",
            "type":"Public Place"
        }
    ],
    "sg:phone":"+44 1876 500375",
    "sg:postcode":"HS6 5AE",
    "sg:province":"Eilean Siar",
    "sg:tags":[
        "local",
        "ds"
    ],
    "wof:name":"Craigard Resource Centre",
    "wof:placetype":"venue"
},
  "geometry": {"coordinates":[-7.157369,57.597195],"type":"Point"}
}