{
  "type": "Feature",
  "properties": {
    "addr:full":"Meadway Barnet Hertfordshire EN5 5RR",
    "addr:postcode":"en5 5rr",
    "addr:street":"Meadway",
    "iso:country":"GB",
    "sg:address":"Meadway",
    "sg:city":"Barnet",
    "sg:classifiers":[
        {
            "category":"Government",
            "subcategory":"City Hall",
            "type":"Public Place"
        }
    ],
    "sg:phone":"+44 20 8441 2933",
    "sg:postcode":"EN5 5RR",
    "sg:province":"Hertfordshire",
    "wof:name":"Queen Elizabeth Centre",
    "wof:placetype":"venue"
},
  "geometry": {"coordinates":[-0.1883179992,51.6534500122],"type":"Point"}
}