{
  "type": "Feature",
  "properties": {
    "addr:full":"Corringham Hall, Springhouse Road, Corringham Stanford-le-hope Essex SS17 7LE",
    "addr:postcode":"ss17 7le",
    "addr:street":"Springhouse Road",
    "iso:country":"GB",
    "sg:address":"Corringham Hall, Springhouse Road, Corringham",
    "sg:city":"Stanford-le-hope",
    "sg:classifiers":[
        {
            "category":"Health Services",
            "subcategory":"Nursing And Care Facility",
            "type":"Services"
        },
        {
            "category":"Social Services",
            "subcategory":"Retirement Home",
            "type":"Services"
        }
    ],
    "sg:phone":"+44 1375 671162",
    "sg:postcode":"SS17 7LE",
    "sg:province":"Essex",
    "sg:tags":[
        "residential"
    ],
    "wof:name":"Collins House",
    "wof:placetype":"venue"
},
  "geometry": {"coordinates":[0.4398239851,51.5261650085],"type":"Point"}
}