{
  "type": "Feature",
  "properties": {
    "addr:full":"43 Beauvale, Newthorpe Nottingham Derbyshire NG16 2EZ",
    "addr:housenumber":"43",
    "addr:postcode":"ng16 2ez",
    "addr:street":"Beauvale Newthorpe",
    "iso:country":"GB",
    "sg:address":"43 Beauvale, Newthorpe",
    "sg:city":"Nottingham",
    "sg:classifiers":[
        {
            "category":"Utilities",
            "subcategory":"Telephone",
            "type":"Services"
        },
        {
            "category":"Communications",
            "type":"Services"
        }
    ],
    "sg:phone":"+44 1773 714293",
    "sg:postcode":"NG16 2EZ",
    "sg:province":"Derbyshire",
    "sg:tags":[
        "telecommunication",
        "network"
    ],
    "wof:name":"Total Telecom Services Ltd",
    "wof:placetype":"venue"
},
  "geometry": {"coordinates":[-1.2834509611,53.0181121826],"type":"Point"}
}