{
  "type": "Feature",
  "properties": {
    "addr:full":"Castle Street Maesteg Bridgend CF34 0LW",
    "addr:postcode":"cf34 0lw",
    "addr:street":"Castle Street",
    "iso:country":"GB",
    "sg:address":"Castle Street",
    "sg:city":"Maesteg",
    "sg:classifiers":[
        {
            "category":"Organizations",
            "subcategory":"Religious Organization",
            "type":"Services"
        }
    ],
    "sg:phone":"+44 1656 732729",
    "sg:postcode":"CF34 0LW",
    "sg:province":"Bridgend",
    "sg:tags":[
        "organisation"
    ],
    "wof:name":"The Salvation Army",
    "wof:placetype":"venue"
},
  "geometry": {"coordinates":[-3.6623489857,51.6143951416],"type":"Point"}
}