{
  "type": "Feature",
  "properties": {
    "addr:full":"31 Bruton St West End Hampshire W1X 7DD",
    "addr:housenumber":"31",
    "addr:postcode":"w1x 7dd",
    "addr:street":"Bruton St",
    "iso:country":"GB",
    "sg:address":"31 Bruton St",
    "sg:city":"West End",
    "sg:classifiers":[
        {
            "category":"Manufacturing",
            "subcategory":"Apparel",
            "type":"Manufacturing & Wholesale Goods"
        }
    ],
    "sg:phone":"+44 20 7495 2689",
    "sg:postcode":"W1X 7DD",
    "sg:province":"Hampshire",
    "sg:tags":[
        "shirt",
        "maker"
    ],
    "wof:name":"Coates Viyella Branded Menswear",
    "wof:placetype":"venue"
},
  "geometry": {"coordinates":[-0.144687,51.510681],"type":"Point"}
}