{
  "type": "Feature",
  "properties": {
    "addr:full":"37 Parliament St Harrogate North Yorkshire HG1 2RE",
    "addr:housenumber":"37",
    "addr:postcode":"hg1 2re",
    "addr:street":"Parliament St",
    "iso:country":"GB",
    "sg:address":"37 Parliament St",
    "sg:city":"Harrogate",
    "sg:classifiers":[
        {
            "category":"Shopping",
            "subcategory":"Shoes",
            "type":"Retail Goods"
        }
    ],
    "sg:postcode":"HG1 2RE",
    "sg:province":"North Yorkshire",
    "sg:tags":[
        "shop"
    ],
    "wof:name":"Rohde Shoes",
    "wof:placetype":"venue"
},
  "geometry": {"coordinates":[-1.5431189537,53.9937705994],"type":"Point"}
}