{
  "type": "Feature",
  "properties": {
    "addr:full":"Unit 19, Corringham Road Industrial Estate Gainsborough Lincolnshire DN21 1QF",
    "addr:housenumber":"unit 19",
    "addr:postcode":"dn21 1qf",
    "addr:street":"Corringham Road Industrial Estate Gainsborough",
    "iso:country":"GB",
    "sg:address":"Unit 19, Corringham Road Industrial Estate",
    "sg:city":"Gainsborough",
    "sg:classifiers":[
        {
            "category":"Manufacturing",
            "subcategory":"Building Materials",
            "type":"Manufacturing & Wholesale Goods"
        }
    ],
    "sg:phone":"+44 1427 810290",
    "sg:postcode":"DN21 1QF",
    "sg:province":"Lincolnshire",
    "sg:tags":[
        "concrete",
        "product"
    ],
    "wof:name":"Interfuse Ltd.",
    "wof:placetype":"venue"
},
  "geometry": {"coordinates":[-0.747154,53.405338],"type":"Point"}
}