{
  "type": "Feature",
  "properties": {
    "addr:full":"313 Upper St London Greater London N1 2XQ",
    "addr:housenumber":"313",
    "addr:postcode":"n1 2xq",
    "addr:street":"Upper St",
    "iso:country":"GB",
    "sg:address":"313 Upper St",
    "sg:city":"London",
    "sg:classifiers":[
        {
            "category":"Professional",
            "subcategory":"Art Services",
            "type":"Services"
        }
    ],
    "sg:phone":"+44 20 7689 3832",
    "sg:postcode":"N1 2XQ",
    "sg:province":"Greater London",
    "sg:tags":[
        "graphic",
        "designer"
    ],
    "wof:name":"Ninety Seven Plus Ltd",
    "wof:placetype":"venue"
},
  "geometry": {"coordinates":[-0.102695,51.537704],"type":"Point"}
}