{
  "type": "Feature",
  "properties": {
    "iso:country":"GB",
    "sg:address":"59 High Street",
    "sg:city":"Burford",
    "sg:classifiers":[
        {
            "category":"Shopping",
            "subcategory":"Antiques",
            "type":"Retail Goods"
        }
    ],
    "sg:phone":"+44 1993 824268",
    "sg:postcode":"OX18 4QA",
    "sg:province":"Gloucestershire",
    "wof:name":"Boxroom Antiques",
    "wof:placetype":"venue"
},
  "geometry": {"coordinates":[-1.636215,51.808399],"type":"Point"}
}