{
  "type": "Feature",
  "properties": {
    "addr:full":"Unit 1a Cockshute Indust Est, Shelton New Rd Stoke On Trent Staffordshire ST4 7DP",
    "addr:housenumber":"unit 1a",
    "addr:postcode":"st4 7dp",
    "addr:street":"Cockshute Indust Est;New Rd",
    "iso:country":"GB",
    "sg:address":"Unit 1a Cockshute Indust Est, Shelton New Rd",
    "sg:city":"Stoke On Trent",
    "sg:classifiers":[
        {
            "category":"Retail",
            "subcategory":"Auto Repair",
            "type":"Services"
        }
    ],
    "sg:phone":"+44 1782 286920",
    "sg:postcode":"ST4 7DP",
    "sg:province":"Staffordshire",
    "sg:tags":[
        "electrician"
    ],
    "wof:name":"Autostart",
    "wof:placetype":"venue"
},
  "geometry": {"coordinates":[-2.1958301067,53.013759613],"type":"Point"}
}