{
  "type": "Feature",
  "properties": {
    "addr:full":"Maxibit House, Arkle Avenue, Stanley Green Trading Estate Wilmslow Cheshire SK9 3RW",
    "addr:postcode":"sk9 3rw",
    "addr:street":"Arkle Avenue;Trading",
    "iso:country":"GB",
    "sg:address":"Maxibit House, Arkle Avenue, Stanley Green Trading Estate",
    "sg:city":"Wilmslow",
    "sg:classifiers":[
        {
            "category":"Professional",
            "type":"Services"
        }
    ],
    "sg:phone":"+44 161 486 0888",
    "sg:postcode":"SK9 3RW",
    "sg:province":"Cheshire",
    "sg:tags":[
        "exhibition"
    ],
    "wof:name":"Maxportables Ltd.",
    "wof:placetype":"venue"
},
  "geometry": {"coordinates":[-2.206974,53.35194],"type":"Point"}
}