{
  "type": "Feature",
  "properties": {
    "iso:country":"GB",
    "sg:address":"319 London Rd",
    "sg:city":"Camberley",
    "sg:classifiers":[
        {
            "category":"Shopping",
            "subcategory":"Books",
            "type":"Retail Goods"
        }
    ],
    "sg:phone":"+44 1276 28977",
    "sg:postcode":"GU15 3HQ",
    "sg:province":"Berkshire",
    "sg:tags":[
        "bookseller"
    ],
    "wof:name":"Magazine Choice",
    "wof:placetype":"venue"
},
  "geometry": {"coordinates":[-0.758494,51.336426],"type":"Point"}
}