{
  "type": "Feature",
  "properties": {
    "iso:country":"GB",
    "sg:address":"8 Ayston Road, Uppingham, Rutland",
    "sg:city":"Oakham",
    "sg:classifiers":[
        {
            "category":"Retail",
            "subcategory":"Repair Shop",
            "type":"Services"
        },
        {
            "category":"Shopping",
            "subcategory":"Used Merchandise",
            "type":"Retail Goods"
        }
    ],
    "sg:phone":"+44 1572 823486",
    "sg:postcode":"LE15 9RL",
    "sg:province":"Leicestershire",
    "sg:tags":[
        "sale",
        "second-hand"
    ],
    "wof:name":"Gilbert's",
    "wof:placetype":"venue"
},
  "geometry": {"coordinates":[-0.722597,52.589733],"type":"Point"}
}