{
  "type": "Feature",
  "properties": {
    "addr:full":"Unit 4/6 Northam Business Centre, Princes Street Southampton Hampshire SO14 5RP",
    "addr:housenumber":"unit 4 / 6",
    "addr:postcode":"so14 5rp",
    "addr:street":"Princes Street",
    "iso:country":"GB",
    "sg:address":"Unit 4/6 Northam Business Centre, Princes Street",
    "sg:city":"Southampton",
    "sg:classifiers":[
        {
            "category":"Professional",
            "subcategory":"Detective & Security Services",
            "type":"Services"
        }
    ],
    "sg:phone":"+44 23 8022 4174",
    "sg:postcode":"SO14 5RP",
    "sg:province":"Hampshire",
    "sg:tags":[
        "alarm",
        "burglar",
        "system"
    ],
    "wof:name":"Avenue Alarms Ltd.",
    "wof:placetype":"venue"
},
  "geometry": {"coordinates":[-1.3866200447,50.9120407104],"type":"Point"}
}