{
  "type": "Feature",
  "properties": {
    "addr:full":"The Sidmouth Shopping Centre, 91 High Street Sidmouth Devon EX10 8LD",
    "addr:housenumber":"91",
    "addr:postcode":"ex10 8ld",
    "addr:street":"High Street",
    "iso:country":"GB",
    "sg:address":"The Sidmouth Shopping Centre, 91 High Street",
    "sg:city":"Sidmouth",
    "sg:classifiers":[
        {
            "category":"Food & Beverages",
            "subcategory":"Meat & Fish",
            "type":"Retail Goods"
        }
    ],
    "sg:postcode":"EX10 8LD",
    "sg:province":"Devon",
    "sg:tags":[
        "butcher"
    ],
    "wof:name":"Trevor's Butchery",
    "wof:placetype":"venue"
},
  "geometry": {"coordinates":[-3.237619,50.68745],"type":"Point"}
}