{
  "type": "Feature",
  "properties": {
    "addr:full":"13 Orlanda Av Salford Greater Manchester M6 8FX",
    "addr:housenumber":"13",
    "addr:postcode":"m6 8fx",
    "addr:street":"Orlanda Av Salford",
    "iso:country":"GB",
    "sg:address":"13 Orlanda Av",
    "sg:city":"Salford",
    "sg:classifiers":[
        {
            "category":"Shopping",
            "subcategory":"Party Supplies",
            "type":"Retail Goods"
        }
    ],
    "sg:phone":"+44 161 788 8819",
    "sg:postcode":"M6 8FX",
    "sg:province":"Greater Manchester",
    "sg:tags":[
        "inflatables",
        "bouncy",
        "castle"
    ],
    "wof:name":"ABC Bouncy Castles",
    "wof:placetype":"venue"
},
  "geometry": {"coordinates":[-2.3250300884,53.4927406311],"type":"Point"}
}