{
  "type": "Feature",
  "properties": {
    "addr:full":"11 New Steine Brighton East Sussex BN2 1PB",
    "addr:housenumber":"11",
    "addr:postcode":"bn2 1pb",
    "addr:street":"New Steine",
    "iso:country":"GB",
    "sg:address":"11 New Steine",
    "sg:city":"Brighton",
    "sg:classifiers":[
        {
            "category":"Recreation",
            "subcategory":"Amusement Park",
            "type":"Entertainment"
        },
        {
            "category":"Travel",
            "subcategory":"Hotels & Motels",
            "type":"Entertainment"
        }
    ],
    "sg:phone":"+44 1273 697384",
    "sg:postcode":"BN2 1PB",
    "sg:province":"East Sussex",
    "sg:tags":[
        "hospitality",
        "corporate"
    ],
    "wof:name":"The Trouville Hotel",
    "wof:placetype":"venue"
},
  "geometry": {"coordinates":[-0.132067,50.82011],"type":"Point"}
}