{
  "type": "Feature",
  "properties": {
    "iso:country":"GB",
    "sg:address":"Kings Court, 185 Kings Rd",
    "sg:city":"Reading",
    "sg:classifiers":[
        {
            "category":"Professional",
            "subcategory":"Research",
            "type":"Services"
        }
    ],
    "sg:phone":"+44 118 956 9165",
    "sg:postcode":"RG1 4EX",
    "sg:province":"Berkshire",
    "sg:tags":[
        "market"
    ],
    "wof:name":"A.C Nielsen MEAL Co Ltd",
    "wof:placetype":"venue"
},
  "geometry": {"coordinates":[-0.9572479725,51.4538726807],"type":"Point"}
}