{
  "type": "Feature",
  "properties": {
    "iso:country":"GB",
    "sg:address":"134 West Regent Street",
    "sg:city":"Glasgow",
    "sg:classifiers":[
        {
            "category":"Insurance",
            "subcategory":"Insurance Agent",
            "type":"Services"
        },
        {
            "category":"Professional",
            "subcategory":"Management & Consulting",
            "type":"Services"
        }
    ],
    "sg:phone":"+44 141 204 2661",
    "sg:postcode":"G2 2RQ",
    "sg:province":"Glasgow City",
    "sg:tags":[
        "environmental",
        "consultant"
    ],
    "wof:name":"Mentor",
    "wof:placetype":"venue"
},
  "geometry": {"coordinates":[-4.2598009109,55.8636245728],"type":"Point"}
}