{
  "type": "Feature",
  "properties": {
    "iso:country":"GB",
    "sg:address":"224-230 London Road",
    "sg:city":"Sheffield",
    "sg:classifiers":[
        {
            "category":"Home & Garden",
            "subcategory":"Home Furnishings",
            "type":"Retail Goods"
        }
    ],
    "sg:phone":"+44 114 250 1060",
    "sg:postcode":"S2 4LW",
    "sg:province":"South Yorkshire",
    "sg:tags":[
        "beds",
        "bedding",
        "blanket"
    ],
    "wof:name":"Sleepers Choice",
    "wof:placetype":"venue"
},
  "geometry": {"coordinates":[-1.4761879444,53.3679466248],"type":"Point"}
}