{
  "type": "Feature",
  "properties": {
    "addr:full":"30 Main Street, Longridge Bathgate North Lanarkshire EH47 8AD",
    "addr:housenumber":"30",
    "addr:postcode":"eh47 8ad",
    "addr:street":"Main Street;Bathgate",
    "iso:country":"GB",
    "sg:address":"30 Main Street, Longridge",
    "sg:city":"Bathgate",
    "sg:classifiers":[
        {
            "category":"Shopping",
            "subcategory":"Department Store",
            "type":"Retail Goods"
        },
        {
            "category":"Food & Beverages",
            "subcategory":"Groceries & Convenience Stores",
            "type":"Retail Goods"
        }
    ],
    "sg:phone":"+44 1501 770507",
    "sg:postcode":"EH47 8AD",
    "sg:province":"North Lanarkshire",
    "wof:name":"David McCord",
    "wof:placetype":"venue"
},
  "geometry": {"coordinates":[-3.678483963,55.8436050415],"type":"Point"}
}