{
  "type": "Feature",
  "properties": {
    "addr:full":"5 Bramley Court Sutton-in-ashfield Nottinghamshire NG17 4AG",
    "addr:housenumber":"5",
    "addr:postcode":"ng17 4ag",
    "addr:street":"Bramley Court",
    "iso:country":"GB",
    "sg:address":"5 Bramley Court",
    "sg:city":"Sutton-in-ashfield",
    "sg:classifiers":[
        {
            "category":"Building & Trades",
            "subcategory":"Construction",
            "type":"Services"
        }
    ],
    "sg:phone":"+44 1623 515160",
    "sg:postcode":"NG17 4AG",
    "sg:province":"Nottinghamshire",
    "sg:tags":[
        "joiner",
        "carpenter"
    ],
    "wof:name":"Christopher Alvey Joinery & Glazing",
    "wof:placetype":"venue"
},
  "geometry": {"coordinates":[-1.2560390234,53.1269302368],"type":"Point"}
}