{
  "type": "Feature",
  "properties": {
    "addr:full":"Buckles Lane South Ockendon Essex RM15 6RS",
    "addr:postcode":"rm15 6rs",
    "addr:street":"Buckles Lane",
    "iso:country":"GB",
    "sg:address":"Buckles Lane",
    "sg:city":"South Ockendon",
    "sg:classifiers":[
        {
            "category":"Sports & Exercise",
            "subcategory":"Sports Center",
            "type":"Entertainment"
        }
    ],
    "sg:phone":"+44 1708 856422",
    "sg:postcode":"RM15 6RS",
    "sg:province":"Essex",
    "sg:tags":[
        "shop",
        "good"
    ],
    "wof:name":"Grangewaters Water Sport Centre",
    "wof:placetype":"venue"
},
  "geometry": {"coordinates":[0.294866,51.510925],"type":"Point"}
}