{
  "type": "Feature",
  "properties": {
    "iso:country":"GB",
    "sg:address":"Unit 4, Tait Road Industrial Estate",
    "sg:city":"Croydon",
    "sg:classifiers":[
        {
            "category":"Professional",
            "subcategory":"Management & Consulting",
            "type":"Services"
        }
    ],
    "sg:phone":"+44 20 8665 6500",
    "sg:postcode":"CR0 2DP",
    "sg:province":"Surrey",
    "sg:tags":[
        "fire",
        "consultant",
        "protection"
    ],
    "wof:name":"Alarmtronic Ltd.",
    "wof:placetype":"venue"
},
  "geometry": {"coordinates":[-0.087977998,51.3850021362],"type":"Point"}
}