{
  "type": "Feature",
  "properties": {
    "addr:full":"Meadowside, Whitestone Nuneaton Leicestershire CV11 6NF",
    "addr:postcode":"cv11 6nf",
    "iso:country":"GB",
    "sg:address":"Meadowside, Whitestone",
    "sg:city":"Nuneaton",
    "sg:classifiers":[
        {
            "category":"Bars & Pubs",
            "type":"Food & Drink"
        },
        {
            "category":"Community Center",
            "subcategory":"Social",
            "type":"Public Place"
        }
    ],
    "sg:phone":"+44 24 7634 8181",
    "sg:postcode":"CV11 6NF",
    "sg:province":"Leicestershire",
    "sg:tags":[
        "pubs",
        "house",
        "inn",
        "activity"
    ],
    "wof:name":"The Hayrick",
    "wof:placetype":"venue"
},
  "geometry": {"coordinates":[-1.4308389425,52.5077438354],"type":"Point"}
}