{
  "type": "Feature",
  "properties": {
    "iso:country":"GB",
    "sg:address":"74 Jordan Avenue, Stretton",
    "sg:city":"Burton On Trent",
    "sg:classifiers":[
        {
            "category":"Health Services",
            "subcategory":"Podiatrist",
            "type":"Services"
        }
    ],
    "sg:phone":"+44 1283 535195",
    "sg:postcode":"DE13 0JB",
    "sg:province":"Derbyshire",
    "sg:tags":[
        "podiatrists",
        "chiropodist"
    ],
    "wof:name":"Helen Beetlestone D.Pod.M M.Ch.S S.R.Ch",
    "wof:placetype":"venue"
},
  "geometry": {"coordinates":[-1.618826,52.836075],"type":"Point"}
}