{
  "type": "Feature",
  "properties": {
    "addr:full":"Unit 36 Riverside Wk Port Talbot Neath Port Talbot SA13 1PH",
    "addr:housenumber":"unit 36",
    "addr:postcode":"sa13 1ph",
    "addr:street":"Riverside Wk Port Talbot",
    "iso:country":"GB",
    "sg:address":"Unit 36 Riverside Wk",
    "sg:city":"Port Talbot",
    "sg:classifiers":[
        {
            "category":"Shopping",
            "subcategory":"Florist",
            "type":"Retail Goods"
        }
    ],
    "sg:postcode":"SA13 1PH",
    "sg:province":"Neath Port Talbot",
    "wof:name":"Ann's Florist",
    "wof:placetype":"venue"
},
  "geometry": {"coordinates":[-3.78399,51.596001],"type":"Point"}
}