{
  "type": "Feature",
  "properties": {
    "addr:full":"High Street, Market Deeping Peterborough Cambridgeshire PE6 8ED",
    "addr:postcode":"pe6 8ed",
    "addr:street":"High Street;Peterborough",
    "iso:country":"GB",
    "sg:address":"High Street, Market Deeping",
    "sg:city":"Peterborough",
    "sg:classifiers":[
        {
            "category":"Retail",
            "subcategory":"Event Space",
            "type":"Services"
        }
    ],
    "sg:phone":"+44 1778 343383",
    "sg:postcode":"PE6 8ED",
    "sg:province":"Cambridgeshire",
    "sg:tags":[
        "banqueting",
        "room"
    ],
    "wof:name":"The Georgians",
    "wof:placetype":"venue"
},
  "geometry": {"coordinates":[-0.313524,52.674419],"type":"Point"}
}