{
  "type": "Feature",
  "properties": {
    "addr:full":"Mearfield House, Nutfield Place Portsmouth Hampshire PO1 4JZ",
    "addr:postcode":"hampshire po1 4jz",
    "addr:street":"Nutfield Place",
    "iso:country":"GB",
    "sg:address":"Mearfield House, Nutfield Place",
    "sg:city":"Portsmouth",
    "sg:classifiers":[
        {
            "category":"Government",
            "subcategory":"Office",
            "type":"Public Place"
        }
    ],
    "sg:phone":"+44 23 9283 9111",
    "sg:postcode":"PO1 4JZ",
    "sg:province":"Hampshire",
    "sg:tags":[
        "local"
    ],
    "wof:name":"Fostering Recruitment Team",
    "wof:placetype":"venue"
},
  "geometry": {"coordinates":[-1.079046011,50.8044815063],"type":"Point"}
}