{
  "type": "Feature",
  "properties": {
    "addr:full":"108 Morden Road London Greater London SW19 3BP",
    "addr:housenumber":"108",
    "addr:postcode":"sw19 3bp",
    "addr:street":"Morden Road",
    "iso:country":"GB",
    "sg:address":"108 Morden Road",
    "sg:city":"London",
    "sg:classifiers":[
        {
            "category":"Restaurant",
            "type":"Food & Drink"
        }
    ],
    "sg:phone":"+44 20 8543 9633",
    "sg:postcode":"SW19 3BP",
    "sg:province":"Greater London",
    "wof:name":"Khan's Restaurant",
    "wof:placetype":"venue"
},
  "geometry": {"coordinates":[-0.1926449984,51.4103126526],"type":"Point"}
}