{
  "type": "Feature",
  "properties": {
    "addr:full":"1 Crown Office Row, Temple St Paul's Greater London EC4Y 7HH",
    "addr:housenumber":"1",
    "addr:postcode":"ec4y 7hh",
    "addr:street":"Office Row Temple St",
    "iso:country":"GB",
    "sg:address":"1 Crown Office Row, Temple",
    "sg:city":"St Paul's",
    "sg:classifiers":[
        {
            "category":"Professional",
            "subcategory":"Lawyer & Legal Services",
            "type":"Services"
        }
    ],
    "sg:phone":"+44 20 7797 7111",
    "sg:postcode":"EC4Y 7HH",
    "sg:province":"Greater London",
    "sg:tags":[
        "barrister"
    ],
    "wof:name":"David Hislop",
    "wof:placetype":"venue"
},
  "geometry": {"coordinates":[-0.1105900034,51.5124702454],"type":"Point"}
}