{
  "type": "Feature",
  "properties": {
    "addr:full":"141 Boston Manor Road Brentford Greater London TW8 9LE",
    "addr:housenumber":"141",
    "addr:postcode":"tw8 9le",
    "addr:street":"Boston Manor Road",
    "iso:country":"GB",
    "sg:address":"141 Boston Manor Road",
    "sg:city":"Brentford",
    "sg:classifiers":[
        {
            "category":"Building & Trades",
            "subcategory":"Construction",
            "type":"Services"
        }
    ],
    "sg:postcode":"TW8 9LE",
    "sg:province":"Greater London",
    "sg:tags":[
        "dry",
        "lining",
        "plasterers",
        "screeders"
    ],
    "wof:name":"Richard the Plasterer",
    "wof:placetype":"venue"
},
  "geometry": {"coordinates":[-0.3174650073,51.4922676086],"type":"Point"}
}