{
  "type": "Feature",
  "properties": {
    "addr:full":"Terminal 3, 3b2 Stonehill Green Swindon Wiltshire SN5 7HB",
    "addr:housenumber":"3 3b2",
    "addr:postcode":"sn5 7hb",
    "addr:street":"Stonehill Green",
    "iso:country":"GB",
    "sg:address":"Terminal 3, 3b2 Stonehill Green",
    "sg:city":"Swindon",
    "sg:classifiers":[
        {
            "category":"Autos & Motor Vehicles",
            "subcategory":"Automobile Sales",
            "type":"Retail Goods"
        }
    ],
    "sg:phone":"+44 1793 432001",
    "sg:postcode":"SN5 7HB",
    "sg:province":"Wiltshire",
    "wof:name":"Honda Lock Co",
    "wof:placetype":"venue"
},
  "geometry": {"coordinates":[-1.818950057,51.5620689392],"type":"Point"}
}