{
  "type": "Feature",
  "properties": {
    "iso:country":"GB",
    "sg:address":"30 Bootle Shopping Arcade,, Stanley Rd",
    "sg:city":"Bootle",
    "sg:classifiers":[
        {
            "category":"Home & Garden",
            "subcategory":"Furniture",
            "type":"Retail Goods"
        }
    ],
    "sg:postcode":"L20 3QH",
    "sg:province":"Merseyside",
    "wof:name":"Aintree Pine",
    "wof:placetype":"venue"
},
  "geometry": {"coordinates":[-2.986464,53.455811],"type":"Point"}
}