{
  "type": "Feature",
  "properties": {
    "addr:full":"11 Deansgate Bolton Lancashire BL1 1HH",
    "addr:housenumber":"11",
    "addr:postcode":"bl1 1hh",
    "addr:street":"Deansgate",
    "iso:country":"GB",
    "sg:address":"11 Deansgate",
    "sg:city":"Bolton",
    "sg:classifiers":[
        {
            "category":"Manufacturing",
            "subcategory":"Jewelry",
            "type":"Manufacturing & Wholesale Goods"
        }
    ],
    "sg:phone":"+44 1204 535647",
    "sg:postcode":"BL1 1HH",
    "sg:province":"Lancashire",
    "sg:tags":[
        "repair",
        "jewellery"
    ],
    "wof:name":"David & Tracey's Jewellery",
    "wof:placetype":"venue"
},
  "geometry": {"coordinates":[-2.4308390617,53.5795898438],"type":"Point"}
}