{
  "type": "Feature",
  "properties": {
    "addr:full":"8-11 Vicar Street Kidderminster Staffordshire DY10 1DE",
    "addr:housenumber":"8-11",
    "addr:postcode":"dy10 1de",
    "addr:street":"Vicar Street",
    "iso:country":"GB",
    "sg:address":"8-11 Vicar Street",
    "sg:city":"Kidderminster",
    "sg:classifiers":[
        {
            "category":"Banks & Credit Unions",
            "subcategory":"Financial Services",
            "type":"Services"
        }
    ],
    "sg:phone":"+44 1562 820903",
    "sg:postcode":"DY10 1DE",
    "sg:province":"Staffordshire",
    "sg:tags":[
        "consultant"
    ],
    "wof:name":"L B I Finance",
    "wof:placetype":"venue"
},
  "geometry": {"coordinates":[-2.2486579418,52.3872909546],"type":"Point"}
}