{
  "type": "Feature",
  "properties": {
    "addr:full":"The Millinery Works, 85-87 Southgate Road London Greater London N1 3JS",
    "addr:housenumber":"85-87",
    "addr:postcode":"n1 3js",
    "addr:street":"Southgate Road",
    "iso:country":"GB",
    "sg:address":"The Millinery Works, 85-87 Southgate Road",
    "sg:city":"London",
    "sg:classifiers":[
        {
            "category":"Arts & Performance",
            "subcategory":"Art Gallery",
            "type":"Entertainment"
        },
        {
            "category":"Shopping",
            "subcategory":"Antiques",
            "type":"Retail Goods"
        }
    ],
    "sg:phone":"+44 20 7359 2019",
    "sg:postcode":"N1 3JS",
    "sg:province":"Greater London",
    "wof:name":"The Millinery Works Ltd.",
    "wof:placetype":"venue"
},
  "geometry": {"coordinates":[-0.08526,51.54113],"type":"Point"}
}