{
  "type": "Feature",
  "properties": {
    "addr:full":"Ashmore Farm, Bridge Of Cally Blairgowrie Perth and Kinross PH10 7JW",
    "addr:postcode":"ph10 7jw",
    "addr:street":"Cally Blairgowrie",
    "iso:country":"GB",
    "sg:address":"Ashmore Farm, Bridge Of Cally",
    "sg:city":"Blairgowrie",
    "sg:classifiers":[
        {
            "category":"Farming",
            "subcategory":"Livestock Farm",
            "type":"Manufacturing & Wholesale Goods"
        }
    ],
    "sg:phone":"+44 1250 886248",
    "sg:postcode":"PH10 7JW",
    "sg:province":"Perth and Kinross",
    "sg:tags":[
        "others"
    ],
    "wof:name":"Henry Angest",
    "wof:placetype":"venue"
},
  "geometry": {"coordinates":[-3.4011230469,56.6491508484],"type":"Point"}
}