{
  "type": "Feature",
  "properties": {
    "iso:country":"GB",
    "sg:address":"27 Sheddingdean Close",
    "sg:city":"Burgess Hill",
    "sg:classifiers":[
        {
            "category":"Professional",
            "subcategory":"Management & Consulting",
            "type":"Services"
        }
    ],
    "sg:postcode":"RH15 8JQ",
    "sg:province":"East Sussex",
    "sg:tags":[
        "consultant",
        "business"
    ],
    "wof:name":"Stylebreak Consultants Ltd",
    "wof:placetype":"venue"
},
  "geometry": {"coordinates":[-0.134774,50.963848],"type":"Point"}
}