{
  "type": "Feature",
  "properties": {
    "iso:country":"GB",
    "sg:address":"91 Regent St",
    "sg:city":"Morecambe",
    "sg:classifiers":[
        {
            "category":"Travel",
            "subcategory":"Hotels & Motels",
            "type":"Entertainment"
        }
    ],
    "sg:phone":"+44 1524 413872",
    "sg:postcode":"LA3 1AF",
    "sg:province":"Lancashire",
    "wof:name":"Top Respect Ltd",
    "wof:placetype":"venue"
},
  "geometry": {"coordinates":[-2.876656,54.063854],"type":"Point"}
}