{
  "type": "Feature",
  "properties": {
    "addr:full":"2nd Floor Jonsen House, 43 Commerical Road Poole Dorset BH14 0HU",
    "addr:housenumber":"2nd floor jonsen house 43",
    "addr:postcode":"bh14 0hu",
    "addr:street":"Commerical Road",
    "iso:country":"GB",
    "sg:address":"2nd Floor Jonsen House, 43 Commerical Road",
    "sg:city":"Poole",
    "sg:classifiers":[
        {
            "category":"Home & Garden",
            "subcategory":"Home Furnishings",
            "type":"Retail Goods"
        }
    ],
    "sg:postcode":"BH14 0HU",
    "sg:province":"Dorset",
    "sg:tags":[
        "tube",
        "fitting",
        "stockist"
    ],
    "wof:name":"J & T Tubes Ltd",
    "wof:placetype":"venue"
},
  "geometry": {"coordinates":[-1.9577800035,50.7235488892],"type":"Point"}
}