{
  "type": "Feature",
  "properties": {
    "iso:country":"GB",
    "sg:address":"Home Farm, Newby Wiske",
    "sg:city":"Northallerton",
    "sg:classifiers":[
        {
            "category":"Home & Garden",
            "subcategory":"Garden Supply",
            "type":"Retail Goods"
        },
        {
            "category":"Farming",
            "subcategory":"Livestock Farm",
            "type":"Manufacturing & Wholesale Goods"
        }
    ],
    "sg:phone":"+44 1609 773604",
    "sg:postcode":"DL7 9HB",
    "sg:province":"North Yorkshire",
    "sg:tags":[
        "bulb",
        "grower",
        "others"
    ],
    "wof:name":"Ronald B Richardson",
    "wof:placetype":"venue"
},
  "geometry": {"coordinates":[-1.437415,54.284306],"type":"Point"}
}