{
  "type": "Feature",
  "properties": {
    "addr:full":"Hill End Lane, Hainsworth Moor, Queensbury Bradford West Yorkshire BD13 2LY",
    "addr:postcode":"bd13 2ly",
    "addr:street":"Hill End Lane Hainsworth Moor;Bradford West",
    "iso:country":"GB",
    "sg:address":"Hill End Lane, Hainsworth Moor, Queensbury",
    "sg:city":"Bradford",
    "sg:classifiers":[
        {
            "category":"Utilities",
            "subcategory":"Refuse",
            "type":"Services"
        }
    ],
    "sg:phone":"+44 1274 814466",
    "sg:postcode":"BD13 2LY",
    "sg:province":"West Yorkshire",
    "sg:tags":[
        "catering"
    ],
    "wof:name":"Shire Trolleys",
    "wof:placetype":"venue"
},
  "geometry": {"coordinates":[-1.856352,53.763233],"type":"Point"}
}