{
  "type": "Feature",
  "properties": {
    "addr:full":"22 Brayton Ave Sale Cheshire M33 5HF",
    "addr:housenumber":"22",
    "addr:postcode":"m33 5hf",
    "addr:street":"Brayton Ave",
    "iso:country":"GB",
    "sg:address":"22 Brayton Ave",
    "sg:city":"Sale",
    "sg:classifiers":[
        {
            "category":"Building & Trades",
            "subcategory":"Plumbing",
            "type":"Services"
        }
    ],
    "sg:postcode":"M33 5HF",
    "sg:province":"Cheshire",
    "sg:tags":[
        "drain",
        "clearance",
        "sewer"
    ],
    "wof:name":"Laserfall Ltd",
    "wof:placetype":"venue"
},
  "geometry": {"coordinates":[-2.3497700691,53.4282264709],"type":"Point"}
}