{
  "type": "Feature",
  "properties": {
    "iso:country":"GB",
    "sg:address":"Guttmann Road Stoke Manderville",
    "sg:city":"Aylesbury",
    "sg:classifiers":[
        {
            "category":"Arena",
            "subcategory":"Sports Club",
            "type":"Entertainment"
        }
    ],
    "sg:phone":"+44 1296 395995",
    "sg:postcode":"HP21 9PP",
    "sg:province":"Buckinghamshire",
    "wof:name":"The British Wheelchair Sports Foundation",
    "wof:placetype":"venue"
},
  "geometry": {"coordinates":[-0.800949,51.802631],"type":"Point"}
}