{
  "type": "Feature",
  "properties": {
    "addr:full":"Maryborough Rd Prestwick South Ayrshire KA9 1SD",
    "addr:postcode":"ka9 1sd",
    "addr:street":"Maryborough Rd",
    "iso:country":"GB",
    "sg:address":"Maryborough Rd",
    "sg:city":"Prestwick",
    "sg:classifiers":[
        {
            "category":"Place Of Worship",
            "type":"Public Place"
        }
    ],
    "sg:phone":"+44 1292 477108",
    "sg:postcode":"KA9 1SD",
    "sg:province":"South Ayrshire",
    "wof:name":"St Ninian's Scottish Episcopal Church",
    "wof:placetype":"venue"
},
  "geometry": {"coordinates":[-4.6138892174,55.4947357178],"type":"Point"}
}