{
  "type": "Feature",
  "properties": {
    "addr:full":"Central Buildings London Greater London W5 2NT",
    "addr:postcode":"w5 2nt",
    "addr:street":"Central Buildings",
    "iso:country":"GB",
    "sg:address":"Central Buildings",
    "sg:city":"London",
    "sg:classifiers":[
        {
            "category":"Real Estate",
            "subcategory":"Real Estate Agent",
            "type":"Services"
        }
    ],
    "sg:postcode":"W5 2NT",
    "sg:province":"Greater London",
    "wof:name":"Faron Sutaria & Co. Ltd.",
    "wof:placetype":"venue"
},
  "geometry": {"coordinates":[-0.30241,51.51466],"type":"Point"}
}