{
  "type": "Feature",
  "properties": {
    "addr:full":"5 Hart House, The Hart Farnham Surrey GU9 7HJ",
    "addr:housenumber":"5",
    "addr:postcode":"gu9 7hj",
    "addr:street":"Hart;The Hart Farnham",
    "iso:country":"GB",
    "sg:address":"5 Hart House, The Hart",
    "sg:city":"Farnham",
    "sg:classifiers":[
        {
            "category":"Health Services",
            "subcategory":"Health Practitioner",
            "type":"Services"
        }
    ],
    "sg:phone":"+44 1252 726479",
    "sg:postcode":"GU9 7HJ",
    "sg:province":"Surrey",
    "sg:tags":[
        "physiotherapist"
    ],
    "wof:name":"Farnham Physiotherapy & Sports Clinic",
    "wof:placetype":"venue"
},
  "geometry": {"coordinates":[-0.800837,51.214321],"type":"Point"}
}