{
  "type": "Feature",
  "properties": {
    "addr:full":"19 Bank Street Wakefield West Yorkshire WF1 1EH",
    "addr:housenumber":"19",
    "addr:postcode":"wf1 1eh",
    "addr:street":"Bank Street",
    "iso:country":"GB",
    "sg:address":"19 Bank Street",
    "sg:city":"Wakefield",
    "sg:classifiers":[
        {
            "category":"Education",
            "subcategory":"Special Training",
            "type":"Public Place"
        }
    ],
    "sg:phone":"+44 1924 217111",
    "sg:postcode":"WF1 1EH",
    "sg:province":"West Yorkshire",
    "sg:tags":[
        "product",
        "centre"
    ],
    "wof:name":"Roger Worth Training Ltd.",
    "wof:placetype":"venue"
},
  "geometry": {"coordinates":[-1.501456,53.681389],"type":"Point"}
}