{
  "type": "Feature",
  "properties": {
    "iso:country":"GB",
    "sg:address":"78 Academy Street",
    "sg:city":"Inverness",
    "sg:classifiers":[
        {
            "category":"Shopping",
            "subcategory":"Discount & Variety Stores",
            "type":"Retail Goods"
        }
    ],
    "sg:phone":"+44 1463 243800",
    "sg:postcode":"IV1 1LU",
    "sg:province":"Highland",
    "sg:tags":[
        "centre"
    ],
    "wof:name":"Your More Stores",
    "wof:placetype":"venue"
},
  "geometry": {"coordinates":[-4.2262887955,57.4801139832],"type":"Point"}
}