{
  "type": "Feature",
  "properties": {
    "iso:country":"GB",
    "sg:address":"Kelburn Business Park",
    "sg:city":"Port Glasgow",
    "sg:classifiers":[
        {
            "category":"Home & Garden",
            "subcategory":"Hardware",
            "type":"Retail Goods"
        }
    ],
    "sg:postcode":"PA14 6TD",
    "sg:province":"Inverclyde",
    "sg:tags":[
        "tarpaulin"
    ],
    "wof:name":"Tees Tarpaulins Ltd.",
    "wof:placetype":"venue"
},
  "geometry": {"coordinates":[-4.6136789322,55.9300003052],"type":"Point"}
}