{
  "type": "Feature",
  "properties": {
    "iso:country":"GB",
    "sg:address":"98 Carlton Road",
    "sg:city":"Boston",
    "sg:classifiers":[
        {
            "category":"Food & Beverages",
            "subcategory":"Meat & Fish",
            "type":"Retail Goods"
        }
    ],
    "sg:postcode":"PE21 8PQ",
    "sg:province":"Lincolnshire",
    "sg:tags":[
        "butcher"
    ],
    "wof:name":"Paul Taylor",
    "wof:placetype":"venue"
},
  "geometry": {"coordinates":[-0.036555,52.981266],"type":"Point"}
}