{
  "type": "Feature",
  "properties": {
    "iso:country":"GB",
    "sg:address":"Wirrall Park, Service Station, Wirral Park Rd",
    "sg:city":"Glastonbury",
    "sg:classifiers":[
        {
            "category":"Autos & Motor Vehicles",
            "subcategory":"Fuel & Gas Station",
            "type":"Retail Goods"
        }
    ],
    "sg:phone":"+44 1458 837000",
    "sg:postcode":"BA6 9XE",
    "sg:province":"Somerset",
    "sg:tags":[
        "petrol",
        "filling"
    ],
    "wof:name":"Texaco",
    "wof:placetype":"venue"
},
  "geometry": {"coordinates":[-2.717009,51.147591],"type":"Point"}
}