{
  "type": "Feature",
  "properties": {
    "addr:full":"729 Wimborne Road Bournemouth Dorset BH9 2AX",
    "addr:housenumber":"729",
    "addr:postcode":"bh9 2ax",
    "addr:street":"Wimborne Road",
    "iso:country":"GB",
    "sg:address":"729 Wimborne Road",
    "sg:city":"Bournemouth",
    "sg:classifiers":[
        {
            "category":"Shopping",
            "subcategory":"Clothing, Apparel, & Fashions",
            "type":"Retail Goods"
        }
    ],
    "sg:phone":"+44 1202 510382",
    "sg:postcode":"BH9 2AX",
    "sg:province":"Dorset",
    "sg:tags":[
        "ladieswear"
    ],
    "wof:name":"M W Olliffe",
    "wof:placetype":"venue"
},
  "geometry": {"coordinates":[-1.877019,50.750061],"type":"Point"}
}