{
  "type": "Feature",
  "properties": {
    "addr:full":"25 Hartswood Road London Greater London W12 9NE",
    "addr:housenumber":"25",
    "addr:postcode":"w12 9ne",
    "addr:street":"Hartswood Road",
    "iso:country":"GB",
    "sg:address":"25 Hartswood Road",
    "sg:city":"London",
    "sg:classifiers":[
        {
            "category":"Building & Trades",
            "subcategory":"Construction",
            "type":"Services"
        }
    ],
    "sg:phone":"+44 20 8740 5171",
    "sg:postcode":"W12 9NE",
    "sg:province":"Greater London",
    "sg:tags":[
        "builder"
    ],
    "wof:name":"A J C Building Services",
    "wof:placetype":"venue"
},
  "geometry": {"coordinates":[-0.247817,51.499512],"type":"Point"}
}