{
  "type": "Feature",
  "properties": {
    "iso:country":"GB",
    "sg:address":"Pigana House",
    "sg:city":"Pinner",
    "sg:classifiers":[
        {
            "category":"Professional",
            "type":"Services"
        }
    ],
    "sg:postcode":"HA5 2HG",
    "sg:province":"Greater London",
    "sg:tags":[
        "entertainer"
    ],
    "wof:name":"Speakers Corner",
    "wof:placetype":"venue"
},
  "geometry": {"coordinates":[-0.380489,51.590939],"type":"Point"}
}