{
  "type": "Feature",
  "properties": {
    "addr:full":"35 Inverleith Terrace Edinburgh City of Edinburgh EH3 5NU",
    "addr:housenumber":"35",
    "addr:postcode":"eh3 5nu",
    "addr:street":"Inverleith Terrace",
    "iso:country":"GB",
    "sg:address":"35 Inverleith Terrace",
    "sg:city":"Edinburgh",
    "sg:classifiers":[
        {
            "category":"Health Services",
            "subcategory":"Nursing And Care Facility",
            "type":"Services"
        },
        {
            "category":"Social Services",
            "subcategory":"Retirement Home",
            "type":"Services"
        }
    ],
    "sg:phone":"+44 131 332 1481",
    "sg:postcode":"EH3 5NU",
    "sg:province":"City of Edinburgh",
    "sg:tags":[
        "residential"
    ],
    "wof:name":"Braeburn Home For The Elderly",
    "wof:placetype":"venue"
},
  "geometry": {"coordinates":[-3.2104649544,55.9627075195],"type":"Point"}
}