{
  "type": "Feature",
  "properties": {
    "iso:country":"GB",
    "sg:address":"Old Pier",
    "sg:city":"Stonehaven",
    "sg:classifiers":[
        {
            "category":"Education",
            "subcategory":"Special Training",
            "type":"Public Place"
        }
    ],
    "sg:phone":"+44 1569 764065",
    "sg:postcode":"AB39 2JU",
    "sg:province":"Aberdeenshire",
    "sg:tags":[
        "product",
        "centre"
    ],
    "wof:name":"Maritime Rescue International Ltd.",
    "wof:placetype":"venue"
},
  "geometry": {"coordinates":[-2.202436924,56.9607315063],"type":"Point"}
}