{
  "type": "Feature",
  "properties": {
    "addr:full":"3 Holly Court Retford Nottinghamshire DN22 6BG",
    "addr:housenumber":"3",
    "addr:postcode":"dn22 6bg",
    "addr:street":"Holly Court",
    "iso:country":"GB",
    "sg:address":"3 Holly Court",
    "sg:city":"Retford",
    "sg:classifiers":[
        {
            "category":"Building & Trades",
            "subcategory":"Plumbing",
            "type":"Services"
        }
    ],
    "sg:phone":"+44 1777 701335",
    "sg:postcode":"DN22 6BG",
    "sg:province":"Nottinghamshire",
    "sg:tags":[
        "drain",
        "clearance",
        "sewer"
    ],
    "wof:name":"Aquajet (G B) Ltd.",
    "wof:placetype":"venue"
},
  "geometry": {"coordinates":[-0.9365760088,53.3181610107],"type":"Point"}
}