{
  "type": "Feature",
  "properties": {
    "iso:country":"GB",
    "sg:address":"Unit 9 Enterprise Park, Etna Road",
    "sg:city":"Bury St Edmunds",
    "sg:classifiers":[
        {
            "category":"Retail",
            "subcategory":"Auto Repair",
            "type":"Services"
        }
    ],
    "sg:phone":"+44 1284 752672",
    "sg:postcode":"IP33 1JF",
    "sg:province":"Suffolk",
    "sg:tags":[
        "car",
        "servicing",
        "radiator"
    ],
    "wof:name":"Serck Marston",
    "wof:placetype":"venue"
},
  "geometry": {"coordinates":[0.70932,52.249905],"type":"Point"}
}