{
  "type": "Feature",
  "properties": {
    "addr:full":"69 Bournemead Ave Northolt Greater London UB5 6PX",
    "addr:housenumber":"69",
    "addr:postcode":"ub5 6px",
    "addr:street":"Bournemead Ave",
    "iso:country":"GB",
    "sg:address":"69 Bournemead Ave",
    "sg:city":"Northolt",
    "sg:classifiers":[
        {
            "category":"Building & Trades",
            "subcategory":"Construction",
            "type":"Services"
        }
    ],
    "sg:postcode":"UB5 6PX",
    "sg:province":"Greater London",
    "sg:tags":[
        "builder"
    ],
    "wof:name":"Elsworth,Brian,",
    "wof:placetype":"venue"
},
  "geometry": {"coordinates":[-0.406579,51.536915],"type":"Point"}
}