{
  "type": "Feature",
  "properties": {
    "iso:country":"GB",
    "sg:address":"29 Vicarage Av",
    "sg:city":"Cheadle",
    "sg:classifiers":[
        {
            "category":"Place Of Worship",
            "type":"Public Place"
        }
    ],
    "sg:phone":"+44 161 485 1685",
    "sg:postcode":"SK8 7JW",
    "sg:province":"Cheshire",
    "wof:name":"St Anns R C Church",
    "wof:placetype":"venue"
},
  "geometry": {"coordinates":[-2.183489,53.365353],"type":"Point"}
}