{
  "type": "Feature",
  "properties": {
    "addr:full":"New Hinksey Vicarage, Vicarage Rd Oxford Oxfordshire OX1 4RD",
    "addr:postcode":"ox1 4rd",
    "addr:street":"Vicarage Rd",
    "iso:country":"GB",
    "sg:address":"New Hinksey Vicarage, Vicarage Rd",
    "sg:city":"Oxford",
    "sg:classifiers":[
        {
            "category":"Place Of Worship",
            "type":"Public Place"
        }
    ],
    "sg:phone":"+44 1865 245879",
    "sg:postcode":"OX1 4RD",
    "sg:province":"Oxfordshire",
    "wof:name":"St John Evangelist C Of E Church",
    "wof:placetype":"venue"
},
  "geometry": {"coordinates":[-1.259489,51.756207],"type":"Point"}
}