{
  "type": "Feature",
  "properties": {
    "addr:full":"1a Warwick Crescent Harrogate North Yorkshire HG2 8JA",
    "addr:housenumber":"1a",
    "addr:postcode":"hg2 8ja",
    "addr:street":"Warwick Crescent",
    "iso:country":"GB",
    "sg:address":"1a Warwick Crescent",
    "sg:city":"Harrogate",
    "sg:classifiers":[
        {
            "category":"Professional",
            "subcategory":"Management & Consulting",
            "type":"Services"
        }
    ],
    "sg:phone":"+44 1423 524111",
    "sg:postcode":"HG2 8JA",
    "sg:province":"North Yorkshire",
    "sg:tags":[
        "consultant",
        "business"
    ],
    "wof:name":"Focus Management Consulting",
    "wof:placetype":"venue"
},
  "geometry": {"coordinates":[-1.530423,53.983364],"type":"Point"}
}