{
  "type": "Feature",
  "properties": {
    "addr:full":"1 Blake Street Congleton Cheshire CW12 4DS",
    "addr:housenumber":"1",
    "addr:postcode":"cw12 4ds",
    "addr:street":"Blake Street",
    "iso:country":"GB",
    "sg:address":"1 Blake Street",
    "sg:city":"Congleton",
    "sg:classifiers":[
        {
            "category":"Professional",
            "subcategory":"Secretarial Services",
            "type":"Services"
        }
    ],
    "sg:phone":"+44 1260 299025",
    "sg:postcode":"CW12 4DS",
    "sg:province":"Cheshire",
    "wof:name":"Blake Street Office Services",
    "wof:placetype":"venue"
},
  "geometry": {"coordinates":[-2.2231359482,53.1642494202],"type":"Point"}
}