{
  "type": "Feature",
  "properties": {
    "addr:full":"High St Stamford Cambridgeshire PE9 2AL",
    "addr:postcode":"pe9 2al",
    "addr:street":"High St",
    "iso:country":"GB",
    "sg:address":"High St",
    "sg:city":"Stamford",
    "sg:classifiers":[
        {
            "category":"Shopping",
            "subcategory":"Clothing, Apparel, & Fashions",
            "type":"Retail Goods"
        }
    ],
    "sg:postcode":"PE9 2AL",
    "sg:province":"Cambridgeshire",
    "sg:tags":[
        "shop"
    ],
    "wof:name":"Edinburgh Woollen Mill Ltd (The)",
    "wof:placetype":"venue"
},
  "geometry": {"coordinates":[-0.4781840146,52.6523590088],"type":"Point"}
}