{
  "type": "Feature",
  "properties": {
    "addr:full":"40 Bridge Street Caernarfon Gwynedd LL55 1AF",
    "addr:housenumber":"40",
    "addr:postcode":"ll55 1af",
    "addr:street":"Bridge Street",
    "iso:country":"GB",
    "sg:address":"40 Bridge Street",
    "sg:city":"Caernarfon",
    "sg:classifiers":[
        {
            "category":"Real Estate",
            "subcategory":"Surveying",
            "type":"Services"
        },
        {
            "category":"Real Estate",
            "subcategory":"Architect",
            "type":"Services"
        }
    ],
    "sg:phone":"+44 1286 672924",
    "sg:postcode":"LL55 1AF",
    "sg:province":"Gwynedd",
    "sg:tags":[
        "surveyor",
        "valuer"
    ],
    "sg:website":"http://www.medforth.co.uk",
    "wof:name":"Chas Medforth & Co",
    "wof:placetype":"venue"
},
  "geometry": {"coordinates":[-4.2740287781,53.140750885],"type":"Point"}
}