{
  "type": "Feature",
  "properties": {
    "iso:country":"GB",
    "sg:address":"239a Seaside",
    "sg:city":"Eastbourne",
    "sg:classifiers":[
        {
            "category":"Professional",
            "subcategory":"Accounting & Tax Preparation",
            "type":"Services"
        }
    ],
    "sg:phone":"+44 1323 412191",
    "sg:postcode":"BN22 7NT",
    "sg:province":"East Sussex",
    "sg:tags":[
        "consultant"
    ],
    "wof:name":"David Cox Associates",
    "wof:placetype":"venue"
},
  "geometry": {"coordinates":[0.2993690073,50.7782936096],"type":"Point"}
}