{
  "type": "Feature",
  "properties": {
    "addr:full":"24 George Street Montrose Aberdeenshire DD10 8EW",
    "addr:housenumber":"24",
    "addr:postcode":"dd10 8ew",
    "addr:street":"George Street",
    "iso:country":"GB",
    "sg:address":"24 George Street",
    "sg:city":"Montrose",
    "sg:classifiers":[
        {
            "category":"Autos & Motor Vehicles",
            "subcategory":"Auto Supplies",
            "type":"Retail Goods"
        }
    ],
    "sg:phone":"+44 1674 676734",
    "sg:postcode":"DD10 8EW",
    "sg:province":"Aberdeenshire",
    "sg:tags":[
        "exhaust",
        "absorber",
        "shock"
    ],
    "wof:name":"Kwik-Fit",
    "wof:placetype":"venue"
},
  "geometry": {"coordinates":[-2.466389,56.708271],"type":"Point"}
}