{
  "type": "Feature",
  "properties": {
    "addr:full":"56 Grange Rd Harwich Essex CO12 4JL",
    "addr:housenumber":"56",
    "addr:postcode":"co12 4jl",
    "addr:street":"Grange Rd",
    "iso:country":"GB",
    "sg:address":"56 Grange Rd",
    "sg:city":"Harwich",
    "sg:classifiers":[
        {
            "category":"Parking",
            "type":"Transportation"
        }
    ],
    "sg:phone":"+44 1255 506543",
    "sg:postcode":"CO12 4JL",
    "sg:province":"Essex",
    "sg:tags":[
        "car",
        "valet"
    ],
    "wof:name":"Shift N Shine",
    "wof:placetype":"venue"
},
  "geometry": {"coordinates":[1.262068,51.932674],"type":"Point"}
}