{
  "type": "Feature",
  "properties": {
    "addr:full":"1 Benbow Road Clydebank East Dunbartonshire G81 4DP",
    "addr:housenumber":"1",
    "addr:postcode":"g81 4dp",
    "addr:street":"Benbow Road",
    "iso:country":"GB",
    "sg:address":"1 Benbow Road",
    "sg:city":"Clydebank",
    "sg:classifiers":[
        {
            "category":"Professional",
            "subcategory":"Art Services",
            "type":"Services"
        },
        {
            "category":"Building & Trades",
            "subcategory":"Construction",
            "type":"Services"
        }
    ],
    "sg:postcode":"G81 4DP",
    "sg:province":"East Dunbartonshire",
    "sg:tags":[
        "decorator",
        "painter"
    ],
    "wof:name":"Peter Duffy",
    "wof:placetype":"venue"
},
  "geometry": {"coordinates":[-4.4203572273,55.9063301086],"type":"Point"}
}