{
  "type": "Feature",
  "properties": {
    "iso:country":"GB",
    "sg:address":"86 High Street",
    "sg:city":"Hythe",
    "sg:classifiers":[
        {
            "category":"Conference Center",
            "type":"Public Place"
        }
    ],
    "sg:phone":"+44 1303 264000",
    "sg:postcode":"CT21 5AJ",
    "sg:province":"Kent",
    "wof:name":"Connoisseur Conferences 4000",
    "wof:placetype":"venue"
},
  "geometry": {"coordinates":[1.084527,51.071442],"type":"Point"}
}