{
  "type": "Feature",
  "properties": {
    "iso:country":"GB",
    "sg:address":"32 Western Avenue",
    "sg:city":"Brentwood",
    "sg:classifiers":[
        {
            "category":"Building & Trades",
            "subcategory":"Construction",
            "type":"Services"
        }
    ],
    "sg:phone":"+44 1277 218385",
    "sg:postcode":"CM14 4XS",
    "sg:province":"Essex",
    "sg:tags":[
        "builder"
    ],
    "wof:name":"A D Todd",
    "wof:placetype":"venue"
},
  "geometry": {"coordinates":[0.300433,51.624226],"type":"Point"}
}