{
  "type": "Feature",
  "properties": {
    "addr:full":"25 High Street, Kingswood Bristol City of Bristol BS15 4AA",
    "addr:housenumber":"25",
    "addr:postcode":"bs15 4aa",
    "addr:street":"High Street",
    "iso:country":"GB",
    "sg:address":"25 High Street, Kingswood",
    "sg:city":"Bristol",
    "sg:classifiers":[
        {
            "category":"Home & Garden",
            "subcategory":"Household Appliances",
            "type":"Retail Goods"
        }
    ],
    "sg:phone":"+44 117 967 3908",
    "sg:postcode":"BS15 4AA",
    "sg:province":"City of Bristol",
    "sg:tags":[
        "electrical"
    ],
    "wof:name":"Radiant Electrics",
    "wof:placetype":"venue"
},
  "geometry": {"coordinates":[-2.504763,51.462608],"type":"Point"}
}