{
  "type": "Feature",
  "properties": {
    "iso:country":"GB",
    "sg:address":"Outlooks, Castle Road",
    "sg:city":"Portland",
    "sg:classifiers":[
        {
            "category":"Organizations",
            "subcategory":"Non-profit Organization",
            "type":"Services"
        }
    ],
    "sg:phone":"+44 1305 823794",
    "sg:postcode":"DT5 1AU",
    "sg:province":"Dorset",
    "sg:tags":[
        "charitable",
        "organisation",
        "voluntary",
        "charity"
    ],
    "wof:name":"N C H ACTION FOR CHILDREN",
    "wof:placetype":"venue"
},
  "geometry": {"coordinates":[-2.435969,50.546902],"type":"Point"}
}