{
  "type": "Feature",
  "properties": {
    "addr:full":"Camp Reception, The Elms Stratford Upon Avon Warwickshire CV37 7AB",
    "addr:postcode":"cv37 7ab",
    "iso:country":"GB",
    "sg:address":"Camp Reception, The Elms",
    "sg:city":"Stratford Upon Avon",
    "sg:classifiers":[
        {
            "category":"Recreation",
            "subcategory":"Campground",
            "type":"Entertainment"
        }
    ],
    "sg:phone":"+44 1789 292312",
    "sg:postcode":"CV37 7AB",
    "sg:province":"Warwickshire",
    "sg:tags":[
        "holiday",
        "centre",
        "camp"
    ],
    "wof:name":"Elms Camp The",
    "wof:placetype":"venue"
},
  "geometry": {"coordinates":[-1.7072689533,52.1941337585],"type":"Point"}
}