{
  "type": "Feature",
  "properties": {
    "addr:full":"61 Wallis Rd, Hackney Hackney Greater London E9 5LH",
    "addr:housenumber":"61",
    "addr:postcode":"e9 5lh",
    "addr:street":"Wallis Rd",
    "iso:country":"GB",
    "sg:address":"61 Wallis Rd, Hackney",
    "sg:city":"Hackney",
    "sg:classifiers":[
        {
            "category":"Building & Trades",
            "subcategory":"Construction",
            "type":"Services"
        }
    ],
    "sg:phone":"+44 70 5013 4700",
    "sg:postcode":"E9 5LH",
    "sg:province":"Greater London",
    "sg:tags":[
        "joiner",
        "carpenter"
    ],
    "wof:name":"A.S.A.P.",
    "wof:placetype":"venue"
},
  "geometry": {"coordinates":[-0.025263,51.544086],"type":"Point"}
}