{
  "type": "Feature",
  "properties": {
    "iso:country":"GB",
    "sg:address":"Farmhouse Chapel",
    "sg:city":"North Berwick",
    "sg:classifiers":[
        {
            "category":"Farming",
            "subcategory":"Farm",
            "type":"Manufacturing & Wholesale Goods"
        }
    ],
    "sg:phone":"+44 1620 893743",
    "sg:postcode":"EH39 5LP",
    "sg:province":"East Lothian",
    "sg:tags":[
        "mixed",
        "crop"
    ],
    "wof:name":"T Elder",
    "wof:placetype":"venue"
},
  "geometry": {"coordinates":[-2.7170538902,56.058555603],"type":"Point"}
}