{
  "type": "Feature",
  "properties": {
    "iso:country":"GB",
    "sg:address":"3 The Courtyard, Stype",
    "sg:city":"Hungerford",
    "sg:classifiers":[
        {
            "category":"Professional",
            "subcategory":"Engineering",
            "type":"Services"
        },
        {
            "category":"Professional",
            "subcategory":"Art Services",
            "type":"Services"
        }
    ],
    "sg:phone":"+44 1488 684554",
    "sg:postcode":"RG17 0RE",
    "sg:province":"Berkshire",
    "sg:tags":[
        "consultant",
        "design",
        "electronic",
        "engineer"
    ],
    "wof:name":"Triteq Ltd",
    "wof:placetype":"venue"
},
  "geometry": {"coordinates":[-1.516156,51.413197],"type":"Point"}
}