{
  "type": "Feature",
  "properties": {
    "addr:full":"Broadgate House, Grasmere Ambleside Cumbria LA22 9SY",
    "addr:postcode":"la22 9sy",
    "addr:street":"Broadgate;Grasmere",
    "iso:country":"GB",
    "sg:address":"Broadgate House, Grasmere",
    "sg:city":"Ambleside",
    "sg:classifiers":[
        {
            "category":"Shopping",
            "subcategory":"Books",
            "type":"Retail Goods"
        }
    ],
    "sg:postcode":"LA22 9SY",
    "sg:province":"Cumbria",
    "sg:tags":[
        "bookseller"
    ],
    "wof:name":"Sam Read",
    "wof:placetype":"venue"
},
  "geometry": {"coordinates":[-2.963089,54.432606],"type":"Point"}
}