{
  "type": "Feature",
  "properties": {
    "iso:country":"GB",
    "sg:address":"22 Clapham Park Rd",
    "sg:city":"Clapham",
    "sg:classifiers":[
        {
            "category":"Retail",
            "subcategory":"Driving School",
            "type":"Services"
        }
    ],
    "sg:phone":"+44 20 7622 1260",
    "sg:postcode":"SW4 7BB",
    "sg:province":"Greater London",
    "wof:name":"Kerel Mason",
    "wof:placetype":"venue"
},
  "geometry": {"coordinates":[-0.13646,51.461029],"type":"Point"}
}