{
  "type": "Feature",
  "properties": {
    "addr:full":"Crawford House, 1a Willow Street London Greater London E4 7EG",
    "addr:housenumber":"1a",
    "addr:postcode":"e4 7eg",
    "addr:street":"Willow Street",
    "iso:country":"GB",
    "sg:address":"Crawford House, 1a Willow Street",
    "sg:city":"London",
    "sg:classifiers":[
        {
            "category":"Building & Trades",
            "subcategory":"Construction",
            "type":"Services"
        }
    ],
    "sg:phone":"+44 20 8559 3533",
    "sg:postcode":"E4 7EG",
    "sg:province":"Greater London",
    "sg:tags":[
        "contractor"
    ],
    "wof:name":"R C T Construction Ltd",
    "wof:placetype":"venue"
},
  "geometry": {"coordinates":[0.0046999999,51.6316986084],"type":"Point"}
}