{
  "type": "Feature",
  "properties": {
    "addr:full":"1110 Lincoln Road, Werrington Peterborough Cambridgeshire PE4 6BP",
    "addr:housenumber":"1110",
    "addr:postcode":"pe4 6bp",
    "addr:street":"Lincoln Road",
    "iso:country":"GB",
    "sg:address":"1110 Lincoln Road, Werrington",
    "sg:city":"Peterborough",
    "sg:classifiers":[
        {
            "category":"Insurance",
            "subcategory":"Insurance Agent",
            "type":"Services"
        }
    ],
    "sg:phone":"+44 1733 325555",
    "sg:postcode":"PE4 6BP",
    "sg:province":"Cambridgeshire",
    "sg:tags":[
        "broker"
    ],
    "wof:name":"Insurewise Ltd.",
    "wof:placetype":"venue"
},
  "geometry": {"coordinates":[-0.2722559869,52.6053199768],"type":"Point"}
}