{
  "type": "Feature",
  "properties": {
    "addr:full":"202 The Blackfriars Foundry, 156 Blackfriars Rd Southwark Greater London SE1 8EN",
    "addr:housenumber":"202;156",
    "addr:postcode":"se1 8en",
    "addr:street":"The;Blackfriars Rd",
    "iso:country":"GB",
    "sg:address":"202 The Blackfriars Foundry, 156 Blackfriars Rd",
    "sg:city":"Southwark",
    "sg:classifiers":[
        {
            "category":"Real Estate",
            "subcategory":"Architect",
            "type":"Services"
        }
    ],
    "sg:phone":"+44 20 7721 7034",
    "sg:postcode":"SE1 8EN",
    "sg:province":"Greater London",
    "wof:name":"Palmar Associates",
    "wof:placetype":"venue"
},
  "geometry": {"coordinates":[-0.1041999981,51.5010414124],"type":"Point"}
}