{
  "type": "Feature",
  "properties": {
    "addr:full":"Chequers Lane, Eversley Cross Basingstoke Berkshire RG27 0NY",
    "addr:postcode":"rg27 0ny",
    "addr:street":"Chequers Lane",
    "iso:country":"GB",
    "sg:address":"Chequers Lane, Eversley Cross",
    "sg:city":"Basingstoke",
    "sg:classifiers":[
        {
            "category":"Retail",
            "subcategory":"Auto Repair",
            "type":"Services"
        }
    ],
    "sg:phone":"+44 1252 890801",
    "sg:postcode":"RG27 0NY",
    "sg:province":"Berkshire",
    "sg:tags":[
        "modification",
        "garage"
    ],
    "wof:name":"Sambrook Motor Services",
    "wof:placetype":"venue"
},
  "geometry": {"coordinates":[-0.8611109853,51.3447189331],"type":"Point"}
}