{
  "type": "Feature",
  "properties": {
    "iso:country":"GB",
    "sg:address":"62b High St",
    "sg:city":"Biggar",
    "sg:classifiers":[
        {
            "category":"Home & Garden",
            "subcategory":"Household Appliances",
            "type":"Retail Goods"
        }
    ],
    "sg:postcode":"ML12 6DA",
    "sg:province":"Dumfries and Galloway",
    "sg:tags":[
        "electrical"
    ],
    "wof:name":"Renton,Stephen John,",
    "wof:placetype":"venue"
},
  "geometry": {"coordinates":[-3.5260150433,55.6235542297],"type":"Point"}
}