{
  "type": "Feature",
  "properties": {
    "addr:full":"139 Church Road Hove East Sussex BN3 2AE",
    "addr:housenumber":"139",
    "addr:postcode":"bn3 2ae",
    "addr:street":"Church Road",
    "iso:country":"GB",
    "sg:address":"139 Church Road",
    "sg:city":"Hove",
    "sg:classifiers":[
        {
            "category":"Travel",
            "subcategory":"Travel Agent",
            "type":"Entertainment"
        }
    ],
    "sg:phone":"+44 1273 367900",
    "sg:postcode":"BN3 2AE",
    "sg:province":"East Sussex",
    "wof:name":"Thomas Cook",
    "wof:placetype":"venue"
},
  "geometry": {"coordinates":[-0.1731020063,50.8280448914],"type":"Point"}
}