{
  "type": "Feature",
  "properties": {
    "addr:full":"Crook Hill, Braishfield Romsey Hampshire SO51 0QB",
    "addr:postcode":"so51 0qb",
    "addr:street":"Crook Hill",
    "iso:country":"GB",
    "sg:address":"Crook Hill, Braishfield",
    "sg:city":"Romsey",
    "sg:classifiers":[
        {
            "category":"Bars & Pubs",
            "type":"Food & Drink"
        }
    ],
    "sg:phone":"+44 1794 368530",
    "sg:postcode":"SO51 0QB",
    "sg:province":"Hampshire",
    "sg:tags":[
        "pubs",
        "inn"
    ],
    "wof:name":"The Dog & Crook",
    "wof:placetype":"venue"
},
  "geometry": {"coordinates":[-1.47155,51.012981],"type":"Point"}
}