{
  "type": "Feature",
  "properties": {
    "addr:full":"Manchester Airport Manchester Greater Manchester M90 1PQ",
    "addr:postcode":"m90 1pq",
    "iso:country":"GB",
    "sg:address":"Manchester Airport",
    "sg:city":"Manchester",
    "sg:classifiers":[
        {
            "category":"Bus Charters",
            "type":"Transportation"
        }
    ],
    "sg:postcode":"M90 1PQ",
    "sg:province":"Greater Manchester",
    "sg:tags":[
        "coach"
    ],
    "wof:name":"Star Line Travel",
    "wof:placetype":"venue"
},
  "geometry": {"coordinates":[-2.26608,53.3606],"type":"Point"}
}