{
  "type": "Feature",
  "properties": {
    "iso:country":"GB",
    "sg:address":"Unit C Jedburgh Court, Jedburgh Close",
    "sg:city":"Cambridge",
    "sg:classifiers":[
        {
            "category":"Government",
            "subcategory":"Post Office",
            "type":"Public Place"
        }
    ],
    "sg:postcode":"CB4 2XH",
    "sg:province":"Cambridgeshire",
    "sg:tags":[
        "messenger",
        "courier"
    ],
    "wof:name":"Millennium Couriers",
    "wof:placetype":"venue"
},
  "geometry": {"coordinates":[0.1224149987,52.2317085266],"type":"Point"}
}