{
  "type": "Feature",
  "properties": {
    "addr:full":"57 High Street, Bovingdon Hemel Hempstead Hertfordshire HP3 0HP",
    "addr:housenumber":"57",
    "addr:postcode":"hp3 0hp",
    "addr:street":"High Street;Hempstead",
    "iso:country":"GB",
    "sg:address":"57 High Street, Bovingdon",
    "sg:city":"Hemel Hempstead",
    "sg:classifiers":[
        {
            "category":"Health Services",
            "subcategory":"Dentist",
            "type":"Services"
        }
    ],
    "sg:postcode":"HP3 0HP",
    "sg:province":"Hertfordshire",
    "wof:name":"L Walters & N G Exley",
    "wof:placetype":"venue"
},
  "geometry": {"coordinates":[-0.5307930112,51.7221641541],"type":"Point"}
}