{
  "type": "Feature",
  "properties": {
    "iso:country":"GB",
    "sg:address":"Unit 8 Cleeve House, Lambourne Crescent, Llanishen",
    "sg:city":"Cardiff",
    "sg:classifiers":[
        {
            "category":"Banks & Credit Unions",
            "subcategory":"Financial Services",
            "type":"Services"
        }
    ],
    "sg:phone":"+44 29 2074 6000",
    "sg:postcode":"CF14 5GJ",
    "sg:province":"Cardiff",
    "sg:tags":[
        "consultant"
    ],
    "wof:name":"Lombard North Central Plc",
    "wof:placetype":"venue"
},
  "geometry": {"coordinates":[-3.191978,51.522346],"type":"Point"}
}