{
  "type": "Feature",
  "properties": {
    "addr:full":"Erskine Rd Rotherham South Yorkshire S65 1RF",
    "addr:postcode":"s65 1rf",
    "addr:street":"Erskine Rd",
    "iso:country":"GB",
    "sg:address":"Erskine Rd",
    "sg:city":"Rotherham",
    "sg:classifiers":[
        {
            "category":"Utilities",
            "subcategory":"Refuse",
            "type":"Services"
        }
    ],
    "sg:phone":"+44 1709 835258",
    "sg:postcode":"S65 1RF",
    "sg:province":"South Yorkshire",
    "sg:tags":[
        "disposal",
        "waste"
    ],
    "wof:name":"Inter Waste",
    "wof:placetype":"venue"
},
  "geometry": {"coordinates":[-1.351095,53.438286],"type":"Point"}
}