{
  "type": "Feature",
  "properties": {
    "iso:country":"GB",
    "sg:address":"Gorse Hill Unit, Milborne St Andrew",
    "sg:city":"Blandford Forum",
    "sg:classifiers":[
        {
            "category":"Retail",
            "subcategory":"Auto Repair",
            "type":"Services"
        }
    ],
    "sg:postcode":"DT11 0LH",
    "sg:province":"Dorset",
    "sg:tags":[
        "modification",
        "garage"
    ],
    "wof:name":"P P Motors",
    "wof:placetype":"venue"
},
  "geometry": {"coordinates":[-2.27663,50.79969],"type":"Point"}
}