{
  "type": "Feature",
  "properties": {
    "addr:full":"128-132 North Parade, Matlock Bath Matlock Derbyshire DE4 3NS",
    "addr:housenumber":"128-132",
    "addr:postcode":"de4 3ns",
    "addr:street":"North Parade",
    "iso:country":"GB",
    "sg:address":"128-132 North Parade, Matlock Bath",
    "sg:city":"Matlock",
    "sg:classifiers":[
        {
            "category":"Food & Beverages",
            "subcategory":"Meat & Fish",
            "type":"Retail Goods"
        },
        {
            "category":"Food & Beverages",
            "subcategory":"Groceries & Convenience Stores",
            "type":"Retail Goods"
        }
    ],
    "sg:phone":"+44 1629 584662",
    "sg:postcode":"DE4 3NS",
    "sg:province":"Derbyshire",
    "sg:tags":[
        "shop",
        "chip"
    ],
    "wof:name":"Promenade Fish Bar",
    "wof:placetype":"venue"
},
  "geometry": {"coordinates":[-1.562978,53.121155],"type":"Point"}
}