{
  "type": "Feature",
  "properties": {
    "addr:full":"Victoria Building, King St Wigan Lancashire WN1 1BS",
    "addr:postcode":"wn1 1bs",
    "addr:street":"King St",
    "iso:country":"GB",
    "sg:address":"Victoria Building, King St",
    "sg:city":"Wigan",
    "sg:classifiers":[
        {
            "category":"Shopping",
            "subcategory":"Event Tickets",
            "type":"Retail Goods"
        }
    ],
    "sg:phone":"+44 1942 745506",
    "sg:postcode":"WN1 1BS",
    "sg:province":"Lancashire",
    "sg:tags":[
        "agency"
    ],
    "wof:name":"Club Zone",
    "wof:placetype":"venue"
},
  "geometry": {"coordinates":[-2.6335320473,53.5441551208],"type":"Point"}
}