{
  "type": "Feature",
  "properties": {
    "addr:full":"60 Chorley New Rd, Bolton Lancashire BL1 4DA",
    "addr:housenumber":"60",
    "addr:postcode":"bl1 4da",
    "addr:street":"Chorley New Rd",
    "iso:country":"GB",
    "sg:address":"60 Chorley New Rd,",
    "sg:city":"Bolton",
    "sg:classifiers":[
        {
            "category":"Real Estate",
            "subcategory":"Real Estate Agent",
            "type":"Services"
        }
    ],
    "sg:postcode":"BL1 4DA",
    "sg:province":"Lancashire",
    "wof:name":"Huntingdon Group Ltd",
    "wof:placetype":"venue"
},
  "geometry": {"coordinates":[-2.4457559586,53.5816841125],"type":"Point"}
}