{
  "type": "Feature",
  "properties": {
    "addr:full":"Crossrds Garage, Bispham Rd, Carleton Poulton Le Fylde Lancashire FY6 7NL",
    "addr:postcode":"fy6 7nl",
    "addr:street":"Bispham Rd",
    "iso:country":"GB",
    "sg:address":"Crossrds Garage, Bispham Rd, Carleton",
    "sg:city":"Poulton Le Fylde",
    "sg:classifiers":[
        {
            "category":"Retail",
            "subcategory":"Auto Repair",
            "type":"Services"
        }
    ],
    "sg:phone":"+44 1253 891811",
    "sg:postcode":"FY6 7NL",
    "sg:province":"Lancashire",
    "sg:tags":[
        "modification",
        "garage"
    ],
    "wof:name":"National Tyres & Autocare",
    "wof:placetype":"venue"
},
  "geometry": {"coordinates":[-2.994659,53.84808],"type":"Point"}
}