{
  "type": "Feature",
  "properties": {
    "addr:full":"133 High St London Greater London SE20 7DS",
    "addr:housenumber":"133",
    "addr:postcode":"se20 7ds",
    "addr:street":"High St",
    "iso:country":"GB",
    "sg:address":"133 High St",
    "sg:city":"London",
    "sg:classifiers":[
        {
            "category":"Organizations",
            "subcategory":"Non-profit Organization",
            "type":"Services"
        }
    ],
    "sg:postcode":"SE20 7DS",
    "sg:province":"Greater London",
    "sg:tags":[
        "organisation",
        "voluntary",
        "charity"
    ],
    "wof:name":"D A W N",
    "wof:placetype":"venue"
},
  "geometry": {"coordinates":[-0.052469,51.41507],"type":"Point"}
}