{
  "type": "Feature",
  "properties": {
    "addr:full":"1 Portland Place Cheltenham Gloucestershire GL52 2HX",
    "addr:housenumber":"1",
    "addr:postcode":"gl52 2hx",
    "addr:street":"Portland Place",
    "iso:country":"GB",
    "sg:address":"1 Portland Place",
    "sg:city":"Cheltenham",
    "sg:classifiers":[
        {
            "category":"Professional",
            "subcategory":"Business Services",
            "type":"Services"
        }
    ],
    "sg:postcode":"GL52 2HX",
    "sg:province":"Gloucestershire",
    "sg:tags":[
        "bookmaker"
    ],
    "wof:name":"Stephen Hearle Turf Accountants",
    "wof:placetype":"venue"
},
  "geometry": {"coordinates":[-2.068576,51.903976],"type":"Point"}
}