{
  "type": "Feature",
  "properties": {
    "addr:full":"52 Strathnaver Avenue, Walney Barrow-in-furness Cumbria LA14 3DG",
    "addr:housenumber":"52",
    "addr:postcode":"la14 3dg",
    "addr:street":"Strathnaver Avenue Walney",
    "iso:country":"GB",
    "sg:address":"52 Strathnaver Avenue, Walney",
    "sg:city":"Barrow-in-furness",
    "sg:classifiers":[
        {
            "category":"Building & Trades",
            "subcategory":"Plumbing",
            "type":"Services"
        }
    ],
    "sg:phone":"+44 1229 471808",
    "sg:postcode":"LA14 3DG",
    "sg:province":"Cumbria",
    "sg:tags":[
        "plumber",
        "heating"
    ],
    "wof:name":"John Walker",
    "wof:placetype":"venue"
},
  "geometry": {"coordinates":[-3.2532451153,54.1018257141],"type":"Point"}
}