{
  "type": "Feature",
  "properties": {
    "iso:country":"GB",
    "sg:address":"30a County Road",
    "sg:city":"Swindon",
    "sg:classifiers":[
        {
            "category":"Retail",
            "subcategory":"Repair Shop",
            "type":"Services"
        }
    ],
    "sg:postcode":"SN1 2EW",
    "sg:province":"Wiltshire",
    "sg:tags":[
        "radio",
        "television",
        "video"
    ],
    "wof:name":"Wiliams Tv & Video",
    "wof:placetype":"venue"
},
  "geometry": {"coordinates":[-1.775674,51.567245],"type":"Point"}
}