{
  "type": "Feature",
  "properties": {
    "addr:full":"Unit 13b Bidavon Industrial Estate, Waterloo Road Alcester Warwickshire B50 4JN",
    "addr:housenumber":"unit 13b",
    "addr:postcode":"b50 4jn",
    "addr:street":"Bidavon Industrial Estate Waterloo Road",
    "iso:country":"GB",
    "sg:address":"Unit 13b Bidavon Industrial Estate, Waterloo Road",
    "sg:city":"Alcester",
    "sg:classifiers":[
        {
            "category":"Retail",
            "subcategory":"Auto Repair",
            "type":"Services"
        }
    ],
    "sg:phone":"+44 1789 772830",
    "sg:postcode":"B50 4JN",
    "sg:province":"Warwickshire",
    "sg:tags":[
        "modification",
        "garage"
    ],
    "wof:name":"Motor & Engineering Services",
    "wof:placetype":"venue"
},
  "geometry": {"coordinates":[-1.8540199995,52.1733589172],"type":"Point"}
}