{
  "type": "Feature",
  "properties": {
    "addr:full":"8 Reynolds Pl Crawley West Sussex RH11 7HB",
    "addr:housenumber":"8",
    "addr:postcode":"rh11 7hb",
    "addr:street":"Reynolds Pl",
    "iso:country":"GB",
    "sg:address":"8 Reynolds Pl",
    "sg:city":"Crawley",
    "sg:classifiers":[
        {
            "category":"Home & Garden",
            "subcategory":"Building Materials",
            "type":"Retail Goods"
        }
    ],
    "sg:postcode":"RH11 7HB",
    "sg:province":"West Sussex",
    "sg:tags":[
        "ornamental",
        "metalwork"
    ],
    "wof:name":"Green, Dennis,",
    "wof:placetype":"venue"
},
  "geometry": {"coordinates":[-0.199832,51.119503],"type":"Point"}
}