{
  "type": "Feature",
  "properties": {
    "iso:country":"GB",
    "sg:address":"Dallas Rd",
    "sg:city":"Lancaster",
    "sg:classifiers":[
        {
            "category":"Retail",
            "subcategory":"Auto Repair",
            "type":"Services"
        }
    ],
    "sg:postcode":"LA1 1TP",
    "sg:province":"Lancashire",
    "sg:tags":[
        "modification",
        "garage"
    ],
    "wof:name":"Tamassy,Martin,",
    "wof:placetype":"venue"
},
  "geometry": {"coordinates":[-2.8050439358,54.0478439331],"type":"Point"}
}