{
  "type": "Feature",
  "properties": {
    "addr:full":"53 Ullswater Rd Lancaster Lancashire LA1 3PS",
    "addr:housenumber":"53",
    "addr:postcode":"la1 3ps",
    "addr:street":"Ullswater Rd",
    "iso:country":"GB",
    "sg:address":"53 Ullswater Rd",
    "sg:city":"Lancaster",
    "sg:classifiers":[
        {
            "category":"Professional",
            "type":"Services"
        }
    ],
    "sg:phone":"+44 1524 844728",
    "sg:postcode":"LA1 3PS",
    "sg:province":"Lancashire",
    "sg:tags":[
        "archaeologist"
    ],
    "wof:name":"Nigel R J Neil",
    "wof:placetype":"venue"
},
  "geometry": {"coordinates":[-2.790389,54.050694],"type":"Point"}
}