{
  "type": "Feature",
  "properties": {
    "addr:full":"Devonshire Ho, Devonshire Sq Loughborough Leicestershire LE11 3DW",
    "addr:postcode":"le11 3dw",
    "addr:street":"Devonshire Sq",
    "iso:country":"GB",
    "sg:address":"Devonshire Ho, Devonshire Sq",
    "sg:city":"Loughborough",
    "sg:classifiers":[
        {
            "category":"Social Services",
            "subcategory":"Retirement Home",
            "type":"Services"
        }
    ],
    "sg:phone":"+44 1509 264634",
    "sg:postcode":"LE11 3DW",
    "sg:province":"Leicestershire",
    "sg:tags":[
        "care"
    ],
    "wof:name":"Primrose Care Ltd",
    "wof:placetype":"venue"
},
  "geometry": {"coordinates":[-1.223474,52.768524],"type":"Point"}
}