{
  "type": "Feature",
  "properties": {
    "iso:country":"GB",
    "sg:address":"Knockeen Farm, Barr",
    "sg:city":"Girvan",
    "sg:classifiers":[
        {
            "category":"Farming",
            "subcategory":"Livestock Farm",
            "type":"Manufacturing & Wholesale Goods"
        }
    ],
    "sg:phone":"+44 1465 861207",
    "sg:postcode":"KA26 9TY",
    "sg:province":"South Ayrshire",
    "sg:tags":[
        "others"
    ],
    "wof:name":"A KAY",
    "wof:placetype":"venue"
},
  "geometry": {"coordinates":[-4.713569,55.210251],"type":"Point"}
}