{
  "type": "Feature",
  "properties": {
    "iso:country":"GB",
    "sg:address":"Burrell Way",
    "sg:city":"Cambridge",
    "sg:classifiers":[
        {
            "category":"Professional",
            "subcategory":"Management & Consulting",
            "type":"Services"
        }
    ],
    "sg:phone":"+44 1223 894025",
    "sg:postcode":"CB1 6DY",
    "sg:province":"Cambridgeshire",
    "sg:tags":[
        "consultant",
        "business"
    ],
    "wof:name":"Dickinson Consulting & Training",
    "wof:placetype":"venue"
},
  "geometry": {"coordinates":[0.321512,52.131775],"type":"Point"}
}