{
  "type": "Feature",
  "properties": {
    "addr:full":"14 Crown Row Bracknell Berkshire RG12 0TH",
    "addr:housenumber":"14",
    "addr:postcode":"rg12 0th",
    "addr:street":"Crown Row",
    "iso:country":"GB",
    "sg:address":"14 Crown Row",
    "sg:city":"Bracknell",
    "sg:classifiers":[
        {
            "category":"Fast Food",
            "type":"Food & Drink"
        }
    ],
    "sg:phone":"+44 1344 481443",
    "sg:postcode":"RG12 0TH",
    "sg:province":"Berkshire",
    "sg:tags":[
        "away",
        "meal",
        "outlet",
        "take"
    ],
    "wof:name":"Raj Indian",
    "wof:placetype":"venue"
},
  "geometry": {"coordinates":[-0.737423,51.395935],"type":"Point"}
}