{
  "type": "Feature",
  "properties": {
    "addr:full":"Beechwood Farm, Scotton Knaresborough North Yorkshire HG5 9HY",
    "addr:postcode":"hg5 9hy",
    "iso:country":"GB",
    "sg:address":"Beechwood Farm, Scotton",
    "sg:city":"Knaresborough",
    "sg:classifiers":[
        {
            "category":"Farming",
            "subcategory":"Livestock Farm",
            "type":"Manufacturing & Wholesale Goods"
        }
    ],
    "sg:postcode":"HG5 9HY",
    "sg:province":"North Yorkshire",
    "sg:tags":[
        "others"
    ],
    "wof:name":"Lionel V Walker",
    "wof:placetype":"venue"
},
  "geometry": {"coordinates":[-1.5040019751,54.0282592773],"type":"Point"}
}