{
  "type": "Feature",
  "properties": {
    "addr:full":"Bungalow Heath Farm, Carlby Stamford Cambridgeshire PE9 4NE",
    "addr:postcode":"pe9 4ne",
    "addr:street":"Heath;Stamford",
    "iso:country":"GB",
    "sg:address":"Bungalow Heath Farm, Carlby",
    "sg:city":"Stamford",
    "sg:classifiers":[
        {
            "category":"Farming",
            "subcategory":"Farm",
            "type":"Manufacturing & Wholesale Goods"
        }
    ],
    "sg:postcode":"PE9 4NE",
    "sg:province":"Cambridgeshire",
    "sg:tags":[
        "mixed",
        "crop"
    ],
    "wof:name":"P J Almond",
    "wof:placetype":"venue"
},
  "geometry": {"coordinates":[-0.445621,52.713036],"type":"Point"}
}