{
  "type": "Feature",
  "properties": {
    "iso:country":"GB",
    "sg:address":"69 Rowlands Road",
    "sg:city":"Worthing",
    "sg:classifiers":[
        {
            "category":"Home & Garden",
            "subcategory":"Home Furnishings",
            "type":"Retail Goods"
        }
    ],
    "sg:phone":"+44 1903 201001",
    "sg:postcode":"BN11 3JN",
    "sg:province":"West Sussex",
    "sg:tags":[
        "furnishers",
        "planner",
        "kitchen"
    ],
    "wof:name":"Facelift Kitchens & Doors",
    "wof:placetype":"venue"
},
  "geometry": {"coordinates":[-0.381675,50.809826],"type":"Point"}
}