{
  "type": "Feature",
  "properties": {
    "addr:full":"St Michaels Chambers, Spurriergate York North Yorkshire YO1 9QR",
    "addr:postcode":"yo1 9qr",
    "addr:street":"Spurriergate",
    "iso:country":"GB",
    "sg:address":"St Michaels Chambers, Spurriergate",
    "sg:city":"York",
    "sg:classifiers":[
        {
            "category":"Professional",
            "subcategory":"Employment Agencies",
            "type":"Services"
        }
    ],
    "sg:postcode":"YO1 9QR",
    "sg:province":"North Yorkshire",
    "sg:tags":[
        "occupational",
        "therapist"
    ],
    "wof:name":"The North Yorkshire Music Therapy Centre",
    "wof:placetype":"venue"
},
  "geometry": {"coordinates":[-1.080046,53.957413],"type":"Point"}
}