{
  "type": "Feature",
  "properties": {
    "addr:full":"223-225 Lockwood Road Huddersfield West Yorkshire HD1 3TG",
    "addr:housenumber":"223-225",
    "addr:postcode":"hd1 3tg",
    "addr:street":"Lockwood Road",
    "iso:country":"GB",
    "sg:address":"223-225 Lockwood Road",
    "sg:city":"Huddersfield",
    "sg:classifiers":[
        {
            "category":"Shopping",
            "subcategory":"News",
            "type":"Retail Goods"
        }
    ],
    "sg:phone":"+44 1484 512197",
    "sg:postcode":"HD1 3TG",
    "sg:province":"West Yorkshire",
    "sg:tags":[
        "newsagent"
    ],
    "wof:name":"Safdar Newsagents",
    "wof:placetype":"venue"
},
  "geometry": {"coordinates":[-1.794775,53.633331],"type":"Point"}
}