{
  "type": "Feature",
  "properties": {
    "addr:full":"Yaohan Plaza, 399 Edgware Rd Colindale Greater London NW9 0JJ",
    "addr:housenumber":"399",
    "addr:postcode":"nw9 0jj",
    "addr:street":"Edgware Rd",
    "iso:country":"GB",
    "sg:address":"Yaohan Plaza, 399 Edgware Rd",
    "sg:city":"Colindale",
    "sg:classifiers":[
        {
            "category":"Arts & Performance",
            "subcategory":"Comedy Club",
            "type":"Entertainment"
        }
    ],
    "sg:phone":"+44 20 8205 1131",
    "sg:postcode":"NW9 0JJ",
    "sg:province":"Greater London",
    "sg:tags":[
        "japanese"
    ],
    "wof:name":"Abeno Otonomiyake Restaurant",
    "wof:placetype":"venue"
},
  "geometry": {"coordinates":[-0.25939,51.593731],"type":"Point"}
}