{
  "type": "Feature",
  "properties": {
    "iso:country":"GB",
    "sg:address":"Unit 5 Valley Heritage Craft Centre, Valley Rd",
    "sg:city":"Cannock",
    "sg:classifiers":[
        {
            "category":"Retail",
            "subcategory":"Repair Shop",
            "type":"Services"
        }
    ],
    "sg:phone":"+44 1543 425546",
    "sg:postcode":"WS12 5TD",
    "sg:province":"Staffordshire",
    "sg:tags":[
        "furniture"
    ],
    "wof:name":"Classical Restoration",
    "wof:placetype":"venue"
},
  "geometry": {"coordinates":[-1.99329,52.713001],"type":"Point"}
}