{
  "type": "Feature",
  "properties": {
    "iso:country":"GB",
    "sg:address":"1 Mission Lane",
    "sg:city":"Falkirk",
    "sg:classifiers":[
        {
            "category":"Education",
            "subcategory":"Library",
            "type":"Public Place"
        },
        {
            "category":"Manufacturing",
            "subcategory":"Furniture",
            "type":"Manufacturing & Wholesale Goods"
        }
    ],
    "sg:phone":"+44 1324 637262",
    "sg:postcode":"FK1 1PN",
    "sg:province":"Falkirk",
    "sg:tags":[
        "reproduction"
    ],
    "wof:name":"Marnwood Reproduction",
    "wof:placetype":"venue"
},
  "geometry": {"coordinates":[-3.782899,55.99844],"type":"Point"}
}