{
  "type": "Feature",
  "properties": {
    "iso:country":"GB",
    "sg:address":"40-40a Market St",
    "sg:city":"Newton-le-willows",
    "sg:classifiers":[
        {
            "category":"Food & Beverages",
            "subcategory":"Meat & Fish",
            "type":"Retail Goods"
        }
    ],
    "sg:phone":"+44 1925 225095",
    "sg:postcode":"WA12 9AN",
    "sg:province":"Cheshire",
    "sg:tags":[
        "butcher"
    ],
    "wof:name":"McCabe,John,(Meats) Ltd",
    "wof:placetype":"venue"
},
  "geometry": {"coordinates":[-2.6413710117,53.4524154663],"type":"Point"}
}