{
  "type": "Feature",
  "properties": {
    "addr:full":"135 Bournemouth Road, Parkstone Poole Dorset BH14 9HR",
    "addr:housenumber":"135",
    "addr:postcode":"bh14 9hr",
    "addr:street":"Bournemouth Road",
    "iso:country":"GB",
    "sg:address":"135 Bournemouth Road, Parkstone",
    "sg:city":"Poole",
    "sg:classifiers":[
        {
            "category":"Professional",
            "subcategory":"Business Services",
            "type":"Services"
        },
        {
            "category":"Manufacturing",
            "subcategory":"Building Materials",
            "type":"Manufacturing & Wholesale Goods"
        }
    ],
    "sg:phone":"+44 1202 730380",
    "sg:postcode":"BH14 9HR",
    "sg:province":"Dorset",
    "sg:tags":[
        "tile",
        "mnfrs",
        "stockist"
    ],
    "wof:name":"Tile Bazar",
    "wof:placetype":"venue"
},
  "geometry": {"coordinates":[-1.9370059967,50.7247505188],"type":"Point"}
}