{
  "type": "Feature",
  "properties": {
    "addr:full":"112 Main Road, Hundleby Spilsby Lincolnshire PE23 5LZ",
    "addr:housenumber":"112",
    "addr:postcode":"pe23 5lz",
    "addr:street":"Main Road",
    "iso:country":"GB",
    "sg:address":"112 Main Road, Hundleby",
    "sg:city":"Spilsby",
    "sg:classifiers":[
        {
            "category":"Farming",
            "subcategory":"Farm",
            "type":"Manufacturing & Wholesale Goods"
        }
    ],
    "sg:postcode":"PE23 5LZ",
    "sg:province":"Lincolnshire",
    "sg:tags":[
        "mixed",
        "crop"
    ],
    "wof:name":"L Dales & Son",
    "wof:placetype":"venue"
},
  "geometry": {"coordinates":[0.081545,53.176151],"type":"Point"}
}