{
  "type": "Feature",
  "properties": {
    "addr:full":"The Strand, St Marys St Marys Cornwall TR21 0LP",
    "addr:postcode":"tr21 0lp",
    "addr:street":"The Strand St Marys",
    "iso:country":"GB",
    "sg:address":"The Strand, St Marys",
    "sg:city":"St Marys",
    "sg:classifiers":[
        {
            "category":"Farming",
            "subcategory":"Dairy Farm",
            "type":"Manufacturing & Wholesale Goods"
        },
        {
            "category":"Organizations",
            "subcategory":"Membership Organization",
            "type":"Services"
        }
    ],
    "sg:phone":"+44 1720 422720",
    "sg:postcode":"TR21 0LP",
    "sg:province":"Cornwall",
    "sg:tags":[
        "club"
    ],
    "wof:name":"The Scillonian Club",
    "wof:placetype":"venue"
},
  "geometry": {"coordinates":[-6.314754,49.914474],"type":"Point"}
}