{
  "type": "Feature",
  "properties": {
    "addr:full":"442-444 Roman Road London Greater London E3 5LU",
    "addr:housenumber":"442-444",
    "addr:postcode":"e3 5lu",
    "addr:street":"Roman Road",
    "iso:country":"GB",
    "sg:address":"442-444 Roman Road",
    "sg:city":"London",
    "sg:classifiers":[
        {
            "category":"Home & Garden",
            "subcategory":"Hardware",
            "type":"Retail Goods"
        }
    ],
    "sg:phone":"+44 20 8980 1672",
    "sg:postcode":"E3 5LU",
    "sg:province":"Greater London",
    "wof:name":"Thompson's",
    "wof:placetype":"venue"
},
  "geometry": {"coordinates":[-0.033928,51.531971],"type":"Point"}
}