{
  "type": "Feature",
  "properties": {
    "addr:full":"Unit 4, Haxby Shopping Centre, Haxby York North Yorkshire YO32 3HU",
    "addr:housenumber":"unit 4",
    "addr:postcode":"yo32 3hu",
    "addr:street":"Shopping",
    "iso:country":"GB",
    "sg:address":"Unit 4, Haxby Shopping Centre, Haxby",
    "sg:city":"York",
    "sg:classifiers":[
        {
            "category":"Shopping",
            "subcategory":"Gifts & Souvenirs",
            "type":"Retail Goods"
        }
    ],
    "sg:phone":"+44 1904 766402",
    "sg:postcode":"YO32 3HU",
    "sg:province":"North Yorkshire",
    "sg:tags":[
        "poster",
        "card"
    ],
    "wof:name":"Greetings of Haxby",
    "wof:placetype":"venue"
},
  "geometry": {"coordinates":[-1.073074,54.002644],"type":"Point"}
}