{
  "type": "Feature",
  "properties": {
    "iso:country":"GB",
    "sg:address":"26 Briar Gro",
    "sg:city":"Ayr",
    "sg:classifiers":[
        {
            "category":"Shopping",
            "subcategory":"Party Supplies",
            "type":"Retail Goods"
        }
    ],
    "sg:postcode":"KA7 3PD",
    "sg:province":"South Ayrshire",
    "sg:tags":[
        "inflatables",
        "bouncy",
        "castle"
    ],
    "wof:name":"Jumping Jax",
    "wof:placetype":"venue"
},
  "geometry": {"coordinates":[-4.602446,55.446278],"type":"Point"}
}