{
  "type": "Feature",
  "properties": {
    "addr:full":"76 Brynhyfryd Street, Penydarren Merthyr Tydfil Merthyr Tydfil CF47 9YW",
    "addr:housenumber":"76",
    "addr:postcode":"cf47 9yw",
    "addr:street":"Brynhyfryd Street;Tydfil",
    "iso:country":"GB",
    "sg:address":"76 Brynhyfryd Street, Penydarren",
    "sg:city":"Merthyr Tydfil",
    "sg:classifiers":[
        {
            "category":"Retail",
            "subcategory":"Funeral Services",
            "type":"Services"
        }
    ],
    "sg:phone":"+44 1685 723533",
    "sg:postcode":"CF47 9YW",
    "sg:province":"Merthyr Tydfil",
    "sg:tags":[
        "director"
    ],
    "wof:name":"Price Caradoc",
    "wof:placetype":"venue"
},
  "geometry": {"coordinates":[-3.366656,51.759274],"type":"Point"}
}