{
  "type": "Feature",
  "properties": {
    "addr:full":"The Street, Shottisham Woodbridge Suffolk IP12 3ET",
    "addr:postcode":"ip12 3et",
    "addr:street":"The Street",
    "iso:country":"GB",
    "sg:address":"The Street, Shottisham",
    "sg:city":"Woodbridge",
    "sg:classifiers":[
        {
            "category":"Building & Trades",
            "subcategory":"Construction",
            "type":"Services"
        }
    ],
    "sg:phone":"+44 1394 411968",
    "sg:postcode":"IP12 3ET",
    "sg:province":"Suffolk",
    "sg:tags":[
        "builder",
        "contractor"
    ],
    "wof:name":"Beeton & Lennard Ltd",
    "wof:placetype":"venue"
},
  "geometry": {"coordinates":[1.4149659872,52.0241470337],"type":"Point"}
}