{
  "type": "Feature",
  "properties": {
    "iso:country":"GB",
    "sg:address":"The Cricket Club, Chatburn Road",
    "sg:city":"Clitheroe",
    "sg:classifiers":[
        {
            "category":"Education",
            "subcategory":"Preschool",
            "type":"Public Place"
        }
    ],
    "sg:postcode":"BB7 2AS",
    "sg:province":"Lancashire",
    "sg:tags":[
        "pre-school",
        "playgroups"
    ],
    "wof:name":"Pendle Pre-School",
    "wof:placetype":"venue"
},
  "geometry": {"coordinates":[-2.391749,53.87278],"type":"Point"}
}