{
  "type": "Feature",
  "properties": {
    "addr:full":"Longloch Farm Kirkcaldy Fife KY2 5UT",
    "addr:postcode":"ky2 5ut",
    "addr:street":"Kirkcaldy",
    "iso:country":"GB",
    "sg:address":"Longloch Farm",
    "sg:city":"Kirkcaldy",
    "sg:classifiers":[
        {
            "category":"Retail",
            "subcategory":"Auto Repair",
            "type":"Services"
        }
    ],
    "sg:postcode":"KY2 5UT",
    "sg:province":"Fife",
    "sg:tags":[
        "modification",
        "garage"
    ],
    "wof:name":"Engineering Workshop",
    "wof:placetype":"venue"
},
  "geometry": {"coordinates":[-3.2605791092,56.1027908325],"type":"Point"}
}