{
  "type": "Feature",
  "properties": {
    "addr:full":"34 Chantry Road, Moseley Birmingham West Midlands B13 8DJ",
    "addr:housenumber":"34",
    "addr:postcode":"b13 8dj",
    "addr:street":"Chantry Road",
    "iso:country":"GB",
    "sg:address":"34 Chantry Road, Moseley",
    "sg:city":"Birmingham",
    "sg:classifiers":[
        {
            "category":"Health Services",
            "subcategory":"Doctor",
            "type":"Services"
        }
    ],
    "sg:postcode":"B13 8DJ",
    "sg:province":"West Midlands",
    "sg:tags":[
        "surgeon"
    ],
    "wof:name":"J M Morrison",
    "wof:placetype":"venue"
},
  "geometry": {"coordinates":[-1.8917349577,52.4495239258],"type":"Point"}
}