{
  "type": "Feature",
  "properties": {
    "addr:full":"2 Station Street Lewes East Sussex BN7 2DA",
    "addr:housenumber":"2",
    "addr:postcode":"bn7 2da",
    "addr:street":"Station Street",
    "iso:country":"GB",
    "sg:address":"2 Station Street",
    "sg:city":"Lewes",
    "sg:classifiers":[
        {
            "category":"Banks & Credit Unions",
            "subcategory":"Financial Services",
            "type":"Services"
        }
    ],
    "sg:postcode":"BN7 2DA",
    "sg:province":"East Sussex",
    "sg:tags":[
        "adviser"
    ],
    "wof:name":"Castillion Consultancy Ltd.",
    "wof:placetype":"venue"
},
  "geometry": {"coordinates":[0.0107850004,50.8729476929],"type":"Point"}
}