{
  "type": "Feature",
  "properties": {
    "iso:country":"GB",
    "sg:address":"183 Cloberhill Road",
    "sg:city":"Glasgow",
    "sg:classifiers":[
        {
            "category":"Retail",
            "subcategory":"Driving School",
            "type":"Services"
        }
    ],
    "sg:phone":"+44 141 954 2377",
    "sg:postcode":"G13 2DD",
    "sg:province":"Glasgow City",
    "wof:name":"West End Driving School",
    "wof:placetype":"venue"
},
  "geometry": {"coordinates":[-4.34866,55.90292],"type":"Point"}
}