{
  "type": "Feature",
  "properties": {
    "iso:country":"GB",
    "sg:address":"8 Eastleaze Rd, Eastleaze",
    "sg:city":"Swindon",
    "sg:classifiers":[
        {
            "category":"Arts & Performance",
            "subcategory":"Music",
            "type":"Entertainment"
        }
    ],
    "sg:phone":"+44 1793 870278",
    "sg:postcode":"SN5 7EB",
    "sg:province":"Wiltshire",
    "sg:tags":[
        "mobile",
        "disco"
    ],
    "wof:name":"Moonshine",
    "wof:placetype":"venue"
},
  "geometry": {"coordinates":[-1.826695,51.563389],"type":"Point"}
}