{
  "type": "Feature",
  "properties": {
    "addr:full":"3 Ramsgate Rd Lytham St Annes Lancashire FY8 3HH",
    "addr:housenumber":"3",
    "addr:postcode":"fy8 3hh",
    "addr:street":"Ramsgate Rd;St",
    "iso:country":"GB",
    "sg:address":"3 Ramsgate Rd",
    "sg:city":"Lytham St Annes",
    "sg:classifiers":[
        {
            "category":"Home & Garden",
            "subcategory":"Home Furnishings",
            "type":"Retail Goods"
        }
    ],
    "sg:phone":"+44 1253 728045",
    "sg:postcode":"FY8 3HH",
    "sg:province":"Lancashire",
    "sg:tags":[
        "furnishers",
        "planner",
        "kitchen"
    ],
    "wof:name":"Distinctive Kitchens",
    "wof:placetype":"venue"
},
  "geometry": {"coordinates":[-3.019488,53.759148],"type":"Point"}
}