{
  "type": "Feature",
  "properties": {
    "iso:country":"GB",
    "sg:address":"23 Sidehill Dr",
    "sg:city":"Brighton",
    "sg:classifiers":[
        {
            "category":"Manufacturing",
            "subcategory":"Petroleum Products",
            "type":"Manufacturing & Wholesale Goods"
        }
    ],
    "sg:phone":"+44 1273 422307",
    "sg:postcode":"BN41 2QA",
    "sg:province":"East Sussex",
    "sg:tags":[
        "double",
        "glazing"
    ],
    "wof:name":"The Fascia & Gutter Co",
    "wof:placetype":"venue"
},
  "geometry": {"coordinates":[-0.227887,50.8456],"type":"Point"}
}