{
  "type": "Feature",
  "properties": {
    "iso:country":"GB",
    "sg:address":"21 Manor Grove",
    "sg:city":"Peckham",
    "sg:classifiers":[
        {
            "category":"Professional",
            "subcategory":"Business Services",
            "type":"Services"
        }
    ],
    "sg:phone":"+44 20 7732 3105",
    "sg:postcode":"SE15 1EG",
    "sg:province":"Greater London",
    "sg:tags":[
        "import",
        "export",
        "agent"
    ],
    "wof:name":"Finbro Ltd",
    "wof:placetype":"venue"
},
  "geometry": {"coordinates":[-0.0543580018,51.4818191528],"type":"Point"}
}