{
  "type": "Feature",
  "properties": {
    "addr:full":"125 Mary Street Scunthorpe Lincolnshire DN15 6LA",
    "addr:housenumber":"125",
    "addr:postcode":"dn15 6la",
    "addr:street":"Mary Street",
    "iso:country":"GB",
    "sg:address":"125 Mary Street",
    "sg:city":"Scunthorpe",
    "sg:classifiers":[
        {
            "category":"Shopping",
            "subcategory":"Clothing, Apparel, & Fashions",
            "type":"Retail Goods"
        }
    ],
    "sg:phone":"+44 1724 866724",
    "sg:postcode":"DN15 6LA",
    "sg:province":"Lincolnshire",
    "sg:tags":[
        "lingerie",
        "hosiery"
    ],
    "wof:name":"G M Othen",
    "wof:placetype":"venue"
},
  "geometry": {"coordinates":[-0.6537700295,53.5898284912],"type":"Point"}
}