{
  "type": "Feature",
  "properties": {
    "addr:full":"8 Allcock Street, Bordesley Birmingham West Midlands B9 4DY",
    "addr:housenumber":"8",
    "addr:postcode":"b9 4dy",
    "addr:street":"Allcock Street",
    "iso:country":"GB",
    "sg:address":"8 Allcock Street, Bordesley",
    "sg:city":"Birmingham",
    "sg:classifiers":[
        {
            "category":"Shopping",
            "subcategory":"Clothing, Apparel, & Fashions",
            "type":"Retail Goods"
        }
    ],
    "sg:phone":"+44 121 753 3487",
    "sg:postcode":"B9 4DY",
    "sg:province":"West Midlands",
    "sg:tags":[
        "sportswear"
    ],
    "wof:name":"Cambridge Collection",
    "wof:placetype":"venue"
},
  "geometry": {"coordinates":[-1.8819259405,52.4763908386],"type":"Point"}
}