{
  "type": "Feature",
  "properties": {
    "addr:full":"2 Cardwell Street, Northwood Stoke-on-trent Staffordshire ST1 6PN",
    "addr:housenumber":"2",
    "addr:postcode":"staffordshire st1 6pn",
    "addr:street":"Cardwell Street",
    "iso:country":"GB",
    "sg:address":"2 Cardwell Street, Northwood",
    "sg:city":"Stoke-on-trent",
    "sg:classifiers":[
        {
            "category":"Building & Trades",
            "subcategory":"Plumbing",
            "type":"Services"
        }
    ],
    "sg:phone":"+44 1782 219223",
    "sg:postcode":"ST1 6PN",
    "sg:province":"Staffordshire",
    "sg:tags":[
        "heating"
    ],
    "wof:name":"J W Egginton",
    "wof:placetype":"venue"
},
  "geometry": {"coordinates":[-2.1638460159,53.0298690796],"type":"Point"}
}