{
  "type": "Feature",
  "properties": {
    "iso:country":"GB",
    "sg:address":"Caprican Ho, Shotley Field",
    "sg:city":"Consett",
    "sg:classifiers":[
        {
            "category":"Manufacturing",
            "subcategory":"Metals",
            "type":"Manufacturing & Wholesale Goods"
        }
    ],
    "sg:phone":"+44 1207 255664",
    "sg:postcode":"DH8 9LF",
    "sg:province":"Durham",
    "sg:tags":[
        "steel",
        "fabricator",
        "erectors"
    ],
    "wof:name":"B Rogan",
    "wof:placetype":"venue"
},
  "geometry": {"coordinates":[-1.835914,54.860989],"type":"Point"}
}