{
  "type": "Feature",
  "properties": {
    "addr:full":"15 Kirk Wynd Kirkcaldy Fife KY1 1EH",
    "addr:housenumber":"15",
    "addr:postcode":"ky1 1eh",
    "addr:street":"Kirk Wynd",
    "iso:country":"GB",
    "sg:address":"15 Kirk Wynd",
    "sg:city":"Kirkcaldy",
    "sg:classifiers":[
        {
            "category":"Personal",
            "subcategory":"Beauty Salon",
            "type":"Services"
        }
    ],
    "sg:phone":"+44 1592 205467",
    "sg:postcode":"KY1 1EH",
    "sg:province":"Fife",
    "sg:tags":[
        "unisex",
        "hairdresser"
    ],
    "wof:name":"L J M",
    "wof:placetype":"venue"
},
  "geometry": {"coordinates":[-3.1581089497,56.1118087769],"type":"Point"}
}