{
  "type": "Feature",
  "properties": {
    "iso:country":"GB",
    "sg:address":"Ashdale House, Wootton Road",
    "sg:city":"Ulceby",
    "sg:classifiers":[
        {
            "category":"Farming",
            "subcategory":"Farm",
            "type":"Manufacturing & Wholesale Goods"
        }
    ],
    "sg:phone":"+44 1469 588224",
    "sg:postcode":"DN39 6XT",
    "sg:province":"Lincolnshire",
    "sg:tags":[
        "mixed",
        "crop"
    ],
    "wof:name":"H A Mollett Ltd.",
    "wof:placetype":"venue"
},
  "geometry": {"coordinates":[-0.3413029909,53.6231422424],"type":"Point"}
}