{
  "type": "Feature",
  "properties": {
    "addr:full":"Graham Road, Newtown Southampton Hampshire SO14 0AW",
    "addr:postcode":"so14 0aw",
    "addr:street":"Graham Road",
    "iso:country":"GB",
    "sg:address":"Graham Road, Newtown",
    "sg:city":"Southampton",
    "sg:classifiers":[
        {
            "category":"Community Center",
            "subcategory":"Youth",
            "type":"Public Place"
        }
    ],
    "sg:phone":"+44 23 8033 0007",
    "sg:postcode":"SO14 0AW",
    "sg:province":"Hampshire",
    "sg:tags":[
        "organisation",
        "centre"
    ],
    "wof:name":"Newtown Youth Centre",
    "wof:placetype":"venue"
},
  "geometry": {"coordinates":[-1.396134,50.911655],"type":"Point"}
}