{
  "type": "Feature",
  "properties": {
    "addr:full":"3 Oakmede Place, Binfield Bracknell Berkshire RG42 4JF",
    "addr:housenumber":"3",
    "addr:postcode":"rg42 4jf",
    "addr:street":"Oakmede Place",
    "iso:country":"GB",
    "sg:address":"3 Oakmede Place, Binfield",
    "sg:city":"Bracknell",
    "sg:classifiers":[
        {
            "category":"Food & Beverages",
            "subcategory":"Bakery",
            "type":"Retail Goods"
        }
    ],
    "sg:phone":"+44 1344 485769",
    "sg:postcode":"RG42 4JF",
    "sg:province":"Berkshire",
    "sg:tags":[
        "shop",
        "baker"
    ],
    "wof:name":"Oakmede Bakery",
    "wof:placetype":"venue"
},
  "geometry": {"coordinates":[-0.78916,51.431522],"type":"Point"}
}