{
  "type": "Feature",
  "properties": {
    "addr:full":"4-5 The Arcade, The Broadway Wickford Essex SS11 7AH",
    "addr:housenumber":"4-5",
    "addr:postcode":"ss11 7ah",
    "addr:street":"The Arcade The Broadway",
    "iso:country":"GB",
    "sg:address":"4-5 The Arcade, The Broadway",
    "sg:city":"Wickford",
    "sg:classifiers":[
        {
            "category":"Professional",
            "subcategory":"Art Services",
            "type":"Services"
        }
    ],
    "sg:phone":"+44 1268 572689",
    "sg:postcode":"SS11 7AH",
    "sg:province":"Essex",
    "sg:tags":[
        "framing"
    ],
    "wof:name":"Mirror Image",
    "wof:placetype":"venue"
},
  "geometry": {"coordinates":[0.52188,51.61401],"type":"Point"}
}