{
  "type": "Feature",
  "properties": {
    "addr:full":"80 Appin Rd Birkenhead Merseyside L41 9HH",
    "addr:housenumber":"80",
    "addr:postcode":"l41 9hh",
    "addr:street":"Appin Rd",
    "iso:country":"GB",
    "sg:address":"80 Appin Rd",
    "sg:city":"Birkenhead",
    "sg:classifiers":[
        {
            "category":"Wholesale",
            "subcategory":"Construction Materials",
            "type":"Manufacturing & Wholesale Goods"
        }
    ],
    "sg:phone":"+44 151 666 2385",
    "sg:postcode":"L41 9HH",
    "sg:province":"Merseyside",
    "sg:tags":[
        "merchant",
        "glass"
    ],
    "wof:name":"Holborn Glass Ltd",
    "wof:placetype":"venue"
},
  "geometry": {"coordinates":[-3.0254900455,53.3925590515],"type":"Point"}
}