{
  "type": "Feature",
  "properties": {
    "addr:full":"97 Stonald Road, Whittlesey Peterborough Cambridgeshire PE7 1QP",
    "addr:housenumber":"97",
    "addr:postcode":"pe7 1qp",
    "addr:street":"Stonald Road",
    "iso:country":"GB",
    "sg:address":"97 Stonald Road, Whittlesey",
    "sg:city":"Peterborough",
    "sg:classifiers":[
        {
            "category":"Organizations",
            "subcategory":"Membership Organization",
            "type":"Services"
        }
    ],
    "sg:postcode":"PE7 1QP",
    "sg:province":"Cambridgeshire",
    "sg:tags":[
        "club"
    ],
    "wof:name":"The Square Management Company Limited",
    "wof:placetype":"venue"
},
  "geometry": {"coordinates":[-0.137021,52.561867],"type":"Point"}
}