{
  "type": "Feature",
  "properties": {
    "addr:full":"145 Balby Road Doncaster South Yorkshire DN4 0RG",
    "addr:housenumber":"145",
    "addr:postcode":"dn4 0rg",
    "addr:street":"Balby Road",
    "iso:country":"GB",
    "sg:address":"145 Balby Road",
    "sg:city":"Doncaster",
    "sg:classifiers":[
        {
            "category":"Fast Food",
            "type":"Food & Drink"
        }
    ],
    "sg:phone":"+44 1302 854255",
    "sg:postcode":"DN4 0RG",
    "sg:province":"South Yorkshire",
    "sg:tags":[
        "away",
        "meal",
        "outlet",
        "take"
    ],
    "wof:name":"Wonderful Two",
    "wof:placetype":"venue"
},
  "geometry": {"coordinates":[-1.146244,53.50919],"type":"Point"}
}