{
  "type": "Feature",
  "properties": {
    "addr:full":"2 Old Brompton Road London Greater London SW7 3DQ",
    "addr:housenumber":"2",
    "addr:postcode":"sw7 3dq",
    "addr:street":"Old Brompton Road",
    "iso:country":"GB",
    "sg:address":"2 Old Brompton Road",
    "sg:city":"London",
    "sg:classifiers":[
        {
            "category":"Shopping",
            "subcategory":"Clothing, Apparel, & Fashions",
            "type":"Retail Goods"
        }
    ],
    "sg:phone":"+44 20 7821 8250",
    "sg:postcode":"SW7 3DQ",
    "sg:province":"Greater London",
    "sg:tags":[
        "mnfr",
        "staff",
        "wear",
        "uniform"
    ],
    "wof:name":"Delabond Design Studios",
    "wof:placetype":"venue"
},
  "geometry": {"coordinates":[-0.174461,51.49387],"type":"Point"}
}