{
  "type": "Feature",
  "properties": {
    "addr:full":"43 Tamworth Drive Fleet Hampshire GU51 2UP",
    "addr:housenumber":"43",
    "addr:postcode":"gu51 2up",
    "addr:street":"Tamworth Drive",
    "iso:country":"GB",
    "sg:address":"43 Tamworth Drive",
    "sg:city":"Fleet",
    "sg:classifiers":[
        {
            "category":"Professional",
            "subcategory":"Management & Consulting",
            "type":"Services"
        }
    ],
    "sg:postcode":"GU51 2UP",
    "sg:province":"Hampshire",
    "sg:tags":[
        "consultant",
        "business"
    ],
    "wof:name":"Nad Consulting Ltd.",
    "wof:placetype":"venue"
},
  "geometry": {"coordinates":[-0.829952,51.294353],"type":"Point"}
}