{
  "type": "Feature",
  "properties": {
    "addr:full":"The Old Dairy, 3-5 Church Street Littlehampton West Sussex BN17 5EL",
    "addr:housenumber":"3-5",
    "addr:postcode":"bn17 5el",
    "addr:street":"Church Street",
    "iso:country":"GB",
    "sg:address":"The Old Dairy, 3-5 Church Street",
    "sg:city":"Littlehampton",
    "sg:classifiers":[
        {
            "category":"Professional",
            "subcategory":"Business Services",
            "type":"Services"
        },
        {
            "category":"Organizations",
            "subcategory":"Non-profit Organization",
            "type":"Services"
        }
    ],
    "sg:phone":"+44 1903 723584",
    "sg:postcode":"BN17 5EL",
    "sg:province":"West Sussex",
    "sg:tags":[
        "voluntary",
        "organisation",
        "agent",
        "export",
        "import",
        "charity"
    ],
    "wof:name":"Arun Council Voluntary Service",
    "wof:placetype":"venue"
},
  "geometry": {"coordinates":[-0.5389590263,50.8210296631],"type":"Point"}
}