{
  "type": "Feature",
  "properties": {
    "iso:country":"GB",
    "sg:address":"25 Upper Brook Str Street, Mayfair",
    "sg:city":"London",
    "sg:classifiers":[
        {
            "category":"Professional",
            "subcategory":"Management & Consulting",
            "type":"Services"
        }
    ],
    "sg:phone":"+44 20 7499 7710",
    "sg:postcode":"W1K 7QD",
    "sg:province":"Greater London",
    "sg:tags":[
        "consultant",
        "business"
    ],
    "wof:name":"Ghadeco (U K) Ltd.",
    "wof:placetype":"venue"
},
  "geometry": {"coordinates":[-0.1568460017,51.5111961365],"type":"Point"}
}