{
  "type": "Feature",
  "properties": {
    "addr:full":"St. Saviourgate York North Yorkshire YO1 8NQ",
    "addr:postcode":"yo1 8nq",
    "addr:street":"St. Saviourgate",
    "iso:country":"GB",
    "sg:address":"St. Saviourgate",
    "sg:city":"York",
    "sg:classifiers":[
        {
            "category":"Place Of Worship",
            "type":"Public Place"
        }
    ],
    "sg:phone":"+44 1904 612171",
    "sg:postcode":"YO1 8NQ",
    "sg:province":"North Yorkshire",
    "wof:name":"Central Methodist Church",
    "wof:placetype":"venue"
},
  "geometry": {"coordinates":[-1.0776599646,53.9599876404],"type":"Point"}
}