{
  "type": "Feature",
  "properties": {
    "iso:country":"GB",
    "sg:address":"7 Belmont Cres",
    "sg:city":"Buckley",
    "sg:classifiers":[
        {
            "category":"Wholesale",
            "subcategory":"Scrap",
            "type":"Manufacturing & Wholesale Goods"
        }
    ],
    "sg:phone":"+44 1244 549706",
    "sg:postcode":"CH7 3NE",
    "sg:province":"Denbighshire",
    "sg:tags":[
        "waste",
        "metal"
    ],
    "wof:name":"T C Metals",
    "wof:placetype":"venue"
},
  "geometry": {"coordinates":[-3.078671,53.17424],"type":"Point"}
}