{
  "type": "Feature",
  "properties": {
    "addr:full":"241 Wood Street London Greater London E17 3NT",
    "addr:housenumber":"241",
    "addr:postcode":"e17 3nt",
    "addr:street":"Wood Street",
    "iso:country":"GB",
    "sg:address":"241 Wood Street",
    "sg:city":"London",
    "sg:classifiers":[
        {
            "category":"Shopping",
            "subcategory":"Department Store",
            "type":"Retail Goods"
        }
    ],
    "sg:phone":"+44 20 8520 1570",
    "sg:postcode":"E17 3NT",
    "sg:province":"Greater London",
    "wof:name":"Hassans Food Store",
    "wof:placetype":"venue"
},
  "geometry": {"coordinates":[-0.000918,51.584587],"type":"Point"}
}