{
  "type": "Feature",
  "properties": {
    "addr:full":"243 Henley Road Ipswich Suffolk IP1 6RL",
    "addr:housenumber":"243",
    "addr:postcode":"ip1 6rl",
    "addr:street":"Henley Road",
    "iso:country":"GB",
    "sg:address":"243 Henley Road",
    "sg:city":"Ipswich",
    "sg:classifiers":[
        {
            "category":"Building & Trades",
            "subcategory":"Cleaning & Sanitation",
            "type":"Services"
        },
        {
            "category":"Retail",
            "subcategory":"Laundry & Dry Cleaning",
            "type":"Services"
        }
    ],
    "sg:phone":"+44 1473 259138",
    "sg:postcode":"IP1 6RL",
    "sg:province":"Suffolk",
    "sg:tags":[
        "contracting",
        "commercial",
        "alteration"
    ],
    "wof:name":"Civic Cleaning Services",
    "wof:placetype":"venue"
},
  "geometry": {"coordinates":[1.1493849754,52.0813484192],"type":"Point"}
}