{
  "type": "Feature",
  "properties": {
    "addr:full":"5 Jubilee Close Ventnor Isle of Wight PO38 3HD",
    "addr:housenumber":"5",
    "addr:postcode":"po38 3hd",
    "addr:street":"Jubilee Close",
    "iso:country":"GB",
    "sg:address":"5 Jubilee Close",
    "sg:city":"Ventnor",
    "sg:classifiers":[
        {
            "category":"Building & Trades",
            "subcategory":"Plumbing",
            "type":"Services"
        }
    ],
    "sg:phone":"+44 1983 840451",
    "sg:postcode":"PO38 3HD",
    "sg:province":"Isle of Wight",
    "sg:tags":[
        "central",
        "heating"
    ],
    "wof:name":"A R Neale",
    "wof:placetype":"venue"
},
  "geometry": {"coordinates":[-1.2598730326,50.6348876953],"type":"Point"}
}