{
  "type": "Feature",
  "properties": {
    "addr:full":"The Register Office Block, County Hall Hertford Hertfordshire SG13 8EJ",
    "addr:housenumber":"block",
    "addr:postcode":"sg13 8ej",
    "addr:street":"Hertford",
    "iso:country":"GB",
    "sg:address":"The Register Office Block, County Hall",
    "sg:city":"Hertford",
    "sg:classifiers":[
        {
            "category":"Education",
            "subcategory":"Library",
            "type":"Public Place"
        },
        {
            "category":"Government",
            "subcategory":"Office",
            "type":"Public Place"
        }
    ],
    "sg:postcode":"SG13 8EJ",
    "sg:province":"Hertfordshire",
    "sg:tags":[
        "book",
        "local"
    ],
    "wof:name":"Hertfordshire County Council",
    "wof:placetype":"venue"
},
  "geometry": {"coordinates":[-0.08036,51.79155],"type":"Point"}
}