{
  "type": "Feature",
  "properties": {
    "iso:country":"GB",
    "sg:address":"Stone Bridge House, 28-32 Bridge Street",
    "sg:city":"Leatherhead",
    "sg:classifiers":[
        {
            "category":"Professional",
            "subcategory":"Art Services",
            "type":"Services"
        }
    ],
    "sg:phone":"+44 1372 360477",
    "sg:postcode":"KT22 8BZ",
    "sg:province":"Surrey",
    "sg:tags":[
        "graphic",
        "designer"
    ],
    "wof:name":"Nigel Smith Design Associates Ltd.",
    "wof:placetype":"venue"
},
  "geometry": {"coordinates":[-0.331601,51.294704],"type":"Point"}
}