{
  "type": "Feature",
  "properties": {
    "addr:full":"20 Station Road Wymondham Norfolk NR18 0JX",
    "addr:housenumber":"20",
    "addr:postcode":"nr18 0jx",
    "addr:street":"Station Road",
    "iso:country":"GB",
    "sg:address":"20 Station Road",
    "sg:city":"Wymondham",
    "sg:classifiers":[
        {
            "category":"Professional",
            "subcategory":"Accounting & Tax Preparation",
            "type":"Services"
        }
    ],
    "sg:phone":"+44 1953 603471",
    "sg:postcode":"NR18 0JX",
    "sg:province":"Norfolk",
    "sg:tags":[
        "accountant"
    ],
    "wof:name":"T B Reeve Book-Keeping",
    "wof:placetype":"venue"
},
  "geometry": {"coordinates":[1.117585,52.567066],"type":"Point"}
}