{
  "type": "Feature",
  "properties": {
    "addr:full":"4 Endless St Salisbury Wiltshire SP1 1DL",
    "addr:housenumber":"4",
    "addr:postcode":"sp1 1dl",
    "addr:street":"Endless St",
    "iso:country":"GB",
    "sg:address":"4 Endless St",
    "sg:city":"Salisbury",
    "sg:classifiers":[
        {
            "category":"Bars & Pubs",
            "subcategory":"Nightclub",
            "type":"Food & Drink"
        }
    ],
    "sg:phone":"+44 1722 337415",
    "sg:postcode":"SP1 1DL",
    "sg:province":"Wiltshire",
    "sg:tags":[
        "club",
        "night"
    ],
    "wof:name":"Rhythmicon",
    "wof:placetype":"venue"
},
  "geometry": {"coordinates":[-1.794145,51.069817],"type":"Point"}
}