{
  "type": "Feature",
  "properties": {
    "addr:full":"10 Upper Berkley Street London Greater London W1H 7PE",
    "addr:housenumber":"10",
    "addr:postcode":"w1h 7pe",
    "addr:street":"Upper Berkley Street",
    "iso:country":"GB",
    "sg:address":"10 Upper Berkley Street",
    "sg:city":"London",
    "sg:classifiers":[
        {
            "category":"Real Estate",
            "subcategory":"Developer",
            "type":"Services"
        }
    ],
    "sg:phone":"+44 20 7402 0402",
    "sg:postcode":"W1H 7PE",
    "sg:province":"Greater London",
    "sg:tags":[
        "property"
    ],
    "wof:name":"Johnson Collins Ltd.",
    "wof:placetype":"venue"
},
  "geometry": {"coordinates":[-0.1600099951,51.5155601501],"type":"Point"}
}