{
  "type": "Feature",
  "properties": {
    "addr:full":"93-107 Belmont Ct, Highbury New Pk London Greater London N5 2HA",
    "addr:housenumber":"93-107",
    "addr:postcode":"n5 2ha",
    "addr:street":"Belmont Ct;New",
    "iso:country":"GB",
    "sg:address":"93-107 Belmont Ct, Highbury New Pk",
    "sg:city":"London",
    "sg:classifiers":[
        {
            "category":"Professional",
            "subcategory":"Secretarial Services",
            "type":"Services"
        }
    ],
    "sg:phone":"+44 20 7359 5800",
    "sg:postcode":"N5 2HA",
    "sg:province":"Greater London",
    "wof:name":"Highbury Secretarial Services Ltd",
    "wof:placetype":"venue"
},
  "geometry": {"coordinates":[-0.09222,51.55402],"type":"Point"}
}