{
  "type": "Feature",
  "properties": {
    "addr:full":"2-4 Fitzalan Road Horsham West Sussex RH13 6AA",
    "addr:housenumber":"2-4",
    "addr:postcode":"rh13 6aa",
    "addr:street":"Fitzalan Road",
    "iso:country":"GB",
    "sg:address":"2-4 Fitzalan Road",
    "sg:city":"Horsham",
    "sg:classifiers":[
        {
            "category":"Food & Beverages",
            "subcategory":"Groceries & Convenience Stores",
            "type":"Retail Goods"
        }
    ],
    "sg:phone":"+44 1403 261551",
    "sg:postcode":"RH13 6AA",
    "sg:province":"West Sussex",
    "wof:name":"Alldays",
    "wof:placetype":"venue"
},
  "geometry": {"coordinates":[-0.3018760085,51.0729293823],"type":"Point"}
}