{
  "type": "Feature",
  "properties": {
    "iso:country":"GB",
    "sg:address":"5 Millford Way, Bowburn",
    "sg:city":"Durham",
    "sg:classifiers":[
        {
            "category":"Home & Garden",
            "subcategory":"Building Materials",
            "type":"Retail Goods"
        }
    ],
    "sg:postcode":"DH6 5DE",
    "sg:province":"Durham",
    "sg:tags":[
        "shower",
        "unit"
    ],
    "wof:name":"Nuflow Showers",
    "wof:placetype":"venue"
},
  "geometry": {"coordinates":[-1.5166620016,54.7408676147],"type":"Point"}
}