{
  "type": "Feature",
  "properties": {
    "iso:country":"GB",
    "sg:address":"1 Calow Lane, Hasland",
    "sg:city":"Chesterfield",
    "sg:classifiers":[
        {
            "category":"Wholesale",
            "subcategory":"Electrical",
            "type":"Manufacturing & Wholesale Goods"
        }
    ],
    "sg:phone":"+44 1246 272281",
    "sg:postcode":"S41 0AL",
    "sg:province":"Derbyshire",
    "sg:tags":[
        "equipment",
        "refrigeration"
    ],
    "wof:name":"W R Refrigeration Ltd.",
    "wof:placetype":"venue"
},
  "geometry": {"coordinates":[-1.406254,53.220459],"type":"Point"}
}