{
  "type": "Feature",
  "properties": {
    "iso:country":"GB",
    "sg:address":"19 Regent Terrace",
    "sg:city":"Gateshead",
    "sg:classifiers":[
        {
            "category":"Professional",
            "subcategory":"Lawyer & Legal Services",
            "type":"Services"
        }
    ],
    "sg:phone":"+44 191 477 2288",
    "sg:postcode":"NE8 1LU",
    "sg:province":"Tyne and Wear",
    "sg:tags":[
        "solicitor"
    ],
    "wof:name":"Edward Hathaway & Co.",
    "wof:placetype":"venue"
},
  "geometry": {"coordinates":[-1.603579998,54.9607887268],"type":"Point"}
}