{
  "type": "Feature",
  "properties": {
    "iso:country":"GB",
    "sg:address":"119 Devonshire Street",
    "sg:city":"Sheffield",
    "sg:classifiers":[
        {
            "category":"Restaurant",
            "type":"Food & Drink"
        }
    ],
    "sg:phone":"+44 114 279 9394",
    "sg:postcode":"S3 7SB",
    "sg:province":"South Yorkshire",
    "sg:tags":[
        "italian"
    ],
    "wof:name":"Bb's",
    "wof:placetype":"venue"
},
  "geometry": {"coordinates":[-1.477122,53.379337],"type":"Point"}
}