{
  "type": "Feature",
  "properties": {
    "addr:full":"256 Bolton Rd Bolton Lancashire BL5 3EF",
    "addr:housenumber":"256",
    "addr:postcode":"bl5 3ef",
    "addr:street":"Bolton Rd",
    "iso:country":"GB",
    "sg:address":"256 Bolton Rd",
    "sg:city":"Bolton",
    "sg:classifiers":[
        {
            "category":"Autos & Motor Vehicles",
            "subcategory":"Automobile Sales",
            "type":"Retail Goods"
        }
    ],
    "sg:phone":"+44 1942 818991",
    "sg:postcode":"BL5 3EF",
    "sg:province":"Lancashire",
    "sg:tags":[
        "car"
    ],
    "wof:name":"Hunt A.T Car Sales",
    "wof:placetype":"venue"
},
  "geometry": {"coordinates":[-2.510378,53.554676],"type":"Point"}
}