{
  "type": "Feature",
  "properties": {
    "addr:full":"14-16 Haden Street, Balsall Heath Birmingham West Midlands B12 9BH",
    "addr:housenumber":"14-16",
    "addr:postcode":"b12 9bh",
    "addr:street":"Haden Street",
    "iso:country":"GB",
    "sg:address":"14-16 Haden Street, Balsall Heath",
    "sg:city":"Birmingham",
    "sg:classifiers":[
        {
            "category":"Professional",
            "subcategory":"Engineering",
            "type":"Services"
        }
    ],
    "sg:phone":"+44 121 440 0901",
    "sg:postcode":"B12 9BH",
    "sg:province":"West Midlands",
    "sg:tags":[
        "engineer"
    ],
    "wof:name":"Warwick Brassfounders & Engineering Co Ltd",
    "wof:placetype":"venue"
},
  "geometry": {"coordinates":[-1.8859469891,52.4607505798],"type":"Point"}
}