{
  "type": "Feature",
  "properties": {
    "addr:full":"48 Almondview Perth Perth and Kinross PH1 1QQ",
    "addr:housenumber":"48",
    "addr:postcode":"ph1 1qq",
    "addr:street":"Almondview Perth",
    "iso:country":"GB",
    "sg:address":"48 Almondview",
    "sg:city":"Perth",
    "sg:classifiers":[
        {
            "category":"Banks & Credit Unions",
            "subcategory":"Financial Services",
            "type":"Services"
        }
    ],
    "sg:phone":"+44 1738 444166",
    "sg:postcode":"PH1 1QQ",
    "sg:province":"Perth and Kinross",
    "sg:tags":[
        "consultant"
    ],
    "wof:name":"William Monks",
    "wof:placetype":"venue"
},
  "geometry": {"coordinates":[-3.4838581085,56.3961105347],"type":"Point"}
}