{
  "type": "Feature",
  "properties": {
    "addr:full":"Otley Rd Harrogate North Yorkshire HG3 2DF",
    "addr:postcode":"hg3 2df",
    "addr:street":"Otley Rd",
    "iso:country":"GB",
    "sg:address":"Otley Rd",
    "sg:city":"Harrogate",
    "sg:classifiers":[
        {
            "category":"Place Of Worship",
            "type":"Public Place"
        }
    ],
    "sg:phone":"+44 1423 770337",
    "sg:postcode":"HG3 2DF",
    "sg:province":"North Yorkshire",
    "wof:name":"St Thomas The Apostlle C Of E Church",
    "wof:placetype":"venue"
},
  "geometry": {"coordinates":[-1.564874053,54.0233383179],"type":"Point"}
}