{
  "type": "Feature",
  "properties": {
    "iso:country":"GB",
    "sg:address":"104 Field Lane, Pelsall",
    "sg:city":"Walsall",
    "sg:classifiers":[
        {
            "category":"Professional",
            "subcategory":"Engineering",
            "type":"Services"
        }
    ],
    "sg:postcode":"WS4 1DN",
    "sg:province":"West Midlands",
    "sg:tags":[
        "contractor",
        "electrical",
        "engineer"
    ],
    "wof:name":"N Richardson Electrical Contractors",
    "wof:placetype":"venue"
},
  "geometry": {"coordinates":[-1.95849,52.621017],"type":"Point"}
}