{
  "type": "Feature",
  "properties": {
    "addr:full":"50 Buckland Road Reading Berkshire RG2 7SW",
    "addr:housenumber":"50",
    "addr:postcode":"rg2 7sw",
    "addr:street":"Buckland Road",
    "iso:country":"GB",
    "sg:address":"50 Buckland Road",
    "sg:city":"Reading",
    "sg:classifiers":[
        {
            "category":"Shopping",
            "subcategory":"Pets & Pet Supplies",
            "type":"Retail Goods"
        }
    ],
    "sg:postcode":"RG2 7SW",
    "sg:province":"Berkshire",
    "wof:name":"Wild Side Exotics",
    "wof:placetype":"venue"
},
  "geometry": {"coordinates":[-0.9629489779,51.4337692261],"type":"Point"}
}