{
  "type": "Feature",
  "properties": {
    "addr:full":"Britannia House, 50 Great Charles Street Birmingham West Midlands B3 2LT",
    "addr:housenumber":"50",
    "addr:postcode":"b3 2lt",
    "addr:street":"Great Charles Street",
    "iso:country":"GB",
    "sg:address":"Britannia House, 50 Great Charles Street",
    "sg:city":"Birmingham",
    "sg:classifiers":[
        {
            "category":"Real Estate",
            "subcategory":"Developer",
            "type":"Services"
        }
    ],
    "sg:phone":"+44 870 787 0901",
    "sg:postcode":"B3 2LT",
    "sg:province":"West Midlands",
    "sg:tags":[
        "property"
    ],
    "wof:name":"Cannock Investments Ltd.",
    "wof:placetype":"venue"
},
  "geometry": {"coordinates":[-1.9021550417,52.4829978943],"type":"Point"}
}