{
  "type": "Feature",
  "properties": {
    "addr:full":"Ash Gro, Bamber Bridge Preston Lancashire PR5 6GY",
    "addr:postcode":"pr5 6gy",
    "addr:street":"Gro",
    "iso:country":"GB",
    "sg:address":"Ash Gro, Bamber Bridge",
    "sg:city":"Preston",
    "sg:classifiers":[
        {
            "category":"Education",
            "subcategory":"School",
            "type":"Public Place"
        },
        {
            "category":"Government",
            "subcategory":"Office",
            "type":"Public Place"
        }
    ],
    "sg:phone":"+44 1772 336342",
    "sg:postcode":"PR5 6GY",
    "sg:province":"Lancashire",
    "sg:tags":[
        "local",
        "authority"
    ],
    "wof:name":"Coppice School",
    "wof:placetype":"venue"
},
  "geometry": {"coordinates":[-2.6546800137,53.7325706482],"type":"Point"}
}