{
  "type": "Feature",
  "properties": {
    "addr:full":"5b Hartfield Road Forest Row East Sussex RH18 5DN",
    "addr:housenumber":"5b",
    "addr:postcode":"rh18 5dn",
    "addr:street":"Hartfield Road",
    "iso:country":"GB",
    "sg:address":"5b Hartfield Road",
    "sg:city":"Forest Row",
    "sg:classifiers":[
        {
            "category":"Communications",
            "subcategory":"News Services",
            "type":"Services"
        }
    ],
    "sg:phone":"+44 1342 826578",
    "sg:postcode":"RH18 5DN",
    "sg:province":"East Sussex",
    "sg:tags":[
        "journalist"
    ],
    "wof:name":"des Dearlove",
    "wof:placetype":"venue"
},
  "geometry": {"coordinates":[0.034136001,51.0976982117],"type":"Point"}
}