{
  "type": "Feature",
  "properties": {
    "iso:country":"GB",
    "sg:address":"Old Brewery House, Portersbridge Street",
    "sg:city":"Romsey",
    "sg:classifiers":[
        {
            "category":"Professional",
            "subcategory":"Engineering",
            "type":"Services"
        }
    ],
    "sg:phone":"+44 1794 524447",
    "sg:postcode":"SO51 8DJ",
    "sg:province":"Hampshire",
    "sg:tags":[
        "consultant",
        "structural"
    ],
    "wof:name":"Andrew Waring Associates",
    "wof:placetype":"venue"
},
  "geometry": {"coordinates":[-1.499043,50.990498],"type":"Point"}
}