{
  "type": "Feature",
  "properties": {
    "addr:full":"924 Neath Road, Morriston Swansea Swansea SA6 8ES",
    "addr:housenumber":"924",
    "addr:postcode":"sa6 8es",
    "addr:street":"Neath Road",
    "iso:country":"GB",
    "sg:address":"924 Neath Road, Morriston",
    "sg:city":"Swansea",
    "sg:classifiers":[
        {
            "category":"Bars & Pubs",
            "type":"Food & Drink"
        }
    ],
    "sg:postcode":"SA6 8ES",
    "sg:province":"Swansea",
    "sg:tags":[
        "pubs",
        "inn"
    ],
    "wof:name":"The Wychtree Inn",
    "wof:placetype":"venue"
},
  "geometry": {"coordinates":[-3.9235239029,51.6596107483],"type":"Point"}
}