{
  "type": "Feature",
  "properties": {
    "addr:full":"69 Seymour Road Newton Abbot Devon TQ12 2PX",
    "addr:housenumber":"69",
    "addr:postcode":"tq12 2px",
    "addr:street":"Seymour Road",
    "iso:country":"GB",
    "sg:address":"69 Seymour Road",
    "sg:city":"Newton Abbot",
    "sg:classifiers":[
        {
            "category":"Building & Trades",
            "subcategory":"Cleaning & Sanitation",
            "type":"Services"
        }
    ],
    "sg:postcode":"TQ12 2PX",
    "sg:province":"Devon",
    "sg:tags":[
        "commercial"
    ],
    "wof:name":"Square 1 Cleaning Services",
    "wof:placetype":"venue"
},
  "geometry": {"coordinates":[-3.6076478958,50.5339164734],"type":"Point"}
}