{
  "type": "Feature",
  "properties": {
    "iso:country":"GB",
    "sg:address":"The Craythorne, Craythorne Road",
    "sg:city":"Burton-on-trent",
    "sg:classifiers":[
        {
            "category":"Community Center",
            "type":"Public Place"
        }
    ],
    "sg:phone":"+44 1283 564329",
    "sg:postcode":"DE13 0AZ",
    "sg:province":"Derbyshire",
    "sg:tags":[
        "recreation",
        "leisure",
        "centre"
    ],
    "wof:name":"Peach Leisure Ltd.",
    "wof:placetype":"venue"
},
  "geometry": {"coordinates":[-1.635619,52.82793],"type":"Point"}
}