{
  "type": "Feature",
  "properties": {
    "addr:full":"47 Buckstone Terrace Edinburgh City of Edinburgh EH10 6QJ",
    "addr:housenumber":"47",
    "addr:postcode":"eh10 6qj",
    "addr:street":"Buckstone Terrace",
    "iso:country":"GB",
    "sg:address":"47 Buckstone Terrace",
    "sg:city":"Edinburgh",
    "sg:classifiers":[
        {
            "category":"Bars & Pubs",
            "subcategory":"Wine Bar",
            "type":"Food & Drink"
        },
        {
            "category":"Community Center",
            "subcategory":"Social",
            "type":"Public Place"
        }
    ],
    "sg:phone":"+44 131 445 5584",
    "sg:postcode":"EH10 6QJ",
    "sg:province":"City of Edinburgh",
    "sg:tags":[
        "house",
        "activity"
    ],
    "wof:name":"The Pavilion",
    "wof:placetype":"venue"
},
  "geometry": {"coordinates":[-3.2020089626,55.9094848633],"type":"Point"}
}