{
  "type": "Feature",
  "properties": {
    "addr:full":"2-2a Unit, Bricett Business Park, Great Bricett Ipswich Suffolk IP7 7DZ",
    "addr:housenumber":"2-2a unit bricett business",
    "addr:postcode":"ip7 7dz",
    "addr:street":"Park",
    "iso:country":"GB",
    "sg:address":"2-2a Unit, Bricett Business Park, Great Bricett",
    "sg:city":"Ipswich",
    "sg:classifiers":[
        {
            "category":"Shopping",
            "subcategory":"Clothing, Apparel, & Fashions",
            "type":"Retail Goods"
        }
    ],
    "sg:phone":"+44 1473 658000",
    "sg:postcode":"IP7 7DZ",
    "sg:province":"Suffolk",
    "sg:tags":[
        "workwear",
        "protective"
    ],
    "wof:name":"Puffa Ltd.",
    "wof:placetype":"venue"
},
  "geometry": {"coordinates":[0.9799950123,52.1152458191],"type":"Point"}
}