{
  "type": "Feature",
  "properties": {
    "iso:country":"GB",
    "sg:address":"9 Taymouth Street",
    "sg:city":"Carnoustie",
    "sg:classifiers":[
        {
            "category":"Arena",
            "subcategory":"Sports Club",
            "type":"Entertainment"
        }
    ],
    "sg:phone":"+44 1241 852425",
    "sg:postcode":"DD7 7HS",
    "sg:province":"Angus",
    "wof:name":"New Taymouth Golf Club",
    "wof:placetype":"venue"
},
  "geometry": {"coordinates":[-2.715619,56.499084],"type":"Point"}
}