{
  "type": "Feature",
  "properties": {
    "iso:country":"GB",
    "sg:address":"Godley Branch Raod, Godley",
    "sg:city":"Halifax",
    "sg:classifiers":[
        {
            "category":"Retail",
            "subcategory":"Auto Repair",
            "type":"Services"
        }
    ],
    "sg:phone":"+44 1422 364299",
    "sg:postcode":"HX3 6AH",
    "sg:province":"West Yorkshire",
    "sg:tags":[
        "body",
        "car",
        "repairer"
    ],
    "wof:name":"Bowers David Vehicle Body Repairs",
    "wof:placetype":"venue"
},
  "geometry": {"coordinates":[-1.84913,53.72543],"type":"Point"}
}