{
  "type": "Feature",
  "properties": {
    "addr:full":"5 Manor Parade, Sheepcote Road Harrow Greater London HA1 2JN",
    "addr:housenumber":"5",
    "addr:postcode":"ha1 2jn",
    "addr:street":"Manor Parade Sheepcote Road",
    "iso:country":"GB",
    "sg:address":"5 Manor Parade, Sheepcote Road",
    "sg:city":"Harrow",
    "sg:classifiers":[
        {
            "category":"Ice Cream",
            "type":"Food & Drink"
        }
    ],
    "sg:phone":"+44 20 8427 4479",
    "sg:postcode":"HA1 2JN",
    "sg:province":"Greater London",
    "sg:tags":[
        "shop",
        "mobile",
        "parlour"
    ],
    "wof:name":"Baskin Robbins",
    "wof:placetype":"venue"
},
  "geometry": {"coordinates":[-0.3267349899,51.5816421509],"type":"Point"}
}