{
  "type": "Feature",
  "properties": {
    "addr:full":"Berrows Business Centre, Bath Street Hereford Herefordshire HR1 2HE",
    "addr:postcode":"hr1 2he",
    "addr:street":"Bath Street",
    "iso:country":"GB",
    "sg:address":"Berrows Business Centre, Bath Street",
    "sg:city":"Hereford",
    "sg:classifiers":[
        {
            "category":"Home & Garden",
            "subcategory":"Carpets & Floor Coverings",
            "type":"Retail Goods"
        }
    ],
    "sg:postcode":"HR1 2HE",
    "sg:province":"Herefordshire",
    "sg:tags":[
        "carpets",
        "rug",
        "matting"
    ],
    "wof:name":"The Kings Mill",
    "wof:placetype":"venue"
},
  "geometry": {"coordinates":[-2.7110199928,52.0570411682],"type":"Point"}
}