{
  "type": "Feature",
  "properties": {
    "addr:full":"22 Warren Close, Edmonton London Greater London N9 8QE",
    "addr:housenumber":"22",
    "addr:postcode":"n9 8qe",
    "addr:street":"Warren Close",
    "iso:country":"GB",
    "sg:address":"22 Warren Close, Edmonton",
    "sg:city":"London",
    "sg:classifiers":[
        {
            "category":"Building & Trades",
            "subcategory":"Construction",
            "type":"Services"
        }
    ],
    "sg:phone":"+44 20 8805 3974",
    "sg:postcode":"N9 8QE",
    "sg:province":"Greater London",
    "sg:tags":[
        "builder"
    ],
    "wof:name":"Homebuild Construction Ltd.",
    "wof:placetype":"venue"
},
  "geometry": {"coordinates":[-0.0416099988,51.6331367493],"type":"Point"}
}