{
  "type": "Feature",
  "properties": {
    "iso:country":"GB",
    "sg:address":"22 Merchant St",
    "sg:city":"Bristol",
    "sg:classifiers":[
        {
            "category":"Shopping",
            "subcategory":"Hobbies, Toys, & Games",
            "type":"Retail Goods"
        }
    ],
    "sg:phone":"+44 117 927 6060",
    "sg:postcode":"BS1 3EP",
    "sg:province":"City of Bristol",
    "sg:tags":[
        "computer"
    ],
    "wof:name":"E Play",
    "wof:placetype":"venue"
},
  "geometry": {"coordinates":[-2.586429,51.456871],"type":"Point"}
}