{
  "type": "Feature",
  "properties": {
    "iso:country":"GB",
    "sg:address":"Snydale Gro",
    "sg:city":"Normanton",
    "sg:classifiers":[
        {
            "category":"Professional",
            "subcategory":"Engineering",
            "type":"Services"
        }
    ],
    "sg:phone":"+44 1924 894081",
    "sg:postcode":"WF6 1SU",
    "sg:province":"West Yorkshire",
    "sg:tags":[
        "gas",
        "engineer"
    ],
    "wof:name":"MJS Gas Services",
    "wof:placetype":"venue"
},
  "geometry": {"coordinates":[-1.412878,53.698082],"type":"Point"}
}