{
  "type": "Feature",
  "properties": {
    "iso:country":"GB",
    "sg:address":"Unit 16, Hoobrook Enterprise Centre, Worcester Road",
    "sg:city":"Kidderminster",
    "sg:classifiers":[
        {
            "category":"Retail",
            "subcategory":"Auto Repair",
            "type":"Services"
        }
    ],
    "sg:phone":"+44 1562 861651",
    "sg:postcode":"DY10 1HB",
    "sg:province":"Staffordshire",
    "sg:tags":[
        "modification",
        "garage"
    ],
    "wof:name":"Universal Transmission Services",
    "wof:placetype":"venue"
},
  "geometry": {"coordinates":[-2.2490839958,52.3881111145],"type":"Point"}
}