{
  "type": "Feature",
  "properties": {
    "addr:full":"3 Kimberly Close, Thorpe Audlin Pontefract North Yorkshire WF8 3ER",
    "addr:housenumber":"3",
    "addr:postcode":"wf8 3er",
    "addr:street":"Kimberly Close",
    "iso:country":"GB",
    "sg:address":"3 Kimberly Close, Thorpe Audlin",
    "sg:city":"Pontefract",
    "sg:classifiers":[
        {
            "category":"Retail",
            "subcategory":"Repair Shop",
            "type":"Services"
        },
        {
            "category":"Wholesale",
            "subcategory":"Machinery & Supplies",
            "type":"Manufacturing & Wholesale Goods"
        }
    ],
    "sg:phone":"+44 1977 620600",
    "sg:postcode":"WF8 3ER",
    "sg:province":"North Yorkshire",
    "sg:tags":[
        "agricultural",
        "sale"
    ],
    "sg:website":"http://www.rwilcock.co.uk",
    "wof:name":"R Wilcock & Co",
    "wof:placetype":"venue"
},
  "geometry": {"coordinates":[-1.282595,53.640263],"type":"Point"}
}