{
  "type": "Feature",
  "properties": {
    "addr:full":"394 Lee High Road London Greater London SE12 8RW",
    "addr:housenumber":"394",
    "addr:postcode":"se12 8rw",
    "addr:street":"Lee High Road",
    "iso:country":"GB",
    "sg:address":"394 Lee High Road",
    "sg:city":"London",
    "sg:classifiers":[
        {
            "category":"Bars & Pubs",
            "type":"Food & Drink"
        }
    ],
    "sg:phone":"+44 20 8297 9399",
    "sg:postcode":"SE12 8RW",
    "sg:province":"Greater London",
    "sg:tags":[
        "pubs",
        "inn"
    ],
    "wof:name":"Duke of Edinburgh",
    "wof:placetype":"venue"
},
  "geometry": {"coordinates":[0.009088,51.456863],"type":"Point"}
}