{
  "type": "Feature",
  "properties": {
    "iso:country":"GB",
    "sg:address":"4 Wood St",
    "sg:city":"Liverpool",
    "sg:classifiers":[
        {
            "category":"Retail",
            "subcategory":"Repair Shop",
            "type":"Services"
        }
    ],
    "sg:phone":"+44 151 427 6051",
    "sg:postcode":"L19 2LU",
    "sg:province":"Merseyside",
    "sg:tags":[
        "upholsterer"
    ],
    "wof:name":"Hodgsons Suites",
    "wof:placetype":"venue"
},
  "geometry": {"coordinates":[-2.898242,53.355064],"type":"Point"}
}