{
  "type": "Feature",
  "properties": {
    "addr:full":"465 Buxton Road Stockport Cheshire SK2 7HE",
    "addr:housenumber":"465",
    "addr:postcode":"sk2 7he",
    "addr:street":"Buxton Road",
    "iso:country":"GB",
    "sg:address":"465 Buxton Road",
    "sg:city":"Stockport",
    "sg:classifiers":[
        {
            "category":"Banks & Credit Unions",
            "subcategory":"Financial Services",
            "type":"Services"
        }
    ],
    "sg:postcode":"SK2 7HE",
    "sg:province":"Cheshire",
    "sg:tags":[
        "adviser"
    ],
    "wof:name":"David  Dingsdale",
    "wof:placetype":"venue"
},
  "geometry": {"coordinates":[-2.131743,53.387001],"type":"Point"}
}