{
  "type": "Feature",
  "properties": {
    "addr:full":"Glen House, 200 Tottenham Court Road London Greater London W1T 7PL",
    "addr:housenumber":"200",
    "addr:postcode":"w1t 7pl",
    "addr:street":"Tottenham Court Road",
    "iso:country":"GB",
    "sg:address":"Glen House, 200 Tottenham Court Road",
    "sg:city":"London",
    "sg:classifiers":[
        {
            "category":"Travel",
            "subcategory":"Travel Agent",
            "type":"Entertainment"
        }
    ],
    "sg:postcode":"W1T 7PL",
    "sg:province":"Greater London",
    "sg:tags":[
        "hotel",
        "agency",
        "booking"
    ],
    "wof:name":"A C T Enterprise",
    "wof:placetype":"venue"
},
  "geometry": {"coordinates":[-0.133814,51.519855],"type":"Point"}
}