{
  "type": "Feature",
  "properties": {
    "addr:full":"Tiverton House, Llechryd Cardigan Ceredigion SA43 2NU",
    "addr:postcode":"sa43 2nu",
    "addr:street":"Llechryd",
    "iso:country":"GB",
    "sg:address":"Tiverton House, Llechryd",
    "sg:city":"Cardigan",
    "sg:classifiers":[
        {
            "category":"Building & Trades",
            "subcategory":"Cleaning & Sanitation",
            "type":"Services"
        },
        {
            "category":"Home & Garden",
            "subcategory":"Carpets & Floor Coverings",
            "type":"Retail Goods"
        }
    ],
    "sg:phone":"+44 1239 682497",
    "sg:postcode":"SA43 2NU",
    "sg:province":"Ceredigion",
    "sg:tags":[
        "cleaner",
        "upholstery",
        "sweep",
        "chimney"
    ],
    "wof:name":"Parrys of Cardigan",
    "wof:placetype":"venue"
},
  "geometry": {"coordinates":[-4.608479,52.067921],"type":"Point"}
}