{
  "type": "Feature",
  "properties": {
    "iso:country":"GB",
    "sg:address":"170 Longridge Rd",
    "sg:city":"Preston",
    "sg:classifiers":[
        {
            "category":"Manufacturing",
            "subcategory":"Paper Products",
            "type":"Manufacturing & Wholesale Goods"
        }
    ],
    "sg:phone":"+44 1772 781900",
    "sg:postcode":"PR2 5BE",
    "sg:province":"Lancashire",
    "sg:tags":[
        "cardboard"
    ],
    "wof:name":"Modelboard Ltd",
    "wof:placetype":"venue"
},
  "geometry": {"coordinates":[-2.637869,53.792011],"type":"Point"}
}