{
  "type": "Feature",
  "properties": {
    "addr:full":"Care Of Home Base, Rookery Way, The Hyde London Greater London NW9 6SS",
    "addr:postcode":"nw9 6ss",
    "addr:street":"Rookery Way",
    "iso:country":"GB",
    "sg:address":"Care Of Home Base, Rookery Way, The Hyde",
    "sg:city":"London",
    "sg:classifiers":[
        {
            "category":"Home & Garden",
            "subcategory":"Carpets & Floor Coverings",
            "type":"Retail Goods"
        }
    ],
    "sg:phone":"+44 20 8200 5408",
    "sg:postcode":"NW9 6SS",
    "sg:province":"Greater London",
    "sg:tags":[
        "carpets",
        "rug",
        "matting"
    ],
    "wof:name":"Premier Carpets",
    "wof:placetype":"venue"
},
  "geometry": {"coordinates":[-0.2458499968,51.5846214294],"type":"Point"}
}