{
  "type": "Feature",
  "properties": {
    "addr:full":"7 Fforchaman Road Aberdare Neath Port Talbot CF44 6NS",
    "addr:housenumber":"7",
    "addr:postcode":"cf44 6ns",
    "addr:street":"Fforchaman Road",
    "iso:country":"GB",
    "sg:address":"7 Fforchaman Road",
    "sg:city":"Aberdare",
    "sg:classifiers":[
        {
            "category":"Professional",
            "subcategory":"Business Services",
            "type":"Services"
        }
    ],
    "sg:phone":"+44 1685 879700",
    "sg:postcode":"CF44 6NS",
    "sg:province":"Neath Port Talbot",
    "sg:tags":[
        "bookmaker"
    ],
    "wof:name":"K Hughes",
    "wof:placetype":"venue"
},
  "geometry": {"coordinates":[-3.4425649643,51.6855545044],"type":"Point"}
}