{
  "type": "Feature",
  "properties": {
    "addr:full":"47 Redwing Brae Livingston West Lothian EH54 6UH",
    "addr:housenumber":"47",
    "addr:postcode":"eh54 6uh",
    "addr:street":"Redwing Brae",
    "iso:country":"GB",
    "sg:address":"47 Redwing Brae",
    "sg:city":"Livingston",
    "sg:classifiers":[
        {
            "category":"Building & Trades",
            "subcategory":"Landscaping Services",
            "type":"Services"
        }
    ],
    "sg:phone":"+44 1506 461700",
    "sg:postcode":"EH54 6UH",
    "sg:province":"West Lothian",
    "sg:tags":[
        "landscape",
        "contractor"
    ],
    "wof:name":"Reed Landscaping",
    "wof:placetype":"venue"
},
  "geometry": {"coordinates":[-3.528493,55.900181],"type":"Point"}
}