{
  "type": "Feature",
  "properties": {
    "iso:country":"GB",
    "sg:address":"4 Lower Dale Road",
    "sg:city":"Derby",
    "sg:classifiers":[
        {
            "category":"Personal",
            "subcategory":"Beauty Salon",
            "type":"Services"
        }
    ],
    "sg:phone":"+44 7866 264542",
    "sg:postcode":"DE23 6WY",
    "sg:province":"Derbyshire",
    "sg:tags":[
        "unisex",
        "hairdresser"
    ],
    "wof:name":"Jenni's Salon",
    "wof:placetype":"venue"
},
  "geometry": {"coordinates":[-1.479149,52.909061],"type":"Point"}
}