{
  "type": "Feature",
  "properties": {
    "addr:full":"24 Garnet House, St Georges Road Brighton East Sussex BN2 1EU",
    "addr:housenumber":"24",
    "addr:postcode":"bn2 1eu",
    "addr:street":"Garnet House St Georges Road",
    "iso:country":"GB",
    "sg:address":"24 Garnet House, St Georges Road",
    "sg:city":"Brighton",
    "sg:classifiers":[
        {
            "category":"Education",
            "subcategory":"Special Training",
            "type":"Public Place"
        }
    ],
    "sg:phone":"+44 1273 622933",
    "sg:postcode":"BN2 1EU",
    "sg:province":"East Sussex",
    "sg:tags":[
        "diving",
        "school"
    ],
    "wof:name":"The Brighton Dive Co.",
    "wof:placetype":"venue"
},
  "geometry": {"coordinates":[-0.1222210005,50.8188934326],"type":"Point"}
}