{
  "type": "Feature",
  "properties": {
    "iso:country":"GB",
    "sg:address":"168 Solly Street",
    "sg:city":"Sheffield",
    "sg:classifiers":[
        {
            "category":"Bars & Pubs",
            "type":"Food & Drink"
        },
        {
            "category":"Community Center",
            "subcategory":"Social",
            "type":"Public Place"
        }
    ],
    "sg:phone":"+44 114 272 7926",
    "sg:postcode":"S1 4BB",
    "sg:province":"South Yorkshire",
    "sg:tags":[
        "pubs",
        "house",
        "inn",
        "activity"
    ],
    "wof:name":"The Red House",
    "wof:placetype":"venue"
},
  "geometry": {"coordinates":[-1.478178978,53.3844985962],"type":"Point"}
}