{
  "type": "Feature",
  "properties": {
    "iso:country":"GB",
    "sg:address":"8 Boughton Road",
    "sg:city":"Rugby",
    "sg:classifiers":[
        {
            "category":"Fast Food",
            "type":"Food & Drink"
        }
    ],
    "sg:phone":"+44 1788 573251",
    "sg:postcode":"CV21 1BJ",
    "sg:province":"Warwickshire",
    "sg:tags":[
        "away",
        "take"
    ],
    "wof:name":"The Great Wall",
    "wof:placetype":"venue"
},
  "geometry": {"coordinates":[-1.247264,52.383045],"type":"Point"}
}