{
  "type": "Feature",
  "properties": {
    "iso:country":"GB",
    "sg:address":"Townbridge",
    "sg:city":"Trowbridge",
    "sg:classifiers":[
        {
            "category":"Autos & Motor Vehicles",
            "subcategory":"Automobile Sales",
            "type":"Retail Goods"
        }
    ],
    "sg:phone":"+44 1225 766191",
    "sg:postcode":"BA14 8JZ",
    "sg:province":"Wiltshire",
    "sg:tags":[
        "car"
    ],
    "wof:name":"G K Trowbridge",
    "wof:placetype":"venue"
},
  "geometry": {"coordinates":[-2.208374,51.315342],"type":"Point"}
}