{
  "type": "Feature",
  "properties": {
    "iso:country":"GB",
    "sg:address":"7a Pound Street",
    "sg:city":"Exmouth",
    "sg:classifiers":[
        {
            "category":"Manufacturing",
            "subcategory":"Metals",
            "type":"Manufacturing & Wholesale Goods"
        },
        {
            "category":"Professional",
            "subcategory":"Printing & Photocopies",
            "type":"Services"
        }
    ],
    "sg:postcode":"EX8 2SY",
    "sg:province":"Devon",
    "sg:tags":[
        "engraving",
        "heat",
        "-",
        "treatment"
    ],
    "wof:name":"Baker Engraving Co",
    "wof:placetype":"venue"
},
  "geometry": {"coordinates":[-3.4106650352,50.6187896729],"type":"Point"}
}