{
  "type": "Feature",
  "properties": {
    "addr:full":"9 The Cedars Sunderland Tyne and Wear SR2 7TW",
    "addr:housenumber":"9",
    "addr:postcode":"sr2 7tw",
    "addr:street":"The Cedars",
    "iso:country":"GB",
    "sg:address":"9 The Cedars",
    "sg:city":"Sunderland",
    "sg:classifiers":[
        {
            "category":"Organizations",
            "subcategory":"Non-profit Organization",
            "type":"Services"
        }
    ],
    "sg:phone":"+44 191 567 3523",
    "sg:postcode":"SR2 7TW",
    "sg:province":"Tyne and Wear",
    "sg:tags":[
        "organisation",
        "voluntary",
        "charity"
    ],
    "wof:name":"European Services for People With Autism Ltd.",
    "wof:placetype":"venue"
},
  "geometry": {"coordinates":[-1.379207015,54.8924980164],"type":"Point"}
}