{
  "type": "Feature",
  "properties": {
    "addr:full":"22 Queens Road Hastings East Sussex TN34 1LU",
    "addr:housenumber":"22",
    "addr:postcode":"tn34 1lu",
    "addr:street":"Queens Road",
    "iso:country":"GB",
    "sg:address":"22 Queens Road",
    "sg:city":"Hastings",
    "sg:classifiers":[
        {
            "category":"Banks & Credit Unions",
            "subcategory":"Financial Services",
            "type":"Services"
        }
    ],
    "sg:phone":"+44 1424 721144",
    "sg:postcode":"TN34 1LU",
    "sg:province":"East Sussex",
    "sg:tags":[
        "building",
        "society"
    ],
    "wof:name":"Alliance & Leicester Building Society",
    "wof:placetype":"venue"
},
  "geometry": {"coordinates":[0.5819349885,50.8567428589],"type":"Point"}
}