{
  "type": "Feature",
  "properties": {
    "addr:full":"5 Seabright Way, Alveley Bridgnorth Shropshire WV15 6PE",
    "addr:housenumber":"5",
    "addr:postcode":"wv15 6pe",
    "addr:street":"Seabright Way",
    "iso:country":"GB",
    "sg:address":"5 Seabright Way, Alveley",
    "sg:city":"Bridgnorth",
    "sg:classifiers":[
        {
            "category":"Professional",
            "subcategory":"Art Services",
            "type":"Services"
        }
    ],
    "sg:postcode":"WV15 6PE",
    "sg:province":"Shropshire",
    "sg:tags":[
        "photographer"
    ],
    "wof:name":"S J Restorick Photography",
    "wof:placetype":"venue"
},
  "geometry": {"coordinates":[-2.3506479263,52.4555702209],"type":"Point"}
}