{
  "type": "Feature",
  "properties": {
    "iso:country":"GB",
    "sg:address":"57 Piccadily",
    "sg:city":"Manchester",
    "sg:classifiers":[
        {
            "category":"Shopping",
            "subcategory":"Shoes",
            "type":"Retail Goods"
        }
    ],
    "sg:phone":"+44 161 236 3862",
    "sg:postcode":"M1 2AP",
    "sg:province":"Greater Manchester",
    "wof:name":"Timpsons Shoe Repairs",
    "wof:placetype":"venue"
},
  "geometry": {"coordinates":[-2.234663,53.480873],"type":"Point"}
}