{
  "type": "Feature",
  "properties": {
    "iso:country":"GB",
    "sg:address":"No 1 Tabley Mews",
    "sg:city":"Altrincham",
    "sg:classifiers":[
        {
            "category":"Manufacturing",
            "subcategory":"Textiles",
            "type":"Manufacturing & Wholesale Goods"
        }
    ],
    "sg:phone":"+44 161 929 1110",
    "sg:postcode":"WA14 1DA",
    "sg:province":"Cheshire",
    "sg:tags":[
        "merchant",
        "agent"
    ],
    "wof:name":"Davies Pugh Properties Ltd.",
    "wof:placetype":"venue"
},
  "geometry": {"coordinates":[-2.3492090702,53.3867263794],"type":"Point"}
}