{
  "type": "Feature",
  "properties": {
    "addr:full":"Calf House, Abbott Brow, Mellor Blackburn Lancashire BB2 7HU",
    "addr:postcode":"bb2 7hu",
    "addr:street":"Abbott Brow",
    "iso:country":"GB",
    "sg:address":"Calf House, Abbott Brow, Mellor",
    "sg:city":"Blackburn",
    "sg:classifiers":[
        {
            "category":"Professional",
            "subcategory":"Lawyer & Legal Services",
            "type":"Services"
        }
    ],
    "sg:phone":"+44 1254 813209",
    "sg:postcode":"BB2 7HU",
    "sg:province":"Lancashire",
    "sg:tags":[
        "advice",
        "counselling"
    ],
    "wof:name":"Quest Educational Development",
    "wof:placetype":"venue"
},
  "geometry": {"coordinates":[-2.5281410217,53.7734603882],"type":"Point"}
}