{
  "type": "Feature",
  "properties": {
    "addr:full":"14 Chilton Square Hereford Herefordshire HR1 1PS",
    "addr:housenumber":"14",
    "addr:postcode":"hr1 1ps",
    "addr:street":"Chilton Square",
    "iso:country":"GB",
    "sg:address":"14 Chilton Square",
    "sg:city":"Hereford",
    "sg:classifiers":[
        {
            "category":"Shopping",
            "subcategory":"Department Store",
            "type":"Retail Goods"
        },
        {
            "category":"Food & Beverages",
            "subcategory":"Groceries & Convenience Stores",
            "type":"Retail Goods"
        }
    ],
    "sg:phone":"+44 1432 273673",
    "sg:postcode":"HR1 1PS",
    "sg:province":"Herefordshire",
    "wof:name":"The Corner Stores",
    "wof:placetype":"venue"
},
  "geometry": {"coordinates":[-2.6882419586,52.0616569519],"type":"Point"}
}