{
  "type": "Feature",
  "properties": {
    "addr:full":"138 Bolton Rd West, Ramsbottom Bury Lancashire BL0 9PD",
    "addr:housenumber":"138",
    "addr:postcode":"bl0 9pd",
    "addr:street":"Bolton Rd West",
    "iso:country":"GB",
    "sg:address":"138 Bolton Rd West, Ramsbottom",
    "sg:city":"Bury",
    "sg:classifiers":[
        {
            "category":"Health Services",
            "subcategory":"Health Practitioner",
            "type":"Services"
        }
    ],
    "sg:phone":"+44 1706 825727",
    "sg:postcode":"BL0 9PD",
    "sg:province":"Lancashire",
    "sg:tags":[
        "physiotherapist"
    ],
    "wof:name":"Ramsbottom Physiotherapy Clinic",
    "wof:placetype":"venue"
},
  "geometry": {"coordinates":[-2.3262109756,53.6401596069],"type":"Point"}
}