{
  "type": "Feature",
  "properties": {
    "iso:country":"GB",
    "sg:address":"Forest St",
    "sg:city":"Chester",
    "sg:classifiers":[
        {
            "category":"Bars & Pubs",
            "subcategory":"Nightclub",
            "type":"Food & Drink"
        }
    ],
    "sg:postcode":"CH1 1QR",
    "sg:province":"Cheshire",
    "sg:tags":[
        "club",
        "night"
    ],
    "wof:name":"Copacobana Club",
    "wof:placetype":"venue"
},
  "geometry": {"coordinates":[-2.883867,53.191055],"type":"Point"}
}