{
  "type": "Feature",
  "properties": {
    "iso:country":"GB",
    "sg:address":"The Lecturage, Almshouse Road",
    "sg:city":"Coleford",
    "sg:classifiers":[
        {
            "category":"Real Estate",
            "subcategory":"Surveying",
            "type":"Services"
        }
    ],
    "sg:postcode":"GL16 8NL",
    "sg:province":"Gloucestershire",
    "sg:tags":[
        "surveyor",
        "quantity"
    ],
    "wof:name":"Craigdam Services Ltd.",
    "wof:placetype":"venue"
},
  "geometry": {"coordinates":[-2.604089,51.791393],"type":"Point"}
}