{
  "type": "Feature",
  "properties": {
    "iso:country":"GB",
    "sg:address":"23 Church Street",
    "sg:city":"Rushden",
    "sg:classifiers":[
        {
            "category":"Real Estate",
            "subcategory":"Real Estate Agent",
            "type":"Services"
        }
    ],
    "sg:phone":"+44 1933 355124",
    "sg:postcode":"NN10 9YU",
    "sg:province":"Bedfordshire",
    "wof:name":"Windsor Estate Agents",
    "wof:placetype":"venue"
},
  "geometry": {"coordinates":[-0.598688,52.289101],"type":"Point"}
}