{
  "type": "Feature",
  "properties": {
    "iso:country":"GB",
    "sg:address":"58 Craigentinny Avenue North",
    "sg:city":"Edinburgh",
    "sg:classifiers":[
        {
            "category":"Manufacturing",
            "subcategory":"Building Materials",
            "type":"Manufacturing & Wholesale Goods"
        }
    ],
    "sg:phone":"+44 131 554 1144",
    "sg:postcode":"EH6 7RD",
    "sg:province":"City of Edinburgh",
    "sg:tags":[
        "merchant",
        "builder"
    ],
    "wof:name":"Jewson Ltd.",
    "wof:placetype":"venue"
},
  "geometry": {"coordinates":[-3.140564,55.96682],"type":"Point"}
}