{
  "type": "Feature",
  "properties": {
    "addr:full":"229 Mansfield Road Chesterfield Derbyshire S41 0JJ",
    "addr:housenumber":"229",
    "addr:postcode":"s41 0jj",
    "addr:street":"Mansfield Road",
    "iso:country":"GB",
    "sg:address":"229 Mansfield Road",
    "sg:city":"Chesterfield",
    "sg:classifiers":[
        {
            "category":"Bars & Pubs",
            "type":"Food & Drink"
        }
    ],
    "sg:phone":"+44 1246 273727",
    "sg:postcode":"S41 0JJ",
    "sg:province":"Derbyshire",
    "sg:tags":[
        "pubs",
        "inn"
    ],
    "wof:name":"Whitbread Hotel Co. Ltd.",
    "wof:placetype":"venue"
},
  "geometry": {"coordinates":[-1.395605,53.2146],"type":"Point"}
}