{
  "type": "Feature",
  "properties": {
    "addr:full":"Pengegin Uchaf Fishguard Pembrokeshire SA65 9SB",
    "addr:postcode":"sa65 9sb",
    "iso:country":"GB",
    "sg:address":"Pengegin Uchaf",
    "sg:city":"Fishguard",
    "sg:classifiers":[
        {
            "category":"Farming",
            "subcategory":"Livestock Farm",
            "type":"Manufacturing & Wholesale Goods"
        }
    ],
    "sg:phone":"+44 1348 881353",
    "sg:postcode":"SA65 9SB",
    "sg:province":"Pembrokeshire",
    "sg:tags":[
        "others"
    ],
    "wof:name":"G Phillips",
    "wof:placetype":"venue"
},
  "geometry": {"coordinates":[-4.977397,51.994373],"type":"Point"}
}