{
  "type": "Feature",
  "properties": {
    "addr:full":"Platting Lane Rochdale Lancashire OL11 2HD",
    "addr:postcode":"ol11 2hd",
    "addr:street":"Platting Lane",
    "iso:country":"GB",
    "sg:address":"Platting Lane",
    "sg:city":"Rochdale",
    "sg:classifiers":[
        {
            "category":"Education",
            "subcategory":"Library",
            "type":"Public Place"
        }
    ],
    "sg:phone":"+44 1706 640438",
    "sg:postcode":"OL11 2HD",
    "sg:province":"Lancashire",
    "sg:tags":[
        "book"
    ],
    "wof:name":"Balderstone Branch Library",
    "wof:placetype":"venue"
},
  "geometry": {"coordinates":[-2.147214,53.601509],"type":"Point"}
}