{
  "type": "Feature",
  "properties": {
    "iso:country":"GB",
    "sg:address":"Penarth Road",
    "sg:city":"Cardiff",
    "sg:classifiers":[
        {
            "category":"Bars & Pubs",
            "type":"Food & Drink"
        }
    ],
    "sg:phone":"+44 29 2025 7502",
    "sg:postcode":"CF11 6NL",
    "sg:province":"Cardiff",
    "sg:tags":[
        "pubs",
        "inn"
    ],
    "wof:name":"The Baroness Windsor",
    "wof:placetype":"venue"
},
  "geometry": {"coordinates":[-3.1831040382,51.4719657898],"type":"Point"}
}