{
  "type": "Feature",
  "properties": {
    "addr:full":"Rear Of 38 Osborne Road Southsea Hampshire PO5 3LT",
    "addr:housenumber":"rear of 38",
    "addr:postcode":"po5 3lt",
    "addr:street":"Osborne Road",
    "iso:country":"GB",
    "sg:address":"Rear Of 38 Osborne Road",
    "sg:city":"Southsea",
    "sg:classifiers":[
        {
            "category":"Utilities",
            "subcategory":"Natural Gas",
            "type":"Services"
        }
    ],
    "sg:phone":"+44 23 9275 3562",
    "sg:postcode":"PO5 3LT",
    "sg:province":"Hampshire",
    "sg:tags":[
        "blacksmith"
    ],
    "wof:name":"Peter Clutterbuck",
    "wof:placetype":"venue"
},
  "geometry": {"coordinates":[-1.088164,50.784664],"type":"Point"}
}