{
  "type": "Feature",
  "properties": {
    "iso:country":"GB",
    "sg:address":"409c Ashley Road",
    "sg:city":"Poole",
    "sg:classifiers":[
        {
            "category":"Food & Beverages",
            "subcategory":"Meat & Fish",
            "type":"Retail Goods"
        }
    ],
    "sg:phone":"+44 1202 740896",
    "sg:postcode":"BH14 0AX",
    "sg:province":"Dorset",
    "sg:tags":[
        "chip"
    ],
    "wof:name":"Seaview Fish Bar",
    "wof:placetype":"venue"
},
  "geometry": {"coordinates":[-1.943992,50.729057],"type":"Point"}
}