{
  "type": "Feature",
  "properties": {
    "addr:full":"47 Chestergate Macclesfield Cheshire SK11 6DG",
    "addr:housenumber":"47",
    "addr:postcode":"sk11 6dg",
    "addr:street":"Chestergate Macclesfield",
    "iso:country":"GB",
    "sg:address":"47 Chestergate",
    "sg:city":"Macclesfield",
    "sg:classifiers":[
        {
            "category":"Shopping",
            "subcategory":"Comic Books",
            "type":"Retail Goods"
        }
    ],
    "sg:phone":"+44 1625 616133",
    "sg:postcode":"SK11 6DG",
    "sg:province":"Cheshire",
    "sg:tags":[
        "jeweller"
    ],
    "wof:name":"D J Massey & Son",
    "wof:placetype":"venue"
},
  "geometry": {"coordinates":[-2.1284379959,53.2611274719],"type":"Point"}
}