{
  "type": "Feature",
  "properties": {
    "iso:country":"GB",
    "sg:address":"9 Green Bank Rd, Cumbernauld",
    "sg:city":"Glasgow",
    "sg:classifiers":[
        {
            "category":"Government",
            "subcategory":"Post Office",
            "type":"Public Place"
        }
    ],
    "sg:phone":"+44 1236 733446",
    "sg:postcode":"G68 9BY",
    "sg:province":"East Dunbartonshire",
    "sg:tags":[
        "window",
        "display",
        "dressing"
    ],
    "wof:name":"Papillon Displays",
    "wof:placetype":"venue"
},
  "geometry": {"coordinates":[-4.0128250122,55.9501037598],"type":"Point"}
}