{
  "type": "Feature",
  "properties": {
    "addr:full":"96-97 Stratford Road, Wolverton Milton Keynes Buckinghamshire MK12 5LX",
    "addr:housenumber":"96-97",
    "addr:postcode":"mk12 5lx",
    "addr:street":"Stratford Road",
    "iso:country":"GB",
    "sg:address":"96-97 Stratford Road, Wolverton",
    "sg:city":"Milton Keynes",
    "sg:classifiers":[
        {
            "category":"Professional",
            "subcategory":"Art Services",
            "type":"Services"
        }
    ],
    "sg:phone":"+44 1908 222881",
    "sg:postcode":"MK12 5LX",
    "sg:province":"Buckinghamshire",
    "sg:tags":[
        "photographer"
    ],
    "wof:name":"New City Graphic",
    "wof:placetype":"venue"
},
  "geometry": {"coordinates":[-0.818558991,52.0622444153],"type":"Point"}
}