{
  "type": "Feature",
  "properties": {
    "addr:full":"60 Clifton Road Rugby Warwickshire CV21 3QF",
    "addr:housenumber":"60",
    "addr:postcode":"cv21 3qf",
    "addr:street":"Clifton Road",
    "iso:country":"GB",
    "sg:address":"60 Clifton Road",
    "sg:city":"Rugby",
    "sg:classifiers":[
        {
            "category":"Professional",
            "subcategory":"Art Services",
            "type":"Services"
        }
    ],
    "sg:postcode":"CV21 3QF",
    "sg:province":"Warwickshire",
    "sg:tags":[
        "graphic",
        "designer"
    ],
    "wof:name":"David Ross Design",
    "wof:placetype":"venue"
},
  "geometry": {"coordinates":[-1.2503910065,52.3721923828],"type":"Point"}
}