{
  "type": "Feature",
  "properties": {
    "addr:full":"21 Beesmoor Road, Coalpit Heath Bristol Gloucestershire BS36 2RS",
    "addr:housenumber":"21",
    "addr:postcode":"bs36 2rs",
    "addr:street":"Beesmoor Road",
    "iso:country":"GB",
    "sg:address":"21 Beesmoor Road, Coalpit Heath",
    "sg:city":"Bristol",
    "sg:classifiers":[
        {
            "category":"Shopping",
            "subcategory":"News",
            "type":"Retail Goods"
        }
    ],
    "sg:postcode":"BS36 2RS",
    "sg:province":"Gloucestershire",
    "sg:tags":[
        "newsagent"
    ],
    "wof:name":"Greens Newsagent",
    "wof:placetype":"venue"
},
  "geometry": {"coordinates":[-2.477659,51.526829],"type":"Point"}
}