{
  "type": "Feature",
  "properties": {
    "addr:full":"69 Main Street Prestwick South Ayrshire KA9 1JN",
    "addr:housenumber":"69",
    "addr:postcode":"ka9 1jn",
    "addr:street":"Main Street",
    "iso:country":"GB",
    "sg:address":"69 Main Street",
    "sg:city":"Prestwick",
    "sg:classifiers":[
        {
            "category":"Fast Food",
            "type":"Food & Drink"
        }
    ],
    "sg:postcode":"KA9 1JN",
    "sg:province":"South Ayrshire",
    "sg:tags":[
        "away",
        "take"
    ],
    "wof:name":"A Araslan",
    "wof:placetype":"venue"
},
  "geometry": {"coordinates":[-4.610752,55.500092],"type":"Point"}
}