{
  "type": "Feature",
  "properties": {
    "iso:country":"GB",
    "sg:address":"Po Box 141",
    "sg:city":"Stoke-on-trent",
    "sg:classifiers":[
        {
            "category":"Shopping",
            "subcategory":"Computers & Home Electronics",
            "type":"Retail Goods"
        }
    ],
    "sg:phone":"+44 1782 854100",
    "sg:postcode":"ST4 1EW",
    "sg:province":"Staffordshire",
    "sg:tags":[
        "electrical"
    ],
    "wof:name":"Swift Electrical Wholesalers (S-o-T) Ltd.",
    "wof:placetype":"venue"
},
  "geometry": {"coordinates":[-2.18399,53.003281],"type":"Point"}
}