{
  "type": "Feature",
  "properties": {
    "iso:country":"GB",
    "sg:address":"Padbury Avenue",
    "sg:city":"Filey",
    "sg:classifiers":[
        {
            "category":"Education",
            "subcategory":"School",
            "type":"Public Place"
        },
        {
            "category":"Government",
            "subcategory":"Office",
            "type":"Public Place"
        }
    ],
    "sg:phone":"+44 1723 513077",
    "sg:postcode":"YO14 0BA",
    "sg:province":"North Yorkshire",
    "sg:tags":[
        "local",
        "authority"
    ],
    "wof:name":"C Filey of E Infant School",
    "wof:placetype":"venue"
},
  "geometry": {"coordinates":[-0.293787,54.205921],"type":"Point"}
}