{
  "type": "Feature",
  "properties": {
    "addr:full":"Chester Road, Gresford Wrexham Wrexham LL12 8PW",
    "addr:postcode":"ll12 8pw",
    "addr:street":"Chester Road",
    "iso:country":"GB",
    "sg:address":"Chester Road, Gresford",
    "sg:city":"Wrexham",
    "sg:classifiers":[
        {
            "category":"Travel",
            "subcategory":"Hotels & Motels",
            "type":"Entertainment"
        }
    ],
    "sg:phone":"+44 1978 853214",
    "sg:postcode":"LL12 8PW",
    "sg:province":"Wrexham",
    "wof:name":"Travel Inn",
    "wof:placetype":"venue"
},
  "geometry": {"coordinates":[-2.965414,53.088017],"type":"Point"}
}