{
  "type": "Feature",
  "properties": {
    "iso:country":"GB",
    "sg:address":"Meals On Wheels, Harras Bank",
    "sg:city":"Chester Le Street",
    "sg:classifiers":[
        {
            "category":"Social Services",
            "type":"Services"
        }
    ],
    "sg:phone":"+44 191 410 6612",
    "sg:postcode":"DH3 2PE",
    "sg:province":"Durham",
    "wof:name":"Social Services",
    "wof:placetype":"venue"
},
  "geometry": {"coordinates":[-1.574964,54.859135],"type":"Point"}
}