{
  "type": "Feature",
  "properties": {
    "iso:country":"GB",
    "sg:address":"Cross Green Trading Estate",
    "sg:city":"Leeds",
    "sg:classifiers":[
        {
            "category":"Wholesale",
            "subcategory":"Scrap",
            "type":"Manufacturing & Wholesale Goods"
        },
        {
            "category":"Wholesale",
            "subcategory":"Auto Parts",
            "type":"Manufacturing & Wholesale Goods"
        }
    ],
    "sg:phone":"+44 113 235 0391",
    "sg:postcode":"LS9 0PF",
    "sg:province":"West Yorkshire",
    "sg:tags":[
        "car",
        "breaker",
        "dismantlers"
    ],
    "wof:name":"Cross Green Auto Wreckers",
    "wof:placetype":"venue"
},
  "geometry": {"coordinates":[-1.522704,53.78936],"type":"Point"}
}