{
  "type": "Feature",
  "properties": {
    "addr:full":"76 Castle Street Canterbury Kent CT1 2QD",
    "addr:housenumber":"76",
    "addr:postcode":"ct1 2qd",
    "addr:street":"Castle Street",
    "iso:country":"GB",
    "sg:address":"76 Castle Street",
    "sg:city":"Canterbury",
    "sg:classifiers":[
        {
            "category":"Social Services",
            "subcategory":"Adult Care",
            "type":"Services"
        }
    ],
    "sg:postcode":"CT1 2QD",
    "sg:province":"Kent",
    "sg:tags":[
        "domestic",
        "cleaning"
    ],
    "wof:name":"The Cleaning Co.",
    "wof:placetype":"venue"
},
  "geometry": {"coordinates":[1.077825,51.277496],"type":"Point"}
}