{
  "type": "Feature",
  "properties": {
    "addr:full":"196 Main Road, Great Leighs Chelmsford Essex CM3 1NR",
    "addr:housenumber":"196",
    "addr:postcode":"cm3 1nr",
    "addr:street":"Main Road",
    "iso:country":"GB",
    "sg:address":"196 Main Road, Great Leighs",
    "sg:city":"Chelmsford",
    "sg:classifiers":[
        {
            "category":"Building & Trades",
            "subcategory":"Construction",
            "type":"Services"
        }
    ],
    "sg:postcode":"CM3 1NR",
    "sg:province":"Essex",
    "sg:tags":[
        "builder"
    ],
    "wof:name":"H C Hiskey & Son",
    "wof:placetype":"venue"
},
  "geometry": {"coordinates":[0.511333,51.833485],"type":"Point"}
}