{
  "type": "Feature",
  "properties": {
    "iso:country":"GB",
    "sg:address":"31 Wrayfield Rd",
    "sg:city":"Sutton",
    "sg:classifiers":[
        {
            "category":"Building & Trades",
            "subcategory":"Construction",
            "type":"Services"
        }
    ],
    "sg:postcode":"SM3 9TJ",
    "sg:province":"Surrey",
    "sg:tags":[
        "builder"
    ],
    "wof:name":"Hutchison & Taylor Ltd",
    "wof:placetype":"venue"
},
  "geometry": {"coordinates":[-0.220807,51.370342],"type":"Point"}
}