{
  "type": "Feature",
  "properties": {
    "addr:full":"10 St Edwards Walk Cheltenham Gloucestershire GL53 7RS",
    "addr:housenumber":"10",
    "addr:postcode":"gl53 7rs",
    "addr:street":"St Edwards Walk",
    "iso:country":"GB",
    "sg:address":"10 St Edwards Walk",
    "sg:city":"Cheltenham",
    "sg:classifiers":[
        {
            "category":"Professional",
            "subcategory":"Accounting & Tax Preparation",
            "type":"Services"
        }
    ],
    "sg:postcode":"GL53 7RS",
    "sg:province":"Gloucestershire",
    "sg:tags":[
        "accountant"
    ],
    "wof:name":"Finnemore",
    "wof:placetype":"venue"
},
  "geometry": {"coordinates":[-2.0587420464,51.8871994019],"type":"Point"}
}