{
  "type": "Feature",
  "properties": {
    "addr:full":"3 Weston Mill La, Via Billing Northampton Northamptonshire NN3 3HJ",
    "addr:housenumber":"3",
    "addr:postcode":"nn3 3hj",
    "addr:street":"Weston Mill La;Billing",
    "iso:country":"GB",
    "sg:address":"3 Weston Mill La, Via Billing",
    "sg:city":"Northampton",
    "sg:classifiers":[
        {
            "category":"Autos & Motor Vehicles",
            "subcategory":"Motorcycle Sales",
            "type":"Retail Goods"
        }
    ],
    "sg:postcode":"NN3 3HJ",
    "sg:province":"Northamptonshire",
    "sg:tags":[
        "chauffeur",
        "driven",
        "car"
    ],
    "wof:name":"Cottage Cars",
    "wof:placetype":"venue"
},
  "geometry": {"coordinates":[-0.844257,52.241772],"type":"Point"}
}