{
  "type": "Feature",
  "properties": {
    "addr:full":"330 Long Lane, Hillingdon Uxbridge Greater London UB10 9PF",
    "addr:housenumber":"330",
    "addr:postcode":"ub10 9pf",
    "addr:street":"Long Lane",
    "iso:country":"GB",
    "sg:address":"330 Long Lane, Hillingdon",
    "sg:city":"Uxbridge",
    "sg:classifiers":[
        {
            "category":"Health Services",
            "subcategory":"Dentist",
            "type":"Services"
        }
    ],
    "sg:phone":"+44 1895 234540",
    "sg:postcode":"UB10 9PF",
    "sg:province":"Greater London",
    "wof:name":"B Taank Dental Surgeon",
    "wof:placetype":"venue"
},
  "geometry": {"coordinates":[-0.448801,51.549728],"type":"Point"}
}