{
  "type": "Feature",
  "properties": {
    "addr:full":"Unit 9 Eastburn Mills, Main Road Keighley North Yorkshire BD20 7SJ",
    "addr:housenumber":"unit 9",
    "addr:postcode":"bd20 7sj",
    "addr:street":"Eastburn Mills Main Road",
    "iso:country":"GB",
    "sg:address":"Unit 9 Eastburn Mills, Main Road",
    "sg:city":"Keighley",
    "sg:classifiers":[
        {
            "category":"Professional",
            "type":"Services"
        },
        {
            "category":"Professional",
            "subcategory":"Advertising",
            "type":"Services"
        }
    ],
    "sg:postcode":"BD20 7SJ",
    "sg:province":"North Yorkshire",
    "sg:tags":[
        "agency",
        "display",
        "maker"
    ],
    "wof:name":"Factotum",
    "wof:placetype":"venue"
},
  "geometry": {"coordinates":[-1.9725300074,53.8968887329],"type":"Point"}
}