{
  "type": "Feature",
  "properties": {
    "iso:country":"GB",
    "sg:address":"Greenstones Road",
    "sg:city":"Redcar",
    "sg:classifiers":[
        {
            "category":"Food & Beverages",
            "subcategory":"Groceries & Convenience Stores",
            "type":"Retail Goods"
        }
    ],
    "sg:phone":"+44 1642 470166",
    "sg:postcode":"TS10 2RA",
    "sg:province":"North Yorkshire",
    "wof:name":"Bells Stores",
    "wof:placetype":"venue"
},
  "geometry": {"coordinates":[-1.0533970594,54.6007156372],"type":"Point"}
}