{
  "type": "Feature",
  "properties": {
    "addr:full":"Neath Farm Business Park, 154 Church End Cambridge Cambridgeshire CB1 3LD",
    "addr:housenumber":"154",
    "addr:postcode":"cb1 3ld",
    "addr:street":"Neath;Church End",
    "iso:country":"GB",
    "sg:address":"Neath Farm Business Park, 154 Church End",
    "sg:city":"Cambridge",
    "sg:classifiers":[
        {
            "category":"Shopping",
            "subcategory":"Books",
            "type":"Retail Goods"
        }
    ],
    "sg:phone":"+44 1223 245222",
    "sg:postcode":"CB1 3LD",
    "sg:province":"Cambridgeshire",
    "wof:name":"L F B Media Ltd",
    "wof:placetype":"venue"
},
  "geometry": {"coordinates":[0.1431200057,52.1982803345],"type":"Point"}
}