{
  "type": "Feature",
  "properties": {
    "iso:country":"GB",
    "sg:address":"30 Meadow Street",
    "sg:city":"Weston-super-mare",
    "sg:classifiers":[
        {
            "category":"Shopping",
            "subcategory":"Department Store",
            "type":"Retail Goods"
        },
        {
            "category":"Shopping",
            "subcategory":"Hobbies, Toys, & Games",
            "type":"Retail Goods"
        }
    ],
    "sg:phone":"+44 1934 614282",
    "sg:postcode":"BS23 1QQ",
    "sg:province":"Somerset",
    "sg:tags":[
        "shop"
    ],
    "wof:name":"Ncc Games",
    "wof:placetype":"venue"
},
  "geometry": {"coordinates":[-2.977296114,51.347984314],"type":"Point"}
}