{
  "type": "Feature",
  "properties": {
    "addr:full":"18 Hardy Rd Doncaster South Yorkshire DN2 4DW",
    "addr:housenumber":"18",
    "addr:postcode":"dn2 4dw",
    "addr:street":"Hardy Rd",
    "iso:country":"GB",
    "sg:address":"18 Hardy Rd",
    "sg:city":"Doncaster",
    "sg:classifiers":[
        {
            "category":"Autos & Motor Vehicles",
            "subcategory":"Boat Sales",
            "type":"Retail Goods"
        }
    ],
    "sg:postcode":"DN2 4DW",
    "sg:province":"South Yorkshire",
    "sg:tags":[
        "repair",
        "builder"
    ],
    "wof:name":"Twiby,Walter A,",
    "wof:placetype":"venue"
},
  "geometry": {"coordinates":[-1.119448,53.535412],"type":"Point"}
}