{
  "type": "Feature",
  "properties": {
    "iso:country":"GB",
    "sg:address":"Church Street",
    "sg:city":"Wetherby",
    "sg:classifiers":[
        {
            "category":"Manufacturing",
            "subcategory":"Textiles",
            "type":"Manufacturing & Wholesale Goods"
        }
    ],
    "sg:phone":"+44 1937 587661",
    "sg:postcode":"LS22 6LP",
    "sg:province":"North Yorkshire",
    "sg:tags":[
        "made-up"
    ],
    "wof:name":"Goggies Quality Home Textile",
    "wof:placetype":"venue"
},
  "geometry": {"coordinates":[-1.386454,53.929363],"type":"Point"}
}