{
  "type": "Feature",
  "properties": {
    "addr:full":"48 High Street Spennymoor Durham DL16 6DD",
    "addr:housenumber":"48",
    "addr:postcode":"dl16 6dd",
    "addr:street":"High Street",
    "iso:country":"GB",
    "sg:address":"48 High Street",
    "sg:city":"Spennymoor",
    "sg:classifiers":[
        {
            "category":"Shopping",
            "subcategory":"Optician",
            "type":"Retail Goods"
        }
    ],
    "sg:phone":"+44 1388 815482",
    "sg:postcode":"DL16 6DD",
    "sg:province":"Durham",
    "wof:name":"Walkers Opticians",
    "wof:placetype":"venue"
},
  "geometry": {"coordinates":[-1.6032910347,54.6982727051],"type":"Point"}
}