{
  "type": "Feature",
  "properties": {
    "iso:country":"GB",
    "sg:address":"123 Belle Vue Road",
    "sg:city":"Shrewsbury",
    "sg:classifiers":[
        {
            "category":"Shopping",
            "subcategory":"Used Merchandise",
            "type":"Retail Goods"
        }
    ],
    "sg:phone":"+44 1743 351324",
    "sg:postcode":"SY3 7NJ",
    "sg:province":"Shropshire",
    "sg:tags":[
        "shop",
        "second-hand"
    ],
    "wof:name":"Ancient & Modern",
    "wof:placetype":"venue"
},
  "geometry": {"coordinates":[-2.748939,52.69894],"type":"Point"}
}