{
  "type": "Feature",
  "properties": {
    "iso:country":"GB",
    "sg:address":"Elstree Way",
    "sg:city":"Borehamwood",
    "sg:classifiers":[
        {
            "category":"Shopping",
            "subcategory":"Computers & Home Electronics",
            "type":"Retail Goods"
        }
    ],
    "sg:phone":"+44 20 8236 0032",
    "sg:postcode":"WD6 1ND",
    "sg:province":"Hertfordshire",
    "sg:tags":[
        "equipment",
        "radio"
    ],
    "wof:name":"Standard Communications (UK)",
    "wof:placetype":"venue"
},
  "geometry": {"coordinates":[-0.256754,51.659546],"type":"Point"}
}