{
  "type": "Feature",
  "properties": {
    "iso:country":"GB",
    "sg:address":"26-28 St Johns Street",
    "sg:city":"Keswick",
    "sg:classifiers":[
        {
            "category":"Restaurant",
            "type":"Food & Drink"
        }
    ],
    "sg:phone":"+44 17687 72932",
    "sg:postcode":"CA12 5AS",
    "sg:province":"Cumbria",
    "wof:name":"St.John's Bisto Utiopa",
    "wof:placetype":"venue"
},
  "geometry": {"coordinates":[-3.135605,54.59988],"type":"Point"}
}