{
  "type": "Feature",
  "properties": {
    "addr:full":"Unit 49, Hollybank Crescent Southampton Hampshire SO45 5FZ",
    "addr:housenumber":"unit 49",
    "addr:postcode":"so45 5fz",
    "addr:street":"Hollybank Crescent",
    "iso:country":"GB",
    "sg:address":"Unit 49, Hollybank Crescent",
    "sg:city":"Southampton",
    "sg:classifiers":[
        {
            "category":"Building & Trades",
            "subcategory":"Construction",
            "type":"Services"
        }
    ],
    "sg:phone":"+44 23 8084 4134",
    "sg:postcode":"SO45 5FZ",
    "sg:province":"Hampshire",
    "sg:tags":[
        "roofing"
    ],
    "wof:name":"Bailey's",
    "wof:placetype":"venue"
},
  "geometry": {"coordinates":[-1.406011,50.867329],"type":"Point"}
}