{
  "type": "Feature",
  "properties": {
    "iso:country":"GB",
    "sg:address":"2 Calder Avenue",
    "sg:city":"Halifax",
    "sg:classifiers":[
        {
            "category":"Shopping",
            "subcategory":"News",
            "type":"Retail Goods"
        }
    ],
    "sg:postcode":"HX2 7DL",
    "sg:province":"West Yorkshire",
    "sg:tags":[
        "newsagent"
    ],
    "wof:name":"Scar Bottom Sub Post Office",
    "wof:placetype":"venue"
},
  "geometry": {"coordinates":[-1.8875290155,53.7131767273],"type":"Point"}
}