{
  "type": "Feature",
  "properties": {
    "addr:full":"Highwood Road, Gazeley Newmarket Cambridgeshire CB8 8RJ",
    "addr:postcode":"cb8 8rj",
    "addr:street":"Highwood Road",
    "iso:country":"GB",
    "sg:address":"Highwood Road, Gazeley",
    "sg:city":"Newmarket",
    "sg:classifiers":[
        {
            "category":"Banks & Credit Unions",
            "subcategory":"Bureau De Change",
            "type":"Services"
        },
        {
            "category":"Building & Trades",
            "subcategory":"Cleaning & Sanitation",
            "type":"Services"
        }
    ],
    "sg:phone":"+44 1638 750833",
    "sg:postcode":"CB8 8RJ",
    "sg:province":"Cambridgeshire",
    "sg:tags":[
        "hygiene",
        "commercial"
    ],
    "wof:name":"A B CLEANING SERVICES",
    "wof:placetype":"venue"
},
  "geometry": {"coordinates":[0.518404,52.246937],"type":"Point"}
}