{
  "type": "Feature",
  "properties": {
    "addr:full":"29 High Street Chesterfield Derbyshire S43 1HH",
    "addr:housenumber":"29",
    "addr:postcode":"s43 1hh",
    "addr:street":"High Street",
    "iso:country":"GB",
    "sg:address":"29 High Street",
    "sg:city":"Chesterfield",
    "sg:classifiers":[
        {
            "category":"Taxi",
            "type":"Transportation"
        }
    ],
    "sg:phone":"+44 1246 234133",
    "sg:postcode":"S43 1HH",
    "sg:province":"Derbyshire",
    "sg:tags":[
        "mini",
        "cab"
    ],
    "wof:name":"Brimington Private Hire",
    "wof:placetype":"venue"
},
  "geometry": {"coordinates":[-1.3941860199,53.2584724426],"type":"Point"}
}