{
  "type": "Feature",
  "properties": {
    "addr:full":"Hill Farm, Church Road, Wentworth Ely Cambridgeshire CB6 3QE",
    "addr:postcode":"cb6 3qe",
    "addr:street":"Hill;Church Road",
    "iso:country":"GB",
    "sg:address":"Hill Farm, Church Road, Wentworth",
    "sg:city":"Ely",
    "sg:classifiers":[
        {
            "category":"Home & Garden",
            "subcategory":"Garden Supply",
            "type":"Retail Goods"
        },
        {
            "category":"Farming",
            "subcategory":"Crops",
            "type":"Manufacturing & Wholesale Goods"
        },
        {
            "category":"Farming",
            "subcategory":"Livestock Farm",
            "type":"Manufacturing & Wholesale Goods"
        }
    ],
    "sg:phone":"+44 1353 778280",
    "sg:postcode":"CB6 3QE",
    "sg:province":"Cambridgeshire",
    "sg:tags":[
        "bulb",
        "arable",
        "grower",
        "others"
    ],
    "wof:name":"D J Langley",
    "wof:placetype":"venue"
},
  "geometry": {"coordinates":[0.174435,52.38509],"type":"Point"}
}