{
  "type": "Feature",
  "properties": {
    "iso:country":"GB",
    "sg:address":"Hill Farm, Priors Hardwick",
    "sg:city":"Rugby",
    "sg:classifiers":[
        {
            "category":"Farming",
            "subcategory":"Livestock Farm",
            "type":"Manufacturing & Wholesale Goods"
        }
    ],
    "sg:phone":"+44 1327 260338",
    "sg:postcode":"CV47 7SP",
    "sg:province":"Warwickshire",
    "sg:tags":[
        "others"
    ],
    "wof:name":"M Darbishire",
    "wof:placetype":"venue"
},
  "geometry": {"coordinates":[-1.312617,52.200699],"type":"Point"}
}