{
  "type": "Feature",
  "properties": {
    "addr:full":"Po Box 42 Elbow Street Cradley Heath West Midlands B64 6JS",
    "addr:housenumber":"po box 42",
    "addr:postcode":"b64 6js",
    "addr:street":"Elbow Street",
    "iso:country":"GB",
    "sg:address":"Po Box 42 Elbow Street",
    "sg:city":"Cradley Heath",
    "sg:classifiers":[
        {
            "category":"Professional",
            "subcategory":"Engineering",
            "type":"Services"
        }
    ],
    "sg:postcode":"B64 6JS",
    "sg:province":"West Midlands",
    "wof:name":"Benjamin Priest Ltd.",
    "wof:placetype":"venue"
},
  "geometry": {"coordinates":[-2.081574,52.472416],"type":"Point"}
}