{
  "type": "Feature",
  "properties": {
    "addr:full":"Sunnybrow Post Office, 1 Hunwick Lane Crook Durham DL15 0LT",
    "addr:housenumber":"1",
    "addr:postcode":"dl15 0lt",
    "addr:street":"Hunwick Lane",
    "iso:country":"GB",
    "sg:address":"Sunnybrow Post Office, 1 Hunwick Lane",
    "sg:city":"Crook",
    "sg:classifiers":[
        {
            "category":"Shopping",
            "subcategory":"Department Store",
            "type":"Retail Goods"
        }
    ],
    "sg:phone":"+44 1388 746238",
    "sg:postcode":"DL15 0LT",
    "sg:province":"Durham",
    "wof:name":"Sunnybrow Sub Post Office",
    "wof:placetype":"venue"
},
  "geometry": {"coordinates":[-1.7074240446,54.6869659424],"type":"Point"}
}