{
  "type": "Feature",
  "properties": {
    "iso:country":"GB",
    "sg:address":"101 Causewayend",
    "sg:city":"Aberdeen",
    "sg:classifiers":[
        {
            "category":"Building & Trades",
            "subcategory":"Plumbing",
            "type":"Services"
        },
        {
            "category":"Home & Garden",
            "subcategory":"Hardware",
            "type":"Retail Goods"
        }
    ],
    "sg:phone":"+44 1224 642594",
    "sg:postcode":"AB25 3TQ",
    "sg:province":"Aberdeen City",
    "sg:tags":[
        "merchant",
        "plumber",
        "plumbers'"
    ],
    "wof:name":"City Plumbing Supplies Ltd",
    "wof:placetype":"venue"
},
  "geometry": {"coordinates":[-2.115629,57.157925],"type":"Point"}
}