{
  "type": "Feature",
  "properties": {
    "addr:full":"99 Oxenhurst Grn Stockport Cheshire SK2 5PE",
    "addr:housenumber":"99",
    "addr:postcode":"sk2 5pe",
    "addr:street":"Oxenhurst Grn",
    "iso:country":"GB",
    "sg:address":"99 Oxenhurst Grn",
    "sg:city":"Stockport",
    "sg:classifiers":[
        {
            "category":"Social Services",
            "subcategory":"Retirement Home",
            "type":"Services"
        }
    ],
    "sg:postcode":"SK2 5PE",
    "sg:province":"Cheshire",
    "sg:tags":[
        "care"
    ],
    "wof:name":"Quality Care",
    "wof:placetype":"venue"
},
  "geometry": {"coordinates":[-2.1177461147,53.3919792175],"type":"Point"}
}