{
  "type": "Feature",
  "properties": {
    "iso:country":"GB",
    "sg:address":"48 Ware Road",
    "sg:city":"Hoddesdon",
    "sg:classifiers":[
        {
            "category":"Shopping",
            "subcategory":"Department Store",
            "type":"Retail Goods"
        }
    ],
    "sg:phone":"+44 1992 460399",
    "sg:postcode":"EN11 9DU",
    "sg:province":"Essex",
    "wof:name":"Omega Cycles",
    "wof:placetype":"venue"
},
  "geometry": {"coordinates":[-0.012433,51.767349],"type":"Point"}
}