{
  "type": "Feature",
  "properties": {
    "addr:full":"21 Birch Terrace, Hanley Stoke-on-trent Staffordshire ST1 3JN",
    "addr:housenumber":"21",
    "addr:postcode":"staffordshire st1 3jn",
    "addr:street":"Birch Terrace",
    "iso:country":"GB",
    "sg:address":"21 Birch Terrace, Hanley",
    "sg:city":"Stoke-on-trent",
    "sg:classifiers":[
        {
            "category":"Health Services",
            "subcategory":"Clinic",
            "type":"Services"
        }
    ],
    "sg:phone":"+44 1782 261708",
    "sg:postcode":"ST1 3JN",
    "sg:province":"Staffordshire",
    "sg:tags":[
        "private"
    ],
    "wof:name":"Health Therapy & Hair Treatment",
    "wof:placetype":"venue"
},
  "geometry": {"coordinates":[-2.1730709076,53.0230941772],"type":"Point"}
}