{
  "type": "Feature",
  "properties": {
    "iso:country":"GB",
    "sg:address":"7 Holbein Place",
    "sg:city":"London",
    "sg:classifiers":[
        {
            "category":"Organizations",
            "subcategory":"Non-profit Organization",
            "type":"Services"
        }
    ],
    "sg:phone":"+44 20 7591 6000",
    "sg:postcode":"SW1W 8NR",
    "sg:province":"Greater London",
    "sg:tags":[
        "organisation",
        "voluntary",
        "charity"
    ],
    "wof:name":"Heritage Lottery Fund",
    "wof:placetype":"venue"
},
  "geometry": {"coordinates":[-0.155959,51.492188],"type":"Point"}
}