{
  "type": "Feature",
  "properties": {
    "iso:country":"GB",
    "sg:address":"Health Centre, Central Av",
    "sg:city":"Ardrossan",
    "sg:classifiers":[
        {
            "category":"Health Services",
            "subcategory":"Doctor",
            "type":"Services"
        }
    ],
    "sg:phone":"+44 1294 463838",
    "sg:postcode":"KA22 7DX",
    "sg:province":"North Ayrshire",
    "sg:tags":[
        "practitioners"
    ],
    "wof:name":"Haggerty, G",
    "wof:placetype":"venue"
},
  "geometry": {"coordinates":[-4.8062,55.650921],"type":"Point"}
}