{
  "type": "Feature",
  "properties": {
    "addr:full":"16 The Quantocks Bedford Bedfordshire MK45 1TQ",
    "addr:housenumber":"16",
    "addr:postcode":"mk45 1tq",
    "addr:street":"The Quantocks",
    "iso:country":"GB",
    "sg:address":"16 The Quantocks",
    "sg:city":"Bedford",
    "sg:classifiers":[
        {
            "category":"Military Area",
            "subcategory":"Air Force Base",
            "type":"Public Place"
        }
    ],
    "sg:postcode":"MK45 1TQ",
    "sg:province":"Bedfordshire",
    "sg:tags":[
        "taxi",
        "hire",
        "private"
    ],
    "wof:name":"Elephant Taxis",
    "wof:placetype":"venue"
},
  "geometry": {"coordinates":[-0.5066120028,52.0025253296],"type":"Point"}
}