{
  "type": "Feature",
  "properties": {
    "iso:country":"GB",
    "sg:address":"87 West St",
    "sg:city":"Gravesend",
    "sg:classifiers":[
        {
            "category":"Retail",
            "subcategory":"Event Space",
            "type":"Services"
        }
    ],
    "sg:phone":"+44 1474 560675",
    "sg:postcode":"DA11 0BL",
    "sg:province":"Kent",
    "sg:tags":[
        "function",
        "room"
    ],
    "wof:name":"The New Falcon",
    "wof:placetype":"venue"
},
  "geometry": {"coordinates":[0.3683339953,51.4449119568],"type":"Point"}
}