{
  "type": "Feature",
  "properties": {
    "iso:country":"GB",
    "sg:address":"9 Lavender Walk",
    "sg:city":"Leeds",
    "sg:classifiers":[
        {
            "category":"Professional",
            "subcategory":"Art Services",
            "type":"Services"
        }
    ],
    "sg:phone":"+44 113 235 1363",
    "sg:postcode":"LS9 8JB",
    "sg:province":"West Yorkshire",
    "sg:tags":[
        "graphic",
        "designer"
    ],
    "wof:name":"Spiral Communications Ltd.",
    "wof:placetype":"venue"
},
  "geometry": {"coordinates":[-1.52227,53.795631],"type":"Point"}
}