{
  "type": "Feature",
  "properties": {
    "iso:country":"GB",
    "sg:address":"Tickhill Road, Maltby",
    "sg:city":"Rotherham",
    "sg:classifiers":[
        {
            "category":"Retail",
            "subcategory":"Auto Repair",
            "type":"Services"
        }
    ],
    "sg:phone":"+44 1709 816412",
    "sg:postcode":"S66 7PW",
    "sg:province":"South Yorkshire",
    "sg:tags":[
        "modification",
        "garage",
        "related"
    ],
    "wof:name":"Maltby Service Station",
    "wof:placetype":"venue"
},
  "geometry": {"coordinates":[-1.201234,53.423271],"type":"Point"}
}