{
  "type": "Feature",
  "properties": {
    "iso:country":"GB",
    "sg:address":"Keljony, First Lane, Wickersley",
    "sg:city":"Rotherham",
    "sg:classifiers":[
        {
            "category":"Building & Trades",
            "subcategory":"Construction",
            "type":"Services"
        }
    ],
    "sg:phone":"+44 1709 542328",
    "sg:postcode":"S66 1DU",
    "sg:province":"South Yorkshire",
    "sg:tags":[
        "decorator",
        "painter"
    ],
    "wof:name":"Gary Cox",
    "wof:placetype":"venue"
},
  "geometry": {"coordinates":[-1.278344,53.416145],"type":"Point"}
}