{
  "type": "Feature",
  "properties": {
    "iso:country":"GB",
    "sg:address":"121-131 New Union Street",
    "sg:city":"Coventry",
    "sg:classifiers":[
        {
            "category":"Real Estate",
            "subcategory":"Real Estate Agent",
            "type":"Services"
        }
    ],
    "sg:phone":"+44 24 7625 6616",
    "sg:postcode":"CV1 2NT",
    "sg:province":"West Midlands",
    "wof:name":"Cartwright Marsdon",
    "wof:placetype":"venue"
},
  "geometry": {"coordinates":[-1.510446,52.404964],"type":"Point"}
}