{
  "type": "Feature",
  "properties": {
    "addr:full":"Unit 1, 27 Burwash Rd Hove East Sussex BN3 8GQ",
    "addr:housenumber":"unit;27",
    "addr:postcode":"bn3 8gq",
    "addr:street":"Burwash Rd",
    "iso:country":"GB",
    "sg:address":"Unit 1, 27 Burwash Rd",
    "sg:city":"Hove",
    "sg:classifiers":[
        {
            "category":"Retail",
            "subcategory":"Auto Repair",
            "type":"Services"
        }
    ],
    "sg:phone":"+44 1273 771136",
    "sg:postcode":"BN3 8GQ",
    "sg:province":"East Sussex",
    "sg:tags":[
        "car",
        "upholsterer"
    ],
    "wof:name":"Valeting Services",
    "wof:placetype":"venue"
},
  "geometry": {"coordinates":[-0.1911209971,50.8513145447],"type":"Point"}
}