{
  "type": "Feature",
  "properties": {
    "addr:full":"Bank Top, Bishop Middleham Ferryhill Durham DL17 9AW",
    "addr:postcode":"dl17 9aw",
    "addr:street":"Top Bishop Middleham",
    "iso:country":"GB",
    "sg:address":"Bank Top, Bishop Middleham",
    "sg:city":"Ferryhill",
    "sg:classifiers":[
        {
            "category":"Bars & Pubs",
            "type":"Food & Drink"
        }
    ],
    "sg:postcode":"DL17 9AW",
    "sg:province":"Durham",
    "sg:tags":[
        "pubs",
        "inn"
    ],
    "wof:name":"Ye Olde Fleece Inn",
    "wof:placetype":"venue"
},
  "geometry": {"coordinates":[-1.491667,54.677486],"type":"Point"}
}