{
  "type": "Feature",
  "properties": {
    "addr:full":"Unit 1 Chandlers Yard, Bobbers Mill Nottingham Nottinghamshire NG8 5AD",
    "addr:housenumber":"unit 1",
    "addr:postcode":"ng8 5ad",
    "addr:street":"Chandlers Yard Bobbers Mill",
    "iso:country":"GB",
    "sg:address":"Unit 1 Chandlers Yard, Bobbers Mill",
    "sg:city":"Nottingham",
    "sg:classifiers":[
        {
            "category":"Communications",
            "subcategory":"Film & Video Production",
            "type":"Services"
        }
    ],
    "sg:phone":"+44 115 942 2668",
    "sg:postcode":"NG8 5AD",
    "sg:province":"Nottinghamshire",
    "sg:tags":[
        "tv",
        "studio"
    ],
    "wof:name":"Unit One Tv And Video Services",
    "wof:placetype":"venue"
},
  "geometry": {"coordinates":[-1.1817,52.967991],"type":"Point"}
}