{
  "type": "Feature",
  "properties": {
    "addr:full":"7 Whins Close Camberley Berkshire GU15 3NW",
    "addr:housenumber":"7",
    "addr:postcode":"gu15 3nw",
    "addr:street":"Whins Close",
    "iso:country":"GB",
    "sg:address":"7 Whins Close",
    "sg:city":"Camberley",
    "sg:classifiers":[
        {
            "category":"Building & Trades",
            "subcategory":"Construction",
            "type":"Services"
        }
    ],
    "sg:postcode":"GU15 3NW",
    "sg:province":"Berkshire",
    "sg:tags":[
        "builder"
    ],
    "wof:name":"Building Contractors T M",
    "wof:placetype":"venue"
},
  "geometry": {"coordinates":[-0.753015995,51.3310813904],"type":"Point"}
}