{
  "type": "Feature",
  "properties": {
    "addr:full":"21 Tennant Street Edinburgh City of Edinburgh EH6 5NA",
    "addr:housenumber":"21",
    "addr:postcode":"eh6 5na",
    "addr:street":"Tennant Street",
    "iso:country":"GB",
    "sg:address":"21 Tennant Street",
    "sg:city":"Edinburgh",
    "sg:classifiers":[
        {
            "category":"Professional",
            "subcategory":"Printing & Photocopies",
            "type":"Services"
        }
    ],
    "sg:phone":"+44 131 554 2431",
    "sg:postcode":"EH6 5NA",
    "sg:province":"City of Edinburgh",
    "sg:tags":[
        "printer"
    ],
    "wof:name":"Nimmos Colour Printers Ltd.",
    "wof:placetype":"venue"
},
  "geometry": {"coordinates":[-3.1771459579,55.9706077576],"type":"Point"}
}