{
  "type": "Feature",
  "properties": {
    "addr:full":"4 St Mary Street Chepstow Gloucestershire NP16 5EU",
    "addr:housenumber":"4",
    "addr:postcode":"np16 5eu",
    "addr:street":"St Mary Street",
    "iso:country":"GB",
    "sg:address":"4 St Mary Street",
    "sg:city":"Chepstow",
    "sg:classifiers":[
        {
            "category":"Shopping",
            "subcategory":"Clothing, Apparel, & Fashions",
            "type":"Retail Goods"
        }
    ],
    "sg:phone":"+44 1291 628585",
    "sg:postcode":"NP16 5EU",
    "sg:province":"Gloucestershire",
    "sg:tags":[
        "shop"
    ],
    "wof:name":"Earthquake",
    "wof:placetype":"venue"
},
  "geometry": {"coordinates":[-2.674186945,51.6422042847],"type":"Point"}
}