{
  "type": "Feature",
  "properties": {
    "addr:full":"The Barn Ho, Lidget La, Bramley Rotherham South Yorkshire S65 4LY",
    "addr:postcode":"s65 4ly",
    "addr:street":"Lidget;Rotherham South",
    "iso:country":"GB",
    "sg:address":"The Barn Ho, Lidget La, Bramley",
    "sg:city":"Rotherham",
    "sg:classifiers":[
        {
            "category":"Building & Trades",
            "subcategory":"Construction",
            "type":"Services"
        }
    ],
    "sg:postcode":"S65 4LY",
    "sg:province":"South Yorkshire",
    "sg:tags":[
        "decorator",
        "painter"
    ],
    "wof:name":"Lee,Wayne,",
    "wof:placetype":"venue"
},
  "geometry": {"coordinates":[-1.266979,53.437851],"type":"Point"}
}