{
  "type": "Feature",
  "properties": {
    "addr:full":"37 Mayfair Ho, New Mkt Sq Basingstoke Hampshire RG21 1RG",
    "addr:housenumber":"37",
    "addr:postcode":"rg21 1rg",
    "addr:street":"Mayfair Ho New Mkt Sq",
    "iso:country":"GB",
    "sg:address":"37 Mayfair Ho, New Mkt Sq",
    "sg:city":"Basingstoke",
    "sg:classifiers":[
        {
            "category":"Shopping",
            "subcategory":"Gifts & Souvenirs",
            "type":"Retail Goods"
        }
    ],
    "sg:postcode":"RG21 1RG",
    "sg:province":"Hampshire",
    "sg:tags":[
        "shop"
    ],
    "wof:name":"Dev,Sandy,",
    "wof:placetype":"venue"
},
  "geometry": {"coordinates":[-1.083088994,51.2624435425],"type":"Point"}
}