{
  "type": "Feature",
  "properties": {
    "iso:country":"GB",
    "sg:address":"2 Boston Avenue",
    "sg:city":"Runcorn",
    "sg:classifiers":[
        {
            "category":"Bars & Pubs",
            "type":"Food & Drink"
        }
    ],
    "sg:phone":"+44 1928 564024",
    "sg:postcode":"WA7 5JQ",
    "sg:province":"Cheshire",
    "sg:tags":[
        "pubs",
        "inn"
    ],
    "wof:name":"The Red Admiral",
    "wof:placetype":"venue"
},
  "geometry": {"coordinates":[-2.717312,53.33337],"type":"Point"}
}