{
  "type": "Feature",
  "properties": {
    "iso:country":"GB",
    "sg:address":"123 Gloucester Rd",
    "sg:city":"Cheltenham",
    "sg:classifiers":[
        {
            "category":"Taxi",
            "type":"Transportation"
        }
    ],
    "sg:phone":"+44 1242 692900",
    "sg:postcode":"GL51 8NG",
    "sg:province":"Gloucestershire",
    "sg:tags":[
        "mini",
        "cab"
    ],
    "wof:name":"Airport Express",
    "wof:placetype":"venue"
},
  "geometry": {"coordinates":[-2.093992,51.900829],"type":"Point"}
}