{
  "type": "Feature",
  "properties": {
    "iso:country":"GB",
    "sg:address":"3 Guinea Street",
    "sg:city":"Exeter",
    "sg:classifiers":[
        {
            "category":"Retail",
            "subcategory":"Laundry & Dry Cleaning",
            "type":"Services"
        }
    ],
    "sg:postcode":"EX1 1BS",
    "sg:province":"Devon",
    "sg:tags":[
        "alteration"
    ],
    "wof:name":"Express Alteration Tailoring",
    "wof:placetype":"venue"
},
  "geometry": {"coordinates":[-3.532576,50.721371],"type":"Point"}
}