{
  "type": "Feature",
  "properties": {
    "iso:country":"GB",
    "sg:address":"45 Chase Side",
    "sg:city":"London",
    "sg:classifiers":[
        {
            "category":"Professional",
            "subcategory":"Art Services",
            "type":"Services"
        }
    ],
    "sg:postcode":"N14 5BP",
    "sg:province":"Greater London",
    "sg:tags":[
        "stone",
        "restoration",
        "cleaning"
    ],
    "wof:name":"Mead Construction Ltd.",
    "wof:placetype":"venue"
},
  "geometry": {"coordinates":[-0.13038,51.633015],"type":"Point"}
}