{
  "type": "Feature",
  "properties": {
    "iso:country":"GB",
    "sg:address":"Butchers Market, High Street",
    "sg:city":"Wrexham",
    "sg:classifiers":[
        {
            "category":"Professional",
            "subcategory":"Art Services",
            "type":"Services"
        }
    ],
    "sg:postcode":"LL13 8HP",
    "sg:province":"Wrexham",
    "sg:tags":[
        "framing"
    ],
    "wof:name":"Pambow of Wrexham",
    "wof:placetype":"venue"
},
  "geometry": {"coordinates":[-2.9971289635,53.0419540405],"type":"Point"}
}