{
  "type": "Feature",
  "properties": {
    "iso:country":"GB",
    "sg:address":"164 Elm High Road, Elm",
    "sg:city":"Wisbech",
    "sg:classifiers":[
        {
            "category":"Professional",
            "subcategory":"Management & Consulting",
            "type":"Services"
        }
    ],
    "sg:phone":"+44 1945 474640",
    "sg:postcode":"PE14 0DP",
    "sg:province":"Cambridgeshire",
    "sg:tags":[
        "consultant",
        "business"
    ],
    "wof:name":"Christine Joan Morton",
    "wof:placetype":"venue"
},
  "geometry": {"coordinates":[0.175663,52.645298],"type":"Point"}
}