{
  "type": "Feature",
  "properties": {
    "iso:country":"GB",
    "sg:address":"13 Meneage Road",
    "sg:city":"Helston",
    "sg:classifiers":[
        {
            "category":"Shopping",
            "subcategory":"Bicycles & Sporting Goods",
            "type":"Retail Goods"
        }
    ],
    "sg:phone":"+44 1326 564564",
    "sg:postcode":"TR13 8BQ",
    "sg:province":"Cornwall",
    "sg:tags":[
        "cycle",
        "accessory"
    ],
    "wof:name":"Peter Johnson-Pollie",
    "wof:placetype":"venue"
},
  "geometry": {"coordinates":[-5.2677397728,50.0950622559],"type":"Point"}
}