{
  "type": "Feature",
  "properties": {
    "iso:country":"GB",
    "sg:address":"3 Lakeside View, Great Georges Road",
    "sg:city":"Liverpool",
    "sg:classifiers":[
        {
            "category":"Retail",
            "subcategory":"Auto Rental",
            "type":"Services"
        },
        {
            "category":"Autos & Motor Vehicles",
            "subcategory":"Motorcycle Sales",
            "type":"Retail Goods"
        }
    ],
    "sg:phone":"+44 151 928 7091",
    "sg:postcode":"L22 5QN",
    "sg:province":"Merseyside",
    "sg:tags":[
        "chauffeur",
        "driven",
        "hire",
        "car"
    ],
    "wof:name":"Full Stretch Limousines",
    "wof:placetype":"venue"
},
  "geometry": {"coordinates":[-3.02707,53.47131],"type":"Point"}
}