{
  "type": "Feature",
  "properties": {
    "addr:full":"11 Freeland Road London Greater London W5 3HR",
    "addr:housenumber":"11",
    "addr:postcode":"w5 3hr",
    "addr:street":"Freeland Road",
    "iso:country":"GB",
    "sg:address":"11 Freeland Road",
    "sg:city":"London",
    "sg:classifiers":[
        {
            "category":"Building & Trades",
            "subcategory":"Plumbing",
            "type":"Services"
        }
    ],
    "sg:phone":"+44 20 8992 7652",
    "sg:postcode":"W5 3HR",
    "sg:province":"Greater London",
    "sg:tags":[
        "heating"
    ],
    "wof:name":"Peter Joseph Lowery",
    "wof:placetype":"venue"
},
  "geometry": {"coordinates":[-0.2905780077,51.5130882263],"type":"Point"}
}