{
  "type": "Feature",
  "properties": {
    "addr:full":"10 Finchfield Road West, Finchfield Wolverhampton Staffordshire WV3 8AZ",
    "addr:housenumber":"10",
    "addr:postcode":"wv3 8az",
    "addr:street":"Finchfield Road West Finchfield",
    "iso:country":"GB",
    "sg:address":"10 Finchfield Road West, Finchfield",
    "sg:city":"Wolverhampton",
    "sg:classifiers":[
        {
            "category":"Shopping",
            "subcategory":"News",
            "type":"Retail Goods"
        }
    ],
    "sg:phone":"+44 1902 762484",
    "sg:postcode":"WV3 8AZ",
    "sg:province":"Staffordshire",
    "sg:tags":[
        "newsagent"
    ],
    "wof:name":"Stars News Shops",
    "wof:placetype":"venue"
},
  "geometry": {"coordinates":[-2.172092,52.580429],"type":"Point"}
}