{
  "type": "Feature",
  "properties": {
    "iso:country":"GB",
    "sg:address":"567 Garratt Lane",
    "sg:city":"London",
    "sg:classifiers":[
        {
            "category":"Wholesale",
            "subcategory":"Fruits & Vegetables",
            "type":"Manufacturing & Wholesale Goods"
        }
    ],
    "sg:phone":"+44 20 8947 7096",
    "sg:postcode":"SW18 2AF",
    "sg:province":"Greater London",
    "wof:name":"Morning Fresh Produce",
    "wof:placetype":"venue"
},
  "geometry": {"coordinates":[-0.1867790073,51.4405212402],"type":"Point"}
}