{
  "type": "Feature",
  "properties": {
    "addr:full":"Unit 4, Home Farm, Slugwash La Haywards Heath East Sussex RH17 7RQ",
    "addr:housenumber":"unit 4",
    "addr:postcode":"rh17 7rq",
    "addr:street":"Home;Slugwash La Haywards",
    "iso:country":"GB",
    "sg:address":"Unit 4, Home Farm, Slugwash La",
    "sg:city":"Haywards Heath",
    "sg:classifiers":[
        {
            "category":"Professional",
            "type":"Services"
        }
    ],
    "sg:phone":"+44 1444 443223",
    "sg:postcode":"RH17 7RQ",
    "sg:province":"East Sussex",
    "sg:tags":[
        "specialist",
        "coating"
    ],
    "wof:name":"Commercial Protective Systems Ltd",
    "wof:placetype":"venue"
},
  "geometry": {"coordinates":[-0.07297,50.983292],"type":"Point"}
}