{
  "type": "Feature",
  "properties": {
    "addr:full":"173a Preston New Road Southport Lancashire PR9 8NS",
    "addr:housenumber":"173a",
    "addr:postcode":"pr9 8ns",
    "addr:street":"Preston New Road",
    "iso:country":"GB",
    "sg:address":"173a Preston New Road",
    "sg:city":"Southport",
    "sg:classifiers":[
        {
            "category":"Personal",
            "subcategory":"Beauty Salon",
            "type":"Services"
        }
    ],
    "sg:postcode":"PR9 8NS",
    "sg:province":"Lancashire",
    "wof:name":"X L Beauty",
    "wof:placetype":"venue"
},
  "geometry": {"coordinates":[-2.957245,53.67049],"type":"Point"}
}