{
  "type": "Feature",
  "properties": {
    "addr:full":"26-28 Brick Lane London Greater London E1 6RF",
    "addr:housenumber":"26-28",
    "addr:postcode":"e1 6rf",
    "addr:street":"Brick Lane",
    "iso:country":"GB",
    "sg:address":"26-28 Brick Lane",
    "sg:city":"London",
    "sg:classifiers":[
        {
            "category":"Shopping",
            "subcategory":"Clothing, Apparel, & Fashions",
            "type":"Retail Goods"
        }
    ],
    "sg:phone":"+44 20 7247 4040",
    "sg:postcode":"E1 6RF",
    "sg:province":"Greater London",
    "sg:tags":[
        "ladieswear"
    ],
    "wof:name":"Modern Saree Centre",
    "wof:placetype":"venue"
},
  "geometry": {"coordinates":[-0.0714820027,51.5182189941],"type":"Point"}
}