{
  "type": "Feature",
  "properties": {
    "iso:country":"GB",
    "sg:address":"79 Oxford Street",
    "sg:city":"London",
    "sg:classifiers":[
        {
            "category":"Food & Beverages",
            "subcategory":"Bakery",
            "type":"Retail Goods"
        }
    ],
    "sg:phone":"+44 20 7734 4534",
    "sg:postcode":"W1D 2ES",
    "sg:province":"Greater London",
    "sg:tags":[
        "pizza"
    ],
    "wof:name":"Pizza Hut",
    "wof:placetype":"venue"
},
  "geometry": {"coordinates":[-0.1346089989,51.5160598755],"type":"Point"}
}