{
  "type": "Feature",
  "properties": {
    "addr:full":"15 Ivy Road Kettering Northamptonshire NN16 9TQ",
    "addr:housenumber":"15",
    "addr:postcode":"nn16 9tq",
    "addr:street":"Ivy Road",
    "iso:country":"GB",
    "sg:address":"15 Ivy Road",
    "sg:city":"Kettering",
    "sg:classifiers":[
        {
            "category":"Building & Trades",
            "subcategory":"Construction",
            "type":"Services"
        }
    ],
    "sg:phone":"+44 1536 485886",
    "sg:postcode":"NN16 9TQ",
    "sg:province":"Northamptonshire",
    "sg:tags":[
        "glazier",
        "decorator",
        "painter"
    ],
    "wof:name":"John Brian Sirrell",
    "wof:placetype":"venue"
},
  "geometry": {"coordinates":[-0.708236,52.409641],"type":"Point"}
}