{
  "type": "Feature",
  "properties": {
    "iso:country":"GB",
    "sg:address":"Unit 8 Earlsway Park, Team Valley Trading Estate",
    "sg:city":"Gateshead",
    "sg:classifiers":[
        {
            "category":"Freight",
            "type":"Transportation"
        }
    ],
    "sg:phone":"+44 191 482 2200",
    "sg:postcode":"NE11 0RY",
    "sg:province":"Tyne and Wear",
    "sg:tags":[
        "haulage",
        "road"
    ],
    "wof:name":"Eley Brothers Warehousing",
    "wof:placetype":"venue"
},
  "geometry": {"coordinates":[-1.6227289438,54.9453735352],"type":"Point"}
}