{
  "type": "Feature",
  "properties": {
    "addr:full":"P O Box 44 Liverpool Lancashire L37 0AS",
    "addr:housenumber":"box 44",
    "addr:postcode":"l37 0as",
    "addr:street":"P O",
    "iso:country":"GB",
    "sg:address":"P O Box 44",
    "sg:city":"Liverpool",
    "sg:classifiers":[
        {
            "category":"Retail",
            "subcategory":"Event Space",
            "type":"Services"
        }
    ],
    "sg:phone":"+44 1704 877324",
    "sg:postcode":"L37 0AS",
    "sg:province":"Lancashire",
    "sg:tags":[
        "exhibition",
        "organiser"
    ],
    "wof:name":"Showground Uk Ltd",
    "wof:placetype":"venue"
},
  "geometry": {"coordinates":[-3.04065,53.570999],"type":"Point"}
}