{
  "type": "Feature",
  "properties": {
    "iso:country":"GB",
    "sg:address":"Development House, Rood End Road",
    "sg:city":"Oldbury",
    "sg:classifiers":[
        {
            "category":"Professional",
            "subcategory":"Engineering",
            "type":"Services"
        }
    ],
    "sg:phone":"+44 121 544 5575",
    "sg:postcode":"B69 4HW",
    "sg:province":"West Midlands",
    "sg:tags":[
        "consulting",
        "engineer"
    ],
    "wof:name":"Gibb Ltd",
    "wof:placetype":"venue"
},
  "geometry": {"coordinates":[-1.998533,52.499252],"type":"Point"}
}