{
  "type": "Feature",
  "properties": {
    "iso:country":"GB",
    "sg:address":"Unit 4 Moston Indoor Market, Hartley Street",
    "sg:city":"Manchester",
    "sg:classifiers":[
        {
            "category":"Manufacturing",
            "subcategory":"Jewelry",
            "type":"Manufacturing & Wholesale Goods"
        }
    ],
    "sg:postcode":"M40 9NR",
    "sg:province":"Greater Manchester",
    "sg:tags":[
        "repair",
        "jewellery"
    ],
    "wof:name":"Dawn's Jewellery Repair Centre",
    "wof:placetype":"venue"
},
  "geometry": {"coordinates":[-2.1988799572,53.5134811401],"type":"Point"}
}