{
  "type": "Feature",
  "properties": {
    "addr:full":"Easter Beltie Ho, Glassel Banchory Aberdeen City AB31 4DT",
    "addr:postcode":"ab31 4dt",
    "addr:street":"Beltie;Glassel",
    "iso:country":"GB",
    "sg:address":"Easter Beltie Ho, Glassel",
    "sg:city":"Banchory",
    "sg:classifiers":[
        {
            "category":"Manufacturing",
            "subcategory":"Tools & Machinery",
            "type":"Manufacturing & Wholesale Goods"
        }
    ],
    "sg:postcode":"AB31 4DT",
    "sg:province":"Aberdeen City",
    "sg:tags":[
        "society",
        "friendly"
    ],
    "wof:name":"Keith,R A,",
    "wof:placetype":"venue"
},
  "geometry": {"coordinates":[-2.5697889328,57.0856933594],"type":"Point"}
}