{
  "type": "Feature",
  "properties": {
    "addr:full":"44b Bird In Bush Road London Greater London SE15 6RW",
    "addr:housenumber":"44b",
    "addr:postcode":"se15 6rw",
    "addr:street":"Bird In Bush Road",
    "iso:country":"GB",
    "sg:address":"44b Bird In Bush Road",
    "sg:city":"London",
    "sg:classifiers":[
        {
            "category":"Retail",
            "subcategory":"Storage",
            "type":"Services"
        }
    ],
    "sg:postcode":"SE15 6RW",
    "sg:province":"Greater London",
    "sg:tags":[
        "household",
        "removal"
    ],
    "wof:name":"Lamo Removal Services",
    "wof:placetype":"venue"
},
  "geometry": {"coordinates":[-0.069479,51.479912],"type":"Point"}
}