{
  "type": "Feature",
  "properties": {
    "addr:full":"350-372 Streatham High Road London Greater London SW16 6HP",
    "addr:housenumber":"350-372",
    "addr:postcode":"sw16 6hp",
    "addr:street":"Streatham High Road",
    "iso:country":"GB",
    "sg:address":"350-372 Streatham High Road",
    "sg:city":"London",
    "sg:classifiers":[
        {
            "category":"Food & Beverages",
            "subcategory":"Supermarket",
            "type":"Retail Goods"
        }
    ],
    "sg:phone":"+44 20 8769 0691",
    "sg:postcode":"SW16 6HP",
    "sg:province":"Greater London",
    "wof:name":"Safeway Stores Ltd.",
    "wof:placetype":"venue"
},
  "geometry": {"coordinates":[-0.13104,51.42569],"type":"Point"}
}