{
  "type": "Feature",
  "properties": {
    "iso:country":"GB",
    "sg:address":"2 Embankment Road",
    "sg:city":"Kingsbridge",
    "sg:classifiers":[
        {
            "category":"Military Area",
            "subcategory":"Air Force Base",
            "type":"Public Place"
        }
    ],
    "sg:phone":"+44 1548 856120",
    "sg:postcode":"TQ7 1JZ",
    "sg:province":"Devon",
    "sg:tags":[
        "taxi",
        "hire",
        "private"
    ],
    "wof:name":"Arrow Car Taxis",
    "wof:placetype":"venue"
},
  "geometry": {"coordinates":[-3.773602,50.279453],"type":"Point"}
}