{
  "type": "Feature",
  "properties": {
    "addr:full":"195-201 Wellingborough Road Northampton Northamptonshire NN1 4AT",
    "addr:postcode":"195-201;nn1 4at",
    "addr:street":"Wellingborough Road",
    "iso:country":"GB",
    "sg:address":"195-201 Wellingborough Road",
    "sg:city":"Northampton",
    "sg:classifiers":[
        {
            "category":"Home & Garden",
            "subcategory":"Furniture",
            "type":"Retail Goods"
        }
    ],
    "sg:postcode":"NN1 4AT",
    "sg:province":"Northamptonshire",
    "wof:name":"Parsonson Brothers Ltd.",
    "wof:placetype":"venue"
},
  "geometry": {"coordinates":[-0.878555,52.241779],"type":"Point"}
}