{
  "type": "Feature",
  "properties": {
    "iso:country":"GB",
    "sg:address":"2 Pullman Court, Great Western Road",
    "sg:city":"Gloucester",
    "sg:classifiers":[
        {
            "category":"Building & Trades",
            "subcategory":"Construction",
            "type":"Services"
        }
    ],
    "sg:postcode":"GL1 3ND",
    "sg:province":"Gloucestershire",
    "sg:tags":[
        "builder"
    ],
    "wof:name":"Britannia Builders Ltd",
    "wof:placetype":"venue"
},
  "geometry": {"coordinates":[-2.249624,51.863811],"type":"Point"}
}