{
  "type": "Feature",
  "properties": {
    "iso:country":"GB",
    "sg:address":"Unit 4 Moston Road, Millbuck Industrial Estate",
    "sg:city":"Sandbach",
    "sg:classifiers":[
        {
            "category":"Wholesale",
            "subcategory":"Machinery & Supplies",
            "type":"Manufacturing & Wholesale Goods"
        }
    ],
    "sg:phone":"+44 1270 765911",
    "sg:postcode":"CW11 9HT",
    "sg:province":"Cheshire",
    "sg:tags":[
        "industrial",
        "commercial"
    ],
    "wof:name":"Colorbatch Ltd.",
    "wof:placetype":"venue"
},
  "geometry": {"coordinates":[-2.3636479378,53.1422080994],"type":"Point"}
}