{
  "type": "Feature",
  "properties": {
    "addr:full":"60a Highertown, Truro Cornwall TR1 3QA",
    "addr:housenumber":"60a",
    "addr:postcode":"tr1 3qa",
    "addr:street":"Highertown",
    "iso:country":"GB",
    "sg:address":"60a Highertown,",
    "sg:city":"Truro",
    "sg:classifiers":[
        {
            "category":"Building & Trades",
            "subcategory":"Pest Control",
            "type":"Services"
        }
    ],
    "sg:postcode":"TR1 3QA",
    "sg:province":"Cornwall",
    "sg:tags":[
        "woodworm"
    ],
    "wof:name":"Pestatak Services (S W) Ltd",
    "wof:placetype":"venue"
},
  "geometry": {"coordinates":[-5.07563,50.261826],"type":"Point"}
}