{
  "type": "Feature",
  "properties": {
    "addr:full":"Flat F 12 Eastcroft, Rutherglen Glasgow Glasgow City G73 3AH",
    "addr:housenumber":"flat f 12",
    "addr:postcode":"g73 3ah",
    "addr:street":"Eastcroft",
    "iso:country":"GB",
    "sg:address":"Flat F 12 Eastcroft, Rutherglen",
    "sg:city":"Glasgow",
    "sg:classifiers":[
        {
            "category":"Social Services",
            "subcategory":"Adult Care",
            "type":"Services"
        }
    ],
    "sg:phone":"+44 141 647 9718",
    "sg:postcode":"G73 3AH",
    "sg:province":"Glasgow City",
    "sg:tags":[
        "housing",
        "sheltered"
    ],
    "wof:name":"Eastcroft Sheltered Housing",
    "wof:placetype":"venue"
},
  "geometry": {"coordinates":[-4.20726,55.828789],"type":"Point"}
}