{
  "type": "Feature",
  "properties": {
    "iso:country":"GB",
    "sg:address":"94 Ormskirk Rd",
    "sg:city":"St Helens",
    "sg:classifiers":[
        {
            "category":"Home & Garden",
            "subcategory":"Hardware",
            "type":"Retail Goods"
        }
    ],
    "sg:postcode":"WA11 8JD",
    "sg:province":"Lancashire",
    "sg:tags":[
        "retailer",
        "diy"
    ],
    "wof:name":"The Home & Garden Emporium",
    "wof:placetype":"venue"
},
  "geometry": {"coordinates":[-2.793095,53.50563],"type":"Point"}
}