{
  "type": "Feature",
  "properties": {
    "iso:country":"GB",
    "sg:address":"20 Copper Tree Court",
    "sg:city":"Maidstone",
    "sg:classifiers":[
        {
            "category":"Manufacturing",
            "subcategory":"Tools & Machinery",
            "type":"Manufacturing & Wholesale Goods"
        }
    ],
    "sg:phone":"+44 1622 747121",
    "sg:postcode":"ME15 9RW",
    "sg:province":"Kent",
    "sg:tags":[
        "society",
        "friendly"
    ],
    "wof:name":"Dyer & Holmes Motorcycles Insurance Consultants",
    "wof:placetype":"venue"
},
  "geometry": {"coordinates":[0.5218750238,51.2424697876],"type":"Point"}
}