{
  "type": "Feature",
  "properties": {
    "iso:country":"GB",
    "sg:address":"169 St Andrews Drive",
    "sg:city":"Fraserburgh",
    "sg:classifiers":[
        {
            "category":"Military Area",
            "subcategory":"Air Force Base",
            "type":"Public Place"
        }
    ],
    "sg:phone":"+44 1346 511211",
    "sg:postcode":"AB43 9BG",
    "sg:province":"Aberdeenshire",
    "sg:tags":[
        "taxi",
        "hire",
        "private"
    ],
    "wof:name":"Sanlen Taxis",
    "wof:placetype":"venue"
},
  "geometry": {"coordinates":[-2.0237429142,57.6880493164],"type":"Point"}
}