{
  "type": "Feature",
  "properties": {
    "addr:full":"Hill View, Whirley Lane, Henbury Macclesfield Cheshire SK10 4RL",
    "addr:postcode":"sk10 4rl",
    "addr:street":"Whirley Lane",
    "iso:country":"GB",
    "sg:address":"Hill View, Whirley Lane, Henbury",
    "sg:city":"Macclesfield",
    "sg:classifiers":[
        {
            "category":"Home & Garden",
            "subcategory":"Building Materials",
            "type":"Retail Goods"
        },
        {
            "category":"Building & Trades",
            "subcategory":"Construction",
            "type":"Services"
        },
        {
            "category":"Manufacturing",
            "subcategory":"Furniture",
            "type":"Manufacturing & Wholesale Goods"
        }
    ],
    "sg:phone":"+44 1625 422476",
    "sg:postcode":"SK10 4RL",
    "sg:province":"Cheshire",
    "sg:tags":[
        "wooden",
        "joinery",
        "door",
        "barrier",
        "gate"
    ],
    "wof:name":"Home Timber Products Ltd",
    "wof:placetype":"venue"
},
  "geometry": {"coordinates":[-2.1821699142,53.2682189941],"type":"Point"}
}