{
  "type": "Feature",
  "properties": {
    "addr:full":"No1 The Highway Beaconsfield Buckinghamshire HP9 1QD",
    "addr:postcode":"hp9 1qd",
    "addr:street":"The Highway",
    "iso:country":"GB",
    "sg:address":"No1 The Highway",
    "sg:city":"Beaconsfield",
    "sg:classifiers":[
        {
            "category":"Professional",
            "subcategory":"Art Services",
            "type":"Services"
        }
    ],
    "sg:postcode":"HP9 1QD",
    "sg:province":"Buckinghamshire",
    "sg:tags":[
        "consultant",
        "design"
    ],
    "wof:name":"Milestone Strategic Design Ltd.",
    "wof:placetype":"venue"
},
  "geometry": {"coordinates":[-0.647023,51.61187],"type":"Point"}
}