{
  "type": "Feature",
  "properties": {
    "iso:country":"GB",
    "sg:address":"Station Road, Ranskill",
    "sg:city":"Retford",
    "sg:classifiers":[
        {
            "category":"Manufacturing",
            "subcategory":"Lumber",
            "type":"Manufacturing & Wholesale Goods"
        }
    ],
    "sg:postcode":"DN22 8LU",
    "sg:province":"Nottinghamshire",
    "sg:tags":[
        "importer",
        "merchants",
        "agent",
        "timber"
    ],
    "wof:name":"Walter Millington (Timber Merchants)",
    "wof:placetype":"venue"
},
  "geometry": {"coordinates":[-1.013329,53.384106],"type":"Point"}
}