{
  "type": "Feature",
  "properties": {
    "iso:country":"GB",
    "sg:address":"18 Lawton Road, Alsager",
    "sg:city":"Stoke-on-trent",
    "sg:classifiers":[
        {
            "category":"Shopping",
            "subcategory":"Clothing, Apparel, & Fashions",
            "type":"Retail Goods"
        }
    ],
    "sg:phone":"+44 1270 872792",
    "sg:postcode":"ST7 2AF",
    "sg:province":"Cheshire",
    "sg:tags":[
        "shop"
    ],
    "wof:name":"Top Cats",
    "wof:placetype":"venue"
},
  "geometry": {"coordinates":[-2.3032019138,53.0962409973],"type":"Point"}
}