{
  "type": "Feature",
  "properties": {
    "iso:country":"GB",
    "sg:address":"8 Walsall Road",
    "sg:city":"Willenhall",
    "sg:classifiers":[
        {
            "category":"Bars & Pubs",
            "type":"Food & Drink"
        }
    ],
    "sg:phone":"+44 1902 609903",
    "sg:postcode":"WV13 2EH",
    "sg:province":"West Midlands",
    "sg:tags":[
        "pubs",
        "inn"
    ],
    "wof:name":"Enterprise Inns Plc",
    "wof:placetype":"venue"
},
  "geometry": {"coordinates":[-2.045997,52.585171],"type":"Point"}
}