{
  "type": "Feature",
  "properties": {
    "addr:full":"Merthyr Road Pontypridd Caerphilly CF37 4DW",
    "addr:postcode":"cf37 4dw",
    "addr:street":"Merthyr Road",
    "iso:country":"GB",
    "sg:address":"Merthyr Road",
    "sg:city":"Pontypridd",
    "sg:classifiers":[
        {
            "category":"Bars & Pubs",
            "type":"Food & Drink"
        }
    ],
    "sg:phone":"+44 1443 485867",
    "sg:postcode":"CF37 4DW",
    "sg:province":"Caerphilly",
    "sg:tags":[
        "pubs",
        "inn"
    ],
    "wof:name":"Royal Oak",
    "wof:placetype":"venue"
},
  "geometry": {"coordinates":[-3.3260691166,51.6108055115],"type":"Point"}
}