{
  "type": "Feature",
  "properties": {
    "iso:country":"GB",
    "sg:address":"189 Tring Rd",
    "sg:city":"Aylesbury",
    "sg:classifiers":[
        {
            "category":"Manufacturing",
            "subcategory":"Wood Products",
            "type":"Manufacturing & Wholesale Goods"
        }
    ],
    "sg:phone":"+44 1296 397661",
    "sg:postcode":"HP20 1JH",
    "sg:province":"Buckinghamshire",
    "sg:tags":[
        "maker",
        "cabinet"
    ],
    "wof:name":"Hartwell Interiors",
    "wof:placetype":"venue"
},
  "geometry": {"coordinates":[-0.788101,51.814613],"type":"Point"}
}