{
  "type": "Feature",
  "properties": {
    "iso:country":"GB",
    "sg:address":"6 Wycliffe Close",
    "sg:city":"Newton Aycliffe",
    "sg:classifiers":[
        {
            "category":"Building & Trades",
            "subcategory":"Cleaning & Sanitation",
            "type":"Services"
        },
        {
            "category":"Retail",
            "subcategory":"Repair Shop",
            "type":"Services"
        }
    ],
    "sg:phone":"+44 1325 300322",
    "sg:postcode":"DL5 4BN",
    "sg:province":"Durham",
    "sg:tags":[
        "plant",
        "machinery",
        "maintenance"
    ],
    "wof:name":"Wycliffe Electrical Services",
    "wof:placetype":"venue"
},
  "geometry": {"coordinates":[-1.558469,54.62442],"type":"Point"}
}