{
  "type": "Feature",
  "properties": {
    "addr:full":"149 Rowner Lane Gosport Hampshire PO13 9SP",
    "addr:housenumber":"149",
    "addr:postcode":"po13 9sp",
    "addr:street":"Rowner Lane",
    "iso:country":"GB",
    "sg:address":"149 Rowner Lane",
    "sg:city":"Gosport",
    "sg:classifiers":[
        {
            "category":"Shopping",
            "subcategory":"Used Merchandise",
            "type":"Retail Goods"
        }
    ],
    "sg:phone":"+44 23 9258 3555",
    "sg:postcode":"PO13 9SP",
    "sg:province":"Hampshire",
    "sg:tags":[
        "shop",
        "second-hand"
    ],
    "wof:name":"Padgets",
    "wof:placetype":"venue"
},
  "geometry": {"coordinates":[-1.174378,50.812714],"type":"Point"}
}