{
  "type": "Feature",
  "properties": {
    "iso:country":"GB",
    "sg:address":"Custom House, 35 Regent Quay",
    "sg:city":"Aberdeen",
    "sg:classifiers":[
        {
            "category":"Professional",
            "subcategory":"Computer Services",
            "type":"Services"
        }
    ],
    "sg:phone":"+44 1224 213412",
    "sg:postcode":"AB11 5BE",
    "sg:province":"Aberdeen City",
    "sg:tags":[
        "system",
        "software"
    ],
    "wof:name":"Albatech Ltd.",
    "wof:placetype":"venue"
},
  "geometry": {"coordinates":[-2.091075,57.146503],"type":"Point"}
}