{
  "type": "Feature",
  "properties": {
    "addr:full":"71 Harold Road, Cliftonville Margate Kent CT9 2HS",
    "addr:housenumber":"71",
    "addr:postcode":"ct9 2hs",
    "addr:street":"Harold Road;Margate",
    "iso:country":"GB",
    "sg:address":"71 Harold Road, Cliftonville",
    "sg:city":"Margate",
    "sg:classifiers":[
        {
            "category":"Shopping",
            "subcategory":"Pets & Pet Supplies",
            "type":"Retail Goods"
        }
    ],
    "sg:phone":"+44 1843 291592",
    "sg:postcode":"CT9 2HS",
    "sg:province":"Kent",
    "sg:tags":[
        "food",
        "feed",
        "animal"
    ],
    "wof:name":"Creature Comforts",
    "wof:placetype":"venue"
},
  "geometry": {"coordinates":[1.3990590572,51.3875694275],"type":"Point"}
}