{
  "type": "Feature",
  "properties": {
    "addr:full":"7 King Street Mirfield West Yorkshire WF14 8AP",
    "addr:housenumber":"7",
    "addr:postcode":"wf14 8ap",
    "addr:street":"King Street",
    "iso:country":"GB",
    "sg:address":"7 King Street",
    "sg:city":"Mirfield",
    "sg:classifiers":[
        {
            "category":"Professional",
            "subcategory":"Lawyer & Legal Services",
            "type":"Services"
        }
    ],
    "sg:phone":"+44 1924 499251",
    "sg:postcode":"WF14 8AP",
    "sg:province":"West Yorkshire",
    "sg:tags":[
        "solicitor"
    ],
    "wof:name":"Whitfield Hallam & Goodhall",
    "wof:placetype":"venue"
},
  "geometry": {"coordinates":[-1.6948590279,53.6742286682],"type":"Point"}
}