{
  "type": "Feature",
  "properties": {
    "addr:full":"1056 Coventry Rd Birmingham West Midlands B25 8DP",
    "addr:housenumber":"1056",
    "addr:postcode":"b25 8dp",
    "addr:street":"Coventry Rd",
    "iso:country":"GB",
    "sg:address":"1056 Coventry Rd",
    "sg:city":"Birmingham",
    "sg:classifiers":[
        {
            "category":"Food & Beverages",
            "subcategory":"Bakery",
            "type":"Retail Goods"
        }
    ],
    "sg:postcode":"B25 8DP",
    "sg:province":"West Midlands",
    "sg:tags":[
        "baker"
    ],
    "wof:name":"Hannams Bakery",
    "wof:placetype":"venue"
},
  "geometry": {"coordinates":[-1.8355779648,52.4636611938],"type":"Point"}
}