{
  "type": "Feature",
  "properties": {
    "addr:full":"4 Well Street Exeter Devon EX4 6QR",
    "addr:housenumber":"4",
    "addr:postcode":"ex4 6qr",
    "addr:street":"Well Street",
    "iso:country":"GB",
    "sg:address":"4 Well Street",
    "sg:city":"Exeter",
    "sg:classifiers":[
        {
            "category":"Manufacturing",
            "subcategory":"Glass & Minerals",
            "type":"Manufacturing & Wholesale Goods"
        }
    ],
    "sg:phone":"+44 1392 272799",
    "sg:postcode":"EX4 6QR",
    "sg:province":"Devon",
    "sg:tags":[
        "stained"
    ],
    "wof:name":"David Gubbin Stained Glass",
    "wof:placetype":"venue"
},
  "geometry": {"coordinates":[-3.52368,50.728489],"type":"Point"}
}