{
  "type": "Feature",
  "properties": {
    "addr:full":"1 Peet's Cottages, New Cut Lane Ormskirk Lancashire L39 8SW",
    "addr:housenumber":"1",
    "addr:postcode":"l39 8sw",
    "addr:street":"Cottages New Cut Lane",
    "iso:country":"GB",
    "sg:address":"1 Peet's Cottages, New Cut Lane",
    "sg:city":"Ormskirk",
    "sg:classifiers":[
        {
            "category":"Farming",
            "subcategory":"Poultry Farm",
            "type":"Manufacturing & Wholesale Goods"
        }
    ],
    "sg:phone":"+44 1704 565581",
    "sg:postcode":"L39 8SW",
    "sg:province":"Lancashire",
    "sg:tags":[
        "game"
    ],
    "wof:name":"Hainsworth International Livestock Ltd.",
    "wof:placetype":"venue"
},
  "geometry": {"coordinates":[-2.9860999584,53.6068687439],"type":"Point"}
}