{
  "type": "Feature",
  "properties": {
    "addr:full":"Main Road, Brancaster King's Lynn Norfolk PE31 8AA",
    "addr:postcode":"pe31 8aa",
    "addr:street":"Main Road;Lynn",
    "iso:country":"GB",
    "sg:address":"Main Road, Brancaster",
    "sg:city":"King's Lynn",
    "sg:classifiers":[
        {
            "category":"Retail",
            "subcategory":"Auto Repair",
            "type":"Services"
        }
    ],
    "sg:postcode":"PE31 8AA",
    "sg:province":"Norfolk",
    "sg:tags":[
        "modification",
        "garage",
        "related"
    ],
    "wof:name":"LINKS GARAGE",
    "wof:placetype":"venue"
},
  "geometry": {"coordinates":[0.6439099908,52.9628295898],"type":"Point"}
}