{
  "type": "Feature",
  "properties": {
    "iso:country":"GB",
    "sg:address":"19-21 Skinner Street",
    "sg:city":"Whitby",
    "sg:classifiers":[
        {
            "category":"Shopping",
            "subcategory":"Books",
            "type":"Retail Goods"
        }
    ],
    "sg:phone":"+44 1947 602372",
    "sg:postcode":"YO21 3AH",
    "sg:province":"North Yorkshire",
    "sg:tags":[
        "bookseller",
        "retailer"
    ],
    "wof:name":"HOLMAN'S BOOKSHOP (WHITBY)",
    "wof:placetype":"venue"
},
  "geometry": {"coordinates":[-0.6172879934,54.4872665405],"type":"Point"}
}