{
  "type": "Feature",
  "properties": {
    "addr:full":"32 Linden Avenue Willesden Greater London NW10 5RE",
    "addr:housenumber":"32",
    "addr:postcode":"nw10 5re",
    "addr:street":"Linden Avenue",
    "iso:country":"GB",
    "sg:address":"32 Linden Avenue",
    "sg:city":"Willesden",
    "sg:classifiers":[
        {
            "category":"Professional",
            "subcategory":"Engineering",
            "type":"Services"
        },
        {
            "category":"Building & Trades",
            "subcategory":"Electrical",
            "type":"Services"
        }
    ],
    "sg:phone":"+44 20 8960 7830",
    "sg:postcode":"NW10 5RE",
    "sg:province":"Greater London",
    "sg:tags":[
        "engineer",
        "electrician",
        "contractor"
    ],
    "wof:name":"M M Electrical",
    "wof:placetype":"venue"
},
  "geometry": {"coordinates":[-0.2206400037,51.5333023071],"type":"Point"}
}