{
  "type": "Feature",
  "properties": {
    "iso:country":"GB",
    "sg:address":"Broad Acre, Killay",
    "sg:city":"Swansea",
    "sg:classifiers":[
        {
            "category":"Arena",
            "subcategory":"Sports Club",
            "type":"Entertainment"
        }
    ],
    "sg:phone":"+44 1792 207291",
    "sg:postcode":"SA2 7RU",
    "sg:province":"Swansea",
    "wof:name":"Dunvant R.F.C",
    "wof:placetype":"venue"
},
  "geometry": {"coordinates":[-4.0153222084,51.6183853149],"type":"Point"}
}