{
  "type": "Feature",
  "properties": {
    "iso:country":"GB",
    "sg:address":"28 Hermitage Street, Rishton",
    "sg:city":"Blackburn",
    "sg:classifiers":[
        {
            "category":"Building & Trades",
            "subcategory":"Construction",
            "type":"Services"
        }
    ],
    "sg:postcode":"BB1 4NL",
    "sg:province":"Lancashire",
    "sg:tags":[
        "roofing"
    ],
    "wof:name":"A & J Building & Roofing Contractors",
    "wof:placetype":"venue"
},
  "geometry": {"coordinates":[-2.410848,53.768753],"type":"Point"}
}