{
  "type": "Feature",
  "properties": {
    "iso:country":"GB",
    "sg:address":"79 High Street",
    "sg:city":"Wooler",
    "sg:classifiers":[
        {
            "category":"Home & Garden",
            "subcategory":"Carpets & Floor Coverings",
            "type":"Retail Goods"
        }
    ],
    "sg:postcode":"NE71 6BD",
    "sg:province":"Northumberland",
    "sg:tags":[
        "carpets",
        "rug",
        "matting"
    ],
    "wof:name":"Frances Flannigan",
    "wof:placetype":"venue"
},
  "geometry": {"coordinates":[-2.017584,55.547157],"type":"Point"}
}