{
  "type": "Feature",
  "properties": {
    "addr:full":"Dugald Drummond St Portsmouth Hampshire PO1 2BB",
    "addr:postcode":"hampshire po1 2bb",
    "addr:street":"Dugald Drummond St",
    "iso:country":"GB",
    "sg:address":"Dugald Drummond St",
    "sg:city":"Portsmouth",
    "sg:classifiers":[
        {
            "category":"Professional",
            "subcategory":"Lawyer & Legal Services",
            "type":"Services"
        }
    ],
    "sg:phone":"+44 23 9286 4396",
    "sg:postcode":"PO1 2BB",
    "sg:province":"Hampshire",
    "sg:tags":[
        "advice",
        "counselling"
    ],
    "wof:name":"Money Advice Centre",
    "wof:placetype":"venue"
},
  "geometry": {"coordinates":[-1.090644002,50.7976493835],"type":"Point"}
}