{
  "type": "Feature",
  "properties": {
    "addr:full":"466 Bromley Rd Bromley Kent BR1 4PP",
    "addr:housenumber":"466",
    "addr:postcode":"br1 4pp",
    "addr:street":"Bromley Rd",
    "iso:country":"GB",
    "sg:address":"466 Bromley Rd",
    "sg:city":"Bromley",
    "sg:classifiers":[
        {
            "category":"Restaurant",
            "type":"Food & Drink"
        }
    ],
    "sg:phone":"+44 20 8698 8626",
    "sg:postcode":"BR1 4PP",
    "sg:province":"Kent",
    "wof:name":"Suruchi Restaurant",
    "wof:placetype":"venue"
},
  "geometry": {"coordinates":[0.0011699999,51.4120292664],"type":"Point"}
}