{
  "type": "Feature",
  "properties": {
    "iso:country":"GB",
    "sg:address":"Marine Parade, Lower Sandgate Road",
    "sg:city":"Folkestone",
    "sg:classifiers":[
        {
            "category":"Restaurant",
            "type":"Food & Drink"
        }
    ],
    "sg:phone":"+44 1303 220421",
    "sg:postcode":"CT20 1PX",
    "sg:province":"Kent",
    "wof:name":"Sea View Restaurant",
    "wof:placetype":"venue"
},
  "geometry": {"coordinates":[1.1779450178,51.0844306946],"type":"Point"}
}