{
  "type": "Feature",
  "properties": {
    "addr:full":"55 High St Tewkesbury Gloucestershire GL20 5BJ",
    "addr:housenumber":"55",
    "addr:postcode":"gl20 5bj",
    "addr:street":"High St",
    "iso:country":"GB",
    "sg:address":"55 High St",
    "sg:city":"Tewkesbury",
    "sg:classifiers":[
        {
            "category":"Bars & Pubs",
            "type":"Food & Drink"
        }
    ],
    "sg:phone":"+44 1684 297897",
    "sg:postcode":"GL20 5BJ",
    "sg:province":"Gloucestershire",
    "sg:tags":[
        "pubs",
        "inn"
    ],
    "wof:name":"St George",
    "wof:placetype":"venue"
},
  "geometry": {"coordinates":[-2.155979,51.996201],"type":"Point"}
}