{
  "type": "Feature",
  "properties": {
    "addr:full":"63 Church St Huntly Aberdeenshire AB54 8AW",
    "addr:housenumber":"63",
    "addr:postcode":"ab54 8aw",
    "addr:street":"Church St",
    "iso:country":"GB",
    "sg:address":"63 Church St",
    "sg:city":"Huntly",
    "sg:classifiers":[
        {
            "category":"Professional",
            "subcategory":"Detective & Security Services",
            "type":"Services"
        }
    ],
    "sg:phone":"+44 1466 794974",
    "sg:postcode":"AB54 8AW",
    "sg:province":"Aberdeenshire",
    "sg:tags":[
        "locksmith"
    ],
    "wof:name":"Huntly Security Systems",
    "wof:placetype":"venue"
},
  "geometry": {"coordinates":[-2.787774086,57.4435882568],"type":"Point"}
}