{
  "type": "Feature",
  "properties": {
    "iso:country":"GB",
    "sg:address":"6 Maximin Road, Margam",
    "sg:city":"Port Talbot",
    "sg:classifiers":[
        {
            "category":"Professional",
            "subcategory":"Engineering",
            "type":"Services"
        }
    ],
    "sg:postcode":"SA13 2EA",
    "sg:province":"Neath Port Talbot",
    "sg:tags":[
        "contractor",
        "electrical",
        "engineer"
    ],
    "wof:name":"Keith Hook",
    "wof:placetype":"venue"
},
  "geometry": {"coordinates":[-3.757463,51.572247],"type":"Point"}
}