{
  "type": "Feature",
  "properties": {
    "iso:country":"GB",
    "sg:address":"Scala House, Abbey Street",
    "sg:city":"Nuneaton",
    "sg:classifiers":[
        {
            "category":"Recreation",
            "subcategory":"Amusement Park",
            "type":"Entertainment"
        },
        {
            "category":"Community Center",
            "type":"Public Place"
        }
    ],
    "sg:phone":"+44 24 7638 5008",
    "sg:postcode":"CV11 5BZ",
    "sg:province":"Leicestershire",
    "sg:tags":[
        "arcade",
        "leisure",
        "centre"
    ],
    "wof:name":"H J M Caterers Ltd",
    "wof:placetype":"venue"
},
  "geometry": {"coordinates":[-1.472937,52.525253],"type":"Point"}
}