{
  "type": "Feature",
  "properties": {
    "iso:country":"GB",
    "sg:address":"29 Glenview Terrace, Crumlin",
    "sg:city":"Newport",
    "sg:classifiers":[
        {
            "category":"Building & Trades",
            "subcategory":"Construction",
            "type":"Services"
        }
    ],
    "sg:phone":"+44 1495 244087",
    "sg:postcode":"NP11 4QE",
    "sg:province":"Blaenau Gwent",
    "sg:tags":[
        "builder"
    ],
    "wof:name":"P Webley",
    "wof:placetype":"venue"
},
  "geometry": {"coordinates":[-3.141526,51.678066],"type":"Point"}
}