{
  "type": "Feature",
  "properties": {
    "addr:full":"Unit 6 Crispin Industrial Estate, Angel Road Works London Greater London N18 3EA",
    "addr:housenumber":"unit 6",
    "addr:postcode":"n18 3ea",
    "addr:street":"Crispin Industrial Estate Angel Road",
    "iso:country":"GB",
    "sg:address":"Unit 6 Crispin Industrial Estate, Angel Road Works",
    "sg:city":"London",
    "sg:classifiers":[
        {
            "category":"Home & Garden",
            "subcategory":"Furniture",
            "type":"Retail Goods"
        }
    ],
    "sg:postcode":"N18 3EA",
    "sg:province":"Greater London",
    "wof:name":"Pine Design",
    "wof:placetype":"venue"
},
  "geometry": {"coordinates":[-0.0467399992,51.6128501892],"type":"Point"}
}