{
  "type": "Feature",
  "properties": {
    "iso:country":"GB",
    "sg:address":"130 Fenchurch St",
    "sg:city":"Monument",
    "sg:classifiers":[
        {
            "category":"Insurance",
            "subcategory":"Insurance Agent",
            "type":"Services"
        }
    ],
    "sg:phone":"+44 20 7929 6660",
    "sg:postcode":"EC3M 5DJ",
    "sg:province":"Greater London",
    "wof:name":"The Swedish Club",
    "wof:placetype":"venue"
},
  "geometry": {"coordinates":[-0.080311,51.512115],"type":"Point"}
}