{
  "type": "Feature",
  "properties": {
    "addr:full":"251 Linthorpe Rd Middlesbrough North Yorkshire TS1 4AT",
    "addr:housenumber":"251",
    "addr:postcode":"ts1 4at",
    "addr:street":"Linthorpe Rd",
    "iso:country":"GB",
    "sg:address":"251 Linthorpe Rd",
    "sg:city":"Middlesbrough",
    "sg:classifiers":[
        {
            "category":"Sports & Exercise",
            "subcategory":"Gym",
            "type":"Entertainment"
        }
    ],
    "sg:phone":"+44 1642 254447",
    "sg:postcode":"TS1 4AT",
    "sg:province":"North Yorkshire",
    "sg:tags":[
        "fitness",
        "health",
        "centre"
    ],
    "wof:name":"Kingsway Leisure Club",
    "wof:placetype":"venue"
},
  "geometry": {"coordinates":[-1.239427,54.569241],"type":"Point"}
}