{
  "type": "Feature",
  "properties": {
    "iso:country":"GB",
    "sg:address":"74 Newstead Road",
    "sg:city":"Sheffield",
    "sg:classifiers":[
        {
            "category":"Building & Trades",
            "subcategory":"Construction",
            "type":"Services"
        }
    ],
    "sg:postcode":"S12 3BH",
    "sg:province":"Derbyshire",
    "sg:tags":[
        "decorator",
        "painter"
    ],
    "wof:name":"Bland Cleaning & Painting Services",
    "wof:placetype":"venue"
},
  "geometry": {"coordinates":[-1.391443,53.341702],"type":"Point"}
}