{
  "type": "Feature",
  "properties": {
    "iso:country":"GB",
    "sg:address":"14 Victor Terrace, Bear Park",
    "sg:city":"Durham",
    "sg:classifiers":[
        {
            "category":"Freight",
            "type":"Transportation"
        }
    ],
    "sg:postcode":"DH7 7DG",
    "sg:province":"Durham",
    "sg:tags":[
        "haulage",
        "road"
    ],
    "wof:name":"Whitstage Ltd.",
    "wof:placetype":"venue"
},
  "geometry": {"coordinates":[-1.6362140179,54.7833442688],"type":"Point"}
}