{
  "type": "Feature",
  "properties": {
    "iso:country":"GB",
    "sg:address":"Camp Hill, Bordesley",
    "sg:city":"Birmingham",
    "sg:classifiers":[
        {
            "category":"Professional",
            "subcategory":"Engineering",
            "type":"Services"
        }
    ],
    "sg:phone":"+44 121 766 6161",
    "sg:postcode":"B12 0JJ",
    "sg:province":"West Midlands",
    "sg:tags":[
        "electronic",
        "engineer"
    ],
    "wof:name":"Dowding & Mills Plc",
    "wof:placetype":"venue"
},
  "geometry": {"coordinates":[-1.878794,52.471794],"type":"Point"}
}