{
  "type": "Feature",
  "properties": {
    "iso:country":"GB",
    "sg:address":"2 Kelston Road",
    "sg:city":"Bath",
    "sg:classifiers":[
        {
            "category":"Social Services",
            "subcategory":"Adult Care",
            "type":"Services"
        },
        {
            "category":"Government",
            "subcategory":"Office",
            "type":"Public Place"
        }
    ],
    "sg:phone":"+44 1225 464165",
    "sg:postcode":"BA1 3QJ",
    "sg:province":"Bath and North East Somerset",
    "sg:tags":[
        "local",
        "day",
        "centre"
    ],
    "wof:name":"Black & O M E Senior Citizen Project",
    "wof:placetype":"venue"
},
  "geometry": {"coordinates":[-2.3995249271,51.3896598816],"type":"Point"}
}