{
  "type": "Feature",
  "properties": {
    "iso:country":"GB",
    "sg:address":"Unit 1 Hawthorne Ave, Gt Sankey",
    "sg:city":"Warrington",
    "sg:classifiers":[
        {
            "category":"Shopping",
            "subcategory":"Bicycles & Sporting Goods",
            "type":"Retail Goods"
        }
    ],
    "sg:postcode":"WA5 1RJ",
    "sg:province":"Cheshire",
    "sg:tags":[
        "cycle",
        "accessory"
    ],
    "wof:name":"Cowshill,Martin,",
    "wof:placetype":"venue"
},
  "geometry": {"coordinates":[-2.646054,53.392181],"type":"Point"}
}