{
  "type": "Feature",
  "properties": {
    "addr:full":"Unit 2, Hanlon Court, Royal Industrial Estate Jarrow Tyne and Wear NE32 3HR",
    "addr:housenumber":"unit 2",
    "addr:postcode":"ne32 3hr",
    "addr:street":"Hanlon Court Royal Industrial Estate",
    "iso:country":"GB",
    "sg:address":"Unit 2, Hanlon Court, Royal Industrial Estate",
    "sg:city":"Jarrow",
    "sg:classifiers":[
        {
            "category":"Home & Garden",
            "subcategory":"Hardware",
            "type":"Retail Goods"
        }
    ],
    "sg:phone":"+44 191 483 6646",
    "sg:postcode":"NE32 3HR",
    "sg:province":"Tyne and Wear",
    "sg:tags":[
        "product",
        "wire",
        "electrical"
    ],
    "wof:name":"Truetech Ltd.",
    "wof:placetype":"venue"
},
  "geometry": {"coordinates":[-1.5023699999,54.9832305908],"type":"Point"}
}