{
  "type": "Feature",
  "properties": {
    "iso:country":"GB",
    "sg:address":"14 Maypole Crescent, Darent Industrial Estate",
    "sg:city":"Erith",
    "sg:classifiers":[
        {
            "category":"Building & Trades",
            "subcategory":"Construction",
            "type":"Services"
        }
    ],
    "sg:phone":"+44 1322 336058",
    "sg:postcode":"DA8 2JZ",
    "sg:province":"Kent",
    "sg:tags":[
        "platform",
        "work",
        "scaffolding"
    ],
    "wof:name":"Rotor Scaffolding Services Ltd.",
    "wof:placetype":"venue"
},
  "geometry": {"coordinates":[0.213612,51.47913],"type":"Point"}
}