{
  "type": "Feature",
  "properties": {
    "addr:full":"16 Middle Road, Park Gate Southampton Hampshire SO31 7GH",
    "addr:housenumber":"16",
    "addr:postcode":"so31 7gh",
    "addr:street":"Middle Road",
    "iso:country":"GB",
    "sg:address":"16 Middle Road, Park Gate",
    "sg:city":"Southampton",
    "sg:classifiers":[
        {
            "category":"Professional",
            "subcategory":"Art Services",
            "type":"Services"
        }
    ],
    "sg:phone":"+44 1489 584763",
    "sg:postcode":"SO31 7GH",
    "sg:province":"Hampshire",
    "sg:tags":[
        "photographer"
    ],
    "wof:name":"Sandra Day Photographic Services",
    "wof:placetype":"venue"
},
  "geometry": {"coordinates":[-1.268388,50.872368],"type":"Point"}
}