{
  "type": "Feature",
  "properties": {
    "iso:country":"GB",
    "sg:address":"1 High Street",
    "sg:city":"Aldershot",
    "sg:classifiers":[
        {
            "category":"Bars & Pubs",
            "type":"Food & Drink"
        }
    ],
    "sg:phone":"+44 1252 320167",
    "sg:postcode":"GU11 1BH",
    "sg:province":"Hampshire",
    "sg:tags":[
        "pubs",
        "inn"
    ],
    "wof:name":"The Eckstein Group",
    "wof:placetype":"venue"
},
  "geometry": {"coordinates":[-0.767567,51.249996],"type":"Point"}
}