{
  "type": "Feature",
  "properties": {
    "addr:full":"393 Cowley Road Oxford Oxfordshire OX4 2DF",
    "addr:housenumber":"393",
    "addr:postcode":"ox4 2df",
    "addr:street":"Cowley Road",
    "iso:country":"GB",
    "sg:address":"393 Cowley Road",
    "sg:city":"Oxford",
    "sg:classifiers":[
        {
            "category":"Bus Charters",
            "type":"Transportation"
        }
    ],
    "sg:phone":"+44 1865 716656",
    "sg:postcode":"OX4 2DF",
    "sg:province":"Oxfordshire",
    "sg:tags":[
        "coach"
    ],
    "wof:name":"The Go-Ahead Group Plc",
    "wof:placetype":"venue"
},
  "geometry": {"coordinates":[-1.224734,51.74131],"type":"Point"}
}