{
  "type": "Feature",
  "properties": {
    "addr:full":"High Street, Winfrith Newburgh Dorchester Dorset DT2 8JN",
    "addr:postcode":"dt2 8jn",
    "addr:street":"High Street",
    "iso:country":"GB",
    "sg:address":"High Street, Winfrith Newburgh",
    "sg:city":"Dorchester",
    "sg:classifiers":[
        {
            "category":"Shopping",
            "subcategory":"Department Store",
            "type":"Retail Goods"
        },
        {
            "category":"Food & Beverages",
            "subcategory":"Groceries & Convenience Stores",
            "type":"Retail Goods"
        }
    ],
    "sg:phone":"+44 1305 852824",
    "sg:postcode":"DT2 8JN",
    "sg:province":"Dorset",
    "wof:name":"Winfrith Sub Post Office & Stores",
    "wof:placetype":"venue"
},
  "geometry": {"coordinates":[-2.274335,50.661652],"type":"Point"}
}