{
  "type": "Feature",
  "properties": {
    "iso:country":"GB",
    "sg:address":"Lordsmead House, Mere",
    "sg:city":"Warminster",
    "sg:classifiers":[
        {
            "category":"Real Estate",
            "subcategory":"Architect",
            "type":"Services"
        }
    ],
    "sg:phone":"+44 1747 860227",
    "sg:postcode":"BA12 6DB",
    "sg:province":"Somerset",
    "wof:name":"AAP Allied Architects Practice",
    "wof:placetype":"venue"
},
  "geometry": {"coordinates":[-2.270171,51.090511],"type":"Point"}
}