{
  "type": "Feature",
  "properties": {
    "iso:country":"GB",
    "sg:address":"30 Pippins Field",
    "sg:city":"Cullompton",
    "sg:classifiers":[
        {
            "category":"Retail",
            "subcategory":"Driving School",
            "type":"Services"
        }
    ],
    "sg:phone":"+44 1884 841477",
    "sg:postcode":"EX15 3BS",
    "sg:province":"Devon",
    "wof:name":"Brian Clayton",
    "wof:placetype":"venue"
},
  "geometry": {"coordinates":[-3.3369140625,50.902256012],"type":"Point"}
}