{
  "type": "Feature",
  "properties": {
    "iso:country":"GB",
    "sg:address":"388 Long Lane, Hillingdon",
    "sg:city":"Uxbridge",
    "sg:classifiers":[
        {
            "category":"Fast Food",
            "type":"Food & Drink"
        }
    ],
    "sg:phone":"+44 1895 238288",
    "sg:postcode":"UB10 9PG",
    "sg:province":"Greater London",
    "sg:tags":[
        "away",
        "meal",
        "outlet",
        "take"
    ],
    "wof:name":"Dragon Inn",
    "wof:placetype":"venue"
},
  "geometry": {"coordinates":[-0.4487380087,51.5513153076],"type":"Point"}
}