{
  "type": "Feature",
  "properties": {
    "addr:full":"Union St Torquay Devon TQ1 3UT",
    "addr:postcode":"tq1 3ut",
    "addr:street":"Union St",
    "iso:country":"GB",
    "sg:address":"Union St",
    "sg:city":"Torquay",
    "sg:classifiers":[
        {
            "category":"Commercial Area",
            "type":"Public Place"
        }
    ],
    "sg:phone":"+44 1803 294892",
    "sg:postcode":"TQ1 3UT",
    "sg:province":"Devon",
    "sg:tags":[
        "shop",
        "centre"
    ],
    "wof:name":"Union Square Shopping Centre",
    "wof:placetype":"venue"
},
  "geometry": {"coordinates":[-3.532014,50.468109],"type":"Point"}
}