{
  "type": "Feature",
  "properties": {
    "iso:country":"GB",
    "sg:address":"Black Horse Drove, Littleport",
    "sg:city":"Ely",
    "sg:classifiers":[
        {
            "category":"Farming",
            "subcategory":"Livestock Farm",
            "type":"Manufacturing & Wholesale Goods"
        }
    ],
    "sg:phone":"+44 1353 860551",
    "sg:postcode":"CB6 1EH",
    "sg:province":"Cambridgeshire",
    "sg:tags":[
        "others"
    ],
    "wof:name":"J C Rains Ltd.",
    "wof:placetype":"venue"
},
  "geometry": {"coordinates":[0.302056,52.459358],"type":"Point"}
}