{
  "type": "Feature",
  "properties": {
    "addr:full":"Unit 9d Convamore Rd Grimsby Lincolnshire DN32 9HX",
    "addr:housenumber":"unit",
    "addr:postcode":"dn32 9hx",
    "addr:street":"Convamore Rd",
    "iso:country":"GB",
    "sg:address":"Unit 9d Convamore Rd",
    "sg:city":"Grimsby",
    "sg:classifiers":[
        {
            "category":"Shopping",
            "subcategory":"Stationery & Office Supplies",
            "type":"Retail Goods"
        }
    ],
    "sg:phone":"+44 1472 211555",
    "sg:postcode":"DN32 9HX",
    "sg:province":"Lincolnshire",
    "sg:tags":[
        "equipment",
        "printing",
        "mech"
    ],
    "wof:name":"Grantec Web",
    "wof:placetype":"venue"
},
  "geometry": {"coordinates":[-0.0710989982,53.5643959045],"type":"Point"}
}