{
  "type": "Feature",
  "properties": {
    "addr:full":"Cortes Lonmay Fraserburgh Aberdeenshire AB43 8SS",
    "addr:postcode":"ab43 8ss",
    "iso:country":"GB",
    "sg:address":"Cortes Lonmay",
    "sg:city":"Fraserburgh",
    "sg:classifiers":[
        {
            "category":"Home & Garden",
            "subcategory":"Garden Supply",
            "type":"Retail Goods"
        }
    ],
    "sg:phone":"+44 1346 532929",
    "sg:postcode":"AB43 8SS",
    "sg:province":"Aberdeenshire",
    "sg:tags":[
        "nursery",
        "centre"
    ],
    "wof:name":"Richard & Janet Way",
    "wof:placetype":"venue"
},
  "geometry": {"coordinates":[-1.9717390537,57.6195793152],"type":"Point"}
}