{
  "type": "Feature",
  "properties": {
    "iso:country":"GB",
    "sg:address":"Lancaster House",
    "sg:city":"Tenby",
    "sg:classifiers":[
        {
            "category":"Shopping",
            "subcategory":"Comic Books",
            "type":"Retail Goods"
        }
    ],
    "sg:postcode":"SA70 7HD",
    "sg:province":"Pembrokeshire",
    "sg:tags":[
        "jeweller"
    ],
    "wof:name":"Tenby Jewellers Ltd.",
    "wof:placetype":"venue"
},
  "geometry": {"coordinates":[-4.6930971146,51.6395492554],"type":"Point"}
}