{
  "type": "Feature",
  "properties": {
    "addr:full":"P O Box 300 Romford Essex RM5 2DL",
    "addr:housenumber":"300",
    "addr:postcode":"rm5 2dl",
    "addr:street":"P O Box",
    "iso:country":"GB",
    "sg:address":"P O Box 300",
    "sg:city":"Romford",
    "sg:classifiers":[
        {
            "category":"Wholesale",
            "subcategory":"Music Publishers",
            "type":"Manufacturing & Wholesale Goods"
        }
    ],
    "sg:phone":"+44 1708 760953",
    "sg:postcode":"RM5 2DL",
    "sg:province":"Essex",
    "sg:tags":[
        "record"
    ],
    "wof:name":"S U Corporation Ltd.",
    "wof:placetype":"venue"
},
  "geometry": {"coordinates":[0.1563950032,51.5979652405],"type":"Point"}
}