{
  "type": "Feature",
  "properties": {
    "addr:full":"High St Thornhill Dumfries and Galloway DG3 4HN",
    "addr:postcode":"dg3 4hn",
    "addr:street":"High St",
    "iso:country":"GB",
    "sg:address":"High St",
    "sg:city":"Thornhill",
    "sg:classifiers":[
        {
            "category":"Retail",
            "subcategory":"Auto Repair",
            "type":"Services"
        }
    ],
    "sg:phone":"+44 1848 200313",
    "sg:postcode":"DG3 4HN",
    "sg:province":"Dumfries and Galloway",
    "sg:tags":[
        "modification",
        "garage"
    ],
    "wof:name":"Riverside Garage",
    "wof:placetype":"venue"
},
  "geometry": {"coordinates":[-3.91927,55.197594],"type":"Point"}
}