{
  "type": "Feature",
  "properties": {
    "addr:full":"20 Hampden Road Maidenhead Berkshire SL6 5HQ",
    "addr:housenumber":"20",
    "addr:postcode":"sl6 5hq",
    "addr:street":"Hampden Road",
    "iso:country":"GB",
    "sg:address":"20 Hampden Road",
    "sg:city":"Maidenhead",
    "sg:classifiers":[
        {
            "category":"Shopping",
            "subcategory":"Department Store",
            "type":"Retail Goods"
        }
    ],
    "sg:phone":"+44 1628 770074",
    "sg:postcode":"SL6 5HQ",
    "sg:province":"Berkshire",
    "wof:name":"J R General Stores",
    "wof:placetype":"venue"
},
  "geometry": {"coordinates":[-0.751241982,51.5292129517],"type":"Point"}
}