{
  "type": "Feature",
  "properties": {
    "addr:full":"The Old School, 13 Talbot Road Blackpool Lancashire FY1 1LB",
    "addr:housenumber":"13",
    "addr:postcode":"fy1 1lb",
    "addr:street":"Talbot Road",
    "iso:country":"GB",
    "sg:address":"The Old School, 13 Talbot Road",
    "sg:city":"Blackpool",
    "sg:classifiers":[
        {
            "category":"Organizations",
            "subcategory":"Community Association",
            "type":"Services"
        }
    ],
    "sg:phone":"+44 1253 290829",
    "sg:postcode":"FY1 1LB",
    "sg:province":"Lancashire",
    "sg:tags":[
        "society",
        "housing"
    ],
    "wof:name":"The North British Housing Association Ltd.",
    "wof:placetype":"venue"
},
  "geometry": {"coordinates":[-3.050718,53.809101],"type":"Point"}
}