{
  "type": "Feature",
  "properties": {
    "addr:full":"94 Fromond Rd Winchester Hampshire SO22 6EG",
    "addr:housenumber":"94",
    "addr:postcode":"so22 6eg",
    "addr:street":"Fromond Rd",
    "iso:country":"GB",
    "sg:address":"94 Fromond Rd",
    "sg:city":"Winchester",
    "sg:classifiers":[
        {
            "category":"Building & Trades",
            "subcategory":"Construction",
            "type":"Services"
        }
    ],
    "sg:phone":"+44 1962 882021",
    "sg:postcode":"SO22 6EG",
    "sg:province":"Hampshire",
    "sg:tags":[
        "joiner",
        "carpenter"
    ],
    "wof:name":"J & J Home Improvements",
    "wof:placetype":"venue"
},
  "geometry": {"coordinates":[-1.3374880552,51.0762252808],"type":"Point"}
}