{
  "type": "Feature",
  "properties": {
    "addr:full":"1 High Street Ludlow Herefordshire SY8 1BS",
    "addr:housenumber":"1",
    "addr:postcode":"sy8 1bs",
    "addr:street":"High Street",
    "iso:country":"GB",
    "sg:address":"1 High Street",
    "sg:city":"Ludlow",
    "sg:classifiers":[
        {
            "category":"Shopping",
            "subcategory":"Clothing, Apparel, & Fashions",
            "type":"Retail Goods"
        }
    ],
    "sg:postcode":"SY8 1BS",
    "sg:province":"Herefordshire",
    "sg:tags":[
        "wear",
        "leisure"
    ],
    "wof:name":"The Chestnut Gallery",
    "wof:placetype":"venue"
},
  "geometry": {"coordinates":[-2.7192809582,52.3677368164],"type":"Point"}
}