{
  "type": "Feature",
  "properties": {
    "addr:full":"Cae Gwilym Road, Newbridge Wrexham Wrexham LL14 3PE",
    "addr:postcode":"ll14 3pe",
    "addr:street":"Gwilym Road",
    "iso:country":"GB",
    "sg:address":"Cae Gwilym Road, Newbridge",
    "sg:city":"Wrexham",
    "sg:classifiers":[
        {
            "category":"Government",
            "subcategory":"Office",
            "type":"Public Place"
        },
        {
            "category":"Landmark",
            "subcategory":"Tourist Attraction",
            "type":"Public Place"
        }
    ],
    "sg:phone":"+44 1978 822780",
    "sg:postcode":"LL14 3PE",
    "sg:province":"Wrexham",
    "sg:tags":[
        "local",
        "interest"
    ],
    "wof:name":"Ty Mawr Country Park",
    "wof:placetype":"venue"
},
  "geometry": {"coordinates":[-3.078109026,52.9711799622],"type":"Point"}
}