{
  "type": "Feature",
  "properties": {
    "addr:full":"16 St Paul Street London Greater London N1 7AB",
    "addr:housenumber":"16",
    "addr:postcode":"n1 7ab",
    "addr:street":"St Paul Street",
    "iso:country":"GB",
    "sg:address":"16 St Paul Street",
    "sg:city":"London",
    "sg:classifiers":[
        {
            "category":"Health Services",
            "subcategory":"Health Practitioner",
            "type":"Services"
        }
    ],
    "sg:phone":"+44 20 7226 8499",
    "sg:postcode":"N1 7AB",
    "sg:province":"Greater London",
    "sg:tags":[
        "osteopath"
    ],
    "wof:name":"Stella Strong",
    "wof:placetype":"venue"
},
  "geometry": {"coordinates":[-0.09234,51.53751],"type":"Point"}
}