{
  "type": "Feature",
  "properties": {
    "iso:country":"GB",
    "sg:address":"92a Friern Gardens",
    "sg:city":"Wickford",
    "sg:classifiers":[
        {
            "category":"Building & Trades",
            "subcategory":"Construction",
            "type":"Services"
        }
    ],
    "sg:postcode":"SS12 0HD",
    "sg:province":"Essex",
    "sg:tags":[
        "builder"
    ],
    "wof:name":"Excel Interiors (Uk) Ltd",
    "wof:placetype":"venue"
},
  "geometry": {"coordinates":[0.509006,51.606998],"type":"Point"}
}