{
  "type": "Feature",
  "properties": {
    "addr:full":"Burlington Hotel, Whiting Bay Brodick North Ayrshire KA27 8PZ",
    "addr:postcode":"ka27 8pz",
    "iso:country":"GB",
    "sg:address":"Burlington Hotel, Whiting Bay",
    "sg:city":"Brodick",
    "sg:classifiers":[
        {
            "category":"Professional",
            "subcategory":"Management & Consulting",
            "type":"Services"
        }
    ],
    "sg:phone":"+44 1770 700232",
    "sg:postcode":"KA27 8PZ",
    "sg:province":"North Ayrshire",
    "sg:tags":[
        "consultant",
        "business"
    ],
    "wof:name":"Lamont Richardson Associates",
    "wof:placetype":"venue"
},
  "geometry": {"coordinates":[-5.152319,55.577576],"type":"Point"}
}