{
  "type": "Feature",
  "properties": {
    "iso:country":"GB",
    "sg:address":"9 Potter St",
    "sg:city":"Bishops Stortford",
    "sg:classifiers":[
        {
            "category":"Shopping",
            "subcategory":"Clothing, Apparel, & Fashions",
            "type":"Retail Goods"
        }
    ],
    "sg:postcode":"CM23 3UH",
    "sg:province":"Essex",
    "sg:tags":[
        "ladieswear"
    ],
    "wof:name":"Select (Retail) Plc",
    "wof:placetype":"venue"
},
  "geometry": {"coordinates":[0.159876,51.87022],"type":"Point"}
}