{
  "type": "Feature",
  "properties": {
    "iso:country":"GB",
    "sg:address":"55 Knaresborough Road",
    "sg:city":"Harrogate",
    "sg:classifiers":[
        {
            "category":"Shopping",
            "subcategory":"Bicycles & Sporting Goods",
            "type":"Retail Goods"
        }
    ],
    "sg:phone":"+44 1423 885196",
    "sg:postcode":"HG2 7LT",
    "sg:province":"North Yorkshire",
    "sg:tags":[
        "cycle",
        "accessory"
    ],
    "wof:name":"Harrogate Cycle",
    "wof:placetype":"venue"
},
  "geometry": {"coordinates":[-1.514763,53.995964],"type":"Point"}
}