{
  "type": "Feature",
  "properties": {
    "addr:full":"16 Melville Street Falkirk Falkirk FK1 1HZ",
    "addr:housenumber":"16",
    "addr:postcode":"fk1 1hz",
    "addr:street":"Melville Street",
    "iso:country":"GB",
    "sg:address":"16 Melville Street",
    "sg:city":"Falkirk",
    "sg:classifiers":[
        {
            "category":"Organizations",
            "subcategory":"Non-profit Organization",
            "type":"Services"
        }
    ],
    "sg:phone":"+44 1324 621811",
    "sg:postcode":"FK1 1HZ",
    "sg:province":"Falkirk",
    "sg:tags":[
        "organisation",
        "voluntary",
        "charity"
    ],
    "wof:name":"Children 1ST",
    "wof:placetype":"venue"
},
  "geometry": {"coordinates":[-3.7854650021,56.0012550354],"type":"Point"}
}