{
  "type": "Feature",
  "properties": {
    "addr:full":"Kiddiland, 15 Whitefield Road Liverpool Merseyside L6 5DD",
    "addr:housenumber":"15",
    "addr:postcode":"l6 5dd",
    "addr:street":"Kiddiland;Whitefield Road",
    "iso:country":"GB",
    "sg:address":"Kiddiland, 15 Whitefield Road",
    "sg:city":"Liverpool",
    "sg:classifiers":[
        {
            "category":"Education",
            "subcategory":"Special Training",
            "type":"Public Place"
        }
    ],
    "sg:phone":"+44 151 260 9662",
    "sg:postcode":"L6 5DD",
    "sg:province":"Merseyside",
    "sg:tags":[
        "product",
        "centre"
    ],
    "wof:name":"The Whitefield Centre Ltd.",
    "wof:placetype":"venue"
},
  "geometry": {"coordinates":[-2.95658,53.420528],"type":"Point"}
}