{
  "type": "Feature",
  "properties": {
    "addr:full":"10 Heron Drive, Twyford Reading Berkshire RG10 9DE",
    "addr:housenumber":"10",
    "addr:postcode":"rg10 9de",
    "addr:street":"Heron Drive",
    "iso:country":"GB",
    "sg:address":"10 Heron Drive, Twyford",
    "sg:city":"Reading",
    "sg:classifiers":[
        {
            "category":"Building & Trades",
            "subcategory":"Construction",
            "type":"Services"
        }
    ],
    "sg:postcode":"RG10 9DE",
    "sg:province":"Berkshire",
    "sg:tags":[
        "dry",
        "plastering",
        "plasterers",
        "lining",
        "related",
        "screeders"
    ],
    "wof:name":"HORACE COMLEY",
    "wof:placetype":"venue"
},
  "geometry": {"coordinates":[-0.861394,51.486012],"type":"Point"}
}