{
  "type": "Feature",
  "properties": {
    "iso:country":"GB",
    "sg:address":"Linton Ho, Union St",
    "sg:city":"London",
    "sg:classifiers":[
        {
            "category":"Professional",
            "subcategory":"Computer Services",
            "type":"Services"
        }
    ],
    "sg:postcode":"SE1 0LH",
    "sg:province":"Greater London",
    "sg:tags":[
        "information"
    ],
    "wof:name":"Service Associates",
    "wof:placetype":"venue"
},
  "geometry": {"coordinates":[-0.09893,51.503792],"type":"Point"}
}