{
  "type": "Feature",
  "properties": {
    "iso:country":"GB",
    "sg:address":"105 Springfield Avenue, Morley",
    "sg:city":"Leeds",
    "sg:classifiers":[
        {
            "category":"Bars & Pubs",
            "type":"Food & Drink"
        }
    ],
    "sg:phone":"+44 113 253 4646",
    "sg:postcode":"LS27 9PP",
    "sg:province":"West Yorkshire",
    "sg:tags":[
        "pubs",
        "inn"
    ],
    "wof:name":"The Springfield",
    "wof:placetype":"venue"
},
  "geometry": {"coordinates":[-1.6079399586,53.7550163269],"type":"Point"}
}