{
  "type": "Feature",
  "properties": {
    "iso:country":"GB",
    "sg:address":"40 Broadhurst Grove, Lychpit",
    "sg:city":"Basingstoke",
    "sg:classifiers":[
        {
            "category":"Building & Trades",
            "subcategory":"Construction",
            "type":"Services"
        }
    ],
    "sg:postcode":"RG24 8SB",
    "sg:province":"Hampshire",
    "sg:tags":[
        "roofing"
    ],
    "wof:name":"D A King Roofing",
    "wof:placetype":"venue"
},
  "geometry": {"coordinates":[-1.058142,51.273491],"type":"Point"}
}