{
  "type": "Feature",
  "properties": {
    "iso:country":"GB",
    "sg:address":"31 Marmion Close",
    "sg:city":"Chingford",
    "sg:classifiers":[
        {
            "category":"Professional",
            "subcategory":"Engineering",
            "type":"Services"
        }
    ],
    "sg:phone":"+44 20 8529 4105",
    "sg:postcode":"E4 8EN",
    "sg:province":"Greater London",
    "sg:tags":[
        "civil",
        "engineer"
    ],
    "wof:name":"P Mahoney",
    "wof:placetype":"venue"
},
  "geometry": {"coordinates":[-0.023012,51.618591],"type":"Point"}
}