{
  "type": "Feature",
  "properties": {
    "addr:full":"25 Osborne Road Southsea Hampshire PO5 3LR",
    "addr:housenumber":"25",
    "addr:postcode":"po5 3lr",
    "addr:street":"Osborne Road",
    "iso:country":"GB",
    "sg:address":"25 Osborne Road",
    "sg:city":"Southsea",
    "sg:classifiers":[
        {
            "category":"Health Services",
            "subcategory":"Health Practitioner",
            "type":"Services"
        },
        {
            "category":"Shopping",
            "subcategory":"Pharmacy",
            "type":"Retail Goods"
        }
    ],
    "sg:phone":"+44 23 9287 4748",
    "sg:postcode":"PO5 3LR",
    "sg:province":"Hampshire",
    "sg:tags":[
        "acupuncture",
        "medicine",
        "therapy"
    ],
    "wof:name":"Southsea Centre for Complementary Medicine (The)",
    "wof:placetype":"venue"
},
  "geometry": {"coordinates":[-1.0925780535,50.7853164673],"type":"Point"}
}