{
  "type": "Feature",
  "properties": {
    "iso:country":"GB",
    "sg:address":"71-79 Eaton Road",
    "sg:city":"Margate",
    "sg:classifiers":[
        {
            "category":"Autos & Motor Vehicles",
            "subcategory":"Auto Supplies",
            "type":"Retail Goods"
        }
    ],
    "sg:postcode":"CT9 1XB",
    "sg:province":"Kent",
    "sg:tags":[
        "tyre"
    ],
    "wof:name":"A1 Quality Used Tyres",
    "wof:placetype":"venue"
},
  "geometry": {"coordinates":[1.380491972,51.3832855225],"type":"Point"}
}