{
  "type": "Feature",
  "properties": {
    "iso:country":"GB",
    "sg:address":"55 College Street",
    "sg:city":"Ammanford",
    "sg:classifiers":[
        {
            "category":"Health Services",
            "subcategory":"Dentist",
            "type":"Services"
        }
    ],
    "sg:phone":"+44 1269 592868",
    "sg:postcode":"SA18 2BU",
    "sg:province":"Carmarthenshire",
    "wof:name":"M J Pyle",
    "wof:placetype":"venue"
},
  "geometry": {"coordinates":[-3.993474,51.797134],"type":"Point"}
}