{
  "type": "Feature",
  "properties": {
    "addr:full":"236 Ramsey Rd Peterborough Cambridgeshire PE7 1DR",
    "addr:housenumber":"236",
    "addr:postcode":"pe7 1dr",
    "addr:street":"Ramsey Rd",
    "iso:country":"GB",
    "sg:address":"236 Ramsey Rd",
    "sg:city":"Peterborough",
    "sg:classifiers":[
        {
            "category":"Building & Trades",
            "subcategory":"Construction",
            "type":"Services"
        }
    ],
    "sg:phone":"+44 1733 844599",
    "sg:postcode":"PE7 1DR",
    "sg:province":"Cambridgeshire",
    "sg:tags":[
        "decorator",
        "painter"
    ],
    "wof:name":"John Wade & Sons",
    "wof:placetype":"venue"
},
  "geometry": {"coordinates":[-0.133359,52.552158],"type":"Point"}
}