{
  "type": "Feature",
  "properties": {
    "addr:full":"1 Kingston Drive Beccles Norfolk NR34 9RP",
    "addr:housenumber":"1",
    "addr:postcode":"nr34 9rp",
    "addr:street":"Kingston Drive",
    "iso:country":"GB",
    "sg:address":"1 Kingston Drive",
    "sg:city":"Beccles",
    "sg:classifiers":[
        {
            "category":"Military Area",
            "subcategory":"Army Base",
            "type":"Public Place"
        }
    ],
    "sg:phone":"+44 1502 712423",
    "sg:postcode":"NR34 9RP",
    "sg:province":"Norfolk",
    "sg:tags":[
        "transportation",
        "livestock"
    ],
    "wof:name":"R T Nelson & Son",
    "wof:placetype":"venue"
},
  "geometry": {"coordinates":[1.5738630295,52.4547805786],"type":"Point"}
}