{
  "type": "Feature",
  "properties": {
    "addr:full":"11 Shambles York North Yorkshire YO1 2LZ",
    "addr:housenumber":"11",
    "addr:postcode":"yo1 2lz",
    "addr:street":"Shambles York",
    "iso:country":"GB",
    "sg:address":"11 Shambles",
    "sg:city":"York",
    "sg:classifiers":[
        {
            "category":"Shopping",
            "subcategory":"Gifts & Souvenirs",
            "type":"Retail Goods"
        }
    ],
    "sg:phone":"+44 1904 656470",
    "sg:postcode":"YO1 2LZ",
    "sg:province":"North Yorkshire",
    "sg:tags":[
        "shop"
    ],
    "wof:name":"Greetings",
    "wof:placetype":"venue"
},
  "geometry": {"coordinates":[-1.079838,53.959469],"type":"Point"}
}