{
  "type": "Feature",
  "properties": {
    "addr:full":"33-35 King Street Saffron Walden Cambridgeshire CB10 1EU",
    "addr:housenumber":"33-35",
    "addr:postcode":"cb10 1eu",
    "addr:street":"King Street",
    "iso:country":"GB",
    "sg:address":"33-35 King Street",
    "sg:city":"Saffron Walden",
    "sg:classifiers":[
        {
            "category":"Shopping",
            "subcategory":"Pharmacy",
            "type":"Retail Goods"
        }
    ],
    "sg:phone":"+44 1799 513461",
    "sg:postcode":"CB10 1EU",
    "sg:province":"Cambridgeshire",
    "sg:tags":[
        "store",
        "drug",
        "outlet"
    ],
    "wof:name":"Superdrug Stores plc",
    "wof:placetype":"venue"
},
  "geometry": {"coordinates":[0.2394489944,52.0230636597],"type":"Point"}
}