{
  "type": "Feature",
  "properties": {
    "iso:country":"GB",
    "sg:address":"Malvern Hill Cottage, Marston Road",
    "sg:city":"Cheltenham",
    "sg:classifiers":[
        {
            "category":"Building & Trades",
            "subcategory":"Construction",
            "type":"Services"
        }
    ],
    "sg:phone":"+44 1242 244413",
    "sg:postcode":"GL52 3JQ",
    "sg:province":"Gloucestershire",
    "sg:tags":[
        "supplier",
        "installers",
        "builder",
        "cladding"
    ],
    "wof:name":"Neil Waterman Building Contractors",
    "wof:placetype":"venue"
},
  "geometry": {"coordinates":[-2.06588,51.912708],"type":"Point"}
}