{
  "type": "Feature",
  "properties": {
    "addr:full":"41 Princess Road Manchester Greater Manchester M14 4TE",
    "addr:housenumber":"41",
    "addr:postcode":"m14 4te",
    "addr:street":"Princess Road",
    "iso:country":"GB",
    "sg:address":"41 Princess Road",
    "sg:city":"Manchester",
    "sg:classifiers":[
        {
            "category":"Food & Beverages",
            "subcategory":"Meat & Fish",
            "type":"Retail Goods"
        }
    ],
    "sg:postcode":"M14 4TE",
    "sg:province":"Greater Manchester",
    "sg:tags":[
        "butcher"
    ],
    "wof:name":"Reid's Butchers",
    "wof:placetype":"venue"
},
  "geometry": {"coordinates":[-2.241465,53.478439],"type":"Point"}
}