{
  "type": "Feature",
  "properties": {
    "addr:full":"78 Albion St Castleford West Yorkshire WF10 1QX",
    "addr:housenumber":"78",
    "addr:postcode":"wf10 1qx",
    "addr:street":"Albion St",
    "iso:country":"GB",
    "sg:address":"78 Albion St",
    "sg:city":"Castleford",
    "sg:classifiers":[
        {
            "category":"Shopping",
            "subcategory":"Discount & Variety Stores",
            "type":"Retail Goods"
        }
    ],
    "sg:phone":"+44 1977 555167",
    "sg:postcode":"WF10 1QX",
    "sg:province":"West Yorkshire",
    "sg:tags":[
        "shop",
        "model"
    ],
    "wof:name":"Castleford Car Alarms",
    "wof:placetype":"venue"
},
  "geometry": {"coordinates":[-1.3588689566,53.724571228],"type":"Point"}
}