{
  "type": "Feature",
  "properties": {
    "addr:full":"Westbrook Centre, Westbrook Warrington Cheshire WA5 8UD",
    "addr:postcode":"wa5 8ud",
    "addr:street":"Westbrook",
    "iso:country":"GB",
    "sg:address":"Westbrook Centre, Westbrook",
    "sg:city":"Warrington",
    "sg:classifiers":[
        {
            "category":"Cinema",
            "subcategory":"Movie Theater",
            "type":"Entertainment"
        }
    ],
    "sg:phone":"+44 1925 416698",
    "sg:postcode":"WA5 8UD",
    "sg:province":"Cheshire",
    "wof:name":"Uci 10 Cinemas",
    "wof:placetype":"venue"
},
  "geometry": {"coordinates":[-2.6363620758,53.4080162048],"type":"Point"}
}