{
  "type": "Feature",
  "properties": {
    "addr:full":"3 Old Grove Court Norwich Norfolk NR3 3NL",
    "addr:housenumber":"3",
    "addr:postcode":"nr3 3nl",
    "addr:street":"Old Grove Court",
    "iso:country":"GB",
    "sg:address":"3 Old Grove Court",
    "sg:city":"Norwich",
    "sg:classifiers":[
        {
            "category":"Retail",
            "subcategory":"Repair Shop",
            "type":"Services"
        }
    ],
    "sg:phone":"+44 1603 404799",
    "sg:postcode":"NR3 3NL",
    "sg:province":"Norfolk",
    "sg:tags":[
        "upholsterer"
    ],
    "wof:name":"R A Cullum",
    "wof:placetype":"venue"
},
  "geometry": {"coordinates":[1.2901070118,52.6500701904],"type":"Point"}
}