{
  "type": "Feature",
  "properties": {
    "addr:full":"29 Kingston Road Southall Greater London UB2 4AP",
    "addr:housenumber":"29",
    "addr:postcode":"ub2 4ap",
    "addr:street":"Kingston Road",
    "iso:country":"GB",
    "sg:address":"29 Kingston Road",
    "sg:city":"Southall",
    "sg:classifiers":[
        {
            "category":"Social Services",
            "subcategory":"Retirement Home",
            "type":"Services"
        }
    ],
    "sg:postcode":"UB2 4AP",
    "sg:province":"Greater London",
    "sg:tags":[
        "residential",
        "care"
    ],
    "wof:name":"The Abbeyfield Hounslow Society Ltd",
    "wof:placetype":"venue"
},
  "geometry": {"coordinates":[-0.3785449862,51.5039863586],"type":"Point"}
}