{
  "type": "Feature",
  "properties": {
    "addr:full":"121 Ormskirk Road, Newtown Wigan Lancashire WN5 9EA",
    "addr:housenumber":"121",
    "addr:postcode":"wn5 9ea",
    "addr:street":"Ormskirk Road",
    "iso:country":"GB",
    "sg:address":"121 Ormskirk Road, Newtown",
    "sg:city":"Wigan",
    "sg:classifiers":[
        {
            "category":"Fast Food",
            "type":"Food & Drink"
        }
    ],
    "sg:postcode":"WN5 9EA",
    "sg:province":"Lancashire",
    "sg:tags":[
        "away",
        "take"
    ],
    "wof:name":"Pizza Heaven",
    "wof:placetype":"venue"
},
  "geometry": {"coordinates":[-2.653407,53.539444],"type":"Point"}
}