{
  "type": "Feature",
  "properties": {
    "addr:full":"The Connifers, Badger Rise, Sportishead Bristol Somerset BS20 8LU",
    "addr:postcode":"bs20 8lu",
    "addr:street":"Badger Rise",
    "iso:country":"GB",
    "sg:address":"The Connifers, Badger Rise, Sportishead",
    "sg:city":"Bristol",
    "sg:classifiers":[
        {
            "category":"Professional",
            "subcategory":"Advertising",
            "type":"Services"
        }
    ],
    "sg:phone":"+44 1275 371117",
    "sg:postcode":"BS20 8LU",
    "sg:province":"Somerset",
    "sg:tags":[
        "agency"
    ],
    "wof:name":"Alternative Advertising",
    "wof:placetype":"venue"
},
  "geometry": {"coordinates":[-2.8021800518,51.4743614197],"type":"Point"}
}