{
  "type": "Feature",
  "properties": {
    "addr:full":"22 Dagenham Rd Leyton Greater London E10 7LH",
    "addr:housenumber":"22",
    "addr:postcode":"e10 7lh",
    "addr:street":"Dagenham Rd",
    "iso:country":"GB",
    "sg:address":"22 Dagenham Rd",
    "sg:city":"Leyton",
    "sg:classifiers":[
        {
            "category":"Military Area",
            "subcategory":"Air Force Base",
            "type":"Public Place"
        }
    ],
    "sg:phone":"+44 20 8673 5454",
    "sg:postcode":"E10 7LH",
    "sg:province":"Greater London",
    "sg:tags":[
        "taxi",
        "hire",
        "private"
    ],
    "wof:name":"Southside Cars",
    "wof:placetype":"venue"
},
  "geometry": {"coordinates":[-0.027039,51.568905],"type":"Point"}
}