{
  "type": "Feature",
  "properties": {
    "addr:full":"Whitehill Swindon Wiltshire SN5 6PA",
    "addr:postcode":"sn5 6pa",
    "iso:country":"GB",
    "sg:address":"Whitehill",
    "sg:city":"Swindon",
    "sg:classifiers":[
        {
            "category":"Real Estate",
            "subcategory":"Developer",
            "type":"Services"
        },
        {
            "category":"Real Estate",
            "subcategory":"Real Estate Agent",
            "type":"Services"
        }
    ],
    "sg:phone":"+44 1793 870358",
    "sg:postcode":"SN5 6PA",
    "sg:province":"Wiltshire",
    "sg:tags":[
        "property"
    ],
    "wof:name":"Windmill Hill Business Park",
    "wof:placetype":"venue"
},
  "geometry": {"coordinates":[-1.838219,51.555676],"type":"Point"}
}