{
  "type": "Feature",
  "properties": {
    "addr:full":"51 New Street, Rothes Aberlour Moray AB38 7BJ",
    "addr:housenumber":"51",
    "addr:postcode":"ab38 7bj",
    "addr:street":"New Street",
    "iso:country":"GB",
    "sg:address":"51 New Street, Rothes",
    "sg:city":"Aberlour",
    "sg:classifiers":[
        {
            "category":"Travel",
            "subcategory":"Hotels & Motels",
            "type":"Entertainment"
        }
    ],
    "sg:phone":"+44 1340 831240",
    "sg:postcode":"AB38 7BJ",
    "sg:province":"Moray",
    "wof:name":"The Ben Aigen Hotel",
    "wof:placetype":"venue"
},
  "geometry": {"coordinates":[-3.2079811096,57.5289878845],"type":"Point"}
}