{
  "type": "Feature",
  "properties": {
    "addr:full":"New Tythe Street, Long Eaton Nottingham Derbyshire NG10 2DL",
    "addr:postcode":"ng10 2dl",
    "addr:street":"New Tythe Street",
    "iso:country":"GB",
    "sg:address":"New Tythe Street, Long Eaton",
    "sg:city":"Nottingham",
    "sg:classifiers":[
        {
            "category":"Shopping",
            "subcategory":"Crafts & Fabrics",
            "type":"Retail Goods"
        },
        {
            "category":"Home & Garden",
            "subcategory":"Furniture",
            "type":"Retail Goods"
        }
    ],
    "sg:phone":"+44 115 973 3446",
    "sg:postcode":"NG10 2DL",
    "sg:province":"Derbyshire",
    "sg:tags":[
        "upholsterers'",
        "supply"
    ],
    "wof:name":"GREENSMITH UPHOLSTERY LTD",
    "wof:placetype":"venue"
},
  "geometry": {"coordinates":[-1.264044,52.895531],"type":"Point"}
}