{
  "type": "Feature",
  "properties": {
    "addr:full":"33 Broad Street Bromyard Herefordshire HR7 4BT",
    "addr:housenumber":"33",
    "addr:postcode":"hr7 4bt",
    "addr:street":"Broad Street",
    "iso:country":"GB",
    "sg:address":"33 Broad Street",
    "sg:city":"Bromyard",
    "sg:classifiers":[
        {
            "category":"Home & Garden",
            "subcategory":"Household Appliances",
            "type":"Retail Goods"
        }
    ],
    "sg:phone":"+44 1885 488262",
    "sg:postcode":"HR7 4BT",
    "sg:province":"Herefordshire",
    "sg:tags":[
        "electrical",
        "domestic"
    ],
    "wof:name":"Jolly Rogers Lighthouse",
    "wof:placetype":"venue"
},
  "geometry": {"coordinates":[-2.5054988861,52.1888313293],"type":"Point"}
}