{
  "type": "Feature",
  "properties": {
    "iso:country":"GB",
    "sg:address":"20 Bridge Street, Slaithwaite",
    "sg:city":"Huddersfield",
    "sg:classifiers":[
        {
            "category":"Farming",
            "subcategory":"Nursery",
            "type":"Manufacturing & Wholesale Goods"
        },
        {
            "category":"Social Services",
            "subcategory":"Child Care",
            "type":"Services"
        }
    ],
    "sg:phone":"+44 1484 848440",
    "sg:postcode":"HD7 5JN",
    "sg:province":"West Yorkshire",
    "sg:tags":[
        "creche"
    ],
    "wof:name":"Cornfields",
    "wof:placetype":"venue"
},
  "geometry": {"coordinates":[-1.875565,53.623035],"type":"Point"}
}