{
  "type": "Feature",
  "properties": {
    "iso:country":"GB",
    "sg:address":"Northwoods Farm, Dacre",
    "sg:city":"Harrogate",
    "sg:classifiers":[
        {
            "category":"Farming",
            "subcategory":"Livestock Farm",
            "type":"Manufacturing & Wholesale Goods"
        }
    ],
    "sg:phone":"+44 1423 780225",
    "sg:postcode":"HG3 4EU",
    "sg:province":"North Yorkshire",
    "sg:tags":[
        "others"
    ],
    "wof:name":"F B Stoney",
    "wof:placetype":"venue"
},
  "geometry": {"coordinates":[-1.707774,54.043049],"type":"Point"}
}