{
  "type": "Feature",
  "properties": {
    "addr:full":"Ford Road, Upton Wirral Merseyside CH49 0TB",
    "addr:postcode":"ch49 0tb",
    "addr:street":"Ford Road",
    "iso:country":"GB",
    "sg:address":"Ford Road, Upton",
    "sg:city":"Wirral",
    "sg:classifiers":[
        {
            "category":"Building & Trades",
            "subcategory":"Construction",
            "type":"Services"
        }
    ],
    "sg:postcode":"CH49 0TB",
    "sg:province":"Merseyside",
    "sg:tags":[
        "conversion",
        "loft"
    ],
    "wof:name":"North West Loft Conversions",
    "wof:placetype":"venue"
},
  "geometry": {"coordinates":[-3.0885689259,53.3851318359],"type":"Point"}
}