{
  "type": "Feature",
  "properties": {
    "addr:full":"Alexandra House, 43 Alexandra St Nottingham Nottinghamshire NG5 1AY",
    "addr:housenumber":"43",
    "addr:postcode":"ng5 1ay",
    "addr:street":"Alexandra St",
    "iso:country":"GB",
    "sg:address":"Alexandra House, 43 Alexandra St",
    "sg:city":"Nottingham",
    "sg:classifiers":[
        {
            "category":"Professional",
            "subcategory":"Accounting & Tax Preparation",
            "type":"Services"
        }
    ],
    "sg:phone":"+44 115 962 1590",
    "sg:postcode":"NG5 1AY",
    "sg:province":"Nottinghamshire",
    "sg:tags":[
        "accountant"
    ],
    "wof:name":"Hobsons Chartered Accountants",
    "wof:placetype":"venue"
},
  "geometry": {"coordinates":[-1.155337,52.973015],"type":"Point"}
}