{
  "type": "Feature",
  "properties": {
    "addr:full":"Marshfield, Instow Bideford Devon EX39 4HS",
    "addr:postcode":"ex39 4hs",
    "iso:country":"GB",
    "sg:address":"Marshfield, Instow",
    "sg:city":"Bideford",
    "sg:classifiers":[
        {
            "category":"Manufacturing",
            "subcategory":"Rubber & Plastics",
            "type":"Manufacturing & Wholesale Goods"
        }
    ],
    "sg:phone":"+44 1271 861091",
    "sg:postcode":"EX39 4HS",
    "sg:province":"Devon",
    "sg:tags":[
        "injection",
        "moulding"
    ],
    "wof:name":"Lyndale Plastics",
    "wof:placetype":"venue"
},
  "geometry": {"coordinates":[-4.178523,51.054031],"type":"Point"}
}