{
  "type": "Feature",
  "properties": {
    "iso:country":"GB",
    "sg:address":"61 Colebrook La",
    "sg:city":"Loughton",
    "sg:classifiers":[
        {
            "category":"Professional",
            "subcategory":"Engineering",
            "type":"Services"
        }
    ],
    "sg:postcode":"IG10 2HL",
    "sg:province":"Essex",
    "sg:tags":[
        "contractor",
        "electrical",
        "engineer"
    ],
    "wof:name":"Frank,Daniel,",
    "wof:placetype":"venue"
},
  "geometry": {"coordinates":[0.0787699968,51.6554870605],"type":"Point"}
}