{
  "type": "Feature",
  "properties": {
    "addr:full":"199 Rickmansworth Road Watford Hertfordshire WD18 7JH",
    "addr:housenumber":"199",
    "addr:postcode":"wd18 7jh",
    "addr:street":"Rickmansworth Road",
    "iso:country":"GB",
    "sg:address":"199 Rickmansworth Road",
    "sg:city":"Watford",
    "sg:classifiers":[
        {
            "category":"Building & Trades",
            "subcategory":"Construction",
            "type":"Services"
        }
    ],
    "sg:postcode":"WD18 7JH",
    "sg:province":"Hertfordshire",
    "sg:tags":[
        "builder"
    ],
    "wof:name":"C & L Builders",
    "wof:placetype":"venue"
},
  "geometry": {"coordinates":[-0.4220370054,51.6533164978],"type":"Point"}
}