{
  "type": "Feature",
  "properties": {
    "iso:country":"GB",
    "sg:address":"6 Connaught Road",
    "sg:city":"Ilford",
    "sg:classifiers":[
        {
            "category":"Wholesale",
            "subcategory":"Apparel",
            "type":"Manufacturing & Wholesale Goods"
        },
        {
            "category":"Manufacturing",
            "subcategory":"Retail Goods",
            "type":"Manufacturing & Wholesale Goods"
        }
    ],
    "sg:phone":"+44 20 8478 6700",
    "sg:postcode":"IG1 1QT",
    "sg:province":"Essex",
    "sg:tags":[
        "manufacture",
        "child",
        "childrens",
        "babywear"
    ],
    "wof:name":"K S Kids Ltd.",
    "wof:placetype":"venue"
},
  "geometry": {"coordinates":[0.08476,51.560631],"type":"Point"}
}