{
  "type": "Feature",
  "properties": {
    "addr:full":"Wobaston Road, Fordhouses Wolverhampton Staffordshire WV10 6QJ",
    "addr:postcode":"wv10 6qj",
    "addr:street":"Wobaston Road Fordhouses",
    "iso:country":"GB",
    "sg:address":"Wobaston Road, Fordhouses",
    "sg:city":"Wolverhampton",
    "sg:classifiers":[
        {
            "category":"Personal",
            "type":"Services"
        }
    ],
    "sg:phone":"+44 1902 398069",
    "sg:postcode":"WV10 6QJ",
    "sg:province":"Staffordshire",
    "sg:tags":[
        "delivery"
    ],
    "wof:name":"Rowan Services",
    "wof:placetype":"venue"
},
  "geometry": {"coordinates":[-2.12762,52.627979],"type":"Point"}
}