{
  "type": "Feature",
  "properties": {
    "addr:full":"14 Louches Lane, Naphill High Wycombe Buckinghamshire HP14 4QH",
    "addr:housenumber":"14",
    "addr:postcode":"hp14 4qh",
    "addr:street":"Louches Lane Naphill",
    "iso:country":"GB",
    "sg:address":"14 Louches Lane, Naphill",
    "sg:city":"High Wycombe",
    "sg:classifiers":[
        {
            "category":"Professional",
            "subcategory":"Engineering",
            "type":"Services"
        }
    ],
    "sg:phone":"+44 1494 562581",
    "sg:postcode":"HP14 4QH",
    "sg:province":"Buckinghamshire",
    "sg:tags":[
        "contractor",
        "electrical",
        "engineer"
    ],
    "wof:name":"K Powell Electrical",
    "wof:placetype":"venue"
},
  "geometry": {"coordinates":[-0.771725,51.662045],"type":"Point"}
}