{
  "type": "Feature",
  "properties": {
    "iso:country":"GB",
    "sg:address":"2 Fair Park Road, Cattle Market",
    "sg:city":"Liskeard",
    "sg:classifiers":[
        {
            "category":"Insurance",
            "subcategory":"Insurance Agent",
            "type":"Services"
        }
    ],
    "sg:phone":"+44 1579 342870",
    "sg:postcode":"PL14 4BA",
    "sg:province":"Cornwall",
    "wof:name":"N F U Mutual & Avon Group",
    "wof:placetype":"venue"
},
  "geometry": {"coordinates":[-4.466427,50.453598],"type":"Point"}
}