{
  "type": "Feature",
  "properties": {
    "addr:full":"48 Godmanston Close, Canford Heath Poole Dorset BH17 8BU",
    "addr:housenumber":"48",
    "addr:postcode":"bh17 8bu",
    "addr:street":"Godmanston Close",
    "iso:country":"GB",
    "sg:address":"48 Godmanston Close, Canford Heath",
    "sg:city":"Poole",
    "sg:classifiers":[
        {
            "category":"Professional",
            "type":"Services"
        }
    ],
    "sg:phone":"+44 1202 770044",
    "sg:postcode":"BH17 8BU",
    "sg:province":"Dorset",
    "sg:tags":[
        "repair",
        "tech",
        "maintenance"
    ],
    "wof:name":"Bits & P C's (Euro) Ltd.",
    "wof:placetype":"venue"
},
  "geometry": {"coordinates":[-1.955074,50.749104],"type":"Point"}
}