{
  "type": "Feature",
  "properties": {
    "iso:country":"GB",
    "sg:address":"Queens Sq",
    "sg:city":"Corby",
    "sg:classifiers":[
        {
            "category":"Shopping",
            "subcategory":"Catalog Store",
            "type":"Retail Goods"
        }
    ],
    "sg:phone":"+44 1536 401263",
    "sg:postcode":"NN17 1PA",
    "sg:province":"Northamptonshire",
    "sg:tags":[
        "catalogue",
        "showroom"
    ],
    "wof:name":"Index The Catalogue Shop",
    "wof:placetype":"venue"
},
  "geometry": {"coordinates":[-0.701749,52.487171],"type":"Point"}
}