{
  "type": "Feature",
  "properties": {
    "addr:full":"Prospect Road Harrogate North Yorkshire HG2 7PW",
    "addr:postcode":"hg2 7pw",
    "addr:street":"Prospect Road",
    "iso:country":"GB",
    "sg:address":"Prospect Road",
    "sg:city":"Harrogate",
    "sg:classifiers":[
        {
            "category":"Building & Trades",
            "subcategory":"Equipment Rental",
            "type":"Services"
        }
    ],
    "sg:phone":"+44 1423 812293",
    "sg:postcode":"HG2 7PW",
    "sg:province":"North Yorkshire",
    "sg:tags":[
        "plant",
        "machinery"
    ],
    "wof:name":"Groundforce",
    "wof:placetype":"venue"
},
  "geometry": {"coordinates":[-1.501109004,53.9976768494],"type":"Point"}
}