{
  "type": "Feature",
  "properties": {
    "addr:full":"2 Nixon Street, Castleton Rochdale Lancashire OL11 3JN",
    "addr:housenumber":"2",
    "addr:postcode":"ol11 3jn",
    "addr:street":"Nixon Street",
    "iso:country":"GB",
    "sg:address":"2 Nixon Street, Castleton",
    "sg:city":"Rochdale",
    "sg:classifiers":[
        {
            "category":"Shopping",
            "subcategory":"News",
            "type":"Retail Goods"
        }
    ],
    "sg:phone":"+44 1706 631851",
    "sg:postcode":"OL11 3JN",
    "sg:province":"Lancashire",
    "sg:tags":[
        "newsagent"
    ],
    "wof:name":"I E & H V Partington",
    "wof:placetype":"venue"
},
  "geometry": {"coordinates":[-2.182362,53.59684],"type":"Point"}
}