{
  "type": "Feature",
  "properties": {
    "addr:full":"Flat 11 Vincent Court, Seymour Place London Greater London W1H 2ND",
    "addr:housenumber":"flat 11",
    "addr:postcode":"w1h 2nd",
    "addr:street":"Vincent Court Seymour Place",
    "iso:country":"GB",
    "sg:address":"Flat 11 Vincent Court, Seymour Place",
    "sg:city":"London",
    "sg:classifiers":[
        {
            "category":"Health Services",
            "subcategory":"Dentist",
            "type":"Services"
        }
    ],
    "sg:phone":"+44 20 7402 7303",
    "sg:postcode":"W1H 2ND",
    "sg:province":"Greater London",
    "wof:name":"Michael Szasz",
    "wof:placetype":"venue"
},
  "geometry": {"coordinates":[-0.16216,51.517448],"type":"Point"}
}