{
  "type": "Feature",
  "properties": {
    "addr:full":"Southe East Site Office, Dungeness B Power Station Romney Marsh Kent TN29 9PL",
    "addr:postcode":"tn29 9pl",
    "iso:country":"GB",
    "sg:address":"Southe East Site Office, Dungeness B Power Station",
    "sg:city":"Romney Marsh",
    "sg:classifiers":[
        {
            "category":"Utilities",
            "subcategory":"Electric",
            "type":"Services"
        }
    ],
    "sg:phone":"+44 1797 343030",
    "sg:postcode":"TN29 9PL",
    "sg:province":"Kent",
    "sg:tags":[
        "electricity"
    ],
    "wof:name":"British Energy Generation Ltd.",
    "wof:placetype":"venue"
},
  "geometry": {"coordinates":[0.9772289991,50.9158821106],"type":"Point"}
}