{
  "type": "Feature",
  "properties": {
    "iso:country":"GB",
    "sg:address":"The Barn, Ashgrove Farm, Leamington Road",
    "sg:city":"Warwick",
    "sg:classifiers":[
        {
            "category":"Personal",
            "type":"Services"
        },
        {
            "category":"Retail",
            "subcategory":"Auto Rental",
            "type":"Services"
        }
    ],
    "sg:phone":"+44 1926 613030",
    "sg:postcode":"CV33 9PQ",
    "sg:province":"Warwickshire",
    "sg:tags":[
        "chauffeur",
        "car",
        "hire",
        "driven",
        "wedding"
    ],
    "wof:name":"Aristoclassics",
    "wof:placetype":"venue"
},
  "geometry": {"coordinates":[-1.4488,52.259541],"type":"Point"}
}