{
  "type": "Feature",
  "properties": {
    "iso:country":"GB",
    "sg:address":"18 Commercial Street, Nelson",
    "sg:city":"Treharris",
    "sg:classifiers":[
        {
            "category":"Fast Food",
            "type":"Food & Drink"
        }
    ],
    "sg:phone":"+44 1443 451133",
    "sg:postcode":"CF46 6NF",
    "sg:province":"Caerphilly",
    "sg:tags":[
        "away",
        "meal",
        "outlet",
        "take"
    ],
    "wof:name":"Lucky Dragon",
    "wof:placetype":"venue"
},
  "geometry": {"coordinates":[-3.3155488968,51.7024154663],"type":"Point"}
}