{
  "type": "Feature",
  "properties": {
    "addr:full":"Spring Barn Farm, Kingston Road Lewes East Sussex BN7 3ND",
    "addr:postcode":"bn7 3nd",
    "addr:street":"Kingston Road",
    "iso:country":"GB",
    "sg:address":"Spring Barn Farm, Kingston Road",
    "sg:city":"Lewes",
    "sg:classifiers":[
        {
            "category":"Farming",
            "subcategory":"Farm",
            "type":"Manufacturing & Wholesale Goods"
        }
    ],
    "sg:postcode":"BN7 3ND",
    "sg:province":"East Sussex",
    "sg:tags":[
        "mixed",
        "crop"
    ],
    "wof:name":"T A Carr",
    "wof:placetype":"venue"
},
  "geometry": {"coordinates":[-0.023668,50.85918],"type":"Point"}
}