{
  "type": "Feature",
  "properties": {
    "iso:country":"GB",
    "sg:address":"Warden, 17 Blythe Way",
    "sg:city":"Sandy",
    "sg:classifiers":[
        {
            "category":"Social Services",
            "subcategory":"Adult Care",
            "type":"Services"
        }
    ],
    "sg:phone":"+44 1767 650307",
    "sg:postcode":"SG19 3JQ",
    "sg:province":"Bedfordshire",
    "sg:tags":[
        "housing",
        "sheltered"
    ],
    "wof:name":"Blythe Way Sheltered Housing",
    "wof:placetype":"venue"
},
  "geometry": {"coordinates":[-0.291109,52.12928],"type":"Point"}
}