{
  "type": "Feature",
  "properties": {
    "iso:country":"GB",
    "sg:address":"Mill Farm, Great Cheverell",
    "sg:city":"Devizes",
    "sg:classifiers":[
        {
            "category":"Building & Trades",
            "subcategory":"Construction",
            "type":"Services"
        }
    ],
    "sg:phone":"+44 1380 812100",
    "sg:postcode":"SN10 5SF",
    "sg:province":"Wiltshire",
    "sg:tags":[
        "restoration",
        "refurbishment"
    ],
    "wof:name":"Brackstone Building Contractors Ltd.",
    "wof:placetype":"venue"
},
  "geometry": {"coordinates":[-1.9950309992,51.3514785767],"type":"Point"}
}