{
  "type": "Feature",
  "properties": {
    "iso:country":"GB",
    "sg:address":"42-43 Market Pl",
    "sg:city":"Wisbech",
    "sg:classifiers":[
        {
            "category":"Shopping",
            "subcategory":"Music",
            "type":"Retail Goods"
        }
    ],
    "sg:phone":"+44 1945 474945",
    "sg:postcode":"PE13 1DP",
    "sg:province":"Cambridgeshire",
    "sg:tags":[
        "record",
        "tape",
        "cd"
    ],
    "wof:name":"Record Store The",
    "wof:placetype":"venue"
},
  "geometry": {"coordinates":[0.1613979936,52.6648902893],"type":"Point"}
}