{
  "type": "Feature",
  "properties": {
    "iso:country":"GB",
    "sg:address":"Malvern House, 269 Stockton Road",
    "sg:city":"Hartlepool",
    "sg:classifiers":[
        {
            "category":"Utilities",
            "subcategory":"Fuel Oil & Lpg",
            "type":"Services"
        }
    ],
    "sg:postcode":"TS25 5AU",
    "sg:province":"Durham",
    "wof:name":"Malvern Fuels",
    "wof:placetype":"venue"
},
  "geometry": {"coordinates":[-1.215368,54.671898],"type":"Point"}
}