{
  "type": "Feature",
  "properties": {
    "addr:full":"1a Oliver Street Northampton Northamptonshire NN2 7JJ",
    "addr:housenumber":"1a",
    "addr:postcode":"nn2 7jj",
    "addr:street":"Oliver Street",
    "iso:country":"GB",
    "sg:address":"1a Oliver Street",
    "sg:city":"Northampton",
    "sg:classifiers":[
        {
            "category":"Home & Garden",
            "subcategory":"Carpets & Floor Coverings",
            "type":"Retail Goods"
        }
    ],
    "sg:phone":"+44 1604 717770",
    "sg:postcode":"NN2 7JJ",
    "sg:province":"Northamptonshire",
    "sg:tags":[
        "carpets",
        "rug",
        "matting"
    ],
    "wof:name":"Carpet Market",
    "wof:placetype":"venue"
},
  "geometry": {"coordinates":[-0.8794800043,52.2515830994],"type":"Point"}
}