{
  "type": "Feature",
  "properties": {
    "addr:full":"Bridgend Creamery Dingwall Highland IV15 9QG",
    "addr:postcode":"iv15 9qg",
    "addr:street":"Dingwall",
    "iso:country":"GB",
    "sg:address":"Bridgend Creamery",
    "sg:city":"Dingwall",
    "sg:classifiers":[
        {
            "category":"Farming",
            "subcategory":"Dairy Farm",
            "type":"Manufacturing & Wholesale Goods"
        }
    ],
    "sg:phone":"+44 1349 863120",
    "sg:postcode":"IV15 9QG",
    "sg:province":"Highland",
    "wof:name":"North of Scotland Milk Cooperative Society (Claymo",
    "wof:placetype":"venue"
},
  "geometry": {"coordinates":[-4.4314479828,57.5961799622],"type":"Point"}
}