{
  "type": "Feature",
  "properties": {
    "iso:country":"GB",
    "sg:address":"Unit 22, Emley Moor Business Park, Emley Moor",
    "sg:city":"Huddersfield",
    "sg:classifiers":[
        {
            "category":"Real Estate",
            "subcategory":"Real Estate Agent",
            "type":"Services"
        }
    ],
    "sg:phone":"+44 1924 848801",
    "sg:postcode":"HD8 9QY",
    "sg:province":"South Yorkshire",
    "wof:name":"Jeremy N Patterson",
    "wof:placetype":"venue"
},
  "geometry": {"coordinates":[-1.633754015,53.6136207581],"type":"Point"}
}