{
  "type": "Feature",
  "properties": {
    "addr:full":"A20 Firs Farm, Hawkinge Folkestone Kent CT18 7AT",
    "addr:postcode":"ct18 7at",
    "iso:country":"GB",
    "sg:address":"A20 Firs Farm, Hawkinge",
    "sg:city":"Folkestone",
    "sg:classifiers":[
        {
            "category":"Restaurant",
            "type":"Food & Drink"
        }
    ],
    "sg:phone":"+44 1303 279878",
    "sg:postcode":"CT18 7AT",
    "sg:province":"Kent",
    "wof:name":"Little Chef",
    "wof:placetype":"venue"
},
  "geometry": {"coordinates":[1.180008,51.094952],"type":"Point"}
}