{
  "type": "Feature",
  "properties": {
    "addr:full":"Pett Farm, Pett Lane Faversham Kent TN27 0DS",
    "addr:housenumber":"pett",
    "addr:postcode":"tn27 0ds",
    "addr:street":"Pett Lane",
    "iso:country":"GB",
    "sg:address":"Pett Farm, Pett Lane",
    "sg:city":"Faversham",
    "sg:classifiers":[
        {
            "category":"Shopping",
            "subcategory":"Party Supplies",
            "type":"Retail Goods"
        }
    ],
    "sg:phone":"+44 1233 713350",
    "sg:postcode":"TN27 0DS",
    "sg:province":"Kent",
    "sg:tags":[
        "marquees",
        "floor",
        "tent"
    ],
    "wof:name":"Kent Marquees",
    "wof:placetype":"venue"
},
  "geometry": {"coordinates":[0.80611,51.20599],"type":"Point"}
}