{
  "type": "Feature",
  "properties": {
    "iso:country":"GB",
    "sg:address":"453-455 Armstrong Road",
    "sg:city":"Newcastle-upon-tyne",
    "sg:classifiers":[
        {
            "category":"Shopping",
            "subcategory":"Department Store",
            "type":"Retail Goods"
        }
    ],
    "sg:phone":"+44 191 274 4037",
    "sg:postcode":"NE15 6HT",
    "sg:province":"Northumberland",
    "wof:name":"S S Bal",
    "wof:placetype":"venue"
},
  "geometry": {"coordinates":[-1.682103,54.970814],"type":"Point"}
}