{
  "type": "Feature",
  "properties": {
    "iso:country":"GB",
    "sg:address":"Market Chambers, 14 Market Pl",
    "sg:city":"Bedale",
    "sg:classifiers":[
        {
            "category":"Professional",
            "type":"Services"
        }
    ],
    "sg:phone":"+44 1677 424114",
    "sg:postcode":"DL8 1EQ",
    "sg:province":"North Yorkshire",
    "sg:tags":[
        "auctioneer"
    ],
    "wof:name":"Bonhams Group Ltd",
    "wof:placetype":"venue"
},
  "geometry": {"coordinates":[-1.592345953,54.28881073],"type":"Point"}
}