{
  "type": "Feature",
  "properties": {
    "addr:full":"83-85 South Burns Chester-le-street Durham DH2 2AB",
    "addr:housenumber":"83-85",
    "addr:postcode":"dh2 2ab",
    "addr:street":"South Burns",
    "iso:country":"GB",
    "sg:address":"83-85 South Burns",
    "sg:city":"Chester-le-street",
    "sg:classifiers":[
        {
            "category":"Building & Trades",
            "subcategory":"Construction",
            "type":"Services"
        }
    ],
    "sg:phone":"+44 191 388 5703",
    "sg:postcode":"DH2 2AB",
    "sg:province":"Durham",
    "sg:tags":[
        "builder"
    ],
    "wof:name":"L Steel Ltd.",
    "wof:placetype":"venue"
},
  "geometry": {"coordinates":[-1.5811790228,54.8616981506],"type":"Point"}
}