{
  "type": "Feature",
  "properties": {
    "addr:full":"28 Blackwell Street Kidderminster Staffordshire DY10 2DU",
    "addr:housenumber":"28",
    "addr:postcode":"dy10 2du",
    "addr:street":"Blackwell Street",
    "iso:country":"GB",
    "sg:address":"28 Blackwell Street",
    "sg:city":"Kidderminster",
    "sg:classifiers":[
        {
            "category":"Fast Food",
            "type":"Food & Drink"
        }
    ],
    "sg:phone":"+44 1562 820070",
    "sg:postcode":"DY10 2DU",
    "sg:province":"Staffordshire",
    "sg:tags":[
        "away",
        "take"
    ],
    "wof:name":"Maharaja",
    "wof:placetype":"venue"
},
  "geometry": {"coordinates":[-2.247474,52.39032],"type":"Point"}
}