{
  "type": "Feature",
  "properties": {
    "addr:full":"2 Constance Close Witham Essex CM8 1XL",
    "addr:housenumber":"2",
    "addr:postcode":"cm8 1xl",
    "addr:street":"Constance Close",
    "iso:country":"GB",
    "sg:address":"2 Constance Close",
    "sg:city":"Witham",
    "sg:classifiers":[
        {
            "category":"Building & Trades",
            "subcategory":"Plumbing",
            "type":"Services"
        }
    ],
    "sg:phone":"+44 1376 510628",
    "sg:postcode":"CM8 1XL",
    "sg:province":"Essex",
    "sg:tags":[
        "heating"
    ],
    "wof:name":"KDR Plumbing & Heating",
    "wof:placetype":"venue"
},
  "geometry": {"coordinates":[0.644421,51.791889],"type":"Point"}
}