{
  "type": "Feature",
  "properties": {
    "iso:country":"GB",
    "sg:address":"44 Wilmot Way",
    "sg:city":"Banstead",
    "sg:classifiers":[
        {
            "category":"Shopping",
            "subcategory":"Stationery & Office Supplies",
            "type":"Retail Goods"
        }
    ],
    "sg:postcode":"SM7 2PY",
    "sg:province":"Surrey",
    "sg:tags":[
        "equipment",
        "school"
    ],
    "wof:name":"Air Con Equipt",
    "wof:placetype":"venue"
},
  "geometry": {"coordinates":[-0.2027630061,51.32472229],"type":"Point"}
}