{
  "type": "Feature",
  "properties": {
    "iso:country":"GB",
    "sg:address":"6 Lake St",
    "sg:city":"Leighton Buzzard",
    "sg:classifiers":[
        {
            "category":"Home & Garden",
            "subcategory":"Furniture",
            "type":"Retail Goods"
        }
    ],
    "sg:postcode":"LU7 1RT",
    "sg:province":"Bedfordshire",
    "wof:name":"Denton,Nicholas,",
    "wof:placetype":"venue"
},
  "geometry": {"coordinates":[-0.660766,51.916279],"type":"Point"}
}