{
  "type": "Feature",
  "properties": {
    "iso:country":"GB",
    "sg:address":"3 Westbrooke Close, Horndean",
    "sg:city":"Waterlooville",
    "sg:classifiers":[
        {
            "category":"Retail",
            "subcategory":"Repair Shop",
            "type":"Services"
        }
    ],
    "sg:postcode":"PO8 9RE",
    "sg:province":"Hampshire",
    "sg:tags":[
        "radio",
        "television",
        "video"
    ],
    "wof:name":"Alex McFarlane",
    "wof:placetype":"venue"
},
  "geometry": {"coordinates":[-1.013418,50.910015],"type":"Point"}
}