{
  "type": "Feature",
  "properties": {
    "addr:full":"307-309 Mansfield Road Nottingham Nottinghamshire NG5 2DA",
    "addr:housenumber":"307-309",
    "addr:postcode":"ng5 2da",
    "addr:street":"Mansfield Road",
    "iso:country":"GB",
    "sg:address":"307-309 Mansfield Road",
    "sg:city":"Nottingham",
    "sg:classifiers":[
        {
            "category":"Food & Beverages",
            "subcategory":"Liquor & Beverages",
            "type":"Retail Goods"
        }
    ],
    "sg:phone":"+44 115 962 4773",
    "sg:postcode":"NG5 2DA",
    "sg:province":"Nottinghamshire",
    "sg:tags":[
        "beer",
        "spirit",
        "wines"
    ],
    "wof:name":"Wine Rack",
    "wof:placetype":"venue"
},
  "geometry": {"coordinates":[-1.153315,52.971294],"type":"Point"}
}