{
  "type": "Feature",
  "properties": {
    "addr:full":"1 St Nicholas Glebe, Rectory Lane London Greater London SW17 9QH",
    "addr:housenumber":"1",
    "addr:postcode":"sw17 9qh",
    "addr:street":"St Nicholas;Rectory Lane",
    "iso:country":"GB",
    "sg:address":"1 St Nicholas Glebe, Rectory Lane",
    "sg:city":"London",
    "sg:classifiers":[
        {
            "category":"Organizations",
            "subcategory":"Community Association",
            "type":"Services"
        }
    ],
    "sg:phone":"+44 20 8672 2262",
    "sg:postcode":"SW17 9QH",
    "sg:province":"Greater London",
    "sg:tags":[
        "society",
        "housing"
    ],
    "wof:name":"Shaftesbury Housing Association Ltd.",
    "wof:placetype":"venue"
},
  "geometry": {"coordinates":[-0.15967,51.423618],"type":"Point"}
}