{
  "type": "Feature",
  "properties": {
    "addr:full":"Dornfell Street London Greater London NW6 1QL",
    "addr:postcode":"nw6 1ql",
    "addr:street":"Dornfell Street",
    "iso:country":"GB",
    "sg:address":"Dornfell Street",
    "sg:city":"London",
    "sg:classifiers":[
        {
            "category":"Education",
            "subcategory":"School",
            "type":"Public Place"
        },
        {
            "category":"Sports & Exercise",
            "subcategory":"Tennis Court",
            "type":"Entertainment"
        }
    ],
    "sg:postcode":"NW6 1QL",
    "sg:province":"Greater London",
    "sg:tags":[
        "local",
        "authority",
        "leisure"
    ],
    "wof:name":"Beckford Primary School",
    "wof:placetype":"venue"
},
  "geometry": {"coordinates":[-0.199754,51.550884],"type":"Point"}
}