{
  "type": "Feature",
  "properties": {
    "iso:country":"GB",
    "sg:address":"58 Berry Street",
    "sg:city":"Liverpool",
    "sg:classifiers":[
        {
            "category":"Professional",
            "subcategory":"Printing & Photocopies",
            "type":"Services"
        }
    ],
    "sg:phone":"+44 151 709 4550",
    "sg:postcode":"L1 4JQ",
    "sg:province":"Merseyside",
    "sg:tags":[
        "printer"
    ],
    "wof:name":"L Cocker",
    "wof:placetype":"venue"
},
  "geometry": {"coordinates":[-2.976303,53.400574],"type":"Point"}
}