{
  "type": "Feature",
  "properties": {
    "addr:full":"Britannia Ho, 958 High Rd, Finchley London Greater London N12 9RY",
    "addr:housenumber":"958",
    "addr:postcode":"n12 9ry",
    "addr:street":"High Rd",
    "iso:country":"GB",
    "sg:address":"Britannia Ho, 958 High Rd, Finchley",
    "sg:city":"London",
    "sg:classifiers":[
        {
            "category":"Fast Food",
            "type":"Food & Drink"
        }
    ],
    "sg:postcode":"N12 9RY",
    "sg:province":"Greater London",
    "sg:tags":[
        "away",
        "take"
    ],
    "wof:name":"Futurearoma Ltd",
    "wof:placetype":"venue"
},
  "geometry": {"coordinates":[-0.1767639965,51.6158981323],"type":"Point"}
}