{
  "type": "Feature",
  "properties": {
    "addr:full":"111 High Street March Cambridgeshire PE15 9LH",
    "addr:housenumber":"111",
    "addr:postcode":"pe15 9lh",
    "addr:street":"High Street",
    "iso:country":"GB",
    "sg:address":"111 High Street",
    "sg:city":"March",
    "sg:classifiers":[
        {
            "category":"Organizations",
            "subcategory":"Political Organization",
            "type":"Services"
        }
    ],
    "sg:phone":"+44 1354 652295",
    "sg:postcode":"PE15 9LH",
    "sg:province":"Cambridgeshire",
    "sg:tags":[
        "party"
    ],
    "wof:name":"Conservative Association",
    "wof:placetype":"venue"
},
  "geometry": {"coordinates":[0.0872550011,52.5451889038],"type":"Point"}
}