{
  "type": "Feature",
  "properties": {
    "addr:full":"36 Church Street, Lavenham Sudbury Essex CO10 9SA",
    "addr:housenumber":"36",
    "addr:postcode":"co10 9sa",
    "addr:street":"Church Street",
    "iso:country":"GB",
    "sg:address":"36 Church Street, Lavenham",
    "sg:city":"Sudbury",
    "sg:classifiers":[
        {
            "category":"Health Services",
            "subcategory":"Doctor",
            "type":"Services"
        }
    ],
    "sg:phone":"+44 1787 378226",
    "sg:postcode":"CO10 9SA",
    "sg:province":"Essex",
    "sg:tags":[
        "practitioners"
    ],
    "wof:name":"Tessa Norris",
    "wof:placetype":"venue"
},
  "geometry": {"coordinates":[0.794294,52.106655],"type":"Point"}
}