{
  "type": "Feature",
  "properties": {
    "iso:country":"GB",
    "sg:address":"1a Mansel Terrace, Cwmbwrla",
    "sg:city":"Swansea",
    "sg:classifiers":[
        {
            "category":"Shopping",
            "subcategory":"News",
            "type":"Retail Goods"
        }
    ],
    "sg:postcode":"SA5 8NN",
    "sg:province":"Swansea",
    "sg:tags":[
        "newsagent"
    ],
    "wof:name":"M H & G Downing",
    "wof:placetype":"venue"
},
  "geometry": {"coordinates":[-3.9520390034,51.6355361938],"type":"Point"}
}