{
  "type": "Feature",
  "properties": {
    "addr:full":"Queens Park Distribution Centre, Chamberlayne Road London Greater London NW10 3NB",
    "addr:postcode":"nw10 3nb",
    "addr:street":"Queens;Chamberlayne Road",
    "iso:country":"GB",
    "sg:address":"Queens Park Distribution Centre, Chamberlayne Road",
    "sg:city":"London",
    "sg:classifiers":[
        {
            "category":"Manufacturing",
            "subcategory":"Building Materials",
            "type":"Manufacturing & Wholesale Goods"
        }
    ],
    "sg:postcode":"NW10 3NB",
    "sg:province":"Greater London",
    "sg:tags":[
        "merchant",
        "builder"
    ],
    "wof:name":"Lawford & Sons Ltd.",
    "wof:placetype":"venue"
},
  "geometry": {"coordinates":[-0.21715,51.531731],"type":"Point"}
}