{
  "type": "Feature",
  "properties": {
    "iso:country":"GB",
    "sg:address":"The Granary, Telegraph St",
    "sg:city":"Stafford",
    "sg:classifiers":[
        {
            "category":"Professional",
            "subcategory":"Engineering",
            "type":"Services"
        }
    ],
    "sg:phone":"+44 1785 222229",
    "sg:postcode":"ST17 4AT",
    "sg:province":"Staffordshire",
    "sg:tags":[
        "electronic",
        "engineer"
    ],
    "wof:name":"Montronix (UK) Ltd",
    "wof:placetype":"venue"
},
  "geometry": {"coordinates":[-2.1169,52.799332],"type":"Point"}
}