{
  "type": "Feature",
  "properties": {
    "iso:country":"GB",
    "sg:address":"55 Storthes Hall Lane",
    "sg:city":"Huddersfield",
    "sg:classifiers":[
        {
            "category":"Communications",
            "type":"Services"
        }
    ],
    "sg:phone":"+44 1484 607851",
    "sg:postcode":"HD8 0PT",
    "sg:province":"South Yorkshire",
    "sg:tags":[
        "tv",
        "video",
        "radio"
    ],
    "wof:name":"Merlind Services",
    "wof:placetype":"venue"
},
  "geometry": {"coordinates":[-1.730718,53.611622],"type":"Point"}
}