{
  "type": "Feature",
  "properties": {
    "iso:country":"GB",
    "sg:address":"Po Box 43, 2 Church Road",
    "sg:city":"Welwyn Garden City",
    "sg:classifiers":[
        {
            "category":"Recreation",
            "subcategory":"Gun Range",
            "type":"Entertainment"
        }
    ],
    "sg:postcode":"AL8 6PQ",
    "sg:province":"Hertfordshire",
    "sg:tags":[
        "operator",
        "tour"
    ],
    "wof:name":"Austrian Alpine Club",
    "wof:placetype":"venue"
},
  "geometry": {"coordinates":[-0.205729,51.80143],"type":"Point"}
}