{
  "type": "Feature",
  "properties": {
    "iso:country":"GB",
    "sg:address":"9 Hall St",
    "sg:city":"Dalton In Furness",
    "sg:classifiers":[
        {
            "category":"Taxi",
            "type":"Transportation"
        }
    ],
    "sg:phone":"+44 1229 466699",
    "sg:postcode":"LA15 8RS",
    "sg:province":"Cumbria",
    "sg:tags":[
        "mini",
        "cab"
    ],
    "wof:name":"A Line Cars Dalton",
    "wof:placetype":"venue"
},
  "geometry": {"coordinates":[-3.179341,54.157375],"type":"Point"}
}