{
  "type": "Feature",
  "properties": {
    "iso:country":"GB",
    "sg:address":"Frinton-on-sea Delivery Office, Connaught Avenue",
    "sg:city":"Frinton-on-sea",
    "sg:classifiers":[
        {
            "category":"Government",
            "subcategory":"Post Office",
            "type":"Public Place"
        }
    ],
    "sg:phone":"+44 1255 677222",
    "sg:postcode":"CO13 9QB",
    "sg:province":"Essex",
    "wof:name":"Royal Mail",
    "wof:placetype":"venue"
},
  "geometry": {"coordinates":[1.2419110537,51.8380317688],"type":"Point"}
}