{
  "type": "Feature",
  "properties": {
    "addr:full":"69 Francis Avenue St. Albans Hertfordshire AL3 6BW",
    "addr:housenumber":"69",
    "addr:postcode":"al3 6bw",
    "addr:street":"Francis Avenue",
    "iso:country":"GB",
    "sg:address":"69 Francis Avenue",
    "sg:city":"St. Albans",
    "sg:classifiers":[
        {
            "category":"Building & Trades",
            "subcategory":"Construction",
            "type":"Services"
        }
    ],
    "sg:phone":"+44 1727 862209",
    "sg:postcode":"AL3 6BW",
    "sg:province":"Hertfordshire",
    "sg:tags":[
        "joiner",
        "carpenter"
    ],
    "wof:name":"John F Wren",
    "wof:placetype":"venue"
},
  "geometry": {"coordinates":[-0.3415459991,51.7667770386],"type":"Point"}
}