{
  "type": "Feature",
  "properties": {
    "addr:full":"Unit E5, Broadoak Enterprise Village, Broadoak Rd Sittingbourne Kent ME9 8AQ",
    "addr:housenumber":"e5 broadoak",
    "addr:postcode":"me9 8aq",
    "addr:street":"Enterprise Village Broadoak Rd",
    "iso:country":"GB",
    "sg:address":"Unit E5, Broadoak Enterprise Village, Broadoak Rd",
    "sg:city":"Sittingbourne",
    "sg:classifiers":[
        {
            "category":"Home & Garden",
            "subcategory":"Home Furnishings",
            "type":"Retail Goods"
        }
    ],
    "sg:phone":"+44 1795 430399",
    "sg:postcode":"ME9 8AQ",
    "sg:province":"Kent",
    "sg:tags":[
        "awning",
        "canopy",
        "blinds"
    ],
    "wof:name":"A.T Blind Services",
    "wof:placetype":"venue"
},
  "geometry": {"coordinates":[0.73193,51.31295],"type":"Point"}
}