{
  "type": "Feature",
  "properties": {
    "addr:full":"The Park, Gwersyllt Wrexham Wrexham LL11 2DA",
    "addr:postcode":"ll11 2da",
    "iso:country":"GB",
    "sg:address":"The Park, Gwersyllt",
    "sg:city":"Wrexham",
    "sg:classifiers":[
        {
            "category":"Organizations",
            "subcategory":"Membership Organization",
            "type":"Services"
        },
        {
            "category":"Arena",
            "subcategory":"Sports Club",
            "type":"Entertainment"
        }
    ],
    "sg:phone":"+44 1978 720357",
    "sg:postcode":"LL11 2DA",
    "sg:province":"Wrexham",
    "wof:name":"Bradley Gwersyllt Park Sports & Social Club",
    "wof:placetype":"venue"
},
  "geometry": {"coordinates":[-2.997058,53.054523],"type":"Point"}
}