{
  "type": "Feature",
  "properties": {
    "addr:full":"31 Brandhall Court, Wolverhampton Road Oldbury West Midlands B68 8DE",
    "addr:housenumber":"31",
    "addr:postcode":"b68 8de",
    "addr:street":"Brandhall Court Wolverhampton Road",
    "iso:country":"GB",
    "sg:address":"31 Brandhall Court, Wolverhampton Road",
    "sg:city":"Oldbury",
    "sg:classifiers":[
        {
            "category":"Banks & Credit Unions",
            "subcategory":"Financial Services",
            "type":"Services"
        }
    ],
    "sg:phone":"+44 121 422 4688",
    "sg:postcode":"B68 8DE",
    "sg:province":"West Midlands",
    "sg:tags":[
        "consultant"
    ],
    "wof:name":"Moneybox",
    "wof:placetype":"venue"
},
  "geometry": {"coordinates":[-2.004083,52.478954],"type":"Point"}
}