{
  "type": "Feature",
  "properties": {
    "addr:full":"Dunstone, Yealmpton Plymouth Devon PL8 2EL",
    "addr:postcode":"pl8 2el",
    "iso:country":"GB",
    "sg:address":"Dunstone, Yealmpton",
    "sg:city":"Plymouth",
    "sg:classifiers":[
        {
            "category":"Landmark",
            "subcategory":"Tourist Attraction",
            "type":"Public Place"
        }
    ],
    "sg:postcode":"PL8 2EL",
    "sg:province":"Devon",
    "sg:tags":[
        "interest"
    ],
    "wof:name":"National Shire Horse Centre",
    "wof:placetype":"venue"
},
  "geometry": {"coordinates":[-3.9982709885,50.3471794128],"type":"Point"}
}