{
  "type": "Feature",
  "properties": {
    "iso:country":"GB",
    "sg:address":"Churchfield Way, Wye",
    "sg:city":"Ashford",
    "sg:classifiers":[
        {
            "category":"Food & Beverages",
            "subcategory":"Supermarket",
            "type":"Retail Goods"
        }
    ],
    "sg:phone":"+44 1233 812659",
    "sg:postcode":"TN25 5BP",
    "sg:province":"Kent",
    "wof:name":"South Eastern Co-Op Food Stores",
    "wof:placetype":"venue"
},
  "geometry": {"coordinates":[0.936188,51.18401],"type":"Point"}
}