{
  "type": "Feature",
  "properties": {
    "iso:country":"GB",
    "sg:address":"National Counties House, 30 Church Street",
    "sg:city":"Epsom",
    "sg:classifiers":[
        {
            "category":"Banks & Credit Unions",
            "subcategory":"Financial Services",
            "type":"Services"
        }
    ],
    "sg:phone":"+44 1372 724611",
    "sg:postcode":"KT17 4QF",
    "sg:province":"Surrey",
    "sg:tags":[
        "consultant"
    ],
    "wof:name":"National Counties Financial Services Ltd.",
    "wof:placetype":"venue"
},
  "geometry": {"coordinates":[-0.2600640059,51.3303565979],"type":"Point"}
}