{
  "type": "Feature",
  "properties": {
    "addr:full":"Woodrow House, The Holloway Droitwich Worcestershire WR9 8HD",
    "addr:housenumber":"the",
    "addr:postcode":"wr9 8hd",
    "iso:country":"GB",
    "sg:address":"Woodrow House, The Holloway",
    "sg:city":"Droitwich",
    "sg:classifiers":[
        {
            "category":"Organizations",
            "subcategory":"Non-profit Organization",
            "type":"Services"
        }
    ],
    "sg:phone":"+44 1905 794483",
    "sg:postcode":"WR9 8HD",
    "sg:province":"Worcestershire",
    "sg:tags":[
        "organisation",
        "voluntary",
        "charity"
    ],
    "wof:name":"Coventry Charity",
    "wof:placetype":"venue"
},
  "geometry": {"coordinates":[-2.143378973,52.2685050964],"type":"Point"}
}