{
  "type": "Feature",
  "properties": {
    "iso:country":"GB",
    "sg:address":"110 Main Street, Horsley Woodhouse",
    "sg:city":"Ilkeston",
    "sg:classifiers":[
        {
            "category":"Farming",
            "subcategory":"Livestock Farm",
            "type":"Manufacturing & Wholesale Goods"
        }
    ],
    "sg:postcode":"DE7 6AU",
    "sg:province":"Derbyshire",
    "sg:tags":[
        "others"
    ],
    "wof:name":"Trevor F Askey",
    "wof:placetype":"venue"
},
  "geometry": {"coordinates":[-1.395258,52.992542],"type":"Point"}
}