{
  "type": "Feature",
  "properties": {
    "iso:country":"GB",
    "sg:address":"Tower Hill, Chipperfield",
    "sg:city":"King's Langley",
    "sg:classifiers":[
        {
            "category":"Bars & Pubs",
            "type":"Food & Drink"
        }
    ],
    "sg:phone":"+44 1442 833155",
    "sg:postcode":"WD4 9LN",
    "sg:province":"Hertfordshire",
    "sg:tags":[
        "pubs",
        "inn"
    ],
    "wof:name":"The Boot Inn",
    "wof:placetype":"venue"
},
  "geometry": {"coordinates":[-0.5003,51.71125],"type":"Point"}
}