{
  "type": "Feature",
  "properties": {
    "iso:country":"GB",
    "sg:address":"Binley Road",
    "sg:city":"Coventry",
    "sg:classifiers":[
        {
            "category":"Autos & Motor Vehicles",
            "subcategory":"Fuel & Gas Station",
            "type":"Retail Goods"
        }
    ],
    "sg:phone":"+44 24 7645 1149",
    "sg:postcode":"CV3 1HB",
    "sg:province":"Warwickshire",
    "sg:tags":[
        "hr",
        "petrol"
    ],
    "wof:name":"Oakstead",
    "wof:placetype":"venue"
},
  "geometry": {"coordinates":[-1.491889,52.407879],"type":"Point"}
}