{
  "type": "Feature",
  "properties": {
    "iso:country":"GB",
    "sg:address":"68b Eld Rd",
    "sg:city":"Coventry",
    "sg:classifiers":[
        {
            "category":"Retail",
            "subcategory":"Auto Repair",
            "type":"Services"
        }
    ],
    "sg:phone":"+44 24 7666 5355",
    "sg:postcode":"CV6 5DD",
    "sg:province":"Warwickshire",
    "sg:tags":[
        "modification",
        "garage"
    ],
    "wof:name":"R.M.S Car Repairs",
    "wof:placetype":"venue"
},
  "geometry": {"coordinates":[-1.494499,52.429752],"type":"Point"}
}