{
  "type": "Feature",
  "properties": {
    "iso:country":"GB",
    "sg:address":"60 The Broadway",
    "sg:city":"London",
    "sg:classifiers":[
        {
            "category":"Banks & Credit Unions",
            "subcategory":"Bank",
            "type":"Services"
        }
    ],
    "sg:phone":"+44 20 8555 8841",
    "sg:postcode":"E15 1NG",
    "sg:province":"Greater London",
    "wof:name":"Lloyds T S B Bank Plc",
    "wof:placetype":"venue"
},
  "geometry": {"coordinates":[0.00205,51.541458],"type":"Point"}
}