{
  "type": "Feature",
  "properties": {
    "iso:country":"GB",
    "sg:address":"Head Street",
    "sg:city":"Pershore",
    "sg:classifiers":[
        {
            "category":"Professional",
            "subcategory":"Accounting & Tax Preparation",
            "type":"Services"
        }
    ],
    "sg:phone":"+44 1386 553542",
    "sg:postcode":"WR10 1DA",
    "sg:province":"Worcestershire",
    "sg:tags":[
        "stove",
        "woodburning"
    ],
    "wof:name":"Chase Heating Ltd.",
    "wof:placetype":"venue"
},
  "geometry": {"coordinates":[-2.080334,52.113224],"type":"Point"}
}