{
  "type": "Feature",
  "properties": {
    "addr:full":"Woolwards, 358 Roman Rd, Mountnessing Brentwood Essex CM15 0TZ",
    "addr:housenumber":"358",
    "addr:postcode":"cm15 0tz",
    "addr:street":"Roman Rd",
    "iso:country":"GB",
    "sg:address":"Woolwards, 358 Roman Rd, Mountnessing",
    "sg:city":"Brentwood",
    "sg:classifiers":[
        {
            "category":"Transit Center",
            "subcategory":"Passenger",
            "type":"Transportation"
        }
    ],
    "sg:phone":"+44 1277 355550",
    "sg:postcode":"CM15 0TZ",
    "sg:province":"Essex",
    "sg:tags":[
        "ship",
        "broker"
    ],
    "wof:name":"Mercantile Freights Ltd",
    "wof:placetype":"venue"
},
  "geometry": {"coordinates":[0.3553850055,51.6546592712],"type":"Point"}
}