{
  "type": "Feature",
  "properties": {
    "iso:country":"GB",
    "sg:address":"35 Greywell Road, Leigh Park",
    "sg:city":"Havant",
    "sg:classifiers":[
        {
            "category":"Food & Beverages",
            "subcategory":"Supermarket",
            "type":"Retail Goods"
        }
    ],
    "sg:phone":"+44 23 9247 0308",
    "sg:postcode":"PO9 5AL",
    "sg:province":"Hampshire",
    "wof:name":"Kwik Save Stores Ltd.",
    "wof:placetype":"venue"
},
  "geometry": {"coordinates":[-0.985544,50.854496],"type":"Point"}
}