{
  "type": "Feature",
  "properties": {
    "addr:full":"23 Clearwater Way Cardiff Cardiff CF23 6DL",
    "addr:housenumber":"23",
    "addr:postcode":"cf23 6dl",
    "addr:street":"Clearwater Way",
    "iso:country":"GB",
    "sg:address":"23 Clearwater Way",
    "sg:city":"Cardiff",
    "sg:classifiers":[
        {
            "category":"Shopping",
            "subcategory":"News",
            "type":"Retail Goods"
        }
    ],
    "sg:phone":"+44 29 2075 4088",
    "sg:postcode":"CF23 6DL",
    "sg:province":"Cardiff",
    "sg:tags":[
        "newsagent"
    ],
    "wof:name":"United News Shops Ltd.",
    "wof:placetype":"venue"
},
  "geometry": {"coordinates":[-3.169768,51.514545],"type":"Point"}
}