{
  "type": "Feature",
  "properties": {
    "iso:country":"GB",
    "sg:address":"1 Harvesters Way, Weavering",
    "sg:city":"Maidstone",
    "sg:classifiers":[
        {
            "category":"Organizations",
            "subcategory":"Membership Organization",
            "type":"Services"
        }
    ],
    "sg:postcode":"ME14 5SH",
    "sg:province":"Kent",
    "sg:tags":[
        "club"
    ],
    "wof:name":"Agentcourt Ltd",
    "wof:placetype":"venue"
},
  "geometry": {"coordinates":[0.548846,51.272766],"type":"Point"}
}