{
  "type": "Feature",
  "properties": {
    "iso:country":"GB",
    "sg:address":"Ferny Glen, Roch",
    "sg:city":"Haverfordwest",
    "sg:classifiers":[
        {
            "category":"Home & Garden",
            "subcategory":"Garden Supply",
            "type":"Retail Goods"
        }
    ],
    "sg:phone":"+44 1437 710216",
    "sg:postcode":"SA62 6HD",
    "sg:province":"Pembrokeshire",
    "sg:tags":[
        "bulb",
        "grower"
    ],
    "wof:name":"Nicholas & Davies",
    "wof:placetype":"venue"
},
  "geometry": {"coordinates":[-5.0889830589,51.8480606079],"type":"Point"}
}