{
  "type": "Feature",
  "properties": {
    "addr:full":"105 New Park Street Blackburn Lancashire BB2 1DF",
    "addr:housenumber":"105",
    "addr:postcode":"bb2 1df",
    "addr:street":"New Park Street",
    "iso:country":"GB",
    "sg:address":"105 New Park Street",
    "sg:city":"Blackburn",
    "sg:classifiers":[
        {
            "category":"Organizations",
            "subcategory":"Non-profit Organization",
            "type":"Services"
        }
    ],
    "sg:phone":"+44 1254 662424",
    "sg:postcode":"BB2 1DF",
    "sg:province":"Lancashire",
    "sg:tags":[
        "organisation",
        "voluntary",
        "charity"
    ],
    "wof:name":"The Samaritans",
    "wof:placetype":"venue"
},
  "geometry": {"coordinates":[-2.4893579483,53.7518730164],"type":"Point"}
}