{
  "type": "Feature",
  "properties": {
    "addr:full":"11 Court View, Brixton Plymouth Devon PL8 2NY",
    "addr:housenumber":"11",
    "addr:postcode":"pl8 2ny",
    "addr:street":"Court View",
    "iso:country":"GB",
    "sg:address":"11 Court View, Brixton",
    "sg:city":"Plymouth",
    "sg:classifiers":[
        {
            "category":"Building & Trades",
            "subcategory":"Landscaping Services",
            "type":"Services"
        }
    ],
    "sg:postcode":"PL8 2NY",
    "sg:province":"Devon",
    "sg:tags":[
        "landscape",
        "contractor"
    ],
    "wof:name":"Dragon Garden Construction",
    "wof:placetype":"venue"
},
  "geometry": {"coordinates":[-4.034558773,50.3514595032],"type":"Point"}
}