{
  "type": "Feature",
  "properties": {
    "addr:full":"147a St Albans Road Watford Hertfordshire WD24 5BB",
    "addr:housenumber":"147a",
    "addr:postcode":"wd24 5bb",
    "addr:street":"St Albans Road",
    "iso:country":"GB",
    "sg:address":"147a St Albans Road",
    "sg:city":"Watford",
    "sg:classifiers":[
        {
            "category":"Autos & Motor Vehicles",
            "subcategory":"Automobile Sales",
            "type":"Retail Goods"
        }
    ],
    "sg:phone":"+44 1923 244349",
    "sg:postcode":"WD24 5BB",
    "sg:province":"Hertfordshire",
    "sg:tags":[
        "car"
    ],
    "wof:name":"M & M Motors",
    "wof:placetype":"venue"
},
  "geometry": {"coordinates":[-0.3986339867,51.6668357849],"type":"Point"}
}