{
  "type": "Feature",
  "properties": {
    "iso:country":"GB",
    "sg:address":"Station House, Station Road",
    "sg:city":"Wigton",
    "sg:classifiers":[
        {
            "category":"Bus Charters",
            "type":"Transportation"
        },
        {
            "category":"Military Area",
            "subcategory":"Air Force Base",
            "type":"Public Place"
        }
    ],
    "sg:phone":"+44 16973 45007",
    "sg:postcode":"CA7 9BA",
    "sg:province":"Cumbria",
    "sg:tags":[
        "taxi",
        "hire",
        "coach",
        "private"
    ],
    "wof:name":"A P & C A Birtwistle",
    "wof:placetype":"venue"
},
  "geometry": {"coordinates":[-3.161234,54.826408],"type":"Point"}
}