{
  "type": "Feature",
  "properties": {
    "iso:country":"GB",
    "sg:address":"10 Strathavon Clo",
    "sg:city":"Cranleigh",
    "sg:classifiers":[
        {
            "category":"Professional",
            "subcategory":"Art Services",
            "type":"Services"
        }
    ],
    "sg:phone":"+44 1483 277538",
    "sg:postcode":"GU6 8PW",
    "sg:province":"Surrey",
    "sg:tags":[
        "photographer"
    ],
    "wof:name":"Diane Photographics",
    "wof:placetype":"venue"
},
  "geometry": {"coordinates":[-0.5034350157,51.159954071],"type":"Point"}
}