{
  "type": "Feature",
  "properties": {
    "addr:full":"Unit V36 Antiquarious, 135 Kings Road London Greater London SW3 4PW",
    "addr:housenumber":"135",
    "addr:postcode":"sw3 4pw",
    "addr:street":"Kings Road",
    "iso:country":"GB",
    "sg:address":"Unit V36 Antiquarious, 135 Kings Road",
    "sg:city":"London",
    "sg:classifiers":[
        {
            "category":"Shopping",
            "subcategory":"Comic Books",
            "type":"Retail Goods"
        }
    ],
    "sg:phone":"+44 20 7629 7234",
    "sg:postcode":"SW3 4PW",
    "sg:province":"Greater London",
    "sg:tags":[
        "jeweller"
    ],
    "wof:name":"225 Jewellery",
    "wof:placetype":"venue"
},
  "geometry": {"coordinates":[-0.17643,51.48418],"type":"Point"}
}