{
  "type": "Feature",
  "properties": {
    "iso:country":"GB",
    "sg:address":"Unit 3 The Fen, Baston",
    "sg:city":"Peterborough",
    "sg:classifiers":[
        {
            "category":"Autos & Motor Vehicles",
            "subcategory":"Automobile Sales",
            "type":"Retail Goods"
        }
    ],
    "sg:postcode":"PE6 9PT",
    "sg:province":"Cambridgeshire",
    "sg:tags":[
        "car",
        "specialist",
        "sales",
        "classic"
    ],
    "wof:name":"Cooke,J E,",
    "wof:placetype":"venue"
},
  "geometry": {"coordinates":[-0.356869,52.710545],"type":"Point"}
}