{
  "type": "Feature",
  "properties": {
    "iso:country":"GB",
    "sg:address":"12 Clifton Avenue",
    "sg:city":"Hartlepool",
    "sg:classifiers":[
        {
            "category":"Autos & Motor Vehicles",
            "subcategory":"Auto Supplies",
            "type":"Retail Goods"
        }
    ],
    "sg:phone":"+44 1429 869220",
    "sg:postcode":"TS26 9QN",
    "sg:province":"Durham",
    "sg:tags":[
        "car",
        "audio"
    ],
    "wof:name":"Putnoe Radio Service",
    "wof:placetype":"venue"
},
  "geometry": {"coordinates":[-1.2215319872,54.6839065552],"type":"Point"}
}