{
  "type": "Feature",
  "properties": {
    "iso:country":"GB",
    "sg:address":"58 New Road, Deri",
    "sg:city":"Bargoed",
    "sg:classifiers":[
        {
            "category":"Freight",
            "type":"Transportation"
        }
    ],
    "sg:phone":"+44 1443 834085",
    "sg:postcode":"CF81 9GL",
    "sg:province":"Caerphilly",
    "sg:tags":[
        "haulage",
        "road"
    ],
    "wof:name":"Graham Price Transport",
    "wof:placetype":"venue"
},
  "geometry": {"coordinates":[-3.259208,51.705475],"type":"Point"}
}