{
  "type": "Feature",
  "properties": {
    "addr:full":"194 Tollcross Road Glasgow Glasgow City G31 4UZ",
    "addr:housenumber":"194",
    "addr:postcode":"g31 4uz",
    "addr:street":"Tollcross Road",
    "iso:country":"GB",
    "sg:address":"194 Tollcross Road",
    "sg:city":"Glasgow",
    "sg:classifiers":[
        {
            "category":"Bars & Pubs",
            "type":"Food & Drink"
        },
        {
            "category":"Community Center",
            "subcategory":"Social",
            "type":"Public Place"
        }
    ],
    "sg:phone":"+44 141 554 8498",
    "sg:postcode":"G31 4UZ",
    "sg:province":"Glasgow City",
    "sg:tags":[
        "pubs",
        "house",
        "inn",
        "activity"
    ],
    "wof:name":"CHRIS GALLAGHER & STEVEN KELLY",
    "wof:placetype":"venue"
},
  "geometry": {"coordinates":[-4.1917500496,55.849281311],"type":"Point"}
}