{
  "type": "Feature",
  "properties": {
    "addr:full":"72 Egerton Road North Manchester Cheshire M16 0BZ",
    "addr:housenumber":"72",
    "addr:postcode":"m16 0bz",
    "addr:street":"Egerton Road North",
    "iso:country":"GB",
    "sg:address":"72 Egerton Road North",
    "sg:city":"Manchester",
    "sg:classifiers":[
        {
            "category":"Retail",
            "subcategory":"Auto Repair",
            "type":"Services"
        }
    ],
    "sg:postcode":"M16 0BZ",
    "sg:province":"Cheshire",
    "sg:tags":[
        "modification",
        "garage"
    ],
    "wof:name":"Southside Motors",
    "wof:placetype":"venue"
},
  "geometry": {"coordinates":[-2.270955,53.447006],"type":"Point"}
}