{
  "type": "Feature",
  "properties": {
    "iso:country":"GB",
    "sg:address":"8 Marine St, Cwm",
    "sg:city":"Ebbw Vale",
    "sg:classifiers":[
        {
            "category":"Personal",
            "subcategory":"Beauty Salon",
            "type":"Services"
        }
    ],
    "sg:phone":"+44 1495 370702",
    "sg:postcode":"NP23 7ST",
    "sg:province":"Blaenau Gwent",
    "sg:tags":[
        "unisex",
        "hairdresser"
    ],
    "wof:name":"Style-u-like",
    "wof:placetype":"venue"
},
  "geometry": {"coordinates":[-3.1827809811,51.7403144836],"type":"Point"}
}