{
  "type": "Feature",
  "properties": {
    "addr:full":"18 Albert Road Cleethorpes Lincolnshire DN35 8LX",
    "addr:housenumber":"18",
    "addr:postcode":"dn35 8lx",
    "addr:street":"Albert Road",
    "iso:country":"GB",
    "sg:address":"18 Albert Road",
    "sg:city":"Cleethorpes",
    "sg:classifiers":[
        {
            "category":"Travel",
            "subcategory":"Hotels & Motels",
            "type":"Entertainment"
        }
    ],
    "sg:phone":"+44 1472 692988",
    "sg:postcode":"DN35 8LX",
    "sg:province":"Lincolnshire",
    "sg:tags":[
        "house",
        "guest"
    ],
    "wof:name":"DOVEDALE GUEST HOUSE",
    "wof:placetype":"venue"
},
  "geometry": {"coordinates":[-0.0284410007,53.5591583252],"type":"Point"}
}