{
  "type": "Feature",
  "properties": {
    "addr:full":"96 Totteridge Village, Whetstone Totteridge Greater London N20 8AE",
    "addr:housenumber":"96",
    "addr:postcode":"n20 8ae",
    "addr:street":"Totteridge Village",
    "iso:country":"GB",
    "sg:address":"96 Totteridge Village, Whetstone",
    "sg:city":"Totteridge",
    "sg:classifiers":[
        {
            "category":"Health Services",
            "subcategory":"Nursing And Care Facility",
            "type":"Services"
        }
    ],
    "sg:phone":"+44 20 8445 0943",
    "sg:postcode":"N20 8AE",
    "sg:province":"Greater London",
    "sg:tags":[
        "home"
    ],
    "wof:name":"The Conifers",
    "wof:placetype":"venue"
},
  "geometry": {"coordinates":[-0.2061119974,51.6346740723],"type":"Point"}
}