{
  "type": "Feature",
  "properties": {
    "addr:full":"6 Beechcroft Road, Longlevens Gloucester Gloucestershire GL2 9HF",
    "addr:housenumber":"6",
    "addr:postcode":"gl2 9hf",
    "addr:street":"Beechcroft Road",
    "iso:country":"GB",
    "sg:address":"6 Beechcroft Road, Longlevens",
    "sg:city":"Gloucester",
    "sg:classifiers":[
        {
            "category":"Professional",
            "subcategory":"Accounting & Tax Preparation",
            "type":"Services"
        }
    ],
    "sg:phone":"+44 1452 505707",
    "sg:postcode":"GL2 9HF",
    "sg:province":"Gloucestershire",
    "sg:tags":[
        "accountant",
        "activity"
    ],
    "wof:name":"Laurence Myears",
    "wof:placetype":"venue"
},
  "geometry": {"coordinates":[-2.2278590202,51.8802185059],"type":"Point"}
}