{
  "type": "Feature",
  "properties": {
    "addr:full":"Cauldwell Hall Road Ipswich Suffolk IP4 4QE",
    "addr:postcode":"ip4 4qe",
    "addr:street":"Hall Road",
    "iso:country":"GB",
    "sg:address":"Cauldwell Hall Road",
    "sg:city":"Ipswich",
    "sg:classifiers":[
        {
            "category":"Education",
            "subcategory":"Preschool",
            "type":"Public Place"
        }
    ],
    "sg:phone":"+44 1473 721252",
    "sg:postcode":"IP4 4QE",
    "sg:province":"Suffolk",
    "sg:tags":[
        "pre-school",
        "playgroups"
    ],
    "wof:name":"Noah's Ark Playgroup",
    "wof:placetype":"venue"
},
  "geometry": {"coordinates":[1.182379961,52.0610313416],"type":"Point"}
}