{
  "type": "Feature",
  "properties": {
    "addr:full":"5 Market Place Woodstock Oxfordshire OX20 1SY",
    "addr:housenumber":"5",
    "addr:postcode":"ox20 1sy",
    "addr:street":"Market Place",
    "iso:country":"GB",
    "sg:address":"5 Market Place",
    "sg:city":"Woodstock",
    "sg:classifiers":[
        {
            "category":"Professional",
            "subcategory":"Business Services",
            "type":"Services"
        }
    ],
    "sg:phone":"+44 1993 812267",
    "sg:postcode":"OX20 1SY",
    "sg:province":"Oxfordshire",
    "sg:tags":[
        "bookmaker"
    ],
    "wof:name":"Woodstock Turf Accountants",
    "wof:placetype":"venue"
},
  "geometry": {"coordinates":[-1.355902,51.847458],"type":"Point"}
}