{
  "type": "Feature",
  "properties": {
    "iso:country":"GB",
    "sg:address":"Front Street, Sherburn Hill",
    "sg:city":"Durham",
    "sg:classifiers":[
        {
            "category":"Education",
            "subcategory":"School",
            "type":"Public Place"
        },
        {
            "category":"Government",
            "subcategory":"Office",
            "type":"Public Place"
        }
    ],
    "sg:phone":"+44 191 372 0315",
    "sg:postcode":"DH6 1PA",
    "sg:province":"Durham",
    "sg:tags":[
        "local",
        "authority"
    ],
    "wof:name":"Sherburn Hill Primary School",
    "wof:placetype":"venue"
},
  "geometry": {"coordinates":[-1.495069,54.797215],"type":"Point"}
}