{
  "type": "Feature",
  "properties": {
    "addr:full":"126 Sunbridge Rd Bradford West Yorkshire BD1 2ND",
    "addr:housenumber":"126",
    "addr:postcode":"bd1 2nd",
    "addr:street":"Sunbridge Rd",
    "iso:country":"GB",
    "sg:address":"126 Sunbridge Rd",
    "sg:city":"Bradford",
    "sg:classifiers":[
        {
            "category":"Recreation",
            "subcategory":"Gun Range",
            "type":"Entertainment"
        }
    ],
    "sg:phone":"+44 1274 393480",
    "sg:postcode":"BD1 2ND",
    "sg:province":"West Yorkshire",
    "sg:tags":[
        "operator",
        "tour"
    ],
    "wof:name":"Taber Holidays",
    "wof:placetype":"venue"
},
  "geometry": {"coordinates":[-1.757875,53.793987],"type":"Point"}
}