{
  "type": "Feature",
  "properties": {
    "addr:full":"12 Market Place, St Johns Chapel Bishop Auckland Durham DL13 1QF",
    "addr:housenumber":"12;chapel",
    "addr:postcode":"dl13 1qf",
    "addr:street":"Market Place St Johns;Auckland",
    "iso:country":"GB",
    "sg:address":"12 Market Place, St Johns Chapel",
    "sg:city":"Bishop Auckland",
    "sg:classifiers":[
        {
            "category":"Bars & Pubs",
            "type":"Food & Drink"
        },
        {
            "category":"Community Center",
            "subcategory":"Social",
            "type":"Public Place"
        }
    ],
    "sg:phone":"+44 1388 537231",
    "sg:postcode":"DL13 1QF",
    "sg:province":"Durham",
    "sg:tags":[
        "pubs",
        "house",
        "inn",
        "activity"
    ],
    "wof:name":"Golden Lion Hotel",
    "wof:placetype":"venue"
},
  "geometry": {"coordinates":[-2.180259943,54.7361183167],"type":"Point"}
}