{
  "type": "Feature",
  "properties": {
    "addr:full":"Ansley Hall Nuneaton Leicestershire CV10 0QN",
    "addr:postcode":"cv10 0qn",
    "iso:country":"GB",
    "sg:address":"Ansley Hall",
    "sg:city":"Nuneaton",
    "sg:classifiers":[
        {
            "category":"Professional",
            "subcategory":"Engineering",
            "type":"Services"
        }
    ],
    "sg:phone":"+44 24 7639 2543",
    "sg:postcode":"CV10 0QN",
    "sg:province":"Leicestershire",
    "sg:tags":[
        "precision",
        "engineer"
    ],
    "wof:name":"A B M Precisions (Nuneaton)",
    "wof:placetype":"venue"
},
  "geometry": {"coordinates":[-1.539114,52.538971],"type":"Point"}
}