{
  "type": "Feature",
  "properties": {
    "addr:full":"147 High St Poole Dorset BH15 1DN",
    "addr:housenumber":"147",
    "addr:postcode":"bh15 1dn",
    "addr:street":"High St",
    "iso:country":"GB",
    "sg:address":"147 High St",
    "sg:city":"Poole",
    "sg:classifiers":[
        {
            "category":"Food & Beverages",
            "subcategory":"Bakery",
            "type":"Retail Goods"
        }
    ],
    "sg:phone":"+44 1202 674004",
    "sg:postcode":"BH15 1DN",
    "sg:province":"Dorset",
    "sg:tags":[
        "baker"
    ],
    "wof:name":"Three Cooks The",
    "wof:placetype":"venue"
},
  "geometry": {"coordinates":[-1.9832090139,50.7162246704],"type":"Point"}
}