{
  "type": "Feature",
  "properties": {
    "iso:country":"GB",
    "sg:address":"123a Oving Rd",
    "sg:city":"Chichester",
    "sg:classifiers":[
        {
            "category":"Retail",
            "subcategory":"Auto Repair",
            "type":"Services"
        }
    ],
    "sg:phone":"+44 1243 839520",
    "sg:postcode":"PO19 4EP",
    "sg:province":"West Sussex",
    "sg:tags":[
        "modification",
        "garage"
    ],
    "wof:name":"Stares Auto Services",
    "wof:placetype":"venue"
},
  "geometry": {"coordinates":[-0.756301,50.837894],"type":"Point"}
}