{
  "type": "Feature",
  "properties": {
    "iso:country":"GB",
    "sg:address":"2 Bowater St",
    "sg:city":"West Bromwich",
    "sg:classifiers":[
        {
            "category":"Building & Trades",
            "subcategory":"Construction",
            "type":"Services"
        }
    ],
    "sg:postcode":"B70 8AR",
    "sg:province":"West Midlands",
    "sg:tags":[
        "builder"
    ],
    "wof:name":"Swaby,M,",
    "wof:placetype":"venue"
},
  "geometry": {"coordinates":[-1.999977,52.517109],"type":"Point"}
}