{
  "type": "Feature",
  "properties": {
    "addr:full":"156 High Street Honiton Devon EX14 1JX",
    "addr:housenumber":"156",
    "addr:postcode":"ex14 1jx",
    "addr:street":"High Street",
    "iso:country":"GB",
    "sg:address":"156 High Street",
    "sg:city":"Honiton",
    "sg:classifiers":[
        {
            "category":"Food & Beverages",
            "subcategory":"Meat & Fish",
            "type":"Retail Goods"
        },
        {
            "category":"Food & Beverages",
            "subcategory":"Groceries & Convenience Stores",
            "type":"Retail Goods"
        }
    ],
    "sg:phone":"+44 1404 42383",
    "sg:postcode":"EX14 1JX",
    "sg:province":"Devon",
    "sg:tags":[
        "shop",
        "chip"
    ],
    "wof:name":"N George",
    "wof:placetype":"venue"
},
  "geometry": {"coordinates":[-3.192946,50.798489],"type":"Point"}
}