{
  "type": "Feature",
  "properties": {
    "addr:full":"2 The Grn Tadley Berkshire RG26 3PG",
    "addr:housenumber":"2",
    "addr:postcode":"rg26 3pg",
    "addr:street":"The Grn",
    "iso:country":"GB",
    "sg:address":"2 The Grn",
    "sg:city":"Tadley",
    "sg:classifiers":[
        {
            "category":"Professional",
            "subcategory":"Management & Consulting",
            "type":"Services"
        }
    ],
    "sg:postcode":"RG26 3PG",
    "sg:province":"Berkshire",
    "sg:tags":[
        "consultant",
        "business"
    ],
    "wof:name":"P P A",
    "wof:placetype":"venue"
},
  "geometry": {"coordinates":[-1.134366,51.345119],"type":"Point"}
}