{
  "type": "Feature",
  "properties": {
    "iso:country":"GB",
    "sg:address":"19 Cresswell Rd",
    "sg:city":"Twickenham",
    "sg:classifiers":[
        {
            "category":"Real Estate",
            "subcategory":"Surveying",
            "type":"Services"
        }
    ],
    "sg:postcode":"TW1 2EA",
    "sg:province":"Greater London",
    "sg:tags":[
        "surveyor",
        "valuer"
    ],
    "wof:name":"Deane,Nigel,",
    "wof:placetype":"venue"
},
  "geometry": {"coordinates":[-0.308652997,51.4553031921],"type":"Point"}
}