{
  "type": "Feature",
  "properties": {
    "addr:full":"19 The Broadway Surbiton Surrey KT6 7DJ",
    "addr:housenumber":"19",
    "addr:postcode":"kt6 7dj",
    "addr:street":"The Broadway",
    "iso:country":"GB",
    "sg:address":"19 The Broadway",
    "sg:city":"Surbiton",
    "sg:classifiers":[
        {
            "category":"Fast Food",
            "type":"Food & Drink"
        }
    ],
    "sg:phone":"+44 20 8339 9351",
    "sg:postcode":"KT6 7DJ",
    "sg:province":"Surrey",
    "sg:tags":[
        "away",
        "take"
    ],
    "wof:name":"Perfect Fried Chicken",
    "wof:placetype":"venue"
},
  "geometry": {"coordinates":[-0.283589,51.381611],"type":"Point"}
}