{
  "type": "Feature",
  "properties": {
    "addr:full":"16 Lydgate, Northowram Halifax West Yorkshire HX3 7EJ",
    "addr:housenumber":"16",
    "addr:postcode":"hx3 7ej",
    "addr:street":"Lydgate Northowram",
    "iso:country":"GB",
    "sg:address":"16 Lydgate, Northowram",
    "sg:city":"Halifax",
    "sg:classifiers":[
        {
            "category":"Building & Trades",
            "subcategory":"Plumbing",
            "type":"Services"
        }
    ],
    "sg:postcode":"HX3 7EJ",
    "sg:province":"West Yorkshire",
    "sg:tags":[
        "central",
        "heating"
    ],
    "wof:name":"Rawnsley David Plumbing & Heating Engineer",
    "wof:placetype":"venue"
},
  "geometry": {"coordinates":[-1.830521,53.740108],"type":"Point"}
}