{
  "type": "Feature",
  "properties": {
    "iso:country":"GB",
    "sg:address":"18 Skipton Street",
    "sg:city":"Morecambe",
    "sg:classifiers":[
        {
            "category":"Professional",
            "subcategory":"Accounting & Tax Preparation",
            "type":"Services"
        }
    ],
    "sg:phone":"+44 1524 415121",
    "sg:postcode":"LA4 4AR",
    "sg:province":"Lancashire",
    "sg:tags":[
        "accountant",
        "activites",
        "primarily",
        "bookeeping"
    ],
    "wof:name":"Ramsden Armitage & Co.",
    "wof:placetype":"venue"
},
  "geometry": {"coordinates":[-2.868386,54.071892],"type":"Point"}
}