{
  "type": "Feature",
  "properties": {
    "iso:country":"GB",
    "sg:address":"374 Goldhawk Rd",
    "sg:city":"Hammersmith",
    "sg:classifiers":[
        {
            "category":"Building & Trades",
            "subcategory":"Construction",
            "type":"Services"
        }
    ],
    "sg:phone":"+44 20 8741 8188",
    "sg:postcode":"W6 0XA",
    "sg:province":"Greater London",
    "sg:tags":[
        "joinery"
    ],
    "wof:name":"Stamford Brook Joinery",
    "wof:placetype":"venue"
},
  "geometry": {"coordinates":[-0.244719997,51.4956817627],"type":"Point"}
}