{
  "type": "Feature",
  "properties": {
    "addr:full":"Unit 2a, Hatston Industrial Estate Kirkwall Orkney Islands KW15 1RE",
    "addr:housenumber":"unit 2a",
    "addr:postcode":"kw15 1re",
    "addr:street":"Hatston Industrial Estate",
    "iso:country":"GB",
    "sg:address":"Unit 2a, Hatston Industrial Estate",
    "sg:city":"Kirkwall",
    "sg:classifiers":[
        {
            "category":"Communications",
            "subcategory":"Film & Video Production",
            "type":"Services"
        },
        {
            "category":"Retail",
            "subcategory":"Repair Shop",
            "type":"Services"
        },
        {
            "category":"Manufacturing",
            "subcategory":"Electronics",
            "type":"Manufacturing & Wholesale Goods"
        }
    ],
    "sg:phone":"+44 1856 870695",
    "sg:postcode":"KW15 1RE",
    "sg:province":"Orkney Islands",
    "sg:tags":[
        "television",
        "tv",
        "microwave",
        "radio",
        "oven",
        "studio"
    ],
    "wof:name":"A Learmonth",
    "wof:placetype":"venue"
},
  "geometry": {"coordinates":[-2.9604189396,58.9817314148],"type":"Point"}
}