{
  "type": "Feature",
  "properties": {
    "iso:country":"GB",
    "sg:address":"Essex Street Chambers",
    "sg:city":"London",
    "sg:classifiers":[
        {
            "category":"Professional",
            "subcategory":"Lawyer & Legal Services",
            "type":"Services"
        }
    ],
    "sg:postcode":"WC2R 3AT",
    "sg:province":"Greater London",
    "sg:tags":[
        "barrister"
    ],
    "wof:name":"Edwin Glasgow",
    "wof:placetype":"venue"
},
  "geometry": {"coordinates":[-0.113104,51.512863],"type":"Point"}
}