{
  "type": "Feature",
  "properties": {
    "addr:full":"26 Devon Square Newton Abbot Devon TQ12 2HH",
    "addr:housenumber":"26",
    "addr:postcode":"tq12 2hh",
    "addr:street":"Devon Square",
    "iso:country":"GB",
    "sg:address":"26 Devon Square",
    "sg:city":"Newton Abbot",
    "sg:classifiers":[
        {
            "category":"Health Services",
            "subcategory":"Chiropractor",
            "type":"Services"
        }
    ],
    "sg:phone":"+44 1626 202026",
    "sg:postcode":"TQ12 2HH",
    "sg:province":"Devon",
    "wof:name":"Newton Abbot Chiropractic Centre",
    "wof:placetype":"venue"
},
  "geometry": {"coordinates":[-3.604807,50.529335],"type":"Point"}
}