{
  "type": "Feature",
  "properties": {
    "iso:country":"GB",
    "sg:address":"35a Gaolgate St",
    "sg:city":"Stafford",
    "sg:classifiers":[
        {
            "category":"Retail",
            "subcategory":"Photofinishing",
            "type":"Services"
        }
    ],
    "sg:postcode":"ST16 2NU",
    "sg:province":"Staffordshire",
    "sg:tags":[
        "photographic",
        "processor"
    ],
    "wof:name":"Hemsworth Photo Finishers Ltd",
    "wof:placetype":"venue"
},
  "geometry": {"coordinates":[-2.1178290844,52.8080978394],"type":"Point"}
}