{
  "type": "Feature",
  "properties": {
    "addr:full":"Unit 14, Syston Street West Leicester Leicestershire LE1 2JU",
    "addr:housenumber":"unit 14",
    "addr:postcode":"le1 2ju",
    "addr:street":"Syston Street",
    "iso:country":"GB",
    "sg:address":"Unit 14, Syston Street West",
    "sg:city":"Leicester",
    "sg:classifiers":[
        {
            "category":"Professional",
            "subcategory":"Engineering",
            "type":"Services"
        }
    ],
    "sg:phone":"+44 116 251 5254",
    "sg:postcode":"LE1 2JU",
    "sg:province":"Leicestershire",
    "sg:tags":[
        "engineer"
    ],
    "wof:name":"A B K Engineering",
    "wof:placetype":"venue"
},
  "geometry": {"coordinates":[-1.123563,52.644279],"type":"Point"}
}