{
  "type": "Feature",
  "properties": {
    "iso:country":"GB",
    "sg:address":"81 Green Glade, Theydon Bois",
    "sg:city":"Epping",
    "sg:classifiers":[
        {
            "category":"Building & Trades",
            "subcategory":"Construction",
            "type":"Services"
        }
    ],
    "sg:phone":"+44 1992 814204",
    "sg:postcode":"CM16 7LZ",
    "sg:province":"Essex",
    "sg:tags":[
        "joiner",
        "carpenter"
    ],
    "wof:name":"John Rayner",
    "wof:placetype":"venue"
},
  "geometry": {"coordinates":[0.0998210013,51.6679534912],"type":"Point"}
}