{
  "type": "Feature",
  "properties": {
    "iso:country":"GB",
    "sg:address":"143a Union St",
    "sg:city":"Oldham",
    "sg:classifiers":[
        {
            "category":"Shopping",
            "subcategory":"Tobacco",
            "type":"Retail Goods"
        }
    ],
    "sg:phone":"+44 161 624 9941",
    "sg:postcode":"OL1 1TE",
    "sg:province":"Lancashire",
    "sg:tags":[
        "tobacconist"
    ],
    "wof:name":"Woollard The Tobacconist",
    "wof:placetype":"venue"
},
  "geometry": {"coordinates":[-2.1067590714,53.5413665771],"type":"Point"}
}