{
  "type": "Feature",
  "properties": {
    "addr:full":"93 Camberwell Station Road, Camberwell London Greater London SE5 9JJ",
    "addr:housenumber":"93",
    "addr:postcode":"se5 9jj",
    "addr:street":"Camberwell Station Road",
    "iso:country":"GB",
    "sg:address":"93 Camberwell Station Road, Camberwell",
    "sg:city":"London",
    "sg:classifiers":[
        {
            "category":"Organizations",
            "subcategory":"Non-profit Organization",
            "type":"Services"
        }
    ],
    "sg:phone":"+44 20 7737 7475",
    "sg:postcode":"SE5 9JJ",
    "sg:province":"Greater London",
    "sg:tags":[
        "organisation",
        "voluntary",
        "charity"
    ],
    "wof:name":"Shaftesbury Resources Centre",
    "wof:placetype":"venue"
},
  "geometry": {"coordinates":[-0.0987149999,51.4727249146],"type":"Point"}
}