{
  "type": "Feature",
  "properties": {
    "addr:full":"Derby Road, Hathern Loughborough Leicestershire LE12 5LD",
    "addr:postcode":"le12 5ld",
    "addr:street":"Derby Road",
    "iso:country":"GB",
    "sg:address":"Derby Road, Hathern",
    "sg:city":"Loughborough",
    "sg:classifiers":[
        {
            "category":"Autos & Motor Vehicles",
            "subcategory":"Fuel & Gas Station",
            "type":"Retail Goods"
        }
    ],
    "sg:postcode":"LE12 5LD",
    "sg:province":"Leicestershire",
    "sg:tags":[
        "petrol",
        "filling"
    ],
    "wof:name":"Friend Filling Station",
    "wof:placetype":"venue"
},
  "geometry": {"coordinates":[-1.25617,52.792515],"type":"Point"}
}