{
  "type": "Feature",
  "properties": {
    "iso:country":"GB",
    "sg:address":"3 St Marys Gate, Priory Industrial Estate",
    "sg:city":"Birkenhead",
    "sg:classifiers":[
        {
            "category":"Wholesale",
            "subcategory":"Fruits & Vegetables",
            "type":"Manufacturing & Wholesale Goods"
        }
    ],
    "sg:postcode":"CH41 5DW",
    "sg:province":"Merseyside",
    "wof:name":"Simpson's Wholesale",
    "wof:placetype":"venue"
},
  "geometry": {"coordinates":[-3.01376,53.389633],"type":"Point"}
}