{
  "type": "Feature",
  "properties": {
    "addr:full":"96 Ash Drive, Wardley Manchester Greater Manchester M27 9RR",
    "addr:housenumber":"96",
    "addr:postcode":"m27 9rr",
    "addr:street":"Ash Drive",
    "iso:country":"GB",
    "sg:address":"96 Ash Drive, Wardley",
    "sg:city":"Manchester",
    "sg:classifiers":[
        {
            "category":"Building & Trades",
            "subcategory":"Plumbing",
            "type":"Services"
        }
    ],
    "sg:phone":"+44 161 794 9775",
    "sg:postcode":"M27 9RR",
    "sg:province":"Greater Manchester",
    "sg:tags":[
        "heating"
    ],
    "wof:name":"Advanced Plumbing Services",
    "wof:placetype":"venue"
},
  "geometry": {"coordinates":[-2.3533689976,53.5210456848],"type":"Point"}
}