{
  "type": "Feature",
  "properties": {
    "addr:full":"Western House, High Street, Barmby-on-the-marsh Goole East Riding of Yorkshire DN14 7HU",
    "addr:postcode":"dn14 7hu",
    "addr:street":"High Street",
    "iso:country":"GB",
    "sg:address":"Western House, High Street, Barmby-on-the-marsh",
    "sg:city":"Goole",
    "sg:classifiers":[
        {
            "category":"Professional",
            "type":"Services"
        }
    ],
    "sg:phone":"+44 1757 630622",
    "sg:postcode":"DN14 7HU",
    "sg:province":"East Riding of Yorkshire",
    "sg:tags":[
        "repair",
        "tech",
        "maintenance"
    ],
    "wof:name":"Freelance Computer Services Ltd.",
    "wof:placetype":"venue"
},
  "geometry": {"coordinates":[-0.9578480124,53.7498397827],"type":"Point"}
}