{
  "type": "Feature",
  "properties": {
    "addr:full":"457 Mile Oak Road, Portslade Brighton East Sussex BN41 2RE",
    "addr:housenumber":"457",
    "addr:postcode":"bn41 2re",
    "addr:street":"Mile Oak Road",
    "iso:country":"GB",
    "sg:address":"457 Mile Oak Road, Portslade",
    "sg:city":"Brighton",
    "sg:classifiers":[
        {
            "category":"Home & Garden",
            "subcategory":"Building Materials",
            "type":"Retail Goods"
        }
    ],
    "sg:phone":"+44 1273 414786",
    "sg:postcode":"BN41 2RE",
    "sg:province":"East Sussex",
    "sg:tags":[
        "fencing"
    ],
    "wof:name":"R J Meaker (Fencing) Ltd.",
    "wof:placetype":"venue"
},
  "geometry": {"coordinates":[-0.233962,50.856102],"type":"Point"}
}