{
  "type": "Feature",
  "properties": {
    "iso:country":"GB",
    "sg:address":"Unit 1-3, Nelson Street",
    "sg:city":"Widnes",
    "sg:classifiers":[
        {
            "category":"Bus Charters",
            "type":"Transportation"
        }
    ],
    "sg:phone":"+44 151 424 5846",
    "sg:postcode":"WA8 0QD",
    "sg:province":"Cheshire",
    "sg:tags":[
        "hire",
        "coach"
    ],
    "wof:name":"Halton Traveller",
    "wof:placetype":"venue"
},
  "geometry": {"coordinates":[-2.7357990742,53.356338501],"type":"Point"}
}