{
  "type": "Feature",
  "properties": {
    "iso:country":"GB",
    "sg:address":"27a Ardleigh Road",
    "sg:city":"London",
    "sg:classifiers":[
        {
            "category":"Retail",
            "subcategory":"Auto Repair",
            "type":"Services"
        }
    ],
    "sg:phone":"+44 20 7249 8106",
    "sg:postcode":"N1 4HS",
    "sg:province":"Greater London",
    "sg:tags":[
        "modification",
        "garage"
    ],
    "wof:name":"Atlas Garage",
    "wof:placetype":"venue"
},
  "geometry": {"coordinates":[-0.082639,51.543884],"type":"Point"}
}