{
  "type": "Feature",
  "properties": {
    "iso:country":"GB",
    "sg:address":"Unit 9d, Chadwick Ind Est",
    "sg:city":"Stourport On Severn",
    "sg:classifiers":[
        {
            "category":"Retail",
            "subcategory":"Auto Repair",
            "type":"Services"
        }
    ],
    "sg:phone":"+44 1299 251007",
    "sg:postcode":"DY13 9QW",
    "sg:province":"Worcestershire",
    "sg:tags":[
        "body",
        "car"
    ],
    "wof:name":"L C R",
    "wof:placetype":"venue"
},
  "geometry": {"coordinates":[-2.2478659153,52.332611084],"type":"Point"}
}