{
  "type": "Feature",
  "properties": {
    "addr:full":"23 Bamburgh Gro Jarrow Tyne and Wear NE32 5QQ",
    "addr:housenumber":"23",
    "addr:postcode":"ne32 5qq",
    "addr:street":"Bamburgh Gro",
    "iso:country":"GB",
    "sg:address":"23 Bamburgh Gro",
    "sg:city":"Jarrow",
    "sg:classifiers":[
        {
            "category":"Building & Trades",
            "subcategory":"Construction",
            "type":"Services"
        }
    ],
    "sg:phone":"+44 191 489 4125",
    "sg:postcode":"NE32 5QQ",
    "sg:province":"Tyne and Wear",
    "sg:tags":[
        "flooring"
    ],
    "wof:name":"Flooring International (Uk) Ltd.",
    "wof:placetype":"venue"
},
  "geometry": {"coordinates":[-1.492549,54.96777],"type":"Point"}
}