{
  "type": "Feature",
  "properties": {
    "addr:full":"Unit 11 Rear Of Keirmar House, Tut Hill, Fornham All Saints Bury St Edmunds Cambridgeshire IP28 6LE",
    "addr:housenumber":"unit 11 rear",
    "addr:postcode":"ip28 6le",
    "addr:street":"Tut Hill;St",
    "iso:country":"GB",
    "sg:address":"Unit 11 Rear Of Keirmar House, Tut Hill, Fornham All Saints",
    "sg:city":"Bury St Edmunds",
    "sg:classifiers":[
        {
            "category":"Shopping",
            "subcategory":"Antiques",
            "type":"Retail Goods"
        }
    ],
    "sg:phone":"+44 1284 704894",
    "sg:postcode":"IP28 6LE",
    "sg:province":"Cambridgeshire",
    "wof:name":"R J Smith Restorations",
    "wof:placetype":"venue"
},
  "geometry": {"coordinates":[0.688217,52.271519],"type":"Point"}
}