{
  "type": "Feature",
  "properties": {
    "iso:country":"GB",
    "sg:address":"61 Longridge Road, Ribbleton",
    "sg:city":"Preston",
    "sg:classifiers":[
        {
            "category":"Professional",
            "subcategory":"Business Services",
            "type":"Services"
        }
    ],
    "sg:phone":"+44 1772 796235",
    "sg:postcode":"PR2 6RE",
    "sg:province":"Lancashire",
    "sg:tags":[
        "bookmaker"
    ],
    "wof:name":"Seymour & Storey",
    "wof:placetype":"venue"
},
  "geometry": {"coordinates":[-2.657256,53.781914],"type":"Point"}
}