{
  "type": "Feature",
  "properties": {
    "iso:country":"GB",
    "sg:address":"17 Edinburgh Road",
    "sg:city":"Bathgate",
    "sg:classifiers":[
        {
            "category":"Travel",
            "subcategory":"Hotels & Motels",
            "type":"Entertainment"
        },
        {
            "category":"Retail",
            "subcategory":"Auto Repair",
            "type":"Services"
        }
    ],
    "sg:phone":"+44 1506 653399",
    "sg:postcode":"EH48 1EP",
    "sg:province":"West Lothian",
    "sg:tags":[
        "modification",
        "garage"
    ],
    "wof:name":"Kaim Park Hotel",
    "wof:placetype":"venue"
},
  "geometry": {"coordinates":[-3.637247,55.898342],"type":"Point"}
}