{
  "type": "Feature",
  "properties": {
    "addr:full":"Jubilee Wks Colchester Essex CO6 3QA",
    "addr:postcode":"co6 3qa",
    "iso:country":"GB",
    "sg:address":"Jubilee Wks",
    "sg:city":"Colchester",
    "sg:classifiers":[
        {
            "category":"Professional",
            "subcategory":"Engineering",
            "type":"Services"
        }
    ],
    "sg:postcode":"CO6 3QA",
    "sg:province":"Essex",
    "sg:tags":[
        "contractor",
        "electrical",
        "engineer"
    ],
    "wof:name":"Woodward,John William,",
    "wof:placetype":"venue"
},
  "geometry": {"coordinates":[0.8206800222,51.8967285156],"type":"Point"}
}