{
  "type": "Feature",
  "properties": {
    "iso:country":"GB",
    "sg:address":"15 Balmoral Av",
    "sg:city":"Northwich",
    "sg:classifiers":[
        {
            "category":"Personal",
            "subcategory":"Barber",
            "type":"Services"
        }
    ],
    "sg:phone":"+44 1606 47887",
    "sg:postcode":"CW9 8BH",
    "sg:province":"Cheshire",
    "sg:tags":[
        "men's",
        "hairdresser"
    ],
    "wof:name":"Haircut Sir",
    "wof:placetype":"venue"
},
  "geometry": {"coordinates":[-2.508194,53.245712],"type":"Point"}
}