{
  "type": "Feature",
  "properties": {
    "addr:full":"114 Fartown Pudsey West Yorkshire LS28 8LU",
    "addr:housenumber":"114",
    "addr:postcode":"ls28 8lu",
    "addr:street":"Fartown Pudsey West",
    "iso:country":"GB",
    "sg:address":"114 Fartown",
    "sg:city":"Pudsey",
    "sg:classifiers":[
        {
            "category":"Personal",
            "type":"Services"
        }
    ],
    "sg:phone":"+44 113 257 6386",
    "sg:postcode":"LS28 8LU",
    "sg:province":"West Yorkshire",
    "sg:tags":[
        "wedding"
    ],
    "wof:name":"Scarlet Poppy",
    "wof:placetype":"venue"
},
  "geometry": {"coordinates":[-1.666087985,53.7880249023],"type":"Point"}
}