{
  "type": "Feature",
  "properties": {
    "addr:full":"3 Farriers Way, Netherton Bootle Merseyside L30 4XL",
    "addr:housenumber":"3",
    "addr:postcode":"l30 4xl",
    "addr:street":"Farriers Way",
    "iso:country":"GB",
    "sg:address":"3 Farriers Way, Netherton",
    "sg:city":"Bootle",
    "sg:classifiers":[
        {
            "category":"Professional",
            "subcategory":"Detective & Security Services",
            "type":"Services"
        }
    ],
    "sg:phone":"+44 151 525 8755",
    "sg:postcode":"L30 4XL",
    "sg:province":"Merseyside",
    "wof:name":"Micro Digital Technology Ltd.",
    "wof:placetype":"venue"
},
  "geometry": {"coordinates":[-2.9710359573,53.4726638794],"type":"Point"}
}