{
  "type": "Feature",
  "properties": {
    "addr:full":"6 West Way Gardens Croydon Surrey CR0 8RA",
    "addr:housenumber":"6",
    "addr:postcode":"cr0 8ra",
    "addr:street":"West Way Gardens",
    "iso:country":"GB",
    "sg:address":"6 West Way Gardens",
    "sg:city":"Croydon",
    "sg:classifiers":[
        {
            "category":"Organizations",
            "subcategory":"Non-profit Organization",
            "type":"Services"
        }
    ],
    "sg:phone":"+44 20 8655 3344",
    "sg:postcode":"CR0 8RA",
    "sg:province":"Surrey",
    "sg:tags":[
        "organisation",
        "voluntary",
        "charity"
    ],
    "wof:name":"Status Employment Ltd.",
    "wof:placetype":"venue"
},
  "geometry": {"coordinates":[-0.0486310013,51.3742370605],"type":"Point"}
}