{
  "type": "Feature",
  "properties": {
    "iso:country":"GB",
    "sg:address":"Unit 3 Industrial Estate, Wheldrake",
    "sg:city":"York",
    "sg:classifiers":[
        {
            "category":"Professional",
            "subcategory":"Management & Consulting",
            "type":"Services"
        }
    ],
    "sg:phone":"+44 1904 448960",
    "sg:postcode":"YO19 6AH",
    "sg:province":"North Yorkshire",
    "sg:tags":[
        "consultant",
        "safety"
    ],
    "wof:name":"Pennine Safety Unit",
    "wof:placetype":"venue"
},
  "geometry": {"coordinates":[-0.9659820199,53.896030426],"type":"Point"}
}