{
  "type": "Feature",
  "properties": {
    "addr:full":"Fore Street Lifton Devon PL16 0AA",
    "addr:postcode":"pl16 0aa",
    "addr:street":"Fore Street",
    "iso:country":"GB",
    "sg:address":"Fore Street",
    "sg:city":"Lifton",
    "sg:classifiers":[
        {
            "category":"Shopping",
            "subcategory":"Department Store",
            "type":"Retail Goods"
        }
    ],
    "sg:phone":"+44 1566 784211",
    "sg:postcode":"PL16 0AA",
    "sg:province":"Devon",
    "wof:name":"A G Phillips & Sons",
    "wof:placetype":"venue"
},
  "geometry": {"coordinates":[-4.283153,50.643166],"type":"Point"}
}