{
  "type": "Feature",
  "properties": {
    "addr:full":"339 Calder Road Edinburgh City of Edinburgh EH11 4AH",
    "addr:housenumber":"339",
    "addr:postcode":"eh11 4ah",
    "addr:street":"Calder Road",
    "iso:country":"GB",
    "sg:address":"339 Calder Road",
    "sg:city":"Edinburgh",
    "sg:classifiers":[
        {
            "category":"Shopping",
            "subcategory":"News",
            "type":"Retail Goods"
        }
    ],
    "sg:phone":"+44 131 455 7649",
    "sg:postcode":"EH11 4AH",
    "sg:province":"City of Edinburgh",
    "sg:tags":[
        "newsagent"
    ],
    "wof:name":"R S McColl",
    "wof:placetype":"venue"
},
  "geometry": {"coordinates":[-3.277488,55.924438],"type":"Point"}
}