{
  "type": "Feature",
  "properties": {
    "iso:country":"GB",
    "sg:address":"30 Bedford Square",
    "sg:city":"London",
    "sg:classifiers":[
        {
            "category":"Professional",
            "subcategory":"Management & Consulting",
            "type":"Services"
        }
    ],
    "sg:phone":"+44 20 7436 6664",
    "sg:postcode":"WC1B 3EG",
    "sg:province":"Greater London",
    "sg:tags":[
        "consultant",
        "promotion",
        "direct",
        "sale"
    ],
    "wof:name":"C B H & Partners Ltd.",
    "wof:placetype":"venue"
},
  "geometry": {"coordinates":[-0.131015,51.518608],"type":"Point"}
}