{
  "type": "Feature",
  "properties": {
    "addr:full":"21 St. Georges Av Southall Greater London UB1 1PZ",
    "addr:housenumber":"21",
    "addr:postcode":"ub1 1pz",
    "addr:street":"St. Georges Av",
    "iso:country":"GB",
    "sg:address":"21 St. Georges Av",
    "sg:city":"Southall",
    "sg:classifiers":[
        {
            "category":"Health Services",
            "subcategory":"Doctor",
            "type":"Services"
        }
    ],
    "sg:phone":"+44 20 8813 8122",
    "sg:postcode":"UB1 1PZ",
    "sg:province":"Greater London",
    "sg:tags":[
        "practitioners"
    ],
    "wof:name":"Radhakrishnan, S M",
    "wof:placetype":"venue"
},
  "geometry": {"coordinates":[-0.3776569963,51.5123558044],"type":"Point"}
}