{
  "type": "Feature",
  "properties": {
    "addr:full":"256 Lower Twydall Lane, Rainham Gillingham Kent ME8 6XX",
    "addr:housenumber":"256",
    "addr:postcode":"me8 6xx",
    "addr:street":"Lower Twydall Lane",
    "iso:country":"GB",
    "sg:address":"256 Lower Twydall Lane, Rainham",
    "sg:city":"Gillingham",
    "sg:classifiers":[
        {
            "category":"Building & Trades",
            "subcategory":"Construction",
            "type":"Services"
        }
    ],
    "sg:phone":"+44 1634 233615",
    "sg:postcode":"ME8 6XX",
    "sg:province":"Kent",
    "sg:tags":[
        "builder"
    ],
    "wof:name":"David Harris Contracts Ltd.",
    "wof:placetype":"venue"
},
  "geometry": {"coordinates":[0.58697,51.37923],"type":"Point"}
}