{
  "type": "Feature",
  "properties": {
    "addr:full":"6 New Pit Cotts, Bridge Place Road Bath Somerset BA2 0PE",
    "addr:housenumber":"6",
    "addr:postcode":"ba2 0pe",
    "addr:street":"New;Cotts Bridge Place Road",
    "iso:country":"GB",
    "sg:address":"6 New Pit Cotts, Bridge Place Road",
    "sg:city":"Bath",
    "sg:classifiers":[
        {
            "category":"Professional",
            "subcategory":"Management & Consulting",
            "type":"Services"
        },
        {
            "category":"Government",
            "subcategory":"Post Office",
            "type":"Public Place"
        }
    ],
    "sg:phone":"+44 1761 411362",
    "sg:postcode":"BA2 0PE",
    "sg:province":"Somerset",
    "sg:tags":[
        "consultant",
        "messenger",
        "courier",
        "specialist"
    ],
    "wof:name":"Claire Freeman",
    "wof:placetype":"venue"
},
  "geometry": {"coordinates":[-2.4531900883,51.3205986023],"type":"Point"}
}