{
  "type": "Feature",
  "properties": {
    "addr:full":"13 Reffley La King's Lynn Norfolk PE30 3EF",
    "addr:housenumber":"13",
    "addr:postcode":"pe30 3ef",
    "addr:street":"Reffley La King'S Lynn",
    "iso:country":"GB",
    "sg:address":"13 Reffley La",
    "sg:city":"King's Lynn",
    "sg:classifiers":[
        {
            "category":"Arts & Performance",
            "subcategory":"Music",
            "type":"Entertainment"
        }
    ],
    "sg:phone":"+44 1553 671353",
    "sg:postcode":"PE30 3EF",
    "sg:province":"Norfolk",
    "sg:tags":[
        "mobile",
        "disco"
    ],
    "wof:name":"Pigs Parties",
    "wof:placetype":"venue"
},
  "geometry": {"coordinates":[0.4359700084,52.7707595825],"type":"Point"}
}