{
  "type": "Feature",
  "properties": {
    "iso:country":"GB",
    "sg:address":"13 Reffley La",
    "sg:city":"King's Lynn",
    "sg:classifiers":[
        {
            "category":"Arts & Performance",
            "subcategory":"Music",
            "type":"Entertainment"
        }
    ],
    "sg:phone":"+44 1553 671353",
    "sg:postcode":"PE30 3EF",
    "sg:province":"Norfolk",
    "sg:tags":[
        "mobile",
        "disco"
    ],
    "wof:name":"Pigs Parties",
    "wof:placetype":"venue"
},
  "geometry": {"coordinates":[0.4359700084,52.7707595825],"type":"Point"}
}