{
  "type": "Feature",
  "properties": {
    "iso:country":"GB",
    "sg:address":"14 Crescent Rd",
    "sg:city":"Tunbridge Wells",
    "sg:classifiers":[
        {
            "category":"Shopping",
            "subcategory":"Thrift Store",
            "type":"Retail Goods"
        }
    ],
    "sg:phone":"+44 1892 522002",
    "sg:postcode":"TN1 2LU",
    "sg:province":"Kent",
    "sg:tags":[
        "shop",
        "charity"
    ],
    "wof:name":"Seven Springs Boutique",
    "wof:placetype":"venue"
},
  "geometry": {"coordinates":[0.265821,51.132065],"type":"Point"}
}