{
  "type": "Feature",
  "properties": {
    "iso:country":"GB",
    "sg:address":"1-3 Station Road",
    "sg:city":"Swanage",
    "sg:classifiers":[
        {
            "category":"Shopping",
            "subcategory":"Pharmacy",
            "type":"Retail Goods"
        }
    ],
    "sg:phone":"+44 1929 422096",
    "sg:postcode":"BH19 1AB",
    "sg:province":"Dorset",
    "sg:tags":[
        "pharmacist",
        "dispensing",
        "chemist"
    ],
    "sg:website":"http://www.boots.com",
    "wof:name":"Boots The Chemists",
    "wof:placetype":"venue"
},
  "geometry": {"coordinates":[-1.957596,50.609245],"type":"Point"}
}