{
  "type": "Feature",
  "properties": {
    "addr:full":"333-335 High St North London Greater London E12 6PQ",
    "addr:housenumber":"333-335",
    "addr:postcode":"e12 6pq",
    "addr:street":"High St North",
    "iso:country":"GB",
    "sg:address":"333-335 High St North",
    "sg:city":"London",
    "sg:classifiers":[
        {
            "category":"Shopping",
            "subcategory":"Clothing, Apparel, & Fashions",
            "type":"Retail Goods"
        },
        {
            "category":"Shopping",
            "subcategory":"Crafts & Fabrics",
            "type":"Retail Goods"
        }
    ],
    "sg:phone":"+44 20 8472 7387",
    "sg:postcode":"E12 6PQ",
    "sg:province":"Greater London",
    "sg:tags":[
        "shop",
        "lady",
        "fashionwear"
    ],
    "wof:name":"Ruby Fashions",
    "wof:placetype":"venue"
},
  "geometry": {"coordinates":[0.049647,51.543621],"type":"Point"}
}