{
  "type": "Feature",
  "properties": {
    "addr:full":"329 Burley Road Leeds West Yorkshire LS4 2BP",
    "addr:housenumber":"329",
    "addr:postcode":"ls4 2bp",
    "addr:street":"Burley Road",
    "iso:country":"GB",
    "sg:address":"329 Burley Road",
    "sg:city":"Leeds",
    "sg:classifiers":[
        {
            "category":"Retail",
            "subcategory":"Auto Repair",
            "type":"Services"
        }
    ],
    "sg:phone":"+44 113 274 1532",
    "sg:postcode":"LS4 2BP",
    "sg:province":"West Yorkshire",
    "sg:tags":[
        "car",
        "specialist",
        "customizing"
    ],
    "wof:name":"Tyremart",
    "wof:placetype":"venue"
},
  "geometry": {"coordinates":[-1.5835,53.809151],"type":"Point"}
}