{
  "type": "Feature",
  "properties": {
    "addr:full":"Railway Street Dewsbury West Yorkshire WF12 8EQ",
    "addr:postcode":"wf12 8eq",
    "addr:street":"Railway Street",
    "iso:country":"GB",
    "sg:address":"Railway Street",
    "sg:city":"Dewsbury",
    "sg:classifiers":[
        {
            "category":"Home & Garden",
            "subcategory":"Hardware",
            "type":"Retail Goods"
        }
    ],
    "sg:phone":"+44 1924 457598",
    "sg:postcode":"WF12 8EQ",
    "sg:province":"West Yorkshire",
    "sg:tags":[
        "retailer",
        "diy"
    ],
    "wof:name":"Do It All Ltd.",
    "wof:placetype":"venue"
},
  "geometry": {"coordinates":[-1.6267240047,53.6907081604],"type":"Point"}
}