{
  "type": "Feature",
  "properties": {
    "iso:country":"GB",
    "sg:address":"71-73 Southgate Street",
    "sg:city":"Gloucester",
    "sg:classifiers":[
        {
            "category":"Home & Garden",
            "subcategory":"Furniture",
            "type":"Retail Goods"
        }
    ],
    "sg:phone":"+44 1452 304424",
    "sg:postcode":"GL1 1TX",
    "sg:province":"Gloucestershire",
    "sg:tags":[
        "outlet"
    ],
    "wof:name":"Gloucester Furniture Exhibition Centre",
    "wof:placetype":"venue"
},
  "geometry": {"coordinates":[-2.248452,51.86311],"type":"Point"}
}