{
  "type": "Feature",
  "properties": {
    "addr:full":"24 Porden Road London Greater London SW2 5RT",
    "addr:housenumber":"24",
    "addr:postcode":"sw2 5rt",
    "addr:street":"Porden Road",
    "iso:country":"GB",
    "sg:address":"24 Porden Road",
    "sg:city":"London",
    "sg:classifiers":[
        {
            "category":"Wholesale",
            "subcategory":"Music Publishers",
            "type":"Manufacturing & Wholesale Goods"
        }
    ],
    "sg:postcode":"SW2 5RT",
    "sg:province":"Greater London",
    "sg:tags":[
        "record"
    ],
    "wof:name":"Hypnotic Records",
    "wof:placetype":"venue"
},
  "geometry": {"coordinates":[-0.11784,51.459747],"type":"Point"}
}