{
  "type": "Feature",
  "properties": {
    "iso:country":"GB",
    "sg:address":"12 Willow Lane, Stanion",
    "sg:city":"Kettering",
    "sg:classifiers":[
        {
            "category":"Building & Trades",
            "subcategory":"Construction",
            "type":"Services"
        }
    ],
    "sg:phone":"+44 1536 204393",
    "sg:postcode":"NN14 1DT",
    "sg:province":"Northamptonshire",
    "sg:tags":[
        "glazier"
    ],
    "wof:name":"A H Jamieson Glazing Contractors",
    "wof:placetype":"venue"
},
  "geometry": {"coordinates":[-0.65331,52.472122],"type":"Point"}
}