{
  "type": "Feature",
  "properties": {
    "addr:full":"3 Henrietta St Holborn Greater London WC2E 8LU",
    "addr:housenumber":"3",
    "addr:postcode":"wc2e 8lu",
    "addr:street":"Henrietta St",
    "iso:country":"GB",
    "sg:address":"3 Henrietta St",
    "sg:city":"Holborn",
    "sg:classifiers":[
        {
            "category":"Professional",
            "subcategory":"Printing & Photocopies",
            "type":"Services"
        }
    ],
    "sg:phone":"+44 20 8346 8349",
    "sg:postcode":"WC2E 8LU",
    "sg:province":"Greater London",
    "sg:tags":[
        "printer"
    ],
    "wof:name":"United Print Process",
    "wof:placetype":"venue"
},
  "geometry": {"coordinates":[-0.1245089993,51.5107803345],"type":"Point"}
}