{
  "type": "Feature",
  "properties": {
    "iso:country":"GB",
    "sg:address":"5 Berners St",
    "sg:city":"West End",
    "sg:classifiers":[
        {
            "category":"Building & Trades",
            "subcategory":"Construction",
            "type":"Services"
        }
    ],
    "sg:phone":"+44 20 7323 3399",
    "sg:postcode":"W1P 3AG",
    "sg:province":"Hampshire",
    "sg:tags":[
        "contractor"
    ],
    "wof:name":"Hazama Corporation",
    "wof:placetype":"venue"
},
  "geometry": {"coordinates":[-0.135916,51.516296],"type":"Point"}
}