{
  "type": "Feature",
  "properties": {
    "addr:full":"62 Manor View Par Cornwall PL24 2EN",
    "addr:housenumber":"62",
    "addr:postcode":"pl24 2en",
    "addr:street":"Manor View Par",
    "iso:country":"GB",
    "sg:address":"62 Manor View",
    "sg:city":"Par",
    "sg:classifiers":[
        {
            "category":"Building & Trades",
            "subcategory":"Plumbing",
            "type":"Services"
        }
    ],
    "sg:postcode":"PL24 2EN",
    "sg:province":"Cornwall",
    "sg:tags":[
        "central",
        "heating"
    ],
    "wof:name":"Robert Thomas",
    "wof:placetype":"venue"
},
  "geometry": {"coordinates":[-4.715954,50.349937],"type":"Point"}
}