{
  "type": "Feature",
  "properties": {
    "iso:country":"GB",
    "sg:address":"62 Manor View",
    "sg:city":"Par",
    "sg:classifiers":[
        {
            "category":"Building & Trades",
            "subcategory":"Plumbing",
            "type":"Services"
        }
    ],
    "sg:postcode":"PL24 2EN",
    "sg:province":"Cornwall",
    "sg:tags":[
        "central",
        "heating"
    ],
    "wof:name":"Robert Thomas",
    "wof:placetype":"venue"
},
  "geometry": {"coordinates":[-4.715954,50.349937],"type":"Point"}
}