{
  "type": "Feature",
  "properties": {
    "addr:full":"128 Coast Road, West Mersea Colchester Essex CO5 8PA",
    "addr:housenumber":"128",
    "addr:postcode":"co5 8pa",
    "addr:street":"Coast Road West;Colchester",
    "iso:country":"GB",
    "sg:address":"128 Coast Road, West Mersea",
    "sg:city":"Colchester",
    "sg:classifiers":[
        {
            "category":"Social Services",
            "subcategory":"Job Training",
            "type":"Services"
        }
    ],
    "sg:phone":"+44 1206 384350",
    "sg:postcode":"CO5 8PA",
    "sg:province":"Essex",
    "sg:tags":[
        "engineering",
        "marine"
    ],
    "wof:name":"West Mersea Marine Engineering Ltd.",
    "wof:placetype":"venue"
},
  "geometry": {"coordinates":[0.899465,51.779736],"type":"Point"}
}