{
  "type": "Feature",
  "properties": {
    "addr:full":"Alpha Works Smalley Street, Castleton Rochdale Lancashire OL11 3EB",
    "addr:postcode":"ol11 3eb",
    "addr:street":"Smalley Street",
    "iso:country":"GB",
    "sg:address":"Alpha Works Smalley Street, Castleton",
    "sg:city":"Rochdale",
    "sg:classifiers":[
        {
            "category":"Building & Trades",
            "subcategory":"Plumbing",
            "type":"Services"
        }
    ],
    "sg:phone":"+44 1706 632318",
    "sg:postcode":"OL11 3EB",
    "sg:province":"Lancashire",
    "sg:tags":[
        "heating"
    ],
    "wof:name":"Airflow (Uk) Ltd.",
    "wof:placetype":"venue"
},
  "geometry": {"coordinates":[-2.1800000668,53.5937004089],"type":"Point"}
}