{
  "type": "Feature",
  "properties": {
    "addr:full":"Wheatsheaf Workshop, High Street Wrexham Wrexham LL14 3YE",
    "addr:postcode":"ll14 3ye",
    "addr:street":"High Street",
    "iso:country":"GB",
    "sg:address":"Wheatsheaf Workshop, High Street",
    "sg:city":"Wrexham",
    "sg:classifiers":[
        {
            "category":"Deli",
            "type":"Food & Drink"
        },
        {
            "category":"Government",
            "subcategory":"Office",
            "type":"Public Place"
        }
    ],
    "sg:phone":"+44 1978 810138",
    "sg:postcode":"LL14 3YE",
    "sg:province":"Wrexham",
    "sg:tags":[
        "delivery",
        "sandwich",
        "local"
    ],
    "wof:name":"The Cesn Lunch Run",
    "wof:placetype":"venue"
},
  "geometry": {"coordinates":[-3.06827,52.975399],"type":"Point"}
}