{
  "type": "Feature",
  "properties": {
    "addr:full":"67 Downleaze, South Woodham Ferrers Chelmsford Essex CM3 5SJ",
    "addr:housenumber":"67",
    "addr:postcode":"cm3 5sj",
    "addr:street":"Downleaze South Woodham Ferrers Chelmsford",
    "iso:country":"GB",
    "sg:address":"67 Downleaze, South Woodham Ferrers",
    "sg:city":"Chelmsford",
    "sg:classifiers":[
        {
            "category":"Education",
            "subcategory":"Dance Studio",
            "type":"Public Place"
        }
    ],
    "sg:phone":"+44 1245 320176",
    "sg:postcode":"CM3 5SJ",
    "sg:province":"Essex",
    "sg:tags":[
        "school",
        "dancing"
    ],
    "wof:name":"Laura Faulkner School",
    "wof:placetype":"venue"
},
  "geometry": {"coordinates":[0.6159920096,51.6480255127],"type":"Point"}
}