{
  "type": "Feature",
  "properties": {
    "addr:full":"4 Thirleby Road Edgware Greater London HA8 0HQ",
    "addr:housenumber":"4",
    "addr:postcode":"ha8 0hq",
    "addr:street":"Thirleby Road",
    "iso:country":"GB",
    "sg:address":"4 Thirleby Road",
    "sg:city":"Edgware",
    "sg:classifiers":[
        {
            "category":"Community Center",
            "subcategory":"Youth",
            "type":"Public Place"
        }
    ],
    "sg:phone":"+44 20 8959 0911",
    "sg:postcode":"HA8 0HQ",
    "sg:province":"Greater London",
    "sg:tags":[
        "organisation",
        "centre"
    ],
    "wof:name":"Annunciation Catholic Youth Club",
    "wof:placetype":"venue"
},
  "geometry": {"coordinates":[-0.26036,51.602695],"type":"Point"}
}