{
  "type": "Feature",
  "properties": {
    "addr:full":"Byres Road Kilwinning East Ayrshire KA13 6NS",
    "addr:postcode":"ka13 6ns",
    "addr:street":"Byres Road",
    "iso:country":"GB",
    "sg:address":"Byres Road",
    "sg:city":"Kilwinning",
    "sg:classifiers":[
        {
            "category":"Home & Garden",
            "subcategory":"Building Materials",
            "type":"Retail Goods"
        },
        {
            "category":"Building & Trades",
            "subcategory":"Construction",
            "type":"Services"
        }
    ],
    "sg:phone":"+44 1294 552202",
    "sg:postcode":"KA13 6NS",
    "sg:province":"East Ayrshire",
    "sg:tags":[
        "fencing",
        "contractor"
    ],
    "wof:name":"Hay & Anderson (Kilwinning) Ltd.",
    "wof:placetype":"venue"
},
  "geometry": {"coordinates":[-4.707662,55.654518],"type":"Point"}
}