{
  "type": "Feature",
  "properties": {
    "iso:country":"GB",
    "sg:address":"40 Beaconsfield Road",
    "sg:city":"Hatfield",
    "sg:classifiers":[
        {
            "category":"Professional",
            "type":"Services"
        }
    ],
    "sg:phone":"+44 1707 264237",
    "sg:postcode":"AL10 8BA",
    "sg:province":"Hertfordshire",
    "sg:tags":[
        "shopfitters"
    ],
    "wof:name":"Davis Ridley & Co. Ltd.",
    "wof:placetype":"venue"
},
  "geometry": {"coordinates":[-0.216776,51.764595],"type":"Point"}
}