{
  "type": "Feature",
  "properties": {
    "addr:full":"West Whitecastle Farm Biggar Dumfries and Galloway ML12 6LZ",
    "addr:postcode":"ml12 6lz",
    "addr:street":"West",
    "iso:country":"GB",
    "sg:address":"West Whitecastle Farm",
    "sg:city":"Biggar",
    "sg:classifiers":[
        {
            "category":"Farming",
            "subcategory":"Livestock Farm",
            "type":"Manufacturing & Wholesale Goods"
        }
    ],
    "sg:phone":"+44 1899 221118",
    "sg:postcode":"ML12 6LZ",
    "sg:province":"Dumfries and Galloway",
    "sg:tags":[
        "others"
    ],
    "wof:name":"Wester",
    "wof:placetype":"venue"
},
  "geometry": {"coordinates":[-3.5230190754,55.624420166],"type":"Point"}
}