{
  "type": "Feature",
  "properties": {
    "addr:full":"Parcel Depot, The Ridge West St Leonards On Sea East Sussex TN37 7RZ",
    "addr:postcode":"tn37 7rz",
    "addr:street":"West;Sea",
    "iso:country":"GB",
    "sg:address":"Parcel Depot, The Ridge West",
    "sg:city":"St Leonards On Sea",
    "sg:classifiers":[
        {
            "category":"Personal",
            "type":"Services"
        }
    ],
    "sg:phone":"+44 1424 753555",
    "sg:postcode":"TN37 7RZ",
    "sg:province":"East Sussex",
    "sg:tags":[
        "delivery"
    ],
    "wof:name":"Royal Mail Parcelforce",
    "wof:placetype":"venue"
},
  "geometry": {"coordinates":[0.5396389961,50.8927726746],"type":"Point"}
}