{
  "type": "Feature",
  "properties": {
    "addr:full":"Tingewick Road Industrial Estate, Tingewick Road Buckingham Buckinghamshire MK18 1SU",
    "addr:postcode":"mk18 1su",
    "addr:street":"Tingewick Road Industrial Estate Tingewick Road",
    "iso:country":"GB",
    "sg:address":"Tingewick Road Industrial Estate, Tingewick Road",
    "sg:city":"Buckingham",
    "sg:classifiers":[
        {
            "category":"Communications",
            "type":"Services"
        },
        {
            "category":"Shopping",
            "subcategory":"Computers & Home Electronics",
            "type":"Retail Goods"
        }
    ],
    "sg:phone":"+44 1280 820420",
    "sg:postcode":"MK18 1SU",
    "sg:province":"Buckinghamshire",
    "sg:tags":[
        "equipment",
        "audio-visual"
    ],
    "wof:name":"A R B Audio & Visual Hire Ltd.",
    "wof:placetype":"venue"
},
  "geometry": {"coordinates":[-0.997572,51.997814],"type":"Point"}
}