{
  "type": "Feature",
  "properties": {
    "addr:full":"2 Clarendon Road Ashford Greater London TW15 2QE",
    "addr:housenumber":"2",
    "addr:postcode":"tw15 2qe",
    "addr:street":"Clarendon Road",
    "iso:country":"GB",
    "sg:address":"2 Clarendon Road",
    "sg:city":"Ashford",
    "sg:classifiers":[
        {
            "category":"Organizations",
            "subcategory":"Membership Organization",
            "type":"Services"
        }
    ],
    "sg:postcode":"TW15 2QE",
    "sg:province":"Greater London",
    "sg:tags":[
        "club"
    ],
    "wof:name":"Bramley Court (Bedfont) Residents Associ",
    "wof:placetype":"venue"
},
  "geometry": {"coordinates":[-0.467476,51.43544],"type":"Point"}
}