{
  "type": "Feature",
  "properties": {
    "addr:full":"Dr Trust & Partners, 46-62 Bank St Alexandria Argyll and Bute G83 0LS",
    "addr:housenumber":"46-62",
    "addr:postcode":"g83 0ls",
    "addr:street":"Bank St",
    "iso:country":"GB",
    "sg:address":"Dr Trust & Partners, 46-62 Bank St",
    "sg:city":"Alexandria",
    "sg:classifiers":[
        {
            "category":"Health Services",
            "subcategory":"Doctor",
            "type":"Services"
        }
    ],
    "sg:phone":"+44 1389 752419",
    "sg:postcode":"G83 0LS",
    "sg:province":"Argyll and Bute",
    "sg:tags":[
        "practitioners"
    ],
    "wof:name":"Shand, J",
    "wof:placetype":"venue"
},
  "geometry": {"coordinates":[-4.5797729492,55.987033844],"type":"Point"}
}