{
  "type": "Feature",
  "properties": {
    "addr:full":"North Street, Hundon Sudbury Essex CO10 8EE",
    "addr:postcode":"co10 8ee",
    "addr:street":"North Street",
    "iso:country":"GB",
    "sg:address":"North Street, Hundon",
    "sg:city":"Sudbury",
    "sg:classifiers":[
        {
            "category":"Shopping",
            "subcategory":"Hobbies, Toys, & Games",
            "type":"Retail Goods"
        }
    ],
    "sg:postcode":"CO10 8EE",
    "sg:province":"Essex",
    "sg:tags":[
        "toy"
    ],
    "wof:name":"Birthday Box",
    "wof:placetype":"venue"
},
  "geometry": {"coordinates":[0.5366050005,52.1092262268],"type":"Point"}
}