{
  "type": "Feature",
  "properties": {
    "addr:full":"5 Links House, Dundas Lane Portsmouth Hampshire PO3 5BL",
    "addr:housenumber":"5",
    "addr:postcode":"hampshire po3 5bl",
    "addr:street":"Links House Dundas Lane",
    "iso:country":"GB",
    "sg:address":"5 Links House, Dundas Lane",
    "sg:city":"Portsmouth",
    "sg:classifiers":[
        {
            "category":"Professional",
            "subcategory":"Art Services",
            "type":"Services"
        }
    ],
    "sg:postcode":"PO3 5BL",
    "sg:province":"Hampshire",
    "sg:tags":[
        "graphic",
        "designer"
    ],
    "wof:name":"Crisp Designs Ltd.",
    "wof:placetype":"venue"
},
  "geometry": {"coordinates":[-1.05038,50.822689],"type":"Point"}
}