{
  "type": "Feature",
  "properties": {
    "addr:full":"Coast Road Wallsend Tyne and Wear NE28 9HP",
    "addr:postcode":"ne28 9hp",
    "addr:street":"Coast Road",
    "iso:country":"GB",
    "sg:address":"Coast Road",
    "sg:city":"Wallsend",
    "sg:classifiers":[
        {
            "category":"Bars & Pubs",
            "type":"Food & Drink"
        },
        {
            "category":"Community Center",
            "subcategory":"Social",
            "type":"Public Place"
        }
    ],
    "sg:phone":"+44 191 234 2044",
    "sg:postcode":"NE28 9HP",
    "sg:province":"Tyne and Wear",
    "sg:tags":[
        "pubs",
        "house",
        "inn",
        "activity"
    ],
    "wof:name":"Gala Holdings Ltd.",
    "wof:placetype":"venue"
},
  "geometry": {"coordinates":[-1.5346699953,55.0019683838],"type":"Point"}
}