{
  "type": "Feature",
  "properties": {
    "iso:country":"GB",
    "sg:address":"8 Oakwood Road",
    "sg:city":"Wetherby",
    "sg:classifiers":[
        {
            "category":"Building & Trades",
            "subcategory":"Construction",
            "type":"Services"
        }
    ],
    "sg:phone":"+44 1937 583399",
    "sg:postcode":"LS22 7QY",
    "sg:province":"North Yorkshire",
    "sg:tags":[
        "builder"
    ],
    "wof:name":"T D Building Contractors",
    "wof:placetype":"venue"
},
  "geometry": {"coordinates":[-1.3934309483,53.9378356934],"type":"Point"}
}