{
  "type": "Feature",
  "properties": {
    "addr:full":"Old Grange Farm, Grange Lane, Hutton Preston Lancashire PR4 5JH",
    "addr:postcode":"pr4 5jh",
    "addr:street":"Grange Lane",
    "iso:country":"GB",
    "sg:address":"Old Grange Farm, Grange Lane, Hutton",
    "sg:city":"Preston",
    "sg:classifiers":[
        {
            "category":"Farming",
            "subcategory":"Livestock Farm",
            "type":"Manufacturing & Wholesale Goods"
        }
    ],
    "sg:phone":"+44 1772 613237",
    "sg:postcode":"PR4 5JH",
    "sg:province":"Lancashire",
    "sg:tags":[
        "others"
    ],
    "wof:name":"William Hesketh & Sons",
    "wof:placetype":"venue"
},
  "geometry": {"coordinates":[-2.790479,53.71209],"type":"Point"}
}