{
  "type": "Feature",
  "properties": {
    "addr:full":"B D O Stoy Hayward, Northside House, 69 Tweedy Road Bromley Kent BR1 3WA",
    "addr:housenumber":"69",
    "addr:postcode":"br1 3wa",
    "addr:street":"Hayward;Tweedy Road",
    "iso:country":"GB",
    "sg:address":"B D O Stoy Hayward, Northside House, 69 Tweedy Road",
    "sg:city":"Bromley",
    "sg:classifiers":[
        {
            "category":"Professional",
            "subcategory":"Business Services",
            "type":"Services"
        }
    ],
    "sg:postcode":"BR1 3WA",
    "sg:province":"Kent",
    "sg:tags":[
        "holding"
    ],
    "wof:name":"Magpie Holdings Ltd",
    "wof:placetype":"venue"
},
  "geometry": {"coordinates":[0.016518,51.408192],"type":"Point"}
}