{
  "type": "Feature",
  "properties": {
    "iso:country":"GB",
    "sg:address":"167 Station Road",
    "sg:city":"Sidcup",
    "sg:classifiers":[
        {
            "category":"Home & Garden",
            "subcategory":"Household Appliances",
            "type":"Retail Goods"
        },
        {
            "category":"Home & Garden",
            "subcategory":"Building Materials",
            "type":"Retail Goods"
        }
    ],
    "sg:phone":"+44 20 8309 5973",
    "sg:postcode":"DA15 7AA",
    "sg:province":"Kent",
    "sg:tags":[
        "installers",
        "planner",
        "electrical",
        "kitchen"
    ],
    "wof:name":"Sidcup Kitchen & Bathroom Centre",
    "wof:placetype":"venue"
},
  "geometry": {"coordinates":[0.101546,51.435783],"type":"Point"}
}