{
  "type": "Feature",
  "properties": {
    "addr:full":"489 Oxford Street London Greater London W1C 2PZ",
    "addr:housenumber":"489",
    "addr:postcode":"w1c 2pz",
    "addr:street":"Oxford Street",
    "iso:country":"GB",
    "sg:address":"489 Oxford Street",
    "sg:city":"London",
    "sg:classifiers":[
        {
            "category":"Shopping",
            "subcategory":"Clothing, Apparel, & Fashions",
            "type":"Retail Goods"
        }
    ],
    "sg:phone":"+44 20 7495 3812",
    "sg:postcode":"W1C 2PZ",
    "sg:province":"Greater London",
    "sg:tags":[
        "ladieswear"
    ],
    "wof:name":"Bay Trading Co",
    "wof:placetype":"venue"
},
  "geometry": {"coordinates":[-0.1482789963,51.5144996643],"type":"Point"}
}