{
  "type": "Feature",
  "properties": {
    "iso:country":"GB",
    "sg:address":"10a Belle Vue Way",
    "sg:city":"Swansea",
    "sg:classifiers":[
        {
            "category":"Personal",
            "subcategory":"Beauty Salon",
            "type":"Services"
        }
    ],
    "sg:postcode":"SA1 5BY",
    "sg:province":"Neath Port Talbot",
    "wof:name":"Eleanor's Electrolysis & Beauty Salon",
    "wof:placetype":"venue"
},
  "geometry": {"coordinates":[-3.944034,51.62178],"type":"Point"}
}