{
  "type": "Feature",
  "properties": {
    "addr:full":"Grove Road Burnham-on-sea Somerset TA8 2HF",
    "addr:postcode":"ta8 2hf",
    "addr:street":"Grove Road",
    "iso:country":"GB",
    "sg:address":"Grove Road",
    "sg:city":"Burnham-on-sea",
    "sg:classifiers":[
        {
            "category":"Health Services",
            "subcategory":"Nursing And Care Facility",
            "type":"Services"
        }
    ],
    "sg:phone":"+44 1278 782943",
    "sg:postcode":"TA8 2HF",
    "sg:province":"Somerset",
    "sg:tags":[
        "home"
    ],
    "wof:name":"R J Homes Ltd.",
    "wof:placetype":"venue"
},
  "geometry": {"coordinates":[-2.9981389046,51.2440795898],"type":"Point"}
}