{
  "type": "Feature",
  "properties": {
    "addr:full":"The Old Stables Perranporth Cornwall TR6 0BB",
    "addr:postcode":"tr6 0bb",
    "addr:street":"Perranporth",
    "iso:country":"GB",
    "sg:address":"The Old Stables",
    "sg:city":"Perranporth",
    "sg:classifiers":[
        {
            "category":"Professional",
            "subcategory":"Engineering",
            "type":"Services"
        }
    ],
    "sg:phone":"+44 1872 572425",
    "sg:postcode":"TR6 0BB",
    "sg:province":"Cornwall",
    "sg:tags":[
        "contractor",
        "electrical",
        "engineer"
    ],
    "wof:name":"Connexions of Perranporth",
    "wof:placetype":"venue"
},
  "geometry": {"coordinates":[-5.1549959183,50.3441162109],"type":"Point"}
}