{
  "type": "Feature",
  "properties": {
    "iso:country":"GB",
    "sg:address":"23 Coalbrookdale Road, Clayhill Light Industrial Park, Neston",
    "sg:city":"Ellesmere Port",
    "sg:classifiers":[
        {
            "category":"Taxi",
            "type":"Transportation"
        },
        {
            "category":"Military Area",
            "subcategory":"Air Force Base",
            "type":"Public Place"
        }
    ],
    "sg:phone":"+44 151 336 3999",
    "sg:postcode":"CH64 3UG",
    "sg:province":"Cheshire",
    "sg:tags":[
        "hire",
        "private"
    ],
    "wof:name":"Thunderbird Taxis",
    "wof:placetype":"venue"
},
  "geometry": {"coordinates":[-3.0578870773,53.3015823364],"type":"Point"}
}