{
  "type": "Feature",
  "properties": {
    "iso:country":"GB",
    "sg:address":"Church Corner, Combe Martin",
    "sg:city":"Ilfracombe",
    "sg:classifiers":[
        {
            "category":"Education",
            "subcategory":"Preschool",
            "type":"Public Place"
        }
    ],
    "sg:phone":"+44 1271 883134",
    "sg:postcode":"EX34 0LQ",
    "sg:province":"Devon",
    "sg:tags":[
        "pre-school",
        "playgroups"
    ],
    "wof:name":"Combe Martin Community Pre-School",
    "wof:placetype":"venue"
},
  "geometry": {"coordinates":[-4.0237140656,51.1986083984],"type":"Point"}
}