{
  "type": "Feature",
  "properties": {
    "addr:full":"54 Newgate St Bishop Auckland Durham DL14 7EQ",
    "addr:housenumber":"54",
    "addr:postcode":"dl14 7eq",
    "addr:street":"Newgate St",
    "iso:country":"GB",
    "sg:address":"54 Newgate St",
    "sg:city":"Bishop Auckland",
    "sg:classifiers":[
        {
            "category":"Communications",
            "subcategory":"Film & Video Production",
            "type":"Services"
        }
    ],
    "sg:phone":"+44 1388 603240",
    "sg:postcode":"DL14 7EQ",
    "sg:province":"Durham",
    "sg:tags":[
        "tv"
    ],
    "wof:name":"Radio Rentals",
    "wof:placetype":"venue"
},
  "geometry": {"coordinates":[-1.6750830412,54.6635322571],"type":"Point"}
}