{
  "type": "Feature",
  "properties": {
    "iso:country":"GB",
    "sg:address":"447 Gallowgate",
    "sg:city":"Glasgow",
    "sg:classifiers":[
        {
            "category":"Bars & Pubs",
            "type":"Food & Drink"
        }
    ],
    "sg:postcode":"G40 2DX",
    "sg:province":"Glasgow City",
    "sg:tags":[
        "pubs",
        "inn"
    ],
    "wof:name":"The Drover Bar",
    "wof:placetype":"venue"
},
  "geometry": {"coordinates":[-4.226662159,55.8556442261],"type":"Point"}
}