{
  "type": "Feature",
  "properties": {
    "addr:full":"140b Ashford Road, Bearsted Maidstone Kent ME14 4NA",
    "addr:housenumber":"140b",
    "addr:postcode":"me14 4na",
    "addr:street":"Ashford Road",
    "iso:country":"GB",
    "sg:address":"140b Ashford Road, Bearsted",
    "sg:city":"Maidstone",
    "sg:classifiers":[
        {
            "category":"Food & Beverages",
            "subcategory":"Meat & Fish",
            "type":"Retail Goods"
        },
        {
            "category":"Food & Beverages",
            "subcategory":"Groceries & Convenience Stores",
            "type":"Retail Goods"
        }
    ],
    "sg:phone":"+44 1622 737081",
    "sg:postcode":"ME14 4NA",
    "sg:province":"Kent",
    "sg:tags":[
        "shop",
        "chip"
    ],
    "wof:name":"Marino Fish Bar",
    "wof:placetype":"venue"
},
  "geometry": {"coordinates":[0.573384,51.267254],"type":"Point"}
}