{
  "type": "Feature",
  "properties": {
    "addr:full":"The Mill House, Lilling York North Yorkshire YO60 6RP",
    "addr:postcode":"yo60 6rp",
    "addr:street":"Lilling",
    "iso:country":"GB",
    "sg:address":"The Mill House, Lilling",
    "sg:city":"York",
    "sg:classifiers":[
        {
            "category":"Professional",
            "subcategory":"Management & Consulting",
            "type":"Services"
        }
    ],
    "sg:postcode":"YO60 6RP",
    "sg:province":"North Yorkshire",
    "sg:tags":[
        "consultant",
        "business"
    ],
    "wof:name":"Terry Ashton",
    "wof:placetype":"venue"
},
  "geometry": {"coordinates":[-0.981404,54.067162],"type":"Point"}
}