{
  "type": "Feature",
  "properties": {
    "iso:country":"GB",
    "sg:address":"East Cramlington Industrial Esta",
    "sg:city":"Cramlington",
    "sg:classifiers":[
        {
            "category":"Retail",
            "subcategory":"Auto Repair",
            "type":"Services"
        }
    ],
    "sg:phone":"+44 1670 733355",
    "sg:postcode":"NE23 6XW",
    "sg:province":"Northumberland",
    "sg:tags":[
        "modification",
        "garage"
    ],
    "wof:name":"Mel's Garage",
    "wof:placetype":"venue"
},
  "geometry": {"coordinates":[-1.564857,55.078117],"type":"Point"}
}