{
  "type": "Feature",
  "properties": {
    "iso:country":"GB",
    "sg:address":"Brighton Terrace",
    "sg:city":"Penzance",
    "sg:classifiers":[
        {
            "category":"Autos & Motor Vehicles",
            "subcategory":"Automobile Sales",
            "type":"Retail Goods"
        },
        {
            "category":"Retail",
            "subcategory":"Auto Repair",
            "type":"Services"
        }
    ],
    "sg:phone":"+44 1736 362717",
    "sg:postcode":"TR18 4HB",
    "sg:province":"Cornwall",
    "sg:tags":[
        "body",
        "car"
    ],
    "wof:name":"Trelawny Garage",
    "wof:placetype":"venue"
},
  "geometry": {"coordinates":[-5.5377788544,50.1143493652],"type":"Point"}
}