{
  "type": "Feature",
  "properties": {
    "addr:full":"Ducksen Road, Mendlesham Stowmarket Suffolk IP14 5TJ",
    "addr:postcode":"ip14 5tj",
    "addr:street":"Ducksen Road",
    "iso:country":"GB",
    "sg:address":"Ducksen Road, Mendlesham",
    "sg:city":"Stowmarket",
    "sg:classifiers":[
        {
            "category":"Social Services",
            "subcategory":"Adult Care",
            "type":"Services"
        },
        {
            "category":"Government",
            "subcategory":"Office",
            "type":"Public Place"
        }
    ],
    "sg:phone":"+44 1449 766654",
    "sg:postcode":"IP14 5TJ",
    "sg:province":"Suffolk",
    "sg:tags":[
        "housing",
        "central",
        "sheltered"
    ],
    "wof:name":"Mason Court Sheltered Housing",
    "wof:placetype":"venue"
},
  "geometry": {"coordinates":[1.0826450586,52.2504997253],"type":"Point"}
}