{
  "type": "Feature",
  "properties": {
    "addr:full":"21 Victoria Avenue Harrogate North Yorkshire HG1 5RD",
    "addr:housenumber":"21",
    "addr:postcode":"hg1 5rd",
    "addr:street":"Victoria Avenue",
    "iso:country":"GB",
    "sg:address":"21 Victoria Avenue",
    "sg:city":"Harrogate",
    "sg:classifiers":[
        {
            "category":"Real Estate",
            "subcategory":"Surveying",
            "type":"Services"
        }
    ],
    "sg:phone":"+44 1423 566362",
    "sg:postcode":"HG1 5RD",
    "sg:province":"North Yorkshire",
    "sg:tags":[
        "surveyor",
        "valuer"
    ],
    "wof:name":"Robert Barry & Co.",
    "wof:placetype":"venue"
},
  "geometry": {"coordinates":[-1.5358480215,53.9912261963],"type":"Point"}
}