{
  "type": "Feature",
  "properties": {
    "iso:country":"GB",
    "sg:address":"Unit 9 Station Yard",
    "sg:city":"Alston",
    "sg:classifiers":[
        {
            "category":"Manufacturing",
            "subcategory":"Rubber & Plastics",
            "type":"Manufacturing & Wholesale Goods"
        }
    ],
    "sg:postcode":"CA9 3HZ",
    "sg:province":"Cumbria",
    "sg:tags":[
        "product"
    ],
    "wof:name":"Portabowl Products",
    "wof:placetype":"venue"
},
  "geometry": {"coordinates":[-2.4417738914,54.8115158081],"type":"Point"}
}