{
  "type": "Feature",
  "properties": {
    "iso:country":"GB",
    "sg:address":"Equity House Business Centre, 6-7 Duke Street",
    "sg:city":"Cardiff",
    "sg:classifiers":[
        {
            "category":"Professional",
            "subcategory":"Detective & Security Services",
            "type":"Services"
        }
    ],
    "sg:postcode":"CF10 1AY",
    "sg:province":"Cardiff",
    "sg:tags":[
        "alarm",
        "burglar",
        "system"
    ],
    "wof:name":"Domestic Audio & Visual Security Systems Ltd.",
    "wof:placetype":"venue"
},
  "geometry": {"coordinates":[-3.180669,51.481258],"type":"Point"}
}