{
  "type": "Feature",
  "properties": {
    "addr:full":"Unit 34, High St Durham Durham DH1 3UL",
    "addr:housenumber":"unit 34",
    "addr:postcode":"dh1 3ul",
    "addr:street":"High St",
    "iso:country":"GB",
    "sg:address":"Unit 34, High St",
    "sg:city":"Durham",
    "sg:classifiers":[
        {
            "category":"Travel",
            "subcategory":"Travel Agent",
            "type":"Entertainment"
        }
    ],
    "sg:phone":"+44 191 374 4300",
    "sg:postcode":"DH1 3UL",
    "sg:province":"Durham",
    "wof:name":"Going Places",
    "wof:placetype":"venue"
},
  "geometry": {"coordinates":[-1.5239390135,54.7925262451],"type":"Point"}
}