{
  "type": "Feature",
  "properties": {
    "addr:full":"14 Seaside Rd Eastbourne East Sussex BN21 3PA",
    "addr:housenumber":"14",
    "addr:postcode":"bn21 3pa",
    "addr:street":"Seaside Rd",
    "iso:country":"GB",
    "sg:address":"14 Seaside Rd",
    "sg:city":"Eastbourne",
    "sg:classifiers":[
        {
            "category":"Shopping",
            "subcategory":"Clothing, Apparel, & Fashions",
            "type":"Retail Goods"
        }
    ],
    "sg:postcode":"BN21 3PA",
    "sg:province":"East Sussex",
    "sg:tags":[
        "menswear"
    ],
    "wof:name":"Chohan,S,",
    "wof:placetype":"venue"
},
  "geometry": {"coordinates":[0.289696,50.767845],"type":"Point"}
}