{
  "type": "Feature",
  "properties": {
    "addr:full":"11 Agincourt Square Monmouth Gloucestershire NP25 3DY",
    "addr:housenumber":"11",
    "addr:postcode":"np25 3dy",
    "addr:street":"Agincourt Square",
    "iso:country":"GB",
    "sg:address":"11 Agincourt Square",
    "sg:city":"Monmouth",
    "sg:classifiers":[
        {
            "category":"Travel",
            "subcategory":"Travel Agent",
            "type":"Entertainment"
        }
    ],
    "sg:phone":"+44 1600 715736",
    "sg:postcode":"NP25 3DY",
    "sg:province":"Gloucestershire",
    "wof:name":"Lunn Poly Ltd.",
    "wof:placetype":"venue"
},
  "geometry": {"coordinates":[-2.7158410549,51.8120231628],"type":"Point"}
}