{
  "type": "Feature",
  "properties": {
    "addr:full":"56 High Street, Kings Heath Birmingham West Midlands B14 7JZ",
    "addr:housenumber":"56",
    "addr:postcode":"b14 7jz",
    "addr:street":"High Street",
    "iso:country":"GB",
    "sg:address":"56 High Street, Kings Heath",
    "sg:city":"Birmingham",
    "sg:classifiers":[
        {
            "category":"Food & Beverages",
            "subcategory":"Meat & Fish",
            "type":"Retail Goods"
        },
        {
            "category":"Food & Beverages",
            "subcategory":"Groceries & Convenience Stores",
            "type":"Retail Goods"
        }
    ],
    "sg:phone":"+44 121 444 8960",
    "sg:postcode":"B14 7JZ",
    "sg:province":"West Midlands",
    "sg:tags":[
        "shop",
        "chip"
    ],
    "wof:name":"High Tide",
    "wof:placetype":"venue"
},
  "geometry": {"coordinates":[-1.8928129673,52.4363517761],"type":"Point"}
}