{
  "type": "Feature",
  "properties": {
    "addr:full":"Broadclose Farm, Broadclose Lane, Inkberrow Worcester Worcestershire WR7 4JW",
    "addr:postcode":"wr7 4jw",
    "addr:street":"Broadclose Lane",
    "iso:country":"GB",
    "sg:address":"Broadclose Farm, Broadclose Lane, Inkberrow",
    "sg:city":"Worcester",
    "sg:classifiers":[
        {
            "category":"Sports & Exercise",
            "subcategory":"Stables",
            "type":"Entertainment"
        }
    ],
    "sg:phone":"+44 1386 792266",
    "sg:postcode":"WR7 4JW",
    "sg:province":"Worcestershire",
    "sg:tags":[
        "education",
        "equestrian"
    ],
    "wof:name":"Broadclose Livery",
    "wof:placetype":"venue"
},
  "geometry": {"coordinates":[-1.980557,52.21323],"type":"Point"}
}