{
  "type": "Feature",
  "properties": {
    "iso:country":"GB",
    "sg:address":"Plaistow La",
    "sg:city":"Bromley",
    "sg:classifiers":[
        {
            "category":"Professional",
            "subcategory":"Management & Consulting",
            "type":"Services"
        },
        {
            "category":"Education",
            "subcategory":"Special Training",
            "type":"Public Place"
        }
    ],
    "sg:phone":"+44 20 8313 3131",
    "sg:postcode":"BR1 3TP",
    "sg:province":"Kent",
    "sg:tags":[
        "consultant",
        "product",
        "business",
        "centre"
    ],
    "wof:name":"Tweed Investments Ltd",
    "wof:placetype":"venue"
},
  "geometry": {"coordinates":[0.02318,51.413857],"type":"Point"}
}