{
  "type": "Feature",
  "properties": {
    "addr:full":"Morven Road, Bearsden Glasgow East Dunbartonshire G61 3SU",
    "addr:postcode":"g61 3su",
    "addr:street":"Morven Road",
    "iso:country":"GB",
    "sg:address":"Morven Road, Bearsden",
    "sg:city":"Glasgow",
    "sg:classifiers":[
        {
            "category":"Education",
            "subcategory":"School",
            "type":"Public Place"
        },
        {
            "category":"Government",
            "subcategory":"Office",
            "type":"Public Place"
        }
    ],
    "sg:phone":"+44 141 942 2297",
    "sg:postcode":"G61 3SU",
    "sg:province":"East Dunbartonshire",
    "sg:tags":[
        "local",
        "authority"
    ],
    "wof:name":"Bearsden Academy",
    "wof:placetype":"venue"
},
  "geometry": {"coordinates":[-4.3273768425,55.9275474548],"type":"Point"}
}