{
  "type": "Feature",
  "properties": {
    "addr:full":"Grove House, Main St Pershore Worcestershire WR10 2NH",
    "addr:postcode":"wr10 2nh",
    "addr:street":"Main St",
    "iso:country":"GB",
    "sg:address":"Grove House, Main St",
    "sg:city":"Pershore",
    "sg:classifiers":[
        {
            "category":"Building & Trades",
            "subcategory":"Cleaning & Sanitation",
            "type":"Services"
        }
    ],
    "sg:phone":"+44 1386 462060",
    "sg:postcode":"WR10 2NH",
    "sg:province":"Worcestershire",
    "sg:tags":[
        "commercial"
    ],
    "wof:name":"Deepclean Hygiene Solutions",
    "wof:placetype":"venue"
},
  "geometry": {"coordinates":[-2.0171310902,52.161441803],"type":"Point"}
}