{
  "type": "Feature",
  "properties": {
    "iso:country":"GB",
    "sg:address":"1 Challymead, Bradford Rd",
    "sg:city":"Melksham",
    "sg:classifiers":[
        {
            "category":"Building & Trades",
            "subcategory":"Construction",
            "type":"Services"
        }
    ],
    "sg:phone":"+44 1225 791919",
    "sg:postcode":"SN12 8BU",
    "sg:province":"Wiltshire",
    "sg:tags":[
        "builder"
    ],
    "wof:name":"Keyford Estates Ltd",
    "wof:placetype":"venue"
},
  "geometry": {"coordinates":[-2.13560009,51.3740653992],"type":"Point"}
}