{
  "type": "Feature",
  "properties": {
    "addr:full":"11 Rhos Road, Rhos On Sea Colwyn Bay Conwy LL28 4PP",
    "addr:housenumber":"11",
    "addr:postcode":"ll28 4pp",
    "addr:street":"Rhos Road",
    "iso:country":"GB",
    "sg:address":"11 Rhos Road, Rhos On Sea",
    "sg:city":"Colwyn Bay",
    "sg:classifiers":[
        {
            "category":"Shopping",
            "subcategory":"Gifts & Souvenirs",
            "type":"Retail Goods"
        }
    ],
    "sg:phone":"+44 1492 548879",
    "sg:postcode":"LL28 4PP",
    "sg:province":"Conwy",
    "sg:tags":[
        "shop"
    ],
    "wof:name":"Shelagh Hyde",
    "wof:placetype":"venue"
},
  "geometry": {"coordinates":[-3.7397890091,53.3089294434],"type":"Point"}
}