{
  "type": "Feature",
  "properties": {
    "addr:full":"Chalk Pit Farm, School Lane, Bekesbourne Canterbury Kent CT4 5ER",
    "addr:postcode":"ct4 5er",
    "addr:street":"School Lane",
    "iso:country":"GB",
    "sg:address":"Chalk Pit Farm, School Lane, Bekesbourne",
    "sg:city":"Canterbury",
    "sg:classifiers":[
        {
            "category":"Shopping",
            "subcategory":"Baby Store",
            "type":"Retail Goods"
        }
    ],
    "sg:phone":"+44 1227 832008",
    "sg:postcode":"CT4 5ER",
    "sg:province":"Kent",
    "sg:tags":[
        "nursery",
        "accessory"
    ],
    "wof:name":"Nippers",
    "wof:placetype":"venue"
},
  "geometry": {"coordinates":[1.1489470005,51.2545166016],"type":"Point"}
}