{
  "type": "Feature",
  "properties": {
    "iso:country":"GB",
    "sg:address":"44 Paramount Court, University Street",
    "sg:city":"London",
    "sg:classifiers":[
        {
            "category":"Professional",
            "subcategory":"Art Services",
            "type":"Services"
        }
    ],
    "sg:postcode":"WC1E 6JP",
    "sg:province":"Greater London",
    "sg:tags":[
        "consultant",
        "design"
    ],
    "wof:name":"Centrepoint Design",
    "wof:placetype":"venue"
},
  "geometry": {"coordinates":[-0.13638,51.523281],"type":"Point"}
}