{
  "type": "Feature",
  "properties": {
    "addr:full":"Dental Surgery, 1 New Market Otley North Yorkshire LS21 3AE",
    "addr:housenumber":"1",
    "addr:postcode":"ls21 3ae",
    "addr:street":"New Market",
    "iso:country":"GB",
    "sg:address":"Dental Surgery, 1 New Market",
    "sg:city":"Otley",
    "sg:classifiers":[
        {
            "category":"Health Services",
            "subcategory":"Dentist",
            "type":"Services"
        }
    ],
    "sg:phone":"+44 1943 464964",
    "sg:postcode":"LS21 3AE",
    "sg:province":"North Yorkshire",
    "wof:name":"R English",
    "wof:placetype":"venue"
},
  "geometry": {"coordinates":[-1.6949529648,53.9057197571],"type":"Point"}
}