{
  "type": "Feature",
  "properties": {
    "addr:full":"Anchor Works, Evesham Road, Astwood Bank Redditch Warwickshire B96 6DU",
    "addr:postcode":"b96 6du",
    "addr:street":"Evesham Road",
    "iso:country":"GB",
    "sg:address":"Anchor Works, Evesham Road, Astwood Bank",
    "sg:city":"Redditch",
    "sg:classifiers":[
        {
            "category":"Communications",
            "subcategory":"News Services",
            "type":"Services"
        }
    ],
    "sg:phone":"+44 1527 892447",
    "sg:postcode":"B96 6DU",
    "sg:province":"Warwickshire",
    "sg:tags":[
        "press"
    ],
    "wof:name":"Cheltenham Road Engineering Co. Ltd.",
    "wof:placetype":"venue"
},
  "geometry": {"coordinates":[-1.937269,52.257889],"type":"Point"}
}