{
  "type": "Feature",
  "properties": {
    "iso:country":"GB",
    "sg:address":"303-305 Burdett Road",
    "sg:city":"London",
    "sg:classifiers":[
        {
            "category":"Communications",
            "type":"Services"
        }
    ],
    "sg:phone":"+44 20 7515 6789",
    "sg:postcode":"E14 7EL",
    "sg:province":"Greater London",
    "sg:tags":[
        "telecommunication"
    ],
    "wof:name":"Blink Design & Communication Ltd.",
    "wof:placetype":"venue"
},
  "geometry": {"coordinates":[-0.027889,51.51408],"type":"Point"}
}