{
  "type": "Feature",
  "properties": {
    "addr:full":"48 Waterside Street Strathaven South Lanarkshire ML10 6AW",
    "addr:housenumber":"48",
    "addr:postcode":"ml10 6aw",
    "addr:street":"Waterside Street",
    "iso:country":"GB",
    "sg:address":"48 Waterside Street",
    "sg:city":"Strathaven",
    "sg:classifiers":[
        {
            "category":"Shopping",
            "subcategory":"Clothing, Apparel, & Fashions",
            "type":"Retail Goods"
        }
    ],
    "sg:phone":"+44 1357 529779",
    "sg:postcode":"ML10 6AW",
    "sg:province":"South Lanarkshire",
    "sg:tags":[
        "dresswear"
    ],
    "wof:name":"Encore Dress Agency",
    "wof:placetype":"venue"
},
  "geometry": {"coordinates":[-4.0647478104,55.677532196],"type":"Point"}
}