{
  "type": "Feature",
  "properties": {
    "addr:full":"193 Lent Rise Road, Burnham Slough Berkshire SL1 7AU",
    "addr:housenumber":"193",
    "addr:postcode":"sl1 7au",
    "addr:street":"Lent Rise Road",
    "iso:country":"GB",
    "sg:address":"193 Lent Rise Road, Burnham",
    "sg:city":"Slough",
    "sg:classifiers":[
        {
            "category":"Building & Trades",
            "subcategory":"Construction",
            "type":"Services"
        },
        {
            "category":"Home & Garden",
            "subcategory":"Carpets & Floor Coverings",
            "type":"Retail Goods"
        }
    ],
    "sg:postcode":"SL1 7AU",
    "sg:province":"Berkshire",
    "sg:tags":[
        "textile",
        "flooring",
        "floorcoverings"
    ],
    "wof:name":"Burnham Flooring Services",
    "wof:placetype":"venue"
},
  "geometry": {"coordinates":[-0.66649,51.531986],"type":"Point"}
}