{
  "type": "Feature",
  "properties": {
    "iso:country":"GB",
    "sg:address":"844 Tong Rd",
    "sg:city":"Leeds",
    "sg:classifiers":[
        {
            "category":"Building & Trades",
            "subcategory":"Plumbing",
            "type":"Services"
        }
    ],
    "sg:phone":"+44 113 255 4741",
    "sg:postcode":"LS12 5HE",
    "sg:province":"West Yorkshire",
    "sg:tags":[
        "central",
        "installation",
        "system",
        "servicing",
        "heating"
    ],
    "wof:name":"Tim Hawkins",
    "wof:placetype":"venue"
},
  "geometry": {"coordinates":[-1.635841,53.783806],"type":"Point"}
}