{
  "type": "Feature",
  "properties": {
    "iso:country":"GB",
    "sg:address":"Bramble, Great Gregories Lane",
    "sg:city":"Epping",
    "sg:classifiers":[
        {
            "category":"Professional",
            "subcategory":"Detective & Security Services",
            "type":"Services"
        }
    ],
    "sg:postcode":"CM16 4EJ",
    "sg:province":"Essex",
    "wof:name":"M C P Security",
    "wof:placetype":"venue"
},
  "geometry": {"coordinates":[0.097428,51.686386],"type":"Point"}
}