{
  "type": "Feature",
  "properties": {
    "iso:country":"GB",
    "sg:address":"Stowford Mills",
    "sg:city":"Ivybridge",
    "sg:classifiers":[
        {
            "category":"Manufacturing",
            "subcategory":"Paper Products",
            "type":"Manufacturing & Wholesale Goods"
        }
    ],
    "sg:phone":"+44 1752 612100",
    "sg:postcode":"PL21 0AA",
    "sg:province":"Devon",
    "sg:tags":[
        "cardboard"
    ],
    "wof:name":"Arjo Wiggings (Fine Paper)",
    "wof:placetype":"venue"
},
  "geometry": {"coordinates":[-3.929039,50.387264],"type":"Point"}
}