{
  "type": "Feature",
  "properties": {
    "addr:full":"43-45 Eastcheap London Greater London EC3M 1JA",
    "addr:housenumber":"43-45",
    "addr:postcode":"ec3m 1ja",
    "addr:street":"Eastcheap",
    "iso:country":"GB",
    "sg:address":"43-45 Eastcheap",
    "sg:city":"London",
    "sg:classifiers":[
        {
            "category":"Banks & Credit Unions",
            "subcategory":"Financial Services",
            "type":"Services"
        }
    ],
    "sg:phone":"+44 20 7621 1109",
    "sg:postcode":"EC3M 1JA",
    "sg:province":"Greater London",
    "sg:tags":[
        "building",
        "society"
    ],
    "wof:name":"Britannia Building Society",
    "wof:placetype":"venue"
},
  "geometry": {"coordinates":[-0.0832289979,51.5105781555],"type":"Point"}
}