{
  "type": "Feature",
  "properties": {
    "addr:full":"1a Swanbourne Road Sheffield South Yorkshire S5 7TJ",
    "addr:housenumber":"1a",
    "addr:postcode":"s5 7tj",
    "addr:street":"Swanbourne Road",
    "iso:country":"GB",
    "sg:address":"1a Swanbourne Road",
    "sg:city":"Sheffield",
    "sg:classifiers":[
        {
            "category":"Retail",
            "subcategory":"Driving School",
            "type":"Services"
        }
    ],
    "sg:phone":"+44 114 245 9777",
    "sg:postcode":"S5 7TJ",
    "sg:province":"South Yorkshire",
    "wof:name":"Martins Driving School",
    "wof:placetype":"venue"
},
  "geometry": {"coordinates":[-1.4567079544,53.4220962524],"type":"Point"}
}