{
  "type": "Feature",
  "properties": {
    "iso:country":"GB",
    "sg:address":", West Burton Leyburn",
    "sg:city":"Leyburn",
    "sg:classifiers":[
        {
            "category":"Education",
            "subcategory":"School",
            "type":"Public Place"
        }
    ],
    "sg:phone":"+44 1969 663230",
    "sg:postcode":"DL8 4JY",
    "sg:province":"North Yorkshire",
    "sg:tags":[
        "local",
        "authority"
    ],
    "wof:name":"West Burton C of E Primary School",
    "wof:placetype":"venue"
},
  "geometry": {"coordinates":[-1.973304987,54.2791252136],"type":"Point"}
}