{
  "type": "Feature",
  "properties": {
    "addr:full":"222 Kneller Road, Whitton Twickenham Greater London TW2 7EF",
    "addr:housenumber":"222",
    "addr:postcode":"tw2 7ef",
    "addr:street":"Kneller Road",
    "iso:country":"GB",
    "sg:address":"222 Kneller Road, Whitton",
    "sg:city":"Twickenham",
    "sg:classifiers":[
        {
            "category":"Organizations",
            "subcategory":"Professional Association",
            "type":"Services"
        }
    ],
    "sg:postcode":"TW2 7EF",
    "sg:province":"Greater London",
    "sg:tags":[
        "artist",
        "make-up"
    ],
    "wof:name":"Aspects of Faces",
    "wof:placetype":"venue"
},
  "geometry": {"coordinates":[-0.360054,51.456448],"type":"Point"}
}