{
  "type": "Feature",
  "properties": {
    "addr:full":"Rear Of 43a Wrotham Rd Gravesend Kent DA11 0PN",
    "addr:housenumber":"rear of 43a",
    "addr:postcode":"da11 0pn",
    "addr:street":"Wrotham Rd",
    "iso:country":"GB",
    "sg:address":"Rear Of 43a Wrotham Rd",
    "sg:city":"Gravesend",
    "sg:classifiers":[
        {
            "category":"Retail",
            "subcategory":"Auto Repair",
            "type":"Services"
        }
    ],
    "sg:postcode":"DA11 0PN",
    "sg:province":"Kent",
    "sg:tags":[
        "modification",
        "garage"
    ],
    "wof:name":"Wallington,Mark,",
    "wof:placetype":"venue"
},
  "geometry": {"coordinates":[0.364606,51.432827],"type":"Point"}
}