{
  "type": "Feature",
  "properties": {
    "addr:full":"Unit 4 Brunel Avenue Salford Greater Manchester M5 4BE",
    "addr:housenumber":"unit 4",
    "addr:postcode":"m5 4be",
    "addr:street":"Brunel Avenue",
    "iso:country":"GB",
    "sg:address":"Unit 4 Brunel Avenue",
    "sg:city":"Salford",
    "sg:classifiers":[
        {
            "category":"Building & Trades",
            "subcategory":"Plumbing",
            "type":"Services"
        },
        {
            "category":"Home & Garden",
            "subcategory":"Hardware",
            "type":"Retail Goods"
        }
    ],
    "sg:phone":"+44 161 925 0873",
    "sg:postcode":"M5 4BE",
    "sg:province":"Greater Manchester",
    "sg:tags":[
        "merchant",
        "plumber",
        "plumbers'"
    ],
    "wof:name":"Plumb Center Ltd",
    "wof:placetype":"venue"
},
  "geometry": {"coordinates":[-2.276084,53.481739],"type":"Point"}
}