{
  "type": "Feature",
  "properties": {
    "iso:country":"GB",
    "sg:address":"47 Countess Street",
    "sg:city":"Saltcoats",
    "sg:classifiers":[
        {
            "category":"Professional",
            "type":"Services"
        }
    ],
    "sg:postcode":"KA21 5HP",
    "sg:province":"North Ayrshire",
    "sg:tags":[
        "repair",
        "tech",
        "maintenance"
    ],
    "wof:name":"P & M Computer Services",
    "wof:placetype":"venue"
},
  "geometry": {"coordinates":[-4.784527,55.633446],"type":"Point"}
}