{
  "type": "Feature",
  "properties": {
    "addr:full":"Stennars Yard, Hartcliffe Way Bristol City of Bristol BS3 5RN",
    "addr:postcode":"bs3 5rn",
    "addr:street":"Hartcliffe Way",
    "iso:country":"GB",
    "sg:address":"Stennars Yard, Hartcliffe Way",
    "sg:city":"Bristol",
    "sg:classifiers":[
        {
            "category":"Home & Garden",
            "subcategory":"Home Furnishings",
            "type":"Retail Goods"
        }
    ],
    "sg:phone":"+44 117 966 6311",
    "sg:postcode":"BS3 5RN",
    "sg:province":"City of Bristol",
    "sg:tags":[
        "furnishers",
        "planner",
        "kitchen"
    ],
    "wof:name":"S & A Kitchens",
    "wof:placetype":"venue"
},
  "geometry": {"coordinates":[-2.6040899754,51.4271888733],"type":"Point"}
}