{
  "type": "Feature",
  "properties": {
    "iso:country":"GB",
    "sg:address":"4 Tower Street",
    "sg:city":"Leicester",
    "sg:classifiers":[
        {
            "category":"Personal",
            "type":"Services"
        },
        {
            "category":"Professional",
            "subcategory":"Lawyer & Legal Services",
            "type":"Services"
        }
    ],
    "sg:phone":"+44 116 254 4341",
    "sg:postcode":"LE1 6WS",
    "sg:province":"Leicestershire",
    "sg:tags":[
        "advice",
        "counselling"
    ],
    "wof:name":"The Laura Centre",
    "wof:placetype":"venue"
},
  "geometry": {"coordinates":[-1.132652,52.628418],"type":"Point"}
}