{
  "type": "Feature",
  "properties": {
    "addr:full":"53 Islington Park Street London Greater London N1 1QB",
    "addr:housenumber":"53",
    "addr:postcode":"n1 1qb",
    "addr:street":"Islington Park Street",
    "iso:country":"GB",
    "sg:address":"53 Islington Park Street",
    "sg:city":"London",
    "sg:classifiers":[
        {
            "category":"Professional",
            "subcategory":"Accounting & Tax Preparation",
            "type":"Services"
        },
        {
            "category":"Food & Beverages",
            "subcategory":"Fruits & Vegetables",
            "type":"Retail Goods"
        }
    ],
    "sg:phone":"+44 20 7359 0827",
    "sg:postcode":"N1 1QB",
    "sg:province":"Greater London",
    "sg:tags":[
        "accountant",
        "greengrocer"
    ],
    "wof:name":"Alpinehurst Ltd.",
    "wof:placetype":"venue"
},
  "geometry": {"coordinates":[-0.1036870033,51.5432472229],"type":"Point"}
}