{
  "type": "Feature",
  "properties": {
    "addr:full":"L I Regimental Association, 14 Mount Street Taunton Somerset TA1 3QE",
    "addr:housenumber":"14",
    "addr:postcode":"ta1 3qe",
    "addr:street":"Mount Street",
    "iso:country":"GB",
    "sg:address":"L I Regimental Association, 14 Mount Street",
    "sg:city":"Taunton",
    "sg:classifiers":[
        {
            "category":"Organizations",
            "subcategory":"Membership Organization",
            "type":"Services"
        }
    ],
    "sg:phone":"+44 1823 333434",
    "sg:postcode":"TA1 3QE",
    "sg:province":"Somerset",
    "sg:tags":[
        "club"
    ],
    "wof:name":"Light Infantry Office",
    "wof:placetype":"venue"
},
  "geometry": {"coordinates":[-3.1106989384,51.0104904175],"type":"Point"}
}