{
  "type": "Feature",
  "properties": {
    "addr:full":"187 High Street, Hampton Hill Hampton Greater London TW12 1NL",
    "addr:housenumber":"187",
    "addr:postcode":"tw12 1nl",
    "addr:street":"High Street",
    "iso:country":"GB",
    "sg:address":"187 High Street, Hampton Hill",
    "sg:city":"Hampton",
    "sg:classifiers":[
        {
            "category":"Manufacturing",
            "subcategory":"Tools & Machinery",
            "type":"Manufacturing & Wholesale Goods"
        },
        {
            "category":"Home & Garden",
            "subcategory":"Hardware",
            "type":"Retail Goods"
        }
    ],
    "sg:phone":"+44 20 8941 0880",
    "sg:postcode":"TW12 1NL",
    "sg:province":"Greater London",
    "wof:name":"A Boyall Ltd.",
    "wof:placetype":"venue"
},
  "geometry": {"coordinates":[-0.3546769917,51.4286231995],"type":"Point"}
}