{
  "type": "Feature",
  "properties": {
    "addr:full":"126 Bangor St, South Reddish Stockport Cheshire SK5 7QA",
    "addr:housenumber":"126",
    "addr:postcode":"sk5 7qa",
    "addr:street":"Bangor St",
    "iso:country":"GB",
    "sg:address":"126 Bangor St, South Reddish",
    "sg:city":"Stockport",
    "sg:classifiers":[
        {
            "category":"Arts & Performance",
            "subcategory":"Music",
            "type":"Entertainment"
        }
    ],
    "sg:phone":"+44 161 477 0838",
    "sg:postcode":"SK5 7QA",
    "sg:province":"Cheshire",
    "sg:tags":[
        "musician",
        "composer"
    ],
    "wof:name":"Adam Hutchins",
    "wof:placetype":"venue"
},
  "geometry": {"coordinates":[-2.1554830074,53.4235343933],"type":"Point"}
}