{
  "type": "Feature",
  "properties": {
    "iso:country":"GB",
    "sg:address":"2 Pavilion Court",
    "sg:city":"Northampton",
    "sg:classifiers":[
        {
            "category":"Professional",
            "subcategory":"Management & Consulting",
            "type":"Services"
        },
        {
            "category":"Organizations",
            "subcategory":"Membership Organization",
            "type":"Services"
        }
    ],
    "sg:phone":"+44 1604 660697",
    "sg:postcode":"NN4 7SL",
    "sg:province":"Northamptonshire",
    "sg:tags":[
        "club",
        "marketing",
        "consultant"
    ],
    "wof:name":"Forecourt & Convenience Services (Facs) Ltd.",
    "wof:placetype":"venue"
},
  "geometry": {"coordinates":[-0.87233,52.218353],"type":"Point"}
}