{
  "type": "Feature",
  "properties": {
    "addr:full":"24-26 Hopetown Road South Queensferry City of Edinburgh EH30 9RB",
    "addr:housenumber":"24-26",
    "addr:postcode":"eh30 9rb",
    "addr:street":"Hopetown Road",
    "iso:country":"GB",
    "sg:address":"24-26 Hopetown Road",
    "sg:city":"South Queensferry",
    "sg:classifiers":[
        {
            "category":"Bars & Pubs",
            "type":"Food & Drink"
        }
    ],
    "sg:phone":"+44 131 331 4346",
    "sg:postcode":"EH30 9RB",
    "sg:province":"City of Edinburgh",
    "sg:tags":[
        "pubs",
        "inn"
    ],
    "wof:name":"The Moorings",
    "wof:placetype":"venue"
},
  "geometry": {"coordinates":[-3.4000499249,55.9907722473],"type":"Point"}
}