{
  "type": "Feature",
  "properties": {
    "addr:full":"58 Knowle Drive, Exwick Exeter Devon EX4 2DG",
    "addr:housenumber":"58",
    "addr:postcode":"ex4 2dg",
    "addr:street":"Knowle Drive",
    "iso:country":"GB",
    "sg:address":"58 Knowle Drive, Exwick",
    "sg:city":"Exeter",
    "sg:classifiers":[
        {
            "category":"Professional",
            "subcategory":"Detective & Security Services",
            "type":"Services"
        }
    ],
    "sg:postcode":"EX4 2DG",
    "sg:province":"Devon",
    "sg:tags":[
        "alarm",
        "burglar",
        "system"
    ],
    "wof:name":"A J Tech",
    "wof:placetype":"venue"
},
  "geometry": {"coordinates":[-3.551906,50.729267],"type":"Point"}
}