{
  "type": "Feature",
  "properties": {
    "addr:full":"Pine Tree Garage Dunstable Bedfordshire LU6 2EQ",
    "addr:postcode":"lu6 2eq",
    "iso:country":"GB",
    "sg:address":"Pine Tree Garage",
    "sg:city":"Dunstable",
    "sg:classifiers":[
        {
            "category":"Autos & Motor Vehicles",
            "subcategory":"Automobile Sales",
            "type":"Retail Goods"
        }
    ],
    "sg:phone":"+44 1525 220000",
    "sg:postcode":"LU6 2EQ",
    "sg:province":"Bedfordshire",
    "sg:tags":[
        "car"
    ],
    "wof:name":"Autobarn",
    "wof:placetype":"venue"
},
  "geometry": {"coordinates":[-0.582865,51.851517],"type":"Point"}
}