{
  "type": "Feature",
  "properties": {
    "iso:country":"GB",
    "sg:address":"164 Walkden Rd, Worsley",
    "sg:city":"Manchester",
    "sg:classifiers":[
        {
            "category":"Banks & Credit Unions",
            "subcategory":"Bank",
            "type":"Services"
        }
    ],
    "sg:phone":"+44 161 799 8812",
    "sg:postcode":"M28 7DP",
    "sg:province":"Greater Manchester",
    "sg:tags":[
        "broker",
        "mortgage"
    ],
    "wof:name":"Mortgage Focus",
    "wof:placetype":"venue"
},
  "geometry": {"coordinates":[-2.3964750767,53.5184631348],"type":"Point"}
}