{
  "type": "Feature",
  "properties": {
    "iso:country":"GB",
    "sg:address":"The Stables, Cuddra Farm",
    "sg:city":"St Austell",
    "sg:classifiers":[
        {
            "category":"Building & Trades",
            "subcategory":"Construction",
            "type":"Services"
        }
    ],
    "sg:postcode":"PL25 3RQ",
    "sg:province":"Cornwall",
    "sg:tags":[
        "builder"
    ],
    "wof:name":"Steve Walker",
    "wof:placetype":"venue"
},
  "geometry": {"coordinates":[-4.74868,50.341808],"type":"Point"}
}