{
  "type": "Feature",
  "properties": {
    "addr:full":"32 Milnrow Road, Shaw Oldham Lancashire OL2 8EQ",
    "addr:housenumber":"32",
    "addr:postcode":"ol2 8eq",
    "addr:street":"Milnrow Road",
    "iso:country":"GB",
    "sg:address":"32 Milnrow Road, Shaw",
    "sg:city":"Oldham",
    "sg:classifiers":[
        {
            "category":"Personal",
            "subcategory":"Barber",
            "type":"Services"
        }
    ],
    "sg:postcode":"OL2 8EQ",
    "sg:province":"Lancashire",
    "sg:tags":[
        "men's",
        "hairdresser"
    ],
    "wof:name":"Margaret Millard",
    "wof:placetype":"venue"
},
  "geometry": {"coordinates":[-2.0925240517,53.5787353516],"type":"Point"}
}