{
  "type": "Feature",
  "properties": {
    "addr:full":"12 High Street, Littlebourne Canterbury Kent CT3 1ST",
    "addr:housenumber":"12",
    "addr:postcode":"ct3 1st",
    "addr:street":"High Street",
    "iso:country":"GB",
    "sg:address":"12 High Street, Littlebourne",
    "sg:city":"Canterbury",
    "sg:classifiers":[
        {
            "category":"Shopping",
            "subcategory":"News",
            "type":"Retail Goods"
        }
    ],
    "sg:postcode":"CT3 1ST",
    "sg:province":"Kent",
    "sg:tags":[
        "newsagent"
    ],
    "wof:name":"Paul A Newton",
    "wof:placetype":"venue"
},
  "geometry": {"coordinates":[1.166273,51.272888],"type":"Point"}
}