{
  "type": "Feature",
  "properties": {
    "addr:full":"30 Mardale Crescent Edinburgh City of Edinburgh EH10 5AG",
    "addr:housenumber":"30",
    "addr:postcode":"eh10 5ag",
    "addr:street":"Mardale Crescent",
    "iso:country":"GB",
    "sg:address":"30 Mardale Crescent",
    "sg:city":"Edinburgh",
    "sg:classifiers":[
        {
            "category":"Professional",
            "subcategory":"Management & Consulting",
            "type":"Services"
        }
    ],
    "sg:postcode":"EH10 5AG",
    "sg:province":"City of Edinburgh",
    "sg:tags":[
        "consultant",
        "business"
    ],
    "wof:name":"Gravity Consultants Ltd",
    "wof:placetype":"venue"
},
  "geometry": {"coordinates":[-3.2155489922,55.933467865],"type":"Point"}
}