{
  "type": "Feature",
  "properties": {
    "addr:full":"Unit 1, 312 Ware Road Hertford Hertfordshire SG13 7ER",
    "addr:housenumber":"unit 1 312",
    "addr:postcode":"sg13 7er",
    "addr:street":"Ware Road",
    "iso:country":"GB",
    "sg:address":"Unit 1, 312 Ware Road",
    "sg:city":"Hertford",
    "sg:classifiers":[
        {
            "category":"Shopping",
            "type":"Retail Goods"
        }
    ],
    "sg:phone":"+44 1992 553655",
    "sg:postcode":"SG13 7ER",
    "sg:province":"Hertfordshire",
    "sg:tags":[
        "part",
        "accessory"
    ],
    "wof:name":"Hertford Brake & Clutch Services Ltd.",
    "wof:placetype":"venue"
},
  "geometry": {"coordinates":[-0.050619,51.802578],"type":"Point"}
}