{
  "type": "Feature",
  "properties": {
    "iso:country":"GB",
    "sg:address":"16 Rushton Crescent",
    "sg:city":"Bournemouth",
    "sg:classifiers":[
        {
            "category":"Travel",
            "subcategory":"Hotels & Motels",
            "type":"Entertainment"
        }
    ],
    "sg:phone":"+44 1202 552808",
    "sg:postcode":"BH3 7AF",
    "sg:province":"Dorset",
    "sg:tags":[
        "house",
        "guest"
    ],
    "wof:name":"Tony Taylor",
    "wof:placetype":"venue"
},
  "geometry": {"coordinates":[-1.8770489693,50.732963562],"type":"Point"}
}