{
  "type": "Feature",
  "properties": {
    "iso:country":"GB",
    "sg:address":"11 Brodawel, Bodedern",
    "sg:city":"Holyhead",
    "sg:classifiers":[
        {
            "category":"Building & Trades",
            "subcategory":"Construction",
            "type":"Services"
        }
    ],
    "sg:phone":"+44 1407 740669",
    "sg:postcode":"LL65 3TB",
    "sg:province":"Isle of Anglesey",
    "sg:tags":[
        "roofing"
    ],
    "wof:name":"H W Roberts & Sons",
    "wof:placetype":"venue"
},
  "geometry": {"coordinates":[-4.5185189247,53.2765007019],"type":"Point"}
}