{
  "type": "Feature",
  "properties": {
    "iso:country":"GB",
    "sg:address":"Albion Mill, Water Street, Great Harwood",
    "sg:city":"Blackburn",
    "sg:classifiers":[
        {
            "category":"Professional",
            "subcategory":"Printing & Photocopies",
            "type":"Services"
        }
    ],
    "sg:phone":"+44 1254 882080",
    "sg:postcode":"BB6 7QR",
    "sg:province":"Lancashire",
    "sg:tags":[
        "printer"
    ],
    "sg:website":"http://www.eprint.co.uk",
    "wof:name":"Educational Printing Services Ltd.",
    "wof:placetype":"venue"
},
  "geometry": {"coordinates":[-2.407644,53.787014],"type":"Point"}
}