{
  "type": "Feature",
  "properties": {
    "addr:full":"73 Townhead, Kirkintilloch Glasgow East Dunbartonshire G66 1NN",
    "addr:housenumber":"73",
    "addr:postcode":"g66 1nn",
    "addr:street":"Townhead Kirkintilloch",
    "iso:country":"GB",
    "sg:address":"73 Townhead, Kirkintilloch",
    "sg:city":"Glasgow",
    "sg:classifiers":[
        {
            "category":"Insurance",
            "subcategory":"Insurance Agent",
            "type":"Services"
        }
    ],
    "sg:phone":"+44 141 776 1214",
    "sg:postcode":"G66 1NN",
    "sg:province":"East Dunbartonshire",
    "sg:tags":[
        "broker"
    ],
    "wof:name":"Kirkintilloch Insurance Services Ltd",
    "wof:placetype":"venue"
},
  "geometry": {"coordinates":[-4.153044,55.937046],"type":"Point"}
}