{
  "type": "Feature",
  "properties": {
    "iso:country":"GB",
    "sg:address":"5 Springfield Crescent",
    "sg:city":"Bideford",
    "sg:classifiers":[
        {
            "category":"Building & Trades",
            "subcategory":"Plumbing",
            "type":"Services"
        }
    ],
    "sg:phone":"+44 1237 470081",
    "sg:postcode":"EX39 1DP",
    "sg:province":"Devon",
    "sg:tags":[
        "heating"
    ],
    "wof:name":"M J McMurray",
    "wof:placetype":"venue"
},
  "geometry": {"coordinates":[-4.237027,51.041698],"type":"Point"}
}