{
  "type": "Feature",
  "properties": {
    "iso:country":"GB",
    "sg:address":"Unit 3b, South Street, Brunswick Industrial Estate",
    "sg:city":"Halifax",
    "sg:classifiers":[
        {
            "category":"Manufacturing",
            "subcategory":"Metals",
            "type":"Manufacturing & Wholesale Goods"
        },
        {
            "category":"Building & Trades",
            "subcategory":"Construction",
            "type":"Services"
        }
    ],
    "sg:phone":"+44 1422 340859",
    "sg:postcode":"HX1 2EL",
    "sg:province":"West Yorkshire",
    "sg:tags":[
        "spinner",
        "worker"
    ],
    "wof:name":"Brunswick Metal Spinners",
    "wof:placetype":"venue"
},
  "geometry": {"coordinates":[-1.867209,53.719395],"type":"Point"}
}