{
  "type": "Feature",
  "properties": {
    "addr:full":"Francis House, Francis Street London Greater London SW1P 1DE",
    "addr:postcode":"sw1p 1de",
    "addr:street":"Francis Street",
    "iso:country":"GB",
    "sg:address":"Francis House, Francis Street",
    "sg:city":"London",
    "sg:classifiers":[
        {
            "category":"Arena",
            "subcategory":"Sports Club",
            "type":"Entertainment"
        }
    ],
    "sg:phone":"+44 20 7233 8898",
    "sg:postcode":"SW1P 1DE",
    "sg:province":"Greater London",
    "wof:name":"The Keep Fit Association",
    "wof:placetype":"venue"
},
  "geometry": {"coordinates":[-0.13647,51.496639],"type":"Point"}
}