{
  "type": "Feature",
  "properties": {
    "addr:full":"Crooks Beck, Ravenstonedale Kirkby Stephen Cumbria CA17 4LJ",
    "addr:postcode":"ca17 4lj",
    "iso:country":"GB",
    "sg:address":"Crooks Beck, Ravenstonedale",
    "sg:city":"Kirkby Stephen",
    "sg:classifiers":[
        {
            "category":"Home & Garden",
            "subcategory":"Garden Supply",
            "type":"Retail Goods"
        },
        {
            "category":"Farming",
            "subcategory":"Farm",
            "type":"Manufacturing & Wholesale Goods"
        }
    ],
    "sg:phone":"+44 15396 23636",
    "sg:postcode":"CA17 4LJ",
    "sg:province":"Cumbria",
    "sg:tags":[
        "mixed",
        "bulb",
        "crop",
        "grower"
    ],
    "wof:name":"James R Law",
    "wof:placetype":"venue"
},
  "geometry": {"coordinates":[-2.3486230373,54.4727172852],"type":"Point"}
}