{
  "type": "Feature",
  "properties": {
    "iso:country":"GB",
    "sg:address":"101 Elwick Road",
    "sg:city":"Hartlepool",
    "sg:classifiers":[
        {
            "category":"Food & Beverages",
            "subcategory":"Meat & Fish",
            "type":"Retail Goods"
        }
    ],
    "sg:phone":"+44 1429 421002",
    "sg:postcode":"TS26 9BB",
    "sg:province":"Durham",
    "sg:tags":[
        "butcher"
    ],
    "wof:name":"Atkinson Butchers",
    "wof:placetype":"venue"
},
  "geometry": {"coordinates":[-1.22103,54.679394],"type":"Point"}
}