{
  "type": "Feature",
  "properties": {
    "addr:full":"Everdene House Anglebury Busines, S Park Sandford L Wareham Dorset BH20 4DY",
    "addr:housenumber":"busines s park",
    "addr:postcode":"bh20 4dy",
    "addr:street":"Anglebury;Sandford L Wareham",
    "iso:country":"GB",
    "sg:address":"Everdene House Anglebury Busines, S Park Sandford L",
    "sg:city":"Wareham",
    "sg:classifiers":[
        {
            "category":"Professional",
            "subcategory":"Business Services",
            "type":"Services"
        }
    ],
    "sg:phone":"+44 1929 555006",
    "sg:postcode":"BH20 4DY",
    "sg:province":"Dorset",
    "sg:tags":[
        "holding"
    ],
    "wof:name":"Realtree Outdoor Products (Europe) Ltd.",
    "wof:placetype":"venue"
},
  "geometry": {"coordinates":[-2.1126070023,50.6898880005],"type":"Point"}
}