{
  "type": "Feature",
  "properties": {
    "iso:country":"GB",
    "sg:address":"Unit 5 Forward Works, Foxoak Street",
    "sg:city":"Cradley Heath",
    "sg:classifiers":[
        {
            "category":"Retail",
            "subcategory":"Auto Repair",
            "type":"Services"
        }
    ],
    "sg:phone":"+44 1384 562499",
    "sg:postcode":"B64 5DP",
    "sg:province":"West Midlands",
    "sg:tags":[
        "modification",
        "garage",
        "related"
    ],
    "wof:name":"M C Motors",
    "wof:placetype":"venue"
},
  "geometry": {"coordinates":[-2.081574,52.472416],"type":"Point"}
}