{
  "type": "Feature",
  "properties": {
    "addr:full":"90 Farrington Road Wolverhampton Staffordshire WV4 6QH",
    "addr:housenumber":"90",
    "addr:postcode":"wv4 6qh",
    "addr:street":"Farrington Road",
    "iso:country":"GB",
    "sg:address":"90 Farrington Road",
    "sg:city":"Wolverhampton",
    "sg:classifiers":[
        {
            "category":"Building & Trades",
            "subcategory":"Construction",
            "type":"Services"
        }
    ],
    "sg:phone":"+44 1902 885414",
    "sg:postcode":"WV4 6QH",
    "sg:province":"Staffordshire",
    "sg:tags":[
        "builder"
    ],
    "wof:name":"Midland Region Development",
    "wof:placetype":"venue"
},
  "geometry": {"coordinates":[-2.118163,52.553631],"type":"Point"}
}