{
  "type": "Feature",
  "properties": {
    "addr:full":"Paul St Exeter Devon EX4 3TT",
    "addr:postcode":"ex4 3tt",
    "addr:street":"Paul St",
    "iso:country":"GB",
    "sg:address":"Paul St",
    "sg:city":"Exeter",
    "sg:classifiers":[
        {
            "category":"Commercial Area",
            "type":"Public Place"
        }
    ],
    "sg:phone":"+44 1392 219366",
    "sg:postcode":"EX4 3TT",
    "sg:province":"Devon",
    "sg:tags":[
        "shop",
        "centre"
    ],
    "wof:name":"Harlequins Shopping Centre",
    "wof:placetype":"venue"
},
  "geometry": {"coordinates":[-3.533344,50.72419],"type":"Point"}
}