{
  "type": "Feature",
  "properties": {
    "addr:full":"49 Fieldhouse Road, Humberston Grimsby Lincolnshire DN36 4UJ",
    "addr:housenumber":"49",
    "addr:postcode":"dn36 4uj",
    "addr:street":"Fieldhouse Road",
    "iso:country":"GB",
    "sg:address":"49 Fieldhouse Road, Humberston",
    "sg:city":"Grimsby",
    "sg:classifiers":[
        {
            "category":"Shopping",
            "subcategory":"Computers & Home Electronics",
            "type":"Retail Goods"
        }
    ],
    "sg:phone":"+44 1472 210601",
    "sg:postcode":"DN36 4UJ",
    "sg:province":"Lincolnshire",
    "wof:name":"J A H Associates",
    "wof:placetype":"venue"
},
  "geometry": {"coordinates":[-0.021682,53.535217],"type":"Point"}
}