{
  "type": "Feature",
  "properties": {
    "addr:full":"131-135 Earls Court Rd Earl's Court Greater London SW5 9RH",
    "addr:housenumber":"131-135",
    "addr:postcode":"sw5 9rh",
    "addr:street":"Earls Court Rd Earl'S Court",
    "iso:country":"GB",
    "sg:address":"131-135 Earls Court Rd",
    "sg:city":"Earl's Court",
    "sg:classifiers":[
        {
            "category":"Health Services",
            "subcategory":"Clinic",
            "type":"Services"
        }
    ],
    "sg:phone":"+44 20 7259 2180",
    "sg:postcode":"SW5 9RH",
    "sg:province":"Greater London",
    "sg:tags":[
        "private"
    ],
    "wof:name":"International Medical Centre",
    "wof:placetype":"venue"
},
  "geometry": {"coordinates":[-0.194284007,51.4933319092],"type":"Point"}
}