{
  "type": "Feature",
  "properties": {
    "addr:full":"498 Fulham Rd Fulham Greater London SW6 5NH",
    "addr:housenumber":"498",
    "addr:postcode":"sw6 5nh",
    "addr:street":"Fulham Rd",
    "iso:country":"GB",
    "sg:address":"498 Fulham Rd",
    "sg:city":"Fulham",
    "sg:classifiers":[
        {
            "category":"Restaurant",
            "type":"Food & Drink"
        }
    ],
    "sg:phone":"+44 1452 332788",
    "sg:postcode":"SW6 5NH",
    "sg:province":"Greater London",
    "sg:tags":[
        "american"
    ],
    "wof:name":"Fat Sams American Food & Beverage Co Ltd",
    "wof:placetype":"venue"
},
  "geometry": {"coordinates":[-0.1986510009,51.4800605774],"type":"Point"}
}