{
  "type": "Feature",
  "properties": {
    "iso:country":"GB",
    "sg:address":"Bryndefaid Farm, Cwmdu",
    "sg:city":"Maesteg",
    "sg:classifiers":[
        {
            "category":"Farming",
            "subcategory":"Livestock Farm",
            "type":"Manufacturing & Wholesale Goods"
        }
    ],
    "sg:phone":"+44 1656 739989",
    "sg:postcode":"CF34 0DH",
    "sg:province":"Bridgend",
    "sg:tags":[
        "others"
    ],
    "wof:name":"E I Howells",
    "wof:placetype":"venue"
},
  "geometry": {"coordinates":[-3.621959,51.60136],"type":"Point"}
}