{
  "type": "Feature",
  "properties": {
    "addr:full":"25a Sutton Court Drive Rochford Essex SS4 1HR",
    "addr:housenumber":"25a",
    "addr:postcode":"ss4 1hr",
    "addr:street":"Sutton Court Drive",
    "iso:country":"GB",
    "sg:address":"25a Sutton Court Drive",
    "sg:city":"Rochford",
    "sg:classifiers":[
        {
            "category":"Freight",
            "type":"Transportation"
        }
    ],
    "sg:postcode":"SS4 1HR",
    "sg:province":"Essex",
    "sg:tags":[
        "haulage",
        "road"
    ],
    "wof:name":"Christopher R Heal",
    "wof:placetype":"venue"
},
  "geometry": {"coordinates":[0.7107669711,51.5731048584],"type":"Point"}
}