{
  "type": "Feature",
  "properties": {
    "addr:full":"174 Manor Lane, Lee London Greater London SE12 8LP",
    "addr:housenumber":"174",
    "addr:postcode":"se12 8lp",
    "addr:street":"Manor Lane",
    "iso:country":"GB",
    "sg:address":"174 Manor Lane, Lee",
    "sg:city":"London",
    "sg:classifiers":[
        {
            "category":"Health Services",
            "subcategory":"Health Practitioner",
            "type":"Services"
        }
    ],
    "sg:phone":"+44 20 8297 8887",
    "sg:postcode":"SE12 8LP",
    "sg:province":"Greater London",
    "sg:tags":[
        "acupuncture",
        "osteopath"
    ],
    "wof:name":"Complementary Health Centre",
    "wof:placetype":"venue"
},
  "geometry": {"coordinates":[0.0055889999,51.4514083862],"type":"Point"}
}