{
  "type": "Feature",
  "properties": {
    "iso:country":"GB",
    "sg:address":"42 Station Road, Darton",
    "sg:city":"Barnsley",
    "sg:classifiers":[
        {
            "category":"Food & Beverages",
            "subcategory":"Bakery",
            "type":"Retail Goods"
        }
    ],
    "sg:phone":"+44 1226 382182",
    "sg:postcode":"S75 5AA",
    "sg:province":"South Yorkshire",
    "sg:tags":[
        "baker"
    ],
    "wof:name":"L Birkinshaw & Sons",
    "wof:placetype":"venue"
},
  "geometry": {"coordinates":[-1.526769,53.585789],"type":"Point"}
}