{
  "type": "Feature",
  "properties": {
    "iso:country":"GB",
    "sg:address":"9 Old Mill, Edinburgh Road, Bridge Of Earn",
    "sg:city":"Perth",
    "sg:classifiers":[
        {
            "category":"Home & Garden",
            "subcategory":"Carpets & Floor Coverings",
            "type":"Retail Goods"
        }
    ],
    "sg:postcode":"PH2 9SZ",
    "sg:province":"Perth and Kinross",
    "sg:tags":[
        "cleaner",
        "upholstery"
    ],
    "wof:name":"Rainbow International",
    "wof:placetype":"venue"
},
  "geometry": {"coordinates":[-3.404575,56.346127],"type":"Point"}
}