{
  "type": "Feature",
  "properties": {
    "addr:full":"Croyland Hall, Burystead Place Wellingborough Northamptonshire NN8 1BJ",
    "addr:postcode":"nn8 1bj",
    "addr:street":"Burystead Place",
    "iso:country":"GB",
    "sg:address":"Croyland Hall, Burystead Place",
    "sg:city":"Wellingborough",
    "sg:classifiers":[
        {
            "category":"Recreation",
            "subcategory":"Water Park",
            "type":"Entertainment"
        },
        {
            "category":"Landmark",
            "subcategory":"Tourist Attraction",
            "type":"Public Place"
        }
    ],
    "sg:phone":"+44 1933 276838",
    "sg:postcode":"NN8 1BJ",
    "sg:province":"Northamptonshire",
    "sg:tags":[
        "theme",
        "interest"
    ],
    "wof:name":"Wellingborough Heritage Centre",
    "wof:placetype":"venue"
},
  "geometry": {"coordinates":[-0.6962959766,52.3024215698],"type":"Point"}
}