{
  "type": "Feature",
  "properties": {
    "addr:full":"117-121 Vicar Lane Leeds West Yorkshire LS1 6PJ",
    "addr:housenumber":"117-121",
    "addr:postcode":"ls1 6pj",
    "addr:street":"Vicar Lane",
    "iso:country":"GB",
    "sg:address":"117-121 Vicar Lane",
    "sg:city":"Leeds",
    "sg:classifiers":[
        {
            "category":"Shopping",
            "subcategory":"Bicycles & Sporting Goods",
            "type":"Retail Goods"
        }
    ],
    "sg:phone":"+44 113 246 5339",
    "sg:postcode":"LS1 6PJ",
    "sg:province":"West Yorkshire",
    "sg:tags":[
        "equipment",
        "camping"
    ],
    "wof:name":"Y H A Adventure Shops Plc",
    "wof:placetype":"venue"
},
  "geometry": {"coordinates":[-1.539968,53.79829],"type":"Point"}
}