{
  "type": "Feature",
  "properties": {
    "iso:country":"GB",
    "sg:address":"Unit 7, Balloon Wood Ind Est, Coventry Lane, Beeston",
    "sg:city":"Nottingham",
    "sg:classifiers":[
        {
            "category":"Retail",
            "subcategory":"Auto Repair",
            "type":"Services"
        }
    ],
    "sg:phone":"+44 115 928 3223",
    "sg:postcode":"NG9 3GJ",
    "sg:province":"Nottinghamshire",
    "sg:tags":[
        "modification",
        "garage"
    ],
    "wof:name":"Conquest International",
    "wof:placetype":"venue"
},
  "geometry": {"coordinates":[-1.2529000044,52.9476013184],"type":"Point"}
}