{
  "type": "Feature",
  "properties": {
    "iso:country":"GB",
    "sg:address":"Office, 17 Metro House, 57 Pepper Rd",
    "sg:city":"Leeds",
    "sg:classifiers":[
        {
            "category":"Professional",
            "subcategory":"Business Services",
            "type":"Services"
        }
    ],
    "sg:phone":"+44 113 277 5222",
    "sg:postcode":"LS10 2RU",
    "sg:province":"West Yorkshire",
    "sg:tags":[
        "shop",
        "cleaning"
    ],
    "wof:name":"D.G.M.G Cleaning Services",
    "wof:placetype":"venue"
},
  "geometry": {"coordinates":[-1.522374,53.773838],"type":"Point"}
}