{
  "type": "Feature",
  "properties": {
    "iso:country":"GB",
    "sg:address":"40 Lily Hill Road",
    "sg:city":"Bracknell",
    "sg:classifiers":[
        {
            "category":"Building & Trades",
            "subcategory":"Construction",
            "type":"Services"
        }
    ],
    "sg:phone":"+44 1344 426585",
    "sg:postcode":"RG12 2SD",
    "sg:province":"Berkshire",
    "sg:tags":[
        "builder"
    ],
    "wof:name":"Ascot Home Improvements",
    "wof:placetype":"venue"
},
  "geometry": {"coordinates":[-0.7202399969,51.4145851135],"type":"Point"}
}