{
  "type": "Feature",
  "properties": {
    "addr:full":"157 Blackpool Old Road Poulton-le-fylde Lancashire FY6 7RS",
    "addr:housenumber":"157",
    "addr:postcode":"fy6 7rs",
    "addr:street":"Blackpool Old Road Poulton-Le-Fylde",
    "iso:country":"GB",
    "sg:address":"157 Blackpool Old Road",
    "sg:city":"Poulton-le-fylde",
    "sg:classifiers":[
        {
            "category":"Food & Beverages",
            "subcategory":"Liquor & Beverages",
            "type":"Retail Goods"
        }
    ],
    "sg:phone":"+44 1253 883068",
    "sg:postcode":"FY6 7RS",
    "sg:province":"Lancashire",
    "sg:tags":[
        "beer",
        "wine",
        "spirit",
        "wines"
    ],
    "wof:name":"Continental Wines",
    "wof:placetype":"venue"
},
  "geometry": {"coordinates":[-3.005127,53.843159],"type":"Point"}
}