{
  "type": "Feature",
  "properties": {
    "addr:full":"23 Stockton Rd Rugby Northamptonshire CV23 8QP",
    "addr:housenumber":"23",
    "addr:postcode":"cv23 8qp",
    "addr:street":"Stockton Rd",
    "iso:country":"GB",
    "sg:address":"23 Stockton Rd",
    "sg:city":"Rugby",
    "sg:classifiers":[
        {
            "category":"Retail",
            "subcategory":"Driving School",
            "type":"Services"
        }
    ],
    "sg:phone":"+44 1926 812751",
    "sg:postcode":"CV23 8QP",
    "sg:province":"Northamptonshire",
    "wof:name":"A Charles",
    "wof:placetype":"venue"
},
  "geometry": {"coordinates":[-1.388212,52.281227],"type":"Point"}
}