{
  "type": "Feature",
  "properties": {
    "addr:full":"Cedar House, The Parade, Frimley High St, Frimley Camberley Hampshire GU16 5HY",
    "addr:postcode":"gu16 5hy",
    "addr:street":"The Parade;High St",
    "iso:country":"GB",
    "sg:address":"Cedar House, The Parade, Frimley High St, Frimley",
    "sg:city":"Camberley",
    "sg:classifiers":[
        {
            "category":"Professional",
            "subcategory":"Management & Consulting",
            "type":"Services"
        }
    ],
    "sg:phone":"+44 1276 691019",
    "sg:postcode":"GU16 5HY",
    "sg:province":"Hampshire",
    "sg:tags":[
        "consultant",
        "business"
    ],
    "wof:name":"Bridge",
    "wof:placetype":"venue"
},
  "geometry": {"coordinates":[-0.7143,51.30394],"type":"Point"}
}