{
  "type": "Feature",
  "properties": {
    "iso:country":"GB",
    "sg:address":"1-3 Catherine Street",
    "sg:city":"Rochester",
    "sg:classifiers":[
        {
            "category":"Bars & Pubs",
            "type":"Food & Drink"
        }
    ],
    "sg:phone":"+44 1634 843934",
    "sg:postcode":"ME1 2HJ",
    "sg:province":"Kent",
    "sg:tags":[
        "pubs",
        "inn"
    ],
    "wof:name":"The Rose Inn",
    "wof:placetype":"venue"
},
  "geometry": {"coordinates":[0.50733,51.37785],"type":"Point"}
}