{
  "type": "Feature",
  "properties": {
    "addr:full":"The Old Methodist Church Alford Lincolnshire LN13 9DU",
    "addr:postcode":"ln13 9du",
    "iso:country":"GB",
    "sg:address":"The Old Methodist Church",
    "sg:city":"Alford",
    "sg:classifiers":[
        {
            "category":"Home & Garden",
            "subcategory":"Furniture",
            "type":"Retail Goods"
        }
    ],
    "sg:phone":"+44 1507 462936",
    "sg:postcode":"LN13 9DU",
    "sg:province":"Lincolnshire",
    "wof:name":"Alford Bargain Centre",
    "wof:placetype":"venue"
},
  "geometry": {"coordinates":[0.1800930053,53.261505127],"type":"Point"}
}