{
  "type": "Feature",
  "properties": {
    "addr:full":"Capitol House, Russell Street Leeds West Yorkshire LS1 5SP",
    "addr:postcode":"ls1 5sp",
    "addr:street":"Russell Street",
    "iso:country":"GB",
    "sg:address":"Capitol House, Russell Street",
    "sg:city":"Leeds",
    "sg:classifiers":[
        {
            "category":"Education",
            "subcategory":"Special Training",
            "type":"Public Place"
        }
    ],
    "sg:phone":"+44 113 234 6777",
    "sg:postcode":"LS1 5SP",
    "sg:province":"West Yorkshire",
    "sg:tags":[
        "product",
        "centre"
    ],
    "wof:name":"Remarc Technologies Ltd.",
    "wof:placetype":"venue"
},
  "geometry": {"coordinates":[-1.547844,53.798069],"type":"Point"}
}