{
  "type": "Feature",
  "properties": {
    "iso:country":"GB",
    "sg:address":"Unit E, 6 Harwood Road",
    "sg:city":"York",
    "sg:classifiers":[
        {
            "category":"Home & Garden",
            "subcategory":"Home Furnishings",
            "type":"Retail Goods"
        },
        {
            "category":"Home & Garden",
            "subcategory":"Carpets & Floor Coverings",
            "type":"Retail Goods"
        }
    ],
    "sg:phone":"+44 1904 799733",
    "sg:postcode":"YO26 6QU",
    "sg:province":"North Yorkshire",
    "sg:tags":[
        "blind",
        "rug",
        "matting",
        "fitting",
        "awning",
        "curtain",
        "blinds",
        "canopy",
        "carpets"
    ],
    "wof:name":"Brian Bell Carpets",
    "wof:placetype":"venue"
},
  "geometry": {"coordinates":[-1.1519,53.968418],"type":"Point"}
}