{
  "type": "Feature",
  "properties": {
    "iso:country":"GB",
    "sg:address":"Church Farm, Church Road, Aldermaston",
    "sg:city":"Reading",
    "sg:classifiers":[
        {
            "category":"Farming",
            "subcategory":"Livestock Farm",
            "type":"Manufacturing & Wholesale Goods"
        }
    ],
    "sg:phone":"+44 118 971 2344",
    "sg:postcode":"RG7 4LR",
    "sg:province":"Berkshire",
    "sg:tags":[
        "others"
    ],
    "wof:name":"Frank West",
    "wof:placetype":"venue"
},
  "geometry": {"coordinates":[-1.152579,51.382935],"type":"Point"}
}