{
  "type": "Feature",
  "properties": {
    "iso:country":"GB",
    "sg:address":"Sittingbourne Track Ferry Rd, Iwade",
    "sg:city":"Sittingbourne",
    "sg:classifiers":[
        {
            "category":"Sports & Exercise",
            "subcategory":"Race Track",
            "type":"Entertainment"
        }
    ],
    "sg:phone":"+44 1795 430014",
    "sg:postcode":"ME9 8SP",
    "sg:province":"Kent",
    "sg:tags":[
        "motor"
    ],
    "wof:name":"Sittingbourne Speedway",
    "wof:placetype":"venue"
},
  "geometry": {"coordinates":[0.729547,51.376553],"type":"Point"}
}