{
  "type": "Feature",
  "properties": {
    "iso:country":"GB",
    "sg:address":"The Almonds, Off Almond Close",
    "sg:city":"Liverpool",
    "sg:classifiers":[
        {
            "category":"Building & Trades",
            "subcategory":"Construction",
            "type":"Services"
        }
    ],
    "sg:postcode":"L26 1XL",
    "sg:province":"Merseyside",
    "sg:tags":[
        "decorator",
        "painter"
    ],
    "wof:name":"Heritage Decorators",
    "wof:placetype":"venue"
},
  "geometry": {"coordinates":[-2.840949,53.360497],"type":"Point"}
}