{
  "type": "Feature",
  "properties": {
    "addr:full":"Doncaster Road, Whitley Bridge Goole East Riding of Yorkshire DN14 0JW",
    "addr:postcode":"dn14 0jw",
    "addr:street":"Doncaster Road Whitley Bridge",
    "iso:country":"GB",
    "sg:address":"Doncaster Road, Whitley Bridge",
    "sg:city":"Goole",
    "sg:classifiers":[
        {
            "category":"Home & Garden",
            "subcategory":"Garden Supply",
            "type":"Retail Goods"
        }
    ],
    "sg:phone":"+44 1977 661643",
    "sg:postcode":"DN14 0JW",
    "sg:province":"East Riding of Yorkshire",
    "sg:tags":[
        "nursery",
        "centre"
    ],
    "wof:name":"Crown Garden Centre",
    "wof:placetype":"venue"
},
  "geometry": {"coordinates":[-1.153177,53.696384],"type":"Point"}
}