{
  "type": "Feature",
  "properties": {
    "iso:country":"GB",
    "sg:address":"41 Churchfield Rd",
    "sg:city":"London",
    "sg:classifiers":[
        {
            "category":"Restaurant",
            "type":"Food & Drink"
        }
    ],
    "sg:phone":"+44 20 8896 0202",
    "sg:postcode":"W3 6AY",
    "sg:province":"Greater London",
    "wof:name":"Mijori",
    "wof:placetype":"venue"
},
  "geometry": {"coordinates":[-0.265384,51.508606],"type":"Point"}
}