{
  "type": "Feature",
  "properties": {
    "addr:full":"56a Chapel Road Worthing West Sussex BN11 1DQ",
    "addr:housenumber":"56a",
    "addr:postcode":"bn11 1dq",
    "addr:street":"Chapel Road",
    "iso:country":"GB",
    "sg:address":"56a Chapel Road",
    "sg:city":"Worthing",
    "sg:classifiers":[
        {
            "category":"Communications",
            "subcategory":"Newspaper",
            "type":"Services"
        }
    ],
    "sg:phone":"+44 1903 209025",
    "sg:postcode":"BN11 1DQ",
    "sg:province":"West Sussex",
    "sg:tags":[
        "magazine"
    ],
    "wof:name":"Worthing Guardian Series",
    "wof:placetype":"venue"
},
  "geometry": {"coordinates":[-0.3707489967,50.8132667542],"type":"Point"}
}