{
  "type": "Feature",
  "properties": {
    "iso:country":"GB",
    "sg:address":"Unit 2e, Crossley Park, Crossley Road",
    "sg:city":"Stockport",
    "sg:classifiers":[
        {
            "category":"Shopping",
            "subcategory":"Stationery & Office Supplies",
            "type":"Retail Goods"
        }
    ],
    "sg:phone":"+44 161 432 8111",
    "sg:postcode":"SK4 5BF",
    "sg:province":"Cheshire",
    "sg:tags":[
        "box",
        "carton"
    ],
    "wof:name":"Carton Craft Ltd.",
    "wof:placetype":"venue"
},
  "geometry": {"coordinates":[-2.189049,53.434334],"type":"Point"}
}