{
  "type": "Feature",
  "properties": {
    "iso:country":"GB",
    "sg:address":"Fron Goch, Pencaenewydd",
    "sg:city":"Pwllheli",
    "sg:classifiers":[
        {
            "category":"Shopping",
            "subcategory":"News",
            "type":"Retail Goods"
        }
    ],
    "sg:phone":"+44 1766 810244",
    "sg:postcode":"LL53 6RB",
    "sg:province":"Gwynedd",
    "sg:tags":[
        "newsagent"
    ],
    "wof:name":"Pencaenewydd Village Shop",
    "wof:placetype":"venue"
},
  "geometry": {"coordinates":[-4.37436,52.943417],"type":"Point"}
}