{
  "type": "Feature",
  "properties": {
    "iso:country":"GB",
    "sg:address":"Unit 3 Vale Craft Studios",
    "sg:city":"Worthing",
    "sg:classifiers":[
        {
            "category":"Education",
            "subcategory":"Library",
            "type":"Public Place"
        },
        {
            "category":"Home & Garden",
            "subcategory":"Furniture",
            "type":"Retail Goods"
        }
    ],
    "sg:phone":"+44 1903 874198",
    "sg:postcode":"BN14 0RQ",
    "sg:province":"West Sussex",
    "sg:tags":[
        "reproduction"
    ],
    "wof:name":"Jays",
    "wof:placetype":"venue"
},
  "geometry": {"coordinates":[-0.401424,50.84901],"type":"Point"}
}