{
  "type": "Feature",
  "properties": {
    "iso:country":"GB",
    "sg:address":"The Precinct, Fore St",
    "sg:city":"Kingsbridge",
    "sg:classifiers":[
        {
            "category":"Building & Trades",
            "subcategory":"Plumbing",
            "type":"Services"
        }
    ],
    "sg:phone":"+44 1548 857800",
    "sg:postcode":"TQ7 1PG",
    "sg:province":"Devon",
    "sg:tags":[
        "heating"
    ],
    "wof:name":"T J Rigby",
    "wof:placetype":"venue"
},
  "geometry": {"coordinates":[-3.7775790691,50.288394928],"type":"Point"}
}