{
  "type": "Feature",
  "properties": {
    "iso:country":"GB",
    "sg:address":"42 Church Road",
    "sg:city":"Northolt",
    "sg:classifiers":[
        {
            "category":"Restaurant",
            "type":"Food & Drink"
        }
    ],
    "sg:phone":"+44 20 8845 4361",
    "sg:postcode":"UB5 5AB",
    "sg:province":"Greater London",
    "sg:tags":[
        "indian"
    ],
    "wof:name":"Empress of India",
    "wof:placetype":"venue"
},
  "geometry": {"coordinates":[-0.372988,51.54475],"type":"Point"}
}