{
  "type": "Feature",
  "properties": {
    "iso:country":"GB",
    "sg:address":"Tower Works, Tower Street",
    "sg:city":"Newcastle-upon-tyne",
    "sg:classifiers":[
        {
            "category":"Building & Trades",
            "subcategory":"Construction",
            "type":"Services"
        }
    ],
    "sg:postcode":"NE1 2HZ",
    "sg:province":"Tyne and Wear",
    "sg:tags":[
        "builder"
    ],
    "wof:name":"Hallmark Construction",
    "wof:placetype":"venue"
},
  "geometry": {"coordinates":[-1.612369,54.977917],"type":"Point"}
}