{
  "type": "Feature",
  "properties": {
    "addr:full":"Reigate Road, Hookwood Horley Surrey RH6 0HU",
    "addr:postcode":"rh6 0hu",
    "addr:street":"Reigate Road",
    "iso:country":"GB",
    "sg:address":"Reigate Road, Hookwood",
    "sg:city":"Horley",
    "sg:classifiers":[
        {
            "category":"Bars & Pubs",
            "type":"Food & Drink"
        }
    ],
    "sg:phone":"+44 1293 773611",
    "sg:postcode":"RH6 0HU",
    "sg:province":"Surrey",
    "sg:tags":[
        "pubs",
        "inn"
    ],
    "wof:name":"The Black Horse",
    "wof:placetype":"venue"
},
  "geometry": {"coordinates":[-0.1864109933,51.1691818237],"type":"Point"}
}