{
  "type": "Feature",
  "properties": {
    "addr:full":"Green Lane Medical Centre, Green La Coventry Warwickshire CV3 6EA",
    "addr:postcode":"cv3 6ea",
    "addr:street":"Green La",
    "iso:country":"GB",
    "sg:address":"Green Lane Medical Centre, Green La",
    "sg:city":"Coventry",
    "sg:classifiers":[
        {
            "category":"Health Services",
            "subcategory":"Doctor",
            "type":"Services"
        }
    ],
    "sg:phone":"+44 24 7641 8841",
    "sg:postcode":"CV3 6EA",
    "sg:province":"Warwickshire",
    "sg:tags":[
        "practitioners"
    ],
    "wof:name":"Mohan, J V",
    "wof:placetype":"venue"
},
  "geometry": {"coordinates":[-1.5288239717,52.388004303],"type":"Point"}
}