{
  "type": "Feature",
  "properties": {
    "addr:full":"86 Balham High Road London Greater London SW12 9AG",
    "addr:housenumber":"86",
    "addr:postcode":"sw12 9ag",
    "addr:street":"Balham High Road",
    "iso:country":"GB",
    "sg:address":"86 Balham High Road",
    "sg:city":"London",
    "sg:classifiers":[
        {
            "category":"Professional",
            "subcategory":"Printing & Photocopies",
            "type":"Services"
        }
    ],
    "sg:phone":"+44 20 8673 6765",
    "sg:postcode":"SW12 9AG",
    "sg:province":"Greater London",
    "sg:tags":[
        "printer"
    ],
    "wof:name":"Craigs of Balham",
    "wof:placetype":"venue"
},
  "geometry": {"coordinates":[-0.1498389989,51.4464263916],"type":"Point"}
}