{
  "type": "Feature",
  "properties": {
    "addr:full":"Datchet Road, Horton Slough Berkshire SL3 9QE",
    "addr:postcode":"sl3 9qe",
    "addr:street":"Datchet Road",
    "iso:country":"GB",
    "sg:address":"Datchet Road, Horton",
    "sg:city":"Slough",
    "sg:classifiers":[
        {
            "category":"Arena",
            "subcategory":"Sports Club",
            "type":"Entertainment"
        }
    ],
    "sg:phone":"+44 1753 686016",
    "sg:postcode":"SL3 9QE",
    "sg:province":"Berkshire",
    "wof:name":"Kingsmead Sailing Club",
    "wof:placetype":"venue"
},
  "geometry": {"coordinates":[-0.580488,51.484074],"type":"Point"}
}