{
  "type": "Feature",
  "properties": {
    "addr:full":"14 St Johns Lane Gloucester Gloucestershire GL1 2AT",
    "addr:housenumber":"14",
    "addr:postcode":"gl1 2at",
    "addr:street":"St Johns Lane",
    "iso:country":"GB",
    "sg:address":"14 St Johns Lane",
    "sg:city":"Gloucester",
    "sg:classifiers":[
        {
            "category":"Shopping",
            "subcategory":"Comic Books",
            "type":"Retail Goods"
        }
    ],
    "sg:postcode":"GL1 2AT",
    "sg:province":"Gloucestershire",
    "sg:tags":[
        "jeweller"
    ],
    "wof:name":"J D Brown Ltd.",
    "wof:placetype":"venue"
},
  "geometry": {"coordinates":[-2.24597,51.865852],"type":"Point"}
}