{
  "type": "Feature",
  "properties": {
    "addr:full":"Bell La Brecon Powys LD3 9EE",
    "addr:postcode":"ld3 9ee",
    "addr:street":"Bell La Brecon",
    "iso:country":"GB",
    "sg:address":"Bell La",
    "sg:city":"Brecon",
    "sg:classifiers":[
        {
            "category":"Professional",
            "subcategory":"Printing & Photocopies",
            "type":"Services"
        }
    ],
    "sg:postcode":"LD3 9EE",
    "sg:province":"Powys",
    "sg:tags":[
        "printer"
    ],
    "wof:name":"Acorn Print Services",
    "wof:placetype":"venue"
},
  "geometry": {"coordinates":[-3.3923459053,51.9481697083],"type":"Point"}
}