{
  "type": "Feature",
  "properties": {
    "addr:full":"95 High Rd Benfleet Essex SS7 5LN",
    "addr:housenumber":"95",
    "addr:postcode":"ss7 5ln",
    "addr:street":"High Rd",
    "iso:country":"GB",
    "sg:address":"95 High Rd",
    "sg:city":"Benfleet",
    "sg:classifiers":[
        {
            "category":"Professional",
            "type":"Services"
        }
    ],
    "sg:phone":"+44 1268 755568",
    "sg:postcode":"SS7 5LN",
    "sg:province":"Essex",
    "sg:tags":[
        "entertainer"
    ],
    "wof:name":"Sharpe,Jack,",
    "wof:placetype":"venue"
},
  "geometry": {"coordinates":[0.563065,51.548862],"type":"Point"}
}