{
  "type": "Feature",
  "properties": {
    "iso:country":"GB",
    "sg:address":"Unit 6, Forge Way, Cleveland Industrial Estate",
    "sg:city":"Darlington",
    "sg:classifiers":[
        {
            "category":"Shopping",
            "type":"Retail Goods"
        }
    ],
    "sg:postcode":"DL1 2PJ",
    "sg:province":"Durham",
    "sg:tags":[
        "part",
        "accessory"
    ],
    "wof:name":"Craftgrange Ltd.",
    "wof:placetype":"venue"
},
  "geometry": {"coordinates":[-1.544309,54.538254],"type":"Point"}
}