{
  "type": "Feature",
  "properties": {
    "addr:full":"44 Arden Wy Market Harborough Leicestershire LE16 7DD",
    "addr:housenumber":"44",
    "addr:postcode":"le16 7dd",
    "addr:street":"Arden Wy",
    "iso:country":"GB",
    "sg:address":"44 Arden Wy",
    "sg:city":"Market Harborough",
    "sg:classifiers":[
        {
            "category":"Building & Trades",
            "subcategory":"Construction",
            "type":"Services"
        }
    ],
    "sg:phone":"+44 1858 433656",
    "sg:postcode":"LE16 7DD",
    "sg:province":"Leicestershire",
    "sg:tags":[
        "decorator",
        "painter"
    ],
    "wof:name":"Bob Finch",
    "wof:placetype":"venue"
},
  "geometry": {"coordinates":[-0.9149540067,52.4856491089],"type":"Point"}
}