{
  "type": "Feature",
  "properties": {
    "iso:country":"GB",
    "sg:address":"Grey Street",
    "sg:city":"Warrington",
    "sg:classifiers":[
        {
            "category":"Manufacturing",
            "subcategory":"Wood Products",
            "type":"Manufacturing & Wholesale Goods"
        }
    ],
    "sg:phone":"+44 1925 634334",
    "sg:postcode":"WA1 2PH",
    "sg:province":"Cheshire",
    "sg:tags":[
        "maker",
        "cabinet"
    ],
    "wof:name":"R E Forster (Furniture) Ltd.",
    "wof:placetype":"venue"
},
  "geometry": {"coordinates":[-2.584609,53.392609],"type":"Point"}
}