{
  "type": "Feature",
  "properties": {
    "iso:country":"GB",
    "sg:address":"105-107 Rocky La, Anfield",
    "sg:city":"Liverpool",
    "sg:classifiers":[
        {
            "category":"Food & Beverages",
            "subcategory":"Groceries & Convenience Stores",
            "type":"Retail Goods"
        }
    ],
    "sg:postcode":"L6 4BB",
    "sg:province":"Merseyside",
    "wof:name":"Rahin,J A,",
    "wof:placetype":"venue"
},
  "geometry": {"coordinates":[-2.941247,53.422565],"type":"Point"}
}