{
  "type": "Feature",
  "properties": {
    "addr:full":"Alfreton Road Nottingham Nottinghamshire NG7 4AA",
    "addr:postcode":"ng7 4aa",
    "addr:street":"Alfreton Road",
    "iso:country":"GB",
    "sg:address":"Alfreton Road",
    "sg:city":"Nottingham",
    "sg:classifiers":[
        {
            "category":"Education",
            "subcategory":"School",
            "type":"Public Place"
        }
    ],
    "sg:postcode":"NG7 4AA",
    "sg:province":"Nottinghamshire",
    "sg:tags":[
        "local",
        "authority"
    ],
    "wof:name":"Nottinghamshire County Council",
    "wof:placetype":"venue"
},
  "geometry": {"coordinates":[-1.169627,52.960789],"type":"Point"}
}