{
  "type": "Feature",
  "properties": {
    "addr:full":"1 Manchester Road Exmouth Devon EX8 1DE",
    "addr:housenumber":"1",
    "addr:postcode":"ex8 1de",
    "addr:street":"Manchester Road",
    "iso:country":"GB",
    "sg:address":"1 Manchester Road",
    "sg:city":"Exmouth",
    "sg:classifiers":[
        {
            "category":"Utilities",
            "subcategory":"Mobile Phone",
            "type":"Services"
        }
    ],
    "sg:phone":"+44 1395 224482",
    "sg:postcode":"EX8 1DE",
    "sg:province":"Devon",
    "sg:tags":[
        "battery",
        "supplier"
    ],
    "wof:name":"Exmouth Battery Centre",
    "wof:placetype":"venue"
},
  "geometry": {"coordinates":[-3.4152479172,50.6199378967],"type":"Point"}
}