{
  "type": "Feature",
  "properties": {
    "addr:full":"The New Southgate Surgery, Borough Rd Wakefield West Yorkshire WF1 3SW",
    "addr:postcode":"wf1 3sw",
    "addr:street":"Borough Rd",
    "iso:country":"GB",
    "sg:address":"The New Southgate Surgery, Borough Rd",
    "sg:city":"Wakefield",
    "sg:classifiers":[
        {
            "category":"Health Services",
            "subcategory":"Doctor",
            "type":"Services"
        }
    ],
    "sg:phone":"+44 1924 374974",
    "sg:postcode":"WF1 3SW",
    "sg:province":"West Yorkshire",
    "sg:tags":[
        "practitioners"
    ],
    "wof:name":"Wroe, S J",
    "wof:placetype":"venue"
},
  "geometry": {"coordinates":[-1.49576,53.69968],"type":"Point"}
}