{
  "type": "Feature",
  "properties": {
    "iso:country":"GB",
    "sg:address":"25 Bexhill Road",
    "sg:city":"St Leonards-on-sea",
    "sg:classifiers":[
        {
            "category":"Restaurant",
            "type":"Food & Drink"
        }
    ],
    "sg:phone":"+44 1424 443350",
    "sg:postcode":"TN38 0AH",
    "sg:province":"East Sussex",
    "sg:tags":[
        "oriental"
    ],
    "wof:name":"Yasmin Restaurant",
    "wof:placetype":"venue"
},
  "geometry": {"coordinates":[0.537276,50.851128],"type":"Point"}
}