{
  "type": "Feature",
  "properties": {
    "iso:country":"GB",
    "sg:address":"9 Dunning Walk",
    "sg:city":"Teignmouth",
    "sg:classifiers":[
        {
            "category":"Home & Garden",
            "subcategory":"Carpets & Floor Coverings",
            "type":"Retail Goods"
        }
    ],
    "sg:phone":"+44 1626 770287",
    "sg:postcode":"TQ14 9LW",
    "sg:province":"Devon",
    "sg:tags":[
        "cleaner",
        "upholstery"
    ],
    "wof:name":"Tim's Carpet Fitting",
    "wof:placetype":"venue"
},
  "geometry": {"coordinates":[-3.5076038837,50.5558815002],"type":"Point"}
}