{
  "type": "Feature",
  "properties": {
    "addr:full":"Unit 5 Westover Industrial Estate, Ermington Road Ivybridge Devon PL21 9ES",
    "addr:housenumber":"unit 5",
    "addr:postcode":"pl21 9es",
    "addr:street":"Industrial Estate Ermington Road",
    "iso:country":"GB",
    "sg:address":"Unit 5 Westover Industrial Estate, Ermington Road",
    "sg:city":"Ivybridge",
    "sg:classifiers":[
        {
            "category":"Retail",
            "subcategory":"Auto Repair",
            "type":"Services"
        }
    ],
    "sg:phone":"+44 1752 894663",
    "sg:postcode":"PL21 9ES",
    "sg:province":"Devon",
    "sg:tags":[
        "modification",
        "garage"
    ],
    "wof:name":"K & L Motors",
    "wof:placetype":"venue"
},
  "geometry": {"coordinates":[-3.9273629189,50.3855667114],"type":"Point"}
}