{
  "type": "Feature",
  "properties": {
    "iso:country":"GB",
    "sg:address":"536 Moseley Rd",
    "sg:city":"Birmingham",
    "sg:classifiers":[
        {
            "category":"Autos & Motor Vehicles",
            "subcategory":"Auto Supplies",
            "type":"Retail Goods"
        }
    ],
    "sg:phone":"+44 121 440 0190",
    "sg:postcode":"B12 9AE",
    "sg:province":"West Midlands",
    "sg:tags":[
        "electric"
    ],
    "wof:name":"A J S Electrical",
    "wof:placetype":"venue"
},
  "geometry": {"coordinates":[-1.885956,52.455917],"type":"Point"}
}