{
  "type": "Feature",
  "properties": {
    "addr:full":"Hillfields Farm, Walsgrave-on-sowe Coventry Warwickshire CV2 2DS",
    "addr:postcode":"cv2 2ds",
    "addr:street":"Walsgrave-On-Sowe",
    "iso:country":"GB",
    "sg:address":"Hillfields Farm, Walsgrave-on-sowe",
    "sg:city":"Coventry",
    "sg:classifiers":[
        {
            "category":"Farming",
            "subcategory":"Livestock Farm",
            "type":"Manufacturing & Wholesale Goods"
        }
    ],
    "sg:postcode":"CV2 2DS",
    "sg:province":"Warwickshire",
    "sg:tags":[
        "others"
    ],
    "wof:name":"L E Hill & Co.",
    "wof:placetype":"venue"
},
  "geometry": {"coordinates":[-1.4443689585,52.4248657227],"type":"Point"}
}