{
  "type": "Feature",
  "properties": {
    "iso:country":"GB",
    "sg:address":"Ross Way",
    "sg:city":"Folkestone",
    "sg:classifiers":[
        {
            "category":"Autos & Motor Vehicles",
            "subcategory":"Automobile Sales",
            "type":"Retail Goods"
        },
        {
            "category":"Autos & Motor Vehicles",
            "subcategory":"Auto Supplies",
            "type":"Retail Goods"
        },
        {
            "category":"Autos & Motor Vehicles",
            "subcategory":"Recreational Vehicle Sales",
            "type":"Retail Goods"
        },
        {
            "category":"Retail",
            "subcategory":"Auto Repair",
            "type":"Services"
        }
    ],
    "sg:phone":"+44 1303 249656",
    "sg:postcode":"CT20 3UJ",
    "sg:province":"Kent",
    "sg:tags":[
        "body",
        "used",
        "car",
        "garage",
        "tyre",
        "modification",
        "new"
    ],
    "wof:name":"Kent Auto Panels Ltd.",
    "wof:placetype":"venue"
},
  "geometry": {"coordinates":[1.1412,51.081291],"type":"Point"}
}