{
  "type": "Feature",
  "properties": {
    "iso:country":"GB",
    "sg:address":"Goat Hall Lane, Galleywood",
    "sg:city":"Chelmsford",
    "sg:classifiers":[
        {
            "category":"Transit Center",
            "subcategory":"Passenger",
            "type":"Transportation"
        }
    ],
    "sg:phone":"+44 1245 353847",
    "sg:postcode":"CM2 8PH",
    "sg:province":"Essex",
    "sg:tags":[
        "boarding",
        "kennel",
        "catteries"
    ],
    "wof:name":"Bushmoor Kennels & Cattery",
    "wof:placetype":"venue"
},
  "geometry": {"coordinates":[0.466357,51.69701],"type":"Point"}
}