{
  "type": "Feature",
  "properties": {
    "addr:full":"6a London Road Peterborough Cambridgeshire PE2 8AR",
    "addr:housenumber":"6a",
    "addr:postcode":"pe2 8ar",
    "addr:street":"London Road",
    "iso:country":"GB",
    "sg:address":"6a London Road",
    "sg:city":"Peterborough",
    "sg:classifiers":[
        {
            "category":"Personal",
            "subcategory":"Beauty Salon",
            "type":"Services"
        },
        {
            "category":"Personal",
            "subcategory":"Barber",
            "type":"Services"
        }
    ],
    "sg:phone":"+44 1733 894988",
    "sg:postcode":"PE2 8AR",
    "sg:province":"Cambridgeshire",
    "sg:tags":[
        "unisex",
        "hairdresser"
    ],
    "wof:name":"Hair by Mario & Tonino",
    "wof:placetype":"venue"
},
  "geometry": {"coordinates":[-0.2424090058,52.5654258728],"type":"Point"}
}