{
  "type": "Feature",
  "properties": {
    "addr:full":"4 Station Parade Ruislip Greater London HA4 7DL",
    "addr:housenumber":"4",
    "addr:postcode":"ha4 7dl",
    "addr:street":"Station Parade",
    "iso:country":"GB",
    "sg:address":"4 Station Parade",
    "sg:city":"Ruislip",
    "sg:classifiers":[
        {
            "category":"Food & Beverages",
            "subcategory":"Candy",
            "type":"Retail Goods"
        }
    ],
    "sg:phone":"+44 1895 632812",
    "sg:postcode":"HA4 7DL",
    "sg:province":"Greater London",
    "sg:tags":[
        "confectioner"
    ],
    "wof:name":"Ickenham Rd Post Office",
    "wof:placetype":"venue"
},
  "geometry": {"coordinates":[-0.426279,51.575886],"type":"Point"}
}