{
  "type": "Feature",
  "properties": {
    "addr:full":"37 Manor Road Trowbridge Wiltshire BA14 9HR",
    "addr:housenumber":"37",
    "addr:postcode":"ba14 9hr",
    "addr:street":"Manor Road",
    "iso:country":"GB",
    "sg:address":"37 Manor Road",
    "sg:city":"Trowbridge",
    "sg:classifiers":[
        {
            "category":"Taxi",
            "type":"Transportation"
        },
        {
            "category":"Military Area",
            "subcategory":"Air Force Base",
            "type":"Public Place"
        }
    ],
    "sg:phone":"+44 1225 751152",
    "sg:postcode":"BA14 9HR",
    "sg:province":"Wiltshire",
    "sg:tags":[
        "mini",
        "hire",
        "private",
        "cab"
    ],
    "wof:name":"Black and White Cabs",
    "wof:placetype":"venue"
},
  "geometry": {"coordinates":[-2.228017,51.309292],"type":"Point"}
}