{
  "type": "Feature",
  "properties": {
    "addr:full":"57 John Finnie St Kilmarnock East Ayrshire KA1 1BH",
    "addr:housenumber":"57",
    "addr:postcode":"ka1 1bh",
    "addr:street":"John Finnie St",
    "iso:country":"GB",
    "sg:address":"57 John Finnie St",
    "sg:city":"Kilmarnock",
    "sg:classifiers":[
        {
            "category":"Communications",
            "type":"Services"
        }
    ],
    "sg:phone":"+44 1563 525292",
    "sg:postcode":"KA1 1BH",
    "sg:province":"East Ayrshire",
    "sg:tags":[
        "telecommunication"
    ],
    "wof:name":"Zip Communications",
    "wof:placetype":"venue"
},
  "geometry": {"coordinates":[-4.4997639656,55.6088600159],"type":"Point"}
}