{
  "type": "Feature",
  "properties": {
    "addr:full":"Ashtree Farm, Main Rd, Langrick Boston Lincolnshire PE22 7AW",
    "addr:postcode":"pe22 7aw",
    "addr:street":"Main Rd",
    "iso:country":"GB",
    "sg:address":"Ashtree Farm, Main Rd, Langrick",
    "sg:city":"Boston",
    "sg:classifiers":[
        {
            "category":"Farming",
            "subcategory":"Crops",
            "type":"Manufacturing & Wholesale Goods"
        },
        {
            "category":"Farming",
            "subcategory":"Farm",
            "type":"Manufacturing & Wholesale Goods"
        }
    ],
    "sg:phone":"+44 1205 280309",
    "sg:postcode":"PE22 7AW",
    "sg:province":"Lincolnshire",
    "sg:tags":[
        "mixed",
        "arable"
    ],
    "wof:name":"J R Flatters",
    "wof:placetype":"venue"
},
  "geometry": {"coordinates":[-0.1071270034,53.0221481323],"type":"Point"}
}