{
  "type": "Feature",
  "properties": {
    "addr:full":"24 Balmoral Close Ipswich Suffolk IP2 9EJ",
    "addr:housenumber":"24",
    "addr:postcode":"ip2 9ej",
    "addr:street":"Balmoral Close",
    "iso:country":"GB",
    "sg:address":"24 Balmoral Close",
    "sg:city":"Ipswich",
    "sg:classifiers":[
        {
            "category":"Military Area",
            "subcategory":"Air Force Base",
            "type":"Public Place"
        }
    ],
    "sg:phone":"+44 1473 682488",
    "sg:postcode":"IP2 9EJ",
    "sg:province":"Suffolk",
    "sg:tags":[
        "water",
        "treatment"
    ],
    "wof:name":"Coleman Water Group",
    "wof:placetype":"venue"
},
  "geometry": {"coordinates":[1.130244,52.038635],"type":"Point"}
}