{
  "type": "Feature",
  "properties": {
    "addr:full":"High St Hunstanton Norfolk PE36 6LX",
    "addr:postcode":"pe36 6lx",
    "addr:street":"High St",
    "iso:country":"GB",
    "sg:address":"High St",
    "sg:city":"Hunstanton",
    "sg:classifiers":[
        {
            "category":"Retail",
            "subcategory":"Auto Repair",
            "type":"Services"
        }
    ],
    "sg:postcode":"PE36 6LX",
    "sg:province":"Norfolk",
    "sg:tags":[
        "modification",
        "garage"
    ],
    "wof:name":"Hayward,Ken W,",
    "wof:placetype":"venue"
},
  "geometry": {"coordinates":[0.5879250169,52.9595451355],"type":"Point"}
}