{
  "type": "Feature",
  "properties": {
    "addr:full":"Unit 14 Springvale Mill, Flip Road Rossendale Lancashire BB4 5EJ",
    "addr:housenumber":"unit 14",
    "addr:postcode":"bb4 5ej",
    "addr:street":"Springvale Mill Flip Road",
    "iso:country":"GB",
    "sg:address":"Unit 14 Springvale Mill, Flip Road",
    "sg:city":"Rossendale",
    "sg:classifiers":[
        {
            "category":"Home & Garden",
            "subcategory":"Home Furnishings",
            "type":"Retail Goods"
        }
    ],
    "sg:postcode":"BB4 5EJ",
    "sg:province":"Lancashire",
    "sg:tags":[
        "soft"
    ],
    "wof:name":"R Cushions Us",
    "wof:placetype":"venue"
},
  "geometry": {"coordinates":[-2.274823904,53.7089614868],"type":"Point"}
}