{
  "type": "Feature",
  "properties": {
    "addr:full":"132 Stanley Park Road Carshalton Surrey SM5 3JG",
    "addr:housenumber":"132",
    "addr:postcode":"sm5 3jg",
    "addr:street":"Stanley Park Road",
    "iso:country":"GB",
    "sg:address":"132 Stanley Park Road",
    "sg:city":"Carshalton",
    "sg:classifiers":[
        {
            "category":"Retail",
            "subcategory":"Emissions Testing",
            "type":"Services"
        },
        {
            "category":"Professional",
            "subcategory":"Testing Lab",
            "type":"Services"
        }
    ],
    "sg:phone":"+44 20 8669 1996",
    "sg:postcode":"SM5 3JG",
    "sg:province":"Surrey",
    "sg:tags":[
        "mot"
    ],
    "wof:name":"Regency Car Centre",
    "wof:placetype":"venue"
},
  "geometry": {"coordinates":[-0.1643929929,51.3542137146],"type":"Point"}
}