{
  "type": "Feature",
  "properties": {
    "addr:full":"227 Rosemount Place Aberdeen Aberdeen City AB2 4XS",
    "addr:housenumber":"227",
    "addr:postcode":"ab2 4xs",
    "addr:street":"Rosemount Place",
    "iso:country":"GB",
    "sg:address":"227 Rosemount Place",
    "sg:city":"Aberdeen",
    "sg:classifiers":[
        {
            "category":"Food & Beverages",
            "subcategory":"Bakery",
            "type":"Retail Goods"
        }
    ],
    "sg:postcode":"AB2 4XS",
    "sg:province":"Aberdeen City",
    "sg:tags":[
        "baker"
    ],
    "wof:name":"Thain's Bakery",
    "wof:placetype":"venue"
},
  "geometry": {"coordinates":[-2.1198129654,57.1494522095],"type":"Point"}
}