{
  "type": "Feature",
  "properties": {
    "addr:full":"2 Cecil Court, London Road Enfield Greater London EN2 6DB",
    "addr:housenumber":"2",
    "addr:postcode":"en2 6db",
    "addr:street":"Cecil Court London Road",
    "iso:country":"GB",
    "sg:address":"2 Cecil Court, London Road",
    "sg:city":"Enfield",
    "sg:classifiers":[
        {
            "category":"Professional",
            "subcategory":"Accounting & Tax Preparation",
            "type":"Services"
        }
    ],
    "sg:postcode":"EN2 6DB",
    "sg:province":"Greater London",
    "sg:tags":[
        "accountant"
    ],
    "wof:name":"Armitage Davis & Co",
    "wof:placetype":"venue"
},
  "geometry": {"coordinates":[-0.0876490027,51.6531066895],"type":"Point"}
}