{
  "type": "Feature",
  "properties": {
    "addr:full":"56 Walton Street London Greater London SW3 1RB",
    "addr:housenumber":"56",
    "addr:postcode":"sw3 1rb",
    "addr:street":"Walton Street",
    "iso:country":"GB",
    "sg:address":"56 Walton Street",
    "sg:city":"London",
    "sg:classifiers":[
        {
            "category":"Food & Beverages",
            "subcategory":"Liquor & Beverages",
            "type":"Retail Goods"
        }
    ],
    "sg:phone":"+44 20 8978 5601",
    "sg:postcode":"SW3 1RB",
    "sg:province":"Greater London",
    "sg:tags":[
        "beer",
        "spirit",
        "wines"
    ],
    "wof:name":"College Cellar Ltd.",
    "wof:placetype":"venue"
},
  "geometry": {"coordinates":[-0.1641290039,51.4965515137],"type":"Point"}
}