{
  "type": "Feature",
  "properties": {
    "iso:country":"GB",
    "sg:address":"Owlet Road",
    "sg:city":"Chester-le-street",
    "sg:classifiers":[
        {
            "category":"Autos & Motor Vehicles",
            "subcategory":"Automobile Sales",
            "type":"Retail Goods"
        }
    ],
    "sg:phone":"+44 191 388 4412",
    "sg:postcode":"DH2 2RR",
    "sg:province":"Durham",
    "sg:tags":[
        "car"
    ],
    "wof:name":"Owlet Car Sales",
    "wof:placetype":"venue"
},
  "geometry": {"coordinates":[-1.60734,54.862011],"type":"Point"}
}