{
  "type": "Feature",
  "properties": {
    "addr:full":"109 Roundhill Road Kettering Northamptonshire NN15 6BG",
    "addr:housenumber":"109",
    "addr:postcode":"nn15 6bg",
    "addr:street":"Roundhill Road",
    "iso:country":"GB",
    "sg:address":"109 Roundhill Road",
    "sg:city":"Kettering",
    "sg:classifiers":[
        {
            "category":"Building & Trades",
            "subcategory":"Construction",
            "type":"Services"
        }
    ],
    "sg:phone":"+44 1536 512455",
    "sg:postcode":"NN15 6BG",
    "sg:province":"Northamptonshire",
    "sg:tags":[
        "decorator",
        "painter"
    ],
    "wof:name":"Jane Neilan",
    "wof:placetype":"venue"
},
  "geometry": {"coordinates":[-0.7245429754,52.3906211853],"type":"Point"}
}