{
  "type": "Feature",
  "properties": {
    "addr:full":"5 Oldroyd Todmorden Lancashire OL14 6BE",
    "addr:housenumber":"5",
    "addr:postcode":"ol14 6be",
    "addr:street":"Oldroyd Todmorden",
    "iso:country":"GB",
    "sg:address":"5 Oldroyd",
    "sg:city":"Todmorden",
    "sg:classifiers":[
        {
            "category":"Professional",
            "subcategory":"Engineering",
            "type":"Services"
        }
    ],
    "sg:phone":"+44 1706 818889",
    "sg:postcode":"OL14 6BE",
    "sg:province":"Lancashire",
    "sg:tags":[
        "contractor",
        "electrical",
        "engineer"
    ],
    "wof:name":"Geoffrey F Shepherd",
    "wof:placetype":"venue"
},
  "geometry": {"coordinates":[-2.07576,53.711269],"type":"Point"}
}