{
  "type": "Feature",
  "properties": {
    "addr:full":"18 The Oval Bath Somerset BA2 2HB",
    "addr:housenumber":"18",
    "addr:postcode":"ba2 2hb",
    "addr:street":"The Oval",
    "iso:country":"GB",
    "sg:address":"18 The Oval",
    "sg:city":"Bath",
    "sg:classifiers":[
        {
            "category":"Building & Trades",
            "subcategory":"Construction",
            "type":"Services"
        }
    ],
    "sg:phone":"+44 1225 319750",
    "sg:postcode":"BA2 2HB",
    "sg:province":"Somerset",
    "sg:tags":[
        "roofing",
        "contracting"
    ],
    "wof:name":"Frome Roofing Specialists",
    "wof:placetype":"venue"
},
  "geometry": {"coordinates":[-2.3841600418,51.3697395325],"type":"Point"}
}