{
  "type": "Feature",
  "properties": {
    "iso:country":"GB",
    "sg:address":"33 Pudding La",
    "sg:city":"Hemel Hempstead",
    "sg:classifiers":[
        {
            "category":"Building & Trades",
            "subcategory":"Construction",
            "type":"Services"
        }
    ],
    "sg:phone":"+44 1442 253690",
    "sg:postcode":"HP1 3JU",
    "sg:province":"Hertfordshire",
    "sg:tags":[
        "contractor",
        "paving",
        "driveway"
    ],
    "wof:name":"G.L. Parbery Paving Services",
    "wof:placetype":"venue"
},
  "geometry": {"coordinates":[-0.4913380146,51.7632064819],"type":"Point"}
}