{
  "type": "Feature",
  "properties": {
    "addr:full":"Woodlands Ave, Immingham Grimsby Lincolnshire DN40 2JB",
    "addr:postcode":"dn40 2jb",
    "addr:street":"Woodlands Ave",
    "iso:country":"GB",
    "sg:address":"Woodlands Ave, Immingham",
    "sg:city":"Grimsby",
    "sg:classifiers":[
        {
            "category":"Community Center",
            "type":"Public Place"
        },
        {
            "category":"Organizations",
            "subcategory":"Membership Organization",
            "type":"Services"
        }
    ],
    "sg:postcode":"DN40 2JB",
    "sg:province":"Lincolnshire",
    "sg:tags":[
        "club",
        "recreation",
        "leisure",
        "centre"
    ],
    "wof:name":"Hobson,Michael,",
    "wof:placetype":"venue"
},
  "geometry": {"coordinates":[-0.2079239935,53.6205787659],"type":"Point"}
}