{
  "type": "Feature",
  "properties": {
    "addr:full":"6 Brooke Street Dumfries Dumfries and Galloway DG1 2JL",
    "addr:housenumber":"6",
    "addr:postcode":"dg1 2jl",
    "addr:street":"Brooke Street",
    "iso:country":"GB",
    "sg:address":"6 Brooke Street",
    "sg:city":"Dumfries",
    "sg:classifiers":[
        {
            "category":"Communications",
            "subcategory":"Film & Video Production",
            "type":"Services"
        },
        {
            "category":"Retail",
            "subcategory":"Repair Shop",
            "type":"Services"
        }
    ],
    "sg:phone":"+44 1387 265600",
    "sg:postcode":"DG1 2JL",
    "sg:province":"Dumfries and Galloway",
    "sg:tags":[
        "tv",
        "radio",
        "television",
        "studio"
    ],
    "wof:name":"Alistair S Rankin",
    "wof:placetype":"venue"
},
  "geometry": {"coordinates":[-3.607472,55.068329],"type":"Point"}
}