{
  "type": "Feature",
  "properties": {
    "addr:full":"Derby House Lytham Road, Fulwood Preston Lancashire PR2 8JF",
    "addr:postcode":"pr2 8jf",
    "addr:street":"Lytham Road",
    "iso:country":"GB",
    "sg:address":"Derby House Lytham Road, Fulwood",
    "sg:city":"Preston",
    "sg:classifiers":[
        {
            "category":"Banks & Credit Unions",
            "subcategory":"Financial Services",
            "type":"Services"
        }
    ],
    "sg:phone":"+44 1772 718817",
    "sg:postcode":"PR2 8JF",
    "sg:province":"Lancashire",
    "sg:tags":[
        "adviser"
    ],
    "wof:name":"Wallwork Ludlow Ltd.",
    "wof:placetype":"venue"
},
  "geometry": {"coordinates":[-2.710694,53.777538],"type":"Point"}
}