{
  "type": "Feature",
  "properties": {
    "addr:full":"4 Lemon Street Truro Cornwall TR1 2LQ",
    "addr:housenumber":"4",
    "addr:postcode":"tr1 2lq",
    "addr:street":"Lemon Street",
    "iso:country":"GB",
    "sg:address":"4 Lemon Street",
    "sg:city":"Truro",
    "sg:classifiers":[
        {
            "category":"Retail",
            "subcategory":"Photofinishing",
            "type":"Services"
        }
    ],
    "sg:phone":"+44 1872 277760",
    "sg:postcode":"TR1 2LQ",
    "sg:province":"Cornwall",
    "sg:tags":[
        "photographic",
        "processor"
    ],
    "wof:name":"Hot Shots",
    "wof:placetype":"venue"
},
  "geometry": {"coordinates":[-5.051007,50.263203],"type":"Point"}
}