{
  "type": "Feature",
  "properties": {
    "addr:full":"Woodstock, Westwood Road Welshpool Shropshire SY21 7EJ",
    "addr:postcode":"sy21 7ej",
    "addr:street":"Westwood Road",
    "iso:country":"GB",
    "sg:address":"Woodstock, Westwood Road",
    "sg:city":"Welshpool",
    "sg:classifiers":[
        {
            "category":"Professional",
            "subcategory":"Art Services",
            "type":"Services"
        }
    ],
    "sg:phone":"+44 1938 553750",
    "sg:postcode":"SY21 7EJ",
    "sg:province":"Shropshire",
    "sg:tags":[
        "photographer"
    ],
    "wof:name":"Photography by Ken Noy",
    "wof:placetype":"venue"
},
  "geometry": {"coordinates":[-3.145203,52.66119],"type":"Point"}
}