{
  "type": "Feature",
  "properties": {
    "iso:country":"GB",
    "sg:address":"Tyburn Industrial Estate, Ashold Farm Road",
    "sg:city":"Birmingham",
    "sg:classifiers":[
        {
            "category":"Home & Garden",
            "subcategory":"Building Materials",
            "type":"Retail Goods"
        }
    ],
    "sg:phone":"+44 121 382 4312",
    "sg:postcode":"B24 9QG",
    "sg:province":"West Midlands",
    "sg:tags":[
        "ventilator",
        "ventilation",
        "system"
    ],
    "wof:name":"Ketville Ltd.",
    "wof:placetype":"venue"
},
  "geometry": {"coordinates":[-1.8169089556,52.5150260925],"type":"Point"}
}