{
  "type": "Feature",
  "properties": {
    "addr:full":"107 High Street, Wealdstone Harrow Greater London HA3 5DL",
    "addr:housenumber":"107",
    "addr:postcode":"ha3 5dl",
    "addr:street":"High Street",
    "iso:country":"GB",
    "sg:address":"107 High Street, Wealdstone",
    "sg:city":"Harrow",
    "sg:classifiers":[
        {
            "category":"Retail",
            "subcategory":"Funeral Services",
            "type":"Services"
        }
    ],
    "sg:phone":"+44 20 8427 6739",
    "sg:postcode":"HA3 5DL",
    "sg:province":"Greater London",
    "sg:tags":[
        "director"
    ],
    "wof:name":"G Saville & Son Ltd.",
    "wof:placetype":"venue"
},
  "geometry": {"coordinates":[-0.336307,51.597095],"type":"Point"}
}