{
  "type": "Feature",
  "properties": {
    "iso:country":"GB",
    "sg:address":"High Street",
    "sg:city":"Macduff",
    "sg:classifiers":[
        {
            "category":"Education",
            "subcategory":"Library",
            "type":"Public Place"
        }
    ],
    "sg:phone":"+44 1261 833289",
    "sg:postcode":"AB44 1LR",
    "sg:province":"Aberdeenshire",
    "sg:tags":[
        "book"
    ],
    "wof:name":"Macduff Library",
    "wof:placetype":"venue"
},
  "geometry": {"coordinates":[-2.492464,57.669361],"type":"Point"}
}