{
  "type": "Feature",
  "properties": {
    "addr:full":"Thorngreen Farm Blairgowrie Perth and Kinross PH10 6SE",
    "addr:postcode":"ph10 6se",
    "addr:street":"Blairgowrie",
    "iso:country":"GB",
    "sg:address":"Thorngreen Farm",
    "sg:city":"Blairgowrie",
    "sg:classifiers":[
        {
            "category":"Farming",
            "subcategory":"Farm",
            "type":"Manufacturing & Wholesale Goods"
        }
    ],
    "sg:phone":"+44 1250 884215",
    "sg:postcode":"PH10 6SE",
    "sg:province":"Perth and Kinross",
    "sg:tags":[
        "mixed",
        "crop"
    ],
    "wof:name":"James Neill & Sons",
    "wof:placetype":"venue"
},
  "geometry": {"coordinates":[-3.336929,56.591431],"type":"Point"}
}