{
  "type": "Feature",
  "properties": {
    "iso:country":"GB",
    "sg:address":"4 Spring Road, Tyseley",
    "sg:city":"Birmingham",
    "sg:classifiers":[
        {
            "category":"Health Services",
            "subcategory":"Dentist",
            "type":"Services"
        }
    ],
    "sg:phone":"+44 121 777 1827",
    "sg:postcode":"B11 3DL",
    "sg:province":"West Midlands",
    "sg:tags":[
        "technician",
        "dental"
    ],
    "wof:name":"David Thompson",
    "wof:placetype":"venue"
},
  "geometry": {"coordinates":[-1.846654,52.446598],"type":"Point"}
}