{
  "type": "Feature",
  "properties": {
    "iso:country":"GB",
    "sg:address":"9 Reynolds Road",
    "sg:city":"Ipswich",
    "sg:classifiers":[
        {
            "category":"Home & Garden",
            "subcategory":"Hardware",
            "type":"Retail Goods"
        }
    ],
    "sg:phone":"+44 1473 725773",
    "sg:postcode":"IP3 0JL",
    "sg:province":"Suffolk",
    "wof:name":"Quality Hardware & D.I.Y",
    "wof:placetype":"venue"
},
  "geometry": {"coordinates":[1.179821,52.035633],"type":"Point"}
}