{
  "type": "Feature",
  "properties": {
    "addr:full":"121 Middleton Avenue, Chingford London Greater London E4 8EE",
    "addr:housenumber":"121",
    "addr:postcode":"e4 8ee",
    "addr:street":"Middleton Avenue",
    "iso:country":"GB",
    "sg:address":"121 Middleton Avenue, Chingford",
    "sg:city":"London",
    "sg:classifiers":[
        {
            "category":"Professional",
            "subcategory":"Engineering",
            "type":"Services"
        }
    ],
    "sg:phone":"+44 20 8524 8625",
    "sg:postcode":"E4 8EE",
    "sg:province":"Greater London",
    "sg:tags":[
        "contractor",
        "electrical",
        "engineer"
    ],
    "wof:name":"E M F Electrical Contractors",
    "wof:placetype":"venue"
},
  "geometry": {"coordinates":[-0.021002,51.620796],"type":"Point"}
}