{
  "type": "Feature",
  "properties": {
    "addr:full":"6 New St Chelmsford Essex CM1 1NT",
    "addr:housenumber":"6",
    "addr:postcode":"cm1 1nt",
    "addr:street":"New St",
    "iso:country":"GB",
    "sg:address":"6 New St",
    "sg:city":"Chelmsford",
    "sg:classifiers":[
        {
            "category":"Freight",
            "type":"Transportation"
        }
    ],
    "sg:phone":"+44 1245 705661",
    "sg:postcode":"CM1 1NT",
    "sg:province":"Essex",
    "sg:tags":[
        "shipping"
    ],
    "wof:name":"Jardine Ship Management (uk) Ltd",
    "wof:placetype":"venue"
},
  "geometry": {"coordinates":[0.473108,51.735432],"type":"Point"}
}