{
  "type": "Feature",
  "properties": {
    "iso:country":"GB",
    "sg:address":"148-150 Hills Road",
    "sg:city":"Cambridge",
    "sg:classifiers":[
        {
            "category":"Shopping",
            "subcategory":"Mobile Phones",
            "type":"Retail Goods"
        }
    ],
    "sg:phone":"+44 870 168 2035",
    "sg:postcode":"CB2 2PB",
    "sg:province":"Cambridgeshire",
    "sg:tags":[
        "supplier"
    ],
    "wof:name":"The Carphone Warehouse Ltd",
    "wof:placetype":"venue"
},
  "geometry": {"coordinates":[0.135845,52.189198],"type":"Point"}
}