{
  "type": "Feature",
  "properties": {
    "iso:country":"GB",
    "sg:address":"13a North Street",
    "sg:city":"Havant",
    "sg:classifiers":[
        {
            "category":"Professional",
            "type":"Services"
        },
        {
            "category":"Health Services",
            "subcategory":"Health Practitioner",
            "type":"Services"
        },
        {
            "category":"Health Services",
            "subcategory":"Chiropractor",
            "type":"Services"
        }
    ],
    "sg:phone":"+44 23 9247 1757",
    "sg:postcode":"PO9 1PW",
    "sg:province":"Hampshire",
    "sg:tags":[
        "hypnotherapists",
        "homoeopathic",
        "technique",
        "acupuncture",
        "reflexologists",
        "homeopathic",
        "alexander"
    ],
    "wof:name":"The Homoeopathic Clinic",
    "wof:placetype":"venue"
},
  "geometry": {"coordinates":[-0.981602,50.852184],"type":"Point"}
}