{
  "type": "Feature",
  "properties": {
    "addr:full":"Dental Surgery, 22 Arden Rd, Rubery Birmingham West Midlands B45 0JA",
    "addr:housenumber":"22",
    "addr:postcode":"b45 0ja",
    "addr:street":"Arden Rd",
    "iso:country":"GB",
    "sg:address":"Dental Surgery, 22 Arden Rd, Rubery",
    "sg:city":"Birmingham",
    "sg:classifiers":[
        {
            "category":"Health Services",
            "subcategory":"Dentist",
            "type":"Services"
        }
    ],
    "sg:phone":"+44 121 453 1346",
    "sg:postcode":"B45 0JA",
    "sg:province":"West Midlands",
    "wof:name":"L C Williams",
    "wof:placetype":"venue"
},
  "geometry": {"coordinates":[-2.01584,52.403542],"type":"Point"}
}