{
  "type": "Feature",
  "properties": {
    "iso:country":"GB",
    "sg:address":"55 The Avenue",
    "sg:city":"Seaham",
    "sg:classifiers":[
        {
            "category":"Personal",
            "subcategory":"Barber",
            "type":"Services"
        }
    ],
    "sg:phone":"+44 191 581 4510",
    "sg:postcode":"SR7 8NS",
    "sg:province":"Durham",
    "sg:tags":[
        "men's",
        "hairdresser"
    ],
    "wof:name":"Menz Barber Shop",
    "wof:placetype":"venue"
},
  "geometry": {"coordinates":[-1.3531470299,54.8360176086],"type":"Point"}
}