{
  "type": "Feature",
  "properties": {
    "iso:country":"GB",
    "sg:address":"Farthingloe Cotts, Folkestone Rd",
    "sg:city":"Dover",
    "sg:classifiers":[
        {
            "category":"Professional",
            "subcategory":"Testing Lab",
            "type":"Services"
        }
    ],
    "sg:postcode":"CT15 7AA",
    "sg:province":"Kent",
    "sg:tags":[
        "mot"
    ],
    "wof:name":"Trice,S,",
    "wof:placetype":"venue"
},
  "geometry": {"coordinates":[1.27751,51.117039],"type":"Point"}
}