{
  "type": "Feature",
  "properties": {
    "addr:full":"Rear Of, 1 Walker Road Cardiff Cardiff CF24 2EG",
    "addr:housenumber":"rear of 1",
    "addr:postcode":"cf24 2eg",
    "addr:street":"Walker Road",
    "iso:country":"GB",
    "sg:address":"Rear Of, 1 Walker Road",
    "sg:city":"Cardiff",
    "sg:classifiers":[
        {
            "category":"Retail",
            "subcategory":"Auto Repair",
            "type":"Services"
        }
    ],
    "sg:phone":"+44 29 2046 1676",
    "sg:postcode":"CF24 2EG",
    "sg:province":"Cardiff",
    "sg:tags":[
        "modification",
        "garage"
    ],
    "wof:name":"Alexander Motors",
    "wof:placetype":"venue"
},
  "geometry": {"coordinates":[-3.150949955,51.4807891846],"type":"Point"}
}