{
  "type": "Feature",
  "properties": {
    "addr:full":"24 St Mary Street Chepstow Gloucestershire NP16 5EU",
    "addr:housenumber":"24",
    "addr:postcode":"np16 5eu",
    "addr:street":"St Mary Street",
    "iso:country":"GB",
    "sg:address":"24 St Mary Street",
    "sg:city":"Chepstow",
    "sg:classifiers":[
        {
            "category":"Restaurant",
            "type":"Food & Drink"
        }
    ],
    "sg:phone":"+44 1291 620959",
    "sg:postcode":"NP16 5EU",
    "sg:province":"Gloucestershire",
    "wof:name":"The Grape Escape",
    "wof:placetype":"venue"
},
  "geometry": {"coordinates":[-2.6745529175,51.6423339844],"type":"Point"}
}