{
  "type": "Feature",
  "properties": {
    "iso:country":"GB",
    "sg:address":"Chiswick Centre, 414 Chiswick High Road",
    "sg:city":"London",
    "sg:classifiers":[
        {
            "category":"Wholesale",
            "subcategory":"Books, Periodicals, & Newspapers",
            "type":"Manufacturing & Wholesale Goods"
        }
    ],
    "sg:phone":"+44 20 8996 3333",
    "sg:postcode":"W4 5TF",
    "sg:province":"Greater London",
    "sg:tags":[
        "publishing"
    ],
    "wof:name":"Letts Educational Ltd.",
    "wof:placetype":"venue"
},
  "geometry": {"coordinates":[-0.276565,51.492161],"type":"Point"}
}