{
  "type": "Feature",
  "properties": {
    "addr:full":"Throapham House, Oldcotes Road, Dinnington Sheffield South Yorkshire S25 2QS",
    "addr:postcode":"s25 2qs",
    "addr:street":"Oldcotes Road",
    "iso:country":"GB",
    "sg:address":"Throapham House, Oldcotes Road, Dinnington",
    "sg:city":"Sheffield",
    "sg:classifiers":[
        {
            "category":"Professional",
            "subcategory":"Engineering",
            "type":"Services"
        },
        {
            "category":"Professional",
            "subcategory":"Computer Services",
            "type":"Services"
        }
    ],
    "sg:phone":"+44 1909 568630",
    "sg:postcode":"S25 2QS",
    "sg:province":"South Yorkshire",
    "sg:tags":[
        "development",
        "software",
        "design",
        "engineer"
    ],
    "sg:website":"http://www.bradwell.net",
    "wof:name":"Bradwell I T Solutions Ltd",
    "wof:placetype":"venue"
},
  "geometry": {"coordinates":[-1.209574,53.378925],"type":"Point"}
}