{
  "type": "Feature",
  "properties": {
    "iso:country":"GB",
    "sg:address":"Ashburnham House, Crossways Road",
    "sg:city":"Hindhead",
    "sg:classifiers":[
        {
            "category":"Food & Beverages",
            "subcategory":"Meat & Fish",
            "type":"Retail Goods"
        }
    ],
    "sg:phone":"+44 1428 604442",
    "sg:postcode":"GU26 6HJ",
    "sg:province":"Hampshire",
    "sg:tags":[
        "butcher"
    ],
    "wof:name":"J D McClelland Traditional Butchers",
    "wof:placetype":"venue"
},
  "geometry": {"coordinates":[-0.7536330223,51.1103134155],"type":"Point"}
}