{
  "type": "Feature",
  "properties": {
    "addr:full":"53 Barns Clo, Greenhill Way Newton Abbot Devon TQ12 3SS",
    "addr:housenumber":"53;clo",
    "addr:postcode":"tq12 3ss",
    "addr:street":"Greenhill Way",
    "iso:country":"GB",
    "sg:address":"53 Barns Clo, Greenhill Way",
    "sg:city":"Newton Abbot",
    "sg:classifiers":[
        {
            "category":"Arts & Performance",
            "subcategory":"Music",
            "type":"Entertainment"
        }
    ],
    "sg:phone":"+44 1626 334758",
    "sg:postcode":"TQ12 3SS",
    "sg:province":"Devon",
    "sg:tags":[
        "mobile",
        "disco"
    ],
    "wof:name":"Global Entertainments",
    "wof:placetype":"venue"
},
  "geometry": {"coordinates":[-3.5906889439,50.5433731079],"type":"Point"}
}