{
  "type": "Feature",
  "properties": {
    "addr:full":"Blackabroom Farm Okehampton Devon EX20 4HE",
    "addr:postcode":"ex20 4he",
    "iso:country":"GB",
    "sg:address":"Blackabroom Farm",
    "sg:city":"Okehampton",
    "sg:classifiers":[
        {
            "category":"Farming",
            "subcategory":"Livestock Farm",
            "type":"Manufacturing & Wholesale Goods"
        }
    ],
    "sg:phone":"+44 1837 861223",
    "sg:postcode":"EX20 4HE",
    "sg:province":"Devon",
    "sg:tags":[
        "others"
    ],
    "wof:name":"J T Horn",
    "wof:placetype":"venue"
},
  "geometry": {"coordinates":[-4.120169,50.679871],"type":"Point"}
}