{
  "type": "Feature",
  "properties": {
    "addr:full":"46 The Drive Chelmsford Essex CM3 6AA",
    "addr:housenumber":"46",
    "addr:postcode":"cm3 6aa",
    "addr:street":"The Drive",
    "iso:country":"GB",
    "sg:address":"46 The Drive",
    "sg:city":"Chelmsford",
    "sg:classifiers":[
        {
            "category":"Autos & Motor Vehicles",
            "subcategory":"Automobile Sales",
            "type":"Retail Goods"
        }
    ],
    "sg:phone":"+44 1621 740249",
    "sg:postcode":"CM3 6AA",
    "sg:province":"Essex",
    "sg:tags":[
        "car"
    ],
    "wof:name":"John W Valentine",
    "wof:placetype":"venue"
},
  "geometry": {"coordinates":[0.76144,51.681858],"type":"Point"}
}