{
  "type": "Feature",
  "properties": {
    "addr:full":"8-19 Whitehall Maybole East Ayrshire KA19 7AJ",
    "addr:housenumber":"8-19",
    "addr:postcode":"ka19 7aj",
    "addr:street":"Whitehall Maybole East",
    "iso:country":"GB",
    "sg:address":"8-19 Whitehall",
    "sg:city":"Maybole",
    "sg:classifiers":[
        {
            "category":"Organizations",
            "subcategory":"Community Association",
            "type":"Services"
        },
        {
            "category":"Organizations",
            "subcategory":"Membership Organization",
            "type":"Services"
        }
    ],
    "sg:phone":"+44 1655 883019",
    "sg:postcode":"KA19 7AJ",
    "sg:province":"East Ayrshire",
    "sg:tags":[
        "club",
        "social"
    ],
    "wof:name":"Carrick Sports Club",
    "wof:placetype":"venue"
},
  "geometry": {"coordinates":[-4.6857261658,55.3519935608],"type":"Point"}
}