{
  "type": "Feature",
  "properties": {
    "iso:country":"GB",
    "sg:address":"Coney Hill Education Centre, Croydon Road",
    "sg:city":"Bromley",
    "sg:classifiers":[
        {
            "category":"Education",
            "subcategory":"Special Training",
            "type":"Public Place"
        }
    ],
    "sg:phone":"+44 20 8462 7419",
    "sg:postcode":"BR2 7AG",
    "sg:province":"Kent",
    "sg:tags":[
        "school"
    ],
    "wof:name":"Nash Further Education Centre",
    "wof:placetype":"venue"
},
  "geometry": {"coordinates":[0.00459,51.37117],"type":"Point"}
}