{
  "type": "Feature",
  "properties": {
    "iso:country":"GB",
    "sg:address":"Unit 3, Europa Way",
    "sg:city":"Norwich",
    "sg:classifiers":[
        {
            "category":"Professional",
            "subcategory":"Printing & Photocopies",
            "type":"Services"
        }
    ],
    "sg:phone":"+44 1603 628583",
    "sg:postcode":"NR1 2EN",
    "sg:province":"Norfolk",
    "sg:tags":[
        "printer"
    ],
    "wof:name":"Norwich Label Converters Ltd",
    "wof:placetype":"venue"
},
  "geometry": {"coordinates":[1.310462,52.614902],"type":"Point"}
}