{
  "type": "Feature",
  "properties": {
    "iso:country":"GB",
    "sg:address":"213 Parker Road",
    "sg:city":"Hastings",
    "sg:classifiers":[
        {
            "category":"Retail",
            "subcategory":"Driving School",
            "type":"Services"
        }
    ],
    "sg:postcode":"TN34 3UA",
    "sg:province":"East Sussex",
    "wof:name":"Automatic & Disabled Driving Services",
    "wof:placetype":"venue"
},
  "geometry": {"coordinates":[0.5929560065,50.8712425232],"type":"Point"}
}