{
  "type": "Feature",
  "properties": {
    "iso:country":"GB",
    "sg:address":"22 Broad Street, Staple Hill",
    "sg:city":"Bristol",
    "sg:classifiers":[
        {
            "category":"Real Estate",
            "subcategory":"Real Estate Agent",
            "type":"Services"
        }
    ],
    "sg:phone":"+44 117 956 6004",
    "sg:postcode":"BS16 5NX",
    "sg:province":"City of Bristol",
    "wof:name":"Brunt & Fussell",
    "wof:placetype":"venue"
},
  "geometry": {"coordinates":[-2.591429,51.453667],"type":"Point"}
}