{
  "type": "Feature",
  "properties": {
    "iso:country":"GB",
    "sg:address":"24 Woodhorn Road",
    "sg:city":"Ashington",
    "sg:classifiers":[
        {
            "category":"Organizations",
            "subcategory":"Membership Organization",
            "type":"Services"
        }
    ],
    "sg:phone":"+44 1670 812336",
    "sg:postcode":"NE63 9AE",
    "sg:province":"Northumberland",
    "sg:tags":[
        "club"
    ],
    "wof:name":"Linton & Woodhorn Social Club Ltd.",
    "wof:placetype":"venue"
},
  "geometry": {"coordinates":[-1.56596,55.183926],"type":"Point"}
}