{
  "type": "Feature",
  "properties": {
    "addr:full":"17 Bryce Rd Currie City of Edinburgh EH14 5LT",
    "addr:housenumber":"17",
    "addr:postcode":"eh14 5lt",
    "addr:street":"Bryce Rd",
    "iso:country":"GB",
    "sg:address":"17 Bryce Rd",
    "sg:city":"Currie",
    "sg:classifiers":[
        {
            "category":"Professional",
            "subcategory":"Management & Consulting",
            "type":"Services"
        }
    ],
    "sg:phone":"+44 131 449 2020",
    "sg:postcode":"EH14 5LT",
    "sg:province":"City of Edinburgh",
    "sg:tags":[
        "consultant",
        "specialist"
    ],
    "wof:name":"Beauty By Fiona",
    "wof:placetype":"venue"
},
  "geometry": {"coordinates":[-3.3077299595,55.8999710083],"type":"Point"}
}