{
  "type": "Feature",
  "properties": {
    "addr:full":"Second Floor Nottingham Nottinghamshire NG1 5BH",
    "addr:housenumber":"second",
    "addr:postcode":"ng1 5bh",
    "iso:country":"GB",
    "sg:address":"Second Floor",
    "sg:city":"Nottingham",
    "sg:classifiers":[
        {
            "category":"Professional",
            "subcategory":"Management & Consulting",
            "type":"Services"
        }
    ],
    "sg:phone":"+44 115 924 2944",
    "sg:postcode":"NG1 5BH",
    "sg:province":"Nottinghamshire",
    "sg:tags":[
        "consultant",
        "business"
    ],
    "wof:name":"R B W Associates Ltd.",
    "wof:placetype":"venue"
},
  "geometry": {"coordinates":[-1.1439239979,52.9492263794],"type":"Point"}
}