{
  "type": "Feature",
  "properties": {
    "addr:full":"108 High Street Lockerbie Dumfries and Galloway DG11 2ES",
    "addr:housenumber":"108",
    "addr:postcode":"dg11 2es",
    "addr:street":"High Street",
    "iso:country":"GB",
    "sg:address":"108 High Street",
    "sg:city":"Lockerbie",
    "sg:classifiers":[
        {
            "category":"Shopping",
            "subcategory":"Music",
            "type":"Retail Goods"
        }
    ],
    "sg:phone":"+44 1576 203189",
    "sg:postcode":"DG11 2ES",
    "sg:province":"Dumfries and Galloway",
    "sg:tags":[
        "record",
        "tape",
        "cd"
    ],
    "wof:name":"Margarets",
    "wof:placetype":"venue"
},
  "geometry": {"coordinates":[-3.3554329872,55.1211242676],"type":"Point"}
}