{
  "type": "Feature",
  "properties": {
    "iso:country":"GB",
    "sg:address":"1 Park Square",
    "sg:city":"Scunthorpe",
    "sg:classifiers":[
        {
            "category":"Government",
            "subcategory":"Office",
            "type":"Public Place"
        }
    ],
    "sg:phone":"+44 1724 861222",
    "sg:postcode":"DN15 6JH",
    "sg:province":"Lincolnshire",
    "sg:tags":[
        "central"
    ],
    "wof:name":"The Probation Service",
    "wof:placetype":"venue"
},
  "geometry": {"coordinates":[-0.650529,53.587444],"type":"Point"}
}