{
  "type": "Feature",
  "properties": {
    "iso:country":"GB",
    "sg:address":"Ridge Cottage, Barden Road, Speldhurst",
    "sg:city":"Tunbridge Wells",
    "sg:classifiers":[
        {
            "category":"Professional",
            "subcategory":"Testing Lab",
            "type":"Services"
        }
    ],
    "sg:postcode":"TN3 0LE",
    "sg:province":"East Sussex",
    "sg:tags":[
        "inspection",
        "calibration"
    ],
    "wof:name":"Lambeth Scientific Services Ltd",
    "wof:placetype":"venue"
},
  "geometry": {"coordinates":[0.220383,51.150982],"type":"Point"}
}