{
  "type": "Feature",
  "properties": {
    "addr:full":"1 Collenswood Road Stevenage Hertfordshire SG2 9ER",
    "addr:housenumber":"1",
    "addr:postcode":"sg2 9er",
    "addr:street":"Collenswood Road",
    "iso:country":"GB",
    "sg:address":"1 Collenswood Road",
    "sg:city":"Stevenage",
    "sg:classifiers":[
        {
            "category":"Professional",
            "subcategory":"Employment Agencies",
            "type":"Services"
        }
    ],
    "sg:phone":"+44 1438 214872",
    "sg:postcode":"SG2 9ER",
    "sg:province":"Hertfordshire",
    "sg:tags":[
        "consultant"
    ],
    "wof:name":"Prospects Recruitment Consultants",
    "wof:placetype":"venue"
},
  "geometry": {"coordinates":[-0.172677,51.898705],"type":"Point"}
}