{
  "type": "Feature",
  "properties": {
    "addr:full":"R N A S Culdrose Helston Cornwall TR12 7RP",
    "addr:postcode":"tr12 7rp",
    "addr:street":"R N A S Culdrose",
    "iso:country":"GB",
    "sg:address":"R N A S Culdrose",
    "sg:city":"Helston",
    "sg:classifiers":[
        {
            "category":"Shopping",
            "subcategory":"Clothing, Apparel, & Fashions",
            "type":"Retail Goods"
        }
    ],
    "sg:phone":"+44 1326 562541",
    "sg:postcode":"TR12 7RP",
    "sg:province":"Cornwall",
    "sg:tags":[
        "staff",
        "wear",
        "uniform"
    ],
    "wof:name":"Bernards Naval Tailors",
    "wof:placetype":"venue"
},
  "geometry": {"coordinates":[-5.2663898468,50.0967597961],"type":"Point"}
}