{
  "type": "Feature",
  "properties": {
    "iso:country":"GB",
    "sg:address":"903 Chester Rd",
    "sg:city":"Birmingham",
    "sg:classifiers":[
        {
            "category":"Building & Trades",
            "subcategory":"Construction",
            "type":"Services"
        }
    ],
    "sg:phone":"+44 121 350 4983",
    "sg:postcode":"B24 0HJ",
    "sg:province":"West Midlands",
    "sg:tags":[
        "decorator",
        "painter"
    ],
    "wof:name":"Chester Edwards Decorations",
    "wof:placetype":"venue"
},
  "geometry": {"coordinates":[-1.816568017,52.5287437439],"type":"Point"}
}