{
  "type": "Feature",
  "properties": {
    "addr:full":"Dusthill Farm, Naseby Road, Sibbertoft Market Harborough Leicestershire LE16 9UH",
    "addr:postcode":"le16 9uh",
    "addr:street":"Naseby Road",
    "iso:country":"GB",
    "sg:address":"Dusthill Farm, Naseby Road, Sibbertoft",
    "sg:city":"Market Harborough",
    "sg:classifiers":[
        {
            "category":"Home & Garden",
            "subcategory":"Garden Supply",
            "type":"Retail Goods"
        },
        {
            "category":"Farming",
            "subcategory":"Farm",
            "type":"Manufacturing & Wholesale Goods"
        }
    ],
    "sg:phone":"+44 1858 525211",
    "sg:postcode":"LE16 9UH",
    "sg:province":"Leicestershire",
    "sg:tags":[
        "mixed",
        "bulb",
        "crop",
        "grower"
    ],
    "wof:name":"A & C BOULTON",
    "wof:placetype":"venue"
},
  "geometry": {"coordinates":[-1.000262022,52.4362373352],"type":"Point"}
}