{
  "type": "Feature",
  "properties": {
    "addr:full":"The Stores & Bakery, Rhesycae Holywell Denbighshire CH8 8JG",
    "addr:postcode":"ch8 8jg",
    "addr:street":"Holywell",
    "iso:country":"GB",
    "sg:address":"The Stores & Bakery, Rhesycae",
    "sg:city":"Holywell",
    "sg:classifiers":[
        {
            "category":"Food & Beverages",
            "subcategory":"Fruits & Vegetables",
            "type":"Retail Goods"
        }
    ],
    "sg:postcode":"CH8 8JG",
    "sg:province":"Denbighshire",
    "sg:tags":[
        "greengrocer"
    ],
    "wof:name":"Jones Bros",
    "wof:placetype":"venue"
},
  "geometry": {"coordinates":[-3.2154,53.22897],"type":"Point"}
}