{
  "type": "Feature",
  "properties": {
    "addr:full":"2 Longfield Road London Greater London W5 2DH",
    "addr:housenumber":"2",
    "addr:postcode":"w5 2dh",
    "addr:street":"Longfield Road",
    "iso:country":"GB",
    "sg:address":"2 Longfield Road",
    "sg:city":"London",
    "sg:classifiers":[
        {
            "category":"Arena",
            "subcategory":"Sports Club",
            "type":"Entertainment"
        }
    ],
    "sg:phone":"+44 20 8998 9438",
    "sg:postcode":"W5 2DH",
    "sg:province":"Greater London",
    "wof:name":"London Kyudo Society",
    "wof:placetype":"venue"
},
  "geometry": {"coordinates":[-0.3079920113,51.5163154602],"type":"Point"}
}