{
  "type": "Feature",
  "properties": {
    "addr:full":"Church Road, Trimdon Trimdon Station Durham TS29 6PY",
    "addr:postcode":"ts29 6py",
    "addr:street":"Church Road;Station",
    "iso:country":"GB",
    "sg:address":"Church Road, Trimdon",
    "sg:city":"Trimdon Station",
    "sg:classifiers":[
        {
            "category":"Food & Beverages",
            "subcategory":"Supermarket",
            "type":"Retail Goods"
        }
    ],
    "sg:phone":"+44 1429 880339",
    "sg:postcode":"TS29 6PY",
    "sg:province":"Durham",
    "wof:name":"North Eastern Co-Operative",
    "wof:placetype":"venue"
},
  "geometry": {"coordinates":[-1.4285589457,54.7010726929],"type":"Point"}
}