{
  "type": "Feature",
  "properties": {
    "iso:country":"GB",
    "sg:address":"Gelt Hall, Castle Carrock",
    "sg:city":"Carlisle",
    "sg:classifiers":[
        {
            "category":"Travel",
            "subcategory":"Travel Agent",
            "type":"Entertainment"
        }
    ],
    "sg:phone":"+44 1228 670700",
    "sg:postcode":"CA4 9LT",
    "sg:province":"Cumbria",
    "wof:name":"Lifestyle Travel",
    "wof:placetype":"venue"
},
  "geometry": {"coordinates":[-2.71548,54.89122],"type":"Point"}
}