{
  "type": "Feature",
  "properties": {
    "iso:country":"GB",
    "sg:address":"28 Biddulph Road",
    "sg:city":"Stoke-on-trent",
    "sg:classifiers":[
        {
            "category":"Shopping",
            "subcategory":"News",
            "type":"Retail Goods"
        }
    ],
    "sg:phone":"+44 1782 837536",
    "sg:postcode":"ST6 6SH",
    "sg:province":"Staffordshire",
    "sg:tags":[
        "newsagent"
    ],
    "wof:name":"Mickey's News",
    "wof:placetype":"venue"
},
  "geometry": {"coordinates":[-2.194035,53.072006],"type":"Point"}
}