{
  "type": "Feature",
  "properties": {
    "addr:full":"Balmuick Farm, Comrie Crieff Perth and Kinross PH6 2LY",
    "addr:postcode":"ph6 2ly",
    "iso:country":"GB",
    "sg:address":"Balmuick Farm, Comrie",
    "sg:city":"Crieff",
    "sg:classifiers":[
        {
            "category":"Home & Garden",
            "subcategory":"Garden Supply",
            "type":"Retail Goods"
        }
    ],
    "sg:phone":"+44 1764 670286",
    "sg:postcode":"PH6 2LY",
    "sg:province":"Perth and Kinross",
    "sg:tags":[
        "bulb",
        "grower"
    ],
    "wof:name":"Colin P Crabbie",
    "wof:placetype":"venue"
},
  "geometry": {"coordinates":[-3.985064,56.370964],"type":"Point"}
}