{
  "type": "Feature",
  "properties": {
    "iso:country":"GB",
    "sg:address":"Main Rd",
    "sg:city":"Emsworth",
    "sg:classifiers":[
        {
            "category":"Recreation",
            "subcategory":"Campground",
            "type":"Entertainment"
        }
    ],
    "sg:phone":"+44 1243 373202",
    "sg:postcode":"PO10 8JH",
    "sg:province":"Hampshire",
    "sg:tags":[
        "site",
        "camping"
    ],
    "wof:name":"Chichester Camping",
    "wof:placetype":"venue"
},
  "geometry": {"coordinates":[-0.931289,50.846565],"type":"Point"}
}