{
  "type": "Feature",
  "properties": {
    "addr:full":"32 Glyncollen Crescent, Ynysforgan Swansea Swansea SA6 6SB",
    "addr:housenumber":"32",
    "addr:postcode":"sa6 6sb",
    "addr:street":"Glyncollen Crescent",
    "iso:country":"GB",
    "sg:address":"32 Glyncollen Crescent, Ynysforgan",
    "sg:city":"Swansea",
    "sg:classifiers":[
        {
            "category":"Retail",
            "subcategory":"Driving School",
            "type":"Services"
        }
    ],
    "sg:phone":"+44 1792 772127",
    "sg:postcode":"SA6 6SB",
    "sg:province":"Swansea",
    "wof:name":"Automatic Specialist Tuition",
    "wof:placetype":"venue"
},
  "geometry": {"coordinates":[-3.921206,51.676437],"type":"Point"}
}