{
  "type": "Feature",
  "properties": {
    "iso:country":"GB",
    "sg:address":"26 North Street",
    "sg:city":"Fraserburgh",
    "sg:classifiers":[
        {
            "category":"Building & Trades",
            "subcategory":"Plumbing",
            "type":"Services"
        }
    ],
    "sg:phone":"+44 1346 514474",
    "sg:postcode":"AB43 5DJ",
    "sg:province":"Aberdeenshire",
    "sg:tags":[
        "merchant",
        "plumbers'"
    ],
    "wof:name":"William Wilson Ltd.",
    "wof:placetype":"venue"
},
  "geometry": {"coordinates":[-2.007141,57.694965],"type":"Point"}
}