{
  "type": "Feature",
  "properties": {
    "addr:full":"P O Box 3390, Hatfield Chelmsford Essex CM3 2NE",
    "addr:housenumber":"p o;3390",
    "addr:postcode":"cm3 2ne",
    "addr:street":"Hatfield",
    "iso:country":"GB",
    "sg:address":"P O Box 3390, Hatfield",
    "sg:city":"Chelmsford",
    "sg:classifiers":[
        {
            "category":"Manufacturing",
            "subcategory":"Tools & Machinery",
            "type":"Manufacturing & Wholesale Goods"
        }
    ],
    "sg:phone":"+44 1245 382828",
    "sg:postcode":"CM3 2NE",
    "sg:province":"Essex",
    "sg:tags":[
        "society",
        "friendly"
    ],
    "wof:name":"Hollingworth Associates Ltd.",
    "wof:placetype":"venue"
},
  "geometry": {"coordinates":[0.5913900137,51.7792510986],"type":"Point"}
}