{
  "type": "Feature",
  "properties": {
    "addr:full":"New Ash Tree Farm, Leicester Road, Churchover Rugby Northamptonshire CV23 0EZ",
    "addr:postcode":"cv23 0ez",
    "addr:street":"Leicester Road",
    "iso:country":"GB",
    "sg:address":"New Ash Tree Farm, Leicester Road, Churchover",
    "sg:city":"Rugby",
    "sg:classifiers":[
        {
            "category":"Home & Garden",
            "subcategory":"Garden Supply",
            "type":"Retail Goods"
        },
        {
            "category":"Farming",
            "subcategory":"Crops",
            "type":"Manufacturing & Wholesale Goods"
        },
        {
            "category":"Farming",
            "subcategory":"Livestock Farm",
            "type":"Manufacturing & Wholesale Goods"
        }
    ],
    "sg:phone":"+44 1788 543533",
    "sg:postcode":"CV23 0EZ",
    "sg:province":"Northamptonshire",
    "sg:tags":[
        "bulb",
        "arable",
        "grower",
        "others"
    ],
    "wof:name":"Peter Fowkes",
    "wof:placetype":"venue"
},
  "geometry": {"coordinates":[-1.2493890524,52.4212646484],"type":"Point"}
}