{
  "type": "Feature",
  "properties": {
    "addr:full":"7-11 Broad Weir Bristol City of Bristol BS1 3AZ",
    "addr:housenumber":"7-11",
    "addr:postcode":"bs1 3az",
    "addr:street":"Broad Weir",
    "iso:country":"GB",
    "sg:address":"7-11 Broad Weir",
    "sg:city":"Bristol",
    "sg:classifiers":[
        {
            "category":"Professional",
            "subcategory":"Employment Agencies",
            "type":"Services"
        }
    ],
    "sg:phone":"+44 117 991 3000",
    "sg:postcode":"BS1 3AZ",
    "sg:province":"City of Bristol",
    "sg:tags":[
        "consultant"
    ],
    "wof:name":"Employment Service Jobcentre",
    "wof:placetype":"venue"
},
  "geometry": {"coordinates":[-2.5877459049,51.4566001892],"type":"Point"}
}