{
  "type": "Feature",
  "properties": {
    "addr:full":"124-132 Ber Street Norwich Norfolk NR1 3ES",
    "addr:housenumber":"124-132",
    "addr:postcode":"nr1 3es",
    "addr:street":"Ber Street",
    "iso:country":"GB",
    "sg:address":"124-132 Ber Street",
    "sg:city":"Norwich",
    "sg:classifiers":[
        {
            "category":"Autos & Motor Vehicles",
            "subcategory":"Automobile Sales",
            "type":"Retail Goods"
        }
    ],
    "sg:phone":"+44 1603 615037",
    "sg:postcode":"NR1 3ES",
    "sg:province":"Norfolk",
    "sg:tags":[
        "car"
    ],
    "wof:name":"Sabers",
    "wof:placetype":"venue"
},
  "geometry": {"coordinates":[1.2995100021,52.6224327087],"type":"Point"}
}