{
  "type": "Feature",
  "properties": {
    "iso:country":"GB",
    "sg:address":"2 Cherry Orchard",
    "sg:city":"Newcastle",
    "sg:classifiers":[
        {
            "category":"Real Estate",
            "subcategory":"Surveying",
            "type":"Services"
        }
    ],
    "sg:phone":"+44 1782 715743",
    "sg:postcode":"ST5 2UB",
    "sg:province":"Staffordshire",
    "sg:tags":[
        "surveyor",
        "quantity"
    ],
    "wof:name":"Martin Warrington",
    "wof:placetype":"venue"
},
  "geometry": {"coordinates":[-2.225035,53.014088],"type":"Point"}
}