{
  "type": "Feature",
  "properties": {
    "addr:full":"224 Winsley Road Bradford-on-avon Wiltshire BA15 1QT",
    "addr:housenumber":"224",
    "addr:postcode":"ba15 1qt",
    "addr:street":"Winsley Road",
    "iso:country":"GB",
    "sg:address":"224 Winsley Road",
    "sg:city":"Bradford-on-avon",
    "sg:classifiers":[
        {
            "category":"Food & Beverages",
            "subcategory":"Fruits & Vegetables",
            "type":"Retail Goods"
        }
    ],
    "sg:phone":"+44 1225 862211",
    "sg:postcode":"BA15 1QT",
    "sg:province":"Wiltshire",
    "sg:tags":[
        "greengrocer"
    ],
    "wof:name":"G W R Stone",
    "wof:placetype":"venue"
},
  "geometry": {"coordinates":[-2.25478,51.350483],"type":"Point"}
}