{
  "type": "Feature",
  "properties": {
    "iso:country":"GB",
    "sg:address":"219 Brighton Road",
    "sg:city":"Lancing",
    "sg:classifiers":[
        {
            "category":"Building & Trades",
            "subcategory":"Construction",
            "type":"Services"
        }
    ],
    "sg:postcode":"BN15 8JP",
    "sg:province":"West Sussex",
    "sg:tags":[
        "decorator",
        "painter"
    ],
    "wof:name":"John A Rowe",
    "wof:placetype":"venue"
},
  "geometry": {"coordinates":[-0.311573,50.822701],"type":"Point"}
}