{
  "type": "Feature",
  "properties": {
    "addr:full":"16 Hall Farm Ct Trimdon Station Durham TS29 6QL",
    "addr:housenumber":"16",
    "addr:postcode":"ts29 6ql",
    "addr:street":"Hall Farm Ct",
    "iso:country":"GB",
    "sg:address":"16 Hall Farm Ct",
    "sg:city":"Trimdon Station",
    "sg:classifiers":[
        {
            "category":"Taxi",
            "type":"Transportation"
        }
    ],
    "sg:postcode":"TS29 6QL",
    "sg:province":"Durham",
    "sg:tags":[
        "mini",
        "cab"
    ],
    "wof:name":"Crake,Maurice,",
    "wof:placetype":"venue"
},
  "geometry": {"coordinates":[-1.4082260132,54.6999130249],"type":"Point"}
}