{
  "type": "Feature",
  "properties": {
    "addr:full":"16 Water St Todmorden Lancashire OL14 5AB",
    "addr:housenumber":"16",
    "addr:postcode":"ol14 5ab",
    "addr:street":"Water St",
    "iso:country":"GB",
    "sg:address":"16 Water St",
    "sg:city":"Todmorden",
    "sg:classifiers":[
        {
            "category":"Personal",
            "subcategory":"Nail Salon",
            "type":"Services"
        }
    ],
    "sg:postcode":"OL14 5AB",
    "sg:province":"Lancashire",
    "sg:tags":[
        "solarium",
        "tanning"
    ],
    "wof:name":"Rod's Sun Domes",
    "wof:placetype":"venue"
},
  "geometry": {"coordinates":[-2.097891,53.713451],"type":"Point"}
}