{
  "type": "Feature",
  "properties": {
    "addr:full":"23 Main Street, Kinglassie Lochgelly Fife KY5 0XA",
    "addr:housenumber":"23",
    "addr:postcode":"ky5 0xa",
    "addr:street":"Main Street;Lochgelly",
    "iso:country":"GB",
    "sg:address":"23 Main Street, Kinglassie",
    "sg:city":"Lochgelly",
    "sg:classifiers":[
        {
            "category":"Bus Charters",
            "type":"Transportation"
        }
    ],
    "sg:phone":"+44 1592 882306",
    "sg:postcode":"KY5 0XA",
    "sg:province":"Fife",
    "sg:tags":[
        "hire",
        "coach"
    ],
    "wof:name":"Reekie of Kinglassie Co. Ltd.",
    "wof:placetype":"venue"
},
  "geometry": {"coordinates":[-3.264387,56.147545],"type":"Point"}
}