{
  "type": "Feature",
  "properties": {
    "addr:full":"Burwash Road, Broad Oak Heathfield East Sussex TN21 8XG",
    "addr:postcode":"tn21 8xg",
    "addr:street":"Burwash Road",
    "iso:country":"GB",
    "sg:address":"Burwash Road, Broad Oak",
    "sg:city":"Heathfield",
    "sg:classifiers":[
        {
            "category":"Home & Garden",
            "subcategory":"Garden Supply",
            "type":"Retail Goods"
        }
    ],
    "sg:postcode":"TN21 8XG",
    "sg:province":"East Sussex",
    "sg:tags":[
        "nursery",
        "centre"
    ],
    "wof:name":"Garlands Garden Centre & Nursery",
    "wof:placetype":"venue"
},
  "geometry": {"coordinates":[0.252349,50.971859],"type":"Point"}
}