{
  "type": "Feature",
  "properties": {
    "iso:country":"GB",
    "sg:address":"513 Foleshill Road",
    "sg:city":"Coventry",
    "sg:classifiers":[
        {
            "category":"Fast Food",
            "type":"Food & Drink"
        }
    ],
    "sg:phone":"+44 24 7663 8828",
    "sg:postcode":"CV6 5AU",
    "sg:province":"Warwickshire",
    "sg:tags":[
        "away",
        "meal",
        "outlet",
        "take"
    ],
    "wof:name":"S & H Morjaria",
    "wof:placetype":"venue"
},
  "geometry": {"coordinates":[-1.4995,52.428577],"type":"Point"}
}