{
  "type": "Feature",
  "properties": {
    "addr:full":"8 The Rosary, Wootton Bassett Swindon Wiltshire SN4 8AF",
    "addr:housenumber":"8",
    "addr:postcode":"sn4 8af",
    "addr:street":"The",
    "iso:country":"GB",
    "sg:address":"8 The Rosary, Wootton Bassett",
    "sg:city":"Swindon",
    "sg:classifiers":[
        {
            "category":"Arts & Performance",
            "subcategory":"Music",
            "type":"Entertainment"
        }
    ],
    "sg:postcode":"SN4 8AF",
    "sg:province":"Wiltshire",
    "sg:tags":[
        "mobile",
        "disco"
    ],
    "wof:name":"Celebration Roadshow",
    "wof:placetype":"venue"
},
  "geometry": {"coordinates":[-1.898703,51.542603],"type":"Point"}
}