{
  "type": "Feature",
  "properties": {
    "iso:country":"GB",
    "sg:address":"91-93 Main Street",
    "sg:city":"Alford",
    "sg:classifiers":[
        {
            "category":"Retail",
            "subcategory":"Auto Rental",
            "type":"Services"
        }
    ],
    "sg:phone":"+44 1975 563600",
    "sg:postcode":"AB33 8AD",
    "sg:province":"Aberdeenshire",
    "sg:tags":[
        "truck",
        "hire",
        "van"
    ],
    "wof:name":"PRACTICAL CAR & VAN RENTAL LTD",
    "wof:placetype":"venue"
},
  "geometry": {"coordinates":[-2.693731,57.230907],"type":"Point"}
}