{
  "type": "Feature",
  "properties": {
    "addr:full":"143 Cherrywood Rd, Bordesley Green Birmingham West Midlands B9 4XE",
    "addr:housenumber":"143",
    "addr:postcode":"b9 4xe",
    "addr:street":"Cherrywood Rd",
    "iso:country":"GB",
    "sg:address":"143 Cherrywood Rd, Bordesley Green",
    "sg:city":"Birmingham",
    "sg:classifiers":[
        {
            "category":"Professional",
            "subcategory":"Engineering",
            "type":"Services"
        }
    ],
    "sg:postcode":"B9 4XE",
    "sg:province":"West Midlands",
    "sg:tags":[
        "civil",
        "engineer"
    ],
    "wof:name":"Seahurst",
    "wof:placetype":"venue"
},
  "geometry": {"coordinates":[-1.853129,52.479439],"type":"Point"}
}