{
  "type": "Feature",
  "properties": {
    "addr:full":"323 Clarkston Road Glasgow East Renfrewshire G44 3EJ",
    "addr:housenumber":"323",
    "addr:postcode":"g44 3ej",
    "addr:street":"Clarkston Road",
    "iso:country":"GB",
    "sg:address":"323 Clarkston Road",
    "sg:city":"Glasgow",
    "sg:classifiers":[
        {
            "category":"Food & Beverages",
            "subcategory":"Bakery",
            "type":"Retail Goods"
        }
    ],
    "sg:phone":"+44 141 637 3432",
    "sg:postcode":"G44 3EJ",
    "sg:province":"East Renfrewshire",
    "sg:tags":[
        "shop",
        "baker"
    ],
    "wof:name":"Newlands Home Bakery",
    "wof:placetype":"venue"
},
  "geometry": {"coordinates":[-4.2688360214,55.8125648499],"type":"Point"}
}