{
  "type": "Feature",
  "properties": {
    "addr:full":"School Lane, St Johns Crowborough East Sussex TN6 1SE",
    "addr:postcode":"tn6 1se",
    "addr:street":"School Lane St",
    "iso:country":"GB",
    "sg:address":"School Lane, St Johns",
    "sg:city":"Crowborough",
    "sg:classifiers":[
        {
            "category":"Retail",
            "subcategory":"Auto Repair",
            "type":"Services"
        }
    ],
    "sg:phone":"+44 1892 653519",
    "sg:postcode":"TN6 1SE",
    "sg:province":"East Sussex",
    "sg:tags":[
        "modification",
        "garage"
    ],
    "wof:name":"Cares Garage",
    "wof:placetype":"venue"
},
  "geometry": {"coordinates":[0.1467230022,51.0663452148],"type":"Point"}
}