{
  "type": "Feature",
  "properties": {
    "addr:full":"Unit 11 Sheoden Business Centre, Marytime Close, Midway City Estate Rochester Kent ME2 4AF",
    "addr:housenumber":"unit 11",
    "addr:postcode":"me2 4af",
    "addr:street":"Sheoden Business Centre Marytime Close;City",
    "iso:country":"GB",
    "sg:address":"Unit 11 Sheoden Business Centre, Marytime Close, Midway City Estate",
    "sg:city":"Rochester",
    "sg:classifiers":[
        {
            "category":"Building & Trades",
            "subcategory":"Construction",
            "type":"Services"
        }
    ],
    "sg:phone":"+44 1634 573355",
    "sg:postcode":"ME2 4AF",
    "sg:province":"Kent",
    "sg:tags":[
        "heating",
        "contractor"
    ],
    "wof:name":"Ward Electrical Insulation",
    "wof:placetype":"venue"
},
  "geometry": {"coordinates":[0.4887830019,51.3963699341],"type":"Point"}
}