{
  "type": "Feature",
  "properties": {
    "addr:full":"12 Senna Lane Northwich Cheshire CW9 6BQ",
    "addr:housenumber":"12",
    "addr:postcode":"cw9 6bq",
    "addr:street":"Senna Lane",
    "iso:country":"GB",
    "sg:address":"12 Senna Lane",
    "sg:city":"Northwich",
    "sg:classifiers":[
        {
            "category":"Shopping",
            "subcategory":"Department Store",
            "type":"Retail Goods"
        }
    ],
    "sg:phone":"+44 1606 891429",
    "sg:postcode":"CW9 6BQ",
    "sg:province":"Cheshire",
    "wof:name":"Comberbach Post Office",
    "wof:placetype":"venue"
},
  "geometry": {"coordinates":[-2.535973,53.292744],"type":"Point"}
}