{
  "type": "Feature",
  "properties": {
    "iso:country":"GB",
    "sg:address":"5 Broad Street",
    "sg:city":"Denny",
    "sg:classifiers":[
        {
            "category":"Home & Garden",
            "subcategory":"Hardware",
            "type":"Retail Goods"
        }
    ],
    "sg:phone":"+44 1324 822879",
    "sg:postcode":"FK6 6DX",
    "sg:province":"Falkirk",
    "sg:tags":[
        "merchant",
        "retailer",
        "ironmonger",
        "diy"
    ],
    "wof:name":"William Bulloch",
    "wof:placetype":"venue"
},
  "geometry": {"coordinates":[-3.907145,56.023056],"type":"Point"}
}