{
  "type": "Feature",
  "properties": {
    "iso:country":"GB",
    "sg:address":"30 Loughborough Road, West Bridgford",
    "sg:city":"Nottingham",
    "sg:classifiers":[
        {
            "category":"Health Services",
            "subcategory":"Dentist",
            "type":"Services"
        }
    ],
    "sg:phone":"+44 115 981 9396",
    "sg:postcode":"NG2 7JJ",
    "sg:province":"Nottinghamshire",
    "wof:name":"MATTHEW BURTON",
    "wof:placetype":"venue"
},
  "geometry": {"coordinates":[-1.1373519897,52.9317779541],"type":"Point"}
}