{
  "type": "Feature",
  "properties": {
    "addr:full":"Manor Farm, Nobut Road, Leigh Stoke-on-trent Staffordshire ST10 4QG",
    "addr:postcode":"st10 4qg",
    "addr:street":"Manor;Nobut Road",
    "iso:country":"GB",
    "sg:address":"Manor Farm, Nobut Road, Leigh",
    "sg:city":"Stoke-on-trent",
    "sg:classifiers":[
        {
            "category":"Farming",
            "subcategory":"Livestock Farm",
            "type":"Manufacturing & Wholesale Goods"
        }
    ],
    "sg:postcode":"ST10 4QG",
    "sg:province":"Staffordshire",
    "sg:tags":[
        "others"
    ],
    "wof:name":"D A & M A Whitehurst",
    "wof:placetype":"venue"
},
  "geometry": {"coordinates":[-1.9781659842,52.9226493835],"type":"Point"}
}