{
  "type": "Feature",
  "properties": {
    "addr:full":"Chelsea Lane, West High Street Inverurie Aberdeenshire AB51 3QQ",
    "addr:postcode":"ab51 3qq",
    "addr:street":"Chelsea Lane West High Street",
    "iso:country":"GB",
    "sg:address":"Chelsea Lane, West High Street",
    "sg:city":"Inverurie",
    "sg:classifiers":[
        {
            "category":"Professional",
            "subcategory":"Management & Consulting",
            "type":"Services"
        },
        {
            "category":"Personal",
            "type":"Services"
        }
    ],
    "sg:phone":"+44 1467 624888",
    "sg:postcode":"AB51 3QQ",
    "sg:province":"Aberdeenshire",
    "sg:tags":[
        "consultant",
        "beauty",
        "specialist"
    ],
    "wof:name":"K Scott",
    "wof:placetype":"venue"
},
  "geometry": {"coordinates":[-2.3769040108,57.2842750549],"type":"Point"}
}