{
  "type": "Feature",
  "properties": {
    "iso:country":"GB",
    "sg:address":"2 Birch Way",
    "sg:city":"Poulton-le-fylde",
    "sg:classifiers":[
        {
            "category":"Retail",
            "subcategory":"Funeral Services",
            "type":"Services"
        }
    ],
    "sg:phone":"+44 1253 899845",
    "sg:postcode":"FY6 7SF",
    "sg:province":"Lancashire",
    "sg:tags":[
        "director",
        "cemetery",
        "crematorium"
    ],
    "wof:name":"C T Hull Funeral Directors",
    "wof:placetype":"venue"
},
  "geometry": {"coordinates":[-2.997737,53.847916],"type":"Point"}
}