{
  "type": "Feature",
  "properties": {
    "iso:country":"GB",
    "sg:address":"14 Bogie Street",
    "sg:city":"Huntly",
    "sg:classifiers":[
        {
            "category":"Food & Beverages",
            "subcategory":"Groceries & Convenience Stores",
            "type":"Retail Goods"
        }
    ],
    "sg:phone":"+44 1466 792772",
    "sg:postcode":"AB54 8DX",
    "sg:province":"Aberdeenshire",
    "wof:name":"G & D Anderson",
    "wof:placetype":"venue"
},
  "geometry": {"coordinates":[-2.7812619209,57.4466667175],"type":"Point"}
}