{
  "type": "Feature",
  "properties": {
    "addr:full":"Above Burtons, 314 Station Road Harrow Greater London HA1 2DX",
    "addr:housenumber":"314",
    "addr:postcode":"ha1 2dx",
    "addr:street":"Station Road",
    "iso:country":"GB",
    "sg:address":"Above Burtons, 314 Station Road",
    "sg:city":"Harrow",
    "sg:classifiers":[
        {
            "category":"Education",
            "subcategory":"Dance Studio",
            "type":"Public Place"
        }
    ],
    "sg:postcode":"HA1 2DX",
    "sg:province":"Greater London",
    "sg:tags":[
        "school",
        "dancing"
    ],
    "wof:name":"Harrow Regal Dance Centre",
    "wof:placetype":"venue"
},
  "geometry": {"coordinates":[-0.3360820115,51.5787849426],"type":"Point"}
}