{
  "type": "Feature",
  "properties": {
    "addr:full":"1 Moss House, Moss Lane Altrincham Cheshire WA14 1BA",
    "addr:housenumber":"1",
    "addr:postcode":"wa14 1ba",
    "addr:street":"Moss House Moss Lane",
    "iso:country":"GB",
    "sg:address":"1 Moss House, Moss Lane",
    "sg:city":"Altrincham",
    "sg:classifiers":[
        {
            "category":"Professional",
            "subcategory":"Lawyer & Legal Services",
            "type":"Services"
        }
    ],
    "sg:phone":"+44 161 929 7494",
    "sg:postcode":"WA14 1BA",
    "sg:province":"Cheshire",
    "sg:tags":[
        "solicitor"
    ],
    "wof:name":"Maidments Solicitors",
    "wof:placetype":"venue"
},
  "geometry": {"coordinates":[-2.3492090702,53.3867263794],"type":"Point"}
}