{
  "type": "Feature",
  "properties": {
    "iso:country":"GB",
    "sg:address":"Stones Courtyard, High Street",
    "sg:city":"Chesham",
    "sg:classifiers":[
        {
            "category":"Real Estate",
            "subcategory":"Surveying",
            "type":"Services"
        }
    ],
    "sg:phone":"+44 1494 791869",
    "sg:postcode":"HP5 1DE",
    "sg:province":"Buckinghamshire",
    "sg:tags":[
        "building",
        "surveyor"
    ],
    "wof:name":"Thomas D M C",
    "wof:placetype":"venue"
},
  "geometry": {"coordinates":[-0.609333,51.710537],"type":"Point"}
}