{
  "type": "Feature",
  "properties": {
    "iso:country":"GB",
    "sg:address":"76 Millbank Court, John Islip Street",
    "sg:city":"London",
    "sg:classifiers":[
        {
            "category":"Professional",
            "subcategory":"Management & Consulting",
            "type":"Services"
        }
    ],
    "sg:phone":"+44 20 7828 4886",
    "sg:postcode":"SW1P 4LG",
    "sg:province":"Greater London",
    "sg:tags":[
        "marketing",
        "consultant"
    ],
    "wof:name":"John Spencer Associates",
    "wof:placetype":"venue"
},
  "geometry": {"coordinates":[-0.127599,51.492935],"type":"Point"}
}