{
  "type": "Feature",
  "properties": {
    "addr:full":"11-12 The Centre, Rawtenstall Rossendale Lancashire BB4 7QG",
    "addr:housenumber":"11-12",
    "addr:postcode":"bb4 7qg",
    "addr:street":"The Centre Rawtenstall",
    "iso:country":"GB",
    "sg:address":"11-12 The Centre, Rawtenstall",
    "sg:city":"Rossendale",
    "sg:classifiers":[
        {
            "category":"Food & Beverages",
            "subcategory":"Candy",
            "type":"Retail Goods"
        }
    ],
    "sg:postcode":"BB4 7QG",
    "sg:province":"Lancashire",
    "sg:tags":[
        "confectioner"
    ],
    "wof:name":"David Laithwate",
    "wof:placetype":"venue"
},
  "geometry": {"coordinates":[-2.2798690796,53.7003707886],"type":"Point"}
}