{
  "type": "Feature",
  "properties": {
    "addr:full":"14 Fletcher Gate Nottingham Nottinghamshire NG1 2FS",
    "addr:housenumber":"14",
    "addr:postcode":"ng1 2fs",
    "addr:street":"Fletcher Gate",
    "iso:country":"GB",
    "sg:address":"14 Fletcher Gate",
    "sg:city":"Nottingham",
    "sg:classifiers":[
        {
            "category":"Professional",
            "subcategory":"Lawyer & Legal Services",
            "type":"Services"
        }
    ],
    "sg:phone":"+44 115 936 6000",
    "sg:postcode":"NG1 2FS",
    "sg:province":"Nottinghamshire",
    "sg:tags":[
        "solicitor"
    ],
    "wof:name":"Eversheds",
    "wof:placetype":"venue"
},
  "geometry": {"coordinates":[-1.145845,52.952801],"type":"Point"}
}