{
  "type": "Feature",
  "properties": {
    "addr:full":"28 Bolney Avenue Peacehaven East Sussex BN10 8NA",
    "addr:housenumber":"28",
    "addr:postcode":"bn10 8na",
    "addr:street":"Bolney Avenue Peacehaven",
    "iso:country":"GB",
    "sg:address":"28 Bolney Avenue",
    "sg:city":"Peacehaven",
    "sg:classifiers":[
        {
            "category":"Professional",
            "subcategory":"Computer Services",
            "type":"Services"
        }
    ],
    "sg:phone":"+44 1273 583304",
    "sg:postcode":"BN10 8NA",
    "sg:province":"East Sussex",
    "sg:tags":[
        "consultant"
    ],
    "wof:name":"Crombie Computer Consultants",
    "wof:placetype":"venue"
},
  "geometry": {"coordinates":[0.0048989998,50.7911872864],"type":"Point"}
}