{
  "type": "Feature",
  "properties": {
    "addr:full":"Pride Hill Centre Shrewsbury Shropshire SY1 1BU",
    "addr:postcode":"sy1 1bu",
    "addr:street":"Pride Hill Centre",
    "iso:country":"GB",
    "sg:address":"Pride Hill Centre",
    "sg:city":"Shrewsbury",
    "sg:classifiers":[
        {
            "category":"Shopping",
            "subcategory":"Luggage & Leather Goods",
            "type":"Retail Goods"
        }
    ],
    "sg:postcode":"SY1 1BU",
    "sg:province":"Shropshire",
    "sg:tags":[
        "shop",
        "leathergoods"
    ],
    "wof:name":"Akhtar,Toni,",
    "wof:placetype":"venue"
},
  "geometry": {"coordinates":[-2.752894,52.70882],"type":"Point"}
}