{
  "type": "Feature",
  "properties": {
    "iso:country":"GB",
    "sg:address":"Imperial House, St Nicholas Circle",
    "sg:city":"Leicester",
    "sg:classifiers":[
        {
            "category":"Education",
            "subcategory":"Special Training",
            "type":"Public Place"
        }
    ],
    "sg:phone":"+44 116 223 9666",
    "sg:postcode":"LE1 4LF",
    "sg:province":"Leicestershire",
    "sg:tags":[
        "product",
        "centre"
    ],
    "wof:name":"Pitman Training Centre",
    "wof:placetype":"venue"
},
  "geometry": {"coordinates":[-1.141229,52.634556],"type":"Point"}
}