{
  "type": "Feature",
  "properties": {
    "addr:full":"380-382 Bethnal Green Road London Greater London E2 0AH",
    "addr:housenumber":"380-382",
    "addr:postcode":"e2 0ah",
    "addr:street":"Bethnal Green Road",
    "iso:country":"GB",
    "sg:address":"380-382 Bethnal Green Road",
    "sg:city":"London",
    "sg:classifiers":[
        {
            "category":"Home & Garden",
            "subcategory":"Household Appliances",
            "type":"Retail Goods"
        }
    ],
    "sg:phone":"+44 20 7739 3577",
    "sg:postcode":"E2 0AH",
    "sg:province":"Greater London",
    "sg:tags":[
        "electrical",
        "domestic"
    ],
    "wof:name":"Tempo",
    "wof:placetype":"venue"
},
  "geometry": {"coordinates":[-0.0615990013,51.5267372131],"type":"Point"}
}