{
  "type": "Feature",
  "properties": {
    "addr:full":"7 Dale Road Dunstable Bedfordshire LU5 4PY",
    "addr:housenumber":"7",
    "addr:postcode":"lu5 4py",
    "addr:street":"Dale Road",
    "iso:country":"GB",
    "sg:address":"7 Dale Road",
    "sg:city":"Dunstable",
    "sg:classifiers":[
        {
            "category":"Building & Trades",
            "subcategory":"Construction",
            "type":"Services"
        }
    ],
    "sg:postcode":"LU5 4PY",
    "sg:province":"Bedfordshire",
    "sg:tags":[
        "decorator",
        "painter"
    ],
    "wof:name":"Russell Perry",
    "wof:placetype":"venue"
},
  "geometry": {"coordinates":[-0.4937570095,51.8890304565],"type":"Point"}
}