{
  "type": "Feature",
  "properties": {
    "addr:full":"Gwynfryn Terr, Cynheidre Llanelli Carmarthenshire SA15 5YF",
    "addr:postcode":"sa15 5yf",
    "addr:street":"Gwynfryn Terr",
    "iso:country":"GB",
    "sg:address":"Gwynfryn Terr, Cynheidre",
    "sg:city":"Llanelli",
    "sg:classifiers":[
        {
            "category":"Sports & Exercise",
            "subcategory":"Tennis Court",
            "type":"Entertainment"
        }
    ],
    "sg:postcode":"SA15 5YF",
    "sg:province":"Carmarthenshire",
    "sg:tags":[
        "breakdown",
        "recovery"
    ],
    "wof:name":"Gladwyn,Steven,",
    "wof:placetype":"venue"
},
  "geometry": {"coordinates":[-4.188169,51.744499],"type":"Point"}
}