{
  "type": "Feature",
  "properties": {
    "iso:country":"GB",
    "sg:address":"Douglasfield, Douglas Rd",
    "sg:city":"Dundee",
    "sg:classifiers":[
        {
            "category":"Organizations",
            "subcategory":"Political Organization",
            "type":"Services"
        }
    ],
    "sg:phone":"+44 1382 508090",
    "sg:postcode":"DD4 7SN",
    "sg:province":"Dundee City",
    "sg:tags":[
        "promoter",
        "pool"
    ],
    "wof:name":"Mecca",
    "wof:placetype":"venue"
},
  "geometry": {"coordinates":[-2.92227,56.476311],"type":"Point"}
}