{
  "type": "Feature",
  "properties": {
    "iso:country":"GB",
    "sg:address":"365 High Street",
    "sg:city":"Cheltenham",
    "sg:classifiers":[
        {
            "category":"Insurance",
            "subcategory":"Insurance Agent",
            "type":"Services"
        }
    ],
    "sg:phone":"+44 1242 516558",
    "sg:postcode":"GL50 3HT",
    "sg:province":"Gloucestershire",
    "wof:name":"Mark Richard (Brokers) Ltd.",
    "wof:placetype":"venue"
},
  "geometry": {"coordinates":[-2.081193,51.904041],"type":"Point"}
}