{
  "type": "Feature",
  "properties": {
    "addr:full":"5 Prospect Road Broadstairs Kent CT10 1LD",
    "addr:housenumber":"5",
    "addr:postcode":"ct10 1ld",
    "addr:street":"Prospect Road",
    "iso:country":"GB",
    "sg:address":"5 Prospect Road",
    "sg:city":"Broadstairs",
    "sg:classifiers":[
        {
            "category":"Professional",
            "subcategory":"Engineering",
            "type":"Services"
        },
        {
            "category":"Building & Trades",
            "subcategory":"Electrical",
            "type":"Services"
        }
    ],
    "sg:phone":"+44 1843 861580",
    "sg:postcode":"CT10 1LD",
    "sg:province":"Kent",
    "sg:tags":[
        "engineer",
        "electrician",
        "contractor"
    ],
    "wof:name":"HARRY ERNEST ATHERTON",
    "wof:placetype":"venue"
},
  "geometry": {"coordinates":[1.440985,51.359531],"type":"Point"}
}