{
  "type": "Feature",
  "properties": {
    "addr:full":"3a Harrington Rd South Kensington Greater London SW7 3ES",
    "addr:housenumber":"3a",
    "addr:postcode":"sw7 3es",
    "addr:street":"Harrington Rd",
    "iso:country":"GB",
    "sg:address":"3a Harrington Rd",
    "sg:city":"South Kensington",
    "sg:classifiers":[
        {
            "category":"Health Services",
            "subcategory":"Dentist",
            "type":"Services"
        }
    ],
    "sg:phone":"+44 20 7589 2637",
    "sg:postcode":"SW7 3ES",
    "sg:province":"Greater London",
    "wof:name":"John Smith B.D.S M.Sc.",
    "wof:placetype":"venue"
},
  "geometry": {"coordinates":[-0.176279,51.494068],"type":"Point"}
}