{
  "type": "Feature",
  "properties": {
    "addr:full":"51 Derby Rd Nottingham Nottinghamshire NG17 9DH",
    "addr:housenumber":"51",
    "addr:postcode":"ng17 9dh",
    "addr:street":"Derby Rd",
    "iso:country":"GB",
    "sg:address":"51 Derby Rd",
    "sg:city":"Nottingham",
    "sg:classifiers":[
        {
            "category":"Building & Trades",
            "subcategory":"Construction",
            "type":"Services"
        }
    ],
    "sg:phone":"+44 1623 753570",
    "sg:postcode":"NG17 9DH",
    "sg:province":"Nottinghamshire",
    "sg:tags":[
        "decorator",
        "painter"
    ],
    "wof:name":"Colin B Sewell",
    "wof:placetype":"venue"
},
  "geometry": {"coordinates":[-1.242099,53.082447],"type":"Point"}
}