{
  "type": "Feature",
  "properties": {
    "iso:country":"GB",
    "sg:address":"Baughurst Road, Baughurst",
    "sg:city":"Tadley",
    "sg:classifiers":[
        {
            "category":"Bars & Pubs",
            "type":"Food & Drink"
        },
        {
            "category":"Community Center",
            "subcategory":"Social",
            "type":"Public Place"
        }
    ],
    "sg:phone":"+44 118 981 4330",
    "sg:postcode":"RG26 5LP",
    "sg:province":"Berkshire",
    "sg:tags":[
        "pubs",
        "house",
        "inn",
        "activity"
    ],
    "wof:name":"The Wellington Arms",
    "wof:placetype":"venue"
},
  "geometry": {"coordinates":[-1.168584,51.352604],"type":"Point"}
}