{
  "type": "Feature",
  "properties": {
    "iso:country":"GB",
    "sg:address":"Poplar Farm, Sheepy Road, Sibson",
    "sg:city":"Nuneaton",
    "sg:classifiers":[
        {
            "category":"Farming",
            "subcategory":"Livestock Farm",
            "type":"Manufacturing & Wholesale Goods"
        }
    ],
    "sg:phone":"+44 1827 880263",
    "sg:postcode":"CV13 6LE",
    "sg:province":"Leicestershire",
    "sg:tags":[
        "others"
    ],
    "wof:name":"E W Blood & Sons Ltd",
    "wof:placetype":"venue"
},
  "geometry": {"coordinates":[-1.476838,52.604633],"type":"Point"}
}