{
  "type": "Feature",
  "properties": {
    "addr:full":"Unit 26 Whitworth Industrial Estate Birmingham West Midlands B9 4PP",
    "addr:housenumber":"unit 26",
    "addr:postcode":"b9 4pp",
    "addr:street":"Industrial Estate",
    "iso:country":"GB",
    "sg:address":"Unit 26 Whitworth Industrial Estate",
    "sg:city":"Birmingham",
    "sg:classifiers":[
        {
            "category":"Building & Trades",
            "subcategory":"Construction",
            "type":"Services"
        }
    ],
    "sg:phone":"+44 121 753 1647",
    "sg:postcode":"B9 4PP",
    "sg:province":"West Midlands",
    "sg:tags":[
        "heating",
        "contractor"
    ],
    "wof:name":"Comstead Ltd.",
    "wof:placetype":"venue"
},
  "geometry": {"coordinates":[-1.8567169905,52.4807395935],"type":"Point"}
}