{
  "type": "Feature",
  "properties": {
    "iso:country":"GB",
    "sg:address":"Eddington Lane",
    "sg:city":"Herne Bay",
    "sg:classifiers":[
        {
            "category":"Manufacturing",
            "subcategory":"Building Materials",
            "type":"Manufacturing & Wholesale Goods"
        }
    ],
    "sg:phone":"+44 1227 366633",
    "sg:postcode":"CT6 5TX",
    "sg:province":"Kent",
    "sg:tags":[
        "merchant",
        "builder"
    ],
    "wof:name":"Wacher & Co. Ltd.",
    "wof:placetype":"venue"
},
  "geometry": {"coordinates":[1.1251,51.371216],"type":"Point"}
}