{
  "type": "Feature",
  "properties": {
    "iso:country":"GB",
    "sg:address":"26 Easton Square",
    "sg:city":"Portland",
    "sg:classifiers":[
        {
            "category":"Retail",
            "subcategory":"Auto Repair",
            "type":"Services"
        }
    ],
    "sg:phone":"+44 1305 820259",
    "sg:postcode":"DT5 1BX",
    "sg:province":"Dorset",
    "sg:tags":[
        "modification",
        "garage",
        "related"
    ],
    "wof:name":"Easton Motor Services",
    "wof:placetype":"venue"
},
  "geometry": {"coordinates":[-2.437099,50.545506],"type":"Point"}
}