{
  "type": "Feature",
  "properties": {
    "iso:country":"GB",
    "sg:address":"9 Fairley Street",
    "sg:city":"Glasgow",
    "sg:classifiers":[
        {
            "category":"Shopping",
            "subcategory":"Bicycles & Sporting Goods",
            "type":"Retail Goods"
        }
    ],
    "sg:phone":"+44 141 427 3175",
    "sg:postcode":"G51 2SN",
    "sg:province":"Glasgow City",
    "sg:tags":[
        "water",
        "cooler"
    ],
    "wof:name":"H2O",
    "wof:placetype":"venue"
},
  "geometry": {"coordinates":[-4.301491,55.852932],"type":"Point"}
}