{
  "type": "Feature",
  "properties": {
    "addr:full":"Unit 2a Hampton Heath Indstl Est Malpas Cheshire SY14 8LU",
    "addr:housenumber":"unit 2a",
    "addr:postcode":"sy14 8lu",
    "addr:street":"Hampton Heath Indstl Est",
    "iso:country":"GB",
    "sg:address":"Unit 2a Hampton Heath Indstl Est",
    "sg:city":"Malpas",
    "sg:classifiers":[
        {
            "category":"Manufacturing",
            "subcategory":"Chemicals & Compounds",
            "type":"Manufacturing & Wholesale Goods"
        }
    ],
    "sg:postcode":"SY14 8LU",
    "sg:province":"Cheshire",
    "sg:tags":[
        "pesticide"
    ],
    "wof:name":"Penta Chemicals Ltd",
    "wof:placetype":"venue"
},
  "geometry": {"coordinates":[-2.728428,53.02692],"type":"Point"}
}