{
  "type": "Feature",
  "properties": {
    "addr:full":"50 York St Bedford Bedfordshire MK40 3RJ",
    "addr:housenumber":"50",
    "addr:postcode":"mk40 3rj",
    "addr:street":"York St",
    "iso:country":"GB",
    "sg:address":"50 York St",
    "sg:city":"Bedford",
    "sg:classifiers":[
        {
            "category":"Sports & Exercise",
            "subcategory":"Playing Field",
            "type":"Entertainment"
        }
    ],
    "sg:phone":"+44 1234 352232",
    "sg:postcode":"MK40 3RJ",
    "sg:province":"Bedfordshire",
    "sg:tags":[
        "ticket",
        "agency",
        "airline"
    ],
    "wof:name":"African Freight & Travel Times",
    "wof:placetype":"venue"
},
  "geometry": {"coordinates":[-0.4520449936,52.1369590759],"type":"Point"}
}