{
  "type": "Feature",
  "properties": {
    "iso:country":"GB",
    "sg:address":"The Old Smithy, Ecclesgrieg St Syrus",
    "sg:city":"Montrose",
    "sg:classifiers":[
        {
            "category":"Communications",
            "type":"Services"
        }
    ],
    "sg:postcode":"DD10 0DR",
    "sg:province":"Aberdeenshire",
    "sg:tags":[
        "audio-visual"
    ],
    "wof:name":"Eyeline Video Productions",
    "wof:placetype":"venue"
},
  "geometry": {"coordinates":[-2.44561,56.78223],"type":"Point"}
}