{
  "type": "Feature",
  "properties": {
    "iso:country":"GB",
    "sg:address":"106 High St, Gorleston",
    "sg:city":"Great Yarmouth",
    "sg:classifiers":[
        {
            "category":"Shopping",
            "subcategory":"Department Store",
            "type":"Retail Goods"
        }
    ],
    "sg:postcode":"NR31 6RF",
    "sg:province":"Norfolk",
    "wof:name":"Platford,Greg J,",
    "wof:placetype":"venue"
},
  "geometry": {"coordinates":[1.728144,52.579159],"type":"Point"}
}