{
  "type": "Feature",
  "properties": {
    "addr:full":"Boat Market, Mill Hill Lostwithiel Cornwall PL22 0HB",
    "addr:postcode":"pl22 0hb",
    "addr:street":"Mill Hill",
    "iso:country":"GB",
    "sg:address":"Boat Market, Mill Hill",
    "sg:city":"Lostwithiel",
    "sg:classifiers":[
        {
            "category":"Train Station",
            "subcategory":"Rail",
            "type":"Transportation"
        }
    ],
    "sg:phone":"+44 1208 873034",
    "sg:postcode":"PL22 0HB",
    "sg:province":"Cornwall",
    "sg:tags":[
        "caravan"
    ],
    "wof:name":"Castle Caravans",
    "wof:placetype":"venue"
},
  "geometry": {"coordinates":[-4.669903,50.408272],"type":"Point"}
}