{
  "type": "Feature",
  "properties": {
    "iso:country":"GB",
    "sg:address":"Chesil House, Shakespeare Road",
    "sg:city":"Eastleigh",
    "sg:classifiers":[
        {
            "category":"Professional",
            "subcategory":"Computer Services",
            "type":"Services"
        }
    ],
    "sg:postcode":"SO50 4SY",
    "sg:province":"Hampshire",
    "sg:tags":[
        "consultant"
    ],
    "wof:name":"Rex Software Ltd.",
    "wof:placetype":"venue"
},
  "geometry": {"coordinates":[-1.3585879803,50.9769477844],"type":"Point"}
}