{
  "type": "Feature",
  "properties": {
    "iso:country":"GB",
    "sg:address":"347 Walmersley Rd",
    "sg:city":"Bury",
    "sg:classifiers":[
        {
            "category":"Food & Beverages",
            "subcategory":"Supermarket",
            "type":"Retail Goods"
        }
    ],
    "sg:postcode":"BL9 5EZ",
    "sg:province":"Lancashire",
    "wof:name":"Hodgkinson,Dave,",
    "wof:placetype":"venue"
},
  "geometry": {"coordinates":[-2.292596,53.60994],"type":"Point"}
}