{
  "type": "Feature",
  "properties": {
    "iso:country":"GB",
    "sg:address":"86 West Street, Oundle",
    "sg:city":"Peterborough",
    "sg:classifiers":[
        {
            "category":"Shopping",
            "subcategory":"Discount & Variety Stores",
            "type":"Retail Goods"
        }
    ],
    "sg:phone":"+44 1832 273866",
    "sg:postcode":"PE8 4EF",
    "sg:province":"Cambridgeshire",
    "sg:tags":[
        "shop",
        "model"
    ],
    "wof:name":"Geoffrey Stubs Model Shop",
    "wof:placetype":"venue"
},
  "geometry": {"coordinates":[-0.473683,52.48082],"type":"Point"}
}