{
  "type": "Feature",
  "properties": {
    "addr:full":"The Firs Bungalow, Bromyard Road, Sutton Tenbury Wells Herefordshire WR15 8RH",
    "addr:postcode":"wr15 8rh",
    "addr:street":"Bromyard Road",
    "iso:country":"GB",
    "sg:address":"The Firs Bungalow, Bromyard Road, Sutton",
    "sg:city":"Tenbury Wells",
    "sg:classifiers":[
        {
            "category":"Farming",
            "subcategory":"Livestock Farm",
            "type":"Manufacturing & Wholesale Goods"
        }
    ],
    "sg:postcode":"WR15 8RH",
    "sg:province":"Herefordshire",
    "sg:tags":[
        "others"
    ],
    "wof:name":"E Turner",
    "wof:placetype":"venue"
},
  "geometry": {"coordinates":[-2.594179,52.312584],"type":"Point"}
}