{
  "type": "Feature",
  "properties": {
    "addr:full":"5 Southampton Place London Greater London WC1A 2DA",
    "addr:housenumber":"5",
    "addr:postcode":"wc1a 2da",
    "addr:street":"Southampton Place",
    "iso:country":"GB",
    "sg:address":"5 Southampton Place",
    "sg:city":"London",
    "sg:classifiers":[
        {
            "category":"Shopping",
            "subcategory":"Shoes",
            "type":"Retail Goods"
        }
    ],
    "sg:postcode":"WC1A 2DA",
    "sg:province":"Greater London",
    "sg:tags":[
        "shop"
    ],
    "wof:name":"Hexagone Ltd",
    "wof:placetype":"venue"
},
  "geometry": {"coordinates":[-0.1218559965,51.5181617737],"type":"Point"}
}