{
  "type": "Feature",
  "properties": {
    "addr:full":"5-15 Maney House, Maney Corner Sutton Coldfield West Midlands B72 1QL",
    "addr:housenumber":"5-15",
    "addr:postcode":"b72 1ql",
    "addr:street":"Maney House Maney Corner",
    "iso:country":"GB",
    "sg:address":"5-15 Maney House, Maney Corner",
    "sg:city":"Sutton Coldfield",
    "sg:classifiers":[
        {
            "category":"Restaurant",
            "type":"Food & Drink"
        }
    ],
    "sg:phone":"+44 121 321 2446",
    "sg:postcode":"B72 1QL",
    "sg:province":"West Midlands",
    "sg:tags":[
        "indian",
        "-"
    ],
    "wof:name":"Samoli Indian Cuisine",
    "wof:placetype":"venue"
},
  "geometry": {"coordinates":[-1.82624,52.5569],"type":"Point"}
}