{
  "type": "Feature",
  "properties": {
    "iso:country":"GB",
    "sg:address":"13 Broadwalk",
    "sg:city":"Dunstable",
    "sg:classifiers":[
        {
            "category":"Professional",
            "subcategory":"Art Services",
            "type":"Services"
        }
    ],
    "sg:phone":"+44 1582 471234",
    "sg:postcode":"LU5 4RH",
    "sg:province":"Bedfordshire",
    "sg:tags":[
        "photographer"
    ],
    "wof:name":"Amazon Commercial Studios Ltd.",
    "wof:placetype":"venue"
},
  "geometry": {"coordinates":[-0.509335,51.895012],"type":"Point"}
}