{
  "type": "Feature",
  "properties": {
    "iso:country":"GB",
    "sg:address":"1 Burned House Cottage, Bucklow Hill Lane",
    "sg:city":"Knutsford",
    "sg:classifiers":[
        {
            "category":"Retail",
            "subcategory":"Veterinary Services",
            "type":"Services"
        }
    ],
    "sg:postcode":"WA16 6LD",
    "sg:province":"Cheshire",
    "sg:tags":[
        "pharmacy"
    ],
    "wof:name":"Assisi Homoeopathic Veterinary Products",
    "wof:placetype":"venue"
},
  "geometry": {"coordinates":[-2.406396,53.344402],"type":"Point"}
}