{
  "type": "Feature",
  "properties": {
    "iso:country":"GB",
    "sg:address":"60 West St, Millbrook",
    "sg:city":"Torpoint",
    "sg:classifiers":[
        {
            "category":"Taxi",
            "type":"Transportation"
        }
    ],
    "sg:phone":"+44 1752 822333",
    "sg:postcode":"PL10 1AE",
    "sg:province":"Cornwall",
    "sg:tags":[
        "mini",
        "cab"
    ],
    "wof:name":"Coastline Cars",
    "wof:placetype":"venue"
},
  "geometry": {"coordinates":[-4.221049,50.346611],"type":"Point"}
}