{
  "type": "Feature",
  "properties": {
    "addr:full":"Jays Grn Harleston Norfolk IP20 9HH",
    "addr:postcode":"ip20 9hh",
    "addr:street":"Jays Grn Harleston",
    "iso:country":"GB",
    "sg:address":"Jays Grn",
    "sg:city":"Harleston",
    "sg:classifiers":[
        {
            "category":"Community Center",
            "subcategory":"Youth",
            "type":"Public Place"
        },
        {
            "category":"Government",
            "subcategory":"Office",
            "type":"Public Place"
        }
    ],
    "sg:phone":"+44 1379 852847",
    "sg:postcode":"IP20 9HH",
    "sg:province":"Norfolk",
    "sg:tags":[
        "organisation",
        "local",
        "centre"
    ],
    "wof:name":"Harlestone Youth & Community Centre",
    "wof:placetype":"venue"
},
  "geometry": {"coordinates":[1.3108149767,52.4035987854],"type":"Point"}
}