{
  "type": "Feature",
  "properties": {
    "addr:full":"302 Rempstone Road Wimborne Dorset BH21 1SZ",
    "addr:housenumber":"302",
    "addr:postcode":"bh21 1sz",
    "addr:street":"Rempstone Road",
    "iso:country":"GB",
    "sg:address":"302 Rempstone Road",
    "sg:city":"Wimborne",
    "sg:classifiers":[
        {
            "category":"Retail",
            "subcategory":"Driving School",
            "type":"Services"
        }
    ],
    "sg:postcode":"BH21 1SZ",
    "sg:province":"Dorset",
    "wof:name":"Heartfield School of Motoring",
    "wof:placetype":"venue"
},
  "geometry": {"coordinates":[-1.974609971,50.7785377502],"type":"Point"}
}