{
  "type": "Feature",
  "properties": {
    "addr:full":"89 Springfields Wigton Cumbria CA7 9JT",
    "addr:housenumber":"89",
    "addr:postcode":"ca7 9jt",
    "addr:street":"Springfields Wigton",
    "iso:country":"GB",
    "sg:address":"89 Springfields",
    "sg:city":"Wigton",
    "sg:classifiers":[
        {
            "category":"Manufacturing",
            "subcategory":"Building Materials",
            "type":"Manufacturing & Wholesale Goods"
        }
    ],
    "sg:phone":"+44 16973 44008",
    "sg:postcode":"CA7 9JT",
    "sg:province":"Cumbria",
    "sg:tags":[
        "shutter",
        "supp",
        "door"
    ],
    "wof:name":"Border Roller Doors",
    "wof:placetype":"venue"
},
  "geometry": {"coordinates":[-3.160777092,54.8167686462],"type":"Point"}
}