{
  "type": "Feature",
  "properties": {
    "addr:full":"50 West Harbour Road Edinburgh City of Edinburgh EH5 1PP",
    "addr:housenumber":"50",
    "addr:postcode":"eh5 1pp",
    "addr:street":"West Harbour Road",
    "iso:country":"GB",
    "sg:address":"50 West Harbour Road",
    "sg:city":"Edinburgh",
    "sg:classifiers":[
        {
            "category":"Retail",
            "subcategory":"Repair Shop",
            "type":"Services"
        }
    ],
    "sg:postcode":"EH5 1PP",
    "sg:province":"City of Edinburgh",
    "sg:tags":[
        "maintenance"
    ],
    "wof:name":"Newtown Construction (Scotland) Ltd.",
    "wof:placetype":"venue"
},
  "geometry": {"coordinates":[-3.2301280499,55.9823379517],"type":"Point"}
}