{
  "type": "Feature",
  "properties": {
    "addr:full":"Essex Ho, Stevenson Rd, Gorse Lane Indstl Est Clacton-on-sea Essex CO15 4XD",
    "addr:postcode":"co15 4xd",
    "addr:street":"Stevenson Rd Gorse Lane Indstl Est",
    "iso:country":"GB",
    "sg:address":"Essex Ho, Stevenson Rd, Gorse Lane Indstl Est",
    "sg:city":"Clacton-on-sea",
    "sg:classifiers":[
        {
            "category":"Home & Garden",
            "subcategory":"Household Appliances",
            "type":"Retail Goods"
        }
    ],
    "sg:phone":"+44 1255 474757",
    "sg:postcode":"CO15 4XD",
    "sg:province":"Essex",
    "sg:tags":[
        "refrigeration",
        "air conditioning"
    ],
    "wof:name":"E A C Planned Maintenance Ltd",
    "wof:placetype":"venue"
},
  "geometry": {"coordinates":[1.1728099585,51.8140411377],"type":"Point"}
}