{
  "type": "Feature",
  "properties": {
    "addr:full":"43 Maffey Court, Union Street Rugby Warwickshire CV22 6AW",
    "addr:housenumber":"43",
    "addr:postcode":"cv22 6aw",
    "addr:street":"Maffey Court Union Street",
    "iso:country":"GB",
    "sg:address":"43 Maffey Court, Union Street",
    "sg:city":"Rugby",
    "sg:classifiers":[
        {
            "category":"Health Services",
            "subcategory":"Nursing And Care Facility",
            "type":"Services"
        },
        {
            "category":"Organizations",
            "subcategory":"Community Association",
            "type":"Services"
        }
    ],
    "sg:phone":"+44 1788 568431",
    "sg:postcode":"CV22 6AW",
    "sg:province":"Warwickshire",
    "sg:tags":[
        "residential",
        "housing",
        "society"
    ],
    "wof:name":"ORBIT HOUSING ASSOCIATION",
    "wof:placetype":"venue"
},
  "geometry": {"coordinates":[-1.2607090473,52.3703384399],"type":"Point"}
}