{
  "type": "Feature",
  "properties": {
    "addr:full":"64 Whitburn St Bridgnorth Shropshire WV16 4QP",
    "addr:housenumber":"64",
    "addr:postcode":"wv16 4qp",
    "addr:street":"Whitburn St",
    "iso:country":"GB",
    "sg:address":"64 Whitburn St",
    "sg:city":"Bridgnorth",
    "sg:classifiers":[
        {
            "category":"Insurance",
            "subcategory":"Insurance Agent",
            "type":"Services"
        }
    ],
    "sg:phone":"+44 1746 766102",
    "sg:postcode":"WV16 4QP",
    "sg:province":"Shropshire",
    "sg:tags":[
        "broker"
    ],
    "wof:name":"Wynnstay Financial Consultancy",
    "wof:placetype":"venue"
},
  "geometry": {"coordinates":[-2.422868,52.53587],"type":"Point"}
}