{
  "type": "Feature",
  "properties": {
    "addr:full":"Queens Walk Mansfield Nottinghamshire NG18 1JX",
    "addr:postcode":"ng18 1jx",
    "addr:street":"Queens Walk",
    "iso:country":"GB",
    "sg:address":"Queens Walk",
    "sg:city":"Mansfield",
    "sg:classifiers":[
        {
            "category":"Professional",
            "subcategory":"Lawyer & Legal Services",
            "type":"Services"
        }
    ],
    "sg:phone":"+44 1623 627163",
    "sg:postcode":"NG18 1JX",
    "sg:province":"Nottinghamshire",
    "sg:tags":[
        "advice",
        "counselling"
    ],
    "wof:name":"Citizens Advice Bureau",
    "wof:placetype":"venue"
},
  "geometry": {"coordinates":[-1.1978189945,53.1440353394],"type":"Point"}
}