{
  "type": "Feature",
  "properties": {
    "addr:full":"1 Cherrybrook Close Leicester Leicestershire LE4 1EH",
    "addr:housenumber":"1",
    "addr:postcode":"le4 1eh",
    "addr:street":"Cherrybrook Close",
    "iso:country":"GB",
    "sg:address":"1 Cherrybrook Close",
    "sg:city":"Leicester",
    "sg:classifiers":[
        {
            "category":"Professional",
            "subcategory":"Accounting & Tax Preparation",
            "type":"Services"
        }
    ],
    "sg:phone":"+44 116 271 3130",
    "sg:postcode":"LE4 1EH",
    "sg:province":"Leicestershire",
    "sg:tags":[
        "accountant"
    ],
    "wof:name":"S & T Courier Services Ltd.",
    "wof:placetype":"venue"
},
  "geometry": {"coordinates":[-1.1621049643,52.6768875122],"type":"Point"}
}