{
  "type": "Feature",
  "properties": {
    "iso:country":"GB",
    "sg:address":"36 Church Hill",
    "sg:city":"Loughton",
    "sg:classifiers":[
        {
            "category":"Real Estate",
            "subcategory":"Surveying",
            "type":"Services"
        }
    ],
    "sg:phone":"+44 20 8508 2001",
    "sg:postcode":"IG10 1LA",
    "sg:province":"Essex",
    "sg:tags":[
        "building",
        "surveyor"
    ],
    "wof:name":"Sheeley & Associates",
    "wof:placetype":"venue"
},
  "geometry": {"coordinates":[0.0597990006,51.6517486572],"type":"Point"}
}