{
  "type": "Feature",
  "properties": {
    "addr:full":"Broad Road, Kentisbeare Cullompton Devon EX15 2EU",
    "addr:postcode":"ex15 2eu",
    "addr:street":"Broad Road",
    "iso:country":"GB",
    "sg:address":"Broad Road, Kentisbeare",
    "sg:city":"Cullompton",
    "sg:classifiers":[
        {
            "category":"Retail",
            "subcategory":"Storage",
            "type":"Services"
        }
    ],
    "sg:phone":"+44 1884 266655",
    "sg:postcode":"EX15 2EU",
    "sg:province":"Devon",
    "sg:tags":[
        "vault",
        "safe"
    ],
    "wof:name":"A C M Security Services Ltd.",
    "wof:placetype":"venue"
},
  "geometry": {"coordinates":[-3.3281359673,50.865486145],"type":"Point"}
}