{
  "type": "Feature",
  "properties": {
    "addr:full":"67 Micklegate York North Yorkshire YO1 1LL",
    "addr:housenumber":"67",
    "addr:postcode":"yo1 1ll",
    "addr:street":"Micklegate",
    "iso:country":"GB",
    "sg:address":"67 Micklegate",
    "sg:city":"York",
    "sg:classifiers":[
        {
            "category":"Home & Garden",
            "subcategory":"Furniture",
            "type":"Retail Goods"
        }
    ],
    "sg:phone":"+44 1904 611443",
    "sg:postcode":"YO1 1LL",
    "sg:province":"North Yorkshire",
    "wof:name":"Dodsworth Interiors",
    "wof:placetype":"venue"
},
  "geometry": {"coordinates":[-1.088151,53.957176],"type":"Point"}
}