{
  "type": "Feature",
  "properties": {
    "addr:full":"59 Hamilton Square Birkenhead Merseyside CH41 5AT",
    "addr:housenumber":"59",
    "addr:postcode":"ch41 5at",
    "addr:street":"Hamilton Square",
    "iso:country":"GB",
    "sg:address":"59 Hamilton Square",
    "sg:city":"Birkenhead",
    "sg:classifiers":[
        {
            "category":"Professional",
            "subcategory":"Lawyer & Legal Services",
            "type":"Services"
        }
    ],
    "sg:phone":"+44 151 647 9821",
    "sg:postcode":"CH41 5AT",
    "sg:province":"Merseyside",
    "sg:tags":[
        "solicitor"
    ],
    "wof:name":"D P Roberts Hughes & Deyne",
    "wof:placetype":"venue"
},
  "geometry": {"coordinates":[-3.015239,53.39296],"type":"Point"}
}