{
  "type": "Feature",
  "properties": {
    "addr:full":"Unit 27f & G, Hartlebury Trading Estate, Hartlebury Kidderminster Staffordshire DY10 4JB",
    "addr:postcode":"dy10 4jb",
    "iso:country":"GB",
    "sg:address":"Unit 27f & G, Hartlebury Trading Estate, Hartlebury",
    "sg:city":"Kidderminster",
    "sg:classifiers":[
        {
            "category":"Home & Garden",
            "subcategory":"Kitchen Supply",
            "type":"Retail Goods"
        }
    ],
    "sg:phone":"+44 1299 253332",
    "sg:postcode":"DY10 4JB",
    "sg:province":"Staffordshire",
    "sg:tags":[
        "ware"
    ],
    "wof:name":"Jv Work Surfaces",
    "wof:placetype":"venue"
},
  "geometry": {"coordinates":[-2.2389400005,52.3694000244],"type":"Point"}
}