{
  "type": "Feature",
  "properties": {
    "iso:country":"GB",
    "sg:address":"170 Maple Road",
    "sg:city":"London",
    "sg:classifiers":[
        {
            "category":"Food & Beverages",
            "subcategory":"Candy",
            "type":"Retail Goods"
        }
    ],
    "sg:phone":"+44 20 8778 3022",
    "sg:postcode":"SE20 8JB",
    "sg:province":"Greater London",
    "sg:tags":[
        "confectioner"
    ],
    "wof:name":"T Goff",
    "wof:placetype":"venue"
},
  "geometry": {"coordinates":[-0.055313,51.414505],"type":"Point"}
}