{
  "type": "Feature",
  "properties": {
    "addr:full":"9 Laking Avenue Broadstairs Kent CT10 3NE",
    "addr:housenumber":"9",
    "addr:postcode":"ct10 3ne",
    "addr:street":"Laking Avenue",
    "iso:country":"GB",
    "sg:address":"9 Laking Avenue",
    "sg:city":"Broadstairs",
    "sg:classifiers":[
        {
            "category":"Professional",
            "subcategory":"Engineering",
            "type":"Services"
        },
        {
            "category":"Building & Trades",
            "subcategory":"Electrical",
            "type":"Services"
        }
    ],
    "sg:phone":"+44 1843 601221",
    "sg:postcode":"CT10 3NE",
    "sg:province":"Kent",
    "sg:tags":[
        "engineer",
        "electrician",
        "contractor"
    ],
    "wof:name":"Roger Scott Young",
    "wof:placetype":"venue"
},
  "geometry": {"coordinates":[1.4394420385,51.3699150085],"type":"Point"}
}