{
  "type": "Feature",
  "properties": {
    "iso:country":"GB",
    "sg:address":"138 Stockport Road, Marple",
    "sg:city":"Stockport",
    "sg:classifiers":[
        {
            "category":"Shopping",
            "subcategory":"Bicycles & Sporting Goods",
            "type":"Retail Goods"
        }
    ],
    "sg:postcode":"SK6 6DQ",
    "sg:province":"Cheshire",
    "sg:tags":[
        "cycle",
        "accessory"
    ],
    "wof:name":"Marple Cyclesport",
    "wof:placetype":"venue"
},
  "geometry": {"coordinates":[-2.070528,53.395828],"type":"Point"}
}