{
  "type": "Feature",
  "properties": {
    "addr:full":"4 Rumbridge Street Southampton Hampshire SO40 9DP",
    "addr:housenumber":"4",
    "addr:postcode":"so40 9dp",
    "addr:street":"Rumbridge Street",
    "iso:country":"GB",
    "sg:address":"4 Rumbridge Street",
    "sg:city":"Southampton",
    "sg:classifiers":[
        {
            "category":"Food & Beverages",
            "subcategory":"Fruits & Vegetables",
            "type":"Retail Goods"
        }
    ],
    "sg:phone":"+44 23 8086 2733",
    "sg:postcode":"SO40 9DP",
    "sg:province":"Hampshire",
    "sg:tags":[
        "greengrocer"
    ],
    "wof:name":"R W Barnes & Sons",
    "wof:placetype":"venue"
},
  "geometry": {"coordinates":[-1.485462,50.916012],"type":"Point"}
}