{
  "type": "Feature",
  "properties": {
    "addr:full":"162 Evelyn Street Warrington Cheshire WA5 1BJ",
    "addr:housenumber":"162",
    "addr:postcode":"wa5 1bj",
    "addr:street":"Evelyn Street",
    "iso:country":"GB",
    "sg:address":"162 Evelyn Street",
    "sg:city":"Warrington",
    "sg:classifiers":[
        {
            "category":"Building & Trades",
            "subcategory":"Cleaning & Sanitation",
            "type":"Services"
        }
    ],
    "sg:postcode":"WA5 1BJ",
    "sg:province":"Cheshire",
    "sg:tags":[
        "commercial"
    ],
    "wof:name":"Servicemaster",
    "wof:placetype":"venue"
},
  "geometry": {"coordinates":[-2.6201190948,53.3845863342],"type":"Point"}
}