{
  "type": "Feature",
  "properties": {
    "iso:country":"GB",
    "sg:address":"Sherburn Road",
    "sg:city":"Durham",
    "sg:classifiers":[
        {
            "category":"Autos & Motor Vehicles",
            "subcategory":"Auto Supplies",
            "type":"Retail Goods"
        }
    ],
    "sg:phone":"+44 191 384 2741",
    "sg:postcode":"DH1 2LJ",
    "sg:province":"Durham",
    "sg:tags":[
        "tyre"
    ],
    "wof:name":"National Tyres and Autocare",
    "wof:placetype":"venue"
},
  "geometry": {"coordinates":[-1.5556470156,54.7790145874],"type":"Point"}
}