{
  "type": "Feature",
  "properties": {
    "addr:full":"Derwent House, Clarence Avenue, Trafford Park Manchester Cheshire M17 1QS",
    "addr:postcode":"m17 1qs",
    "addr:street":"Clarence Avenue",
    "iso:country":"GB",
    "sg:address":"Derwent House, Clarence Avenue, Trafford Park",
    "sg:city":"Manchester",
    "sg:classifiers":[
        {
            "category":"Professional",
            "subcategory":"Engineering",
            "type":"Services"
        }
    ],
    "sg:phone":"+44 161 876 3200",
    "sg:postcode":"M17 1QS",
    "sg:province":"Cheshire",
    "sg:tags":[
        "precision",
        "engineer"
    ],
    "wof:name":"U.K. Robotics",
    "wof:placetype":"venue"
},
  "geometry": {"coordinates":[-2.3330440521,53.4721755981],"type":"Point"}
}