{
  "type": "Feature",
  "properties": {
    "iso:country":"GB",
    "sg:address":"83-84 Berwick St",
    "sg:city":"West End",
    "sg:classifiers":[
        {
            "category":"Personal",
            "type":"Services"
        }
    ],
    "sg:phone":"+44 20 7439 9834",
    "sg:postcode":"W1V 3PJ",
    "sg:province":"Hampshire",
    "sg:tags":[
        "dressmaker"
    ],
    "wof:name":"Peter Simple London",
    "wof:placetype":"venue"
},
  "geometry": {"coordinates":[-0.1354030073,51.5138969421],"type":"Point"}
}