{
  "type": "Feature",
  "properties": {
    "iso:country":"GB",
    "sg:address":"Dornoch Road, Bonar Bridge",
    "sg:city":"Ardgay",
    "sg:classifiers":[
        {
            "category":"Shopping",
            "subcategory":"Department Store",
            "type":"Retail Goods"
        }
    ],
    "sg:postcode":"IV24 3EB",
    "sg:province":"Highland",
    "wof:name":"W I & I L Wilson",
    "wof:placetype":"venue"
},
  "geometry": {"coordinates":[-4.344404,57.889194],"type":"Point"}
}