{
  "type": "Feature",
  "properties": {
    "iso:country":"GB",
    "sg:address":"Croespenmaen Industrial Estate, Kendon, Crumlin",
    "sg:city":"Newport",
    "sg:classifiers":[
        {
            "category":"Retail",
            "subcategory":"Auto Repair",
            "type":"Services"
        }
    ],
    "sg:postcode":"NP11 3AG",
    "sg:province":"Blaenau Gwent",
    "sg:tags":[
        "modification",
        "garage"
    ],
    "wof:name":"Davies Auto Services",
    "wof:placetype":"venue"
},
  "geometry": {"coordinates":[-3.164144,51.680424],"type":"Point"}
}