{
  "type": "Feature",
  "properties": {
    "addr:full":"Werrington Stoke On Trent Staffordshire ST9 0DX",
    "addr:postcode":"st9 0dx",
    "iso:country":"GB",
    "sg:address":"Werrington",
    "sg:city":"Stoke On Trent",
    "sg:classifiers":[
        {
            "category":"Government",
            "subcategory":"Prison",
            "type":"Public Place"
        }
    ],
    "sg:phone":"+44 1782 303514",
    "sg:postcode":"ST9 0DX",
    "sg:province":"Staffordshire",
    "wof:name":"H M Young Offenders Institution",
    "wof:placetype":"venue"
},
  "geometry": {"coordinates":[-2.0885500908,53.0225601196],"type":"Point"}
}