{
  "type": "Feature",
  "properties": {
    "iso:country":"GB",
    "sg:address":"Roundhills Road",
    "sg:city":"Halesowen",
    "sg:classifiers":[
        {
            "category":"Autos & Motor Vehicles",
            "subcategory":"Fuel & Gas Station",
            "type":"Retail Goods"
        }
    ],
    "sg:phone":"+44 121 423 1666",
    "sg:postcode":"B62 9RZ",
    "sg:province":"West Midlands",
    "sg:tags":[
        "petrol",
        "filling"
    ],
    "wof:name":"Roundhills Service Station",
    "wof:placetype":"venue"
},
  "geometry": {"coordinates":[-2.018074,52.47023],"type":"Point"}
}