{
  "type": "Feature",
  "properties": {
    "addr:full":"22 Borough Street, Castle Donington Derby Leicestershire DE74 2LA",
    "addr:housenumber":"22",
    "addr:postcode":"de74 2la",
    "addr:street":"Borough Street",
    "iso:country":"GB",
    "sg:address":"22 Borough Street, Castle Donington",
    "sg:city":"Derby",
    "sg:classifiers":[
        {
            "category":"Personal",
            "subcategory":"Beauty Salon",
            "type":"Services"
        }
    ],
    "sg:phone":"+44 1332 850932",
    "sg:postcode":"DE74 2LA",
    "sg:province":"Leicestershire",
    "wof:name":"Debonair Health & Beauty Centre",
    "wof:placetype":"venue"
},
  "geometry": {"coordinates":[-1.278593,52.837719],"type":"Point"}
}