{
  "type": "Feature",
  "properties": {
    "iso:country":"GB",
    "sg:address":"2 Castle Terrace",
    "sg:city":"Tayport",
    "sg:classifiers":[
        {
            "category":"Retail",
            "subcategory":"Funeral Services",
            "type":"Services"
        }
    ],
    "sg:phone":"+44 1382 552723",
    "sg:postcode":"DD6 9AG",
    "sg:province":"Fife",
    "wof:name":"John C Beat",
    "wof:placetype":"venue"
},
  "geometry": {"coordinates":[-2.8817329407,56.4496498108],"type":"Point"}
}