{
  "type": "Feature",
  "properties": {
    "iso:country":"GB",
    "sg:address":"Natural Health Clinic, 177 Moorside Rd",
    "sg:city":"Manchester",
    "sg:classifiers":[
        {
            "category":"Health Services",
            "subcategory":"Medical Lab",
            "type":"Services"
        },
        {
            "category":"Shopping",
            "subcategory":"Pharmacy",
            "type":"Retail Goods"
        }
    ],
    "sg:phone":"+44 161 793 0091",
    "sg:postcode":"M27 9LD",
    "sg:province":"Greater Manchester",
    "sg:tags":[
        "medicine",
        "alternative",
        "therapy",
        "treatment"
    ],
    "wof:name":"Alan Hopewell",
    "wof:placetype":"venue"
},
  "geometry": {"coordinates":[-2.3540799618,53.5108184814],"type":"Point"}
}