{
  "type": "Feature",
  "properties": {
    "addr:full":"309 Ballards Lane London Greater London N12 8LU",
    "addr:housenumber":"309",
    "addr:postcode":"n12 8lu",
    "addr:street":"Ballards Lane",
    "iso:country":"GB",
    "sg:address":"309 Ballards Lane",
    "sg:city":"London",
    "sg:classifiers":[
        {
            "category":"Professional",
            "subcategory":"Secretarial Services",
            "type":"Services"
        },
        {
            "category":"Real Estate",
            "subcategory":"Architect",
            "type":"Services"
        }
    ],
    "sg:postcode":"N12 8LU",
    "sg:province":"Greater London",
    "wof:name":"Cbga Lp Ltd",
    "wof:placetype":"venue"
},
  "geometry": {"coordinates":[-0.1779289991,51.6124992371],"type":"Point"}
}