{
  "type": "Feature",
  "properties": {
    "addr:full":"Unit 3 South Mill Rd Southampton Hampshire SO15 4AB",
    "addr:housenumber":"unit 3",
    "addr:postcode":"so15 4ab",
    "addr:street":"South Mill Rd",
    "iso:country":"GB",
    "sg:address":"Unit 3 South Mill Rd",
    "sg:city":"Southampton",
    "sg:classifiers":[
        {
            "category":"Home & Garden",
            "subcategory":"Home Furnishings",
            "type":"Retail Goods"
        }
    ],
    "sg:phone":"+44 23 8057 9440",
    "sg:postcode":"SO15 4AB",
    "sg:province":"Hampshire",
    "sg:tags":[
        "patio",
        "furniture"
    ],
    "wof:name":"United Teak Producers Uk Ltd",
    "wof:placetype":"venue"
},
  "geometry": {"coordinates":[-1.445374012,50.9161643982],"type":"Point"}
}