{
  "type": "Feature",
  "properties": {
    "addr:full":"23 Perryn Rd Acton Greater London W3 7LS",
    "addr:housenumber":"23",
    "addr:postcode":"w3 7ls",
    "addr:street":"Perryn Rd",
    "iso:country":"GB",
    "sg:address":"23 Perryn Rd",
    "sg:city":"Acton",
    "sg:classifiers":[
        {
            "category":"Health Services",
            "subcategory":"Nursing And Care Facility",
            "type":"Services"
        }
    ],
    "sg:phone":"+44 20 8749 8273",
    "sg:postcode":"W3 7LS",
    "sg:province":"Greater London",
    "sg:tags":[
        "home"
    ],
    "wof:name":"Amitra Villa",
    "wof:placetype":"venue"
},
  "geometry": {"coordinates":[-0.261424005,51.510974884],"type":"Point"}
}