{
  "type": "Feature",
  "properties": {
    "iso:country":"GB",
    "sg:address":"New Baltic House, Kingsway",
    "sg:city":"Cardiff",
    "sg:classifiers":[
        {
            "category":"Professional",
            "subcategory":"Employment Agencies",
            "type":"Services"
        }
    ],
    "sg:phone":"+44 29 2022 7225",
    "sg:postcode":"CF10 3FD",
    "sg:province":"Cardiff",
    "sg:tags":[
        "factoring"
    ],
    "wof:name":"Kellock Sales & Marketing",
    "wof:placetype":"venue"
},
  "geometry": {"coordinates":[-3.178544,51.484249],"type":"Point"}
}