{
  "type": "Feature",
  "properties": {
    "addr:full":"Unit 1 Brandon Business Centre, Putney Close Brandon Norfolk IP27 0PA",
    "addr:housenumber":"unit 1",
    "addr:postcode":"ip27 0pa",
    "addr:street":"Brandon Business Centre Putney Close",
    "iso:country":"GB",
    "sg:address":"Unit 1 Brandon Business Centre, Putney Close",
    "sg:city":"Brandon",
    "sg:classifiers":[
        {
            "category":"Retail",
            "subcategory":"Auto Repair",
            "type":"Services"
        }
    ],
    "sg:phone":"+44 1842 810287",
    "sg:postcode":"IP27 0PA",
    "sg:province":"Norfolk",
    "sg:tags":[
        "modification",
        "garage",
        "related"
    ],
    "wof:name":"R H Turner",
    "wof:placetype":"venue"
},
  "geometry": {"coordinates":[0.6262050271,52.442741394],"type":"Point"}
}