{
  "type": "Feature",
  "properties": {
    "iso:country":"GB",
    "sg:address":"41 Newport Road",
    "sg:city":"Cowes",
    "sg:classifiers":[
        {
            "category":"Social Services",
            "subcategory":"Retirement Home",
            "type":"Services"
        }
    ],
    "sg:phone":"+44 1983 294134",
    "sg:postcode":"PO31 7PW",
    "sg:province":"Isle of Wight",
    "sg:tags":[
        "residential",
        "care"
    ],
    "wof:name":"Islecare 97 Ltd.",
    "wof:placetype":"venue"
},
  "geometry": {"coordinates":[-1.297894001,50.7560157776],"type":"Point"}
}