{
  "type": "Feature",
  "properties": {
    "iso:country":"GB",
    "sg:address":"25 Dorset Grn, Moredon",
    "sg:city":"Swindon",
    "sg:classifiers":[
        {
            "category":"Building & Trades",
            "subcategory":"Construction",
            "type":"Services"
        }
    ],
    "sg:postcode":"SN2 2JY",
    "sg:province":"Wiltshire",
    "sg:tags":[
        "joinery",
        "builder"
    ],
    "wof:name":"Halen Building Contractors Ltd.",
    "wof:placetype":"venue"
},
  "geometry": {"coordinates":[-1.805639,51.580906],"type":"Point"}
}