{
  "type": "Feature",
  "properties": {
    "iso:country":"GB",
    "sg:address":"38 Station Road, North Elmham",
    "sg:city":"Dereham",
    "sg:classifiers":[
        {
            "category":"Retail",
            "subcategory":"Auto Repair",
            "type":"Services"
        }
    ],
    "sg:phone":"+44 1362 668690",
    "sg:postcode":"NR20 5HH",
    "sg:province":"Norfolk",
    "sg:tags":[
        "body",
        "car"
    ],
    "wof:name":"Leede Bodywork",
    "wof:placetype":"venue"
},
  "geometry": {"coordinates":[1.0094159842,52.7801589966],"type":"Point"}
}