{
  "type": "Feature",
  "properties": {
    "addr:full":"54 Andrews Close Chippenham Gloucestershire SN14 0TX",
    "addr:housenumber":"54",
    "addr:postcode":"sn14 0tx",
    "addr:street":"Andrews Close",
    "iso:country":"GB",
    "sg:address":"54 Andrews Close",
    "sg:city":"Chippenham",
    "sg:classifiers":[
        {
            "category":"Arena",
            "subcategory":"Sports Club",
            "type":"Entertainment"
        }
    ],
    "sg:phone":"+44 1249 448004",
    "sg:postcode":"SN14 0TX",
    "sg:province":"Gloucestershire",
    "wof:name":"Academy of Tae Kwon-do & Self Defence",
    "wof:placetype":"venue"
},
  "geometry": {"coordinates":[-2.135374,51.459988],"type":"Point"}
}