{
  "type": "Feature",
  "properties": {
    "iso:country":"GB",
    "sg:address":"30 Shrubbery Road, Drakes Broughton",
    "sg:city":"Pershore",
    "sg:classifiers":[
        {
            "category":"Personal",
            "subcategory":"Beauty Salon",
            "type":"Services"
        }
    ],
    "sg:phone":"+44 1905 840473",
    "sg:postcode":"WR10 2BA",
    "sg:province":"Worcestershire",
    "sg:tags":[
        "unisex",
        "hairdresser"
    ],
    "wof:name":"Haircraft",
    "wof:placetype":"venue"
},
  "geometry": {"coordinates":[-2.106852,52.137165],"type":"Point"}
}