{
  "type": "Feature",
  "properties": {
    "addr:full":"Albion House, Temple Street Llandrindod Wells Powys LD1 5DP",
    "addr:postcode":"ld1 5dp",
    "addr:street":"Temple Street",
    "iso:country":"GB",
    "sg:address":"Albion House, Temple Street",
    "sg:city":"Llandrindod Wells",
    "sg:classifiers":[
        {
            "category":"Shopping",
            "subcategory":"News",
            "type":"Retail Goods"
        }
    ],
    "sg:phone":"+44 1597 822323",
    "sg:postcode":"LD1 5DP",
    "sg:province":"Powys",
    "sg:tags":[
        "newsagent"
    ],
    "wof:name":"C A & J G Owen",
    "wof:placetype":"venue"
},
  "geometry": {"coordinates":[-3.3777320385,52.2409744263],"type":"Point"}
}