{
  "type": "Feature",
  "properties": {
    "addr:full":"8a Herring Lane Spalding Lincolnshire PE11 1TL",
    "addr:housenumber":"8a",
    "addr:postcode":"pe11 1tl",
    "addr:street":"Herring Lane",
    "iso:country":"GB",
    "sg:address":"8a Herring Lane",
    "sg:city":"Spalding",
    "sg:classifiers":[
        {
            "category":"Banks & Credit Unions",
            "subcategory":"Financial Services",
            "type":"Services"
        }
    ],
    "sg:phone":"+44 1775 714777",
    "sg:postcode":"PE11 1TL",
    "sg:province":"Lincolnshire",
    "sg:tags":[
        "adviser"
    ],
    "wof:name":"Deerfield Financial Planning",
    "wof:placetype":"venue"
},
  "geometry": {"coordinates":[-0.1499460042,52.7872123718],"type":"Point"}
}