{
  "type": "Feature",
  "properties": {
    "addr:full":"1 The Promenade Edgware Greater London HA8 7JZ",
    "addr:housenumber":"1",
    "addr:postcode":"ha8 7jz",
    "addr:street":"The Promenade",
    "iso:country":"GB",
    "sg:address":"1 The Promenade",
    "sg:city":"Edgware",
    "sg:classifiers":[
        {
            "category":"Health Services",
            "subcategory":"Optometrist",
            "type":"Services"
        }
    ],
    "sg:phone":"+44 20 8958 1628",
    "sg:postcode":"HA8 7JZ",
    "sg:province":"Greater London",
    "sg:tags":[
        "optician"
    ],
    "wof:name":"Edgware Optical Centre",
    "wof:placetype":"venue"
},
  "geometry": {"coordinates":[-0.2753120065,51.6160964966],"type":"Point"}
}