{
  "type": "Feature",
  "properties": {
    "addr:full":"423-425 Caledonian Road London Greater London N7 9BQ",
    "addr:housenumber":"423-425",
    "addr:postcode":"n7 9bq",
    "addr:street":"Caledonian Road",
    "iso:country":"GB",
    "sg:address":"423-425 Caledonian Road",
    "sg:city":"London",
    "sg:classifiers":[
        {
            "category":"Professional",
            "subcategory":"Computer Services",
            "type":"Services"
        }
    ],
    "sg:phone":"+44 20 7619 1500",
    "sg:postcode":"N7 9BQ",
    "sg:province":"Greater London",
    "sg:tags":[
        "development",
        "system",
        "software"
    ],
    "wof:name":"Eurodata Systems Plc",
    "wof:placetype":"venue"
},
  "geometry": {"coordinates":[-0.117765,51.546257],"type":"Point"}
}