{
  "type": "Feature",
  "properties": {
    "addr:full":"25 Oakfield Rd, Aylsham Norwich Norfolk NR11 6AL",
    "addr:housenumber":"25",
    "addr:postcode":"nr11 6al",
    "addr:street":"Oakfield Rd;Norwich",
    "iso:country":"GB",
    "sg:address":"25 Oakfield Rd, Aylsham",
    "sg:city":"Norwich",
    "sg:classifiers":[
        {
            "category":"Building & Trades",
            "subcategory":"Cleaning & Sanitation",
            "type":"Services"
        }
    ],
    "sg:phone":"+44 1263 735737",
    "sg:postcode":"NR11 6AL",
    "sg:province":"Norfolk",
    "sg:tags":[
        "polishing",
        "floor"
    ],
    "wof:name":"Springfield",
    "wof:placetype":"venue"
},
  "geometry": {"coordinates":[1.254064,52.794647],"type":"Point"}
}