{
  "type": "Feature",
  "properties": {
    "iso:country":"GB",
    "sg:address":"Unit J, Jarrold Way Bowthorpe Employment Area",
    "sg:city":"Norwich",
    "sg:classifiers":[
        {
            "category":"Home & Garden",
            "subcategory":"Furniture",
            "type":"Retail Goods"
        }
    ],
    "sg:phone":"+44 1603 743713",
    "sg:postcode":"NR5 9JD",
    "sg:province":"Norfolk",
    "wof:name":"Quintell Resources Ltd",
    "wof:placetype":"venue"
},
  "geometry": {"coordinates":[1.218265,52.643055],"type":"Point"}
}