{
  "type": "Feature",
  "properties": {
    "iso:country":"GB",
    "sg:address":"28 Westby Road",
    "sg:city":"Bournemouth",
    "sg:classifiers":[
        {
            "category":"Shopping",
            "subcategory":"Antiques",
            "type":"Retail Goods"
        }
    ],
    "sg:postcode":"BH5 1HD",
    "sg:province":"Dorset",
    "wof:name":"Broadway Antiques",
    "wof:placetype":"venue"
},
  "geometry": {"coordinates":[-1.838089,50.72541],"type":"Point"}
}