{
  "type": "Feature",
  "properties": {
    "iso:country":"GB",
    "sg:address":"64 Brinkburn Ave",
    "sg:city":"Darlington",
    "sg:classifiers":[
        {
            "category":"Building & Trades",
            "subcategory":"Construction",
            "type":"Services"
        }
    ],
    "sg:postcode":"DL3 0JW",
    "sg:province":"Durham",
    "sg:tags":[
        "builder"
    ],
    "wof:name":"Durham Bros",
    "wof:placetype":"venue"
},
  "geometry": {"coordinates":[-1.5705189705,54.5392608643],"type":"Point"}
}