{
  "type": "Feature",
  "properties": {
    "addr:full":"Unit 1, Neighbourhood Centre, Brimsham Park Yate Bristol Gloucestershire BS37 7PQ",
    "addr:housenumber":"unit",
    "addr:postcode":"bs37 7pq",
    "iso:country":"GB",
    "sg:address":"Unit 1, Neighbourhood Centre, Brimsham Park Yate",
    "sg:city":"Bristol",
    "sg:classifiers":[
        {
            "category":"Food & Beverages",
            "subcategory":"Groceries & Convenience Stores",
            "type":"Retail Goods"
        }
    ],
    "sg:phone":"+44 1454 322099",
    "sg:postcode":"BS37 7PQ",
    "sg:province":"Gloucestershire",
    "wof:name":"One Stop Community Stores Ltd.",
    "wof:placetype":"venue"
},
  "geometry": {"coordinates":[-2.41432,51.552441],"type":"Point"}
}