{
  "type": "Feature",
  "properties": {
    "iso:country":"GB",
    "sg:address":"Dolphin Centre",
    "sg:city":"Poole",
    "sg:classifiers":[
        {
            "category":"Shopping",
            "subcategory":"Department Store",
            "type":"Retail Goods"
        }
    ],
    "sg:phone":"+44 1202 675721",
    "sg:postcode":"BH15 1SQ",
    "sg:province":"Dorset",
    "wof:name":"Beales Department Store",
    "wof:placetype":"venue"
},
  "geometry": {"coordinates":[-1.986739,50.714485],"type":"Point"}
}