{
  "type": "Feature",
  "properties": {
    "addr:full":"1 Forest Close, Wendover Aylesbury Buckinghamshire HP22 6BT",
    "addr:housenumber":"1",
    "addr:postcode":"hp22 6bt",
    "addr:street":"Forest Close",
    "iso:country":"GB",
    "sg:address":"1 Forest Close, Wendover",
    "sg:city":"Aylesbury",
    "sg:classifiers":[
        {
            "category":"Organizations",
            "subcategory":"Non-profit Organization",
            "type":"Services"
        }
    ],
    "sg:phone":"+44 1296 642020",
    "sg:postcode":"HP22 6BT",
    "sg:province":"Buckinghamshire",
    "sg:tags":[
        "organisation",
        "voluntary",
        "charity"
    ],
    "wof:name":"Toch H",
    "wof:placetype":"venue"
},
  "geometry": {"coordinates":[-0.746053,51.762833],"type":"Point"}
}