{
  "type": "Feature",
  "properties": {
    "addr:full":"53 Aperfield Road, Biggin Hill Westerham Kent TN16 3LX",
    "addr:housenumber":"53",
    "addr:postcode":"tn16 3lx",
    "addr:street":"Aperfield Road",
    "iso:country":"GB",
    "sg:address":"53 Aperfield Road, Biggin Hill",
    "sg:city":"Westerham",
    "sg:classifiers":[
        {
            "category":"Building & Trades",
            "subcategory":"Construction",
            "type":"Services"
        }
    ],
    "sg:phone":"+44 1959 575109",
    "sg:postcode":"TN16 3LX",
    "sg:province":"Kent",
    "sg:tags":[
        "dry",
        "lining",
        "plasterers",
        "screeders"
    ],
    "wof:name":"M Pilcher",
    "wof:placetype":"venue"
},
  "geometry": {"coordinates":[0.0434210002,51.308971405],"type":"Point"}
}