{
  "type": "Feature",
  "properties": {
    "addr:full":"Stannard Island, Chantry Bridge Wakefield West Yorkshire WF1 5DL",
    "addr:postcode":"wf1 5dl",
    "addr:street":"Stannard Island;West",
    "iso:country":"GB",
    "sg:address":"Stannard Island, Chantry Bridge",
    "sg:city":"Wakefield",
    "sg:classifiers":[
        {
            "category":"Professional",
            "subcategory":"Business Services",
            "type":"Services"
        }
    ],
    "sg:phone":"+44 1924 200580",
    "sg:postcode":"WF1 5DL",
    "sg:province":"West Yorkshire",
    "sg:tags":[
        "accomodation"
    ],
    "wof:name":"Confidential Business Services",
    "wof:placetype":"venue"
},
  "geometry": {"coordinates":[-1.4887700081,53.6766090393],"type":"Point"}
}