{
  "type": "Feature",
  "properties": {
    "addr:full":"6 Highfield Way Walsall Staffordshire WS9 8XF",
    "addr:housenumber":"6",
    "addr:postcode":"ws9 8xf",
    "addr:street":"Highfield Way",
    "iso:country":"GB",
    "sg:address":"6 Highfield Way",
    "sg:city":"Walsall",
    "sg:classifiers":[
        {
            "category":"Home & Garden",
            "subcategory":"Building Materials",
            "type":"Retail Goods"
        }
    ],
    "sg:phone":"+44 1922 454447",
    "sg:postcode":"WS9 8XF",
    "sg:province":"Staffordshire",
    "sg:tags":[
        "access",
        "equipment"
    ],
    "wof:name":"Midland Access Ltd.",
    "wof:placetype":"venue"
},
  "geometry": {"coordinates":[-1.9178539515,52.621887207],"type":"Point"}
}