{
  "type": "Feature",
  "properties": {
    "addr:full":"6 Clifton Terrace, Haymarket Edinburgh City of Edinburgh EH12 5ET",
    "addr:housenumber":"6",
    "addr:postcode":"eh12 5et",
    "addr:street":"Clifton Terrace",
    "iso:country":"GB",
    "sg:address":"6 Clifton Terrace, Haymarket",
    "sg:city":"Edinburgh",
    "sg:classifiers":[
        {
            "category":"Professional",
            "subcategory":"Lawyer & Legal Services",
            "type":"Services"
        }
    ],
    "sg:postcode":"EH12 5ET",
    "sg:province":"City of Edinburgh",
    "sg:tags":[
        "solicitor"
    ],
    "wof:name":"Grays Solicitors",
    "wof:placetype":"venue"
},
  "geometry": {"coordinates":[-3.2176349163,55.9459877014],"type":"Point"}
}