{
  "type": "Feature",
  "properties": {
    "iso:country":"GB",
    "sg:address":"5a Factory Lane, Beeston",
    "sg:city":"Nottingham",
    "sg:classifiers":[
        {
            "category":"Professional",
            "subcategory":"Art Services",
            "type":"Services"
        }
    ],
    "sg:phone":"+44 115 922 9632",
    "sg:postcode":"NG9 4AA",
    "sg:province":"Nottinghamshire",
    "sg:tags":[
        "graphic",
        "designer"
    ],
    "wof:name":"DW Illustration & Graphic Design",
    "wof:placetype":"venue"
},
  "geometry": {"coordinates":[-1.221282,52.921631],"type":"Point"}
}