{
  "type": "Feature",
  "properties": {
    "iso:country":"GB",
    "sg:address":"16 Ellison Avenue",
    "sg:city":"Scarborough",
    "sg:classifiers":[
        {
            "category":"Building & Trades",
            "subcategory":"Construction",
            "type":"Services"
        }
    ],
    "sg:phone":"+44 1723 363737",
    "sg:postcode":"YO12 6UY",
    "sg:province":"North Yorkshire",
    "sg:tags":[
        "roofing"
    ],
    "wof:name":"Scarborough Felt Roofing",
    "wof:placetype":"venue"
},
  "geometry": {"coordinates":[-0.440381,54.298702],"type":"Point"}
}