{
  "type": "Feature",
  "properties": {
    "addr:full":"1 Weybrook Road, Heaton Chapel Stockport Greater Manchester M19 2QD",
    "addr:housenumber":"1",
    "addr:postcode":"m19 2qd",
    "addr:street":"Weybrook Road",
    "iso:country":"GB",
    "sg:address":"1 Weybrook Road, Heaton Chapel",
    "sg:city":"Stockport",
    "sg:classifiers":[
        {
            "category":"Retail",
            "subcategory":"Auto Repair",
            "type":"Services"
        }
    ],
    "sg:phone":"+44 161 443 1265",
    "sg:postcode":"M19 2QD",
    "sg:province":"Greater Manchester",
    "sg:tags":[
        "modification",
        "garage"
    ],
    "wof:name":"New Beech Garage",
    "wof:placetype":"venue"
},
  "geometry": {"coordinates":[-2.18965,53.439919],"type":"Point"}
}