{
  "type": "Feature",
  "properties": {
    "addr:full":"Unit 4, 328 Romford Road, Forest Gate London Greater London E7 8BS",
    "addr:housenumber":"unit 4",
    "addr:postcode":"328;e7 8bs",
    "addr:street":"Romford Road",
    "iso:country":"GB",
    "sg:address":"Unit 4, 328 Romford Road, Forest Gate",
    "sg:city":"London",
    "sg:classifiers":[
        {
            "category":"Home & Garden",
            "subcategory":"Home Furnishings",
            "type":"Retail Goods"
        }
    ],
    "sg:phone":"+44 20 8519 0100",
    "sg:postcode":"E7 8BS",
    "sg:province":"Greater London",
    "sg:tags":[
        "homefurnishings"
    ],
    "wof:name":"Woodstyle Carpentry",
    "wof:placetype":"venue"
},
  "geometry": {"coordinates":[0.0290649999,51.5466156006],"type":"Point"}
}