{
  "type": "Feature",
  "properties": {
    "iso:country":"GB",
    "sg:address":"Tyhurst, Keysford Lane, Horsted Keynes",
    "sg:city":"Haywards Heath",
    "sg:classifiers":[
        {
            "category":"Professional",
            "subcategory":"Engineering",
            "type":"Services"
        },
        {
            "category":"Building & Trades",
            "subcategory":"Electrical",
            "type":"Services"
        }
    ],
    "sg:phone":"+44 1825 790260",
    "sg:postcode":"RH17 7EL",
    "sg:province":"East Sussex",
    "sg:tags":[
        "engineer",
        "electrician",
        "contractor"
    ],
    "wof:name":"Electrical & Data Services",
    "wof:placetype":"venue"
},
  "geometry": {"coordinates":[-0.028284,51.036671],"type":"Point"}
}