{
  "type": "Feature",
  "properties": {
    "iso:country":"GB",
    "sg:address":"Chertsey House, London Road",
    "sg:city":"Carlisle",
    "sg:classifiers":[
        {
            "category":"Social Services",
            "subcategory":"Job Training",
            "type":"Services"
        },
        {
            "category":"Education",
            "subcategory":"Special Training",
            "type":"Public Place"
        }
    ],
    "sg:phone":"+44 1228 593446",
    "sg:postcode":"CA1 2QX",
    "sg:province":"Cumbria",
    "sg:tags":[
        "product",
        "centre"
    ],
    "sg:website":"http://www.rwp.co.uk",
    "wof:name":"RWP Training Ltd",
    "wof:placetype":"venue"
},
  "geometry": {"coordinates":[-2.926388979,54.8887214661],"type":"Point"}
}