{
  "type": "Feature",
  "properties": {
    "iso:country":"GB",
    "sg:address":"1 More London Place",
    "sg:city":"London",
    "sg:classifiers":[
        {
            "category":"Professional",
            "subcategory":"Accounting & Tax Preparation",
            "type":"Services"
        }
    ],
    "sg:phone":"+44 20 7951 2000",
    "sg:postcode":"SE1 2AF",
    "sg:province":"Greater London",
    "sg:tags":[
        "accountant",
        "activity"
    ],
    "wof:name":"Ernst & Young Ltd",
    "wof:placetype":"venue"
},
  "geometry": {"coordinates":[-0.0778,51.50177],"type":"Point"}
}