{
  "type": "Feature",
  "properties": {
    "addr:full":"Bracklinn Road Callander Stirling FK17 8EQ",
    "addr:postcode":"fk17 8eq",
    "addr:street":"Bracklinn Road",
    "iso:country":"GB",
    "sg:address":"Bracklinn Road",
    "sg:city":"Callander",
    "sg:classifiers":[
        {
            "category":"Travel",
            "subcategory":"Hotels & Motels",
            "type":"Entertainment"
        }
    ],
    "sg:phone":"+44 1877 330235",
    "sg:postcode":"FK17 8EQ",
    "sg:province":"Stirling",
    "sg:tags":[
        "house",
        "guest"
    ],
    "wof:name":"James Mcgregor",
    "wof:placetype":"venue"
},
  "geometry": {"coordinates":[-4.254063,56.237206],"type":"Point"}
}