{
  "type": "Feature",
  "properties": {
    "addr:full":"Old Abc Cinema, St John Street Colchester Essex CO2 7AA",
    "addr:postcode":"co2 7aa",
    "addr:street":"St John Street",
    "iso:country":"GB",
    "sg:address":"Old Abc Cinema, St John Street",
    "sg:city":"Colchester",
    "sg:classifiers":[
        {
            "category":"Bars & Pubs",
            "type":"Food & Drink"
        }
    ],
    "sg:phone":"+44 1206 571003",
    "sg:postcode":"CO2 7AA",
    "sg:province":"Essex",
    "sg:tags":[
        "pubs",
        "inn"
    ],
    "wof:name":"The Playhouse",
    "wof:placetype":"venue"
},
  "geometry": {"coordinates":[0.9035140276,51.8852996826],"type":"Point"}
}