{
  "type": "Feature",
  "properties": {
    "addr:full":"Horspath Driftway, Headington Oxford Oxfordshire OX3 7JH",
    "addr:postcode":"ox3 7jh",
    "addr:street":"Horspath Driftway",
    "iso:country":"GB",
    "sg:address":"Horspath Driftway, Headington",
    "sg:city":"Oxford",
    "sg:classifiers":[
        {
            "category":"Food & Beverages",
            "subcategory":"Specialty",
            "type":"Retail Goods"
        }
    ],
    "sg:phone":"+44 1865 747010",
    "sg:postcode":"OX3 7JH",
    "sg:province":"Oxfordshire",
    "sg:tags":[
        "dietetic",
        "homogenised"
    ],
    "wof:name":"Orchard Food Services",
    "wof:placetype":"venue"
},
  "geometry": {"coordinates":[-1.1986800432,51.7434082031],"type":"Point"}
}