{
  "type": "Feature",
  "properties": {
    "iso:country":"GB",
    "sg:address":"Narberth Road",
    "sg:city":"Haverfordwest",
    "sg:classifiers":[
        {
            "category":"Autos & Motor Vehicles",
            "subcategory":"Automobile Sales",
            "type":"Retail Goods"
        },
        {
            "category":"Autos & Motor Vehicles",
            "subcategory":"Auto Supplies",
            "type":"Retail Goods"
        }
    ],
    "sg:phone":"+44 1437 771117",
    "sg:postcode":"SA61 2XG",
    "sg:province":"Pembrokeshire",
    "sg:tags":[
        "car",
        "component"
    ],
    "wof:name":"Express Factors",
    "wof:placetype":"venue"
},
  "geometry": {"coordinates":[-4.957394,51.804562],"type":"Point"}
}