{
  "type": "Feature",
  "properties": {
    "addr:full":"Cross Street, Syston Leicester Leicestershire LE7 2JG",
    "addr:postcode":"le7 2jg",
    "addr:street":"Cross Street",
    "iso:country":"GB",
    "sg:address":"Cross Street, Syston",
    "sg:city":"Leicester",
    "sg:classifiers":[
        {
            "category":"Professional",
            "type":"Services"
        }
    ],
    "sg:phone":"+44 116 260 8211",
    "sg:postcode":"LE7 2JG",
    "sg:province":"Leicestershire",
    "sg:tags":[
        "shopfitters"
    ],
    "wof:name":"Antone Displays Ltd.",
    "wof:placetype":"venue"
},
  "geometry": {"coordinates":[-1.073708,52.698517],"type":"Point"}
}