{
  "type": "Feature",
  "properties": {
    "addr:full":"115 Southwark Bridge Rd London Greater London SE1 0AX",
    "addr:housenumber":"115",
    "addr:postcode":"se1 0ax",
    "addr:street":"Southwark Bridge Rd",
    "iso:country":"GB",
    "sg:address":"115 Southwark Bridge Rd",
    "sg:city":"London",
    "sg:classifiers":[
        {
            "category":"Organizations",
            "subcategory":"Religious Organization",
            "type":"Services"
        }
    ],
    "sg:phone":"+44 20 7450 9070",
    "sg:postcode":"SE1 0AX",
    "sg:province":"Greater London",
    "sg:tags":[
        "organisation"
    ],
    "wof:name":"Fanfare for A New Generation",
    "wof:placetype":"venue"
},
  "geometry": {"coordinates":[-0.096228,51.502899],"type":"Point"}
}