{
  "type": "Feature",
  "properties": {
    "addr:full":"Baynton Way, Edington Westbury Wiltshire BA13 4PT",
    "addr:postcode":"ba13 4pt",
    "addr:street":"Baynton Way",
    "iso:country":"GB",
    "sg:address":"Baynton Way, Edington",
    "sg:city":"Westbury",
    "sg:classifiers":[
        {
            "category":"Building & Trades",
            "subcategory":"Construction",
            "type":"Services"
        }
    ],
    "sg:phone":"+44 1380 830951",
    "sg:postcode":"BA13 4PT",
    "sg:province":"Wiltshire",
    "sg:tags":[
        "specialised",
        "work",
        "platform",
        "scaffolding",
        "contractor"
    ],
    "wof:name":"CALLAWAY SCAFFOLDS LTD",
    "wof:placetype":"venue"
},
  "geometry": {"coordinates":[-2.096694,51.278961],"type":"Point"}
}