{
  "type": "Feature",
  "properties": {
    "addr:full":"Park Ho, 64 West Ham La London Greater London E15 4PT",
    "addr:housenumber":"64",
    "addr:postcode":"e15 4pt",
    "addr:street":"Park;West Ham La",
    "iso:country":"GB",
    "sg:address":"Park Ho, 64 West Ham La",
    "sg:city":"London",
    "sg:classifiers":[
        {
            "category":"Professional",
            "subcategory":"Detective & Security Services",
            "type":"Services"
        }
    ],
    "sg:postcode":"E15 4PT",
    "sg:province":"Greater London",
    "wof:name":"Kilo Guard Services Ltd",
    "wof:placetype":"venue"
},
  "geometry": {"coordinates":[0.00603,51.537239],"type":"Point"}
}