{
  "type": "Feature",
  "properties": {
    "addr:full":"9 York Street Twickenham Greater London TW1 3JZ",
    "addr:housenumber":"9",
    "addr:postcode":"tw1 3jz",
    "addr:street":"York Street",
    "iso:country":"GB",
    "sg:address":"9 York Street",
    "sg:city":"Twickenham",
    "sg:classifiers":[
        {
            "category":"Travel",
            "subcategory":"Travel Agent",
            "type":"Entertainment"
        }
    ],
    "sg:phone":"+44 20 8288 1000",
    "sg:postcode":"TW1 3JZ",
    "sg:province":"Greater London",
    "wof:name":"Rugby Travel Specialists Ltd.",
    "wof:placetype":"venue"
},
  "geometry": {"coordinates":[-0.328173995,51.4469833374],"type":"Point"}
}