{
  "type": "Feature",
  "properties": {
    "addr:full":"461 Tamworth Road, Sawley, Long Eaton Nottingham Derbyshire NG10 3GR",
    "addr:housenumber":"461",
    "addr:postcode":"ng10 3gr",
    "addr:street":"Tamworth Road",
    "iso:country":"GB",
    "sg:address":"461 Tamworth Road, Sawley, Long Eaton",
    "sg:city":"Nottingham",
    "sg:classifiers":[
        {
            "category":"Shopping",
            "subcategory":"Clothing, Apparel, & Fashions",
            "type":"Retail Goods"
        }
    ],
    "sg:postcode":"NG10 3GR",
    "sg:province":"Derbyshire",
    "sg:tags":[
        "shop"
    ],
    "wof:name":"County Style",
    "wof:placetype":"venue"
},
  "geometry": {"coordinates":[-1.2872600555,52.8843193054],"type":"Point"}
}