{
  "type": "Feature",
  "properties": {
    "addr:full":"114 Hebrew Road, Duke Bar Burnley Lancashire BB10 1LR",
    "addr:housenumber":"114",
    "addr:postcode":"bb10 1lr",
    "addr:street":"Hebrew Road",
    "iso:country":"GB",
    "sg:address":"114 Hebrew Road, Duke Bar",
    "sg:city":"Burnley",
    "sg:classifiers":[
        {
            "category":"Shopping",
            "subcategory":"Clothing, Apparel, & Fashions",
            "type":"Retail Goods"
        }
    ],
    "sg:postcode":"BB10 1LR",
    "sg:province":"Lancashire",
    "sg:tags":[
        "lingerie",
        "hosiery"
    ],
    "wof:name":"Dennis Walker",
    "wof:placetype":"venue"
},
  "geometry": {"coordinates":[-2.2370209694,53.8010215759],"type":"Point"}
}