{
  "type": "Feature",
  "properties": {
    "addr:full":"Harbour House, West Quay Gloucester Gloucestershire GL1 2LG",
    "addr:postcode":"gl1 2lg",
    "addr:street":"West Quay",
    "iso:country":"GB",
    "sg:address":"Harbour House, West Quay",
    "sg:city":"Gloucester",
    "sg:classifiers":[
        {
            "category":"Marine",
            "type":"Transportation"
        }
    ],
    "sg:phone":"+44 1452 318000",
    "sg:postcode":"GL1 2LG",
    "sg:province":"Gloucestershire",
    "sg:tags":[
        "inland",
        "waterway",
        "river"
    ],
    "wof:name":"British Waterways",
    "wof:placetype":"venue"
},
  "geometry": {"coordinates":[-2.2496240139,51.8638114929],"type":"Point"}
}