{
  "type": "Feature",
  "properties": {
    "iso:country":"GB",
    "sg:address":"Capital House, 11 Market Pl, Acton",
    "sg:city":"London",
    "sg:classifiers":[
        {
            "category":"Real Estate",
            "subcategory":"Surveying",
            "type":"Services"
        }
    ],
    "sg:postcode":"W3 6QS",
    "sg:province":"Greater London",
    "sg:tags":[
        "surveyor",
        "valuer"
    ],
    "wof:name":"Wiseman,Gerald,",
    "wof:placetype":"venue"
},
  "geometry": {"coordinates":[-0.2709639966,51.5077972412],"type":"Point"}
}