{
  "type": "Feature",
  "properties": {
    "addr:full":"238 King St London Greater London W6 0RF",
    "addr:housenumber":"238",
    "addr:postcode":"w6 0rf",
    "addr:street":"King St",
    "iso:country":"GB",
    "sg:address":"238 King St",
    "sg:city":"London",
    "sg:classifiers":[
        {
            "category":"Professional",
            "subcategory":"Business Services",
            "type":"Services"
        }
    ],
    "sg:postcode":"W6 0RF",
    "sg:province":"Greater London",
    "sg:tags":[
        "import",
        "export",
        "agent"
    ],
    "wof:name":"Phoenix International (U K) Ltd",
    "wof:placetype":"venue"
},
  "geometry": {"coordinates":[-0.237169,51.493351],"type":"Point"}
}