{
  "type": "Feature",
  "properties": {
    "iso:country":"GB",
    "sg:address":"29 St Simons Road",
    "sg:city":"Southsea",
    "sg:classifiers":[
        {
            "category":"Travel",
            "subcategory":"Hotels & Motels",
            "type":"Entertainment"
        }
    ],
    "sg:phone":"+44 23 9235 1277",
    "sg:postcode":"PO5 2PE",
    "sg:province":"Hampshire",
    "sg:tags":[
        "house",
        "guest"
    ],
    "wof:name":"Casco Services",
    "wof:placetype":"venue"
},
  "geometry": {"coordinates":[-1.080468,50.782631],"type":"Point"}
}