{
  "type": "Feature",
  "properties": {
    "iso:country":"GB",
    "sg:address":"461 Oxford Street",
    "sg:city":"London",
    "sg:classifiers":[
        {
            "category":"Shopping",
            "subcategory":"Baby Store",
            "type":"Retail Goods"
        }
    ],
    "sg:phone":"+44 20 7629 6621",
    "sg:postcode":"W1R 1DB",
    "sg:province":"Greater London",
    "sg:tags":[
        "nursery",
        "accessory"
    ],
    "wof:name":"Mothercare",
    "wof:placetype":"venue"
},
  "geometry": {"coordinates":[-0.154482007,51.5137939453],"type":"Point"}
}