{
  "type": "Feature",
  "properties": {
    "addr:full":"Cooks Farm, Downside Road, Backwell Bristol Somerset BS48 3DN",
    "addr:postcode":"bs48 3dn",
    "addr:street":"Downside Road",
    "iso:country":"GB",
    "sg:address":"Cooks Farm, Downside Road, Backwell",
    "sg:city":"Bristol",
    "sg:classifiers":[
        {
            "category":"Farming",
            "subcategory":"Livestock Farm",
            "type":"Manufacturing & Wholesale Goods"
        }
    ],
    "sg:postcode":"BS48 3DN",
    "sg:province":"Somerset",
    "sg:tags":[
        "others"
    ],
    "wof:name":"J & E Marshall",
    "wof:placetype":"venue"
},
  "geometry": {"coordinates":[-2.7411789894,51.4130897522],"type":"Point"}
}