{
  "type": "Feature",
  "properties": {
    "addr:full":"Kinfauns Rd, Goodmayes Ilford Essex IG3 9QL",
    "addr:postcode":"ig3 9ql",
    "addr:street":"Kinfauns Rd",
    "iso:country":"GB",
    "sg:address":"Kinfauns Rd, Goodmayes",
    "sg:city":"Ilford",
    "sg:classifiers":[
        {
            "category":"Place Of Worship",
            "type":"Public Place"
        }
    ],
    "sg:phone":"+44 20 8590 2468",
    "sg:postcode":"IG3 9QL",
    "sg:province":"Essex",
    "wof:name":"Goodmayes Baptist Church",
    "wof:placetype":"venue"
},
  "geometry": {"coordinates":[0.116475,51.564526],"type":"Point"}
}