{
  "type": "Feature",
  "properties": {
    "addr:full":"Corinium House Gloucester Gloucestershire GL4 3HX",
    "addr:postcode":"gl4 3hx",
    "iso:country":"GB",
    "sg:address":"Corinium House",
    "sg:city":"Gloucester",
    "sg:classifiers":[
        {
            "category":"Building & Trades",
            "subcategory":"Construction",
            "type":"Services"
        }
    ],
    "sg:phone":"+44 1452 501501",
    "sg:postcode":"GL4 3HX",
    "sg:province":"Gloucestershire",
    "sg:tags":[
        "excavation",
        "groundwork",
        "contractor"
    ],
    "wof:name":"E M G Ltd.",
    "wof:placetype":"venue"
},
  "geometry": {"coordinates":[-2.209339,51.862801],"type":"Point"}
}