{
  "type": "Feature",
  "properties": {
    "iso:country":"GB",
    "sg:address":"Wolfson Hall, 2317 Maryhill Road",
    "sg:city":"Glasgow",
    "sg:classifiers":[
        {
            "category":"Education",
            "subcategory":"University",
            "type":"Public Place"
        }
    ],
    "sg:phone":"+44 141 946 5252",
    "sg:postcode":"G20 0TH",
    "sg:province":"Glasgow City",
    "sg:tags":[
        "medical",
        "school"
    ],
    "wof:name":"The University of Glasgow",
    "wof:placetype":"venue"
},
  "geometry": {"coordinates":[-4.31248,55.90192],"type":"Point"}
}