{
  "type": "Feature",
  "properties": {
    "addr:full":"Ravenswood, Forth Lanark South Lanarkshire ML11 8DN",
    "addr:postcode":"ml11 8dn",
    "addr:street":"Forth",
    "iso:country":"GB",
    "sg:address":"Ravenswood, Forth",
    "sg:city":"Lanark",
    "sg:classifiers":[
        {
            "category":"Home & Garden",
            "subcategory":"Garden Supply",
            "type":"Retail Goods"
        }
    ],
    "sg:phone":"+44 1555 666888",
    "sg:postcode":"ML11 8DN",
    "sg:province":"South Lanarkshire",
    "sg:tags":[
        "tree",
        "shrub"
    ],
    "wof:name":"Plantkraft Nurseries",
    "wof:placetype":"venue"
},
  "geometry": {"coordinates":[-3.6883490086,55.7654800415],"type":"Point"}
}