{
  "type": "Feature",
  "properties": {
    "iso:country":"GB",
    "sg:address":"84 Meadrow",
    "sg:city":"Godalming",
    "sg:classifiers":[
        {
            "category":"Professional",
            "subcategory":"Lawyer & Legal Services",
            "type":"Services"
        }
    ],
    "sg:phone":"+44 1483 416134",
    "sg:postcode":"GU7 3HT",
    "sg:province":"Surrey",
    "sg:tags":[
        "solicitor"
    ],
    "wof:name":"Layard Horsfall",
    "wof:placetype":"venue"
},
  "geometry": {"coordinates":[-0.599665,51.192696],"type":"Point"}
}