{
  "type": "Feature",
  "properties": {
    "addr:full":"44 Briardale Rd, Little Sutton Ellesmere Port Cheshire CH66 1QB",
    "addr:housenumber":"44",
    "addr:postcode":"ch66 1qb",
    "addr:street":"Briardale Rd",
    "iso:country":"GB",
    "sg:address":"44 Briardale Rd, Little Sutton",
    "sg:city":"Ellesmere Port",
    "sg:classifiers":[
        {
            "category":"Manufacturing",
            "subcategory":"Food",
            "type":"Manufacturing & Wholesale Goods"
        }
    ],
    "sg:phone":"+44 151 339 1938",
    "sg:postcode":"CH66 1QB",
    "sg:province":"Cheshire",
    "sg:tags":[
        "technologist"
    ],
    "wof:name":"Euro-pharm",
    "wof:placetype":"venue"
},
  "geometry": {"coordinates":[-2.9408249855,53.2840614319],"type":"Point"}
}