{
  "type": "Feature",
  "properties": {
    "addr:full":"36-38 Eastern Esplanade Southend-on-sea Essex SS1 2ES",
    "addr:housenumber":"36-38",
    "addr:postcode":"ss1 2es",
    "addr:street":"Eastern Esplanade",
    "iso:country":"GB",
    "sg:address":"36-38 Eastern Esplanade",
    "sg:city":"Southend-on-sea",
    "sg:classifiers":[
        {
            "category":"Manufacturing",
            "subcategory":"Retail Goods",
            "type":"Manufacturing & Wholesale Goods"
        }
    ],
    "sg:phone":"+44 1702 444444",
    "sg:postcode":"SS1 2ES",
    "sg:province":"Essex",
    "sg:tags":[
        "chandler"
    ],
    "wof:name":"Shoreline (Yachtsman) Ltd.",
    "wof:placetype":"venue"
},
  "geometry": {"coordinates":[0.7276819944,51.5315742493],"type":"Point"}
}