{
  "type": "Feature",
  "properties": {
    "iso:country":"GB",
    "sg:address":"Pound Cottage, Alhampton Shepton Mallet",
    "sg:city":"Shepton Mallet",
    "sg:classifiers":[
        {
            "category":"Professional",
            "subcategory":"Secretarial Services",
            "type":"Services"
        }
    ],
    "sg:phone":"+44 1749 860558",
    "sg:postcode":"BA4 6PY",
    "sg:province":"Somerset",
    "wof:name":"Text",
    "wof:placetype":"venue"
},
  "geometry": {"coordinates":[-2.533733,51.1115],"type":"Point"}
}