{
  "type": "Feature",
  "properties": {
    "addr:full":"33a Oxford Rd Oxford Oxfordshire OX4 4PF",
    "addr:housenumber":"33a",
    "addr:postcode":"ox4 4pf",
    "addr:street":"Oxford Rd",
    "iso:country":"GB",
    "sg:address":"33a Oxford Rd",
    "sg:city":"Oxford",
    "sg:classifiers":[
        {
            "category":"Building & Trades",
            "subcategory":"Landscaping Services",
            "type":"Services"
        }
    ],
    "sg:phone":"+44 1865 771424",
    "sg:postcode":"OX4 4PF",
    "sg:province":"Oxfordshire",
    "sg:tags":[
        "gardening"
    ],
    "wof:name":"Beaver Gardening",
    "wof:placetype":"venue"
},
  "geometry": {"coordinates":[-1.224218,51.722069],"type":"Point"}
}