{
  "type": "Feature",
  "properties": {
    "addr:full":"Grasmere Crescent, Eccles Manchester Greater Manchester M30 8DN",
    "addr:postcode":"m30 8dn",
    "addr:street":"Grasmere Crescent",
    "iso:country":"GB",
    "sg:address":"Grasmere Crescent, Eccles",
    "sg:city":"Manchester",
    "sg:classifiers":[
        {
            "category":"Community Center",
            "type":"Public Place"
        }
    ],
    "sg:phone":"+44 161 789 2233",
    "sg:postcode":"M30 8DN",
    "sg:province":"Greater Manchester",
    "sg:tags":[
        "centre"
    ],
    "wof:name":"Westwood Park Community Centre Playgroup",
    "wof:placetype":"venue"
},
  "geometry": {"coordinates":[-2.367463,53.4935],"type":"Point"}
}