{
  "type": "Feature",
  "properties": {
    "addr:full":"16 Borrowdale Close, Gunthorpe Peterborough Cambridgeshire PE4 7YA",
    "addr:housenumber":"16",
    "addr:postcode":"pe4 7ya",
    "addr:street":"Borrowdale Close",
    "iso:country":"GB",
    "sg:address":"16 Borrowdale Close, Gunthorpe",
    "sg:city":"Peterborough",
    "sg:classifiers":[
        {
            "category":"Professional",
            "subcategory":"Detective & Security Services",
            "type":"Services"
        }
    ],
    "sg:phone":"+44 1733 709666",
    "sg:postcode":"PE4 7YA",
    "sg:province":"Cambridgeshire",
    "sg:tags":[
        "locksmith"
    ],
    "wof:name":"Open-Ups",
    "wof:placetype":"venue"
},
  "geometry": {"coordinates":[-0.2530269921,52.6150550842],"type":"Point"}
}