{
  "type": "Feature",
  "properties": {
    "iso:country":"GB",
    "sg:address":"25 Acres Rd",
    "sg:city":"Manchester",
    "sg:classifiers":[
        {
            "category":"Real Estate",
            "subcategory":"Surveying",
            "type":"Services"
        }
    ],
    "sg:postcode":"M21 9EB",
    "sg:province":"Cheshire",
    "sg:tags":[
        "surveyor",
        "quantity"
    ],
    "wof:name":"Calder,Roy W,",
    "wof:placetype":"venue"
},
  "geometry": {"coordinates":[-2.279499,53.439781],"type":"Point"}
}