{
  "type": "Feature",
  "properties": {
    "iso:country":"GB",
    "sg:address":"Old Boywood Farm, West Lane, Hazelbury Bryan",
    "sg:city":"Sturminster Newton",
    "sg:classifiers":[
        {
            "category":"Farming",
            "subcategory":"Livestock Farm",
            "type":"Manufacturing & Wholesale Goods"
        }
    ],
    "sg:phone":"+44 1258 817456",
    "sg:postcode":"DT10 2BQ",
    "sg:province":"Dorset",
    "sg:tags":[
        "others"
    ],
    "wof:name":"R J & P Cake",
    "wof:placetype":"venue"
},
  "geometry": {"coordinates":[-2.357865,50.87616],"type":"Point"}
}