{
  "type": "Feature",
  "properties": {
    "addr:full":"Springhill House, Pilgrims Way Westerham Kent TN16 2DU",
    "addr:postcode":"tn16 2du",
    "addr:street":"Pilgrims Way",
    "iso:country":"GB",
    "sg:address":"Springhill House, Pilgrims Way",
    "sg:city":"Westerham",
    "sg:classifiers":[
        {
            "category":"Professional",
            "subcategory":"Management & Consulting",
            "type":"Services"
        }
    ],
    "sg:postcode":"TN16 2DU",
    "sg:province":"Kent",
    "sg:tags":[
        "marketing",
        "consultant"
    ],
    "wof:name":"Mks Marketing Solutions Ltd",
    "wof:placetype":"venue"
},
  "geometry": {"coordinates":[0.078089,51.284409],"type":"Point"}
}