{
  "type": "Feature",
  "properties": {
    "iso:country":"GB",
    "sg:address":"Unit 28-29 Four Seasons Centre",
    "sg:city":"Mansfield",
    "sg:classifiers":[
        {
            "category":"Shopping",
            "subcategory":"Clothing, Apparel, & Fashions",
            "type":"Retail Goods"
        }
    ],
    "sg:phone":"+44 1623 624001",
    "sg:postcode":"NG18 1SU",
    "sg:province":"Nottinghamshire",
    "sg:tags":[
        "menswear"
    ],
    "wof:name":"Topshop",
    "wof:placetype":"venue"
},
  "geometry": {"coordinates":[-1.201743,53.144024],"type":"Point"}
}