{
  "type": "Feature",
  "properties": {
    "addr:full":"Bankhouse Farm, Audley Rd Stoke On Trent Cheshire ST7 2UH",
    "addr:postcode":"st7 2uh",
    "addr:street":"Audley Rd",
    "iso:country":"GB",
    "sg:address":"Bankhouse Farm, Audley Rd",
    "sg:city":"Stoke On Trent",
    "sg:classifiers":[
        {
            "category":"Farming",
            "subcategory":"Livestock Farm",
            "type":"Manufacturing & Wholesale Goods"
        }
    ],
    "sg:phone":"+44 1270 872446",
    "sg:postcode":"ST7 2UH",
    "sg:province":"Cheshire",
    "sg:tags":[
        "others"
    ],
    "wof:name":"E J Morris & Son",
    "wof:placetype":"venue"
},
  "geometry": {"coordinates":[-2.3067400455,53.0877914429],"type":"Point"}
}