{
  "type": "Feature",
  "properties": {
    "iso:country":"GB",
    "sg:address":"Unit 24c Airfield Indstl Est",
    "sg:city":"Stafford",
    "sg:classifiers":[
        {
            "category":"Shopping",
            "subcategory":"Books",
            "type":"Retail Goods"
        }
    ],
    "sg:postcode":"ST18 0PF",
    "sg:province":"Staffordshire",
    "wof:name":"Grandreams Ltd",
    "wof:placetype":"venue"
},
  "geometry": {"coordinates":[-2.0024991035,52.8327102661],"type":"Point"}
}