{
  "type": "Feature",
  "properties": {
    "iso:country":"GB",
    "sg:address":"Ulverston Health Centre, Victoria Rd",
    "sg:city":"Ulverston",
    "sg:classifiers":[
        {
            "category":"Health Services",
            "subcategory":"Doctor",
            "type":"Services"
        }
    ],
    "sg:phone":"+44 1229 583732",
    "sg:postcode":"LA12 0EW",
    "sg:province":"Cumbria",
    "sg:tags":[
        "practitioners"
    ],
    "wof:name":"Brice, J A R",
    "wof:placetype":"venue"
},
  "geometry": {"coordinates":[-3.092354,54.196732],"type":"Point"}
}