{
  "type": "Feature",
  "properties": {
    "addr:full":"130 High Street Orpington Kent BR6 0JS",
    "addr:housenumber":"130",
    "addr:postcode":"br6 0js",
    "addr:street":"High Street",
    "iso:country":"GB",
    "sg:address":"130 High Street",
    "sg:city":"Orpington",
    "sg:classifiers":[
        {
            "category":"Fast Food",
            "type":"Food & Drink"
        }
    ],
    "sg:postcode":"BR6 0JS",
    "sg:province":"Kent",
    "sg:tags":[
        "away",
        "take"
    ],
    "wof:name":"Greatvalue Ltd",
    "wof:placetype":"venue"
},
  "geometry": {"coordinates":[0.1013910025,51.3785934448],"type":"Point"}
}