{
  "type": "Feature",
  "properties": {
    "iso:country":"GB",
    "sg:address":"38 Woodhead Road",
    "sg:city":"Huddersfield",
    "sg:classifiers":[
        {
            "category":"Bars & Pubs",
            "type":"Food & Drink"
        }
    ],
    "sg:phone":"+44 1484 683673",
    "sg:postcode":"HD9 2PR",
    "sg:province":"South Yorkshire",
    "sg:tags":[
        "pubs",
        "inn"
    ],
    "wof:name":"Victoria Inn",
    "wof:placetype":"venue"
},
  "geometry": {"coordinates":[-1.797134,53.629887],"type":"Point"}
}