{
  "type": "Feature",
  "properties": {
    "addr:full":"Haywards Yard, Brockley Road London Greater London SE4 1EJ",
    "addr:postcode":"se4 1ej",
    "addr:street":"Brockley Road",
    "iso:country":"GB",
    "sg:address":"Haywards Yard, Brockley Road",
    "sg:city":"London",
    "sg:classifiers":[
        {
            "category":"Manufacturing",
            "subcategory":"Building Materials",
            "type":"Manufacturing & Wholesale Goods"
        }
    ],
    "sg:phone":"+44 20 8692 5638",
    "sg:postcode":"SE4 1EJ",
    "sg:province":"Greater London",
    "sg:tags":[
        "mnfr",
        "marble",
        "specialist"
    ],
    "wof:name":"Tudor (Architectural Masons) Ltd.",
    "wof:placetype":"venue"
},
  "geometry": {"coordinates":[-0.0342100002,51.4545097351],"type":"Point"}
}