{
  "type": "Feature",
  "properties": {
    "iso:country":"GB",
    "sg:address":"21 Windsor Rd, Huyton-with-roby",
    "sg:city":"Liverpool",
    "sg:classifiers":[
        {
            "category":"Building & Trades",
            "subcategory":"Cleaning & Sanitation",
            "type":"Services"
        }
    ],
    "sg:postcode":"L36 4NQ",
    "sg:province":"Merseyside",
    "sg:tags":[
        "commercial"
    ],
    "wof:name":"Houghton,N,",
    "wof:placetype":"venue"
},
  "geometry": {"coordinates":[-2.866368,53.41243],"type":"Point"}
}