{
  "type": "Feature",
  "properties": {
    "addr:full":"84 Ballindean Road Dundee Dundee City DD4 8NU",
    "addr:housenumber":"84",
    "addr:postcode":"dd4 8nu",
    "addr:street":"Ballindean Road",
    "iso:country":"GB",
    "sg:address":"84 Ballindean Road",
    "sg:city":"Dundee",
    "sg:classifiers":[
        {
            "category":"Government",
            "subcategory":"Post Office",
            "type":"Public Place"
        }
    ],
    "sg:phone":"+44 1382 502109",
    "sg:postcode":"DD4 8NU",
    "sg:province":"Dundee City",
    "wof:name":"Ballindean Road Sub Post Office",
    "wof:placetype":"venue"
},
  "geometry": {"coordinates":[-2.9159319401,56.4802627563],"type":"Point"}
}