{
  "type": "Feature",
  "properties": {
    "iso:country":"GB",
    "sg:address":"Rollesby Road",
    "sg:city":"King's Lynn",
    "sg:classifiers":[
        {
            "category":"Shopping",
            "subcategory":"Computers & Home Electronics",
            "type":"Retail Goods"
        }
    ],
    "sg:phone":"+44 1553 760822",
    "sg:postcode":"PE30 4DX",
    "sg:province":"Norfolk",
    "sg:tags":[
        "electrical"
    ],
    "wof:name":"City Electrical Factors Ltd.",
    "wof:placetype":"venue"
},
  "geometry": {"coordinates":[0.42228,52.745628],"type":"Point"}
}