{
  "type": "Feature",
  "properties": {
    "addr:full":"470a Tong Rd Leeds West Yorkshire LS12 5AU",
    "addr:housenumber":"470a",
    "addr:postcode":"ls12 5au",
    "addr:street":"Tong Rd",
    "iso:country":"GB",
    "sg:address":"470a Tong Rd",
    "sg:city":"Leeds",
    "sg:classifiers":[
        {
            "category":"Professional",
            "subcategory":"Lawyer & Legal Services",
            "type":"Services"
        }
    ],
    "sg:phone":"+44 113 263 1832",
    "sg:postcode":"LS12 5AU",
    "sg:province":"West Yorkshire",
    "sg:tags":[
        "advice",
        "counselling"
    ],
    "wof:name":"Stroke Association Dysphasia Support",
    "wof:placetype":"venue"
},
  "geometry": {"coordinates":[-1.620906949,53.7921333313],"type":"Point"}
}