{
  "type": "Feature",
  "properties": {
    "addr:full":"Merriscourt House, Merriscourt, Churchill Chipping Norton Gloucestershire OX7 6QX",
    "addr:postcode":"ox7 6qx",
    "addr:street":"Merriscourt Churchill",
    "iso:country":"GB",
    "sg:address":"Merriscourt House, Merriscourt, Churchill",
    "sg:city":"Chipping Norton",
    "sg:classifiers":[
        {
            "category":"Wholesale",
            "subcategory":"Scrap",
            "type":"Manufacturing & Wholesale Goods"
        }
    ],
    "sg:postcode":"OX7 6QX",
    "sg:province":"Gloucestershire",
    "sg:tags":[
        "waste",
        "metal"
    ],
    "wof:name":"St Albans Recycling Ltd",
    "wof:placetype":"venue"
},
  "geometry": {"coordinates":[-1.591438,51.912914],"type":"Point"}
}