{
  "type": "Feature",
  "properties": {
    "addr:full":"Moorcroft House, Maldon Road Chelmsford Essex CM3 2JP",
    "addr:postcode":"cm3 2jp",
    "addr:street":"Maldon Road",
    "iso:country":"GB",
    "sg:address":"Moorcroft House, Maldon Road",
    "sg:city":"Chelmsford",
    "sg:classifiers":[
        {
            "category":"Professional",
            "subcategory":"Accounting & Tax Preparation",
            "type":"Services"
        }
    ],
    "sg:postcode":"CM3 2JP",
    "sg:province":"Essex",
    "sg:tags":[
        "accountant"
    ],
    "wof:name":"Options Business Services",
    "wof:placetype":"venue"
},
  "geometry": {"coordinates":[0.6187130213,51.7682762146],"type":"Point"}
}