{
  "type": "Feature",
  "properties": {
    "iso:country":"GB",
    "sg:address":"Comet Dr",
    "sg:city":"Shrewsbury",
    "sg:classifiers":[
        {
            "category":"Place Of Worship",
            "type":"Public Place"
        }
    ],
    "sg:phone":"+44 1743 245939",
    "sg:postcode":"SY1 4AX",
    "sg:province":"Shropshire",
    "wof:name":"Church of Jesus Christ of Latter Day Saints",
    "wof:placetype":"venue"
},
  "geometry": {"coordinates":[-2.737254,52.724312],"type":"Point"}
}