{
  "type": "Feature",
  "properties": {
    "addr:full":"Care Of Seaton School, Valley View Road Seaton Devon EX12 2HF",
    "addr:postcode":"ex12 2hf",
    "addr:street":"Valley View Road",
    "iso:country":"GB",
    "sg:address":"Care Of Seaton School, Valley View Road",
    "sg:city":"Seaton",
    "sg:classifiers":[
        {
            "category":"Education",
            "subcategory":"Preschool",
            "type":"Public Place"
        }
    ],
    "sg:phone":"+44 1297 625621",
    "sg:postcode":"EX12 2HF",
    "sg:province":"Devon",
    "sg:tags":[
        "pre",
        "school",
        "playgroups",
        "pre-school"
    ],
    "wof:name":"Ruperts under 5s",
    "wof:placetype":"venue"
},
  "geometry": {"coordinates":[-3.075809,50.70454],"type":"Point"}
}