{
  "type": "Feature",
  "properties": {
    "addr:full":"94c High Street Uckfield East Sussex TN22 1PU",
    "addr:housenumber":"94c",
    "addr:postcode":"tn22 1pu",
    "addr:street":"High Street",
    "iso:country":"GB",
    "sg:address":"94c High Street",
    "sg:city":"Uckfield",
    "sg:classifiers":[
        {
            "category":"Shopping",
            "subcategory":"Clothing, Apparel, & Fashions",
            "type":"Retail Goods"
        }
    ],
    "sg:postcode":"TN22 1PU",
    "sg:province":"East Sussex",
    "sg:tags":[
        "shop"
    ],
    "wof:name":"Berenice",
    "wof:placetype":"venue"
},
  "geometry": {"coordinates":[0.096042,50.969383],"type":"Point"}
}