{
  "type": "Feature",
  "properties": {
    "addr:full":"186 Queensway Rochdale Lancashire OL11 1TU",
    "addr:housenumber":"186",
    "addr:postcode":"ol11 1tu",
    "addr:street":"Queensway Rochdale",
    "iso:country":"GB",
    "sg:address":"186 Queensway",
    "sg:city":"Rochdale",
    "sg:classifiers":[
        {
            "category":"Shopping",
            "subcategory":"Department Store",
            "type":"Retail Goods"
        }
    ],
    "sg:phone":"+44 1706 649142",
    "sg:postcode":"OL11 1TU",
    "sg:province":"Lancashire",
    "wof:name":"R Goodall",
    "wof:placetype":"venue"
},
  "geometry": {"coordinates":[-2.1584689617,53.6006126404],"type":"Point"}
}