{
  "type": "Feature",
  "properties": {
    "addr:full":"Park Buildings Hill, Top West Bromwich West Midlands B70 0RZ",
    "addr:postcode":"b70 0rz",
    "addr:street":"Park Buildings;Top",
    "iso:country":"GB",
    "sg:address":"Park Buildings Hill, Top",
    "sg:city":"West Bromwich",
    "sg:classifiers":[
        {
            "category":"Education",
            "subcategory":"Library",
            "type":"Public Place"
        }
    ],
    "sg:phone":"+44 121 556 0605",
    "sg:postcode":"B70 0RZ",
    "sg:province":"West Midlands",
    "sg:tags":[
        "book"
    ],
    "wof:name":"Hill Top Library",
    "wof:placetype":"venue"
},
  "geometry": {"coordinates":[-2.01116395,52.5367393494],"type":"Point"}
}