{
  "type": "Feature",
  "properties": {
    "addr:full":"Boslowen, Nancledra Penzance Cornwall TR20 8NB",
    "addr:postcode":"tr20 8nb",
    "iso:country":"GB",
    "sg:address":"Boslowen, Nancledra",
    "sg:city":"Penzance",
    "sg:classifiers":[
        {
            "category":"Building & Trades",
            "subcategory":"Equipment Rental",
            "type":"Services"
        }
    ],
    "sg:postcode":"TR20 8NB",
    "sg:province":"Cornwall",
    "sg:tags":[
        "plant",
        "machinery"
    ],
    "wof:name":"Neil O'Connor",
    "wof:placetype":"venue"
},
  "geometry": {"coordinates":[-5.5080771446,50.1707229614],"type":"Point"}
}