{
  "type": "Feature",
  "properties": {
    "iso:country":"GB",
    "sg:address":"Keyhaven",
    "sg:city":"Lymington",
    "sg:classifiers":[
        {
            "category":"Organizations",
            "subcategory":"Membership Organization",
            "type":"Services"
        }
    ],
    "sg:phone":"+44 1590 645589",
    "sg:postcode":"SO41 0TP",
    "sg:province":"Hampshire",
    "sg:tags":[
        "club"
    ],
    "wof:name":"Hurst Castle Sailing Club",
    "wof:placetype":"venue"
},
  "geometry": {"coordinates":[-1.56765,50.721378],"type":"Point"}
}