{
  "type": "Feature",
  "properties": {
    "iso:country":"GB",
    "sg:address":"576 Ashton Road",
    "sg:city":"Oldham",
    "sg:classifiers":[
        {
            "category":"Food & Beverages",
            "subcategory":"Bakery",
            "type":"Retail Goods"
        }
    ],
    "sg:postcode":"OL8 3HW",
    "sg:province":"Lancashire",
    "sg:tags":[
        "shop",
        "baker"
    ],
    "wof:name":"F WARDLE",
    "wof:placetype":"venue"
},
  "geometry": {"coordinates":[-2.11001,53.52103],"type":"Point"}
}