{
  "type": "Feature",
  "properties": {
    "addr:full":"104 Station Road, Countesthorpe Leicester Leicestershire LE8 5TD",
    "addr:housenumber":"104",
    "addr:postcode":"le8 5td",
    "addr:street":"Station Road",
    "iso:country":"GB",
    "sg:address":"104 Station Road, Countesthorpe",
    "sg:city":"Leicester",
    "sg:classifiers":[
        {
            "category":"Building & Trades",
            "subcategory":"Plumbing",
            "type":"Services"
        }
    ],
    "sg:phone":"+44 116 247 7700",
    "sg:postcode":"LE8 5TD",
    "sg:province":"Leicestershire",
    "sg:tags":[
        "drain",
        "clearance",
        "sewer"
    ],
    "wof:name":"Drain Surgeons",
    "wof:placetype":"venue"
},
  "geometry": {"coordinates":[-1.147314,52.553509],"type":"Point"}
}