{
  "type": "Feature",
  "properties": {
    "addr:full":"68 Grosvenor Road Aldershot Hampshire GU11 3EA",
    "addr:housenumber":"68",
    "addr:postcode":"gu11 3ea",
    "addr:street":"Grosvenor Road",
    "iso:country":"GB",
    "sg:address":"68 Grosvenor Road",
    "sg:city":"Aldershot",
    "sg:classifiers":[
        {
            "category":"Fast Food",
            "type":"Food & Drink"
        }
    ],
    "sg:phone":"+44 1252 320330",
    "sg:postcode":"GU11 3EA",
    "sg:province":"Hampshire",
    "sg:tags":[
        "away",
        "meal",
        "outlet",
        "take"
    ],
    "wof:name":"The Oriental Kitchen",
    "wof:placetype":"venue"
},
  "geometry": {"coordinates":[-0.766241014,51.2464675903],"type":"Point"}
}