{
  "type": "Feature",
  "properties": {
    "addr:full":"60 Galmington Rd Taunton Somerset TA1 5NZ",
    "addr:housenumber":"60",
    "addr:postcode":"ta1 5nz",
    "addr:street":"Galmington Rd",
    "iso:country":"GB",
    "sg:address":"60 Galmington Rd",
    "sg:city":"Taunton",
    "sg:classifiers":[
        {
            "category":"Shopping",
            "subcategory":"Pets & Pet Supplies",
            "type":"Retail Goods"
        }
    ],
    "sg:phone":"+44 1823 351700",
    "sg:postcode":"TA1 5NZ",
    "sg:province":"Somerset",
    "wof:name":"HEADS & TAILS PET SUPPLIES",
    "wof:placetype":"venue"
},
  "geometry": {"coordinates":[-3.124791,51.008137],"type":"Point"}
}