{
  "type": "Feature",
  "properties": {
    "addr:full":"Top Lodge, Norton Bromyard Herefordshire HR7 4PQ",
    "addr:postcode":"hr7 4pq",
    "iso:country":"GB",
    "sg:address":"Top Lodge, Norton",
    "sg:city":"Bromyard",
    "sg:classifiers":[
        {
            "category":"Professional",
            "subcategory":"Art Services",
            "type":"Services"
        }
    ],
    "sg:phone":"+44 1885 488273",
    "sg:postcode":"HR7 4PQ",
    "sg:province":"Herefordshire",
    "sg:tags":[
        "framing"
    ],
    "wof:name":"Wyeland Picture Framing Services",
    "wof:placetype":"venue"
},
  "geometry": {"coordinates":[-2.5103991032,52.1890983582],"type":"Point"}
}