{
  "type": "Feature",
  "properties": {
    "addr:full":"4 Church Street Llangefni Gwynedd LL77 7DU",
    "addr:housenumber":"4",
    "addr:postcode":"ll77 7du",
    "addr:street":"Church Street",
    "iso:country":"GB",
    "sg:address":"4 Church Street",
    "sg:city":"Llangefni",
    "sg:classifiers":[
        {
            "category":"Shopping",
            "subcategory":"Mobile Phones",
            "type":"Retail Goods"
        }
    ],
    "sg:phone":"+44 1248 722270",
    "sg:postcode":"LL77 7DU",
    "sg:province":"Gwynedd",
    "wof:name":"Bayline Sysytems",
    "wof:placetype":"venue"
},
  "geometry": {"coordinates":[-4.3113718033,53.2572097778],"type":"Point"}
}