{
  "type": "Feature",
  "properties": {
    "iso:country":"GB",
    "sg:address":"Unit 7 Ghyll Industrial Estate",
    "sg:city":"Heathfield",
    "sg:classifiers":[
        {
            "category":"Manufacturing",
            "subcategory":"Tools & Machinery",
            "type":"Manufacturing & Wholesale Goods"
        }
    ],
    "sg:phone":"+44 1435 868869",
    "sg:postcode":"TN21 8AW",
    "sg:province":"East Sussex",
    "wof:name":"Tamco Ltd",
    "wof:placetype":"venue"
},
  "geometry": {"coordinates":[0.2516050041,50.961856842],"type":"Point"}
}