{
  "type": "Feature",
  "properties": {
    "addr:full":"4 St Pauls Rd Newton Abbot Devon TQ12 2HP",
    "addr:housenumber":"4",
    "addr:postcode":"tq12 2hp",
    "addr:street":"St Pauls Rd",
    "iso:country":"GB",
    "sg:address":"4 St Pauls Rd",
    "sg:city":"Newton Abbot",
    "sg:classifiers":[
        {
            "category":"Health Services",
            "subcategory":"Dentist",
            "type":"Services"
        }
    ],
    "sg:phone":"+44 1626 365896",
    "sg:postcode":"TQ12 2HP",
    "sg:province":"Devon",
    "wof:name":"A M Stanley",
    "wof:placetype":"venue"
},
  "geometry": {"coordinates":[-3.603561,50.530495],"type":"Point"}
}