{
  "type": "Feature",
  "properties": {
    "addr:full":"9 Blackford Close South Croydon Surrey CR2 6BT",
    "addr:housenumber":"9",
    "addr:postcode":"cr2 6bt",
    "addr:street":"Blackford Close",
    "iso:country":"GB",
    "sg:address":"9 Blackford Close",
    "sg:city":"South Croydon",
    "sg:classifiers":[
        {
            "category":"Food & Beverages",
            "subcategory":"Liquor & Beverages",
            "type":"Retail Goods"
        }
    ],
    "sg:phone":"+44 20 8310 5097",
    "sg:postcode":"CR2 6BT",
    "sg:province":"Surrey",
    "sg:tags":[
        "beer",
        "spirit",
        "wines"
    ],
    "wof:name":"Glory Ltd.",
    "wof:placetype":"venue"
},
  "geometry": {"coordinates":[-0.1064589992,51.3499755859],"type":"Point"}
}