{
  "type": "Feature",
  "properties": {
    "addr:full":"71 School Rd, West Walton Wisbech Cambridgeshire PE14 7HA",
    "addr:housenumber":"71",
    "addr:postcode":"pe14 7ha",
    "addr:street":"School Rd West Walton",
    "iso:country":"GB",
    "sg:address":"71 School Rd, West Walton",
    "sg:city":"Wisbech",
    "sg:classifiers":[
        {
            "category":"Community Center",
            "subcategory":"Youth",
            "type":"Public Place"
        },
        {
            "category":"Government",
            "subcategory":"Office",
            "type":"Public Place"
        }
    ],
    "sg:phone":"+44 1945 461299",
    "sg:postcode":"PE14 7HA",
    "sg:province":"Cambridgeshire",
    "sg:tags":[
        "organisation",
        "local",
        "centre"
    ],
    "wof:name":"Norfolk County Council",
    "wof:placetype":"venue"
},
  "geometry": {"coordinates":[0.183808,52.695518],"type":"Point"}
}