{
  "type": "Feature",
  "properties": {
    "addr:full":"Unit 7 Ventura Retail Park, Bonehill Road Tamworth Staffordshire B78 3HB",
    "addr:housenumber":"unit 7",
    "addr:postcode":"b78 3hb",
    "addr:street":"Ventura Retail Park Bonehill Road",
    "iso:country":"GB",
    "sg:address":"Unit 7 Ventura Retail Park, Bonehill Road",
    "sg:city":"Tamworth",
    "sg:classifiers":[
        {
            "category":"Shopping",
            "subcategory":"Clothing, Apparel, & Fashions",
            "type":"Retail Goods"
        }
    ],
    "sg:phone":"+44 1827 50900",
    "sg:postcode":"B78 3HB",
    "sg:province":"Staffordshire",
    "sg:tags":[
        "shop"
    ],
    "wof:name":"Matalan Store",
    "wof:placetype":"venue"
},
  "geometry": {"coordinates":[-1.703579,52.626694],"type":"Point"}
}