{
  "type": "Feature",
  "properties": {
    "addr:full":"93 Corporation St Birmingham West Midlands B2 4UG",
    "addr:housenumber":"93",
    "addr:postcode":"4ug",
    "addr:street":"Corporation St",
    "iso:country":"GB",
    "sg:address":"93 Corporation St",
    "sg:city":"Birmingham",
    "sg:classifiers":[
        {
            "category":"Home & Garden",
            "subcategory":"Kitchen Supply",
            "type":"Retail Goods"
        }
    ],
    "sg:phone":"+44 121 236 0440",
    "sg:postcode":"B2 4UG",
    "sg:province":"West Midlands",
    "sg:tags":[
        "glassware",
        "china"
    ],
    "wof:name":"Pottery Plus",
    "wof:placetype":"venue"
},
  "geometry": {"coordinates":[-1.8965229988,52.4805526733],"type":"Point"}
}