{
  "type": "Feature",
  "properties": {
    "iso:country":"GB",
    "sg:address":"35 Storth Park, Fulwood Road",
    "sg:city":"Sheffield",
    "sg:classifiers":[
        {
            "category":"Shopping",
            "subcategory":"Musical Instruments",
            "type":"Retail Goods"
        }
    ],
    "sg:phone":"+44 114 263 0121",
    "sg:postcode":"S10 3QH",
    "sg:province":"South Yorkshire",
    "sg:tags":[
        "piano",
        "tuning",
        "maintenance"
    ],
    "wof:name":"C P Fox",
    "wof:placetype":"venue"
},
  "geometry": {"coordinates":[-1.529817,53.370663],"type":"Point"}
}