{
  "type": "Feature",
  "properties": {
    "addr:full":"Littlefield La Grimsby Lincolnshire DN34 4PS",
    "addr:postcode":"dn34 4ps",
    "addr:street":"La Grimsby",
    "iso:country":"GB",
    "sg:address":"Littlefield La",
    "sg:city":"Grimsby",
    "sg:classifiers":[
        {
            "category":"Bars & Pubs",
            "type":"Food & Drink"
        }
    ],
    "sg:phone":"+44 1472 343016",
    "sg:postcode":"DN34 4PS",
    "sg:province":"Lincolnshire",
    "sg:tags":[
        "pubs",
        "inn"
    ],
    "wof:name":"Punch Retail Ltd",
    "wof:placetype":"venue"
},
  "geometry": {"coordinates":[-0.0966340005,53.5635986328],"type":"Point"}
}