{
  "type": "Feature",
  "properties": {
    "addr:full":"18 Tweed Road Northampton Northamptonshire NN5 5AJ",
    "addr:housenumber":"18",
    "addr:postcode":"nn5 5aj",
    "addr:street":"Tweed Road",
    "iso:country":"GB",
    "sg:address":"18 Tweed Road",
    "sg:city":"Northampton",
    "sg:classifiers":[
        {
            "category":"Shopping",
            "subcategory":"Computers & Home Electronics",
            "type":"Retail Goods"
        }
    ],
    "sg:phone":"+44 1604 582000",
    "sg:postcode":"NN5 5AJ",
    "sg:province":"Northamptonshire",
    "sg:tags":[
        "sales",
        "system",
        "software"
    ],
    "sg:website":"http://www.milenium.co.uk",
    "wof:name":"Milenium Computers Ltd",
    "wof:placetype":"venue"
},
  "geometry": {"coordinates":[-0.929488,52.238689],"type":"Point"}
}