{
  "type": "Feature",
  "properties": {
    "iso:country":"GB",
    "sg:address":"45 London Road",
    "sg:city":"King's Lynn",
    "sg:classifiers":[
        {
            "category":"Shopping",
            "subcategory":"Stationery & Office Supplies",
            "type":"Retail Goods"
        }
    ],
    "sg:postcode":"PE30 5QH",
    "sg:province":"Norfolk",
    "sg:tags":[
        "equipment"
    ],
    "wof:name":"West Norfolk Office Supplies",
    "wof:placetype":"venue"
},
  "geometry": {"coordinates":[0.4024499953,52.7469787598],"type":"Point"}
}