{
  "type": "Feature",
  "properties": {
    "addr:full":"151a Clinton Lane Kenilworth Warwickshire CV8 1AY",
    "addr:housenumber":"151a",
    "addr:postcode":"cv8 1ay",
    "addr:street":"Clinton Lane",
    "iso:country":"GB",
    "sg:address":"151a Clinton Lane",
    "sg:city":"Kenilworth",
    "sg:classifiers":[
        {
            "category":"Building & Trades",
            "subcategory":"Construction",
            "type":"Services"
        }
    ],
    "sg:postcode":"CV8 1AY",
    "sg:province":"Warwickshire",
    "sg:tags":[
        "guttering",
        "glazier"
    ],
    "wof:name":"Guttering & Cleaning Services & Repairs",
    "wof:placetype":"venue"
},
  "geometry": {"coordinates":[-1.5929579735,52.3543891907],"type":"Point"}
}