{
  "type": "Feature",
  "properties": {
    "iso:country":"GB",
    "sg:address":"48 Elizabeth St",
    "sg:city":"Westminster",
    "sg:classifiers":[
        {
            "category":"Organizations",
            "subcategory":"Community Association",
            "type":"Services"
        }
    ],
    "sg:phone":"+44 20 7730 7425",
    "sg:postcode":"SW1W 9PA",
    "sg:province":"Greater London",
    "sg:tags":[
        "relation",
        "public"
    ],
    "wof:name":"M.C.P.R",
    "wof:placetype":"venue"
},
  "geometry": {"coordinates":[-0.14778,51.49255],"type":"Point"}
}