{
  "type": "Feature",
  "properties": {
    "iso:country":"GB",
    "sg:address":"54 Kirby Street",
    "sg:city":"Ipswich",
    "sg:classifiers":[
        {
            "category":"Organizations",
            "subcategory":"Community Association",
            "type":"Services"
        },
        {
            "category":"Organizations",
            "subcategory":"Membership Organization",
            "type":"Services"
        }
    ],
    "sg:phone":"+44 1473 728233",
    "sg:postcode":"IP4 4PT",
    "sg:province":"Suffolk",
    "sg:tags":[
        "club",
        "social"
    ],
    "wof:name":"St.John's Conservative & Constitutional Club",
    "wof:placetype":"venue"
},
  "geometry": {"coordinates":[1.184486,52.060642],"type":"Point"}
}