{
  "type": "Feature",
  "properties": {
    "iso:country":"GB",
    "sg:address":"Unit 4 Windmill Rd",
    "sg:city":"Loughborough",
    "sg:classifiers":[
        {
            "category":"Professional",
            "subcategory":"Advertising",
            "type":"Services"
        }
    ],
    "sg:postcode":"LE11 1RA",
    "sg:province":"Leicestershire",
    "wof:name":"Davies,Joan,",
    "wof:placetype":"venue"
},
  "geometry": {"coordinates":[-1.193289,52.767689],"type":"Point"}
}