{
  "type": "Feature",
  "properties": {
    "addr:full":"48 Monks Way Nottingham Nottinghamshire NG11 7FH",
    "addr:housenumber":"48",
    "addr:postcode":"ng11 7fh",
    "addr:street":"Monks Way",
    "iso:country":"GB",
    "sg:address":"48 Monks Way",
    "sg:city":"Nottingham",
    "sg:classifiers":[
        {
            "category":"Personal",
            "subcategory":"Beauty Salon",
            "type":"Services"
        },
        {
            "category":"Personal",
            "subcategory":"Barber",
            "type":"Services"
        }
    ],
    "sg:phone":"+44 115 981 9112",
    "sg:postcode":"NG11 7FH",
    "sg:province":"Nottinghamshire",
    "sg:tags":[
        "unisex",
        "hairdresser"
    ],
    "wof:name":"Young Hairstyles",
    "wof:placetype":"venue"
},
  "geometry": {"coordinates":[-1.163559,52.914871],"type":"Point"}
}