{
  "type": "Feature",
  "properties": {
    "addr:full":"Astley Hall Farm House, Hall Gate, Astley Village Chorley Lancashire PR7 1XA",
    "addr:postcode":"lancashire pr7 1xa",
    "addr:street":"Hall Gate",
    "iso:country":"GB",
    "sg:address":"Astley Hall Farm House, Hall Gate, Astley Village",
    "sg:city":"Chorley",
    "sg:classifiers":[
        {
            "category":"Organizations",
            "subcategory":"Non-profit Organization",
            "type":"Services"
        }
    ],
    "sg:phone":"+44 1257 263254",
    "sg:postcode":"PR7 1XA",
    "sg:province":"Lancashire",
    "sg:tags":[
        "organisation",
        "voluntary",
        "charity"
    ],
    "wof:name":"Chorley & South Ribble Council for Vouluntary Service",
    "wof:placetype":"venue"
},
  "geometry": {"coordinates":[-2.6449959278,53.6622543335],"type":"Point"}
}