{
  "type": "Feature",
  "properties": {
    "iso:country":"GB",
    "sg:address":"5 High March",
    "sg:city":"Daventry",
    "sg:classifiers":[
        {
            "category":"Professional",
            "subcategory":"Business Services",
            "type":"Services"
        }
    ],
    "sg:phone":"+44 1327 704767",
    "sg:postcode":"NN11 4QE",
    "sg:province":"Northamptonshire",
    "sg:tags":[
        "holding"
    ],
    "wof:name":"Rediweld 2003 Ltd.",
    "wof:placetype":"venue"
},
  "geometry": {"coordinates":[-1.149655,52.247124],"type":"Point"}
}