{
  "type": "Feature",
  "properties": {
    "addr:full":"216 Marton Road Middlesbrough North Yorkshire TS4 2ET",
    "addr:housenumber":"216",
    "addr:postcode":"ts4 2et",
    "addr:street":"Marton Road",
    "iso:country":"GB",
    "sg:address":"216 Marton Road",
    "sg:city":"Middlesbrough",
    "sg:classifiers":[
        {
            "category":"Health Services",
            "subcategory":"Health Practitioner",
            "type":"Services"
        }
    ],
    "sg:postcode":"TS4 2ET",
    "sg:province":"North Yorkshire",
    "sg:tags":[
        "acupuncture"
    ],
    "wof:name":"Cliff Wicks",
    "wof:placetype":"venue"
},
  "geometry": {"coordinates":[-1.2241319418,54.5687522888],"type":"Point"}
}