{
  "type": "Feature",
  "properties": {
    "addr:full":"173-175 London Road, Hazel Gro Stockport Cheshire SK7 4HJ",
    "addr:housenumber":"173-175",
    "addr:postcode":"sk7 4hj",
    "addr:street":"London Road",
    "iso:country":"GB",
    "sg:address":"173-175 London Road, Hazel Gro",
    "sg:city":"Stockport",
    "sg:classifiers":[
        {
            "category":"Cinema",
            "subcategory":"Movie Rental",
            "type":"Entertainment"
        }
    ],
    "sg:phone":"+44 161 419 9697",
    "sg:postcode":"SK7 4HJ",
    "sg:province":"Cheshire",
    "sg:tags":[
        "video",
        "library"
    ],
    "wof:name":"Eternity Video",
    "wof:placetype":"venue"
},
  "geometry": {"coordinates":[-2.1219279766,53.3802108765],"type":"Point"}
}