{
  "type": "Feature",
  "properties": {
    "iso:country":"GB",
    "sg:address":"Newburn Bridge Road",
    "sg:city":"Blaydon-on-tyne",
    "sg:classifiers":[
        {
            "category":"Building & Trades",
            "subcategory":"Cleaning & Sanitation",
            "type":"Services"
        },
        {
            "category":"Manufacturing",
            "subcategory":"Building Materials",
            "type":"Manufacturing & Wholesale Goods"
        }
    ],
    "sg:phone":"+44 191 414 8000",
    "sg:postcode":"NE21 4NT",
    "sg:province":"Tyne and Wear",
    "sg:tags":[
        "asbestos",
        "product",
        "removal"
    ],
    "wof:name":"Chirmarn Ltd.",
    "wof:placetype":"venue"
},
  "geometry": {"coordinates":[-1.740302,54.975658],"type":"Point"}
}