{
  "type": "Feature",
  "properties": {
    "iso:country":"GB",
    "sg:address":"104 Pen-y-lan Road",
    "sg:city":"Cardiff",
    "sg:classifiers":[
        {
            "category":"Travel",
            "subcategory":"Hotels & Motels",
            "type":"Entertainment"
        }
    ],
    "sg:phone":"+44 29 2048 5727",
    "sg:postcode":"CF23 5HY",
    "sg:province":"Cardiff",
    "sg:tags":[
        "house",
        "guest"
    ],
    "wof:name":"OLYMPOS HOTEL",
    "wof:placetype":"venue"
},
  "geometry": {"coordinates":[-3.162014,51.49884],"type":"Point"}
}