{
  "type": "Feature",
  "properties": {
    "iso:country":"GB",
    "sg:address":"7 St Andrew Street",
    "sg:city":"Stranraer",
    "sg:classifiers":[
        {
            "category":"Food & Beverages",
            "subcategory":"Fruits & Vegetables",
            "type":"Retail Goods"
        }
    ],
    "sg:phone":"+44 1776 702720",
    "sg:postcode":"DG9 7EB",
    "sg:province":"Dumfries and Galloway",
    "sg:tags":[
        "greengrocer"
    ],
    "wof:name":"Fruit Bazaar",
    "wof:placetype":"venue"
},
  "geometry": {"coordinates":[-5.0244731903,54.904460907],"type":"Point"}
}