{
  "type": "Feature",
  "properties": {
    "addr:full":"226 Strathmartine Road Dundee Dundee City DD3 8DD",
    "addr:housenumber":"226",
    "addr:postcode":"dd3 8dd",
    "addr:street":"Strathmartine Road",
    "iso:country":"GB",
    "sg:address":"226 Strathmartine Road",
    "sg:city":"Dundee",
    "sg:classifiers":[
        {
            "category":"Fast Food",
            "type":"Food & Drink"
        },
        {
            "category":"Ice Cream",
            "type":"Food & Drink"
        }
    ],
    "sg:phone":"+44 1382 828221",
    "sg:postcode":"DD3 8DD",
    "sg:province":"Dundee City",
    "sg:tags":[
        "shop",
        "mobile",
        "away",
        "parlour",
        "take"
    ],
    "wof:name":"Vettrainos",
    "wof:placetype":"venue"
},
  "geometry": {"coordinates":[-2.984051,56.4781],"type":"Point"}
}