{
  "type": "Feature",
  "properties": {
    "addr:full":"Manor Farm, Milton Banbury Oxfordshire OX15 4HH",
    "addr:housenumber":"milton",
    "addr:postcode":"ox15 4hh",
    "addr:street":"Manor;Banbury",
    "iso:country":"GB",
    "sg:address":"Manor Farm, Milton",
    "sg:city":"Banbury",
    "sg:classifiers":[
        {
            "category":"Farming",
            "subcategory":"Farm",
            "type":"Manufacturing & Wholesale Goods"
        }
    ],
    "sg:postcode":"OX15 4HH",
    "sg:province":"Oxfordshire",
    "sg:tags":[
        "mixed",
        "crop"
    ],
    "wof:name":"Jonathan Raynard Adams",
    "wof:placetype":"venue"
},
  "geometry": {"coordinates":[-1.344664,52.011211],"type":"Point"}
}