{
  "type": "Feature",
  "properties": {
    "iso:country":"GB",
    "sg:address":"The Covey, Chattisham Road, Washbrook",
    "sg:city":"Ipswich",
    "sg:classifiers":[
        {
            "category":"Shopping",
            "subcategory":"Department Store",
            "type":"Retail Goods"
        },
        {
            "category":"Shopping",
            "subcategory":"Bicycles & Sporting Goods",
            "type":"Retail Goods"
        }
    ],
    "sg:phone":"+44 1473 652563",
    "sg:postcode":"IP8 3HB",
    "sg:province":"Suffolk",
    "sg:tags":[
        "riding",
        "saddlery",
        "wear"
    ],
    "wof:name":"Suffolk Saddles",
    "wof:placetype":"venue"
},
  "geometry": {"coordinates":[1.04693,52.038452],"type":"Point"}
}