{
  "type": "Feature",
  "properties": {
    "addr:full":"Unit 2a Heath Mill Clo Wolverhampton Shropshire WV5 8EX",
    "addr:housenumber":"unit 2a",
    "addr:postcode":"wv5 8ex",
    "addr:street":"Heath Mill Clo",
    "iso:country":"GB",
    "sg:address":"Unit 2a Heath Mill Clo",
    "sg:city":"Wolverhampton",
    "sg:classifiers":[
        {
            "category":"Manufacturing",
            "subcategory":"Wood Products",
            "type":"Manufacturing & Wholesale Goods"
        }
    ],
    "sg:phone":"+44 1902 898232",
    "sg:postcode":"WV5 8EX",
    "sg:province":"Shropshire",
    "sg:tags":[
        "packaging",
        "crate",
        "pallets"
    ],
    "wof:name":"Escott Packaging",
    "wof:placetype":"venue"
},
  "geometry": {"coordinates":[-2.210399,52.522266],"type":"Point"}
}