{
  "type": "Feature",
  "properties": {
    "addr:full":"27 Sloane St Ayr South Ayrshire KA8 9QY",
    "addr:housenumber":"27",
    "addr:postcode":"ka8 9qy",
    "addr:street":"Sloane St",
    "iso:country":"GB",
    "sg:address":"27 Sloane St",
    "sg:city":"Ayr",
    "sg:classifiers":[
        {
            "category":"Building & Trades",
            "subcategory":"Construction",
            "type":"Services"
        }
    ],
    "sg:phone":"+44 1292 284257",
    "sg:postcode":"KA8 9QY",
    "sg:province":"South Ayrshire",
    "sg:tags":[
        "roofing"
    ],
    "wof:name":"Frizzell James",
    "wof:placetype":"venue"
},
  "geometry": {"coordinates":[-4.606269,55.477718],"type":"Point"}
}