{
  "type": "Feature",
  "properties": {
    "addr:full":"17 Flamingo Ct Nottingham Nottinghamshire NG7 1GJ",
    "addr:housenumber":"17",
    "addr:postcode":"ng7 1gj",
    "addr:street":"Flamingo Ct",
    "iso:country":"GB",
    "sg:address":"17 Flamingo Ct",
    "sg:city":"Nottingham",
    "sg:classifiers":[
        {
            "category":"Professional",
            "subcategory":"Management & Consulting",
            "type":"Services"
        }
    ],
    "sg:phone":"+44 115 937 7222",
    "sg:postcode":"NG7 1GJ",
    "sg:province":"Nottinghamshire",
    "sg:tags":[
        "consultant",
        "business"
    ],
    "wof:name":"Metis Consulting Organisation Ltd The",
    "wof:placetype":"venue"
},
  "geometry": {"coordinates":[-1.16638,52.944489],"type":"Point"}
}