{
  "type": "Feature",
  "properties": {
    "addr:full":"Uplands Farm, Little Bourton Banbury Northamptonshire OX17 1RF",
    "addr:postcode":"ox17 1rf",
    "addr:street":"Little",
    "iso:country":"GB",
    "sg:address":"Uplands Farm, Little Bourton",
    "sg:city":"Banbury",
    "sg:classifiers":[
        {
            "category":"Wholesale",
            "subcategory":"Farm Supplies",
            "type":"Manufacturing & Wholesale Goods"
        }
    ],
    "sg:postcode":"OX17 1RF",
    "sg:province":"Northamptonshire",
    "sg:tags":[
        "straw",
        "hay",
        "merchant"
    ],
    "wof:name":"I A Buzzard",
    "wof:placetype":"venue"
},
  "geometry": {"coordinates":[-1.336069,52.094234],"type":"Point"}
}