{
  "type": "Feature",
  "properties": {
    "iso:country":"GB",
    "sg:address":"2 Martland Mill Lane",
    "sg:city":"Wigan",
    "sg:classifiers":[
        {
            "category":"Home & Garden",
            "subcategory":"Carpets & Floor Coverings",
            "type":"Retail Goods"
        }
    ],
    "sg:phone":"+44 1942 224626",
    "sg:postcode":"WN5 0LZ",
    "sg:province":"Lancashire",
    "sg:tags":[
        "rubber",
        "plastic"
    ],
    "wof:name":"Martland Rollers Ltd.",
    "wof:placetype":"venue"
},
  "geometry": {"coordinates":[-2.668448925,53.5542755127],"type":"Point"}
}