{
  "type": "Feature",
  "properties": {
    "iso:country":"GB",
    "sg:address":"62 Holly Walk",
    "sg:city":"Leamington Spa",
    "sg:classifiers":[
        {
            "category":"Health Services",
            "subcategory":"Clinic",
            "type":"Services"
        }
    ],
    "sg:phone":"+44 1926 881451",
    "sg:postcode":"CV32 4JE",
    "sg:province":"Warwickshire",
    "sg:tags":[
        "private"
    ],
    "wof:name":"Holly Walk Clinic",
    "wof:placetype":"venue"
},
  "geometry": {"coordinates":[-1.5289009809,52.2913551331],"type":"Point"}
}