{
  "type": "Feature",
  "properties": {
    "iso:country":"GB",
    "sg:address":"26 Thackeray Drive, Vicars Cross",
    "sg:city":"Chester",
    "sg:classifiers":[
        {
            "category":"Building & Trades",
            "subcategory":"Construction",
            "type":"Services"
        }
    ],
    "sg:phone":"+44 1244 346935",
    "sg:postcode":"CH3 5LR",
    "sg:province":"Cheshire",
    "sg:tags":[
        "glazier"
    ],
    "wof:name":"Cyril E Kiberd",
    "wof:placetype":"venue"
},
  "geometry": {"coordinates":[-2.850989,53.197048],"type":"Point"}
}