{
  "type": "Feature",
  "properties": {
    "iso:country":"GB",
    "sg:address":"Pinewood, Great Mead, Denmead",
    "sg:city":"Portsmouth",
    "sg:classifiers":[
        {
            "category":"Building & Trades",
            "subcategory":"Construction",
            "type":"Services"
        }
    ],
    "sg:phone":"+44 23 9223 0402",
    "sg:postcode":"PO7 6HH",
    "sg:province":"Hampshire",
    "sg:tags":[
        "roofing"
    ],
    "wof:name":"A Hall",
    "wof:placetype":"venue"
},
  "geometry": {"coordinates":[-1.061859,50.902599],"type":"Point"}
}