{
  "type": "Feature",
  "properties": {
    "iso:country":"GB",
    "sg:address":"4 Wheatley Street, Denaby Main",
    "sg:city":"Doncaster",
    "sg:classifiers":[
        {
            "category":"Personal",
            "subcategory":"Beauty Salon",
            "type":"Services"
        }
    ],
    "sg:phone":"+44 1709 865189",
    "sg:postcode":"DN12 4AU",
    "sg:province":"South Yorkshire",
    "sg:tags":[
        "unisex",
        "hairdresser"
    ],
    "wof:name":"Stephen Jon's",
    "wof:placetype":"venue"
},
  "geometry": {"coordinates":[-1.250621,53.489052],"type":"Point"}
}