{
  "type": "Feature",
  "properties": {
    "iso:country":"GB",
    "sg:address":"Lower Chicks Gro",
    "sg:city":"Salisbury",
    "sg:classifiers":[
        {
            "category":"Professional",
            "subcategory":"Employment Agencies",
            "type":"Services"
        }
    ],
    "sg:phone":"+44 1722 714333",
    "sg:postcode":"SP3 6NB",
    "sg:province":"Wiltshire",
    "sg:tags":[
        "agricultural",
        "advice"
    ],
    "wof:name":"B J Agri-Hire",
    "wof:placetype":"venue"
},
  "geometry": {"coordinates":[-2.0374200344,51.0641593933],"type":"Point"}
}