{
  "type": "Feature",
  "properties": {
    "iso:country":"GB",
    "sg:address":"Unit 17, Euston Station",
    "sg:city":"Camden",
    "sg:classifiers":[
        {
            "category":"Shopping",
            "subcategory":"Stationery & Office Supplies",
            "type":"Retail Goods"
        }
    ],
    "sg:phone":"+44 20 7387 5829",
    "sg:postcode":"NW1 2HS",
    "sg:province":"Greater London",
    "wof:name":"Paperchase",
    "wof:placetype":"venue"
},
  "geometry": {"coordinates":[-0.122539,51.530682],"type":"Point"}
}