{
  "type": "Feature",
  "properties": {
    "iso:country":"GB",
    "sg:address":"116 Ewell Road",
    "sg:city":"Surbiton",
    "sg:classifiers":[
        {
            "category":"Organizations",
            "subcategory":"Community Association",
            "type":"Services"
        },
        {
            "category":"Landmark",
            "subcategory":"Tourist Information",
            "type":"Public Place"
        }
    ],
    "sg:phone":"+44 20 8390 0888",
    "sg:postcode":"KT6 6HA",
    "sg:province":"Surrey",
    "sg:tags":[
        "guide",
        "tour",
        "sightseeing",
        "excursion",
        "activity"
    ],
    "wof:name":"The Classic Coach Co",
    "wof:placetype":"venue"
},
  "geometry": {"coordinates":[-0.298045,51.38995],"type":"Point"}
}