{
  "type": "Feature",
  "properties": {
    "addr:full":"62 Hamer Clo Ashton-under-lyne Greater Manchester OL7 0SG",
    "addr:housenumber":"62",
    "addr:postcode":"ol7 0sg",
    "addr:street":"Hamer Clo Ashton-Under-Lyne",
    "iso:country":"GB",
    "sg:address":"62 Hamer Clo",
    "sg:city":"Ashton-under-lyne",
    "sg:classifiers":[
        {
            "category":"Shopping",
            "subcategory":"News",
            "type":"Retail Goods"
        }
    ],
    "sg:postcode":"OL7 0SG",
    "sg:province":"Greater Manchester",
    "sg:tags":[
        "newsagent"
    ],
    "wof:name":"West Park Newsagents",
    "wof:placetype":"venue"
},
  "geometry": {"coordinates":[-2.11232,53.482029],"type":"Point"}
}