{
  "type": "Feature",
  "properties": {
    "iso:country":"GB",
    "sg:address":"Medici Court, 67-69 New Bond Street",
    "sg:city":"London",
    "sg:classifiers":[
        {
            "category":"Real Estate",
            "subcategory":"Developer",
            "type":"Services"
        }
    ],
    "sg:phone":"+44 20 7907 9200",
    "sg:postcode":"W1S 1DF",
    "sg:province":"Greater London",
    "sg:tags":[
        "property"
    ],
    "wof:name":"B A A Lynton Plc",
    "wof:placetype":"venue"
},
  "geometry": {"coordinates":[-0.1456380039,51.5136756897],"type":"Point"}
}