{
  "type": "Feature",
  "properties": {
    "addr:full":"Harwood House, Clarendon Court, Carrs Rd Cheadle Cheshire SK8 2LA",
    "addr:postcode":"sk8 2la",
    "addr:street":"Clarendon Court Carrs Rd Cheadle",
    "iso:country":"GB",
    "sg:address":"Harwood House, Clarendon Court, Carrs Rd",
    "sg:city":"Cheadle",
    "sg:classifiers":[
        {
            "category":"Shopping",
            "type":"Retail Goods"
        }
    ],
    "sg:phone":"+44 161 428 0009",
    "sg:postcode":"SK8 2LA",
    "sg:province":"Cheshire",
    "sg:tags":[
        "med",
        "scientific",
        "apparatus"
    ],
    "wof:name":"Hook & Tucker Zenyx",
    "wof:placetype":"venue"
},
  "geometry": {"coordinates":[-2.1967470646,53.3970756531],"type":"Point"}
}