{
  "type": "Feature",
  "properties": {
    "addr:full":"5 Thurland Street Nottingham Nottinghamshire NG1 3DR",
    "addr:housenumber":"5",
    "addr:postcode":"ng1 3dr",
    "addr:street":"Thurland Street",
    "iso:country":"GB",
    "sg:address":"5 Thurland Street",
    "sg:city":"Nottingham",
    "sg:classifiers":[
        {
            "category":"Fast Food",
            "type":"Food & Drink"
        }
    ],
    "sg:phone":"+44 115 948 1856",
    "sg:postcode":"NG1 3DR",
    "sg:province":"Nottinghamshire",
    "sg:tags":[
        "away",
        "take"
    ],
    "wof:name":"Snappers",
    "wof:placetype":"venue"
},
  "geometry": {"coordinates":[-1.146799,52.954342],"type":"Point"}
}