{
  "type": "Feature",
  "properties": {
    "addr:full":"White House, Drakes View, Staddon Heights Plymouth Devon PL9 9SP",
    "addr:postcode":"pl9 9sp",
    "addr:street":"Drakes View Staddon Heights",
    "iso:country":"GB",
    "sg:address":"White House, Drakes View, Staddon Heights",
    "sg:city":"Plymouth",
    "sg:classifiers":[
        {
            "category":"Communications",
            "subcategory":"Film & Video Production",
            "type":"Services"
        }
    ],
    "sg:phone":"+44 1752 182722",
    "sg:postcode":"PL9 9SP",
    "sg:province":"Devon",
    "sg:tags":[
        "survey",
        "aerial",
        "photographer"
    ],
    "wof:name":"Hovercam Ltd.",
    "wof:placetype":"venue"
},
  "geometry": {"coordinates":[-4.0947642326,50.3588981628],"type":"Point"}
}