{
  "type": "Feature",
  "properties": {
    "addr:full":"12 Hartington Drive, Selston Nottingham Derbyshire NG16 6QY",
    "addr:housenumber":"12",
    "addr:postcode":"ng16 6qy",
    "addr:street":"Hartington Drive",
    "iso:country":"GB",
    "sg:address":"12 Hartington Drive, Selston",
    "sg:city":"Nottingham",
    "sg:classifiers":[
        {
            "category":"Building & Trades",
            "subcategory":"Construction",
            "type":"Services"
        }
    ],
    "sg:phone":"+44 1773 862384",
    "sg:postcode":"NG16 6QY",
    "sg:province":"Derbyshire",
    "sg:tags":[
        "heating",
        "contractor"
    ],
    "wof:name":"Mike Lambert Plumbing & Heating",
    "wof:placetype":"venue"
},
  "geometry": {"coordinates":[-1.2969870567,53.0740509033],"type":"Point"}
}