{
  "type": "Feature",
  "properties": {
    "addr:full":"Dolgarreg, North Road Builth Wells Powys LD2 3DD",
    "addr:postcode":"ld2 3dd",
    "addr:street":"North Road",
    "iso:country":"GB",
    "sg:address":"Dolgarreg, North Road",
    "sg:city":"Builth Wells",
    "sg:classifiers":[
        {
            "category":"Real Estate",
            "subcategory":"Real Estate Agent",
            "type":"Services"
        }
    ],
    "sg:phone":"+44 1982 553248",
    "sg:postcode":"LD2 3DD",
    "sg:province":"Powys",
    "wof:name":"Chester-Master Ltd.",
    "wof:placetype":"venue"
},
  "geometry": {"coordinates":[-3.40306,52.148273],"type":"Point"}
}