{
  "type": "Feature",
  "properties": {
    "addr:full":"587 London Road Thornton Heath Surrey CR7 6AY",
    "addr:housenumber":"587",
    "addr:postcode":"cr7 6ay",
    "addr:street":"London Road",
    "iso:country":"GB",
    "sg:address":"587 London Road",
    "sg:city":"Thornton Heath",
    "sg:classifiers":[
        {
            "category":"Travel",
            "subcategory":"Hotels & Motels",
            "type":"Entertainment"
        }
    ],
    "sg:phone":"+44 20 8689 8989",
    "sg:postcode":"CR7 6AY",
    "sg:province":"Surrey",
    "wof:name":"Rollaim Ltd.",
    "wof:placetype":"venue"
},
  "geometry": {"coordinates":[-0.112356998,51.3900146484],"type":"Point"}
}