{
  "type": "Feature",
  "properties": {
    "addr:full":"30 Holly Lea, Jacob's Well Guildford Surrey GU4 7PG",
    "addr:housenumber":"30",
    "addr:postcode":"gu4 7pg",
    "addr:street":"Holly Lea Jacob'S Well",
    "iso:country":"GB",
    "sg:address":"30 Holly Lea, Jacob's Well",
    "sg:city":"Guildford",
    "sg:classifiers":[
        {
            "category":"Banks & Credit Unions",
            "subcategory":"Bureau De Change",
            "type":"Services"
        },
        {
            "category":"Park",
            "subcategory":"Town Common",
            "type":"Public Place"
        },
        {
            "category":"Real Estate",
            "subcategory":"Architect",
            "type":"Services"
        }
    ],
    "sg:phone":"+44 1483 450410",
    "sg:postcode":"GU4 7PG",
    "sg:province":"Surrey",
    "sg:tags":[
        "city",
        "planning",
        "consultant"
    ],
    "wof:name":"Langridge Planning Services",
    "wof:placetype":"venue"
},
  "geometry": {"coordinates":[-0.5682809949,51.2680664062],"type":"Point"}
}