{
  "type": "Feature",
  "properties": {
    "iso:country":"GB",
    "sg:address":"32 College Street",
    "sg:city":"Rotherham",
    "sg:classifiers":[
        {
            "category":"Shopping",
            "subcategory":"Shoes",
            "type":"Retail Goods"
        }
    ],
    "sg:phone":"+44 1709 382406",
    "sg:postcode":"S65 1AG",
    "sg:province":"South Yorkshire",
    "sg:tags":[
        "shop"
    ],
    "wof:name":"Oliver Timpsons",
    "wof:placetype":"venue"
},
  "geometry": {"coordinates":[-1.3552629948,53.4308738708],"type":"Point"}
}