{
  "type": "Feature",
  "properties": {
    "addr:full":"Gun House London Greater London E1 7LJ",
    "addr:postcode":"e1 7lj",
    "iso:country":"GB",
    "sg:address":"Gun House",
    "sg:city":"London",
    "sg:classifiers":[
        {
            "category":"Professional",
            "subcategory":"Business Services",
            "type":"Services"
        }
    ],
    "sg:phone":"+44 20 7426 3391",
    "sg:postcode":"E1 7LJ",
    "sg:province":"Greater London",
    "sg:tags":[
        "holding"
    ],
    "wof:name":"Gallic Shipping Ltd.",
    "wof:placetype":"venue"
},
  "geometry": {"coordinates":[0.0177149996,51.5305671692],"type":"Point"}
}