{
  "type": "Feature",
  "properties": {
    "addr:full":"68 Sidwell Street Exeter Devon EX4 6PH",
    "addr:housenumber":"68",
    "addr:postcode":"ex4 6ph",
    "addr:street":"Sidwell Street",
    "iso:country":"GB",
    "sg:address":"68 Sidwell Street",
    "sg:city":"Exeter",
    "sg:classifiers":[
        {
            "category":"Shopping",
            "subcategory":"Comic Books",
            "type":"Retail Goods"
        }
    ],
    "sg:phone":"+44 1392 275291",
    "sg:postcode":"EX4 6PH",
    "sg:province":"Devon",
    "sg:tags":[
        "jeweller"
    ],
    "wof:name":"Kent Jewellers",
    "wof:placetype":"venue"
},
  "geometry": {"coordinates":[-3.52282691,50.7280235291],"type":"Point"}
}