{
  "type": "Feature",
  "properties": {
    "addr:full":"110-116 Grey St Newcastle Upon Tyne Tyne and Wear NE1 6JG",
    "addr:housenumber":"110-116",
    "addr:postcode":"ne1 6jg",
    "addr:street":"Grey St",
    "iso:country":"GB",
    "sg:address":"110-116 Grey St",
    "sg:city":"Newcastle Upon Tyne",
    "sg:classifiers":[
        {
            "category":"Banks & Credit Unions",
            "subcategory":"Bank",
            "type":"Services"
        }
    ],
    "sg:phone":"+44 191 230 5962",
    "sg:postcode":"NE1 6JG",
    "sg:province":"Tyne and Wear",
    "wof:name":"Commercial Business Centre",
    "wof:placetype":"venue"
},
  "geometry": {"coordinates":[-1.6124589443,54.9732513428],"type":"Point"}
}