{
  "type": "Feature",
  "properties": {
    "iso:country":"GB",
    "sg:address":"Area Community Education Office, Vicarage Rd",
    "sg:city":"Barnstaple",
    "sg:classifiers":[
        {
            "category":"Government",
            "subcategory":"Office",
            "type":"Public Place"
        }
    ],
    "sg:phone":"+44 1271 321728",
    "sg:postcode":"EX32 0JR",
    "sg:province":"Devon",
    "sg:tags":[
        "local"
    ],
    "wof:name":"Devon County Council",
    "wof:placetype":"venue"
},
  "geometry": {"coordinates":[-4.056222,51.078323],"type":"Point"}
}