{
  "type": "Feature",
  "properties": {
    "addr:full":"3 Shepherd Street St Leonards-on-sea East Sussex TN38 0ET",
    "addr:housenumber":"3",
    "addr:postcode":"tn38 0et",
    "addr:street":"Shepherd Street St",
    "iso:country":"GB",
    "sg:address":"3 Shepherd Street",
    "sg:city":"St Leonards-on-sea",
    "sg:classifiers":[
        {
            "category":"Retail",
            "subcategory":"Auto Repair",
            "type":"Services"
        }
    ],
    "sg:postcode":"TN38 0ET",
    "sg:province":"East Sussex",
    "sg:tags":[
        "modification",
        "garage"
    ],
    "wof:name":"G G Car Repairs",
    "wof:placetype":"venue"
},
  "geometry": {"coordinates":[0.559838,50.852627],"type":"Point"}
}