{
  "type": "Feature",
  "properties": {
    "iso:country":"GB",
    "sg:address":"13 Vernon Road, Salford",
    "sg:city":"Manchester",
    "sg:classifiers":[
        {
            "category":"Fast Food",
            "type":"Food & Drink"
        }
    ],
    "sg:phone":"+44 20 8202 3301",
    "sg:postcode":"M7 0NW",
    "sg:province":"Greater Manchester",
    "sg:tags":[
        "away",
        "take"
    ],
    "wof:name":"Capeworld Ltd.",
    "wof:placetype":"venue"
},
  "geometry": {"coordinates":[-2.26904,53.501789],"type":"Point"}
}