{
  "type": "Feature",
  "properties": {
    "iso:country":"GB",
    "sg:address":"Bethesda, The Old Chapel, Park La",
    "sg:city":"Telford",
    "sg:classifiers":[
        {
            "category":"Manufacturing",
            "subcategory":"Wood Products",
            "type":"Manufacturing & Wholesale Goods"
        }
    ],
    "sg:phone":"+44 1952 613894",
    "sg:postcode":"TF3 4TE",
    "sg:province":"Shropshire",
    "sg:tags":[
        "craftsman"
    ],
    "wof:name":"M E C Davies",
    "wof:placetype":"venue"
},
  "geometry": {"coordinates":[-2.44176507,52.6766624451],"type":"Point"}
}