{
  "type": "Feature",
  "properties": {
    "addr:full":"Danescroft Hough Green Widnes Cheshire WA8 4NS",
    "addr:postcode":"wa8 4ns",
    "addr:street":"Danescroft",
    "iso:country":"GB",
    "sg:address":"Danescroft Hough Green",
    "sg:city":"Widnes",
    "sg:classifiers":[
        {
            "category":"Health Services",
            "subcategory":"Dentist",
            "type":"Services"
        }
    ],
    "sg:phone":"+44 151 423 6792",
    "sg:postcode":"WA8 4NS",
    "sg:province":"Cheshire",
    "wof:name":"P E Rendle",
    "wof:placetype":"venue"
},
  "geometry": {"coordinates":[-2.771219,53.37846],"type":"Point"}
}