{
  "type": "Feature",
  "properties": {
    "addr:full":"7 Cadzow Avenue, Giffnock Glasgow East Renfrewshire G46 6RD",
    "addr:housenumber":"7",
    "addr:postcode":"g46 6rd",
    "addr:street":"Cadzow Avenue",
    "iso:country":"GB",
    "sg:address":"7 Cadzow Avenue, Giffnock",
    "sg:city":"Glasgow",
    "sg:classifiers":[
        {
            "category":"Professional",
            "subcategory":"Lawyer & Legal Services",
            "type":"Services"
        }
    ],
    "sg:postcode":"G46 6RD",
    "sg:province":"East Renfrewshire",
    "sg:tags":[
        "advice",
        "counselling"
    ],
    "wof:name":"Assist Counselling Service",
    "wof:placetype":"venue"
},
  "geometry": {"coordinates":[-4.298661232,55.7935562134],"type":"Point"}
}