{
  "type": "Feature",
  "properties": {
    "addr:full":"Ashdene, Romney Road Ashford Kent TN26 2JB",
    "addr:postcode":"tn26 2jb",
    "addr:street":"Ashdene Romney Road",
    "iso:country":"GB",
    "sg:address":"Ashdene, Romney Road",
    "sg:city":"Ashford",
    "sg:classifiers":[
        {
            "category":"Building & Trades",
            "subcategory":"Construction",
            "type":"Services"
        }
    ],
    "sg:postcode":"TN26 2JB",
    "sg:province":"Kent",
    "sg:tags":[
        "dry",
        "lining",
        "plasterers",
        "screeders"
    ],
    "wof:name":"Ralph Spears",
    "wof:placetype":"venue"
},
  "geometry": {"coordinates":[0.85792,51.06163],"type":"Point"}
}