{
  "type": "Feature",
  "properties": {
    "addr:full":"1 Upper Brook Street Winchester Hampshire SO23 8AL",
    "addr:housenumber":"1",
    "addr:postcode":"so23 8al",
    "addr:street":"Upper Brook Street",
    "iso:country":"GB",
    "sg:address":"1 Upper Brook Street",
    "sg:city":"Winchester",
    "sg:classifiers":[
        {
            "category":"Shopping",
            "subcategory":"Shoes",
            "type":"Retail Goods"
        }
    ],
    "sg:postcode":"SO23 8AL",
    "sg:province":"Hampshire",
    "sg:tags":[
        "shop"
    ],
    "wof:name":"Raw",
    "wof:placetype":"venue"
},
  "geometry": {"coordinates":[-1.312678,51.063316],"type":"Point"}
}