{
  "type": "Feature",
  "properties": {
    "addr:full":"206 Hawthorn Road, Kingstanding Birmingham West Midlands B44 8PP",
    "addr:housenumber":"206",
    "addr:postcode":"b44 8pp",
    "addr:street":"Hawthorn Road",
    "iso:country":"GB",
    "sg:address":"206 Hawthorn Road, Kingstanding",
    "sg:city":"Birmingham",
    "sg:classifiers":[
        {
            "category":"Shopping",
            "subcategory":"Pets & Pet Supplies",
            "type":"Retail Goods"
        }
    ],
    "sg:phone":"+44 121 373 4990",
    "sg:postcode":"B44 8PP",
    "sg:province":"West Midlands",
    "sg:tags":[
        "shop"
    ],
    "wof:name":"MILES KINGSTANDING PET SHOP",
    "wof:placetype":"venue"
},
  "geometry": {"coordinates":[-1.883973,52.540497],"type":"Point"}
}