{
  "type": "Feature",
  "properties": {
    "iso:country":"GB",
    "sg:address":"22 Mill St",
    "sg:city":"Porth",
    "sg:classifiers":[
        {
            "category":"Shopping",
            "subcategory":"Pharmacy",
            "type":"Retail Goods"
        }
    ],
    "sg:phone":"+44 1443 670394",
    "sg:postcode":"CF39 8AA",
    "sg:province":"Bridgend",
    "sg:tags":[
        "pharmacist",
        "chemist"
    ],
    "wof:name":"Co-op Pharmacy",
    "wof:placetype":"venue"
},
  "geometry": {"coordinates":[-3.431876,51.580017],"type":"Point"}
}