{
  "type": "Feature",
  "properties": {
    "addr:full":"9 Beaumont Business Centre, Beaumont Close Banbury Oxfordshire OX16 7TN",
    "addr:housenumber":"9",
    "addr:postcode":"ox16 7tn",
    "addr:street":"Beaumont Business Centre Beaumont Close",
    "iso:country":"GB",
    "sg:address":"9 Beaumont Business Centre, Beaumont Close",
    "sg:city":"Banbury",
    "sg:classifiers":[
        {
            "category":"Professional",
            "subcategory":"Printing & Photocopies",
            "type":"Services"
        }
    ],
    "sg:phone":"+44 1295 267645",
    "sg:postcode":"OX16 7TN",
    "sg:province":"Oxfordshire",
    "sg:tags":[
        "printer"
    ],
    "wof:name":"D B Printing",
    "wof:placetype":"venue"
},
  "geometry": {"coordinates":[-1.340028,52.061111],"type":"Point"}
}