{
  "type": "Feature",
  "properties": {
    "iso:country":"GB",
    "sg:address":"76 Victoria Road, Writtle",
    "sg:city":"Chelmsford",
    "sg:classifiers":[
        {
            "category":"Bars & Pubs",
            "type":"Food & Drink"
        }
    ],
    "sg:phone":"+44 1245 420535",
    "sg:postcode":"CM1 3PA",
    "sg:province":"Essex",
    "sg:tags":[
        "pubs",
        "inn"
    ],
    "wof:name":"Victoria Public House",
    "wof:placetype":"venue"
},
  "geometry": {"coordinates":[0.4115650058,51.7309303284],"type":"Point"}
}