{
  "type": "Feature",
  "properties": {
    "addr:full":"487 Church Road Bolton Lancashire BL1 5RE",
    "addr:housenumber":"487",
    "addr:postcode":"bl1 5re",
    "addr:street":"Church Road",
    "iso:country":"GB",
    "sg:address":"487 Church Road",
    "sg:city":"Bolton",
    "sg:classifiers":[
        {
            "category":"Bars & Pubs",
            "type":"Food & Drink"
        }
    ],
    "sg:phone":"+44 1204 848244",
    "sg:postcode":"BL1 5RE",
    "sg:province":"Lancashire",
    "sg:tags":[
        "pubs",
        "house",
        "inn",
        "public",
        "activity"
    ],
    "wof:name":"The Finishers Arms",
    "wof:placetype":"venue"
},
  "geometry": {"coordinates":[-2.4679350853,53.5916252136],"type":"Point"}
}