{
  "type": "Feature",
  "properties": {
    "addr:full":"27 Millwrights, Tiptree Colchester Essex CO5 0LQ",
    "addr:housenumber":"27",
    "addr:postcode":"co5 0lq",
    "addr:street":"Millwrights Tiptree Colchester",
    "iso:country":"GB",
    "sg:address":"27 Millwrights, Tiptree",
    "sg:city":"Colchester",
    "sg:classifiers":[
        {
            "category":"Retail",
            "subcategory":"Repair Shop",
            "type":"Services"
        }
    ],
    "sg:phone":"+44 7779 216662",
    "sg:postcode":"CO5 0LQ",
    "sg:province":"Essex",
    "sg:tags":[
        "radio",
        "television",
        "video"
    ],
    "wof:name":"Coleman T V Services",
    "wof:placetype":"venue"
},
  "geometry": {"coordinates":[0.7498400211,51.81042099],"type":"Point"}
}