{
  "type": "Feature",
  "properties": {
    "addr:full":"18 Milton Grove Manchester Cheshire M16 0BP",
    "addr:housenumber":"18",
    "addr:postcode":"m16 0bp",
    "addr:street":"Milton Grove",
    "iso:country":"GB",
    "sg:address":"18 Milton Grove",
    "sg:city":"Manchester",
    "sg:classifiers":[
        {
            "category":"Professional",
            "subcategory":"Management & Consulting",
            "type":"Services"
        }
    ],
    "sg:phone":"+44 161 861 7287",
    "sg:postcode":"M16 0BP",
    "sg:province":"Cheshire",
    "sg:tags":[
        "consultant",
        "business"
    ],
    "wof:name":"Millennium Consulting Conferencing & Training Group",
    "wof:placetype":"venue"
},
  "geometry": {"coordinates":[-2.270378,53.450531],"type":"Point"}
}