{
  "type": "Feature",
  "properties": {
    "addr:full":"46/48 Rivington Street London Greater London EC2A 3QP",
    "addr:housenumber":"46 / 48",
    "addr:postcode":"ec2a 3qp",
    "addr:street":"Rivington Street",
    "iso:country":"GB",
    "sg:address":"46/48 Rivington Street",
    "sg:city":"London",
    "sg:classifiers":[
        {
            "category":"Transit Center",
            "subcategory":"Passenger",
            "type":"Transportation"
        }
    ],
    "sg:phone":"+44 20 7739 2161",
    "sg:postcode":"EC2A 3QP",
    "sg:province":"Greater London",
    "sg:tags":[
        "ship",
        "broker"
    ],
    "wof:name":"Loucas Nomicos (England) Co. Ltd.",
    "wof:placetype":"venue"
},
  "geometry": {"coordinates":[-0.080606,51.525993],"type":"Point"}
}