{
  "type": "Feature",
  "properties": {
    "iso:country":"GB",
    "sg:address":"Burton Lane End, Saxilby Road",
    "sg:city":"Lincoln",
    "sg:classifiers":[
        {
            "category":"Bars & Pubs",
            "type":"Food & Drink"
        }
    ],
    "sg:phone":"+44 1522 703460",
    "sg:postcode":"LN1 2BE",
    "sg:province":"Lincolnshire",
    "sg:tags":[
        "pubs",
        "house",
        "inn",
        "public",
        "activity"
    ],
    "wof:name":"The Woodcocks Inn",
    "wof:placetype":"venue"
},
  "geometry": {"coordinates":[-0.655976,53.271435],"type":"Point"}
}