{
  "type": "Feature",
  "properties": {
    "iso:country":"GB",
    "sg:address":"Bury Lane",
    "sg:city":"Chorley",
    "sg:classifiers":[
        {
            "category":"Social Services",
            "subcategory":"Retirement Home",
            "type":"Services"
        }
    ],
    "sg:phone":"+44 1254 830341",
    "sg:postcode":"PR6 8BH",
    "sg:province":"Lancashire",
    "sg:tags":[
        "rest"
    ],
    "wof:name":"Withnell House",
    "wof:placetype":"venue"
},
  "geometry": {"coordinates":[-2.559726,53.696739],"type":"Point"}
}