{
  "type": "Feature",
  "properties": {
    "addr:full":"St Albans Road Watford Hertfordshire WD24 7RZ",
    "addr:postcode":"wd24 7rz",
    "addr:street":"St Albans Road",
    "iso:country":"GB",
    "sg:address":"St Albans Road",
    "sg:city":"Watford",
    "sg:classifiers":[
        {
            "category":"Health Services",
            "subcategory":"Clinic",
            "type":"Services"
        }
    ],
    "sg:phone":"+44 1923 243568",
    "sg:postcode":"WD24 7RZ",
    "sg:province":"Hertfordshire",
    "sg:tags":[
        "nh"
    ],
    "wof:name":"Garston Clinic",
    "wof:placetype":"venue"
},
  "geometry": {"coordinates":[-0.396299,51.672165],"type":"Point"}
}