{
  "type": "Feature",
  "properties": {
    "addr:full":"1 Millstone Close, South Darenth Dartford Kent DA4 9BJ",
    "addr:housenumber":"1",
    "addr:postcode":"da4 9bj",
    "addr:street":"Millstone Close South",
    "iso:country":"GB",
    "sg:address":"1 Millstone Close, South Darenth",
    "sg:city":"Dartford",
    "sg:classifiers":[
        {
            "category":"Building & Trades",
            "subcategory":"Construction",
            "type":"Services"
        }
    ],
    "sg:phone":"+44 1322 864100",
    "sg:postcode":"DA4 9BJ",
    "sg:province":"Kent",
    "sg:tags":[
        "roofing"
    ],
    "wof:name":"Nicholson Roofing",
    "wof:placetype":"venue"
},
  "geometry": {"coordinates":[0.243709,51.403362],"type":"Point"}
}