{
  "type": "Feature",
  "properties": {
    "addr:full":"13 Church St, Minster Ramsgate Kent CT12 4BX",
    "addr:housenumber":"13",
    "addr:postcode":"ct12 4bx",
    "addr:street":"Church St;Ramsgate",
    "iso:country":"GB",
    "sg:address":"13 Church St, Minster",
    "sg:city":"Ramsgate",
    "sg:classifiers":[
        {
            "category":"Food & Beverages",
            "subcategory":"Supermarket",
            "type":"Retail Goods"
        }
    ],
    "sg:postcode":"CT12 4BX",
    "sg:province":"Kent",
    "wof:name":"Village Store (The)",
    "wof:placetype":"venue"
},
  "geometry": {"coordinates":[1.3157709837,51.3311233521],"type":"Point"}
}