{
  "type": "Feature",
  "properties": {
    "iso:country":"GB",
    "sg:address":"Unit 14 Marston Moor Business Park",
    "sg:city":"York",
    "sg:classifiers":[
        {
            "category":"Freight",
            "type":"Transportation"
        }
    ],
    "sg:phone":"+44 1423 359111",
    "sg:postcode":"YO5 8QF",
    "sg:province":"East Riding of Yorkshire",
    "sg:tags":[
        "haulage",
        "road"
    ],
    "wof:name":"Dales Transport Services",
    "wof:placetype":"venue"
},
  "geometry": {"coordinates":[-1.310989,53.965969],"type":"Point"}
}