{
  "type": "Feature",
  "properties": {
    "iso:country":"GB",
    "sg:address":"24 Commercial Street, Rothwell",
    "sg:city":"Leeds",
    "sg:classifiers":[
        {
            "category":"Travel",
            "subcategory":"Travel Agent",
            "type":"Entertainment"
        }
    ],
    "sg:phone":"+44 113 288 0088",
    "sg:postcode":"LS26 0AW",
    "sg:province":"West Yorkshire",
    "wof:name":"Dave Simpson",
    "wof:placetype":"venue"
},
  "geometry": {"coordinates":[-1.476416,53.748577],"type":"Point"}
}