{
  "type": "Feature",
  "properties": {
    "addr:full":"31 Murraygate Dundee Dundee City DD1 2EE",
    "addr:housenumber":"31",
    "addr:postcode":"dd1 2ee",
    "addr:street":"Murraygate Dundee",
    "iso:country":"GB",
    "sg:address":"31 Murraygate",
    "sg:city":"Dundee",
    "sg:classifiers":[
        {
            "category":"Organizations",
            "subcategory":"Non-profit Organization",
            "type":"Services"
        }
    ],
    "sg:postcode":"DD1 2EE",
    "sg:province":"Dundee City",
    "sg:tags":[
        "organisation",
        "voluntary",
        "charity"
    ],
    "wof:name":"Dundee Disabled Children's Association",
    "wof:placetype":"venue"
},
  "geometry": {"coordinates":[-2.968502,56.462528],"type":"Point"}
}