{
  "type": "Feature",
  "properties": {
    "iso:country":"GB",
    "sg:address":"65 High St",
    "sg:city":"Egham",
    "sg:classifiers":[
        {
            "category":"Food & Beverages",
            "subcategory":"Meat & Fish",
            "type":"Retail Goods"
        }
    ],
    "sg:postcode":"TW20 9EY",
    "sg:province":"Surrey",
    "sg:tags":[
        "butcher"
    ],
    "wof:name":"Clarke Bros",
    "wof:placetype":"venue"
},
  "geometry": {"coordinates":[-0.5447340012,51.4326400757],"type":"Point"}
}