{
  "type": "Feature",
  "properties": {
    "iso:country":"GB",
    "sg:address":"6 Mortimer Lane",
    "sg:city":"Basingstoke",
    "sg:classifiers":[
        {
            "category":"Retail",
            "subcategory":"Auto Rental",
            "type":"Services"
        }
    ],
    "sg:postcode":"RG21 1SG",
    "sg:province":"Hampshire",
    "sg:tags":[
        "truck",
        "hire",
        "van"
    ],
    "wof:name":"Budget Rent A Car",
    "wof:placetype":"venue"
},
  "geometry": {"coordinates":[-1.091557,51.264217],"type":"Point"}
}