{
  "type": "Feature",
  "properties": {
    "iso:country":"GB",
    "sg:address":"3 Mansbrook House, 15 High Street, Midsomer Norton",
    "sg:city":"Bath",
    "sg:classifiers":[
        {
            "category":"Shopping",
            "subcategory":"Bicycles & Sporting Goods",
            "type":"Retail Goods"
        },
        {
            "category":"Sports & Exercise",
            "subcategory":"Sports Center",
            "type":"Entertainment"
        }
    ],
    "sg:phone":"+44 1761 416168",
    "sg:postcode":"BA3 2HW",
    "sg:province":"Somerset",
    "sg:tags":[
        "shop",
        "sale"
    ],
    "wof:name":"Performance Sports",
    "wof:placetype":"venue"
},
  "geometry": {"coordinates":[-2.4871239662,51.2867698669],"type":"Point"}
}