{
  "type": "Feature",
  "properties": {
    "addr:full":"Oak Tree Lodge, Lord Street, Croft Warrington Cheshire WA3 7DB",
    "addr:postcode":"wa3 7db",
    "addr:street":"Lord Street Croft",
    "iso:country":"GB",
    "sg:address":"Oak Tree Lodge, Lord Street, Croft",
    "sg:city":"Warrington",
    "sg:classifiers":[
        {
            "category":"Professional",
            "subcategory":"Lawyer & Legal Services",
            "type":"Services"
        }
    ],
    "sg:postcode":"WA3 7DB",
    "sg:province":"Cheshire",
    "wof:name":"Claims Direct",
    "wof:placetype":"venue"
},
  "geometry": {"coordinates":[-2.5541689396,53.4383506775],"type":"Point"}
}