{
  "type": "Feature",
  "properties": {
    "addr:full":"Sale Moor Service Station, Northenden Road Sale Cheshire M33 2FE",
    "addr:postcode":"m33 2fe",
    "addr:street":"Northenden Road",
    "iso:country":"GB",
    "sg:address":"Sale Moor Service Station, Northenden Road",
    "sg:city":"Sale",
    "sg:classifiers":[
        {
            "category":"Autos & Motor Vehicles",
            "subcategory":"Auto Supplies",
            "type":"Retail Goods"
        }
    ],
    "sg:phone":"+44 161 969 4090",
    "sg:postcode":"M33 2FE",
    "sg:province":"Cheshire",
    "sg:tags":[
        "tyre"
    ],
    "wof:name":"Sale Tyre & Battery",
    "wof:placetype":"venue"
},
  "geometry": {"coordinates":[-2.3204169273,53.4259490967],"type":"Point"}
}