{
  "type": "Feature",
  "properties": {
    "addr:full":"Bridgerule Holsworthy Cornwall EX22 7EX",
    "addr:housenumber":"bridgerule",
    "addr:postcode":"ex22 7ex",
    "addr:street":"Holsworthy",
    "iso:country":"GB",
    "sg:address":"Bridgerule",
    "sg:city":"Holsworthy",
    "sg:classifiers":[
        {
            "category":"Home & Garden",
            "subcategory":"Home Furnishings",
            "type":"Retail Goods"
        }
    ],
    "sg:postcode":"EX22 7EX",
    "sg:province":"Cornwall",
    "sg:tags":[
        "homefurnishings"
    ],
    "wof:name":"Eastcott Furniture",
    "wof:placetype":"venue"
},
  "geometry": {"coordinates":[-4.455791,50.799919],"type":"Point"}
}