{
  "type": "Feature",
  "properties": {
    "addr:full":"Edwards Yard, Edendale Terrace, Horden Peterlee Durham SR8 4RD",
    "addr:postcode":"sr8 4rd",
    "addr:street":"Edendale Terrace",
    "iso:country":"GB",
    "sg:address":"Edwards Yard, Edendale Terrace, Horden",
    "sg:city":"Peterlee",
    "sg:classifiers":[
        {
            "category":"Professional",
            "type":"Services"
        }
    ],
    "sg:phone":"+44 191 517 2856",
    "sg:postcode":"SR8 4RD",
    "sg:province":"Durham",
    "sg:tags":[
        "entertainer"
    ],
    "wof:name":"Playboys International",
    "wof:placetype":"venue"
},
  "geometry": {"coordinates":[-1.311139,54.75956],"type":"Point"}
}