{
  "type": "Feature",
  "properties": {
    "iso:country":"GB",
    "sg:address":"13 Blenheim Street",
    "sg:city":"Newcastle-upon-tyne",
    "sg:classifiers":[
        {
            "category":"Professional",
            "subcategory":"Business Services",
            "type":"Services"
        }
    ],
    "sg:phone":"+44 191 230 1682",
    "sg:postcode":"NE1 4AY",
    "sg:province":"Tyne and Wear",
    "sg:tags":[
        "import",
        "export",
        "agent"
    ],
    "wof:name":"Manyee U K Ltd.",
    "wof:placetype":"venue"
},
  "geometry": {"coordinates":[-1.6224700212,54.9707450867],"type":"Point"}
}