{
  "type": "Feature",
  "properties": {
    "addr:full":"102 New George Street Plymouth Devon PL1 1RZ",
    "addr:housenumber":"102",
    "addr:postcode":"pl1 1rz",
    "addr:street":"New George Street",
    "iso:country":"GB",
    "sg:address":"102 New George Street",
    "sg:city":"Plymouth",
    "sg:classifiers":[
        {
            "category":"Shopping",
            "subcategory":"Department Store",
            "type":"Retail Goods"
        },
        {
            "category":"Insurance",
            "subcategory":"Insurance Agent",
            "type":"Services"
        },
        {
            "category":"Shopping",
            "subcategory":"Jewelry",
            "type":"Retail Goods"
        }
    ],
    "sg:phone":"+44 1752 661651",
    "sg:postcode":"PL1 1RZ",
    "sg:province":"Devon",
    "sg:tags":[
        "sale",
        "jewellery"
    ],
    "wof:name":"W Wray & Co",
    "wof:placetype":"venue"
},
  "geometry": {"coordinates":[-4.146216,50.371407],"type":"Point"}
}