{
  "type": "Feature",
  "properties": {
    "iso:country":"GB",
    "sg:address":"35 High Street, Theale",
    "sg:city":"Reading",
    "sg:classifiers":[
        {
            "category":"Professional",
            "subcategory":"Accounting & Tax Preparation",
            "type":"Services"
        }
    ],
    "sg:phone":"+44 118 930 4788",
    "sg:postcode":"RG7 5AH",
    "sg:province":"Berkshire",
    "sg:tags":[
        "consultant"
    ],
    "wof:name":"The Tax Team",
    "wof:placetype":"venue"
},
  "geometry": {"coordinates":[-1.074734,51.437859],"type":"Point"}
}