{
  "type": "Feature",
  "properties": {
    "iso:country":"GB",
    "sg:address":"19 Regent Way",
    "sg:city":"Hamilton",
    "sg:classifiers":[
        {
            "category":"Shopping",
            "subcategory":"Clothing, Apparel, & Fashions",
            "type":"Retail Goods"
        }
    ],
    "sg:phone":"+44 1698 428478",
    "sg:postcode":"ML3 7EF",
    "sg:province":"South Lanarkshire",
    "sg:tags":[
        "shop"
    ],
    "wof:name":"State of Independence",
    "wof:placetype":"venue"
},
  "geometry": {"coordinates":[-4.052891,55.777321],"type":"Point"}
}