{
  "type": "Feature",
  "properties": {
    "addr:full":"97 Old Shoreham Rd Hove East Sussex BN3 7AQ",
    "addr:housenumber":"97",
    "addr:postcode":"bn3 7aq",
    "addr:street":"Old Shoreham Rd",
    "iso:country":"GB",
    "sg:address":"97 Old Shoreham Rd",
    "sg:city":"Hove",
    "sg:classifiers":[
        {
            "category":"Professional",
            "subcategory":"Art Services",
            "type":"Services"
        }
    ],
    "sg:phone":"+44 1273 702233",
    "sg:postcode":"BN3 7AQ",
    "sg:province":"East Sussex",
    "sg:tags":[
        "photographer"
    ],
    "wof:name":"Richard Holmes Photography",
    "wof:placetype":"venue"
},
  "geometry": {"coordinates":[-0.177869007,50.8389015198],"type":"Point"}
}