{
  "type": "Feature",
  "properties": {
    "iso:country":"GB",
    "sg:address":"51 Street Lane",
    "sg:city":"Leeds",
    "sg:classifiers":[
        {
            "category":"Shopping",
            "subcategory":"Shoes",
            "type":"Retail Goods"
        }
    ],
    "sg:phone":"+44 113 266 1667",
    "sg:postcode":"LS8 1AP",
    "sg:province":"West Yorkshire",
    "sg:tags":[
        "shop"
    ],
    "wof:name":"Keith Shepherd",
    "wof:placetype":"venue"
},
  "geometry": {"coordinates":[-1.5087959766,53.8441238403],"type":"Point"}
}