{
  "type": "Feature",
  "properties": {
    "addr:full":"Ivy House Farm, Newhaven Buxton Derbyshire SK17 0DT",
    "addr:postcode":"sk17 0dt",
    "iso:country":"GB",
    "sg:address":"Ivy House Farm, Newhaven",
    "sg:city":"Buxton",
    "sg:classifiers":[
        {
            "category":"Banks & Credit Unions",
            "subcategory":"Investment Brokerage",
            "type":"Services"
        }
    ],
    "sg:phone":"+44 1298 84370",
    "sg:postcode":"SK17 0DT",
    "sg:province":"Derbyshire",
    "sg:tags":[
        "contractor"
    ],
    "wof:name":"Frank W Mellor",
    "wof:placetype":"venue"
},
  "geometry": {"coordinates":[-1.753584981,53.1394958496],"type":"Point"}
}