{
  "type": "Feature",
  "properties": {
    "addr:full":"West End Lane Pinner Greater London HA5 1AF",
    "addr:postcode":"ha5 1af",
    "addr:street":"West End Lane",
    "iso:country":"GB",
    "sg:address":"West End Lane",
    "sg:city":"Pinner",
    "sg:classifiers":[
        {
            "category":"Education",
            "subcategory":"School",
            "type":"Public Place"
        }
    ],
    "sg:phone":"+44 20 8866 9836",
    "sg:postcode":"HA5 1AF",
    "sg:province":"Greater London",
    "sg:tags":[
        "local",
        "authority"
    ],
    "wof:name":"West Lodge Middle School",
    "wof:placetype":"venue"
},
  "geometry": {"coordinates":[-0.3871749938,51.5926437378],"type":"Point"}
}