{
  "type": "Feature",
  "properties": {
    "addr:full":"257 Dalmarnock Road Glasgow Glasgow City G40 4LX",
    "addr:housenumber":"257",
    "addr:postcode":"g40 4lx",
    "addr:street":"Dalmarnock Road",
    "iso:country":"GB",
    "sg:address":"257 Dalmarnock Road",
    "sg:city":"Glasgow",
    "sg:classifiers":[
        {
            "category":"Home & Garden",
            "subcategory":"Hardware",
            "type":"Retail Goods"
        }
    ],
    "sg:phone":"+44 141 554 7732",
    "sg:postcode":"G40 4LX",
    "sg:province":"Glasgow City",
    "sg:tags":[
        "product",
        "wire",
        "electrical"
    ],
    "wof:name":"Newco Wire Products Ltd.",
    "wof:placetype":"venue"
},
  "geometry": {"coordinates":[-4.2211289406,55.8456115723],"type":"Point"}
}