{
  "type": "Feature",
  "properties": {
    "iso:country":"GB",
    "sg:address":"36 Prestonville Rd, Seven Dials",
    "sg:city":"Brighton",
    "sg:classifiers":[
        {
            "category":"Fast Food",
            "type":"Food & Drink"
        }
    ],
    "sg:phone":"+44 1273 820628",
    "sg:postcode":"BN1 3TJ",
    "sg:province":"East Sussex",
    "sg:tags":[
        "away",
        "take"
    ],
    "wof:name":"Curry Inn Tandoori Take Away Ltd",
    "wof:placetype":"venue"
},
  "geometry": {"coordinates":[-0.1471350044,50.831615448],"type":"Point"}
}