{
  "type": "Feature",
  "properties": {
    "addr:full":"Glen Havon, Horton Road Staines Berkshire TW19 6AF",
    "addr:postcode":"tw19 6af",
    "addr:street":"Horton Road",
    "iso:country":"GB",
    "sg:address":"Glen Havon, Horton Road",
    "sg:city":"Staines",
    "sg:classifiers":[
        {
            "category":"Retail",
            "subcategory":"Auto Repair",
            "type":"Services"
        }
    ],
    "sg:postcode":"TW19 6AF",
    "sg:province":"Berkshire",
    "sg:tags":[
        "body",
        "car"
    ],
    "wof:name":"Auto Weld Coachworks",
    "wof:placetype":"venue"
},
  "geometry": {"coordinates":[-0.4991999865,51.4609603882],"type":"Point"}
}