{
  "type": "Feature",
  "properties": {
    "addr:full":"459 Southmead Road, Southmead Bristol City of Bristol BS10 5LZ",
    "addr:housenumber":"459",
    "addr:postcode":"bs10 5lz",
    "addr:street":"Southmead Road",
    "iso:country":"GB",
    "sg:address":"459 Southmead Road, Southmead",
    "sg:city":"Bristol",
    "sg:classifiers":[
        {
            "category":"Professional",
            "subcategory":"Business Services",
            "type":"Services"
        }
    ],
    "sg:phone":"+44 117 987 3929",
    "sg:postcode":"BS10 5LZ",
    "sg:province":"City of Bristol",
    "sg:tags":[
        "bookmaker"
    ],
    "wof:name":"Southmead Racing",
    "wof:placetype":"venue"
},
  "geometry": {"coordinates":[-2.5928339958,51.5008010864],"type":"Point"}
}