{
  "type": "Feature",
  "properties": {
    "iso:country":"GB",
    "sg:address":"Glengate",
    "sg:city":"Kirriemuir",
    "sg:classifiers":[
        {
            "category":"Retail",
            "subcategory":"Auto Repair",
            "type":"Services"
        }
    ],
    "sg:phone":"+44 1575 574258",
    "sg:postcode":"DD8 4JX",
    "sg:province":"Angus",
    "sg:tags":[
        "modification",
        "garage"
    ],
    "wof:name":"Glengate Garage",
    "wof:placetype":"venue"
},
  "geometry": {"coordinates":[-3.013044,56.676125],"type":"Point"}
}