{
  "type": "Feature",
  "properties": {
    "iso:country":"GB",
    "sg:address":"Blake Hall Farm, Langley La",
    "sg:city":"Preston",
    "sg:classifiers":[
        {
            "category":"Farming",
            "subcategory":"Dairy Farm",
            "type":"Manufacturing & Wholesale Goods"
        }
    ],
    "sg:phone":"+44 1772 862250",
    "sg:postcode":"PR3 2JS",
    "sg:province":"Lancashire",
    "wof:name":"Anns Dairy Products",
    "wof:placetype":"venue"
},
  "geometry": {"coordinates":[-2.69474,53.839642],"type":"Point"}
}