{
  "type": "Feature",
  "properties": {
    "iso:country":"GB",
    "sg:address":"Woodside Farm, Duttons Lane, Roughley",
    "sg:city":"Sutton Coldfield",
    "sg:classifiers":[
        {
            "category":"Building & Trades",
            "subcategory":"Construction",
            "type":"Services"
        }
    ],
    "sg:phone":"+44 121 323 4789",
    "sg:postcode":"B75 5RJ",
    "sg:province":"Staffordshire",
    "sg:tags":[
        "contractor",
        "paving",
        "driveway"
    ],
    "wof:name":"L & H Driveways Ltd.",
    "wof:placetype":"venue"
},
  "geometry": {"coordinates":[-1.80607,52.5942],"type":"Point"}
}