{
  "type": "Feature",
  "properties": {
    "iso:country":"GB",
    "sg:address":"Mitalee Centre, Stanley Road",
    "sg:city":"London",
    "sg:classifiers":[
        {
            "category":"Education",
            "subcategory":"Special Training",
            "type":"Public Place"
        }
    ],
    "sg:postcode":"N15 3HB",
    "sg:province":"Greater London",
    "sg:tags":[
        "product",
        "centre"
    ],
    "wof:name":"The Bangladesh Women's Association in Ha",
    "wof:placetype":"venue"
},
  "geometry": {"coordinates":[-0.09766,51.58606],"type":"Point"}
}