{
  "type": "Feature",
  "properties": {
    "addr:full":"110 Hermitage Road, St Johns Woking Surrey GU21 8TQ",
    "addr:housenumber":"110",
    "addr:postcode":"gu21 8tq",
    "addr:street":"Hermitage Road",
    "iso:country":"GB",
    "sg:address":"110 Hermitage Road, St Johns",
    "sg:city":"Woking",
    "sg:classifiers":[
        {
            "category":"Personal",
            "subcategory":"Beauty Salon",
            "type":"Services"
        },
        {
            "category":"Personal",
            "subcategory":"Barber",
            "type":"Services"
        }
    ],
    "sg:phone":"+44 1483 472694",
    "sg:postcode":"GU21 8TQ",
    "sg:province":"Surrey",
    "sg:tags":[
        "unisex",
        "lady",
        "hairdresser"
    ],
    "wof:name":"Headways",
    "wof:placetype":"venue"
},
  "geometry": {"coordinates":[-0.6062819958,51.3125839233],"type":"Point"}
}