{
  "type": "Feature",
  "properties": {
    "iso:country":"GB",
    "sg:address":"Great Chester Farm",
    "sg:city":"Haltwhistle",
    "sg:classifiers":[
        {
            "category":"Farming",
            "subcategory":"Farm",
            "type":"Manufacturing & Wholesale Goods"
        }
    ],
    "sg:postcode":"NE49 9NF",
    "sg:province":"Northumberland",
    "sg:tags":[
        "mixed",
        "crop"
    ],
    "wof:name":"J E Woodman & Son",
    "wof:placetype":"venue"
},
  "geometry": {"coordinates":[-2.464497,54.968594],"type":"Point"}
}