{
  "type": "Feature",
  "properties": {
    "addr:full":"70 Cambridge Road Southampton Hampshire SO14 6US",
    "addr:housenumber":"70",
    "addr:postcode":"so14 6us",
    "addr:street":"Cambridge Road",
    "iso:country":"GB",
    "sg:address":"70 Cambridge Road",
    "sg:city":"Southampton",
    "sg:classifiers":[
        {
            "category":"Food & Beverages",
            "subcategory":"Liquor & Beverages",
            "type":"Retail Goods"
        }
    ],
    "sg:phone":"+44 23 8055 4881",
    "sg:postcode":"SO14 6US",
    "sg:province":"Hampshire",
    "sg:tags":[
        "beer",
        "spirit",
        "wines"
    ],
    "wof:name":"Bitter Virtue",
    "wof:placetype":"venue"
},
  "geometry": {"coordinates":[-1.4018759727,50.9213294983],"type":"Point"}
}