{
  "type": "Feature",
  "properties": {
    "iso:country":"GB",
    "sg:address":"55 St. Pauls Sq",
    "sg:city":"Birmingham",
    "sg:classifiers":[
        {
            "category":"Professional",
            "subcategory":"Advertising",
            "type":"Services"
        }
    ],
    "sg:phone":"+44 121 233 3770",
    "sg:postcode":"B3 1QS",
    "sg:province":"West Midlands",
    "sg:tags":[
        "agency"
    ],
    "wof:name":"Sutcliffe Reynolds Fitzgerald",
    "wof:placetype":"venue"
},
  "geometry": {"coordinates":[-1.90603,52.484447],"type":"Point"}
}