{
  "type": "Feature",
  "properties": {
    "addr:full":"71 Greenford Avenue London Greater London W7 1LJ",
    "addr:housenumber":"71",
    "addr:postcode":"w7 1lj",
    "addr:street":"Greenford Avenue",
    "iso:country":"GB",
    "sg:address":"71 Greenford Avenue",
    "sg:city":"London",
    "sg:classifiers":[
        {
            "category":"Retail",
            "subcategory":"Funeral Services",
            "type":"Services"
        }
    ],
    "sg:postcode":"W7 1LJ",
    "sg:province":"Greater London",
    "wof:name":"Christopher Wickenden Funeral Services",
    "wof:placetype":"venue"
},
  "geometry": {"coordinates":[-0.3372499943,51.5146865845],"type":"Point"}
}