{
  "type": "Feature",
  "properties": {
    "iso:country":"GB",
    "sg:address":"The Sidings, Cammock Lane",
    "sg:city":"Settle",
    "sg:classifiers":[
        {
            "category":"Manufacturing",
            "subcategory":"Apparel",
            "type":"Manufacturing & Wholesale Goods"
        }
    ],
    "sg:phone":"+44 1729 825446",
    "sg:postcode":"BD24 9BH",
    "sg:province":"North Yorkshire",
    "sg:tags":[
        "garment",
        "designer"
    ],
    "wof:name":"Neil Holgate",
    "wof:placetype":"venue"
},
  "geometry": {"coordinates":[-2.277606,54.069759],"type":"Point"}
}