{
  "type": "Feature",
  "properties": {
    "addr:full":"31a Derby Road Enfield Greater London EN3 4AJ",
    "addr:housenumber":"31a",
    "addr:postcode":"en3 4aj",
    "addr:street":"Derby Road",
    "iso:country":"GB",
    "sg:address":"31a Derby Road",
    "sg:city":"Enfield",
    "sg:classifiers":[
        {
            "category":"Personal",
            "type":"Services"
        },
        {
            "category":"Professional",
            "subcategory":"Lawyer & Legal Services",
            "type":"Services"
        }
    ],
    "sg:phone":"+44 20 8351 8934",
    "sg:postcode":"EN3 4AJ",
    "sg:province":"Greater London",
    "sg:tags":[
        "advice",
        "counselling"
    ],
    "wof:name":"Enfield Womens Centre",
    "wof:placetype":"venue"
},
  "geometry": {"coordinates":[-0.0487949997,51.6445808411],"type":"Point"}
}