{
  "type": "Feature",
  "properties": {
    "addr:full":"1 Bassett Close, Shawclough Rochdale Lancashire OL12 6NR",
    "addr:housenumber":"1",
    "addr:postcode":"ol12 6nr",
    "addr:street":"Bassett Close;Rochdale",
    "iso:country":"GB",
    "sg:address":"1 Bassett Close, Shawclough",
    "sg:city":"Rochdale",
    "sg:classifiers":[
        {
            "category":"Home & Garden",
            "subcategory":"Household Appliances",
            "type":"Retail Goods"
        }
    ],
    "sg:postcode":"OL12 6NR",
    "sg:province":"Lancashire",
    "sg:tags":[
        "electrical"
    ],
    "wof:name":"Tony Wild Repairs & Service",
    "wof:placetype":"venue"
},
  "geometry": {"coordinates":[-2.1673839092,53.6314811707],"type":"Point"}
}