{
  "type": "Feature",
  "properties": {
    "iso:country":"GB",
    "sg:address":"The Strand",
    "sg:city":"Rye",
    "sg:classifiers":[
        {
            "category":"Travel",
            "subcategory":"Hotels & Motels",
            "type":"Entertainment"
        }
    ],
    "sg:phone":"+44 1797 222128",
    "sg:postcode":"TN31 7DB",
    "sg:province":"East Sussex",
    "wof:name":"The Old Borough Arms",
    "wof:placetype":"venue"
},
  "geometry": {"coordinates":[0.730801,50.949398],"type":"Point"}
}