{
  "type": "Feature",
  "properties": {
    "addr:full":"7 Chapel Street Ct Poulton-le-fylde Lancashire FY6 7BH",
    "addr:housenumber":"7",
    "addr:postcode":"fy6 7bh",
    "addr:street":"Chapel Street Ct Poulton-Le-Fylde",
    "iso:country":"GB",
    "sg:address":"7 Chapel Street Ct",
    "sg:city":"Poulton-le-fylde",
    "sg:classifiers":[
        {
            "category":"Fast Food",
            "type":"Food & Drink"
        }
    ],
    "sg:postcode":"FY6 7BH",
    "sg:province":"Lancashire",
    "sg:tags":[
        "away",
        "take"
    ],
    "wof:name":"Moss,Dawn,",
    "wof:placetype":"venue"
},
  "geometry": {"coordinates":[-2.990942,53.847111],"type":"Point"}
}