{
  "type": "Feature",
  "properties": {
    "iso:country":"GB",
    "sg:address":"7 Chapel Street Ct",
    "sg:city":"Poulton-le-fylde",
    "sg:classifiers":[
        {
            "category":"Fast Food",
            "type":"Food & Drink"
        }
    ],
    "sg:postcode":"FY6 7BH",
    "sg:province":"Lancashire",
    "sg:tags":[
        "away",
        "take"
    ],
    "wof:name":"Moss,Dawn,",
    "wof:placetype":"venue"
},
  "geometry": {"coordinates":[-2.990942,53.847111],"type":"Point"}
}