{
  "type": "Feature",
  "properties": {
    "addr:full":"104 Saffron Drive Christchurch Dorset BH23 4TG",
    "addr:housenumber":"104",
    "addr:postcode":"bh23 4tg",
    "addr:street":"Saffron Drive",
    "iso:country":"GB",
    "sg:address":"104 Saffron Drive",
    "sg:city":"Christchurch",
    "sg:classifiers":[
        {
            "category":"Health Services",
            "subcategory":"Dentist",
            "type":"Services"
        }
    ],
    "sg:phone":"+44 1425 277245",
    "sg:postcode":"BH23 4TG",
    "sg:province":"Dorset",
    "wof:name":"Newman & Associates",
    "wof:placetype":"venue"
},
  "geometry": {"coordinates":[-1.735509038,50.7431297302],"type":"Point"}
}