{
  "type": "Feature",
  "properties": {
    "addr:full":"29 Wilmot Road Swadlincote Derbyshire DE11 9BH",
    "addr:housenumber":"29",
    "addr:postcode":"de11 9bh",
    "addr:street":"Wilmot Road",
    "iso:country":"GB",
    "sg:address":"29 Wilmot Road",
    "sg:city":"Swadlincote",
    "sg:classifiers":[
        {
            "category":"Building & Trades",
            "subcategory":"Plumbing",
            "type":"Services"
        }
    ],
    "sg:phone":"+44 1283 222732",
    "sg:postcode":"DE11 9BH",
    "sg:province":"Derbyshire",
    "sg:tags":[
        "heating"
    ],
    "wof:name":"Steve Pickess",
    "wof:placetype":"venue"
},
  "geometry": {"coordinates":[-1.562926,52.770817],"type":"Point"}
}