{
  "type": "Feature",
  "properties": {
    "addr:full":"Unit 13 Argyle Way Ely Distribution Cent, Ely Cardiff Cardiff CF5 5NJ",
    "addr:housenumber":"unit 13",
    "addr:postcode":"cf5 5nj",
    "addr:street":"Argyle Way",
    "iso:country":"GB",
    "sg:address":"Unit 13 Argyle Way Ely Distribution Cent, Ely",
    "sg:city":"Cardiff",
    "sg:classifiers":[
        {
            "category":"Retail",
            "subcategory":"Auto Repair",
            "type":"Services"
        }
    ],
    "sg:postcode":"CF5 5NJ",
    "sg:province":"Cardiff",
    "sg:tags":[
        "engine",
        "car",
        "specialist"
    ],
    "wof:name":"James,Paul,",
    "wof:placetype":"venue"
},
  "geometry": {"coordinates":[-3.236379,51.472649],"type":"Point"}
}