{
  "type": "Feature",
  "properties": {
    "addr:full":"Pool Street Wolverhampton West Midlands WV2 4HN",
    "addr:postcode":"wv2 4hn",
    "addr:street":"Pool Street",
    "iso:country":"GB",
    "sg:address":"Pool Street",
    "sg:city":"Wolverhampton",
    "sg:classifiers":[
        {
            "category":"Home & Garden",
            "subcategory":"Hardware",
            "type":"Retail Goods"
        }
    ],
    "sg:phone":"+44 1902 428381",
    "sg:postcode":"WV2 4HN",
    "sg:province":"West Midlands",
    "sg:tags":[
        "device",
        "fixing",
        "fastener"
    ],
    "wof:name":"Martin Scott Fasteners",
    "wof:placetype":"venue"
},
  "geometry": {"coordinates":[-2.1312100887,52.5785980225],"type":"Point"}
}