{
  "type": "Feature",
  "properties": {
    "iso:country":"GB",
    "sg:address":"57 Arcot Street",
    "sg:city":"Penarth",
    "sg:classifiers":[
        {
            "category":"Insurance",
            "subcategory":"Insurance Agent",
            "type":"Services"
        }
    ],
    "sg:postcode":"CF64 1ET",
    "sg:province":"The Vale of Glamorgan",
    "wof:name":"R W Mott & Partners",
    "wof:placetype":"venue"
},
  "geometry": {"coordinates":[-3.176295,51.441238],"type":"Point"}
}