{
  "type": "Feature",
  "properties": {
    "iso:country":"GB",
    "sg:address":"4 Gill Wk, Shelton",
    "sg:city":"Stoke-on-trent",
    "sg:classifiers":[
        {
            "category":"Professional",
            "subcategory":"Engineering",
            "type":"Services"
        },
        {
            "category":"Shopping",
            "subcategory":"Computers & Home Electronics",
            "type":"Retail Goods"
        }
    ],
    "sg:postcode":"ST1 4LH",
    "sg:province":"Staffordshire",
    "sg:tags":[
        "television",
        "aerial",
        "contractor",
        "electrical",
        "radio",
        "engineer"
    ],
    "wof:name":"Venables,Malcolm G,",
    "wof:placetype":"venue"
},
  "geometry": {"coordinates":[-2.182899,53.02063],"type":"Point"}
}