{
  "type": "Feature",
  "properties": {
    "iso:country":"GB",
    "sg:address":"12 Vicarage Street, Oldbury",
    "sg:city":"Birmingham",
    "sg:classifiers":[
        {
            "category":"Retail",
            "subcategory":"Driving School",
            "type":"Services"
        }
    ],
    "sg:phone":"+44 121 533 9132",
    "sg:postcode":"B68 8HQ",
    "sg:province":"West Midlands",
    "wof:name":"Alert School of Motoring",
    "wof:placetype":"venue"
},
  "geometry": {"coordinates":[-2.0011029243,52.4915275574],"type":"Point"}
}