{
  "type": "Feature",
  "properties": {
    "iso:country":"GB",
    "sg:address":"Railway Street",
    "sg:city":"Chelmsford",
    "sg:classifiers":[
        {
            "category":"Shopping",
            "subcategory":"Computers & Home Electronics",
            "type":"Retail Goods"
        }
    ],
    "sg:phone":"+44 1245 357066",
    "sg:postcode":"CM1 1QS",
    "sg:province":"Essex",
    "sg:tags":[
        "electrical"
    ],
    "wof:name":"Burrows Electrical Wholesale Ltd.",
    "wof:placetype":"venue"
},
  "geometry": {"coordinates":[0.467049,51.737385],"type":"Point"}
}