{
  "type": "Feature",
  "properties": {
    "addr:full":"58-62 Kingsbury Road, Erdington Birmingham West Midlands B24 8QJ",
    "addr:housenumber":"58-62",
    "addr:postcode":"b24 8qj",
    "addr:street":"Kingsbury Road",
    "iso:country":"GB",
    "sg:address":"58-62 Kingsbury Road, Erdington",
    "sg:city":"Birmingham",
    "sg:classifiers":[
        {
            "category":"Health Services",
            "subcategory":"Nursing And Care Facility",
            "type":"Services"
        }
    ],
    "sg:phone":"+44 121 350 3553",
    "sg:postcode":"B24 8QJ",
    "sg:province":"West Midlands",
    "sg:tags":[
        "home"
    ],
    "wof:name":"Kingsmere Nursing Home",
    "wof:placetype":"venue"
},
  "geometry": {"coordinates":[-1.8477669954,52.5141716003],"type":"Point"}
}