{
  "type": "Feature",
  "properties": {
    "addr:full":"Micro-world House, Park Road West Huddersfield West Yorkshire HD4 5RX",
    "addr:postcode":"hd4 5rx",
    "addr:street":"Park Road West",
    "iso:country":"GB",
    "sg:address":"Micro-world House, Park Road West",
    "sg:city":"Huddersfield",
    "sg:classifiers":[
        {
            "category":"Professional",
            "subcategory":"Computer Services",
            "type":"Services"
        }
    ],
    "sg:postcode":"HD4 5RX",
    "sg:province":"West Yorkshire",
    "sg:tags":[
        "system",
        "software"
    ],
    "wof:name":"Micro-World Computers",
    "wof:placetype":"venue"
},
  "geometry": {"coordinates":[-1.808128953,53.6378135681],"type":"Point"}
}