{
  "type": "Feature",
  "properties": {
    "iso:country":"GB",
    "sg:address":"Pepper Road, Hazel Grove",
    "sg:city":"Stockport",
    "sg:classifiers":[
        {
            "category":"Wholesale",
            "subcategory":"Sporting Goods",
            "type":"Manufacturing & Wholesale Goods"
        }
    ],
    "sg:phone":"+44 161 419 2500",
    "sg:postcode":"SK7 5SA",
    "sg:province":"Cheshire",
    "sg:tags":[
        "mnfr",
        "sport",
        "equipment"
    ],
    "wof:name":"Adidas Trefoil Trading (U K) Ltd.",
    "wof:placetype":"venue"
},
  "geometry": {"coordinates":[-2.137787,53.377171],"type":"Point"}
}