{
  "type": "Feature",
  "properties": {
    "addr:full":"26 Otley Road, Guisley Leeds West Yorkshire LS20 8AH",
    "addr:housenumber":"26",
    "addr:postcode":"ls20 8ah",
    "addr:street":"Otley Road Guisley Leeds West",
    "iso:country":"GB",
    "sg:address":"26 Otley Road, Guisley",
    "sg:city":"Leeds",
    "sg:classifiers":[
        {
            "category":"Shopping",
            "subcategory":"Pharmacy",
            "type":"Retail Goods"
        }
    ],
    "sg:postcode":"LS20 8AH",
    "sg:province":"West Yorkshire",
    "sg:tags":[
        "pharmacist",
        "chemist"
    ],
    "wof:name":"Broading Pharmacy",
    "wof:placetype":"venue"
},
  "geometry": {"coordinates":[-1.7105460167,53.8731918335],"type":"Point"}
}