{
  "type": "Feature",
  "properties": {
    "addr:full":"Maesteg Terrace, Glan Road Porthcawl Bridgend CF36 5DF",
    "addr:postcode":"cf36 5df",
    "addr:street":"Maesteg Terrace Glan Road",
    "iso:country":"GB",
    "sg:address":"Maesteg Terrace, Glan Road",
    "sg:city":"Porthcawl",
    "sg:classifiers":[
        {
            "category":"Building & Trades",
            "subcategory":"Construction",
            "type":"Services"
        }
    ],
    "sg:postcode":"CF36 5DF",
    "sg:province":"Bridgend",
    "sg:tags":[
        "builder"
    ],
    "wof:name":"Horton Grinding Co",
    "wof:placetype":"venue"
},
  "geometry": {"coordinates":[-3.690919,51.48761],"type":"Point"}
}