{
  "type": "Feature",
  "properties": {
    "addr:full":"Raans Road Amersham Buckinghamshire HP6 6LX",
    "addr:postcode":"hp6 6lx",
    "addr:street":"Raans Road",
    "iso:country":"GB",
    "sg:address":"Raans Road",
    "sg:city":"Amersham",
    "sg:classifiers":[
        {
            "category":"Organizations",
            "subcategory":"Membership Organization",
            "type":"Services"
        }
    ],
    "sg:phone":"+44 1494 727173",
    "sg:postcode":"HP6 6LX",
    "sg:province":"Buckinghamshire",
    "sg:tags":[
        "club",
        "social"
    ],
    "wof:name":"Polish Ex-Servicemens Club",
    "wof:placetype":"venue"
},
  "geometry": {"coordinates":[-0.588944,51.673737],"type":"Point"}
}