{
  "type": "Feature",
  "properties": {
    "iso:country":"GB",
    "sg:address":"15 Hill Top Walk, Bilton",
    "sg:city":"Harrogate",
    "sg:classifiers":[
        {
            "category":"Personal",
            "type":"Services"
        }
    ],
    "sg:postcode":"HG1 3BX",
    "sg:province":"North Yorkshire",
    "sg:tags":[
        "wedding"
    ],
    "wof:name":"Graceful Favours",
    "wof:placetype":"venue"
},
  "geometry": {"coordinates":[-1.539109,54.010353],"type":"Point"}
}