{
  "type": "Feature",
  "properties": {
    "iso:country":"GB",
    "sg:address":"The Old Bakery, Claremont Street",
    "sg:city":"Ashton-under-lyne",
    "sg:classifiers":[
        {
            "category":"Retail",
            "subcategory":"Auto Repair",
            "type":"Services"
        }
    ],
    "sg:postcode":"OL6 8EN",
    "sg:province":"Greater Manchester",
    "sg:tags":[
        "modification",
        "garage"
    ],
    "wof:name":"Vehicle Services & Repairs",
    "wof:placetype":"venue"
},
  "geometry": {"coordinates":[-2.088242,53.489239],"type":"Point"}
}