{
  "type": "Feature",
  "properties": {
    "iso:country":"GB",
    "sg:address":"Spring House, 24 Wavell Avenue",
    "sg:city":"Colchester",
    "sg:classifiers":[
        {
            "category":"Professional",
            "subcategory":"Management & Consulting",
            "type":"Services"
        }
    ],
    "sg:postcode":"CO2 7HR",
    "sg:province":"Essex",
    "sg:tags":[
        "consultant",
        "business"
    ],
    "wof:name":"Life Directions Ltd.",
    "wof:placetype":"venue"
},
  "geometry": {"coordinates":[0.881221,51.877316],"type":"Point"}
}