{
  "type": "Feature",
  "properties": {
    "addr:full":"Unit 24-25 Mini Unit Site, Southwall Industrial Estate Deal Kent CT14 6RE",
    "addr:housenumber":"unit 24-25;unit site",
    "addr:postcode":"ct14 6re",
    "addr:street":"Industrial Estate",
    "iso:country":"GB",
    "sg:address":"Unit 24-25 Mini Unit Site, Southwall Industrial Estate",
    "sg:city":"Deal",
    "sg:classifiers":[
        {
            "category":"Retail",
            "subcategory":"Auto Repair",
            "type":"Services"
        }
    ],
    "sg:postcode":"CT14 6RE",
    "sg:province":"Kent",
    "sg:tags":[
        "modification",
        "garage"
    ],
    "wof:name":"Collect Vehicle Repairs",
    "wof:placetype":"venue"
},
  "geometry": {"coordinates":[1.4032349586,51.2231292725],"type":"Point"}
}