{
  "type": "Feature",
  "properties": {
    "addr:full":"51 Meadowlands Avenue, Hampden Park Eastbourne East Sussex BN22 0DU",
    "addr:housenumber":"51",
    "addr:postcode":"bn22 0du",
    "addr:street":"Meadowlands Avenue",
    "iso:country":"GB",
    "sg:address":"51 Meadowlands Avenue, Hampden Park",
    "sg:city":"Eastbourne",
    "sg:classifiers":[
        {
            "category":"Building & Trades",
            "subcategory":"Construction",
            "type":"Services"
        }
    ],
    "sg:postcode":"BN22 0DU",
    "sg:province":"East Sussex",
    "sg:tags":[
        "glazier",
        "decorator",
        "painter"
    ],
    "wof:name":"M D Benneyworth Painting & Decorating",
    "wof:placetype":"venue"
},
  "geometry": {"coordinates":[0.2643840015,50.7990379333],"type":"Point"}
}