{
  "type": "Feature",
  "properties": {
    "iso:country":"GB",
    "sg:address":"3 Dereham Road, Mattishall",
    "sg:city":"Dereham",
    "sg:classifiers":[
        {
            "category":"Bars & Pubs",
            "type":"Food & Drink"
        },
        {
            "category":"Community Center",
            "subcategory":"Social",
            "type":"Public Place"
        }
    ],
    "sg:phone":"+44 1362 850305",
    "sg:postcode":"NR20 3QB",
    "sg:province":"Norfolk",
    "sg:tags":[
        "pubs",
        "house",
        "inn",
        "activity"
    ],
    "wof:name":"THE SWAN PUBLIC HOUSE",
    "wof:placetype":"venue"
},
  "geometry": {"coordinates":[1.019303,52.66061],"type":"Point"}
}