{
  "type": "Feature",
  "properties": {
    "addr:full":"Newark House, 26-45 Cheltenham Street Bath Somerset BA2 3EX",
    "addr:housenumber":"26-45",
    "addr:postcode":"ba2 3ex",
    "addr:street":"Cheltenham Street",
    "iso:country":"GB",
    "sg:address":"Newark House, 26-45 Cheltenham Street",
    "sg:city":"Bath",
    "sg:classifiers":[
        {
            "category":"Professional",
            "subcategory":"Engineering",
            "type":"Services"
        }
    ],
    "sg:postcode":"BA2 3EX",
    "sg:province":"Somerset",
    "sg:tags":[
        "consulting",
        "engineer"
    ],
    "wof:name":"Thales Geosolutions Ltd.",
    "wof:placetype":"venue"
},
  "geometry": {"coordinates":[-2.3694589138,51.3784255981],"type":"Point"}
}