{
  "type": "Feature",
  "properties": {
    "addr:full":"3rd Flr, Northburgh House London Greater London EC1V 0AT",
    "addr:housenumber":"3rd flr northburgh house",
    "addr:postcode":"ec1v 0at",
    "iso:country":"GB",
    "sg:address":"3rd Flr, Northburgh House",
    "sg:city":"London",
    "sg:classifiers":[
        {
            "category":"Professional",
            "subcategory":"Management & Consulting",
            "type":"Services"
        }
    ],
    "sg:postcode":"EC1V 0AT",
    "sg:province":"Greater London",
    "sg:tags":[
        "marketing",
        "consultant"
    ],
    "wof:name":"Dlb Marketing",
    "wof:placetype":"venue"
},
  "geometry": {"coordinates":[-0.10054,51.524021],"type":"Point"}
}