{
  "type": "Feature",
  "properties": {
    "iso:country":"GB",
    "sg:address":"70 Cardinals Gate",
    "sg:city":"Peterborough",
    "sg:classifiers":[
        {
            "category":"Personal",
            "subcategory":"Psychics & Astrologers",
            "type":"Services"
        }
    ],
    "sg:postcode":"PE4 5AT",
    "sg:province":"Cambridgeshire",
    "wof:name":"Jan Ross Professional Astrologer",
    "wof:placetype":"venue"
},
  "geometry": {"coordinates":[-0.286218,52.620548],"type":"Point"}
}