{
  "type": "Feature",
  "properties": {
    "addr:full":"44 Corringway Ealing Greater London W5 3AD",
    "addr:housenumber":"44",
    "addr:postcode":"w5 3ad",
    "addr:street":"Corringway",
    "iso:country":"GB",
    "sg:address":"44 Corringway",
    "sg:city":"Ealing",
    "sg:classifiers":[
        {
            "category":"Health Services",
            "subcategory":"Dentist",
            "type":"Services"
        }
    ],
    "sg:phone":"+44 20 8998 3423",
    "sg:postcode":"W5 3AD",
    "sg:province":"Greater London",
    "wof:name":"Jonathan Kay",
    "wof:placetype":"venue"
},
  "geometry": {"coordinates":[-0.286433,51.520672],"type":"Point"}
}