{
  "type": "Feature",
  "properties": {
    "addr:full":"2270 Coventry Rd Birmingham West Midlands B26 3JP",
    "addr:housenumber":"2270",
    "addr:postcode":"b26 3jp",
    "addr:street":"Coventry Rd",
    "iso:country":"GB",
    "sg:address":"2270 Coventry Rd",
    "sg:city":"Birmingham",
    "sg:classifiers":[
        {
            "category":"Travel",
            "subcategory":"Travel Agent",
            "type":"Entertainment"
        }
    ],
    "sg:phone":"+44 121 742 5151",
    "sg:postcode":"B26 3JP",
    "sg:province":"West Midlands",
    "wof:name":"Travelcare",
    "wof:placetype":"venue"
},
  "geometry": {"coordinates":[-1.77765,52.451668],"type":"Point"}
}