{
  "type": "Feature",
  "properties": {
    "iso:country":"GB",
    "sg:address":"70 Spital Street",
    "sg:city":"Dartford",
    "sg:classifiers":[
        {
            "category":"Restaurant",
            "type":"Food & Drink"
        }
    ],
    "sg:phone":"+44 1322 224691",
    "sg:postcode":"DA1 2DT",
    "sg:province":"Kent",
    "wof:name":"The Hide Out",
    "wof:placetype":"venue"
},
  "geometry": {"coordinates":[0.213007,51.444946],"type":"Point"}
}