{
  "type": "Feature",
  "properties": {
    "iso:country":"GB",
    "sg:address":"Unit W6",
    "sg:city":"Halifax",
    "sg:classifiers":[
        {
            "category":"Building & Trades",
            "subcategory":"Construction",
            "type":"Services"
        }
    ],
    "sg:phone":"+44 1422 886871",
    "sg:postcode":"HX2 6EQ",
    "sg:province":"West Yorkshire",
    "sg:tags":[
        "joiner",
        "carpenter"
    ],
    "wof:name":"Steadfast Joinery",
    "wof:placetype":"venue"
},
  "geometry": {"coordinates":[-1.9419569969,53.7257347107],"type":"Point"}
}