{
  "type": "Feature",
  "properties": {
    "addr:full":"Home Farm Barn, Winkburn Newark Nottinghamshire NG22 8PQ",
    "addr:postcode":"ng22 8pq",
    "iso:country":"GB",
    "sg:address":"Home Farm Barn, Winkburn",
    "sg:city":"Newark",
    "sg:classifiers":[
        {
            "category":"Real Estate",
            "subcategory":"Surveying",
            "type":"Services"
        }
    ],
    "sg:phone":"+44 1636 636699",
    "sg:postcode":"NG22 8PQ",
    "sg:province":"Nottinghamshire",
    "sg:tags":[
        "surveyor",
        "valuer"
    ],
    "wof:name":"Wayleave Services Ltd",
    "wof:placetype":"venue"
},
  "geometry": {"coordinates":[-0.9407190084,53.1183891296],"type":"Point"}
}