{
  "type": "Feature",
  "properties": {
    "iso:country":"GB",
    "sg:address":"15 Progress Business Centre, Whittle Parkway",
    "sg:city":"Slough",
    "sg:classifiers":[
        {
            "category":"Professional",
            "subcategory":"Management & Consulting",
            "type":"Services"
        }
    ],
    "sg:phone":"+44 1628 663600",
    "sg:postcode":"SL1 6DQ",
    "sg:province":"Berkshire",
    "sg:tags":[
        "consultant",
        "promotion",
        "direct",
        "sale"
    ],
    "wof:name":"Fontwood Ltd.",
    "wof:placetype":"venue"
},
  "geometry": {"coordinates":[-0.650409,51.522224],"type":"Point"}
}