{
  "type": "Feature",
  "properties": {
    "addr:full":"Lyster Road Bootle Merseyside L20 1AS",
    "addr:postcode":"l20 1as",
    "addr:street":"Lyster Road",
    "iso:country":"GB",
    "sg:address":"Lyster Road",
    "sg:city":"Bootle",
    "sg:classifiers":[
        {
            "category":"Shopping",
            "subcategory":"Pets & Pet Supplies",
            "type":"Retail Goods"
        }
    ],
    "sg:phone":"+44 151 933 2892",
    "sg:postcode":"L20 1AS",
    "sg:province":"Merseyside",
    "sg:tags":[
        "food"
    ],
    "wof:name":"A-One Feed Supplements",
    "wof:placetype":"venue"
},
  "geometry": {"coordinates":[-3.0031340122,53.4512443542],"type":"Point"}
}