{
  "type": "Feature",
  "properties": {
    "iso:country":"GB",
    "sg:address":"Edward Ho, Edward St",
    "sg:city":"Stockport",
    "sg:classifiers":[
        {
            "category":"Organizations",
            "subcategory":"Professional Association",
            "type":"Services"
        }
    ],
    "sg:phone":"+44 161 480 3280",
    "sg:postcode":"SK1 3DQ",
    "sg:province":"Cheshire",
    "sg:tags":[
        "union",
        "trade"
    ],
    "wof:name":"GMB",
    "wof:placetype":"venue"
},
  "geometry": {"coordinates":[-2.155332,53.406509],"type":"Point"}
}