{
  "type": "Feature",
  "properties": {
    "addr:full":"12 Morningside Place Aberdeen Aberdeen City AB10 7NG",
    "addr:housenumber":"12",
    "addr:postcode":"ab10 7ng",
    "addr:street":"Morningside Place",
    "iso:country":"GB",
    "sg:address":"12 Morningside Place",
    "sg:city":"Aberdeen",
    "sg:classifiers":[
        {
            "category":"Professional",
            "subcategory":"Engineering",
            "type":"Services"
        }
    ],
    "sg:phone":"+44 1224 323664",
    "sg:postcode":"AB10 7NG",
    "sg:province":"Aberdeen City",
    "sg:tags":[
        "contractor",
        "electrical",
        "engineer"
    ],
    "wof:name":"I.G.S Electrical Services",
    "wof:placetype":"venue"
},
  "geometry": {"coordinates":[-2.1349229813,57.1266212463],"type":"Point"}
}