{
  "type": "Feature",
  "properties": {
    "iso:country":"GB",
    "sg:address":"Kirkstall Lodge, Suite 1 & 6, High Street",
    "sg:city":"Nottingham",
    "sg:classifiers":[
        {
            "category":"Banks & Credit Unions",
            "subcategory":"Financial Services",
            "type":"Services"
        }
    ],
    "sg:phone":"+44 1623 823833",
    "sg:postcode":"NG21 9QS",
    "sg:province":"Nottinghamshire",
    "sg:tags":[
        "adviser"
    ],
    "wof:name":"Flynn Associates Ltd.",
    "wof:placetype":"venue"
},
  "geometry": {"coordinates":[-1.064723,53.19495],"type":"Point"}
}