{
  "type": "Feature",
  "properties": {
    "iso:country":"GB",
    "sg:address":"Glebe Farm, Main Street, Upton",
    "sg:city":"Newark",
    "sg:classifiers":[
        {
            "category":"Building & Trades",
            "subcategory":"Equipment Rental",
            "type":"Services"
        }
    ],
    "sg:phone":"+44 1636 815082",
    "sg:postcode":"NG23 5ST",
    "sg:province":"Lincolnshire",
    "sg:tags":[
        "plant",
        "machinery"
    ],
    "wof:name":"C & A Building Services",
    "wof:placetype":"venue"
},
  "geometry": {"coordinates":[-0.901979,53.08213],"type":"Point"}
}