{
  "type": "Feature",
  "properties": {
    "addr:full":"Cox Green Road, Egerton Bolton Lancashire BL7 9RJ",
    "addr:postcode":"bl7 9rj",
    "addr:street":"Cox Green Road",
    "iso:country":"GB",
    "sg:address":"Cox Green Road, Egerton",
    "sg:city":"Bolton",
    "sg:classifiers":[
        {
            "category":"Real Estate",
            "subcategory":"Real Estate Agent",
            "type":"Services"
        }
    ],
    "sg:phone":"+44 1204 596586",
    "sg:postcode":"BL7 9RJ",
    "sg:province":"Lancashire",
    "wof:name":"Apex Lettings",
    "wof:placetype":"venue"
},
  "geometry": {"coordinates":[-2.440946,53.6339],"type":"Point"}
}