{
  "type": "Feature",
  "properties": {
    "iso:country":"GB",
    "sg:address":"40 Kirk Rd",
    "sg:city":"Wishaw",
    "sg:classifiers":[
        {
            "category":"Food & Beverages",
            "subcategory":"Meat & Fish",
            "type":"Retail Goods"
        }
    ],
    "sg:phone":"+44 1698 376829",
    "sg:postcode":"ML2 7BL",
    "sg:province":"North Lanarkshire",
    "sg:tags":[
        "chip"
    ],
    "wof:name":"Mario & Son",
    "wof:placetype":"venue"
},
  "geometry": {"coordinates":[-3.9148890972,55.7762985229],"type":"Point"}
}