{
  "type": "Feature",
  "properties": {
    "addr:full":"280 High Street Lincoln Lincolnshire LN2 1JG",
    "addr:housenumber":"280",
    "addr:postcode":"ln2 1jg",
    "addr:street":"High Street",
    "iso:country":"GB",
    "sg:address":"280 High Street",
    "sg:city":"Lincoln",
    "sg:classifiers":[
        {
            "category":"Home & Garden",
            "subcategory":"Furniture",
            "type":"Retail Goods"
        }
    ],
    "sg:phone":"+44 191 260 3277",
    "sg:postcode":"LN2 1JG",
    "sg:province":"Lincolnshire",
    "wof:name":"Darrington Ltd",
    "wof:placetype":"venue"
},
  "geometry": {"coordinates":[-0.539449,53.23151],"type":"Point"}
}