{
  "type": "Feature",
  "properties": {
    "addr:full":"74a Keelings Road Stoke-on-trent Staffordshire ST1 6PB",
    "addr:housenumber":"74a",
    "addr:postcode":"st1 6pb",
    "addr:street":"Keelings Road",
    "iso:country":"GB",
    "sg:address":"74a Keelings Road",
    "sg:city":"Stoke-on-trent",
    "sg:classifiers":[
        {
            "category":"Personal",
            "type":"Services"
        }
    ],
    "sg:postcode":"ST1 6PB",
    "sg:province":"Staffordshire",
    "sg:tags":[
        "wedding"
    ],
    "wof:name":"Aisle of Brides",
    "wof:placetype":"venue"
},
  "geometry": {"coordinates":[-2.1664791107,53.0305633545],"type":"Point"}
}