{
  "type": "Feature",
  "properties": {
    "iso:country":"GB",
    "sg:address":"Bower Bank, 14 Grove Avenue",
    "sg:city":"Wilmslow",
    "sg:classifiers":[
        {
            "category":"Professional",
            "subcategory":"Management & Consulting",
            "type":"Services"
        }
    ],
    "sg:phone":"+44 1625 520523",
    "sg:postcode":"SK9 5EG",
    "sg:province":"Cheshire",
    "sg:tags":[
        "consultant",
        "business"
    ],
    "wof:name":"Interchange Ltd",
    "wof:placetype":"venue"
},
  "geometry": {"coordinates":[-2.2278969288,53.3267974854],"type":"Point"}
}