{
  "type": "Feature",
  "properties": {
    "iso:country":"GB",
    "sg:address":"690 Beverley High Road",
    "sg:city":"Hull",
    "sg:classifiers":[
        {
            "category":"Freight",
            "type":"Transportation"
        }
    ],
    "sg:phone":"+44 1482 803300",
    "sg:postcode":"HU6 7JH",
    "sg:province":"East Riding of Yorkshire",
    "sg:tags":[
        "haulage",
        "road"
    ],
    "wof:name":"A Hamilton Transport",
    "wof:placetype":"venue"
},
  "geometry": {"coordinates":[-0.355692,53.774765],"type":"Point"}
}