{
  "type": "Feature",
  "properties": {
    "addr:full":"3 Layerthorpe York North Yorkshire YO31 7UZ",
    "addr:housenumber":"3",
    "addr:postcode":"yo31 7uz",
    "addr:street":"Layerthorpe",
    "iso:country":"GB",
    "sg:address":"3 Layerthorpe",
    "sg:city":"York",
    "sg:classifiers":[
        {
            "category":"Retail",
            "subcategory":"Auto Repair",
            "type":"Services"
        }
    ],
    "sg:phone":"+44 1904 627716",
    "sg:postcode":"YO31 7UZ",
    "sg:province":"North Yorkshire",
    "sg:tags":[
        "body",
        "car"
    ],
    "wof:name":"Ray Quinn Motor Body Repairs",
    "wof:placetype":"venue"
},
  "geometry": {"coordinates":[-1.0737069845,53.9617500305],"type":"Point"}
}