{
  "type": "Feature",
  "properties": {
    "addr:full":"Unit 9 Kendal Court, Hurricane Way Wickford Essex SS11 8YB",
    "addr:housenumber":"unit 9",
    "addr:postcode":"ss11 8yb",
    "addr:street":"Kendal Court Hurricane Way",
    "iso:country":"GB",
    "sg:address":"Unit 9 Kendal Court, Hurricane Way",
    "sg:city":"Wickford",
    "sg:classifiers":[
        {
            "category":"Education",
            "subcategory":"Special Training",
            "type":"Public Place"
        }
    ],
    "sg:phone":"+44 1268 761942",
    "sg:postcode":"SS11 8YB",
    "sg:province":"Essex",
    "sg:tags":[
        "diving",
        "school"
    ],
    "wof:name":"Scuba",
    "wof:placetype":"venue"
},
  "geometry": {"coordinates":[0.544492,51.602749],"type":"Point"}
}