{
  "type": "Feature",
  "properties": {
    "addr:full":"67 Weald Bridge Road, North Weald Epping Essex CM16 6ES",
    "addr:housenumber":"67",
    "addr:postcode":"cm16 6es",
    "addr:street":"Weald Bridge Road North",
    "iso:country":"GB",
    "sg:address":"67 Weald Bridge Road, North Weald",
    "sg:city":"Epping",
    "sg:classifiers":[
        {
            "category":"Building & Trades",
            "subcategory":"Landscaping Services",
            "type":"Services"
        }
    ],
    "sg:phone":"+44 1992 522437",
    "sg:postcode":"CM16 6ES",
    "sg:province":"Essex",
    "sg:tags":[
        "forestry",
        "tree"
    ],
    "wof:name":"Epping Tree & Garden Co",
    "wof:placetype":"venue"
},
  "geometry": {"coordinates":[0.185527,51.733719],"type":"Point"}
}