{
  "type": "Feature",
  "properties": {
    "addr:full":"Railway Street, Summerseat Bury Lancashire BL9 5QD",
    "addr:postcode":"bl9 5qd",
    "addr:street":"Railway Street",
    "iso:country":"GB",
    "sg:address":"Railway Street, Summerseat",
    "sg:city":"Bury",
    "sg:classifiers":[
        {
            "category":"Home & Garden",
            "subcategory":"Garden Supply",
            "type":"Retail Goods"
        }
    ],
    "sg:phone":"+44 1204 883048",
    "sg:postcode":"BL9 5QD",
    "sg:province":"Lancashire",
    "sg:tags":[
        "nursery",
        "centre"
    ],
    "wof:name":"Summerseat Garden Centre Ltd.",
    "wof:placetype":"venue"
},
  "geometry": {"coordinates":[-2.3010540009,53.5897331238],"type":"Point"}
}