{
  "type": "Feature",
  "properties": {
    "iso:country":"GB",
    "sg:address":"5 Blandford Place",
    "sg:city":"Seaham",
    "sg:classifiers":[
        {
            "category":"Insurance",
            "subcategory":"Insurance Agent",
            "type":"Services"
        }
    ],
    "sg:postcode":"SR7 7EL",
    "sg:province":"Durham",
    "sg:tags":[
        "broker"
    ],
    "wof:name":"Pounder Insurance Services",
    "wof:placetype":"venue"
},
  "geometry": {"coordinates":[-1.3359730244,54.8374595642],"type":"Point"}
}