{
  "type": "Feature",
  "properties": {
    "iso:country":"GB",
    "sg:address":"Fieldview, Burntwood Lane",
    "sg:city":"London",
    "sg:classifiers":[
        {
            "category":"Arena",
            "subcategory":"Sports Club",
            "type":"Entertainment"
        }
    ],
    "sg:phone":"+44 20 8874 2717",
    "sg:postcode":"SW17 0AH",
    "sg:province":"Greater London",
    "wof:name":"The Spencer Club",
    "wof:placetype":"venue"
},
  "geometry": {"coordinates":[-0.173044,51.441216],"type":"Point"}
}