{
  "type": "Feature",
  "properties": {
    "addr:full":"18 Bache Hall Estate, Upton Chester Cheshire CH2 1BR",
    "addr:housenumber":"18",
    "addr:postcode":"ch2 1br",
    "addr:street":"Bache Hall Estate",
    "iso:country":"GB",
    "sg:address":"18 Bache Hall Estate, Upton",
    "sg:city":"Chester",
    "sg:classifiers":[
        {
            "category":"Professional",
            "subcategory":"Business Services",
            "type":"Services"
        }
    ],
    "sg:phone":"+44 1244 375246",
    "sg:postcode":"CH2 1BR",
    "sg:province":"Cheshire",
    "sg:tags":[
        "shop",
        "cleaning"
    ],
    "wof:name":"A & S Cleaning Services",
    "wof:placetype":"venue"
},
  "geometry": {"coordinates":[-2.8890891075,53.2164764404],"type":"Point"}
}