{
  "type": "Feature",
  "properties": {
    "addr:full":"38 Kyotts Lake Road Birmingham West Midlands B11 1JT",
    "addr:housenumber":"38",
    "addr:postcode":"b11 1jt",
    "addr:street":"Kyotts Lake Road",
    "iso:country":"GB",
    "sg:address":"38 Kyotts Lake Road",
    "sg:city":"Birmingham",
    "sg:classifiers":[
        {
            "category":"Shopping",
            "subcategory":"Clothing, Apparel, & Fashions",
            "type":"Retail Goods"
        }
    ],
    "sg:postcode":"B11 1JT",
    "sg:province":"West Midlands",
    "sg:tags":[
        "clothing",
        "fabric"
    ],
    "wof:name":"Sams (U K) Garments",
    "wof:placetype":"venue"
},
  "geometry": {"coordinates":[-1.8764179945,52.4654808044],"type":"Point"}
}