{
  "type": "Feature",
  "properties": {
    "iso:country":"GB",
    "sg:address":"71 Chantry Way",
    "sg:city":"Andover",
    "sg:classifiers":[
        {
            "category":"Restaurant",
            "type":"Food & Drink"
        }
    ],
    "sg:postcode":"SP10 1LT",
    "sg:province":"Hampshire",
    "wof:name":"Wimpy International Ltd.",
    "wof:placetype":"venue"
},
  "geometry": {"coordinates":[-1.481059,51.209629],"type":"Point"}
}