{
  "type": "Feature",
  "properties": {
    "addr:full":"6 Stroudley Walk London Greater London E3 3EW",
    "addr:housenumber":"6",
    "addr:postcode":"e3 3ew",
    "addr:street":"Stroudley Walk",
    "iso:country":"GB",
    "sg:address":"6 Stroudley Walk",
    "sg:city":"London",
    "sg:classifiers":[
        {
            "category":"Food & Beverages",
            "subcategory":"Meat & Fish",
            "type":"Retail Goods"
        },
        {
            "category":"Food & Beverages",
            "subcategory":"Groceries & Convenience Stores",
            "type":"Retail Goods"
        }
    ],
    "sg:phone":"+44 20 8981 5574",
    "sg:postcode":"E3 3EW",
    "sg:province":"Greater London",
    "sg:tags":[
        "shop",
        "chip"
    ],
    "wof:name":"Bow Fisheries",
    "wof:placetype":"venue"
},
  "geometry": {"coordinates":[-0.017569,51.527901],"type":"Point"}
}