{
  "type": "Feature",
  "properties": {
    "iso:country":"GB",
    "sg:address":"24 Broadway",
    "sg:city":"London",
    "sg:classifiers":[
        {
            "category":"Cafe",
            "type":"Food & Drink"
        }
    ],
    "sg:phone":"+44 20 7222 2129",
    "sg:postcode":"SW1H 0BH",
    "sg:province":"Greater London",
    "sg:tags":[
        "tea",
        "room"
    ],
    "wof:name":"Fresco",
    "wof:placetype":"venue"
},
  "geometry": {"coordinates":[-0.1330090016,51.4993400574],"type":"Point"}
}