{
  "type": "Feature",
  "properties": {
    "addr:full":"8 High Street Glastonbury Somerset BA6 9DU",
    "addr:housenumber":"8",
    "addr:postcode":"ba6 9du",
    "addr:street":"High Street",
    "iso:country":"GB",
    "sg:address":"8 High Street",
    "sg:city":"Glastonbury",
    "sg:classifiers":[
        {
            "category":"Travel",
            "subcategory":"Hotels & Motels",
            "type":"Entertainment"
        }
    ],
    "sg:postcode":"BA6 9DU",
    "sg:province":"Somerset",
    "sg:tags":[
        "house",
        "guest"
    ],
    "wof:name":"Hangmans House",
    "wof:placetype":"venue"
},
  "geometry": {"coordinates":[-2.717137,51.147427],"type":"Point"}
}