{
  "type": "Feature",
  "properties": {
    "iso:country":"GB",
    "sg:address":"8 High Street",
    "sg:city":"Glastonbury",
    "sg:classifiers":[
        {
            "category":"Travel",
            "subcategory":"Hotels & Motels",
            "type":"Entertainment"
        }
    ],
    "sg:postcode":"BA6 9DU",
    "sg:province":"Somerset",
    "sg:tags":[
        "house",
        "guest"
    ],
    "wof:name":"Hangmans House",
    "wof:placetype":"venue"
},
  "geometry": {"coordinates":[-2.717137,51.147427],"type":"Point"}
}