{
  "type": "Feature",
  "properties": {
    "addr:full":"Eurobell House, Churchill Court, Manor Royal Crawley Surrey RH10 9EB",
    "addr:postcode":"rh10 9eb",
    "addr:street":"Churchill Court;Royal",
    "iso:country":"GB",
    "sg:address":"Eurobell House, Churchill Court, Manor Royal",
    "sg:city":"Crawley",
    "sg:classifiers":[
        {
            "category":"Communications",
            "type":"Services"
        }
    ],
    "sg:phone":"+44 1293 400444",
    "sg:postcode":"RH10 9EB",
    "sg:province":"Surrey",
    "sg:tags":[
        "telecommunication"
    ],
    "wof:name":"Eurobell (Sussex) Ltd.",
    "wof:placetype":"venue"
},
  "geometry": {"coordinates":[-0.1713719964,51.1303939819],"type":"Point"}
}