{
  "type": "Feature",
  "properties": {
    "addr:full":"Great Coombe Farm, Fishpond Bridport Dorset DT6 6NR",
    "addr:postcode":"dt6 6nr",
    "iso:country":"GB",
    "sg:address":"Great Coombe Farm, Fishpond",
    "sg:city":"Bridport",
    "sg:classifiers":[
        {
            "category":"Farming",
            "subcategory":"Livestock Farm",
            "type":"Manufacturing & Wholesale Goods"
        }
    ],
    "sg:phone":"+44 1297 560416",
    "sg:postcode":"DT6 6NR",
    "sg:province":"Dorset",
    "sg:tags":[
        "others"
    ],
    "wof:name":"D & M Legg & Sons",
    "wof:placetype":"venue"
},
  "geometry": {"coordinates":[-2.8993740082,50.7810935974],"type":"Point"}
}