{
  "type": "Feature",
  "properties": {
    "addr:full":"85a St Marks Road, Bush Hill Park Barnet Hertfordshire EN5 1BJ",
    "addr:housenumber":"85a",
    "addr:postcode":"en5 1bj",
    "addr:street":"St Marks Road Bush Hill Park",
    "iso:country":"GB",
    "sg:address":"85a St Marks Road, Bush Hill Park",
    "sg:city":"Barnet",
    "sg:classifiers":[
        {
            "category":"Professional",
            "type":"Services"
        }
    ],
    "sg:phone":"+44 20 8482 2535",
    "sg:postcode":"EN5 1BJ",
    "sg:province":"Hertfordshire",
    "sg:tags":[
        "caterer"
    ],
    "wof:name":"Blue Flamingo Catering Co",
    "wof:placetype":"venue"
},
  "geometry": {"coordinates":[-0.17768,51.6437],"type":"Point"}
}