{
  "type": "Feature",
  "properties": {
    "addr:full":"Central Mills, Raymond St Bradford West Yorkshire BD5 8DT",
    "addr:postcode":"bd5 8dt",
    "addr:street":"Raymond St",
    "iso:country":"GB",
    "sg:address":"Central Mills, Raymond St",
    "sg:city":"Bradford",
    "sg:classifiers":[
        {
            "category":"Utilities",
            "subcategory":"Telephone",
            "type":"Services"
        }
    ],
    "sg:postcode":"BD5 8DT",
    "sg:province":"West Yorkshire",
    "sg:tags":[
        "telecommunication"
    ],
    "wof:name":"Eurotek Industries Ltd",
    "wof:placetype":"venue"
},
  "geometry": {"coordinates":[-1.7578300238,53.7717590332],"type":"Point"}
}