{
  "type": "Feature",
  "properties": {
    "addr:full":"1 Lawrence Drive, Minworth Coldfield Sutton Coldfield Warwickshire B76 9AX",
    "addr:housenumber":"1",
    "addr:postcode":"b76 9ax",
    "addr:street":"Lawrence Drive;Coldfield",
    "iso:country":"GB",
    "sg:address":"1 Lawrence Drive, Minworth Coldfield",
    "sg:city":"Sutton Coldfield",
    "sg:classifiers":[
        {
            "category":"Building & Trades",
            "subcategory":"Construction",
            "type":"Services"
        }
    ],
    "sg:phone":"+44 121 351 2707",
    "sg:postcode":"B76 9AX",
    "sg:province":"Warwickshire",
    "sg:tags":[
        "roofing"
    ],
    "wof:name":"Cherry Cole Roofing",
    "wof:placetype":"venue"
},
  "geometry": {"coordinates":[-1.7683010101,52.5315437317],"type":"Point"}
}