{
  "type": "Feature",
  "properties": {
    "addr:full":"Reevy Hill Health Centre, 50 Reevy Road West Bradford West Yorkshire BD6 3LX",
    "addr:housenumber":"50",
    "addr:postcode":"bd6 3lx",
    "addr:street":"Reevy;Reevy Road West",
    "iso:country":"GB",
    "sg:address":"Reevy Hill Health Centre, 50 Reevy Road West",
    "sg:city":"Bradford",
    "sg:classifiers":[
        {
            "category":"Health Services",
            "subcategory":"Doctor",
            "type":"Services"
        }
    ],
    "sg:phone":"+44 1274 691098",
    "sg:postcode":"BD6 3LX",
    "sg:province":"West Yorkshire",
    "sg:tags":[
        "practitioners"
    ],
    "wof:name":"Patterson, C",
    "wof:placetype":"venue"
},
  "geometry": {"coordinates":[-1.7971899509,53.7640686035],"type":"Point"}
}