{
  "type": "Feature",
  "properties": {
    "iso:country":"GB",
    "sg:address":"Old Docks Canteen, Atlantic Way",
    "sg:city":"Barry",
    "sg:classifiers":[
        {
            "category":"Building & Trades",
            "subcategory":"Construction",
            "type":"Services"
        }
    ],
    "sg:phone":"+44 1446 745593",
    "sg:postcode":"CF63 3RA",
    "sg:province":"The Vale of Glamorgan",
    "sg:tags":[
        "frame",
        "window",
        "sale"
    ],
    "wof:name":"Salevon Ltd",
    "wof:placetype":"venue"
},
  "geometry": {"coordinates":[-3.2504599094,51.4015007019],"type":"Point"}
}