{
  "type": "Feature",
  "properties": {
    "iso:country":"GB",
    "sg:address":"1 Alcumlow Cottage, Brook Lane",
    "sg:city":"Congleton",
    "sg:classifiers":[
        {
            "category":"Professional",
            "subcategory":"Engineering",
            "type":"Services"
        }
    ],
    "sg:postcode":"CW12 4TJ",
    "sg:province":"Cheshire",
    "sg:tags":[
        "agricultural",
        "engineer"
    ],
    "wof:name":"Peter Cliff",
    "wof:placetype":"venue"
},
  "geometry": {"coordinates":[-2.212205,53.163635],"type":"Point"}
}