{
  "type": "Feature",
  "properties": {
    "addr:full":"The Rectory, The Green Stanford Le Hope Essex SS17 0EP",
    "addr:postcode":"ss17 0ep",
    "addr:street":"The Green",
    "iso:country":"GB",
    "sg:address":"The Rectory, The Green",
    "sg:city":"Stanford Le Hope",
    "sg:classifiers":[
        {
            "category":"Place Of Worship",
            "type":"Public Place"
        }
    ],
    "sg:phone":"+44 1375 672271",
    "sg:postcode":"SS17 0EP",
    "sg:province":"Essex",
    "wof:name":"St Margaret'S Parish Church",
    "wof:placetype":"venue"
},
  "geometry": {"coordinates":[0.426878,51.5145],"type":"Point"}
}