{
  "type": "Feature",
  "properties": {
    "addr:full":"Bardwell Road, Neepsend Sheffield South Yorkshire S3 8AS",
    "addr:postcode":"s3 8as",
    "addr:street":"Bardwell Road",
    "iso:country":"GB",
    "sg:address":"Bardwell Road, Neepsend",
    "sg:city":"Sheffield",
    "sg:classifiers":[
        {
            "category":"Professional",
            "subcategory":"Engineering",
            "type":"Services"
        }
    ],
    "sg:phone":"+44 114 281 2258",
    "sg:postcode":"S3 8AS",
    "sg:province":"South Yorkshire",
    "wof:name":"Clarkson & Harrison Ltd.",
    "wof:placetype":"venue"
},
  "geometry": {"coordinates":[-1.478649,53.394531],"type":"Point"}
}