{
  "type": "Feature",
  "properties": {
    "iso:country":"GB",
    "sg:address":"32 St. Marys St",
    "sg:city":"Ely",
    "sg:classifiers":[
        {
            "category":"Government",
            "subcategory":"Post Office",
            "type":"Public Place"
        }
    ],
    "sg:phone":"+44 1353 669789",
    "sg:postcode":"CB7 4ES",
    "sg:province":"Cambridgeshire",
    "sg:tags":[
        "organisation",
        "soc",
        "research"
    ],
    "wof:name":"International Research Consultants",
    "wof:placetype":"venue"
},
  "geometry": {"coordinates":[0.260168,52.39983],"type":"Point"}
}