{
  "type": "Feature",
  "properties": {
    "iso:country":"GB",
    "sg:address":"39 Market Place",
    "sg:city":"Belper",
    "sg:classifiers":[
        {
            "category":"Shopping",
            "subcategory":"Baby Store",
            "type":"Retail Goods"
        }
    ],
    "sg:postcode":"DE56 1FZ",
    "sg:province":"Derbyshire",
    "sg:tags":[
        "babywear",
        "childrens"
    ],
    "wof:name":"Merry Go Round",
    "wof:placetype":"venue"
},
  "geometry": {"coordinates":[-1.478966,53.023151],"type":"Point"}
}