{
  "type": "Feature",
  "properties": {
    "addr:full":"Fairway Court London Greater London NW7 3HH",
    "addr:postcode":"nw7 3hh",
    "addr:street":"Fairway Court",
    "iso:country":"GB",
    "sg:address":"Fairway Court",
    "sg:city":"London",
    "sg:classifiers":[
        {
            "category":"Parking",
            "type":"Transportation"
        }
    ],
    "sg:phone":"+44 20 8201 0888",
    "sg:postcode":"NW7 3HH",
    "sg:province":"Greater London",
    "sg:tags":[
        "car",
        "valet"
    ],
    "wof:name":"Apex Mobile Steam Cleaning",
    "wof:placetype":"venue"
},
  "geometry": {"coordinates":[-0.259431,51.626293],"type":"Point"}
}