{
  "type": "Feature",
  "properties": {
    "iso:country":"GB",
    "sg:address":"2 Vicarage Close, Adlington",
    "sg:city":"Chorley",
    "sg:classifiers":[
        {
            "category":"Building & Trades",
            "subcategory":"Construction",
            "type":"Services"
        }
    ],
    "sg:phone":"+44 1257 481578",
    "sg:postcode":"PR6 9QP",
    "sg:province":"Lancashire",
    "sg:tags":[
        "decorator",
        "painter"
    ],
    "wof:name":"M S Contracts",
    "wof:placetype":"venue"
},
  "geometry": {"coordinates":[-2.599927,53.616985],"type":"Point"}
}