{
  "type": "Feature",
  "properties": {
    "addr:full":"The Flying Centre, Bristol Airport Bristol Somerset BS48 3DP",
    "addr:postcode":"bs48 3dp",
    "iso:country":"GB",
    "sg:address":"The Flying Centre, Bristol Airport",
    "sg:city":"Bristol",
    "sg:classifiers":[
        {
            "category":"Education",
            "subcategory":"Special Training",
            "type":"Public Place"
        },
        {
            "category":"Airline",
            "type":"Transportation"
        }
    ],
    "sg:phone":"+44 1275 474745",
    "sg:postcode":"BS48 3DP",
    "sg:province":"Somerset",
    "sg:tags":[
        "school",
        "flying"
    ],
    "wof:name":"Instrument Flight Training",
    "wof:placetype":"venue"
},
  "geometry": {"coordinates":[-2.7060530186,51.3865509033],"type":"Point"}
}