{
  "type": "Feature",
  "properties": {
    "addr:full":"Almana Studios, Glasson Indstl Est Maryport Cumbria CA15 8NT",
    "addr:postcode":"ca15 8nt",
    "addr:street":"Indstl Est",
    "iso:country":"GB",
    "sg:address":"Almana Studios, Glasson Indstl Est",
    "sg:city":"Maryport",
    "sg:classifiers":[
        {
            "category":"Shopping",
            "subcategory":"Gifts & Souvenirs",
            "type":"Retail Goods"
        }
    ],
    "sg:phone":"+44 1900 818500",
    "sg:postcode":"CA15 8NT",
    "sg:province":"Cumbria",
    "sg:tags":[
        "giftware"
    ],
    "wof:name":"Lakeland Studios Ltd",
    "wof:placetype":"venue"
},
  "geometry": {"coordinates":[-3.4965350628,54.7123908997],"type":"Point"}
}