{
  "type": "Feature",
  "properties": {
    "addr:full":"14 Eastgate Street Chester Cheshire CH1 1LE",
    "addr:housenumber":"14",
    "addr:postcode":"ch1 1le",
    "addr:street":"Eastgate Street",
    "iso:country":"GB",
    "sg:address":"14 Eastgate Street",
    "sg:city":"Chester",
    "sg:classifiers":[
        {
            "category":"Shopping",
            "subcategory":"Clothing, Apparel, & Fashions",
            "type":"Retail Goods"
        }
    ],
    "sg:phone":"+44 1244 325633",
    "sg:postcode":"CH1 1LE",
    "sg:province":"Cheshire",
    "sg:tags":[
        "shop",
        "accessory"
    ],
    "wof:name":"MONSOON ACCESSORIZE LTD",
    "wof:placetype":"venue"
},
  "geometry": {"coordinates":[-2.890709,53.190346],"type":"Point"}
}