{
  "type": "Feature",
  "properties": {
    "iso:country":"GB",
    "sg:address":"Brighton Road, Bolney",
    "sg:city":"Haywards Heath",
    "sg:classifiers":[
        {
            "category":"Wholesale",
            "subcategory":"Machinery & Supplies",
            "type":"Manufacturing & Wholesale Goods"
        }
    ],
    "sg:postcode":"RH17 5NA",
    "sg:province":"East Sussex",
    "sg:tags":[
        "theatrical"
    ],
    "wof:name":"Rainmaker Ltd.",
    "wof:placetype":"venue"
},
  "geometry": {"coordinates":[-0.1944590062,51.0178909302],"type":"Point"}
}