{
  "type": "Feature",
  "properties": {
    "addr:full":"34 Union Rd High Peak Cheshire SK22 3ES",
    "addr:housenumber":"34",
    "addr:postcode":"sk22 3es",
    "addr:street":"Union Rd",
    "iso:country":"GB",
    "sg:address":"34 Union Rd",
    "sg:city":"High Peak",
    "sg:classifiers":[
        {
            "category":"Shopping",
            "subcategory":"Stationery & Office Supplies",
            "type":"Retail Goods"
        }
    ],
    "sg:phone":"+44 1663 749187",
    "sg:postcode":"SK22 3ES",
    "sg:province":"Cheshire",
    "wof:name":"Tompla Uk Ltd",
    "wof:placetype":"venue"
},
  "geometry": {"coordinates":[-2.0010108948,53.3640441895],"type":"Point"}
}