{
  "type": "Feature",
  "properties": {
    "iso:country":"GB",
    "sg:address":"Cpa House, 49 Bolton Road, Farnworth",
    "sg:city":"Bolton",
    "sg:classifiers":[
        {
            "category":"Professional",
            "subcategory":"Credit Reporting & Collection",
            "type":"Services"
        }
    ],
    "sg:phone":"+44 1204 709501",
    "sg:postcode":"BL4 7JN",
    "sg:province":"Lancashire",
    "sg:tags":[
        "collecting",
        "agency"
    ],
    "wof:name":"Credit Protection Association",
    "wof:placetype":"venue"
},
  "geometry": {"coordinates":[-2.399322,53.553654],"type":"Point"}
}