{
  "type": "Feature",
  "properties": {
    "addr:full":"303 Goldhawk Road, Shepherds Bush London Greater London W12 8EZ",
    "addr:housenumber":"303",
    "addr:postcode":"w12 8ez",
    "addr:street":"Goldhawk Road",
    "iso:country":"GB",
    "sg:address":"303 Goldhawk Road, Shepherds Bush",
    "sg:city":"London",
    "sg:classifiers":[
        {
            "category":"Shopping",
            "type":"Retail Goods"
        }
    ],
    "sg:phone":"+44 20 8748 7824",
    "sg:postcode":"W12 8EZ",
    "sg:province":"Greater London",
    "sg:tags":[
        "part",
        "accessory"
    ],
    "wof:name":"Jag Shop Ltd.",
    "wof:placetype":"venue"
},
  "geometry": {"coordinates":[-0.2422699928,51.4988098145],"type":"Point"}
}