{
  "type": "Feature",
  "properties": {
    "addr:full":"6 Johnsons Way London Greater London NW10 7PF",
    "addr:housenumber":"6",
    "addr:postcode":"nw10 7pf",
    "addr:street":"Johnsons Way",
    "iso:country":"GB",
    "sg:address":"6 Johnsons Way",
    "sg:city":"London",
    "sg:classifiers":[
        {
            "category":"Retail",
            "subcategory":"Auto Repair",
            "type":"Services"
        }
    ],
    "sg:phone":"+44 20 8961 4343",
    "sg:postcode":"NW10 7PF",
    "sg:province":"Greater London",
    "sg:tags":[
        "car",
        "servicing",
        "radiator"
    ],
    "wof:name":"Performance 4 X 4",
    "wof:placetype":"venue"
},
  "geometry": {"coordinates":[-0.2773120105,51.5275268555],"type":"Point"}
}