{
  "type": "Feature",
  "properties": {
    "iso:country":"GB",
    "sg:address":"19b Alston Road, Hellesdon Park Industrial Estate",
    "sg:city":"Norwich",
    "sg:classifiers":[
        {
            "category":"Home & Garden",
            "subcategory":"Hardware",
            "type":"Retail Goods"
        }
    ],
    "sg:phone":"+44 1603 411022",
    "sg:postcode":"NR6 5DS",
    "sg:province":"Norfolk",
    "sg:tags":[
        "fixing",
        "nuts",
        "bolt"
    ],
    "wof:name":"Tolway (East) Ltd.",
    "wof:placetype":"venue"
},
  "geometry": {"coordinates":[1.25609,52.651436],"type":"Point"}
}