{
  "type": "Feature",
  "properties": {
    "addr:full":"25 Church Street Sheringham Norfolk NR26 8QR",
    "addr:housenumber":"25",
    "addr:postcode":"nr26 8qr",
    "addr:street":"Church Street",
    "iso:country":"GB",
    "sg:address":"25 Church Street",
    "sg:city":"Sheringham",
    "sg:classifiers":[
        {
            "category":"Food & Beverages",
            "subcategory":"Meat & Fish",
            "type":"Retail Goods"
        }
    ],
    "sg:phone":"+44 1263 822297",
    "sg:postcode":"NR26 8QR",
    "sg:province":"Norfolk",
    "sg:tags":[
        "chip"
    ],
    "wof:name":"Seafare",
    "wof:placetype":"venue"
},
  "geometry": {"coordinates":[1.2098679543,52.9431114197],"type":"Point"}
}