{
  "type": "Feature",
  "properties": {
    "addr:full":"26 Manor Hall Gardens London Greater London E10 7AT",
    "addr:housenumber":"26",
    "addr:postcode":"e10 7at",
    "addr:street":"Manor Hall Gardens",
    "iso:country":"GB",
    "sg:address":"26 Manor Hall Gardens",
    "sg:city":"London",
    "sg:classifiers":[
        {
            "category":"Professional",
            "subcategory":"Secretarial Services",
            "type":"Services"
        }
    ],
    "sg:postcode":"E10 7AT",
    "sg:province":"Greater London",
    "wof:name":"Type It Right",
    "wof:placetype":"venue"
},
  "geometry": {"coordinates":[-0.0176299997,51.5674285889],"type":"Point"}
}