{
  "type": "Feature",
  "properties": {
    "addr:full":"71 Peppard Rd Reading Berkshire RG4 8NH",
    "addr:housenumber":"71",
    "addr:postcode":"rg4 8nh",
    "addr:street":"Peppard Rd",
    "iso:country":"GB",
    "sg:address":"71 Peppard Rd",
    "sg:city":"Reading",
    "sg:classifiers":[
        {
            "category":"Building & Trades",
            "subcategory":"Plumbing",
            "type":"Services"
        }
    ],
    "sg:phone":"+44 118 946 2100",
    "sg:postcode":"RG4 8NH",
    "sg:province":"Berkshire",
    "sg:tags":[
        "heating"
    ],
    "wof:name":"Gas Appliance Servicing",
    "wof:placetype":"venue"
},
  "geometry": {"coordinates":[-0.9680690169,51.4737968445],"type":"Point"}
}