{
  "type": "Feature",
  "properties": {
    "iso:country":"GB",
    "sg:address":"71-75 Park Street",
    "sg:city":"Walsall",
    "sg:classifiers":[
        {
            "category":"Shopping",
            "subcategory":"Department Store",
            "type":"Retail Goods"
        }
    ],
    "sg:phone":"+44 1922 610864",
    "sg:postcode":"WS1 1NW",
    "sg:province":"West Midlands",
    "wof:name":"B H S Ltd.",
    "wof:placetype":"venue"
},
  "geometry": {"coordinates":[-1.9829039574,52.5850868225],"type":"Point"}
}