{
  "type": "Feature",
  "properties": {
    "addr:full":"Head Office, 150 Macdonald Rd Lightwater Surrey GU18 5YB",
    "addr:housenumber":"150",
    "addr:postcode":"gu18 5yb",
    "addr:street":"Macdonald Rd",
    "iso:country":"GB",
    "sg:address":"Head Office, 150 Macdonald Rd",
    "sg:city":"Lightwater",
    "sg:classifiers":[
        {
            "category":"Food & Beverages",
            "subcategory":"Groceries & Convenience Stores",
            "type":"Retail Goods"
        }
    ],
    "sg:phone":"+44 1276 475171",
    "sg:postcode":"GU18 5YB",
    "sg:province":"Surrey",
    "wof:name":"Circle C",
    "wof:placetype":"venue"
},
  "geometry": {"coordinates":[-0.6643589735,51.3508338928],"type":"Point"}
}