{
  "type": "Feature",
  "properties": {
    "iso:country":"GB",
    "sg:address":"Kesteven Street",
    "sg:city":"Sleaford",
    "sg:classifiers":[
        {
            "category":"Social Services",
            "subcategory":"Retirement Home",
            "type":"Services"
        },
        {
            "category":"Government",
            "subcategory":"Office",
            "type":"Public Place"
        }
    ],
    "sg:phone":"+44 1529 304351",
    "sg:postcode":"NG34 7DT",
    "sg:province":"Lincolnshire",
    "sg:tags":[
        "residential",
        "local",
        "care"
    ],
    "wof:name":"Jubilee Court Residential Care",
    "wof:placetype":"venue"
},
  "geometry": {"coordinates":[-0.406329,52.99966],"type":"Point"}
}