{
  "type": "Feature",
  "properties": {
    "iso:country":"GB",
    "sg:address":"47 Boodle St",
    "sg:city":"Ashton Under Lyne",
    "sg:classifiers":[
        {
            "category":"Building & Trades",
            "subcategory":"Construction",
            "type":"Services"
        }
    ],
    "sg:phone":"+44 161 339 2953",
    "sg:postcode":"OL6 8NF",
    "sg:province":"Greater Manchester",
    "sg:tags":[
        "builder"
    ],
    "wof:name":"Glendon Construction",
    "wof:placetype":"venue"
},
  "geometry": {"coordinates":[-2.096211,53.492287],"type":"Point"}
}