{
  "type": "Feature",
  "properties": {
    "addr:full":"262 Northdown Road Margate Kent CT9 2PX",
    "addr:housenumber":"262",
    "addr:postcode":"ct9 2px",
    "addr:street":"Northdown Road",
    "iso:country":"GB",
    "sg:address":"262 Northdown Road",
    "sg:city":"Margate",
    "sg:classifiers":[
        {
            "category":"Shopping",
            "subcategory":"Clothing, Apparel, & Fashions",
            "type":"Retail Goods"
        }
    ],
    "sg:phone":"+44 1843 223636",
    "sg:postcode":"CT9 2PX",
    "sg:province":"Kent",
    "sg:tags":[
        "menswear"
    ],
    "wof:name":"Pottons Ltd",
    "wof:placetype":"venue"
},
  "geometry": {"coordinates":[1.39641,51.387959],"type":"Point"}
}