{
  "type": "Feature",
  "properties": {
    "addr:full":"5 Bashley Road London Greater London NW10 6SD",
    "addr:housenumber":"5",
    "addr:postcode":"nw10 6sd",
    "addr:street":"Bashley Road",
    "iso:country":"GB",
    "sg:address":"5 Bashley Road",
    "sg:city":"London",
    "sg:classifiers":[
        {
            "category":"Personal",
            "type":"Services"
        }
    ],
    "sg:phone":"+44 20 8961 9393",
    "sg:postcode":"NW10 6SD",
    "sg:province":"Greater London",
    "sg:tags":[
        "delivery"
    ],
    "wof:name":"T N T Transport Ltd.",
    "wof:placetype":"venue"
},
  "geometry": {"coordinates":[-0.2583940029,51.5277557373],"type":"Point"}
}