{
  "type": "Feature",
  "properties": {
    "iso:country":"GB",
    "sg:address":"West Cliff Road",
    "sg:city":"Bournemouth",
    "sg:classifiers":[
        {
            "category":"Place Of Worship",
            "type":"Public Place"
        }
    ],
    "sg:phone":"+44 1202 764957",
    "sg:postcode":"BH4 8BE",
    "sg:province":"Dorset",
    "wof:name":"St. Ambrose Church",
    "wof:placetype":"venue"
},
  "geometry": {"coordinates":[-1.902116,50.718655],"type":"Point"}
}