{
  "type": "Feature",
  "properties": {
    "addr:full":"41 Princess Drive, Thurnscoe Rotherham South Yorkshire S63 0BL",
    "addr:housenumber":"41",
    "addr:postcode":"s63 0bl",
    "addr:street":"Princess Drive",
    "iso:country":"GB",
    "sg:address":"41 Princess Drive, Thurnscoe",
    "sg:city":"Rotherham",
    "sg:classifiers":[
        {
            "category":"Professional",
            "subcategory":"Detective & Security Services",
            "type":"Services"
        }
    ],
    "sg:postcode":"S63 0BL",
    "sg:province":"South Yorkshire",
    "sg:tags":[
        "alarm",
        "burglar",
        "system"
    ],
    "wof:name":"Regal Security Systems",
    "wof:placetype":"venue"
},
  "geometry": {"coordinates":[-1.304869,53.543976],"type":"Point"}
}