{
  "type": "Feature",
  "properties": {
    "addr:full":"41-42 Moorland Road, Oldfield Park Bath Somerset BA2 3PN",
    "addr:housenumber":"41-42",
    "addr:postcode":"ba2 3pn",
    "addr:street":"Moorland Road Oldfield Park",
    "iso:country":"GB",
    "sg:address":"41-42 Moorland Road, Oldfield Park",
    "sg:city":"Bath",
    "sg:classifiers":[
        {
            "category":"Personal",
            "subcategory":"Beauty Salon",
            "type":"Services"
        }
    ],
    "sg:postcode":"BA2 3PN",
    "sg:province":"Somerset",
    "sg:tags":[
        "lady",
        "hairdresser"
    ],
    "wof:name":"Nicholas Paul Hair Studio",
    "wof:placetype":"venue"
},
  "geometry": {"coordinates":[-2.3782389164,51.3769836426],"type":"Point"}
}