{
  "type": "Feature",
  "properties": {
    "iso:country":"GB",
    "sg:address":"Rectory Lane",
    "sg:city":"Bracknell",
    "sg:classifiers":[
        {
            "category":"Education",
            "subcategory":"School",
            "type":"Public Place"
        },
        {
            "category":"Government",
            "subcategory":"Office",
            "type":"Public Place"
        }
    ],
    "sg:phone":"+44 1344 423041",
    "sg:postcode":"RG12 7BA",
    "sg:province":"Berkshire",
    "sg:tags":[
        "local",
        "authority"
    ],
    "wof:name":"Brakenhale Comprehensive School",
    "wof:placetype":"venue"
},
  "geometry": {"coordinates":[-0.753229,51.406357],"type":"Point"}
}