{
  "type": "Feature",
  "properties": {
    "addr:full":"Mill House, Buttercrambe York East Riding of Yorkshire YO41 1XU",
    "addr:postcode":"yo41 1xu",
    "addr:street":"Buttercrambe",
    "iso:country":"GB",
    "sg:address":"Mill House, Buttercrambe",
    "sg:city":"York",
    "sg:classifiers":[
        {
            "category":"Farming",
            "subcategory":"Livestock Farm",
            "type":"Manufacturing & Wholesale Goods"
        }
    ],
    "sg:postcode":"YO41 1XU",
    "sg:province":"East Riding of Yorkshire",
    "sg:tags":[
        "others"
    ],
    "wof:name":"A & D Kerridge",
    "wof:placetype":"venue"
},
  "geometry": {"coordinates":[-0.915788,53.992474],"type":"Point"}
}