{
  "type": "Feature",
  "properties": {
    "iso:country":"GB",
    "sg:address":"Cedarwood, Crown Lane",
    "sg:city":"Knutsford",
    "sg:classifiers":[
        {
            "category":"Organizations",
            "subcategory":"Membership Organization",
            "type":"Services"
        }
    ],
    "sg:postcode":"WA16 9QB",
    "sg:province":"Cheshire",
    "sg:tags":[
        "club"
    ],
    "wof:name":"Champions Management Ltd.",
    "wof:placetype":"venue"
},
  "geometry": {"coordinates":[-2.37624,53.304203],"type":"Point"}
}