{
  "type": "Feature",
  "properties": {
    "iso:country":"GB",
    "sg:address":"126 East Street",
    "sg:city":"South Molton",
    "sg:classifiers":[
        {
            "category":"Manufacturing",
            "subcategory":"Tools & Machinery",
            "type":"Manufacturing & Wholesale Goods"
        },
        {
            "category":"Banks & Credit Unions",
            "subcategory":"Financial Services",
            "type":"Services"
        }
    ],
    "sg:phone":"+44 1769 573373",
    "sg:postcode":"EX36 3BU",
    "sg:province":"Devon",
    "sg:tags":[
        "society",
        "independent",
        "friendly",
        "adviser"
    ],
    "wof:name":"Anstey Financial Planning",
    "wof:placetype":"venue"
},
  "geometry": {"coordinates":[-3.832449,51.018002],"type":"Point"}
}