{
  "type": "Feature",
  "properties": {
    "addr:full":"34 Bridge St Lampeter Carmarthenshire SA48 7AA",
    "addr:housenumber":"34",
    "addr:postcode":"sa48 7aa",
    "addr:street":"Bridge St",
    "iso:country":"GB",
    "sg:address":"34 Bridge St",
    "sg:city":"Lampeter",
    "sg:classifiers":[
        {
            "category":"Personal",
            "subcategory":"Beauty Salon",
            "type":"Services"
        }
    ],
    "sg:phone":"+44 1570 422928",
    "sg:postcode":"SA48 7AA",
    "sg:province":"Carmarthenshire",
    "sg:tags":[
        "lady",
        "hairdresser"
    ],
    "wof:name":"Modest",
    "wof:placetype":"venue"
},
  "geometry": {"coordinates":[-4.077017,52.111656],"type":"Point"}
}