{
  "type": "Feature",
  "properties": {
    "addr:full":"891-995 Greenford Road Greenford Greater London UB6 0NN",
    "addr:housenumber":"891-995",
    "addr:postcode":"ub6 0nn",
    "addr:street":"Greenford Road",
    "iso:country":"GB",
    "sg:address":"891-995 Greenford Road",
    "sg:city":"Greenford",
    "sg:classifiers":[
        {
            "category":"Professional",
            "subcategory":"Business Services",
            "type":"Services"
        }
    ],
    "sg:postcode":"UB6 0NN",
    "sg:province":"Greater London",
    "sg:tags":[
        "holding"
    ],
    "wof:name":"Glaxo Wellcome Services Ltd.",
    "wof:placetype":"venue"
},
  "geometry": {"coordinates":[-0.3429400027,51.5430297852],"type":"Point"}
}