{
  "type": "Feature",
  "properties": {
    "addr:full":"Block 9, Unit 2, Roseberry Road Airdrie North Lanarkshire ML6 8QH",
    "addr:housenumber":"2",
    "addr:postcode":"ml6 8qh",
    "addr:street":"Roseberry Road",
    "iso:country":"GB",
    "sg:address":"Block 9, Unit 2, Roseberry Road",
    "sg:city":"Airdrie",
    "sg:classifiers":[
        {
            "category":"Freight",
            "type":"Transportation"
        },
        {
            "category":"Manufacturing",
            "subcategory":"Lumber",
            "type":"Manufacturing & Wholesale Goods"
        }
    ],
    "sg:phone":"+44 1236 755447",
    "sg:postcode":"ML6 8QH",
    "sg:province":"North Lanarkshire",
    "sg:tags":[
        "merchants",
        "haulage",
        "agent",
        "importer",
        "road",
        "timber"
    ],
    "wof:name":"Gordon & McLoughlin Transport (Salsburgh) Ltd.",
    "wof:placetype":"venue"
},
  "geometry": {"coordinates":[-3.9807839394,55.8658638],"type":"Point"}
}