{
  "type": "Feature",
  "properties": {
    "addr:full":"Warstones Y M C A Youth Club, Claverley Drive Wolverhampton Staffordshire WV4 4QL",
    "addr:postcode":"wv4 4ql",
    "addr:street":"Claverley Drive",
    "iso:country":"GB",
    "sg:address":"Warstones Y M C A Youth Club, Claverley Drive",
    "sg:city":"Wolverhampton",
    "sg:classifiers":[
        {
            "category":"Organizations",
            "subcategory":"Non-profit Organization",
            "type":"Services"
        }
    ],
    "sg:phone":"+44 1902 341822",
    "sg:postcode":"WV4 4QL",
    "sg:province":"Staffordshire",
    "sg:tags":[
        "organisation",
        "voluntary",
        "charity"
    ],
    "wof:name":"Ywca England & Wales",
    "wof:placetype":"venue"
},
  "geometry": {"coordinates":[-2.1684,52.564541],"type":"Point"}
}