{
  "type": "Feature",
  "properties": {
    "addr:full":"129 Old Castle Road Glasgow East Renfrewshire G44 5TJ",
    "addr:housenumber":"129",
    "addr:postcode":"g44 5tj",
    "addr:street":"Old Castle Road",
    "iso:country":"GB",
    "sg:address":"129 Old Castle Road",
    "sg:city":"Glasgow",
    "sg:classifiers":[
        {
            "category":"Personal",
            "subcategory":"Beauty Salon",
            "type":"Services"
        }
    ],
    "sg:phone":"+44 141 633 1655",
    "sg:postcode":"G44 5TJ",
    "sg:province":"East Renfrewshire",
    "sg:tags":[
        "unisex",
        "hairdresser"
    ],
    "wof:name":"James Buchanan",
    "wof:placetype":"venue"
},
  "geometry": {"coordinates":[-4.2575941086,55.8151855469],"type":"Point"}
}