{
  "type": "Feature",
  "properties": {
    "iso:country":"GB",
    "sg:address":"14 Bridge Street",
    "sg:city":"Whitby",
    "sg:classifiers":[
        {
            "category":"Cafe",
            "type":"Food & Drink"
        }
    ],
    "sg:postcode":"YO22 4BG",
    "sg:province":"North Yorkshire",
    "sg:tags":[
        "tea",
        "snack",
        "bar",
        "room"
    ],
    "wof:name":"BRIDGE CAFE",
    "wof:placetype":"venue"
},
  "geometry": {"coordinates":[-0.6121109724,54.4871749878],"type":"Point"}
}