{
  "type": "Feature",
  "properties": {
    "addr:full":"95 Rosary Road Norwich Norfolk NR1 4BX",
    "addr:housenumber":"95",
    "addr:postcode":"nr1 4bx",
    "addr:street":"Rosary Road Norwich Norfolk",
    "iso:country":"GB",
    "sg:address":"95 Rosary Road",
    "sg:city":"Norwich",
    "sg:classifiers":[
        {
            "category":"Bars & Pubs",
            "type":"Food & Drink"
        }
    ],
    "sg:postcode":"NR1 4BX",
    "sg:province":"Norfolk",
    "sg:tags":[
        "pubs",
        "inn"
    ],
    "wof:name":"The Rosary Tavern",
    "wof:placetype":"venue"
},
  "geometry": {"coordinates":[1.309336,52.628315],"type":"Point"}
}