{
  "type": "Feature",
  "properties": {
    "addr:full":"D S O Catering, Woodhill Ho, Westburn Rd Aberdeen Aberdeen City AB16 5GA",
    "addr:housenumber":"s",
    "addr:postcode":"ab16 5ga",
    "addr:street":"D;Woodhill;Westburn Rd",
    "iso:country":"GB",
    "sg:address":"D S O Catering, Woodhill Ho, Westburn Rd",
    "sg:city":"Aberdeen",
    "sg:classifiers":[
        {
            "category":"Government",
            "subcategory":"Office",
            "type":"Public Place"
        }
    ],
    "sg:phone":"+44 1224 664993",
    "sg:postcode":"AB16 5GA",
    "sg:province":"Aberdeen City",
    "sg:tags":[
        "local"
    ],
    "wof:name":"Aberdeen City Council",
    "wof:placetype":"venue"
},
  "geometry": {"coordinates":[-2.1477398872,57.1535110474],"type":"Point"}
}