{
  "type": "Feature",
  "properties": {
    "addr:full":"7 Morecambe Close, Bewbush Crawley West Sussex RH11 8RF",
    "addr:housenumber":"7",
    "addr:postcode":"rh11 8rf",
    "addr:street":"Morecambe Close",
    "iso:country":"GB",
    "sg:address":"7 Morecambe Close, Bewbush",
    "sg:city":"Crawley",
    "sg:classifiers":[
        {
            "category":"Professional",
            "subcategory":"Computer Services",
            "type":"Services"
        }
    ],
    "sg:postcode":"RH11 8RF",
    "sg:province":"West Sussex",
    "sg:tags":[
        "system",
        "software"
    ],
    "wof:name":"Alphainput Ltd",
    "wof:placetype":"venue"
},
  "geometry": {"coordinates":[-0.221641,51.106609],"type":"Point"}
}