{
  "type": "Feature",
  "properties": {
    "addr:full":"Sydney House, Nevendon Road Wickford Essex SS12 0PZ",
    "addr:postcode":"ss12 0pz",
    "addr:street":"Nevendon Road",
    "iso:country":"GB",
    "sg:address":"Sydney House, Nevendon Road",
    "sg:city":"Wickford",
    "sg:classifiers":[
        {
            "category":"Restaurant",
            "type":"Food & Drink"
        }
    ],
    "sg:phone":"+44 1268 561424",
    "sg:postcode":"SS12 0PZ",
    "sg:province":"Essex",
    "sg:tags":[
        "indian"
    ],
    "wof:name":"Bekash Indian Restaurant",
    "wof:placetype":"venue"
},
  "geometry": {"coordinates":[0.5197100043,51.6101264954],"type":"Point"}
}