{
  "type": "Feature",
  "properties": {
    "addr:full":"32 Ebury Bridge Road London Greater London SW1W 8PZ",
    "addr:housenumber":"32",
    "addr:postcode":"sw1w 8pz",
    "addr:street":"Ebury Bridge Road",
    "iso:country":"GB",
    "sg:address":"32 Ebury Bridge Road",
    "sg:city":"London",
    "sg:classifiers":[
        {
            "category":"Professional",
            "subcategory":"Management & Consulting",
            "type":"Services"
        }
    ],
    "sg:phone":"+44 20 7259 9900",
    "sg:postcode":"SW1W 8PZ",
    "sg:province":"Greater London",
    "sg:tags":[
        "consultant",
        "business"
    ],
    "wof:name":"Financial Product Development Associates",
    "wof:placetype":"venue"
},
  "geometry": {"coordinates":[-0.1503490061,51.4901237488],"type":"Point"}
}