{
  "type": "Feature",
  "properties": {
    "iso:country":"GB",
    "sg:address":"1st Floor 11 Argile Street",
    "sg:city":"London",
    "sg:classifiers":[
        {
            "category":"Professional",
            "subcategory":"Employment Agencies",
            "type":"Services"
        }
    ],
    "sg:phone":"+44 20 7287 0055",
    "sg:postcode":"W1F 7TH",
    "sg:province":"Greater London",
    "sg:tags":[
        "consultant"
    ],
    "wof:name":"City Centre",
    "wof:placetype":"venue"
},
  "geometry": {"coordinates":[-0.140809,51.514679],"type":"Point"}
}