{
  "type": "Feature",
  "properties": {
    "iso:country":"GB",
    "sg:address":"1 - 3 Pitt Street",
    "sg:city":"Heywood",
    "sg:classifiers":[
        {
            "category":"Banks & Credit Unions",
            "subcategory":"Financial Services",
            "type":"Services"
        }
    ],
    "sg:postcode":"OL10 1JP",
    "sg:province":"Lancashire",
    "sg:tags":[
        "consultant"
    ],
    "wof:name":"Marsh Finance Ltd.",
    "wof:placetype":"venue"
},
  "geometry": {"coordinates":[-2.2242910862,53.5938072205],"type":"Point"}
}