{
  "type": "Feature",
  "properties": {
    "addr:full":"The Old Bakery 67a Hounslow Road, Hanworth Feltham Greater London TW13 6QA",
    "addr:housenumber":"67a",
    "addr:postcode":"tw13 6qa",
    "addr:street":"Hounslow Road",
    "iso:country":"GB",
    "sg:address":"The Old Bakery 67a Hounslow Road, Hanworth",
    "sg:city":"Feltham",
    "sg:classifiers":[
        {
            "category":"Professional",
            "subcategory":"Detective & Security Services",
            "type":"Services"
        }
    ],
    "sg:postcode":"TW13 6QA",
    "sg:province":"Greater London",
    "sg:tags":[
        "agency"
    ],
    "wof:name":"C G Consultants Ltd.",
    "wof:placetype":"venue"
},
  "geometry": {"coordinates":[-0.390237,51.430511],"type":"Point"}
}