{
  "type": "Feature",
  "properties": {
    "addr:full":"8 Church Wk Leeds West Yorkshire LS2 7DP",
    "addr:housenumber":"8",
    "addr:postcode":"ls2 7dp",
    "addr:street":"Church Wk;West",
    "iso:country":"GB",
    "sg:address":"8 Church Wk",
    "sg:city":"Leeds",
    "sg:classifiers":[
        {
            "category":"Autos & Motor Vehicles",
            "subcategory":"Auto Supplies",
            "type":"Retail Goods"
        }
    ],
    "sg:postcode":"LS2 7DP",
    "sg:province":"West Yorkshire",
    "sg:tags":[
        "car",
        "accessory"
    ],
    "wof:name":"Sillshaws of Leeds",
    "wof:placetype":"venue"
},
  "geometry": {"coordinates":[-1.5365250111,53.7958030701],"type":"Point"}
}