{
  "type": "Feature",
  "properties": {
    "iso:country":"GB",
    "sg:address":"65 North Meggetland",
    "sg:city":"Edinburgh",
    "sg:classifiers":[
        {
            "category":"Education",
            "subcategory":"Special Training",
            "type":"Public Place"
        }
    ],
    "sg:phone":"+44 131 443 2730",
    "sg:postcode":"EH14 1XQ",
    "sg:province":"City of Edinburgh",
    "sg:tags":[
        "martial art",
        "instruction"
    ],
    "wof:name":"Edinburgh Tae Kwon Do",
    "wof:placetype":"venue"
},
  "geometry": {"coordinates":[-3.23356,55.928638],"type":"Point"}
}