{
  "type": "Feature",
  "properties": {
    "iso:country":"GB",
    "sg:address":"5 Pooles Close, Nether Stowey",
    "sg:city":"Bridgwater",
    "sg:classifiers":[
        {
            "category":"Banks & Credit Unions",
            "subcategory":"Bureau De Change",
            "type":"Services"
        },
        {
            "category":"Park",
            "subcategory":"Town Common",
            "type":"Public Place"
        }
    ],
    "sg:phone":"+44 1278 651110",
    "sg:postcode":"TA5 1LZ",
    "sg:province":"Somerset",
    "sg:tags":[
        "consultant",
        "planning",
        "city"
    ],
    "wof:name":"Ian McDonald",
    "wof:placetype":"venue"
},
  "geometry": {"coordinates":[-3.163643,51.151237],"type":"Point"}
}