{
  "type": "Feature",
  "properties": {
    "iso:country":"GB",
    "sg:address":"Church Farm, Chillesford",
    "sg:city":"Woodbridge",
    "sg:classifiers":[
        {
            "category":"Professional",
            "subcategory":"Engineering",
            "type":"Services"
        }
    ],
    "sg:phone":"+44 1394 450940",
    "sg:postcode":"IP12 3PS",
    "sg:province":"Suffolk",
    "sg:tags":[
        "engineer"
    ],
    "wof:name":"R C Engineering Ltd",
    "wof:placetype":"venue"
},
  "geometry": {"coordinates":[1.463214,52.099953],"type":"Point"}
}