{
  "type": "Feature",
  "properties": {
    "addr:full":"Lynnat House, Little Peter St Manchester Cheshire M15 4PS",
    "addr:postcode":"m15 4ps",
    "addr:street":"Little Peter St",
    "iso:country":"GB",
    "sg:address":"Lynnat House, Little Peter St",
    "sg:city":"Manchester",
    "sg:classifiers":[
        {
            "category":"Professional",
            "subcategory":"Business Services",
            "type":"Services"
        }
    ],
    "sg:phone":"+44 161 228 1311",
    "sg:postcode":"M15 4PS",
    "sg:province":"Cheshire",
    "sg:tags":[
        "import",
        "export",
        "agent"
    ],
    "wof:name":"Dalya (Babywear) Ltd",
    "wof:placetype":"venue"
},
  "geometry": {"coordinates":[-2.250594,53.47364],"type":"Point"}
}