{
  "type": "Feature",
  "properties": {
    "iso:country":"GB",
    "sg:address":"75 Torbay Rd",
    "sg:city":"Paignton",
    "sg:classifiers":[
        {
            "category":"Sports & Exercise",
            "subcategory":"Sports Center",
            "type":"Entertainment"
        }
    ],
    "sg:phone":"+44 1803 527885",
    "sg:postcode":"TQ4 6AJ",
    "sg:province":"Devon",
    "sg:tags":[
        "shop",
        "good"
    ],
    "wof:name":"Ghetto Sports Ltd",
    "wof:placetype":"venue"
},
  "geometry": {"coordinates":[-3.5607569218,50.4353523254],"type":"Point"}
}