{
  "type": "Feature",
  "properties": {
    "iso:country":"GB",
    "sg:address":"Pinelands Industrial Estate, Holt Road",
    "sg:city":"Norwich",
    "sg:classifiers":[
        {
            "category":"Professional",
            "type":"Services"
        }
    ],
    "sg:phone":"+44 1603 899700",
    "sg:postcode":"NR10 3EB",
    "sg:province":"Norfolk",
    "sg:tags":[
        "control",
        "system"
    ],
    "wof:name":"Center-Switch Ltd.",
    "wof:placetype":"venue"
},
  "geometry": {"coordinates":[1.2949,52.622494],"type":"Point"}
}