{
  "type": "Feature",
  "properties": {
    "iso:country":"GB",
    "sg:address":"90 English Street",
    "sg:city":"Dumfries",
    "sg:classifiers":[
        {
            "category":"Shopping",
            "subcategory":"News",
            "type":"Retail Goods"
        }
    ],
    "sg:phone":"+44 1387 252258",
    "sg:postcode":"DG1 2BY",
    "sg:province":"Dumfries and Galloway",
    "sg:tags":[
        "newsagent"
    ],
    "wof:name":"Yousaf Newsagents",
    "wof:placetype":"venue"
},
  "geometry": {"coordinates":[-3.607721,55.068951],"type":"Point"}
}