{
  "type": "Feature",
  "properties": {
    "addr:full":"405 Hoe Street London Greater London E17 9AP",
    "addr:housenumber":"405",
    "addr:postcode":"e17 9ap",
    "addr:street":"Hoe Street",
    "iso:country":"GB",
    "sg:address":"405 Hoe Street",
    "sg:city":"London",
    "sg:classifiers":[
        {
            "category":"Health Services",
            "subcategory":"Optometrist",
            "type":"Services"
        },
        {
            "category":"Shopping",
            "subcategory":"Optician",
            "type":"Retail Goods"
        }
    ],
    "sg:phone":"+44 20 8520 5278",
    "sg:postcode":"E17 9AP",
    "sg:province":"Greater London",
    "sg:tags":[
        "ophthalmic"
    ],
    "wof:name":"Phillips Opticians Ltd",
    "wof:placetype":"venue"
},
  "geometry": {"coordinates":[-0.015453,51.576313],"type":"Point"}
}