{
  "type": "Feature",
  "properties": {
    "addr:full":"54 Hospital Street Nantwich Cheshire CW5 5RP",
    "addr:housenumber":"54",
    "addr:postcode":"cw5 5rp",
    "addr:street":"Hospital Street",
    "iso:country":"GB",
    "sg:address":"54 Hospital Street",
    "sg:city":"Nantwich",
    "sg:classifiers":[
        {
            "category":"Shopping",
            "subcategory":"Clothing, Apparel, & Fashions",
            "type":"Retail Goods"
        }
    ],
    "sg:phone":"+44 1270 623334",
    "sg:postcode":"CW5 5RP",
    "sg:province":"Cheshire",
    "sg:tags":[
        "dresswear"
    ],
    "wof:name":"Top Notch",
    "wof:placetype":"venue"
},
  "geometry": {"coordinates":[-2.5196359158,53.0659751892],"type":"Point"}
}