{
  "type": "Feature",
  "properties": {
    "iso:country":"GB",
    "sg:address":"Keyworth Street",
    "sg:city":"London",
    "sg:classifiers":[
        {
            "category":"Education",
            "subcategory":"University",
            "type":"Public Place"
        }
    ],
    "sg:phone":"+44 20 7815 6060",
    "sg:postcode":"SE1 6NG",
    "sg:province":"Greater London",
    "sg:tags":[
        "medical",
        "school"
    ],
    "wof:name":"Students Union Bldg",
    "wof:placetype":"venue"
},
  "geometry": {"coordinates":[-0.101859,51.497875],"type":"Point"}
}