{
  "type": "Feature",
  "properties": {
    "addr:full":"Brocklebank, Butts La Cheltenham Gloucestershire GL52 4QH",
    "addr:postcode":"gl52 4qh",
    "addr:street":"Butts La Cheltenham",
    "iso:country":"GB",
    "sg:address":"Brocklebank, Butts La",
    "sg:city":"Cheltenham",
    "sg:classifiers":[
        {
            "category":"Professional",
            "subcategory":"Management & Consulting",
            "type":"Services"
        }
    ],
    "sg:phone":"+44 1242 674839",
    "sg:postcode":"GL52 4QH",
    "sg:province":"Gloucestershire",
    "sg:tags":[
        "conservation"
    ],
    "wof:name":"International Centre For Conservation Education",
    "wof:placetype":"venue"
},
  "geometry": {"coordinates":[-2.0784599781,51.8980484009],"type":"Point"}
}