{
  "type": "Feature",
  "properties": {
    "addr:full":"41 Park Avenue London Greater London NW2 5AN",
    "addr:housenumber":"41",
    "addr:postcode":"nw2 5an",
    "addr:street":"Park Avenue",
    "iso:country":"GB",
    "sg:address":"41 Park Avenue",
    "sg:city":"London",
    "sg:classifiers":[
        {
            "category":"Travel",
            "subcategory":"Hostel",
            "type":"Entertainment"
        }
    ],
    "sg:phone":"+44 20 8459 0718",
    "sg:postcode":"NW2 5AN",
    "sg:province":"Greater London",
    "wof:name":"Brent Mind",
    "wof:placetype":"venue"
},
  "geometry": {"coordinates":[-0.2271299958,51.5489082336],"type":"Point"}
}