{
  "type": "Feature",
  "properties": {
    "addr:full":"4 Clunie Place, Mastrick Aberdeen Aberdeen City AB16 5RN",
    "addr:housenumber":"4",
    "addr:postcode":"ab16 5rn",
    "addr:street":"Clunie Place",
    "iso:country":"GB",
    "sg:address":"4 Clunie Place, Mastrick",
    "sg:city":"Aberdeen",
    "sg:classifiers":[
        {
            "category":"Food & Beverages",
            "subcategory":"Bakery",
            "type":"Retail Goods"
        }
    ],
    "sg:phone":"+44 1224 691545",
    "sg:postcode":"AB16 5RN",
    "sg:province":"Aberdeen City",
    "sg:tags":[
        "baker"
    ],
    "wof:name":"The Pie In The Sky",
    "wof:placetype":"venue"
},
  "geometry": {"coordinates":[-2.159562,57.159809],"type":"Point"}
}