{
  "type": "Feature",
  "properties": {
    "addr:full":"228-230 Whitechapel Road London Greater London E1 1BJ",
    "addr:housenumber":"228-230",
    "addr:postcode":"e1 1bj",
    "addr:street":"Whitechapel Road",
    "iso:country":"GB",
    "sg:address":"228-230 Whitechapel Road",
    "sg:city":"London",
    "sg:classifiers":[
        {
            "category":"Professional",
            "subcategory":"Lawyer & Legal Services",
            "type":"Services"
        },
        {
            "category":"Food & Beverages",
            "subcategory":"Supermarket",
            "type":"Retail Goods"
        }
    ],
    "sg:phone":"+44 20 7375 3750",
    "sg:postcode":"E1 1BJ",
    "sg:province":"Greater London",
    "sg:tags":[
        "solicitor"
    ],
    "wof:name":"A S International",
    "wof:placetype":"venue"
},
  "geometry": {"coordinates":[-0.0570570007,51.5196418762],"type":"Point"}
}