{
  "type": "Feature",
  "properties": {
    "addr:full":"8 Moorfield Parade, Liverpool Road Manchester Greater Manchester M44 6FY",
    "addr:housenumber":"8",
    "addr:postcode":"m44 6fy",
    "addr:street":"Moorfield Parade Liverpool Road",
    "iso:country":"GB",
    "sg:address":"8 Moorfield Parade, Liverpool Road",
    "sg:city":"Manchester",
    "sg:classifiers":[
        {
            "category":"Shopping",
            "subcategory":"Gifts & Souvenirs",
            "type":"Retail Goods"
        }
    ],
    "sg:postcode":"M44 6FY",
    "sg:province":"Greater Manchester",
    "sg:tags":[
        "shop"
    ],
    "wof:name":"Bonus",
    "wof:placetype":"venue"
},
  "geometry": {"coordinates":[-2.4152169228,53.4516944885],"type":"Point"}
}