{
  "type": "Feature",
  "properties": {
    "addr:full":"16 Cannock Road Burntwood Staffordshire WS7 0BJ",
    "addr:housenumber":"16",
    "addr:postcode":"ws7 0bj",
    "addr:street":"Cannock Road",
    "iso:country":"GB",
    "sg:address":"16 Cannock Road",
    "sg:city":"Burntwood",
    "sg:classifiers":[
        {
            "category":"Restaurant",
            "type":"Food & Drink"
        }
    ],
    "sg:phone":"+44 1543 677800",
    "sg:postcode":"WS7 0BJ",
    "sg:province":"Staffordshire",
    "wof:name":"Aashiq's",
    "wof:placetype":"venue"
},
  "geometry": {"coordinates":[-1.9084709883,52.6782722473],"type":"Point"}
}