{
  "type": "Feature",
  "properties": {
    "iso:country":"GB",
    "sg:address":"1 Kirkhill Gate",
    "sg:city":"Glasgow",
    "sg:classifiers":[
        {
            "category":"Home & Garden",
            "subcategory":"Household Appliances",
            "type":"Retail Goods"
        },
        {
            "category":"Building & Trades",
            "subcategory":"Cleaning & Sanitation",
            "type":"Services"
        },
        {
            "category":"Communications",
            "type":"Services"
        }
    ],
    "sg:phone":"+44 141 639 7827",
    "sg:postcode":"G77 5RH",
    "sg:province":"East Ayrshire",
    "sg:tags":[
        "cleaner",
        "tv",
        "repairer",
        "domestic",
        "sale",
        "video",
        "vacuum",
        "radio"
    ],
    "wof:name":"Bel Air Central Vacuum Systems",
    "wof:placetype":"venue"
},
  "geometry": {"coordinates":[-4.3021111488,55.7746505737],"type":"Point"}
}