{
  "type": "Feature",
  "properties": {
    "iso:country":"GB",
    "sg:address":"1 Fleuret Close, Hythe",
    "sg:city":"Southampton",
    "sg:classifiers":[
        {
            "category":"Building & Trades",
            "subcategory":"Cleaning & Sanitation",
            "type":"Services"
        }
    ],
    "sg:phone":"+44 23 8084 8339",
    "sg:postcode":"SO45 3NS",
    "sg:province":"Hampshire",
    "sg:tags":[
        "blast"
    ],
    "wof:name":"Masterblast",
    "wof:placetype":"venue"
},
  "geometry": {"coordinates":[-1.398325,50.852341],"type":"Point"}
}