{
  "type": "Feature",
  "properties": {
    "iso:country":"GB",
    "sg:address":"18 Barnwood Crescent",
    "sg:city":"Cardiff",
    "sg:classifiers":[
        {
            "category":"Bus Charters",
            "type":"Transportation"
        }
    ],
    "sg:phone":"+44 29 2059 4367",
    "sg:postcode":"CF5 4TA",
    "sg:province":"Cardiff",
    "sg:tags":[
        "hire",
        "coach"
    ],
    "wof:name":"Ivanhoe Coaches",
    "wof:placetype":"venue"
},
  "geometry": {"coordinates":[-3.2709,51.474018],"type":"Point"}
}