{
  "type": "Feature",
  "properties": {
    "addr:full":"Carr Farm, Brompton-by-sawdon Scarborough North Yorkshire YO13 9DW",
    "addr:postcode":"yo13 9dw",
    "addr:street":"Carr;Brompton-By-Sawdon",
    "iso:country":"GB",
    "sg:address":"Carr Farm, Brompton-by-sawdon",
    "sg:city":"Scarborough",
    "sg:classifiers":[
        {
            "category":"Farming",
            "subcategory":"Livestock Farm",
            "type":"Manufacturing & Wholesale Goods"
        },
        {
            "category":"Farming",
            "subcategory":"Farm",
            "type":"Manufacturing & Wholesale Goods"
        }
    ],
    "sg:phone":"+44 1723 859405",
    "sg:postcode":"YO13 9DW",
    "sg:province":"North Yorkshire",
    "sg:tags":[
        "mixed",
        "others"
    ],
    "wof:name":"Geoffrey A Fothergill",
    "wof:placetype":"venue"
},
  "geometry": {"coordinates":[-0.5529440045,54.227104187],"type":"Point"}
}