{
  "type": "Feature",
  "properties": {
    "iso:country":"GB",
    "sg:address":"428 Whippendell Rd",
    "sg:city":"Watford",
    "sg:classifiers":[
        {
            "category":"Manufacturing",
            "subcategory":"Rubber & Plastics",
            "type":"Manufacturing & Wholesale Goods"
        }
    ],
    "sg:phone":"+44 1923 212122",
    "sg:postcode":"WD1 7PT",
    "sg:province":"Hertfordshire",
    "sg:tags":[
        "supplier",
        "stockist"
    ],
    "wof:name":"Panacrylic",
    "wof:placetype":"venue"
},
  "geometry": {"coordinates":[-0.417144,51.65123],"type":"Point"}
}