{
  "type": "Feature",
  "properties": {
    "iso:country":"GB",
    "sg:address":"37 Westbourne Rd",
    "sg:city":"Southport",
    "sg:classifiers":[
        {
            "category":"Health Services",
            "subcategory":"Chiropractor",
            "type":"Services"
        }
    ],
    "sg:phone":"+44 1704 569695",
    "sg:postcode":"PR8 2HY",
    "sg:province":"Lancashire",
    "wof:name":"Birkdale Chiropractic Clinic",
    "wof:placetype":"venue"
},
  "geometry": {"coordinates":[-3.033144,53.633369],"type":"Point"}
}