{
  "type": "Feature",
  "properties": {
    "iso:country":"GB",
    "sg:address":"15 Vicarage La",
    "sg:city":"Horley",
    "sg:classifiers":[
        {
            "category":"Professional",
            "subcategory":"Printing & Photocopies",
            "type":"Services"
        }
    ],
    "sg:phone":"+44 1293 824242",
    "sg:postcode":"RH6 8AR",
    "sg:province":"Surrey",
    "sg:tags":[
        "computer",
        "tag",
        "label"
    ],
    "wof:name":"Impression Label",
    "wof:placetype":"venue"
},
  "geometry": {"coordinates":[-0.172255,51.175991],"type":"Point"}
}