{
  "type": "Feature",
  "properties": {
    "addr:full":"3 Duchess Place, Hagley Road Birmingham West Midlands B16 8NH",
    "addr:housenumber":"3",
    "addr:postcode":"b16 8nh",
    "addr:street":"Duchess Place Hagley Road",
    "iso:country":"GB",
    "sg:address":"3 Duchess Place, Hagley Road",
    "sg:city":"Birmingham",
    "sg:classifiers":[
        {
            "category":"Professional",
            "subcategory":"Engineering",
            "type":"Services"
        }
    ],
    "sg:phone":"+44 121 456 1568",
    "sg:postcode":"B16 8NH",
    "sg:province":"West Midlands",
    "sg:tags":[
        "civil",
        "engineer"
    ],
    "wof:name":"Owen Williams Group Ltd.",
    "wof:placetype":"venue"
},
  "geometry": {"coordinates":[-1.923569,52.473419],"type":"Point"}
}