{
  "type": "Feature",
  "properties": {
    "addr:full":"Chaseley, Park La Stoke On Trent Cheshire ST7 8HW",
    "addr:postcode":"st7 8hw",
    "addr:street":"Park La Stoke On Trent",
    "iso:country":"GB",
    "sg:address":"Chaseley, Park La",
    "sg:city":"Stoke On Trent",
    "sg:classifiers":[
        {
            "category":"Professional",
            "subcategory":"Detective & Security Services",
            "type":"Services"
        }
    ],
    "sg:phone":"+44 7973 624877",
    "sg:postcode":"ST7 8HW",
    "sg:province":"Cheshire",
    "sg:tags":[
        "agency"
    ],
    "wof:name":"Fred H Cole",
    "wof:placetype":"venue"
},
  "geometry": {"coordinates":[-2.3084099293,53.0556983948],"type":"Point"}
}