{
  "type": "Feature",
  "properties": {
    "addr:full":"Chatterton Drive Rotherham South Yorkshire S65 2JW",
    "addr:postcode":"s65 2jw",
    "addr:street":"Chatterton Drive",
    "iso:country":"GB",
    "sg:address":"Chatterton Drive",
    "sg:city":"Rotherham",
    "sg:classifiers":[
        {
            "category":"Education",
            "subcategory":"School",
            "type":"Public Place"
        },
        {
            "category":"Government",
            "subcategory":"Office",
            "type":"Public Place"
        }
    ],
    "sg:phone":"+44 1709 828168",
    "sg:postcode":"S65 2JW",
    "sg:province":"South Yorkshire",
    "sg:tags":[
        "local",
        "authority"
    ],
    "wof:name":"Herringthorpe Junior School",
    "wof:placetype":"venue"
},
  "geometry": {"coordinates":[-1.329843998,53.4218940735],"type":"Point"}
}