{
  "type": "Feature",
  "properties": {
    "addr:full":"11 Lee Circle Leicester Leicestershire LE1 3SU",
    "addr:housenumber":"11",
    "addr:postcode":"le1 3su",
    "addr:street":"Lee Circle",
    "iso:country":"GB",
    "sg:address":"11 Lee Circle",
    "sg:city":"Leicester",
    "sg:classifiers":[
        {
            "category":"Home & Garden",
            "subcategory":"Home Furnishings",
            "type":"Retail Goods"
        }
    ],
    "sg:phone":"+44 116 253 8121",
    "sg:postcode":"LE1 3SU",
    "sg:province":"Leicestershire",
    "sg:tags":[
        "furnishers",
        "planner",
        "kitchen"
    ],
    "wof:name":"Express Kitchens & Bathrooms",
    "wof:placetype":"venue"
},
  "geometry": {"coordinates":[-1.128469944,52.6387519836],"type":"Point"}
}