{
  "type": "Feature",
  "properties": {
    "addr:full":"Unit 27 Addison Rd Port Talbot Neath Port Talbot SA12 6HZ",
    "addr:housenumber":"unit 27",
    "addr:postcode":"sa12 6hz",
    "addr:street":"Addison Rd",
    "iso:country":"GB",
    "sg:address":"Unit 27 Addison Rd",
    "sg:city":"Port Talbot",
    "sg:classifiers":[
        {
            "category":"Professional",
            "subcategory":"Engineering",
            "type":"Services"
        }
    ],
    "sg:phone":"+44 1639 888119",
    "sg:postcode":"SA12 6HZ",
    "sg:province":"Neath Port Talbot",
    "sg:tags":[
        "contractor",
        "electrical",
        "engineer"
    ],
    "wof:name":"C Brown Ltd",
    "wof:placetype":"venue"
},
  "geometry": {"coordinates":[-3.8000340462,51.5936355591],"type":"Point"}
}