{
  "type": "Feature",
  "properties": {
    "addr:full":"Independent House, 178 Brompton Road London Greater London SW3 1HQ",
    "addr:housenumber":"178",
    "addr:postcode":"sw3 1hq",
    "addr:street":"Brompton Road",
    "iso:country":"GB",
    "sg:address":"Independent House, 178 Brompton Road",
    "sg:city":"London",
    "sg:classifiers":[
        {
            "category":"Banks & Credit Unions",
            "subcategory":"Financial Services",
            "type":"Services"
        }
    ],
    "sg:phone":"+44 20 7225 2220",
    "sg:postcode":"SW3 1HQ",
    "sg:province":"Greater London",
    "sg:tags":[
        "consultant"
    ],
    "wof:name":"Scandinavian Finance (U K) Ltd.",
    "wof:placetype":"venue"
},
  "geometry": {"coordinates":[-0.164479,51.499161],"type":"Point"}
}