{
  "type": "Feature",
  "properties": {
    "iso:country":"GB",
    "sg:address":"Plot C, Glendale Gardens, Fleur De Lys",
    "sg:city":"Blackwood",
    "sg:classifiers":[
        {
            "category":"Building & Trades",
            "subcategory":"Construction",
            "type":"Services"
        }
    ],
    "sg:phone":"+44 1443 830140",
    "sg:postcode":"NP12 3TR",
    "sg:province":"Caerphilly",
    "sg:tags":[
        "builder"
    ],
    "wof:name":"S Walwyn Building Contractors",
    "wof:placetype":"venue"
},
  "geometry": {"coordinates":[-3.195614,51.667274],"type":"Point"}
}