{
  "type": "Feature",
  "properties": {
    "addr:full":"85 Johnston Street Blackburn Lancashire BB2 1HY",
    "addr:housenumber":"85",
    "addr:postcode":"bb2 1hy",
    "addr:street":"Johnston Street",
    "iso:country":"GB",
    "sg:address":"85 Johnston Street",
    "sg:city":"Blackburn",
    "sg:classifiers":[
        {
            "category":"Place Of Worship",
            "type":"Public Place"
        }
    ],
    "sg:phone":"+44 1254 681594",
    "sg:postcode":"BB2 1HY",
    "sg:province":"Lancashire",
    "wof:name":"St Barnabas Church & Community Centre",
    "wof:placetype":"venue"
},
  "geometry": {"coordinates":[-2.4959590435,53.7481765747],"type":"Point"}
}