{
  "type": "Feature",
  "properties": {
    "iso:country":"GB",
    "sg:address":"Little Aiden Cottage, Kilcreggen",
    "sg:city":"Helensburgh",
    "sg:classifiers":[
        {
            "category":"Retail",
            "subcategory":"Funeral Services",
            "type":"Services"
        }
    ],
    "sg:postcode":"G84 0LA",
    "sg:province":"Argyll and Bute",
    "wof:name":"James Auld",
    "wof:placetype":"venue"
},
  "geometry": {"coordinates":[-4.823964,55.987209],"type":"Point"}
}