{
  "type": "Feature",
  "properties": {
    "iso:country":"GB",
    "sg:address":"12 Moor Lane, Crosby",
    "sg:city":"Liverpool",
    "sg:classifiers":[
        {
            "category":"Shopping",
            "subcategory":"Shoes",
            "type":"Retail Goods"
        }
    ],
    "sg:phone":"+44 151 932 9046",
    "sg:postcode":"L23 2UE",
    "sg:province":"Merseyside",
    "sg:tags":[
        "shop",
        "retailer",
        "footwear"
    ],
    "wof:name":"Medina Shoes Ltd",
    "wof:placetype":"venue"
},
  "geometry": {"coordinates":[-3.0244789124,53.4926452637],"type":"Point"}
}