{
  "type": "Feature",
  "properties": {
    "addr:full":"7 Buchanen Drive Glasgow South Lanarkshire G72 8HE",
    "addr:housenumber":"7",
    "addr:postcode":"g72 8he",
    "addr:street":"Buchanen Drive",
    "iso:country":"GB",
    "sg:address":"7 Buchanen Drive",
    "sg:city":"Glasgow",
    "sg:classifiers":[
        {
            "category":"Food & Beverages",
            "subcategory":"Candy",
            "type":"Retail Goods"
        }
    ],
    "sg:phone":"+44 141 641 1138",
    "sg:postcode":"G72 8HE",
    "sg:province":"South Lanarkshire",
    "sg:tags":[
        "confectioner"
    ],
    "wof:name":"Dino's Confectionery",
    "wof:placetype":"venue"
},
  "geometry": {"coordinates":[-4.178983,55.82077],"type":"Point"}
}