{
  "type": "Feature",
  "properties": {
    "iso:country":"GB",
    "sg:address":"Penywern Cottage, Joiners Road",
    "sg:city":"Swansea",
    "sg:classifiers":[
        {
            "category":"Farming",
            "subcategory":"Dairy Farm",
            "type":"Manufacturing & Wholesale Goods"
        }
    ],
    "sg:postcode":"SA4 3NY",
    "sg:province":"Carmarthenshire",
    "wof:name":"Philip O Lewis",
    "wof:placetype":"venue"
},
  "geometry": {"coordinates":[-4.06725,51.629871],"type":"Point"}
}