{
  "type": "Feature",
  "properties": {
    "addr:full":"160 Kings Rd Harrogate North Yorkshire HG1 5JG",
    "addr:housenumber":"160",
    "addr:postcode":"hg1 5jg",
    "addr:street":"Kings Rd",
    "iso:country":"GB",
    "sg:address":"160 Kings Rd",
    "sg:city":"Harrogate",
    "sg:classifiers":[
        {
            "category":"Personal",
            "subcategory":"Barber",
            "type":"Services"
        }
    ],
    "sg:phone":"+44 1423 502888",
    "sg:postcode":"HG1 5JG",
    "sg:province":"North Yorkshire",
    "sg:tags":[
        "men's",
        "hairdresser"
    ],
    "wof:name":"Liannes",
    "wof:placetype":"venue"
},
  "geometry": {"coordinates":[-1.5374449492,54.0026435852],"type":"Point"}
}