{
  "type": "Feature",
  "properties": {
    "iso:country":"GB",
    "sg:address":"28 Long Street",
    "sg:city":"Dursley",
    "sg:classifiers":[
        {
            "category":"Professional",
            "subcategory":"Engineering",
            "type":"Services"
        },
        {
            "category":"Professional",
            "subcategory":"Management & Consulting",
            "type":"Services"
        }
    ],
    "sg:phone":"+44 1453 519602",
    "sg:postcode":"GL11 4HX",
    "sg:province":"Gloucestershire",
    "sg:tags":[
        "consultant",
        "business",
        "engineer"
    ],
    "wof:name":"Absorption Technology Ltd.",
    "wof:placetype":"venue"
},
  "geometry": {"coordinates":[-2.352489,51.681812],"type":"Point"}
}