{
  "type": "Feature",
  "properties": {
    "iso:country":"GB",
    "sg:address":"Unit 3 Sylvan Industrial Park, Sylvan Grove, Peckham",
    "sg:city":"Peckham",
    "sg:classifiers":[
        {
            "category":"Professional",
            "subcategory":"Engineering",
            "type":"Services"
        }
    ],
    "sg:phone":"+44 20 7277 5750",
    "sg:postcode":"SE15 1PD",
    "sg:province":"Greater London",
    "wof:name":"Ryefield Engineering",
    "wof:placetype":"venue"
},
  "geometry": {"coordinates":[-0.067794,51.472179],"type":"Point"}
}