{
  "type": "Feature",
  "properties": {
    "addr:full":"30 East Parade Harrogate North Yorkshire HG1 5LT",
    "addr:housenumber":"30",
    "addr:postcode":"hg1 5lt",
    "addr:street":"East Parade",
    "iso:country":"GB",
    "sg:address":"30 East Parade",
    "sg:city":"Harrogate",
    "sg:classifiers":[
        {
            "category":"Health Services",
            "subcategory":"Dentist",
            "type":"Services"
        }
    ],
    "sg:phone":"+44 1423 504399",
    "sg:postcode":"HG1 5LT",
    "sg:province":"North Yorkshire",
    "wof:name":"S.P.A Parker BDS LDS RCS",
    "wof:placetype":"venue"
},
  "geometry": {"coordinates":[-1.5329370499,53.99584198],"type":"Point"}
}