{
  "type": "Feature",
  "properties": {
    "addr:full":"Station Road, New Mills High Peak Cheshire SK22 3JB",
    "addr:postcode":"sk22 3jb",
    "addr:street":"Station Road",
    "iso:country":"GB",
    "sg:address":"Station Road, New Mills",
    "sg:city":"High Peak",
    "sg:classifiers":[
        {
            "category":"Manufacturing",
            "subcategory":"Metals",
            "type":"Manufacturing & Wholesale Goods"
        }
    ],
    "sg:phone":"+44 1663 742483",
    "sg:postcode":"SK22 3JB",
    "sg:province":"Cheshire",
    "sg:tags":[
        "heat",
        "-",
        "treatment"
    ],
    "wof:name":"Induction Heat Treatment (Manchester) Ltd.",
    "wof:placetype":"venue"
},
  "geometry": {"coordinates":[-2.005212,53.364838],"type":"Point"}
}