{
  "type": "Feature",
  "properties": {
    "addr:full":"217 High Street Herne Bay Kent CT6 5AD",
    "addr:housenumber":"217",
    "addr:postcode":"ct6 5ad",
    "addr:street":"High Street",
    "iso:country":"GB",
    "sg:address":"217 High Street",
    "sg:city":"Herne Bay",
    "sg:classifiers":[
        {
            "category":"Restaurant",
            "type":"Food & Drink"
        }
    ],
    "sg:phone":"+44 1227 741118",
    "sg:postcode":"CT6 5AD",
    "sg:province":"Kent",
    "sg:tags":[
        "chinese"
    ],
    "wof:name":"YANTZE CHINESE RESTAURANT",
    "wof:placetype":"venue"
},
  "geometry": {"coordinates":[1.13301301,51.3713951111],"type":"Point"}
}