{
  "type": "Feature",
  "properties": {
    "iso:country":"GB",
    "sg:address":"103 Wapping Lane",
    "sg:city":"Whitechapel",
    "sg:classifiers":[
        {
            "category":"Shopping",
            "subcategory":"Florist",
            "type":"Retail Goods"
        }
    ],
    "sg:phone":"+44 20 7488 9888",
    "sg:postcode":"E1W 2RW",
    "sg:province":"Greater London",
    "wof:name":"Lauralls",
    "wof:placetype":"venue"
},
  "geometry": {"coordinates":[-0.056681,51.504498],"type":"Point"}
}