{
  "type": "Feature",
  "properties": {
    "addr:full":"Chatteris Delivery Office, 15 Park Street Chatteris Cambridgeshire PE16 6AA",
    "addr:housenumber":"15",
    "addr:postcode":"pe16 6aa",
    "addr:street":"Park Street",
    "iso:country":"GB",
    "sg:address":"Chatteris Delivery Office, 15 Park Street",
    "sg:city":"Chatteris",
    "sg:classifiers":[
        {
            "category":"Professional",
            "type":"Services"
        },
        {
            "category":"Personal",
            "type":"Services"
        }
    ],
    "sg:phone":"+44 1354 692565",
    "sg:postcode":"PE16 6AA",
    "sg:province":"Cambridgeshire",
    "sg:tags":[
        "delivery",
        "good"
    ],
    "sg:website":"http://www.royalmail.com",
    "wof:name":"Royal Mail Group Ltd",
    "wof:placetype":"venue"
},
  "geometry": {"coordinates":[0.0487210006,52.4538040161],"type":"Point"}
}