{
  "type": "Feature",
  "properties": {
    "addr:full":"16 Southcote Way, Penn High Wycombe Buckinghamshire HP10 8JG",
    "addr:housenumber":"16",
    "addr:postcode":"hp10 8jg",
    "addr:street":"Southcote Way",
    "iso:country":"GB",
    "sg:address":"16 Southcote Way, Penn",
    "sg:city":"High Wycombe",
    "sg:classifiers":[
        {
            "category":"Home & Garden",
            "subcategory":"Household Appliances",
            "type":"Retail Goods"
        }
    ],
    "sg:phone":"+44 1494 813018",
    "sg:postcode":"HP10 8JG",
    "sg:province":"Buckinghamshire",
    "sg:tags":[
        "electrical"
    ],
    "wof:name":"Penn Installations",
    "wof:placetype":"venue"
},
  "geometry": {"coordinates":[-0.707669,51.639027],"type":"Point"}
}