{
  "type": "Feature",
  "properties": {
    "addr:full":"Whiffletree Farm, Kirdford Billingshurst West Sussex RH14 0NN",
    "addr:housenumber":"kirdford billingshurst",
    "addr:postcode":"rh14 0nn",
    "iso:country":"GB",
    "sg:address":"Whiffletree Farm, Kirdford",
    "sg:city":"Billingshurst",
    "sg:classifiers":[
        {
            "category":"Farming",
            "subcategory":"Livestock Farm",
            "type":"Manufacturing & Wholesale Goods"
        }
    ],
    "sg:phone":"+44 1403 820637",
    "sg:postcode":"RH14 0NN",
    "sg:province":"West Sussex",
    "sg:tags":[
        "others"
    ],
    "wof:name":"R A Putnam",
    "wof:placetype":"venue"
},
  "geometry": {"coordinates":[-0.5526239872,51.0324287415],"type":"Point"}
}