{
  "type": "Feature",
  "properties": {
    "addr:full":"24 Talbot Road Littlehampton West Sussex BN17 7BL",
    "addr:housenumber":"24",
    "addr:postcode":"bn17 7bl",
    "addr:street":"Talbot Road",
    "iso:country":"GB",
    "sg:address":"24 Talbot Road",
    "sg:city":"Littlehampton",
    "sg:classifiers":[
        {
            "category":"Professional",
            "subcategory":"Art Services",
            "type":"Services"
        }
    ],
    "sg:postcode":"BN17 7BL",
    "sg:province":"West Sussex",
    "sg:tags":[
        "photographer"
    ],
    "wof:name":"Image Maker Photography",
    "wof:placetype":"venue"
},
  "geometry": {"coordinates":[-0.5479279757,50.8119087219],"type":"Point"}
}