{
  "type": "Feature",
  "properties": {
    "addr:full":"10 Mollins Court, Westfield Glasgow East Dunbartonshire G68 9HP",
    "addr:housenumber":"10",
    "addr:postcode":"g68 9hp",
    "addr:street":"Mollins Court",
    "iso:country":"GB",
    "sg:address":"10 Mollins Court, Westfield",
    "sg:city":"Glasgow",
    "sg:classifiers":[
        {
            "category":"Health Services",
            "subcategory":"Optometrist",
            "type":"Services"
        }
    ],
    "sg:phone":"+44 1236 723300",
    "sg:postcode":"G68 9HP",
    "sg:province":"East Dunbartonshire",
    "sg:tags":[
        "optician"
    ],
    "wof:name":"Optical Express (Holdings) Ltd.",
    "wof:placetype":"venue"
},
  "geometry": {"coordinates":[-4.0523481369,55.9278411865],"type":"Point"}
}