{
  "type": "Feature",
  "properties": {
    "addr:full":"20 Mercer Place Dunfermline Fife KY11 4UG",
    "addr:housenumber":"20",
    "addr:postcode":"ky11 4ug",
    "addr:street":"Mercer Place Dunfermline",
    "iso:country":"GB",
    "sg:address":"20 Mercer Place",
    "sg:city":"Dunfermline",
    "sg:classifiers":[
        {
            "category":"Personal",
            "subcategory":"Beauty Salon",
            "type":"Services"
        }
    ],
    "sg:phone":"+44 1383 732178",
    "sg:postcode":"KY11 4UG",
    "sg:province":"Fife",
    "sg:tags":[
        "unisex",
        "hairdresser"
    ],
    "wof:name":"Simply Hair",
    "wof:placetype":"venue"
},
  "geometry": {"coordinates":[-3.4252851009,56.0747756958],"type":"Point"}
}