{
  "type": "Feature",
  "properties": {
    "addr:full":"20 Pantbach Rd Cardiff Cardiff CF4 1UA",
    "addr:housenumber":"20",
    "addr:postcode":"cf4 1ua",
    "addr:street":"Pantbach Rd",
    "iso:country":"GB",
    "sg:address":"20 Pantbach Rd",
    "sg:city":"Cardiff",
    "sg:classifiers":[
        {
            "category":"Professional",
            "subcategory":"Accounting & Tax Preparation",
            "type":"Services"
        }
    ],
    "sg:phone":"+44 29 2052 0900",
    "sg:postcode":"CF4 1UA",
    "sg:province":"Cardiff",
    "sg:tags":[
        "accountant"
    ],
    "wof:name":"S J Hull & Co",
    "wof:placetype":"venue"
},
  "geometry": {"coordinates":[-3.202186,51.511681],"type":"Point"}
}