{
  "type": "Feature",
  "properties": {
    "iso:country":"GB",
    "sg:address":"20 Harland Street",
    "sg:city":"Glasgow",
    "sg:classifiers":[
        {
            "category":"Shopping",
            "subcategory":"Party Supplies",
            "type":"Retail Goods"
        }
    ],
    "sg:postcode":"G14 0AT",
    "sg:province":"Glasgow City",
    "sg:tags":[
        "inflatables",
        "bouncy",
        "castle"
    ],
    "wof:name":"Bounce Higher",
    "wof:placetype":"venue"
},
  "geometry": {"coordinates":[-4.3489208221,55.8768043518],"type":"Point"}
}