{
  "type": "Feature",
  "properties": {
    "addr:full":"46 Quarry Road Tunbridge Wells Kent TN1 2EZ",
    "addr:housenumber":"46",
    "addr:postcode":"tn1 2ez",
    "addr:street":"Quarry Road",
    "iso:country":"GB",
    "sg:address":"46 Quarry Road",
    "sg:city":"Tunbridge Wells",
    "sg:classifiers":[
        {
            "category":"Health Services",
            "subcategory":"Medical Lab",
            "type":"Services"
        }
    ],
    "sg:postcode":"TN1 2EZ",
    "sg:province":"Kent",
    "sg:tags":[
        "dental"
    ],
    "wof:name":"Advanced Chrome Design Ltd.",
    "wof:placetype":"venue"
},
  "geometry": {"coordinates":[0.270848006,51.1402893066],"type":"Point"}
}