{
  "type": "Feature",
  "properties": {
    "iso:country":"GB",
    "sg:address":"Sinclair Drive, Park Farm Industrial Estate",
    "sg:city":"Wellingborough",
    "sg:classifiers":[
        {
            "category":"Shopping",
            "subcategory":"Catalog Store",
            "type":"Retail Goods"
        }
    ],
    "sg:phone":"+44 1933 674411",
    "sg:postcode":"NN8 6UY",
    "sg:province":"Northamptonshire",
    "sg:tags":[
        "mail",
        "order"
    ],
    "wof:name":"Leisure Circle",
    "wof:placetype":"venue"
},
  "geometry": {"coordinates":[-0.733409,52.313141],"type":"Point"}
}