{
  "type": "Feature",
  "properties": {
    "addr:full":"75 Rickmansworth Road Amersham Buckinghamshire HP6 5JW",
    "addr:housenumber":"75",
    "addr:postcode":"hp6 5jw",
    "addr:street":"Rickmansworth Road",
    "iso:country":"GB",
    "sg:address":"75 Rickmansworth Road",
    "sg:city":"Amersham",
    "sg:classifiers":[
        {
            "category":"Professional",
            "subcategory":"Business Services",
            "type":"Services"
        },
        {
            "category":"Real Estate",
            "subcategory":"Real Estate Agent",
            "type":"Services"
        }
    ],
    "sg:postcode":"HP6 5JW",
    "sg:province":"Buckinghamshire",
    "sg:tags":[
        "holding"
    ],
    "wof:name":"Callcott Holdings Limited",
    "wof:placetype":"venue"
},
  "geometry": {"coordinates":[-0.605132997,51.6787757874],"type":"Point"}
}