{
  "type": "Feature",
  "properties": {
    "addr:full":"39a Hermitage Rd Hitchin Bedfordshire SG5 1BY",
    "addr:housenumber":"39a",
    "addr:postcode":"sg5 1by",
    "addr:street":"Hermitage Rd",
    "iso:country":"GB",
    "sg:address":"39a Hermitage Rd",
    "sg:city":"Hitchin",
    "sg:classifiers":[
        {
            "category":"Banks & Credit Unions",
            "subcategory":"Financial Services",
            "type":"Services"
        }
    ],
    "sg:postcode":"SG5 1BY",
    "sg:province":"Bedfordshire",
    "sg:tags":[
        "consultant"
    ],
    "wof:name":"United Friendly Insurance Plc",
    "wof:placetype":"venue"
},
  "geometry": {"coordinates":[-0.274783,51.949276],"type":"Point"}
}