{
  "type": "Feature",
  "properties": {
    "addr:full":"2 High Street, Market Lavington Devizes Wiltshire SN10 4AF",
    "addr:housenumber":"2",
    "addr:postcode":"sn10 4af",
    "addr:street":"High Street",
    "iso:country":"GB",
    "sg:address":"2 High Street, Market Lavington",
    "sg:city":"Devizes",
    "sg:classifiers":[
        {
            "category":"Personal",
            "subcategory":"Beauty Salon",
            "type":"Services"
        },
        {
            "category":"Personal",
            "subcategory":"Barber",
            "type":"Services"
        }
    ],
    "sg:phone":"+44 1380 812205",
    "sg:postcode":"SN10 4AF",
    "sg:province":"Wiltshire",
    "sg:tags":[
        "unisex",
        "hairdresser"
    ],
    "wof:name":"PAUL GREAVES",
    "wof:placetype":"venue"
},
  "geometry": {"coordinates":[-1.9711220264,51.2929725647],"type":"Point"}
}