{
  "type": "Feature",
  "properties": {
    "iso:country":"GB",
    "sg:address":"Blake Street",
    "sg:city":"Barrow-in-furness",
    "sg:classifiers":[
        {
            "category":"Education",
            "subcategory":"School",
            "type":"Public Place"
        }
    ],
    "sg:phone":"+44 1229 894630",
    "sg:postcode":"LA14 1NY",
    "sg:province":"Cumbria",
    "sg:tags":[
        "local",
        "authority"
    ],
    "wof:name":"Brisbane Park County Infants School",
    "wof:placetype":"venue"
},
  "geometry": {"coordinates":[-3.235279,54.117756],"type":"Point"}
}