{
  "type": "Feature",
  "properties": {
    "addr:full":"26-27 High Street Marlborough Berkshire SN8 1LW",
    "addr:housenumber":"26-27",
    "addr:postcode":"sn8 1lw",
    "addr:street":"High Street",
    "iso:country":"GB",
    "sg:address":"26-27 High Street",
    "sg:city":"Marlborough",
    "sg:classifiers":[
        {
            "category":"Restaurant",
            "type":"Food & Drink"
        }
    ],
    "sg:postcode":"SN8 1LW",
    "sg:province":"Berkshire",
    "wof:name":"The Polly Tea Rooms",
    "wof:placetype":"venue"
},
  "geometry": {"coordinates":[-1.7336779833,51.4185256958],"type":"Point"}
}