{
  "type": "Feature",
  "properties": {
    "addr:full":"17 Carey Way Olney Buckinghamshire MK46 4DR",
    "addr:housenumber":"17",
    "addr:postcode":"mk46 4dr",
    "addr:street":"Carey Way",
    "iso:country":"GB",
    "sg:address":"17 Carey Way",
    "sg:city":"Olney",
    "sg:classifiers":[
        {
            "category":"Health Services",
            "subcategory":"Health Practitioner",
            "type":"Services"
        }
    ],
    "sg:phone":"+44 1234 713425",
    "sg:postcode":"MK46 4DR",
    "sg:province":"Buckinghamshire",
    "sg:tags":[
        "hypnotherapists"
    ],
    "wof:name":"Denise Messenger",
    "wof:placetype":"venue"
},
  "geometry": {"coordinates":[-0.6977750063,52.158290863],"type":"Point"}
}