{
  "type": "Feature",
  "properties": {
    "addr:full":"North Ct, Bridge St, Kineton Warwick Warwickshire CV35 0JR",
    "addr:postcode":"cv35 0jr",
    "addr:street":"North Ct Bridge St",
    "iso:country":"GB",
    "sg:address":"North Ct, Bridge St, Kineton",
    "sg:city":"Warwick",
    "sg:classifiers":[
        {
            "category":"Airline",
            "type":"Transportation"
        }
    ],
    "sg:postcode":"CV35 0JR",
    "sg:province":"Warwickshire",
    "sg:tags":[
        "aircraft",
        "charter"
    ],
    "wof:name":"Nash Group Ltd",
    "wof:placetype":"venue"
},
  "geometry": {"coordinates":[-1.5106090307,52.1565742493],"type":"Point"}
}