{
  "type": "Feature",
  "properties": {
    "addr:full":"Hurlingham Business Park, Fulbeck Heath Grantham Leicestershire NG32 3HL",
    "addr:postcode":"ng32 3hl",
    "addr:street":"Business Park",
    "iso:country":"GB",
    "sg:address":"Hurlingham Business Park, Fulbeck Heath",
    "sg:city":"Grantham",
    "sg:classifiers":[
        {
            "category":"Shopping",
            "subcategory":"Clothing, Apparel, & Fashions",
            "type":"Retail Goods"
        },
        {
            "category":"Personal",
            "type":"Services"
        },
        {
            "category":"Shopping",
            "subcategory":"Gifts & Souvenirs",
            "type":"Retail Goods"
        }
    ],
    "sg:phone":"+44 1400 262196",
    "sg:postcode":"NG32 3HL",
    "sg:province":"Leicestershire",
    "sg:tags":[
        "giftware",
        "lingerie"
    ],
    "wof:name":"Jig U K Ltd.",
    "wof:placetype":"venue"
},
  "geometry": {"coordinates":[-0.5856099725,53.0404052734],"type":"Point"}
}