{
  "type": "Feature",
  "properties": {
    "addr:full":"4 Brentwood Avenue Burnley Lancashire BB11 2PJ",
    "addr:housenumber":"4",
    "addr:postcode":"bb11 2pj",
    "addr:street":"Brentwood Avenue",
    "iso:country":"GB",
    "sg:address":"4 Brentwood Avenue",
    "sg:city":"Burnley",
    "sg:classifiers":[
        {
            "category":"Health Services",
            "subcategory":"Nursing And Care Facility",
            "type":"Services"
        }
    ],
    "sg:postcode":"BB11 2PJ",
    "sg:province":"Lancashire",
    "sg:tags":[
        "agency"
    ],
    "wof:name":"Brentwood Home Care",
    "wof:placetype":"venue"
},
  "geometry": {"coordinates":[-2.252546072,53.7788314819],"type":"Point"}
}