{
  "type": "Feature",
  "properties": {
    "iso:country":"GB",
    "sg:address":"The Cors",
    "sg:city":"Carmarthen",
    "sg:classifiers":[
        {
            "category":"Restaurant",
            "type":"Food & Drink"
        }
    ],
    "sg:phone":"+44 1994 427219",
    "sg:postcode":"SA33 4SH",
    "sg:province":"Carmarthenshire",
    "wof:name":"Cors Country House Restaurant & Hotel (The)",
    "wof:placetype":"venue"
},
  "geometry": {"coordinates":[-4.464,51.769363],"type":"Point"}
}