{
  "type": "Feature",
  "properties": {
    "iso:country":"GB",
    "sg:address":"Westgate",
    "sg:city":"Morecambe",
    "sg:classifiers":[
        {
            "category":"Farming",
            "subcategory":"Poultry Farm",
            "type":"Manufacturing & Wholesale Goods"
        }
    ],
    "sg:postcode":"LA3 3DD",
    "sg:province":"Lancashire",
    "wof:name":"Gott Foods Ltd.",
    "wof:placetype":"venue"
},
  "geometry": {"coordinates":[-2.839014,54.065872],"type":"Point"}
}