{
  "type": "Feature",
  "properties": {
    "addr:full":"Tir Powell Ddu, Nantyglyn Road, Glanamman Ammanford Carmarthenshire SA18 2YT",
    "addr:postcode":"sa18 2yt",
    "addr:street":"Tir;Nantyglyn Road",
    "iso:country":"GB",
    "sg:address":"Tir Powell Ddu, Nantyglyn Road, Glanamman",
    "sg:city":"Ammanford",
    "sg:classifiers":[
        {
            "category":"Farming",
            "subcategory":"Livestock Farm",
            "type":"Manufacturing & Wholesale Goods"
        }
    ],
    "sg:phone":"+44 1269 823962",
    "sg:postcode":"SA18 2YT",
    "sg:province":"Carmarthenshire",
    "sg:tags":[
        "others"
    ],
    "wof:name":"R E Bundock",
    "wof:placetype":"venue"
},
  "geometry": {"coordinates":[-3.9332098961,51.8089294434],"type":"Point"}
}