{
  "type": "Feature",
  "properties": {
    "iso:country":"GB",
    "sg:address":"9 Matlock Avenue",
    "sg:city":"Liverpool",
    "sg:classifiers":[
        {
            "category":"Farming",
            "subcategory":"Dairy Farm",
            "type":"Manufacturing & Wholesale Goods"
        }
    ],
    "sg:postcode":"L9 3AS",
    "sg:province":"Merseyside",
    "wof:name":"Wilcox Dairies",
    "wof:placetype":"venue"
},
  "geometry": {"coordinates":[-2.965089,53.461609],"type":"Point"}
}