{
  "type": "Feature",
  "properties": {
    "addr:full":"6 Gortoncross Retail Market, Gortoncross St Manchester Greater Manchester M18 8LD",
    "addr:housenumber":"6",
    "addr:postcode":"m18 8ld",
    "addr:street":"Gortoncross;St",
    "iso:country":"GB",
    "sg:address":"6 Gortoncross Retail Market, Gortoncross St",
    "sg:city":"Manchester",
    "sg:classifiers":[
        {
            "category":"Shopping",
            "subcategory":"Department Store",
            "type":"Retail Goods"
        },
        {
            "category":"Food & Beverages",
            "subcategory":"Groceries & Convenience Stores",
            "type":"Retail Goods"
        }
    ],
    "sg:phone":"+44 161 223 3416",
    "sg:postcode":"M18 8LD",
    "sg:province":"Greater Manchester",
    "wof:name":"J Singleton",
    "wof:placetype":"venue"
},
  "geometry": {"coordinates":[-2.2488100529,53.4796218872],"type":"Point"}
}