{
  "type": "Feature",
  "properties": {
    "addr:full":"8 The Close, Blacon Chester Cheshire CH1 5QR",
    "addr:housenumber":"8",
    "addr:postcode":"ch1 5qr",
    "addr:street":"The Close",
    "iso:country":"GB",
    "sg:address":"8 The Close, Blacon",
    "sg:city":"Chester",
    "sg:classifiers":[
        {
            "category":"Personal",
            "subcategory":"Beauty Salon",
            "type":"Services"
        }
    ],
    "sg:postcode":"CH1 5QR",
    "sg:province":"Cheshire",
    "sg:tags":[
        "unisex",
        "hairdresser"
    ],
    "wof:name":"Shampers",
    "wof:placetype":"venue"
},
  "geometry": {"coordinates":[-2.927298,53.20475],"type":"Point"}
}