{
  "type": "Feature",
  "properties": {
    "addr:full":"Unit 15e, Bergen Way Hull East Riding of Yorkshire HU7 0YQ",
    "addr:housenumber":"unit 15e",
    "addr:postcode":"hu7 0yq",
    "addr:street":"Bergen Way",
    "iso:country":"GB",
    "sg:address":"Unit 15e, Bergen Way",
    "sg:city":"Hull",
    "sg:classifiers":[
        {
            "category":"Real Estate",
            "subcategory":"Architect",
            "type":"Services"
        }
    ],
    "sg:phone":"+44 1482 370375",
    "sg:postcode":"HU7 0YQ",
    "sg:province":"East Riding of Yorkshire",
    "wof:name":"Pjh Engineering Ltd.",
    "wof:placetype":"venue"
},
  "geometry": {"coordinates":[-0.3463389874,53.7789535522],"type":"Point"}
}