{
  "type": "Feature",
  "properties": {
    "addr:full":"35 Mayne Avenue Luton Bedfordshire LU4 9LR",
    "addr:housenumber":"35",
    "addr:postcode":"lu4 9lr",
    "addr:street":"Mayne Avenue",
    "iso:country":"GB",
    "sg:address":"35 Mayne Avenue",
    "sg:city":"Luton",
    "sg:classifiers":[
        {
            "category":"Social Services",
            "type":"Services"
        },
        {
            "category":"Government",
            "subcategory":"Office",
            "type":"Public Place"
        }
    ],
    "sg:phone":"+44 1582 582962",
    "sg:postcode":"LU4 9LR",
    "sg:province":"Bedfordshire",
    "sg:tags":[
        "local"
    ],
    "wof:name":"Leagrave Family Centre",
    "wof:placetype":"venue"
},
  "geometry": {"coordinates":[-0.4688189924,51.9042129517],"type":"Point"}
}