{
  "type": "Feature",
  "properties": {
    "addr:full":"54b Aidan Court Jarrow Tyne and Wear NE32 3EF",
    "addr:housenumber":"54b",
    "addr:postcode":"ne32 3ef",
    "addr:street":"Aidan Court",
    "iso:country":"GB",
    "sg:address":"54b Aidan Court",
    "sg:city":"Jarrow",
    "sg:classifiers":[
        {
            "category":"Professional",
            "subcategory":"Printing & Photocopies",
            "type":"Services"
        }
    ],
    "sg:phone":"+44 191 428 2428",
    "sg:postcode":"NE32 3EF",
    "sg:province":"Tyne and Wear",
    "sg:tags":[
        "printer"
    ],
    "wof:name":"Bayriver Ltd.",
    "wof:placetype":"venue"
},
  "geometry": {"coordinates":[-1.4725879431,54.9762954712],"type":"Point"}
}