{
  "type": "Feature",
  "properties": {
    "addr:full":"261 Bristol Road Gloucester Gloucestershire GL2 5DB",
    "addr:housenumber":"261",
    "addr:postcode":"gl2 5db",
    "addr:street":"Bristol Road",
    "iso:country":"GB",
    "sg:address":"261 Bristol Road",
    "sg:city":"Gloucester",
    "sg:classifiers":[
        {
            "category":"Education",
            "subcategory":"Music School",
            "type":"Public Place"
        }
    ],
    "sg:phone":"+44 1452 414080",
    "sg:postcode":"GL2 5DB",
    "sg:province":"Gloucestershire",
    "sg:tags":[
        "teacher"
    ],
    "wof:name":"Guitar Tuition",
    "wof:placetype":"venue"
},
  "geometry": {"coordinates":[-2.263428,51.845505],"type":"Point"}
}