{
  "type": "Feature",
  "properties": {
    "addr:full":"302 St Leonards Road Windsor Berkshire SL4 3DX",
    "addr:housenumber":"302",
    "addr:postcode":"sl4 3dx",
    "addr:street":"St Leonards Road",
    "iso:country":"GB",
    "sg:address":"302 St Leonards Road",
    "sg:city":"Windsor",
    "sg:classifiers":[
        {
            "category":"Bars & Pubs",
            "type":"Food & Drink"
        }
    ],
    "sg:postcode":"SL4 3DX",
    "sg:province":"Berkshire",
    "sg:tags":[
        "pubs",
        "inn"
    ],
    "wof:name":"The Stag & Hounds",
    "wof:placetype":"venue"
},
  "geometry": {"coordinates":[-0.6221339703,51.471206665],"type":"Point"}
}