{
  "type": "Feature",
  "properties": {
    "addr:full":"16-18 Sneinton Dale Nottingham Nottinghamshire NG2 4HA",
    "addr:housenumber":"16-18",
    "addr:postcode":"ng2 4ha",
    "addr:street":"Sneinton Dale",
    "iso:country":"GB",
    "sg:address":"16-18 Sneinton Dale",
    "sg:city":"Nottingham",
    "sg:classifiers":[
        {
            "category":"Retail",
            "subcategory":"Auto Repair",
            "type":"Services"
        }
    ],
    "sg:phone":"+44 115 950 0159",
    "sg:postcode":"NG2 4HA",
    "sg:province":"Nottinghamshire",
    "sg:tags":[
        "modification",
        "garage"
    ],
    "wof:name":"Windmill Service Station",
    "wof:placetype":"venue"
},
  "geometry": {"coordinates":[-1.136627,52.953339],"type":"Point"}
}