{
  "type": "Feature",
  "properties": {
    "iso:country":"GB",
    "sg:address":"4 Fore Street",
    "sg:city":"Torrington",
    "sg:classifiers":[
        {
            "category":"Food & Beverages",
            "subcategory":"Meat & Fish",
            "type":"Retail Goods"
        }
    ],
    "sg:postcode":"EX38 8HQ",
    "sg:province":"Devon",
    "sg:tags":[
        "butcher"
    ],
    "wof:name":"Farm Fresh Quality Butchers",
    "wof:placetype":"venue"
},
  "geometry": {"coordinates":[-4.143077,50.952168],"type":"Point"}
}