{
  "type": "Feature",
  "properties": {
    "addr:full":"25 Argyle Street Birkenhead Merseyside CH41 6AA",
    "addr:housenumber":"25",
    "addr:postcode":"ch41 6aa",
    "addr:street":"Argyle Street",
    "iso:country":"GB",
    "sg:address":"25 Argyle Street",
    "sg:city":"Birkenhead",
    "sg:classifiers":[
        {
            "category":"Bars & Pubs",
            "type":"Food & Drink"
        }
    ],
    "sg:postcode":"CH41 6AA",
    "sg:province":"Merseyside",
    "sg:tags":[
        "pubs",
        "inn"
    ],
    "wof:name":"Letters Inn",
    "wof:placetype":"venue"
},
  "geometry": {"coordinates":[-3.0174729824,53.3930091858],"type":"Point"}
}