{
  "type": "Feature",
  "properties": {
    "iso:country":"GB",
    "sg:address":"Care Of George Street Clinic, George St",
    "sg:city":"Glossop",
    "sg:classifiers":[
        {
            "category":"Health Services",
            "subcategory":"Clinic",
            "type":"Services"
        }
    ],
    "sg:phone":"+44 1457 855612",
    "sg:postcode":"SK13 8AY",
    "sg:province":"Derbyshire",
    "sg:tags":[
        "planning",
        "family",
        "centre"
    ],
    "wof:name":"Family Planning Service",
    "wof:placetype":"venue"
},
  "geometry": {"coordinates":[-1.9465700388,53.4433364868],"type":"Point"}
}