{
  "type": "Feature",
  "properties": {
    "addr:full":"16 Lonsdale Gardens Tunbridge Wells Kent TN1 1NU",
    "addr:housenumber":"16",
    "addr:postcode":"tn1 1nu",
    "addr:street":"Lonsdale Gardens;Wells",
    "iso:country":"GB",
    "sg:address":"16 Lonsdale Gardens",
    "sg:city":"Tunbridge Wells",
    "sg:classifiers":[
        {
            "category":"Communications",
            "type":"Services"
        }
    ],
    "sg:postcode":"TN1 1NU",
    "sg:province":"Kent",
    "sg:tags":[
        "telecommunication"
    ],
    "wof:name":"Lynton Communications Ltd",
    "wof:placetype":"venue"
},
  "geometry": {"coordinates":[0.2612049878,51.131111145],"type":"Point"}
}