{
  "type": "Feature",
  "properties": {
    "iso:country":"GB",
    "sg:address":"61 St Georges Road",
    "sg:city":"Brighton",
    "sg:classifiers":[
        {
            "category":"Food & Beverages",
            "subcategory":"Liquor & Beverages",
            "type":"Retail Goods"
        }
    ],
    "sg:phone":"+44 1273 681030",
    "sg:postcode":"BN2 1EF",
    "sg:province":"East Sussex",
    "sg:tags":[
        "beer",
        "spirit",
        "wines"
    ],
    "wof:name":"Whitbread",
    "wof:placetype":"venue"
},
  "geometry": {"coordinates":[-0.1168759987,50.8171958923],"type":"Point"}
}