{
  "type": "Feature",
  "properties": {
    "addr:full":"Unit 2270c, Dunbeath Road Swindon Wiltshire SN2 8EA",
    "addr:housenumber":"2270c",
    "addr:postcode":"sn2 8ea",
    "addr:street":"Dunbeath Road",
    "iso:country":"GB",
    "sg:address":"Unit 2270c, Dunbeath Road",
    "sg:city":"Swindon",
    "sg:classifiers":[
        {
            "category":"Building & Trades",
            "subcategory":"Equipment Rental",
            "type":"Services"
        }
    ],
    "sg:phone":"+44 1793 480008",
    "sg:postcode":"SN2 8EA",
    "sg:province":"Wiltshire",
    "sg:tags":[
        "hire",
        "centre"
    ],
    "wof:name":"Britannia Tool Hire Ltd.",
    "wof:placetype":"venue"
},
  "geometry": {"coordinates":[-1.768084,51.574364],"type":"Point"}
}