{
  "type": "Feature",
  "properties": {
    "addr:full":"11-12 Penistone Road Indust Est Sheffield South Yorkshire S6 3AL",
    "addr:housenumber":"11-12",
    "addr:postcode":"s6 3al",
    "addr:street":"Penistone Road",
    "iso:country":"GB",
    "sg:address":"11-12 Penistone Road Indust Est",
    "sg:city":"Sheffield",
    "sg:classifiers":[
        {
            "category":"Manufacturing",
            "subcategory":"Motor Vehicles & Parts",
            "type":"Manufacturing & Wholesale Goods"
        }
    ],
    "sg:phone":"+44 114 285 5051",
    "sg:postcode":"S6 3AL",
    "sg:province":"South Yorkshire",
    "sg:tags":[
        "bearing"
    ],
    "wof:name":"Premier Engineering Services",
    "wof:placetype":"venue"
},
  "geometry": {"coordinates":[-1.4780819416,53.3894729614],"type":"Point"}
}