{
  "type": "Feature",
  "properties": {
    "addr:full":"38 Brunswick Arcade Keighley West Yorkshire BD21 3QB",
    "addr:housenumber":"38;arcade",
    "addr:postcode":"bd21 3qb",
    "addr:street":"Brunswick;West",
    "iso:country":"GB",
    "sg:address":"38 Brunswick Arcade",
    "sg:city":"Keighley",
    "sg:classifiers":[
        {
            "category":"Shopping",
            "subcategory":"Gifts & Souvenirs",
            "type":"Retail Goods"
        }
    ],
    "sg:postcode":"BD21 3QB",
    "sg:province":"West Yorkshire",
    "sg:tags":[
        "shop"
    ],
    "wof:name":"The Lighthouse",
    "wof:placetype":"venue"
},
  "geometry": {"coordinates":[-1.9071890116,53.8671684265],"type":"Point"}
}