{
  "type": "Feature",
  "properties": {
    "iso:country":"GB",
    "sg:address":"Austin Rd, Cobholm",
    "sg:city":"Great Yarmouth",
    "sg:classifiers":[
        {
            "category":"Retail",
            "subcategory":"Auto Repair",
            "type":"Services"
        }
    ],
    "sg:phone":"+44 1493 655355",
    "sg:postcode":"NR31 0DF",
    "sg:province":"Norfolk",
    "sg:tags":[
        "modification",
        "garage"
    ],
    "wof:name":"D & S Motors",
    "wof:placetype":"venue"
},
  "geometry": {"coordinates":[1.715605,52.605583],"type":"Point"}
}