{
  "type": "Feature",
  "properties": {
    "addr:full":"Hammond Road Liverpool Lancashire L33 7UL",
    "addr:postcode":"l33 7ul",
    "addr:street":"Hammond Road",
    "iso:country":"GB",
    "sg:address":"Hammond Road",
    "sg:city":"Liverpool",
    "sg:classifiers":[
        {
            "category":"Building & Trades",
            "subcategory":"Construction",
            "type":"Services"
        }
    ],
    "sg:phone":"+44 151 546 3777",
    "sg:postcode":"L33 7UL",
    "sg:province":"Lancashire",
    "sg:tags":[
        "builder"
    ],
    "wof:name":"Ash Building Joinery & Maintenance Services Ltd.",
    "wof:placetype":"venue"
},
  "geometry": {"coordinates":[-2.853694,53.488216],"type":"Point"}
}