{
  "type": "Feature",
  "properties": {
    "addr:full":"50 High St, Irchester Wellingborough Bedfordshire NN29 7AB",
    "addr:housenumber":"50",
    "addr:postcode":"nn29 7ab",
    "addr:street":"High St",
    "iso:country":"GB",
    "sg:address":"50 High St, Irchester",
    "sg:city":"Wellingborough",
    "sg:classifiers":[
        {
            "category":"Shopping",
            "subcategory":"Baby Store",
            "type":"Retail Goods"
        }
    ],
    "sg:postcode":"NN29 7AB",
    "sg:province":"Bedfordshire",
    "sg:tags":[
        "nursery",
        "accessory"
    ],
    "wof:name":"Josephine's",
    "wof:placetype":"venue"
},
  "geometry": {"coordinates":[-0.707542,52.274551],"type":"Point"}
}