{
  "type": "Feature",
  "properties": {
    "addr:full":"Glebelands Barm, Yapton Rd Bognor Regis West Sussex PO22 0AX",
    "addr:postcode":"po22 0ax",
    "addr:street":"Yapton Rd",
    "iso:country":"GB",
    "sg:address":"Glebelands Barm, Yapton Rd",
    "sg:city":"Bognor Regis",
    "sg:classifiers":[
        {
            "category":"Banks & Credit Unions",
            "subcategory":"Investment Brokerage",
            "type":"Services"
        }
    ],
    "sg:phone":"+44 1243 554499",
    "sg:postcode":"PO22 0AX",
    "sg:province":"West Sussex",
    "sg:tags":[
        "contractor"
    ],
    "wof:name":"Alan Barrett Straw",
    "wof:placetype":"venue"
},
  "geometry": {"coordinates":[-0.634920001,50.8293609619],"type":"Point"}
}