{
  "type": "Feature",
  "properties": {
    "addr:full":"201 Attercliffe Road Sheffield South Yorkshire S4 7XF",
    "addr:housenumber":"201",
    "addr:postcode":"s4 7xf",
    "addr:street":"Attercliffe Road",
    "iso:country":"GB",
    "sg:address":"201 Attercliffe Road",
    "sg:city":"Sheffield",
    "sg:classifiers":[
        {
            "category":"Manufacturing",
            "subcategory":"Textiles",
            "type":"Manufacturing & Wholesale Goods"
        }
    ],
    "sg:phone":"+44 114 273 9823",
    "sg:postcode":"S4 7XF",
    "sg:province":"South Yorkshire",
    "sg:tags":[
        "knitwear"
    ],
    "wof:name":"199 Ltd.",
    "wof:placetype":"venue"
},
  "geometry": {"coordinates":[-1.447245,53.39045],"type":"Point"}
}