{
  "type": "Feature",
  "properties": {
    "iso:country":"GB",
    "sg:address":"14 George Street",
    "sg:city":"Barton-upon-humber",
    "sg:classifiers":[
        {
            "category":"Banks & Credit Unions",
            "subcategory":"Bureau De Change",
            "type":"Services"
        },
        {
            "category":"Shopping",
            "subcategory":"Pharmacy",
            "type":"Retail Goods"
        }
    ],
    "sg:phone":"+44 1652 634705",
    "sg:postcode":"DN18 5ES",
    "sg:province":"Lincolnshire",
    "sg:tags":[
        "toilet",
        "toiletry",
        "article"
    ],
    "wof:name":"This 'N' That",
    "wof:placetype":"venue"
},
  "geometry": {"coordinates":[-0.4392769933,53.6835441589],"type":"Point"}
}