{
  "type": "Feature",
  "properties": {
    "addr:full":"Arthur Street Redditch Warwickshire B98 8JY",
    "addr:postcode":"b98 8jy",
    "addr:street":"Arthur Street",
    "iso:country":"GB",
    "sg:address":"Arthur Street",
    "sg:city":"Redditch",
    "sg:classifiers":[
        {
            "category":"Building & Trades",
            "subcategory":"Construction",
            "type":"Services"
        }
    ],
    "sg:phone":"+44 1527 522566",
    "sg:postcode":"B98 8JY",
    "sg:province":"Warwickshire",
    "sg:tags":[
        "ceiling",
        "contractor"
    ],
    "wof:name":"Midland Interiors Ltd.",
    "wof:placetype":"venue"
},
  "geometry": {"coordinates":[-1.919659,52.305103],"type":"Point"}
}