{
  "type": "Feature",
  "properties": {
    "iso:country":"GB",
    "sg:address":"55 Newmarket Street",
    "sg:city":"Ayr",
    "sg:classifiers":[
        {
            "category":"Shopping",
            "subcategory":"Department Store",
            "type":"Retail Goods"
        }
    ],
    "sg:postcode":"KA7 1LL",
    "sg:province":"South Ayrshire",
    "wof:name":"Alan Stevenson",
    "wof:placetype":"venue"
},
  "geometry": {"coordinates":[-4.630466,55.463413],"type":"Point"}
}