{
  "type": "Feature",
  "properties": {
    "addr:full":"39 Elm Grove Orpington Kent BR6 0AA",
    "addr:housenumber":"39",
    "addr:postcode":"br6 0aa",
    "addr:street":"Elm Grove",
    "iso:country":"GB",
    "sg:address":"39 Elm Grove",
    "sg:city":"Orpington",
    "sg:classifiers":[
        {
            "category":"Professional",
            "subcategory":"Computer Services",
            "type":"Services"
        }
    ],
    "sg:postcode":"BR6 0AA",
    "sg:province":"Kent",
    "sg:tags":[
        "system",
        "software"
    ],
    "wof:name":"Softlink Limited",
    "wof:placetype":"venue"
},
  "geometry": {"coordinates":[0.0932599977,51.3745994568],"type":"Point"}
}