{
  "type": "Feature",
  "properties": {
    "iso:country":"GB",
    "sg:address":"Rhosfach, Llantood",
    "sg:city":"Cardigan",
    "sg:classifiers":[
        {
            "category":"Farming",
            "subcategory":"Livestock Farm",
            "type":"Manufacturing & Wholesale Goods"
        }
    ],
    "sg:phone":"+44 1239 612319",
    "sg:postcode":"SA41 3QA",
    "sg:province":"Pembrokeshire",
    "sg:tags":[
        "others"
    ],
    "wof:name":"S E Williams & Son",
    "wof:placetype":"venue"
},
  "geometry": {"coordinates":[-4.70146,52.037899],"type":"Point"}
}