{
  "type": "Feature",
  "properties": {
    "iso:country":"GB",
    "sg:address":"61 Curzon St",
    "sg:city":"Birmingham",
    "sg:classifiers":[
        {
            "category":"Professional",
            "subcategory":"Printing & Photocopies",
            "type":"Services"
        },
        {
            "category":"Government",
            "subcategory":"Post Office",
            "type":"Public Place"
        }
    ],
    "sg:phone":"+44 121 359 8943",
    "sg:postcode":"B4 7XG",
    "sg:province":"West Midlands",
    "sg:tags":[
        "print",
        "typesetter",
        "printer"
    ],
    "wof:name":"Fleet Graphics Ltd",
    "wof:placetype":"venue"
},
  "geometry": {"coordinates":[-1.884127,52.482403],"type":"Point"}
}