{
  "type": "Feature",
  "properties": {
    "addr:full":"Glenisla, Drumoak Banchory Aberdeen City AB31 5AJ",
    "addr:postcode":"ab31 5aj",
    "addr:street":"Banchory Aberdeen",
    "iso:country":"GB",
    "sg:address":"Glenisla, Drumoak",
    "sg:city":"Banchory",
    "sg:classifiers":[
        {
            "category":"Home & Garden",
            "subcategory":"Garden Supply",
            "type":"Retail Goods"
        }
    ],
    "sg:phone":"+44 1330 811234",
    "sg:postcode":"AB31 5AJ",
    "sg:province":"Aberdeen City",
    "sg:tags":[
        "nursery",
        "centre"
    ],
    "wof:name":"Heather Centre",
    "wof:placetype":"venue"
},
  "geometry": {"coordinates":[-2.4564170837,57.0617408752],"type":"Point"}
}