{
  "type": "Feature",
  "properties": {
    "addr:full":"The Ox House, Market Place, Northleach Cheltenham Gloucestershire GL54 3EG",
    "addr:postcode":"gl54 3eg",
    "addr:street":"Market Place",
    "iso:country":"GB",
    "sg:address":"The Ox House, Market Place, Northleach",
    "sg:city":"Cheltenham",
    "sg:classifiers":[
        {
            "category":"Real Estate",
            "subcategory":"Real Estate Agent",
            "type":"Services"
        }
    ],
    "sg:phone":"+44 1451 861270",
    "sg:postcode":"GL54 3EG",
    "sg:province":"Gloucestershire",
    "wof:name":"Moore Allen & Innocent",
    "wof:placetype":"venue"
},
  "geometry": {"coordinates":[-1.837334,51.829834],"type":"Point"}
}