{
  "type": "Feature",
  "properties": {
    "iso:country":"GB",
    "sg:address":"Ashley Park Hotel",
    "sg:city":"Walton-on-thames",
    "sg:classifiers":[
        {
            "category":"Travel",
            "subcategory":"Hotels & Motels",
            "type":"Entertainment"
        }
    ],
    "sg:phone":"+44 1932 220196",
    "sg:postcode":"KT12 1JP",
    "sg:province":"Surrey",
    "wof:name":"Nigel Clarke",
    "wof:placetype":"venue"
},
  "geometry": {"coordinates":[-0.4218440056,51.3807868958],"type":"Point"}
}