{
  "type": "Feature",
  "properties": {
    "addr:full":"60 Birmingham Rd Sutton Coldfield West Midlands B72 1QP",
    "addr:housenumber":"60",
    "addr:postcode":"b72 1qp",
    "addr:street":"Birmingham Rd",
    "iso:country":"GB",
    "sg:address":"60 Birmingham Rd",
    "sg:city":"Sutton Coldfield",
    "sg:classifiers":[
        {
            "category":"Health Services",
            "subcategory":"Dentist",
            "type":"Services"
        }
    ],
    "sg:phone":"+44 121 354 1922",
    "sg:postcode":"B72 1QP",
    "sg:province":"West Midlands",
    "wof:name":"Y K L Chan",
    "wof:placetype":"venue"
},
  "geometry": {"coordinates":[-1.826687,52.556393],"type":"Point"}
}