{
  "type": "Feature",
  "properties": {
    "addr:full":"Woodstock Main St, Brandesburton Driffield East Riding of Yorkshire YO25 8RG",
    "addr:postcode":"yo25 8rg",
    "addr:street":"Main St",
    "iso:country":"GB",
    "sg:address":"Woodstock Main St, Brandesburton",
    "sg:city":"Driffield",
    "sg:classifiers":[
        {
            "category":"Building & Trades",
            "subcategory":"Construction",
            "type":"Services"
        }
    ],
    "sg:postcode":"YO25 8RG",
    "sg:province":"East Riding of Yorkshire",
    "sg:tags":[
        "builder"
    ],
    "wof:name":"Myers,A P,",
    "wof:placetype":"venue"
},
  "geometry": {"coordinates":[-0.3021189868,53.9109992981],"type":"Point"}
}