{
  "type": "Feature",
  "properties": {
    "addr:full":"Parkside, Chart Way Horsham West Sussex RH12 1XA",
    "addr:postcode":"rh12 1xa",
    "addr:street":"Chart Way",
    "iso:country":"GB",
    "sg:address":"Parkside, Chart Way",
    "sg:city":"Horsham",
    "sg:classifiers":[
        {
            "category":"Insurance",
            "subcategory":"Insurance Agent",
            "type":"Services"
        }
    ],
    "sg:phone":"+44 1403 232323",
    "sg:postcode":"RH12 1XA",
    "sg:province":"West Sussex",
    "wof:name":"Sun Alliance Insurance Group",
    "wof:placetype":"venue"
},
  "geometry": {"coordinates":[-0.329107,51.065182],"type":"Point"}
}