{
  "type": "Feature",
  "properties": {
    "iso:country":"GB",
    "sg:address":"118 High Street",
    "sg:city":"Ramsgate",
    "sg:classifiers":[
        {
            "category":"Personal",
            "subcategory":"Beauty Salon",
            "type":"Services"
        }
    ],
    "sg:postcode":"CT11 9UA",
    "sg:province":"Kent",
    "sg:tags":[
        "lady",
        "hairdresser"
    ],
    "wof:name":"Bridget's",
    "wof:placetype":"venue"
},
  "geometry": {"coordinates":[1.415685,51.335842],"type":"Point"}
}