{
  "type": "Feature",
  "properties": {
    "iso:country":"GB",
    "sg:address":"4 Chalet Hill",
    "sg:city":"Bordon",
    "sg:classifiers":[
        {
            "category":"Banks & Credit Unions",
            "subcategory":"Bank",
            "type":"Services"
        }
    ],
    "sg:phone":"+44 1420 473333",
    "sg:postcode":"GU35 0TQ",
    "sg:province":"Hampshire",
    "sg:tags":[
        "broker",
        "mortgage"
    ],
    "wof:name":"Kingswood Property & Financial Services Ltd.",
    "wof:placetype":"venue"
},
  "geometry": {"coordinates":[-0.863082,51.111843],"type":"Point"}
}