{
  "type": "Feature",
  "properties": {
    "iso:country":"GB",
    "sg:address":"Ringway House, Daneshill",
    "sg:city":"Basingstoke",
    "sg:classifiers":[
        {
            "category":"Real Estate",
            "subcategory":"Real Estate Agent",
            "type":"Services"
        }
    ],
    "sg:postcode":"RG24 8FB",
    "sg:province":"Hampshire",
    "wof:name":"Castle Estates (Hampshire) Ltd.",
    "wof:placetype":"venue"
},
  "geometry": {"coordinates":[-1.0544830561,51.2801513672],"type":"Point"}
}