{
  "type": "Feature",
  "properties": {
    "iso:country":"GB",
    "sg:address":"347 Eastern Avenue",
    "sg:city":"Ilford",
    "sg:classifiers":[
        {
            "category":"Building & Trades",
            "subcategory":"Construction",
            "type":"Services"
        }
    ],
    "sg:phone":"+44 20 8551 1659",
    "sg:postcode":"IG2 6NX",
    "sg:province":"Essex",
    "sg:tags":[
        "monumental",
        "mason"
    ],
    "wof:name":"Memorial Firms",
    "wof:placetype":"venue"
},
  "geometry": {"coordinates":[0.064432,51.576725],"type":"Point"}
}