{
  "type": "Feature",
  "properties": {
    "addr:full":"Suite 2 Second Floor, Kings Chambers Derby Derbyshire DE1 3DS",
    "addr:housenumber":"suite 2 second floor",
    "addr:postcode":"de1 3ds",
    "addr:street":"Kings Chambers",
    "iso:country":"GB",
    "sg:address":"Suite 2 Second Floor, Kings Chambers",
    "sg:city":"Derby",
    "sg:classifiers":[
        {
            "category":"Building & Trades",
            "subcategory":"Plumbing",
            "type":"Services"
        }
    ],
    "sg:phone":"+44 1332 514358",
    "sg:postcode":"DE1 3DS",
    "sg:province":"Derbyshire",
    "sg:tags":[
        "heating"
    ],
    "wof:name":"Procad Detailing Ltd.",
    "wof:placetype":"venue"
},
  "geometry": {"coordinates":[-1.4813870192,52.9280967712],"type":"Point"}
}