{
  "type": "Feature",
  "properties": {
    "addr:full":"1 Ewart Place London Greater London E3 5EQ",
    "addr:housenumber":"1",
    "addr:postcode":"e3 5eq",
    "addr:street":"Ewart Place",
    "iso:country":"GB",
    "sg:address":"1 Ewart Place",
    "sg:city":"London",
    "sg:classifiers":[
        {
            "category":"Government",
            "subcategory":"Office",
            "type":"Public Place"
        }
    ],
    "sg:phone":"+44 20 7364 5969",
    "sg:postcode":"E3 5EQ",
    "sg:province":"Greater London",
    "sg:tags":[
        "local"
    ],
    "wof:name":"Bow One Stop Shop",
    "wof:placetype":"venue"
},
  "geometry": {"coordinates":[-0.030405,51.532612],"type":"Point"}
}