{
  "type": "Feature",
  "properties": {
    "addr:full":"300 Upper Rainham Road Hornchurch Essex RM12 4EQ",
    "addr:housenumber":"300",
    "addr:postcode":"rm12 4eq",
    "addr:street":"Upper Rainham Road",
    "iso:country":"GB",
    "sg:address":"300 Upper Rainham Road",
    "sg:city":"Hornchurch",
    "sg:classifiers":[
        {
            "category":"Health Services",
            "subcategory":"Doctor",
            "type":"Services"
        },
        {
            "category":"Health Services",
            "subcategory":"Clinic",
            "type":"Services"
        }
    ],
    "sg:phone":"+44 1708 476411",
    "sg:postcode":"RM12 4EQ",
    "sg:province":"Essex",
    "sg:tags":[
        "nh",
        "practitioners"
    ],
    "wof:name":"Maylands Surgery",
    "wof:placetype":"venue"
},
  "geometry": {"coordinates":[0.1880799979,51.5602111816],"type":"Point"}
}