{
  "type": "Feature",
  "properties": {
    "iso:country":"GB",
    "sg:address":"207 Church St",
    "sg:city":"Dumfries",
    "sg:classifiers":[
        {
            "category":"Professional",
            "subcategory":"Art Services",
            "type":"Services"
        }
    ],
    "sg:postcode":"DG2 7AZ",
    "sg:province":"Dumfries and Galloway",
    "sg:tags":[
        "graphic",
        "designer"
    ],
    "wof:name":"Crosby,Robert,",
    "wof:placetype":"venue"
},
  "geometry": {"coordinates":[-3.614039,55.065285],"type":"Point"}
}