{
  "type": "Feature",
  "properties": {
    "addr:full":"34 Tippett Gardens, Hatch Warren Basingstoke Hampshire RG22 4NT",
    "addr:housenumber":"34",
    "addr:postcode":"rg22 4nt",
    "addr:street":"Tippett Gardens",
    "iso:country":"GB",
    "sg:address":"34 Tippett Gardens, Hatch Warren",
    "sg:city":"Basingstoke",
    "sg:classifiers":[
        {
            "category":"Shopping",
            "subcategory":"Catalog Store",
            "type":"Retail Goods"
        }
    ],
    "sg:phone":"+44 1256 414126",
    "sg:postcode":"RG22 4NT",
    "sg:province":"Hampshire",
    "sg:tags":[
        "mail",
        "order"
    ],
    "wof:name":"Betterware U K Ltd.",
    "wof:placetype":"venue"
},
  "geometry": {"coordinates":[-1.10482,51.241001],"type":"Point"}
}