{
  "type": "Feature",
  "properties": {
    "addr:full":"32-34 Cook Lane, Airedale Centre Keighley West Yorkshire BD21 3PF",
    "addr:housenumber":"32-34",
    "addr:postcode":"bd21 3pf",
    "addr:street":"Cook Lane;West",
    "iso:country":"GB",
    "sg:address":"32-34 Cook Lane, Airedale Centre",
    "sg:city":"Keighley",
    "sg:classifiers":[
        {
            "category":"Shopping",
            "subcategory":"Clothing, Apparel, & Fashions",
            "type":"Retail Goods"
        },
        {
            "category":"Shopping",
            "subcategory":"Baby Store",
            "type":"Retail Goods"
        }
    ],
    "sg:phone":"+44 1535 611001",
    "sg:postcode":"BD21 3PF",
    "sg:province":"West Yorkshire",
    "sg:tags":[
        "child",
        "childrens",
        "babywear"
    ],
    "sg:website":"http://www.adams.co.uk",
    "wof:name":"Adams Childrenswear Ltd.",
    "wof:placetype":"venue"
},
  "geometry": {"coordinates":[-1.9084310532,53.8671531677],"type":"Point"}
}