{
  "type": "Feature",
  "properties": {
    "addr:full":"Civic Industrial Estate, Homefield Road Haverhill Essex CB9 8QP",
    "addr:postcode":"cb9 8qp",
    "addr:street":"Homefield Road",
    "iso:country":"GB",
    "sg:address":"Civic Industrial Estate, Homefield Road",
    "sg:city":"Haverhill",
    "sg:classifiers":[
        {
            "category":"Wholesale",
            "subcategory":"Scrap",
            "type":"Manufacturing & Wholesale Goods"
        }
    ],
    "sg:phone":"+44 1440 706867",
    "sg:postcode":"CB9 8QP",
    "sg:province":"Essex",
    "sg:tags":[
        "waste",
        "metal"
    ],
    "wof:name":"Jodal Ltd.",
    "wof:placetype":"venue"
},
  "geometry": {"coordinates":[0.435798,52.085129],"type":"Point"}
}