{
  "type": "Feature",
  "properties": {
    "addr:full":"67 Bridge Street Derby Derbyshire DE1 3LB",
    "addr:housenumber":"67",
    "addr:postcode":"de1 3lb",
    "addr:street":"Bridge Street",
    "iso:country":"GB",
    "sg:address":"67 Bridge Street",
    "sg:city":"Derby",
    "sg:classifiers":[
        {
            "category":"Autos & Motor Vehicles",
            "subcategory":"Auto Supplies",
            "type":"Retail Goods"
        }
    ],
    "sg:phone":"+44 1332 347327",
    "sg:postcode":"DE1 3LB",
    "sg:province":"Derbyshire",
    "sg:tags":[
        "tyre"
    ],
    "wof:name":"Ats",
    "wof:placetype":"venue"
},
  "geometry": {"coordinates":[-1.4860479832,52.9267311096],"type":"Point"}
}