{
  "type": "Feature",
  "properties": {
    "iso:country":"GB",
    "sg:address":"264 Old Durham Rd",
    "sg:city":"Gateshead",
    "sg:classifiers":[
        {
            "category":"Taxi",
            "type":"Transportation"
        }
    ],
    "sg:phone":"+44 191 477 5555",
    "sg:postcode":"NE8 4BP",
    "sg:province":"Tyne and Wear",
    "sg:tags":[
        "mini",
        "cab"
    ],
    "wof:name":"Federation Leam Central",
    "wof:placetype":"venue"
},
  "geometry": {"coordinates":[-1.596146,54.951828],"type":"Point"}
}