{
  "type": "Feature",
  "properties": {
    "addr:full":"17-21 West End Hebden Bridge West Yorkshire HX7 8UQ",
    "addr:housenumber":"17-21",
    "addr:postcode":"hx7 8uq",
    "addr:street":"West;West",
    "iso:country":"GB",
    "sg:address":"17-21 West End",
    "sg:city":"Hebden Bridge",
    "sg:classifiers":[
        {
            "category":"Military Area",
            "subcategory":"Air Force Base",
            "type":"Public Place"
        }
    ],
    "sg:phone":"+44 1422 846666",
    "sg:postcode":"HX7 8UQ",
    "sg:province":"West Yorkshire",
    "sg:tags":[
        "taxi",
        "hire",
        "private"
    ],
    "wof:name":"Calder Cars",
    "wof:placetype":"venue"
},
  "geometry": {"coordinates":[-2.01414,53.741112],"type":"Point"}
}