{
  "type": "Feature",
  "properties": {
    "addr:full":"Railway Station Gravesend Kent DA11 0HP",
    "addr:postcode":"da11 0hp",
    "iso:country":"GB",
    "sg:address":"Railway Station",
    "sg:city":"Gravesend",
    "sg:classifiers":[
        {
            "category":"Cafe",
            "type":"Food & Drink"
        }
    ],
    "sg:phone":"+44 1474 533089",
    "sg:postcode":"DA11 0HP",
    "sg:province":"Kent",
    "sg:tags":[
        "tea",
        "room"
    ],
    "wof:name":"Travellers Fare Bookstall",
    "wof:placetype":"venue"
},
  "geometry": {"coordinates":[0.364605993,51.4328269958],"type":"Point"}
}