{
  "type": "Feature",
  "properties": {
    "addr:full":"137 High St Yarm North Yorkshire TS15 9AY",
    "addr:housenumber":"137",
    "addr:postcode":"ts15 9ay",
    "addr:street":"High St",
    "iso:country":"GB",
    "sg:address":"137 High St",
    "sg:city":"Yarm",
    "sg:classifiers":[
        {
            "category":"Sports & Exercise",
            "subcategory":"Gym",
            "type":"Entertainment"
        }
    ],
    "sg:postcode":"TS15 9AY",
    "sg:province":"North Yorkshire",
    "sg:tags":[
        "fitness",
        "health",
        "centre"
    ],
    "wof:name":"Bainbridge,Susan,",
    "wof:placetype":"venue"
},
  "geometry": {"coordinates":[-1.3559980392,54.5109863281],"type":"Point"}
}