{
  "type": "Feature",
  "properties": {
    "iso:country":"GB",
    "sg:address":"17 Borthwick Castle Terr, North Middleton",
    "sg:city":"Gorebridge",
    "sg:classifiers":[
        {
            "category":"Government",
            "subcategory":"Post Office",
            "type":"Public Place"
        }
    ],
    "sg:postcode":"EH23 4QU",
    "sg:province":"Midlothian",
    "wof:name":"Campbell,Elizabeth,",
    "wof:placetype":"venue"
},
  "geometry": {"coordinates":[-3.025415,55.820713],"type":"Point"}
}