{
  "type": "Feature",
  "properties": {
    "addr:full":"6 Angus Court Peterborough Cambridgeshire PE3 6BE",
    "addr:housenumber":"6",
    "addr:postcode":"pe3 6be",
    "addr:street":"Angus Court",
    "iso:country":"GB",
    "sg:address":"6 Angus Court",
    "sg:city":"Peterborough",
    "sg:classifiers":[
        {
            "category":"Food & Beverages",
            "subcategory":"Meat & Fish",
            "type":"Retail Goods"
        }
    ],
    "sg:phone":"+44 1733 348686",
    "sg:postcode":"PE3 6BE",
    "sg:province":"Cambridgeshire",
    "sg:tags":[
        "butcher"
    ],
    "wof:name":"Butchers",
    "wof:placetype":"venue"
},
  "geometry": {"coordinates":[-0.2611449957,52.5767288208],"type":"Point"}
}