{
  "type": "Feature",
  "properties": {
    "addr:full":"46 Evesham Walk, Kingfisher Shopping Cen Redditch Warwickshire B97 4HA",
    "addr:housenumber":"46",
    "addr:postcode":"b97 4ha",
    "addr:street":"Evesham Walk",
    "iso:country":"GB",
    "sg:address":"46 Evesham Walk, Kingfisher Shopping Cen",
    "sg:city":"Redditch",
    "sg:classifiers":[
        {
            "category":"Shopping",
            "subcategory":"Baby Store",
            "type":"Retail Goods"
        }
    ],
    "sg:phone":"+44 1527 69376",
    "sg:postcode":"B97 4HA",
    "sg:province":"Warwickshire",
    "sg:tags":[
        "nursery",
        "accessory"
    ],
    "wof:name":"Mothercare (U K) Ltd",
    "wof:placetype":"venue"
},
  "geometry": {"coordinates":[-1.9463,52.293694],"type":"Point"}
}