{
  "type": "Feature",
  "properties": {
    "iso:country":"GB",
    "sg:address":"Storaenso House, New Mill Road",
    "sg:city":"Orpington",
    "sg:classifiers":[
        {
            "category":"Manufacturing",
            "subcategory":"Paper Products",
            "type":"Manufacturing & Wholesale Goods"
        }
    ],
    "sg:phone":"+44 1689 892700",
    "sg:postcode":"BR5 3TW",
    "sg:province":"Kent",
    "sg:tags":[
        "board"
    ],
    "wof:name":"Enso Publication Papers Ltd.",
    "wof:placetype":"venue"
},
  "geometry": {"coordinates":[0.116606,51.406052],"type":"Point"}
}