{
  "type": "Feature",
  "properties": {
    "addr:full":"Hale Rd, Swavesey Cambridge Cambridgeshire CB4 5QP",
    "addr:postcode":"cb4 5qp",
    "addr:street":"Hale Rd",
    "iso:country":"GB",
    "sg:address":"Hale Rd, Swavesey",
    "sg:city":"Cambridge",
    "sg:classifiers":[
        {
            "category":"Building & Trades",
            "subcategory":"Construction",
            "type":"Services"
        }
    ],
    "sg:phone":"+44 1954 232366",
    "sg:postcode":"CB4 5QP",
    "sg:province":"Cambridgeshire",
    "sg:tags":[
        "platform",
        "work",
        "scaffolding"
    ],
    "wof:name":"R S S",
    "wof:placetype":"venue"
},
  "geometry": {"coordinates":[-0.003419,52.298969],"type":"Point"}
}