{
  "type": "Feature",
  "properties": {
    "addr:full":"224-230 Kingston Rd Portsmouth Hampshire PO2 7LR",
    "addr:housenumber":"224-230",
    "addr:postcode":"hampshire po2 7lr",
    "addr:street":"Kingston Rd",
    "iso:country":"GB",
    "sg:address":"224-230 Kingston Rd",
    "sg:city":"Portsmouth",
    "sg:classifiers":[
        {
            "category":"Manufacturing",
            "subcategory":"Rubber & Plastics",
            "type":"Manufacturing & Wholesale Goods"
        }
    ],
    "sg:phone":"+44 23 9266 2945",
    "sg:postcode":"PO2 7LR",
    "sg:province":"Hampshire",
    "sg:tags":[
        "product",
        "foam"
    ],
    "wof:name":"The Foam Shop",
    "wof:placetype":"venue"
},
  "geometry": {"coordinates":[-1.0798319578,50.8124275208],"type":"Point"}
}