{
  "type": "Feature",
  "properties": {
    "iso:country":"GB",
    "sg:address":"Yolinar Lancaster Rd",
    "sg:city":"St Leonards On Sea",
    "sg:classifiers":[
        {
            "category":"Home & Garden",
            "subcategory":"Home Furnishings",
            "type":"Retail Goods"
        }
    ],
    "sg:phone":"+44 1424 855228",
    "sg:postcode":"TN38 9LU",
    "sg:province":"East Sussex",
    "sg:tags":[
        "blind",
        "curtain",
        "fitting"
    ],
    "wof:name":"Coach House Contracts",
    "wof:placetype":"venue"
},
  "geometry": {"coordinates":[0.542262,50.880398],"type":"Point"}
}