{
  "type": "Feature",
  "properties": {
    "iso:country":"GB",
    "sg:address":"Sundorne Road",
    "sg:city":"Shrewsbury",
    "sg:classifiers":[
        {
            "category":"Education",
            "subcategory":"Special Training",
            "type":"Public Place"
        }
    ],
    "sg:phone":"+44 1743 344445",
    "sg:postcode":"SY1 4RG",
    "sg:province":"Shropshire",
    "sg:tags":[
        "martial art",
        "instruction"
    ],
    "wof:name":"Shropshire Martial Arts Centre",
    "wof:placetype":"venue"
},
  "geometry": {"coordinates":[-2.713966,52.728802],"type":"Point"}
}