{
  "type": "Feature",
  "properties": {
    "iso:country":"GB",
    "sg:address":"34 Hurst Road, Twyford",
    "sg:city":"Reading",
    "sg:classifiers":[
        {
            "category":"Farming",
            "subcategory":"Poultry Farm",
            "type":"Manufacturing & Wholesale Goods"
        }
    ],
    "sg:phone":"+44 118 934 0692",
    "sg:postcode":"RG10 0AJ",
    "sg:province":"Berkshire",
    "wof:name":"Winterton Bros",
    "wof:placetype":"venue"
},
  "geometry": {"coordinates":[-0.8628439903,51.4732322693],"type":"Point"}
}