{
  "type": "Feature",
  "properties": {
    "addr:full":"Home Farm, School Lane, Henbury Macclesfield Cheshire SK11 9PH",
    "addr:postcode":"sk11 9ph",
    "addr:street":"School Lane",
    "iso:country":"GB",
    "sg:address":"Home Farm, School Lane, Henbury",
    "sg:city":"Macclesfield",
    "sg:classifiers":[
        {
            "category":"Sports & Exercise",
            "subcategory":"Stables",
            "type":"Entertainment"
        }
    ],
    "sg:phone":"+44 1625 422511",
    "sg:postcode":"SK11 9PH",
    "sg:province":"Cheshire",
    "sg:tags":[
        "education",
        "equestrian"
    ],
    "wof:name":"Henbury Equestrian Services",
    "wof:placetype":"venue"
},
  "geometry": {"coordinates":[-2.18059,53.260124],"type":"Point"}
}