{
  "type": "Feature",
  "properties": {
    "addr:full":"Market Street, Clay Cross Chesterfield Derbyshire S45 9LX",
    "addr:postcode":"s45 9lx",
    "addr:street":"Market Street",
    "iso:country":"GB",
    "sg:address":"Market Street, Clay Cross",
    "sg:city":"Chesterfield",
    "sg:classifiers":[
        {
            "category":"Community Center",
            "type":"Public Place"
        }
    ],
    "sg:phone":"+44 1246 217277",
    "sg:postcode":"S45 9LX",
    "sg:province":"Derbyshire",
    "sg:tags":[
        "recreation",
        "leisure",
        "centre"
    ],
    "wof:name":"Sharley Park Leisure Centre",
    "wof:placetype":"venue"
},
  "geometry": {"coordinates":[-1.403914,53.170631],"type":"Point"}
}