{
  "type": "Feature",
  "properties": {
    "iso:country":"GB",
    "sg:address":"The Yard Rear Of Church St, Church St",
    "sg:city":"Neath",
    "sg:classifiers":[
        {
            "category":"Building & Trades",
            "subcategory":"Construction",
            "type":"Services"
        }
    ],
    "sg:phone":"+44 1639 820431",
    "sg:postcode":"SA11 2JD",
    "sg:province":"Neath Port Talbot",
    "sg:tags":[
        "roofing"
    ],
    "wof:name":"Williams",
    "wof:placetype":"venue"
},
  "geometry": {"coordinates":[-3.799813,51.662712],"type":"Point"}
}