{
  "type": "Feature",
  "properties": {
    "iso:country":"GB",
    "sg:address":"Bamfield Ho",
    "sg:city":"Bristol",
    "sg:classifiers":[
        {
            "category":"Bus Charters",
            "type":"Transportation"
        }
    ],
    "sg:phone":"+44 1275 839555",
    "sg:postcode":"BS14 0XD",
    "sg:province":"City of Bristol",
    "sg:tags":[
        "hire",
        "coach"
    ],
    "wof:name":"Peter Carol Prestige Coaching",
    "wof:placetype":"venue"
},
  "geometry": {"coordinates":[-2.5792140961,51.42029953],"type":"Point"}
}