{
  "type": "Feature",
  "properties": {
    "iso:country":"GB",
    "sg:address":"718 King Lane",
    "sg:city":"Leeds",
    "sg:classifiers":[
        {
            "category":"Retail",
            "subcategory":"Laundry & Dry Cleaning",
            "type":"Services"
        }
    ],
    "sg:phone":"+44 113 261 3055",
    "sg:postcode":"LS17 7BA",
    "sg:province":"North Yorkshire",
    "sg:tags":[
        "cleaner",
        "alteration"
    ],
    "wof:name":"Regency Dry Cleaners",
    "wof:placetype":"venue"
},
  "geometry": {"coordinates":[-1.562951,53.856884],"type":"Point"}
}