{
  "type": "Feature",
  "properties": {
    "addr:full":"Whitchurch Road Chester Cheshire CH3 6AE",
    "addr:postcode":"ch3 6ae",
    "addr:street":"Whitchurch Road",
    "iso:country":"GB",
    "sg:address":"Whitchurch Road",
    "sg:city":"Chester",
    "sg:classifiers":[
        {
            "category":"Autos & Motor Vehicles",
            "subcategory":"Automobile Sales",
            "type":"Retail Goods"
        }
    ],
    "sg:phone":"+44 1244 336565",
    "sg:postcode":"CH3 6AE",
    "sg:province":"Cheshire",
    "sg:tags":[
        "car"
    ],
    "wof:name":"N & G Dickens",
    "wof:placetype":"venue"
},
  "geometry": {"coordinates":[-2.845267,53.18515],"type":"Point"}
}