{
  "type": "Feature",
  "properties": {
    "addr:full":"Back La Hitchin Hertfordshire SG4 7UJ",
    "addr:postcode":"sg4 7uj",
    "addr:street":"La Hitchin",
    "iso:country":"GB",
    "sg:address":"Back La",
    "sg:city":"Hitchin",
    "sg:classifiers":[
        {
            "category":"Building & Trades",
            "subcategory":"Construction",
            "type":"Services"
        }
    ],
    "sg:phone":"+44 1462 459475",
    "sg:postcode":"SG4 7UJ",
    "sg:province":"Hertfordshire",
    "sg:tags":[
        "platform",
        "work",
        "scaffolding"
    ],
    "wof:name":"Benbridge (Scaffolding) Ltd",
    "wof:placetype":"venue"
},
  "geometry": {"coordinates":[-0.29294,51.907154],"type":"Point"}
}