{
  "type": "Feature",
  "properties": {
    "addr:full":"4 Main Street Wishaw North Lanarkshire ML2 7AF",
    "addr:housenumber":"4",
    "addr:postcode":"ml2 7af",
    "addr:street":"Main Street",
    "iso:country":"GB",
    "sg:address":"4 Main Street",
    "sg:city":"Wishaw",
    "sg:classifiers":[
        {
            "category":"Health Services",
            "subcategory":"Dentist",
            "type":"Services"
        }
    ],
    "sg:phone":"+44 1698 372277",
    "sg:postcode":"ML2 7AF",
    "sg:province":"North Lanarkshire",
    "wof:name":"Wishaw Cross Dental Surgery",
    "wof:placetype":"venue"
},
  "geometry": {"coordinates":[-3.9212119579,55.7746925354],"type":"Point"}
}