{
  "type": "Feature",
  "properties": {
    "iso:country":"GB",
    "sg:address":"71 Redditch Road, Stoke Heath",
    "sg:city":"Bromsgrove",
    "sg:classifiers":[
        {
            "category":"Education",
            "subcategory":"Special Training",
            "type":"Public Place"
        }
    ],
    "sg:phone":"+44 1527 878493",
    "sg:postcode":"B60 4JP",
    "sg:province":"Worcestershire",
    "sg:tags":[
        "school",
        "language"
    ],
    "wof:name":"Nicole Harris",
    "wof:placetype":"venue"
},
  "geometry": {"coordinates":[-2.074679,52.314812],"type":"Point"}
}