{
  "type": "Feature",
  "properties": {
    "addr:full":"8 Ross Avenue, Whitefield Manchester Lancashire M45 7FH",
    "addr:housenumber":"8",
    "addr:postcode":"m45 7fh",
    "addr:street":"Ross Avenue",
    "iso:country":"GB",
    "sg:address":"8 Ross Avenue, Whitefield",
    "sg:city":"Manchester",
    "sg:classifiers":[
        {
            "category":"Health Services",
            "subcategory":"Health Practitioner",
            "type":"Services"
        }
    ],
    "sg:phone":"+44 161 766 3160",
    "sg:postcode":"M45 7FH",
    "sg:province":"Lancashire",
    "sg:tags":[
        "therapist",
        "speech"
    ],
    "wof:name":"Ross Therapies",
    "wof:placetype":"venue"
},
  "geometry": {"coordinates":[-2.2937760353,53.5390090942],"type":"Point"}
}