{
  "type": "Feature",
  "properties": {
    "iso:country":"GB",
    "sg:address":"11 Oakfield Avenue",
    "sg:city":"Hitchin",
    "sg:classifiers":[
        {
            "category":"Professional",
            "subcategory":"Management & Consulting",
            "type":"Services"
        }
    ],
    "sg:phone":"+44 1462 433695",
    "sg:postcode":"SG4 9JB",
    "sg:province":"Hertfordshire",
    "sg:tags":[
        "consultant",
        "energy",
        "conservation"
    ],
    "wof:name":"The P A Network",
    "wof:placetype":"venue"
},
  "geometry": {"coordinates":[-0.261897,51.940338],"type":"Point"}
}