{
  "type": "Feature",
  "properties": {
    "addr:full":"46 Kempe Road Enfield Greater London EN1 4QS",
    "addr:housenumber":"46",
    "addr:postcode":"en1 4qs",
    "addr:street":"Kempe Road",
    "iso:country":"GB",
    "sg:address":"46 Kempe Road",
    "sg:city":"Enfield",
    "sg:classifiers":[
        {
            "category":"Education",
            "subcategory":"Library",
            "type":"Public Place"
        }
    ],
    "sg:phone":"+44 1992 788779",
    "sg:postcode":"EN1 4QS",
    "sg:province":"Greater London",
    "sg:tags":[
        "book"
    ],
    "wof:name":"Kempe Road Library",
    "wof:placetype":"venue"
},
  "geometry": {"coordinates":[-0.048287,51.676273],"type":"Point"}
}