{
  "type": "Feature",
  "properties": {
    "addr:full":"6-16 Neptune Street Birkenhead Merseyside CH41 3QT",
    "addr:housenumber":"6-16",
    "addr:postcode":"ch41 3qt",
    "addr:street":"Neptune Street",
    "iso:country":"GB",
    "sg:address":"6-16 Neptune Street",
    "sg:city":"Birkenhead",
    "sg:classifiers":[
        {
            "category":"Personal",
            "subcategory":"Beauty Salon",
            "type":"Services"
        },
        {
            "category":"Freight",
            "type":"Transportation"
        }
    ],
    "sg:phone":"+44 151 647 9708",
    "sg:postcode":"CH41 3QT",
    "sg:province":"Merseyside",
    "sg:tags":[
        "haulage",
        "unisex",
        "road",
        "transport",
        "hairdresser"
    ],
    "wof:name":"WHALLEY ROAD SERVICES LTD",
    "wof:placetype":"venue"
},
  "geometry": {"coordinates":[-3.0272250175,53.3987770081],"type":"Point"}
}