{
  "type": "Feature",
  "properties": {
    "addr:full":"36 Inkerman Terrace Chesham Buckinghamshire HP5 1QA",
    "addr:housenumber":"36",
    "addr:postcode":"hp5 1qa",
    "addr:street":"Inkerman Terrace",
    "iso:country":"GB",
    "sg:address":"36 Inkerman Terrace",
    "sg:city":"Chesham",
    "sg:classifiers":[
        {
            "category":"Professional",
            "subcategory":"Business Services",
            "type":"Services"
        }
    ],
    "sg:phone":"+44 1494 786710",
    "sg:postcode":"HP5 1QA",
    "sg:province":"Buckinghamshire",
    "sg:tags":[
        "import",
        "export",
        "agent"
    ],
    "wof:name":"Martin Christopher Crosbie",
    "wof:placetype":"venue"
},
  "geometry": {"coordinates":[-0.6063230038,51.6990127563],"type":"Point"}
}