{
  "type": "Feature",
  "properties": {
    "iso:country":"GB",
    "sg:address":"4 Bexley High Street",
    "sg:city":"Bexley",
    "sg:classifiers":[
        {
            "category":"Real Estate",
            "subcategory":"Real Estate Agent",
            "type":"Services"
        }
    ],
    "sg:phone":"+44 1322 522111",
    "sg:postcode":"DA5 1AD",
    "sg:province":"Kent",
    "wof:name":"Village Estates",
    "wof:placetype":"venue"
},
  "geometry": {"coordinates":[0.1481409967,51.4413566589],"type":"Point"}
}