{
  "type": "Feature",
  "properties": {
    "iso:country":"GB",
    "sg:address":"Hursley Business Park, Bickleigh Down Rd, Roborough",
    "sg:city":"Plymouth",
    "sg:classifiers":[
        {
            "category":"Home & Garden",
            "subcategory":"Garden Supply",
            "type":"Retail Goods"
        }
    ],
    "sg:phone":"+44 1752 775526",
    "sg:postcode":"PL7 2GN",
    "sg:province":"Devon",
    "sg:tags":[
        "aggregate",
        "sand",
        "gravel"
    ],
    "wof:name":"Arggregate Supplies South West Ltd",
    "wof:placetype":"venue"
},
  "geometry": {"coordinates":[-4.02539,50.388821],"type":"Point"}
}