{
  "type": "Feature",
  "properties": {
    "addr:full":"Kingston International Bsns Park, Somerden Road, Hedon Road Hull East Riding of Yorkshire HU9 5PE",
    "addr:postcode":"hu9 5pe",
    "addr:street":"Somerden Road Hedon Road",
    "iso:country":"GB",
    "sg:address":"Kingston International Bsns Park, Somerden Road, Hedon Road",
    "sg:city":"Hull",
    "sg:classifiers":[
        {
            "category":"Building & Trades",
            "subcategory":"Construction",
            "type":"Services"
        }
    ],
    "sg:phone":"+44 1482 789000",
    "sg:postcode":"HU9 5PE",
    "sg:province":"East Riding of Yorkshire",
    "sg:tags":[
        "door",
        "replacement"
    ],
    "wof:name":"Hurst Plastics Ltd.",
    "wof:placetype":"venue"
},
  "geometry": {"coordinates":[-0.2500700057,53.7474212646],"type":"Point"}
}