{
  "type": "Feature",
  "properties": {
    "iso:country":"GB",
    "sg:address":"271 Banbury Road, Summertown",
    "sg:city":"Oxford",
    "sg:classifiers":[
        {
            "category":"Health Services",
            "subcategory":"Health Practitioner",
            "type":"Services"
        }
    ],
    "sg:postcode":"OX2 7JF",
    "sg:province":"Oxfordshire",
    "sg:tags":[
        "osteopath"
    ],
    "wof:name":"John C O'Brien",
    "wof:placetype":"venue"
},
  "geometry": {"coordinates":[-1.26594,51.779503],"type":"Point"}
}