{
  "type": "Feature",
  "properties": {
    "addr:full":"Crabtree Farm, Watling Street, Witherley Atherstone Leicestershire CV9 1RE",
    "addr:postcode":"cv9 1re",
    "addr:street":"Watling Street",
    "iso:country":"GB",
    "sg:address":"Crabtree Farm, Watling Street, Witherley",
    "sg:city":"Atherstone",
    "sg:classifiers":[
        {
            "category":"Farming",
            "subcategory":"Livestock Farm",
            "type":"Manufacturing & Wholesale Goods"
        }
    ],
    "sg:phone":"+44 1827 713140",
    "sg:postcode":"CV9 1RE",
    "sg:province":"Leicestershire",
    "sg:tags":[
        "others"
    ],
    "wof:name":"Ingram Bros",
    "wof:placetype":"venue"
},
  "geometry": {"coordinates":[-1.541959,52.575935],"type":"Point"}
}