{
  "type": "Feature",
  "properties": {
    "addr:full":"125 College Road, Crosby Liverpool Merseyside L23 3AS",
    "addr:housenumber":"125",
    "addr:postcode":"l23 3as",
    "addr:street":"College Road",
    "iso:country":"GB",
    "sg:address":"125 College Road, Crosby",
    "sg:city":"Liverpool",
    "sg:classifiers":[
        {
            "category":"Health Services",
            "subcategory":"Dentist",
            "type":"Services"
        }
    ],
    "sg:phone":"+44 151 932 0330",
    "sg:postcode":"L23 3AS",
    "sg:province":"Merseyside",
    "sg:tags":[
        "technician",
        "dental"
    ],
    "wof:name":"Denture Cosmetics",
    "wof:placetype":"venue"
},
  "geometry": {"coordinates":[-3.0324289799,53.4858283997],"type":"Point"}
}