{
  "type": "Feature",
  "properties": {
    "addr:full":"161 Bute St, Treherbert Treorchy Rhondda, Cynon, Taff CF42 5PE",
    "addr:housenumber":"161",
    "addr:postcode":"cf42 5pe",
    "addr:street":"Bute St;Cynon Taff",
    "iso:country":"GB",
    "sg:address":"161 Bute St, Treherbert",
    "sg:city":"Treorchy",
    "sg:classifiers":[
        {
            "category":"Home & Garden",
            "subcategory":"Hardware",
            "type":"Retail Goods"
        }
    ],
    "sg:postcode":"CF42 5PE",
    "sg:province":"Rhondda, Cynon, Taff",
    "sg:tags":[
        "retailer",
        "diy"
    ],
    "wof:name":"K & E Morgan",
    "wof:placetype":"venue"
},
  "geometry": {"coordinates":[-3.535792,51.674267],"type":"Point"}
}