{
  "type": "Feature",
  "properties": {
    "iso:country":"GB",
    "sg:address":"Cooper Street",
    "sg:city":"Hull",
    "sg:classifiers":[
        {
            "category":"Professional",
            "subcategory":"Engineering",
            "type":"Services"
        }
    ],
    "sg:phone":"+44 1482 327666",
    "sg:postcode":"HU2 0HA",
    "sg:province":"East Riding of Yorkshire",
    "wof:name":"Fentons Maintenance",
    "wof:placetype":"venue"
},
  "geometry": {"coordinates":[-0.334474,53.751476],"type":"Point"}
}