{
  "type": "Feature",
  "properties": {
    "iso:country":"GB",
    "sg:address":"7 Denning Drive, Irby",
    "sg:city":"Wirral",
    "sg:classifiers":[
        {
            "category":"Retail",
            "subcategory":"Driving School",
            "type":"Services"
        }
    ],
    "sg:postcode":"CH61 4YH",
    "sg:province":"Merseyside",
    "wof:name":"Morris School of Motoring",
    "wof:placetype":"venue"
},
  "geometry": {"coordinates":[-3.113947,53.358833],"type":"Point"}
}