{
  "type": "Feature",
  "properties": {
    "iso:country":"GB",
    "sg:address":"17 Church Street",
    "sg:city":"Cardiff",
    "sg:classifiers":[
        {
            "category":"Restaurant",
            "type":"Food & Drink"
        }
    ],
    "sg:phone":"+44 29 2022 2078",
    "sg:postcode":"CF10 1BG",
    "sg:province":"Cardiff",
    "sg:tags":[
        "american",
        "-"
    ],
    "sg:website":"http://www.oldorleans.com",
    "wof:name":"Old Orleans",
    "wof:placetype":"venue"
},
  "geometry": {"coordinates":[-3.179435,51.48019],"type":"Point"}
}