{
  "type": "Feature",
  "properties": {
    "addr:full":"8 Oakleigh Road Bexhill-on-sea East Sussex TN39 4PY",
    "addr:housenumber":"8",
    "addr:postcode":"tn39 4py",
    "addr:street":"Oakleigh Road",
    "iso:country":"GB",
    "sg:address":"8 Oakleigh Road",
    "sg:city":"Bexhill-on-sea",
    "sg:classifiers":[
        {
            "category":"Building & Trades",
            "subcategory":"Construction",
            "type":"Services"
        }
    ],
    "sg:phone":"+44 1424 845053",
    "sg:postcode":"TN39 4PY",
    "sg:province":"East Sussex",
    "sg:tags":[
        "decorator",
        "painter"
    ],
    "wof:name":"Ninfield Decorating Service",
    "wof:placetype":"venue"
},
  "geometry": {"coordinates":[0.4316090047,50.8462562561],"type":"Point"}
}