{
  "type": "Feature",
  "properties": {
    "addr:full":"103 Overstone Road, Sywell Northampton Northamptonshire NN6 0AW",
    "addr:housenumber":"103",
    "addr:postcode":"nn6 0aw",
    "addr:street":"Overstone Road",
    "iso:country":"GB",
    "sg:address":"103 Overstone Road, Sywell",
    "sg:city":"Northampton",
    "sg:classifiers":[
        {
            "category":"Retail",
            "subcategory":"Auto Repair",
            "type":"Services"
        }
    ],
    "sg:phone":"+44 7973 841947",
    "sg:postcode":"NN6 0AW",
    "sg:province":"Northamptonshire",
    "sg:tags":[
        "modification",
        "garage"
    ],
    "wof:name":"Sywell Auto's",
    "wof:placetype":"venue"
},
  "geometry": {"coordinates":[-0.806602,52.294247],"type":"Point"}
}