{
  "type": "Feature",
  "properties": {
    "iso:country":"GB",
    "sg:address":"34 Lowther Street",
    "sg:city":"Carlisle",
    "sg:classifiers":[
        {
            "category":"Real Estate",
            "subcategory":"Surveying",
            "type":"Services"
        }
    ],
    "sg:phone":"+44 1228 810348",
    "sg:postcode":"CA3 8DH",
    "sg:province":"Cumbria",
    "sg:tags":[
        "surveyor",
        "valuer"
    ],
    "wof:name":"S W Holmes & Co",
    "wof:placetype":"venue"
},
  "geometry": {"coordinates":[-2.9332020283,54.8943328857],"type":"Point"}
}