{
  "type": "Feature",
  "properties": {
    "iso:country":"GB",
    "sg:address":"Drop In Centre, Winchester Rd",
    "sg:city":"Andover",
    "sg:classifiers":[
        {
            "category":"Professional",
            "subcategory":"Lawyer & Legal Services",
            "type":"Services"
        }
    ],
    "sg:phone":"+44 1264 332053",
    "sg:postcode":"SP10 2EG",
    "sg:province":"Hampshire",
    "sg:tags":[
        "advice",
        "counselling"
    ],
    "wof:name":"House The",
    "wof:placetype":"venue"
},
  "geometry": {"coordinates":[-1.476779,51.206493],"type":"Point"}
}