{
  "type": "Feature",
  "properties": {
    "iso:country":"GB",
    "sg:address":"8 Norton Lees Lane",
    "sg:city":"Sheffield",
    "sg:classifiers":[
        {
            "category":"Retail",
            "subcategory":"Driving School",
            "type":"Services"
        }
    ],
    "sg:postcode":"S8 9BD",
    "sg:province":"Derbyshire",
    "sg:tags":[
        "instruction",
        "cycling",
        "motor"
    ],
    "wof:name":"White Rose Motor Cycle Training Centre",
    "wof:placetype":"venue"
},
  "geometry": {"coordinates":[-1.476343,53.348392],"type":"Point"}
}