{
  "type": "Feature",
  "properties": {
    "iso:country":"GB",
    "sg:address":"6 South Close, Village Way",
    "sg:city":"Pinner",
    "sg:classifiers":[
        {
            "category":"Professional",
            "subcategory":"Printing & Photocopies",
            "type":"Services"
        }
    ],
    "sg:postcode":"HA5 5AE",
    "sg:province":"Greater London",
    "sg:tags":[
        "embroiderer"
    ],
    "wof:name":"Elgina",
    "wof:placetype":"venue"
},
  "geometry": {"coordinates":[-0.3729659915,51.5762863159],"type":"Point"}
}