{
  "type": "Feature",
  "properties": {
    "addr:full":"Orchard House, Boleness Road Wisbech Cambridgeshire PE13 2RB",
    "addr:postcode":"pe13 2rb",
    "addr:street":"Boleness Road",
    "iso:country":"GB",
    "sg:address":"Orchard House, Boleness Road",
    "sg:city":"Wisbech",
    "sg:classifiers":[
        {
            "category":"Freight",
            "type":"Transportation"
        }
    ],
    "sg:postcode":"PE13 2RB",
    "sg:province":"Cambridgeshire",
    "sg:tags":[
        "haulage",
        "road"
    ],
    "wof:name":"Heathcliff Haulage Ltd",
    "wof:placetype":"venue"
},
  "geometry": {"coordinates":[0.1610530019,52.6523132324],"type":"Point"}
}