{
  "type": "Feature",
  "properties": {
    "iso:country":"GB",
    "sg:address":"2 Aughton Street",
    "sg:city":"Ormskirk",
    "sg:classifiers":[
        {
            "category":"Shopping",
            "subcategory":"Optician",
            "type":"Retail Goods"
        },
        {
            "category":"Health Services",
            "subcategory":"Optometrist",
            "type":"Services"
        }
    ],
    "sg:phone":"+44 151 708 5072",
    "sg:postcode":"L39 3BW",
    "sg:province":"Lancashire",
    "sg:tags":[
        "opthalmic",
        "ophthalmic"
    ],
    "sg:website":"http://www.conlons.co.uk",
    "wof:name":"Conlon & Sons Opticians",
    "wof:placetype":"venue"
},
  "geometry": {"coordinates":[-2.886279,53.567326],"type":"Point"}
}