{
  "type": "Feature",
  "properties": {
    "addr:full":"The Old Bakery Fford Maelog Rhosneigr Isle of Anglesey LL64 5QE",
    "addr:postcode":"ll64 5qe",
    "addr:street":"Rhosneigr",
    "iso:country":"GB",
    "sg:address":"The Old Bakery Fford Maelog",
    "sg:city":"Rhosneigr",
    "sg:classifiers":[
        {
            "category":"Health Services",
            "subcategory":"Dentist",
            "type":"Services"
        }
    ],
    "sg:phone":"+44 1407 810872",
    "sg:postcode":"LL64 5QE",
    "sg:province":"Isle of Anglesey",
    "sg:tags":[
        "technician",
        "dental"
    ],
    "wof:name":"Homer Dental Services",
    "wof:placetype":"venue"
},
  "geometry": {"coordinates":[-4.5197491646,53.2297286987],"type":"Point"}
}