{
  "type": "Feature",
  "properties": {
    "iso:country":"GB",
    "sg:address":"72 Whireladies Road, Clifton",
    "sg:city":"Bristol",
    "sg:classifiers":[
        {
            "category":"Personal",
            "subcategory":"Beauty Salon",
            "type":"Services"
        }
    ],
    "sg:phone":"+44 117 973 8228",
    "sg:postcode":"BS8 2QA",
    "sg:province":"City of Bristol",
    "sg:tags":[
        "unisex",
        "hairdresser"
    ],
    "wof:name":"Paul Bond Hair & Beauty",
    "wof:placetype":"venue"
},
  "geometry": {"coordinates":[-2.6109600067,51.4658203125],"type":"Point"}
}