{
  "type": "Feature",
  "properties": {
    "iso:country":"GB",
    "sg:address":"The Plaza, Ironmasters Way",
    "sg:city":"Telford",
    "sg:classifiers":[
        {
            "category":"Professional",
            "subcategory":"Employment Agencies",
            "type":"Services"
        }
    ],
    "sg:phone":"+44 1952 299633",
    "sg:postcode":"TF3 4NT",
    "sg:province":"Shropshire",
    "sg:tags":[
        "consultant"
    ],
    "wof:name":"The Pyrah Harris Partnership",
    "wof:placetype":"venue"
},
  "geometry": {"coordinates":[-2.443571,52.678844],"type":"Point"}
}