{
  "type": "Feature",
  "properties": {
    "addr:full":"Kempton Park Close, Alvaston Derby Derbyshire DE24 8QB",
    "addr:postcode":"de24 8qb",
    "addr:street":"Kempton Park Close",
    "iso:country":"GB",
    "sg:address":"Kempton Park Close, Alvaston",
    "sg:city":"Derby",
    "sg:classifiers":[
        {
            "category":"Building & Trades",
            "subcategory":"Construction",
            "type":"Services"
        }
    ],
    "sg:postcode":"DE24 8QB",
    "sg:province":"Derbyshire",
    "sg:tags":[
        "window",
        "replacement"
    ],
    "wof:name":"A & R Building Services",
    "wof:placetype":"venue"
},
  "geometry": {"coordinates":[-1.453783989,52.8995628357],"type":"Point"}
}