{
  "type": "Feature",
  "properties": {
    "iso:country":"GB",
    "sg:address":"46-48 Market Street",
    "sg:city":"Carnforth",
    "sg:classifiers":[
        {
            "category":"Health Services",
            "subcategory":"Dentist",
            "type":"Services"
        }
    ],
    "sg:phone":"+44 1524 733867",
    "sg:postcode":"LA5 9LB",
    "sg:province":"Cumbria",
    "wof:name":"Peter J M Docton",
    "wof:placetype":"venue"
},
  "geometry": {"coordinates":[-2.767208,54.128937],"type":"Point"}
}