{
  "type": "Feature",
  "properties": {
    "addr:full":"50 Cornhill London Greater London EC3V 3PD",
    "addr:housenumber":"50",
    "addr:postcode":"ec3v 3pd",
    "addr:street":"Cornhill",
    "iso:country":"GB",
    "sg:address":"50 Cornhill",
    "sg:city":"London",
    "sg:classifiers":[
        {
            "category":"Organizations",
            "subcategory":"Membership Organization",
            "type":"Services"
        }
    ],
    "sg:postcode":"EC3V 3PD",
    "sg:province":"Greater London",
    "sg:tags":[
        "club"
    ],
    "wof:name":"City University Club",
    "wof:placetype":"venue"
},
  "geometry": {"coordinates":[-0.084963,51.513313],"type":"Point"}
}