{
  "type": "Feature",
  "properties": {
    "addr:full":"Elgin Place Falkirk Falkirk FK1 1QN",
    "addr:postcode":"fk1 1qn",
    "addr:street":"Elgin Place",
    "iso:country":"GB",
    "sg:address":"Elgin Place",
    "sg:city":"Falkirk",
    "sg:classifiers":[
        {
            "category":"Organizations",
            "subcategory":"Non-profit Organization",
            "type":"Services"
        }
    ],
    "sg:phone":"+44 1324 620394",
    "sg:postcode":"FK1 1QN",
    "sg:province":"Falkirk",
    "sg:tags":[
        "charitable",
        "organisation",
        "voluntary",
        "charity"
    ],
    "wof:name":"Enable Scottish Society For The Mentally Handicapped",
    "wof:placetype":"venue"
},
  "geometry": {"coordinates":[-3.781024,55.996429],"type":"Point"}
}