{
  "type": "Feature",
  "properties": {
    "iso:country":"GB",
    "sg:address":"37 Stamperland Crescent, Clarkston",
    "sg:city":"Glasgow",
    "sg:classifiers":[
        {
            "category":"Home & Garden",
            "subcategory":"Kitchen Supply",
            "type":"Retail Goods"
        }
    ],
    "sg:postcode":"G76 8LH",
    "sg:province":"East Renfrewshire",
    "sg:tags":[
        "measuring",
        "scale"
    ],
    "wof:name":"D Brash & Sons Ltd.",
    "wof:placetype":"venue"
},
  "geometry": {"coordinates":[-4.270878,55.79002],"type":"Point"}
}