{
  "type": "Feature",
  "properties": {
    "addr:full":"Shore Street Campbeltown Argyll and Bute PA28 6BT",
    "addr:postcode":"pa28 6bt",
    "addr:street":"Shore Street",
    "iso:country":"GB",
    "sg:address":"Shore Street",
    "sg:city":"Campbeltown",
    "sg:classifiers":[
        {
            "category":"Social Services",
            "subcategory":"Retirement Home",
            "type":"Services"
        }
    ],
    "sg:phone":"+44 1586 553615",
    "sg:postcode":"PA28 6BT",
    "sg:province":"Argyll and Bute",
    "sg:tags":[
        "residential",
        "care"
    ],
    "wof:name":"Kintyre Care Centre",
    "wof:placetype":"venue"
},
  "geometry": {"coordinates":[-5.604404,55.424225],"type":"Point"}
}