{
  "type": "Feature",
  "properties": {
    "addr:full":"9 Penn Drive, Denham Grn Uxbridge Buckinghamshire UB9 5JP",
    "addr:housenumber":"9",
    "addr:postcode":"ub9 5jp",
    "addr:street":"Penn Drive;Grn",
    "iso:country":"GB",
    "sg:address":"9 Penn Drive, Denham Grn",
    "sg:city":"Uxbridge",
    "sg:classifiers":[
        {
            "category":"Professional",
            "subcategory":"Engineering",
            "type":"Services"
        }
    ],
    "sg:postcode":"UB9 5JP",
    "sg:province":"Buckinghamshire",
    "sg:tags":[
        "contractor",
        "electrical",
        "engineer"
    ],
    "wof:name":"Wise Electrical Developments",
    "wof:placetype":"venue"
},
  "geometry": {"coordinates":[-0.502855,51.581146],"type":"Point"}
}