{
  "type": "Feature",
  "properties": {
    "addr:full":"102 Queen St Newton Abbot Devon TQ12 2EU",
    "addr:housenumber":"102",
    "addr:postcode":"tq12 2eu",
    "addr:street":"Queen St",
    "iso:country":"GB",
    "sg:address":"102 Queen St",
    "sg:city":"Newton Abbot",
    "sg:classifiers":[
        {
            "category":"Personal",
            "subcategory":"Barber",
            "type":"Services"
        }
    ],
    "sg:postcode":"TQ12 2EU",
    "sg:province":"Devon",
    "sg:tags":[
        "men's",
        "hairdresser"
    ],
    "wof:name":"Brimson,R H,",
    "wof:placetype":"venue"
},
  "geometry": {"coordinates":[-3.6028709412,50.530834198],"type":"Point"}
}