{
  "type": "Feature",
  "properties": {
    "iso:country":"GB",
    "sg:address":"24 Aviemore Road",
    "sg:city":"Doncaster",
    "sg:classifiers":[
        {
            "category":"Professional",
            "type":"Services"
        }
    ],
    "sg:phone":"+44 1302 310690",
    "sg:postcode":"DN4 9NE",
    "sg:province":"South Yorkshire",
    "sg:tags":[
        "entertainer"
    ],
    "wof:name":"Java & Management",
    "wof:placetype":"venue"
},
  "geometry": {"coordinates":[-1.170716,53.498676],"type":"Point"}
}