{
  "type": "Feature",
  "properties": {
    "addr:full":"386 East Park Road Leicester Leicestershire LE5 5HH",
    "addr:housenumber":"386",
    "addr:postcode":"le5 5hh",
    "addr:street":"East Park Road",
    "iso:country":"GB",
    "sg:address":"386 East Park Road",
    "sg:city":"Leicester",
    "sg:classifiers":[
        {
            "category":"Professional",
            "subcategory":"Business Services",
            "type":"Services"
        }
    ],
    "sg:phone":"+44 116 273 5111",
    "sg:postcode":"LE5 5HH",
    "sg:province":"Leicestershire",
    "sg:tags":[
        "import",
        "export",
        "agent"
    ],
    "wof:name":"C E M Engineering Ltd.",
    "wof:placetype":"venue"
},
  "geometry": {"coordinates":[-1.107596,52.628845],"type":"Point"}
}