{
  "type": "Feature",
  "properties": {
    "addr:full":"17 Roundham Road Paignton Devon TQ4 6DN",
    "addr:housenumber":"17",
    "addr:postcode":"tq4 6dn",
    "addr:street":"Roundham Road",
    "iso:country":"GB",
    "sg:address":"17 Roundham Road",
    "sg:city":"Paignton",
    "sg:classifiers":[
        {
            "category":"Travel",
            "subcategory":"Hotels & Motels",
            "type":"Entertainment"
        }
    ],
    "sg:phone":"+44 1803 557722",
    "sg:postcode":"TQ4 6DN",
    "sg:province":"Devon",
    "wof:name":"Seaford Sands Hotel",
    "wof:placetype":"venue"
},
  "geometry": {"coordinates":[-3.56175,50.429298],"type":"Point"}
}