{
  "type": "Feature",
  "properties": {
    "addr:full":"6a Wales Court Downham Market Cambridgeshire PE38 9JZ",
    "addr:housenumber":"6a",
    "addr:postcode":"pe38 9jz",
    "addr:street":"Wales Court",
    "iso:country":"GB",
    "sg:address":"6a Wales Court",
    "sg:city":"Downham Market",
    "sg:classifiers":[
        {
            "category":"Community Center",
            "subcategory":"Social",
            "type":"Public Place"
        }
    ],
    "sg:phone":"+44 1366 386390",
    "sg:postcode":"PE38 9JZ",
    "sg:province":"Cambridgeshire",
    "sg:tags":[
        "frozen",
        "food",
        "freezer",
        "centre"
    ],
    "wof:name":"Iceland Foods Plc",
    "wof:placetype":"venue"
},
  "geometry": {"coordinates":[0.3793950081,52.6009254456],"type":"Point"}
}