{
  "type": "Feature",
  "properties": {
    "iso:country":"GB",
    "sg:address":"26 Blackhorse Road",
    "sg:city":"Bristol",
    "sg:classifiers":[
        {
            "category":"Building & Trades",
            "subcategory":"Construction",
            "type":"Services"
        }
    ],
    "sg:postcode":"BS15 8EF",
    "sg:province":"City of Bristol",
    "sg:tags":[
        "joiner",
        "carpenter"
    ],
    "wof:name":"Ash Carpenters",
    "wof:placetype":"venue"
},
  "geometry": {"coordinates":[-2.512203,51.46011],"type":"Point"}
}