{
  "type": "Feature",
  "properties": {
    "iso:country":"GB",
    "sg:address":"Rear Of 475 Christchurch Road",
    "sg:city":"Bournemouth",
    "sg:classifiers":[
        {
            "category":"Retail",
            "subcategory":"Auto Repair",
            "type":"Services"
        }
    ],
    "sg:phone":"+44 1202 303788",
    "sg:postcode":"BH1 4AD",
    "sg:province":"Dorset",
    "sg:tags":[
        "engine",
        "car",
        "specialist"
    ],
    "wof:name":"Targa Florio",
    "wof:placetype":"venue"
},
  "geometry": {"coordinates":[-1.845780015,50.7248191833],"type":"Point"}
}