{
  "type": "Feature",
  "properties": {
    "iso:country":"GB",
    "sg:address":"36 St Botolphs Street",
    "sg:city":"Colchester",
    "sg:classifiers":[
        {
            "category":"Shopping",
            "subcategory":"Hobbies, Toys, & Games",
            "type":"Retail Goods"
        },
        {
            "category":"Transit Center",
            "subcategory":"Freight",
            "type":"Transportation"
        }
    ],
    "sg:phone":"+44 1206 368787",
    "sg:postcode":"CO2 7EA",
    "sg:province":"Essex",
    "sg:tags":[
        "item",
        "collector",
        "gunsmith"
    ],
    "wof:name":"Jeremy Tenniswood",
    "wof:placetype":"venue"
},
  "geometry": {"coordinates":[0.90365,51.88726],"type":"Point"}
}