{
  "type": "Feature",
  "properties": {
    "addr:full":"138 Kingsbury Road, Erdington Birmingham West Midlands B24 8QU",
    "addr:housenumber":"138",
    "addr:postcode":"b24 8qu",
    "addr:street":"Kingsbury Road",
    "iso:country":"GB",
    "sg:address":"138 Kingsbury Road, Erdington",
    "sg:city":"Birmingham",
    "sg:classifiers":[
        {
            "category":"Health Services",
            "subcategory":"Nursing And Care Facility",
            "type":"Services"
        }
    ],
    "sg:postcode":"B24 8QU",
    "sg:province":"West Midlands",
    "sg:tags":[
        "home",
        "residential"
    ],
    "wof:name":"LEANNE MARIE",
    "wof:placetype":"venue"
},
  "geometry": {"coordinates":[-1.8435419798,52.5157737732],"type":"Point"}
}