{
  "type": "Feature",
  "properties": {
    "iso:country":"GB",
    "sg:address":"Saltmakers House, Hamble Point Marina",
    "sg:city":"Southampton",
    "sg:classifiers":[
        {
            "category":"Autos & Motor Vehicles",
            "subcategory":"Boat Sales",
            "type":"Retail Goods"
        }
    ],
    "sg:phone":"+44 23 8045 5339",
    "sg:postcode":"SO31 4NB",
    "sg:province":"Hampshire",
    "sg:tags":[
        "yacht",
        "broker"
    ],
    "wof:name":"J Boats",
    "wof:placetype":"venue"
},
  "geometry": {"coordinates":[-1.328794,50.863125],"type":"Point"}
}