{
  "type": "Feature",
  "properties": {
    "addr:full":"5th Floor Maybrook Ho, 40 Blackfriars St Manchester Greater Manchester M3 2EG",
    "addr:housenumber":"5th floor;40",
    "addr:postcode":"m3 2eg",
    "addr:street":"Maybrook Ho;Blackfriars St",
    "iso:country":"GB",
    "sg:address":"5th Floor Maybrook Ho, 40 Blackfriars St",
    "sg:city":"Manchester",
    "sg:classifiers":[
        {
            "category":"Professional",
            "subcategory":"Lawyer & Legal Services",
            "type":"Services"
        }
    ],
    "sg:phone":"+44 161 831 7782",
    "sg:postcode":"M3 2EG",
    "sg:province":"Greater Manchester",
    "sg:tags":[
        "advice",
        "counselling"
    ],
    "wof:name":"Commission For Racial Equality",
    "wof:placetype":"venue"
},
  "geometry": {"coordinates":[-2.2488090992,53.4796218872],"type":"Point"}
}