{
  "type": "Feature",
  "properties": {
    "addr:full":"105 Bridge Road Lowestoft Suffolk NR32 3LN",
    "addr:housenumber":"105",
    "addr:postcode":"nr32 3ln",
    "addr:street":"Bridge Road",
    "iso:country":"GB",
    "sg:address":"105 Bridge Road",
    "sg:city":"Lowestoft",
    "sg:classifiers":[
        {
            "category":"Shopping",
            "subcategory":"Pharmacy",
            "type":"Retail Goods"
        }
    ],
    "sg:phone":"+44 1502 574721",
    "sg:postcode":"NR32 3LN",
    "sg:province":"Suffolk",
    "sg:tags":[
        "pharmacist",
        "chemist"
    ],
    "wof:name":"D G Hayden (Chemists)",
    "wof:placetype":"venue"
},
  "geometry": {"coordinates":[1.7136909962,52.4767189026],"type":"Point"}
}