{
  "type": "Feature",
  "properties": {
    "addr:full":"The Springs Oswestry Shropshire SY11 4EG",
    "addr:postcode":"sy11 4eg",
    "iso:country":"GB",
    "sg:address":"The Springs",
    "sg:city":"Oswestry",
    "sg:classifiers":[
        {
            "category":"Building & Trades",
            "subcategory":"Construction",
            "type":"Services"
        }
    ],
    "sg:phone":"+44 1691 610373",
    "sg:postcode":"SY11 4EG",
    "sg:province":"Shropshire",
    "sg:tags":[
        "excavation",
        "groundwork",
        "contractor"
    ],
    "wof:name":"Idris Owen",
    "wof:placetype":"venue"
},
  "geometry": {"coordinates":[-2.9687840939,52.8212585449],"type":"Point"}
}