{
  "type": "Feature",
  "properties": {
    "iso:country":"GB",
    "sg:address":"834 Bristol Road South, Northfield",
    "sg:city":"Birmingham",
    "sg:classifiers":[
        {
            "category":"Real Estate",
            "subcategory":"Real Estate Agent",
            "type":"Services"
        }
    ],
    "sg:postcode":"B31 2NS",
    "sg:province":"West Midlands",
    "wof:name":"Timms,Steve,",
    "wof:placetype":"venue"
},
  "geometry": {"coordinates":[-1.972089,52.413589],"type":"Point"}
}