{
  "type": "Feature",
  "properties": {
    "addr:full":"87 High Street Egham Surrey TW20 9HF",
    "addr:housenumber":"87",
    "addr:postcode":"tw20 9hf",
    "addr:street":"High Street",
    "iso:country":"GB",
    "sg:address":"87 High Street",
    "sg:city":"Egham",
    "sg:classifiers":[
        {
            "category":"Home & Garden",
            "subcategory":"Furniture",
            "type":"Retail Goods"
        }
    ],
    "sg:postcode":"TW20 9HF",
    "sg:province":"Surrey",
    "wof:name":"Reflexions",
    "wof:placetype":"venue"
},
  "geometry": {"coordinates":[-0.5447340012,51.4326400757],"type":"Point"}
}