{
  "type": "Feature",
  "properties": {
    "iso:country":"GB",
    "sg:address":"5 Grand Parade, High Street",
    "sg:city":"Poole",
    "sg:classifiers":[
        {
            "category":"Food & Beverages",
            "subcategory":"Bakery",
            "type":"Retail Goods"
        }
    ],
    "sg:postcode":"BH15 1AD",
    "sg:province":"Dorset",
    "sg:tags":[
        "pizza"
    ],
    "wof:name":"Michael Huney",
    "wof:placetype":"venue"
},
  "geometry": {"coordinates":[-1.988411,50.712444],"type":"Point"}
}