{
  "type": "Feature",
  "properties": {
    "iso:country":"GB",
    "sg:address":"342d Herringthorpe Valley Rd",
    "sg:city":"Rotherham",
    "sg:classifiers":[
        {
            "category":"Shopping",
            "subcategory":"News",
            "type":"Retail Goods"
        }
    ],
    "sg:phone":"+44 1709 377205",
    "sg:postcode":"S60 4LA",
    "sg:province":"South Yorkshire",
    "sg:tags":[
        "newsagent"
    ],
    "wof:name":"Spot Newsagents Ltd",
    "wof:placetype":"venue"
},
  "geometry": {"coordinates":[-1.321653,53.418056],"type":"Point"}
}