{
  "type": "Feature",
  "properties": {
    "addr:full":"23 Garth Road London Greater London NW2 2NH",
    "addr:housenumber":"23",
    "addr:postcode":"nw2 2nh",
    "addr:street":"Garth Road",
    "iso:country":"GB",
    "sg:address":"23 Garth Road",
    "sg:city":"London",
    "sg:classifiers":[
        {
            "category":"Utilities",
            "subcategory":"Refuse",
            "type":"Services"
        }
    ],
    "sg:phone":"+44 20 8458 7908",
    "sg:postcode":"NW2 2NH",
    "sg:province":"Greater London",
    "sg:tags":[
        "skip",
        "hire"
    ],
    "wof:name":"D O'Sullivan",
    "wof:placetype":"venue"
},
  "geometry": {"coordinates":[-0.2039020061,51.5641517639],"type":"Point"}
}