{
  "type": "Feature",
  "properties": {
    "iso:country":"GB",
    "sg:address":"117 Shepherds Bush Rd",
    "sg:city":"London",
    "sg:classifiers":[
        {
            "category":"Home & Garden",
            "subcategory":"Hardware",
            "type":"Retail Goods"
        }
    ],
    "sg:postcode":"W6 7LP",
    "sg:province":"Greater London",
    "sg:tags":[
        "retailer",
        "lighting"
    ],
    "wof:name":"Davighi,R,",
    "wof:placetype":"venue"
},
  "geometry": {"coordinates":[-0.222361,51.497646],"type":"Point"}
}