{
  "type": "Feature",
  "properties": {
    "addr:full":"64 Scotch Street Carlisle Cumbria CA3 8PN",
    "addr:housenumber":"64",
    "addr:postcode":"ca3 8pn",
    "addr:street":"Scotch Street",
    "iso:country":"GB",
    "sg:address":"64 Scotch Street",
    "sg:city":"Carlisle",
    "sg:classifiers":[
        {
            "category":"Shopping",
            "subcategory":"Bicycles & Sporting Goods",
            "type":"Retail Goods"
        },
        {
            "category":"Wholesale",
            "subcategory":"Sporting Goods",
            "type":"Manufacturing & Wholesale Goods"
        }
    ],
    "sg:phone":"+44 1228 539542",
    "sg:postcode":"CA3 8PN",
    "sg:province":"Cumbria",
    "sg:tags":[
        "supplier",
        "equipment",
        "camping"
    ],
    "wof:name":"FAMOUS ARMY STORES LTD",
    "wof:placetype":"venue"
},
  "geometry": {"coordinates":[-2.9357039928,54.8950195312],"type":"Point"}
}