{
  "type": "Feature",
  "properties": {
    "addr:full":"273 London Road Staines Berkshire TW18 4JJ",
    "addr:housenumber":"273",
    "addr:postcode":"tw18 4jj",
    "addr:street":"London Road",
    "iso:country":"GB",
    "sg:address":"273 London Road",
    "sg:city":"Staines",
    "sg:classifiers":[
        {
            "category":"Shopping",
            "subcategory":"Stationery & Office Supplies",
            "type":"Retail Goods"
        }
    ],
    "sg:phone":"+44 1784 465375",
    "sg:postcode":"TW18 4JJ",
    "sg:province":"Berkshire",
    "wof:name":"Classic Stationery Ltd.",
    "wof:placetype":"venue"
},
  "geometry": {"coordinates":[-0.493591,51.437988],"type":"Point"}
}