{
  "type": "Feature",
  "properties": {
    "addr:full":"40 Grainger Park Road Newcastle-upon-tyne Tyne and Wear NE4 8RY",
    "addr:housenumber":"40",
    "addr:postcode":"ne4 8ry",
    "addr:street":"Grainger Park Road",
    "iso:country":"GB",
    "sg:address":"40 Grainger Park Road",
    "sg:city":"Newcastle-upon-tyne",
    "sg:classifiers":[
        {
            "category":"Health Services",
            "subcategory":"Nursing And Care Facility",
            "type":"Services"
        },
        {
            "category":"Organizations",
            "subcategory":"Non-profit Organization",
            "type":"Services"
        }
    ],
    "sg:phone":"+44 191 273 4614",
    "sg:postcode":"NE4 8RY",
    "sg:province":"Tyne and Wear",
    "sg:tags":[
        "residential",
        "organisation",
        "voluntary",
        "charity"
    ],
    "wof:name":"MENTAL HEALTH MATTERS",
    "wof:placetype":"venue"
},
  "geometry": {"coordinates":[-1.647458,54.971661],"type":"Point"}
}