{
  "type": "Feature",
  "properties": {
    "addr:full":"Tec House, Pickering Drive Coalville Leicestershire LE67 1HB",
    "addr:postcode":"le67 1hb",
    "addr:street":"Pickering Drive",
    "iso:country":"GB",
    "sg:address":"Tec House, Pickering Drive",
    "sg:city":"Coalville",
    "sg:classifiers":[
        {
            "category":"Professional",
            "subcategory":"Detective & Security Services",
            "type":"Services"
        }
    ],
    "sg:phone":"+44 1530 264410",
    "sg:postcode":"LE67 1HB",
    "sg:province":"Leicestershire",
    "sg:tags":[
        "car"
    ],
    "wof:name":"Microtechnics",
    "wof:placetype":"venue"
},
  "geometry": {"coordinates":[-1.373329,52.699989],"type":"Point"}
}