{
  "type": "Feature",
  "properties": {
    "iso:country":"GB",
    "sg:address":"4 Carlisle St",
    "sg:city":"Leicester",
    "sg:classifiers":[
        {
            "category":"Shopping",
            "subcategory":"Shoes",
            "type":"Retail Goods"
        }
    ],
    "sg:phone":"+44 116 255 7007",
    "sg:postcode":"LE3 6AF",
    "sg:province":"Leicestershire",
    "wof:name":"Peters Shoes",
    "wof:placetype":"venue"
},
  "geometry": {"coordinates":[-1.159966,52.63327],"type":"Point"}
}