{
  "type": "Feature",
  "properties": {
    "iso:country":"GB",
    "sg:address":"1 Wolverhampton Road, Codsall",
    "sg:city":"Wolverhampton",
    "sg:classifiers":[
        {
            "category":"Banks & Credit Unions",
            "subcategory":"Financial Services",
            "type":"Services"
        }
    ],
    "sg:phone":"+44 1902 842083",
    "sg:postcode":"WV8 1QA",
    "sg:province":"Shropshire",
    "sg:tags":[
        "building",
        "society"
    ],
    "wof:name":"The Staffordshire",
    "wof:placetype":"venue"
},
  "geometry": {"coordinates":[-2.200784,52.630524],"type":"Point"}
}