{
  "type": "Feature",
  "properties": {
    "iso:country":"GB",
    "sg:address":"19a Heathcoat Street",
    "sg:city":"Nottingham",
    "sg:classifiers":[
        {
            "category":"Banks & Credit Unions",
            "subcategory":"Financial Services",
            "type":"Services"
        }
    ],
    "sg:phone":"+44 115 950 8411",
    "sg:postcode":"NG1 3AF",
    "sg:province":"Nottinghamshire",
    "sg:tags":[
        "consultant"
    ],
    "wof:name":"Key Homes",
    "wof:placetype":"venue"
},
  "geometry": {"coordinates":[-1.143393,52.954418],"type":"Point"}
}