{
  "type": "Feature",
  "properties": {
    "addr:full":"21 Bridle Road, Bromborough Wirral Cheshire CH62 6AP",
    "addr:housenumber":"21",
    "addr:postcode":"ch62 6ap",
    "addr:street":"Bridle Road",
    "iso:country":"GB",
    "sg:address":"21 Bridle Road, Bromborough",
    "sg:city":"Wirral",
    "sg:classifiers":[
        {
            "category":"Bus Charters",
            "type":"Transportation"
        }
    ],
    "sg:phone":"+44 151 327 8777",
    "sg:postcode":"CH62 6AP",
    "sg:province":"Cheshire",
    "sg:tags":[
        "coach"
    ],
    "wof:name":"Regency Travel",
    "wof:placetype":"venue"
},
  "geometry": {"coordinates":[-2.975209,53.323154],"type":"Point"}
}