{
  "type": "Feature",
  "properties": {
    "iso:country":"GB",
    "sg:address":"49 Old Palace Rd",
    "sg:city":"Norwich",
    "sg:classifiers":[
        {
            "category":"Retail",
            "subcategory":"Auto Repair",
            "type":"Services"
        }
    ],
    "sg:phone":"+44 1603 622394",
    "sg:postcode":"NR2 4JG",
    "sg:province":"Norfolk",
    "sg:tags":[
        "car",
        "upholsterer"
    ],
    "wof:name":"P W Cooke",
    "wof:placetype":"venue"
},
  "geometry": {"coordinates":[1.278243,52.635288],"type":"Point"}
}