{
  "type": "Feature",
  "properties": {
    "iso:country":"GB",
    "sg:address":"107 George Lane",
    "sg:city":"London",
    "sg:classifiers":[
        {
            "category":"Professional",
            "subcategory":"Management & Consulting",
            "type":"Services"
        }
    ],
    "sg:postcode":"E18 1AN",
    "sg:province":"Greater London",
    "sg:tags":[
        "consultant",
        "business"
    ],
    "wof:name":"Ragtown Consultants Limited",
    "wof:placetype":"venue"
},
  "geometry": {"coordinates":[0.026433,51.592766],"type":"Point"}
}