{
  "type": "Feature",
  "properties": {
    "iso:country":"GB",
    "sg:address":"5 Bainford Avenue",
    "sg:city":"Newcastle-upon-tyne",
    "sg:classifiers":[
        {
            "category":"Manufacturing",
            "subcategory":"Petroleum Products",
            "type":"Manufacturing & Wholesale Goods"
        }
    ],
    "sg:phone":"+44 191 274 1206",
    "sg:postcode":"NE15 7AN",
    "sg:province":"Northumberland",
    "sg:tags":[
        "double",
        "glazing"
    ],
    "wof:name":"L MORTON GLAZIERS",
    "wof:placetype":"venue"
},
  "geometry": {"coordinates":[-1.6852600574,54.9789466858],"type":"Point"}
}