{
  "type": "Feature",
  "properties": {
    "iso:country":"GB",
    "sg:address":"36a Erith Road",
    "sg:city":"Leicester",
    "sg:classifiers":[
        {
            "category":"Building & Trades",
            "subcategory":"Plumbing",
            "type":"Services"
        }
    ],
    "sg:phone":"+44 116 283 7426",
    "sg:postcode":"LE2 7QA",
    "sg:province":"Leicestershire",
    "sg:tags":[
        "plumber",
        "heating"
    ],
    "wof:name":"L V A Mechanical Services Ltd",
    "wof:placetype":"venue"
},
  "geometry": {"coordinates":[-1.1449199915,52.6139602661],"type":"Point"}
}