{
  "type": "Feature",
  "properties": {
    "addr:full":"105 Carterhatch Road Enfield Greater London EN3 5LU",
    "addr:housenumber":"105",
    "addr:postcode":"en3 5lu",
    "addr:street":"Carterhatch Road",
    "iso:country":"GB",
    "sg:address":"105 Carterhatch Road",
    "sg:city":"Enfield",
    "sg:classifiers":[
        {
            "category":"Building & Trades",
            "subcategory":"Landscaping Services",
            "type":"Services"
        }
    ],
    "sg:postcode":"EN3 5LU",
    "sg:province":"Greater London",
    "sg:tags":[
        "gardening"
    ],
    "wof:name":"A G S Landscapes",
    "wof:placetype":"venue"
},
  "geometry": {"coordinates":[-0.041936,51.659721],"type":"Point"}
}