{
  "type": "Feature",
  "properties": {
    "iso:country":"GB",
    "sg:address":"366 Leeds Road",
    "sg:city":"Dewsbury",
    "sg:classifiers":[
        {
            "category":"Bus Charters",
            "type":"Transportation"
        }
    ],
    "sg:postcode":"WF12 7QD",
    "sg:province":"West Yorkshire",
    "sg:tags":[
        "hire",
        "coach"
    ],
    "wof:name":"Trevor Lyle",
    "wof:placetype":"venue"
},
  "geometry": {"coordinates":[-1.61389,53.698814],"type":"Point"}
}