{
  "type": "Feature",
  "properties": {
    "iso:country":"GB",
    "sg:address":"135 Old Road, Overton",
    "sg:city":"Wakefield",
    "sg:classifiers":[
        {
            "category":"Building & Trades",
            "subcategory":"Plumbing",
            "type":"Services"
        }
    ],
    "sg:postcode":"WF4 4RB",
    "sg:province":"West Yorkshire",
    "sg:tags":[
        "heating"
    ],
    "wof:name":"Philip Wood Plumbing & Glazing",
    "wof:placetype":"venue"
},
  "geometry": {"coordinates":[-1.609771,53.646603],"type":"Point"}
}