{
  "type": "Feature",
  "properties": {
    "iso:country":"GB",
    "sg:address":"35-41 Queen Street",
    "sg:city":"Glasgow",
    "sg:classifiers":[
        {
            "category":"Bars & Pubs",
            "type":"Food & Drink"
        }
    ],
    "sg:phone":"+44 141 248 4455",
    "sg:postcode":"G1 3EF",
    "sg:province":"Glasgow City",
    "sg:tags":[
        "pubs",
        "inn"
    ],
    "wof:name":"BANK RESTAURANT",
    "wof:placetype":"venue"
},
  "geometry": {"coordinates":[-4.252613,55.858627],"type":"Point"}
}