{
  "type": "Feature",
  "properties": {
    "iso:country":"GB",
    "sg:address":"14 Wesley Street",
    "sg:city":"Southport",
    "sg:classifiers":[
        {
            "category":"Retail",
            "subcategory":"Repair Shop",
            "type":"Services"
        }
    ],
    "sg:phone":"+44 1704 540024",
    "sg:postcode":"PR8 1BN",
    "sg:province":"Lancashire",
    "sg:tags":[
        "clocks",
        "watch"
    ],
    "wof:name":"Andersons Jewellers",
    "wof:placetype":"venue"
},
  "geometry": {"coordinates":[-3.003805,53.645382],"type":"Point"}
}