{
  "type": "Feature",
  "properties": {
    "addr:full":"Yardley Wood Rd, Shirley Solihull West Midlands B90 1JU",
    "addr:postcode":"b90 1ju",
    "addr:street":"Yardley Wood Rd",
    "iso:country":"GB",
    "sg:address":"Yardley Wood Rd, Shirley",
    "sg:city":"Solihull",
    "sg:classifiers":[
        {
            "category":"Bars & Pubs",
            "type":"Food & Drink"
        }
    ],
    "sg:phone":"+44 121 430 2727",
    "sg:postcode":"B90 1JU",
    "sg:province":"West Midlands",
    "sg:tags":[
        "pubs",
        "inn"
    ],
    "wof:name":"Punch Retail Ltd",
    "wof:placetype":"venue"
},
  "geometry": {"coordinates":[-1.866014,52.409672],"type":"Point"}
}