{
  "type": "Feature",
  "properties": {
    "addr:full":"Cradle Bridge, Mortimer Street Trowbridge Wiltshire BA14 8BA",
    "addr:housenumber":"bridge",
    "addr:postcode":"ba14 8ba",
    "addr:street":"Cradle;Mortimer Street",
    "iso:country":"GB",
    "sg:address":"Cradle Bridge, Mortimer Street",
    "sg:city":"Trowbridge",
    "sg:classifiers":[
        {
            "category":"Education",
            "subcategory":"Library",
            "type":"Public Place"
        }
    ],
    "sg:phone":"+44 1225 761171",
    "sg:postcode":"BA14 8BA",
    "sg:province":"Wiltshire",
    "sg:tags":[
        "book"
    ],
    "wof:name":"Trowbridge Public Library",
    "wof:placetype":"venue"
},
  "geometry": {"coordinates":[-2.2083740234,51.3153419495],"type":"Point"}
}