{
  "type": "Feature",
  "properties": {
    "addr:full":"Sutton Lane, Lower Brailes Banbury Oxfordshire OX15 5BB",
    "addr:postcode":"ox15 5bb",
    "addr:street":"Sutton Lane",
    "iso:country":"GB",
    "sg:address":"Sutton Lane, Lower Brailes",
    "sg:city":"Banbury",
    "sg:classifiers":[
        {
            "category":"Sports & Exercise",
            "subcategory":"Golf",
            "type":"Entertainment"
        }
    ],
    "sg:phone":"+44 1608 685336",
    "sg:postcode":"OX15 5BB",
    "sg:province":"Oxfordshire",
    "sg:tags":[
        "club",
        "course"
    ],
    "wof:name":"Brailes Golf Club Ltd.",
    "wof:placetype":"venue"
},
  "geometry": {"coordinates":[-1.550216,52.048939],"type":"Point"}
}