{
  "type": "Feature",
  "properties": {
    "addr:full":"178-188 Great South West Road, Orbital Park Hounslow Greater London TW4 6JS",
    "addr:housenumber":"178-188",
    "addr:postcode":"tw4 6js",
    "addr:street":"Great South West Road Orbital Park",
    "iso:country":"GB",
    "sg:address":"178-188 Great South West Road, Orbital Park",
    "sg:city":"Hounslow",
    "sg:classifiers":[
        {
            "category":"Government",
            "subcategory":"Post Office",
            "type":"Public Place"
        }
    ],
    "sg:phone":"+44 20 8818 8000",
    "sg:postcode":"TW4 6JS",
    "sg:province":"Greater London",
    "sg:tags":[
        "messenger",
        "courier"
    ],
    "wof:name":"D H L International (U K) Ltd.",
    "wof:placetype":"venue"
},
  "geometry": {"coordinates":[-0.405594,51.471966],"type":"Point"}
}