{
  "type": "Feature",
  "properties": {
    "iso:country":"GB",
    "sg:address":"Longwood, Lee Road",
    "sg:city":"Princes Risborough",
    "sg:classifiers":[
        {
            "category":"Building & Trades",
            "subcategory":"Landscaping Services",
            "type":"Services"
        },
        {
            "category":"Social Services",
            "subcategory":"Retirement Home",
            "type":"Services"
        }
    ],
    "sg:phone":"+44 1844 343371",
    "sg:postcode":"HP27 9NU",
    "sg:province":"Buckinghamshire",
    "sg:tags":[
        "gardening",
        "care"
    ],
    "wof:name":"D L Hill & Co",
    "wof:placetype":"venue"
},
  "geometry": {"coordinates":[-0.8286939859,51.7318763733],"type":"Point"}
}