{
  "type": "Feature",
  "properties": {
    "addr:full":"46 Winstree Basildon Essex SS13 1PG",
    "addr:housenumber":"46",
    "addr:postcode":"ss13 1pg",
    "addr:street":"Winstree Basildon",
    "iso:country":"GB",
    "sg:address":"46 Winstree",
    "sg:city":"Basildon",
    "sg:classifiers":[
        {
            "category":"Bus Charters",
            "type":"Transportation"
        }
    ],
    "sg:phone":"+44 1268 473559",
    "sg:postcode":"SS13 1PG",
    "sg:province":"Essex",
    "sg:tags":[
        "hire",
        "coach"
    ],
    "wof:name":"Sterling Mini Coaches",
    "wof:placetype":"venue"
},
  "geometry": {"coordinates":[0.5033550262,51.5803871155],"type":"Point"}
}