{
  "type": "Feature",
  "properties": {
    "iso:country":"GB",
    "sg:address":"24 Fore Street",
    "sg:city":"Fowey",
    "sg:classifiers":[
        {
            "category":"Deli",
            "type":"Food & Drink"
        }
    ],
    "sg:phone":"+44 1726 832322",
    "sg:postcode":"PL23 1AQ",
    "sg:province":"Cornwall",
    "sg:tags":[
        "delicatessen"
    ],
    "wof:name":"Sams Delicateseen & Bakery",
    "wof:placetype":"venue"
},
  "geometry": {"coordinates":[-4.634122,50.335976],"type":"Point"}
}