{
  "type": "Feature",
  "properties": {
    "addr:full":"Stewarton Shop Campbeltown Argyll and Bute PA28 6PG",
    "addr:postcode":"pa28 6pg",
    "iso:country":"GB",
    "sg:address":"Stewarton Shop",
    "sg:city":"Campbeltown",
    "sg:classifiers":[
        {
            "category":"Building & Trades",
            "subcategory":"Landscaping Services",
            "type":"Services"
        },
        {
            "category":"Professional",
            "subcategory":"Employment Agencies",
            "type":"Services"
        }
    ],
    "sg:phone":"+44 1586 552385",
    "sg:postcode":"PA28 6PG",
    "sg:province":"Argyll and Bute",
    "sg:tags":[
        "agricultural",
        "advice"
    ],
    "wof:name":"Agricultural Services Co",
    "wof:placetype":"venue"
},
  "geometry": {"coordinates":[-5.608384,55.426605],"type":"Point"}
}