{
  "type": "Feature",
  "properties": {
    "addr:full":"1 Hurst Rd Horsham West Sussex RH12 2ES",
    "addr:housenumber":"1",
    "addr:postcode":"rh12 2es",
    "addr:street":"Hurst Rd",
    "iso:country":"GB",
    "sg:address":"1 Hurst Rd",
    "sg:city":"Horsham",
    "sg:classifiers":[
        {
            "category":"Shopping",
            "subcategory":"Photographic Equipment",
            "type":"Retail Goods"
        }
    ],
    "sg:phone":"+44 1403 274268",
    "sg:postcode":"RH12 2ES",
    "sg:province":"West Sussex",
    "wof:name":"Parkside Studios",
    "wof:placetype":"venue"
},
  "geometry": {"coordinates":[-0.3202959895,51.0662155151],"type":"Point"}
}