{
  "type": "Feature",
  "properties": {
    "iso:country":"GB",
    "sg:address":"20 Pauls Row",
    "sg:city":"High Wycombe",
    "sg:classifiers":[
        {
            "category":"Professional",
            "subcategory":"Employment Agencies",
            "type":"Services"
        }
    ],
    "sg:phone":"+44 1494 474000",
    "sg:postcode":"HP11 2HQ",
    "sg:province":"Buckinghamshire",
    "sg:tags":[
        "consultant",
        "recruitment"
    ],
    "wof:name":"Recruit",
    "wof:placetype":"venue"
},
  "geometry": {"coordinates":[-0.751548,51.628571],"type":"Point"}
}