{
  "type": "Feature",
  "properties": {
    "addr:full":"Piddington Gate Farm, Brill Aylesbury Buckinghamshire HP18 9XA",
    "addr:housenumber":"brill",
    "addr:postcode":"hp18 9xa",
    "addr:street":"Piddington Gate;Aylesbury",
    "iso:country":"GB",
    "sg:address":"Piddington Gate Farm, Brill",
    "sg:city":"Aylesbury",
    "sg:classifiers":[
        {
            "category":"Farming",
            "subcategory":"Crops",
            "type":"Manufacturing & Wholesale Goods"
        },
        {
            "category":"Farming",
            "subcategory":"Livestock Farm",
            "type":"Manufacturing & Wholesale Goods"
        }
    ],
    "sg:phone":"+44 1844 238259",
    "sg:postcode":"HP18 9XA",
    "sg:province":"Buckinghamshire",
    "sg:tags":[
        "arable",
        "others"
    ],
    "wof:name":"J & S Stockil & Sons",
    "wof:placetype":"venue"
},
  "geometry": {"coordinates":[-1.046061039,51.8546333313],"type":"Point"}
}