{
  "type": "Feature",
  "properties": {
    "addr:full":"110 Southfield Lane, Horbury Wakefield West Yorkshire WF4 5AP",
    "addr:housenumber":"110",
    "addr:postcode":"wf4 5ap",
    "addr:street":"Southfield Lane;West",
    "iso:country":"GB",
    "sg:address":"110 Southfield Lane, Horbury",
    "sg:city":"Wakefield",
    "sg:classifiers":[
        {
            "category":"Retail",
            "subcategory":"Driving School",
            "type":"Services"
        }
    ],
    "sg:phone":"+44 1924 277407",
    "sg:postcode":"WF4 5AP",
    "sg:province":"West Yorkshire",
    "wof:name":"Dave Hunt",
    "wof:placetype":"venue"
},
  "geometry": {"coordinates":[-1.549602,53.656879],"type":"Point"}
}