{
  "type": "Feature",
  "properties": {
    "addr:full":"47 Ridgemount Guildford Surrey GU2 7TH",
    "addr:housenumber":"47",
    "addr:postcode":"gu2 7th",
    "addr:street":"Ridgemount",
    "iso:country":"GB",
    "sg:address":"47 Ridgemount",
    "sg:city":"Guildford",
    "sg:classifiers":[
        {
            "category":"Real Estate",
            "subcategory":"Architect",
            "type":"Services"
        }
    ],
    "sg:phone":"+44 1483 505787",
    "sg:postcode":"GU2 7TH",
    "sg:province":"Surrey",
    "wof:name":"John Storry",
    "wof:placetype":"venue"
},
  "geometry": {"coordinates":[-0.588881,51.239697],"type":"Point"}
}