{
  "type": "Feature",
  "properties": {
    "iso:country":"GB",
    "sg:address":"48a Copthorne Road",
    "sg:city":"Shrewsbury",
    "sg:classifiers":[
        {
            "category":"Professional",
            "subcategory":"Management & Consulting",
            "type":"Services"
        }
    ],
    "sg:postcode":"SY3 8NL",
    "sg:province":"Shropshire",
    "sg:tags":[
        "consultant",
        "business"
    ],
    "wof:name":"Ichthus Ltd",
    "wof:placetype":"venue"
},
  "geometry": {"coordinates":[-2.766151,52.710674],"type":"Point"}
}