{
  "type": "Feature",
  "properties": {
    "iso:country":"GB",
    "sg:address":"58 Fore Street, Bovey Tracey",
    "sg:city":"Newton Abbot",
    "sg:classifiers":[
        {
            "category":"Personal",
            "subcategory":"Beauty Salon",
            "type":"Services"
        }
    ],
    "sg:postcode":"TQ13 9AE",
    "sg:province":"Devon",
    "sg:tags":[
        "unisex",
        "hairdresser"
    ],
    "wof:name":"New Image",
    "wof:placetype":"venue"
},
  "geometry": {"coordinates":[-3.674409,50.594254],"type":"Point"}
}