{
  "type": "Feature",
  "properties": {
    "iso:country":"GB",
    "sg:address":"Honicknowle Lane, Pennycross",
    "sg:city":"Plymouth",
    "sg:classifiers":[
        {
            "category":"Place Of Worship",
            "type":"Public Place"
        }
    ],
    "sg:postcode":"PL2 3QT",
    "sg:province":"Devon",
    "wof:name":"St. Pancras Church",
    "wof:placetype":"venue"
},
  "geometry": {"coordinates":[-4.150117,50.400501],"type":"Point"}
}