{
  "type": "Feature",
  "properties": {
    "addr:full":"77 Friar Street Droitwich Worcestershire WR9 8EQ",
    "addr:housenumber":"77",
    "addr:postcode":"wr9 8eq",
    "addr:street":"Friar Street",
    "iso:country":"GB",
    "sg:address":"77 Friar Street",
    "sg:city":"Droitwich",
    "sg:classifiers":[
        {
            "category":"Bars & Pubs",
            "type":"Food & Drink"
        }
    ],
    "sg:phone":"+44 1905 774233",
    "sg:postcode":"WR9 8EQ",
    "sg:province":"Worcestershire",
    "sg:tags":[
        "pubs",
        "inn"
    ],
    "wof:name":"The Old Cock Inn",
    "wof:placetype":"venue"
},
  "geometry": {"coordinates":[-2.1508150101,52.2692604065],"type":"Point"}
}