{
  "type": "Feature",
  "properties": {
    "addr:full":"14 Church Lane, Cookhill Alcester Warwickshire B49 5JS",
    "addr:housenumber":"14",
    "addr:postcode":"b49 5js",
    "addr:street":"Church Lane",
    "iso:country":"GB",
    "sg:address":"14 Church Lane, Cookhill",
    "sg:city":"Alcester",
    "sg:classifiers":[
        {
            "category":"Government",
            "subcategory":"Post Office",
            "type":"Public Place"
        }
    ],
    "sg:phone":"+44 1527 892432",
    "sg:postcode":"B49 5JS",
    "sg:province":"Warwickshire",
    "wof:name":"Cookhill Post Office",
    "wof:placetype":"venue"
},
  "geometry": {"coordinates":[-1.8686959743,52.2150993347],"type":"Point"}
}