{
  "type": "Feature",
  "properties": {
    "iso:country":"GB",
    "sg:address":"23 Carlowrie Place",
    "sg:city":"Gorebridge",
    "sg:classifiers":[
        {
            "category":"Building & Trades",
            "subcategory":"Construction",
            "type":"Services"
        }
    ],
    "sg:phone":"+44 1875 823022",
    "sg:postcode":"EH23 4XL",
    "sg:province":"Midlothian",
    "sg:tags":[
        "joiner",
        "carpenter"
    ],
    "wof:name":"A.T.K Contracts",
    "wof:placetype":"venue"
},
  "geometry": {"coordinates":[-3.047945,55.836441],"type":"Point"}
}