{
  "type": "Feature",
  "properties": {
    "addr:full":"Middlesex University Queensway Enfield Greater London EN3 4SA",
    "addr:postcode":"en3 4sa",
    "addr:street":"Queensway",
    "iso:country":"GB",
    "sg:address":"Middlesex University Queensway",
    "sg:city":"Enfield",
    "sg:classifiers":[
        {
            "category":"Organizations",
            "subcategory":"Non-profit Organization",
            "type":"Services"
        }
    ],
    "sg:phone":"+44 20 8362 5366",
    "sg:postcode":"EN3 4SA",
    "sg:province":"Greater London",
    "sg:tags":[
        "organisation",
        "voluntary",
        "charity"
    ],
    "wof:name":"The Able Centre",
    "wof:placetype":"venue"
},
  "geometry": {"coordinates":[-0.0504099987,51.6468811035],"type":"Point"}
}