{
  "type": "Feature",
  "properties": {
    "addr:full":"Anna House, 214 218 High Rd Seven Sisters Greater London N15 4NP",
    "addr:housenumber":"214 218",
    "addr:postcode":"n15 4np",
    "addr:street":"High Rd",
    "iso:country":"GB",
    "sg:address":"Anna House, 214 218 High Rd",
    "sg:city":"Seven Sisters",
    "sg:classifiers":[
        {
            "category":"Wholesale",
            "subcategory":"Music Publishers",
            "type":"Manufacturing & Wholesale Goods"
        }
    ],
    "sg:phone":"+44 20 8885 9360",
    "sg:postcode":"N15 4NP",
    "sg:province":"Greater London",
    "sg:tags":[
        "record"
    ],
    "wof:name":"Maxos & Marco Polo",
    "wof:placetype":"venue"
},
  "geometry": {"coordinates":[-0.07225,51.582481],"type":"Point"}
}