{
  "type": "Feature",
  "properties": {
    "iso:country":"GB",
    "sg:address":"47 Constance Road",
    "sg:city":"Leicester",
    "sg:classifiers":[
        {
            "category":"Shopping",
            "subcategory":"Clothing, Apparel, & Fashions",
            "type":"Retail Goods"
        }
    ],
    "sg:postcode":"LE5 5DE",
    "sg:province":"Leicestershire",
    "sg:tags":[
        "clothing",
        "fabric"
    ],
    "wof:name":"H P Clothing",
    "wof:placetype":"venue"
},
  "geometry": {"coordinates":[-1.100235,52.63242],"type":"Point"}
}