{
  "type": "Feature",
  "properties": {
    "addr:full":"2a Nith Avenue Dumfries Dumfries and Galloway DG1 1EF",
    "addr:housenumber":"2a",
    "addr:postcode":"dg1 1ef",
    "addr:street":"Nith Avenue",
    "iso:country":"GB",
    "sg:address":"2a Nith Avenue",
    "sg:city":"Dumfries",
    "sg:classifiers":[
        {
            "category":"Professional",
            "subcategory":"Art Services",
            "type":"Services"
        },
        {
            "category":"Military Area",
            "subcategory":"Air Force Base",
            "type":"Public Place"
        }
    ],
    "sg:phone":"+44 1387 247128",
    "sg:postcode":"DG1 1EF",
    "sg:province":"Dumfries and Galloway",
    "sg:tags":[
        "picture",
        "frame",
        "restoration",
        "cleaning"
    ],
    "wof:name":"OTTERSBURN GALLERY",
    "wof:placetype":"venue"
},
  "geometry": {"coordinates":[-3.6150810719,55.070980072],"type":"Point"}
}