{
  "type": "Feature",
  "properties": {
    "addr:full":"Wrexham Rd Wrexham Wrexham LL14 4DW",
    "addr:postcode":"ll14 4dw",
    "addr:street":"Wrexham Rd",
    "iso:country":"GB",
    "sg:address":"Wrexham Rd",
    "sg:city":"Wrexham",
    "sg:classifiers":[
        {
            "category":"Place Of Worship",
            "type":"Public Place"
        }
    ],
    "sg:phone":"+44 1978 354438",
    "sg:postcode":"LL14 4DW",
    "sg:province":"Wrexham",
    "wof:name":"Holy Trinity Church",
    "wof:placetype":"venue"
},
  "geometry": {"coordinates":[-3.0283439159,53.0278739929],"type":"Point"}
}