{
  "type": "Feature",
  "properties": {
    "addr:full":"Unit 8, Restormel Este Lostwithiel Cornwall PL22 0HD",
    "addr:housenumber":"unit 8",
    "addr:postcode":"pl22 0hd",
    "addr:street":"Restormel Este",
    "iso:country":"GB",
    "sg:address":"Unit 8, Restormel Este",
    "sg:city":"Lostwithiel",
    "sg:classifiers":[
        {
            "category":"Utilities",
            "subcategory":"Telephone",
            "type":"Services"
        }
    ],
    "sg:phone":"+44 1342 713966",
    "sg:postcode":"PL22 0HD",
    "sg:province":"Cornwall",
    "sg:tags":[
        "telecommunication"
    ],
    "wof:name":"Mitec Telecom Ltd.",
    "wof:placetype":"venue"
},
  "geometry": {"coordinates":[-4.669787,50.408875],"type":"Point"}
}