{
  "type": "Feature",
  "properties": {
    "addr:full":"Prosper House, P O Box 2273 Warminster Somerset BA12 7YL",
    "addr:housenumber":"2273",
    "addr:postcode":"ba12 7yl",
    "addr:street":"O Box",
    "iso:country":"GB",
    "sg:address":"Prosper House, P O Box 2273",
    "sg:city":"Warminster",
    "sg:classifiers":[
        {
            "category":"Conference Center",
            "type":"Public Place"
        }
    ],
    "sg:phone":"+44 1985 301130",
    "sg:postcode":"BA12 7YL",
    "sg:province":"Somerset",
    "wof:name":"Gibson Rawlins Ltd.",
    "wof:placetype":"venue"
},
  "geometry": {"coordinates":[-2.231691,51.193054],"type":"Point"}
}