{
  "type": "Feature",
  "properties": {
    "addr:full":"Portrodie Stranraer Dumfries and Galloway DG9 8EH",
    "addr:postcode":"dg9 8eh",
    "iso:country":"GB",
    "sg:address":"Portrodie",
    "sg:city":"Stranraer",
    "sg:classifiers":[
        {
            "category":"Travel",
            "subcategory":"Hotels & Motels",
            "type":"Entertainment"
        }
    ],
    "sg:phone":"+44 1776 704413",
    "sg:postcode":"DG9 8EH",
    "sg:province":"Dumfries and Galloway",
    "wof:name":"North West Castle Hotel",
    "wof:placetype":"venue"
},
  "geometry": {"coordinates":[-5.0164442062,54.9056358337],"type":"Point"}
}