{
  "type": "Feature",
  "properties": {
    "addr:full":"133 Tenby Dr Luton Bedfordshire LU4 9BN",
    "addr:housenumber":"133",
    "addr:postcode":"lu4 9bn",
    "addr:street":"Tenby Dr",
    "iso:country":"GB",
    "sg:address":"133 Tenby Dr",
    "sg:city":"Luton",
    "sg:classifiers":[
        {
            "category":"Professional",
            "subcategory":"Detective & Security Services",
            "type":"Services"
        }
    ],
    "sg:phone":"+44 1582 564880",
    "sg:postcode":"LU4 9BN",
    "sg:province":"Bedfordshire",
    "sg:tags":[
        "alarm",
        "burglar",
        "system"
    ],
    "wof:name":"A. Shakespeare Immobilisers",
    "wof:placetype":"venue"
},
  "geometry": {"coordinates":[-0.4533649981,51.8972854614],"type":"Point"}
}