{
  "type": "Feature",
  "properties": {
    "iso:country":"GB",
    "sg:address":"Unit 30 Rilend Industrial Cenrt",
    "sg:city":"Sutton Coldfield",
    "sg:classifiers":[
        {
            "category":"Shopping",
            "subcategory":"Stationery & Office Supplies",
            "type":"Retail Goods"
        }
    ],
    "sg:postcode":"B75 7BB",
    "sg:province":"Staffordshire",
    "sg:tags":[
        "item",
        "promotional"
    ],
    "wof:name":"Suggestions Ltd.",
    "wof:placetype":"venue"
},
  "geometry": {"coordinates":[-1.81601,52.56324],"type":"Point"}
}