{
  "type": "Feature",
  "properties": {
    "iso:country":"GB",
    "sg:address":"Pilot Road",
    "sg:city":"Corby",
    "sg:classifiers":[
        {
            "category":"Cafe",
            "type":"Food & Drink"
        }
    ],
    "sg:phone":"+44 1536 407177",
    "sg:postcode":"NN17 5YH",
    "sg:province":"Northamptonshire",
    "sg:tags":[
        "tea",
        "snack",
        "bar",
        "room"
    ],
    "wof:name":"Cliff McInnes",
    "wof:placetype":"venue"
},
  "geometry": {"coordinates":[-0.672759,52.497318],"type":"Point"}
}