{
  "type": "Feature",
  "properties": {
    "addr:full":"34 Mill Clo, Deddington Banbury Oxfordshire OX15 0UN",
    "addr:housenumber":"34",
    "addr:postcode":"ox15 0un",
    "addr:street":"Mill Clo",
    "iso:country":"GB",
    "sg:address":"34 Mill Clo, Deddington",
    "sg:city":"Banbury",
    "sg:classifiers":[
        {
            "category":"Building & Trades",
            "subcategory":"Construction",
            "type":"Services"
        }
    ],
    "sg:postcode":"OX15 0UN",
    "sg:province":"Oxfordshire",
    "sg:tags":[
        "glazier"
    ],
    "wof:name":"A A Glazing",
    "wof:placetype":"venue"
},
  "geometry": {"coordinates":[-1.3309060335,51.9808158875],"type":"Point"}
}