{
  "type": "Feature",
  "properties": {
    "iso:country":"GB",
    "sg:address":"Tanners Court, Tanners Lane, East Wellow",
    "sg:city":"Romsey",
    "sg:classifiers":[
        {
            "category":"Manufacturing",
            "subcategory":"Electronics",
            "type":"Manufacturing & Wholesale Goods"
        }
    ],
    "sg:postcode":"SO51 6DP",
    "sg:province":"Hampshire",
    "sg:tags":[
        "control",
        "component",
        "-",
        "electronic"
    ],
    "wof:name":"Rainbow Interconnect Ltd.",
    "wof:placetype":"venue"
},
  "geometry": {"coordinates":[-1.548051,50.997162],"type":"Point"}
}