{
  "type": "Feature",
  "properties": {
    "addr:full":"18 Netherhall Gardens London Greater London NW3 5TH",
    "addr:housenumber":"18",
    "addr:postcode":"nw3 5th",
    "addr:street":"Netherhall Gardens",
    "iso:country":"GB",
    "sg:address":"18 Netherhall Gardens",
    "sg:city":"London",
    "sg:classifiers":[
        {
            "category":"Education",
            "subcategory":"Special Training",
            "type":"Public Place"
        },
        {
            "category":"Organizations",
            "subcategory":"Membership Organization",
            "type":"Services"
        }
    ],
    "sg:phone":"+44 20 7794 1122",
    "sg:postcode":"NW3 5TH",
    "sg:province":"Greater London",
    "sg:tags":[
        "club",
        "school",
        "language",
        "social"
    ],
    "wof:name":"Netherhall International College Ltd",
    "wof:placetype":"venue"
},
  "geometry": {"coordinates":[-0.178946,51.549732],"type":"Point"}
}