{
  "type": "Feature",
  "properties": {
    "addr:full":"The Cottage, 139 London Road Derby Derbyshire DE72 2HA",
    "addr:housenumber":"139",
    "addr:postcode":"de72 2ha",
    "addr:street":"London Road",
    "iso:country":"GB",
    "sg:address":"The Cottage, 139 London Road",
    "sg:city":"Derby",
    "sg:classifiers":[
        {
            "category":"Professional",
            "subcategory":"Printing & Photocopies",
            "type":"Services"
        }
    ],
    "sg:postcode":"DE72 2HA",
    "sg:province":"Derbyshire",
    "sg:tags":[
        "t-shirt"
    ],
    "wof:name":"Design A Print",
    "wof:placetype":"venue"
},
  "geometry": {"coordinates":[-1.3454040289,52.8683586121],"type":"Point"}
}