{
  "type": "Feature",
  "properties": {
    "iso:country":"GB",
    "sg:address":"1a Meanwood Close",
    "sg:city":"Leeds",
    "sg:classifiers":[
        {
            "category":"Arts & Performance",
            "subcategory":"Art Gallery",
            "type":"Entertainment"
        }
    ],
    "sg:phone":"+44 113 262 0056",
    "sg:postcode":"LS7 2JL",
    "sg:province":"West Yorkshire",
    "wof:name":"Alcove Galleries",
    "wof:placetype":"venue"
},
  "geometry": {"coordinates":[-1.547582,53.817261],"type":"Point"}
}