{
  "type": "Feature",
  "properties": {
    "iso:country":"GB",
    "sg:address":"28 Winchester Road",
    "sg:city":"Romsey",
    "sg:classifiers":[
        {
            "category":"Professional",
            "subcategory":"Engineering",
            "type":"Services"
        }
    ],
    "sg:phone":"+44 1794 515120",
    "sg:postcode":"SO51 8AA",
    "sg:province":"Hampshire",
    "sg:tags":[
        "engineer",
        "structural"
    ],
    "wof:name":"Wedgewood Associates",
    "wof:placetype":"venue"
},
  "geometry": {"coordinates":[-1.4914549589,50.989730835],"type":"Point"}
}