{
  "type": "Feature",
  "properties": {
    "iso:country":"GB",
    "sg:address":"153 High Street",
    "sg:city":"London",
    "sg:classifiers":[
        {
            "category":"Fast Food",
            "type":"Food & Drink"
        }
    ],
    "sg:phone":"+44 20 8896 3776",
    "sg:postcode":"W3 6LP",
    "sg:province":"Greater London",
    "sg:tags":[
        "away",
        "take"
    ],
    "wof:name":"Tennessee Fried Chicken",
    "wof:placetype":"venue"
},
  "geometry": {"coordinates":[-0.2705500126,51.5069465637],"type":"Point"}
}