{
  "type": "Feature",
  "properties": {
    "addr:full":"32 Long Causeway Peterborough Cambridgeshire PE1 1YJ",
    "addr:housenumber":"32",
    "addr:postcode":"pe1 1yj",
    "addr:street":"Long Causeway",
    "iso:country":"GB",
    "sg:address":"32 Long Causeway",
    "sg:city":"Peterborough",
    "sg:classifiers":[
        {
            "category":"Professional",
            "subcategory":"Employment Agencies",
            "type":"Services"
        }
    ],
    "sg:phone":"+44 1733 560242",
    "sg:postcode":"PE1 1YJ",
    "sg:province":"Cambridgeshire",
    "sg:tags":[
        "consultant"
    ],
    "wof:name":"Stilton Staff (Executive Recruitment) Ltd.",
    "wof:placetype":"venue"
},
  "geometry": {"coordinates":[-0.2422170043,52.572593689],"type":"Point"}
}