{
  "type": "Feature",
  "properties": {
    "addr:full":"1 Mountbatten Court, Belmont Street Bognor Regis West Sussex PO21 1BJ",
    "addr:housenumber":"1",
    "addr:postcode":"po21 1bj",
    "addr:street":"Mountbatten Court Belmont Street",
    "iso:country":"GB",
    "sg:address":"1 Mountbatten Court, Belmont Street",
    "sg:city":"Bognor Regis",
    "sg:classifiers":[
        {
            "category":"Shopping",
            "subcategory":"Department Store",
            "type":"Retail Goods"
        },
        {
            "category":"Shopping",
            "subcategory":"Gifts & Souvenirs",
            "type":"Retail Goods"
        }
    ],
    "sg:postcode":"PO21 1BJ",
    "sg:province":"West Sussex",
    "sg:tags":[
        "shop"
    ],
    "wof:name":"Pic-A-Brac",
    "wof:placetype":"venue"
},
  "geometry": {"coordinates":[-0.675349,50.782967],"type":"Point"}
}