{
  "type": "Feature",
  "properties": {
    "iso:country":"GB",
    "sg:address":"Plymouth Road",
    "sg:city":"Tavistock",
    "sg:classifiers":[
        {
            "category":"Shopping",
            "subcategory":"News",
            "type":"Retail Goods"
        }
    ],
    "sg:phone":"+44 1822 610612",
    "sg:postcode":"PL19 8AY",
    "sg:province":"Devon",
    "sg:tags":[
        "newsagent"
    ],
    "wof:name":"Bus Station Kiosk",
    "wof:placetype":"venue"
},
  "geometry": {"coordinates":[-4.150161,50.546616],"type":"Point"}
}