{
  "type": "Feature",
  "properties": {
    "addr:full":"Fairbanks House, Bunkershill Skipton Lancashire BD23 1HU",
    "addr:postcode":"bd23 1hu",
    "addr:street":"Bunkershill",
    "iso:country":"GB",
    "sg:address":"Fairbanks House, Bunkershill",
    "sg:city":"Skipton",
    "sg:classifiers":[
        {
            "category":"Retail",
            "subcategory":"Funeral Services",
            "type":"Services"
        }
    ],
    "sg:phone":"+44 1756 792738",
    "sg:postcode":"BD23 1HU",
    "sg:province":"Lancashire",
    "sg:tags":[
        "director"
    ],
    "wof:name":"Brook Smith & Son",
    "wof:placetype":"venue"
},
  "geometry": {"coordinates":[-2.018514,53.960201],"type":"Point"}
}