{
  "type": "Feature",
  "properties": {
    "addr:full":"209 Lower Clapton Road London Greater London E5 8EG",
    "addr:housenumber":"209",
    "addr:postcode":"e5 8eg",
    "addr:street":"Lower Clapton Road",
    "iso:country":"GB",
    "sg:address":"209 Lower Clapton Road",
    "sg:city":"London",
    "sg:classifiers":[
        {
            "category":"Retail",
            "subcategory":"Funeral Services",
            "type":"Services"
        }
    ],
    "sg:phone":"+44 20 8985 5702",
    "sg:postcode":"E5 8EG",
    "sg:province":"Greater London",
    "sg:tags":[
        "director"
    ],
    "wof:name":"G R Moss",
    "wof:placetype":"venue"
},
  "geometry": {"coordinates":[-0.055956,51.556797],"type":"Point"}
}