{
  "type": "Feature",
  "properties": {
    "addr:full":"23 St Kildas Road London Greater London N16 5BS",
    "addr:housenumber":"23",
    "addr:postcode":"n16 5bs",
    "addr:street":"St Kildas Road",
    "iso:country":"GB",
    "sg:address":"23 St Kildas Road",
    "sg:city":"London",
    "sg:classifiers":[
        {
            "category":"Manufacturing",
            "subcategory":"Rubber & Plastics",
            "type":"Manufacturing & Wholesale Goods"
        }
    ],
    "sg:phone":"+44 20 8800 4422",
    "sg:postcode":"N16 5BS",
    "sg:province":"Greater London",
    "sg:tags":[
        "injection",
        "moulding"
    ],
    "wof:name":"Bentex Plastics",
    "wof:placetype":"venue"
},
  "geometry": {"coordinates":[-0.081314,51.567802],"type":"Point"}
}