{
  "type": "Feature",
  "properties": {
    "iso:country":"GB",
    "sg:address":"19 Brundage Rd",
    "sg:city":"Manchester",
    "sg:classifiers":[
        {
            "category":"Building & Trades",
            "subcategory":"Plumbing",
            "type":"Services"
        }
    ],
    "sg:phone":"+44 161 436 7542",
    "sg:postcode":"M22 0BY",
    "sg:province":"Greater Manchester",
    "sg:tags":[
        "central",
        "heating"
    ],
    "wof:name":"Alan Groom",
    "wof:placetype":"venue"
},
  "geometry": {"coordinates":[-2.2613370419,53.3760375977],"type":"Point"}
}