{
  "type": "Feature",
  "properties": {
    "addr:full":"Pool Farm, Crumpfields Lane Redditch Warwickshire B97 5PW",
    "addr:postcode":"b97 5pw",
    "addr:street":"Pool;Crumpfields Lane",
    "iso:country":"GB",
    "sg:address":"Pool Farm, Crumpfields Lane",
    "sg:city":"Redditch",
    "sg:classifiers":[
        {
            "category":"Farming",
            "subcategory":"Livestock Farm",
            "type":"Manufacturing & Wholesale Goods"
        },
        {
            "category":"Farming",
            "subcategory":"Farm",
            "type":"Manufacturing & Wholesale Goods"
        }
    ],
    "sg:phone":"+44 1527 541328",
    "sg:postcode":"B97 5PW",
    "sg:province":"Warwickshire",
    "sg:tags":[
        "mixed",
        "crop"
    ],
    "wof:name":"E T & M Kember",
    "wof:placetype":"venue"
},
  "geometry": {"coordinates":[-1.9728339911,52.2931594849],"type":"Point"}
}