{
  "type": "Feature",
  "properties": {
    "iso:country":"GB",
    "sg:address":"Highgate Common East, Swindon",
    "sg:city":"Dudley",
    "sg:classifiers":[
        {
            "category":"Farming",
            "subcategory":"Farm",
            "type":"Manufacturing & Wholesale Goods"
        }
    ],
    "sg:phone":"+44 1384 872572",
    "sg:postcode":"DY3 4QE",
    "sg:province":"Staffordshire",
    "sg:tags":[
        "mixed",
        "crop"
    ],
    "wof:name":"Christopher Stanley",
    "wof:placetype":"venue"
},
  "geometry": {"coordinates":[-2.202464,52.513821],"type":"Point"}
}