{
  "type": "Feature",
  "properties": {
    "iso:country":"GB",
    "sg:address":"20 The Willows",
    "sg:city":"Stevenage",
    "sg:classifiers":[
        {
            "category":"Building & Trades",
            "subcategory":"Construction",
            "type":"Services"
        }
    ],
    "sg:postcode":"SG2 8AW",
    "sg:province":"Hertfordshire",
    "sg:tags":[
        "roofing"
    ],
    "wof:name":"Heyman,William,",
    "wof:placetype":"venue"
},
  "geometry": {"coordinates":[-0.17945,51.882977],"type":"Point"}
}