{
  "type": "Feature",
  "properties": {
    "addr:full":"Oakwood Nursery Stirling Stirling FK8 3DP",
    "addr:postcode":"fk8 3dp",
    "addr:street":"Stirling",
    "iso:country":"GB",
    "sg:address":"Oakwood Nursery",
    "sg:city":"Stirling",
    "sg:classifiers":[
        {
            "category":"Building & Trades",
            "subcategory":"Landscaping Services",
            "type":"Services"
        }
    ],
    "sg:phone":"+44 1786 870906",
    "sg:postcode":"FK8 3DP",
    "sg:province":"Stirling",
    "sg:tags":[
        "landscape",
        "contractor"
    ],
    "wof:name":"Stephen Paul Associates",
    "wof:placetype":"venue"
},
  "geometry": {"coordinates":[-4.2605190277,56.1528587341],"type":"Point"}
}