{
  "type": "Feature",
  "properties": {
    "addr:full":"27 Adelaide Street Luton Bedfordshire LU1 5BB",
    "addr:housenumber":"27",
    "addr:postcode":"lu1 5bb",
    "addr:street":"Adelaide Street",
    "iso:country":"GB",
    "sg:address":"27 Adelaide Street",
    "sg:city":"Luton",
    "sg:classifiers":[
        {
            "category":"Professional",
            "subcategory":"Accounting & Tax Preparation",
            "type":"Services"
        }
    ],
    "sg:phone":"+44 1582 734731",
    "sg:postcode":"LU1 5BB",
    "sg:province":"Bedfordshire",
    "sg:tags":[
        "accountant"
    ],
    "wof:name":"Shah & Co Certified Accountants",
    "wof:placetype":"venue"
},
  "geometry": {"coordinates":[-0.420425,51.877556],"type":"Point"}
}