{
  "type": "Feature",
  "properties": {
    "addr:full":"Belgrave Rd Crewe Cheshire CW2 7NH",
    "addr:postcode":"cw2 7nh",
    "addr:street":"Belgrave Rd",
    "iso:country":"GB",
    "sg:address":"Belgrave Rd",
    "sg:city":"Crewe",
    "sg:classifiers":[
        {
            "category":"Education",
            "subcategory":"School",
            "type":"Public Place"
        }
    ],
    "sg:phone":"+44 1270 662328",
    "sg:postcode":"CW2 7NH",
    "sg:province":"Cheshire",
    "sg:tags":[
        "local",
        "authority"
    ],
    "wof:name":"Gainsborough County Junior School",
    "wof:placetype":"venue"
},
  "geometry": {"coordinates":[-2.453629,53.090851],"type":"Point"}
}