{
  "type": "Feature",
  "properties": {
    "iso:country":"GB",
    "sg:address":"56-58 Cove Rd, Cove",
    "sg:city":"Farnborough",
    "sg:classifiers":[
        {
            "category":"Building & Trades",
            "subcategory":"Construction",
            "type":"Services"
        }
    ],
    "sg:postcode":"GU14 0EN",
    "sg:province":"Hampshire",
    "sg:tags":[
        "glazier"
    ],
    "wof:name":"Sibbald,Duncan,",
    "wof:placetype":"venue"
},
  "geometry": {"coordinates":[-0.767313,51.292427],"type":"Point"}
}