{
  "type": "Feature",
  "properties": {
    "addr:full":"2 Greenfinch Close Crowthorne Berkshire RG45 6TZ",
    "addr:housenumber":"2",
    "addr:postcode":"rg45 6tz",
    "addr:street":"Greenfinch Close",
    "iso:country":"GB",
    "sg:address":"2 Greenfinch Close",
    "sg:city":"Crowthorne",
    "sg:classifiers":[
        {
            "category":"Communications",
            "type":"Services"
        }
    ],
    "sg:phone":"+44 1344 776744",
    "sg:postcode":"RG45 6TZ",
    "sg:province":"Berkshire",
    "sg:tags":[
        "telecommunication"
    ],
    "wof:name":"SBE Inc",
    "wof:placetype":"venue"
},
  "geometry": {"coordinates":[-0.808937,51.37711],"type":"Point"}
}