{
  "type": "Feature",
  "properties": {
    "addr:full":"6 Chester Street Edinburgh City of Edinburgh EH3 7RA",
    "addr:housenumber":"6",
    "addr:postcode":"eh3 7ra",
    "addr:street":"Chester Street",
    "iso:country":"GB",
    "sg:address":"6 Chester Street",
    "sg:city":"Edinburgh",
    "sg:classifiers":[
        {
            "category":"Banks & Credit Unions",
            "subcategory":"Financial Services",
            "type":"Services"
        }
    ],
    "sg:phone":"+44 131 225 2929",
    "sg:postcode":"EH3 7RA",
    "sg:province":"City of Edinburgh",
    "sg:tags":[
        "adviser"
    ],
    "wof:name":"Whyte Sharp Independent",
    "wof:placetype":"venue"
},
  "geometry": {"coordinates":[-3.215393,55.950104],"type":"Point"}
}