{
  "type": "Feature",
  "properties": {
    "iso:country":"GB",
    "sg:address":"14-16 Main Street",
    "sg:city":"Sedbergh",
    "sg:classifiers":[
        {
            "category":"Fast Food",
            "type":"Food & Drink"
        }
    ],
    "sg:phone":"+44 15396 21277",
    "sg:postcode":"LA10 5BN",
    "sg:province":"Cumbria",
    "sg:tags":[
        "away",
        "take"
    ],
    "wof:name":"Bazza's Pizza & Video",
    "wof:placetype":"venue"
},
  "geometry": {"coordinates":[-2.529489,54.32365],"type":"Point"}
}