{
  "type": "Feature",
  "properties": {
    "addr:full":"The Council House, Ventnor Rd Cwmbran Monmouthshire NP44 3JY",
    "addr:postcode":"np44 3jy",
    "addr:street":"Ventnor Rd",
    "iso:country":"GB",
    "sg:address":"The Council House, Ventnor Rd",
    "sg:city":"Cwmbran",
    "sg:classifiers":[
        {
            "category":"Organizations",
            "subcategory":"Non-profit Organization",
            "type":"Services"
        }
    ],
    "sg:phone":"+44 1633 868939",
    "sg:postcode":"NP44 3JY",
    "sg:province":"Monmouthshire",
    "sg:tags":[
        "organisation",
        "voluntary",
        "charity"
    ],
    "wof:name":"Gwent Association of Voluntary Organisations",
    "wof:placetype":"venue"
},
  "geometry": {"coordinates":[-3.021337,51.64706],"type":"Point"}
}