{
  "type": "Feature",
  "properties": {
    "addr:full":"4-6 Grimshaw Street Burnley Lancashire BB11 2AZ",
    "addr:housenumber":"4-6",
    "addr:postcode":"bb11 2az",
    "addr:street":"Grimshaw Street",
    "iso:country":"GB",
    "sg:address":"4-6 Grimshaw Street",
    "sg:city":"Burnley",
    "sg:classifiers":[
        {
            "category":"Professional",
            "subcategory":"Detective & Security Services",
            "type":"Services"
        }
    ],
    "sg:phone":"+44 161 886 9001",
    "sg:postcode":"BB11 2AZ",
    "sg:province":"Lancashire",
    "wof:name":"Priority Security Services Ltd.",
    "wof:placetype":"venue"
},
  "geometry": {"coordinates":[-2.242898941,53.787940979],"type":"Point"}
}