{
  "type": "Feature",
  "properties": {
    "addr:full":"66 Upper Wickham La Welling Kent DA16 3AB",
    "addr:housenumber":"66",
    "addr:postcode":"da16 3ab",
    "addr:street":"Upper Wickham La Welling",
    "iso:country":"GB",
    "sg:address":"66 Upper Wickham La",
    "sg:city":"Welling",
    "sg:classifiers":[
        {
            "category":"Manufacturing",
            "subcategory":"Furniture",
            "type":"Manufacturing & Wholesale Goods"
        }
    ],
    "sg:phone":"+44 1322 334185",
    "sg:postcode":"DA16 3AB",
    "sg:province":"Kent",
    "sg:tags":[
        "polishing",
        "french"
    ],
    "wof:name":"Furniture Care",
    "wof:placetype":"venue"
},
  "geometry": {"coordinates":[0.1091319993,51.4650230408],"type":"Point"}
}