{
  "type": "Feature",
  "properties": {
    "addr:full":"Hayscastle Cross Haverfordwest Pembrokeshire SA62 5PR",
    "addr:postcode":"sa62 5pr",
    "addr:street":"Hayscastle Cross",
    "iso:country":"GB",
    "sg:address":"Hayscastle Cross",
    "sg:city":"Haverfordwest",
    "sg:classifiers":[
        {
            "category":"Bars & Pubs",
            "type":"Food & Drink"
        }
    ],
    "sg:phone":"+44 1348 840216",
    "sg:postcode":"SA62 5PR",
    "sg:province":"Pembrokeshire",
    "sg:tags":[
        "pubs",
        "inn"
    ],
    "wof:name":"The Cross Inn",
    "wof:placetype":"venue"
},
  "geometry": {"coordinates":[-5.058315,51.889706],"type":"Point"}
}