{
  "type": "Feature",
  "properties": {
    "addr:full":"Bargrave St Stoke On Trent Staffordshire ST2 0HG",
    "addr:postcode":"st2 0hg",
    "addr:street":"Bargrave St",
    "iso:country":"GB",
    "sg:address":"Bargrave St",
    "sg:city":"Stoke On Trent",
    "sg:classifiers":[
        {
            "category":"Health Services",
            "subcategory":"Clinic",
            "type":"Services"
        }
    ],
    "sg:phone":"+44 1782 425900",
    "sg:postcode":"ST2 0HG",
    "sg:province":"Staffordshire",
    "sg:tags":[
        "nh"
    ],
    "wof:name":"Bentilee Health Centre",
    "wof:placetype":"venue"
},
  "geometry": {"coordinates":[-2.1265490055,53.0118789673],"type":"Point"}
}