{
  "type": "Feature",
  "properties": {
    "iso:country":"GB",
    "sg:address":"10 Queens Rd",
    "sg:city":"Aberdeen",
    "sg:classifiers":[
        {
            "category":"Government",
            "subcategory":"Office",
            "type":"Public Place"
        }
    ],
    "sg:phone":"+44 1224 626310",
    "sg:postcode":"AB15 4ZT",
    "sg:province":"Aberdeen City",
    "sg:tags":[
        "local"
    ],
    "wof:name":"Scottish Enterprise",
    "wof:placetype":"venue"
},
  "geometry": {"coordinates":[-2.130609,57.142464],"type":"Point"}
}