{
  "type": "Feature",
  "properties": {
    "iso:country":"GB",
    "sg:address":"17 Chichacott Rd",
    "sg:city":"Okehampton",
    "sg:classifiers":[
        {
            "category":"Wholesale",
            "subcategory":"Metals & Minerals",
            "type":"Manufacturing & Wholesale Goods"
        }
    ],
    "sg:phone":"+44 1837 54554",
    "sg:postcode":"EX20 1PA",
    "sg:province":"Devon",
    "sg:tags":[
        "merchant"
    ],
    "wof:name":"J R Smith",
    "wof:placetype":"venue"
},
  "geometry": {"coordinates":[-3.9902989864,50.7454948425],"type":"Point"}
}