{
  "type": "Feature",
  "properties": {
    "iso:country":"GB",
    "sg:address":"Mile End, Old Odiham Road",
    "sg:city":"Alton",
    "sg:classifiers":[
        {
            "category":"Professional",
            "subcategory":"Management & Consulting",
            "type":"Services"
        },
        {
            "category":"Real Estate",
            "subcategory":"Surveying",
            "type":"Services"
        }
    ],
    "sg:phone":"+44 7871 436833",
    "sg:postcode":"GU34 4BW",
    "sg:province":"Hampshire",
    "sg:tags":[
        "building",
        "surveyor",
        "business",
        "consultant"
    ],
    "wof:name":"A Consult",
    "wof:placetype":"venue"
},
  "geometry": {"coordinates":[-0.9809659719,51.1625862122],"type":"Point"}
}