{
  "type": "Feature",
  "properties": {
    "iso:country":"GB",
    "sg:address":"2 Downland Clo, Whetstone",
    "sg:city":"London",
    "sg:classifiers":[
        {
            "category":"Freight",
            "type":"Transportation"
        },
        {
            "category":"Retail",
            "subcategory":"Storage",
            "type":"Services"
        }
    ],
    "sg:phone":"+44 20 8343 9500",
    "sg:postcode":"N20 9LB",
    "sg:province":"Greater London",
    "sg:tags":[
        "household",
        "overseas",
        "shipping",
        "removal"
    ],
    "wof:name":"Art Overseas Ltd",
    "wof:placetype":"venue"
},
  "geometry": {"coordinates":[-0.1772779971,51.6334609985],"type":"Point"}
}