{
  "type": "Feature",
  "properties": {
    "iso:country":"GB",
    "sg:address":"Poor Park, Wethersfield",
    "sg:city":"Braintree",
    "sg:classifiers":[
        {
            "category":"Building & Trades",
            "subcategory":"Landscaping Services",
            "type":"Services"
        }
    ],
    "sg:phone":"+44 1371 850182",
    "sg:postcode":"CM7 4EQ",
    "sg:province":"Essex",
    "sg:tags":[
        "landscape",
        "contractor"
    ],
    "wof:name":"Amenity Landscapes Ltd.",
    "wof:placetype":"venue"
},
  "geometry": {"coordinates":[0.490235,51.953781],"type":"Point"}
}