{
  "type": "Feature",
  "properties": {
    "addr:full":"9 Woodstock Mead Basingstoke Hampshire RG22 4YW",
    "addr:housenumber":"9",
    "addr:postcode":"rg22 4yw",
    "addr:street":"Woodstock Mead",
    "iso:country":"GB",
    "sg:address":"9 Woodstock Mead",
    "sg:city":"Basingstoke",
    "sg:classifiers":[
        {
            "category":"Professional",
            "subcategory":"Management & Consulting",
            "type":"Services"
        }
    ],
    "sg:phone":"+44 1256 469000",
    "sg:postcode":"RG22 4YW",
    "sg:province":"Hampshire",
    "sg:tags":[
        "environmental",
        "consultant"
    ],
    "wof:name":"Safety Training & Consultancy Services",
    "wof:placetype":"venue"
},
  "geometry": {"coordinates":[-1.1323590279,51.233001709],"type":"Point"}
}