{
  "type": "Feature",
  "properties": {
    "iso:country":"GB",
    "sg:address":"Vanguard Wks, Blandford Heights Indstl Est",
    "sg:city":"Blandford Forum",
    "sg:classifiers":[
        {
            "category":"Professional",
            "subcategory":"Business Services",
            "type":"Services"
        }
    ],
    "sg:postcode":"DT11 7TE",
    "sg:province":"Dorset",
    "sg:tags":[
        "import",
        "export",
        "agent"
    ],
    "wof:name":"Cresta Alloway Ltd",
    "wof:placetype":"venue"
},
  "geometry": {"coordinates":[-2.159354,50.870708],"type":"Point"}
}