{
  "type": "Feature",
  "properties": {
    "addr:full":"250 Crownpoint Road Glasgow Glasgow City G40 2UJ",
    "addr:housenumber":"250",
    "addr:postcode":"g40 2uj",
    "addr:street":"Crownpoint Road",
    "iso:country":"GB",
    "sg:address":"250 Crownpoint Road",
    "sg:city":"Glasgow",
    "sg:classifiers":[
        {
            "category":"Building & Trades",
            "subcategory":"Locksmith",
            "type":"Services"
        }
    ],
    "sg:phone":"+44 141 556 6834",
    "sg:postcode":"G40 2UJ",
    "sg:province":"Glasgow City",
    "sg:tags":[
        "steeplejack"
    ],
    "wof:name":"Apex Steeplejacks Ltd.",
    "wof:placetype":"venue"
},
  "geometry": {"coordinates":[-4.215389,55.852779],"type":"Point"}
}