{
  "type": "Feature",
  "properties": {
    "iso:country":"GB",
    "sg:address":"7 Chamber House Drive",
    "sg:city":"Rochdale",
    "sg:classifiers":[
        {
            "category":"Professional",
            "subcategory":"Management & Consulting",
            "type":"Services"
        }
    ],
    "sg:postcode":"OL11 3LS",
    "sg:province":"Lancashire",
    "sg:tags":[
        "consultant",
        "training"
    ],
    "wof:name":"En Accord",
    "wof:placetype":"venue"
},
  "geometry": {"coordinates":[-2.189105,53.600079],"type":"Point"}
}