{
  "type": "Feature",
  "properties": {
    "addr:full":"7 King Street Chester Cheshire CH1 2AH",
    "addr:housenumber":"7",
    "addr:postcode":"ch1 2ah",
    "addr:street":"King Street",
    "iso:country":"GB",
    "sg:address":"7 King Street",
    "sg:city":"Chester",
    "sg:classifiers":[
        {
            "category":"Professional",
            "subcategory":"Printing & Photocopies",
            "type":"Services"
        }
    ],
    "sg:phone":"+44 1244 326730",
    "sg:postcode":"CH1 2AH",
    "sg:province":"Cheshire",
    "sg:tags":[
        "engraving",
        "engraver"
    ],
    "wof:name":"MIKE SHOBBROOK",
    "wof:placetype":"venue"
},
  "geometry": {"coordinates":[-2.8935248852,53.1929321289],"type":"Point"}
}