{
  "type": "Feature",
  "properties": {
    "addr:full":"Lyme Regis Road Banstead Surrey SM7 2EY",
    "addr:postcode":"sm7 2ey",
    "addr:street":"Lyme Regis Road",
    "iso:country":"GB",
    "sg:address":"Lyme Regis Road",
    "sg:city":"Banstead",
    "sg:classifiers":[
        {
            "category":"Social Services",
            "subcategory":"Adult Care",
            "type":"Services"
        },
        {
            "category":"Government",
            "subcategory":"Office",
            "type":"Public Place"
        }
    ],
    "sg:phone":"+44 1737 361556",
    "sg:postcode":"SM7 2EY",
    "sg:province":"Surrey",
    "sg:tags":[
        "housing",
        "local",
        "sheltered"
    ],
    "wof:name":"Lyme Regis Road Sheltered Housing",
    "wof:placetype":"venue"
},
  "geometry": {"coordinates":[-0.2076040059,51.3163909912],"type":"Point"}
}