{
  "type": "Feature",
  "properties": {
    "addr:full":"30 Walmley Road Sutton Coldfield Warwickshire B76 1QN",
    "addr:housenumber":"30",
    "addr:postcode":"b76 1qn",
    "addr:street":"Walmley Road",
    "iso:country":"GB",
    "sg:address":"30 Walmley Road",
    "sg:city":"Sutton Coldfield",
    "sg:classifiers":[
        {
            "category":"Professional",
            "subcategory":"Lawyer & Legal Services",
            "type":"Services"
        }
    ],
    "sg:phone":"+44 121 351 6296",
    "sg:postcode":"B76 1QN",
    "sg:province":"Warwickshire",
    "sg:tags":[
        "solicitor"
    ],
    "wof:name":"Keith Bright",
    "wof:placetype":"venue"
},
  "geometry": {"coordinates":[-1.8000429869,52.5410575867],"type":"Point"}
}