{
  "type": "Feature",
  "properties": {
    "iso:country":"GB",
    "sg:address":"Po Box 3",
    "sg:city":"Maryport",
    "sg:classifiers":[
        {
            "category":"Professional",
            "subcategory":"Lawyer & Legal Services",
            "type":"Services"
        }
    ],
    "sg:phone":"+44 1900 815880",
    "sg:postcode":"CA15 6SF",
    "sg:province":"Cumbria",
    "sg:tags":[
        "advice",
        "counselling"
    ],
    "wof:name":"Cumbria Christian Centre",
    "wof:placetype":"venue"
},
  "geometry": {"coordinates":[-3.4504830837,54.7413787842],"type":"Point"}
}