{
  "type": "Feature",
  "properties": {
    "addr:full":"West Malling Station, Station App West Malling Kent ME19 5AE",
    "addr:postcode":"me19 5ae",
    "iso:country":"GB",
    "sg:address":"West Malling Station, Station App",
    "sg:city":"West Malling",
    "sg:classifiers":[
        {
            "category":"Taxi",
            "type":"Transportation"
        },
        {
            "category":"Military Area",
            "subcategory":"Air Force Base",
            "type":"Public Place"
        }
    ],
    "sg:phone":"+44 1732 845535",
    "sg:postcode":"ME19 5AE",
    "sg:province":"Kent",
    "sg:tags":[
        "mini",
        "hire",
        "private",
        "cab"
    ],
    "wof:name":"Larkfield & Malling Taxis",
    "wof:placetype":"venue"
},
  "geometry": {"coordinates":[0.4129399955,51.2937088013],"type":"Point"}
}