{
  "type": "Feature",
  "properties": {
    "iso:country":"GB",
    "sg:address":"Mile Oak Business Park, Hints Rd, Mile Oak",
    "sg:city":"Tamworth",
    "sg:classifiers":[
        {
            "category":"Real Estate",
            "subcategory":"Developer",
            "type":"Services"
        }
    ],
    "sg:phone":"+44 1827 250600",
    "sg:postcode":"B78 3PQ",
    "sg:province":"Staffordshire",
    "sg:tags":[
        "property"
    ],
    "wof:name":"B.T.S International",
    "wof:placetype":"venue"
},
  "geometry": {"coordinates":[-1.768079,52.624615],"type":"Point"}
}