{
  "type": "Feature",
  "properties": {
    "iso:country":"GB",
    "sg:address":"Hostel, High St East",
    "sg:city":"Sunderland",
    "sg:classifiers":[
        {
            "category":"Organizations",
            "subcategory":"Non-profit Organization",
            "type":"Services"
        }
    ],
    "sg:phone":"+44 191 565 5411",
    "sg:postcode":"SR1 2AU",
    "sg:province":"Tyne and Wear",
    "sg:tags":[
        "organisation",
        "voluntary",
        "charity"
    ],
    "wof:name":"The Salvation Army",
    "wof:placetype":"venue"
},
  "geometry": {"coordinates":[-1.373949,54.908695],"type":"Point"}
}