{
  "type": "Feature",
  "properties": {
    "iso:country":"GB",
    "sg:address":"Warrington Road, Rainhill",
    "sg:city":"Prescot",
    "sg:classifiers":[
        {
            "category":"Place Of Worship",
            "type":"Public Place"
        }
    ],
    "sg:phone":"+44 151 426 4638",
    "sg:postcode":"L35 6NY",
    "sg:province":"Cheshire",
    "wof:name":"St.Bartholomews Roman Catholic Church",
    "wof:placetype":"venue"
},
  "geometry": {"coordinates":[-2.750623,53.40493],"type":"Point"}
}