{
  "type": "Feature",
  "properties": {
    "addr:full":"30 Trelawn Clo Weston Super Mare Somerset BS22 7XW",
    "addr:housenumber":"30;clo",
    "addr:postcode":"bs22 7xw",
    "addr:street":"Weston",
    "iso:country":"GB",
    "sg:address":"30 Trelawn Clo",
    "sg:city":"Weston Super Mare",
    "sg:classifiers":[
        {
            "category":"Building & Trades",
            "subcategory":"Construction",
            "type":"Services"
        }
    ],
    "sg:phone":"+44 1934 510545",
    "sg:postcode":"BS22 7XW",
    "sg:province":"Somerset",
    "sg:tags":[
        "builder"
    ],
    "wof:name":"R J Hart",
    "wof:placetype":"venue"
},
  "geometry": {"coordinates":[-2.8969409466,51.3616981506],"type":"Point"}
}