{
  "type": "Feature",
  "properties": {
    "addr:full":"4 Forest Rd, Walthamstow Walthamstow Greater London E17 6JJ",
    "addr:housenumber":"4",
    "addr:postcode":"e17 6jj",
    "addr:street":"Forest Rd",
    "iso:country":"GB",
    "sg:address":"4 Forest Rd, Walthamstow",
    "sg:city":"Walthamstow",
    "sg:classifiers":[
        {
            "category":"Retail",
            "subcategory":"Auto Repair",
            "type":"Services"
        }
    ],
    "sg:phone":"+44 20 8509 1591",
    "sg:postcode":"E17 6JJ",
    "sg:province":"Greater London",
    "sg:tags":[
        "modification",
        "garage"
    ],
    "wof:name":"Victory Service Station",
    "wof:placetype":"venue"
},
  "geometry": {"coordinates":[-0.0437289998,51.5867118835],"type":"Point"}
}