{
  "type": "Feature",
  "properties": {
    "addr:full":"47 Stamford Road Bournemouth Dorset BH6 5DS",
    "addr:housenumber":"47",
    "addr:postcode":"bh6 5ds",
    "addr:street":"Stamford Road",
    "iso:country":"GB",
    "sg:address":"47 Stamford Road",
    "sg:city":"Bournemouth",
    "sg:classifiers":[
        {
            "category":"Utilities",
            "type":"Services"
        }
    ],
    "sg:phone":"+44 7904 245606",
    "sg:postcode":"BH6 5DS",
    "sg:province":"Dorset",
    "sg:tags":[
        "internet"
    ],
    "wof:name":"Midas Interactive Ltd.",
    "wof:placetype":"venue"
},
  "geometry": {"coordinates":[-1.8082859516,50.7319755554],"type":"Point"}
}