{
  "type": "Feature",
  "properties": {
    "addr:full":"3 Downsland Parade Basingstoke Hampshire RG21 1TX",
    "addr:housenumber":"3",
    "addr:postcode":"rg21 1tx",
    "addr:street":"Downsland Parade",
    "iso:country":"GB",
    "sg:address":"3 Downsland Parade",
    "sg:city":"Basingstoke",
    "sg:classifiers":[
        {
            "category":"Fast Food",
            "type":"Food & Drink"
        }
    ],
    "sg:phone":"+44 1256 353035",
    "sg:postcode":"RG21 1TX",
    "sg:province":"Hampshire",
    "sg:tags":[
        "away",
        "take"
    ],
    "wof:name":"Sunny Take Away",
    "wof:placetype":"venue"
},
  "geometry": {"coordinates":[-1.098229,51.263084],"type":"Point"}
}