{
  "type": "Feature",
  "properties": {
    "iso:country":"GB",
    "sg:address":"School Office & Admissions, Leatherhead Road",
    "sg:city":"Leatherhead",
    "sg:classifiers":[
        {
            "category":"Education",
            "subcategory":"School",
            "type":"Public Place"
        }
    ],
    "sg:phone":"+44 1372 842509",
    "sg:postcode":"KT22 0JG",
    "sg:province":"Surrey",
    "sg:tags":[
        "independent",
        "preparatory"
    ],
    "wof:name":"Danes Hill School",
    "wof:placetype":"venue"
},
  "geometry": {"coordinates":[-0.3582499921,51.328868866],"type":"Point"}
}