{
  "type": "Feature",
  "properties": {
    "iso:country":"GB",
    "sg:address":"1 Waterhouse Farm, Station Road",
    "sg:city":"Thirsk",
    "sg:classifiers":[
        {
            "category":"Retail",
            "subcategory":"Auto Repair",
            "type":"Services"
        }
    ],
    "sg:phone":"+44 1845 587055",
    "sg:postcode":"YO7 3SG",
    "sg:province":"North Yorkshire",
    "sg:tags":[
        "modification",
        "garage"
    ],
    "wof:name":"Maddison 4 X 4",
    "wof:placetype":"venue"
},
  "geometry": {"coordinates":[-1.342253,54.232689],"type":"Point"}
}