{
  "type": "Feature",
  "properties": {
    "addr:full":"Studio 2 54a Fountainbridge, Tollcross Edinburgh City of Edinburgh EH3 9PY",
    "addr:housenumber":"54a",
    "addr:postcode":"eh3 9py",
    "addr:street":"Fountainbridge Tollcross",
    "iso:country":"GB",
    "sg:address":"Studio 2 54a Fountainbridge, Tollcross",
    "sg:city":"Edinburgh",
    "sg:classifiers":[
        {
            "category":"Sports & Exercise",
            "subcategory":"Gym",
            "type":"Entertainment"
        }
    ],
    "sg:postcode":"EH3 9PY",
    "sg:province":"City of Edinburgh",
    "sg:tags":[
        "fitness",
        "health",
        "centre"
    ],
    "wof:name":"Paula Bell",
    "wof:placetype":"venue"
},
  "geometry": {"coordinates":[-3.203404,55.943901],"type":"Point"}
}