{
  "type": "Feature",
  "properties": {
    "iso:country":"GB",
    "sg:address":"58 Wallgate",
    "sg:city":"Wigan",
    "sg:classifiers":[
        {
            "category":"Home & Garden",
            "subcategory":"Carpets & Floor Coverings",
            "type":"Retail Goods"
        }
    ],
    "sg:phone":"+44 1942 243634",
    "sg:postcode":"WN1 1BA",
    "sg:province":"Lancashire",
    "sg:tags":[
        "carpets",
        "rug",
        "matting"
    ],
    "wof:name":"D & S Carpet Showrooms",
    "wof:placetype":"venue"
},
  "geometry": {"coordinates":[-2.6334359646,53.5444831848],"type":"Point"}
}