{
  "type": "Feature",
  "properties": {
    "addr:full":"7 Bowring Park Road Liverpool Merseyside L14 3ND",
    "addr:housenumber":"7",
    "addr:postcode":"l14 3nd",
    "addr:street":"Bowring Park Road",
    "iso:country":"GB",
    "sg:address":"7 Bowring Park Road",
    "sg:city":"Liverpool",
    "sg:classifiers":[
        {
            "category":"Banks & Credit Unions",
            "subcategory":"Bank",
            "type":"Services"
        },
        {
            "category":"Banks & Credit Unions",
            "subcategory":"Financial Services",
            "type":"Services"
        }
    ],
    "sg:phone":"+44 151 252 0086",
    "sg:postcode":"L14 3ND",
    "sg:province":"Merseyside",
    "sg:tags":[
        "consultant",
        "broker",
        "mortgage"
    ],
    "wof:name":"LONDON SCOTTISH FINANCE LTD",
    "wof:placetype":"venue"
},
  "geometry": {"coordinates":[-2.9004430771,53.4069099426],"type":"Point"}
}