{
  "type": "Feature",
  "properties": {
    "addr:full":"The Coach Ho, Avondale, London Road East Bath Bath and North East Somerset BA1 7RB",
    "addr:postcode":"ba1 7rb",
    "addr:street":"London Road East",
    "iso:country":"GB",
    "sg:address":"The Coach Ho, Avondale, London Road East",
    "sg:city":"Bath",
    "sg:classifiers":[
        {
            "category":"Building & Trades",
            "subcategory":"Construction",
            "type":"Services"
        }
    ],
    "sg:phone":"+44 1225 859323",
    "sg:postcode":"BA1 7RB",
    "sg:province":"Bath and North East Somerset",
    "sg:tags":[
        "builder"
    ],
    "wof:name":"Spruce Homes",
    "wof:placetype":"venue"
},
  "geometry": {"coordinates":[-2.3126471043,51.4037857056],"type":"Point"}
}