{
  "type": "Feature",
  "properties": {
    "addr:full":"60a Trinity Rd Tooting Greater London SW17 7HR",
    "addr:housenumber":"60a",
    "addr:postcode":"sw17 7hr",
    "addr:street":"Trinity Rd",
    "iso:country":"GB",
    "sg:address":"60a Trinity Rd",
    "sg:city":"Tooting",
    "sg:classifiers":[
        {
            "category":"Building & Trades",
            "subcategory":"Construction",
            "type":"Services"
        }
    ],
    "sg:phone":"+44 20 7738 9989",
    "sg:postcode":"SW17 7HR",
    "sg:province":"Greater London",
    "sg:tags":[
        "glazier"
    ],
    "wof:name":"Mr Express",
    "wof:placetype":"venue"
},
  "geometry": {"coordinates":[-0.161373,51.436954],"type":"Point"}
}