{
  "type": "Feature",
  "properties": {
    "iso:country":"GB",
    "sg:address":"121 Grimshaw Lane",
    "sg:city":"Ormskirk",
    "sg:classifiers":[
        {
            "category":"Building & Trades",
            "subcategory":"Construction",
            "type":"Services"
        }
    ],
    "sg:phone":"+44 1695 570089",
    "sg:postcode":"L39 1PB",
    "sg:province":"Lancashire",
    "sg:tags":[
        "roofing"
    ],
    "wof:name":"B J Roofing",
    "wof:placetype":"venue"
},
  "geometry": {"coordinates":[-2.8881149292,53.5780906677],"type":"Point"}
}