{
  "type": "Feature",
  "properties": {
    "addr:full":"Unit 17 Trade Croft Industrial Estate, Wide Street Portland Dorset DT5 2JP",
    "addr:housenumber":"unit 17;estate",
    "addr:postcode":"dt5 2jp",
    "addr:street":"Trade Croft Industrial;Wide Street",
    "iso:country":"GB",
    "sg:address":"Unit 17 Trade Croft Industrial Estate, Wide Street",
    "sg:city":"Portland",
    "sg:classifiers":[
        {
            "category":"Retail",
            "subcategory":"Auto Rental",
            "type":"Services"
        }
    ],
    "sg:phone":"+44 1305 822488",
    "sg:postcode":"DT5 2JP",
    "sg:province":"Dorset",
    "sg:tags":[
        "car"
    ],
    "wof:name":"Avis Rent A Car Ltd.",
    "wof:placetype":"venue"
},
  "geometry": {"coordinates":[-2.445096,50.550285],"type":"Point"}
}