{
  "type": "Feature",
  "properties": {
    "iso:country":"GB",
    "sg:address":"29 Mow Cop Road",
    "sg:city":"Stoke-on-trent",
    "sg:classifiers":[
        {
            "category":"Shopping",
            "subcategory":"Department Store",
            "type":"Retail Goods"
        }
    ],
    "sg:phone":"+44 1782 513222",
    "sg:postcode":"ST7 4LZ",
    "sg:province":"Cheshire",
    "wof:name":"Castle Stores & News",
    "wof:placetype":"venue"
},
  "geometry": {"coordinates":[-2.2127621174,53.1113510132],"type":"Point"}
}