{
  "type": "Feature",
  "properties": {
    "addr:full":"254 St Clair Street Kirkcaldy Fife KY1 2DB",
    "addr:housenumber":"254",
    "addr:postcode":"ky1 2db",
    "addr:street":"St Clair Street",
    "iso:country":"GB",
    "sg:address":"254 St Clair Street",
    "sg:city":"Kirkcaldy",
    "sg:classifiers":[
        {
            "category":"Restaurant",
            "type":"Food & Drink"
        }
    ],
    "sg:phone":"+44 1592 654852",
    "sg:postcode":"KY1 2DB",
    "sg:province":"Fife",
    "wof:name":"Happy Days",
    "wof:placetype":"venue"
},
  "geometry": {"coordinates":[-3.137117,56.128746],"type":"Point"}
}