{
  "type": "Feature",
  "properties": {
    "iso:country":"GB",
    "sg:address":"3a Livingstone Place, Chepstow Road",
    "sg:city":"Newport",
    "sg:classifiers":[
        {
            "category":"Building & Trades",
            "subcategory":"Construction",
            "type":"Services"
        }
    ],
    "sg:phone":"+44 1633 221229",
    "sg:postcode":"NP19 8EY",
    "sg:province":"Newport",
    "sg:tags":[
        "demolition",
        "contractor"
    ],
    "wof:name":"A B Demolition (S W) Ltd.",
    "wof:placetype":"venue"
},
  "geometry": {"coordinates":[-2.9825251102,51.5900382996],"type":"Point"}
}