{
  "type": "Feature",
  "properties": {
    "addr:full":"45-51 Standishgate Wigan Lancashire WN1 1UP",
    "addr:housenumber":"45-51",
    "addr:postcode":"wn1 1up",
    "addr:street":"Standishgate Wigan",
    "iso:country":"GB",
    "sg:address":"45-51 Standishgate",
    "sg:city":"Wigan",
    "sg:classifiers":[
        {
            "category":"Shopping",
            "subcategory":"Clothing, Apparel, & Fashions",
            "type":"Retail Goods"
        }
    ],
    "sg:phone":"+44 1942 242885",
    "sg:postcode":"WN1 1UP",
    "sg:province":"Lancashire",
    "sg:tags":[
        "shop"
    ],
    "wof:name":"C & A",
    "wof:placetype":"venue"
},
  "geometry": {"coordinates":[-2.6300370693,53.5482635498],"type":"Point"}
}