{
  "type": "Feature",
  "properties": {
    "addr:full":"Premier Works, Canal Street Wigston Leicestershire LE18 4PN",
    "addr:postcode":"le18 4pn",
    "addr:street":"Canal Street",
    "iso:country":"GB",
    "sg:address":"Premier Works, Canal Street",
    "sg:city":"Wigston",
    "sg:classifiers":[
        {
            "category":"Manufacturing",
            "subcategory":"Electronics",
            "type":"Manufacturing & Wholesale Goods"
        },
        {
            "category":"Government",
            "subcategory":"Post Office",
            "type":"Public Place"
        }
    ],
    "sg:phone":"+44 116 278 5241",
    "sg:postcode":"LE18 4PN",
    "sg:province":"Leicestershire",
    "sg:tags":[
        "manufacture",
        "computer",
        "-",
        "printed",
        "circuit"
    ],
    "wof:name":"P W Circuits Ltd.",
    "wof:placetype":"venue"
},
  "geometry": {"coordinates":[-1.1142890453,52.5829811096],"type":"Point"}
}