{
  "type": "Feature",
  "properties": {
    "addr:full":"33 Back Goldspink Lane Newcastle-upon-tyne Tyne and Wear NE2 1NU",
    "addr:housenumber":"33",
    "addr:postcode":"ne2 1nu",
    "addr:street":"Back Goldspink Lane",
    "iso:country":"GB",
    "sg:address":"33 Back Goldspink Lane",
    "sg:city":"Newcastle-upon-tyne",
    "sg:classifiers":[
        {
            "category":"Retail",
            "subcategory":"Auto Repair",
            "type":"Services"
        }
    ],
    "sg:postcode":"NE2 1NU",
    "sg:province":"Tyne and Wear",
    "sg:tags":[
        "modification",
        "garage"
    ],
    "wof:name":"Malcolm Dickinson Motors",
    "wof:placetype":"venue"
},
  "geometry": {"coordinates":[-1.595805,54.983097],"type":"Point"}
}