{
  "type": "Feature",
  "properties": {
    "iso:country":"GB",
    "sg:address":"Unit 14 Sirhowy Industrial Estate, Thomas Ellis Way",
    "sg:city":"Tredegar",
    "sg:classifiers":[
        {
            "category":"Shopping",
            "subcategory":"Books",
            "type":"Retail Goods"
        }
    ],
    "sg:phone":"+44 1495 711900",
    "sg:postcode":"NP2 4QZ",
    "sg:province":"Blaenau Gwent",
    "sg:tags":[
        "sample",
        "pattern"
    ],
    "wof:name":"Swatch Gallery The",
    "wof:placetype":"venue"
},
  "geometry": {"coordinates":[-3.23717,51.783661],"type":"Point"}
}