{
  "type": "Feature",
  "properties": {
    "iso:country":"GB",
    "sg:address":"Deganwy, Pentre Road, St Clears",
    "sg:city":"Carmarthen",
    "sg:classifiers":[
        {
            "category":"Food & Beverages",
            "subcategory":"Meat & Fish",
            "type":"Retail Goods"
        }
    ],
    "sg:phone":"+44 1994 230226",
    "sg:postcode":"SA33 4LR",
    "sg:province":"Carmarthenshire",
    "sg:tags":[
        "butcher"
    ],
    "wof:name":"Eynon's of St Clears",
    "wof:placetype":"venue"
},
  "geometry": {"coordinates":[-4.49323,51.819981],"type":"Point"}
}