{
  "type": "Feature",
  "properties": {
    "iso:country":"GB",
    "sg:address":"23 Beckets Avenue, Aldwick",
    "sg:city":"Bognor Regis",
    "sg:classifiers":[
        {
            "category":"Home & Garden",
            "subcategory":"Household Appliances",
            "type":"Retail Goods"
        }
    ],
    "sg:phone":"+44 1243 264791",
    "sg:postcode":"PO21 4LX",
    "sg:province":"West Sussex",
    "sg:tags":[
        "electrical"
    ],
    "wof:name":"Geoff Dawes Refrigeration",
    "wof:placetype":"venue"
},
  "geometry": {"coordinates":[-0.7271919847,50.777759552],"type":"Point"}
}