{
  "type": "Feature",
  "properties": {
    "iso:country":"GB",
    "sg:address":"308 Oxford Road",
    "sg:city":"Reading",
    "sg:classifiers":[
        {
            "category":"Shopping",
            "subcategory":"Thrift Store",
            "type":"Retail Goods"
        }
    ],
    "sg:phone":"+44 118 939 3859",
    "sg:postcode":"RG30 1AD",
    "sg:province":"Berkshire",
    "sg:tags":[
        "shop",
        "charity"
    ],
    "wof:name":"Mind",
    "wof:placetype":"venue"
},
  "geometry": {"coordinates":[-0.994287014,51.4564704895],"type":"Point"}
}