{
  "type": "Feature",
  "properties": {
    "iso:country":"GB",
    "sg:address":"15-16 Bond Street",
    "sg:city":"Wolverhampton",
    "sg:classifiers":[
        {
            "category":"Professional",
            "subcategory":"Accounting & Tax Preparation",
            "type":"Services"
        }
    ],
    "sg:phone":"+44 1902 425175",
    "sg:postcode":"WV2 4AS",
    "sg:province":"West Midlands",
    "sg:tags":[
        "accountant"
    ],
    "wof:name":"Corke & Co",
    "wof:placetype":"venue"
},
  "geometry": {"coordinates":[-2.128249,52.581509],"type":"Point"}
}