{
  "type": "Feature",
  "properties": {
    "iso:country":"GB",
    "sg:address":"Old Town Hall",
    "sg:city":"Dunmow",
    "sg:classifiers":[
        {
            "category":"Real Estate",
            "subcategory":"Real Estate Agent",
            "type":"Services"
        }
    ],
    "sg:phone":"+44 1371 872117",
    "sg:postcode":"CM6 1AU",
    "sg:province":"Essex",
    "wof:name":"Trembath Welch",
    "wof:placetype":"venue"
},
  "geometry": {"coordinates":[0.364977,51.870613],"type":"Point"}
}