{
  "type": "Feature",
  "properties": {
    "iso:country":"GB",
    "sg:address":"Chateau Pleck, Darlaston Road",
    "sg:city":"Walsall",
    "sg:classifiers":[
        {
            "category":"Food & Beverages",
            "subcategory":"Liquor & Beverages",
            "type":"Retail Goods"
        }
    ],
    "sg:phone":"+44 1922 636161",
    "sg:postcode":"WS2 9SQ",
    "sg:province":"West Midlands",
    "sg:tags":[
        "beer",
        "spirit",
        "wines"
    ],
    "wof:name":"Whittalls Wines Ltd.",
    "wof:placetype":"venue"
},
  "geometry": {"coordinates":[-2.007349968,52.577091217],"type":"Point"}
}