{
  "type": "Feature",
  "properties": {
    "addr:full":"Manchester Road Buxton Derbyshire SK17 6TE",
    "addr:postcode":"sk17 6te",
    "addr:street":"Manchester Road",
    "iso:country":"GB",
    "sg:address":"Manchester Road",
    "sg:city":"Buxton",
    "sg:classifiers":[
        {
            "category":"Health Services",
            "subcategory":"Hospital",
            "type":"Services"
        }
    ],
    "sg:phone":"+44 1298 79236",
    "sg:postcode":"SK17 6TE",
    "sg:province":"Derbyshire",
    "wof:name":"Cavendish Hospital",
    "wof:placetype":"venue"
},
  "geometry": {"coordinates":[-1.931283,53.265141],"type":"Point"}
}