{
  "type": "Feature",
  "properties": {
    "iso:country":"GB",
    "sg:address":"Newsham Grange, Eaglescliffe",
    "sg:city":"Stockton-on-tees",
    "sg:classifiers":[
        {
            "category":"Farming",
            "subcategory":"Crops",
            "type":"Manufacturing & Wholesale Goods"
        },
        {
            "category":"Farming",
            "subcategory":"Livestock Farm",
            "type":"Manufacturing & Wholesale Goods"
        }
    ],
    "sg:phone":"+44 1325 332320",
    "sg:postcode":"TS16 0QS",
    "sg:province":"Durham",
    "sg:tags":[
        "arable",
        "others"
    ],
    "wof:name":"B G Dale",
    "wof:placetype":"venue"
},
  "geometry": {"coordinates":[-1.4113199711,54.4945907593],"type":"Point"}
}