{
  "type": "Feature",
  "properties": {
    "addr:full":"Unit 1-2, 122 Heston Road, Heston Hounslow Greater London TW5 0QU",
    "addr:housenumber":"unit 1-2",
    "addr:postcode":"122;tw5 0qu",
    "addr:street":"Heston Road",
    "iso:country":"GB",
    "sg:address":"Unit 1-2, 122 Heston Road, Heston",
    "sg:city":"Hounslow",
    "sg:classifiers":[
        {
            "category":"Home & Garden",
            "subcategory":"Hardware",
            "type":"Retail Goods"
        }
    ],
    "sg:phone":"+44 20 8570 5521",
    "sg:postcode":"TW5 0QU",
    "sg:province":"Greater London",
    "sg:tags":[
        "gear",
        "cutter"
    ],
    "wof:name":"The Gear Cutting Co. Ltd.",
    "wof:placetype":"venue"
},
  "geometry": {"coordinates":[-0.3649590015,51.4794654846],"type":"Point"}
}