{
  "type": "Feature",
  "properties": {
    "addr:full":"Beith Post Office Beith North Ayrshire KA15 1AQ",
    "addr:postcode":"ka15 1aq",
    "iso:country":"GB",
    "sg:address":"Beith Post Office",
    "sg:city":"Beith",
    "sg:classifiers":[
        {
            "category":"Government",
            "subcategory":"Post Office",
            "type":"Public Place"
        }
    ],
    "sg:phone":"+44 151 550 4966",
    "sg:postcode":"KA15 1AQ",
    "sg:province":"North Ayrshire",
    "wof:name":"Beith Sub Post Office",
    "wof:placetype":"venue"
},
  "geometry": {"coordinates":[-4.6378979683,55.7480659485],"type":"Point"}
}