{
  "type": "Feature",
  "properties": {
    "addr:full":"Unit 7 Bluebird House, Povey Cross Rd Horley Surrey RH6 0AG",
    "addr:housenumber":"unit 7 bluebird",
    "addr:postcode":"rh6 0ag",
    "addr:street":"House Povey Cross Rd",
    "iso:country":"GB",
    "sg:address":"Unit 7 Bluebird House, Povey Cross Rd",
    "sg:city":"Horley",
    "sg:classifiers":[
        {
            "category":"Personal",
            "type":"Services"
        }
    ],
    "sg:phone":"+44 1293 820415",
    "sg:postcode":"RH6 0AG",
    "sg:province":"Surrey",
    "sg:tags":[
        "delivery"
    ],
    "wof:name":"Securicor Pony Express",
    "wof:placetype":"venue"
},
  "geometry": {"coordinates":[-0.1789290011,51.1671905518],"type":"Point"}
}