{
  "type": "Feature",
  "properties": {
    "addr:full":"The Health Centre, Gas House La Morpeth Northumberland NE61 1SR",
    "addr:postcode":"ne61 1sr",
    "addr:street":"La;Northumberland",
    "iso:country":"GB",
    "sg:address":"The Health Centre, Gas House La",
    "sg:city":"Morpeth",
    "sg:classifiers":[
        {
            "category":"Health Services",
            "subcategory":"Doctor",
            "type":"Services"
        }
    ],
    "sg:phone":"+44 1670 513657",
    "sg:postcode":"NE61 1SR",
    "sg:province":"Northumberland",
    "sg:tags":[
        "practitioners"
    ],
    "wof:name":"O'Neill, J P J",
    "wof:placetype":"venue"
},
  "geometry": {"coordinates":[-1.688929,55.167397],"type":"Point"}
}