{
  "type": "Feature",
  "properties": {
    "addr:full":"147 Woburn Tower, Broomcroft Ave Northolt Greater London UB5 6HU",
    "addr:housenumber":"147",
    "addr:postcode":"ub5 6hu",
    "addr:street":"Woburn;Broomcroft Ave",
    "iso:country":"GB",
    "sg:address":"147 Woburn Tower, Broomcroft Ave",
    "sg:city":"Northolt",
    "sg:classifiers":[
        {
            "category":"Government",
            "subcategory":"Customs House",
            "type":"Public Place"
        }
    ],
    "sg:postcode":"UB5 6HU",
    "sg:province":"Greater London",
    "sg:tags":[
        "plant",
        "crushing"
    ],
    "wof:name":"Industrial Supplies International Ltd",
    "wof:placetype":"venue"
},
  "geometry": {"coordinates":[-0.37444,51.544106],"type":"Point"}
}