{
  "type": "Feature",
  "properties": {
    "iso:country":"GB",
    "sg:address":"370 Mare Street, Hackney",
    "sg:city":"London",
    "sg:classifiers":[
        {
            "category":"Shopping",
            "subcategory":"Books",
            "type":"Retail Goods"
        }
    ],
    "sg:phone":"+44 20 8985 8148",
    "sg:postcode":"E8 1HR",
    "sg:province":"Greater London",
    "sg:tags":[
        "bookseller",
        "retailer"
    ],
    "wof:name":"Roundabout Bookshop",
    "wof:placetype":"venue"
},
  "geometry": {"coordinates":[-0.054776,51.548092],"type":"Point"}
}