{
  "type": "Feature",
  "properties": {
    "addr:full":"104 Rolleston Rd Sheffield Derbyshire S12 4PF",
    "addr:housenumber":"104",
    "addr:postcode":"s12 4pf",
    "addr:street":"Rolleston Rd",
    "iso:country":"GB",
    "sg:address":"104 Rolleston Rd",
    "sg:city":"Sheffield",
    "sg:classifiers":[
        {
            "category":"Home & Garden",
            "subcategory":"Household Appliances",
            "type":"Retail Goods"
        }
    ],
    "sg:phone":"+44 114 239 9274",
    "sg:postcode":"S12 4PF",
    "sg:province":"Derbyshire",
    "sg:tags":[
        "domestic",
        "oven",
        "microwave"
    ],
    "wof:name":"M B Servicing",
    "wof:placetype":"venue"
},
  "geometry": {"coordinates":[-1.448258,53.422054],"type":"Point"}
}