{
  "type": "Feature",
  "properties": {
    "addr:full":"Unit 8-9, 96 White Post Lane London Greater London E9 5EN",
    "addr:housenumber":"unit;96",
    "addr:postcode":"e9 5en",
    "addr:street":"White Post Lane",
    "iso:country":"GB",
    "sg:address":"Unit 8-9, 96 White Post Lane",
    "sg:city":"London",
    "sg:classifiers":[
        {
            "category":"Professional",
            "subcategory":"Printing & Photocopies",
            "type":"Services"
        }
    ],
    "sg:phone":"+44 20 8986 4818",
    "sg:postcode":"E9 5EN",
    "sg:province":"Greater London",
    "sg:tags":[
        "printer"
    ],
    "wof:name":"Quadroprint Ltd",
    "wof:placetype":"venue"
},
  "geometry": {"coordinates":[-0.0221730005,51.5425834656],"type":"Point"}
}