{
  "type": "Feature",
  "properties": {
    "addr:full":"8 Falsgrave Road Scarborough North Yorkshire YO12 5AT",
    "addr:housenumber":"8",
    "addr:postcode":"yo12 5at",
    "addr:street":"Falsgrave Road",
    "iso:country":"GB",
    "sg:address":"8 Falsgrave Road",
    "sg:city":"Scarborough",
    "sg:classifiers":[
        {
            "category":"Professional",
            "subcategory":"Engineering",
            "type":"Services"
        }
    ],
    "sg:phone":"+44 1723 366548",
    "sg:postcode":"YO12 5AT",
    "sg:province":"North Yorkshire",
    "sg:tags":[
        "consulting",
        "design",
        "engineer"
    ],
    "sg:website":"http://www.alanwood.co.uk",
    "wof:name":"Alan Wood & Partners",
    "wof:placetype":"venue"
},
  "geometry": {"coordinates":[-0.4106410146,54.2777481079],"type":"Point"}
}