{
  "type": "Feature",
  "properties": {
    "addr:full":"Flat D9 Elizabeth Court, Grove Road Bournemouth Dorset BH1 3DT",
    "addr:housenumber":"flat d9",
    "addr:postcode":"bh1 3dt",
    "addr:street":"Elizabeth Court Grove Road",
    "iso:country":"GB",
    "sg:address":"Flat D9 Elizabeth Court, Grove Road",
    "sg:city":"Bournemouth",
    "sg:classifiers":[
        {
            "category":"Health Services",
            "subcategory":"Health Practitioner",
            "type":"Services"
        }
    ],
    "sg:phone":"+44 1202 296269",
    "sg:postcode":"BH1 3DT",
    "sg:province":"Dorset",
    "sg:tags":[
        "acupuncture"
    ],
    "wof:name":"Dr Pauline Heath-Ruminska",
    "wof:placetype":"venue"
},
  "geometry": {"coordinates":[-1.8669,50.718819],"type":"Point"}
}