{
  "type": "Feature",
  "properties": {
    "addr:full":"19 Queen Street Portsmouth Hampshire PO1 3HL",
    "addr:housenumber":"19",
    "addr:postcode":"hampshire po1 3hl",
    "addr:street":"Queen Street",
    "iso:country":"GB",
    "sg:address":"19 Queen Street",
    "sg:city":"Portsmouth",
    "sg:classifiers":[
        {
            "category":"Transit Center",
            "subcategory":"Passenger",
            "type":"Transportation"
        },
        {
            "category":"Autos & Motor Vehicles",
            "subcategory":"Motorcycle Sales",
            "type":"Retail Goods"
        },
        {
            "category":"Military Area",
            "subcategory":"Air Force Base",
            "type":"Public Place"
        }
    ],
    "sg:postcode":"PO1 3HL",
    "sg:province":"Hampshire",
    "sg:tags":[
        "taxi",
        "chauffeur",
        "hire",
        "car",
        "private",
        "driven",
        "airport"
    ],
    "wof:name":"N Slingsby & J Lovelock",
    "wof:placetype":"venue"
},
  "geometry": {"coordinates":[-1.099141,50.799679],"type":"Point"}
}