{
  "type": "Feature",
  "properties": {
    "addr:full":"22 Leighton Road, Southville Bristol City of Bristol BS3 1NT",
    "addr:housenumber":"22",
    "addr:postcode":"bs3 1nt",
    "addr:street":"Leighton Road",
    "iso:country":"GB",
    "sg:address":"22 Leighton Road, Southville",
    "sg:city":"Bristol",
    "sg:classifiers":[
        {
            "category":"Professional",
            "subcategory":"Art Services",
            "type":"Services"
        }
    ],
    "sg:phone":"+44 117 902 0207",
    "sg:postcode":"BS3 1NT",
    "sg:province":"City of Bristol",
    "sg:tags":[
        "graphic",
        "designer"
    ],
    "wof:name":"Drum",
    "wof:placetype":"venue"
},
  "geometry": {"coordinates":[-2.6082060337,51.4443054199],"type":"Point"}
}