{
  "type": "Feature",
  "properties": {
    "iso:country":"GB",
    "sg:address":"16 South Parade",
    "sg:city":"Doncaster",
    "sg:classifiers":[
        {
            "category":"Communications",
            "type":"Services"
        }
    ],
    "sg:phone":"+44 1302 343940",
    "sg:postcode":"DN1 2DR",
    "sg:province":"South Yorkshire",
    "sg:tags":[
        "audio-visual"
    ],
    "wof:name":"Fern Digital",
    "wof:placetype":"venue"
},
  "geometry": {"coordinates":[-1.127051,53.5215],"type":"Point"}
}