{
  "type": "Feature",
  "properties": {
    "addr:full":"102 Laneside Road, Haslingden Rossendale Lancashire BB4 6PG",
    "addr:housenumber":"102",
    "addr:postcode":"bb4 6pg",
    "addr:street":"Laneside Road",
    "iso:country":"GB",
    "sg:address":"102 Laneside Road, Haslingden",
    "sg:city":"Rossendale",
    "sg:classifiers":[
        {
            "category":"Shopping",
            "subcategory":"Stationery & Office Supplies",
            "type":"Retail Goods"
        },
        {
            "category":"Manufacturing",
            "subcategory":"Wood Products",
            "type":"Manufacturing & Wholesale Goods"
        }
    ],
    "sg:phone":"+44 1706 213197",
    "sg:postcode":"BB4 6PG",
    "sg:province":"Lancashire",
    "sg:tags":[
        "packaging",
        "equipment",
        "crate",
        "pallets"
    ],
    "wof:name":"Acre Packaging Supplies Ltd.",
    "wof:placetype":"venue"
},
  "geometry": {"coordinates":[-2.318175,53.699223],"type":"Point"}
}