{
  "type": "Feature",
  "properties": {
    "iso:country":"GB",
    "sg:address":"High Street, Goudhurst",
    "sg:city":"Cranbrook",
    "sg:classifiers":[
        {
            "category":"Personal",
            "subcategory":"Beauty Salon",
            "type":"Services"
        },
        {
            "category":"Personal",
            "subcategory":"Barber",
            "type":"Services"
        }
    ],
    "sg:phone":"+44 1580 211696",
    "sg:postcode":"TN17 1AL",
    "sg:province":"Kent",
    "sg:tags":[
        "unisex",
        "hairdresser"
    ],
    "wof:name":"Libra Hair",
    "wof:placetype":"venue"
},
  "geometry": {"coordinates":[0.459739,51.113346],"type":"Point"}
}