{
  "type": "Feature",
  "properties": {
    "addr:full":"20 Manor Way, Rutherglen Glasgow Glasgow City G73 4EP",
    "addr:housenumber":"20",
    "addr:postcode":"g73 4ep",
    "addr:street":"Manor Way",
    "iso:country":"GB",
    "sg:address":"20 Manor Way, Rutherglen",
    "sg:city":"Glasgow",
    "sg:classifiers":[
        {
            "category":"Professional",
            "subcategory":"Computer Services",
            "type":"Services"
        }
    ],
    "sg:phone":"+44 1236 726945",
    "sg:postcode":"G73 4EP",
    "sg:province":"Glasgow City",
    "sg:tags":[
        "system",
        "software"
    ],
    "wof:name":"Solico Ltd",
    "wof:placetype":"venue"
},
  "geometry": {"coordinates":[-4.2030639648,55.8104820251],"type":"Point"}
}