{
  "type": "Feature",
  "properties": {
    "iso:country":"GB",
    "sg:address":"Oakvale Funeral Home, 106 White House Loan",
    "sg:city":"Edinburgh",
    "sg:classifiers":[
        {
            "category":"Retail",
            "subcategory":"Funeral Services",
            "type":"Services"
        }
    ],
    "sg:postcode":"EH9 1BD",
    "sg:province":"City of Edinburgh",
    "wof:name":"William Purves (Funeral Directors) Ltd.",
    "wof:placetype":"venue"
},
  "geometry": {"coordinates":[-3.2015900612,55.9354400635],"type":"Point"}
}