{
  "type": "Feature",
  "properties": {
    "iso:country":"GB",
    "sg:address":"Arden House, 341 Kenilworth Road, Borsall Common",
    "sg:city":"Coventry",
    "sg:classifiers":[
        {
            "category":"Professional",
            "type":"Services"
        }
    ],
    "sg:phone":"+44 1676 535500",
    "sg:postcode":"CV7 7DL",
    "sg:province":"Warwickshire",
    "sg:tags":[
        "shopfitters"
    ],
    "wof:name":"Chadwick Shopfitting Ltd.",
    "wof:placetype":"venue"
},
  "geometry": {"coordinates":[-1.649692,52.391243],"type":"Point"}
}