{
  "type": "Feature",
  "properties": {
    "iso:country":"GB",
    "sg:address":"Unit 325-326, 30 Great Guildford St",
    "sg:city":"Southwark",
    "sg:classifiers":[
        {
            "category":"Professional",
            "subcategory":"Management & Consulting",
            "type":"Services"
        }
    ],
    "sg:phone":"+44 20 7207 9052",
    "sg:postcode":"SE1 0HS",
    "sg:province":"Greater London",
    "sg:tags":[
        "consultant",
        "energy",
        "conservation"
    ],
    "wof:name":"Tennants Energy Advice Service",
    "wof:placetype":"venue"
},
  "geometry": {"coordinates":[-0.09716,51.502823],"type":"Point"}
}