{
  "type": "Feature",
  "properties": {
    "iso:country":"GB",
    "sg:address":"3 Tulliebelton Place, Bankfoot",
    "sg:city":"Perth",
    "sg:classifiers":[
        {
            "category":"Building & Trades",
            "subcategory":"Construction",
            "type":"Services"
        }
    ],
    "sg:phone":"+44 1738 787203",
    "sg:postcode":"PH1 4BU",
    "sg:province":"Perth and Kinross",
    "sg:tags":[
        "dry",
        "lining",
        "plasterers",
        "screeders"
    ],
    "wof:name":"Stewart & Dick",
    "wof:placetype":"venue"
},
  "geometry": {"coordinates":[-3.522704,56.49894],"type":"Point"}
}