{
  "type": "Feature",
  "properties": {
    "iso:country":"GB",
    "sg:address":"Pendine Park",
    "sg:city":"Wrexham",
    "sg:classifiers":[
        {
            "category":"Social Services",
            "subcategory":"Adult Care",
            "type":"Services"
        },
        {
            "category":"Government",
            "subcategory":"Office",
            "type":"Public Place"
        }
    ],
    "sg:phone":"+44 1978 720030",
    "sg:postcode":"LL11 4XA",
    "sg:province":"Wrexham",
    "sg:tags":[
        "housing",
        "local",
        "sheltered"
    ],
    "wof:name":"Royal Court",
    "wof:placetype":"venue"
},
  "geometry": {"coordinates":[-3.022294,53.068024],"type":"Point"}
}