{
  "type": "Feature",
  "properties": {
    "addr:full":"80 Brook Street Carlisle Cumbria CA1 2HP",
    "addr:housenumber":"80",
    "addr:postcode":"ca1 2hp",
    "addr:street":"Brook Street",
    "iso:country":"GB",
    "sg:address":"80 Brook Street",
    "sg:city":"Carlisle",
    "sg:classifiers":[
        {
            "category":"Food & Beverages",
            "subcategory":"Candy",
            "type":"Retail Goods"
        }
    ],
    "sg:phone":"+44 1228 525656",
    "sg:postcode":"CA1 2HP",
    "sg:province":"Cumbria",
    "sg:tags":[
        "confectioner"
    ],
    "wof:name":"N ROUTLEDGE & SONS",
    "wof:placetype":"venue"
},
  "geometry": {"coordinates":[-2.92106,54.888866],"type":"Point"}
}