{
  "type": "Feature",
  "properties": {
    "addr:full":"37 Floral Street, Covent Garden London Greater London WC2E 9DJ",
    "addr:housenumber":"37",
    "addr:postcode":"wc2e 9dj",
    "addr:street":"Floral Street",
    "iso:country":"GB",
    "sg:address":"37 Floral Street, Covent Garden",
    "sg:city":"London",
    "sg:classifiers":[
        {
            "category":"Professional",
            "subcategory":"Art Services",
            "type":"Services"
        }
    ],
    "sg:phone":"+44 20 7240 4020",
    "sg:postcode":"WC2E 9DJ",
    "sg:province":"Greater London",
    "sg:tags":[
        "graphic",
        "designer"
    ],
    "wof:name":"Templar Downie Ltd.",
    "wof:placetype":"venue"
},
  "geometry": {"coordinates":[-0.124513,51.512463],"type":"Point"}
}