{
  "type": "Feature",
  "properties": {
    "iso:country":"GB",
    "sg:address":"Old Sgb Buildings, Llewellyns Quay",
    "sg:city":"Port Talbot",
    "sg:classifiers":[
        {
            "category":"Military Area",
            "subcategory":"Air Force Base",
            "type":"Public Place"
        }
    ],
    "sg:phone":"+44 1639 899131",
    "sg:postcode":"SA13 1RF",
    "sg:province":"Neath Port Talbot",
    "sg:tags":[
        "taxi",
        "hire",
        "private"
    ],
    "wof:name":"Town Taxis",
    "wof:placetype":"venue"
},
  "geometry": {"coordinates":[-3.78037,51.586472],"type":"Point"}
}