{
  "type": "Feature",
  "properties": {
    "addr:full":"Clifford House, New Road, Penn High Wycombe Buckinghamshire HP10 8DL",
    "addr:postcode":"hp10 8dl",
    "addr:street":"New Road",
    "iso:country":"GB",
    "sg:address":"Clifford House, New Road, Penn",
    "sg:city":"High Wycombe",
    "sg:classifiers":[
        {
            "category":"Professional",
            "subcategory":"Accounting & Tax Preparation",
            "type":"Services"
        }
    ],
    "sg:phone":"+44 1494 812069",
    "sg:postcode":"HP10 8DL",
    "sg:province":"Buckinghamshire",
    "sg:tags":[
        "accountant"
    ],
    "wof:name":"Simmonds & Co",
    "wof:placetype":"venue"
},
  "geometry": {"coordinates":[-0.6945090294,51.6392402649],"type":"Point"}
}