{
  "type": "Feature",
  "properties": {
    "addr:full":"Birch Green Skelmersdale Lancashire WN8 6RS",
    "addr:postcode":"wn8 6rs",
    "iso:country":"GB",
    "sg:address":"Birch Green",
    "sg:city":"Skelmersdale",
    "sg:classifiers":[
        {
            "category":"Health Services",
            "subcategory":"Nursing And Care Facility",
            "type":"Services"
        }
    ],
    "sg:phone":"+44 1695 50916",
    "sg:postcode":"WN8 6RS",
    "sg:province":"Lancashire",
    "sg:tags":[
        "home"
    ],
    "wof:name":"Ivydale Nursing Home",
    "wof:placetype":"venue"
},
  "geometry": {"coordinates":[-2.7661540508,53.5603790283],"type":"Point"}
}