{
  "type": "Feature",
  "properties": {
    "iso:country":"GB",
    "sg:address":"6 The Triangle",
    "sg:city":"Bournemouth",
    "sg:classifiers":[
        {
            "category":"Fast Food",
            "type":"Food & Drink"
        }
    ],
    "sg:phone":"+44 1202 553574",
    "sg:postcode":"BH2 5RY",
    "sg:province":"Dorset",
    "sg:tags":[
        "away",
        "take"
    ],
    "wof:name":"P Senariph",
    "wof:placetype":"venue"
},
  "geometry": {"coordinates":[-1.885452,50.720192],"type":"Point"}
}