{
  "type": "Feature",
  "properties": {
    "iso:country":"GB",
    "sg:address":"Spring Lane, Moorlinch",
    "sg:city":"Bridgwater",
    "sg:classifiers":[
        {
            "category":"Farming",
            "subcategory":"Vineyard",
            "type":"Manufacturing & Wholesale Goods"
        }
    ],
    "sg:postcode":"TA7 9DD",
    "sg:province":"Somerset",
    "wof:name":"Moorlynch Vineyard",
    "wof:placetype":"venue"
},
  "geometry": {"coordinates":[-2.85914,51.127769],"type":"Point"}
}