{
  "type": "Feature",
  "properties": {
    "iso:country":"GB",
    "sg:address":"44 Cliff Parade",
    "sg:city":"Hunstanton",
    "sg:classifiers":[
        {
            "category":"Travel",
            "subcategory":"Hotels & Motels",
            "type":"Entertainment"
        }
    ],
    "sg:phone":"+44 1485 533240",
    "sg:postcode":"PE36 6EH",
    "sg:province":"Norfolk",
    "sg:tags":[
        "house",
        "guest"
    ],
    "wof:name":"Green Shutters Guest House",
    "wof:placetype":"venue"
},
  "geometry": {"coordinates":[0.490502,52.94648],"type":"Point"}
}