{
  "type": "Feature",
  "properties": {
    "addr:full":"87 Turves Grn Birmingham West Midlands B31 4AH",
    "addr:housenumber":"87",
    "addr:postcode":"b31 4ah",
    "addr:street":"Turves Grn",
    "iso:country":"GB",
    "sg:address":"87 Turves Grn",
    "sg:city":"Birmingham",
    "sg:classifiers":[
        {
            "category":"Food & Beverages",
            "subcategory":"Meat & Fish",
            "type":"Retail Goods"
        }
    ],
    "sg:phone":"+44 121 477 5332",
    "sg:postcode":"B31 4AH",
    "sg:province":"West Midlands",
    "sg:tags":[
        "chip"
    ],
    "wof:name":"Moby Dick Fish & Chips",
    "wof:placetype":"venue"
},
  "geometry": {"coordinates":[-1.96727705,52.4027824402],"type":"Point"}
}