{
  "type": "Feature",
  "properties": {
    "addr:full":"79 High Street, Wargrave Reading Berkshire RG10 8BU",
    "addr:housenumber":"79",
    "addr:postcode":"rg10 8bu",
    "addr:street":"High Street",
    "iso:country":"GB",
    "sg:address":"79 High Street, Wargrave",
    "sg:city":"Reading",
    "sg:classifiers":[
        {
            "category":"Bars & Pubs",
            "type":"Food & Drink"
        }
    ],
    "sg:phone":"+44 118 940 2556",
    "sg:postcode":"RG10 8BU",
    "sg:province":"Berkshire",
    "sg:tags":[
        "pubs",
        "inn"
    ],
    "wof:name":"The Greyhound",
    "wof:placetype":"venue"
},
  "geometry": {"coordinates":[-0.869898,51.500736],"type":"Point"}
}