{
  "type": "Feature",
  "properties": {
    "iso:country":"GB",
    "sg:address":"60 Belwell Lane",
    "sg:city":"Sutton Coldfield",
    "sg:classifiers":[
        {
            "category":"Personal",
            "subcategory":"Beauty Salon",
            "type":"Services"
        }
    ],
    "sg:phone":"+44 121 323 2605",
    "sg:postcode":"B74 4TR",
    "sg:province":"Staffordshire",
    "sg:tags":[
        "unisex",
        "hairdresser"
    ],
    "wof:name":"L'ARCO",
    "wof:placetype":"venue"
},
  "geometry": {"coordinates":[-1.8390289545,52.586025238],"type":"Point"}
}