{
  "type": "Feature",
  "properties": {
    "iso:country":"GB",
    "sg:address":"64 Wilmere Lane",
    "sg:city":"Widnes",
    "sg:classifiers":[
        {
            "category":"Farming",
            "subcategory":"Nursery",
            "type":"Manufacturing & Wholesale Goods"
        }
    ],
    "sg:phone":"+44 151 495 2939",
    "sg:postcode":"WA8 5UR",
    "sg:province":"Cheshire",
    "sg:tags":[
        "creche"
    ],
    "wof:name":"Playmates Day Nursery",
    "wof:placetype":"venue"
},
  "geometry": {"coordinates":[-2.734607,53.393169],"type":"Point"}
}