{
  "type": "Feature",
  "properties": {
    "iso:country":"GB",
    "sg:address":"96 Bradford St",
    "sg:city":"Birmingham",
    "sg:classifiers":[
        {
            "category":"Organizations",
            "subcategory":"Religious Organization",
            "type":"Services"
        }
    ],
    "sg:phone":"+44 121 772 0522",
    "sg:postcode":"B12 0PB",
    "sg:province":"West Midlands",
    "sg:tags":[
        "organisation"
    ],
    "wof:name":"Catholic Student Council",
    "wof:placetype":"venue"
},
  "geometry": {"coordinates":[-1.8841320276,52.4725646973],"type":"Point"}
}