{
  "type": "Feature",
  "properties": {
    "addr:full":"45 South Molton St West End Hampshire W1Y 1HD",
    "addr:housenumber":"45",
    "addr:postcode":"w1y 1hd",
    "addr:street":"South Molton St",
    "iso:country":"GB",
    "sg:address":"45 South Molton St",
    "sg:city":"West End",
    "sg:classifiers":[
        {
            "category":"Professional",
            "subcategory":"Art Services",
            "type":"Services"
        }
    ],
    "sg:phone":"+44 20 7629 8499",
    "sg:postcode":"W1Y 1HD",
    "sg:province":"Hampshire",
    "sg:tags":[
        "photographer"
    ],
    "wof:name":"H Schierke Ltd",
    "wof:placetype":"venue"
},
  "geometry": {"coordinates":[-0.148261,51.514061],"type":"Point"}
}