{
  "type": "Feature",
  "properties": {
    "addr:full":"1 Logie Street Dundee Dundee City DD2 2QF",
    "addr:housenumber":"1",
    "addr:postcode":"dd2 2qf",
    "addr:street":"Logie Street",
    "iso:country":"GB",
    "sg:address":"1 Logie Street",
    "sg:city":"Dundee",
    "sg:classifiers":[
        {
            "category":"Health Services",
            "subcategory":"Nursing And Care Facility",
            "type":"Services"
        }
    ],
    "sg:postcode":"DD2 2QF",
    "sg:province":"Dundee City",
    "sg:tags":[
        "home"
    ],
    "wof:name":"St. Columbas Nursing Home",
    "wof:placetype":"venue"
},
  "geometry": {"coordinates":[-3.000845,56.468109],"type":"Point"}
}