{
  "type": "Feature",
  "properties": {
    "addr:full":"Manna Farm, Louth Road Louth Lincolnshire LN11 0UG",
    "addr:postcode":"ln11 0ug",
    "addr:street":"Louth Road Louth",
    "iso:country":"GB",
    "sg:address":"Manna Farm, Louth Road",
    "sg:city":"Louth",
    "sg:classifiers":[
        {
            "category":"Farming",
            "subcategory":"Livestock Farm",
            "type":"Manufacturing & Wholesale Goods"
        }
    ],
    "sg:phone":"+44 1507 450262",
    "sg:postcode":"LN11 0UG",
    "sg:province":"Lincolnshire",
    "sg:tags":[
        "others"
    ],
    "wof:name":"Manna Park Farms",
    "wof:placetype":"venue"
},
  "geometry": {"coordinates":[-0.007391,53.366497],"type":"Point"}
}