{
  "type": "Feature",
  "properties": {
    "addr:full":"30-32 Northmead Drive Poole Dorset BH17 7RP",
    "addr:housenumber":"30-32",
    "addr:postcode":"bh17 7rp",
    "addr:street":"Northmead Drive",
    "iso:country":"GB",
    "sg:address":"30-32 Northmead Drive",
    "sg:city":"Poole",
    "sg:classifiers":[
        {
            "category":"Recreation",
            "type":"Entertainment"
        }
    ],
    "sg:postcode":"BH17 7RP",
    "sg:province":"Dorset",
    "sg:tags":[
        "outdoor",
        "pursuit"
    ],
    "wof:name":"Youth Afloat Festival Office",
    "wof:placetype":"venue"
},
  "geometry": {"coordinates":[-2.005276,50.741955],"type":"Point"}
}