{
  "type": "Feature",
  "properties": {
    "iso:country":"GB",
    "sg:address":"Royd Ho, 224 Hale Rd",
    "sg:city":"Altrincham",
    "sg:classifiers":[
        {
            "category":"Health Services",
            "subcategory":"Doctor",
            "type":"Services"
        }
    ],
    "sg:phone":"+44 161 926 9858",
    "sg:postcode":"WA15 8EB",
    "sg:province":"Cheshire",
    "sg:tags":[
        "practitioners"
    ],
    "wof:name":"Pearson Dr D J",
    "wof:placetype":"venue"
},
  "geometry": {"coordinates":[-2.32612,53.376381],"type":"Point"}
}