{
  "type": "Feature",
  "properties": {
    "iso:country":"GB",
    "sg:address":"Sunwin House, 2-3 Railway Road",
    "sg:city":"Ilkley",
    "sg:classifiers":[
        {
            "category":"Travel",
            "subcategory":"Travel Agent",
            "type":"Entertainment"
        }
    ],
    "sg:phone":"+44 1943 816230",
    "sg:postcode":"LS29 8HA",
    "sg:province":"North Yorkshire",
    "wof:name":"Sunwin Travel",
    "wof:placetype":"venue"
},
  "geometry": {"coordinates":[-1.82274,53.92532],"type":"Point"}
}