{
  "type": "Feature",
  "properties": {
    "addr:full":"7 High Street Purley Surrey CR8 2AF",
    "addr:housenumber":"7",
    "addr:postcode":"cr8 2af",
    "addr:street":"High Street",
    "iso:country":"GB",
    "sg:address":"7 High Street",
    "sg:city":"Purley",
    "sg:classifiers":[
        {
            "category":"Shopping",
            "subcategory":"News",
            "type":"Retail Goods"
        }
    ],
    "sg:phone":"+44 20 8660 0526",
    "sg:postcode":"CR8 2AF",
    "sg:province":"Surrey",
    "sg:tags":[
        "newsagent"
    ],
    "wof:name":"Purley Bon Bon",
    "wof:placetype":"venue"
},
  "geometry": {"coordinates":[-0.1158220023,51.3379974365],"type":"Point"}
}