{
  "type": "Feature",
  "properties": {
    "addr:full":"137 High Street, Hanham Bristol City of Bristol BS15 3QY",
    "addr:housenumber":"137",
    "addr:postcode":"bs15 3qy",
    "addr:street":"High Street",
    "iso:country":"GB",
    "sg:address":"137 High Street, Hanham",
    "sg:city":"Bristol",
    "sg:classifiers":[
        {
            "category":"Autos & Motor Vehicles",
            "subcategory":"Auto Supplies",
            "type":"Retail Goods"
        }
    ],
    "sg:postcode":"BS15 3QY",
    "sg:province":"City of Bristol",
    "sg:tags":[
        "windscreen"
    ],
    "wof:name":"Avon Windscreens",
    "wof:placetype":"venue"
},
  "geometry": {"coordinates":[-2.5121629238,51.4478263855],"type":"Point"}
}