{
  "type": "Feature",
  "properties": {
    "addr:full":"Well Hall Road London Greater London SE9 6UB",
    "addr:postcode":"se9 6ub",
    "addr:street":"Hall Road",
    "iso:country":"GB",
    "sg:address":"Well Hall Road",
    "sg:city":"London",
    "sg:classifiers":[
        {
            "category":"Restaurant",
            "type":"Food & Drink"
        }
    ],
    "sg:phone":"+44 20 8319 0666",
    "sg:postcode":"SE9 6UB",
    "sg:province":"Greater London",
    "wof:name":"Welcome Inn",
    "wof:placetype":"venue"
},
  "geometry": {"coordinates":[0.0532200001,51.4676513672],"type":"Point"}
}