{
  "type": "Feature",
  "properties": {
    "addr:full":"Unit 22 The Galleries Wigan Lancashire WN1 1PX",
    "addr:housenumber":"unit 22 the galleries",
    "addr:postcode":"wn1 1px",
    "iso:country":"GB",
    "sg:address":"Unit 22 The Galleries",
    "sg:city":"Wigan",
    "sg:classifiers":[
        {
            "category":"Shopping",
            "subcategory":"Shoes",
            "type":"Retail Goods"
        }
    ],
    "sg:phone":"+44 1942 821997",
    "sg:postcode":"WN1 1PX",
    "sg:province":"Lancashire",
    "sg:tags":[
        "shop"
    ],
    "wof:name":"Jeffrey Tonks Shoes",
    "wof:placetype":"venue"
},
  "geometry": {"coordinates":[-2.6337490082,53.5466918945],"type":"Point"}
}