{
  "type": "Feature",
  "properties": {
    "iso:country":"GB",
    "sg:address":"Unit 6/7, Brocklebank Industrial Estate, Brocklebank Road",
    "sg:city":"London",
    "sg:classifiers":[
        {
            "category":"Manufacturing",
            "subcategory":"Petroleum Products",
            "type":"Manufacturing & Wholesale Goods"
        },
        {
            "category":"Building & Trades",
            "subcategory":"Construction",
            "type":"Services"
        }
    ],
    "sg:phone":"+44 20 8305 0022",
    "sg:postcode":"SE7 7SX",
    "sg:province":"Greater London",
    "sg:tags":[
        "double",
        "glazing",
        "installers"
    ],
    "wof:name":"Hallmark Glazing",
    "wof:placetype":"venue"
},
  "geometry": {"coordinates":[0.02243,51.49057],"type":"Point"}
}