{
  "type": "Feature",
  "properties": {
    "addr:full":"99 Slag Lane, Haydock St. Helens Lancashire WA11 0UY",
    "addr:housenumber":"99",
    "addr:postcode":"wa11 0uy",
    "addr:street":"Slag Lane Haydock",
    "iso:country":"GB",
    "sg:address":"99 Slag Lane, Haydock",
    "sg:city":"St. Helens",
    "sg:classifiers":[
        {
            "category":"Building & Trades",
            "subcategory":"Cleaning & Sanitation",
            "type":"Services"
        }
    ],
    "sg:phone":"+44 1744 739720",
    "sg:postcode":"WA11 0UY",
    "sg:province":"Lancashire",
    "sg:tags":[
        "commercial"
    ],
    "wof:name":"Drive Clean",
    "wof:placetype":"venue"
},
  "geometry": {"coordinates":[-2.6756880283,53.4709472656],"type":"Point"}
}