{
  "type": "Feature",
  "properties": {
    "iso:country":"GB",
    "sg:address":"123 High Street",
    "sg:city":"Sevenoaks",
    "sg:classifiers":[
        {
            "category":"Shopping",
            "subcategory":"Photographic Equipment",
            "type":"Retail Goods"
        }
    ],
    "sg:phone":"+44 1732 453335",
    "sg:postcode":"TN13 1UP",
    "sg:province":"Kent",
    "sg:tags":[
        "supply"
    ],
    "wof:name":"Fielders Photographic",
    "wof:placetype":"venue"
},
  "geometry": {"coordinates":[0.192568,51.271584],"type":"Point"}
}