{
  "type": "Feature",
  "properties": {
    "addr:full":"Grange Lane North Scunthorpe Lincolnshire DN16 1BZ",
    "addr:postcode":"dn16 1bz",
    "addr:street":"Grange Lane North",
    "iso:country":"GB",
    "sg:address":"Grange Lane North",
    "sg:city":"Scunthorpe",
    "sg:classifiers":[
        {
            "category":"Autos & Motor Vehicles",
            "subcategory":"Automobile Sales",
            "type":"Retail Goods"
        }
    ],
    "sg:postcode":"DN16 1BZ",
    "sg:province":"Lincolnshire",
    "sg:tags":[
        "car"
    ],
    "wof:name":"First Choice Cars",
    "wof:placetype":"venue"
},
  "geometry": {"coordinates":[-0.6283490062,53.57213974],"type":"Point"}
}