{
  "type": "Feature",
  "properties": {
    "addr:full":"Hermitage Farm, Harpswell Gainsborough Lincolnshire DN21 5UX",
    "addr:postcode":"dn21 5ux",
    "addr:street":"Hermitage",
    "iso:country":"GB",
    "sg:address":"Hermitage Farm, Harpswell",
    "sg:city":"Gainsborough",
    "sg:classifiers":[
        {
            "category":"Home & Garden",
            "subcategory":"Garden Supply",
            "type":"Retail Goods"
        }
    ],
    "sg:phone":"+44 1427 668363",
    "sg:postcode":"DN21 5UX",
    "sg:province":"Lincolnshire",
    "sg:tags":[
        "bulb",
        "grower"
    ],
    "wof:name":"P Marris",
    "wof:placetype":"venue"
},
  "geometry": {"coordinates":[-0.5944740176,53.397228241],"type":"Point"}
}