{
  "type": "Feature",
  "properties": {
    "addr:full":"13 Church St Manchester Greater Manchester M46 9DE",
    "addr:housenumber":"13",
    "addr:postcode":"m46 9de",
    "addr:street":"Church St",
    "iso:country":"GB",
    "sg:address":"13 Church St",
    "sg:city":"Manchester",
    "sg:classifiers":[
        {
            "category":"Professional",
            "subcategory":"Art Services",
            "type":"Services"
        }
    ],
    "sg:phone":"+44 1942 883208",
    "sg:postcode":"M46 9DE",
    "sg:province":"Greater Manchester",
    "sg:tags":[
        "photographer"
    ],
    "wof:name":"Dalton & Rimmer",
    "wof:placetype":"venue"
},
  "geometry": {"coordinates":[-2.4895188808,53.5240249634],"type":"Point"}
}