{
  "type": "Feature",
  "properties": {
    "iso:country":"GB",
    "sg:address":"The Motor Showrooms, Main Road",
    "sg:city":"Stanley",
    "sg:classifiers":[
        {
            "category":"Autos & Motor Vehicles",
            "subcategory":"Automobile Sales",
            "type":"Retail Goods"
        }
    ],
    "sg:phone":"+44 1207 280648",
    "sg:postcode":"DH9 0JR",
    "sg:province":"Durham",
    "sg:tags":[
        "car"
    ],
    "wof:name":"North East Premier Motors",
    "wof:placetype":"venue"
},
  "geometry": {"coordinates":[-1.690338,54.872379],"type":"Point"}
}