{
  "type": "Feature",
  "properties": {
    "iso:country":"GB",
    "sg:address":"43 Park Place",
    "sg:city":"Leeds",
    "sg:classifiers":[
        {
            "category":"Building & Trades",
            "subcategory":"Landscaping Services",
            "type":"Services"
        }
    ],
    "sg:phone":"+44 113 243 9080",
    "sg:postcode":"LS1 2RY",
    "sg:province":"West Yorkshire",
    "sg:tags":[
        "consultant"
    ],
    "wof:name":"James R Knowles Ltd.",
    "wof:placetype":"venue"
},
  "geometry": {"coordinates":[-1.550525,53.797283],"type":"Point"}
}