{
  "type": "Feature",
  "properties": {
    "iso:country":"GB",
    "sg:address":"45 Dunraven Street",
    "sg:city":"Tonypandy",
    "sg:classifiers":[
        {
            "category":"Banks & Credit Unions",
            "subcategory":"Bank",
            "type":"Services"
        }
    ],
    "sg:phone":"+44 845 765 4321",
    "sg:postcode":"CF40 1AL",
    "sg:province":"Rhondda, Cynon, Taff",
    "sg:tags":[
        "financial",
        "institution"
    ],
    "wof:name":"ABBEY NATIONAL PLC",
    "wof:placetype":"venue"
},
  "geometry": {"coordinates":[-3.453701973,51.6215362549],"type":"Point"}
}