{
  "type": "Feature",
  "properties": {
    "addr:full":"Unit 4b Rivulet Rd Wrexham Wrexham LL13 8DT",
    "addr:housenumber":"unit 4b",
    "addr:postcode":"ll13 8dt",
    "addr:street":"Rivulet Rd",
    "iso:country":"GB",
    "sg:address":"Unit 4b Rivulet Rd",
    "sg:city":"Wrexham",
    "sg:classifiers":[
        {
            "category":"Building & Trades",
            "subcategory":"Construction",
            "type":"Services"
        }
    ],
    "sg:phone":"+44 1352 700333",
    "sg:postcode":"LL13 8DT",
    "sg:province":"Wrexham",
    "sg:tags":[
        "equipment"
    ],
    "wof:name":"Wirral Hire Ltd",
    "wof:placetype":"venue"
},
  "geometry": {"coordinates":[-2.9849219322,53.0418739319],"type":"Point"}
}