{
  "type": "Feature",
  "properties": {
    "iso:country":"GB",
    "sg:address":"136 Norwich Drive, Upton",
    "sg:city":"Wirral",
    "sg:classifiers":[
        {
            "category":"Professional",
            "type":"Services"
        },
        {
            "category":"Fast Food",
            "type":"Food & Drink"
        }
    ],
    "sg:postcode":"CH49 4GD",
    "sg:province":"Merseyside",
    "sg:tags":[
        "away",
        "take",
        "caterer"
    ],
    "wof:name":"Buffets by Design",
    "wof:placetype":"venue"
},
  "geometry": {"coordinates":[-3.091093,53.395622],"type":"Point"}
}