{
  "type": "Feature",
  "properties": {
    "addr:full":"458 Bordesley Green Birmingham West Midlands B9 5NS",
    "addr:housenumber":"458",
    "addr:postcode":"b9 5ns",
    "addr:street":"Bordesley Green",
    "iso:country":"GB",
    "sg:address":"458 Bordesley Green",
    "sg:city":"Birmingham",
    "sg:classifiers":[
        {
            "category":"Professional",
            "subcategory":"Business Services",
            "type":"Services"
        }
    ],
    "sg:phone":"+44 121 687 7808",
    "sg:postcode":"B9 5NS",
    "sg:province":"West Midlands",
    "sg:tags":[
        "import",
        "export",
        "agent"
    ],
    "wof:name":"Concept Communications Services",
    "wof:placetype":"venue"
},
  "geometry": {"coordinates":[-1.843831,52.478409],"type":"Point"}
}