{
  "type": "Feature",
  "properties": {
    "addr:full":"26 Fauconberg Road London Greater London W4 3JY",
    "addr:housenumber":"26",
    "addr:postcode":"w4 3jy",
    "addr:street":"Fauconberg Road",
    "iso:country":"GB",
    "sg:address":"26 Fauconberg Road",
    "sg:city":"London",
    "sg:classifiers":[
        {
            "category":"Professional",
            "subcategory":"Business Services",
            "type":"Services"
        },
        {
            "category":"Casinos & Gambling",
            "type":"Entertainment"
        }
    ],
    "sg:phone":"+44 20 8995 1804",
    "sg:postcode":"W4 3JY",
    "sg:province":"Greater London",
    "sg:tags":[
        "turf",
        "accountant",
        "bookmaker"
    ],
    "wof:name":"Fleming & Smith Ltd",
    "wof:placetype":"venue"
},
  "geometry": {"coordinates":[-0.271198988,51.4862747192],"type":"Point"}
}