{
  "type": "Feature",
  "properties": {
    "iso:country":"GB",
    "sg:address":"11 Wych Elm",
    "sg:city":"Harlow",
    "sg:classifiers":[
        {
            "category":"Retail",
            "subcategory":"Veterinary Services",
            "type":"Services"
        }
    ],
    "sg:phone":"+44 1279 422066",
    "sg:postcode":"CM20 1QR",
    "sg:province":"Essex",
    "sg:tags":[
        "surgeon",
        "activity"
    ],
    "wof:name":"J A C Kew & Partners",
    "wof:placetype":"venue"
},
  "geometry": {"coordinates":[0.089753,51.772186],"type":"Point"}
}