{
  "type": "Feature",
  "properties": {
    "addr:full":"22 New Road Ascot Berkshire SL5 8QQ",
    "addr:housenumber":"22",
    "addr:postcode":"sl5 8qq",
    "addr:street":"New Road",
    "iso:country":"GB",
    "sg:address":"22 New Road",
    "sg:city":"Ascot",
    "sg:classifiers":[
        {
            "category":"Government",
            "subcategory":"Post Office",
            "type":"Public Place"
        }
    ],
    "sg:postcode":"SL5 8QQ",
    "sg:province":"Berkshire",
    "wof:name":"Brookside Sub Post Office",
    "wof:placetype":"venue"
},
  "geometry": {"coordinates":[-0.679258,51.428299],"type":"Point"}
}