{
  "type": "Feature",
  "properties": {
    "addr:full":"Partridge Lane, Newdigate Dorking Surrey RH5 5EE",
    "addr:postcode":"rh5 5ee",
    "addr:street":"Partridge Lane",
    "iso:country":"GB",
    "sg:address":"Partridge Lane, Newdigate",
    "sg:city":"Dorking",
    "sg:classifiers":[
        {
            "category":"Building & Trades",
            "subcategory":"Equipment Rental",
            "type":"Services"
        }
    ],
    "sg:phone":"+44 1293 862666",
    "sg:postcode":"RH5 5EE",
    "sg:province":"Surrey",
    "sg:tags":[
        "plant",
        "machinery"
    ],
    "wof:name":"Bill Kear Plant & Agricultural Contractors Ltd.",
    "wof:placetype":"venue"
},
  "geometry": {"coordinates":[-0.2905510068,51.167591095],"type":"Point"}
}