{
  "type": "Feature",
  "properties": {
    "addr:full":"Unit 10 The Market Place Blackwood Caerphilly NP12 1AU",
    "addr:housenumber":"unit 10",
    "addr:postcode":"np12 1au",
    "addr:street":"The Market Place",
    "iso:country":"GB",
    "sg:address":"Unit 10 The Market Place",
    "sg:city":"Blackwood",
    "sg:classifiers":[
        {
            "category":"Shopping",
            "subcategory":"Clothing, Apparel, & Fashions",
            "type":"Retail Goods"
        }
    ],
    "sg:phone":"+44 1495 226153",
    "sg:postcode":"NP12 1AU",
    "sg:province":"Caerphilly",
    "sg:tags":[
        "shop"
    ],
    "wof:name":"Zaks Clothing Co. Ltd.",
    "wof:placetype":"venue"
},
  "geometry": {"coordinates":[-3.1956489086,51.666595459],"type":"Point"}
}