{
  "type": "Feature",
  "properties": {
    "iso:country":"GB",
    "sg:address":"Elkesley",
    "sg:city":"Retford",
    "sg:classifiers":[
        {
            "category":"Manufacturing",
            "subcategory":"Wood Products",
            "type":"Manufacturing & Wholesale Goods"
        }
    ],
    "sg:postcode":"DN22 8BT",
    "sg:province":"Nottinghamshire",
    "sg:tags":[
        "sawdust",
        "agric",
        "shaving"
    ],
    "wof:name":"Osbourne Poultry Services Ltd.",
    "wof:placetype":"venue"
},
  "geometry": {"coordinates":[-0.9591799974,53.2738800049],"type":"Point"}
}