{
  "type": "Feature",
  "properties": {
    "iso:country":"GB",
    "sg:address":"Unit 7b",
    "sg:city":"Bognor Regis",
    "sg:classifiers":[
        {
            "category":"Home & Garden",
            "subcategory":"Kitchen Supply",
            "type":"Retail Goods"
        }
    ],
    "sg:postcode":"PO22 9RL",
    "sg:province":"West Sussex",
    "sg:tags":[
        "ware"
    ],
    "wof:name":"The Kitchen Sink Co",
    "wof:placetype":"venue"
},
  "geometry": {"coordinates":[-0.680769,50.799259],"type":"Point"}
}