{
  "type": "Feature",
  "properties": {
    "addr:full":"564 Burton Road Derby Derbyshire DE23 6DF",
    "addr:housenumber":"564",
    "addr:postcode":"de23 6df",
    "addr:street":"Burton Road",
    "iso:country":"GB",
    "sg:address":"564 Burton Road",
    "sg:city":"Derby",
    "sg:classifiers":[
        {
            "category":"Shopping",
            "subcategory":"Optician",
            "type":"Retail Goods"
        },
        {
            "category":"Health Services",
            "subcategory":"Optometrist",
            "type":"Services"
        }
    ],
    "sg:phone":"+44 1332 291010",
    "sg:postcode":"DE23 6DF",
    "sg:province":"Derbyshire",
    "sg:tags":[
        "opthalmic"
    ],
    "wof:name":"Bray & Petrie",
    "wof:placetype":"venue"
},
  "geometry": {"coordinates":[-1.5056279898,52.9059867859],"type":"Point"}
}