{
  "type": "Feature",
  "properties": {
    "addr:full":"163 The Broadway Southall Greater London UB1 1LR",
    "addr:housenumber":"163",
    "addr:postcode":"ub1 1lr",
    "addr:street":"The Broadway",
    "iso:country":"GB",
    "sg:address":"163 The Broadway",
    "sg:city":"Southall",
    "sg:classifiers":[
        {
            "category":"Fast Food",
            "type":"Food & Drink"
        },
        {
            "category":"Restaurant",
            "type":"Food & Drink"
        }
    ],
    "sg:phone":"+44 20 8571 5738",
    "sg:postcode":"UB1 1LR",
    "sg:province":"Greater London",
    "sg:tags":[
        "away",
        "indian",
        "take"
    ],
    "wof:name":"Tandoori Kebab Centre",
    "wof:placetype":"venue"
},
  "geometry": {"coordinates":[-0.390344,51.51318],"type":"Point"}
}