{
  "type": "Feature",
  "properties": {
    "iso:country":"GB",
    "sg:address":"5 Davidson Pl",
    "sg:city":"Ayr",
    "sg:classifiers":[
        {
            "category":"Building & Trades",
            "subcategory":"Construction",
            "type":"Services"
        }
    ],
    "sg:phone":"+44 1292 288030",
    "sg:postcode":"KA8 0DE",
    "sg:province":"South Ayrshire",
    "sg:tags":[
        "decorator",
        "painter"
    ],
    "wof:name":"Deluxe Decor Painters & Decorators",
    "wof:placetype":"venue"
},
  "geometry": {"coordinates":[-4.62196,55.464031],"type":"Point"}
}