{
  "type": "Feature",
  "properties": {
    "addr:full":"Church Road, Flitcham King's Lynn Norfolk PE31 6BU",
    "addr:postcode":"pe31 6bu",
    "addr:street":"Church Road;Lynn",
    "iso:country":"GB",
    "sg:address":"Church Road, Flitcham",
    "sg:city":"King's Lynn",
    "sg:classifiers":[
        {
            "category":"Education",
            "subcategory":"School",
            "type":"Public Place"
        }
    ],
    "sg:phone":"+44 1485 600383",
    "sg:postcode":"PE31 6BU",
    "sg:province":"Norfolk",
    "sg:tags":[
        "local",
        "authority"
    ],
    "wof:name":"Flitcham Voluntary Aided C of E School",
    "wof:placetype":"venue"
},
  "geometry": {"coordinates":[0.56007,52.809879],"type":"Point"}
}