{
  "type": "Feature",
  "properties": {
    "iso:country":"GB",
    "sg:address":"Unit 11 Trinity Centre, 155 Union Street",
    "sg:city":"Aberdeen",
    "sg:classifiers":[
        {
            "category":"Shopping",
            "subcategory":"Gifts & Souvenirs",
            "type":"Retail Goods"
        }
    ],
    "sg:postcode":"AB11 6BE",
    "sg:province":"Aberdeen City",
    "sg:tags":[
        "poster",
        "card"
    ],
    "wof:name":"Events",
    "wof:placetype":"venue"
},
  "geometry": {"coordinates":[-2.1015200615,57.1456985474],"type":"Point"}
}