{
  "type": "Feature",
  "properties": {
    "addr:full":"Gale Road, Knowsley Industrial Park Liverpool Lancashire L33 7YB",
    "addr:postcode":"l33 7yb",
    "addr:street":"Gale Road;Industrial Park",
    "iso:country":"GB",
    "sg:address":"Gale Road, Knowsley Industrial Park",
    "sg:city":"Liverpool",
    "sg:classifiers":[
        {
            "category":"Sports & Exercise",
            "subcategory":"Gym",
            "type":"Entertainment"
        }
    ],
    "sg:phone":"+44 151 548 0839",
    "sg:postcode":"L33 7YB",
    "sg:province":"Lancashire",
    "sg:tags":[
        "club",
        "fitness",
        "health",
        "centre"
    ],
    "wof:name":"P B Leisure",
    "wof:placetype":"venue"
},
  "geometry": {"coordinates":[-2.8560249805,53.4744606018],"type":"Point"}
}