{
  "type": "Feature",
  "properties": {
    "addr:full":"Press & Information Officer, Louisa Ryeland Ho Birmingham West Midlands B3 3PN",
    "addr:postcode":"b3 3pn",
    "addr:street":"Ryeland Ho",
    "iso:country":"GB",
    "sg:address":"Press & Information Officer, Louisa Ryeland Ho",
    "sg:city":"Birmingham",
    "sg:classifiers":[
        {
            "category":"Government",
            "subcategory":"Office",
            "type":"Public Place"
        }
    ],
    "sg:phone":"+44 121 303 3621",
    "sg:postcode":"B3 3PN",
    "sg:province":"West Midlands",
    "sg:tags":[
        "local"
    ],
    "wof:name":"Birmingham City Council",
    "wof:placetype":"venue"
},
  "geometry": {"coordinates":[-1.902690053,52.4814910889],"type":"Point"}
}