{
  "type": "Feature",
  "properties": {
    "addr:full":"373-399 London Rd Camberley Berkshire GU15 3HR",
    "addr:housenumber":"373-399",
    "addr:postcode":"gu15 3hr",
    "addr:street":"London Rd",
    "iso:country":"GB",
    "sg:address":"373-399 London Rd",
    "sg:city":"Camberley",
    "sg:classifiers":[
        {
            "category":"Professional",
            "subcategory":"Computer Services",
            "type":"Services"
        }
    ],
    "sg:phone":"+44 1276 414000",
    "sg:postcode":"GU15 3HR",
    "sg:province":"Berkshire",
    "sg:tags":[
        "system",
        "software"
    ],
    "wof:name":"C B S I",
    "wof:placetype":"venue"
},
  "geometry": {"coordinates":[-0.760689,51.33609],"type":"Point"}
}