{
  "type": "Feature",
  "properties": {
    "addr:full":"Princess Elizabeth Way Cheltenham Gloucestershire GL51 7SL",
    "addr:postcode":"gl51 7sl",
    "addr:street":"Princess Elizabeth Way",
    "iso:country":"GB",
    "sg:address":"Princess Elizabeth Way",
    "sg:city":"Cheltenham",
    "sg:classifiers":[
        {
            "category":"Education",
            "subcategory":"School",
            "type":"Public Place"
        }
    ],
    "sg:phone":"+44 1242 523169",
    "sg:postcode":"GL51 7SL",
    "sg:province":"Gloucestershire",
    "sg:tags":[
        "college"
    ],
    "wof:name":"Pate's Grammar School",
    "wof:placetype":"venue"
},
  "geometry": {"coordinates":[-2.103214,51.910946],"type":"Point"}
}