{
  "type": "Feature",
  "properties": {
    "iso:country":"GB",
    "sg:address":"Unit 10 Fifth Avenue, Blue Bridge Industrial Estate",
    "sg:city":"Halstead",
    "sg:classifiers":[
        {
            "category":"Building & Trades",
            "subcategory":"Cleaning & Sanitation",
            "type":"Services"
        }
    ],
    "sg:phone":"+44 1787 478380",
    "sg:postcode":"CO9 2SZ",
    "sg:province":"Essex",
    "sg:tags":[
        "contracting",
        "commercial"
    ],
    "wof:name":"A & H ASSOCIATES LLP",
    "wof:placetype":"venue"
},
  "geometry": {"coordinates":[0.65787,51.941879],"type":"Point"}
}