{
  "type": "Feature",
  "properties": {
    "addr:full":"Wendover Christian Centre, Aylesbury Rd Aylesbury Buckinghamshire HP22 6JG",
    "addr:postcode":"hp22 6jg",
    "addr:street":"Aylesbury Rd",
    "iso:country":"GB",
    "sg:address":"Wendover Christian Centre, Aylesbury Rd",
    "sg:city":"Aylesbury",
    "sg:classifiers":[
        {
            "category":"Place Of Worship",
            "type":"Public Place"
        }
    ],
    "sg:phone":"+44 1296 623404",
    "sg:postcode":"HP22 6JG",
    "sg:province":"Buckinghamshire",
    "wof:name":"Wendover Free Church",
    "wof:placetype":"venue"
},
  "geometry": {"coordinates":[-0.7332860231,51.769115448],"type":"Point"}
}