{
  "type": "Feature",
  "properties": {
    "iso:country":"GB",
    "sg:address":"24 St Martins Street",
    "sg:city":"Hereford",
    "sg:classifiers":[
        {
            "category":"Personal",
            "subcategory":"Beauty Salon",
            "type":"Services"
        }
    ],
    "sg:postcode":"HR2 7RE",
    "sg:province":"Herefordshire",
    "sg:tags":[
        "lady",
        "hairdresser"
    ],
    "wof:name":"Shirley's the Hairdressers",
    "wof:placetype":"venue"
},
  "geometry": {"coordinates":[-2.718756,52.051388],"type":"Point"}
}