{
  "type": "Feature",
  "properties": {
    "addr:full":"29 Fleet Street London Greater London EC4Y 1AA",
    "addr:housenumber":"29",
    "addr:postcode":"ec4y 1aa",
    "addr:street":"Fleet Street",
    "iso:country":"GB",
    "sg:address":"29 Fleet Street",
    "sg:city":"London",
    "sg:classifiers":[
        {
            "category":"Professional",
            "subcategory":"Lawyer & Legal Services",
            "type":"Services"
        }
    ],
    "sg:phone":"+44 20 7353 4777",
    "sg:postcode":"EC4Y 1AA",
    "sg:province":"Greater London",
    "sg:tags":[
        "solicitor"
    ],
    "wof:name":"Smyth Barkham",
    "wof:placetype":"venue"
},
  "geometry": {"coordinates":[-0.110303,51.51392],"type":"Point"}
}