{
  "type": "Feature",
  "properties": {
    "iso:country":"GB",
    "sg:address":"105 Wilmslow Rd",
    "sg:city":"Wilmslow",
    "sg:classifiers":[
        {
            "category":"Restaurant",
            "type":"Food & Drink"
        }
    ],
    "sg:phone":"+44 1625 537873",
    "sg:postcode":"SK9 3ER",
    "sg:province":"Cheshire",
    "wof:name":"Tapas Espana Restaurant",
    "wof:placetype":"venue"
},
  "geometry": {"coordinates":[-2.215279,53.347279],"type":"Point"}
}