{
  "type": "Feature",
  "properties": {
    "addr:full":"Blackbird Hill London Greater London NW9 8SD",
    "addr:postcode":"nw9 8sd",
    "addr:street":"Blackbird Hill",
    "iso:country":"GB",
    "sg:address":"Blackbird Hill",
    "sg:city":"London",
    "sg:classifiers":[
        {
            "category":"Food & Beverages",
            "subcategory":"Supermarket",
            "type":"Retail Goods"
        }
    ],
    "sg:phone":"+44 20 8555 0518",
    "sg:postcode":"NW9 8SD",
    "sg:province":"Greater London",
    "wof:name":"Safeway Stores Ltd.",
    "wof:placetype":"venue"
},
  "geometry": {"coordinates":[-0.2623789907,51.5643615723],"type":"Point"}
}