{
  "type": "Feature",
  "properties": {
    "addr:full":"20 High Street, Irthlingborough Wellingborough Northamptonshire NN9 5TN",
    "addr:housenumber":"20",
    "addr:postcode":"nn9 5tn",
    "addr:street":"High Street",
    "iso:country":"GB",
    "sg:address":"20 High Street, Irthlingborough",
    "sg:city":"Wellingborough",
    "sg:classifiers":[
        {
            "category":"Food & Beverages",
            "subcategory":"Meat & Fish",
            "type":"Retail Goods"
        }
    ],
    "sg:phone":"+44 1933 651605",
    "sg:postcode":"NN9 5TN",
    "sg:province":"Northamptonshire",
    "sg:tags":[
        "butcher"
    ],
    "wof:name":"Wilson's Butchers",
    "wof:placetype":"venue"
},
  "geometry": {"coordinates":[-0.6553720236,52.338634491],"type":"Point"}
}