{
  "type": "Feature",
  "properties": {
    "iso:country":"GB",
    "sg:address":"96 Colman Road",
    "sg:city":"Norwich",
    "sg:classifiers":[
        {
            "category":"Fast Food",
            "type":"Food & Drink"
        },
        {
            "category":"Wholesale",
            "subcategory":"Groceries",
            "type":"Manufacturing & Wholesale Goods"
        }
    ],
    "sg:phone":"+44 1603 504433",
    "sg:postcode":"NR4 7EH",
    "sg:province":"Norfolk",
    "sg:tags":[
        "supplier",
        "away",
        "take",
        "pizza"
    ],
    "wof:name":"Perfect Pizza Ltd",
    "wof:placetype":"venue"
},
  "geometry": {"coordinates":[1.261898,52.622116],"type":"Point"}
}