{
  "type": "Feature",
  "properties": {
    "addr:full":"17 Ash Street Walsall Staffordshire WS3 3AN",
    "addr:housenumber":"17",
    "addr:postcode":"ws3 3an",
    "addr:street":"Ash Street",
    "iso:country":"GB",
    "sg:address":"17 Ash Street",
    "sg:city":"Walsall",
    "sg:classifiers":[
        {
            "category":"Education",
            "subcategory":"Music School",
            "type":"Public Place"
        }
    ],
    "sg:postcode":"WS3 3AN",
    "sg:province":"Staffordshire",
    "sg:tags":[
        "teacher"
    ],
    "wof:name":"A Petkovic Music Teacher",
    "wof:placetype":"venue"
},
  "geometry": {"coordinates":[-1.9920719862,52.6198043823],"type":"Point"}
}