{
  "type": "Feature",
  "properties": {
    "addr:full":"30 Houndean Rise Lewes East Sussex BN7 1EQ",
    "addr:housenumber":"30",
    "addr:postcode":"bn7 1eq",
    "addr:street":"Houndean Rise",
    "iso:country":"GB",
    "sg:address":"30 Houndean Rise",
    "sg:city":"Lewes",
    "sg:classifiers":[
        {
            "category":"Building & Trades",
            "subcategory":"Plumbing",
            "type":"Services"
        }
    ],
    "sg:postcode":"BN7 1EQ",
    "sg:province":"East Sussex",
    "sg:tags":[
        "central",
        "heating"
    ],
    "wof:name":"A P S Services",
    "wof:placetype":"venue"
},
  "geometry": {"coordinates":[-0.012319,50.871113],"type":"Point"}
}