{
  "type": "Feature",
  "properties": {
    "addr:full":"The Garage, Bar Girvan South Ayrshire KA26 9TU",
    "addr:postcode":"ka26 9tu",
    "iso:country":"GB",
    "sg:address":"The Garage, Bar",
    "sg:city":"Girvan",
    "sg:classifiers":[
        {
            "category":"Freight",
            "type":"Transportation"
        }
    ],
    "sg:phone":"+44 1465 861271",
    "sg:postcode":"KA26 9TU",
    "sg:province":"South Ayrshire",
    "sg:tags":[
        "haulage",
        "road"
    ],
    "wof:name":"Scottserv Ltd.",
    "wof:placetype":"venue"
},
  "geometry": {"coordinates":[-4.857722,55.236031],"type":"Point"}
}