{
  "type": "Feature",
  "properties": {
    "addr:full":"39 Elmfield Gillingham Kent ME8 6BW",
    "addr:housenumber":"39",
    "addr:postcode":"me8 6bw",
    "addr:street":"Elmfield Gillingham",
    "iso:country":"GB",
    "sg:address":"39 Elmfield",
    "sg:city":"Gillingham",
    "sg:classifiers":[
        {
            "category":"Professional",
            "subcategory":"Accounting & Tax Preparation",
            "type":"Services"
        }
    ],
    "sg:postcode":"ME8 6BW",
    "sg:province":"Kent",
    "sg:tags":[
        "accountant"
    ],
    "wof:name":"Snap Dragon (Uk) Ltd",
    "wof:placetype":"venue"
},
  "geometry": {"coordinates":[0.5755839944,51.3741416931],"type":"Point"}
}