{
  "type": "Feature",
  "properties": {
    "iso:country":"GB",
    "sg:address":"Unit 6 Main Street",
    "sg:city":"Sheffield",
    "sg:classifiers":[
        {
            "category":"Retail",
            "subcategory":"Auto Repair",
            "type":"Services"
        }
    ],
    "sg:phone":"+44 114 248 8508",
    "sg:postcode":"S12 4LB",
    "sg:province":"Derbyshire",
    "sg:tags":[
        "modification",
        "garage"
    ],
    "wof:name":"C & B Cars",
    "wof:placetype":"venue"
},
  "geometry": {"coordinates":[-1.376254,53.346748],"type":"Point"}
}