{
  "type": "Feature",
  "properties": {
    "addr:full":"Annandale, Mutton La Potters Bar Greater London EN6 2AS",
    "addr:postcode":"en6 2as",
    "addr:street":"Mutton",
    "iso:country":"GB",
    "sg:address":"Annandale, Mutton La",
    "sg:city":"Potters Bar",
    "sg:classifiers":[
        {
            "category":"Health Services",
            "subcategory":"Doctor",
            "type":"Services"
        }
    ],
    "sg:phone":"+44 1707 644451",
    "sg:postcode":"EN6 2AS",
    "sg:province":"Greater London",
    "sg:tags":[
        "practitioners"
    ],
    "wof:name":"Woods, B T",
    "wof:placetype":"venue"
},
  "geometry": {"coordinates":[-0.1784240007,51.6930122375],"type":"Point"}
}