{
  "type": "Feature",
  "properties": {
    "addr:full":"The Station Yard Llanfyrnach Carmarthenshire SA35 0BZ",
    "addr:postcode":"sa35 0bz",
    "iso:country":"GB",
    "sg:address":"The Station Yard",
    "sg:city":"Llanfyrnach",
    "sg:classifiers":[
        {
            "category":"Retail",
            "subcategory":"Auto Repair",
            "type":"Services"
        }
    ],
    "sg:phone":"+44 1239 831631",
    "sg:postcode":"SA35 0BZ",
    "sg:province":"Carmarthenshire",
    "sg:tags":[
        "modification",
        "garage"
    ],
    "wof:name":"Mansel Davies & Son (Garages) Ltd.",
    "wof:placetype":"venue"
},
  "geometry": {"coordinates":[-4.589888,51.951145],"type":"Point"}
}