{
  "type": "Feature",
  "properties": {
    "addr:full":"Middlewood Court, Chadderton Oldham Lancashire OL9 9SR",
    "addr:postcode":"ol9 9sr",
    "addr:street":"Middlewood Court",
    "iso:country":"GB",
    "sg:address":"Middlewood Court, Chadderton",
    "sg:city":"Oldham",
    "sg:classifiers":[
        {
            "category":"Health Services",
            "subcategory":"Nursing And Care Facility",
            "type":"Services"
        }
    ],
    "sg:phone":"+44 161 627 0027",
    "sg:postcode":"OL9 9SR",
    "sg:province":"Lancashire",
    "sg:tags":[
        "home"
    ],
    "wof:name":"Chadderton Total Care Unit Ltd",
    "wof:placetype":"venue"
},
  "geometry": {"coordinates":[-2.150343895,53.5469551086],"type":"Point"}
}