{
  "type": "Feature",
  "properties": {
    "iso:country":"GB",
    "sg:address":"346 Garth Road",
    "sg:city":"Morden",
    "sg:classifiers":[
        {
            "category":"Education",
            "subcategory":"School",
            "type":"Public Place"
        }
    ],
    "sg:phone":"+44 20 8715 4963",
    "sg:postcode":"SM4 4NW",
    "sg:province":"Surrey",
    "sg:tags":[
        "local",
        "authority"
    ],
    "wof:name":"V S  & Associates One Ltd.",
    "wof:placetype":"venue"
},
  "geometry": {"coordinates":[-0.2265820056,51.388999939],"type":"Point"}
}