{
  "type": "Feature",
  "properties": {
    "addr:full":"17 Ethelbert Square Westgate-on-sea Kent CT8 8SR",
    "addr:housenumber":"17",
    "addr:postcode":"ct8 8sr",
    "addr:street":"Ethelbert Square Westgate-On-Sea",
    "iso:country":"GB",
    "sg:address":"17 Ethelbert Square",
    "sg:city":"Westgate-on-sea",
    "sg:classifiers":[
        {
            "category":"Social Services",
            "subcategory":"Retirement Home",
            "type":"Services"
        },
        {
            "category":"Government",
            "subcategory":"Office",
            "type":"Public Place"
        }
    ],
    "sg:postcode":"CT8 8SR",
    "sg:province":"Kent",
    "sg:tags":[
        "residential",
        "central",
        "care"
    ],
    "wof:name":"M & L Hilliar",
    "wof:placetype":"venue"
},
  "geometry": {"coordinates":[1.3386230469,51.3818283081],"type":"Point"}
}