{
  "type": "Feature",
  "properties": {
    "iso:country":"GB",
    "sg:address":"Caerhys Farm, Berea",
    "sg:city":"Haverfordwest",
    "sg:classifiers":[
        {
            "category":"Farming",
            "subcategory":"Livestock Farm",
            "type":"Manufacturing & Wholesale Goods"
        }
    ],
    "sg:phone":"+44 1348 831244",
    "sg:postcode":"SA62 6DX",
    "sg:province":"Pembrokeshire",
    "sg:tags":[
        "others"
    ],
    "wof:name":"G D & G A Miles",
    "wof:placetype":"venue"
},
  "geometry": {"coordinates":[-5.201764,51.925915],"type":"Point"}
}