{
  "type": "Feature",
  "properties": {
    "addr:full":"Hathern Road, Shepshed Loughborough Leicestershire LE12 9RP",
    "addr:postcode":"le12 9rp",
    "addr:street":"Hathern Road",
    "iso:country":"GB",
    "sg:address":"Hathern Road, Shepshed",
    "sg:city":"Loughborough",
    "sg:classifiers":[
        {
            "category":"Wholesale",
            "subcategory":"Scrap",
            "type":"Manufacturing & Wholesale Goods"
        },
        {
            "category":"Building & Trades",
            "subcategory":"Pest Control",
            "type":"Services"
        }
    ],
    "sg:phone":"+44 1509 600072",
    "sg:postcode":"LE12 9RP",
    "sg:province":"Leicestershire",
    "sg:tags":[
        "waste",
        "metal"
    ],
    "wof:name":"Higgins",
    "wof:placetype":"venue"
},
  "geometry": {"coordinates":[-1.289013,52.770943],"type":"Point"}
}