{
  "type": "Feature",
  "properties": {
    "iso:country":"GB",
    "sg:address":"3 New London Rd",
    "sg:city":"Chelmsford",
    "sg:classifiers":[
        {
            "category":"Professional",
            "subcategory":"Employment Agencies",
            "type":"Services"
        }
    ],
    "sg:phone":"+44 1245 245500",
    "sg:postcode":"CM2 0NA",
    "sg:province":"Essex",
    "sg:tags":[
        "consultant"
    ],
    "wof:name":"Reed Accountancy Personnel",
    "wof:placetype":"venue"
},
  "geometry": {"coordinates":[0.473621,51.733139],"type":"Point"}
}