{
  "type": "Feature",
  "properties": {
    "addr:full":"Units B2 - B5, Tweedale Industrial Estate Telford Shropshire TF7 4JR",
    "addr:housenumber":"b5;estate",
    "addr:postcode":"tf7 4jr",
    "addr:street":"Tweedale Industrial",
    "iso:country":"GB",
    "sg:address":"Units B2 - B5, Tweedale Industrial Estate",
    "sg:city":"Telford",
    "sg:classifiers":[
        {
            "category":"Manufacturing",
            "subcategory":"Rubber & Plastics",
            "type":"Manufacturing & Wholesale Goods"
        }
    ],
    "sg:phone":"+44 1952 684849",
    "sg:postcode":"TF7 4JR",
    "sg:province":"Shropshire",
    "sg:tags":[
        "product"
    ],
    "wof:name":"B U Industrial Components Ltd.",
    "wof:placetype":"venue"
},
  "geometry": {"coordinates":[-2.4431099892,52.6408805847],"type":"Point"}
}