{
  "type": "Feature",
  "properties": {
    "addr:full":"41 Larch Place, Greenhill, East Kilbride Glasgow South Lanarkshire G75 9HQ",
    "addr:housenumber":"41",
    "addr:postcode":"g75 9hq",
    "addr:street":"Larch Place",
    "iso:country":"GB",
    "sg:address":"41 Larch Place, Greenhill, East Kilbride",
    "sg:city":"Glasgow",
    "sg:classifiers":[
        {
            "category":"Shopping",
            "subcategory":"News",
            "type":"Retail Goods"
        }
    ],
    "sg:phone":"+44 1355 248971",
    "sg:postcode":"G75 9HQ",
    "sg:province":"South Lanarkshire",
    "sg:tags":[
        "newsagent"
    ],
    "wof:name":"Wiseman Stationeries Supplies",
    "wof:placetype":"venue"
},
  "geometry": {"coordinates":[-4.200197,55.743168],"type":"Point"}
}