{
  "type": "Feature",
  "properties": {
    "iso:country":"GB",
    "sg:address":"32 Thorpe Lane, Cawood",
    "sg:city":"Selby",
    "sg:classifiers":[
        {
            "category":"Real Estate",
            "subcategory":"Developer",
            "type":"Services"
        }
    ],
    "sg:phone":"+44 1757 268454",
    "sg:postcode":"YO8 0SG",
    "sg:province":"East Riding of Yorkshire",
    "sg:tags":[
        "property"
    ],
    "wof:name":"Ronros Properties Ltd",
    "wof:placetype":"venue"
},
  "geometry": {"coordinates":[-1.0703459978,53.783908844],"type":"Point"}
}