{
  "type": "Feature",
  "properties": {
    "addr:full":"49 The Green High Wycombe Buckinghamshire HP10 0EU",
    "addr:housenumber":"49",
    "addr:postcode":"hp10 0eu",
    "addr:street":"The Green",
    "iso:country":"GB",
    "sg:address":"49 The Green",
    "sg:city":"High Wycombe",
    "sg:classifiers":[
        {
            "category":"Professional",
            "subcategory":"Business Services",
            "type":"Services"
        }
    ],
    "sg:phone":"+44 1628 525885",
    "sg:postcode":"HP10 0EU",
    "sg:province":"Buckinghamshire",
    "sg:tags":[
        "bookmaker"
    ],
    "wof:name":"V J Racing",
    "wof:placetype":"venue"
},
  "geometry": {"coordinates":[-0.6838290095,51.5883789062],"type":"Point"}
}