{
  "type": "Feature",
  "properties": {
    "iso:country":"GB",
    "sg:address":"40 Sidegate",
    "sg:city":"Haddington",
    "sg:classifiers":[
        {
            "category":"Real Estate",
            "subcategory":"Surveying",
            "type":"Services"
        }
    ],
    "sg:phone":"+44 1620 824986",
    "sg:postcode":"EH41 4BU",
    "sg:province":"East Lothian",
    "sg:tags":[
        "surveyor",
        "land",
        "activity"
    ],
    "wof:name":"Chalmers & Co.",
    "wof:placetype":"venue"
},
  "geometry": {"coordinates":[-2.774334,55.953888],"type":"Point"}
}