{
  "type": "Feature",
  "properties": {
    "iso:country":"GB",
    "sg:address":"381 Fareham Road",
    "sg:city":"Gosport",
    "sg:classifiers":[
        {
            "category":"Building & Trades",
            "subcategory":"Construction",
            "type":"Services"
        }
    ],
    "sg:phone":"+44 1329 221649",
    "sg:postcode":"PO13 0AD",
    "sg:province":"Hampshire",
    "sg:tags":[
        "dry",
        "plastering",
        "plasterers",
        "lining",
        "related",
        "screeders"
    ],
    "wof:name":"Michael W Bernice",
    "wof:placetype":"venue"
},
  "geometry": {"coordinates":[-1.178367,50.835602],"type":"Point"}
}