{
  "type": "Feature",
  "properties": {
    "iso:country":"GB",
    "sg:address":"41 Hull Road",
    "sg:city":"Blackpool",
    "sg:classifiers":[
        {
            "category":"Travel",
            "subcategory":"Hotels & Motels",
            "type":"Entertainment"
        }
    ],
    "sg:phone":"+44 1253 622677",
    "sg:postcode":"FY1 4QB",
    "sg:province":"Lancashire",
    "wof:name":"Windsor Private Hotel",
    "wof:placetype":"venue"
},
  "geometry": {"coordinates":[-3.05171,53.814526],"type":"Point"}
}