{
  "type": "Feature",
  "properties": {
    "addr:full":"103 Whiteladies Road, Clifton Bristol City of Bristol BS8 2PB",
    "addr:housenumber":"103",
    "addr:postcode":"bs8 2pb",
    "addr:street":"Whiteladies Road",
    "iso:country":"GB",
    "sg:address":"103 Whiteladies Road, Clifton",
    "sg:city":"Bristol",
    "sg:classifiers":[
        {
            "category":"Insurance",
            "subcategory":"Insurance Agent",
            "type":"Services"
        }
    ],
    "sg:phone":"+44 117 973 3430",
    "sg:postcode":"BS8 2PB",
    "sg:province":"City of Bristol",
    "wof:name":"Britannic Assurance Plc",
    "wof:placetype":"venue"
},
  "geometry": {"coordinates":[-2.6092948914,51.4640312195],"type":"Point"}
}