{
  "type": "Feature",
  "properties": {
    "iso:country":"GB",
    "sg:address":"39 Lesbourne Road",
    "sg:city":"Reigate",
    "sg:classifiers":[
        {
            "category":"Shopping",
            "subcategory":"Party Supplies",
            "type":"Retail Goods"
        }
    ],
    "sg:phone":"+44 1737 221081",
    "sg:postcode":"RH2 7JS",
    "sg:province":"Surrey",
    "sg:tags":[
        "inflatables",
        "bouncy",
        "castle"
    ],
    "wof:name":"Monkey Business",
    "wof:placetype":"venue"
},
  "geometry": {"coordinates":[-0.1994670033,51.23387146],"type":"Point"}
}