{
  "type": "Feature",
  "properties": {
    "addr:full":"20-21a Buttermarket Bury St Edmunds Suffolk IP33 1DU",
    "addr:housenumber":"20-21a",
    "addr:postcode":"ip33 1du",
    "addr:street":"Buttermarket",
    "iso:country":"GB",
    "sg:address":"20-21a Buttermarket",
    "sg:city":"Bury St Edmunds",
    "sg:classifiers":[
        {
            "category":"Home & Garden",
            "subcategory":"Household Appliances",
            "type":"Retail Goods"
        }
    ],
    "sg:phone":"+44 1284 754516",
    "sg:postcode":"IP33 1DU",
    "sg:province":"Suffolk",
    "sg:tags":[
        "electrical",
        "domestic"
    ],
    "wof:name":"Dixons",
    "wof:placetype":"venue"
},
  "geometry": {"coordinates":[0.71336,52.246021],"type":"Point"}
}