{
  "type": "Feature",
  "properties": {
    "addr:full":"151 Dixons Hill Road Hatfield Hertfordshire AL9 7JE",
    "addr:housenumber":"151",
    "addr:postcode":"al9 7je",
    "addr:street":"Dixons Hill Road",
    "iso:country":"GB",
    "sg:address":"151 Dixons Hill Road",
    "sg:city":"Hatfield",
    "sg:classifiers":[
        {
            "category":"Social Services",
            "type":"Services"
        }
    ],
    "sg:phone":"+44 1707 266726",
    "sg:postcode":"AL9 7JE",
    "sg:province":"Hertfordshire",
    "sg:tags":[
        "disability"
    ],
    "wof:name":"Intrad Ltd.",
    "wof:placetype":"venue"
},
  "geometry": {"coordinates":[-0.2152570039,51.7355690002],"type":"Point"}
}