{
  "type": "Feature",
  "properties": {
    "addr:full":"The Presbytery, New Street Ledbury Gloucestershire HR8 2EE",
    "addr:postcode":"hr8 2ee",
    "addr:street":"New Street",
    "iso:country":"GB",
    "sg:address":"The Presbytery, New Street",
    "sg:city":"Ledbury",
    "sg:classifiers":[
        {
            "category":"Place Of Worship",
            "type":"Public Place"
        }
    ],
    "sg:postcode":"HR8 2EE",
    "sg:province":"Gloucestershire",
    "wof:name":"Church of the Holy Trinity Rc Church",
    "wof:placetype":"venue"
},
  "geometry": {"coordinates":[-2.4243400097,52.0389404297],"type":"Point"}
}