{
  "type": "Feature",
  "properties": {
    "addr:full":"2a Green Lane, Sonning Common Reading Berkshire RG4 9NA",
    "addr:housenumber":"2a",
    "addr:postcode":"rg4 9na",
    "addr:street":"Green Lane",
    "iso:country":"GB",
    "sg:address":"2a Green Lane, Sonning Common",
    "sg:city":"Reading",
    "sg:classifiers":[
        {
            "category":"Food & Beverages",
            "subcategory":"Meat & Fish",
            "type":"Retail Goods"
        },
        {
            "category":"Food & Beverages",
            "subcategory":"Groceries & Convenience Stores",
            "type":"Retail Goods"
        }
    ],
    "sg:phone":"+44 118 972 2721",
    "sg:postcode":"RG4 9NA",
    "sg:province":"Berkshire",
    "sg:tags":[
        "shop",
        "chip"
    ],
    "wof:name":"Sonning Common Fish Bar",
    "wof:placetype":"venue"
},
  "geometry": {"coordinates":[-0.9829170108,51.5163612366],"type":"Point"}
}