{
  "type": "Feature",
  "properties": {
    "iso:country":"GB",
    "sg:address":"156 Arle Road",
    "sg:city":"Cheltenham",
    "sg:classifiers":[
        {
            "category":"Farming",
            "subcategory":"Nursery",
            "type":"Manufacturing & Wholesale Goods"
        }
    ],
    "sg:phone":"+44 1242 693200",
    "sg:postcode":"GL51 8LH",
    "sg:province":"Gloucestershire",
    "sg:tags":[
        "creche"
    ],
    "wof:name":"Early Birds Day Nursery",
    "wof:placetype":"venue"
},
  "geometry": {"coordinates":[-2.096139,51.90572],"type":"Point"}
}