{
  "type": "Feature",
  "properties": {
    "iso:country":"GB",
    "sg:address":"Nook Farm, Low Road, Little Stukeley",
    "sg:city":"Huntingdon",
    "sg:classifiers":[
        {
            "category":"Home & Garden",
            "subcategory":"Garden Supply",
            "type":"Retail Goods"
        },
        {
            "category":"Farming",
            "subcategory":"Livestock Farm",
            "type":"Manufacturing & Wholesale Goods"
        }
    ],
    "sg:postcode":"PE28 4BA",
    "sg:province":"Bedfordshire",
    "sg:tags":[
        "bulb",
        "grower",
        "others"
    ],
    "wof:name":"G C Field & Sons",
    "wof:placetype":"venue"
},
  "geometry": {"coordinates":[-0.2281589955,52.365486145],"type":"Point"}
}