{
  "type": "Feature",
  "properties": {
    "addr:full":"Unit 14 Nottingham Fashion Centre, Huntingdon St Nottingham Nottinghamshire NG1 3LH",
    "addr:housenumber":"unit 14",
    "addr:postcode":"ng1 3lh",
    "addr:street":"Huntingdon St",
    "iso:country":"GB",
    "sg:address":"Unit 14 Nottingham Fashion Centre, Huntingdon St",
    "sg:city":"Nottingham",
    "sg:classifiers":[
        {
            "category":"Professional",
            "subcategory":"Business Services",
            "type":"Services"
        }
    ],
    "sg:phone":"+44 115 950 8325",
    "sg:postcode":"NG1 3LH",
    "sg:province":"Nottinghamshire",
    "sg:tags":[
        "agent",
        "manufacturers'"
    ],
    "wof:name":"John Pullman Textiles",
    "wof:placetype":"venue"
},
  "geometry": {"coordinates":[-1.1439239979,52.9492263794],"type":"Point"}
}