{
  "type": "Feature",
  "properties": {
    "addr:full":"18 Hillcrest Road London Greater London E17 4AP",
    "addr:housenumber":"18",
    "addr:postcode":"e17 4ap",
    "addr:street":"Hillcrest Road",
    "iso:country":"GB",
    "sg:address":"18 Hillcrest Road",
    "sg:city":"London",
    "sg:classifiers":[
        {
            "category":"Retail",
            "subcategory":"Driving School",
            "type":"Services"
        }
    ],
    "sg:phone":"+44 20 8527 2950",
    "sg:postcode":"E17 4AP",
    "sg:province":"Greater London",
    "wof:name":"D Harper School Of Motoring",
    "wof:placetype":"venue"
},
  "geometry": {"coordinates":[0.0039840001,51.5937385559],"type":"Point"}
}