{
  "type": "Feature",
  "properties": {
    "iso:country":"GB",
    "sg:address":"Antivian, Upwood Road, Bury",
    "sg:city":"Huntingdon",
    "sg:classifiers":[
        {
            "category":"Real Estate",
            "subcategory":"Architect",
            "type":"Services"
        }
    ],
    "sg:phone":"+44 1487 813852",
    "sg:postcode":"PE26 2PE",
    "sg:province":"Cambridgeshire",
    "sg:tags":[
        "architectural"
    ],
    "wof:name":"Brian Woodward",
    "wof:placetype":"venue"
},
  "geometry": {"coordinates":[-0.1209,52.434738],"type":"Point"}
}