{
  "type": "Feature",
  "properties": {
    "addr:full":"1-3 Wellington New Road Taunton Somerset TA1 5NH",
    "addr:housenumber":"1-3",
    "addr:postcode":"ta1 5nh",
    "addr:street":"Wellington New Road",
    "iso:country":"GB",
    "sg:address":"1-3 Wellington New Road",
    "sg:city":"Taunton",
    "sg:classifiers":[
        {
            "category":"Manufacturing",
            "subcategory":"Petroleum Products",
            "type":"Manufacturing & Wholesale Goods"
        }
    ],
    "sg:phone":"+44 1823 333911",
    "sg:postcode":"TA1 5NH",
    "sg:province":"Somerset",
    "sg:tags":[
        "double",
        "glazing"
    ],
    "wof:name":"Climax Windows & Conservatories",
    "wof:placetype":"venue"
},
  "geometry": {"coordinates":[-3.126169,51.013081],"type":"Point"}
}