{
  "type": "Feature",
  "properties": {
    "addr:full":"35-36 High Street, Cricklade Swindon Gloucestershire SN6 6AY",
    "addr:housenumber":"35-36",
    "addr:postcode":"sn6 6ay",
    "addr:street":"High Street",
    "iso:country":"GB",
    "sg:address":"35-36 High Street, Cricklade",
    "sg:city":"Swindon",
    "sg:classifiers":[
        {
            "category":"Wholesale",
            "subcategory":"Machinery & Supplies",
            "type":"Manufacturing & Wholesale Goods"
        }
    ],
    "sg:phone":"+44 1793 751882",
    "sg:postcode":"SN6 6AY",
    "sg:province":"Gloucestershire",
    "sg:tags":[
        "hydraulic"
    ],
    "wof:name":"Hunger Hydraulics (U K) Ltd.",
    "wof:placetype":"venue"
},
  "geometry": {"coordinates":[-1.8564100266,51.6415290833],"type":"Point"}
}