{
  "type": "Feature",
  "properties": {
    "addr:full":"70-72 Chancery Lane London Greater London WC2A 1AB",
    "addr:housenumber":"70-72",
    "addr:postcode":"wc2a 1ab",
    "addr:street":"Chancery Lane",
    "iso:country":"GB",
    "sg:address":"70-72 Chancery Lane",
    "sg:city":"London",
    "sg:classifiers":[
        {
            "category":"Professional",
            "subcategory":"Lawyer & Legal Services",
            "type":"Services"
        }
    ],
    "sg:phone":"+44 20 7405 6879",
    "sg:postcode":"WC2A 1AB",
    "sg:province":"Greater London",
    "sg:tags":[
        "barrister"
    ],
    "wof:name":"St.Ville L A",
    "wof:placetype":"venue"
},
  "geometry": {"coordinates":[-0.1135179996,51.5179290771],"type":"Point"}
}