{
  "type": "Feature",
  "properties": {
    "addr:full":"Horwath Clark Whitehill, Kennet House 80 Kings Road Reading Berkshire RG1 3BL",
    "addr:housenumber":"80",
    "addr:postcode":"rg1 3bl",
    "addr:street":"Kings Road",
    "iso:country":"GB",
    "sg:address":"Horwath Clark Whitehill, Kennet House 80 Kings Road",
    "sg:city":"Reading",
    "sg:classifiers":[
        {
            "category":"Autos & Motor Vehicles",
            "subcategory":"Motorcycle Sales",
            "type":"Retail Goods"
        }
    ],
    "sg:postcode":"RG1 3BL",
    "sg:province":"Berkshire",
    "sg:tags":[
        "chauffeur",
        "driven",
        "car"
    ],
    "wof:name":"Hudson Chauffeur Drive Ltd",
    "wof:placetype":"venue"
},
  "geometry": {"coordinates":[-0.9647949934,51.454662323],"type":"Point"}
}