{
  "type": "Feature",
  "properties": {
    "iso:country":"GB",
    "sg:address":"70 New Hey Rd, Lindley",
    "sg:city":"Huddersfield",
    "sg:classifiers":[
        {
            "category":"Government",
            "subcategory":"City Hall",
            "type":"Public Place"
        }
    ],
    "sg:phone":"+44 1484 420419",
    "sg:postcode":"HD3 4AJ",
    "sg:province":"West Yorkshire",
    "wof:name":"Masonic Hall",
    "wof:placetype":"venue"
},
  "geometry": {"coordinates":[-1.8155469894,53.6526565552],"type":"Point"}
}