{
  "type": "Feature",
  "properties": {
    "addr:full":"1 Blenheim Road Plymouth Devon PL4 8LJ",
    "addr:housenumber":"1",
    "addr:postcode":"pl4 8lj",
    "addr:street":"Blenheim Road",
    "iso:country":"GB",
    "sg:address":"1 Blenheim Road",
    "sg:city":"Plymouth",
    "sg:classifiers":[
        {
            "category":"Professional",
            "subcategory":"Lawyer & Legal Services",
            "type":"Services"
        }
    ],
    "sg:postcode":"PL4 8LJ",
    "sg:province":"Devon",
    "sg:tags":[
        "solicitor"
    ],
    "wof:name":"MURRAY JONES & MARSHALL",
    "wof:placetype":"venue"
},
  "geometry": {"coordinates":[-4.1367712021,50.3751869202],"type":"Point"}
}