{
  "type": "Feature",
  "properties": {
    "addr:full":"30 St.vincent Rd Walton On Thames Surrey KT12 1PB",
    "addr:housenumber":"30",
    "addr:postcode":"kt12 1pb",
    "addr:street":"St.Vincent Rd",
    "iso:country":"GB",
    "sg:address":"30 St.vincent Rd",
    "sg:city":"Walton On Thames",
    "sg:classifiers":[
        {
            "category":"Professional",
            "subcategory":"Engineering",
            "type":"Services"
        }
    ],
    "sg:phone":"+44 1932 242211",
    "sg:postcode":"KT12 1PB",
    "sg:province":"Surrey",
    "sg:tags":[
        "consulting",
        "engineer"
    ],
    "wof:name":"W.F Botting",
    "wof:placetype":"venue"
},
  "geometry": {"coordinates":[-0.4107680023,51.3760528564],"type":"Point"}
}