{
  "type": "Feature",
  "properties": {
    "addr:full":"102 Victor Road Teddington Greater London TW11 8SS",
    "addr:housenumber":"102",
    "addr:postcode":"tw11 8ss",
    "addr:street":"Victor Road",
    "iso:country":"GB",
    "sg:address":"102 Victor Road",
    "sg:city":"Teddington",
    "sg:classifiers":[
        {
            "category":"Communications",
            "subcategory":"Newspaper",
            "type":"Services"
        }
    ],
    "sg:phone":"+44 20 8943 3630",
    "sg:postcode":"TW11 8SS",
    "sg:province":"Greater London",
    "sg:tags":[
        "magazine"
    ],
    "wof:name":"Hilal I N T (U K) Ltd.",
    "wof:placetype":"venue"
},
  "geometry": {"coordinates":[-0.3405930102,51.430847168],"type":"Point"}
}