{
  "type": "Feature",
  "properties": {
    "addr:full":"32 Winterford Avenue Manchester Greater Manchester M13 9AY",
    "addr:housenumber":"32",
    "addr:postcode":"m13 9ay",
    "addr:street":"Winterford Avenue",
    "iso:country":"GB",
    "sg:address":"32 Winterford Avenue",
    "sg:city":"Manchester",
    "sg:classifiers":[
        {
            "category":"Professional",
            "subcategory":"Employment Agencies",
            "type":"Services"
        }
    ],
    "sg:phone":"+44 161 272 7859",
    "sg:postcode":"M13 9AY",
    "sg:province":"Greater Manchester",
    "sg:tags":[
        "consultant"
    ],
    "wof:name":"Agnes Contractors",
    "wof:placetype":"venue"
},
  "geometry": {"coordinates":[-2.214369,53.46331],"type":"Point"}
}