{
  "type": "Feature",
  "properties": {
    "addr:full":"The Old School Grounds, Station Road Narberth Carmarthenshire SA67 8DU",
    "addr:postcode":"sa67 8du",
    "addr:street":"Station Road",
    "iso:country":"GB",
    "sg:address":"The Old School Grounds, Station Road",
    "sg:city":"Narberth",
    "sg:classifiers":[
        {
            "category":"Sports & Exercise",
            "subcategory":"Swimming Pool",
            "type":"Entertainment"
        }
    ],
    "sg:phone":"+44 1834 860940",
    "sg:postcode":"SA67 8DU",
    "sg:province":"Carmarthenshire",
    "wof:name":"Narberth Swimming Pool",
    "wof:placetype":"venue"
},
  "geometry": {"coordinates":[-4.7442269325,51.8011703491],"type":"Point"}
}