{
  "type": "Feature",
  "properties": {
    "addr:full":"Coles Farm, Bury Lane, Totton Southampton Hampshire SO40 9FZ",
    "addr:postcode":"so40 9fz",
    "addr:street":"Bury Lane",
    "iso:country":"GB",
    "sg:address":"Coles Farm, Bury Lane, Totton",
    "sg:city":"Southampton",
    "sg:classifiers":[
        {
            "category":"Farming",
            "subcategory":"Livestock Farm",
            "type":"Manufacturing & Wholesale Goods"
        }
    ],
    "sg:phone":"+44 23 8086 3092",
    "sg:postcode":"SO40 9FZ",
    "sg:province":"Hampshire",
    "sg:tags":[
        "others"
    ],
    "wof:name":"G Abraham",
    "wof:placetype":"venue"
},
  "geometry": {"coordinates":[-1.47752,50.906658],"type":"Point"}
}