{
  "type": "Feature",
  "properties": {
    "addr:full":"Manchester Rd Nelson Lancashire BB9 7AL",
    "addr:postcode":"bb9 7al",
    "addr:street":"Manchester Rd",
    "iso:country":"GB",
    "sg:address":"Manchester Rd",
    "sg:city":"Nelson",
    "sg:classifiers":[
        {
            "category":"Retail",
            "subcategory":"Auto Repair",
            "type":"Services"
        }
    ],
    "sg:phone":"+44 1282 616771",
    "sg:postcode":"BB9 7AL",
    "sg:province":"Lancashire",
    "sg:tags":[
        "modification",
        "garage"
    ],
    "wof:name":"Churchills",
    "wof:placetype":"venue"
},
  "geometry": {"coordinates":[-2.2155690193,53.836151123],"type":"Point"}
}