{
  "type": "Feature",
  "properties": {
    "addr:full":"Kimbolton Ct Peterborough Cambridgeshire PE1 2NX",
    "addr:postcode":"pe1 2nx",
    "addr:street":"Kimbolton Ct",
    "iso:country":"GB",
    "sg:address":"Kimbolton Ct",
    "sg:city":"Peterborough",
    "sg:classifiers":[
        {
            "category":"Social Services",
            "subcategory":"Adult Care",
            "type":"Services"
        }
    ],
    "sg:phone":"+44 1733 346850",
    "sg:postcode":"PE1 2NX",
    "sg:province":"Cambridgeshire",
    "sg:tags":[
        "housing",
        "sheltered"
    ],
    "wof:name":"Haven Management Services Ltd",
    "wof:placetype":"venue"
},
  "geometry": {"coordinates":[-0.245289,52.580475],"type":"Point"}
}