{
  "type": "Feature",
  "properties": {
    "addr:full":"Dukeries Community College, Whinney La Newark Nottinghamshire NG22 9TD",
    "addr:postcode":"ng22 9td",
    "addr:street":"Whinney La Newark",
    "iso:country":"GB",
    "sg:address":"Dukeries Community College, Whinney La",
    "sg:city":"Newark",
    "sg:classifiers":[
        {
            "category":"Social Services",
            "type":"Services"
        }
    ],
    "sg:phone":"+44 1623 862363",
    "sg:postcode":"NG22 9TD",
    "sg:province":"Nottinghamshire",
    "wof:name":"Under Fives Family Centre",
    "wof:placetype":"venue"
},
  "geometry": {"coordinates":[-1.00071,53.208939],"type":"Point"}
}