{
  "type": "Feature",
  "properties": {
    "iso:country":"GB",
    "sg:address":"59 Old Park Lane",
    "sg:city":"Southport",
    "sg:classifiers":[
        {
            "category":"Home & Garden",
            "subcategory":"Building Materials",
            "type":"Retail Goods"
        },
        {
            "category":"Building & Trades",
            "subcategory":"Construction",
            "type":"Services"
        }
    ],
    "sg:phone":"+44 1704 224923",
    "sg:postcode":"PR9 7BQ",
    "sg:province":"Lancashire",
    "sg:tags":[
        "fencing",
        "contractor"
    ],
    "sg:website":"http://www.abramfencing.co.uk",
    "wof:name":"Abram Fencing",
    "wof:placetype":"venue"
},
  "geometry": {"coordinates":[-2.9673030376,53.6509246826],"type":"Point"}
}