{
  "type": "Feature",
  "properties": {
    "addr:full":"2 Centre Street Coatbridge North Lanarkshire ML5 2RY",
    "addr:housenumber":"2",
    "addr:postcode":"ml5 2ry",
    "addr:street":"Centre Street",
    "iso:country":"GB",
    "sg:address":"2 Centre Street",
    "sg:city":"Coatbridge",
    "sg:classifiers":[
        {
            "category":"Food & Beverages",
            "subcategory":"Supermarket",
            "type":"Retail Goods"
        }
    ],
    "sg:phone":"+44 1236 872530",
    "sg:postcode":"ML5 2RY",
    "sg:province":"North Lanarkshire",
    "wof:name":"Shop Wise",
    "wof:placetype":"venue"
},
  "geometry": {"coordinates":[-4.0574622154,55.8966217041],"type":"Point"}
}