{
  "type": "Feature",
  "properties": {
    "addr:full":"67 Fore Street Redruth Cornwall TR15 2AF",
    "addr:housenumber":"67",
    "addr:postcode":"tr15 2af",
    "addr:street":"Fore Street",
    "iso:country":"GB",
    "sg:address":"67 Fore Street",
    "sg:city":"Redruth",
    "sg:classifiers":[
        {
            "category":"Organizations",
            "subcategory":"Non-profit Organization",
            "type":"Services"
        }
    ],
    "sg:phone":"+44 1209 313253",
    "sg:postcode":"TR15 2AF",
    "sg:province":"Cornwall",
    "sg:tags":[
        "organisation",
        "voluntary",
        "charity"
    ],
    "wof:name":"Save the Children Fund",
    "wof:placetype":"venue"
},
  "geometry": {"coordinates":[-5.227037,50.233566],"type":"Point"}
}