{
  "type": "Feature",
  "properties": {
    "iso:country":"GB",
    "sg:address":"3 Marina Gardens",
    "sg:city":"Felixstowe",
    "sg:classifiers":[
        {
            "category":"Professional",
            "subcategory":"Business Services",
            "type":"Services"
        }
    ],
    "sg:phone":"+44 1394 286438",
    "sg:postcode":"IP11 2HW",
    "sg:province":"Suffolk",
    "sg:tags":[
        "shop",
        "cleaning"
    ],
    "wof:name":"C J Hembling",
    "wof:placetype":"venue"
},
  "geometry": {"coordinates":[1.337801,51.955101],"type":"Point"}
}