{
  "type": "Feature",
  "properties": {
    "addr:full":"526 Gibbet Street Halifax West Yorkshire HX2 0AH",
    "addr:housenumber":"526",
    "addr:postcode":"hx2 0ah",
    "addr:street":"Gibbet Street",
    "iso:country":"GB",
    "sg:address":"526 Gibbet Street",
    "sg:city":"Halifax",
    "sg:classifiers":[
        {
            "category":"Personal",
            "subcategory":"Beauty Salon",
            "type":"Services"
        }
    ],
    "sg:phone":"+44 1422 359814",
    "sg:postcode":"HX2 0AH",
    "sg:province":"West Yorkshire",
    "sg:tags":[
        "lady",
        "hairdresser"
    ],
    "wof:name":"Silvia's",
    "wof:placetype":"venue"
},
  "geometry": {"coordinates":[-1.8998049498,53.7235374451],"type":"Point"}
}