{
  "type": "Feature",
  "properties": {
    "iso:country":"GB",
    "sg:address":"Veterinary Surgery, 69 Christchurch Rd",
    "sg:city":"Ringwood",
    "sg:classifiers":[
        {
            "category":"Retail",
            "subcategory":"Veterinary Services",
            "type":"Services"
        }
    ],
    "sg:phone":"+44 1425 473683",
    "sg:postcode":"BH24 1DH",
    "sg:province":"Dorset",
    "sg:tags":[
        "surgeon"
    ],
    "wof:name":"C Trickey",
    "wof:placetype":"venue"
},
  "geometry": {"coordinates":[-1.7929890156,50.8463287354],"type":"Point"}
}