{
  "type": "Feature",
  "properties": {
    "iso:country":"GB",
    "sg:address":"27 Market Street",
    "sg:city":"Wirral",
    "sg:classifiers":[
        {
            "category":"Shopping",
            "subcategory":"Gifts & Souvenirs",
            "type":"Retail Goods"
        }
    ],
    "sg:postcode":"CH47 2BG",
    "sg:province":"Merseyside",
    "sg:tags":[
        "giftware"
    ],
    "wof:name":"Designer Crafts",
    "wof:placetype":"venue"
},
  "geometry": {"coordinates":[-3.177036047,53.3929481506],"type":"Point"}
}