{
  "type": "Feature",
  "properties": {
    "iso:country":"GB",
    "sg:address":"Blays House, Churchfield Road, Chalfont St Peter",
    "sg:city":"Gerrards Cross",
    "sg:classifiers":[
        {
            "category":"Professional",
            "subcategory":"Art Services",
            "type":"Services"
        }
    ],
    "sg:phone":"+44 1753 893800",
    "sg:postcode":"SL9 9EW",
    "sg:province":"Buckinghamshire",
    "sg:tags":[
        "consultant",
        "design"
    ],
    "wof:name":"Ferro Design Ltd",
    "wof:placetype":"venue"
},
  "geometry": {"coordinates":[-0.5576589704,51.6074028015],"type":"Point"}
}