{
  "type": "Feature",
  "properties": {
    "iso:country":"GB",
    "sg:address":"7 Stoneleigh Broadway",
    "sg:city":"Epsom",
    "sg:classifiers":[
        {
            "category":"Personal",
            "subcategory":"Beauty Salon",
            "type":"Services"
        },
        {
            "category":"Personal",
            "subcategory":"Barber",
            "type":"Services"
        }
    ],
    "sg:phone":"+44 20 8393 7360",
    "sg:postcode":"KT17 2JA",
    "sg:province":"Surrey",
    "sg:tags":[
        "unisex",
        "hairdresser"
    ],
    "wof:name":"New Image",
    "wof:placetype":"venue"
},
  "geometry": {"coordinates":[-0.2496290058,51.365688324],"type":"Point"}
}