{
  "type": "Feature",
  "properties": {
    "addr:full":"International Ho, 174 Three Bridges Rd Crawley Surrey RH10 1LE",
    "addr:housenumber":"174",
    "addr:postcode":"rh10 1le",
    "addr:street":"Three Bridges Rd",
    "iso:country":"GB",
    "sg:address":"International Ho, 174 Three Bridges Rd",
    "sg:city":"Crawley",
    "sg:classifiers":[
        {
            "category":"Professional",
            "subcategory":"Detective & Security Services",
            "type":"Services"
        }
    ],
    "sg:phone":"+44 1293 449633",
    "sg:postcode":"RH10 1LE",
    "sg:province":"Surrey",
    "sg:tags":[
        "agency"
    ],
    "wof:name":"Peregrine Consultants Ltd",
    "wof:placetype":"venue"
},
  "geometry": {"coordinates":[-0.1847530007,51.1184577942],"type":"Point"}
}