{
  "type": "Feature",
  "properties": {
    "iso:country":"GB",
    "sg:address":"Greenvilla The Grn",
    "sg:city":"Denbigh",
    "sg:classifiers":[
        {
            "category":"Building & Trades",
            "subcategory":"Cleaning & Sanitation",
            "type":"Services"
        }
    ],
    "sg:postcode":"LL16 5TN",
    "sg:province":"Conwy",
    "sg:tags":[
        "sweep",
        "chimney"
    ],
    "wof:name":"Jimmy H Gilmore",
    "wof:placetype":"venue"
},
  "geometry": {"coordinates":[-3.4211490154,53.1834106445],"type":"Point"}
}