{
  "type": "Feature",
  "properties": {
    "addr:full":"13 Burnley Rd, Luddendenfoot Halifax West Yorkshire HX2 6AA",
    "addr:housenumber":"13",
    "addr:postcode":"hx2 6aa",
    "addr:street":"Burnley Rd",
    "iso:country":"GB",
    "sg:address":"13 Burnley Rd, Luddendenfoot",
    "sg:city":"Halifax",
    "sg:classifiers":[
        {
            "category":"Health Services",
            "subcategory":"Health Practitioner",
            "type":"Services"
        },
        {
            "category":"Shopping",
            "subcategory":"Pharmacy",
            "type":"Retail Goods"
        }
    ],
    "sg:phone":"+44 1422 882791",
    "sg:postcode":"HX2 6AA",
    "sg:province":"West Yorkshire",
    "sg:tags":[
        "medicine",
        "medical",
        "therapy",
        "treatment",
        "alternative"
    ],
    "wof:name":"Pennine Natural Healing Centre Ltd (The)",
    "wof:placetype":"venue"
},
  "geometry": {"coordinates":[-1.9436210394,53.7207832336],"type":"Point"}
}