{
  "type": "Feature",
  "properties": {
    "addr:full":"2 Old Mill Cottage, Tilbury Road Brentwood Essex CM13 3LU",
    "addr:housenumber":"2",
    "addr:postcode":"cm13 3lu",
    "addr:street":"Old;Tilbury Road",
    "iso:country":"GB",
    "sg:address":"2 Old Mill Cottage, Tilbury Road",
    "sg:city":"Brentwood",
    "sg:classifiers":[
        {
            "category":"Home & Garden",
            "subcategory":"Building Materials",
            "type":"Retail Goods"
        }
    ],
    "sg:phone":"+44 1277 810828",
    "sg:postcode":"CM13 3LU",
    "sg:province":"Essex",
    "sg:tags":[
        "fencing"
    ],
    "wof:name":"Middleton Services",
    "wof:placetype":"venue"
},
  "geometry": {"coordinates":[0.35829,51.56987],"type":"Point"}
}