{
  "type": "Feature",
  "properties": {
    "addr:full":"11 Dinsdale Road Sunderland Tyne and Wear SR6 9TF",
    "addr:housenumber":"11",
    "addr:postcode":"sr6 9tf",
    "addr:street":"Dinsdale Road",
    "iso:country":"GB",
    "sg:address":"11 Dinsdale Road",
    "sg:city":"Sunderland",
    "sg:classifiers":[
        {
            "category":"Professional",
            "subcategory":"Detective & Security Services",
            "type":"Services"
        }
    ],
    "sg:postcode":"SR6 9TF",
    "sg:province":"Tyne and Wear",
    "wof:name":"Armour Security & Protection",
    "wof:placetype":"venue"
},
  "geometry": {"coordinates":[-1.372569,54.922646],"type":"Point"}
}