{
  "type": "Feature",
  "properties": {
    "addr:full":"Unit 3, Victoria Road Waterlooville Hampshire PO7 7ET",
    "addr:housenumber":"unit 3",
    "addr:postcode":"po7 7et",
    "addr:street":"Victoria Road",
    "iso:country":"GB",
    "sg:address":"Unit 3, Victoria Road",
    "sg:city":"Waterlooville",
    "sg:classifiers":[
        {
            "category":"Autos & Motor Vehicles",
            "subcategory":"Auto Supplies",
            "type":"Retail Goods"
        }
    ],
    "sg:postcode":"PO7 7ET",
    "sg:province":"Hampshire",
    "sg:tags":[
        "tyre"
    ],
    "wof:name":"Tony's Tyres",
    "wof:placetype":"venue"
},
  "geometry": {"coordinates":[-1.0333089828,50.8781700134],"type":"Point"}
}