{
  "type": "Feature",
  "properties": {
    "iso:country":"GB",
    "sg:address":"18 Beckford",
    "sg:city":"Washington",
    "sg:classifiers":[
        {
            "category":"Home & Garden",
            "subcategory":"Household Appliances",
            "type":"Retail Goods"
        }
    ],
    "sg:phone":"+44 191 416 2477",
    "sg:postcode":"NE38 8TP",
    "sg:province":"Durham",
    "sg:tags":[
        "electrical"
    ],
    "wof:name":"A+ Domesticss",
    "wof:placetype":"venue"
},
  "geometry": {"coordinates":[-1.4949940443,54.8955497742],"type":"Point"}
}