{
  "type": "Feature",
  "properties": {
    "iso:country":"GB",
    "sg:address":"16 Paris Street",
    "sg:city":"Exeter",
    "sg:classifiers":[
        {
            "category":"Personal",
            "subcategory":"Nail Salon",
            "type":"Services"
        }
    ],
    "sg:phone":"+44 1392 427721",
    "sg:postcode":"EX1 2JR",
    "sg:province":"Devon",
    "sg:tags":[
        "solarium",
        "tanning"
    ],
    "wof:name":"The Tanning Shop Ltd.",
    "wof:placetype":"venue"
},
  "geometry": {"coordinates":[-3.526277,50.725006],"type":"Point"}
}