{
  "type": "Feature",
  "properties": {
    "addr:full":"97 High Street Uttoxeter Derbyshire ST14 7JJ",
    "addr:housenumber":"97",
    "addr:postcode":"st14 7jj",
    "addr:street":"High Street",
    "iso:country":"GB",
    "sg:address":"97 High Street",
    "sg:city":"Uttoxeter",
    "sg:classifiers":[
        {
            "category":"Government",
            "subcategory":"Post Office",
            "type":"Public Place"
        }
    ],
    "sg:postcode":"ST14 7JJ",
    "sg:province":"Derbyshire",
    "wof:name":"Uttoxeter Heath Post Office",
    "wof:placetype":"venue"
},
  "geometry": {"coordinates":[-1.866569,52.90258],"type":"Point"}
}