{
  "type": "Feature",
  "properties": {
    "iso:country":"GB",
    "sg:address":"15 Market Square",
    "sg:city":"Bishops Stortford",
    "sg:classifiers":[
        {
            "category":"Professional",
            "subcategory":"Employment Agencies",
            "type":"Services"
        }
    ],
    "sg:phone":"+44 1279 465655",
    "sg:postcode":"CM23 3UT",
    "sg:province":"Essex",
    "sg:tags":[
        "consultant"
    ],
    "wof:name":"Parkwood Healthcare Ltd",
    "wof:placetype":"venue"
},
  "geometry": {"coordinates":[0.158394,51.871178],"type":"Point"}
}