{
  "type": "Feature",
  "properties": {
    "addr:full":"26 Swan St Warwick Warwickshire CV34 4BJ",
    "addr:housenumber":"26",
    "addr:postcode":"cv34 4bj",
    "addr:street":"Swan St",
    "iso:country":"GB",
    "sg:address":"26 Swan St",
    "sg:city":"Warwick",
    "sg:classifiers":[
        {
            "category":"Home & Garden",
            "subcategory":"Furniture",
            "type":"Retail Goods"
        }
    ],
    "sg:postcode":"CV34 4BJ",
    "sg:province":"Warwickshire",
    "wof:name":"Cheetham,Barrie,",
    "wof:placetype":"venue"
},
  "geometry": {"coordinates":[-1.589291,52.281513],"type":"Point"}
}