{
  "type": "Feature",
  "properties": {
    "addr:full":"Cropston Road, Anstey Leicester Leicestershire LE7 7BP",
    "addr:postcode":"le7 7bp",
    "addr:street":"Cropston Road",
    "iso:country":"GB",
    "sg:address":"Cropston Road, Anstey",
    "sg:city":"Leicester",
    "sg:classifiers":[
        {
            "category":"Organizations",
            "subcategory":"Membership Organization",
            "type":"Services"
        }
    ],
    "sg:phone":"+44 116 236 4868",
    "sg:postcode":"LE7 7BP",
    "sg:province":"Leicestershire",
    "sg:tags":[
        "club"
    ],
    "wof:name":"Anstey Nomads Football Club",
    "wof:placetype":"venue"
},
  "geometry": {"coordinates":[-1.179146,52.679276],"type":"Point"}
}