{
  "type": "Feature",
  "properties": {
    "addr:full":"Dinmore Av Blackpool Lancashire FY3 7RW",
    "addr:postcode":"fy3 7rw",
    "addr:street":"Dinmore Av",
    "iso:country":"GB",
    "sg:address":"Dinmore Av",
    "sg:city":"Blackpool",
    "sg:classifiers":[
        {
            "category":"Health Services",
            "subcategory":"Doctor",
            "type":"Services"
        }
    ],
    "sg:phone":"+44 1253 302794",
    "sg:postcode":"FY3 7RW",
    "sg:province":"Lancashire",
    "sg:tags":[
        "practitioners"
    ],
    "wof:name":"Bedell, J",
    "wof:placetype":"venue"
},
  "geometry": {"coordinates":[-3.0141289234,53.8355064392],"type":"Point"}
}