{
  "type": "Feature",
  "properties": {
    "addr:full":"14 Queen Elizabeth Ii Square, South Woodham Ferrers Chelmsford Essex CM3 5TD",
    "addr:housenumber":"14",
    "addr:postcode":"cm3 5td",
    "addr:street":"Queen Elizabeth Ii Square South",
    "iso:country":"GB",
    "sg:address":"14 Queen Elizabeth Ii Square, South Woodham Ferrers",
    "sg:city":"Chelmsford",
    "sg:classifiers":[
        {
            "category":"Shopping",
            "subcategory":"Pharmacy",
            "type":"Retail Goods"
        }
    ],
    "sg:phone":"+44 1245 321910",
    "sg:postcode":"CM3 5TD",
    "sg:province":"Essex",
    "sg:tags":[
        "pharmacist",
        "chemist"
    ],
    "wof:name":"Govani (Molend)",
    "wof:placetype":"venue"
},
  "geometry": {"coordinates":[0.61747998,51.6441383362],"type":"Point"}
}