{
  "type": "Feature",
  "properties": {
    "addr:full":"67 Oakley Road Bromley Kent BR2 8HD",
    "addr:housenumber":"67",
    "addr:postcode":"br2 8hd",
    "addr:street":"Oakley Road",
    "iso:country":"GB",
    "sg:address":"67 Oakley Road",
    "sg:city":"Bromley",
    "sg:classifiers":[
        {
            "category":"Professional",
            "type":"Services"
        }
    ],
    "sg:phone":"+44 1689 861362",
    "sg:postcode":"BR2 8HD",
    "sg:province":"Kent",
    "sg:tags":[
        "display",
        "maker"
    ],
    "wof:name":"The Display House",
    "wof:placetype":"venue"
},
  "geometry": {"coordinates":[0.03934,51.370049],"type":"Point"}
}