{
  "type": "Feature",
  "properties": {
    "iso:country":"GB",
    "sg:address":"Carpenters Lodge, St. Nicolas La",
    "sg:city":"Chislehurst",
    "sg:classifiers":[
        {
            "category":"Building & Trades",
            "subcategory":"Construction",
            "type":"Services"
        }
    ],
    "sg:postcode":"BR7 5LL",
    "sg:province":"Kent",
    "sg:tags":[
        "builder"
    ],
    "wof:name":"Carpentar,C,& Sons",
    "wof:placetype":"venue"
},
  "geometry": {"coordinates":[0.06639,51.419285],"type":"Point"}
}