{
  "type": "Feature",
  "properties": {
    "iso:country":"GB",
    "sg:address":"Ringwood Road, Woodlands",
    "sg:city":"Southampton",
    "sg:classifiers":[
        {
            "category":"Education",
            "subcategory":"School",
            "type":"Public Place"
        }
    ],
    "sg:phone":"+44 23 8086 2009",
    "sg:postcode":"SO40 7GY",
    "sg:province":"Hampshire",
    "sg:tags":[
        "local",
        "authority"
    ],
    "wof:name":"Netley Marsh C of E Infant School",
    "wof:placetype":"venue"
},
  "geometry": {"coordinates":[-1.5423389673,50.9040603638],"type":"Point"}
}