{
  "type": "Feature",
  "properties": {
    "addr:full":"High Bickerton Umberleigh Devon EX37 9AY",
    "addr:postcode":"ex37 9ay",
    "iso:country":"GB",
    "sg:address":"High Bickerton",
    "sg:city":"Umberleigh",
    "sg:classifiers":[
        {
            "category":"Education",
            "subcategory":"School",
            "type":"Public Place"
        }
    ],
    "sg:phone":"+44 1769 560324",
    "sg:postcode":"EX37 9AY",
    "sg:province":"Devon",
    "sg:tags":[
        "local",
        "authority"
    ],
    "wof:name":"High Bickerton Primary School",
    "wof:placetype":"venue"
},
  "geometry": {"coordinates":[-3.9853448868,50.9958152771],"type":"Point"}
}