{
  "type": "Feature",
  "properties": {
    "addr:full":"77 Ronelean Road, Tolworth Surbiton Surrey KT6 7LL",
    "addr:housenumber":"77",
    "addr:postcode":"kt6 7ll",
    "addr:street":"Ronelean Road",
    "iso:country":"GB",
    "sg:address":"77 Ronelean Road, Tolworth",
    "sg:city":"Surbiton",
    "sg:classifiers":[
        {
            "category":"Professional",
            "subcategory":"Engineering",
            "type":"Services"
        }
    ],
    "sg:phone":"+44 20 8397 8001",
    "sg:postcode":"KT6 7LL",
    "sg:province":"Surrey",
    "sg:tags":[
        "contractor",
        "electrical",
        "engineer"
    ],
    "wof:name":"Ken Gower Electrician",
    "wof:placetype":"venue"
},
  "geometry": {"coordinates":[-0.2984080017,51.376335144],"type":"Point"}
}