{
  "type": "Feature",
  "properties": {
    "iso:country":"GB",
    "sg:address":"103-105 High St",
    "sg:city":"Edinburgh",
    "sg:classifiers":[
        {
            "category":"Cafe",
            "type":"Food & Drink"
        }
    ],
    "sg:phone":"+44 131 558 3083",
    "sg:postcode":"EH1 1SG",
    "sg:province":"City of Edinburgh",
    "sg:tags":[
        "tea",
        "room"
    ],
    "wof:name":"Gustos",
    "wof:placetype":"venue"
},
  "geometry": {"coordinates":[-3.188509,55.949169],"type":"Point"}
}