{
  "type": "Feature",
  "properties": {
    "iso:country":"GB",
    "sg:address":"212-214 Maidstone Road",
    "sg:city":"Rochester",
    "sg:classifiers":[
        {
            "category":"Food & Beverages",
            "subcategory":"Liquor & Beverages",
            "type":"Retail Goods"
        }
    ],
    "sg:phone":"+44 1634 841254",
    "sg:postcode":"ME1 3LP",
    "sg:province":"Kent",
    "sg:tags":[
        "beer",
        "spirit",
        "wines"
    ],
    "wof:name":"The Wine Cellar",
    "wof:placetype":"venue"
},
  "geometry": {"coordinates":[0.499303,51.368019],"type":"Point"}
}