{
  "type": "Feature",
  "properties": {
    "iso:country":"GB",
    "sg:address":"725 Green Lane, Winchmore Hill",
    "sg:city":"Winchmore Hill",
    "sg:classifiers":[
        {
            "category":"Professional",
            "subcategory":"Accounting & Tax Preparation",
            "type":"Services"
        }
    ],
    "sg:phone":"+44 1920 484297",
    "sg:postcode":"N21 3RX",
    "sg:province":"Greater London",
    "sg:tags":[
        "accountant"
    ],
    "wof:name":"Adam Armsby Chartered Accountant",
    "wof:placetype":"venue"
},
  "geometry": {"coordinates":[-0.096536,51.631016],"type":"Point"}
}