{
  "type": "Feature",
  "properties": {
    "iso:country":"GB",
    "sg:address":"Unit 19, Donkin Rd, Armstrong",
    "sg:city":"Washington",
    "sg:classifiers":[
        {
            "category":"Building & Trades",
            "subcategory":"Construction",
            "type":"Services"
        }
    ],
    "sg:phone":"+44 191 415 4700",
    "sg:postcode":"NE37 1PF",
    "sg:province":"Tyne and Wear",
    "sg:tags":[
        "window",
        "replacement"
    ],
    "wof:name":"21st Century Windows & Home Improvements Ltd",
    "wof:placetype":"venue"
},
  "geometry": {"coordinates":[-1.549578,54.909306],"type":"Point"}
}