{
  "type": "Feature",
  "properties": {
    "iso:country":"GB",
    "sg:address":"57 Heanor Road",
    "sg:city":"Ilkeston",
    "sg:classifiers":[
        {
            "category":"Professional",
            "subcategory":"Accounting & Tax Preparation",
            "type":"Services"
        }
    ],
    "sg:postcode":"DE7 8DY",
    "sg:province":"Derbyshire",
    "sg:tags":[
        "consultant"
    ],
    "wof:name":"White Knight (Derbyshire)",
    "wof:placetype":"venue"
},
  "geometry": {"coordinates":[-1.312164,52.980656],"type":"Point"}
}