{
  "type": "Feature",
  "properties": {
    "addr:full":"12 Wellington Crescent, Kirkton Dumfries Dumfries and Galloway DG1 1SP",
    "addr:housenumber":"12",
    "addr:postcode":"dg1 1sp",
    "addr:street":"Wellington Crescent",
    "iso:country":"GB",
    "sg:address":"12 Wellington Crescent, Kirkton",
    "sg:city":"Dumfries",
    "sg:classifiers":[
        {
            "category":"Organizations",
            "subcategory":"Non-profit Organization",
            "type":"Services"
        }
    ],
    "sg:phone":"+44 1387 710083",
    "sg:postcode":"DG1 1SP",
    "sg:province":"Dumfries and Galloway",
    "sg:tags":[
        "organisation",
        "animal",
        "welfare"
    ],
    "wof:name":"Cats Protection",
    "wof:placetype":"venue"
},
  "geometry": {"coordinates":[-3.6103579998,55.1154403687],"type":"Point"}
}