{
  "type": "Feature",
  "properties": {
    "addr:full":"56 Fore Street Callington Cornwall PL17 7AQ",
    "addr:housenumber":"56",
    "addr:postcode":"pl17 7aq",
    "addr:street":"Fore Street",
    "iso:country":"GB",
    "sg:address":"56 Fore Street",
    "sg:city":"Callington",
    "sg:classifiers":[
        {
            "category":"Shopping",
            "subcategory":"Shoes",
            "type":"Retail Goods"
        }
    ],
    "sg:postcode":"PL17 7AQ",
    "sg:province":"Cornwall",
    "wof:name":"Andy's of Callington",
    "wof:placetype":"venue"
},
  "geometry": {"coordinates":[-4.3141059875,50.5028533936],"type":"Point"}
}