{
  "type": "Feature",
  "properties": {
    "addr:full":"1 Clayton Road Hayes Greater London UB3 1AX",
    "addr:housenumber":"1",
    "addr:postcode":"ub3 1ax",
    "addr:street":"Clayton Road",
    "iso:country":"GB",
    "sg:address":"1 Clayton Road",
    "sg:city":"Hayes",
    "sg:classifiers":[
        {
            "category":"Fast Food",
            "type":"Food & Drink"
        }
    ],
    "sg:phone":"+44 20 8573 1295",
    "sg:postcode":"UB3 1AX",
    "sg:province":"Greater London",
    "sg:tags":[
        "away",
        "take"
    ],
    "wof:name":"Sandwich Choice",
    "wof:placetype":"venue"
},
  "geometry": {"coordinates":[-0.4202310145,51.5043678284],"type":"Point"}
}