{
  "type": "Feature",
  "properties": {
    "addr:full":"Unit 2 Riverside Mill, George St Glossop Derbyshire SK13 8AY",
    "addr:housenumber":"unit 2",
    "addr:postcode":"sk13 8ay",
    "addr:street":"Riverside Mill George St",
    "iso:country":"GB",
    "sg:address":"Unit 2 Riverside Mill, George St",
    "sg:city":"Glossop",
    "sg:classifiers":[
        {
            "category":"Personal",
            "subcategory":"Nail Salon",
            "type":"Services"
        }
    ],
    "sg:phone":"+44 1457 868806",
    "sg:postcode":"SK13 8AY",
    "sg:province":"Derbyshire",
    "sg:tags":[
        "solarium",
        "tanning"
    ],
    "wof:name":"Tanfastic",
    "wof:placetype":"venue"
},
  "geometry": {"coordinates":[-1.9465700388,53.4433364868],"type":"Point"}
}