{
  "type": "Feature",
  "properties": {
    "addr:full":"35 Falmouth Road Truro Cornwall TR1 2BL",
    "addr:housenumber":"35",
    "addr:postcode":"tr1 2bl",
    "addr:street":"Falmouth Road",
    "iso:country":"GB",
    "sg:address":"35 Falmouth Road",
    "sg:city":"Truro",
    "sg:classifiers":[
        {
            "category":"Real Estate",
            "subcategory":"Architect",
            "type":"Services"
        }
    ],
    "sg:phone":"+44 1872 272067",
    "sg:postcode":"TR1 2BL",
    "sg:province":"Cornwall",
    "wof:name":"Michael Lasbury Associates",
    "wof:placetype":"venue"
},
  "geometry": {"coordinates":[-5.0553631783,50.2577972412],"type":"Point"}
}