{
  "type": "Feature",
  "properties": {
    "addr:full":"29 Play Street, Soham Ely Cambridgeshire CB7 5HJ",
    "addr:housenumber":"29",
    "addr:postcode":"cb7 5hj",
    "addr:street":"Play Street",
    "iso:country":"GB",
    "sg:address":"29 Play Street, Soham",
    "sg:city":"Ely",
    "sg:classifiers":[
        {
            "category":"Bars & Pubs",
            "type":"Food & Drink"
        }
    ],
    "sg:postcode":"CB7 5HJ",
    "sg:province":"Cambridgeshire",
    "sg:tags":[
        "pubs",
        "inn"
    ],
    "wof:name":"Alan Killick Surfacing Contractor",
    "wof:placetype":"venue"
},
  "geometry": {"coordinates":[0.3569400012,52.3179893494],"type":"Point"}
}