{
  "type": "Feature",
  "properties": {
    "iso:country":"GB",
    "sg:address":"29 Glenfield Road East",
    "sg:city":"Leicester",
    "sg:classifiers":[
        {
            "category":"Retail",
            "subcategory":"Veterinary Services",
            "type":"Services"
        }
    ],
    "sg:phone":"+44 116 251 7677",
    "sg:postcode":"LE3 5QW",
    "sg:province":"Leicestershire",
    "sg:tags":[
        "surgeon"
    ],
    "wof:name":"Thomason,John,",
    "wof:placetype":"venue"
},
  "geometry": {"coordinates":[-1.1520969868,52.63463974],"type":"Point"}
}