{
  "type": "Feature",
  "properties": {
    "iso:country":"GB",
    "sg:address":"Mill Cotts, Gt Chalfield",
    "sg:city":"Melksham",
    "sg:classifiers":[
        {
            "category":"Building & Trades",
            "subcategory":"Landscaping Services",
            "type":"Services"
        }
    ],
    "sg:postcode":"SN12 8NJ",
    "sg:province":"Wiltshire",
    "sg:tags":[
        "forestry",
        "tree"
    ],
    "wof:name":"Rice,David,",
    "wof:placetype":"venue"
},
  "geometry": {"coordinates":[-2.13560009,51.3740653992],"type":"Point"}
}