{
  "type": "Feature",
  "properties": {
    "addr:full":"Old Luxters Henley On Thames Berkshire RG9 6JW",
    "addr:postcode":"rg9 6jw",
    "iso:country":"GB",
    "sg:address":"Old Luxters",
    "sg:city":"Henley On Thames",
    "sg:classifiers":[
        {
            "category":"Arts & Performance",
            "subcategory":"Art Gallery",
            "type":"Entertainment"
        }
    ],
    "sg:phone":"+44 1491 638816",
    "sg:postcode":"RG9 6JW",
    "sg:province":"Berkshire",
    "wof:name":"Luxters Fine Art",
    "wof:placetype":"venue"
},
  "geometry": {"coordinates":[-0.903189,51.535297],"type":"Point"}
}