{
  "type": "Feature",
  "properties": {
    "iso:country":"GB",
    "sg:address":"59 Stanstead Rd",
    "sg:city":"Hoddesdon",
    "sg:classifiers":[
        {
            "category":"Freight",
            "type":"Transportation"
        }
    ],
    "sg:postcode":"EN11 0PR",
    "sg:province":"Essex",
    "sg:tags":[
        "haulage",
        "road"
    ],
    "wof:name":"Eggenton,James M,",
    "wof:placetype":"venue"
},
  "geometry": {"coordinates":[-0.006579,51.76992],"type":"Point"}
}