{
  "type": "Feature",
  "properties": {
    "addr:full":"High Street Wanstead Greater London E11 2RH",
    "addr:postcode":"e11 2rh",
    "addr:street":"High Street",
    "iso:country":"GB",
    "sg:address":"High Street",
    "sg:city":"Wanstead",
    "sg:classifiers":[
        {
            "category":"Restaurant",
            "type":"Food & Drink"
        }
    ],
    "sg:phone":"+44 20 8989 5757",
    "sg:postcode":"E11 2RH",
    "sg:province":"Greater London",
    "sg:tags":[
        "indian"
    ],
    "wof:name":"Provini Indian Cuisine",
    "wof:placetype":"venue"
},
  "geometry": {"coordinates":[0.0275669992,51.5762786865],"type":"Point"}
}