{
  "type": "Feature",
  "properties": {
    "addr:full":"129 Bournemouth Road Poole Dorset BH14 9HR",
    "addr:housenumber":"129",
    "addr:postcode":"bh14 9hr",
    "addr:street":"Bournemouth Road",
    "iso:country":"GB",
    "sg:address":"129 Bournemouth Road",
    "sg:city":"Poole",
    "sg:classifiers":[
        {
            "category":"Fast Food",
            "type":"Food & Drink"
        }
    ],
    "sg:phone":"+44 1202 743838",
    "sg:postcode":"BH14 9HR",
    "sg:province":"Dorset",
    "sg:tags":[
        "away",
        "meal",
        "outlet",
        "take"
    ],
    "wof:name":"RONALD LUKE",
    "wof:placetype":"venue"
},
  "geometry": {"coordinates":[-1.9373780489,50.7247581482],"type":"Point"}
}