{
  "type": "Feature",
  "properties": {
    "iso:country":"GB",
    "sg:address":"Metheringham Depot, Sleaford Road Metheringham",
    "sg:city":"Lincoln",
    "sg:classifiers":[
        {
            "category":"Utilities",
            "subcategory":"Refuse",
            "type":"Services"
        }
    ],
    "sg:phone":"+44 1526 321888",
    "sg:postcode":"LN4 3DG",
    "sg:province":"Lincolnshire",
    "sg:tags":[
        "disposal",
        "waste",
        "retail"
    ],
    "wof:name":"North Kesteven District Council Direct Services",
    "wof:placetype":"venue"
},
  "geometry": {"coordinates":[-0.4050700068,53.1418952942],"type":"Point"}
}