{
  "type": "Feature",
  "properties": {
    "iso:country":"GB",
    "sg:address":"66 King Street",
    "sg:city":"Southall",
    "sg:classifiers":[
        {
            "category":"Health Services",
            "subcategory":"Dentist",
            "type":"Services"
        }
    ],
    "sg:phone":"+44 20 8574 2505",
    "sg:postcode":"UB2 4DD",
    "sg:province":"Greater London",
    "wof:name":"SURINDER GHALLEY",
    "wof:placetype":"venue"
},
  "geometry": {"coordinates":[-0.38308,51.500603],"type":"Point"}
}