{
  "type": "Feature",
  "properties": {
    "iso:country":"GB",
    "sg:address":"6 Hargreaves Street",
    "sg:city":"Burnley",
    "sg:classifiers":[
        {
            "category":"Personal",
            "subcategory":"Beauty Salon",
            "type":"Services"
        },
        {
            "category":"Personal",
            "subcategory":"Barber",
            "type":"Services"
        }
    ],
    "sg:phone":"+44 1282 422660",
    "sg:postcode":"BB11 1EA",
    "sg:province":"Lancashire",
    "sg:tags":[
        "unisex",
        "hairdresser"
    ],
    "wof:name":"Image Hair Studio",
    "wof:placetype":"venue"
},
  "geometry": {"coordinates":[-2.2441020012,53.7883033752],"type":"Point"}
}