{
  "type": "Feature",
  "properties": {
    "addr:full":"North Road, Stokesley Middlesbrough North Yorkshire TS9 5DY",
    "addr:postcode":"ts9 5dy",
    "addr:street":"North Road",
    "iso:country":"GB",
    "sg:address":"North Road, Stokesley",
    "sg:city":"Middlesbrough",
    "sg:classifiers":[
        {
            "category":"Bus Charters",
            "type":"Transportation"
        }
    ],
    "sg:phone":"+44 1642 710324",
    "sg:postcode":"TS9 5DY",
    "sg:province":"North Yorkshire",
    "sg:tags":[
        "coach"
    ],
    "wof:name":"Arriva Tees & District Ltd.",
    "wof:placetype":"venue"
},
  "geometry": {"coordinates":[-1.1887899637,54.470703125],"type":"Point"}
}