{
  "type": "Feature",
  "properties": {
    "iso:country":"GB",
    "sg:address":"Radway Stores, Radway Place",
    "sg:city":"Sidmouth",
    "sg:classifiers":[
        {
            "category":"Food & Beverages",
            "subcategory":"Fruits & Vegetables",
            "type":"Retail Goods"
        }
    ],
    "sg:postcode":"EX10 8TL",
    "sg:province":"Devon",
    "sg:tags":[
        "greengrocer"
    ],
    "wof:name":"Rodney Rogers",
    "wof:placetype":"venue"
},
  "geometry": {"coordinates":[-3.237619,50.68745],"type":"Point"}
}