{
  "type": "Feature",
  "properties": {
    "iso:country":"GB",
    "sg:address":"Birch Hall, Kirby-le-soken",
    "sg:city":"Frinton-on-sea",
    "sg:classifiers":[
        {
            "category":"Farming",
            "subcategory":"Dairy Farm",
            "type":"Manufacturing & Wholesale Goods"
        }
    ],
    "sg:postcode":"CO13 0EL",
    "sg:province":"Essex",
    "wof:name":"Flemings Farm Dairy",
    "wof:placetype":"venue"
},
  "geometry": {"coordinates":[1.241911,51.838032],"type":"Point"}
}