{
  "type": "Feature",
  "properties": {
    "iso:country":"GB",
    "sg:address":"16 Station Road East",
    "sg:city":"Oxted",
    "sg:classifiers":[
        {
            "category":"Shopping",
            "subcategory":"Comic Books",
            "type":"Retail Goods"
        }
    ],
    "sg:phone":"+44 1883 714837",
    "sg:postcode":"RH8 0PG",
    "sg:province":"Surrey",
    "sg:tags":[
        "jeweller"
    ],
    "wof:name":"Walsh Bros",
    "wof:placetype":"venue"
},
  "geometry": {"coordinates":[-0.001352,51.257366],"type":"Point"}
}