{
  "type": "Feature",
  "properties": {
    "addr:full":"53 Windmillhill Street Motherwell North Lanarkshire ML1 1RY",
    "addr:housenumber":"53",
    "addr:postcode":"ml1 1ry",
    "addr:street":"Windmillhill Street",
    "iso:country":"GB",
    "sg:address":"53 Windmillhill Street",
    "sg:city":"Motherwell",
    "sg:classifiers":[
        {
            "category":"Shopping",
            "subcategory":"Mobile Phones",
            "type":"Retail Goods"
        }
    ],
    "sg:postcode":"ML1 1RY",
    "sg:province":"North Lanarkshire",
    "wof:name":"S O S Communications",
    "wof:placetype":"venue"
},
  "geometry": {"coordinates":[-3.9837169647,55.7857971191],"type":"Point"}
}