{
  "type": "Feature",
  "properties": {
    "iso:country":"GB",
    "sg:address":"School La",
    "sg:city":"Worcester",
    "sg:classifiers":[
        {
            "category":"Place Of Worship",
            "type":"Public Place"
        }
    ],
    "sg:phone":"+44 1684 592602",
    "sg:postcode":"WR8 0LA",
    "sg:province":"Gloucestershire",
    "wof:name":"St Josephs R C Church",
    "wof:placetype":"venue"
},
  "geometry": {"coordinates":[-2.216627,52.062412],"type":"Point"}
}