{
  "type": "Feature",
  "properties": {
    "iso:country":"GB",
    "sg:address":"15 The Centre, High St",
    "sg:city":"Margate",
    "sg:classifiers":[
        {
            "category":"Shopping",
            "subcategory":"Shoes",
            "type":"Retail Goods"
        }
    ],
    "sg:phone":"+44 1843 291450",
    "sg:postcode":"CT9 1JG",
    "sg:province":"Kent",
    "sg:tags":[
        "shop"
    ],
    "wof:name":"Curtess",
    "wof:placetype":"venue"
},
  "geometry": {"coordinates":[1.379247,51.386662],"type":"Point"}
}