{
  "type": "Feature",
  "properties": {
    "iso:country":"GB",
    "sg:address":"Meikle Barncleuch, Irongray",
    "sg:city":"Dumfries",
    "sg:classifiers":[
        {
            "category":"Farming",
            "subcategory":"Farm",
            "type":"Manufacturing & Wholesale Goods"
        }
    ],
    "sg:phone":"+44 1387 730229",
    "sg:postcode":"DG2 9SE",
    "sg:province":"Dumfries and Galloway",
    "sg:tags":[
        "mixed",
        "crop"
    ],
    "wof:name":"Grove Farm",
    "wof:placetype":"venue"
},
  "geometry": {"coordinates":[-3.699244,55.098095],"type":"Point"}
}