{
  "type": "Feature",
  "properties": {
    "iso:country":"GB",
    "sg:address":"Unit 20 Barnfield Busns Ctr, Brunswick Street",
    "sg:city":"Nelson",
    "sg:classifiers":[
        {
            "category":"Shopping",
            "subcategory":"Party Supplies",
            "type":"Retail Goods"
        },
        {
            "category":"Professional",
            "subcategory":"Advertising",
            "type":"Services"
        }
    ],
    "sg:phone":"+44 1282 617398",
    "sg:postcode":"BB9 0HT",
    "sg:province":"Lancashire",
    "sg:tags":[
        "marquees",
        "hire",
        "marquee",
        "tent",
        "floor"
    ],
    "wof:name":"Pennine Marquees",
    "wof:placetype":"venue"
},
  "geometry": {"coordinates":[-2.21334,53.835968],"type":"Point"}
}