{
  "type": "Feature",
  "properties": {
    "iso:country":"GB",
    "sg:address":"23 New Street",
    "sg:city":"Lymington",
    "sg:classifiers":[
        {
            "category":"Professional",
            "subcategory":"Art Services",
            "type":"Services"
        }
    ],
    "sg:postcode":"SO41 9BH",
    "sg:province":"Hampshire",
    "sg:tags":[
        "graphic",
        "designer"
    ],
    "wof:name":"Tinstar Design",
    "wof:placetype":"venue"
},
  "geometry": {"coordinates":[-1.542922,50.759258],"type":"Point"}
}