{
  "type": "Feature",
  "properties": {
    "iso:country":"GB",
    "sg:address":"Hawkchurch",
    "sg:city":"Axminster",
    "sg:classifiers":[
        {
            "category":"Recreation",
            "subcategory":"Campground",
            "type":"Entertainment"
        }
    ],
    "sg:phone":"+44 1297 678402",
    "sg:postcode":"EX13 5UL",
    "sg:province":"Devon",
    "sg:tags":[
        "holiday",
        "centre",
        "camp"
    ],
    "wof:name":"Hunters Moon Holiday Park",
    "wof:placetype":"venue"
},
  "geometry": {"coordinates":[-3.0005619526,50.7812767029],"type":"Point"}
}