{
  "type": "Feature",
  "properties": {
    "iso:country":"GB",
    "sg:address":"28 Roseburn Terrace",
    "sg:city":"Edinburgh",
    "sg:classifiers":[
        {
            "category":"Banks & Credit Unions",
            "subcategory":"Bank",
            "type":"Services"
        }
    ],
    "sg:phone":"+44 131 456 2700",
    "sg:postcode":"EH12 6AW",
    "sg:province":"City of Edinburgh",
    "wof:name":"Bank of Scotland",
    "wof:placetype":"venue"
},
  "geometry": {"coordinates":[-3.234586,55.945843],"type":"Point"}
}