{
  "type": "Feature",
  "properties": {
    "addr:full":"1 Cunninghame Road, Irvine Industrial Estate Irvine North Ayrshire KA12 8JJ",
    "addr:housenumber":"1",
    "addr:postcode":"ka12 8jj",
    "addr:street":"Cunninghame Road;Industrial Estate",
    "iso:country":"GB",
    "sg:address":"1 Cunninghame Road, Irvine Industrial Estate",
    "sg:city":"Irvine",
    "sg:classifiers":[
        {
            "category":"Fast Food",
            "type":"Food & Drink"
        }
    ],
    "sg:phone":"+44 1294 271400",
    "sg:postcode":"KA12 8JJ",
    "sg:province":"North Ayrshire",
    "sg:tags":[
        "away",
        "meal",
        "outlet",
        "take"
    ],
    "wof:name":"J & L's",
    "wof:placetype":"venue"
},
  "geometry": {"coordinates":[-4.67249,55.602734],"type":"Point"}
}