{
  "type": "Feature",
  "properties": {
    "addr:full":"Ingham House, Horsley Hill Road South Shields Tyne and Wear NE33 3DP",
    "addr:postcode":"ne33 3dp",
    "addr:street":"Horsley Hill Road",
    "iso:country":"GB",
    "sg:address":"Ingham House, Horsley Hill Road",
    "sg:city":"South Shields",
    "sg:classifiers":[
        {
            "category":"Government",
            "subcategory":"Office",
            "type":"Public Place"
        }
    ],
    "sg:phone":"+44 191 401 4500",
    "sg:postcode":"NE33 3DP",
    "sg:province":"Tyne and Wear",
    "sg:tags":[
        "central"
    ],
    "wof:name":"Gateshead & South Tyneside Health Authority",
    "wof:placetype":"venue"
},
  "geometry": {"coordinates":[-1.4148110151,54.9893417358],"type":"Point"}
}