{
  "type": "Feature",
  "properties": {
    "iso:country":"GB",
    "sg:address":"Barclay Curle House, 739 South Street",
    "sg:city":"Glasgow",
    "sg:classifiers":[
        {
            "category":"Manufacturing",
            "subcategory":"Tools & Machinery",
            "type":"Manufacturing & Wholesale Goods"
        },
        {
            "category":"Banks & Credit Unions",
            "subcategory":"Financial Services",
            "type":"Services"
        }
    ],
    "sg:postcode":"G14 0AH",
    "sg:province":"Glasgow City",
    "sg:tags":[
        "adviser",
        "friendly",
        "society"
    ],
    "wof:name":"Medical Assurance Bureau",
    "wof:placetype":"venue"
},
  "geometry": {"coordinates":[-4.346574,55.874966],"type":"Point"}
}