{
  "type": "Feature",
  "properties": {
    "addr:full":"22 Wates Way Mitcham Greater London CR4 4HR",
    "addr:housenumber":"22",
    "addr:postcode":"cr4 4hr",
    "addr:street":"Wates Way",
    "iso:country":"GB",
    "sg:address":"22 Wates Way",
    "sg:city":"Mitcham",
    "sg:classifiers":[
        {
            "category":"Wholesale",
            "subcategory":"Construction Materials",
            "type":"Manufacturing & Wholesale Goods"
        }
    ],
    "sg:phone":"+44 20 8646 6596",
    "sg:postcode":"CR4 4HR",
    "sg:province":"Greater London",
    "sg:tags":[
        "distributor",
        "spring"
    ],
    "wof:name":"Industrial Gas Springs Ltd.",
    "wof:placetype":"venue"
},
  "geometry": {"coordinates":[-0.1651269943,51.389831543],"type":"Point"}
}