{
  "type": "Feature",
  "properties": {
    "iso:country":"GB",
    "sg:address":"Habberley, Low Habberley",
    "sg:city":"Kidderminster",
    "sg:classifiers":[
        {
            "category":"Sports & Exercise",
            "subcategory":"Golf",
            "type":"Entertainment"
        }
    ],
    "sg:phone":"+44 1562 745756",
    "sg:postcode":"DY11 5RF",
    "sg:province":"Staffordshire",
    "sg:tags":[
        "club",
        "course"
    ],
    "wof:name":"Habberley Golf Club",
    "wof:placetype":"venue"
},
  "geometry": {"coordinates":[-2.286523,52.396969],"type":"Point"}
}