{
  "type": "Feature",
  "properties": {
    "addr:full":"5 Waterbeach Welwyn Garden City Hertfordshire AL7 2PT",
    "addr:housenumber":"5",
    "addr:postcode":"al7 2pt",
    "addr:street":"Waterbeach Welwyn",
    "iso:country":"GB",
    "sg:address":"5 Waterbeach",
    "sg:city":"Welwyn Garden City",
    "sg:classifiers":[
        {
            "category":"Professional",
            "subcategory":"Art Services",
            "type":"Services"
        }
    ],
    "sg:phone":"+44 1707 334599",
    "sg:postcode":"AL7 2PT",
    "sg:province":"Hertfordshire",
    "sg:tags":[
        "photographer"
    ],
    "wof:name":"Barrington Hill Photography",
    "wof:placetype":"venue"
},
  "geometry": {"coordinates":[-0.164971,51.800755],"type":"Point"}
}