{
  "type": "Feature",
  "properties": {
    "addr:full":"Viking Way, Winch Wen Industrial Estat, Winch Wen Swansea Neath Port Talbot SA1 7DA",
    "addr:postcode":"sa1 7da",
    "addr:street":"Viking Way",
    "iso:country":"GB",
    "sg:address":"Viking Way, Winch Wen Industrial Estat, Winch Wen",
    "sg:city":"Swansea",
    "sg:classifiers":[
        {
            "category":"Shopping",
            "subcategory":"Computers & Home Electronics",
            "type":"Retail Goods"
        }
    ],
    "sg:phone":"+44 1792 774777",
    "sg:postcode":"SA1 7DA",
    "sg:province":"Neath Port Talbot",
    "sg:tags":[
        "electrical"
    ],
    "wof:name":"A N Supplies",
    "wof:placetype":"venue"
},
  "geometry": {"coordinates":[-3.899971,51.650627],"type":"Point"}
}