{
  "type": "Feature",
  "properties": {
    "addr:full":"7 Priory Road Liverpool Merseyside L4 2RT",
    "addr:housenumber":"7",
    "addr:postcode":"l4 2rt",
    "addr:street":"Priory Road",
    "iso:country":"GB",
    "sg:address":"7 Priory Road",
    "sg:city":"Liverpool",
    "sg:classifiers":[
        {
            "category":"Health Services",
            "subcategory":"Dentist",
            "type":"Services"
        }
    ],
    "sg:phone":"+44 151 263 6414",
    "sg:postcode":"L4 2RT",
    "sg:province":"Merseyside",
    "wof:name":"PETRIE TUCKER & PARTNERS LTD",
    "wof:placetype":"venue"
},
  "geometry": {"coordinates":[-2.950182,53.428318],"type":"Point"}
}