{
  "type": "Feature",
  "properties": {
    "iso:country":"GB",
    "sg:address":"5 Waterside Business Park, Eastways",
    "sg:city":"Witham",
    "sg:classifiers":[
        {
            "category":"Manufacturing",
            "subcategory":"Buildings",
            "type":"Manufacturing & Wholesale Goods"
        },
        {
            "category":"Utilities",
            "subcategory":"Electric",
            "type":"Services"
        }
    ],
    "sg:phone":"+44 1376 503040",
    "sg:postcode":"CM8 3YQ",
    "sg:province":"Essex",
    "sg:tags":[
        "consultant",
        "system",
        "air conditioning"
    ],
    "sg:website":"http://www.halton.com",
    "wof:name":"Halton Products Ltd",
    "wof:placetype":"venue"
},
  "geometry": {"coordinates":[0.65287,51.810749],"type":"Point"}
}