{
  "type": "Feature",
  "properties": {
    "addr:full":"9-12 East Parade Sheffield South Yorkshire S1 2ET",
    "addr:housenumber":"9-12",
    "addr:postcode":"s1 2et",
    "addr:street":"East Parade",
    "iso:country":"GB",
    "sg:address":"9-12 East Parade",
    "sg:city":"Sheffield",
    "sg:classifiers":[
        {
            "category":"Professional",
            "subcategory":"Lawyer & Legal Services",
            "type":"Services"
        }
    ],
    "sg:postcode":"S1 2ET",
    "sg:province":"South Yorkshire",
    "sg:tags":[
        "solicitor"
    ],
    "wof:name":"Norrie Waite & Co.",
    "wof:placetype":"venue"
},
  "geometry": {"coordinates":[-1.468855,53.383209],"type":"Point"}
}