{
  "type": "Feature",
  "properties": {
    "iso:country":"GB",
    "sg:address":"18 Dean Lane",
    "sg:city":"Bristol",
    "sg:classifiers":[
        {
            "category":"Bars & Pubs",
            "type":"Food & Drink"
        }
    ],
    "sg:phone":"+44 117 940 9044",
    "sg:postcode":"BS3 1DD",
    "sg:province":"City of Bristol",
    "sg:tags":[
        "pubs",
        "inn"
    ],
    "wof:name":"The Coronation",
    "wof:placetype":"venue"
},
  "geometry": {"coordinates":[-2.600117,51.444344],"type":"Point"}
}