{
  "type": "Feature",
  "properties": {
    "addr:full":"Main A20 Road, Harrietsham Maidstone Kent ME17 1HN",
    "addr:postcode":"me17 1hn",
    "addr:street":"A20 Road",
    "iso:country":"GB",
    "sg:address":"Main A20 Road, Harrietsham",
    "sg:city":"Maidstone",
    "sg:classifiers":[
        {
            "category":"Education",
            "subcategory":"Music School",
            "type":"Public Place"
        },
        {
            "category":"Train Station",
            "subcategory":"Rail",
            "type":"Transportation"
        }
    ],
    "sg:phone":"+44 1622 859301",
    "sg:postcode":"ME17 1HN",
    "sg:province":"Kent",
    "sg:tags":[
        "caravan",
        "conservatory"
    ],
    "wof:name":"Lee Davey Caravans Ltd.",
    "wof:placetype":"venue"
},
  "geometry": {"coordinates":[0.5988190174,51.2650260925],"type":"Point"}
}