{
  "type": "Feature",
  "properties": {
    "addr:full":"2002 Bristol Road South, Rednal Birmingham West Midlands B45 9XS",
    "addr:housenumber":"2002",
    "addr:postcode":"9xs",
    "addr:street":"Bristol Road South Rednal",
    "iso:country":"GB",
    "sg:address":"2002 Bristol Road South, Rednal",
    "sg:city":"Birmingham",
    "sg:classifiers":[
        {
            "category":"Shopping",
            "subcategory":"Florist",
            "type":"Retail Goods"
        }
    ],
    "sg:postcode":"B45 9XS",
    "sg:province":"West Midlands",
    "wof:name":"Julie Anne Florists",
    "wof:placetype":"venue"
},
  "geometry": {"coordinates":[-2.011715889,52.3954086304],"type":"Point"}
}