{
  "type": "Feature",
  "properties": {
    "iso:country":"GB",
    "sg:address":"693 Rochdale Road, Middleton",
    "sg:city":"Manchester",
    "sg:classifiers":[
        {
            "category":"Bars & Pubs",
            "type":"Food & Drink"
        }
    ],
    "sg:phone":"+44 161 643 5871",
    "sg:postcode":"M24 2RN",
    "sg:province":"Greater Manchester",
    "sg:tags":[
        "pubs",
        "inn"
    ],
    "wof:name":"The Ship Inn",
    "wof:placetype":"venue"
},
  "geometry": {"coordinates":[-2.175442,53.57214],"type":"Point"}
}