{
  "type": "Feature",
  "properties": {
    "addr:full":"39 The Hastings Lancaster Lancashire LA1 4TF",
    "addr:housenumber":"39",
    "addr:postcode":"la1 4tf",
    "addr:street":"The Hastings",
    "iso:country":"GB",
    "sg:address":"39 The Hastings",
    "sg:city":"Lancaster",
    "sg:classifiers":[
        {
            "category":"Professional",
            "subcategory":"Art Services",
            "type":"Services"
        }
    ],
    "sg:phone":"+44 1524 846965",
    "sg:postcode":"LA1 4TF",
    "sg:province":"Lancashire",
    "sg:tags":[
        "graphic",
        "designer"
    ],
    "wof:name":"Taylored Design",
    "wof:placetype":"venue"
},
  "geometry": {"coordinates":[-2.796544075,54.017490387],"type":"Point"}
}