{
  "type": "Feature",
  "properties": {
    "iso:country":"GB",
    "sg:address":"1 Avenue Parade",
    "sg:city":"Accrington",
    "sg:classifiers":[
        {
            "category":"Health Services",
            "subcategory":"Dentist",
            "type":"Services"
        }
    ],
    "sg:phone":"+44 1254 871540",
    "sg:postcode":"BB5 6PN",
    "sg:province":"Lancashire",
    "wof:name":"Lawson Miss Lawson Mrs Griffiths & Griffiths BDS",
    "wof:placetype":"venue"
},
  "geometry": {"coordinates":[-2.3624780178,53.7540245056],"type":"Point"}
}