{
  "type": "Feature",
  "properties": {
    "iso:country":"GB",
    "sg:address":"Bromley",
    "sg:city":"Brierley Hill",
    "sg:classifiers":[
        {
            "category":"Education",
            "subcategory":"School",
            "type":"Public Place"
        },
        {
            "category":"Government",
            "subcategory":"Office",
            "type":"Public Place"
        }
    ],
    "sg:phone":"+44 1384 816865",
    "sg:postcode":"DY5 4PJ",
    "sg:province":"West Midlands",
    "sg:tags":[
        "local",
        "authority"
    ],
    "wof:name":"Bromley Primary School",
    "wof:placetype":"venue"
},
  "geometry": {"coordinates":[-2.137109,52.493015],"type":"Point"}
}