{
  "type": "Feature",
  "properties": {
    "addr:full":"17 Hill Street, Mayfair London Greater London W1J 5LJ",
    "addr:housenumber":"17",
    "addr:postcode":"w1j 5lj",
    "addr:street":"Hill Street",
    "iso:country":"GB",
    "sg:address":"17 Hill Street, Mayfair",
    "sg:city":"London",
    "sg:classifiers":[
        {
            "category":"Shopping",
            "subcategory":"Bicycles & Sporting Goods",
            "type":"Retail Goods"
        }
    ],
    "sg:phone":"+44 20 7495 5554",
    "sg:postcode":"W1J 5LJ",
    "sg:province":"Greater London",
    "sg:tags":[
        "water",
        "cooler"
    ],
    "wof:name":"Springtime Ltd.",
    "wof:placetype":"venue"
},
  "geometry": {"coordinates":[-0.148019,51.508736],"type":"Point"}
}