{
  "type": "Feature",
  "properties": {
    "iso:country":"GB",
    "sg:address":"82-84 Junction Road, Archway",
    "sg:city":"London",
    "sg:classifiers":[
        {
            "category":"Building & Trades",
            "subcategory":"Construction",
            "type":"Services"
        }
    ],
    "sg:phone":"+44 20 7272 8704",
    "sg:postcode":"N19 5QZ",
    "sg:province":"Greater London",
    "sg:tags":[
        "builder"
    ],
    "wof:name":"Clipfine Ltd.",
    "wof:placetype":"venue"
},
  "geometry": {"coordinates":[-0.13551,51.563278],"type":"Point"}
}