{
  "type": "Feature",
  "properties": {
    "addr:full":"Copthorne Common Road Crawley Surrey RH10 3PF",
    "addr:postcode":"rh10 3pf",
    "addr:street":"Common Road",
    "iso:country":"GB",
    "sg:address":"Copthorne Common Road",
    "sg:city":"Crawley",
    "sg:classifiers":[
        {
            "category":"Travel",
            "subcategory":"Hotels & Motels",
            "type":"Entertainment"
        }
    ],
    "sg:phone":"+44 1342 714422",
    "sg:postcode":"RH10 3PF",
    "sg:province":"Surrey",
    "sg:tags":[
        "house",
        "guest"
    ],
    "wof:name":"Kitsbridge House",
    "wof:placetype":"venue"
},
  "geometry": {"coordinates":[-0.10231,51.137051],"type":"Point"}
}