{
  "type": "Feature",
  "properties": {
    "addr:full":"93 Staines Road Hounslow Greater London TW3 3JB",
    "addr:housenumber":"93",
    "addr:postcode":"tw3 3jb",
    "addr:street":"Staines Road",
    "iso:country":"GB",
    "sg:address":"93 Staines Road",
    "sg:city":"Hounslow",
    "sg:classifiers":[
        {
            "category":"Wholesale",
            "subcategory":"Books, Periodicals, & Newspapers",
            "type":"Manufacturing & Wholesale Goods"
        }
    ],
    "sg:phone":"+44 20 8572 4141",
    "sg:postcode":"TW3 3JB",
    "sg:province":"Greater London",
    "sg:tags":[
        "publishing"
    ],
    "wof:name":"Hounslow Chronicle",
    "wof:placetype":"venue"
},
  "geometry": {"coordinates":[-0.369339,51.467091],"type":"Point"}
}