{
  "type": "Feature",
  "properties": {
    "addr:full":"15 Clarendon Street Hyde Cheshire SK14 2EL",
    "addr:housenumber":"15",
    "addr:postcode":"sk14 2el",
    "addr:street":"Clarendon Street",
    "iso:country":"GB",
    "sg:address":"15 Clarendon Street",
    "sg:city":"Hyde",
    "sg:classifiers":[
        {
            "category":"Organizations",
            "subcategory":"Non-profit Organization",
            "type":"Services"
        }
    ],
    "sg:phone":"+44 161 367 8788",
    "sg:postcode":"SK14 2EL",
    "sg:province":"Cheshire",
    "sg:tags":[
        "organisation",
        "voluntary",
        "charity"
    ],
    "wof:name":"Arthritis Research Shop",
    "wof:placetype":"venue"
},
  "geometry": {"coordinates":[-2.0753340721,53.4514122009],"type":"Point"}
}