{
  "type": "Feature",
  "properties": {
    "iso:country":"GB",
    "sg:address":"7 Moor House Drive, Birkenshaw",
    "sg:city":"Bradford",
    "sg:classifiers":[
        {
            "category":"Professional",
            "subcategory":"Management & Consulting",
            "type":"Services"
        }
    ],
    "sg:phone":"+44 1274 686935",
    "sg:postcode":"BD11 2BB",
    "sg:province":"West Yorkshire",
    "sg:tags":[
        "consultant",
        "business"
    ],
    "wof:name":"Rosemead International",
    "wof:placetype":"venue"
},
  "geometry": {"coordinates":[-1.69896,53.758778],"type":"Point"}
}