{
  "type": "Feature",
  "properties": {
    "addr:full":"55-56 Poland Street London Greater London W1F 7NB",
    "addr:housenumber":"55-56",
    "addr:postcode":"w1f 7nb",
    "addr:street":"Poland Street",
    "iso:country":"GB",
    "sg:address":"55-56 Poland Street",
    "sg:city":"London",
    "sg:classifiers":[
        {
            "category":"Organizations",
            "subcategory":"Community Association",
            "type":"Services"
        }
    ],
    "sg:phone":"+44 20 7439 2559",
    "sg:postcode":"W1F 7NB",
    "sg:province":"Greater London",
    "sg:tags":[
        "relation",
        "public"
    ],
    "wof:name":"Shilland & Co. Ltd.",
    "wof:placetype":"venue"
},
  "geometry": {"coordinates":[-0.1368560046,51.513961792],"type":"Point"}
}