{
  "type": "Feature",
  "properties": {
    "addr:full":"2-3 Elsinore Way, Lower Richmond Rd Richmond Greater London TW9 4LS",
    "addr:housenumber":"2-3",
    "addr:postcode":"tw9 4ls",
    "addr:street":"Elsinore Way;Rd",
    "iso:country":"GB",
    "sg:address":"2-3 Elsinore Way, Lower Richmond Rd",
    "sg:city":"Richmond",
    "sg:classifiers":[
        {
            "category":"Professional",
            "subcategory":"Printing & Photocopies",
            "type":"Services"
        }
    ],
    "sg:phone":"+44 20 8541 5377",
    "sg:postcode":"TW9 4LS",
    "sg:province":"Greater London",
    "sg:tags":[
        "printer"
    ],
    "wof:name":"Print Angle The",
    "wof:placetype":"venue"
},
  "geometry": {"coordinates":[-0.278669,51.468323],"type":"Point"}
}