{
  "type": "Feature",
  "properties": {
    "addr:full":"89 College Rd Epsom Surrey KT17 4HH",
    "addr:housenumber":"89",
    "addr:postcode":"kt17 4hh",
    "addr:street":"College Rd",
    "iso:country":"GB",
    "sg:address":"89 College Rd",
    "sg:city":"Epsom",
    "sg:classifiers":[
        {
            "category":"Social Services",
            "subcategory":"Child Care",
            "type":"Services"
        }
    ],
    "sg:phone":"+44 1372 722519",
    "sg:postcode":"KT17 4HH",
    "sg:province":"Surrey",
    "sg:tags":[
        "agency",
        "nanny"
    ],
    "wof:name":"The Nanny Agency",
    "wof:placetype":"venue"
},
  "geometry": {"coordinates":[-0.2491929978,51.3292770386],"type":"Point"}
}