{
  "type": "Feature",
  "properties": {
    "addr:full":"Unit 4, The Office Village London Greater London E15 4EA",
    "addr:housenumber":"unit 4",
    "addr:postcode":"e15 4ea",
    "addr:street":"Village",
    "iso:country":"GB",
    "sg:address":"Unit 4, The Office Village",
    "sg:city":"London",
    "sg:classifiers":[
        {
            "category":"Professional",
            "subcategory":"Art Services",
            "type":"Services"
        }
    ],
    "sg:phone":"+44 20 8522 0499",
    "sg:postcode":"E15 4EA",
    "sg:province":"Greater London",
    "sg:tags":[
        "graphic",
        "designer"
    ],
    "wof:name":"Good Impressions (London) Ltd.",
    "wof:placetype":"venue"
},
  "geometry": {"coordinates":[0.00414,51.54187],"type":"Point"}
}