{
  "type": "Feature",
  "properties": {
    "iso:country":"GB",
    "sg:address":"The Granary, Oxton Barns, Kenton",
    "sg:city":"Exeter",
    "sg:classifiers":[
        {
            "category":"Shopping",
            "subcategory":"Catalog Store",
            "type":"Retail Goods"
        }
    ],
    "sg:phone":"+44 1626 891198",
    "sg:postcode":"EX6 8EX",
    "sg:province":"Devon",
    "sg:tags":[
        "mail",
        "order"
    ],
    "wof:name":"Vaak Trading Co.Ltd",
    "wof:placetype":"venue"
},
  "geometry": {"coordinates":[-3.4729659557,50.6399497986],"type":"Point"}
}