{
  "type": "Feature",
  "properties": {
    "addr:full":"16 Moorside Drive Bradford West Yorkshire BD11 1HD",
    "addr:housenumber":"16",
    "addr:postcode":"bd11 1hd",
    "addr:street":"Moorside Drive",
    "iso:country":"GB",
    "sg:address":"16 Moorside Drive",
    "sg:city":"Bradford",
    "sg:classifiers":[
        {
            "category":"Manufacturing",
            "subcategory":"Rubber & Plastics",
            "type":"Manufacturing & Wholesale Goods"
        }
    ],
    "sg:phone":"+44 113 285 3102",
    "sg:postcode":"BD11 1HD",
    "sg:province":"West Yorkshire",
    "sg:tags":[
        "product"
    ],
    "wof:name":"Moorside Marketing",
    "wof:placetype":"venue"
},
  "geometry": {"coordinates":[-1.657097,53.752453],"type":"Point"}
}