{
  "type": "Feature",
  "properties": {
    "iso:country":"GB",
    "sg:address":"6 Blenheim Terrace",
    "sg:city":"Leeds",
    "sg:classifiers":[
        {
            "category":"Real Estate",
            "subcategory":"Architect",
            "type":"Services"
        }
    ],
    "sg:phone":"+44 113 245 2636",
    "sg:postcode":"LS2 9HZ",
    "sg:province":"West Yorkshire",
    "wof:name":"Vaughan Monckton Architecture",
    "wof:placetype":"venue"
},
  "geometry": {"coordinates":[-1.5487560034,53.8090019226],"type":"Point"}
}