{
  "type": "Feature",
  "properties": {
    "addr:full":"33 Park St Leamington Spa Warwickshire CV32 4QN",
    "addr:housenumber":"33",
    "addr:postcode":"cv32 4qn",
    "addr:street":"Park St",
    "iso:country":"GB",
    "sg:address":"33 Park St",
    "sg:city":"Leamington Spa",
    "sg:classifiers":[
        {
            "category":"Health Services",
            "subcategory":"Doctor",
            "type":"Services"
        }
    ],
    "sg:phone":"+44 1926 422580",
    "sg:postcode":"CV32 4QN",
    "sg:province":"Warwickshire",
    "sg:tags":[
        "practitioners"
    ],
    "wof:name":"Susan Laird",
    "wof:placetype":"venue"
},
  "geometry": {"coordinates":[-1.5333299637,52.2911491394],"type":"Point"}
}