{
  "type": "Feature",
  "properties": {
    "iso:country":"GB",
    "sg:address":"33-35 Cathedral Road",
    "sg:city":"Cardiff",
    "sg:classifiers":[
        {
            "category":"Arena",
            "subcategory":"Sports Club",
            "type":"Entertainment"
        }
    ],
    "sg:phone":"+44 29 2023 7048",
    "sg:postcode":"CF11 9HB",
    "sg:province":"Cardiff",
    "wof:name":"The Welsh Netball Association",
    "wof:placetype":"venue"
},
  "geometry": {"coordinates":[-3.192134,51.484035],"type":"Point"}
}