{
  "type": "Feature",
  "properties": {
    "iso:country":"GB",
    "sg:address":"321 Horbury Road",
    "sg:city":"Wakefield",
    "sg:classifiers":[
        {
            "category":"Autos & Motor Vehicles",
            "subcategory":"Fuel & Gas Station",
            "type":"Retail Goods"
        },
        {
            "category":"Retail",
            "subcategory":"Auto Repair",
            "type":"Services"
        }
    ],
    "sg:phone":"+44 1924 375548",
    "sg:postcode":"WF2 8JN",
    "sg:province":"West Yorkshire",
    "sg:tags":[
        "petrol",
        "garage",
        "modification"
    ],
    "wof:name":"Lupset Garage",
    "wof:placetype":"venue"
},
  "geometry": {"coordinates":[-1.533758,53.668713],"type":"Point"}
}