{
  "type": "Feature",
  "properties": {
    "iso:country":"GB",
    "sg:address":"The Marlborough, Charles Street",
    "sg:city":"Seaham",
    "sg:classifiers":[
        {
            "category":"Bars & Pubs",
            "type":"Food & Drink"
        }
    ],
    "sg:postcode":"SR7 7SJ",
    "sg:province":"Durham",
    "sg:tags":[
        "pubs",
        "inn"
    ],
    "wof:name":"Nice Pint Ltd.",
    "wof:placetype":"venue"
},
  "geometry": {"coordinates":[-1.342079,54.83757],"type":"Point"}
}