{
  "type": "Feature",
  "properties": {
    "iso:country":"GB",
    "sg:address":"Surrey Quays Shopping Centre, Redriff Road",
    "sg:city":"London",
    "sg:classifiers":[
        {
            "category":"Real Estate",
            "subcategory":"Real Estate Agent",
            "type":"Services"
        }
    ],
    "sg:phone":"+44 20 7231 3800",
    "sg:postcode":"SE16 7LR",
    "sg:province":"Greater London",
    "wof:name":"Kinleigh Folkard & Hayward Estate Agents",
    "wof:placetype":"venue"
},
  "geometry": {"coordinates":[-0.04136,51.4991],"type":"Point"}
}