{
  "type": "Feature",
  "properties": {
    "addr:full":"22 North Street Redhill Surrey RH1 1EG",
    "addr:housenumber":"22",
    "addr:postcode":"rh1 1eg",
    "addr:street":"North Street",
    "iso:country":"GB",
    "sg:address":"22 North Street",
    "sg:city":"Redhill",
    "sg:classifiers":[
        {
            "category":"Building & Trades",
            "subcategory":"Construction",
            "type":"Services"
        }
    ],
    "sg:phone":"+44 1737 211186",
    "sg:postcode":"RH1 1EG",
    "sg:province":"Surrey",
    "sg:tags":[
        "builder"
    ],
    "wof:name":"Barry Kerr Ltd.",
    "wof:placetype":"venue"
},
  "geometry": {"coordinates":[-0.1742919981,51.2426986694],"type":"Point"}
}