{
  "type": "Feature",
  "properties": {
    "addr:full":"Stonehenge Glover Avenue, Wollaton Nottingham Nottinghamshire NG8 2EL",
    "addr:postcode":"ng8 2el",
    "addr:street":"Glover Avenue",
    "iso:country":"GB",
    "sg:address":"Stonehenge Glover Avenue, Wollaton",
    "sg:city":"Nottingham",
    "sg:classifiers":[
        {
            "category":"Home & Garden",
            "subcategory":"Home Furnishings",
            "type":"Retail Goods"
        },
        {
            "category":"Home & Garden",
            "subcategory":"Carpets & Floor Coverings",
            "type":"Retail Goods"
        }
    ],
    "sg:phone":"+44 115 928 7443",
    "sg:postcode":"NG8 2EL",
    "sg:province":"Nottinghamshire",
    "sg:tags":[
        "fitting",
        "rug",
        "matting",
        "carpets"
    ],
    "wof:name":"A E Seelig",
    "wof:placetype":"venue"
},
  "geometry": {"coordinates":[-1.2240539789,52.9549713135],"type":"Point"}
}