{
  "type": "Feature",
  "properties": {
    "iso:country":"GB",
    "sg:address":"Green Lane Farm, Green La",
    "sg:city":"St Albans",
    "sg:classifiers":[
        {
            "category":"Building & Trades",
            "subcategory":"Landscaping Services",
            "type":"Services"
        }
    ],
    "sg:phone":"+44 1582 792358",
    "sg:postcode":"AL3 8BD",
    "sg:province":"Hertfordshire",
    "sg:tags":[
        "horticultural",
        "consultant"
    ],
    "wof:name":"C P Rigal",
    "wof:placetype":"venue"
},
  "geometry": {"coordinates":[-0.448855,51.832817],"type":"Point"}
}