{
  "type": "Feature",
  "properties": {
    "iso:country":"GB",
    "sg:address":"Sunset Farm, Germoe",
    "sg:city":"Penzance",
    "sg:classifiers":[
        {
            "category":"Farming",
            "subcategory":"Farm",
            "type":"Manufacturing & Wholesale Goods"
        }
    ],
    "sg:phone":"+44 1736 762164",
    "sg:postcode":"TR20 9SA",
    "sg:province":"Cornwall",
    "sg:tags":[
        "mixed",
        "crop"
    ],
    "wof:name":"Harold Thomas",
    "wof:placetype":"venue"
},
  "geometry": {"coordinates":[-5.382154,50.112789],"type":"Point"}
}