{
  "type": "Feature",
  "properties": {
    "iso:country":"GB",
    "sg:address":"Larch Street",
    "sg:city":"Dundee",
    "sg:classifiers":[
        {
            "category":"Restaurant",
            "type":"Food & Drink"
        }
    ],
    "sg:postcode":"DD1 5NP",
    "sg:province":"Dundee City",
    "wof:name":"Czech Cafe",
    "wof:placetype":"venue"
},
  "geometry": {"coordinates":[-2.9853439331,56.4606246948],"type":"Point"}
}