{
  "type": "Feature",
  "properties": {
    "addr:full":"Knyverton Road, East Cliff Bournemouth Dorset BH1 3QR",
    "addr:postcode":"bh1 3qr",
    "addr:street":"Knyverton Road East",
    "iso:country":"GB",
    "sg:address":"Knyverton Road, East Cliff",
    "sg:city":"Bournemouth",
    "sg:classifiers":[
        {
            "category":"Health Services",
            "subcategory":"Nursing And Care Facility",
            "type":"Services"
        },
        {
            "category":"Social Services",
            "subcategory":"Retirement Home",
            "type":"Services"
        }
    ],
    "sg:phone":"+44 1202 557671",
    "sg:postcode":"BH1 3QR",
    "sg:province":"Dorset",
    "sg:tags":[
        "residential"
    ],
    "wof:name":"ALAN COGGINS LTD",
    "wof:placetype":"venue"
},
  "geometry": {"coordinates":[-1.851449,50.724857],"type":"Point"}
}