{
  "type": "Feature",
  "properties": {
    "iso:country":"GB",
    "sg:address":"63-65 Rickmansworth Road",
    "sg:city":"Amersham",
    "sg:classifiers":[
        {
            "category":"Retail",
            "subcategory":"Laundry & Dry Cleaning",
            "type":"Services"
        }
    ],
    "sg:phone":"+44 1494 727051",
    "sg:postcode":"HP6 5JW",
    "sg:province":"Buckinghamshire",
    "sg:tags":[
        "cleaner",
        "alteration"
    ],
    "wof:name":"Amersham Launderette",
    "wof:placetype":"venue"
},
  "geometry": {"coordinates":[-0.6057850122,51.6790084839],"type":"Point"}
}