{
  "type": "Feature",
  "properties": {
    "iso:country":"GB",
    "sg:address":"1 Bournemead, Winterbourne Steepleton",
    "sg:city":"Dorchester",
    "sg:classifiers":[
        {
            "category":"Building & Trades",
            "subcategory":"Cleaning & Sanitation",
            "type":"Services"
        },
        {
            "category":"Retail",
            "subcategory":"Auto Repair",
            "type":"Services"
        }
    ],
    "sg:phone":"+44 1305 889564",
    "sg:postcode":"DT2 9LQ",
    "sg:province":"Dorset",
    "sg:tags":[
        "caravan",
        "commercial",
        "servicing",
        "contracting"
    ],
    "wof:name":"Bourne Valley Services",
    "wof:placetype":"venue"
},
  "geometry": {"coordinates":[-2.526524,50.706459],"type":"Point"}
}