{
  "type": "Feature",
  "properties": {
    "iso:country":"GB",
    "sg:address":"Shrubbery Farm, Turnpike, Carleton Rode",
    "sg:city":"Norwich",
    "sg:classifiers":[
        {
            "category":"Farming",
            "subcategory":"Livestock Farm",
            "type":"Manufacturing & Wholesale Goods"
        }
    ],
    "sg:postcode":"NR16 1NL",
    "sg:province":"Norfolk",
    "sg:tags":[
        "others"
    ],
    "wof:name":"Barry P Garner",
    "wof:placetype":"venue"
},
  "geometry": {"coordinates":[1.099605,52.495911],"type":"Point"}
}