{
  "type": "Feature",
  "properties": {
    "iso:country":"GB",
    "sg:address":"Springfield New Road",
    "sg:city":"Chatteris",
    "sg:classifiers":[
        {
            "category":"Farming",
            "subcategory":"Farm",
            "type":"Manufacturing & Wholesale Goods"
        }
    ],
    "sg:phone":"+44 1354 692180",
    "sg:postcode":"PE16 6XP",
    "sg:province":"Cambridgeshire",
    "sg:tags":[
        "egg",
        "producer"
    ],
    "wof:name":"Camvale Ltd.",
    "wof:placetype":"venue"
},
  "geometry": {"coordinates":[0.0486660004,52.4536323547],"type":"Point"}
}