{
  "type": "Feature",
  "properties": {
    "addr:full":"Central Road Harlow Essex CM20 2ST",
    "addr:postcode":"cm20 2st",
    "addr:street":"Central Road",
    "iso:country":"GB",
    "sg:address":"Central Road",
    "sg:city":"Harlow",
    "sg:classifiers":[
        {
            "category":"Professional",
            "subcategory":"Printing & Photocopies",
            "type":"Services"
        }
    ],
    "sg:phone":"+44 1279 454333",
    "sg:postcode":"CM20 2ST",
    "sg:province":"Essex",
    "sg:tags":[
        "wooden",
        "seal"
    ],
    "wof:name":"E Wish & Co. Ltd.",
    "wof:placetype":"venue"
},
  "geometry": {"coordinates":[0.1199010015,51.7846374512],"type":"Point"}
}