{
  "type": "Feature",
  "properties": {
    "iso:country":"GB",
    "sg:address":"19 Wheelgate",
    "sg:city":"Malton",
    "sg:classifiers":[
        {
            "category":"Professional",
            "subcategory":"Accounting & Tax Preparation",
            "type":"Services"
        }
    ],
    "sg:postcode":"YO17 0HT",
    "sg:province":"North Yorkshire",
    "sg:tags":[
        "accountant"
    ],
    "wof:name":"Ashby Berry & Co.",
    "wof:placetype":"venue"
},
  "geometry": {"coordinates":[-0.796766,54.135101],"type":"Point"}
}