{
  "type": "Feature",
  "properties": {
    "iso:country":"GB",
    "sg:address":"432 Cheetham Hill Rd",
    "sg:city":"Manchester",
    "sg:classifiers":[
        {
            "category":"Utilities",
            "subcategory":"Mobile Phone",
            "type":"Services"
        }
    ],
    "sg:postcode":"M8 9LE",
    "sg:province":"Greater Manchester",
    "sg:tags":[
        "telephone",
        "card"
    ],
    "wof:name":"Iqbal,Azar,",
    "wof:placetype":"venue"
},
  "geometry": {"coordinates":[-2.242938,53.509583],"type":"Point"}
}