{
  "type": "Feature",
  "properties": {
    "iso:country":"GB",
    "sg:address":"2 Station Road, Soham",
    "sg:city":"Ely",
    "sg:classifiers":[
        {
            "category":"Farming",
            "subcategory":"Livestock Farm",
            "type":"Manufacturing & Wholesale Goods"
        },
        {
            "category":"Shopping",
            "subcategory":"Florist",
            "type":"Retail Goods"
        }
    ],
    "sg:phone":"+44 1353 721336",
    "sg:postcode":"CB7 5DY",
    "sg:province":"Cambridgeshire",
    "sg:tags":[
        "breeder"
    ],
    "wof:name":"Brenda's Flowers",
    "wof:placetype":"venue"
},
  "geometry": {"coordinates":[0.3370600045,52.3356399536],"type":"Point"}
}