{
  "type": "Feature",
  "properties": {
    "iso:country":"GB",
    "sg:address":"St Giles House, Narcot Lane",
    "sg:city":"Chalfont St. Giles",
    "sg:classifiers":[
        {
            "category":"Shopping",
            "subcategory":"Computers & Home Electronics",
            "type":"Retail Goods"
        }
    ],
    "sg:phone":"+44 1494 581677",
    "sg:postcode":"HP8 4DA",
    "sg:province":"Buckinghamshire",
    "sg:tags":[
        "aerial",
        "television",
        "radio"
    ],
    "wof:name":"Sound Creation",
    "wof:placetype":"venue"
},
  "geometry": {"coordinates":[-0.580709,51.62653],"type":"Point"}
}