{
  "type": "Feature",
  "properties": {
    "addr:full":"8 Cedar Avenue, Blackwater Camberley Hampshire GU17 0JF",
    "addr:housenumber":"8",
    "addr:postcode":"gu17 0jf",
    "addr:street":"Cedar Avenue",
    "iso:country":"GB",
    "sg:address":"8 Cedar Avenue, Blackwater",
    "sg:city":"Camberley",
    "sg:classifiers":[
        {
            "category":"Professional",
            "type":"Services"
        }
    ],
    "sg:postcode":"GU17 0JF",
    "sg:province":"Hampshire",
    "sg:tags":[
        "exhibition"
    ],
    "wof:name":"About Plants",
    "wof:placetype":"venue"
},
  "geometry": {"coordinates":[-0.7831199765,51.3341522217],"type":"Point"}
}