{
  "type": "Feature",
  "properties": {
    "addr:full":"46 Ironbridge Road Broseley Shropshire TF12 5AF",
    "addr:housenumber":"46",
    "addr:postcode":"tf12 5af",
    "addr:street":"Ironbridge Road",
    "iso:country":"GB",
    "sg:address":"46 Ironbridge Road",
    "sg:city":"Broseley",
    "sg:classifiers":[
        {
            "category":"Shopping",
            "subcategory":"Pharmacy",
            "type":"Retail Goods"
        }
    ],
    "sg:phone":"+44 1952 882857",
    "sg:postcode":"TF12 5AF",
    "sg:province":"Shropshire",
    "sg:tags":[
        "medicine",
        "therapy"
    ],
    "wof:name":"D C Hoyle",
    "wof:placetype":"venue"
},
  "geometry": {"coordinates":[-2.472807,52.61647],"type":"Point"}
}