{
  "type": "Feature",
  "properties": {
    "addr:full":"Howard Court, Browns Lane, Effingham Leatherhead Surrey KT24 5NJ",
    "addr:postcode":"kt24 5nj",
    "addr:street":"Howard Court Browns Lane",
    "iso:country":"GB",
    "sg:address":"Howard Court, Browns Lane, Effingham",
    "sg:city":"Leatherhead",
    "sg:classifiers":[
        {
            "category":"Government",
            "subcategory":"Office",
            "type":"Public Place"
        }
    ],
    "sg:phone":"+44 1372 454910",
    "sg:postcode":"KT24 5NJ",
    "sg:province":"Surrey",
    "sg:tags":[
        "local"
    ],
    "wof:name":"Guildford Borough Council",
    "wof:placetype":"venue"
},
  "geometry": {"coordinates":[-0.3970490098,51.2697601318],"type":"Point"}
}