{
  "type": "Feature",
  "properties": {
    "iso:country":"GB",
    "sg:address":"Piece, Carnkie",
    "sg:city":"Redruth",
    "sg:classifiers":[
        {
            "category":"Bars & Pubs",
            "type":"Food & Drink"
        }
    ],
    "sg:postcode":"TR16 6SG",
    "sg:province":"Cornwall",
    "sg:tags":[
        "pubs",
        "inn"
    ],
    "wof:name":"The Countryman",
    "wof:placetype":"venue"
},
  "geometry": {"coordinates":[-5.2529492378,50.2130889893],"type":"Point"}
}