{
  "type": "Feature",
  "properties": {
    "iso:country":"GB",
    "sg:address":"Royal George Street, Via Charlesworth Street",
    "sg:city":"Stockport",
    "sg:classifiers":[
        {
            "category":"Shopping",
            "subcategory":"Clothing, Apparel, & Fashions",
            "type":"Retail Goods"
        }
    ],
    "sg:phone":"+44 161 477 9447",
    "sg:postcode":"SK3 8AS",
    "sg:province":"Cheshire",
    "sg:tags":[
        "cap",
        "hat"
    ],
    "wof:name":"The Denton Hat Co. Ltd.",
    "wof:placetype":"venue"
},
  "geometry": {"coordinates":[-2.160149,53.403919],"type":"Point"}
}