{
  "type": "Feature",
  "properties": {
    "iso:country":"GB",
    "sg:address":"1 Lindenfield",
    "sg:city":"Chislehurst",
    "sg:classifiers":[
        {
            "category":"Building & Trades",
            "subcategory":"Construction",
            "type":"Services"
        }
    ],
    "sg:phone":"+44 20 8467 6663",
    "sg:postcode":"BR7 5RG",
    "sg:province":"Kent",
    "sg:tags":[
        "roofing"
    ],
    "wof:name":"John Totman",
    "wof:placetype":"venue"
},
  "geometry": {"coordinates":[0.0624589995,51.4048843384],"type":"Point"}
}