{
  "type": "Feature",
  "properties": {
    "addr:full":"228 Peverel Road Cambridge Cambridgeshire CB5 8RL",
    "addr:housenumber":"228",
    "addr:postcode":"cb5 8rl",
    "addr:street":"Peverel Road",
    "iso:country":"GB",
    "sg:address":"228 Peverel Road",
    "sg:city":"Cambridge",
    "sg:classifiers":[
        {
            "category":"Fast Food",
            "type":"Food & Drink"
        },
        {
            "category":"Deli",
            "type":"Food & Drink"
        }
    ],
    "sg:phone":"+44 1223 241562",
    "sg:postcode":"CB5 8RL",
    "sg:province":"Cambridgeshire",
    "sg:tags":[
        "delivery",
        "snack",
        "sandwich"
    ],
    "wof:name":"Express Sandwiches",
    "wof:placetype":"venue"
},
  "geometry": {"coordinates":[0.1640769988,52.2107658386],"type":"Point"}
}