{
  "type": "Feature",
  "properties": {
    "addr:full":"Jerviston Rd, New Stevenston Motherwell North Lanarkshire ML1 4AD",
    "addr:postcode":"ml1 4ad",
    "addr:street":"Jerviston Rd",
    "iso:country":"GB",
    "sg:address":"Jerviston Rd, New Stevenston",
    "sg:city":"Motherwell",
    "sg:classifiers":[
        {
            "category":"Community Center",
            "type":"Public Place"
        }
    ],
    "sg:phone":"+44 1698 732402",
    "sg:postcode":"ML1 4AD",
    "sg:province":"North Lanarkshire",
    "sg:tags":[
        "centre"
    ],
    "wof:name":"New Stevenston Community Centre",
    "wof:placetype":"venue"
},
  "geometry": {"coordinates":[-3.976921,55.816025],"type":"Point"}
}