{
  "type": "Feature",
  "properties": {
    "addr:full":"3 Crane Street, Cranborne Wimborne Dorset BH21 5QD",
    "addr:housenumber":"3",
    "addr:postcode":"bh21 5qd",
    "addr:street":"Crane Street",
    "iso:country":"GB",
    "sg:address":"3 Crane Street, Cranborne",
    "sg:city":"Wimborne",
    "sg:classifiers":[
        {
            "category":"Retail",
            "subcategory":"Auto Repair",
            "type":"Services"
        }
    ],
    "sg:phone":"+44 1725 517376",
    "sg:postcode":"BH21 5QD",
    "sg:province":"Dorset",
    "sg:tags":[
        "engine",
        "specialist",
        "tuning",
        "car",
        "diagnostic",
        "garage",
        "modification"
    ],
    "wof:name":"Steven Harris",
    "wof:placetype":"venue"
},
  "geometry": {"coordinates":[-1.921722,50.919483],"type":"Point"}
}