{
  "type": "Feature",
  "properties": {
    "addr:full":"24 Bromley Road Shipley West Yorkshire BD18 4DS",
    "addr:housenumber":"24",
    "addr:postcode":"bd18 4ds",
    "addr:street":"Bromley Road",
    "iso:country":"GB",
    "sg:address":"24 Bromley Road",
    "sg:city":"Shipley",
    "sg:classifiers":[
        {
            "category":"Retail",
            "subcategory":"Repair Shop",
            "type":"Services"
        },
        {
            "category":"Building & Trades",
            "subcategory":"Construction",
            "type":"Services"
        }
    ],
    "sg:phone":"+44 1274 586326",
    "sg:postcode":"BD18 4DS",
    "sg:province":"West Yorkshire",
    "sg:tags":[
        "builder",
        "upholsterer"
    ],
    "wof:name":"Davies Upholstery Services",
    "wof:placetype":"venue"
},
  "geometry": {"coordinates":[-1.797116,53.834667],"type":"Point"}
}