{
  "type": "Feature",
  "properties": {
    "addr:full":"Inglestone St Greenock Inverclyde PA15 4UQ",
    "addr:postcode":"pa15 4uq",
    "addr:street":"Inglestone St Greenock",
    "iso:country":"GB",
    "sg:address":"Inglestone St",
    "sg:city":"Greenock",
    "sg:classifiers":[
        {
            "category":"Education",
            "subcategory":"School",
            "type":"Public Place"
        }
    ],
    "sg:phone":"+44 1475 715690",
    "sg:postcode":"PA15 4UQ",
    "sg:province":"Inverclyde",
    "sg:tags":[
        "local",
        "authority"
    ],
    "wof:name":"St. Lawrence Primary School",
    "wof:placetype":"venue"
},
  "geometry": {"coordinates":[-4.74742,55.940491],"type":"Point"}
}