{
  "type": "Feature",
  "properties": {
    "iso:country":"GB",
    "sg:address":"19-21 Smith Street",
    "sg:city":"Warwick",
    "sg:classifiers":[
        {
            "category":"Shopping",
            "subcategory":"Crafts & Fabrics",
            "type":"Retail Goods"
        }
    ],
    "sg:phone":"+44 1926 491214",
    "sg:postcode":"CV34 4JA",
    "sg:province":"Warwickshire",
    "sg:tags":[
        "shop"
    ],
    "wof:name":"The Warwick Fabric Shop",
    "wof:placetype":"venue"
},
  "geometry": {"coordinates":[-1.5838639736,52.2828063965],"type":"Point"}
}