{
  "type": "Feature",
  "properties": {
    "iso:country":"GB",
    "sg:address":"8 St George's Square, St Annes",
    "sg:city":"Lytham St Annes",
    "sg:classifiers":[
        {
            "category":"Organizations",
            "subcategory":"Non-profit Organization",
            "type":"Services"
        }
    ],
    "sg:postcode":"FY8 2NY",
    "sg:province":"Lancashire",
    "sg:tags":[
        "organisation",
        "voluntary",
        "charity"
    ],
    "wof:name":"Soroptimist Housing (Fylde) Ltd.",
    "wof:placetype":"venue"
},
  "geometry": {"coordinates":[-2.943022,53.740555],"type":"Point"}
}