{
  "type": "Feature",
  "properties": {
    "addr:full":"32 Granby St Newmarket Cambridgeshire CB8 8HE",
    "addr:housenumber":"32",
    "addr:postcode":"cb8 8he",
    "addr:street":"Granby St",
    "iso:country":"GB",
    "sg:address":"32 Granby St",
    "sg:city":"Newmarket",
    "sg:classifiers":[
        {
            "category":"Autos & Motor Vehicles",
            "subcategory":"Auto Supplies",
            "type":"Retail Goods"
        }
    ],
    "sg:phone":"+44 1638 663675",
    "sg:postcode":"CB8 8HE",
    "sg:province":"Cambridgeshire",
    "sg:tags":[
        "tyre"
    ],
    "wof:name":"Hi-q Tyreservices",
    "wof:placetype":"venue"
},
  "geometry": {"coordinates":[0.4106299877,52.2415237427],"type":"Point"}
}