{
  "type": "Feature",
  "properties": {
    "iso:country":"GB",
    "sg:address":"3 Ship Inn Yard",
    "sg:city":"Stockton-on-tees",
    "sg:classifiers":[
        {
            "category":"Shopping",
            "subcategory":"Clothing, Apparel, & Fashions",
            "type":"Retail Goods"
        }
    ],
    "sg:postcode":"TS18 1BX",
    "sg:province":"Durham",
    "sg:tags":[
        "shop"
    ],
    "wof:name":"Mischief",
    "wof:placetype":"venue"
},
  "geometry": {"coordinates":[-1.3137739897,54.5637321472],"type":"Point"}
}