{
  "type": "Feature",
  "properties": {
    "addr:full":"Post Office St, Witton-le-wear Bishop Auckland Durham DL14 0AW",
    "addr:postcode":"dl14 0aw",
    "addr:street":"St Witton-Le-Wear Bishop Auckland",
    "iso:country":"GB",
    "sg:address":"Post Office St, Witton-le-wear",
    "sg:city":"Bishop Auckland",
    "sg:classifiers":[
        {
            "category":"Food & Beverages",
            "subcategory":"Supermarket",
            "type":"Retail Goods"
        }
    ],
    "sg:postcode":"DL14 0AW",
    "sg:province":"Durham",
    "wof:name":"Simon,John,",
    "wof:placetype":"venue"
},
  "geometry": {"coordinates":[-1.7702070475,54.6763153076],"type":"Point"}
}