{
  "type": "Feature",
  "properties": {
    "addr:full":"1601 Great Western Road Glasgow Glasgow City G13 1LP",
    "addr:housenumber":"1601",
    "addr:postcode":"g13 1lp",
    "addr:street":"Great Western Road",
    "iso:country":"GB",
    "sg:address":"1601 Great Western Road",
    "sg:city":"Glasgow",
    "sg:classifiers":[
        {
            "category":"Food & Beverages",
            "subcategory":"Meat & Fish",
            "type":"Retail Goods"
        }
    ],
    "sg:phone":"+44 141 959 2015",
    "sg:postcode":"G13 1LP",
    "sg:province":"Glasgow City",
    "sg:tags":[
        "butcher"
    ],
    "wof:name":"Andrew Gillespie",
    "wof:placetype":"venue"
},
  "geometry": {"coordinates":[-4.3240981102,55.8894882202],"type":"Point"}
}