{
  "type": "Feature",
  "properties": {
    "iso:country":"GB",
    "sg:address":"Head Office Building, Rectory Lane",
    "sg:city":"Westerham",
    "sg:classifiers":[
        {
            "category":"Utilities",
            "subcategory":"Fuel Oil & Lpg",
            "type":"Services"
        }
    ],
    "sg:postcode":"TN16 1JR",
    "sg:province":"Kent",
    "wof:name":"Green Waste Services Ltd.",
    "wof:placetype":"venue"
},
  "geometry": {"coordinates":[0.0712649971,51.267074585],"type":"Point"}
}