{
  "type": "Feature",
  "properties": {
    "addr:full":"London Rd Superstore, Far Cotton Northampton Northamptonshire NN4 9AH",
    "addr:postcode":"nn4 9ah",
    "addr:street":"London",
    "iso:country":"GB",
    "sg:address":"London Rd Superstore, Far Cotton",
    "sg:city":"Northampton",
    "sg:classifiers":[
        {
            "category":"Food & Beverages",
            "subcategory":"Supermarket",
            "type":"Retail Goods"
        }
    ],
    "sg:phone":"+44 1604 764256",
    "sg:postcode":"NN4 9AH",
    "sg:province":"Northamptonshire",
    "wof:name":"South Midlands Co-Op Society",
    "wof:placetype":"venue"
},
  "geometry": {"coordinates":[-0.90255,52.222858],"type":"Point"}
}