{
  "type": "Feature",
  "properties": {
    "addr:full":"17 Market Way Wakefield West Yorkshire WF1 1PW",
    "addr:housenumber":"17",
    "addr:postcode":"wf1 1pw",
    "addr:street":"Market Way",
    "iso:country":"GB",
    "sg:address":"17 Market Way",
    "sg:city":"Wakefield",
    "sg:classifiers":[
        {
            "category":"Social Services",
            "type":"Services"
        }
    ],
    "sg:phone":"+44 1924 372824",
    "sg:postcode":"WF1 1PW",
    "sg:province":"West Yorkshire",
    "sg:tags":[
        "disability"
    ],
    "wof:name":"Acorn Medical Ltd.",
    "wof:placetype":"venue"
},
  "geometry": {"coordinates":[-1.5006370544,53.681804657],"type":"Point"}
}