{
  "type": "Feature",
  "properties": {
    "addr:full":"35 Huntly Street Aberdeen Aberdeen City AB10 1TJ",
    "addr:housenumber":"35",
    "addr:postcode":"ab10 1tj",
    "addr:street":"Huntly Street",
    "iso:country":"GB",
    "sg:address":"35 Huntly Street",
    "sg:city":"Aberdeen",
    "sg:classifiers":[
        {
            "category":"Communications",
            "subcategory":"Newspaper",
            "type":"Services"
        }
    ],
    "sg:phone":"+44 1224 644725",
    "sg:postcode":"AB10 1TJ",
    "sg:province":"Aberdeen City",
    "sg:tags":[
        "magazine"
    ],
    "wof:name":"Aberdeen Petroleum Publishing Ltd.",
    "wof:placetype":"venue"
},
  "geometry": {"coordinates":[-2.107173,57.145245],"type":"Point"}
}