{
  "type": "Feature",
  "properties": {
    "iso:country":"GB",
    "sg:address":"107 Acklam Road",
    "sg:city":"Middlesbrough",
    "sg:classifiers":[
        {
            "category":"Food & Beverages",
            "subcategory":"Meat & Fish",
            "type":"Retail Goods"
        },
        {
            "category":"Food & Beverages",
            "subcategory":"Groceries & Convenience Stores",
            "type":"Retail Goods"
        }
    ],
    "sg:phone":"+44 1642 852575",
    "sg:postcode":"TS5 5HR",
    "sg:province":"North Yorkshire",
    "sg:tags":[
        "shop",
        "chip"
    ],
    "wof:name":"SKIPPERS FISH BAR",
    "wof:placetype":"venue"
},
  "geometry": {"coordinates":[-1.2627040148,54.5530357361],"type":"Point"}
}