{
  "type": "Feature",
  "properties": {
    "iso:country":"GB",
    "sg:address":"1 Grasmere Av",
    "sg:city":"Houghton Le Spring",
    "sg:classifiers":[
        {
            "category":"Building & Trades",
            "subcategory":"Construction",
            "type":"Services"
        }
    ],
    "sg:phone":"+44 191 517 0452",
    "sg:postcode":"DH5 0PW",
    "sg:province":"Durham",
    "sg:tags":[
        "dry",
        "lining",
        "plasterers",
        "screeders"
    ],
    "wof:name":"TMC Plasterers",
    "wof:placetype":"venue"
},
  "geometry": {"coordinates":[-1.4364960194,54.8069458008],"type":"Point"}
}