{
  "type": "Feature",
  "properties": {
    "iso:country":"GB",
    "sg:address":"1 Station Road",
    "sg:city":"Harleston",
    "sg:classifiers":[
        {
            "category":"Manufacturing",
            "subcategory":"Pottery",
            "type":"Manufacturing & Wholesale Goods"
        }
    ],
    "sg:phone":"+44 1379 852556",
    "sg:postcode":"IP20 9ES",
    "sg:province":"Norfolk",
    "wof:name":"Millhouse Pottery",
    "wof:placetype":"venue"
},
  "geometry": {"coordinates":[1.301428,52.404121],"type":"Point"}
}