{
  "type": "Feature",
  "properties": {
    "addr:full":"1 Harcourt Rd Maidenhead Berkshire SL6 0DT",
    "addr:housenumber":"1",
    "addr:postcode":"sl6 0dt",
    "addr:street":"Harcourt Rd",
    "iso:country":"GB",
    "sg:address":"1 Harcourt Rd",
    "sg:city":"Maidenhead",
    "sg:classifiers":[
        {
            "category":"Building & Trades",
            "subcategory":"Construction",
            "type":"Services"
        }
    ],
    "sg:phone":"+44 1628 631268",
    "sg:postcode":"SL6 0DT",
    "sg:province":"Berkshire",
    "sg:tags":[
        "builder"
    ],
    "wof:name":"B & S Builders (slough)",
    "wof:placetype":"venue"
},
  "geometry": {"coordinates":[-0.676256001,51.5067939758],"type":"Point"}
}