{
  "type": "Feature",
  "properties": {
    "addr:full":"39 Junction Road, Woodhouse Sheffield South Yorkshire S13 7RP",
    "addr:housenumber":"39",
    "addr:postcode":"s13 7rp",
    "addr:street":"Junction Road",
    "iso:country":"GB",
    "sg:address":"39 Junction Road, Woodhouse",
    "sg:city":"Sheffield",
    "sg:classifiers":[
        {
            "category":"Building & Trades",
            "subcategory":"Construction",
            "type":"Services"
        }
    ],
    "sg:phone":"+44 114 269 8824",
    "sg:postcode":"S13 7RP",
    "sg:province":"South Yorkshire",
    "sg:tags":[
        "builder"
    ],
    "wof:name":"Woodhouse Timber Products",
    "wof:placetype":"venue"
},
  "geometry": {"coordinates":[-1.380494,53.357433],"type":"Point"}
}