{
  "type": "Feature",
  "properties": {
    "iso:country":"GB",
    "sg:address":"The Old Tennis Court Farm House, Wells Road, Hallatrow",
    "sg:city":"Bristol",
    "sg:classifiers":[
        {
            "category":"Mining & Drilling",
            "type":"Manufacturing & Wholesale Goods"
        }
    ],
    "sg:phone":"+44 1761 453622",
    "sg:postcode":"BS39 6EJ",
    "sg:province":"Somerset",
    "sg:tags":[
        "coal"
    ],
    "wof:name":"Bristol Coal Mining Archive",
    "wof:placetype":"venue"
},
  "geometry": {"coordinates":[-2.52002,51.312901],"type":"Point"}
}