{
  "type": "Feature",
  "properties": {
    "iso:country":"GB",
    "sg:address":"8 Minories",
    "sg:city":"Monument",
    "sg:classifiers":[
        {
            "category":"Transit Center",
            "subcategory":"Passenger",
            "type":"Transportation"
        }
    ],
    "sg:phone":"+44 20 7488 3234",
    "sg:postcode":"EC3N 1BJ",
    "sg:province":"Greater London",
    "sg:tags":[
        "ship",
        "broker"
    ],
    "wof:name":"Rainbow Chartering Ltd",
    "wof:placetype":"venue"
},
  "geometry": {"coordinates":[-0.075619,51.513435],"type":"Point"}
}