{
  "type": "Feature",
  "properties": {
    "addr:full":"Cumnonk Business Park, Glaisnock Road Cumnock East Ayrshire KA18 3BY",
    "addr:postcode":"ka18 3by",
    "addr:street":"Business Park Glaisnock Road",
    "iso:country":"GB",
    "sg:address":"Cumnonk Business Park, Glaisnock Road",
    "sg:city":"Cumnock",
    "sg:classifiers":[
        {
            "category":"Manufacturing",
            "subcategory":"Food",
            "type":"Manufacturing & Wholesale Goods"
        }
    ],
    "sg:phone":"+44 1290 422909",
    "sg:postcode":"KA18 3BY",
    "sg:province":"East Ayrshire",
    "sg:tags":[
        "mnfr",
        "drink",
        "soft"
    ],
    "wof:name":"Caledonian Bottlers Plc",
    "wof:placetype":"venue"
},
  "geometry": {"coordinates":[-4.2640991211,55.4532546997],"type":"Point"}
}