{
  "type": "Feature",
  "properties": {
    "addr:full":"Britannia House, Six Lanes End, Leeds Rd Heckmondwike West Yorkshire WF16 9BS",
    "addr:postcode":"wf16 9bs",
    "addr:street":"End Leeds Rd",
    "iso:country":"GB",
    "sg:address":"Britannia House, Six Lanes End, Leeds Rd",
    "sg:city":"Heckmondwike",
    "sg:classifiers":[
        {
            "category":"Home & Garden",
            "subcategory":"Building Materials",
            "type":"Retail Goods"
        }
    ],
    "sg:phone":"+44 1924 411281",
    "sg:postcode":"WF16 9BS",
    "sg:province":"West Yorkshire",
    "sg:tags":[
        "furnishers",
        "bathroom",
        "planner"
    ],
    "wof:name":"THE PRESTIGE BATHROOM COMPANY",
    "wof:placetype":"venue"
},
  "geometry": {"coordinates":[-1.6775239706,53.7136611938],"type":"Point"}
}