{
  "type": "Feature",
  "properties": {
    "addr:full":"Ladies Hill, Pilling Preston Lancashire PR3 6HA",
    "addr:postcode":"pr3 6ha",
    "addr:street":"Ladies Hill",
    "iso:country":"GB",
    "sg:address":"Ladies Hill, Pilling",
    "sg:city":"Preston",
    "sg:classifiers":[
        {
            "category":"Education",
            "subcategory":"School",
            "type":"Public Place"
        }
    ],
    "sg:phone":"+44 1253 790282",
    "sg:postcode":"PR3 6HA",
    "sg:province":"Lancashire",
    "sg:tags":[
        "local",
        "authority"
    ],
    "wof:name":"Pilling St Johns C of E Primary Sschool",
    "wof:placetype":"venue"
},
  "geometry": {"coordinates":[-2.910156,53.930977],"type":"Point"}
}