{
  "type": "Feature",
  "properties": {
    "addr:full":"Langston Rd Loughton Essex IG10 3TQ",
    "addr:postcode":"ig10 3tq",
    "addr:street":"Langston Rd",
    "iso:country":"GB",
    "sg:address":"Langston Rd",
    "sg:city":"Loughton",
    "sg:classifiers":[
        {
            "category":"Transit Center",
            "subcategory":"Passenger",
            "type":"Transportation"
        },
        {
            "category":"Professional",
            "subcategory":"Business Services",
            "type":"Services"
        },
        {
            "category":"Conference Center",
            "type":"Public Place"
        }
    ],
    "sg:phone":"+44 20 8787 7000",
    "sg:postcode":"IG10 3TQ",
    "sg:province":"Essex",
    "sg:tags":[
        "accomodation",
        "centre",
        "commerce"
    ],
    "wof:name":"Loughton Seedbed Centre",
    "wof:placetype":"venue"
},
  "geometry": {"coordinates":[0.08389,51.643181],"type":"Point"}
}