{
  "type": "Feature",
  "properties": {
    "addr:full":"Wigham Farm, Morchard Bishop Crediton Devon EX17 6RJ",
    "addr:postcode":"ex17 6rj",
    "iso:country":"GB",
    "sg:address":"Wigham Farm, Morchard Bishop",
    "sg:city":"Crediton",
    "sg:classifiers":[
        {
            "category":"Travel",
            "subcategory":"Hotels & Motels",
            "type":"Entertainment"
        }
    ],
    "sg:phone":"+44 1363 877350",
    "sg:postcode":"EX17 6RJ",
    "sg:province":"Devon",
    "sg:tags":[
        "house",
        "guest"
    ],
    "wof:name":"Wigham Farm Ltd.",
    "wof:placetype":"venue"
},
  "geometry": {"coordinates":[-3.7483110428,50.8541259766],"type":"Point"}
}