{
  "type": "Feature",
  "properties": {
    "addr:full":"Unit 7 Court Road Indust Est Cwmbran Monmouthshire NP44 3AS",
    "addr:housenumber":"unit 7",
    "addr:postcode":"np44 3as",
    "addr:street":"Court Road",
    "iso:country":"GB",
    "sg:address":"Unit 7 Court Road Indust Est",
    "sg:city":"Cwmbran",
    "sg:classifiers":[
        {
            "category":"Retail",
            "subcategory":"Auto Rental",
            "type":"Services"
        }
    ],
    "sg:phone":"+44 1633 866722",
    "sg:postcode":"NP44 3AS",
    "sg:province":"Monmouthshire",
    "sg:tags":[
        "car"
    ],
    "wof:name":"3 Arrows Ltd",
    "wof:placetype":"venue"
},
  "geometry": {"coordinates":[-3.0143990517,51.64453125],"type":"Point"}
}