{
  "type": "Feature",
  "properties": {
    "addr:full":"453 Leyland Road, Lostock Hall Preston Lancashire PR5 5SB",
    "addr:housenumber":"453",
    "addr:postcode":"pr5 5sb",
    "addr:street":"Leyland Road",
    "iso:country":"GB",
    "sg:address":"453 Leyland Road, Lostock Hall",
    "sg:city":"Preston",
    "sg:classifiers":[
        {
            "category":"Organizations",
            "subcategory":"Non-profit Organization",
            "type":"Services"
        }
    ],
    "sg:phone":"+44 1772 629470",
    "sg:postcode":"PR5 5SB",
    "sg:province":"Lancashire",
    "sg:tags":[
        "charitable",
        "organisation",
        "voluntary",
        "charity"
    ],
    "sg:website":"http://www.barnados.org.uk",
    "wof:name":"Barnardo S",
    "wof:placetype":"venue"
},
  "geometry": {"coordinates":[-2.694936,53.728184],"type":"Point"}
}