{
  "type": "Feature",
  "properties": {
    "addr:full":"Canal Road Bradford West Yorkshire BD3 0PA",
    "addr:postcode":"bd3 0pa",
    "addr:street":"Canal Road",
    "iso:country":"GB",
    "sg:address":"Canal Road",
    "sg:city":"Bradford",
    "sg:classifiers":[
        {
            "category":"Professional",
            "type":"Services"
        },
        {
            "category":"Shopping",
            "subcategory":"Gifts & Souvenirs",
            "type":"Retail Goods"
        },
        {
            "category":"Home & Garden",
            "subcategory":"Hardware",
            "type":"Retail Goods"
        }
    ],
    "sg:phone":"+44 1274 734421",
    "sg:postcode":"BD3 0PA",
    "sg:province":"West Yorkshire",
    "sg:tags":[
        "retailer",
        "maker",
        "diy",
        "display"
    ],
    "wof:name":"Arnold Laver (D I Y)",
    "wof:placetype":"venue"
},
  "geometry": {"coordinates":[-1.7499439716,53.8015060425],"type":"Point"}
}