{
  "type": "Feature",
  "properties": {
    "iso:country":"GB",
    "sg:address":"35-41 The Green",
    "sg:city":"Southall",
    "sg:classifiers":[
        {
            "category":"Autos & Motor Vehicles",
            "subcategory":"Automobile Sales",
            "type":"Retail Goods"
        }
    ],
    "sg:phone":"+44 20 8813 8767",
    "sg:postcode":"UB2 4AN",
    "sg:province":"Greater London",
    "sg:tags":[
        "car"
    ],
    "wof:name":"Middlesex Carriage Co",
    "wof:placetype":"venue"
},
  "geometry": {"coordinates":[-0.379691,51.504147],"type":"Point"}
}