{
  "type": "Feature",
  "properties": {
    "iso:country":"GB",
    "sg:address":"124 North Hill",
    "sg:city":"Plymouth",
    "sg:classifiers":[
        {
            "category":"Professional",
            "subcategory":"Engineering",
            "type":"Services"
        }
    ],
    "sg:phone":"+44 1752 225757",
    "sg:postcode":"PL4 8LA",
    "sg:province":"Devon",
    "sg:tags":[
        "consultant",
        "structural"
    ],
    "wof:name":"Duncan Cooper & Chadwick",
    "wof:placetype":"venue"
},
  "geometry": {"coordinates":[-4.1339020729,50.3796272278],"type":"Point"}
}