{
  "type": "Feature",
  "properties": {
    "addr:full":"3 Willow Square Crianlarich Argyll and Bute FK20 8RR",
    "addr:housenumber":"3",
    "addr:postcode":"fk20 8rr",
    "addr:street":"Willow Square",
    "iso:country":"GB",
    "sg:address":"3 Willow Square",
    "sg:city":"Crianlarich",
    "sg:classifiers":[
        {
            "category":"Banks & Credit Unions",
            "subcategory":"Financial Services",
            "type":"Services"
        }
    ],
    "sg:postcode":"FK20 8RR",
    "sg:province":"Argyll and Bute",
    "sg:tags":[
        "consultant"
    ],
    "wof:name":"Strathfillan Community Development Trust",
    "wof:placetype":"venue"
},
  "geometry": {"coordinates":[-4.6219611168,56.3932228088],"type":"Point"}
}