{
  "type": "Feature",
  "properties": {
    "addr:full":"28 New Street Honiton Devon EX14 1EX",
    "addr:housenumber":"28",
    "addr:postcode":"ex14 1ex",
    "addr:street":"New Street",
    "iso:country":"GB",
    "sg:address":"28 New Street",
    "sg:city":"Honiton",
    "sg:classifiers":[
        {
            "category":"Shopping",
            "subcategory":"Discount & Variety Stores",
            "type":"Retail Goods"
        }
    ],
    "sg:postcode":"EX14 1EX",
    "sg:province":"Devon",
    "sg:tags":[
        "surplus"
    ],
    "wof:name":"Honiton Army Surplus",
    "wof:placetype":"venue"
},
  "geometry": {"coordinates":[-3.1880669594,50.7986831665],"type":"Point"}
}