{
  "type": "Feature",
  "properties": {
    "iso:country":"GB",
    "sg:address":"Spenbrook Mill, Spenbrook Rd, Newchurch In Pendle",
    "sg:city":"Burnley",
    "sg:classifiers":[
        {
            "category":"Manufacturing",
            "subcategory":"Textiles",
            "type":"Manufacturing & Wholesale Goods"
        }
    ],
    "sg:phone":"+44 1282 611711",
    "sg:postcode":"BB12 9JH",
    "sg:province":"Lancashire",
    "sg:tags":[
        "mnfr",
        "rug",
        "carpet"
    ],
    "wof:name":"Wm. Pownall & Sons Ltd",
    "wof:placetype":"venue"
},
  "geometry": {"coordinates":[-2.270874,53.850578],"type":"Point"}
}