{
  "type": "Feature",
  "properties": {
    "iso:country":"GB",
    "sg:address":"3 High Street, Bishops Waltham",
    "sg:city":"Southampton",
    "sg:classifiers":[
        {
            "category":"Health Services",
            "subcategory":"Optometrist",
            "type":"Services"
        }
    ],
    "sg:phone":"+44 1489 891182",
    "sg:postcode":"SO32 1AB",
    "sg:province":"Hampshire",
    "sg:tags":[
        "optician"
    ],
    "wof:name":"Stricklands Opticians",
    "wof:placetype":"venue"
},
  "geometry": {"coordinates":[-1.2130850554,50.9534950256],"type":"Point"}
}