{
  "type": "Feature",
  "properties": {
    "addr:full":"High Street, Selborne Alton Hampshire GU34 3JJ",
    "addr:postcode":"gu34 3jj",
    "addr:street":"High Street",
    "iso:country":"GB",
    "sg:address":"High Street, Selborne",
    "sg:city":"Alton",
    "sg:classifiers":[
        {
            "category":"Travel",
            "subcategory":"Hotels & Motels",
            "type":"Entertainment"
        }
    ],
    "sg:phone":"+44 1420 511454",
    "sg:postcode":"GU34 3JJ",
    "sg:province":"Hampshire",
    "wof:name":"The Queens",
    "wof:placetype":"venue"
},
  "geometry": {"coordinates":[-0.944309,51.098274],"type":"Point"}
}