{
  "type": "Feature",
  "properties": {
    "addr:full":"Lanam House, Kennel Grn Ascot Berkshire SL5 8ET",
    "addr:postcode":"sl5 8et",
    "addr:street":"Kennel Grn",
    "iso:country":"GB",
    "sg:address":"Lanam House, Kennel Grn",
    "sg:city":"Ascot",
    "sg:classifiers":[
        {
            "category":"Retail",
            "subcategory":"Driving School",
            "type":"Services"
        }
    ],
    "sg:phone":"+44 1344 628002",
    "sg:postcode":"SL5 8ET",
    "sg:province":"Berkshire",
    "wof:name":"Aira Michael Professional Driving Tuition",
    "wof:placetype":"venue"
},
  "geometry": {"coordinates":[-0.686035,51.4189],"type":"Point"}
}