{
  "type": "Feature",
  "properties": {
    "addr:full":"164 Banbury Road Oxford Oxfordshire OX2 7BU",
    "addr:housenumber":"164",
    "addr:postcode":"ox2 7bu",
    "addr:street":"Banbury Road",
    "iso:country":"GB",
    "sg:address":"164 Banbury Road",
    "sg:city":"Oxford",
    "sg:classifiers":[
        {
            "category":"Travel",
            "subcategory":"Hotels & Motels",
            "type":"Entertainment"
        }
    ],
    "sg:postcode":"OX2 7BU",
    "sg:province":"Oxfordshire",
    "sg:tags":[
        "house",
        "guest"
    ],
    "wof:name":"Ryan's Guest House",
    "wof:placetype":"venue"
},
  "geometry": {"coordinates":[-1.2635240555,51.7743453979],"type":"Point"}
}