{
  "type": "Feature",
  "properties": {
    "addr:full":"Secom House, 52 Godstone Road Kenley Surrey CR8 5JF",
    "addr:housenumber":"52",
    "addr:postcode":"cr8 5jf",
    "addr:street":"Godstone Road",
    "iso:country":"GB",
    "sg:address":"Secom House, 52 Godstone Road",
    "sg:city":"Kenley",
    "sg:classifiers":[
        {
            "category":"Professional",
            "subcategory":"Detective & Security Services",
            "type":"Services"
        }
    ],
    "sg:phone":"+44 20 8645 5400",
    "sg:postcode":"CR8 5JF",
    "sg:province":"Surrey",
    "sg:tags":[
        "equipment",
        "installers"
    ],
    "wof:name":"Secom Plc",
    "wof:placetype":"venue"
},
  "geometry": {"coordinates":[-0.1035569981,51.3267288208],"type":"Point"}
}