{
  "type": "Feature",
  "properties": {
    "iso:country":"GB",
    "sg:address":"37 Wollaton Road, Beeston",
    "sg:city":"Nottingham",
    "sg:classifiers":[
        {
            "category":"Professional",
            "subcategory":"Accounting & Tax Preparation",
            "type":"Services"
        }
    ],
    "sg:phone":"+44 115 967 8388",
    "sg:postcode":"NG9 2NG",
    "sg:province":"Nottinghamshire",
    "sg:tags":[
        "accountant"
    ],
    "wof:name":"I M Pretty",
    "wof:placetype":"venue"
},
  "geometry": {"coordinates":[-1.217337966,52.9284744263],"type":"Point"}
}