{
  "type": "Feature",
  "properties": {
    "iso:country":"GB",
    "sg:address":"56 Allison Road",
    "sg:city":"Liverpool",
    "sg:classifiers":[
        {
            "category":"Shopping",
            "subcategory":"Clothing, Apparel, & Fashions",
            "type":"Retail Goods"
        }
    ],
    "sg:phone":"+44 151 428 3678",
    "sg:postcode":"L13 9AD",
    "sg:province":"Merseyside",
    "sg:tags":[
        "shop"
    ],
    "wof:name":"Cat Walk",
    "wof:placetype":"venue"
},
  "geometry": {"coordinates":[-2.9279589653,53.4316711426],"type":"Point"}
}