{
  "type": "Feature",
  "properties": {
    "addr:full":"35 Rose Hill Chesterfield Derbyshire S40 1TT",
    "addr:housenumber":"35",
    "addr:postcode":"s40 1tt",
    "addr:street":"Rose Hill",
    "iso:country":"GB",
    "sg:address":"35 Rose Hill",
    "sg:city":"Chesterfield",
    "sg:classifiers":[
        {
            "category":"Insurance",
            "subcategory":"Insurance Agent",
            "type":"Services"
        }
    ],
    "sg:phone":"+44 1246 557727",
    "sg:postcode":"S40 1TT",
    "sg:province":"Derbyshire",
    "wof:name":"Colonnade Insurance Brokers",
    "wof:placetype":"venue"
},
  "geometry": {"coordinates":[-1.4296449423,53.2362213135],"type":"Point"}
}