{
  "type": "Feature",
  "properties": {
    "iso:country":"GB",
    "sg:address":"1a Sheriff Hutton Trading Estate, Sheriff Hutton",
    "sg:city":"York",
    "sg:classifiers":[
        {
            "category":"Sports & Exercise",
            "subcategory":"Race Track",
            "type":"Entertainment"
        }
    ],
    "sg:postcode":"YO6 1RH",
    "sg:province":"East Riding of Yorkshire",
    "sg:tags":[
        "motor"
    ],
    "wof:name":"Dave Cook",
    "wof:placetype":"venue"
},
  "geometry": {"coordinates":[-1.00789,54.088032],"type":"Point"}
}