{
  "type": "Feature",
  "properties": {
    "iso:country":"GB",
    "sg:address":"Unit 3 -3A, 312 Ware Road",
    "sg:city":"Hertford",
    "sg:classifiers":[
        {
            "category":"Retail",
            "subcategory":"Auto Repair",
            "type":"Services"
        }
    ],
    "sg:phone":"+44 1992 550497",
    "sg:postcode":"SG13 7ER",
    "sg:province":"Hertfordshire",
    "sg:tags":[
        "modification",
        "garage",
        "related"
    ],
    "wof:name":"Roy Carter Ltd.",
    "wof:placetype":"venue"
},
  "geometry": {"coordinates":[-0.050619,51.802578],"type":"Point"}
}