{
  "type": "Feature",
  "properties": {
    "addr:full":"215 Portland Road Weymouth Dorset DT4 9BH",
    "addr:housenumber":"215",
    "addr:postcode":"dt4 9bh",
    "addr:street":"Portland Road",
    "iso:country":"GB",
    "sg:address":"215 Portland Road",
    "sg:city":"Weymouth",
    "sg:classifiers":[
        {
            "category":"Building & Trades",
            "subcategory":"Landscaping Services",
            "type":"Services"
        }
    ],
    "sg:phone":"+44 1305 770240",
    "sg:postcode":"DT4 9BH",
    "sg:province":"Dorset",
    "sg:tags":[
        "horticultural",
        "consultant"
    ],
    "wof:name":"Barry Walsh",
    "wof:placetype":"venue"
},
  "geometry": {"coordinates":[-2.4722321033,50.5876197815],"type":"Point"}
}