{
  "type": "Feature",
  "properties": {
    "iso:country":"GB",
    "sg:address":"Trevu Road",
    "sg:city":"Camborne",
    "sg:classifiers":[
        {
            "category":"Education",
            "subcategory":"School",
            "type":"Public Place"
        }
    ],
    "sg:phone":"+44 1209 713944",
    "sg:postcode":"TR14 7AE",
    "sg:province":"Cornwall",
    "sg:tags":[
        "local",
        "authority"
    ],
    "wof:name":"St.Johns R C Primary School",
    "wof:placetype":"venue"
},
  "geometry": {"coordinates":[-5.296979,50.210522],"type":"Point"}
}