{
  "type": "Feature",
  "properties": {
    "iso:country":"GB",
    "sg:address":"149 Lower High Street",
    "sg:city":"Merthyr Tydfil",
    "sg:classifiers":[
        {
            "category":"Personal",
            "subcategory":"Beauty Salon",
            "type":"Services"
        }
    ],
    "sg:postcode":"CF47 8EB",
    "sg:province":"Merthyr Tydfil",
    "sg:tags":[
        "unisex",
        "hairdresser"
    ],
    "wof:name":"Cutting Corner",
    "wof:placetype":"venue"
},
  "geometry": {"coordinates":[-3.377159,51.74239],"type":"Point"}
}