{
  "type": "Feature",
  "properties": {
    "iso:country":"GB",
    "sg:address":"Riddings Poultry Farm, Watling Street, Grendon",
    "sg:city":"Atherstone",
    "sg:classifiers":[
        {
            "category":"Farming",
            "subcategory":"Poultry Farm",
            "type":"Manufacturing & Wholesale Goods"
        }
    ],
    "sg:phone":"+44 1827 713244",
    "sg:postcode":"CV9 2PE",
    "sg:province":"Leicestershire",
    "sg:tags":[
        "game",
        "farmer"
    ],
    "wof:name":"F Everitt & Sons",
    "wof:placetype":"venue"
},
  "geometry": {"coordinates":[-1.5994729996,52.5859069824],"type":"Point"}
}