{
  "type": "Feature",
  "properties": {
    "addr:full":"67 East St Newton Abbot Devon TQ12 2JR",
    "addr:housenumber":"67",
    "addr:postcode":"tq12 2jr",
    "addr:street":"East St",
    "iso:country":"GB",
    "sg:address":"67 East St",
    "sg:city":"Newton Abbot",
    "sg:classifiers":[
        {
            "category":"Bars & Pubs",
            "type":"Food & Drink"
        }
    ],
    "sg:phone":"+44 1626 368725",
    "sg:postcode":"TQ12 2JR",
    "sg:province":"Devon",
    "sg:tags":[
        "pubs",
        "inn"
    ],
    "wof:name":"Devon Arms The",
    "wof:placetype":"venue"
},
  "geometry": {"coordinates":[-3.608289,50.528912],"type":"Point"}
}