{
  "type": "Feature",
  "properties": {
    "iso:country":"GB",
    "sg:address":"108 Belgrave Road",
    "sg:city":"Leicester",
    "sg:classifiers":[
        {
            "category":"Restaurant",
            "type":"Food & Drink"
        }
    ],
    "sg:postcode":"LE4 5AT",
    "sg:province":"Leicestershire",
    "wof:name":"Chaat House",
    "wof:placetype":"venue"
},
  "geometry": {"coordinates":[-1.1238119602,52.6483383179],"type":"Point"}
}