{
  "type": "Feature",
  "properties": {
    "addr:full":"24 Queen Elizabeth Avenue, Hillington Glasgow Glasgow City G52 4NQ",
    "addr:housenumber":"24",
    "addr:postcode":"g52 4nq",
    "addr:street":"Queen Elizabeth Avenue",
    "iso:country":"GB",
    "sg:address":"24 Queen Elizabeth Avenue, Hillington",
    "sg:city":"Glasgow",
    "sg:classifiers":[
        {
            "category":"Manufacturing",
            "subcategory":"Food",
            "type":"Manufacturing & Wholesale Goods"
        }
    ],
    "sg:phone":"+44 141 882 6200",
    "sg:postcode":"G52 4NQ",
    "sg:province":"Glasgow City",
    "sg:tags":[
        "technologist"
    ],
    "wof:name":"W E  Enterprises Ltd.",
    "wof:placetype":"venue"
},
  "geometry": {"coordinates":[-4.37555,55.857189],"type":"Point"}
}