{
  "type": "Feature",
  "properties": {
    "iso:country":"GB",
    "sg:address":"16 Bennetts Field Trading Est, Bennetts Field",
    "sg:city":"Wincanton",
    "sg:classifiers":[
        {
            "category":"Wholesale",
            "subcategory":"Non-durable Goods",
            "type":"Manufacturing & Wholesale Goods"
        }
    ],
    "sg:phone":"+44 1963 34144",
    "sg:postcode":"BA9 9DT",
    "sg:province":"Somerset",
    "sg:tags":[
        "carry",
        "cash"
    ],
    "wof:name":"Wincanton Wholesale Grocers Ltd",
    "wof:placetype":"venue"
},
  "geometry": {"coordinates":[-2.413179,51.0578],"type":"Point"}
}