{
  "type": "Feature",
  "properties": {
    "iso:country":"GB",
    "sg:address":"Group House, 40 Waterside Road, Hamilton Industrial Park",
    "sg:city":"Leicester",
    "sg:classifiers":[
        {
            "category":"Professional",
            "subcategory":"Printing & Photocopies",
            "type":"Services"
        }
    ],
    "sg:phone":"+44 116 276 5302",
    "sg:postcode":"LE5 1TL",
    "sg:province":"Leicestershire",
    "sg:tags":[
        "printer"
    ],
    "sg:website":"http://www.kpegroup.com",
    "wof:name":"K P E (Leicester) Ltd.",
    "wof:placetype":"venue"
},
  "geometry": {"coordinates":[-1.0791239738,52.6587295532],"type":"Point"}
}