{
  "type": "Feature",
  "properties": {
    "addr:full":"Broadway (the) Crowborough East Sussex TN6 1DB",
    "addr:postcode":"tn6 1db",
    "addr:street":"Broadway",
    "iso:country":"GB",
    "sg:address":"Broadway (the)",
    "sg:city":"Crowborough",
    "sg:classifiers":[
        {
            "category":"Travel",
            "subcategory":"Travel Agent",
            "type":"Entertainment"
        }
    ],
    "sg:phone":"+44 1892 653456",
    "sg:postcode":"TN6 1DB",
    "sg:province":"East Sussex",
    "wof:name":"Beacon Travel Service",
    "wof:placetype":"venue"
},
  "geometry": {"coordinates":[0.1628669947,51.0587081909],"type":"Point"}
}