{
  "type": "Feature",
  "properties": {
    "addr:full":"Yard, Rr 45 Lee Lane, Horwich Bolton Lancashire BL6 7AX",
    "addr:housenumber":"45",
    "addr:postcode":"bl6 7ax",
    "addr:street":"Rr;Lee Lane",
    "iso:country":"GB",
    "sg:address":"Yard, Rr 45 Lee Lane, Horwich",
    "sg:city":"Bolton",
    "sg:classifiers":[
        {
            "category":"Building & Trades",
            "subcategory":"Construction",
            "type":"Services"
        }
    ],
    "sg:phone":"+44 1204 690950",
    "sg:postcode":"BL6 7AX",
    "sg:province":"Lancashire",
    "sg:tags":[
        "builder"
    ],
    "wof:name":"M.J.C Builders",
    "wof:placetype":"venue"
},
  "geometry": {"coordinates":[-2.5470790863,53.6006851196],"type":"Point"}
}