{
  "type": "Feature",
  "properties": {
    "addr:full":"12 Coburg Road Dorchester Dorset DT1 2HW",
    "addr:housenumber":"12",
    "addr:postcode":"dt1 2hw",
    "addr:street":"Coburg Road",
    "iso:country":"GB",
    "sg:address":"12 Coburg Road",
    "sg:city":"Dorchester",
    "sg:classifiers":[
        {
            "category":"Social Services",
            "subcategory":"Retirement Home",
            "type":"Services"
        }
    ],
    "sg:postcode":"DT1 2HW",
    "sg:province":"Dorset",
    "sg:tags":[
        "residential",
        "care"
    ],
    "wof:name":"Brook House",
    "wof:placetype":"venue"
},
  "geometry": {"coordinates":[-2.443435,50.708389],"type":"Point"}
}