{
  "type": "Feature",
  "properties": {
    "iso:country":"GB",
    "sg:address":"Valley House, Gypsy Lane, Fiskerton",
    "sg:city":"Southwell",
    "sg:classifiers":[
        {
            "category":"Transit Center",
            "subcategory":"Passenger",
            "type":"Transportation"
        },
        {
            "category":"Retail",
            "subcategory":"Pet Boarding",
            "type":"Services"
        }
    ],
    "sg:phone":"+44 1636 830268",
    "sg:postcode":"NG25 0XN",
    "sg:province":"Nottinghamshire",
    "sg:tags":[
        "kennel",
        "catteries"
    ],
    "wof:name":"VALLEY BOARDING KENNELS",
    "wof:placetype":"venue"
},
  "geometry": {"coordinates":[-0.955189,53.078121],"type":"Point"}
}