{
  "type": "Feature",
  "properties": {
    "iso:country":"GB",
    "sg:address":"8 Warwick Lane, Warwick Street",
    "sg:city":"Worthing",
    "sg:classifiers":[
        {
            "category":"Cafe",
            "type":"Food & Drink"
        }
    ],
    "sg:phone":"+44 1903 212780",
    "sg:postcode":"BN11 3DP",
    "sg:province":"West Sussex",
    "sg:tags":[
        "tea",
        "room"
    ],
    "wof:name":"Pasqualinis House of Coffee",
    "wof:placetype":"venue"
},
  "geometry": {"coordinates":[-0.3643989861,50.8109588623],"type":"Point"}
}