{
  "type": "Feature",
  "properties": {
    "iso:country":"GB",
    "sg:address":"Priory Farm, Ickleton",
    "sg:city":"Saffron Walden",
    "sg:classifiers":[
        {
            "category":"Farming",
            "subcategory":"Livestock Farm",
            "type":"Manufacturing & Wholesale Goods"
        }
    ],
    "sg:phone":"+44 1799 530262",
    "sg:postcode":"CB10 1SS",
    "sg:province":"Cambridgeshire",
    "sg:tags":[
        "others"
    ],
    "wof:name":"M E Griggs",
    "wof:placetype":"venue"
},
  "geometry": {"coordinates":[0.2399380058,52.0205764771],"type":"Point"}
}