{
  "type": "Feature",
  "properties": {
    "iso:country":"GB",
    "sg:address":"2a Station Road, Mundesley",
    "sg:city":"Norwich",
    "sg:classifiers":[
        {
            "category":"Landmark",
            "subcategory":"Tourist Information",
            "type":"Public Place"
        }
    ],
    "sg:phone":"+44 1263 721070",
    "sg:postcode":"NR11 8JH",
    "sg:province":"Norfolk",
    "wof:name":"Mundesley Tourist Information Centre",
    "wof:placetype":"venue"
},
  "geometry": {"coordinates":[1.43285501,52.8769569397],"type":"Point"}
}