{
  "type": "Feature",
  "properties": {
    "addr:full":"St Davids Railway Station, St Davids Exeter Devon EX4 4NT",
    "addr:postcode":"ex4 4nt",
    "addr:street":"St;St Davids",
    "iso:country":"GB",
    "sg:address":"St Davids Railway Station, St Davids",
    "sg:city":"Exeter",
    "sg:classifiers":[
        {
            "category":"Government",
            "subcategory":"Police Station",
            "type":"Public Place"
        }
    ],
    "sg:phone":"+44 1392 431593",
    "sg:postcode":"EX4 4NT",
    "sg:province":"Devon",
    "sg:tags":[
        "support",
        "force"
    ],
    "wof:name":"British Transport Police",
    "wof:placetype":"venue"
},
  "geometry": {"coordinates":[-3.541166,50.729668],"type":"Point"}
}