{
  "type": "Feature",
  "properties": {
    "iso:country":"GB",
    "sg:address":"Scorton Road Farm, South Cowton",
    "sg:city":"Northallerton",
    "sg:classifiers":[
        {
            "category":"Farming",
            "subcategory":"Dairy Farm",
            "type":"Manufacturing & Wholesale Goods"
        }
    ],
    "sg:phone":"+44 1325 378237",
    "sg:postcode":"DL7 0JD",
    "sg:province":"North Yorkshire",
    "wof:name":"D & A Alderson",
    "wof:placetype":"venue"
},
  "geometry": {"coordinates":[-1.5717999935,54.4139289856],"type":"Point"}
}