{
  "type": "Feature",
  "properties": {
    "addr:full":"4 Church St Ilkley North Yorkshire LS29 9DS",
    "addr:housenumber":"4",
    "addr:postcode":"ls29 9ds",
    "addr:street":"Church St",
    "iso:country":"GB",
    "sg:address":"4 Church St",
    "sg:city":"Ilkley",
    "sg:classifiers":[
        {
            "category":"Personal",
            "subcategory":"Barber",
            "type":"Services"
        }
    ],
    "sg:phone":"+44 1943 607331",
    "sg:postcode":"LS29 9DS",
    "sg:province":"North Yorkshire",
    "sg:tags":[
        "men's",
        "hairdresser"
    ],
    "wof:name":"For Him",
    "wof:placetype":"venue"
},
  "geometry": {"coordinates":[-1.8236190081,53.9262809753],"type":"Point"}
}