{
  "type": "Feature",
  "properties": {
    "iso:country":"GB",
    "sg:address":"New Road, Kennoway",
    "sg:city":"Leven",
    "sg:classifiers":[
        {
            "category":"Food & Beverages",
            "subcategory":"Meat & Fish",
            "type":"Retail Goods"
        },
        {
            "category":"Food & Beverages",
            "subcategory":"Groceries & Convenience Stores",
            "type":"Retail Goods"
        }
    ],
    "sg:phone":"+44 1333 350371",
    "sg:postcode":"KY8 5JR",
    "sg:province":"Fife",
    "sg:tags":[
        "shop",
        "chip"
    ],
    "wof:name":"The Little Friar",
    "wof:placetype":"venue"
},
  "geometry": {"coordinates":[-3.048894,56.211174],"type":"Point"}
}