{
  "type": "Feature",
  "properties": {
    "iso:country":"GB",
    "sg:address":"85 Church St",
    "sg:city":"Leigh",
    "sg:classifiers":[
        {
            "category":"Banks & Credit Unions",
            "subcategory":"Financial Services",
            "type":"Services"
        }
    ],
    "sg:phone":"+44 1942 740444",
    "sg:postcode":"WN7 1AZ",
    "sg:province":"Lancashire",
    "sg:tags":[
        "adviser"
    ],
    "wof:name":"Richmond Financial Services",
    "wof:placetype":"venue"
},
  "geometry": {"coordinates":[-2.5135779381,53.4976577759],"type":"Point"}
}