{
  "type": "Feature",
  "properties": {
    "addr:full":"14 Grove Heath Court, Gambles Lane, Ripley Woking Surrey GU23 6HL",
    "addr:housenumber":"14",
    "addr:postcode":"gu23 6hl",
    "addr:street":"Grove Heath Court Gambles Lane",
    "iso:country":"GB",
    "sg:address":"14 Grove Heath Court, Gambles Lane, Ripley",
    "sg:city":"Woking",
    "sg:classifiers":[
        {
            "category":"Home & Garden",
            "subcategory":"Household Appliances",
            "type":"Retail Goods"
        },
        {
            "category":"Building & Trades",
            "subcategory":"Construction",
            "type":"Services"
        }
    ],
    "sg:phone":"+44 1483 224738",
    "sg:postcode":"GU23 6HL",
    "sg:province":"Surrey",
    "sg:tags":[
        "electrical",
        "decorator",
        "painter"
    ],
    "wof:name":"Paintcraft",
    "wof:placetype":"venue"
},
  "geometry": {"coordinates":[-0.490569,51.30106],"type":"Point"}
}