{
  "type": "Feature",
  "properties": {
    "addr:full":"P O Box 47 Accrington Lancashire BB5 5GU",
    "addr:housenumber":"box 47",
    "addr:postcode":"bb5 5gu",
    "addr:street":"P O",
    "iso:country":"GB",
    "sg:address":"P O Box 47",
    "sg:city":"Accrington",
    "sg:classifiers":[
        {
            "category":"Wholesale",
            "subcategory":"Vending Machines",
            "type":"Manufacturing & Wholesale Goods"
        }
    ],
    "sg:postcode":"BB5 5GU",
    "sg:province":"Lancashire",
    "sg:tags":[
        "business"
    ],
    "wof:name":"Metronics Dealer Services Uk",
    "wof:placetype":"venue"
},
  "geometry": {"coordinates":[-2.376839,53.774212],"type":"Point"}
}