{
  "type": "Feature",
  "properties": {
    "addr:full":"10 Condor Walk Hornchurch Essex RM12 5QD",
    "addr:housenumber":"10",
    "addr:postcode":"rm12 5qd",
    "addr:street":"Condor Walk",
    "iso:country":"GB",
    "sg:address":"10 Condor Walk",
    "sg:city":"Hornchurch",
    "sg:classifiers":[
        {
            "category":"Professional",
            "subcategory":"Engineering",
            "type":"Services"
        }
    ],
    "sg:phone":"+44 1708 554573",
    "sg:postcode":"RM12 5QD",
    "sg:province":"Essex",
    "sg:tags":[
        "civil",
        "engineer"
    ],
    "wof:name":"D.R Fleckney Ltd",
    "wof:placetype":"venue"
},
  "geometry": {"coordinates":[0.1992350072,51.5382766724],"type":"Point"}
}