{
  "type": "Feature",
  "properties": {
    "addr:full":"80 Sheridan Rd, Frimley Camberley Hampshire GU16 7EG",
    "addr:housenumber":"80",
    "addr:postcode":"gu16 7eg",
    "addr:street":"Sheridan Rd",
    "iso:country":"GB",
    "sg:address":"80 Sheridan Rd, Frimley",
    "sg:city":"Camberley",
    "sg:classifiers":[
        {
            "category":"Professional",
            "subcategory":"Lawyer & Legal Services",
            "type":"Services"
        }
    ],
    "sg:phone":"+44 1276 24161",
    "sg:postcode":"GU16 7EG",
    "sg:province":"Hampshire",
    "sg:tags":[
        "patent",
        "agent"
    ],
    "wof:name":"Handley,Suzanna,",
    "wof:placetype":"venue"
},
  "geometry": {"coordinates":[-0.7418889999,51.3125953674],"type":"Point"}
}