{
  "type": "Feature",
  "properties": {
    "addr:full":"Unit 4, Hawthorne Rd, The Causeway Staines Berkshire TW18 3AY",
    "addr:housenumber":"unit 4",
    "addr:postcode":"tw18 3ay",
    "addr:street":"Hawthorne Rd;Causeway",
    "iso:country":"GB",
    "sg:address":"Unit 4, Hawthorne Rd, The Causeway",
    "sg:city":"Staines",
    "sg:classifiers":[
        {
            "category":"Professional",
            "subcategory":"Computer Services",
            "type":"Services"
        }
    ],
    "sg:phone":"+44 1784 469902",
    "sg:postcode":"TW18 3AY",
    "sg:province":"Berkshire",
    "sg:tags":[
        "system",
        "software"
    ],
    "wof:name":"Computechnology",
    "wof:placetype":"venue"
},
  "geometry": {"coordinates":[-0.5305690169,51.434463501],"type":"Point"}
}