{
  "type": "Feature",
  "properties": {
    "iso:country":"GB",
    "sg:address":"Ravenscroft Rd",
    "sg:city":"Beckenham",
    "sg:classifiers":[
        {
            "category":"Place Of Worship",
            "type":"Public Place"
        }
    ],
    "sg:phone":"+44 20 8778 6569",
    "sg:postcode":"BR3 4SS",
    "sg:province":"Kent",
    "wof:name":"St Michaels C Of E Church",
    "wof:placetype":"venue"
},
  "geometry": {"coordinates":[-0.048857,51.409538],"type":"Point"}
}