{
  "type": "Feature",
  "properties": {
    "iso:country":"GB",
    "sg:address":"30 Grove Place",
    "sg:city":"Bedford",
    "sg:classifiers":[
        {
            "category":"Professional",
            "subcategory":"Lawyer & Legal Services",
            "type":"Services"
        }
    ],
    "sg:phone":"+44 1234 360388",
    "sg:postcode":"MK40 3JJ",
    "sg:province":"Bedfordshire",
    "sg:tags":[
        "advice",
        "counselling"
    ],
    "wof:name":"Bedford Open Door",
    "wof:placetype":"venue"
},
  "geometry": {"coordinates":[-0.4609940052,52.138381958],"type":"Point"}
}