{
  "type": "Feature",
  "properties": {
    "iso:country":"GB",
    "sg:address":"The Data Bank 3 Unit 2 Redhill, Distribution Ctr, Salbrook Road Salfords",
    "sg:city":"Redhill",
    "sg:classifiers":[
        {
            "category":"Retail",
            "subcategory":"Storage",
            "type":"Services"
        }
    ],
    "sg:phone":"+44 1293 446270",
    "sg:postcode":"RH1 5DY",
    "sg:province":"Surrey",
    "sg:tags":[
        "household",
        "removal",
        "operation",
        "facility"
    ],
    "sg:website":"http://www.restore.co.uk",
    "wof:name":"Restore Ltd",
    "wof:placetype":"venue"
},
  "geometry": {"coordinates":[-0.165758,51.19825],"type":"Point"}
}