{
  "type": "Feature",
  "properties": {
    "iso:country":"GB",
    "sg:address":"7 Gordon Street",
    "sg:city":"Huntly",
    "sg:classifiers":[
        {
            "category":"Professional",
            "subcategory":"Art Services",
            "type":"Services"
        }
    ],
    "sg:phone":"+44 1466 792552",
    "sg:postcode":"AB54 8AJ",
    "sg:province":"Aberdeenshire",
    "sg:tags":[
        "photographer"
    ],
    "wof:name":"Webster Photographic",
    "wof:placetype":"venue"
},
  "geometry": {"coordinates":[-2.7869029045,57.4471931458],"type":"Point"}
}