{
  "type": "Feature",
  "properties": {
    "iso:country":"GB",
    "sg:address":"22 West Hill Road",
    "sg:city":"Bournemouth",
    "sg:classifiers":[
        {
            "category":"Farming",
            "subcategory":"Nursery",
            "type":"Manufacturing & Wholesale Goods"
        }
    ],
    "sg:phone":"+44 1202 311900",
    "sg:postcode":"BH2 5PG",
    "sg:province":"Dorset",
    "sg:tags":[
        "creche"
    ],
    "wof:name":"Bournemouth West Pre-School Day Nursery",
    "wof:placetype":"venue"
},
  "geometry": {"coordinates":[-1.8864099979,50.7182159424],"type":"Point"}
}