{
  "type": "Feature",
  "properties": {
    "addr:full":"Carlton House, Carlton Road Worksop Nottinghamshire S81 7QF",
    "addr:postcode":"s81 7qf",
    "addr:street":"Carlton Road",
    "iso:country":"GB",
    "sg:address":"Carlton House, Carlton Road",
    "sg:city":"Worksop",
    "sg:classifiers":[
        {
            "category":"Professional",
            "subcategory":"Detective & Security Services",
            "type":"Services"
        }
    ],
    "sg:phone":"+44 1909 501584",
    "sg:postcode":"S81 7QF",
    "sg:province":"Nottinghamshire",
    "wof:name":"Gsl Court Services Ltd.",
    "wof:placetype":"venue"
},
  "geometry": {"coordinates":[-1.1211839914,53.3285903931],"type":"Point"}
}