{
  "type": "Feature",
  "properties": {
    "addr:full":"10 Market St Bracknell Berkshire RG12 1JG",
    "addr:housenumber":"10",
    "addr:postcode":"rg12 1jg",
    "addr:street":"Market St",
    "iso:country":"GB",
    "sg:address":"10 Market St",
    "sg:city":"Bracknell",
    "sg:classifiers":[
        {
            "category":"Shopping",
            "subcategory":"Baby Store",
            "type":"Retail Goods"
        }
    ],
    "sg:postcode":"RG12 1JG",
    "sg:province":"Berkshire",
    "sg:tags":[
        "nursery",
        "accessory"
    ],
    "wof:name":"Baby Wise Buys",
    "wof:placetype":"venue"
},
  "geometry": {"coordinates":[-0.752692,51.41573],"type":"Point"}
}