{
  "type": "Feature",
  "properties": {
    "addr:full":"565 High Rd Leytonstone Wanstead Greater London E11 4PB",
    "addr:housenumber":"565",
    "addr:postcode":"e11 4pb",
    "addr:street":"High Rd",
    "iso:country":"GB",
    "sg:address":"565 High Rd Leytonstone",
    "sg:city":"Wanstead",
    "sg:classifiers":[
        {
            "category":"Home & Garden",
            "subcategory":"Kitchen Supply",
            "type":"Retail Goods"
        }
    ],
    "sg:phone":"+44 20 8505 0038",
    "sg:postcode":"E11 4PB",
    "sg:province":"Greater London",
    "sg:tags":[
        "equipment",
        "catering"
    ],
    "wof:name":"Acme Catering & Bar Equipment Co",
    "wof:placetype":"venue"
},
  "geometry": {"coordinates":[0.008205,51.561069],"type":"Point"}
}