{
  "type": "Feature",
  "properties": {
    "addr:full":"St. Pauls View, 15 Amwell St Clerkenwell Greater London EC1R 1UP",
    "addr:housenumber":"15",
    "addr:postcode":"ec1r 1up",
    "addr:street":"St. Pauls View;Amwell St",
    "iso:country":"GB",
    "sg:address":"St. Pauls View, 15 Amwell St",
    "sg:city":"Clerkenwell",
    "sg:classifiers":[
        {
            "category":"Shopping",
            "subcategory":"Event Tickets",
            "type":"Retail Goods"
        }
    ],
    "sg:phone":"+44 20 7833 9591",
    "sg:postcode":"EC1R 1UP",
    "sg:province":"Greater London",
    "sg:tags":[
        "agency"
    ],
    "wof:name":"London Ticket Brokers",
    "wof:placetype":"venue"
},
  "geometry": {"coordinates":[-0.099616,51.610538],"type":"Point"}
}