{
  "type": "Feature",
  "properties": {
    "iso:country":"GB",
    "sg:address":"21 Queen St",
    "sg:city":"Louth",
    "sg:classifiers":[
        {
            "category":"Food & Beverages",
            "subcategory":"Liquor & Beverages",
            "type":"Retail Goods"
        }
    ],
    "sg:phone":"+44 1507 603114",
    "sg:postcode":"LN11 9AU",
    "sg:province":"Lincolnshire",
    "sg:tags":[
        "beer",
        "spirit",
        "wines"
    ],
    "wof:name":"Thresher Wine Shop",
    "wof:placetype":"venue"
},
  "geometry": {"coordinates":[-0.002846,53.366676],"type":"Point"}
}