{
  "type": "Feature",
  "properties": {
    "addr:full":"Greenacres, Gibbett Lane, Shawell Lutterworth Leicestershire LE17 6BT",
    "addr:postcode":"le17 6bt",
    "addr:street":"Gibbett Lane",
    "iso:country":"GB",
    "sg:address":"Greenacres, Gibbett Lane, Shawell",
    "sg:city":"Lutterworth",
    "sg:classifiers":[
        {
            "category":"Professional",
            "subcategory":"Management & Consulting",
            "type":"Services"
        }
    ],
    "sg:postcode":"LE17 6BT",
    "sg:province":"Leicestershire",
    "sg:tags":[
        "consultant",
        "promotion",
        "direct",
        "sale"
    ],
    "wof:name":"Market Capture",
    "wof:placetype":"venue"
},
  "geometry": {"coordinates":[-1.1998289824,52.4179954529],"type":"Point"}
}