{
  "type": "Feature",
  "properties": {
    "addr:full":"42 Church Street Oswestry Shropshire SY11 2SY",
    "addr:housenumber":"42",
    "addr:postcode":"sy11 2sy",
    "addr:street":"Church Street",
    "iso:country":"GB",
    "sg:address":"42 Church Street",
    "sg:city":"Oswestry",
    "sg:classifiers":[
        {
            "category":"Fast Food",
            "type":"Food & Drink"
        }
    ],
    "sg:phone":"+44 1691 652782",
    "sg:postcode":"SY11 2SY",
    "sg:province":"Shropshire",
    "sg:tags":[
        "away",
        "take"
    ],
    "wof:name":"Abbott",
    "wof:placetype":"venue"
},
  "geometry": {"coordinates":[-3.0578050613,52.856803894],"type":"Point"}
}