{
  "type": "Feature",
  "properties": {
    "addr:full":"Hazel Grove Delivery Office, Short Street, Hazel Grove Stockport Cheshire SK7 4AD",
    "addr:postcode":"sk7 4ad",
    "addr:street":"Short Street",
    "iso:country":"GB",
    "sg:address":"Hazel Grove Delivery Office, Short Street, Hazel Grove",
    "sg:city":"Stockport",
    "sg:classifiers":[
        {
            "category":"Personal",
            "type":"Services"
        }
    ],
    "sg:phone":"+44 161 483 4600",
    "sg:postcode":"SK7 4AD",
    "sg:province":"Cheshire",
    "sg:tags":[
        "delivery"
    ],
    "wof:name":"Royal Mail",
    "wof:placetype":"venue"
},
  "geometry": {"coordinates":[-2.121126,53.382099],"type":"Point"}
}