{
  "type": "Feature",
  "properties": {
    "iso:country":"GB",
    "sg:address":"2 Love Lane",
    "sg:city":"Romsey",
    "sg:classifiers":[
        {
            "category":"Shopping",
            "subcategory":"Thrift Store",
            "type":"Retail Goods"
        }
    ],
    "sg:phone":"+44 1794 511503",
    "sg:postcode":"SO51 8DE",
    "sg:province":"Hampshire",
    "sg:tags":[
        "shop",
        "charity"
    ],
    "wof:name":"Help the Aged",
    "wof:placetype":"venue"
},
  "geometry": {"coordinates":[-1.496804,50.98922],"type":"Point"}
}