{
  "type": "Feature",
  "properties": {
    "addr:full":"Halliford Studios, Manygate Lane Shepperton Surrey TW17 9EG",
    "addr:postcode":"tw17 9eg",
    "addr:street":"Manygate Lane",
    "iso:country":"GB",
    "sg:address":"Halliford Studios, Manygate Lane",
    "sg:city":"Shepperton",
    "sg:classifiers":[
        {
            "category":"Communications",
            "subcategory":"Film & Video Production",
            "type":"Services"
        }
    ],
    "sg:postcode":"TW17 9EG",
    "sg:province":"Surrey",
    "sg:tags":[
        "tv",
        "studio"
    ],
    "wof:name":"Halliford Studios Ltd.",
    "wof:placetype":"venue"
},
  "geometry": {"coordinates":[-0.448547,51.394321],"type":"Point"}
}