{
  "type": "Feature",
  "properties": {
    "iso:country":"GB",
    "sg:address":"Parciau Penmynydd",
    "sg:city":"Llanfairpwllgwyngyll",
    "sg:classifiers":[
        {
            "category":"Farming",
            "subcategory":"Livestock Farm",
            "type":"Manufacturing & Wholesale Goods"
        }
    ],
    "sg:phone":"+44 1248 714051",
    "sg:postcode":"LL61 6PL",
    "sg:province":"Isle of Anglesey",
    "sg:tags":[
        "others"
    ],
    "wof:name":"W H Roberts",
    "wof:placetype":"venue"
},
  "geometry": {"coordinates":[-4.2097492218,53.2214431763],"type":"Point"}
}