{
  "type": "Feature",
  "properties": {
    "addr:full":"184 Freeman St Grimsby Lincolnshire DN32 7AT",
    "addr:housenumber":"184",
    "addr:postcode":"dn32 7at",
    "addr:street":"Freeman St",
    "iso:country":"GB",
    "sg:address":"184 Freeman St",
    "sg:city":"Grimsby",
    "sg:classifiers":[
        {
            "category":"Shopping",
            "subcategory":"Thrift Store",
            "type":"Retail Goods"
        }
    ],
    "sg:phone":"+44 1472 320633",
    "sg:postcode":"DN32 7AT",
    "sg:province":"Lincolnshire",
    "sg:tags":[
        "shop",
        "charity"
    ],
    "wof:name":"Grimsby & District Health Care Charity",
    "wof:placetype":"venue"
},
  "geometry": {"coordinates":[-0.074365,53.569637],"type":"Point"}
}