{
  "type": "Feature",
  "properties": {
    "addr:full":"20 Braybank, Bray Maidenhead Berkshire SL6 2BQ",
    "addr:housenumber":"20",
    "addr:postcode":"sl6 2bq",
    "addr:street":"Braybank Bray",
    "iso:country":"GB",
    "sg:address":"20 Braybank, Bray",
    "sg:city":"Maidenhead",
    "sg:classifiers":[
        {
            "category":"Professional",
            "subcategory":"Management & Consulting",
            "type":"Services"
        }
    ],
    "sg:phone":"+44 1628 633213",
    "sg:postcode":"SL6 2BQ",
    "sg:province":"Berkshire",
    "sg:tags":[
        "consultant",
        "training"
    ],
    "wof:name":"Priority Management",
    "wof:placetype":"venue"
},
  "geometry": {"coordinates":[-0.70148,51.507195],"type":"Point"}
}