{
  "type": "Feature",
  "properties": {
    "addr:full":"1 Angel Passage London Greater London EC4R 3TP",
    "addr:housenumber":"1",
    "addr:postcode":"ec4r 3tp",
    "addr:street":"Angel Passage",
    "iso:country":"GB",
    "sg:address":"1 Angel Passage",
    "sg:city":"London",
    "sg:classifiers":[
        {
            "category":"Parking",
            "type":"Transportation"
        }
    ],
    "sg:phone":"+44 20 7283 1410",
    "sg:postcode":"EC4R 3TP",
    "sg:province":"Greater London",
    "sg:tags":[
        "car",
        "park"
    ],
    "wof:name":"National Car Parks Ltd.",
    "wof:placetype":"venue"
},
  "geometry": {"coordinates":[-0.0891299993,51.5096588135],"type":"Point"}
}