{
  "type": "Feature",
  "properties": {
    "addr:full":"The Old Chapel, Widegates Looe Cornwall PL13 1QB",
    "addr:postcode":"pl13 1qb",
    "addr:street":"Widegates",
    "iso:country":"GB",
    "sg:address":"The Old Chapel, Widegates",
    "sg:city":"Looe",
    "sg:classifiers":[
        {
            "category":"Shopping",
            "subcategory":"Antiques",
            "type":"Retail Goods"
        }
    ],
    "sg:postcode":"PL13 1QB",
    "sg:province":"Cornwall",
    "wof:name":"Splinters",
    "wof:placetype":"venue"
},
  "geometry": {"coordinates":[-4.4551510811,50.3570518494],"type":"Point"}
}