{
  "type": "Feature",
  "properties": {
    "iso:country":"GB",
    "sg:address":"45 Deerstone Ridge",
    "sg:city":"Wetherby",
    "sg:classifiers":[
        {
            "category":"Professional",
            "subcategory":"Accounting & Tax Preparation",
            "type":"Services"
        }
    ],
    "sg:phone":"+44 1937 582062",
    "sg:postcode":"LS22 7XN",
    "sg:province":"North Yorkshire",
    "sg:tags":[
        "accountant"
    ],
    "wof:name":"Malcolm Viney Chartered Accountant",
    "wof:placetype":"venue"
},
  "geometry": {"coordinates":[-1.3874750137,53.9425125122],"type":"Point"}
}