{
  "type": "Feature",
  "properties": {
    "addr:full":"1a St Andrews Street, Kirton Lindsey Gainsborough Lincolnshire DN21 4PJ",
    "addr:housenumber":"1a",
    "addr:postcode":"dn21 4pj",
    "addr:street":"St Andrews Street",
    "iso:country":"GB",
    "sg:address":"1a St Andrews Street, Kirton Lindsey",
    "sg:city":"Gainsborough",
    "sg:classifiers":[
        {
            "category":"Manufacturing",
            "subcategory":"Building Materials",
            "type":"Manufacturing & Wholesale Goods"
        }
    ],
    "sg:postcode":"DN21 4PJ",
    "sg:province":"Lincolnshire",
    "sg:tags":[
        "tarmac",
        "asphalt"
    ],
    "wof:name":"Hemswell Contracting Ltd.",
    "wof:placetype":"venue"
},
  "geometry": {"coordinates":[-0.5932260156,53.4756507874],"type":"Point"}
}