{
  "type": "Feature",
  "properties": {
    "addr:full":"Old Sutch Farm, Meadow Lane, Lathom Ormskirk Lancashire L40 4BR",
    "addr:postcode":"l40 4br",
    "addr:street":"Farm Meadow Lane",
    "iso:country":"GB",
    "sg:address":"Old Sutch Farm, Meadow Lane, Lathom",
    "sg:city":"Ormskirk",
    "sg:classifiers":[
        {
            "category":"Home & Garden",
            "subcategory":"Garden Supply",
            "type":"Retail Goods"
        }
    ],
    "sg:postcode":"L40 4BR",
    "sg:province":"Lancashire",
    "sg:tags":[
        "turfing"
    ],
    "wof:name":"Premier Turf Co.",
    "wof:placetype":"venue"
},
  "geometry": {"coordinates":[-2.81483,53.600391],"type":"Point"}
}