{
  "type": "Feature",
  "properties": {
    "iso:country":"GB",
    "sg:address":"20 Mapplewell Crescent",
    "sg:city":"Warrington",
    "sg:classifiers":[
        {
            "category":"Home & Garden",
            "subcategory":"Home Furnishings",
            "type":"Retail Goods"
        },
        {
            "category":"Home & Garden",
            "subcategory":"Furniture",
            "type":"Retail Goods"
        }
    ],
    "sg:phone":"+44 1925 722855",
    "sg:postcode":"WA5 1UT",
    "sg:province":"Cheshire",
    "sg:tags":[
        "furnishers",
        "planner",
        "bedroom"
    ],
    "wof:name":"Parr Fitments",
    "wof:placetype":"venue"
},
  "geometry": {"coordinates":[-2.640679,53.392956],"type":"Point"}
}