{
  "type": "Feature",
  "properties": {
    "addr:full":"Ground Floor Suite, Auckland House, New Zealand Avenue Walton-on-thames Surrey KT12 1PL",
    "addr:housenumber":"ground floor suite auckland house",
    "addr:postcode":"kt12 1pl",
    "addr:street":"New Zealand Avenue",
    "iso:country":"GB",
    "sg:address":"Ground Floor Suite, Auckland House, New Zealand Avenue",
    "sg:city":"Walton-on-thames",
    "sg:classifiers":[
        {
            "category":"Recreation",
            "subcategory":"Gun Range",
            "type":"Entertainment"
        }
    ],
    "sg:phone":"+44 1932 225544",
    "sg:postcode":"KT12 1PL",
    "sg:province":"Surrey",
    "sg:tags":[
        "operator",
        "tour"
    ],
    "wof:name":"Sunstyle Villas Condos & Hotels Ltd.",
    "wof:placetype":"venue"
},
  "geometry": {"coordinates":[-0.4256739914,51.3856048584],"type":"Point"}
}