{
  "type": "Feature",
  "properties": {
    "addr:full":"118 Sutcliffe Av Grimsby Lincolnshire DN33 1AP",
    "addr:housenumber":"118",
    "addr:postcode":"dn33 1ap",
    "addr:street":"Sutcliffe Av",
    "iso:country":"GB",
    "sg:address":"118 Sutcliffe Av",
    "sg:city":"Grimsby",
    "sg:classifiers":[
        {
            "category":"Shopping",
            "subcategory":"Gifts & Souvenirs",
            "type":"Retail Goods"
        }
    ],
    "sg:phone":"+44 1472 751997",
    "sg:postcode":"DN33 1AP",
    "sg:province":"Lincolnshire",
    "sg:tags":[
        "christmas"
    ],
    "wof:name":"Toy Boyz Enterprises",
    "wof:placetype":"venue"
},
  "geometry": {"coordinates":[-0.1023039967,53.5492324829],"type":"Point"}
}