{
  "type": "Feature",
  "properties": {
    "iso:country":"GB",
    "sg:address":"536 Manchester Rd",
    "sg:city":"Sheffield",
    "sg:classifiers":[
        {
            "category":"Bars & Pubs",
            "type":"Food & Drink"
        }
    ],
    "sg:phone":"+44 114 283 7001",
    "sg:postcode":"S36 2DW",
    "sg:province":"South Yorkshire",
    "sg:tags":[
        "pubs",
        "inn"
    ],
    "wof:name":"Friendship Hotel",
    "wof:placetype":"venue"
},
  "geometry": {"coordinates":[-1.6185990572,53.4912261963],"type":"Point"}
}