{
  "type": "Feature",
  "properties": {
    "iso:country":"GB",
    "sg:address":"306 Killinghall Road",
    "sg:city":"Bradford",
    "sg:classifiers":[
        {
            "category":"Government",
            "subcategory":"Post Office",
            "type":"Public Place"
        }
    ],
    "sg:phone":"+44 1274 638012",
    "sg:postcode":"BD2 4SE",
    "sg:province":"West Yorkshire",
    "wof:name":"Killinghall Road Sub Post Office",
    "wof:placetype":"venue"
},
  "geometry": {"coordinates":[-1.72569,53.805248],"type":"Point"}
}