{
  "type": "Feature",
  "properties": {
    "iso:country":"GB",
    "sg:address":"70 Coton Rd, Nether Whitacre",
    "sg:city":"Birmingham",
    "sg:classifiers":[
        {
            "category":"Building & Trades",
            "subcategory":"Plumbing",
            "type":"Services"
        }
    ],
    "sg:phone":"+44 1675 464591",
    "sg:postcode":"B46 2HL",
    "sg:province":"Warwickshire",
    "sg:tags":[
        "heating"
    ],
    "wof:name":"Peter Lapworth",
    "wof:placetype":"venue"
},
  "geometry": {"coordinates":[-1.678254,52.534809],"type":"Point"}
}