{
  "type": "Feature",
  "properties": {
    "iso:country":"GB",
    "sg:address":"114 New Road",
    "sg:city":"London",
    "sg:classifiers":[
        {
            "category":"Health Services",
            "subcategory":"Doctor",
            "type":"Services"
        }
    ],
    "sg:phone":"+44 20 8524 8124",
    "sg:postcode":"E4 9SY",
    "sg:province":"Greater London",
    "sg:tags":[
        "practitioners"
    ],
    "wof:name":"The Surgery",
    "wof:placetype":"venue"
},
  "geometry": {"coordinates":[-0.009151,51.617924],"type":"Point"}
}