{
  "type": "Feature",
  "properties": {
    "addr:full":"Financial Research Centre, Haddenham Business Park Aylesbury Buckinghamshire HP17 8LJ",
    "addr:housenumber":"haddenham",
    "addr:postcode":"hp17 8lj",
    "addr:street":"Business Park",
    "iso:country":"GB",
    "sg:address":"Financial Research Centre, Haddenham Business Park",
    "sg:city":"Aylesbury",
    "sg:classifiers":[
        {
            "category":"Government",
            "subcategory":"Post Office",
            "type":"Public Place"
        }
    ],
    "sg:phone":"+44 1844 295454",
    "sg:postcode":"HP17 8LJ",
    "sg:province":"Buckinghamshire",
    "sg:tags":[
        "organisation",
        "soc",
        "research"
    ],
    "wof:name":"Defaqto Ltd.",
    "wof:placetype":"venue"
},
  "geometry": {"coordinates":[-0.921174,51.775661],"type":"Point"}
}