{
  "type": "Feature",
  "properties": {
    "addr:full":"123 Seaford Rd Salford Greater Manchester M6 6DD",
    "addr:housenumber":"123",
    "addr:postcode":"m6 6dd",
    "addr:street":"Seaford Rd",
    "iso:country":"GB",
    "sg:address":"123 Seaford Rd",
    "sg:city":"Salford",
    "sg:classifiers":[
        {
            "category":"Building & Trades",
            "subcategory":"Construction",
            "type":"Services"
        }
    ],
    "sg:postcode":"M6 6DD",
    "sg:province":"Greater Manchester",
    "sg:tags":[
        "glazier"
    ],
    "wof:name":"S K Windows",
    "wof:placetype":"venue"
},
  "geometry": {"coordinates":[-2.273653,53.497105],"type":"Point"}
}