{
  "type": "Feature",
  "properties": {
    "addr:full":"Cobalt House, Theatre Court London Road Northwich Cheshire CW9 5HB",
    "addr:postcode":"cw9 5hb",
    "addr:street":"Court London Road",
    "iso:country":"GB",
    "sg:address":"Cobalt House, Theatre Court London Road",
    "sg:city":"Northwich",
    "sg:classifiers":[
        {
            "category":"Utilities",
            "subcategory":"Mobile Phone",
            "type":"Services"
        }
    ],
    "sg:phone":"+44 1606 42500",
    "sg:postcode":"CW9 5HB",
    "sg:province":"Cheshire",
    "sg:tags":[
        "coding",
        "bar"
    ],
    "wof:name":"Cobalt I S  Auto Id Ltd.",
    "wof:placetype":"venue"
},
  "geometry": {"coordinates":[-2.514115,53.259388],"type":"Point"}
}