{
  "type": "Feature",
  "properties": {
    "addr:full":"399 Rochdale Road Bury Lancashire BL9 7DB",
    "addr:housenumber":"399",
    "addr:postcode":"bl9 7db",
    "addr:street":"Rochdale Road",
    "iso:country":"GB",
    "sg:address":"399 Rochdale Road",
    "sg:city":"Bury",
    "sg:classifiers":[
        {
            "category":"Bars & Pubs",
            "type":"Food & Drink"
        }
    ],
    "sg:phone":"+44 161 764 7305",
    "sg:postcode":"BL9 7DB",
    "sg:province":"Lancashire",
    "sg:tags":[
        "pubs",
        "inn"
    ],
    "wof:name":"Seven Stars",
    "wof:placetype":"venue"
},
  "geometry": {"coordinates":[-2.2752571106,53.5920982361],"type":"Point"}
}