{
  "type": "Feature",
  "properties": {
    "addr:full":"79a Dean Drive Wilmslow Cheshire SK9 2EY",
    "addr:housenumber":"79a",
    "addr:postcode":"sk9 2ey",
    "addr:street":"Dean Drive",
    "iso:country":"GB",
    "sg:address":"79a Dean Drive",
    "sg:city":"Wilmslow",
    "sg:classifiers":[
        {
            "category":"Wholesale",
            "subcategory":"Sporting Goods",
            "type":"Manufacturing & Wholesale Goods"
        }
    ],
    "sg:postcode":"SK9 2EY",
    "sg:province":"Cheshire",
    "sg:tags":[
        "mnfr",
        "sport",
        "equipment"
    ],
    "wof:name":"Lacrosse Trading Co.",
    "wof:placetype":"venue"
},
  "geometry": {"coordinates":[-2.2182230949,53.3422012329],"type":"Point"}
}