{
  "type": "Feature",
  "properties": {
    "iso:country":"GB",
    "sg:address":"69a The Street, Old Basing",
    "sg:city":"Basingstoke",
    "sg:classifiers":[
        {
            "category":"Banks & Credit Unions",
            "subcategory":"Financial Services",
            "type":"Services"
        }
    ],
    "sg:postcode":"RG24 7BY",
    "sg:province":"Hampshire",
    "sg:tags":[
        "claim",
        "assessor"
    ],
    "wof:name":"Wings Assessors",
    "wof:placetype":"venue"
},
  "geometry": {"coordinates":[-1.046833,51.273666],"type":"Point"}
}