{
  "type": "Feature",
  "properties": {
    "addr:full":"Meadow Side, Plough Road, Tibberton Droitwich Worcestershire WR9 7NQ",
    "addr:postcode":"wr9 7nq",
    "addr:street":"Meadow;Plough Road;Droitwich",
    "iso:country":"GB",
    "sg:address":"Meadow Side, Plough Road, Tibberton",
    "sg:city":"Droitwich",
    "sg:classifiers":[
        {
            "category":"Building & Trades",
            "subcategory":"Landscaping Services",
            "type":"Services"
        }
    ],
    "sg:postcode":"WR9 7NQ",
    "sg:province":"Worcestershire",
    "sg:tags":[
        "pond",
        "aquarium"
    ],
    "wof:name":"Simply Fish Aquaria",
    "wof:placetype":"venue"
},
  "geometry": {"coordinates":[-2.1416790485,52.2122383118],"type":"Point"}
}