{
  "type": "Feature",
  "properties": {
    "addr:full":"18 Mill Road Rye East Sussex TN31 7NN",
    "addr:housenumber":"18",
    "addr:postcode":"tn31 7nn",
    "addr:street":"Mill Road",
    "iso:country":"GB",
    "sg:address":"18 Mill Road",
    "sg:city":"Rye",
    "sg:classifiers":[
        {
            "category":"Professional",
            "type":"Services"
        }
    ],
    "sg:phone":"+44 1797 224601",
    "sg:postcode":"TN31 7NN",
    "sg:province":"East Sussex",
    "sg:tags":[
        "entertainer"
    ],
    "wof:name":"Style Promotions",
    "wof:placetype":"venue"
},
  "geometry": {"coordinates":[0.7355430126,50.9590835571],"type":"Point"}
}