{
  "type": "Feature",
  "properties": {
    "iso:country":"GB",
    "sg:address":"90 High Street",
    "sg:city":"Banstead",
    "sg:classifiers":[
        {
            "category":"Wholesale",
            "subcategory":"Photographic Equipment",
            "type":"Manufacturing & Wholesale Goods"
        },
        {
            "category":"Shopping",
            "subcategory":"Photographic Equipment",
            "type":"Retail Goods"
        }
    ],
    "sg:phone":"+44 1737 370166",
    "sg:postcode":"SM7 2NN",
    "sg:province":"Surrey",
    "sg:tags":[
        "supply"
    ],
    "wof:name":"Banstead Photo Video Centre",
    "wof:placetype":"venue"
},
  "geometry": {"coordinates":[-0.199714,51.322933],"type":"Point"}
}