{
  "type": "Feature",
  "properties": {
    "addr:full":"236 Frodingham Road Scunthorpe Lincolnshire DN15 7NW",
    "addr:housenumber":"236",
    "addr:postcode":"dn15 7nw",
    "addr:street":"Frodingham Road",
    "iso:country":"GB",
    "sg:address":"236 Frodingham Road",
    "sg:city":"Scunthorpe",
    "sg:classifiers":[
        {
            "category":"Professional",
            "subcategory":"Printing & Photocopies",
            "type":"Services"
        }
    ],
    "sg:phone":"+44 1724 861655",
    "sg:postcode":"DN15 7NW",
    "sg:province":"Lincolnshire",
    "sg:tags":[
        "printer"
    ],
    "wof:name":"T S W Printers",
    "wof:placetype":"venue"
},
  "geometry": {"coordinates":[-0.6554319859,53.5969543457],"type":"Point"}
}