{
  "type": "Feature",
  "properties": {
    "iso:country":"GB",
    "sg:address":"13b Ropergate End",
    "sg:city":"Pontefract",
    "sg:classifiers":[
        {
            "category":"Shopping",
            "subcategory":"Florist",
            "type":"Retail Goods"
        }
    ],
    "sg:postcode":"WF8 1JX",
    "sg:province":"North Yorkshire",
    "wof:name":"Rosa Rugosa",
    "wof:placetype":"venue"
},
  "geometry": {"coordinates":[-1.312266,53.690407],"type":"Point"}
}