{
  "type": "Feature",
  "properties": {
    "addr:full":"Cavendish Dr Edgware Greater London HA8 7NS",
    "addr:postcode":"ha8 7ns",
    "addr:street":"Cavendish Dr",
    "iso:country":"GB",
    "sg:address":"Cavendish Dr",
    "sg:city":"Edgware",
    "sg:classifiers":[
        {
            "category":"Professional",
            "type":"Services"
        }
    ],
    "sg:phone":"+44 20 8800 6649",
    "sg:postcode":"HA8 7NS",
    "sg:province":"Greater London",
    "sg:tags":[
        "notary",
        "public"
    ],
    "wof:name":"Julian Kostick",
    "wof:placetype":"venue"
},
  "geometry": {"coordinates":[-0.283984,51.61203],"type":"Point"}
}