{
  "type": "Feature",
  "properties": {
    "addr:full":"Dean Clarke House, Southernhay East Exeter Devon EX1 1PQ",
    "addr:postcode":"ex1 1pq",
    "addr:street":"Southernhay East",
    "iso:country":"GB",
    "sg:address":"Dean Clarke House, Southernhay East",
    "sg:city":"Exeter",
    "sg:classifiers":[
        {
            "category":"Health Services",
            "subcategory":"Clinic",
            "type":"Services"
        }
    ],
    "sg:phone":"+44 1392 205205",
    "sg:postcode":"EX1 1PQ",
    "sg:province":"Devon",
    "sg:tags":[
        "nh"
    ],
    "wof:name":"NORTH & EAST DEVON HEALTH AUTHORITY",
    "wof:placetype":"venue"
},
  "geometry": {"coordinates":[-3.5316441059,50.7199058533],"type":"Point"}
}