{
  "type": "Feature",
  "properties": {
    "iso:country":"GB",
    "sg:address":"Out Lane, Croston",
    "sg:city":"Preston",
    "sg:classifiers":[
        {
            "category":"Education",
            "subcategory":"Library",
            "type":"Public Place"
        }
    ],
    "sg:phone":"+44 1772 600966",
    "sg:postcode":"PR5 7HJ",
    "sg:province":"Lancashire",
    "sg:tags":[
        "book"
    ],
    "wof:name":"Croston Trailer Library",
    "wof:placetype":"venue"
},
  "geometry": {"coordinates":[-2.77429,53.660721],"type":"Point"}
}