{
  "type": "Feature",
  "properties": {
    "addr:full":"Broomhill Grange, Edwinstowe Mansfield Nottinghamshire NG21 9HG",
    "addr:postcode":"ng21 9hg",
    "iso:country":"GB",
    "sg:address":"Broomhill Grange, Edwinstowe",
    "sg:city":"Mansfield",
    "sg:classifiers":[
        {
            "category":"Farming",
            "subcategory":"Livestock Farm",
            "type":"Manufacturing & Wholesale Goods"
        }
    ],
    "sg:phone":"+44 1623 822306",
    "sg:postcode":"NG21 9HG",
    "sg:province":"Nottinghamshire",
    "sg:tags":[
        "others"
    ],
    "wof:name":"J Bealby & Sons Ltd.",
    "wof:placetype":"venue"
},
  "geometry": {"coordinates":[-1.068122983,53.1949691772],"type":"Point"}
}