{
  "type": "Feature",
  "properties": {
    "addr:full":"Cavendish Street Barrow-in-furness Cumbria LA14 1SY",
    "addr:postcode":"la14 1sy",
    "addr:street":"Cavendish Street",
    "iso:country":"GB",
    "sg:address":"Cavendish Street",
    "sg:city":"Barrow-in-furness",
    "sg:classifiers":[
        {
            "category":"Social Services",
            "subcategory":"Adult Care",
            "type":"Services"
        },
        {
            "category":"Social Services",
            "subcategory":"Retirement Home",
            "type":"Services"
        }
    ],
    "sg:phone":"+44 1229 839151",
    "sg:postcode":"LA14 1SY",
    "sg:province":"Cumbria",
    "sg:tags":[
        "housing",
        "sheltered",
        "accommodation"
    ],
    "wof:name":"Ramsey Park",
    "wof:placetype":"venue"
},
  "geometry": {"coordinates":[-3.2239439487,54.1147384644],"type":"Point"}
}