{
  "type": "Feature",
  "properties": {
    "iso:country":"GB",
    "sg:address":"40 Westbourne Terrace",
    "sg:city":"Houghton-le-spring",
    "sg:classifiers":[
        {
            "category":"Shopping",
            "subcategory":"Pets & Pet Supplies",
            "type":"Retail Goods"
        }
    ],
    "sg:phone":"+44 191 385 9991",
    "sg:postcode":"DH4 4QU",
    "sg:province":"Durham",
    "sg:tags":[
        "food"
    ],
    "wof:name":"Family Pets",
    "wof:placetype":"venue"
},
  "geometry": {"coordinates":[-1.497049,54.867085],"type":"Point"}
}