{
  "type": "Feature",
  "properties": {
    "addr:full":"2a Thackerays Lane, Woodthorpe Nottingham Nottinghamshire NG5 4HP",
    "addr:housenumber":"2a",
    "addr:postcode":"ng5 4hp",
    "addr:street":"Thackerays Lane",
    "iso:country":"GB",
    "sg:address":"2a Thackerays Lane, Woodthorpe",
    "sg:city":"Nottingham",
    "sg:classifiers":[
        {
            "category":"Shopping",
            "subcategory":"Clothing, Apparel, & Fashions",
            "type":"Retail Goods"
        }
    ],
    "sg:phone":"+44 115 926 7050",
    "sg:postcode":"NG5 4HP",
    "sg:province":"Nottinghamshire",
    "sg:tags":[
        "shop"
    ],
    "wof:name":"Jenni Stewart Ltd.",
    "wof:placetype":"venue"
},
  "geometry": {"coordinates":[-1.1385840178,52.9932594299],"type":"Point"}
}