{
  "type": "Feature",
  "properties": {
    "iso:country":"GB",
    "sg:address":"Carlisle Street",
    "sg:city":"Leicester",
    "sg:classifiers":[
        {
            "category":"Retail",
            "subcategory":"Auto Repair",
            "type":"Services"
        }
    ],
    "sg:phone":"+44 116 255 8282",
    "sg:postcode":"LE3 6AH",
    "sg:province":"Leicestershire",
    "sg:tags":[
        "modification",
        "garage",
        "related"
    ],
    "wof:name":"B H SERVICES",
    "wof:placetype":"venue"
},
  "geometry": {"coordinates":[-1.158424,52.634735],"type":"Point"}
}