{
  "type": "Feature",
  "properties": {
    "addr:full":"12a Woodbine Place, Wanstead London Greater London E11 2RH",
    "addr:housenumber":"12a",
    "addr:postcode":"e11 2rh",
    "addr:street":"Woodbine Place",
    "iso:country":"GB",
    "sg:address":"12a Woodbine Place, Wanstead",
    "sg:city":"London",
    "sg:classifiers":[
        {
            "category":"Wholesale",
            "subcategory":"Photographic Equipment",
            "type":"Manufacturing & Wholesale Goods"
        }
    ],
    "sg:phone":"+44 20 8989 1674",
    "sg:postcode":"E11 2RH",
    "sg:province":"Greater London",
    "sg:tags":[
        "w'sale"
    ],
    "wof:name":"Argon Europe Ltd.",
    "wof:placetype":"venue"
},
  "geometry": {"coordinates":[0.0253040008,51.5760726929],"type":"Point"}
}