{
  "type": "Feature",
  "properties": {
    "addr:full":"Sycamore Mews, Sycamore Street, Blaby Leicester Leicestershire LE8 4FL",
    "addr:postcode":"le8 4fl",
    "addr:street":"Sycamore Mews Sycamore Street",
    "iso:country":"GB",
    "sg:address":"Sycamore Mews, Sycamore Street, Blaby",
    "sg:city":"Leicester",
    "sg:classifiers":[
        {
            "category":"Shopping",
            "subcategory":"Beauty & Cosmetics",
            "type":"Retail Goods"
        }
    ],
    "sg:phone":"+44 116 277 2660",
    "sg:postcode":"LE8 4FL",
    "sg:province":"Leicestershire",
    "sg:tags":[
        "equipment",
        "supply",
        "hairdressing"
    ],
    "wof:name":"Hair & Beauty Supplies L & N",
    "wof:placetype":"venue"
},
  "geometry": {"coordinates":[-1.1647130251,52.5734481812],"type":"Point"}
}