{
  "type": "Feature",
  "properties": {
    "iso:country":"GB",
    "sg:address":"2 Bude Street, Appledore",
    "sg:city":"Bideford",
    "sg:classifiers":[
        {
            "category":"Manufacturing",
            "subcategory":"Signs",
            "type":"Manufacturing & Wholesale Goods"
        }
    ],
    "sg:postcode":"EX39 1PS",
    "sg:province":"Devon",
    "sg:tags":[
        "writer"
    ],
    "wof:name":"Frank Arnold",
    "wof:placetype":"venue"
},
  "geometry": {"coordinates":[-4.191254,51.053001],"type":"Point"}
}