{
  "type": "Feature",
  "properties": {
    "iso:country":"GB",
    "sg:address":"Sluice Rd, South Ferriby",
    "sg:city":"Barton-upon-humber",
    "sg:classifiers":[
        {
            "category":"Government",
            "subcategory":"Post Office",
            "type":"Public Place"
        }
    ],
    "sg:postcode":"DN18 6JA",
    "sg:province":"Lincolnshire",
    "wof:name":"Heathershaw J P",
    "wof:placetype":"venue"
},
  "geometry": {"coordinates":[-0.5199,53.676773],"type":"Point"}
}