{
  "type": "Feature",
  "properties": {
    "iso:country":"GB",
    "sg:address":"17 Woburn Place",
    "sg:city":"London",
    "sg:classifiers":[
        {
            "category":"Banks & Credit Unions",
            "subcategory":"Bureau De Change",
            "type":"Services"
        }
    ],
    "sg:phone":"+44 20 7278 9924",
    "sg:postcode":"WC1H 0LU",
    "sg:province":"Greater London",
    "wof:name":"N Anand",
    "wof:placetype":"venue"
},
  "geometry": {"coordinates":[-0.126923,51.524017],"type":"Point"}
}