{
  "type": "Feature",
  "properties": {
    "addr:full":"Churchill Yard Industrial Estate, Jubilee Road Waterlooville Hampshire PO7 7RF",
    "addr:housenumber":"estate",
    "addr:postcode":"po7 7rf",
    "addr:street":"Churchill Yard Industrial;Jubilee Road",
    "iso:country":"GB",
    "sg:address":"Churchill Yard Industrial Estate, Jubilee Road",
    "sg:city":"Waterlooville",
    "sg:classifiers":[
        {
            "category":"Professional",
            "subcategory":"Engineering",
            "type":"Services"
        }
    ],
    "sg:phone":"+44 23 9226 3122",
    "sg:postcode":"PO7 7RF",
    "sg:province":"Hampshire",
    "sg:tags":[
        "precision",
        "engineer"
    ],
    "wof:name":"Goble & Cross (Engineering) Ltd.",
    "wof:placetype":"venue"
},
  "geometry": {"coordinates":[-1.0288540125,50.8826332092],"type":"Point"}
}