{
  "type": "Feature",
  "properties": {
    "addr:full":"1 Colville Mews, Lonsdale Road London Greater London W11 2AR",
    "addr:housenumber":"1",
    "addr:postcode":"w11 2ar",
    "addr:street":"Colville Mews Lonsdale Road",
    "iso:country":"GB",
    "sg:address":"1 Colville Mews, Lonsdale Road",
    "sg:city":"London",
    "sg:classifiers":[
        {
            "category":"Professional",
            "subcategory":"Business Services",
            "type":"Services"
        }
    ],
    "sg:phone":"+44 20 7727 3226",
    "sg:postcode":"W11 2AR",
    "sg:province":"Greater London",
    "sg:tags":[
        "accomodation"
    ],
    "wof:name":"Bemacraft Ltd.",
    "wof:placetype":"venue"
},
  "geometry": {"coordinates":[-0.2012889981,51.5149726868],"type":"Point"}
}