{
  "type": "Feature",
  "properties": {
    "addr:full":"20 Mackenders La Aylesford Kent ME20 7HX",
    "addr:housenumber":"20",
    "addr:postcode":"me20 7hx",
    "addr:street":"Mackenders La Aylesford",
    "iso:country":"GB",
    "sg:address":"20 Mackenders La",
    "sg:city":"Aylesford",
    "sg:classifiers":[
        {
            "category":"Home & Garden",
            "subcategory":"Carpets & Floor Coverings",
            "type":"Retail Goods"
        }
    ],
    "sg:phone":"+44 1622 882213",
    "sg:postcode":"ME20 7HX",
    "sg:province":"Kent",
    "sg:tags":[
        "carpets",
        "rug",
        "matting"
    ],
    "wof:name":"Floor Coverings International",
    "wof:placetype":"venue"
},
  "geometry": {"coordinates":[0.48235,51.319092],"type":"Point"}
}