{
  "type": "Feature",
  "properties": {
    "addr:full":"Holme Mill, Railway Street, Ramsbottom Bury Lancashire BL0 9AU",
    "addr:postcode":"bl0 9au",
    "addr:street":"Holme;Railway Street",
    "iso:country":"GB",
    "sg:address":"Holme Mill, Railway Street, Ramsbottom",
    "sg:city":"Bury",
    "sg:classifiers":[
        {
            "category":"Manufacturing",
            "subcategory":"Textiles",
            "type":"Manufacturing & Wholesale Goods"
        },
        {
            "category":"Manufacturing",
            "subcategory":"Retail Goods",
            "type":"Manufacturing & Wholesale Goods"
        }
    ],
    "sg:phone":"+44 1706 825211",
    "sg:postcode":"BL0 9AU",
    "sg:province":"Lancashire",
    "sg:tags":[
        "mnfr",
        "carpet",
        "rug",
        "manufacturer"
    ],
    "wof:name":"Greenwood & Coope Ltd",
    "wof:placetype":"venue"
},
  "geometry": {"coordinates":[-2.318599,53.648476],"type":"Point"}
}