{
  "type": "Feature",
  "properties": {
    "iso:country":"GB",
    "sg:address":"15 Woodside Crescent",
    "sg:city":"Glasgow",
    "sg:classifiers":[
        {
            "category":"Real Estate",
            "subcategory":"Surveying",
            "type":"Services"
        }
    ],
    "sg:postcode":"G3 7UL",
    "sg:province":"Glasgow City",
    "sg:tags":[
        "surveyor",
        "quantity"
    ],
    "wof:name":"Doig Hart Consultants",
    "wof:placetype":"venue"
},
  "geometry": {"coordinates":[-4.272262,55.867649],"type":"Point"}
}