{
  "type": "Feature",
  "properties": {
    "addr:full":"142 Fortess Rd Kentish Town Greater London NW5 2HP",
    "addr:housenumber":"142",
    "addr:postcode":"nw5 2hp",
    "addr:street":"Fortess Rd",
    "iso:country":"GB",
    "sg:address":"142 Fortess Rd",
    "sg:city":"Kentish Town",
    "sg:classifiers":[
        {
            "category":"Communications",
            "subcategory":"Film & Video Production",
            "type":"Services"
        }
    ],
    "sg:phone":"+44 20 7485 1591",
    "sg:postcode":"NW5 2HP",
    "sg:province":"Greater London",
    "sg:tags":[
        "tv"
    ],
    "wof:name":"Camden Rentals",
    "wof:placetype":"venue"
},
  "geometry": {"coordinates":[-0.1391070038,51.5555725098],"type":"Point"}
}