{
  "type": "Feature",
  "properties": {
    "addr:full":"2 Roscoe Place Liverpool Merseyside L1 4HF",
    "addr:housenumber":"2",
    "addr:postcode":"l1 4hf",
    "addr:street":"Roscoe Place",
    "iso:country":"GB",
    "sg:address":"2 Roscoe Place",
    "sg:city":"Liverpool",
    "sg:classifiers":[
        {
            "category":"Organizations",
            "subcategory":"Non-profit Organization",
            "type":"Services"
        }
    ],
    "sg:postcode":"L1 4HF",
    "sg:province":"Merseyside",
    "sg:tags":[
        "organisation",
        "voluntary",
        "charity"
    ],
    "wof:name":"The Weston Spirit",
    "wof:placetype":"venue"
},
  "geometry": {"coordinates":[-2.976828,53.402199],"type":"Point"}
}