{
  "type": "Feature",
  "properties": {
    "addr:full":"Tape Street, Cheadle Stoke-on-trent Staffordshire ST10 1BG",
    "addr:postcode":"st10 1bg",
    "addr:street":"Tape Street Cheadle",
    "iso:country":"GB",
    "sg:address":"Tape Street, Cheadle",
    "sg:city":"Stoke-on-trent",
    "sg:classifiers":[
        {
            "category":"Bars & Pubs",
            "type":"Food & Drink"
        }
    ],
    "sg:phone":"+44 1538 751175",
    "sg:postcode":"ST10 1BG",
    "sg:province":"Staffordshire",
    "sg:tags":[
        "pubs",
        "inn"
    ],
    "wof:name":"The Alton Castle",
    "wof:placetype":"venue"
},
  "geometry": {"coordinates":[-1.9872339964,52.9883117676],"type":"Point"}
}