{
  "type": "Feature",
  "properties": {
    "iso:country":"GB",
    "sg:address":"Fosse Farm, Withybrook",
    "sg:city":"Coventry",
    "sg:classifiers":[
        {
            "category":"Farming",
            "subcategory":"Livestock Farm",
            "type":"Manufacturing & Wholesale Goods"
        },
        {
            "category":"Farming",
            "subcategory":"Farm",
            "type":"Manufacturing & Wholesale Goods"
        }
    ],
    "sg:phone":"+44 1788 832291",
    "sg:postcode":"CV7 9LR",
    "sg:province":"Warwickshire",
    "sg:tags":[
        "mixed",
        "crop",
        "others"
    ],
    "wof:name":"Thomas John Dewes",
    "wof:placetype":"venue"
},
  "geometry": {"coordinates":[-1.360855,52.453175],"type":"Point"}
}