{
  "type": "Feature",
  "properties": {
    "addr:full":"12 Windsor Terrace Whitby North Yorkshire YO21 1ET",
    "addr:housenumber":"12",
    "addr:postcode":"yo21 1et",
    "addr:street":"Windsor Terrace",
    "iso:country":"GB",
    "sg:address":"12 Windsor Terrace",
    "sg:city":"Whitby",
    "sg:classifiers":[
        {
            "category":"Shopping",
            "type":"Retail Goods"
        }
    ],
    "sg:phone":"+44 1947 604708",
    "sg:postcode":"YO21 1ET",
    "sg:province":"North Yorkshire",
    "sg:tags":[
        "merchant"
    ],
    "wof:name":"Abbott & Co",
    "wof:placetype":"venue"
},
  "geometry": {"coordinates":[-0.614503,54.483318],"type":"Point"}
}