{
  "type": "Feature",
  "properties": {
    "addr:full":"7 Weston Street Heanor Derbyshire DE75 7NG",
    "addr:housenumber":"7",
    "addr:postcode":"de75 7ng",
    "addr:street":"Weston Street",
    "iso:country":"GB",
    "sg:address":"7 Weston Street",
    "sg:city":"Heanor",
    "sg:classifiers":[
        {
            "category":"Manufacturing",
            "subcategory":"Wood Products",
            "type":"Manufacturing & Wholesale Goods"
        },
        {
            "category":"Building & Trades",
            "subcategory":"Construction",
            "type":"Services"
        }
    ],
    "sg:phone":"+44 1773 716892",
    "sg:postcode":"DE75 7NG",
    "sg:province":"Derbyshire",
    "sg:tags":[
        "joinery",
        "manufacturer"
    ],
    "wof:name":"Housley & Birks",
    "wof:placetype":"venue"
},
  "geometry": {"coordinates":[-1.3435230255,53.0082092285],"type":"Point"}
}