{
  "type": "Feature",
  "properties": {
    "addr:full":"Eastfield Road Enfield Greater London EN3 5UX",
    "addr:postcode":"en3 5ux",
    "addr:street":"Eastfield Road",
    "iso:country":"GB",
    "sg:address":"Eastfield Road",
    "sg:city":"Enfield",
    "sg:classifiers":[
        {
            "category":"Education",
            "subcategory":"School",
            "type":"Public Place"
        },
        {
            "category":"Government",
            "subcategory":"Office",
            "type":"Public Place"
        }
    ],
    "sg:phone":"+44 20 8804 5013",
    "sg:postcode":"EN3 5UX",
    "sg:province":"Greater London",
    "sg:tags":[
        "local",
        "authority"
    ],
    "wof:name":"Eastfield Primary School",
    "wof:placetype":"venue"
},
  "geometry": {"coordinates":[-0.039731,51.666203],"type":"Point"}
}