{
  "type": "Feature",
  "properties": {
    "addr:full":"10 Market Street Wisbech Cambridgeshire PE13 1EX",
    "addr:housenumber":"10",
    "addr:postcode":"pe13 1ex",
    "addr:street":"Market Street",
    "iso:country":"GB",
    "sg:address":"10 Market Street",
    "sg:city":"Wisbech",
    "sg:classifiers":[
        {
            "category":"Professional",
            "subcategory":"Employment Agencies",
            "type":"Services"
        }
    ],
    "sg:phone":"+44 1945 464747",
    "sg:postcode":"PE13 1EX",
    "sg:province":"Cambridgeshire",
    "sg:tags":[
        "agricultural",
        "advice"
    ],
    "wof:name":"William H Brown",
    "wof:placetype":"venue"
},
  "geometry": {"coordinates":[0.1611,52.66478],"type":"Point"}
}