{
  "type": "Feature",
  "properties": {
    "addr:full":"24 Orchard Close, Weaverhead Lane, Thaxted Dunmow Essex CM6 2JX",
    "addr:housenumber":"24",
    "addr:postcode":"cm6 2jx",
    "addr:street":"Orchard Close Weaverhead Lane",
    "iso:country":"GB",
    "sg:address":"24 Orchard Close, Weaverhead Lane, Thaxted",
    "sg:city":"Dunmow",
    "sg:classifiers":[
        {
            "category":"Retail",
            "subcategory":"Driving School",
            "type":"Services"
        }
    ],
    "sg:postcode":"CM6 2JX",
    "sg:province":"Essex",
    "wof:name":"Bradbury School of Motoring",
    "wof:placetype":"venue"
},
  "geometry": {"coordinates":[0.3442569971,51.9549102783],"type":"Point"}
}