{
  "type": "Feature",
  "properties": {
    "addr:full":"32 Queens Road Nuneaton Leicestershire CV11 5JU",
    "addr:housenumber":"32",
    "addr:postcode":"cv11 5ju",
    "addr:street":"Queens Road",
    "iso:country":"GB",
    "sg:address":"32 Queens Road",
    "sg:city":"Nuneaton",
    "sg:classifiers":[
        {
            "category":"Communications",
            "subcategory":"Film & Video Production",
            "type":"Services"
        }
    ],
    "sg:phone":"+44 24 7638 4401",
    "sg:postcode":"CV11 5JU",
    "sg:province":"Leicestershire",
    "sg:tags":[
        "tv"
    ],
    "wof:name":"Granada Home Technology",
    "wof:placetype":"venue"
},
  "geometry": {"coordinates":[-1.4710839987,52.5226593018],"type":"Point"}
}