{
  "type": "Feature",
  "properties": {
    "addr:full":"Queen Alexandra Road North Shields Tyne and Wear NE29 9AL",
    "addr:postcode":"ne29 9al",
    "addr:street":"Queen Alexandra Road",
    "iso:country":"GB",
    "sg:address":"Queen Alexandra Road",
    "sg:city":"North Shields",
    "sg:classifiers":[
        {
            "category":"Autos & Motor Vehicles",
            "subcategory":"Automobile Sales",
            "type":"Retail Goods"
        },
        {
            "category":"Bars & Pubs",
            "type":"Food & Drink"
        }
    ],
    "sg:postcode":"NE29 9AL",
    "sg:province":"Tyne and Wear",
    "sg:tags":[
        "pubs",
        "car",
        "inn"
    ],
    "wof:name":"Hallewell,M W,",
    "wof:placetype":"venue"
},
  "geometry": {"coordinates":[-1.4561599493,55.0145301819],"type":"Point"}
}