{
  "type": "Feature",
  "properties": {
    "addr:full":"111 King Street Knutsford Cheshire WA16 6EH",
    "addr:housenumber":"111",
    "addr:postcode":"wa16 6eh",
    "addr:street":"King Street",
    "iso:country":"GB",
    "sg:address":"111 King Street",
    "sg:city":"Knutsford",
    "sg:classifiers":[
        {
            "category":"Shopping",
            "subcategory":"Clothing, Apparel, & Fashions",
            "type":"Retail Goods"
        }
    ],
    "sg:phone":"+44 1565 633680",
    "sg:postcode":"WA16 6EH",
    "sg:province":"Cheshire",
    "sg:tags":[
        "dresswear"
    ],
    "wof:name":"Second Elegance Dress Agency",
    "wof:placetype":"venue"
},
  "geometry": {"coordinates":[-2.3738520145,53.3055419922],"type":"Point"}
}