{
  "type": "Feature",
  "properties": {
    "addr:full":"Ingleby Way, Off Barwick Way, Ingleby Barwick Stockton-on-tees Durham TS17 0RH",
    "addr:postcode":"ts17 0rh",
    "addr:street":"Ingleby Way Off Barwick Way",
    "iso:country":"GB",
    "sg:address":"Ingleby Way, Off Barwick Way, Ingleby Barwick",
    "sg:city":"Stockton-on-tees",
    "sg:classifiers":[
        {
            "category":"Autos & Motor Vehicles",
            "subcategory":"Fuel & Gas Station",
            "type":"Retail Goods"
        },
        {
            "category":"Food & Beverages",
            "subcategory":"Supermarket",
            "type":"Retail Goods"
        }
    ],
    "sg:phone":"+44 1642 762816",
    "sg:postcode":"TS17 0RH",
    "sg:province":"Durham",
    "sg:tags":[
        "petrol",
        "filling"
    ],
    "wof:name":"Safeway Stores Ltd.",
    "wof:placetype":"venue"
},
  "geometry": {"coordinates":[-1.2982939482,54.5237731934],"type":"Point"}
}