{
  "type": "Feature",
  "properties": {
    "iso:country":"GB",
    "sg:address":"6-8 School La",
    "sg:city":"Wigan",
    "sg:classifiers":[
        {
            "category":"Building & Trades",
            "subcategory":"Construction",
            "type":"Services"
        }
    ],
    "sg:phone":"+44 1257 426126",
    "sg:postcode":"WN6 0TD",
    "sg:province":"Lancashire",
    "sg:tags":[
        "builder"
    ],
    "wof:name":"John Culshaw",
    "wof:placetype":"venue"
},
  "geometry": {"coordinates":[-2.6646840572,53.5864639282],"type":"Point"}
}