{
  "type": "Feature",
  "properties": {
    "iso:country":"GB",
    "sg:address":"981 Ecclesall Road",
    "sg:city":"Sheffield",
    "sg:classifiers":[
        {
            "category":"Real Estate",
            "subcategory":"Real Estate Agent",
            "type":"Services"
        }
    ],
    "sg:phone":"+44 114 268 2000",
    "sg:postcode":"S11 8TN",
    "sg:province":"Derbyshire",
    "wof:name":"Property Plus",
    "wof:placetype":"venue"
},
  "geometry": {"coordinates":[-1.508062005,53.3613471985],"type":"Point"}
}