{
  "type": "Feature",
  "properties": {
    "iso:country":"GB",
    "sg:address":"23 Cumberland Street",
    "sg:city":"Macclesfield",
    "sg:classifiers":[
        {
            "category":"Health Services",
            "subcategory":"Health Practitioner",
            "type":"Services"
        }
    ],
    "sg:phone":"+44 1625 434202",
    "sg:postcode":"SK10 1DD",
    "sg:province":"Cheshire",
    "sg:tags":[
        "osteopath"
    ],
    "wof:name":"Denis Brown Osteopath",
    "wof:placetype":"venue"
},
  "geometry": {"coordinates":[-2.126879,53.262424],"type":"Point"}
}