{
  "type": "Feature",
  "properties": {
    "addr:full":"8 Moreton Crescent Shrewsbury Shropshire SY3 7BZ",
    "addr:housenumber":"8",
    "addr:postcode":"sy3 7bz",
    "addr:street":"Moreton Crescent",
    "iso:country":"GB",
    "sg:address":"8 Moreton Crescent",
    "sg:city":"Shrewsbury",
    "sg:classifiers":[
        {
            "category":"Building & Trades",
            "subcategory":"Construction",
            "type":"Services"
        }
    ],
    "sg:phone":"+44 1743 235447",
    "sg:postcode":"SY3 7BZ",
    "sg:province":"Shropshire",
    "sg:tags":[
        "decorator",
        "painter"
    ],
    "wof:name":"J F Owen & Sons",
    "wof:placetype":"venue"
},
  "geometry": {"coordinates":[-2.745384,52.705078],"type":"Point"}
}