{
  "type": "Feature",
  "properties": {
    "iso:country":"GB",
    "sg:address":"27 East Street",
    "sg:city":"Hereford",
    "sg:classifiers":[
        {
            "category":"Professional",
            "subcategory":"Accounting & Tax Preparation",
            "type":"Services"
        }
    ],
    "sg:phone":"+44 1432 273845",
    "sg:postcode":"HR1 2LU",
    "sg:province":"Herefordshire",
    "sg:tags":[
        "accountant",
        "activity"
    ],
    "wof:name":"Diana Duggan & Co",
    "wof:placetype":"venue"
},
  "geometry": {"coordinates":[-2.7134449482,52.0552215576],"type":"Point"}
}