{
  "type": "Feature",
  "properties": {
    "iso:country":"GB",
    "sg:address":"46 Gibson Street",
    "sg:city":"Wrexham",
    "sg:classifiers":[
        {
            "category":"Professional",
            "subcategory":"Employment Agencies",
            "type":"Services"
        }
    ],
    "sg:phone":"+44 1978 351596",
    "sg:postcode":"LL13 7TS",
    "sg:province":"Wrexham",
    "sg:tags":[
        "consultant"
    ],
    "wof:name":"P Murphy",
    "wof:placetype":"venue"
},
  "geometry": {"coordinates":[-3.003986,53.043392],"type":"Point"}
}