{
  "type": "Feature",
  "properties": {
    "iso:country":"GB",
    "sg:address":"72 Berkeley Av",
    "sg:city":"Reading",
    "sg:classifiers":[
        {
            "category":"Health Services",
            "subcategory":"Doctor",
            "type":"Services"
        }
    ],
    "sg:phone":"+44 118 958 4711",
    "sg:postcode":"RG1 6HY",
    "sg:province":"Berkshire",
    "sg:tags":[
        "surgeon"
    ],
    "wof:name":"B M Billington",
    "wof:placetype":"venue"
},
  "geometry": {"coordinates":[-0.987918,51.447464],"type":"Point"}
}