{
  "type": "Feature",
  "properties": {
    "addr:full":"Swanns Barn, 10 Banningham Road, Tuttington Norwich Norfolk NR11 6TG",
    "addr:housenumber":"10",
    "addr:postcode":"nr11 6tg",
    "addr:street":"Banningham Road",
    "iso:country":"GB",
    "sg:address":"Swanns Barn, 10 Banningham Road, Tuttington",
    "sg:city":"Norwich",
    "sg:classifiers":[
        {
            "category":"Building & Trades",
            "subcategory":"Construction",
            "type":"Services"
        }
    ],
    "sg:postcode":"NR11 6TG",
    "sg:province":"Norfolk",
    "sg:tags":[
        "builder"
    ],
    "wof:name":"Kt Drilling Consultants Ltd",
    "wof:placetype":"venue"
},
  "geometry": {"coordinates":[1.30072,52.797226],"type":"Point"}
}