{
  "type": "Feature",
  "properties": {
    "iso:country":"GB",
    "sg:address":"Charles House, 5 Regent Street",
    "sg:city":"London",
    "sg:classifiers":[
        {
            "category":"Government",
            "subcategory":"Office",
            "type":"Public Place"
        }
    ],
    "sg:phone":"+44 20 7321 5600",
    "sg:postcode":"SW1Y 4LR",
    "sg:province":"Greater London",
    "sg:tags":[
        "central"
    ],
    "wof:name":"Contact Singapore",
    "wof:placetype":"venue"
},
  "geometry": {"coordinates":[-0.133646,51.508148],"type":"Point"}
}