{
  "type": "Feature",
  "properties": {
    "iso:country":"GB",
    "sg:address":"Cliff Rd",
    "sg:city":"Hornsea",
    "sg:classifiers":[
        {
            "category":"Retail",
            "subcategory":"Storage",
            "type":"Services"
        }
    ],
    "sg:phone":"+44 1262 672842",
    "sg:postcode":"HU18 1JB",
    "sg:province":"East Riding of Yorkshire",
    "sg:tags":[
        "household",
        "removal"
    ],
    "wof:name":"Kidds Removals",
    "wof:placetype":"venue"
},
  "geometry": {"coordinates":[-0.1718389988,53.9082336426],"type":"Point"}
}