{
  "type": "Feature",
  "properties": {
    "iso:country":"GB",
    "sg:address":"Ayston Mill, Ayston Road, Uppingham",
    "sg:city":"Oakham",
    "sg:classifiers":[
        {
            "category":"Professional",
            "subcategory":"Management & Consulting",
            "type":"Services"
        }
    ],
    "sg:postcode":"LE15 9RL",
    "sg:province":"Leicestershire",
    "sg:tags":[
        "consultant",
        "training"
    ],
    "wof:name":"A Hamilton Ltd.",
    "wof:placetype":"venue"
},
  "geometry": {"coordinates":[-0.730297,52.599373],"type":"Point"}
}