{
  "type": "Feature",
  "properties": {
    "addr:full":"Westbourne Centre, Kelburn Street, Barrhead Glasgow East Ayrshire G78 1LR",
    "addr:postcode":"g78 1lr",
    "addr:street":"Kelburn Street",
    "iso:country":"GB",
    "sg:address":"Westbourne Centre, Kelburn Street, Barrhead",
    "sg:city":"Glasgow",
    "sg:classifiers":[
        {
            "category":"Shopping",
            "subcategory":"Pets & Pet Supplies",
            "type":"Retail Goods"
        }
    ],
    "sg:phone":"+44 141 881 2992",
    "sg:postcode":"G78 1LR",
    "sg:province":"East Ayrshire",
    "wof:name":"James Gibb Country Feeds",
    "wof:placetype":"venue"
},
  "geometry": {"coordinates":[-4.4044981003,55.7953147888],"type":"Point"}
}