{
  "type": "Feature",
  "properties": {
    "iso:country":"GB",
    "sg:address":"48 Craven Park Road",
    "sg:city":"London",
    "sg:classifiers":[
        {
            "category":"Professional",
            "type":"Services"
        },
        {
            "category":"Fast Food",
            "type":"Food & Drink"
        }
    ],
    "sg:phone":"+44 20 8965 4055",
    "sg:postcode":"NW10 4AE",
    "sg:province":"Greater London",
    "sg:tags":[
        "take",
        "away",
        "meal",
        "outlet",
        "caterer"
    ],
    "wof:name":"Mister Patty",
    "wof:placetype":"venue"
},
  "geometry": {"coordinates":[-0.250696,51.539143],"type":"Point"}
}