{
  "type": "Feature",
  "properties": {
    "iso:country":"GB",
    "sg:address":"6 Orchard Street",
    "sg:city":"Gillingham",
    "sg:classifiers":[
        {
            "category":"Retail",
            "subcategory":"Auto Repair",
            "type":"Services"
        }
    ],
    "sg:phone":"+44 1634 263804",
    "sg:postcode":"ME8 9AA",
    "sg:province":"Kent",
    "sg:tags":[
        "modification",
        "garage"
    ],
    "wof:name":"Parkwood Auto Services",
    "wof:placetype":"venue"
},
  "geometry": {"coordinates":[0.606663,51.363438],"type":"Point"}
}