{
  "type": "Feature",
  "properties": {
    "addr:full":"68-70 Chapel Ash Wolverhampton Staffordshire WV3 0TT",
    "addr:housenumber":"68-70",
    "addr:postcode":"wv3 0tt",
    "addr:street":"Chapel Ash",
    "iso:country":"GB",
    "sg:address":"68-70 Chapel Ash",
    "sg:city":"Wolverhampton",
    "sg:classifiers":[
        {
            "category":"Fast Food",
            "type":"Food & Drink"
        }
    ],
    "sg:phone":"+44 1902 311223",
    "sg:postcode":"WV3 0TT",
    "sg:province":"Staffordshire",
    "sg:tags":[
        "away",
        "take"
    ],
    "wof:name":"Loonchun Chinese Takeaway",
    "wof:placetype":"venue"
},
  "geometry": {"coordinates":[-2.13893,52.585381],"type":"Point"}
}