{
  "type": "Feature",
  "properties": {
    "addr:full":"13 Rolle Street Exmouth Devon EX8 1HA",
    "addr:housenumber":"13",
    "addr:postcode":"ex8 1ha",
    "addr:street":"Rolle Street",
    "iso:country":"GB",
    "sg:address":"13 Rolle Street",
    "sg:city":"Exmouth",
    "sg:classifiers":[
        {
            "category":"Shopping",
            "subcategory":"Department Store",
            "type":"Retail Goods"
        }
    ],
    "sg:phone":"+44 1395 223823",
    "sg:postcode":"EX8 1HA",
    "sg:province":"Devon",
    "wof:name":"Linda Jones",
    "wof:placetype":"venue"
},
  "geometry": {"coordinates":[-3.4132258892,50.6195869446],"type":"Point"}
}