{
  "type": "Feature",
  "properties": {
    "addr:full":"Hangar 125 London Luton Airport Luton Bedfordshire LU2 9LR",
    "addr:housenumber":"125",
    "addr:postcode":"lu2 9lr",
    "iso:country":"GB",
    "sg:address":"Hangar 125 London Luton Airport",
    "sg:city":"Luton",
    "sg:classifiers":[
        {
            "category":"Manufacturing",
            "subcategory":"Aerospace",
            "type":"Manufacturing & Wholesale Goods"
        }
    ],
    "sg:phone":"+44 1582 726760",
    "sg:postcode":"LU2 9LR",
    "sg:province":"Bedfordshire",
    "sg:tags":[
        "aircraft",
        "component"
    ],
    "wof:name":"Hamlin Jet Ltd.",
    "wof:placetype":"venue"
},
  "geometry": {"coordinates":[-0.375695,51.877029],"type":"Point"}
}