{
  "type": "Feature",
  "properties": {
    "addr:full":"166 Bramley Road, Oakwood London Greater London N14 4HX",
    "addr:housenumber":"166",
    "addr:postcode":"n14 4hx",
    "addr:street":"Bramley Road",
    "iso:country":"GB",
    "sg:address":"166 Bramley Road, Oakwood",
    "sg:city":"London",
    "sg:classifiers":[
        {
            "category":"Health Services",
            "subcategory":"Health Practitioner",
            "type":"Services"
        }
    ],
    "sg:postcode":"N14 4HX",
    "sg:province":"Greater London",
    "sg:tags":[
        "osteopath"
    ],
    "wof:name":"Oakwood Osteopaths",
    "wof:placetype":"venue"
},
  "geometry": {"coordinates":[-0.1346749961,51.6472434998],"type":"Point"}
}