{
  "type": "Feature",
  "properties": {
    "addr:full":"Unit 2/7 Bumpers Farm Industrial Estate, Bumpers Waybristol Road Chippenham Gloucestershire SN14 6LH",
    "addr:housenumber":"unit 2 / 7 bumpers;industrial",
    "addr:postcode":"sn14 6lh",
    "addr:street":"Waybristol Road",
    "iso:country":"GB",
    "sg:address":"Unit 2/7 Bumpers Farm Industrial Estate, Bumpers Waybristol Road",
    "sg:city":"Chippenham",
    "sg:classifiers":[
        {
            "category":"Home & Garden",
            "subcategory":"Hardware",
            "type":"Retail Goods"
        }
    ],
    "sg:phone":"+44 1249 655481",
    "sg:postcode":"SN14 6LH",
    "sg:province":"Gloucestershire",
    "sg:tags":[
        "wheel",
        "castor"
    ],
    "wof:name":"Dymag Racing U K Ltd.",
    "wof:placetype":"venue"
},
  "geometry": {"coordinates":[-2.12621,51.463348],"type":"Point"}
}