{
  "type": "Feature",
  "properties": {
    "addr:full":"Atkinson Service Station, Sluice Road Barton-upon-humber Lincolnshire DN18 6JG",
    "addr:postcode":"dn18 6jg",
    "addr:street":"Sluice Road",
    "iso:country":"GB",
    "sg:address":"Atkinson Service Station, Sluice Road",
    "sg:city":"Barton-upon-humber",
    "sg:classifiers":[
        {
            "category":"Home & Garden",
            "subcategory":"Hardware",
            "type":"Retail Goods"
        }
    ],
    "sg:postcode":"DN18 6JG",
    "sg:province":"Lincolnshire",
    "sg:tags":[
        "lawnmowers",
        "machinery"
    ],
    "wof:name":"Harry Emms",
    "wof:placetype":"venue"
},
  "geometry": {"coordinates":[-0.443241,53.684448],"type":"Point"}
}