{
  "type": "Feature",
  "properties": {
    "addr:full":"9 Barnkirk Ave Glasgow Glasgow City G15 7SF",
    "addr:housenumber":"9",
    "addr:postcode":"g15 7sf",
    "addr:street":"Barnkirk Ave",
    "iso:country":"GB",
    "sg:address":"9 Barnkirk Ave",
    "sg:city":"Glasgow",
    "sg:classifiers":[
        {
            "category":"Building & Trades",
            "subcategory":"Landscaping Services",
            "type":"Services"
        }
    ],
    "sg:postcode":"G15 7SF",
    "sg:province":"Glasgow City",
    "sg:tags":[
        "gardening"
    ],
    "wof:name":"Domestic Gardening Services",
    "wof:placetype":"venue"
},
  "geometry": {"coordinates":[-4.3640170097,55.9132461548],"type":"Point"}
}