{
  "type": "Feature",
  "properties": {
    "addr:full":"Unit 4/6 Coventry Warwickshire CV4 9TB",
    "addr:housenumber":"unit 4 / 6",
    "addr:postcode":"cv4 9tb",
    "iso:country":"GB",
    "sg:address":"Unit 4/6",
    "sg:city":"Coventry",
    "sg:classifiers":[
        {
            "category":"Shopping",
            "subcategory":"Shoes",
            "type":"Retail Goods"
        }
    ],
    "sg:phone":"+44 24 7646 8599",
    "sg:postcode":"CV4 9TB",
    "sg:province":"Warwickshire",
    "sg:tags":[
        "shop"
    ],
    "wof:name":"Boss Shoes",
    "wof:placetype":"venue"
},
  "geometry": {"coordinates":[-1.5829139948,52.3963088989],"type":"Point"}
}