{
  "type": "Feature",
  "properties": {
    "addr:full":"Peter House, St Peters Square Manchester Greater Manchester M1 5AN",
    "addr:postcode":"m1 5an",
    "addr:street":"St Peters Square",
    "iso:country":"GB",
    "sg:address":"Peter House, St Peters Square",
    "sg:city":"Manchester",
    "sg:classifiers":[
        {
            "category":"Real Estate",
            "subcategory":"Developer",
            "type":"Services"
        }
    ],
    "sg:postcode":"M1 5AN",
    "sg:province":"Greater Manchester",
    "sg:tags":[
        "property"
    ],
    "wof:name":"Hitspark Limited",
    "wof:placetype":"venue"
},
  "geometry": {"coordinates":[-2.2440290451,53.4774589539],"type":"Point"}
}