{
  "type": "Feature",
  "properties": {
    "iso:country":"GB",
    "sg:address":"28 Hallcraig Street",
    "sg:city":"Airdrie",
    "sg:classifiers":[
        {
            "category":"Military Area",
            "subcategory":"Air Force Base",
            "type":"Public Place"
        }
    ],
    "sg:phone":"+44 1236 747111",
    "sg:postcode":"ML6 6AH",
    "sg:province":"North Lanarkshire",
    "sg:tags":[
        "taxi",
        "hire",
        "private"
    ],
    "wof:name":"Shevills T O A",
    "wof:placetype":"venue"
},
  "geometry": {"coordinates":[-3.979565,55.867214],"type":"Point"}
}