{
  "type": "Feature",
  "properties": {
    "addr:full":"36 Clapham High St Clapham Greater London SW4 7UR",
    "addr:housenumber":"36",
    "addr:postcode":"sw4 7ur",
    "addr:street":"Clapham High St",
    "iso:country":"GB",
    "sg:address":"36 Clapham High St",
    "sg:city":"Clapham",
    "sg:classifiers":[
        {
            "category":"Organizations",
            "subcategory":"Non-profit Organization",
            "type":"Services"
        }
    ],
    "sg:phone":"+44 20 7978 2542",
    "sg:postcode":"SW4 7UR",
    "sg:province":"Greater London",
    "sg:tags":[
        "organisation",
        "voluntary",
        "charity"
    ],
    "wof:name":"Save The Children Charity Shop",
    "wof:placetype":"venue"
},
  "geometry": {"coordinates":[-0.131942004,51.4641342163],"type":"Point"}
}