{
  "type": "Feature",
  "properties": {
    "addr:full":"8 Railway Terrace Abertillery Blaenau Gwent NP13 2AD",
    "addr:housenumber":"8",
    "addr:postcode":"np13 2ad",
    "addr:street":"Railway Terrace;Gwent",
    "iso:country":"GB",
    "sg:address":"8 Railway Terrace",
    "sg:city":"Abertillery",
    "sg:classifiers":[
        {
            "category":"Bars & Pubs",
            "type":"Food & Drink"
        }
    ],
    "sg:postcode":"NP13 2AD",
    "sg:province":"Blaenau Gwent",
    "sg:tags":[
        "pubs",
        "inn"
    ],
    "wof:name":"Colin Jones",
    "wof:placetype":"venue"
},
  "geometry": {"coordinates":[-3.1352128983,51.6996955872],"type":"Point"}
}