{
  "type": "Feature",
  "properties": {
    "addr:full":"Unit 4, Chillingham Trading Estate, Shields Rd Byker Newcastle Upon Tyne Tyne and Wear NE6 2XX",
    "addr:housenumber":"unit 4 chillingham;estate",
    "addr:postcode":"ne6 2xx",
    "addr:street":"Trading;Shields Rd",
    "iso:country":"GB",
    "sg:address":"Unit 4, Chillingham Trading Estate, Shields Rd Byker",
    "sg:city":"Newcastle Upon Tyne",
    "sg:classifiers":[
        {
            "category":"Autos & Motor Vehicles",
            "subcategory":"Auto Supplies",
            "type":"Retail Goods"
        }
    ],
    "sg:phone":"+44 191 265 7383",
    "sg:postcode":"NE6 2XX",
    "sg:province":"Tyne and Wear",
    "sg:tags":[
        "windscreen"
    ],
    "wof:name":"Silver Shield Automotive Windscreens",
    "wof:placetype":"venue"
},
  "geometry": {"coordinates":[-1.57213,54.981392],"type":"Point"}
}