{
  "type": "Feature",
  "properties": {
    "addr:full":"Blackheath Lane Stafford Staffordshire ST18 0YG",
    "addr:postcode":"st18 0yg",
    "addr:street":"Blackheath Lane",
    "iso:country":"GB",
    "sg:address":"Blackheath Lane",
    "sg:city":"Stafford",
    "sg:classifiers":[
        {
            "category":"Education",
            "subcategory":"School",
            "type":"Public Place"
        },
        {
            "category":"Government",
            "subcategory":"Office",
            "type":"Public Place"
        }
    ],
    "sg:phone":"+44 1785 356700",
    "sg:postcode":"ST18 0YG",
    "sg:province":"Staffordshire",
    "sg:tags":[
        "local",
        "authority"
    ],
    "wof:name":"Weston Road High School",
    "wof:placetype":"venue"
},
  "geometry": {"coordinates":[-2.074543,52.806145],"type":"Point"}
}