{
  "type": "Feature",
  "properties": {
    "addr:full":"127 Eastgate Louth Lincolnshire LN11 9QE",
    "addr:housenumber":"127",
    "addr:postcode":"ln11 9qe",
    "addr:street":"Eastgate Louth",
    "iso:country":"GB",
    "sg:address":"127 Eastgate",
    "sg:city":"Louth",
    "sg:classifiers":[
        {
            "category":"Home & Garden",
            "subcategory":"Furniture",
            "type":"Retail Goods"
        }
    ],
    "sg:phone":"+44 1507 609447",
    "sg:postcode":"LN11 9QE",
    "sg:province":"Lincolnshire",
    "wof:name":"Harveys",
    "wof:placetype":"venue"
},
  "geometry": {"coordinates":[-0.000489,53.367661],"type":"Point"}
}