{
  "type": "Feature",
  "properties": {
    "addr:full":"101 Murray Road London Greater London W5 4DB",
    "addr:housenumber":"101",
    "addr:postcode":"w5 4db",
    "addr:street":"Murray Road",
    "iso:country":"GB",
    "sg:address":"101 Murray Road",
    "sg:city":"London",
    "sg:classifiers":[
        {
            "category":"Professional",
            "subcategory":"Management & Consulting",
            "type":"Services"
        }
    ],
    "sg:postcode":"W5 4DB",
    "sg:province":"Greater London",
    "sg:tags":[
        "consultant",
        "business"
    ],
    "wof:name":"Jackpot (Uk) Ltd",
    "wof:placetype":"venue"
},
  "geometry": {"coordinates":[-0.3104780018,51.4947052002],"type":"Point"}
}