{
  "type": "Feature",
  "properties": {
    "addr:full":"Eastville Station, Eastville Boston Lincolnshire PE22 8LS",
    "addr:postcode":"pe22 8ls",
    "iso:country":"GB",
    "sg:address":"Eastville Station, Eastville",
    "sg:city":"Boston",
    "sg:classifiers":[
        {
            "category":"Shopping",
            "type":"Retail Goods"
        }
    ],
    "sg:phone":"+44 1205 270502",
    "sg:postcode":"PE22 8LS",
    "sg:province":"Lincolnshire",
    "sg:tags":[
        "part",
        "accessory"
    ],
    "wof:name":"James Carpenter",
    "wof:placetype":"venue"
},
  "geometry": {"coordinates":[0.09317,53.091011],"type":"Point"}
}