{
  "type": "Feature",
  "properties": {
    "addr:full":"Westcroft District Centre, Westcroft Milton Keynes Buckinghamshire MK4 4DD",
    "addr:postcode":"mk4 4dd",
    "iso:country":"GB",
    "sg:address":"Westcroft District Centre, Westcroft",
    "sg:city":"Milton Keynes",
    "sg:classifiers":[
        {
            "category":"Shopping",
            "subcategory":"Discount & Variety Stores",
            "type":"Retail Goods"
        }
    ],
    "sg:phone":"+44 1908 520079",
    "sg:postcode":"MK4 4DD",
    "sg:province":"Buckinghamshire",
    "sg:tags":[
        "centre"
    ],
    "wof:name":"In Store",
    "wof:placetype":"venue"
},
  "geometry": {"coordinates":[-0.7960180044,52.005065918],"type":"Point"}
}