{
  "type": "Feature",
  "properties": {
    "iso:country":"GB",
    "sg:address":"West Street",
    "sg:city":"Brighton",
    "sg:classifiers":[
        {
            "category":"Travel",
            "subcategory":"Hotels & Motels",
            "type":"Entertainment"
        }
    ],
    "sg:phone":"+44 1273 220033",
    "sg:postcode":"BN1 2RQ",
    "sg:province":"East Sussex",
    "wof:name":"Quality Hotels",
    "wof:placetype":"venue"
},
  "geometry": {"coordinates":[-0.1436389983,50.8233947754],"type":"Point"}
}