{
  "type": "Feature",
  "properties": {
    "iso:country":"GB",
    "sg:address":"Nantyffin Road, Llansamlet",
    "sg:city":"Swansea",
    "sg:classifiers":[
        {
            "category":"Food & Beverages",
            "subcategory":"Supermarket",
            "type":"Retail Goods"
        }
    ],
    "sg:phone":"+44 1792 497400",
    "sg:postcode":"SA7 9RD",
    "sg:province":"Neath Port Talbot",
    "wof:name":"Tesco Stores Ltd.",
    "wof:placetype":"venue"
},
  "geometry": {"coordinates":[-3.90268,51.658844],"type":"Point"}
}