{
  "type": "Feature",
  "properties": {
    "addr:full":"927 Finchley Road London Greater London NW11 7PE",
    "addr:housenumber":"927",
    "addr:postcode":"nw11 7pe",
    "addr:street":"Finchley Road",
    "iso:country":"GB",
    "sg:address":"927 Finchley Road",
    "sg:city":"London",
    "sg:classifiers":[
        {
            "category":"Wholesale",
            "subcategory":"Medical Equipment & Supplies",
            "type":"Manufacturing & Wholesale Goods"
        },
        {
            "category":"Building & Trades",
            "subcategory":"Equipment Rental",
            "type":"Services"
        }
    ],
    "sg:phone":"+44 20 8458 3785",
    "sg:postcode":"NW11 7PE",
    "sg:province":"Greater London",
    "sg:tags":[
        "supplier",
        "dental"
    ],
    "wof:name":"Premadent Ltd.",
    "wof:placetype":"venue"
},
  "geometry": {"coordinates":[-0.196053,51.573483],"type":"Point"}
}