{
  "type": "Feature",
  "properties": {
    "addr:full":"Whitehill Farm, 54 Preston Road, Whittle-le-woods Chorley Lancashire PR6 7HH",
    "addr:housenumber":"54",
    "addr:postcode":"pr6 7hh",
    "addr:street":"Preston Road",
    "iso:country":"GB",
    "sg:address":"Whitehill Farm, 54 Preston Road, Whittle-le-woods",
    "sg:city":"Chorley",
    "sg:classifiers":[
        {
            "category":"Retail",
            "subcategory":"Repair Shop",
            "type":"Services"
        },
        {
            "category":"Manufacturing",
            "subcategory":"Furniture",
            "type":"Manufacturing & Wholesale Goods"
        }
    ],
    "sg:phone":"+44 1257 267159",
    "sg:postcode":"PR6 7HH",
    "sg:province":"Lancashire",
    "sg:tags":[
        "mnfr",
        "upholsterer"
    ],
    "wof:name":"Astbury & Sons",
    "wof:placetype":"venue"
},
  "geometry": {"coordinates":[-2.6393740177,53.6991386414],"type":"Point"}
}