{
  "type": "Feature",
  "properties": {
    "iso:country":"GB",
    "sg:address":"13 Tithe Barn Close",
    "sg:city":"St Albans",
    "sg:classifiers":[
        {
            "category":"Education",
            "subcategory":"Music School",
            "type":"Public Place"
        }
    ],
    "sg:phone":"+44 1727 768738",
    "sg:postcode":"AL1 2QD",
    "sg:province":"Hertfordshire",
    "wof:name":"Stage Coach Theatre Arts (Watford)",
    "wof:placetype":"venue"
},
  "geometry": {"coordinates":[-0.3480750024,51.7371788025],"type":"Point"}
}