{
  "type": "Feature",
  "properties": {
    "addr:full":"74 Collett Avenue Swindon Wiltshire SN2 1NG",
    "addr:housenumber":"74",
    "addr:postcode":"sn2 1ng",
    "addr:street":"Collett Avenue",
    "iso:country":"GB",
    "sg:address":"74 Collett Avenue",
    "sg:city":"Swindon",
    "sg:classifiers":[
        {
            "category":"Retail",
            "subcategory":"Driving School",
            "type":"Services"
        }
    ],
    "sg:phone":"+44 1793 524842",
    "sg:postcode":"SN2 1NG",
    "sg:province":"Wiltshire",
    "wof:name":"George S School of Motoring",
    "wof:placetype":"venue"
},
  "geometry": {"coordinates":[-1.795404,51.574814],"type":"Point"}
}