{
  "type": "Feature",
  "properties": {
    "addr:full":"138 Gloucester Road, Walthamstow London Greater London E17 6AF",
    "addr:housenumber":"138",
    "addr:postcode":"e17 6af",
    "addr:street":"Gloucester Road",
    "iso:country":"GB",
    "sg:address":"138 Gloucester Road, Walthamstow",
    "sg:city":"London",
    "sg:classifiers":[
        {
            "category":"Building & Trades",
            "subcategory":"Construction",
            "type":"Services"
        }
    ],
    "sg:postcode":"E17 6AF",
    "sg:province":"Greater London",
    "sg:tags":[
        "tiling",
        "contractor"
    ],
    "wof:name":"R A Smith Tiling Contractors",
    "wof:placetype":"venue"
},
  "geometry": {"coordinates":[-0.0357570015,51.5960006714],"type":"Point"}
}