{
  "type": "Feature",
  "properties": {
    "iso:country":"GB",
    "sg:address":"Castle Market",
    "sg:city":"Sheffield",
    "sg:classifiers":[
        {
            "category":"Shopping",
            "subcategory":"Luggage & Leather Goods",
            "type":"Retail Goods"
        }
    ],
    "sg:phone":"+44 114 270 1966",
    "sg:postcode":"S1 2AP",
    "sg:province":"South Yorkshire",
    "sg:tags":[
        "shop",
        "leathergoods"
    ],
    "wof:name":"Leather Lords",
    "wof:placetype":"venue"
},
  "geometry": {"coordinates":[-1.464544,53.38311],"type":"Point"}
}