{
  "type": "Feature",
  "properties": {
    "addr:full":"27 Hooe Road Plymouth Devon PL9 9QS",
    "addr:housenumber":"27",
    "addr:postcode":"pl9 9qs",
    "addr:street":"Hooe Road",
    "iso:country":"GB",
    "sg:address":"27 Hooe Road",
    "sg:city":"Plymouth",
    "sg:classifiers":[
        {
            "category":"Bars & Pubs",
            "type":"Food & Drink"
        }
    ],
    "sg:postcode":"PL9 9QS",
    "sg:province":"Devon",
    "sg:tags":[
        "pubs",
        "inn"
    ],
    "wof:name":"The Victoria Inn",
    "wof:placetype":"venue"
},
  "geometry": {"coordinates":[-4.1110010147,50.3532867432],"type":"Point"}
}