{
  "type": "Feature",
  "properties": {
    "iso:country":"GB",
    "sg:address":"3 Missouri Avenue",
    "sg:city":"Salford",
    "sg:classifiers":[
        {
            "category":"Professional",
            "subcategory":"Advertising",
            "type":"Services"
        }
    ],
    "sg:phone":"+44 161 736 6100",
    "sg:postcode":"M5 2NP",
    "sg:province":"Greater Manchester",
    "sg:tags":[
        "outdoor"
    ],
    "wof:name":"Signways Ltd.",
    "wof:placetype":"venue"
},
  "geometry": {"coordinates":[-2.297188,53.480656],"type":"Point"}
}