{
  "type": "Feature",
  "properties": {
    "addr:full":"1 Crossland Crescent Peebles Scottish Borders EH45 8LF",
    "addr:housenumber":"1",
    "addr:postcode":"eh45 8lf",
    "addr:street":"Crossland Crescent",
    "iso:country":"GB",
    "sg:address":"1 Crossland Crescent",
    "sg:city":"Peebles",
    "sg:classifiers":[
        {
            "category":"Health Services",
            "subcategory":"Dentist",
            "type":"Services"
        }
    ],
    "sg:phone":"+44 1721 720574",
    "sg:postcode":"EH45 8LF",
    "sg:province":"Scottish Borders",
    "wof:name":"John Hammond Surgery",
    "wof:placetype":"venue"
},
  "geometry": {"coordinates":[-3.19318,55.652813],"type":"Point"}
}