{
  "type": "Feature",
  "properties": {
    "addr:full":"37 Derby Road Loughborough Leicestershire LE11 5AD",
    "addr:housenumber":"37",
    "addr:postcode":"le11 5ad",
    "addr:street":"Derby Road",
    "iso:country":"GB",
    "sg:address":"37 Derby Road",
    "sg:city":"Loughborough",
    "sg:classifiers":[
        {
            "category":"Autos & Motor Vehicles",
            "subcategory":"Auto Supplies",
            "type":"Retail Goods"
        }
    ],
    "sg:phone":"+44 1509 610500",
    "sg:postcode":"LE11 5AD",
    "sg:province":"Leicestershire",
    "sg:tags":[
        "tyre"
    ],
    "wof:name":"Tanvic Tyre Distributors",
    "wof:placetype":"venue"
},
  "geometry": {"coordinates":[-1.211842,52.774891],"type":"Point"}
}