{
  "type": "Feature",
  "properties": {
    "addr:full":"20 St Annes Road Eastbourne East Sussex BN21 2HQ",
    "addr:housenumber":"20",
    "addr:postcode":"bn21 2hq",
    "addr:street":"St Annes Road",
    "iso:country":"GB",
    "sg:address":"20 St Annes Road",
    "sg:city":"Eastbourne",
    "sg:classifiers":[
        {
            "category":"Social Services",
            "subcategory":"Retirement Home",
            "type":"Services"
        }
    ],
    "sg:postcode":"BN21 2HQ",
    "sg:province":"East Sussex",
    "sg:tags":[
        "rest"
    ],
    "wof:name":"Old Vicarage Rest Home",
    "wof:placetype":"venue"
},
  "geometry": {"coordinates":[0.274129,50.775433],"type":"Point"}
}