{
  "type": "Feature",
  "properties": {
    "iso:country":"GB",
    "sg:address":"79a Blenheim Rd",
    "sg:city":"Barnsley",
    "sg:classifiers":[
        {
            "category":"Personal",
            "subcategory":"Beauty Salon",
            "type":"Services"
        }
    ],
    "sg:phone":"+44 1226 205532",
    "sg:postcode":"S70 6AS",
    "sg:province":"South Yorkshire",
    "sg:tags":[
        "lady",
        "hairdresser"
    ],
    "wof:name":"Angelas",
    "wof:placetype":"venue"
},
  "geometry": {"coordinates":[-1.488154,53.547073],"type":"Point"}
}