{
  "type": "Feature",
  "properties": {
    "addr:full":"New Fen Farm, White City Road, Barroway Drove Downham Market Cambridgeshire PE38 0AP",
    "addr:postcode":"pe38 0ap",
    "addr:street":"White City Road Barroway Drove;Market",
    "iso:country":"GB",
    "sg:address":"New Fen Farm, White City Road, Barroway Drove",
    "sg:city":"Downham Market",
    "sg:classifiers":[
        {
            "category":"Banks & Credit Unions",
            "subcategory":"Investment Brokerage",
            "type":"Services"
        }
    ],
    "sg:postcode":"PE38 0AP",
    "sg:province":"Cambridgeshire",
    "sg:tags":[
        "contractor"
    ],
    "wof:name":"Russell & Co",
    "wof:placetype":"venue"
},
  "geometry": {"coordinates":[0.321906,52.609161],"type":"Point"}
}