{
  "type": "Feature",
  "properties": {
    "addr:full":"15a Tollington Way Holloway Greater London N7 6RG",
    "addr:housenumber":"15a",
    "addr:postcode":"n7 6rg",
    "addr:street":"Tollington Way",
    "iso:country":"GB",
    "sg:address":"15a Tollington Way",
    "sg:city":"Holloway",
    "sg:classifiers":[
        {
            "category":"Communications",
            "subcategory":"Film & Video Production",
            "type":"Services"
        }
    ],
    "sg:phone":"+44 20 7686 5882",
    "sg:postcode":"N7 6RG",
    "sg:province":"Greater London",
    "sg:tags":[
        "recording",
        "studio"
    ],
    "wof:name":"Lovestreet Recording Studio",
    "wof:placetype":"venue"
},
  "geometry": {"coordinates":[-0.123819001,51.5612945557],"type":"Point"}
}