{
  "type": "Feature",
  "properties": {
    "iso:country":"GB",
    "sg:address":"61 Stanhill Road, Oswaldtwistle",
    "sg:city":"Accrington",
    "sg:classifiers":[
        {
            "category":"Bars & Pubs",
            "type":"Food & Drink"
        },
        {
            "category":"Community Center",
            "subcategory":"Social",
            "type":"Public Place"
        }
    ],
    "sg:phone":"+44 1254 381694",
    "sg:postcode":"BB5 4PS",
    "sg:province":"Lancashire",
    "sg:tags":[
        "pubs",
        "house",
        "inn",
        "activity"
    ],
    "wof:name":"Stanhill Inn",
    "wof:placetype":"venue"
},
  "geometry": {"coordinates":[-2.4137339592,53.7456321716],"type":"Point"}
}