{
  "type": "Feature",
  "properties": {
    "addr:full":"Shore House, Compass Road Portsmouth Hampshire PO6 4PR",
    "addr:postcode":"hampshire po6 4pr",
    "addr:street":"Compass Road",
    "iso:country":"GB",
    "sg:address":"Shore House, Compass Road",
    "sg:city":"Portsmouth",
    "sg:classifiers":[
        {
            "category":"Manufacturing",
            "subcategory":"Tools & Machinery",
            "type":"Manufacturing & Wholesale Goods"
        }
    ],
    "sg:phone":"+44 23 9273 0344",
    "sg:postcode":"PO6 4PR",
    "sg:province":"Hampshire",
    "sg:tags":[
        "society",
        "friendly"
    ],
    "wof:name":"McLarens Toplis",
    "wof:placetype":"venue"
},
  "geometry": {"coordinates":[-1.0922889709,50.8460845947],"type":"Point"}
}