{
  "type": "Feature",
  "properties": {
    "addr:full":"21 Templedene Avenue Staines Berkshire TW18 1LH",
    "addr:housenumber":"21",
    "addr:postcode":"tw18 1lh",
    "addr:street":"Templedene Avenue",
    "iso:country":"GB",
    "sg:address":"21 Templedene Avenue",
    "sg:city":"Staines",
    "sg:classifiers":[
        {
            "category":"Home & Garden",
            "subcategory":"Household Appliances",
            "type":"Retail Goods"
        }
    ],
    "sg:phone":"+44 1784 454323",
    "sg:postcode":"TW18 1LH",
    "sg:province":"Berkshire",
    "sg:tags":[
        "electrical"
    ],
    "wof:name":"N Atkins",
    "wof:placetype":"venue"
},
  "geometry": {"coordinates":[-0.4925360084,51.4237480164],"type":"Point"}
}