{
  "type": "Feature",
  "properties": {
    "iso:country":"GB",
    "sg:address":"23 North Avenue, Westerhope",
    "sg:city":"Newcastle-upon-tyne",
    "sg:classifiers":[
        {
            "category":"Arts & Performance",
            "subcategory":"Music",
            "type":"Entertainment"
        }
    ],
    "sg:postcode":"NE5 5HY",
    "sg:province":"Tyne and Wear",
    "sg:tags":[
        "mobile",
        "disco"
    ],
    "wof:name":"Lamplight Entertainment",
    "wof:placetype":"venue"
},
  "geometry": {"coordinates":[-1.6889389753,54.9973220825],"type":"Point"}
}