{
  "type": "Feature",
  "properties": {
    "addr:full":"41 Chingford Mount Road London Greater London E4 8LU",
    "addr:housenumber":"41",
    "addr:postcode":"e4 8lu",
    "addr:street":"Chingford Mount Road",
    "iso:country":"GB",
    "sg:address":"41 Chingford Mount Road",
    "sg:city":"London",
    "sg:classifiers":[
        {
            "category":"Personal",
            "type":"Services"
        }
    ],
    "sg:phone":"+44 20 8527 1606",
    "sg:postcode":"E4 8LU",
    "sg:province":"Greater London",
    "sg:tags":[
        "tailor"
    ],
    "wof:name":"Ray Young Tailors",
    "wof:placetype":"venue"
},
  "geometry": {"coordinates":[-0.0180440005,51.6101951599],"type":"Point"}
}