{
  "type": "Feature",
  "properties": {
    "addr:full":"Townsend House Harrow Greater London HA2 0PG",
    "addr:postcode":"ha2 0pg",
    "iso:country":"GB",
    "sg:address":"Townsend House",
    "sg:city":"Harrow",
    "sg:classifiers":[
        {
            "category":"Banks & Credit Unions",
            "subcategory":"Financial Services",
            "type":"Services"
        },
        {
            "category":"Organizations",
            "subcategory":"Community Association",
            "type":"Services"
        }
    ],
    "sg:phone":"+44 20 8422 7101",
    "sg:postcode":"HA2 0PG",
    "sg:province":"Greater London",
    "sg:tags":[
        "consultant",
        "hire",
        "furniture"
    ],
    "wof:name":"Siemens Leasing Ltd.",
    "wof:placetype":"venue"
},
  "geometry": {"coordinates":[-0.35152,51.565899],"type":"Point"}
}