{
  "type": "Feature",
  "properties": {
    "iso:country":"GB",
    "sg:address":"Canal Farm, Thornfalcon",
    "sg:city":"Taunton",
    "sg:classifiers":[
        {
            "category":"Farming",
            "subcategory":"Livestock Farm",
            "type":"Manufacturing & Wholesale Goods"
        }
    ],
    "sg:phone":"+44 1823 442919",
    "sg:postcode":"TA3 5NS",
    "sg:province":"Devon",
    "sg:tags":[
        "others"
    ],
    "wof:name":"A W Godfrey",
    "wof:placetype":"venue"
},
  "geometry": {"coordinates":[-3.026739,51.008717],"type":"Point"}
}