{
  "type": "Feature",
  "properties": {
    "iso:country":"GB",
    "sg:address":"14 Station Road",
    "sg:city":"Colwyn Bay",
    "sg:classifiers":[
        {
            "category":"Shopping",
            "subcategory":"Clothing, Apparel, & Fashions",
            "type":"Retail Goods"
        },
        {
            "category":"Shopping",
            "subcategory":"Thrift Store",
            "type":"Retail Goods"
        }
    ],
    "sg:phone":"+44 1492 533768",
    "sg:postcode":"LL29 8BU",
    "sg:province":"Conwy",
    "sg:tags":[
        "shop",
        "charity"
    ],
    "wof:name":"OXFAM",
    "wof:placetype":"venue"
},
  "geometry": {"coordinates":[-3.697953,53.290092],"type":"Point"}
}