{
  "type": "Feature",
  "properties": {
    "iso:country":"GB",
    "sg:address":"Melton Station, Melton",
    "sg:city":"Woodbridge",
    "sg:classifiers":[
        {
            "category":"Shopping",
            "subcategory":"Discount & Variety Stores",
            "type":"Retail Goods"
        }
    ],
    "sg:phone":"+44 1728 453666",
    "sg:postcode":"IP12 1LS",
    "sg:province":"Suffolk",
    "sg:tags":[
        "cleaning",
        "supply"
    ],
    "wof:name":"Saxmundham Solid Fuel",
    "wof:placetype":"venue"
},
  "geometry": {"coordinates":[1.33714,52.104092],"type":"Point"}
}