{
  "type": "Feature",
  "properties": {
    "addr:full":"Unit 3 & 4 Pacific Wharf, Hertford Rd Barking Essex IG11 8BL",
    "addr:housenumber":"unit 3 & 4",
    "addr:postcode":"ig11 8bl",
    "addr:street":"Pacific Wharf Hertford Rd",
    "iso:country":"GB",
    "sg:address":"Unit 3 & 4 Pacific Wharf, Hertford Rd",
    "sg:city":"Barking",
    "sg:classifiers":[
        {
            "category":"Professional",
            "subcategory":"Printing & Photocopies",
            "type":"Services"
        }
    ],
    "sg:phone":"+44 20 8594 2896",
    "sg:postcode":"IG11 8BL",
    "sg:province":"Essex",
    "sg:tags":[
        "embroiderer"
    ],
    "wof:name":"East End Embroidery Ltd",
    "wof:placetype":"venue"
},
  "geometry": {"coordinates":[0.0681599975,51.5391387939],"type":"Point"}
}