{
  "type": "Feature",
  "properties": {
    "addr:full":"19 The Grove Studley Warwickshire B80 7QL",
    "addr:housenumber":"19",
    "addr:postcode":"b80 7ql",
    "addr:street":"The Grove",
    "iso:country":"GB",
    "sg:address":"19 The Grove",
    "sg:city":"Studley",
    "sg:classifiers":[
        {
            "category":"Professional",
            "subcategory":"Computer Services",
            "type":"Services"
        }
    ],
    "sg:postcode":"B80 7QL",
    "sg:province":"Warwickshire",
    "sg:tags":[
        "system",
        "software"
    ],
    "wof:name":"Simmtek Computer Services",
    "wof:placetype":"venue"
},
  "geometry": {"coordinates":[-1.899768,52.265209],"type":"Point"}
}