{
  "type": "Feature",
  "properties": {
    "addr:full":"127 The Street, Rustington Littlehampton West Sussex BN16 3DN",
    "addr:housenumber":"127",
    "addr:postcode":"bn16 3dn",
    "addr:street":"The Street",
    "iso:country":"GB",
    "sg:address":"127 The Street, Rustington",
    "sg:city":"Littlehampton",
    "sg:classifiers":[
        {
            "category":"Shopping",
            "subcategory":"Shoes",
            "type":"Retail Goods"
        }
    ],
    "sg:postcode":"BN16 3DN",
    "sg:province":"West Sussex",
    "sg:tags":[
        "shop"
    ],
    "wof:name":"James W Smith",
    "wof:placetype":"venue"
},
  "geometry": {"coordinates":[-0.50616,50.810226],"type":"Point"}
}