{
  "type": "Feature",
  "properties": {
    "addr:full":"Westminster Ho, 875 London Essex SS0 9SZ",
    "addr:housenumber":"875",
    "addr:postcode":"ss0 9sz",
    "addr:street":"London",
    "iso:country":"GB",
    "sg:address":"Westminster Ho, 875",
    "sg:city":"London",
    "sg:classifiers":[
        {
            "category":"Building & Trades",
            "subcategory":"Construction",
            "type":"Services"
        }
    ],
    "sg:phone":"+44 1708 343370",
    "sg:postcode":"SS0 9SZ",
    "sg:province":"Essex",
    "sg:tags":[
        "roofing"
    ],
    "wof:name":"Safetest U K (Southern) Ltd",
    "wof:placetype":"venue"
},
  "geometry": {"coordinates":[0.6852700114,51.5454483032],"type":"Point"}
}