{
  "type": "Feature",
  "properties": {
    "addr:full":"100 Pencisely Rd Cardiff Cardiff CF5 1DQ",
    "addr:housenumber":"100",
    "addr:postcode":"cf5 1dq",
    "addr:street":"Pencisely Rd",
    "iso:country":"GB",
    "sg:address":"100 Pencisely Rd",
    "sg:city":"Cardiff",
    "sg:classifiers":[
        {
            "category":"Social Services",
            "subcategory":"Retirement Home",
            "type":"Services"
        }
    ],
    "sg:phone":"+44 29 2056 1891",
    "sg:postcode":"CF5 1DQ",
    "sg:province":"Cardiff",
    "sg:tags":[
        "residential",
        "care"
    ],
    "wof:name":"Brookvale Residential Home",
    "wof:placetype":"venue"
},
  "geometry": {"coordinates":[-3.2177450657,51.4893836975],"type":"Point"}
}