{
  "type": "Feature",
  "properties": {
    "addr:full":"Units 5-7, Cotswold Business Pk, Range Rd Witney Oxfordshire OX29 0YB",
    "addr:housenumber":"units 5-7",
    "addr:postcode":"ox29 0yb",
    "addr:street":"Business Pk Range Rd",
    "iso:country":"GB",
    "sg:address":"Units 5-7, Cotswold Business Pk, Range Rd",
    "sg:city":"Witney",
    "sg:classifiers":[
        {
            "category":"Wholesale",
            "subcategory":"Office Equipment",
            "type":"Manufacturing & Wholesale Goods"
        }
    ],
    "sg:phone":"+44 1993 776812",
    "sg:postcode":"OX29 0YB",
    "sg:province":"Oxfordshire",
    "sg:tags":[
        "bookbinding"
    ],
    "wof:name":"Giddins,Steve,Engineering (& Bookbinding",
    "wof:placetype":"venue"
},
  "geometry": {"coordinates":[-1.5228600502,51.7903213501],"type":"Point"}
}