{
  "type": "Feature",
  "properties": {
    "iso:country":"GB",
    "sg:address":"Pilgrims Manor, Chapmans Lane",
    "sg:city":"Orpington",
    "sg:classifiers":[
        {
            "category":"Professional",
            "subcategory":"Employment Agencies",
            "type":"Services"
        }
    ],
    "sg:phone":"+44 1689 831555",
    "sg:postcode":"BR5 3JA",
    "sg:province":"Kent",
    "sg:tags":[
        "consultant"
    ],
    "wof:name":"I T Force Recruitment",
    "wof:placetype":"venue"
},
  "geometry": {"coordinates":[0.1252,51.401852],"type":"Point"}
}