{
  "type": "Feature",
  "properties": {
    "addr:full":"16 Clarion Court, Enterprise Park, Morriston Swansea Swansea SA6 8RF",
    "addr:housenumber":"16",
    "addr:postcode":"sa6 8rf",
    "addr:street":"Clarion Court Enterprise Park",
    "iso:country":"GB",
    "sg:address":"16 Clarion Court, Enterprise Park, Morriston",
    "sg:city":"Swansea",
    "sg:classifiers":[
        {
            "category":"Government",
            "subcategory":"Post Office",
            "type":"Public Place"
        }
    ],
    "sg:phone":"+44 1792 797106",
    "sg:postcode":"SA6 8RF",
    "sg:province":"Swansea",
    "sg:tags":[
        "messenger",
        "courier"
    ],
    "wof:name":"City Link Swansea",
    "wof:placetype":"venue"
},
  "geometry": {"coordinates":[-3.9049088955,51.6636009216],"type":"Point"}
}