{
  "type": "Feature",
  "properties": {
    "addr:full":"24a Barnsbury Park London Greater London N1 1HQ",
    "addr:housenumber":"24a",
    "addr:postcode":"n1 1hq",
    "addr:street":"Barnsbury Park",
    "iso:country":"GB",
    "sg:address":"24a Barnsbury Park",
    "sg:city":"London",
    "sg:classifiers":[
        {
            "category":"Professional",
            "subcategory":"Employment Agencies",
            "type":"Services"
        }
    ],
    "sg:postcode":"N1 1HQ",
    "sg:province":"Greater London",
    "sg:tags":[
        "consultant"
    ],
    "wof:name":"Downey Associates Ltd",
    "wof:placetype":"venue"
},
  "geometry": {"coordinates":[-0.107731,51.54306],"type":"Point"}
}