{
  "type": "Feature",
  "properties": {
    "iso:country":"GB",
    "sg:address":"106 Foxley Lane",
    "sg:city":"Purley",
    "sg:classifiers":[
        {
            "category":"Health Services",
            "subcategory":"Nursing And Care Facility",
            "type":"Services"
        }
    ],
    "sg:phone":"+44 20 8660 6453",
    "sg:postcode":"CR8 3NB",
    "sg:province":"Surrey",
    "sg:tags":[
        "home"
    ],
    "wof:name":"Westside Nursing Homes",
    "wof:placetype":"venue"
},
  "geometry": {"coordinates":[-0.132987,51.343239],"type":"Point"}
}