{
  "type": "Feature",
  "properties": {
    "iso:country":"GB",
    "sg:address":"Health Centre, 9 Carrington Way",
    "sg:city":"Wincanton",
    "sg:classifiers":[
        {
            "category":"Health Services",
            "subcategory":"Doctor",
            "type":"Services"
        }
    ],
    "sg:phone":"+44 1963 32554",
    "sg:postcode":"BA9 9JS",
    "sg:province":"Somerset",
    "sg:tags":[
        "practitioners"
    ],
    "wof:name":"East Somerset Community Services Unit",
    "wof:placetype":"venue"
},
  "geometry": {"coordinates":[-2.413179,51.0578],"type":"Point"}
}