{
  "type": "Feature",
  "properties": {
    "addr:full":"174 Hurlford Road Kilmarnock East Ayrshire KA1 3NQ",
    "addr:housenumber":"174",
    "addr:postcode":"ka1 3nq",
    "addr:street":"Hurlford Road",
    "iso:country":"GB",
    "sg:address":"174 Hurlford Road",
    "sg:city":"Kilmarnock",
    "sg:classifiers":[
        {
            "category":"Building & Trades",
            "subcategory":"Construction",
            "type":"Services"
        }
    ],
    "sg:postcode":"KA1 3NQ",
    "sg:province":"East Ayrshire",
    "sg:tags":[
        "roofing"
    ],
    "wof:name":"J P Roofing",
    "wof:placetype":"venue"
},
  "geometry": {"coordinates":[-4.480908,55.596775],"type":"Point"}
}