{
  "type": "Feature",
  "properties": {
    "addr:full":"The Dairy House, 869 Plymouth Road Slough Berkshire SL1 2LP",
    "addr:housenumber":"869",
    "addr:postcode":"sl1 2lp",
    "addr:street":"Plymouth Road",
    "iso:country":"GB",
    "sg:address":"The Dairy House, 869 Plymouth Road",
    "sg:city":"Slough",
    "sg:classifiers":[
        {
            "category":"Professional",
            "type":"Services"
        }
    ],
    "sg:postcode":"SL1 2LP",
    "sg:province":"Berkshire",
    "sg:tags":[
        "control",
        "system"
    ],
    "wof:name":"Jotax Ltd.",
    "wof:placetype":"venue"
},
  "geometry": {"coordinates":[-0.6415740252,51.525970459],"type":"Point"}
}