{
  "type": "Feature",
  "properties": {
    "addr:full":"Carpenters Road, Brading Sandown Isle of Wight PO36 0QA",
    "addr:postcode":"po36 0qa",
    "addr:street":"Carpenters Road",
    "iso:country":"GB",
    "sg:address":"Carpenters Road, Brading",
    "sg:city":"Sandown",
    "sg:classifiers":[
        {
            "category":"Sports & Exercise",
            "subcategory":"Stables",
            "type":"Entertainment"
        }
    ],
    "sg:phone":"+44 1983 811404",
    "sg:postcode":"PO36 0QA",
    "sg:province":"Isle of Wight",
    "sg:tags":[
        "education",
        "equestrian"
    ],
    "wof:name":"Delysia Stud Stables",
    "wof:placetype":"venue"
},
  "geometry": {"coordinates":[-1.1432939768,50.6819496155],"type":"Point"}
}