{
  "type": "Feature",
  "properties": {
    "addr:full":"Hollins Mill Todmorden Lancashire OL14 6SA",
    "addr:postcode":"ol14 6sa",
    "addr:street":"Hollins",
    "iso:country":"GB",
    "sg:address":"Hollins Mill",
    "sg:city":"Todmorden",
    "sg:classifiers":[
        {
            "category":"Home & Garden",
            "subcategory":"Home Furnishings",
            "type":"Retail Goods"
        }
    ],
    "sg:postcode":"OL14 6SA",
    "sg:province":"Lancashire",
    "sg:tags":[
        "blind",
        "curtain",
        "fitting"
    ],
    "wof:name":"J & F Manufacturing",
    "wof:placetype":"venue"
},
  "geometry": {"coordinates":[-2.0997810364,53.6958580017],"type":"Point"}
}