{
  "type": "Feature",
  "properties": {
    "iso:country":"GB",
    "sg:address":"1-26 Stillwell House, Barncroft Close, Hillingdon",
    "sg:city":"Uxbridge",
    "sg:classifiers":[
        {
            "category":"Social Services",
            "subcategory":"Adult Care",
            "type":"Services"
        },
        {
            "category":"Government",
            "subcategory":"Office",
            "type":"Public Place"
        }
    ],
    "sg:phone":"+44 1895 233076",
    "sg:postcode":"UB8 3JN",
    "sg:province":"Buckinghamshire",
    "sg:tags":[
        "housing",
        "local",
        "sheltered"
    ],
    "wof:name":"Stillwell House",
    "wof:placetype":"venue"
},
  "geometry": {"coordinates":[-0.44917,51.5256],"type":"Point"}
}