{
  "type": "Feature",
  "properties": {
    "iso:country":"GB",
    "sg:address":"133 Cheadle Old Road",
    "sg:city":"Stockport",
    "sg:classifiers":[
        {
            "category":"Social Services",
            "subcategory":"Retirement Home",
            "type":"Services"
        }
    ],
    "sg:phone":"+44 161 477 1572",
    "sg:postcode":"SK3 9RH",
    "sg:province":"Cheshire",
    "sg:tags":[
        "rest"
    ],
    "wof:name":"Rosemount Rest Home",
    "wof:placetype":"venue"
},
  "geometry": {"coordinates":[-2.180385,53.397743],"type":"Point"}
}