{
  "type": "Feature",
  "properties": {
    "addr:full":"79 West Ham Lane, Stratford Stratford Greater London E15 4PH",
    "addr:housenumber":"79",
    "addr:postcode":"e15 4ph",
    "addr:street":"West Ham Lane",
    "iso:country":"GB",
    "sg:address":"79 West Ham Lane, Stratford",
    "sg:city":"Stratford",
    "sg:classifiers":[
        {
            "category":"Professional",
            "subcategory":"Employment Agencies",
            "type":"Services"
        }
    ],
    "sg:phone":"+44 20 8534 2158",
    "sg:postcode":"E15 4PH",
    "sg:province":"Greater London",
    "sg:tags":[
        "consultant"
    ],
    "wof:name":"Tanlen Personnel International",
    "wof:placetype":"venue"
},
  "geometry": {"coordinates":[0.0056540002,51.5376205444],"type":"Point"}
}