{
  "type": "Feature",
  "properties": {
    "addr:full":"233 Camberwell New Road London Greater London SE5 0TH",
    "addr:housenumber":"233",
    "addr:postcode":"se5 0th",
    "addr:street":"Camberwell New Road",
    "iso:country":"GB",
    "sg:address":"233 Camberwell New Road",
    "sg:city":"London",
    "sg:classifiers":[
        {
            "category":"Professional",
            "subcategory":"Art Services",
            "type":"Services"
        }
    ],
    "sg:phone":"+44 20 7701 6868",
    "sg:postcode":"SE5 0TH",
    "sg:province":"Greater London",
    "sg:tags":[
        "graphic",
        "designer"
    ],
    "wof:name":"Quest Design Ltd.",
    "wof:placetype":"venue"
},
  "geometry": {"coordinates":[-0.100912,51.477413],"type":"Point"}
}