{
  "type": "Feature",
  "properties": {
    "iso:country":"GB",
    "sg:address":"18 Gladstone Terrace, New Penshaw",
    "sg:city":"Houghton-le-spring",
    "sg:classifiers":[
        {
            "category":"Professional",
            "subcategory":"Accounting & Tax Preparation",
            "type":"Services"
        }
    ],
    "sg:postcode":"DH4 7PJ",
    "sg:province":"Durham",
    "sg:tags":[
        "accountant"
    ],
    "wof:name":"Brian Carrick Accounting",
    "wof:placetype":"venue"
},
  "geometry": {"coordinates":[-1.506906,54.876839],"type":"Point"}
}