{
  "type": "Feature",
  "properties": {
    "addr:full":"Unit B, Artic House, Mitchell Avenue Ventnor Isle of Wight PO38 1DL",
    "addr:postcode":"po38 1dl",
    "addr:street":"Mitchell Avenue Ventnor",
    "iso:country":"GB",
    "sg:address":"Unit B, Artic House, Mitchell Avenue",
    "sg:city":"Ventnor",
    "sg:classifiers":[
        {
            "category":"Retail",
            "subcategory":"Auto Repair",
            "type":"Services"
        }
    ],
    "sg:postcode":"PO38 1DL",
    "sg:province":"Isle of Wight",
    "sg:tags":[
        "garage",
        "mechanic"
    ],
    "wof:name":"Autocheck",
    "wof:placetype":"venue"
},
  "geometry": {"coordinates":[-1.2047840357,50.5977096558],"type":"Point"}
}