{
  "type": "Feature",
  "properties": {
    "iso:country":"GB",
    "sg:address":"Church Lane, Arnesby",
    "sg:city":"Leicester",
    "sg:classifiers":[
        {
            "category":"Manufacturing",
            "subcategory":"Paper Products",
            "type":"Manufacturing & Wholesale Goods"
        }
    ],
    "sg:postcode":"LE8 5UU",
    "sg:province":"Leicestershire",
    "sg:tags":[
        "cardboard"
    ],
    "wof:name":"M D White",
    "wof:placetype":"venue"
},
  "geometry": {"coordinates":[-1.089874,52.526985],"type":"Point"}
}