{
  "type": "Feature",
  "properties": {
    "iso:country":"GB",
    "sg:address":"33 Attercliffe Common, Attercliffe",
    "sg:city":"Sheffield",
    "sg:classifiers":[
        {
            "category":"Taxi",
            "type":"Transportation"
        },
        {
            "category":"Military Area",
            "subcategory":"Air Force Base",
            "type":"Public Place"
        }
    ],
    "sg:phone":"+44 114 243 0430",
    "sg:postcode":"S9 2AE",
    "sg:province":"South Yorkshire",
    "sg:tags":[
        "hire",
        "private",
        "vehicle"
    ],
    "wof:name":"Express Taxis",
    "wof:placetype":"venue"
},
  "geometry": {"coordinates":[-1.427374,53.398094],"type":"Point"}
}