{
  "type": "Feature",
  "properties": {
    "addr:full":"36 Woodbridge Road Birmingham West Midlands B13 8EJ",
    "addr:housenumber":"36",
    "addr:postcode":"b13 8ej",
    "addr:street":"Woodbridge Road",
    "iso:country":"GB",
    "sg:address":"36 Woodbridge Road",
    "sg:city":"Birmingham",
    "sg:classifiers":[
        {
            "category":"Retail",
            "subcategory":"Auto Rental",
            "type":"Services"
        }
    ],
    "sg:postcode":"B13 8EJ",
    "sg:province":"West Midlands",
    "sg:tags":[
        "car",
        "hire",
        "truck"
    ],
    "wof:name":"1M Vehicle Leasing",
    "wof:placetype":"venue"
},
  "geometry": {"coordinates":[-1.886014,52.44812],"type":"Point"}
}