{
  "type": "Feature",
  "properties": {
    "addr:full":"Burnham Medical Centre Burnham-on-sea Somerset TA8 1EY",
    "addr:postcode":"ta8 1ey",
    "addr:street":"Somerset",
    "iso:country":"GB",
    "sg:address":"Burnham Medical Centre",
    "sg:city":"Burnham-on-sea",
    "sg:classifiers":[
        {
            "category":"Health Services",
            "subcategory":"Health Practitioner",
            "type":"Services"
        }
    ],
    "sg:phone":"+44 1278 793223",
    "sg:postcode":"TA8 1EY",
    "sg:province":"Somerset",
    "sg:tags":[
        "osteopath"
    ],
    "wof:name":"Peter J Everett",
    "wof:placetype":"venue"
},
  "geometry": {"coordinates":[-2.993099,51.238449],"type":"Point"}
}