{
  "type": "Feature",
  "properties": {
    "addr:full":"84 London Rd, Stanway Colchester Essex CO3 5HD",
    "addr:housenumber":"84",
    "addr:postcode":"co3 5hd",
    "addr:street":"London Rd",
    "iso:country":"GB",
    "sg:address":"84 London Rd, Stanway",
    "sg:city":"Colchester",
    "sg:classifiers":[
        {
            "category":"Autos & Motor Vehicles",
            "subcategory":"Automobile Sales",
            "type":"Retail Goods"
        }
    ],
    "sg:phone":"+44 1206 500406",
    "sg:postcode":"CO3 5HD",
    "sg:province":"Essex",
    "sg:tags":[
        "car"
    ],
    "wof:name":"K J K Company Cars",
    "wof:placetype":"venue"
},
  "geometry": {"coordinates":[0.84286,51.883598],"type":"Point"}
}