{
  "type": "Feature",
  "properties": {
    "iso:country":"GB",
    "sg:address":"72 Chadwick Road",
    "sg:city":"Eastleigh",
    "sg:classifiers":[
        {
            "category":"Building & Trades",
            "subcategory":"Construction",
            "type":"Services"
        }
    ],
    "sg:phone":"+44 23 8061 7821",
    "sg:postcode":"SO50 9GH",
    "sg:province":"Hampshire",
    "sg:tags":[
        "decorator",
        "painter"
    ],
    "wof:name":"K Clark",
    "wof:placetype":"venue"
},
  "geometry": {"coordinates":[-1.3678150177,50.9675064087],"type":"Point"}
}