{
  "type": "Feature",
  "properties": {
    "addr:full":"Felhampton Farm, Upton Bishop Ross-on-wye Gloucestershire HR9 7UB",
    "addr:housenumber":"upton",
    "addr:postcode":"hr9 7ub",
    "addr:street":"Bishop Ross-On-Wye Gloucestershire",
    "iso:country":"GB",
    "sg:address":"Felhampton Farm, Upton Bishop",
    "sg:city":"Ross-on-wye",
    "sg:classifiers":[
        {
            "category":"Farming",
            "subcategory":"Livestock Farm",
            "type":"Manufacturing & Wholesale Goods"
        }
    ],
    "sg:phone":"+44 1989 780236",
    "sg:postcode":"HR9 7UB",
    "sg:province":"Gloucestershire",
    "sg:tags":[
        "others"
    ],
    "wof:name":"A G & J K Watkins",
    "wof:placetype":"venue"
},
  "geometry": {"coordinates":[-2.581733,51.916481],"type":"Point"}
}