{
  "type": "Feature",
  "properties": {
    "addr:full":"107 Sheen Road Richmond Greater London TW9 1YJ",
    "addr:housenumber":"107",
    "addr:postcode":"tw9 1yj",
    "addr:street":"Sheen Road",
    "iso:country":"GB",
    "sg:address":"107 Sheen Road",
    "sg:city":"Richmond",
    "sg:classifiers":[
        {
            "category":"Health Services",
            "subcategory":"Dentist",
            "type":"Services"
        }
    ],
    "sg:phone":"+44 20 8940 1416",
    "sg:postcode":"TW9 1YJ",
    "sg:province":"Greater London",
    "wof:name":"Perminder S Chaggar",
    "wof:placetype":"venue"
},
  "geometry": {"coordinates":[-0.2946969867,51.462059021],"type":"Point"}
}