{
  "type": "Feature",
  "properties": {
    "iso:country":"GB",
    "sg:address":"8 Flitcroft St",
    "sg:city":"Holborn",
    "sg:classifiers":[
        {
            "category":"Retail",
            "subcategory":"Photofinishing",
            "type":"Services"
        }
    ],
    "sg:phone":"+44 20 7836 7420",
    "sg:postcode":"WC2H 8DJ",
    "sg:province":"Greater London",
    "sg:tags":[
        "photographic",
        "processor"
    ],
    "wof:name":"Quicksilver Photographic & Digital Imaging",
    "wof:placetype":"venue"
},
  "geometry": {"coordinates":[-0.128929,51.515072],"type":"Point"}
}