{
  "type": "Feature",
  "properties": {
    "addr:full":"St Albans Road Industrial Estate Stafford Staffordshire ST16 3DR",
    "addr:postcode":"st16 3dr",
    "addr:street":"St Albans Road Industrial Estate",
    "iso:country":"GB",
    "sg:address":"St Albans Road Industrial Estate",
    "sg:city":"Stafford",
    "sg:classifiers":[
        {
            "category":"Professional",
            "type":"Services"
        }
    ],
    "sg:phone":"+44 1785 252247",
    "sg:postcode":"ST16 3DR",
    "sg:province":"Staffordshire",
    "sg:tags":[
        "caterer"
    ],
    "wof:name":"Jenkinsons Caterers (Stafford) Ltd.",
    "wof:placetype":"venue"
},
  "geometry": {"coordinates":[-2.1136989594,52.8262405396],"type":"Point"}
}