{
  "type": "Feature",
  "properties": {
    "iso:country":"GB",
    "sg:address":"8 Augusta Rd",
    "sg:city":"Ramsgate",
    "sg:classifiers":[
        {
            "category":"Health Services",
            "subcategory":"Clinic",
            "type":"Services"
        }
    ],
    "sg:phone":"+44 1843 590630",
    "sg:postcode":"CT11 8JP",
    "sg:province":"Kent",
    "sg:tags":[
        "aromatherapy"
    ],
    "wof:name":"Michael Benson",
    "wof:placetype":"venue"
},
  "geometry": {"coordinates":[1.4247119427,51.3356018066],"type":"Point"}
}