{
  "type": "Feature",
  "properties": {
    "iso:country":"GB",
    "sg:address":"Francis House",
    "sg:city":"Wrexham",
    "sg:classifiers":[
        {
            "category":"Professional",
            "subcategory":"Employment Agencies",
            "type":"Services"
        }
    ],
    "sg:postcode":"SS15 6PX",
    "sg:province":"Essex",
    "sg:tags":[
        "consultant"
    ],
    "wof:name":"Proofwork Limited",
    "wof:placetype":"venue"
},
  "geometry": {"coordinates":[0.4103490114,51.5749893188],"type":"Point"}
}