{
  "type": "Feature",
  "properties": {
    "addr:full":"1 Leighton Road, Ealing London Greater London W13 9EL",
    "addr:housenumber":"1",
    "addr:postcode":"w13 9el",
    "addr:street":"Leighton Road",
    "iso:country":"GB",
    "sg:address":"1 Leighton Road, Ealing",
    "sg:city":"London",
    "sg:classifiers":[
        {
            "category":"Bus Charters",
            "type":"Transportation"
        }
    ],
    "sg:phone":"+44 20 8579 9922",
    "sg:postcode":"W13 9EL",
    "sg:province":"Greater London",
    "sg:tags":[
        "hire",
        "coach"
    ],
    "wof:name":"Tony Hill",
    "wof:placetype":"venue"
},
  "geometry": {"coordinates":[-0.320198,51.505959],"type":"Point"}
}