{
  "type": "Feature",
  "properties": {
    "addr:full":"The Courts Carlisle Cumbria CA3 8NA",
    "addr:postcode":"ca3 8na",
    "iso:country":"GB",
    "sg:address":"The Courts",
    "sg:city":"Carlisle",
    "sg:classifiers":[
        {
            "category":"Government",
            "subcategory":"Office",
            "type":"Public Place"
        }
    ],
    "sg:phone":"+44 1228 606060",
    "sg:postcode":"CA3 8NA",
    "sg:province":"Cumbria",
    "sg:tags":[
        "local"
    ],
    "wof:name":"Cumbria County Council",
    "wof:placetype":"venue"
},
  "geometry": {"coordinates":[-2.9361689091,54.8965148926],"type":"Point"}
}