{
  "type": "Feature",
  "properties": {
    "addr:full":"1 The Gallery, Castle Market Sheffield South Yorkshire S1 1FZ",
    "addr:housenumber":"1",
    "addr:postcode":"s1 1fz",
    "addr:street":"The Gallery",
    "iso:country":"GB",
    "sg:address":"1 The Gallery, Castle Market",
    "sg:city":"Sheffield",
    "sg:classifiers":[
        {
            "category":"Professional",
            "subcategory":"Employment Agencies",
            "type":"Services"
        }
    ],
    "sg:phone":"+44 114 272 3301",
    "sg:postcode":"S1 1FZ",
    "sg:province":"South Yorkshire",
    "sg:tags":[
        "career",
        "guidance"
    ],
    "wof:name":"Royal Air Force Careers Information",
    "wof:placetype":"venue"
},
  "geometry": {"coordinates":[-1.4645440578,53.3831100464],"type":"Point"}
}