{
  "type": "Feature",
  "properties": {
    "addr:full":"55 Mount Pleasant, Biggin Hill Westerham Kent TN16 3TP",
    "addr:housenumber":"55",
    "addr:postcode":"tn16 3tp",
    "addr:street":"Mount Pleasant",
    "iso:country":"GB",
    "sg:address":"55 Mount Pleasant, Biggin Hill",
    "sg:city":"Westerham",
    "sg:classifiers":[
        {
            "category":"Building & Trades",
            "subcategory":"Cleaning & Sanitation",
            "type":"Services"
        }
    ],
    "sg:phone":"+44 1959 574033",
    "sg:postcode":"TN16 3TP",
    "sg:province":"Kent",
    "sg:tags":[
        "commercial"
    ],
    "wof:name":"Prompt Cleaning Services",
    "wof:placetype":"venue"
},
  "geometry": {"coordinates":[0.0301329996,51.3110771179],"type":"Point"}
}