{
  "type": "Feature",
  "properties": {
    "addr:full":"Wyck Beck Road, Cribbs Causeway Bristol City of Bristol BS10 7JD",
    "addr:postcode":"bs10 7jd",
    "addr:street":"Beck Road Cribbs Causeway",
    "iso:country":"GB",
    "sg:address":"Wyck Beck Road, Cribbs Causeway",
    "sg:city":"Bristol",
    "sg:classifiers":[
        {
            "category":"Autos & Motor Vehicles",
            "subcategory":"Fuel & Gas Station",
            "type":"Retail Goods"
        }
    ],
    "sg:postcode":"BS10 7JD",
    "sg:province":"City of Bristol",
    "sg:tags":[
        "petrol",
        "filling"
    ],
    "wof:name":"Severnway Filling Station",
    "wof:placetype":"venue"
},
  "geometry": {"coordinates":[-2.6204090118,51.5147247314],"type":"Point"}
}