{
  "type": "Feature",
  "properties": {
    "addr:full":"2 St Mary's Terrace Rossendale Lancashire BB4 8SQ",
    "addr:housenumber":"2",
    "addr:postcode":"bb4 8sq",
    "addr:street":"St Mary'S Terrace",
    "iso:country":"GB",
    "sg:address":"2 St Mary's Terrace",
    "sg:city":"Rossendale",
    "sg:classifiers":[
        {
            "category":"Health Services",
            "subcategory":"Optometrist",
            "type":"Services"
        }
    ],
    "sg:postcode":"BB4 8SQ",
    "sg:province":"Lancashire",
    "sg:tags":[
        "optician"
    ],
    "wof:name":"S W Allen Ltd.",
    "wof:placetype":"venue"
},
  "geometry": {"coordinates":[-2.2834239006,53.7033042908],"type":"Point"}
}