{
  "type": "Feature",
  "properties": {
    "addr:full":"8 Royal Esplanade, Westbrook Margate Kent CT9 5DL",
    "addr:housenumber":"8",
    "addr:postcode":"ct9 5dl",
    "addr:street":"Royal Esplanade",
    "iso:country":"GB",
    "sg:address":"8 Royal Esplanade, Westbrook",
    "sg:city":"Margate",
    "sg:classifiers":[
        {
            "category":"Travel",
            "subcategory":"Hotels & Motels",
            "type":"Entertainment"
        },
        {
            "category":"Education",
            "subcategory":"School",
            "type":"Public Place"
        }
    ],
    "sg:phone":"+44 1843 220415",
    "sg:postcode":"CT9 5DL",
    "sg:province":"Kent",
    "sg:tags":[
        "house",
        "guest",
        "private",
        "tuition"
    ],
    "wof:name":"Mariden Guest House",
    "wof:placetype":"venue"
},
  "geometry": {"coordinates":[1.3638180494,51.3850898743],"type":"Point"}
}