{
  "type": "Feature",
  "properties": {
    "addr:full":"Brickhouse La Bromsgrove Worcestershire B60 4LX",
    "addr:postcode":"b60 4lx",
    "iso:country":"GB",
    "sg:address":"Brickhouse La",
    "sg:city":"Bromsgrove",
    "sg:classifiers":[
        {
            "category":"Shopping",
            "type":"Retail Goods"
        }
    ],
    "sg:phone":"+44 1527 831663",
    "sg:postcode":"B60 4LX",
    "sg:province":"Worcestershire",
    "sg:tags":[
        "merchant"
    ],
    "wof:name":"Midland Shires Farmers Ltd",
    "wof:placetype":"venue"
},
  "geometry": {"coordinates":[-2.0840098858,52.3088951111],"type":"Point"}
}