{
  "type": "Feature",
  "properties": {
    "iso:country":"GB",
    "sg:address":"6th Floor Crown House, 51 Alydwich",
    "sg:city":"London",
    "sg:classifiers":[
        {
            "category":"Communications",
            "type":"Services"
        }
    ],
    "sg:phone":"+44 20 7395 4500",
    "sg:postcode":"WC2B 4AX",
    "sg:province":"Greater London",
    "sg:tags":[
        "telecommunication"
    ],
    "wof:name":"Band-X Ltd.",
    "wof:placetype":"venue"
},
  "geometry": {"coordinates":[-0.1181299984,51.5130805969],"type":"Point"}
}