{
  "type": "Feature",
  "properties": {
    "iso:country":"GB",
    "sg:address":"1 Carley Drive",
    "sg:city":"Sheffield",
    "sg:classifiers":[
        {
            "category":"Wholesale",
            "subcategory":"Machinery & Supplies",
            "type":"Manufacturing & Wholesale Goods"
        }
    ],
    "sg:phone":"+44 114 247 2522",
    "sg:postcode":"S19 5NQ",
    "sg:province":"Derbyshire",
    "sg:tags":[
        "equipment",
        "pneumatic",
        "system"
    ],
    "wof:name":"A B Pneumatic Products Ltd",
    "wof:placetype":"venue"
},
  "geometry": {"coordinates":[-1.464544,53.38311],"type":"Point"}
}