{
  "type": "Feature",
  "properties": {
    "iso:country":"GB",
    "sg:address":"175 Scargreen Av",
    "sg:city":"Liverpool",
    "sg:classifiers":[
        {
            "category":"Wholesale",
            "subcategory":"Groceries",
            "type":"Manufacturing & Wholesale Goods"
        }
    ],
    "sg:phone":"+44 151 256 5855",
    "sg:postcode":"L11 3BA",
    "sg:province":"Merseyside",
    "sg:tags":[
        "sausage",
        "product"
    ],
    "wof:name":"Joe's",
    "wof:placetype":"venue"
},
  "geometry": {"coordinates":[-2.919223,53.447365],"type":"Point"}
}