{
  "type": "Feature",
  "properties": {
    "addr:full":"Unit 1 Maltkiln Lane Castleford West Yorkshire WF10 4LF",
    "addr:housenumber":"unit 1",
    "addr:postcode":"wf10 4lf",
    "addr:street":"Maltkiln Lane",
    "iso:country":"GB",
    "sg:address":"Unit 1 Maltkiln Lane",
    "sg:city":"Castleford",
    "sg:classifiers":[
        {
            "category":"Retail",
            "subcategory":"Auto Repair",
            "type":"Services"
        }
    ],
    "sg:phone":"+44 1977 517659",
    "sg:postcode":"WF10 4LF",
    "sg:province":"West Yorkshire",
    "sg:tags":[
        "body",
        "car"
    ],
    "wof:name":"Maltkiln Auto Body Shop",
    "wof:placetype":"venue"
},
  "geometry": {"coordinates":[-1.345459,53.726006],"type":"Point"}
}