{
  "type": "Feature",
  "properties": {
    "addr:full":"2a Villiers Street, Briton Ferry Neath Neath Port Talbot SA11 2DZ",
    "addr:housenumber":"2a",
    "addr:postcode":"sa11 2dz",
    "addr:street":"Villiers Street",
    "iso:country":"GB",
    "sg:address":"2a Villiers Street, Briton Ferry",
    "sg:city":"Neath",
    "sg:classifiers":[
        {
            "category":"Bars & Pubs",
            "type":"Food & Drink"
        }
    ],
    "sg:phone":"+44 1639 813899",
    "sg:postcode":"SA11 2DZ",
    "sg:province":"Neath Port Talbot",
    "sg:tags":[
        "pubs",
        "inn"
    ],
    "wof:name":"Valentines",
    "wof:placetype":"venue"
},
  "geometry": {"coordinates":[-3.8217010498,51.6309967041],"type":"Point"}
}