{
  "type": "Feature",
  "properties": {
    "iso:country":"GB",
    "sg:address":"Ravenscroft, Smelterwood Dr",
    "sg:city":"Sheffield",
    "sg:classifiers":[
        {
            "category":"Social Services",
            "subcategory":"Retirement Home",
            "type":"Services"
        }
    ],
    "sg:phone":"+44 114 239 3874",
    "sg:postcode":"S13 8RL",
    "sg:province":"South Yorkshire",
    "sg:tags":[
        "care"
    ],
    "wof:name":"Community Care Line Services",
    "wof:placetype":"venue"
},
  "geometry": {"coordinates":[-1.398162,53.365059],"type":"Point"}
}