{
  "type": "Feature",
  "properties": {
    "addr:full":"1 Northcote Rd Bristol City of Bristol BS17 3HF",
    "addr:housenumber":"1",
    "addr:postcode":"bs17 3hf",
    "addr:street":"Northcote Rd",
    "iso:country":"GB",
    "sg:address":"1 Northcote Rd",
    "sg:city":"Bristol",
    "sg:classifiers":[
        {
            "category":"Shopping",
            "subcategory":"Department Store",
            "type":"Retail Goods"
        }
    ],
    "sg:phone":"+44 117 957 0498",
    "sg:postcode":"BS17 3HF",
    "sg:province":"City of Bristol",
    "wof:name":"Londis",
    "wof:placetype":"venue"
},
  "geometry": {"coordinates":[-2.546151,51.459824],"type":"Point"}
}