{
  "type": "Feature",
  "properties": {
    "addr:full":"Tretharrup Farm, St Martin Helston Cornwall TR12 6EE",
    "addr:postcode":"tr12 6ee",
    "iso:country":"GB",
    "sg:address":"Tretharrup Farm, St Martin",
    "sg:city":"Helston",
    "sg:classifiers":[
        {
            "category":"Farming",
            "subcategory":"Farm",
            "type":"Manufacturing & Wholesale Goods"
        }
    ],
    "sg:postcode":"TR12 6EE",
    "sg:province":"Cornwall",
    "sg:tags":[
        "mixed",
        "crop"
    ],
    "wof:name":"Robert G Williams",
    "wof:placetype":"venue"
},
  "geometry": {"coordinates":[-5.15942,50.059528],"type":"Point"}
}