{
  "type": "Feature",
  "properties": {
    "iso:country":"GB",
    "sg:address":"Unit W7 Newhouse Business Park, Newhouse Road",
    "sg:city":"Grangemouth",
    "sg:classifiers":[
        {
            "category":"Manufacturing",
            "subcategory":"Wood Products",
            "type":"Manufacturing & Wholesale Goods"
        }
    ],
    "sg:phone":"+44 1324 887029",
    "sg:postcode":"FK3 8LL",
    "sg:province":"Falkirk",
    "sg:tags":[
        "maker",
        "cabinet"
    ],
    "wof:name":"Grangemouth Kitchen & Bathroom",
    "wof:placetype":"venue"
},
  "geometry": {"coordinates":[-3.7238938808,56.0093307495],"type":"Point"}
}