{
  "type": "Feature",
  "properties": {
    "addr:full":"Phoenix House, Lingfield Rd East Grinstead East Sussex RH19 2EU",
    "addr:postcode":"rh19 2eu",
    "addr:street":"Lingfield Rd",
    "iso:country":"GB",
    "sg:address":"Phoenix House, Lingfield Rd",
    "sg:city":"East Grinstead",
    "sg:classifiers":[
        {
            "category":"Freight",
            "type":"Transportation"
        }
    ],
    "sg:phone":"+44 1342 316044",
    "sg:postcode":"RH19 2EU",
    "sg:province":"East Sussex",
    "sg:tags":[
        "haulage",
        "road"
    ],
    "wof:name":"Courtesy Carriage Co",
    "wof:placetype":"venue"
},
  "geometry": {"coordinates":[-0.018409,51.136875],"type":"Point"}
}