{
  "type": "Feature",
  "properties": {
    "addr:full":"80a Institute Rd Birmingham West Midlands B14 7EY",
    "addr:housenumber":"80a",
    "addr:postcode":"b14 7ey",
    "addr:street":"Institute Rd",
    "iso:country":"GB",
    "sg:address":"80a Institute Rd",
    "sg:city":"Birmingham",
    "sg:classifiers":[
        {
            "category":"Professional",
            "subcategory":"Printing & Photocopies",
            "type":"Services"
        }
    ],
    "sg:phone":"+44 121 444 4255",
    "sg:postcode":"B14 7EY",
    "sg:province":"West Midlands",
    "sg:tags":[
        "printer"
    ],
    "wof:name":"HAYDON PRINTING COMPANY",
    "wof:placetype":"venue"
},
  "geometry": {"coordinates":[-1.888894,52.433376],"type":"Point"}
}