{
  "type": "Feature",
  "properties": {
    "iso:country":"GB",
    "sg:address":"331 Fox Hollies Road, Acocks Green",
    "sg:city":"Birmingham",
    "sg:classifiers":[
        {
            "category":"Retail",
            "subcategory":"Laundry & Dry Cleaning",
            "type":"Services"
        }
    ],
    "sg:phone":"+44 121 706 4056",
    "sg:postcode":"B27 7PS",
    "sg:province":"West Midlands",
    "sg:tags":[
        "launderette"
    ],
    "wof:name":"Fox Hollies Cleaning Centre",
    "wof:placetype":"venue"
},
  "geometry": {"coordinates":[-1.8340779543,52.4423484802],"type":"Point"}
}