{
  "type": "Feature",
  "properties": {
    "addr:full":"Wards Hurst Farm, Ringshall Berkhamsted Bedfordshire HP4 1NF",
    "addr:housenumber":"farm",
    "addr:postcode":"hp4 1nf",
    "addr:street":"Wards Hurst",
    "iso:country":"GB",
    "sg:address":"Wards Hurst Farm, Ringshall",
    "sg:city":"Berkhamsted",
    "sg:classifiers":[
        {
            "category":"Building & Trades",
            "subcategory":"Equipment Rental",
            "type":"Services"
        },
        {
            "category":"Social Services",
            "subcategory":"Retirement Home",
            "type":"Services"
        }
    ],
    "sg:phone":"+44 1442 843479",
    "sg:postcode":"HP4 1NF",
    "sg:province":"Bedfordshire",
    "sg:tags":[
        "plant",
        "leasing",
        "machinery"
    ],
    "wof:name":"Mark Gent",
    "wof:placetype":"venue"
},
  "geometry": {"coordinates":[-0.573149,51.817722],"type":"Point"}
}