{
  "type": "Feature",
  "properties": {
    "iso:country":"GB",
    "sg:address":"Kerry",
    "sg:city":"Newtown",
    "sg:classifiers":[
        {
            "category":"Retail",
            "subcategory":"Auto Repair",
            "type":"Services"
        }
    ],
    "sg:phone":"+44 1686 670443",
    "sg:postcode":"SY16 4LW",
    "sg:province":"Powys",
    "sg:tags":[
        "modification",
        "garage"
    ],
    "wof:name":"Glanmule Garage",
    "wof:placetype":"venue"
},
  "geometry": {"coordinates":[-3.2337799072,52.5048294067],"type":"Point"}
}