{
  "type": "Feature",
  "properties": {
    "addr:full":"Quilow Farm Ashbourne Derbyshire DE6 1LU",
    "addr:postcode":"de6 1lu",
    "iso:country":"GB",
    "sg:address":"Quilow Farm",
    "sg:city":"Ashbourne",
    "sg:classifiers":[
        {
            "category":"Shopping",
            "subcategory":"Department Store",
            "type":"Retail Goods"
        }
    ],
    "sg:postcode":"DE6 1LU",
    "sg:province":"Derbyshire",
    "wof:name":"Des & Di",
    "wof:placetype":"venue"
},
  "geometry": {"coordinates":[-1.7325639725,53.0182800293],"type":"Point"}
}