{
  "type": "Feature",
  "properties": {
    "addr:full":"25 Glenfield Ho, Philips Rd Blackburn Lancashire BB1 5PF",
    "addr:housenumber":"25",
    "addr:postcode":"bb1 5pf",
    "addr:street":"Glenfield Ho Philips Rd",
    "iso:country":"GB",
    "sg:address":"25 Glenfield Ho, Philips Rd",
    "sg:city":"Blackburn",
    "sg:classifiers":[
        {
            "category":"Professional",
            "subcategory":"Advertising",
            "type":"Services"
        }
    ],
    "sg:postcode":"BB1 5PF",
    "sg:province":"Lancashire",
    "sg:tags":[
        "agency"
    ],
    "wof:name":"Unified Media Marketing Ltd",
    "wof:placetype":"venue"
},
  "geometry": {"coordinates":[-2.480399,53.748516],"type":"Point"}
}