{
  "type": "Feature",
  "properties": {
    "addr:full":"Flat 12a 163 Balgrayhill Rd Glasgow East Dunbartonshire G21 3AP",
    "addr:housenumber":"12a 163",
    "addr:postcode":"g21 3ap",
    "addr:street":"Balgrayhill Rd",
    "iso:country":"GB",
    "sg:address":"Flat 12a 163 Balgrayhill Rd",
    "sg:city":"Glasgow",
    "sg:classifiers":[
        {
            "category":"Professional",
            "subcategory":"Lawyer & Legal Services",
            "type":"Services"
        }
    ],
    "sg:phone":"+44 141 558 1305",
    "sg:postcode":"G21 3AP",
    "sg:province":"East Dunbartonshire",
    "sg:tags":[
        "advice",
        "counselling"
    ],
    "wof:name":"M A R C Link",
    "wof:placetype":"venue"
},
  "geometry": {"coordinates":[-4.23021,55.890862],"type":"Point"}
}