{
  "type": "Feature",
  "properties": {
    "addr:full":"5 Marine Walk Street Hythe Kent CT21 5NW",
    "addr:housenumber":"5",
    "addr:postcode":"ct21 5nw",
    "addr:street":"Marine Walk Street",
    "iso:country":"GB",
    "sg:address":"5 Marine Walk Street",
    "sg:city":"Hythe",
    "sg:classifiers":[
        {
            "category":"Home & Garden",
            "subcategory":"Household Appliances",
            "type":"Retail Goods"
        }
    ],
    "sg:postcode":"CT21 5NW",
    "sg:province":"Kent",
    "sg:tags":[
        "domestic",
        "oven",
        "microwave"
    ],
    "wof:name":"D Easton",
    "wof:placetype":"venue"
},
  "geometry": {"coordinates":[1.084848,51.071457],"type":"Point"}
}