{
  "type": "Feature",
  "properties": {
    "iso:country":"GB",
    "sg:address":"The Barn, Westlakes Science & Technology Pk",
    "sg:city":"Moor Row",
    "sg:classifiers":[
        {
            "category":"Professional",
            "subcategory":"Management & Consulting",
            "type":"Services"
        }
    ],
    "sg:postcode":"CA24 3JG",
    "sg:province":"Cumbria",
    "sg:tags":[
        "consultant",
        "business"
    ],
    "wof:name":"Maddison,Roy,",
    "wof:placetype":"venue"
},
  "geometry": {"coordinates":[-3.53743,54.514462],"type":"Point"}
}