{
  "type": "Feature",
  "properties": {
    "addr:full":"1b Hodge Lea Lane, Hodge Lea Milton Keynes Buckinghamshire MK12 6JA",
    "addr:housenumber":"1b",
    "addr:postcode":"mk12 6ja",
    "addr:street":"Hodge Lea Lane",
    "iso:country":"GB",
    "sg:address":"1b Hodge Lea Lane, Hodge Lea",
    "sg:city":"Milton Keynes",
    "sg:classifiers":[
        {
            "category":"Building & Trades",
            "subcategory":"Landscaping Services",
            "type":"Services"
        }
    ],
    "sg:phone":"+44 1908 320241",
    "sg:postcode":"MK12 6JA",
    "sg:province":"Buckinghamshire",
    "sg:tags":[
        "landscape",
        "contractor"
    ],
    "wof:name":"Robert Lyne Kent",
    "wof:placetype":"venue"
},
  "geometry": {"coordinates":[-0.813772,52.05011],"type":"Point"}
}