{
  "type": "Feature",
  "properties": {
    "iso:country":"GB",
    "sg:address":"Higher Coxes Farm, Weston",
    "sg:city":"Sidmouth",
    "sg:classifiers":[
        {
            "category":"Farming",
            "subcategory":"Livestock Farm",
            "type":"Manufacturing & Wholesale Goods"
        },
        {
            "category":"Farming",
            "subcategory":"Farm",
            "type":"Manufacturing & Wholesale Goods"
        }
    ],
    "sg:phone":"+44 1297 680528",
    "sg:postcode":"EX10 0PG",
    "sg:province":"Devon",
    "sg:tags":[
        "mixed",
        "others"
    ],
    "wof:name":"John D Burrough",
    "wof:placetype":"venue"
},
  "geometry": {"coordinates":[-3.185674,50.696064],"type":"Point"}
}