{
  "type": "Feature",
  "properties": {
    "addr:full":"56 St Thomas Road Derby Derbyshire DE23 8SU",
    "addr:housenumber":"56",
    "addr:postcode":"de23 8su",
    "addr:street":"St Thomas Road",
    "iso:country":"GB",
    "sg:address":"56 St Thomas Road",
    "sg:city":"Derby",
    "sg:classifiers":[
        {
            "category":"Professional",
            "subcategory":"Employment Agencies",
            "type":"Services"
        }
    ],
    "sg:phone":"+44 1332 369330",
    "sg:postcode":"DE23 8SU",
    "sg:province":"Derbyshire",
    "sg:tags":[
        "consultant"
    ],
    "wof:name":"Centre Locum",
    "wof:placetype":"venue"
},
  "geometry": {"coordinates":[-1.476312995,52.9042854309],"type":"Point"}
}