{
  "type": "Feature",
  "properties": {
    "addr:full":"13 Ratcliffe Terrace Edinburgh City of Edinburgh EH9 1SX",
    "addr:housenumber":"13",
    "addr:postcode":"eh9 1sx",
    "addr:street":"Ratcliffe Terrace",
    "iso:country":"GB",
    "sg:address":"13 Ratcliffe Terrace",
    "sg:city":"Edinburgh",
    "sg:classifiers":[
        {
            "category":"Retail",
            "subcategory":"Laundry & Dry Cleaning",
            "type":"Services"
        }
    ],
    "sg:postcode":"EH9 1SX",
    "sg:province":"City of Edinburgh",
    "sg:tags":[
        "launderette"
    ],
    "wof:name":"Sundial Launderette",
    "wof:placetype":"venue"
},
  "geometry": {"coordinates":[-3.1786100864,55.9346237183],"type":"Point"}
}