{
  "type": "Feature",
  "properties": {
    "iso:country":"GB",
    "sg:address":"16 Lias Road",
    "sg:city":"Porthcawl",
    "sg:classifiers":[
        {
            "category":"Professional",
            "subcategory":"Printing & Photocopies",
            "type":"Services"
        }
    ],
    "sg:phone":"+44 1656 772960",
    "sg:postcode":"CF36 3AH",
    "sg:province":"Bridgend",
    "sg:tags":[
        "duplicating",
        "copying"
    ],
    "wof:name":"S J C Copy Centres Ltd.",
    "wof:placetype":"venue"
},
  "geometry": {"coordinates":[-3.704925,51.479111],"type":"Point"}
}