{
  "type": "Feature",
  "properties": {
    "iso:country":"GB",
    "sg:address":"1st Floor, 348 Regents Park Road",
    "sg:city":"London",
    "sg:classifiers":[
        {
            "category":"Professional",
            "subcategory":"Business Services",
            "type":"Services"
        }
    ],
    "sg:phone":"+44 20 8346 9273",
    "sg:postcode":"N3 2LJ",
    "sg:province":"Greater London",
    "sg:tags":[
        "holding"
    ],
    "wof:name":"T Tazaki & Co. Ltd.",
    "wof:placetype":"venue"
},
  "geometry": {"coordinates":[-0.193931,51.600899],"type":"Point"}
}