{
  "type": "Feature",
  "properties": {
    "iso:country":"GB",
    "sg:address":"11a Childerditch Industrial Estate, Little Warley",
    "sg:city":"Brentwood",
    "sg:classifiers":[
        {
            "category":"Cafe",
            "type":"Food & Drink"
        }
    ],
    "sg:phone":"+44 1277 810964",
    "sg:postcode":"CM13 3HD",
    "sg:province":"Essex",
    "sg:tags":[
        "tea",
        "room"
    ],
    "wof:name":"The Cafe",
    "wof:placetype":"venue"
},
  "geometry": {"coordinates":[0.321805,51.581532],"type":"Point"}
}