{
  "type": "Feature",
  "properties": {
    "iso:country":"GB",
    "sg:address":"103 Anglesea Rd",
    "sg:city":"Ipswich",
    "sg:classifiers":[
        {
            "category":"Professional",
            "subcategory":"Management & Consulting",
            "type":"Services"
        }
    ],
    "sg:phone":"+44 1473 251601",
    "sg:postcode":"IP1 3PJ",
    "sg:province":"Suffolk",
    "sg:tags":[
        "consultant",
        "training"
    ],
    "wof:name":"Language Solutions",
    "wof:placetype":"venue"
},
  "geometry": {"coordinates":[1.1430989504,52.0644187927],"type":"Point"}
}