{
  "type": "Feature",
  "properties": {
    "iso:country":"GB",
    "sg:address":"59 Trafalgar Street",
    "sg:city":"Sheffield",
    "sg:classifiers":[
        {
            "category":"Manufacturing",
            "subcategory":"Furniture",
            "type":"Manufacturing & Wholesale Goods"
        }
    ],
    "sg:phone":"+44 114 273 0451",
    "sg:postcode":"S1 4GN",
    "sg:province":"South Yorkshire",
    "sg:tags":[
        "design"
    ],
    "wof:name":"Paul Carruthers Design",
    "wof:placetype":"venue"
},
  "geometry": {"coordinates":[-1.475749,53.378605],"type":"Point"}
}