{
  "type": "Feature",
  "properties": {
    "addr:full":"597 Halifax Rd Bradford West Yorkshire BD6 2DU",
    "addr:housenumber":"597",
    "addr:postcode":"bd6 2du",
    "addr:street":"Halifax Rd",
    "iso:country":"GB",
    "sg:address":"597 Halifax Rd",
    "sg:city":"Bradford",
    "sg:classifiers":[
        {
            "category":"Organizations",
            "subcategory":"Non-profit Organization",
            "type":"Services"
        }
    ],
    "sg:phone":"+44 1274 676959",
    "sg:postcode":"BD6 2DU",
    "sg:province":"West Yorkshire",
    "sg:tags":[
        "organisation",
        "voluntary",
        "charity"
    ],
    "wof:name":"Guide Dogs For The Blind Association The",
    "wof:placetype":"venue"
},
  "geometry": {"coordinates":[-1.7926390171,53.7585983276],"type":"Point"}
}