{
  "type": "Feature",
  "properties": {
    "iso:country":"GB",
    "sg:address":"6a Brinsworth Lane, Brinsworth",
    "sg:city":"Rotherham",
    "sg:classifiers":[
        {
            "category":"Government",
            "subcategory":"Post Office",
            "type":"Public Place"
        }
    ],
    "sg:phone":"+44 1709 364798",
    "sg:postcode":"S60 5BS",
    "sg:province":"South Yorkshire",
    "wof:name":"Brinsworth Post Office",
    "wof:placetype":"venue"
},
  "geometry": {"coordinates":[-1.3756140471,53.4038505554],"type":"Point"}
}