{
  "type": "Feature",
  "properties": {
    "addr:full":"15 Otley Street Skipton Lancashire BD23 1DY",
    "addr:housenumber":"15",
    "addr:postcode":"bd23 1dy",
    "addr:street":"Otley Street",
    "iso:country":"GB",
    "sg:address":"15 Otley Street",
    "sg:city":"Skipton",
    "sg:classifiers":[
        {
            "category":"Farming",
            "subcategory":"Livestock Farm",
            "type":"Manufacturing & Wholesale Goods"
        },
        {
            "category":"Shopping",
            "subcategory":"Florist",
            "type":"Retail Goods"
        }
    ],
    "sg:postcode":"BD23 1DY",
    "sg:province":"Lancashire",
    "sg:tags":[
        "breeder"
    ],
    "wof:name":"Flowers by Design",
    "wof:placetype":"venue"
},
  "geometry": {"coordinates":[-2.0157148838,53.9616546631],"type":"Point"}
}