{
  "type": "Feature",
  "properties": {
    "iso:country":"GB",
    "sg:address":"College Court, 15 Bowen Lane",
    "sg:city":"Petersfield",
    "sg:classifiers":[
        {
            "category":"Professional",
            "subcategory":"Accounting & Tax Preparation",
            "type":"Services"
        }
    ],
    "sg:phone":"+44 1730 266015",
    "sg:postcode":"GU31 4DR",
    "sg:province":"Hampshire",
    "sg:tags":[
        "accountant"
    ],
    "wof:name":"Jennifer Broadhead",
    "wof:placetype":"venue"
},
  "geometry": {"coordinates":[-0.9347000122,51.0040016174],"type":"Point"}
}