{
  "type": "Feature",
  "properties": {
    "iso:country":"GB",
    "sg:address":"1 Sidlaw Terrace, Clarence Road",
    "sg:city":"Bognor Regis",
    "sg:classifiers":[
        {
            "category":"Professional",
            "subcategory":"Accounting & Tax Preparation",
            "type":"Services"
        }
    ],
    "sg:phone":"+44 1243 823745",
    "sg:postcode":"PO21 1JY",
    "sg:province":"West Sussex",
    "sg:tags":[
        "accountant",
        "activity"
    ],
    "wof:name":"C B Mandry",
    "wof:placetype":"venue"
},
  "geometry": {"coordinates":[-0.675349,50.782967],"type":"Point"}
}