{
  "type": "Feature",
  "properties": {
    "addr:full":"159 Deane Road Bolton Lancashire BL3 5HP",
    "addr:housenumber":"159",
    "addr:postcode":"bl3 5hp",
    "addr:street":"Deane Road",
    "iso:country":"GB",
    "sg:address":"159 Deane Road",
    "sg:city":"Bolton",
    "sg:classifiers":[
        {
            "category":"Retail",
            "subcategory":"Auto Repair",
            "type":"Services"
        }
    ],
    "sg:phone":"+44 1204 522786",
    "sg:postcode":"BL3 5HP",
    "sg:province":"Lancashire",
    "sg:tags":[
        "modification",
        "garage"
    ],
    "wof:name":"A P N A Motors",
    "wof:placetype":"venue"
},
  "geometry": {"coordinates":[-2.4381539822,53.5742835999],"type":"Point"}
}