{
  "type": "Feature",
  "properties": {
    "addr:full":"Archway 2 Station Yard, Shaw Street St Helens Merseyside WA10 1DQ",
    "addr:housenumber":"2",
    "addr:postcode":"wa10 1dq",
    "addr:street":"Archway;Station Yard Shaw Street",
    "iso:country":"GB",
    "sg:address":"Archway 2 Station Yard, Shaw Street",
    "sg:city":"St Helens",
    "sg:classifiers":[
        {
            "category":"Retail",
            "subcategory":"Repair Shop",
            "type":"Services"
        }
    ],
    "sg:phone":"+44 1744 614198",
    "sg:postcode":"WA10 1DQ",
    "sg:province":"Merseyside",
    "sg:tags":[
        "upholsterer"
    ],
    "wof:name":"New Style Upholstery",
    "wof:placetype":"venue"
},
  "geometry": {"coordinates":[-2.7388679981,53.4516868591],"type":"Point"}
}