{
  "type": "Feature",
  "properties": {
    "addr:full":"Wellbank Farm, Pillar Box Lane Sandbach Cheshire CW11 1RE",
    "addr:postcode":"cw11 1re",
    "addr:street":"Box Lane",
    "iso:country":"GB",
    "sg:address":"Wellbank Farm, Pillar Box Lane",
    "sg:city":"Sandbach",
    "sg:classifiers":[
        {
            "category":"Professional",
            "subcategory":"Computer Services",
            "type":"Services"
        }
    ],
    "sg:phone":"+44 1270 766679",
    "sg:postcode":"CW11 1RE",
    "sg:province":"Cheshire",
    "sg:tags":[
        "system",
        "software"
    ],
    "wof:name":"Cybermetrix Ltd.",
    "wof:placetype":"venue"
},
  "geometry": {"coordinates":[-2.363648,53.142208],"type":"Point"}
}