{
  "type": "Feature",
  "properties": {
    "addr:full":"Middle Street Farm, Middle Street, Eastington Stonehouse Gloucestershire GL10 3BA",
    "addr:postcode":"gl10 3ba",
    "addr:street":"Middle Street;Middle Street",
    "iso:country":"GB",
    "sg:address":"Middle Street Farm, Middle Street, Eastington",
    "sg:city":"Stonehouse",
    "sg:classifiers":[
        {
            "category":"Farming",
            "subcategory":"Livestock Farm",
            "type":"Manufacturing & Wholesale Goods"
        }
    ],
    "sg:phone":"+44 1453 822103",
    "sg:postcode":"GL10 3BA",
    "sg:province":"Gloucestershire",
    "sg:tags":[
        "others"
    ],
    "wof:name":"Martin S Coole",
    "wof:placetype":"venue"
},
  "geometry": {"coordinates":[-2.325842,51.746082],"type":"Point"}
}