{
  "type": "Feature",
  "properties": {
    "iso:country":"GB",
    "sg:address":"Sully House, 7 Clovelly Road Industrial Estate",
    "sg:city":"Bideford",
    "sg:classifiers":[
        {
            "category":"Professional",
            "subcategory":"Art Services",
            "type":"Services"
        }
    ],
    "sg:phone":"+44 1237 425140",
    "sg:postcode":"EX39 3HN",
    "sg:province":"Devon",
    "sg:tags":[
        "graphic",
        "designer"
    ],
    "wof:name":"Deighton Needleworks Ltd.",
    "wof:placetype":"venue"
},
  "geometry": {"coordinates":[-4.212713,51.01545],"type":"Point"}
}