{
  "type": "Feature",
  "properties": {
    "addr:full":"Charlton Street Grimsby Lincolnshire DN31 1SQ",
    "addr:postcode":"dn31 1sq",
    "addr:street":"Charlton Street",
    "iso:country":"GB",
    "sg:address":"Charlton Street",
    "sg:city":"Grimsby",
    "sg:classifiers":[
        {
            "category":"Building & Trades",
            "subcategory":"Construction",
            "type":"Services"
        }
    ],
    "sg:phone":"+44 1472 509944",
    "sg:postcode":"DN31 1SQ",
    "sg:province":"Lincolnshire",
    "sg:tags":[
        "roofing"
    ],
    "wof:name":"Miller Hills Roofing Ltd.",
    "wof:placetype":"venue"
},
  "geometry": {"coordinates":[-0.093179,53.573196],"type":"Point"}
}