{
  "type": "Feature",
  "properties": {
    "addr:full":"60 Charles Street Leicester Leicestershire LE1 1FB",
    "addr:housenumber":"60",
    "addr:postcode":"le1 1fb",
    "addr:street":"Charles Street",
    "iso:country":"GB",
    "sg:address":"60 Charles Street",
    "sg:city":"Leicester",
    "sg:classifiers":[
        {
            "category":"Professional",
            "subcategory":"Employment Agencies",
            "type":"Services"
        }
    ],
    "sg:phone":"+44 116 253 2000",
    "sg:postcode":"LE1 1FB",
    "sg:province":"Leicestershire",
    "sg:tags":[
        "consultant",
        "recruitment"
    ],
    "wof:name":"TFR Driving",
    "wof:placetype":"venue"
},
  "geometry": {"coordinates":[-1.129728,52.635464],"type":"Point"}
}