{
  "type": "Feature",
  "properties": {
    "iso:country":"GB",
    "sg:address":"63 North Rd",
    "sg:city":"Wimbledon",
    "sg:classifiers":[
        {
            "category":"Bus Charters",
            "type":"Transportation"
        }
    ],
    "sg:phone":"+44 20 8543 3048",
    "sg:postcode":"SW19 1AQ",
    "sg:province":"Greater London",
    "sg:tags":[
        "mini",
        "hire",
        "leasing"
    ],
    "wof:name":"Guideline Coaches Of Wimbledon",
    "wof:placetype":"venue"
},
  "geometry": {"coordinates":[-0.183636,51.42131],"type":"Point"}
}