{
  "type": "Feature",
  "properties": {
    "addr:full":"11 Berkeley Crescent Barnet Hertfordshire EN4 8BP",
    "addr:housenumber":"11",
    "addr:postcode":"en4 8bp",
    "addr:street":"Berkeley Crescent",
    "iso:country":"GB",
    "sg:address":"11 Berkeley Crescent",
    "sg:city":"Barnet",
    "sg:classifiers":[
        {
            "category":"Building & Trades",
            "subcategory":"Landscaping Services",
            "type":"Services"
        }
    ],
    "sg:postcode":"EN4 8BP",
    "sg:province":"Hertfordshire",
    "sg:tags":[
        "landscape",
        "contractor"
    ],
    "wof:name":"Evergreen Landscapes & Building Services",
    "wof:placetype":"venue"
},
  "geometry": {"coordinates":[-0.1681730002,51.6451339722],"type":"Point"}
}