{
  "type": "Feature",
  "properties": {
    "iso:country":"GB",
    "sg:address":"The Cottage, St James South Elmham",
    "sg:city":"Halesworth",
    "sg:classifiers":[
        {
            "category":"Freight",
            "type":"Transportation"
        }
    ],
    "sg:phone":"+44 1986 782574",
    "sg:postcode":"IP19 0HL",
    "sg:province":"Suffolk",
    "sg:tags":[
        "haulage",
        "road"
    ],
    "wof:name":"D M Pipe Transport",
    "wof:placetype":"venue"
},
  "geometry": {"coordinates":[1.4101500511,52.38022995],"type":"Point"}
}