{
  "type": "Feature",
  "properties": {
    "addr:full":"258 Upper Shoreham Road Shoreham-by-sea West Sussex BN13 3AB",
    "addr:housenumber":"258",
    "addr:postcode":"bn13 3ab",
    "addr:street":"Upper Shoreham Road",
    "iso:country":"GB",
    "sg:address":"258 Upper Shoreham Road",
    "sg:city":"Shoreham-by-sea",
    "sg:classifiers":[
        {
            "category":"Government",
            "subcategory":"Post Office",
            "type":"Public Place"
        }
    ],
    "sg:phone":"+44 1273 707011",
    "sg:postcode":"BN13 3AB",
    "sg:province":"West Sussex",
    "sg:tags":[
        "messenger",
        "courier"
    ],
    "wof:name":"K S Couriers",
    "wof:placetype":"venue"
},
  "geometry": {"coordinates":[-0.259369,50.841625],"type":"Point"}
}