{
  "type": "Feature",
  "properties": {
    "iso:country":"GB",
    "sg:address":"12 Main Street, Bothwell",
    "sg:city":"Glasgow",
    "sg:classifiers":[
        {
            "category":"Personal",
            "subcategory":"Beauty Salon",
            "type":"Services"
        }
    ],
    "sg:phone":"+44 1698 852291",
    "sg:postcode":"G71 8RF",
    "sg:province":"Glasgow City",
    "sg:tags":[
        "unisex",
        "hairdresser"
    ],
    "wof:name":"Sense of Style",
    "wof:placetype":"venue"
},
  "geometry": {"coordinates":[-4.0667929649,55.802696228],"type":"Point"}
}