{
  "type": "Feature",
  "properties": {
    "addr:full":"208 Picton Rd Liverpool Merseyside L15 4LL",
    "addr:housenumber":"208",
    "addr:postcode":"l15 4ll",
    "addr:street":"Picton Rd",
    "iso:country":"GB",
    "sg:address":"208 Picton Rd",
    "sg:city":"Liverpool",
    "sg:classifiers":[
        {
            "category":"Wholesale",
            "subcategory":"Books, Periodicals, & Newspapers",
            "type":"Manufacturing & Wholesale Goods"
        }
    ],
    "sg:phone":"+44 151 281 8110",
    "sg:postcode":"L15 4LL",
    "sg:province":"Merseyside",
    "sg:tags":[
        "publishing"
    ],
    "wof:name":"Picton Publi",
    "wof:placetype":"venue"
},
  "geometry": {"coordinates":[-2.9270610809,53.3999443054],"type":"Point"}
}