{
  "type": "Feature",
  "properties": {
    "addr:full":"43 Treyew Road, The Donnington House Truro Cornwall TR1 2BY",
    "addr:housenumber":"43",
    "addr:postcode":"tr1 2by",
    "addr:street":"Treyew Road The",
    "iso:country":"GB",
    "sg:address":"43 Treyew Road, The Donnington House",
    "sg:city":"Truro",
    "sg:classifiers":[
        {
            "category":"Government",
            "subcategory":"Office",
            "type":"Public Place"
        }
    ],
    "sg:phone":"+44 1872 240044",
    "sg:postcode":"TR1 2BY",
    "sg:province":"Cornwall",
    "sg:tags":[
        "chamber",
        "commerce"
    ],
    "wof:name":"City of Truro Chamber of Commerce",
    "wof:placetype":"venue"
},
  "geometry": {"coordinates":[-5.0641841888,50.258808136],"type":"Point"}
}