{
  "type": "Feature",
  "properties": {
    "addr:full":"High Street Chalfont St Giles Buckinghamshire HP8 4QH",
    "addr:postcode":"hp8 4qh",
    "addr:street":"High Street",
    "iso:country":"GB",
    "sg:address":"High Street",
    "sg:city":"Chalfont St Giles",
    "sg:classifiers":[
        {
            "category":"Farming",
            "subcategory":"Fish & Marine Products",
            "type":"Manufacturing & Wholesale Goods"
        },
        {
            "category":"Food & Beverages",
            "subcategory":"Meat & Fish",
            "type":"Retail Goods"
        }
    ],
    "sg:phone":"+44 1494 872016",
    "sg:postcode":"HP8 4QH",
    "sg:province":"Buckinghamshire",
    "sg:tags":[
        "fishmonger",
        "butcher"
    ],
    "wof:name":"Albert Warner",
    "wof:placetype":"venue"
},
  "geometry": {"coordinates":[-0.5689039826,51.6331710815],"type":"Point"}
}