{
  "type": "Feature",
  "properties": {
    "addr:full":"Coed Gwgan Hall, Crossgates Llandrindod Wells Powys LD1 6RS",
    "addr:postcode":"ld1 6rs",
    "iso:country":"GB",
    "sg:address":"Coed Gwgan Hall, Crossgates",
    "sg:city":"Llandrindod Wells",
    "sg:classifiers":[
        {
            "category":"Real Estate",
            "subcategory":"Architect",
            "type":"Services"
        }
    ],
    "sg:phone":"+44 1597 851391",
    "sg:postcode":"LD1 6RS",
    "sg:province":"Powys",
    "wof:name":"J V Gibberd",
    "wof:placetype":"venue"
},
  "geometry": {"coordinates":[-3.3403940201,52.2746429443],"type":"Point"}
}