{
  "type": "Feature",
  "properties": {
    "iso:country":"GB",
    "sg:address":"Britannia Suite International, House, 82-86 Deansgate",
    "sg:city":"Manchester",
    "sg:classifiers":[
        {
            "category":"Professional",
            "subcategory":"Computer Services",
            "type":"Services"
        }
    ],
    "sg:postcode":"M3 2ER",
    "sg:province":"Greater Manchester",
    "sg:tags":[
        "system",
        "software"
    ],
    "wof:name":"Rebourn Ltd",
    "wof:placetype":"venue"
},
  "geometry": {"coordinates":[-2.247179,53.482052],"type":"Point"}
}