{
  "type": "Feature",
  "properties": {
    "iso:country":"GB",
    "sg:address":"Poppyfields",
    "sg:city":"Northampton",
    "sg:classifiers":[
        {
            "category":"Building & Trades",
            "subcategory":"Construction",
            "type":"Services"
        }
    ],
    "sg:phone":"+44 1536 401938",
    "sg:postcode":"NN18 8NG",
    "sg:province":"Northamptonshire",
    "sg:tags":[
        "builder"
    ],
    "wof:name":"McAlpine Alfred Homes",
    "wof:placetype":"venue"
},
  "geometry": {"coordinates":[-0.7062990069,52.4744682312],"type":"Point"}
}