{
  "type": "Feature",
  "properties": {
    "addr:full":"66 Newland Street Witham Essex CM8 1AH",
    "addr:housenumber":"66",
    "addr:postcode":"cm8 1ah",
    "addr:street":"Newland Street",
    "iso:country":"GB",
    "sg:address":"66 Newland Street",
    "sg:city":"Witham",
    "sg:classifiers":[
        {
            "category":"Professional",
            "subcategory":"Management & Consulting",
            "type":"Services"
        }
    ],
    "sg:phone":"+44 1376 501148",
    "sg:postcode":"CM8 1AH",
    "sg:province":"Essex",
    "sg:tags":[
        "consultant",
        "business"
    ],
    "wof:name":"S P C Services Ltd.",
    "wof:placetype":"venue"
},
  "geometry": {"coordinates":[0.6391509771,51.7992134094],"type":"Point"}
}