{
  "type": "Feature",
  "properties": {
    "addr:full":"Murchington Farm, Murchington, Chagford Newton Abbot Devon TQ13 8HJ",
    "addr:postcode":"tq13 8hj",
    "addr:street":"Murchington Chagford",
    "iso:country":"GB",
    "sg:address":"Murchington Farm, Murchington, Chagford",
    "sg:city":"Newton Abbot",
    "sg:classifiers":[
        {
            "category":"Building & Trades",
            "subcategory":"Landscaping Services",
            "type":"Services"
        }
    ],
    "sg:phone":"+44 1647 433389",
    "sg:postcode":"TQ13 8HJ",
    "sg:province":"Devon",
    "sg:tags":[
        "landscape",
        "contractor"
    ],
    "wof:name":"Tamar Construction",
    "wof:placetype":"venue"
},
  "geometry": {"coordinates":[-3.8342559338,50.6774177551],"type":"Point"}
}