{
  "type": "Feature",
  "properties": {
    "addr:full":"135 Waterloo St Burton-on-trent Derbyshire DE14 2NF",
    "addr:housenumber":"135",
    "addr:postcode":"de14 2nf",
    "addr:street":"Waterloo St",
    "iso:country":"GB",
    "sg:address":"135 Waterloo St",
    "sg:city":"Burton-on-trent",
    "sg:classifiers":[
        {
            "category":"Building & Trades",
            "subcategory":"Plumbing",
            "type":"Services"
        }
    ],
    "sg:postcode":"DE14 2NF",
    "sg:province":"Derbyshire",
    "sg:tags":[
        "heating"
    ],
    "wof:name":"Beacon Building & Plumbing Services",
    "wof:placetype":"venue"
},
  "geometry": {"coordinates":[-1.642588973,52.8133926392],"type":"Point"}
}