{
  "type": "Feature",
  "properties": {
    "addr:full":"Shelibost, Harris Harris Eilean Siar HS3 3HP",
    "addr:postcode":"hs3 3hp",
    "iso:country":"GB",
    "sg:address":"Shelibost, Harris",
    "sg:city":"Harris",
    "sg:classifiers":[
        {
            "category":"Education",
            "subcategory":"School",
            "type":"Public Place"
        }
    ],
    "sg:phone":"+44 1859 550216",
    "sg:postcode":"HS3 3HP",
    "sg:province":"Eilean Siar",
    "sg:tags":[
        "local",
        "authority"
    ],
    "wof:name":"Shelibost School",
    "wof:placetype":"venue"
},
  "geometry": {"coordinates":[-6.798484,57.897346],"type":"Point"}
}