{
  "type": "Feature",
  "properties": {
    "addr:full":"Warren House Farm, Woodfield Road, Wentbridge Pontefract North Yorkshire WF8 3JG",
    "addr:postcode":"wf8 3jg",
    "addr:street":"Warren House;Woodfield Road",
    "iso:country":"GB",
    "sg:address":"Warren House Farm, Woodfield Road, Wentbridge",
    "sg:city":"Pontefract",
    "sg:classifiers":[
        {
            "category":"Farming",
            "subcategory":"Crops",
            "type":"Manufacturing & Wholesale Goods"
        },
        {
            "category":"Farming",
            "subcategory":"Livestock Farm",
            "type":"Manufacturing & Wholesale Goods"
        }
    ],
    "sg:phone":"+44 1302 722713",
    "sg:postcode":"WF8 3JG",
    "sg:province":"North Yorkshire",
    "sg:tags":[
        "arable",
        "others"
    ],
    "wof:name":"Alan Clark",
    "wof:placetype":"venue"
},
  "geometry": {"coordinates":[-1.2631839514,53.6508102417],"type":"Point"}
}