{
  "type": "Feature",
  "properties": {
    "addr:full":"Heath Cottage, 14 Elm Av Littlehampton West Sussex BN16 1HJ",
    "addr:housenumber":"14",
    "addr:postcode":"bn16 1hj",
    "addr:street":"Elm Av Littlehampton",
    "iso:country":"GB",
    "sg:address":"Heath Cottage, 14 Elm Av",
    "sg:city":"Littlehampton",
    "sg:classifiers":[
        {
            "category":"Professional",
            "subcategory":"Secretarial Services",
            "type":"Services"
        }
    ],
    "sg:phone":"+44 1903 850279",
    "sg:postcode":"BN16 1HJ",
    "sg:province":"West Sussex",
    "wof:name":"Type-Write",
    "wof:placetype":"venue"
},
  "geometry": {"coordinates":[-0.4739800096,50.8121185303],"type":"Point"}
}