{
  "type": "Feature",
  "properties": {
    "iso:country":"GB",
    "sg:address":"54 The Portlands, Sovereign Harbour Village",
    "sg:city":"Eastbourne",
    "sg:classifiers":[
        {
            "category":"Arts & Performance",
            "subcategory":"Music",
            "type":"Entertainment"
        }
    ],
    "sg:phone":"+44 1323 470544",
    "sg:postcode":"BN23 5RD",
    "sg:province":"East Sussex",
    "sg:tags":[
        "mobile",
        "disco"
    ],
    "wof:name":"Keith Brady Roadshow",
    "wof:placetype":"venue"
},
  "geometry": {"coordinates":[0.32597,50.787239],"type":"Point"}
}