{
  "type": "Feature",
  "properties": {
    "iso:country":"GB",
    "sg:address":"14 Ely Place, Holborn Circus",
    "sg:city":"London",
    "sg:classifiers":[
        {
            "category":"Place Of Worship",
            "type":"Public Place"
        }
    ],
    "sg:phone":"+44 20 7405 1061",
    "sg:postcode":"EC1N 6RY",
    "sg:province":"Greater London",
    "wof:name":"St.Ethelredas R C Church",
    "wof:placetype":"venue"
},
  "geometry": {"coordinates":[-0.107153,51.518822],"type":"Point"}
}