{
  "type": "Feature",
  "properties": {
    "iso:country":"GB",
    "sg:address":"Unit 1, Inkerman Road, Tow Law",
    "sg:city":"Bishop Auckland",
    "sg:classifiers":[
        {
            "category":"Building & Trades",
            "subcategory":"Landscaping Services",
            "type":"Services"
        }
    ],
    "sg:phone":"+44 1388 730257",
    "sg:postcode":"DL13 4QB",
    "sg:province":"Durham",
    "sg:tags":[
        "landscape",
        "contractor"
    ],
    "wof:name":"Batson Landscape & Arboricultural Services",
    "wof:placetype":"venue"
},
  "geometry": {"coordinates":[-1.8255690336,54.7538757324],"type":"Point"}
}