{
  "type": "Feature",
  "properties": {
    "addr:full":"979-981 Wimborne Rd, Moordown Bournemouth Dorset BH9 2BN",
    "addr:housenumber":"979-981",
    "addr:postcode":"bh9 2bn",
    "addr:street":"Wimborne Rd",
    "iso:country":"GB",
    "sg:address":"979-981 Wimborne Rd, Moordown",
    "sg:city":"Bournemouth",
    "sg:classifiers":[
        {
            "category":"Home & Garden",
            "subcategory":"Furniture",
            "type":"Retail Goods"
        }
    ],
    "sg:postcode":"BH9 2BN",
    "sg:province":"Dorset",
    "wof:name":"Moordown Suite Centre",
    "wof:placetype":"venue"
},
  "geometry": {"coordinates":[-1.874078989,50.7554092407],"type":"Point"}
}