{
  "type": "Feature",
  "properties": {
    "iso:country":"GB",
    "sg:address":"Old Hall, Orcop",
    "sg:city":"Hereford",
    "sg:classifiers":[
        {
            "category":"Farming",
            "subcategory":"Livestock Farm",
            "type":"Manufacturing & Wholesale Goods"
        }
    ],
    "sg:phone":"+44 1981 580371",
    "sg:postcode":"HR2 8ET",
    "sg:province":"Herefordshire",
    "sg:tags":[
        "others"
    ],
    "wof:name":"J Griffiths & Sons",
    "wof:placetype":"venue"
},
  "geometry": {"coordinates":[-2.766487,51.931873],"type":"Point"}
}