{
  "type": "Feature",
  "properties": {
    "addr:full":"14 Main Street, East Leake Loughborough Leicestershire LE12 6PG",
    "addr:housenumber":"14",
    "addr:postcode":"le12 6pg",
    "addr:street":"Main Street",
    "iso:country":"GB",
    "sg:address":"14 Main Street, East Leake",
    "sg:city":"Loughborough",
    "sg:classifiers":[
        {
            "category":"Bars & Pubs",
            "type":"Food & Drink"
        }
    ],
    "sg:postcode":"LE12 6PG",
    "sg:province":"Leicestershire",
    "sg:tags":[
        "pubs",
        "inn"
    ],
    "wof:name":"The Nags Head",
    "wof:placetype":"venue"
},
  "geometry": {"coordinates":[-1.146984,52.831718],"type":"Point"}
}