{
  "type": "Feature",
  "properties": {
    "addr:full":"Princes Street, Metheringham Lincoln Lincolnshire LN4 3BX",
    "addr:postcode":"ln4 3bx",
    "addr:street":"Princes Street",
    "iso:country":"GB",
    "sg:address":"Princes Street, Metheringham",
    "sg:city":"Lincoln",
    "sg:classifiers":[
        {
            "category":"Education",
            "subcategory":"School",
            "type":"Public Place"
        },
        {
            "category":"Government",
            "subcategory":"Office",
            "type":"Public Place"
        }
    ],
    "sg:phone":"+44 1526 320039",
    "sg:postcode":"LN4 3BX",
    "sg:province":"Lincolnshire",
    "sg:tags":[
        "local",
        "authority"
    ],
    "wof:name":"Metheringham County Primary School",
    "wof:placetype":"venue"
},
  "geometry": {"coordinates":[-0.4050700068,53.1418952942],"type":"Point"}
}