{
  "type": "Feature",
  "properties": {
    "addr:full":"6 High Street Stone Staffordshire ST15 8AW",
    "addr:housenumber":"6",
    "addr:postcode":"st15 8aw",
    "addr:street":"High Street",
    "iso:country":"GB",
    "sg:address":"6 High Street",
    "sg:city":"Stone",
    "sg:classifiers":[
        {
            "category":"Insurance",
            "subcategory":"Insurance Agent",
            "type":"Services"
        }
    ],
    "sg:phone":"+44 1785 817728",
    "sg:postcode":"ST15 8AW",
    "sg:province":"Staffordshire",
    "sg:tags":[
        "broker"
    ],
    "wof:name":"Argent Commerial Insurance",
    "wof:placetype":"venue"
},
  "geometry": {"coordinates":[-2.1458289623,52.9015579224],"type":"Point"}
}