{
  "type": "Feature",
  "properties": {
    "iso:country":"GB",
    "sg:address":"34 Leicester Road",
    "sg:city":"Blackpool",
    "sg:classifiers":[
        {
            "category":"Building & Trades",
            "subcategory":"Construction",
            "type":"Services"
        }
    ],
    "sg:phone":"+44 1253 622226",
    "sg:postcode":"FY1 4HL",
    "sg:province":"Lancashire",
    "sg:tags":[
        "builder"
    ],
    "wof:name":"Kean & Marsh",
    "wof:placetype":"venue"
},
  "geometry": {"coordinates":[-3.041541,53.816837],"type":"Point"}
}