{
  "type": "Feature",
  "properties": {
    "iso:country":"GB",
    "sg:address":"The Lookout, Langton Road, Kingston",
    "sg:city":"Wareham",
    "sg:classifiers":[
        {
            "category":"Autos & Motor Vehicles",
            "subcategory":"Boat Sales",
            "type":"Retail Goods"
        }
    ],
    "sg:postcode":"BH20 5LR",
    "sg:province":"Dorset",
    "sg:tags":[
        "repair",
        "builder"
    ],
    "wof:name":"Andrew Barker",
    "wof:placetype":"venue"
},
  "geometry": {"coordinates":[-2.0551099777,50.6134796143],"type":"Point"}
}