{
  "type": "Feature",
  "properties": {
    "iso:country":"GB",
    "sg:address":"30 Bedford St",
    "sg:city":"North Shields",
    "sg:classifiers":[
        {
            "category":"Retail",
            "subcategory":"Laundry & Dry Cleaning",
            "type":"Services"
        }
    ],
    "sg:phone":"+44 191 257 0718",
    "sg:postcode":"NE29 6QA",
    "sg:province":"Tyne and Wear",
    "sg:tags":[
        "alteration"
    ],
    "wof:name":"Harton Clean",
    "wof:placetype":"venue"
},
  "geometry": {"coordinates":[-1.4461810589,55.0083847046],"type":"Point"}
}