{
  "type": "Feature",
  "properties": {
    "iso:country":"GB",
    "sg:address":"Segensworth Road",
    "sg:city":"Fareham",
    "sg:classifiers":[
        {
            "category":"Professional",
            "subcategory":"Testing Lab",
            "type":"Services"
        },
        {
            "category":"Professional",
            "subcategory":"Art Services",
            "type":"Services"
        },
        {
            "category":"Home & Garden",
            "subcategory":"Household Appliances",
            "type":"Retail Goods"
        }
    ],
    "sg:phone":"+44 1329 443441",
    "sg:postcode":"PO15 5RH",
    "sg:province":"Hampshire",
    "sg:tags":[
        "inspection",
        "graphic",
        "electrical",
        "designer",
        "calibration"
    ],
    "wof:name":"Visual Media Services",
    "wof:placetype":"venue"
},
  "geometry": {"coordinates":[-1.2477190495,50.8644981384],"type":"Point"}
}