{
  "type": "Feature",
  "properties": {
    "addr:full":"Dunkirk Norwich Norfolk NR11 6SU",
    "addr:postcode":"nr11 6su",
    "addr:street":"Norwich",
    "iso:country":"GB",
    "sg:address":"Dunkirk",
    "sg:city":"Norwich",
    "sg:classifiers":[
        {
            "category":"Retail",
            "subcategory":"Auto Repair",
            "type":"Services"
        }
    ],
    "sg:phone":"+44 1263 733621",
    "sg:postcode":"NR11 6SU",
    "sg:province":"Norfolk",
    "sg:tags":[
        "body",
        "car"
    ],
    "wof:name":"Aylsham Accident Repair Centre",
    "wof:placetype":"venue"
},
  "geometry": {"coordinates":[1.2657200098,52.803352356],"type":"Point"}
}