{
  "type": "Feature",
  "properties": {
    "iso:country":"GB",
    "sg:address":"Delves Road, Heanor Gate Industrial Estate",
    "sg:city":"Heanor",
    "sg:classifiers":[
        {
            "category":"Wholesale",
            "subcategory":"Metals & Minerals",
            "type":"Manufacturing & Wholesale Goods"
        },
        {
            "category":"Home & Garden",
            "subcategory":"Carpets & Floor Coverings",
            "type":"Retail Goods"
        }
    ],
    "sg:phone":"+44 1773 763134",
    "sg:postcode":"DE75 7SJ",
    "sg:province":"Derbyshire",
    "sg:tags":[
        "rubber",
        "fabricator",
        "sheet",
        "plastic"
    ],
    "wof:name":"Four D Rubber (1998) Ltd.",
    "wof:placetype":"venue"
},
  "geometry": {"coordinates":[-1.360585,53.006794],"type":"Point"}
}