{
  "type": "Feature",
  "properties": {
    "iso:country":"GB",
    "sg:address":"Market Hall, Church Street, Eccles",
    "sg:city":"Manchester",
    "sg:classifiers":[
        {
            "category":"Home & Garden",
            "subcategory":"Carpets & Floor Coverings",
            "type":"Retail Goods"
        }
    ],
    "sg:phone":"+44 161 789 8004",
    "sg:postcode":"M30 0EW",
    "sg:province":"Greater Manchester",
    "sg:tags":[
        "carpets",
        "retailer",
        "rug",
        "matting"
    ],
    "wof:name":"Faredeal Carpets",
    "wof:placetype":"venue"
},
  "geometry": {"coordinates":[-2.344569,53.482979],"type":"Point"}
}