{
  "type": "Feature",
  "properties": {
    "iso:country":"GB",
    "sg:address":"Bassetts Farm, Lavenham Road, Acton",
    "sg:city":"Sudbury",
    "sg:classifiers":[
        {
            "category":"Farming",
            "subcategory":"Livestock Farm",
            "type":"Manufacturing & Wholesale Goods"
        }
    ],
    "sg:phone":"+44 1787 379685",
    "sg:postcode":"CO10 0BH",
    "sg:province":"Essex",
    "sg:tags":[
        "others"
    ],
    "wof:name":"E & N Shropshire & Co.",
    "wof:placetype":"venue"
},
  "geometry": {"coordinates":[0.7650979757,52.0690536499],"type":"Point"}
}