{
  "type": "Feature",
  "properties": {
    "iso:country":"GB",
    "sg:address":"Po Box 7634",
    "sg:city":"Mill Hill",
    "sg:classifiers":[
        {
            "category":"Shopping",
            "subcategory":"Clothing, Apparel, & Fashions",
            "type":"Retail Goods"
        }
    ],
    "sg:phone":"+44 20 8906 8421",
    "sg:postcode":"NW7 3WB",
    "sg:province":"Greater London",
    "sg:tags":[
        "maternity",
        "wear"
    ],
    "wof:name":"Fit For Two",
    "wof:placetype":"venue"
},
  "geometry": {"coordinates":[-0.255359,51.620831],"type":"Point"}
}