{
  "type": "Feature",
  "properties": {
    "iso:country":"GB",
    "sg:address":"P O Box 100",
    "sg:city":"Paignton",
    "sg:classifiers":[
        {
            "category":"Health Services",
            "subcategory":"Hospital",
            "type":"Services"
        }
    ],
    "sg:phone":"+44 1803 666999",
    "sg:postcode":"TQ3 1YE",
    "sg:province":"Devon",
    "sg:tags":[
        "ambulance"
    ],
    "wof:name":"Southern Ambulance Services",
    "wof:placetype":"venue"
},
  "geometry": {"coordinates":[-3.592729,50.456291],"type":"Point"}
}