{
  "type": "Feature",
  "properties": {
    "addr:full":"Bartley House, Main Road, East Boldre Brockenhurst Hampshire SO42 7WD",
    "addr:postcode":"so42 7wd",
    "addr:street":"Main Road East",
    "iso:country":"GB",
    "sg:address":"Bartley House, Main Road, East Boldre",
    "sg:city":"Brockenhurst",
    "sg:classifiers":[
        {
            "category":"Professional",
            "subcategory":"Management & Consulting",
            "type":"Services"
        }
    ],
    "sg:phone":"+44 1590 612855",
    "sg:postcode":"SO42 7WD",
    "sg:province":"Hampshire",
    "sg:tags":[
        "marketing",
        "consultant"
    ],
    "wof:name":"Jane Porter Direct",
    "wof:placetype":"venue"
},
  "geometry": {"coordinates":[-1.572004,50.818642],"type":"Point"}
}