{
  "type": "Feature",
  "properties": {
    "addr:full":"17 Parkside Crescent Exeter Devon EX1 3TW",
    "addr:housenumber":"17",
    "addr:postcode":"ex1 3tw",
    "addr:street":"Parkside Crescent",
    "iso:country":"GB",
    "sg:address":"17 Parkside Crescent",
    "sg:city":"Exeter",
    "sg:classifiers":[
        {
            "category":"Building & Trades",
            "subcategory":"Construction",
            "type":"Services"
        }
    ],
    "sg:phone":"+44 1392 466525",
    "sg:postcode":"EX1 3TW",
    "sg:province":"Devon",
    "sg:tags":[
        "roofing"
    ],
    "wof:name":"Astley Roofing",
    "wof:placetype":"venue"
},
  "geometry": {"coordinates":[-3.4622189999,50.7501068115],"type":"Point"}
}