{
  "type": "Feature",
  "properties": {
    "addr:full":"67 Tawel Fan, Nelson Treharris Caerphilly CF46 6EH",
    "addr:housenumber":"67",
    "addr:postcode":"cf46 6eh",
    "addr:street":"Tawel Fan",
    "iso:country":"GB",
    "sg:address":"67 Tawel Fan, Nelson",
    "sg:city":"Treharris",
    "sg:classifiers":[
        {
            "category":"Professional",
            "subcategory":"Printing & Photocopies",
            "type":"Services"
        }
    ],
    "sg:phone":"+44 1443 451895",
    "sg:postcode":"CF46 6EH",
    "sg:province":"Caerphilly",
    "sg:tags":[
        "printer"
    ],
    "wof:name":"Nelson Print",
    "wof:placetype":"venue"
},
  "geometry": {"coordinates":[-3.284114,51.652679],"type":"Point"}
}