{
  "type": "Feature",
  "properties": {
    "addr:full":"138 South Street Romford Essex RM1 1TE",
    "addr:housenumber":"138",
    "addr:postcode":"rm1 1te",
    "addr:street":"South Street",
    "iso:country":"GB",
    "sg:address":"138 South Street",
    "sg:city":"Romford",
    "sg:classifiers":[
        {
            "category":"Shopping",
            "subcategory":"News",
            "type":"Retail Goods"
        }
    ],
    "sg:phone":"+44 800 028 0402",
    "sg:postcode":"RM1 1TE",
    "sg:province":"Essex",
    "sg:tags":[
        "newsagent"
    ],
    "wof:name":"M A Office Supplies Ltd",
    "wof:placetype":"venue"
},
  "geometry": {"coordinates":[0.183347,51.574894],"type":"Point"}
}