{
  "type": "Feature",
  "properties": {
    "addr:full":"Martells Quarry, Slough Lane, Ardleigh Colchester Essex CO7 7RU",
    "addr:postcode":"co7 7ru",
    "addr:street":"Martells Quarry Slough Lane",
    "iso:country":"GB",
    "sg:address":"Martells Quarry, Slough Lane, Ardleigh",
    "sg:city":"Colchester",
    "sg:classifiers":[
        {
            "category":"Home & Garden",
            "subcategory":"Garden Supply",
            "type":"Retail Goods"
        }
    ],
    "sg:phone":"+44 1206 230310",
    "sg:postcode":"CO7 7RU",
    "sg:province":"Essex",
    "sg:tags":[
        "sand",
        "gravel"
    ],
    "wof:name":"Buckbricks Co. Ltd.",
    "wof:placetype":"venue"
},
  "geometry": {"coordinates":[0.9837970138,51.9258880615],"type":"Point"}
}