{
  "type": "Feature",
  "properties": {
    "addr:full":"22 Heyscroft Road Manchester Greater Manchester M20 4XL",
    "addr:housenumber":"22",
    "addr:postcode":"m20 4xl",
    "addr:street":"Heyscroft Road",
    "iso:country":"GB",
    "sg:address":"22 Heyscroft Road",
    "sg:city":"Manchester",
    "sg:classifiers":[
        {
            "category":"Home & Garden",
            "subcategory":"Home Furnishings",
            "type":"Retail Goods"
        }
    ],
    "sg:postcode":"M20 4XL",
    "sg:province":"Greater Manchester",
    "sg:tags":[
        "blind",
        "curtain",
        "fitting"
    ],
    "wof:name":"Busy Bee Curtain Care",
    "wof:placetype":"venue"
},
  "geometry": {"coordinates":[-2.2176959515,53.4282913208],"type":"Point"}
}