{
  "type": "Feature",
  "properties": {
    "iso:country":"GB",
    "sg:address":"Unit 3 Cliffe St",
    "sg:city":"Nelson",
    "sg:classifiers":[
        {
            "category":"Wholesale",
            "subcategory":"Scrap",
            "type":"Manufacturing & Wholesale Goods"
        },
        {
            "category":"Retail",
            "subcategory":"Auto Repair",
            "type":"Services"
        }
    ],
    "sg:postcode":"BB9 7QR",
    "sg:province":"Lancashire",
    "sg:tags":[
        "modification",
        "garage",
        "breaker",
        "dismantlers"
    ],
    "wof:name":"Talbot,Keith,",
    "wof:placetype":"venue"
},
  "geometry": {"coordinates":[-2.210254,53.84082],"type":"Point"}
}