{
  "type": "Feature",
  "properties": {
    "addr:full":"12 North Avenue, Burton-latimer Kettering Northamptonshire NN15 5PG",
    "addr:housenumber":"12",
    "addr:postcode":"nn15 5pg",
    "addr:street":"North Avenue Burton-Latimer",
    "iso:country":"GB",
    "sg:address":"12 North Avenue, Burton-latimer",
    "sg:city":"Kettering",
    "sg:classifiers":[
        {
            "category":"Professional",
            "subcategory":"Detective & Security Services",
            "type":"Services"
        }
    ],
    "sg:phone":"+44 1536 724354",
    "sg:postcode":"NN15 5PG",
    "sg:province":"Northamptonshire",
    "sg:tags":[
        "agency",
        "activity"
    ],
    "wof:name":"P J S Investigations",
    "wof:placetype":"venue"
},
  "geometry": {"coordinates":[-0.686792,52.367695],"type":"Point"}
}