{
  "type": "Feature",
  "properties": {
    "iso:country":"GB",
    "sg:address":"85 Sandown Rd",
    "sg:city":"Sandown",
    "sg:classifiers":[
        {
            "category":"Travel",
            "subcategory":"Hotels & Motels",
            "type":"Entertainment"
        }
    ],
    "sg:phone":"+44 1983 402834",
    "sg:postcode":"PO36 9LE",
    "sg:province":"Isle of Wight",
    "sg:tags":[
        "house",
        "guest"
    ],
    "wof:name":"Woodbury",
    "wof:placetype":"venue"
},
  "geometry": {"coordinates":[-1.168849,50.645447],"type":"Point"}
}