{
  "type": "Feature",
  "properties": {
    "addr:full":"Y-glyn Industrial Estate, Llanberis Caernarfon Gwynedd LL55 4EL",
    "addr:postcode":"ll55 4el",
    "addr:street":"Estate Llanberis",
    "iso:country":"GB",
    "sg:address":"Y-glyn Industrial Estate, Llanberis",
    "sg:city":"Caernarfon",
    "sg:classifiers":[
        {
            "category":"Bus Charters",
            "type":"Transportation"
        }
    ],
    "sg:phone":"+44 1286 870880",
    "sg:postcode":"LL55 4EL",
    "sg:province":"Gwynedd",
    "sg:tags":[
        "hire",
        "coach"
    ],
    "wof:name":"K M P Coaches",
    "wof:placetype":"venue"
},
  "geometry": {"coordinates":[-4.1301832199,53.1235809326],"type":"Point"}
}