{
  "type": "Feature",
  "properties": {
    "iso:country":"GB",
    "sg:address":"James Watt Building, James Watt Avenue, East Kilbride",
    "sg:city":"Glasgow",
    "sg:classifiers":[
        {
            "category":"Utilities",
            "subcategory":"Refuse",
            "type":"Services"
        }
    ],
    "sg:phone":"+44 1355 272244",
    "sg:postcode":"G75 0QD",
    "sg:province":"South Lanarkshire",
    "sg:tags":[
        "disposal",
        "waste"
    ],
    "wof:name":"Alco Waste Management Ltd.",
    "wof:placetype":"venue"
},
  "geometry": {"coordinates":[-4.16754,55.756149],"type":"Point"}
}