{
  "type": "Feature",
  "properties": {
    "addr:full":"Bourne House, Horsell Park Woking Surrey GU21 4LY",
    "addr:postcode":"gu21 4ly",
    "addr:street":"Horsell Park",
    "iso:country":"GB",
    "sg:address":"Bourne House, Horsell Park",
    "sg:city":"Woking",
    "sg:classifiers":[
        {
            "category":"Utilities",
            "subcategory":"Refuse",
            "type":"Services"
        }
    ],
    "sg:phone":"+44 1483 750991",
    "sg:postcode":"GU21 4LY",
    "sg:province":"Surrey",
    "sg:tags":[
        "catering"
    ],
    "wof:name":"A V L Consultancy Ltd.",
    "wof:placetype":"venue"
},
  "geometry": {"coordinates":[-0.5642139912,51.3236198425],"type":"Point"}
}