{
  "type": "Feature",
  "properties": {
    "addr:full":"199 East Bawtry Rd Rotherham South Yorkshire S60 4LH",
    "addr:housenumber":"199",
    "addr:postcode":"s60 4lh",
    "addr:street":"East Bawtry Rd",
    "iso:country":"GB",
    "sg:address":"199 East Bawtry Rd",
    "sg:city":"Rotherham",
    "sg:classifiers":[
        {
            "category":"Personal",
            "type":"Services"
        }
    ],
    "sg:phone":"+44 1709 541449",
    "sg:postcode":"S60 4LH",
    "sg:province":"South Yorkshire",
    "sg:tags":[
        "delivery"
    ],
    "wof:name":"LK Carriers",
    "wof:placetype":"venue"
},
  "geometry": {"coordinates":[-1.318051,53.415012],"type":"Point"}
}