{
  "type": "Feature",
  "properties": {
    "addr:full":"241 Holton Road Barry The Vale of Glamorgan CF63 4HT",
    "addr:housenumber":"241",
    "addr:postcode":"cf63 4ht",
    "addr:street":"Holton Road;Vale",
    "iso:country":"GB",
    "sg:address":"241 Holton Road",
    "sg:city":"Barry",
    "sg:classifiers":[
        {
            "category":"Personal",
            "subcategory":"Beauty Salon",
            "type":"Services"
        },
        {
            "category":"Personal",
            "subcategory":"Barber",
            "type":"Services"
        }
    ],
    "sg:postcode":"CF63 4HT",
    "sg:province":"The Vale of Glamorgan",
    "sg:tags":[
        "men's",
        "lady",
        "hairdresser"
    ],
    "wof:name":"Andreas Asprou Gents Hairstylists",
    "wof:placetype":"venue"
},
  "geometry": {"coordinates":[-3.2598729134,51.4076805115],"type":"Point"}
}