{
  "type": "Feature",
  "properties": {
    "iso:country":"GB",
    "sg:address":"85 Perth Road",
    "sg:city":"Dundee",
    "sg:classifiers":[
        {
            "category":"Food & Beverages",
            "subcategory":"Liquor & Beverages",
            "type":"Retail Goods"
        }
    ],
    "sg:phone":"+44 1382 200807",
    "sg:postcode":"DD1 4HZ",
    "sg:province":"Dundee City",
    "sg:tags":[
        "beer",
        "spirit",
        "wines"
    ],
    "wof:name":"Victoria Wine",
    "wof:placetype":"venue"
},
  "geometry": {"coordinates":[-2.9886300564,56.4561805725],"type":"Point"}
}