{
  "type": "Feature",
  "properties": {
    "addr:full":"10 Magpie Close Basingstoke Hampshire RG22 5QG",
    "addr:housenumber":"10",
    "addr:postcode":"rg22 5qg",
    "addr:street":"Magpie Close",
    "iso:country":"GB",
    "sg:address":"10 Magpie Close",
    "sg:city":"Basingstoke",
    "sg:classifiers":[
        {
            "category":"Professional",
            "subcategory":"Art Services",
            "type":"Services"
        },
        {
            "category":"Building & Trades",
            "subcategory":"Construction",
            "type":"Services"
        }
    ],
    "sg:phone":"+44 1256 476648",
    "sg:postcode":"RG22 5QG",
    "sg:province":"Hampshire",
    "sg:tags":[
        "decorator",
        "painter"
    ],
    "wof:name":"K Wright",
    "wof:placetype":"venue"
},
  "geometry": {"coordinates":[-1.144525,51.243832],"type":"Point"}
}