{
  "type": "Feature",
  "properties": {
    "addr:full":"Dering Place Croydon Surrey CR0 1DT",
    "addr:postcode":"cr0 1dt",
    "addr:street":"Dering Place",
    "iso:country":"GB",
    "sg:address":"Dering Place",
    "sg:city":"Croydon",
    "sg:classifiers":[
        {
            "category":"Education",
            "subcategory":"School",
            "type":"Public Place"
        }
    ],
    "sg:phone":"+44 20 8688 4216",
    "sg:postcode":"CR0 1DT",
    "sg:province":"Surrey",
    "sg:tags":[
        "local",
        "authority"
    ],
    "wof:name":"Howard Primary School",
    "wof:placetype":"venue"
},
  "geometry": {"coordinates":[-0.1012839973,51.3648605347],"type":"Point"}
}