{
  "type": "Feature",
  "properties": {
    "addr:full":"8 Wellington Place, Barrack Road Northampton Northamptonshire NN1 3RQ",
    "addr:housenumber":"8",
    "addr:postcode":"nn1 3rq",
    "addr:street":"Wellington Place Barrack Road",
    "iso:country":"GB",
    "sg:address":"8 Wellington Place, Barrack Road",
    "sg:city":"Northampton",
    "sg:classifiers":[
        {
            "category":"Shopping",
            "subcategory":"Used Merchandise",
            "type":"Retail Goods"
        }
    ],
    "sg:postcode":"NN1 3RQ",
    "sg:province":"Northamptonshire",
    "sg:tags":[
        "shop",
        "second-hand"
    ],
    "wof:name":"Secondhand Goods",
    "wof:placetype":"venue"
},
  "geometry": {"coordinates":[-0.892372,52.24057],"type":"Point"}
}