{
  "type": "Feature",
  "properties": {
    "addr:full":"33 Sandy Lane Shanklin Isle of Wight PO37 7DT",
    "addr:housenumber":"33",
    "addr:postcode":"po37 7dt",
    "addr:street":"Sandy Lane",
    "iso:country":"GB",
    "sg:address":"33 Sandy Lane",
    "sg:city":"Shanklin",
    "sg:classifiers":[
        {
            "category":"Home & Garden",
            "subcategory":"Building Materials",
            "type":"Retail Goods"
        }
    ],
    "sg:phone":"+44 1983 867337",
    "sg:postcode":"PO37 7DT",
    "sg:province":"Isle of Wight",
    "sg:tags":[
        "garage",
        "door"
    ],
    "wof:name":"Lakeside Security Shutters",
    "wof:placetype":"venue"
},
  "geometry": {"coordinates":[-1.180179,50.639835],"type":"Point"}
}