{
  "type": "Feature",
  "properties": {
    "addr:full":"Asgeda House, 8 Old London Road St Albans Hertfordshire AL1 1QQ",
    "addr:housenumber":"8",
    "addr:postcode":"al1 1qq",
    "addr:street":"Old London Road",
    "iso:country":"GB",
    "sg:address":"Asgeda House, 8 Old London Road",
    "sg:city":"St Albans",
    "sg:classifiers":[
        {
            "category":"Building & Trades",
            "subcategory":"Construction",
            "type":"Services"
        }
    ],
    "sg:phone":"+44 1727 839626",
    "sg:postcode":"AL1 1QQ",
    "sg:province":"Hertfordshire",
    "sg:tags":[
        "builder"
    ],
    "wof:name":"A P Wright",
    "wof:placetype":"venue"
},
  "geometry": {"coordinates":[-0.3358489871,51.7477493286],"type":"Point"}
}