{
  "type": "Feature",
  "properties": {
    "addr:full":"64 Old Compton Street London Greater London W1D 4UQ",
    "addr:housenumber":"64",
    "addr:postcode":"w1d 4uq",
    "addr:street":"Old Compton Street",
    "iso:country":"GB",
    "sg:address":"64 Old Compton Street",
    "sg:city":"London",
    "sg:classifiers":[
        {
            "category":"Shopping",
            "subcategory":"Clothing, Apparel, & Fashions",
            "type":"Retail Goods"
        }
    ],
    "sg:phone":"+44 20 7287 3530",
    "sg:postcode":"W1D 4UQ",
    "sg:province":"Greater London",
    "sg:tags":[
        "menswear"
    ],
    "wof:name":"Clone Zone",
    "wof:placetype":"venue"
},
  "geometry": {"coordinates":[-0.1327069998,51.5127792358],"type":"Point"}
}