{
  "type": "Feature",
  "properties": {
    "iso:country":"GB",
    "sg:address":"5 Grays Av",
    "sg:city":"Bridgwater",
    "sg:classifiers":[
        {
            "category":"Personal",
            "type":"Services"
        }
    ],
    "sg:phone":"+44 1278 691903",
    "sg:postcode":"TA7 0HP",
    "sg:province":"Somerset",
    "sg:tags":[
        "wedding"
    ],
    "wof:name":"Sitting Pretty Wedding Car Hire",
    "wof:placetype":"venue"
},
  "geometry": {"coordinates":[-2.93261,51.11134],"type":"Point"}
}