{
  "type": "Feature",
  "properties": {
    "iso:country":"GB",
    "sg:address":"Southmoor Road, Wythenshawe",
    "sg:city":"Manchester",
    "sg:classifiers":[
        {
            "category":"Home & Garden",
            "subcategory":"Furniture",
            "type":"Retail Goods"
        }
    ],
    "sg:phone":"+44 161 902 0441",
    "sg:postcode":"M23 9DS",
    "sg:province":"Cheshire",
    "wof:name":"Habitat",
    "wof:placetype":"venue"
},
  "geometry": {"coordinates":[-2.294809,53.401005],"type":"Point"}
}