{
  "type": "Feature",
  "properties": {
    "addr:full":"William Street, Little Lever Bolton Lancashire BL3 1AR",
    "addr:postcode":"bl3 1ar",
    "addr:street":"William Street",
    "iso:country":"GB",
    "sg:address":"William Street, Little Lever",
    "sg:city":"Bolton",
    "sg:classifiers":[
        {
            "category":"Building & Trades",
            "subcategory":"Construction",
            "type":"Services"
        }
    ],
    "sg:phone":"+44 1204 796176",
    "sg:postcode":"BL3 1AR",
    "sg:province":"Lancashire",
    "sg:tags":[
        "tiling",
        "contractor"
    ],
    "wof:name":"Pts North West",
    "wof:placetype":"venue"
},
  "geometry": {"coordinates":[-2.365183,53.561253],"type":"Point"}
}