{
  "type": "Feature",
  "properties": {
    "iso:country":"GB",
    "sg:address":"114a Brixton Hill",
    "sg:city":"London",
    "sg:classifiers":[
        {
            "category":"Retail",
            "subcategory":"Laundry & Dry Cleaning",
            "type":"Services"
        }
    ],
    "sg:phone":"+44 20 8674 4873",
    "sg:postcode":"SW2 1RS",
    "sg:province":"Greater London",
    "sg:tags":[
        "alteration"
    ],
    "wof:name":"Poleo Cleaners",
    "wof:placetype":"venue"
},
  "geometry": {"coordinates":[-0.118671,51.456715],"type":"Point"}
}