{
  "type": "Feature",
  "properties": {
    "addr:full":"Watts Farm, Tickners Heath, Alfold Cranleigh Surrey GU6 8HU",
    "addr:postcode":"gu6 8hu",
    "addr:street":"Heath",
    "iso:country":"GB",
    "sg:address":"Watts Farm, Tickners Heath, Alfold",
    "sg:city":"Cranleigh",
    "sg:classifiers":[
        {
            "category":"Banks & Credit Unions",
            "subcategory":"Investment Brokerage",
            "type":"Services"
        }
    ],
    "sg:postcode":"GU6 8HU",
    "sg:province":"Surrey",
    "sg:tags":[
        "contractor"
    ],
    "wof:name":"Hill,Peter,",
    "wof:placetype":"venue"
},
  "geometry": {"coordinates":[-0.5179370046,51.0959701538],"type":"Point"}
}