{
  "type": "Feature",
  "properties": {
    "addr:full":"5 Firs Entry Stirling Falkirk FK7 0HW",
    "addr:housenumber":"5",
    "addr:postcode":"fk7 0hw",
    "addr:street":"Firs Entry",
    "iso:country":"GB",
    "sg:address":"5 Firs Entry",
    "sg:city":"Stirling",
    "sg:classifiers":[
        {
            "category":"Food & Beverages",
            "subcategory":"Supermarket",
            "type":"Retail Goods"
        },
        {
            "category":"Food & Beverages",
            "subcategory":"Groceries & Convenience Stores",
            "type":"Retail Goods"
        }
    ],
    "sg:postcode":"FK7 0HW",
    "sg:province":"Falkirk",
    "wof:name":"Spar Store",
    "wof:placetype":"venue"
},
  "geometry": {"coordinates":[-3.922196,56.093708],"type":"Point"}
}