{
  "type": "Feature",
  "properties": {
    "addr:full":"19 Robin Hill Drive Camberley Berkshire GU15 1EG",
    "addr:housenumber":"19",
    "addr:postcode":"gu15 1eg",
    "addr:street":"Robin Hill Drive",
    "iso:country":"GB",
    "sg:address":"19 Robin Hill Drive",
    "sg:city":"Camberley",
    "sg:classifiers":[
        {
            "category":"Shopping",
            "subcategory":"Computers & Home Electronics",
            "type":"Retail Goods"
        }
    ],
    "sg:phone":"+44 1276 64454",
    "sg:postcode":"GU15 1EG",
    "sg:province":"Berkshire",
    "sg:tags":[
        "consumables"
    ],
    "wof:name":"Southern Computer Supplies",
    "wof:placetype":"venue"
},
  "geometry": {"coordinates":[-0.720242,51.327003],"type":"Point"}
}