{
  "type": "Feature",
  "properties": {
    "addr:full":"21-49 Ballards Lane, Finchley London Greater London N3 1XP",
    "addr:housenumber":"21-49",
    "addr:postcode":"n3 1xp",
    "addr:street":"Ballards Lane",
    "iso:country":"GB",
    "sg:address":"21-49 Ballards Lane, Finchley",
    "sg:city":"London",
    "sg:classifiers":[
        {
            "category":"Food & Beverages",
            "subcategory":"Supermarket",
            "type":"Retail Goods"
        }
    ],
    "sg:phone":"+44 20 8349 9387",
    "sg:postcode":"N3 1XP",
    "sg:province":"Greater London",
    "wof:name":"Tesco Stores Ltd.",
    "wof:placetype":"venue"
},
  "geometry": {"coordinates":[-0.1910299957,51.6033401489],"type":"Point"}
}