{
  "type": "Feature",
  "properties": {
    "iso:country":"GB",
    "sg:address":"175 High Street",
    "sg:city":"Banstead",
    "sg:classifiers":[
        {
            "category":"Animal Shelter",
            "type":"Public Place"
        }
    ],
    "sg:postcode":"SM7 2NT",
    "sg:province":"Surrey",
    "sg:tags":[
        "racking",
        "shelving"
    ],
    "wof:name":"Spacelink Commercial Interiors Ltd.",
    "wof:placetype":"venue"
},
  "geometry": {"coordinates":[-0.196362,51.324299],"type":"Point"}
}