{
  "type": "Feature",
  "properties": {
    "iso:country":"GB",
    "sg:address":"97 Hurst Green Road",
    "sg:city":"Oxted",
    "sg:classifiers":[
        {
            "category":"Shopping",
            "subcategory":"Department Store",
            "type":"Retail Goods"
        }
    ],
    "sg:phone":"+44 1883 713895",
    "sg:postcode":"RH8 9AP",
    "sg:province":"Surrey",
    "wof:name":"F Hobbs & Son Ltd.",
    "wof:placetype":"venue"
},
  "geometry": {"coordinates":[0.006699,51.240734],"type":"Point"}
}