{
  "type": "Feature",
  "properties": {
    "addr:full":"16 Beckenham Road Beckenham Kent BR3 4LS",
    "addr:housenumber":"16",
    "addr:postcode":"br3 4ls",
    "addr:street":"Beckenham Road",
    "iso:country":"GB",
    "sg:address":"16 Beckenham Road",
    "sg:city":"Beckenham",
    "sg:classifiers":[
        {
            "category":"Health Services",
            "subcategory":"Health Practitioner",
            "type":"Services"
        }
    ],
    "sg:phone":"+44 20 8650 4313",
    "sg:postcode":"BR3 4LS",
    "sg:province":"Kent",
    "sg:tags":[
        "osteopath"
    ],
    "wof:name":"Alain F Lebret",
    "wof:placetype":"venue"
},
  "geometry": {"coordinates":[-0.03592,51.408108],"type":"Point"}
}