{
  "type": "Feature",
  "properties": {
    "addr:full":"31 Station Road, Market Bosworth Nuneaton Leicestershire CV13 0JS",
    "addr:housenumber":"31",
    "addr:postcode":"cv13 0js",
    "addr:street":"Station Road",
    "iso:country":"GB",
    "sg:address":"31 Station Road, Market Bosworth",
    "sg:city":"Nuneaton",
    "sg:classifiers":[
        {
            "category":"Fast Food",
            "type":"Food & Drink"
        }
    ],
    "sg:phone":"+44 1455 292828",
    "sg:postcode":"CV13 0JS",
    "sg:province":"Leicestershire",
    "sg:tags":[
        "away",
        "meal",
        "outlet",
        "take"
    ],
    "wof:name":"TIN TIN CHINESE TAKEAWAY",
    "wof:placetype":"venue"
},
  "geometry": {"coordinates":[-1.4034620523,52.6237945557],"type":"Point"}
}