{
  "type": "Feature",
  "properties": {
    "addr:full":"Cheetham Mill, Cheetham Works, Park Street Stalybridge Greater Manchester SK15 2BT",
    "addr:postcode":"sk15 2bt",
    "addr:street":"Cheetham;Park Street",
    "iso:country":"GB",
    "sg:address":"Cheetham Mill, Cheetham Works, Park Street",
    "sg:city":"Stalybridge",
    "sg:classifiers":[
        {
            "category":"Building & Trades",
            "subcategory":"Landscaping Services",
            "type":"Services"
        }
    ],
    "sg:phone":"+44 161 338 7356",
    "sg:postcode":"SK15 2BT",
    "sg:province":"Greater Manchester",
    "sg:tags":[
        "horticultural",
        "consultant"
    ],
    "wof:name":"Woodbank Plastics Machinery Ltd.",
    "wof:placetype":"venue"
},
  "geometry": {"coordinates":[-2.057569,53.483543],"type":"Point"}
}