{
  "type": "Feature",
  "properties": {
    "addr:full":"Hoscar Hall Farm, Hoscar Moss Rd, Lathom Ormskirk Lancashire L40 4BG",
    "addr:postcode":"l40 4bg",
    "addr:street":"Hoscar Moss Rd",
    "iso:country":"GB",
    "sg:address":"Hoscar Hall Farm, Hoscar Moss Rd, Lathom",
    "sg:city":"Ormskirk",
    "sg:classifiers":[
        {
            "category":"Education",
            "subcategory":"Music School",
            "type":"Public Place"
        }
    ],
    "sg:postcode":"L40 4BG",
    "sg:province":"Lancashire",
    "sg:tags":[
        "conservatory"
    ],
    "wof:name":"Abbey Windows",
    "wof:placetype":"venue"
},
  "geometry": {"coordinates":[-2.80666,53.597439],"type":"Point"}
}