{
  "type": "Feature",
  "properties": {
    "addr:full":"7 Minster Court, Tustam Way, Yorktown Industrial Estate Camberley Berkshire GU15 3YY",
    "addr:housenumber":"7",
    "addr:postcode":"gu15 3yy",
    "addr:street":"Minster Court Tustam Way;Industrial Estate",
    "iso:country":"GB",
    "sg:address":"7 Minster Court, Tustam Way, Yorktown Industrial Estate",
    "sg:city":"Camberley",
    "sg:classifiers":[
        {
            "category":"Professional",
            "subcategory":"Engineering",
            "type":"Services"
        }
    ],
    "sg:phone":"+44 1276 683355",
    "sg:postcode":"GU15 3YY",
    "sg:province":"Berkshire",
    "sg:tags":[
        "contractor",
        "electrical",
        "engineer"
    ],
    "wof:name":"Fairways Engineering (Electrical) Ltd.",
    "wof:placetype":"venue"
},
  "geometry": {"coordinates":[-0.73423,51.336216],"type":"Point"}
}