{
  "type": "Feature",
  "properties": {
    "iso:country":"GB",
    "sg:address":"Brumby Wood Lane",
    "sg:city":"Scunthorpe",
    "sg:classifiers":[
        {
            "category":"Autos & Motor Vehicles",
            "subcategory":"Auto Supplies",
            "type":"Retail Goods"
        }
    ],
    "sg:phone":"+44 1724 289666",
    "sg:postcode":"DN17 1AA",
    "sg:province":"Lincolnshire",
    "sg:tags":[
        "exhaust",
        "absorber",
        "shock"
    ],
    "wof:name":"Kwik-Fit",
    "wof:placetype":"venue"
},
  "geometry": {"coordinates":[-0.657087,53.584499],"type":"Point"}
}