{
  "type": "Feature",
  "properties": {
    "addr:full":"Second Ave, Eastchurch Sheerness Kent ME12 4EP",
    "addr:postcode":"me12 4ep",
    "addr:street":"Second Ave",
    "iso:country":"GB",
    "sg:address":"Second Ave, Eastchurch",
    "sg:city":"Sheerness",
    "sg:classifiers":[
        {
            "category":"Recreation",
            "subcategory":"Campground",
            "type":"Entertainment"
        }
    ],
    "sg:phone":"+44 1795 880338",
    "sg:postcode":"ME12 4EP",
    "sg:province":"Kent",
    "sg:tags":[
        "holiday",
        "centre",
        "camp"
    ],
    "wof:name":"Bramley Park",
    "wof:placetype":"venue"
},
  "geometry": {"coordinates":[0.8604419827,51.4039115906],"type":"Point"}
}