{
  "type": "Feature",
  "properties": {
    "iso:country":"GB",
    "sg:address":"Unit 13a Lowesmoor Trading Estate",
    "sg:city":"Worcester",
    "sg:classifiers":[
        {
            "category":"Retail",
            "subcategory":"Auto Repair",
            "type":"Services"
        }
    ],
    "sg:phone":"+44 1905 22879",
    "sg:postcode":"WR1 2SF",
    "sg:province":"Worcestershire",
    "sg:tags":[
        "modification",
        "garage"
    ],
    "wof:name":"John Austin",
    "wof:placetype":"venue"
},
  "geometry": {"coordinates":[-2.217237,52.194656],"type":"Point"}
}