{
  "type": "Feature",
  "properties": {
    "iso:country":"GB",
    "sg:address":"Station Lane, Millbrook",
    "sg:city":"Bedford",
    "sg:classifiers":[
        {
            "category":"Professional",
            "subcategory":"Testing Lab",
            "type":"Services"
        }
    ],
    "sg:phone":"+44 1525 404242",
    "sg:postcode":"MK45 2JQ",
    "sg:province":"Bedfordshire",
    "sg:tags":[
        "inspection",
        "calibration"
    ],
    "wof:name":"Millbrook Proving Ground Ltd.",
    "wof:placetype":"venue"
},
  "geometry": {"coordinates":[-0.5241190195,52.0389900208],"type":"Point"}
}