{
  "type": "Feature",
  "properties": {
    "addr:full":"Wernfach, Llanigon Hereford Herefordshire HR3 5QL",
    "addr:postcode":"hr3 5ql",
    "iso:country":"GB",
    "sg:address":"Wernfach, Llanigon",
    "sg:city":"Hereford",
    "sg:classifiers":[
        {
            "category":"Banks & Credit Unions",
            "subcategory":"Investment Brokerage",
            "type":"Services"
        },
        {
            "category":"Farming",
            "subcategory":"Farm & Veterinary Services",
            "type":"Manufacturing & Wholesale Goods"
        }
    ],
    "sg:phone":"+44 1497 847492",
    "sg:postcode":"HR3 5QL",
    "sg:province":"Herefordshire",
    "sg:tags":[
        "agricultural",
        "contractor"
    ],
    "wof:name":"H M & M S Davies",
    "wof:placetype":"venue"
},
  "geometry": {"coordinates":[-3.151348,52.054707],"type":"Point"}
}