{
  "type": "Feature",
  "properties": {
    "iso:country":"GB",
    "sg:address":"8 Barnsley Road",
    "sg:city":"Rotherham",
    "sg:classifiers":[
        {
            "category":"Autos & Motor Vehicles",
            "subcategory":"Auto Supplies",
            "type":"Retail Goods"
        }
    ],
    "sg:phone":"+44 1709 878316",
    "sg:postcode":"S63 6PY",
    "sg:province":"South Yorkshire",
    "sg:tags":[
        "car",
        "audio"
    ],
    "wof:name":"E R S",
    "wof:placetype":"venue"
},
  "geometry": {"coordinates":[-1.353549,53.504349],"type":"Point"}
}