{
  "type": "Feature",
  "properties": {
    "addr:full":"41 Broomhill Dr Glasgow Glasgow City G11 7AD",
    "addr:housenumber":"41",
    "addr:postcode":"g11 7ad",
    "addr:street":"Broomhill Dr",
    "iso:country":"GB",
    "sg:address":"41 Broomhill Dr",
    "sg:city":"Glasgow",
    "sg:classifiers":[
        {
            "category":"Health Services",
            "subcategory":"Doctor",
            "type":"Services"
        }
    ],
    "sg:phone":"+44 141 339 3626",
    "sg:postcode":"G11 7AD",
    "sg:province":"Glasgow City",
    "sg:tags":[
        "practitioners"
    ],
    "wof:name":"Marshall, A J",
    "wof:placetype":"venue"
},
  "geometry": {"coordinates":[-4.323532,55.872692],"type":"Point"}
}