{
  "type": "Feature",
  "properties": {
    "addr:full":"3 Elan Road South Ockendon Essex RM15 5EG",
    "addr:housenumber":"3",
    "addr:postcode":"rm15 5eg",
    "addr:street":"Elan Road",
    "iso:country":"GB",
    "sg:address":"3 Elan Road",
    "sg:city":"South Ockendon",
    "sg:classifiers":[
        {
            "category":"Shopping",
            "subcategory":"Computers & Home Electronics",
            "type":"Retail Goods"
        }
    ],
    "sg:phone":"+44 1708 856610",
    "sg:postcode":"RM15 5EG",
    "sg:province":"Essex",
    "sg:tags":[
        "aerial",
        "television",
        "radio"
    ],
    "wof:name":"Clearview Aerial Installations",
    "wof:placetype":"venue"
},
  "geometry": {"coordinates":[0.282251,51.511433],"type":"Point"}
}