{
  "type": "Feature",
  "properties": {
    "addr:full":"85 Stonesby Avenue Leicester Leicestershire LE2 6TY",
    "addr:housenumber":"85",
    "addr:postcode":"le2 6ty",
    "addr:street":"Stonesby Avenue",
    "iso:country":"GB",
    "sg:address":"85 Stonesby Avenue",
    "sg:city":"Leicester",
    "sg:classifiers":[
        {
            "category":"Food & Beverages",
            "subcategory":"Fruits & Vegetables",
            "type":"Retail Goods"
        },
        {
            "category":"Food & Beverages",
            "subcategory":"Groceries & Convenience Stores",
            "type":"Retail Goods"
        }
    ],
    "sg:phone":"+44 116 283 1213",
    "sg:postcode":"LE2 6TY",
    "sg:province":"Leicestershire",
    "sg:tags":[
        "greengrocer"
    ],
    "wof:name":"J & D MINI MARKET",
    "wof:placetype":"venue"
},
  "geometry": {"coordinates":[-1.1361219883,52.5949401855],"type":"Point"}
}