{
  "type": "Feature",
  "properties": {
    "iso:country":"GB",
    "sg:address":"Westfield, Commercial Road, Oldmeldrum",
    "sg:city":"Inverurie",
    "sg:classifiers":[
        {
            "category":"Building & Trades",
            "subcategory":"Construction",
            "type":"Services"
        }
    ],
    "sg:postcode":"AB51 0DT",
    "sg:province":"Aberdeenshire",
    "sg:tags":[
        "builder"
    ],
    "wof:name":"Alexander Duguid & Son",
    "wof:placetype":"venue"
},
  "geometry": {"coordinates":[-2.324019,57.334717],"type":"Point"}
}