{
  "type": "Feature",
  "properties": {
    "iso:country":"GB",
    "sg:address":"Unit 1, 41a St. Johns",
    "sg:city":"Worcester",
    "sg:classifiers":[
        {
            "category":"Shopping",
            "subcategory":"Computers & Home Electronics",
            "type":"Retail Goods"
        }
    ],
    "sg:phone":"+44 1905 421221",
    "sg:postcode":"WR2 5AG",
    "sg:province":"Worcestershire",
    "sg:tags":[
        "aerial",
        "television",
        "radio"
    ],
    "wof:name":"1st Call Aerial Specialists",
    "wof:placetype":"venue"
},
  "geometry": {"coordinates":[-2.234703,52.187805],"type":"Point"}
}