{
  "type": "Feature",
  "properties": {
    "addr:full":"1 Cavendish Rd Chingford Greater London E4 9NQ",
    "addr:housenumber":"1",
    "addr:postcode":"e4 9nq",
    "addr:street":"Cavendish Rd",
    "iso:country":"GB",
    "sg:address":"1 Cavendish Rd",
    "sg:city":"Chingford",
    "sg:classifiers":[
        {
            "category":"Health Services",
            "subcategory":"Doctor",
            "type":"Services"
        }
    ],
    "sg:phone":"+44 20 8523 1401",
    "sg:postcode":"E4 9NQ",
    "sg:province":"Greater London",
    "sg:tags":[
        "practitioners"
    ],
    "wof:name":"Parkhurst Surgery",
    "wof:placetype":"venue"
},
  "geometry": {"coordinates":[-0.00181,51.606369],"type":"Point"}
}