{
  "type": "Feature",
  "properties": {
    "addr:full":"Milson Road Health Centre, 1-13 Milson Rd West Kensington Greater London W14 0LJ",
    "addr:housenumber":"1-13",
    "addr:postcode":"w14 0lj",
    "addr:street":"Milson;Milson Rd",
    "iso:country":"GB",
    "sg:address":"Milson Road Health Centre, 1-13 Milson Rd",
    "sg:city":"West Kensington",
    "sg:classifiers":[
        {
            "category":"Health Services",
            "subcategory":"Doctor",
            "type":"Services"
        }
    ],
    "sg:phone":"+44 181 846 6262",
    "sg:postcode":"W14 0LJ",
    "sg:province":"Greater London",
    "sg:tags":[
        "practitioners"
    ],
    "wof:name":"Soni, B",
    "wof:placetype":"venue"
},
  "geometry": {"coordinates":[-0.21626,51.499821],"type":"Point"}
}