{
  "type": "Feature",
  "properties": {
    "addr:full":"37 Eileen Road Birmingham West Midlands B11 4HX",
    "addr:housenumber":"37",
    "addr:postcode":"b11 4hx",
    "addr:street":"Eileen Road",
    "iso:country":"GB",
    "sg:address":"37 Eileen Road",
    "sg:city":"Birmingham",
    "sg:classifiers":[
        {
            "category":"Home & Garden",
            "subcategory":"Home Furnishings",
            "type":"Retail Goods"
        }
    ],
    "sg:phone":"+44 121 449 3918",
    "sg:postcode":"B11 4HX",
    "sg:province":"West Midlands",
    "sg:tags":[
        "blind",
        "manufacture",
        "fitting",
        "curtain"
    ],
    "wof:name":"Cloth in Home",
    "wof:placetype":"venue"
},
  "geometry": {"coordinates":[-1.867699,52.445782],"type":"Point"}
}