{
  "type": "Feature",
  "properties": {
    "addr:full":"143b High Street Northallerton North Yorkshire DL7 8PE",
    "addr:housenumber":"143b",
    "addr:postcode":"dl7 8pe",
    "addr:street":"High Street",
    "iso:country":"GB",
    "sg:address":"143b High Street",
    "sg:city":"Northallerton",
    "sg:classifiers":[
        {
            "category":"Shopping",
            "subcategory":"Stationery & Office Supplies",
            "type":"Retail Goods"
        }
    ],
    "sg:phone":"+44 1609 773422",
    "sg:postcode":"DL7 8PE",
    "sg:province":"North Yorkshire",
    "sg:tags":[
        "equipment"
    ],
    "wof:name":"E C Jarred (Northallerton) Ltd.",
    "wof:placetype":"venue"
},
  "geometry": {"coordinates":[-1.433611,54.336777],"type":"Point"}
}