{
  "type": "Feature",
  "properties": {
    "iso:country":"GB",
    "sg:address":"40 Duffryn St",
    "sg:city":"Ferndale",
    "sg:classifiers":[
        {
            "category":"Health Services",
            "subcategory":"Clinic",
            "type":"Services"
        }
    ],
    "sg:phone":"+44 1443 733359",
    "sg:postcode":"CF43 4EP",
    "sg:province":"Rhondda, Cynon, Taff",
    "sg:tags":[
        "injury",
        "sport"
    ],
    "wof:name":"W Fraser",
    "wof:placetype":"venue"
},
  "geometry": {"coordinates":[-3.4470291138,51.6599884033],"type":"Point"}
}