{
  "type": "Feature",
  "properties": {
    "iso:country":"GB",
    "sg:address":"11-13 Grampian Road",
    "sg:city":"Aberdeen",
    "sg:classifiers":[
        {
            "category":"Building & Trades",
            "subcategory":"Construction",
            "type":"Services"
        }
    ],
    "sg:postcode":"AB11 8EB",
    "sg:province":"Aberdeen City",
    "sg:tags":[
        "flooring"
    ],
    "wof:name":"Aspect Furnishings",
    "wof:placetype":"venue"
},
  "geometry": {"coordinates":[-2.086905,57.136311],"type":"Point"}
}