{
  "type": "Feature",
  "properties": {
    "iso:country":"GB",
    "sg:address":"44 Salisbury Rd, Dronfiled",
    "sg:city":"Dronfield",
    "sg:classifiers":[
        {
            "category":"Home & Garden",
            "subcategory":"Building Materials",
            "type":"Retail Goods"
        }
    ],
    "sg:postcode":"S18 1UG",
    "sg:province":"Derbyshire",
    "sg:tags":[
        "polythene",
        "plastic"
    ],
    "wof:name":"Proctor,Reg,",
    "wof:placetype":"venue"
},
  "geometry": {"coordinates":[-1.467325,53.292534],"type":"Point"}
}