{
  "type": "Feature",
  "properties": {
    "iso:country":"GB",
    "sg:address":"The Station, Whinney Lane, Street House",
    "sg:city":"Pontefract",
    "sg:classifiers":[
        {
            "category":"Building & Trades",
            "subcategory":"Construction",
            "type":"Services"
        }
    ],
    "sg:postcode":"WF7 6DE",
    "sg:province":"West Yorkshire",
    "sg:tags":[
        "excavation",
        "groundwork",
        "contractor"
    ],
    "wof:name":"M R Hall Construction Ltd.",
    "wof:placetype":"venue"
},
  "geometry": {"coordinates":[-1.376419,53.681751],"type":"Point"}
}