{
  "type": "Feature",
  "properties": {
    "iso:country":"GB",
    "sg:address":"276 Church Road, Sheldon",
    "sg:city":"Birmingham",
    "sg:classifiers":[
        {
            "category":"Travel",
            "subcategory":"Travel Agent",
            "type":"Entertainment"
        }
    ],
    "sg:postcode":"B26 3YH",
    "sg:province":"West Midlands",
    "wof:name":"B & H Travel Services",
    "wof:placetype":"venue"
},
  "geometry": {"coordinates":[-1.776451,52.463512],"type":"Point"}
}