{
  "type": "Feature",
  "properties": {
    "iso:country":"GB",
    "sg:address":"54 New Road, Seven Kings",
    "sg:city":"Ilford",
    "sg:classifiers":[
        {
            "category":"Professional",
            "subcategory":"Accounting & Tax Preparation",
            "type":"Services"
        }
    ],
    "sg:phone":"+44 20 8597 3270",
    "sg:postcode":"IG3 8AT",
    "sg:province":"Essex",
    "sg:tags":[
        "accountant"
    ],
    "wof:name":"Berger & Partners",
    "wof:placetype":"venue"
},
  "geometry": {"coordinates":[0.0990549996,51.5613899231],"type":"Point"}
}