{
  "type": "Feature",
  "properties": {
    "addr:full":"Brook Farm House, Back Lane, Birdingbury Rugby Northamptonshire CV23 8EN",
    "addr:postcode":"cv23 8en",
    "addr:street":"Brook;Back Lane",
    "iso:country":"GB",
    "sg:address":"Brook Farm House, Back Lane, Birdingbury",
    "sg:city":"Rugby",
    "sg:classifiers":[
        {
            "category":"Shopping",
            "subcategory":"Computers & Home Electronics",
            "type":"Retail Goods"
        }
    ],
    "sg:postcode":"CV23 8EN",
    "sg:province":"Northamptonshire",
    "wof:name":"Chris Barney Furniture",
    "wof:placetype":"venue"
},
  "geometry": {"coordinates":[-1.368104,52.311649],"type":"Point"}
}