{
  "type": "Feature",
  "properties": {
    "addr:full":"63 Stour Road, Dover Court Harwich Essex CO12 3HS",
    "addr:housenumber":"63",
    "addr:postcode":"co12 3hs",
    "addr:street":"Stour Road Dover Court",
    "iso:country":"GB",
    "sg:address":"63 Stour Road, Dover Court",
    "sg:city":"Harwich",
    "sg:classifiers":[
        {
            "category":"Freight",
            "type":"Transportation"
        }
    ],
    "sg:postcode":"CO12 3HS",
    "sg:province":"Essex",
    "sg:tags":[
        "haulage",
        "road"
    ],
    "wof:name":"The Haulage Co-Operative",
    "wof:placetype":"venue"
},
  "geometry": {"coordinates":[1.285665,51.944859],"type":"Point"}
}