{
  "type": "Feature",
  "properties": {
    "iso:country":"GB",
    "sg:address":"125 Wellington St",
    "sg:city":"Batley",
    "sg:classifiers":[
        {
            "category":"Bars & Pubs",
            "type":"Food & Drink"
        }
    ],
    "sg:postcode":"WF17 5TH",
    "sg:province":"West Yorkshire",
    "sg:tags":[
        "pubs",
        "inn"
    ],
    "wof:name":"West,E,",
    "wof:placetype":"venue"
},
  "geometry": {"coordinates":[-1.639765,53.712181],"type":"Point"}
}