{
  "type": "Feature",
  "properties": {
    "addr:full":"23 Church Rd Stanmore Greater London HA7 4AR",
    "addr:housenumber":"23",
    "addr:postcode":"ha7 4ar",
    "addr:street":"Church Rd",
    "iso:country":"GB",
    "sg:address":"23 Church Rd",
    "sg:city":"Stanmore",
    "sg:classifiers":[
        {
            "category":"Manufacturing",
            "subcategory":"Tools & Machinery",
            "type":"Manufacturing & Wholesale Goods"
        }
    ],
    "sg:phone":"+44 20 8420 7171",
    "sg:postcode":"HA7 4AR",
    "sg:province":"Greater London",
    "sg:tags":[
        "society",
        "friendly"
    ],
    "wof:name":"Warranty Concepts Ltd",
    "wof:placetype":"venue"
},
  "geometry": {"coordinates":[-0.312442,51.617432],"type":"Point"}
}