{
  "type": "Feature",
  "properties": {
    "addr:full":"99 Gresham St Moorgate Greater London EC2V 7NG",
    "addr:housenumber":"99",
    "addr:postcode":"ec2v 7ng",
    "addr:street":"Gresham St Moorgate",
    "iso:country":"GB",
    "sg:address":"99 Gresham St",
    "sg:city":"Moorgate",
    "sg:classifiers":[
        {
            "category":"Banks & Credit Unions",
            "subcategory":"Bank",
            "type":"Services"
        }
    ],
    "sg:phone":"+44 20 7696 0500",
    "sg:postcode":"EC2V 7NG",
    "sg:province":"Greater London",
    "wof:name":"Pierson Heldring & Pierson",
    "wof:placetype":"venue"
},
  "geometry": {"coordinates":[-0.093359001,51.5154190063],"type":"Point"}
}