{
  "type": "Feature",
  "properties": {
    "addr:full":"Residential Customer Service, Videotron Ho, West Quay Rd Southampton Hampshire SO15 1GZ",
    "addr:postcode":"so15 1gz",
    "addr:street":"West Quay Rd",
    "iso:country":"GB",
    "sg:address":"Residential Customer Service, Videotron Ho, West Quay Rd",
    "sg:city":"Southampton",
    "sg:classifiers":[
        {
            "category":"Communications",
            "type":"Services"
        }
    ],
    "sg:phone":"+44 23 8031 5315",
    "sg:postcode":"SO15 1GZ",
    "sg:province":"Hampshire",
    "sg:tags":[
        "telecommunication"
    ],
    "wof:name":"Cable & Wireless Communications PLC",
    "wof:placetype":"venue"
},
  "geometry": {"coordinates":[-1.41223,50.901581],"type":"Point"}
}