{
  "type": "Feature",
  "properties": {
    "addr:full":"Nothe Parade Weymouth Dorset DT4 8TX",
    "addr:postcode":"dt4 8tx",
    "addr:street":"Nothe Parade",
    "iso:country":"GB",
    "sg:address":"Nothe Parade",
    "sg:city":"Weymouth",
    "sg:classifiers":[
        {
            "category":"Organizations",
            "subcategory":"Community Association",
            "type":"Services"
        },
        {
            "category":"Arena",
            "subcategory":"Sports Club",
            "type":"Entertainment"
        }
    ],
    "sg:phone":"+44 1305 779403",
    "sg:postcode":"DT4 8TX",
    "sg:province":"Dorset",
    "sg:tags":[
        "social"
    ],
    "wof:name":"Weymouth Sailing Club",
    "wof:placetype":"venue"
},
  "geometry": {"coordinates":[-2.451569,50.606743],"type":"Point"}
}