{
  "type": "Feature",
  "properties": {
    "iso:country":"GB",
    "sg:address":"38-40 Telford Way",
    "sg:city":"London",
    "sg:classifiers":[
        {
            "category":"Shopping",
            "subcategory":"Musical Instruments",
            "type":"Retail Goods"
        }
    ],
    "sg:phone":"+44 870 760 7171",
    "sg:postcode":"W3 7XS",
    "sg:province":"Greater London",
    "wof:name":"Cimple Solutions Professional Ltd.",
    "wof:placetype":"venue"
},
  "geometry": {"coordinates":[-0.254506,51.520378],"type":"Point"}
}