{
  "type": "Feature",
  "properties": {
    "addr:full":"45 Tothill Street London Greater London SW1H 9LQ",
    "addr:housenumber":"45",
    "addr:postcode":"sw1h 9lq",
    "addr:street":"Tothill Street",
    "iso:country":"GB",
    "sg:address":"45 Tothill Street",
    "sg:city":"London",
    "sg:classifiers":[
        {
            "category":"Shopping",
            "subcategory":"News",
            "type":"Retail Goods"
        }
    ],
    "sg:phone":"+44 20 7799 1773",
    "sg:postcode":"SW1H 9LQ",
    "sg:province":"Greater London",
    "sg:tags":[
        "newsagent"
    ],
    "wof:name":"Martin the Newsagent",
    "wof:placetype":"venue"
},
  "geometry": {"coordinates":[-0.132507,51.499588],"type":"Point"}
}