{
  "type": "Feature",
  "properties": {
    "iso:country":"GB",
    "sg:address":"The Old Coppermill, Copper Mill Lane",
    "sg:city":"London",
    "sg:classifiers":[
        {
            "category":"Professional",
            "subcategory":"Engineering",
            "type":"Services"
        }
    ],
    "sg:phone":"+44 20 8944 0818",
    "sg:postcode":"SW17 0BN",
    "sg:province":"Greater London",
    "sg:tags":[
        "consulting",
        "engineer"
    ],
    "wof:name":"Sure Engineering Europe Ltd.",
    "wof:placetype":"venue"
},
  "geometry": {"coordinates":[-0.1871,51.429779],"type":"Point"}
}