{
  "type": "Feature",
  "properties": {
    "iso:country":"GB",
    "sg:address":"Birches Avenue, Codsall",
    "sg:city":"Wolverhampton",
    "sg:classifiers":[
        {
            "category":"Education",
            "subcategory":"School",
            "type":"Public Place"
        },
        {
            "category":"Government",
            "subcategory":"Office",
            "type":"Public Place"
        }
    ],
    "sg:phone":"+44 1902 434100",
    "sg:postcode":"WV8 2JG",
    "sg:province":"Shropshire",
    "sg:tags":[
        "local",
        "authority"
    ],
    "wof:name":"Birches First School",
    "wof:placetype":"venue"
},
  "geometry": {"coordinates":[-2.178028,52.618526],"type":"Point"}
}