{
  "type": "Feature",
  "properties": {
    "iso:country":"GB",
    "sg:address":"17-19 Prideaux Road",
    "sg:city":"Eastbourne",
    "sg:classifiers":[
        {
            "category":"Health Services",
            "subcategory":"Nursing And Care Facility",
            "type":"Services"
        }
    ],
    "sg:phone":"+44 1323 721911",
    "sg:postcode":"BN21 2ND",
    "sg:province":"East Sussex",
    "sg:tags":[
        "home"
    ],
    "wof:name":"Springfield Care Ltd.",
    "wof:placetype":"venue"
},
  "geometry": {"coordinates":[0.2771260142,50.7787780762],"type":"Point"}
}