{
  "type": "Feature",
  "properties": {
    "iso:country":"GB",
    "sg:address":"22 Kingsbury",
    "sg:city":"Aylesbury",
    "sg:classifiers":[
        {
            "category":"Organizations",
            "subcategory":"Community Association",
            "type":"Services"
        },
        {
            "category":"Organizations",
            "subcategory":"Membership Organization",
            "type":"Services"
        }
    ],
    "sg:phone":"+44 1296 482184",
    "sg:postcode":"HP20 2HT",
    "sg:province":"Buckinghamshire",
    "sg:tags":[
        "club",
        "social"
    ],
    "wof:name":"Victoria Club",
    "wof:placetype":"venue"
},
  "geometry": {"coordinates":[-0.813261,51.81715],"type":"Point"}
}