{
  "type": "Feature",
  "properties": {
    "iso:country":"GB",
    "sg:address":"73 Severn Drive",
    "sg:city":"Burntwood",
    "sg:classifiers":[
        {
            "category":"Home & Garden",
            "subcategory":"Household Appliances",
            "type":"Retail Goods"
        }
    ],
    "sg:postcode":"WS7 9JF",
    "sg:province":"Staffordshire",
    "sg:tags":[
        "electrical"
    ],
    "wof:name":"Burntwood Refrigeration",
    "wof:placetype":"venue"
},
  "geometry": {"coordinates":[-1.897258997,52.6783485413],"type":"Point"}
}