{
  "type": "Feature",
  "properties": {
    "iso:country":"GB",
    "sg:address":"3 Perigree Road",
    "sg:city":"Sheffield",
    "sg:classifiers":[
        {
            "category":"Arena",
            "subcategory":"Sports Club",
            "type":"Entertainment"
        }
    ],
    "sg:postcode":"S8 0NE",
    "sg:province":"Derbyshire",
    "wof:name":"Sheffield & District Amateur Swimming Association",
    "wof:placetype":"venue"
},
  "geometry": {"coordinates":[-1.484573,53.346088],"type":"Point"}
}