{
  "type": "Feature",
  "properties": {
    "addr:full":"138 London Rd Braintree Essex CM7 8PU",
    "addr:housenumber":"138",
    "addr:postcode":"cm7 8pu",
    "addr:street":"London Rd",
    "iso:country":"GB",
    "sg:address":"138 London Rd",
    "sg:city":"Braintree",
    "sg:classifiers":[
        {
            "category":"Professional",
            "subcategory":"Engineering",
            "type":"Services"
        }
    ],
    "sg:phone":"+44 1376 349911",
    "sg:postcode":"CM7 8PU",
    "sg:province":"Essex",
    "sg:tags":[
        "contractor",
        "electrical",
        "engineer"
    ],
    "wof:name":"Coy Electrical Ltd",
    "wof:placetype":"venue"
},
  "geometry": {"coordinates":[0.538456,51.865086],"type":"Point"}
}