{
  "type": "Feature",
  "properties": {
    "addr:full":"Robin Hill, Fell Drive Grange-over-sands Cumbria LA11 7JF",
    "addr:postcode":"la11 7jf",
    "addr:street":"Fell Drive Grange-Over-Sands",
    "iso:country":"GB",
    "sg:address":"Robin Hill, Fell Drive",
    "sg:city":"Grange-over-sands",
    "sg:classifiers":[
        {
            "category":"Building & Trades",
            "subcategory":"Construction",
            "type":"Services"
        }
    ],
    "sg:postcode":"LA11 7JF",
    "sg:province":"Cumbria",
    "sg:tags":[
        "glazier",
        "decorator",
        "painter"
    ],
    "wof:name":"G Porter",
    "wof:placetype":"venue"
},
  "geometry": {"coordinates":[-2.92164,54.184158],"type":"Point"}
}