{
  "type": "Feature",
  "properties": {
    "addr:full":"8 Whins Road Stirling Falkirk FK7 0HA",
    "addr:housenumber":"8",
    "addr:postcode":"fk7 0ha",
    "addr:street":"Whins Road",
    "iso:country":"GB",
    "sg:address":"8 Whins Road",
    "sg:city":"Stirling",
    "sg:classifiers":[
        {
            "category":"Sports & Exercise",
            "subcategory":"Athletic Track",
            "type":"Entertainment"
        }
    ],
    "sg:phone":"+44 1786 812547",
    "sg:postcode":"FK7 0HA",
    "sg:province":"Falkirk",
    "sg:tags":[
        "gauge",
        "maker"
    ],
    "wof:name":"William Dunn",
    "wof:placetype":"venue"
},
  "geometry": {"coordinates":[-3.932264,56.096394],"type":"Point"}
}