{
  "type": "Feature",
  "properties": {
    "addr:full":"4 Bank Square Wilmslow Cheshire SK9 1AN",
    "addr:housenumber":"4",
    "addr:postcode":"sk9 1an",
    "addr:street":"Bank Square",
    "iso:country":"GB",
    "sg:address":"4 Bank Square",
    "sg:city":"Wilmslow",
    "sg:classifiers":[
        {
            "category":"Restaurant",
            "type":"Food & Drink"
        }
    ],
    "sg:phone":"+44 1625 539754",
    "sg:postcode":"SK9 1AN",
    "sg:province":"Cheshire",
    "wof:name":"Bank Square Cafe Bar Ltd.",
    "wof:placetype":"venue"
},
  "geometry": {"coordinates":[-2.229811,53.328281],"type":"Point"}
}