{
  "type": "Feature",
  "properties": {
    "iso:country":"GB",
    "sg:address":"32-34 Cardiff Road",
    "sg:city":"Cardiff",
    "sg:classifiers":[
        {
            "category":"Home & Garden",
            "subcategory":"Hardware",
            "type":"Retail Goods"
        }
    ],
    "sg:phone":"+44 29 2081 0427",
    "sg:postcode":"CF15 7RF",
    "sg:province":"Caerphilly",
    "sg:tags":[
        "retailer",
        "diy"
    ],
    "wof:name":"Arthur's D I Y",
    "wof:placetype":"venue"
},
  "geometry": {"coordinates":[-3.221979,51.495281],"type":"Point"}
}