{
  "type": "Feature",
  "properties": {
    "addr:full":"86 Winkworth Rd Banstead Surrey SM7 2QR",
    "addr:housenumber":"86",
    "addr:postcode":"sm7 2qr",
    "addr:street":"Winkworth Rd",
    "iso:country":"GB",
    "sg:address":"86 Winkworth Rd",
    "sg:city":"Banstead",
    "sg:classifiers":[
        {
            "category":"Professional",
            "subcategory":"Engineering",
            "type":"Services"
        }
    ],
    "sg:phone":"+44 1737 356369",
    "sg:postcode":"SM7 2QR",
    "sg:province":"Surrey",
    "sg:tags":[
        "contractor",
        "electrical",
        "engineer"
    ],
    "wof:name":"Powertec",
    "wof:placetype":"venue"
},
  "geometry": {"coordinates":[-0.199855,51.327801],"type":"Point"}
}