{
  "type": "Feature",
  "properties": {
    "iso:country":"GB",
    "sg:address":"Old House Farm, Hall La, Wrangle",
    "sg:city":"Boston",
    "sg:classifiers":[
        {
            "category":"Home & Garden",
            "subcategory":"Garden Supply",
            "type":"Retail Goods"
        }
    ],
    "sg:phone":"+44 1205 870407",
    "sg:postcode":"PE22 9EZ",
    "sg:province":"Lincolnshire",
    "sg:tags":[
        "bulb",
        "grower"
    ],
    "wof:name":"Danby,S G,& Sons",
    "wof:placetype":"venue"
},
  "geometry": {"coordinates":[0.126063,53.038956],"type":"Point"}
}