{
  "type": "Feature",
  "properties": {
    "addr:full":"16 Albert Street Aberdeen Aberdeen City AB25 1XQ",
    "addr:housenumber":"16",
    "addr:postcode":"ab25 1xq",
    "addr:street":"Albert Street",
    "iso:country":"GB",
    "sg:address":"16 Albert Street",
    "sg:city":"Aberdeen",
    "sg:classifiers":[
        {
            "category":"Professional",
            "subcategory":"Engineering",
            "type":"Services"
        }
    ],
    "sg:postcode":"AB25 1XQ",
    "sg:province":"Aberdeen City",
    "sg:tags":[
        "consulting",
        "engineer"
    ],
    "wof:name":"Mott Macdonald Scotland",
    "wof:placetype":"venue"
},
  "geometry": {"coordinates":[-2.117123,57.144836],"type":"Point"}
}