{
  "type": "Feature",
  "properties": {
    "iso:country":"GB",
    "sg:address":"Western Industrial Estate, Ponthir Road",
    "sg:city":"Newport",
    "sg:classifiers":[
        {
            "category":"Home & Garden",
            "subcategory":"Building Materials",
            "type":"Retail Goods"
        }
    ],
    "sg:phone":"+44 1633 423549",
    "sg:postcode":"NP18 3NN",
    "sg:province":"Monmouthshire",
    "sg:tags":[
        "ready",
        "mixed",
        "concrete"
    ],
    "wof:name":"Caerleon Ready Mixed Concrete Ltd.",
    "wof:placetype":"venue"
},
  "geometry": {"coordinates":[-2.95937,51.618881],"type":"Point"}
}