{
  "type": "Feature",
  "properties": {
    "iso:country":"GB",
    "sg:address":"7 Cunard Close, Brunswick",
    "sg:city":"Manchester",
    "sg:classifiers":[
        {
            "category":"Wholesale",
            "subcategory":"Books, Periodicals, & Newspapers",
            "type":"Manufacturing & Wholesale Goods"
        }
    ],
    "sg:phone":"+44 161 273 6967",
    "sg:postcode":"M13 9YD",
    "sg:province":"Greater Manchester",
    "sg:tags":[
        "newsagent"
    ],
    "wof:name":"Jumbo Lucky Bags",
    "wof:placetype":"venue"
},
  "geometry": {"coordinates":[-2.224441,53.468208],"type":"Point"}
}