{
  "type": "Feature",
  "properties": {
    "addr:full":"128 Moat Street Wigston Leicestershire LE18 2GE",
    "addr:housenumber":"128",
    "addr:postcode":"le18 2ge",
    "addr:street":"Moat Street",
    "iso:country":"GB",
    "sg:address":"128 Moat Street",
    "sg:city":"Wigston",
    "sg:classifiers":[
        {
            "category":"Personal",
            "subcategory":"Beauty Salon",
            "type":"Services"
        }
    ],
    "sg:phone":"+44 116 281 2120",
    "sg:postcode":"LE18 2GE",
    "sg:province":"Leicestershire",
    "sg:tags":[
        "unisex",
        "hairdresser"
    ],
    "wof:name":"Manuela Hair Design",
    "wof:placetype":"venue"
},
  "geometry": {"coordinates":[-1.104971,52.581841],"type":"Point"}
}