{
  "type": "Feature",
  "properties": {
    "iso:country":"GB",
    "sg:address":"60 Keats Way",
    "sg:city":"West Drayton",
    "sg:classifiers":[
        {
            "category":"Retail",
            "subcategory":"Auto Repair",
            "type":"Services"
        }
    ],
    "sg:postcode":"UB7 9DU",
    "sg:province":"Greater London",
    "sg:tags":[
        "engine",
        "car",
        "specialist"
    ],
    "wof:name":"Tune Up",
    "wof:placetype":"venue"
},
  "geometry": {"coordinates":[-0.463514,51.496643],"type":"Point"}
}