{
  "type": "Feature",
  "properties": {
    "addr:full":"Bedford Corn Exchange, Harpur Suite, Harpur Street Bedford Bedfordshire MK40 1LA",
    "addr:housenumber":"harpur suite",
    "addr:postcode":"mk40 1la",
    "addr:street":"Harpur Street",
    "iso:country":"GB",
    "sg:address":"Bedford Corn Exchange, Harpur Suite, Harpur Street",
    "sg:city":"Bedford",
    "sg:classifiers":[
        {
            "category":"Arts & Performance",
            "subcategory":"Theater",
            "type":"Entertainment"
        }
    ],
    "sg:phone":"+44 1234 269519",
    "sg:postcode":"MK40 1LA",
    "sg:province":"Bedfordshire",
    "sg:tags":[
        "hall",
        "theatre",
        "concert"
    ],
    "wof:name":"Central Box Office",
    "wof:placetype":"venue"
},
  "geometry": {"coordinates":[-0.4649580121,52.1389732361],"type":"Point"}
}