{
  "type": "Feature",
  "properties": {
    "addr:full":"2 Darin Ct Milton Keynes Buckinghamshire MK8 0AD",
    "addr:housenumber":"2",
    "addr:postcode":"mk8 0ad",
    "addr:street":"Darin Ct",
    "iso:country":"GB",
    "sg:address":"2 Darin Ct",
    "sg:city":"Milton Keynes",
    "sg:classifiers":[
        {
            "category":"Home & Garden",
            "subcategory":"Hardware",
            "type":"Retail Goods"
        }
    ],
    "sg:phone":"+44 1908 560904",
    "sg:postcode":"MK8 0AD",
    "sg:province":"Buckinghamshire",
    "sg:tags":[
        "wheel",
        "castor"
    ],
    "wof:name":"Rotal Ltd",
    "wof:placetype":"venue"
},
  "geometry": {"coordinates":[-0.798472,52.030571],"type":"Point"}
}