{
  "type": "Feature",
  "properties": {
    "addr:full":"179 Buchanan Street Glasgow Glasgow City G1 2JZ",
    "addr:housenumber":"179",
    "addr:postcode":"g1 2jz",
    "addr:street":"Buchanan Street",
    "iso:country":"GB",
    "sg:address":"179 Buchanan Street",
    "sg:city":"Glasgow",
    "sg:classifiers":[
        {
            "category":"Arts & Performance",
            "subcategory":"Theater",
            "type":"Entertainment"
        }
    ],
    "sg:phone":"+44 141 332 2333",
    "sg:postcode":"G1 2JZ",
    "sg:province":"Glasgow City",
    "sg:tags":[
        "hall",
        "theatre",
        "concert"
    ],
    "wof:name":"The Athenaeum Old",
    "wof:placetype":"venue"
},
  "geometry": {"coordinates":[-4.2536711693,55.8621292114],"type":"Point"}
}