{
  "type": "Feature",
  "properties": {
    "addr:full":"Osborne Ho, 3-5 Portland Rd Hythe Kent CT21 6EG",
    "addr:housenumber":"3-5",
    "addr:postcode":"ct21 6eg",
    "addr:street":"Portland Rd",
    "iso:country":"GB",
    "sg:address":"Osborne Ho, 3-5 Portland Rd",
    "sg:city":"Hythe",
    "sg:classifiers":[
        {
            "category":"Banks & Credit Unions",
            "subcategory":"Financial Services",
            "type":"Services"
        }
    ],
    "sg:phone":"+44 1303 237002",
    "sg:postcode":"CT21 6EG",
    "sg:province":"Kent",
    "sg:tags":[
        "consultant"
    ],
    "wof:name":"Hythe Ethical",
    "wof:placetype":"venue"
},
  "geometry": {"coordinates":[1.0804810524,51.0708274841],"type":"Point"}
}