{
  "type": "Feature",
  "properties": {
    "iso:country":"GB",
    "sg:address":"4-6 Summerleaze Crescent",
    "sg:city":"Bude",
    "sg:classifiers":[
        {
            "category":"Health Services",
            "subcategory":"Nursing And Care Facility",
            "type":"Services"
        }
    ],
    "sg:postcode":"EX23 8HH",
    "sg:province":"Cornwall",
    "sg:tags":[
        "home"
    ],
    "wof:name":"Bude Nursing Home",
    "wof:placetype":"venue"
},
  "geometry": {"coordinates":[-4.5459809303,50.8360519409],"type":"Point"}
}