{
  "type": "Feature",
  "properties": {
    "iso:country":"GB",
    "sg:address":"18 Waveney Road",
    "sg:city":"Droitwich",
    "sg:classifiers":[
        {
            "category":"Government",
            "subcategory":"Post Office",
            "type":"Public Place"
        }
    ],
    "sg:postcode":"WR9 8TS",
    "sg:province":"Worcestershire",
    "sg:tags":[
        "messenger",
        "courier"
    ],
    "wof:name":"J P Booth",
    "wof:placetype":"venue"
},
  "geometry": {"coordinates":[-2.167998,52.258102],"type":"Point"}
}