{
  "type": "Feature",
  "properties": {
    "iso:country":"GB",
    "sg:address":"62 Woodside Grn",
    "sg:city":"London",
    "sg:classifiers":[
        {
            "category":"Professional",
            "subcategory":"Art Services",
            "type":"Services"
        }
    ],
    "sg:phone":"+44 20 8656 3914",
    "sg:postcode":"SE25 5EU",
    "sg:province":"Greater London",
    "sg:tags":[
        "photographer"
    ],
    "wof:name":"Edward Phillips",
    "wof:placetype":"venue"
},
  "geometry": {"coordinates":[-0.070532,51.386703],"type":"Point"}
}