{
  "type": "Feature",
  "properties": {
    "addr:full":"Unit 17 Moncur St Glasgow Glasgow City G40 2SL",
    "addr:housenumber":"unit 17",
    "addr:postcode":"g40 2sl",
    "addr:street":"Moncur St",
    "iso:country":"GB",
    "sg:address":"Unit 17 Moncur St",
    "sg:city":"Glasgow",
    "sg:classifiers":[
        {
            "category":"Home & Garden",
            "subcategory":"Carpets & Floor Coverings",
            "type":"Retail Goods"
        }
    ],
    "sg:phone":"+44 141 552 3484",
    "sg:postcode":"G40 2SL",
    "sg:province":"Glasgow City",
    "sg:tags":[
        "carpets",
        "rug",
        "matting"
    ],
    "wof:name":"Caledonian Carpets",
    "wof:placetype":"venue"
},
  "geometry": {"coordinates":[-4.236004,55.85461],"type":"Point"}
}