{
  "type": "Feature",
  "properties": {
    "addr:full":"2b Port Street Evesham Gloucestershire WR11 1AN",
    "addr:housenumber":"2b",
    "addr:postcode":"wr11 1an",
    "addr:street":"Port Street",
    "iso:country":"GB",
    "sg:address":"2b Port Street",
    "sg:city":"Evesham",
    "sg:classifiers":[
        {
            "category":"Shopping",
            "subcategory":"Computers & Home Electronics",
            "type":"Retail Goods"
        }
    ],
    "sg:phone":"+44 1386 40280",
    "sg:postcode":"WR11 1AN",
    "sg:province":"Gloucestershire",
    "wof:name":"Megabytes",
    "wof:placetype":"venue"
},
  "geometry": {"coordinates":[-1.9420150518,52.0911560059],"type":"Point"}
}