{
  "type": "Feature",
  "properties": {
    "iso:country":"GB",
    "sg:address":"99 Main Street, Glenluce",
    "sg:city":"Newton Stewart",
    "sg:classifiers":[
        {
            "category":"Bus Charters",
            "type":"Transportation"
        },
        {
            "category":"Bus Stop",
            "subcategory":"None",
            "type":"Transportation"
        }
    ],
    "sg:phone":"+44 1581 300345",
    "sg:postcode":"DG8 0PT",
    "sg:province":"Dumfries and Galloway",
    "sg:tags":[
        "operator",
        "coach"
    ],
    "wof:name":"A F Irvine & Son",
    "wof:placetype":"venue"
},
  "geometry": {"coordinates":[-4.807175,54.880676],"type":"Point"}
}