{
  "type": "Feature",
  "properties": {
    "iso:country":"GB",
    "sg:address":"11 Bridge Street",
    "sg:city":"Macclesfield",
    "sg:classifiers":[
        {
            "category":"Personal",
            "subcategory":"Barber",
            "type":"Services"
        }
    ],
    "sg:phone":"+44 1625 613563",
    "sg:postcode":"SK11 6EG",
    "sg:province":"Cheshire",
    "sg:tags":[
        "men's",
        "hairdresser"
    ],
    "wof:name":"Klips N Kutz",
    "wof:placetype":"venue"
},
  "geometry": {"coordinates":[-2.1297690868,53.2605857849],"type":"Point"}
}