{
  "type": "Feature",
  "properties": {
    "iso:country":"GB",
    "sg:address":"Monument Hill",
    "sg:city":"Weybridge",
    "sg:classifiers":[
        {
            "category":"Home & Garden",
            "subcategory":"Hardware",
            "type":"Retail Goods"
        }
    ],
    "sg:phone":"+44 1932 850811",
    "sg:postcode":"KT13 8LH",
    "sg:province":"Surrey",
    "sg:tags":[
        "retailer",
        "diy"
    ],
    "wof:name":"Focus",
    "wof:placetype":"venue"
},
  "geometry": {"coordinates":[-0.455354,51.373611],"type":"Point"}
}