{
  "type": "Feature",
  "properties": {
    "addr:full":"Oteley Road Shrewsbury Shropshire SY2 6QL",
    "addr:postcode":"sy2 6ql",
    "addr:street":"Oteley Road",
    "iso:country":"GB",
    "sg:address":"Oteley Road",
    "sg:city":"Shrewsbury",
    "sg:classifiers":[
        {
            "category":"Home & Garden",
            "subcategory":"Garden Supply",
            "type":"Retail Goods"
        }
    ],
    "sg:postcode":"SY2 6QL",
    "sg:province":"Shropshire",
    "sg:tags":[
        "nursery",
        "centre"
    ],
    "wof:name":"Sutton Grange Nursery",
    "wof:placetype":"venue"
},
  "geometry": {"coordinates":[-2.72928,52.688881],"type":"Point"}
}