{
  "type": "Feature",
  "properties": {
    "iso:country":"GB",
    "sg:address":"22 Quarry Rd",
    "sg:city":"Irvine",
    "sg:classifiers":[
        {
            "category":"Retail",
            "subcategory":"Auto Repair",
            "type":"Services"
        }
    ],
    "sg:phone":"+44 1294 312727",
    "sg:postcode":"KA12 0TH",
    "sg:province":"North Ayrshire",
    "sg:tags":[
        "body",
        "car"
    ],
    "wof:name":"Norloch Autos",
    "wof:placetype":"venue"
},
  "geometry": {"coordinates":[-4.664709,55.620937],"type":"Point"}
}