{
  "type": "Feature",
  "properties": {
    "addr:full":"5 Broadgate Close Barnstaple Devon EX31 4AL",
    "addr:housenumber":"5",
    "addr:postcode":"ex31 4al",
    "addr:street":"Broadgate Close",
    "iso:country":"GB",
    "sg:address":"5 Broadgate Close",
    "sg:city":"Barnstaple",
    "sg:classifiers":[
        {
            "category":"Retail",
            "subcategory":"Auto Repair",
            "type":"Services"
        }
    ],
    "sg:postcode":"EX31 4AL",
    "sg:province":"Devon",
    "sg:tags":[
        "garage"
    ],
    "wof:name":"X-Tec Engineering",
    "wof:placetype":"venue"
},
  "geometry": {"coordinates":[-4.06703,51.090149],"type":"Point"}
}