{
  "type": "Feature",
  "properties": {
    "addr:full":"112 Regents Park Road, Shirley Southampton Hampshire SO15 8PD",
    "addr:housenumber":"112",
    "addr:postcode":"so15 8pd",
    "addr:street":"Regents Park Road",
    "iso:country":"GB",
    "sg:address":"112 Regents Park Road, Shirley",
    "sg:city":"Southampton",
    "sg:classifiers":[
        {
            "category":"Professional",
            "subcategory":"Engineering",
            "type":"Services"
        }
    ],
    "sg:phone":"+44 23 8077 4725",
    "sg:postcode":"SO15 8PD",
    "sg:province":"Hampshire",
    "sg:tags":[
        "contractor",
        "electrical",
        "engineer"
    ],
    "wof:name":"Sliema Electrics",
    "wof:placetype":"venue"
},
  "geometry": {"coordinates":[-1.4401630163,50.917388916],"type":"Point"}
}