{
  "type": "Feature",
  "properties": {
    "addr:full":"Blakes Farm, Parsloe Road, Epping Upland Epping Essex CM16 6QB",
    "addr:postcode":"cm16 6qb",
    "addr:street":"Parsloe Road",
    "iso:country":"GB",
    "sg:address":"Blakes Farm, Parsloe Road, Epping Upland",
    "sg:city":"Epping",
    "sg:classifiers":[
        {
            "category":"Food & Beverages",
            "subcategory":"Farmers Market",
            "type":"Retail Goods"
        },
        {
            "category":"Utilities",
            "subcategory":"Natural Gas",
            "type":"Services"
        },
        {
            "category":"Food & Beverages",
            "subcategory":"Meat & Fish",
            "type":"Retail Goods"
        }
    ],
    "sg:phone":"+44 1992 890806",
    "sg:postcode":"CM16 6QB",
    "sg:province":"Essex",
    "sg:tags":[
        "shop",
        "farm",
        "supplier",
        "butcher",
        "pyo"
    ],
    "wof:name":"M C Peacock",
    "wof:placetype":"venue"
},
  "geometry": {"coordinates":[0.0897049978,51.72108078],"type":"Point"}
}