{
  "type": "Feature",
  "properties": {
    "addr:full":"Cardale Grange, Otley Road, Beckwithshaw Harrogate North Yorkshire HG3 1QL",
    "addr:postcode":"hg3 1ql",
    "addr:street":"Otley Road Beckwithshaw",
    "iso:country":"GB",
    "sg:address":"Cardale Grange, Otley Road, Beckwithshaw",
    "sg:city":"Harrogate",
    "sg:classifiers":[
        {
            "category":"Farming",
            "subcategory":"Farm",
            "type":"Manufacturing & Wholesale Goods"
        }
    ],
    "sg:phone":"+44 1423 530760",
    "sg:postcode":"HG3 1QL",
    "sg:province":"North Yorkshire",
    "sg:tags":[
        "mixed",
        "crop"
    ],
    "wof:name":"Cardale Estates",
    "wof:placetype":"venue"
},
  "geometry": {"coordinates":[-1.5659840107,53.9760131836],"type":"Point"}
}