{
  "type": "Feature",
  "properties": {
    "addr:full":"Harley St West End Hampshire W1N 2AL",
    "addr:postcode":"2al",
    "addr:street":"Harley St",
    "iso:country":"GB",
    "sg:address":"Harley St",
    "sg:city":"West End",
    "sg:classifiers":[
        {
            "category":"Real Estate",
            "subcategory":"Surveying",
            "type":"Services"
        }
    ],
    "sg:phone":"+44 20 7637 8471",
    "sg:postcode":"W1N 2AL",
    "sg:province":"Hampshire",
    "sg:tags":[
        "surveyor",
        "valuer"
    ],
    "wof:name":"Wilks Head & Eve",
    "wof:placetype":"venue"
},
  "geometry": {"coordinates":[-0.146285,51.517532],"type":"Point"}
}