{
  "type": "Feature",
  "properties": {
    "iso:country":"GB",
    "sg:address":"Powder Works, Melling",
    "sg:city":"Liverpool",
    "sg:classifiers":[
        {
            "category":"Building & Trades",
            "subcategory":"Construction",
            "type":"Services"
        }
    ],
    "sg:phone":"+44 151 526 7236",
    "sg:postcode":"L31 1AU",
    "sg:province":"Lancashire",
    "sg:tags":[
        "joiner",
        "carpenter"
    ],
    "wof:name":"Melbac",
    "wof:placetype":"venue"
},
  "geometry": {"coordinates":[-2.927275,53.497738],"type":"Point"}
}