{
  "type": "Feature",
  "properties": {
    "iso:country":"GB",
    "sg:address":"9 Friars Road",
    "sg:city":"Stoke-on-trent",
    "sg:classifiers":[
        {
            "category":"Real Estate",
            "subcategory":"Surveying",
            "type":"Services"
        }
    ],
    "sg:phone":"+44 1785 222167",
    "sg:postcode":"ST2 8DQ",
    "sg:province":"Staffordshire",
    "sg:tags":[
        "surveyor",
        "valuer"
    ],
    "wof:name":"Hockleys Professional Ltd.",
    "wof:placetype":"venue"
},
  "geometry": {"coordinates":[-2.140379,53.040367],"type":"Point"}
}