{
  "type": "Feature",
  "properties": {
    "addr:full":"78 Cross Hill, Ecclesfield Sheffield South Yorkshire S35 9TU",
    "addr:housenumber":"78",
    "addr:postcode":"s35 9tu",
    "addr:street":"Cross Hill",
    "iso:country":"GB",
    "sg:address":"78 Cross Hill, Ecclesfield",
    "sg:city":"Sheffield",
    "sg:classifiers":[
        {
            "category":"Utilities",
            "subcategory":"Natural Gas",
            "type":"Services"
        }
    ],
    "sg:postcode":"S35 9TU",
    "sg:province":"South Yorkshire",
    "sg:tags":[
        "supp",
        "glazier"
    ],
    "wof:name":"Nationwide Glass & Glazing Systems Ltd",
    "wof:placetype":"venue"
},
  "geometry": {"coordinates":[-1.4586770535,53.4373512268],"type":"Point"}
}