{
  "type": "Feature",
  "properties": {
    "addr:full":"493 New Cross Rd London Greater London SE14 6TQ",
    "addr:housenumber":"493",
    "addr:postcode":"se14 6tq",
    "addr:street":"New Cross Rd",
    "iso:country":"GB",
    "sg:address":"493 New Cross Rd",
    "sg:city":"London",
    "sg:classifiers":[
        {
            "category":"Food & Beverages",
            "subcategory":"Bakery",
            "type":"Retail Goods"
        }
    ],
    "sg:postcode":"SE14 6TQ",
    "sg:province":"Greater London",
    "sg:tags":[
        "baker"
    ],
    "wof:name":"Three Star Bakery",
    "wof:placetype":"venue"
},
  "geometry": {"coordinates":[-0.026934,51.475174],"type":"Point"}
}