{
  "type": "Feature",
  "properties": {
    "addr:full":"10 Burtree Lane Darlington Durham DL3 0XQ",
    "addr:housenumber":"10",
    "addr:postcode":"dl3 0xq",
    "addr:street":"Burtree Lane",
    "iso:country":"GB",
    "sg:address":"10 Burtree Lane",
    "sg:city":"Darlington",
    "sg:classifiers":[
        {
            "category":"Health Services",
            "subcategory":"Health Practitioner",
            "type":"Services"
        }
    ],
    "sg:phone":"+44 1325 355388",
    "sg:postcode":"DL3 0XQ",
    "sg:province":"Durham",
    "sg:tags":[
        "homoeopathic",
        "homeopathic"
    ],
    "wof:name":"CARRIE WATSON",
    "wof:placetype":"venue"
},
  "geometry": {"coordinates":[-1.549932,54.55489],"type":"Point"}
}