{
  "type": "Feature",
  "properties": {
    "addr:full":"Second Floor, 58-60 Blackburn Road Accrington Lancashire BB5 1LE",
    "addr:housenumber":"second;58-60",
    "addr:postcode":"bb5 1le",
    "addr:street":"Blackburn Road",
    "iso:country":"GB",
    "sg:address":"Second Floor, 58-60 Blackburn Road",
    "sg:city":"Accrington",
    "sg:classifiers":[
        {
            "category":"Professional",
            "subcategory":"Art Services",
            "type":"Services"
        }
    ],
    "sg:postcode":"BB5 1LE",
    "sg:province":"Lancashire",
    "sg:tags":[
        "consultant",
        "design"
    ],
    "wof:name":"Traffex Tool Design Service",
    "wof:placetype":"venue"
},
  "geometry": {"coordinates":[-2.3663859367,53.7533760071],"type":"Point"}
}