{
  "type": "Feature",
  "properties": {
    "iso:country":"GB",
    "sg:address":"Chase Farm Hospital, The Ridgeway",
    "sg:city":"Enfield",
    "sg:classifiers":[
        {
            "category":"Shopping",
            "subcategory":"Florist",
            "type":"Retail Goods"
        }
    ],
    "sg:postcode":"EN4 8JL",
    "sg:province":"Hertfordshire",
    "wof:name":"Chase Farm Flower & Ballon Shop",
    "wof:placetype":"venue"
},
  "geometry": {"coordinates":[-0.17112,51.6432],"type":"Point"}
}