{
  "type": "Feature",
  "properties": {
    "addr:full":"132 Royal Oak Road Manchester Cheshire M23 1FB",
    "addr:housenumber":"132",
    "addr:postcode":"m23 1fb",
    "addr:street":"Royal Oak Road",
    "iso:country":"GB",
    "sg:address":"132 Royal Oak Road",
    "sg:city":"Manchester",
    "sg:classifiers":[
        {
            "category":"Food & Beverages",
            "subcategory":"Meat & Fish",
            "type":"Retail Goods"
        }
    ],
    "sg:phone":"+44 161 902 0396",
    "sg:postcode":"M23 1FB",
    "sg:province":"Cheshire",
    "sg:tags":[
        "chip"
    ],
    "wof:name":"The Magic Wok",
    "wof:placetype":"venue"
},
  "geometry": {"coordinates":[-2.2801189423,53.3942909241],"type":"Point"}
}