{
  "type": "Feature",
  "properties": {
    "addr:full":"5 Tudor Workshops Tudor Lane, Tudor Rd Cardiff Cardiff CF14 6BQ",
    "addr:housenumber":"5",
    "addr:postcode":"cf14 6bq",
    "addr:street":"Tudor Workshops Tudor Lane Tudor Rd",
    "iso:country":"GB",
    "sg:address":"5 Tudor Workshops Tudor Lane, Tudor Rd",
    "sg:city":"Cardiff",
    "sg:classifiers":[
        {
            "category":"Manufacturing",
            "subcategory":"Building Materials",
            "type":"Manufacturing & Wholesale Goods"
        }
    ],
    "sg:phone":"+44 29 2061 2901",
    "sg:postcode":"CF14 6BQ",
    "sg:province":"Cardiff",
    "sg:tags":[
        "shutter",
        "supp",
        "door"
    ],
    "wof:name":"Discount Garage Doors",
    "wof:placetype":"venue"
},
  "geometry": {"coordinates":[-3.21035,51.517979],"type":"Point"}
}