{
  "type": "Feature",
  "properties": {
    "addr:full":"Pisgah Street, Kenfig Hill Bridgend Bridgend CF33 6DA",
    "addr:postcode":"cf33 6da",
    "addr:street":"Pisgah Street",
    "iso:country":"GB",
    "sg:address":"Pisgah Street, Kenfig Hill",
    "sg:city":"Bridgend",
    "sg:classifiers":[
        {
            "category":"Bars & Pubs",
            "type":"Food & Drink"
        },
        {
            "category":"Travel",
            "subcategory":"Hotels & Motels",
            "type":"Entertainment"
        }
    ],
    "sg:phone":"+44 1656 740238",
    "sg:postcode":"CF33 6DA",
    "sg:province":"Bridgend",
    "sg:tags":[
        "pubs",
        "inn"
    ],
    "wof:name":"The Walnut Tree",
    "wof:placetype":"venue"
},
  "geometry": {"coordinates":[-3.683824,51.530773],"type":"Point"}
}