{
  "type": "Feature",
  "properties": {
    "addr:full":"Dewmead Farm, New Inn Road Baldock Bedfordshire SG7 5HG",
    "addr:postcode":"sg7 5hg",
    "addr:street":"New Inn Road",
    "iso:country":"GB",
    "sg:address":"Dewmead Farm, New Inn Road",
    "sg:city":"Baldock",
    "sg:classifiers":[
        {
            "category":"Retail",
            "subcategory":"Auto Repair",
            "type":"Services"
        }
    ],
    "sg:phone":"+44 1462 743037",
    "sg:postcode":"SG7 5HG",
    "sg:province":"Bedfordshire",
    "sg:tags":[
        "modification",
        "garage"
    ],
    "wof:name":"Hinxworth Garage",
    "wof:placetype":"venue"
},
  "geometry": {"coordinates":[-0.1878540069,51.9887695312],"type":"Point"}
}