{
  "type": "Feature",
  "properties": {
    "addr:full":"1 College St St Albans Hertfordshire AL3 4PW",
    "addr:housenumber":"1",
    "addr:postcode":"al3 4pw",
    "addr:street":"College St",
    "iso:country":"GB",
    "sg:address":"1 College St",
    "sg:city":"St Albans",
    "sg:classifiers":[
        {
            "category":"Real Estate",
            "subcategory":"Architect",
            "type":"Services"
        }
    ],
    "sg:phone":"+44 1727 866810",
    "sg:postcode":"AL3 4PW",
    "sg:province":"Hertfordshire",
    "wof:name":"Meacher,Paul,",
    "wof:placetype":"venue"
},
  "geometry": {"coordinates":[-0.342066,51.753551],"type":"Point"}
}