{
  "type": "Feature",
  "properties": {
    "addr:full":"3 Forth Avenue Indust Est Kirkcaldy Fife KY2 5QW",
    "addr:housenumber":"3",
    "addr:postcode":"ky2 5qw",
    "addr:street":"Forth Avenue Indust Est",
    "iso:country":"GB",
    "sg:address":"3 Forth Avenue Indust Est",
    "sg:city":"Kirkcaldy",
    "sg:classifiers":[
        {
            "category":"Autos & Motor Vehicles",
            "subcategory":"Auto Supplies",
            "type":"Retail Goods"
        }
    ],
    "sg:phone":"+44 1592 264191",
    "sg:postcode":"KY2 5QW",
    "sg:province":"Fife",
    "sg:tags":[
        "component"
    ],
    "wof:name":"Edmunds Walker",
    "wof:placetype":"venue"
},
  "geometry": {"coordinates":[-3.169478,56.110462],"type":"Point"}
}