{
  "type": "Feature",
  "properties": {
    "addr:full":"Wharehouse, Mill Road Wellingborough Northamptonshire NN8 1QW",
    "addr:postcode":"nn8 1qw",
    "addr:street":"Mill Road",
    "iso:country":"GB",
    "sg:address":"Wharehouse, Mill Road",
    "sg:city":"Wellingborough",
    "sg:classifiers":[
        {
            "category":"Shopping",
            "subcategory":"Luggage & Leather Goods",
            "type":"Retail Goods"
        }
    ],
    "sg:phone":"+44 1933 441305",
    "sg:postcode":"NN8 1QW",
    "sg:province":"Northamptonshire",
    "wof:name":"W Brown (Wholesale)",
    "wof:placetype":"venue"
},
  "geometry": {"coordinates":[-0.696296,52.302422],"type":"Point"}
}