{
  "type": "Feature",
  "properties": {
    "iso:country":"GB",
    "sg:address":"386 Paisley Road West",
    "sg:city":"Glasgow",
    "sg:classifiers":[
        {
            "category":"Personal",
            "subcategory":"Beauty Salon",
            "type":"Services"
        },
        {
            "category":"Personal",
            "subcategory":"Barber",
            "type":"Services"
        }
    ],
    "sg:phone":"+44 141 427 5351",
    "sg:postcode":"G51 1BG",
    "sg:province":"Glasgow City",
    "sg:tags":[
        "unisex",
        "hairdresser"
    ],
    "wof:name":"J R's Hair Studio",
    "wof:placetype":"venue"
},
  "geometry": {"coordinates":[-4.2960472107,55.8519287109],"type":"Point"}
}