{
  "type": "Feature",
  "properties": {
    "addr:full":"126 Weston Park Road Plymouth Devon PL3 4NR",
    "addr:housenumber":"126",
    "addr:postcode":"pl3 4nr",
    "addr:street":"Weston Park Road",
    "iso:country":"GB",
    "sg:address":"126 Weston Park Road",
    "sg:city":"Plymouth",
    "sg:classifiers":[
        {
            "category":"Professional",
            "subcategory":"Accounting & Tax Preparation",
            "type":"Services"
        }
    ],
    "sg:phone":"+44 1752 254562",
    "sg:postcode":"PL3 4NR",
    "sg:province":"Devon",
    "sg:tags":[
        "accountant",
        "bookkeeping",
        "primarily",
        "activity"
    ],
    "wof:name":"Lynian Business Services Ltd",
    "wof:placetype":"venue"
},
  "geometry": {"coordinates":[-4.140753,50.392197],"type":"Point"}
}