{
  "type": "Feature",
  "properties": {
    "addr:full":"1-5 Regent Road Morecambe Lancashire LA3 1QG",
    "addr:housenumber":"1-5",
    "addr:postcode":"la3 1qg",
    "addr:street":"Regent Road",
    "iso:country":"GB",
    "sg:address":"1-5 Regent Road",
    "sg:city":"Morecambe",
    "sg:classifiers":[
        {
            "category":"Personal",
            "subcategory":"Shoe Repair & Shine",
            "type":"Services"
        },
        {
            "category":"Shopping",
            "subcategory":"Shoes",
            "type":"Retail Goods"
        }
    ],
    "sg:phone":"+44 1524 415125",
    "sg:postcode":"LA3 1QG",
    "sg:province":"Lancashire",
    "wof:name":"The Lady Cobbler",
    "wof:placetype":"venue"
},
  "geometry": {"coordinates":[-2.88088,54.06617],"type":"Point"}
}