{
  "type": "Feature",
  "properties": {
    "iso:country":"GB",
    "sg:address":"46 The Knoll, Hayes",
    "sg:city":"Bromley",
    "sg:classifiers":[
        {
            "category":"Organizations",
            "subcategory":"Membership Organization",
            "type":"Services"
        }
    ],
    "sg:postcode":"BR2 7DH",
    "sg:province":"Kent",
    "sg:tags":[
        "club"
    ],
    "wof:name":"Doverton Information Management Ltd",
    "wof:placetype":"venue"
},
  "geometry": {"coordinates":[0.0155440001,51.3755912781],"type":"Point"}
}