{
  "type": "Feature",
  "properties": {
    "addr:full":"3 Derby Road, Beeston Nottingham Nottinghamshire NG9 2TA",
    "addr:housenumber":"3",
    "addr:postcode":"ng9 2ta",
    "addr:street":"Derby Road",
    "iso:country":"GB",
    "sg:address":"3 Derby Road, Beeston",
    "sg:city":"Nottingham",
    "sg:classifiers":[
        {
            "category":"Professional",
            "subcategory":"Business Services",
            "type":"Services"
        }
    ],
    "sg:phone":"+44 115 943 0899",
    "sg:postcode":"NG9 2TA",
    "sg:province":"Nottinghamshire",
    "sg:tags":[
        "bookmaker"
    ],
    "wof:name":"Victor Chandler Bookmakers",
    "wof:placetype":"venue"
},
  "geometry": {"coordinates":[-1.218036,52.938698],"type":"Point"}
}