{
  "type": "Feature",
  "properties": {
    "iso:country":"GB",
    "sg:address":"16 Holkham Road, Orton Southgate",
    "sg:city":"Peterborough",
    "sg:classifiers":[
        {
            "category":"Building & Trades",
            "subcategory":"Construction",
            "type":"Services"
        }
    ],
    "sg:phone":"+44 1733 239292",
    "sg:postcode":"PE2 6TE",
    "sg:province":"Cambridgeshire",
    "sg:tags":[
        "fork",
        "lift",
        "truck"
    ],
    "wof:name":"Windsor Engineering Ltd",
    "wof:placetype":"venue"
},
  "geometry": {"coordinates":[-0.30771,52.540157],"type":"Point"}
}