{
  "type": "Feature",
  "properties": {
    "addr:full":"9 North St Hornchurch Essex RM11 1RL",
    "addr:housenumber":"9",
    "addr:postcode":"rm11 1rl",
    "addr:street":"North St",
    "iso:country":"GB",
    "sg:address":"9 North St",
    "sg:city":"Hornchurch",
    "sg:classifiers":[
        {
            "category":"Travel",
            "subcategory":"Travel Agent",
            "type":"Entertainment"
        }
    ],
    "sg:phone":"+44 1708 471611",
    "sg:postcode":"RM11 1RL",
    "sg:province":"Essex",
    "wof:name":"Travelworld",
    "wof:placetype":"venue"
},
  "geometry": {"coordinates":[0.219972,51.563053],"type":"Point"}
}