{
  "type": "Feature",
  "properties": {
    "iso:country":"GB",
    "sg:address":"9 The Regent Centre, Kirkintilloch",
    "sg:city":"Glasgow",
    "sg:classifiers":[
        {
            "category":"Shopping",
            "subcategory":"Pharmacy",
            "type":"Retail Goods"
        }
    ],
    "sg:phone":"+44 141 776 3418",
    "sg:postcode":"G66 1JH",
    "sg:province":"East Dunbartonshire",
    "sg:tags":[
        "pharmacist",
        "chemist"
    ],
    "wof:name":"Boots the Chemists",
    "wof:placetype":"venue"
},
  "geometry": {"coordinates":[-4.15795,55.93959],"type":"Point"}
}