{
  "type": "Feature",
  "properties": {
    "iso:country":"GB",
    "sg:address":"18 Hainton Avenue",
    "sg:city":"Grimsby",
    "sg:classifiers":[
        {
            "category":"Organizations",
            "subcategory":"Non-profit Organization",
            "type":"Services"
        }
    ],
    "sg:phone":"+44 1472 310102",
    "sg:postcode":"DN32 9BB",
    "sg:province":"Lincolnshire",
    "sg:tags":[
        "organisation",
        "voluntary",
        "charity"
    ],
    "wof:name":"Crossroads - Caring for Carers",
    "wof:placetype":"venue"
},
  "geometry": {"coordinates":[-0.075292,53.566124],"type":"Point"}
}