{
  "type": "Feature",
  "properties": {
    "addr:full":"67 King Street Stirling Stirling FK8 1BN",
    "addr:housenumber":"67",
    "addr:postcode":"fk8 1bn",
    "addr:street":"King Street",
    "iso:country":"GB",
    "sg:address":"67 King Street",
    "sg:city":"Stirling",
    "sg:classifiers":[
        {
            "category":"Manufacturing",
            "subcategory":"Jewelry",
            "type":"Manufacturing & Wholesale Goods"
        }
    ],
    "sg:phone":"+44 1786 478928",
    "sg:postcode":"FK8 1BN",
    "sg:province":"Stirling",
    "sg:tags":[
        "repair",
        "jewellery"
    ],
    "wof:name":"Stuarts",
    "wof:placetype":"venue"
},
  "geometry": {"coordinates":[-3.9386129379,56.1185379028],"type":"Point"}
}