{
  "type": "Feature",
  "properties": {
    "addr:full":"5 Shaftesbury Road, West Moors Ferndown Dorset BH22 0DY",
    "addr:housenumber":"5",
    "addr:postcode":"bh22 0dy",
    "addr:street":"Shaftesbury Road West",
    "iso:country":"GB",
    "sg:address":"5 Shaftesbury Road, West Moors",
    "sg:city":"Ferndown",
    "sg:classifiers":[
        {
            "category":"Building & Trades",
            "subcategory":"Cleaning & Sanitation",
            "type":"Services"
        }
    ],
    "sg:postcode":"BH22 0DY",
    "sg:province":"Dorset",
    "sg:tags":[
        "cleaner",
        "window"
    ],
    "wof:name":"4 Corners Cleaning Contractors",
    "wof:placetype":"venue"
},
  "geometry": {"coordinates":[-1.876546,50.821568],"type":"Point"}
}