{
  "type": "Feature",
  "properties": {
    "iso:country":"GB",
    "sg:address":"Suite 4 Unit F Warners Mill, Silks Way",
    "sg:city":"Braintree",
    "sg:classifiers":[
        {
            "category":"Retail",
            "subcategory":"Auto Repair",
            "type":"Services"
        }
    ],
    "sg:phone":"+44 1376 349444",
    "sg:postcode":"CM7 3GB",
    "sg:province":"Essex",
    "sg:tags":[
        "bodybuilder",
        "repairer"
    ],
    "wof:name":"Polyfont T P I Ltd.",
    "wof:placetype":"venue"
},
  "geometry": {"coordinates":[0.553242,51.877758],"type":"Point"}
}