{
  "type": "Feature",
  "properties": {
    "iso:country":"GB",
    "sg:address":"70 March Hywel, Cilfrew",
    "sg:city":"Neath",
    "sg:classifiers":[
        {
            "category":"Building & Trades",
            "subcategory":"Construction",
            "type":"Services"
        }
    ],
    "sg:phone":"+44 1792 324324",
    "sg:postcode":"SA10 8NB",
    "sg:province":"Neath Port Talbot",
    "sg:tags":[
        "flooring"
    ],
    "wof:name":"Splinters Ltd",
    "wof:placetype":"venue"
},
  "geometry": {"coordinates":[-3.7799739838,51.6871185303],"type":"Point"}
}