{
  "type": "Feature",
  "properties": {
    "addr:full":"Oliver & Robb Ho, Pitreavie Dr Dunfermline Fife KY11 5PU",
    "addr:postcode":"ky11 5pu",
    "addr:street":"Dr",
    "iso:country":"GB",
    "sg:address":"Oliver & Robb Ho, Pitreavie Dr",
    "sg:city":"Dunfermline",
    "sg:classifiers":[
        {
            "category":"Home & Garden",
            "subcategory":"Hardware",
            "type":"Retail Goods"
        }
    ],
    "sg:phone":"+44 1383 607000",
    "sg:postcode":"KY11 5PU",
    "sg:province":"Fife",
    "sg:tags":[
        "centre",
        "improvement"
    ],
    "wof:name":"Eco Group Ltd The",
    "wof:placetype":"venue"
},
  "geometry": {"coordinates":[-3.4339001179,56.0478668213],"type":"Point"}
}