{
  "type": "Feature",
  "properties": {
    "iso:country":"GB",
    "sg:address":"1st Floor Block A, Jarmin Road",
    "sg:city":"Colchester",
    "sg:classifiers":[
        {
            "category":"Professional",
            "subcategory":"Engineering",
            "type":"Services"
        }
    ],
    "sg:phone":"+44 1553 772423",
    "sg:postcode":"CO1 1XW",
    "sg:province":"Essex",
    "sg:tags":[
        "contractor",
        "electrical",
        "engineer"
    ],
    "wof:name":"Dodd Group (Eastern)",
    "wof:placetype":"venue"
},
  "geometry": {"coordinates":[0.90106,51.896671],"type":"Point"}
}