{
  "type": "Feature",
  "properties": {
    "addr:full":"66 Broomhill Road Aberdeen Aberdeen City AB10 6HT",
    "addr:housenumber":"66",
    "addr:postcode":"ab10 6ht",
    "addr:street":"Broomhill Road",
    "iso:country":"GB",
    "sg:address":"66 Broomhill Road",
    "sg:city":"Aberdeen",
    "sg:classifiers":[
        {
            "category":"Food & Beverages",
            "subcategory":"Fruits & Vegetables",
            "type":"Retail Goods"
        },
        {
            "category":"Food & Beverages",
            "subcategory":"Groceries & Convenience Stores",
            "type":"Retail Goods"
        }
    ],
    "sg:phone":"+44 1224 581751",
    "sg:postcode":"AB10 6HT",
    "sg:province":"Aberdeen City",
    "sg:tags":[
        "grocer",
        "greengrocer"
    ],
    "wof:name":"J & C Lynch",
    "wof:placetype":"venue"
},
  "geometry": {"coordinates":[-2.118378,57.134789],"type":"Point"}
}