{
  "type": "Feature",
  "properties": {
    "addr:full":"Green Farm Building, Barrow Hill, Barrow Bury St Edmunds Suffolk IP29 5DX",
    "addr:postcode":"ip29 5dx",
    "iso:country":"GB",
    "sg:address":"Green Farm Building, Barrow Hill, Barrow",
    "sg:city":"Bury St Edmunds",
    "sg:classifiers":[
        {
            "category":"Retail",
            "subcategory":"Auto Repair",
            "type":"Services"
        }
    ],
    "sg:postcode":"IP29 5DX",
    "sg:province":"Suffolk",
    "sg:tags":[
        "bodybuilder",
        "repairer"
    ],
    "wof:name":"N A Cansdale & Sons",
    "wof:placetype":"venue"
},
  "geometry": {"coordinates":[0.5807449818,52.2434043884],"type":"Point"}
}