{
  "type": "Feature",
  "properties": {
    "iso:country":"GB",
    "sg:address":"Trellwyfan Farm, Llantilio Crossenny",
    "sg:city":"Abergavenny",
    "sg:classifiers":[
        {
            "category":"Farming",
            "subcategory":"Livestock Farm",
            "type":"Manufacturing & Wholesale Goods"
        }
    ],
    "sg:phone":"+44 1600 780478",
    "sg:postcode":"NP7 8UE",
    "sg:province":"Herefordshire",
    "sg:tags":[
        "others"
    ],
    "wof:name":"S D Watkins",
    "wof:placetype":"venue"
},
  "geometry": {"coordinates":[-2.8749189377,51.8299331665],"type":"Point"}
}