{
  "type": "Feature",
  "properties": {
    "addr:full":"Little Brook Cottage, East Portlemouth Salcombe Devon TQ8 8PW",
    "addr:postcode":"tq8 8pw",
    "iso:country":"GB",
    "sg:address":"Little Brook Cottage, East Portlemouth",
    "sg:city":"Salcombe",
    "sg:classifiers":[
        {
            "category":"Real Estate",
            "subcategory":"Surveying",
            "type":"Services"
        }
    ],
    "sg:postcode":"TQ8 8PW",
    "sg:province":"Devon",
    "sg:tags":[
        "surveyor",
        "marine"
    ],
    "wof:name":"Ward & McKenzie (South West)",
    "wof:placetype":"venue"
},
  "geometry": {"coordinates":[-3.7747991085,50.237865448],"type":"Point"}
}