{
  "type": "Feature",
  "properties": {
    "addr:full":"102-104 Park Lane Croydon Surrey CR0 1JB",
    "addr:housenumber":"102-104",
    "addr:postcode":"cr0 1jb",
    "addr:street":"Park Lane",
    "iso:country":"GB",
    "sg:address":"102-104 Park Lane",
    "sg:city":"Croydon",
    "sg:classifiers":[
        {
            "category":"Professional",
            "subcategory":"Accounting & Tax Preparation",
            "type":"Services"
        },
        {
            "category":"Banks & Credit Unions",
            "subcategory":"Investment Brokerage",
            "type":"Services"
        }
    ],
    "sg:phone":"+44 20 8686 3571",
    "sg:postcode":"CR0 1JB",
    "sg:province":"Surrey",
    "sg:tags":[
        "accountant",
        "auditor"
    ],
    "wof:name":"Ingle Shamash & Co",
    "wof:placetype":"venue"
},
  "geometry": {"coordinates":[-0.096855,51.368851],"type":"Point"}
}