{
  "type": "Feature",
  "properties": {
    "iso:country":"GB",
    "sg:address":"Princes Rd",
    "sg:city":"Maldon",
    "sg:classifiers":[
        {
            "category":"Professional",
            "subcategory":"Lawyer & Legal Services",
            "type":"Services"
        }
    ],
    "sg:phone":"+44 1621 858334",
    "sg:postcode":"CM9 5NY",
    "sg:province":"Essex",
    "sg:tags":[
        "advice",
        "counselling"
    ],
    "wof:name":"Maldon Citizens Advice Bureau",
    "wof:placetype":"venue"
},
  "geometry": {"coordinates":[0.6798700094,51.7281265259],"type":"Point"}
}