{
  "type": "Feature",
  "properties": {
    "addr:full":"88 Bermondsey St Southwark Greater London SE1 3UB",
    "addr:housenumber":"88",
    "addr:postcode":"se1 3ub",
    "addr:street":"Bermondsey St",
    "iso:country":"GB",
    "sg:address":"88 Bermondsey St",
    "sg:city":"Southwark",
    "sg:classifiers":[
        {
            "category":"Organizations",
            "subcategory":"Religious Organization",
            "type":"Services"
        }
    ],
    "sg:phone":"+44 20 7357 0910",
    "sg:postcode":"SE1 3UB",
    "sg:province":"Greater London",
    "sg:tags":[
        "organisation"
    ],
    "wof:name":"World Miracle Outreach",
    "wof:placetype":"venue"
},
  "geometry": {"coordinates":[-0.082,51.501019],"type":"Point"}
}