{
  "type": "Feature",
  "properties": {
    "iso:country":"GB",
    "sg:address":"Unit 205 Gardener House, 3-9 Broomhill Road",
    "sg:city":"London",
    "sg:classifiers":[
        {
            "category":"Wholesale",
            "subcategory":"Books, Periodicals, & Newspapers",
            "type":"Manufacturing & Wholesale Goods"
        }
    ],
    "sg:phone":"+44 20 8870 3176",
    "sg:postcode":"SW18 4JQ",
    "sg:province":"Greater London",
    "sg:tags":[
        "publishing"
    ],
    "wof:name":"Ralston Publications Ltd.",
    "wof:placetype":"venue"
},
  "geometry": {"coordinates":[-0.197495,51.455265],"type":"Point"}
}