{
  "type": "Feature",
  "properties": {
    "addr:full":"147 Uxbridge Road London Greater London W7 3ST",
    "addr:housenumber":"147",
    "addr:postcode":"w7 3st",
    "addr:street":"Uxbridge Road",
    "iso:country":"GB",
    "sg:address":"147 Uxbridge Road",
    "sg:city":"London",
    "sg:classifiers":[
        {
            "category":"Food & Beverages",
            "subcategory":"Meat & Fish",
            "type":"Retail Goods"
        }
    ],
    "sg:phone":"+44 20 8567 8317",
    "sg:postcode":"W7 3ST",
    "sg:province":"Greater London",
    "sg:tags":[
        "butcher"
    ],
    "wof:name":"Hanwell Halal Meat",
    "wof:placetype":"venue"
},
  "geometry": {"coordinates":[-0.337759,51.509007],"type":"Point"}
}