{
  "type": "Feature",
  "properties": {
    "iso:country":"GB",
    "sg:address":"13 Edgefield Drive, Hartford Grn",
    "sg:city":"Cramlington",
    "sg:classifiers":[
        {
            "category":"Professional",
            "subcategory":"Engineering",
            "type":"Services"
        },
        {
            "category":"Building & Trades",
            "subcategory":"Electrical",
            "type":"Services"
        }
    ],
    "sg:phone":"+44 1670 714073",
    "sg:postcode":"NE23 3HZ",
    "sg:province":"Northumberland",
    "sg:tags":[
        "engineer",
        "electrician",
        "contractor"
    ],
    "wof:name":"J M Electrical Services",
    "wof:placetype":"venue"
},
  "geometry": {"coordinates":[-1.57356,55.102566],"type":"Point"}
}