{
  "type": "Feature",
  "properties": {
    "iso:country":"GB",
    "sg:address":"9 Creel Gardens, Cove",
    "sg:city":"Aberdeen",
    "sg:classifiers":[
        {
            "category":"Arts & Performance",
            "subcategory":"Music",
            "type":"Entertainment"
        }
    ],
    "sg:phone":"+44 1224 895297",
    "sg:postcode":"AB12 3BW",
    "sg:province":"Aberdeen City",
    "sg:tags":[
        "mobile",
        "disco"
    ],
    "wof:name":"Disco 2000",
    "wof:placetype":"venue"
},
  "geometry": {"coordinates":[-2.0883638859,57.0960083008],"type":"Point"}
}