{
  "type": "Feature",
  "properties": {
    "iso:country":"GB",
    "sg:address":"350 Bloxwich Road",
    "sg:city":"Walsall",
    "sg:classifiers":[
        {
            "category":"Building & Trades",
            "subcategory":"Equipment Rental",
            "type":"Services"
        }
    ],
    "sg:phone":"+44 1922 615181",
    "sg:postcode":"WS2 7BG",
    "sg:province":"West Midlands",
    "sg:tags":[
        "hire",
        "centre"
    ],
    "wof:name":"Hss Hire Shops",
    "wof:placetype":"venue"
},
  "geometry": {"coordinates":[-1.9905190468,52.6028404236],"type":"Point"}
}