{
  "type": "Feature",
  "properties": {
    "addr:full":"54 Caunce Street Blackpool Lancashire FY1 3LJ",
    "addr:housenumber":"54",
    "addr:postcode":"fy1 3lj",
    "addr:street":"Caunce Street",
    "iso:country":"GB",
    "sg:address":"54 Caunce Street",
    "sg:city":"Blackpool",
    "sg:classifiers":[
        {
            "category":"Professional",
            "subcategory":"Accounting & Tax Preparation",
            "type":"Services"
        },
        {
            "category":"Banks & Credit Unions",
            "subcategory":"Investment Brokerage",
            "type":"Services"
        }
    ],
    "sg:phone":"+44 1253 621512",
    "sg:postcode":"FY1 3LJ",
    "sg:province":"Lancashire",
    "sg:tags":[
        "accountant",
        "auditor"
    ],
    "wof:name":"Haworth Moore",
    "wof:placetype":"venue"
},
  "geometry": {"coordinates":[-3.0455598831,53.8193969727],"type":"Point"}
}