{
  "type": "Feature",
  "properties": {
    "iso:country":"GB",
    "sg:address":"Unit 69 Roman Way, Longridge Road, Ribbleton",
    "sg:city":"Preston",
    "sg:classifiers":[
        {
            "category":"Personal",
            "type":"Services"
        }
    ],
    "sg:phone":"+44 1772 701007",
    "sg:postcode":"PR2 5BE",
    "sg:province":"Lancashire",
    "sg:tags":[
        "gift"
    ],
    "wof:name":"Abbotson & Co. Ltd.",
    "wof:placetype":"venue"
},
  "geometry": {"coordinates":[-2.634729,53.79163],"type":"Point"}
}