{
  "type": "Feature",
  "properties": {
    "iso:country":"GB",
    "sg:address":"8 Fore Street",
    "sg:city":"Bodmin",
    "sg:classifiers":[
        {
            "category":"Shopping",
            "subcategory":"Clothing, Apparel, & Fashions",
            "type":"Retail Goods"
        }
    ],
    "sg:phone":"+44 1208 72711",
    "sg:postcode":"PL31 2HQ",
    "sg:province":"Cornwall",
    "sg:tags":[
        "menswear"
    ],
    "wof:name":"J Brewer & Son (Bodmin) Ltd.",
    "wof:placetype":"venue"
},
  "geometry": {"coordinates":[-4.7196650505,50.470867157],"type":"Point"}
}