{
  "type": "Feature",
  "properties": {
    "iso:country":"GB",
    "sg:address":"Care Of British Travel Centre",
    "sg:city":"London",
    "sg:classifiers":[
        {
            "category":"Travel",
            "subcategory":"Travel Agent",
            "type":"Entertainment"
        }
    ],
    "sg:phone":"+44 20 7930 0572",
    "sg:postcode":"SW1Y 4PQ",
    "sg:province":"Greater London",
    "sg:tags":[
        "hotel",
        "agency",
        "booking"
    ],
    "wof:name":"Room Centre (U K) Ltd.",
    "wof:placetype":"venue"
},
  "geometry": {"coordinates":[-0.1334899962,51.5082092285],"type":"Point"}
}