{
  "type": "Feature",
  "properties": {
    "iso:country":"GB",
    "sg:address":"1145 London Road",
    "sg:city":"Leigh-on-sea",
    "sg:classifiers":[
        {
            "category":"Food & Beverages",
            "subcategory":"Meat & Fish",
            "type":"Retail Goods"
        }
    ],
    "sg:postcode":"SS9 3JE",
    "sg:province":"Essex",
    "sg:tags":[
        "butcher"
    ],
    "wof:name":"The Lazy Lamb",
    "wof:placetype":"venue"
},
  "geometry": {"coordinates":[0.659762,51.547798],"type":"Point"}
}