{
  "type": "Feature",
  "properties": {
    "addr:full":"41a Leg Street Oswestry Shropshire SY11 2NN",
    "addr:housenumber":"41a",
    "addr:postcode":"sy11 2nn",
    "addr:street":"Leg Street",
    "iso:country":"GB",
    "sg:address":"41a Leg Street",
    "sg:city":"Oswestry",
    "sg:classifiers":[
        {
            "category":"Organizations",
            "subcategory":"Non-profit Organization",
            "type":"Services"
        }
    ],
    "sg:phone":"+44 1691 671700",
    "sg:postcode":"SY11 2NN",
    "sg:province":"Shropshire",
    "sg:tags":[
        "organisation",
        "voluntary",
        "charity"
    ],
    "wof:name":"Oswestry & Borderlands Citizens Advocacy",
    "wof:placetype":"venue"
},
  "geometry": {"coordinates":[-3.053222,52.859306],"type":"Point"}
}