{
  "type": "Feature",
  "properties": {
    "addr:full":"19 North Street, Abercynon Mountain Ash Rhondda, Cynon, Taff CF45 4ST",
    "addr:housenumber":"19",
    "addr:postcode":"cf45 4st",
    "addr:street":"North Street;Ash;Cynon Taff",
    "iso:country":"GB",
    "sg:address":"19 North Street, Abercynon",
    "sg:city":"Mountain Ash",
    "sg:classifiers":[
        {
            "category":"Home & Garden",
            "subcategory":"Furniture",
            "type":"Retail Goods"
        }
    ],
    "sg:phone":"+44 1443 740162",
    "sg:postcode":"CF45 4ST",
    "sg:province":"Rhondda, Cynon, Taff",
    "sg:tags":[
        "built-in",
        "fitted"
    ],
    "wof:name":"William H Evans",
    "wof:placetype":"venue"
},
  "geometry": {"coordinates":[-3.328635931,51.6472434998],"type":"Point"}
}