{
  "type": "Feature",
  "properties": {
    "addr:full":"27 Woodside Place Glasgow Glasgow City G3 7QL",
    "addr:housenumber":"27",
    "addr:postcode":"g3 7ql",
    "addr:street":"Woodside Place",
    "iso:country":"GB",
    "sg:address":"27 Woodside Place",
    "sg:city":"Glasgow",
    "sg:classifiers":[
        {
            "category":"Professional",
            "subcategory":"Printing & Photocopies",
            "type":"Services"
        }
    ],
    "sg:phone":"+44 141 572 1216",
    "sg:postcode":"G3 7QL",
    "sg:province":"Glasgow City",
    "sg:tags":[
        "plate",
        "lithographic",
        "maker"
    ],
    "wof:name":"The Dapp Agency",
    "wof:placetype":"venue"
},
  "geometry": {"coordinates":[-4.2758598328,55.8669204712],"type":"Point"}
}