{
  "type": "Feature",
  "properties": {
    "iso:country":"GB",
    "sg:address":"3 Rushton Road, Cheadle Hulme",
    "sg:city":"Cheadle",
    "sg:classifiers":[
        {
            "category":"Professional",
            "subcategory":"Computer Services",
            "type":"Services"
        }
    ],
    "sg:phone":"+44 161 355 3052",
    "sg:postcode":"SK8 6NS",
    "sg:province":"Cheshire",
    "sg:tags":[
        "system",
        "software"
    ],
    "wof:name":"Glycar Computing",
    "wof:placetype":"venue"
},
  "geometry": {"coordinates":[-2.196287,53.360226],"type":"Point"}
}