{
  "type": "Feature",
  "properties": {
    "iso:country":"GB",
    "sg:address":"Walton Head Farm, Pannal",
    "sg:city":"Harrogate",
    "sg:classifiers":[
        {
            "category":"Farming",
            "subcategory":"Livestock Farm",
            "type":"Manufacturing & Wholesale Goods"
        },
        {
            "category":"Farming",
            "subcategory":"Farm",
            "type":"Manufacturing & Wholesale Goods"
        }
    ],
    "sg:phone":"+44 1423 872787",
    "sg:postcode":"HG3 1LF",
    "sg:province":"North Yorkshire",
    "sg:tags":[
        "mixed",
        "crop",
        "others"
    ],
    "wof:name":"F Twisleton",
    "wof:placetype":"venue"
},
  "geometry": {"coordinates":[-1.537346,53.961437],"type":"Point"}
}