{
  "type": "Feature",
  "properties": {
    "addr:full":"7 Rookery Close Nantwich Cheshire CW5 5SJ",
    "addr:housenumber":"7",
    "addr:postcode":"cw5 5sj",
    "addr:street":"Rookery Close",
    "iso:country":"GB",
    "sg:address":"7 Rookery Close",
    "sg:city":"Nantwich",
    "sg:classifiers":[
        {
            "category":"Retail",
            "subcategory":"Driving School",
            "type":"Services"
        }
    ],
    "sg:phone":"+44 1270 629066",
    "sg:postcode":"CW5 5SJ",
    "sg:province":"Cheshire",
    "wof:name":"Carvel School of Motoring",
    "wof:placetype":"venue"
},
  "geometry": {"coordinates":[-2.5155880451,53.0664138794],"type":"Point"}
}