{
  "type": "Feature",
  "properties": {
    "iso:country":"GB",
    "sg:address":"17 Main Street, Eaton",
    "sg:city":"Grantham",
    "sg:classifiers":[
        {
            "category":"Building & Trades",
            "subcategory":"Construction",
            "type":"Services"
        }
    ],
    "sg:postcode":"NG32 1SE",
    "sg:province":"Leicestershire",
    "sg:tags":[
        "roofing"
    ],
    "wof:name":"M E Jarvis (Joinery) Ltd",
    "wof:placetype":"venue"
},
  "geometry": {"coordinates":[-0.798573,52.856529],"type":"Point"}
}