{
  "type": "Feature",
  "properties": {
    "iso:country":"GB",
    "sg:address":"Crovie Farm, Gardenstown",
    "sg:city":"Banff",
    "sg:classifiers":[
        {
            "category":"Building & Trades",
            "subcategory":"Construction",
            "type":"Services"
        }
    ],
    "sg:phone":"+44 1261 851544",
    "sg:postcode":"AB45 3JJ",
    "sg:province":"Aberdeenshire",
    "sg:tags":[
        "equipment"
    ],
    "wof:name":"William Geddes",
    "wof:placetype":"venue"
},
  "geometry": {"coordinates":[-2.338337,57.671852],"type":"Point"}
}