{
  "type": "Feature",
  "properties": {
    "addr:full":"24 Foxhill Road Reading Berkshire RG1 5QS",
    "addr:housenumber":"24",
    "addr:postcode":"rg1 5qs",
    "addr:street":"Foxhill Road",
    "iso:country":"GB",
    "sg:address":"24 Foxhill Road",
    "sg:city":"Reading",
    "sg:classifiers":[
        {
            "category":"Building & Trades",
            "subcategory":"Plumbing",
            "type":"Services"
        }
    ],
    "sg:phone":"+44 118 966 3192",
    "sg:postcode":"RG1 5QS",
    "sg:province":"Berkshire",
    "sg:tags":[
        "heating"
    ],
    "wof:name":"Angle Plumbing & Heating",
    "wof:placetype":"venue"
},
  "geometry": {"coordinates":[-0.947768,51.448044],"type":"Point"}
}