{
  "type": "Feature",
  "properties": {
    "addr:full":"134 Northern Avenue Sheffield South Yorkshire S2 2EH",
    "addr:housenumber":"134",
    "addr:postcode":"s2 2eh",
    "addr:street":"Northern Avenue",
    "iso:country":"GB",
    "sg:address":"134 Northern Avenue",
    "sg:city":"Sheffield",
    "sg:classifiers":[
        {
            "category":"Shopping",
            "subcategory":"Pets & Pet Supplies",
            "type":"Retail Goods"
        }
    ],
    "sg:phone":"+44 114 249 1777",
    "sg:postcode":"S2 2EH",
    "sg:province":"South Yorkshire",
    "sg:tags":[
        "shop"
    ],
    "wof:name":"Tony's Pet Store",
    "wof:placetype":"venue"
},
  "geometry": {"coordinates":[-1.438142,53.360233],"type":"Point"}
}