{
  "type": "Feature",
  "properties": {
    "addr:full":"84 Newgate Street Bishop Auckland Durham DL14 7HB",
    "addr:housenumber":"84",
    "addr:postcode":"dl14 7hb",
    "addr:street":"Newgate Street",
    "iso:country":"GB",
    "sg:address":"84 Newgate Street",
    "sg:city":"Bishop Auckland",
    "sg:classifiers":[
        {
            "category":"Shopping",
            "subcategory":"Department Store",
            "type":"Retail Goods"
        }
    ],
    "sg:phone":"+44 1388 602018",
    "sg:postcode":"DL14 7HB",
    "sg:province":"Durham",
    "sg:tags":[
        "departmental"
    ],
    "wof:name":"Woolworths Plc",
    "wof:placetype":"venue"
},
  "geometry": {"coordinates":[-1.675424,54.662395],"type":"Point"}
}