{
  "type": "Feature",
  "properties": {
    "iso:country":"GB",
    "sg:address":"Unit 6 The Old Sawmills, Hawkerland Road, Colaton Raleigh",
    "sg:city":"Sidmouth",
    "sg:classifiers":[
        {
            "category":"Building & Trades",
            "subcategory":"Construction",
            "type":"Services"
        }
    ],
    "sg:phone":"+44 1395 568123",
    "sg:postcode":"EX10 0HP",
    "sg:province":"Devon",
    "sg:tags":[
        "joinery"
    ],
    "wof:name":"Westgrove (Homes) Ltd.",
    "wof:placetype":"venue"
},
  "geometry": {"coordinates":[-3.3067669868,50.6803131104],"type":"Point"}
}