{
  "type": "Feature",
  "properties": {
    "addr:full":"Unit 1, Tulsi Centre, Constitution Hill Birmingham West Midlands B19 3JX",
    "addr:housenumber":"unit 1;centre",
    "addr:postcode":"b19 3jx",
    "addr:street":"Tulsi;Hill",
    "iso:country":"GB",
    "sg:address":"Unit 1, Tulsi Centre, Constitution Hill",
    "sg:city":"Birmingham",
    "sg:classifiers":[
        {
            "category":"Shopping",
            "subcategory":"Clothing, Apparel, & Fashions",
            "type":"Retail Goods"
        }
    ],
    "sg:postcode":"B19 3JX",
    "sg:province":"West Midlands",
    "sg:tags":[
        "clothing"
    ],
    "wof:name":"Kids Korner",
    "wof:placetype":"venue"
},
  "geometry": {"coordinates":[-1.905857,52.488041],"type":"Point"}
}