{
  "type": "Feature",
  "properties": {
    "addr:full":"Sandy Lane, Chadwell St Mary Grays Essex RM16 4LR",
    "addr:postcode":"rm16 4lr",
    "addr:street":"Sandy Lane",
    "iso:country":"GB",
    "sg:address":"Sandy Lane, Chadwell St Mary",
    "sg:city":"Grays",
    "sg:classifiers":[
        {
            "category":"Building & Trades",
            "subcategory":"Construction",
            "type":"Services"
        }
    ],
    "sg:phone":"+44 1375 844889",
    "sg:postcode":"RM16 4LR",
    "sg:province":"Essex",
    "sg:tags":[
        "welder"
    ],
    "wof:name":"Chadwell Panel Craft",
    "wof:placetype":"venue"
},
  "geometry": {"coordinates":[0.3741779923,51.4769287109],"type":"Point"}
}