{
  "type": "Feature",
  "properties": {
    "addr:full":"3 Commercial Street, Risca Newport Blaenau Gwent NP11 6AW",
    "addr:housenumber":"3",
    "addr:postcode":"np11 6aw",
    "addr:street":"Commercial Street",
    "iso:country":"GB",
    "sg:address":"3 Commercial Street, Risca",
    "sg:city":"Newport",
    "sg:classifiers":[
        {
            "category":"Health Services",
            "subcategory":"Dentist",
            "type":"Services"
        }
    ],
    "sg:postcode":"NP11 6AW",
    "sg:province":"Blaenau Gwent",
    "wof:name":"The Dental Surgery",
    "wof:placetype":"venue"
},
  "geometry": {"coordinates":[-3.0996279716,51.6059341431],"type":"Point"}
}