{
  "type": "Feature",
  "properties": {
    "iso:country":"GB",
    "sg:address":"Unit 14b, No One Industrial Estate",
    "sg:city":"Consett",
    "sg:classifiers":[
        {
            "category":"Home & Garden",
            "subcategory":"Home Furnishings",
            "type":"Retail Goods"
        }
    ],
    "sg:phone":"+44 1207 590131",
    "sg:postcode":"DH8 6SX",
    "sg:province":"Durham",
    "sg:tags":[
        "furnishers",
        "planner",
        "kitchen"
    ],
    "wof:name":"S C C (Installation) Ltd.",
    "wof:placetype":"venue"
},
  "geometry": {"coordinates":[-1.8359140158,54.8609886169],"type":"Point"}
}