{
  "type": "Feature",
  "properties": {
    "addr:full":"16 Pinfold Lane, Butterknowle Bishop Auckland Durham DL13 5NX",
    "addr:housenumber":"16",
    "addr:postcode":"dl13 5nx",
    "addr:street":"Pinfold Lane;Auckland",
    "iso:country":"GB",
    "sg:address":"16 Pinfold Lane, Butterknowle",
    "sg:city":"Bishop Auckland",
    "sg:classifiers":[
        {
            "category":"Utilities",
            "subcategory":"Fuel Oil & Lpg",
            "type":"Services"
        }
    ],
    "sg:phone":"+44 1388 718440",
    "sg:postcode":"DL13 5NX",
    "sg:province":"Durham",
    "wof:name":"Copley Coal Co",
    "wof:placetype":"venue"
},
  "geometry": {"coordinates":[-1.8387960196,54.6270103455],"type":"Point"}
}