{
  "type": "Feature",
  "properties": {
    "addr:full":"77 Stonegate Spalding Lincolnshire PE11 2PH",
    "addr:housenumber":"77",
    "addr:postcode":"pe11 2ph",
    "addr:street":"Stonegate Spalding",
    "iso:country":"GB",
    "sg:address":"77 Stonegate",
    "sg:city":"Spalding",
    "sg:classifiers":[
        {
            "category":"Retail",
            "subcategory":"Driving School",
            "type":"Services"
        }
    ],
    "sg:postcode":"PE11 2PH",
    "sg:province":"Lincolnshire",
    "wof:name":"Elloes Driving Academy",
    "wof:placetype":"venue"
},
  "geometry": {"coordinates":[-0.143893,52.783794],"type":"Point"}
}