{
  "type": "Feature",
  "properties": {
    "iso:country":"GB",
    "sg:address":"6 Avondale Street",
    "sg:city":"Lincoln",
    "sg:classifiers":[
        {
            "category":"Building & Trades",
            "subcategory":"Construction",
            "type":"Services"
        }
    ],
    "sg:phone":"+44 1522 530842",
    "sg:postcode":"LN2 5BL",
    "sg:province":"Lincolnshire",
    "sg:tags":[
        "decorator",
        "painter"
    ],
    "wof:name":"R H Harrison",
    "wof:placetype":"venue"
},
  "geometry": {"coordinates":[-0.5280320048,53.2304000854],"type":"Point"}
}