{
  "type": "Feature",
  "properties": {
    "iso:country":"GB",
    "sg:address":"Beechcroft, Fore Street, Holverton",
    "sg:city":"Plymouth",
    "sg:classifiers":[
        {
            "category":"Military Area",
            "subcategory":"Air Force Base",
            "type":"Public Place"
        }
    ],
    "sg:postcode":"PL8 1NE",
    "sg:province":"Devon",
    "sg:tags":[
        "taxi",
        "hire",
        "private"
    ],
    "wof:name":"Tim's Taxis",
    "wof:placetype":"venue"
},
  "geometry": {"coordinates":[-3.94899,50.334251],"type":"Point"}
}