{
  "type": "Feature",
  "properties": {
    "iso:country":"GB",
    "sg:address":"Unit 14, Parmiter Industrial Centre",
    "sg:city":"London",
    "sg:classifiers":[
        {
            "category":"Professional",
            "subcategory":"Printing & Photocopies",
            "type":"Services"
        }
    ],
    "sg:phone":"+44 20 8983 4488",
    "sg:postcode":"E2 9HZ",
    "sg:province":"Greater London",
    "sg:tags":[
        "printer"
    ],
    "wof:name":"C & C Print & Design Ltd.",
    "wof:placetype":"venue"
},
  "geometry": {"coordinates":[-0.056444,51.532085],"type":"Point"}
}