{
  "type": "Feature",
  "properties": {
    "iso:country":"GB",
    "sg:address":"Oatlands House, Oatlands Road",
    "sg:city":"Manchester",
    "sg:classifiers":[
        {
            "category":"Military Area",
            "subcategory":"Air Force Base",
            "type":"Public Place"
        }
    ],
    "sg:phone":"+44 161 436 4000",
    "sg:postcode":"M22 1AH",
    "sg:province":"Greater Manchester",
    "sg:tags":[
        "taxi",
        "hire",
        "private"
    ],
    "wof:name":"Wythenshawe Private Hire Ltd.",
    "wof:placetype":"venue"
},
  "geometry": {"coordinates":[-2.266114,53.378433],"type":"Point"}
}