{
  "type": "Feature",
  "properties": {
    "addr:full":"1 Alta Vista Road Paignton Devon TQ4 6DB",
    "addr:housenumber":"1",
    "addr:postcode":"tq4 6db",
    "addr:street":"Alta Vista Road",
    "iso:country":"GB",
    "sg:address":"1 Alta Vista Road",
    "sg:city":"Paignton",
    "sg:classifiers":[
        {
            "category":"Travel",
            "subcategory":"Hotels & Motels",
            "type":"Entertainment"
        }
    ],
    "sg:phone":"+44 1803 558128",
    "sg:postcode":"TQ4 6DB",
    "sg:province":"Devon",
    "wof:name":"Benbows Hotel",
    "wof:placetype":"venue"
},
  "geometry": {"coordinates":[-3.557777,50.429703],"type":"Point"}
}