{
  "type": "Feature",
  "properties": {
    "addr:full":"Foxearth, The Street, Heveningham Halesworth Suffolk IP19 0EP",
    "addr:postcode":"ip19 0ep",
    "addr:street":"The Street",
    "iso:country":"GB",
    "sg:address":"Foxearth, The Street, Heveningham",
    "sg:city":"Halesworth",
    "sg:classifiers":[
        {
            "category":"Professional",
            "subcategory":"Credit Reporting & Collection",
            "type":"Services"
        }
    ],
    "sg:phone":"+44 1986 798627",
    "sg:postcode":"IP19 0EP",
    "sg:province":"Suffolk",
    "sg:tags":[
        "collecting",
        "agency"
    ],
    "wof:name":"Recoup",
    "wof:placetype":"venue"
},
  "geometry": {"coordinates":[1.4223669767,52.302066803],"type":"Point"}
}