{
  "type": "Feature",
  "properties": {
    "iso:country":"GB",
    "sg:address":"194 Kings Gate",
    "sg:city":"Aberdeen",
    "sg:classifiers":[
        {
            "category":"Social Services",
            "subcategory":"Retirement Home",
            "type":"Services"
        },
        {
            "category":"Government",
            "subcategory":"Office",
            "type":"Public Place"
        }
    ],
    "sg:phone":"+44 1224 318366",
    "sg:postcode":"AB9 2YP",
    "sg:province":"Aberdeen City",
    "sg:tags":[
        "residential",
        "local",
        "care"
    ],
    "wof:name":"Rosewell House",
    "wof:placetype":"venue"
},
  "geometry": {"coordinates":[-2.1526770592,57.1448898315],"type":"Point"}
}