{
  "type": "Feature",
  "properties": {
    "iso:country":"GB",
    "sg:address":"47 Holly Lane",
    "sg:city":"Smethwick",
    "sg:classifiers":[
        {
            "category":"Health Services",
            "subcategory":"Dentist",
            "type":"Services"
        }
    ],
    "sg:phone":"+44 121 558 3326",
    "sg:postcode":"B67 7JE",
    "sg:province":"West Midlands",
    "wof:name":"T S Rupra Surgery",
    "wof:placetype":"venue"
},
  "geometry": {"coordinates":[-1.9836449623,52.4989280701],"type":"Point"}
}