{
  "type": "Feature",
  "properties": {
    "iso:country":"GB",
    "sg:address":"96 Nuneaton Road",
    "sg:city":"Nuneaton",
    "sg:classifiers":[
        {
            "category":"Building & Trades",
            "subcategory":"Construction",
            "type":"Services"
        }
    ],
    "sg:phone":"+44 24 7631 9094",
    "sg:postcode":"CV12 9QN",
    "sg:province":"Warwickshire",
    "sg:tags":[
        "builder"
    ],
    "wof:name":"Barry Jacques Building Services",
    "wof:placetype":"venue"
},
  "geometry": {"coordinates":[-1.433209,52.4963],"type":"Point"}
}