{
  "type": "Feature",
  "properties": {
    "addr:full":"27-29 Stilton Drive Manchester Greater Manchester M11 3SB",
    "addr:housenumber":"27-29",
    "addr:postcode":"m11 3sb",
    "addr:street":"Stilton Drive",
    "iso:country":"GB",
    "sg:address":"27-29 Stilton Drive",
    "sg:city":"Manchester",
    "sg:classifiers":[
        {
            "category":"Shopping",
            "subcategory":"Clothing, Apparel, & Fashions",
            "type":"Retail Goods"
        }
    ],
    "sg:phone":"+44 161 223 6083",
    "sg:postcode":"M11 3SB",
    "sg:province":"Greater Manchester",
    "sg:tags":[
        "lingerie"
    ],
    "wof:name":"Just Fancy",
    "wof:placetype":"venue"
},
  "geometry": {"coordinates":[-2.1957969666,53.4774169922],"type":"Point"}
}