{
  "type": "Feature",
  "properties": {
    "addr:full":"1 Grant Road Arbroath Angus DD11 1JY",
    "addr:housenumber":"1",
    "addr:postcode":"dd11 1jy",
    "addr:street":"Grant Road",
    "iso:country":"GB",
    "sg:address":"1 Grant Road",
    "sg:city":"Arbroath",
    "sg:classifiers":[
        {
            "category":"Fast Food",
            "type":"Food & Drink"
        }
    ],
    "sg:phone":"+44 1241 871053",
    "sg:postcode":"DD11 1JY",
    "sg:province":"Angus",
    "sg:tags":[
        "away",
        "meal",
        "outlet",
        "take"
    ],
    "wof:name":"Golden City Take-Away",
    "wof:placetype":"venue"
},
  "geometry": {"coordinates":[-2.582914,56.564758],"type":"Point"}
}