{
  "type": "Feature",
  "properties": {
    "addr:full":"89 Easton St High Wycombe Buckinghamshire HP11 1LT",
    "addr:housenumber":"89",
    "addr:postcode":"hp11 1lt",
    "addr:street":"Easton St",
    "iso:country":"GB",
    "sg:address":"89 Easton St",
    "sg:city":"High Wycombe",
    "sg:classifiers":[
        {
            "category":"Professional",
            "subcategory":"Lawyer & Legal Services",
            "type":"Services"
        }
    ],
    "sg:phone":"+44 1494 440199",
    "sg:postcode":"HP11 1LT",
    "sg:province":"Buckinghamshire",
    "sg:tags":[
        "advice",
        "counselling"
    ],
    "wof:name":"Marlow Pastoral Foundation",
    "wof:placetype":"venue"
},
  "geometry": {"coordinates":[-0.7469040155,51.6279335022],"type":"Point"}
}