{
  "type": "Feature",
  "properties": {
    "iso:country":"GB",
    "sg:address":"48 St Andrews Road, Avonmouth",
    "sg:city":"Bristol",
    "sg:classifiers":[
        {
            "category":"Wholesale",
            "subcategory":"Electrical",
            "type":"Manufacturing & Wholesale Goods"
        }
    ],
    "sg:phone":"+44 117 982 1877",
    "sg:postcode":"BS11 9EU",
    "sg:province":"City of Bristol",
    "sg:tags":[
        "equipment",
        "refrigeration"
    ],
    "wof:name":"Coolcrest Refrigeration Ltd.",
    "wof:placetype":"venue"
},
  "geometry": {"coordinates":[-2.6972439289,51.5013427734],"type":"Point"}
}