{
  "type": "Feature",
  "properties": {
    "iso:country":"GB",
    "sg:address":"102 Emily St",
    "sg:city":"Birmingham",
    "sg:classifiers":[
        {
            "category":"Retail",
            "subcategory":"Auto Repair",
            "type":"Services"
        }
    ],
    "sg:phone":"+44 121 440 8800",
    "sg:postcode":"B12 0XJ",
    "sg:province":"West Midlands",
    "sg:tags":[
        "body",
        "car"
    ],
    "wof:name":"A M S Autorepairs",
    "wof:placetype":"venue"
},
  "geometry": {"coordinates":[-1.8866690397,52.4666099548],"type":"Point"}
}