{
  "type": "Feature",
  "properties": {
    "addr:full":"220 Mile End Road London Greater London E1 4LJ",
    "addr:housenumber":"220",
    "addr:postcode":"e1 4lj",
    "addr:street":"Mile End Road",
    "iso:country":"GB",
    "sg:address":"220 Mile End Road",
    "sg:city":"London",
    "sg:classifiers":[
        {
            "category":"Recreation",
            "subcategory":"Amusement Park",
            "type":"Entertainment"
        }
    ],
    "sg:phone":"+44 20 7790 7884",
    "sg:postcode":"E1 4LJ",
    "sg:province":"Greater London",
    "sg:tags":[
        "arcade"
    ],
    "wof:name":"Funland Amusement Arcade Ltd.",
    "wof:placetype":"venue"
},
  "geometry": {"coordinates":[-0.0472819991,51.5215072632],"type":"Point"}
}