{
  "type": "Feature",
  "properties": {
    "addr:full":"4 Sylvester Parade, Sow Hill Road Beverley East Riding of Yorkshire HU17 8BG",
    "addr:housenumber":"4",
    "addr:postcode":"hu17 8bg",
    "addr:street":"Sylvester Parade Sow Hill Road",
    "iso:country":"GB",
    "sg:address":"4 Sylvester Parade, Sow Hill Road",
    "sg:city":"Beverley",
    "sg:classifiers":[
        {
            "category":"Shopping",
            "subcategory":"Department Store",
            "type":"Retail Goods"
        }
    ],
    "sg:phone":"+44 1482 860206",
    "sg:postcode":"HU17 8BG",
    "sg:province":"East Riding of Yorkshire",
    "wof:name":"Stuart Norman",
    "wof:placetype":"venue"
},
  "geometry": {"coordinates":[-0.443139,53.828861],"type":"Point"}
}