{
  "type": "Feature",
  "properties": {
    "iso:country":"GB",
    "sg:address":"Lyminster Rd",
    "sg:city":"Littlehampton",
    "sg:classifiers":[
        {
            "category":"Social Services",
            "subcategory":"Retirement Home",
            "type":"Services"
        }
    ],
    "sg:phone":"+44 1903 884783",
    "sg:postcode":"BN17 7QQ",
    "sg:province":"West Sussex",
    "sg:tags":[
        "residential",
        "care"
    ],
    "wof:name":"Brooklawns Rest Home",
    "wof:placetype":"venue"
},
  "geometry": {"coordinates":[-0.5424770117,50.8261146545],"type":"Point"}
}