{
  "type": "Feature",
  "properties": {
    "iso:country":"GB",
    "sg:address":"The Homestead, Selby Road, Wistow",
    "sg:city":"Selby",
    "sg:classifiers":[
        {
            "category":"Retail",
            "subcategory":"Driving School",
            "type":"Services"
        }
    ],
    "sg:phone":"+44 1757 268008",
    "sg:postcode":"YO8 3UT",
    "sg:province":"East Riding of Yorkshire",
    "wof:name":"Oaklands School of Motoring",
    "wof:placetype":"venue"
},
  "geometry": {"coordinates":[-1.100945,53.812885],"type":"Point"}
}