{
  "type": "Feature",
  "properties": {
    "iso:country":"GB",
    "sg:address":"84a Townside, Haddenham",
    "sg:city":"Aylesbury",
    "sg:classifiers":[
        {
            "category":"Professional",
            "subcategory":"Accounting & Tax Preparation",
            "type":"Services"
        }
    ],
    "sg:postcode":"HP17 8AW",
    "sg:province":"Buckinghamshire",
    "sg:tags":[
        "accountant"
    ],
    "wof:name":"Peter G Jeffery",
    "wof:placetype":"venue"
},
  "geometry": {"coordinates":[-0.897059,51.787472],"type":"Point"}
}