{
  "type": "Feature",
  "properties": {
    "iso:country":"GB",
    "sg:address":"347 Edgeley Road, Cheadle Heath",
    "sg:city":"Stockport",
    "sg:classifiers":[
        {
            "category":"Professional",
            "subcategory":"Art Services",
            "type":"Services"
        }
    ],
    "sg:phone":"+44 161 491 6690",
    "sg:postcode":"SK3 0RJ",
    "sg:province":"Cheshire",
    "sg:tags":[
        "photographer"
    ],
    "wof:name":"Silver Image Photography",
    "wof:placetype":"venue"
},
  "geometry": {"coordinates":[-2.191007,53.400112],"type":"Point"}
}