{
  "type": "Feature",
  "properties": {
    "addr:full":"Select Trust Building, 12-14 Masons Avenue Moorgate Greater London EC2V 5BB",
    "addr:housenumber":"12-14",
    "addr:postcode":"ec2v 5bb",
    "addr:street":"Masons Avenue Moorgate",
    "iso:country":"GB",
    "sg:address":"Select Trust Building, 12-14 Masons Avenue",
    "sg:city":"Moorgate",
    "sg:classifiers":[
        {
            "category":"Professional",
            "subcategory":"Employment Agencies",
            "type":"Services"
        }
    ],
    "sg:phone":"+44 20 7726 6726",
    "sg:postcode":"EC2V 5BB",
    "sg:province":"Greater London",
    "sg:tags":[
        "consultant"
    ],
    "wof:name":"K C A Search & Selection",
    "wof:placetype":"venue"
},
  "geometry": {"coordinates":[-0.0905399993,51.5156517029],"type":"Point"}
}