{
  "type": "Feature",
  "properties": {
    "addr:full":"4 Ashley Road Epsom Surrey KT18 5AQ",
    "addr:housenumber":"4",
    "addr:postcode":"kt18 5aq",
    "addr:street":"Ashley Road",
    "iso:country":"GB",
    "sg:address":"4 Ashley Road",
    "sg:city":"Epsom",
    "sg:classifiers":[
        {
            "category":"Health Services",
            "subcategory":"Podiatrist",
            "type":"Services"
        }
    ],
    "sg:phone":"+44 1372 722092",
    "sg:postcode":"KT18 5AQ",
    "sg:province":"Surrey",
    "sg:tags":[
        "podiatrists",
        "chiropodist"
    ],
    "wof:name":"F Hill",
    "wof:placetype":"venue"
},
  "geometry": {"coordinates":[-0.2669099867,51.331905365],"type":"Point"}
}