{
  "type": "Feature",
  "properties": {
    "addr:full":"Croft Pit Yard, Bigrigg Egremont Cumbria CA22 2TX",
    "addr:postcode":"ca22 2tx",
    "addr:street":"Croft",
    "iso:country":"GB",
    "sg:address":"Croft Pit Yard, Bigrigg",
    "sg:city":"Egremont",
    "sg:classifiers":[
        {
            "category":"Home & Garden",
            "subcategory":"Building Materials",
            "type":"Retail Goods"
        }
    ],
    "sg:phone":"+44 1946 810406",
    "sg:postcode":"CA22 2TX",
    "sg:province":"Cumbria",
    "sg:tags":[
        "aggregate",
        "concrete",
        "mixed",
        "shale",
        "supplier",
        "sand",
        "including",
        "ready",
        "gravel"
    ],
    "sg:website":"http://www.hanson.co.uk",
    "wof:name":"Hanson Aggregates Ltd",
    "wof:placetype":"venue"
},
  "geometry": {"coordinates":[-3.5283100605,54.4829177856],"type":"Point"}
}