{
  "type": "Feature",
  "properties": {
    "addr:full":"226 Rochdale Rd Rochdale Lancashire OL16 3BN",
    "addr:housenumber":"226",
    "addr:postcode":"ol16 3bn",
    "addr:street":"Rochdale Rd",
    "iso:country":"GB",
    "sg:address":"226 Rochdale Rd",
    "sg:city":"Rochdale",
    "sg:classifiers":[
        {
            "category":"Food & Beverages",
            "subcategory":"Meat & Fish",
            "type":"Retail Goods"
        }
    ],
    "sg:phone":"+44 1706 650204",
    "sg:postcode":"OL16 3BN",
    "sg:province":"Lancashire",
    "sg:tags":[
        "butcher"
    ],
    "wof:name":"P C Bamford",
    "wof:placetype":"venue"
},
  "geometry": {"coordinates":[-2.124305,53.615818],"type":"Point"}
}