{
  "type": "Feature",
  "properties": {
    "addr:full":"62 High Street Dingwall Highland IV15 9RY",
    "addr:housenumber":"62",
    "addr:postcode":"iv15 9ry",
    "addr:street":"High Street",
    "iso:country":"GB",
    "sg:address":"62 High Street",
    "sg:city":"Dingwall",
    "sg:classifiers":[
        {
            "category":"Food & Beverages",
            "subcategory":"Bakery",
            "type":"Retail Goods"
        }
    ],
    "sg:phone":"+44 1349 863129",
    "sg:postcode":"IV15 9RY",
    "sg:province":"Highland",
    "sg:tags":[
        "baker"
    ],
    "wof:name":"Deas Bakers",
    "wof:placetype":"venue"
},
  "geometry": {"coordinates":[-4.4269552231,57.5952606201],"type":"Point"}
}