{
  "type": "Feature",
  "properties": {
    "iso:country":"GB",
    "sg:address":"271 Upper Brook Street",
    "sg:city":"Manchester",
    "sg:classifiers":[
        {
            "category":"Food & Beverages",
            "subcategory":"Supermarket",
            "type":"Retail Goods"
        }
    ],
    "sg:phone":"+44 161 272 6340",
    "sg:postcode":"M13 0HR",
    "sg:province":"Greater Manchester",
    "sg:tags":[
        "frozen"
    ],
    "wof:name":"Annaman Foods",
    "wof:placetype":"venue"
},
  "geometry": {"coordinates":[-2.221846,53.460918],"type":"Point"}
}