{
  "type": "Feature",
  "properties": {
    "iso:country":"GB",
    "sg:address":"55 Bridgwater Road",
    "sg:city":"Bristol",
    "sg:classifiers":[
        {
            "category":"Building & Trades",
            "subcategory":"Construction",
            "type":"Services"
        }
    ],
    "sg:postcode":"BS13 7AX",
    "sg:province":"City of Bristol",
    "sg:tags":[
        "builder"
    ],
    "wof:name":"S & S Builders",
    "wof:placetype":"venue"
},
  "geometry": {"coordinates":[-2.626466,51.422527],"type":"Point"}
}