{
  "type": "Feature",
  "properties": {
    "addr:full":"77 Christchurch Way London Greater London SE10 0AE",
    "addr:housenumber":"77",
    "addr:postcode":"se10 0ae",
    "addr:street":"Christchurch Way",
    "iso:country":"GB",
    "sg:address":"77 Christchurch Way",
    "sg:city":"London",
    "sg:classifiers":[
        {
            "category":"Retail",
            "subcategory":"Auto Repair",
            "type":"Services"
        }
    ],
    "sg:phone":"+44 20 8858 0057",
    "sg:postcode":"SE10 0AE",
    "sg:province":"Greater London",
    "sg:tags":[
        "bodybuilder",
        "repairer"
    ],
    "wof:name":"Phoenix Coachworks Ltd.",
    "wof:placetype":"venue"
},
  "geometry": {"coordinates":[0.004269,51.48867],"type":"Point"}
}