{
  "type": "Feature",
  "properties": {
    "iso:country":"GB",
    "sg:address":"Bdo Stoy Hayward, Beneficial Building, 28 Paradise Circus",
    "sg:city":"Birmingham",
    "sg:classifiers":[
        {
            "category":"Home & Garden",
            "subcategory":"Building Materials",
            "type":"Retail Goods"
        }
    ],
    "sg:postcode":"B1 2BJ",
    "sg:province":"West Midlands",
    "sg:tags":[
        "fencing"
    ],
    "wof:name":"Telford Fencing Ltd",
    "wof:placetype":"venue"
},
  "geometry": {"coordinates":[-1.908604,52.478596],"type":"Point"}
}