{
  "type": "Feature",
  "properties": {
    "addr:full":"151 Wyke La Bradford West Yorkshire BD12 9EN",
    "addr:housenumber":"151",
    "addr:postcode":"bd12 9en",
    "addr:street":"Wyke La Bradford West",
    "iso:country":"GB",
    "sg:address":"151 Wyke La",
    "sg:city":"Bradford",
    "sg:classifiers":[
        {
            "category":"Shopping",
            "subcategory":"Department Store",
            "type":"Retail Goods"
        }
    ],
    "sg:postcode":"BD12 9EN",
    "sg:province":"West Yorkshire",
    "wof:name":"Jayans Superette",
    "wof:placetype":"venue"
},
  "geometry": {"coordinates":[-1.763628,53.737663],"type":"Point"}
}