{
  "type": "Feature",
  "properties": {
    "iso:country":"GB",
    "sg:address":"9 Gleneagles Avenue, Bridge Of Don",
    "sg:city":"Aberdeen",
    "sg:classifiers":[
        {
            "category":"Building & Trades",
            "subcategory":"Plumbing",
            "type":"Services"
        }
    ],
    "sg:phone":"+44 1224 703207",
    "sg:postcode":"AB22 8SH",
    "sg:province":"Aberdeen City",
    "sg:tags":[
        "plumber",
        "heating"
    ],
    "wof:name":"JOHN BUCHAN PLUMBING & HEATING LTD",
    "wof:placetype":"venue"
},
  "geometry": {"coordinates":[-2.11208,57.186306],"type":"Point"}
}