{
  "type": "Feature",
  "properties": {
    "iso:country":"GB",
    "sg:address":"26 Seymour St",
    "sg:city":"London",
    "sg:classifiers":[
        {
            "category":"Real Estate",
            "subcategory":"Real Estate Agent",
            "type":"Services"
        }
    ],
    "sg:postcode":"W1H 7JA",
    "sg:province":"Greater London",
    "wof:name":"Blair,David,",
    "wof:placetype":"venue"
},
  "geometry": {"coordinates":[-0.158236,51.514908],"type":"Point"}
}