{
  "type": "Feature",
  "properties": {
    "iso:country":"GB",
    "sg:address":"20 The Parade, Northgate",
    "sg:city":"Crawley",
    "sg:classifiers":[
        {
            "category":"Professional",
            "subcategory":"Management & Consulting",
            "type":"Services"
        }
    ],
    "sg:phone":"+44 1293 613122",
    "sg:postcode":"RH10 8DT",
    "sg:province":"Surrey",
    "sg:tags":[
        "fire",
        "consultant",
        "protection"
    ],
    "wof:name":"Scot Fire Ltd.",
    "wof:placetype":"venue"
},
  "geometry": {"coordinates":[-0.184753,51.118458],"type":"Point"}
}