{
  "type": "Feature",
  "properties": {
    "addr:full":"Downs Road Seaford East Sussex BN25 4QL",
    "addr:postcode":"bn25 4ql",
    "addr:street":"Downs Road",
    "iso:country":"GB",
    "sg:address":"Downs Road",
    "sg:city":"Seaford",
    "sg:classifiers":[
        {
            "category":"Education",
            "subcategory":"School",
            "type":"Public Place"
        }
    ],
    "sg:phone":"+44 1323 897815",
    "sg:postcode":"BN25 4QL",
    "sg:province":"East Sussex",
    "sg:tags":[
        "local",
        "authority"
    ],
    "wof:name":"Tower House",
    "wof:placetype":"venue"
},
  "geometry": {"coordinates":[0.1139950007,50.7745437622],"type":"Point"}
}