{
  "type": "Feature",
  "properties": {
    "addr:full":"65 Dudley Street Luton Bedfordshire LU2 0NP",
    "addr:housenumber":"65",
    "addr:postcode":"lu2 0np",
    "addr:street":"Dudley Street",
    "iso:country":"GB",
    "sg:address":"65 Dudley Street",
    "sg:city":"Luton",
    "sg:classifiers":[
        {
            "category":"Shopping",
            "subcategory":"Stationery & Office Supplies",
            "type":"Retail Goods"
        },
        {
            "category":"Manufacturing",
            "subcategory":"Paper Products",
            "type":"Manufacturing & Wholesale Goods"
        }
    ],
    "sg:phone":"+44 1582 425512",
    "sg:postcode":"LU2 0NP",
    "sg:province":"Bedfordshire",
    "sg:tags":[
        "box",
        "carton",
        "cardboard"
    ],
    "wof:name":"A1 Boxes",
    "wof:placetype":"venue"
},
  "geometry": {"coordinates":[-0.4157190025,51.8846702576],"type":"Point"}
}