{
  "type": "Feature",
  "properties": {
    "addr:full":"33 Splott Road Cardiff Cardiff CF24 2BU",
    "addr:housenumber":"33",
    "addr:postcode":"cf24 2bu",
    "addr:street":"Splott Road",
    "iso:country":"GB",
    "sg:address":"33 Splott Road",
    "sg:city":"Cardiff",
    "sg:classifiers":[
        {
            "category":"Fast Food",
            "type":"Food & Drink"
        }
    ],
    "sg:phone":"+44 29 2046 3900",
    "sg:postcode":"CF24 2BU",
    "sg:province":"Cardiff",
    "sg:tags":[
        "away",
        "take"
    ],
    "wof:name":"Imperial Cafe",
    "wof:placetype":"venue"
},
  "geometry": {"coordinates":[-3.1523249149,51.4837989807],"type":"Point"}
}