{
  "type": "Feature",
  "properties": {
    "addr:full":"19a Derwen Road, Tumble Llanelli Carmarthenshire SA14 6HG",
    "addr:housenumber":"19a",
    "addr:postcode":"sa14 6hg",
    "addr:street":"Derwen Road",
    "iso:country":"GB",
    "sg:address":"19a Derwen Road, Tumble",
    "sg:city":"Llanelli",
    "sg:classifiers":[
        {
            "category":"Personal",
            "subcategory":"Beauty Salon",
            "type":"Services"
        }
    ],
    "sg:phone":"+44 1269 841328",
    "sg:postcode":"SA14 6HG",
    "sg:province":"Carmarthenshire",
    "sg:tags":[
        "unisex",
        "hairdresser"
    ],
    "wof:name":"Gills Hairdressers",
    "wof:placetype":"venue"
},
  "geometry": {"coordinates":[-4.1306300163,51.790561676],"type":"Point"}
}