{
  "type": "Feature",
  "properties": {
    "addr:full":"83 Ryelands Road Lancaster Lancashire LA1 2QZ",
    "addr:housenumber":"83",
    "addr:postcode":"la1 2qz",
    "addr:street":"Ryelands Road",
    "iso:country":"GB",
    "sg:address":"83 Ryelands Road",
    "sg:city":"Lancaster",
    "sg:classifiers":[
        {
            "category":"Personal",
            "type":"Services"
        }
    ],
    "sg:postcode":"LA1 2QZ",
    "sg:province":"Lancashire",
    "sg:tags":[
        "kiss-o-grams"
    ],
    "wof:name":"Crazy Girls",
    "wof:placetype":"venue"
},
  "geometry": {"coordinates":[-2.811828,54.060078],"type":"Point"}
}