{
  "type": "Feature",
  "properties": {
    "addr:full":"North Medrox Farm, Cumbernauld Glasgow Falkirk G67 4HH",
    "addr:postcode":"g67 4hh",
    "addr:street":"North",
    "iso:country":"GB",
    "sg:address":"North Medrox Farm, Cumbernauld",
    "sg:city":"Glasgow",
    "sg:classifiers":[
        {
            "category":"Farming",
            "subcategory":"Livestock Farm",
            "type":"Manufacturing & Wholesale Goods"
        }
    ],
    "sg:phone":"+44 1236 872387",
    "sg:postcode":"G67 4HH",
    "sg:province":"Falkirk",
    "sg:tags":[
        "others"
    ],
    "wof:name":"J Johnston & Son",
    "wof:placetype":"venue"
},
  "geometry": {"coordinates":[-4.02783,55.936272],"type":"Point"}
}