{
  "type": "Feature",
  "properties": {
    "iso:country":"GB",
    "sg:address":"Petersfield Rd",
    "sg:city":"Havant",
    "sg:classifiers":[
        {
            "category":"Place Of Worship",
            "type":"Public Place"
        }
    ],
    "sg:phone":"+44 23 9247 3787",
    "sg:postcode":"PO9 2HU",
    "sg:province":"Hampshire",
    "wof:name":"Havant Methodist Church & Pastoral Centre",
    "wof:placetype":"venue"
},
  "geometry": {"coordinates":[-0.9783729911,50.8638458252],"type":"Point"}
}