{
  "type": "Feature",
  "properties": {
    "iso:country":"GB",
    "sg:address":"Royds Lane, Ring Road",
    "sg:city":"Leeds",
    "sg:classifiers":[
        {
            "category":"Wholesale",
            "subcategory":"Non-durable Goods",
            "type":"Manufacturing & Wholesale Goods"
        }
    ],
    "sg:phone":"+44 113 263 3341",
    "sg:postcode":"LS12 6HU",
    "sg:province":"West Yorkshire",
    "sg:tags":[
        "carry",
        "cash"
    ],
    "wof:name":"Makro Self Service Wholesalers Ltd.",
    "wof:placetype":"venue"
},
  "geometry": {"coordinates":[-1.590834,53.781582],"type":"Point"}
}