{
  "type": "Feature",
  "properties": {
    "addr:full":"20 The Mead Business Centre, Mead Lane Hertford Hertfordshire SG13 7BJ",
    "addr:housenumber":"20;business centre",
    "addr:postcode":"sg13 7bj",
    "addr:street":"The Mead;Mead Lane",
    "iso:country":"GB",
    "sg:address":"20 The Mead Business Centre, Mead Lane",
    "sg:city":"Hertford",
    "sg:classifiers":[
        {
            "category":"Food & Beverages",
            "subcategory":"Bakery",
            "type":"Retail Goods"
        }
    ],
    "sg:phone":"+44 1992 551075",
    "sg:postcode":"SG13 7BJ",
    "sg:province":"Hertfordshire",
    "sg:tags":[
        "confectionery"
    ],
    "wof:name":"The Fine Confectionery Co. Ltd.",
    "wof:placetype":"venue"
},
  "geometry": {"coordinates":[-0.045925,51.782917],"type":"Point"}
}