{
  "type": "Feature",
  "properties": {
    "addr:full":"493 Manchester Road, Stocksbridge Sheffield Derbyshire S30 5DH",
    "addr:housenumber":"493",
    "addr:postcode":"s30 5dh",
    "addr:street":"Manchester Road",
    "iso:country":"GB",
    "sg:address":"493 Manchester Road, Stocksbridge",
    "sg:city":"Sheffield",
    "sg:classifiers":[
        {
            "category":"Food & Beverages",
            "subcategory":"Supermarket",
            "type":"Retail Goods"
        }
    ],
    "sg:phone":"+44 114 288 4543",
    "sg:postcode":"S30 5DH",
    "sg:province":"Derbyshire",
    "wof:name":"Sheffield Co-Operative Society Ltd.",
    "wof:placetype":"venue"
},
  "geometry": {"coordinates":[-1.591070056,53.4819717407],"type":"Point"}
}