{
  "type": "Feature",
  "properties": {
    "iso:country":"GB",
    "sg:address":"10 The Square",
    "sg:city":"Market Harborough",
    "sg:classifiers":[
        {
            "category":"Professional",
            "subcategory":"Secretarial Services",
            "type":"Services"
        }
    ],
    "sg:phone":"+44 1858 463588",
    "sg:postcode":"LE16 7PA",
    "sg:province":"Leicestershire",
    "wof:name":"Telfax Business Services",
    "wof:placetype":"venue"
},
  "geometry": {"coordinates":[-0.920241,52.477779],"type":"Point"}
}