{
  "type": "Feature",
  "properties": {
    "addr:full":"466 Armstrong Road Newcastle-upon-tyne Northumberland NE15 6BY",
    "addr:housenumber":"466",
    "addr:postcode":"ne15 6by",
    "addr:street":"Armstrong Road",
    "iso:country":"GB",
    "sg:address":"466 Armstrong Road",
    "sg:city":"Newcastle-upon-tyne",
    "sg:classifiers":[
        {
            "category":"Farming",
            "subcategory":"Nursery",
            "type":"Manufacturing & Wholesale Goods"
        },
        {
            "category":"Government",
            "subcategory":"Post Office",
            "type":"Public Place"
        }
    ],
    "sg:phone":"+44 191 274 2656",
    "sg:postcode":"NE15 6BY",
    "sg:province":"Northumberland",
    "sg:tags":[
        "creche"
    ],
    "wof:name":"Armstrong Road Sub Post Office",
    "wof:placetype":"venue"
},
  "geometry": {"coordinates":[-1.6802150011,54.9709091187],"type":"Point"}
}