{
  "type": "Feature",
  "properties": {
    "iso:country":"GB",
    "sg:address":"20 Park Av",
    "sg:city":"Dover",
    "sg:classifiers":[
        {
            "category":"Organizations",
            "subcategory":"Religious Organization",
            "type":"Services"
        }
    ],
    "sg:phone":"+44 1304 206807",
    "sg:postcode":"CT16 1HE",
    "sg:province":"Kent",
    "sg:tags":[
        "organisation"
    ],
    "wof:name":"St Ursulas Convent",
    "wof:placetype":"venue"
},
  "geometry": {"coordinates":[1.310109973,51.1326255798],"type":"Point"}
}