{
  "type": "Feature",
  "properties": {
    "addr:full":"177 Queens Road London Greater London SE15 2ND",
    "addr:housenumber":"177",
    "addr:postcode":"se15 2nd",
    "addr:street":"Queens Road",
    "iso:country":"GB",
    "sg:address":"177 Queens Road",
    "sg:city":"London",
    "sg:classifiers":[
        {
            "category":"Home & Garden",
            "subcategory":"Hardware",
            "type":"Retail Goods"
        }
    ],
    "sg:phone":"+44 20 7652 1029",
    "sg:postcode":"SE15 2ND",
    "sg:province":"Greater London",
    "sg:tags":[
        "retailer",
        "diy"
    ],
    "wof:name":"Eldorado D I Y",
    "wof:placetype":"venue"
},
  "geometry": {"coordinates":[-0.0586,51.473415],"type":"Point"}
}