{
  "type": "Feature",
  "properties": {
    "addr:full":"3 Ovenden Road Halifax West Yorkshire HX3 5PN",
    "addr:housenumber":"3",
    "addr:postcode":"hx3 5pn",
    "addr:street":"Ovenden Road",
    "iso:country":"GB",
    "sg:address":"3 Ovenden Road",
    "sg:city":"Halifax",
    "sg:classifiers":[
        {
            "category":"Professional",
            "type":"Services"
        }
    ],
    "sg:phone":"+44 1422 368000",
    "sg:postcode":"HX3 5PN",
    "sg:province":"West Yorkshire",
    "sg:tags":[
        "repair",
        "tech",
        "maintenance"
    ],
    "wof:name":"Computer Warehouse",
    "wof:placetype":"venue"
},
  "geometry": {"coordinates":[-1.87417,53.735798],"type":"Point"}
}