{
  "type": "Feature",
  "properties": {
    "addr:full":"Charlton Cross, Whitstone Rd Shepton Mallet Somerset BA4 5PT",
    "addr:postcode":"ba4 5pt",
    "addr:street":"Charlton;Whitstone Rd",
    "iso:country":"GB",
    "sg:address":"Charlton Cross, Whitstone Rd",
    "sg:city":"Shepton Mallet",
    "sg:classifiers":[
        {
            "category":"Autos & Motor Vehicles",
            "subcategory":"Automobile Sales",
            "type":"Retail Goods"
        }
    ],
    "sg:phone":"+44 1749 342029",
    "sg:postcode":"BA4 5PT",
    "sg:province":"Somerset",
    "sg:tags":[
        "commercial"
    ],
    "wof:name":"Malcolm Stevens",
    "wof:placetype":"venue"
},
  "geometry": {"coordinates":[-2.5467779636,51.1897315979],"type":"Point"}
}