{
  "type": "Feature",
  "properties": {
    "addr:full":"1-5 Mill Place Cleethorpes Lincolnshire DN35 8ND",
    "addr:housenumber":"1-5",
    "addr:postcode":"dn35 8nd",
    "addr:street":"Mill Place Cleethorpes",
    "iso:country":"GB",
    "sg:address":"1-5 Mill Place",
    "sg:city":"Cleethorpes",
    "sg:classifiers":[
        {
            "category":"Wholesale",
            "subcategory":"Construction Materials",
            "type":"Manufacturing & Wholesale Goods"
        }
    ],
    "sg:postcode":"DN35 8ND",
    "sg:province":"Lincolnshire",
    "sg:tags":[
        "merchant",
        "glass"
    ],
    "wof:name":"S & S Leisure Ltd.",
    "wof:placetype":"venue"
},
  "geometry": {"coordinates":[-0.0296410006,53.5601119995],"type":"Point"}
}