{
  "type": "Feature",
  "properties": {
    "addr:full":"Beck Yat, Lamplugh Workington Cumbria CA14 4SF",
    "addr:postcode":"ca14 4sf",
    "addr:street":"Beck",
    "iso:country":"GB",
    "sg:address":"Beck Yat, Lamplugh",
    "sg:city":"Workington",
    "sg:classifiers":[
        {
            "category":"Building & Trades",
            "subcategory":"Construction",
            "type":"Services"
        }
    ],
    "sg:phone":"+44 1946 861776",
    "sg:postcode":"CA14 4SF",
    "sg:province":"Cumbria",
    "sg:tags":[
        "builder"
    ],
    "wof:name":"W.R Richardson",
    "wof:placetype":"venue"
},
  "geometry": {"coordinates":[-3.410939,54.575375],"type":"Point"}
}