{
  "type": "Feature",
  "properties": {
    "iso:country":"GB",
    "sg:address":"4 Devonshire Rd",
    "sg:city":"Chiswick",
    "sg:classifiers":[
        {
            "category":"Communications",
            "type":"Services"
        }
    ],
    "sg:phone":"+44 20 8987 0225",
    "sg:postcode":"W4 2HD",
    "sg:province":"Greater London",
    "sg:tags":[
        "data",
        "network"
    ],
    "wof:name":"Syskonnect",
    "wof:placetype":"venue"
},
  "geometry": {"coordinates":[-0.255818,51.491989],"type":"Point"}
}