{
  "type": "Feature",
  "properties": {
    "iso:country":"GB",
    "sg:address":"19-21 Uplands Crescent, Uplands",
    "sg:city":"Swansea",
    "sg:classifiers":[
        {
            "category":"Education",
            "subcategory":"Special Training",
            "type":"Public Place"
        }
    ],
    "sg:phone":"+44 1792 464103",
    "sg:postcode":"SA2 0NX",
    "sg:province":"Swansea",
    "sg:tags":[
        "school",
        "language"
    ],
    "wof:name":"English Studies Centre",
    "wof:placetype":"venue"
},
  "geometry": {"coordinates":[-3.964663,51.618183],"type":"Point"}
}