{
  "type": "Feature",
  "properties": {
    "addr:full":"3 Market Street Hexham Northumberland NE46 2NS",
    "addr:housenumber":"3",
    "addr:postcode":"ne46 2ns",
    "addr:street":"Market Street",
    "iso:country":"GB",
    "sg:address":"3 Market Street",
    "sg:city":"Hexham",
    "sg:classifiers":[
        {
            "category":"Professional",
            "subcategory":"Business Services",
            "type":"Services"
        }
    ],
    "sg:postcode":"NE46 2NS",
    "sg:province":"Northumberland",
    "sg:tags":[
        "import",
        "export",
        "agent"
    ],
    "wof:name":"Ritter Outdoor Ltd.",
    "wof:placetype":"venue"
},
  "geometry": {"coordinates":[-2.101949,54.972271],"type":"Point"}
}