{
  "type": "Feature",
  "properties": {
    "addr:full":"160 Stratford Road, Shirley Solihull West Midlands B90 3BD",
    "addr:housenumber":"160",
    "addr:postcode":"b90 3bd",
    "addr:street":"Stratford Road",
    "iso:country":"GB",
    "sg:address":"160 Stratford Road, Shirley",
    "sg:city":"Solihull",
    "sg:classifiers":[
        {
            "category":"Shopping",
            "subcategory":"Mobile Phones",
            "type":"Retail Goods"
        }
    ],
    "sg:phone":"+44 121 744 0707",
    "sg:postcode":"B90 3BD",
    "sg:province":"West Midlands",
    "sg:tags":[
        "supplier"
    ],
    "wof:name":"INTERCITY MOBILE COMMUNICATIONS LTD",
    "wof:placetype":"venue"
},
  "geometry": {"coordinates":[-1.828347,52.413757],"type":"Point"}
}