{
  "type": "Feature",
  "properties": {
    "iso:country":"GB",
    "sg:address":"36 Anson Road",
    "sg:city":"Manchester",
    "sg:classifiers":[
        {
            "category":"Professional",
            "subcategory":"Engineering",
            "type":"Services"
        }
    ],
    "sg:phone":"+44 161 335 9734",
    "sg:postcode":"M34 2HL",
    "sg:province":"Greater Manchester",
    "sg:tags":[
        "gas",
        "engineer"
    ],
    "wof:name":"Gas Master",
    "wof:placetype":"venue"
},
  "geometry": {"coordinates":[-2.145366,53.451107],"type":"Point"}
}