{
  "type": "Feature",
  "properties": {
    "addr:full":"2 Bore Street Lichfield Staffordshire WS13 6LL",
    "addr:housenumber":"2",
    "addr:postcode":"ws13 6ll",
    "addr:street":"Bore Street",
    "iso:country":"GB",
    "sg:address":"2 Bore Street",
    "sg:city":"Lichfield",
    "sg:classifiers":[
        {
            "category":"Shopping",
            "subcategory":"Clothing, Apparel, & Fashions",
            "type":"Retail Goods"
        }
    ],
    "sg:phone":"+44 1543 262264",
    "sg:postcode":"WS13 6LL",
    "sg:province":"Staffordshire",
    "sg:tags":[
        "menswear"
    ],
    "wof:name":"Taylers",
    "wof:placetype":"venue"
},
  "geometry": {"coordinates":[-1.8288060427,52.6821136475],"type":"Point"}
}