{
  "type": "Feature",
  "properties": {
    "addr:full":"Southampton Road Salisbury Wiltshire SP1 2JS",
    "addr:postcode":"sp1 2js",
    "addr:street":"Southampton Road",
    "iso:country":"GB",
    "sg:address":"Southampton Road",
    "sg:city":"Salisbury",
    "sg:classifiers":[
        {
            "category":"Autos & Motor Vehicles",
            "subcategory":"Automobile Sales",
            "type":"Retail Goods"
        }
    ],
    "sg:phone":"+44 1722 411555",
    "sg:postcode":"SP1 2JS",
    "sg:province":"Wiltshire",
    "sg:tags":[
        "car"
    ],
    "wof:name":"Caffyns Plc",
    "wof:placetype":"venue"
},
  "geometry": {"coordinates":[-1.77758,51.061256],"type":"Point"}
}