{
  "type": "Feature",
  "properties": {
    "addr:full":"10b Callieburn Road, Bishopbriggs Glasgow East Dunbartonshire G64 1TJ",
    "addr:housenumber":"10b",
    "addr:postcode":"g64 1tj",
    "addr:street":"Callieburn Road",
    "iso:country":"GB",
    "sg:address":"10b Callieburn Road, Bishopbriggs",
    "sg:city":"Glasgow",
    "sg:classifiers":[
        {
            "category":"Personal",
            "subcategory":"Beauty Salon",
            "type":"Services"
        }
    ],
    "sg:phone":"+44 141 762 2300",
    "sg:postcode":"G64 1TJ",
    "sg:province":"East Dunbartonshire",
    "sg:tags":[
        "unisex",
        "hairdresser"
    ],
    "wof:name":"Hair by Michelle",
    "wof:placetype":"venue"
},
  "geometry": {"coordinates":[-4.21759,55.902416],"type":"Point"}
}