{
  "type": "Feature",
  "properties": {
    "addr:full":"Charles Ho, 148 Gt Charles St Birmingham West Midlands B3 3HT",
    "addr:housenumber":"148",
    "addr:postcode":"b3 3ht",
    "addr:street":"Gt Charles St",
    "iso:country":"GB",
    "sg:address":"Charles Ho, 148 Gt Charles St",
    "sg:city":"Birmingham",
    "sg:classifiers":[
        {
            "category":"Professional",
            "subcategory":"Management & Consulting",
            "type":"Services"
        }
    ],
    "sg:postcode":"B3 3HT",
    "sg:province":"West Midlands",
    "sg:tags":[
        "consultant",
        "business"
    ],
    "wof:name":"G H M Associates Ltd",
    "wof:placetype":"venue"
},
  "geometry": {"coordinates":[-1.9046200514,52.4817390442],"type":"Point"}
}