{
  "type": "Feature",
  "properties": {
    "addr:full":"Waterloo Mill, Howden Road Keighley North Yorkshire BD20 5RL",
    "addr:postcode":"bd20 5rl",
    "addr:street":"Waterloo;Howden Road",
    "iso:country":"GB",
    "sg:address":"Waterloo Mill, Howden Road",
    "sg:city":"Keighley",
    "sg:classifiers":[
        {
            "category":"Retail",
            "subcategory":"Auto Repair",
            "type":"Services"
        }
    ],
    "sg:postcode":"BD20 5RL",
    "sg:province":"North Yorkshire",
    "sg:tags":[
        "modification",
        "garage"
    ],
    "wof:name":"Wainwright Bros of Silsden",
    "wof:placetype":"venue"
},
  "geometry": {"coordinates":[-1.90607,53.892921],"type":"Point"}
}