{
  "type": "Feature",
  "properties": {
    "addr:full":"35 Spratt Hall Road, Wanstead London Greater London E11 2RQ",
    "addr:housenumber":"35",
    "addr:postcode":"e11 2rq",
    "addr:street":"Spratt Hall Road",
    "iso:country":"GB",
    "sg:address":"35 Spratt Hall Road, Wanstead",
    "sg:city":"London",
    "sg:classifiers":[
        {
            "category":"Health Services",
            "subcategory":"Podiatrist",
            "type":"Services"
        }
    ],
    "sg:postcode":"E11 2RQ",
    "sg:province":"Greater London",
    "sg:tags":[
        "podiatrists",
        "chiropodist"
    ],
    "wof:name":"J M George",
    "wof:placetype":"venue"
},
  "geometry": {"coordinates":[0.0235430002,51.5766296387],"type":"Point"}
}