{
  "type": "Feature",
  "properties": {
    "iso:country":"GB",
    "sg:address":"Maidstone Road",
    "sg:city":"Chatham",
    "sg:classifiers":[
        {
            "category":"Travel",
            "subcategory":"Hotels & Motels",
            "type":"Entertainment"
        }
    ],
    "sg:postcode":"ME5 9SF",
    "sg:province":"Kent",
    "wof:name":"Travelrest Services Ltd.",
    "wof:placetype":"venue"
},
  "geometry": {"coordinates":[0.505516,51.339432],"type":"Point"}
}