{
  "type": "Feature",
  "properties": {
    "addr:full":"Staple Ho, Staple Gardens Winchester Hampshire SO23 9EJ",
    "addr:postcode":"so23 9ej",
    "iso:country":"GB",
    "sg:address":"Staple Ho, Staple Gardens",
    "sg:city":"Winchester",
    "sg:classifiers":[
        {
            "category":"Professional",
            "subcategory":"Accounting & Tax Preparation",
            "type":"Services"
        }
    ],
    "sg:phone":"+44 1962 844744",
    "sg:postcode":"SO23 9EJ",
    "sg:province":"Hampshire",
    "sg:tags":[
        "accountant"
    ],
    "wof:name":"R M Senior",
    "wof:placetype":"venue"
},
  "geometry": {"coordinates":[-1.316809,51.063068],"type":"Point"}
}