{
  "type": "Feature",
  "properties": {
    "addr:full":"23 Park Lane Swindon Wiltshire SN1 5EL",
    "addr:housenumber":"23",
    "addr:postcode":"sn1 5el",
    "addr:street":"Park Lane",
    "iso:country":"GB",
    "sg:address":"23 Park Lane",
    "sg:city":"Swindon",
    "sg:classifiers":[
        {
            "category":"Social Services",
            "subcategory":"Retirement Home",
            "type":"Services"
        }
    ],
    "sg:phone":"+44 1793 496458",
    "sg:postcode":"SN1 5EL",
    "sg:province":"Wiltshire",
    "sg:tags":[
        "residential",
        "care"
    ],
    "wof:name":"The Laurel Residential Home",
    "wof:placetype":"venue"
},
  "geometry": {"coordinates":[-1.796781,51.55983],"type":"Point"}
}