{
  "type": "Feature",
  "properties": {
    "addr:full":"Furlong Business Centre, The Furlong Berry Hill Ind Est Droitwich Worcestershire WR9 9AH",
    "addr:postcode":"wr9 9ah",
    "addr:street":"The Furlong;Hill",
    "iso:country":"GB",
    "sg:address":"Furlong Business Centre, The Furlong Berry Hill Ind Est",
    "sg:city":"Droitwich",
    "sg:classifiers":[
        {
            "category":"Shopping",
            "subcategory":"Optical Goods",
            "type":"Retail Goods"
        }
    ],
    "sg:phone":"+44 1905 795657",
    "sg:postcode":"WR9 9AH",
    "sg:province":"Worcestershire",
    "wof:name":"Azincourt Laser",
    "wof:placetype":"venue"
},
  "geometry": {"coordinates":[-2.1564879417,52.2680778503],"type":"Point"}
}