{
  "type": "Feature",
  "properties": {
    "addr:full":"Newmans Row, Battle Hill Hexham Northumberland NE46 1BB",
    "addr:postcode":"ne46 1bb",
    "addr:street":"Newmans Row Battle Hill",
    "iso:country":"GB",
    "sg:address":"Newmans Row, Battle Hill",
    "sg:city":"Hexham",
    "sg:classifiers":[
        {
            "category":"Retail",
            "subcategory":"Driving School",
            "type":"Services"
        }
    ],
    "sg:postcode":"NE46 1BB",
    "sg:province":"Northumberland",
    "wof:name":"Learners Motor School",
    "wof:placetype":"venue"
},
  "geometry": {"coordinates":[-2.1012940407,54.970035553],"type":"Point"}
}