{
  "type": "Feature",
  "properties": {
    "iso:country":"GB",
    "sg:address":"Montague Street",
    "sg:city":"Clitheroe",
    "sg:classifiers":[
        {
            "category":"Wholesale",
            "subcategory":"Fruits & Vegetables",
            "type":"Manufacturing & Wholesale Goods"
        }
    ],
    "sg:phone":"+44 1200 422641",
    "sg:postcode":"BB7 2EB",
    "sg:province":"Lancashire",
    "wof:name":"D N D PENDLE VALLEY PRODUCE",
    "wof:placetype":"venue"
},
  "geometry": {"coordinates":[-2.397159,53.871559],"type":"Point"}
}