{
  "type": "Feature",
  "properties": {
    "iso:country":"GB",
    "sg:address":"Hilltop Industrial Estate",
    "sg:city":"Coalville",
    "sg:classifiers":[
        {
            "category":"Shopping",
            "subcategory":"Stationery & Office Supplies",
            "type":"Retail Goods"
        }
    ],
    "sg:phone":"+44 1530 278140",
    "sg:postcode":"LE67 1TW",
    "sg:province":"Leicestershire",
    "sg:tags":[
        "merchant",
        "paper"
    ],
    "wof:name":"James McNaughton Graphical Papers Ltd.",
    "wof:placetype":"venue"
},
  "geometry": {"coordinates":[-1.333794,52.702091],"type":"Point"}
}