{
  "type": "Feature",
  "properties": {
    "addr:full":"3 Maple Avenue, Newtown, Disley Stockport Cheshire SK12 2RE",
    "addr:housenumber":"3",
    "addr:postcode":"sk12 2re",
    "addr:street":"Maple Avenue",
    "iso:country":"GB",
    "sg:address":"3 Maple Avenue, Newtown, Disley",
    "sg:city":"Stockport",
    "sg:classifiers":[
        {
            "category":"Building & Trades",
            "subcategory":"Construction",
            "type":"Services"
        }
    ],
    "sg:phone":"+44 1663 744893",
    "sg:postcode":"SK12 2RE",
    "sg:province":"Cheshire",
    "sg:tags":[
        "glazier",
        "decorator",
        "painter"
    ],
    "wof:name":"T V Fleet",
    "wof:placetype":"venue"
},
  "geometry": {"coordinates":[-2.0124289989,53.3591308594],"type":"Point"}
}