{
  "type": "Feature",
  "properties": {
    "addr:full":"2 Pembridge Square London Greater London W2 4EW",
    "addr:housenumber":"2",
    "addr:postcode":"w2 4ew",
    "addr:street":"Pembridge Square",
    "iso:country":"GB",
    "sg:address":"2 Pembridge Square",
    "sg:city":"London",
    "sg:classifiers":[
        {
            "category":"Travel",
            "subcategory":"Hotels & Motels",
            "type":"Entertainment"
        }
    ],
    "sg:phone":"+44 20 7727 1316",
    "sg:postcode":"W2 4EW",
    "sg:province":"Greater London",
    "wof:name":"Jupiter Enterprises (Uk) Ltd.",
    "wof:placetype":"venue"
},
  "geometry": {"coordinates":[-0.197277,51.51133],"type":"Point"}
}