{
  "type": "Feature",
  "properties": {
    "iso:country":"GB",
    "sg:address":"1249 Pershore Road, Stirchley",
    "sg:city":"Birmingham",
    "sg:classifiers":[
        {
            "category":"Home & Garden",
            "subcategory":"Hardware",
            "type":"Retail Goods"
        }
    ],
    "sg:phone":"+44 121 459 1300",
    "sg:postcode":"B30 2YT",
    "sg:province":"West Midlands",
    "sg:tags":[
        "tubing",
        "fitting",
        "hose",
        "diy"
    ],
    "wof:name":"Britannia Hose & Rubber Ltd.",
    "wof:placetype":"venue"
},
  "geometry": {"coordinates":[-1.9204579592,52.4306983948],"type":"Point"}
}