{
  "type": "Feature",
  "properties": {
    "addr:full":"33 Queens Road, Formby Liverpool Lancashire L37 2HF",
    "addr:housenumber":"33",
    "addr:postcode":"l37 2hf",
    "addr:street":"Queens Road",
    "iso:country":"GB",
    "sg:address":"33 Queens Road, Formby",
    "sg:city":"Liverpool",
    "sg:classifiers":[
        {
            "category":"Food & Beverages",
            "subcategory":"Liquor & Beverages",
            "type":"Retail Goods"
        }
    ],
    "sg:phone":"+44 1704 872062",
    "sg:postcode":"L37 2HF",
    "sg:province":"Lancashire",
    "sg:tags":[
        "beer",
        "spirit",
        "wines"
    ],
    "wof:name":"Thresher",
    "wof:placetype":"venue"
},
  "geometry": {"coordinates":[-3.073968,53.551105],"type":"Point"}
}