{
  "type": "Feature",
  "properties": {
    "iso:country":"GB",
    "sg:address":"14 Hubbard Close, Twyford",
    "sg:city":"Reading",
    "sg:classifiers":[
        {
            "category":"Professional",
            "subcategory":"Accounting & Tax Preparation",
            "type":"Services"
        }
    ],
    "sg:phone":"+44 118 934 4822",
    "sg:postcode":"RG10 0XU",
    "sg:province":"Berkshire",
    "sg:tags":[
        "accountant"
    ],
    "wof:name":"Bell Court Associates",
    "wof:placetype":"venue"
},
  "geometry": {"coordinates":[-0.855046,51.468109],"type":"Point"}
}