{
  "type": "Feature",
  "properties": {
    "iso:country":"GB",
    "sg:address":"163 Bath St",
    "sg:city":"Glasgow",
    "sg:classifiers":[
        {
            "category":"Government",
            "subcategory":"Police Station",
            "type":"Public Place"
        }
    ],
    "sg:phone":"+44 141 248 1914",
    "sg:postcode":"G2 4SP",
    "sg:province":"Glasgow City",
    "sg:tags":[
        "officer",
        "sheriff"
    ],
    "wof:name":"William G Kay & Co",
    "wof:placetype":"venue"
},
  "geometry": {"coordinates":[-4.261682,55.864326],"type":"Point"}
}