{
  "type": "Feature",
  "properties": {
    "iso:country":"GB",
    "sg:address":"1, Sansedis, Hoovers Lane",
    "sg:city":"Ross-on-wye",
    "sg:classifiers":[
        {
            "category":"Train Station",
            "subcategory":"Rail",
            "type":"Transportation"
        },
        {
            "category":"Retail",
            "subcategory":"Auto Repair",
            "type":"Services"
        }
    ],
    "sg:phone":"+44 1989 750468",
    "sg:postcode":"HR9 5TX",
    "sg:province":"Gloucestershire",
    "sg:tags":[
        "repairs",
        "caravan",
        "commercial",
        "accessory",
        "part",
        "servicing",
        "vehicle"
    ],
    "wof:name":"C & W Motors",
    "wof:placetype":"venue"
},
  "geometry": {"coordinates":[-2.5114378929,51.889831543],"type":"Point"}
}