{
  "type": "Feature",
  "properties": {
    "iso:country":"GB",
    "sg:address":"The Warehouse",
    "sg:city":"Abertillery",
    "sg:classifiers":[
        {
            "category":"Retail",
            "subcategory":"Auto Repair",
            "type":"Services"
        }
    ],
    "sg:phone":"+44 1495 216820",
    "sg:postcode":"NP13 1BS",
    "sg:province":"Blaenau Gwent",
    "sg:tags":[
        "electrician"
    ],
    "wof:name":"Abertillery Auto Electrics",
    "wof:placetype":"venue"
},
  "geometry": {"coordinates":[-3.137623,51.730118],"type":"Point"}
}