{
  "type": "Feature",
  "properties": {
    "addr:full":"6 College Road, Quinton Birmingham West Midlands B32 1AB",
    "addr:housenumber":"6",
    "addr:postcode":"b32 1ab",
    "addr:street":"College Road",
    "iso:country":"GB",
    "sg:address":"6 College Road, Quinton",
    "sg:city":"Birmingham",
    "sg:classifiers":[
        {
            "category":"Professional",
            "subcategory":"Engineering",
            "type":"Services"
        }
    ],
    "sg:phone":"+44 121 422 9876",
    "sg:postcode":"B32 1AB",
    "sg:province":"West Midlands",
    "wof:name":"Redman Components",
    "wof:placetype":"venue"
},
  "geometry": {"coordinates":[-1.996836,52.463444],"type":"Point"}
}