{
  "type": "Feature",
  "properties": {
    "addr:full":"5 Tree Tops, Bromley Cross Bolton Lancashire BL7 9YB",
    "addr:housenumber":"5",
    "addr:postcode":"bl7 9yb",
    "addr:street":"Tree Tops;Cross",
    "iso:country":"GB",
    "sg:address":"5 Tree Tops, Bromley Cross",
    "sg:city":"Bolton",
    "sg:classifiers":[
        {
            "category":"Real Estate",
            "subcategory":"Architect",
            "type":"Services"
        }
    ],
    "sg:postcode":"BL7 9YB",
    "sg:province":"Lancashire",
    "sg:tags":[
        "architectural"
    ],
    "wof:name":"Whittam Building Services",
    "wof:placetype":"venue"
},
  "geometry": {"coordinates":[-2.4092309475,53.6123275757],"type":"Point"}
}