{
  "type": "Feature",
  "properties": {
    "iso:country":"GB",
    "sg:address":"Regent House, 235/241 Regent Street",
    "sg:city":"London",
    "sg:classifiers":[
        {
            "category":"Banks & Credit Unions",
            "subcategory":"Financial Services",
            "type":"Services"
        }
    ],
    "sg:postcode":"W1B 2PS",
    "sg:province":"Greater London",
    "sg:tags":[
        "consultant"
    ],
    "wof:name":"Blue Horseshoe Investments Ltd.",
    "wof:placetype":"venue"
},
  "geometry": {"coordinates":[-0.142449,51.516449],"type":"Point"}
}