{
  "type": "Feature",
  "properties": {
    "iso:country":"GB",
    "sg:address":"Milnwood House, 13 North Parade",
    "sg:city":"Horsham",
    "sg:classifiers":[
        {
            "category":"Professional",
            "subcategory":"Computer Services",
            "type":"Services"
        }
    ],
    "sg:phone":"+44 1403 240303",
    "sg:postcode":"RH12 2BT",
    "sg:province":"West Sussex",
    "sg:tags":[
        "system",
        "software"
    ],
    "wof:name":"Aralia Systems Ltd.",
    "wof:placetype":"venue"
},
  "geometry": {"coordinates":[-0.327944994,51.070690155],"type":"Point"}
}