{
  "type": "Feature",
  "properties": {
    "addr:full":"The Green, Goathland Whitby North Yorkshire YO22 5LX",
    "addr:postcode":"yo22 5lx",
    "addr:street":"The Green Goathland",
    "iso:country":"GB",
    "sg:address":"The Green, Goathland",
    "sg:city":"Whitby",
    "sg:classifiers":[
        {
            "category":"Shopping",
            "subcategory":"Gifts & Souvenirs",
            "type":"Retail Goods"
        }
    ],
    "sg:phone":"+44 1947 896428",
    "sg:postcode":"YO22 5LX",
    "sg:province":"North Yorkshire",
    "sg:tags":[
        "shop"
    ],
    "wof:name":"Goathland Stores",
    "wof:placetype":"venue"
},
  "geometry": {"coordinates":[-0.71884,54.399929],"type":"Point"}
}