{
  "type": "Feature",
  "properties": {
    "addr:full":"29 Heapworth Avenue, Ramsbottom Bury Lancashire BL0 9EH",
    "addr:housenumber":"29",
    "addr:postcode":"bl0 9eh",
    "addr:street":"Heapworth Avenue Ramsbottom",
    "iso:country":"GB",
    "sg:address":"29 Heapworth Avenue, Ramsbottom",
    "sg:city":"Bury",
    "sg:classifiers":[
        {
            "category":"Education",
            "subcategory":"Music School",
            "type":"Public Place"
        }
    ],
    "sg:phone":"+44 1706 826817",
    "sg:postcode":"BL0 9EH",
    "sg:province":"Lancashire",
    "sg:tags":[
        "teacher"
    ],
    "wof:name":"D Martin",
    "wof:placetype":"venue"
},
  "geometry": {"coordinates":[-2.3239700794,53.6467208862],"type":"Point"}
}