{
  "type": "Feature",
  "properties": {
    "addr:full":"2 Broadmead Rd, Three Legged Cross Wimborne Wimborne Dorset BH21 6SA",
    "addr:housenumber":"2",
    "addr:postcode":"bh21 6sa",
    "addr:street":"Broadmead Rd",
    "iso:country":"GB",
    "sg:address":"2 Broadmead Rd, Three Legged Cross Wimborne",
    "sg:city":"Wimborne",
    "sg:classifiers":[
        {
            "category":"Taxi",
            "type":"Transportation"
        }
    ],
    "sg:phone":"+44 1202 889999",
    "sg:postcode":"BH21 6SA",
    "sg:province":"Dorset",
    "sg:tags":[
        "mini",
        "cab"
    ],
    "wof:name":"Broadmead Cars & Taxis",
    "wof:placetype":"venue"
},
  "geometry": {"coordinates":[-1.8800070286,50.8567276001],"type":"Point"}
}