{
  "type": "Feature",
  "properties": {
    "addr:full":"324 Soho Rd Birmingham West Midlands B21 9NA",
    "addr:housenumber":"324",
    "addr:postcode":"b21 9na",
    "addr:street":"Soho Rd",
    "iso:country":"GB",
    "sg:address":"324 Soho Rd",
    "sg:city":"Birmingham",
    "sg:classifiers":[
        {
            "category":"Food & Beverages",
            "subcategory":"Candy",
            "type":"Retail Goods"
        }
    ],
    "sg:phone":"+44 121 551 1911",
    "sg:postcode":"B21 9NA",
    "sg:province":"West Midlands",
    "sg:tags":[
        "confectioner"
    ],
    "wof:name":"Ambala Sweet Centre",
    "wof:placetype":"venue"
},
  "geometry": {"coordinates":[-1.9395190477,52.5043716431],"type":"Point"}
}