{
  "type": "Feature",
  "properties": {
    "addr:full":"1 St Catherines Terrace Hove East Sussex BN3 2RR",
    "addr:housenumber":"1",
    "addr:postcode":"bn3 2rr",
    "addr:street":"St Catherines Terrace",
    "iso:country":"GB",
    "sg:address":"1 St Catherines Terrace",
    "sg:city":"Hove",
    "sg:classifiers":[
        {
            "category":"Professional",
            "subcategory":"Detective & Security Services",
            "type":"Services"
        }
    ],
    "sg:postcode":"BN3 2RR",
    "sg:province":"East Sussex",
    "sg:tags":[
        "agency"
    ],
    "wof:name":"Jay Kays Detective Agency Ltd.",
    "wof:placetype":"venue"
},
  "geometry": {"coordinates":[-0.172765,50.82481],"type":"Point"}
}