{
  "type": "Feature",
  "properties": {
    "addr:full":"7 Ampthill Business Pk, Station Rd, Ampthill Bedford Bedfordshire MK45 2QW",
    "addr:housenumber":"7",
    "addr:postcode":"mk45 2qw",
    "addr:street":"Business Pk Station Rd",
    "iso:country":"GB",
    "sg:address":"7 Ampthill Business Pk, Station Rd, Ampthill",
    "sg:city":"Bedford",
    "sg:classifiers":[
        {
            "category":"Professional",
            "subcategory":"Testing Lab",
            "type":"Services"
        }
    ],
    "sg:phone":"+44 1525 840022",
    "sg:postcode":"MK45 2QW",
    "sg:province":"Bedfordshire",
    "sg:tags":[
        "laboratory"
    ],
    "wof:name":"Laboratory Equipment Service Ltd",
    "wof:placetype":"venue"
},
  "geometry": {"coordinates":[-0.4949940145,52.0279464722],"type":"Point"}
}