{
  "type": "Feature",
  "properties": {
    "addr:full":"305 Whitley Road Whitley Bay Northumberland NE26 2HU",
    "addr:housenumber":"305",
    "addr:postcode":"ne26 2hu",
    "addr:street":"Whitley Road",
    "iso:country":"GB",
    "sg:address":"305 Whitley Road",
    "sg:city":"Whitley Bay",
    "sg:classifiers":[
        {
            "category":"Food & Beverages",
            "subcategory":"Supermarket",
            "type":"Retail Goods"
        }
    ],
    "sg:phone":"+44 191 252 2311",
    "sg:postcode":"NE26 2HU",
    "sg:province":"Northumberland",
    "wof:name":"North Eastern & Cumbrian Co-Op Food Stores",
    "wof:placetype":"venue"
},
  "geometry": {"coordinates":[-1.4472689629,55.0419197083],"type":"Point"}
}