{
  "type": "Feature",
  "properties": {
    "addr:full":"112 Hathersage Rd Birmingham West Midlands B42 2RY",
    "addr:housenumber":"112",
    "addr:postcode":"b42 2ry",
    "addr:street":"Hathersage Rd",
    "iso:country":"GB",
    "sg:address":"112 Hathersage Rd",
    "sg:city":"Birmingham",
    "sg:classifiers":[
        {
            "category":"Building & Trades",
            "subcategory":"Construction",
            "type":"Services"
        }
    ],
    "sg:phone":"+44 121 360 3715",
    "sg:postcode":"B42 2RY",
    "sg:province":"West Midlands",
    "sg:tags":[
        "decorator",
        "painter"
    ],
    "wof:name":"C.A Eurell",
    "wof:placetype":"venue"
},
  "geometry": {"coordinates":[-1.9001100063,52.5363960266],"type":"Point"}
}