{
  "type": "Feature",
  "properties": {
    "iso:country":"GB",
    "sg:address":"33 Walter Road",
    "sg:city":"Swansea",
    "sg:classifiers":[
        {
            "category":"Real Estate",
            "subcategory":"Surveying",
            "type":"Services"
        }
    ],
    "sg:phone":"+44 1792 648881",
    "sg:postcode":"SA1 5NW",
    "sg:province":"Neath Port Talbot",
    "sg:tags":[
        "surveyor",
        "quantity"
    ],
    "wof:name":"Landers Wheelers",
    "wof:placetype":"venue"
},
  "geometry": {"coordinates":[-3.956387,51.619328],"type":"Point"}
}