{
  "type": "Feature",
  "properties": {
    "iso:country":"GB",
    "sg:address":"58 Scarborough Road",
    "sg:city":"Filey",
    "sg:classifiers":[
        {
            "category":"Social Services",
            "subcategory":"Retirement Home",
            "type":"Services"
        }
    ],
    "sg:phone":"+44 1723 512207",
    "sg:postcode":"YO14 9NH",
    "sg:province":"North Yorkshire",
    "sg:tags":[
        "residential",
        "care"
    ],
    "wof:name":"Grovehill House Residential Care Home",
    "wof:placetype":"venue"
},
  "geometry": {"coordinates":[-0.294627,54.213837],"type":"Point"}
}