{
  "type": "Feature",
  "properties": {
    "addr:full":"55 Church Road Hove East Sussex BN3 2BD",
    "addr:housenumber":"55",
    "addr:postcode":"bn3 2bd",
    "addr:street":"Church Road",
    "iso:country":"GB",
    "sg:address":"55 Church Road",
    "sg:city":"Hove",
    "sg:classifiers":[
        {
            "category":"Insurance",
            "subcategory":"Health Insurance",
            "type":"Services"
        }
    ],
    "sg:phone":"+44 1273 728536",
    "sg:postcode":"BN3 2BD",
    "sg:province":"East Sussex",
    "wof:name":"Western Provident Association",
    "wof:placetype":"venue"
},
  "geometry": {"coordinates":[-0.165527001,50.8270950317],"type":"Point"}
}