{
  "type": "Feature",
  "properties": {
    "iso:country":"GB",
    "sg:address":"Jerusalem, Cyfronydd",
    "sg:city":"Welshpool",
    "sg:classifiers":[
        {
            "category":"Freight",
            "type":"Transportation"
        }
    ],
    "sg:phone":"+44 1938 850495",
    "sg:postcode":"SY21 9EW",
    "sg:province":"Shropshire",
    "sg:tags":[
        "forwarders"
    ],
    "wof:name":"A M  & P M  Transportation Ltd.",
    "wof:placetype":"venue"
},
  "geometry": {"coordinates":[-3.2677268982,52.6615447998],"type":"Point"}
}