{
  "type": "Feature",
  "properties": {
    "iso:country":"GB",
    "sg:address":"18a High Street, Middleton Cheney",
    "sg:city":"Banbury",
    "sg:classifiers":[
        {
            "category":"Retail",
            "subcategory":"Veterinary Services",
            "type":"Services"
        }
    ],
    "sg:postcode":"OX17 2PB",
    "sg:province":"Northamptonshire",
    "sg:tags":[
        "surgeon"
    ],
    "wof:name":"Croft Veterinary Centre",
    "wof:placetype":"venue"
},
  "geometry": {"coordinates":[-1.273637,52.073196],"type":"Point"}
}