{
  "type": "Feature",
  "properties": {
    "iso:country":"GB",
    "sg:address":"589 Duke Street",
    "sg:city":"Glasgow",
    "sg:classifiers":[
        {
            "category":"Home & Garden",
            "subcategory":"Household Appliances",
            "type":"Retail Goods"
        }
    ],
    "sg:phone":"+44 141 556 5569",
    "sg:postcode":"G31 1PY",
    "sg:province":"Glasgow City",
    "sg:tags":[
        "electrical",
        "domestic"
    ],
    "wof:name":"J Stepek Ltd.",
    "wof:placetype":"venue"
},
  "geometry": {"coordinates":[-4.215736,55.858658],"type":"Point"}
}