{
  "type": "Feature",
  "properties": {
    "addr:full":"197 Gallowgate Glasgow Glasgow City G1 5DY",
    "addr:housenumber":"197",
    "addr:postcode":"g1 5dy",
    "addr:street":"Gallowgate",
    "iso:country":"GB",
    "sg:address":"197 Gallowgate",
    "sg:city":"Glasgow",
    "sg:classifiers":[
        {
            "category":"Professional",
            "subcategory":"Computer Services",
            "type":"Services"
        }
    ],
    "sg:postcode":"G1 5DY",
    "sg:province":"Glasgow City",
    "sg:tags":[
        "system",
        "software"
    ],
    "wof:name":"Express Components",
    "wof:placetype":"venue"
},
  "geometry": {"coordinates":[-4.238327,55.855736],"type":"Point"}
}