{
  "type": "Feature",
  "properties": {
    "iso:country":"GB",
    "sg:address":"Rake Heath, London Rd, Hillbrow",
    "sg:city":"Liss",
    "sg:classifiers":[
        {
            "category":"Building & Trades",
            "subcategory":"Construction",
            "type":"Services"
        }
    ],
    "sg:phone":"+44 1730 895858",
    "sg:postcode":"GU33 7NT",
    "sg:province":"Hampshire",
    "sg:tags":[
        "worker",
        "metal"
    ],
    "wof:name":"G.B Services",
    "wof:placetype":"venue"
},
  "geometry": {"coordinates":[-0.8754400015,51.0314483643],"type":"Point"}
}