{
  "type": "Feature",
  "properties": {
    "addr:full":"16 The Cross Prestwick South Ayrshire KA9 1AJ",
    "addr:housenumber":"16",
    "addr:postcode":"ka9 1aj",
    "addr:street":"The Cross Prestwick",
    "iso:country":"GB",
    "sg:address":"16 The Cross",
    "sg:city":"Prestwick",
    "sg:classifiers":[
        {
            "category":"Food & Beverages",
            "subcategory":"Meat & Fish",
            "type":"Retail Goods"
        }
    ],
    "sg:phone":"+44 1292 477331",
    "sg:postcode":"KA9 1AJ",
    "sg:province":"South Ayrshire",
    "sg:tags":[
        "butcher"
    ],
    "wof:name":"Laurence Hood",
    "wof:placetype":"venue"
},
  "geometry": {"coordinates":[-4.610784,55.501884],"type":"Point"}
}