{
  "type": "Feature",
  "properties": {
    "addr:full":"46 Main Rd, Sheepy Magna Atherstone Atherstone Leicestershire CV9 3QR",
    "addr:housenumber":"46",
    "addr:postcode":"cv9 3qr",
    "addr:street":"Main Rd",
    "iso:country":"GB",
    "sg:address":"46 Main Rd, Sheepy Magna Atherstone",
    "sg:city":"Atherstone",
    "sg:classifiers":[
        {
            "category":"Communications",
            "subcategory":"Newspaper",
            "type":"Services"
        }
    ],
    "sg:phone":"+44 1827 880089",
    "sg:postcode":"CV9 3QR",
    "sg:province":"Leicestershire",
    "sg:tags":[
        "magazine"
    ],
    "wof:name":"Grapevine",
    "wof:placetype":"venue"
},
  "geometry": {"coordinates":[-1.5193450451,52.6092987061],"type":"Point"}
}