{
  "type": "Feature",
  "properties": {
    "addr:full":"Transperience Way Bradford West Yorkshire BD12 7HQ",
    "addr:postcode":"bd12 7hq",
    "addr:street":"Transperience Way",
    "iso:country":"GB",
    "sg:address":"Transperience Way",
    "sg:city":"Bradford",
    "sg:classifiers":[
        {
            "category":"Landmark",
            "subcategory":"Tourist Attraction",
            "type":"Public Place"
        }
    ],
    "sg:phone":"+44 1274 690909",
    "sg:postcode":"BD12 7HQ",
    "sg:province":"West Yorkshire",
    "sg:tags":[
        "interest"
    ],
    "wof:name":"Transperience Discovery Park",
    "wof:placetype":"venue"
},
  "geometry": {"coordinates":[-1.758306,53.795738],"type":"Point"}
}