{
  "type": "Feature",
  "properties": {
    "iso:country":"GB",
    "sg:address":"Vulcan House Farm, Coopers Grn",
    "sg:city":"Uckfield",
    "sg:classifiers":[
        {
            "category":"Shopping",
            "subcategory":"Used Merchandise",
            "type":"Retail Goods"
        }
    ],
    "sg:postcode":"TN22 4AT",
    "sg:province":"East Sussex",
    "sg:tags":[
        "shop",
        "second-hand"
    ],
    "wof:name":"Vulcan House Furniture",
    "wof:placetype":"venue"
},
  "geometry": {"coordinates":[0.09665,50.971813],"type":"Point"}
}