{
  "type": "Feature",
  "properties": {
    "iso:country":"GB",
    "sg:address":"1 East Wonford Hill",
    "sg:city":"Exeter",
    "sg:classifiers":[
        {
            "category":"Personal",
            "subcategory":"Beauty Salon",
            "type":"Services"
        },
        {
            "category":"Personal",
            "subcategory":"Barber",
            "type":"Services"
        }
    ],
    "sg:phone":"+44 1392 273453",
    "sg:postcode":"EX1 3BS",
    "sg:province":"Devon",
    "sg:tags":[
        "unisex",
        "hairdresser"
    ],
    "wof:name":"Hairlines",
    "wof:placetype":"venue"
},
  "geometry": {"coordinates":[-3.498031,50.721058],"type":"Point"}
}