{
  "type": "Feature",
  "properties": {
    "iso:country":"GB",
    "sg:address":"91 Poole Rd",
    "sg:city":"Bournemouth",
    "sg:classifiers":[
        {
            "category":"Shopping",
            "type":"Retail Goods"
        }
    ],
    "sg:postcode":"BH4 9BB",
    "sg:province":"Dorset",
    "sg:tags":[
        "part",
        "accessory"
    ],
    "wof:name":"Autobitz",
    "wof:placetype":"venue"
},
  "geometry": {"coordinates":[-1.903839,50.72308],"type":"Point"}
}