{
  "type": "Feature",
  "properties": {
    "addr:full":"Crickleaze Farm, Whitestornton Chard Devon TA20 3DR",
    "addr:postcode":"ta20 3dr",
    "addr:street":"Whitestornton",
    "iso:country":"GB",
    "sg:address":"Crickleaze Farm, Whitestornton",
    "sg:city":"Chard",
    "sg:classifiers":[
        {
            "category":"Farming",
            "subcategory":"Dairy Farm",
            "type":"Manufacturing & Wholesale Goods"
        }
    ],
    "sg:phone":"+44 1460 234287",
    "sg:postcode":"TA20 3DR",
    "sg:province":"Devon",
    "wof:name":"J A Hurford & Sons",
    "wof:placetype":"venue"
},
  "geometry": {"coordinates":[-3.0372860432,50.8960533142],"type":"Point"}
}