{
  "type": "Feature",
  "properties": {
    "iso:country":"GB",
    "sg:address":"2 West End Ct",
    "sg:city":"Wrexham",
    "sg:classifiers":[
        {
            "category":"Home & Garden",
            "subcategory":"Building Materials",
            "type":"Retail Goods"
        }
    ],
    "sg:phone":"+44 1829 271411",
    "sg:postcode":"LL13 9YJ",
    "sg:province":"Wrexham",
    "sg:tags":[
        "gate",
        "door",
        "barrier"
    ],
    "wof:name":"Wego System Ltd",
    "wof:placetype":"venue"
},
  "geometry": {"coordinates":[-2.884599,53.075275],"type":"Point"}
}