{
  "type": "Feature",
  "properties": {
    "addr:full":"260 High Street Lincoln Lincolnshire LN2 1JG",
    "addr:housenumber":"260",
    "addr:postcode":"ln2 1jg",
    "addr:street":"High Street",
    "iso:country":"GB",
    "sg:address":"260 High Street",
    "sg:city":"Lincoln",
    "sg:classifiers":[
        {
            "category":"Shopping",
            "subcategory":"Crafts & Fabrics",
            "type":"Retail Goods"
        },
        {
            "category":"Building & Trades",
            "subcategory":"Construction",
            "type":"Services"
        }
    ],
    "sg:phone":"+44 1522 527485",
    "sg:postcode":"LN2 1JG",
    "sg:province":"Lincolnshire",
    "sg:tags":[
        "paint",
        "household",
        "material",
        "art",
        "spraying"
    ],
    "wof:name":"F W Gadsby",
    "wof:placetype":"venue"
},
  "geometry": {"coordinates":[-0.539449,53.23151],"type":"Point"}
}