{
  "type": "Feature",
  "properties": {
    "addr:full":"6 Pikelaw Place, West Pimbo Industrial Estate Skelmersdale Lancashire WN8 9PP",
    "addr:housenumber":"6",
    "addr:postcode":"wn8 9pp",
    "addr:street":"Pikelaw Place West;Industrial Estate",
    "iso:country":"GB",
    "sg:address":"6 Pikelaw Place, West Pimbo Industrial Estate",
    "sg:city":"Skelmersdale",
    "sg:classifiers":[
        {
            "category":"Autos & Motor Vehicles",
            "subcategory":"Automobile Sales",
            "type":"Retail Goods"
        }
    ],
    "sg:phone":"+44 808 100 2760",
    "sg:postcode":"WN8 9PP",
    "sg:province":"Lancashire",
    "sg:tags":[
        "commercial"
    ],
    "wof:name":"Deeside Materials Handling Ltd.",
    "wof:placetype":"venue"
},
  "geometry": {"coordinates":[-2.766349,53.533585],"type":"Point"}
}