{
  "type": "Feature",
  "properties": {
    "addr:full":"15 Pednandrea Penzance Cornwall TR19 7UA",
    "addr:housenumber":"15",
    "addr:postcode":"tr19 7ua",
    "addr:street":"Pednandrea",
    "iso:country":"GB",
    "sg:address":"15 Pednandrea",
    "sg:city":"Penzance",
    "sg:classifiers":[
        {
            "category":"Place Of Worship",
            "type":"Public Place"
        }
    ],
    "sg:phone":"+44 1736 788506",
    "sg:postcode":"TR19 7UA",
    "sg:province":"Cornwall",
    "wof:name":"St. Just Methodist Church",
    "wof:placetype":"venue"
},
  "geometry": {"coordinates":[-5.683874,50.126637],"type":"Point"}
}