{
  "type": "Feature",
  "properties": {
    "iso:country":"GB",
    "sg:address":"6 Trinity Road",
    "sg:city":"Sheerness",
    "sg:classifiers":[
        {
            "category":"Professional",
            "type":"Services"
        },
        {
            "category":"Professional",
            "subcategory":"Computer Services",
            "type":"Services"
        }
    ],
    "sg:postcode":"ME12 2PJ",
    "sg:province":"Kent",
    "sg:tags":[
        "development",
        "repair",
        "tech",
        "maintenance",
        "software"
    ],
    "wof:name":"Fairview Computer Services Ltd",
    "wof:placetype":"venue"
},
  "geometry": {"coordinates":[0.764499,51.43977],"type":"Point"}
}