{
  "type": "Feature",
  "properties": {
    "iso:country":"GB",
    "sg:address":"2 Deane Walk",
    "sg:city":"Bolton",
    "sg:classifiers":[
        {
            "category":"Professional",
            "subcategory":"Lawyer & Legal Services",
            "type":"Services"
        }
    ],
    "sg:phone":"+44 1204 386066",
    "sg:postcode":"BL3 5DG",
    "sg:province":"Lancashire",
    "sg:tags":[
        "advice",
        "counselling"
    ],
    "wof:name":"Neighbour Dispute Service",
    "wof:placetype":"venue"
},
  "geometry": {"coordinates":[-2.437926,53.574238],"type":"Point"}
}