{
  "type": "Feature",
  "properties": {
    "addr:full":"18 The Rosary, Holmer Green High Wycombe Buckinghamshire HP15 6UJ",
    "addr:housenumber":"18",
    "addr:postcode":"hp15 6uj",
    "addr:street":"The",
    "iso:country":"GB",
    "sg:address":"18 The Rosary, Holmer Green",
    "sg:city":"High Wycombe",
    "sg:classifiers":[
        {
            "category":"Wholesale",
            "subcategory":"Vending Machines",
            "type":"Manufacturing & Wholesale Goods"
        }
    ],
    "sg:postcode":"HP15 6UJ",
    "sg:province":"Buckinghamshire",
    "sg:tags":[
        "equipment",
        "mailing"
    ],
    "wof:name":"Mikrojet U K",
    "wof:placetype":"venue"
},
  "geometry": {"coordinates":[-0.698999,51.667145],"type":"Point"}
}