{
  "type": "Feature",
  "properties": {
    "iso:country":"GB",
    "sg:address":"30 Cottage Farm Road, Two Gates",
    "sg:city":"Tamworth",
    "sg:classifiers":[
        {
            "category":"Home & Garden",
            "subcategory":"Garden Supply",
            "type":"Retail Goods"
        },
        {
            "category":"Banks & Credit Unions",
            "subcategory":"Investment Brokerage",
            "type":"Services"
        }
    ],
    "sg:phone":"+44 1827 284014",
    "sg:postcode":"B77 1NN",
    "sg:province":"Staffordshire",
    "sg:tags":[
        "supplier",
        "turf",
        "turfing",
        "contractor"
    ],
    "wof:name":"Ash Landscape Services Turf Supplies",
    "wof:placetype":"venue"
},
  "geometry": {"coordinates":[-1.681757,52.61031],"type":"Point"}
}