{
  "type": "Feature",
  "properties": {
    "addr:full":"200 Soho Road, Handsworth Birmingham West Midlands B21 9LR",
    "addr:housenumber":"200",
    "addr:postcode":"b21 9lr",
    "addr:street":"Soho Road",
    "iso:country":"GB",
    "sg:address":"200 Soho Road, Handsworth",
    "sg:city":"Birmingham",
    "sg:classifiers":[
        {
            "category":"Shopping",
            "subcategory":"Crafts & Fabrics",
            "type":"Retail Goods"
        }
    ],
    "sg:phone":"+44 121 523 7724",
    "sg:postcode":"B21 9LR",
    "sg:province":"West Midlands",
    "sg:tags":[
        "sewing",
        "centre"
    ],
    "wof:name":"Sunlight Textiles",
    "wof:placetype":"venue"
},
  "geometry": {"coordinates":[-1.9348230362,52.5035247803],"type":"Point"}
}