{
  "type": "Feature",
  "properties": {
    "iso:country":"GB",
    "sg:address":"Trevarthian Road",
    "sg:city":"St Austell",
    "sg:classifiers":[
        {
            "category":"Farming",
            "subcategory":"Nursery",
            "type":"Manufacturing & Wholesale Goods"
        }
    ],
    "sg:phone":"+44 1726 63528",
    "sg:postcode":"PL25 4BZ",
    "sg:province":"Cornwall",
    "sg:tags":[
        "creche"
    ],
    "wof:name":"Playtime Day Nursery",
    "wof:placetype":"venue"
},
  "geometry": {"coordinates":[-4.787428,50.341934],"type":"Point"}
}