{
  "type": "Feature",
  "properties": {
    "iso:country":"GB",
    "sg:address":"Norlington Road",
    "sg:city":"London",
    "sg:classifiers":[
        {
            "category":"Retail",
            "subcategory":"Auto Repair",
            "type":"Services"
        }
    ],
    "sg:phone":"+44 20 8539 1833",
    "sg:postcode":"E10 6JZ",
    "sg:province":"Greater London",
    "sg:tags":[
        "modification",
        "garage"
    ],
    "wof:name":"Don F Smith",
    "wof:placetype":"venue"
},
  "geometry": {"coordinates":[-0.00584,51.568375],"type":"Point"}
}