{
  "type": "Feature",
  "properties": {
    "addr:full":"Units 11-12 Vulcan Works, Leckhampton Road Cheltenham Gloucestershire GL53 0DL",
    "addr:housenumber":"units 11-12",
    "addr:postcode":"gl53 0dl",
    "addr:street":"Vulcan Works Leckhampton Road",
    "iso:country":"GB",
    "sg:address":"Units 11-12 Vulcan Works, Leckhampton Road",
    "sg:city":"Cheltenham",
    "sg:classifiers":[
        {
            "category":"Professional",
            "subcategory":"Engineering",
            "type":"Services"
        }
    ],
    "sg:phone":"+44 1242 227764",
    "sg:postcode":"GL53 0DL",
    "sg:province":"Gloucestershire",
    "wof:name":"G B Engineering",
    "wof:placetype":"venue"
},
  "geometry": {"coordinates":[-2.078469,51.88158],"type":"Point"}
}