{
  "type": "Feature",
  "properties": {
    "addr:full":"146 Dee Road, Tilehurst Reading Berkshire RG30 4BT",
    "addr:housenumber":"146",
    "addr:postcode":"rg30 4bt",
    "addr:street":"Dee Road",
    "iso:country":"GB",
    "sg:address":"146 Dee Road, Tilehurst",
    "sg:city":"Reading",
    "sg:classifiers":[
        {
            "category":"Retail",
            "subcategory":"Driving School",
            "type":"Services"
        },
        {
            "category":"Shopping",
            "subcategory":"Pets & Pet Supplies",
            "type":"Retail Goods"
        }
    ],
    "sg:phone":"+44 118 945 2727",
    "sg:postcode":"RG30 4BT",
    "sg:province":"Berkshire",
    "sg:tags":[
        "feed",
        "food",
        "animal"
    ],
    "wof:name":"Trophy Pet Foods",
    "wof:placetype":"venue"
},
  "geometry": {"coordinates":[-1.014181,51.454632],"type":"Point"}
}