{
  "type": "Feature",
  "properties": {
    "addr:full":"Orchard House, South Drive, Stow Lincoln Lincolnshire LN1 2DH",
    "addr:postcode":"ln1 2dh",
    "addr:street":"South Drive",
    "iso:country":"GB",
    "sg:address":"Orchard House, South Drive, Stow",
    "sg:city":"Lincoln",
    "sg:classifiers":[
        {
            "category":"Professional",
            "subcategory":"Business Services",
            "type":"Services"
        }
    ],
    "sg:phone":"+44 1427 787700",
    "sg:postcode":"LN1 2DH",
    "sg:province":"Lincolnshire",
    "sg:tags":[
        "transfer",
        "agent"
    ],
    "wof:name":"Adams & Co",
    "wof:placetype":"venue"
},
  "geometry": {"coordinates":[-0.6740249991,53.3271484375],"type":"Point"}
}