{
  "type": "Feature",
  "properties": {
    "addr:full":"Reymerston Norwich Norfolk NR9 4QD",
    "addr:postcode":"nr9 4qd",
    "addr:street":"Norwich Norfolk",
    "iso:country":"GB",
    "sg:address":"Reymerston",
    "sg:city":"Norwich",
    "sg:classifiers":[
        {
            "category":"Shopping",
            "subcategory":"Florist",
            "type":"Retail Goods"
        }
    ],
    "sg:postcode":"NR9 4QD",
    "sg:province":"Norfolk",
    "wof:name":"Calveley Flowers",
    "wof:placetype":"venue"
},
  "geometry": {"coordinates":[0.9841250181,52.6146697998],"type":"Point"}
}