{
  "type": "Feature",
  "properties": {
    "iso:country":"GB",
    "sg:address":"300 London Road",
    "sg:city":"Westcliff-on-sea",
    "sg:classifiers":[
        {
            "category":"Shopping",
            "subcategory":"Clothing, Apparel, & Fashions",
            "type":"Retail Goods"
        }
    ],
    "sg:phone":"+44 1702 335522",
    "sg:postcode":"SS0 7JJ",
    "sg:province":"Essex",
    "sg:tags":[
        "t-shirt"
    ],
    "wof:name":"Heroes & Idols",
    "wof:placetype":"venue"
},
  "geometry": {"coordinates":[0.698194,51.540981],"type":"Point"}
}