{
  "type": "Feature",
  "properties": {
    "addr:full":"120 Liverpool Road, Irlam Manchester Greater Manchester M44 6FF",
    "addr:housenumber":"120",
    "addr:postcode":"m44 6ff",
    "addr:street":"Liverpool Road",
    "iso:country":"GB",
    "sg:address":"120 Liverpool Road, Irlam",
    "sg:city":"Manchester",
    "sg:classifiers":[
        {
            "category":"Shopping",
            "subcategory":"Baby Store",
            "type":"Retail Goods"
        }
    ],
    "sg:postcode":"M44 6FF",
    "sg:province":"Greater Manchester",
    "sg:tags":[
        "equipment",
        "nursery",
        "accessory"
    ],
    "wof:name":"THE NURSERY SHOP",
    "wof:placetype":"venue"
},
  "geometry": {"coordinates":[-2.413997,53.451172],"type":"Point"}
}