{
  "type": "Feature",
  "properties": {
    "addr:full":"156 Woodthorpe Rd, Kings Heath Birmingham West Midlands B14 6EQ",
    "addr:housenumber":"156",
    "addr:postcode":"b14 6eq",
    "addr:street":"Woodthorpe Rd",
    "iso:country":"GB",
    "sg:address":"156 Woodthorpe Rd, Kings Heath",
    "sg:city":"Birmingham",
    "sg:classifiers":[
        {
            "category":"Manufacturing",
            "subcategory":"Building Materials",
            "type":"Manufacturing & Wholesale Goods"
        }
    ],
    "sg:postcode":"B14 6EQ",
    "sg:province":"West Midlands",
    "sg:tags":[
        "tarmac",
        "asphalt"
    ],
    "wof:name":"Malformac Construction Ltd",
    "wof:placetype":"venue"
},
  "geometry": {"coordinates":[-1.899365,52.419109],"type":"Point"}
}