{
  "type": "Feature",
  "properties": {
    "addr:full":"17 Sedlescombe Road North St Leonards-on-sea East Sussex TN37 7DA",
    "addr:housenumber":"17",
    "addr:postcode":"tn37 7da",
    "addr:street":"Sedlescombe Road North St Leonards-On-Sea",
    "iso:country":"GB",
    "sg:address":"17 Sedlescombe Road North",
    "sg:city":"St Leonards-on-sea",
    "sg:classifiers":[
        {
            "category":"Personal",
            "subcategory":"Beauty Salon",
            "type":"Services"
        }
    ],
    "sg:postcode":"TN37 7DA",
    "sg:province":"East Sussex",
    "sg:tags":[
        "unisex",
        "hairdresser"
    ],
    "wof:name":"Clippers",
    "wof:placetype":"venue"
},
  "geometry": {"coordinates":[0.555963,50.868015],"type":"Point"}
}