{
  "type": "Feature",
  "properties": {
    "iso:country":"GB",
    "sg:address":"Unit C3, Pinetrees Road",
    "sg:city":"Norwich",
    "sg:classifiers":[
        {
            "category":"Shopping",
            "subcategory":"Pharmacy",
            "type":"Retail Goods"
        }
    ],
    "sg:phone":"+44 1603 300336",
    "sg:postcode":"NR7 9BB",
    "sg:province":"Norfolk",
    "sg:tags":[
        "pharmaceutical"
    ],
    "wof:name":"East Anglian Pharmaceuticals Ltd.",
    "wof:placetype":"venue"
},
  "geometry": {"coordinates":[1.33732,52.650028],"type":"Point"}
}