{
  "type": "Feature",
  "properties": {
    "addr:full":"22 Forest Hall Rd Newcastle Upon Tyne Tyne and Wear NE12 9AL",
    "addr:housenumber":"22",
    "addr:postcode":"ne12 9al",
    "addr:street":"Forest Hall Rd",
    "iso:country":"GB",
    "sg:address":"22 Forest Hall Rd",
    "sg:city":"Newcastle Upon Tyne",
    "sg:classifiers":[
        {
            "category":"Food & Beverages",
            "subcategory":"Liquor & Beverages",
            "type":"Retail Goods"
        }
    ],
    "sg:phone":"+44 191 268 9685",
    "sg:postcode":"NE12 9AL",
    "sg:province":"Tyne and Wear",
    "sg:tags":[
        "beer",
        "wine",
        "spirit",
        "wines"
    ],
    "wof:name":"Liquor Mart",
    "wof:placetype":"venue"
},
  "geometry": {"coordinates":[-1.5614180565,55.0228538513],"type":"Point"}
}