{
  "type": "Feature",
  "properties": {
    "addr:full":"7 Mill Street Ludlow Herefordshire SY8 1BA",
    "addr:housenumber":"7",
    "addr:postcode":"sy8 1ba",
    "addr:street":"Mill Street",
    "iso:country":"GB",
    "sg:address":"7 Mill Street",
    "sg:city":"Ludlow",
    "sg:classifiers":[
        {
            "category":"Banks & Credit Unions",
            "subcategory":"Financial Services",
            "type":"Services"
        }
    ],
    "sg:postcode":"SY8 1BA",
    "sg:province":"Herefordshire",
    "sg:tags":[
        "consultant"
    ],
    "wof:name":"Murivance Investments (1993) Issue 2 Lim",
    "wof:placetype":"venue"
},
  "geometry": {"coordinates":[-2.7205460072,52.3665046692],"type":"Point"}
}