{
  "type": "Feature",
  "properties": {
    "addr:full":"11a Liverpool Road Chester Cheshire CH2 1AA",
    "addr:housenumber":"11a",
    "addr:postcode":"ch2 1aa",
    "addr:street":"Liverpool Road",
    "iso:country":"GB",
    "sg:address":"11a Liverpool Road",
    "sg:city":"Chester",
    "sg:classifiers":[
        {
            "category":"Autos & Motor Vehicles",
            "subcategory":"Motorcycle Sales",
            "type":"Retail Goods"
        }
    ],
    "sg:phone":"+44 1244 378365",
    "sg:postcode":"CH2 1AA",
    "sg:province":"Cheshire",
    "sg:tags":[
        "scooter",
        "cycle"
    ],
    "wof:name":"Chester Honda Centre",
    "wof:placetype":"venue"
},
  "geometry": {"coordinates":[-2.894662,53.197914],"type":"Point"}
}