{
  "type": "Feature",
  "properties": {
    "iso:country":"GB",
    "sg:address":"Buckingham Road",
    "sg:city":"Shoreham-by-sea",
    "sg:classifiers":[
        {
            "category":"Education",
            "subcategory":"School",
            "type":"Public Place"
        }
    ],
    "sg:phone":"+44 1273 453515",
    "sg:postcode":"BN43 5UD",
    "sg:province":"West Sussex",
    "sg:tags":[
        "local",
        "authority"
    ],
    "wof:name":"Buckingham County Middle School",
    "wof:placetype":"venue"
},
  "geometry": {"coordinates":[-0.270464,50.839588],"type":"Point"}
}