{
  "type": "Feature",
  "properties": {
    "addr:full":"20 Prospect St Reading Berkshire RG1 7YG",
    "addr:housenumber":"20",
    "addr:postcode":"rg1 7yg",
    "addr:street":"Prospect St",
    "iso:country":"GB",
    "sg:address":"20 Prospect St",
    "sg:city":"Reading",
    "sg:classifiers":[
        {
            "category":"Professional",
            "subcategory":"Lawyer & Legal Services",
            "type":"Services"
        }
    ],
    "sg:phone":"+44 118 950 7283",
    "sg:postcode":"RG1 7YG",
    "sg:province":"Berkshire",
    "sg:tags":[
        "advice",
        "counselling"
    ],
    "wof:name":"Relate",
    "wof:placetype":"venue"
},
  "geometry": {"coordinates":[-0.9864720106,51.4544410706],"type":"Point"}
}