{
  "type": "Feature",
  "properties": {
    "addr:full":"60 Broad Oaks Sheffield South Yorkshire S9 3HJ",
    "addr:housenumber":"60",
    "addr:postcode":"s9 3hj",
    "addr:street":"Broad Oaks",
    "iso:country":"GB",
    "sg:address":"60 Broad Oaks",
    "sg:city":"Sheffield",
    "sg:classifiers":[
        {
            "category":"Professional",
            "subcategory":"Engineering",
            "type":"Services"
        }
    ],
    "sg:phone":"+44 114 256 2222",
    "sg:postcode":"S9 3HJ",
    "sg:province":"South Yorkshire",
    "sg:tags":[
        "engineer",
        "mechanical"
    ],
    "wof:name":"W A Carr",
    "wof:placetype":"venue"
},
  "geometry": {"coordinates":[-1.4313590527,53.3876686096],"type":"Point"}
}