{
  "type": "Feature",
  "properties": {
    "iso:country":"GB",
    "sg:address":"15 Forsyth Gardens, Kennington",
    "sg:city":"London",
    "sg:classifiers":[
        {
            "category":"Real Estate",
            "subcategory":"Architect",
            "type":"Services"
        }
    ],
    "sg:postcode":"SE17 3NE",
    "sg:province":"Greater London",
    "wof:name":"Soul Touchey A Ltd",
    "wof:placetype":"venue"
},
  "geometry": {"coordinates":[-0.102977,51.483849],"type":"Point"}
}