{
  "type": "Feature",
  "properties": {
    "addr:full":"Linco House, Manchester Road, Carrington Manchester Cheshire M31 4BX",
    "addr:postcode":"m31 4bx",
    "addr:street":"Manchester Road",
    "iso:country":"GB",
    "sg:address":"Linco House, Manchester Road, Carrington",
    "sg:city":"Manchester",
    "sg:classifiers":[
        {
            "category":"Real Estate",
            "subcategory":"Real Estate Operator",
            "type":"Services"
        }
    ],
    "sg:postcode":"M31 4BX",
    "sg:province":"Cheshire",
    "sg:tags":[
        "letting",
        "agent"
    ],
    "wof:name":"Bridge Properties",
    "wof:placetype":"venue"
},
  "geometry": {"coordinates":[-2.4258790016,53.4200782776],"type":"Point"}
}