{
  "type": "Feature",
  "properties": {
    "addr:full":"Unit 11, Eastlands Industrial Estate Leiston Suffolk IP16 4LL",
    "addr:housenumber":"unit 11",
    "addr:postcode":"ip16 4ll",
    "addr:street":"Eastlands Industrial Estate",
    "iso:country":"GB",
    "sg:address":"Unit 11, Eastlands Industrial Estate",
    "sg:city":"Leiston",
    "sg:classifiers":[
        {
            "category":"Retail",
            "subcategory":"Auto Repair",
            "type":"Services"
        }
    ],
    "sg:phone":"+44 1728 833933",
    "sg:postcode":"IP16 4LL",
    "sg:province":"Suffolk",
    "sg:tags":[
        "modification",
        "garage"
    ],
    "wof:name":"Aerodyne Equipment",
    "wof:placetype":"venue"
},
  "geometry": {"coordinates":[1.5739899874,52.2095947266],"type":"Point"}
}