{
  "type": "Feature",
  "properties": {
    "addr:full":"26 Dalziel Drive Glasgow Glasgow City G41 4PU",
    "addr:housenumber":"26",
    "addr:postcode":"g41 4pu",
    "addr:street":"Dalziel Drive",
    "iso:country":"GB",
    "sg:address":"26 Dalziel Drive",
    "sg:city":"Glasgow",
    "sg:classifiers":[
        {
            "category":"Health Services",
            "subcategory":"Doctor",
            "type":"Services"
        }
    ],
    "sg:phone":"+44 141 423 5830",
    "sg:postcode":"G41 4PU",
    "sg:province":"Glasgow City",
    "sg:tags":[
        "surgeon"
    ],
    "wof:name":"Henry I Tankel",
    "wof:placetype":"venue"
},
  "geometry": {"coordinates":[-4.288871,55.840874],"type":"Point"}
}