{
  "type": "Feature",
  "properties": {
    "addr:full":"Unit 2, Ellgreave Street Stoke-on-trent Staffordshire ST6 4DJ",
    "addr:housenumber":"unit 2",
    "addr:postcode":"st6 4dj",
    "addr:street":"Ellgreave Street",
    "iso:country":"GB",
    "sg:address":"Unit 2, Ellgreave Street",
    "sg:city":"Stoke-on-trent",
    "sg:classifiers":[
        {
            "category":"Building & Trades",
            "subcategory":"Construction",
            "type":"Services"
        }
    ],
    "sg:phone":"+44 1782 811002",
    "sg:postcode":"ST6 4DJ",
    "sg:province":"Staffordshire",
    "sg:tags":[
        "roofing"
    ],
    "wof:name":"J P R Roofing & Flooring Ltd.",
    "wof:placetype":"venue"
},
  "geometry": {"coordinates":[-2.207076,53.044975],"type":"Point"}
}