{
  "type": "Feature",
  "properties": {
    "addr:full":"Adelaide Farm, Wyatts Grn Road, Swallows Cross Brentwood Essex CM15 0ST",
    "addr:postcode":"cm15 0st",
    "addr:street":"Wyatts Grn Road Swallows Cross",
    "iso:country":"GB",
    "sg:address":"Adelaide Farm, Wyatts Grn Road, Swallows Cross",
    "sg:city":"Brentwood",
    "sg:classifiers":[
        {
            "category":"Transit Center",
            "subcategory":"Passenger",
            "type":"Transportation"
        }
    ],
    "sg:phone":"+44 1277 352370",
    "sg:postcode":"CM15 0ST",
    "sg:province":"Essex",
    "sg:tags":[
        "boarding",
        "kennel",
        "catteries"
    ],
    "wof:name":"Arllaide Boarding Kennels & Cattery",
    "wof:placetype":"venue"
},
  "geometry": {"coordinates":[0.3285000026,51.6642112732],"type":"Point"}
}