{
  "type": "Feature",
  "properties": {
    "addr:full":"41 Eardley Rd Streatham Greater London SW16 6DA",
    "addr:housenumber":"41",
    "addr:postcode":"sw16 6da",
    "addr:street":"Eardley Rd",
    "iso:country":"GB",
    "sg:address":"41 Eardley Rd",
    "sg:city":"Streatham",
    "sg:classifiers":[
        {
            "category":"Home & Garden",
            "subcategory":"Home Furnishings",
            "type":"Retail Goods"
        }
    ],
    "sg:phone":"+44 20 8769 7329",
    "sg:postcode":"SW16 6DA",
    "sg:province":"Greater London",
    "sg:tags":[
        "soft"
    ],
    "wof:name":"Amex",
    "wof:placetype":"venue"
},
  "geometry": {"coordinates":[-0.139458999,51.4241218567],"type":"Point"}
}