{
  "type": "Feature",
  "properties": {
    "iso:country":"GB",
    "sg:address":"Unit B61, Lind Rd",
    "sg:city":"Sutton",
    "sg:classifiers":[
        {
            "category":"Retail",
            "subcategory":"Auto Repair",
            "type":"Services"
        }
    ],
    "sg:phone":"+44 181 643 9507",
    "sg:postcode":"SM1 4PP",
    "sg:province":"Surrey",
    "sg:tags":[
        "modification",
        "garage"
    ],
    "wof:name":"Callaghan Taxi Enterprises Ltd",
    "wof:placetype":"venue"
},
  "geometry": {"coordinates":[-0.185882,51.364796],"type":"Point"}
}