{
  "type": "Feature",
  "properties": {
    "addr:full":"Unit 5, The Hatchery, Great North Road Welwyn Garden City Hertfordshire AL8 7SR",
    "addr:housenumber":"unit 5",
    "addr:postcode":"al8 7sr",
    "addr:street":"The Hatchery Great North Road",
    "iso:country":"GB",
    "sg:address":"Unit 5, The Hatchery, Great North Road",
    "sg:city":"Welwyn Garden City",
    "sg:classifiers":[
        {
            "category":"Shopping",
            "subcategory":"Stationery & Office Supplies",
            "type":"Retail Goods"
        }
    ],
    "sg:phone":"+44 1707 327840",
    "sg:postcode":"AL8 7SR",
    "sg:province":"Hertfordshire",
    "sg:tags":[
        "equipment"
    ],
    "wof:name":"Budget Design",
    "wof:placetype":"venue"
},
  "geometry": {"coordinates":[-0.227182,51.800743],"type":"Point"}
}