{
  "type": "Feature",
  "properties": {
    "addr:full":"19 Ashby High St Scunthorpe Lincolnshire DN16 2NN",
    "addr:housenumber":"19",
    "addr:postcode":"dn16 2nn",
    "addr:street":"Ashby High St",
    "iso:country":"GB",
    "sg:address":"19 Ashby High St",
    "sg:city":"Scunthorpe",
    "sg:classifiers":[
        {
            "category":"Food & Beverages",
            "subcategory":"Meat & Fish",
            "type":"Retail Goods"
        }
    ],
    "sg:postcode":"DN16 2NN",
    "sg:province":"Lincolnshire",
    "sg:tags":[
        "chip"
    ],
    "wof:name":"Ann's Chippy",
    "wof:placetype":"venue"
},
  "geometry": {"coordinates":[-0.6337789893,53.5667457581],"type":"Point"}
}