{
  "type": "Feature",
  "properties": {
    "iso:country":"GB",
    "sg:address":"49 Bryn Eglwys Gardens, Newton",
    "sg:city":"Porthcawl",
    "sg:classifiers":[
        {
            "category":"Building & Trades",
            "subcategory":"Construction",
            "type":"Services"
        }
    ],
    "sg:phone":"+44 1656 785878",
    "sg:postcode":"CF36 5PR",
    "sg:province":"Bridgend",
    "sg:tags":[
        "builder"
    ],
    "wof:name":"J C Securities",
    "wof:placetype":"venue"
},
  "geometry": {"coordinates":[-3.673853,51.482319],"type":"Point"}
}