{
  "type": "Feature",
  "properties": {
    "addr:full":"Milner Way Ossett West Yorkshire WF5 9JE",
    "addr:postcode":"wf5 9je",
    "addr:street":"Milner Way",
    "iso:country":"GB",
    "sg:address":"Milner Way",
    "sg:city":"Ossett",
    "sg:classifiers":[
        {
            "category":"Food & Beverages",
            "subcategory":"Supermarket",
            "type":"Retail Goods"
        }
    ],
    "sg:phone":"+44 1924 280180",
    "sg:postcode":"WF5 9JE",
    "sg:province":"West Yorkshire",
    "sg:tags":[
        "frozen"
    ],
    "wof:name":"Zeina Foods",
    "wof:placetype":"venue"
},
  "geometry": {"coordinates":[-1.567765,53.684566],"type":"Point"}
}