{
  "type": "Feature",
  "properties": {
    "addr:full":"The Grange, Wycombe Road, Saunderton High Wycombe Buckinghamshire HP27 9NS",
    "addr:postcode":"hp27 9ns",
    "addr:street":"Wycombe Road",
    "iso:country":"GB",
    "sg:address":"The Grange, Wycombe Road, Saunderton",
    "sg:city":"High Wycombe",
    "sg:classifiers":[
        {
            "category":"Organizations",
            "subcategory":"Non-profit Organization",
            "type":"Services"
        }
    ],
    "sg:phone":"+44 1844 348100",
    "sg:postcode":"HP27 9NS",
    "sg:province":"Buckinghamshire",
    "sg:tags":[
        "charitable",
        "organisation",
        "voluntary",
        "charity"
    ],
    "wof:name":"Hearing Dogs for Deaf People",
    "wof:placetype":"venue"
},
  "geometry": {"coordinates":[-0.8505380154,51.711265564],"type":"Point"}
}