{
  "type": "Feature",
  "properties": {
    "addr:full":"39-42 Bridge Street, Swinton Mexborough South Yorkshire S64 8AP",
    "addr:housenumber":"39-42",
    "addr:postcode":"s64 8ap",
    "addr:street":"Bridge Street",
    "iso:country":"GB",
    "sg:address":"39-42 Bridge Street, Swinton",
    "sg:city":"Mexborough",
    "sg:classifiers":[
        {
            "category":"Communications",
            "subcategory":"Newspaper",
            "type":"Services"
        }
    ],
    "sg:postcode":"S64 8AP",
    "sg:province":"South Yorkshire",
    "sg:tags":[
        "magazine"
    ],
    "wof:name":"Impress Ltd",
    "wof:placetype":"venue"
},
  "geometry": {"coordinates":[-1.3024580479,53.4883804321],"type":"Point"}
}