{
  "type": "Feature",
  "properties": {
    "addr:full":"Halla Industrial Park Merthyr Tydfil Caerphilly CF48 4UD",
    "addr:postcode":"cf48 4ud",
    "addr:street":"Halla Industrial Park",
    "iso:country":"GB",
    "sg:address":"Halla Industrial Park",
    "sg:city":"Merthyr Tydfil",
    "sg:classifiers":[
        {
            "category":"Building & Trades",
            "subcategory":"Construction",
            "type":"Services"
        }
    ],
    "sg:postcode":"CF48 4UD",
    "sg:province":"Caerphilly",
    "sg:tags":[
        "fork",
        "lift",
        "truck"
    ],
    "wof:name":"Halla Euro Enterprise Ltd.",
    "wof:placetype":"venue"
},
  "geometry": {"coordinates":[-3.347407,51.717506],"type":"Point"}
}