{
  "type": "Feature",
  "properties": {
    "addr:full":"32 Cromwell Rd Canterbury Kent CT1 3LE",
    "addr:housenumber":"32",
    "addr:postcode":"ct1 3le",
    "addr:street":"Cromwell Rd",
    "iso:country":"GB",
    "sg:address":"32 Cromwell Rd",
    "sg:city":"Canterbury",
    "sg:classifiers":[
        {
            "category":"Shopping",
            "subcategory":"Pharmacy",
            "type":"Retail Goods"
        }
    ],
    "sg:phone":"+44 1227 462511",
    "sg:postcode":"CT1 3LE",
    "sg:province":"Kent",
    "sg:tags":[
        "medicine",
        "therapy"
    ],
    "wof:name":"Ann Riding MA UKCP",
    "wof:placetype":"venue"
},
  "geometry": {"coordinates":[1.0848590136,51.2685394287],"type":"Point"}
}