{
  "type": "Feature",
  "properties": {
    "addr:full":"142 The Grove London Greater London E15 1NS",
    "addr:housenumber":"142",
    "addr:postcode":"e15 1ns",
    "addr:street":"The Grove",
    "iso:country":"GB",
    "sg:address":"142 The Grove",
    "sg:city":"London",
    "sg:classifiers":[
        {
            "category":"Real Estate",
            "subcategory":"Real Estate Agent",
            "type":"Services"
        }
    ],
    "sg:phone":"+44 20 8519 3919",
    "sg:postcode":"E15 1NS",
    "sg:province":"Greater London",
    "wof:name":"Bairstow Eves",
    "wof:placetype":"venue"
},
  "geometry": {"coordinates":[0.003809,51.543259],"type":"Point"}
}