{
  "type": "Feature",
  "properties": {
    "addr:full":"49-51 Bellhouse Road Sheffield South Yorkshire S5 6HJ",
    "addr:housenumber":"49-51",
    "addr:postcode":"s5 6hj",
    "addr:street":"Bellhouse Road",
    "iso:country":"GB",
    "sg:address":"49-51 Bellhouse Road",
    "sg:city":"Sheffield",
    "sg:classifiers":[
        {
            "category":"Shopping",
            "subcategory":"News",
            "type":"Retail Goods"
        }
    ],
    "sg:phone":"+44 114 281 4692",
    "sg:postcode":"S5 6HJ",
    "sg:province":"South Yorkshire",
    "sg:tags":[
        "newsagent"
    ],
    "wof:name":"G T News",
    "wof:placetype":"venue"
},
  "geometry": {"coordinates":[-1.4469629526,53.4190826416],"type":"Point"}
}