{
  "type": "Feature",
  "properties": {
    "iso:country":"GB",
    "sg:address":"1 Robin Close, Market Depping",
    "sg:city":"Peterborough",
    "sg:classifiers":[
        {
            "category":"Building & Trades",
            "subcategory":"Construction",
            "type":"Services"
        }
    ],
    "sg:postcode":"PE6 8PQ",
    "sg:province":"Cambridgeshire",
    "sg:tags":[
        "builder"
    ],
    "wof:name":"G & P Design & Build",
    "wof:placetype":"venue"
},
  "geometry": {"coordinates":[-0.308806,52.678101],"type":"Point"}
}