{
  "type": "Feature",
  "properties": {
    "addr:full":"131 St Marys Street Warrington Cheshire WA4 1EL",
    "addr:housenumber":"131",
    "addr:postcode":"wa4 1el",
    "addr:street":"St Marys Street",
    "iso:country":"GB",
    "sg:address":"131 St Marys Street",
    "sg:city":"Warrington",
    "sg:classifiers":[
        {
            "category":"Building & Trades",
            "subcategory":"Construction",
            "type":"Services"
        }
    ],
    "sg:phone":"+44 1925 630083",
    "sg:postcode":"WA4 1EL",
    "sg:province":"Cheshire",
    "sg:tags":[
        "glazier"
    ],
    "wof:name":"Eric John Jackson",
    "wof:placetype":"venue"
},
  "geometry": {"coordinates":[-2.5791759491,53.380821228],"type":"Point"}
}