{
  "type": "Feature",
  "properties": {
    "addr:full":"57 High Street, Dodworth Barnsley South Yorkshire S75 3RG",
    "addr:housenumber":"57",
    "addr:postcode":"s75 3rg",
    "addr:street":"High Street;Yorkshire",
    "iso:country":"GB",
    "sg:address":"57 High Street, Dodworth",
    "sg:city":"Barnsley",
    "sg:classifiers":[
        {
            "category":"Shopping",
            "subcategory":"Musical Instruments",
            "type":"Retail Goods"
        }
    ],
    "sg:postcode":"S75 3RG",
    "sg:province":"South Yorkshire",
    "sg:tags":[
        "music",
        "sheet"
    ],
    "wof:name":"Pjs Music Services Ltd.",
    "wof:placetype":"venue"
},
  "geometry": {"coordinates":[-1.5228849649,53.5417556763],"type":"Point"}
}