{
  "type": "Feature",
  "properties": {
    "iso:country":"GB",
    "sg:address":"33-35 Mere Lane",
    "sg:city":"Rochdale",
    "sg:classifiers":[
        {
            "category":"Shopping",
            "subcategory":"Clothing, Apparel, & Fashions",
            "type":"Retail Goods"
        }
    ],
    "sg:phone":"+44 1706 345322",
    "sg:postcode":"OL11 3TD",
    "sg:province":"Lancashire",
    "sg:tags":[
        "clothing",
        "fabric"
    ],
    "wof:name":"Brightlook Fashions",
    "wof:placetype":"venue"
},
  "geometry": {"coordinates":[-2.158097,53.608543],"type":"Point"}
}