{
  "type": "Feature",
  "properties": {
    "addr:full":"153 Miller Street Birmingham West Midlands B6 4NG",
    "addr:housenumber":"153",
    "addr:postcode":"b6 4ng",
    "addr:street":"Miller Street",
    "iso:country":"GB",
    "sg:address":"153 Miller Street",
    "sg:city":"Birmingham",
    "sg:classifiers":[
        {
            "category":"Bus Charters",
            "type":"Transportation"
        }
    ],
    "sg:phone":"+44 121 254 6961",
    "sg:postcode":"B6 4NG",
    "sg:province":"West Midlands",
    "sg:tags":[
        "coach"
    ],
    "wof:name":"Smiths Central Liner",
    "wof:placetype":"venue"
},
  "geometry": {"coordinates":[-1.895275,52.492809],"type":"Point"}
}