{
  "type": "Feature",
  "properties": {
    "addr:full":"9 Strollers Way, Stetchworth Newmarket Cambridgeshire CB8 9TZ",
    "addr:housenumber":"9",
    "addr:postcode":"cb8 9tz",
    "addr:street":"Strollers Way",
    "iso:country":"GB",
    "sg:address":"9 Strollers Way, Stetchworth",
    "sg:city":"Newmarket",
    "sg:classifiers":[
        {
            "category":"Building & Trades",
            "subcategory":"Construction",
            "type":"Services"
        }
    ],
    "sg:postcode":"CB8 9TZ",
    "sg:province":"Cambridgeshire",
    "sg:tags":[
        "resurfacing",
        "laying",
        "flooring",
        "floor"
    ],
    "wof:name":"Anderton & Bush",
    "wof:placetype":"venue"
},
  "geometry": {"coordinates":[0.400802,52.199425],"type":"Point"}
}