{
  "type": "Feature",
  "properties": {
    "addr:full":"Vulcan Road Bilston West Midlands WV14 7JW",
    "addr:postcode":"wv14 7jw",
    "addr:street":"Vulcan Road",
    "iso:country":"GB",
    "sg:address":"Vulcan Road",
    "sg:city":"Bilston",
    "sg:classifiers":[
        {
            "category":"Retail",
            "subcategory":"Auto Rental",
            "type":"Services"
        }
    ],
    "sg:phone":"+44 1902 353300",
    "sg:postcode":"WV14 7JW",
    "sg:province":"West Midlands",
    "sg:tags":[
        "car"
    ],
    "wof:name":"Enterprise Rent-A-Car",
    "wof:placetype":"venue"
},
  "geometry": {"coordinates":[-2.0608189106,52.5696907043],"type":"Point"}
}