{
  "type": "Feature",
  "properties": {
    "addr:full":"21 Mill La, Brockworth Gloucester Gloucestershire GL3 4QQ",
    "addr:housenumber":"21",
    "addr:postcode":"gl3 4qq",
    "addr:street":"Mill La Brockworth",
    "iso:country":"GB",
    "sg:address":"21 Mill La, Brockworth",
    "sg:city":"Gloucester",
    "sg:classifiers":[
        {
            "category":"Retail",
            "subcategory":"Repair Shop",
            "type":"Services"
        }
    ],
    "sg:phone":"+44 1452 862717",
    "sg:postcode":"GL3 4QQ",
    "sg:province":"Gloucestershire",
    "sg:tags":[
        "maintenance"
    ],
    "wof:name":"Ace Maintenance Roofing Contractors",
    "wof:placetype":"venue"
},
  "geometry": {"coordinates":[-2.154874,51.849258],"type":"Point"}
}