{
  "type": "Feature",
  "properties": {
    "iso:country":"GB",
    "sg:address":"Elm Hill",
    "sg:city":"Guildford",
    "sg:classifiers":[
        {
            "category":"Bus Charters",
            "type":"Transportation"
        }
    ],
    "sg:phone":"+44 1252 344083",
    "sg:postcode":"GU3 2HR",
    "sg:province":"Surrey",
    "sg:tags":[
        "mini",
        "hire",
        "leasing"
    ],
    "wof:name":"Dickson Mini Bus Travel",
    "wof:placetype":"venue"
},
  "geometry": {"coordinates":[-0.69757,51.25388],"type":"Point"}
}