{
  "type": "Feature",
  "properties": {
    "addr:full":"Torrance Road, Torrance Glasgow East Dunbartonshire G64 4EG",
    "addr:postcode":"g64 4eg",
    "addr:street":"Torrance Road",
    "iso:country":"GB",
    "sg:address":"Torrance Road, Torrance",
    "sg:city":"Glasgow",
    "sg:classifiers":[
        {
            "category":"Recreation",
            "subcategory":"Dog Park",
            "type":"Entertainment"
        }
    ],
    "sg:postcode":"G64 4EG",
    "sg:province":"East Dunbartonshire",
    "wof:name":"Robin Hill Grooming",
    "wof:placetype":"venue"
},
  "geometry": {"coordinates":[-4.212414,55.938274],"type":"Point"}
}