{
  "type": "Feature",
  "properties": {
    "addr:full":"Brixham Road, Old Trafford Manchester Cheshire M16 0WT",
    "addr:postcode":"m16 0wt",
    "addr:street":"Brixham Road",
    "iso:country":"GB",
    "sg:address":"Brixham Road, Old Trafford",
    "sg:city":"Manchester",
    "sg:classifiers":[
        {
            "category":"Freight",
            "type":"Transportation"
        }
    ],
    "sg:phone":"+44 161 877 7015",
    "sg:postcode":"M16 0WT",
    "sg:province":"Cheshire",
    "sg:tags":[
        "haulage",
        "road"
    ],
    "wof:name":"R J Edwards & Sons",
    "wof:placetype":"venue"
},
  "geometry": {"coordinates":[-2.2794129848,53.4559745789],"type":"Point"}
}