{
  "type": "Feature",
  "properties": {
    "addr:full":"52 New Road, Tylers Grn High Wycombe Buckinghamshire HP10 8DL",
    "addr:housenumber":"52",
    "addr:postcode":"hp10 8dl",
    "addr:street":"New Road Tylers Grn",
    "iso:country":"GB",
    "sg:address":"52 New Road, Tylers Grn",
    "sg:city":"High Wycombe",
    "sg:classifiers":[
        {
            "category":"Professional",
            "type":"Services"
        }
    ],
    "sg:phone":"+44 1494 815168",
    "sg:postcode":"HP10 8DL",
    "sg:province":"Buckinghamshire",
    "sg:tags":[
        "entertainer"
    ],
    "wof:name":"Oscar's Childrens Parties",
    "wof:placetype":"venue"
},
  "geometry": {"coordinates":[-0.6981509924,51.6382446289],"type":"Point"}
}