{
  "type": "Feature",
  "properties": {
    "addr:full":"14 High Street, Burnham Slough Berkshire SL1 7JH",
    "addr:housenumber":"14",
    "addr:postcode":"sl1 7jh",
    "addr:street":"High Street",
    "iso:country":"GB",
    "sg:address":"14 High Street, Burnham",
    "sg:city":"Slough",
    "sg:classifiers":[
        {
            "category":"Home & Garden",
            "subcategory":"Carpets & Floor Coverings",
            "type":"Retail Goods"
        }
    ],
    "sg:phone":"+44 1628 668174",
    "sg:postcode":"SL1 7JH",
    "sg:province":"Berkshire",
    "sg:tags":[
        "carpets",
        "retailer",
        "rug",
        "matting"
    ],
    "wof:name":"Sovereign Carpets",
    "wof:placetype":"venue"
},
  "geometry": {"coordinates":[-0.658106,51.532963],"type":"Point"}
}