{
  "type": "Feature",
  "properties": {
    "addr:full":"Harden House, Cemetery Road, Hemsworth Pontefract West Yorkshire WF9 4QF",
    "addr:postcode":"wf9 4qf",
    "addr:street":"Cemetery Road",
    "iso:country":"GB",
    "sg:address":"Harden House, Cemetery Road, Hemsworth",
    "sg:city":"Pontefract",
    "sg:classifiers":[
        {
            "category":"Building & Trades",
            "subcategory":"Construction",
            "type":"Services"
        }
    ],
    "sg:postcode":"WF9 4QF",
    "sg:province":"West Yorkshire",
    "sg:tags":[
        "builder"
    ],
    "wof:name":"David Wiggins",
    "wof:placetype":"venue"
},
  "geometry": {"coordinates":[-1.3560940027,53.6173095703],"type":"Point"}
}