{
  "type": "Feature",
  "properties": {
    "iso:country":"GB",
    "sg:address":"Unit 4 Kings Meadow, Ferry Hinksey Road",
    "sg:city":"Oxford",
    "sg:classifiers":[
        {
            "category":"Wholesale",
            "subcategory":"Books, Periodicals, & Newspapers",
            "type":"Manufacturing & Wholesale Goods"
        }
    ],
    "sg:postcode":"OX2 0DP",
    "sg:province":"Oxfordshire",
    "sg:tags":[
        "publishing"
    ],
    "wof:name":"Oxford Academic Publishing",
    "wof:placetype":"venue"
},
  "geometry": {"coordinates":[-1.276211,51.751202],"type":"Point"}
}