{
  "type": "Feature",
  "properties": {
    "addr:full":"Back West Crescent Lytham St Annes Lancashire FY8 1SQ",
    "addr:postcode":"fy8 1sq",
    "addr:street":"Back West Crescent",
    "iso:country":"GB",
    "sg:address":"Back West Crescent",
    "sg:city":"Lytham St Annes",
    "sg:classifiers":[
        {
            "category":"Bars & Pubs",
            "type":"Food & Drink"
        },
        {
            "category":"Community Center",
            "subcategory":"Social",
            "type":"Public Place"
        }
    ],
    "sg:phone":"+44 1253 722250",
    "sg:postcode":"FY8 1SQ",
    "sg:province":"Lancashire",
    "sg:tags":[
        "pubs",
        "house",
        "inn",
        "activity"
    ],
    "wof:name":"THE NEW VOGUE BAR RESTAURANT",
    "wof:placetype":"venue"
},
  "geometry": {"coordinates":[-3.029059,53.751942],"type":"Point"}
}