{
  "type": "Feature",
  "properties": {
    "addr:full":"25 Brimsome Meadow, Highnam Gloucester Gloucestershire GL2 8EW",
    "addr:housenumber":"25",
    "addr:postcode":"gl2 8ew",
    "addr:street":"Brimsome Meadow",
    "iso:country":"GB",
    "sg:address":"25 Brimsome Meadow, Highnam",
    "sg:city":"Gloucester",
    "sg:classifiers":[
        {
            "category":"Organizations",
            "subcategory":"Non-profit Organization",
            "type":"Services"
        }
    ],
    "sg:phone":"+44 1452 424789",
    "sg:postcode":"GL2 8EW",
    "sg:province":"Gloucestershire",
    "sg:tags":[
        "charitable",
        "organisation",
        "voluntary",
        "charity"
    ],
    "wof:name":"MYASTHENIA GRAVIS ASSOCIATION",
    "wof:placetype":"venue"
},
  "geometry": {"coordinates":[-2.2934930325,51.8796234131],"type":"Point"}
}