{
  "type": "Feature",
  "properties": {
    "iso:country":"GB",
    "sg:address":"15 Jesmond Grove",
    "sg:city":"Stockton-on-tees",
    "sg:classifiers":[
        {
            "category":"Banks & Credit Unions",
            "subcategory":"Financial Services",
            "type":"Services"
        }
    ],
    "sg:phone":"+44 1642 873330",
    "sg:postcode":"TS18 5ES",
    "sg:province":"Durham",
    "sg:tags":[
        "adviser"
    ],
    "wof:name":"Race & Co",
    "wof:placetype":"venue"
},
  "geometry": {"coordinates":[-1.344824,54.553879],"type":"Point"}
}