{
  "type": "Feature",
  "properties": {
    "addr:full":"Brambledown Pewsey Wiltshire SN9 6EN",
    "addr:postcode":"sn9 6en",
    "addr:street":"Pewsey",
    "iso:country":"GB",
    "sg:address":"Brambledown",
    "sg:city":"Pewsey",
    "sg:classifiers":[
        {
            "category":"Food & Beverages",
            "subcategory":"Specialty",
            "type":"Retail Goods"
        }
    ],
    "sg:phone":"+44 1980 630389",
    "sg:postcode":"SN9 6EN",
    "sg:province":"Wiltshire",
    "sg:tags":[
        "organic"
    ],
    "wof:name":"Rushall Organic Farm",
    "wof:placetype":"venue"
},
  "geometry": {"coordinates":[-1.7623189688,51.3402862549],"type":"Point"}
}