{
  "type": "Feature",
  "properties": {
    "addr:full":"7 Hughes Business Centre, Wilverley Road Christchurch Dorset BH23 3RU",
    "addr:housenumber":"7",
    "addr:postcode":"bh23 3ru",
    "addr:street":"Hughes Business;Wilverley Road",
    "iso:country":"GB",
    "sg:address":"7 Hughes Business Centre, Wilverley Road",
    "sg:city":"Christchurch",
    "sg:classifiers":[
        {
            "category":"Manufacturing",
            "subcategory":"Buildings",
            "type":"Manufacturing & Wholesale Goods"
        }
    ],
    "sg:phone":"+44 1202 475757",
    "sg:postcode":"BH23 3RU",
    "sg:province":"Dorset",
    "sg:tags":[
        "system",
        "air conditioning"
    ],
    "wof:name":"Process Temperature Control Ltd.",
    "wof:placetype":"venue"
},
  "geometry": {"coordinates":[-1.776564,50.73407],"type":"Point"}
}