{
  "type": "Feature",
  "properties": {
    "addr:full":"20a Willesden Clo Hull East Riding of Yorkshire HU8 0TS",
    "addr:housenumber":"20a",
    "addr:postcode":"hu8 0ts",
    "addr:street":"Willesden Clo",
    "iso:country":"GB",
    "sg:address":"20a Willesden Clo",
    "sg:city":"Hull",
    "sg:classifiers":[
        {
            "category":"Health Services",
            "subcategory":"Doctor",
            "type":"Services"
        }
    ],
    "sg:phone":"+44 1482 784996",
    "sg:postcode":"HU8 0TS",
    "sg:province":"East Riding of Yorkshire",
    "sg:tags":[
        "practitioners"
    ],
    "wof:name":"Shaikh, M",
    "wof:placetype":"venue"
},
  "geometry": {"coordinates":[-0.2898899913,53.7729797363],"type":"Point"}
}