{
  "type": "Feature",
  "properties": {
    "addr:full":"White Hart House, High St Limpsfield Oxted Surrey RH8 0DT",
    "addr:postcode":"rh8 0dt",
    "addr:street":"High St;Oxted",
    "iso:country":"GB",
    "sg:address":"White Hart House, High St Limpsfield",
    "sg:city":"Oxted",
    "sg:classifiers":[
        {
            "category":"Professional",
            "subcategory":"Computer Services",
            "type":"Services"
        }
    ],
    "sg:postcode":"RH8 0DT",
    "sg:province":"Surrey",
    "sg:tags":[
        "system",
        "software"
    ],
    "wof:name":"Technophob Ltd",
    "wof:placetype":"venue"
},
  "geometry": {"coordinates":[0.0041149999,51.2569503784],"type":"Point"}
}