{
  "type": "Feature",
  "properties": {
    "iso:country":"GB",
    "sg:address":"12 Langlands Street",
    "sg:city":"Dundee",
    "sg:classifiers":[
        {
            "category":"Building & Trades",
            "subcategory":"Construction",
            "type":"Services"
        }
    ],
    "sg:phone":"+44 1382 451566",
    "sg:postcode":"DD4 6SZ",
    "sg:province":"Dundee City",
    "sg:tags":[
        "roofing",
        "contracting"
    ],
    "wof:name":"Tay Roofing Services Ltd",
    "wof:placetype":"venue"
},
  "geometry": {"coordinates":[-2.958074,56.471073],"type":"Point"}
}