{
  "type": "Feature",
  "properties": {
    "addr:full":"781 Liverpool Road Southport Lancashire PR8 3NT",
    "addr:housenumber":"781",
    "addr:postcode":"pr8 3nt",
    "addr:street":"Liverpool Road",
    "iso:country":"GB",
    "sg:address":"781 Liverpool Road",
    "sg:city":"Southport",
    "sg:classifiers":[
        {
            "category":"Food & Beverages",
            "subcategory":"Groceries & Convenience Stores",
            "type":"Retail Goods"
        }
    ],
    "sg:phone":"+44 1704 578486",
    "sg:postcode":"PR8 3NT",
    "sg:province":"Lancashire",
    "wof:name":"G & E Murgatroyd",
    "wof:placetype":"venue"
},
  "geometry": {"coordinates":[-3.0388269424,53.5922355652],"type":"Point"}
}