{
  "type": "Feature",
  "properties": {
    "addr:full":"19a Bridge St Haverfordwest Pembrokeshire SA61 2AL",
    "addr:housenumber":"19a",
    "addr:postcode":"sa61 2al",
    "addr:street":"Bridge St",
    "iso:country":"GB",
    "sg:address":"19a Bridge St",
    "sg:city":"Haverfordwest",
    "sg:classifiers":[
        {
            "category":"Health Services",
            "subcategory":"Clinic",
            "type":"Services"
        }
    ],
    "sg:phone":"+44 1437 769484",
    "sg:postcode":"SA61 2AL",
    "sg:province":"Pembrokeshire",
    "sg:tags":[
        "misuse",
        "alcohol"
    ],
    "wof:name":"Prism-Alcohol Advisory Service",
    "wof:placetype":"venue"
},
  "geometry": {"coordinates":[-4.968871,51.803028],"type":"Point"}
}