{
  "type": "Feature",
  "properties": {
    "addr:full":"Beaumont Terrace, Brunswick Village Newcastle-upon-tyne Northumberland NE13 7DZ",
    "addr:postcode":"ne13 7dz",
    "addr:street":"Beaumont Terrace",
    "iso:country":"GB",
    "sg:address":"Beaumont Terrace, Brunswick Village",
    "sg:city":"Newcastle-upon-tyne",
    "sg:classifiers":[
        {
            "category":"Travel",
            "subcategory":"Hotels & Motels",
            "type":"Entertainment"
        }
    ],
    "sg:postcode":"NE13 7DZ",
    "sg:province":"Northumberland",
    "wof:name":"Big Waters Hotel",
    "wof:placetype":"venue"
},
  "geometry": {"coordinates":[-1.638029,55.047916],"type":"Point"}
}