{
  "type": "Feature",
  "properties": {
    "iso:country":"GB",
    "sg:address":"Unit 15, Grays Farm Production Village, Grays Farm Rd",
    "sg:city":"Orpington",
    "sg:classifiers":[
        {
            "category":"Personal",
            "type":"Services"
        }
    ],
    "sg:phone":"+44 20 8309 9335",
    "sg:postcode":"BR5 3BD",
    "sg:province":"Kent",
    "sg:tags":[
        "wedding"
    ],
    "wof:name":"Tous Les Jours Ltd",
    "wof:placetype":"venue"
},
  "geometry": {"coordinates":[0.11191,51.408199],"type":"Point"}
}