{
  "type": "Feature",
  "properties": {
    "addr:full":"18 Fortess Road London Greater London NW5 2HB",
    "addr:housenumber":"18",
    "addr:postcode":"nw5 2hb",
    "addr:street":"Fortess Road",
    "iso:country":"GB",
    "sg:address":"18 Fortess Road",
    "sg:city":"London",
    "sg:classifiers":[
        {
            "category":"Restaurant",
            "type":"Food & Drink"
        }
    ],
    "sg:phone":"+44 20 7485 0152",
    "sg:postcode":"NW5 2HB",
    "sg:province":"Greater London",
    "wof:name":"Happy House",
    "wof:placetype":"venue"
},
  "geometry": {"coordinates":[-0.1408250034,51.5523910522],"type":"Point"}
}