{
  "type": "Feature",
  "properties": {
    "addr:full":"4 Gate Street London Greater London WC2A 3HP",
    "addr:housenumber":"4",
    "addr:postcode":"wc2a 3hp",
    "addr:street":"Gate Street",
    "iso:country":"GB",
    "sg:address":"4 Gate Street",
    "sg:city":"London",
    "sg:classifiers":[
        {
            "category":"Shopping",
            "subcategory":"Department Store",
            "type":"Retail Goods"
        }
    ],
    "sg:phone":"+44 20 7242 2795",
    "sg:postcode":"WC2A 3HP",
    "sg:province":"Greater London",
    "wof:name":"Mish Mash Ltd.",
    "wof:placetype":"venue"
},
  "geometry": {"coordinates":[-0.118761003,51.5170249939],"type":"Point"}
}