{
  "type": "Feature",
  "properties": {
    "iso:country":"GB",
    "sg:address":"2 Dover Road, Northfleet",
    "sg:city":"Gravesend",
    "sg:classifiers":[
        {
            "category":"Professional",
            "subcategory":"Art Services",
            "type":"Services"
        }
    ],
    "sg:phone":"+44 1474 568234",
    "sg:postcode":"DA11 9QG",
    "sg:province":"Kent",
    "sg:tags":[
        "picture",
        "restoration",
        "cleaning"
    ],
    "wof:name":"Keith Mcclelland Ltd",
    "wof:placetype":"venue"
},
  "geometry": {"coordinates":[0.3387959898,51.4411773682],"type":"Point"}
}