{
  "type": "Feature",
  "properties": {
    "iso:country":"GB",
    "sg:address":"55 Park View",
    "sg:city":"Whitley Bay",
    "sg:classifiers":[
        {
            "category":"Real Estate",
            "subcategory":"Real Estate Agent",
            "type":"Services"
        }
    ],
    "sg:phone":"+44 191 251 0011",
    "sg:postcode":"NE26 2TP",
    "sg:province":"Northumberland",
    "wof:name":"Cooke & Co",
    "wof:placetype":"venue"
},
  "geometry": {"coordinates":[-1.4501769543,55.0419235229],"type":"Point"}
}