{
  "type": "Feature",
  "properties": {
    "addr:full":"486 Woodchurch Rd Birkenhead Merseyside L43 0SF",
    "addr:housenumber":"486",
    "addr:postcode":"l43 0sf",
    "addr:street":"Woodchurch Rd",
    "iso:country":"GB",
    "sg:address":"486 Woodchurch Rd",
    "sg:city":"Birkenhead",
    "sg:classifiers":[
        {
            "category":"Building & Trades",
            "subcategory":"Construction",
            "type":"Services"
        }
    ],
    "sg:phone":"+44 151 608 9716",
    "sg:postcode":"L43 0SF",
    "sg:province":"Merseyside",
    "sg:tags":[
        "roofing"
    ],
    "wof:name":"Prenton Roofing Co",
    "wof:placetype":"venue"
},
  "geometry": {"coordinates":[-3.057253,53.372143],"type":"Point"}
}