{
  "type": "Feature",
  "properties": {
    "iso:country":"GB",
    "sg:address":"Market House, Church Street",
    "sg:city":"Harleston",
    "sg:classifiers":[
        {
            "category":"Real Estate",
            "subcategory":"Developer",
            "type":"Services"
        }
    ],
    "sg:postcode":"IP20 9BB",
    "sg:province":"Norfolk",
    "sg:tags":[
        "property"
    ],
    "wof:name":"Drewdeeds Limited",
    "wof:placetype":"venue"
},
  "geometry": {"coordinates":[1.299776,52.40189],"type":"Point"}
}