{
  "type": "Feature",
  "properties": {
    "addr:full":"43a Warwick Way, Victoria Westminster Greater London SW1V 1QS",
    "addr:housenumber":"43a",
    "addr:postcode":"sw1v 1qs",
    "addr:street":"Warwick Way",
    "iso:country":"GB",
    "sg:address":"43a Warwick Way, Victoria",
    "sg:city":"Westminster",
    "sg:classifiers":[
        {
            "category":"Professional",
            "subcategory":"Lawyer & Legal Services",
            "type":"Services"
        }
    ],
    "sg:phone":"+44 20 7834 2888",
    "sg:postcode":"SW1V 1QS",
    "sg:province":"Greater London",
    "sg:tags":[
        "solicitor"
    ],
    "wof:name":"Tony Purton",
    "wof:placetype":"venue"
},
  "geometry": {"coordinates":[-0.140543,51.492191],"type":"Point"}
}