{
  "type": "Feature",
  "properties": {
    "addr:full":"3 Chene Court, Modbury Ivybridge Devon PL21 0QJ",
    "addr:housenumber":"3",
    "addr:postcode":"pl21 0qj",
    "addr:street":"Chene Court",
    "iso:country":"GB",
    "sg:address":"3 Chene Court, Modbury",
    "sg:city":"Ivybridge",
    "sg:classifiers":[
        {
            "category":"Health Services",
            "subcategory":"Optometrist",
            "type":"Services"
        },
        {
            "category":"Shopping",
            "subcategory":"Optician",
            "type":"Retail Goods"
        }
    ],
    "sg:phone":"+44 1548 830944",
    "sg:postcode":"PL21 0QJ",
    "sg:province":"Devon",
    "sg:tags":[
        "ophthalmic"
    ],
    "wof:name":"Nigel Frost Optometrist",
    "wof:placetype":"venue"
},
  "geometry": {"coordinates":[-3.8878660202,50.3491783142],"type":"Point"}
}