{
  "type": "Feature",
  "properties": {
    "addr:full":"146 Blacker Road, Birkby Huddersfield West Yorkshire HD1 5HH",
    "addr:housenumber":"146",
    "addr:postcode":"hd1 5hh",
    "addr:street":"Blacker Road;West",
    "iso:country":"GB",
    "sg:address":"146 Blacker Road, Birkby",
    "sg:city":"Huddersfield",
    "sg:classifiers":[
        {
            "category":"Professional",
            "subcategory":"Detective & Security Services",
            "type":"Services"
        }
    ],
    "sg:postcode":"HD1 5HH",
    "sg:province":"West Yorkshire",
    "sg:tags":[
        "alarm",
        "burglar",
        "system"
    ],
    "wof:name":"Armco Security",
    "wof:placetype":"venue"
},
  "geometry": {"coordinates":[-1.7922170162,53.6566772461],"type":"Point"}
}