{
  "type": "Feature",
  "properties": {
    "addr:full":"8 Oxford Road, Lostock Bolton Lancashire BL6 4AY",
    "addr:housenumber":"8",
    "addr:postcode":"bl6 4ay",
    "addr:street":"Oxford Road",
    "iso:country":"GB",
    "sg:address":"8 Oxford Road, Lostock",
    "sg:city":"Bolton",
    "sg:classifiers":[
        {
            "category":"Wholesale",
            "subcategory":"Electrical",
            "type":"Manufacturing & Wholesale Goods"
        }
    ],
    "sg:phone":"+44 1204 693289",
    "sg:postcode":"BL6 4AY",
    "sg:province":"Lancashire",
    "sg:tags":[
        "equipment",
        "refrigeration"
    ],
    "wof:name":"G K M Refrigeration Service",
    "wof:placetype":"venue"
},
  "geometry": {"coordinates":[-2.5209949017,53.5832290649],"type":"Point"}
}