{
  "type": "Feature",
  "properties": {
    "addr:full":"74 Milford Road Lymington Hampshire SO41 8DP",
    "addr:housenumber":"74",
    "addr:postcode":"so41 8dp",
    "addr:street":"Milford Road",
    "iso:country":"GB",
    "sg:address":"74 Milford Road",
    "sg:city":"Lymington",
    "sg:classifiers":[
        {
            "category":"Travel",
            "subcategory":"Hotels & Motels",
            "type":"Entertainment"
        }
    ],
    "sg:postcode":"SO41 8DP",
    "sg:province":"Hampshire",
    "sg:tags":[
        "house",
        "guest"
    ],
    "wof:name":"The Hillsman House",
    "wof:placetype":"venue"
},
  "geometry": {"coordinates":[-1.552689,50.751846],"type":"Point"}
}