{
  "type": "Feature",
  "properties": {
    "addr:full":"4 Norfolk Road Rickmansworth Hertfordshire WD3 1QE",
    "addr:housenumber":"4",
    "addr:postcode":"wd3 1qe",
    "addr:street":"Norfolk Road",
    "iso:country":"GB",
    "sg:address":"4 Norfolk Road",
    "sg:city":"Rickmansworth",
    "sg:classifiers":[
        {
            "category":"Building & Trades",
            "subcategory":"Construction",
            "type":"Services"
        }
    ],
    "sg:postcode":"WD3 1QE",
    "sg:province":"Hertfordshire",
    "sg:tags":[
        "builder"
    ],
    "wof:name":"D W Developments",
    "wof:placetype":"venue"
},
  "geometry": {"coordinates":[-0.468247,51.637341],"type":"Point"}
}