{
  "type": "Feature",
  "properties": {
    "addr:full":"P O Box 99 Swansea Neath Port Talbot SA1 1YP",
    "addr:housenumber":"box 99",
    "addr:postcode":"sa1 1yp",
    "addr:street":"P O",
    "iso:country":"GB",
    "sg:address":"P O Box 99",
    "sg:city":"Swansea",
    "sg:classifiers":[
        {
            "category":"Manufacturing",
            "subcategory":"Building Materials",
            "type":"Manufacturing & Wholesale Goods"
        }
    ],
    "sg:phone":"+44 1792 473748",
    "sg:postcode":"SA1 1YP",
    "sg:province":"Neath Port Talbot",
    "sg:tags":[
        "merchant",
        "builder"
    ],
    "wof:name":"Exall & Jones Ltd.",
    "wof:placetype":"venue"
},
  "geometry": {"coordinates":[-3.9391839504,51.6148796082],"type":"Point"}
}