{
  "type": "Feature",
  "properties": {
    "addr:full":"Tarrareach Station Road, Armadale Bathgate West Lothian EH48 3BJ",
    "addr:postcode":"eh48 3bj",
    "addr:street":"Station Road;Bathgate",
    "iso:country":"GB",
    "sg:address":"Tarrareach Station Road, Armadale",
    "sg:city":"Bathgate",
    "sg:classifiers":[
        {
            "category":"Shopping",
            "subcategory":"Discount & Variety Stores",
            "type":"Retail Goods"
        }
    ],
    "sg:phone":"+44 1501 730404",
    "sg:postcode":"EH48 3BJ",
    "sg:province":"West Lothian",
    "sg:tags":[
        "cleaning",
        "supply"
    ],
    "wof:name":"David Evans",
    "wof:placetype":"venue"
},
  "geometry": {"coordinates":[-3.641629,55.900757],"type":"Point"}
}