{
  "type": "Feature",
  "properties": {
    "addr:full":"191 Church Rd Birkenhead Merseyside L42 0LD",
    "addr:housenumber":"191",
    "addr:postcode":"l42 0ld",
    "addr:street":"Church Rd",
    "iso:country":"GB",
    "sg:address":"191 Church Rd",
    "sg:city":"Birkenhead",
    "sg:classifiers":[
        {
            "category":"Military Area",
            "subcategory":"Air Force Base",
            "type":"Public Place"
        }
    ],
    "sg:phone":"+44 151 645 6000",
    "sg:postcode":"L42 0LD",
    "sg:province":"Merseyside",
    "sg:tags":[
        "taxi",
        "hire",
        "private"
    ],
    "wof:name":"Dial Taxis",
    "wof:placetype":"venue"
},
  "geometry": {"coordinates":[-3.0249741077,53.3775863647],"type":"Point"}
}