{
  "type": "Feature",
  "properties": {
    "addr:full":"227 Burnage Lane Manchester Greater Manchester M19 1FN",
    "addr:housenumber":"227",
    "addr:postcode":"m19 1fn",
    "addr:street":"Burnage Lane",
    "iso:country":"GB",
    "sg:address":"227 Burnage Lane",
    "sg:city":"Manchester",
    "sg:classifiers":[
        {
            "category":"Professional",
            "subcategory":"Accounting & Tax Preparation",
            "type":"Services"
        }
    ],
    "sg:postcode":"M19 1FN",
    "sg:province":"Greater Manchester",
    "sg:tags":[
        "accountant"
    ],
    "wof:name":"N H C",
    "wof:placetype":"venue"
},
  "geometry": {"coordinates":[-2.2004818916,53.4320793152],"type":"Point"}
}