{
  "type": "Feature",
  "properties": {
    "addr:full":"46-62 High Street Hornchurch Essex RM12 4UN",
    "addr:housenumber":"46-62",
    "addr:postcode":"rm12 4un",
    "addr:street":"High Street",
    "iso:country":"GB",
    "sg:address":"46-62 High Street",
    "sg:city":"Hornchurch",
    "sg:classifiers":[
        {
            "category":"Bars & Pubs",
            "type":"Food & Drink"
        }
    ],
    "sg:phone":"+44 1708 478410",
    "sg:postcode":"RM12 4UN",
    "sg:province":"Essex",
    "sg:tags":[
        "pubs",
        "inn"
    ],
    "wof:name":"J J Moon's",
    "wof:placetype":"venue"
},
  "geometry": {"coordinates":[0.215982,51.562881],"type":"Point"}
}