{
  "type": "Feature",
  "properties": {
    "addr:full":"Unit 52 Suite 4, 26 Roundhay Leeds West Yorkshire LS12 5BN",
    "addr:housenumber":"unit 52 suite 4 26",
    "addr:postcode":"ls12 5bn",
    "iso:country":"GB",
    "sg:address":"Unit 52 Suite 4, 26 Roundhay",
    "sg:city":"Leeds",
    "sg:classifiers":[
        {
            "category":"Professional",
            "subcategory":"Detective & Security Services",
            "type":"Services"
        }
    ],
    "sg:postcode":"LS12 5BN",
    "sg:province":"West Yorkshire",
    "sg:tags":[
        "agency"
    ],
    "wof:name":"Shadoe Investigations",
    "wof:placetype":"venue"
},
  "geometry": {"coordinates":[-1.517521,53.820732],"type":"Point"}
}