{
  "type": "Feature",
  "properties": {
    "addr:full":"114 Harvist Rd Kilburn Greater London NW6 6HJ",
    "addr:housenumber":"114",
    "addr:postcode":"nw6 6hj",
    "addr:street":"Harvist Rd",
    "iso:country":"GB",
    "sg:address":"114 Harvist Rd",
    "sg:city":"Kilburn",
    "sg:classifiers":[
        {
            "category":"Organizations",
            "subcategory":"Religious Organization",
            "type":"Services"
        }
    ],
    "sg:phone":"+44 20 8964 2337",
    "sg:postcode":"NW6 6HJ",
    "sg:province":"Greater London",
    "sg:tags":[
        "organisation"
    ],
    "wof:name":"Drukpa Kargyud Trust",
    "wof:placetype":"venue"
},
  "geometry": {"coordinates":[-0.217447,51.5322],"type":"Point"}
}