{
  "type": "Feature",
  "properties": {
    "iso:country":"GB",
    "sg:address":"Easterfield House, 1 New Road",
    "sg:city":"Driffield",
    "sg:classifiers":[
        {
            "category":"Retail",
            "subcategory":"Funeral Services",
            "type":"Services"
        }
    ],
    "sg:phone":"+44 1377 252222",
    "sg:postcode":"YO25 5DL",
    "sg:province":"East Riding of Yorkshire",
    "sg:tags":[
        "cemetery",
        "crematorium"
    ],
    "wof:name":"Henry Naylor (Funeral Directors) Ltd.",
    "wof:placetype":"venue"
},
  "geometry": {"coordinates":[-0.4310300052,54.004360199],"type":"Point"}
}