{
  "type": "Feature",
  "properties": {
    "addr:full":"9 Newnham Street Bedford Bedfordshire MK40 3JR",
    "addr:housenumber":"9",
    "addr:postcode":"mk40 3jr",
    "addr:street":"Newnham Street",
    "iso:country":"GB",
    "sg:address":"9 Newnham Street",
    "sg:city":"Bedford",
    "sg:classifiers":[
        {
            "category":"Food & Beverages",
            "subcategory":"Bakery",
            "type":"Retail Goods"
        }
    ],
    "sg:phone":"+44 1234 353742",
    "sg:postcode":"MK40 3JR",
    "sg:province":"Bedfordshire",
    "sg:tags":[
        "pizza"
    ],
    "wof:name":"Pizzeria Santaniello",
    "wof:placetype":"venue"
},
  "geometry": {"coordinates":[-0.462272,52.137035],"type":"Point"}
}