{
  "type": "Feature",
  "properties": {
    "addr:full":"33 Osborne St Burton On Trent Derbyshire DE15 0JL",
    "addr:housenumber":"33",
    "addr:postcode":"trent derbyshire de15 0jl",
    "addr:street":"Osborne St",
    "iso:country":"GB",
    "sg:address":"33 Osborne St",
    "sg:city":"Burton On Trent",
    "sg:classifiers":[
        {
            "category":"Professional",
            "subcategory":"Art Services",
            "type":"Services"
        }
    ],
    "sg:phone":"+44 1283 542148",
    "sg:postcode":"DE15 0JL",
    "sg:province":"Derbyshire",
    "sg:tags":[
        "photographer"
    ],
    "wof:name":"Anderson McInnes",
    "wof:placetype":"venue"
},
  "geometry": {"coordinates":[-1.611969,52.807556],"type":"Point"}
}