{
  "type": "Feature",
  "properties": {
    "addr:full":"11 Springfield St Warrington Cheshire WA1 1BB",
    "addr:housenumber":"11",
    "addr:postcode":"wa1 1bb",
    "addr:street":"Springfield St",
    "iso:country":"GB",
    "sg:address":"11 Springfield St",
    "sg:city":"Warrington",
    "sg:classifiers":[
        {
            "category":"Professional",
            "subcategory":"Accounting & Tax Preparation",
            "type":"Services"
        }
    ],
    "sg:phone":"+44 1925 655518",
    "sg:postcode":"WA1 1BB",
    "sg:province":"Cheshire",
    "sg:tags":[
        "accountant"
    ],
    "wof:name":"Miller & Co",
    "wof:placetype":"venue"
},
  "geometry": {"coordinates":[-2.598508,53.387627],"type":"Point"}
}