{
  "type": "Feature",
  "properties": {
    "iso:country":"GB",
    "sg:address":"1470 Leeds Road",
    "sg:city":"Bradford",
    "sg:classifiers":[
        {
            "category":"Deli",
            "type":"Food & Drink"
        }
    ],
    "sg:phone":"+44 1274 656107",
    "sg:postcode":"BD3 7AA",
    "sg:province":"West Yorkshire",
    "sg:tags":[
        "delivery",
        "sandwich"
    ],
    "wof:name":"Get Stuffed",
    "wof:placetype":"venue"
},
  "geometry": {"coordinates":[-1.708252,53.80064],"type":"Point"}
}