{
  "type": "Feature",
  "properties": {
    "addr:full":"Upper High St Treharris Caerphilly CF46 6RY",
    "addr:postcode":"cf46 6ry",
    "addr:street":"Upper High St",
    "iso:country":"GB",
    "sg:address":"Upper High St",
    "sg:city":"Treharris",
    "sg:classifiers":[
        {
            "category":"Education",
            "subcategory":"School",
            "type":"Public Place"
        }
    ],
    "sg:phone":"+44 1443 710229",
    "sg:postcode":"CF46 6RY",
    "sg:province":"Caerphilly",
    "sg:tags":[
        "local",
        "authority"
    ],
    "wof:name":"Graig Bedlinog Infant School",
    "wof:placetype":"venue"
},
  "geometry": {"coordinates":[-3.3117039204,51.7052459717],"type":"Point"}
}