{
  "type": "Feature",
  "properties": {
    "iso:country":"GB",
    "sg:address":"18 Churchward Close",
    "sg:city":"Chester",
    "sg:classifiers":[
        {
            "category":"Autos & Motor Vehicles",
            "subcategory":"Motorcycle Sales",
            "type":"Retail Goods"
        }
    ],
    "sg:phone":"+44 1244 379655",
    "sg:postcode":"CH2 2BG",
    "sg:province":"Cheshire",
    "sg:tags":[
        "chauffeur",
        "driven",
        "car"
    ],
    "wof:name":"Prima Executive Cars",
    "wof:placetype":"venue"
},
  "geometry": {"coordinates":[-2.890473,53.204086],"type":"Point"}
}