{
  "type": "Feature",
  "properties": {
    "iso:country":"GB",
    "sg:address":"24 Pinemount Rd, Hucclecote",
    "sg:city":"Gloucester",
    "sg:classifiers":[
        {
            "category":"Professional",
            "subcategory":"Art Services",
            "type":"Services"
        }
    ],
    "sg:phone":"+44 1452 618539",
    "sg:postcode":"GL3 3EL",
    "sg:province":"Gloucestershire",
    "sg:tags":[
        "photographer"
    ],
    "wof:name":"Wingate,Michael J,",
    "wof:placetype":"venue"
},
  "geometry": {"coordinates":[-2.186473,51.853703],"type":"Point"}
}