{
  "type": "Feature",
  "properties": {
    "addr:full":"Home Farm, Great Finborough Stowmarket Suffolk IP14 3BQ",
    "addr:housenumber":"finborough",
    "addr:postcode":"ip14 3bq",
    "iso:country":"GB",
    "sg:address":"Home Farm, Great Finborough",
    "sg:city":"Stowmarket",
    "sg:classifiers":[
        {
            "category":"Farming",
            "subcategory":"Livestock Farm",
            "type":"Manufacturing & Wholesale Goods"
        }
    ],
    "sg:phone":"+44 1449 678388",
    "sg:postcode":"IP14 3BQ",
    "sg:province":"Suffolk",
    "sg:tags":[
        "others"
    ],
    "wof:name":"Blyth Breeding Co Ltd",
    "wof:placetype":"venue"
},
  "geometry": {"coordinates":[0.9420350194,52.1787834167],"type":"Point"}
}