{
  "type": "Feature",
  "properties": {
    "iso:country":"GB",
    "sg:address":"7 Barnes High Street",
    "sg:city":"London",
    "sg:classifiers":[
        {
            "category":"Food & Beverages",
            "subcategory":"Meat & Fish",
            "type":"Retail Goods"
        }
    ],
    "sg:phone":"+44 20 8876 5118",
    "sg:postcode":"SW13 9LW",
    "sg:province":"Greater London",
    "sg:tags":[
        "butcher"
    ],
    "wof:name":"J Seal Butchers",
    "wof:placetype":"venue"
},
  "geometry": {"coordinates":[-0.248592,51.473438],"type":"Point"}
}