{
  "type": "Feature",
  "properties": {
    "iso:country":"GB",
    "sg:address":"90 Hoole Rd",
    "sg:city":"Wirral",
    "sg:classifiers":[
        {
            "category":"Shopping",
            "subcategory":"News",
            "type":"Retail Goods"
        }
    ],
    "sg:phone":"+44 151 677 1952",
    "sg:postcode":"CH49 8EG",
    "sg:province":"Merseyside",
    "sg:tags":[
        "newsagent"
    ],
    "wof:name":"United Norwest",
    "wof:placetype":"venue"
},
  "geometry": {"coordinates":[-3.084645,53.376019],"type":"Point"}
}