{
  "type": "Feature",
  "properties": {
    "addr:full":"Richmond Drive Leigh Lancashire WN7 2XW",
    "addr:postcode":"wn7 2xw",
    "addr:street":"Richmond Drive Leigh",
    "iso:country":"GB",
    "sg:address":"Richmond Drive",
    "sg:city":"Leigh",
    "sg:classifiers":[
        {
            "category":"Place Of Worship",
            "type":"Public Place"
        }
    ],
    "sg:phone":"+44 1942 672731",
    "sg:postcode":"WN7 2XW",
    "sg:province":"Lancashire",
    "wof:name":"St. Gabriels Parish Centre",
    "wof:placetype":"venue"
},
  "geometry": {"coordinates":[-2.4790790081,53.5073738098],"type":"Point"}
}