{
  "type": "Feature",
  "properties": {
    "addr:full":"Church Street Bishops Castle Shropshire SY9 5AA",
    "addr:postcode":"sy9 5aa",
    "addr:street":"Church Street",
    "iso:country":"GB",
    "sg:address":"Church Street",
    "sg:city":"Bishops Castle",
    "sg:classifiers":[
        {
            "category":"Bars & Pubs",
            "type":"Food & Drink"
        }
    ],
    "sg:phone":"+44 1588 630144",
    "sg:postcode":"SY9 5AA",
    "sg:province":"Shropshire",
    "sg:tags":[
        "pubs",
        "inn"
    ],
    "wof:name":"Six Bells Public House",
    "wof:placetype":"venue"
},
  "geometry": {"coordinates":[-2.997917,52.4921],"type":"Point"}
}