{
  "type": "Feature",
  "properties": {
    "addr:full":"11 The Glade, Redwood Dr Morecambe Lancashire LA4 6TT",
    "addr:housenumber":"11",
    "addr:postcode":"la4 6tt",
    "addr:street":"The Glade Redwood Dr",
    "iso:country":"GB",
    "sg:address":"11 The Glade, Redwood Dr",
    "sg:city":"Morecambe",
    "sg:classifiers":[
        {
            "category":"Professional",
            "subcategory":"Management & Consulting",
            "type":"Services"
        }
    ],
    "sg:phone":"+44 1524 413643",
    "sg:postcode":"LA4 6TT",
    "sg:province":"Lancashire",
    "sg:tags":[
        "fire",
        "consultant",
        "protection"
    ],
    "wof:name":"Lune Fire Protection",
    "wof:placetype":"venue"
},
  "geometry": {"coordinates":[-2.839958,54.070656],"type":"Point"}
}