{
  "type": "Feature",
  "properties": {
    "addr:full":"Coxwold Pottery, Coxwold York North Yorkshire YO61 4AA",
    "addr:postcode":"yo61 4aa",
    "iso:country":"GB",
    "sg:address":"Coxwold Pottery, Coxwold",
    "sg:city":"York",
    "sg:classifiers":[
        {
            "category":"Manufacturing",
            "subcategory":"Pottery",
            "type":"Manufacturing & Wholesale Goods"
        }
    ],
    "sg:phone":"+44 1347 868344",
    "sg:postcode":"YO61 4AA",
    "sg:province":"North Yorkshire",
    "wof:name":"Coxwold Pottery",
    "wof:placetype":"venue"
},
  "geometry": {"coordinates":[-1.1858830452,54.1882553101],"type":"Point"}
}