{
  "type": "Feature",
  "properties": {
    "iso:country":"GB",
    "sg:address":"Trescowthick Farm",
    "sg:city":"Newquay",
    "sg:classifiers":[
        {
            "category":"Travel",
            "subcategory":"Hotels & Motels",
            "type":"Entertainment"
        }
    ],
    "sg:phone":"+44 1637 830958",
    "sg:postcode":"TR8 5NS",
    "sg:province":"Cornwall",
    "sg:tags":[
        "house",
        "guest"
    ],
    "wof:name":"S A Buscombe",
    "wof:placetype":"venue"
},
  "geometry": {"coordinates":[-5.0513310432,50.3759384155],"type":"Point"}
}