{
  "type": "Feature",
  "properties": {
    "addr:full":"120 Hillingford Avenue Birmingham West Midlands B43 7JU",
    "addr:housenumber":"120",
    "addr:postcode":"b43 7ju",
    "addr:street":"Hillingford Avenue",
    "iso:country":"GB",
    "sg:address":"120 Hillingford Avenue",
    "sg:city":"Birmingham",
    "sg:classifiers":[
        {
            "category":"Shopping",
            "subcategory":"News",
            "type":"Retail Goods"
        }
    ],
    "sg:phone":"+44 121 360 0830",
    "sg:postcode":"B43 7JU",
    "sg:province":"West Midlands",
    "sg:tags":[
        "newsagent"
    ],
    "wof:name":"Barry's Newsagents",
    "wof:placetype":"venue"
},
  "geometry": {"coordinates":[-1.9049940109,52.5576171875],"type":"Point"}
}