{
  "type": "Feature",
  "properties": {
    "iso:country":"GB",
    "sg:address":"Unit 23 Riverside Workshops, 28 Park Street",
    "sg:city":"London",
    "sg:classifiers":[
        {
            "category":"Professional",
            "type":"Services"
        }
    ],
    "sg:phone":"+44 20 7357 6624",
    "sg:postcode":"SE1 9EQ",
    "sg:province":"Greater London",
    "sg:tags":[
        "repair",
        "tech",
        "maintenance"
    ],
    "wof:name":"Thameside Systems Ltd.",
    "wof:placetype":"venue"
},
  "geometry": {"coordinates":[-0.092594,51.506317],"type":"Point"}
}