{
  "type": "Feature",
  "properties": {
    "iso:country":"GB",
    "sg:address":"21 Stephendale Road",
    "sg:city":"Farnham",
    "sg:classifiers":[
        {
            "category":"Manufacturing",
            "subcategory":"Textiles",
            "type":"Manufacturing & Wholesale Goods"
        }
    ],
    "sg:phone":"+44 1252 715252",
    "sg:postcode":"GU9 9QP",
    "sg:province":"Surrey",
    "sg:tags":[
        "dyer"
    ],
    "wof:name":"Nick Taylor",
    "wof:placetype":"venue"
},
  "geometry": {"coordinates":[-0.7870990038,51.2213592529],"type":"Point"}
}