{
  "type": "Feature",
  "properties": {
    "addr:full":"Broad Oak Works, Airport Services Road, Airport Industrial Estate Portsmouth Hampshire PO3 5PQ",
    "addr:postcode":"hampshire po3 5pq",
    "addr:street":"Road Airport Industrial Estate",
    "iso:country":"GB",
    "sg:address":"Broad Oak Works, Airport Services Road, Airport Industrial Estate",
    "sg:city":"Portsmouth",
    "sg:classifiers":[
        {
            "category":"Arena",
            "subcategory":"Sports Club",
            "type":"Entertainment"
        }
    ],
    "sg:phone":"+44 23 9222 7414",
    "sg:postcode":"PO3 5PQ",
    "sg:province":"Hampshire",
    "wof:name":"Marconi Sports & Social Club",
    "wof:placetype":"venue"
},
  "geometry": {"coordinates":[-1.056743,50.830654],"type":"Point"}
}