{
  "type": "Feature",
  "properties": {
    "iso:country":"GB",
    "sg:address":"123 Cherry Tree La",
    "sg:city":"Rainham",
    "sg:classifiers":[
        {
            "category":"Personal",
            "subcategory":"Beauty Salon",
            "type":"Services"
        }
    ],
    "sg:phone":"+44 1708 523451",
    "sg:postcode":"RM13 8TT",
    "sg:province":"Essex",
    "sg:tags":[
        "unisex",
        "hairdresser"
    ],
    "wof:name":"Sweeneys",
    "wof:placetype":"venue"
},
  "geometry": {"coordinates":[0.186388,51.52692],"type":"Point"}
}