{
  "type": "Feature",
  "properties": {
    "iso:country":"GB",
    "sg:address":"Ackhurst Road",
    "sg:city":"Chorley",
    "sg:classifiers":[
        {
            "category":"Manufacturing",
            "subcategory":"Food",
            "type":"Manufacturing & Wholesale Goods"
        }
    ],
    "sg:phone":"+44 1257 241206",
    "sg:postcode":"PR7 1NH",
    "sg:province":"Lancashire",
    "sg:tags":[
        "processing"
    ],
    "wof:name":"Petrie Technologies Ltd.",
    "wof:placetype":"venue"
},
  "geometry": {"coordinates":[-2.65396,53.655384],"type":"Point"}
}