{
  "type": "Feature",
  "properties": {
    "addr:full":"Church Road, Kenardington Ashford Kent TN26 2NQ",
    "addr:postcode":"tn26 2nq",
    "addr:street":"Church Road",
    "iso:country":"GB",
    "sg:address":"Church Road, Kenardington",
    "sg:city":"Ashford",
    "sg:classifiers":[
        {
            "category":"Building & Trades",
            "subcategory":"Construction",
            "type":"Services"
        }
    ],
    "sg:postcode":"TN26 2NQ",
    "sg:province":"Kent",
    "sg:tags":[
        "builder"
    ],
    "wof:name":"R G Watson",
    "wof:placetype":"venue"
},
  "geometry": {"coordinates":[0.816839993,51.0503540039],"type":"Point"}
}