{
  "type": "Feature",
  "properties": {
    "addr:full":"One & Half Ardleigh Road London Greater London N1 4HS",
    "addr:postcode":"n1 4hs",
    "addr:street":"Ardleigh Road",
    "iso:country":"GB",
    "sg:address":"One & Half Ardleigh Road",
    "sg:city":"London",
    "sg:classifiers":[
        {
            "category":"Professional",
            "subcategory":"Art Services",
            "type":"Services"
        }
    ],
    "sg:phone":"+44 20 7923 2133",
    "sg:postcode":"N1 4HS",
    "sg:province":"Greater London",
    "sg:tags":[
        "graphic",
        "designer"
    ],
    "wof:name":"Spinner Ltd.",
    "wof:placetype":"venue"
},
  "geometry": {"coordinates":[-0.08299,51.544491],"type":"Point"}
}