{
  "type": "Feature",
  "properties": {
    "addr:full":"82 Town St, Armley Leeds West Yorkshire LS12 3AA",
    "addr:housenumber":"82",
    "addr:postcode":"ls12 3aa",
    "addr:street":"Town St",
    "iso:country":"GB",
    "sg:address":"82 Town St, Armley",
    "sg:city":"Leeds",
    "sg:classifiers":[
        {
            "category":"Real Estate",
            "subcategory":"Real Estate Agent",
            "type":"Services"
        }
    ],
    "sg:phone":"+44 113 263 6211",
    "sg:postcode":"LS12 3AA",
    "sg:province":"West Yorkshire",
    "wof:name":"Rowan Estates",
    "wof:placetype":"venue"
},
  "geometry": {"coordinates":[-1.5925829411,53.7967300415],"type":"Point"}
}