{
  "type": "Feature",
  "properties": {
    "addr:full":"22 Rhos Road, Rhos On Sea Colwyn Bay Conwy LL28 4PP",
    "addr:housenumber":"22",
    "addr:postcode":"ll28 4pp",
    "addr:street":"Rhos Road",
    "iso:country":"GB",
    "sg:address":"22 Rhos Road, Rhos On Sea",
    "sg:city":"Colwyn Bay",
    "sg:classifiers":[
        {
            "category":"Shopping",
            "subcategory":"News",
            "type":"Retail Goods"
        }
    ],
    "sg:phone":"+44 1492 548061",
    "sg:postcode":"LL28 4PP",
    "sg:province":"Conwy",
    "sg:tags":[
        "newsagent"
    ],
    "wof:name":"Rhos Newsagents",
    "wof:placetype":"venue"
},
  "geometry": {"coordinates":[-3.7398779392,53.3090629578],"type":"Point"}
}