{
  "type": "Feature",
  "properties": {
    "addr:full":"1240 Evesham Road, Astwood Bank Redditch Warwickshire B96 6AA",
    "addr:housenumber":"1240",
    "addr:postcode":"b96 6aa",
    "addr:street":"Evesham Road",
    "iso:country":"GB",
    "sg:address":"1240 Evesham Road, Astwood Bank",
    "sg:city":"Redditch",
    "sg:classifiers":[
        {
            "category":"Food & Beverages",
            "subcategory":"Liquor & Beverages",
            "type":"Retail Goods"
        }
    ],
    "sg:phone":"+44 1527 893140",
    "sg:postcode":"B96 6AA",
    "sg:province":"Warwickshire",
    "sg:tags":[
        "beer",
        "wine",
        "spirit",
        "wines"
    ],
    "wof:name":"Manor Wines",
    "wof:placetype":"venue"
},
  "geometry": {"coordinates":[-1.9375020266,52.2580337524],"type":"Point"}
}