{
  "type": "Feature",
  "properties": {
    "addr:full":"1 Fulham Road Birmingham West Midlands B11 4QD",
    "addr:housenumber":"1",
    "addr:postcode":"b11 4qd",
    "addr:street":"Fulham Road",
    "iso:country":"GB",
    "sg:address":"1 Fulham Road",
    "sg:city":"Birmingham",
    "sg:classifiers":[
        {
            "category":"Food & Beverages",
            "subcategory":"Groceries & Convenience Stores",
            "type":"Retail Goods"
        }
    ],
    "sg:phone":"+44 121 773 1470",
    "sg:postcode":"B11 4QD",
    "sg:province":"West Midlands",
    "sg:tags":[
        "frozen",
        "ice"
    ],
    "wof:name":"Naim Foods Ltd.",
    "wof:placetype":"venue"
},
  "geometry": {"coordinates":[-1.869027,52.456482],"type":"Point"}
}