{
  "type": "Feature",
  "properties": {
    "iso:country":"GB",
    "sg:address":"5 Kenton Park Shopping Centre",
    "sg:city":"Newcastle-upon-tyne",
    "sg:classifiers":[
        {
            "category":"Farming",
            "subcategory":"Nursery",
            "type":"Manufacturing & Wholesale Goods"
        },
        {
            "category":"Education",
            "subcategory":"Preschool",
            "type":"Public Place"
        }
    ],
    "sg:phone":"+44 191 285 5020",
    "sg:postcode":"NE3 4RU",
    "sg:province":"Tyne and Wear",
    "sg:tags":[
        "school",
        "creche"
    ],
    "wof:name":"Kenton Park Nursery School",
    "wof:placetype":"venue"
},
  "geometry": {"coordinates":[-1.6296219826,54.996509552],"type":"Point"}
}