{
  "type": "Feature",
  "properties": {
    "iso:country":"GB",
    "sg:address":"Aspect Court, 47 Park Square East",
    "sg:city":"Leeds",
    "sg:classifiers":[
        {
            "category":"Professional",
            "subcategory":"Lawyer & Legal Services",
            "type":"Services"
        }
    ],
    "sg:phone":"+44 113 244 3448",
    "sg:postcode":"LS1 2NL",
    "sg:province":"West Yorkshire",
    "sg:tags":[
        "solicitor"
    ],
    "wof:name":"S Field",
    "wof:placetype":"venue"
},
  "geometry": {"coordinates":[-1.5509639978,53.7994537354],"type":"Point"}
}