{
  "type": "Feature",
  "properties": {
    "iso:country":"GB",
    "sg:address":"15 Wellington Street",
    "sg:city":"Leicester",
    "sg:classifiers":[
        {
            "category":"Professional",
            "subcategory":"Lawyer & Legal Services",
            "type":"Services"
        }
    ],
    "sg:phone":"+44 116 254 1747",
    "sg:postcode":"LE1 6HH",
    "sg:province":"Leicestershire",
    "sg:tags":[
        "advice",
        "counselling"
    ],
    "wof:name":"Trade - Mens Sexual Health Project",
    "wof:placetype":"venue"
},
  "geometry": {"coordinates":[-1.131718,52.631428],"type":"Point"}
}