{
  "type": "Feature",
  "properties": {
    "iso:country":"GB",
    "sg:address":"Leach Farm, Swaindrod Lane",
    "sg:city":"Littleborough",
    "sg:classifiers":[
        {
            "category":"Organizations",
            "subcategory":"Non-profit Organization",
            "type":"Services"
        }
    ],
    "sg:phone":"+44 1706 371731",
    "sg:postcode":"OL15 0LE",
    "sg:province":"Lancashire",
    "sg:tags":[
        "organisation",
        "voluntary",
        "charity"
    ],
    "wof:name":"Animals in Distress Field of Dreams",
    "wof:placetype":"venue"
},
  "geometry": {"coordinates":[-2.096913,53.643787],"type":"Point"}
}