{
  "type": "Feature",
  "properties": {
    "addr:full":"Unit 6 Corbett Indust Est, Cinder Bank Dudley West Midlands DY2 9BG",
    "addr:housenumber":"unit 6",
    "addr:postcode":"dy2 9bg",
    "addr:street":"Indust;Dudley",
    "iso:country":"GB",
    "sg:address":"Unit 6 Corbett Indust Est, Cinder Bank",
    "sg:city":"Dudley",
    "sg:classifiers":[
        {
            "category":"Shopping",
            "type":"Retail Goods"
        }
    ],
    "sg:phone":"+44 1384 241454",
    "sg:postcode":"DY2 9BG",
    "sg:province":"West Midlands",
    "sg:tags":[
        "equipment",
        "clothing",
        "safety"
    ],
    "wof:name":"Machine Safety Guards Ltd",
    "wof:placetype":"venue"
},
  "geometry": {"coordinates":[-2.083509,52.509521],"type":"Point"}
}