{
  "type": "Feature",
  "properties": {
    "iso:country":"GB",
    "sg:address":"North Sherwood Street",
    "sg:city":"Nottingham",
    "sg:classifiers":[
        {
            "category":"Bars & Pubs",
            "type":"Food & Drink"
        }
    ],
    "sg:phone":"+44 115 947 2833",
    "sg:postcode":"NG1 4EZ",
    "sg:province":"Nottinghamshire",
    "sg:tags":[
        "pubs",
        "inn"
    ],
    "wof:name":"Hole in the Wall",
    "wof:placetype":"venue"
},
  "geometry": {"coordinates":[-1.152139,52.962719],"type":"Point"}
}