{
  "type": "Feature",
  "properties": {
    "addr:full":"Halsinger Granary, Halsinger Braunton Devon EX33 2NL",
    "addr:housenumber":"braunton",
    "addr:postcode":"ex33 2nl",
    "addr:street":"Devon",
    "iso:country":"GB",
    "sg:address":"Halsinger Granary, Halsinger",
    "sg:city":"Braunton",
    "sg:classifiers":[
        {
            "category":"Building & Trades",
            "subcategory":"Plumbing",
            "type":"Services"
        },
        {
            "category":"Building & Trades",
            "subcategory":"Construction",
            "type":"Services"
        }
    ],
    "sg:phone":"+44 1271 816169",
    "sg:postcode":"EX33 2NL",
    "sg:province":"Devon",
    "sg:tags":[
        "plumber",
        "builder"
    ],
    "wof:name":"HAYES BUILDING & HEATING SERVICES",
    "wof:placetype":"venue"
},
  "geometry": {"coordinates":[-4.161649,51.109818],"type":"Point"}
}