{
  "type": "Feature",
  "properties": {
    "iso:country":"GB",
    "sg:address":"77 Glasgow Rd",
    "sg:city":"Paisley",
    "sg:classifiers":[
        {
            "category":"Personal",
            "subcategory":"Beauty Salon",
            "type":"Services"
        }
    ],
    "sg:phone":"+44 141 887 1332",
    "sg:postcode":"PA1 3PE",
    "sg:province":"Renfrewshire",
    "sg:tags":[
        "unisex",
        "hairdresser"
    ],
    "wof:name":"Sahara Hair",
    "wof:placetype":"venue"
},
  "geometry": {"coordinates":[-4.405992,55.847031],"type":"Point"}
}