{
  "type": "Feature",
  "properties": {
    "addr:full":"22 Stevenage Enterprise Centre, Orchard Rd Stevenage Hertfordshire SG1 3HH",
    "addr:housenumber":"22",
    "addr:postcode":"sg1 3hh",
    "addr:street":"Stevenage Enterprise Centre Orchard Rd",
    "iso:country":"GB",
    "sg:address":"22 Stevenage Enterprise Centre, Orchard Rd",
    "sg:city":"Stevenage",
    "sg:classifiers":[
        {
            "category":"Retail",
            "subcategory":"Auto Repair",
            "type":"Services"
        }
    ],
    "sg:phone":"+44 1438 316562",
    "sg:postcode":"SG1 3HH",
    "sg:province":"Hertfordshire",
    "sg:tags":[
        "modification",
        "garage"
    ],
    "wof:name":"Mattie's Car Care Centre",
    "wof:placetype":"venue"
},
  "geometry": {"coordinates":[-0.1886799932,51.9056091309],"type":"Point"}
}