{
  "type": "Feature",
  "properties": {
    "addr:full":"Salt Cellar Workshops, Salt Cellar Hill Helston Cornwall TR13 9DP",
    "addr:postcode":"tr13 9dp",
    "addr:street":"Hill",
    "iso:country":"GB",
    "sg:address":"Salt Cellar Workshops, Salt Cellar Hill",
    "sg:city":"Helston",
    "sg:classifiers":[
        {
            "category":"Shopping",
            "subcategory":"Clothing, Apparel, & Fashions",
            "type":"Retail Goods"
        }
    ],
    "sg:phone":"+44 1326 565707",
    "sg:postcode":"TR13 9DP",
    "sg:province":"Cornwall",
    "sg:tags":[
        "shop",
        "hat"
    ],
    "wof:name":"Salt Cellar Hats",
    "wof:placetype":"venue"
},
  "geometry": {"coordinates":[-5.266959,50.10582],"type":"Point"}
}