{
  "type": "Feature",
  "properties": {
    "addr:full":"North East Avenue, Brinscall Chorley Lancashire PR6 8RR",
    "addr:postcode":"pr6 8rr",
    "addr:street":"North East Avenue",
    "iso:country":"GB",
    "sg:address":"North East Avenue, Brinscall",
    "sg:city":"Chorley",
    "sg:classifiers":[
        {
            "category":"Manufacturing",
            "subcategory":"Lumber",
            "type":"Manufacturing & Wholesale Goods"
        }
    ],
    "sg:phone":"+44 1254 833510",
    "sg:postcode":"PR6 8RR",
    "sg:province":"Lancashire",
    "sg:tags":[
        "merchant",
        "merchants",
        "importer",
        "agent",
        "timber"
    ],
    "wof:name":"Alfred Hulme",
    "wof:placetype":"venue"
},
  "geometry": {"coordinates":[-2.5692241192,53.6882705688],"type":"Point"}
}