{
  "type": "Feature",
  "properties": {
    "iso:country":"GB",
    "sg:address":"56 Marston Rd",
    "sg:city":"Stafford",
    "sg:classifiers":[
        {
            "category":"Food & Beverages",
            "subcategory":"Meat & Fish",
            "type":"Retail Goods"
        }
    ],
    "sg:phone":"+44 1785 224250",
    "sg:postcode":"ST16 3BX",
    "sg:province":"Staffordshire",
    "sg:tags":[
        "chip"
    ],
    "wof:name":"Vasey's Fish Bar",
    "wof:placetype":"venue"
},
  "geometry": {"coordinates":[-2.118822,52.817696],"type":"Point"}
}