{
  "type": "Feature",
  "properties": {
    "addr:full":"7-9 Walton Road Liverpool Merseyside L4 4AD",
    "addr:housenumber":"7-9",
    "addr:postcode":"l4 4ad",
    "addr:street":"Walton Road",
    "iso:country":"GB",
    "sg:address":"7-9 Walton Road",
    "sg:city":"Liverpool",
    "sg:classifiers":[
        {
            "category":"Food & Beverages",
            "subcategory":"Liquor & Beverages",
            "type":"Retail Goods"
        }
    ],
    "sg:phone":"+44 151 207 6690",
    "sg:postcode":"L4 4AD",
    "sg:province":"Merseyside",
    "sg:tags":[
        "beer",
        "spirit",
        "wines"
    ],
    "wof:name":"Thresher",
    "wof:placetype":"venue"
},
  "geometry": {"coordinates":[-2.976295,53.430786],"type":"Point"}
}