{
  "type": "Feature",
  "properties": {
    "addr:full":"Clerkenwel House, 45-47 Clerkenwel Grn London Greater London EC1R 0HT",
    "addr:housenumber":"45-47",
    "addr:postcode":"ec1r 0ht",
    "addr:street":"Clerkenwel Grn",
    "iso:country":"GB",
    "sg:address":"Clerkenwel House, 45-47 Clerkenwel Grn",
    "sg:city":"London",
    "sg:classifiers":[
        {
            "category":"Organizations",
            "subcategory":"Professional Association",
            "type":"Services"
        }
    ],
    "sg:phone":"+44 20 7251 0125",
    "sg:postcode":"EC1R 0HT",
    "sg:province":"Greater London",
    "sg:tags":[
        "literary",
        "agent"
    ],
    "wof:name":"Johnson & Alcock Ltd.",
    "wof:placetype":"venue"
},
  "geometry": {"coordinates":[-0.106257,51.524101],"type":"Point"}
}