{
  "type": "Feature",
  "properties": {
    "addr:full":"129 Portland Road, Holland Park London Greater London W11 4LW",
    "addr:housenumber":"129",
    "addr:postcode":"w11 4lw",
    "addr:street":"Portland Road",
    "iso:country":"GB",
    "sg:address":"129 Portland Road, Holland Park",
    "sg:city":"London",
    "sg:classifiers":[
        {
            "category":"Organizations",
            "subcategory":"Community Association",
            "type":"Services"
        }
    ],
    "sg:phone":"+44 20 7727 7198",
    "sg:postcode":"W11 4LW",
    "sg:province":"Greater London",
    "sg:tags":[
        "relation",
        "public"
    ],
    "wof:name":"Mathews & Mann Ltd.",
    "wof:placetype":"venue"
},
  "geometry": {"coordinates":[-0.2105830014,51.510093689],"type":"Point"}
}