{
  "type": "Feature",
  "properties": {
    "addr:full":"135 Nightingale Lane Balham Greater London SW12 8NE",
    "addr:housenumber":"135",
    "addr:postcode":"sw12 8ne",
    "addr:street":"Nightingale Lane",
    "iso:country":"GB",
    "sg:address":"135 Nightingale Lane",
    "sg:city":"Balham",
    "sg:classifiers":[
        {
            "category":"Community Center",
            "subcategory":"Youth",
            "type":"Public Place"
        }
    ],
    "sg:phone":"+44 20 8673 4422",
    "sg:postcode":"SW12 8NE",
    "sg:province":"Greater London",
    "sg:tags":[
        "organisation",
        "centre"
    ],
    "wof:name":"Southwark Catholic Youth Service",
    "wof:placetype":"venue"
},
  "geometry": {"coordinates":[-0.161701,51.448868],"type":"Point"}
}