{
  "type": "Feature",
  "properties": {
    "iso:country":"GB",
    "sg:address":"2c Park Road Industrial Estate",
    "sg:city":"Consett",
    "sg:classifiers":[
        {
            "category":"Food & Beverages",
            "subcategory":"Specialty",
            "type":"Retail Goods"
        }
    ],
    "sg:postcode":"DH8 5PU",
    "sg:province":"Durham",
    "sg:tags":[
        "dietetic",
        "homogenised"
    ],
    "wof:name":"Rowbotham Ltd.",
    "wof:placetype":"venue"
},
  "geometry": {"coordinates":[-1.835455,54.85482],"type":"Point"}
}