{
  "type": "Feature",
  "properties": {
    "addr:full":"2c Park Road Industrial Estate Consett Durham DH8 5PU",
    "addr:housenumber":"2c",
    "addr:postcode":"dh8 5pu",
    "addr:street":"Park Road Industrial Estate",
    "iso:country":"GB",
    "sg:address":"2c Park Road Industrial Estate",
    "sg:city":"Consett",
    "sg:classifiers":[
        {
            "category":"Food & Beverages",
            "subcategory":"Specialty",
            "type":"Retail Goods"
        }
    ],
    "sg:postcode":"DH8 5PU",
    "sg:province":"Durham",
    "sg:tags":[
        "dietetic",
        "homogenised"
    ],
    "wof:name":"Rowbotham Ltd.",
    "wof:placetype":"venue"
},
  "geometry": {"coordinates":[-1.835455,54.85482],"type":"Point"}
}