{
  "type": "Feature",
  "properties": {
    "addr:full":"192 Duffield Road Derby Derbyshire DE22 1BJ",
    "addr:housenumber":"192",
    "addr:postcode":"de22 1bj",
    "addr:street":"Duffield Road",
    "iso:country":"GB",
    "sg:address":"192 Duffield Road",
    "sg:city":"Derby",
    "sg:classifiers":[
        {
            "category":"Professional",
            "subcategory":"Business Services",
            "type":"Services"
        }
    ],
    "sg:phone":"+44 1332 265511",
    "sg:postcode":"DE22 1BJ",
    "sg:province":"Derbyshire",
    "sg:tags":[
        "trade"
    ],
    "wof:name":"Association of Suppliers to the Furniture Industry Ltd.",
    "wof:placetype":"venue"
},
  "geometry": {"coordinates":[-1.483569,52.93539],"type":"Point"}
}