{
  "type": "Feature",
  "properties": {
    "addr:full":"5 High Street Woking Surrey GU21 6BG",
    "addr:housenumber":"5",
    "addr:postcode":"gu21 6bg",
    "addr:street":"High Street",
    "iso:country":"GB",
    "sg:address":"5 High Street",
    "sg:city":"Woking",
    "sg:classifiers":[
        {
            "category":"Banks & Credit Unions",
            "subcategory":"Investment Brokerage",
            "type":"Services"
        },
        {
            "category":"Professional",
            "subcategory":"Business Services",
            "type":"Services"
        }
    ],
    "sg:phone":"+44 1483 720030",
    "sg:postcode":"GU21 6BG",
    "sg:province":"Surrey",
    "sg:tags":[
        "accomodation",
        "bullion"
    ],
    "wof:name":"Temple Court Business Centre",
    "wof:placetype":"venue"
},
  "geometry": {"coordinates":[-0.5575090051,51.3187561035],"type":"Point"}
}