{
  "type": "Feature",
  "properties": {
    "addr:full":"62 Barnsley Road, Upper Cumberworth Huddersfield South Yorkshire HD8 8NS",
    "addr:housenumber":"62",
    "addr:postcode":"hd8 8ns",
    "addr:street":"Barnsley Road Upper",
    "iso:country":"GB",
    "sg:address":"62 Barnsley Road, Upper Cumberworth",
    "sg:city":"Huddersfield",
    "sg:classifiers":[
        {
            "category":"Building & Trades",
            "subcategory":"Construction",
            "type":"Services"
        }
    ],
    "sg:postcode":"HD8 8NS",
    "sg:province":"South Yorkshire",
    "sg:tags":[
        "builder"
    ],
    "wof:name":"Wagstaff Builders",
    "wof:placetype":"venue"
},
  "geometry": {"coordinates":[-1.6877219677,53.5748291016],"type":"Point"}
}