{
  "type": "Feature",
  "properties": {
    "addr:full":"39 High Street Watford Hertfordshire WD23 1BD",
    "addr:housenumber":"39",
    "addr:postcode":"wd23 1bd",
    "addr:street":"High Street",
    "iso:country":"GB",
    "sg:address":"39 High Street",
    "sg:city":"Watford",
    "sg:classifiers":[
        {
            "category":"Shopping",
            "subcategory":"Computers & Home Electronics",
            "type":"Retail Goods"
        }
    ],
    "sg:phone":"+44 20 8386 1545",
    "sg:postcode":"WD23 1BD",
    "sg:province":"Hertfordshire",
    "wof:name":"French Country Dining Tables Ltd.",
    "wof:placetype":"venue"
},
  "geometry": {"coordinates":[-0.39726,51.656425],"type":"Point"}
}