{
  "type": "Feature",
  "properties": {
    "addr:full":"Nickel Close, Winnall Winchester Hampshire SO23 7RJ",
    "addr:postcode":"so23 7rj",
    "addr:street":"Nickel Close",
    "iso:country":"GB",
    "sg:address":"Nickel Close, Winnall",
    "sg:city":"Winchester",
    "sg:classifiers":[
        {
            "category":"Professional",
            "subcategory":"Printing & Photocopies",
            "type":"Services"
        }
    ],
    "sg:phone":"+44 1962 855155",
    "sg:postcode":"SO23 7RJ",
    "sg:province":"Hampshire",
    "sg:tags":[
        "printer"
    ],
    "wof:name":"Setprint",
    "wof:placetype":"venue"
},
  "geometry": {"coordinates":[-1.3168090582,51.0630683899],"type":"Point"}
}