{
  "type": "Feature",
  "properties": {
    "iso:country":"GB",
    "sg:address":"44 Hawthorn Crescent, Tottington",
    "sg:city":"Bury",
    "sg:classifiers":[
        {
            "category":"Building & Trades",
            "subcategory":"Construction",
            "type":"Services"
        }
    ],
    "sg:phone":"+44 1204 885062",
    "sg:postcode":"BL8 3NG",
    "sg:province":"Lancashire",
    "sg:tags":[
        "glazier"
    ],
    "wof:name":"John Henderson",
    "wof:placetype":"venue"
},
  "geometry": {"coordinates":[-2.335475,53.616608],"type":"Point"}
}