{
  "type": "Feature",
  "properties": {
    "iso:country":"GB",
    "sg:address":"142 The Rowans, Milton",
    "sg:city":"Cambridge",
    "sg:classifiers":[
        {
            "category":"Building & Trades",
            "subcategory":"Construction",
            "type":"Services"
        }
    ],
    "sg:phone":"+44 1223 571212",
    "sg:postcode":"CB4 6YX",
    "sg:province":"Cambridgeshire",
    "sg:tags":[
        "glazier"
    ],
    "wof:name":"Paul Dopson",
    "wof:placetype":"venue"
},
  "geometry": {"coordinates":[0.156627,52.24736],"type":"Point"}
}