{
  "type": "Feature",
  "properties": {
    "addr:full":"8 Windermere Avenue St Albans Hertfordshire AL1 5QW",
    "addr:housenumber":"8",
    "addr:postcode":"al1 5qw",
    "addr:street":"Windermere Avenue",
    "iso:country":"GB",
    "sg:address":"8 Windermere Avenue",
    "sg:city":"St Albans",
    "sg:classifiers":[
        {
            "category":"Professional",
            "subcategory":"Engineering",
            "type":"Services"
        }
    ],
    "sg:phone":"+44 1727 850980",
    "sg:postcode":"AL1 5QW",
    "sg:province":"Hertfordshire",
    "sg:tags":[
        "contractor",
        "electrical",
        "engineer"
    ],
    "wof:name":"Welex Electrical Ltd.",
    "wof:placetype":"venue"
},
  "geometry": {"coordinates":[-0.307945,51.745495],"type":"Point"}
}