{
  "type": "Feature",
  "properties": {
    "addr:full":"39-43 The Green Southall Greater London UB2 4AN",
    "addr:housenumber":"39-43",
    "addr:postcode":"ub2 4an",
    "addr:street":"The Green",
    "iso:country":"GB",
    "sg:address":"39-43 The Green",
    "sg:city":"Southall",
    "sg:classifiers":[
        {
            "category":"Autos & Motor Vehicles",
            "subcategory":"Auto Supplies",
            "type":"Retail Goods"
        }
    ],
    "sg:phone":"+44 20 8813 9154",
    "sg:postcode":"UB2 4AN",
    "sg:province":"Greater London",
    "sg:tags":[
        "tyre"
    ],
    "wof:name":"Auto Tyres & Exhausts Ltd",
    "wof:placetype":"venue"
},
  "geometry": {"coordinates":[-0.379731,51.504063],"type":"Point"}
}