{
  "type": "Feature",
  "properties": {
    "iso:country":"GB",
    "sg:address":"Atlantic Way",
    "sg:city":"Barry",
    "sg:classifiers":[
        {
            "category":"Freight",
            "type":"Transportation"
        }
    ],
    "sg:phone":"+44 1446 420800",
    "sg:postcode":"CF63 3RA",
    "sg:province":"The Vale of Glamorgan",
    "sg:tags":[
        "haulage",
        "transport",
        "road"
    ],
    "wof:name":"John T Evans Haulage Contractors",
    "wof:placetype":"venue"
},
  "geometry": {"coordinates":[-3.2487089634,51.4039115906],"type":"Point"}
}