{
  "type": "Feature",
  "properties": {
    "addr:full":"37 Mallory Road Hove East Sussex BN3 6TD",
    "addr:housenumber":"37",
    "addr:postcode":"bn3 6td",
    "addr:street":"Mallory Road",
    "iso:country":"GB",
    "sg:address":"37 Mallory Road",
    "sg:city":"Hove",
    "sg:classifiers":[
        {
            "category":"Real Estate",
            "subcategory":"Architect",
            "type":"Services"
        }
    ],
    "sg:postcode":"BN3 6TD",
    "sg:province":"East Sussex",
    "sg:tags":[
        "architectural"
    ],
    "wof:name":"Garmston Associates Ltd.",
    "wof:placetype":"venue"
},
  "geometry": {"coordinates":[-0.1627839953,50.8447532654],"type":"Point"}
}