{
  "type": "Feature",
  "properties": {
    "addr:full":"Unit 14, St Annes Road Willenhall West Midlands WV13 1DY",
    "addr:housenumber":"unit 14",
    "addr:postcode":"wv13 1dy",
    "addr:street":"St Annes Road",
    "iso:country":"GB",
    "sg:address":"Unit 14, St Annes Road",
    "sg:city":"Willenhall",
    "sg:classifiers":[
        {
            "category":"Home & Garden",
            "subcategory":"Building Materials",
            "type":"Retail Goods"
        }
    ],
    "sg:phone":"+44 1902 603892",
    "sg:postcode":"WV13 1DY",
    "sg:province":"West Midlands",
    "sg:tags":[
        "ironwork",
        "diy",
        "wrought"
    ],
    "wof:name":"G A Fabrications (W/Hall) Ltd.",
    "wof:placetype":"venue"
},
  "geometry": {"coordinates":[-2.050868988,52.5921516418],"type":"Point"}
}