{
  "type": "Feature",
  "properties": {
    "iso:country":"GB",
    "sg:address":"202 Deakin Avenue, Witton",
    "sg:city":"Birmingham",
    "sg:classifiers":[
        {
            "category":"Home & Garden",
            "subcategory":"Building Materials",
            "type":"Retail Goods"
        }
    ],
    "sg:phone":"+44 121 327 5264",
    "sg:postcode":"B6 7BH",
    "sg:province":"West Midlands",
    "sg:tags":[
        "insulation",
        "installers"
    ],
    "wof:name":"J Cullen Thermals Ltd.",
    "wof:placetype":"venue"
},
  "geometry": {"coordinates":[-1.880706,52.514698],"type":"Point"}
}