{
  "type": "Feature",
  "properties": {
    "iso:country":"GB",
    "sg:address":"Grosvenor House, 16 Grosvenor Road",
    "sg:city":"Cheadle",
    "sg:classifiers":[
        {
            "category":"Building & Trades",
            "subcategory":"Construction",
            "type":"Services"
        }
    ],
    "sg:phone":"+44 161 485 4582",
    "sg:postcode":"SK8 5QL",
    "sg:province":"Cheshire",
    "sg:tags":[
        "dry",
        "lining",
        "plasterers",
        "screeders"
    ],
    "wof:name":"Plaster Plus Ltd.",
    "wof:placetype":"venue"
},
  "geometry": {"coordinates":[-2.1789050102,53.3881416321],"type":"Point"}
}