{
  "type": "Feature",
  "properties": {
    "iso:country":"GB",
    "sg:address":"Salisbury Road",
    "sg:city":"York",
    "sg:classifiers":[
        {
            "category":"Retail",
            "subcategory":"Veterinary Services",
            "type":"Services"
        }
    ],
    "sg:phone":"+44 1904 643997",
    "sg:postcode":"YO26 4YN",
    "sg:province":"North Yorkshire",
    "sg:tags":[
        "surgeon",
        "activity"
    ],
    "wof:name":"The Minster Veterinary Practice",
    "wof:placetype":"venue"
},
  "geometry": {"coordinates":[-1.109115,53.965263],"type":"Point"}
}