{
  "type": "Feature",
  "properties": {
    "iso:country":"GB",
    "sg:address":"Pulsar House, 1-3 Malvern Rd",
    "sg:city":"Maidenhead",
    "sg:classifiers":[
        {
            "category":"Professional",
            "subcategory":"Business Services",
            "type":"Services"
        }
    ],
    "sg:phone":"+44 1628 798133",
    "sg:postcode":"SL6 7QY",
    "sg:province":"Berkshire",
    "sg:tags":[
        "distribution"
    ],
    "wof:name":"C D Group Holdings",
    "wof:placetype":"venue"
},
  "geometry": {"coordinates":[-0.7349889874,51.5340194702],"type":"Point"}
}