{
  "type": "Feature",
  "properties": {
    "addr:full":"Unit A And B, Shenfield Court, Perry Road Harlow Essex CM18 7NN",
    "addr:housenumber":"unit",
    "addr:postcode":"cm18 7nn",
    "addr:street":"And B Shenfield Court Perry Road",
    "iso:country":"GB",
    "sg:address":"Unit A And B, Shenfield Court, Perry Road",
    "sg:city":"Harlow",
    "sg:classifiers":[
        {
            "category":"Autos & Motor Vehicles",
            "subcategory":"Auto Supplies",
            "type":"Retail Goods"
        }
    ],
    "sg:phone":"+44 1279 421461",
    "sg:postcode":"CM18 7NN",
    "sg:province":"Essex",
    "sg:tags":[
        "gearbox"
    ],
    "wof:name":"Royce Power Transmission Services Plc",
    "wof:placetype":"venue"
},
  "geometry": {"coordinates":[0.0895659998,51.7510528564],"type":"Point"}
}