{
  "type": "Feature",
  "properties": {
    "addr:full":"2 Sinclair Drive Glasgow Glasgow City G42 9QE",
    "addr:housenumber":"2",
    "addr:postcode":"g42 9qe",
    "addr:street":"Sinclair Drive",
    "iso:country":"GB",
    "sg:address":"2 Sinclair Drive",
    "sg:city":"Glasgow",
    "sg:classifiers":[
        {
            "category":"Education",
            "subcategory":"Library",
            "type":"Public Place"
        }
    ],
    "sg:phone":"+44 141 632 0810",
    "sg:postcode":"G42 9QE",
    "sg:province":"Glasgow City",
    "sg:tags":[
        "book"
    ],
    "wof:name":"Langside Library",
    "wof:placetype":"venue"
},
  "geometry": {"coordinates":[-4.267044,55.827011],"type":"Point"}
}