{
  "type": "Feature",
  "properties": {
    "iso:country":"GB",
    "sg:address":"142 King Street",
    "sg:city":"Castle Douglas",
    "sg:classifiers":[
        {
            "category":"Personal",
            "subcategory":"Beauty Salon",
            "type":"Services"
        }
    ],
    "sg:phone":"+44 1556 503652",
    "sg:postcode":"DG7 1LU",
    "sg:province":"Dumfries and Galloway",
    "sg:tags":[
        "unisex",
        "hairdresser"
    ],
    "wof:name":"Hallidays Hair Salon",
    "wof:placetype":"venue"
},
  "geometry": {"coordinates":[-3.930535078,54.9404640198],"type":"Point"}
}