{
  "type": "Feature",
  "properties": {
    "iso:country":"GB",
    "sg:address":"Torpenhow Hall, Torpenhow",
    "sg:city":"Wigton",
    "sg:classifiers":[
        {
            "category":"Farming",
            "subcategory":"Dairy Farm",
            "type":"Manufacturing & Wholesale Goods"
        }
    ],
    "sg:postcode":"CA7 1HT",
    "sg:province":"Cumbria",
    "wof:name":"Messrs Bell",
    "wof:placetype":"venue"
},
  "geometry": {"coordinates":[-3.240554,54.746265],"type":"Point"}
}