{
  "type": "Feature",
  "properties": {
    "addr:full":"5/7 Westover Road Bournemouth Dorset BH1 2BY",
    "addr:housenumber":"5 / 7",
    "addr:postcode":"bh1 2by",
    "addr:street":"Westover Road",
    "iso:country":"GB",
    "sg:address":"5/7 Westover Road",
    "sg:city":"Bournemouth",
    "sg:classifiers":[
        {
            "category":"Food & Beverages",
            "subcategory":"Candy",
            "type":"Retail Goods"
        }
    ],
    "sg:phone":"+44 1202 789370",
    "sg:postcode":"BH1 2BY",
    "sg:province":"Dorset",
    "sg:tags":[
        "confectioner"
    ],
    "wof:name":"Westover Leisure Ltd.",
    "wof:placetype":"venue"
},
  "geometry": {"coordinates":[-1.876025,50.719318],"type":"Point"}
}