{
  "type": "Feature",
  "properties": {
    "addr:full":"Forge Lane Halesowen West Midlands B62 8EF",
    "addr:postcode":"b62 8ef",
    "addr:street":"Forge Lane",
    "iso:country":"GB",
    "sg:address":"Forge Lane",
    "sg:city":"Halesowen",
    "sg:classifiers":[
        {
            "category":"Shopping",
            "subcategory":"Optical Goods",
            "type":"Retail Goods"
        }
    ],
    "sg:phone":"+44 121 550 8986",
    "sg:postcode":"B62 8EF",
    "sg:province":"West Midlands",
    "wof:name":"Chadwick Taylor",
    "wof:placetype":"venue"
},
  "geometry": {"coordinates":[-2.044965,52.454617],"type":"Point"}
}