{
  "type": "Feature",
  "properties": {
    "iso:country":"GB",
    "sg:address":"998 Stratford Rd",
    "sg:city":"Birmingham",
    "sg:classifiers":[
        {
            "category":"Building & Trades",
            "subcategory":"Construction",
            "type":"Services"
        }
    ],
    "sg:phone":"+44 121 243 1010",
    "sg:postcode":"B28 8BJ",
    "sg:province":"West Midlands",
    "sg:tags":[
        "builder"
    ],
    "wof:name":"Ims Industrial Maintenance Services Ltd",
    "wof:placetype":"venue"
},
  "geometry": {"coordinates":[-1.852749,52.443001],"type":"Point"}
}