{
  "type": "Feature",
  "properties": {
    "addr:full":"Ashurst Hospital, Lyndhurst Road, Ashurst Southampton Hampshire SO40 7AR",
    "addr:postcode":"so40 7ar",
    "addr:street":"Lyndhurst Road",
    "iso:country":"GB",
    "sg:address":"Ashurst Hospital, Lyndhurst Road, Ashurst",
    "sg:city":"Southampton",
    "sg:classifiers":[
        {
            "category":"Health Services",
            "subcategory":"Hospital",
            "type":"Services"
        }
    ],
    "sg:phone":"+44 23 8029 3636",
    "sg:postcode":"SO40 7AR",
    "sg:province":"Hampshire",
    "wof:name":"Snowdon House",
    "wof:placetype":"venue"
},
  "geometry": {"coordinates":[-1.5166840553,50.8948135376],"type":"Point"}
}