{
  "type": "Feature",
  "properties": {
    "iso:country":"GB",
    "sg:address":"12 Rea Street",
    "sg:city":"Birmingham",
    "sg:classifiers":[
        {
            "category":"Home & Garden",
            "subcategory":"Furniture",
            "type":"Retail Goods"
        }
    ],
    "sg:phone":"+44 121 772 5342",
    "sg:postcode":"B5 6LB",
    "sg:province":"West Midlands",
    "wof:name":"World of Pine",
    "wof:placetype":"venue"
},
  "geometry": {"coordinates":[-1.889119,52.473419],"type":"Point"}
}