{
  "type": "Feature",
  "properties": {
    "addr:full":"12 Rea Street Birmingham West Midlands B5 6LB",
    "addr:housenumber":"12",
    "addr:postcode":"b5 6lb",
    "addr:street":"Rea Street",
    "iso:country":"GB",
    "sg:address":"12 Rea Street",
    "sg:city":"Birmingham",
    "sg:classifiers":[
        {
            "category":"Home & Garden",
            "subcategory":"Furniture",
            "type":"Retail Goods"
        }
    ],
    "sg:phone":"+44 121 772 5342",
    "sg:postcode":"B5 6LB",
    "sg:province":"West Midlands",
    "wof:name":"World of Pine",
    "wof:placetype":"venue"
},
  "geometry": {"coordinates":[-1.889119,52.473419],"type":"Point"}
}