{
  "type": "Feature",
  "properties": {
    "addr:full":"2-4 High Street Bristol Somerset BS20 6EW",
    "addr:housenumber":"2-4",
    "addr:postcode":"bs20 6ew",
    "addr:street":"High Street",
    "iso:country":"GB",
    "sg:address":"2-4 High Street",
    "sg:city":"Bristol",
    "sg:classifiers":[
        {
            "category":"Professional",
            "subcategory":"Printing & Photocopies",
            "type":"Services"
        }
    ],
    "sg:phone":"+44 1275 844100",
    "sg:postcode":"BS20 6EW",
    "sg:province":"Somerset",
    "sg:tags":[
        "printer"
    ],
    "wof:name":"Printacopy",
    "wof:placetype":"venue"
},
  "geometry": {"coordinates":[-2.768148,51.485405],"type":"Point"}
}