{
  "type": "Feature",
  "properties": {
    "iso:country":"GB",
    "sg:address":"Brancepeth Rd",
    "sg:city":"Washington",
    "sg:classifiers":[
        {
            "category":"Place Of Worship",
            "type":"Public Place"
        }
    ],
    "sg:phone":"+44 191 416 3071",
    "sg:postcode":"NE38 0LA",
    "sg:province":"Durham",
    "wof:name":"Oxclose Ecumenical Church",
    "wof:placetype":"venue"
},
  "geometry": {"coordinates":[-1.54394,54.897228],"type":"Point"}
}