{
  "type": "Feature",
  "properties": {
    "addr:full":"20 Wisteria Court, Up Hatherley Cheltenham Gloucestershire GL51 3WG",
    "addr:housenumber":"20",
    "addr:postcode":"gl51 3wg",
    "addr:street":"Wisteria Court",
    "iso:country":"GB",
    "sg:address":"20 Wisteria Court, Up Hatherley",
    "sg:city":"Cheltenham",
    "sg:classifiers":[
        {
            "category":"Home & Garden",
            "subcategory":"Carpets & Floor Coverings",
            "type":"Retail Goods"
        }
    ],
    "sg:phone":"+44 1242 516657",
    "sg:postcode":"GL51 3WG",
    "sg:province":"Gloucestershire",
    "sg:tags":[
        "carpets",
        "rug",
        "matting"
    ],
    "wof:name":"Jason Bond Rd",
    "wof:placetype":"venue"
},
  "geometry": {"coordinates":[-2.102404,51.878334],"type":"Point"}
}