{
  "type": "Feature",
  "properties": {
    "iso:country":"GB",
    "sg:address":"154 Ellesmere Road",
    "sg:city":"Bolton",
    "sg:classifiers":[
        {
            "category":"Professional",
            "subcategory":"Engineering",
            "type":"Services"
        }
    ],
    "sg:postcode":"BL3 3JN",
    "sg:province":"Lancashire",
    "sg:tags":[
        "design",
        "engineer"
    ],
    "wof:name":"Design Engineering Gb Ltd",
    "wof:placetype":"venue"
},
  "geometry": {"coordinates":[-2.448156,53.562138],"type":"Point"}
}