{
  "type": "Feature",
  "properties": {
    "addr:full":"Peel House (the), Wolverhampton Road, Pattingham Wolverhampton Shropshire WV6 7AF",
    "addr:postcode":"wv6 7af",
    "addr:street":"The Wolverhampton Road",
    "iso:country":"GB",
    "sg:address":"Peel House (the), Wolverhampton Road, Pattingham",
    "sg:city":"Wolverhampton",
    "sg:classifiers":[
        {
            "category":"Professional",
            "subcategory":"Art Services",
            "type":"Services"
        }
    ],
    "sg:postcode":"WV6 7AF",
    "sg:province":"Shropshire",
    "sg:tags":[
        "photographer"
    ],
    "wof:name":"Brett Prestidge",
    "wof:placetype":"venue"
},
  "geometry": {"coordinates":[-2.262564,52.589169],"type":"Point"}
}