{
  "type": "Feature",
  "properties": {
    "addr:full":"Lynwood Road Liverpool Merseyside L9 3AE",
    "addr:postcode":"l9 3ae",
    "addr:street":"Lynwood Road",
    "iso:country":"GB",
    "sg:address":"Lynwood Road",
    "sg:city":"Liverpool",
    "sg:classifiers":[
        {
            "category":"Education",
            "subcategory":"School",
            "type":"Public Place"
        },
        {
            "category":"Government",
            "subcategory":"Office",
            "type":"Public Place"
        }
    ],
    "sg:phone":"+44 151 525 9776",
    "sg:postcode":"L9 3AE",
    "sg:province":"Merseyside",
    "sg:tags":[
        "local",
        "authority"
    ],
    "wof:name":"Rice Lane Infant & Nursery School",
    "wof:placetype":"venue"
},
  "geometry": {"coordinates":[-2.963208,53.459663],"type":"Point"}
}