{
  "type": "Feature",
  "properties": {
    "addr:full":"4-6 Guildhall Road Northampton Northamptonshire NN1 1DP",
    "addr:housenumber":"4-6",
    "addr:postcode":"nn1 1dp",
    "addr:street":"Guildhall Road",
    "iso:country":"GB",
    "sg:address":"4-6 Guildhall Road",
    "sg:city":"Northampton",
    "sg:classifiers":[
        {
            "category":"Museum",
            "subcategory":"Art Museum",
            "type":"Entertainment"
        },
        {
            "category":"Arts & Performance",
            "subcategory":"Theater",
            "type":"Entertainment"
        }
    ],
    "sg:phone":"+44 1604 238548",
    "sg:postcode":"NN1 1DP",
    "sg:province":"Northamptonshire",
    "sg:tags":[
        "gallery",
        "concert",
        "theatre",
        "hall"
    ],
    "wof:name":"Royal Theatre",
    "wof:placetype":"venue"
},
  "geometry": {"coordinates":[-0.894574,52.236343],"type":"Point"}
}