{
  "type": "Feature",
  "properties": {
    "iso:country":"GB",
    "sg:address":"13 Brookdale",
    "sg:city":"Ottery St Mary",
    "sg:classifiers":[
        {
            "category":"Professional",
            "subcategory":"Art Services",
            "type":"Services"
        },
        {
            "category":"Building & Trades",
            "subcategory":"Construction",
            "type":"Services"
        },
        {
            "category":"Manufacturing",
            "subcategory":"Paper Products",
            "type":"Manufacturing & Wholesale Goods"
        }
    ],
    "sg:phone":"+44 1404 813217",
    "sg:postcode":"EX11 1EB",
    "sg:province":"Devon",
    "sg:tags":[
        "cardboard",
        "decorator",
        "painter"
    ],
    "wof:name":"JIMMIE ISAAC",
    "wof:placetype":"venue"
},
  "geometry": {"coordinates":[-3.283026,50.751137],"type":"Point"}
}