{
  "type": "Feature",
  "properties": {
    "addr:full":"Northshore Yacht Yard, Itchenor Chichester West Sussex PO20 7AE",
    "addr:postcode":"po20 7ae",
    "iso:country":"GB",
    "sg:address":"Northshore Yacht Yard, Itchenor",
    "sg:city":"Chichester",
    "sg:classifiers":[
        {
            "category":"Farming",
            "subcategory":"Fish & Marine Products",
            "type":"Manufacturing & Wholesale Goods"
        }
    ],
    "sg:phone":"+44 1243 511070",
    "sg:postcode":"PO20 7AE",
    "sg:province":"West Sussex",
    "sg:tags":[
        "equipment",
        "electrical"
    ],
    "wof:name":"Greenham & Regis Electronics",
    "wof:placetype":"venue"
},
  "geometry": {"coordinates":[-0.8668180108,50.7997283936],"type":"Point"}
}