{
  "type": "Feature",
  "properties": {
    "iso:country":"GB",
    "sg:address":"Wormsley",
    "sg:city":"Hereford",
    "sg:classifiers":[
        {
            "category":"Sports & Exercise",
            "subcategory":"Golf",
            "type":"Entertainment"
        }
    ],
    "sg:phone":"+44 1432 830219",
    "sg:postcode":"HR4 8LY",
    "sg:province":"Herefordshire",
    "sg:tags":[
        "club",
        "course",
        "equipment"
    ],
    "wof:name":"Herefordshire Golf Club",
    "wof:placetype":"venue"
},
  "geometry": {"coordinates":[-2.8331360817,52.1262397766],"type":"Point"}
}