{
  "type": "Feature",
  "properties": {
    "addr:full":"66 Bounces Road London Greater London N9 8JS",
    "addr:housenumber":"66",
    "addr:postcode":"n9 8js",
    "addr:street":"Bounces Road",
    "iso:country":"GB",
    "sg:address":"66 Bounces Road",
    "sg:city":"London",
    "sg:classifiers":[
        {
            "category":"Personal",
            "subcategory":"Beauty Salon",
            "type":"Services"
        },
        {
            "category":"Personal",
            "subcategory":"Barber",
            "type":"Services"
        }
    ],
    "sg:phone":"+44 20 8807 7311",
    "sg:postcode":"N9 8JS",
    "sg:province":"Greater London",
    "sg:tags":[
        "unisex",
        "hairdresser"
    ],
    "wof:name":"Lustrous Hair",
    "wof:placetype":"venue"
},
  "geometry": {"coordinates":[-0.0524680018,51.6282615662],"type":"Point"}
}