{
  "type": "Feature",
  "properties": {
    "iso:country":"GB",
    "sg:address":"Holme Mills Industrial Park, Britannia Road",
    "sg:city":"Huddersfield",
    "sg:classifiers":[
        {
            "category":"Home & Garden",
            "subcategory":"Building Materials",
            "type":"Retail Goods"
        }
    ],
    "sg:phone":"+44 1484 461083",
    "sg:postcode":"HD3 4QG",
    "sg:province":"West Yorkshire",
    "sg:tags":[
        "tanks",
        "cistern",
        "vat"
    ],
    "wof:name":"Kel-Air Plastics Ltd.",
    "wof:placetype":"venue"
},
  "geometry": {"coordinates":[-1.83737,53.63858],"type":"Point"}
}