{
  "type": "Feature",
  "properties": {
    "addr:full":"19a St Margarets Street Canterbury Kent CT1 2TH",
    "addr:housenumber":"19a",
    "addr:postcode":"ct1 2th",
    "addr:street":"St Margarets Street",
    "iso:country":"GB",
    "sg:address":"19a St Margarets Street",
    "sg:city":"Canterbury",
    "sg:classifiers":[
        {
            "category":"Shopping",
            "subcategory":"Florist",
            "type":"Retail Goods"
        }
    ],
    "sg:phone":"+44 1227 463275",
    "sg:postcode":"CT1 2TH",
    "sg:province":"Kent",
    "wof:name":"Marlowe Florist",
    "wof:placetype":"venue"
},
  "geometry": {"coordinates":[1.08028,51.278278],"type":"Point"}
}