{
  "type": "Feature",
  "properties": {
    "addr:full":"Stannary Road, Stenalees St Austell Cornwall PL26 8SP",
    "addr:postcode":"pl26 8sp",
    "addr:street":"Stannary Road",
    "iso:country":"GB",
    "sg:address":"Stannary Road, Stenalees",
    "sg:city":"St Austell",
    "sg:classifiers":[
        {
            "category":"Shopping",
            "subcategory":"Department Store",
            "type":"Retail Goods"
        }
    ],
    "sg:phone":"+44 1726 850372",
    "sg:postcode":"PL26 8SP",
    "sg:province":"Cornwall",
    "wof:name":"General Stores",
    "wof:placetype":"venue"
},
  "geometry": {"coordinates":[-4.793715,50.385204],"type":"Point"}
}