{
  "type": "Feature",
  "properties": {
    "iso:country":"GB",
    "sg:address":"90 Springbank Road",
    "sg:city":"London",
    "sg:classifiers":[
        {
            "category":"Cafe",
            "type":"Food & Drink"
        }
    ],
    "sg:phone":"+44 20 8265 6654",
    "sg:postcode":"SE13 6SX",
    "sg:province":"Greater London",
    "sg:tags":[
        "tea",
        "room"
    ],
    "wof:name":"The Full Monty",
    "wof:placetype":"venue"
},
  "geometry": {"coordinates":[0.000507,51.449215],"type":"Point"}
}