{
  "type": "Feature",
  "properties": {
    "addr:full":"1 Mccrone Mews London Greater London NW3 5BG",
    "addr:housenumber":"1",
    "addr:postcode":"nw3 5bg",
    "addr:street":"Mccrone Mews",
    "iso:country":"GB",
    "sg:address":"1 Mccrone Mews",
    "sg:city":"London",
    "sg:classifiers":[
        {
            "category":"Professional",
            "subcategory":"Management & Consulting",
            "type":"Services"
        }
    ],
    "sg:phone":"+44 20 7431 8271",
    "sg:postcode":"NW3 5BG",
    "sg:province":"Greater London",
    "sg:tags":[
        "music"
    ],
    "wof:name":"140DB Management",
    "wof:placetype":"venue"
},
  "geometry": {"coordinates":[-0.172539,51.548538],"type":"Point"}
}