{
  "type": "Feature",
  "properties": {
    "iso:country":"GB",
    "sg:address":"Minshull Ho, 47-49 Chorlton St",
    "sg:city":"Manchester",
    "sg:classifiers":[
        {
            "category":"Sports & Exercise",
            "subcategory":"Bowling",
            "type":"Entertainment"
        }
    ],
    "sg:phone":"+44 161 247 3097",
    "sg:postcode":"M60 7DN",
    "sg:province":"Greater Manchester",
    "sg:tags":[
        "photography"
    ],
    "wof:name":"North West Film Archive",
    "wof:placetype":"venue"
},
  "geometry": {"coordinates":[-2.22892,53.476429],"type":"Point"}
}