{
  "type": "Feature",
  "properties": {
    "addr:full":"74 Ashton Road West, Failsworth Manchester Lancashire M35 0ES",
    "addr:housenumber":"74",
    "addr:postcode":"m35 0es",
    "addr:street":"Ashton Road West",
    "iso:country":"GB",
    "sg:address":"74 Ashton Road West, Failsworth",
    "sg:city":"Manchester",
    "sg:classifiers":[
        {
            "category":"Bars & Pubs",
            "type":"Food & Drink"
        }
    ],
    "sg:phone":"+44 161 681 3112",
    "sg:postcode":"M35 0ES",
    "sg:province":"Lancashire",
    "sg:tags":[
        "pubs",
        "inn"
    ],
    "wof:name":"The Mare & Foal",
    "wof:placetype":"venue"
},
  "geometry": {"coordinates":[-2.1606380939,53.5070800781],"type":"Point"}
}