{
  "type": "Feature",
  "properties": {
    "addr:full":"Newgale, Kingston Hill Kingston-upon-thames Greater London KT2 7JP",
    "addr:postcode":"kt2 7jp",
    "addr:street":"Newgale Kingston Hill Kingston-Upon-Thames",
    "iso:country":"GB",
    "sg:address":"Newgale, Kingston Hill",
    "sg:city":"Kingston-upon-thames",
    "sg:classifiers":[
        {
            "category":"Professional",
            "subcategory":"Business Services",
            "type":"Services"
        }
    ],
    "sg:phone":"+44 20 8974 5665",
    "sg:postcode":"KT2 7JP",
    "sg:province":"Greater London",
    "sg:tags":[
        "import",
        "export",
        "agent"
    ],
    "wof:name":"Dari Ltd.",
    "wof:placetype":"venue"
},
  "geometry": {"coordinates":[-0.281035,51.417801],"type":"Point"}
}