{
  "type": "Feature",
  "properties": {
    "addr:full":"17 Oxbridge Lane Stockton-on-tees Durham TS18 4AW",
    "addr:housenumber":"17",
    "addr:postcode":"ts18 4aw",
    "addr:street":"Oxbridge Lane",
    "iso:country":"GB",
    "sg:address":"17 Oxbridge Lane",
    "sg:city":"Stockton-on-tees",
    "sg:classifiers":[
        {
            "category":"Bars & Pubs",
            "type":"Food & Drink"
        }
    ],
    "sg:phone":"+44 1642 678129",
    "sg:postcode":"TS18 4AW",
    "sg:province":"Durham",
    "sg:tags":[
        "pubs",
        "inn"
    ],
    "wof:name":"The Oxbridge",
    "wof:placetype":"venue"
},
  "geometry": {"coordinates":[-1.3393210173,54.5630187988],"type":"Point"}
}