{
  "type": "Feature",
  "properties": {
    "addr:full":"512-516 Harrow Road, Paddington London Greater London W9 3QA",
    "addr:housenumber":"512-516",
    "addr:postcode":"w9 3qa",
    "addr:street":"Harrow Road",
    "iso:country":"GB",
    "sg:address":"512-516 Harrow Road, Paddington",
    "sg:city":"London",
    "sg:classifiers":[
        {
            "category":"Community Center",
            "subcategory":"Social",
            "type":"Public Place"
        }
    ],
    "sg:phone":"+44 20 8960 0918",
    "sg:postcode":"W9 3QA",
    "sg:province":"Greater London",
    "sg:tags":[
        "frozen",
        "food",
        "freezer",
        "centre"
    ],
    "wof:name":"Iceland Foods Plc",
    "wof:placetype":"venue"
},
  "geometry": {"coordinates":[-0.202828005,51.5250015259],"type":"Point"}
}