{
  "type": "Feature",
  "properties": {
    "addr:full":"Station Road Keswick Cumbria CA12 4NB",
    "addr:postcode":"ca12 4nb",
    "addr:street":"Station Road",
    "iso:country":"GB",
    "sg:address":"Station Road",
    "sg:city":"Keswick",
    "sg:classifiers":[
        {
            "category":"Education",
            "subcategory":"Special Training",
            "type":"Public Place"
        },
        {
            "category":"Professional",
            "subcategory":"Business Services",
            "type":"Services"
        }
    ],
    "sg:phone":"+44 17687 73100",
    "sg:postcode":"CA12 4NB",
    "sg:province":"Cumbria",
    "sg:tags":[
        "hospitality",
        "product",
        "corporate",
        "centre"
    ],
    "wof:name":"Active Imagination Ltd.",
    "wof:placetype":"venue"
},
  "geometry": {"coordinates":[-3.0553019047,54.6144142151],"type":"Point"}
}