{
  "type": "Feature",
  "properties": {
    "iso:country":"GB",
    "sg:address":"Unit 2 Queen St Industrial Estate, Queen Street, Queen Street",
    "sg:city":"Leeds",
    "sg:classifiers":[
        {
            "category":"Government",
            "subcategory":"Post Office",
            "type":"Public Place"
        }
    ],
    "sg:phone":"+44 113 270 0788",
    "sg:postcode":"LS10 1SL",
    "sg:province":"West Yorkshire",
    "sg:tags":[
        "messenger",
        "courier"
    ],
    "wof:name":"Securicor Pony Express",
    "wof:placetype":"venue"
},
  "geometry": {"coordinates":[-1.513201952,53.7721633911],"type":"Point"}
}