{
  "type": "Feature",
  "properties": {
    "iso:country":"GB",
    "sg:address":"New Cabin, Steven Road",
    "sg:city":"Huntly",
    "sg:classifiers":[
        {
            "category":"Wholesale",
            "subcategory":"Scrap",
            "type":"Manufacturing & Wholesale Goods"
        },
        {
            "category":"Wholesale",
            "subcategory":"Auto Parts",
            "type":"Manufacturing & Wholesale Goods"
        }
    ],
    "sg:phone":"+44 1466 792191",
    "sg:postcode":"AB54 8SX",
    "sg:province":"Aberdeenshire",
    "sg:tags":[
        "car",
        "breaker",
        "dismantlers"
    ],
    "wof:name":"Frasers Motor Spares",
    "wof:placetype":"venue"
},
  "geometry": {"coordinates":[-2.7934091091,57.4425811768],"type":"Point"}
}