{
  "type": "Feature",
  "properties": {
    "addr:full":"Metro Borough Weighbridge, Spring St Bury Lancashire BL9 0RW",
    "addr:postcode":"bl9 0rw",
    "addr:street":"Spring St",
    "iso:country":"GB",
    "sg:address":"Metro Borough Weighbridge, Spring St",
    "sg:city":"Bury",
    "sg:classifiers":[
        {
            "category":"Organizations",
            "subcategory":"Non-profit Organization",
            "type":"Services"
        }
    ],
    "sg:phone":"+44 161 763 1907",
    "sg:postcode":"BL9 0RW",
    "sg:province":"Lancashire",
    "sg:tags":[
        "organisation",
        "voluntary",
        "charity"
    ],
    "wof:name":"Bury & District Federation Of Tenants & Residents Association",
    "wof:placetype":"venue"
},
  "geometry": {"coordinates":[-2.3010540009,53.5897331238],"type":"Point"}
}