{
  "type": "Feature",
  "properties": {
    "iso:country":"GB",
    "sg:address":"Noddle, Halifax Rd",
    "sg:city":"Huddersfield",
    "sg:classifiers":[
        {
            "category":"Government",
            "subcategory":"Department Of Motor Vehicles",
            "type":"Public Place"
        }
    ],
    "sg:phone":"+44 1484 656888",
    "sg:postcode":"HD7 7NS",
    "sg:province":"West Yorkshire",
    "sg:tags":[
        "conversion"
    ],
    "wof:name":"Autotrim Specialist Services Ltd",
    "wof:placetype":"venue"
},
  "geometry": {"coordinates":[-1.78268,53.64695],"type":"Point"}
}