{
  "type": "Feature",
  "properties": {
    "addr:full":"11 Barnfield Way, Batheaston Bath Bath and North East Somerset BA1 7PW",
    "addr:housenumber":"11",
    "addr:postcode":"ba1 7pw",
    "addr:street":"Barnfield Way",
    "iso:country":"GB",
    "sg:address":"11 Barnfield Way, Batheaston",
    "sg:city":"Bath",
    "sg:classifiers":[
        {
            "category":"Building & Trades",
            "subcategory":"Construction",
            "type":"Services"
        }
    ],
    "sg:postcode":"BA1 7PW",
    "sg:province":"Bath and North East Somerset",
    "sg:tags":[
        "builder"
    ],
    "wof:name":"K I G Construction Ltd.",
    "wof:placetype":"venue"
},
  "geometry": {"coordinates":[-2.3089809418,51.406993866],"type":"Point"}
}