{
  "type": "Feature",
  "properties": {
    "addr:full":"250 Victoria Avenue, Ockbrook Derby Derbyshire DE72 3RL",
    "addr:housenumber":"250",
    "addr:postcode":"de72 3rl",
    "addr:street":"Victoria Avenue",
    "iso:country":"GB",
    "sg:address":"250 Victoria Avenue, Ockbrook",
    "sg:city":"Derby",
    "sg:classifiers":[
        {
            "category":"Professional",
            "subcategory":"Engineering",
            "type":"Services"
        },
        {
            "category":"Retail",
            "subcategory":"Event Space",
            "type":"Services"
        }
    ],
    "sg:phone":"+44 1332 676984",
    "sg:postcode":"DE72 3RL",
    "sg:province":"Derbyshire",
    "sg:tags":[
        "civil",
        "pipeline",
        "engineer"
    ],
    "wof:name":"Pipeline Personnel Services Ltd.",
    "wof:placetype":"venue"
},
  "geometry": {"coordinates":[-1.375326,52.915504],"type":"Point"}
}