{
  "type": "Feature",
  "properties": {
    "iso:country":"GB",
    "sg:address":"The Quay, Polruan",
    "sg:city":"Fowey",
    "sg:classifiers":[
        {
            "category":"Health Services",
            "subcategory":"Doctor",
            "type":"Services"
        }
    ],
    "sg:phone":"+44 1726 870396",
    "sg:postcode":"PL23 1PA",
    "sg:province":"Cornwall",
    "sg:tags":[
        "practitioners"
    ],
    "wof:name":"A Middleton",
    "wof:placetype":"venue"
},
  "geometry": {"coordinates":[-4.639648,50.336273],"type":"Point"}
}