{
  "type": "Feature",
  "properties": {
    "addr:full":"405 High St Stratford Greater London E15 4QZ",
    "addr:housenumber":"405",
    "addr:postcode":"e15 4qz",
    "addr:street":"High St",
    "iso:country":"GB",
    "sg:address":"405 High St",
    "sg:city":"Stratford",
    "sg:classifiers":[
        {
            "category":"Professional",
            "subcategory":"Business Services",
            "type":"Services"
        }
    ],
    "sg:phone":"+44 20 8519 5550",
    "sg:postcode":"E15 4QZ",
    "sg:province":"Greater London",
    "sg:tags":[
        "import",
        "export",
        "agent"
    ],
    "wof:name":"United Group International Ltd",
    "wof:placetype":"venue"
},
  "geometry": {"coordinates":[0.000124,51.5395011902],"type":"Point"}
}