{
  "type": "Feature",
  "properties": {
    "iso:country":"GB",
    "sg:address":"5 Abbey Drive, Orrell",
    "sg:city":"Wigan",
    "sg:classifiers":[
        {
            "category":"Building & Trades",
            "subcategory":"Construction",
            "type":"Services"
        }
    ],
    "sg:phone":"+44 1942 222766",
    "sg:postcode":"WN5 8RW",
    "sg:province":"Lancashire",
    "sg:tags":[
        "joiner",
        "carpenter"
    ],
    "wof:name":"Neil  Chisnall",
    "wof:placetype":"venue"
},
  "geometry": {"coordinates":[-2.707147,53.53854],"type":"Point"}
}