{
  "type": "Feature",
  "properties": {
    "addr:full":"41 Regent Street Rugby Warwickshire CV21 2PS",
    "addr:housenumber":"41",
    "addr:postcode":"cv21 2ps",
    "addr:street":"Regent Street",
    "iso:country":"GB",
    "sg:address":"41 Regent Street",
    "sg:city":"Rugby",
    "sg:classifiers":[
        {
            "category":"Real Estate",
            "subcategory":"Real Estate Agent",
            "type":"Services"
        }
    ],
    "sg:phone":"+44 1788 551111",
    "sg:postcode":"CV21 2PS",
    "sg:province":"Warwickshire",
    "wof:name":"Brown & Cockerill Estate Agents & Financial Services",
    "wof:placetype":"venue"
},
  "geometry": {"coordinates":[-1.2609159946,52.3741264343],"type":"Point"}
}