{
  "type": "Feature",
  "properties": {
    "addr:full":"253 Doncaster Road Barnsley South Yorkshire S70 3RH",
    "addr:housenumber":"253",
    "addr:postcode":"s70 3rh",
    "addr:street":"Doncaster Road;Yorkshire",
    "iso:country":"GB",
    "sg:address":"253 Doncaster Road",
    "sg:city":"Barnsley",
    "sg:classifiers":[
        {
            "category":"Retail",
            "subcategory":"Laundry & Dry Cleaning",
            "type":"Services"
        },
        {
            "category":"Wholesale",
            "subcategory":"Vending Machines",
            "type":"Manufacturing & Wholesale Goods"
        }
    ],
    "sg:phone":"+44 1226 298981",
    "sg:postcode":"S70 3RH",
    "sg:province":"South Yorkshire",
    "sg:tags":[
        "type",
        "washing",
        "alteration"
    ],
    "wof:name":"Stairfoot Dry Cleaners & Launderette",
    "wof:placetype":"venue"
},
  "geometry": {"coordinates":[-1.450461,53.546505],"type":"Point"}
}