{
  "type": "Feature",
  "properties": {
    "addr:full":"10 High Street Dronfield Derbyshire S18 1PY",
    "addr:housenumber":"10",
    "addr:postcode":"s18 1py",
    "addr:street":"High Street",
    "iso:country":"GB",
    "sg:address":"10 High Street",
    "sg:city":"Dronfield",
    "sg:classifiers":[
        {
            "category":"Shopping",
            "subcategory":"Gifts & Souvenirs",
            "type":"Retail Goods"
        }
    ],
    "sg:phone":"+44 1246 291179",
    "sg:postcode":"S18 1PY",
    "sg:province":"Derbyshire",
    "sg:tags":[
        "poster",
        "card"
    ],
    "wof:name":"C A Sorsby",
    "wof:placetype":"venue"
},
  "geometry": {"coordinates":[-1.4740350246,53.3021125793],"type":"Point"}
}