{
  "type": "Feature",
  "properties": {
    "addr:full":"7 Main Street Ferryhill Durham DL17 8LA",
    "addr:housenumber":"7",
    "addr:postcode":"dl17 8la",
    "addr:street":"Main Street",
    "iso:country":"GB",
    "sg:address":"7 Main Street",
    "sg:city":"Ferryhill",
    "sg:classifiers":[
        {
            "category":"Fast Food",
            "type":"Food & Drink"
        }
    ],
    "sg:phone":"+44 1740 652589",
    "sg:postcode":"DL17 8LA",
    "sg:province":"Durham",
    "sg:tags":[
        "away",
        "meal",
        "outlet",
        "take"
    ],
    "wof:name":"FERRYHILL CHOP SUEY HOUSE",
    "wof:placetype":"venue"
},
  "geometry": {"coordinates":[-1.5579589605,54.6887588501],"type":"Point"}
}