{
  "type": "Feature",
  "properties": {
    "iso:country":"GB",
    "sg:address":"39 Pride Hill",
    "sg:city":"Shrewsbury",
    "sg:classifiers":[
        {
            "category":"Shopping",
            "subcategory":"Comic Books",
            "type":"Retail Goods"
        }
    ],
    "sg:phone":"+44 1743 343099",
    "sg:postcode":"SY1 1DN",
    "sg:province":"Shropshire",
    "sg:tags":[
        "jeweller"
    ],
    "wof:name":"T H Baker & Co. (Established 1888) Ltd.",
    "wof:placetype":"venue"
},
  "geometry": {"coordinates":[-2.753559,52.708355],"type":"Point"}
}