{
  "type": "Feature",
  "properties": {
    "iso:country":"GB",
    "sg:address":"32 Bevan Close, Rainworth",
    "sg:city":"Mansfield",
    "sg:classifiers":[
        {
            "category":"Professional",
            "subcategory":"Engineering",
            "type":"Services"
        }
    ],
    "sg:phone":"+44 1623 490459",
    "sg:postcode":"NG21 0EX",
    "sg:province":"Nottinghamshire",
    "sg:tags":[
        "contractor",
        "electrical",
        "engineer"
    ],
    "wof:name":"Douglas Electrical",
    "wof:placetype":"venue"
},
  "geometry": {"coordinates":[-1.104984,53.113327],"type":"Point"}
}