{
  "type": "Feature",
  "properties": {
    "addr:full":"8 Hesnall Close, Glazebury Warrington Cheshire WA3 5PB",
    "addr:housenumber":"8",
    "addr:postcode":"wa3 5pb",
    "addr:street":"Hesnall Close",
    "iso:country":"GB",
    "sg:address":"8 Hesnall Close, Glazebury",
    "sg:city":"Warrington",
    "sg:classifiers":[
        {
            "category":"Social Services",
            "subcategory":"Job Training",
            "type":"Services"
        }
    ],
    "sg:phone":"+44 1942 677502",
    "sg:postcode":"WA3 5PB",
    "sg:province":"Cheshire",
    "sg:tags":[
        "translator",
        "interpreter"
    ],
    "wof:name":"Jenny Johnstone",
    "wof:placetype":"venue"
},
  "geometry": {"coordinates":[-2.495233,53.474449],"type":"Point"}
}