{
  "type": "Feature",
  "properties": {
    "iso:country":"GB",
    "sg:address":"91 Wimpole St",
    "sg:city":"West End",
    "sg:classifiers":[
        {
            "category":"Banks & Credit Unions",
            "subcategory":"Investment Brokerage",
            "type":"Services"
        }
    ],
    "sg:phone":"+44 20 7629 2630",
    "sg:postcode":"W1M 7DA",
    "sg:province":"Hampshire",
    "sg:tags":[
        "property",
        "broker",
        "commodity"
    ],
    "wof:name":"Kazakhstan Republic Trading House",
    "wof:placetype":"venue"
},
  "geometry": {"coordinates":[-0.147612,51.516373],"type":"Point"}
}