{
  "type": "Feature",
  "properties": {
    "addr:full":"Winston Churchill Building, Radbrook Road Shrewsbury Shropshire SY3 9BL",
    "addr:postcode":"sy3 9bl",
    "addr:street":"Winston;Radbrook Road",
    "iso:country":"GB",
    "sg:address":"Winston Churchill Building, Radbrook Road",
    "sg:city":"Shrewsbury",
    "sg:classifiers":[
        {
            "category":"Government",
            "subcategory":"Office",
            "type":"Public Place"
        }
    ],
    "sg:phone":"+44 1743 254086",
    "sg:postcode":"SY3 9BL",
    "sg:province":"Shropshire",
    "sg:tags":[
        "education",
        "agency",
        "authority"
    ],
    "wof:name":"Service for Visually Impaired Children (The)",
    "wof:placetype":"venue"
},
  "geometry": {"coordinates":[-2.77965,52.700871],"type":"Point"}
}