{
  "type": "Feature",
  "properties": {
    "addr:full":"Cliffdale House Cliffdale Road, 376 Meanwood Road Leeds West Yorkshire LS7 2JF",
    "addr:postcode":"ls7 2jf",
    "addr:street":"Cliffdale Road 376 Meanwood Road",
    "iso:country":"GB",
    "sg:address":"Cliffdale House Cliffdale Road, 376 Meanwood Road",
    "sg:city":"Leeds",
    "sg:classifiers":[
        {
            "category":"Real Estate",
            "subcategory":"Real Estate Operator",
            "type":"Services"
        }
    ],
    "sg:postcode":"LS7 2JF",
    "sg:province":"West Yorkshire",
    "sg:tags":[
        "letting",
        "agent"
    ],
    "wof:name":"Cavendish Property Management Ltd",
    "wof:placetype":"venue"
},
  "geometry": {"coordinates":[-1.54911,53.817421],"type":"Point"}
}