{
  "type": "Feature",
  "properties": {
    "addr:full":"1 Jubilee Pl, Viaduct Rd Pontypool Monmouthshire NP4 7PJ",
    "addr:housenumber":"1",
    "addr:postcode":"np4 7pj",
    "addr:street":"Jubilee Pl Viaduct Rd",
    "iso:country":"GB",
    "sg:address":"1 Jubilee Pl, Viaduct Rd",
    "sg:city":"Pontypool",
    "sg:classifiers":[
        {
            "category":"Building & Trades",
            "subcategory":"Cleaning & Sanitation",
            "type":"Services"
        }
    ],
    "sg:phone":"+44 1495 757187",
    "sg:postcode":"NP4 7PJ",
    "sg:province":"Monmouthshire",
    "sg:tags":[
        "blast"
    ],
    "wof:name":"Gwentblast",
    "wof:placetype":"venue"
},
  "geometry": {"coordinates":[-3.062798,51.73085],"type":"Point"}
}