{
  "type": "Feature",
  "properties": {
    "iso:country":"GB",
    "sg:address":"Ridingleaze",
    "sg:city":"Bristol",
    "sg:classifiers":[
        {
            "category":"Community Center",
            "type":"Public Place"
        }
    ],
    "sg:phone":"+44 117 938 4636",
    "sg:postcode":"BS11 0QE",
    "sg:province":"City of Bristol",
    "sg:tags":[
        "centre"
    ],
    "wof:name":"The Rock Community Centre Ltd.",
    "wof:placetype":"venue"
},
  "geometry": {"coordinates":[-2.658544,51.501846],"type":"Point"}
}