{
  "type": "Feature",
  "properties": {
    "iso:country":"GB",
    "sg:address":"201 Two Mile Hill Road",
    "sg:city":"Bristol",
    "sg:classifiers":[
        {
            "category":"Professional",
            "subcategory":"Advertising",
            "type":"Services"
        }
    ],
    "sg:phone":"+44 117 904 9311",
    "sg:postcode":"BS15 1AZ",
    "sg:province":"City of Bristol",
    "sg:tags":[
        "ear",
        "piercing"
    ],
    "wof:name":"European Professional Piercers Association",
    "wof:placetype":"venue"
},
  "geometry": {"coordinates":[-2.514919,51.463234],"type":"Point"}
}