{
  "type": "Feature",
  "properties": {
    "addr:full":"41 Norton Road Stockton-on-tees Durham TS18 2BU",
    "addr:housenumber":"41",
    "addr:postcode":"ts18 2bu",
    "addr:street":"Norton Road",
    "iso:country":"GB",
    "sg:address":"41 Norton Road",
    "sg:city":"Stockton-on-tees",
    "sg:classifiers":[
        {
            "category":"Taxi",
            "type":"Transportation"
        }
    ],
    "sg:phone":"+44 1642 676710",
    "sg:postcode":"TS18 2BU",
    "sg:province":"Durham",
    "sg:tags":[
        "mini",
        "cab"
    ],
    "wof:name":"Super Car Taxis",
    "wof:placetype":"venue"
},
  "geometry": {"coordinates":[-1.3126829863,54.5692634583],"type":"Point"}
}