{
  "type": "Feature",
  "properties": {
    "iso:country":"GB",
    "sg:address":"Bellsford Ho Richardland Rd",
    "sg:city":"Kilmarnock",
    "sg:classifiers":[
        {
            "category":"Organizations",
            "subcategory":"Non-profit Organization",
            "type":"Services"
        }
    ],
    "sg:postcode":"KA1 3JS",
    "sg:province":"East Ayrshire",
    "sg:tags":[
        "organisation",
        "voluntary",
        "charity"
    ],
    "wof:name":"C S V",
    "wof:placetype":"venue"
},
  "geometry": {"coordinates":[-4.491838,55.605511],"type":"Point"}
}