{
  "type": "Feature",
  "properties": {
    "iso:country":"GB",
    "sg:address":"Valetta, College Lane",
    "sg:city":"Woking",
    "sg:classifiers":[
        {
            "category":"Shopping",
            "subcategory":"Musical Instruments",
            "type":"Retail Goods"
        }
    ],
    "sg:phone":"+44 1483 757857",
    "sg:postcode":"GU22 0EW",
    "sg:province":"Surrey",
    "wof:name":"Woodwind Repair",
    "wof:placetype":"venue"
},
  "geometry": {"coordinates":[-0.576932013,51.3100395203],"type":"Point"}
}