{
  "type": "Feature",
  "properties": {
    "iso:country":"GB",
    "sg:address":"25 London Road",
    "sg:city":"Cheltenham",
    "sg:classifiers":[
        {
            "category":"Health Services",
            "subcategory":"Health Practitioner",
            "type":"Services"
        }
    ],
    "sg:phone":"+44 1242 221000",
    "sg:postcode":"GL52 6EY",
    "sg:province":"Gloucestershire",
    "sg:tags":[
        "hypnotherapists"
    ],
    "wof:name":"David Greenwell",
    "wof:placetype":"venue"
},
  "geometry": {"coordinates":[-2.0675768852,51.8956413269],"type":"Point"}
}