{
  "type": "Feature",
  "properties": {
    "addr:full":"13 Derwent Drive Tewkesbury Gloucestershire GL20 8AZ",
    "addr:housenumber":"13",
    "addr:postcode":"gl20 8az",
    "addr:street":"Derwent Drive",
    "iso:country":"GB",
    "sg:address":"13 Derwent Drive",
    "sg:city":"Tewkesbury",
    "sg:classifiers":[
        {
            "category":"Home & Garden",
            "subcategory":"Home Furnishings",
            "type":"Retail Goods"
        },
        {
            "category":"Home & Garden",
            "subcategory":"Building Materials",
            "type":"Retail Goods"
        }
    ],
    "sg:phone":"+44 1684 274757",
    "sg:postcode":"GL20 8AZ",
    "sg:province":"Gloucestershire",
    "sg:tags":[
        "installers",
        "planner",
        "kitchen",
        "furnishers"
    ],
    "wof:name":"Aston Gough",
    "wof:placetype":"venue"
},
  "geometry": {"coordinates":[-2.1432380676,52.0016937256],"type":"Point"}
}