{
  "type": "Feature",
  "properties": {
    "iso:country":"GB",
    "sg:address":"33a Adelaide St",
    "sg:city":"Fleetwood",
    "sg:classifiers":[
        {
            "category":"Social Services",
            "subcategory":"Retirement Home",
            "type":"Services"
        }
    ],
    "sg:phone":"+44 1253 773000",
    "sg:postcode":"FY7 6AD",
    "sg:province":"Lancashire",
    "sg:tags":[
        "care"
    ],
    "wof:name":"Nelly Murry's",
    "wof:placetype":"venue"
},
  "geometry": {"coordinates":[-3.0081279278,53.9238548279],"type":"Point"}
}