{
  "type": "Feature",
  "properties": {
    "iso:country":"GB",
    "sg:address":"116 Hadfield Street",
    "sg:city":"Sheffield",
    "sg:classifiers":[
        {
            "category":"Retail",
            "subcategory":"Driving School",
            "type":"Services"
        }
    ],
    "sg:postcode":"S6 3RS",
    "sg:province":"South Yorkshire",
    "wof:name":"A B C School of Motoring",
    "wof:placetype":"venue"
},
  "geometry": {"coordinates":[-1.501226,53.390762],"type":"Point"}
}