{
  "type": "Feature",
  "properties": {
    "addr:full":"Samsung House, 3 Riverbank Way, Great West Road Brentford Greater London TW8 9RE",
    "addr:housenumber":"3",
    "addr:postcode":"tw8 9re",
    "addr:street":"Riverbank Way",
    "iso:country":"GB",
    "sg:address":"Samsung House, 3 Riverbank Way, Great West Road",
    "sg:city":"Brentford",
    "sg:classifiers":[
        {
            "category":"Manufacturing",
            "subcategory":"Watercraft",
            "type":"Manufacturing & Wholesale Goods"
        }
    ],
    "sg:phone":"+44 20 8862 9333",
    "sg:postcode":"TW8 9RE",
    "sg:province":"Greater London",
    "sg:tags":[
        "repair",
        "ship",
        "builder"
    ],
    "wof:name":"Samsung Heavy Industries Co. Ltd.",
    "wof:placetype":"venue"
},
  "geometry": {"coordinates":[-0.3149980009,51.4872398376],"type":"Point"}
}