{
  "type": "Feature",
  "properties": {
    "addr:full":"Skandia Terminals, Osbourne Rd, Stallinborough Grimsby Lincolnshire DN41 8DG",
    "addr:postcode":"dn41 8dg",
    "addr:street":"Osbourne Rd Stallinborough",
    "iso:country":"GB",
    "sg:address":"Skandia Terminals, Osbourne Rd, Stallinborough",
    "sg:city":"Grimsby",
    "sg:classifiers":[
        {
            "category":"Freight",
            "type":"Transportation"
        }
    ],
    "sg:postcode":"DN41 8DG",
    "sg:province":"Lincolnshire",
    "sg:tags":[
        "forwarders"
    ],
    "wof:name":"Dan Transport (Uk) Ltd",
    "wof:placetype":"venue"
},
  "geometry": {"coordinates":[-0.17482,53.605419],"type":"Point"}
}