{
  "type": "Feature",
  "properties": {
    "addr:full":"160 Walsall Road, Norton Canes Cannock Staffordshire WS11 3RB",
    "addr:housenumber":"160",
    "addr:postcode":"ws11 3rb",
    "addr:street":"Walsall Road",
    "iso:country":"GB",
    "sg:address":"160 Walsall Road, Norton Canes",
    "sg:city":"Cannock",
    "sg:classifiers":[
        {
            "category":"Fast Food",
            "type":"Food & Drink"
        }
    ],
    "sg:postcode":"WS11 3RB",
    "sg:province":"Staffordshire",
    "sg:tags":[
        "away",
        "take"
    ],
    "wof:name":"Jean's Pantry",
    "wof:placetype":"venue"
},
  "geometry": {"coordinates":[-2.0266039371,52.6793251038],"type":"Point"}
}