{
  "type": "Feature",
  "properties": {
    "iso:country":"GB",
    "sg:address":"Coach Lane",
    "sg:city":"Redruth",
    "sg:classifiers":[
        {
            "category":"Utilities",
            "subcategory":"Fuel Oil & Lpg",
            "type":"Services"
        }
    ],
    "sg:phone":"+44 1209 213803",
    "sg:postcode":"TR15 2TP",
    "sg:province":"Cornwall",
    "sg:tags":[
        "coal",
        "smokeless"
    ],
    "wof:name":"K Abrahams",
    "wof:placetype":"venue"
},
  "geometry": {"coordinates":[-5.234394,50.23032],"type":"Point"}
}