{
  "type": "Feature",
  "properties": {
    "addr:full":"Buccleuch Mills Langholm Dumfries and Galloway DG13 0EB",
    "addr:postcode":"dg13 0eb",
    "addr:street":"Buccleuch",
    "iso:country":"GB",
    "sg:address":"Buccleuch Mills",
    "sg:city":"Langholm",
    "sg:classifiers":[
        {
            "category":"Manufacturing",
            "subcategory":"Textiles",
            "type":"Manufacturing & Wholesale Goods"
        }
    ],
    "sg:phone":"+44 13873 80371",
    "sg:postcode":"DG13 0EB",
    "sg:province":"Dumfries and Galloway",
    "sg:tags":[
        "made-up"
    ],
    "wof:name":"Bell Arthur (Scotch Tweeds)",
    "wof:placetype":"venue"
},
  "geometry": {"coordinates":[-3.0037488937,55.1530456543],"type":"Point"}
}