{
  "type": "Feature",
  "properties": {
    "addr:full":"Southrepps Road, Antingham North Walsham Norfolk NR28 0NW",
    "addr:postcode":"nr28 0nw",
    "addr:street":"Southrepps Road;Walsham",
    "iso:country":"GB",
    "sg:address":"Southrepps Road, Antingham",
    "sg:city":"North Walsham",
    "sg:classifiers":[
        {
            "category":"Farming",
            "subcategory":"Farm",
            "type":"Manufacturing & Wholesale Goods"
        }
    ],
    "sg:phone":"+44 1263 833265",
    "sg:postcode":"NR28 0NW",
    "sg:province":"Norfolk",
    "sg:tags":[
        "mixed",
        "crop"
    ],
    "wof:name":"D J & J M Blaxell",
    "wof:placetype":"venue"
},
  "geometry": {"coordinates":[1.38476,52.818314],"type":"Point"}
}