{
  "type": "Feature",
  "properties": {
    "addr:full":"86 High Road, Willesden London Greater London NW10 2PR",
    "addr:housenumber":"86",
    "addr:postcode":"nw10 2pr",
    "addr:street":"High Road",
    "iso:country":"GB",
    "sg:address":"86 High Road, Willesden",
    "sg:city":"London",
    "sg:classifiers":[
        {
            "category":"Retail",
            "subcategory":"Storage",
            "type":"Services"
        }
    ],
    "sg:phone":"+44 20 8830 1392",
    "sg:postcode":"NW10 2PR",
    "sg:province":"Greater London",
    "sg:tags":[
        "household",
        "removal"
    ],
    "wof:name":"Andy's Furniture",
    "wof:placetype":"venue"
},
  "geometry": {"coordinates":[-0.230113,51.547169],"type":"Point"}
}