{
  "type": "Feature",
  "properties": {
    "iso:country":"GB",
    "sg:address":"16 Elder Croft",
    "sg:city":"Leeds",
    "sg:classifiers":[
        {
            "category":"Professional",
            "subcategory":"Detective & Security Services",
            "type":"Services"
        }
    ],
    "sg:phone":"+44 70 5005 5023",
    "sg:postcode":"LS13 4BX",
    "sg:province":"West Yorkshire",
    "sg:tags":[
        "alarm",
        "burglar",
        "system"
    ],
    "wof:name":"Diamond Security Systems",
    "wof:placetype":"venue"
},
  "geometry": {"coordinates":[-1.6301510334,53.8048858643],"type":"Point"}
}