{
  "type": "Feature",
  "properties": {
    "iso:country":"GB",
    "sg:address":"1 Grafton Road",
    "sg:city":"Newport",
    "sg:classifiers":[
        {
            "category":"Retail",
            "subcategory":"Funeral Services",
            "type":"Services"
        }
    ],
    "sg:phone":"+44 1633 259225",
    "sg:postcode":"NP19 0AS",
    "sg:province":"Newport",
    "sg:tags":[
        "director"
    ],
    "wof:name":"Albert E Hicks Ltd.",
    "wof:placetype":"venue"
},
  "geometry": {"coordinates":[-2.989072,51.590176],"type":"Point"}
}