{
  "type": "Feature",
  "properties": {
    "addr:full":"Unit 19 Cossall Industrial Estate, Solomon Road Ilkeston Derbyshire DE7 5UA",
    "addr:housenumber":"unit 19",
    "addr:postcode":"de7 5ua",
    "addr:street":"Industrial Estate Solomon Road",
    "iso:country":"GB",
    "sg:address":"Unit 19 Cossall Industrial Estate, Solomon Road",
    "sg:city":"Ilkeston",
    "sg:classifiers":[
        {
            "category":"Retail",
            "subcategory":"Auto Repair",
            "type":"Services"
        }
    ],
    "sg:phone":"+44 115 944 5414",
    "sg:postcode":"DE7 5UA",
    "sg:province":"Derbyshire",
    "sg:tags":[
        "modification",
        "garage"
    ],
    "wof:name":"F G Evans Motors",
    "wof:placetype":"venue"
},
  "geometry": {"coordinates":[-1.3101890087,52.9786109924],"type":"Point"}
}