{
  "type": "Feature",
  "properties": {
    "iso:country":"GB",
    "sg:address":"Sea View Farm, Sparnon Gate",
    "sg:city":"Redruth",
    "sg:classifiers":[
        {
            "category":"Farming",
            "subcategory":"Livestock Farm",
            "type":"Manufacturing & Wholesale Goods"
        }
    ],
    "sg:postcode":"TR16 4JA",
    "sg:province":"Cornwall",
    "sg:tags":[
        "others"
    ],
    "wof:name":"J M Gribble",
    "wof:placetype":"venue"
},
  "geometry": {"coordinates":[-5.256807,50.251839],"type":"Point"}
}