{
  "type": "Feature",
  "properties": {
    "addr:full":"Exchange Quay, Salford Quays Manchester Greater Manchester M5 3BT",
    "addr:postcode":"m5 3bt",
    "addr:street":"Quay",
    "iso:country":"GB",
    "sg:address":"Exchange Quay, Salford Quays",
    "sg:city":"Manchester",
    "sg:classifiers":[
        {
            "category":"Banks & Credit Unions",
            "subcategory":"Financial Services",
            "type":"Services"
        }
    ],
    "sg:phone":"+44 161 869 6050",
    "sg:postcode":"M5 3BT",
    "sg:province":"Greater Manchester",
    "sg:tags":[
        "consultant"
    ],
    "wof:name":"The Associates Capital Corporation",
    "wof:placetype":"venue"
},
  "geometry": {"coordinates":[-2.2824289799,53.4662284851],"type":"Point"}
}