{
  "type": "Feature",
  "properties": {
    "addr:full":"Clifford Bridge Rd, Walsgrave Coventry Warwickshire CV2 2DX",
    "addr:postcode":"cv2 2dx",
    "addr:street":"Clifford Bridge Rd",
    "iso:country":"GB",
    "sg:address":"Clifford Bridge Rd, Walsgrave",
    "sg:city":"Coventry",
    "sg:classifiers":[
        {
            "category":"Health Services",
            "subcategory":"Hospital",
            "type":"Services"
        }
    ],
    "sg:phone":"+44 24 7660 2020",
    "sg:postcode":"CV2 2DX",
    "sg:province":"Warwickshire",
    "wof:name":"Walsgrave N.H.S Trust Hospital",
    "wof:placetype":"venue"
},
  "geometry": {"coordinates":[-1.4443700314,52.4248580933],"type":"Point"}
}