{
  "type": "Feature",
  "properties": {
    "iso:country":"GB",
    "sg:address":"111 Bridgnorth Road, Wollaston",
    "sg:city":"Stourbridge",
    "sg:classifiers":[
        {
            "category":"Home & Garden",
            "subcategory":"Home Furnishings",
            "type":"Retail Goods"
        }
    ],
    "sg:phone":"+44 1384 394110",
    "sg:postcode":"DY8 3NY",
    "sg:province":"Staffordshire",
    "sg:tags":[
        "blind",
        "awning",
        "canopy",
        "blinds"
    ],
    "wof:name":"Blinds By S A S",
    "wof:placetype":"venue"
},
  "geometry": {"coordinates":[-2.163674,52.460342],"type":"Point"}
}