{
  "type": "Feature",
  "properties": {
    "addr:full":"9 East Laith Gate Doncaster South Yorkshire DN1 1JG",
    "addr:housenumber":"9",
    "addr:postcode":"dn1 1jg",
    "addr:street":"East Laith Gate",
    "iso:country":"GB",
    "sg:address":"9 East Laith Gate",
    "sg:city":"Doncaster",
    "sg:classifiers":[
        {
            "category":"Professional",
            "subcategory":"Management & Consulting",
            "type":"Services"
        },
        {
            "category":"Personal",
            "type":"Services"
        }
    ],
    "sg:phone":"+44 1302 360112",
    "sg:postcode":"DN1 1JG",
    "sg:province":"South Yorkshire",
    "sg:tags":[
        "consultant",
        "beauty",
        "specialist"
    ],
    "wof:name":"The Tan Factory",
    "wof:placetype":"venue"
},
  "geometry": {"coordinates":[-1.130383,53.524475],"type":"Point"}
}