{
  "type": "Feature",
  "properties": {
    "iso:country":"GB",
    "sg:address":"Southlinks Enterprise Workshops, Unit A, Station Road East",
    "sg:city":"Grantham",
    "sg:classifiers":[
        {
            "category":"Military Area",
            "subcategory":"Air Force Base",
            "type":"Public Place"
        }
    ],
    "sg:postcode":"NG31 6HX",
    "sg:province":"Lincolnshire",
    "sg:tags":[
        "taxi",
        "hire",
        "private"
    ],
    "wof:name":"Tiger Taxis",
    "wof:placetype":"venue"
},
  "geometry": {"coordinates":[-0.642859,52.913197],"type":"Point"}
}