{
  "type": "Feature",
  "properties": {
    "iso:country":"GB",
    "sg:address":"43 Queensway",
    "sg:city":"Billingham",
    "sg:classifiers":[
        {
            "category":"Shopping",
            "subcategory":"Shoes",
            "type":"Retail Goods"
        }
    ],
    "sg:postcode":"TS23 2ND",
    "sg:province":"Durham",
    "sg:tags":[
        "shop"
    ],
    "wof:name":"Stead & Simpson Ltd",
    "wof:placetype":"venue"
},
  "geometry": {"coordinates":[-1.293864,54.608028],"type":"Point"}
}