{
  "type": "Feature",
  "properties": {
    "iso:country":"GB",
    "sg:address":"30 Faygate Road",
    "sg:city":"Eastbourne",
    "sg:classifiers":[
        {
            "category":"Professional",
            "subcategory":"Computer Services",
            "type":"Services"
        }
    ],
    "sg:postcode":"BN22 9RR",
    "sg:province":"East Sussex",
    "sg:tags":[
        "consultant"
    ],
    "wof:name":"Coastline Computer Support",
    "wof:placetype":"venue"
},
  "geometry": {"coordinates":[0.2720179856,50.8008422852],"type":"Point"}
}