{
  "type": "Feature",
  "properties": {
    "addr:full":"Unit 2, High Street, Princes End Tipton West Midlands DY4 9HX",
    "addr:housenumber":"unit 2",
    "addr:postcode":"dy4 9hx",
    "addr:street":"High Street",
    "iso:country":"GB",
    "sg:address":"Unit 2, High Street, Princes End",
    "sg:city":"Tipton",
    "sg:classifiers":[
        {
            "category":"Professional",
            "subcategory":"Engineering",
            "type":"Services"
        }
    ],
    "sg:phone":"+44 121 520 4320",
    "sg:postcode":"DY4 9HX",
    "sg:province":"West Midlands",
    "wof:name":"Midland Power Press Services Ltd.",
    "wof:placetype":"venue"
},
  "geometry": {"coordinates":[-2.0594439507,52.5443153381],"type":"Point"}
}