{
  "type": "Feature",
  "properties": {
    "iso:country":"GB",
    "sg:address":"7-11 St Vincents Road",
    "sg:city":"Ryde",
    "sg:classifiers":[
        {
            "category":"Food & Beverages",
            "subcategory":"Groceries & Convenience Stores",
            "type":"Retail Goods"
        }
    ],
    "sg:phone":"+44 1983 562994",
    "sg:postcode":"PO33 3PS",
    "sg:province":"Isle of Wight",
    "wof:name":"St Vincents Stores",
    "wof:placetype":"venue"
},
  "geometry": {"coordinates":[-1.1754260063,50.7267608643],"type":"Point"}
}