{
  "type": "Feature",
  "properties": {
    "addr:full":"The Pentagon, 42 Railway Street Stafford Staffordshire ST16 2DS",
    "addr:housenumber":"42",
    "addr:postcode":"st16 2ds",
    "addr:street":"Pentagon;Railway Street",
    "iso:country":"GB",
    "sg:address":"The Pentagon, 42 Railway Street",
    "sg:city":"Stafford",
    "sg:classifiers":[
        {
            "category":"Professional",
            "subcategory":"Research",
            "type":"Services"
        }
    ],
    "sg:phone":"+44 1785 211023",
    "sg:postcode":"ST16 2DS",
    "sg:province":"Staffordshire",
    "sg:tags":[
        "market"
    ],
    "wof:name":"Marketlink Ltd.",
    "wof:placetype":"venue"
},
  "geometry": {"coordinates":[-2.121768,52.803959],"type":"Point"}
}