{
  "type": "Feature",
  "properties": {
    "iso:country":"GB",
    "sg:address":"73 Ardoch Crescent",
    "sg:city":"Dumbarton",
    "sg:classifiers":[
        {
            "category":"Farming",
            "subcategory":"Nursery",
            "type":"Manufacturing & Wholesale Goods"
        }
    ],
    "sg:phone":"+44 1389 762840",
    "sg:postcode":"G82 4EN",
    "sg:province":"Argyll and Bute",
    "sg:tags":[
        "creche"
    ],
    "wof:name":"BRUCEHILL NURSERY SCHOOL",
    "wof:placetype":"venue"
},
  "geometry": {"coordinates":[-4.585017,55.946854],"type":"Point"}
}