{
  "type": "Feature",
  "properties": {
    "iso:country":"GB",
    "sg:address":"Unit 3 Snedshill Indust Est",
    "sg:city":"Telford",
    "sg:classifiers":[
        {
            "category":"Military Area",
            "subcategory":"Air Force Base",
            "type":"Public Place"
        }
    ],
    "sg:phone":"+44 1952 401000",
    "sg:postcode":"TF2 9NH",
    "sg:province":"Shropshire",
    "sg:tags":[
        "taxi",
        "hire",
        "private"
    ],
    "wof:name":"All Cars",
    "wof:placetype":"venue"
},
  "geometry": {"coordinates":[-2.444282,52.68811],"type":"Point"}
}