{
  "type": "Feature",
  "properties": {
    "addr:full":"113 Brynheulog, Pentwyn Cardiff Cardiff CF23 7JD",
    "addr:housenumber":"113",
    "addr:postcode":"cf23 7jd",
    "addr:street":"Brynheulog Pentwyn",
    "iso:country":"GB",
    "sg:address":"113 Brynheulog, Pentwyn",
    "sg:city":"Cardiff",
    "sg:classifiers":[
        {
            "category":"Bars & Pubs",
            "type":"Food & Drink"
        }
    ],
    "sg:phone":"+44 29 2054 9378",
    "sg:postcode":"CF23 7JD",
    "sg:province":"Cardiff",
    "sg:tags":[
        "pubs",
        "inn"
    ],
    "wof:name":"The Grand Slam",
    "wof:placetype":"venue"
},
  "geometry": {"coordinates":[-3.146664,51.524906],"type":"Point"}
}