{
  "type": "Feature",
  "properties": {
    "iso:country":"GB",
    "sg:address":"The Picture Palace, Tong Street, Dudley Hill",
    "sg:city":"Bradford",
    "sg:classifiers":[
        {
            "category":"Shopping",
            "subcategory":"Department Store",
            "type":"Retail Goods"
        },
        {
            "category":"Home & Garden",
            "subcategory":"Carpets & Floor Coverings",
            "type":"Retail Goods"
        }
    ],
    "sg:phone":"+44 1274 687044",
    "sg:postcode":"BD4 9PY",
    "sg:province":"West Yorkshire",
    "sg:tags":[
        "carpets",
        "rug",
        "matting"
    ],
    "wof:name":"Cut Price Carpets",
    "wof:placetype":"venue"
},
  "geometry": {"coordinates":[-1.7190500498,53.7710189819],"type":"Point"}
}