{
  "type": "Feature",
  "properties": {
    "iso:country":"GB",
    "sg:address":"922 Springfield Road",
    "sg:city":"Glasgow",
    "sg:classifiers":[
        {
            "category":"Organizations",
            "subcategory":"Non-profit Organization",
            "type":"Services"
        }
    ],
    "sg:phone":"+44 141 551 8387",
    "sg:postcode":"G31 4HE",
    "sg:province":"Glasgow City",
    "sg:tags":[
        "charitable",
        "organisation",
        "voluntary",
        "charity"
    ],
    "wof:name":"Parkhead Credit Union Ltd",
    "wof:placetype":"venue"
},
  "geometry": {"coordinates":[-4.198244,55.851002],"type":"Point"}
}