{
  "type": "Feature",
  "properties": {
    "iso:country":"GB",
    "sg:address":"65 Union Street",
    "sg:city":"Ryde",
    "sg:classifiers":[
        {
            "category":"Shopping",
            "subcategory":"Clothing, Apparel, & Fashions",
            "type":"Retail Goods"
        }
    ],
    "sg:phone":"+44 1983 563508",
    "sg:postcode":"PO33 2LG",
    "sg:province":"Isle of Wight",
    "sg:tags":[
        "menswear"
    ],
    "wof:name":"Woodnutt Menswear",
    "wof:placetype":"venue"
},
  "geometry": {"coordinates":[-1.161879,50.731743],"type":"Point"}
}