{
  "type": "Feature",
  "properties": {
    "iso:country":"GB",
    "sg:address":"26 Felix Rd, Stowupland",
    "sg:city":"Stowmarket",
    "sg:classifiers":[
        {
            "category":"Building & Trades",
            "subcategory":"Construction",
            "type":"Services"
        }
    ],
    "sg:phone":"+44 1449 774004",
    "sg:postcode":"IP14 4DD",
    "sg:province":"Suffolk",
    "sg:tags":[
        "builder"
    ],
    "wof:name":"S.R Alexander",
    "wof:placetype":"venue"
},
  "geometry": {"coordinates":[1.017966,52.196766],"type":"Point"}
}