{
  "type": "Feature",
  "properties": {
    "addr:full":"50 Icen Way Dorchester Dorset DT1 1EW",
    "addr:housenumber":"50",
    "addr:postcode":"dt1 1ew",
    "addr:street":"Icen Way",
    "iso:country":"GB",
    "sg:address":"50 Icen Way",
    "sg:city":"Dorchester",
    "sg:classifiers":[
        {
            "category":"Personal",
            "subcategory":"Barber",
            "type":"Services"
        }
    ],
    "sg:phone":"+44 1305 263564",
    "sg:postcode":"DT1 1EW",
    "sg:province":"Dorset",
    "sg:tags":[
        "men's",
        "hairdresser"
    ],
    "wof:name":"Chris's Hairdressers",
    "wof:placetype":"venue"
},
  "geometry": {"coordinates":[-2.433867,50.714405],"type":"Point"}
}