{
  "type": "Feature",
  "properties": {
    "iso:country":"GB",
    "sg:address":"Unit 521, Brompton Walk, Lakeside Shopping Centre",
    "sg:city":"Grays",
    "sg:classifiers":[
        {
            "category":"Cafe",
            "type":"Food & Drink"
        }
    ],
    "sg:phone":"+44 1708 863612",
    "sg:postcode":"RM16 1ZL",
    "sg:province":"Essex",
    "sg:tags":[
        "tea",
        "room"
    ],
    "wof:name":"Spreads Cafe",
    "wof:placetype":"venue"
},
  "geometry": {"coordinates":[0.3427,51.505421],"type":"Point"}
}