{
  "type": "Feature",
  "properties": {
    "addr:full":"299 Oxford St West End Hampshire W1R 1LE",
    "addr:housenumber":"299",
    "addr:postcode":"w1r 1le",
    "addr:street":"Oxford St",
    "iso:country":"GB",
    "sg:address":"299 Oxford St",
    "sg:city":"West End",
    "sg:classifiers":[
        {
            "category":"Professional",
            "subcategory":"Employment Agencies",
            "type":"Services"
        }
    ],
    "sg:phone":"+44 20 7393 1390",
    "sg:postcode":"W1R 1LE",
    "sg:province":"Hampshire",
    "sg:tags":[
        "consultant"
    ],
    "wof:name":"Price Trace Hawes",
    "wof:placetype":"venue"
},
  "geometry": {"coordinates":[-0.145142,51.514744],"type":"Point"}
}