{
  "type": "Feature",
  "properties": {
    "addr:full":"2 Middle Street Padstow Cornwall PL28 8AP",
    "addr:housenumber":"2",
    "addr:postcode":"pl28 8ap",
    "addr:street":"Middle Street",
    "iso:country":"GB",
    "sg:address":"2 Middle Street",
    "sg:city":"Padstow",
    "sg:classifiers":[
        {
            "category":"Food & Beverages",
            "subcategory":"Groceries & Convenience Stores",
            "type":"Retail Goods"
        }
    ],
    "sg:phone":"+44 1841 533400",
    "sg:postcode":"PL28 8AP",
    "sg:province":"Cornwall",
    "wof:name":"Spar Stores",
    "wof:placetype":"venue"
},
  "geometry": {"coordinates":[-4.9400000572,50.5415534973],"type":"Point"}
}