{
  "type": "Feature",
  "properties": {
    "addr:full":"Little Blackhall, Blackhall Lane Sevenoaks Kent TN15 0HS",
    "addr:postcode":"tn15 0hs",
    "addr:street":"Blackhall Lane",
    "iso:country":"GB",
    "sg:address":"Little Blackhall, Blackhall Lane",
    "sg:city":"Sevenoaks",
    "sg:classifiers":[
        {
            "category":"Professional",
            "subcategory":"Accounting & Tax Preparation",
            "type":"Services"
        }
    ],
    "sg:phone":"+44 1732 464827",
    "sg:postcode":"TN15 0HS",
    "sg:province":"Kent",
    "sg:tags":[
        "accountant"
    ],
    "wof:name":"James J Madden",
    "wof:placetype":"venue"
},
  "geometry": {"coordinates":[0.20549,51.282269],"type":"Point"}
}