{
  "type": "Feature",
  "properties": {
    "addr:full":"Cree Mills Newton Stewart Dumfries and Galloway DG8 6DQ",
    "addr:postcode":"dg8 6dq",
    "addr:street":"Cree Mills",
    "iso:country":"GB",
    "sg:address":"Cree Mills",
    "sg:city":"Newton Stewart",
    "sg:classifiers":[
        {
            "category":"Landmark",
            "subcategory":"Tourist Information",
            "type":"Public Place"
        }
    ],
    "sg:phone":"+44 1671 402549",
    "sg:postcode":"DG8 6DQ",
    "sg:province":"Dumfries and Galloway",
    "wof:name":"Dumfries & Galloway Tourist Board",
    "wof:placetype":"venue"
},
  "geometry": {"coordinates":[-4.482984,54.954784],"type":"Point"}
}