{
  "type": "Feature",
  "properties": {
    "addr:full":"4 Cobble Yard Cambridge Cambridgeshire CB1 1HR",
    "addr:housenumber":"4",
    "addr:postcode":"cb1 1hr",
    "addr:street":"Cobble Yard",
    "iso:country":"GB",
    "sg:address":"4 Cobble Yard",
    "sg:city":"Cambridge",
    "sg:classifiers":[
        {
            "category":"Personal",
            "subcategory":"Beauty Salon",
            "type":"Services"
        }
    ],
    "sg:phone":"+44 1223 311112",
    "sg:postcode":"CB1 1HR",
    "sg:province":"Cambridgeshire",
    "sg:tags":[
        "unisex",
        "hairdresser"
    ],
    "wof:name":"Diane Hair International",
    "wof:placetype":"venue"
},
  "geometry": {"coordinates":[0.134856,52.20747],"type":"Point"}
}