{
  "type": "Feature",
  "properties": {
    "iso:country":"GB",
    "sg:address":"25 Spencer Road",
    "sg:city":"London",
    "sg:classifiers":[
        {
            "category":"Building & Trades",
            "subcategory":"Plumbing",
            "type":"Services"
        }
    ],
    "sg:postcode":"SW18 2SP",
    "sg:province":"Greater London",
    "sg:tags":[
        "heating"
    ],
    "wof:name":"Gaswise",
    "wof:placetype":"venue"
},
  "geometry": {"coordinates":[-0.1751170009,51.4592132568],"type":"Point"}
}