{
  "type": "Feature",
  "properties": {
    "iso:country":"GB",
    "sg:address":"Carrington Way",
    "sg:city":"Wincanton",
    "sg:classifiers":[
        {
            "category":"Shopping",
            "type":"Retail Goods"
        }
    ],
    "sg:phone":"+44 1963 824600",
    "sg:postcode":"BA9 9JS",
    "sg:province":"Somerset",
    "sg:tags":[
        "part",
        "accessory"
    ],
    "wof:name":"Gillams Car Spares",
    "wof:placetype":"venue"
},
  "geometry": {"coordinates":[-2.4117,51.058071],"type":"Point"}
}