{
  "type": "Feature",
  "properties": {
    "addr:full":"41 Ashley Terrace Edinburgh City of Edinburgh EH11 1RY",
    "addr:housenumber":"41",
    "addr:postcode":"eh11 1ry",
    "addr:street":"Ashley Terrace",
    "iso:country":"GB",
    "sg:address":"41 Ashley Terrace",
    "sg:city":"Edinburgh",
    "sg:classifiers":[
        {
            "category":"Food & Beverages",
            "subcategory":"Supermarket",
            "type":"Retail Goods"
        }
    ],
    "sg:phone":"+44 131 538 8412",
    "sg:postcode":"EH11 1RY",
    "sg:province":"City of Edinburgh",
    "wof:name":"Geordie Jean",
    "wof:placetype":"venue"
},
  "geometry": {"coordinates":[-3.216409,55.941124],"type":"Point"}
}