{
  "type": "Feature",
  "properties": {
    "addr:full":"The Mill, Hardwick Witney Oxfordshire OX8 7QE",
    "addr:postcode":"ox8 7qe",
    "iso:country":"GB",
    "sg:address":"The Mill, Hardwick",
    "sg:city":"Witney",
    "sg:classifiers":[
        {
            "category":"Shopping",
            "subcategory":"Jewelry",
            "type":"Retail Goods"
        }
    ],
    "sg:phone":"+44 1865 300742",
    "sg:postcode":"OX8 7QE",
    "sg:province":"Oxfordshire",
    "sg:tags":[
        "gold",
        "silversmith"
    ],
    "wof:name":"The Mill Workshop",
    "wof:placetype":"venue"
},
  "geometry": {"coordinates":[-1.4543,51.750061],"type":"Point"}
}