{
  "type": "Feature",
  "properties": {
    "iso:country":"GB",
    "sg:address":"251 Neasden Lane, Neasden",
    "sg:city":"London",
    "sg:classifiers":[
        {
            "category":"Professional",
            "subcategory":"Business Services",
            "type":"Services"
        }
    ],
    "sg:postcode":"NW10 9QH",
    "sg:province":"Greater London",
    "sg:tags":[
        "holding"
    ],
    "wof:name":"Slocombes Holdings Ltd.",
    "wof:placetype":"venue"
},
  "geometry": {"coordinates":[-0.2522900105,51.545009613],"type":"Point"}
}