{
  "type": "Feature",
  "properties": {
    "iso:country":"GB",
    "sg:address":"143 Carshalton Park Road",
    "sg:city":"Carshalton",
    "sg:classifiers":[
        {
            "category":"Education",
            "subcategory":"Music School",
            "type":"Public Place"
        }
    ],
    "sg:phone":"+44 20 8647 6376",
    "sg:postcode":"SM5 3SF",
    "sg:province":"Surrey",
    "sg:tags":[
        "teacher"
    ],
    "wof:name":"ALAN PINCHES",
    "wof:placetype":"venue"
},
  "geometry": {"coordinates":[-0.168344,51.358036],"type":"Point"}
}