{
  "type": "Feature",
  "properties": {
    "addr:full":"Trenance Cotts, Trenance, St Issey Wadebridge Cornwall PL27 7QX",
    "addr:postcode":"pl27 7qx",
    "addr:street":"Trenance St",
    "iso:country":"GB",
    "sg:address":"Trenance Cotts, Trenance, St Issey",
    "sg:city":"Wadebridge",
    "sg:classifiers":[
        {
            "category":"Shopping",
            "subcategory":"Computers & Home Electronics",
            "type":"Retail Goods"
        }
    ],
    "sg:postcode":"PL27 7QX",
    "sg:province":"Cornwall",
    "wof:name":"Woodpecker Design",
    "wof:placetype":"venue"
},
  "geometry": {"coordinates":[-4.8380241394,50.5181884766],"type":"Point"}
}