{
  "type": "Feature",
  "properties": {
    "addr:full":"Unit 70a, The Airfield Bedford Bedfordshire MK44 2BN",
    "addr:housenumber":"unit 70a",
    "addr:postcode":"mk44 2bn",
    "addr:street":"The Airfield",
    "iso:country":"GB",
    "sg:address":"Unit 70a, The Airfield",
    "sg:city":"Bedford",
    "sg:classifiers":[
        {
            "category":"Retail",
            "subcategory":"Auto Repair",
            "type":"Services"
        }
    ],
    "sg:phone":"+44 1234 376464",
    "sg:postcode":"MK44 2BN",
    "sg:province":"Bedfordshire",
    "sg:tags":[
        "modification",
        "garage"
    ],
    "wof:name":"Mike Treutlein",
    "wof:placetype":"venue"
},
  "geometry": {"coordinates":[-0.418339,52.216621],"type":"Point"}
}