{
  "type": "Feature",
  "properties": {
    "addr:full":"Gillars Lane St Helens Merseyside WA10 5PT",
    "addr:postcode":"wa10 5pt",
    "addr:street":"Gillars Lane",
    "iso:country":"GB",
    "sg:address":"Gillars Lane",
    "sg:city":"St Helens",
    "sg:classifiers":[
        {
            "category":"Bars & Pubs",
            "type":"Food & Drink"
        }
    ],
    "sg:phone":"+44 1744 25706",
    "sg:postcode":"WA10 5PT",
    "sg:province":"Merseyside",
    "sg:tags":[
        "pubs",
        "inn"
    ],
    "wof:name":"The Stanley Arms",
    "wof:placetype":"venue"
},
  "geometry": {"coordinates":[-2.795816,53.453442],"type":"Point"}
}