{
  "type": "Feature",
  "properties": {
    "iso:country":"GB",
    "sg:address":"467 Abbey Road",
    "sg:city":"Belvedere",
    "sg:classifiers":[
        {
            "category":"Building & Trades",
            "subcategory":"Cleaning & Sanitation",
            "type":"Services"
        }
    ],
    "sg:phone":"+44 20 8310 4600",
    "sg:postcode":"DA17 5DJ",
    "sg:province":"Kent",
    "sg:tags":[
        "sweep",
        "chimney"
    ],
    "wof:name":"Bexley Building Services",
    "wof:placetype":"venue"
},
  "geometry": {"coordinates":[0.123726,51.489937],"type":"Point"}
}