{
  "type": "Feature",
  "properties": {
    "addr:full":"6 The Firs Thatcham Berkshire RG18 3EX",
    "addr:housenumber":"6",
    "addr:postcode":"rg18 3ex",
    "addr:street":"The Firs Thatcham",
    "iso:country":"GB",
    "sg:address":"6 The Firs",
    "sg:city":"Thatcham",
    "sg:classifiers":[
        {
            "category":"Freight",
            "type":"Transportation"
        }
    ],
    "sg:phone":"+44 1635 865408",
    "sg:postcode":"RG18 3EX",
    "sg:province":"Berkshire",
    "sg:tags":[
        "haulage",
        "road"
    ],
    "wof:name":"Hamblin Haulage",
    "wof:placetype":"venue"
},
  "geometry": {"coordinates":[-1.269114,51.40543],"type":"Point"}
}