{
  "type": "Feature",
  "properties": {
    "addr:full":"6 St Anne Street Birkenhead Merseyside CH41 3JU",
    "addr:housenumber":"6",
    "addr:postcode":"ch41 3ju",
    "addr:street":"St Anne Street",
    "iso:country":"GB",
    "sg:address":"6 St Anne Street",
    "sg:city":"Birkenhead",
    "sg:classifiers":[
        {
            "category":"Food & Beverages",
            "subcategory":"Meat & Fish",
            "type":"Retail Goods"
        }
    ],
    "sg:phone":"+44 151 650 1987",
    "sg:postcode":"CH41 3JU",
    "sg:province":"Merseyside",
    "sg:tags":[
        "butcher"
    ],
    "wof:name":"Jeff's",
    "wof:placetype":"venue"
},
  "geometry": {"coordinates":[-3.0248420238,53.3948364258],"type":"Point"}
}