{
  "type": "Feature",
  "properties": {
    "iso:country":"GB",
    "sg:address":"West Glamorgan House, Orchard Street",
    "sg:city":"Swansea",
    "sg:classifiers":[
        {
            "category":"Government",
            "subcategory":"Police Station",
            "type":"Public Place"
        }
    ],
    "sg:phone":"+44 1792 645505",
    "sg:postcode":"SA1 5AD",
    "sg:province":"Neath Port Talbot",
    "sg:tags":[
        "support"
    ],
    "wof:name":"The Probation Service",
    "wof:placetype":"venue"
},
  "geometry": {"coordinates":[-3.943294,51.622833],"type":"Point"}
}