{
  "type": "Feature",
  "properties": {
    "iso:country":"GB",
    "sg:address":"1 Hillcourt Street",
    "sg:city":"Manchester",
    "sg:classifiers":[
        {
            "category":"Building & Trades",
            "subcategory":"Cleaning & Sanitation",
            "type":"Services"
        }
    ],
    "sg:phone":"+44 161 274 3095",
    "sg:postcode":"M1 7HL",
    "sg:province":"Greater Manchester",
    "sg:tags":[
        "cleaner",
        "window"
    ],
    "wof:name":"Elite Window & Office Cleaning Co",
    "wof:placetype":"venue"
},
  "geometry": {"coordinates":[-2.236164093,53.4708862305],"type":"Point"}
}