{
  "type": "Feature",
  "properties": {
    "addr:full":"32 Bridge St Stranraer Dumfries and Galloway DG9 7JF",
    "addr:housenumber":"32",
    "addr:postcode":"dg9 7jf",
    "addr:street":"Bridge St",
    "iso:country":"GB",
    "sg:address":"32 Bridge St",
    "sg:city":"Stranraer",
    "sg:classifiers":[
        {
            "category":"Building & Trades",
            "subcategory":"Landscaping Services",
            "type":"Services"
        },
        {
            "category":"Farming",
            "subcategory":"Livestock Farm",
            "type":"Manufacturing & Wholesale Goods"
        }
    ],
    "sg:postcode":"DG9 7JF",
    "sg:province":"Dumfries and Galloway",
    "sg:tags":[
        "pond",
        "aquarium",
        "others"
    ],
    "wof:name":"McGeoch,P,",
    "wof:placetype":"venue"
},
  "geometry": {"coordinates":[-5.0276589394,54.9038696289],"type":"Point"}
}