{
  "type": "Feature",
  "properties": {
    "addr:full":"The Old Mill, Hoopers Bridge, Lanivet Bodmin Cornwall PL30 5LW",
    "addr:postcode":"pl30 5lw",
    "addr:street":"Hoopers Bridge",
    "iso:country":"GB",
    "sg:address":"The Old Mill, Hoopers Bridge, Lanivet",
    "sg:city":"Bodmin",
    "sg:classifiers":[
        {
            "category":"Shopping",
            "subcategory":"Catalog Store",
            "type":"Retail Goods"
        }
    ],
    "sg:phone":"+44 1208 831266",
    "sg:postcode":"PL30 5LW",
    "sg:province":"Cornwall",
    "sg:tags":[
        "mail",
        "order"
    ],
    "wof:name":"Sandycrafts",
    "wof:placetype":"venue"
},
  "geometry": {"coordinates":[-4.7638411522,50.4403686523],"type":"Point"}
}