{
  "type": "Feature",
  "properties": {
    "iso:country":"GB",
    "sg:address":"11c Station Rd",
    "sg:city":"Knebworth",
    "sg:classifiers":[
        {
            "category":"Military Area",
            "subcategory":"Air Force Base",
            "type":"Public Place"
        }
    ],
    "sg:postcode":"SG3 6AP",
    "sg:province":"Hertfordshire",
    "sg:tags":[
        "taxi",
        "hire",
        "private"
    ],
    "wof:name":"Beck,Jeff,",
    "wof:placetype":"venue"
},
  "geometry": {"coordinates":[-0.184881,51.866386],"type":"Point"}
}