{
  "type": "Feature",
  "properties": {
    "iso:country":"GB",
    "sg:address":"57 High Street, Holme On Spalding Moor",
    "sg:city":"York",
    "sg:classifiers":[
        {
            "category":"Bars & Pubs",
            "type":"Food & Drink"
        }
    ],
    "sg:postcode":"YO43 4EN",
    "sg:province":"East Riding of Yorkshire",
    "sg:tags":[
        "pubs",
        "inn"
    ],
    "wof:name":"Hare & Hounds Inn",
    "wof:placetype":"venue"
},
  "geometry": {"coordinates":[-0.7705150247,53.8365974426],"type":"Point"}
}