{
  "type": "Feature",
  "properties": {
    "addr:full":"2 High St Buildings, Tattenhall Chester Cheshire CH3 9PX",
    "addr:housenumber":"2",
    "addr:postcode":"ch3 9px",
    "addr:street":"High St",
    "iso:country":"GB",
    "sg:address":"2 High St Buildings, Tattenhall",
    "sg:city":"Chester",
    "sg:classifiers":[
        {
            "category":"Manufacturing",
            "subcategory":"Electronics",
            "type":"Manufacturing & Wholesale Goods"
        }
    ],
    "sg:phone":"+44 1829 771122",
    "sg:postcode":"CH3 9PX",
    "sg:province":"Cheshire",
    "sg:tags":[
        "mnfrs",
        "transformer"
    ],
    "wof:name":"Sass Electronic Services",
    "wof:placetype":"venue"
},
  "geometry": {"coordinates":[-2.7693729401,53.1201934814],"type":"Point"}
}