{
  "type": "Feature",
  "properties": {
    "addr:full":"Monk Meadow Dock Gloucester Gloucestershire GL2 5HU",
    "addr:postcode":"gl2 5hu",
    "addr:street":"Monk Meadow Dock Gloucester",
    "iso:country":"GB",
    "sg:address":"Monk Meadow Dock",
    "sg:city":"Gloucester",
    "sg:classifiers":[
        {
            "category":"Shopping",
            "subcategory":"Pets & Pet Supplies",
            "type":"Retail Goods"
        }
    ],
    "sg:postcode":"GL2 5HU",
    "sg:province":"Gloucestershire",
    "sg:tags":[
        "food"
    ],
    "wof:name":"Pet Feeds Ltd.",
    "wof:placetype":"venue"
},
  "geometry": {"coordinates":[-2.2599480152,51.8539505005],"type":"Point"}
}