{
  "type": "Feature",
  "properties": {
    "iso:country":"GB",
    "sg:address":"Nelson Court, 1a Nelsons Lane",
    "sg:city":"York",
    "sg:classifiers":[
        {
            "category":"Health Services",
            "subcategory":"Clinic",
            "type":"Services"
        }
    ],
    "sg:phone":"+44 1904 700720",
    "sg:postcode":"YO24 1HD",
    "sg:province":"North Yorkshire",
    "sg:tags":[
        "nh"
    ],
    "wof:name":"Meadowfields Community Unit For The Elderly",
    "wof:placetype":"venue"
},
  "geometry": {"coordinates":[-1.104216,53.943649],"type":"Point"}
}