{
  "type": "Feature",
  "properties": {
    "addr:full":"Unit 12 Calow Brook Drive Chesterfield Derbyshire S41 0DR",
    "addr:housenumber":"unit 12",
    "addr:postcode":"s41 0dr",
    "addr:street":"Brook Drive",
    "iso:country":"GB",
    "sg:address":"Unit 12 Calow Brook Drive",
    "sg:city":"Chesterfield",
    "sg:classifiers":[
        {
            "category":"Manufacturing",
            "subcategory":"Tools & Machinery",
            "type":"Manufacturing & Wholesale Goods"
        }
    ],
    "sg:phone":"+44 1246 556456",
    "sg:postcode":"S41 0DR",
    "sg:province":"Derbyshire",
    "wof:name":"Supertech Machine Tools Ltd",
    "wof:placetype":"venue"
},
  "geometry": {"coordinates":[-1.4000680447,53.2214622498],"type":"Point"}
}