{
  "type": "Feature",
  "properties": {
    "addr:full":"P O Box 256 Middlesbrough North Yorkshire TS1 5YB",
    "addr:housenumber":"256",
    "addr:postcode":"ts1 5yb",
    "addr:street":"P O Box",
    "iso:country":"GB",
    "sg:address":"P O Box 256",
    "sg:city":"Middlesbrough",
    "sg:classifiers":[
        {
            "category":"Professional",
            "subcategory":"Employment Agencies",
            "type":"Services"
        }
    ],
    "sg:phone":"+44 1642 240074",
    "sg:postcode":"TS1 5YB",
    "sg:province":"North Yorkshire",
    "sg:tags":[
        "consultant"
    ],
    "wof:name":"Fsl Recruitment",
    "wof:placetype":"venue"
},
  "geometry": {"coordinates":[-1.236569,54.572971],"type":"Point"}
}