{
  "type": "Feature",
  "properties": {
    "iso:country":"GB",
    "sg:address":"1368 Walker Road",
    "sg:city":"Newcastle-upon-tyne",
    "sg:classifiers":[
        {
            "category":"Food & Beverages",
            "subcategory":"Liquor & Beverages",
            "type":"Retail Goods"
        }
    ],
    "sg:phone":"+44 191 224 0936",
    "sg:postcode":"NE6 3JX",
    "sg:province":"Tyne and Wear",
    "sg:tags":[
        "beer",
        "spirit",
        "wines"
    ],
    "wof:name":"Bhandal Wine & Food Store",
    "wof:placetype":"venue"
},
  "geometry": {"coordinates":[-1.55273,54.964775],"type":"Point"}
}