{
  "type": "Feature",
  "properties": {
    "addr:full":"61 West St Horsham West Sussex RH12 1PL",
    "addr:housenumber":"61",
    "addr:postcode":"rh12 1pl",
    "addr:street":"West St",
    "iso:country":"GB",
    "sg:address":"61 West St",
    "sg:city":"Horsham",
    "sg:classifiers":[
        {
            "category":"Shopping",
            "subcategory":"Luggage & Leather Goods",
            "type":"Retail Goods"
        }
    ],
    "sg:phone":"+44 1403 263157",
    "sg:postcode":"RH12 1PL",
    "sg:province":"West Sussex",
    "sg:tags":[
        "shop",
        "leathergoods"
    ],
    "wof:name":"Steps",
    "wof:placetype":"venue"
},
  "geometry": {"coordinates":[-0.3293339908,51.0626411438],"type":"Point"}
}