{
  "type": "Feature",
  "properties": {
    "iso:country":"GB",
    "sg:address":"153/155 Sunbridge Road",
    "sg:city":"Bradford",
    "sg:classifiers":[
        {
            "category":"Freight",
            "type":"Transportation"
        }
    ],
    "sg:phone":"+44 1274 743402",
    "sg:postcode":"BD1 2NU",
    "sg:province":"West Yorkshire",
    "sg:tags":[
        "forwarders"
    ],
    "wof:name":"Frans Maas (Uk)",
    "wof:placetype":"venue"
},
  "geometry": {"coordinates":[-1.761523,53.794758],"type":"Point"}
}