{
  "type": "Feature",
  "properties": {
    "iso:country":"GB",
    "sg:address":"1 Camden Walk",
    "sg:city":"London",
    "sg:classifiers":[
        {
            "category":"Real Estate",
            "subcategory":"Real Estate Agent",
            "type":"Services"
        }
    ],
    "sg:phone":"+44 20 7704 5000",
    "sg:postcode":"N1 8DY",
    "sg:province":"Greater London",
    "wof:name":"Foxtons",
    "wof:placetype":"venue"
},
  "geometry": {"coordinates":[-0.1020329967,51.5355415344],"type":"Point"}
}