{
  "type": "Feature",
  "properties": {
    "addr:full":"152 Henver Road Newquay Cornwall TR7 3EQ",
    "addr:housenumber":"152",
    "addr:postcode":"tr7 3eq",
    "addr:street":"Henver Road",
    "iso:country":"GB",
    "sg:address":"152 Henver Road",
    "sg:city":"Newquay",
    "sg:classifiers":[
        {
            "category":"Travel",
            "subcategory":"Hotels & Motels",
            "type":"Entertainment"
        }
    ],
    "sg:phone":"+44 1637 875307",
    "sg:postcode":"TR7 3EQ",
    "sg:province":"Cornwall",
    "wof:name":"Ter-Ray-Lin Hotel",
    "wof:placetype":"venue"
},
  "geometry": {"coordinates":[-5.0532422066,50.4180221558],"type":"Point"}
}