{
  "type": "Feature",
  "properties": {
    "iso:country":"GB",
    "sg:address":"67 Edinburgh Rd, Ditton",
    "sg:city":"Widnes",
    "sg:classifiers":[
        {
            "category":"Organizations",
            "subcategory":"Non-profit Organization",
            "type":"Services"
        }
    ],
    "sg:phone":"+44 151 424 3362",
    "sg:postcode":"WA8 8BG",
    "sg:province":"Cheshire",
    "sg:tags":[
        "organisation",
        "voluntary",
        "charity"
    ],
    "wof:name":"Edinburgh Rd Day Centre",
    "wof:placetype":"venue"
},
  "geometry": {"coordinates":[-2.776202,53.366161],"type":"Point"}
}