{
  "type": "Feature",
  "properties": {
    "iso:country":"GB",
    "sg:address":"P O Box 328",
    "sg:city":"Lincoln",
    "sg:classifiers":[
        {
            "category":"Shopping",
            "subcategory":"Catalog Store",
            "type":"Retail Goods"
        }
    ],
    "sg:phone":"+44 1522 576670",
    "sg:postcode":"LN6 7YU",
    "sg:province":"Lincolnshire",
    "sg:tags":[
        "mail",
        "order"
    ],
    "wof:name":"Attitude Clothing Co.",
    "wof:placetype":"venue"
},
  "geometry": {"coordinates":[-0.56627,53.2094],"type":"Point"}
}