{
  "type": "Feature",
  "properties": {
    "addr:full":"Unit 7 Canalside Studios, 2-4 Orsman Rd Islington Greater London N1 5QJ",
    "addr:housenumber":"unit 7;2-4",
    "addr:postcode":"n1 5qj",
    "addr:street":"Orsman Rd",
    "iso:country":"GB",
    "sg:address":"Unit 7 Canalside Studios, 2-4 Orsman Rd",
    "sg:city":"Islington",
    "sg:classifiers":[
        {
            "category":"Manufacturing",
            "subcategory":"Metals",
            "type":"Manufacturing & Wholesale Goods"
        }
    ],
    "sg:phone":"+44 20 7729 3041",
    "sg:postcode":"N1 5QJ",
    "sg:province":"Greater London",
    "sg:tags":[
        "product",
        "fabricated"
    ],
    "wof:name":"Quality Castings",
    "wof:placetype":"venue"
},
  "geometry": {"coordinates":[-0.07888,51.536339],"type":"Point"}
}