{
  "type": "Feature",
  "properties": {
    "addr:full":"22 Pantain Road Loughborough Leicestershire LE11 3NA",
    "addr:housenumber":"22",
    "addr:postcode":"le11 3na",
    "addr:street":"Pantain Road",
    "iso:country":"GB",
    "sg:address":"22 Pantain Road",
    "sg:city":"Loughborough",
    "sg:classifiers":[
        {
            "category":"Autos & Motor Vehicles",
            "subcategory":"Automobile Sales",
            "type":"Retail Goods"
        },
        {
            "category":"Banks & Credit Unions",
            "subcategory":"Financial Services",
            "type":"Services"
        }
    ],
    "sg:postcode":"LE11 3NA",
    "sg:province":"Leicestershire",
    "sg:tags":[
        "consultant",
        "car"
    ],
    "wof:name":"M V M",
    "wof:placetype":"venue"
},
  "geometry": {"coordinates":[-1.2229939699,52.7578887939],"type":"Point"}
}