{
  "type": "Feature",
  "properties": {
    "addr:full":"213 High St Chatham Kent ME4 4BG",
    "addr:housenumber":"213",
    "addr:postcode":"me4 4bg",
    "addr:street":"High St",
    "iso:country":"GB",
    "sg:address":"213 High St",
    "sg:city":"Chatham",
    "sg:classifiers":[
        {
            "category":"Shopping",
            "subcategory":"Mobile Phones",
            "type":"Retail Goods"
        }
    ],
    "sg:phone":"+44 1634 848197",
    "sg:postcode":"ME4 4BG",
    "sg:province":"Kent",
    "wof:name":"Moco Developments Ltd",
    "wof:placetype":"venue"
},
  "geometry": {"coordinates":[0.5175309777,51.3832817078],"type":"Point"}
}