{
  "type": "Feature",
  "properties": {
    "iso:country":"GB",
    "sg:address":"46 College Road",
    "sg:city":"Maidstone",
    "sg:classifiers":[
        {
            "category":"Professional",
            "subcategory":"Management & Consulting",
            "type":"Services"
        }
    ],
    "sg:postcode":"ME15 6YF",
    "sg:province":"Kent",
    "sg:tags":[
        "consultant",
        "safety"
    ],
    "wof:name":"Construction Safety (Kent) Ltd.",
    "wof:placetype":"venue"
},
  "geometry": {"coordinates":[0.522655,51.268635],"type":"Point"}
}