{
  "type": "Feature",
  "properties": {
    "iso:country":"GB",
    "sg:address":"4a Cross Lane, Earlestown",
    "sg:city":"Newton Le Willows",
    "sg:classifiers":[
        {
            "category":"Organizations",
            "subcategory":"Political Organization",
            "type":"Services"
        }
    ],
    "sg:phone":"+44 1925 227210",
    "sg:postcode":"WA12 9QE",
    "sg:province":"Cheshire",
    "sg:tags":[
        "promoter",
        "pool"
    ],
    "wof:name":"Zetters Pools",
    "wof:placetype":"venue"
},
  "geometry": {"coordinates":[-2.6387019157,53.4535675049],"type":"Point"}
}