{
  "type": "Feature",
  "properties": {
    "iso:country":"GB",
    "sg:address":"44 Bury New Road, Prestwich",
    "sg:city":"Manchester",
    "sg:classifiers":[
        {
            "category":"Banks & Credit Unions",
            "subcategory":"Bank",
            "type":"Services"
        }
    ],
    "sg:phone":"+44 845 601 2288",
    "sg:postcode":"M25 1AB",
    "sg:province":"Greater Manchester",
    "wof:name":"National Westminster Bank Plc",
    "wof:placetype":"venue"
},
  "geometry": {"coordinates":[-2.282917,53.530651],"type":"Point"}
}