{
  "type": "Feature",
  "properties": {
    "addr:full":"Priors Way Maidenhead Berkshire SL6 2XJ",
    "addr:postcode":"sl6 2xj",
    "addr:street":"Priors Way",
    "iso:country":"GB",
    "sg:address":"Priors Way",
    "sg:city":"Maidenhead",
    "sg:classifiers":[
        {
            "category":"Utilities",
            "subcategory":"Telephone",
            "type":"Services"
        }
    ],
    "sg:phone":"+44 1628 785351",
    "sg:postcode":"SL6 2XJ",
    "sg:province":"Berkshire",
    "sg:tags":[
        "telecommunication"
    ],
    "wof:name":"Lane Group Of Companies",
    "wof:placetype":"venue"
},
  "geometry": {"coordinates":[-0.70769,51.501125],"type":"Point"}
}