{
  "type": "Feature",
  "properties": {
    "iso:country":"GB",
    "sg:address":"78 Whitmore Rd",
    "sg:city":"Harrow",
    "sg:classifiers":[
        {
            "category":"Professional",
            "subcategory":"Detective & Security Services",
            "type":"Services"
        }
    ],
    "sg:postcode":"HA1 4AH",
    "sg:province":"Greater London",
    "wof:name":"Tossain,C J,",
    "wof:placetype":"venue"
},
  "geometry": {"coordinates":[-0.350466,51.575317],"type":"Point"}
}