{
  "type": "Feature",
  "properties": {
    "addr:full":"89a Commercial Street, Risca Newport Blaenau Gwent NP11 6AW",
    "addr:housenumber":"89a",
    "addr:postcode":"np11 6aw",
    "addr:street":"Commercial Street",
    "iso:country":"GB",
    "sg:address":"89a Commercial Street, Risca",
    "sg:city":"Newport",
    "sg:classifiers":[
        {
            "category":"Building & Trades",
            "subcategory":"Construction",
            "type":"Services"
        }
    ],
    "sg:phone":"+44 1633 614460",
    "sg:postcode":"NP11 6AW",
    "sg:province":"Blaenau Gwent",
    "sg:tags":[
        "dry",
        "lining",
        "plasterers",
        "screeders"
    ],
    "wof:name":"Joyner P A (Cymru) Ltd.",
    "wof:placetype":"venue"
},
  "geometry": {"coordinates":[-3.0966670513,51.6042556763],"type":"Point"}
}