{
  "type": "Feature",
  "properties": {
    "addr:full":"37 Lowtown Pudsey West Yorkshire LS28 7DF",
    "addr:housenumber":"37",
    "addr:postcode":"ls28 7df",
    "addr:street":"Lowtown Pudsey West",
    "iso:country":"GB",
    "sg:address":"37 Lowtown",
    "sg:city":"Pudsey",
    "sg:classifiers":[
        {
            "category":"Cafe",
            "type":"Food & Drink"
        }
    ],
    "sg:postcode":"LS28 7DF",
    "sg:province":"West Yorkshire",
    "sg:tags":[
        "tea",
        "snack",
        "bar",
        "room"
    ],
    "wof:name":"Butterflies",
    "wof:placetype":"venue"
},
  "geometry": {"coordinates":[-1.659841,53.797413],"type":"Point"}
}