{
  "type": "Feature",
  "properties": {
    "addr:full":"76 Ermine Street South, Papworth Everard Cambridge Cambridgeshire CB3 8QA",
    "addr:housenumber":"76",
    "addr:postcode":"cb3 8qa",
    "addr:street":"Ermine Street South",
    "iso:country":"GB",
    "sg:address":"76 Ermine Street South, Papworth Everard",
    "sg:city":"Cambridge",
    "sg:classifiers":[
        {
            "category":"Building & Trades",
            "subcategory":"Pest Control",
            "type":"Services"
        }
    ],
    "sg:phone":"+44 1480 831010",
    "sg:postcode":"CB3 8QA",
    "sg:province":"Cambridgeshire",
    "sg:tags":[
        "shredding",
        "eqpt"
    ],
    "wof:name":"Industrial Shredding Systems Ltd.",
    "wof:placetype":"venue"
},
  "geometry": {"coordinates":[-0.093446,52.208183],"type":"Point"}
}