{
  "type": "Feature",
  "properties": {
    "iso:country":"GB",
    "sg:address":"The Warehouse, Chequers Hill, Doddington",
    "sg:city":"Sittingbourne",
    "sg:classifiers":[
        {
            "category":"Manufacturing",
            "subcategory":"Rubber & Plastics",
            "type":"Manufacturing & Wholesale Goods"
        }
    ],
    "sg:phone":"+44 1795 886869",
    "sg:postcode":"ME9 0BN",
    "sg:province":"Kent",
    "sg:tags":[
        "product",
        "foam"
    ],
    "wof:name":"Peter Dewson",
    "wof:placetype":"venue"
},
  "geometry": {"coordinates":[0.7713950276,51.2812232971],"type":"Point"}
}