{
  "type": "Feature",
  "properties": {
    "iso:country":"GB",
    "sg:address":"34 Parkett Heyes Road",
    "sg:city":"Macclesfield",
    "sg:classifiers":[
        {
            "category":"Building & Trades",
            "subcategory":"Construction",
            "type":"Services"
        }
    ],
    "sg:phone":"+44 1625 511227",
    "sg:postcode":"SK11 8UD",
    "sg:province":"Cheshire",
    "sg:tags":[
        "decorator",
        "painter"
    ],
    "wof:name":"Mark Thomas Lee",
    "wof:placetype":"venue"
},
  "geometry": {"coordinates":[-2.159819,53.257034],"type":"Point"}
}