{
  "type": "Feature",
  "properties": {
    "addr:full":"63 Derby Rd Manchester Greater Manchester M14 6RE",
    "addr:housenumber":"63",
    "addr:postcode":"m14 6re",
    "addr:street":"Derby Rd",
    "iso:country":"GB",
    "sg:address":"63 Derby Rd",
    "sg:city":"Manchester",
    "sg:classifiers":[
        {
            "category":"Building & Trades",
            "subcategory":"Pest Control",
            "type":"Services"
        }
    ],
    "sg:phone":"+44 161 224 3660",
    "sg:postcode":"M14 6RE",
    "sg:province":"Greater Manchester",
    "sg:tags":[
        "corrosion",
        "prevention"
    ],
    "wof:name":"C-probe Technologies",
    "wof:placetype":"venue"
},
  "geometry": {"coordinates":[-2.2151451111,53.4370193481],"type":"Point"}
}