{
  "type": "Feature",
  "properties": {
    "addr:full":"80 Westbere Road, West Hampstead London Greater London NW2 3RU",
    "addr:housenumber":"80",
    "addr:postcode":"nw2 3ru",
    "addr:street":"Westbere Road",
    "iso:country":"GB",
    "sg:address":"80 Westbere Road, West Hampstead",
    "sg:city":"London",
    "sg:classifiers":[
        {
            "category":"Farming",
            "subcategory":"Nursery",
            "type":"Manufacturing & Wholesale Goods"
        }
    ],
    "sg:phone":"+44 20 7794 6359",
    "sg:postcode":"NW2 3RU",
    "sg:province":"Greater London",
    "sg:tags":[
        "creche"
    ],
    "wof:name":"The Little Ark Montessori",
    "wof:placetype":"venue"
},
  "geometry": {"coordinates":[-0.2069859952,51.5540161133],"type":"Point"}
}