{
  "type": "Feature",
  "properties": {
    "iso:country":"GB",
    "sg:address":"Kirkintilloch Road, Bishopriggs",
    "sg:city":"Glasgow",
    "sg:classifiers":[
        {
            "category":"Autos & Motor Vehicles",
            "subcategory":"Fuel & Gas Station",
            "type":"Retail Goods"
        }
    ],
    "sg:phone":"+44 141 761 1270",
    "sg:postcode":"G64 2HS",
    "sg:province":"East Dunbartonshire",
    "sg:tags":[
        "hr",
        "petrol"
    ],
    "wof:name":"Shell Lowmoss",
    "wof:placetype":"venue"
},
  "geometry": {"coordinates":[-4.214154,55.917809],"type":"Point"}
}