{
  "type": "Feature",
  "properties": {
    "addr:full":"Christchurch Road New Milton Hampshire BH25 6QF",
    "addr:postcode":"bh25 6qf",
    "addr:street":"Christchurch Road",
    "iso:country":"GB",
    "sg:address":"Christchurch Road",
    "sg:city":"New Milton",
    "sg:classifiers":[
        {
            "category":"Bars & Pubs",
            "type":"Food & Drink"
        }
    ],
    "sg:phone":"+44 1425 618521",
    "sg:postcode":"BH25 6QF",
    "sg:province":"Hampshire",
    "sg:tags":[
        "pubs",
        "inn"
    ],
    "wof:name":"Centurion",
    "wof:placetype":"venue"
},
  "geometry": {"coordinates":[-1.6708120108,50.7455406189],"type":"Point"}
}