{
  "type": "Feature",
  "properties": {
    "addr:full":"Care Of Farnham Rugby Club, Westfield Lane, Wrecclesham Farnham Hampshire GU10 4QP",
    "addr:postcode":"gu10 4qp",
    "addr:street":"Westfield Lane",
    "iso:country":"GB",
    "sg:address":"Care Of Farnham Rugby Club, Westfield Lane, Wrecclesham",
    "sg:city":"Farnham",
    "sg:classifiers":[
        {
            "category":"Farming",
            "subcategory":"Nursery",
            "type":"Manufacturing & Wholesale Goods"
        }
    ],
    "sg:phone":"+44 1252 792630",
    "sg:postcode":"GU10 4QP",
    "sg:province":"Hampshire",
    "sg:tags":[
        "creche"
    ],
    "wof:name":"Farnham Montessori School",
    "wof:placetype":"venue"
},
  "geometry": {"coordinates":[-0.8176919818,51.200088501],"type":"Point"}
}