{
  "type": "Feature",
  "properties": {
    "addr:full":"72 Charlotte St Glasgow Glasgow City G1 5DW",
    "addr:housenumber":"72",
    "addr:postcode":"g1 5dw",
    "addr:street":"Charlotte St",
    "iso:country":"GB",
    "sg:address":"72 Charlotte St",
    "sg:city":"Glasgow",
    "sg:classifiers":[
        {
            "category":"Professional",
            "subcategory":"Management & Consulting",
            "type":"Services"
        }
    ],
    "sg:phone":"+44 141 552 0799",
    "sg:postcode":"G1 5DW",
    "sg:province":"Glasgow City",
    "sg:tags":[
        "consultant",
        "energy",
        "conservation"
    ],
    "wof:name":"Strathclyde & Central Energy Efficiency Advice Centre",
    "wof:placetype":"venue"
},
  "geometry": {"coordinates":[-4.241094,55.853497],"type":"Point"}
}