{
  "type": "Feature",
  "properties": {
    "addr:full":"Unit 15, Swan Centre, High Street Leatherhead Surrey KT22 8AH",
    "addr:housenumber":"unit 15",
    "addr:postcode":"kt22 8ah",
    "addr:street":"Swan Centre High Street",
    "iso:country":"GB",
    "sg:address":"Unit 15, Swan Centre, High Street",
    "sg:city":"Leatherhead",
    "sg:classifiers":[
        {
            "category":"Shopping",
            "subcategory":"Thrift Store",
            "type":"Retail Goods"
        }
    ],
    "sg:phone":"+44 1372 372922",
    "sg:postcode":"KT22 8AH",
    "sg:province":"Surrey",
    "sg:tags":[
        "shop",
        "charity"
    ],
    "wof:name":"Debra Charity Shop",
    "wof:placetype":"venue"
},
  "geometry": {"coordinates":[-0.329418987,51.2963600159],"type":"Point"}
}