{
  "type": "Feature",
  "properties": {
    "iso:country":"GB",
    "sg:address":"Stour Valley Industrial Estate, Ashford Road",
    "sg:city":"Canterbury",
    "sg:classifiers":[
        {
            "category":"Food & Beverages",
            "subcategory":"Ethnic Foods",
            "type":"Retail Goods"
        }
    ],
    "sg:phone":"+44 1227 731489",
    "sg:postcode":"CT4 7HS",
    "sg:province":"Kent",
    "sg:tags":[
        "merchant",
        "oil",
        "essential"
    ],
    "wof:name":"Meadows of Canterbury Ltd.",
    "wof:placetype":"venue"
},
  "geometry": {"coordinates":[1.021465,51.254566],"type":"Point"}
}