{
  "type": "Feature",
  "properties": {
    "addr:full":"353 Morland Road Croydon Surrey CR0 6HF",
    "addr:housenumber":"353",
    "addr:postcode":"cr0 6hf",
    "addr:street":"Morland Road",
    "iso:country":"GB",
    "sg:address":"353 Morland Road",
    "sg:city":"Croydon",
    "sg:classifiers":[
        {
            "category":"Fast Food",
            "type":"Food & Drink"
        },
        {
            "category":"Deli",
            "type":"Food & Drink"
        }
    ],
    "sg:phone":"+44 20 8656 8901",
    "sg:postcode":"CR0 6HF",
    "sg:province":"Surrey",
    "sg:tags":[
        "delivery",
        "snack",
        "sandwich"
    ],
    "wof:name":"The Knuckle Sandwich",
    "wof:placetype":"venue"
},
  "geometry": {"coordinates":[-0.0721829981,51.3856811523],"type":"Point"}
}