{
  "type": "Feature",
  "properties": {
    "iso:country":"GB",
    "sg:address":"40 Cape Hill",
    "sg:city":"Smethwick",
    "sg:classifiers":[
        {
            "category":"Farming",
            "subcategory":"Poultry Farm",
            "type":"Manufacturing & Wholesale Goods"
        }
    ],
    "sg:phone":"+44 121 558 9203",
    "sg:postcode":"B66 4PB",
    "sg:province":"West Midlands",
    "wof:name":"Best British Poultry",
    "wof:placetype":"venue"
},
  "geometry": {"coordinates":[-1.95972,52.486668],"type":"Point"}
}