{
  "type": "Feature",
  "properties": {
    "iso:country":"GB",
    "sg:address":"4 Toad Lane, Elston",
    "sg:city":"Newark",
    "sg:classifiers":[
        {
            "category":"Building & Trades",
            "subcategory":"Construction",
            "type":"Services"
        }
    ],
    "sg:phone":"+44 1636 525367",
    "sg:postcode":"NG23 5NS",
    "sg:province":"Lincolnshire",
    "sg:tags":[
        "contractor"
    ],
    "wof:name":"William Hudson",
    "wof:placetype":"venue"
},
  "geometry": {"coordinates":[-0.8661860228,53.0240402222],"type":"Point"}
}