{
  "type": "Feature",
  "properties": {
    "addr:full":"Po Box 4370 Epping Essex CM16 5FA",
    "addr:housenumber":"po;epping",
    "addr:postcode":"cm16 5fa",
    "addr:street":"Box 4370",
    "iso:country":"GB",
    "sg:address":"Po Box 4370",
    "sg:city":"Epping",
    "sg:classifiers":[
        {
            "category":"Communications",
            "subcategory":"Film & Video Production",
            "type":"Services"
        },
        {
            "category":"Shopping",
            "subcategory":"Computers & Home Electronics",
            "type":"Retail Goods"
        },
        {
            "category":"Communications",
            "subcategory":"Television Station",
            "type":"Services"
        }
    ],
    "sg:phone":"+44 1992 573550",
    "sg:postcode":"CM16 5FA",
    "sg:province":"Essex",
    "sg:tags":[
        "mnfr",
        "cctv",
        "equipment"
    ],
    "wof:name":"Laser Lynk 2000 Ltd.",
    "wof:placetype":"venue"
},
  "geometry": {"coordinates":[0.1116589978,51.6992988586],"type":"Point"}
}