{
  "type": "Feature",
  "properties": {
    "iso:country":"GB",
    "sg:address":"131 Whetstone La",
    "sg:city":"Birkenhead",
    "sg:classifiers":[
        {
            "category":"Shopping",
            "subcategory":"News",
            "type":"Retail Goods"
        }
    ],
    "sg:phone":"+44 151 647 8629",
    "sg:postcode":"L41 2TE",
    "sg:province":"Merseyside",
    "sg:tags":[
        "newsagent"
    ],
    "wof:name":"Tranmere Newsagents",
    "wof:placetype":"venue"
},
  "geometry": {"coordinates":[-3.024285,53.38459],"type":"Point"}
}