{
  "type": "Feature",
  "properties": {
    "iso:country":"GB",
    "sg:address":"3 Home Farm Cotts, Thetford Road, Riddlseworth",
    "sg:city":"Diss",
    "sg:classifiers":[
        {
            "category":"Building & Trades",
            "subcategory":"Landscaping Services",
            "type":"Services"
        }
    ],
    "sg:phone":"+44 1359 259368",
    "sg:postcode":"IP22 2TD",
    "sg:province":"Norfolk",
    "sg:tags":[
        "forestry",
        "tree"
    ],
    "wof:name":"M D Bleay",
    "wof:placetype":"venue"
},
  "geometry": {"coordinates":[0.8787599802,52.4014511108],"type":"Point"}
}