{
  "type": "Feature",
  "properties": {
    "addr:full":"Stambermill Indust Est, Timmis Rd Stourbridge West Midlands DY9 7BP",
    "addr:postcode":"dy9 7bp",
    "addr:street":"Timmis Rd",
    "iso:country":"GB",
    "sg:address":"Stambermill Indust Est, Timmis Rd",
    "sg:city":"Stourbridge",
    "sg:classifiers":[
        {
            "category":"Autos & Motor Vehicles",
            "subcategory":"Auto Supplies",
            "type":"Retail Goods"
        }
    ],
    "sg:phone":"+44 1384 424434",
    "sg:postcode":"DY9 7BP",
    "sg:province":"West Midlands",
    "sg:tags":[
        "component"
    ],
    "wof:name":"Brown Bros Group",
    "wof:placetype":"venue"
},
  "geometry": {"coordinates":[-2.1264,52.458851],"type":"Point"}
}