{
  "type": "Feature",
  "properties": {
    "addr:full":"8 The Old Rectory, Rectory Lane Banstead Surrey SM7 3PW",
    "addr:housenumber":"8",
    "addr:postcode":"sm7 3pw",
    "addr:street":"The;Rectory Lane",
    "iso:country":"GB",
    "sg:address":"8 The Old Rectory, Rectory Lane",
    "sg:city":"Banstead",
    "sg:classifiers":[
        {
            "category":"Building & Trades",
            "subcategory":"Landscaping Services",
            "type":"Services"
        }
    ],
    "sg:postcode":"SM7 3PW",
    "sg:province":"Surrey",
    "sg:tags":[
        "gardening"
    ],
    "wof:name":"A & S Roofing",
    "wof:placetype":"venue"
},
  "geometry": {"coordinates":[-0.200601995,51.3228225708],"type":"Point"}
}