{
  "type": "Feature",
  "properties": {
    "addr:full":"Leisure Hall, 22 Glasgow Road Denny Falkirk FK6 5BA",
    "addr:housenumber":"22",
    "addr:postcode":"fk6 5ba",
    "addr:street":"Glasgow Road",
    "iso:country":"GB",
    "sg:address":"Leisure Hall, 22 Glasgow Road",
    "sg:city":"Denny",
    "sg:classifiers":[
        {
            "category":"Community Center",
            "type":"Public Place"
        }
    ],
    "sg:phone":"+44 1324 822044",
    "sg:postcode":"FK6 5BA",
    "sg:province":"Falkirk",
    "sg:tags":[
        "centre",
        "entertainment"
    ],
    "wof:name":"Top Value Leisure Ltd.",
    "wof:placetype":"venue"
},
  "geometry": {"coordinates":[-3.916404,56.014584],"type":"Point"}
}