{
  "type": "Feature",
  "properties": {
    "iso:country":"GB",
    "sg:address":"10-14 Gwent Square",
    "sg:city":"Cwmbran",
    "sg:classifiers":[
        {
            "category":"Food & Beverages",
            "subcategory":"Supermarket",
            "type":"Retail Goods"
        }
    ],
    "sg:phone":"+44 1633 867303",
    "sg:postcode":"NP44 1PW",
    "sg:province":"Monmouthshire",
    "wof:name":"Somerfield Stores",
    "wof:placetype":"venue"
},
  "geometry": {"coordinates":[-3.0205760002,51.6545257568],"type":"Point"}
}