{
  "type": "Feature",
  "properties": {
    "iso:country":"GB",
    "sg:address":"9 Cannon Street, Atherton",
    "sg:city":"Manchester",
    "sg:classifiers":[
        {
            "category":"Personal",
            "subcategory":"Beauty Salon",
            "type":"Services"
        }
    ],
    "sg:phone":"+44 1942 882791",
    "sg:postcode":"M46 9JA",
    "sg:province":"Greater Manchester",
    "sg:tags":[
        "lady",
        "hairdresser"
    ],
    "wof:name":"May's",
    "wof:placetype":"venue"
},
  "geometry": {"coordinates":[-2.488679,53.525265],"type":"Point"}
}