{
  "type": "Feature",
  "properties": {
    "addr:full":"Mill Field Meadow, Holm Mill Lane Maidstone Kent ME17 1LA",
    "addr:postcode":"me17 1la",
    "addr:street":"Mill Field Meadow Holm Mill Lane",
    "iso:country":"GB",
    "sg:address":"Mill Field Meadow, Holm Mill Lane",
    "sg:city":"Maidstone",
    "sg:classifiers":[
        {
            "category":"Building & Trades",
            "subcategory":"Construction",
            "type":"Services"
        }
    ],
    "sg:postcode":"ME17 1LA",
    "sg:province":"Kent",
    "sg:tags":[
        "roofing"
    ],
    "wof:name":"Second Hand Building Materials",
    "wof:placetype":"venue"
},
  "geometry": {"coordinates":[0.606490016,51.2568778992],"type":"Point"}
}