{
  "type": "Feature",
  "properties": {
    "addr:full":"Northorpe Road, Northorpe Spalding Lincolnshire PE11 4XX",
    "addr:postcode":"pe11 4xx",
    "addr:street":"Northorpe Road;Spalding",
    "iso:country":"GB",
    "sg:address":"Northorpe Road, Northorpe",
    "sg:city":"Spalding",
    "sg:classifiers":[
        {
            "category":"Farming",
            "subcategory":"Livestock Farm",
            "type":"Manufacturing & Wholesale Goods"
        }
    ],
    "sg:postcode":"PE11 4XX",
    "sg:province":"Lincolnshire",
    "sg:tags":[
        "others"
    ],
    "wof:name":"R P & G M Haynes",
    "wof:placetype":"venue"
},
  "geometry": {"coordinates":[-0.2187840044,52.9147605896],"type":"Point"}
}