{
  "type": "Feature",
  "properties": {
    "addr:full":"Southampton Rd Lymington Hampshire SO41 8ND",
    "addr:postcode":"so41 8nd",
    "addr:street":"Southampton Rd",
    "iso:country":"GB",
    "sg:address":"Southampton Rd",
    "sg:city":"Lymington",
    "sg:classifiers":[
        {
            "category":"Travel",
            "subcategory":"Hotels & Motels",
            "type":"Entertainment"
        }
    ],
    "sg:phone":"+44 1590 679833",
    "sg:postcode":"SO41 8ND",
    "sg:province":"Hampshire",
    "sg:tags":[
        "house",
        "guest"
    ],
    "wof:name":"Boldremead Rest Home",
    "wof:placetype":"venue"
},
  "geometry": {"coordinates":[-1.552989006,50.7680664062],"type":"Point"}
}