{
  "type": "Feature",
  "properties": {
    "iso:country":"GB",
    "sg:address":"Howe House, 13 Sommers Road",
    "sg:city":"Halesowen",
    "sg:classifiers":[
        {
            "category":"Government",
            "subcategory":"Fire Station",
            "type":"Public Place"
        },
        {
            "category":"Food & Beverages",
            "subcategory":"Fruits & Vegetables",
            "type":"Retail Goods"
        }
    ],
    "sg:phone":"+44 121 585 3870",
    "sg:postcode":"B62 8EN",
    "sg:province":"West Midlands",
    "sg:tags":[
        "security",
        "greengrocer"
    ],
    "wof:name":"Firstfire Ltd.",
    "wof:placetype":"venue"
},
  "geometry": {"coordinates":[-2.045589,52.454739],"type":"Point"}
}