{
  "type": "Feature",
  "properties": {
    "addr:full":"Unit 22 Rainbow Indust Est, Trout Rd West Drayton Greater London UB7 7RN",
    "addr:housenumber":"unit 22",
    "addr:postcode":"ub7 7rn",
    "addr:street":"Rainbow Indust Est Trout Rd",
    "iso:country":"GB",
    "sg:address":"Unit 22 Rainbow Indust Est, Trout Rd",
    "sg:city":"West Drayton",
    "sg:classifiers":[
        {
            "category":"Professional",
            "subcategory":"Engineering",
            "type":"Services"
        }
    ],
    "sg:phone":"+44 1895 430248",
    "sg:postcode":"UB7 7RN",
    "sg:province":"Greater London",
    "sg:tags":[
        "precision",
        "engineer"
    ],
    "wof:name":"D R Precision Engineering",
    "wof:placetype":"venue"
},
  "geometry": {"coordinates":[-0.4739899933,51.5091171265],"type":"Point"}
}