{
  "type": "Feature",
  "properties": {
    "addr:full":"Flat 4, 23 Chestnut Road London Greater London SW20 8ED",
    "addr:housenumber":"23",
    "addr:postcode":"sw20 8ed",
    "addr:street":"Chestnut Road",
    "iso:country":"GB",
    "sg:address":"Flat 4, 23 Chestnut Road",
    "sg:city":"London",
    "sg:classifiers":[
        {
            "category":"Professional",
            "subcategory":"Computer Services",
            "type":"Services"
        }
    ],
    "sg:postcode":"SW20 8ED",
    "sg:province":"Greater London",
    "sg:tags":[
        "system",
        "software"
    ],
    "wof:name":"Matchville Limited",
    "wof:placetype":"venue"
},
  "geometry": {"coordinates":[-0.2197699994,51.4098892212],"type":"Point"}
}