{
  "type": "Feature",
  "properties": {
    "iso:country":"GB",
    "sg:address":"109 High Street",
    "sg:city":"Kirkcudbright",
    "sg:classifiers":[
        {
            "category":"Professional",
            "subcategory":"Accounting & Tax Preparation",
            "type":"Services"
        }
    ],
    "sg:phone":"+44 1557 330050",
    "sg:postcode":"DG6 4JG",
    "sg:province":"Dumfries and Galloway",
    "sg:tags":[
        "accountant"
    ],
    "wof:name":"D M Campbell & Company",
    "wof:placetype":"venue"
},
  "geometry": {"coordinates":[-4.0530948639,54.8351097107],"type":"Point"}
}