{
  "type": "Feature",
  "properties": {
    "iso:country":"GB",
    "sg:address":"39a Millrise Rd",
    "sg:city":"Stoke-on-trent",
    "sg:classifiers":[
        {
            "category":"Sports & Exercise",
            "subcategory":"Gym",
            "type":"Entertainment"
        }
    ],
    "sg:postcode":"ST2 7BN",
    "sg:province":"Staffordshire",
    "sg:tags":[
        "fitness",
        "health",
        "centre"
    ],
    "wof:name":"Bradley,Stephen,",
    "wof:placetype":"venue"
},
  "geometry": {"coordinates":[-2.142113,53.049244],"type":"Point"}
}