{
  "type": "Feature",
  "properties": {
    "iso:country":"GB",
    "sg:address":"Fordhay, East Chinnock",
    "sg:city":"Yeovil",
    "sg:classifiers":[
        {
            "category":"Shopping",
            "subcategory":"Department Store",
            "type":"Retail Goods"
        }
    ],
    "sg:phone":"+44 1935 862157",
    "sg:postcode":"BA22 9EE",
    "sg:province":"Dorset",
    "wof:name":"East Chinnock Post Office Stores",
    "wof:placetype":"venue"
},
  "geometry": {"coordinates":[-2.7186939716,50.9156951904],"type":"Point"}
}