{
  "type": "Feature",
  "properties": {
    "addr:full":"192 Vauxhall Bridge Road London Greater London SW1V 1DX",
    "addr:housenumber":"192",
    "addr:postcode":"sw1v 1dx",
    "addr:street":"Vauxhall Bridge Road",
    "iso:country":"GB",
    "sg:address":"192 Vauxhall Bridge Road",
    "sg:city":"London",
    "sg:classifiers":[
        {
            "category":"Conference Center",
            "type":"Public Place"
        }
    ],
    "sg:postcode":"SW1V 1DX",
    "sg:province":"Greater London",
    "wof:name":"Tfi Holdings Ltd.",
    "wof:placetype":"venue"
},
  "geometry": {"coordinates":[-0.13899,51.493393],"type":"Point"}
}