{
  "type": "Feature",
  "properties": {
    "iso:country":"GB",
    "sg:address":"Daimler House, Paradise Circus",
    "sg:city":"Birmingham",
    "sg:classifiers":[
        {
            "category":"Organizations",
            "subcategory":"Community Association",
            "type":"Services"
        }
    ],
    "sg:phone":"+44 121 687 5000",
    "sg:postcode":"B1 2BJ",
    "sg:province":"West Midlands",
    "sg:tags":[
        "society",
        "housing"
    ],
    "wof:name":"Focus Housing Association Ltd.",
    "wof:placetype":"venue"
},
  "geometry": {"coordinates":[-1.908604,52.478596],"type":"Point"}
}