{
  "type": "Feature",
  "properties": {
    "iso:country":"GB",
    "sg:address":"48 De Parys Avenue",
    "sg:city":"Bedford",
    "sg:classifiers":[
        {
            "category":"Travel",
            "subcategory":"Hotels & Motels",
            "type":"Entertainment"
        }
    ],
    "sg:phone":"+44 1234 352445",
    "sg:postcode":"MK40 2TP",
    "sg:province":"Bedfordshire",
    "sg:tags":[
        "house",
        "guest"
    ],
    "wof:name":"De Parys Guest House",
    "wof:placetype":"venue"
},
  "geometry": {"coordinates":[-0.467071,52.143314],"type":"Point"}
}