{
  "type": "Feature",
  "properties": {
    "addr:full":"11-18 Royal Avenue, Kirkham Preston Lancashire PR4 2ST",
    "addr:housenumber":"11-18",
    "addr:postcode":"pr4 2st",
    "addr:street":"Royal Avenue",
    "iso:country":"GB",
    "sg:address":"11-18 Royal Avenue, Kirkham",
    "sg:city":"Preston",
    "sg:classifiers":[
        {
            "category":"Education",
            "subcategory":"School",
            "type":"Public Place"
        }
    ],
    "sg:phone":"+44 1772 682008",
    "sg:postcode":"PR4 2ST",
    "sg:province":"Lancashire",
    "sg:tags":[
        "local",
        "authority"
    ],
    "wof:name":"Carr Hill 11-18 High School",
    "wof:placetype":"venue"
},
  "geometry": {"coordinates":[-2.8694639206,53.7793159485],"type":"Point"}
}