{
  "type": "Feature",
  "properties": {
    "addr:full":"3 The Old Coachouse, Llangattock Crickhowell Monmouthshire NP8 1PH",
    "addr:housenumber":"3",
    "addr:postcode":"np8 1ph",
    "addr:street":"The Old Coachouse",
    "iso:country":"GB",
    "sg:address":"3 The Old Coachouse, Llangattock",
    "sg:city":"Crickhowell",
    "sg:classifiers":[
        {
            "category":"Home & Garden",
            "subcategory":"Garden Supply",
            "type":"Retail Goods"
        }
    ],
    "sg:phone":"+44 1873 811234",
    "sg:postcode":"NP8 1PH",
    "sg:province":"Monmouthshire",
    "sg:tags":[
        "water"
    ],
    "wof:name":"Hortas Water Gardens",
    "wof:placetype":"venue"
},
  "geometry": {"coordinates":[-3.138122,51.861626],"type":"Point"}
}