{
  "type": "Feature",
  "properties": {
    "iso:country":"GB",
    "sg:address":"12 Hill St",
    "sg:city":"Swadlincote",
    "sg:classifiers":[
        {
            "category":"Professional",
            "subcategory":"Lawyer & Legal Services",
            "type":"Services"
        }
    ],
    "sg:postcode":"DE11 8HL",
    "sg:province":"Derbyshire",
    "sg:tags":[
        "solicitor"
    ],
    "wof:name":"Parrans & Co",
    "wof:placetype":"venue"
},
  "geometry": {"coordinates":[-1.552996,52.772152],"type":"Point"}
}