{
  "type": "Feature",
  "properties": {
    "iso:country":"GB",
    "sg:address":"The Owlpen, Kites Nest Lane, Churcham",
    "sg:city":"Gloucester",
    "sg:classifiers":[
        {
            "category":"Farming",
            "subcategory":"Livestock Farm",
            "type":"Manufacturing & Wholesale Goods"
        }
    ],
    "sg:phone":"+44 1452 790342",
    "sg:postcode":"GL2 8BL",
    "sg:province":"Gloucestershire",
    "sg:tags":[
        "others"
    ],
    "wof:name":"D H H Wheeler",
    "wof:placetype":"venue"
},
  "geometry": {"coordinates":[-2.3411459923,51.8666687012],"type":"Point"}
}