{
  "type": "Feature",
  "properties": {
    "addr:full":"24 Salisbury Street Blandford Forum Dorset DT11 7AR",
    "addr:housenumber":"24",
    "addr:postcode":"dt11 7ar",
    "addr:street":"Salisbury Street",
    "iso:country":"GB",
    "sg:address":"24 Salisbury Street",
    "sg:city":"Blandford Forum",
    "sg:classifiers":[
        {
            "category":"Shopping",
            "subcategory":"Clothing, Apparel, & Fashions",
            "type":"Retail Goods"
        }
    ],
    "sg:postcode":"DT11 7AR",
    "sg:province":"Dorset",
    "sg:tags":[
        "shop"
    ],
    "wof:name":"Easy Strider",
    "wof:placetype":"venue"
},
  "geometry": {"coordinates":[-2.1650800705,50.856754303],"type":"Point"}
}