{
  "type": "Feature",
  "properties": {
    "addr:full":"2nd Floor 17 Queens Gate Inverness Highland IV1 1DF",
    "addr:housenumber":"2nd floor 17",
    "addr:postcode":"iv1 1df",
    "addr:street":"Queens Gate",
    "iso:country":"GB",
    "sg:address":"2nd Floor 17 Queens Gate",
    "sg:city":"Inverness",
    "sg:classifiers":[
        {
            "category":"Banks & Credit Unions",
            "subcategory":"Financial Services",
            "type":"Services"
        }
    ],
    "sg:phone":"+44 1463 718111",
    "sg:postcode":"IV1 1DF",
    "sg:province":"Highland",
    "sg:tags":[
        "adviser"
    ],
    "wof:name":"M C M Investment House & Mortgage Bureau",
    "wof:placetype":"venue"
},
  "geometry": {"coordinates":[-4.2260169983,57.479221344],"type":"Point"}
}