{
  "type": "Feature",
  "properties": {
    "addr:full":"29 Burroway Road, Langley Slough Berkshire SL3 8EH",
    "addr:housenumber":"29",
    "addr:postcode":"sl3 8eh",
    "addr:street":"Burroway Road",
    "iso:country":"GB",
    "sg:address":"29 Burroway Road, Langley",
    "sg:city":"Slough",
    "sg:classifiers":[
        {
            "category":"Professional",
            "subcategory":"Management & Consulting",
            "type":"Services"
        }
    ],
    "sg:phone":"+44 1753 540541",
    "sg:postcode":"SL3 8EH",
    "sg:province":"Berkshire",
    "sg:tags":[
        "consultant",
        "business"
    ],
    "wof:name":"D Stacey",
    "wof:placetype":"venue"
},
  "geometry": {"coordinates":[-0.533419,51.502041],"type":"Point"}
}