{
  "type": "Feature",
  "properties": {
    "iso:country":"GB",
    "sg:address":"10 Devonshire Rd, Upton",
    "sg:city":"Wirral",
    "sg:classifiers":[
        {
            "category":"Freight",
            "type":"Transportation"
        }
    ],
    "sg:postcode":"CH49 6NW",
    "sg:province":"Merseyside",
    "sg:tags":[
        "cargo",
        "handling"
    ],
    "wof:name":"Euro-Land Shipping (U K) Ltd",
    "wof:placetype":"venue"
},
  "geometry": {"coordinates":[-3.111202,53.386768],"type":"Point"}
}