{
  "type": "Feature",
  "properties": {
    "addr:full":"Downton Cottage, Crescent St Halkirk Highland KW12 6XN",
    "addr:postcode":"kw12 6xn",
    "addr:street":"Crescent St",
    "iso:country":"GB",
    "sg:address":"Downton Cottage, Crescent St",
    "sg:city":"Halkirk",
    "sg:classifiers":[
        {
            "category":"Building & Trades",
            "subcategory":"Construction",
            "type":"Services"
        }
    ],
    "sg:postcode":"KW12 6XN",
    "sg:province":"Highland",
    "sg:tags":[
        "joiner",
        "carpenter"
    ],
    "wof:name":"Mackay,Jock,",
    "wof:placetype":"venue"
},
  "geometry": {"coordinates":[-3.495523,58.514343],"type":"Point"}
}