{
  "type": "Feature",
  "properties": {
    "addr:full":"61 Caledonian Road London Greater London N1 9BT",
    "addr:housenumber":"61",
    "addr:postcode":"n1 9bt",
    "addr:street":"Caledonian Road",
    "iso:country":"GB",
    "sg:address":"61 Caledonian Road",
    "sg:city":"London",
    "sg:classifiers":[
        {
            "category":"Real Estate",
            "subcategory":"Real Estate Operator",
            "type":"Services"
        }
    ],
    "sg:phone":"+44 20 7619 9500",
    "sg:postcode":"N1 9BT",
    "sg:province":"Greater London",
    "sg:tags":[
        "letting",
        "agent"
    ],
    "wof:name":"Caledonian Accommodation Agency",
    "wof:placetype":"venue"
},
  "geometry": {"coordinates":[-0.1198860034,51.53282547],"type":"Point"}
}