{
  "type": "Feature",
  "properties": {
    "iso:country":"GB",
    "sg:address":"55 Queen Street, Morley",
    "sg:city":"Leeds",
    "sg:classifiers":[
        {
            "category":"Professional",
            "subcategory":"Computer Services",
            "type":"Services"
        }
    ],
    "sg:postcode":"LS27 8EB",
    "sg:province":"West Yorkshire",
    "sg:tags":[
        "system",
        "software"
    ],
    "wof:name":"Steven Springer",
    "wof:placetype":"venue"
},
  "geometry": {"coordinates":[-1.602244,53.747246],"type":"Point"}
}