{
  "type": "Feature",
  "properties": {
    "iso:country":"GB",
    "sg:address":"272 Barking Road, East Ham",
    "sg:city":"London",
    "sg:classifiers":[
        {
            "category":"Real Estate",
            "subcategory":"Real Estate Agent",
            "type":"Services"
        }
    ],
    "sg:postcode":"E6 3BA",
    "sg:province":"Greater London",
    "wof:name":"Eden Homes",
    "wof:placetype":"venue"
},
  "geometry": {"coordinates":[0.051039,51.532333],"type":"Point"}
}