{
  "type": "Feature",
  "properties": {
    "addr:full":"125 Richmond Rd Kingston Upon Thames Greater London KT2 5BX",
    "addr:housenumber":"125",
    "addr:postcode":"kt2 5bx",
    "addr:street":"Richmond Rd",
    "iso:country":"GB",
    "sg:address":"125 Richmond Rd",
    "sg:city":"Kingston Upon Thames",
    "sg:classifiers":[
        {
            "category":"Government",
            "subcategory":"Police Station",
            "type":"Public Place"
        }
    ],
    "sg:phone":"+44 20 8541 0233",
    "sg:postcode":"KT2 5BX",
    "sg:province":"Greater London",
    "sg:tags":[
        "support"
    ],
    "wof:name":"The Family Court Unit",
    "wof:placetype":"venue"
},
  "geometry": {"coordinates":[-0.3017530143,51.4182472229],"type":"Point"}
}