{
  "type": "Feature",
  "properties": {
    "iso:country":"GB",
    "sg:address":"Siop-y-llan",
    "sg:city":"Dolwyddelan",
    "sg:classifiers":[
        {
            "category":"Shopping",
            "subcategory":"Department Store",
            "type":"Retail Goods"
        }
    ],
    "sg:phone":"+44 1690 750237",
    "sg:postcode":"LL25 0NZ",
    "sg:province":"Conwy",
    "wof:name":"Spar",
    "wof:placetype":"venue"
},
  "geometry": {"coordinates":[-3.889524,53.052963],"type":"Point"}
}