{
  "type": "Feature",
  "properties": {
    "addr:full":"Suite 8 Fraser Ho Bridge La, Frodsham Warrington Cheshire WA6 7HD",
    "addr:housenumber":"suite 8",
    "addr:postcode":"wa6 7hd",
    "addr:street":"Fraser Ho Bridge La Frodsham",
    "iso:country":"GB",
    "sg:address":"Suite 8 Fraser Ho Bridge La, Frodsham",
    "sg:city":"Warrington",
    "sg:classifiers":[
        {
            "category":"Shopping",
            "subcategory":"Stationery & Office Supplies",
            "type":"Retail Goods"
        }
    ],
    "sg:postcode":"WA6 7HD",
    "sg:province":"Cheshire",
    "sg:tags":[
        "printers'"
    ],
    "wof:name":"Newhouse,John,",
    "wof:placetype":"venue"
},
  "geometry": {"coordinates":[-2.7251389027,53.2964401245],"type":"Point"}
}