{
  "type": "Feature",
  "properties": {
    "iso:country":"GB",
    "sg:address":"Wighay Bdge, Annesley Rd, Hucknall",
    "sg:city":"Nottingham",
    "sg:classifiers":[
        {
            "category":"Retail",
            "subcategory":"Auto Repair",
            "type":"Services"
        }
    ],
    "sg:phone":"+44 115 963 2428",
    "sg:postcode":"NG15 7DA",
    "sg:province":"Nottinghamshire",
    "sg:tags":[
        "modification",
        "garage"
    ],
    "wof:name":"Granville Motors",
    "wof:placetype":"venue"
},
  "geometry": {"coordinates":[-1.209209,53.032398],"type":"Point"}
}