{
  "type": "Feature",
  "properties": {
    "addr:full":"Malborough Street Bristol City of Bristol BS2 8HW",
    "addr:postcode":"bs2 8hw",
    "addr:street":"Malborough Street",
    "iso:country":"GB",
    "sg:address":"Malborough Street",
    "sg:city":"Bristol",
    "sg:classifiers":[
        {
            "category":"Health Services",
            "subcategory":"Hospital",
            "type":"Services"
        }
    ],
    "sg:phone":"+44 117 923 0000",
    "sg:postcode":"BS2 8HW",
    "sg:province":"City of Bristol",
    "wof:name":"Bristol Royal Infirmary",
    "wof:placetype":"venue"
},
  "geometry": {"coordinates":[-2.5940189362,51.4598312378],"type":"Point"}
}