{
  "type": "Feature",
  "properties": {
    "addr:full":"275 High Street Canvey Island Essex SS8 7RS",
    "addr:housenumber":"275",
    "addr:postcode":"ss8 7rs",
    "addr:street":"High Street",
    "iso:country":"GB",
    "sg:address":"275 High Street",
    "sg:city":"Canvey Island",
    "sg:classifiers":[
        {
            "category":"Food & Beverages",
            "subcategory":"Fruits & Vegetables",
            "type":"Retail Goods"
        }
    ],
    "sg:phone":"+44 1268 682031",
    "sg:postcode":"SS8 7RS",
    "sg:province":"Essex",
    "sg:tags":[
        "greengrocer"
    ],
    "wof:name":"Fruits and Roots",
    "wof:placetype":"venue"
},
  "geometry": {"coordinates":[0.609421,51.519043],"type":"Point"}
}