{
  "type": "Feature",
  "properties": {
    "addr:full":"200 Meadowpark Street Glasgow Glasgow City G31 2TE",
    "addr:housenumber":"200",
    "addr:postcode":"g31 2te",
    "addr:street":"Meadowpark Street",
    "iso:country":"GB",
    "sg:address":"200 Meadowpark Street",
    "sg:city":"Glasgow",
    "sg:classifiers":[
        {
            "category":"Restaurant",
            "type":"Food & Drink"
        }
    ],
    "sg:phone":"+44 141 556 4433",
    "sg:postcode":"G31 2TE",
    "sg:province":"Glasgow City",
    "wof:name":"Parade Restaurant Bar",
    "wof:placetype":"venue"
},
  "geometry": {"coordinates":[-4.213958,55.862938],"type":"Point"}
}