{
  "type": "Feature",
  "properties": {
    "iso:country":"GB",
    "sg:address":"Summerbank Road",
    "sg:city":"Stoke-on-trent",
    "sg:classifiers":[
        {
            "category":"Manufacturing",
            "subcategory":"Pottery",
            "type":"Manufacturing & Wholesale Goods"
        }
    ],
    "sg:phone":"+44 1782 837303",
    "sg:postcode":"ST6 5EZ",
    "sg:province":"Staffordshire",
    "wof:name":"Harry Hancock (Tunstall) Ltd.",
    "wof:placetype":"venue"
},
  "geometry": {"coordinates":[-2.2158439159,53.0653610229],"type":"Point"}
}