{
  "type": "Feature",
  "properties": {
    "iso:country":"GB",
    "sg:address":"P O Box 29",
    "sg:city":"Ammanford",
    "sg:classifiers":[
        {
            "category":"Banks & Credit Unions",
            "subcategory":"Financial Services",
            "type":"Services"
        }
    ],
    "sg:postcode":"SA18 2YY",
    "sg:province":"Carmarthenshire",
    "sg:tags":[
        "consultant"
    ],
    "wof:name":"Kimlan Corporations",
    "wof:placetype":"venue"
},
  "geometry": {"coordinates":[-3.984129,51.789398],"type":"Point"}
}