{
  "type": "Feature",
  "properties": {
    "iso:country":"GB",
    "sg:address":"Chelmsley Wood Library, Stephenson Drive",
    "sg:city":"Birmingham",
    "sg:classifiers":[
        {
            "category":"Education",
            "subcategory":"Library",
            "type":"Public Place"
        },
        {
            "category":"Government",
            "subcategory":"Office",
            "type":"Public Place"
        }
    ],
    "sg:phone":"+44 121 788 4380",
    "sg:postcode":"B37 5TA",
    "sg:province":"West Midlands",
    "sg:tags":[
        "book",
        "local"
    ],
    "wof:name":"Chelmsley Wood Library",
    "wof:placetype":"venue"
},
  "geometry": {"coordinates":[-1.740567,52.480465],"type":"Point"}
}