{
  "type": "Feature",
  "properties": {
    "addr:full":"51 Leopold Road Felixstowe Suffolk IP11 7NR",
    "addr:housenumber":"51",
    "addr:postcode":"ip11 7nr",
    "addr:street":"Leopold Road",
    "iso:country":"GB",
    "sg:address":"51 Leopold Road",
    "sg:city":"Felixstowe",
    "sg:classifiers":[
        {
            "category":"Professional",
            "subcategory":"Business Services",
            "type":"Services"
        }
    ],
    "sg:phone":"+44 1394 279539",
    "sg:postcode":"IP11 7NR",
    "sg:province":"Suffolk",
    "sg:tags":[
        "trade"
    ],
    "wof:name":"European Confederation of Care Home Owners",
    "wof:placetype":"venue"
},
  "geometry": {"coordinates":[1.3494930267,51.9609909058],"type":"Point"}
}