{
  "type": "Feature",
  "properties": {
    "iso:country":"GB",
    "sg:address":"1 Sybil Road",
    "sg:city":"Leicester",
    "sg:classifiers":[
        {
            "category":"Health Services",
            "subcategory":"Clinic",
            "type":"Services"
        }
    ],
    "sg:postcode":"LE3 2EX",
    "sg:province":"Leicestershire",
    "sg:tags":[
        "private"
    ],
    "wof:name":"Ayurveda Health Centre",
    "wof:placetype":"venue"
},
  "geometry": {"coordinates":[-1.16048,52.61647],"type":"Point"}
}