{
  "type": "Feature",
  "properties": {
    "addr:full":"56 Factory Lane Croydon Surrey CR0 3RL",
    "addr:housenumber":"56",
    "addr:postcode":"cr0 3rl",
    "addr:street":"Factory Lane",
    "iso:country":"GB",
    "sg:address":"56 Factory Lane",
    "sg:city":"Croydon",
    "sg:classifiers":[
        {
            "category":"Retail",
            "subcategory":"Auto Rental",
            "type":"Services"
        }
    ],
    "sg:phone":"+44 20 8688 8598",
    "sg:postcode":"CR0 3RL",
    "sg:province":"Surrey",
    "sg:tags":[
        "truck",
        "hire",
        "van"
    ],
    "wof:name":"Via Countryside Vehicle Rental & Contract Hire",
    "wof:placetype":"venue"
},
  "geometry": {"coordinates":[-0.1101490036,51.3770599365],"type":"Point"}
}