{
  "type": "Feature",
  "properties": {
    "addr:full":"Station Road Industrial Estate Rowley Regis West Midlands B65 0JY",
    "addr:postcode":"b65 0jy",
    "addr:street":"Station Road Industrial Estate Rowley",
    "iso:country":"GB",
    "sg:address":"Station Road Industrial Estate",
    "sg:city":"Rowley Regis",
    "sg:classifiers":[
        {
            "category":"Building & Trades",
            "subcategory":"Construction",
            "type":"Services"
        }
    ],
    "sg:postcode":"B65 0JY",
    "sg:province":"West Midlands",
    "sg:tags":[
        "flooring"
    ],
    "wof:name":"Stebro Flooring Co. Ltd.",
    "wof:placetype":"venue"
},
  "geometry": {"coordinates":[-2.0326368809,52.4779014587],"type":"Point"}
}