{
  "type": "Feature",
  "properties": {
    "iso:country":"GB",
    "sg:address":"15 Southlands Avenue",
    "sg:city":"Newcastle",
    "sg:classifiers":[
        {
            "category":"Farming",
            "subcategory":"Nursery",
            "type":"Manufacturing & Wholesale Goods"
        }
    ],
    "sg:phone":"+44 1782 626148",
    "sg:postcode":"ST5 8BZ",
    "sg:province":"Staffordshire",
    "sg:tags":[
        "creche"
    ],
    "wof:name":"Southlands Creche & Kindergarten",
    "wof:placetype":"venue"
},
  "geometry": {"coordinates":[-2.223025,53.030067],"type":"Point"}
}