{
  "type": "Feature",
  "properties": {
    "addr:full":"Eastgate House, Humberstone Road Leicester Leicestershire LE5 3GJ",
    "addr:postcode":"le5 3gj",
    "addr:street":"Eastgate;Humberstone Road",
    "iso:country":"GB",
    "sg:address":"Eastgate House, Humberstone Road",
    "sg:city":"Leicester",
    "sg:classifiers":[
        {
            "category":"Home & Garden",
            "subcategory":"Home Furnishings",
            "type":"Retail Goods"
        }
    ],
    "sg:postcode":"LE5 3GJ",
    "sg:province":"Leicestershire",
    "sg:tags":[
        "homefurnishings"
    ],
    "wof:name":"Sloane Furniture Systems Ltd",
    "wof:placetype":"venue"
},
  "geometry": {"coordinates":[-1.1042040586,52.642288208],"type":"Point"}
}