{
  "type": "Feature",
  "properties": {
    "iso:country":"GB",
    "sg:address":"37 Main Street",
    "sg:city":"Cockermouth",
    "sg:classifiers":[
        {
            "category":"Bars & Pubs",
            "type":"Food & Drink"
        }
    ],
    "sg:phone":"+44 1900 823174",
    "sg:postcode":"CA13 9JS",
    "sg:province":"Cumbria",
    "sg:tags":[
        "pubs",
        "inn"
    ],
    "wof:name":"Ann Coats",
    "wof:placetype":"venue"
},
  "geometry": {"coordinates":[-3.364824,54.663574],"type":"Point"}
}