{
  "type": "Feature",
  "properties": {
    "addr:full":"3 Barnard Clo Norwich Norfolk NR14 8LJ",
    "addr:housenumber":"3",
    "addr:postcode":"nr14 8lj",
    "addr:street":"Barnard;Norwich",
    "iso:country":"GB",
    "sg:address":"3 Barnard Clo",
    "sg:city":"Norwich",
    "sg:classifiers":[
        {
            "category":"Retail",
            "subcategory":"Auto Repair",
            "type":"Services"
        }
    ],
    "sg:phone":"+44 1508 493331",
    "sg:postcode":"NR14 8LJ",
    "sg:province":"Norfolk",
    "sg:tags":[
        "modification",
        "garage"
    ],
    "wof:name":"A 1 Mobile Brake Service",
    "wof:placetype":"venue"
},
  "geometry": {"coordinates":[1.2992949486,52.5667152405],"type":"Point"}
}