{
  "type": "Feature",
  "properties": {
    "addr:full":", Blagdon Hill Taunton Devon TA3 7SG",
    "addr:postcode":"ta3 7sg",
    "addr:street":"Hill",
    "iso:country":"GB",
    "sg:address":", Blagdon Hill",
    "sg:city":"Taunton",
    "sg:classifiers":[
        {
            "category":"Bars & Pubs",
            "type":"Food & Drink"
        }
    ],
    "sg:phone":"+44 1823 421296",
    "sg:postcode":"TA3 7SG",
    "sg:province":"Devon",
    "sg:tags":[
        "pubs",
        "inn"
    ],
    "wof:name":"The White Lion",
    "wof:placetype":"venue"
},
  "geometry": {"coordinates":[-3.116575,51.005302],"type":"Point"}
}