{
  "type": "Feature",
  "properties": {
    "iso:country":"GB",
    "sg:address":"17 Yelvertoft Road, Crick",
    "sg:city":"Northampton",
    "sg:classifiers":[
        {
            "category":"Building & Trades",
            "subcategory":"Landscaping Services",
            "type":"Services"
        },
        {
            "category":"Organizations",
            "subcategory":"Labor Organization",
            "type":"Services"
        }
    ],
    "sg:phone":"+44 1788 823811",
    "sg:postcode":"NN6 7XS",
    "sg:province":"Northamptonshire",
    "sg:tags":[
        "development",
        "irrigation",
        "design",
        "system"
    ],
    "wof:name":"Access Irrigation Ltd.",
    "wof:placetype":"venue"
},
  "geometry": {"coordinates":[-1.170041,52.386616],"type":"Point"}
}