{
  "type": "Feature",
  "properties": {
    "addr:full":"Sea View Road Colwyn Bay Conwy LL29 8DG",
    "addr:postcode":"ll29 8dg",
    "addr:street":"Sea View Road",
    "iso:country":"GB",
    "sg:address":"Sea View Road",
    "sg:city":"Colwyn Bay",
    "sg:classifiers":[
        {
            "category":"Personal",
            "subcategory":"Beauty Salon",
            "type":"Services"
        }
    ],
    "sg:phone":"+44 1492 530773",
    "sg:postcode":"LL29 8DG",
    "sg:province":"Conwy",
    "sg:tags":[
        "unisex",
        "hairdresser"
    ],
    "wof:name":"Hair Express",
    "wof:placetype":"venue"
},
  "geometry": {"coordinates":[-3.726079,53.294464],"type":"Point"}
}