{
  "type": "Feature",
  "properties": {
    "iso:country":"GB",
    "sg:address":"28 Fleet Street",
    "sg:city":"London",
    "sg:classifiers":[
        {
            "category":"Cafe",
            "type":"Food & Drink"
        }
    ],
    "sg:phone":"+44 20 7353 2332",
    "sg:postcode":"EC4Y 1AA",
    "sg:province":"Greater London",
    "sg:tags":[
        "tea",
        "room"
    ],
    "wof:name":"Pret A Manger (U K) Ltd.",
    "wof:placetype":"venue"
},
  "geometry": {"coordinates":[-0.110437,51.513885],"type":"Point"}
}