{
  "type": "Feature",
  "properties": {
    "iso:country":"GB",
    "sg:address":"Offshore House",
    "sg:city":"Blyth",
    "sg:classifiers":[
        {
            "category":"Professional",
            "subcategory":"Computer Services",
            "type":"Services"
        }
    ],
    "sg:postcode":"NE24 1LZ",
    "sg:province":"Northumberland",
    "sg:tags":[
        "system",
        "software"
    ],
    "wof:name":"I T M S",
    "wof:placetype":"venue"
},
  "geometry": {"coordinates":[-1.533384,55.156425],"type":"Point"}
}