{
  "type": "Feature",
  "properties": {
    "addr:full":"191 Spital Rd Wirral Cheshire CH62 2AF",
    "addr:housenumber":"191",
    "addr:postcode":"ch62 2af",
    "addr:street":"Spital Rd",
    "iso:country":"GB",
    "sg:address":"191 Spital Rd",
    "sg:city":"Wirral",
    "sg:classifiers":[
        {
            "category":"Social Services",
            "subcategory":"Retirement Home",
            "type":"Services"
        }
    ],
    "sg:phone":"+44 151 334 0142",
    "sg:postcode":"CH62 2AF",
    "sg:province":"Cheshire",
    "sg:tags":[
        "residential",
        "care"
    ],
    "wof:name":"Sylvandale Residential Home",
    "wof:placetype":"venue"
},
  "geometry": {"coordinates":[-2.985004,53.340172],"type":"Point"}
}