{
  "type": "Feature",
  "properties": {
    "iso:country":"GB",
    "sg:address":"9 King Street",
    "sg:city":"Blackpool",
    "sg:classifiers":[
        {
            "category":"Personal",
            "type":"Services"
        }
    ],
    "sg:phone":"+44 1253 625431",
    "sg:postcode":"FY1 3EJ",
    "sg:province":"Lancashire",
    "sg:tags":[
        "tailor"
    ],
    "wof:name":"Nat Dunsby",
    "wof:placetype":"venue"
},
  "geometry": {"coordinates":[-3.0489959717,53.8195075989],"type":"Point"}
}