{
  "type": "Feature",
  "properties": {
    "iso:country":"GB",
    "sg:address":"Unit 2/3 Sproughton Business Par, K Farthing Road",
    "sg:city":"Ipswich",
    "sg:classifiers":[
        {
            "category":"Home & Garden",
            "subcategory":"Hardware",
            "type":"Retail Goods"
        },
        {
            "category":"Manufacturing",
            "subcategory":"Textiles",
            "type":"Manufacturing & Wholesale Goods"
        }
    ],
    "sg:phone":"+44 1473 740400",
    "sg:postcode":"IP1 5AP",
    "sg:province":"Suffolk",
    "sg:tags":[
        "tarpaulin",
        "manufacturer"
    ],
    "wof:name":"Martin Fenn Tarpaulins",
    "wof:placetype":"venue"
},
  "geometry": {"coordinates":[1.1270589828,52.066570282],"type":"Point"}
}