{
  "type": "Feature",
  "properties": {
    "iso:country":"GB",
    "sg:address":"2 Chell Street",
    "sg:city":"Stoke-on-trent",
    "sg:classifiers":[
        {
            "category":"Bars & Pubs",
            "type":"Food & Drink"
        }
    ],
    "sg:phone":"+44 1782 272723",
    "sg:postcode":"ST1 6BA",
    "sg:province":"Staffordshire",
    "sg:tags":[
        "pubs",
        "inn"
    ],
    "wof:name":"The Fox & Duck",
    "wof:placetype":"venue"
},
  "geometry": {"coordinates":[-2.1696500778,53.0332336426],"type":"Point"}
}