{
  "type": "Feature",
  "properties": {
    "addr:full":"678 Fulham Road London Greater London SW6 5HH",
    "addr:housenumber":"678",
    "addr:postcode":"sw6 5hh",
    "addr:street":"Fulham Road",
    "iso:country":"GB",
    "sg:address":"678 Fulham Road",
    "sg:city":"London",
    "sg:classifiers":[
        {
            "category":"Food & Beverages",
            "subcategory":"Bakery",
            "type":"Retail Goods"
        }
    ],
    "sg:postcode":"SW6 5HH",
    "sg:province":"Greater London",
    "sg:tags":[
        "pizza"
    ],
    "wof:name":"Pizza the Action",
    "wof:placetype":"venue"
},
  "geometry": {"coordinates":[-0.2064760029,51.4751205444],"type":"Point"}
}