{
  "type": "Feature",
  "properties": {
    "addr:full":"71-77 Byron Street Glasgow Glasgow City G11 6LY",
    "addr:housenumber":"71-77",
    "addr:postcode":"g11 6ly",
    "addr:street":"Byron Street",
    "iso:country":"GB",
    "sg:address":"71-77 Byron Street",
    "sg:city":"Glasgow",
    "sg:classifiers":[
        {
            "category":"Retail",
            "subcategory":"Auto Repair",
            "type":"Services"
        }
    ],
    "sg:phone":"+44 141 337 1062",
    "sg:postcode":"G11 6LY",
    "sg:province":"Glasgow City",
    "sg:tags":[
        "modification",
        "garage"
    ],
    "wof:name":"New Beetlemania",
    "wof:placetype":"venue"
},
  "geometry": {"coordinates":[-4.3268790245,55.8714103699],"type":"Point"}
}