{
  "type": "Feature",
  "properties": {
    "addr:full":"2 Barmeston Road, Catford London Greater London SE6 3BH",
    "addr:housenumber":"2",
    "addr:postcode":"se6 3bh",
    "addr:street":"Barmeston Road",
    "iso:country":"GB",
    "sg:address":"2 Barmeston Road, Catford",
    "sg:city":"London",
    "sg:classifiers":[
        {
            "category":"Wholesale",
            "subcategory":"Electrical",
            "type":"Manufacturing & Wholesale Goods"
        },
        {
            "category":"Shopping",
            "subcategory":"Computers & Home Electronics",
            "type":"Retail Goods"
        }
    ],
    "sg:phone":"+44 20 8695 6989",
    "sg:postcode":"SE6 3BH",
    "sg:province":"Greater London",
    "sg:tags":[
        "wholesaler"
    ],
    "wof:name":"Gurney & White Ltd.",
    "wof:placetype":"venue"
},
  "geometry": {"coordinates":[-0.0198260006,51.4386482239],"type":"Point"}
}