{
  "type": "Feature",
  "properties": {
    "addr:full":"8 Chaucer Park, Sterndale Road Dartford Kent DA1 1RE",
    "addr:housenumber":"8",
    "addr:postcode":"da1 1re",
    "addr:street":"Chaucer Park Sterndale Road",
    "iso:country":"GB",
    "sg:address":"8 Chaucer Park, Sterndale Road",
    "sg:city":"Dartford",
    "sg:classifiers":[
        {
            "category":"Professional",
            "subcategory":"Engineering",
            "type":"Services"
        }
    ],
    "sg:postcode":"DA1 1RE",
    "sg:province":"Kent",
    "wof:name":"A E Callard (Engineering) Ltd.",
    "wof:placetype":"venue"
},
  "geometry": {"coordinates":[0.22416,51.442116],"type":"Point"}
}