{
  "type": "Feature",
  "properties": {
    "addr:full":"1 Phoenix Ho, Golborne Enterprise Pk Warrington Cheshire WA3 3DP",
    "addr:housenumber":"1;golborne",
    "addr:postcode":"wa3 3dp",
    "addr:street":"Phoenix Ho;Enterprise Pk Warrington Cheshire",
    "iso:country":"GB",
    "sg:address":"1 Phoenix Ho, Golborne Enterprise Pk",
    "sg:city":"Warrington",
    "sg:classifiers":[
        {
            "category":"Organizations",
            "subcategory":"Non-profit Organization",
            "type":"Services"
        }
    ],
    "sg:postcode":"WA3 3DP",
    "sg:province":"Cheshire",
    "sg:tags":[
        "organisation",
        "voluntary",
        "charity"
    ],
    "wof:name":"Transplant Life Foundation",
    "wof:placetype":"venue"
},
  "geometry": {"coordinates":[-2.5968389511,53.4766998291],"type":"Point"}
}