{
  "type": "Feature",
  "properties": {
    "addr:full":"Hope Mill, Racecommon Rd Barnsley South Yorkshire S70 6AA",
    "addr:postcode":"s70 6aa",
    "addr:street":"Hope;Racecommon Rd;Yorkshire",
    "iso:country":"GB",
    "sg:address":"Hope Mill, Racecommon Rd",
    "sg:city":"Barnsley",
    "sg:classifiers":[
        {
            "category":"Professional",
            "subcategory":"Employment Agencies",
            "type":"Services"
        }
    ],
    "sg:phone":"+44 1226 288377",
    "sg:postcode":"S70 6AA",
    "sg:province":"South Yorkshire",
    "sg:tags":[
        "consultant"
    ],
    "wof:name":"Staff & Office Services",
    "wof:placetype":"venue"
},
  "geometry": {"coordinates":[-1.487999,53.551331],"type":"Point"}
}