{
  "type": "Feature",
  "properties": {
    "addr:full":"Oxford St Southampton Hampshire SO14 3DT",
    "addr:postcode":"so14 3dt",
    "addr:street":"Oxford St",
    "iso:country":"GB",
    "sg:address":"Oxford St",
    "sg:city":"Southampton",
    "sg:classifiers":[
        {
            "category":"Bars & Pubs",
            "subcategory":"Nightclub",
            "type":"Food & Drink"
        }
    ],
    "sg:phone":"+44 23 8032 6325",
    "sg:postcode":"SO14 3DT",
    "sg:province":"Hampshire",
    "sg:tags":[
        "club",
        "night"
    ],
    "wof:name":"Tube The",
    "wof:placetype":"venue"
},
  "geometry": {"coordinates":[-1.3993120193,50.8985786438],"type":"Point"}
}