{
  "type": "Feature",
  "properties": {
    "iso:country":"GB",
    "sg:address":"554 Elder Gate",
    "sg:city":"Milton Keynes",
    "sg:classifiers":[
        {
            "category":"Personal",
            "subcategory":"Beauty Salon",
            "type":"Services"
        }
    ],
    "sg:phone":"+44 1908 235555",
    "sg:postcode":"MK9 1LR",
    "sg:province":"Buckinghamshire",
    "sg:tags":[
        "unisex",
        "hairdresser"
    ],
    "wof:name":"Chesney Hair & Beauty Salon",
    "wof:placetype":"venue"
},
  "geometry": {"coordinates":[-0.770523,52.034184],"type":"Point"}
}