{
  "type": "Feature",
  "properties": {
    "addr:full":"Bakehouse Lane, Burton Latimer Kettering Northamptonshire NN15 5NJ",
    "addr:postcode":"nn15 5nj",
    "addr:street":"Bakehouse Lane",
    "iso:country":"GB",
    "sg:address":"Bakehouse Lane, Burton Latimer",
    "sg:city":"Kettering",
    "sg:classifiers":[
        {
            "category":"Restaurant",
            "type":"Food & Drink"
        }
    ],
    "sg:postcode":"NN15 5NJ",
    "sg:province":"Northamptonshire",
    "wof:name":"Olde Victoria Public House & Restaurant",
    "wof:placetype":"venue"
},
  "geometry": {"coordinates":[-0.6899039745,52.3654556274],"type":"Point"}
}