{
  "type": "Feature",
  "properties": {
    "iso:country":"GB",
    "sg:address":"64 High Street",
    "sg:city":"Braintree",
    "sg:classifiers":[
        {
            "category":"Food & Beverages",
            "subcategory":"Fruits & Vegetables",
            "type":"Retail Goods"
        }
    ],
    "sg:postcode":"CM7 1JP",
    "sg:province":"Essex",
    "sg:tags":[
        "greengrocer"
    ],
    "wof:name":"Gowlings",
    "wof:placetype":"venue"
},
  "geometry": {"coordinates":[0.550582,51.878361],"type":"Point"}
}