{
  "type": "Feature",
  "properties": {
    "addr:full":"51 Castle Gate Newark Nottinghamshire NG24 1BE",
    "addr:housenumber":"51",
    "addr:postcode":"ng24 1be",
    "addr:street":"Castle Gate",
    "iso:country":"GB",
    "sg:address":"51 Castle Gate",
    "sg:city":"Newark",
    "sg:classifiers":[
        {
            "category":"Food & Beverages",
            "subcategory":"Meat & Fish",
            "type":"Retail Goods"
        }
    ],
    "sg:postcode":"NG24 1BE",
    "sg:province":"Nottinghamshire",
    "sg:tags":[
        "chip"
    ],
    "wof:name":"Correa,Justin,",
    "wof:placetype":"venue"
},
  "geometry": {"coordinates":[-0.813042,53.07626],"type":"Point"}
}