{
  "type": "Feature",
  "properties": {
    "addr:full":"Unit 1-2, 13-17 Grecian Street Salford Greater Manchester M7 1JF",
    "addr:housenumber":"unit 1-2",
    "addr:postcode":"13-17;m7 1jf",
    "addr:street":"Grecian Street",
    "iso:country":"GB",
    "sg:address":"Unit 1-2, 13-17 Grecian Street",
    "sg:city":"Salford",
    "sg:classifiers":[
        {
            "category":"Building & Trades",
            "subcategory":"Construction",
            "type":"Services"
        },
        {
            "category":"Home & Garden",
            "subcategory":"Carpets & Floor Coverings",
            "type":"Retail Goods"
        }
    ],
    "sg:phone":"+44 161 708 9373",
    "sg:postcode":"M7 1JF",
    "sg:province":"Greater Manchester",
    "sg:tags":[
        "resurfacing",
        "laying",
        "refinishing",
        "flooring"
    ],
    "wof:name":"A G Flooring Ltd",
    "wof:placetype":"venue"
},
  "geometry": {"coordinates":[-2.2667059898,53.4977493286],"type":"Point"}
}