{
  "type": "Feature",
  "properties": {
    "iso:country":"GB",
    "sg:address":"32 Scotby Avenue",
    "sg:city":"Chatham",
    "sg:classifiers":[
        {
            "category":"Building & Trades",
            "subcategory":"Construction",
            "type":"Services"
        }
    ],
    "sg:phone":"+44 1634 865774",
    "sg:postcode":"ME5 8ER",
    "sg:province":"Kent",
    "sg:tags":[
        "decorator",
        "painter"
    ],
    "wof:name":"Colin Munn",
    "wof:placetype":"venue"
},
  "geometry": {"coordinates":[0.53561,51.347679],"type":"Point"}
}