{
  "type": "Feature",
  "properties": {
    "addr:full":"55 West Main Street, Whitburn Bathgate North Lanarkshire EH47 0QD",
    "addr:housenumber":"55",
    "addr:postcode":"eh47 0qd",
    "addr:street":"West Main Street;Bathgate",
    "iso:country":"GB",
    "sg:address":"55 West Main Street, Whitburn",
    "sg:city":"Bathgate",
    "sg:classifiers":[
        {
            "category":"Bars & Pubs",
            "type":"Food & Drink"
        }
    ],
    "sg:phone":"+44 1501 742797",
    "sg:postcode":"EH47 0QD",
    "sg:province":"North Lanarkshire",
    "sg:tags":[
        "pubs",
        "inn"
    ],
    "wof:name":"The Double Fife",
    "wof:placetype":"venue"
},
  "geometry": {"coordinates":[-3.6874990463,55.8662452698],"type":"Point"}
}