{
  "type": "Feature",
  "properties": {
    "iso:country":"GB",
    "sg:address":"Hollygrove Farm, Upper Northam Drive, The Hedge End",
    "sg:city":"Southampton",
    "sg:classifiers":[
        {
            "category":"Retail",
            "subcategory":"Auto Repair",
            "type":"Services"
        }
    ],
    "sg:postcode":"SO30 4BG",
    "sg:province":"Hampshire",
    "sg:tags":[
        "modification",
        "garage"
    ],
    "wof:name":"The Hedge End Car Clinic",
    "wof:placetype":"venue"
},
  "geometry": {"coordinates":[-1.292531,50.91584],"type":"Point"}
}