{
  "type": "Feature",
  "properties": {
    "addr:full":"The Old Town Hall, Market Sq Dunstable Bedfordshire LU5 6QJ",
    "addr:postcode":"lu5 6qj",
    "addr:street":"Market Sq",
    "iso:country":"GB",
    "sg:address":"The Old Town Hall, Market Sq",
    "sg:city":"Dunstable",
    "sg:classifiers":[
        {
            "category":"Professional",
            "subcategory":"Computer Services",
            "type":"Services"
        }
    ],
    "sg:phone":"+44 1525 877229",
    "sg:postcode":"LU5 6QJ",
    "sg:province":"Bedfordshire",
    "sg:tags":[
        "system",
        "software"
    ],
    "wof:name":"Datascan 2000 Ltd",
    "wof:placetype":"venue"
},
  "geometry": {"coordinates":[-0.53219,51.949551],"type":"Point"}
}