{
  "type": "Feature",
  "properties": {
    "addr:full":"Unit 11 Denby Dale Indstl Pk, Wakefield Rd, Denby Dale Huddersfield South Yorkshire HD8 8QH",
    "addr:housenumber":"unit 11",
    "addr:postcode":"hd8 8qh",
    "addr:street":"Indstl Pk Wakefield Rd;Dale",
    "iso:country":"GB",
    "sg:address":"Unit 11 Denby Dale Indstl Pk, Wakefield Rd, Denby Dale",
    "sg:city":"Huddersfield",
    "sg:classifiers":[
        {
            "category":"Home & Garden",
            "subcategory":"Garden Supply",
            "type":"Retail Goods"
        }
    ],
    "sg:postcode":"HD8 8QH",
    "sg:province":"South Yorkshire",
    "sg:tags":[
        "ornament"
    ],
    "wof:name":"Brainwaves",
    "wof:placetype":"venue"
},
  "geometry": {"coordinates":[-1.6537419558,53.5735244751],"type":"Point"}
}