{
  "type": "Feature",
  "properties": {
    "addr:full":"22 Oakleigh Road South Friern Barnet Greater London N11 1NH",
    "addr:housenumber":"22",
    "addr:postcode":"n11 1nh",
    "addr:street":"Oakleigh Road South",
    "iso:country":"GB",
    "sg:address":"22 Oakleigh Road South",
    "sg:city":"Friern Barnet",
    "sg:classifiers":[
        {
            "category":"Personal",
            "subcategory":"Beauty Salon",
            "type":"Services"
        }
    ],
    "sg:phone":"+44 20 8368 2192",
    "sg:postcode":"N11 1NH",
    "sg:province":"Greater London",
    "sg:tags":[
        "unisex",
        "hairdresser"
    ],
    "wof:name":"Emile",
    "wof:placetype":"venue"
},
  "geometry": {"coordinates":[-0.1424320042,51.6173973083],"type":"Point"}
}