{
  "type": "Feature",
  "properties": {
    "addr:full":"154 Cowley Road Oxford Oxfordshire OX4 1UE",
    "addr:housenumber":"154",
    "addr:postcode":"ox4 1ue",
    "addr:street":"Cowley Road",
    "iso:country":"GB",
    "sg:address":"154 Cowley Road",
    "sg:city":"Oxford",
    "sg:classifiers":[
        {
            "category":"Banks & Credit Unions",
            "subcategory":"Bank",
            "type":"Services"
        },
        {
            "category":"Banks & Credit Unions",
            "subcategory":"Financial Services",
            "type":"Services"
        }
    ],
    "sg:phone":"+44 1865 433360",
    "sg:postcode":"OX4 1UE",
    "sg:province":"Oxfordshire",
    "sg:tags":[
        "broker",
        "mortgage"
    ],
    "wof:name":"Oxford Financial Services",
    "wof:placetype":"venue"
},
  "geometry": {"coordinates":[-1.2362600565,51.7474784851],"type":"Point"}
}