{
  "type": "Feature",
  "properties": {
    "iso:country":"GB",
    "sg:address":"Unit 2 Hercules House, Calleva Park, Aldermaston",
    "sg:city":"Reading",
    "sg:classifiers":[
        {
            "category":"Wholesale",
            "subcategory":"Chemicals & Plastics",
            "type":"Manufacturing & Wholesale Goods"
        }
    ],
    "sg:phone":"+44 118 981 3333",
    "sg:postcode":"RG7 8DN",
    "sg:province":"Berkshire",
    "sg:tags":[
        "product",
        "allied"
    ],
    "wof:name":"Agil Ltd.",
    "wof:placetype":"venue"
},
  "geometry": {"coordinates":[-1.16283,51.36071],"type":"Point"}
}