{
  "type": "Feature",
  "properties": {
    "addr:full":"Beresford Building, The Greenway, Thorntree Middlesbrough North Yorkshire TS3 9NB",
    "addr:postcode":"ts3 9nb",
    "addr:street":"The Greenway Thorntree",
    "iso:country":"GB",
    "sg:address":"Beresford Building, The Greenway, Thorntree",
    "sg:city":"Middlesbrough",
    "sg:classifiers":[
        {
            "category":"Professional",
            "subcategory":"Employment Agencies",
            "type":"Services"
        }
    ],
    "sg:phone":"+44 1642 398001",
    "sg:postcode":"TS3 9NB",
    "sg:province":"North Yorkshire",
    "sg:tags":[
        "consultant"
    ],
    "wof:name":"Employment Service Jobcentre",
    "wof:placetype":"venue"
},
  "geometry": {"coordinates":[-1.184833,54.564808],"type":"Point"}
}