{
  "type": "Feature",
  "properties": {
    "iso:country":"GB",
    "sg:address":"Doctors Surgery, 135 Mill Lane",
    "sg:city":"Romford",
    "sg:classifiers":[
        {
            "category":"Health Services",
            "subcategory":"Doctor",
            "type":"Services"
        }
    ],
    "sg:phone":"+44 20 8599 6835",
    "sg:postcode":"RM6 6RS",
    "sg:province":"Essex",
    "sg:tags":[
        "practitioners"
    ],
    "wof:name":"N P S Teotia",
    "wof:placetype":"venue"
},
  "geometry": {"coordinates":[0.1396999955,51.5753097534],"type":"Point"}
}