{
  "type": "Feature",
  "properties": {
    "iso:country":"GB",
    "sg:address":"Care Of Brook St Garage, Higher Hillgate",
    "sg:city":"Stockport",
    "sg:classifiers":[
        {
            "category":"Retail",
            "subcategory":"Auto Repair",
            "type":"Services"
        }
    ],
    "sg:phone":"+44 161 477 7426",
    "sg:postcode":"SK1 3HS",
    "sg:province":"Cheshire",
    "sg:tags":[
        "modification",
        "garage"
    ],
    "wof:name":"S R T Motor Services",
    "wof:placetype":"venue"
},
  "geometry": {"coordinates":[-2.1530799866,53.4008789062],"type":"Point"}
}