{
  "type": "Feature",
  "properties": {
    "iso:country":"GB",
    "sg:address":"Rutledge Mews, 1 Southbourne Road",
    "sg:city":"Sheffield",
    "sg:classifiers":[
        {
            "category":"Real Estate",
            "subcategory":"Real Estate Operator",
            "type":"Services"
        },
        {
            "category":"Real Estate",
            "subcategory":"Real Estate Services",
            "type":"Services"
        }
    ],
    "sg:phone":"+44 845 437 6012",
    "sg:postcode":"S10 2QN",
    "sg:province":"South Yorkshire",
    "sg:tags":[
        "letting",
        "management",
        "agent"
    ],
    "wof:name":"City Estates",
    "wof:placetype":"venue"
},
  "geometry": {"coordinates":[-1.464544,53.38311],"type":"Point"}
}