{
  "type": "Feature",
  "properties": {
    "iso:country":"GB",
    "sg:address":"93 Victoria Rd",
    "sg:city":"Aldershot",
    "sg:classifiers":[
        {
            "category":"Fast Food",
            "type":"Food & Drink"
        }
    ],
    "sg:postcode":"GU11 1JE",
    "sg:province":"Hampshire",
    "sg:tags":[
        "away",
        "take"
    ],
    "wof:name":"Spanish Delicious",
    "wof:placetype":"venue"
},
  "geometry": {"coordinates":[-0.7621440291,51.2481842041],"type":"Point"}
}