{
  "type": "Feature",
  "properties": {
    "addr:full":"Overbecks, Sharpitor Salcombe Devon TQ8 8LW",
    "addr:postcode":"tq8 8lw",
    "iso:country":"GB",
    "sg:address":"Overbecks, Sharpitor",
    "sg:city":"Salcombe",
    "sg:classifiers":[
        {
            "category":"Travel",
            "subcategory":"Hostel",
            "type":"Entertainment"
        }
    ],
    "sg:phone":"+44 1548 842856",
    "sg:postcode":"TQ8 8LW",
    "sg:province":"Devon",
    "sg:tags":[
        "youth"
    ],
    "wof:name":"Youth Hostels Association (England & Wales)",
    "wof:placetype":"venue"
},
  "geometry": {"coordinates":[-3.774799,50.237865],"type":"Point"}
}