{
  "type": "Feature",
  "properties": {
    "iso:country":"GB",
    "sg:address":"Ensign House, 56 Regent Road",
    "sg:city":"Leicester",
    "sg:classifiers":[
        {
            "category":"Professional",
            "subcategory":"Computer Services",
            "type":"Services"
        }
    ],
    "sg:phone":"+44 116 254 9444",
    "sg:postcode":"LE1 6YD",
    "sg:province":"Leicestershire",
    "sg:tags":[
        "development",
        "system",
        "software"
    ],
    "wof:name":"Ensign Advanced Systems Ltd",
    "wof:placetype":"venue"
},
  "geometry": {"coordinates":[-1.140365,52.637886],"type":"Point"}
}