{
  "type": "Feature",
  "properties": {
    "addr:full":"477 Greenwood Crescent Warrington Cheshire WA2 0EE",
    "addr:housenumber":"477",
    "addr:postcode":"wa2 0ee",
    "addr:street":"Greenwood Crescent",
    "iso:country":"GB",
    "sg:address":"477 Greenwood Crescent",
    "sg:city":"Warrington",
    "sg:classifiers":[
        {
            "category":"Home & Garden",
            "subcategory":"Building Materials",
            "type":"Retail Goods"
        }
    ],
    "sg:phone":"+44 1925 824131",
    "sg:postcode":"WA2 0EE",
    "sg:province":"Cheshire",
    "sg:tags":[
        "fencing"
    ],
    "wof:name":"D J Hines",
    "wof:placetype":"venue"
},
  "geometry": {"coordinates":[-2.567992,53.41478],"type":"Point"}
}