{
  "type": "Feature",
  "properties": {
    "iso:country":"GB",
    "sg:address":"Marley Lane, Kingston",
    "sg:city":"Canterbury",
    "sg:classifiers":[
        {
            "category":"Transit Center",
            "subcategory":"Passenger",
            "type":"Transportation"
        }
    ],
    "sg:phone":"+44 1227 830145",
    "sg:postcode":"CT4 6JH",
    "sg:province":"Kent",
    "sg:tags":[
        "boarding",
        "kennel",
        "catteries"
    ],
    "wof:name":"Little Marley Farm Boarding Kennels",
    "wof:placetype":"venue"
},
  "geometry": {"coordinates":[1.13332,51.211712],"type":"Point"}
}