{
  "type": "Feature",
  "properties": {
    "addr:full":"2 Baffins Rd Portsmouth Hampshire PO3 6BG",
    "addr:housenumber":"2",
    "addr:postcode":"hampshire po3 6bg",
    "addr:street":"Baffins Rd",
    "iso:country":"GB",
    "sg:address":"2 Baffins Rd",
    "sg:city":"Portsmouth",
    "sg:classifiers":[
        {
            "category":"Food & Beverages",
            "subcategory":"Liquor & Beverages",
            "type":"Retail Goods"
        }
    ],
    "sg:phone":"+44 23 9282 5947",
    "sg:postcode":"PO3 6BG",
    "sg:province":"Hampshire",
    "sg:tags":[
        "beer",
        "spirit",
        "wines"
    ],
    "wof:name":"Drinks Cabin",
    "wof:placetype":"venue"
},
  "geometry": {"coordinates":[-1.063609,50.802776],"type":"Point"}
}