{
  "type": "Feature",
  "properties": {
    "addr:full":"Lower Denford Hungerford Berkshire RG17 0UN",
    "addr:postcode":"rg17 0un",
    "addr:street":"Lower Denford",
    "iso:country":"GB",
    "sg:address":"Lower Denford",
    "sg:city":"Hungerford",
    "sg:classifiers":[
        {
            "category":"Farming",
            "subcategory":"Farm",
            "type":"Manufacturing & Wholesale Goods"
        }
    ],
    "sg:postcode":"RG17 0UN",
    "sg:province":"Berkshire",
    "sg:tags":[
        "hatchery"
    ],
    "wof:name":"The Berkshire Trout Farm Ltd.",
    "wof:placetype":"venue"
},
  "geometry": {"coordinates":[-1.516156,51.413197],"type":"Point"}
}