{
  "type": "Feature",
  "properties": {
    "addr:full":"Halls Dunbar East Lothian EH42 1RN",
    "addr:postcode":"eh42 1rn",
    "iso:country":"GB",
    "sg:address":"Halls",
    "sg:city":"Dunbar",
    "sg:classifiers":[
        {
            "category":"Home & Garden",
            "subcategory":"Garden Supply",
            "type":"Retail Goods"
        },
        {
            "category":"Farming",
            "subcategory":"Farm",
            "type":"Manufacturing & Wholesale Goods"
        }
    ],
    "sg:phone":"+44 1368 850242",
    "sg:postcode":"EH42 1RN",
    "sg:province":"East Lothian",
    "sg:tags":[
        "mixed",
        "bulb",
        "crop",
        "grower"
    ],
    "wof:name":"R G Jeffrey",
    "wof:placetype":"venue"
},
  "geometry": {"coordinates":[-2.5317389965,55.9885902405],"type":"Point"}
}