{
  "type": "Feature",
  "properties": {
    "addr:full":"12 Heathfield Gardens London Greater London W4 4JY",
    "addr:housenumber":"12",
    "addr:postcode":"w4 4jy",
    "addr:street":"Heathfield Gardens",
    "iso:country":"GB",
    "sg:address":"12 Heathfield Gardens",
    "sg:city":"London",
    "sg:classifiers":[
        {
            "category":"Professional",
            "subcategory":"Management & Consulting",
            "type":"Services"
        }
    ],
    "sg:phone":"+44 20 8995 5485",
    "sg:postcode":"W4 4JY",
    "sg:province":"Greater London",
    "sg:tags":[
        "consultant",
        "business"
    ],
    "wof:name":"Alison Hodge Associates",
    "wof:placetype":"venue"
},
  "geometry": {"coordinates":[-0.2687630057,51.4906692505],"type":"Point"}
}