{
  "type": "Feature",
  "properties": {
    "addr:full":"1-11 Harrisons Rise Croydon Surrey CR0 4LL",
    "addr:housenumber":"1-11",
    "addr:postcode":"cr0 4ll",
    "addr:street":"Harrisons Rise",
    "iso:country":"GB",
    "sg:address":"1-11 Harrisons Rise",
    "sg:city":"Croydon",
    "sg:classifiers":[
        {
            "category":"Professional",
            "subcategory":"Engineering",
            "type":"Services"
        }
    ],
    "sg:phone":"+44 20 8688 8497",
    "sg:postcode":"CR0 4LL",
    "sg:province":"Surrey",
    "sg:tags":[
        "contractor",
        "electrical",
        "engineer"
    ],
    "wof:name":"G T Bellamy & Co. Ltd.",
    "wof:placetype":"venue"
},
  "geometry": {"coordinates":[-0.1088740006,51.371799469],"type":"Point"}
}