{
  "type": "Feature",
  "properties": {
    "iso:country":"GB",
    "sg:address":"83 Gladstone Road",
    "sg:city":"Scarborough",
    "sg:classifiers":[
        {
            "category":"Building & Trades",
            "subcategory":"Construction",
            "type":"Services"
        }
    ],
    "sg:phone":"+44 1723 507670",
    "sg:postcode":"YO12 7BJ",
    "sg:province":"North Yorkshire",
    "sg:tags":[
        "supplier",
        "installers",
        "cladding"
    ],
    "wof:name":"R P B (Hunmanby) Ltd.",
    "wof:placetype":"venue"
},
  "geometry": {"coordinates":[-0.412069,54.280231],"type":"Point"}
}