{
  "type": "Feature",
  "properties": {
    "addr:full":"47 Fore Street, Heavitree Exeter Devon EX1 2QN",
    "addr:housenumber":"47",
    "addr:postcode":"ex1 2qn",
    "addr:street":"Fore Street",
    "iso:country":"GB",
    "sg:address":"47 Fore Street, Heavitree",
    "sg:city":"Exeter",
    "sg:classifiers":[
        {
            "category":"Real Estate",
            "subcategory":"Real Estate Agent",
            "type":"Services"
        }
    ],
    "sg:phone":"+44 1392 270105",
    "sg:postcode":"EX1 2QN",
    "sg:province":"Devon",
    "wof:name":"Friends Provident Estate Agency Financia",
    "wof:placetype":"venue"
},
  "geometry": {"coordinates":[-3.505789,50.72155],"type":"Point"}
}