{
  "type": "Feature",
  "properties": {
    "addr:full":"119 Portview Road Bristol City of Bristol BS11 9JE",
    "addr:housenumber":"119",
    "addr:postcode":"bs11 9je",
    "addr:street":"Portview Road",
    "iso:country":"GB",
    "sg:address":"119 Portview Road",
    "sg:city":"Bristol",
    "sg:classifiers":[
        {
            "category":"Shopping",
            "type":"Retail Goods"
        }
    ],
    "sg:phone":"+44 117 914 4478",
    "sg:postcode":"BS11 9JE",
    "sg:province":"City of Bristol",
    "sg:tags":[
        "part",
        "accessory"
    ],
    "wof:name":"Avonmouth Autoparts",
    "wof:placetype":"venue"
},
  "geometry": {"coordinates":[-2.6862640381,51.4925727844],"type":"Point"}
}