{
  "type": "Feature",
  "properties": {
    "iso:country":"GB",
    "sg:address":"4 Cromar Cottages, Tarland",
    "sg:city":"Aboyne",
    "sg:classifiers":[
        {
            "category":"Home & Garden",
            "subcategory":"Hardware",
            "type":"Retail Goods"
        }
    ],
    "sg:phone":"+44 1339 881218",
    "sg:postcode":"AB34 4UA",
    "sg:province":"Aberdeenshire",
    "sg:tags":[
        "equipment",
        "heating"
    ],
    "wof:name":"Deeside Plumbing Services",
    "wof:placetype":"venue"
},
  "geometry": {"coordinates":[-2.862345,57.131561],"type":"Point"}
}