{
  "type": "Feature",
  "properties": {
    "addr:full":"107 Castle Road West Oldbury West Midlands B68 0EL",
    "addr:housenumber":"107",
    "addr:postcode":"b68 0el",
    "addr:street":"Castle Road West Oldbury",
    "iso:country":"GB",
    "sg:address":"107 Castle Road West",
    "sg:city":"Oldbury",
    "sg:classifiers":[
        {
            "category":"Professional",
            "subcategory":"Engineering",
            "type":"Services"
        }
    ],
    "sg:postcode":"B68 0EL",
    "sg:province":"West Midlands",
    "sg:tags":[
        "contractor",
        "electrical",
        "engineer"
    ],
    "wof:name":"M E Electrics",
    "wof:placetype":"venue"
},
  "geometry": {"coordinates":[-1.996942997,52.4687728882],"type":"Point"}
}