{
  "type": "Feature",
  "properties": {
    "addr:full":"The Poplars, Hallcroft Road Retford Nottinghamshire DN22 7RA",
    "addr:postcode":"dn22 7ra",
    "addr:street":"Hallcroft Road",
    "iso:country":"GB",
    "sg:address":"The Poplars, Hallcroft Road",
    "sg:city":"Retford",
    "sg:classifiers":[
        {
            "category":"Building & Trades",
            "subcategory":"Equipment Rental",
            "type":"Services"
        }
    ],
    "sg:phone":"+44 1777 719937",
    "sg:postcode":"DN22 7RA",
    "sg:province":"Nottinghamshire",
    "sg:tags":[
        "hire",
        "centre"
    ],
    "wof:name":"Anglo-American Vending Ltd.",
    "wof:placetype":"venue"
},
  "geometry": {"coordinates":[-0.945728004,53.3251838684],"type":"Point"}
}