{
  "type": "Feature",
  "properties": {
    "iso:country":"GB",
    "sg:address":"Knox Road",
    "sg:city":"Cardiff",
    "sg:classifiers":[
        {
            "category":"Parking",
            "type":"Transportation"
        }
    ],
    "sg:phone":"+44 29 2045 7250",
    "sg:postcode":"CF24 0EA",
    "sg:province":"Cardiff",
    "sg:tags":[
        "car",
        "park"
    ],
    "wof:name":"Apcoa Knox Court Car-Park",
    "wof:placetype":"venue"
},
  "geometry": {"coordinates":[-3.167974,51.481892],"type":"Point"}
}