{
  "type": "Feature",
  "properties": {
    "iso:country":"GB",
    "sg:address":"256 Kingston Road",
    "sg:city":"Teddington",
    "sg:classifiers":[
        {
            "category":"Professional",
            "subcategory":"Management & Consulting",
            "type":"Services"
        }
    ],
    "sg:phone":"+44 20 8943 5577",
    "sg:postcode":"TW11 9JQ",
    "sg:province":"Greater London",
    "sg:tags":[
        "marketing",
        "consultant"
    ],
    "sg:website":"http://www.lindum.co.uk",
    "wof:name":"Lindum Associates",
    "wof:placetype":"venue"
},
  "geometry": {"coordinates":[-0.3172209859,51.4192886353],"type":"Point"}
}