{
  "type": "Feature",
  "properties": {
    "addr:full":"1 Sandy Lane Sevenoaks Kent TN13 3TP",
    "addr:housenumber":"1",
    "addr:postcode":"tn13 3tp",
    "addr:street":"Sandy Lane",
    "iso:country":"GB",
    "sg:address":"1 Sandy Lane",
    "sg:city":"Sevenoaks",
    "sg:classifiers":[
        {
            "category":"Bars & Pubs",
            "type":"Food & Drink"
        }
    ],
    "sg:postcode":"TN13 3TP",
    "sg:province":"Kent",
    "sg:tags":[
        "pubs",
        "inn"
    ],
    "wof:name":"The Man of Kent",
    "wof:placetype":"venue"
},
  "geometry": {"coordinates":[0.1970320046,51.2814102173],"type":"Point"}
}