{
  "type": "Feature",
  "properties": {
    "iso:country":"GB",
    "sg:address":"Merebarn Farm, Milcote Road, Welford On Avon",
    "sg:city":"Stratford-upon-avon",
    "sg:classifiers":[
        {
            "category":"Retail",
            "subcategory":"Auto Repair",
            "type":"Services"
        }
    ],
    "sg:phone":"+44 1789 750455",
    "sg:postcode":"CV37 8AD",
    "sg:province":"Warwickshire",
    "sg:tags":[
        "modification",
        "garage"
    ],
    "wof:name":"Mere Motors",
    "wof:placetype":"venue"
},
  "geometry": {"coordinates":[-1.7339789867,52.1710357666],"type":"Point"}
}