{
  "type": "Feature",
  "properties": {
    "addr:full":"Site Office, Off Burnmill Road Market Harborough Leicestershire LE16 7JG",
    "addr:postcode":"le16 7jg",
    "addr:street":"Off Burnmill Road",
    "iso:country":"GB",
    "sg:address":"Site Office, Off Burnmill Road",
    "sg:city":"Market Harborough",
    "sg:classifiers":[
        {
            "category":"Building & Trades",
            "subcategory":"Construction",
            "type":"Services"
        }
    ],
    "sg:phone":"+44 1858 466162",
    "sg:postcode":"LE16 7JG",
    "sg:province":"Leicestershire",
    "sg:tags":[
        "builder"
    ],
    "wof:name":"David Wilson Builders",
    "wof:placetype":"venue"
},
  "geometry": {"coordinates":[-0.922579,52.479397],"type":"Point"}
}