{
  "type": "Feature",
  "properties": {
    "addr:full":"Rivercourt, Albert Drive, Sheerwater Woking Surrey GU21 5PR",
    "addr:postcode":"gu21 5pr",
    "addr:street":"Albert Drive",
    "iso:country":"GB",
    "sg:address":"Rivercourt, Albert Drive, Sheerwater",
    "sg:city":"Woking",
    "sg:classifiers":[
        {
            "category":"Professional",
            "subcategory":"Computer Services",
            "type":"Services"
        }
    ],
    "sg:phone":"+44 1483 724411",
    "sg:postcode":"GU21 5PR",
    "sg:province":"Surrey",
    "sg:tags":[
        "system",
        "software"
    ],
    "wof:name":"Csi",
    "wof:placetype":"venue"
},
  "geometry": {"coordinates":[-0.5231410265,51.335231781],"type":"Point"}
}