{
  "type": "Feature",
  "properties": {
    "iso:country":"GB",
    "sg:address":"71-79 Chingford Mount Road",
    "sg:city":"London",
    "sg:classifiers":[
        {
            "category":"Autos & Motor Vehicles",
            "subcategory":"Fuel & Gas Station",
            "type":"Retail Goods"
        }
    ],
    "sg:phone":"+44 20 8531 5643",
    "sg:postcode":"E4 8LU",
    "sg:province":"Greater London",
    "sg:tags":[
        "hr",
        "petrol"
    ],
    "wof:name":"Chingford Mount Service Station",
    "wof:placetype":"venue"
},
  "geometry": {"coordinates":[-0.0174979996,51.6152572632],"type":"Point"}
}