{
  "type": "Feature",
  "properties": {
    "addr:full":"52 South Street Bridport Dorset DT6 3NN",
    "addr:housenumber":"52",
    "addr:postcode":"dt6 3nn",
    "addr:street":"South Street",
    "iso:country":"GB",
    "sg:address":"52 South Street",
    "sg:city":"Bridport",
    "sg:classifiers":[
        {
            "category":"Home & Garden",
            "subcategory":"Hardware",
            "type":"Retail Goods"
        }
    ],
    "sg:phone":"+44 1308 422318",
    "sg:postcode":"DT6 3NN",
    "sg:province":"Dorset",
    "sg:tags":[
        "retailer",
        "lighting"
    ],
    "wof:name":"Bridport Lighting Centre",
    "wof:placetype":"venue"
},
  "geometry": {"coordinates":[-2.75832,50.731808],"type":"Point"}
}