{
  "type": "Feature",
  "properties": {
    "iso:country":"GB",
    "sg:address":"77 Allensbank Road",
    "sg:city":"Cardiff",
    "sg:classifiers":[
        {
            "category":"Shopping",
            "subcategory":"Mobile Phones",
            "type":"Retail Goods"
        }
    ],
    "sg:phone":"+44 29 2023 0240",
    "sg:postcode":"CF14 3PP",
    "sg:province":"Cardiff",
    "sg:tags":[
        "supplier"
    ],
    "wof:name":"General Communications UK Ltd",
    "wof:placetype":"venue"
},
  "geometry": {"coordinates":[-3.184068,51.501133],"type":"Point"}
}