{
  "type": "Feature",
  "properties": {
    "iso:country":"GB",
    "sg:address":"Burning Springs, Gorsty Knoll",
    "sg:city":"Coleford",
    "sg:classifiers":[
        {
            "category":"Building & Trades",
            "subcategory":"Construction",
            "type":"Services"
        }
    ],
    "sg:phone":"+44 1594 810300",
    "sg:postcode":"GL16 7LR",
    "sg:province":"Gloucestershire",
    "sg:tags":[
        "builder"
    ],
    "wof:name":"Simon Clark Ltd.",
    "wof:placetype":"venue"
},
  "geometry": {"coordinates":[-2.604089,51.791393],"type":"Point"}
}