{
  "type": "Feature",
  "properties": {
    "iso:country":"GB",
    "sg:address":"639-641 Ormskirk Road",
    "sg:city":"Wigan",
    "sg:classifiers":[
        {
            "category":"Food & Beverages",
            "subcategory":"Bakery",
            "type":"Retail Goods"
        }
    ],
    "sg:phone":"+44 1942 222318",
    "sg:postcode":"WN5 8AG",
    "sg:province":"Lancashire",
    "sg:tags":[
        "baker"
    ],
    "wof:name":"Village Bakery",
    "wof:placetype":"venue"
},
  "geometry": {"coordinates":[-2.6783208847,53.535697937],"type":"Point"}
}