{
  "type": "Feature",
  "properties": {
    "addr:full":"48b Brighton Road, Salfords Redhill Surrey RH1 5BX",
    "addr:housenumber":"48b",
    "addr:postcode":"rh1 5bx",
    "addr:street":"Brighton Road;Redhill",
    "iso:country":"GB",
    "sg:address":"48b Brighton Road, Salfords",
    "sg:city":"Redhill",
    "sg:classifiers":[
        {
            "category":"Professional",
            "subcategory":"Printing & Photocopies",
            "type":"Services"
        }
    ],
    "sg:phone":"+44 1293 820130",
    "sg:postcode":"RH1 5BX",
    "sg:province":"Surrey",
    "sg:tags":[
        "printer"
    ],
    "wof:name":"Graphic Impress Ltd.",
    "wof:placetype":"venue"
},
  "geometry": {"coordinates":[-0.16754,51.203522],"type":"Point"}
}