{
  "type": "Feature",
  "properties": {
    "iso:country":"GB",
    "sg:address":"Lingfield House, Ickornshaw, Cowlingl",
    "sg:city":"Keighley",
    "sg:classifiers":[
        {
            "category":"Utilities",
            "type":"Services"
        }
    ],
    "sg:phone":"+44 1535 636920",
    "sg:postcode":"BD22 0DE",
    "sg:province":"North Yorkshire",
    "sg:tags":[
        "internet"
    ],
    "wof:name":"Netaddress Ltd.",
    "wof:placetype":"venue"
},
  "geometry": {"coordinates":[-2.0528,53.882729],"type":"Point"}
}