{
  "type": "Feature",
  "properties": {
    "iso:country":"GB",
    "sg:address":"33 Hillside Dr",
    "sg:city":"Chesterfield",
    "sg:classifiers":[
        {
            "category":"Taxi",
            "type":"Transportation"
        }
    ],
    "sg:postcode":"S43 3AA",
    "sg:province":"Derbyshire",
    "sg:tags":[
        "mini",
        "cab"
    ],
    "wof:name":"Berrys Private Hire",
    "wof:placetype":"venue"
},
  "geometry": {"coordinates":[-1.322164,53.27494],"type":"Point"}
}