{
  "type": "Feature",
  "properties": {
    "iso:country":"GB",
    "sg:address":"1 Kings Road, Shalford",
    "sg:city":"Guildford",
    "sg:classifiers":[
        {
            "category":"Shopping",
            "subcategory":"News",
            "type":"Retail Goods"
        }
    ],
    "sg:postcode":"GU4 8JU",
    "sg:province":"Surrey",
    "sg:tags":[
        "newsagent"
    ],
    "wof:name":"Green's Newsagents",
    "wof:placetype":"venue"
},
  "geometry": {"coordinates":[-0.5676019788,51.2137107849],"type":"Point"}
}