{
  "type": "Feature",
  "properties": {
    "addr:full":"176 Kingston Rd Portsmouth Hampshire PO2 7LP",
    "addr:housenumber":"176",
    "addr:postcode":"hampshire po2 7lp",
    "addr:street":"Kingston Rd",
    "iso:country":"GB",
    "sg:address":"176 Kingston Rd",
    "sg:city":"Portsmouth",
    "sg:classifiers":[
        {
            "category":"Food & Beverages",
            "subcategory":"Groceries & Convenience Stores",
            "type":"Retail Goods"
        }
    ],
    "sg:postcode":"PO2 7LP",
    "sg:province":"Hampshire",
    "wof:name":"Thacker,Divefh,",
    "wof:placetype":"venue"
},
  "geometry": {"coordinates":[-1.079218,50.811192],"type":"Point"}
}