{
  "type": "Feature",
  "properties": {
    "addr:full":"Flat, 18 Queen Anne Street West End Hampshire W1M 9LB",
    "addr:housenumber":"flat 18",
    "addr:postcode":"w1m 9lb",
    "addr:street":"Queen Anne Street",
    "iso:country":"GB",
    "sg:address":"Flat, 18 Queen Anne Street",
    "sg:city":"West End",
    "sg:classifiers":[
        {
            "category":"Real Estate",
            "subcategory":"Developer",
            "type":"Services"
        }
    ],
    "sg:postcode":"W1M 9LB",
    "sg:province":"Hampshire",
    "sg:tags":[
        "property"
    ],
    "wof:name":"Freshcove Ltd",
    "wof:placetype":"venue"
},
  "geometry": {"coordinates":[-0.146201998,51.5180740356],"type":"Point"}
}