{
  "type": "Feature",
  "properties": {
    "addr:full":"Hilton Industrial Estate, 43 Carlyle Avenue Glasgow Glasgow City G52 4XX",
    "addr:housenumber":"43",
    "addr:postcode":"g52 4xx",
    "addr:street":"Carlyle Avenue",
    "iso:country":"GB",
    "sg:address":"Hilton Industrial Estate, 43 Carlyle Avenue",
    "sg:city":"Glasgow",
    "sg:classifiers":[
        {
            "category":"Freight",
            "type":"Transportation"
        }
    ],
    "sg:phone":"+44 141 883 5445",
    "sg:postcode":"G52 4XX",
    "sg:province":"Glasgow City",
    "sg:tags":[
        "forwarders"
    ],
    "wof:name":"Panalpina World Transport Ltd.",
    "wof:placetype":"venue"
},
  "geometry": {"coordinates":[-4.36879,55.861839],"type":"Point"}
}