{
  "type": "Feature",
  "properties": {
    "addr:full":"26 Oakeshott Avenue London Greater London N6 6NS",
    "addr:housenumber":"26",
    "addr:postcode":"n6 6ns",
    "addr:street":"Oakeshott Avenue",
    "iso:country":"GB",
    "sg:address":"26 Oakeshott Avenue",
    "sg:city":"London",
    "sg:classifiers":[
        {
            "category":"Professional",
            "subcategory":"Management & Consulting",
            "type":"Services"
        }
    ],
    "sg:phone":"+44 20 8341 4241",
    "sg:postcode":"N6 6NS",
    "sg:province":"Greater London",
    "sg:tags":[
        "consultant",
        "business"
    ],
    "wof:name":"Economic Healthcare Associates",
    "wof:placetype":"venue"
},
  "geometry": {"coordinates":[-0.150721997,51.5652542114],"type":"Point"}
}