{
  "type": "Feature",
  "properties": {
    "addr:full":"Northend Business Park, Station Road, Swines Head Boston Lincolnshire PE20 3PW",
    "addr:postcode":"pe20 3pw",
    "addr:street":"Station Road Swines Head",
    "iso:country":"GB",
    "sg:address":"Northend Business Park, Station Road, Swines Head",
    "sg:city":"Boston",
    "sg:classifiers":[
        {
            "category":"Professional",
            "subcategory":"Printing & Photocopies",
            "type":"Services"
        }
    ],
    "sg:phone":"+44 1205 820757",
    "sg:postcode":"PE20 3PW",
    "sg:province":"Lincolnshire",
    "sg:tags":[
        "finishing",
        "tag",
        "computer",
        "label",
        "supply"
    ],
    "wof:name":"Superior Labels Ltd",
    "wof:placetype":"venue"
},
  "geometry": {"coordinates":[-0.17487,52.956329],"type":"Point"}
}