{
  "type": "Feature",
  "properties": {
    "addr:full":"6 Benner Road Industrial Estate, Wardentree Lane, Pinchbeck Spalding Lincolnshire PE11 3TZ",
    "addr:housenumber":"6",
    "addr:postcode":"pe11 3tz",
    "addr:street":"Benner Road Industrial Estate Wardentree Lane",
    "iso:country":"GB",
    "sg:address":"6 Benner Road Industrial Estate, Wardentree Lane, Pinchbeck",
    "sg:city":"Spalding",
    "sg:classifiers":[
        {
            "category":"Home & Garden",
            "subcategory":"Hardware",
            "type":"Retail Goods"
        }
    ],
    "sg:postcode":"PE11 3TZ",
    "sg:province":"Lincolnshire",
    "wof:name":"Kirby & Wells Ltd.",
    "wof:placetype":"venue"
},
  "geometry": {"coordinates":[-0.1405629963,52.8070716858],"type":"Point"}
}