{
  "type": "Feature",
  "properties": {
    "addr:full":"Muir Farm Cumnock East Ayrshire KA18 2RG",
    "addr:postcode":"ka18 2rg",
    "addr:street":"Muir;Cumnock East",
    "iso:country":"GB",
    "sg:address":"Muir Farm",
    "sg:city":"Cumnock",
    "sg:classifiers":[
        {
            "category":"Farming",
            "subcategory":"Livestock Farm",
            "type":"Manufacturing & Wholesale Goods"
        },
        {
            "category":"Farming",
            "subcategory":"Farm",
            "type":"Manufacturing & Wholesale Goods"
        }
    ],
    "sg:phone":"+44 1290 700249",
    "sg:postcode":"KA18 2RG",
    "sg:province":"East Ayrshire",
    "sg:tags":[
        "mixed",
        "others"
    ],
    "wof:name":"HUGH W C POLLOCK",
    "wof:placetype":"venue"
},
  "geometry": {"coordinates":[-4.348861,55.473122],"type":"Point"}
}