{
  "type": "Feature",
  "properties": {
    "addr:full":"Windmill Hill Street Motherwell North Lanarkshire ML1 1ZU",
    "addr:postcode":"ml1 1zu",
    "addr:street":"Windmill Hill Street",
    "iso:country":"GB",
    "sg:address":"Windmill Hill Street",
    "sg:city":"Motherwell",
    "sg:classifiers":[
        {
            "category":"Education",
            "subcategory":"Special Training",
            "type":"Public Place"
        }
    ],
    "sg:phone":"+44 1698 276440",
    "sg:postcode":"ML1 1ZU",
    "sg:province":"North Lanarkshire",
    "sg:tags":[
        "product",
        "centre"
    ],
    "wof:name":"Scottish National Council of Y M C A's",
    "wof:placetype":"venue"
},
  "geometry": {"coordinates":[-3.9840381145,55.785785675],"type":"Point"}
}