{
  "type": "Feature",
  "properties": {
    "addr:full":"High Fernley Service Station, Woodside Rd Bradford West Yorkshire BD12 8AP",
    "addr:postcode":"bd12 8ap",
    "addr:street":"Woodside Rd",
    "iso:country":"GB",
    "sg:address":"High Fernley Service Station, Woodside Rd",
    "sg:city":"Bradford",
    "sg:classifiers":[
        {
            "category":"Autos & Motor Vehicles",
            "subcategory":"Automobile Sales",
            "type":"Retail Goods"
        }
    ],
    "sg:phone":"+44 1274 693027",
    "sg:postcode":"BD12 8AP",
    "sg:province":"West Yorkshire",
    "sg:tags":[
        "car"
    ],
    "wof:name":"Woodside Motor Co",
    "wof:placetype":"venue"
},
  "geometry": {"coordinates":[-1.758306,53.795738],"type":"Point"}
}