{
  "type": "Feature",
  "properties": {
    "addr:full":"20 Henley Rd Upper Edmonton Greater London N18 1NT",
    "addr:housenumber":"20",
    "addr:postcode":"n18 1nt",
    "addr:street":"Henley Rd",
    "iso:country":"GB",
    "sg:address":"20 Henley Rd",
    "sg:city":"Upper Edmonton",
    "sg:classifiers":[
        {
            "category":"Building & Trades",
            "subcategory":"Plumbing",
            "type":"Services"
        }
    ],
    "sg:phone":"+44 20 8803 1989",
    "sg:postcode":"N18 1NT",
    "sg:province":"Greater London",
    "sg:tags":[
        "central",
        "heating"
    ],
    "wof:name":"ABS Services",
    "wof:placetype":"venue"
},
  "geometry": {"coordinates":[-0.07668,51.618866],"type":"Point"}
}