{
  "type": "Feature",
  "properties": {
    "addr:full":"Chuch Rd Bus Centre Sittingbourne Kent ME10 3RS",
    "addr:postcode":"me10 3rs",
    "addr:street":"Chuch Rd Bus Centre Sittingbourne",
    "iso:country":"GB",
    "sg:address":"Chuch Rd Bus Centre",
    "sg:city":"Sittingbourne",
    "sg:classifiers":[
        {
            "category":"Home & Garden",
            "subcategory":"Household Appliances",
            "type":"Retail Goods"
        }
    ],
    "sg:phone":"+44 1795 474080",
    "sg:postcode":"ME10 3RS",
    "sg:province":"Kent",
    "sg:tags":[
        "electrical"
    ],
    "wof:name":"Wash-Vac Services",
    "wof:placetype":"venue"
},
  "geometry": {"coordinates":[0.752885,51.340225],"type":"Point"}
}