{
  "type": "Feature",
  "properties": {
    "iso:country":"GB",
    "sg:address":"3 The Lawns",
    "sg:city":"Hinckley",
    "sg:classifiers":[
        {
            "category":"Home & Garden",
            "subcategory":"Hardware",
            "type":"Retail Goods"
        }
    ],
    "sg:phone":"+44 1455 636090",
    "sg:postcode":"LE10 1DY",
    "sg:province":"Leicestershire",
    "sg:tags":[
        "lawnmowers",
        "machinery"
    ],
    "wof:name":"Clarendon Lawnmowers",
    "wof:placetype":"venue"
},
  "geometry": {"coordinates":[-1.366527,52.54155],"type":"Point"}
}