{
  "type": "Feature",
  "properties": {
    "iso:country":"GB",
    "sg:address":"9 Concorde Drive",
    "sg:city":"Hemel Hempstead",
    "sg:classifiers":[
        {
            "category":"Organizations",
            "subcategory":"Non-profit Organization",
            "type":"Services"
        }
    ],
    "sg:phone":"+44 1442 254996",
    "sg:postcode":"HP2 4AW",
    "sg:province":"Hertfordshire",
    "sg:tags":[
        "organisation",
        "voluntary",
        "charity"
    ],
    "wof:name":"Alzheimers Disease Society",
    "wof:placetype":"venue"
},
  "geometry": {"coordinates":[-0.466799,51.754627],"type":"Point"}
}