{
  "type": "Feature",
  "properties": {
    "addr:full":"Greyhound Trading Park, Greyhound Way Southend-on-sea Essex SS2 5PY",
    "addr:postcode":"ss2 5py",
    "addr:street":"Greyhound Way",
    "iso:country":"GB",
    "sg:address":"Greyhound Trading Park, Greyhound Way",
    "sg:city":"Southend-on-sea",
    "sg:classifiers":[
        {
            "category":"Shopping",
            "subcategory":"Clothing, Apparel, & Fashions",
            "type":"Retail Goods"
        }
    ],
    "sg:phone":"+44 1702 466248",
    "sg:postcode":"SS2 5PY",
    "sg:province":"Essex",
    "sg:tags":[
        "shop"
    ],
    "wof:name":"Matalan Retail Ltd.",
    "wof:placetype":"venue"
},
  "geometry": {"coordinates":[0.71599,51.544701],"type":"Point"}
}