{
  "type": "Feature",
  "properties": {
    "addr:full":"139 Bellegrove Road Welling Kent DA16 3QS",
    "addr:housenumber":"139",
    "addr:postcode":"da16 3qs",
    "addr:street":"Bellegrove Road",
    "iso:country":"GB",
    "sg:address":"139 Bellegrove Road",
    "sg:city":"Welling",
    "sg:classifiers":[
        {
            "category":"Fast Food",
            "type":"Food & Drink"
        }
    ],
    "sg:phone":"+44 20 8298 9500",
    "sg:postcode":"DA16 3QS",
    "sg:province":"Kent",
    "sg:tags":[
        "away",
        "take"
    ],
    "wof:name":"Ye Kebab",
    "wof:placetype":"venue"
},
  "geometry": {"coordinates":[0.1005199999,51.4634552002],"type":"Point"}
}