{
  "type": "Feature",
  "properties": {
    "addr:full":"52 Shelley Road, Swinton Manchester Greater Manchester M27 0PB",
    "addr:housenumber":"52",
    "addr:postcode":"m27 0pb",
    "addr:street":"Shelley Road",
    "iso:country":"GB",
    "sg:address":"52 Shelley Road, Swinton",
    "sg:city":"Manchester",
    "sg:classifiers":[
        {
            "category":"Retail",
            "subcategory":"Driving School",
            "type":"Services"
        }
    ],
    "sg:phone":"+44 161 793 6172",
    "sg:postcode":"M27 0PB",
    "sg:province":"Greater Manchester",
    "wof:name":"Timothy Lavelle",
    "wof:placetype":"venue"
},
  "geometry": {"coordinates":[-2.348599,53.5131],"type":"Point"}
}