{
  "type": "Feature",
  "properties": {
    "addr:full":"63 The Arches, New Covent Garden Market London Greater London SW8 5PP",
    "addr:housenumber":"63;arches;covent garden",
    "addr:postcode":"sw8 5pp",
    "addr:street":"The;New;Market",
    "iso:country":"GB",
    "sg:address":"63 The Arches, New Covent Garden Market",
    "sg:city":"London",
    "sg:classifiers":[
        {
            "category":"Retail",
            "subcategory":"Auto Repair",
            "type":"Services"
        }
    ],
    "sg:phone":"+44 20 7720 3778",
    "sg:postcode":"SW8 5PP",
    "sg:province":"Greater London",
    "sg:tags":[
        "modification",
        "garage",
        "related"
    ],
    "sg:website":"http://www.ascottengineering.co.uk",
    "wof:name":"Ascot Engineering",
    "wof:placetype":"venue"
},
  "geometry": {"coordinates":[-0.13191,51.480331],"type":"Point"}
}