{
  "type": "Feature",
  "properties": {
    "addr:full":"9 Park End, Bodicote Banbury Oxfordshire OX15 4DF",
    "addr:housenumber":"9",
    "addr:postcode":"ox15 4df",
    "addr:street":"Park End",
    "iso:country":"GB",
    "sg:address":"9 Park End, Bodicote",
    "sg:city":"Banbury",
    "sg:classifiers":[
        {
            "category":"Home & Garden",
            "subcategory":"Household Appliances",
            "type":"Retail Goods"
        },
        {
            "category":"Retail",
            "subcategory":"Repair Shop",
            "type":"Services"
        }
    ],
    "sg:phone":"+44 1295 276896",
    "sg:postcode":"OX15 4DF",
    "sg:province":"Oxfordshire",
    "sg:tags":[
        "refrigerator",
        "electrical",
        "servicing",
        "freezer"
    ],
    "wof:name":"Kestrel Warranty Services",
    "wof:placetype":"venue"
},
  "geometry": {"coordinates":[-1.326035,52.039719],"type":"Point"}
}