{
  "type": "Feature",
  "properties": {
    "addr:full":"93 Oldham Road Rochdale Lancashire OL16 5QR",
    "addr:housenumber":"93",
    "addr:postcode":"ol16 5qr",
    "addr:street":"Oldham Road",
    "iso:country":"GB",
    "sg:address":"93 Oldham Road",
    "sg:city":"Rochdale",
    "sg:classifiers":[
        {
            "category":"Deli",
            "type":"Food & Drink"
        }
    ],
    "sg:phone":"+44 1706 632889",
    "sg:postcode":"OL16 5QR",
    "sg:province":"Lancashire",
    "sg:tags":[
        "delivery",
        "sandwich"
    ],
    "wof:name":"The Sandwich Shop",
    "wof:placetype":"venue"
},
  "geometry": {"coordinates":[-2.150805,53.612431],"type":"Point"}
}