{
  "type": "Feature",
  "properties": {
    "addr:full":"10 Angel Crescent Bridgwater Somerset TA6 3EW",
    "addr:housenumber":"10",
    "addr:postcode":"ta6 3ew",
    "addr:street":"Angel Crescent",
    "iso:country":"GB",
    "sg:address":"10 Angel Crescent",
    "sg:city":"Bridgwater",
    "sg:classifiers":[
        {
            "category":"Professional",
            "subcategory":"Engineering",
            "type":"Services"
        }
    ],
    "sg:postcode":"TA6 3EW",
    "sg:province":"Somerset",
    "sg:tags":[
        "design",
        "engineer"
    ],
    "wof:name":"Dan Alsop",
    "wof:placetype":"venue"
},
  "geometry": {"coordinates":[-3.00567,51.129135],"type":"Point"}
}