{
  "type": "Feature",
  "properties": {
    "addr:full":"Park House, 18 Park St Leamington Spa Warwickshire CV32 4QN",
    "addr:housenumber":"18",
    "addr:postcode":"cv32 4qn",
    "addr:street":"Park St",
    "iso:country":"GB",
    "sg:address":"Park House, 18 Park St",
    "sg:city":"Leamington Spa",
    "sg:classifiers":[
        {
            "category":"Professional",
            "subcategory":"Employment Agencies",
            "type":"Services"
        }
    ],
    "sg:phone":"+44 1926 335644",
    "sg:postcode":"CV32 4QN",
    "sg:province":"Warwickshire",
    "sg:tags":[
        "consultant"
    ],
    "wof:name":"Nigel Lynn Associates",
    "wof:placetype":"venue"
},
  "geometry": {"coordinates":[-1.533763051,52.2910957336],"type":"Point"}
}