{
  "type": "Feature",
  "properties": {
    "addr:full":"Worth Farm, Hele Exeter Devon EX5 4PS",
    "addr:postcode":"ex5 4ps",
    "addr:street":"Worth;Hele",
    "iso:country":"GB",
    "sg:address":"Worth Farm, Hele",
    "sg:city":"Exeter",
    "sg:classifiers":[
        {
            "category":"Farming",
            "subcategory":"Livestock Farm",
            "type":"Manufacturing & Wholesale Goods"
        },
        {
            "category":"Farming",
            "subcategory":"Farm",
            "type":"Manufacturing & Wholesale Goods"
        }
    ],
    "sg:phone":"+44 1392 881206",
    "sg:postcode":"EX5 4PS",
    "sg:province":"Devon",
    "sg:tags":[
        "mixed",
        "others"
    ],
    "wof:name":"R J WEBBER",
    "wof:placetype":"venue"
},
  "geometry": {"coordinates":[-3.430258,50.814026],"type":"Point"}
}