{
  "type": "Feature",
  "properties": {
    "iso:country":"GB",
    "sg:address":"14 High Street",
    "sg:city":"Downham Market",
    "sg:classifiers":[
        {
            "category":"Shopping",
            "subcategory":"Gifts & Souvenirs",
            "type":"Retail Goods"
        }
    ],
    "sg:phone":"+44 1366 382198",
    "sg:postcode":"PE38 9DB",
    "sg:province":"Cambridgeshire",
    "sg:tags":[
        "poster",
        "card"
    ],
    "wof:name":"Mackies",
    "wof:placetype":"venue"
},
  "geometry": {"coordinates":[0.377586,52.602581],"type":"Point"}
}