{
  "type": "Feature",
  "properties": {
    "addr:full":"The Royal Corner Crook Durham DL15 9UA",
    "addr:postcode":"dl15 9ua",
    "iso:country":"GB",
    "sg:address":"The Royal Corner",
    "sg:city":"Crook",
    "sg:classifiers":[
        {
            "category":"Food & Beverages",
            "subcategory":"Bakery",
            "type":"Retail Goods"
        }
    ],
    "sg:phone":"+44 1388 766160",
    "sg:postcode":"DL15 9UA",
    "sg:province":"Durham",
    "sg:tags":[
        "baker"
    ],
    "wof:name":"Greggs of Gosforth",
    "wof:placetype":"venue"
},
  "geometry": {"coordinates":[-1.748794,54.714363],"type":"Point"}
}