{
  "type": "Feature",
  "properties": {
    "iso:country":"GB",
    "sg:address":"Hammersmith Grove",
    "sg:city":"London",
    "sg:classifiers":[
        {
            "category":"Parking",
            "type":"Transportation"
        }
    ],
    "sg:phone":"+44 20 8563 7847",
    "sg:postcode":"W6 7EJ",
    "sg:province":"Greater London",
    "sg:tags":[
        "car",
        "garaging",
        "park"
    ],
    "wof:name":"National Car Parks Ltd.",
    "wof:placetype":"venue"
},
  "geometry": {"coordinates":[-0.2241210043,51.4932556152],"type":"Point"}
}