{
  "type": "Feature",
  "properties": {
    "addr:full":"Dyfed Avenue Swansea Neath Port Talbot SA1 6NF",
    "addr:postcode":"sa1 6nf",
    "addr:street":"Dyfed Avenue",
    "iso:country":"GB",
    "sg:address":"Dyfed Avenue",
    "sg:city":"Swansea",
    "sg:classifiers":[
        {
            "category":"Taxi",
            "type":"Transportation"
        }
    ],
    "sg:phone":"+44 1792 545454",
    "sg:postcode":"SA1 6NF",
    "sg:province":"Neath Port Talbot",
    "sg:tags":[
        "mini",
        "cab"
    ],
    "wof:name":"Data Cabs",
    "wof:placetype":"venue"
},
  "geometry": {"coordinates":[-3.9649488926,51.6252708435],"type":"Point"}
}