{
  "type": "Feature",
  "properties": {
    "iso:country":"GB",
    "sg:address":"63 Staddlestones, Midsomer Norton",
    "sg:city":"Bath",
    "sg:classifiers":[
        {
            "category":"Building & Trades",
            "subcategory":"Construction",
            "type":"Services"
        },
        {
            "category":"Real Estate",
            "subcategory":"Architect",
            "type":"Services"
        }
    ],
    "sg:phone":"+44 1985 847405",
    "sg:postcode":"BA3 2PX",
    "sg:province":"Somerset",
    "sg:tags":[
        "builder"
    ],
    "wof:name":"J S P Consultants",
    "wof:placetype":"venue"
},
  "geometry": {"coordinates":[-2.492149,51.278175],"type":"Point"}
}