{
  "type": "Feature",
  "properties": {
    "iso:country":"GB",
    "sg:address":"107 Braemar Avenue",
    "sg:city":"London",
    "sg:classifiers":[
        {
            "category":"Building & Trades",
            "subcategory":"Construction",
            "type":"Services"
        }
    ],
    "sg:phone":"+44 20 8838 2333",
    "sg:postcode":"NW10 0DT",
    "sg:province":"Greater London",
    "sg:tags":[
        "joinery",
        "joiner",
        "carpenter",
        "carpentry"
    ],
    "wof:name":"Ques Construction",
    "wof:placetype":"venue"
},
  "geometry": {"coordinates":[-0.256613,51.565166],"type":"Point"}
}