{
  "type": "Feature",
  "properties": {
    "addr:full":"Po Box 6, Ravenshead Nottingham Nottinghamshire NG15 9HT",
    "addr:housenumber":"po;6",
    "addr:postcode":"ng15 9ht",
    "addr:street":"Box",
    "iso:country":"GB",
    "sg:address":"Po Box 6, Ravenshead",
    "sg:city":"Nottingham",
    "sg:classifiers":[
        {
            "category":"Shopping",
            "subcategory":"Hobbies, Toys, & Games",
            "type":"Retail Goods"
        }
    ],
    "sg:phone":"+44 1623 797100",
    "sg:postcode":"NG15 9HT",
    "sg:province":"Nottinghamshire",
    "sg:tags":[
        "stamp"
    ],
    "wof:name":"Ark Stamps",
    "wof:placetype":"venue"
},
  "geometry": {"coordinates":[-1.165705,53.085636],"type":"Point"}
}