{
  "type": "Feature",
  "properties": {
    "iso:country":"GB",
    "sg:address":"Eaton Chambers, 95 Victoria Road",
    "sg:city":"Horley",
    "sg:classifiers":[
        {
            "category":"Professional",
            "subcategory":"Lawyer & Legal Services",
            "type":"Services"
        }
    ],
    "sg:phone":"+44 1293 782425",
    "sg:postcode":"RH6 7QH",
    "sg:province":"Surrey",
    "sg:tags":[
        "solicitor"
    ],
    "wof:name":"Ross & Son",
    "wof:placetype":"venue"
},
  "geometry": {"coordinates":[-0.1692889929,51.175365448],"type":"Point"}
}