{
  "type": "Feature",
  "properties": {
    "addr:full":"2a Leicester Road Hinckley Leicestershire LE10 1LS",
    "addr:housenumber":"2a",
    "addr:postcode":"le10 1ls",
    "addr:street":"Leicester Road",
    "iso:country":"GB",
    "sg:address":"2a Leicester Road",
    "sg:city":"Hinckley",
    "sg:classifiers":[
        {
            "category":"Autos & Motor Vehicles",
            "subcategory":"Fuel & Gas Station",
            "type":"Retail Goods"
        }
    ],
    "sg:phone":"+44 1455 615340",
    "sg:postcode":"LE10 1LS",
    "sg:province":"Leicestershire",
    "sg:tags":[
        "petrol",
        "filling"
    ],
    "wof:name":"Leicester Road Service Station",
    "wof:placetype":"venue"
},
  "geometry": {"coordinates":[-1.3675630093,52.5442581177],"type":"Point"}
}