{
  "type": "Feature",
  "properties": {
    "addr:full":"72 Irwell Road Warrington Cheshire WA4 6BB",
    "addr:housenumber":"72",
    "addr:postcode":"wa4 6bb",
    "addr:street":"Irwell Road",
    "iso:country":"GB",
    "sg:address":"72 Irwell Road",
    "sg:city":"Warrington",
    "sg:classifiers":[
        {
            "category":"Professional",
            "subcategory":"Engineering",
            "type":"Services"
        }
    ],
    "sg:postcode":"WA4 6BB",
    "sg:province":"Cheshire",
    "sg:tags":[
        "gas",
        "engineer"
    ],
    "wof:name":"G W Gas Services",
    "wof:placetype":"venue"
},
  "geometry": {"coordinates":[-2.591293,53.376637],"type":"Point"}
}