{
  "type": "Feature",
  "properties": {
    "iso:country":"GB",
    "sg:address":"45 North Road",
    "sg:city":"Boldon Colliery",
    "sg:classifiers":[
        {
            "category":"Home & Garden",
            "subcategory":"Hardware",
            "type":"Retail Goods"
        }
    ],
    "sg:phone":"+44 191 536 7127",
    "sg:postcode":"NE35 9AX",
    "sg:province":"Tyne and Wear",
    "sg:tags":[
        "merchant",
        "ironmonger"
    ],
    "wof:name":"Joseph's Hardware",
    "wof:placetype":"venue"
},
  "geometry": {"coordinates":[-1.4600180387,54.9473686218],"type":"Point"}
}