{
  "type": "Feature",
  "properties": {
    "addr:full":"4 Meadow Parade, Rottingdean Brighton East Sussex BN2 7FA",
    "addr:housenumber":"4",
    "addr:postcode":"bn2 7fa",
    "addr:street":"Meadow Parade",
    "iso:country":"GB",
    "sg:address":"4 Meadow Parade, Rottingdean",
    "sg:city":"Brighton",
    "sg:classifiers":[
        {
            "category":"Personal",
            "subcategory":"Beauty Salon",
            "type":"Services"
        }
    ],
    "sg:phone":"+44 1273 302043",
    "sg:postcode":"BN2 7FA",
    "sg:province":"East Sussex",
    "sg:tags":[
        "unisex",
        "hairdresser"
    ],
    "wof:name":"The Styling Shop",
    "wof:placetype":"venue"
},
  "geometry": {"coordinates":[-0.0632949993,50.811882019],"type":"Point"}
}