{
  "type": "Feature",
  "properties": {
    "iso:country":"GB",
    "sg:address":"Sherfield English",
    "sg:city":"Romsey",
    "sg:classifiers":[
        {
            "category":"Shopping",
            "type":"Retail Goods"
        }
    ],
    "sg:phone":"+44 1794 884456",
    "sg:postcode":"SO51 6FT",
    "sg:province":"Hampshire",
    "sg:tags":[
        "merchant"
    ],
    "wof:name":"Farm & General Supplies",
    "wof:placetype":"venue"
},
  "geometry": {"coordinates":[-1.6073,51.009609],"type":"Point"}
}