{
  "type": "Feature",
  "properties": {
    "addr:full":"7 High Road, Byfleet Weybridge Surrey KT14 7QH",
    "addr:housenumber":"7",
    "addr:postcode":"kt14 7qh",
    "addr:street":"High Road",
    "iso:country":"GB",
    "sg:address":"7 High Road, Byfleet",
    "sg:city":"Weybridge",
    "sg:classifiers":[
        {
            "category":"Autos & Motor Vehicles",
            "subcategory":"Automobile Sales",
            "type":"Retail Goods"
        }
    ],
    "sg:phone":"+44 1932 340268",
    "sg:postcode":"KT14 7QH",
    "sg:province":"Surrey",
    "sg:tags":[
        "car"
    ],
    "wof:name":"Byfleet Classic Cars",
    "wof:placetype":"venue"
},
  "geometry": {"coordinates":[-0.4787180126,51.3394889832],"type":"Point"}
}