{
  "type": "Feature",
  "properties": {
    "iso:country":"GB",
    "sg:address":"28 Kimberley Rd",
    "sg:city":"Leicester",
    "sg:classifiers":[
        {
            "category":"Building & Trades",
            "subcategory":"Cleaning & Sanitation",
            "type":"Services"
        }
    ],
    "sg:phone":"+44 116 273 7553",
    "sg:postcode":"LE2 1LF",
    "sg:province":"Leicestershire",
    "sg:tags":[
        "cleaner",
        "window"
    ],
    "wof:name":"Jaygar Group",
    "wof:placetype":"venue"
},
  "geometry": {"coordinates":[-1.1122909784,52.6247787476],"type":"Point"}
}