{
  "type": "Feature",
  "properties": {
    "iso:country":"GB",
    "sg:address":"1b Almoners Lane",
    "sg:city":"Peterborough",
    "sg:classifiers":[
        {
            "category":"Home & Garden",
            "subcategory":"Home Furnishings",
            "type":"Retail Goods"
        },
        {
            "category":"Home & Garden",
            "subcategory":"Building Materials",
            "type":"Retail Goods"
        }
    ],
    "sg:phone":"+44 1733 561991",
    "sg:postcode":"PE3 9EH",
    "sg:province":"Cambridgeshire",
    "sg:tags":[
        "installers",
        "planner",
        "kitchen",
        "furnishers"
    ],
    "wof:name":"Tebbutt Bros Kitchen Furnishers Ltd",
    "wof:placetype":"venue"
},
  "geometry": {"coordinates":[-0.256382,52.579308],"type":"Point"}
}