{
  "type": "Feature",
  "properties": {
    "addr:full":"129 Northern Av Sheffield South Yorkshire S2 2EH",
    "addr:housenumber":"129",
    "addr:postcode":"s2 2eh",
    "addr:street":"Northern Av",
    "iso:country":"GB",
    "sg:address":"129 Northern Av",
    "sg:city":"Sheffield",
    "sg:classifiers":[
        {
            "category":"Food & Beverages",
            "subcategory":"Fruits & Vegetables",
            "type":"Retail Goods"
        }
    ],
    "sg:phone":"+44 114 249 1193",
    "sg:postcode":"S2 2EH",
    "sg:province":"South Yorkshire",
    "sg:tags":[
        "greengrocer"
    ],
    "wof:name":"Lacey Carrotts",
    "wof:placetype":"venue"
},
  "geometry": {"coordinates":[-1.437715,53.360332],"type":"Point"}
}