{
  "type": "Feature",
  "properties": {
    "addr:full":"21-23 Morden Hill Lewisham Greater London SE13 7NN",
    "addr:housenumber":"21-23",
    "addr:postcode":"se13 7nn",
    "addr:street":"Morden Hill",
    "iso:country":"GB",
    "sg:address":"21-23 Morden Hill",
    "sg:city":"Lewisham",
    "sg:classifiers":[
        {
            "category":"Health Services",
            "subcategory":"Clinic",
            "type":"Services"
        }
    ],
    "sg:phone":"+44 20 8469 2880",
    "sg:postcode":"SE13 7NN",
    "sg:province":"Greater London",
    "sg:tags":[
        "nh"
    ],
    "wof:name":"Morden Hill Surgery",
    "wof:placetype":"venue"
},
  "geometry": {"coordinates":[-0.015799,51.471191],"type":"Point"}
}