{
  "type": "Feature",
  "properties": {
    "iso:country":"GB",
    "sg:address":"58 Union Street",
    "sg:city":"Torquay",
    "sg:classifiers":[
        {
            "category":"Shopping",
            "subcategory":"Shoes",
            "type":"Retail Goods"
        }
    ],
    "sg:phone":"+44 1803 298759",
    "sg:postcode":"TQ2 5PS",
    "sg:province":"Devon",
    "sg:tags":[
        "shop"
    ],
    "wof:name":"Stylo Barratt Shoes Ltd.",
    "wof:placetype":"venue"
},
  "geometry": {"coordinates":[-3.529669,50.466515],"type":"Point"}
}