{
  "type": "Feature",
  "properties": {
    "addr:full":"70 Forrester Road Edinburgh City of Edinburgh EH12 8AG",
    "addr:housenumber":"70",
    "addr:postcode":"eh12 8ag",
    "addr:street":"Forrester Road",
    "iso:country":"GB",
    "sg:address":"70 Forrester Road",
    "sg:city":"Edinburgh",
    "sg:classifiers":[
        {
            "category":"Retail",
            "subcategory":"Driving School",
            "type":"Services"
        }
    ],
    "sg:phone":"+44 131 334 6973",
    "sg:postcode":"EH12 8AG",
    "sg:province":"City of Edinburgh",
    "wof:name":"CURRIE SCHOOL OF MOTORING",
    "wof:placetype":"venue"
},
  "geometry": {"coordinates":[-3.2877159119,55.9458427429],"type":"Point"}
}