{
  "type": "Feature",
  "properties": {
    "iso:country":"GB",
    "sg:address":"10 Kyveilog Street, Pontcanna",
    "sg:city":"Cardiff",
    "sg:classifiers":[
        {
            "category":"Sports & Exercise",
            "subcategory":"Bowling",
            "type":"Entertainment"
        }
    ],
    "sg:phone":"+44 29 2023 6879",
    "sg:postcode":"CF11 9JA",
    "sg:province":"Cardiff",
    "sg:tags":[
        "photography"
    ],
    "wof:name":"Ffotograff Ltd.",
    "wof:placetype":"venue"
},
  "geometry": {"coordinates":[-3.196748,51.487652],"type":"Point"}
}