{
  "type": "Feature",
  "properties": {
    "addr:full":"Priestlands County Secondary School, North St Lymington Hampshire SO41 8FZ",
    "addr:postcode":"so41 8fz",
    "addr:street":"North St",
    "iso:country":"GB",
    "sg:address":"Priestlands County Secondary School, North St",
    "sg:city":"Lymington",
    "sg:classifiers":[
        {
            "category":"Education",
            "subcategory":"Preschool",
            "type":"Public Place"
        }
    ],
    "sg:phone":"+44 1590 676577",
    "sg:postcode":"SO41 8FZ",
    "sg:province":"Hampshire",
    "sg:tags":[
        "pre-school",
        "playgroups"
    ],
    "wof:name":"Little Peoples Pre-School",
    "wof:placetype":"venue"
},
  "geometry": {"coordinates":[-1.538911,50.758938],"type":"Point"}
}