{
  "type": "Feature",
  "properties": {
    "addr:full":"Blackburn Bathgate North Lanarkshire EH47 8AA",
    "addr:postcode":"eh47 8aa",
    "addr:street":"Bathgate",
    "iso:country":"GB",
    "sg:address":"Blackburn",
    "sg:city":"Bathgate",
    "sg:classifiers":[
        {
            "category":"Farming",
            "subcategory":"Farm",
            "type":"Manufacturing & Wholesale Goods"
        }
    ],
    "sg:postcode":"EH47 8AA",
    "sg:province":"North Lanarkshire",
    "sg:tags":[
        "mixed",
        "crop"
    ],
    "wof:name":"James Barrie",
    "wof:placetype":"venue"
},
  "geometry": {"coordinates":[-3.6501500607,55.8555107117],"type":"Point"}
}