{
  "type": "Feature",
  "properties": {
    "addr:full":"97 Foxhole Road Paignton Devon TQ3 3SU",
    "addr:housenumber":"97",
    "addr:postcode":"tq3 3su",
    "addr:street":"Foxhole Road",
    "iso:country":"GB",
    "sg:address":"97 Foxhole Road",
    "sg:city":"Paignton",
    "sg:classifiers":[
        {
            "category":"Food & Beverages",
            "subcategory":"Fruits & Vegetables",
            "type":"Retail Goods"
        }
    ],
    "sg:postcode":"TQ3 3SU",
    "sg:province":"Devon",
    "sg:tags":[
        "greengrocer"
    ],
    "wof:name":"The Orange Box",
    "wof:placetype":"venue"
},
  "geometry": {"coordinates":[-3.584713,50.439545],"type":"Point"}
}