{
  "type": "Feature",
  "properties": {
    "addr:full":"305 Old Road Clacton-on-sea Essex CO15 3NT",
    "addr:housenumber":"305",
    "addr:postcode":"co15 3nt",
    "addr:street":"Old Road",
    "iso:country":"GB",
    "sg:address":"305 Old Road",
    "sg:city":"Clacton-on-sea",
    "sg:classifiers":[
        {
            "category":"Manufacturing",
            "subcategory":"Building Materials",
            "type":"Manufacturing & Wholesale Goods"
        }
    ],
    "sg:phone":"+44 1255 475006",
    "sg:postcode":"CO15 3NT",
    "sg:province":"Essex",
    "sg:tags":[
        "concrete",
        "product"
    ],
    "wof:name":"M A Concrete Products",
    "wof:placetype":"venue"
},
  "geometry": {"coordinates":[1.15184,51.800022],"type":"Point"}
}