{
  "type": "Feature",
  "properties": {
    "addr:full":"10 Hill Street Dingwall Highland IV15 9JP",
    "addr:housenumber":"10",
    "addr:postcode":"iv15 9jp",
    "addr:street":"Hill Street",
    "iso:country":"GB",
    "sg:address":"10 Hill Street",
    "sg:city":"Dingwall",
    "sg:classifiers":[
        {
            "category":"Professional",
            "subcategory":"Art Services",
            "type":"Services"
        }
    ],
    "sg:phone":"+44 1349 863054",
    "sg:postcode":"IV15 9JP",
    "sg:province":"Highland",
    "sg:tags":[
        "decorating",
        "painting"
    ],
    "wof:name":"Decor",
    "wof:placetype":"venue"
},
  "geometry": {"coordinates":[-4.4262681007,57.5944824219],"type":"Point"}
}