{
  "type": "Feature",
  "properties": {
    "addr:full":"172 London Rd Reading Berkshire RG1 3PA",
    "addr:housenumber":"172",
    "addr:postcode":"rg1 3pa",
    "addr:street":"London Rd",
    "iso:country":"GB",
    "sg:address":"172 London Rd",
    "sg:city":"Reading",
    "sg:classifiers":[
        {
            "category":"Health Services",
            "subcategory":"Doctor",
            "type":"Services"
        }
    ],
    "sg:phone":"+44 118 926 4992",
    "sg:postcode":"RG1 3PA",
    "sg:province":"Berkshire",
    "sg:tags":[
        "practitioners"
    ],
    "wof:name":"Patel, S M",
    "wof:placetype":"venue"
},
  "geometry": {"coordinates":[-0.94354,51.454247],"type":"Point"}
}