{
  "type": "Feature",
  "properties": {
    "iso:country":"GB",
    "sg:address":"588 Bury Road",
    "sg:city":"Bolton",
    "sg:classifiers":[
        {
            "category":"Autos & Motor Vehicles",
            "subcategory":"Auto Supplies",
            "type":"Retail Goods"
        }
    ],
    "sg:phone":"+44 1204 394555",
    "sg:postcode":"BL2 6HZ",
    "sg:province":"Lancashire",
    "sg:tags":[
        "component"
    ],
    "wof:name":"Morgan Bros",
    "wof:placetype":"venue"
},
  "geometry": {"coordinates":[-2.39421,53.58075],"type":"Point"}
}