{
  "type": "Feature",
  "properties": {
    "addr:full":"171 South Street Perth Perth and Kinross PH2 8NY",
    "addr:housenumber":"171",
    "addr:postcode":"ph2 8ny",
    "addr:street":"South Street",
    "iso:country":"GB",
    "sg:address":"171 South Street",
    "sg:city":"Perth",
    "sg:classifiers":[
        {
            "category":"Professional",
            "subcategory":"Printing & Photocopies",
            "type":"Services"
        }
    ],
    "sg:postcode":"PH2 8NY",
    "sg:province":"Perth and Kinross",
    "sg:tags":[
        "trophy"
    ],
    "wof:name":"Perth Trophies",
    "wof:placetype":"venue"
},
  "geometry": {"coordinates":[-3.4331650734,56.3955116272],"type":"Point"}
}