{
  "type": "Feature",
  "properties": {
    "iso:country":"GB",
    "sg:address":"Premier House, 112 Station Road",
    "sg:city":"Edgware",
    "sg:classifiers":[
        {
            "category":"Professional",
            "subcategory":"Accounting & Tax Preparation",
            "type":"Services"
        }
    ],
    "sg:phone":"+44 20 8951 5656",
    "sg:postcode":"HA8 7BJ",
    "sg:province":"Greater London",
    "sg:tags":[
        "accountant"
    ],
    "wof:name":"R N S Chartered Accountants",
    "wof:placetype":"venue"
},
  "geometry": {"coordinates":[-0.277377,51.612019],"type":"Point"}
}