{
  "type": "Feature",
  "properties": {
    "iso:country":"GB",
    "sg:address":"132 Magdalen St",
    "sg:city":"Norwich",
    "sg:classifiers":[
        {
            "category":"Food & Beverages",
            "subcategory":"Specialty",
            "type":"Retail Goods"
        }
    ],
    "sg:postcode":"NR3 1JD",
    "sg:province":"Norfolk",
    "sg:tags":[
        "product",
        "health"
    ],
    "wof:name":"Lowe,D A,",
    "wof:placetype":"venue"
},
  "geometry": {"coordinates":[1.29661,52.637959],"type":"Point"}
}