{
  "type": "Feature",
  "properties": {
    "iso:country":"GB",
    "sg:address":"21-23 Dudley Rd",
    "sg:city":"Brierley Hill",
    "sg:classifiers":[
        {
            "category":"Shopping",
            "subcategory":"Mobile Phones",
            "type":"Retail Goods"
        }
    ],
    "sg:phone":"+44 1384 572144",
    "sg:postcode":"DY5 1HA",
    "sg:province":"West Midlands",
    "wof:name":"Jwe Telecoms",
    "wof:placetype":"venue"
},
  "geometry": {"coordinates":[-2.121251,52.484531],"type":"Point"}
}