{
  "type": "Feature",
  "properties": {
    "addr:full":"Unit 13, Kingston Park Shopping Centre, Brunton Lane Newcastle-upon-tyne Tyne and Wear NE3 2SW",
    "addr:housenumber":"unit 13",
    "addr:postcode":"ne3 2sw",
    "addr:street":"Kingston Park Shopping;Brunton Lane",
    "iso:country":"GB",
    "sg:address":"Unit 13, Kingston Park Shopping Centre, Brunton Lane",
    "sg:city":"Newcastle-upon-tyne",
    "sg:classifiers":[
        {
            "category":"Fast Food",
            "type":"Food & Drink"
        }
    ],
    "sg:postcode":"NE3 2SW",
    "sg:province":"Tyne and Wear",
    "sg:tags":[
        "away",
        "take"
    ],
    "wof:name":"Kingston Chinese Takeaway",
    "wof:placetype":"venue"
},
  "geometry": {"coordinates":[-1.670658946,55.0184402466],"type":"Point"}
}