{
  "type": "Feature",
  "properties": {
    "iso:country":"GB",
    "sg:address":"2 Waterside",
    "sg:city":"Evesham",
    "sg:classifiers":[
        {
            "category":"Shopping",
            "subcategory":"Department Store",
            "type":"Retail Goods"
        }
    ],
    "sg:phone":"+44 1386 45289",
    "sg:postcode":"WR11 1BS",
    "sg:province":"Gloucestershire",
    "wof:name":"Empire Supplies Ltd",
    "wof:placetype":"venue"
},
  "geometry": {"coordinates":[-1.94211,52.090843],"type":"Point"}
}