{
  "type": "Feature",
  "properties": {
    "addr:full":"Hales Meadow Abingdon Oxfordshire OX14 3HP",
    "addr:postcode":"ox14 3hp",
    "addr:street":"Hales Meadow",
    "iso:country":"GB",
    "sg:address":"Hales Meadow",
    "sg:city":"Abingdon",
    "sg:classifiers":[
        {
            "category":"Arena",
            "subcategory":"Sports Club",
            "type":"Entertainment"
        }
    ],
    "sg:phone":"+44 1235 524405",
    "sg:postcode":"OX14 3HP",
    "sg:province":"Oxfordshire",
    "wof:name":"Abingdon Cricket Club",
    "wof:placetype":"venue"
},
  "geometry": {"coordinates":[-1.285489,51.673325],"type":"Point"}
}