{
  "type": "Feature",
  "properties": {
    "addr:full":"262 Silver Street London Greater London N18 1PJ",
    "addr:housenumber":"262",
    "addr:postcode":"n18 1pj",
    "addr:street":"Silver Street",
    "iso:country":"GB",
    "sg:address":"262 Silver Street",
    "sg:city":"London",
    "sg:classifiers":[
        {
            "category":"Professional",
            "type":"Services"
        }
    ],
    "sg:phone":"+44 20 8807 1663",
    "sg:postcode":"N18 1PJ",
    "sg:province":"Greater London",
    "sg:tags":[
        "entertainer"
    ],
    "wof:name":"Ali Cardabra",
    "wof:placetype":"venue"
},
  "geometry": {"coordinates":[-0.079257,51.616379],"type":"Point"}
}