{
  "type": "Feature",
  "properties": {
    "iso:country":"GB",
    "sg:address":"21 Morven Av, Mansfield Woodhouse",
    "sg:city":"Mansfield",
    "sg:classifiers":[
        {
            "category":"Home & Garden",
            "subcategory":"Household Appliances",
            "type":"Retail Goods"
        }
    ],
    "sg:phone":"+44 1623 632587",
    "sg:postcode":"NG19 9JQ",
    "sg:province":"Derbyshire",
    "sg:tags":[
        "electrical"
    ],
    "wof:name":"Wakelin Electrical",
    "wof:placetype":"venue"
},
  "geometry": {"coordinates":[-1.1942509413,53.1571159363],"type":"Point"}
}