{
  "type": "Feature",
  "properties": {
    "iso:country":"GB",
    "sg:address":"30 Barmby Avenue",
    "sg:city":"York",
    "sg:classifiers":[
        {
            "category":"Home & Garden",
            "subcategory":"Hardware",
            "type":"Retail Goods"
        }
    ],
    "sg:postcode":"YO10 4HX",
    "sg:province":"North Yorkshire",
    "sg:tags":[
        "equipment",
        "welding"
    ],
    "wof:name":"Swift Arc Service Welding Equipment Specialist",
    "wof:placetype":"venue"
},
  "geometry": {"coordinates":[-1.0661779642,53.9402008057],"type":"Point"}
}