{
  "type": "Feature",
  "properties": {
    "iso:country":"GB",
    "sg:address":"1 Eagle Brow",
    "sg:city":"Lymm",
    "sg:classifiers":[
        {
            "category":"Professional",
            "subcategory":"Engineering",
            "type":"Services"
        }
    ],
    "sg:phone":"+44 1925 757182",
    "sg:postcode":"WA13 0AG",
    "sg:province":"Cheshire",
    "sg:tags":[
        "consulting",
        "engineer"
    ],
    "wof:name":"Acoustic Air Technology Ltd.",
    "wof:placetype":"venue"
},
  "geometry": {"coordinates":[-2.4791278839,53.3808288574],"type":"Point"}
}