{
  "type": "Feature",
  "properties": {
    "addr:full":"Inverary Road, Wroughton Swindon Wiltshire SN4 9DJ",
    "addr:postcode":"sn4 9dj",
    "addr:street":"Inverary Road",
    "iso:country":"GB",
    "sg:address":"Inverary Road, Wroughton",
    "sg:city":"Swindon",
    "sg:classifiers":[
        {
            "category":"Education",
            "subcategory":"School",
            "type":"Public Place"
        }
    ],
    "sg:phone":"+44 1793 846100",
    "sg:postcode":"SN4 9DJ",
    "sg:province":"Wiltshire",
    "sg:tags":[
        "college",
        "local",
        "authority"
    ],
    "wof:name":"The Ridgeway School",
    "wof:placetype":"venue"
},
  "geometry": {"coordinates":[-1.792891,51.530552],"type":"Point"}
}