{
  "type": "Feature",
  "properties": {
    "iso:country":"GB",
    "sg:address":"45 Blakelow Road, Abbey Hulton",
    "sg:city":"Stoke-on-trent",
    "sg:classifiers":[
        {
            "category":"Shopping",
            "subcategory":"Computers & Home Electronics",
            "type":"Retail Goods"
        }
    ],
    "sg:phone":"+44 1782 537004",
    "sg:postcode":"ST2 8HR",
    "sg:province":"Staffordshire",
    "sg:tags":[
        "aerial",
        "television",
        "radio"
    ],
    "wof:name":"Abbey Aerials",
    "wof:placetype":"venue"
},
  "geometry": {"coordinates":[-2.1409480572,53.0345497131],"type":"Point"}
}