{
  "type": "Feature",
  "properties": {
    "addr:full":"66a Ashmore Road London Greater London W9 1QT",
    "addr:housenumber":"66a",
    "addr:postcode":"w9 1qt",
    "addr:street":"Ashmore Road",
    "iso:country":"GB",
    "sg:address":"66a Ashmore Road",
    "sg:city":"London",
    "sg:classifiers":[
        {
            "category":"Real Estate",
            "subcategory":"Real Estate Agent",
            "type":"Services"
        }
    ],
    "sg:phone":"+44 20 7625 1909",
    "sg:postcode":"W9 1QT",
    "sg:province":"Greater London",
    "wof:name":"Maida Hill Builders Ltd.",
    "wof:placetype":"venue"
},
  "geometry": {"coordinates":[-0.203028,51.5271],"type":"Point"}
}