{
  "type": "Feature",
  "properties": {
    "addr:full":"15 Whitefield Road Liverpool Merseyside L6 5DB",
    "addr:housenumber":"15",
    "addr:postcode":"l6 5db",
    "addr:street":"Whitefield Road",
    "iso:country":"GB",
    "sg:address":"15 Whitefield Road",
    "sg:city":"Liverpool",
    "sg:classifiers":[
        {
            "category":"Bus Charters",
            "type":"Transportation"
        }
    ],
    "sg:postcode":"L6 5DB",
    "sg:province":"Merseyside",
    "sg:tags":[
        "hire",
        "coach"
    ],
    "wof:name":"Central Travel",
    "wof:placetype":"venue"
},
  "geometry": {"coordinates":[-2.953299,53.421581],"type":"Point"}
}