{
  "type": "Feature",
  "properties": {
    "addr:full":"Castle Heather Drive Inverness Highland IV2 4ED",
    "addr:postcode":"iv2 4ed",
    "addr:street":"Heather Drive",
    "iso:country":"GB",
    "sg:address":"Castle Heather Drive",
    "sg:city":"Inverness",
    "sg:classifiers":[
        {
            "category":"Building & Trades",
            "subcategory":"Construction",
            "type":"Services"
        }
    ],
    "sg:postcode":"IV2 4ED",
    "sg:province":"Highland",
    "sg:tags":[
        "builder"
    ],
    "wof:name":"A W G Residential Ltd.",
    "wof:placetype":"venue"
},
  "geometry": {"coordinates":[-4.204279,57.459957],"type":"Point"}
}