{
  "type": "Feature",
  "properties": {
    "iso:country":"GB",
    "sg:address":"Unit E2 The Bramery, Alstone La",
    "sg:city":"Cheltenham",
    "sg:classifiers":[
        {
            "category":"Retail",
            "subcategory":"Auto Repair",
            "type":"Services"
        }
    ],
    "sg:postcode":"GL51 8HE",
    "sg:province":"Gloucestershire",
    "sg:tags":[
        "modification",
        "garage"
    ],
    "wof:name":"Ace Auto Services",
    "wof:placetype":"venue"
},
  "geometry": {"coordinates":[-2.0961399078,51.9024581909],"type":"Point"}
}