{
  "type": "Feature",
  "properties": {
    "addr:full":"Unit 6 Haweswater Road, Penrith Industrial Estate Penrith Cumbria CA11 9EQ",
    "addr:housenumber":"unit 6",
    "addr:postcode":"ca11 9eq",
    "addr:street":"Haweswater Road;Industrial Estate",
    "iso:country":"GB",
    "sg:address":"Unit 6 Haweswater Road, Penrith Industrial Estate",
    "sg:city":"Penrith",
    "sg:classifiers":[
        {
            "category":"Professional",
            "subcategory":"Business Services",
            "type":"Services"
        }
    ],
    "sg:postcode":"CA11 9EQ",
    "sg:province":"Cumbria",
    "sg:tags":[
        "house",
        "mailing"
    ],
    "wof:name":"Cumbria Mailing Services Ltd.",
    "wof:placetype":"venue"
},
  "geometry": {"coordinates":[-2.7674949169,54.6601524353],"type":"Point"}
}