{
  "type": "Feature",
  "properties": {
    "iso:country":"GB",
    "sg:address":"13 High Street",
    "sg:city":"Hawick",
    "sg:classifiers":[
        {
            "category":"Professional",
            "subcategory":"Lawyer & Legal Services",
            "type":"Services"
        }
    ],
    "sg:postcode":"TD9 9DH",
    "sg:province":"Cumbria",
    "sg:tags":[
        "solicitor"
    ],
    "wof:name":"G & J Oliver",
    "wof:placetype":"venue"
},
  "geometry": {"coordinates":[-2.787642,55.42207],"type":"Point"}
}