{
  "type": "Feature",
  "properties": {
    "addr:full":"35 Hayden Lane, Hucknall Nottingham Nottinghamshire NG15 8BJ",
    "addr:housenumber":"35",
    "addr:postcode":"ng15 8bj",
    "addr:street":"Hayden Lane",
    "iso:country":"GB",
    "sg:address":"35 Hayden Lane, Hucknall",
    "sg:city":"Nottingham",
    "sg:classifiers":[
        {
            "category":"Personal",
            "subcategory":"Beauty Salon",
            "type":"Services"
        }
    ],
    "sg:phone":"+44 115 963 0804",
    "sg:postcode":"NG15 8BJ",
    "sg:province":"Nottinghamshire",
    "sg:tags":[
        "unisex",
        "hairdresser"
    ],
    "wof:name":"Top to Toe Hair & Beauty Studio",
    "wof:placetype":"venue"
},
  "geometry": {"coordinates":[-1.1939959526,53.0475921631],"type":"Point"}
}