{
  "type": "Feature",
  "properties": {
    "iso:country":"GB",
    "sg:address":"229 Beverley Drive",
    "sg:city":"Stoke-on-trent",
    "sg:classifiers":[
        {
            "category":"Government",
            "subcategory":"Post Office",
            "type":"Public Place"
        }
    ],
    "sg:phone":"+44 1782 213486",
    "sg:postcode":"ST2 0NA",
    "sg:province":"Staffordshire",
    "wof:name":"Beverley Drive Sub Post Office",
    "wof:placetype":"venue"
},
  "geometry": {"coordinates":[-2.127874,53.018082],"type":"Point"}
}