{
  "type": "Feature",
  "properties": {
    "addr:full":"210 Great North Rd, Eaton Socon St Neots Bedfordshire PE19 8ED",
    "addr:housenumber":"210",
    "addr:postcode":"pe19 8ed",
    "addr:street":"Great North Rd Eaton Socon",
    "iso:country":"GB",
    "sg:address":"210 Great North Rd, Eaton Socon",
    "sg:city":"St Neots",
    "sg:classifiers":[
        {
            "category":"Professional",
            "subcategory":"Art Services",
            "type":"Services"
        }
    ],
    "sg:postcode":"PE19 8ED",
    "sg:province":"Bedfordshire",
    "sg:tags":[
        "glass",
        "engraver"
    ],
    "wof:name":"Glass Engravings 'N' Things",
    "wof:placetype":"venue"
},
  "geometry": {"coordinates":[-0.28902,52.214787],"type":"Point"}
}