{
  "type": "Feature",
  "properties": {
    "iso:country":"GB",
    "sg:address":"2 Emery Lane",
    "sg:city":"Boston",
    "sg:classifiers":[
        {
            "category":"Bars & Pubs",
            "type":"Food & Drink"
        },
        {
            "category":"Community Center",
            "subcategory":"Social",
            "type":"Public Place"
        }
    ],
    "sg:phone":"+44 1205 362926",
    "sg:postcode":"PE21 8QA",
    "sg:province":"Lincolnshire",
    "sg:tags":[
        "pubs",
        "house",
        "inn",
        "activity"
    ],
    "wof:name":"King's Head",
    "wof:placetype":"venue"
},
  "geometry": {"coordinates":[-0.025274,52.976669],"type":"Point"}
}