{
  "type": "Feature",
  "properties": {
    "addr:full":"69a Lower Dock Street Newport Newport NP20 1EH",
    "addr:housenumber":"69a",
    "addr:postcode":"np20 1eh",
    "addr:street":"Lower Dock Street",
    "iso:country":"GB",
    "sg:address":"69a Lower Dock Street",
    "sg:city":"Newport",
    "sg:classifiers":[
        {
            "category":"Place Of Worship",
            "type":"Public Place"
        }
    ],
    "sg:phone":"+44 1633 244453",
    "sg:postcode":"NP20 1EH",
    "sg:province":"Newport",
    "wof:name":"The Kings Church",
    "wof:placetype":"venue"
},
  "geometry": {"coordinates":[-2.989256,51.583012],"type":"Point"}
}