{
  "type": "Feature",
  "properties": {
    "iso:country":"GB",
    "sg:address":"24 Brookfield Drive, Swinton",
    "sg:city":"Manchester",
    "sg:classifiers":[
        {
            "category":"Building & Trades",
            "subcategory":"Construction",
            "type":"Services"
        }
    ],
    "sg:phone":"+44 161 728 1725",
    "sg:postcode":"M27 9TJ",
    "sg:province":"Greater Manchester",
    "sg:tags":[
        "joinery",
        "joiner",
        "carpenter",
        "carpentry"
    ],
    "wof:name":"A J Skinner Joinery",
    "wof:placetype":"venue"
},
  "geometry": {"coordinates":[-2.343894,53.516464],"type":"Point"}
}