{
  "type": "Feature",
  "properties": {
    "addr:full":"C/0 117 Boundary Rd, First Floor,stjohns Wood London Greater London NW8 0RG",
    "addr:housenumber":"117",
    "addr:postcode":"nw8 0rg",
    "addr:street":"C / 0;Boundary Rd;Floor Stjohns Wood",
    "iso:country":"GB",
    "sg:address":"C/0 117 Boundary Rd, First Floor,stjohns Wood",
    "sg:city":"London",
    "sg:classifiers":[
        {
            "category":"Shopping",
            "subcategory":"Stationery & Office Supplies",
            "type":"Retail Goods"
        },
        {
            "category":"Professional",
            "subcategory":"Business Services",
            "type":"Services"
        }
    ],
    "sg:postcode":"NW8 0RG",
    "sg:province":"Greater London",
    "sg:tags":[
        "import",
        "export",
        "agent"
    ],
    "wof:name":"Gemco Trading Ltd",
    "wof:placetype":"venue"
},
  "geometry": {"coordinates":[-0.1781190038,51.5397911072],"type":"Point"}
}