{
  "type": "Feature",
  "properties": {
    "addr:full":"Cullacott Farm, Yeolmbridge Launceston Cornwall PL15 8NH",
    "addr:postcode":"pl15 8nh",
    "iso:country":"GB",
    "sg:address":"Cullacott Farm, Yeolmbridge",
    "sg:city":"Launceston",
    "sg:classifiers":[
        {
            "category":"Farming",
            "subcategory":"Livestock Farm",
            "type":"Manufacturing & Wholesale Goods"
        }
    ],
    "sg:postcode":"PL15 8NH",
    "sg:province":"Cornwall",
    "sg:tags":[
        "others"
    ],
    "wof:name":"K J Cole",
    "wof:placetype":"venue"
},
  "geometry": {"coordinates":[-4.3633441925,50.6367073059],"type":"Point"}
}