{
  "type": "Feature",
  "properties": {
    "iso:country":"GB",
    "sg:address":"Hartshill Rd",
    "sg:city":"Stoke On Trent",
    "sg:classifiers":[
        {
            "category":"Shopping",
            "subcategory":"Pets & Pet Supplies",
            "type":"Retail Goods"
        }
    ],
    "sg:phone":"+44 1782 714151",
    "sg:postcode":"ST4 6AB",
    "sg:province":"Staffordshire",
    "sg:tags":[
        "cemetery",
        "crematorium"
    ],
    "wof:name":"Greenmeadow Pet Caskets",
    "wof:placetype":"venue"
},
  "geometry": {"coordinates":[-2.2121090889,53.0110397339],"type":"Point"}
}