{
  "type": "Feature",
  "properties": {
    "addr:full":"Blackgate West, Coxhoe Durham Durham DH6 4AJ",
    "addr:postcode":"dh6 4aj",
    "addr:street":"Blackgate",
    "iso:country":"GB",
    "sg:address":"Blackgate West, Coxhoe",
    "sg:city":"Durham",
    "sg:classifiers":[
        {
            "category":"Bars & Pubs",
            "type":"Food & Drink"
        }
    ],
    "sg:phone":"+44 191 377 2841",
    "sg:postcode":"DH6 4AJ",
    "sg:province":"Durham",
    "sg:tags":[
        "pubs",
        "inn"
    ],
    "wof:name":"Punch Retail Ltd",
    "wof:placetype":"venue"
},
  "geometry": {"coordinates":[-1.502434,54.714901],"type":"Point"}
}