{
  "type": "Feature",
  "properties": {
    "addr:full":"80 Bushey Road London Greater London SW20 0JQ",
    "addr:housenumber":"80",
    "addr:postcode":"sw20 0jq",
    "addr:street":"Bushey Road",
    "iso:country":"GB",
    "sg:address":"80 Bushey Road",
    "sg:city":"London",
    "sg:classifiers":[
        {
            "category":"Professional",
            "subcategory":"Business Services",
            "type":"Services"
        }
    ],
    "sg:phone":"+44 20 8946 7885",
    "sg:postcode":"SW20 0JQ",
    "sg:province":"Greater London",
    "sg:tags":[
        "tile",
        "stockist"
    ],
    "wof:name":"Topps Tiles",
    "wof:placetype":"venue"
},
  "geometry": {"coordinates":[-0.2373699993,51.4051895142],"type":"Point"}
}