{
  "type": "Feature",
  "properties": {
    "iso:country":"GB",
    "sg:address":"71 Wilsheres Road",
    "sg:city":"Biggleswade",
    "sg:classifiers":[
        {
            "category":"Shopping",
            "subcategory":"Catalog Store",
            "type":"Retail Goods"
        }
    ],
    "sg:phone":"+44 1767 601031",
    "sg:postcode":"SG18 0DN",
    "sg:province":"Bedfordshire",
    "sg:tags":[
        "mail",
        "order"
    ],
    "wof:name":"Me Mail Order",
    "wof:placetype":"venue"
},
  "geometry": {"coordinates":[-0.2632539868,52.0938262939],"type":"Point"}
}