{
  "type": "Feature",
  "properties": {
    "iso:country":"GB",
    "sg:address":"Roedean Manor, Roedean Road",
    "sg:city":"Tunbridge Wells",
    "sg:classifiers":[
        {
            "category":"Social Services",
            "subcategory":"Retirement Home",
            "type":"Services"
        }
    ],
    "sg:postcode":"TN2 5JX",
    "sg:province":"East Sussex",
    "sg:tags":[
        "residential",
        "care"
    ],
    "wof:name":"Roedean Manor Ltd.",
    "wof:placetype":"venue"
},
  "geometry": {"coordinates":[0.26179,51.121868],"type":"Point"}
}