{
  "type": "Feature",
  "properties": {
    "iso:country":"GB",
    "sg:address":"7 North Street, Winchcombe",
    "sg:city":"Cheltenham",
    "sg:classifiers":[
        {
            "category":"Wholesale",
            "subcategory":"Toys & Hobbies",
            "type":"Manufacturing & Wholesale Goods"
        }
    ],
    "sg:phone":"+44 1242 603302",
    "sg:postcode":"GL54 5LH",
    "sg:province":"Gloucestershire",
    "sg:tags":[
        "hospital",
        "doll"
    ],
    "wof:name":"Middleton Lilian Antique Dolls Shop & Hospital",
    "wof:placetype":"venue"
},
  "geometry": {"coordinates":[-1.963972,51.95377],"type":"Point"}
}