{
  "type": "Feature",
  "properties": {
    "addr:full":"Little Butter Hill, Sandon Lane Buntingford Hertfordshire SG9 0RY",
    "addr:postcode":"sg9 0ry",
    "addr:street":"Sandon Lane",
    "iso:country":"GB",
    "sg:address":"Little Butter Hill, Sandon Lane",
    "sg:city":"Buntingford",
    "sg:classifiers":[
        {
            "category":"Home & Garden",
            "subcategory":"Garden Supply",
            "type":"Retail Goods"
        }
    ],
    "sg:postcode":"SG9 0RY",
    "sg:province":"Hertfordshire",
    "sg:tags":[
        "sand",
        "gravel"
    ],
    "wof:name":"A L Burr",
    "wof:placetype":"venue"
},
  "geometry": {"coordinates":[-0.0868040025,51.9864044189],"type":"Point"}
}