{
  "type": "Feature",
  "properties": {
    "iso:country":"GB",
    "sg:address":"22 Moreton Street",
    "sg:city":"London",
    "sg:classifiers":[
        {
            "category":"Professional",
            "subcategory":"Engineering",
            "type":"Services"
        }
    ],
    "sg:phone":"+44 20 7828 5234",
    "sg:postcode":"SW1V 2PT",
    "sg:province":"Greater London",
    "sg:tags":[
        "engineer",
        "structural"
    ],
    "wof:name":"Michael Blacker Partnership",
    "wof:placetype":"venue"
},
  "geometry": {"coordinates":[-0.134698,51.490597],"type":"Point"}
}