{
  "type": "Feature",
  "properties": {
    "iso:country":"GB",
    "sg:address":"18 Imperial Square",
    "sg:city":"Cheltenham",
    "sg:classifiers":[
        {
            "category":"Professional",
            "type":"Services"
        }
    ],
    "sg:phone":"+44 1242 510500",
    "sg:postcode":"GL50 1QZ",
    "sg:province":"Gloucestershire",
    "sg:tags":[
        "valuer",
        "auctioneer"
    ],
    "wof:name":"Sotheby's",
    "wof:placetype":"venue"
},
  "geometry": {"coordinates":[-2.0770840645,51.8967247009],"type":"Point"}
}