{
  "type": "Feature",
  "properties": {
    "addr:full":"70 St Pauls Rd Salisbury Wiltshire SP2 7BE",
    "addr:housenumber":"70",
    "addr:postcode":"sp2 7be",
    "addr:street":"St Pauls Rd",
    "iso:country":"GB",
    "sg:address":"70 St Pauls Rd",
    "sg:city":"Salisbury",
    "sg:classifiers":[
        {
            "category":"Manufacturing",
            "subcategory":"Wood Products",
            "type":"Manufacturing & Wholesale Goods"
        }
    ],
    "sg:phone":"+44 1722 338694",
    "sg:postcode":"SP2 7BE",
    "sg:province":"Wiltshire",
    "sg:tags":[
        "maker",
        "cabinet"
    ],
    "wof:name":"Babey & Son",
    "wof:placetype":"venue"
},
  "geometry": {"coordinates":[-1.8002990484,51.0734558105],"type":"Point"}
}