{
  "type": "Feature",
  "properties": {
    "iso:country":"GB",
    "sg:address":"53 Cardiff Road, Taffs Well",
    "sg:city":"Cardiff",
    "sg:classifiers":[
        {
            "category":"Fast Food",
            "type":"Food & Drink"
        }
    ],
    "sg:phone":"+44 29 2081 0349",
    "sg:postcode":"CF15 7RD",
    "sg:province":"Caerphilly",
    "sg:tags":[
        "away",
        "meal",
        "outlet",
        "take"
    ],
    "wof:name":"Hong Kong Takeaway",
    "wof:placetype":"venue"
},
  "geometry": {"coordinates":[-3.26755,51.542431],"type":"Point"}
}