{
  "type": "Feature",
  "properties": {
    "iso:country":"GB",
    "sg:address":"Research House, Fraser Rd",
    "sg:city":"Greenford",
    "sg:classifiers":[
        {
            "category":"Government",
            "subcategory":"Post Office",
            "type":"Public Place"
        }
    ],
    "sg:phone":"+44 20 8537 3242",
    "sg:postcode":"UB6 7AQ",
    "sg:province":"Greater London",
    "sg:tags":[
        "messenger",
        "courier"
    ],
    "wof:name":"Square Mile Couriers",
    "wof:placetype":"venue"
},
  "geometry": {"coordinates":[-0.315119,51.539261],"type":"Point"}
}