{
  "type": "Feature",
  "properties": {
    "addr:full":"Nelson House, 58 Wimbledon Hill Road London Greater London SW19 7PA",
    "addr:housenumber":"58",
    "addr:postcode":"sw19 7pa",
    "addr:street":"Wimbledon Hill Road",
    "iso:country":"GB",
    "sg:address":"Nelson House, 58 Wimbledon Hill Road",
    "sg:city":"London",
    "sg:classifiers":[
        {
            "category":"Fast Food",
            "type":"Food & Drink"
        }
    ],
    "sg:postcode":"SW19 7PA",
    "sg:province":"Greater London",
    "sg:tags":[
        "away",
        "take"
    ],
    "wof:name":"Nue 18 Enterprises Ltd",
    "wof:placetype":"venue"
},
  "geometry": {"coordinates":[-0.2093590051,51.4225997925],"type":"Point"}
}