{
  "type": "Feature",
  "properties": {
    "iso:country":"GB",
    "sg:address":"Signal House, 16 Lyon Road",
    "sg:city":"Harrow",
    "sg:classifiers":[
        {
            "category":"Real Estate",
            "subcategory":"Developer",
            "type":"Services"
        },
        {
            "category":"Real Estate",
            "subcategory":"Real Estate Agent",
            "type":"Services"
        }
    ],
    "sg:phone":"+44 20 8861 2625",
    "sg:postcode":"HA1 2AG",
    "sg:province":"Greater London",
    "sg:tags":[
        "property"
    ],
    "wof:name":"Fikornbay Estate & Property Ltd.",
    "wof:placetype":"venue"
},
  "geometry": {"coordinates":[-0.332783,51.580433],"type":"Point"}
}