{
  "type": "Feature",
  "properties": {
    "addr:full":"10a Caen Street Braunton Devon EX33 1AA",
    "addr:housenumber":"10a",
    "addr:postcode":"ex33 1aa",
    "addr:street":"Caen Street",
    "iso:country":"GB",
    "sg:address":"10a Caen Street",
    "sg:city":"Braunton",
    "sg:classifiers":[
        {
            "category":"Shopping",
            "subcategory":"Crafts & Fabrics",
            "type":"Retail Goods"
        }
    ],
    "sg:phone":"+44 1271 816442",
    "sg:postcode":"EX33 1AA",
    "sg:province":"Devon",
    "sg:tags":[
        "shop",
        "linen"
    ],
    "wof:name":"Holly's Linens",
    "wof:placetype":"venue"
},
  "geometry": {"coordinates":[-4.1620202065,51.1087417603],"type":"Point"}
}