{
  "type": "Feature",
  "properties": {
    "iso:country":"GB",
    "sg:address":"5-7 Limpsfield Road",
    "sg:city":"Sheffield",
    "sg:classifiers":[
        {
            "category":"Retail",
            "subcategory":"Auto Repair",
            "type":"Services"
        }
    ],
    "sg:phone":"+44 114 243 1764",
    "sg:postcode":"S9 1BJ",
    "sg:province":"South Yorkshire",
    "sg:tags":[
        "modification",
        "garage"
    ],
    "wof:name":"Rusling Motor Engineers",
    "wof:placetype":"venue"
},
  "geometry": {"coordinates":[-1.4236090183,53.4108505249],"type":"Point"}
}