{
  "type": "Feature",
  "properties": {
    "iso:country":"GB",
    "sg:address":"88 Sheep St",
    "sg:city":"Bicester",
    "sg:classifiers":[
        {
            "category":"Shopping",
            "subcategory":"Baby Store",
            "type":"Retail Goods"
        }
    ],
    "sg:postcode":"OX26 6LP",
    "sg:province":"Oxfordshire",
    "sg:tags":[
        "nursery",
        "accessory"
    ],
    "wof:name":"Treasure Cot",
    "wof:placetype":"venue"
},
  "geometry": {"coordinates":[-1.152930975,51.8998184204],"type":"Point"}
}