{
  "type": "Feature",
  "properties": {
    "addr:full":"Squires House, 3 Waverley Lane Farnham Surrey GU9 8BB",
    "addr:housenumber":"3",
    "addr:postcode":"gu9 8bb",
    "addr:street":"Waverley Lane",
    "iso:country":"GB",
    "sg:address":"Squires House, 3 Waverley Lane",
    "sg:city":"Farnham",
    "sg:classifiers":[
        {
            "category":"Bakery",
            "type":"Food & Drink"
        }
    ],
    "sg:phone":"+44 845 225 5671",
    "sg:postcode":"GU9 8BB",
    "sg:province":"Surrey",
    "sg:tags":[
        "cake",
        "maker"
    ],
    "wof:name":"Squires Kitchen Sugarcraft",
    "wof:placetype":"venue"
},
  "geometry": {"coordinates":[-0.791001,51.212147],"type":"Point"}
}