{
  "type": "Feature",
  "properties": {
    "addr:full":"Polborder Farm, Widegates Looe Cornwall PL13 1QR",
    "addr:postcode":"pl13 1qr",
    "addr:street":"Widegates",
    "iso:country":"GB",
    "sg:address":"Polborder Farm, Widegates",
    "sg:city":"Looe",
    "sg:classifiers":[
        {
            "category":"Recreation",
            "subcategory":"Campground",
            "type":"Entertainment"
        }
    ],
    "sg:phone":"+44 1503 240265",
    "sg:postcode":"PL13 1QR",
    "sg:province":"Cornwall",
    "sg:tags":[
        "caravan",
        "park"
    ],
    "wof:name":"Polborder House Caravan & Camping Park",
    "wof:placetype":"venue"
},
  "geometry": {"coordinates":[-4.4551510811,50.3570518494],"type":"Point"}
}