{
  "type": "Feature",
  "properties": {
    "addr:full":"1 Manor Park Estate, Wyndham Street Aldershot Hampshire GU12 4NZ",
    "addr:housenumber":"1",
    "addr:postcode":"gu12 4nz",
    "addr:street":"Manor Park Estate Wyndham Street",
    "iso:country":"GB",
    "sg:address":"1 Manor Park Estate, Wyndham Street",
    "sg:city":"Aldershot",
    "sg:classifiers":[
        {
            "category":"Retail",
            "subcategory":"Auto Repair",
            "type":"Services"
        },
        {
            "category":"Shopping Center",
            "type":"Public Place"
        }
    ],
    "sg:phone":"+44 1252 329121",
    "sg:postcode":"GU12 4NZ",
    "sg:province":"Hampshire",
    "sg:tags":[
        "modification",
        "clutch",
        "garage",
        "brake",
        "centre"
    ],
    "wof:name":"D B K Auto Repairs",
    "wof:placetype":"venue"
},
  "geometry": {"coordinates":[-0.75354,51.245998],"type":"Point"}
}