{
  "type": "Feature",
  "properties": {
    "addr:full":"Littlecroft, Stanton Road Oxford Buckinghamshire OX33 1DT",
    "addr:postcode":"ox33 1dt",
    "addr:street":"Stanton Road",
    "iso:country":"GB",
    "sg:address":"Littlecroft, Stanton Road",
    "sg:city":"Oxford",
    "sg:classifiers":[
        {
            "category":"Professional",
            "type":"Services"
        },
        {
            "category":"Professional",
            "subcategory":"Computer Services",
            "type":"Services"
        }
    ],
    "sg:phone":"+44 1865 873226",
    "sg:postcode":"OX33 1DT",
    "sg:province":"Buckinghamshire",
    "sg:tags":[
        "entertainer",
        "bureau",
        "facility"
    ],
    "wof:name":"J B G Systems Developments",
    "wof:placetype":"venue"
},
  "geometry": {"coordinates":[-1.15343,51.766659],"type":"Point"}
}