{
  "type": "Feature",
  "properties": {
    "addr:full":"Curtis Road Norwich Norfolk NR6 6RB",
    "addr:postcode":"nr6 6rb",
    "addr:street":"Curtis Road Norwich Norfolk",
    "iso:country":"GB",
    "sg:address":"Curtis Road",
    "sg:city":"Norwich",
    "sg:classifiers":[
        {
            "category":"Wholesale",
            "subcategory":"Petroleum",
            "type":"Manufacturing & Wholesale Goods"
        },
        {
            "category":"Real Estate",
            "subcategory":"Architect",
            "type":"Services"
        }
    ],
    "sg:phone":"+44 1603 426928",
    "sg:postcode":"NR6 6RB",
    "sg:province":"Norfolk",
    "wof:name":"Harrisons Engineers (Norwich) Ltd",
    "wof:placetype":"venue"
},
  "geometry": {"coordinates":[1.2793409824,52.6563873291],"type":"Point"}
}