{
  "type": "Feature",
  "properties": {
    "iso:country":"GB",
    "sg:address":"20 Kirkham Avenue, Marton",
    "sg:city":"Blackpool",
    "sg:classifiers":[
        {
            "category":"Building & Trades",
            "subcategory":"Plumbing",
            "type":"Services"
        },
        {
            "category":"Utilities",
            "subcategory":"Natural Gas",
            "type":"Services"
        }
    ],
    "sg:phone":"+44 1253 692126",
    "sg:postcode":"FY1 6RJ",
    "sg:province":"Lancashire",
    "sg:tags":[
        "control",
        "energy",
        "management",
        "heating",
        "system"
    ],
    "wof:name":"Jack Owen",
    "wof:placetype":"venue"
},
  "geometry": {"coordinates":[-3.0308530331,53.8061256409],"type":"Point"}
}