{
  "type": "Feature",
  "properties": {
    "iso:country":"GB",
    "sg:address":"794 Bury Road",
    "sg:city":"Bolton",
    "sg:classifiers":[
        {
            "category":"Health Services",
            "subcategory":"Dentist",
            "type":"Services"
        }
    ],
    "sg:phone":"+44 1204 524046",
    "sg:postcode":"BL2 6PA",
    "sg:province":"Lancashire",
    "wof:name":"Dental Surgery",
    "wof:placetype":"venue"
},
  "geometry": {"coordinates":[-2.386218,53.580807],"type":"Point"}
}