{
  "type": "Feature",
  "properties": {
    "addr:full":"14 Bradford Road, Toddington Dunstable Bedfordshire LU5 6EQ",
    "addr:housenumber":"14",
    "addr:postcode":"lu5 6eq",
    "addr:street":"Bradford Road",
    "iso:country":"GB",
    "sg:address":"14 Bradford Road, Toddington",
    "sg:city":"Dunstable",
    "sg:classifiers":[
        {
            "category":"Building & Trades",
            "subcategory":"Construction",
            "type":"Services"
        }
    ],
    "sg:phone":"+44 1582 607664",
    "sg:postcode":"LU5 6EQ",
    "sg:province":"Bedfordshire",
    "sg:tags":[
        "tiling",
        "contractor"
    ],
    "wof:name":"C C Peck Carpet & Vinyl",
    "wof:placetype":"venue"
},
  "geometry": {"coordinates":[-0.5310649872,51.9414596558],"type":"Point"}
}