{
  "type": "Feature",
  "properties": {
    "addr:full":"79 South Street Romford Essex RM1 1NL",
    "addr:housenumber":"79",
    "addr:postcode":"rm1 1nl",
    "addr:street":"South Street",
    "iso:country":"GB",
    "sg:address":"79 South Street",
    "sg:city":"Romford",
    "sg:classifiers":[
        {
            "category":"Organizations",
            "subcategory":"Non-profit Organization",
            "type":"Services"
        }
    ],
    "sg:phone":"+44 1708 753363",
    "sg:postcode":"RM1 1NL",
    "sg:province":"Essex",
    "sg:tags":[
        "organisation",
        "voluntary",
        "charity"
    ],
    "wof:name":"British Heart Foundation",
    "wof:placetype":"venue"
},
  "geometry": {"coordinates":[0.184101,51.573986],"type":"Point"}
}