{
  "type": "Feature",
  "properties": {
    "addr:full":"Roskestal, St Levan Penzance Cornwall TR19 6JN",
    "addr:postcode":"tr19 6jn",
    "iso:country":"GB",
    "sg:address":"Roskestal, St Levan",
    "sg:city":"Penzance",
    "sg:classifiers":[
        {
            "category":"Farming",
            "subcategory":"Dairy Farm",
            "type":"Manufacturing & Wholesale Goods"
        }
    ],
    "sg:phone":"+44 1736 871236",
    "sg:postcode":"TR19 6JN",
    "sg:province":"Cornwall",
    "wof:name":"J Williams & Sons",
    "wof:placetype":"venue"
},
  "geometry": {"coordinates":[-5.6744,50.042149],"type":"Point"}
}