{
  "type": "Feature",
  "properties": {
    "addr:full":"Broadford Isle Of Skye Highland IV49 9AA",
    "addr:postcode":"iv49 9aa",
    "iso:country":"GB",
    "sg:address":"Broadford",
    "sg:city":"Isle Of Skye",
    "sg:classifiers":[
        {
            "category":"Social Services",
            "subcategory":"Retirement Home",
            "type":"Services"
        }
    ],
    "sg:phone":"+44 1471 822359",
    "sg:postcode":"IV49 9AA",
    "sg:province":"Highland",
    "sg:tags":[
        "residential",
        "care"
    ],
    "wof:name":"Strathcare Residential Home",
    "wof:placetype":"venue"
},
  "geometry": {"coordinates":[-5.91217,57.246288],"type":"Point"}
}