{
  "type": "Feature",
  "properties": {
    "iso:country":"GB",
    "sg:address":"15 Curzon St",
    "sg:city":"Burnley",
    "sg:classifiers":[
        {
            "category":"Professional",
            "subcategory":"Business Services",
            "type":"Services"
        },
        {
            "category":"Shopping",
            "subcategory":"Pets & Pet Supplies",
            "type":"Retail Goods"
        }
    ],
    "sg:postcode":"BB11 1BB",
    "sg:province":"Lancashire",
    "sg:tags":[
        "import",
        "export",
        "agent"
    ],
    "wof:name":"Ruddick,D,",
    "wof:placetype":"venue"
},
  "geometry": {"coordinates":[-2.24447,53.790306],"type":"Point"}
}