{
  "type": "Feature",
  "properties": {
    "addr:full":"5 Bedford Corner, South Parade London Greater London W4 1LD",
    "addr:housenumber":"5",
    "addr:postcode":"w4 1ld",
    "addr:street":"Bedford Corner South Parade",
    "iso:country":"GB",
    "sg:address":"5 Bedford Corner, South Parade",
    "sg:city":"London",
    "sg:classifiers":[
        {
            "category":"Shopping",
            "subcategory":"News",
            "type":"Retail Goods"
        }
    ],
    "sg:phone":"+44 20 8994 3098",
    "sg:postcode":"W4 1LD",
    "sg:province":"Greater London",
    "sg:tags":[
        "newsagent"
    ],
    "wof:name":"Ctn News",
    "wof:placetype":"venue"
},
  "geometry": {"coordinates":[-0.2559700012,51.4963607788],"type":"Point"}
}