{
  "type": "Feature",
  "properties": {
    "addr:full":"Unit 4 Honeyholes Lane, Dunholme Lincoln Lincolnshire LN2 3SU",
    "addr:housenumber":"unit 4",
    "addr:postcode":"ln2 3su",
    "addr:street":"Honeyholes Lane",
    "iso:country":"GB",
    "sg:address":"Unit 4 Honeyholes Lane, Dunholme",
    "sg:city":"Lincoln",
    "sg:classifiers":[
        {
            "category":"Home & Garden",
            "subcategory":"Hardware",
            "type":"Retail Goods"
        }
    ],
    "sg:postcode":"LN2 3SU",
    "sg:province":"Lincolnshire",
    "sg:tags":[
        "tarpaulin"
    ],
    "wof:name":"Lincoln Sheeting Products",
    "wof:placetype":"venue"
},
  "geometry": {"coordinates":[-0.468519,53.301094],"type":"Point"}
}