{
  "type": "Feature",
  "properties": {
    "addr:full":"Wirral Park Glastonbury Somerset BA6 9XE",
    "addr:postcode":"ba6 9xe",
    "addr:street":"Wirral Park",
    "iso:country":"GB",
    "sg:address":"Wirral Park",
    "sg:city":"Glastonbury",
    "sg:classifiers":[
        {
            "category":"Recreation",
            "subcategory":"Water Park",
            "type":"Entertainment"
        }
    ],
    "sg:phone":"+44 1458 834344",
    "sg:postcode":"BA6 9XE",
    "sg:province":"Somerset",
    "sg:tags":[
        "supplier",
        "bottled"
    ],
    "wof:name":"Glastonbury Spring Water Co. Ltd.",
    "wof:placetype":"venue"
},
  "geometry": {"coordinates":[-2.728704,51.142246],"type":"Point"}
}