{
  "type": "Feature",
  "properties": {
    "iso:country":"GB",
    "sg:address":"Lochend Close",
    "sg:city":"Edinburgh",
    "sg:classifiers":[
        {
            "category":"Social Services",
            "type":"Services"
        }
    ],
    "sg:phone":"+44 131 556 8833",
    "sg:postcode":"EH8 8BL",
    "sg:province":"City of Edinburgh",
    "wof:name":"Panmure House Youth Strategy Centre",
    "wof:placetype":"venue"
},
  "geometry": {"coordinates":[-3.1783549786,55.9525108337],"type":"Point"}
}