{
  "type": "Feature",
  "properties": {
    "iso:country":"GB",
    "sg:address":"5a Beulah Road",
    "sg:city":"Cardiff",
    "sg:classifiers":[
        {
            "category":"Personal",
            "subcategory":"Beauty Salon",
            "type":"Services"
        }
    ],
    "sg:postcode":"CF14 6LT",
    "sg:province":"Cardiff",
    "wof:name":"Cleverstix",
    "wof:placetype":"venue"
},
  "geometry": {"coordinates":[-3.211366,51.522449],"type":"Point"}
}