{
  "type": "Feature",
  "properties": {
    "addr:full":"10 Huntley Close High Wycombe Buckinghamshire HP13 5PQ",
    "addr:housenumber":"10",
    "addr:postcode":"hp13 5pq",
    "addr:street":"Huntley Close",
    "iso:country":"GB",
    "sg:address":"10 Huntley Close",
    "sg:city":"High Wycombe",
    "sg:classifiers":[
        {
            "category":"Shopping",
            "subcategory":"Musical Instruments",
            "type":"Retail Goods"
        }
    ],
    "sg:postcode":"HP13 5PQ",
    "sg:province":"Buckinghamshire",
    "sg:tags":[
        "music",
        "sheet"
    ],
    "wof:name":"N & K Barr",
    "wof:placetype":"venue"
},
  "geometry": {"coordinates":[-0.740413,51.64444],"type":"Point"}
}