{
  "type": "Feature",
  "properties": {
    "addr:full":"37 Lloyd Street South Manchester Greater Manchester M14 7HS",
    "addr:housenumber":"37",
    "addr:postcode":"m14 7hs",
    "addr:street":"Lloyd Street South",
    "iso:country":"GB",
    "sg:address":"37 Lloyd Street South",
    "sg:city":"Manchester",
    "sg:classifiers":[
        {
            "category":"Communications",
            "subcategory":"Film & Video Production",
            "type":"Services"
        }
    ],
    "sg:phone":"+44 161 227 9910",
    "sg:postcode":"M14 7HS",
    "sg:province":"Greater Manchester",
    "sg:tags":[
        "tv",
        "studio"
    ],
    "wof:name":"Goodspeed T V S",
    "wof:placetype":"venue"
},
  "geometry": {"coordinates":[-2.2384140491,53.4505004883],"type":"Point"}
}