{
  "type": "Feature",
  "properties": {
    "addr:full":"1 Wentworth Street Wakefield West Yorkshire WF1 2QS",
    "addr:housenumber":"1",
    "addr:postcode":"wf1 2qs",
    "addr:street":"Wentworth Street",
    "iso:country":"GB",
    "sg:address":"1 Wentworth Street",
    "sg:city":"Wakefield",
    "sg:classifiers":[
        {
            "category":"Education",
            "subcategory":"School",
            "type":"Public Place"
        }
    ],
    "sg:phone":"+44 1924 372490",
    "sg:postcode":"WF1 2QS",
    "sg:province":"West Yorkshire",
    "sg:tags":[
        "independent",
        "preparatory"
    ],
    "sg:website":"http://www.wghsjs.org.uk",
    "wof:name":"Wakefield Girls High School",
    "wof:placetype":"venue"
},
  "geometry": {"coordinates":[-1.5059740543,53.689491272],"type":"Point"}
}