{
  "type": "Feature",
  "properties": {
    "iso:country":"GB",
    "sg:address":"371 George Street",
    "sg:city":"Aberdeen",
    "sg:classifiers":[
        {
            "category":"Food & Beverages",
            "subcategory":"Supermarket",
            "type":"Retail Goods"
        }
    ],
    "sg:phone":"+44 1224 632789",
    "sg:postcode":"AB25 1EQ",
    "sg:province":"Aberdeen City",
    "wof:name":"Spar",
    "wof:placetype":"venue"
},
  "geometry": {"coordinates":[-2.105144,57.15303],"type":"Point"}
}