{
  "type": "Feature",
  "properties": {
    "addr:full":"5 Jubilee Street Melton Mowbray Leicestershire LE13 1ND",
    "addr:housenumber":"5",
    "addr:postcode":"le13 1nd",
    "addr:street":"Jubilee Street",
    "iso:country":"GB",
    "sg:address":"5 Jubilee Street",
    "sg:city":"Melton Mowbray",
    "sg:classifiers":[
        {
            "category":"Taxi",
            "type":"Transportation"
        },
        {
            "category":"Military Area",
            "subcategory":"Air Force Base",
            "type":"Public Place"
        }
    ],
    "sg:phone":"+44 1664 480900",
    "sg:postcode":"LE13 1ND",
    "sg:province":"Leicestershire",
    "sg:tags":[
        "mini",
        "hire",
        "private",
        "cab"
    ],
    "wof:name":"Dean's Taxi",
    "wof:placetype":"venue"
},
  "geometry": {"coordinates":[-0.884386003,52.7675056458],"type":"Point"}
}