{
  "type": "Feature",
  "properties": {
    "addr:full":"82 Hilton Road, Mapperley Nottingham Nottinghamshire NG3 6AQ",
    "addr:housenumber":"82",
    "addr:postcode":"ng3 6aq",
    "addr:street":"Hilton Road",
    "iso:country":"GB",
    "sg:address":"82 Hilton Road, Mapperley",
    "sg:city":"Nottingham",
    "sg:classifiers":[
        {
            "category":"Professional",
            "subcategory":"Engineering",
            "type":"Services"
        }
    ],
    "sg:postcode":"NG3 6AQ",
    "sg:province":"Nottinghamshire",
    "sg:tags":[
        "contractor",
        "electrical",
        "engineer"
    ],
    "wof:name":"John Shepherd",
    "wof:placetype":"venue"
},
  "geometry": {"coordinates":[-1.1197240353,52.9816246033],"type":"Point"}
}