{
  "type": "Feature",
  "properties": {
    "iso:country":"GB",
    "sg:address":"Victoria Rd",
    "sg:city":"Cambridge",
    "sg:classifiers":[
        {
            "category":"Place Of Worship",
            "type":"Public Place"
        }
    ],
    "sg:phone":"+44 1223 351943",
    "sg:postcode":"CB4 3BW",
    "sg:province":"Cambridgeshire",
    "wof:name":"United Reformed Church",
    "wof:placetype":"venue"
},
  "geometry": {"coordinates":[0.11489,52.215687],"type":"Point"}
}