{
  "type": "Feature",
  "properties": {
    "iso:country":"GB",
    "sg:address":"134 West Road",
    "sg:city":"Newcastle-upon-tyne",
    "sg:classifiers":[
        {
            "category":"Food & Beverages",
            "subcategory":"Fruits & Vegetables",
            "type":"Retail Goods"
        }
    ],
    "sg:phone":"+44 191 226 0059",
    "sg:postcode":"NE4 9QA",
    "sg:province":"Tyne and Wear",
    "sg:tags":[
        "greengrocer"
    ],
    "wof:name":"ELAINE HANNAH",
    "wof:placetype":"venue"
},
  "geometry": {"coordinates":[-1.655297,54.976093],"type":"Point"}
}