{
  "type": "Feature",
  "properties": {
    "addr:full":"14 Bryneithin Avenue Prestatyn Denbighshire LL19 9LS",
    "addr:housenumber":"14",
    "addr:postcode":"ll19 9ls",
    "addr:street":"Bryneithin Avenue",
    "iso:country":"GB",
    "sg:address":"14 Bryneithin Avenue",
    "sg:city":"Prestatyn",
    "sg:classifiers":[
        {
            "category":"Organizations",
            "subcategory":"Community Association",
            "type":"Services"
        }
    ],
    "sg:phone":"+44 1745 854629",
    "sg:postcode":"LL19 9LS",
    "sg:province":"Denbighshire",
    "sg:tags":[
        "society",
        "housing"
    ],
    "wof:name":"Abbeyfield Prestatyn Society Ltd.",
    "wof:placetype":"venue"
},
  "geometry": {"coordinates":[-3.399945,53.334595],"type":"Point"}
}