{
  "type": "Feature",
  "properties": {
    "addr:full":"18 St Johns Way Stanford Le Hope Essex SS17 7LJ",
    "addr:housenumber":"18",
    "addr:postcode":"ss17 7lj",
    "addr:street":"St Johns Way",
    "iso:country":"GB",
    "sg:address":"18 St Johns Way",
    "sg:city":"Stanford Le Hope",
    "sg:classifiers":[
        {
            "category":"Shopping",
            "subcategory":"Department Store",
            "type":"Retail Goods"
        }
    ],
    "sg:phone":"+44 1375 672074",
    "sg:postcode":"SS17 7LJ",
    "sg:province":"Essex",
    "wof:name":"Price Slashers Ltd",
    "wof:placetype":"venue"
},
  "geometry": {"coordinates":[0.44828,51.525089],"type":"Point"}
}