{
  "type": "Feature",
  "properties": {
    "addr:full":"Imperial College South Kensington Campus London sw7 2az",
    "addr:postcode":"sw7 2az",
    "iso:country":"GB",
    "sg:address":"Imperial College South Kensington Campus",
    "sg:city":"London",
    "sg:classifiers":[
        {
            "category":"Professional",
            "subcategory":"Computer Services",
            "type":"Services"
        }
    ],
    "sg:postcode":"sw7 2az",
    "sg:tags":[
        "science",
        "bibliography",
        "community",
        "collaboration",
        "papers"
    ],
    "sg:website":"http://www.kappaprime.com/",
    "wof:name":"Kappa Prime",
    "wof:placetype":"venue"
},
  "geometry": {"coordinates":[-0.175393,51.498067],"type":"Point"}
}