{
  "type": "Feature",
  "properties": {
    "iso:country":"GB",
    "sg:address":"14 Chesterton Road",
    "sg:city":"Cambridge",
    "sg:classifiers":[
        {
            "category":"Bars & Pubs",
            "type":"Food & Drink"
        }
    ],
    "sg:phone":"+44 1223 460905",
    "sg:postcode":"CB4 3AX",
    "sg:province":"Cambridgeshire",
    "sg:tags":[
        "pubs",
        "inn"
    ],
    "wof:name":"The Boat House",
    "wof:placetype":"venue"
},
  "geometry": {"coordinates":[0.1236670017,52.2137336731],"type":"Point"}
}