{
  "type": "Feature",
  "properties": {
    "iso:country":"GB",
    "sg:address":"72 Alma Rd",
    "sg:city":"Bristol",
    "sg:classifiers":[
        {
            "category":"Insurance",
            "subcategory":"Insurance Agent",
            "type":"Services"
        }
    ],
    "sg:phone":"+44 117 923 9249",
    "sg:postcode":"BS8 2DJ",
    "sg:province":"City of Bristol",
    "wof:name":"Heywood Collins Ltd",
    "wof:placetype":"venue"
},
  "geometry": {"coordinates":[-2.610185,51.463104],"type":"Point"}
}