{
  "type": "Feature",
  "properties": {
    "addr:full":"Riverside Farm, Vicarage Lane, Scrooby Doncaster Lincolnshire DN10 6AD",
    "addr:postcode":"dn10 6ad",
    "addr:street":"Vicarage Lane",
    "iso:country":"GB",
    "sg:address":"Riverside Farm, Vicarage Lane, Scrooby",
    "sg:city":"Doncaster",
    "sg:classifiers":[
        {
            "category":"Retail",
            "subcategory":"Animal Services",
            "type":"Services"
        }
    ],
    "sg:phone":"+44 1302 710439",
    "sg:postcode":"DN10 6AD",
    "sg:province":"Lincolnshire",
    "sg:tags":[
        "farrier"
    ],
    "wof:name":"David Hull Farrier",
    "wof:placetype":"venue"
},
  "geometry": {"coordinates":[-1.020981,53.408791],"type":"Point"}
}