{
  "type": "Feature",
  "properties": {
    "iso:country":"GB",
    "sg:address":"34a Nellgrove Rd",
    "sg:city":"Uxbridge",
    "sg:classifiers":[
        {
            "category":"Retail",
            "subcategory":"Auto Repair",
            "type":"Services"
        }
    ],
    "sg:phone":"+44 20 8561 0512",
    "sg:postcode":"UB10 0SX",
    "sg:province":"Greater London",
    "sg:tags":[
        "modification",
        "garage"
    ],
    "wof:name":"A.A1. Rofis Garage",
    "wof:placetype":"venue"
},
  "geometry": {"coordinates":[-0.4451160133,51.5276374817],"type":"Point"}
}