{
  "type": "Feature",
  "properties": {
    "addr:full":"46 Bridgegate Retford Nottinghamshire DN22 7UZ",
    "addr:housenumber":"46",
    "addr:postcode":"dn22 7uz",
    "addr:street":"Bridgegate",
    "iso:country":"GB",
    "sg:address":"46 Bridgegate",
    "sg:city":"Retford",
    "sg:classifiers":[
        {
            "category":"Social Services",
            "type":"Services"
        }
    ],
    "sg:phone":"+44 1777 708595",
    "sg:postcode":"DN22 7UZ",
    "sg:province":"Nottinghamshire",
    "sg:tags":[
        "disability"
    ],
    "wof:name":"Care Matters",
    "wof:placetype":"venue"
},
  "geometry": {"coordinates":[-0.9458640218,53.3243560791],"type":"Point"}
}