{
  "type": "Feature",
  "properties": {
    "addr:full":"1-4 Meachin Court, Church Road, Westbury On Trym Bristol City of Bristol BS9 3EF",
    "addr:housenumber":"1-4",
    "addr:postcode":"bs9 3ef",
    "addr:street":"Meachin Court Church Road",
    "iso:country":"GB",
    "sg:address":"1-4 Meachin Court, Church Road, Westbury On Trym",
    "sg:city":"Bristol",
    "sg:classifiers":[
        {
            "category":"Professional",
            "subcategory":"Employment Agencies",
            "type":"Services"
        }
    ],
    "sg:phone":"+44 117 991 3541",
    "sg:postcode":"BS9 3EF",
    "sg:province":"City of Bristol",
    "sg:tags":[
        "consultant"
    ],
    "wof:name":"Job Centre",
    "wof:placetype":"venue"
},
  "geometry": {"coordinates":[-2.6219639778,51.492729187],"type":"Point"}
}