{
  "type": "Feature",
  "properties": {
    "iso:country":"GB",
    "sg:address":"Unit M7, Morton Pk, Yarn Rd",
    "sg:city":"Darlington",
    "sg:classifiers":[
        {
            "category":"Shopping",
            "subcategory":"Department Store",
            "type":"Retail Goods"
        }
    ],
    "sg:postcode":"DL1 4PJ",
    "sg:province":"Durham",
    "wof:name":"Hanbok Martial Arts Supplies",
    "wof:placetype":"venue"
},
  "geometry": {"coordinates":[-1.502839,54.518921],"type":"Point"}
}