{
  "type": "Feature",
  "properties": {
    "iso:country":"GB",
    "sg:address":"3 West Main Street, Armadale",
    "sg:city":"Bathgate",
    "sg:classifiers":[
        {
            "category":"Health Services",
            "subcategory":"Dentist",
            "type":"Services"
        }
    ],
    "sg:phone":"+44 1501 732724",
    "sg:postcode":"EH48 3PZ",
    "sg:province":"West Lothian",
    "wof:name":"Heather Shields J V B D S",
    "wof:placetype":"venue"
},
  "geometry": {"coordinates":[-3.700586,55.89864],"type":"Point"}
}