{
  "type": "Feature",
  "properties": {
    "iso:country":"GB",
    "sg:address":"109-111 Church St",
    "sg:city":"Stoke On Trent",
    "sg:classifiers":[
        {
            "category":"Home & Garden",
            "subcategory":"Home Furnishings",
            "type":"Retail Goods"
        }
    ],
    "sg:phone":"+44 1782 411164",
    "sg:postcode":"ST4 1DE",
    "sg:province":"Staffordshire",
    "sg:tags":[
        "awning",
        "canopy",
        "blinds"
    ],
    "wof:name":"Blinds & Fabrics",
    "wof:placetype":"venue"
},
  "geometry": {"coordinates":[-2.1861550808,53.0042457581],"type":"Point"}
}