{
  "type": "Feature",
  "properties": {
    "addr:full":"253 Ben Lane Sheffield South Yorkshire S6 4SE",
    "addr:housenumber":"253",
    "addr:postcode":"s6 4se",
    "addr:street":"Ben Lane",
    "iso:country":"GB",
    "sg:address":"253 Ben Lane",
    "sg:city":"Sheffield",
    "sg:classifiers":[
        {
            "category":"Shopping",
            "subcategory":"Department Store",
            "type":"Retail Goods"
        }
    ],
    "sg:postcode":"S6 4SE",
    "sg:province":"South Yorkshire",
    "wof:name":"Old Corner Shop",
    "wof:placetype":"venue"
},
  "geometry": {"coordinates":[-1.5213830471,53.4079208374],"type":"Point"}
}