{
  "type": "Feature",
  "properties": {
    "addr:full":"10 Broadstone Road Stockport Cheshire SK5 7AE",
    "addr:housenumber":"10",
    "addr:postcode":"sk5 7ae",
    "addr:street":"Broadstone Road",
    "iso:country":"GB",
    "sg:address":"10 Broadstone Road",
    "sg:city":"Stockport",
    "sg:classifiers":[
        {
            "category":"Personal",
            "subcategory":"Beauty Salon",
            "type":"Services"
        }
    ],
    "sg:phone":"+44 161 432 8072",
    "sg:postcode":"SK5 7AE",
    "sg:province":"Cheshire",
    "sg:tags":[
        "unisex",
        "hairdresser"
    ],
    "wof:name":"Emilios",
    "wof:placetype":"venue"
},
  "geometry": {"coordinates":[-2.1607348919,53.437122345],"type":"Point"}
}