{
  "type": "Feature",
  "properties": {
    "addr:full":"Seafield Garage, Port Road, Palnackie Castle Douglas Dumfries and Galloway DG7 1PQ",
    "addr:postcode":"dg7 1pq",
    "addr:street":"Port Road Palnackie",
    "iso:country":"GB",
    "sg:address":"Seafield Garage, Port Road, Palnackie",
    "sg:city":"Castle Douglas",
    "sg:classifiers":[
        {
            "category":"Utilities",
            "subcategory":"Refuse",
            "type":"Services"
        }
    ],
    "sg:phone":"+44 1556 600317",
    "sg:postcode":"DG7 1PQ",
    "sg:province":"Dumfries and Galloway",
    "sg:tags":[
        "skip",
        "hire"
    ],
    "wof:name":"J R Halliday",
    "wof:placetype":"venue"
},
  "geometry": {"coordinates":[-3.928704,54.94162],"type":"Point"}
}