{
  "type": "Feature",
  "properties": {
    "addr:full":"9 Powderham Rd Newton Abbot Devon TQ12 1EU",
    "addr:housenumber":"9",
    "addr:postcode":"tq12 1eu",
    "addr:street":"Powderham Rd",
    "iso:country":"GB",
    "sg:address":"9 Powderham Rd",
    "sg:city":"Newton Abbot",
    "sg:classifiers":[
        {
            "category":"Health Services",
            "subcategory":"Clinic",
            "type":"Services"
        }
    ],
    "sg:phone":"+44 1626 351925",
    "sg:postcode":"TQ12 1EU",
    "sg:province":"Devon",
    "sg:tags":[
        "nh"
    ],
    "wof:name":"Laurels Mental Health Centre The",
    "wof:placetype":"venue"
},
  "geometry": {"coordinates":[-3.611561,50.528248],"type":"Point"}
}