{
  "type": "Feature",
  "properties": {
    "addr:full":"82 Frances Rd Windsor Berkshire SL4 3AJ",
    "addr:housenumber":"82",
    "addr:postcode":"sl4 3aj",
    "addr:street":"Frances Rd",
    "iso:country":"GB",
    "sg:address":"82 Frances Rd",
    "sg:city":"Windsor",
    "sg:classifiers":[
        {
            "category":"Shopping",
            "subcategory":"Pharmacy",
            "type":"Retail Goods"
        }
    ],
    "sg:phone":"+44 1753 830470",
    "sg:postcode":"SL4 3AJ",
    "sg:province":"Berkshire",
    "sg:tags":[
        "medicine",
        "therapy"
    ],
    "wof:name":"Elton Clinic",
    "wof:placetype":"venue"
},
  "geometry": {"coordinates":[-0.6108919978,51.4756202698],"type":"Point"}
}