{
  "type": "Feature",
  "properties": {
    "addr:full":"Ashingdon Road Rochford Essex SS4 1RS",
    "addr:postcode":"ss4 1rs",
    "addr:street":"Ashingdon Road",
    "iso:country":"GB",
    "sg:address":"Ashingdon Road",
    "sg:city":"Rochford",
    "sg:classifiers":[
        {
            "category":"Education",
            "subcategory":"School",
            "type":"Public Place"
        }
    ],
    "sg:phone":"+44 1702 545131",
    "sg:postcode":"SS4 1RS",
    "sg:province":"Essex",
    "sg:tags":[
        "local",
        "authority"
    ],
    "wof:name":"Holt Farm County Junior School",
    "wof:placetype":"venue"
},
  "geometry": {"coordinates":[0.696645,51.597408],"type":"Point"}
}