{
  "type": "Feature",
  "properties": {
    "iso:country":"GB",
    "sg:address":"Rickford, Burrington",
    "sg:city":"Bristol",
    "sg:classifiers":[
        {
            "category":"Bars & Pubs",
            "type":"Food & Drink"
        }
    ],
    "sg:phone":"+44 1761 462682",
    "sg:postcode":"BS40 7AH",
    "sg:province":"Somerset",
    "sg:tags":[
        "pubs",
        "inn"
    ],
    "wof:name":"The Plume of Feathers",
    "wof:placetype":"venue"
},
  "geometry": {"coordinates":[-2.750704,51.332664],"type":"Point"}
}