{
  "type": "Feature",
  "properties": {
    "addr:full":"210a Jamaica Road London Greater London SE16 4RT",
    "addr:housenumber":"210a",
    "addr:postcode":"se16 4rt",
    "addr:street":"Jamaica Road",
    "iso:country":"GB",
    "sg:address":"210a Jamaica Road",
    "sg:city":"London",
    "sg:classifiers":[
        {
            "category":"Organizations",
            "subcategory":"Membership Organization",
            "type":"Services"
        }
    ],
    "sg:phone":"+44 20 7237 2350",
    "sg:postcode":"SE16 4RT",
    "sg:province":"Greater London",
    "sg:tags":[
        "club"
    ],
    "wof:name":"Millpond Tennants Association",
    "wof:placetype":"venue"
},
  "geometry": {"coordinates":[-0.0609119982,51.4983940125],"type":"Point"}
}