{
  "type": "Feature",
  "properties": {
    "iso:country":"GB",
    "sg:address":"12 The Courtyard, Montpellier Street",
    "sg:city":"Cheltenham",
    "sg:classifiers":[
        {
            "category":"Shopping",
            "subcategory":"Baby Store",
            "type":"Retail Goods"
        }
    ],
    "sg:phone":"+44 1242 255955",
    "sg:postcode":"GL50 1SX",
    "sg:province":"Gloucestershire",
    "sg:tags":[
        "babywear",
        "childrens"
    ],
    "wof:name":"Good As Gold",
    "wof:placetype":"venue"
},
  "geometry": {"coordinates":[-2.0784590244,51.8980484009],"type":"Point"}
}