{
  "type": "Feature",
  "properties": {
    "iso:country":"GB",
    "sg:address":"Burley Road",
    "sg:city":"Leeds",
    "sg:classifiers":[
        {
            "category":"Professional",
            "subcategory":"Computer Services",
            "type":"Services"
        }
    ],
    "sg:phone":"+44 870 046 3388",
    "sg:postcode":"LS3 1JX",
    "sg:province":"West Yorkshire",
    "sg:tags":[
        "system",
        "software"
    ],
    "wof:name":"Pc Ideas Ltd.",
    "wof:placetype":"venue"
},
  "geometry": {"coordinates":[-1.569512,53.804749],"type":"Point"}
}