{
  "type": "Feature",
  "properties": {
    "addr:full":"1 Hove Street Hove East Sussex BN3 2TR",
    "addr:housenumber":"1",
    "addr:postcode":"bn3 2tr",
    "addr:street":"Hove Street",
    "iso:country":"GB",
    "sg:address":"1 Hove Street",
    "sg:city":"Hove",
    "sg:classifiers":[
        {
            "category":"Retail",
            "subcategory":"Auto Repair",
            "type":"Services"
        }
    ],
    "sg:phone":"+44 1273 202832",
    "sg:postcode":"BN3 2TR",
    "sg:province":"East Sussex",
    "sg:tags":[
        "modification",
        "garage"
    ],
    "wof:name":"Manser Motors Buzbee Bee",
    "wof:placetype":"venue"
},
  "geometry": {"coordinates":[-0.180385,50.825802],"type":"Point"}
}