{
  "type": "Feature",
  "properties": {
    "iso:country":"GB",
    "sg:address":"5 Salisbury Square",
    "sg:city":"Hatfield",
    "sg:classifiers":[
        {
            "category":"Retail",
            "subcategory":"Laundry & Dry Cleaning",
            "type":"Services"
        }
    ],
    "sg:phone":"+44 1707 267224",
    "sg:postcode":"AL9 5AD",
    "sg:province":"Hertfordshire",
    "sg:tags":[
        "launderette"
    ],
    "wof:name":"Old Hatfield Launderette & Dry Cleaners",
    "wof:placetype":"venue"
},
  "geometry": {"coordinates":[-0.2138289958,51.7624282837],"type":"Point"}
}