{
  "type": "Feature",
  "properties": {
    "addr:full":"Birches, Kerry Newtown Powys SY16 4DR",
    "addr:postcode":"sy16 4dr",
    "addr:street":"Kerry",
    "iso:country":"GB",
    "sg:address":"Birches, Kerry",
    "sg:city":"Newtown",
    "sg:classifiers":[
        {
            "category":"Building & Trades",
            "subcategory":"Construction",
            "type":"Services"
        }
    ],
    "sg:postcode":"SY16 4DR",
    "sg:province":"Powys",
    "sg:tags":[
        "decorator",
        "painter"
    ],
    "wof:name":"Nigel Whittington",
    "wof:placetype":"venue"
},
  "geometry": {"coordinates":[-3.259424,52.501148],"type":"Point"}
}