{
  "type": "Feature",
  "properties": {
    "iso:country":"GB",
    "sg:address":"Dalton Road",
    "sg:city":"Barrow-in-furness",
    "sg:classifiers":[
        {
            "category":"Bars & Pubs",
            "type":"Food & Drink"
        },
        {
            "category":"Community Center",
            "subcategory":"Social",
            "type":"Public Place"
        }
    ],
    "sg:phone":"+44 1229 820089",
    "sg:postcode":"LA14 2EX",
    "sg:province":"Cumbria",
    "sg:tags":[
        "pubs",
        "house",
        "inn",
        "activity"
    ],
    "wof:name":"Albion Hotel",
    "wof:placetype":"venue"
},
  "geometry": {"coordinates":[-3.226259,54.109707],"type":"Point"}
}