{
  "type": "Feature",
  "properties": {
    "addr:full":"7 Coal Wharf Rd London Greater London W12 8LZ",
    "addr:housenumber":"7",
    "addr:postcode":"w12 8lz",
    "addr:street":"Coal Wharf Rd",
    "iso:country":"GB",
    "sg:address":"7 Coal Wharf Rd",
    "sg:city":"London",
    "sg:classifiers":[
        {
            "category":"Autos & Motor Vehicles",
            "subcategory":"Automobile Sales",
            "type":"Retail Goods"
        }
    ],
    "sg:postcode":"W12 8LZ",
    "sg:province":"Greater London",
    "sg:tags":[
        "car"
    ],
    "wof:name":"Brown,D,",
    "wof:placetype":"venue"
},
  "geometry": {"coordinates":[-0.2179500014,51.504901886],"type":"Point"}
}