{
  "type": "Feature",
  "properties": {
    "iso:country":"GB",
    "sg:address":"Unit 9 Stable Hobba, Newlyn",
    "sg:city":"Penzance",
    "sg:classifiers":[
        {
            "category":"Shopping",
            "subcategory":"Bicycles & Sporting Goods",
            "type":"Retail Goods"
        }
    ],
    "sg:phone":"+44 1736 331666",
    "sg:postcode":"TR20 8TL",
    "sg:province":"Cornwall",
    "sg:tags":[
        "equipment",
        "marine",
        "supply"
    ],
    "wof:name":"Keith Gruzelier",
    "wof:placetype":"venue"
},
  "geometry": {"coordinates":[-5.5605998039,50.1090888977],"type":"Point"}
}