{
  "type": "Feature",
  "properties": {
    "iso:country":"GB",
    "sg:address":"16 High Street, Middleton Cheney",
    "sg:city":"Banbury",
    "sg:classifiers":[
        {
            "category":"Real Estate",
            "subcategory":"Real Estate Services",
            "type":"Services"
        },
        {
            "category":"Building & Trades",
            "subcategory":"Construction",
            "type":"Services"
        }
    ],
    "sg:phone":"+44 1295 711137",
    "sg:postcode":"OX17 2PB",
    "sg:province":"Northamptonshire",
    "sg:tags":[
        "builder"
    ],
    "wof:name":"JAMES BROS. (BUILDING SERVICES CONTRACTOR) LTD",
    "wof:placetype":"venue"
},
  "geometry": {"coordinates":[-1.273601,52.073307],"type":"Point"}
}