{
  "type": "Feature",
  "properties": {
    "addr:full":"Cromwell Industrial Estate, Staffa Road London Greater London E10 7QZ",
    "addr:postcode":"e10 7qz",
    "addr:street":"Cromwell Industrial Estate Staffa Road",
    "iso:country":"GB",
    "sg:address":"Cromwell Industrial Estate, Staffa Road",
    "sg:city":"London",
    "sg:classifiers":[
        {
            "category":"Fast Food",
            "type":"Food & Drink"
        }
    ],
    "sg:phone":"+44 20 8556 0485",
    "sg:postcode":"E10 7QZ",
    "sg:province":"Greater London",
    "sg:tags":[
        "delivery",
        "away",
        "take",
        "outlet",
        "meal"
    ],
    "wof:name":"Albatros Trading Ltd.",
    "wof:placetype":"venue"
},
  "geometry": {"coordinates":[-0.03777,51.56955],"type":"Point"}
}