{
  "type": "Feature",
  "properties": {
    "addr:full":"1053 London Rd Leigh On Sea Essex SS9 3JP",
    "addr:housenumber":"1053",
    "addr:postcode":"ss9 3jp",
    "addr:street":"London Rd",
    "iso:country":"GB",
    "sg:address":"1053 London Rd",
    "sg:city":"Leigh On Sea",
    "sg:classifiers":[
        {
            "category":"Autos & Motor Vehicles",
            "subcategory":"Automobile Sales",
            "type":"Retail Goods"
        }
    ],
    "sg:phone":"+44 1702 480218",
    "sg:postcode":"SS9 3JP",
    "sg:province":"Essex",
    "sg:tags":[
        "commercial"
    ],
    "wof:name":"Motorlink",
    "wof:placetype":"venue"
},
  "geometry": {"coordinates":[0.663991,51.547504],"type":"Point"}
}