{
  "type": "Feature",
  "properties": {
    "iso:country":"GB",
    "sg:address":"11 Fistral Avenue, Heald Green",
    "sg:city":"Cheadle",
    "sg:classifiers":[
        {
            "category":"Social Services",
            "subcategory":"Adult Care",
            "type":"Services"
        }
    ],
    "sg:postcode":"SK8 3HB",
    "sg:province":"Cheshire",
    "sg:tags":[
        "domestic",
        "cleaning"
    ],
    "wof:name":"Carol Pearce",
    "wof:placetype":"venue"
},
  "geometry": {"coordinates":[-2.2240049839,53.3679580688],"type":"Point"}
}