{
  "type": "Feature",
  "properties": {
    "addr:full":"21 Maple Drive Larkhall South Lanarkshire ML9 2AR",
    "addr:housenumber":"21",
    "addr:postcode":"ml9 2ar",
    "addr:street":"Maple Drive",
    "iso:country":"GB",
    "sg:address":"21 Maple Drive",
    "sg:city":"Larkhall",
    "sg:classifiers":[
        {
            "category":"Organizations",
            "subcategory":"Membership Organization",
            "type":"Services"
        },
        {
            "category":"Professional",
            "subcategory":"Computer Services",
            "type":"Services"
        }
    ],
    "sg:postcode":"ML9 2AR",
    "sg:province":"South Lanarkshire",
    "sg:tags":[
        "club",
        "information",
        "business"
    ],
    "wof:name":"Clyde Valley Project Management Ltd.",
    "wof:placetype":"venue"
},
  "geometry": {"coordinates":[-3.975004,55.746838],"type":"Point"}
}