{
  "type": "Feature",
  "properties": {
    "iso:country":"GB",
    "sg:address":"Courthope Road",
    "sg:city":"Greenford",
    "sg:classifiers":[
        {
            "category":"Organizations",
            "subcategory":"Political Organization",
            "type":"Services"
        }
    ],
    "sg:phone":"+44 20 8578 5912",
    "sg:postcode":"UB6 8PZ",
    "sg:province":"Greater London",
    "sg:tags":[
        "party"
    ],
    "wof:name":"Ealing North Conservative Association",
    "wof:placetype":"venue"
},
  "geometry": {"coordinates":[-0.347288,51.538631],"type":"Point"}
}