{
  "type": "Feature",
  "properties": {
    "iso:country":"GB",
    "sg:address":"149 Toft Hill",
    "sg:city":"Bishop Auckland",
    "sg:classifiers":[
        {
            "category":"Shopping",
            "subcategory":"Department Store",
            "type":"Retail Goods"
        }
    ],
    "sg:postcode":"DL14 0JB",
    "sg:province":"Durham",
    "wof:name":"J P & S A Mulgrew Post Office Stores",
    "wof:placetype":"venue"
},
  "geometry": {"coordinates":[-1.765294,54.649139],"type":"Point"}
}