{
  "type": "Feature",
  "properties": {
    "iso:country":"GB",
    "sg:address":"7 Churchfields Road, Solkingham",
    "sg:city":"Sleaford",
    "sg:classifiers":[
        {
            "category":"Shopping",
            "type":"Retail Goods"
        }
    ],
    "sg:phone":"+44 1529 497513",
    "sg:postcode":"NG34 0TR",
    "sg:province":"Lincolnshire",
    "sg:tags":[
        "equipment",
        "clothing",
        "safety"
    ],
    "wof:name":"Playsafe",
    "wof:placetype":"venue"
},
  "geometry": {"coordinates":[-0.415426,52.88937],"type":"Point"}
}