{
  "type": "Feature",
  "properties": {
    "addr:full":"53 Frewin Road, Wandsworth Common London Greater London SW18 3LR",
    "addr:housenumber":"53",
    "addr:postcode":"sw18 3lr",
    "addr:street":"Frewin Road",
    "iso:country":"GB",
    "sg:address":"53 Frewin Road, Wandsworth Common",
    "sg:city":"London",
    "sg:classifiers":[
        {
            "category":"Real Estate",
            "subcategory":"Developer",
            "type":"Services"
        }
    ],
    "sg:phone":"+44 20 8874 4555",
    "sg:postcode":"SW18 3LR",
    "sg:province":"Greater London",
    "sg:tags":[
        "property"
    ],
    "wof:name":"Hunts Cross Ltd.",
    "wof:placetype":"venue"
},
  "geometry": {"coordinates":[-0.176367,51.443855],"type":"Point"}
}