{
  "type": "Feature",
  "properties": {
    "iso:country":"GB",
    "sg:address":"73 Llewellyn St",
    "sg:city":"Pentre",
    "sg:classifiers":[
        {
            "category":"Retail",
            "subcategory":"Repair Shop",
            "type":"Services"
        }
    ],
    "sg:postcode":"CF41 7BS",
    "sg:province":"Rhondda, Cynon, Taff",
    "sg:tags":[
        "radio",
        "television",
        "video"
    ],
    "wof:name":"Davies,R,",
    "wof:placetype":"venue"
},
  "geometry": {"coordinates":[-3.489643,51.652363],"type":"Point"}
}