{
  "type": "Feature",
  "properties": {
    "addr:full":"High Street, Queen Camel Yeovil Dorset BA22 7NJ",
    "addr:postcode":"ba22 7nj",
    "addr:street":"High Street",
    "iso:country":"GB",
    "sg:address":"High Street, Queen Camel",
    "sg:city":"Yeovil",
    "sg:classifiers":[
        {
            "category":"Bars & Pubs",
            "type":"Food & Drink"
        },
        {
            "category":"Community Center",
            "subcategory":"Social",
            "type":"Public Place"
        }
    ],
    "sg:phone":"+44 1935 850456",
    "sg:postcode":"BA22 7NJ",
    "sg:province":"Dorset",
    "sg:tags":[
        "pubs",
        "house",
        "inn",
        "activity"
    ],
    "wof:name":"Mildmay Arms",
    "wof:placetype":"venue"
},
  "geometry": {"coordinates":[-2.5769040585,51.0196990967],"type":"Point"}
}