{
  "type": "Feature",
  "properties": {
    "addr:full":"80 High Street, Clapham Bedford Bedfordshire MK41 6BW",
    "addr:housenumber":"80",
    "addr:postcode":"mk41 6bw",
    "addr:street":"High Street",
    "iso:country":"GB",
    "sg:address":"80 High Street, Clapham",
    "sg:city":"Bedford",
    "sg:classifiers":[
        {
            "category":"Retail",
            "subcategory":"Auto Repair",
            "type":"Services"
        }
    ],
    "sg:phone":"+44 1234 218462",
    "sg:postcode":"MK41 6BW",
    "sg:province":"Bedfordshire",
    "sg:tags":[
        "modification",
        "garage"
    ],
    "wof:name":"North Beds Diesel Electrics Ltd.",
    "wof:placetype":"venue"
},
  "geometry": {"coordinates":[-0.4939970076,52.1607170105],"type":"Point"}
}