{
  "type": "Feature",
  "properties": {
    "addr:full":"32 Springfield Road Stroud Gloucestershire GL5 4RE",
    "addr:housenumber":"32",
    "addr:postcode":"gl5 4re",
    "addr:street":"Springfield Road",
    "iso:country":"GB",
    "sg:address":"32 Springfield Road",
    "sg:city":"Stroud",
    "sg:classifiers":[
        {
            "category":"Building & Trades",
            "subcategory":"Construction",
            "type":"Services"
        }
    ],
    "sg:postcode":"GL5 4RE",
    "sg:province":"Gloucestershire",
    "sg:tags":[
        "builder"
    ],
    "wof:name":"Martin Driver",
    "wof:placetype":"venue"
},
  "geometry": {"coordinates":[-2.2488019466,51.7498626709],"type":"Point"}
}