{
  "type": "Feature",
  "properties": {
    "addr:full":"16 Park Street, Breaston Derby Derbyshire DE72 3AD",
    "addr:housenumber":"16",
    "addr:postcode":"de72 3ad",
    "addr:street":"Park Street",
    "iso:country":"GB",
    "sg:address":"16 Park Street, Breaston",
    "sg:city":"Derby",
    "sg:classifiers":[
        {
            "category":"Real Estate",
            "subcategory":"Developer",
            "type":"Services"
        },
        {
            "category":"Building & Trades",
            "subcategory":"Construction",
            "type":"Services"
        }
    ],
    "sg:phone":"+44 1332 875164",
    "sg:postcode":"DE72 3AD",
    "sg:province":"Derbyshire",
    "sg:tags":[
        "builder",
        "property"
    ],
    "wof:name":"Belvoir Developments",
    "wof:placetype":"venue"
},
  "geometry": {"coordinates":[-1.3094,52.900127],"type":"Point"}
}