{
  "type": "Feature",
  "properties": {
    "iso:country":"GB",
    "sg:address":"4b Dock Road, Connah's Quay",
    "sg:city":"Deeside",
    "sg:classifiers":[
        {
            "category":"Professional",
            "subcategory":"Testing Lab",
            "type":"Services"
        }
    ],
    "sg:phone":"+44 1244 830431",
    "sg:postcode":"CH5 4DS",
    "sg:province":"Flintshire",
    "sg:tags":[
        "mot"
    ],
    "wof:name":"Chapman's Garage",
    "wof:placetype":"venue"
},
  "geometry": {"coordinates":[-3.05876,53.220261],"type":"Point"}
}