{
  "type": "Feature",
  "properties": {
    "iso:country":"GB",
    "sg:address":"Bennet Rd",
    "sg:city":"Reading",
    "sg:classifiers":[
        {
            "category":"Arena",
            "subcategory":"Sports Club",
            "type":"Entertainment"
        }
    ],
    "sg:phone":"+44 118 986 3161",
    "sg:postcode":"RG2 0JL",
    "sg:province":"Berkshire",
    "sg:tags":[
        "ground"
    ],
    "wof:name":"Allied Presentations Ltd",
    "wof:placetype":"venue"
},
  "geometry": {"coordinates":[-0.980055,51.425907],"type":"Point"}
}