{
  "type": "Feature",
  "properties": {
    "iso:country":"GB",
    "sg:address":"6 Jacobs Yard, Middle Barton",
    "sg:city":"Chipping Norton",
    "sg:classifiers":[
        {
            "category":"Professional",
            "subcategory":"Accounting & Tax Preparation",
            "type":"Services"
        }
    ],
    "sg:phone":"+44 1869 347666",
    "sg:postcode":"OX7 7BY",
    "sg:province":"Gloucestershire",
    "sg:tags":[
        "accountant",
        "activity"
    ],
    "wof:name":"Potts & Co.",
    "wof:placetype":"venue"
},
  "geometry": {"coordinates":[-1.36283,51.92841],"type":"Point"}
}