{
  "type": "Feature",
  "properties": {
    "iso:country":"GB",
    "sg:address":"High Street Chambers, High Street",
    "sg:city":"Loughborough",
    "sg:classifiers":[
        {
            "category":"Travel",
            "subcategory":"Travel Agent",
            "type":"Entertainment"
        },
        {
            "category":"Recreation",
            "subcategory":"Gun Range",
            "type":"Entertainment"
        }
    ],
    "sg:phone":"+44 1509 236001",
    "sg:postcode":"LE11 2PZ",
    "sg:province":"Leicestershire",
    "sg:tags":[
        "operator",
        "tour",
        "agency",
        "activity"
    ],
    "wof:name":"Laver Holidays Ltd",
    "wof:placetype":"venue"
},
  "geometry": {"coordinates":[-1.205009,52.771358],"type":"Point"}
}