{
  "type": "Feature",
  "properties": {
    "addr:full":"Unit 4 Basildon Essex SS15 6SS",
    "addr:housenumber":"unit 4",
    "addr:postcode":"ss15 6ss",
    "iso:country":"GB",
    "sg:address":"Unit 4",
    "sg:city":"Basildon",
    "sg:classifiers":[
        {
            "category":"Building & Trades",
            "subcategory":"Cleaning & Sanitation",
            "type":"Services"
        }
    ],
    "sg:phone":"+44 1268 545400",
    "sg:postcode":"SS15 6SS",
    "sg:province":"Essex",
    "sg:tags":[
        "commercial"
    ],
    "wof:name":"Beaver Cleaning & Maintenance Services",
    "wof:placetype":"venue"
},
  "geometry": {"coordinates":[0.409336,51.57513],"type":"Point"}
}