{
  "type": "Feature",
  "properties": {
    "addr:full":"148 New Road Bromsgrove Worcestershire B60 2LE",
    "addr:housenumber":"148",
    "addr:postcode":"b60 2le",
    "addr:street":"New Road",
    "iso:country":"GB",
    "sg:address":"148 New Road",
    "sg:city":"Bromsgrove",
    "sg:classifiers":[
        {
            "category":"Home & Garden",
            "subcategory":"Furniture",
            "type":"Retail Goods"
        }
    ],
    "sg:phone":"+44 1527 871626",
    "sg:postcode":"B60 2LE",
    "sg:province":"Worcestershire",
    "wof:name":"James Design Furnishings Ltd.",
    "wof:placetype":"venue"
},
  "geometry": {"coordinates":[-2.048658,52.323353],"type":"Point"}
}