{
  "type": "Feature",
  "properties": {
    "addr:full":"14 Allerton Drive, Nether Poppleton York North Yorkshire YO26 6HN",
    "addr:housenumber":"14",
    "addr:postcode":"yo26 6hn",
    "addr:street":"Allerton Drive",
    "iso:country":"GB",
    "sg:address":"14 Allerton Drive, Nether Poppleton",
    "sg:city":"York",
    "sg:classifiers":[
        {
            "category":"Personal",
            "subcategory":"Beauty Salon",
            "type":"Services"
        }
    ],
    "sg:postcode":"YO26 6HN",
    "sg:province":"North Yorkshire",
    "sg:tags":[
        "unisex",
        "hairdresser"
    ],
    "wof:name":"Heather Wilson Hair Design",
    "wof:placetype":"venue"
},
  "geometry": {"coordinates":[-1.148891,53.985043],"type":"Point"}
}