{
  "type": "Feature",
  "properties": {
    "iso:country":"GB",
    "sg:address":"1 Otter Court, Manaton Close",
    "sg:city":"Exeter",
    "sg:classifiers":[
        {
            "category":"Manufacturing",
            "subcategory":"Petroleum Products",
            "type":"Manufacturing & Wholesale Goods"
        }
    ],
    "sg:phone":"+44 1392 824090",
    "sg:postcode":"EX2 8PF",
    "sg:province":"Devon",
    "sg:tags":[
        "double",
        "glazing"
    ],
    "wof:name":"Interplas Windows",
    "wof:placetype":"venue"
},
  "geometry": {"coordinates":[-3.524668932,50.6979598999],"type":"Point"}
}