{
  "type": "Feature",
  "properties": {
    "addr:full":"162 High Street Ryde Isle of Wight PO33 2HT",
    "addr:housenumber":"162",
    "addr:postcode":"po33 2ht",
    "addr:street":"High Street",
    "iso:country":"GB",
    "sg:address":"162 High Street",
    "sg:city":"Ryde",
    "sg:classifiers":[
        {
            "category":"Shopping",
            "subcategory":"Hobbies, Toys, & Games",
            "type":"Retail Goods"
        }
    ],
    "sg:phone":"+44 1983 811466",
    "sg:postcode":"PO33 2HT",
    "sg:province":"Isle of Wight",
    "sg:tags":[
        "shop",
        "toy"
    ],
    "wof:name":"Toys 'N' Things",
    "wof:placetype":"venue"
},
  "geometry": {"coordinates":[-1.163301,50.728027],"type":"Point"}
}