{
  "type": "Feature",
  "properties": {
    "addr:full":"43-45 Ulster Avenue Ipswich Suffolk IP1 5JS",
    "addr:housenumber":"43-45",
    "addr:postcode":"ip1 5js",
    "addr:street":"Ulster Avenue",
    "iso:country":"GB",
    "sg:address":"43-45 Ulster Avenue",
    "sg:city":"Ipswich",
    "sg:classifiers":[
        {
            "category":"Shopping",
            "subcategory":"News",
            "type":"Retail Goods"
        }
    ],
    "sg:phone":"+44 1473 741456",
    "sg:postcode":"IP1 5JS",
    "sg:province":"Suffolk",
    "sg:tags":[
        "newsagent"
    ],
    "wof:name":"The Paper Shop",
    "wof:placetype":"venue"
},
  "geometry": {"coordinates":[1.118431,52.075199],"type":"Point"}
}