{
  "type": "Feature",
  "properties": {
    "iso:country":"GB",
    "sg:address":"162 Romsey Road",
    "sg:city":"Southampton",
    "sg:classifiers":[
        {
            "category":"Professional",
            "subcategory":"Employment Agencies",
            "type":"Services"
        }
    ],
    "sg:phone":"+44 23 8078 5277",
    "sg:postcode":"SO16 4DQ",
    "sg:province":"Hampshire",
    "sg:tags":[
        "consultant"
    ],
    "wof:name":"Temps Staff Bureau",
    "wof:placetype":"venue"
},
  "geometry": {"coordinates":[-1.441747,50.925991],"type":"Point"}
}