{
  "type": "Feature",
  "properties": {
    "addr:full":"36 Drummond Road Skegness Lincolnshire PE25 3EB",
    "addr:housenumber":"36",
    "addr:postcode":"pe25 3eb",
    "addr:street":"Drummond Road",
    "iso:country":"GB",
    "sg:address":"36 Drummond Road",
    "sg:city":"Skegness",
    "sg:classifiers":[
        {
            "category":"Travel",
            "subcategory":"Hotels & Motels",
            "type":"Entertainment"
        }
    ],
    "sg:phone":"+44 1754 763690",
    "sg:postcode":"PE25 3EB",
    "sg:province":"Lincolnshire",
    "wof:name":"Fairfax Hotel",
    "wof:placetype":"venue"
},
  "geometry": {"coordinates":[0.3424740136,53.1401176453],"type":"Point"}
}