{
  "type": "Feature",
  "properties": {
    "addr:full":"Toft Hill Hall, Toft Hill Bishop Auckland Durham DL14 0PU",
    "addr:postcode":"dl14 0pu",
    "addr:street":"Toft;Toft Hill",
    "iso:country":"GB",
    "sg:address":"Toft Hill Hall, Toft Hill",
    "sg:city":"Bishop Auckland",
    "sg:classifiers":[
        {
            "category":"Farming",
            "subcategory":"Livestock Farm",
            "type":"Manufacturing & Wholesale Goods"
        }
    ],
    "sg:phone":"+44 1388 833765",
    "sg:postcode":"DL14 0PU",
    "sg:province":"Durham",
    "sg:tags":[
        "others"
    ],
    "wof:name":"N E & G E Raw",
    "wof:placetype":"venue"
},
  "geometry": {"coordinates":[-1.751534,54.648159],"type":"Point"}
}