{
  "type": "Feature",
  "properties": {
    "iso:country":"GB",
    "sg:address":"2 Beza Road, Hunslet",
    "sg:city":"Leeds",
    "sg:classifiers":[
        {
            "category":"Manufacturing",
            "subcategory":"Wood Products",
            "type":"Manufacturing & Wholesale Goods"
        }
    ],
    "sg:phone":"+44 1924 496591",
    "sg:postcode":"LS10 2BR",
    "sg:province":"West Yorkshire",
    "wof:name":"Renaissance Interiors Ltd.",
    "wof:placetype":"venue"
},
  "geometry": {"coordinates":[-1.532775,53.774677],"type":"Point"}
}