{
  "type": "Feature",
  "properties": {
    "addr:full":"216 The Broad Marsh Centre Nottingham Nottinghamshire NG1 7LR",
    "addr:housenumber":"216",
    "addr:postcode":"ng1 7lr",
    "addr:street":"The",
    "iso:country":"GB",
    "sg:address":"216 The Broad Marsh Centre",
    "sg:city":"Nottingham",
    "sg:classifiers":[
        {
            "category":"Retail",
            "subcategory":"Repair Shop",
            "type":"Services"
        },
        {
            "category":"Shopping",
            "subcategory":"Luggage & Leather Goods",
            "type":"Retail Goods"
        }
    ],
    "sg:phone":"+44 115 959 8288",
    "sg:postcode":"NG1 7LR",
    "sg:province":"Nottinghamshire",
    "sg:tags":[
        "leathergoods"
    ],
    "wof:name":"Leatherland Neki Fashions",
    "wof:placetype":"venue"
},
  "geometry": {"coordinates":[-1.143924,52.949226],"type":"Point"}
}