{
  "type": "Feature",
  "properties": {
    "iso:country":"GB",
    "sg:address":"12 Burley Hill Drive",
    "sg:city":"Leeds",
    "sg:classifiers":[
        {
            "category":"Retail",
            "subcategory":"Auto Repair",
            "type":"Services"
        }
    ],
    "sg:postcode":"LS4 2SZ",
    "sg:province":"West Yorkshire",
    "sg:tags":[
        "modification",
        "garage"
    ],
    "wof:name":"Daytona Motor Services",
    "wof:placetype":"venue"
},
  "geometry": {"coordinates":[-1.590953,53.812897],"type":"Point"}
}