{
  "type": "Feature",
  "properties": {
    "iso:country":"GB",
    "sg:address":"7 Red Lion Parade, Bridge Street",
    "sg:city":"Pinner",
    "sg:classifiers":[
        {
            "category":"Restaurant",
            "type":"Food & Drink"
        }
    ],
    "sg:phone":"+44 20 8866 2464",
    "sg:postcode":"HA5 3JD",
    "sg:province":"Greater London",
    "wof:name":"Paphos Restaurant",
    "wof:placetype":"venue"
},
  "geometry": {"coordinates":[-0.380489,51.590939],"type":"Point"}
}