{
  "type": "Feature",
  "properties": {
    "addr:full":"8 St Oswalds Street Liverpool Merseyside L13 2BY",
    "addr:housenumber":"8",
    "addr:postcode":"l13 2by",
    "addr:street":"St Oswalds Street",
    "iso:country":"GB",
    "sg:address":"8 St Oswalds Street",
    "sg:city":"Liverpool",
    "sg:classifiers":[
        {
            "category":"Shopping",
            "subcategory":"Clothing, Apparel, & Fashions",
            "type":"Retail Goods"
        }
    ],
    "sg:postcode":"L13 2BY",
    "sg:province":"Merseyside",
    "sg:tags":[
        "shop"
    ],
    "wof:name":"Fashion Force",
    "wof:placetype":"venue"
},
  "geometry": {"coordinates":[-2.914372921,53.4132499695],"type":"Point"}
}