{
  "type": "Feature",
  "properties": {
    "addr:full":"9 London Rd, Widley Waterlooville Hampshire PO7 5AT",
    "addr:housenumber":"9",
    "addr:postcode":"po7 5at",
    "addr:street":"London Rd",
    "iso:country":"GB",
    "sg:address":"9 London Rd, Widley",
    "sg:city":"Waterlooville",
    "sg:classifiers":[
        {
            "category":"Travel",
            "subcategory":"Hotels & Motels",
            "type":"Entertainment"
        }
    ],
    "sg:phone":"+44 23 9237 4079",
    "sg:postcode":"PO7 5AT",
    "sg:province":"Hampshire",
    "wof:name":"Corner House Hotel",
    "wof:placetype":"venue"
},
  "geometry": {"coordinates":[-1.0445510149,50.8679199219],"type":"Point"}
}