{
  "type": "Feature",
  "properties": {
    "iso:country":"GB",
    "sg:address":"3 St. James St",
    "sg:city":"Bolton",
    "sg:classifiers":[
        {
            "category":"Building & Trades",
            "subcategory":"Construction",
            "type":"Services"
        }
    ],
    "sg:postcode":"BL4 9SJ",
    "sg:province":"Lancashire",
    "sg:tags":[
        "builder"
    ],
    "wof:name":"Richardson,Kevin,",
    "wof:placetype":"venue"
},
  "geometry": {"coordinates":[-2.4085609913,53.5410766602],"type":"Point"}
}