{
  "type": "Feature",
  "properties": {
    "addr:full":"82 Gibraltar Road Halifax West Yorkshire HX1 4HE",
    "addr:housenumber":"82",
    "addr:postcode":"hx1 4he",
    "addr:street":"Gibraltar Road",
    "iso:country":"GB",
    "sg:address":"82 Gibraltar Road",
    "sg:city":"Halifax",
    "sg:classifiers":[
        {
            "category":"Shopping",
            "subcategory":"Clothing, Apparel, & Fashions",
            "type":"Retail Goods"
        }
    ],
    "sg:phone":"+44 1422 353137",
    "sg:postcode":"HX1 4HE",
    "sg:province":"West Yorkshire",
    "sg:tags":[
        "shop"
    ],
    "wof:name":"B Bright Fashions",
    "wof:placetype":"venue"
},
  "geometry": {"coordinates":[-1.89036,53.720634],"type":"Point"}
}