{
  "type": "Feature",
  "properties": {
    "iso:country":"GB",
    "sg:address":"101-103 The Moor",
    "sg:city":"Sheffield",
    "sg:classifiers":[
        {
            "category":"Home & Garden",
            "subcategory":"Furniture",
            "type":"Retail Goods"
        }
    ],
    "sg:postcode":"S1 4PG",
    "sg:province":"South Yorkshire",
    "wof:name":"Harveys Furnishing Group Ltd",
    "wof:placetype":"venue"
},
  "geometry": {"coordinates":[-1.473956,53.375591],"type":"Point"}
}