{
  "type": "Feature",
  "properties": {
    "addr:full":"Freeman Road, North Hykeham Lincoln Lincolnshire LN6 9AP",
    "addr:postcode":"ln6 9ap",
    "addr:street":"Freeman Road North",
    "iso:country":"GB",
    "sg:address":"Freeman Road, North Hykeham",
    "sg:city":"Lincoln",
    "sg:classifiers":[
        {
            "category":"Professional",
            "subcategory":"Engineering",
            "type":"Services"
        },
        {
            "category":"Banks & Credit Unions",
            "subcategory":"Bank",
            "type":"Services"
        }
    ],
    "sg:phone":"+44 1522 680353",
    "sg:postcode":"LN6 9AP",
    "sg:province":"Lincolnshire",
    "sg:tags":[
        "belt",
        "conveyor"
    ],
    "wof:name":"F S E Ltd.",
    "wof:placetype":"venue"
},
  "geometry": {"coordinates":[-0.59707,53.193741],"type":"Point"}
}