{
  "type": "Feature",
  "properties": {
    "iso:country":"GB",
    "sg:address":"24 Knowsley Street",
    "sg:city":"Bolton",
    "sg:classifiers":[
        {
            "category":"Food & Beverages",
            "subcategory":"Bakery",
            "type":"Retail Goods"
        }
    ],
    "sg:phone":"+44 1204 523871",
    "sg:postcode":"BL1 2AP",
    "sg:province":"Lancashire",
    "sg:tags":[
        "baker"
    ],
    "wof:name":"Hampsons",
    "wof:placetype":"venue"
},
  "geometry": {"coordinates":[-2.430551,53.581211],"type":"Point"}
}