{
  "type": "Feature",
  "properties": {
    "addr:full":"6 Ladywynd Cupar Fife KY15 4DE",
    "addr:housenumber":"6",
    "addr:postcode":"ky15 4de",
    "addr:street":"Ladywynd Cupar",
    "iso:country":"GB",
    "sg:address":"6 Ladywynd",
    "sg:city":"Cupar",
    "sg:classifiers":[
        {
            "category":"Personal",
            "subcategory":"Beauty Salon",
            "type":"Services"
        }
    ],
    "sg:postcode":"KY15 4DE",
    "sg:province":"Fife",
    "sg:tags":[
        "unisex",
        "hairdresser"
    ],
    "wof:name":"Uppercut",
    "wof:placetype":"venue"
},
  "geometry": {"coordinates":[-3.0135540962,56.3199882507],"type":"Point"}
}