{
  "type": "Feature",
  "properties": {
    "iso:country":"GB",
    "sg:address":"177 Hawkes Mill Lane, Allesley",
    "sg:city":"Coventry",
    "sg:classifiers":[
        {
            "category":"Transit Center",
            "subcategory":"Passenger",
            "type":"Transportation"
        }
    ],
    "sg:phone":"+44 24 7640 2737",
    "sg:postcode":"CV5 9FP",
    "sg:province":"West Midlands",
    "sg:tags":[
        "boarding",
        "kennel",
        "catteries"
    ],
    "wof:name":"Chatz Cattery",
    "wof:placetype":"venue"
},
  "geometry": {"coordinates":[-1.561733,52.4417],"type":"Point"}
}