{
  "type": "Feature",
  "properties": {
    "iso:country":"GB",
    "sg:address":"Unit 7/8 Wansdyke Workshops, Unity Road, Keynsham",
    "sg:city":"Bristol",
    "sg:classifiers":[
        {
            "category":"Manufacturing",
            "subcategory":"Metals",
            "type":"Manufacturing & Wholesale Goods"
        }
    ],
    "sg:postcode":"BS31 1NH",
    "sg:province":"City of Bristol",
    "sg:tags":[
        "steel",
        "fabricator",
        "erectors"
    ],
    "wof:name":"Fab-Weld Keynsham",
    "wof:placetype":"venue"
},
  "geometry": {"coordinates":[-2.4964289665,51.4144706726],"type":"Point"}
}