{
  "type": "Feature",
  "properties": {
    "iso:country":"GB",
    "sg:address":"Binders Ind Est, Cryers Hill, Hazlemere",
    "sg:city":"High Wycombe",
    "sg:classifiers":[
        {
            "category":"Utilities",
            "subcategory":"Natural Gas",
            "type":"Services"
        }
    ],
    "sg:phone":"+44 1494 816576",
    "sg:postcode":"HP15 7NU",
    "sg:province":"Buckinghamshire",
    "sg:tags":[
        "control",
        "energy",
        "management",
        "system"
    ],
    "wof:name":"Croft Drive Ltd",
    "wof:placetype":"venue"
},
  "geometry": {"coordinates":[-0.708729,51.651031],"type":"Point"}
}