{
  "type": "Feature",
  "properties": {
    "addr:full":"Eureka, Eglwyswrw Crymych Pembrokeshire SA41 3UJ",
    "addr:postcode":"sa41 3uj",
    "iso:country":"GB",
    "sg:address":"Eureka, Eglwyswrw",
    "sg:city":"Crymych",
    "sg:classifiers":[
        {
            "category":"Retail",
            "subcategory":"Driving School",
            "type":"Services"
        }
    ],
    "sg:phone":"+44 1239 891377",
    "sg:postcode":"SA41 3UJ",
    "sg:province":"Pembrokeshire",
    "wof:name":"Selby School of Motoring",
    "wof:placetype":"venue"
},
  "geometry": {"coordinates":[-4.648454,51.971241],"type":"Point"}
}