{
  "type": "Feature",
  "properties": {
    "iso:country":"GB",
    "sg:address":"22 Oughtrington Lane",
    "sg:city":"Lymm",
    "sg:classifiers":[
        {
            "category":"Wholesale",
            "subcategory":"Scrap",
            "type":"Manufacturing & Wholesale Goods"
        }
    ],
    "sg:phone":"+44 1925 756376",
    "sg:postcode":"WA13 0RD",
    "sg:province":"Cheshire",
    "sg:tags":[
        "waste",
        "metal"
    ],
    "wof:name":"Lymm Metals",
    "wof:placetype":"venue"
},
  "geometry": {"coordinates":[-2.460357,53.376835],"type":"Point"}
}