{
  "type": "Feature",
  "properties": {
    "addr:full":"421 High Road Ilford Essex IG1 1TR",
    "addr:housenumber":"421",
    "addr:postcode":"ig1 1tr",
    "addr:street":"High Road",
    "iso:country":"GB",
    "sg:address":"421 High Road",
    "sg:city":"Ilford",
    "sg:classifiers":[
        {
            "category":"Retail",
            "subcategory":"Auto Repair",
            "type":"Services"
        }
    ],
    "sg:postcode":"IG1 1TR",
    "sg:province":"Essex",
    "sg:tags":[
        "modification",
        "garage"
    ],
    "wof:name":"C B Autos",
    "wof:placetype":"venue"
},
  "geometry": {"coordinates":[0.085202001,51.561542511],"type":"Point"}
}