{
  "type": "Feature",
  "properties": {
    "addr:full":"31 Edward Street Morecambe Lancashire LA4 4BL",
    "addr:housenumber":"31",
    "addr:postcode":"la4 4bl",
    "addr:street":"Edward Street",
    "iso:country":"GB",
    "sg:address":"31 Edward Street",
    "sg:city":"Morecambe",
    "sg:classifiers":[
        {
            "category":"Organizations",
            "subcategory":"Membership Organization",
            "type":"Services"
        }
    ],
    "sg:postcode":"LA4 4BL",
    "sg:province":"Lancashire",
    "sg:tags":[
        "club"
    ],
    "wof:name":"Royal British Legion (Morecambe & Heysham) Club Ltd.",
    "wof:placetype":"venue"
},
  "geometry": {"coordinates":[-2.86818,54.071243],"type":"Point"}
}