{
  "type": "Feature",
  "properties": {
    "iso:country":"GB",
    "sg:address":"65 Wimbledon Hill Road",
    "sg:city":"London",
    "sg:classifiers":[
        {
            "category":"Farming",
            "subcategory":"Nursery",
            "type":"Manufacturing & Wholesale Goods"
        }
    ],
    "sg:phone":"+44 20 8946 7467",
    "sg:postcode":"SW19 7QP",
    "sg:province":"Greater London",
    "sg:tags":[
        "creche"
    ],
    "wof:name":"The Hill Kindergarten",
    "wof:placetype":"venue"
},
  "geometry": {"coordinates":[-0.2120659947,51.4240531921],"type":"Point"}
}