{
  "type": "Feature",
  "properties": {
    "iso:country":"GB",
    "sg:address":"3 Armour Street",
    "sg:city":"Glasgow",
    "sg:classifiers":[
        {
            "category":"Autos & Motor Vehicles",
            "subcategory":"Auto Supplies",
            "type":"Retail Goods"
        }
    ],
    "sg:phone":"+44 141 402 5601",
    "sg:postcode":"G31 1DG",
    "sg:province":"Glasgow City",
    "sg:tags":[
        "gearbox"
    ],
    "wof:name":"M R Scanlon",
    "wof:placetype":"venue"
},
  "geometry": {"coordinates":[-4.231729,55.85693],"type":"Point"}
}