{
  "type": "Feature",
  "properties": {
    "iso:country":"GB",
    "sg:address":"Unit 1 St Johns Road",
    "sg:city":"Macclesfield",
    "sg:classifiers":[
        {
            "category":"Building & Trades",
            "subcategory":"Construction",
            "type":"Services"
        }
    ],
    "sg:postcode":"SK11 6XW",
    "sg:province":"Cheshire",
    "sg:tags":[
        "joinery"
    ],
    "wof:name":"Stephen Kirk",
    "wof:placetype":"venue"
},
  "geometry": {"coordinates":[-2.129234,53.255264],"type":"Point"}
}