{
  "type": "Feature",
  "properties": {
    "addr:full":"Unit 1 St Johns Road Macclesfield Cheshire SK11 6XW",
    "addr:housenumber":"unit 1",
    "addr:postcode":"sk11 6xw",
    "addr:street":"St Johns Road",
    "iso:country":"GB",
    "sg:address":"Unit 1 St Johns Road",
    "sg:city":"Macclesfield",
    "sg:classifiers":[
        {
            "category":"Building & Trades",
            "subcategory":"Construction",
            "type":"Services"
        }
    ],
    "sg:postcode":"SK11 6XW",
    "sg:province":"Cheshire",
    "sg:tags":[
        "joinery"
    ],
    "wof:name":"Stephen Kirk",
    "wof:placetype":"venue"
},
  "geometry": {"coordinates":[-2.129234,53.255264],"type":"Point"}
}