{
  "type": "Feature",
  "properties": {
    "addr:full":"218 St Marys Lane Upminster Essex RM14 3DH",
    "addr:housenumber":"218",
    "addr:postcode":"rm14 3dh",
    "addr:street":"St Marys Lane",
    "iso:country":"GB",
    "sg:address":"218 St Marys Lane",
    "sg:city":"Upminster",
    "sg:classifiers":[
        {
            "category":"Food & Beverages",
            "subcategory":"Supermarket",
            "type":"Retail Goods"
        }
    ],
    "sg:phone":"+44 1708 251191",
    "sg:postcode":"RM14 3DH",
    "sg:province":"Essex",
    "wof:name":"Somerfield",
    "wof:placetype":"venue"
},
  "geometry": {"coordinates":[0.2534129918,51.5567474365],"type":"Point"}
}