{
  "type": "Feature",
  "properties": {
    "addr:full":"29 Pheasant Way, Yaxley Peterborough Cambridgeshire PE7 3HN",
    "addr:housenumber":"29",
    "addr:postcode":"pe7 3hn",
    "addr:street":"Pheasant Way",
    "iso:country":"GB",
    "sg:address":"29 Pheasant Way, Yaxley",
    "sg:city":"Peterborough",
    "sg:classifiers":[
        {
            "category":"Home & Garden",
            "subcategory":"Home Furnishings",
            "type":"Retail Goods"
        }
    ],
    "sg:phone":"+44 1733 240777",
    "sg:postcode":"PE7 3HN",
    "sg:province":"Cambridgeshire",
    "sg:tags":[
        "furnishers",
        "planner",
        "kitchen"
    ],
    "wof:name":"Kitchen Care",
    "wof:placetype":"venue"
},
  "geometry": {"coordinates":[-0.268281,52.516663],"type":"Point"}
}