{
  "type": "Feature",
  "properties": {
    "iso:country":"GB",
    "sg:address":"361 Staniforth Road",
    "sg:city":"Sheffield",
    "sg:classifiers":[
        {
            "category":"Professional",
            "subcategory":"Engineering",
            "type":"Services"
        }
    ],
    "sg:phone":"+44 114 244 2542",
    "sg:postcode":"S9 3FP",
    "sg:province":"South Yorkshire",
    "sg:tags":[
        "engineer"
    ],
    "wof:name":"Binks & Walker",
    "wof:placetype":"venue"
},
  "geometry": {"coordinates":[-1.4249260426,53.389251709],"type":"Point"}
}