{
  "type": "Feature",
  "properties": {
    "addr:full":"High Street, Adderbury Banbury Northamptonshire OX17 3LS",
    "addr:postcode":"ox17 3ls",
    "addr:street":"High Street",
    "iso:country":"GB",
    "sg:address":"High Street, Adderbury",
    "sg:city":"Banbury",
    "sg:classifiers":[
        {
            "category":"Retail",
            "subcategory":"Veterinary Services",
            "type":"Services"
        }
    ],
    "sg:phone":"+44 1295 812063",
    "sg:postcode":"OX17 3LS",
    "sg:province":"Northamptonshire",
    "sg:tags":[
        "surgeon"
    ],
    "wof:name":"Beehive Veterinary Surgery",
    "wof:placetype":"venue"
},
  "geometry": {"coordinates":[-1.3097640276,52.0187911987],"type":"Point"}
}