{
  "type": "Feature",
  "properties": {
    "iso:country":"GB",
    "sg:address":"Cronehills Health Centre, Cronehills Linkway",
    "sg:city":"West Bromwich",
    "sg:classifiers":[
        {
            "category":"Health Services",
            "subcategory":"Doctor",
            "type":"Services"
        },
        {
            "category":"Health Services",
            "subcategory":"Clinic",
            "type":"Services"
        }
    ],
    "sg:phone":"+44 121 553 0277",
    "sg:postcode":"B70 8TJ",
    "sg:province":"West Midlands",
    "sg:tags":[
        "planning",
        "practitioners",
        "family",
        "centre"
    ],
    "wof:name":"T R Bassan",
    "wof:placetype":"venue"
},
  "geometry": {"coordinates":[-1.990224,52.518623],"type":"Point"}
}