{
  "type": "Feature",
  "properties": {
    "addr:full":"Lancaster App, North Killingholme Indstl, Immingham Grimsby Lincolnshire DN40 3JZ",
    "addr:postcode":"dn40 3jz",
    "iso:country":"GB",
    "sg:address":"Lancaster App, North Killingholme Indstl, Immingham",
    "sg:city":"Grimsby",
    "sg:classifiers":[
        {
            "category":"Wholesale",
            "subcategory":"Scrap",
            "type":"Manufacturing & Wholesale Goods"
        }
    ],
    "sg:postcode":"DN40 3JZ",
    "sg:province":"Lincolnshire",
    "sg:tags":[
        "breaker",
        "dismantlers"
    ],
    "wof:name":"Immingham Auto Breakers",
    "wof:placetype":"venue"
},
  "geometry": {"coordinates":[-0.2752439976,53.6421661377],"type":"Point"}
}