{
  "type": "Feature",
  "properties": {
    "iso:country":"GB",
    "sg:address":"The Surgery, East Cleveland Hospital, Alford Rd",
    "sg:city":"Saltburn By The Sea",
    "sg:classifiers":[
        {
            "category":"Health Services",
            "subcategory":"Doctor",
            "type":"Services"
        }
    ],
    "sg:phone":"+44 1287 676215",
    "sg:postcode":"TS12 2FF",
    "sg:province":"North Yorkshire",
    "sg:tags":[
        "practitioners"
    ],
    "wof:name":"Clements, B W",
    "wof:placetype":"venue"
},
  "geometry": {"coordinates":[-0.974189,54.582371],"type":"Point"}
}