{
  "type": "Feature",
  "properties": {
    "addr:full":"30 Bracken Park Gardens, Wordsley Stourbridge Staffordshire DY8 5SZ",
    "addr:housenumber":"30",
    "addr:postcode":"dy8 5sz",
    "addr:street":"Bracken Park Gardens",
    "iso:country":"GB",
    "sg:address":"30 Bracken Park Gardens, Wordsley",
    "sg:city":"Stourbridge",
    "sg:classifiers":[
        {
            "category":"Professional",
            "subcategory":"Computer Services",
            "type":"Services"
        }
    ],
    "sg:phone":"+44 1384 350320",
    "sg:postcode":"DY8 5SZ",
    "sg:province":"Staffordshire",
    "sg:tags":[
        "system",
        "software"
    ],
    "wof:name":"Premier Business Systems",
    "wof:placetype":"venue"
},
  "geometry": {"coordinates":[-2.1551930904,52.4776878357],"type":"Point"}
}