{
  "type": "Feature",
  "properties": {
    "iso:country":"GB",
    "sg:address":"136 Auchenlodment Rd",
    "sg:city":"Johnstone",
    "sg:classifiers":[
        {
            "category":"Health Services",
            "subcategory":"Nursing And Care Facility",
            "type":"Services"
        },
        {
            "category":"Social Services",
            "subcategory":"Retirement Home",
            "type":"Services"
        }
    ],
    "sg:phone":"+44 1505 337322",
    "sg:postcode":"PA5 9NX",
    "sg:province":"Renfrewshire",
    "sg:tags":[
        "residential"
    ],
    "wof:name":"Adams House",
    "wof:placetype":"venue"
},
  "geometry": {"coordinates":[-4.49404,55.826656],"type":"Point"}
}