{
  "type": "Feature",
  "properties": {
    "addr:full":"Haltoft House, Wainfleet Road, Freiston Boston Lincolnshire PE22 0PG",
    "addr:postcode":"pe22 0pg",
    "addr:street":"Wainfleet Road",
    "iso:country":"GB",
    "sg:address":"Haltoft House, Wainfleet Road, Freiston",
    "sg:city":"Boston",
    "sg:classifiers":[
        {
            "category":"Autos & Motor Vehicles",
            "subcategory":"Auto Supplies",
            "type":"Retail Goods"
        }
    ],
    "sg:phone":"+44 1205 761622",
    "sg:postcode":"PE22 0PG",
    "sg:province":"Lincolnshire",
    "sg:tags":[
        "windscreen"
    ],
    "wof:name":"Boston Windscreens",
    "wof:placetype":"venue"
},
  "geometry": {"coordinates":[0.029718,52.985161],"type":"Point"}
}