{
  "type": "Feature",
  "properties": {
    "addr:full":"162 East End Road London Greater London N2 0RU",
    "addr:housenumber":"162",
    "addr:postcode":"n2 0ru",
    "addr:street":"East End Road",
    "iso:country":"GB",
    "sg:address":"162 East End Road",
    "sg:city":"London",
    "sg:classifiers":[
        {
            "category":"Health Services",
            "subcategory":"Nursing And Care Facility",
            "type":"Services"
        },
        {
            "category":"Social Services",
            "subcategory":"Retirement Home",
            "type":"Services"
        }
    ],
    "sg:phone":"+44 20 8883 1104",
    "sg:postcode":"N2 0RU",
    "sg:province":"Greater London",
    "sg:tags":[
        "residential"
    ],
    "wof:name":"Nazareth House",
    "wof:placetype":"venue"
},
  "geometry": {"coordinates":[-0.1721689999,51.5901908875],"type":"Point"}
}