{
  "type": "Feature",
  "properties": {
    "addr:full":"Unit 15 Foxoak Enterprise Centre, 94 Foxoak Street Smethwick West Midlands B64 5DP",
    "addr:housenumber":"unit 15 foxoak;94",
    "addr:postcode":"b64 5dp",
    "addr:street":"Foxoak Street",
    "iso:country":"GB",
    "sg:address":"Unit 15 Foxoak Enterprise Centre, 94 Foxoak Street",
    "sg:city":"Smethwick",
    "sg:classifiers":[
        {
            "category":"Home & Garden",
            "subcategory":"Building Materials",
            "type":"Retail Goods"
        },
        {
            "category":"Home & Garden",
            "subcategory":"Furniture",
            "type":"Retail Goods"
        }
    ],
    "sg:postcode":"B64 5DP",
    "sg:province":"West Midlands",
    "sg:tags":[
        "plaster",
        "ware"
    ],
    "wof:name":"Alan Woodall Crafts",
    "wof:placetype":"venue"
},
  "geometry": {"coordinates":[-2.0808,52.473862],"type":"Point"}
}