{
  "type": "Feature",
  "properties": {
    "iso:country":"GB",
    "sg:address":"37 High Street",
    "sg:city":"Nairn",
    "sg:classifiers":[
        {
            "category":"Home & Garden",
            "subcategory":"Hardware",
            "type":"Retail Goods"
        }
    ],
    "sg:phone":"+44 1667 453886",
    "sg:postcode":"IV12 4AG",
    "sg:province":"Highland",
    "sg:tags":[
        "retailer",
        "diy"
    ],
    "wof:name":"Tradeway",
    "wof:placetype":"venue"
},
  "geometry": {"coordinates":[-3.8692409992,57.5841751099],"type":"Point"}
}