{
  "type": "Feature",
  "properties": {
    "addr:full":"34 Trebellan Drive Hemel Hempstead Hertfordshire HP2 5EL",
    "addr:housenumber":"34",
    "addr:postcode":"hp2 5el",
    "addr:street":"Trebellan Drive",
    "iso:country":"GB",
    "sg:address":"34 Trebellan Drive",
    "sg:city":"Hemel Hempstead",
    "sg:classifiers":[
        {
            "category":"Professional",
            "type":"Services"
        },
        {
            "category":"Social Services",
            "subcategory":"Job Training",
            "type":"Services"
        }
    ],
    "sg:phone":"+44 1442 217381",
    "sg:postcode":"HP2 5EL",
    "sg:province":"Hertfordshire",
    "sg:tags":[
        "translator",
        "interpreter",
        "translation",
        "activity"
    ],
    "wof:name":"Nicole Ferguson",
    "wof:placetype":"venue"
},
  "geometry": {"coordinates":[-0.456349,51.758049],"type":"Point"}
}