{
  "type": "Feature",
  "properties": {
    "addr:full":"74 Harrington Road Workington Cumbria CA14 2UE",
    "addr:housenumber":"74",
    "addr:postcode":"ca14 2ue",
    "addr:street":"Harrington Road",
    "iso:country":"GB",
    "sg:address":"74 Harrington Road",
    "sg:city":"Workington",
    "sg:classifiers":[
        {
            "category":"Shopping",
            "subcategory":"News",
            "type":"Retail Goods"
        }
    ],
    "sg:postcode":"CA14 2UE",
    "sg:province":"Cumbria",
    "sg:tags":[
        "newsagent"
    ],
    "wof:name":"B W Atkinson",
    "wof:placetype":"venue"
},
  "geometry": {"coordinates":[-3.547751,54.639481],"type":"Point"}
}