{
  "type": "Feature",
  "properties": {
    "iso:country":"GB",
    "sg:address":"Unit 16, Cliffe Commercial Business Park",
    "sg:city":"Huddersfield",
    "sg:classifiers":[
        {
            "category":"Manufacturing",
            "subcategory":"Motor Vehicles & Parts",
            "type":"Manufacturing & Wholesale Goods"
        }
    ],
    "sg:phone":"+44 1484 451911",
    "sg:postcode":"HD1 3JD",
    "sg:province":"West Yorkshire",
    "sg:tags":[
        "machine",
        "shop"
    ],
    "wof:name":"M O A T Engineering Ltd.",
    "wof:placetype":"venue"
},
  "geometry": {"coordinates":[-1.7965489626,53.6412086487],"type":"Point"}
}