{
  "type": "Feature",
  "properties": {
    "addr:full":"15 High Street Droitwich Worcestershire WR9 8EJ",
    "addr:housenumber":"15",
    "addr:postcode":"wr9 8ej",
    "addr:street":"High Street",
    "iso:country":"GB",
    "sg:address":"15 High Street",
    "sg:city":"Droitwich",
    "sg:classifiers":[
        {
            "category":"Home & Garden",
            "subcategory":"Home Furnishings",
            "type":"Retail Goods"
        }
    ],
    "sg:postcode":"WR9 8EJ",
    "sg:province":"Worcestershire",
    "sg:tags":[
        "blind",
        "curtain",
        "fitting"
    ],
    "wof:name":"Curtains of Quality",
    "wof:placetype":"venue"
},
  "geometry": {"coordinates":[-2.1484360695,52.2686157227],"type":"Point"}
}