{
  "type": "Feature",
  "properties": {
    "addr:full":"34 Regent Street Great Yarmouth Norfolk NR30 1RR",
    "addr:housenumber":"34",
    "addr:postcode":"nr30 1rr",
    "addr:street":"Regent Street",
    "iso:country":"GB",
    "sg:address":"34 Regent Street",
    "sg:city":"Great Yarmouth",
    "sg:classifiers":[
        {
            "category":"Shopping",
            "subcategory":"Catalog Store",
            "type":"Retail Goods"
        }
    ],
    "sg:postcode":"NR30 1RR",
    "sg:province":"Norfolk",
    "sg:tags":[
        "mail",
        "order",
        "house"
    ],
    "wof:name":"David Marshall",
    "wof:placetype":"venue"
},
  "geometry": {"coordinates":[1.726575,52.606716],"type":"Point"}
}