{
  "type": "Feature",
  "properties": {
    "addr:full":"98 Penny Meadow Ashton-under-lyne Greater Manchester OL6 6EP",
    "addr:housenumber":"98",
    "addr:postcode":"ol6 6ep",
    "addr:street":"Penny Meadow",
    "iso:country":"GB",
    "sg:address":"98 Penny Meadow",
    "sg:city":"Ashton-under-lyne",
    "sg:classifiers":[
        {
            "category":"Shopping",
            "subcategory":"Bicycles & Sporting Goods",
            "type":"Retail Goods"
        }
    ],
    "sg:postcode":"OL6 6EP",
    "sg:province":"Greater Manchester",
    "sg:tags":[
        "cycle",
        "accessory"
    ],
    "wof:name":"T P S Cycles",
    "wof:placetype":"venue"
},
  "geometry": {"coordinates":[-2.091217041,53.4899482727],"type":"Point"}
}