{
  "type": "Feature",
  "properties": {
    "addr:full":"55 Downings London Greater London E6 6WR",
    "addr:housenumber":"55",
    "addr:postcode":"e6 6wr",
    "addr:street":"Downings",
    "iso:country":"GB",
    "sg:address":"55 Downings",
    "sg:city":"London",
    "sg:classifiers":[
        {
            "category":"Professional",
            "subcategory":"Art Services",
            "type":"Services"
        }
    ],
    "sg:phone":"+44 20 7473 1383",
    "sg:postcode":"E6 6WR",
    "sg:province":"Greater London",
    "sg:tags":[
        "graphic",
        "designer"
    ],
    "wof:name":"Mughal Graphic Design",
    "wof:placetype":"venue"
},
  "geometry": {"coordinates":[0.06645,51.512691],"type":"Point"}
}