{
  "type": "Feature",
  "properties": {
    "addr:full":"58 Unicorn Avenue Coventry West Midlands CV5 7GH",
    "addr:housenumber":"58",
    "addr:postcode":"cv5 7gh",
    "addr:street":"Unicorn Avenue",
    "iso:country":"GB",
    "sg:address":"58 Unicorn Avenue",
    "sg:city":"Coventry",
    "sg:classifiers":[
        {
            "category":"Building & Trades",
            "subcategory":"Construction",
            "type":"Services"
        }
    ],
    "sg:phone":"+44 24 7646 1172",
    "sg:postcode":"CV5 7GH",
    "sg:province":"West Midlands",
    "sg:tags":[
        "glazier"
    ],
    "wof:name":"Eric Calcott",
    "wof:placetype":"venue"
},
  "geometry": {"coordinates":[-1.58264,52.416203],"type":"Point"}
}