{
  "type": "Feature",
  "properties": {
    "iso:country":"GB",
    "sg:address":"6- 7 Blythsood Square",
    "sg:city":"Glasgow",
    "sg:classifiers":[
        {
            "category":"Personal",
            "subcategory":"Beauty Salon",
            "type":"Services"
        }
    ],
    "sg:phone":"+44 141 225 8086",
    "sg:postcode":"G2 4AD",
    "sg:province":"Glasgow City",
    "sg:tags":[
        "unisex",
        "hairdresser"
    ],
    "wof:name":"Rita Rusk International Ltd.",
    "wof:placetype":"venue"
},
  "geometry": {"coordinates":[-4.2631697655,55.8640327454],"type":"Point"}
}