{
  "type": "Feature",
  "properties": {
    "addr:full":"28 Polweath Rd Penzance Cornwall TR18 3PN",
    "addr:housenumber":"28",
    "addr:postcode":"tr18 3pn",
    "addr:street":"Polweath Rd",
    "iso:country":"GB",
    "sg:address":"28 Polweath Rd",
    "sg:city":"Penzance",
    "sg:classifiers":[
        {
            "category":"Professional",
            "subcategory":"Employment Agencies",
            "type":"Services"
        }
    ],
    "sg:phone":"+44 1736 350576",
    "sg:postcode":"TR18 3PN",
    "sg:province":"Cornwall",
    "sg:tags":[
        "consultant"
    ],
    "wof:name":"Grafters",
    "wof:placetype":"venue"
},
  "geometry": {"coordinates":[-5.5397830009,50.1286697388],"type":"Point"}
}