{
  "type": "Feature",
  "properties": {
    "addr:full":"Fairway Garages, The Fairway, Millhill London Greater London NW7 3HJ",
    "addr:postcode":"nw7 3hj",
    "addr:street":"The Fairway",
    "iso:country":"GB",
    "sg:address":"Fairway Garages, The Fairway, Millhill",
    "sg:city":"London",
    "sg:classifiers":[
        {
            "category":"Retail",
            "subcategory":"Auto Repair",
            "type":"Services"
        }
    ],
    "sg:postcode":"NW7 3HJ",
    "sg:province":"Greater London",
    "sg:tags":[
        "modification",
        "garage"
    ],
    "wof:name":"Young Motor Engineers",
    "wof:placetype":"venue"
},
  "geometry": {"coordinates":[-0.25902,51.62645],"type":"Point"}
}