{
  "type": "Feature",
  "properties": {
    "iso:country":"GB",
    "sg:address":"Featherstone Farm, New Road",
    "sg:city":"Wolverhampton",
    "sg:classifiers":[
        {
            "category":"Travel",
            "subcategory":"Hotels & Motels",
            "type":"Entertainment"
        }
    ],
    "sg:phone":"+44 1902 725371",
    "sg:postcode":"WV10 7NW",
    "sg:province":"Staffordshire",
    "sg:tags":[
        "house",
        "guest"
    ],
    "wof:name":"Featherstone Farm Hotel",
    "wof:placetype":"venue"
},
  "geometry": {"coordinates":[-2.085239,52.645546],"type":"Point"}
}