{
  "type": "Feature",
  "properties": {
    "addr:full":"Frederick St South, Meadowfield Durham Durham DH7 8LZ",
    "addr:postcode":"dh7 8lz",
    "addr:street":"Frederick St",
    "iso:country":"GB",
    "sg:address":"Frederick St South, Meadowfield",
    "sg:city":"Durham",
    "sg:classifiers":[
        {
            "category":"Retail",
            "subcategory":"Auto Repair",
            "type":"Services"
        }
    ],
    "sg:phone":"+44 191 378 0284",
    "sg:postcode":"DH7 8LZ",
    "sg:province":"Durham",
    "sg:tags":[
        "modification",
        "car",
        "vehicle",
        "commercial",
        "garage"
    ],
    "wof:name":"Volksparts Of Durham Ltd",
    "wof:placetype":"venue"
},
  "geometry": {"coordinates":[-1.61983,54.750687],"type":"Point"}
}