{
  "type": "Feature",
  "properties": {
    "iso:country":"GB",
    "sg:address":"121 The Street, Rustington",
    "sg:city":"Littlehampton",
    "sg:classifiers":[
        {
            "category":"Food & Beverages",
            "subcategory":"Bakery",
            "type":"Retail Goods"
        }
    ],
    "sg:phone":"+44 1903 786144",
    "sg:postcode":"BN16 3DN",
    "sg:province":"West Sussex",
    "sg:tags":[
        "baker"
    ],
    "wof:name":"R J Pegrum",
    "wof:placetype":"venue"
},
  "geometry": {"coordinates":[-0.506217,50.810265],"type":"Point"}
}