{
  "type": "Feature",
  "properties": {
    "addr:full":"Acorn Cottage, Cossall Road, Trowell Nottingham Nottinghamshire NG9 3PG",
    "addr:postcode":"ng9 3pg",
    "addr:street":"Cossall Road",
    "iso:country":"GB",
    "sg:address":"Acorn Cottage, Cossall Road, Trowell",
    "sg:city":"Nottingham",
    "sg:classifiers":[
        {
            "category":"Building & Trades",
            "subcategory":"Construction",
            "type":"Services"
        }
    ],
    "sg:postcode":"NG9 3PG",
    "sg:province":"Nottinghamshire",
    "sg:tags":[
        "decorator",
        "painter"
    ],
    "wof:name":"F R Eley & Son",
    "wof:placetype":"venue"
},
  "geometry": {"coordinates":[-1.281635046,52.9525947571],"type":"Point"}
}