{
  "type": "Feature",
  "properties": {
    "addr:full":"Fox Centre, Edge St Kensington Greater London W8 7PN",
    "addr:postcode":"w8 7pn",
    "addr:street":"St",
    "iso:country":"GB",
    "sg:address":"Fox Centre, Edge St",
    "sg:city":"Kensington",
    "sg:classifiers":[
        {
            "category":"Government",
            "subcategory":"Office",
            "type":"Public Place"
        }
    ],
    "sg:phone":"+44 20 7727 1275",
    "sg:postcode":"W8 7PN",
    "sg:province":"Greater London",
    "sg:tags":[
        "local"
    ],
    "wof:name":"Royal Borough of Kensington & Chelsea The",
    "wof:placetype":"venue"
},
  "geometry": {"coordinates":[-0.1960200071,51.5075683594],"type":"Point"}
}