{
  "type": "Feature",
  "properties": {
    "iso:country":"GB",
    "sg:address":"Unit G3, South St",
    "sg:city":"Keighley",
    "sg:classifiers":[
        {
            "category":"Building & Trades",
            "subcategory":"Construction",
            "type":"Services"
        }
    ],
    "sg:phone":"+44 1535 608066",
    "sg:postcode":"BD21 1AG",
    "sg:province":"West Yorkshire",
    "sg:tags":[
        "welder",
        "mechanical"
    ],
    "wof:name":"Secureweld",
    "wof:placetype":"venue"
},
  "geometry": {"coordinates":[-1.911474,53.863605],"type":"Point"}
}