{
  "type": "Feature",
  "properties": {
    "addr:full":"Suites 1-4 1 John St Swindon Wiltshire SN1 1RT",
    "addr:housenumber":"1-4 1",
    "addr:postcode":"sn1 1rt",
    "addr:street":"John St",
    "iso:country":"GB",
    "sg:address":"Suites 1-4 1 John St",
    "sg:city":"Swindon",
    "sg:classifiers":[
        {
            "category":"Organizations",
            "subcategory":"Non-profit Organization",
            "type":"Services"
        }
    ],
    "sg:phone":"+44 1793 531174",
    "sg:postcode":"SN1 1RT",
    "sg:province":"Wiltshire",
    "sg:tags":[
        "organisation",
        "voluntary",
        "charity"
    ],
    "wof:name":"Shopperphone",
    "wof:placetype":"venue"
},
  "geometry": {"coordinates":[-1.7818139791,51.5617637634],"type":"Point"}
}