{
  "type": "Feature",
  "properties": {
    "iso:country":"GB",
    "sg:address":"21 High Street, Debenham",
    "sg:city":"Stowmarket",
    "sg:classifiers":[
        {
            "category":"Shopping",
            "subcategory":"Antiques",
            "type":"Retail Goods"
        },
        {
            "category":"Shopping",
            "subcategory":"Used Merchandise",
            "type":"Retail Goods"
        }
    ],
    "sg:postcode":"IP14 6QL",
    "sg:province":"Suffolk",
    "sg:tags":[
        "shop",
        "second-hand"
    ],
    "wof:name":"N A J Lanchester",
    "wof:placetype":"venue"
},
  "geometry": {"coordinates":[1.181562,52.224869],"type":"Point"}
}