{
  "type": "Feature",
  "properties": {
    "addr:full":"17 St Blaise Rd Sutton Coldfield Staffordshire B75 5NH",
    "addr:housenumber":"17",
    "addr:postcode":"b75 5nh",
    "addr:street":"St Blaise Rd",
    "iso:country":"GB",
    "sg:address":"17 St Blaise Rd",
    "sg:city":"Sutton Coldfield",
    "sg:classifiers":[
        {
            "category":"Professional",
            "subcategory":"Engineering",
            "type":"Services"
        }
    ],
    "sg:phone":"+44 121 308 0939",
    "sg:postcode":"B75 5NH",
    "sg:province":"Staffordshire",
    "sg:tags":[
        "contractor",
        "electrical",
        "engineer"
    ],
    "wof:name":"Little Sutton",
    "wof:placetype":"venue"
},
  "geometry": {"coordinates":[-1.8149180412,52.5922393799],"type":"Point"}
}