{
  "type": "Feature",
  "properties": {
    "addr:full":"24 Lawn Street Paisley Renfrewshire PA1 1HF",
    "addr:housenumber":"24",
    "addr:postcode":"pa1 1hf",
    "addr:street":"Lawn Street",
    "iso:country":"GB",
    "sg:address":"24 Lawn Street",
    "sg:city":"Paisley",
    "sg:classifiers":[
        {
            "category":"Shopping",
            "subcategory":"Photographic Equipment",
            "type":"Retail Goods"
        }
    ],
    "sg:phone":"+44 141 889 6229",
    "sg:postcode":"PA1 1HF",
    "sg:province":"Renfrewshire",
    "sg:tags":[
        "supply"
    ],
    "wof:name":"David Deayton",
    "wof:placetype":"venue"
},
  "geometry": {"coordinates":[-4.419224,55.847065],"type":"Point"}
}