{
  "type": "Feature",
  "properties": {
    "addr:full":"1 Saxon Road Coventry Warwickshire CV2 4LB",
    "addr:housenumber":"1",
    "addr:postcode":"cv2 4lb",
    "addr:street":"Saxon Road",
    "iso:country":"GB",
    "sg:address":"1 Saxon Road",
    "sg:city":"Coventry",
    "sg:classifiers":[
        {
            "category":"Wholesale",
            "subcategory":"Office Equipment",
            "type":"Manufacturing & Wholesale Goods"
        },
        {
            "category":"Government",
            "subcategory":"Post Office",
            "type":"Public Place"
        }
    ],
    "sg:phone":"+44 24 7644 3728",
    "sg:postcode":"CV2 4LB",
    "sg:province":"Warwickshire",
    "sg:tags":[
        "register",
        "cash",
        "accessory"
    ],
    "wof:name":"Brian Ellis & Co",
    "wof:placetype":"venue"
},
  "geometry": {"coordinates":[-1.4775480032,52.4126548767],"type":"Point"}
}