{
  "type": "Feature",
  "properties": {
    "iso:country":"GB",
    "sg:address":"Pyefordbrook Garage, Kings Bromley Rd, Alrewas",
    "sg:city":"Burton-on-trent",
    "sg:classifiers":[
        {
            "category":"Autos & Motor Vehicles",
            "subcategory":"Automobile Sales",
            "type":"Retail Goods"
        }
    ],
    "sg:phone":"+44 1283 792049",
    "sg:postcode":"DE13 7DE",
    "sg:province":"Derbyshire",
    "sg:tags":[
        "commercial"
    ],
    "wof:name":"Bradbury,Michael,",
    "wof:placetype":"venue"
},
  "geometry": {"coordinates":[-1.7537889481,52.7287445068],"type":"Point"}
}