{
  "type": "Feature",
  "properties": {
    "iso:country":"GB",
    "sg:address":"1 Westdown Drive, Thurmaston",
    "sg:city":"Leicester",
    "sg:classifiers":[
        {
            "category":"Manufacturing",
            "subcategory":"Metals",
            "type":"Manufacturing & Wholesale Goods"
        }
    ],
    "sg:phone":"+44 116 269 4437",
    "sg:postcode":"LE4 8HU",
    "sg:province":"Leicestershire",
    "sg:tags":[
        "steel",
        "fabricator",
        "erectors"
    ],
    "wof:name":"RAVEN PROJECT MANAGEMENT",
    "wof:placetype":"venue"
},
  "geometry": {"coordinates":[-1.095085,52.672337],"type":"Point"}
}