{
  "type": "Feature",
  "properties": {
    "addr:full":"20 Davaar Street Glasgow Glasgow City G40 3RB",
    "addr:housenumber":"20",
    "addr:postcode":"g40 3rb",
    "addr:street":"Davaar Street",
    "iso:country":"GB",
    "sg:address":"20 Davaar Street",
    "sg:city":"Glasgow",
    "sg:classifiers":[
        {
            "category":"Organizations",
            "subcategory":"Political Organization",
            "type":"Services"
        }
    ],
    "sg:phone":"+44 141 551 9922",
    "sg:postcode":"G40 3RB",
    "sg:province":"Glasgow City",
    "sg:tags":[
        "promoter",
        "pool"
    ],
    "wof:name":"Celtic Development Pools Ltd.",
    "wof:placetype":"venue"
},
  "geometry": {"coordinates":[-4.2084021568,55.8485603333],"type":"Point"}
}