{
  "type": "Feature",
  "properties": {
    "addr:full":"12 Clavering Avenue, Richmond Barnes Greater London SW13 8DY",
    "addr:housenumber":"12",
    "addr:postcode":"sw13 8dy",
    "addr:street":"Clavering Avenue",
    "iso:country":"GB",
    "sg:address":"12 Clavering Avenue, Richmond",
    "sg:city":"Barnes",
    "sg:classifiers":[
        {
            "category":"Social Services",
            "subcategory":"Child Care",
            "type":"Services"
        }
    ],
    "sg:phone":"+44 20 8748 0345",
    "sg:postcode":"SW13 8DY",
    "sg:province":"Greater London",
    "sg:tags":[
        "agency",
        "nanny"
    ],
    "wof:name":"Tinies (Richmond) The Nanny Agency",
    "wof:placetype":"venue"
},
  "geometry": {"coordinates":[-0.2312330008,51.4863739014],"type":"Point"}
}