{
  "type": "Feature",
  "properties": {
    "addr:full":"76 Tessall Lane Birmingham West Midlands B31 2SF",
    "addr:housenumber":"76",
    "addr:postcode":"b31 2sf",
    "addr:street":"Tessall Lane",
    "iso:country":"GB",
    "sg:address":"76 Tessall Lane",
    "sg:city":"Birmingham",
    "sg:classifiers":[
        {
            "category":"Professional",
            "subcategory":"Detective & Security Services",
            "type":"Services"
        }
    ],
    "sg:phone":"+44 121 475 0200",
    "sg:postcode":"B31 2SF",
    "sg:province":"West Midlands",
    "wof:name":"Leo Security",
    "wof:placetype":"venue"
},
  "geometry": {"coordinates":[-1.98202,52.399902],"type":"Point"}
}