{
  "type": "Feature",
  "properties": {
    "addr:full":"Exchange Pk, 3 Bedford Pk Croydon Surrey CR0 2AQ",
    "addr:postcode":"cr0 2aq",
    "addr:street":"Exchange Pk 3;Pk",
    "iso:country":"GB",
    "sg:address":"Exchange Pk, 3 Bedford Pk",
    "sg:city":"Croydon",
    "sg:classifiers":[
        {
            "category":"Banks & Credit Unions",
            "subcategory":"Financial Services",
            "type":"Services"
        }
    ],
    "sg:phone":"+44 20 8405 5000",
    "sg:postcode":"CR0 2AQ",
    "sg:province":"Surrey",
    "sg:tags":[
        "consultant"
    ],
    "wof:name":"Royal Bank Invoice Finance Ltd",
    "wof:placetype":"venue"
},
  "geometry": {"coordinates":[-0.0978500023,51.3791809082],"type":"Point"}
}