{
  "type": "Feature",
  "properties": {
    "addr:full":"38 Lister Gate Nottingham Nottinghamshire NG1 7EE",
    "addr:housenumber":"38",
    "addr:postcode":"ng1 7ee",
    "addr:street":"Lister Gate",
    "iso:country":"GB",
    "sg:address":"38 Lister Gate",
    "sg:city":"Nottingham",
    "sg:classifiers":[
        {
            "category":"Shopping",
            "subcategory":"Music",
            "type":"Retail Goods"
        }
    ],
    "sg:phone":"+44 115 950 2841",
    "sg:postcode":"NG1 7EE",
    "sg:province":"Nottinghamshire",
    "sg:tags":[
        "record",
        "tape",
        "cd"
    ],
    "wof:name":"H M V (U K) Ltd.",
    "wof:placetype":"venue"
},
  "geometry": {"coordinates":[-1.1486749649,52.9505195618],"type":"Point"}
}