{
  "type": "Feature",
  "properties": {
    "addr:full":"639 Old Kent Rd Peckham Greater London SE15 1JU",
    "addr:housenumber":"639",
    "addr:postcode":"se15 1ju",
    "addr:street":"Old Kent Rd",
    "iso:country":"GB",
    "sg:address":"639 Old Kent Rd",
    "sg:city":"Peckham",
    "sg:classifiers":[
        {
            "category":"Professional",
            "subcategory":"Printing & Photocopies",
            "type":"Services"
        }
    ],
    "sg:phone":"+44 20 7732 3277",
    "sg:postcode":"SE15 1JU",
    "sg:province":"Greater London",
    "sg:tags":[
        "printer"
    ],
    "wof:name":"A S L Printers",
    "wof:placetype":"venue"
},
  "geometry": {"coordinates":[-0.0630749986,51.4828300476],"type":"Point"}
}