{
  "type": "Feature",
  "properties": {
    "iso:country":"GB",
    "sg:address":"Unit 1 Bowers Row",
    "sg:city":"Nantwich",
    "sg:classifiers":[
        {
            "category":"Personal",
            "subcategory":"Barber",
            "type":"Services"
        }
    ],
    "sg:phone":"+44 1270 627825",
    "sg:postcode":"CW5 5DZ",
    "sg:province":"Cheshire",
    "sg:tags":[
        "men's",
        "hairdresser"
    ],
    "wof:name":"Nantwich Hair Studio for Men",
    "wof:placetype":"venue"
},
  "geometry": {"coordinates":[-2.523274,53.06665],"type":"Point"}
}