{
  "type": "Feature",
  "properties": {
    "addr:full":"23 London Road Stranraer Dumfries and Galloway DG9 8AF",
    "addr:housenumber":"23",
    "addr:postcode":"dg9 8af",
    "addr:street":"London Road",
    "iso:country":"GB",
    "sg:address":"23 London Road",
    "sg:city":"Stranraer",
    "sg:classifiers":[
        {
            "category":"Building & Trades",
            "subcategory":"Construction",
            "type":"Services"
        }
    ],
    "sg:postcode":"DG9 8AF",
    "sg:province":"Dumfries and Galloway",
    "sg:tags":[
        "decorator",
        "painter"
    ],
    "wof:name":"J Hainey & Partner",
    "wof:placetype":"venue"
},
  "geometry": {"coordinates":[-5.018251,54.90337],"type":"Point"}
}