{
  "type": "Feature",
  "properties": {
    "addr:full":"Pollards Moor Road, Cadnam Southampton Hampshire SO40 2NZ",
    "addr:postcode":"so40 2nz",
    "addr:street":"Pollards Moor Road",
    "iso:country":"GB",
    "sg:address":"Pollards Moor Road, Cadnam",
    "sg:city":"Southampton",
    "sg:classifiers":[
        {
            "category":"Home & Garden",
            "subcategory":"Garden Supply",
            "type":"Retail Goods"
        }
    ],
    "sg:phone":"+44 23 8081 2302",
    "sg:postcode":"SO40 2NZ",
    "sg:province":"Hampshire",
    "sg:tags":[
        "turfing"
    ],
    "wof:name":"Abbey Turf",
    "wof:placetype":"venue"
},
  "geometry": {"coordinates":[-1.574074,50.919258],"type":"Point"}
}