{
  "type": "Feature",
  "properties": {
    "iso:country":"GB",
    "sg:address":"Unit 3 Arden Forest Industrial Estate, Tything Road East, Kinwarton",
    "sg:city":"Alcester",
    "sg:classifiers":[
        {
            "category":"Professional",
            "subcategory":"Engineering",
            "type":"Services"
        }
    ],
    "sg:phone":"+44 1789 400357",
    "sg:postcode":"B49 6ES",
    "sg:province":"Warwickshire",
    "sg:tags":[
        "electrical",
        "contractor",
        "electronic",
        "engineer"
    ],
    "wof:name":"Audio Visual Technicians",
    "wof:placetype":"venue"
},
  "geometry": {"coordinates":[-1.860992,52.221798],"type":"Point"}
}