{
  "type": "Feature",
  "properties": {
    "iso:country":"GB",
    "sg:address":"40 Acacia Ave, Chapel St. Leonards",
    "sg:city":"Skegness",
    "sg:classifiers":[
        {
            "category":"Freight",
            "type":"Transportation"
        }
    ],
    "sg:postcode":"PE24 5RE",
    "sg:province":"Lincolnshire",
    "sg:tags":[
        "haulage",
        "road"
    ],
    "wof:name":"Booton,David W,",
    "wof:placetype":"venue"
},
  "geometry": {"coordinates":[0.333276,53.231518],"type":"Point"}
}