{
  "type": "Feature",
  "properties": {
    "iso:country":"GB",
    "sg:address":"Unit 3 Wyndham Park Business Centre, Bepton Rd",
    "sg:city":"Midhurst",
    "sg:classifiers":[
        {
            "category":"Professional",
            "subcategory":"Engineering",
            "type":"Services"
        }
    ],
    "sg:phone":"+44 1730 812413",
    "sg:postcode":"GU29 9RE",
    "sg:province":"West Sussex",
    "sg:tags":[
        "civil",
        "engineer"
    ],
    "wof:name":"SDH Midhurst",
    "wof:placetype":"venue"
},
  "geometry": {"coordinates":[-0.74058,50.984913],"type":"Point"}
}