{
  "type": "Feature",
  "properties": {
    "addr:full":"20 Beancroft Road Castleford West Yorkshire WF10 5BW",
    "addr:housenumber":"20",
    "addr:postcode":"wf10 5bw",
    "addr:street":"Beancroft Road",
    "iso:country":"GB",
    "sg:address":"20 Beancroft Road",
    "sg:city":"Castleford",
    "sg:classifiers":[
        {
            "category":"Government",
            "subcategory":"Post Office",
            "type":"Public Place"
        }
    ],
    "sg:postcode":"WF10 5BW",
    "sg:province":"West Yorkshire",
    "wof:name":"Half Acres Post Office",
    "wof:placetype":"venue"
},
  "geometry": {"coordinates":[-1.3556879759,53.7222824097],"type":"Point"}
}