{
  "type": "Feature",
  "properties": {
    "addr:full":"6 Kitsbury Court, Kitsbury Terrace Berkhamsted Bedfordshire HP4 3EL",
    "addr:housenumber":"6",
    "addr:postcode":"hp4 3el",
    "addr:street":"Kitsbury Court Kitsbury Terrace",
    "iso:country":"GB",
    "sg:address":"6 Kitsbury Court, Kitsbury Terrace",
    "sg:city":"Berkhamsted",
    "sg:classifiers":[
        {
            "category":"Professional",
            "subcategory":"Management & Consulting",
            "type":"Services"
        }
    ],
    "sg:phone":"+44 1442 870100",
    "sg:postcode":"HP4 3EL",
    "sg:province":"Bedfordshire",
    "sg:tags":[
        "marketing",
        "consultant"
    ],
    "wof:name":"Gameplan Europe Ltd.",
    "wof:placetype":"venue"
},
  "geometry": {"coordinates":[-0.571418,51.762135],"type":"Point"}
}