{
  "type": "Feature",
  "properties": {
    "iso:country":"GB",
    "sg:address":"75 St Peters Road",
    "sg:city":"Great Yarmouth",
    "sg:classifiers":[
        {
            "category":"Travel",
            "subcategory":"Hotels & Motels",
            "type":"Entertainment"
        }
    ],
    "sg:phone":"+44 1493 858793",
    "sg:postcode":"NR30 3AY",
    "sg:province":"Norfolk",
    "sg:tags":[
        "house",
        "guest"
    ],
    "wof:name":"Newhaven Guest House",
    "wof:placetype":"venue"
},
  "geometry": {"coordinates":[1.732613,52.602467],"type":"Point"}
}