{
  "type": "Feature",
  "properties": {
    "addr:full":"36 Dukes Close, Earls Way Industrial Estate Leicester Leicestershire LE4 8EY",
    "addr:housenumber":"36;estate",
    "addr:postcode":"le4 8ey",
    "addr:street":"Dukes Close Earls Way Industrial",
    "iso:country":"GB",
    "sg:address":"36 Dukes Close, Earls Way Industrial Estate",
    "sg:city":"Leicester",
    "sg:classifiers":[
        {
            "category":"Manufacturing",
            "subcategory":"Tools & Machinery",
            "type":"Manufacturing & Wholesale Goods"
        }
    ],
    "sg:phone":"+44 116 264 0440",
    "sg:postcode":"LE4 8EY",
    "sg:province":"Leicestershire",
    "sg:tags":[
        "manufacture",
        "powertools",
        "power",
        "supply"
    ],
    "wof:name":"Ask Millers",
    "wof:placetype":"venue"
},
  "geometry": {"coordinates":[-1.08686,52.677906],"type":"Point"}
}