{
  "type": "Feature",
  "properties": {
    "addr:full":"7a Currie Street Hertford Hertfordshire SG13 7DA",
    "addr:housenumber":"7a",
    "addr:postcode":"sg13 7da",
    "addr:street":"Currie Street",
    "iso:country":"GB",
    "sg:address":"7a Currie Street",
    "sg:city":"Hertford",
    "sg:classifiers":[
        {
            "category":"Professional",
            "subcategory":"Engineering",
            "type":"Services"
        },
        {
            "category":"Building & Trades",
            "subcategory":"Electrical",
            "type":"Services"
        }
    ],
    "sg:phone":"+44 1992 553840",
    "sg:postcode":"SG13 7DA",
    "sg:province":"Hertfordshire",
    "sg:tags":[
        "engineer",
        "electrician",
        "contractor"
    ],
    "wof:name":"P J S Electrical Contractors Ltd",
    "wof:placetype":"venue"
},
  "geometry": {"coordinates":[-0.066592,51.798927],"type":"Point"}
}