{
  "type": "Feature",
  "properties": {
    "iso:country":"GB",
    "sg:address":"110 High Street",
    "sg:city":"Edgware",
    "sg:classifiers":[
        {
            "category":"Shopping",
            "subcategory":"Hobbies, Toys, & Games",
            "type":"Retail Goods"
        },
        {
            "category":"Recreation",
            "type":"Entertainment"
        }
    ],
    "sg:phone":"+44 20 8952 2002",
    "sg:postcode":"HA8 7HF",
    "sg:province":"Greater London",
    "sg:tags":[
        "snooker",
        "billiards",
        "retailer",
        "pool",
        "computer"
    ],
    "wof:name":"Thurstons",
    "wof:placetype":"venue"
},
  "geometry": {"coordinates":[-0.281189,51.612396],"type":"Point"}
}