{
  "type": "Feature",
  "properties": {
    "addr:full":"2 Cumbernauld Road, Longcroft Bonnybridge Falkirk FK4 1QJ",
    "addr:housenumber":"2",
    "addr:postcode":"fk4 1qj",
    "addr:street":"Cumbernauld Road",
    "iso:country":"GB",
    "sg:address":"2 Cumbernauld Road, Longcroft",
    "sg:city":"Bonnybridge",
    "sg:classifiers":[
        {
            "category":"Building & Trades",
            "subcategory":"Construction",
            "type":"Services"
        }
    ],
    "sg:phone":"+44 1324 840005",
    "sg:postcode":"FK4 1QJ",
    "sg:province":"Falkirk",
    "sg:tags":[
        "roofing",
        "contracting"
    ],
    "wof:name":"John Henderson & Sons",
    "wof:placetype":"venue"
},
  "geometry": {"coordinates":[-3.930253,55.991802],"type":"Point"}
}