{
  "type": "Feature",
  "properties": {
    "addr:full":"Unit 10-11, 48 Horn Lane Acton Greater London W3 6NP",
    "addr:housenumber":"unit 10-11 48",
    "addr:postcode":"w3 6np",
    "addr:street":"Horn Lane",
    "iso:country":"GB",
    "sg:address":"Unit 10-11, 48 Horn Lane",
    "sg:city":"Acton",
    "sg:classifiers":[
        {
            "category":"Home & Garden",
            "subcategory":"Hardware",
            "type":"Retail Goods"
        }
    ],
    "sg:phone":"+44 20 8723 7223",
    "sg:postcode":"W3 6NP",
    "sg:province":"Greater London",
    "sg:tags":[
        "part",
        "accessory"
    ],
    "wof:name":"Easy Rider",
    "wof:placetype":"venue"
},
  "geometry": {"coordinates":[-0.2702389956,51.5127983093],"type":"Point"}
}