{
  "type": "Feature",
  "properties": {
    "addr:full":"24 Exeter Drive, Irlam Manchester Greater Manchester M44 6FH",
    "addr:housenumber":"24",
    "addr:postcode":"m44 6fh",
    "addr:street":"Exeter Drive",
    "iso:country":"GB",
    "sg:address":"24 Exeter Drive, Irlam",
    "sg:city":"Manchester",
    "sg:classifiers":[
        {
            "category":"Building & Trades",
            "subcategory":"Construction",
            "type":"Services"
        }
    ],
    "sg:postcode":"M44 6FH",
    "sg:province":"Greater Manchester",
    "sg:tags":[
        "builder"
    ],
    "wof:name":"R & D Plumbing & Heating Ltd",
    "wof:placetype":"venue"
},
  "geometry": {"coordinates":[-2.413125,53.450226],"type":"Point"}
}