{
  "type": "Feature",
  "properties": {
    "addr:full":"Shop D1/2 Antiquarius, 131 Kings Road London Greater London SW3 4PW",
    "addr:housenumber":"d1 / 2;131",
    "addr:postcode":"sw3 4pw",
    "addr:street":"Antiquarius;Kings Road",
    "iso:country":"GB",
    "sg:address":"Shop D1/2 Antiquarius, 131 Kings Road",
    "sg:city":"London",
    "sg:classifiers":[
        {
            "category":"Shopping",
            "subcategory":"Antiques",
            "type":"Retail Goods"
        }
    ],
    "sg:phone":"+44 20 7349 9080",
    "sg:postcode":"SW3 4PW",
    "sg:province":"Greater London",
    "wof:name":"Little River",
    "wof:placetype":"venue"
},
  "geometry": {"coordinates":[-0.17643,51.48418],"type":"Point"}
}