{
  "type": "Feature",
  "properties": {
    "addr:full":"Millans Court Ambleside Cumbria LA22 9BW",
    "addr:postcode":"la22 9bw",
    "addr:street":"Ambleside",
    "iso:country":"GB",
    "sg:address":"Millans Court",
    "sg:city":"Ambleside",
    "sg:classifiers":[
        {
            "category":"Health Services",
            "subcategory":"Nursing And Care Facility",
            "type":"Services"
        }
    ],
    "sg:phone":"+44 15394 34134",
    "sg:postcode":"LA22 9BW",
    "sg:province":"Cumbria",
    "sg:tags":[
        "home"
    ],
    "wof:name":"Anchor Trust",
    "wof:placetype":"venue"
},
  "geometry": {"coordinates":[-2.9630889893,54.4326057434],"type":"Point"}
}