{
  "type": "Feature",
  "properties": {
    "iso:country":"GB",
    "sg:address":"97 St Clements Street",
    "sg:city":"Oxford",
    "sg:classifiers":[
        {
            "category":"Restaurant",
            "type":"Food & Drink"
        }
    ],
    "sg:postcode":"OX4 1AR",
    "sg:province":"Oxfordshire",
    "wof:name":"Genies International Restaurant",
    "wof:placetype":"venue"
},
  "geometry": {"coordinates":[-1.242216,51.75008],"type":"Point"}
}