{
  "type": "Feature",
  "properties": {
    "iso:country":"GB",
    "sg:address":"102-104 Union St",
    "sg:city":"Torquay",
    "sg:classifiers":[
        {
            "category":"Health Services",
            "subcategory":"Podiatrist",
            "type":"Services"
        }
    ],
    "sg:phone":"+44 1803 292153",
    "sg:postcode":"TQ2 5PY",
    "sg:province":"Devon",
    "sg:tags":[
        "podiatrists",
        "chiropodist"
    ],
    "wof:name":"Scholl Foot & Legcare Centre",
    "wof:placetype":"venue"
},
  "geometry": {"coordinates":[-3.530741,50.467201],"type":"Point"}
}