{
  "type": "Feature",
  "properties": {
    "addr:full":"75a Westmead Road Sutton Surrey SM1 4JF",
    "addr:housenumber":"75a",
    "addr:postcode":"sm1 4jf",
    "addr:street":"Westmead Road",
    "iso:country":"GB",
    "sg:address":"75a Westmead Road",
    "sg:city":"Sutton",
    "sg:classifiers":[
        {
            "category":"Wholesale",
            "subcategory":"Non-durable Goods",
            "type":"Manufacturing & Wholesale Goods"
        }
    ],
    "sg:phone":"+44 20 8642 4484",
    "sg:postcode":"SM1 4JF",
    "sg:province":"Surrey",
    "sg:tags":[
        "carry",
        "wholesaler",
        "cash"
    ],
    "wof:name":"Edward Paul & Co. (Grocers) Ltd.",
    "wof:placetype":"venue"
},
  "geometry": {"coordinates":[-0.1797409952,51.3660392761],"type":"Point"}
}