{
  "type": "Feature",
  "properties": {
    "addr:full":"12 Fore St Redruth Cornwall TR15 2AZ",
    "addr:housenumber":"12",
    "addr:postcode":"tr15 2az",
    "addr:street":"Fore St",
    "iso:country":"GB",
    "sg:address":"12 Fore St",
    "sg:city":"Redruth",
    "sg:classifiers":[
        {
            "category":"Professional",
            "subcategory":"Management & Consulting",
            "type":"Services"
        }
    ],
    "sg:phone":"+44 1209 214999",
    "sg:postcode":"TR15 2AZ",
    "sg:province":"Cornwall",
    "sg:tags":[
        "conservation"
    ],
    "wof:name":"Cornish Solidarity",
    "wof:placetype":"venue"
},
  "geometry": {"coordinates":[-5.229254,50.23304],"type":"Point"}
}