{
  "type": "Feature",
  "properties": {
    "iso:country":"GB",
    "sg:address":"Grange Park",
    "sg:city":"Wetherby",
    "sg:classifiers":[
        {
            "category":"Education",
            "subcategory":"Special Training",
            "type":"Public Place"
        }
    ],
    "sg:phone":"+44 1937 586817",
    "sg:postcode":"LS22 4NQ",
    "sg:province":"North Yorkshire",
    "sg:tags":[
        "product",
        "centre"
    ],
    "wof:name":"J H Hudson & Son",
    "wof:placetype":"venue"
},
  "geometry": {"coordinates":[-1.386804,53.92799],"type":"Point"}
}