{
  "type": "Feature",
  "properties": {
    "addr:full":"Unit 1a  Ravenswarf Rd, Scout Hill Dewsbury West Yorkshire WF13 3SQ",
    "addr:housenumber":"unit 1a",
    "addr:postcode":"wf13 3sq",
    "addr:street":"Ravenswarf Rd Scout Hill",
    "iso:country":"GB",
    "sg:address":"Unit 1a  Ravenswarf Rd, Scout Hill",
    "sg:city":"Dewsbury",
    "sg:classifiers":[
        {
            "category":"Building & Trades",
            "subcategory":"Construction",
            "type":"Services"
        }
    ],
    "sg:postcode":"WF13 3SQ",
    "sg:province":"West Yorkshire",
    "sg:tags":[
        "roofing"
    ],
    "wof:name":"Competent Asphalt Co Ltd",
    "wof:placetype":"venue"
},
  "geometry": {"coordinates":[-1.651049,53.681469],"type":"Point"}
}