{
  "type": "Feature",
  "properties": {
    "addr:full":"North Street Dorking Surrey RH4 1DN",
    "addr:postcode":"rh4 1dn",
    "addr:street":"North Street",
    "iso:country":"GB",
    "sg:address":"North Street",
    "sg:city":"Dorking",
    "sg:classifiers":[
        {
            "category":"Retail",
            "subcategory":"Auto Repair",
            "type":"Services"
        }
    ],
    "sg:phone":"+44 1306 880100",
    "sg:postcode":"RH4 1DN",
    "sg:province":"Surrey",
    "sg:tags":[
        "modification",
        "garage"
    ],
    "wof:name":"B W Batchelor Autos",
    "wof:placetype":"venue"
},
  "geometry": {"coordinates":[-0.3333,51.232037],"type":"Point"}
}