{
  "type": "Feature",
  "properties": {
    "addr:full":"286 South Rd Sheffield South Yorkshire S6 3TE",
    "addr:housenumber":"286",
    "addr:postcode":"s6 3te",
    "addr:street":"South Rd",
    "iso:country":"GB",
    "sg:address":"286 South Rd",
    "sg:city":"Sheffield",
    "sg:classifiers":[
        {
            "category":"Organizations",
            "subcategory":"Non-profit Organization",
            "type":"Services"
        }
    ],
    "sg:postcode":"S6 3TE",
    "sg:province":"South Yorkshire",
    "sg:tags":[
        "organisation",
        "voluntary",
        "charity"
    ],
    "wof:name":"Child Helpline",
    "wof:placetype":"venue"
},
  "geometry": {"coordinates":[-1.500433,53.392982],"type":"Point"}
}