{
  "type": "Feature",
  "properties": {
    "addr:full":"6 Leysdown Rd, Leysdown On Sea Sheerness Kent ME12 4RD",
    "addr:housenumber":"6",
    "addr:postcode":"me12 4rd",
    "addr:street":"Leysdown Rd",
    "iso:country":"GB",
    "sg:address":"6 Leysdown Rd, Leysdown On Sea",
    "sg:city":"Sheerness",
    "sg:classifiers":[
        {
            "category":"Bars & Pubs",
            "type":"Food & Drink"
        },
        {
            "category":"Community Center",
            "subcategory":"Social",
            "type":"Public Place"
        }
    ],
    "sg:phone":"+44 1795 510523",
    "sg:postcode":"ME12 4RD",
    "sg:province":"Kent",
    "sg:tags":[
        "pubs",
        "house",
        "inn",
        "activity"
    ],
    "wof:name":"Rose & Crown Ltd",
    "wof:placetype":"venue"
},
  "geometry": {"coordinates":[0.862326026,51.405834198],"type":"Point"}
}