{
  "type": "Feature",
  "properties": {
    "addr:full":"Cefn Goleu, Myddfai Llandovery Carmarthenshire SA20 0QA",
    "addr:postcode":"sa20 0qa",
    "iso:country":"GB",
    "sg:address":"Cefn Goleu, Myddfai",
    "sg:city":"Llandovery",
    "sg:classifiers":[
        {
            "category":"Farming",
            "subcategory":"Livestock Farm",
            "type":"Manufacturing & Wholesale Goods"
        }
    ],
    "sg:phone":"+44 1550 720482",
    "sg:postcode":"SA20 0QA",
    "sg:province":"Carmarthenshire",
    "sg:tags":[
        "others"
    ],
    "wof:name":"Bryan A McSwiney",
    "wof:placetype":"venue"
},
  "geometry": {"coordinates":[-3.800155,51.994087],"type":"Point"}
}