{
  "type": "Feature",
  "properties": {
    "addr:full":"Bushbury La Wolverhampton Staffordshire WV10 9UQ",
    "addr:postcode":"wv10 9uq",
    "addr:street":"La",
    "iso:country":"GB",
    "sg:address":"Bushbury La",
    "sg:city":"Wolverhampton",
    "sg:classifiers":[
        {
            "category":"Sports & Exercise",
            "subcategory":"Bowling",
            "type":"Entertainment"
        }
    ],
    "sg:phone":"+44 1902 711934",
    "sg:postcode":"WV10 9UQ",
    "sg:province":"Staffordshire",
    "wof:name":"Strykers Pleasure Bowl",
    "wof:placetype":"venue"
},
  "geometry": {"coordinates":[-2.116949,52.616905],"type":"Point"}
}