{
  "type": "Feature",
  "properties": {
    "iso:country":"GB",
    "sg:address":"28 Innerbrook Road",
    "sg:city":"Torquay",
    "sg:classifiers":[
        {
            "category":"Wholesale",
            "subcategory":"Books, Periodicals, & Newspapers",
            "type":"Manufacturing & Wholesale Goods"
        }
    ],
    "sg:postcode":"TQ2 6AQ",
    "sg:province":"Devon",
    "sg:tags":[
        "publishing"
    ],
    "wof:name":"Alven Promotions",
    "wof:placetype":"venue"
},
  "geometry": {"coordinates":[-3.5462579727,50.4684829712],"type":"Point"}
}