{
  "type": "Feature",
  "properties": {
    "addr:full":"12 Wellington Square Hastings East Sussex TN34 1PB",
    "addr:housenumber":"12",
    "addr:postcode":"tn34 1pb",
    "addr:street":"Wellington Square Hastings",
    "iso:country":"GB",
    "sg:address":"12 Wellington Square",
    "sg:city":"Hastings",
    "sg:classifiers":[
        {
            "category":"Professional",
            "subcategory":"Lawyer & Legal Services",
            "type":"Services"
        }
    ],
    "sg:phone":"+44 1424 721821",
    "sg:postcode":"TN34 1PB",
    "sg:province":"East Sussex",
    "sg:tags":[
        "solicitor"
    ],
    "wof:name":"Morgan & Lamplugh",
    "wof:placetype":"venue"
},
  "geometry": {"coordinates":[0.58316,50.856037],"type":"Point"}
}