{
  "type": "Feature",
  "properties": {
    "iso:country":"GB",
    "sg:address":"40 Auburn Road, Edlington",
    "sg:city":"Doncaster",
    "sg:classifiers":[
        {
            "category":"Building & Trades",
            "subcategory":"Construction",
            "type":"Services"
        }
    ],
    "sg:phone":"+44 1709 862501",
    "sg:postcode":"DN12 1DP",
    "sg:province":"South Yorkshire",
    "sg:tags":[
        "roofing"
    ],
    "wof:name":"Steve Roofing Shelton",
    "wof:placetype":"venue"
},
  "geometry": {"coordinates":[-1.194122,53.484097],"type":"Point"}
}