{
  "type": "Feature",
  "properties": {
    "addr:full":"260 Northolt Road Harrow Greater London HA2 8DY",
    "addr:housenumber":"260",
    "addr:postcode":"ha2 8dy",
    "addr:street":"Northolt Road",
    "iso:country":"GB",
    "sg:address":"260 Northolt Road",
    "sg:city":"Harrow",
    "sg:classifiers":[
        {
            "category":"Manufacturing",
            "subcategory":"Petroleum Products",
            "type":"Manufacturing & Wholesale Goods"
        },
        {
            "category":"Building & Trades",
            "subcategory":"Construction",
            "type":"Services"
        }
    ],
    "sg:phone":"+44 20 8248 7860",
    "sg:postcode":"HA2 8DY",
    "sg:province":"Greater London",
    "sg:tags":[
        "double",
        "glazing",
        "installers"
    ],
    "wof:name":"A A Cladding",
    "wof:placetype":"venue"
},
  "geometry": {"coordinates":[-0.354671,51.563969],"type":"Point"}
}