{
  "type": "Feature",
  "properties": {
    "addr:full":"214 London Road Southend-on-sea Essex SS1 1PJ",
    "addr:housenumber":"214",
    "addr:postcode":"ss1 1pj",
    "addr:street":"London Road",
    "iso:country":"GB",
    "sg:address":"214 London Road",
    "sg:city":"Southend-on-sea",
    "sg:classifiers":[
        {
            "category":"Home & Garden",
            "subcategory":"Household Appliances",
            "type":"Retail Goods"
        }
    ],
    "sg:phone":"+44 1702 340000",
    "sg:postcode":"SS1 1PJ",
    "sg:province":"Essex",
    "sg:tags":[
        "electrical"
    ],
    "wof:name":"Cowans Electrical",
    "wof:placetype":"venue"
},
  "geometry": {"coordinates":[0.7012839913,51.5397949219],"type":"Point"}
}