{
  "type": "Feature",
  "properties": {
    "iso:country":"GB",
    "sg:address":"8 The Circle, Barton Rd, Stretford",
    "sg:city":"Manchester",
    "sg:classifiers":[
        {
            "category":"Shopping",
            "subcategory":"Pets & Pet Supplies",
            "type":"Retail Goods"
        }
    ],
    "sg:postcode":"M32 9TR",
    "sg:province":"Cheshire",
    "wof:name":"Circle Pets & Aquatics",
    "wof:placetype":"venue"
},
  "geometry": {"coordinates":[-2.336769,53.456329],"type":"Point"}
}