{
  "type": "Feature",
  "properties": {
    "iso:country":"GB",
    "sg:address":"Bitton Park Rd",
    "sg:city":"Teignmouth",
    "sg:classifiers":[
        {
            "category":"Place Of Worship",
            "type":"Public Place"
        }
    ],
    "sg:phone":"+44 1626 778575",
    "sg:postcode":"TQ14 9BT",
    "sg:province":"Devon",
    "wof:name":"St James Church West Teignmouth",
    "wof:placetype":"venue"
},
  "geometry": {"coordinates":[-3.507064,50.547939],"type":"Point"}
}