{
  "type": "Feature",
  "properties": {
    "iso:country":"GB",
    "sg:address":"11 Coates Gardens",
    "sg:city":"Edinburgh",
    "sg:classifiers":[
        {
            "category":"Travel",
            "subcategory":"Hotels & Motels",
            "type":"Entertainment"
        }
    ],
    "sg:phone":"+44 131 337 1050",
    "sg:postcode":"EH12 5LG",
    "sg:province":"City of Edinburgh",
    "sg:tags":[
        "house",
        "guest"
    ],
    "wof:name":"The Lairg",
    "wof:placetype":"venue"
},
  "geometry": {"coordinates":[-3.221838,55.94659],"type":"Point"}
}