{
  "type": "Feature",
  "properties": {
    "iso:country":"GB",
    "sg:address":"49 Midland Road",
    "sg:city":"Bedford",
    "sg:classifiers":[
        {
            "category":"Fast Food",
            "type":"Food & Drink"
        }
    ],
    "sg:postcode":"MK40 1PW",
    "sg:province":"Bedfordshire",
    "sg:tags":[
        "away",
        "take"
    ],
    "wof:name":"Cherry's Sandwich Bar",
    "wof:placetype":"venue"
},
  "geometry": {"coordinates":[-0.47098,52.136379],"type":"Point"}
}