{
  "type": "Feature",
  "properties": {
    "addr:full":"175 Bramley Road, Oakwood London Greater London N14 4XA",
    "addr:housenumber":"175",
    "addr:postcode":"n14 4xa",
    "addr:street":"Bramley Road",
    "iso:country":"GB",
    "sg:address":"175 Bramley Road, Oakwood",
    "sg:city":"London",
    "sg:classifiers":[
        {
            "category":"Shopping",
            "subcategory":"Stationery & Office Supplies",
            "type":"Retail Goods"
        }
    ],
    "sg:phone":"+44 20 8362 1000",
    "sg:postcode":"N14 4XA",
    "sg:province":"Greater London",
    "wof:name":"Sprint Printers & Stationers",
    "wof:placetype":"venue"
},
  "geometry": {"coordinates":[-0.129678,51.648605],"type":"Point"}
}