{
  "type": "Feature",
  "properties": {
    "iso:country":"GB",
    "sg:address":"117 High Street",
    "sg:city":"North Berwick",
    "sg:classifiers":[
        {
            "category":"Professional",
            "type":"Services"
        }
    ],
    "sg:postcode":"EH39 4HD",
    "sg:province":"East Lothian",
    "sg:tags":[
        "interior",
        "furnishers",
        "designer"
    ],
    "wof:name":"Interior Fabrics",
    "wof:placetype":"venue"
},
  "geometry": {"coordinates":[-2.7228319645,56.0580482483],"type":"Point"}
}