{
  "type": "Feature",
  "properties": {
    "addr:full":"Sawmill High St Lockerbie Dumfries and Galloway DG11 3DF",
    "addr:postcode":"dg11 3df",
    "addr:street":"High St",
    "iso:country":"GB",
    "sg:address":"Sawmill High St",
    "sg:city":"Lockerbie",
    "sg:classifiers":[
        {
            "category":"Building & Trades",
            "subcategory":"Construction",
            "type":"Services"
        }
    ],
    "sg:phone":"+44 1576 300436",
    "sg:postcode":"DG11 3DF",
    "sg:province":"Dumfries and Galloway",
    "sg:tags":[
        "builder"
    ],
    "wof:name":"Carruthers Bros Ltd",
    "wof:placetype":"venue"
},
  "geometry": {"coordinates":[-3.2055990696,55.055770874],"type":"Point"}
}