{
  "type": "Feature",
  "properties": {
    "iso:country":"GB",
    "sg:address":"Stock Exchange Building, 125 Old Broad Street",
    "sg:city":"London",
    "sg:classifiers":[
        {
            "category":"Banks & Credit Unions",
            "subcategory":"Investment Brokerage",
            "type":"Services"
        }
    ],
    "sg:postcode":"EC2N 1HP",
    "sg:province":"Greater London",
    "sg:tags":[
        "stockbroker"
    ],
    "wof:name":"Samsung Securities Co. Ltd.",
    "wof:placetype":"venue"
},
  "geometry": {"coordinates":[-0.085304,51.515022],"type":"Point"}
}