{
  "type": "Feature",
  "properties": {
    "addr:full":"The Oaks, 2 Packhorse Road Gerrards Cross Buckinghamshire SL9 7QE",
    "addr:housenumber":"2",
    "addr:postcode":"sl9 7qe",
    "addr:street":"Packhorse Road",
    "iso:country":"GB",
    "sg:address":"The Oaks, 2 Packhorse Road",
    "sg:city":"Gerrards Cross",
    "sg:classifiers":[
        {
            "category":"Communications",
            "type":"Services"
        }
    ],
    "sg:postcode":"SL9 7QE",
    "sg:province":"Buckinghamshire",
    "sg:tags":[
        "telecommunication"
    ],
    "wof:name":"Mosaix Ltd.",
    "wof:placetype":"venue"
},
  "geometry": {"coordinates":[-0.562579,51.578976],"type":"Point"}
}