{
  "type": "Feature",
  "properties": {
    "addr:full":"30 Stokesley Rd Middlesbrough North Yorkshire TS7 8DX",
    "addr:housenumber":"30",
    "addr:postcode":"ts7 8dx",
    "addr:street":"Stokesley Rd",
    "iso:country":"GB",
    "sg:address":"30 Stokesley Rd",
    "sg:city":"Middlesbrough",
    "sg:classifiers":[
        {
            "category":"Banks & Credit Unions",
            "subcategory":"Financial Services",
            "type":"Services"
        }
    ],
    "sg:phone":"+44 1642 317261",
    "sg:postcode":"TS7 8DX",
    "sg:province":"North Yorkshire",
    "sg:tags":[
        "building",
        "society"
    ],
    "wof:name":"Thirlwells",
    "wof:placetype":"venue"
},
  "geometry": {"coordinates":[-1.1986860037,54.5304031372],"type":"Point"}
}