{
  "type": "Feature",
  "properties": {
    "addr:full":"325a Goring Road, Goring By Sea Worthing West Sussex BN12 4NX",
    "addr:housenumber":"325a",
    "addr:postcode":"bn12 4nx",
    "addr:street":"Goring Road",
    "iso:country":"GB",
    "sg:address":"325a Goring Road, Goring By Sea",
    "sg:city":"Worthing",
    "sg:classifiers":[
        {
            "category":"Real Estate",
            "subcategory":"Real Estate Operator",
            "type":"Services"
        }
    ],
    "sg:postcode":"BN12 4NX",
    "sg:province":"West Sussex",
    "sg:tags":[
        "letting",
        "agent"
    ],
    "wof:name":"Claire Seaby",
    "wof:placetype":"venue"
},
  "geometry": {"coordinates":[-0.422679,50.812096],"type":"Point"}
}