{
  "type": "Feature",
  "properties": {
    "iso:country":"GB",
    "sg:address":"7 Park Road, Radyr",
    "sg:city":"Cardiff",
    "sg:classifiers":[
        {
            "category":"Food & Beverages",
            "subcategory":"Groceries & Convenience Stores",
            "type":"Retail Goods"
        }
    ],
    "sg:phone":"+44 29 2084 2213",
    "sg:postcode":"CF15 8DF",
    "sg:province":"Caerphilly",
    "wof:name":"Radyr Stores",
    "wof:placetype":"venue"
},
  "geometry": {"coordinates":[-3.257605,51.518547],"type":"Point"}
}