{
  "type": "Feature",
  "properties": {
    "addr:full":"10 Newmarket Road Norwich Norfolk NR2 2LA",
    "addr:housenumber":"10",
    "addr:postcode":"nr2 2la",
    "addr:street":"Newmarket Road Norwich Norfolk",
    "iso:country":"GB",
    "sg:address":"10 Newmarket Road",
    "sg:city":"Norwich",
    "sg:classifiers":[
        {
            "category":"Professional",
            "type":"Services"
        }
    ],
    "sg:postcode":"NR2 2LA",
    "sg:province":"Norfolk",
    "sg:tags":[
        "relocation"
    ],
    "wof:name":"Anglian Relocation Services",
    "wof:placetype":"venue"
},
  "geometry": {"coordinates":[1.2858860493,52.620803833],"type":"Point"}
}