{
  "type": "Feature",
  "properties": {
    "iso:country":"GB",
    "sg:address":"160 Highfield Way",
    "sg:city":"Rickmansworth",
    "sg:classifiers":[
        {
            "category":"Organizations",
            "subcategory":"Membership Organization",
            "type":"Services"
        }
    ],
    "sg:postcode":"WD3 7PJ",
    "sg:province":"Hertfordshire",
    "sg:tags":[
        "club"
    ],
    "wof:name":"The Holiday Club (Rickmansworth) Ltd.",
    "wof:placetype":"venue"
},
  "geometry": {"coordinates":[-0.4862689972,51.6455383301],"type":"Point"}
}