{
  "type": "Feature",
  "properties": {
    "addr:full":"Wood Gate, Loppington Shrewsbury Shropshire SY4 5ST",
    "addr:postcode":"sy4 5st",
    "addr:street":"Wood Gate",
    "iso:country":"GB",
    "sg:address":"Wood Gate, Loppington",
    "sg:city":"Shrewsbury",
    "sg:classifiers":[
        {
            "category":"Banks & Credit Unions",
            "subcategory":"Investment Brokerage",
            "type":"Services"
        }
    ],
    "sg:postcode":"SY4 5ST",
    "sg:province":"Shropshire",
    "sg:tags":[
        "contractor"
    ],
    "wof:name":"W A  & H T Dyson",
    "wof:placetype":"venue"
},
  "geometry": {"coordinates":[-2.7879140377,52.8589897156],"type":"Point"}
}