{
  "type": "Feature",
  "properties": {
    "iso:country":"GB",
    "sg:address":"Manor Farm, High Street, Avebury",
    "sg:city":"Marlborough",
    "sg:classifiers":[
        {
            "category":"Farming",
            "subcategory":"Livestock Farm",
            "type":"Manufacturing & Wholesale Goods"
        }
    ],
    "sg:postcode":"SN8 1RF",
    "sg:province":"Berkshire",
    "sg:tags":[
        "others"
    ],
    "wof:name":"Anthony A  Farthing",
    "wof:placetype":"venue"
},
  "geometry": {"coordinates":[-1.729889,51.421333],"type":"Point"}
}