{
  "type": "Feature",
  "properties": {
    "iso:country":"GB",
    "sg:address":"Unit 61, Boleness Road",
    "sg:city":"Wisbech",
    "sg:classifiers":[
        {
            "category":"Autos & Motor Vehicles",
            "subcategory":"Auto Supplies",
            "type":"Retail Goods"
        }
    ],
    "sg:phone":"+44 1945 587478",
    "sg:postcode":"PE13 2RB",
    "sg:province":"Cambridgeshire",
    "sg:tags":[
        "component"
    ],
    "wof:name":"Refinishing Supplies",
    "wof:placetype":"venue"
},
  "geometry": {"coordinates":[0.1610530019,52.6523132324],"type":"Point"}
}