{
  "type": "Feature",
  "properties": {
    "addr:full":"10 St Georges Road North Shields Tyne and Wear NE30 3JY",
    "addr:housenumber":"10",
    "addr:postcode":"ne30 3jy",
    "addr:street":"St Georges Road",
    "iso:country":"GB",
    "sg:address":"10 St Georges Road",
    "sg:city":"North Shields",
    "sg:classifiers":[
        {
            "category":"Personal",
            "subcategory":"Beauty Salon",
            "type":"Services"
        }
    ],
    "sg:phone":"+44 191 251 2531",
    "sg:postcode":"NE30 3JY",
    "sg:province":"Tyne and Wear",
    "sg:tags":[
        "unisex",
        "hairdresser"
    ],
    "wof:name":"Jigsaw",
    "wof:placetype":"venue"
},
  "geometry": {"coordinates":[-1.4363570213,55.0341491699],"type":"Point"}
}