{
  "type": "Feature",
  "properties": {
    "iso:country":"GB",
    "sg:address":"1 Grant Street",
    "sg:city":"Wick",
    "sg:classifiers":[
        {
            "category":"Shopping",
            "subcategory":"Shoes",
            "type":"Retail Goods"
        }
    ],
    "sg:postcode":"KW1 5AY",
    "sg:province":"Highland",
    "wof:name":"Patty's",
    "wof:placetype":"venue"
},
  "geometry": {"coordinates":[-3.08674,58.437557],"type":"Point"}
}