{
  "type": "Feature",
  "properties": {
    "addr:full":"127 Tunstall Road Croydon Surrey CR0 6TZ",
    "addr:housenumber":"127",
    "addr:postcode":"cr0 6tz",
    "addr:street":"Tunstall Road",
    "iso:country":"GB",
    "sg:address":"127 Tunstall Road",
    "sg:city":"Croydon",
    "sg:classifiers":[
        {
            "category":"Professional",
            "subcategory":"Detective & Security Services",
            "type":"Services"
        }
    ],
    "sg:phone":"+44 20 8654 9141",
    "sg:postcode":"CR0 6TZ",
    "sg:province":"Surrey",
    "wof:name":"Galago Ltd.",
    "wof:placetype":"venue"
},
  "geometry": {"coordinates":[-0.084117,51.376122],"type":"Point"}
}