{
  "type": "Feature",
  "properties": {
    "addr:full":"53 Church Street Cromer Norfolk NR27 9HH",
    "addr:housenumber":"53",
    "addr:postcode":"nr27 9hh",
    "addr:street":"Church Street",
    "iso:country":"GB",
    "sg:address":"53 Church Street",
    "sg:city":"Cromer",
    "sg:classifiers":[
        {
            "category":"Shopping",
            "subcategory":"Discount & Variety Stores",
            "type":"Retail Goods"
        }
    ],
    "sg:phone":"+44 1263 510123",
    "sg:postcode":"NR27 9HH",
    "sg:province":"Norfolk",
    "sg:tags":[
        "centre"
    ],
    "wof:name":"H K Clearance Depot",
    "wof:placetype":"venue"
},
  "geometry": {"coordinates":[1.300212,52.931137],"type":"Point"}
}