{
  "type": "Feature",
  "properties": {
    "addr:full":"95 High St Willesden Greater London NW10 4TS",
    "addr:housenumber":"95",
    "addr:postcode":"nw10 4ts",
    "addr:street":"High St",
    "iso:country":"GB",
    "sg:address":"95 High St",
    "sg:city":"Willesden",
    "sg:classifiers":[
        {
            "category":"Bars & Pubs",
            "type":"Food & Drink"
        }
    ],
    "sg:phone":"+44 20 8965 0228",
    "sg:postcode":"NW10 4TS",
    "sg:province":"Greater London",
    "sg:tags":[
        "pubs",
        "inn"
    ],
    "wof:name":"The Royal Oak",
    "wof:placetype":"venue"
},
  "geometry": {"coordinates":[-0.228872,51.547085],"type":"Point"}
}