{
  "type": "Feature",
  "properties": {
    "addr:full":"34 North Vennel Lanark South Lanarkshire ML11 7LY",
    "addr:housenumber":"34",
    "addr:postcode":"ml11 7ly",
    "addr:street":"North Vennel",
    "iso:country":"GB",
    "sg:address":"34 North Vennel",
    "sg:city":"Lanark",
    "sg:classifiers":[
        {
            "category":"Professional",
            "subcategory":"Printing & Photocopies",
            "type":"Services"
        }
    ],
    "sg:phone":"+44 1555 663657",
    "sg:postcode":"ML11 7LY",
    "sg:province":"South Lanarkshire",
    "sg:tags":[
        "printer"
    ],
    "wof:name":"T Houston Printers Lanark",
    "wof:placetype":"venue"
},
  "geometry": {"coordinates":[-3.780382,55.674496],"type":"Point"}
}