{
  "type": "Feature",
  "properties": {
    "addr:full":"4 Hayes Rd Clacton-on-sea Essex CO15 1TX",
    "addr:housenumber":"4",
    "addr:postcode":"co15 1tx",
    "addr:street":"Hayes Rd",
    "iso:country":"GB",
    "sg:address":"4 Hayes Rd",
    "sg:city":"Clacton-on-sea",
    "sg:classifiers":[
        {
            "category":"Military Area",
            "subcategory":"Air Force Base",
            "type":"Public Place"
        }
    ],
    "sg:postcode":"CO15 1TX",
    "sg:province":"Essex",
    "sg:tags":[
        "taxi",
        "hire",
        "private"
    ],
    "wof:name":"Temple,Alan,",
    "wof:placetype":"venue"
},
  "geometry": {"coordinates":[1.1519340277,51.7904014587],"type":"Point"}
}