{
  "type": "Feature",
  "properties": {
    "addr:full":"52 Sandy Lane, Fair Oak Eastleigh Hampshire SO50 8GB",
    "addr:housenumber":"52",
    "addr:postcode":"so50 8gb",
    "addr:street":"Sandy Lane",
    "iso:country":"GB",
    "sg:address":"52 Sandy Lane, Fair Oak",
    "sg:city":"Eastleigh",
    "sg:classifiers":[
        {
            "category":"Shopping",
            "type":"Retail Goods"
        }
    ],
    "sg:phone":"+44 23 8060 0989",
    "sg:postcode":"SO50 8GB",
    "sg:province":"Hampshire",
    "sg:tags":[
        "part",
        "accessory"
    ],
    "wof:name":"Autostop",
    "wof:placetype":"venue"
},
  "geometry": {"coordinates":[-1.304284,50.967857],"type":"Point"}
}