{
  "type": "Feature",
  "properties": {
    "addr:full":"84 Tollesbury Road, Tolleshunt D'arcy Maldon Essex CM9 8UB",
    "addr:housenumber":"84",
    "addr:postcode":"cm9 8ub",
    "addr:street":"Tollesbury Road",
    "iso:country":"GB",
    "sg:address":"84 Tollesbury Road, Tolleshunt D'arcy",
    "sg:city":"Maldon",
    "sg:classifiers":[
        {
            "category":"Professional",
            "type":"Services"
        }
    ],
    "sg:phone":"+44 1621 868029",
    "sg:postcode":"CM9 8UB",
    "sg:province":"Essex",
    "sg:tags":[
        "entertainer"
    ],
    "wof:name":"Ron Lang",
    "wof:placetype":"venue"
},
  "geometry": {"coordinates":[0.796626,51.771435],"type":"Point"}
}