{
  "type": "Feature",
  "properties": {
    "addr:full":"18 St Marys Gate Rochdale Lancashire OL16 1DZ",
    "addr:housenumber":"18",
    "addr:postcode":"ol16 1dz",
    "addr:street":"St Marys Gate",
    "iso:country":"GB",
    "sg:address":"18 St Marys Gate",
    "sg:city":"Rochdale",
    "sg:classifiers":[
        {
            "category":"Building & Trades",
            "subcategory":"Landscaping Services",
            "type":"Services"
        }
    ],
    "sg:phone":"+44 1706 647211",
    "sg:postcode":"OL16 1DZ",
    "sg:province":"Lancashire",
    "sg:tags":[
        "pond",
        "aquarium"
    ],
    "wof:name":"Kays Fishing Tackle & Aquarium Supplies",
    "wof:placetype":"venue"
},
  "geometry": {"coordinates":[-2.1568939686,53.6196556091],"type":"Point"}
}