{
  "type": "Feature",
  "properties": {
    "addr:full":"154 London Road Mitcham Greater London CR4 3LD",
    "addr:housenumber":"154",
    "addr:postcode":"cr4 3ld",
    "addr:street":"London Road",
    "iso:country":"GB",
    "sg:address":"154 London Road",
    "sg:city":"Mitcham",
    "sg:classifiers":[
        {
            "category":"Food & Beverages",
            "subcategory":"Meat & Fish",
            "type":"Retail Goods"
        }
    ],
    "sg:phone":"+44 20 8648 1221",
    "sg:postcode":"CR4 3LD",
    "sg:province":"Greater London",
    "sg:tags":[
        "chip"
    ],
    "wof:name":"Oysters Fish Bar",
    "wof:placetype":"venue"
},
  "geometry": {"coordinates":[-0.161747,51.411339],"type":"Point"}
}