{
  "type": "Feature",
  "properties": {
    "addr:full":"35-37 Cardigan Road Bournemouth Dorset BH9 1BD",
    "addr:housenumber":"35-37",
    "addr:postcode":"bh9 1bd",
    "addr:street":"Cardigan Road",
    "iso:country":"GB",
    "sg:address":"35-37 Cardigan Road",
    "sg:city":"Bournemouth",
    "sg:classifiers":[
        {
            "category":"Building & Trades",
            "subcategory":"Construction",
            "type":"Services"
        }
    ],
    "sg:phone":"+44 1202 519963",
    "sg:postcode":"BH9 1BD",
    "sg:province":"Dorset",
    "sg:tags":[
        "platform",
        "work",
        "scaffolding"
    ],
    "wof:name":"Terrence Pitman",
    "wof:placetype":"venue"
},
  "geometry": {"coordinates":[-1.8755940199,50.7408866882],"type":"Point"}
}