{
  "type": "Feature",
  "properties": {
    "iso:country":"GB",
    "sg:address":"Woodbine Farm, Back Lane, Cross In Hand",
    "sg:city":"Heathfield",
    "sg:classifiers":[
        {
            "category":"Farming",
            "subcategory":"Crops",
            "type":"Manufacturing & Wholesale Goods"
        },
        {
            "category":"Farming",
            "subcategory":"Livestock Farm",
            "type":"Manufacturing & Wholesale Goods"
        }
    ],
    "sg:phone":"+44 1435 867458",
    "sg:postcode":"TN21 0QA",
    "sg:province":"East Sussex",
    "sg:tags":[
        "arable",
        "others"
    ],
    "wof:name":"H H Harvey & Sons",
    "wof:placetype":"venue"
},
  "geometry": {"coordinates":[0.225756,50.973572],"type":"Point"}
}