{
  "type": "Feature",
  "properties": {
    "addr:full":"76-80 Goring Road Worthing West Sussex BN12 4AB",
    "addr:housenumber":"76-80",
    "addr:postcode":"bn12 4ab",
    "addr:street":"Goring Road",
    "iso:country":"GB",
    "sg:address":"76-80 Goring Road",
    "sg:city":"Worthing",
    "sg:classifiers":[
        {
            "category":"Shopping",
            "subcategory":"Clothing, Apparel, & Fashions",
            "type":"Retail Goods"
        }
    ],
    "sg:phone":"+44 1903 247701",
    "sg:postcode":"BN12 4AB",
    "sg:province":"West Sussex",
    "sg:tags":[
        "dresswear"
    ],
    "wof:name":"Dickies Dress Hire",
    "wof:placetype":"venue"
},
  "geometry": {"coordinates":[-0.4044530094,50.813293457],"type":"Point"}
}