{
  "type": "Feature",
  "properties": {
    "addr:full":"15 Trough Gate Oldham Lancashire OL8 3TH",
    "addr:housenumber":"15",
    "addr:postcode":"ol8 3th",
    "addr:street":"Trough Gate",
    "iso:country":"GB",
    "sg:address":"15 Trough Gate",
    "sg:city":"Oldham",
    "sg:classifiers":[
        {
            "category":"Personal",
            "subcategory":"Beauty Salon",
            "type":"Services"
        },
        {
            "category":"Personal",
            "subcategory":"Barber",
            "type":"Services"
        }
    ],
    "sg:phone":"+44 161 652 8698",
    "sg:postcode":"OL8 3TH",
    "sg:province":"Lancashire",
    "sg:tags":[
        "unisex",
        "hairdresser"
    ],
    "wof:name":"Options Ladies Hairdressers",
    "wof:placetype":"venue"
},
  "geometry": {"coordinates":[-2.123188,53.522617],"type":"Point"}
}