{
  "type": "Feature",
  "properties": {
    "addr:full":"Unit 6 Marshlands Road Portsmouth Hampshire PO6 1ST",
    "addr:housenumber":"unit 6",
    "addr:postcode":"hampshire po6 1st",
    "addr:street":"Marshlands Road",
    "iso:country":"GB",
    "sg:address":"Unit 6 Marshlands Road",
    "sg:city":"Portsmouth",
    "sg:classifiers":[
        {
            "category":"Manufacturing",
            "subcategory":"Glass & Minerals",
            "type":"Manufacturing & Wholesale Goods"
        }
    ],
    "sg:phone":"+44 23 9221 4113",
    "sg:postcode":"PO6 1ST",
    "sg:province":"Hampshire",
    "sg:tags":[
        "stained"
    ],
    "wof:name":"S G O Decorative Glass",
    "wof:placetype":"venue"
},
  "geometry": {"coordinates":[-1.03563,50.841789],"type":"Point"}
}