{
  "type": "Feature",
  "properties": {
    "addr:full":"7 Wardour Street London Greater London W1D 6PB",
    "addr:housenumber":"7",
    "addr:postcode":"w1d 6pb",
    "addr:street":"Wardour Street",
    "iso:country":"GB",
    "sg:address":"7 Wardour Street",
    "sg:city":"London",
    "sg:classifiers":[
        {
            "category":"Shopping",
            "subcategory":"Pharmacy",
            "type":"Retail Goods"
        }
    ],
    "sg:postcode":"W1D 6PB",
    "sg:province":"Greater London",
    "sg:tags":[
        "pharmaceutical"
    ],
    "wof:name":"K T N T",
    "wof:placetype":"venue"
},
  "geometry": {"coordinates":[-0.1318320036,51.5106048584],"type":"Point"}
}