{
  "type": "Feature",
  "properties": {
    "iso:country":"GB",
    "sg:address":"1 Gloucester Road",
    "sg:city":"London",
    "sg:classifiers":[
        {
            "category":"Shopping",
            "subcategory":"Bicycles & Sporting Goods",
            "type":"Retail Goods"
        }
    ],
    "sg:postcode":"SW7 4PP",
    "sg:province":"Greater London",
    "sg:tags":[
        "water",
        "cooler"
    ],
    "wof:name":"Health-Spa Water Ltd.",
    "wof:placetype":"venue"
},
  "geometry": {"coordinates":[-0.183564,51.499088],"type":"Point"}
}