{
  "type": "Feature",
  "properties": {
    "iso:country":"GB",
    "sg:address":"1 Alexandra Gardens",
    "sg:city":"Folkestone",
    "sg:classifiers":[
        {
            "category":"Restaurant",
            "type":"Food & Drink"
        }
    ],
    "sg:phone":"+44 1303 242578",
    "sg:postcode":"CT20 1SS",
    "sg:province":"Kent",
    "wof:name":"Papa's",
    "wof:placetype":"venue"
},
  "geometry": {"coordinates":[1.178797,51.079376],"type":"Point"}
}