{
  "type": "Feature",
  "properties": {
    "iso:country":"GB",
    "sg:address":"16 Jacomb Road, Lower Broadheath",
    "sg:city":"Worcester",
    "sg:classifiers":[
        {
            "category":"Building & Trades",
            "subcategory":"Plumbing",
            "type":"Services"
        }
    ],
    "sg:phone":"+44 1905 640709",
    "sg:postcode":"WR2 6QW",
    "sg:province":"Worcestershire",
    "sg:tags":[
        "heating"
    ],
    "wof:name":"Domestic & Industrial Services",
    "wof:placetype":"venue"
},
  "geometry": {"coordinates":[-2.275796,52.214108],"type":"Point"}
}