{
  "type": "Feature",
  "properties": {
    "addr:full":"Unit B, 5-7 Wallyford Indstl Est, Wallyf Musselburgh City of Edinburgh EH21 8QJ",
    "addr:housenumber":"5-7",
    "addr:postcode":"eh21 8qj",
    "addr:street":"Indstl Est",
    "iso:country":"GB",
    "sg:address":"Unit B, 5-7 Wallyford Indstl Est, Wallyf",
    "sg:city":"Musselburgh",
    "sg:classifiers":[
        {
            "category":"Building & Trades",
            "subcategory":"Construction",
            "type":"Services"
        }
    ],
    "sg:postcode":"EH21 8QJ",
    "sg:province":"City of Edinburgh",
    "sg:tags":[
        "builder"
    ],
    "wof:name":"Heanley,T,",
    "wof:placetype":"venue"
},
  "geometry": {"coordinates":[-3.0143239498,55.9378700256],"type":"Point"}
}