{
  "type": "Feature",
  "properties": {
    "addr:full":"36 Kings Avenue Sunbury-on-thames Surrey TW16 7QE",
    "addr:housenumber":"36",
    "addr:postcode":"tw16 7qe",
    "addr:street":"Kings Avenue",
    "iso:country":"GB",
    "sg:address":"36 Kings Avenue",
    "sg:city":"Sunbury-on-thames",
    "sg:classifiers":[
        {
            "category":"Transit Center",
            "subcategory":"Passenger",
            "type":"Transportation"
        }
    ],
    "sg:postcode":"TW16 7QE",
    "sg:province":"Surrey",
    "sg:tags":[
        "boarding",
        "kennel",
        "catteries"
    ],
    "wof:name":"Fir Tree Cattery",
    "wof:placetype":"venue"
},
  "geometry": {"coordinates":[-0.421556,51.426884],"type":"Point"}
}