{
  "type": "Feature",
  "properties": {
    "addr:full":"Chessingham Pk, Common Rd, Dunnington York North Yorkshire YO19 5SE",
    "addr:postcode":"yo19 5se",
    "addr:street":"Chessingham Pk Common Rd",
    "iso:country":"GB",
    "sg:address":"Chessingham Pk, Common Rd, Dunnington",
    "sg:city":"York",
    "sg:classifiers":[
        {
            "category":"Retail",
            "subcategory":"Auto Repair",
            "type":"Services"
        }
    ],
    "sg:postcode":"YO19 5SE",
    "sg:province":"North Yorkshire",
    "sg:tags":[
        "modification",
        "garage"
    ],
    "wof:name":"Alwyn Kershaw",
    "wof:placetype":"venue"
},
  "geometry": {"coordinates":[-0.9734489918,53.9576416016],"type":"Point"}
}