{
  "type": "Feature",
  "properties": {
    "iso:country":"GB",
    "sg:address":"New Road",
    "sg:city":"Bromsgrove",
    "sg:classifiers":[
        {
            "category":"Community Center",
            "type":"Public Place"
        },
        {
            "category":"Community Center",
            "subcategory":"Youth",
            "type":"Public Place"
        },
        {
            "category":"Government",
            "subcategory":"Office",
            "type":"Public Place"
        }
    ],
    "sg:phone":"+44 1527 875207",
    "sg:postcode":"B60 2JS",
    "sg:province":"Worcestershire",
    "sg:tags":[
        "recreation",
        "local",
        "leisure",
        "centre"
    ],
    "wof:name":"The Ryland Centre",
    "wof:placetype":"venue"
},
  "geometry": {"coordinates":[-2.061075,52.334209],"type":"Point"}
}