{
  "type": "Feature",
  "properties": {
    "addr:full":"123 Hamlet Court Road Westcliff-on-sea Essex SS0 7EW",
    "addr:housenumber":"123",
    "addr:postcode":"ss0 7ew",
    "addr:street":"Hamlet Court Road",
    "iso:country":"GB",
    "sg:address":"123 Hamlet Court Road",
    "sg:city":"Westcliff-on-sea",
    "sg:classifiers":[
        {
            "category":"Food & Beverages",
            "subcategory":"Bakery",
            "type":"Retail Goods"
        }
    ],
    "sg:phone":"+44 1702 435678",
    "sg:postcode":"SS0 7EW",
    "sg:province":"Essex",
    "sg:tags":[
        "baker"
    ],
    "wof:name":"Westcliff Hot Beigel Bakery",
    "wof:placetype":"venue"
},
  "geometry": {"coordinates":[0.6942420006,51.5400314331],"type":"Point"}
}