{
  "type": "Feature",
  "properties": {
    "iso:country":"GB",
    "sg:address":"144 Church Road",
    "sg:city":"Hove",
    "sg:classifiers":[
        {
            "category":"Shopping",
            "subcategory":"Mobile Phones",
            "type":"Retail Goods"
        }
    ],
    "sg:phone":"+44 1273 740003",
    "sg:postcode":"BN3 2DL",
    "sg:province":"East Sussex",
    "wof:name":"Autocall Mobile Phone Centre",
    "wof:placetype":"venue"
},
  "geometry": {"coordinates":[-0.1744499952,50.8281021118],"type":"Point"}
}