{
  "type": "Feature",
  "properties": {
    "addr:full":"Eurorent House, Slade Green Road Erith Kent DA8 2HU",
    "addr:postcode":"da8 2hu",
    "addr:street":"Slade Green Road",
    "iso:country":"GB",
    "sg:address":"Eurorent House, Slade Green Road",
    "sg:city":"Erith",
    "sg:classifiers":[
        {
            "category":"Professional",
            "subcategory":"Computer Services",
            "type":"Services"
        }
    ],
    "sg:phone":"+44 1322 345645",
    "sg:postcode":"DA8 2HU",
    "sg:province":"Kent",
    "sg:tags":[
        "system",
        "software"
    ],
    "wof:name":"Eurorent U K Ltd.",
    "wof:placetype":"venue"
},
  "geometry": {"coordinates":[0.1952189952,51.4746513367],"type":"Point"}
}