{
  "type": "Feature",
  "properties": {
    "iso:country":"GB",
    "sg:address":"St Matthias Centre, Church Road",
    "sg:city":"Richmond",
    "sg:classifiers":[
        {
            "category":"Health Services",
            "subcategory":"Health Practitioner",
            "type":"Services"
        }
    ],
    "sg:postcode":"TW10 6LX",
    "sg:province":"Greater London",
    "sg:tags":[
        "homoeopathic"
    ],
    "wof:name":"Richmond Homoeopathic Clinic",
    "wof:placetype":"venue"
},
  "geometry": {"coordinates":[-0.2974199951,51.4603805542],"type":"Point"}
}