{
  "type": "Feature",
  "properties": {
    "addr:full":"Main Rd, Marlesford Woodbridge Suffolk IP13 0AY",
    "addr:postcode":"ip13 0ay",
    "addr:street":"Main Rd",
    "iso:country":"GB",
    "sg:address":"Main Rd, Marlesford",
    "sg:city":"Woodbridge",
    "sg:classifiers":[
        {
            "category":"Bars & Pubs",
            "type":"Food & Drink"
        }
    ],
    "sg:phone":"+44 1728 746242",
    "sg:postcode":"IP13 0AY",
    "sg:province":"Suffolk",
    "sg:tags":[
        "pubs",
        "inn"
    ],
    "wof:name":"The Bell",
    "wof:placetype":"venue"
},
  "geometry": {"coordinates":[1.398567,52.173435],"type":"Point"}
}