{
  "type": "Feature",
  "properties": {
    "addr:full":"191 Shawbridge Street Glasgow Glasgow City G43 1QN",
    "addr:housenumber":"191",
    "addr:postcode":"g43 1qn",
    "addr:street":"Shawbridge Street",
    "iso:country":"GB",
    "sg:address":"191 Shawbridge Street",
    "sg:city":"Glasgow",
    "sg:classifiers":[
        {
            "category":"Fast Food",
            "type":"Food & Drink"
        }
    ],
    "sg:phone":"+44 141 632 0091",
    "sg:postcode":"G43 1QN",
    "sg:province":"Glasgow City",
    "sg:tags":[
        "away",
        "meal",
        "outlet",
        "take"
    ],
    "wof:name":"Golden Cuisine",
    "wof:placetype":"venue"
},
  "geometry": {"coordinates":[-4.298511982,55.82289505],"type":"Point"}
}