{
  "type": "Feature",
  "properties": {
    "iso:country":"GB",
    "sg:address":"Regional Office, Waterloo House, 40 Baker Street",
    "sg:city":"Weybridge",
    "sg:classifiers":[
        {
            "category":"Real Estate",
            "subcategory":"Surveying",
            "type":"Services"
        },
        {
            "category":"Real Estate",
            "subcategory":"Real Estate Agent",
            "type":"Services"
        }
    ],
    "sg:phone":"+44 1932 857811",
    "sg:postcode":"KT13 8AR",
    "sg:province":"Surrey",
    "sg:tags":[
        "surveyor",
        "valuer"
    ],
    "wof:name":"Bradford & Bingley Building Society",
    "wof:placetype":"venue"
},
  "geometry": {"coordinates":[-0.456768,51.372215],"type":"Point"}
}