{
  "type": "Feature",
  "properties": {
    "iso:country":"GB",
    "sg:address":"31a Broadwater Road, Leeway Industrial Estate",
    "sg:city":"Newport",
    "sg:classifiers":[
        {
            "category":"Building & Trades",
            "subcategory":"Construction",
            "type":"Services"
        }
    ],
    "sg:phone":"+44 1633 278545",
    "sg:postcode":"NP19 4SN",
    "sg:province":"Newport",
    "sg:tags":[
        "scaffolding",
        "builder",
        "work",
        "platform",
        "erectors",
        "scaffold"
    ],
    "wof:name":"Rushar Ltd.",
    "wof:placetype":"venue"
},
  "geometry": {"coordinates":[-2.947604,51.570469],"type":"Point"}
}