{
  "type": "Feature",
  "properties": {
    "addr:full":"73 Doncaster Rd, Goldthorpe Rotherham South Yorkshire S63 9HJ",
    "addr:housenumber":"73",
    "addr:postcode":"s63 9hj",
    "addr:street":"Doncaster Rd",
    "iso:country":"GB",
    "sg:address":"73 Doncaster Rd, Goldthorpe",
    "sg:city":"Rotherham",
    "sg:classifiers":[
        {
            "category":"Food & Beverages",
            "subcategory":"Bakery",
            "type":"Retail Goods"
        }
    ],
    "sg:phone":"+44 1709 881595",
    "sg:postcode":"S63 9HJ",
    "sg:province":"South Yorkshire",
    "sg:tags":[
        "baker"
    ],
    "wof:name":"Allass & Son",
    "wof:placetype":"venue"
},
  "geometry": {"coordinates":[-1.3006,53.534718],"type":"Point"}
}