{
  "type": "Feature",
  "properties": {
    "addr:full":"19-35 Warwick Street, Earlsdon Coventry West Midlands CV5 6ET",
    "addr:housenumber":"19-35",
    "addr:postcode":"cv5 6et",
    "addr:street":"Warwick Street",
    "iso:country":"GB",
    "sg:address":"19-35 Warwick Street, Earlsdon",
    "sg:city":"Coventry",
    "sg:classifiers":[
        {
            "category":"Building & Trades",
            "subcategory":"Construction",
            "type":"Services"
        },
        {
            "category":"Utilities",
            "subcategory":"Natural Gas",
            "type":"Services"
        }
    ],
    "sg:phone":"+44 24 7667 2224",
    "sg:postcode":"CV5 6ET",
    "sg:province":"West Midlands",
    "sg:tags":[
        "control",
        "management",
        "system",
        "energy",
        "heating",
        "contractor"
    ],
    "wof:name":"Heating & Industrial Pipework Ltd.",
    "wof:placetype":"venue"
},
  "geometry": {"coordinates":[-1.533651948,52.3990135193],"type":"Point"}
}