{
  "type": "Feature",
  "properties": {
    "addr:full":"25 Moorfield Ave Manchester Greater Manchester M34 7TF",
    "addr:housenumber":"25",
    "addr:postcode":"m34 7tf",
    "addr:street":"Moorfield Ave",
    "iso:country":"GB",
    "sg:address":"25 Moorfield Ave",
    "sg:city":"Manchester",
    "sg:classifiers":[
        {
            "category":"Home & Garden",
            "subcategory":"Hardware",
            "type":"Retail Goods"
        }
    ],
    "sg:postcode":"M34 7TF",
    "sg:province":"Greater Manchester",
    "wof:name":"Mitchell,George,",
    "wof:placetype":"venue"
},
  "geometry": {"coordinates":[-2.1043241024,53.4476966858],"type":"Point"}
}