{
  "type": "Feature",
  "properties": {
    "addr:full":"75-83 Brighton Road Coulsdon Surrey CR5 3EG",
    "addr:housenumber":"75-83",
    "addr:postcode":"cr5 3eg",
    "addr:street":"Brighton Road",
    "iso:country":"GB",
    "sg:address":"75-83 Brighton Road",
    "sg:city":"Coulsdon",
    "sg:classifiers":[
        {
            "category":"Autos & Motor Vehicles",
            "subcategory":"Fuel & Gas Station",
            "type":"Retail Goods"
        }
    ],
    "sg:phone":"+44 1737 554390",
    "sg:postcode":"CR5 3EG",
    "sg:province":"Surrey",
    "sg:tags":[
        "hr",
        "petrol"
    ],
    "wof:name":"Hooley Service Station",
    "wof:placetype":"venue"
},
  "geometry": {"coordinates":[-0.1544629931,51.2910690308],"type":"Point"}
}