{
  "type": "Feature",
  "properties": {
    "iso:country":"GB",
    "sg:address":"17 Linhope Street",
    "sg:city":"London",
    "sg:classifiers":[
        {
            "category":"Professional",
            "subcategory":"Business Services",
            "type":"Services"
        }
    ],
    "sg:postcode":"NW1 6HT",
    "sg:province":"Greater London",
    "sg:tags":[
        "holding"
    ],
    "wof:name":"Winslade Management",
    "wof:placetype":"venue"
},
  "geometry": {"coordinates":[-0.161745,51.524723],"type":"Point"}
}