{
  "type": "Feature",
  "properties": {
    "addr:full":"17 Linhope Street London Greater London NW1 6HT",
    "addr:housenumber":"17",
    "addr:postcode":"nw1 6ht",
    "addr:street":"Linhope Street",
    "iso:country":"GB",
    "sg:address":"17 Linhope Street",
    "sg:city":"London",
    "sg:classifiers":[
        {
            "category":"Professional",
            "subcategory":"Business Services",
            "type":"Services"
        }
    ],
    "sg:postcode":"NW1 6HT",
    "sg:province":"Greater London",
    "sg:tags":[
        "holding"
    ],
    "wof:name":"Winslade Management",
    "wof:placetype":"venue"
},
  "geometry": {"coordinates":[-0.161745,51.524723],"type":"Point"}
}