{
  "type": "Feature",
  "properties": {
    "addr:full":"23 Ismay Road Cheltenham Gloucestershire GL51 0EL",
    "addr:housenumber":"23",
    "addr:postcode":"gl51 0el",
    "addr:street":"Ismay Road",
    "iso:country":"GB",
    "sg:address":"23 Ismay Road",
    "sg:city":"Cheltenham",
    "sg:classifiers":[
        {
            "category":"Bars & Pubs",
            "subcategory":"Nightclub",
            "type":"Food & Drink"
        },
        {
            "category":"Communications",
            "type":"Services"
        }
    ],
    "sg:phone":"+44 1242 255065",
    "sg:postcode":"GL51 0EL",
    "sg:province":"Gloucestershire",
    "sg:tags":[
        "tv",
        "video",
        "karaoke",
        "radio"
    ],
    "wof:name":"KARAOKE DISCO SERVICES",
    "wof:placetype":"venue"
},
  "geometry": {"coordinates":[-2.1104340553,51.9115829468],"type":"Point"}
}