{
  "type": "Feature",
  "properties": {
    "addr:full":"83 Friars Vennel Dumfries Dumfries and Galloway DG1 2RF",
    "addr:housenumber":"83",
    "addr:postcode":"dg1 2rf",
    "addr:street":"Friars Vennel",
    "iso:country":"GB",
    "sg:address":"83 Friars Vennel",
    "sg:city":"Dumfries",
    "sg:classifiers":[
        {
            "category":"Professional",
            "subcategory":"Lawyer & Legal Services",
            "type":"Services"
        }
    ],
    "sg:phone":"+44 1387 263939",
    "sg:postcode":"DG1 2RF",
    "sg:province":"Dumfries and Galloway",
    "sg:tags":[
        "solicitor"
    ],
    "wof:name":"Austins",
    "wof:placetype":"venue"
},
  "geometry": {"coordinates":[-3.6126630306,55.0699234009],"type":"Point"}
}