{
  "type": "Feature",
  "properties": {
    "addr:full":"2b Curbridge Road Witney Oxfordshire OX28 5JR",
    "addr:housenumber":"2b",
    "addr:postcode":"ox28 5jr",
    "addr:street":"Curbridge Road",
    "iso:country":"GB",
    "sg:address":"2b Curbridge Road",
    "sg:city":"Witney",
    "sg:classifiers":[
        {
            "category":"Shopping",
            "subcategory":"Clothing, Apparel, & Fashions",
            "type":"Retail Goods"
        }
    ],
    "sg:phone":"+44 1993 772386",
    "sg:postcode":"OX28 5JR",
    "sg:province":"Oxfordshire",
    "sg:tags":[
        "dresswear"
    ],
    "wof:name":"Special Occasion",
    "wof:placetype":"venue"
},
  "geometry": {"coordinates":[-1.4977890253,51.7850227356],"type":"Point"}
}