{
  "type": "Feature",
  "properties": {
    "addr:full":"7 Mount Pleasant, Bridge Of Don Aberdeen Aberdeen City AB23 8ES",
    "addr:housenumber":"7",
    "addr:postcode":"ab23 8es",
    "addr:street":"Mount Pleasant",
    "iso:country":"GB",
    "sg:address":"7 Mount Pleasant, Bridge Of Don",
    "sg:city":"Aberdeen",
    "sg:classifiers":[
        {
            "category":"Professional",
            "subcategory":"Art Services",
            "type":"Services"
        },
        {
            "category":"Building & Trades",
            "subcategory":"Construction",
            "type":"Services"
        }
    ],
    "sg:phone":"+44 1224 820357",
    "sg:postcode":"AB23 8ES",
    "sg:province":"Aberdeen City",
    "sg:tags":[
        "glazier",
        "decorator",
        "painter"
    ],
    "wof:name":"Balmedie Decorating Services",
    "wof:placetype":"venue"
},
  "geometry": {"coordinates":[-2.0923559666,57.1790885925],"type":"Point"}
}