{
  "type": "Feature",
  "properties": {
    "addr:full":"4 Faraday Road Glenrothes Fife KY6 2RU",
    "addr:housenumber":"4",
    "addr:postcode":"ky6 2ru",
    "addr:street":"Faraday Road",
    "iso:country":"GB",
    "sg:address":"4 Faraday Road",
    "sg:city":"Glenrothes",
    "sg:classifiers":[
        {
            "category":"Professional",
            "subcategory":"Printing & Photocopies",
            "type":"Services"
        }
    ],
    "sg:phone":"+44 1592 776870",
    "sg:postcode":"KY6 2RU",
    "sg:province":"Fife",
    "sg:tags":[
        "printer"
    ],
    "wof:name":"Barr Printers Glenrothes Ltd.",
    "wof:placetype":"venue"
},
  "geometry": {"coordinates":[-3.194349,56.180481],"type":"Point"}
}