{
  "type": "Feature",
  "properties": {
    "addr:full":"5 Fore Street, Plympton Plymouth Devon PL7 1LZ",
    "addr:housenumber":"5",
    "addr:postcode":"pl7 1lz",
    "addr:street":"Fore Street",
    "iso:country":"GB",
    "sg:address":"5 Fore Street, Plympton",
    "sg:city":"Plymouth",
    "sg:classifiers":[
        {
            "category":"Professional",
            "type":"Services"
        },
        {
            "category":"Building & Trades",
            "subcategory":"Construction",
            "type":"Services"
        }
    ],
    "sg:postcode":"PL7 1LZ",
    "sg:province":"Devon",
    "sg:tags":[
        "joiner",
        "carpenter",
        "shopfitters"
    ],
    "wof:name":"Insight Design & Contract Services",
    "wof:placetype":"venue"
},
  "geometry": {"coordinates":[-4.0469408035,50.3828468323],"type":"Point"}
}