{
  "type": "Feature",
  "properties": {
    "addr:full":"28 Bodmin Av Wigston Leicestershire LE18 2HB",
    "addr:housenumber":"28",
    "addr:postcode":"le18 2hb",
    "addr:street":"Bodmin Av Wigston",
    "iso:country":"GB",
    "sg:address":"28 Bodmin Av",
    "sg:city":"Wigston",
    "sg:classifiers":[
        {
            "category":"Professional",
            "subcategory":"Engineering",
            "type":"Services"
        }
    ],
    "sg:phone":"+44 116 288 0912",
    "sg:postcode":"LE18 2HB",
    "sg:province":"Leicestershire",
    "sg:tags":[
        "contractor",
        "electrical",
        "engineer"
    ],
    "wof:name":"Faim Electrical Services",
    "wof:placetype":"venue"
},
  "geometry": {"coordinates":[-1.1094700098,52.5755462646],"type":"Point"}
}