{
  "type": "Feature",
  "properties": {
    "addr:full":"35 Park Rd Camden Greater London NW1 6XT",
    "addr:housenumber":"35",
    "addr:postcode":"nw1 6xt",
    "addr:street":"Park Rd",
    "iso:country":"GB",
    "sg:address":"35 Park Rd",
    "sg:city":"Camden",
    "sg:classifiers":[
        {
            "category":"Shopping",
            "subcategory":"Books",
            "type":"Retail Goods"
        }
    ],
    "sg:phone":"+44 20 7723 4400",
    "sg:postcode":"NW1 6XT",
    "sg:province":"Greater London",
    "sg:tags":[
        "bookseller"
    ],
    "wof:name":"Rudolf Steiner House & Bookshop",
    "wof:placetype":"venue"
},
  "geometry": {"coordinates":[-0.1603,51.525059],"type":"Point"}
}