{
  "type": "Feature",
  "properties": {
    "iso:country":"GB",
    "sg:address":"57 Rhosmaen Street",
    "sg:city":"Llandeilo",
    "sg:classifiers":[
        {
            "category":"Bars & Pubs",
            "type":"Food & Drink"
        }
    ],
    "sg:postcode":"SA19 6LW",
    "sg:province":"Carmarthenshire",
    "sg:tags":[
        "pubs",
        "inn"
    ],
    "wof:name":"Farmers Arms",
    "wof:placetype":"venue"
},
  "geometry": {"coordinates":[-3.990432,51.88538],"type":"Point"}
}