{
  "type": "Feature",
  "properties": {
    "iso:country":"GB",
    "sg:address":"59 Oxford Street, Pontycymmer",
    "sg:city":"Bridgend",
    "sg:classifiers":[
        {
            "category":"Manufacturing",
            "subcategory":"Tools & Machinery",
            "type":"Manufacturing & Wholesale Goods"
        }
    ],
    "sg:phone":"+44 1656 871597",
    "sg:postcode":"CF32 8DE",
    "sg:province":"Bridgend",
    "sg:tags":[
        "society",
        "friendly"
    ],
    "wof:name":"Garw Insurance Consultants",
    "wof:placetype":"venue"
},
  "geometry": {"coordinates":[-3.5840220451,51.6099510193],"type":"Point"}
}