{
  "type": "Feature",
  "properties": {
    "addr:full":"Unit 203, Blackburn Market Blackburn Lancashire BB1 6AF",
    "addr:housenumber":"203",
    "addr:postcode":"bb1 6af",
    "addr:street":"Blackburn Market",
    "iso:country":"GB",
    "sg:address":"Unit 203, Blackburn Market",
    "sg:city":"Blackburn",
    "sg:classifiers":[
        {
            "category":"Shopping",
            "subcategory":"Crafts & Fabrics",
            "type":"Retail Goods"
        }
    ],
    "sg:phone":"+44 1254 673322",
    "sg:postcode":"BB1 6AF",
    "sg:province":"Lancashire",
    "sg:tags":[
        "lace"
    ],
    "wof:name":"A.V & C Sandler Ltd",
    "wof:placetype":"venue"
},
  "geometry": {"coordinates":[-2.482239,53.754799],"type":"Point"}
}