{
  "type": "Feature",
  "properties": {
    "addr:full":"10 Jeffrey Street Edinburgh City of Edinburgh EH1 1DT",
    "addr:housenumber":"10",
    "addr:postcode":"eh1 1dt",
    "addr:street":"Jeffrey Street",
    "iso:country":"GB",
    "sg:address":"10 Jeffrey Street",
    "sg:city":"Edinburgh",
    "sg:classifiers":[
        {
            "category":"Personal",
            "subcategory":"Beauty Salon",
            "type":"Services"
        },
        {
            "category":"Personal",
            "subcategory":"Barber",
            "type":"Services"
        }
    ],
    "sg:phone":"+44 131 556 1475",
    "sg:postcode":"EH1 1DT",
    "sg:province":"City of Edinburgh",
    "sg:tags":[
        "unisex",
        "hairdresser"
    ],
    "wof:name":"Saks",
    "wof:placetype":"venue"
},
  "geometry": {"coordinates":[-3.1855349541,55.951461792],"type":"Point"}
}