{
  "type": "Feature",
  "properties": {
    "addr:full":"52b Stratford Road, West Bridgford Nottingham Nottinghamshire NG2 6BA",
    "addr:housenumber":"52b",
    "addr:postcode":"ng2 6ba",
    "addr:street":"Stratford Road",
    "iso:country":"GB",
    "sg:address":"52b Stratford Road, West Bridgford",
    "sg:city":"Nottingham",
    "sg:classifiers":[
        {
            "category":"Shopping",
            "subcategory":"Computers & Home Electronics",
            "type":"Retail Goods"
        }
    ],
    "sg:phone":"+44 115 981 6065",
    "sg:postcode":"NG2 6BA",
    "sg:province":"Nottinghamshire",
    "sg:tags":[
        "aerial",
        "television",
        "radio"
    ],
    "wof:name":"Trent Aerial Service",
    "wof:placetype":"venue"
},
  "geometry": {"coordinates":[-1.1300270557,52.9322013855],"type":"Point"}
}