{
  "type": "Feature",
  "properties": {
    "addr:full":"32 The Mall Montrose Aberdeenshire DD10 8SS",
    "addr:housenumber":"32",
    "addr:postcode":"dd10 8ss",
    "addr:street":"The Mall",
    "iso:country":"GB",
    "sg:address":"32 The Mall",
    "sg:city":"Montrose",
    "sg:classifiers":[
        {
            "category":"Professional",
            "subcategory":"Management & Consulting",
            "type":"Services"
        }
    ],
    "sg:phone":"+44 1674 672900",
    "sg:postcode":"DD10 8SS",
    "sg:province":"Aberdeenshire",
    "sg:tags":[
        "consultant",
        "business"
    ],
    "wof:name":"Q A Consultancy Services",
    "wof:placetype":"venue"
},
  "geometry": {"coordinates":[-2.4661879539,56.7184181213],"type":"Point"}
}