{
  "type": "Feature",
  "properties": {
    "addr:full":"Summerleys Farm, Leighton Road, Great Billington Leighton Buzzard Bedfordshire LU7 9BJ",
    "addr:postcode":"lu7 9bj",
    "addr:street":"Leighton Road",
    "iso:country":"GB",
    "sg:address":"Summerleys Farm, Leighton Road, Great Billington",
    "sg:city":"Leighton Buzzard",
    "sg:classifiers":[
        {
            "category":"Farming",
            "subcategory":"Crops",
            "type":"Manufacturing & Wholesale Goods"
        },
        {
            "category":"Farming",
            "subcategory":"Livestock Farm",
            "type":"Manufacturing & Wholesale Goods"
        }
    ],
    "sg:phone":"+44 1525 220280",
    "sg:postcode":"LU7 9BJ",
    "sg:province":"Bedfordshire",
    "sg:tags":[
        "arable",
        "others"
    ],
    "wof:name":"W Adams & Sons",
    "wof:placetype":"venue"
},
  "geometry": {"coordinates":[-0.634235,51.895092],"type":"Point"}
}