{
  "type": "Feature",
  "properties": {
    "addr:full":"Brewery Lane, Thornhill Leas Dewsbury West Yorkshire WF12 9HU",
    "addr:postcode":"wf12 9hu",
    "addr:street":"Brewery Lane",
    "iso:country":"GB",
    "sg:address":"Brewery Lane, Thornhill Leas",
    "sg:city":"Dewsbury",
    "sg:classifiers":[
        {
            "category":"Shopping",
            "subcategory":"Clothing, Apparel, & Fashions",
            "type":"Retail Goods"
        }
    ],
    "sg:phone":"+44 1924 509509",
    "sg:postcode":"WF12 9HU",
    "sg:province":"West Yorkshire",
    "sg:tags":[
        "workwear",
        "protective",
        "clothing"
    ],
    "wof:name":"Applied Visibility Ltd.",
    "wof:placetype":"venue"
},
  "geometry": {"coordinates":[-1.635924,53.675404],"type":"Point"}
}