{
  "type": "Feature",
  "properties": {
    "addr:full":"The Raveningham Centre Norwich Norfolk NR14 6NU",
    "addr:postcode":"nr14 6nu",
    "addr:street":"Norwich",
    "iso:country":"GB",
    "sg:address":"The Raveningham Centre",
    "sg:city":"Norwich",
    "sg:classifiers":[
        {
            "category":"Home & Garden",
            "subcategory":"Furniture",
            "type":"Retail Goods"
        }
    ],
    "sg:phone":"+44 1508 548406",
    "sg:postcode":"NR14 6NU",
    "sg:province":"Norfolk",
    "wof:name":"Country Pine",
    "wof:placetype":"venue"
},
  "geometry": {"coordinates":[1.5342919827,52.5188484192],"type":"Point"}
}