{
  "type": "Feature",
  "properties": {
    "addr:full":"35 Market Place Oakham Leicestershire LE15 6DT",
    "addr:housenumber":"35",
    "addr:postcode":"le15 6dt",
    "addr:street":"Market Place",
    "iso:country":"GB",
    "sg:address":"35 Market Place",
    "sg:city":"Oakham",
    "sg:classifiers":[
        {
            "category":"Professional",
            "subcategory":"Lawyer & Legal Services",
            "type":"Services"
        }
    ],
    "sg:phone":"+44 1572 722002",
    "sg:postcode":"LE15 6DT",
    "sg:province":"Leicestershire",
    "sg:tags":[
        "solicitor"
    ],
    "wof:name":"Daltons",
    "wof:placetype":"venue"
},
  "geometry": {"coordinates":[-0.728046,52.6704177856],"type":"Point"}
}