{
  "type": "Feature",
  "properties": {
    "addr:full":"15-19 Greenhill Street Bedford Bedfordshire MK40 1LX",
    "addr:housenumber":"15-19",
    "addr:postcode":"mk40 1lx",
    "addr:street":"Greenhill Street",
    "iso:country":"GB",
    "sg:address":"15-19 Greenhill Street",
    "sg:city":"Bedford",
    "sg:classifiers":[
        {
            "category":"Community Center",
            "subcategory":"Social",
            "type":"Public Place"
        }
    ],
    "sg:phone":"+44 1234 356249",
    "sg:postcode":"MK40 1LX",
    "sg:province":"Bedfordshire",
    "sg:tags":[
        "frozen",
        "food",
        "freezer",
        "centre"
    ],
    "wof:name":"Iceland Foods Plc",
    "wof:placetype":"venue"
},
  "geometry": {"coordinates":[-0.470657,52.137932],"type":"Point"}
}