{
  "type": "Feature",
  "properties": {
    "addr:full":"57 Wilbury Crescent Hove East Sussex BN3 6FJ",
    "addr:housenumber":"57",
    "addr:postcode":"bn3 6fj",
    "addr:street":"Wilbury Crescent",
    "iso:country":"GB",
    "sg:address":"57 Wilbury Crescent",
    "sg:city":"Hove",
    "sg:classifiers":[
        {
            "category":"Real Estate",
            "subcategory":"Surveying",
            "type":"Services"
        }
    ],
    "sg:postcode":"BN3 6FJ",
    "sg:province":"East Sussex",
    "sg:tags":[
        "surveyor",
        "quantity"
    ],
    "wof:name":"A P T Services",
    "wof:placetype":"venue"
},
  "geometry": {"coordinates":[-0.160131,50.834328],"type":"Point"}
}