{
  "type": "Feature",
  "properties": {
    "addr:full":"Eastern Area, Cobham Road Ipswich Suffolk IP3 9JE",
    "addr:postcode":"ip3 9je",
    "addr:street":"Cobham Road",
    "iso:country":"GB",
    "sg:address":"Eastern Area, Cobham Road",
    "sg:city":"Ipswich",
    "sg:classifiers":[
        {
            "category":"Government",
            "subcategory":"Office",
            "type":"Public Place"
        }
    ],
    "sg:phone":"+44 1473 727712",
    "sg:postcode":"IP3 9JE",
    "sg:province":"Suffolk",
    "sg:tags":[
        "central"
    ],
    "wof:name":"The Environment Agency Anglian Region",
    "wof:placetype":"venue"
},
  "geometry": {"coordinates":[1.1992000341,52.0366210938],"type":"Point"}
}