{
  "type": "Feature",
  "properties": {
    "addr:full":"Akamsara, Ratcher Way, Crown Farm Industrial Park Mansfield Derbyshire NG19 0FS",
    "addr:postcode":"ng19 0fs",
    "addr:street":"Ratcher Way;Industrial;Mansfield",
    "iso:country":"GB",
    "sg:address":"Akamsara, Ratcher Way, Crown Farm Industrial Park",
    "sg:city":"Mansfield",
    "sg:classifiers":[
        {
            "category":"Wholesale",
            "subcategory":"Scrap",
            "type":"Manufacturing & Wholesale Goods"
        }
    ],
    "sg:phone":"+44 1623 420620",
    "sg:postcode":"NG19 0FS",
    "sg:province":"Derbyshire",
    "sg:tags":[
        "waste",
        "metal"
    ],
    "wof:name":"Akam Ltd.",
    "wof:placetype":"venue"
},
  "geometry": {"coordinates":[-1.15074,53.14769],"type":"Point"}
}