{
  "type": "Feature",
  "properties": {
    "addr:full":"Nelson Lane Warwick Warwickshire CV34 5JB",
    "addr:postcode":"cv34 5jb",
    "addr:street":"Nelson Lane",
    "iso:country":"GB",
    "sg:address":"Nelson Lane",
    "sg:city":"Warwick",
    "sg:classifiers":[
        {
            "category":"Retail",
            "subcategory":"Auto Repair",
            "type":"Services"
        }
    ],
    "sg:phone":"+44 1926 407067",
    "sg:postcode":"CV34 5JB",
    "sg:province":"Warwickshire",
    "sg:tags":[
        "body",
        "car",
        "repairer"
    ],
    "wof:name":"P L Carbodies",
    "wof:placetype":"venue"
},
  "geometry": {"coordinates":[-1.5775539875,52.290561676],"type":"Point"}
}