{
  "type": "Feature",
  "properties": {
    "iso:country":"GB",
    "sg:address":"1 The Chestnuts, Codicote",
    "sg:city":"Hitchin",
    "sg:classifiers":[
        {
            "category":"Home & Garden",
            "subcategory":"Building Materials",
            "type":"Retail Goods"
        }
    ],
    "sg:postcode":"SG4 8XR",
    "sg:province":"Hertfordshire",
    "sg:tags":[
        "mnfr",
        "conductor",
        "lightning"
    ],
    "wof:name":"A & J Installations",
    "wof:placetype":"venue"
},
  "geometry": {"coordinates":[-0.275912,51.863987],"type":"Point"}
}