{
  "type": "Feature",
  "properties": {
    "addr:full":"67 Grange Road West Birkenhead Merseyside CH41 4BZ",
    "addr:housenumber":"67",
    "addr:postcode":"ch41 4bz",
    "addr:street":"Grange Road West",
    "iso:country":"GB",
    "sg:address":"67 Grange Road West",
    "sg:city":"Birkenhead",
    "sg:classifiers":[
        {
            "category":"Food & Beverages",
            "subcategory":"Liquor & Beverages",
            "type":"Retail Goods"
        }
    ],
    "sg:phone":"+44 151 670 1802",
    "sg:postcode":"CH41 4BZ",
    "sg:province":"Merseyside",
    "sg:tags":[
        "beer",
        "spirit",
        "wines"
    ],
    "wof:name":"Victoria Wine",
    "wof:placetype":"venue"
},
  "geometry": {"coordinates":[-3.03497,53.388958],"type":"Point"}
}