{
  "type": "Feature",
  "properties": {
    "addr:full":"Unit 3 Padmore Works, Block House Close Worcester Worcestershire WR1 2BU",
    "addr:housenumber":"unit 3;works block",
    "addr:postcode":"wr1 2bu",
    "addr:street":"Padmore;House Close",
    "iso:country":"GB",
    "sg:address":"Unit 3 Padmore Works, Block House Close",
    "sg:city":"Worcester",
    "sg:classifiers":[
        {
            "category":"Retail",
            "subcategory":"Auto Repair",
            "type":"Services"
        }
    ],
    "sg:phone":"+44 1905 29924",
    "sg:postcode":"WR1 2BU",
    "sg:province":"Worcestershire",
    "sg:tags":[
        "modification",
        "garage"
    ],
    "wof:name":"Garage",
    "wof:placetype":"venue"
},
  "geometry": {"coordinates":[-2.2199790478,52.1897201538],"type":"Point"}
}