{
  "type": "Feature",
  "properties": {
    "addr:full":"Gold Oak Farm, Hare La Wimborne Dorset BH21 5QT",
    "addr:postcode":"bh21 5qt",
    "addr:street":"Gold Oak Farm Hare La Wimborne",
    "iso:country":"GB",
    "sg:address":"Gold Oak Farm, Hare La",
    "sg:city":"Wimborne",
    "sg:classifiers":[
        {
            "category":"Farming",
            "subcategory":"Livestock Farm",
            "type":"Manufacturing & Wholesale Goods"
        }
    ],
    "sg:phone":"+44 1725 517275",
    "sg:postcode":"BH21 5QT",
    "sg:province":"Dorset",
    "sg:tags":[
        "others"
    ],
    "wof:name":"A C Butler",
    "wof:placetype":"venue"
},
  "geometry": {"coordinates":[-1.956449,50.907581],"type":"Point"}
}