{
  "type": "Feature",
  "properties": {
    "iso:country":"GB",
    "sg:address":"The Little Chest, Ashford Road",
    "sg:city":"Maidstone",
    "sg:classifiers":[
        {
            "category":"Freight",
            "type":"Transportation"
        }
    ],
    "sg:postcode":"ME17 2DL",
    "sg:province":"Kent",
    "sg:tags":[
        "haulage",
        "road"
    ],
    "wof:name":"Holdfast Services Ltd.",
    "wof:placetype":"venue"
},
  "geometry": {"coordinates":[0.7312700152,51.236038208],"type":"Point"}
}