{
  "type": "Feature",
  "properties": {
    "addr:full":"Mandarin Court, Hambrige Road Newbury Berkshire RG14 5SQ",
    "addr:postcode":"rg14 5sq",
    "addr:street":"Mandarin;Hambrige Road",
    "iso:country":"GB",
    "sg:address":"Mandarin Court, Hambrige Road",
    "sg:city":"Newbury",
    "sg:classifiers":[
        {
            "category":"Building & Trades",
            "subcategory":"Construction",
            "type":"Services"
        }
    ],
    "sg:phone":"+44 1635 523969",
    "sg:postcode":"RG14 5SQ",
    "sg:province":"Berkshire",
    "sg:tags":[
        "builder"
    ],
    "wof:name":"Beaufort Homes Ltd.",
    "wof:placetype":"venue"
},
  "geometry": {"coordinates":[-1.3131489754,51.399433136],"type":"Point"}
}