{
  "type": "Feature",
  "properties": {
    "iso:country":"GB",
    "sg:address":"6 Marsh Lane, Ashton",
    "sg:city":"Bristol",
    "sg:classifiers":[
        {
            "category":"Professional",
            "type":"Services"
        }
    ],
    "sg:phone":"+44 117 963 1790",
    "sg:postcode":"BS3 2NR",
    "sg:province":"City of Bristol",
    "sg:tags":[
        "shopfitters"
    ],
    "wof:name":"Adam (Services) Ltd.",
    "wof:placetype":"venue"
},
  "geometry": {"coordinates":[-2.6119630337,51.4335899353],"type":"Point"}
}