{
  "type": "Feature",
  "properties": {
    "iso:country":"GB",
    "sg:address":"Mason House, Evesham Road, Headless Cross",
    "sg:city":"Redditch",
    "sg:classifiers":[
        {
            "category":"Real Estate",
            "subcategory":"Surveying",
            "type":"Services"
        }
    ],
    "sg:phone":"+44 1527 541875",
    "sg:postcode":"B97 4BZ",
    "sg:province":"Warwickshire",
    "sg:tags":[
        "surveyor",
        "valuer"
    ],
    "wof:name":"Philip Moran",
    "wof:placetype":"venue"
},
  "geometry": {"coordinates":[-1.941267,52.30727],"type":"Point"}
}