{
  "type": "Feature",
  "properties": {
    "addr:full":"3 Rawstorne Place London Greater London EC1V 7NL",
    "addr:housenumber":"3",
    "addr:postcode":"ec1v 7nl",
    "addr:street":"Rawstorne Place",
    "iso:country":"GB",
    "sg:address":"3 Rawstorne Place",
    "sg:city":"London",
    "sg:classifiers":[
        {
            "category":"Professional",
            "subcategory":"Printing & Photocopies",
            "type":"Services"
        }
    ],
    "sg:postcode":"EC1V 7NL",
    "sg:province":"Greater London",
    "sg:tags":[
        "duplicating",
        "copying"
    ],
    "wof:name":"Chroma Reprographics Ltd.",
    "wof:placetype":"venue"
},
  "geometry": {"coordinates":[-0.103999,51.52906],"type":"Point"}
}