{
  "type": "Feature",
  "properties": {
    "addr:full":"229 Buchanan Street Glasgow Glasgow City G1 2NG",
    "addr:housenumber":"229",
    "addr:postcode":"g1 2ng",
    "addr:street":"Buchanan Street",
    "iso:country":"GB",
    "sg:address":"229 Buchanan Street",
    "sg:city":"Glasgow",
    "sg:classifiers":[
        {
            "category":"Travel",
            "subcategory":"Hotels & Motels",
            "type":"Entertainment"
        }
    ],
    "sg:postcode":"G1 2NG",
    "sg:province":"Glasgow City",
    "wof:name":"Commercial Hotel",
    "wof:placetype":"venue"
},
  "geometry": {"coordinates":[-4.253113,55.863548],"type":"Point"}
}