{
  "type": "Feature",
  "properties": {
    "addr:full":"41 Syke Green Leeds West Yorkshire LS14 3BS",
    "addr:housenumber":"41",
    "addr:postcode":"ls14 3bs",
    "addr:street":"Syke Green Leeds West",
    "iso:country":"GB",
    "sg:address":"41 Syke Green",
    "sg:city":"Leeds",
    "sg:classifiers":[
        {
            "category":"Professional",
            "subcategory":"Credit Reporting & Collection",
            "type":"Services"
        }
    ],
    "sg:phone":"+44 113 289 3661",
    "sg:postcode":"LS14 3BS",
    "sg:province":"West Yorkshire",
    "sg:tags":[
        "collecting",
        "agency"
    ],
    "wof:name":"Argus Arbitration Services",
    "wof:placetype":"venue"
},
  "geometry": {"coordinates":[-1.448325,53.86982],"type":"Point"}
}