{
  "type": "Feature",
  "properties": {
    "addr:full":"40 Rushmore Grove, Paddington Warrington Cheshire WA1 3EX",
    "addr:housenumber":"40",
    "addr:postcode":"wa1 3ex",
    "addr:street":"Rushmore Grove",
    "iso:country":"GB",
    "sg:address":"40 Rushmore Grove, Paddington",
    "sg:city":"Warrington",
    "sg:classifiers":[
        {
            "category":"Professional",
            "subcategory":"Management & Consulting",
            "type":"Services"
        }
    ],
    "sg:phone":"+44 1925 816477",
    "sg:postcode":"WA1 3EX",
    "sg:province":"Cheshire",
    "sg:tags":[
        "consultant",
        "business"
    ],
    "wof:name":"Bevens Associates",
    "wof:placetype":"venue"
},
  "geometry": {"coordinates":[-2.5528459549,53.3984146118],"type":"Point"}
}