{
  "type": "Feature",
  "properties": {
    "addr:full":"141 High St Montrose Aberdeenshire DD10 8QN",
    "addr:housenumber":"141",
    "addr:postcode":"dd10 8qn",
    "addr:street":"High St",
    "iso:country":"GB",
    "sg:address":"141 High St",
    "sg:city":"Montrose",
    "sg:classifiers":[
        {
            "category":"Shopping",
            "subcategory":"Florist",
            "type":"Retail Goods"
        }
    ],
    "sg:postcode":"DD10 8QN",
    "sg:province":"Aberdeenshire",
    "wof:name":"Mutch,Tom,",
    "wof:placetype":"venue"
},
  "geometry": {"coordinates":[-2.4682729244,56.7101860046],"type":"Point"}
}