{
  "type": "Feature",
  "properties": {
    "iso:country":"GB",
    "sg:address":"7 South William Street",
    "sg:city":"Workington",
    "sg:classifiers":[
        {
            "category":"Personal",
            "subcategory":"Beauty Salon",
            "type":"Services"
        }
    ],
    "sg:postcode":"CA14 2DZ",
    "sg:province":"Cumbria",
    "sg:tags":[
        "unisex",
        "hairdresser"
    ],
    "wof:name":"Brendas Salon",
    "wof:placetype":"venue"
},
  "geometry": {"coordinates":[-3.549096,54.645145],"type":"Point"}
}