{
  "type": "Feature",
  "properties": {
    "addr:full":"Lane Casita, Trent Side, Swarkestone Derby Derbyshire DE73 1JB",
    "addr:postcode":"de73 1jb",
    "addr:street":"Lane;Trent Side",
    "iso:country":"GB",
    "sg:address":"Lane Casita, Trent Side, Swarkestone",
    "sg:city":"Derby",
    "sg:classifiers":[
        {
            "category":"Shopping",
            "subcategory":"Clothing, Apparel, & Fashions",
            "type":"Retail Goods"
        }
    ],
    "sg:phone":"+44 1332 702881",
    "sg:postcode":"DE73 1JB",
    "sg:province":"Derbyshire",
    "sg:tags":[
        "staff",
        "wear",
        "uniform"
    ],
    "wof:name":"Linda Lee Associates",
    "wof:placetype":"venue"
},
  "geometry": {"coordinates":[-1.4504300356,52.855052948],"type":"Point"}
}