{
  "type": "Feature",
  "properties": {
    "addr:full":"Atlas House, 15 Bell Street West Bromwich West Midlands B70 7BT",
    "addr:housenumber":"15",
    "addr:postcode":"b70 7bt",
    "addr:street":"Bell Street",
    "iso:country":"GB",
    "sg:address":"Atlas House, 15 Bell Street",
    "sg:city":"West Bromwich",
    "sg:classifiers":[
        {
            "category":"Building & Trades",
            "subcategory":"Construction",
            "type":"Services"
        }
    ],
    "sg:phone":"+44 121 500 5885",
    "sg:postcode":"B70 7BT",
    "sg:province":"West Midlands",
    "sg:tags":[
        "fork",
        "lift",
        "truck"
    ],
    "wof:name":"Hoots Lift Trucks",
    "wof:placetype":"venue"
},
  "geometry": {"coordinates":[-1.9928760529,52.5137214661],"type":"Point"}
}