{
  "type": "Feature",
  "properties": {
    "addr:full":"25 Frances Rd, Erdington Birmingham West Midlands B23 7LD",
    "addr:housenumber":"25",
    "addr:postcode":"b23 7ld",
    "addr:street":"Frances Rd",
    "iso:country":"GB",
    "sg:address":"25 Frances Rd, Erdington",
    "sg:city":"Birmingham",
    "sg:classifiers":[
        {
            "category":"Professional",
            "subcategory":"Engineering",
            "type":"Services"
        }
    ],
    "sg:postcode":"B23 7LD",
    "sg:province":"West Midlands",
    "sg:tags":[
        "contractor",
        "electrical",
        "engineer"
    ],
    "wof:name":"D J Electrical Co",
    "wof:placetype":"venue"
},
  "geometry": {"coordinates":[-1.859262,52.521381],"type":"Point"}
}