{
  "type": "Feature",
  "properties": {
    "addr:full":"1 Petticoat Lane Shepton Mallet Somerset BA4 5DA",
    "addr:housenumber":"1",
    "addr:postcode":"ba4 5da",
    "addr:street":"Petticoat Lane",
    "iso:country":"GB",
    "sg:address":"1 Petticoat Lane",
    "sg:city":"Shepton Mallet",
    "sg:classifiers":[
        {
            "category":"Home & Garden",
            "subcategory":"Garden Supply",
            "type":"Retail Goods"
        }
    ],
    "sg:postcode":"BA4 5DA",
    "sg:province":"Somerset",
    "sg:tags":[
        "nursery",
        "centre"
    ],
    "wof:name":"The Shrubbery Plants & Gardens",
    "wof:placetype":"venue"
},
  "geometry": {"coordinates":[-2.546778,51.189732],"type":"Point"}
}