{
  "type": "Feature",
  "properties": {
    "addr:full":"29 Knoll Park Road Chertsey Surrey KT16 9LR",
    "addr:housenumber":"29",
    "addr:postcode":"kt16 9lr",
    "addr:street":"Knoll Park Road",
    "iso:country":"GB",
    "sg:address":"29 Knoll Park Road",
    "sg:city":"Chertsey",
    "sg:classifiers":[
        {
            "category":"Professional",
            "subcategory":"Computer Services",
            "type":"Services"
        }
    ],
    "sg:phone":"+44 1932 570057",
    "sg:postcode":"KT16 9LR",
    "sg:province":"Surrey",
    "sg:tags":[
        "system",
        "software"
    ],
    "wof:name":"Ultrasoft Technologies Ltd.",
    "wof:placetype":"venue"
},
  "geometry": {"coordinates":[-0.512659,51.385201],"type":"Point"}
}