{
  "type": "Feature",
  "properties": {
    "addr:full":"76 Welsh Road, Garden City Deeside Flintshire CH5 2HU",
    "addr:housenumber":"76",
    "addr:postcode":"ch5 2hu",
    "addr:street":"Welsh Road",
    "iso:country":"GB",
    "sg:address":"76 Welsh Road, Garden City",
    "sg:city":"Deeside",
    "sg:classifiers":[
        {
            "category":"Professional",
            "subcategory":"Business Services",
            "type":"Services"
        }
    ],
    "sg:phone":"+44 1244 813121",
    "sg:postcode":"CH5 2HU",
    "sg:province":"Flintshire",
    "sg:tags":[
        "bookmaker"
    ],
    "wof:name":"Corbett Bookmakers Ltd.",
    "wof:placetype":"venue"
},
  "geometry": {"coordinates":[-3.007711,53.214161],"type":"Point"}
}