{
  "type": "Feature",
  "properties": {
    "iso:country":"GB",
    "sg:address":"38 Knowle Wood Road, Dorridge",
    "sg:city":"Solihull",
    "sg:classifiers":[
        {
            "category":"Health Services",
            "subcategory":"Doctor",
            "type":"Services"
        }
    ],
    "sg:phone":"+44 1564 770947",
    "sg:postcode":"B93 8JN",
    "sg:province":"Warwickshire",
    "sg:tags":[
        "practitioners"
    ],
    "wof:name":"Pauline Yardley",
    "wof:placetype":"venue"
},
  "geometry": {"coordinates":[-1.743876,52.373714],"type":"Point"}
}