{
  "type": "Feature",
  "properties": {
    "addr:full":"129 Linton Road Maidstone Kent ME15 0AS",
    "addr:housenumber":"129",
    "addr:postcode":"me15 0as",
    "addr:street":"Linton Road",
    "iso:country":"GB",
    "sg:address":"129 Linton Road",
    "sg:city":"Maidstone",
    "sg:classifiers":[
        {
            "category":"Building & Trades",
            "subcategory":"Construction",
            "type":"Services"
        }
    ],
    "sg:phone":"+44 1622 747727",
    "sg:postcode":"ME15 0AS",
    "sg:province":"Kent",
    "sg:tags":[
        "builder"
    ],
    "wof:name":"P G Stringer & Sons",
    "wof:placetype":"venue"
},
  "geometry": {"coordinates":[0.514938,51.233322],"type":"Point"}
}