{
  "type": "Feature",
  "properties": {
    "addr:full":"70 Dalesford Rd Aylesbury Buckinghamshire HP21 9XZ",
    "addr:housenumber":"70",
    "addr:postcode":"hp21 9xz",
    "addr:street":"Dalesford Rd",
    "iso:country":"GB",
    "sg:address":"70 Dalesford Rd",
    "sg:city":"Aylesbury",
    "sg:classifiers":[
        {
            "category":"Building & Trades",
            "subcategory":"Landscaping Services",
            "type":"Services"
        }
    ],
    "sg:postcode":"HP21 9XZ",
    "sg:province":"Buckinghamshire",
    "sg:tags":[
        "gardening"
    ],
    "wof:name":"Webb,Steven,",
    "wof:placetype":"venue"
},
  "geometry": {"coordinates":[-0.7938740253,51.7965927124],"type":"Point"}
}