{
  "type": "Feature",
  "properties": {
    "addr:full":"22 Broughton Road Salford Greater Manchester M6 6LS",
    "addr:housenumber":"22",
    "addr:postcode":"m6 6ls",
    "addr:street":"Broughton Road",
    "iso:country":"GB",
    "sg:address":"22 Broughton Road",
    "sg:city":"Salford",
    "sg:classifiers":[
        {
            "category":"Fast Food",
            "type":"Food & Drink"
        }
    ],
    "sg:phone":"+44 161 736 0675",
    "sg:postcode":"M6 6LS",
    "sg:province":"Greater Manchester",
    "sg:tags":[
        "away",
        "take"
    ],
    "wof:name":"The Bigger Bite",
    "wof:placetype":"venue"
},
  "geometry": {"coordinates":[-2.283694,53.492783],"type":"Point"}
}