{
  "type": "Feature",
  "properties": {
    "iso:country":"GB",
    "sg:address":"28 Moorlands View Edenfield",
    "sg:city":"Bury",
    "sg:classifiers":[
        {
            "category":"Professional",
            "subcategory":"Computer Services",
            "type":"Services"
        }
    ],
    "sg:postcode":"BL0 0HZ",
    "sg:province":"Lancashire",
    "sg:tags":[
        "system",
        "software"
    ],
    "wof:name":"N & P Graphics Ltd.",
    "wof:placetype":"venue"
},
  "geometry": {"coordinates":[-2.3056321144,53.6783447266],"type":"Point"}
}