{
  "type": "Feature",
  "properties": {
    "addr:full":"22 Cornwall Road London Greater London SE1 8TW",
    "addr:housenumber":"22",
    "addr:postcode":"se1 8tw",
    "addr:street":"Cornwall Road",
    "iso:country":"GB",
    "sg:address":"22 Cornwall Road",
    "sg:city":"London",
    "sg:classifiers":[
        {
            "category":"Food & Beverages",
            "subcategory":"Bakery",
            "type":"Retail Goods"
        }
    ],
    "sg:phone":"+44 20 7261 0456",
    "sg:postcode":"SE1 8TW",
    "sg:province":"Greater London",
    "sg:tags":[
        "shop",
        "baker"
    ],
    "wof:name":"Konditor & Cook Ltd",
    "wof:placetype":"venue"
},
  "geometry": {"coordinates":[-0.11024,51.504246],"type":"Point"}
}