{
  "type": "Feature",
  "properties": {
    "iso:country":"GB",
    "sg:address":"96 Ilford Lane",
    "sg:city":"Ilford",
    "sg:classifiers":[
        {
            "category":"Personal",
            "subcategory":"Barber",
            "type":"Services"
        }
    ],
    "sg:phone":"+44 20 8478 1927",
    "sg:postcode":"IG1 2LD",
    "sg:province":"Essex",
    "sg:tags":[
        "men's",
        "hairdresser"
    ],
    "wof:name":"Ilford Hairdresser",
    "wof:placetype":"venue"
},
  "geometry": {"coordinates":[0.0724750012,51.5543365479],"type":"Point"}
}