{
  "type": "Feature",
  "properties": {
    "addr:full":"49a London Road, Cowplain Waterlooville Hampshire PO8 8UJ",
    "addr:housenumber":"49a",
    "addr:postcode":"po8 8uj",
    "addr:street":"London Road",
    "iso:country":"GB",
    "sg:address":"49a London Road, Cowplain",
    "sg:city":"Waterlooville",
    "sg:classifiers":[
        {
            "category":"Building & Trades",
            "subcategory":"Construction",
            "type":"Services"
        }
    ],
    "sg:postcode":"PO8 8UJ",
    "sg:province":"Hampshire",
    "sg:tags":[
        "guttering"
    ],
    "wof:name":"Kg Installations Ltd",
    "wof:placetype":"venue"
},
  "geometry": {"coordinates":[-1.018813014,50.8940315247],"type":"Point"}
}