{
  "type": "Feature",
  "properties": {
    "addr:full":"Care Of Allders, 162 High St Bromley Kent BR1 1HJ",
    "addr:housenumber":"162",
    "addr:postcode":"br1 1hj",
    "addr:street":"High St",
    "iso:country":"GB",
    "sg:address":"Care Of Allders, 162 High St",
    "sg:city":"Bromley",
    "sg:classifiers":[
        {
            "category":"Shopping",
            "subcategory":"Comic Books",
            "type":"Retail Goods"
        }
    ],
    "sg:phone":"+44 20 8313 1364",
    "sg:postcode":"BR1 1HJ",
    "sg:province":"Kent",
    "sg:tags":[
        "jeweller"
    ],
    "wof:name":"Ciro Pearls Ltd",
    "wof:placetype":"venue"
},
  "geometry": {"coordinates":[0.014928,51.405701],"type":"Point"}
}