{
  "type": "Feature",
  "properties": {
    "addr:full":"P O Box 150 Bexleyheath Kent DA16 1YF",
    "addr:housenumber":"150",
    "addr:postcode":"da16 1yf",
    "addr:street":"P O Box",
    "iso:country":"GB",
    "sg:address":"P O Box 150",
    "sg:city":"Bexleyheath",
    "sg:classifiers":[
        {
            "category":"Professional",
            "subcategory":"Management & Consulting",
            "type":"Services"
        }
    ],
    "sg:postcode":"DA16 1YF",
    "sg:province":"Kent",
    "sg:tags":[
        "consultant",
        "business"
    ],
    "wof:name":"Paul Temple Consultancy Ltd.",
    "wof:placetype":"venue"
},
  "geometry": {"coordinates":[0.11267,51.468071],"type":"Point"}
}