{
  "type": "Feature",
  "properties": {
    "addr:full":"Clayland House Kineton Road Warwick Warwickshire CV35 0HB",
    "addr:postcode":"cv35 0hb",
    "addr:street":"Kineton Road",
    "iso:country":"GB",
    "sg:address":"Clayland House Kineton Road",
    "sg:city":"Warwick",
    "sg:classifiers":[
        {
            "category":"Retail",
            "subcategory":"Auto Rental",
            "type":"Services"
        }
    ],
    "sg:phone":"+44 1926 642992",
    "sg:postcode":"CV35 0HB",
    "sg:province":"Warwickshire",
    "sg:tags":[
        "car"
    ],
    "wof:name":"Chequered Flag Racing Ltd.",
    "wof:placetype":"venue"
},
  "geometry": {"coordinates":[-1.5106090307,52.1565742493],"type":"Point"}
}