{
  "type": "Feature",
  "properties": {
    "addr:full":"2 Oak Hill Surbiton Surrey KT6 6DY",
    "addr:housenumber":"2",
    "addr:postcode":"kt6 6dy",
    "addr:street":"Oak Hill",
    "iso:country":"GB",
    "sg:address":"2 Oak Hill",
    "sg:city":"Surbiton",
    "sg:classifiers":[
        {
            "category":"Shopping",
            "subcategory":"Gifts & Souvenirs",
            "type":"Retail Goods"
        },
        {
            "category":"Wholesale",
            "subcategory":"Stationery",
            "type":"Manufacturing & Wholesale Goods"
        }
    ],
    "sg:phone":"+44 20 8399 9044",
    "sg:postcode":"KT6 6DY",
    "sg:province":"Surrey",
    "sg:tags":[
        "giftware"
    ],
    "wof:name":"Atlas Star Ltd.",
    "wof:placetype":"venue"
},
  "geometry": {"coordinates":[-0.301188,51.390064],"type":"Point"}
}