{
  "type": "Feature",
  "properties": {
    "addr:full":"176 Towcester Road Northampton Northamptonshire NN4 8LW",
    "addr:housenumber":"176",
    "addr:postcode":"nn4 8lw",
    "addr:street":"Towcester Road",
    "iso:country":"GB",
    "sg:address":"176 Towcester Road",
    "sg:city":"Northampton",
    "sg:classifiers":[
        {
            "category":"Professional",
            "subcategory":"Computer Services",
            "type":"Services"
        }
    ],
    "sg:phone":"+44 1604 700357",
    "sg:postcode":"NN4 8LW",
    "sg:province":"Northamptonshire",
    "sg:tags":[
        "development",
        "system",
        "software"
    ],
    "wof:name":"Marshall Computers",
    "wof:placetype":"venue"
},
  "geometry": {"coordinates":[-0.908772,52.221954],"type":"Point"}
}