{
  "type": "Feature",
  "properties": {
    "iso:country":"GB",
    "sg:address":"Suite 6 Anson Ct, Horninglow St",
    "sg:city":"Burton On Trent",
    "sg:classifiers":[
        {
            "category":"Real Estate",
            "subcategory":"Surveying",
            "type":"Services"
        }
    ],
    "sg:phone":"+44 1283 539211",
    "sg:postcode":"DE14 1NG",
    "sg:province":"Derbyshire",
    "sg:tags":[
        "surveyor",
        "valuer"
    ],
    "wof:name":"C R B Commercial Surveyors",
    "wof:placetype":"venue"
},
  "geometry": {"coordinates":[-1.627051,52.807693],"type":"Point"}
}