{
  "type": "Feature",
  "properties": {
    "addr:full":"Cheverells, Hoseley Lane, Marford Wrexham Wrexham LL12 8YE",
    "addr:postcode":"ll12 8ye",
    "addr:street":"Hoseley Lane Marford",
    "iso:country":"GB",
    "sg:address":"Cheverells, Hoseley Lane, Marford",
    "sg:city":"Wrexham",
    "sg:classifiers":[
        {
            "category":"Professional",
            "subcategory":"Management & Consulting",
            "type":"Services"
        }
    ],
    "sg:phone":"+44 1978 855664",
    "sg:postcode":"LL12 8YE",
    "sg:province":"Wrexham",
    "sg:tags":[
        "consultant",
        "business"
    ],
    "wof:name":"Marford Consultants Ltd.",
    "wof:placetype":"venue"
},
  "geometry": {"coordinates":[-2.9573090076,53.1005973816],"type":"Point"}
}