{
  "type": "Feature",
  "properties": {
    "iso:country":"GB",
    "sg:address":"1b Basset Road",
    "sg:city":"Camborne",
    "sg:classifiers":[
        {
            "category":"Fast Food",
            "type":"Food & Drink"
        }
    ],
    "sg:postcode":"TR14 8SE",
    "sg:province":"Cornwall",
    "sg:tags":[
        "away",
        "take"
    ],
    "wof:name":"Far East Chinese Take Away",
    "wof:placetype":"venue"
},
  "geometry": {"coordinates":[-5.300587,50.212818],"type":"Point"}
}