{
  "type": "Feature",
  "properties": {
    "addr:full":"12 Pickwick Ho, Ebenezer St Islington Greater London N1 7NP",
    "addr:housenumber":"12",
    "addr:postcode":"n1 7np",
    "addr:street":"Pickwick Ho;St",
    "iso:country":"GB",
    "sg:address":"12 Pickwick Ho, Ebenezer St",
    "sg:city":"Islington",
    "sg:classifiers":[
        {
            "category":"Professional",
            "type":"Services"
        }
    ],
    "sg:phone":"+44 20 7684 0300",
    "sg:postcode":"N1 7NP",
    "sg:province":"Greater London",
    "sg:tags":[
        "interior",
        "furnishers",
        "designer"
    ],
    "wof:name":"Dare I D",
    "wof:placetype":"venue"
},
  "geometry": {"coordinates":[-0.08989,51.528549],"type":"Point"}
}