{
  "type": "Feature",
  "properties": {
    "iso:country":"GB",
    "sg:address":"59 Canterbury Road, Willesborough",
    "sg:city":"Ashford",
    "sg:classifiers":[
        {
            "category":"Farming",
            "subcategory":"Nursery",
            "type":"Manufacturing & Wholesale Goods"
        }
    ],
    "sg:postcode":"TN24 0BH",
    "sg:province":"Kent",
    "sg:tags":[
        "creche"
    ],
    "wof:name":"Canterbury House Nursery School",
    "wof:placetype":"venue"
},
  "geometry": {"coordinates":[0.8915669918,51.1319503784],"type":"Point"}
}