{
  "type": "Feature",
  "properties": {
    "addr:full":"214 Borough High Street London Greater London SE1 1JX",
    "addr:housenumber":"214",
    "addr:postcode":"se1 1jx",
    "addr:street":"Borough High Street",
    "iso:country":"GB",
    "sg:address":"214 Borough High Street",
    "sg:city":"London",
    "sg:classifiers":[
        {
            "category":"Shopping",
            "subcategory":"Department Store",
            "type":"Retail Goods"
        }
    ],
    "sg:phone":"+44 20 7407 1028",
    "sg:postcode":"SE1 1JX",
    "sg:province":"Greater London",
    "wof:name":"Right Price",
    "wof:placetype":"venue"
},
  "geometry": {"coordinates":[-0.09383,51.500996],"type":"Point"}
}