{
  "type": "Feature",
  "properties": {
    "addr:full":"7 Burnley Rd, Brierfield Nelson Lancashire BB9 5HX",
    "addr:housenumber":"7",
    "addr:postcode":"bb9 5hx",
    "addr:street":"Burnley Rd",
    "iso:country":"GB",
    "sg:address":"7 Burnley Rd, Brierfield",
    "sg:city":"Nelson",
    "sg:classifiers":[
        {
            "category":"Professional",
            "subcategory":"Business Services",
            "type":"Services"
        }
    ],
    "sg:phone":"+44 1282 606015",
    "sg:postcode":"BB9 5HX",
    "sg:province":"Lancashire",
    "sg:tags":[
        "answering"
    ],
    "wof:name":"Euro Asia Public Call Office",
    "wof:placetype":"venue"
},
  "geometry": {"coordinates":[-2.2345271111,53.82213974],"type":"Point"}
}