{
  "type": "Feature",
  "properties": {
    "addr:full":"27 Talbot Road, Talbot Green Pontyclun Bridgend CF72 8AD",
    "addr:housenumber":"27",
    "addr:postcode":"cf72 8ad",
    "addr:street":"Talbot Road",
    "iso:country":"GB",
    "sg:address":"27 Talbot Road, Talbot Green",
    "sg:city":"Pontyclun",
    "sg:classifiers":[
        {
            "category":"Fast Food",
            "type":"Food & Drink"
        }
    ],
    "sg:phone":"+44 1443 223547",
    "sg:postcode":"CF72 8AD",
    "sg:province":"Bridgend",
    "sg:tags":[
        "away",
        "take"
    ],
    "wof:name":"Jade Garden Cantonese & Mandarin Cuisine",
    "wof:placetype":"venue"
},
  "geometry": {"coordinates":[-3.3853590488,51.5370025635],"type":"Point"}
}