{
  "type": "Feature",
  "properties": {
    "addr:full":"Battersea Delivery Office, 202 Lavender Hill Battersea Greater London SW11 1AA",
    "addr:housenumber":"202",
    "addr:postcode":"sw11 1aa",
    "addr:street":"Lavender Hill",
    "iso:country":"GB",
    "sg:address":"Battersea Delivery Office, 202 Lavender Hill",
    "sg:city":"Battersea",
    "sg:classifiers":[
        {
            "category":"Personal",
            "type":"Services"
        }
    ],
    "sg:phone":"+44 20 7239 6642",
    "sg:postcode":"SW11 1AA",
    "sg:province":"Greater London",
    "sg:tags":[
        "delivery"
    ],
    "wof:name":"Royal Mail",
    "wof:placetype":"venue"
},
  "geometry": {"coordinates":[-0.164579004,51.4609107971],"type":"Point"}
}