{
  "type": "Feature",
  "properties": {
    "addr:full":"20 Woodland Crescent, Kelloe Durham Durham DH6 4LU",
    "addr:housenumber":"20",
    "addr:postcode":"dh6 4lu",
    "addr:street":"Woodland Crescent",
    "iso:country":"GB",
    "sg:address":"20 Woodland Crescent, Kelloe",
    "sg:city":"Durham",
    "sg:classifiers":[
        {
            "category":"Personal",
            "subcategory":"Tanning Parlor",
            "type":"Services"
        }
    ],
    "sg:phone":"+44 191 377 3100",
    "sg:postcode":"DH6 4LU",
    "sg:province":"Durham",
    "sg:tags":[
        "sunbeds"
    ],
    "wof:name":"Betta-Tan-Sunbeds",
    "wof:placetype":"venue"
},
  "geometry": {"coordinates":[-1.478732,54.719994],"type":"Point"}
}