{
  "type": "Feature",
  "properties": {
    "addr:full":"New Street, Aberkenfig Bridgend Bridgend CF32 9BL",
    "addr:postcode":"cf32 9bl",
    "addr:street":"New Street",
    "iso:country":"GB",
    "sg:address":"New Street, Aberkenfig",
    "sg:city":"Bridgend",
    "sg:classifiers":[
        {
            "category":"Health Services",
            "subcategory":"Clinic",
            "type":"Services"
        }
    ],
    "sg:phone":"+44 1656 720430",
    "sg:postcode":"CF32 9BL",
    "sg:province":"Bridgend",
    "sg:tags":[
        "nh"
    ],
    "wof:name":"Bro Morgannwg N H S Trust",
    "wof:placetype":"venue"
},
  "geometry": {"coordinates":[-3.597744,51.539085],"type":"Point"}
}