{
  "type": "Feature",
  "properties": {
    "iso:country":"GB",
    "sg:address":"Palatine Street",
    "sg:city":"Nottingham",
    "sg:classifiers":[
        {
            "category":"Shopping",
            "subcategory":"Books",
            "type":"Retail Goods"
        }
    ],
    "sg:phone":"+44 115 979 9081",
    "sg:postcode":"NG7 1GA",
    "sg:province":"Nottinghamshire",
    "wof:name":"My Very Own Book",
    "wof:placetype":"venue"
},
  "geometry": {"coordinates":[-1.156979,52.947697],"type":"Point"}
}