{
  "type": "Feature",
  "properties": {
    "addr:full":"239a High Rd Loughton Essex IG10 1AD",
    "addr:housenumber":"239a",
    "addr:postcode":"ig10 1ad",
    "addr:street":"High Rd",
    "iso:country":"GB",
    "sg:address":"239a High Rd",
    "sg:city":"Loughton",
    "sg:classifiers":[
        {
            "category":"Shopping",
            "subcategory":"Thrift Store",
            "type":"Retail Goods"
        }
    ],
    "sg:phone":"+44 20 8508 3055",
    "sg:postcode":"IG10 1AD",
    "sg:province":"Essex",
    "sg:tags":[
        "shop",
        "charity"
    ],
    "wof:name":"Sense",
    "wof:placetype":"venue"
},
  "geometry": {"coordinates":[0.055675,51.6476287842],"type":"Point"}
}