{
  "type": "Feature",
  "properties": {
    "addr:full":"Knights Close, Tiptree Colchester Essex CO5 0RH",
    "addr:postcode":"co5 0rh",
    "addr:street":"Knights Close",
    "iso:country":"GB",
    "sg:address":"Knights Close, Tiptree",
    "sg:city":"Colchester",
    "sg:classifiers":[
        {
            "category":"Real Estate",
            "subcategory":"Real Estate Agent",
            "type":"Services"
        }
    ],
    "sg:phone":"+44 1621 819325",
    "sg:postcode":"CO5 0RH",
    "sg:province":"Essex",
    "wof:name":"Warden Of Sheltered Accommodation",
    "wof:placetype":"venue"
},
  "geometry": {"coordinates":[0.745334,51.816463],"type":"Point"}
}