{
  "type": "Feature",
  "properties": {
    "addr:full":"10 Pyket Way Northampton Northamptonshire NN3 3JU",
    "addr:housenumber":"10",
    "addr:postcode":"nn3 3ju",
    "addr:street":"Pyket Way",
    "iso:country":"GB",
    "sg:address":"10 Pyket Way",
    "sg:city":"Northampton",
    "sg:classifiers":[
        {
            "category":"Government",
            "subcategory":"Office",
            "type":"Public Place"
        }
    ],
    "sg:postcode":"NN3 3JU",
    "sg:province":"Northamptonshire",
    "sg:tags":[
        "education",
        "agency",
        "authority"
    ],
    "wof:name":"Carol Weston Education Consultant",
    "wof:placetype":"venue"
},
  "geometry": {"coordinates":[-0.843484,52.250557],"type":"Point"}
}