{
  "type": "Feature",
  "properties": {
    "addr:full":"62 Dalkeith Grove Stanmore Greater London HA7 4SF",
    "addr:housenumber":"62",
    "addr:postcode":"ha7 4sf",
    "addr:street":"Dalkeith Grove",
    "iso:country":"GB",
    "sg:address":"62 Dalkeith Grove",
    "sg:city":"Stanmore",
    "sg:classifiers":[
        {
            "category":"Real Estate",
            "subcategory":"Real Estate Operator",
            "type":"Services"
        }
    ],
    "sg:phone":"+44 20 8958 1934",
    "sg:postcode":"HA7 4SF",
    "sg:province":"Greater London",
    "sg:tags":[
        "letting",
        "agent"
    ],
    "wof:name":"Gabrielle Perez Lettings Ltd",
    "wof:placetype":"venue"
},
  "geometry": {"coordinates":[-0.297324,51.615742],"type":"Point"}
}