{
  "type": "Feature",
  "properties": {
    "addr:full":"Boston House, 36-38 Fitzroy Square London Greater London W1T 6EY",
    "addr:housenumber":"36-38",
    "addr:postcode":"w1t 6ey",
    "addr:street":"Fitzroy Square",
    "iso:country":"GB",
    "sg:address":"Boston House, 36-38 Fitzroy Square",
    "sg:city":"London",
    "sg:classifiers":[
        {
            "category":"Communications",
            "type":"Services"
        },
        {
            "category":"Communications",
            "subcategory":"Television Station",
            "type":"Services"
        }
    ],
    "sg:postcode":"W1T 6EY",
    "sg:province":"Greater London",
    "sg:tags":[
        "video",
        "audio-visual"
    ],
    "wof:name":"Barrie Hinchliffe Productions Ltd.",
    "wof:placetype":"venue"
},
  "geometry": {"coordinates":[-0.140179,51.522442],"type":"Point"}
}