{
  "type": "Feature",
  "properties": {
    "iso:country":"GB",
    "sg:address":"164 Cape Hill",
    "sg:city":"Smethwick",
    "sg:classifiers":[
        {
            "category":"Shopping",
            "subcategory":"Luggage & Leather Goods",
            "type":"Retail Goods"
        }
    ],
    "sg:phone":"+44 121 558 1815",
    "sg:postcode":"B66 4SJ",
    "sg:province":"West Midlands",
    "wof:name":"Cape Hill Drapers",
    "wof:placetype":"venue"
},
  "geometry": {"coordinates":[-1.953762,52.487015],"type":"Point"}
}