{
  "type": "Feature",
  "properties": {
    "addr:full":"Appleton Gate Newark Nottinghamshire NG24 2DN",
    "addr:postcode":"ng24 2dn",
    "addr:street":"Appleton Gate",
    "iso:country":"GB",
    "sg:address":"Appleton Gate",
    "sg:city":"Newark",
    "sg:classifiers":[
        {
            "category":"Education",
            "subcategory":"Special Training",
            "type":"Public Place"
        }
    ],
    "sg:phone":"+44 1636 678843",
    "sg:postcode":"NG24 2DN",
    "sg:province":"Nottinghamshire",
    "sg:tags":[
        "aid",
        "first"
    ],
    "wof:name":"St John Ambulance",
    "wof:placetype":"venue"
},
  "geometry": {"coordinates":[-0.801189,53.081089],"type":"Point"}
}