{
  "type": "Feature",
  "properties": {
    "addr:full":"103-105 Commercial Rd Poole Dorset BH14 0JD",
    "addr:housenumber":"103-105",
    "addr:postcode":"bh14 0jd",
    "addr:street":"Commercial Rd",
    "iso:country":"GB",
    "sg:address":"103-105 Commercial Rd",
    "sg:city":"Poole",
    "sg:classifiers":[
        {
            "category":"Autos & Motor Vehicles",
            "subcategory":"Automobile Sales",
            "type":"Retail Goods"
        }
    ],
    "sg:postcode":"BH14 0JD",
    "sg:province":"Dorset",
    "sg:tags":[
        "car"
    ],
    "wof:name":"Auto Trade Centre",
    "wof:placetype":"venue"
},
  "geometry": {"coordinates":[-1.952748,50.723263],"type":"Point"}
}