{
  "type": "Feature",
  "properties": {
    "iso:country":"GB",
    "sg:address":"General Enquiries, Postern Gate, Cinque Ports St",
    "sg:city":"Rye",
    "sg:classifiers":[
        {
            "category":"Health Services",
            "subcategory":"Doctor",
            "type":"Services"
        }
    ],
    "sg:phone":"+44 1797 224924",
    "sg:postcode":"TN31 7AP",
    "sg:province":"East Sussex",
    "sg:tags":[
        "practitioners"
    ],
    "wof:name":"Griffin, A",
    "wof:placetype":"venue"
},
  "geometry": {"coordinates":[0.7356520295,50.9517288208],"type":"Point"}
}