{
  "type": "Feature",
  "properties": {
    "iso:country":"GB",
    "sg:address":"10 Pineapple Park Road, Winsford Industrial Estate",
    "sg:city":"Winsford",
    "sg:classifiers":[
        {
            "category":"Wholesale",
            "subcategory":"Machinery & Supplies",
            "type":"Manufacturing & Wholesale Goods"
        }
    ],
    "sg:phone":"+44 1606 553805",
    "sg:postcode":"CW7 3PR",
    "sg:province":"Cheshire",
    "sg:tags":[
        "control",
        "instrument",
        "industrial",
        "-"
    ],
    "wof:name":"Scully (U K) Ltd.",
    "wof:placetype":"venue"
},
  "geometry": {"coordinates":[-2.489659071,53.1973762512],"type":"Point"}
}