{
  "type": "Feature",
  "properties": {
    "iso:country":"GB",
    "sg:address":"The Terrace",
    "sg:city":"Rochester",
    "sg:classifiers":[
        {
            "category":"Place Of Worship",
            "type":"Public Place"
        },
        {
            "category":"Organizations",
            "subcategory":"Non-profit Organization",
            "type":"Services"
        }
    ],
    "sg:phone":"+44 1634 405892",
    "sg:postcode":"ME1 1XN",
    "sg:province":"Kent",
    "sg:tags":[
        "charitable",
        "organisation",
        "charity"
    ],
    "wof:name":"Vines United Reformed Church",
    "wof:placetype":"venue"
},
  "geometry": {"coordinates":[0.506277,51.385441],"type":"Point"}
}