{
  "type": "Feature",
  "properties": {
    "iso:country":"GB",
    "sg:address":"New Inn Bridge Estate",
    "sg:city":"Coventry",
    "sg:classifiers":[
        {
            "category":"Home & Garden",
            "subcategory":"Building Materials",
            "type":"Retail Goods"
        }
    ],
    "sg:phone":"+44 24 7663 8777",
    "sg:postcode":"CV6 6NE",
    "sg:province":"Warwickshire",
    "sg:tags":[
        "furnishers",
        "bathroom",
        "planner"
    ],
    "wof:name":"Leigh Stewart Products Ltd.",
    "wof:placetype":"venue"
},
  "geometry": {"coordinates":[-1.47446,52.459419],"type":"Point"}
}