{
  "type": "Feature",
  "properties": {
    "iso:country":"GB",
    "sg:address":"4 Nalders Court",
    "sg:city":"Truro",
    "sg:classifiers":[
        {
            "category":"Professional",
            "subcategory":"Art Services",
            "type":"Services"
        }
    ],
    "sg:postcode":"TR1 2XH",
    "sg:province":"Cornwall",
    "sg:tags":[
        "framing"
    ],
    "wof:name":"The Original Art Shop",
    "wof:placetype":"venue"
},
  "geometry": {"coordinates":[-5.0531439781,50.2639312744],"type":"Point"}
}