{
  "type": "Feature",
  "properties": {
    "iso:country":"GB",
    "sg:address":"Featherstall Rd South",
    "sg:city":"Oldham",
    "sg:classifiers":[
        {
            "category":"Train Station",
            "subcategory":"Rail",
            "type":"Transportation"
        }
    ],
    "sg:phone":"+44 161 678 7050",
    "sg:postcode":"OL9 6HL",
    "sg:province":"Lancashire",
    "sg:tags":[
        "caravan"
    ],
    "wof:name":"Manchester Caravans & Leisure Ltd",
    "wof:placetype":"venue"
},
  "geometry": {"coordinates":[-2.127094,53.547417],"type":"Point"}
}