{
  "type": "Feature",
  "properties": {
    "addr:full":"Cambridge Avenue Scunthorpe Lincolnshire DN16 3LG",
    "addr:postcode":"dn16 3lg",
    "addr:street":"Cambridge Avenue",
    "iso:country":"GB",
    "sg:address":"Cambridge Avenue",
    "sg:city":"Scunthorpe",
    "sg:classifiers":[
        {
            "category":"Health Services",
            "subcategory":"Doctor",
            "type":"Services"
        },
        {
            "category":"Health Services",
            "subcategory":"Clinic",
            "type":"Services"
        }
    ],
    "sg:phone":"+44 1724 842415",
    "sg:postcode":"DN16 3LG",
    "sg:province":"Lincolnshire",
    "sg:tags":[
        "nh",
        "practitioners"
    ],
    "wof:name":"The Medical Centre",
    "wof:placetype":"venue"
},
  "geometry": {"coordinates":[-0.635509,53.565834],"type":"Point"}
}