{
  "type": "Feature",
  "properties": {
    "iso:country":"GB",
    "sg:address":"295 High St",
    "sg:city":"Bangor",
    "sg:classifiers":[
        {
            "category":"Wholesale",
            "subcategory":"Medical Equipment & Supplies",
            "type":"Manufacturing & Wholesale Goods"
        }
    ],
    "sg:postcode":"LL57 1UL",
    "sg:province":"Gwynedd",
    "sg:tags":[
        "aid",
        "hearing"
    ],
    "wof:name":"Madoc Purchasing Ltd.",
    "wof:placetype":"venue"
},
  "geometry": {"coordinates":[-4.114512,53.230942],"type":"Point"}
}