{
  "type": "Feature",
  "properties": {
    "addr:full":"1 & 2 Coach House Mews, 33a High Street Bromley Kent BR1 1LA",
    "addr:housenumber":"1 & 2;33a",
    "addr:postcode":"br1 1la",
    "addr:street":"Coach House Mews;High Street",
    "iso:country":"GB",
    "sg:address":"1 & 2 Coach House Mews, 33a High Street",
    "sg:city":"Bromley",
    "sg:classifiers":[
        {
            "category":"Professional",
            "subcategory":"Lawyer & Legal Services",
            "type":"Services"
        }
    ],
    "sg:phone":"+44 20 8466 0967",
    "sg:postcode":"BR1 1LA",
    "sg:province":"Kent",
    "sg:tags":[
        "solicitor"
    ],
    "wof:name":"Dale R Walker Solicitor",
    "wof:placetype":"venue"
},
  "geometry": {"coordinates":[0.0170000009,51.4013290405],"type":"Point"}
}