{
  "type": "Feature",
  "properties": {
    "addr:full":"7 Barnet Dr Grimsby Lincolnshire DN36 4GH",
    "addr:housenumber":"7",
    "addr:postcode":"dn36 4gh",
    "addr:street":"Barnet Dr",
    "iso:country":"GB",
    "sg:address":"7 Barnet Dr",
    "sg:city":"Grimsby",
    "sg:classifiers":[
        {
            "category":"Professional",
            "subcategory":"Engineering",
            "type":"Services"
        }
    ],
    "sg:phone":"+44 1472 811800",
    "sg:postcode":"DN36 4GH",
    "sg:province":"Lincolnshire",
    "sg:tags":[
        "contractor",
        "electrical",
        "engineer"
    ],
    "wof:name":"N B M Electrics",
    "wof:placetype":"venue"
},
  "geometry": {"coordinates":[-0.0553979985,53.5298500061],"type":"Point"}
}