{
  "type": "Feature",
  "properties": {
    "iso:country":"GB",
    "sg:address":"Lower Road, Minster On Sea",
    "sg:city":"Sheerness",
    "sg:classifiers":[
        {
            "category":"Sports & Exercise",
            "subcategory":"Tennis Court",
            "type":"Entertainment"
        }
    ],
    "sg:phone":"+44 1795 871717",
    "sg:postcode":"ME12 3SR",
    "sg:province":"Kent",
    "sg:tags":[
        "breakdown",
        "recovery"
    ],
    "wof:name":"Halls Automotive",
    "wof:placetype":"venue"
},
  "geometry": {"coordinates":[0.776245,51.421951],"type":"Point"}
}