{
  "type": "Feature",
  "properties": {
    "iso:country":"GB",
    "sg:address":"35 Carter Street",
    "sg:city":"Sandown",
    "sg:classifiers":[
        {
            "category":"Organizations",
            "subcategory":"Non-profit Organization",
            "type":"Services"
        }
    ],
    "sg:phone":"+44 1983 408086",
    "sg:postcode":"PO36 8DQ",
    "sg:province":"Isle of Wight",
    "sg:tags":[
        "charitable",
        "organisation",
        "voluntary",
        "charity"
    ],
    "wof:name":"Whitecliff Christian Respite Centre",
    "wof:placetype":"venue"
},
  "geometry": {"coordinates":[-1.155529,50.658581],"type":"Point"}
}