{
  "type": "Feature",
  "properties": {
    "addr:full":"1, Watermeadow Small Industries, Liphook Road, Lindford Bordon Hampshire GU35 0PG",
    "addr:housenumber":"1",
    "addr:postcode":"gu35 0pg",
    "addr:street":"Watermeadow;Liphook Road",
    "iso:country":"GB",
    "sg:address":"1, Watermeadow Small Industries, Liphook Road, Lindford",
    "sg:city":"Bordon",
    "sg:classifiers":[
        {
            "category":"Retail",
            "subcategory":"Auto Repair",
            "type":"Services"
        }
    ],
    "sg:phone":"+44 1420 478267",
    "sg:postcode":"GU35 0PG",
    "sg:province":"Hampshire",
    "sg:tags":[
        "modification",
        "garage",
        "related"
    ],
    "wof:name":"Lindford Auto Repairs",
    "wof:placetype":"venue"
},
  "geometry": {"coordinates":[-0.8447639942,51.118598938],"type":"Point"}
}