{
  "type": "Feature",
  "properties": {
    "addr:full":"Ty'r Gweydd Farm, Wattstown Porth Bridgend CF39 0PS",
    "addr:postcode":"cf39 0ps",
    "addr:street":"Wattstown Porth",
    "iso:country":"GB",
    "sg:address":"Ty'r Gweydd Farm, Wattstown",
    "sg:city":"Porth",
    "sg:classifiers":[
        {
            "category":"Farming",
            "subcategory":"Livestock Farm",
            "type":"Manufacturing & Wholesale Goods"
        }
    ],
    "sg:phone":"+44 1443 730753",
    "sg:postcode":"CF39 0PS",
    "sg:province":"Bridgend",
    "sg:tags":[
        "others"
    ],
    "wof:name":"G Jenkins",
    "wof:placetype":"venue"
},
  "geometry": {"coordinates":[-3.42138,51.637589],"type":"Point"}
}