{
  "type": "Feature",
  "properties": {
    "addr:full":"Dogley Mills Huddersfield South Yorkshire HD8 0LE",
    "addr:postcode":"hd8 0le",
    "addr:street":"South",
    "iso:country":"GB",
    "sg:address":"Dogley Mills",
    "sg:city":"Huddersfield",
    "sg:classifiers":[
        {
            "category":"Government",
            "subcategory":"Post Office",
            "type":"Public Place"
        }
    ],
    "sg:postcode":"HD8 0LE",
    "sg:province":"South Yorkshire",
    "sg:tags":[
        "print",
        "typesetter"
    ],
    "wof:name":"Armitage Typo Graphics Ltd.",
    "wof:placetype":"venue"
},
  "geometry": {"coordinates":[-1.717939,53.623764],"type":"Point"}
}