{
  "type": "Feature",
  "properties": {
    "addr:full":"Mackays Building, Junction Road Kirkwall Orkney Islands KW15 1JY",
    "addr:postcode":"kw15 1jy",
    "addr:street":"Junction Road",
    "iso:country":"GB",
    "sg:address":"Mackays Building, Junction Road",
    "sg:city":"Kirkwall",
    "sg:classifiers":[
        {
            "category":"Home & Garden",
            "subcategory":"Home Furnishings",
            "type":"Retail Goods"
        }
    ],
    "sg:postcode":"KW15 1JY",
    "sg:province":"Orkney Islands",
    "sg:tags":[
        "mantelpiece",
        "fireplace"
    ],
    "wof:name":"The Lighting & Fireplace Centre",
    "wof:placetype":"venue"
},
  "geometry": {"coordinates":[-2.9604189396,58.9817314148],"type":"Point"}
}