{
  "type": "Feature",
  "properties": {
    "iso:country":"GB",
    "sg:address":"101 Walford Road",
    "sg:city":"Birmingham",
    "sg:classifiers":[
        {
            "category":"Shopping",
            "subcategory":"Department Store",
            "type":"Retail Goods"
        }
    ],
    "sg:postcode":"B11 1QL",
    "sg:province":"West Midlands",
    "wof:name":"Mughan General Stores",
    "wof:placetype":"venue"
},
  "geometry": {"coordinates":[-1.866311,52.459251],"type":"Point"}
}