{
  "type": "Feature",
  "properties": {
    "addr:full":"130 Broughton Street Manchester Greater Manchester M8 8AN",
    "addr:housenumber":"130",
    "addr:postcode":"m8 8an",
    "addr:street":"Broughton Street",
    "iso:country":"GB",
    "sg:address":"130 Broughton Street",
    "sg:city":"Manchester",
    "sg:classifiers":[
        {
            "category":"Shopping",
            "subcategory":"Clothing, Apparel, & Fashions",
            "type":"Retail Goods"
        }
    ],
    "sg:phone":"+44 161 834 7003",
    "sg:postcode":"M8 8AN",
    "sg:province":"Greater Manchester",
    "sg:tags":[
        "shop",
        "menswear"
    ],
    "wof:name":"Robert Leonards (Clothiers) Ltd.",
    "wof:placetype":"venue"
},
  "geometry": {"coordinates":[-2.2463300228,53.4972419739],"type":"Point"}
}