{
  "type": "Feature",
  "properties": {
    "addr:full":"62 Charles Street Stockport Cheshire SK1 3JR",
    "addr:housenumber":"62",
    "addr:postcode":"sk1 3jr",
    "addr:street":"Charles Street",
    "iso:country":"GB",
    "sg:address":"62 Charles Street",
    "sg:city":"Stockport",
    "sg:classifiers":[
        {
            "category":"Food & Beverages",
            "subcategory":"Meat & Fish",
            "type":"Retail Goods"
        }
    ],
    "sg:phone":"+44 161 480 6454",
    "sg:postcode":"SK1 3JR",
    "sg:province":"Cheshire",
    "sg:tags":[
        "chip"
    ],
    "wof:name":"Charles Street Chippy",
    "wof:placetype":"venue"
},
  "geometry": {"coordinates":[-2.1509931087,53.4006576538],"type":"Point"}
}