{
  "type": "Feature",
  "properties": {
    "iso:country":"GB",
    "sg:address":"East Barkshire Colle, Montem Lastation Road",
    "sg:city":"Slough",
    "sg:classifiers":[
        {
            "category":"Health Services",
            "subcategory":"Clinic",
            "type":"Services"
        },
        {
            "category":"Health Services",
            "subcategory":"Health Practitioner",
            "type":"Services"
        }
    ],
    "sg:phone":"+44 1753 584458",
    "sg:postcode":"SL3 8BY",
    "sg:province":"Berkshire",
    "sg:tags":[
        "physiotherapist",
        "injury",
        "sport"
    ],
    "wof:name":"The Slough Sports Injuries Clinic",
    "wof:placetype":"venue"
},
  "geometry": {"coordinates":[-0.5451599956,51.5055999756],"type":"Point"}
}