{
  "type": "Feature",
  "properties": {
    "addr:full":"65 Cardiff Street Aberdare Neath Port Talbot CF44 7DG",
    "addr:housenumber":"65",
    "addr:postcode":"cf44 7dg",
    "addr:street":"Cardiff Street",
    "iso:country":"GB",
    "sg:address":"65 Cardiff Street",
    "sg:city":"Aberdare",
    "sg:classifiers":[
        {
            "category":"Fast Food",
            "type":"Food & Drink"
        }
    ],
    "sg:phone":"+44 1685 882799",
    "sg:postcode":"CF44 7DG",
    "sg:province":"Neath Port Talbot",
    "sg:tags":[
        "away",
        "take"
    ],
    "wof:name":"G & T A Negrotti",
    "wof:placetype":"venue"
},
  "geometry": {"coordinates":[-3.444016,51.712955],"type":"Point"}
}