{
  "type": "Feature",
  "properties": {
    "addr:full":"Flixton Lowestoft Suffolk NR32 5PE",
    "addr:postcode":"nr32 5pe",
    "iso:country":"GB",
    "sg:address":"Flixton",
    "sg:city":"Lowestoft",
    "sg:classifiers":[
        {
            "category":"Farming",
            "subcategory":"Livestock Farm",
            "type":"Manufacturing & Wholesale Goods"
        }
    ],
    "sg:postcode":"NR32 5PE",
    "sg:province":"Suffolk",
    "sg:tags":[
        "others"
    ],
    "wof:name":"Old Hall Farm",
    "wof:placetype":"venue"
},
  "geometry": {"coordinates":[1.70867,52.500549],"type":"Point"}
}