{
  "type": "Feature",
  "properties": {
    "addr:full":"Glendearg Galashiels Scottish Borders TD1 2NR",
    "addr:postcode":"td1 2nr",
    "iso:country":"GB",
    "sg:address":"Glendearg",
    "sg:city":"Galashiels",
    "sg:classifiers":[
        {
            "category":"Sports & Exercise",
            "subcategory":"Golf",
            "type":"Entertainment"
        }
    ],
    "sg:phone":"+44 1896 752413",
    "sg:postcode":"TD1 2NR",
    "sg:province":"Scottish Borders",
    "sg:tags":[
        "range",
        "driving"
    ],
    "wof:name":"Meadowfield Golf Driving Range",
    "wof:placetype":"venue"
},
  "geometry": {"coordinates":[-2.7888491154,55.6501808167],"type":"Point"}
}