{
  "type": "Feature",
  "properties": {
    "addr:full":"Lower Common Lane, Scissett Huddersfield South Yorkshire HD8 9HL",
    "addr:postcode":"hd8 9hl",
    "addr:street":"Lower Common Lane",
    "iso:country":"GB",
    "sg:address":"Lower Common Lane, Scissett",
    "sg:city":"Huddersfield",
    "sg:classifiers":[
        {
            "category":"Farming",
            "subcategory":"Nursery",
            "type":"Manufacturing & Wholesale Goods"
        },
        {
            "category":"Social Services",
            "subcategory":"Child Care",
            "type":"Services"
        }
    ],
    "sg:phone":"+44 1484 864926",
    "sg:postcode":"HD8 9HL",
    "sg:province":"South Yorkshire",
    "sg:tags":[
        "creche"
    ],
    "wof:name":"Hillside House Day Nursery",
    "wof:placetype":"venue"
},
  "geometry": {"coordinates":[-1.6225759983,53.5880622864],"type":"Point"}
}