{
  "type": "Feature",
  "properties": {
    "addr:full":"5 Evelyn Terrace Brighton East Sussex BN2 0EP",
    "addr:housenumber":"5",
    "addr:postcode":"bn2 0ep",
    "addr:street":"Evelyn Terrace",
    "iso:country":"GB",
    "sg:address":"5 Evelyn Terrace",
    "sg:city":"Brighton",
    "sg:classifiers":[
        {
            "category":"Health Services",
            "subcategory":"Doctor",
            "type":"Services"
        }
    ],
    "sg:phone":"+44 1273 690026",
    "sg:postcode":"BN2 0EP",
    "sg:province":"East Sussex",
    "sg:tags":[
        "practitioners"
    ],
    "wof:name":"J P Swift",
    "wof:placetype":"venue"
},
  "geometry": {"coordinates":[-0.1215939969,50.8242835999],"type":"Point"}
}