{
  "type": "Feature",
  "properties": {
    "iso:country":"GB",
    "sg:address":"57 Sherrard St",
    "sg:city":"Melton Mowbray",
    "sg:classifiers":[
        {
            "category":"Communications",
            "type":"Services"
        }
    ],
    "sg:phone":"+44 1664 560065",
    "sg:postcode":"LE13 1XH",
    "sg:province":"Leicestershire",
    "sg:tags":[
        "telecommunication"
    ],
    "wof:name":"Phoneline Communications",
    "wof:placetype":"venue"
},
  "geometry": {"coordinates":[-0.883456,52.764763],"type":"Point"}
}