{
  "type": "Feature",
  "properties": {
    "addr:full":"Greensland Farm, Sutton Manderville Salisbury Wiltshire SP3 5NL",
    "addr:postcode":"sp3 5nl",
    "iso:country":"GB",
    "sg:address":"Greensland Farm, Sutton Manderville",
    "sg:city":"Salisbury",
    "sg:classifiers":[
        {
            "category":"Real Estate",
            "subcategory":"Surveying",
            "type":"Services"
        }
    ],
    "sg:postcode":"SP3 5NL",
    "sg:province":"Wiltshire",
    "sg:tags":[
        "surveyor",
        "valuer"
    ],
    "wof:name":"Ian Smee",
    "wof:placetype":"venue"
},
  "geometry": {"coordinates":[-2.02843,51.048279],"type":"Point"}
}