{
  "type": "Feature",
  "properties": {
    "iso:country":"GB",
    "sg:address":"53 George Street",
    "sg:city":"Oldham",
    "sg:classifiers":[
        {
            "category":"Shopping",
            "subcategory":"Clothing, Apparel, & Fashions",
            "type":"Retail Goods"
        }
    ],
    "sg:postcode":"OL1 1LT",
    "sg:province":"Lancashire",
    "sg:tags":[
        "shop"
    ],
    "wof:name":"Joanna Dickinson",
    "wof:placetype":"venue"
},
  "geometry": {"coordinates":[-2.115805,53.54047],"type":"Point"}
}