{
  "type": "Feature",
  "properties": {
    "addr:full":"133 High St Sheerness Kent ME12 1UD",
    "addr:housenumber":"133",
    "addr:postcode":"me12 1ud",
    "addr:street":"High St",
    "iso:country":"GB",
    "sg:address":"133 High St",
    "sg:city":"Sheerness",
    "sg:classifiers":[
        {
            "category":"Taxi",
            "type":"Transportation"
        }
    ],
    "sg:phone":"+44 1795 661000",
    "sg:postcode":"ME12 1UD",
    "sg:province":"Kent",
    "sg:tags":[
        "mini",
        "cab"
    ],
    "wof:name":"Val's Cars 1998 Ltd",
    "wof:placetype":"venue"
},
  "geometry": {"coordinates":[0.763503015,51.4383163452],"type":"Point"}
}