{
  "type": "Feature",
  "properties": {
    "iso:country":"GB",
    "sg:address":"1 Deanhaugh Street",
    "sg:city":"Edinburgh",
    "sg:classifiers":[
        {
            "category":"Food & Beverages",
            "subcategory":"Bakery",
            "type":"Retail Goods"
        }
    ],
    "sg:phone":"+44 131 332 7229",
    "sg:postcode":"EH4 1LU",
    "sg:province":"City of Edinburgh",
    "sg:tags":[
        "pizza"
    ],
    "wof:name":"Pizzaexpress (Restaurants) Ltd.",
    "wof:placetype":"venue"
},
  "geometry": {"coordinates":[-3.2093920708,55.9584083557],"type":"Point"}
}