{
  "type": "Feature",
  "properties": {
    "iso:country":"GB",
    "sg:address":"Unit 24, Sandwich Industrial Estate",
    "sg:city":"Sandwich",
    "sg:classifiers":[
        {
            "category":"Manufacturing",
            "subcategory":"Metals",
            "type":"Manufacturing & Wholesale Goods"
        }
    ],
    "sg:phone":"+44 1304 621121",
    "sg:postcode":"CT13 9LY",
    "sg:province":"Kent",
    "sg:tags":[
        "steel",
        "fabricator",
        "erectors"
    ],
    "wof:name":"T & D Fabrications",
    "wof:placetype":"venue"
},
  "geometry": {"coordinates":[1.3423039913,51.2761688232],"type":"Point"}
}