{
  "type": "Feature",
  "properties": {
    "iso:country":"GB",
    "sg:address":"3 The Neighbourhood Centre, Cogges Hill Road",
    "sg:city":"Witney",
    "sg:classifiers":[
        {
            "category":"Fast Food",
            "type":"Food & Drink"
        }
    ],
    "sg:phone":"+44 1993 776679",
    "sg:postcode":"OX28 3XY",
    "sg:province":"Oxfordshire",
    "sg:tags":[
        "away",
        "meal",
        "outlet",
        "take"
    ],
    "wof:name":"Golden Palace Chinese Take Away",
    "wof:placetype":"venue"
},
  "geometry": {"coordinates":[-1.496171,51.782642],"type":"Point"}
}