{
  "type": "Feature",
  "properties": {
    "addr:full":"Wrose Road Shipley West Yorkshire BD18 1JF",
    "addr:postcode":"bd18 1jf",
    "addr:street":"Wrose Road",
    "iso:country":"GB",
    "sg:address":"Wrose Road",
    "sg:city":"Shipley",
    "sg:classifiers":[
        {
            "category":"Bars & Pubs",
            "type":"Food & Drink"
        }
    ],
    "sg:phone":"+44 1274 595294",
    "sg:postcode":"BD18 1JF",
    "sg:province":"West Yorkshire",
    "sg:tags":[
        "pubs",
        "inn"
    ],
    "wof:name":"Punch Retail (Holdings) Ltd.",
    "wof:placetype":"venue"
},
  "geometry": {"coordinates":[-1.7581889629,53.8288269043],"type":"Point"}
}