{
  "type": "Feature",
  "properties": {
    "addr:full":"33 Southgate Street Gloucester Gloucestershire GL1 1TX",
    "addr:housenumber":"33",
    "addr:postcode":"gl1 1tx",
    "addr:street":"Southgate Street",
    "iso:country":"GB",
    "sg:address":"33 Southgate Street",
    "sg:city":"Gloucester",
    "sg:classifiers":[
        {
            "category":"Shopping",
            "subcategory":"Crafts & Fabrics",
            "type":"Retail Goods"
        }
    ],
    "sg:phone":"+44 1452 311709",
    "sg:postcode":"GL1 1TX",
    "sg:province":"Gloucestershire",
    "sg:tags":[
        "shop"
    ],
    "wof:name":"James Gaunt",
    "wof:placetype":"venue"
},
  "geometry": {"coordinates":[-2.247722,51.863857],"type":"Point"}
}