{
  "type": "Feature",
  "properties": {
    "iso:country":"GB",
    "sg:address":"75 New Bond Street",
    "sg:city":"London",
    "sg:classifiers":[
        {
            "category":"Shopping",
            "subcategory":"Department Store",
            "type":"Retail Goods"
        }
    ],
    "sg:phone":"+44 20 7629 8883",
    "sg:postcode":"W1S 1RU",
    "sg:province":"Greater London",
    "wof:name":"M Abram Ltd.",
    "wof:placetype":"venue"
},
  "geometry": {"coordinates":[-0.14614,51.514137],"type":"Point"}
}