{
  "type": "Feature",
  "properties": {
    "addr:full":"Harold Hill Health Centre, Gooshays Drive, Ingrebourn Romford Essex RM3 9SU",
    "addr:postcode":"rm3 9su",
    "addr:street":"Gooshays Drive",
    "iso:country":"GB",
    "sg:address":"Harold Hill Health Centre, Gooshays Drive, Ingrebourn",
    "sg:city":"Romford",
    "sg:classifiers":[
        {
            "category":"Health Services",
            "subcategory":"Clinic",
            "type":"Services"
        }
    ],
    "sg:phone":"+44 1708 796405",
    "sg:postcode":"RM3 9SU",
    "sg:province":"Essex",
    "sg:tags":[
        "private"
    ],
    "wof:name":"Community Dental Service",
    "wof:placetype":"venue"
},
  "geometry": {"coordinates":[0.2248599976,51.606338501],"type":"Point"}
}