{
  "type": "Feature",
  "properties": {
    "iso:country":"GB",
    "sg:address":"Balsusney Road",
    "sg:city":"Kirkcaldy",
    "sg:classifiers":[
        {
            "category":"Education",
            "subcategory":"School",
            "type":"Public Place"
        },
        {
            "category":"Government",
            "subcategory":"Office",
            "type":"Public Place"
        }
    ],
    "sg:phone":"+44 1592 412173",
    "sg:postcode":"KY2 5LH",
    "sg:province":"Fife",
    "sg:tags":[
        "local",
        "authority"
    ],
    "wof:name":"Fife District Council",
    "wof:placetype":"venue"
},
  "geometry": {"coordinates":[-3.1595709324,56.1189498901],"type":"Point"}
}