{
  "type": "Feature",
  "properties": {
    "addr:full":"28 Sidney Gro Clerkenwell Greater London EC1V 7LP",
    "addr:housenumber":"28",
    "addr:postcode":"ec1v 7lp",
    "addr:street":"Sidney Gro",
    "iso:country":"GB",
    "sg:address":"28 Sidney Gro",
    "sg:city":"Clerkenwell",
    "sg:classifiers":[
        {
            "category":"Professional",
            "subcategory":"Engineering",
            "type":"Services"
        }
    ],
    "sg:phone":"+44 20 7278 5440",
    "sg:postcode":"EC1V 7LP",
    "sg:province":"Greater London",
    "wof:name":"Baltar Engineering",
    "wof:placetype":"venue"
},
  "geometry": {"coordinates":[-0.101932,51.528568],"type":"Point"}
}