{
  "type": "Feature",
  "properties": {
    "addr:full":"495a Bromley Road Bromley Kent BR1 4PQ",
    "addr:housenumber":"495a",
    "addr:postcode":"br1 4pq",
    "addr:street":"Bromley Road",
    "iso:country":"GB",
    "sg:address":"495a Bromley Road",
    "sg:city":"Bromley",
    "sg:classifiers":[
        {
            "category":"Health Services",
            "subcategory":"Optometrist",
            "type":"Services"
        },
        {
            "category":"Professional",
            "subcategory":"Detective & Security Services",
            "type":"Services"
        },
        {
            "category":"Organizations",
            "subcategory":"Membership Organization",
            "type":"Services"
        }
    ],
    "sg:phone":"+44 20 8697 2321",
    "sg:postcode":"BR1 4PQ",
    "sg:province":"Kent",
    "sg:tags":[
        "club",
        "video",
        "cctv",
        "optician"
    ],
    "wof:name":"Points of View",
    "wof:placetype":"venue"
},
  "geometry": {"coordinates":[-0.003214,51.423538208],"type":"Point"}
}