{
  "type": "Feature",
  "properties": {
    "iso:country":"GB",
    "sg:address":"41 High Road, Bushey",
    "sg:city":"Watford",
    "sg:classifiers":[
        {
            "category":"Shopping",
            "subcategory":"Department Store",
            "type":"Retail Goods"
        }
    ],
    "sg:phone":"+44 20 8950 4448",
    "sg:postcode":"WD2 1BN",
    "sg:province":"Hertfordshire",
    "wof:name":"Budgens Stores Ltd.",
    "wof:placetype":"venue"
},
  "geometry": {"coordinates":[-0.36307,51.644341],"type":"Point"}
}