{
  "type": "Feature",
  "properties": {
    "addr:full":"479-481 London Road Camberley Berkshire GU15 3JA",
    "addr:housenumber":"479-481",
    "addr:postcode":"gu15 3ja",
    "addr:street":"London Road",
    "iso:country":"GB",
    "sg:address":"479-481 London Road",
    "sg:city":"Camberley",
    "sg:classifiers":[
        {
            "category":"Shopping",
            "subcategory":"Discount & Variety Stores",
            "type":"Retail Goods"
        }
    ],
    "sg:postcode":"GU15 3JA",
    "sg:province":"Berkshire",
    "sg:tags":[
        "cleaning",
        "supply"
    ],
    "wof:name":"A1 Services (Southern)",
    "wof:placetype":"venue"
},
  "geometry": {"coordinates":[-0.766527,51.33445],"type":"Point"}
}