{
  "type": "Feature",
  "properties": {
    "iso:country":"GB",
    "sg:address":"Coedcae Farm",
    "sg:city":"Llanbrynmair",
    "sg:classifiers":[
        {
            "category":"Farming",
            "subcategory":"Livestock Farm",
            "type":"Manufacturing & Wholesale Goods"
        }
    ],
    "sg:phone":"+44 1650 521242",
    "sg:postcode":"SY19 7AB",
    "sg:province":"Powys",
    "sg:tags":[
        "others"
    ],
    "wof:name":"Hywel B Davies",
    "wof:placetype":"venue"
},
  "geometry": {"coordinates":[-3.638787,52.61092],"type":"Point"}
}