{
  "type": "Feature",
  "properties": {
    "iso:country":"GB",
    "sg:address":"Dukes Way, Teeside Industrial Estate, Thornaby",
    "sg:city":"Stockton-on-tees",
    "sg:classifiers":[
        {
            "category":"Professional",
            "subcategory":"Testing Lab",
            "type":"Services"
        },
        {
            "category":"Utilities",
            "subcategory":"Fuel Oil & Lpg",
            "type":"Services"
        },
        {
            "category":"Professional",
            "subcategory":"Engineering",
            "type":"Services"
        }
    ],
    "sg:phone":"+44 1642 769906",
    "sg:postcode":"TS17 9LT",
    "sg:province":"Durham",
    "sg:tags":[
        "inspection",
        "engineer",
        "gas",
        "calibration"
    ],
    "wof:name":"C E C Time Ltd.",
    "wof:placetype":"venue"
},
  "geometry": {"coordinates":[-1.292764,54.51828],"type":"Point"}
}