{
  "type": "Feature",
  "properties": {
    "addr:full":"Crondall Lane Farnham Surrey GU9 7BG",
    "addr:postcode":"gu9 7bg",
    "addr:street":"Crondall Lane",
    "iso:country":"GB",
    "sg:address":"Crondall Lane",
    "sg:city":"Farnham",
    "sg:classifiers":[
        {
            "category":"Autos & Motor Vehicles",
            "subcategory":"Automobile Sales",
            "type":"Retail Goods"
        }
    ],
    "sg:postcode":"GU9 7BG",
    "sg:province":"Surrey",
    "sg:tags":[
        "car"
    ],
    "wof:name":"Barnett & Small Ltd.",
    "wof:placetype":"venue"
},
  "geometry": {"coordinates":[-0.8193420172,51.2156028748],"type":"Point"}
}