{
  "type": "Feature",
  "properties": {
    "addr:full":"Corner Stones, Beech Waye Gerrards Cross Buckinghamshire SL9 8BL",
    "addr:postcode":"sl9 8bl",
    "iso:country":"GB",
    "sg:address":"Corner Stones, Beech Waye",
    "sg:city":"Gerrards Cross",
    "sg:classifiers":[
        {
            "category":"Professional",
            "subcategory":"Management & Consulting",
            "type":"Services"
        }
    ],
    "sg:postcode":"SL9 8BL",
    "sg:province":"Buckinghamshire",
    "sg:tags":[
        "consultant",
        "business"
    ],
    "wof:name":"Sherrad,Brian,",
    "wof:placetype":"venue"
},
  "geometry": {"coordinates":[-0.5625789762,51.5789756775],"type":"Point"}
}