{
  "type": "Feature",
  "properties": {
    "addr:full":"12 Wombwell Road, Hoyland Barnsley South Yorkshire S74 9SQ",
    "addr:housenumber":"12",
    "addr:postcode":"s74 9sq",
    "addr:street":"Wombwell Road;Yorkshire",
    "iso:country":"GB",
    "sg:address":"12 Wombwell Road, Hoyland",
    "sg:city":"Barnsley",
    "sg:classifiers":[
        {
            "category":"Personal",
            "subcategory":"Beauty Salon",
            "type":"Services"
        }
    ],
    "sg:phone":"+44 1226 742001",
    "sg:postcode":"S74 9SQ",
    "sg:province":"South Yorkshire",
    "sg:tags":[
        "unisex",
        "hairdresser"
    ],
    "wof:name":"Reflections",
    "wof:placetype":"venue"
},
  "geometry": {"coordinates":[-1.440875,53.508995],"type":"Point"}
}