{
  "type": "Feature",
  "properties": {
    "iso:country":"GB",
    "sg:address":"85 High St",
    "sg:city":"Houghton Le Spring",
    "sg:classifiers":[
        {
            "category":"Bus Charters",
            "type":"Transportation"
        }
    ],
    "sg:phone":"+44 191 526 6257",
    "sg:postcode":"DH5 0JR",
    "sg:province":"Durham",
    "sg:tags":[
        "hire",
        "coach"
    ],
    "wof:name":"Style Travel",
    "wof:placetype":"venue"
},
  "geometry": {"coordinates":[-1.4375439882,54.8089065552],"type":"Point"}
}