{
  "type": "Feature",
  "properties": {
    "addr:full":"64 School Lane, Little Melton Norwich Norfolk NR9 3AE",
    "addr:housenumber":"64",
    "addr:postcode":"nr9 3ae",
    "addr:street":"School Lane",
    "iso:country":"GB",
    "sg:address":"64 School Lane, Little Melton",
    "sg:city":"Norwich",
    "sg:classifiers":[
        {
            "category":"Retail",
            "subcategory":"Auto Repair",
            "type":"Services"
        }
    ],
    "sg:phone":"+44 1603 810172",
    "sg:postcode":"NR9 3AE",
    "sg:province":"Norfolk",
    "sg:tags":[
        "modification",
        "garage",
        "related"
    ],
    "wof:name":"Little Melton Service Station",
    "wof:placetype":"venue"
},
  "geometry": {"coordinates":[1.200979948,52.6200523376],"type":"Point"}
}