{
  "type": "Feature",
  "properties": {
    "iso:country":"GB",
    "sg:address":"24 Maddox Street",
    "sg:city":"London",
    "sg:classifiers":[
        {
            "category":"Wholesale",
            "subcategory":"Books, Periodicals, & Newspapers",
            "type":"Manufacturing & Wholesale Goods"
        }
    ],
    "sg:postcode":"W1S 1PP",
    "sg:province":"Greater London",
    "sg:tags":[
        "publishing"
    ],
    "wof:name":"Countrywide Editions Ltd.",
    "wof:placetype":"venue"
},
  "geometry": {"coordinates":[-0.142262,51.513145],"type":"Point"}
}