{
  "type": "Feature",
  "properties": {
    "iso:country":"GB",
    "sg:address":"30 Abington Avenue",
    "sg:city":"Sutton-in-ashfield",
    "sg:classifiers":[
        {
            "category":"Shopping",
            "subcategory":"Computers & Home Electronics",
            "type":"Retail Goods"
        },
        {
            "category":"Building & Trades",
            "subcategory":"Construction",
            "type":"Services"
        }
    ],
    "sg:phone":"+44 1623 511260",
    "sg:postcode":"NG17 4NH",
    "sg:province":"Nottinghamshire",
    "sg:tags":[
        "supplier",
        "radio",
        "television",
        "erectors",
        "aerial"
    ],
    "wof:name":"Alpine Aerials",
    "wof:placetype":"venue"
},
  "geometry": {"coordinates":[-1.260616,53.139259],"type":"Point"}
}