{
  "type": "Feature",
  "properties": {
    "iso:country":"GB",
    "sg:address":"Garthspool, Lerwick",
    "sg:city":"Shetland",
    "sg:classifiers":[
        {
            "category":"Utilities",
            "type":"Services"
        }
    ],
    "sg:phone":"+44 870 743 0585",
    "sg:postcode":"ZE1 0NY",
    "sg:province":"Shetland Islands",
    "sg:tags":[
        "connection",
        "provider",
        "internet"
    ],
    "wof:name":"Zetnet Services Ltd.",
    "wof:placetype":"venue"
},
  "geometry": {"coordinates":[-1.145224,60.151829],"type":"Point"}
}