{
  "type": "Feature",
  "properties": {
    "iso:country":"GB",
    "sg:address":"1 Glebe Farm Court, Up Hatherley",
    "sg:city":"Cheltenham",
    "sg:classifiers":[
        {
            "category":"Social Services",
            "subcategory":"Adult Care",
            "type":"Services"
        }
    ],
    "sg:phone":"+44 1242 862524",
    "sg:postcode":"GL51 3EB",
    "sg:province":"Gloucestershire",
    "sg:tags":[
        "housing",
        "sheltered"
    ],
    "wof:name":"Glebe Farm Court",
    "wof:placetype":"venue"
},
  "geometry": {"coordinates":[-2.10719,51.881969],"type":"Point"}
}