{
  "type": "Feature",
  "properties": {
    "iso:country":"GB",
    "sg:address":"17 Rowantree Avenue",
    "sg:city":"Currie",
    "sg:classifiers":[
        {
            "category":"Building & Trades",
            "subcategory":"Construction",
            "type":"Services"
        }
    ],
    "sg:postcode":"EH14 5AU",
    "sg:province":"City of Edinburgh",
    "sg:tags":[
        "decorator",
        "painter"
    ],
    "wof:name":"Brian Scott Decorating",
    "wof:placetype":"venue"
},
  "geometry": {"coordinates":[-3.325318,55.89418],"type":"Point"}
}