{
  "type": "Feature",
  "properties": {
    "iso:country":"GB",
    "sg:address":"Redstone Indust Est, Redstone Rd",
    "sg:city":"Boston",
    "sg:classifiers":[
        {
            "category":"Wholesale",
            "subcategory":"Scrap",
            "type":"Manufacturing & Wholesale Goods"
        }
    ],
    "sg:postcode":"PE21 8EA",
    "sg:province":"Lincolnshire",
    "sg:tags":[
        "breaker",
        "dismantlers"
    ],
    "wof:name":"D J Services",
    "wof:placetype":"venue"
},
  "geometry": {"coordinates":[-0.0297219995,52.9679336548],"type":"Point"}
}