{
  "type": "Feature",
  "properties": {
    "addr:full":"16 Duke Street Deal Kent CT14 6DU",
    "addr:housenumber":"16",
    "addr:postcode":"ct14 6du",
    "addr:street":"Duke Street Deal",
    "iso:country":"GB",
    "sg:address":"16 Duke Street",
    "sg:city":"Deal",
    "sg:classifiers":[
        {
            "category":"Bars & Pubs",
            "type":"Food & Drink"
        }
    ],
    "sg:postcode":"CT14 6DU",
    "sg:province":"Kent",
    "sg:tags":[
        "pubs",
        "inn"
    ],
    "wof:name":"The Deal Hoy",
    "wof:placetype":"venue"
},
  "geometry": {"coordinates":[1.4007489681,51.2268753052],"type":"Point"}
}