{
  "type": "Feature",
  "properties": {
    "iso:country":"GB",
    "sg:address":"Town Street, Horsforth",
    "sg:city":"Leeds",
    "sg:classifiers":[
        {
            "category":"Health Services",
            "subcategory":"Doctor",
            "type":"Services"
        }
    ],
    "sg:phone":"+44 113 258 9333",
    "sg:postcode":"LS18 5BN",
    "sg:province":"West Yorkshire",
    "sg:tags":[
        "practitioners"
    ],
    "wof:name":"The Croft Surgery",
    "wof:placetype":"venue"
},
  "geometry": {"coordinates":[-1.639264,53.839245],"type":"Point"}
}