{
  "type": "Feature",
  "properties": {
    "addr:full":"51 Oldhill Street London Greater London N16 6LU",
    "addr:housenumber":"51",
    "addr:postcode":"n16 6lu",
    "addr:street":"Oldhill Street",
    "iso:country":"GB",
    "sg:address":"51 Oldhill Street",
    "sg:city":"London",
    "sg:classifiers":[
        {
            "category":"Shopping",
            "subcategory":"Pharmacy",
            "type":"Retail Goods"
        }
    ],
    "sg:postcode":"N16 6LU",
    "sg:province":"Greater London",
    "sg:tags":[
        "pharmacist",
        "chemist"
    ],
    "wof:name":"D P Mark",
    "wof:placetype":"venue"
},
  "geometry": {"coordinates":[-0.0658129975,51.5689163208],"type":"Point"}
}