{
  "type": "Feature",
  "properties": {
    "addr:full":"New Ground, Northway, Midsomer Norton Bath Somerset BA3 2DX",
    "addr:postcode":"ba3 2dx",
    "addr:street":"New Ground Northway",
    "iso:country":"GB",
    "sg:address":"New Ground, Northway, Midsomer Norton",
    "sg:city":"Bath",
    "sg:classifiers":[
        {
            "category":"Arena",
            "subcategory":"Sports Club",
            "type":"Entertainment"
        }
    ],
    "sg:phone":"+44 1761 412827",
    "sg:postcode":"BA3 2DX",
    "sg:province":"Somerset",
    "wof:name":"Midsomer Norton Rugby Football Club",
    "wof:placetype":"venue"
},
  "geometry": {"coordinates":[-2.4871239662,51.2867698669],"type":"Point"}
}