{
  "type": "Feature",
  "properties": {
    "addr:full":"258 Seven Sisters Rd London Greater London N4 2HY",
    "addr:housenumber":"258",
    "addr:postcode":"n4 2hy",
    "addr:street":"Seven Sisters Rd",
    "iso:country":"GB",
    "sg:address":"258 Seven Sisters Rd",
    "sg:city":"London",
    "sg:classifiers":[
        {
            "category":"Food & Beverages",
            "subcategory":"Supermarket",
            "type":"Retail Goods"
        }
    ],
    "sg:postcode":"N4 2HY",
    "sg:province":"Greater London",
    "wof:name":"Sunrise Food Stop",
    "wof:placetype":"venue"
},
  "geometry": {"coordinates":[-0.105332002,51.5641365051],"type":"Point"}
}