{
  "type": "Feature",
  "properties": {
    "addr:full":"42 Church Street, Yaxley Peterborough Cambridgeshire PE7 3LH",
    "addr:housenumber":"42",
    "addr:postcode":"pe7 3lh",
    "addr:street":"Church Street",
    "iso:country":"GB",
    "sg:address":"42 Church Street, Yaxley",
    "sg:city":"Peterborough",
    "sg:classifiers":[
        {
            "category":"Professional",
            "subcategory":"Computer Services",
            "type":"Services"
        }
    ],
    "sg:postcode":"PE7 3LH",
    "sg:province":"Cambridgeshire",
    "sg:tags":[
        "consultant"
    ],
    "wof:name":"Equus Systems Ltd.",
    "wof:placetype":"venue"
},
  "geometry": {"coordinates":[-0.24762,52.477371],"type":"Point"}
}