{
  "type": "Feature",
  "properties": {
    "addr:full":"34 Brooks Rd Cambridge Cambridgeshire CB1 3HR",
    "addr:housenumber":"34",
    "addr:postcode":"cb1 3hr",
    "addr:street":"Brooks Rd",
    "iso:country":"GB",
    "sg:address":"34 Brooks Rd",
    "sg:city":"Cambridge",
    "sg:classifiers":[
        {
            "category":"Building & Trades",
            "subcategory":"Construction",
            "type":"Services"
        }
    ],
    "sg:phone":"+44 1223 245058",
    "sg:postcode":"CB1 3HR",
    "sg:province":"Cambridgeshire",
    "sg:tags":[
        "builder"
    ],
    "wof:name":"L H Blows",
    "wof:placetype":"venue"
},
  "geometry": {"coordinates":[0.156922996,52.1997947693],"type":"Point"}
}