{
  "type": "Feature",
  "properties": {
    "addr:full":"24 Blackstock Road London Greater London N4 2DW",
    "addr:housenumber":"24",
    "addr:postcode":"n4 2dw",
    "addr:street":"Blackstock Road",
    "iso:country":"GB",
    "sg:address":"24 Blackstock Road",
    "sg:city":"London",
    "sg:classifiers":[
        {
            "category":"Restaurant",
            "type":"Food & Drink"
        }
    ],
    "sg:phone":"+44 20 7437 0560",
    "sg:postcode":"N4 2DW",
    "sg:province":"Greater London",
    "wof:name":"Mediterranean Cafe",
    "wof:placetype":"venue"
},
  "geometry": {"coordinates":[-0.1034630015,51.5639343262],"type":"Point"}
}