{
  "type": "Feature",
  "properties": {
    "addr:full":"Mcmillan Centre, Dorset St Bradford West Yorkshire BD5 0LT",
    "addr:postcode":"bd5 0lt",
    "addr:street":"Dorset St",
    "iso:country":"GB",
    "sg:address":"Mcmillan Centre, Dorset St",
    "sg:city":"Bradford",
    "sg:classifiers":[
        {
            "category":"Professional",
            "subcategory":"Employment Agencies",
            "type":"Services"
        }
    ],
    "sg:phone":"+44 1274 521119",
    "sg:postcode":"BD5 0LT",
    "sg:province":"West Yorkshire",
    "sg:tags":[
        "career",
        "guidance"
    ],
    "wof:name":"Y Mega Job Club",
    "wof:placetype":"venue"
},
  "geometry": {"coordinates":[-1.7647,53.778992],"type":"Point"}
}