{
  "type": "Feature",
  "properties": {
    "addr:full":"431 Millbrook Road West Southampton Hampshire SO15 0HX",
    "addr:housenumber":"431",
    "addr:postcode":"so15 0hx",
    "addr:street":"Millbrook Road West",
    "iso:country":"GB",
    "sg:address":"431 Millbrook Road West",
    "sg:city":"Southampton",
    "sg:classifiers":[
        {
            "category":"Sports & Exercise",
            "subcategory":"Winter Sports",
            "type":"Entertainment"
        },
        {
            "category":"Sports & Exercise",
            "subcategory":"Ski Slope",
            "type":"Entertainment"
        }
    ],
    "sg:phone":"+44 23 8077 3925",
    "sg:postcode":"SO15 0HX",
    "sg:province":"Hampshire",
    "sg:tags":[
        "equipment",
        "skiing"
    ],
    "wof:name":"Snow Togs",
    "wof:placetype":"venue"
},
  "geometry": {"coordinates":[-1.4470649958,50.9139099121],"type":"Point"}
}