{
  "type": "Feature",
  "properties": {
    "addr:full":"10 Oxford Court, Bishopsgate Manchester Greater Manchester M2 3WQ",
    "addr:housenumber":"10",
    "addr:postcode":"m2 3wq",
    "addr:street":"Oxford Court",
    "iso:country":"GB",
    "sg:address":"10 Oxford Court, Bishopsgate",
    "sg:city":"Manchester",
    "sg:classifiers":[
        {
            "category":"Professional",
            "subcategory":"Engineering",
            "type":"Services"
        },
        {
            "category":"Building & Trades",
            "subcategory":"Construction",
            "type":"Services"
        }
    ],
    "sg:phone":"+44 161 236 2394",
    "sg:postcode":"M2 3WQ",
    "sg:province":"Greater Manchester",
    "sg:tags":[
        "consultant",
        "builder",
        "structural"
    ],
    "wof:name":"Curtins Walker Building Services Ltd.",
    "wof:placetype":"venue"
},
  "geometry": {"coordinates":[-2.24317,53.476742],"type":"Point"}
}