{
  "type": "Feature",
  "properties": {
    "iso:country":"GB",
    "sg:address":"40 East Street",
    "sg:city":"Faversham",
    "sg:classifiers":[
        {
            "category":"Fast Food",
            "type":"Food & Drink"
        }
    ],
    "sg:phone":"+44 1795 533808",
    "sg:postcode":"ME13 8AU",
    "sg:province":"Kent",
    "sg:tags":[
        "away",
        "take"
    ],
    "wof:name":"Mayflowers",
    "wof:placetype":"venue"
},
  "geometry": {"coordinates":[0.896108,51.314438],"type":"Point"}
}