{
  "type": "Feature",
  "properties": {
    "iso:country":"GB",
    "sg:address":"30 Fenton Avenue, Blackfordby",
    "sg:city":"Swadlincote",
    "sg:classifiers":[
        {
            "category":"Freight",
            "type":"Transportation"
        }
    ],
    "sg:phone":"+44 1283 219470",
    "sg:postcode":"DE11 8AR",
    "sg:province":"Derbyshire",
    "sg:tags":[
        "haulage",
        "transport",
        "road"
    ],
    "wof:name":"Anthony Robert Halstead",
    "wof:placetype":"venue"
},
  "geometry": {"coordinates":[-1.5170639753,52.7596664429],"type":"Point"}
}