{
  "type": "Feature",
  "properties": {
    "addr:full":"47 Mill Street Cannock Staffordshire WS11 3DR",
    "addr:housenumber":"47",
    "addr:postcode":"ws11 3dr",
    "addr:street":"Mill Street",
    "iso:country":"GB",
    "sg:address":"47 Mill Street",
    "sg:city":"Cannock",
    "sg:classifiers":[
        {
            "category":"Restaurant",
            "type":"Food & Drink"
        }
    ],
    "sg:phone":"+44 1543 573205",
    "sg:postcode":"WS11 3DR",
    "sg:province":"Staffordshire",
    "sg:tags":[
        "indian"
    ],
    "wof:name":"Shabab Balti Restaurant",
    "wof:placetype":"venue"
},
  "geometry": {"coordinates":[-2.0265,52.688499],"type":"Point"}
}