{
  "type": "Feature",
  "properties": {
    "addr:full":"The Business Centre, 2 Holly Court, High St Billericay Essex CM12 9AP",
    "addr:housenumber":"2",
    "addr:postcode":"cm12 9ap",
    "addr:street":"Holly Court High St",
    "iso:country":"GB",
    "sg:address":"The Business Centre, 2 Holly Court, High St",
    "sg:city":"Billericay",
    "sg:classifiers":[
        {
            "category":"Freight",
            "type":"Transportation"
        }
    ],
    "sg:phone":"+44 1277 631800",
    "sg:postcode":"CM12 9AP",
    "sg:province":"Essex",
    "sg:tags":[
        "forwarders"
    ],
    "wof:name":"Regency International",
    "wof:placetype":"venue"
},
  "geometry": {"coordinates":[0.4168550074,51.62474823],"type":"Point"}
}