{
  "type": "Feature",
  "properties": {
    "iso:country":"GB",
    "sg:address":"Ten George Street",
    "sg:city":"Edinburgh",
    "sg:classifiers":[
        {
            "category":"Professional",
            "subcategory":"Accounting & Tax Preparation",
            "type":"Services"
        }
    ],
    "sg:phone":"+44 131 777 2000",
    "sg:postcode":"EH2 2DZ",
    "sg:province":"City of Edinburgh",
    "sg:tags":[
        "accountant",
        "activity"
    ],
    "sg:website":"http://www.ey.com",
    "wof:name":"Ernst & Young Ltd",
    "wof:placetype":"venue"
},
  "geometry": {"coordinates":[-3.19873,55.95335],"type":"Point"}
}