{
  "type": "Feature",
  "properties": {
    "addr:full":"41 Townhead Street Cumnock East Ayrshire KA18 1LF",
    "addr:housenumber":"41",
    "addr:postcode":"ka18 1lf",
    "addr:street":"Townhead Street",
    "iso:country":"GB",
    "sg:address":"41 Townhead Street",
    "sg:city":"Cumnock",
    "sg:classifiers":[
        {
            "category":"Health Services",
            "subcategory":"Optometrist",
            "type":"Services"
        },
        {
            "category":"Shopping",
            "subcategory":"Optician",
            "type":"Retail Goods"
        }
    ],
    "sg:phone":"+44 1290 421421",
    "sg:postcode":"KA18 1LF",
    "sg:province":"East Ayrshire",
    "sg:tags":[
        "ophthalmic"
    ],
    "wof:name":"J R Shaw & Sons",
    "wof:placetype":"venue"
},
  "geometry": {"coordinates":[-4.2625322342,55.4545173645],"type":"Point"}
}