{
  "type": "Feature",
  "properties": {
    "iso:country":"GB",
    "sg:address":"39 High St",
    "sg:city":"Lincoln",
    "sg:classifiers":[
        {
            "category":"Health Services",
            "subcategory":"Doctor",
            "type":"Services"
        }
    ],
    "sg:phone":"+44 1526 860103",
    "sg:postcode":"LN4 4AU",
    "sg:province":"Lincolnshire",
    "sg:tags":[
        "practitioners"
    ],
    "wof:name":"Leeper, K",
    "wof:placetype":"venue"
},
  "geometry": {"coordinates":[-0.276858,53.078407],"type":"Point"}
}