{
  "type": "Feature",
  "properties": {
    "addr:full":"Manor Farm, New Rd Fordingbridge Dorset SP6 3NN",
    "addr:postcode":"sp6 3nn",
    "addr:street":"Manor;New Rd",
    "iso:country":"GB",
    "sg:address":"Manor Farm, New Rd",
    "sg:city":"Fordingbridge",
    "sg:classifiers":[
        {
            "category":"Home & Garden",
            "subcategory":"Hardware",
            "type":"Retail Goods"
        }
    ],
    "sg:phone":"+44 1725 518571",
    "sg:postcode":"SP6 3NN",
    "sg:province":"Dorset",
    "sg:tags":[
        "equipment",
        "heating"
    ],
    "wof:name":"Infrasol Ltd",
    "wof:placetype":"venue"
},
  "geometry": {"coordinates":[-1.791652,50.926819],"type":"Point"}
}