{
  "type": "Feature",
  "properties": {
    "iso:country":"GB",
    "sg:address":"27 Walkley Bank Road",
    "sg:city":"Sheffield",
    "sg:classifiers":[
        {
            "category":"Sports & Exercise",
            "subcategory":"Gym",
            "type":"Entertainment"
        }
    ],
    "sg:postcode":"S6 5AJ",
    "sg:province":"South Yorkshire",
    "sg:tags":[
        "fitness",
        "health",
        "centre"
    ],
    "wof:name":"Walkley Gym",
    "wof:placetype":"venue"
},
  "geometry": {"coordinates":[-1.5007,53.395874],"type":"Point"}
}