{
  "type": "Feature",
  "properties": {
    "addr:full":"Inshop Centre, Chelmsley Wood Birmingham West Midlands B37 5TL",
    "addr:postcode":"b37 5tl",
    "addr:street":"Chelmsley Wood",
    "iso:country":"GB",
    "sg:address":"Inshop Centre, Chelmsley Wood",
    "sg:city":"Birmingham",
    "sg:classifiers":[
        {
            "category":"Shopping",
            "subcategory":"Optician",
            "type":"Retail Goods"
        }
    ],
    "sg:postcode":"B37 5TL",
    "sg:province":"West Midlands",
    "wof:name":"Looking After Eyes",
    "wof:placetype":"venue"
},
  "geometry": {"coordinates":[-1.73983,52.479511],"type":"Point"}
}