{
  "type": "Feature",
  "properties": {
    "iso:country":"GB",
    "sg:address":"Grove Cottage, Port Hill",
    "sg:city":"Hertford",
    "sg:classifiers":[
        {
            "category":"Education",
            "subcategory":"Music School",
            "type":"Public Place"
        }
    ],
    "sg:postcode":"SG14 3BH",
    "sg:province":"Hertfordshire",
    "sg:tags":[
        "teacher"
    ],
    "wof:name":"H T Chaplin",
    "wof:placetype":"venue"
},
  "geometry": {"coordinates":[-0.0795169994,51.80809021],"type":"Point"}
}