{
  "type": "Feature",
  "properties": {
    "iso:country":"GB",
    "sg:address":"Boone Street, Lewisham",
    "sg:city":"London",
    "sg:classifiers":[
        {
            "category":"Shopping",
            "type":"Retail Goods"
        }
    ],
    "sg:phone":"+44 20 8852 0143",
    "sg:postcode":"SE13 5SA",
    "sg:province":"Greater London",
    "sg:tags":[
        "med",
        "scientific",
        "apparatus"
    ],
    "wof:name":"Lowne Instruments Ltd.",
    "wof:placetype":"venue"
},
  "geometry": {"coordinates":[0.00297,51.45977],"type":"Point"}
}