{
  "type": "Feature",
  "properties": {
    "addr:full":"54-56 Lant Street London Greater London SE1 1QP",
    "addr:housenumber":"54-56",
    "addr:postcode":"se1 1qp",
    "addr:street":"Lant Street",
    "iso:country":"GB",
    "sg:address":"54-56 Lant Street",
    "sg:city":"London",
    "sg:classifiers":[
        {
            "category":"Professional",
            "subcategory":"Art Services",
            "type":"Services"
        }
    ],
    "sg:phone":"+44 20 7357 6212",
    "sg:postcode":"SE1 1QP",
    "sg:province":"Greater London",
    "sg:tags":[
        "graphic",
        "designer"
    ],
    "wof:name":"Fibre",
    "wof:placetype":"venue"
},
  "geometry": {"coordinates":[-0.0959329978,51.501083374],"type":"Point"}
}