{
  "type": "Feature",
  "properties": {
    "addr:full":"115a High Street Godalming Surrey GU7 1AQ",
    "addr:housenumber":"115a",
    "addr:postcode":"gu7 1aq",
    "addr:street":"High Street",
    "iso:country":"GB",
    "sg:address":"115a High Street",
    "sg:city":"Godalming",
    "sg:classifiers":[
        {
            "category":"Home & Garden",
            "subcategory":"Household Appliances",
            "type":"Retail Goods"
        },
        {
            "category":"Retail",
            "subcategory":"Repair Shop",
            "type":"Services"
        }
    ],
    "sg:postcode":"GU7 1AQ",
    "sg:province":"Surrey",
    "sg:tags":[
        "electrical",
        "domestic"
    ],
    "wof:name":"Magimix U K Ltd.",
    "wof:placetype":"venue"
},
  "geometry": {"coordinates":[-0.6157810092,51.1852035522],"type":"Point"}
}