{
  "type": "Feature",
  "properties": {
    "addr:full":"88 A Wyle Cop Shrewsbury Shropshire SY1 1UT",
    "addr:housenumber":"88",
    "addr:postcode":"sy1 1ut",
    "addr:street":"A Wyle Cop",
    "iso:country":"GB",
    "sg:address":"88 A Wyle Cop",
    "sg:city":"Shrewsbury",
    "sg:classifiers":[
        {
            "category":"Banks & Credit Unions",
            "subcategory":"Bureau De Change",
            "type":"Services"
        }
    ],
    "sg:phone":"+44 1743 231040",
    "sg:postcode":"SY1 1UT",
    "sg:province":"Shropshire",
    "sg:tags":[
        "town",
        "consultant",
        "planning"
    ],
    "wof:name":"les Stephan Partnership",
    "wof:placetype":"venue"
},
  "geometry": {"coordinates":[-2.7498390675,52.706161499],"type":"Point"}
}