{
  "type": "Feature",
  "properties": {
    "addr:full":"113 Reepham Road Norwich Norfolk NR6 5AB",
    "addr:housenumber":"113",
    "addr:postcode":"nr6 5ab",
    "addr:street":"Reepham Road Norwich Norfolk",
    "iso:country":"GB",
    "sg:address":"113 Reepham Road",
    "sg:city":"Norwich",
    "sg:classifiers":[
        {
            "category":"Home & Garden",
            "subcategory":"Furniture",
            "type":"Retail Goods"
        }
    ],
    "sg:phone":"+44 1603 788030",
    "sg:postcode":"NR6 5AB",
    "sg:province":"Norfolk",
    "wof:name":"Pinetree Products (Furniture) Ltd.",
    "wof:placetype":"venue"
},
  "geometry": {"coordinates":[1.269135,52.661041],"type":"Point"}
}