{
  "type": "Feature",
  "properties": {
    "iso:country":"GB",
    "sg:address":"Norhouse, 4 Park 2000 Millenium Way",
    "sg:city":"Newton Aycliffe",
    "sg:classifiers":[
        {
            "category":"Manufacturing",
            "subcategory":"Tools & Machinery",
            "type":"Manufacturing & Wholesale Goods"
        },
        {
            "category":"Manufacturing",
            "subcategory":"Wood Products",
            "type":"Manufacturing & Wholesale Goods"
        }
    ],
    "sg:phone":"+44 1325 300133",
    "sg:postcode":"DL5 6AR",
    "sg:province":"Durham",
    "sg:tags":[
        "packaging",
        "bearing",
        "crate",
        "pallets",
        "stockist"
    ],
    "wof:name":"Northern Packaging Distributors Ltd.",
    "wof:placetype":"venue"
},
  "geometry": {"coordinates":[-1.563024044,54.5962715149],"type":"Point"}
}