{
  "type": "Feature",
  "properties": {
    "addr:full":"44 Priory Road Peterborough Cambridgeshire PE3 9ED",
    "addr:housenumber":"44",
    "addr:postcode":"pe3 9ed",
    "addr:street":"Priory Road",
    "iso:country":"GB",
    "sg:address":"44 Priory Road",
    "sg:city":"Peterborough",
    "sg:classifiers":[
        {
            "category":"Food & Beverages",
            "subcategory":"Groceries & Convenience Stores",
            "type":"Retail Goods"
        }
    ],
    "sg:phone":"+44 1733 565131",
    "sg:postcode":"PE3 9ED",
    "sg:province":"Cambridgeshire",
    "wof:name":"Priory Stores",
    "wof:placetype":"venue"
},
  "geometry": {"coordinates":[-0.259295,52.58086],"type":"Point"}
}