{
  "type": "Feature",
  "properties": {
    "addr:full":"Wakefield Road, Lepton Huddersfield South Yorkshire HD8 0LU",
    "addr:postcode":"hd8 0lu",
    "addr:street":"Wakefield Road",
    "iso:country":"GB",
    "sg:address":"Wakefield Road, Lepton",
    "sg:city":"Huddersfield",
    "sg:classifiers":[
        {
            "category":"Autos & Motor Vehicles",
            "subcategory":"Fuel & Gas Station",
            "type":"Retail Goods"
        }
    ],
    "sg:phone":"+44 1484 604309",
    "sg:postcode":"HD8 0LU",
    "sg:province":"South Yorkshire",
    "sg:tags":[
        "petrol",
        "filling"
    ],
    "wof:name":"ACTION STATIONS LTD",
    "wof:placetype":"venue"
},
  "geometry": {"coordinates":[-1.690664,53.632675],"type":"Point"}
}