{
  "type": "Feature",
  "properties": {
    "addr:full":"39 Pyes Meadow, Elmswell Bury St Edmunds Suffolk IP30 9UF",
    "addr:housenumber":"39",
    "addr:postcode":"ip30 9uf",
    "addr:street":"Pyes Meadow Elmswell",
    "iso:country":"GB",
    "sg:address":"39 Pyes Meadow, Elmswell",
    "sg:city":"Bury St Edmunds",
    "sg:classifiers":[
        {
            "category":"Professional",
            "subcategory":"Credit Reporting & Collection",
            "type":"Services"
        }
    ],
    "sg:postcode":"IP30 9UF",
    "sg:province":"Suffolk",
    "sg:tags":[
        "collecting",
        "agency"
    ],
    "wof:name":"Admin & Debtor Management",
    "wof:placetype":"venue"
},
  "geometry": {"coordinates":[0.9157969952,52.2378463745],"type":"Point"}
}