{
  "type": "Feature",
  "properties": {
    "addr:full":"112 Billesley Lane Birmingham West Midlands B13 9RD",
    "addr:housenumber":"112",
    "addr:postcode":"b13 9rd",
    "addr:street":"Billesley Lane",
    "iso:country":"GB",
    "sg:address":"112 Billesley Lane",
    "sg:city":"Birmingham",
    "sg:classifiers":[
        {
            "category":"Farming",
            "subcategory":"Fish & Marine Products",
            "type":"Manufacturing & Wholesale Goods"
        }
    ],
    "sg:postcode":"B13 9RD",
    "sg:province":"West Midlands",
    "sg:tags":[
        "fishmonger"
    ],
    "wof:name":"G Kent",
    "wof:placetype":"venue"
},
  "geometry": {"coordinates":[-1.8803889751,52.4369163513],"type":"Point"}
}