{
  "type": "Feature",
  "properties": {
    "addr:full":"45 Victoria Street Aberdeen Aberdeen City AB10 1UX",
    "addr:housenumber":"45",
    "addr:postcode":"ab10 1ux",
    "addr:street":"Victoria Street",
    "iso:country":"GB",
    "sg:address":"45 Victoria Street",
    "sg:city":"Aberdeen",
    "sg:classifiers":[
        {
            "category":"Community Center",
            "subcategory":"Youth",
            "type":"Public Place"
        },
        {
            "category":"Organizations",
            "subcategory":"Community Association",
            "type":"Services"
        }
    ],
    "sg:phone":"+44 1224 638685",
    "sg:postcode":"AB10 1UX",
    "sg:province":"Aberdeen City",
    "sg:tags":[
        "associations",
        "centre",
        "housing",
        "co-operatives",
        "trust",
        "organisation",
        "societies"
    ],
    "wof:name":"THE GUIDE ASSOCIATION",
    "wof:placetype":"venue"
},
  "geometry": {"coordinates":[-2.114461,57.145],"type":"Point"}
}