{
  "type": "Feature",
  "properties": {
    "addr:full":"34 North Station Road Colchester Essex CO1 1RB",
    "addr:housenumber":"34",
    "addr:postcode":"co1 1rb",
    "addr:street":"North Station Road Colchester",
    "iso:country":"GB",
    "sg:address":"34 North Station Road",
    "sg:city":"Colchester",
    "sg:classifiers":[
        {
            "category":"Fast Food",
            "type":"Food & Drink"
        }
    ],
    "sg:phone":"+44 1206 563298",
    "sg:postcode":"CO1 1RB",
    "sg:province":"Essex",
    "sg:tags":[
        "away",
        "take"
    ],
    "wof:name":"The Golden Horn",
    "wof:placetype":"venue"
},
  "geometry": {"coordinates":[0.8955630064,51.8953552246],"type":"Point"}
}