{
  "type": "Feature",
  "properties": {
    "addr:full":"3 & 3a Lwr High St Merthyr Tydfil Merthyr Tydfil CF47 8EB",
    "addr:housenumber":"3 & 3a lwr",
    "addr:postcode":"cf47 8eb",
    "addr:street":"High St",
    "iso:country":"GB",
    "sg:address":"3 & 3a Lwr High St",
    "sg:city":"Merthyr Tydfil",
    "sg:classifiers":[
        {
            "category":"Autos & Motor Vehicles",
            "subcategory":"Fuel & Gas Station",
            "type":"Retail Goods"
        }
    ],
    "sg:postcode":"CF47 8EB",
    "sg:province":"Merthyr Tydfil",
    "sg:tags":[
        "petrol",
        "filling"
    ],
    "wof:name":"Bona,Tom,",
    "wof:placetype":"venue"
},
  "geometry": {"coordinates":[-3.377181,51.742409],"type":"Point"}
}