{
  "type": "Feature",
  "properties": {
    "addr:full":"Bridge Farm, Gloucester Road, Staverton Cheltenham Gloucestershire GL51 0TF",
    "addr:postcode":"gl51 0tf",
    "addr:street":"Bridge;Gloucester Road",
    "iso:country":"GB",
    "sg:address":"Bridge Farm, Gloucester Road, Staverton",
    "sg:city":"Cheltenham",
    "sg:classifiers":[
        {
            "category":"Farming",
            "subcategory":"Livestock Farm",
            "type":"Manufacturing & Wholesale Goods"
        }
    ],
    "sg:phone":"+44 1452 712230",
    "sg:postcode":"GL51 0TF",
    "sg:province":"Gloucestershire",
    "sg:tags":[
        "others"
    ],
    "wof:name":"Ken Pink",
    "wof:placetype":"venue"
},
  "geometry": {"coordinates":[-2.1583740711,51.9068565369],"type":"Point"}
}