{
  "type": "Feature",
  "properties": {
    "iso:country":"GB",
    "sg:address":"25 Claydon Drive",
    "sg:city":"Croydon",
    "sg:classifiers":[
        {
            "category":"Professional",
            "subcategory":"Management & Consulting",
            "type":"Services"
        }
    ],
    "sg:phone":"+44 20 8686 6246",
    "sg:postcode":"CR0 4QX",
    "sg:province":"Surrey",
    "sg:tags":[
        "consultant",
        "business"
    ],
    "wof:name":"Causedance Ltd.",
    "wof:placetype":"venue"
},
  "geometry": {"coordinates":[-0.128765,51.36578],"type":"Point"}
}