{
  "type": "Feature",
  "properties": {
    "iso:country":"GB",
    "sg:address":"61 Broadmead Avenue",
    "sg:city":"Northampton",
    "sg:classifiers":[
        {
            "category":"Bars & Pubs",
            "type":"Food & Drink"
        }
    ],
    "sg:phone":"+44 1604 407480",
    "sg:postcode":"NN3 2QX",
    "sg:province":"Northamptonshire",
    "sg:tags":[
        "pubs",
        "inn"
    ],
    "wof:name":"The Broadmead",
    "wof:placetype":"venue"
},
  "geometry": {"coordinates":[-0.865852,52.258434],"type":"Point"}
}