{
  "type": "Feature",
  "properties": {
    "addr:full":"608 Wakefield Road Huddersfield West Yorkshire HD5 8PZ",
    "addr:housenumber":"608",
    "addr:postcode":"hd5 8pz",
    "addr:street":"Wakefield Road",
    "iso:country":"GB",
    "sg:address":"608 Wakefield Road",
    "sg:city":"Huddersfield",
    "sg:classifiers":[
        {
            "category":"Taxi",
            "type":"Transportation"
        },
        {
            "category":"Military Area",
            "subcategory":"Air Force Base",
            "type":"Public Place"
        }
    ],
    "sg:phone":"+44 1484 427572",
    "sg:postcode":"HD5 8PZ",
    "sg:province":"West Yorkshire",
    "sg:tags":[
        "hire",
        "private"
    ],
    "wof:name":"Waterloo Taxis",
    "wof:placetype":"venue"
},
  "geometry": {"coordinates":[-1.7397309542,53.6446838379],"type":"Point"}
}