{
  "type": "Feature",
  "properties": {
    "addr:full":"23-25 High St Epsom Surrey KT17 1SB",
    "addr:housenumber":"23-25",
    "addr:postcode":"kt17 1sb",
    "addr:street":"High St",
    "iso:country":"GB",
    "sg:address":"23-25 High St",
    "sg:city":"Epsom",
    "sg:classifiers":[
        {
            "category":"Personal",
            "type":"Services"
        }
    ],
    "sg:phone":"+44 20 8394 1233",
    "sg:postcode":"KT17 1SB",
    "sg:province":"Surrey",
    "sg:tags":[
        "wedding"
    ],
    "wof:name":"Once Upon A Time",
    "wof:placetype":"venue"
},
  "geometry": {"coordinates":[-0.248973,51.349346],"type":"Point"}
}