{
  "type": "Feature",
  "properties": {
    "addr:full":"6 The Maples,chelsfield Ave, Lake Sandown Isle of Wight PO36 9NP",
    "addr:housenumber":"6",
    "addr:postcode":"po36 9np",
    "addr:street":"The Maples Chelsfield Ave",
    "iso:country":"GB",
    "sg:address":"6 The Maples,chelsfield Ave, Lake",
    "sg:city":"Sandown",
    "sg:classifiers":[
        {
            "category":"Professional",
            "subcategory":"Business Services",
            "type":"Services"
        }
    ],
    "sg:postcode":"PO36 9NP",
    "sg:province":"Isle of Wight",
    "sg:tags":[
        "import",
        "export",
        "agent"
    ],
    "wof:name":"H Toc Association",
    "wof:placetype":"venue"
},
  "geometry": {"coordinates":[-1.1708389521,50.6422424316],"type":"Point"}
}