{
  "type": "Feature",
  "properties": {
    "addr:full":"28 Greville Street London Greater London EC1N 8SU",
    "addr:housenumber":"28",
    "addr:postcode":"ec1n 8su",
    "addr:street":"Greville Street",
    "iso:country":"GB",
    "sg:address":"28 Greville Street",
    "sg:city":"London",
    "sg:classifiers":[
        {
            "category":"Manufacturing",
            "subcategory":"Jewelry",
            "type":"Manufacturing & Wholesale Goods"
        }
    ],
    "sg:phone":"+44 20 7242 6759",
    "sg:postcode":"EC1N 8SU",
    "sg:province":"Greater London",
    "sg:tags":[
        "repair",
        "jewellery"
    ],
    "wof:name":"Trevor Tyler Ltd.",
    "wof:placetype":"venue"
},
  "geometry": {"coordinates":[-0.106455,51.519691],"type":"Point"}
}