{
  "type": "Feature",
  "properties": {
    "iso:country":"GB",
    "sg:address":"23 Canonbury Lane",
    "sg:city":"London",
    "sg:classifiers":[
        {
            "category":"Deli",
            "type":"Food & Drink"
        }
    ],
    "sg:phone":"+44 20 7354 4335",
    "sg:postcode":"N1 2AS",
    "sg:province":"Greater London",
    "sg:tags":[
        "delicatessen"
    ],
    "wof:name":"Monte's Delicatessen",
    "wof:placetype":"venue"
},
  "geometry": {"coordinates":[-0.1026910022,51.5431175232],"type":"Point"}
}