{
  "type": "Feature",
  "properties": {
    "iso:country":"GB",
    "sg:address":"Station Rd",
    "sg:city":"Marlow",
    "sg:classifiers":[
        {
            "category":"Bars & Pubs",
            "type":"Food & Drink"
        }
    ],
    "sg:phone":"+44 1628 482022",
    "sg:postcode":"SL7 1NW",
    "sg:province":"Berkshire",
    "sg:tags":[
        "pubs",
        "inn"
    ],
    "wof:name":"Marlow Donkey",
    "wof:placetype":"venue"
},
  "geometry": {"coordinates":[-0.771484,51.570595],"type":"Point"}
}