{
  "type": "Feature",
  "properties": {
    "addr:full":"103 Dunterlie Avenue, Knightswood Glasgow Glasgow City G13 3EX",
    "addr:housenumber":"103",
    "addr:postcode":"g13 3ex",
    "addr:street":"Dunterlie Avenue",
    "iso:country":"GB",
    "sg:address":"103 Dunterlie Avenue, Knightswood",
    "sg:city":"Glasgow",
    "sg:classifiers":[
        {
            "category":"Organizations",
            "subcategory":"Non-profit Organization",
            "type":"Services"
        }
    ],
    "sg:phone":"+44 141 950 1105",
    "sg:postcode":"G13 3EX",
    "sg:province":"Glasgow City",
    "sg:tags":[
        "alarm",
        "system"
    ],
    "wof:name":"D.M.S Security",
    "wof:placetype":"venue"
},
  "geometry": {"coordinates":[-4.3612289429,55.8882331848],"type":"Point"}
}