{
  "type": "Feature",
  "properties": {
    "iso:country":"GB",
    "sg:address":"175 Fleet Street",
    "sg:city":"London",
    "sg:classifiers":[
        {
            "category":"Fast Food",
            "type":"Food & Drink"
        }
    ],
    "sg:phone":"+44 20 7583 6160",
    "sg:postcode":"EC4A 2EA",
    "sg:province":"Greater London",
    "sg:tags":[
        "away",
        "take"
    ],
    "wof:name":"Di Lieto Sandwich Bar",
    "wof:placetype":"venue"
},
  "geometry": {"coordinates":[-0.1089499965,51.5142021179],"type":"Point"}
}