{
  "type": "Feature",
  "properties": {
    "addr:full":"9 Wheelbarrow Park, Pattenden Lane, Marden Tonbridge Kent TN12 9QD",
    "addr:housenumber":"9",
    "addr:postcode":"tn12 9qd",
    "addr:street":"Wheelbarrow Park Pattenden Lane",
    "iso:country":"GB",
    "sg:address":"9 Wheelbarrow Park, Pattenden Lane, Marden",
    "sg:city":"Tonbridge",
    "sg:classifiers":[
        {
            "category":"Autos & Motor Vehicles",
            "subcategory":"Auto Supplies",
            "type":"Retail Goods"
        }
    ],
    "sg:phone":"+44 1622 833005",
    "sg:postcode":"TN12 9QD",
    "sg:province":"Kent",
    "sg:tags":[
        "car",
        "component"
    ],
    "wof:name":"Automotive Distributors Ltd.",
    "wof:placetype":"venue"
},
  "geometry": {"coordinates":[0.489726007,51.176322937],"type":"Point"}
}