{
  "type": "Feature",
  "properties": {
    "iso:country":"GB",
    "sg:address":"26 Church Road, St Mary Church",
    "sg:city":"Torquay",
    "sg:classifiers":[
        {
            "category":"Home & Garden",
            "subcategory":"Furniture",
            "type":"Retail Goods"
        }
    ],
    "sg:postcode":"TQ1 4QY",
    "sg:province":"Devon",
    "wof:name":"Peertex Textile Merchant",
    "wof:placetype":"venue"
},
  "geometry": {"coordinates":[-3.5268380642,50.4836387634],"type":"Point"}
}