{
  "type": "Feature",
  "properties": {
    "addr:full":"38a Elmers Green Skelmersdale Lancashire WN8 6SB",
    "addr:housenumber":"38a",
    "addr:postcode":"wn8 6sb",
    "addr:street":"Elmers Green",
    "iso:country":"GB",
    "sg:address":"38a Elmers Green",
    "sg:city":"Skelmersdale",
    "sg:classifiers":[
        {
            "category":"Real Estate",
            "subcategory":"Architect",
            "type":"Services"
        }
    ],
    "sg:postcode":"WN8 6SB",
    "sg:province":"Lancashire",
    "wof:name":"R.J.B. Aerospace Engineering Ltd",
    "wof:placetype":"venue"
},
  "geometry": {"coordinates":[-2.7566568851,53.5536613464],"type":"Point"}
}