{
  "type": "Feature",
  "properties": {
    "iso:country":"GB",
    "sg:address":"12 Brinsworth Hall Cres, Brinsworth",
    "sg:city":"Rotherham",
    "sg:classifiers":[
        {
            "category":"Wholesale",
            "subcategory":"Office Equipment",
            "type":"Manufacturing & Wholesale Goods"
        }
    ],
    "sg:postcode":"S60 5EQ",
    "sg:province":"South Yorkshire",
    "sg:tags":[
        "register",
        "cash",
        "accessory"
    ],
    "wof:name":"Till Services",
    "wof:placetype":"venue"
},
  "geometry": {"coordinates":[-1.375545,53.402409],"type":"Point"}
}