{
  "type": "Feature",
  "properties": {
    "iso:country":"GB",
    "sg:address":"Killiow Kea",
    "sg:city":"Truro",
    "sg:classifiers":[
        {
            "category":"Sports & Exercise",
            "subcategory":"Golf",
            "type":"Entertainment"
        }
    ],
    "sg:phone":"+44 1872 261055",
    "sg:postcode":"TR3 6AG",
    "sg:province":"Cornwall",
    "sg:tags":[
        "club",
        "course"
    ],
    "wof:name":"Killow Estate Office",
    "wof:placetype":"venue"
},
  "geometry": {"coordinates":[-5.0838599205,50.2364807129],"type":"Point"}
}