{
  "type": "Feature",
  "properties": {
    "addr:full":"57 Western Road Leigh-on-sea Essex SS9 2PT",
    "addr:housenumber":"57",
    "addr:postcode":"ss9 2pt",
    "addr:street":"Western Road",
    "iso:country":"GB",
    "sg:address":"57 Western Road",
    "sg:city":"Leigh-on-sea",
    "sg:classifiers":[
        {
            "category":"Health Services",
            "subcategory":"Health Practitioner",
            "type":"Services"
        }
    ],
    "sg:postcode":"SS9 2PT",
    "sg:province":"Essex",
    "sg:tags":[
        "psychologist"
    ],
    "wof:name":"Psychological & Therapeutic Consultancy",
    "wof:placetype":"venue"
},
  "geometry": {"coordinates":[0.6403800249,51.545917511],"type":"Point"}
}