{
  "type": "Feature",
  "properties": {
    "addr:full":"Preston Down Road, Preston Paignton Devon TQ3 1RN",
    "addr:postcode":"tq3 1rn",
    "addr:street":"Down Road",
    "iso:country":"GB",
    "sg:address":"Preston Down Road, Preston",
    "sg:city":"Paignton",
    "sg:classifiers":[
        {
            "category":"Social Services",
            "subcategory":"Retirement Home",
            "type":"Services"
        }
    ],
    "sg:phone":"+44 1803 663445",
    "sg:postcode":"TQ3 1RN",
    "sg:province":"Devon",
    "sg:tags":[
        "residential",
        "care"
    ],
    "wof:name":"Burrow Down Residential Care Home",
    "wof:placetype":"venue"
},
  "geometry": {"coordinates":[-3.577699,50.445225],"type":"Point"}
}