{
  "type": "Feature",
  "properties": {
    "addr:full":"6 Spice Ct, Ivory Sq London Greater London SW11 3UE",
    "addr:housenumber":"6",
    "addr:postcode":"sw11 3ue",
    "addr:street":"Spice Ct Ivory Sq",
    "iso:country":"GB",
    "sg:address":"6 Spice Ct, Ivory Sq",
    "sg:city":"London",
    "sg:classifiers":[
        {
            "category":"Manufacturing",
            "subcategory":"Apparel",
            "type":"Manufacturing & Wholesale Goods"
        }
    ],
    "sg:postcode":"SW11 3UE",
    "sg:province":"Greater London",
    "sg:tags":[
        "garment",
        "designer"
    ],
    "wof:name":"Workers for Freedom Ltd",
    "wof:placetype":"venue"
},
  "geometry": {"coordinates":[-0.18168,51.466129],"type":"Point"}
}