{
  "type": "Feature",
  "properties": {
    "iso:country":"GB",
    "sg:address":"Broadcut Farm, Denby Dale Road, Calder Gro",
    "sg:city":"Wakefield",
    "sg:classifiers":[
        {
            "category":"Farming",
            "subcategory":"Livestock Farm",
            "type":"Manufacturing & Wholesale Goods"
        }
    ],
    "sg:phone":"+44 1924 276670",
    "sg:postcode":"WF4 3AB",
    "sg:province":"West Yorkshire",
    "sg:tags":[
        "others"
    ],
    "wof:name":"J S & A M Garthwaite",
    "wof:placetype":"venue"
},
  "geometry": {"coordinates":[-1.540292,53.647655],"type":"Point"}
}