{
  "type": "Feature",
  "properties": {
    "addr:full":"173 Grangeway Rushden Bedfordshire NN10 9JE",
    "addr:housenumber":"173;rushden",
    "addr:postcode":"nn10 9je",
    "addr:street":"Grangeway",
    "iso:country":"GB",
    "sg:address":"173 Grangeway",
    "sg:city":"Rushden",
    "sg:classifiers":[
        {
            "category":"Shopping",
            "subcategory":"News",
            "type":"Retail Goods"
        }
    ],
    "sg:phone":"+44 1933 314054",
    "sg:postcode":"NN10 9JE",
    "sg:province":"Bedfordshire",
    "sg:tags":[
        "newsagent"
    ],
    "wof:name":"Forbuoys Ltd.",
    "wof:placetype":"venue"
},
  "geometry": {"coordinates":[-0.609383,52.28252],"type":"Point"}
}