{
  "type": "Feature",
  "properties": {
    "addr:full":"301 Loddon Bridge Road, Woodley Reading Berkshire RG5 4BE",
    "addr:housenumber":"301",
    "addr:postcode":"rg5 4be",
    "addr:street":"Loddon Bridge Road",
    "iso:country":"GB",
    "sg:address":"301 Loddon Bridge Road, Woodley",
    "sg:city":"Reading",
    "sg:classifiers":[
        {
            "category":"Real Estate",
            "subcategory":"Real Estate Agent",
            "type":"Services"
        }
    ],
    "sg:phone":"+44 118 969 9800",
    "sg:postcode":"RG5 4BE",
    "sg:province":"Berkshire",
    "wof:name":"Stuarts Estate Agents",
    "wof:placetype":"venue"
},
  "geometry": {"coordinates":[-0.897799,51.453739],"type":"Point"}
}