{
  "type": "Feature",
  "properties": {
    "addr:full":"53 Gelligaled Rd, Ystrad Pentre Rhondda, Cynon, Taff CF41 7RQ",
    "addr:housenumber":"53",
    "addr:postcode":"cf41 7rq",
    "addr:street":"Gelligaled Rd;Pentre;Cynon Taff",
    "iso:country":"GB",
    "sg:address":"53 Gelligaled Rd, Ystrad",
    "sg:city":"Pentre",
    "sg:classifiers":[
        {
            "category":"Taxi",
            "type":"Transportation"
        }
    ],
    "sg:phone":"+44 1443 441122",
    "sg:postcode":"CF41 7RQ",
    "sg:province":"Rhondda, Cynon, Taff",
    "sg:tags":[
        "mini",
        "cab"
    ],
    "wof:name":"N & M Taxis",
    "wof:placetype":"venue"
},
  "geometry": {"coordinates":[-3.463805,51.644379],"type":"Point"}
}