{
  "type": "Feature",
  "properties": {
    "iso:country":"GB",
    "sg:address":"12 Abbey Close",
    "sg:city":"Deal",
    "sg:classifiers":[
        {
            "category":"Building & Trades",
            "subcategory":"Construction",
            "type":"Services"
        }
    ],
    "sg:phone":"+44 1304 361689",
    "sg:postcode":"CT14 9UL",
    "sg:province":"Kent",
    "sg:tags":[
        "decorator",
        "painter"
    ],
    "wof:name":"K L & S J Gosden",
    "wof:placetype":"venue"
},
  "geometry": {"coordinates":[1.383983,51.219154],"type":"Point"}
}