{
  "type": "Feature",
  "properties": {
    "addr:full":"Shirra Bakery, 14 Market Place Selkirk Scottish Borders TD7 4BT",
    "addr:housenumber":"14",
    "addr:postcode":"td7 4bt",
    "addr:street":"Market Place Selkirk",
    "iso:country":"GB",
    "sg:address":"Shirra Bakery, 14 Market Place",
    "sg:city":"Selkirk",
    "sg:classifiers":[
        {
            "category":"Home & Garden",
            "subcategory":"Kitchen Supply",
            "type":"Retail Goods"
        }
    ],
    "sg:postcode":"TD7 4BT",
    "sg:province":"Scottish Borders",
    "sg:tags":[
        "equipment",
        "bakery"
    ],
    "wof:name":"Shirra Gourmet Shortbread",
    "wof:placetype":"venue"
},
  "geometry": {"coordinates":[-2.841429,55.547329],"type":"Point"}
}