{
  "type": "Feature",
  "properties": {
    "addr:full":"Unit C Abbeygate Business Centre, Hitchin Road Luton Bedfordshire LU2 0ER",
    "addr:housenumber":"unit c;business",
    "addr:postcode":"lu2 0er",
    "addr:street":"Abbeygate;Hitchin Road",
    "iso:country":"GB",
    "sg:address":"Unit C Abbeygate Business Centre, Hitchin Road",
    "sg:city":"Luton",
    "sg:classifiers":[
        {
            "category":"Social Services",
            "type":"Services"
        },
        {
            "category":"Wholesale",
            "subcategory":"Drugs",
            "type":"Manufacturing & Wholesale Goods"
        }
    ],
    "sg:phone":"+44 1582 484785",
    "sg:postcode":"LU2 0ER",
    "sg:province":"Bedfordshire",
    "sg:tags":[
        "supplier",
        "pharmaceutical",
        "wholesaler",
        "disability"
    ],
    "wof:name":"Simorg Ltd",
    "wof:placetype":"venue"
},
  "geometry": {"coordinates":[-0.40943,51.883091],"type":"Point"}
}