{
  "type": "Feature",
  "properties": {
    "addr:full":"Stall 22 Ashton Market Hall, Bow Street Ashton-under-lyne Greater Manchester OL6 6BU",
    "addr:housenumber":"22",
    "addr:postcode":"ol6 6bu",
    "addr:street":"Stall;Bow Street",
    "iso:country":"GB",
    "sg:address":"Stall 22 Ashton Market Hall, Bow Street",
    "sg:city":"Ashton-under-lyne",
    "sg:classifiers":[
        {
            "category":"Professional",
            "subcategory":"Computer Services",
            "type":"Services"
        }
    ],
    "sg:phone":"+44 161 339 6505",
    "sg:postcode":"OL6 6BU",
    "sg:province":"Greater Manchester",
    "sg:tags":[
        "system",
        "software"
    ],
    "wof:name":"Total Games",
    "wof:placetype":"venue"
},
  "geometry": {"coordinates":[-2.088242054,53.489238739],"type":"Point"}
}