{
  "type": "Feature",
  "properties": {
    "iso:country":"GB",
    "sg:address":"63-64 The Mall",
    "sg:city":"Bexleyheath",
    "sg:classifiers":[
        {
            "category":"Shopping",
            "subcategory":"Clothing, Apparel, & Fashions",
            "type":"Retail Goods"
        }
    ],
    "sg:phone":"+44 20 8301 5622",
    "sg:postcode":"DA6 7JJ",
    "sg:province":"Kent",
    "sg:tags":[
        "shop"
    ],
    "wof:name":"River Island Clothing Co",
    "wof:placetype":"venue"
},
  "geometry": {"coordinates":[0.15153,51.450935],"type":"Point"}
}