{
  "type": "Feature",
  "properties": {
    "addr:full":"Low Wood, Mutton Hall Hill Heathfield East Sussex TN21 8NB",
    "addr:postcode":"tn21 8nb",
    "addr:street":"Hill",
    "iso:country":"GB",
    "sg:address":"Low Wood, Mutton Hall Hill",
    "sg:city":"Heathfield",
    "sg:classifiers":[
        {
            "category":"Manufacturing",
            "subcategory":"Metals",
            "type":"Manufacturing & Wholesale Goods"
        }
    ],
    "sg:phone":"+44 1435 863455",
    "sg:postcode":"TN21 8NB",
    "sg:province":"East Sussex",
    "sg:tags":[
        "steel",
        "fabricator",
        "erectors"
    ],
    "wof:name":"Johnson Engineering Services",
    "wof:placetype":"venue"
},
  "geometry": {"coordinates":[0.252349,50.971859],"type":"Point"}
}