{
  "type": "Feature",
  "properties": {
    "iso:country":"GB",
    "sg:address":"7 Rodney Street",
    "sg:city":"Liverpool",
    "sg:classifiers":[
        {
            "category":"Real Estate",
            "subcategory":"Real Estate Agent",
            "type":"Services"
        }
    ],
    "sg:phone":"+44 151 259 2686",
    "sg:postcode":"L1 9HZ",
    "sg:province":"Merseyside",
    "wof:name":"Drivegreen Ltd.",
    "wof:placetype":"venue"
},
  "geometry": {"coordinates":[-2.973289,53.40189],"type":"Point"}
}