{
  "type": "Feature",
  "properties": {
    "iso:country":"GB",
    "sg:address":"The Ridgeway",
    "sg:city":"London",
    "sg:classifiers":[
        {
            "category":"Place Of Worship",
            "type":"Public Place"
        }
    ],
    "sg:phone":"+44 20 8524 1410",
    "sg:postcode":"E4 6PU",
    "sg:province":"Greater London",
    "wof:name":"Ridgeway Evangelical Church",
    "wof:placetype":"venue"
},
  "geometry": {"coordinates":[-0.00832,51.626999],"type":"Point"}
}