{
  "type": "Feature",
  "properties": {
    "iso:country":"GB",
    "sg:address":"2 Milton Road",
    "sg:city":"Gravesend",
    "sg:classifiers":[
        {
            "category":"Shopping",
            "subcategory":"Pharmacy",
            "type":"Retail Goods"
        }
    ],
    "sg:phone":"+44 1474 323828",
    "sg:postcode":"DA12 2RE",
    "sg:province":"Kent",
    "sg:tags":[
        "pharmacist",
        "dispensing",
        "chemist"
    ],
    "wof:name":"Pender's Pharmacy",
    "wof:placetype":"venue"
},
  "geometry": {"coordinates":[0.371398,51.44202],"type":"Point"}
}