{
  "type": "Feature",
  "properties": {
    "addr:full":"133 Brockhurst Road Gosport Hampshire PO12 3AX",
    "addr:housenumber":"133",
    "addr:postcode":"po12 3ax",
    "addr:street":"Brockhurst Road",
    "iso:country":"GB",
    "sg:address":"133 Brockhurst Road",
    "sg:city":"Gosport",
    "sg:classifiers":[
        {
            "category":"Shopping",
            "subcategory":"Hobbies, Toys, & Games",
            "type":"Retail Goods"
        }
    ],
    "sg:postcode":"PO12 3AX",
    "sg:province":"Hampshire",
    "sg:tags":[
        "gunsmith"
    ],
    "wof:name":"H Cullum",
    "wof:placetype":"venue"
},
  "geometry": {"coordinates":[-1.1531490088,50.8078689575],"type":"Point"}
}