{
  "type": "Feature",
  "properties": {
    "iso:country":"GB",
    "sg:address":"14 Lakeland Drive, Frimley",
    "sg:city":"Callington",
    "sg:classifiers":[
        {
            "category":"Professional",
            "subcategory":"Management & Consulting",
            "type":"Services"
        }
    ],
    "sg:phone":"+44 1276 686556",
    "sg:postcode":"GU16 8LD",
    "sg:province":"Hampshire",
    "sg:tags":[
        "consultant",
        "geophysical",
        "geological"
    ],
    "wof:name":"Antoine A.H Wonders",
    "wof:placetype":"venue"
},
  "geometry": {"coordinates":[-0.732737,51.31741],"type":"Point"}
}