{
  "type": "Feature",
  "properties": {
    "iso:country":"GB",
    "sg:address":"Unit 4 City Business Park, Easton Rd",
    "sg:city":"Bristol",
    "sg:classifiers":[
        {
            "category":"Professional",
            "type":"Services"
        }
    ],
    "sg:phone":"+44 117 954 7400",
    "sg:postcode":"BS5 0SP",
    "sg:province":"City of Bristol",
    "sg:tags":[
        "repair",
        "tech",
        "maintenance"
    ],
    "wof:name":"Cubic Transportation Systems",
    "wof:placetype":"venue"
},
  "geometry": {"coordinates":[-2.5737740993,51.4586410522],"type":"Point"}
}