{
  "type": "Feature",
  "properties": {
    "iso:country":"GB",
    "sg:address":"Chatham Service Station, Dock Road",
    "sg:city":"Chatham",
    "sg:classifiers":[
        {
            "category":"Retail",
            "subcategory":"Auto Rental",
            "type":"Services"
        }
    ],
    "sg:phone":"+44 1634 401201",
    "sg:postcode":"ME4 4SU",
    "sg:province":"Kent",
    "sg:tags":[
        "car"
    ],
    "wof:name":"Hertz Rent A Car",
    "wof:placetype":"venue"
},
  "geometry": {"coordinates":[0.52244,51.381889],"type":"Point"}
}