{
  "type": "Feature",
  "properties": {
    "iso:country":"GB",
    "sg:address":"3-4 Balustrade",
    "sg:city":"Bath",
    "sg:classifiers":[
        {
            "category":"Shopping",
            "subcategory":"Department Store",
            "type":"Retail Goods"
        },
        {
            "category":"Food & Beverages",
            "subcategory":"Groceries & Convenience Stores",
            "type":"Retail Goods"
        }
    ],
    "sg:phone":"+44 1225 422715",
    "sg:postcode":"BA1 6QA",
    "sg:province":"Bath and North East Somerset",
    "wof:name":"Beaufort Stores",
    "wof:placetype":"venue"
},
  "geometry": {"coordinates":[-2.347369,51.393791],"type":"Point"}
}