{
  "type": "Feature",
  "properties": {
    "iso:country":"GB",
    "sg:address":"25 St. John St",
    "sg:city":"Oxford",
    "sg:classifiers":[
        {
            "category":"Health Services",
            "subcategory":"Dentist",
            "type":"Services"
        }
    ],
    "sg:phone":"+44 1865 515967",
    "sg:postcode":"OX1 2LH",
    "sg:province":"Oxfordshire",
    "wof:name":"S M Corsi",
    "wof:placetype":"venue"
},
  "geometry": {"coordinates":[-1.261837,51.756664],"type":"Point"}
}