{
  "type": "Feature",
  "properties": {
    "addr:full":"Mcbrides, Nexus House Sidcup Kent DA14 5DA",
    "addr:postcode":"da14 5da",
    "addr:street":"Sidcup",
    "iso:country":"GB",
    "sg:address":"Mcbrides, Nexus House",
    "sg:city":"Sidcup",
    "sg:classifiers":[
        {
            "category":"Professional",
            "subcategory":"Computer Services",
            "type":"Services"
        }
    ],
    "sg:postcode":"DA14 5DA",
    "sg:province":"Kent",
    "sg:tags":[
        "system",
        "software"
    ],
    "wof:name":"Warden Solutions Ltd",
    "wof:placetype":"venue"
},
  "geometry": {"coordinates":[0.103945,51.425919],"type":"Point"}
}