{
  "type": "Feature",
  "properties": {
    "addr:full":"542 Wakefield Road Ossett West Yorkshire WF5 9QJ",
    "addr:housenumber":"542",
    "addr:postcode":"wf5 9qj",
    "addr:street":"Wakefield Road",
    "iso:country":"GB",
    "sg:address":"542 Wakefield Road",
    "sg:city":"Ossett",
    "sg:classifiers":[
        {
            "category":"Shopping",
            "subcategory":"News",
            "type":"Retail Goods"
        }
    ],
    "sg:phone":"+44 1924 274621",
    "sg:postcode":"WF5 9QJ",
    "sg:province":"West Yorkshire",
    "sg:tags":[
        "newsagent"
    ],
    "wof:name":"R J Hitch Newsagent",
    "wof:placetype":"venue"
},
  "geometry": {"coordinates":[-1.594765,53.691338],"type":"Point"}
}