{
  "type": "Feature",
  "properties": {
    "iso:country":"GB",
    "sg:address":"3 Johns Place, Leith",
    "sg:city":"Edinburgh",
    "sg:classifiers":[
        {
            "category":"Real Estate",
            "subcategory":"Architect",
            "type":"Services"
        }
    ],
    "sg:phone":"+44 131 554 9008",
    "sg:postcode":"EH6 7EL",
    "sg:province":"City of Edinburgh",
    "wof:name":"Lindsay Buchan Architect",
    "wof:placetype":"venue"
},
  "geometry": {"coordinates":[-3.166301,55.973129],"type":"Point"}
}