{
  "type": "Feature",
  "properties": {
    "addr:full":"15a Victoria Street, Aberdeen Aberdeen Aberdeen City AB10 1XB",
    "addr:housenumber":"15a",
    "addr:postcode":"ab10 1xb",
    "addr:street":"Victoria Street",
    "iso:country":"GB",
    "sg:address":"15a Victoria Street, Aberdeen",
    "sg:city":"Aberdeen",
    "sg:classifiers":[
        {
            "category":"Real Estate",
            "subcategory":"Architect",
            "type":"Services"
        }
    ],
    "sg:postcode":"AB10 1XB",
    "sg:province":"Aberdeen City",
    "wof:name":"M T M Process Engineering Ltd",
    "wof:placetype":"venue"
},
  "geometry": {"coordinates":[-2.1135621071,57.1437721252],"type":"Point"}
}