{
  "type": "Feature",
  "properties": {
    "iso:country":"GB",
    "sg:address":"Unit 3b, Park Road East, Calverton",
    "sg:city":"Nottingham",
    "sg:classifiers":[
        {
            "category":"Manufacturing",
            "subcategory":"Metals",
            "type":"Manufacturing & Wholesale Goods"
        },
        {
            "category":"Wholesale",
            "subcategory":"Metals & Minerals",
            "type":"Manufacturing & Wholesale Goods"
        }
    ],
    "sg:phone":"+44 115 965 6656",
    "sg:postcode":"NG14 6LL",
    "sg:province":"Nottinghamshire",
    "sg:tags":[
        "fabricator",
        "work",
        "sheet"
    ],
    "wof:name":"Logistic Designs Ltd.",
    "wof:placetype":"venue"
},
  "geometry": {"coordinates":[-1.087909,53.042904],"type":"Point"}
}