{
  "type": "Feature",
  "properties": {
    "addr:full":"Engine Lane, Shafton Barnsley South Yorkshire S72 8SP",
    "addr:postcode":"s72 8sp",
    "addr:street":"Engine Lane;Yorkshire",
    "iso:country":"GB",
    "sg:address":"Engine Lane, Shafton",
    "sg:city":"Barnsley",
    "sg:classifiers":[
        {
            "category":"Professional",
            "subcategory":"Engineering",
            "type":"Services"
        }
    ],
    "sg:phone":"+44 1226 713990",
    "sg:postcode":"S72 8SP",
    "sg:province":"South Yorkshire",
    "wof:name":"Shafton Engineering Services Ltd",
    "wof:placetype":"venue"
},
  "geometry": {"coordinates":[-1.4132579565,53.5975914001],"type":"Point"}
}