{
  "type": "Feature",
  "properties": {
    "addr:full":"33 Eastwood Av Manchester Greater Manchester M43 6BN",
    "addr:housenumber":"33",
    "addr:postcode":"m43 6bn",
    "addr:street":"Eastwood Av",
    "iso:country":"GB",
    "sg:address":"33 Eastwood Av",
    "sg:city":"Manchester",
    "sg:classifiers":[
        {
            "category":"Building & Trades",
            "subcategory":"Construction",
            "type":"Services"
        }
    ],
    "sg:phone":"+44 161 370 8395",
    "sg:postcode":"M43 6BN",
    "sg:province":"Greater Manchester",
    "sg:tags":[
        "tiling",
        "contractor"
    ],
    "wof:name":"T R M Ceramics",
    "wof:placetype":"venue"
},
  "geometry": {"coordinates":[-2.1629691124,53.4790077209],"type":"Point"}
}