{
  "type": "Feature",
  "properties": {
    "iso:country":"GB",
    "sg:address":"Totnes Road",
    "sg:city":"Newton Abbot",
    "sg:classifiers":[
        {
            "category":"Autos & Motor Vehicles",
            "subcategory":"Automobile Sales",
            "type":"Retail Goods"
        }
    ],
    "sg:phone":"+44 1803 813744",
    "sg:postcode":"TQ12 5NE",
    "sg:province":"Devon",
    "sg:tags":[
        "car"
    ],
    "wof:name":"Denbury Diesels Ltd.",
    "wof:placetype":"venue"
},
  "geometry": {"coordinates":[-3.621928,50.514221],"type":"Point"}
}