{
  "type": "Feature",
  "properties": {
    "addr:full":"5 Broadwalk, Knowle Bristol City of Bristol BS4 2RA",
    "addr:housenumber":"5",
    "addr:postcode":"bs4 2ra",
    "addr:street":"Broadwalk Knowle",
    "iso:country":"GB",
    "sg:address":"5 Broadwalk, Knowle",
    "sg:city":"Bristol",
    "sg:classifiers":[
        {
            "category":"Cinema",
            "subcategory":"Movie Rental",
            "type":"Entertainment"
        }
    ],
    "sg:phone":"+44 117 971 6533",
    "sg:postcode":"BS4 2RA",
    "sg:province":"City of Bristol",
    "sg:tags":[
        "video",
        "library"
    ],
    "wof:name":"Enterprise Video",
    "wof:placetype":"venue"
},
  "geometry": {"coordinates":[-2.5697789192,51.434928894],"type":"Point"}
}