{
  "type": "Feature",
  "properties": {
    "addr:full":"245 County Road, Walton Liverpool Merseyside L4 5PE",
    "addr:housenumber":"245",
    "addr:postcode":"l4 5pe",
    "addr:street":"County Road",
    "iso:country":"GB",
    "sg:address":"245 County Road, Walton",
    "sg:city":"Liverpool",
    "sg:classifiers":[
        {
            "category":"Military Area",
            "subcategory":"Air Force Base",
            "type":"Public Place"
        }
    ],
    "sg:phone":"+44 151 525 7000",
    "sg:postcode":"L4 5PE",
    "sg:province":"Merseyside",
    "sg:tags":[
        "taxi",
        "hire",
        "private"
    ],
    "wof:name":"New County Cars",
    "wof:placetype":"venue"
},
  "geometry": {"coordinates":[-2.968002,53.445953],"type":"Point"}
}