{
  "type": "Feature",
  "properties": {
    "addr:full":"Unit 111 Colne Valley Business Pk, Linthwaite Huddersfield West Yorkshire HD7 5QG",
    "addr:housenumber":"111",
    "addr:postcode":"hd7 5qg",
    "addr:street":"Colne Valley Business Pk Linthwaite",
    "iso:country":"GB",
    "sg:address":"Unit 111 Colne Valley Business Pk, Linthwaite",
    "sg:city":"Huddersfield",
    "sg:classifiers":[
        {
            "category":"Shopping",
            "subcategory":"Clothing, Apparel, & Fashions",
            "type":"Retail Goods"
        },
        {
            "category":"Manufacturing",
            "subcategory":"Textiles",
            "type":"Manufacturing & Wholesale Goods"
        }
    ],
    "sg:postcode":"HD7 5QG",
    "sg:province":"West Yorkshire",
    "sg:tags":[
        "made-up",
        "clothing",
        "fabric"
    ],
    "wof:name":"H L Fabrics Ltd",
    "wof:placetype":"venue"
},
  "geometry": {"coordinates":[-1.8474090099,53.6258544922],"type":"Point"}
}