{
  "type": "Feature",
  "properties": {
    "addr:full":"5 Arundel Road Worthing West Sussex BN13 3EH",
    "addr:housenumber":"5",
    "addr:postcode":"bn13 3eh",
    "addr:street":"Arundel Road",
    "iso:country":"GB",
    "sg:address":"5 Arundel Road",
    "sg:city":"Worthing",
    "sg:classifiers":[
        {
            "category":"Retail",
            "subcategory":"Driving School",
            "type":"Services"
        }
    ],
    "sg:phone":"+44 1903 262451",
    "sg:postcode":"BN13 3EH",
    "sg:province":"West Sussex",
    "wof:name":"Sylvia School Of Motoring",
    "wof:placetype":"venue"
},
  "geometry": {"coordinates":[-0.4001710117,50.8406333923],"type":"Point"}
}