{
  "type": "Feature",
  "properties": {
    "iso:country":"GB",
    "sg:address":"135 Ock Street",
    "sg:city":"Abingdon",
    "sg:classifiers":[
        {
            "category":"Fast Food",
            "type":"Food & Drink"
        }
    ],
    "sg:phone":"+44 1235 523383",
    "sg:postcode":"OX14 5DL",
    "sg:province":"Oxfordshire",
    "sg:tags":[
        "away",
        "take"
    ],
    "wof:name":"Domino's Pizza",
    "wof:placetype":"venue"
},
  "geometry": {"coordinates":[-1.291482,51.669468],"type":"Point"}
}