{
  "type": "Feature",
  "properties": {
    "addr:full":"Victoria Market, 23 Victoria Road West, Cleveleys Thornton-cleveleys Lancashire FY5 1BS",
    "addr:housenumber":"23",
    "addr:postcode":"fy5 1bs",
    "addr:street":"Victoria Road West Cleveleys Thornton-Cleveleys",
    "iso:country":"GB",
    "sg:address":"Victoria Market, 23 Victoria Road West, Cleveleys",
    "sg:city":"Thornton-cleveleys",
    "sg:classifiers":[
        {
            "category":"Shopping",
            "subcategory":"Books",
            "type":"Retail Goods"
        }
    ],
    "sg:phone":"+44 1253 855111",
    "sg:postcode":"FY5 1BS",
    "sg:province":"Lancashire",
    "sg:tags":[
        "bookseller"
    ],
    "wof:name":"Waterson's Book Exchange",
    "wof:placetype":"venue"
},
  "geometry": {"coordinates":[-3.04345,53.877541],"type":"Point"}
}