{
  "type": "Feature",
  "properties": {
    "addr:full":"146a Stamford Street Central Ashton-under-lyne Greater Manchester OL6 6AD",
    "addr:housenumber":"146a",
    "addr:postcode":"ol6 6ad",
    "addr:street":"Stamford Street",
    "iso:country":"GB",
    "sg:address":"146a Stamford Street Central",
    "sg:city":"Ashton-under-lyne",
    "sg:classifiers":[
        {
            "category":"Professional",
            "subcategory":"Employment Agencies",
            "type":"Services"
        }
    ],
    "sg:phone":"+44 161 339 4000",
    "sg:postcode":"OL6 6AD",
    "sg:province":"Greater Manchester",
    "sg:tags":[
        "consultant"
    ],
    "wof:name":"Handson",
    "wof:placetype":"venue"
},
  "geometry": {"coordinates":[-2.0913751125,53.4879341125],"type":"Point"}
}