{
  "type": "Feature",
  "properties": {
    "iso:country":"GB",
    "sg:address":"34 Revesby Avenue",
    "sg:city":"Boston",
    "sg:classifiers":[
        {
            "category":"Professional",
            "subcategory":"Employment Agencies",
            "type":"Services"
        }
    ],
    "sg:phone":"+44 1205 366937",
    "sg:postcode":"PE21 8ES",
    "sg:province":"Lincolnshire",
    "sg:tags":[
        "agricultural",
        "advice"
    ],
    "wof:name":"E Newton",
    "wof:placetype":"venue"
},
  "geometry": {"coordinates":[-0.037089,52.976093],"type":"Point"}
}