{
  "type": "Feature",
  "properties": {
    "iso:country":"GB",
    "sg:address":"66-72 Chapeltown Street",
    "sg:city":"Manchester",
    "sg:classifiers":[
        {
            "category":"Shopping",
            "subcategory":"Crafts & Fabrics",
            "type":"Retail Goods"
        }
    ],
    "sg:phone":"+44 161 273 8716",
    "sg:postcode":"M1 2WH",
    "sg:province":"Greater Manchester",
    "sg:tags":[
        "knitwear",
        "yarn"
    ],
    "wof:name":"Shah & Sons",
    "wof:placetype":"venue"
},
  "geometry": {"coordinates":[-2.225454092,53.4788017273],"type":"Point"}
}