{
  "type": "Feature",
  "properties": {
    "addr:full":"Lenacre Court Farm, 33 Lenacre Lane, Whitfield Dover Kent CT16 3HL",
    "addr:housenumber":"33",
    "addr:postcode":"ct16 3hl",
    "addr:street":"Lenacre Lane;Dover",
    "iso:country":"GB",
    "sg:address":"Lenacre Court Farm, 33 Lenacre Lane, Whitfield",
    "sg:city":"Dover",
    "sg:classifiers":[
        {
            "category":"Farming",
            "subcategory":"Livestock Farm",
            "type":"Manufacturing & Wholesale Goods"
        }
    ],
    "sg:phone":"+44 1304 821064",
    "sg:postcode":"CT16 3HL",
    "sg:province":"Kent",
    "sg:tags":[
        "others"
    ],
    "wof:name":"K Broadley",
    "wof:placetype":"venue"
},
  "geometry": {"coordinates":[1.2875699997,51.1638793945],"type":"Point"}
}