{
  "type": "Feature",
  "properties": {
    "addr:full":"River Works, Brookvale Road, Witton Birmingham West Midlands B6 7EU",
    "addr:postcode":"b6 7eu",
    "addr:street":"Brookvale Road",
    "iso:country":"GB",
    "sg:address":"River Works, Brookvale Road, Witton",
    "sg:city":"Birmingham",
    "sg:classifiers":[
        {
            "category":"Freight",
            "type":"Transportation"
        },
        {
            "category":"Professional",
            "subcategory":"Business Services",
            "type":"Services"
        },
        {
            "category":"Retail",
            "subcategory":"Storage",
            "type":"Services"
        }
    ],
    "sg:phone":"+44 121 328 1166",
    "sg:postcode":"B6 7EU",
    "sg:province":"West Midlands",
    "sg:tags":[
        "haulage",
        "household",
        "distribution",
        "road",
        "removal"
    ],
    "wof:name":"D J Ponsonby Ltd.",
    "wof:placetype":"venue"
},
  "geometry": {"coordinates":[-1.8807059526,52.5146980286],"type":"Point"}
}