{
  "type": "Feature",
  "properties": {
    "iso:country":"GB",
    "sg:address":"Ayr Road, Rigside",
    "sg:city":"Lanark",
    "sg:classifiers":[
        {
            "category":"Sports & Exercise",
            "subcategory":"Golf",
            "type":"Entertainment"
        }
    ],
    "sg:phone":"+44 1555 880361",
    "sg:postcode":"ML11 9NP",
    "sg:province":"South Lanarkshire",
    "sg:tags":[
        "club",
        "course"
    ],
    "wof:name":"Douglas Water Golf Club",
    "wof:placetype":"venue"
},
  "geometry": {"coordinates":[-3.793888092,55.591545105],"type":"Point"}
}