{
  "type": "Feature",
  "properties": {
    "addr:full":"Portman House, Portland Road Newcastle-upon-tyne Tyne and Wear NE2 1AQ",
    "addr:postcode":"ne2 1aq",
    "addr:street":"Portland Road",
    "iso:country":"GB",
    "sg:address":"Portman House, Portland Road",
    "sg:city":"Newcastle-upon-tyne",
    "sg:classifiers":[
        {
            "category":"Utilities",
            "subcategory":"Natural Gas",
            "type":"Services"
        }
    ],
    "sg:phone":"+44 191 232 3808",
    "sg:postcode":"NE2 1AQ",
    "sg:province":"Tyne and Wear",
    "sg:tags":[
        "weather"
    ],
    "wof:name":"The Met Office Marketing Services",
    "wof:placetype":"venue"
},
  "geometry": {"coordinates":[-1.5972900391,54.9772109985],"type":"Point"}
}