{
  "type": "Feature",
  "properties": {
    "addr:full":"5 Tates Hawkhurst East Sussex TN18 4LN",
    "addr:housenumber":"5",
    "addr:postcode":"tn18 4ln",
    "addr:street":"Tates Hawkhurst",
    "iso:country":"GB",
    "sg:address":"5 Tates",
    "sg:city":"Hawkhurst",
    "sg:classifiers":[
        {
            "category":"Professional",
            "subcategory":"Management & Consulting",
            "type":"Services"
        }
    ],
    "sg:phone":"+44 1580 754413",
    "sg:postcode":"TN18 4LN",
    "sg:province":"East Sussex",
    "sg:tags":[
        "consultant",
        "training"
    ],
    "wof:name":"Sales Assessment & Improvements Ltd",
    "wof:placetype":"venue"
},
  "geometry": {"coordinates":[0.509662,51.045254],"type":"Point"}
}