{
  "type": "Feature",
  "properties": {
    "iso:country":"GB",
    "sg:address":"45 Hospital Street",
    "sg:city":"Nantwich",
    "sg:classifiers":[
        {
            "category":"Deli",
            "type":"Food & Drink"
        }
    ],
    "sg:phone":"+44 1270 625491",
    "sg:postcode":"CW5 5RL",
    "sg:province":"Cheshire",
    "sg:tags":[
        "delicatessen"
    ],
    "wof:name":"A T Welch",
    "wof:placetype":"venue"
},
  "geometry": {"coordinates":[-2.519370079,53.0662193298],"type":"Point"}
}