{
  "type": "Feature",
  "properties": {
    "iso:country":"GB",
    "sg:address":"572 Portway",
    "sg:city":"Bristol",
    "sg:classifiers":[
        {
            "category":"Organizations",
            "subcategory":"Non-profit Organization",
            "type":"Services"
        }
    ],
    "sg:phone":"+44 117 923 5970",
    "sg:postcode":"BS11 9QG",
    "sg:province":"City of Bristol",
    "sg:tags":[
        "organisation",
        "voluntary",
        "charity"
    ],
    "wof:name":"Guide Dogs For The Blind Association The",
    "wof:placetype":"venue"
},
  "geometry": {"coordinates":[-2.685681,51.488411],"type":"Point"}
}