{
  "type": "Feature",
  "properties": {
    "addr:full":"Box Tree Farm, Main Street, Farnhill Keighley North Yorkshire BD20 9BW",
    "addr:postcode":"bd20 9bw",
    "addr:street":"Box;Main Street",
    "iso:country":"GB",
    "sg:address":"Box Tree Farm, Main Street, Farnhill",
    "sg:city":"Keighley",
    "sg:classifiers":[
        {
            "category":"Farming",
            "subcategory":"Livestock Farm",
            "type":"Manufacturing & Wholesale Goods"
        }
    ],
    "sg:phone":"+44 1535 632368",
    "sg:postcode":"BD20 9BW",
    "sg:province":"North Yorkshire",
    "sg:tags":[
        "others"
    ],
    "wof:name":"J Roberts",
    "wof:placetype":"venue"
},
  "geometry": {"coordinates":[-1.9443839788,53.9166374207],"type":"Point"}
}