{
  "type": "Feature",
  "properties": {
    "iso:country":"GB",
    "sg:address":"14 Dunyeats Road",
    "sg:city":"Broadstone",
    "sg:classifiers":[
        {
            "category":"Government",
            "subcategory":"Post Office",
            "type":"Public Place"
        }
    ],
    "sg:postcode":"BH18 8AG",
    "sg:province":"Dorset",
    "wof:name":"Broadstone Sub Post Office",
    "wof:placetype":"venue"
},
  "geometry": {"coordinates":[-1.9946420193,50.7621154785],"type":"Point"}
}