{
  "type": "Feature",
  "properties": {
    "addr:full":"Unit 16 Limberline Spur, Hilsea Portsmouth Hampshire PO3 5HJ",
    "addr:housenumber":"unit 16",
    "addr:postcode":"po3 5hj",
    "addr:street":"Limberline Spur Hilsea",
    "iso:country":"GB",
    "sg:address":"Unit 16 Limberline Spur, Hilsea",
    "sg:city":"Portsmouth",
    "sg:classifiers":[
        {
            "category":"Manufacturing",
            "subcategory":"Buildings",
            "type":"Manufacturing & Wholesale Goods"
        },
        {
            "category":"Home & Garden",
            "subcategory":"Garden Supply",
            "type":"Retail Goods"
        }
    ],
    "sg:phone":"+44 23 9266 4811",
    "sg:postcode":"PO3 5HJ",
    "sg:province":"Hampshire",
    "sg:tags":[
        "shed",
        "greenhouse"
    ],
    "wof:name":"Elfords Sheds",
    "wof:placetype":"venue"
},
  "geometry": {"coordinates":[-1.0618970394,50.8329696655],"type":"Point"}
}