{
  "type": "Feature",
  "properties": {
    "addr:full":"13 Wheat Field Way Brighton East Sussex BN2 4RQ",
    "addr:housenumber":"13",
    "addr:postcode":"bn2 4rq",
    "addr:street":"Wheat Field Way",
    "iso:country":"GB",
    "sg:address":"13 Wheat Field Way",
    "sg:city":"Brighton",
    "sg:classifiers":[
        {
            "category":"Building & Trades",
            "subcategory":"Construction",
            "type":"Services"
        }
    ],
    "sg:phone":"+44 1273 622404",
    "sg:postcode":"BN2 4RQ",
    "sg:province":"East Sussex",
    "sg:tags":[
        "roofing"
    ],
    "wof:name":"V G Baker",
    "wof:placetype":"venue"
},
  "geometry": {"coordinates":[-0.1023240015,50.850818634],"type":"Point"}
}