{
  "type": "Feature",
  "properties": {
    "addr:full":"165 Bawtry Road, Wickersley Rotherham South Yorkshire S66 2BW",
    "addr:housenumber":"165",
    "addr:postcode":"s66 2bw",
    "addr:street":"Bawtry Road",
    "iso:country":"GB",
    "sg:address":"165 Bawtry Road, Wickersley",
    "sg:city":"Rotherham",
    "sg:classifiers":[
        {
            "category":"Personal",
            "subcategory":"Barber",
            "type":"Services"
        }
    ],
    "sg:phone":"+44 1709 532002",
    "sg:postcode":"S66 2BW",
    "sg:province":"South Yorkshire",
    "sg:tags":[
        "men's",
        "hairdresser"
    ],
    "wof:name":"Flynns Barber Shop",
    "wof:placetype":"venue"
},
  "geometry": {"coordinates":[-1.2835279703,53.4217224121],"type":"Point"}
}