{
  "type": "Feature",
  "properties": {
    "addr:full":"Point Road Canvey Island Essex SS8 7TX",
    "addr:postcode":"ss8 7tx",
    "addr:street":"Point Road",
    "iso:country":"GB",
    "sg:address":"Point Road",
    "sg:city":"Canvey Island",
    "sg:classifiers":[
        {
            "category":"Arena",
            "subcategory":"Sports Club",
            "type":"Entertainment"
        }
    ],
    "sg:phone":"+44 1268 510360",
    "sg:postcode":"SS8 7TX",
    "sg:province":"Essex",
    "wof:name":"Island Yacht Club",
    "wof:placetype":"venue"
},
  "geometry": {"coordinates":[0.6235899925,51.5190582275],"type":"Point"}
}