{
  "type": "Feature",
  "properties": {
    "iso:country":"GB",
    "sg:address":"24 Ireton Court",
    "sg:city":"Thame",
    "sg:classifiers":[
        {
            "category":"Professional",
            "subcategory":"Computer Services",
            "type":"Services"
        }
    ],
    "sg:postcode":"OX9 3EB",
    "sg:province":"Buckinghamshire",
    "sg:tags":[
        "consultant"
    ],
    "wof:name":"Jefferies Associates",
    "wof:placetype":"venue"
},
  "geometry": {"coordinates":[-0.974961,51.752182],"type":"Point"}
}