{
  "type": "Feature",
  "properties": {
    "addr:full":"Roddington Forge, Allington Lane, West End Southampton Hampshire SO30 3HQ",
    "addr:postcode":"so30 3hq",
    "addr:street":"Allington Lane",
    "iso:country":"GB",
    "sg:address":"Roddington Forge, Allington Lane, West End",
    "sg:city":"Southampton",
    "sg:classifiers":[
        {
            "category":"Wholesale",
            "subcategory":"Scrap",
            "type":"Manufacturing & Wholesale Goods"
        }
    ],
    "sg:phone":"+44 23 8047 7657",
    "sg:postcode":"SO30 3HQ",
    "sg:province":"Hampshire",
    "sg:tags":[
        "breaker",
        "dismantlers"
    ],
    "wof:name":"J M A Salvage Group",
    "wof:placetype":"venue"
},
  "geometry": {"coordinates":[-1.3422700167,50.9391212463],"type":"Point"}
}