{
  "type": "Feature",
  "properties": {
    "iso:country":"GB",
    "sg:address":"105 Corbar Rd",
    "sg:city":"Buxton",
    "sg:classifiers":[
        {
            "category":"Place Of Worship",
            "type":"Public Place"
        }
    ],
    "sg:phone":"+44 1298 73920",
    "sg:postcode":"SK17 6RJ",
    "sg:province":"Derbyshire",
    "wof:name":"Buxton Community Church",
    "wof:placetype":"venue"
},
  "geometry": {"coordinates":[-1.915308,53.266117],"type":"Point"}
}