{
  "type": "Feature",
  "properties": {
    "addr:full":"469 Alexandra Avenue Harrow Greater London HA2 9RY",
    "addr:housenumber":"469",
    "addr:postcode":"ha2 9ry",
    "addr:street":"Alexandra Avenue",
    "iso:country":"GB",
    "sg:address":"469 Alexandra Avenue",
    "sg:city":"Harrow",
    "sg:classifiers":[
        {
            "category":"Personal",
            "subcategory":"Beauty Salon",
            "type":"Services"
        }
    ],
    "sg:postcode":"HA2 9RY",
    "sg:province":"Greater London",
    "sg:tags":[
        "unisex",
        "hairdresser"
    ],
    "wof:name":"Shapes in Hair & Beauty",
    "wof:placetype":"venue"
},
  "geometry": {"coordinates":[-0.371044,51.574665],"type":"Point"}
}