{
  "type": "Feature",
  "properties": {
    "iso:country":"GB",
    "sg:address":"12 Stenhouse Cross",
    "sg:city":"Edinburgh",
    "sg:classifiers":[
        {
            "category":"Fast Food",
            "type":"Food & Drink"
        },
        {
            "category":"Food & Beverages",
            "subcategory":"Meat & Fish",
            "type":"Retail Goods"
        }
    ],
    "sg:phone":"+44 131 443 2900",
    "sg:postcode":"EH11 3JU",
    "sg:province":"City of Edinburgh",
    "sg:tags":[
        "outlet",
        "chip",
        "meal",
        "away",
        "take"
    ],
    "wof:name":"Stenhouse Fish & Chicken Bar",
    "wof:placetype":"venue"
},
  "geometry": {"coordinates":[-3.259937,55.932816],"type":"Point"}
}