{
  "type": "Feature",
  "properties": {
    "iso:country":"GB",
    "sg:address":"52 Edward St, Rusthall",
    "sg:city":"Tunbridge Wells",
    "sg:classifiers":[
        {
            "category":"Professional",
            "subcategory":"Business Services",
            "type":"Services"
        }
    ],
    "sg:phone":"+44 1892 530731",
    "sg:postcode":"TN4 8RP",
    "sg:province":"Kent",
    "sg:tags":[
        "holding"
    ],
    "wof:name":"Wish Tunbridgewells Ltd",
    "wof:placetype":"venue"
},
  "geometry": {"coordinates":[0.22862,51.13448],"type":"Point"}
}