{
  "type": "Feature",
  "properties": {
    "iso:country":"GB",
    "sg:address":"Unit D3 Brookside Business Park, Greengate, Middleton",
    "sg:city":"Manchester",
    "sg:classifiers":[
        {
            "category":"Home & Garden",
            "subcategory":"Home Furnishings",
            "type":"Retail Goods"
        }
    ],
    "sg:phone":"+44 161 653 2270",
    "sg:postcode":"M24 1GS",
    "sg:province":"Greater Manchester",
    "sg:tags":[
        "awning",
        "canopy",
        "blinds"
    ],
    "wof:name":"Summer Street Blinds",
    "wof:placetype":"venue"
},
  "geometry": {"coordinates":[-2.17247,53.53896],"type":"Point"}
}