{
  "type": "Feature",
  "properties": {
    "iso:country":"GB",
    "sg:address":"15 Nunthorpe Avenue",
    "sg:city":"York",
    "sg:classifiers":[
        {
            "category":"Travel",
            "subcategory":"Hotels & Motels",
            "type":"Entertainment"
        }
    ],
    "sg:phone":"+44 1904 620081",
    "sg:postcode":"YO23 1PF",
    "sg:province":"North Yorkshire",
    "sg:tags":[
        "house",
        "guest"
    ],
    "wof:name":"Barrington Guest House",
    "wof:placetype":"venue"
},
  "geometry": {"coordinates":[-1.08986,53.950714],"type":"Point"}
}