{
  "type": "Feature",
  "properties": {
    "addr:full":"Heron House, 5 The Spinney, Compton Winchester Hampshire SO23 9NQ",
    "addr:housenumber":"5",
    "addr:postcode":"so23 9nq",
    "addr:street":"The Spinney",
    "iso:country":"GB",
    "sg:address":"Heron House, 5 The Spinney, Compton",
    "sg:city":"Winchester",
    "sg:classifiers":[
        {
            "category":"Autos & Motor Vehicles",
            "subcategory":"Automobile Sales",
            "type":"Retail Goods"
        }
    ],
    "sg:phone":"+44 1962 712847",
    "sg:postcode":"SO23 9NQ",
    "sg:province":"Hampshire",
    "sg:tags":[
        "car"
    ],
    "wof:name":"Aztec Trading",
    "wof:placetype":"venue"
},
  "geometry": {"coordinates":[-1.3168090582,51.0630683899],"type":"Point"}
}