{
  "type": "Feature",
  "properties": {
    "addr:full":"Back O Hill Road Indust Est Stirling Stirling FK8 1SH",
    "addr:postcode":"fk8 1sh",
    "addr:street":"Back O Hill Road",
    "iso:country":"GB",
    "sg:address":"Back O Hill Road Indust Est",
    "sg:city":"Stirling",
    "sg:classifiers":[
        {
            "category":"Retail",
            "subcategory":"Auto Repair",
            "type":"Services"
        }
    ],
    "sg:phone":"+44 1786 450976",
    "sg:postcode":"FK8 1SH",
    "sg:province":"Stirling",
    "sg:tags":[
        "car",
        "servicing",
        "radiator"
    ],
    "wof:name":"Serck Marston",
    "wof:placetype":"venue"
},
  "geometry": {"coordinates":[-3.952069,56.125637],"type":"Point"}
}