{
  "type": "Feature",
  "properties": {
    "iso:country":"GB",
    "sg:address":"17 School Steet, Elliots Town",
    "sg:city":"New Tredegar",
    "sg:classifiers":[
        {
            "category":"Fast Food",
            "type":"Food & Drink"
        }
    ],
    "sg:phone":"+44 1443 834404",
    "sg:postcode":"NP24 6NG",
    "sg:province":"Caerphilly",
    "sg:tags":[
        "away",
        "meal",
        "outlet",
        "take"
    ],
    "wof:name":"Kings Takeaway",
    "wof:placetype":"venue"
},
  "geometry": {"coordinates":[-3.2377490997,51.7186431885],"type":"Point"}
}