{
  "type": "Feature",
  "properties": {
    "iso:country":"GB",
    "sg:address":"Unit 4 Boxmend Industrial Estate, Bircholt Road",
    "sg:city":"Maidstone",
    "sg:classifiers":[
        {
            "category":"Professional",
            "subcategory":"Detective & Security Services",
            "type":"Services"
        }
    ],
    "sg:postcode":"ME15 9YG",
    "sg:province":"Kent",
    "sg:tags":[
        "alarm",
        "burglar",
        "system"
    ],
    "wof:name":"Response Security Ltd",
    "wof:placetype":"venue"
},
  "geometry": {"coordinates":[0.56128,51.234909],"type":"Point"}
}