{
  "type": "Feature",
  "properties": {
    "addr:full":"46 Chamberlain Avenue Maidstone Kent ME16 8NY",
    "addr:housenumber":"46",
    "addr:postcode":"me16 8ny",
    "addr:street":"Chamberlain Avenue",
    "iso:country":"GB",
    "sg:address":"46 Chamberlain Avenue",
    "sg:city":"Maidstone",
    "sg:classifiers":[
        {
            "category":"Retail",
            "subcategory":"Driving School",
            "type":"Services"
        }
    ],
    "sg:phone":"+44 1622 728788",
    "sg:postcode":"ME16 8NY",
    "sg:province":"Kent",
    "wof:name":"Bryon's School of Motoring",
    "wof:placetype":"venue"
},
  "geometry": {"coordinates":[0.4925749898,51.2635536194],"type":"Point"}
}