{
  "type": "Feature",
  "properties": {
    "addr:full":"24 Port Street Evesham Gloucestershire WR11 1AW",
    "addr:housenumber":"24",
    "addr:postcode":"wr11 1aw",
    "addr:street":"Port Street",
    "iso:country":"GB",
    "sg:address":"24 Port Street",
    "sg:city":"Evesham",
    "sg:classifiers":[
        {
            "category":"Food & Beverages",
            "subcategory":"Meat & Fish",
            "type":"Retail Goods"
        }
    ],
    "sg:postcode":"WR11 1AW",
    "sg:province":"Gloucestershire",
    "sg:tags":[
        "chip"
    ],
    "wof:name":"Friar Tuck",
    "wof:placetype":"venue"
},
  "geometry": {"coordinates":[-1.9408370256,52.0908470154],"type":"Point"}
}