{
  "type": "Feature",
  "properties": {
    "iso:country":"GB",
    "sg:address":"82 Plungington Road",
    "sg:city":"Preston",
    "sg:classifiers":[
        {
            "category":"Professional",
            "subcategory":"Business Services",
            "type":"Services"
        },
        {
            "category":"Casinos & Gambling",
            "type":"Entertainment"
        }
    ],
    "sg:phone":"+44 1772 884471",
    "sg:postcode":"PR1 7RA",
    "sg:province":"Lancashire",
    "sg:tags":[
        "turf",
        "accountant",
        "bookmaker"
    ],
    "wof:name":"Done Brothers (Cash Betting) Ltd.",
    "wof:placetype":"venue"
},
  "geometry": {"coordinates":[-2.711085,53.769882],"type":"Point"}
}