{
  "type": "Feature",
  "properties": {
    "addr:full":"19 Bushey Mill Crescent Watford Hertfordshire WD2 4RA",
    "addr:housenumber":"19",
    "addr:postcode":"wd2 4ra",
    "addr:street":"Bushey Mill Crescent",
    "iso:country":"GB",
    "sg:address":"19 Bushey Mill Crescent",
    "sg:city":"Watford",
    "sg:classifiers":[
        {
            "category":"Organizations",
            "subcategory":"Community Association",
            "type":"Services"
        }
    ],
    "sg:phone":"+44 1923 211667",
    "sg:postcode":"WD2 4RA",
    "sg:province":"Hertfordshire",
    "sg:tags":[
        "relation",
        "public"
    ],
    "wof:name":"Texttalent Copy Writing",
    "wof:placetype":"venue"
},
  "geometry": {"coordinates":[-0.3949739933,51.6786499023],"type":"Point"}
}