{
  "type": "Feature",
  "properties": {
    "addr:full":"Red Post Hill Dulwich Greater London SE21 7BX",
    "addr:postcode":"se21 7bx",
    "addr:street":"Post Hill",
    "iso:country":"GB",
    "sg:address":"Red Post Hill",
    "sg:city":"Dulwich",
    "sg:classifiers":[
        {
            "category":"Landmark",
            "subcategory":"Tourist Attraction",
            "type":"Public Place"
        }
    ],
    "sg:phone":"+44 20 7274 0831",
    "sg:postcode":"SE21 7BX",
    "sg:province":"Greater London",
    "sg:tags":[
        "interest"
    ],
    "wof:name":"Sunray Gardens",
    "wof:placetype":"venue"
},
  "geometry": {"coordinates":[-0.088849,51.440975],"type":"Point"}
}