{
  "type": "Feature",
  "properties": {
    "iso:country":"GB",
    "sg:address":"Kingsforth Road, Thurcroft",
    "sg:city":"Rotherham",
    "sg:classifiers":[
        {
            "category":"Building & Trades",
            "subcategory":"Cleaning & Sanitation",
            "type":"Services"
        }
    ],
    "sg:phone":"+44 1709 545999",
    "sg:postcode":"S66 9HU",
    "sg:province":"South Yorkshire",
    "sg:tags":[
        "door",
        "manufacturer"
    ],
    "wof:name":"Northern Doors (U K) Ltd.",
    "wof:placetype":"venue"
},
  "geometry": {"coordinates":[-1.257554,53.394321],"type":"Point"}
}