{
  "type": "Feature",
  "properties": {
    "addr:full":"68 Church Way, Iffley Oxford Oxfordshire OX4 4EF",
    "addr:housenumber":"68",
    "addr:postcode":"ox4 4ef",
    "addr:street":"Church Way",
    "iso:country":"GB",
    "sg:address":"68 Church Way, Iffley",
    "sg:city":"Oxford",
    "sg:classifiers":[
        {
            "category":"Health Services",
            "subcategory":"Health Practitioner",
            "type":"Services"
        }
    ],
    "sg:postcode":"OX4 4EF",
    "sg:province":"Oxfordshire",
    "sg:tags":[
        "technique",
        "alexander"
    ],
    "wof:name":"Joy Packard",
    "wof:placetype":"venue"
},
  "geometry": {"coordinates":[-1.2366739511,51.730594635],"type":"Point"}
}