{
  "type": "Feature",
  "properties": {
    "addr:full":"176 Beehive Lane Ilford Essex IG4 5EE",
    "addr:housenumber":"176",
    "addr:postcode":"ig4 5ee",
    "addr:street":"Beehive Lane",
    "iso:country":"GB",
    "sg:address":"176 Beehive Lane",
    "sg:city":"Ilford",
    "sg:classifiers":[
        {
            "category":"Health Services",
            "subcategory":"Health Practitioner",
            "type":"Services"
        }
    ],
    "sg:postcode":"IG4 5EE",
    "sg:province":"Essex",
    "sg:tags":[
        "osteopath"
    ],
    "wof:name":"James F Hay",
    "wof:placetype":"venue"
},
  "geometry": {"coordinates":[0.058934,51.579891],"type":"Point"}
}