{
  "type": "Feature",
  "properties": {
    "addr:full":"135 Garscadden Road Glasgow Glasgow City G15 6UQ",
    "addr:housenumber":"135",
    "addr:postcode":"g15 6uq",
    "addr:street":"Garscadden Road",
    "iso:country":"GB",
    "sg:address":"135 Garscadden Road",
    "sg:city":"Glasgow",
    "sg:classifiers":[
        {
            "category":"Food & Beverages",
            "subcategory":"Groceries & Convenience Stores",
            "type":"Retail Goods"
        }
    ],
    "sg:phone":"+44 141 944 4457",
    "sg:postcode":"G15 6UQ",
    "sg:province":"Glasgow City",
    "wof:name":"10 O'Clock Shop",
    "wof:placetype":"venue"
},
  "geometry": {"coordinates":[-4.364076,55.906132],"type":"Point"}
}