{
  "type": "Feature",
  "properties": {
    "iso:country":"GB",
    "sg:address":"6 Dagtail Lane, Astwood Bank",
    "sg:city":"Redditch",
    "sg:classifiers":[
        {
            "category":"Building & Trades",
            "subcategory":"Plumbing",
            "type":"Services"
        }
    ],
    "sg:postcode":"B97 5QT",
    "sg:province":"Warwickshire",
    "sg:tags":[
        "central",
        "heating"
    ],
    "wof:name":"Key & Hulland",
    "wof:placetype":"venue"
},
  "geometry": {"coordinates":[-1.939616,52.269051],"type":"Point"}
}