{
  "type": "Feature",
  "properties": {
    "iso:country":"GB",
    "sg:address":"Stirling Road, Fallin",
    "sg:city":"Stirling",
    "sg:classifiers":[
        {
            "category":"Professional",
            "subcategory":"Engineering",
            "type":"Services"
        }
    ],
    "sg:phone":"+44 1786 818747",
    "sg:postcode":"FK7 7JB",
    "sg:province":"Falkirk",
    "sg:tags":[
        "precision",
        "engineer"
    ],
    "wof:name":"Dunblane Light Engineering Ltd",
    "wof:placetype":"venue"
},
  "geometry": {"coordinates":[-3.881969,56.10606],"type":"Point"}
}