{
  "type": "Feature",
  "properties": {
    "iso:country":"GB",
    "sg:address":"39 Freelands Road",
    "sg:city":"Cobham",
    "sg:classifiers":[
        {
            "category":"Professional",
            "subcategory":"Management & Consulting",
            "type":"Services"
        }
    ],
    "sg:postcode":"KT11 2NA",
    "sg:province":"Surrey",
    "sg:tags":[
        "consultant",
        "business"
    ],
    "wof:name":"Satara Consulting Ltd",
    "wof:placetype":"venue"
},
  "geometry": {"coordinates":[-0.407361,51.331375],"type":"Point"}
}