{
  "type": "Feature",
  "properties": {
    "iso:country":"GB",
    "sg:address":"Donnington Rd",
    "sg:city":"London",
    "sg:classifiers":[
        {
            "category":"Community Center",
            "type":"Public Place"
        }
    ],
    "sg:phone":"+44 20 8459 6605",
    "sg:postcode":"NW10 3QX",
    "sg:province":"Greater London",
    "sg:tags":[
        "recreation",
        "leisure",
        "centre"
    ],
    "wof:name":"Whitewater Leisure Management Ltd",
    "wof:placetype":"venue"
},
  "geometry": {"coordinates":[-0.226635,51.541721],"type":"Point"}
}