{
  "type": "Feature",
  "properties": {
    "addr:full":"Unit 2b, Farlesthorpe Rd Alford Lincolnshire LN13 9PS",
    "addr:housenumber":"unit 2b",
    "addr:postcode":"ln13 9ps",
    "addr:street":"Farlesthorpe Rd",
    "iso:country":"GB",
    "sg:address":"Unit 2b, Farlesthorpe Rd",
    "sg:city":"Alford",
    "sg:classifiers":[
        {
            "category":"Building & Trades",
            "subcategory":"Construction",
            "type":"Services"
        }
    ],
    "sg:phone":"+44 1507 466899",
    "sg:postcode":"LN13 9PS",
    "sg:province":"Lincolnshire",
    "sg:tags":[
        "contractor"
    ],
    "wof:name":"Profile Groundworks",
    "wof:placetype":"venue"
},
  "geometry": {"coordinates":[0.184295,53.255577],"type":"Point"}
}