{
  "type": "Feature",
  "properties": {
    "iso:country":"GB",
    "sg:address":"322 Kennington Pk Rd",
    "sg:city":"London",
    "sg:classifiers":[
        {
            "category":"Professional",
            "subcategory":"Computer Services",
            "type":"Services"
        }
    ],
    "sg:phone":"+44 20 7793 8667",
    "sg:postcode":"SE11 4PX",
    "sg:province":"Greater London",
    "sg:tags":[
        "system",
        "software"
    ],
    "wof:name":"Front,J P Solutions Ltd",
    "wof:placetype":"venue"
},
  "geometry": {"coordinates":[-0.111536,51.486526],"type":"Point"}
}