{
  "type": "Feature",
  "properties": {
    "iso:country":"GB",
    "sg:address":"20 Hurricane Way",
    "sg:city":"Norwich",
    "sg:classifiers":[
        {
            "category":"Education",
            "subcategory":"Special Training",
            "type":"Public Place"
        },
        {
            "category":"Real Estate",
            "subcategory":"Real Estate Agent",
            "type":"Services"
        }
    ],
    "sg:phone":"+44 1603 401606",
    "sg:postcode":"NR6 6EY",
    "sg:province":"Norfolk",
    "sg:tags":[
        "product",
        "centre"
    ],
    "sg:website":"http://www.eagit.co.uk",
    "wof:name":"Eagit Ltd",
    "wof:placetype":"venue"
},
  "geometry": {"coordinates":[1.288115,52.667519],"type":"Point"}
}