{
  "type": "Feature",
  "properties": {
    "iso:country":"GB",
    "sg:address":"The Oxhams, Cross Common Rd",
    "sg:city":"Dinas Powys",
    "sg:classifiers":[
        {
            "category":"Banks & Credit Unions",
            "subcategory":"Bank",
            "type":"Services"
        }
    ],
    "sg:postcode":"CF64 4TP",
    "sg:province":"The Vale of Glamorgan",
    "sg:tags":[
        "stocktaking",
        "inventory"
    ],
    "wof:name":"King,Lyndon,",
    "wof:placetype":"venue"
},
  "geometry": {"coordinates":[-3.2163169384,51.4279670715],"type":"Point"}
}