{
  "type": "Feature",
  "properties": {
    "iso:country":"GB",
    "sg:address":"399 Footscray Road",
    "sg:city":"London",
    "sg:classifiers":[
        {
            "category":"Personal",
            "subcategory":"Nail Salon",
            "type":"Services"
        }
    ],
    "sg:phone":"+44 20 8859 8818",
    "sg:postcode":"SE9 2DR",
    "sg:province":"Greater London",
    "sg:tags":[
        "solarium",
        "tanning"
    ],
    "wof:name":"Tanners",
    "wof:placetype":"venue"
},
  "geometry": {"coordinates":[0.071337,51.438557],"type":"Point"}
}