{
  "type": "Feature",
  "properties": {
    "addr:full":"47 St Giles Street Northampton Northamptonshire NN1 1LU",
    "addr:housenumber":"47",
    "addr:postcode":"nn1 1lu",
    "addr:street":"St Giles Street",
    "iso:country":"GB",
    "sg:address":"47 St Giles Street",
    "sg:city":"Northampton",
    "sg:classifiers":[
        {
            "category":"Bars & Pubs",
            "type":"Food & Drink"
        }
    ],
    "sg:phone":"+44 1604 239534",
    "sg:postcode":"NN1 1LU",
    "sg:province":"Northamptonshire",
    "sg:tags":[
        "pubs",
        "inn"
    ],
    "wof:name":"Rat & Parrot",
    "wof:placetype":"venue"
},
  "geometry": {"coordinates":[-0.8922219872,52.2376594543],"type":"Point"}
}