{
  "type": "Feature",
  "properties": {
    "addr:full":"Unit 4c Grovehill Indust Est, Grovehill Rd Beverley East Riding of Yorkshire HU17 0EA",
    "addr:housenumber":"unit 4c",
    "addr:postcode":"hu17 0ea",
    "addr:street":"Grovehill Indust Est Grovehill Rd",
    "iso:country":"GB",
    "sg:address":"Unit 4c Grovehill Indust Est, Grovehill Rd",
    "sg:city":"Beverley",
    "sg:classifiers":[
        {
            "category":"Professional",
            "subcategory":"Business Services",
            "type":"Services"
        }
    ],
    "sg:phone":"+44 70 7122 3528",
    "sg:postcode":"HU17 0EA",
    "sg:province":"East Riding of Yorkshire",
    "sg:tags":[
        "distribution"
    ],
    "wof:name":"Easton Distribution",
    "wof:placetype":"venue"
},
  "geometry": {"coordinates":[-0.400204,53.843269],"type":"Point"}
}