{
  "type": "Feature",
  "properties": {
    "addr:full":"17 Murray Street Paisley Renfrewshire PA3 1QG",
    "addr:housenumber":"17",
    "addr:postcode":"pa3 1qg",
    "addr:street":"Murray Street",
    "iso:country":"GB",
    "sg:address":"17 Murray Street",
    "sg:city":"Paisley",
    "sg:classifiers":[
        {
            "category":"Professional",
            "subcategory":"Accounting & Tax Preparation",
            "type":"Services"
        }
    ],
    "sg:postcode":"PA3 1QG",
    "sg:province":"Renfrewshire",
    "sg:tags":[
        "accountant"
    ],
    "wof:name":"Metis Ltd.",
    "wof:placetype":"venue"
},
  "geometry": {"coordinates":[-4.4328999519,55.8517189026],"type":"Point"}
}