{
  "type": "Feature",
  "properties": {
    "addr:full":"8 Thackery Street London Greater London W8 5ET",
    "addr:housenumber":"8",
    "addr:postcode":"w8 5et",
    "addr:street":"Thackery Street",
    "iso:country":"GB",
    "sg:address":"8 Thackery Street",
    "sg:city":"London",
    "sg:classifiers":[
        {
            "category":"Shopping",
            "subcategory":"Bicycles & Sporting Goods",
            "type":"Retail Goods"
        }
    ],
    "sg:phone":"+44 20 7937 4377",
    "sg:postcode":"W8 5ET",
    "sg:province":"Greater London",
    "sg:tags":[
        "riding",
        "saddlery",
        "wear"
    ],
    "wof:name":"Riders & Squires of Kensington Ltd.",
    "wof:placetype":"venue"
},
  "geometry": {"coordinates":[-0.1886029989,51.5004730225],"type":"Point"}
}