{
  "type": "Feature",
  "properties": {
    "iso:country":"GB",
    "sg:address":"15 Baneswell Road",
    "sg:city":"Newport",
    "sg:classifiers":[
        {
            "category":"Shopping",
            "subcategory":"Gifts & Souvenirs",
            "type":"Retail Goods"
        },
        {
            "category":"Professional",
            "subcategory":"Printing & Photocopies",
            "type":"Services"
        }
    ],
    "sg:phone":"+44 1633 257748",
    "sg:postcode":"NP20 4BP",
    "sg:province":"Newport",
    "sg:tags":[
        "trophy",
        "supplier",
        "medal"
    ],
    "wof:name":"Cambrian Trophies",
    "wof:placetype":"venue"
},
  "geometry": {"coordinates":[-2.999057,51.587311],"type":"Point"}
}