{
  "type": "Feature",
  "properties": {
    "addr:full":"Cradle Farm, Wiggington Banbury Oxfordshire OX15 4LF",
    "addr:postcode":"ox15 4lf",
    "addr:street":"Wiggington",
    "iso:country":"GB",
    "sg:address":"Cradle Farm, Wiggington",
    "sg:city":"Banbury",
    "sg:classifiers":[
        {
            "category":"Farming",
            "subcategory":"Livestock Farm",
            "type":"Manufacturing & Wholesale Goods"
        }
    ],
    "sg:phone":"+44 1608 737786",
    "sg:postcode":"OX15 4LF",
    "sg:province":"Oxfordshire",
    "sg:tags":[
        "others"
    ],
    "wof:name":"O D Plunkett",
    "wof:placetype":"venue"
},
  "geometry": {"coordinates":[-1.3304640055,52.0333786011],"type":"Point"}
}