{
  "type": "Feature",
  "properties": {
    "addr:full":"173 Boston Road, Hanwell London Greater London W7 3QJ",
    "addr:housenumber":"173",
    "addr:postcode":"w7 3qj",
    "addr:street":"Boston Road",
    "iso:country":"GB",
    "sg:address":"173 Boston Road, Hanwell",
    "sg:city":"London",
    "sg:classifiers":[
        {
            "category":"Shopping Center",
            "type":"Public Place"
        },
        {
            "category":"Sports & Exercise",
            "subcategory":"Race Track",
            "type":"Entertainment"
        }
    ],
    "sg:phone":"+44 20 8567 8948",
    "sg:postcode":"W7 3QJ",
    "sg:province":"Greater London",
    "sg:tags":[
        "clutch",
        "replacement",
        "brake",
        "centre"
    ],
    "wof:name":"A & A Autos",
    "wof:placetype":"venue"
},
  "geometry": {"coordinates":[-0.33328,51.503971],"type":"Point"}
}