{
  "type": "Feature",
  "properties": {
    "addr:full":"Alpha House, 646c Kingsbury Road London Greater London NW9 9HN",
    "addr:housenumber":"646c",
    "addr:postcode":"nw9 9hn",
    "addr:street":"Kingsbury Road",
    "iso:country":"GB",
    "sg:address":"Alpha House, 646c Kingsbury Road",
    "sg:city":"London",
    "sg:classifiers":[
        {
            "category":"Real Estate",
            "subcategory":"Real Estate Agent",
            "type":"Services"
        }
    ],
    "sg:postcode":"NW9 9HN",
    "sg:province":"Greater London",
    "wof:name":"Kara Property Ltd",
    "wof:placetype":"venue"
},
  "geometry": {"coordinates":[-0.2804360092,51.5850448608],"type":"Point"}
}