{
  "type": "Feature",
  "properties": {
    "iso:country":"GB",
    "sg:address":"Unit 8 St Davids Centre",
    "sg:city":"Cardiff",
    "sg:classifiers":[
        {
            "category":"Sports & Exercise",
            "subcategory":"Sports Center",
            "type":"Entertainment"
        }
    ],
    "sg:phone":"+44 29 2037 7282",
    "sg:postcode":"CF10 2DQ",
    "sg:province":"Cardiff",
    "sg:tags":[
        "shop",
        "good"
    ],
    "wof:name":"J J B Sports",
    "wof:placetype":"venue"
},
  "geometry": {"coordinates":[-3.180669,51.481258],"type":"Point"}
}