{
  "type": "Feature",
  "properties": {
    "addr:full":"Coseley, Chad Road Bilston West Midlands WV14 9TF",
    "addr:postcode":"wv14 9tf",
    "addr:street":"Coseley Chad Road",
    "iso:country":"GB",
    "sg:address":"Coseley, Chad Road",
    "sg:city":"Bilston",
    "sg:classifiers":[
        {
            "category":"Retail",
            "subcategory":"Auto Repair",
            "type":"Services"
        }
    ],
    "sg:phone":"+44 1902 663611",
    "sg:postcode":"WV14 9TF",
    "sg:province":"West Midlands",
    "sg:tags":[
        "modification",
        "garage"
    ],
    "wof:name":"Chad Road Service Station",
    "wof:placetype":"venue"
},
  "geometry": {"coordinates":[-2.0870840549,52.5408210754],"type":"Point"}
}