{
  "type": "Feature",
  "properties": {
    "iso:country":"GB",
    "sg:address":"228 Cricklade Road",
    "sg:city":"Swindon",
    "sg:classifiers":[
        {
            "category":"Personal",
            "subcategory":"Beauty Salon",
            "type":"Services"
        }
    ],
    "sg:phone":"+44 1793 535575",
    "sg:postcode":"SN2 8AT",
    "sg:province":"Wiltshire",
    "sg:tags":[
        "unisex",
        "hairdresser"
    ],
    "wof:name":"L A Hairport",
    "wof:placetype":"venue"
},
  "geometry": {"coordinates":[-1.777149,51.572899],"type":"Point"}
}