{
  "type": "Feature",
  "properties": {
    "addr:full":"3 Holmstall Parade, Burnt Oak Broadway Edgware Greater London HA8 5HX",
    "addr:housenumber":"3",
    "addr:postcode":"ha8 5hx",
    "addr:street":"Holmstall Parade Burnt Oak Broadway",
    "iso:country":"GB",
    "sg:address":"3 Holmstall Parade, Burnt Oak Broadway",
    "sg:city":"Edgware",
    "sg:classifiers":[
        {
            "category":"Shopping",
            "type":"Retail Goods"
        }
    ],
    "sg:postcode":"HA8 5HX",
    "sg:province":"Greater London",
    "sg:tags":[
        "part",
        "accessory"
    ],
    "wof:name":"Edgware Automobiles",
    "wof:placetype":"venue"
},
  "geometry": {"coordinates":[-0.263355,51.596893],"type":"Point"}
}