{
  "type": "Feature",
  "properties": {
    "addr:full":"Unit 1 Pendleton Business Centre, Lissadel St Salford Greater Manchester M6 6GG",
    "addr:housenumber":"unit 1",
    "addr:postcode":"m6 6gg",
    "addr:street":"Pendleton Business Centre Lissadel St",
    "iso:country":"GB",
    "sg:address":"Unit 1 Pendleton Business Centre, Lissadel St",
    "sg:city":"Salford",
    "sg:classifiers":[
        {
            "category":"Wholesale",
            "subcategory":"Vending Machines",
            "type":"Manufacturing & Wholesale Goods"
        }
    ],
    "sg:phone":"+44 161 743 9996",
    "sg:postcode":"M6 6GG",
    "sg:province":"Greater Manchester",
    "sg:tags":[
        "sale"
    ],
    "wof:name":"B S Vendmaster",
    "wof:placetype":"venue"
},
  "geometry": {"coordinates":[-2.2842988968,53.489730835],"type":"Point"}
}