{
  "type": "Feature",
  "properties": {
    "addr:full":"122 Chalkwell Road Sittingbourne Kent ME10 2LJ",
    "addr:housenumber":"122",
    "addr:postcode":"me10 2lj",
    "addr:street":"Chalkwell Road",
    "iso:country":"GB",
    "sg:address":"122 Chalkwell Road",
    "sg:city":"Sittingbourne",
    "sg:classifiers":[
        {
            "category":"Shopping",
            "type":"Retail Goods"
        }
    ],
    "sg:phone":"+44 1795 472081",
    "sg:postcode":"ME10 2LJ",
    "sg:province":"Kent",
    "sg:tags":[
        "part",
        "accessory"
    ],
    "wof:name":"Team Drive in",
    "wof:placetype":"venue"
},
  "geometry": {"coordinates":[0.725864,51.344368],"type":"Point"}
}