{
  "type": "Feature",
  "properties": {
    "iso:country":"GB",
    "sg:address":"Pixmore Centre, Pixmore Av",
    "sg:city":"Letchworth",
    "sg:classifiers":[
        {
            "category":"Professional",
            "subcategory":"Detective & Security Services",
            "type":"Services"
        }
    ],
    "sg:phone":"+44 1462 483980",
    "sg:postcode":"SG6 1JG",
    "sg:province":"Hertfordshire",
    "sg:tags":[
        "alarm",
        "burglar",
        "system"
    ],
    "wof:name":"Kettleys",
    "wof:placetype":"venue"
},
  "geometry": {"coordinates":[-0.217649,51.981621],"type":"Point"}
}