{
  "type": "Feature",
  "properties": {
    "iso:country":"GB",
    "sg:address":"21 Bond Street",
    "sg:city":"Yeovil",
    "sg:classifiers":[
        {
            "category":"Professional",
            "subcategory":"Computer Services",
            "type":"Services"
        }
    ],
    "sg:postcode":"BA20 1PE",
    "sg:province":"Somerset",
    "sg:tags":[
        "consultant"
    ],
    "wof:name":"Amethyst",
    "wof:placetype":"venue"
},
  "geometry": {"coordinates":[-2.630041,50.940781],"type":"Point"}
}