{
  "type": "Feature",
  "properties": {
    "addr:full":"Po Box 18 Bolton Lancashire BL3 6NH",
    "addr:housenumber":"po box 18",
    "addr:postcode":"bl3 6nh",
    "iso:country":"GB",
    "sg:address":"Po Box 18",
    "sg:city":"Bolton",
    "sg:classifiers":[
        {
            "category":"Professional",
            "subcategory":"Printing & Photocopies",
            "type":"Services"
        }
    ],
    "sg:phone":"+44 1204 521438",
    "sg:postcode":"BL3 6NH",
    "sg:province":"Lancashire",
    "sg:tags":[
        "printer"
    ],
    "wof:name":"Blackshaw Sykes & Morris Ltd.",
    "wof:placetype":"venue"
},
  "geometry": {"coordinates":[-2.4372301102,53.5676994324],"type":"Point"}
}