{
  "type": "Feature",
  "properties": {
    "iso:country":"GB",
    "sg:address":"1 Amersham Mews, Amersham Hill",
    "sg:city":"High Wycombe",
    "sg:classifiers":[
        {
            "category":"Professional",
            "subcategory":"Advertising",
            "type":"Services"
        }
    ],
    "sg:phone":"+44 1494 459581",
    "sg:postcode":"HP13 6NQ",
    "sg:province":"Buckinghamshire",
    "sg:tags":[
        "agency"
    ],
    "wof:name":"T C C Advertising Ltd.",
    "wof:placetype":"venue"
},
  "geometry": {"coordinates":[-0.747789,51.628944],"type":"Point"}
}