{
  "type": "Feature",
  "properties": {
    "addr:full":"The Workshop, North Corston, Coupar Angus Blairgowrie Angus PH13 9JH",
    "addr:postcode":"ph13 9jh",
    "addr:street":"North",
    "iso:country":"GB",
    "sg:address":"The Workshop, North Corston, Coupar Angus",
    "sg:city":"Blairgowrie",
    "sg:classifiers":[
        {
            "category":"Utilities",
            "subcategory":"Natural Gas",
            "type":"Services"
        }
    ],
    "sg:phone":"+44 1828 627557",
    "sg:postcode":"PH13 9JH",
    "sg:province":"Angus",
    "sg:tags":[
        "blacksmith"
    ],
    "wof:name":"James Miller",
    "wof:placetype":"venue"
},
  "geometry": {"coordinates":[-3.266429,56.546135],"type":"Point"}
}