{
  "type": "Feature",
  "properties": {
    "addr:full":"1-3 Quadrant Arcade, 80-82 Regent Street London Greater London W1B 4DZ",
    "addr:housenumber":"1-3;arcade 80-82",
    "addr:postcode":"w1b 4dz",
    "addr:street":"Quadrant;Regent Street",
    "iso:country":"GB",
    "sg:address":"1-3 Quadrant Arcade, 80-82 Regent Street",
    "sg:city":"London",
    "sg:classifiers":[
        {
            "category":"Shopping",
            "subcategory":"Shoes",
            "type":"Retail Goods"
        }
    ],
    "sg:phone":"+44 20 7734 7900",
    "sg:postcode":"W1B 4DZ",
    "sg:province":"Greater London",
    "sg:tags":[
        "shop"
    ],
    "wof:name":"Bella Ricco Management Ltd.",
    "wof:placetype":"venue"
},
  "geometry": {"coordinates":[-0.1399600059,51.5122909546],"type":"Point"}
}