{
  "type": "Feature",
  "properties": {
    "addr:full":"Unit 8 Oldgate, St Michaels Industrial Estate Widnes Cheshire WA8 8TL",
    "addr:housenumber":"unit 8",
    "addr:postcode":"wa8 8tl",
    "addr:street":"Oldgate St;Industrial Estate",
    "iso:country":"GB",
    "sg:address":"Unit 8 Oldgate, St Michaels Industrial Estate",
    "sg:city":"Widnes",
    "sg:classifiers":[
        {
            "category":"Manufacturing",
            "subcategory":"Petroleum Products",
            "type":"Manufacturing & Wholesale Goods"
        },
        {
            "category":"Building & Trades",
            "subcategory":"Construction",
            "type":"Services"
        }
    ],
    "sg:phone":"+44 151 424 7070",
    "sg:postcode":"WA8 8TL",
    "sg:province":"Cheshire",
    "sg:tags":[
        "double",
        "glazier",
        "glazing"
    ],
    "wof:name":"Merseyside Multi-Glazing Ltd.",
    "wof:placetype":"venue"
},
  "geometry": {"coordinates":[-2.7670340538,53.3595657349],"type":"Point"}
}