{
  "type": "Feature",
  "properties": {
    "addr:full":"Franklin Street Hull East Riding of Yorkshire HU9 1JQ",
    "addr:postcode":"hu9 1jq",
    "addr:street":"Franklin Street",
    "iso:country":"GB",
    "sg:address":"Franklin Street",
    "sg:city":"Hull",
    "sg:classifiers":[
        {
            "category":"Organizations",
            "subcategory":"Non-profit Organization",
            "type":"Services"
        }
    ],
    "sg:phone":"+44 1482 226122",
    "sg:postcode":"HU9 1JQ",
    "sg:province":"East Riding of Yorkshire",
    "sg:tags":[
        "organisation",
        "voluntary",
        "charity"
    ],
    "wof:name":"The Salvation Army",
    "wof:placetype":"venue"
},
  "geometry": {"coordinates":[-0.318069011,53.7503433228],"type":"Point"}
}