{
  "type": "Feature",
  "properties": {
    "addr:full":"51 Cleeve Hill Gdns, Waterthorpe Sheffield South Yorkshire S20 7NP",
    "addr:housenumber":"51",
    "addr:postcode":"s20 7np",
    "addr:street":"Cleeve Hill Gdns",
    "iso:country":"GB",
    "sg:address":"51 Cleeve Hill Gdns, Waterthorpe",
    "sg:city":"Sheffield",
    "sg:classifiers":[
        {
            "category":"Manufacturing",
            "subcategory":"Petroleum Products",
            "type":"Manufacturing & Wholesale Goods"
        }
    ],
    "sg:postcode":"S20 7NP",
    "sg:province":"South Yorkshire",
    "sg:tags":[
        "double",
        "glazing"
    ],
    "wof:name":"Premier Windows",
    "wof:placetype":"venue"
},
  "geometry": {"coordinates":[-1.3454339504,53.3369789124],"type":"Point"}
}