{
  "type": "Feature",
  "properties": {
    "addr:full":"15 Westhill, Elstead Godalming Surrey GU8 6DQ",
    "addr:housenumber":"15",
    "addr:postcode":"gu8 6dq",
    "addr:street":"Westhill Elstead",
    "iso:country":"GB",
    "sg:address":"15 Westhill, Elstead",
    "sg:city":"Godalming",
    "sg:classifiers":[
        {
            "category":"Building & Trades",
            "subcategory":"Construction",
            "type":"Services"
        }
    ],
    "sg:postcode":"GU8 6DQ",
    "sg:province":"Surrey",
    "sg:tags":[
        "builder"
    ],
    "wof:name":"Specialists in Brickwork & Stonework",
    "wof:placetype":"venue"
},
  "geometry": {"coordinates":[-0.7070400119,51.1819496155],"type":"Point"}
}