{
  "type": "Feature",
  "properties": {
    "addr:full":"10 Norfolk Road Sheffield South Yorkshire S2 2SX",
    "addr:housenumber":"10",
    "addr:postcode":"s2 2sx",
    "addr:street":"Norfolk Road",
    "iso:country":"GB",
    "sg:address":"10 Norfolk Road",
    "sg:city":"Sheffield",
    "sg:classifiers":[
        {
            "category":"Health Services",
            "subcategory":"Nursing And Care Facility",
            "type":"Services"
        },
        {
            "category":"Social Services",
            "subcategory":"Retirement Home",
            "type":"Services"
        }
    ],
    "sg:phone":"+44 114 272 2245",
    "sg:postcode":"S2 2SX",
    "sg:province":"South Yorkshire",
    "sg:tags":[
        "residential"
    ],
    "wof:name":"Mental After Care Association",
    "wof:placetype":"venue"
},
  "geometry": {"coordinates":[-1.458966,53.37756],"type":"Point"}
}