{
  "type": "Feature",
  "properties": {
    "iso:country":"GB",
    "sg:address":"Chapel Lane, Werrington",
    "sg:city":"Peterborough",
    "sg:classifiers":[
        {
            "category":"Retail",
            "subcategory":"Auto Repair",
            "type":"Services"
        }
    ],
    "sg:phone":"+44 1733 328013",
    "sg:postcode":"PE4 6RS",
    "sg:province":"Cambridgeshire",
    "sg:tags":[
        "body",
        "car"
    ],
    "wof:name":"Auto Crash Centre Ltd.",
    "wof:placetype":"venue"
},
  "geometry": {"coordinates":[-0.2710889876,52.6142539978],"type":"Point"}
}