{
  "type": "Feature",
  "properties": {
    "iso:country":"GB",
    "sg:address":"The Bungalow, Newby Crescent",
    "sg:city":"Harrogate",
    "sg:classifiers":[
        {
            "category":"Professional",
            "subcategory":"Art Services",
            "type":"Services"
        }
    ],
    "sg:postcode":"HG3 2TT",
    "sg:province":"North Yorkshire",
    "sg:tags":[
        "model",
        "maker"
    ],
    "wof:name":"Emperor Design Studio",
    "wof:placetype":"venue"
},
  "geometry": {"coordinates":[-1.606377,54.022778],"type":"Point"}
}