{
  "type": "Feature",
  "properties": {
    "addr:full":"39 Reigate Road, Hookwood Horley Surrey RH6 0HL",
    "addr:housenumber":"39",
    "addr:postcode":"rh6 0hl",
    "addr:street":"Reigate Road",
    "iso:country":"GB",
    "sg:address":"39 Reigate Road, Hookwood",
    "sg:city":"Horley",
    "sg:classifiers":[
        {
            "category":"Professional",
            "subcategory":"Engineering",
            "type":"Services"
        },
        {
            "category":"Building & Trades",
            "subcategory":"Electrical",
            "type":"Services"
        }
    ],
    "sg:phone":"+44 1293 783193",
    "sg:postcode":"RH6 0HL",
    "sg:province":"Surrey",
    "sg:tags":[
        "engineer",
        "electrician",
        "contractor"
    ],
    "wof:name":"Powerite Electrical",
    "wof:placetype":"venue"
},
  "geometry": {"coordinates":[-0.1959829926,51.1882400513],"type":"Point"}
}