{
  "type": "Feature",
  "properties": {
    "iso:country":"GB",
    "sg:address":"67 Uplands Road",
    "sg:city":"London",
    "sg:classifiers":[
        {
            "category":"Building & Trades",
            "subcategory":"Landscaping Services",
            "type":"Services"
        }
    ],
    "sg:phone":"+44 20 8341 4539",
    "sg:postcode":"N8 9NH",
    "sg:province":"Greater London",
    "sg:tags":[
        "forestry",
        "surgeon",
        "tree"
    ],
    "wof:name":"Gibbs & Haynes",
    "wof:placetype":"venue"
},
  "geometry": {"coordinates":[-0.1112419963,51.5803489685],"type":"Point"}
}