{
  "type": "Feature",
  "properties": {
    "iso:country":"GB",
    "sg:address":"10 Bowling Road",
    "sg:city":"Ware",
    "sg:classifiers":[
        {
            "category":"Recreation",
            "subcategory":"Fishing",
            "type":"Entertainment"
        }
    ],
    "sg:phone":"+44 1920 462658",
    "sg:postcode":"SG12 7EE",
    "sg:province":"Hertfordshire",
    "sg:tags":[
        "equipment",
        "angling"
    ],
    "wof:name":"R Chapman & Co.",
    "wof:placetype":"venue"
},
  "geometry": {"coordinates":[-0.02674,51.810848],"type":"Point"}
}