{
  "type": "Feature",
  "properties": {
    "iso:country":"GB",
    "sg:address":"5 Rossett Avenue",
    "sg:city":"Harrogate",
    "sg:classifiers":[
        {
            "category":"Retail",
            "subcategory":"Driving School",
            "type":"Services"
        }
    ],
    "sg:phone":"+44 1423 872810",
    "sg:postcode":"HG2 9NA",
    "sg:province":"North Yorkshire",
    "wof:name":"Rossett Green School of Motoring",
    "wof:placetype":"venue"
},
  "geometry": {"coordinates":[-1.549179,53.973766],"type":"Point"}
}