{
  "type": "Feature",
  "properties": {
    "addr:full":"2 West Way, Carshalton Beeches Carshalton Surrey SM5 4EW",
    "addr:housenumber":"2",
    "addr:postcode":"sm5 4ew",
    "addr:street":"West Way",
    "iso:country":"GB",
    "sg:address":"2 West Way, Carshalton Beeches",
    "sg:city":"Carshalton",
    "sg:classifiers":[
        {
            "category":"Professional",
            "type":"Services"
        }
    ],
    "sg:postcode":"SM5 4EW",
    "sg:province":"Surrey",
    "sg:tags":[
        "entertainer"
    ],
    "wof:name":"Stevan Magical Entertainer",
    "wof:placetype":"venue"
},
  "geometry": {"coordinates":[-0.178429,51.34568],"type":"Point"}
}