{
  "type": "Feature",
  "properties": {
    "addr:full":"45 Station Road Ashington Northumberland NE63 9XE",
    "addr:housenumber":"45",
    "addr:postcode":"ne63 9xe",
    "addr:street":"Station Road;Northumberland",
    "iso:country":"GB",
    "sg:address":"45 Station Road",
    "sg:city":"Ashington",
    "sg:classifiers":[
        {
            "category":"Cinema",
            "subcategory":"Movie Rental",
            "type":"Entertainment"
        }
    ],
    "sg:phone":"+44 1670 817559",
    "sg:postcode":"NE63 9XE",
    "sg:province":"Northumberland",
    "sg:tags":[
        "video",
        "library"
    ],
    "wof:name":"Global Video (Uk) Ltd.",
    "wof:placetype":"venue"
},
  "geometry": {"coordinates":[-1.572691,55.183575],"type":"Point"}
}