{
  "type": "Feature",
  "properties": {
    "addr:full":"Holly Court 43 St. Modwen Road Plymouth Devon PL6 8LG",
    "addr:housenumber":"43",
    "addr:postcode":"pl6 8lg",
    "addr:street":"Holly Court;Modwen Road",
    "iso:country":"GB",
    "sg:address":"Holly Court 43 St. Modwen Road",
    "sg:city":"Plymouth",
    "sg:classifiers":[
        {
            "category":"Professional",
            "subcategory":"Computer Services",
            "type":"Services"
        }
    ],
    "sg:phone":"+44 1752 255226",
    "sg:postcode":"PL6 8LG",
    "sg:province":"Devon",
    "sg:tags":[
        "system",
        "software"
    ],
    "wof:name":"Technosmiths",
    "wof:placetype":"venue"
},
  "geometry": {"coordinates":[-4.089261,50.39518],"type":"Point"}
}