{
  "type": "Feature",
  "properties": {
    "iso:country":"GB",
    "sg:address":"9 Parham Walk, Grange Park",
    "sg:city":"Swindon",
    "sg:classifiers":[
        {
            "category":"Government",
            "subcategory":"Post Office",
            "type":"Public Place"
        }
    ],
    "sg:phone":"+44 1793 874630",
    "sg:postcode":"SN5 6EQ",
    "sg:province":"Wiltshire",
    "sg:tags":[
        "messenger",
        "courier"
    ],
    "wof:name":"Rod Leverton",
    "wof:placetype":"venue"
},
  "geometry": {"coordinates":[-1.846304,51.55518],"type":"Point"}
}