{
  "type": "Feature",
  "properties": {
    "addr:full":"56 Norfolk Street Liverpool Merseyside L1 0BE",
    "addr:housenumber":"56",
    "addr:postcode":"l1 0be",
    "addr:street":"Norfolk Street",
    "iso:country":"GB",
    "sg:address":"56 Norfolk Street",
    "sg:city":"Liverpool",
    "sg:classifiers":[
        {
            "category":"Shopping",
            "subcategory":"Crafts & Fabrics",
            "type":"Retail Goods"
        },
        {
            "category":"Home & Garden",
            "subcategory":"Carpets & Floor Coverings",
            "type":"Retail Goods"
        }
    ],
    "sg:phone":"+44 151 709 7034",
    "sg:postcode":"L1 0BE",
    "sg:province":"Merseyside",
    "sg:tags":[
        "retailer",
        "rug",
        "proofing"
    ],
    "wof:name":"LATEX COATING WORKS",
    "wof:placetype":"venue"
},
  "geometry": {"coordinates":[-2.9807949066,53.3963432312],"type":"Point"}
}