{
  "type": "Feature",
  "properties": {
    "iso:country":"GB",
    "sg:address":"14a Feckenham Rd",
    "sg:city":"Redditch",
    "sg:classifiers":[
        {
            "category":"Professional",
            "subcategory":"Employment Agencies",
            "type":"Services"
        }
    ],
    "sg:phone":"+44 1527 894200",
    "sg:postcode":"B96 6DS",
    "sg:province":"Warwickshire",
    "sg:tags":[
        "consultant"
    ],
    "wof:name":"Ridgeway Staff Agency",
    "wof:placetype":"venue"
},
  "geometry": {"coordinates":[-1.939358,52.260433],"type":"Point"}
}