{
  "type": "Feature",
  "properties": {
    "iso:country":"GB",
    "sg:address":"367 Cambridge Heath Road",
    "sg:city":"London",
    "sg:classifiers":[
        {
            "category":"Shopping",
            "subcategory":"Clothing, Apparel, & Fashions",
            "type":"Retail Goods"
        }
    ],
    "sg:phone":"+44 20 7739 5552",
    "sg:postcode":"E2 9RA",
    "sg:province":"Greater London",
    "sg:tags":[
        "clothing"
    ],
    "wof:name":"Eran Ltd.",
    "wof:placetype":"venue"
},
  "geometry": {"coordinates":[-0.056292,51.529968],"type":"Point"}
}