{
  "type": "Feature",
  "properties": {
    "iso:country":"GB",
    "sg:address":"314 Prestwood Road",
    "sg:city":"Wolverhampton",
    "sg:classifiers":[
        {
            "category":"Shopping",
            "subcategory":"News",
            "type":"Retail Goods"
        }
    ],
    "sg:phone":"+44 1902 732152",
    "sg:postcode":"WV11 1RH",
    "sg:province":"Staffordshire",
    "sg:tags":[
        "newsagent"
    ],
    "wof:name":"S & M Newsagents",
    "wof:placetype":"venue"
},
  "geometry": {"coordinates":[-2.099376,52.60297],"type":"Point"}
}