{
  "type": "Feature",
  "properties": {
    "addr:full":"Suite B303, Lees Lane Gosport Hampshire PO12 3UL",
    "addr:housenumber":"b303",
    "addr:postcode":"po12 3ul",
    "addr:street":"Lees Lane",
    "iso:country":"GB",
    "sg:address":"Suite B303, Lees Lane",
    "sg:city":"Gosport",
    "sg:classifiers":[
        {
            "category":"Professional",
            "subcategory":"Computer Services",
            "type":"Services"
        }
    ],
    "sg:phone":"+44 23 9236 7123",
    "sg:postcode":"PO12 3UL",
    "sg:province":"Hampshire",
    "sg:tags":[
        "system",
        "software"
    ],
    "wof:name":"Database Logistics",
    "wof:placetype":"venue"
},
  "geometry": {"coordinates":[-1.142537,50.799255],"type":"Point"}
}