{
  "type": "Feature",
  "properties": {
    "iso:country":"GB",
    "sg:address":"Snipe Lane",
    "sg:city":"Darlington",
    "sg:classifiers":[
        {
            "category":"Sports & Exercise",
            "subcategory":"Golf",
            "type":"Entertainment"
        }
    ],
    "sg:phone":"+44 1325 461002",
    "sg:postcode":"DL2 2SA",
    "sg:province":"Durham",
    "sg:tags":[
        "club",
        "equipment"
    ],
    "wof:name":"Stressholme Golf Centre",
    "wof:placetype":"venue"
},
  "geometry": {"coordinates":[-1.562871,54.50737],"type":"Point"}
}