{
  "type": "Feature",
  "properties": {
    "iso:country":"GB",
    "sg:address":"57 Cricklade Street",
    "sg:city":"Cirencester",
    "sg:classifiers":[
        {
            "category":"Shopping",
            "subcategory":"Baby Store",
            "type":"Retail Goods"
        }
    ],
    "sg:postcode":"GL7 1HY",
    "sg:province":"Gloucestershire",
    "sg:tags":[
        "babywear",
        "childrens"
    ],
    "wof:name":"Chatterbox",
    "wof:placetype":"venue"
},
  "geometry": {"coordinates":[-1.967327,51.715843],"type":"Point"}
}