{
  "type": "Feature",
  "properties": {
    "addr:full":"Unit 2 Northchurch London Greater London SE17 2AQ",
    "addr:housenumber":"unit 2",
    "addr:postcode":"se17 2aq",
    "iso:country":"GB",
    "sg:address":"Unit 2 Northchurch",
    "sg:city":"London",
    "sg:classifiers":[
        {
            "category":"Shopping",
            "subcategory":"News",
            "type":"Retail Goods"
        }
    ],
    "sg:phone":"+44 20 7703 4710",
    "sg:postcode":"SE17 2AQ",
    "sg:province":"Greater London",
    "sg:tags":[
        "newsagent"
    ],
    "wof:name":"Lees Newsagents",
    "wof:placetype":"venue"
},
  "geometry": {"coordinates":[-0.086964,51.48782],"type":"Point"}
}