{
  "type": "Feature",
  "properties": {
    "iso:country":"GB",
    "sg:address":"9 Roundway",
    "sg:city":"Egham",
    "sg:classifiers":[
        {
            "category":"Professional",
            "subcategory":"Secretarial Services",
            "type":"Services"
        }
    ],
    "sg:postcode":"TW20 8BS",
    "sg:province":"Surrey",
    "wof:name":"Type Right",
    "wof:placetype":"venue"
},
  "geometry": {"coordinates":[-0.5282170177,51.4296226501],"type":"Point"}
}