{
  "type": "Feature",
  "properties": {
    "addr:full":"32 Hampden Rd Hornsey Greater London N8 0HT",
    "addr:housenumber":"32",
    "addr:postcode":"n8 0ht",
    "addr:street":"Hampden Rd",
    "iso:country":"GB",
    "sg:address":"32 Hampden Rd",
    "sg:city":"Hornsey",
    "sg:classifiers":[
        {
            "category":"Professional",
            "subcategory":"Computer Services",
            "type":"Services"
        }
    ],
    "sg:phone":"+44 20 8340 4675",
    "sg:postcode":"N8 0HT",
    "sg:province":"Greater London",
    "sg:tags":[
        "consultant"
    ],
    "wof:name":"SoftAware Training",
    "wof:placetype":"venue"
},
  "geometry": {"coordinates":[-0.107018,51.587311],"type":"Point"}
}