{
  "type": "Feature",
  "properties": {
    "iso:country":"GB",
    "sg:address":"Wolsey Business Park, Railton Rd",
    "sg:city":"Bedford",
    "sg:classifiers":[
        {
            "category":"Professional",
            "type":"Services"
        }
    ],
    "sg:phone":"+44 1234 400444",
    "sg:postcode":"MK42 7PW",
    "sg:province":"Bedfordshire",
    "sg:tags":[
        "repair",
        "tech",
        "maintenance"
    ],
    "wof:name":"Crimson Eight Computer Repairs",
    "wof:placetype":"venue"
},
  "geometry": {"coordinates":[-0.4979700148,52.1060295105],"type":"Point"}
}