{
  "type": "Feature",
  "properties": {
    "iso:country":"GB",
    "sg:address":"201 London Rd East, Batheaston",
    "sg:city":"Bath",
    "sg:classifiers":[
        {
            "category":"Utilities",
            "type":"Services"
        }
    ],
    "sg:phone":"+44 1225 851177",
    "sg:postcode":"BA1 7NB",
    "sg:province":"Bath and North East Somerset",
    "sg:tags":[
        "internet"
    ],
    "wof:name":"Worldwide Internet Services",
    "wof:placetype":"venue"
},
  "geometry": {"coordinates":[-2.318327,51.405769],"type":"Point"}
}