{
  "type": "Feature",
  "properties": {
    "iso:country":"GB",
    "sg:address":"Main Street",
    "sg:city":"Bridge Of Weir",
    "sg:classifiers":[
        {
            "category":"Place Of Worship",
            "type":"Public Place"
        },
        {
            "category":"Organizations",
            "subcategory":"Non-profit Organization",
            "type":"Services"
        }
    ],
    "sg:phone":"+44 1505 612610",
    "sg:postcode":"PA11 3NR",
    "sg:province":"Inverclyde",
    "sg:tags":[
        "charitable",
        "organisation",
        "charity"
    ],
    "wof:name":"FREELAND CHURCH",
    "wof:placetype":"venue"
},
  "geometry": {"coordinates":[-4.582529,55.85672],"type":"Point"}
}