{
  "type": "Feature",
  "properties": {
    "addr:full":"8 Station Parade, Ockham Road South, East Horsley Leatherhead Surrey KT24 6QN",
    "addr:housenumber":"8",
    "addr:postcode":"kt24 6qn",
    "addr:street":"Station Parade Ockham Road",
    "iso:country":"GB",
    "sg:address":"8 Station Parade, Ockham Road South, East Horsley",
    "sg:city":"Leatherhead",
    "sg:classifiers":[
        {
            "category":"Restaurant",
            "type":"Food & Drink"
        }
    ],
    "sg:phone":"+44 1483 282208",
    "sg:postcode":"KT24 6QN",
    "sg:province":"Surrey",
    "sg:tags":[
        "-",
        "chinese"
    ],
    "wof:name":"Laughing Buddha Chinese Restaurant",
    "wof:placetype":"venue"
},
  "geometry": {"coordinates":[-0.43549,51.277248],"type":"Point"}
}