{
  "type": "Feature",
  "properties": {
    "addr:full":"1a The Rookery Newmarket Cambridgeshire CB8 8EQ",
    "addr:housenumber":"1a",
    "addr:postcode":"cb8 8eq",
    "addr:street":"The Rookery Newmarket",
    "iso:country":"GB",
    "sg:address":"1a The Rookery",
    "sg:city":"Newmarket",
    "sg:classifiers":[
        {
            "category":"Education",
            "subcategory":"Library",
            "type":"Public Place"
        },
        {
            "category":"Government",
            "subcategory":"Office",
            "type":"Public Place"
        }
    ],
    "sg:phone":"+44 1638 661216",
    "sg:postcode":"CB8 8EQ",
    "sg:province":"Cambridgeshire",
    "sg:tags":[
        "book",
        "local"
    ],
    "wof:name":"Newmarket Library",
    "wof:placetype":"venue"
},
  "geometry": {"coordinates":[0.399166,52.249817],"type":"Point"}
}