{
  "type": "Feature",
  "properties": {
    "addr:full":"Taplow Court, Taplow Maidenhead Berkshire SL6 0ER",
    "addr:postcode":"sl6 0er",
    "addr:street":"Taplow Court",
    "iso:country":"GB",
    "sg:address":"Taplow Court, Taplow",
    "sg:city":"Maidenhead",
    "sg:classifiers":[
        {
            "category":"Organizations",
            "subcategory":"Religious Organization",
            "type":"Services"
        }
    ],
    "sg:phone":"+44 1628 773163",
    "sg:postcode":"SL6 0ER",
    "sg:province":"Berkshire",
    "sg:tags":[
        "organisation"
    ],
    "wof:name":"Soka Gakkai International U K",
    "wof:placetype":"venue"
},
  "geometry": {"coordinates":[-0.668666,51.522289],"type":"Point"}
}