{
  "type": "Feature",
  "properties": {
    "iso:country":"GB",
    "sg:address":"27 Woodchurch Rd",
    "sg:city":"Birkenhead",
    "sg:classifiers":[
        {
            "category":"Home & Garden",
            "subcategory":"Household Appliances",
            "type":"Retail Goods"
        }
    ],
    "sg:phone":"+44 151 652 1581",
    "sg:postcode":"CH42 9LG",
    "sg:province":"Merseyside",
    "sg:tags":[
        "refrigeration",
        "air conditioning"
    ],
    "wof:name":"Wirral Refrigeration Ltd",
    "wof:placetype":"venue"
},
  "geometry": {"coordinates":[-3.0364100933,53.3831672668],"type":"Point"}
}