{
  "type": "Feature",
  "properties": {
    "iso:country":"GB",
    "sg:address":"106-108 Radstock Road",
    "sg:city":"Southampton",
    "sg:classifiers":[
        {
            "category":"Social Services",
            "subcategory":"Retirement Home",
            "type":"Services"
        }
    ],
    "sg:phone":"+44 23 8044 5310",
    "sg:postcode":"SO19 2HU",
    "sg:province":"Hampshire",
    "sg:tags":[
        "residential",
        "care"
    ],
    "wof:name":"Avondale Residential Home",
    "wof:placetype":"venue"
},
  "geometry": {"coordinates":[-1.369171,50.898872],"type":"Point"}
}