{
  "type": "Feature",
  "properties": {
    "iso:country":"GB",
    "sg:address":"11-15 Furmage St",
    "sg:city":"Wandsworth",
    "sg:classifiers":[
        {
            "category":"Building & Trades",
            "subcategory":"Plumbing",
            "type":"Services"
        }
    ],
    "sg:phone":"+44 20 8874 2361",
    "sg:postcode":"SW18 4DF",
    "sg:province":"Greater London",
    "sg:tags":[
        "merchant",
        "plumbers'"
    ],
    "wof:name":"W.S McDonald & Son",
    "wof:placetype":"venue"
},
  "geometry": {"coordinates":[-0.190746,51.449554],"type":"Point"}
}