{
  "type": "Feature",
  "properties": {
    "addr:full":"9-11 Wellington Road Blackpool Lancashire FY1 6AR",
    "addr:housenumber":"9-11",
    "addr:postcode":"fy1 6ar",
    "addr:street":"Wellington Road",
    "iso:country":"GB",
    "sg:address":"9-11 Wellington Road",
    "sg:city":"Blackpool",
    "sg:classifiers":[
        {
            "category":"Travel",
            "subcategory":"Hotels & Motels",
            "type":"Entertainment"
        }
    ],
    "sg:phone":"+44 1253 346606",
    "sg:postcode":"FY1 6AR",
    "sg:province":"Lancashire",
    "wof:name":"Douglas Hotel",
    "wof:placetype":"venue"
},
  "geometry": {"coordinates":[-3.053932,53.80389],"type":"Point"}
}