{
  "type": "Feature",
  "properties": {
    "iso:country":"GB",
    "sg:address":"2 Warwick Road",
    "sg:city":"Kenilworth",
    "sg:classifiers":[
        {
            "category":"Community Center",
            "subcategory":"Social",
            "type":"Public Place"
        }
    ],
    "sg:phone":"+44 1926 852786",
    "sg:postcode":"CV8 1HB",
    "sg:province":"Warwickshire",
    "sg:tags":[
        "frozen",
        "food",
        "freezer",
        "centre"
    ],
    "wof:name":"Iceland Frozen Foods",
    "wof:placetype":"venue"
},
  "geometry": {"coordinates":[-1.5791159868,52.3424911499],"type":"Point"}
}