{
  "type": "Feature",
  "properties": {
    "iso:country":"GB",
    "sg:address":"1 Forester Road",
    "sg:city":"Bath",
    "sg:classifiers":[
        {
            "category":"Travel",
            "subcategory":"Hotels & Motels",
            "type":"Entertainment"
        }
    ],
    "sg:phone":"+44 1225 310132",
    "sg:postcode":"BA2 6QF",
    "sg:province":"Somerset",
    "sg:tags":[
        "house",
        "guest"
    ],
    "sg:website":"http://www.visitus.co.uk",
    "wof:name":"Greenways",
    "wof:placetype":"venue"
},
  "geometry": {"coordinates":[-2.350748,51.387432],"type":"Point"}
}