{
  "type": "Feature",
  "properties": {
    "iso:country":"GB",
    "sg:address":"Unit 11, Brittania Enterprise Centre",
    "sg:city":"Hastings",
    "sg:classifiers":[
        {
            "category":"Building & Trades",
            "subcategory":"Construction",
            "type":"Services"
        },
        {
            "category":"Manufacturing",
            "subcategory":"Building Materials",
            "type":"Manufacturing & Wholesale Goods"
        }
    ],
    "sg:postcode":"TN34 1RT",
    "sg:province":"East Sussex",
    "sg:tags":[
        "stonemason",
        "monumental",
        "mason"
    ],
    "wof:name":"Stoneworks",
    "wof:placetype":"venue"
},
  "geometry": {"coordinates":[0.578698,50.85619],"type":"Point"}
}