{
  "type": "Feature",
  "properties": {
    "iso:country":"GB",
    "sg:address":"12a St Nicholas Court",
    "sg:city":"North Walsham",
    "sg:classifiers":[
        {
            "category":"Shopping",
            "subcategory":"Clothing, Apparel, & Fashions",
            "type":"Retail Goods"
        }
    ],
    "sg:phone":"+44 1692 406179",
    "sg:postcode":"NR28 9BY",
    "sg:province":"Norfolk",
    "sg:tags":[
        "ladieswear"
    ],
    "wof:name":"Tiffanys",
    "wof:placetype":"venue"
},
  "geometry": {"coordinates":[1.3962060213,52.8193092346],"type":"Point"}
}