{
  "type": "Feature",
  "properties": {
    "addr:full":"Stockton-on-tees B C, Contract Svcs, Thornaby Road Stockton-on-tees Durham TS17 8AA",
    "addr:postcode":"ts17 8aa",
    "addr:street":"Thornaby Road",
    "iso:country":"GB",
    "sg:address":"Stockton-on-tees B C, Contract Svcs, Thornaby Road",
    "sg:city":"Stockton-on-tees",
    "sg:classifiers":[
        {
            "category":"Government",
            "subcategory":"Office",
            "type":"Public Place"
        },
        {
            "category":"Sports & Exercise",
            "subcategory":"Swimming Pool",
            "type":"Entertainment"
        }
    ],
    "sg:phone":"+44 1642 616727",
    "sg:postcode":"TS17 8AA",
    "sg:province":"Durham",
    "sg:tags":[
        "local"
    ],
    "wof:name":"Thornaby Swimming Pool",
    "wof:placetype":"venue"
},
  "geometry": {"coordinates":[-1.30602,54.550419],"type":"Point"}
}