{
  "type": "Feature",
  "properties": {
    "iso:country":"GB",
    "sg:address":"72 Delancey St",
    "sg:city":"Camden",
    "sg:classifiers":[
        {
            "category":"Travel",
            "subcategory":"Hostel",
            "type":"Entertainment"
        }
    ],
    "sg:phone":"+44 20 7482 0907",
    "sg:postcode":"NW1 7SA",
    "sg:province":"Greater London",
    "wof:name":"Delancey House",
    "wof:placetype":"venue"
},
  "geometry": {"coordinates":[-0.1449110061,51.536491394],"type":"Point"}
}