{
  "type": "Feature",
  "properties": {
    "addr:full":"12 Tyersal Ave Bradford West Yorkshire BD4 8HH",
    "addr:housenumber":"12",
    "addr:postcode":"bd4 8hh",
    "addr:street":"Tyersal Ave",
    "iso:country":"GB",
    "sg:address":"12 Tyersal Ave",
    "sg:city":"Bradford",
    "sg:classifiers":[
        {
            "category":"Manufacturing",
            "subcategory":"Glass & Minerals",
            "type":"Manufacturing & Wholesale Goods"
        }
    ],
    "sg:postcode":"BD4 8HH",
    "sg:province":"West Yorkshire",
    "sg:tags":[
        "stained"
    ],
    "wof:name":"Hicks,Philip,",
    "wof:placetype":"venue"
},
  "geometry": {"coordinates":[-1.70183599,53.7915534973],"type":"Point"}
}