{
  "type": "Feature",
  "properties": {
    "iso:country":"GB",
    "sg:address":"Day House, Shray Hill",
    "sg:city":"Telford",
    "sg:classifiers":[
        {
            "category":"Home & Garden",
            "subcategory":"Garden Supply",
            "type":"Retail Goods"
        },
        {
            "category":"Farming",
            "subcategory":"Livestock Farm",
            "type":"Manufacturing & Wholesale Goods"
        }
    ],
    "sg:postcode":"TF6 6JT",
    "sg:province":"Shropshire",
    "sg:tags":[
        "bulb",
        "grower",
        "others"
    ],
    "wof:name":"J B Crow",
    "wof:placetype":"venue"
},
  "geometry": {"coordinates":[-2.50612,52.770439],"type":"Point"}
}