{
  "type": "Feature",
  "properties": {
    "iso:country":"GB",
    "sg:address":"Lake Road",
    "sg:city":"Windermere",
    "sg:classifiers":[
        {
            "category":"Travel",
            "subcategory":"Hotels & Motels",
            "type":"Entertainment"
        }
    ],
    "sg:postcode":"LA23 2JA",
    "sg:province":"Cumbria",
    "sg:tags":[
        "house",
        "guest"
    ],
    "wof:name":"Oakleigh Guest House",
    "wof:placetype":"venue"
},
  "geometry": {"coordinates":[-2.90837,54.373379],"type":"Point"}
}