{
  "type": "Feature",
  "properties": {
    "addr:full":"18-20 Lewis Street Stornoway Eilean Siar HS1 2JF",
    "addr:housenumber":"18-20",
    "addr:postcode":"hs1 2jf",
    "addr:street":"Lewis Street",
    "iso:country":"GB",
    "sg:address":"18-20 Lewis Street",
    "sg:city":"Stornoway",
    "sg:classifiers":[
        {
            "category":"Manufacturing",
            "subcategory":"Lumber",
            "type":"Manufacturing & Wholesale Goods"
        }
    ],
    "sg:phone":"+44 1851 702160",
    "sg:postcode":"HS1 2JF",
    "sg:province":"Eilean Siar",
    "sg:tags":[
        "importer",
        "merchants",
        "agent",
        "timber"
    ],
    "wof:name":"Morrison Bain & Co. Ltd.",
    "wof:placetype":"venue"
},
  "geometry": {"coordinates":[-6.3846001625,58.2105751038],"type":"Point"}
}