{
  "type": "Feature",
  "properties": {
    "addr:full":"12 Manderston Street Edinburgh City of Edinburgh EH6 8LY",
    "addr:housenumber":"12",
    "addr:postcode":"eh6 8ly",
    "addr:street":"Manderston Street",
    "iso:country":"GB",
    "sg:address":"12 Manderston Street",
    "sg:city":"Edinburgh",
    "sg:classifiers":[
        {
            "category":"Manufacturing",
            "subcategory":"Metals",
            "type":"Manufacturing & Wholesale Goods"
        },
        {
            "category":"Utilities",
            "subcategory":"Natural Gas",
            "type":"Services"
        }
    ],
    "sg:phone":"+44 131 554 6501",
    "sg:postcode":"EH6 8LY",
    "sg:province":"City of Edinburgh",
    "sg:tags":[
        "blacksmith",
        "forgemasters"
    ],
    "wof:name":"R Thompson & Co",
    "wof:placetype":"venue"
},
  "geometry": {"coordinates":[-3.1723220348,55.9688415527],"type":"Point"}
}