{
  "type": "Feature",
  "properties": {
    "addr:full":"88 Abyfields, Rangly Telford Shropshire TF3 2AU",
    "addr:housenumber":"88",
    "addr:postcode":"tf3 2au",
    "addr:street":"Abyfields Rangly",
    "iso:country":"GB",
    "sg:address":"88 Abyfields, Rangly",
    "sg:city":"Telford",
    "sg:classifiers":[
        {
            "category":"Professional",
            "subcategory":"Art Services",
            "type":"Services"
        }
    ],
    "sg:phone":"+44 1952 595665",
    "sg:postcode":"TF3 2AU",
    "sg:province":"Shropshire",
    "sg:tags":[
        "photographer"
    ],
    "wof:name":"D & J Jones Photography",
    "wof:placetype":"venue"
},
  "geometry": {"coordinates":[-2.44176507,52.6766624451],"type":"Point"}
}