{
  "type": "Feature",
  "properties": {
    "addr:full":"29 Grove Hill Road Tunbridge Wells Kent TN1 1SD",
    "addr:housenumber":"29",
    "addr:postcode":"tn1 1sd",
    "addr:street":"Grove Hill Road",
    "iso:country":"GB",
    "sg:address":"29 Grove Hill Road",
    "sg:city":"Tunbridge Wells",
    "sg:classifiers":[
        {
            "category":"Food & Beverages",
            "subcategory":"Groceries & Convenience Stores",
            "type":"Retail Goods"
        }
    ],
    "sg:phone":"+44 1892 532871",
    "sg:postcode":"TN1 1SD",
    "sg:province":"Kent",
    "wof:name":"Masra Bros",
    "wof:placetype":"venue"
},
  "geometry": {"coordinates":[0.2647500038,51.1293411255],"type":"Point"}
}