{
  "type": "Feature",
  "properties": {
    "iso:country":"GB",
    "sg:address":"A36, Troebridge Road",
    "sg:city":"Bath",
    "sg:classifiers":[
        {
            "category":"Restaurant",
            "type":"Food & Drink"
        }
    ],
    "sg:phone":"+44 1373 830192",
    "sg:postcode":"BA1 1TY",
    "sg:province":"Bath and North East Somerset",
    "wof:name":"Little Chef",
    "wof:placetype":"venue"
},
  "geometry": {"coordinates":[-2.3565709591,51.389881134],"type":"Point"}
}