{
  "type": "Feature",
  "properties": {
    "addr:full":"Marshmoor, Travellers Lane, Welham Green Hatfield Hertfordshire AL9 7HN",
    "addr:postcode":"al9 7hn",
    "addr:street":"Travellers Lane",
    "iso:country":"GB",
    "sg:address":"Marshmoor, Travellers Lane, Welham Green",
    "sg:city":"Hatfield",
    "sg:classifiers":[
        {
            "category":"Professional",
            "subcategory":"Engineering",
            "type":"Services"
        }
    ],
    "sg:phone":"+44 1707 272516",
    "sg:postcode":"AL9 7HN",
    "sg:province":"Hertfordshire",
    "sg:tags":[
        "civil",
        "engineer"
    ],
    "wof:name":"Mabey Construction Co Ltd",
    "wof:placetype":"venue"
},
  "geometry": {"coordinates":[-0.213064,51.738243103],"type":"Point"}
}