{
  "type": "Feature",
  "properties": {
    "iso:country":"GB",
    "sg:address":"214 London Road, Balderton",
    "sg:city":"Newark",
    "sg:classifiers":[
        {
            "category":"Military Area",
            "subcategory":"Air Force Base",
            "type":"Public Place"
        }
    ],
    "sg:postcode":"NG24 3HD",
    "sg:province":"Nottinghamshire",
    "sg:tags":[
        "taxi",
        "hire",
        "private"
    ],
    "wof:name":"Alpha Cabs",
    "wof:placetype":"venue"
},
  "geometry": {"coordinates":[-0.784415,53.055885],"type":"Point"}
}