{
  "type": "Feature",
  "properties": {
    "addr:full":"131 Radford Road Coventry Warwickshire CV6 3BQ",
    "addr:housenumber":"131",
    "addr:postcode":"cv6 3bq",
    "addr:street":"Radford Road",
    "iso:country":"GB",
    "sg:address":"131 Radford Road",
    "sg:city":"Coventry",
    "sg:classifiers":[
        {
            "category":"Fast Food",
            "type":"Food & Drink"
        }
    ],
    "sg:phone":"+44 24 7659 8878",
    "sg:postcode":"CV6 3BQ",
    "sg:province":"Warwickshire",
    "sg:tags":[
        "away",
        "meal",
        "outlet",
        "take"
    ],
    "wof:name":"China House",
    "wof:placetype":"venue"
},
  "geometry": {"coordinates":[-1.519651,52.421078],"type":"Point"}
}