{
  "type": "Feature",
  "properties": {
    "addr:full":"5 Gwynne Road, Parkstone Poole Dorset BH12 2AR",
    "addr:housenumber":"5",
    "addr:postcode":"bh12 2ar",
    "addr:street":"Gwynne Road",
    "iso:country":"GB",
    "sg:address":"5 Gwynne Road, Parkstone",
    "sg:city":"Poole",
    "sg:classifiers":[
        {
            "category":"Building & Trades",
            "subcategory":"Construction",
            "type":"Services"
        }
    ],
    "sg:phone":"+44 1202 381444",
    "sg:postcode":"BH12 2AR",
    "sg:province":"Dorset",
    "sg:tags":[
        "builder",
        "glazier"
    ],
    "wof:name":"Paul Squires Decorating Ltd",
    "wof:placetype":"venue"
},
  "geometry": {"coordinates":[-1.9272749424,50.7303695679],"type":"Point"}
}