{
  "type": "Feature",
  "properties": {
    "iso:country":"GB",
    "sg:address":"16-22 Watery Lane, Ashton On Ribble",
    "sg:city":"Preston",
    "sg:classifiers":[
        {
            "category":"Organizations",
            "subcategory":"Non-profit Organization",
            "type":"Services"
        }
    ],
    "sg:phone":"+44 1772 726745",
    "sg:postcode":"PR2 2NN",
    "sg:province":"Lancashire",
    "sg:tags":[
        "organisation",
        "animal",
        "welfare"
    ],
    "wof:name":"Riverbank Veterinary Centre",
    "wof:placetype":"venue"
},
  "geometry": {"coordinates":[-2.7240490913,53.7634391785],"type":"Point"}
}