{
  "type": "Feature",
  "properties": {
    "iso:country":"GB",
    "sg:address":"37 Queen Square",
    "sg:city":"Bristol",
    "sg:classifiers":[
        {
            "category":"Professional",
            "subcategory":"Advertising",
            "type":"Services"
        }
    ],
    "sg:phone":"+44 117 917 1600",
    "sg:postcode":"BS1 4QS",
    "sg:province":"City of Bristol",
    "sg:tags":[
        "agency"
    ],
    "wof:name":"Barkers Human Resources Advertising Ltd",
    "wof:placetype":"venue"
},
  "geometry": {"coordinates":[-2.5950250626,51.449760437],"type":"Point"}
}