{
  "type": "Feature",
  "properties": {
    "addr:full":"7 Hithercroft Court, Lupton Road Wallingford Oxfordshire OX10 9BT",
    "addr:housenumber":"7",
    "addr:postcode":"ox10 9bt",
    "addr:street":"Hithercroft Court Lupton Road",
    "iso:country":"GB",
    "sg:address":"7 Hithercroft Court, Lupton Road",
    "sg:city":"Wallingford",
    "sg:classifiers":[
        {
            "category":"Professional",
            "subcategory":"Printing & Photocopies",
            "type":"Services"
        }
    ],
    "sg:phone":"+44 1491 824827",
    "sg:postcode":"OX10 9BT",
    "sg:province":"Oxfordshire",
    "sg:tags":[
        "printer"
    ],
    "wof:name":"N P Design & Print",
    "wof:placetype":"venue"
},
  "geometry": {"coordinates":[-1.1595560312,51.5948829651],"type":"Point"}
}