{
  "type": "Feature",
  "properties": {
    "iso:country":"GB",
    "sg:address":"2b Riga Wharf, Bristol Rd",
    "sg:city":"Gloucester",
    "sg:classifiers":[
        {
            "category":"Autos & Motor Vehicles",
            "subcategory":"Auto Supplies",
            "type":"Retail Goods"
        }
    ],
    "sg:phone":"+44 1452 506023",
    "sg:postcode":"GL2 6DH",
    "sg:province":"Gloucestershire",
    "sg:tags":[
        "component"
    ],
    "wof:name":"Bancrofts Ltd",
    "wof:placetype":"venue"
},
  "geometry": {"coordinates":[-2.30256,51.8256],"type":"Point"}
}