{
  "type": "Feature",
  "properties": {
    "addr:full":"Goosebrook Lane, Higher Whitley Warrington Cheshire WA4 4PT",
    "addr:postcode":"wa4 4pt",
    "addr:street":"Goosebrook Lane",
    "iso:country":"GB",
    "sg:address":"Goosebrook Lane, Higher Whitley",
    "sg:city":"Warrington",
    "sg:classifiers":[
        {
            "category":"Retail",
            "subcategory":"Auto Repair",
            "type":"Services"
        }
    ],
    "sg:phone":"+44 1606 891527",
    "sg:postcode":"WA4 4PT",
    "sg:province":"Cheshire",
    "sg:tags":[
        "modification",
        "garage"
    ],
    "wof:name":"Mobile Auto Services",
    "wof:placetype":"venue"
},
  "geometry": {"coordinates":[-2.5669600964,53.3068466187],"type":"Point"}
}