{
  "type": "Feature",
  "properties": {
    "addr:full":"Wainsford Rd Lymington Hampshire SO41 8LB",
    "addr:postcode":"so41 8lb",
    "addr:street":"Wainsford Rd",
    "iso:country":"GB",
    "sg:address":"Wainsford Rd",
    "sg:city":"Lymington",
    "sg:classifiers":[
        {
            "category":"Professional",
            "subcategory":"Management & Consulting",
            "type":"Services"
        }
    ],
    "sg:postcode":"SO41 8LB",
    "sg:province":"Hampshire",
    "sg:tags":[
        "consultant",
        "business"
    ],
    "wof:name":"Lymington Vineyard",
    "wof:placetype":"venue"
},
  "geometry": {"coordinates":[-1.5717550516,50.7549858093],"type":"Point"}
}