{
  "type": "Feature",
  "properties": {
    "iso:country":"GB",
    "sg:address":"76 Rickmansworth Lane",
    "sg:city":"Gerrards Cross",
    "sg:classifiers":[
        {
            "category":"Travel",
            "subcategory":"Travel Agent",
            "type":"Entertainment"
        }
    ],
    "sg:phone":"+44 1494 872316",
    "sg:postcode":"SL9 0LY",
    "sg:province":"Buckinghamshire",
    "wof:name":"Travelshaw Services Ltd.",
    "wof:placetype":"venue"
},
  "geometry": {"coordinates":[-0.537764,51.622147],"type":"Point"}
}