{
  "type": "Feature",
  "properties": {
    "addr:full":"77 Boston Manor Road Brentford Greater London TW8 9JQ",
    "addr:housenumber":"77",
    "addr:postcode":"tw8 9jq",
    "addr:street":"Boston Manor Road",
    "iso:country":"GB",
    "sg:address":"77 Boston Manor Road",
    "sg:city":"Brentford",
    "sg:classifiers":[
        {
            "category":"Wholesale",
            "subcategory":"Construction Materials",
            "type":"Manufacturing & Wholesale Goods"
        },
        {
            "category":"Home & Garden",
            "subcategory":"Building Materials",
            "type":"Retail Goods"
        },
        {
            "category":"Manufacturing",
            "subcategory":"Building Materials",
            "type":"Manufacturing & Wholesale Goods"
        }
    ],
    "sg:phone":"+44 20 8380 7300",
    "sg:postcode":"TW8 9JQ",
    "sg:province":"Greater London",
    "sg:tags":[
        "ready",
        "mortar",
        "distributor",
        "concrete",
        "mixed",
        "mnfrs"
    ],
    "wof:name":"London Concrete Ltd.",
    "wof:placetype":"venue"
},
  "geometry": {"coordinates":[-0.3152279854,51.4898376465],"type":"Point"}
}