{
  "type": "Feature",
  "properties": {
    "addr:full":"11 Station Rd, Cholsey Wallingford Oxfordshire OX10 9PT",
    "addr:housenumber":"11",
    "addr:postcode":"ox10 9pt",
    "addr:street":"Station Rd",
    "iso:country":"GB",
    "sg:address":"11 Station Rd, Cholsey",
    "sg:city":"Wallingford",
    "sg:classifiers":[
        {
            "category":"Building & Trades",
            "subcategory":"Construction",
            "type":"Services"
        }
    ],
    "sg:phone":"+44 1491 651584",
    "sg:postcode":"OX10 9PT",
    "sg:province":"Oxfordshire",
    "sg:tags":[
        "joiner",
        "carpenter"
    ],
    "wof:name":"LJS Carpentry & Maintenance",
    "wof:placetype":"venue"
},
  "geometry": {"coordinates":[-1.1538540125,51.574382782],"type":"Point"}
}