{
  "type": "Feature",
  "properties": {
    "addr:full":"Dochcarty Farm Dingwall Highland IV15 9UF",
    "addr:postcode":"iv15 9uf",
    "addr:street":"Dingwall",
    "iso:country":"GB",
    "sg:address":"Dochcarty Farm",
    "sg:city":"Dingwall",
    "sg:classifiers":[
        {
            "category":"Home & Garden",
            "subcategory":"Garden Supply",
            "type":"Retail Goods"
        },
        {
            "category":"Farming",
            "subcategory":"Farm",
            "type":"Manufacturing & Wholesale Goods"
        }
    ],
    "sg:phone":"+44 1349 862117",
    "sg:postcode":"IV15 9UF",
    "sg:province":"Highland",
    "sg:tags":[
        "mixed",
        "bulb",
        "crop",
        "grower"
    ],
    "wof:name":"N A Campbell",
    "wof:placetype":"venue"
},
  "geometry": {"coordinates":[-4.431448,57.59618],"type":"Point"}
}