{
  "type": "Feature",
  "properties": {
    "addr:full":"33 Goodwin Close, Fords Farm, Calcot Reading Berkshire RG31 7ZW",
    "addr:housenumber":"33",
    "addr:postcode":"rg31 7zw",
    "addr:street":"Goodwin Close",
    "iso:country":"GB",
    "sg:address":"33 Goodwin Close, Fords Farm, Calcot",
    "sg:city":"Reading",
    "sg:classifiers":[
        {
            "category":"Home & Garden",
            "subcategory":"Building Materials",
            "type":"Retail Goods"
        }
    ],
    "sg:postcode":"RG31 7ZW",
    "sg:province":"Berkshire",
    "sg:tags":[
        "furnishers",
        "bathroom",
        "planner"
    ],
    "wof:name":"Chris Giles Bathroom Specialists",
    "wof:placetype":"venue"
},
  "geometry": {"coordinates":[-1.034689,51.439014],"type":"Point"}
}