{
  "type": "Feature",
  "properties": {
    "addr:full":"Broxhead Trading Estate, Lindford Bridge Road Bordon Hampshire GU35 0NY",
    "addr:postcode":"gu35 0ny",
    "addr:street":"Lindford Bridge Road",
    "iso:country":"GB",
    "sg:address":"Broxhead Trading Estate, Lindford Bridge Road",
    "sg:city":"Bordon",
    "sg:classifiers":[
        {
            "category":"Sports & Exercise",
            "subcategory":"Tennis Court",
            "type":"Entertainment"
        }
    ],
    "sg:phone":"+44 1420 488330",
    "sg:postcode":"GU35 0NY",
    "sg:province":"Hampshire",
    "sg:tags":[
        "breakdown",
        "recovery"
    ],
    "wof:name":"Safety Autos Recovery",
    "wof:placetype":"venue"
},
  "geometry": {"coordinates":[-0.8447639942,51.118598938],"type":"Point"}
}