{
  "type": "Feature",
  "properties": {
    "addr:full":"6 Jewry Street Winchester Hampshire SO23 8RZ",
    "addr:housenumber":"6",
    "addr:postcode":"so23 8rz",
    "addr:street":"Jewry Street",
    "iso:country":"GB",
    "sg:address":"6 Jewry Street",
    "sg:city":"Winchester",
    "sg:classifiers":[
        {
            "category":"Real Estate",
            "subcategory":"Real Estate Agent",
            "type":"Services"
        }
    ],
    "sg:phone":"+44 1962 869999",
    "sg:postcode":"SO23 8RZ",
    "sg:province":"Hampshire",
    "wof:name":"Lane Fox (Residential) Ltd.",
    "wof:placetype":"venue"
},
  "geometry": {"coordinates":[-1.316347,51.063946],"type":"Point"}
}