{
  "type": "Feature",
  "properties": {
    "addr:full":"Unit 2 Sleaford Industrial Estate, Sleaford Street London Greater London SW8 5AB",
    "addr:housenumber":"unit 2",
    "addr:postcode":"sw8 5ab",
    "addr:street":"Industrial Estate Sleaford Street",
    "iso:country":"GB",
    "sg:address":"Unit 2 Sleaford Industrial Estate, Sleaford Street",
    "sg:city":"London",
    "sg:classifiers":[
        {
            "category":"Building & Trades",
            "subcategory":"Electrical",
            "type":"Services"
        }
    ],
    "sg:postcode":"SW8 5AB",
    "sg:province":"Greater London",
    "sg:tags":[
        "lighting"
    ],
    "wof:name":"S A Huntley",
    "wof:placetype":"venue"
},
  "geometry": {"coordinates":[-0.14015,51.479389],"type":"Point"}
}