{
  "type": "Feature",
  "properties": {
    "iso:country":"GB",
    "sg:address":"41 Greenset Close",
    "sg:city":"Lancaster",
    "sg:classifiers":[
        {
            "category":"Home & Garden",
            "subcategory":"Home Furnishings",
            "type":"Retail Goods"
        }
    ],
    "sg:phone":"+44 1524 65465",
    "sg:postcode":"LA1 2PW",
    "sg:province":"Lancashire",
    "sg:tags":[
        "awning",
        "canopy",
        "blinds"
    ],
    "wof:name":"Clare Blinds",
    "wof:placetype":"venue"
},
  "geometry": {"coordinates":[-2.809548,54.065739],"type":"Point"}
}