{
  "type": "Feature",
  "properties": {
    "addr:full":"Oliver Street Birmingham West Midlands B7 4NX",
    "addr:postcode":"b7 4nx",
    "addr:street":"Oliver Street",
    "iso:country":"GB",
    "sg:address":"Oliver Street",
    "sg:city":"Birmingham",
    "sg:classifiers":[
        {
            "category":"Bars & Pubs",
            "type":"Food & Drink"
        }
    ],
    "sg:phone":"+44 121 359 3588",
    "sg:postcode":"B7 4NX",
    "sg:province":"West Midlands",
    "sg:tags":[
        "pubs",
        "inn"
    ],
    "wof:name":"Punch Pub Co. (Ib) Ltd.",
    "wof:placetype":"venue"
},
  "geometry": {"coordinates":[-1.8770140409,52.4931182861],"type":"Point"}
}