{
  "type": "Feature",
  "properties": {
    "addr:full":"Principality House, The Friary Cardiff Cardiff CF10 3FA",
    "addr:postcode":"cf10 3fa",
    "addr:street":"The Friary",
    "iso:country":"GB",
    "sg:address":"Principality House, The Friary",
    "sg:city":"Cardiff",
    "sg:classifiers":[
        {
            "category":"Banks & Credit Unions",
            "subcategory":"Financial Services",
            "type":"Services"
        }
    ],
    "sg:phone":"+44 29 2023 3661",
    "sg:postcode":"CF10 3FA",
    "sg:province":"Cardiff",
    "sg:tags":[
        "consultant"
    ],
    "wof:name":"Principality Independent Financial Advisers Ltd.",
    "wof:placetype":"venue"
},
  "geometry": {"coordinates":[-3.1775760651,51.482131958],"type":"Point"}
}