{
  "type": "Feature",
  "properties": {
    "iso:country":"GB",
    "sg:address":"38 Watergate St",
    "sg:city":"Chester",
    "sg:classifiers":[
        {
            "category":"Restaurant",
            "type":"Food & Drink"
        }
    ],
    "sg:phone":"+44 1244 400322",
    "sg:postcode":"CH1 2LA",
    "sg:province":"Cheshire",
    "sg:tags":[
        "italian"
    ],
    "wof:name":"L'altro",
    "wof:placetype":"venue"
},
  "geometry": {"coordinates":[-2.893243,53.190186],"type":"Point"}
}