{
  "type": "Feature",
  "properties": {
    "iso:country":"GB",
    "sg:address":"182 Leeds Road",
    "sg:city":"Wakefield",
    "sg:classifiers":[
        {
            "category":"Shopping",
            "subcategory":"Stationery & Office Supplies",
            "type":"Retail Goods"
        }
    ],
    "sg:phone":"+44 1924 386601",
    "sg:postcode":"WF1 2QA",
    "sg:province":"West Yorkshire",
    "sg:tags":[
        "recording",
        "machine",
        "time"
    ],
    "wof:name":"Time Systems",
    "wof:placetype":"venue"
},
  "geometry": {"coordinates":[-1.5031490326,53.6983528137],"type":"Point"}
}