{
  "type": "Feature",
  "properties": {
    "addr:full":"Bletchley Rd, Newton Longville Milton Keynes Bedfordshire MK17 0AB",
    "addr:postcode":"mk17 0ab",
    "addr:street":"Bletchley Rd",
    "iso:country":"GB",
    "sg:address":"Bletchley Rd, Newton Longville",
    "sg:city":"Milton Keynes",
    "sg:classifiers":[
        {
            "category":"Utilities",
            "subcategory":"Refuse",
            "type":"Services"
        }
    ],
    "sg:phone":"+44 1908 367022",
    "sg:postcode":"MK17 0AB",
    "sg:province":"Bedfordshire",
    "sg:tags":[
        "disposal",
        "waste",
        "retail"
    ],
    "wof:name":"Shanks",
    "wof:placetype":"venue"
},
  "geometry": {"coordinates":[-0.766371,51.974079],"type":"Point"}
}