{
  "type": "Feature",
  "properties": {
    "addr:full":"19 Elms Vale Road Dover Kent CT17 9NZ",
    "addr:housenumber":"19",
    "addr:postcode":"ct17 9nz",
    "addr:street":"Elms Vale Road",
    "iso:country":"GB",
    "sg:address":"19 Elms Vale Road",
    "sg:city":"Dover",
    "sg:classifiers":[
        {
            "category":"Personal",
            "subcategory":"Beauty Salon",
            "type":"Services"
        }
    ],
    "sg:phone":"+44 1304 203537",
    "sg:postcode":"CT17 9NZ",
    "sg:province":"Kent",
    "sg:tags":[
        "unisex",
        "ladies",
        "lady",
        "hairdresser"
    ],
    "wof:name":"New Image For Hair",
    "wof:placetype":"venue"
},
  "geometry": {"coordinates":[1.292466,51.123646],"type":"Point"}
}