{
  "type": "Feature",
  "properties": {
    "addr:full":"Unit 2 Horsham West Sussex RH12 4SE",
    "addr:housenumber":"unit",
    "addr:postcode":"rh12 4se",
    "iso:country":"GB",
    "sg:address":"Unit 2",
    "sg:city":"Horsham",
    "sg:classifiers":[
        {
            "category":"Building & Trades",
            "subcategory":"Construction",
            "type":"Services"
        }
    ],
    "sg:phone":"+44 1293 852971",
    "sg:postcode":"RH12 4SE",
    "sg:province":"West Sussex",
    "sg:tags":[
        "builder"
    ],
    "wof:name":"Rusper Developments Ltd.",
    "wof:placetype":"venue"
},
  "geometry": {"coordinates":[-0.2440239936,51.0815238953],"type":"Point"}
}