{
  "type": "Feature",
  "properties": {
    "addr:full":"Bryn Du Ty Croes Isle of Anglesey LL63 5SH",
    "addr:postcode":"ll63 5sh",
    "addr:street":"Croes",
    "iso:country":"GB",
    "sg:address":"Bryn Du",
    "sg:city":"Ty Croes",
    "sg:classifiers":[
        {
            "category":"Farming",
            "subcategory":"Farm",
            "type":"Manufacturing & Wholesale Goods"
        }
    ],
    "sg:phone":"+44 1407 810478",
    "sg:postcode":"LL63 5SH",
    "sg:province":"Isle of Anglesey",
    "sg:tags":[
        "mixed",
        "crop"
    ],
    "wof:name":"Grampian Country Chickens Rearing Ltd",
    "wof:placetype":"venue"
},
  "geometry": {"coordinates":[-4.4749031067,53.2228965759],"type":"Point"}
}