{
  "type": "Feature",
  "properties": {
    "iso:country":"GB",
    "sg:address":"81 Janesbrook Rd",
    "sg:city":"Southport",
    "sg:classifiers":[
        {
            "category":"Home & Garden",
            "subcategory":"Building Materials",
            "type":"Retail Goods"
        }
    ],
    "sg:postcode":"PR8 6NU",
    "sg:province":"Lancashire",
    "sg:tags":[
        "fencing"
    ],
    "wof:name":"Fence Co",
    "wof:placetype":"venue"
},
  "geometry": {"coordinates":[-2.981762,53.634716],"type":"Point"}
}