{
  "type": "Feature",
  "properties": {
    "iso:country":"GB",
    "sg:address":"69 Grantham Road, Radcliffe On Trent",
    "sg:city":"Nottingham",
    "sg:classifiers":[
        {
            "category":"Home & Garden",
            "subcategory":"Garden Supply",
            "type":"Retail Goods"
        }
    ],
    "sg:postcode":"NG12 2HE",
    "sg:province":"Nottinghamshire",
    "sg:tags":[
        "nursery",
        "centre"
    ],
    "wof:name":"West's Nursery",
    "wof:placetype":"venue"
},
  "geometry": {"coordinates":[-1.02048,52.949387],"type":"Point"}
}