{
  "type": "Feature",
  "properties": {
    "addr:full":"Unit 3/5 Overbrook Business Cent, Re Poolbridge Roa, Blackford Wedmore Somerset BS28 4PA",
    "addr:housenumber":"unit 3 / 5",
    "addr:postcode":"bs28 4pa",
    "addr:street":"Overbrook Business Cent Re Poolbridge Roa Blackford",
    "iso:country":"GB",
    "sg:address":"Unit 3/5 Overbrook Business Cent, Re Poolbridge Roa, Blackford",
    "sg:city":"Wedmore",
    "sg:classifiers":[
        {
            "category":"Social Services",
            "type":"Services"
        },
        {
            "category":"Professional",
            "subcategory":"Management & Consulting",
            "type":"Services"
        }
    ],
    "sg:phone":"+44 1934 713465",
    "sg:postcode":"BS28 4PA",
    "sg:province":"Somerset",
    "sg:tags":[
        "consultant",
        "disability",
        "business"
    ],
    "wof:name":"Splashback",
    "wof:placetype":"venue"
},
  "geometry": {"coordinates":[-2.8101599216,51.2276306152],"type":"Point"}
}