{
  "type": "Feature",
  "properties": {
    "iso:country":"GB",
    "sg:address":"65 Sparrow Hill",
    "sg:city":"Loughborough",
    "sg:classifiers":[
        {
            "category":"Professional",
            "subcategory":"Art Services",
            "type":"Services"
        }
    ],
    "sg:phone":"+44 1509 240040",
    "sg:postcode":"LE11 1BU",
    "sg:province":"Leicestershire",
    "sg:tags":[
        "graphic",
        "designer"
    ],
    "wof:name":"Lime",
    "wof:placetype":"venue"
},
  "geometry": {"coordinates":[-1.202967,52.77459],"type":"Point"}
}