{
  "type": "Feature",
  "properties": {
    "iso:country":"GB",
    "sg:address":"60 George Street",
    "sg:city":"Walsall",
    "sg:classifiers":[
        {
            "category":"Cafe",
            "type":"Food & Drink"
        }
    ],
    "sg:phone":"+44 1922 640270",
    "sg:postcode":"WS1 1RS",
    "sg:province":"West Midlands",
    "sg:tags":[
        "tea",
        "room"
    ],
    "wof:name":"The Country Kitchen",
    "wof:placetype":"venue"
},
  "geometry": {"coordinates":[-1.980753,52.582455],"type":"Point"}
}