{
  "type": "Feature",
  "properties": {
    "iso:country":"GB",
    "sg:address":"13 West Street",
    "sg:city":"Cromer",
    "sg:classifiers":[
        {
            "category":"Professional",
            "subcategory":"Accounting & Tax Preparation",
            "type":"Services"
        }
    ],
    "sg:phone":"+44 1263 512907",
    "sg:postcode":"NR27 9HZ",
    "sg:province":"Norfolk",
    "sg:tags":[
        "accountant",
        "activity"
    ],
    "wof:name":"Larking Gowen",
    "wof:placetype":"venue"
},
  "geometry": {"coordinates":[1.296915,52.930412],"type":"Point"}
}