{
  "type": "Feature",
  "properties": {
    "addr:full":"Measurement House, Mancunian Way, Ardwick Manchester Greater Manchester M12 6HN",
    "addr:postcode":"m12 6hn",
    "addr:street":"Mancunian Way",
    "iso:country":"GB",
    "sg:address":"Measurement House, Mancunian Way, Ardwick",
    "sg:city":"Manchester",
    "sg:classifiers":[
        {
            "category":"Home & Garden",
            "subcategory":"Kitchen Supply",
            "type":"Retail Goods"
        }
    ],
    "sg:phone":"+44 161 273 1252",
    "sg:postcode":"M12 6HN",
    "sg:province":"Greater Manchester",
    "sg:tags":[
        "measuring",
        "scale"
    ],
    "wof:name":"Mass Measuring Systems Ltd.",
    "wof:placetype":"venue"
},
  "geometry": {"coordinates":[-2.2224349976,53.4690742493],"type":"Point"}
}