{
  "type": "Feature",
  "properties": {
    "iso:country":"GB",
    "sg:address":"4 The Mount, Fetcham",
    "sg:city":"Leatherhead",
    "sg:classifiers":[
        {
            "category":"Professional",
            "subcategory":"Employment Agencies",
            "type":"Services"
        }
    ],
    "sg:phone":"+44 1372 360859",
    "sg:postcode":"KT22 9EE",
    "sg:province":"Surrey",
    "sg:tags":[
        "agricultural",
        "advice"
    ],
    "wof:name":"Agricultural Agent",
    "wof:placetype":"venue"
},
  "geometry": {"coordinates":[-0.3424499929,51.2919464111],"type":"Point"}
}