{
  "type": "Feature",
  "properties": {
    "addr:full":"97 Fonthill Rd Finsbury Park Greater London N4 3JH",
    "addr:housenumber":"97",
    "addr:postcode":"rd;n4 3jh",
    "addr:street":"Fonthill",
    "iso:country":"GB",
    "sg:address":"97 Fonthill Rd",
    "sg:city":"Finsbury Park",
    "sg:classifiers":[
        {
            "category":"Personal",
            "type":"Services"
        }
    ],
    "sg:phone":"+44 20 7272 3820",
    "sg:postcode":"N4 3JH",
    "sg:province":"Greater London",
    "sg:tags":[
        "dressmaker"
    ],
    "wof:name":"Charmrock Ltd",
    "wof:placetype":"venue"
},
  "geometry": {"coordinates":[-0.1090560034,51.5649414062],"type":"Point"}
}