{
  "type": "Feature",
  "properties": {
    "iso:country":"GB",
    "sg:address":"6 Chaloner Street",
    "sg:city":"Guisborough",
    "sg:classifiers":[
        {
            "category":"Health Services",
            "subcategory":"Dentist",
            "type":"Services"
        }
    ],
    "sg:postcode":"TS14 6QD",
    "sg:province":"North Yorkshire",
    "wof:name":"N Crees",
    "wof:placetype":"venue"
},
  "geometry": {"coordinates":[-1.052842,54.535191],"type":"Point"}
}