{
  "type": "Feature",
  "properties": {
    "iso:country":"GB",
    "sg:address":"105 Queensway",
    "sg:city":"Orpington",
    "sg:classifiers":[
        {
            "category":"Shopping",
            "subcategory":"Antiques",
            "type":"Retail Goods"
        }
    ],
    "sg:phone":"+44 1689 826832",
    "sg:postcode":"BR5 1DG",
    "sg:province":"Kent",
    "wof:name":"Memory Lane Antiques",
    "wof:placetype":"venue"
},
  "geometry": {"coordinates":[0.072402,51.389153],"type":"Point"}
}