{
  "type": "Feature",
  "properties": {
    "addr:full":"21-23 Sagar Street Castleford West Yorkshire WF10 1AG",
    "addr:housenumber":"21-23",
    "addr:postcode":"wf10 1ag",
    "addr:street":"Sagar Street",
    "iso:country":"GB",
    "sg:address":"21-23 Sagar Street",
    "sg:city":"Castleford",
    "sg:classifiers":[
        {
            "category":"Social Services",
            "subcategory":"Job Training",
            "type":"Services"
        },
        {
            "category":"Professional",
            "subcategory":"Employment Agencies",
            "type":"Services"
        }
    ],
    "sg:phone":"+44 1977 552824",
    "sg:postcode":"WF10 1AG",
    "sg:province":"West Yorkshire",
    "sg:tags":[
        "career",
        "information",
        "guidance"
    ],
    "wof:name":"Wakefield District Guidance Services",
    "wof:placetype":"venue"
},
  "geometry": {"coordinates":[-1.351223,53.726608],"type":"Point"}
}