{
  "type": "Feature",
  "properties": {
    "iso:country":"GB",
    "sg:address":"82 High Street",
    "sg:city":"Linlithgow",
    "sg:classifiers":[
        {
            "category":"Food & Beverages",
            "subcategory":"Meat & Fish",
            "type":"Retail Goods"
        }
    ],
    "sg:phone":"+44 1506 842376",
    "sg:postcode":"EH49 7AQ",
    "sg:province":"Falkirk",
    "sg:tags":[
        "butcher"
    ],
    "wof:name":"Steven Forsyth",
    "wof:placetype":"venue"
},
  "geometry": {"coordinates":[-3.598864,55.977058],"type":"Point"}
}