{
  "type": "Feature",
  "properties": {
    "addr:full":"59 High Street Christchurch Dorset BH23 1AS",
    "addr:housenumber":"59",
    "addr:postcode":"bh23 1as",
    "addr:street":"High Street",
    "iso:country":"GB",
    "sg:address":"59 High Street",
    "sg:city":"Christchurch",
    "sg:classifiers":[
        {
            "category":"Shopping",
            "subcategory":"Music",
            "type":"Retail Goods"
        }
    ],
    "sg:phone":"+44 1202 499629",
    "sg:postcode":"BH23 1AS",
    "sg:province":"Dorset",
    "sg:tags":[
        "dvd",
        "record",
        "tape",
        "vinyl",
        "cd"
    ],
    "wof:name":"Trax Of Christchurch",
    "wof:placetype":"venue"
},
  "geometry": {"coordinates":[-1.7766859531,50.7339553833],"type":"Point"}
}