{
  "type": "Feature",
  "properties": {
    "iso:country":"GB",
    "sg:address":"Longcliffe Works, Longcliffe",
    "sg:city":"Matlock",
    "sg:classifiers":[
        {
            "category":"Manufacturing",
            "subcategory":"Metals",
            "type":"Manufacturing & Wholesale Goods"
        }
    ],
    "sg:phone":"+44 1629 540495",
    "sg:postcode":"DE4 4HN",
    "sg:province":"Derbyshire",
    "sg:tags":[
        "steel",
        "fabricator",
        "erectors"
    ],
    "wof:name":"Robinsons Longcliffe Ltd.",
    "wof:placetype":"venue"
},
  "geometry": {"coordinates":[-1.5482740402,53.1356163025],"type":"Point"}
}