{
  "type": "Feature",
  "properties": {
    "addr:full":"11-13 Fishergate Centre Preston Lancashire PR1 8HJ",
    "addr:housenumber":"11-13;centre",
    "addr:postcode":"pr1 8hj",
    "addr:street":"Fishergate;Preston",
    "iso:country":"GB",
    "sg:address":"11-13 Fishergate Centre",
    "sg:city":"Preston",
    "sg:classifiers":[
        {
            "category":"Home & Garden",
            "subcategory":"Household Appliances",
            "type":"Retail Goods"
        }
    ],
    "sg:phone":"+44 1772 202110",
    "sg:postcode":"PR1 8HJ",
    "sg:province":"Lancashire",
    "sg:tags":[
        "electrical",
        "domestic"
    ],
    "wof:name":"Dixons",
    "wof:placetype":"venue"
},
  "geometry": {"coordinates":[-2.713113,53.755032],"type":"Point"}
}