{
  "type": "Feature",
  "properties": {
    "iso:country":"GB",
    "sg:address":"599 Thornton Road",
    "sg:city":"Bradford",
    "sg:classifiers":[
        {
            "category":"Fast Food",
            "type":"Food & Drink"
        }
    ],
    "sg:phone":"+44 1274 483432",
    "sg:postcode":"BD8 9RA",
    "sg:province":"West Yorkshire",
    "sg:tags":[
        "away",
        "take"
    ],
    "wof:name":"C Longbottom",
    "wof:placetype":"venue"
},
  "geometry": {"coordinates":[-1.7913479805,53.7989273071],"type":"Point"}
}