{
  "type": "Feature",
  "properties": {
    "addr:full":"58 Lewin Road, Streatham Common London Greater London SW16 6JT",
    "addr:housenumber":"58",
    "addr:postcode":"sw16 6jt",
    "addr:street":"Lewin Road",
    "iso:country":"GB",
    "sg:address":"58 Lewin Road, Streatham Common",
    "sg:city":"London",
    "sg:classifiers":[
        {
            "category":"Autos & Motor Vehicles",
            "subcategory":"Automobile Sales",
            "type":"Retail Goods"
        }
    ],
    "sg:postcode":"SW16 6JT",
    "sg:province":"Greater London",
    "sg:tags":[
        "car"
    ],
    "wof:name":"Production Cars Ltd.",
    "wof:placetype":"venue"
},
  "geometry": {"coordinates":[-0.133713007,51.422164917],"type":"Point"}
}