{
  "type": "Feature",
  "properties": {
    "addr:full":"11 Folly Hall Road, Wibsey Bradford West Yorkshire BD6 1UL",
    "addr:housenumber":"11",
    "addr:postcode":"bd6 1ul",
    "addr:street":"Folly Hall Road",
    "iso:country":"GB",
    "sg:address":"11 Folly Hall Road, Wibsey",
    "sg:city":"Bradford",
    "sg:classifiers":[
        {
            "category":"Personal",
            "subcategory":"Beauty Salon",
            "type":"Services"
        }
    ],
    "sg:phone":"+44 1274 604048",
    "sg:postcode":"BD6 1UL",
    "sg:province":"West Yorkshire",
    "sg:tags":[
        "unisex",
        "hairdresser"
    ],
    "wof:name":"Studio 2 Raffaels",
    "wof:placetype":"venue"
},
  "geometry": {"coordinates":[-1.7759959698,53.7659378052],"type":"Point"}
}