{
  "type": "Feature",
  "properties": {
    "addr:full":"Bilton Road Hitchin Hertfordshire SG4 0SB",
    "addr:postcode":"sg4 0sb",
    "addr:street":"Bilton Road",
    "iso:country":"GB",
    "sg:address":"Bilton Road",
    "sg:city":"Hitchin",
    "sg:classifiers":[
        {
            "category":"Personal",
            "type":"Services"
        }
    ],
    "sg:phone":"+44 1462 453113",
    "sg:postcode":"SG4 0SB",
    "sg:province":"Hertfordshire",
    "sg:tags":[
        "delivery"
    ],
    "wof:name":"Geodis United Carriers",
    "wof:placetype":"venue"
},
  "geometry": {"coordinates":[-0.269656986,51.963596344],"type":"Point"}
}