{
  "type": "Feature",
  "properties": {
    "addr:full":"2 Victory Bldgs Banbury Oxfordshire OX16 5LT",
    "addr:housenumber":"2",
    "addr:postcode":"ox16 5lt",
    "addr:street":"Victory Bldgs",
    "iso:country":"GB",
    "sg:address":"2 Victory Bldgs",
    "sg:city":"Banbury",
    "sg:classifiers":[
        {
            "category":"Shopping",
            "subcategory":"Clothing, Apparel, & Fashions",
            "type":"Retail Goods"
        }
    ],
    "sg:postcode":"OX16 5LT",
    "sg:province":"Oxfordshire",
    "sg:tags":[
        "wear",
        "leisure"
    ],
    "wof:name":"Walkers O L Ltd",
    "wof:placetype":"venue"
},
  "geometry": {"coordinates":[-1.3400280476,52.0611114502],"type":"Point"}
}