{
  "type": "Feature",
  "properties": {
    "iso:country":"GB",
    "sg:address":"Church Street",
    "sg:city":"Kingsbridge",
    "sg:classifiers":[
        {
            "category":"Restaurant",
            "type":"Food & Drink"
        }
    ],
    "sg:phone":"+44 1548 856707",
    "sg:postcode":"TQ7 1BL",
    "sg:province":"Devon",
    "sg:tags":[
        "italian"
    ],
    "wof:name":"Giovanni's",
    "wof:placetype":"venue"
},
  "geometry": {"coordinates":[-3.771832943,50.2872772217],"type":"Point"}
}