{
  "type": "Feature",
  "properties": {
    "iso:country":"GB",
    "sg:address":"Unit A West End Road",
    "sg:city":"High Wycombe",
    "sg:classifiers":[
        {
            "category":"Manufacturing",
            "subcategory":"Tools & Machinery",
            "type":"Manufacturing & Wholesale Goods"
        }
    ],
    "sg:postcode":"HP11 2QQ",
    "sg:province":"Buckinghamshire",
    "sg:tags":[
        "design",
        "maker"
    ],
    "wof:name":"S C Toolmakers",
    "wof:placetype":"venue"
},
  "geometry": {"coordinates":[-0.763209,51.631393],"type":"Point"}
}