{
  "type": "Feature",
  "properties": {
    "addr:full":"Unit 1 Millennium Way Leeds West Yorkshire LS11 5AL",
    "addr:housenumber":"unit 1",
    "addr:postcode":"ls11 5al",
    "addr:street":"Millennium Way",
    "iso:country":"GB",
    "sg:address":"Unit 1 Millennium Way",
    "sg:city":"Leeds",
    "sg:classifiers":[
        {
            "category":"Professional",
            "subcategory":"Business Services",
            "type":"Services"
        }
    ],
    "sg:phone":"+44 113 205 8400",
    "sg:postcode":"LS11 5AL",
    "sg:province":"West Yorkshire",
    "sg:tags":[
        "accomodation"
    ],
    "wof:name":"Scorpio Executive Lets Ltd.",
    "wof:placetype":"venue"
},
  "geometry": {"coordinates":[-1.552279,53.766258],"type":"Point"}
}