{
  "type": "Feature",
  "properties": {
    "addr:full":"Brevitts Farmhouse, Back Street Thornborough Buckingham Buckinghamshire MK18 2DH",
    "addr:postcode":"mk18 2dh",
    "addr:street":"Back Street",
    "iso:country":"GB",
    "sg:address":"Brevitts Farmhouse, Back Street Thornborough",
    "sg:city":"Buckingham",
    "sg:classifiers":[
        {
            "category":"Professional",
            "subcategory":"Management & Consulting",
            "type":"Services"
        }
    ],
    "sg:phone":"+44 1280 816112",
    "sg:postcode":"MK18 2DH",
    "sg:province":"Buckinghamshire",
    "sg:tags":[
        "consultant",
        "business"
    ],
    "wof:name":"Wilkinson,Jim,Consultancy Ltd",
    "wof:placetype":"venue"
},
  "geometry": {"coordinates":[-0.913176,51.995598],"type":"Point"}
}