{
  "type": "Feature",
  "properties": {
    "addr:full":"Landground Farm, Hardington Mandeville Yeovil Dorset BA22 9PX",
    "addr:postcode":"ba22 9px",
    "iso:country":"GB",
    "sg:address":"Landground Farm, Hardington Mandeville",
    "sg:city":"Yeovil",
    "sg:classifiers":[
        {
            "category":"Farming",
            "subcategory":"Livestock Farm",
            "type":"Manufacturing & Wholesale Goods"
        }
    ],
    "sg:phone":"+44 1935 862805",
    "sg:postcode":"BA22 9PX",
    "sg:province":"Dorset",
    "sg:tags":[
        "others"
    ],
    "wof:name":"Brian G Millard",
    "wof:placetype":"venue"
},
  "geometry": {"coordinates":[-2.6986150742,50.905166626],"type":"Point"}
}