{
  "type": "Feature",
  "properties": {
    "iso:country":"GB",
    "sg:address":"23 New Mount St",
    "sg:city":"Manchester",
    "sg:classifiers":[
        {
            "category":"Banks & Credit Unions",
            "subcategory":"Financial Services",
            "type":"Services"
        }
    ],
    "sg:phone":"+44 161 953 4115",
    "sg:postcode":"M4 4DE",
    "sg:province":"Greater Manchester",
    "sg:tags":[
        "consultant"
    ],
    "wof:name":"Lets Go Manchester",
    "wof:placetype":"venue"
},
  "geometry": {"coordinates":[-2.2354021072,53.4882545471],"type":"Point"}
}