{
  "type": "Feature",
  "properties": {
    "iso:country":"GB",
    "sg:address":"5 Royal Arcade",
    "sg:city":"Bournemouth",
    "sg:classifiers":[
        {
            "category":"Shopping",
            "subcategory":"Hobbies, Toys, & Games",
            "type":"Retail Goods"
        },
        {
            "category":"Transit Center",
            "subcategory":"Freight",
            "type":"Transportation"
        }
    ],
    "sg:postcode":"BH1 4BT",
    "sg:province":"Dorset",
    "sg:tags":[
        "collectors'",
        "item",
        "collector"
    ],
    "wof:name":"RECOLLECTIONS",
    "wof:placetype":"venue"
},
  "geometry": {"coordinates":[-1.841069,50.726753],"type":"Point"}
}