{
  "type": "Feature",
  "properties": {
    "iso:country":"GB",
    "sg:address":"262 Watford Way, Hendon",
    "sg:city":"London",
    "sg:classifiers":[
        {
            "category":"Food & Beverages",
            "subcategory":"Candy",
            "type":"Retail Goods"
        },
        {
            "category":"Professional",
            "type":"Services"
        }
    ],
    "sg:phone":"+44 20 8203 4044",
    "sg:postcode":"NW4 4UJ",
    "sg:province":"Greater London",
    "sg:tags":[
        "confectioner",
        "caterer"
    ],
    "wof:name":"Gupta Confectioners London Ltd",
    "wof:placetype":"venue"
},
  "geometry": {"coordinates":[-0.233834,51.59293],"type":"Point"}
}