{
  "type": "Feature",
  "properties": {
    "iso:country":"GB",
    "sg:address":"Sixth Floor, Medusa House, St Johns Road",
    "sg:city":"Stourbridge",
    "sg:classifiers":[
        {
            "category":"Banks & Credit Unions",
            "subcategory":"Financial Services",
            "type":"Services"
        }
    ],
    "sg:postcode":"DY8 1YS",
    "sg:province":"Staffordshire",
    "sg:tags":[
        "adviser"
    ],
    "wof:name":"Mike Taylor Associates Ltd.",
    "wof:placetype":"venue"
},
  "geometry": {"coordinates":[-2.14447999,52.4567222595],"type":"Point"}
}