{
  "type": "Feature",
  "properties": {
    "addr:full":"85 High Street, Willington Crook Durham DL15 0PE",
    "addr:housenumber":"85",
    "addr:postcode":"dl15 0pe",
    "addr:street":"High Street",
    "iso:country":"GB",
    "sg:address":"85 High Street, Willington",
    "sg:city":"Crook",
    "sg:classifiers":[
        {
            "category":"Shopping",
            "subcategory":"News",
            "type":"Retail Goods"
        }
    ],
    "sg:postcode":"DL15 0PE",
    "sg:province":"Durham",
    "sg:tags":[
        "newsagent"
    ],
    "wof:name":"Willington Sub Post Office",
    "wof:placetype":"venue"
},
  "geometry": {"coordinates":[-1.697437,54.712418],"type":"Point"}
}