{
  "type": "Feature",
  "properties": {
    "addr:full":"9 Station Road Dunmow Essex CM6 1EJ",
    "addr:housenumber":"9",
    "addr:postcode":"cm6 1ej",
    "addr:street":"Station Road",
    "iso:country":"GB",
    "sg:address":"9 Station Road",
    "sg:city":"Dunmow",
    "sg:classifiers":[
        {
            "category":"Building & Trades",
            "subcategory":"Plumbing",
            "type":"Services"
        }
    ],
    "sg:phone":"+44 1371 873450",
    "sg:postcode":"CM6 1EJ",
    "sg:province":"Essex",
    "sg:tags":[
        "plumber",
        "heating"
    ],
    "wof:name":"Martin Salmon",
    "wof:placetype":"venue"
},
  "geometry": {"coordinates":[0.3669860065,51.8687553406],"type":"Point"}
}