{
  "type": "Feature",
  "properties": {
    "addr:full":"3 The Centre, Greenstead Estate Colchester Essex CO5 0HF",
    "addr:housenumber":"3",
    "addr:postcode":"co5 0hf",
    "addr:street":"The Centre",
    "iso:country":"GB",
    "sg:address":"3 The Centre, Greenstead Estate",
    "sg:city":"Colchester",
    "sg:classifiers":[
        {
            "category":"Food & Beverages",
            "subcategory":"Fruits & Vegetables",
            "type":"Retail Goods"
        }
    ],
    "sg:postcode":"CO5 0HF",
    "sg:province":"Essex",
    "sg:tags":[
        "greengrocer"
    ],
    "wof:name":"J H Burt",
    "wof:placetype":"venue"
},
  "geometry": {"coordinates":[0.7504050136,51.810760498],"type":"Point"}
}