{
  "type": "Feature",
  "properties": {
    "addr:full":"Laburnam, Mill End, Bradwell-on-sea Southminster Essex CM0 7HJ",
    "addr:postcode":"cm0 7hj",
    "addr:street":"Mill End;Southminster",
    "iso:country":"GB",
    "sg:address":"Laburnam, Mill End, Bradwell-on-sea",
    "sg:city":"Southminster",
    "sg:classifiers":[
        {
            "category":"Autos & Motor Vehicles",
            "subcategory":"Boat Sales",
            "type":"Retail Goods"
        }
    ],
    "sg:phone":"+44 1621 776397",
    "sg:postcode":"CM0 7HJ",
    "sg:province":"Essex",
    "sg:tags":[
        "repair",
        "builder"
    ],
    "wof:name":"Dragon Marine",
    "wof:placetype":"venue"
},
  "geometry": {"coordinates":[0.82919,51.662418],"type":"Point"}
}