{
  "type": "Feature",
  "properties": {
    "iso:country":"GB",
    "sg:address":"68 Arkles Lane",
    "sg:city":"Liverpool",
    "sg:classifiers":[
        {
            "category":"Retail",
            "subcategory":"Portrait Studio",
            "type":"Services"
        },
        {
            "category":"Professional",
            "subcategory":"Art Services",
            "type":"Services"
        }
    ],
    "sg:phone":"+44 151 260 0111",
    "sg:postcode":"L4 2SP",
    "sg:province":"Merseyside",
    "sg:tags":[
        "photographer",
        "commercial"
    ],
    "sg:website":"http://www.firepix.com",
    "wof:name":"Firepix International",
    "wof:placetype":"venue"
},
  "geometry": {"coordinates":[-2.955362,53.431816],"type":"Point"}
}