{
  "type": "Feature",
  "properties": {
    "addr:full":"5 Pavilion Row Scunthorpe Lincolnshire DN15 7RD",
    "addr:housenumber":"5",
    "addr:postcode":"dn15 7rd",
    "addr:street":"Pavilion Row",
    "iso:country":"GB",
    "sg:address":"5 Pavilion Row",
    "sg:city":"Scunthorpe",
    "sg:classifiers":[
        {
            "category":"Fast Food",
            "type":"Food & Drink"
        }
    ],
    "sg:phone":"+44 1724 280731",
    "sg:postcode":"DN15 7RD",
    "sg:province":"Lincolnshire",
    "sg:tags":[
        "away",
        "take"
    ],
    "wof:name":"Sicilian's",
    "wof:placetype":"venue"
},
  "geometry": {"coordinates":[-0.662893,53.584137],"type":"Point"}
}