{
  "type": "Feature",
  "properties": {
    "iso:country":"GB",
    "sg:address":"Middle Walk, Promenade",
    "sg:city":"Blackpool",
    "sg:classifiers":[
        {
            "category":"Government",
            "subcategory":"Office",
            "type":"Public Place"
        }
    ],
    "sg:phone":"+44 1253 626141",
    "sg:postcode":"FY1 5AA",
    "sg:province":"Lancashire",
    "sg:tags":[
        "local"
    ],
    "wof:name":"Blackpool Beach Patrol",
    "wof:placetype":"venue"
},
  "geometry": {"coordinates":[-3.050262,53.809921],"type":"Point"}
}