{
  "type": "Feature",
  "properties": {
    "addr:full":"38 Trevallen Av Neath Neath Port Talbot SA11 3UR",
    "addr:housenumber":"38",
    "addr:postcode":"sa11 3ur",
    "addr:street":"Av Neath",
    "iso:country":"GB",
    "sg:address":"38 Trevallen Av",
    "sg:city":"Neath",
    "sg:classifiers":[
        {
            "category":"Shopping",
            "subcategory":"Discount & Variety Stores",
            "type":"Retail Goods"
        }
    ],
    "sg:phone":"+44 1639 638606",
    "sg:postcode":"SA11 3UR",
    "sg:province":"Neath Port Talbot",
    "sg:tags":[
        "rental",
        "menswear"
    ],
    "wof:name":"Clive Thomas",
    "wof:placetype":"venue"
},
  "geometry": {"coordinates":[-3.7876589298,51.6534690857],"type":"Point"}
}