{
  "type": "Feature",
  "properties": {
    "addr:full":"68 Bridge Street, Linwood Paisley Renfrewshire PA3 3DR",
    "addr:housenumber":"68",
    "addr:postcode":"pa3 3dr",
    "addr:street":"Bridge Street",
    "iso:country":"GB",
    "sg:address":"68 Bridge Street, Linwood",
    "sg:city":"Paisley",
    "sg:classifiers":[
        {
            "category":"Professional",
            "subcategory":"Engineering",
            "type":"Services"
        }
    ],
    "sg:phone":"+44 1505 321127",
    "sg:postcode":"PA3 3DR",
    "sg:province":"Renfrewshire",
    "sg:tags":[
        "engineer",
        "structural"
    ],
    "wof:name":"Scotia Trading Companies Ltd.",
    "wof:placetype":"venue"
},
  "geometry": {"coordinates":[-4.4907751083,55.8498344421],"type":"Point"}
}