{
  "type": "Feature",
  "properties": {
    "iso:country":"GB",
    "sg:address":"60 Oakwood Avenue",
    "sg:city":"New Milton",
    "sg:classifiers":[
        {
            "category":"Retail",
            "subcategory":"Auto Repair",
            "type":"Services"
        }
    ],
    "sg:postcode":"BH25 5EA",
    "sg:province":"Hampshire",
    "sg:tags":[
        "modification",
        "garage"
    ],
    "wof:name":"M Gibbs Mobile Mechanic",
    "wof:placetype":"venue"
},
  "geometry": {"coordinates":[-1.646044,50.763283],"type":"Point"}
}