{
  "type": "Feature",
  "properties": {
    "addr:full":"52 Norfolk Avenue Slough Berkshire SL1 3AD",
    "addr:housenumber":"52",
    "addr:postcode":"sl1 3ad",
    "addr:street":"Norfolk Avenue",
    "iso:country":"GB",
    "sg:address":"52 Norfolk Avenue",
    "sg:city":"Slough",
    "sg:classifiers":[
        {
            "category":"Shopping",
            "subcategory":"Hobbies, Toys, & Games",
            "type":"Retail Goods"
        }
    ],
    "sg:phone":"+44 1753 531906",
    "sg:postcode":"SL1 3AD",
    "sg:province":"Berkshire",
    "sg:tags":[
        "shop",
        "toy"
    ],
    "wof:name":"Birchwood Models",
    "wof:placetype":"venue"
},
  "geometry": {"coordinates":[-0.611934,51.526505],"type":"Point"}
}