{
  "type": "Feature",
  "properties": {
    "addr:full":"2 Cottesmore Rd Cleethorpes Lincolnshire DN35 0RY",
    "addr:housenumber":"2",
    "addr:postcode":"dn35 0ry",
    "addr:street":"Cottesmore Rd",
    "iso:country":"GB",
    "sg:address":"2 Cottesmore Rd",
    "sg:city":"Cleethorpes",
    "sg:classifiers":[
        {
            "category":"Transit Center",
            "subcategory":"Passenger",
            "type":"Transportation"
        }
    ],
    "sg:phone":"+44 1472 358000",
    "sg:postcode":"DN35 0RY",
    "sg:province":"Lincolnshire",
    "sg:tags":[
        "airport"
    ],
    "wof:name":"Cabbycars",
    "wof:placetype":"venue"
},
  "geometry": {"coordinates":[-0.0374599993,53.542930603],"type":"Point"}
}