{
  "type": "Feature",
  "properties": {
    "addr:full":"Cambrook House, Eastcourt Rd, Temple Cloud Bristol Somerset BS39 5BU",
    "addr:postcode":"bs39 5bu",
    "addr:street":"Eastcourt Rd",
    "iso:country":"GB",
    "sg:address":"Cambrook House, Eastcourt Rd, Temple Cloud",
    "sg:city":"Bristol",
    "sg:classifiers":[
        {
            "category":"Wholesale",
            "subcategory":"Sporting Goods",
            "type":"Manufacturing & Wholesale Goods"
        }
    ],
    "sg:phone":"+44 1761 451049",
    "sg:postcode":"BS39 5BU",
    "sg:province":"Somerset",
    "sg:tags":[
        "mnfr",
        "sport",
        "equipment"
    ],
    "wof:name":"Shapemaster",
    "wof:placetype":"venue"
},
  "geometry": {"coordinates":[-2.531478,51.317448],"type":"Point"}
}