{
  "type": "Feature",
  "properties": {
    "iso:country":"GB",
    "sg:address":"10 Silver Hill",
    "sg:city":"Tenterden",
    "sg:classifiers":[
        {
            "category":"Professional",
            "subcategory":"Art Services",
            "type":"Services"
        }
    ],
    "sg:postcode":"TN30 6NE",
    "sg:province":"Kent",
    "sg:tags":[
        "photographer"
    ],
    "wof:name":"Kemp Photography",
    "wof:placetype":"venue"
},
  "geometry": {"coordinates":[0.695043,51.078114],"type":"Point"}
}