{
  "type": "Feature",
  "properties": {
    "addr:full":"The Rosary, West Hill Wincanton Somerset BA9 9BY",
    "addr:postcode":"ba9 9by",
    "addr:street":"West",
    "iso:country":"GB",
    "sg:address":"The Rosary, West Hill",
    "sg:city":"Wincanton",
    "sg:classifiers":[
        {
            "category":"Real Estate",
            "subcategory":"Real Estate Agent",
            "type":"Services"
        }
    ],
    "sg:postcode":"BA9 9BY",
    "sg:province":"Somerset",
    "wof:name":"Three Counties Property Co",
    "wof:placetype":"venue"
},
  "geometry": {"coordinates":[-2.413179,51.0578],"type":"Point"}
}