{
  "type": "Feature",
  "properties": {
    "addr:full":"Cleveland Centre, Newton Mall Middlesbrough North Yorkshire TS1 2NW",
    "addr:postcode":"ts1 2nw",
    "iso:country":"GB",
    "sg:address":"Cleveland Centre, Newton Mall",
    "sg:city":"Middlesbrough",
    "sg:classifiers":[
        {
            "category":"Communications",
            "subcategory":"Film & Video Production",
            "type":"Services"
        }
    ],
    "sg:phone":"+44 1642 243036",
    "sg:postcode":"TS1 2NW",
    "sg:province":"North Yorkshire",
    "sg:tags":[
        "tv"
    ],
    "wof:name":"Granada TV & Video",
    "wof:placetype":"venue"
},
  "geometry": {"coordinates":[-1.236569,54.572971],"type":"Point"}
}