{
  "type": "Feature",
  "properties": {
    "iso:country":"GB",
    "sg:address":"25 Market Street",
    "sg:city":"Wigan",
    "sg:classifiers":[
        {
            "category":"Shopping",
            "subcategory":"Florist",
            "type":"Retail Goods"
        }
    ],
    "sg:phone":"+44 1942 256700",
    "sg:postcode":"WN2 3AE",
    "sg:province":"Lancashire",
    "wof:name":"Margaret Platts",
    "wof:placetype":"venue"
},
  "geometry": {"coordinates":[-2.577113,53.53635],"type":"Point"}
}