{
  "type": "Feature",
  "properties": {
    "iso:country":"GB",
    "sg:address":"41-54 Buckingham Gate",
    "sg:city":"Westminster",
    "sg:classifiers":[
        {
            "category":"Restaurant",
            "type":"Food & Drink"
        }
    ],
    "sg:phone":"+44 20 7821 1931",
    "sg:postcode":"SW1E 6AF",
    "sg:province":"Greater London",
    "sg:tags":[
        "chinese"
    ],
    "wof:name":"Inn Of Happiness",
    "wof:placetype":"venue"
},
  "geometry": {"coordinates":[-0.137669,51.498734],"type":"Point"}
}