{
  "type": "Feature",
  "properties": {
    "addr:full":"128 St Albans Road, Arnold Nottingham Nottinghamshire NG5 6GW",
    "addr:housenumber":"128",
    "addr:postcode":"ng5 6gw",
    "addr:street":"St Albans Road",
    "iso:country":"GB",
    "sg:address":"128 St Albans Road, Arnold",
    "sg:city":"Nottingham",
    "sg:classifiers":[
        {
            "category":"Building & Trades",
            "subcategory":"Construction",
            "type":"Services"
        }
    ],
    "sg:phone":"+44 1636 636005",
    "sg:postcode":"NG5 6GW",
    "sg:province":"Nottinghamshire",
    "sg:tags":[
        "builder"
    ],
    "wof:name":"N J C (Nottingham) Ltd.",
    "wof:placetype":"venue"
},
  "geometry": {"coordinates":[-1.1367950439,53.0029220581],"type":"Point"}
}