{
  "type": "Feature",
  "properties": {
    "iso:country":"GB",
    "sg:address":"36 Avon Close",
    "sg:city":"Newport Pagnell",
    "sg:classifiers":[
        {
            "category":"Home & Garden",
            "subcategory":"Hardware",
            "type":"Retail Goods"
        }
    ],
    "sg:postcode":"MK16 9DH",
    "sg:province":"Buckinghamshire",
    "sg:tags":[
        "heat",
        "mech",
        "exchanger"
    ],
    "wof:name":"Funke",
    "wof:placetype":"venue"
},
  "geometry": {"coordinates":[-0.7181659937,52.081943512],"type":"Point"}
}