{
  "type": "Feature",
  "properties": {
    "addr:full":"Castle Farm, Raisbeck Penrith Cumbria CA10 3SG",
    "addr:postcode":"ca10 3sg",
    "addr:street":"Raisbeck",
    "iso:country":"GB",
    "sg:address":"Castle Farm, Raisbeck",
    "sg:city":"Penrith",
    "sg:classifiers":[
        {
            "category":"Manufacturing",
            "subcategory":"Glass & Minerals",
            "type":"Manufacturing & Wholesale Goods"
        }
    ],
    "sg:phone":"+44 15396 24481",
    "sg:postcode":"CA10 3SG",
    "sg:province":"Cumbria",
    "sg:tags":[
        "chalk",
        "stone",
        "slate"
    ],
    "wof:name":"K R Venning Slaters Ltd.",
    "wof:placetype":"venue"
},
  "geometry": {"coordinates":[-2.5491890907,54.461479187],"type":"Point"}
}