{
  "type": "Feature",
  "properties": {
    "addr:full":"Averies, Bolney Road, Cowfold Horsham West Sussex RH13 8AZ",
    "addr:postcode":"rh13 8az",
    "addr:street":"Bolney Road",
    "iso:country":"GB",
    "sg:address":"Averies, Bolney Road, Cowfold",
    "sg:city":"Horsham",
    "sg:classifiers":[
        {
            "category":"Home & Garden",
            "subcategory":"Home Furnishings",
            "type":"Retail Goods"
        },
        {
            "category":"Professional",
            "subcategory":"Art Services",
            "type":"Services"
        }
    ],
    "sg:phone":"+44 1403 864866",
    "sg:postcode":"RH13 8AZ",
    "sg:province":"West Sussex",
    "sg:tags":[
        "interior",
        "furnishers",
        "designer",
        "kitchen",
        "planner"
    ],
    "wof:name":"Clifford Interiors",
    "wof:placetype":"venue"
},
  "geometry": {"coordinates":[-0.2553,50.991692],"type":"Point"}
}