{
  "type": "Feature",
  "properties": {
    "iso:country":"GB",
    "sg:address":"Maraquita, Horsham Road",
    "sg:city":"Cranleigh",
    "sg:classifiers":[
        {
            "category":"Travel",
            "subcategory":"Hostel",
            "type":"Entertainment"
        }
    ],
    "sg:postcode":"GU6 8DU",
    "sg:province":"Surrey",
    "sg:tags":[
        "youth"
    ],
    "wof:name":"Cocos Kids Club",
    "wof:placetype":"venue"
},
  "geometry": {"coordinates":[-0.482999,51.141541],"type":"Point"}
}