{
  "type": "Feature",
  "properties": {
    "iso:country":"GB",
    "sg:address":"Thame Road",
    "sg:city":"Princes Risborough",
    "sg:classifiers":[
        {
            "category":"Government",
            "subcategory":"Post Office",
            "type":"Public Place"
        }
    ],
    "sg:phone":"+44 1844 345196",
    "sg:postcode":"HP27 9SF",
    "sg:province":"Buckinghamshire",
    "wof:name":"Longwick Post Office & Stores",
    "wof:placetype":"venue"
},
  "geometry": {"coordinates":[-0.85411,51.735504],"type":"Point"}
}