{
  "type": "Feature",
  "properties": {
    "addr:full":"52 Surrenden Crescent Brighton East Sussex BN1 6WF",
    "addr:housenumber":"52",
    "addr:postcode":"bn1 6wf",
    "addr:street":"Surrenden Crescent",
    "iso:country":"GB",
    "sg:address":"52 Surrenden Crescent",
    "sg:city":"Brighton",
    "sg:classifiers":[
        {
            "category":"Autos & Motor Vehicles",
            "subcategory":"Automobile Sales",
            "type":"Retail Goods"
        }
    ],
    "sg:postcode":"BN1 6WF",
    "sg:province":"East Sussex",
    "sg:tags":[
        "commercial"
    ],
    "wof:name":"First Avenue Commercials",
    "wof:placetype":"venue"
},
  "geometry": {"coordinates":[-0.1480699927,50.8526306152],"type":"Point"}
}