{
  "type": "Feature",
  "properties": {
    "addr:full":"Prescriptions, Clarence Wharf, Barnstaple St Bideford Devon EX39 4AU",
    "addr:postcode":"ex39 4au",
    "addr:street":"Barnstaple St",
    "iso:country":"GB",
    "sg:address":"Prescriptions, Clarence Wharf, Barnstaple St",
    "sg:city":"Bideford",
    "sg:classifiers":[
        {
            "category":"Health Services",
            "subcategory":"Doctor",
            "type":"Services"
        }
    ],
    "sg:phone":"+44 1237 421833",
    "sg:postcode":"EX39 4AU",
    "sg:province":"Devon",
    "sg:tags":[
        "practitioners"
    ],
    "wof:name":"Herriott, S",
    "wof:placetype":"venue"
},
  "geometry": {"coordinates":[-4.2042589188,51.0192489624],"type":"Point"}
}