{
  "type": "Feature",
  "properties": {
    "addr:full":"Dainebridge Cres Derby Derbyshire DE21 2BD",
    "addr:postcode":"de21 2bd",
    "addr:street":"Dainebridge Cres",
    "iso:country":"GB",
    "sg:address":"Dainebridge Cres",
    "sg:city":"Derby",
    "sg:classifiers":[
        {
            "category":"Bars & Pubs",
            "type":"Food & Drink"
        }
    ],
    "sg:phone":"+44 1332 280019",
    "sg:postcode":"DE21 2BD",
    "sg:province":"Derbyshire",
    "sg:tags":[
        "pubs",
        "inn"
    ],
    "wof:name":"Oak & Acorn",
    "wof:placetype":"venue"
},
  "geometry": {"coordinates":[-1.4270340204,52.9417533875],"type":"Point"}
}