{
  "type": "Feature",
  "properties": {
    "iso:country":"GB",
    "sg:address":"Templar House, 81-87 High Holborn",
    "sg:city":"London",
    "sg:classifiers":[
        {
            "category":"Utilities",
            "subcategory":"Electric",
            "type":"Services"
        }
    ],
    "sg:phone":"+44 20 7242 9050",
    "sg:postcode":"WC1V 6NU",
    "sg:province":"Greater London",
    "sg:tags":[
        "electricity"
    ],
    "wof:name":"Electric London Ltd.",
    "wof:placetype":"venue"
},
  "geometry": {"coordinates":[-0.245799,51.536209],"type":"Point"}
}