{
  "type": "Feature",
  "properties": {
    "addr:full":"1 Colyton Road London Greater London SE22 0NE",
    "addr:housenumber":"1",
    "addr:postcode":"se22 0ne",
    "addr:street":"Colyton Road",
    "iso:country":"GB",
    "sg:address":"1 Colyton Road",
    "sg:city":"London",
    "sg:classifiers":[
        {
            "category":"Social Services",
            "type":"Services"
        }
    ],
    "sg:phone":"+44 20 8693 8831",
    "sg:postcode":"SE22 0NE",
    "sg:province":"Greater London",
    "wof:name":"Colyton Road Residential Unit",
    "wof:placetype":"venue"
},
  "geometry": {"coordinates":[-0.0599059984,51.4544792175],"type":"Point"}
}