{
  "type": "Feature",
  "properties": {
    "iso:country":"GB",
    "sg:address":"37a Lancaster Road",
    "sg:city":"London",
    "sg:classifiers":[
        {
            "category":"Health Services",
            "subcategory":"Doctor",
            "type":"Services"
        }
    ],
    "sg:phone":"+44 20 7291 6666",
    "sg:postcode":"W11 1QJ",
    "sg:province":"Greater London",
    "sg:tags":[
        "practitioners"
    ],
    "wof:name":"Doctorcall Ltd.",
    "wof:placetype":"venue"
},
  "geometry": {"coordinates":[-0.204684,51.517769],"type":"Point"}
}