{
  "type": "Feature",
  "properties": {
    "iso:country":"GB",
    "sg:address":"Ilkeston Road",
    "sg:city":"Nottingham",
    "sg:classifiers":[
        {
            "category":"Bars & Pubs",
            "type":"Food & Drink"
        }
    ],
    "sg:phone":"+44 115 970 3491",
    "sg:postcode":"NG7 3HB",
    "sg:province":"Nottinghamshire",
    "sg:tags":[
        "pubs",
        "inn"
    ],
    "wof:name":"The Old Peacock",
    "wof:placetype":"venue"
},
  "geometry": {"coordinates":[-1.166839,52.956139],"type":"Point"}
}