{
  "type": "Feature",
  "properties": {
    "addr:full":"Gill Lane, Longton Preston Lancashire PR4 4SS",
    "addr:postcode":"pr4 4ss",
    "addr:street":"Gill Lane",
    "iso:country":"GB",
    "sg:address":"Gill Lane, Longton",
    "sg:city":"Preston",
    "sg:classifiers":[
        {
            "category":"Home & Garden",
            "subcategory":"Garden Supply",
            "type":"Retail Goods"
        }
    ],
    "sg:postcode":"PR4 4SS",
    "sg:province":"Lancashire",
    "sg:tags":[
        "tree",
        "shrub"
    ],
    "wof:name":"R & J H Duckworth",
    "wof:placetype":"venue"
},
  "geometry": {"coordinates":[-2.7562019825,53.7123260498],"type":"Point"}
}