{
  "type": "Feature",
  "properties": {
    "addr:full":"55 Wilson Marriage Rd Colchester Essex CO4 4DG",
    "addr:housenumber":"55",
    "addr:postcode":"co4 4dg",
    "addr:street":"Wilson Marriage Rd",
    "iso:country":"GB",
    "sg:address":"55 Wilson Marriage Rd",
    "sg:city":"Colchester",
    "sg:classifiers":[
        {
            "category":"Social Services",
            "subcategory":"Adult Care",
            "type":"Services"
        }
    ],
    "sg:phone":"+44 1206 513885",
    "sg:postcode":"CO4 4DG",
    "sg:province":"Essex",
    "sg:tags":[
        "domestic",
        "cleaning"
    ],
    "wof:name":"Dust Busters",
    "wof:placetype":"venue"
},
  "geometry": {"coordinates":[0.923751,51.898838],"type":"Point"}
}