{
  "type": "Feature",
  "properties": {
    "addr:full":"Home Farm, Bower House Tye, Polstead Colchester Essex CO6 5DE",
    "addr:postcode":"co6 5de",
    "addr:street":"Tye",
    "iso:country":"GB",
    "sg:address":"Home Farm, Bower House Tye, Polstead",
    "sg:city":"Colchester",
    "sg:classifiers":[
        {
            "category":"Sports & Exercise",
            "subcategory":"Stables",
            "type":"Entertainment"
        }
    ],
    "sg:phone":"+44 1787 210188",
    "sg:postcode":"CO6 5DE",
    "sg:province":"Essex",
    "sg:tags":[
        "education",
        "equestrian"
    ],
    "wof:name":"Home Farm Livery Stables",
    "wof:placetype":"venue"
},
  "geometry": {"coordinates":[0.8991829753,52.0058708191],"type":"Point"}
}