{
  "type": "Feature",
  "properties": {
    "iso:country":"GB",
    "sg:address":"Automatic Telephone Exchange",
    "sg:city":"Swansea",
    "sg:classifiers":[
        {
            "category":"Building & Trades",
            "subcategory":"Cleaning & Sanitation",
            "type":"Services"
        }
    ],
    "sg:postcode":"SA1 2AB",
    "sg:province":"Neath Port Talbot",
    "sg:tags":[
        "commercial"
    ],
    "wof:name":"Minster Cleaning Services",
    "wof:placetype":"venue"
},
  "geometry": {"coordinates":[-3.940928936,51.6231536865],"type":"Point"}
}