{
  "type": "Feature",
  "properties": {
    "iso:country":"GB",
    "sg:address":"Legh House, 117 Rylands Lane",
    "sg:city":"Weymouth",
    "sg:classifiers":[
        {
            "category":"Health Services",
            "subcategory":"Nursing And Care Facility",
            "type":"Services"
        },
        {
            "category":"Organizations",
            "subcategory":"Community Association",
            "type":"Services"
        }
    ],
    "sg:phone":"+44 1305 773663",
    "sg:postcode":"DT4 9QB",
    "sg:province":"Dorset",
    "sg:tags":[
        "society",
        "housing",
        "home"
    ],
    "wof:name":"The Abbeyfield Weymouth Society Ltd.",
    "wof:placetype":"venue"
},
  "geometry": {"coordinates":[-2.471826,50.598137],"type":"Point"}
}