{
  "type": "Feature",
  "properties": {
    "addr:full":"Strathburn Drive Glenrothes Fife KY7 4UQ",
    "addr:postcode":"ky7 4uq",
    "addr:street":"Strathburn Drive",
    "iso:country":"GB",
    "sg:address":"Strathburn Drive",
    "sg:city":"Glenrothes",
    "sg:classifiers":[
        {
            "category":"Health Services",
            "subcategory":"Nursing And Care Facility",
            "type":"Services"
        }
    ],
    "sg:postcode":"KY7 4UQ",
    "sg:province":"Fife",
    "sg:tags":[
        "home"
    ],
    "wof:name":"Abbotsford Nursing Home",
    "wof:placetype":"venue"
},
  "geometry": {"coordinates":[-3.172863,56.178074],"type":"Point"}
}