{
  "type": "Feature",
  "properties": {
    "iso:country":"GB",
    "sg:address":"72 Brand Street",
    "sg:city":"Glasgow",
    "sg:classifiers":[
        {
            "category":"Building & Trades",
            "subcategory":"Plumbing",
            "type":"Services"
        }
    ],
    "sg:phone":"+44 141 427 3320",
    "sg:postcode":"G51 1DG",
    "sg:province":"Glasgow City",
    "sg:tags":[
        "heating"
    ],
    "wof:name":"Alert (24 Hour) Plumbing Services Ltd.",
    "wof:placetype":"venue"
},
  "geometry": {"coordinates":[-4.2954621315,55.8536987305],"type":"Point"}
}