{
  "type": "Feature",
  "properties": {
    "addr:full":"11 Ossington Close, Meden Vale Mansfield Derbyshire NG20 9PZ",
    "addr:housenumber":"11",
    "addr:postcode":"ng20 9pz",
    "addr:street":"Ossington Close",
    "iso:country":"GB",
    "sg:address":"11 Ossington Close, Meden Vale",
    "sg:city":"Mansfield",
    "sg:classifiers":[
        {
            "category":"Food & Beverages",
            "subcategory":"Supermarket",
            "type":"Retail Goods"
        }
    ],
    "sg:phone":"+44 1623 846642",
    "sg:postcode":"NG20 9PZ",
    "sg:province":"Derbyshire",
    "wof:name":"Youngs Food Stores",
    "wof:placetype":"venue"
},
  "geometry": {"coordinates":[-1.135247,53.21991],"type":"Point"}
}