{
  "type": "Feature",
  "properties": {
    "iso:country":"GB",
    "sg:address":"60 Derby Street",
    "sg:city":"Barrow-in-furness",
    "sg:classifiers":[
        {
            "category":"Home & Garden",
            "subcategory":"Home Furnishings",
            "type":"Retail Goods"
        },
        {
            "category":"Home & Garden",
            "subcategory":"Carpets & Floor Coverings",
            "type":"Retail Goods"
        }
    ],
    "sg:phone":"+44 1229 839431",
    "sg:postcode":"LA13 9TQ",
    "sg:province":"Cumbria",
    "sg:tags":[
        "fitting",
        "rug",
        "matting",
        "carpets"
    ],
    "wof:name":"Dennis Harrison",
    "wof:placetype":"venue"
},
  "geometry": {"coordinates":[-3.2111449242,54.1114883423],"type":"Point"}
}