{
  "type": "Feature",
  "properties": {
    "addr:full":"21-23 Westgate, Baildon Shipley West Yorkshire BD17 5EH",
    "addr:housenumber":"21-23",
    "addr:postcode":"bd17 5eh",
    "addr:street":"Westgate Baildon",
    "iso:country":"GB",
    "sg:address":"21-23 Westgate, Baildon",
    "sg:city":"Shipley",
    "sg:classifiers":[
        {
            "category":"Insurance",
            "subcategory":"Insurance Agent",
            "type":"Services"
        }
    ],
    "sg:phone":"+44 1274 591382",
    "sg:postcode":"BD17 5EH",
    "sg:province":"West Yorkshire",
    "wof:name":"Budget Retail Ltd.",
    "wof:placetype":"venue"
},
  "geometry": {"coordinates":[-1.767286,53.852966],"type":"Point"}
}