{
  "type": "Feature",
  "properties": {
    "iso:country":"GB",
    "sg:address":"Dairy House Farm, Holmes Chapel Road, Sproston",
    "sg:city":"Crewe",
    "sg:classifiers":[
        {
            "category":"Farming",
            "subcategory":"Livestock Farm",
            "type":"Manufacturing & Wholesale Goods"
        }
    ],
    "sg:phone":"+44 1606 832147",
    "sg:postcode":"CW4 7LP",
    "sg:province":"Cheshire",
    "sg:tags":[
        "others"
    ],
    "wof:name":"John A Sherwin & C J",
    "wof:placetype":"venue"
},
  "geometry": {"coordinates":[-2.400523901,53.1988143921],"type":"Point"}
}