{
  "type": "Feature",
  "properties": {
    "addr:full":"12 Weatherbury Way Dorchester Dorset DT1 2EF",
    "addr:housenumber":"12",
    "addr:postcode":"dt1 2ef",
    "addr:street":"Weatherbury Way",
    "iso:country":"GB",
    "sg:address":"12 Weatherbury Way",
    "sg:city":"Dorchester",
    "sg:classifiers":[
        {
            "category":"Social Services",
            "subcategory":"Retirement Home",
            "type":"Services"
        }
    ],
    "sg:phone":"+44 1305 265411",
    "sg:postcode":"DT1 2EF",
    "sg:province":"Dorset",
    "sg:tags":[
        "historian",
        "family"
    ],
    "wof:name":"Dorset Ancestral Research",
    "wof:placetype":"venue"
},
  "geometry": {"coordinates":[-2.4360039234,50.7011299133],"type":"Point"}
}