{
  "type": "Feature",
  "properties": {
    "addr:full":"2-4 Bridge Road, St Mary Cray Orpington Kent BR5 2BH",
    "addr:housenumber":"2-4",
    "addr:postcode":"br5 2bh",
    "addr:street":"Bridge Road",
    "iso:country":"GB",
    "sg:address":"2-4 Bridge Road, St Mary Cray",
    "sg:city":"Orpington",
    "sg:classifiers":[
        {
            "category":"Shopping",
            "subcategory":"Clothing, Apparel, & Fashions",
            "type":"Retail Goods"
        }
    ],
    "sg:phone":"+44 1689 837975",
    "sg:postcode":"BR5 2BH",
    "sg:province":"Kent",
    "sg:tags":[
        "sportswear"
    ],
    "wof:name":"C A B Fashions",
    "wof:placetype":"venue"
},
  "geometry": {"coordinates":[0.108531,51.388222],"type":"Point"}
}