{
  "type": "Feature",
  "properties": {
    "iso:country":"GB",
    "sg:address":"Candyburn Farm",
    "sg:city":"Biggar",
    "sg:classifiers":[
        {
            "category":"Farming",
            "subcategory":"Farm",
            "type":"Manufacturing & Wholesale Goods"
        }
    ],
    "sg:phone":"+44 1899 860243",
    "sg:postcode":"ML12 6QY",
    "sg:province":"Dumfries and Galloway",
    "sg:tags":[
        "mixed",
        "crop"
    ],
    "wof:name":"J H Noble",
    "wof:placetype":"venue"
},
  "geometry": {"coordinates":[-3.5230190754,55.624420166],"type":"Point"}
}