{
  "type": "Feature",
  "properties": {
    "addr:full":"109 Grange Road Ramsgate Kent CT11 9PY",
    "addr:housenumber":"109",
    "addr:postcode":"ct11 9py",
    "addr:street":"Grange Road Ramsgate",
    "iso:country":"GB",
    "sg:address":"109 Grange Road",
    "sg:city":"Ramsgate",
    "sg:classifiers":[
        {
            "category":"Building & Trades",
            "subcategory":"Plumbing",
            "type":"Services"
        }
    ],
    "sg:phone":"+44 1843 851272",
    "sg:postcode":"CT11 9PY",
    "sg:province":"Kent",
    "sg:tags":[
        "plumber",
        "heating"
    ],
    "wof:name":"Grummant (Heating & Plumbing Services) Ltd.",
    "wof:placetype":"venue"
},
  "geometry": {"coordinates":[1.4059950113,51.3340873718],"type":"Point"}
}