{
  "type": "Feature",
  "properties": {
    "iso:country":"GB",
    "sg:address":"Rockfield Road",
    "sg:city":"Monmouth",
    "sg:classifiers":[
        {
            "category":"Education",
            "subcategory":"School",
            "type":"Public Place"
        }
    ],
    "sg:phone":"+44 1600 713458",
    "sg:postcode":"NP25 5BA",
    "sg:province":"Gloucestershire",
    "sg:tags":[
        "local",
        "authority"
    ],
    "wof:name":"Overmonnow Primary School",
    "wof:placetype":"venue"
},
  "geometry": {"coordinates":[-2.727709,51.814934],"type":"Point"}
}