{
  "type": "Feature",
  "properties": {
    "addr:full":"Suite 24 Fitzroy House, Lynwood Drive Worcester Park Surrey KT4 7AT",
    "addr:postcode":"kt4 7at",
    "addr:street":"Suite 24;Lynwood Drive",
    "iso:country":"GB",
    "sg:address":"Suite 24 Fitzroy House, Lynwood Drive",
    "sg:city":"Worcester Park",
    "sg:classifiers":[
        {
            "category":"Professional",
            "subcategory":"Accounting & Tax Preparation",
            "type":"Services"
        }
    ],
    "sg:phone":"+44 20 8337 8963",
    "sg:postcode":"KT4 7AT",
    "sg:province":"Surrey",
    "sg:tags":[
        "accountant",
        "chartered"
    ],
    "wof:name":"Kamal Hussain & Co",
    "wof:placetype":"venue"
},
  "geometry": {"coordinates":[-0.24455,51.378323],"type":"Point"}
}