{
  "type": "Feature",
  "properties": {
    "iso:country":"GB",
    "sg:address":"Grove Green",
    "sg:city":"Maidstone",
    "sg:classifiers":[
        {
            "category":"Health Services",
            "subcategory":"Doctor",
            "type":"Services"
        }
    ],
    "sg:phone":"+44 1622 736777",
    "sg:postcode":"ME14 5PX",
    "sg:province":"Kent",
    "sg:tags":[
        "practitioners"
    ],
    "wof:name":"Whitaker, M J",
    "wof:placetype":"venue"
},
  "geometry": {"coordinates":[0.5563589931,51.275680542],"type":"Point"}
}