{
  "type": "Feature",
  "properties": {
    "addr:full":"Whalley Bank Trading Estate, Brunswick Street Blackburn Lancashire BB2 1NR",
    "addr:postcode":"bb2 1nr",
    "addr:street":"Whalley;Trading;Brunswick Street",
    "iso:country":"GB",
    "sg:address":"Whalley Bank Trading Estate, Brunswick Street",
    "sg:city":"Blackburn",
    "sg:classifiers":[
        {
            "category":"Retail",
            "subcategory":"Auto Repair",
            "type":"Services"
        }
    ],
    "sg:phone":"+44 1254 662330",
    "sg:postcode":"BB2 1NR",
    "sg:province":"Lancashire",
    "sg:tags":[
        "modification",
        "garage"
    ],
    "wof:name":"Trendsetter Motors M O T  Centre Ltd.",
    "wof:placetype":"venue"
},
  "geometry": {"coordinates":[-2.490584,53.744656],"type":"Point"}
}