{
  "type": "Feature",
  "properties": {
    "iso:country":"GB",
    "sg:address":"Lymington Road, Setley",
    "sg:city":"Brockenhurst",
    "sg:classifiers":[
        {
            "category":"Bars & Pubs",
            "type":"Food & Drink"
        }
    ],
    "sg:phone":"+44 1590 623449",
    "sg:postcode":"SO42 7UF",
    "sg:province":"Hampshire",
    "sg:tags":[
        "pubs",
        "inn"
    ],
    "wof:name":"Filly Inn ?the}",
    "wof:placetype":"venue"
},
  "geometry": {"coordinates":[-1.572004,50.818642],"type":"Point"}
}