{
  "type": "Feature",
  "properties": {
    "iso:country":"GB",
    "sg:address":"133 Trysull Road",
    "sg:city":"Wolverhampton",
    "sg:classifiers":[
        {
            "category":"Retail",
            "subcategory":"Driving School",
            "type":"Services"
        }
    ],
    "sg:phone":"+44 1902 334542",
    "sg:postcode":"WV3 7JG",
    "sg:province":"Staffordshire",
    "wof:name":"Merryhill Driving School",
    "wof:placetype":"venue"
},
  "geometry": {"coordinates":[-2.16335392,52.573589325],"type":"Point"}
}