{
  "type": "Feature",
  "properties": {
    "addr:full":"60 Abel Street Burnley Lancashire BB10 1QU",
    "addr:housenumber":"60",
    "addr:postcode":"bb10 1qu",
    "addr:street":"Abel Street",
    "iso:country":"GB",
    "sg:address":"60 Abel Street",
    "sg:city":"Burnley",
    "sg:classifiers":[
        {
            "category":"Shopping",
            "subcategory":"Pharmacy",
            "type":"Retail Goods"
        }
    ],
    "sg:phone":"+44 1282 423722",
    "sg:postcode":"BB10 1QU",
    "sg:province":"Lancashire",
    "sg:tags":[
        "pharmacist",
        "store",
        "drug",
        "chemist"
    ],
    "wof:name":"Coopers Chemist",
    "wof:placetype":"venue"
},
  "geometry": {"coordinates":[-2.2400081158,53.8009719849],"type":"Point"}
}