{
  "type": "Feature",
  "properties": {
    "addr:full":"Bramble House, London Road Retford Nottinghamshire DN22 7JG",
    "addr:postcode":"dn22 7jg",
    "addr:street":"London Road",
    "iso:country":"GB",
    "sg:address":"Bramble House, London Road",
    "sg:city":"Retford",
    "sg:classifiers":[
        {
            "category":"Shopping",
            "subcategory":"Bicycles & Sporting Goods",
            "type":"Retail Goods"
        }
    ],
    "sg:phone":"+44 1777 701707",
    "sg:postcode":"DN22 7JG",
    "sg:province":"Nottinghamshire",
    "sg:tags":[
        "riding",
        "saddlery",
        "wear"
    ],
    "wof:name":"Retford Saddlery Services",
    "wof:placetype":"venue"
},
  "geometry": {"coordinates":[-0.9355040193,53.3160743713],"type":"Point"}
}