{
  "type": "Feature",
  "properties": {
    "addr:full":"Fishwick Mains Berwick-upon-tweed Northumberland TD15 1XQ",
    "addr:postcode":"td15 1xq",
    "addr:street":"Northumberland",
    "iso:country":"GB",
    "sg:address":"Fishwick Mains",
    "sg:city":"Berwick-upon-tweed",
    "sg:classifiers":[
        {
            "category":"Farming",
            "subcategory":"Farm",
            "type":"Manufacturing & Wholesale Goods"
        }
    ],
    "sg:postcode":"TD15 1XQ",
    "sg:province":"Northumberland",
    "sg:tags":[
        "mixed",
        "crop"
    ],
    "wof:name":"John Close & Son Ltd.",
    "wof:placetype":"venue"
},
  "geometry": {"coordinates":[-2.007024,55.771435],"type":"Point"}
}