{
  "type": "Feature",
  "properties": {
    "addr:full":"Lower Cottage, St Weonards Hereford Herefordshire HR2 8QF",
    "addr:postcode":"hr2 8qf",
    "addr:street":"St Weonards",
    "iso:country":"GB",
    "sg:address":"Lower Cottage, St Weonards",
    "sg:city":"Hereford",
    "sg:classifiers":[
        {
            "category":"Building & Trades",
            "subcategory":"Plumbing",
            "type":"Services"
        }
    ],
    "sg:phone":"+44 1981 580598",
    "sg:postcode":"HR2 8QF",
    "sg:province":"Herefordshire",
    "sg:tags":[
        "central",
        "heating"
    ],
    "wof:name":"Joseph & Risbey Plumbing & Heating",
    "wof:placetype":"venue"
},
  "geometry": {"coordinates":[-2.7751600742,51.9166183472],"type":"Point"}
}