{
  "type": "Feature",
  "properties": {
    "addr:full":"Basement 49, Kensington High Street London Greater London W8 5ED",
    "addr:housenumber":"49",
    "addr:postcode":"w8 5ed",
    "addr:street":"Kensington High Street",
    "iso:country":"GB",
    "sg:address":"Basement 49, Kensington High Street",
    "sg:city":"London",
    "sg:classifiers":[
        {
            "category":"Personal",
            "subcategory":"Beauty Salon",
            "type":"Services"
        }
    ],
    "sg:phone":"+44 20 7967 5167",
    "sg:postcode":"W8 5ED",
    "sg:province":"Greater London",
    "sg:tags":[
        "unisex",
        "hairdresser"
    ],
    "wof:name":"Hair by Fairy",
    "wof:placetype":"venue"
},
  "geometry": {"coordinates":[-0.1881590039,51.5023803711],"type":"Point"}
}