{
  "type": "Feature",
  "properties": {
    "addr:full":"212 Hither Green La Lewisham Greater London SE13 6RT",
    "addr:housenumber":"212",
    "addr:postcode":"se13 6rt",
    "addr:street":"Hither",
    "iso:country":"GB",
    "sg:address":"212 Hither Green La",
    "sg:city":"Lewisham",
    "sg:classifiers":[
        {
            "category":"Shopping",
            "subcategory":"Florist",
            "type":"Retail Goods"
        }
    ],
    "sg:phone":"+44 20 8297 1274",
    "sg:postcode":"SE13 6RT",
    "sg:province":"Greater London",
    "wof:name":"Occasions",
    "wof:placetype":"venue"
},
  "geometry": {"coordinates":[-0.006242,51.451012],"type":"Point"}
}