{
  "type": "Feature",
  "properties": {
    "addr:full":"301 Whapload Road Lowestoft Suffolk NR32 1UL",
    "addr:housenumber":"301",
    "addr:postcode":"nr32 1ul",
    "addr:street":"Whapload Road",
    "iso:country":"GB",
    "sg:address":"301 Whapload Road",
    "sg:city":"Lowestoft",
    "sg:classifiers":[
        {
            "category":"Autos & Motor Vehicles",
            "subcategory":"Automobile Sales",
            "type":"Retail Goods"
        }
    ],
    "sg:phone":"+44 1502 574018",
    "sg:postcode":"NR32 1UL",
    "sg:province":"Suffolk",
    "sg:tags":[
        "car"
    ],
    "wof:name":"M & R Car Sales (Lowestoft) Ltd.",
    "wof:placetype":"venue"
},
  "geometry": {"coordinates":[1.758377,52.484028],"type":"Point"}
}