{
  "type": "Feature",
  "properties": {
    "iso:country":"GB",
    "sg:address":"66 High Street, West Wratting",
    "sg:city":"Cambridge",
    "sg:classifiers":[
        {
            "category":"Professional",
            "subcategory":"Management & Consulting",
            "type":"Services"
        },
        {
            "category":"Organizations",
            "subcategory":"Community Association",
            "type":"Services"
        }
    ],
    "sg:postcode":"CB1 5LU",
    "sg:province":"Cambridgeshire",
    "sg:tags":[
        "consultant",
        "relation",
        "public",
        "business"
    ],
    "wof:name":"Robert Barlow Communications Partnership",
    "wof:placetype":"venue"
},
  "geometry": {"coordinates":[0.252342,52.202705],"type":"Point"}
}