{
  "type": "Feature",
  "properties": {
    "iso:country":"GB",
    "sg:address":"8 Birkdale Road, Anstey",
    "sg:city":"Leicester",
    "sg:classifiers":[
        {
            "category":"Taxi",
            "type":"Transportation"
        },
        {
            "category":"Military Area",
            "subcategory":"Air Force Base",
            "type":"Public Place"
        }
    ],
    "sg:phone":"+44 116 236 3481",
    "sg:postcode":"LE7 7DF",
    "sg:province":"Leicestershire",
    "sg:tags":[
        "hire",
        "private"
    ],
    "wof:name":"P Mcgovern",
    "wof:placetype":"venue"
},
  "geometry": {"coordinates":[-1.195122,52.67564],"type":"Point"}
}