{
  "type": "Feature",
  "properties": {
    "addr:full":"1 Millbank London Greater London SW1P 3JZ",
    "addr:housenumber":"1",
    "addr:postcode":"sw1p 3jz",
    "addr:street":"Millbank",
    "iso:country":"GB",
    "sg:address":"1 Millbank",
    "sg:city":"London",
    "sg:classifiers":[
        {
            "category":"Organizations",
            "subcategory":"Non-profit Organization",
            "type":"Services"
        }
    ],
    "sg:phone":"+44 20 7898 1000",
    "sg:postcode":"SW1P 3JZ",
    "sg:province":"Greater London",
    "sg:tags":[
        "organisation",
        "voluntary",
        "charity"
    ],
    "wof:name":"The Church Urban Fund",
    "wof:placetype":"venue"
},
  "geometry": {"coordinates":[-0.1256210059,51.4962005615],"type":"Point"}
}