{
  "type": "Feature",
  "properties": {
    "addr:full":"102 The Fair Tohurgh Woodbridge Suffolk IP12 4AD",
    "addr:housenumber":"102",
    "addr:postcode":"ip12 4ad",
    "addr:street":"The",
    "iso:country":"GB",
    "sg:address":"102 The Fair Tohurgh",
    "sg:city":"Woodbridge",
    "sg:classifiers":[
        {
            "category":"Professional",
            "subcategory":"Accounting & Tax Preparation",
            "type":"Services"
        }
    ],
    "sg:phone":"+44 1394 387645",
    "sg:postcode":"IP12 4AD",
    "sg:province":"Suffolk",
    "sg:tags":[
        "accountant"
    ],
    "wof:name":"Pinfold Business Services Ltd.",
    "wof:placetype":"venue"
},
  "geometry": {"coordinates":[1.32539,52.10545],"type":"Point"}
}