{
  "type": "Feature",
  "properties": {
    "iso:country":"GB",
    "sg:address":"51 Charles Street",
    "sg:city":"Herne Bay",
    "sg:classifiers":[
        {
            "category":"Retail",
            "subcategory":"Driving School",
            "type":"Services"
        }
    ],
    "sg:phone":"+44 1227 366358",
    "sg:postcode":"CT6 5HW",
    "sg:province":"Kent",
    "wof:name":"ALEX J WILKIE",
    "wof:placetype":"venue"
},
  "geometry": {"coordinates":[1.1332989931,51.3725166321],"type":"Point"}
}