{
  "type": "Feature",
  "properties": {
    "addr:full":"287 Darnall Road Sheffield South Yorkshire S9 5AF",
    "addr:housenumber":"287",
    "addr:postcode":"s9 5af",
    "addr:street":"Darnall Road",
    "iso:country":"GB",
    "sg:address":"287 Darnall Road",
    "sg:city":"Sheffield",
    "sg:classifiers":[
        {
            "category":"Bars & Pubs",
            "type":"Food & Drink"
        }
    ],
    "sg:phone":"+44 114 244 1837",
    "sg:postcode":"S9 5AF",
    "sg:province":"South Yorkshire",
    "sg:tags":[
        "pubs",
        "inn"
    ],
    "wof:name":"Ball Inn",
    "wof:placetype":"venue"
},
  "geometry": {"coordinates":[-1.418078,53.390663],"type":"Point"}
}