{
  "type": "Feature",
  "properties": {
    "addr:full":"Unit 14 Clifton Industrial Unit, Rake Lane Manchester Greater Manchester M27 8TJ",
    "addr:housenumber":"unit 14;unit",
    "addr:postcode":"m27 8tj",
    "addr:street":"Clifton;Rake Lane",
    "iso:country":"GB",
    "sg:address":"Unit 14 Clifton Industrial Unit, Rake Lane",
    "sg:city":"Manchester",
    "sg:classifiers":[
        {
            "category":"Government",
            "subcategory":"Post Office",
            "type":"Public Place"
        }
    ],
    "sg:postcode":"M27 8TJ",
    "sg:province":"Greater Manchester",
    "sg:tags":[
        "messenger",
        "courier"
    ],
    "wof:name":"Swinton Couriers",
    "wof:placetype":"venue"
},
  "geometry": {"coordinates":[-2.32006,53.511478],"type":"Point"}
}