{
  "type": "Feature",
  "properties": {
    "iso:country":"GB",
    "sg:address":"2 Kitchenham Cotts, Ashburnham",
    "sg:city":"Battle",
    "sg:classifiers":[
        {
            "category":"Building & Trades",
            "subcategory":"Equipment Rental",
            "type":"Services"
        },
        {
            "category":"Building & Trades",
            "subcategory":"Construction",
            "type":"Services"
        }
    ],
    "sg:phone":"+44 1424 892714",
    "sg:postcode":"TN33 9NP",
    "sg:province":"East Sussex",
    "sg:tags":[
        "plant",
        "machinery"
    ],
    "wof:name":"Ash Plant Hire",
    "wof:placetype":"venue"
},
  "geometry": {"coordinates":[0.489025,50.914616],"type":"Point"}
}