{
  "type": "Feature",
  "properties": {
    "iso:country":"GB",
    "sg:address":"47-50 Tenby Street North",
    "sg:city":"Birmingham",
    "sg:classifiers":[
        {
            "category":"Building & Trades",
            "subcategory":"Electrical",
            "type":"Services"
        }
    ],
    "sg:phone":"+44 121 693 1818",
    "sg:postcode":"B1 3EG",
    "sg:province":"West Midlands",
    "sg:tags":[
        "lighting"
    ],
    "wof:name":"Arden Manufacturing",
    "wof:placetype":"venue"
},
  "geometry": {"coordinates":[-1.9137259722,52.4864082336],"type":"Point"}
}