{
  "type": "Feature",
  "properties": {
    "addr:full":"76 Brockley Rise London Greater London SE23 1LN",
    "addr:housenumber":"76",
    "addr:postcode":"se23 1ln",
    "addr:street":"Brockley Rise",
    "iso:country":"GB",
    "sg:address":"76 Brockley Rise",
    "sg:city":"London",
    "sg:classifiers":[
        {
            "category":"Retail",
            "subcategory":"Repair Shop",
            "type":"Services"
        }
    ],
    "sg:phone":"+44 20 8690 3828",
    "sg:postcode":"SE23 1LN",
    "sg:province":"Greater London",
    "sg:tags":[
        "radio",
        "television",
        "video"
    ],
    "wof:name":"A C Electronics",
    "wof:placetype":"venue"
},
  "geometry": {"coordinates":[-0.040743,51.448078],"type":"Point"}
}