{
  "type": "Feature",
  "properties": {
    "addr:full":"Swinbourne Road, Burnt Mills Industrial Estate Basildon Essex SS13 1EF",
    "addr:postcode":"ss13 1ef",
    "addr:street":"Swinbourne Road;Estate",
    "iso:country":"GB",
    "sg:address":"Swinbourne Road, Burnt Mills Industrial Estate",
    "sg:city":"Basildon",
    "sg:classifiers":[
        {
            "category":"Freight",
            "type":"Transportation"
        }
    ],
    "sg:phone":"+44 1268 502900",
    "sg:postcode":"SS13 1EF",
    "sg:province":"Essex",
    "sg:tags":[
        "forwarders"
    ],
    "wof:name":"Phoenix Freight International Ltd.",
    "wof:placetype":"venue"
},
  "geometry": {"coordinates":[0.5143399835,51.586315155],"type":"Point"}
}