{
  "type": "Feature",
  "properties": {
    "iso:country":"GB",
    "sg:address":"63 Welbeck Road",
    "sg:city":"Sheffield",
    "sg:classifiers":[
        {
            "category":"Retail",
            "subcategory":"Repair Shop",
            "type":"Services"
        }
    ],
    "sg:postcode":"S6 5AY",
    "sg:province":"South Yorkshire",
    "sg:tags":[
        "maintenance"
    ],
    "wof:name":"David A Slater",
    "wof:placetype":"venue"
},
  "geometry": {"coordinates":[-1.509362,53.396477],"type":"Point"}
}