{
  "type": "Feature",
  "properties": {
    "addr:full":"G T X House, Cedarwood Chineham Business Park Basingstoke Hampshire RG24 8WD",
    "addr:postcode":"rg24 8wd",
    "addr:street":"Cedarwood;Business Park",
    "iso:country":"GB",
    "sg:address":"G T X House, Cedarwood Chineham Business Park",
    "sg:city":"Basingstoke",
    "sg:classifiers":[
        {
            "category":"Professional",
            "subcategory":"Computer Services",
            "type":"Services"
        }
    ],
    "sg:phone":"+44 1256 843555",
    "sg:postcode":"RG24 8WD",
    "sg:province":"Hampshire",
    "sg:tags":[
        "aided",
        "design"
    ],
    "wof:name":"G T X Europe Ltd.",
    "wof:placetype":"venue"
},
  "geometry": {"coordinates":[-1.06955,51.293098],"type":"Point"}
}