{
  "type": "Feature",
  "properties": {
    "addr:full":"Whiting Bay Brodick North Ayrshire KA27 8AJ",
    "addr:postcode":"ka27 8aj",
    "iso:country":"GB",
    "sg:address":"Whiting Bay",
    "sg:city":"Brodick",
    "sg:classifiers":[
        {
            "category":"Home & Garden",
            "subcategory":"Hardware",
            "type":"Retail Goods"
        }
    ],
    "sg:phone":"+44 1770 302648",
    "sg:postcode":"KA27 8AJ",
    "sg:province":"North Ayrshire",
    "sg:tags":[
        "retailer",
        "diy"
    ],
    "wof:name":"Homestyles",
    "wof:placetype":"venue"
},
  "geometry": {"coordinates":[-5.1523189545,55.5775756836],"type":"Point"}
}