{
  "type": "Feature",
  "properties": {
    "iso:country":"GB",
    "sg:address":"Bransfield Cottage, Church Lane",
    "sg:city":"Godstone",
    "sg:classifiers":[
        {
            "category":"Social Services",
            "subcategory":"Job Training",
            "type":"Services"
        }
    ],
    "sg:phone":"+44 1883 743614",
    "sg:postcode":"RH9 8BW",
    "sg:province":"Surrey",
    "sg:tags":[
        "translator",
        "interpreter"
    ],
    "wof:name":"Portugese Services",
    "wof:placetype":"venue"
},
  "geometry": {"coordinates":[-0.0669879988,51.2500801086],"type":"Point"}
}