{
  "type": "Feature",
  "properties": {
    "addr:full":"29 Nightingale Road Hitchin Bedfordshire SG5 1QU",
    "addr:housenumber":"29",
    "addr:postcode":"sg5 1qu",
    "addr:street":"Nightingale Road",
    "iso:country":"GB",
    "sg:address":"29 Nightingale Road",
    "sg:city":"Hitchin",
    "sg:classifiers":[
        {
            "category":"Banks & Credit Unions",
            "subcategory":"Financial Services",
            "type":"Services"
        }
    ],
    "sg:phone":"+44 1462 622262",
    "sg:postcode":"SG5 1QU",
    "sg:province":"Bedfordshire",
    "sg:tags":[
        "adviser"
    ],
    "wof:name":"Advance Financial Management",
    "wof:placetype":"venue"
},
  "geometry": {"coordinates":[-0.2721950114,51.9537811279],"type":"Point"}
}