{
  "type": "Feature",
  "properties": {
    "addr:full":"906 Stockport Rd Manchester Greater Manchester M19 3AD",
    "addr:housenumber":"906",
    "addr:postcode":"m19 3ad",
    "addr:street":"Stockport Rd",
    "iso:country":"GB",
    "sg:address":"906 Stockport Rd",
    "sg:city":"Manchester",
    "sg:classifiers":[
        {
            "category":"Shopping",
            "subcategory":"Used Merchandise",
            "type":"Retail Goods"
        }
    ],
    "sg:postcode":"M19 3AD",
    "sg:province":"Greater Manchester",
    "sg:tags":[
        "furniture"
    ],
    "wof:name":"A6 Bargain Centre",
    "wof:placetype":"venue"
},
  "geometry": {"coordinates":[-2.1915891171,53.4448547363],"type":"Point"}
}