{
  "type": "Feature",
  "properties": {
    "addr:full":"One Bridewell St Bristol City of Bristol BS1 2AA",
    "addr:postcode":"bs1 2aa",
    "addr:street":"St",
    "iso:country":"GB",
    "sg:address":"One Bridewell St",
    "sg:city":"Bristol",
    "sg:classifiers":[
        {
            "category":"Professional",
            "subcategory":"Accounting & Tax Preparation",
            "type":"Services"
        }
    ],
    "sg:phone":"+44 117 929 0808",
    "sg:postcode":"BS1 2AA",
    "sg:province":"City of Bristol",
    "sg:tags":[
        "accountant"
    ],
    "wof:name":"Ernst & Young",
    "wof:placetype":"venue"
},
  "geometry": {"coordinates":[-2.5930540562,51.4575500488],"type":"Point"}
}