{
  "type": "Feature",
  "properties": {
    "addr:full":"13 Woodmarket Kelso Scottish Borders TD5 7AT",
    "addr:housenumber":"13",
    "addr:postcode":"td5 7at",
    "addr:street":"Woodmarket Kelso",
    "iso:country":"GB",
    "sg:address":"13 Woodmarket",
    "sg:city":"Kelso",
    "sg:classifiers":[
        {
            "category":"Government",
            "subcategory":"Post Office",
            "type":"Public Place"
        }
    ],
    "sg:phone":"+44 845 722 3344",
    "sg:postcode":"TD5 7AT",
    "sg:province":"Scottish Borders",
    "wof:name":"Post Office Ltd.",
    "wof:placetype":"venue"
},
  "geometry": {"coordinates":[-2.444155,55.611],"type":"Point"}
}