{
  "type": "Feature",
  "properties": {
    "addr:full":"Wortley Garage Scunthorpe Lincolnshire DN16 1ST",
    "addr:postcode":"dn16 1st",
    "iso:country":"GB",
    "sg:address":"Wortley Garage",
    "sg:city":"Scunthorpe",
    "sg:classifiers":[
        {
            "category":"Retail",
            "subcategory":"Auto Repair",
            "type":"Services"
        }
    ],
    "sg:postcode":"DN16 1ST",
    "sg:province":"Lincolnshire",
    "sg:tags":[
        "modification",
        "garage"
    ],
    "wof:name":"J & K Motors",
    "wof:placetype":"venue"
},
  "geometry": {"coordinates":[-0.6511340141,53.5838890076],"type":"Point"}
}