{
  "type": "Feature",
  "properties": {
    "iso:country":"GB",
    "sg:address":"Spring Gardens Road",
    "sg:city":"Bath",
    "sg:classifiers":[
        {
            "category":"Bars & Pubs",
            "type":"Food & Drink"
        },
        {
            "category":"Bars & Pubs",
            "subcategory":"Nightclub",
            "type":"Food & Drink"
        }
    ],
    "sg:phone":"+44 1225 447187",
    "sg:postcode":"BA2 6PW",
    "sg:province":"Somerset",
    "sg:tags":[
        "club",
        "pubs",
        "inn",
        "activity",
        "night"
    ],
    "wof:name":"T'S CLUB",
    "wof:placetype":"venue"
},
  "geometry": {"coordinates":[-2.357007,51.383068],"type":"Point"}
}