{
  "type": "Feature",
  "properties": {
    "addr:full":"17 Black Jack Street Cirencester Gloucestershire GL7 2AA",
    "addr:housenumber":"17",
    "addr:postcode":"gl7 2aa",
    "addr:street":"Black Jack Street",
    "iso:country":"GB",
    "sg:address":"17 Black Jack Street",
    "sg:city":"Cirencester",
    "sg:classifiers":[
        {
            "category":"Real Estate",
            "subcategory":"Surveying",
            "type":"Services"
        }
    ],
    "sg:phone":"+44 1285 640840",
    "sg:postcode":"GL7 2AA",
    "sg:province":"Gloucestershire",
    "sg:tags":[
        "surveyor",
        "valuer"
    ],
    "wof:name":"Central Surveying",
    "wof:placetype":"venue"
},
  "geometry": {"coordinates":[-1.969978,51.717129],"type":"Point"}
}