{
  "type": "Feature",
  "properties": {
    "addr:full":"Heath Lane, Great Boughton Chester Cheshire CH3 5ST",
    "addr:postcode":"ch3 5st",
    "addr:street":"Heath Lane",
    "iso:country":"GB",
    "sg:address":"Heath Lane, Great Boughton",
    "sg:city":"Chester",
    "sg:classifiers":[
        {
            "category":"Food & Beverages",
            "subcategory":"Groceries & Convenience Stores",
            "type":"Retail Goods"
        }
    ],
    "sg:phone":"+44 1244 326288",
    "sg:postcode":"CH3 5ST",
    "sg:province":"Cheshire",
    "wof:name":"Crescent Stores",
    "wof:placetype":"venue"
},
  "geometry": {"coordinates":[-2.862831,53.188766],"type":"Point"}
}