{
  "type": "Feature",
  "properties": {
    "iso:country":"GB",
    "sg:address":"Unit 26b The Bardfield Centre, Great Bardfield",
    "sg:city":"Braintree",
    "sg:classifiers":[
        {
            "category":"Professional",
            "subcategory":"Art Services",
            "type":"Services"
        }
    ],
    "sg:postcode":"CM7 4SL",
    "sg:province":"Essex",
    "sg:tags":[
        "graphic",
        "designer"
    ],
    "wof:name":"Andrew Griib Design",
    "wof:placetype":"venue"
},
  "geometry": {"coordinates":[0.4392699897,51.9443092346],"type":"Point"}
}