{
  "type": "Feature",
  "properties": {
    "addr:full":"2a Norbury Cres Streatham Greater London SW16 4JU",
    "addr:housenumber":"2a",
    "addr:postcode":"sw16 4ju",
    "addr:street":"Norbury Cres",
    "iso:country":"GB",
    "sg:address":"2a Norbury Cres",
    "sg:city":"Streatham",
    "sg:classifiers":[
        {
            "category":"Shopping",
            "subcategory":"Books",
            "type":"Retail Goods"
        }
    ],
    "sg:phone":"+44 20 8765 1174",
    "sg:postcode":"SW16 4JU",
    "sg:province":"Greater London",
    "sg:tags":[
        "bookseller"
    ],
    "wof:name":"SJ Books & Gifts",
    "wof:placetype":"venue"
},
  "geometry": {"coordinates":[-0.1226980016,51.4107551575],"type":"Point"}
}