{
  "type": "Feature",
  "properties": {
    "addr:full":"Station Road Corbridge Northumberland NE45 5AY",
    "addr:postcode":"ne45 5ay",
    "addr:street":"Station Road;Northumberland",
    "iso:country":"GB",
    "sg:address":"Station Road",
    "sg:city":"Corbridge",
    "sg:classifiers":[
        {
            "category":"Travel",
            "subcategory":"Hotels & Motels",
            "type":"Entertainment"
        }
    ],
    "sg:phone":"+44 1434 633633",
    "sg:postcode":"NE45 5AY",
    "sg:province":"Northumberland",
    "wof:name":"Dyvels Hotel",
    "wof:placetype":"venue"
},
  "geometry": {"coordinates":[-2.0191569328,54.9707946777],"type":"Point"}
}