{
  "type": "Feature",
  "properties": {
    "addr:full":"23 Hatfield Close New Cross Greater London SE14 5DP",
    "addr:housenumber":"23",
    "addr:postcode":"se14 5dp",
    "addr:street":"Hatfield Close",
    "iso:country":"GB",
    "sg:address":"23 Hatfield Close",
    "sg:city":"New Cross",
    "sg:classifiers":[
        {
            "category":"Building & Trades",
            "subcategory":"Construction",
            "type":"Services"
        }
    ],
    "sg:phone":"+44 20 7639 3516",
    "sg:postcode":"SE14 5DP",
    "sg:province":"Greater London",
    "sg:tags":[
        "glazier"
    ],
    "wof:name":"Kenneth R Goff",
    "wof:placetype":"venue"
},
  "geometry": {"coordinates":[-0.0494779982,51.4774436951],"type":"Point"}
}