{
  "type": "Feature",
  "properties": {
    "addr:full":"182 Franche Road Kidderminster Staffordshire DY11 5AD",
    "addr:housenumber":"182",
    "addr:postcode":"dy11 5ad",
    "addr:street":"Franche Road",
    "iso:country":"GB",
    "sg:address":"182 Franche Road",
    "sg:city":"Kidderminster",
    "sg:classifiers":[
        {
            "category":"Farming",
            "subcategory":"Nursery",
            "type":"Manufacturing & Wholesale Goods"
        },
        {
            "category":"Social Services",
            "subcategory":"Child Care",
            "type":"Services"
        }
    ],
    "sg:phone":"+44 1562 823569",
    "sg:postcode":"DY11 5AD",
    "sg:province":"Staffordshire",
    "sg:tags":[
        "creche"
    ],
    "wof:name":"Deerhurst Day Nursery",
    "wof:placetype":"venue"
},
  "geometry": {"coordinates":[-2.261886,52.392677],"type":"Point"}
}