{
  "type": "Feature",
  "properties": {
    "iso:country":"GB",
    "sg:address":"Civic Offices, Elstree Way",
    "sg:city":"Borehamwood",
    "sg:classifiers":[
        {
            "category":"Government",
            "subcategory":"Office",
            "type":"Public Place"
        }
    ],
    "sg:phone":"+44 20 8207 7492",
    "sg:postcode":"WD6 1WA",
    "sg:province":"Hertfordshire",
    "sg:tags":[
        "local"
    ],
    "wof:name":"Hertsmere Borough Council Drainage Services",
    "wof:placetype":"venue"
},
  "geometry": {"coordinates":[-0.275754,51.655819],"type":"Point"}
}