{
  "type": "Feature",
  "properties": {
    "addr:full":"18 Russell Road London Greater London NW9 6AL",
    "addr:housenumber":"18",
    "addr:postcode":"nw9 6al",
    "addr:street":"Russell Road",
    "iso:country":"GB",
    "sg:address":"18 Russell Road",
    "sg:city":"London",
    "sg:classifiers":[
        {
            "category":"Utilities",
            "type":"Services"
        }
    ],
    "sg:postcode":"NW9 6AL",
    "sg:province":"Greater London",
    "sg:tags":[
        "internet"
    ],
    "wof:name":"E-Comm International Ltd",
    "wof:placetype":"venue"
},
  "geometry": {"coordinates":[-0.2403910011,51.5796775818],"type":"Point"}
}