{
  "type": "Feature",
  "properties": {
    "addr:full":"Salterns Lane, Bursledon Southampton Hampshire SO31 8DH",
    "addr:postcode":"so31 8dh",
    "addr:street":"Salterns Lane",
    "iso:country":"GB",
    "sg:address":"Salterns Lane, Bursledon",
    "sg:city":"Southampton",
    "sg:classifiers":[
        {
            "category":"Recreation",
            "subcategory":"Marina",
            "type":"Entertainment"
        }
    ],
    "sg:phone":"+44 23 8040 3911",
    "sg:postcode":"SO31 8DH",
    "sg:province":"Hampshire",
    "sg:tags":[
        "mooring",
        "boat"
    ],
    "wof:name":"Salterns Boatyard",
    "wof:placetype":"venue"
},
  "geometry": {"coordinates":[-1.315343976,50.8897209167],"type":"Point"}
}