{
  "type": "Feature",
  "properties": {
    "addr:full":"2a Leigh Road Eastleigh Hampshire SO50 9FH",
    "addr:housenumber":"2a",
    "addr:postcode":"so50 9fh",
    "addr:street":"Leigh Road",
    "iso:country":"GB",
    "sg:address":"2a Leigh Road",
    "sg:city":"Eastleigh",
    "sg:classifiers":[
        {
            "category":"Insurance",
            "subcategory":"Insurance Agent",
            "type":"Services"
        }
    ],
    "sg:postcode":"SO50 9FH",
    "sg:province":"Hampshire",
    "wof:name":"Colonnade Insurance Brokers Ltd.",
    "wof:placetype":"venue"
},
  "geometry": {"coordinates":[-1.350759,50.969391],"type":"Point"}
}