{
  "type": "Feature",
  "properties": {
    "addr:full":"135 Farrant Av Wood Green Greater London N22 6PE",
    "addr:housenumber":"135",
    "addr:postcode":"n22 6pe",
    "addr:street":"Farrant Av;Green",
    "iso:country":"GB",
    "sg:address":"135 Farrant Av",
    "sg:city":"Wood Green",
    "sg:classifiers":[
        {
            "category":"Professional",
            "subcategory":"Art Services",
            "type":"Services"
        }
    ],
    "sg:phone":"+44 20 8889 9798",
    "sg:postcode":"N22 6PE",
    "sg:province":"Greater London",
    "sg:tags":[
        "graphic",
        "designer"
    ],
    "wof:name":"D Streeten",
    "wof:placetype":"venue"
},
  "geometry": {"coordinates":[-0.1002139971,51.5976219177],"type":"Point"}
}