{
  "type": "Feature",
  "properties": {
    "addr:full":"Block 11, Unit 104 Newhouse Industrial Estate, Newhouse Motherwell North Lanarkshire ML1 5RX",
    "addr:housenumber":"unit 104",
    "addr:postcode":"ml1 5rx",
    "addr:street":"Newhouse Industrial Estate",
    "iso:country":"GB",
    "sg:address":"Block 11, Unit 104 Newhouse Industrial Estate, Newhouse",
    "sg:city":"Motherwell",
    "sg:classifiers":[
        {
            "category":"Freight",
            "type":"Transportation"
        }
    ],
    "sg:phone":"+44 1698 734500",
    "sg:postcode":"ML1 5RX",
    "sg:province":"North Lanarkshire",
    "sg:tags":[
        "haulage",
        "road"
    ],
    "wof:name":"C N L Distribution Ltd.",
    "wof:placetype":"venue"
},
  "geometry": {"coordinates":[-3.9275710583,55.830997467],"type":"Point"}
}