{
  "type": "Feature",
  "properties": {
    "addr:full":"Cae Ffynnon, Ffordd Llanelwy Abergele Conwy LL22 8AN",
    "addr:housenumber":"ffynnon",
    "addr:postcode":"ll22 8an",
    "addr:street":"Cae;Ffordd Llanelwy",
    "iso:country":"GB",
    "sg:address":"Cae Ffynnon, Ffordd Llanelwy",
    "sg:city":"Abergele",
    "sg:classifiers":[
        {
            "category":"Farming",
            "subcategory":"Farm",
            "type":"Manufacturing & Wholesale Goods"
        }
    ],
    "sg:postcode":"LL22 8AN",
    "sg:province":"Conwy",
    "sg:tags":[
        "agricultural"
    ],
    "wof:name":"Pump & Seal Services",
    "wof:placetype":"venue"
},
  "geometry": {"coordinates":[-3.643428,53.289932],"type":"Point"}
}