{
  "type": "Feature",
  "properties": {
    "iso:country":"GB",
    "sg:address":"47 Dublin Street",
    "sg:city":"Edinburgh",
    "sg:classifiers":[
        {
            "category":"Health Services",
            "subcategory":"Dentist",
            "type":"Services"
        }
    ],
    "sg:phone":"+44 131 556 2665",
    "sg:postcode":"EH3 6NL",
    "sg:province":"City of Edinburgh",
    "wof:name":"van Schaik Frank",
    "wof:placetype":"venue"
},
  "geometry": {"coordinates":[-3.193459034,55.9573059082],"type":"Point"}
}