{
  "type": "Feature",
  "properties": {
    "addr:full":"465 Nottingham Road, Chaddesden Derby Derbyshire DE21 6NB",
    "addr:housenumber":"465",
    "addr:postcode":"de21 6nb",
    "addr:street":"Nottingham Road",
    "iso:country":"GB",
    "sg:address":"465 Nottingham Road, Chaddesden",
    "sg:city":"Derby",
    "sg:classifiers":[
        {
            "category":"Health Services",
            "subcategory":"Doctor",
            "type":"Services"
        }
    ],
    "sg:phone":"+44 1332 673332",
    "sg:postcode":"DE21 6NB",
    "sg:province":"Derbyshire",
    "sg:tags":[
        "practitioners"
    ],
    "wof:name":"Chaddesden Medical Centre",
    "wof:placetype":"venue"
},
  "geometry": {"coordinates":[-1.441527,52.925446],"type":"Point"}
}