{
  "type": "Feature",
  "properties": {
    "iso:country":"GB",
    "sg:address":"25 Ida Road",
    "sg:city":"Skegness",
    "sg:classifiers":[
        {
            "category":"Travel",
            "subcategory":"Hotels & Motels",
            "type":"Entertainment"
        },
        {
            "category":"Bars & Pubs",
            "subcategory":"Hookah Bar",
            "type":"Food & Drink"
        }
    ],
    "sg:phone":"+44 1754 766108",
    "sg:postcode":"PE25 2AR",
    "sg:province":"Lincolnshire",
    "sg:tags":[
        "self",
        "holiday",
        "catering"
    ],
    "sg:website":"http://www.lyndene-uk.com",
    "wof:name":"Lyndene Holiday Apartments",
    "wof:placetype":"venue"
},
  "geometry": {"coordinates":[0.339688,53.145203],"type":"Point"}
}