{
  "type": "Feature",
  "properties": {
    "addr:full":"Tresillian Terrace Cardiff Cardiff CF10 5RJ",
    "addr:postcode":"cf10 5rj",
    "addr:street":"Tresillian Terrace",
    "iso:country":"GB",
    "sg:address":"Tresillian Terrace",
    "sg:city":"Cardiff",
    "sg:classifiers":[
        {
            "category":"Retail",
            "subcategory":"Storage",
            "type":"Services"
        }
    ],
    "sg:phone":"+44 29 2022 0665",
    "sg:postcode":"CF10 5RJ",
    "sg:province":"Cardiff",
    "sg:tags":[
        "cold"
    ],
    "wof:name":"T D G Plc",
    "wof:placetype":"venue"
},
  "geometry": {"coordinates":[-3.1770439148,51.4741783142],"type":"Point"}
}