{
  "type": "Feature",
  "properties": {
    "addr:full":"3 Church Street, Wye Ashford Kent TN25 5BN",
    "addr:housenumber":"3",
    "addr:postcode":"tn25 5bn",
    "addr:street":"Church Street",
    "iso:country":"GB",
    "sg:address":"3 Church Street, Wye",
    "sg:city":"Ashford",
    "sg:classifiers":[
        {
            "category":"Personal",
            "subcategory":"Beauty Salon",
            "type":"Services"
        }
    ],
    "sg:phone":"+44 1233 812775",
    "sg:postcode":"TN25 5BN",
    "sg:province":"Kent",
    "sg:tags":[
        "unisex",
        "hairdresser"
    ],
    "wof:name":"Sharon's Hairstylists",
    "wof:placetype":"venue"
},
  "geometry": {"coordinates":[0.936714,51.182659],"type":"Point"}
}