{
  "type": "Feature",
  "properties": {
    "addr:full":"15 Acacia Rd Acton Greater London W3 6HD",
    "addr:housenumber":"15",
    "addr:postcode":"w3 6hd",
    "addr:street":"Acacia Rd",
    "iso:country":"GB",
    "sg:address":"15 Acacia Rd",
    "sg:city":"Acton",
    "sg:classifiers":[
        {
            "category":"Health Services",
            "subcategory":"Nursing And Care Facility",
            "type":"Services"
        }
    ],
    "sg:phone":"+44 20 8993 3465",
    "sg:postcode":"W3 6HD",
    "sg:province":"Greater London",
    "sg:tags":[
        "home"
    ],
    "wof:name":"Victoria House Residential Care Home",
    "wof:placetype":"venue"
},
  "geometry": {"coordinates":[-0.2676469982,51.5131072998],"type":"Point"}
}