{
  "type": "Feature",
  "properties": {
    "addr:full":"Penscombe Cross, Lezant Launceston Cornwall PL15 9PT",
    "addr:postcode":"pl15 9pt",
    "addr:street":"Penscombe",
    "iso:country":"GB",
    "sg:address":"Penscombe Cross, Lezant",
    "sg:city":"Launceston",
    "sg:classifiers":[
        {
            "category":"Government",
            "subcategory":"Post Office",
            "type":"Public Place"
        }
    ],
    "sg:postcode":"PL15 9PT",
    "sg:province":"Cornwall",
    "wof:name":"Trekenner Post Office",
    "wof:placetype":"venue"
},
  "geometry": {"coordinates":[-4.346544,50.587894],"type":"Point"}
}