{
  "type": "Feature",
  "properties": {
    "addr:full":"181 Castle Street, Portchester Fareham Hampshire PO16 9QX",
    "addr:housenumber":"181",
    "addr:postcode":"po16 9qx",
    "addr:street":"Castle Street",
    "iso:country":"GB",
    "sg:address":"181 Castle Street, Portchester",
    "sg:city":"Fareham",
    "sg:classifiers":[
        {
            "category":"Bars & Pubs",
            "type":"Food & Drink"
        }
    ],
    "sg:phone":"+44 23 9237 9374",
    "sg:postcode":"PO16 9QX",
    "sg:province":"Hampshire",
    "sg:tags":[
        "pubs",
        "house",
        "inn",
        "public",
        "activity"
    ],
    "wof:name":"The Cormorant",
    "wof:placetype":"venue"
},
  "geometry": {"coordinates":[-1.117965,50.839314],"type":"Point"}
}