{
  "type": "Feature",
  "properties": {
    "addr:full":"16a Cropston Rd, Anstey Leicester Leicestershire LE7 7BJ",
    "addr:housenumber":"16a",
    "addr:postcode":"le7 7bj",
    "addr:street":"Cropston Rd",
    "iso:country":"GB",
    "sg:address":"16a Cropston Rd, Anstey",
    "sg:city":"Leicester",
    "sg:classifiers":[
        {
            "category":"Personal",
            "subcategory":"Beauty Salon",
            "type":"Services"
        }
    ],
    "sg:postcode":"LE7 7BJ",
    "sg:province":"Leicestershire",
    "sg:tags":[
        "unisex",
        "hairdresser"
    ],
    "wof:name":"Total Toning Studio",
    "wof:placetype":"venue"
},
  "geometry": {"coordinates":[-1.186003,52.673126],"type":"Point"}
}