{
  "type": "Feature",
  "properties": {
    "addr:full":"3 Island Rd, Upstreet Canterbury Kent CT3 4BZ",
    "addr:housenumber":"3",
    "addr:postcode":"ct3 4bz",
    "addr:street":"Island Rd",
    "iso:country":"GB",
    "sg:address":"3 Island Rd, Upstreet",
    "sg:city":"Canterbury",
    "sg:classifiers":[
        {
            "category":"Taxi",
            "type":"Transportation"
        },
        {
            "category":"Military Area",
            "subcategory":"Air Force Base",
            "type":"Public Place"
        }
    ],
    "sg:postcode":"CT3 4BZ",
    "sg:province":"Kent",
    "sg:tags":[
        "mini",
        "hire",
        "private",
        "cab"
    ],
    "wof:name":"Boyle,Michael,",
    "wof:placetype":"venue"
},
  "geometry": {"coordinates":[1.170003,51.316792],"type":"Point"}
}