{
  "type": "Feature",
  "properties": {
    "addr:full":"25 The Lanes Shopping Centre, Birmingham Road Sutton Coldfield West Midlands B72 1YG",
    "addr:housenumber":"25",
    "addr:postcode":"b72 1yg",
    "addr:street":"The Lanes Shopping Centre Birmingham Road",
    "iso:country":"GB",
    "sg:address":"25 The Lanes Shopping Centre, Birmingham Road",
    "sg:city":"Sutton Coldfield",
    "sg:classifiers":[
        {
            "category":"Personal",
            "subcategory":"Beauty Salon",
            "type":"Services"
        },
        {
            "category":"Personal",
            "subcategory":"Barber",
            "type":"Services"
        }
    ],
    "sg:phone":"+44 121 386 2262",
    "sg:postcode":"B72 1YG",
    "sg:province":"West Midlands",
    "sg:tags":[
        "unisex",
        "hairdresser"
    ],
    "wof:name":"Legend Hair & Beauty",
    "wof:placetype":"venue"
},
  "geometry": {"coordinates":[-1.82757,52.537251],"type":"Point"}
}