{
  "type": "Feature",
  "properties": {
    "addr:full":"63 Lakeside Rainham Essex RM13 9SN",
    "addr:housenumber":"63",
    "addr:postcode":"rm13 9sn",
    "addr:street":"Lakeside Rainham",
    "iso:country":"GB",
    "sg:address":"63 Lakeside",
    "sg:city":"Rainham",
    "sg:classifiers":[
        {
            "category":"Personal",
            "type":"Services"
        }
    ],
    "sg:phone":"+44 1708 559382",
    "sg:postcode":"RM13 9SN",
    "sg:province":"Essex",
    "sg:tags":[
        "wedding"
    ],
    "wof:name":"Jaz Luxury Cars",
    "wof:placetype":"venue"
},
  "geometry": {"coordinates":[0.2193499953,51.5256729126],"type":"Point"}
}