{
  "type": "Feature",
  "properties": {
    "iso:country":"GB",
    "sg:address":"76 Nevill Avenue",
    "sg:city":"Hove",
    "sg:classifiers":[
        {
            "category":"Banks & Credit Unions",
            "subcategory":"Investment Brokerage",
            "type":"Services"
        }
    ],
    "sg:postcode":"BN3 7NA",
    "sg:province":"East Sussex",
    "wof:name":"Aggarwal Investment Services",
    "wof:placetype":"venue"
},
  "geometry": {"coordinates":[-0.1834030002,50.8422088623],"type":"Point"}
}