{
  "type": "Feature",
  "properties": {
    "addr:full":"Penlan Y Mor Llanarth Ceredigion SA47 0QE",
    "addr:postcode":"sa47 0qe",
    "iso:country":"GB",
    "sg:address":"Penlan Y Mor",
    "sg:city":"Llanarth",
    "sg:classifiers":[
        {
            "category":"Farming",
            "subcategory":"Farm",
            "type":"Manufacturing & Wholesale Goods"
        },
        {
            "category":"Recreation",
            "subcategory":"Campground",
            "type":"Entertainment"
        }
    ],
    "sg:phone":"+44 1545 580936",
    "sg:postcode":"SA47 0QE",
    "sg:province":"Ceredigion",
    "sg:tags":[
        "mixed",
        "caravan",
        "park",
        "crop"
    ],
    "wof:name":"I W & M J Jones",
    "wof:placetype":"venue"
},
  "geometry": {"coordinates":[-4.307499,52.194118],"type":"Point"}
}