{
  "type": "Feature",
  "properties": {
    "iso:country":"GB",
    "sg:address":"16 Vicar Street",
    "sg:city":"Falkirk",
    "sg:classifiers":[
        {
            "category":"Travel",
            "subcategory":"Travel Agent",
            "type":"Entertainment"
        }
    ],
    "sg:phone":"+44 1324 624999",
    "sg:postcode":"FK1 1LL",
    "sg:province":"Falkirk",
    "wof:name":"King World Travel",
    "wof:placetype":"venue"
},
  "geometry": {"coordinates":[-3.7847030163,56.0005340576],"type":"Point"}
}