{
  "type": "Feature",
  "properties": {
    "iso:country":"GB",
    "sg:address":"Shawbury Road, Astley",
    "sg:city":"Shrewsbury",
    "sg:classifiers":[
        {
            "category":"Sports & Exercise",
            "subcategory":"Tennis Court",
            "type":"Entertainment"
        }
    ],
    "sg:phone":"+44 1939 210400",
    "sg:postcode":"SY4 4BU",
    "sg:province":"Shropshire",
    "sg:tags":[
        "breakdown",
        "recovery"
    ],
    "wof:name":"Astley Recovery Services",
    "wof:placetype":"venue"
},
  "geometry": {"coordinates":[-2.6998069286,52.7657737732],"type":"Point"}
}