{
  "type": "Feature",
  "properties": {
    "addr:full":"Howard Bldg(s), 69-71 Burpham Lane Guildford Surrey GU4 7NB",
    "addr:housenumber":"69-71",
    "addr:postcode":"gu4 7nb",
    "addr:street":"Burpham Lane",
    "iso:country":"GB",
    "sg:address":"Howard Bldg(s), 69-71 Burpham Lane",
    "sg:city":"Guildford",
    "sg:classifiers":[
        {
            "category":"Building & Trades",
            "subcategory":"Cleaning & Sanitation",
            "type":"Services"
        },
        {
            "category":"Building & Trades",
            "subcategory":"Construction",
            "type":"Services"
        }
    ],
    "sg:phone":"+44 1483 450251",
    "sg:postcode":"GU4 7NB",
    "sg:province":"Surrey",
    "sg:tags":[
        "dry",
        "control",
        "damp",
        "contractor",
        "ventilation",
        "rot"
    ],
    "wof:name":"McCoy-Hill & Partners Ltd.",
    "wof:placetype":"venue"
},
  "geometry": {"coordinates":[-0.5454589725,51.2584838867],"type":"Point"}
}