{
  "type": "Feature",
  "properties": {
    "iso:country":"GB",
    "sg:address":"49 Palace Gardens",
    "sg:city":"Enfield",
    "sg:classifiers":[
        {
            "category":"Travel",
            "subcategory":"Travel Agent",
            "type":"Entertainment"
        }
    ],
    "sg:phone":"+44 20 8367 1122",
    "sg:postcode":"EN2 6SN",
    "sg:province":"Greater London",
    "wof:name":"Going Places Leisure Travel",
    "wof:placetype":"venue"
},
  "geometry": {"coordinates":[-0.087649,51.653107],"type":"Point"}
}