{
  "type": "Feature",
  "properties": {
    "addr:full":"Doctors Surgery, Old Road North, Kempsey Worcester Worcestershire WR5 3JZ",
    "addr:postcode":"wr5 3jz",
    "addr:street":"Old Road North",
    "iso:country":"GB",
    "sg:address":"Doctors Surgery, Old Road North, Kempsey",
    "sg:city":"Worcester",
    "sg:classifiers":[
        {
            "category":"Health Services",
            "subcategory":"Doctor",
            "type":"Services"
        }
    ],
    "sg:phone":"+44 1905 820466",
    "sg:postcode":"WR5 3JZ",
    "sg:province":"Worcestershire",
    "sg:tags":[
        "practitioners"
    ],
    "wof:name":"A Georgiou",
    "wof:placetype":"venue"
},
  "geometry": {"coordinates":[-2.217885,52.140137],"type":"Point"}
}