{
  "type": "Feature",
  "properties": {
    "addr:full":"15 Harriet Tubman Clo Brixton Greater London SW2 2UQ",
    "addr:housenumber":"15",
    "addr:postcode":"sw2 2uq",
    "addr:street":"Harriet Tubman",
    "iso:country":"GB",
    "sg:address":"15 Harriet Tubman Clo",
    "sg:city":"Brixton",
    "sg:classifiers":[
        {
            "category":"Building & Trades",
            "subcategory":"Construction",
            "type":"Services"
        }
    ],
    "sg:phone":"+44 20 8671 7545",
    "sg:postcode":"SW2 2UQ",
    "sg:province":"Greater London",
    "sg:tags":[
        "tiling",
        "contractor"
    ],
    "wof:name":"Miller G & A",
    "wof:placetype":"venue"
},
  "geometry": {"coordinates":[-0.115722999,51.4466743469],"type":"Point"}
}