{
  "type": "Feature",
  "properties": {
    "addr:full":"23 The Pantiles Tunbridge Wells East Sussex TN2 5TD",
    "addr:housenumber":"23",
    "addr:postcode":"tn2 5td",
    "addr:street":"The Pantiles",
    "iso:country":"GB",
    "sg:address":"23 The Pantiles",
    "sg:city":"Tunbridge Wells",
    "sg:classifiers":[
        {
            "category":"Arts & Performance",
            "subcategory":"Art Gallery",
            "type":"Entertainment"
        }
    ],
    "sg:phone":"+44 1892 525525",
    "sg:postcode":"TN2 5TD",
    "sg:province":"East Sussex",
    "wof:name":"The Fairfax Gallery",
    "wof:placetype":"venue"
},
  "geometry": {"coordinates":[0.2577790022,51.1257705688],"type":"Point"}
}