{
  "type": "Feature",
  "properties": {
    "addr:full":"Chimneys, High Street, Campsall Doncaster North Yorkshire DN6 9AG",
    "addr:postcode":"dn6 9ag",
    "addr:street":"High Street",
    "iso:country":"GB",
    "sg:address":"Chimneys, High Street, Campsall",
    "sg:city":"Doncaster",
    "sg:classifiers":[
        {
            "category":"Personal",
            "type":"Services"
        }
    ],
    "sg:phone":"+44 1302 701458",
    "sg:postcode":"DN6 9AG",
    "sg:province":"North Yorkshire",
    "sg:tags":[
        "consultant",
        "fitness"
    ],
    "wof:name":"Frans Aerobics",
    "wof:placetype":"venue"
},
  "geometry": {"coordinates":[-1.173317,53.62265],"type":"Point"}
}