{
  "type": "Feature",
  "properties": {
    "iso:country":"GB",
    "sg:address":"The Mardy, Llandenny",
    "sg:city":"Usk",
    "sg:classifiers":[
        {
            "category":"Retail",
            "subcategory":"Car Wash",
            "type":"Services"
        }
    ],
    "sg:postcode":"NP15 1DN",
    "sg:province":"Monmouthshire",
    "sg:tags":[
        "polishing",
        "washing"
    ],
    "wof:name":"M B Carwash",
    "wof:placetype":"venue"
},
  "geometry": {"coordinates":[-2.85231,51.730732],"type":"Point"}
}