{
  "type": "Feature",
  "properties": {
    "iso:country":"GB",
    "sg:address":"Wood Barton Farm, Monkokehampton",
    "sg:city":"Winkleigh",
    "sg:classifiers":[
        {
            "category":"Farming",
            "subcategory":"Livestock Farm",
            "type":"Manufacturing & Wholesale Goods"
        },
        {
            "category":"Farming",
            "subcategory":"Farm",
            "type":"Manufacturing & Wholesale Goods"
        }
    ],
    "sg:postcode":"EX19 8RZ",
    "sg:province":"Devon",
    "sg:tags":[
        "mixed",
        "crop",
        "others"
    ],
    "wof:name":"G A & P C Martin",
    "wof:placetype":"venue"
},
  "geometry": {"coordinates":[-3.9423849583,50.8555793762],"type":"Point"}
}