{
  "type": "Feature",
  "properties": {
    "addr:full":"72 Regent Street London Greater London W1B 5RJ",
    "addr:housenumber":"72",
    "addr:postcode":"w1b 5rj",
    "addr:street":"Regent Street",
    "iso:country":"GB",
    "sg:address":"72 Regent Street",
    "sg:city":"London",
    "sg:classifiers":[
        {
            "category":"Food & Beverages",
            "subcategory":"Liquor & Beverages",
            "type":"Retail Goods"
        }
    ],
    "sg:phone":"+44 20 7494 3322",
    "sg:postcode":"W1B 5RJ",
    "sg:province":"Greater London",
    "sg:tags":[
        "beer",
        "spirit",
        "wines"
    ],
    "wof:name":"Cheers",
    "wof:placetype":"venue"
},
  "geometry": {"coordinates":[-0.1362189949,51.5098609924],"type":"Point"}
}