{
  "type": "Feature",
  "properties": {
    "addr:full":"24 The Broadway Amersham Buckinghamshire HP7 0HP",
    "addr:housenumber":"24",
    "addr:postcode":"hp7 0hp",
    "addr:street":"The Broadway",
    "iso:country":"GB",
    "sg:address":"24 The Broadway",
    "sg:city":"Amersham",
    "sg:classifiers":[
        {
            "category":"Health Services",
            "subcategory":"Chiropractor",
            "type":"Services"
        }
    ],
    "sg:postcode":"HP7 0HP",
    "sg:province":"Buckinghamshire",
    "wof:name":"Amersham Chiropractic Clinic",
    "wof:placetype":"venue"
},
  "geometry": {"coordinates":[-0.613270998,51.6656990051],"type":"Point"}
}