{
  "type": "Feature",
  "properties": {
    "addr:full":"3 Church Street Troon South Ayrshire KA10 6AU",
    "addr:housenumber":"3",
    "addr:postcode":"ka10 6au",
    "addr:street":"Church Street",
    "iso:country":"GB",
    "sg:address":"3 Church Street",
    "sg:city":"Troon",
    "sg:classifiers":[
        {
            "category":"Cafe",
            "type":"Food & Drink"
        },
        {
            "category":"Food & Beverages",
            "subcategory":"Bakery",
            "type":"Retail Goods"
        }
    ],
    "sg:phone":"+44 1292 317093",
    "sg:postcode":"KA10 6AU",
    "sg:province":"South Ayrshire",
    "sg:tags":[
        "baker",
        "snack",
        "bar"
    ],
    "wof:name":"The Strawberry Cushion",
    "wof:placetype":"venue"
},
  "geometry": {"coordinates":[-4.661678,55.544571],"type":"Point"}
}