{
  "type": "Feature",
  "properties": {
    "addr:full":"79 Wesley Way Tamworth Staffordshire B77 3JE",
    "addr:housenumber":"79",
    "addr:postcode":"b77 3je",
    "addr:street":"Wesley Way",
    "iso:country":"GB",
    "sg:address":"79 Wesley Way",
    "sg:city":"Tamworth",
    "sg:classifiers":[
        {
            "category":"Building & Trades",
            "subcategory":"Plumbing",
            "type":"Services"
        },
        {
            "category":"Utilities",
            "subcategory":"Natural Gas",
            "type":"Services"
        }
    ],
    "sg:postcode":"B77 3JE",
    "sg:province":"Staffordshire",
    "sg:tags":[
        "control",
        "energy",
        "management",
        "heating",
        "system"
    ],
    "wof:name":"Hendon Heating",
    "wof:placetype":"venue"
},
  "geometry": {"coordinates":[-1.6669909954,52.6333122253],"type":"Point"}
}