{
  "type": "Feature",
  "properties": {
    "iso:country":"GB",
    "sg:address":"Bridgwater Ct, Oldmixon Cres",
    "sg:city":"Weston Super Mare",
    "sg:classifiers":[
        {
            "category":"Shopping",
            "subcategory":"Stationery & Office Supplies",
            "type":"Retail Goods"
        }
    ],
    "sg:phone":"+44 1934 625003",
    "sg:postcode":"BS24 9AY",
    "sg:province":"Somerset",
    "sg:tags":[
        "equipment"
    ],
    "wof:name":"Genesis Business Systems",
    "wof:placetype":"venue"
},
  "geometry": {"coordinates":[-2.957914114,51.3271064758],"type":"Point"}
}