{
  "type": "Feature",
  "properties": {
    "addr:full":"Telephone Av Bristol City of Bristol BS1 4BH",
    "addr:postcode":"bs1 4bh",
    "addr:street":"Telephone Av Bristol",
    "iso:country":"GB",
    "sg:address":"Telephone Av",
    "sg:city":"Bristol",
    "sg:classifiers":[
        {
            "category":"Professional",
            "subcategory":"Detective & Security Services",
            "type":"Services"
        }
    ],
    "sg:phone":"+44 117 930 4802",
    "sg:postcode":"BS1 4BH",
    "sg:province":"City of Bristol",
    "wof:name":"C I P Security Services",
    "wof:placetype":"venue"
},
  "geometry": {"coordinates":[-2.595849,51.452873],"type":"Point"}
}