{
  "type": "Feature",
  "properties": {
    "addr:full":"55 Woodside Road, Silsden Keighley North Yorkshire BD20 0BN",
    "addr:housenumber":"55",
    "addr:postcode":"bd20 0bn",
    "addr:street":"Woodside Road",
    "iso:country":"GB",
    "sg:address":"55 Woodside Road, Silsden",
    "sg:city":"Keighley",
    "sg:classifiers":[
        {
            "category":"Place Of Worship",
            "type":"Public Place"
        },
        {
            "category":"Organizations",
            "subcategory":"Non-profit Organization",
            "type":"Services"
        }
    ],
    "sg:phone":"+44 1535 652353",
    "sg:postcode":"BD20 0BN",
    "sg:province":"North Yorkshire",
    "sg:tags":[
        "charitable",
        "organisation",
        "charity"
    ],
    "wof:name":"Sildsen Methodist Church",
    "wof:placetype":"venue"
},
  "geometry": {"coordinates":[-1.950529,53.911888],"type":"Point"}
}