{
  "type": "Feature",
  "properties": {
    "addr:full":"65 Causeway Street Paisley Renfrewshire PA1 1YP",
    "addr:housenumber":"65",
    "addr:postcode":"pa1 1yp",
    "addr:street":"Causeway Street",
    "iso:country":"GB",
    "sg:address":"65 Causeway Street",
    "sg:city":"Paisley",
    "sg:classifiers":[
        {
            "category":"Wholesale",
            "subcategory":"Medical Equipment & Supplies",
            "type":"Manufacturing & Wholesale Goods"
        }
    ],
    "sg:phone":"+44 141 849 0770",
    "sg:postcode":"PA1 1YP",
    "sg:province":"Renfrewshire",
    "sg:tags":[
        "aid",
        "hearing"
    ],
    "wof:name":"Better Hearing",
    "wof:placetype":"venue"
},
  "geometry": {"coordinates":[-4.42449,55.841019],"type":"Point"}
}