{
  "type": "Feature",
  "properties": {
    "iso:country":"GB",
    "sg:address":"Flower Court, 1 Flower Lane, Amesbury",
    "sg:city":"Salisbury",
    "sg:classifiers":[
        {
            "category":"Travel",
            "subcategory":"Travel Agent",
            "type":"Entertainment"
        }
    ],
    "sg:phone":"+44 1980 624422",
    "sg:postcode":"SP4 7JE",
    "sg:province":"Hampshire",
    "wof:name":"Bath Travel",
    "wof:placetype":"venue"
},
  "geometry": {"coordinates":[-1.781512,51.170753],"type":"Point"}
}