{
  "type": "Feature",
  "properties": {
    "addr:full":"8 The Strand Deal Kent CT14 7DY",
    "addr:housenumber":"8",
    "addr:postcode":"ct14 7dy",
    "addr:street":"The Strand Deal",
    "iso:country":"GB",
    "sg:address":"8 The Strand",
    "sg:city":"Deal",
    "sg:classifiers":[
        {
            "category":"Cinema",
            "subcategory":"Movie Rental",
            "type":"Entertainment"
        }
    ],
    "sg:phone":"+44 1304 366564",
    "sg:postcode":"CT14 7DY",
    "sg:province":"Kent",
    "sg:tags":[
        "video",
        "library"
    ],
    "wof:name":"Screens Video",
    "wof:placetype":"venue"
},
  "geometry": {"coordinates":[1.402351,51.213345],"type":"Point"}
}