{
  "type": "Feature",
  "properties": {
    "addr:full":"143 Carlyon Road Wembley Greater London HA0 1HU",
    "addr:housenumber":"143",
    "addr:postcode":"ha0 1hu",
    "addr:street":"Carlyon Road",
    "iso:country":"GB",
    "sg:address":"143 Carlyon Road",
    "sg:city":"Wembley",
    "sg:classifiers":[
        {
            "category":"Building & Trades",
            "subcategory":"Cleaning & Sanitation",
            "type":"Services"
        }
    ],
    "sg:phone":"+44 20 8998 5010",
    "sg:postcode":"HA0 1HU",
    "sg:province":"Greater London",
    "sg:tags":[
        "contracting",
        "commercial"
    ],
    "wof:name":"EXCLUSIVE CLEANING SERVICES",
    "wof:placetype":"venue"
},
  "geometry": {"coordinates":[-0.2897030115,51.5396690369],"type":"Point"}
}