{
  "type": "Feature",
  "properties": {
    "addr:full":"6 Quay Hill Lymington Hampshire SO41 3AR",
    "addr:housenumber":"6",
    "addr:postcode":"so41 3ar",
    "addr:street":"Quay Hill",
    "iso:country":"GB",
    "sg:address":"6 Quay Hill",
    "sg:city":"Lymington",
    "sg:classifiers":[
        {
            "category":"Personal",
            "subcategory":"Hair Removal",
            "type":"Services"
        }
    ],
    "sg:phone":"+44 1590 677889",
    "sg:postcode":"SO41 3AR",
    "sg:province":"Hampshire",
    "sg:tags":[
        "electrolysis"
    ],
    "wof:name":"Quay Beauty At Aromatica",
    "wof:placetype":"venue"
},
  "geometry": {"coordinates":[-1.5362110138,50.7584190369],"type":"Point"}
}