{
  "type": "Feature",
  "properties": {
    "addr:full":"62 Longridge Avenue Stalybridge Greater Manchester SK15 1HL",
    "addr:housenumber":"62",
    "addr:postcode":"sk15 1hl",
    "addr:street":"Longridge Avenue",
    "iso:country":"GB",
    "sg:address":"62 Longridge Avenue",
    "sg:city":"Stalybridge",
    "sg:classifiers":[
        {
            "category":"Professional",
            "subcategory":"Computer Services",
            "type":"Services"
        }
    ],
    "sg:phone":"+44 7785 371780",
    "sg:postcode":"SK15 1HL",
    "sg:province":"Greater Manchester",
    "sg:tags":[
        "system",
        "software"
    ],
    "wof:name":"Pretex 2000 Ltd.",
    "wof:placetype":"venue"
},
  "geometry": {"coordinates":[-2.054608,53.494747],"type":"Point"}
}