{
  "type": "Feature",
  "properties": {
    "addr:full":"11-13 Chesham Road Amersham Buckinghamshire HP6 5HN",
    "addr:housenumber":"11-13",
    "addr:postcode":"hp6 5hn",
    "addr:street":"Chesham Road",
    "iso:country":"GB",
    "sg:address":"11-13 Chesham Road",
    "sg:city":"Amersham",
    "sg:classifiers":[
        {
            "category":"Personal",
            "subcategory":"Barber",
            "type":"Services"
        }
    ],
    "sg:phone":"+44 1494 432131",
    "sg:postcode":"HP6 5HN",
    "sg:province":"Buckinghamshire",
    "sg:tags":[
        "men's",
        "hairdresser"
    ],
    "wof:name":"Janice Bowlding",
    "wof:placetype":"venue"
},
  "geometry": {"coordinates":[-0.607518971,51.6769294739],"type":"Point"}
}