{
  "type": "Feature",
  "properties": {
    "iso:country":"GB",
    "sg:address":"Vale Road Industrial Estate",
    "sg:city":"Spilsby",
    "sg:classifiers":[
        {
            "category":"Utilities",
            "subcategory":"Mobile Phone",
            "type":"Services"
        }
    ],
    "sg:phone":"+44 1790 753999",
    "sg:postcode":"PE23 5HE",
    "sg:province":"Lincolnshire",
    "sg:tags":[
        "mnfr",
        "good",
        "electrical"
    ],
    "wof:name":"Mill House (2004) Ltd.",
    "wof:placetype":"venue"
},
  "geometry": {"coordinates":[0.094628,53.17107],"type":"Point"}
}