{
  "type": "Feature",
  "properties": {
    "addr:full":"Easey Ho, 385 Edgware Rd London Greater London NW2 6LQ",
    "addr:housenumber":"385",
    "addr:postcode":"nw2 6lq",
    "addr:street":"Edgware Rd",
    "iso:country":"GB",
    "sg:address":"Easey Ho, 385 Edgware Rd",
    "sg:city":"London",
    "sg:classifiers":[
        {
            "category":"Manufacturing",
            "subcategory":"Apparel",
            "type":"Manufacturing & Wholesale Goods"
        }
    ],
    "sg:postcode":"NW2 6LQ",
    "sg:province":"Greater London",
    "sg:tags":[
        "garment",
        "designer"
    ],
    "wof:name":"F C Team Concept Ltd",
    "wof:placetype":"venue"
},
  "geometry": {"coordinates":[-0.225879997,51.5661010742],"type":"Point"}
}