{
  "type": "Feature",
  "properties": {
    "addr:full":"Orchard Croft, Heath Road, Bromstead Newport Shropshire TF10 9DJ",
    "addr:postcode":"tf10 9dj",
    "addr:street":"Orchard Croft Heath Road",
    "iso:country":"GB",
    "sg:address":"Orchard Croft, Heath Road, Bromstead",
    "sg:city":"Newport",
    "sg:classifiers":[
        {
            "category":"Building & Trades",
            "subcategory":"Construction",
            "type":"Services"
        }
    ],
    "sg:phone":"+44 1952 691550",
    "sg:postcode":"TF10 9DJ",
    "sg:province":"Shropshire",
    "sg:tags":[
        "builder"
    ],
    "wof:name":"& Fletcher Yoman Builders",
    "wof:placetype":"venue"
},
  "geometry": {"coordinates":[-2.378768,52.757885],"type":"Point"}
}