{
  "type": "Feature",
  "properties": {
    "addr:full":"25 High Street Bradford West Yorkshire BD13 3ES",
    "addr:housenumber":"25",
    "addr:postcode":"bd13 3es",
    "addr:street":"High Street",
    "iso:country":"GB",
    "sg:address":"25 High Street",
    "sg:city":"Bradford",
    "sg:classifiers":[
        {
            "category":"Deli",
            "type":"Food & Drink"
        }
    ],
    "sg:phone":"+44 1274 884066",
    "sg:postcode":"BD13 3ES",
    "sg:province":"West Yorkshire",
    "sg:tags":[
        "delicatessen"
    ],
    "wof:name":"Jolley Good Food",
    "wof:placetype":"venue"
},
  "geometry": {"coordinates":[-1.8505630493,53.7917251587],"type":"Point"}
}