{
  "type": "Feature",
  "properties": {
    "iso:country":"GB",
    "sg:address":"2 Beech Walk, Alkrington, Middleton",
    "sg:city":"Manchester",
    "sg:classifiers":[
        {
            "category":"Professional",
            "subcategory":"Engineering",
            "type":"Services"
        }
    ],
    "sg:phone":"+44 161 643 4609",
    "sg:postcode":"M24 1JX",
    "sg:province":"Greater Manchester",
    "sg:tags":[
        "contractor",
        "electrical",
        "engineer"
    ],
    "wof:name":"Derrick Croft",
    "wof:placetype":"venue"
},
  "geometry": {"coordinates":[-2.198393,53.539837],"type":"Point"}
}