{
  "type": "Feature",
  "properties": {
    "addr:full":"The Pond Thornton Heath Surrey CR7 6JA",
    "addr:postcode":"cr7 6ja",
    "iso:country":"GB",
    "sg:address":"The Pond",
    "sg:city":"Thornton Heath",
    "sg:classifiers":[
        {
            "category":"Autos & Motor Vehicles",
            "subcategory":"Automobile Sales",
            "type":"Retail Goods"
        },
        {
            "category":"Retail",
            "subcategory":"Auto Rental",
            "type":"Services"
        }
    ],
    "sg:phone":"+44 20 8684 1284",
    "sg:postcode":"CR7 6JA",
    "sg:province":"Surrey",
    "sg:tags":[
        "commercial",
        "hire",
        "van",
        "truck"
    ],
    "wof:name":"Whitehouse Farleigh Ltd.",
    "wof:placetype":"venue"
},
  "geometry": {"coordinates":[-0.111749,51.394291],"type":"Point"}
}