{
  "type": "Feature",
  "properties": {
    "iso:country":"GB",
    "sg:address":"9 The Jays, Ridgewood",
    "sg:city":"Uckfield",
    "sg:classifiers":[
        {
            "category":"Shopping",
            "subcategory":"Gifts & Souvenirs",
            "type":"Retail Goods"
        }
    ],
    "sg:postcode":"TN22 5YG",
    "sg:province":"East Sussex",
    "sg:tags":[
        "shop"
    ],
    "wof:name":"The Language of Flowers Ltd",
    "wof:placetype":"venue"
},
  "geometry": {"coordinates":[0.105744,50.960529],"type":"Point"}
}