{
  "type": "Feature",
  "properties": {
    "addr:full":"Wood End Road Wolverhampton Staffordshire WV11 1YD",
    "addr:postcode":"wv11 1yd",
    "addr:street":"Wood End Road",
    "iso:country":"GB",
    "sg:address":"Wood End Road",
    "sg:city":"Wolverhampton",
    "sg:classifiers":[
        {
            "category":"Bars & Pubs",
            "type":"Food & Drink"
        }
    ],
    "sg:phone":"+44 1902 732188",
    "sg:postcode":"WV11 1YD",
    "sg:province":"Staffordshire",
    "sg:tags":[
        "pubs",
        "inn"
    ],
    "wof:name":"Punch Retail (Holdings) Ltd.",
    "wof:placetype":"venue"
},
  "geometry": {"coordinates":[-2.086744,52.615314],"type":"Point"}
}