{
  "type": "Feature",
  "properties": {
    "iso:country":"GB",
    "sg:address":"60 Fore Street",
    "sg:city":"St Ives",
    "sg:classifiers":[
        {
            "category":"Food & Beverages",
            "subcategory":"Meat & Fish",
            "type":"Retail Goods"
        }
    ],
    "sg:postcode":"TR26 1HW",
    "sg:province":"Cornwall",
    "sg:tags":[
        "butcher"
    ],
    "wof:name":"J B Curnow & Sons",
    "wof:placetype":"venue"
},
  "geometry": {"coordinates":[-5.480298,50.214752],"type":"Point"}
}