{
  "type": "Feature",
  "properties": {
    "addr:full":"Unit 5a Hemel Hempstead Hertfordshire HP1 1DX",
    "addr:housenumber":"unit 5a",
    "addr:postcode":"hp1 1dx",
    "iso:country":"GB",
    "sg:address":"Unit 5a",
    "sg:city":"Hemel Hempstead",
    "sg:classifiers":[
        {
            "category":"Shopping",
            "subcategory":"News",
            "type":"Retail Goods"
        }
    ],
    "sg:phone":"+44 1442 233627",
    "sg:postcode":"HP1 1DX",
    "sg:province":"Hertfordshire",
    "sg:tags":[
        "newsagent"
    ],
    "wof:name":"Pops News",
    "wof:placetype":"venue"
},
  "geometry": {"coordinates":[-0.4862389863,51.7516593933],"type":"Point"}
}