{
  "type": "Feature",
  "properties": {
    "addr:full":"8 Goods Station Road Tunbridge Wells Kent TN1 2RJ",
    "addr:housenumber":"8",
    "addr:postcode":"tn1 2rj",
    "addr:street":"Station Road",
    "iso:country":"GB",
    "sg:address":"8 Goods Station Road",
    "sg:city":"Tunbridge Wells",
    "sg:classifiers":[
        {
            "category":"Bars & Pubs",
            "type":"Food & Drink"
        }
    ],
    "sg:postcode":"TN1 2RJ",
    "sg:province":"Kent",
    "sg:tags":[
        "pubs",
        "inn"
    ],
    "wof:name":"The Victoria Tavern",
    "wof:placetype":"venue"
},
  "geometry": {"coordinates":[0.2638359964,51.1351928711],"type":"Point"}
}