{
  "type": "Feature",
  "properties": {
    "iso:country":"GB",
    "sg:address":"8 Whitby Drive",
    "sg:city":"Washington",
    "sg:classifiers":[
        {
            "category":"Health Services",
            "subcategory":"Nursing And Care Facility",
            "type":"Services"
        },
        {
            "category":"Organizations",
            "subcategory":"Non-profit Organization",
            "type":"Services"
        }
    ],
    "sg:phone":"+44 191 417 2448",
    "sg:postcode":"NE38 7NW",
    "sg:province":"Durham",
    "sg:tags":[
        "residential",
        "organisation",
        "voluntary",
        "charity"
    ],
    "wof:name":"Community Integrated Care Ltd",
    "wof:placetype":"venue"
},
  "geometry": {"coordinates":[-1.519967,54.891434],"type":"Point"}
}