{
  "type": "Feature",
  "properties": {
    "addr:full":"2 Beresford Road Whitstable Kent CT5 1JP",
    "addr:housenumber":"2",
    "addr:postcode":"ct5 1jp",
    "addr:street":"Beresford Road",
    "iso:country":"GB",
    "sg:address":"2 Beresford Road",
    "sg:city":"Whitstable",
    "sg:classifiers":[
        {
            "category":"Building & Trades",
            "subcategory":"Equipment Rental",
            "type":"Services"
        },
        {
            "category":"Building & Trades",
            "subcategory":"Construction",
            "type":"Services"
        }
    ],
    "sg:phone":"+44 1227 771059",
    "sg:postcode":"CT5 1JP",
    "sg:province":"Kent",
    "sg:tags":[
        "plant",
        "hire",
        "tool",
        "machinery"
    ],
    "wof:name":"Whitstable Plant Hire",
    "wof:placetype":"venue"
},
  "geometry": {"coordinates":[1.028962,51.357452],"type":"Point"}
}