{
  "type": "Feature",
  "properties": {
    "iso:country":"GB",
    "sg:address":"Brandon House, Pepper Rd, Hunslet",
    "sg:city":"Leeds",
    "sg:classifiers":[
        {
            "category":"Social Services",
            "type":"Services"
        }
    ],
    "sg:phone":"+44 113 232 9559",
    "sg:postcode":"LS10 2RU",
    "sg:province":"West Yorkshire",
    "sg:tags":[
        "disability"
    ],
    "wof:name":"Alpha-Tec Van Conversions",
    "wof:placetype":"venue"
},
  "geometry": {"coordinates":[-1.522189,53.77169],"type":"Point"}
}