{
  "type": "Feature",
  "properties": {
    "iso:country":"GB",
    "sg:address":"Ridgemount, Honor End Lane, Prestwood",
    "sg:city":"Great Missenden",
    "sg:classifiers":[
        {
            "category":"Organizations",
            "subcategory":"Community Association",
            "type":"Services"
        }
    ],
    "sg:phone":"+44 1494 868343",
    "sg:postcode":"HP16 9HG",
    "sg:province":"Buckinghamshire",
    "sg:tags":[
        "relation",
        "public"
    ],
    "wof:name":"Beechwood Public Relations",
    "wof:placetype":"venue"
},
  "geometry": {"coordinates":[-0.709043,51.704067],"type":"Point"}
}