{
  "type": "Feature",
  "properties": {
    "iso:country":"GB",
    "sg:address":"Eskin Farm, Wythop",
    "sg:city":"Cockermouth",
    "sg:classifiers":[
        {
            "category":"Building & Trades",
            "subcategory":"Landscaping Services",
            "type":"Services"
        }
    ],
    "sg:phone":"+44 17687 76453",
    "sg:postcode":"CA13 9YR",
    "sg:province":"Cumbria",
    "sg:tags":[
        "design",
        "garden"
    ],
    "wof:name":"Garden Care",
    "wof:placetype":"venue"
},
  "geometry": {"coordinates":[-3.365952,54.663647],"type":"Point"}
}