{
  "type": "Feature",
  "properties": {
    "iso:country":"GB",
    "sg:address":"178 Boothtown Road",
    "sg:city":"Halifax",
    "sg:classifiers":[
        {
            "category":"Personal",
            "subcategory":"Beauty Salon",
            "type":"Services"
        }
    ],
    "sg:phone":"+44 1422 361733",
    "sg:postcode":"HX3 6TU",
    "sg:province":"West Yorkshire",
    "sg:tags":[
        "unisex",
        "hairdresser"
    ],
    "wof:name":"Cutting Corners",
    "wof:placetype":"venue"
},
  "geometry": {"coordinates":[-1.867259,53.737888],"type":"Point"}
}