{
  "type": "Feature",
  "properties": {
    "addr:full":"Unit E 259 Coggeshall Road Braintree Essex CM7 9EF",
    "addr:housenumber":"259",
    "addr:postcode":"cm7 9ef",
    "addr:street":"Coggeshall Road",
    "iso:country":"GB",
    "sg:address":"Unit E 259 Coggeshall Road",
    "sg:city":"Braintree",
    "sg:classifiers":[
        {
            "category":"Shopping",
            "subcategory":"Computers & Home Electronics",
            "type":"Retail Goods"
        }
    ],
    "sg:phone":"+44 1376 344486",
    "sg:postcode":"CM7 9EF",
    "sg:province":"Essex",
    "sg:tags":[
        "consumables"
    ],
    "wof:name":"Inkwell Technology Ltd.",
    "wof:placetype":"venue"
},
  "geometry": {"coordinates":[0.5532420278,51.8777580261],"type":"Point"}
}