{
  "type": "Feature",
  "properties": {
    "iso:country":"GB",
    "sg:address":"713 High Road Leyton, Leyton",
    "sg:city":"London",
    "sg:classifiers":[
        {
            "category":"Professional",
            "subcategory":"Printing & Photocopies",
            "type":"Services"
        }
    ],
    "sg:phone":"+44 20 8558 4721",
    "sg:postcode":"E10 5AB",
    "sg:province":"Greater London",
    "sg:tags":[
        "process",
        "screen",
        "printer"
    ],
    "wof:name":"Griffin Design & Print Services Ltd.",
    "wof:placetype":"venue"
},
  "geometry": {"coordinates":[-0.0086019998,51.572303772],"type":"Point"}
}