{
  "type": "Feature",
  "properties": {
    "addr:full":"65a-67 High Street, Sharnbrook Bedford Bedfordshire MK44 1PB",
    "addr:housenumber":"65a-67",
    "addr:postcode":"mk44 1pb",
    "addr:street":"High Street",
    "iso:country":"GB",
    "sg:address":"65a-67 High Street, Sharnbrook",
    "sg:city":"Bedford",
    "sg:classifiers":[
        {
            "category":"Home & Garden",
            "subcategory":"Home Furnishings",
            "type":"Retail Goods"
        }
    ],
    "sg:postcode":"MK44 1PB",
    "sg:province":"Bedfordshire",
    "sg:tags":[
        "blind",
        "curtain",
        "fitting"
    ],
    "wof:name":"Designer Drapes",
    "wof:placetype":"venue"
},
  "geometry": {"coordinates":[-0.4768919945,52.2531890869],"type":"Point"}
}