{
  "type": "Feature",
  "properties": {
    "addr:full":"Po Box 18 Hitchin Bedfordshire SG5 1DH",
    "addr:housenumber":"po box 18",
    "addr:postcode":"sg5 1dh",
    "iso:country":"GB",
    "sg:address":"Po Box 18",
    "sg:city":"Hitchin",
    "sg:classifiers":[
        {
            "category":"Professional",
            "subcategory":"Testing Lab",
            "type":"Services"
        }
    ],
    "sg:postcode":"SG5 1DH",
    "sg:province":"Bedfordshire",
    "sg:tags":[
        "laboratory"
    ],
    "wof:name":"Birchover Instruments Ltd.",
    "wof:placetype":"venue"
},
  "geometry": {"coordinates":[-0.284408,51.952435],"type":"Point"}
}