{
  "type": "Feature",
  "properties": {
    "iso:country":"GB",
    "sg:address":"The Old Barn, Copt Oak Ct",
    "sg:city":"Leicester",
    "sg:classifiers":[
        {
            "category":"Farming",
            "subcategory":"Nursery",
            "type":"Manufacturing & Wholesale Goods"
        }
    ],
    "sg:phone":"+44 116 286 1992",
    "sg:postcode":"LE9 5WY",
    "sg:province":"Leicestershire",
    "sg:tags":[
        "creche"
    ],
    "wof:name":"Rocking Horse Nursery School The",
    "wof:placetype":"venue"
},
  "geometry": {"coordinates":[-1.2739100456,52.585521698],"type":"Point"}
}