{
  "type": "Feature",
  "properties": {
    "addr:full":"P O Box 124, Trafalgar House Altrincham Cheshire WA14 1FB",
    "addr:housenumber":"124",
    "addr:postcode":"wa14 1fb",
    "addr:street":"P O Box;Altrincham Cheshire",
    "iso:country":"GB",
    "sg:address":"P O Box 124, Trafalgar House",
    "sg:city":"Altrincham",
    "sg:classifiers":[
        {
            "category":"Professional",
            "subcategory":"Employment Agencies",
            "type":"Services"
        }
    ],
    "sg:phone":"+44 161 941 6868",
    "sg:postcode":"WA14 1FB",
    "sg:province":"Cheshire",
    "sg:tags":[
        "consultant"
    ],
    "wof:name":"Rullion Engineering Personnel Ltd.",
    "wof:placetype":"venue"
},
  "geometry": {"coordinates":[-2.3492090702,53.3867263794],"type":"Point"}
}