{
  "type": "Feature",
  "properties": {
    "addr:full":"38a Lyndhurst Road Worthing West Sussex BN11 2DF",
    "addr:housenumber":"38a",
    "addr:postcode":"bn11 2df",
    "addr:street":"Lyndhurst Road",
    "iso:country":"GB",
    "sg:address":"38a Lyndhurst Road",
    "sg:city":"Worthing",
    "sg:classifiers":[
        {
            "category":"Professional",
            "subcategory":"Business Services",
            "type":"Services"
        }
    ],
    "sg:phone":"+44 1903 200735",
    "sg:postcode":"BN11 2DF",
    "sg:province":"West Sussex",
    "sg:tags":[
        "shop",
        "cleaning"
    ],
    "wof:name":"Modern Maintenance Services",
    "wof:placetype":"venue"
},
  "geometry": {"coordinates":[-0.3589349985,50.8160705566],"type":"Point"}
}