{
  "type": "Feature",
  "properties": {
    "addr:full":"46 Park Street Weymouth Dorset DT4 7DF",
    "addr:housenumber":"46",
    "addr:postcode":"dt4 7df",
    "addr:street":"Park Street",
    "iso:country":"GB",
    "sg:address":"46 Park Street",
    "sg:city":"Weymouth",
    "sg:classifiers":[
        {
            "category":"Professional",
            "subcategory":"Printing & Photocopies",
            "type":"Services"
        }
    ],
    "sg:phone":"+44 1305 772181",
    "sg:postcode":"DT4 7DF",
    "sg:province":"Dorset",
    "sg:tags":[
        "engraving",
        "printer"
    ],
    "wof:name":"Precision Engraving Signs & Trophies",
    "wof:placetype":"venue"
},
  "geometry": {"coordinates":[-2.454857,50.61335],"type":"Point"}
}