{
  "type": "Feature",
  "properties": {
    "addr:full":"4 Conqueror Road St Leonards-on-sea East Sussex TN38 8DD",
    "addr:housenumber":"4",
    "addr:postcode":"leonards-on-sea;tn38 8dd",
    "addr:street":"Conqueror Road St",
    "iso:country":"GB",
    "sg:address":"4 Conqueror Road",
    "sg:city":"St Leonards-on-sea",
    "sg:classifiers":[
        {
            "category":"Building & Trades",
            "subcategory":"Construction",
            "type":"Services"
        }
    ],
    "sg:phone":"+44 1424 446483",
    "sg:postcode":"TN38 8DD",
    "sg:province":"East Sussex",
    "sg:tags":[
        "builder"
    ],
    "wof:name":"Surebuild",
    "wof:placetype":"venue"
},
  "geometry": {"coordinates":[0.5278769732,50.8534584045],"type":"Point"}
}