{
  "type": "Feature",
  "properties": {
    "iso:country":"GB",
    "sg:address":"236 Whitley Road",
    "sg:city":"Whitley Bay",
    "sg:classifiers":[
        {
            "category":"Restaurant",
            "type":"Food & Drink"
        }
    ],
    "sg:phone":"+44 191 251 1567",
    "sg:postcode":"NE26 2TE",
    "sg:province":"Northumberland",
    "wof:name":"Ritzzy Steak House",
    "wof:placetype":"venue"
},
  "geometry": {"coordinates":[-1.4453259706,55.0423355103],"type":"Point"}
}