{
  "type": "Feature",
  "properties": {
    "iso:country":"GB",
    "sg:address":"2 Clarence Pl",
    "sg:city":"Bath",
    "sg:classifiers":[
        {
            "category":"Place Of Worship",
            "type":"Public Place"
        }
    ],
    "sg:phone":"+44 1225 421868",
    "sg:postcode":"BA1 3EW",
    "sg:province":"Bath and North East Somerset",
    "wof:name":"United Reformed Church",
    "wof:placetype":"venue"
},
  "geometry": {"coordinates":[-2.389937,51.382908],"type":"Point"}
}