{
  "type": "Feature",
  "properties": {
    "iso:country":"GB",
    "sg:address":"282 Allerton Road",
    "sg:city":"Bradford",
    "sg:classifiers":[
        {
            "category":"Communications",
            "type":"Services"
        }
    ],
    "sg:phone":"+44 1274 542044",
    "sg:postcode":"BD15 7QE",
    "sg:province":"West Yorkshire",
    "sg:tags":[
        "tv",
        "video",
        "radio"
    ],
    "wof:name":"Telefix",
    "wof:placetype":"venue"
},
  "geometry": {"coordinates":[-1.8203630447,53.8044624329],"type":"Point"}
}