{
  "type": "Feature",
  "properties": {
    "addr:full":"35 Southampton Row London Greater London WC1B 5HJ",
    "addr:housenumber":"35",
    "addr:postcode":"wc1b 5hj",
    "addr:street":"Southampton Row",
    "iso:country":"GB",
    "sg:address":"35 Southampton Row",
    "sg:city":"London",
    "sg:classifiers":[
        {
            "category":"Shopping",
            "subcategory":"Clothing, Apparel, & Fashions",
            "type":"Retail Goods"
        }
    ],
    "sg:phone":"+44 20 7405 7330",
    "sg:postcode":"WC1B 5HJ",
    "sg:province":"Greater London",
    "sg:tags":[
        "menswear"
    ],
    "wof:name":"Leonard Jay Ltd.",
    "wof:placetype":"venue"
},
  "geometry": {"coordinates":[-0.121242,51.518806],"type":"Point"}
}