{
  "type": "Feature",
  "properties": {
    "iso:country":"GB",
    "sg:address":"55 Greek St",
    "sg:city":"London",
    "sg:classifiers":[
        {
            "category":"Shopping",
            "subcategory":"Music",
            "type":"Retail Goods"
        }
    ],
    "sg:phone":"+44 20 7734 0795",
    "sg:postcode":"W1D 3DX",
    "sg:province":"Greater London",
    "sg:tags":[
        "record",
        "tape",
        "cd"
    ],
    "wof:name":"Trax Records Ltd",
    "wof:placetype":"venue"
},
  "geometry": {"coordinates":[-0.1312830001,51.514339447],"type":"Point"}
}