{
  "type": "Feature",
  "properties": {
    "addr:full":"Hurst Farm, Hurst La, Stoke Pk Market Drayton Shropshire TF9 2LD",
    "addr:housenumber":"hurst farm",
    "addr:postcode":"tf9 2ld",
    "addr:street":"Hurst La Stoke Pk Market",
    "iso:country":"GB",
    "sg:address":"Hurst Farm, Hurst La, Stoke Pk",
    "sg:city":"Market Drayton",
    "sg:classifiers":[
        {
            "category":"Food & Beverages",
            "subcategory":"Liquor & Beverages",
            "type":"Retail Goods"
        }
    ],
    "sg:postcode":"TF9 2LD",
    "sg:province":"Shropshire",
    "sg:tags":[
        "beer",
        "spirit",
        "wines"
    ],
    "wof:name":"Jarcel",
    "wof:placetype":"venue"
},
  "geometry": {"coordinates":[-2.486172,52.904091],"type":"Point"}
}