{
  "type": "Feature",
  "properties": {
    "iso:country":"GB",
    "sg:address":"13 Everard Road, Rhos On Sea",
    "sg:city":"Colwyn Bay",
    "sg:classifiers":[
        {
            "category":"Professional",
            "subcategory":"Lawyer & Legal Services",
            "type":"Services"
        }
    ],
    "sg:phone":"+44 1492 547156",
    "sg:postcode":"LL28 4EY",
    "sg:province":"Conwy",
    "sg:tags":[
        "solicitor"
    ],
    "wof:name":"Gamlins",
    "wof:placetype":"venue"
},
  "geometry": {"coordinates":[-3.740095,53.308052],"type":"Point"}
}