{
  "type": "Feature",
  "properties": {
    "iso:country":"GB",
    "sg:address":"Greenland Road, Farnworth",
    "sg:city":"Bolton",
    "sg:classifiers":[
        {
            "category":"Education",
            "subcategory":"School",
            "type":"Public Place"
        }
    ],
    "sg:phone":"+44 1204 391800",
    "sg:postcode":"BL4 0HU",
    "sg:province":"Lancashire",
    "sg:tags":[
        "local",
        "authority"
    ],
    "wof:name":"Mount St Joseph Business & Enterprise College",
    "wof:placetype":"venue"
},
  "geometry": {"coordinates":[-2.42227,53.55518],"type":"Point"}
}