{
  "type": "Feature",
  "properties": {
    "addr:full":"24 Melbourne Street Stalybridge Greater Manchester SK15 2JE",
    "addr:housenumber":"24",
    "addr:postcode":"sk15 2je",
    "addr:street":"Melbourne Street",
    "iso:country":"GB",
    "sg:address":"24 Melbourne Street",
    "sg:city":"Stalybridge",
    "sg:classifiers":[
        {
            "category":"Bars & Pubs",
            "type":"Food & Drink"
        }
    ],
    "sg:phone":"+44 161 338 6423",
    "sg:postcode":"SK15 2JE",
    "sg:province":"Greater Manchester",
    "sg:tags":[
        "pubs",
        "inn"
    ],
    "wof:name":"The Friendship Inn",
    "wof:placetype":"venue"
},
  "geometry": {"coordinates":[-2.057352,53.482857],"type":"Point"}
}