{
  "type": "Feature",
  "properties": {
    "addr:full":"The Gnome Reserve, West Putford Holsworthy Cornwall EX22 7XE",
    "addr:postcode":"ex22 7xe",
    "addr:street":"West",
    "iso:country":"GB",
    "sg:address":"The Gnome Reserve, West Putford",
    "sg:city":"Holsworthy",
    "sg:classifiers":[
        {
            "category":"Shopping",
            "subcategory":"Pets & Pet Supplies",
            "type":"Retail Goods"
        },
        {
            "category":"Landmark",
            "subcategory":"Tourist Attraction",
            "type":"Public Place"
        }
    ],
    "sg:phone":"+44 1409 241435",
    "sg:postcode":"EX22 7XE",
    "sg:province":"Cornwall",
    "sg:tags":[
        "activity",
        "interest",
        "zoo"
    ],
    "wof:name":"The Gnome Reserve & Wildflower Garden",
    "wof:placetype":"venue"
},
  "geometry": {"coordinates":[-4.3350148201,50.9181480408],"type":"Point"}
}