{
  "type": "Feature",
  "properties": {
    "addr:full":"St. Katharines Parmoor, Frieth Henley On Thames Berkshire RG9 6NN",
    "addr:postcode":"rg9 6nn",
    "addr:street":"Frieth",
    "iso:country":"GB",
    "sg:address":"St. Katharines Parmoor, Frieth",
    "sg:city":"Henley On Thames",
    "sg:classifiers":[
        {
            "category":"Professional",
            "subcategory":"Management & Consulting",
            "type":"Services"
        }
    ],
    "sg:phone":"+44 1494 882628",
    "sg:postcode":"RG9 6NN",
    "sg:province":"Berkshire",
    "sg:tags":[
        "marketing",
        "consultant"
    ],
    "wof:name":"Analytica Consultants",
    "wof:placetype":"venue"
},
  "geometry": {"coordinates":[-0.8517680168,51.6052703857],"type":"Point"}
}