{
  "type": "Feature",
  "properties": {
    "iso:country":"GB",
    "sg:address":"Rose Cottage, Brockley Grn, Hundon",
    "sg:city":"Sudbury",
    "sg:classifiers":[
        {
            "category":"Professional",
            "subcategory":"Art Services",
            "type":"Services"
        }
    ],
    "sg:postcode":"CO10 8DT",
    "sg:province":"Essex",
    "sg:tags":[
        "model",
        "maker"
    ],
    "wof:name":"Colin Graves",
    "wof:placetype":"venue"
},
  "geometry": {"coordinates":[0.536605,52.109226],"type":"Point"}
}