{
  "type": "Feature",
  "properties": {
    "addr:full":"15 Holmhead Kilbirnie North Ayrshire KA25 6BW",
    "addr:housenumber":"15",
    "addr:postcode":"ka25 6bw",
    "addr:street":"Holmhead",
    "iso:country":"GB",
    "sg:address":"15 Holmhead",
    "sg:city":"Kilbirnie",
    "sg:classifiers":[
        {
            "category":"Shopping",
            "subcategory":"News",
            "type":"Retail Goods"
        }
    ],
    "sg:phone":"+44 1505 682278",
    "sg:postcode":"KA25 6BW",
    "sg:province":"North Ayrshire",
    "sg:tags":[
        "newsagent"
    ],
    "wof:name":"T Richardson",
    "wof:placetype":"venue"
},
  "geometry": {"coordinates":[-4.6854701042,55.7497177124],"type":"Point"}
}