{
  "type": "Feature",
  "properties": {
    "addr:full":"13 Victoria Street, Billinghay Lincoln Lincolnshire LN4 4HQ",
    "addr:housenumber":"13",
    "addr:postcode":"ln4 4hq",
    "addr:street":"Victoria Street",
    "iso:country":"GB",
    "sg:address":"13 Victoria Street, Billinghay",
    "sg:city":"Lincoln",
    "sg:classifiers":[
        {
            "category":"Home & Garden",
            "subcategory":"Furniture",
            "type":"Retail Goods"
        }
    ],
    "sg:phone":"+44 1526 860447",
    "sg:postcode":"LN4 4HQ",
    "sg:province":"Lincolnshire",
    "wof:name":"J H Millhouse",
    "wof:placetype":"venue"
},
  "geometry": {"coordinates":[-0.2766799927,53.0792922974],"type":"Point"}
}