{
  "type": "Feature",
  "properties": {
    "addr:full":"Cuckoopen Barn Farm, Shab Hill, Birdlip Gloucester Gloucestershire GL4 8JX",
    "addr:postcode":"gl4 8jx",
    "addr:street":"Shab Hill Birdlip",
    "iso:country":"GB",
    "sg:address":"Cuckoopen Barn Farm, Shab Hill, Birdlip",
    "sg:city":"Gloucester",
    "sg:classifiers":[
        {
            "category":"Building & Trades",
            "subcategory":"Construction",
            "type":"Services"
        }
    ],
    "sg:phone":"+44 1452 862351",
    "sg:postcode":"GL4 8JX",
    "sg:province":"Gloucestershire",
    "sg:tags":[
        "roofing"
    ],
    "wof:name":"Lansdown Roofing Co. Ltd.",
    "wof:placetype":"venue"
},
  "geometry": {"coordinates":[-2.1097540855,51.8279495239],"type":"Point"}
}