{
  "type": "Feature",
  "properties": {
    "addr:full":"14 Riverview, Henderson Drive Dartford Kent DA1 5LB",
    "addr:housenumber":"14",
    "addr:postcode":"da1 5lb",
    "addr:street":"Riverview Henderson Drive",
    "iso:country":"GB",
    "sg:address":"14 Riverview, Henderson Drive",
    "sg:city":"Dartford",
    "sg:classifiers":[
        {
            "category":"Personal",
            "subcategory":"Beauty Salon",
            "type":"Services"
        }
    ],
    "sg:phone":"+44 1322 225622",
    "sg:postcode":"DA1 5LB",
    "sg:province":"Kent",
    "wof:name":"Skin Deep",
    "wof:placetype":"venue"
},
  "geometry": {"coordinates":[0.23575,51.453762],"type":"Point"}
}