{
  "type": "Feature",
  "properties": {
    "addr:full":"15 New Road Spalding Lincolnshire PE11 1DQ",
    "addr:housenumber":"15",
    "addr:postcode":"pe11 1dq",
    "addr:street":"New Road",
    "iso:country":"GB",
    "sg:address":"15 New Road",
    "sg:city":"Spalding",
    "sg:classifiers":[
        {
            "category":"Shopping",
            "subcategory":"Shoes",
            "type":"Retail Goods"
        }
    ],
    "sg:postcode":"PE11 1DQ",
    "sg:province":"Lincolnshire",
    "sg:tags":[
        "shop",
        "retailer",
        "footwear"
    ],
    "wof:name":"JULIA'S",
    "wof:placetype":"venue"
},
  "geometry": {"coordinates":[-0.1514990032,52.7884902954],"type":"Point"}
}