{
  "type": "Feature",
  "properties": {
    "addr:full":"298 Heathway Dagenham Essex RM10 8LU",
    "addr:housenumber":"298",
    "addr:postcode":"rm10 8lu",
    "addr:street":"Heathway",
    "iso:country":"GB",
    "sg:address":"298 Heathway",
    "sg:city":"Dagenham",
    "sg:classifiers":[
        {
            "category":"Real Estate",
            "subcategory":"Real Estate Agent",
            "type":"Services"
        }
    ],
    "sg:phone":"+44 20 8491 1891",
    "sg:postcode":"RM10 8LU",
    "sg:province":"Essex",
    "wof:name":"Dagenham Property Services",
    "wof:placetype":"venue"
},
  "geometry": {"coordinates":[0.1481080055,51.5433425903],"type":"Point"}
}