{
  "type": "Feature",
  "properties": {
    "addr:full":"41 Gracious Street Peterborough Cambridgeshire PE7 1AR",
    "addr:housenumber":"41",
    "addr:postcode":"pe7 1ar",
    "addr:street":"Gracious Street",
    "iso:country":"GB",
    "sg:address":"41 Gracious Street",
    "sg:city":"Peterborough",
    "sg:classifiers":[
        {
            "category":"Retail",
            "subcategory":"Auto Repair",
            "type":"Services"
        }
    ],
    "sg:phone":"+44 1733 202561",
    "sg:postcode":"PE7 1AR",
    "sg:province":"Cambridgeshire",
    "sg:tags":[
        "modification",
        "garage"
    ],
    "wof:name":"Blow & Lawrence",
    "wof:placetype":"venue"
},
  "geometry": {"coordinates":[-0.1297100037,52.5589599609],"type":"Point"}
}