{
  "type": "Feature",
  "properties": {
    "iso:country":"GB",
    "sg:address":"The White Ho, Clifton Marine Pde",
    "sg:city":"Gravesend",
    "sg:classifiers":[
        {
            "category":"Professional",
            "subcategory":"Detective & Security Services",
            "type":"Services"
        }
    ],
    "sg:phone":"+44 1474 355050",
    "sg:postcode":"DA11 0DY",
    "sg:province":"Kent",
    "sg:tags":[
        "equipment"
    ],
    "wof:name":"Qtek Products Ltd",
    "wof:placetype":"venue"
},
  "geometry": {"coordinates":[0.361739,51.445271],"type":"Point"}
}