{
  "type": "Feature",
  "properties": {
    "iso:country":"GB",
    "sg:address":"Barrington Road",
    "sg:city":"Bexleyheath",
    "sg:classifiers":[
        {
            "category":"Education",
            "subcategory":"School",
            "type":"Public Place"
        }
    ],
    "sg:phone":"+44 20 8304 0242",
    "sg:postcode":"DA7 4UN",
    "sg:province":"Kent",
    "sg:tags":[
        "local",
        "authority"
    ],
    "wof:name":"Barrington Primary School",
    "wof:placetype":"venue"
},
  "geometry": {"coordinates":[0.126382,51.464371],"type":"Point"}
}