{
  "type": "Feature",
  "properties": {
    "iso:country":"GB",
    "sg:address":"14 The Tything",
    "sg:city":"Worcester",
    "sg:classifiers":[
        {
            "category":"Real Estate",
            "subcategory":"Real Estate Agent",
            "type":"Services"
        }
    ],
    "sg:phone":"+44 1905 611477",
    "sg:postcode":"WR1 1HD",
    "sg:province":"Worcestershire",
    "wof:name":"Williamdale Property Group Ltd",
    "wof:placetype":"venue"
},
  "geometry": {"coordinates":[-2.2237091064,52.1979789734],"type":"Point"}
}