{
  "type": "Feature",
  "properties": {
    "iso:country":"GB",
    "sg:address":", St. Dogmaels",
    "sg:city":"Cardigan",
    "sg:classifiers":[
        {
            "category":"Bars & Pubs",
            "type":"Food & Drink"
        }
    ],
    "sg:phone":"+44 1239 612680",
    "sg:postcode":"SA43 3ET",
    "sg:province":"Ceredigion",
    "sg:tags":[
        "pubs",
        "inn"
    ],
    "wof:name":"Teifi Netpool Inn",
    "wof:placetype":"venue"
},
  "geometry": {"coordinates":[-4.678309,52.081451],"type":"Point"}
}