{
  "type": "Feature",
  "properties": {
    "iso:country":"GB",
    "sg:address":"Ladyfield Ho, Demmings Indust Est",
    "sg:city":"Cheadle",
    "sg:classifiers":[
        {
            "category":"Wholesale",
            "subcategory":"Sporting Goods",
            "type":"Manufacturing & Wholesale Goods"
        }
    ],
    "sg:postcode":"SK8 2PQ",
    "sg:province":"Cheshire",
    "sg:tags":[
        "linen"
    ],
    "wof:name":"Nordisk Tekstil",
    "wof:placetype":"venue"
},
  "geometry": {"coordinates":[-2.212272,53.395248],"type":"Point"}
}