{
  "type": "Feature",
  "properties": {
    "addr:full":"15 Halford Rd Stratford Upon Avon Warwickshire CV37 9BD",
    "addr:housenumber":"15",
    "addr:postcode":"cv37 9bd",
    "addr:street":"Halford Rd",
    "iso:country":"GB",
    "sg:address":"15 Halford Rd",
    "sg:city":"Stratford Upon Avon",
    "sg:classifiers":[
        {
            "category":"Place Of Worship",
            "type":"Public Place"
        }
    ],
    "sg:phone":"+44 1789 550277",
    "sg:postcode":"CV37 9BD",
    "sg:province":"Warwickshire",
    "wof:name":"The Bridge",
    "wof:placetype":"venue"
},
  "geometry": {"coordinates":[-1.722596,52.185379],"type":"Point"}
}