{
  "type": "Feature",
  "properties": {
    "iso:country":"GB",
    "sg:address":"17 Furness Close",
    "sg:city":"Worcester",
    "sg:classifiers":[
        {
            "category":"Social Services",
            "subcategory":"Adult Care",
            "type":"Services"
        },
        {
            "category":"Government",
            "subcategory":"Office",
            "type":"Public Place"
        }
    ],
    "sg:phone":"+44 1905 613567",
    "sg:postcode":"WR4 9DX",
    "sg:province":"Worcestershire",
    "sg:tags":[
        "housing",
        "local",
        "sheltered"
    ],
    "wof:name":"Furness Close Sheltered Housing",
    "wof:placetype":"venue"
},
  "geometry": {"coordinates":[-2.193794,52.205307],"type":"Point"}
}