{
  "type": "Feature",
  "properties": {
    "iso:country":"GB",
    "sg:address":"8 Boughton Rd",
    "sg:city":"London",
    "sg:classifiers":[
        {
            "category":"Food & Beverages",
            "subcategory":"Supermarket",
            "type":"Retail Goods"
        }
    ],
    "sg:postcode":"SE28 0AG",
    "sg:province":"Greater London",
    "sg:tags":[
        "frozen"
    ],
    "wof:name":"Weems Foods Ltd",
    "wof:placetype":"venue"
},
  "geometry": {"coordinates":[0.093351,51.493782],"type":"Point"}
}