{
  "type": "Feature",
  "properties": {
    "iso:country":"GB",
    "sg:address":"257 Bath Road",
    "sg:city":"Hounslow",
    "sg:classifiers":[
        {
            "category":"Fast Food",
            "type":"Food & Drink"
        }
    ],
    "sg:phone":"+44 20 8570 3170",
    "sg:postcode":"TW3 3DA",
    "sg:province":"Greater London",
    "sg:tags":[
        "away",
        "meal",
        "outlet",
        "take"
    ],
    "wof:name":"Delight Takeaway",
    "wof:placetype":"venue"
},
  "geometry": {"coordinates":[-0.380124,51.470974],"type":"Point"}
}