{
  "type": "Feature",
  "properties": {
    "iso:country":"GB",
    "sg:address":"Hales Street",
    "sg:city":"Coventry",
    "sg:classifiers":[
        {
            "category":"Museum",
            "subcategory":"Art Museum",
            "type":"Entertainment"
        },
        {
            "category":"Government",
            "subcategory":"Office",
            "type":"Public Place"
        }
    ],
    "sg:phone":"+44 24 7683 2425",
    "sg:postcode":"CV1 1PN",
    "sg:province":"West Midlands",
    "sg:tags":[
        "local",
        "gallery"
    ],
    "wof:name":"Museum of British Road Transport",
    "wof:placetype":"venue"
},
  "geometry": {"coordinates":[-1.509174,52.410351],"type":"Point"}
}