{
  "type": "Feature",
  "properties": {
    "iso:country":"GB",
    "sg:address":"Werrington Village Surgery, Ash Bank Rd",
    "sg:city":"Stoke On Trent",
    "sg:classifiers":[
        {
            "category":"Health Services",
            "subcategory":"Doctor",
            "type":"Services"
        }
    ],
    "sg:phone":"+44 1782 304611",
    "sg:postcode":"ST9 0JS",
    "sg:province":"Staffordshire",
    "sg:tags":[
        "practitioners"
    ],
    "wof:name":"Lewis, S E",
    "wof:placetype":"venue"
},
  "geometry": {"coordinates":[-2.09756,53.02145],"type":"Point"}
}