{
  "type": "Feature",
  "properties": {
    "addr:full":"14 Lady Lane Paisley Renfrewshire PA1 2LJ",
    "addr:housenumber":"14",
    "addr:postcode":"pa1 2lj",
    "addr:street":"Lady Lane",
    "iso:country":"GB",
    "sg:address":"14 Lady Lane",
    "sg:city":"Paisley",
    "sg:classifiers":[
        {
            "category":"Arena",
            "subcategory":"Sports Club",
            "type":"Entertainment"
        }
    ],
    "sg:phone":"+44 141 889 0469",
    "sg:postcode":"PA1 2LJ",
    "sg:province":"Renfrewshire",
    "wof:name":"Victoria Bowling Club",
    "wof:placetype":"venue"
},
  "geometry": {"coordinates":[-4.43273,55.843578],"type":"Point"}
}