{
  "type": "Feature",
  "properties": {
    "addr:full":"27a St Andrew Street Aberdeen Aberdeen City AB25 1JA",
    "addr:housenumber":"27a",
    "addr:postcode":"ab25 1ja",
    "addr:street":"St Andrew Street",
    "iso:country":"GB",
    "sg:address":"27a St Andrew Street",
    "sg:city":"Aberdeen",
    "sg:classifiers":[
        {
            "category":"Communications",
            "subcategory":"Film & Video Production",
            "type":"Services"
        },
        {
            "category":"Shopping",
            "subcategory":"Party Supplies",
            "type":"Retail Goods"
        }
    ],
    "sg:phone":"+44 1224 644477",
    "sg:postcode":"AB25 1JA",
    "sg:province":"Aberdeen City",
    "sg:tags":[
        "product",
        "novelty"
    ],
    "wof:name":"Aberdeen Joke Factory",
    "wof:placetype":"venue"
},
  "geometry": {"coordinates":[-2.1027870178,57.1500816345],"type":"Point"}
}