{
  "type": "Feature",
  "properties": {
    "iso:country":"GB",
    "sg:address":"5 The Highway, Hawarden",
    "sg:city":"Deeside",
    "sg:classifiers":[
        {
            "category":"Farming",
            "subcategory":"Livestock Farm",
            "type":"Manufacturing & Wholesale Goods"
        }
    ],
    "sg:phone":"+44 1244 520238",
    "sg:postcode":"CH5 3DG",
    "sg:province":"Flintshire",
    "sg:tags":[
        "breeder"
    ],
    "wof:name":"Flair Hawarden Flower Shop",
    "wof:placetype":"venue"
},
  "geometry": {"coordinates":[-3.028843,53.185284],"type":"Point"}
}