{
  "type": "Feature",
  "properties": {
    "addr:full":"Enterprise House, Lloyd St North, Manchester Science Park Manchester Cheshire M15 6SE",
    "addr:postcode":"m15 6se",
    "addr:street":"Lloyd St;Park",
    "iso:country":"GB",
    "sg:address":"Enterprise House, Lloyd St North, Manchester Science Park",
    "sg:city":"Manchester",
    "sg:classifiers":[
        {
            "category":"Shopping",
            "subcategory":"Optical Goods",
            "type":"Retail Goods"
        }
    ],
    "sg:phone":"+44 161 226 0666",
    "sg:postcode":"M15 6SE",
    "sg:province":"Cheshire",
    "wof:name":"Gerber Optical",
    "wof:placetype":"venue"
},
  "geometry": {"coordinates":[-2.236649,53.464806],"type":"Point"}
}