{
  "type": "Feature",
  "properties": {
    "iso:country":"GB",
    "sg:address":"Coracom, 23-25 Knock Way",
    "sg:city":"Paisley",
    "sg:classifiers":[
        {
            "category":"Organizations",
            "subcategory":"Non-profit Organization",
            "type":"Services"
        }
    ],
    "sg:phone":"+44 141 887 6238",
    "sg:postcode":"PA3 4PB",
    "sg:province":"Renfrewshire",
    "sg:tags":[
        "charitable",
        "organisation",
        "voluntary",
        "charity"
    ],
    "wof:name":"RENFREWSHIRE ASSOCIATION FOR MENTAL HEALTH",
    "wof:placetype":"venue"
},
  "geometry": {"coordinates":[-4.4061999321,55.8591003418],"type":"Point"}
}