{
  "type": "Feature",
  "properties": {
    "iso:country":"GB",
    "sg:address":"Station Road",
    "sg:city":"Ashington",
    "sg:classifiers":[
        {
            "category":"Place Of Worship",
            "type":"Public Place"
        }
    ],
    "sg:postcode":"NE63 8AD",
    "sg:province":"Northumberland",
    "wof:name":"St.Aidans Royal Catholic Church",
    "wof:placetype":"venue"
},
  "geometry": {"coordinates":[-1.5802,55.183033],"type":"Point"}
}