{
  "type": "Feature",
  "properties": {
    "addr:full":"67 Manor Road Wallington Surrey SM6 0DE",
    "addr:housenumber":"67",
    "addr:postcode":"sm6 0de",
    "addr:street":"Manor Road",
    "iso:country":"GB",
    "sg:address":"67 Manor Road",
    "sg:city":"Wallington",
    "sg:classifiers":[
        {
            "category":"Health Services",
            "subcategory":"Nursing And Care Facility",
            "type":"Services"
        },
        {
            "category":"Social Services",
            "subcategory":"Retirement Home",
            "type":"Services"
        }
    ],
    "sg:phone":"+44 20 8669 5305",
    "sg:postcode":"SM6 0DE",
    "sg:province":"Surrey",
    "sg:tags":[
        "residential"
    ],
    "wof:name":"Clifton Manor",
    "wof:placetype":"venue"
},
  "geometry": {"coordinates":[-0.150785,51.362549],"type":"Point"}
}