{
  "type": "Feature",
  "properties": {
    "addr:full":"Danecourt Road, Parkstone Poole Dorset BH14 0NG",
    "addr:postcode":"bh14 0ng",
    "addr:street":"Danecourt Road",
    "iso:country":"GB",
    "sg:address":"Danecourt Road, Parkstone",
    "sg:city":"Poole",
    "sg:classifiers":[
        {
            "category":"Education",
            "subcategory":"Special Training",
            "type":"Public Place"
        }
    ],
    "sg:phone":"+44 1202 205690",
    "sg:postcode":"BH14 0NG",
    "sg:province":"Dorset",
    "sg:tags":[
        "product",
        "centre"
    ],
    "wof:name":"Technology Training",
    "wof:placetype":"venue"
},
  "geometry": {"coordinates":[-1.9604890347,50.7264556885],"type":"Point"}
}