{
  "type": "Feature",
  "properties": {
    "addr:full":"133 Salmon Lane London Greater London E14 7PG",
    "addr:housenumber":"133",
    "addr:postcode":"e14 7pg",
    "addr:street":"Salmon Lane",
    "iso:country":"GB",
    "sg:address":"133 Salmon Lane",
    "sg:city":"London",
    "sg:classifiers":[
        {
            "category":"Fast Food",
            "type":"Food & Drink"
        },
        {
            "category":"Wholesale",
            "subcategory":"Groceries",
            "type":"Manufacturing & Wholesale Goods"
        }
    ],
    "sg:phone":"+44 20 7987 0770",
    "sg:postcode":"E14 7PG",
    "sg:province":"Greater London",
    "sg:tags":[
        "supplier",
        "away",
        "take",
        "pizza"
    ],
    "wof:name":"Mario's Pizza",
    "wof:placetype":"venue"
},
  "geometry": {"coordinates":[-0.0331539996,51.5136756897],"type":"Point"}
}