{
  "type": "Feature",
  "properties": {
    "addr:full":"2c Oxford Street Mountain Ash Rhondda, Cynon, Taff CF45 3PL",
    "addr:housenumber":"2c",
    "addr:postcode":"cf45 3pl",
    "addr:street":"Oxford Street;Cynon Taff",
    "iso:country":"GB",
    "sg:address":"2c Oxford Street",
    "sg:city":"Mountain Ash",
    "sg:classifiers":[
        {
            "category":"Professional",
            "subcategory":"Engineering",
            "type":"Services"
        },
        {
            "category":"Retail",
            "subcategory":"Event Space",
            "type":"Services"
        },
        {
            "category":"Home & Garden",
            "subcategory":"Household Appliances",
            "type":"Retail Goods"
        }
    ],
    "sg:phone":"+44 1443 473263",
    "sg:postcode":"CF45 3PL",
    "sg:province":"Rhondda, Cynon, Taff",
    "sg:tags":[
        "product",
        "domestic",
        "sales",
        "contractor",
        "electrical",
        "engineer"
    ],
    "wof:name":"GEORGE LEWIS",
    "wof:placetype":"venue"
},
  "geometry": {"coordinates":[-3.3797180653,51.6833877563],"type":"Point"}
}