{
  "type": "Feature",
  "properties": {
    "iso:country":"GB",
    "sg:address":"Unitc6, Unit C6, Yelverton Business Park, Crapstone",
    "sg:city":"Yelverton",
    "sg:classifiers":[
        {
            "category":"Shopping",
            "subcategory":"Computers & Home Electronics",
            "type":"Retail Goods"
        },
        {
            "category":"Professional",
            "subcategory":"Computer Services",
            "type":"Services"
        }
    ],
    "sg:phone":"+44 1822 855466",
    "sg:postcode":"PL20 7PY",
    "sg:province":"Devon",
    "sg:tags":[
        "software",
        "sales",
        "system"
    ],
    "wof:name":"Team Systems Ltd",
    "wof:placetype":"venue"
},
  "geometry": {"coordinates":[-4.1090941429,50.4900665283],"type":"Point"}
}