{
  "type": "Feature",
  "properties": {
    "addr:full":"44 Connaught Avenue Frinton-on-sea Essex CO13 9PR",
    "addr:housenumber":"44",
    "addr:postcode":"co13 9pr",
    "addr:street":"Connaught Avenue",
    "iso:country":"GB",
    "sg:address":"44 Connaught Avenue",
    "sg:city":"Frinton-on-sea",
    "sg:classifiers":[
        {
            "category":"Shopping",
            "subcategory":"Gifts & Souvenirs",
            "type":"Retail Goods"
        }
    ],
    "sg:phone":"+44 1255 673820",
    "sg:postcode":"CO13 9PR",
    "sg:province":"Essex",
    "sg:tags":[
        "shop"
    ],
    "wof:name":"Frinton Gift Collection",
    "wof:placetype":"venue"
},
  "geometry": {"coordinates":[1.2456949949,51.8317298889],"type":"Point"}
}