{
  "type": "Feature",
  "properties": {
    "addr:full":"Shop, 3 Victoria Rd, Hartshill Nuneaton Leicestershire CV10 0LS",
    "addr:housenumber":"shop 3",
    "addr:postcode":"cv10 0ls",
    "addr:street":"Victoria Rd",
    "iso:country":"GB",
    "sg:address":"Shop, 3 Victoria Rd, Hartshill",
    "sg:city":"Nuneaton",
    "sg:classifiers":[
        {
            "category":"Personal",
            "subcategory":"Beauty Salon",
            "type":"Services"
        }
    ],
    "sg:postcode":"CV10 0LS",
    "sg:province":"Leicestershire",
    "sg:tags":[
        "unisex",
        "hairdresser"
    ],
    "wof:name":"Dagnan,J,",
    "wof:placetype":"venue"
},
  "geometry": {"coordinates":[-1.5263259411,52.5371208191],"type":"Point"}
}