{
  "type": "Feature",
  "properties": {
    "iso:country":"GB",
    "sg:address":"Earlsway",
    "sg:city":"Gateshead",
    "sg:classifiers":[
        {
            "category":"Food & Beverages",
            "subcategory":"Candy",
            "type":"Retail Goods"
        }
    ],
    "sg:postcode":"NE11 0UU",
    "sg:province":"Tyne and Wear",
    "sg:tags":[
        "confectioner"
    ],
    "wof:name":"C D C (Crisps) Ltd.",
    "wof:placetype":"venue"
},
  "geometry": {"coordinates":[-1.61142,54.930519],"type":"Point"}
}