{
  "type": "Feature",
  "properties": {
    "addr:full":"Unsworth Hall, Manchester Road Bury Lancashire BL9 9TJ",
    "addr:postcode":"bl9 9tj",
    "addr:street":"Manchester Road",
    "iso:country":"GB",
    "sg:address":"Unsworth Hall, Manchester Road",
    "sg:city":"Bury",
    "sg:classifiers":[
        {
            "category":"Sports & Exercise",
            "subcategory":"Golf",
            "type":"Entertainment"
        }
    ],
    "sg:phone":"+44 161 766 4897",
    "sg:postcode":"BL9 9TJ",
    "sg:province":"Lancashire",
    "sg:tags":[
        "club",
        "course"
    ],
    "wof:name":"Bury Golf Club",
    "wof:placetype":"venue"
},
  "geometry": {"coordinates":[-2.3010540009,53.5897331238],"type":"Point"}
}