{
  "type": "Feature",
  "properties": {
    "addr:full":"Burland House, Tysoe Road Warwick Warwickshire CV35 0RD",
    "addr:postcode":"cv35 0rd",
    "addr:street":"Tysoe Road",
    "iso:country":"GB",
    "sg:address":"Burland House, Tysoe Road",
    "sg:city":"Warwick",
    "sg:classifiers":[
        {
            "category":"Health Services",
            "subcategory":"Optometrist",
            "type":"Services"
        }
    ],
    "sg:phone":"+44 1295 680798",
    "sg:postcode":"CV35 0RD",
    "sg:province":"Warwickshire",
    "sg:tags":[
        "optician"
    ],
    "wof:name":"G Sewell & Partners Ltd.",
    "wof:placetype":"venue"
},
  "geometry": {"coordinates":[-1.514459,52.150509],"type":"Point"}
}