{
  "type": "Feature",
  "properties": {
    "addr:full":"Elmfield, Bordyke Tonbridge Kent TN9 1NL",
    "addr:postcode":"tn9 1nl",
    "addr:street":"Tonbridge",
    "iso:country":"GB",
    "sg:address":"Elmfield, Bordyke",
    "sg:city":"Tonbridge",
    "sg:classifiers":[
        {
            "category":"Real Estate",
            "subcategory":"Architect",
            "type":"Services"
        }
    ],
    "sg:phone":"+44 1732 354292",
    "sg:postcode":"TN9 1NL",
    "sg:province":"Kent",
    "wof:name":"Geoffrey Butcher & Associates",
    "wof:placetype":"venue"
},
  "geometry": {"coordinates":[0.27634,51.199829],"type":"Point"}
}