{
  "type": "Feature",
  "properties": {
    "addr:full":"Glenbery House, Walton Street, Long Eaton Nottingham Derbyshire NG10 1PB",
    "addr:postcode":"ng10 1pb",
    "addr:street":"Walton Street",
    "iso:country":"GB",
    "sg:address":"Glenbery House, Walton Street, Long Eaton",
    "sg:city":"Nottingham",
    "sg:classifiers":[
        {
            "category":"Retail",
            "subcategory":"Repair Shop",
            "type":"Services"
        }
    ],
    "sg:phone":"+44 115 946 0625",
    "sg:postcode":"NG10 1PB",
    "sg:province":"Derbyshire",
    "sg:tags":[
        "upholsterer"
    ],
    "wof:name":"Glenbery Upholstery Ltd.",
    "wof:placetype":"venue"
},
  "geometry": {"coordinates":[-1.27433,52.901676],"type":"Point"}
}