{
  "type": "Feature",
  "properties": {
    "iso:country":"GB",
    "sg:address":"2 Old House Farm Barn, Heightington",
    "sg:city":"Bewdley",
    "sg:classifiers":[
        {
            "category":"Building & Trades",
            "subcategory":"Construction",
            "type":"Services"
        }
    ],
    "sg:phone":"+44 1299 824822",
    "sg:postcode":"DY12 2XT",
    "sg:province":"Shropshire",
    "sg:tags":[
        "builder"
    ],
    "wof:name":"H F D Building Maintenance Ltd.",
    "wof:placetype":"venue"
},
  "geometry": {"coordinates":[-2.314779,52.376019],"type":"Point"}
}