{
  "type": "Feature",
  "properties": {
    "iso:country":"GB",
    "sg:address":"1 Loman Rd",
    "sg:city":"Camberley",
    "sg:classifiers":[
        {
            "category":"Building & Trades",
            "subcategory":"Construction",
            "type":"Services"
        }
    ],
    "sg:phone":"+44 1252 542737",
    "sg:postcode":"GU16 6BS",
    "sg:province":"Hampshire",
    "sg:tags":[
        "builder"
    ],
    "wof:name":"Tudor Builders",
    "wof:placetype":"venue"
},
  "geometry": {"coordinates":[-0.724261,51.292431],"type":"Point"}
}