{
  "type": "Feature",
  "properties": {
    "addr:full":"83 Notting Hill Gate London Greater London W11 3JS",
    "addr:housenumber":"83",
    "addr:postcode":"w11 3js",
    "addr:street":"Notting Hill Gate",
    "iso:country":"GB",
    "sg:address":"83 Notting Hill Gate",
    "sg:city":"London",
    "sg:classifiers":[
        {
            "category":"Banks & Credit Unions",
            "subcategory":"Bank",
            "type":"Services"
        }
    ],
    "sg:phone":"+44 20 8301 7307",
    "sg:postcode":"W11 3JS",
    "sg:province":"Greater London",
    "wof:name":"Woolwich",
    "wof:placetype":"venue"
},
  "geometry": {"coordinates":[-0.196792,51.508945],"type":"Point"}
}