{
  "type": "Feature",
  "properties": {
    "iso:country":"GB",
    "sg:address":"151 St Andrews Rd",
    "sg:city":"Coulsdon",
    "sg:classifiers":[
        {
            "category":"Building & Trades",
            "subcategory":"Plumbing",
            "type":"Services"
        }
    ],
    "sg:phone":"+44 20 8668 4894",
    "sg:postcode":"CR5 3HL",
    "sg:province":"Surrey",
    "sg:tags":[
        "central",
        "heating"
    ],
    "wof:name":"Ian Dow",
    "wof:placetype":"venue"
},
  "geometry": {"coordinates":[-0.15505,51.319145],"type":"Point"}
}