{
  "type": "Feature",
  "properties": {
    "addr:full":"2 Hill Cottage, Chesnut Lane, Bassingbourn Royston Bedfordshire SG8 5JH",
    "addr:housenumber":"2 hill cottage",
    "addr:postcode":"sg8 5jh",
    "addr:street":"Chesnut Lane",
    "iso:country":"GB",
    "sg:address":"2 Hill Cottage, Chesnut Lane, Bassingbourn",
    "sg:city":"Royston",
    "sg:classifiers":[
        {
            "category":"Home & Garden",
            "subcategory":"Garden Supply",
            "type":"Retail Goods"
        },
        {
            "category":"Farming",
            "subcategory":"Livestock Farm",
            "type":"Manufacturing & Wholesale Goods"
        }
    ],
    "sg:phone":"+44 1763 242406",
    "sg:postcode":"SG8 5JH",
    "sg:province":"Bedfordshire",
    "sg:tags":[
        "bulb",
        "grower",
        "others"
    ],
    "wof:name":"E W Staden & Son",
    "wof:placetype":"venue"
},
  "geometry": {"coordinates":[-0.0578619987,52.0776519775],"type":"Point"}
}