{
  "type": "Feature",
  "properties": {
    "addr:full":"3 Porchester Rd Kingston-upon-thames Greater London KT1 3PW",
    "addr:housenumber":"3",
    "addr:postcode":"kt1 3pw",
    "addr:street":"Porchester Rd",
    "iso:country":"GB",
    "sg:address":"3 Porchester Rd",
    "sg:city":"Kingston-upon-thames",
    "sg:classifiers":[
        {
            "category":"Professional",
            "subcategory":"Art Services",
            "type":"Services"
        }
    ],
    "sg:postcode":"KT1 3PW",
    "sg:province":"Greater London",
    "sg:tags":[
        "photographer"
    ],
    "wof:name":"David Quay",
    "wof:placetype":"venue"
},
  "geometry": {"coordinates":[-0.280269,51.409611],"type":"Point"}
}