{
  "type": "Feature",
  "properties": {
    "iso:country":"GB",
    "sg:address":"Stawn Ho, Stourbridge Rd",
    "sg:city":"Dudley",
    "sg:classifiers":[
        {
            "category":"Professional",
            "subcategory":"Detective & Security Services",
            "type":"Services"
        }
    ],
    "sg:postcode":"DY1 2ER",
    "sg:province":"West Midlands",
    "sg:tags":[
        "agency"
    ],
    "wof:name":"S T M Investigations",
    "wof:placetype":"venue"
},
  "geometry": {"coordinates":[-2.095399,52.505516],"type":"Point"}
}