{
  "type": "Feature",
  "properties": {
    "addr:full":"123 Stockwell St Glasgow Glasgow City G1 4LT",
    "addr:housenumber":"123",
    "addr:postcode":"g1 4lt",
    "addr:street":"Stockwell St",
    "iso:country":"GB",
    "sg:address":"123 Stockwell St",
    "sg:city":"Glasgow",
    "sg:classifiers":[
        {
            "category":"Personal",
            "type":"Services"
        }
    ],
    "sg:phone":"+44 141 552 8139",
    "sg:postcode":"G1 4LT",
    "sg:province":"Glasgow City",
    "sg:tags":[
        "wedding"
    ],
    "wof:name":"Brides International",
    "wof:placetype":"venue"
},
  "geometry": {"coordinates":[-4.2499871254,55.8554344177],"type":"Point"}
}