{
  "type": "Feature",
  "properties": {
    "addr:full":"9 Merse Road, Moons Moat North Industrial Estate Redditch Warwickshire B98 9HL",
    "addr:housenumber":"9",
    "addr:postcode":"b98 9hl",
    "addr:street":"Merse Road;Estate",
    "iso:country":"GB",
    "sg:address":"9 Merse Road, Moons Moat North Industrial Estate",
    "sg:city":"Redditch",
    "sg:classifiers":[
        {
            "category":"Manufacturing",
            "subcategory":"Tools & Machinery",
            "type":"Manufacturing & Wholesale Goods"
        },
        {
            "category":"Home & Garden",
            "subcategory":"Home Furnishings",
            "type":"Retail Goods"
        },
        {
            "category":"Train Station",
            "subcategory":"Rail",
            "type":"Transportation"
        }
    ],
    "sg:phone":"+44 1527 598050",
    "sg:postcode":"B98 9HL",
    "sg:province":"Warwickshire",
    "sg:tags":[
        "manufacture",
        "supply",
        "tube",
        "fitting",
        "stockist",
        "powertools",
        "supplier"
    ],
    "wof:name":"AUTO-TECHNIK SYSTEMS LTD",
    "wof:placetype":"venue"
},
  "geometry": {"coordinates":[-1.893334,52.317394],"type":"Point"}
}