{
  "type": "Feature",
  "properties": {
    "addr:full":"143 High Street Lewes East Sussex BN7 1XT",
    "addr:housenumber":"143",
    "addr:postcode":"bn7 1xt",
    "addr:street":"High Street",
    "iso:country":"GB",
    "sg:address":"143 High Street",
    "sg:city":"Lewes",
    "sg:classifiers":[
        {
            "category":"Farming",
            "subcategory":"Nursery",
            "type":"Manufacturing & Wholesale Goods"
        }
    ],
    "sg:phone":"+44 1273 486723",
    "sg:postcode":"BN7 1XT",
    "sg:province":"East Sussex",
    "sg:tags":[
        "creche"
    ],
    "wof:name":"Step by Step Centre",
    "wof:placetype":"venue"
},
  "geometry": {"coordinates":[0.0058590001,50.8721122742],"type":"Point"}
}