{
  "type": "Feature",
  "properties": {
    "addr:full":"Orthondontic Practice Outpatient Department, North Main St Alexandria Argyll and Bute G83 0UA",
    "addr:postcode":"g83 0ua",
    "addr:street":"North Main St",
    "iso:country":"GB",
    "sg:address":"Orthondontic Practice Outpatient Department, North Main St",
    "sg:city":"Alexandria",
    "sg:classifiers":[
        {
            "category":"Health Services",
            "subcategory":"Dentist",
            "type":"Services"
        }
    ],
    "sg:phone":"+44 1389 754121",
    "sg:postcode":"G83 0UA",
    "sg:province":"Argyll and Bute",
    "wof:name":"Simon Miller",
    "wof:placetype":"venue"
},
  "geometry": {"coordinates":[-4.585209,55.992142],"type":"Point"}
}