{
  "type": "Feature",
  "properties": {
    "iso:country":"GB",
    "sg:address":"23 Grassmeers Drive, Whitchurch",
    "sg:city":"Bristol",
    "sg:classifiers":[
        {
            "category":"Retail",
            "subcategory":"Driving School",
            "type":"Services"
        }
    ],
    "sg:phone":"+44 1275 837399",
    "sg:postcode":"BS14 0LE",
    "sg:province":"City of Bristol",
    "wof:name":"Chaldon School of Motoring",
    "wof:placetype":"venue"
},
  "geometry": {"coordinates":[-2.572609,51.405781],"type":"Point"}
}