{
  "type": "Feature",
  "properties": {
    "iso:country":"GB",
    "sg:address":"55 Fogwell Rd",
    "sg:city":"Oxford",
    "sg:classifiers":[
        {
            "category":"Building & Trades",
            "subcategory":"Plumbing",
            "type":"Services"
        }
    ],
    "sg:phone":"+44 1865 862689",
    "sg:postcode":"OX2 9SD",
    "sg:province":"Oxfordshire",
    "sg:tags":[
        "heating"
    ],
    "wof:name":"Day John",
    "wof:placetype":"venue"
},
  "geometry": {"coordinates":[-1.30775,51.752453],"type":"Point"}
}