{
  "type": "Feature",
  "properties": {
    "addr:full":"Crowd Hill, Fair Oak Eastleigh Hampshire SO50 7HD",
    "addr:postcode":"so50 7hd",
    "addr:street":"Crowd Hill;Oak",
    "iso:country":"GB",
    "sg:address":"Crowd Hill, Fair Oak",
    "sg:city":"Eastleigh",
    "sg:classifiers":[
        {
            "category":"Education",
            "subcategory":"Music School",
            "type":"Public Place"
        }
    ],
    "sg:phone":"+44 23 8060 1784",
    "sg:postcode":"SO50 7HD",
    "sg:province":"Hampshire",
    "sg:tags":[
        "conservatory"
    ],
    "wof:name":"Southern Stone Paving",
    "wof:placetype":"venue"
},
  "geometry": {"coordinates":[-1.2907940149,50.9654312134],"type":"Point"}
}