{
  "type": "Feature",
  "properties": {
    "addr:full":"Park Terr Brodick North Ayrshire KA27 8NB",
    "addr:postcode":"ka27 8nb",
    "addr:street":"Park Terr",
    "iso:country":"GB",
    "sg:address":"Park Terr",
    "sg:city":"Brodick",
    "sg:classifiers":[
        {
            "category":"Professional",
            "subcategory":"Lawyer & Legal Services",
            "type":"Services"
        }
    ],
    "sg:phone":"+44 1770 600210",
    "sg:postcode":"KA27 8NB",
    "sg:province":"North Ayrshire",
    "sg:tags":[
        "advice",
        "counselling"
    ],
    "wof:name":"Arran Information & Advice Service",
    "wof:placetype":"venue"
},
  "geometry": {"coordinates":[-5.1523189545,55.5775756836],"type":"Point"}
}