{
  "type": "Feature",
  "properties": {
    "addr:full":"22 Lutterworth Road Coventry Warwickshire CV2 3EB",
    "addr:housenumber":"22",
    "addr:postcode":"cv2 3eb",
    "addr:street":"Lutterworth Road",
    "iso:country":"GB",
    "sg:address":"22 Lutterworth Road",
    "sg:city":"Coventry",
    "sg:classifiers":[
        {
            "category":"Retail",
            "subcategory":"Driving School",
            "type":"Services"
        }
    ],
    "sg:phone":"+44 24 7644 3968",
    "sg:postcode":"CV2 3EB",
    "sg:province":"Warwickshire",
    "wof:name":"Barry Shaw School of Motoring",
    "wof:placetype":"venue"
},
  "geometry": {"coordinates":[-1.46773,52.41721],"type":"Point"}
}