{
  "type": "Feature",
  "properties": {
    "iso:country":"GB",
    "sg:address":"Rockingham Dr",
    "sg:city":"Milton Keynes",
    "sg:classifiers":[
        {
            "category":"Manufacturing",
            "subcategory":"Chemicals & Compounds",
            "type":"Manufacturing & Wholesale Goods"
        }
    ],
    "sg:phone":"+44 1908 606040",
    "sg:postcode":"MK14 6LY",
    "sg:province":"Buckinghamshire",
    "wof:name":"M K Envirochemicals",
    "wof:placetype":"venue"
},
  "geometry": {"coordinates":[-0.756804,52.055866],"type":"Point"}
}