{
  "type": "Feature",
  "properties": {
    "addr:full":"183 Trysull Road Wolverhampton Staffordshire WV3 7JP",
    "addr:housenumber":"183",
    "addr:postcode":"wv3 7jp",
    "addr:street":"Trysull Road",
    "iso:country":"GB",
    "sg:address":"183 Trysull Road",
    "sg:city":"Wolverhampton",
    "sg:classifiers":[
        {
            "category":"Building & Trades",
            "subcategory":"Plumbing",
            "type":"Services"
        }
    ],
    "sg:phone":"+44 1902 334986",
    "sg:postcode":"WV3 7JP",
    "sg:province":"Staffordshire",
    "sg:tags":[
        "heating"
    ],
    "wof:name":"John B Clarke",
    "wof:placetype":"venue"
},
  "geometry": {"coordinates":[-2.1663379669,52.5719718933],"type":"Point"}
}