{
  "type": "Feature",
  "properties": {
    "iso:country":"GB",
    "sg:address":"Oxford House, Stakeford Lane",
    "sg:city":"Choppington",
    "sg:classifiers":[
        {
            "category":"Home & Garden",
            "subcategory":"Home Furnishings",
            "type":"Retail Goods"
        }
    ],
    "sg:phone":"+44 1670 811269",
    "sg:postcode":"NE62 5JU",
    "sg:province":"Northumberland",
    "sg:tags":[
        "blind",
        "curtain",
        "fitting"
    ],
    "wof:name":"The Factory Shop",
    "wof:placetype":"venue"
},
  "geometry": {"coordinates":[-1.6000850201,55.1461753845],"type":"Point"}
}