{
  "type": "Feature",
  "properties": {
    "addr:full":"140 Wigan Lower Road, Standish Lower Ground Wigan Lancashire WN6 8JP",
    "addr:housenumber":"140",
    "addr:postcode":"wn6 8jp",
    "addr:street":"Wigan Lower Road",
    "iso:country":"GB",
    "sg:address":"140 Wigan Lower Road, Standish Lower Ground",
    "sg:city":"Wigan",
    "sg:classifiers":[
        {
            "category":"Shopping",
            "subcategory":"Bicycles & Sporting Goods",
            "type":"Retail Goods"
        }
    ],
    "sg:phone":"+44 1942 203871",
    "sg:postcode":"WN6 8JP",
    "sg:province":"Lancashire",
    "sg:tags":[
        "cycle",
        "accessory"
    ],
    "wof:name":"Lower Ground Cycles",
    "wof:placetype":"venue"
},
  "geometry": {"coordinates":[-2.667075,53.561596],"type":"Point"}
}