{
  "type": "Feature",
  "properties": {
    "iso:country":"GB",
    "sg:address":"6a Market Square",
    "sg:city":"Marlow",
    "sg:classifiers":[
        {
            "category":"Restaurant",
            "type":"Food & Drink"
        }
    ],
    "sg:phone":"+44 1628 475035",
    "sg:postcode":"SL7 1DA",
    "sg:province":"Berkshire",
    "wof:name":"Jasmine Peking",
    "wof:placetype":"venue"
},
  "geometry": {"coordinates":[-0.777021,51.571957],"type":"Point"}
}