{
  "type": "Feature",
  "properties": {
    "addr:full":"62 Holland Pk London Greater London W11 3SJ",
    "addr:housenumber":"62",
    "addr:postcode":"w11 3sj",
    "addr:street":"Holland Pk",
    "iso:country":"GB",
    "sg:address":"62 Holland Pk",
    "sg:city":"London",
    "sg:classifiers":[
        {
            "category":"Organizations",
            "subcategory":"Community Association",
            "type":"Services"
        }
    ],
    "sg:phone":"+44 20 7221 1589",
    "sg:postcode":"W11 3SJ",
    "sg:province":"Greater London",
    "sg:tags":[
        "relation",
        "public"
    ],
    "wof:name":"Bloomfield,Julie,",
    "wof:placetype":"venue"
},
  "geometry": {"coordinates":[-0.207552,51.506176],"type":"Point"}
}