{
  "type": "Feature",
  "properties": {
    "addr:full":"Unit 3 Croydon Surrey CR0 3RZ",
    "addr:housenumber":"unit 3",
    "addr:postcode":"cr0 3rz",
    "iso:country":"GB",
    "sg:address":"Unit 3",
    "sg:city":"Croydon",
    "sg:classifiers":[
        {
            "category":"Professional",
            "subcategory":"Printing & Photocopies",
            "type":"Services"
        }
    ],
    "sg:postcode":"CR0 3RZ",
    "sg:province":"Surrey",
    "sg:tags":[
        "printer"
    ],
    "wof:name":"Ikon Printing Co. Ltd.",
    "wof:placetype":"venue"
},
  "geometry": {"coordinates":[-0.111318998,51.3811531067],"type":"Point"}
}