{
  "type": "Feature",
  "properties": {
    "iso:country":"GB",
    "sg:address":"6 Meadowhall Road",
    "sg:city":"Rotherham",
    "sg:classifiers":[
        {
            "category":"Shopping",
            "subcategory":"News",
            "type":"Retail Goods"
        }
    ],
    "sg:phone":"+44 1709 510200",
    "sg:postcode":"S61 2HX",
    "sg:province":"South Yorkshire",
    "sg:tags":[
        "newsagent"
    ],
    "wof:name":"E V & C Kelly",
    "wof:placetype":"venue"
},
  "geometry": {"coordinates":[-1.41165,53.421234],"type":"Point"}
}