{
  "type": "Feature",
  "properties": {
    "addr:full":"24 Newton Avenue, Barrhead Glasgow East Ayrshire G78 2JY",
    "addr:housenumber":"24",
    "addr:postcode":"g78 2jy",
    "addr:street":"Newton Avenue",
    "iso:country":"GB",
    "sg:address":"24 Newton Avenue, Barrhead",
    "sg:city":"Glasgow",
    "sg:classifiers":[
        {
            "category":"Food & Beverages",
            "subcategory":"Fruits & Vegetables",
            "type":"Retail Goods"
        }
    ],
    "sg:phone":"+44 141 881 4810",
    "sg:postcode":"G78 2JY",
    "sg:province":"East Ayrshire",
    "sg:tags":[
        "greengrocer"
    ],
    "wof:name":"Mohammed Hussain",
    "wof:placetype":"venue"
},
  "geometry": {"coordinates":[-4.383891,55.792049],"type":"Point"}
}