{
  "type": "Feature",
  "properties": {
    "iso:country":"GB",
    "sg:address":"Maidstone Road, Platt, Borough Green",
    "sg:city":"Maidstone",
    "sg:classifiers":[
        {
            "category":"Professional",
            "subcategory":"Engineering",
            "type":"Services"
        }
    ],
    "sg:phone":"+44 1732 780780",
    "sg:postcode":"TN15 8JE",
    "sg:province":"Kent",
    "wof:name":"Otford Tool & Gauge Co. Ltd.",
    "wof:placetype":"venue"
},
  "geometry": {"coordinates":[0.316322,51.291424],"type":"Point"}
}