{
  "type": "Feature",
  "properties": {
    "iso:country":"GB",
    "sg:address":"2-4 Market Pl",
    "sg:city":"Shipston On Stour",
    "sg:classifiers":[
        {
            "category":"Shopping",
            "subcategory":"News",
            "type":"Retail Goods"
        }
    ],
    "sg:phone":"+44 1608 661287",
    "sg:postcode":"CV36 4AG",
    "sg:province":"Warwickshire",
    "sg:tags":[
        "newsagent"
    ],
    "wof:name":"B A Bradley",
    "wof:placetype":"venue"
},
  "geometry": {"coordinates":[-1.624568,52.063255],"type":"Point"}
}