{
  "type": "Feature",
  "properties": {
    "addr:full":"1 Brindley Rd, South West Indust Est Peterlee Durham SR8 2LT",
    "addr:housenumber":"1",
    "addr:postcode":"sr8 2lt",
    "addr:street":"Brindley Rd South;Indust",
    "iso:country":"GB",
    "sg:address":"1 Brindley Rd, South West Indust Est",
    "sg:city":"Peterlee",
    "sg:classifiers":[
        {
            "category":"Wholesale",
            "subcategory":"Machinery & Supplies",
            "type":"Manufacturing & Wholesale Goods"
        }
    ],
    "sg:phone":"+44 191 518 1555",
    "sg:postcode":"SR8 2LT",
    "sg:province":"Durham",
    "sg:tags":[
        "hydraulic"
    ],
    "wof:name":"Aldona Hillman Newby Ltd",
    "wof:placetype":"venue"
},
  "geometry": {"coordinates":[-1.3662190437,54.759803772],"type":"Point"}
}