{
  "type": "Feature",
  "properties": {
    "addr:full":"76 Players Crescent, Totton Southampton Hampshire SO40 9BD",
    "addr:housenumber":"76",
    "addr:postcode":"so40 9bd",
    "addr:street":"Players Crescent",
    "iso:country":"GB",
    "sg:address":"76 Players Crescent, Totton",
    "sg:city":"Southampton",
    "sg:classifiers":[
        {
            "category":"Communications",
            "subcategory":"Film & Video Production",
            "type":"Services"
        }
    ],
    "sg:phone":"+44 23 8086 8370",
    "sg:postcode":"SO40 9BD",
    "sg:province":"Hampshire",
    "sg:tags":[
        "illustrator",
        "artist"
    ],
    "wof:name":"G Zlanabitig",
    "wof:placetype":"venue"
},
  "geometry": {"coordinates":[-1.496566,50.910629],"type":"Point"}
}