{
  "type": "Feature",
  "properties": {
    "iso:country":"GB",
    "sg:address":"35 Beechdale Road",
    "sg:city":"London",
    "sg:classifiers":[
        {
            "category":"Communications",
            "type":"Services"
        }
    ],
    "sg:phone":"+44 20 8674 1799",
    "sg:postcode":"SW2 2BN",
    "sg:province":"Greater London",
    "sg:tags":[
        "audio-visual"
    ],
    "wof:name":"Video Portraits",
    "wof:placetype":"venue"
},
  "geometry": {"coordinates":[-0.1188609973,51.4519920349],"type":"Point"}
}