{
  "type": "Feature",
  "properties": {
    "iso:country":"GB",
    "sg:address":"103 Camphill Rd, Chapel End",
    "sg:city":"Nuneaton",
    "sg:classifiers":[
        {
            "category":"Autos & Motor Vehicles",
            "subcategory":"Motorcycle Sales",
            "type":"Retail Goods"
        }
    ],
    "sg:phone":"+44 24 7639 4200",
    "sg:postcode":"CV10 0JR",
    "sg:province":"Leicestershire",
    "sg:tags":[
        "chauffeur",
        "driven",
        "car"
    ],
    "wof:name":"David Sharpe Chauffeur Services",
    "wof:placetype":"venue"
},
  "geometry": {"coordinates":[-1.5132759809,52.5365982056],"type":"Point"}
}