{
  "type": "Feature",
  "properties": {
    "iso:country":"GB",
    "sg:address":"Royal Preston Hospital, Sharoe Green Lane, Fulwood",
    "sg:city":"Preston",
    "sg:classifiers":[
        {
            "category":"Personal",
            "subcategory":"Beauty Salon",
            "type":"Services"
        }
    ],
    "sg:phone":"+44 1772 788002",
    "sg:postcode":"PR2 4HT",
    "sg:province":"Lancashire",
    "sg:tags":[
        "unisex",
        "hairdresser"
    ],
    "wof:name":"Unique Hair Care",
    "wof:placetype":"venue"
},
  "geometry": {"coordinates":[-2.71318,53.790051],"type":"Point"}
}