{
  "type": "Feature",
  "properties": {
    "iso:country":"GB",
    "sg:address":"4 Southgate Drive",
    "sg:city":"Crawley",
    "sg:classifiers":[
        {
            "category":"Shopping",
            "subcategory":"Books",
            "type":"Retail Goods"
        },
        {
            "category":"Organizations",
            "subcategory":"Religious Organization",
            "type":"Services"
        }
    ],
    "sg:postcode":"RH10 6RP",
    "sg:province":"Surrey",
    "sg:tags":[
        "bookseller",
        "organisation"
    ],
    "wof:name":"Diocese of Arundel & Brighton Christian Education Centre",
    "wof:placetype":"venue"
},
  "geometry": {"coordinates":[-0.190184,51.108265],"type":"Point"}
}