{
  "type": "Feature",
  "properties": {
    "iso:country":"GB",
    "sg:address":"Marelands, Bentley",
    "sg:city":"Farnham",
    "sg:classifiers":[
        {
            "category":"Farming",
            "subcategory":"Livestock Farm",
            "type":"Manufacturing & Wholesale Goods"
        }
    ],
    "sg:postcode":"GU10 5JB",
    "sg:province":"Hampshire",
    "sg:tags":[
        "others"
    ],
    "wof:name":"C C MEATYARD",
    "wof:placetype":"venue"
},
  "geometry": {"coordinates":[-0.875309,51.190193],"type":"Point"}
}