{
  "type": "Feature",
  "properties": {
    "iso:country":"GB",
    "sg:address":"Delfan",
    "sg:city":"Pencader",
    "sg:classifiers":[
        {
            "category":"Professional",
            "subcategory":"Engineering",
            "type":"Services"
        }
    ],
    "sg:phone":"+44 1559 384669",
    "sg:postcode":"SA39 9AA",
    "sg:province":"Carmarthenshire",
    "sg:tags":[
        "contractor",
        "electrical",
        "engineer"
    ],
    "wof:name":"R H Joyner &sons",
    "wof:placetype":"venue"
},
  "geometry": {"coordinates":[-4.2658638954,52.0002288818],"type":"Point"}
}