{
  "type": "Feature",
  "properties": {
    "addr:full":"11 Lodge, Forge Trading Estate, Cradley Rd Cradley Heath West Midlands B64 7RW",
    "addr:housenumber":"11",
    "addr:postcode":"b64 7rw",
    "addr:street":"Lodge Forge Trading Estate Cradley Rd",
    "iso:country":"GB",
    "sg:address":"11 Lodge, Forge Trading Estate, Cradley Rd",
    "sg:city":"Cradley Heath",
    "sg:classifiers":[
        {
            "category":"Autos & Motor Vehicles",
            "subcategory":"Auto Supplies",
            "type":"Retail Goods"
        }
    ],
    "sg:phone":"+44 1384 562826",
    "sg:postcode":"B64 7RW",
    "sg:province":"West Midlands",
    "sg:tags":[
        "car",
        "accessory"
    ],
    "wof:name":"X L Components",
    "wof:placetype":"venue"
},
  "geometry": {"coordinates":[-2.081574,52.472416],"type":"Point"}
}