{
  "type": "Feature",
  "properties": {
    "iso:country":"GB",
    "sg:address":"Quay Cottage, Promenade",
    "sg:city":"Kingsbridge",
    "sg:classifiers":[
        {
            "category":"Autos & Motor Vehicles",
            "subcategory":"Boat Sales",
            "type":"Retail Goods"
        }
    ],
    "sg:phone":"+44 1548 852424",
    "sg:postcode":"TQ7 1JF",
    "sg:province":"Devon",
    "sg:tags":[
        "repair",
        "builder"
    ],
    "wof:name":"Mariner Sports Ltd",
    "wof:placetype":"venue"
},
  "geometry": {"coordinates":[-3.776094,50.282696],"type":"Point"}
}