{
  "type": "Feature",
  "properties": {
    "iso:country":"GB",
    "sg:address":"5 Verna Place",
    "sg:city":"Plymouth",
    "sg:classifiers":[
        {
            "category":"Retail",
            "subcategory":"Repair Shop",
            "type":"Services"
        }
    ],
    "sg:phone":"+44 1752 350950",
    "sg:postcode":"PL5 2EJ",
    "sg:province":"Devon",
    "sg:tags":[
        "television",
        "good",
        "video",
        "servicing",
        "maintenance",
        "radio"
    ],
    "wof:name":"C T V Electronics",
    "wof:placetype":"venue"
},
  "geometry": {"coordinates":[-4.184264183,50.4071769714],"type":"Point"}
}