{
  "type": "Feature",
  "properties": {
    "iso:country":"GB",
    "sg:address":"97 Feltham Rd",
    "sg:city":"Ashford",
    "sg:classifiers":[
        {
            "category":"Shopping",
            "subcategory":"News",
            "type":"Retail Goods"
        }
    ],
    "sg:postcode":"TW15 1BS",
    "sg:province":"Greater London",
    "sg:tags":[
        "newsagent"
    ],
    "wof:name":"L F McBride Ltd",
    "wof:placetype":"venue"
},
  "geometry": {"coordinates":[-0.448858,51.432892],"type":"Point"}
}