{
  "type": "Feature",
  "properties": {
    "addr:full":"157-159 Rye Lane Peckham Greater London SE15 4TL",
    "addr:housenumber":"157-159",
    "addr:postcode":"se15 4tl",
    "addr:street":"Rye Lane",
    "iso:country":"GB",
    "sg:address":"157-159 Rye Lane",
    "sg:city":"Peckham",
    "sg:classifiers":[
        {
            "category":"Professional",
            "subcategory":"Art Services",
            "type":"Services"
        }
    ],
    "sg:phone":"+44 20 7732 3986",
    "sg:postcode":"SE15 4TL",
    "sg:province":"Greater London",
    "sg:tags":[
        "decorating",
        "painting"
    ],
    "wof:name":"Discount Decorating",
    "wof:placetype":"venue"
},
  "geometry": {"coordinates":[-0.0675040036,51.4688606262],"type":"Point"}
}