{
  "type": "Feature",
  "properties": {
    "addr:full":"21 Bridgeman Terrace Wigan Lancashire WN1 1TJ",
    "addr:housenumber":"21",
    "addr:postcode":"wn1 1tj",
    "addr:street":"Bridgeman Terrace",
    "iso:country":"GB",
    "sg:address":"21 Bridgeman Terrace",
    "sg:city":"Wigan",
    "sg:classifiers":[
        {
            "category":"Professional",
            "subcategory":"Lawyer & Legal Services",
            "type":"Services"
        }
    ],
    "sg:phone":"+44 1942 826272",
    "sg:postcode":"WN1 1TJ",
    "sg:province":"Lancashire",
    "sg:tags":[
        "solicitor"
    ],
    "wof:name":"John Holland",
    "wof:placetype":"venue"
},
  "geometry": {"coordinates":[-2.6345570087,53.5518798828],"type":"Point"}
}