{
  "type": "Feature",
  "properties": {
    "addr:full":"Unit 5, Barracks Rd, Sandy Lane Indstl Est Stourport-on-severn Worcestershire DY13 9QB",
    "addr:housenumber":"unit 5",
    "addr:postcode":"dy13 9qb",
    "addr:street":"Barracks Rd;Lane;Est",
    "iso:country":"GB",
    "sg:address":"Unit 5, Barracks Rd, Sandy Lane Indstl Est",
    "sg:city":"Stourport-on-severn",
    "sg:classifiers":[
        {
            "category":"Education",
            "subcategory":"Music School",
            "type":"Public Place"
        }
    ],
    "sg:postcode":"DY13 9QB",
    "sg:province":"Worcestershire",
    "sg:tags":[
        "conservatory"
    ],
    "wof:name":"Court Conservatories Ltd",
    "wof:placetype":"venue"
},
  "geometry": {"coordinates":[-2.2650339603,52.3288612366],"type":"Point"}
}