{
  "type": "Feature",
  "properties": {
    "addr:full":"125 Demesne Road Wallington Surrey SM6 8EW",
    "addr:housenumber":"125",
    "addr:postcode":"sm6 8ew",
    "addr:street":"Demesne Road",
    "iso:country":"GB",
    "sg:address":"125 Demesne Road",
    "sg:city":"Wallington",
    "sg:classifiers":[
        {
            "category":"Real Estate",
            "subcategory":"Surveying",
            "type":"Services"
        }
    ],
    "sg:phone":"+44 20 8647 7613",
    "sg:postcode":"SM6 8EW",
    "sg:province":"Surrey",
    "sg:tags":[
        "building",
        "surveyor"
    ],
    "wof:name":"Adam Charles Chartered Surveyors",
    "wof:placetype":"venue"
},
  "geometry": {"coordinates":[-0.140373,51.367947],"type":"Point"}
}