{
  "type": "Feature",
  "properties": {
    "addr:full":"Hazel Farm Road, Totton Southampton Hampshire SO40 8WU",
    "addr:postcode":"so40 8wu",
    "addr:street":"Hazel Farm Road",
    "iso:country":"GB",
    "sg:address":"Hazel Farm Road, Totton",
    "sg:city":"Southampton",
    "sg:classifiers":[
        {
            "category":"Shopping",
            "subcategory":"Pharmacy",
            "type":"Retail Goods"
        }
    ],
    "sg:postcode":"SO40 8WU",
    "sg:province":"Hampshire",
    "sg:tags":[
        "pharmacist",
        "chemist"
    ],
    "wof:name":"A R Pharmacy",
    "wof:placetype":"venue"
},
  "geometry": {"coordinates":[-1.513814,50.91748],"type":"Point"}
}