{
  "type": "Feature",
  "properties": {
    "addr:full":"Pasture Lane Warrington Cheshire WA2 0PZ",
    "addr:postcode":"wa2 0pz",
    "addr:street":"Pasture Lane",
    "iso:country":"GB",
    "sg:address":"Pasture Lane",
    "sg:city":"Warrington",
    "sg:classifiers":[
        {
            "category":"Food & Beverages",
            "subcategory":"Groceries & Convenience Stores",
            "type":"Retail Goods"
        }
    ],
    "sg:phone":"+44 1925 492382",
    "sg:postcode":"WA2 0PZ",
    "sg:province":"Cheshire",
    "wof:name":"Nikita Superstore",
    "wof:placetype":"venue"
},
  "geometry": {"coordinates":[-2.5480389595,53.4093208313],"type":"Point"}
}