{
  "type": "Feature",
  "properties": {
    "iso:country":"GB",
    "sg:address":"5 Rangemoor Terrace, May Bank",
    "sg:city":"Newcastle",
    "sg:classifiers":[
        {
            "category":"Professional",
            "subcategory":"Engineering",
            "type":"Services"
        }
    ],
    "sg:postcode":"ST5 0PY",
    "sg:province":"Staffordshire",
    "sg:tags":[
        "contractor",
        "electrical",
        "engineer"
    ],
    "wof:name":"B P Property Services",
    "wof:placetype":"venue"
},
  "geometry": {"coordinates":[-2.2132658958,53.0239334106],"type":"Point"}
}