{
  "type": "Feature",
  "properties": {
    "addr:full":"44 Gray St, Broughty Ferry Dundee Angus DD5 2BJ",
    "addr:housenumber":"44",
    "addr:postcode":"dd5 2bj",
    "addr:street":"Gray St",
    "iso:country":"GB",
    "sg:address":"44 Gray St, Broughty Ferry",
    "sg:city":"Dundee",
    "sg:classifiers":[
        {
            "category":"Fast Food",
            "type":"Food & Drink"
        },
        {
            "category":"Restaurant",
            "type":"Food & Drink"
        }
    ],
    "sg:postcode":"DD5 2BJ",
    "sg:province":"Angus",
    "sg:tags":[
        "away",
        "indian",
        "take"
    ],
    "wof:name":"Dhiman,T,",
    "wof:placetype":"venue"
},
  "geometry": {"coordinates":[-2.8733329773,56.4661445618],"type":"Point"}
}