{
  "type": "Feature",
  "properties": {
    "addr:full":"26 Foxland Close Birmingham West Midlands B37 6TH",
    "addr:housenumber":"26",
    "addr:postcode":"b37 6th",
    "addr:street":"Foxland Close",
    "iso:country":"GB",
    "sg:address":"26 Foxland Close",
    "sg:city":"Birmingham",
    "sg:classifiers":[
        {
            "category":"Freight",
            "type":"Transportation"
        }
    ],
    "sg:phone":"+44 121 788 8009",
    "sg:postcode":"B37 6TH",
    "sg:province":"West Midlands",
    "sg:tags":[
        "haulage",
        "road"
    ],
    "wof:name":"Gary Douglas Williams",
    "wof:placetype":"venue"
},
  "geometry": {"coordinates":[-1.7237190008,52.480556488],"type":"Point"}
}