{
  "type": "Feature",
  "properties": {
    "addr:full":"41 Sherwood Avenue, Walderslade Chatham Kent ME5 9PP",
    "addr:housenumber":"41",
    "addr:postcode":"me5 9pp",
    "addr:street":"Sherwood Avenue",
    "iso:country":"GB",
    "sg:address":"41 Sherwood Avenue, Walderslade",
    "sg:city":"Chatham",
    "sg:classifiers":[
        {
            "category":"Retail",
            "subcategory":"Driving School",
            "type":"Services"
        }
    ],
    "sg:phone":"+44 1634 865381",
    "sg:postcode":"ME5 9PP",
    "sg:province":"Kent",
    "wof:name":"Francis School of Motoring",
    "wof:placetype":"venue"
},
  "geometry": {"coordinates":[0.5270220041,51.3361244202],"type":"Point"}
}