{
  "type": "Feature",
  "properties": {
    "addr:full":"43 Hillfield Park London Greater London N21 3QJ",
    "addr:housenumber":"43",
    "addr:postcode":"n21 3qj",
    "addr:street":"Hillfield Park",
    "iso:country":"GB",
    "sg:address":"43 Hillfield Park",
    "sg:city":"London",
    "sg:classifiers":[
        {
            "category":"Building & Trades",
            "subcategory":"Plumbing",
            "type":"Services"
        }
    ],
    "sg:phone":"+44 20 8886 4054",
    "sg:postcode":"N21 3QJ",
    "sg:province":"Greater London",
    "sg:tags":[
        "plumber",
        "heating"
    ],
    "wof:name":"George Woods",
    "wof:placetype":"venue"
},
  "geometry": {"coordinates":[-0.1077150032,51.6278953552],"type":"Point"}
}