{
  "type": "Feature",
  "properties": {
    "addr:full":"44 Home Park Road London Greater London SW19 7HN",
    "addr:housenumber":"44",
    "addr:postcode":"sw19 7hn",
    "addr:street":"Home Park Road",
    "iso:country":"GB",
    "sg:address":"44 Home Park Road",
    "sg:city":"London",
    "sg:classifiers":[
        {
            "category":"Travel",
            "subcategory":"Travel Agent",
            "type":"Entertainment"
        }
    ],
    "sg:phone":"+44 20 8241 2700",
    "sg:postcode":"SW19 7HN",
    "sg:province":"Greater London",
    "wof:name":"Beverley Neill Travel",
    "wof:placetype":"venue"
},
  "geometry": {"coordinates":[-0.1990430057,51.4330673218],"type":"Point"}
}