{
  "type": "Feature",
  "properties": {
    "iso:country":"GB",
    "sg:address":"46 Fore Street",
    "sg:city":"Budleigh Salterton",
    "sg:classifiers":[
        {
            "category":"Organizations",
            "subcategory":"Community Association",
            "type":"Services"
        },
        {
            "category":"Organizations",
            "subcategory":"Membership Organization",
            "type":"Services"
        }
    ],
    "sg:phone":"+44 1395 442015",
    "sg:postcode":"EX9 6NJ",
    "sg:province":"Devon",
    "sg:tags":[
        "club",
        "social"
    ],
    "wof:name":"Budleigh Salterton Club",
    "wof:placetype":"venue"
},
  "geometry": {"coordinates":[-3.322609,50.628937],"type":"Point"}
}