{
  "type": "Feature",
  "properties": {
    "iso:country":"GB",
    "sg:address":"Rochester Road",
    "sg:city":"Aylesford",
    "sg:classifiers":[
        {
            "category":"Home & Garden",
            "subcategory":"Garden Supply",
            "type":"Retail Goods"
        }
    ],
    "sg:phone":"+44 1622 715777",
    "sg:postcode":"ME20 7EB",
    "sg:province":"Kent",
    "sg:tags":[
        "nursery",
        "centre"
    ],
    "wof:name":"Rosies' Garden Plants",
    "wof:placetype":"venue"
},
  "geometry": {"coordinates":[0.489667,51.308815],"type":"Point"}
}