{
  "type": "Feature",
  "properties": {
    "iso:country":"GB",
    "sg:address":"Rowgate Upper Cumberworth",
    "sg:city":"Huddersfield",
    "sg:classifiers":[
        {
            "category":"Retail",
            "subcategory":"Auto Repair",
            "type":"Services"
        }
    ],
    "sg:postcode":"HD8 8XJ",
    "sg:province":"South Yorkshire",
    "sg:tags":[
        "modification",
        "garage"
    ],
    "wof:name":"Taylor,M A,",
    "wof:placetype":"venue"
},
  "geometry": {"coordinates":[-1.683989,53.575279],"type":"Point"}
}