{
  "type": "Feature",
  "properties": {
    "addr:full":"21 Westbourne Terrace Houghton-le-spring Durham DH4 4QT",
    "addr:housenumber":"21",
    "addr:postcode":"dh4 4qt",
    "addr:street":"Westbourne Terrace",
    "iso:country":"GB",
    "sg:address":"21 Westbourne Terrace",
    "sg:city":"Houghton-le-spring",
    "sg:classifiers":[
        {
            "category":"Personal",
            "subcategory":"Beauty Salon",
            "type":"Services"
        }
    ],
    "sg:postcode":"DH4 4QT",
    "sg:province":"Durham",
    "sg:tags":[
        "unisex",
        "hairdresser"
    ],
    "wof:name":"Phase 1",
    "wof:placetype":"venue"
},
  "geometry": {"coordinates":[-1.495399,54.866161],"type":"Point"}
}