{
  "type": "Feature",
  "properties": {
    "addr:full":"Fleming Road Liverpool Merseyside L24 9LN",
    "addr:postcode":"l24 9ln",
    "addr:street":"Fleming Road",
    "iso:country":"GB",
    "sg:address":"Fleming Road",
    "sg:city":"Liverpool",
    "sg:classifiers":[
        {
            "category":"Wholesale",
            "subcategory":"Chemicals & Plastics",
            "type":"Manufacturing & Wholesale Goods"
        }
    ],
    "sg:phone":"+44 151 486 3939",
    "sg:postcode":"L24 9LN",
    "sg:province":"Merseyside",
    "sg:tags":[
        "product",
        "allied"
    ],
    "wof:name":"Eli Lilly & Co. Ltd.",
    "wof:placetype":"venue"
},
  "geometry": {"coordinates":[-2.8528690338,53.3557090759],"type":"Point"}
}