{
  "type": "Feature",
  "properties": {
    "iso:country":"GB",
    "sg:address":"106-110 Leyland Rd, Penwortham",
    "sg:city":"Preston",
    "sg:classifiers":[
        {
            "category":"Retail",
            "subcategory":"Funeral Services",
            "type":"Services"
        }
    ],
    "sg:postcode":"PR1 9QJ",
    "sg:province":"Lancashire",
    "wof:name":"Livesey,F,",
    "wof:placetype":"venue"
},
  "geometry": {"coordinates":[-2.711735,53.745464],"type":"Point"}
}