{
  "type": "Feature",
  "properties": {
    "addr:full":"76 Elizabeth Street, Atherton Manchester Greater Manchester M46 9JN",
    "addr:housenumber":"76",
    "addr:postcode":"m46 9jn",
    "addr:street":"Elizabeth Street",
    "iso:country":"GB",
    "sg:address":"76 Elizabeth Street, Atherton",
    "sg:city":"Manchester",
    "sg:classifiers":[
        {
            "category":"Building & Trades",
            "subcategory":"Construction",
            "type":"Services"
        }
    ],
    "sg:phone":"+44 1942 886414",
    "sg:postcode":"M46 9JN",
    "sg:province":"Greater Manchester",
    "sg:tags":[
        "builder",
        "carpenter"
    ],
    "wof:name":"Asb Property Services",
    "wof:placetype":"venue"
},
  "geometry": {"coordinates":[-2.487208,53.526608],"type":"Point"}
}