{
  "type": "Feature",
  "properties": {
    "addr:full":"Moresby Industrial Estate, Moresby Parks Whitehaven Cumbria CA28 8YD",
    "addr:housenumber":"estate moresby",
    "addr:postcode":"ca28 8yd",
    "addr:street":"Moresby Industrial;Parks Whitehaven",
    "iso:country":"GB",
    "sg:address":"Moresby Industrial Estate, Moresby Parks",
    "sg:city":"Whitehaven",
    "sg:classifiers":[
        {
            "category":"Manufacturing",
            "subcategory":"Wood Products",
            "type":"Manufacturing & Wholesale Goods"
        }
    ],
    "sg:phone":"+44 1946 66444",
    "sg:postcode":"CA28 8YD",
    "sg:province":"Cumbria",
    "sg:tags":[
        "packaging",
        "crate",
        "pallets"
    ],
    "wof:name":"Rexam Medical Packaging Ltd.",
    "wof:placetype":"venue"
},
  "geometry": {"coordinates":[-3.5532488823,54.5620384216],"type":"Point"}
}