{
  "type": "Feature",
  "properties": {
    "iso:country":"GB",
    "sg:address":"119 Atholl Rd",
    "sg:city":"Pitlochry",
    "sg:classifiers":[
        {
            "category":"Food & Beverages",
            "subcategory":"Candy",
            "type":"Retail Goods"
        }
    ],
    "sg:postcode":"PH16 5AG",
    "sg:province":"Perth and Kinross",
    "sg:tags":[
        "confectioner"
    ],
    "wof:name":"Johnson,George,",
    "wof:placetype":"venue"
},
  "geometry": {"coordinates":[-3.7373480797,56.7038841248],"type":"Point"}
}