{
  "type": "Feature",
  "properties": {
    "addr:full":"34 High Street, Westbury On Trym Bristol City of Bristol BS9 3DZ",
    "addr:housenumber":"34",
    "addr:postcode":"bs9 3dz",
    "addr:street":"High Street",
    "iso:country":"GB",
    "sg:address":"34 High Street, Westbury On Trym",
    "sg:city":"Bristol",
    "sg:classifiers":[
        {
            "category":"Real Estate",
            "subcategory":"Developer",
            "type":"Services"
        }
    ],
    "sg:postcode":"BS9 3DZ",
    "sg:province":"City of Bristol",
    "sg:tags":[
        "property"
    ],
    "wof:name":"Braveline Ltd",
    "wof:placetype":"venue"
},
  "geometry": {"coordinates":[-2.618382,51.49419],"type":"Point"}
}