{
  "type": "Feature",
  "properties": {
    "iso:country":"GB",
    "sg:address":"Llangewydd Road",
    "sg:city":"Bridgend",
    "sg:classifiers":[
        {
            "category":"Education",
            "subcategory":"School",
            "type":"Public Place"
        },
        {
            "category":"Government",
            "subcategory":"Office",
            "type":"Public Place"
        }
    ],
    "sg:phone":"+44 1656 653348",
    "sg:postcode":"CF31 4JT",
    "sg:province":"Bridgend",
    "sg:tags":[
        "local",
        "authority"
    ],
    "wof:name":"Llangewydd Junior School",
    "wof:placetype":"venue"
},
  "geometry": {"coordinates":[-3.600358,51.511562],"type":"Point"}
}