{
  "type": "Feature",
  "properties": {
    "iso:country":"GB",
    "sg:address":"Unit 1, 94 Kitchener Road",
    "sg:city":"High Wycombe",
    "sg:classifiers":[
        {
            "category":"Professional",
            "subcategory":"Engineering",
            "type":"Services"
        }
    ],
    "sg:phone":"+44 1494 441220",
    "sg:postcode":"HP11 2SW",
    "sg:province":"Buckinghamshire",
    "sg:tags":[
        "precision",
        "engineer"
    ],
    "wof:name":"J F Engineering",
    "wof:placetype":"venue"
},
  "geometry": {"coordinates":[-0.766705,51.631405],"type":"Point"}
}