{
  "type": "Feature",
  "properties": {
    "iso:country":"GB",
    "sg:address":"42 Maple Avenue, Countesthorpe",
    "sg:city":"Leicester",
    "sg:classifiers":[
        {
            "category":"Building & Trades",
            "subcategory":"Construction",
            "type":"Services"
        }
    ],
    "sg:phone":"+44 116 277 9543",
    "sg:postcode":"LE8 5TZ",
    "sg:province":"Leicestershire",
    "sg:tags":[
        "dry",
        "plastering",
        "plasterers",
        "lining",
        "related",
        "screeders"
    ],
    "wof:name":"C A CUMBERLIDGE",
    "wof:placetype":"venue"
},
  "geometry": {"coordinates":[-1.139021,52.55571],"type":"Point"}
}