{
  "type": "Feature",
  "properties": {
    "iso:country":"GB",
    "sg:address":"Unit 1, Douglas St",
    "sg:city":"Dundee",
    "sg:classifiers":[
        {
            "category":"Wholesale",
            "subcategory":"Scrap",
            "type":"Manufacturing & Wholesale Goods"
        }
    ],
    "sg:phone":"+44 1382 201511",
    "sg:postcode":"DD1 5AZ",
    "sg:province":"Dundee City",
    "sg:tags":[
        "waste",
        "metal"
    ],
    "wof:name":"Mr G's Factory Clearance",
    "wof:placetype":"venue"
},
  "geometry": {"coordinates":[-2.9811348915,56.4633216858],"type":"Point"}
}