{
  "type": "Feature",
  "properties": {
    "iso:country":"GB",
    "sg:address":"2 Spencer Street",
    "sg:city":"Leamington Spa",
    "sg:classifiers":[
        {
            "category":"Bars & Pubs",
            "subcategory":"Nightclub",
            "type":"Food & Drink"
        }
    ],
    "sg:phone":"+44 1926 435310",
    "sg:postcode":"CV31 3NF",
    "sg:province":"Warwickshire",
    "sg:tags":[
        "club",
        "night",
        "activity"
    ],
    "wof:name":"Tomarra Ltd",
    "wof:placetype":"venue"
},
  "geometry": {"coordinates":[-1.534478,52.285477],"type":"Point"}
}