{
  "type": "Feature",
  "properties": {
    "addr:full":"9 York Street Ayr South Ayrshire KA8 8AN",
    "addr:housenumber":"9",
    "addr:postcode":"ka8 8an",
    "addr:street":"York Street",
    "iso:country":"GB",
    "sg:address":"9 York Street",
    "sg:city":"Ayr",
    "sg:classifiers":[
        {
            "category":"Manufacturing",
            "subcategory":"Metals",
            "type":"Manufacturing & Wholesale Goods"
        }
    ],
    "sg:phone":"+44 1292 289620",
    "sg:postcode":"KA8 8AN",
    "sg:province":"South Ayrshire",
    "sg:tags":[
        "steel",
        "fabricator",
        "erectors"
    ],
    "wof:name":"Newton Fabrications Ltd",
    "wof:placetype":"venue"
},
  "geometry": {"coordinates":[-4.635144,55.468204],"type":"Point"}
}