{
  "type": "Feature",
  "properties": {
    "iso:country":"GB",
    "sg:address":"57 Cranford Avenue, Stanwell",
    "sg:city":"Staines",
    "sg:classifiers":[
        {
            "category":"Building & Trades",
            "subcategory":"Cleaning & Sanitation",
            "type":"Services"
        }
    ],
    "sg:postcode":"TW19 7AQ",
    "sg:province":"Berkshire",
    "sg:tags":[
        "commercial"
    ],
    "wof:name":"Alpha Maintenance & Cleaning Services",
    "wof:placetype":"venue"
},
  "geometry": {"coordinates":[-0.4696240127,51.4512138367],"type":"Point"}
}