{
  "type": "Feature",
  "properties": {
    "addr:full":"6 Maple Road, Bramhall Stockport Cheshire SK7 2DH",
    "addr:housenumber":"6",
    "addr:postcode":"sk7 2dh",
    "addr:street":"Maple Road",
    "iso:country":"GB",
    "sg:address":"6 Maple Road, Bramhall",
    "sg:city":"Stockport",
    "sg:classifiers":[
        {
            "category":"Professional",
            "type":"Services"
        }
    ],
    "sg:phone":"+44 161 439 2197",
    "sg:postcode":"SK7 2DH",
    "sg:province":"Cheshire",
    "sg:tags":[
        "interior",
        "furnishers",
        "designer"
    ],
    "wof:name":"Gail Marsden Interior Design",
    "wof:placetype":"venue"
},
  "geometry": {"coordinates":[-2.1647040844,53.3573112488],"type":"Point"}
}