{
  "type": "Feature",
  "properties": {
    "addr:full":"21 Broad Street Newent Gloucestershire GL18 1AQ",
    "addr:housenumber":"21",
    "addr:postcode":"gl18 1aq",
    "addr:street":"Broad Street",
    "iso:country":"GB",
    "sg:address":"21 Broad Street",
    "sg:city":"Newent",
    "sg:classifiers":[
        {
            "category":"Food & Beverages",
            "subcategory":"Fruits & Vegetables",
            "type":"Retail Goods"
        }
    ],
    "sg:phone":"+44 1531 820459",
    "sg:postcode":"GL18 1AQ",
    "sg:province":"Gloucestershire",
    "sg:tags":[
        "greengrocer"
    ],
    "wof:name":"Pippins",
    "wof:placetype":"venue"
},
  "geometry": {"coordinates":[-2.4050679207,51.9304885864],"type":"Point"}
}