{
  "type": "Feature",
  "properties": {
    "addr:full":"Green Briars, Western Road Crowborough East Sussex TN6 3HA",
    "addr:postcode":"tn6 3ha",
    "addr:street":"Western Road",
    "iso:country":"GB",
    "sg:address":"Green Briars, Western Road",
    "sg:city":"Crowborough",
    "sg:classifiers":[
        {
            "category":"Building & Trades",
            "subcategory":"Landscaping Services",
            "type":"Services"
        }
    ],
    "sg:phone":"+44 1892 653063",
    "sg:postcode":"TN6 3HA",
    "sg:province":"East Sussex",
    "sg:tags":[
        "landscape",
        "contractor"
    ],
    "wof:name":"D C Monger",
    "wof:placetype":"venue"
},
  "geometry": {"coordinates":[0.171893,51.053196],"type":"Point"}
}