{
  "type": "Feature",
  "properties": {
    "addr:full":"St Heliers, Cottingley Bar Bingley West Yorkshire BD16 1PA",
    "addr:postcode":"bd16 1pa",
    "addr:street":"West",
    "iso:country":"GB",
    "sg:address":"St Heliers, Cottingley Bar",
    "sg:city":"Bingley",
    "sg:classifiers":[
        {
            "category":"Professional",
            "subcategory":"Business Services",
            "type":"Services"
        }
    ],
    "sg:phone":"+44 1274 562624",
    "sg:postcode":"BD16 1PA",
    "sg:province":"West Yorkshire",
    "sg:tags":[
        "import",
        "export",
        "agent"
    ],
    "wof:name":"Moorhouse Wools Ltd.",
    "wof:placetype":"venue"
},
  "geometry": {"coordinates":[-1.8254740238,53.8349952698],"type":"Point"}
}