{
  "type": "Feature",
  "properties": {
    "iso:country":"GB",
    "sg:address":"Mcmillan Road, Alderstone Business Park",
    "sg:city":"Livingston",
    "sg:classifiers":[
        {
            "category":"Professional",
            "subcategory":"Computer Services",
            "type":"Services"
        }
    ],
    "sg:phone":"+44 1506 412222",
    "sg:postcode":"EH54 7DF",
    "sg:province":"West Lothian",
    "sg:tags":[
        "system",
        "software"
    ],
    "wof:name":"Mentor Graphics U K",
    "wof:placetype":"venue"
},
  "geometry": {"coordinates":[-3.529335,55.881573],"type":"Point"}
}