{
  "type": "Feature",
  "properties": {
    "addr:full":"89 Oldfield Circus Northolt Greater London UB5 4RU",
    "addr:housenumber":"89",
    "addr:postcode":"ub5 4ru",
    "addr:street":"Oldfield Circus",
    "iso:country":"GB",
    "sg:address":"89 Oldfield Circus",
    "sg:city":"Northolt",
    "sg:classifiers":[
        {
            "category":"Real Estate",
            "subcategory":"Real Estate Agent",
            "type":"Services"
        }
    ],
    "sg:phone":"+44 20 8422 7181",
    "sg:postcode":"UB5 4RU",
    "sg:province":"Greater London",
    "wof:name":"Bairstow Eves",
    "wof:placetype":"venue"
},
  "geometry": {"coordinates":[-0.3505240083,51.5524291992],"type":"Point"}
}