{
  "type": "Feature",
  "properties": {
    "addr:full":"Goose Lane, Horton Ilminster Somerset TA19 9QQ",
    "addr:postcode":"ta19 9qq",
    "addr:street":"Goose Lane",
    "iso:country":"GB",
    "sg:address":"Goose Lane, Horton",
    "sg:city":"Ilminster",
    "sg:classifiers":[
        {
            "category":"Government",
            "subcategory":"Post Office",
            "type":"Public Place"
        }
    ],
    "sg:phone":"+44 1460 52684",
    "sg:postcode":"TA19 9QQ",
    "sg:province":"Somerset",
    "wof:name":"Horton Post Office and General Store",
    "wof:placetype":"venue"
},
  "geometry": {"coordinates":[-2.9175300598,50.9286689758],"type":"Point"}
}