{
  "type": "Feature",
  "properties": {
    "iso:country":"GB",
    "sg:address":"63 High Street",
    "sg:city":"Walton-on-the-naze",
    "sg:classifiers":[
        {
            "category":"Shopping",
            "subcategory":"News",
            "type":"Retail Goods"
        }
    ],
    "sg:phone":"+44 1255 675585",
    "sg:postcode":"CO14 8AB",
    "sg:province":"Essex",
    "sg:tags":[
        "newsagent"
    ],
    "wof:name":"LESLEY & BRIAN JOHNSON",
    "wof:placetype":"venue"
},
  "geometry": {"coordinates":[1.270797,51.848934],"type":"Point"}
}