{
  "type": "Feature",
  "properties": {
    "iso:country":"GB",
    "sg:address":"3 Springvale Ho, Millfields Rd",
    "sg:city":"Bilston",
    "sg:classifiers":[
        {
            "category":"Organizations",
            "subcategory":"Professional Association",
            "type":"Services"
        }
    ],
    "sg:phone":"+44 1902 405701",
    "sg:postcode":"WV14 0QJ",
    "sg:province":"West Midlands",
    "sg:tags":[
        "union",
        "trade"
    ],
    "wof:name":"General Municipal Boiler Makers & Allied Trades Union",
    "wof:placetype":"venue"
},
  "geometry": {"coordinates":[-2.07449,52.566635],"type":"Point"}
}