{
  "type": "Feature",
  "properties": {
    "iso:country":"GB",
    "sg:address":"8 Church Rd",
    "sg:city":"Hove",
    "sg:classifiers":[
        {
            "category":"Fast Food",
            "type":"Food & Drink"
        }
    ],
    "sg:postcode":"BN3 2FL",
    "sg:province":"East Sussex",
    "sg:tags":[
        "away",
        "take"
    ],
    "wof:name":"Frascati",
    "wof:placetype":"venue"
},
  "geometry": {"coordinates":[-0.1655430049,50.8270683289],"type":"Point"}
}