{
  "type": "Feature",
  "properties": {
    "iso:country":"GB",
    "sg:address":"26 Sunningdale Road",
    "sg:city":"Yeovil",
    "sg:classifiers":[
        {
            "category":"Building & Trades",
            "subcategory":"Plumbing",
            "type":"Services"
        }
    ],
    "sg:phone":"+44 1935 425108",
    "sg:postcode":"BA21 5LX",
    "sg:province":"Somerset",
    "sg:tags":[
        "plumber",
        "heating"
    ],
    "wof:name":"K R WADDLETON",
    "wof:placetype":"venue"
},
  "geometry": {"coordinates":[-2.620620966,50.9510269165],"type":"Point"}
}