{
  "type": "Feature",
  "properties": {
    "iso:country":"GB",
    "sg:address":"197 Foundry Lane",
    "sg:city":"Southampton",
    "sg:classifiers":[
        {
            "category":"Personal",
            "subcategory":"Beauty Salon",
            "type":"Services"
        }
    ],
    "sg:phone":"+44 23 8077 3290",
    "sg:postcode":"SO15 3JY",
    "sg:province":"Hampshire",
    "sg:tags":[
        "lady",
        "hairdresser"
    ],
    "wof:name":"Jenny's Hair Shop",
    "wof:placetype":"venue"
},
  "geometry": {"coordinates":[-1.432894,50.917507],"type":"Point"}
}