{
  "type": "Feature",
  "properties": {
    "addr:full":"Unit 2a Ramsden Road, Rotherwas Industrial Estate Hereford Herefordshire HR2 6NP",
    "addr:housenumber":"unit 2a;estate",
    "addr:postcode":"hr2 6np",
    "addr:street":"Ramsden Road Rotherwas Industrial",
    "iso:country":"GB",
    "sg:address":"Unit 2a Ramsden Road, Rotherwas Industrial Estate",
    "sg:city":"Hereford",
    "sg:classifiers":[
        {
            "category":"Structure",
            "subcategory":"Warehouse",
            "type":"Public Place"
        }
    ],
    "sg:phone":"+44 1432 358428",
    "sg:postcode":"HR2 6NP",
    "sg:province":"Herefordshire",
    "wof:name":"Tomhead Ltd.",
    "wof:placetype":"venue"
},
  "geometry": {"coordinates":[-2.678339,52.036926],"type":"Point"}
}