{
  "type": "Feature",
  "properties": {
    "iso:country":"GB",
    "sg:address":"Colleagues House, 130 - 132 Wells Road",
    "sg:city":"Bath",
    "sg:classifiers":[
        {
            "category":"Real Estate",
            "subcategory":"Real Estate Operator",
            "type":"Services"
        }
    ],
    "sg:phone":"+44 1225 827100",
    "sg:postcode":"BA2 3AH",
    "sg:province":"Somerset",
    "sg:tags":[
        "letting",
        "agent"
    ],
    "wof:name":"Direct Let Ltd.",
    "wof:placetype":"venue"
},
  "geometry": {"coordinates":[-2.3673870564,51.3741149902],"type":"Point"}
}