{
  "type": "Feature",
  "properties": {
    "iso:country":"GB",
    "sg:address":"13 Northweald Lane",
    "sg:city":"Kingston Upon Thames",
    "sg:classifiers":[
        {
            "category":"Shopping",
            "subcategory":"Pharmacy",
            "type":"Retail Goods"
        }
    ],
    "sg:phone":"+44 20 8288 7647",
    "sg:postcode":"KT2 5GL",
    "sg:province":"Greater London",
    "sg:tags":[
        "medicine",
        "therapy"
    ],
    "wof:name":"Richard's Visiting TherapeuticMassage",
    "wof:placetype":"venue"
},
  "geometry": {"coordinates":[-0.310957998,51.4296340942],"type":"Point"}
}