{
  "type": "Feature",
  "properties": {
    "addr:full":"85 Joel Street Northwood Greater London HA6 1LU",
    "addr:housenumber":"85",
    "addr:postcode":"ha6 1lu",
    "addr:street":"Joel Street",
    "iso:country":"GB",
    "sg:address":"85 Joel Street",
    "sg:city":"Northwood",
    "sg:classifiers":[
        {
            "category":"Health Services",
            "subcategory":"Optometrist",
            "type":"Services"
        }
    ],
    "sg:phone":"+44 1923 823027",
    "sg:postcode":"HA6 1LU",
    "sg:province":"Greater London",
    "sg:tags":[
        "optician"
    ],
    "wof:name":"S H Harrold (1937) Ltd.",
    "wof:placetype":"venue"
},
  "geometry": {"coordinates":[-0.409556,51.599876],"type":"Point"}
}