{
  "type": "Feature",
  "properties": {
    "addr:full":"Market End, Coggeshall Colchester Essex CO6 1TP",
    "addr:postcode":"co6 1tp",
    "iso:country":"GB",
    "sg:address":"Market End, Coggeshall",
    "sg:city":"Colchester",
    "sg:classifiers":[
        {
            "category":"Government",
            "subcategory":"Post Office",
            "type":"Public Place"
        }
    ],
    "sg:phone":"+44 1376 561232",
    "sg:postcode":"CO6 1TP",
    "sg:province":"Essex",
    "wof:name":"Coggeshall Post Office & Newsagent",
    "wof:placetype":"venue"
},
  "geometry": {"coordinates":[0.6910380125,51.8712997437],"type":"Point"}
}