{
  "type": "Feature",
  "properties": {
    "addr:full":"The Old Cafe Clacton-on-sea Essex CO16 8ES",
    "addr:postcode":"co16 8es",
    "iso:country":"GB",
    "sg:address":"The Old Cafe",
    "sg:city":"Clacton-on-sea",
    "sg:classifiers":[
        {
            "category":"Home & Garden",
            "subcategory":"Home Furnishings",
            "type":"Retail Goods"
        }
    ],
    "sg:postcode":"CO16 8ES",
    "sg:province":"Essex",
    "sg:tags":[
        "racking",
        "shelving",
        "diy"
    ],
    "wof:name":"A P Haynes",
    "wof:placetype":"venue"
},
  "geometry": {"coordinates":[1.0549099445,51.7886505127],"type":"Point"}
}