{
  "type": "Feature",
  "properties": {
    "addr:full":"866 Uxbridge Rd Hayes Greater London UB4 0RS",
    "addr:housenumber":"866",
    "addr:postcode":"ub4 0rs",
    "addr:street":"Uxbridge Rd",
    "iso:country":"GB",
    "sg:address":"866 Uxbridge Rd",
    "sg:city":"Hayes",
    "sg:classifiers":[
        {
            "category":"Communications",
            "type":"Services"
        }
    ],
    "sg:postcode":"UB4 0RS",
    "sg:province":"Greater London",
    "sg:tags":[
        "data",
        "network"
    ],
    "wof:name":"Zircon Communications Ltd",
    "wof:placetype":"venue"
},
  "geometry": {"coordinates":[-0.415369,51.520592],"type":"Point"}
}