{
  "type": "Feature",
  "properties": {
    "addr:full":"7 Victoria Arcade, 189 Victoria St Westminster Greater London SW1E 5NE",
    "addr:housenumber":"7;189",
    "addr:postcode":"sw1e 5ne",
    "addr:street":"Victoria;Victoria St",
    "iso:country":"GB",
    "sg:address":"7 Victoria Arcade, 189 Victoria St",
    "sg:city":"Westminster",
    "sg:classifiers":[
        {
            "category":"Travel",
            "subcategory":"Travel Agent",
            "type":"Entertainment"
        }
    ],
    "sg:phone":"+44 20 7924 5561",
    "sg:postcode":"SW1E 5NE",
    "sg:province":"Greater London",
    "sg:tags":[
        "hotel",
        "agency",
        "booking"
    ],
    "wof:name":"London Tourist Hotel Reservation Service",
    "wof:placetype":"venue"
},
  "geometry": {"coordinates":[-0.1442700028,51.4966201782],"type":"Point"}
}