{
  "type": "Feature",
  "properties": {
    "iso:country":"GB",
    "sg:address":"Angelton Hall",
    "sg:city":"Bridgend",
    "sg:classifiers":[
        {
            "category":"Social Services",
            "subcategory":"Job Training",
            "type":"Services"
        }
    ],
    "sg:phone":"+44 1656 646318",
    "sg:postcode":"CF31 4LL",
    "sg:province":"Bridgend",
    "wof:name":"The Payroll Training Co. Ltd.",
    "wof:placetype":"venue"
},
  "geometry": {"coordinates":[-3.590984,51.528069],"type":"Point"}
}