{
  "type": "Feature",
  "properties": {
    "addr:full":"110 Coast Road, West Mersea Colchester Essex CO5 8NA",
    "addr:housenumber":"110",
    "addr:postcode":"co5 8na",
    "addr:street":"Coast Road West;Colchester",
    "iso:country":"GB",
    "sg:address":"110 Coast Road, West Mersea",
    "sg:city":"Colchester",
    "sg:classifiers":[
        {
            "category":"Professional",
            "type":"Services"
        }
    ],
    "sg:phone":"+44 1206 384032",
    "sg:postcode":"CO5 8NA",
    "sg:province":"Essex",
    "sg:tags":[
        "marine"
    ],
    "wof:name":"David Royce",
    "wof:placetype":"venue"
},
  "geometry": {"coordinates":[0.8991280198,51.7784385681],"type":"Point"}
}