{
  "type": "Feature",
  "properties": {
    "addr:full":"91 Kilburn High Road London Greater London NW6 6JE",
    "addr:housenumber":"91",
    "addr:postcode":"nw6 6je",
    "addr:street":"Kilburn High Road",
    "iso:country":"GB",
    "sg:address":"91 Kilburn High Road",
    "sg:city":"London",
    "sg:classifiers":[
        {
            "category":"Retail",
            "subcategory":"Laundry & Dry Cleaning",
            "type":"Services"
        },
        {
            "category":"Manufacturing",
            "subcategory":"Textiles",
            "type":"Manufacturing & Wholesale Goods"
        }
    ],
    "sg:phone":"+44 20 7328 4131",
    "sg:postcode":"NW6 6JE",
    "sg:province":"Greater London",
    "sg:tags":[
        "dyer",
        "alteration"
    ],
    "wof:name":"Swan Clothes & Leather Dyers",
    "wof:placetype":"venue"
},
  "geometry": {"coordinates":[-0.193737,51.538509],"type":"Point"}
}