{
  "type": "Feature",
  "properties": {
    "addr:full":"Unit 1 Tipton Trading Estate, Bloomfield Road, Bloomfield Tipton West Midlands DY4 9AH",
    "addr:housenumber":"unit 1",
    "addr:postcode":"dy4 9ah",
    "addr:street":"Trading;Bloomfield Road",
    "iso:country":"GB",
    "sg:address":"Unit 1 Tipton Trading Estate, Bloomfield Road, Bloomfield",
    "sg:city":"Tipton",
    "sg:classifiers":[
        {
            "category":"Professional",
            "subcategory":"Engineering",
            "type":"Services"
        }
    ],
    "sg:phone":"+44 121 520 7313",
    "sg:postcode":"DY4 9AH",
    "sg:province":"West Midlands",
    "wof:name":"Abec Group of Companies",
    "wof:placetype":"venue"
},
  "geometry": {"coordinates":[-2.0740389824,52.5348243713],"type":"Point"}
}