{
  "type": "Feature",
  "properties": {
    "addr:full":"Community Development Team, West Park Wolverhampton Staffordshire WV3 9BH",
    "addr:postcode":"wv3 9bh",
    "iso:country":"GB",
    "sg:address":"Community Development Team, West Park",
    "sg:city":"Wolverhampton",
    "sg:classifiers":[
        {
            "category":"Government",
            "subcategory":"Office",
            "type":"Public Place"
        }
    ],
    "sg:phone":"+44 1902 552182",
    "sg:postcode":"WV3 9BH",
    "sg:province":"Staffordshire",
    "sg:tags":[
        "local"
    ],
    "wof:name":"Wolverhampton Borough Council",
    "wof:placetype":"venue"
},
  "geometry": {"coordinates":[-2.1517500877,52.5801391602],"type":"Point"}
}