{
  "type": "Feature",
  "properties": {
    "iso:country":"GB",
    "sg:address":"81 Berkeley Ave",
    "sg:city":"Greenford",
    "sg:classifiers":[
        {
            "category":"Professional",
            "subcategory":"Management & Consulting",
            "type":"Services"
        }
    ],
    "sg:phone":"+44 20 7223 4846",
    "sg:postcode":"UB6 0NZ",
    "sg:province":"Greater London",
    "sg:tags":[
        "consultant",
        "business"
    ],
    "wof:name":"Blue Space Consulting Ltd",
    "wof:placetype":"venue"
},
  "geometry": {"coordinates":[-0.3355929852,51.5480766296],"type":"Point"}
}