{
  "type": "Feature",
  "properties": {
    "iso:country":"GB",
    "sg:address":"Dodington Hall West Wing",
    "sg:city":"Bridgwater",
    "sg:classifiers":[
        {
            "category":"Education",
            "subcategory":"Music School",
            "type":"Public Place"
        },
        {
            "category":"Building & Trades",
            "subcategory":"Construction",
            "type":"Services"
        }
    ],
    "sg:phone":"+44 1278 741400",
    "sg:postcode":"TA5 1LF",
    "sg:province":"Somerset",
    "sg:tags":[
        "conservatory",
        "builder"
    ],
    "wof:name":"St Cuthbert Conservation",
    "wof:placetype":"venue"
},
  "geometry": {"coordinates":[-3.1775,51.161629],"type":"Point"}
}