{
  "type": "Feature",
  "properties": {
    "iso:country":"GB",
    "sg:address":"Kemp House, Brunel Road, Earlstrees Industrial Estate",
    "sg:city":"Corby",
    "sg:classifiers":[
        {
            "category":"Manufacturing",
            "subcategory":"Metals",
            "type":"Manufacturing & Wholesale Goods"
        }
    ],
    "sg:postcode":"NN17 4AU",
    "sg:province":"Northamptonshire",
    "sg:tags":[
        "steel",
        "fabricator",
        "erectors"
    ],
    "wof:name":"Mayfield Fabrications",
    "wof:placetype":"venue"
},
  "geometry": {"coordinates":[-0.685317,52.508751],"type":"Point"}
}