{
  "type": "Feature",
  "properties": {
    "iso:country":"GB",
    "sg:address":"1 Doughty St",
    "sg:city":"London",
    "sg:classifiers":[
        {
            "category":"Real Estate",
            "subcategory":"Architect",
            "type":"Services"
        }
    ],
    "sg:postcode":"WC1N 2PH",
    "sg:province":"Greater London",
    "wof:name":"Burleigh & Co",
    "wof:placetype":"venue"
},
  "geometry": {"coordinates":[-0.116202,51.522896],"type":"Point"}
}