{
  "type": "Feature",
  "properties": {
    "iso:country":"GB",
    "sg:address":"21 Skipton Street",
    "sg:city":"Morecambe",
    "sg:classifiers":[
        {
            "category":"Travel",
            "subcategory":"Hotels & Motels",
            "type":"Entertainment"
        }
    ],
    "sg:postcode":"LA4 4AR",
    "sg:province":"Lancashire",
    "wof:name":"Kentdale Hotel",
    "wof:placetype":"venue"
},
  "geometry": {"coordinates":[-2.868735,54.071938],"type":"Point"}
}