{
  "type": "Feature",
  "properties": {
    "iso:country":"GB",
    "sg:address":"77 High Street",
    "sg:city":"Lewes",
    "sg:classifiers":[
        {
            "category":"Insurance",
            "subcategory":"Insurance Agent",
            "type":"Services"
        }
    ],
    "sg:phone":"+44 1273 402800",
    "sg:postcode":"BN7 1XN",
    "sg:province":"East Sussex",
    "sg:tags":[
        "broker"
    ],
    "wof:name":"Guild of Master Craftsmen",
    "wof:placetype":"venue"
},
  "geometry": {"coordinates":[0.0082,50.8722953796],"type":"Point"}
}