{
  "type": "Feature",
  "properties": {
    "addr:full":"London Rd, Bassetts Pole Sutton Coldfield Staffordshire B75 5SA",
    "addr:postcode":"b75 5sa",
    "addr:street":"London Rd",
    "iso:country":"GB",
    "sg:address":"London Rd, Bassetts Pole",
    "sg:city":"Sutton Coldfield",
    "sg:classifiers":[
        {
            "category":"Restaurant",
            "type":"Food & Drink"
        }
    ],
    "sg:postcode":"B75 5SA",
    "sg:province":"Staffordshire",
    "wof:name":"Chicanes",
    "wof:placetype":"venue"
},
  "geometry": {"coordinates":[-1.7901389599,52.595539093],"type":"Point"}
}