{
  "type": "Feature",
  "properties": {
    "iso:country":"GB",
    "sg:address":"Broadway",
    "sg:city":"Barnsley",
    "sg:classifiers":[
        {
            "category":"Professional",
            "subcategory":"Business Services",
            "type":"Services"
        }
    ],
    "sg:phone":"+44 1226 779050",
    "sg:postcode":"S70 6RA",
    "sg:province":"South Yorkshire",
    "sg:tags":[
        "distribution"
    ],
    "wof:name":"Wincanton",
    "wof:placetype":"venue"
},
  "geometry": {"coordinates":[-1.5081390142,53.5509147644],"type":"Point"}
}