{
  "type": "Feature",
  "properties": {
    "addr:full":"9 Montrose Close, Marton Middlesbrough North Yorkshire TS7 8LA",
    "addr:housenumber":"9",
    "addr:postcode":"ts7 8la",
    "addr:street":"Montrose Close",
    "iso:country":"GB",
    "sg:address":"9 Montrose Close, Marton",
    "sg:city":"Middlesbrough",
    "sg:classifiers":[
        {
            "category":"Building & Trades",
            "subcategory":"Construction",
            "type":"Services"
        }
    ],
    "sg:postcode":"TS7 8LA",
    "sg:province":"North Yorkshire",
    "sg:tags":[
        "decorator",
        "painter"
    ],
    "wof:name":"William E Millen",
    "wof:placetype":"venue"
},
  "geometry": {"coordinates":[-1.209975,54.529095],"type":"Point"}
}