{
  "type": "Feature",
  "properties": {
    "addr:full":"Brunel Walk Blackburn Lancashire BB1 1HN",
    "addr:postcode":"bb1 1hn",
    "addr:street":"Brunel Walk",
    "iso:country":"GB",
    "sg:address":"Brunel Walk",
    "sg:city":"Blackburn",
    "sg:classifiers":[
        {
            "category":"Farming",
            "subcategory":"Nursery",
            "type":"Manufacturing & Wholesale Goods"
        }
    ],
    "sg:phone":"+44 1254 265433",
    "sg:postcode":"BB1 1HN",
    "sg:province":"Lancashire",
    "sg:tags":[
        "creche"
    ],
    "wof:name":"Brunel Nursery School",
    "wof:placetype":"venue"
},
  "geometry": {"coordinates":[-2.4722540379,53.7454185486],"type":"Point"}
}