{
  "type": "Feature",
  "properties": {
    "addr:full":"20 College St Burnham On Sea Somerset TA8 1AS",
    "addr:housenumber":"20",
    "addr:postcode":"ta8 1as",
    "addr:street":"College St",
    "iso:country":"GB",
    "sg:address":"20 College St",
    "sg:city":"Burnham On Sea",
    "sg:classifiers":[
        {
            "category":"Communications",
            "subcategory":"Newspaper",
            "type":"Services"
        }
    ],
    "sg:phone":"+44 1278 780333",
    "sg:postcode":"TA8 1AS",
    "sg:province":"Somerset",
    "sg:tags":[
        "magazine"
    ],
    "wof:name":"Burnham & Highbridge Weekly News",
    "wof:placetype":"venue"
},
  "geometry": {"coordinates":[-2.996562,51.237064],"type":"Point"}
}