{
  "type": "Feature",
  "properties": {
    "addr:full":"Wincomblee Rd Newcastle-upon-tyne Tyne and Wear NE6 3PL",
    "addr:postcode":"ne6 3pl",
    "addr:street":"Wincomblee Rd",
    "iso:country":"GB",
    "sg:address":"Wincomblee Rd",
    "sg:city":"Newcastle-upon-tyne",
    "sg:classifiers":[
        {
            "category":"Wholesale",
            "subcategory":"Chemicals & Plastics",
            "type":"Manufacturing & Wholesale Goods"
        }
    ],
    "sg:postcode":"NE6 3PL",
    "sg:province":"Tyne and Wear",
    "sg:tags":[
        "retail",
        "freezer",
        "refrigerator"
    ],
    "wof:name":"Black,Lesley,",
    "wof:placetype":"venue"
},
  "geometry": {"coordinates":[-1.539139986,54.9706687927],"type":"Point"}
}