{
  "type": "Feature",
  "properties": {
    "addr:full":"134 Buckingham Palace Rd London Greater London SW1W 9SA",
    "addr:housenumber":"134",
    "addr:postcode":"sw1w 9sa",
    "addr:street":"Buckingham Palace Rd",
    "iso:country":"GB",
    "sg:address":"134 Buckingham Palace Rd",
    "sg:city":"London",
    "sg:classifiers":[
        {
            "category":"Organizations",
            "subcategory":"Non-profit Organization",
            "type":"Services"
        }
    ],
    "sg:postcode":"SW1W 9SA",
    "sg:province":"Greater London",
    "sg:tags":[
        "organisation",
        "voluntary",
        "charity"
    ],
    "wof:name":"Befriend A Family",
    "wof:placetype":"venue"
},
  "geometry": {"coordinates":[-0.1473080069,51.4934272766],"type":"Point"}
}