{
  "type": "Feature",
  "properties": {
    "addr:full":"Unit 3 Bridge Street Indust Est Uttoxeter Derbyshire ST14 8SP",
    "addr:housenumber":"unit 3",
    "addr:postcode":"st14 8sp",
    "addr:street":"Bridge Street",
    "iso:country":"GB",
    "sg:address":"Unit 3 Bridge Street Indust Est",
    "sg:city":"Uttoxeter",
    "sg:classifiers":[
        {
            "category":"Shopping",
            "subcategory":"Computers & Home Electronics",
            "type":"Retail Goods"
        }
    ],
    "sg:phone":"+44 1889 567516",
    "sg:postcode":"ST14 8SP",
    "sg:province":"Derbyshire",
    "sg:tags":[
        "electrical"
    ],
    "wof:name":"Truscott Industrial Supplies Ltd",
    "wof:placetype":"venue"
},
  "geometry": {"coordinates":[-1.863584,52.896412],"type":"Point"}
}