{
  "type": "Feature",
  "properties": {
    "addr:full":"5 Ryton Street Worksop Nottinghamshire S80 2AY",
    "addr:housenumber":"5",
    "addr:postcode":"s80 2ay",
    "addr:street":"Ryton Street",
    "iso:country":"GB",
    "sg:address":"5 Ryton Street",
    "sg:city":"Worksop",
    "sg:classifiers":[
        {
            "category":"Shopping",
            "subcategory":"Clothing, Apparel, & Fashions",
            "type":"Retail Goods"
        }
    ],
    "sg:phone":"+44 1909 531459",
    "sg:postcode":"S80 2AY",
    "sg:province":"Nottinghamshire",
    "sg:tags":[
        "menswear"
    ],
    "wof:name":"Henleys for Men",
    "wof:placetype":"venue"
},
  "geometry": {"coordinates":[-1.123972,53.304863],"type":"Point"}
}