{
  "type": "Feature",
  "properties": {
    "addr:full":"Southwood House, Pond Lane Newbury Berkshire RG18 9RW",
    "addr:postcode":"rg18 9rw",
    "addr:street":"Pond Lane",
    "iso:country":"GB",
    "sg:address":"Southwood House, Pond Lane",
    "sg:city":"Newbury",
    "sg:classifiers":[
        {
            "category":"Professional",
            "subcategory":"Employment Agencies",
            "type":"Services"
        }
    ],
    "sg:phone":"+44 1635 202648",
    "sg:postcode":"RG18 9RW",
    "sg:province":"Berkshire",
    "sg:tags":[
        "consultant"
    ],
    "wof:name":"Numerate Personnel",
    "wof:placetype":"venue"
},
  "geometry": {"coordinates":[-1.3431529999,51.3846893311],"type":"Point"}
}