{
  "type": "Feature",
  "properties": {
    "iso:country":"GB",
    "sg:address":"Arts Project, Unit 33m, Vauxhall Industrial Estate",
    "sg:city":"Stockport",
    "sg:classifiers":[
        {
            "category":"Organizations",
            "subcategory":"Non-profit Organization",
            "type":"Services"
        }
    ],
    "sg:postcode":"SK5 7BR",
    "sg:province":"Cheshire",
    "sg:tags":[
        "organisation",
        "voluntary",
        "charity"
    ],
    "wof:name":"Mind Arts Project in Stockport",
    "wof:placetype":"venue"
},
  "geometry": {"coordinates":[-2.15801,53.424061],"type":"Point"}
}