{
  "type": "Feature",
  "properties": {
    "addr:full":"8 Richlands Avenue Epsom Surrey KT17 2JW",
    "addr:housenumber":"8",
    "addr:postcode":"kt17 2jw",
    "addr:street":"Richlands Avenue",
    "iso:country":"GB",
    "sg:address":"8 Richlands Avenue",
    "sg:city":"Epsom",
    "sg:classifiers":[
        {
            "category":"Bus Charters",
            "type":"Transportation"
        }
    ],
    "sg:phone":"+44 20 8287 9880",
    "sg:postcode":"KT17 2JW",
    "sg:province":"Surrey",
    "sg:tags":[
        "hire",
        "coach"
    ],
    "wof:name":"Escort Coaches",
    "wof:placetype":"venue"
},
  "geometry": {"coordinates":[-0.2441029996,51.3664245605],"type":"Point"}
}