{
  "type": "Feature",
  "properties": {
    "iso:country":"GB",
    "sg:address":"2 14 & 17 Cleve Rd",
    "sg:city":"Kilburn",
    "sg:classifiers":[
        {
            "category":"Health Services",
            "subcategory":"Nursing And Care Facility",
            "type":"Services"
        }
    ],
    "sg:phone":"+44 20 7624 3187",
    "sg:postcode":"NW6 3RL",
    "sg:province":"Greater London",
    "sg:tags":[
        "home"
    ],
    "wof:name":"Central & Cecil Housing Trust",
    "wof:placetype":"venue"
},
  "geometry": {"coordinates":[-0.191749,51.544086],"type":"Point"}
}