{
  "type": "Feature",
  "properties": {
    "iso:country":"GB",
    "sg:address":"27 Church Road, Hanham",
    "sg:city":"Bristol",
    "sg:classifiers":[
        {
            "category":"Manufacturing",
            "subcategory":"Building Materials",
            "type":"Manufacturing & Wholesale Goods"
        }
    ],
    "sg:phone":"+44 117 987 7301",
    "sg:postcode":"BS15 3AE",
    "sg:province":"City of Bristol",
    "sg:tags":[
        "dust",
        "extraction",
        "plant"
    ],
    "wof:name":"Dustcheck Ltd.",
    "wof:placetype":"venue"
},
  "geometry": {"coordinates":[-2.520348,51.449478],"type":"Point"}
}