{
  "type": "Feature",
  "properties": {
    "addr:full":"181 Chorley New Rd Bolton Lancashire BL6 5QE",
    "addr:housenumber":"181",
    "addr:postcode":"bl6 5qe",
    "addr:street":"Chorley New Rd",
    "iso:country":"GB",
    "sg:address":"181 Chorley New Rd",
    "sg:city":"Bolton",
    "sg:classifiers":[
        {
            "category":"Recreation",
            "type":"Entertainment"
        }
    ],
    "sg:phone":"+44 1204 694774",
    "sg:postcode":"BL6 5QE",
    "sg:province":"Lancashire",
    "sg:tags":[
        "snooker",
        "billiards",
        "pool"
    ],
    "wof:name":"Tee-K'S Ltd",
    "wof:placetype":"venue"
},
  "geometry": {"coordinates":[-2.449345,53.580868],"type":"Point"}
}