{
  "type": "Feature",
  "properties": {
    "addr:full":"Rock Road, Rock Wadebridge Cornwall PL27 6NW",
    "addr:postcode":"pl27 6nw",
    "addr:street":"Rock Road",
    "iso:country":"GB",
    "sg:address":"Rock Road, Rock",
    "sg:city":"Wadebridge",
    "sg:classifiers":[
        {
            "category":"Deli",
            "type":"Food & Drink"
        }
    ],
    "sg:phone":"+44 1208 863531",
    "sg:postcode":"PL27 6NW",
    "sg:province":"Cornwall",
    "sg:tags":[
        "delicatessen"
    ],
    "wof:name":"Di's Dairy & Pantry",
    "wof:placetype":"venue"
},
  "geometry": {"coordinates":[-4.9036898613,50.5495262146],"type":"Point"}
}