{
  "type": "Feature",
  "properties": {
    "iso:country":"GB",
    "sg:address":"57 Carr La",
    "sg:city":"Chorley",
    "sg:classifiers":[
        {
            "category":"Professional",
            "subcategory":"Employment Agencies",
            "type":"Services"
        }
    ],
    "sg:postcode":"PR7 3JF",
    "sg:province":"Lancashire",
    "sg:tags":[
        "consultant"
    ],
    "wof:name":"Token Marsh Labour Hire",
    "wof:placetype":"venue"
},
  "geometry": {"coordinates":[-2.629093,53.640003],"type":"Point"}
}