{
  "type": "Feature",
  "properties": {
    "addr:full":"Hopshill Farm, Hopshill Lane Saundersfoot Pembrokeshire SA69 9DT",
    "addr:postcode":"sa69 9dt",
    "addr:street":"Hopshill Lane",
    "iso:country":"GB",
    "sg:address":"Hopshill Farm, Hopshill Lane",
    "sg:city":"Saundersfoot",
    "sg:classifiers":[
        {
            "category":"Farming",
            "subcategory":"Dairy Farm",
            "type":"Manufacturing & Wholesale Goods"
        }
    ],
    "sg:phone":"+44 1834 812493",
    "sg:postcode":"SA69 9DT",
    "sg:province":"Pembrokeshire",
    "wof:name":"A J Merriman",
    "wof:placetype":"venue"
},
  "geometry": {"coordinates":[-4.6995558739,51.7102050781],"type":"Point"}
}