{
  "type": "Feature",
  "properties": {
    "addr:full":"31 Beech Rd Doncaster South Yorkshire DN3 2DZ",
    "addr:housenumber":"31",
    "addr:postcode":"dn3 2dz",
    "addr:street":"Beech Rd",
    "iso:country":"GB",
    "sg:address":"31 Beech Rd",
    "sg:city":"Doncaster",
    "sg:classifiers":[
        {
            "category":"Education",
            "subcategory":"Music School",
            "type":"Public Place"
        }
    ],
    "sg:phone":"+44 1302 830394",
    "sg:postcode":"DN3 2DZ",
    "sg:province":"South Yorkshire",
    "sg:tags":[
        "conservatory"
    ],
    "wof:name":"Proline Plastics",
    "wof:placetype":"venue"
},
  "geometry": {"coordinates":[-1.0567209721,53.5376396179],"type":"Point"}
}