{
  "type": "Feature",
  "properties": {
    "iso:country":"GB",
    "sg:address":"56 Uttoxeter Road, Draycott",
    "sg:city":"Stoke On Trent",
    "sg:classifiers":[
        {
            "category":"Fast Food",
            "type":"Food & Drink"
        }
    ],
    "sg:phone":"+44 1782 398100",
    "sg:postcode":"ST11 9NR",
    "sg:province":"Staffordshire",
    "sg:tags":[
        "away",
        "take"
    ],
    "wof:name":"J F Randell",
    "wof:placetype":"venue"
},
  "geometry": {"coordinates":[-2.0440208912,52.9622001648],"type":"Point"}
}