{
  "type": "Feature",
  "properties": {
    "addr:full":"Burleigh Street Hull East Riding of Yorkshire HU8 8SS",
    "addr:postcode":"hu8 8ss",
    "addr:street":"Burleigh Street",
    "iso:country":"GB",
    "sg:address":"Burleigh Street",
    "sg:city":"Hull",
    "sg:classifiers":[
        {
            "category":"Retail",
            "subcategory":"Auto Repair",
            "type":"Services"
        }
    ],
    "sg:postcode":"HU8 8SS",
    "sg:province":"East Riding of Yorkshire",
    "sg:tags":[
        "modification",
        "garage"
    ],
    "wof:name":"Belcher Motors",
    "wof:placetype":"venue"
},
  "geometry": {"coordinates":[-0.315039,53.752907],"type":"Point"}
}