{
  "type": "Feature",
  "properties": {
    "addr:full":"Canal Head Sth Kendal Cumbria LA9 7DB",
    "addr:postcode":"la9 7db",
    "addr:street":"Canal;Sth Kendal",
    "iso:country":"GB",
    "sg:address":"Canal Head Sth",
    "sg:city":"Kendal",
    "sg:classifiers":[
        {
            "category":"Retail",
            "subcategory":"Auto Repair",
            "type":"Services"
        }
    ],
    "sg:phone":"+44 1539 731307",
    "sg:postcode":"LA9 7DB",
    "sg:province":"Cumbria",
    "sg:tags":[
        "modification",
        "garage"
    ],
    "wof:name":"Mealbank Garage",
    "wof:placetype":"venue"
},
  "geometry": {"coordinates":[-2.74234,54.32637],"type":"Point"}
}