{
  "type": "Feature",
  "properties": {
    "addr:full":"Marconi House, Melbourne Street Newcastle-upon-tyne Tyne and Wear NE1 2JQ",
    "addr:postcode":"ne1 2jq",
    "addr:street":"Melbourne Street",
    "iso:country":"GB",
    "sg:address":"Marconi House, Melbourne Street",
    "sg:city":"Newcastle-upon-tyne",
    "sg:classifiers":[
        {
            "category":"Home & Garden",
            "subcategory":"Building Materials",
            "type":"Retail Goods"
        }
    ],
    "sg:phone":"+44 191 232 9378",
    "sg:postcode":"NE1 2JQ",
    "sg:province":"Tyne and Wear",
    "sg:tags":[
        "ventilator",
        "ventilation",
        "system"
    ],
    "wof:name":"Satchwell Control Systems",
    "wof:placetype":"venue"
},
  "geometry": {"coordinates":[-1.605204,54.971939],"type":"Point"}
}