{
  "type": "Feature",
  "properties": {
    "iso:country":"GB",
    "sg:address":"7 Blythe Road, Corfe Mullen",
    "sg:city":"Wimborne",
    "sg:classifiers":[
        {
            "category":"Building & Trades",
            "subcategory":"Landscaping Services",
            "type":"Services"
        }
    ],
    "sg:phone":"+44 1202 698047",
    "sg:postcode":"BH21 3LP",
    "sg:province":"Dorset",
    "sg:tags":[
        "gardening",
        "landscape",
        "contractor"
    ],
    "wof:name":"M A Carey",
    "wof:placetype":"venue"
},
  "geometry": {"coordinates":[-2.0187699795,50.7711791992],"type":"Point"}
}