{
  "type": "Feature",
  "properties": {
    "addr:full":"2nd Floor, 24-42 Palmestone Road, Wealdstone Harrow Greater London HA3 7RW",
    "addr:housenumber":"2nd floor 24-42",
    "addr:postcode":"ha3 7rw",
    "addr:street":"Palmestone Road",
    "iso:country":"GB",
    "sg:address":"2nd Floor, 24-42 Palmestone Road, Wealdstone",
    "sg:city":"Harrow",
    "sg:classifiers":[
        {
            "category":"Building & Trades",
            "subcategory":"Construction",
            "type":"Services"
        }
    ],
    "sg:phone":"+44 20 8427 3741",
    "sg:postcode":"HA3 7RW",
    "sg:province":"Greater London",
    "sg:tags":[
        "joinery"
    ],
    "wof:name":"Harrow Joinery Ltd.",
    "wof:placetype":"venue"
},
  "geometry": {"coordinates":[-0.3329339921,51.5934791565],"type":"Point"}
}