{
  "type": "Feature",
  "properties": {
    "addr:full":"Burford Road Witney Oxfordshire OX29 0RD",
    "addr:postcode":"ox29 0rd",
    "addr:street":"Burford Road",
    "iso:country":"GB",
    "sg:address":"Burford Road",
    "sg:city":"Witney",
    "sg:classifiers":[
        {
            "category":"Professional",
            "subcategory":"Engineering",
            "type":"Services"
        }
    ],
    "sg:phone":"+44 1993 702829",
    "sg:postcode":"OX29 0RD",
    "sg:province":"Oxfordshire",
    "sg:tags":[
        "hydraulic",
        "engineer"
    ],
    "wof:name":"Edwards Holdings Ltd.",
    "wof:placetype":"venue"
},
  "geometry": {"coordinates":[-1.513242,51.791855],"type":"Point"}
}