{
  "type": "Feature",
  "properties": {
    "addr:full":"5 Pearson Road, Mutley Plymouth Devon PL4 7DH",
    "addr:housenumber":"5",
    "addr:postcode":"pl4 7dh",
    "addr:street":"Pearson Road",
    "iso:country":"GB",
    "sg:address":"5 Pearson Road, Mutley",
    "sg:city":"Plymouth",
    "sg:classifiers":[
        {
            "category":"Retail",
            "subcategory":"Repair Shop",
            "type":"Services"
        }
    ],
    "sg:postcode":"PL4 7DH",
    "sg:province":"Devon",
    "sg:tags":[
        "radio",
        "television",
        "video"
    ],
    "wof:name":"Mike Smith Video Vision S W",
    "wof:placetype":"venue"
},
  "geometry": {"coordinates":[-4.129765,50.383041],"type":"Point"}
}