{
  "type": "Feature",
  "properties": {
    "iso:country":"GB",
    "sg:address":"56 Cliff, Rock Rd, Rednal",
    "sg:city":"Birmingham",
    "sg:classifiers":[
        {
            "category":"Building & Trades",
            "subcategory":"Construction",
            "type":"Services"
        }
    ],
    "sg:phone":"+44 121 453 8865",
    "sg:postcode":"B45 8QG",
    "sg:province":"West Midlands",
    "sg:tags":[
        "ventilation",
        "contractor"
    ],
    "wof:name":"A.M Jack Preservation",
    "wof:placetype":"venue"
},
  "geometry": {"coordinates":[-2.003397,52.392536],"type":"Point"}
}