{
  "type": "Feature",
  "properties": {
    "iso:country":"GB",
    "sg:address":"High Street, Earl Shilton",
    "sg:city":"Leicester",
    "sg:classifiers":[
        {
            "category":"Autos & Motor Vehicles",
            "subcategory":"Fuel & Gas Station",
            "type":"Retail Goods"
        }
    ],
    "sg:phone":"+44 1455 842610",
    "sg:postcode":"LE9 7DG",
    "sg:province":"Leicestershire",
    "sg:tags":[
        "petrol",
        "filling"
    ],
    "wof:name":"High Street Service Station",
    "wof:placetype":"venue"
},
  "geometry": {"coordinates":[-1.3144949675,52.5757751465],"type":"Point"}
}