{
  "type": "Feature",
  "properties": {
    "iso:country":"GB",
    "sg:address":"Principality House, Main Avenue",
    "sg:city":"Bridgend",
    "sg:classifiers":[
        {
            "category":"Insurance",
            "subcategory":"Insurance Agent",
            "type":"Services"
        }
    ],
    "sg:phone":"+44 1656 645422",
    "sg:postcode":"CF31 2BB",
    "sg:province":"Bridgend",
    "sg:tags":[
        "broker"
    ],
    "wof:name":"Vanguard Insurance Services Ltd.",
    "wof:placetype":"venue"
},
  "geometry": {"coordinates":[-3.562573,51.520569],"type":"Point"}
}