{
  "type": "Feature",
  "properties": {
    "addr:full":"60 High Street Selkirk Scottish Borders TD7 4DD",
    "addr:housenumber":"60",
    "addr:postcode":"td7 4dd",
    "addr:street":"High Street",
    "iso:country":"GB",
    "sg:address":"60 High Street",
    "sg:city":"Selkirk",
    "sg:classifiers":[
        {
            "category":"Fast Food",
            "type":"Food & Drink"
        }
    ],
    "sg:phone":"+44 1750 22053",
    "sg:postcode":"TD7 4DD",
    "sg:province":"Scottish Borders",
    "sg:tags":[
        "away",
        "meal",
        "outlet",
        "take"
    ],
    "wof:name":"Ming Chun House",
    "wof:placetype":"venue"
},
  "geometry": {"coordinates":[-2.8400731087,55.5483627319],"type":"Point"}
}