{
  "type": "Feature",
  "properties": {
    "iso:country":"GB",
    "sg:address":"Grove Farm, Upper Northam Drive",
    "sg:city":"Southampton",
    "sg:classifiers":[
        {
            "category":"Retail",
            "subcategory":"Auto Repair",
            "type":"Services"
        }
    ],
    "sg:phone":"+44 23 8047 1471",
    "sg:postcode":"SO30 4BG",
    "sg:province":"Hampshire",
    "sg:tags":[
        "modification",
        "garage"
    ],
    "wof:name":"V W Eastlake",
    "wof:placetype":"venue"
},
  "geometry": {"coordinates":[-1.322197,50.912251],"type":"Point"}
}