{
  "type": "Feature",
  "properties": {
    "addr:full":"Bilston C Of E Primary School, Kitchen, Albany Cres Bilston West Midlands WV14 0HU",
    "addr:postcode":"wv14 0hu",
    "addr:street":"Albany Cres",
    "iso:country":"GB",
    "sg:address":"Bilston C Of E Primary School, Kitchen, Albany Cres",
    "sg:city":"Bilston",
    "sg:classifiers":[
        {
            "category":"Government",
            "subcategory":"Office",
            "type":"Public Place"
        }
    ],
    "sg:phone":"+44 1902 558004",
    "sg:postcode":"WV14 0HU",
    "sg:province":"West Midlands",
    "sg:tags":[
        "local"
    ],
    "wof:name":"Wolverhampton Metropolitan Borough Council",
    "wof:placetype":"venue"
},
  "geometry": {"coordinates":[-2.0744900703,52.5666351318],"type":"Point"}
}