{
  "type": "Feature",
  "properties": {
    "iso:country":"GB",
    "sg:address":"17 Charterhouse Street",
    "sg:city":"London",
    "sg:classifiers":[
        {
            "category":"Manufacturing",
            "subcategory":"Jewelry",
            "type":"Manufacturing & Wholesale Goods"
        }
    ],
    "sg:postcode":"EC1N 6RA",
    "sg:province":"Greater London",
    "sg:tags":[
        "precious",
        "stone"
    ],
    "wof:name":"C S O Valuations A G",
    "wof:placetype":"venue"
},
  "geometry": {"coordinates":[-0.105806,51.518452],"type":"Point"}
}