{
  "type": "Feature",
  "properties": {
    "addr:full":"50 Windy Bank Colne Lancashire BB8 9HY",
    "addr:housenumber":"50",
    "addr:postcode":"bb8 9hy",
    "addr:street":"Windy Bank Colne",
    "iso:country":"GB",
    "sg:address":"50 Windy Bank",
    "sg:city":"Colne",
    "sg:classifiers":[
        {
            "category":"Bars & Pubs",
            "type":"Food & Drink"
        }
    ],
    "sg:postcode":"BB8 9HY",
    "sg:province":"Lancashire",
    "sg:tags":[
        "pubs",
        "inn"
    ],
    "wof:name":"Jolly Hatters Hotel",
    "wof:placetype":"venue"
},
  "geometry": {"coordinates":[-2.167769,53.859119],"type":"Point"}
}