{
  "type": "Feature",
  "properties": {
    "iso:country":"GB",
    "sg:address":"Unit 5 The Tileries St Asaph Av, E, Kinmel Bay",
    "sg:city":"Rhyl",
    "sg:classifiers":[
        {
            "category":"Home & Garden",
            "subcategory":"Building Materials",
            "type":"Retail Goods"
        }
    ],
    "sg:phone":"+44 1745 332112",
    "sg:postcode":"LL18 1EU",
    "sg:province":"Conwy",
    "sg:tags":[
        "ventilator",
        "ventilation",
        "system"
    ],
    "wof:name":"I C C Ventilation",
    "wof:placetype":"venue"
},
  "geometry": {"coordinates":[-3.48982,53.320129],"type":"Point"}
}