{
  "type": "Feature",
  "properties": {
    "addr:full":"37 Cliff Road Leeds West Yorkshire LS6 2ET",
    "addr:housenumber":"37",
    "addr:postcode":"ls6 2et",
    "addr:street":"Cliff Road",
    "iso:country":"GB",
    "sg:address":"37 Cliff Road",
    "sg:city":"Leeds",
    "sg:classifiers":[
        {
            "category":"Professional",
            "subcategory":"Computer Services",
            "type":"Services"
        }
    ],
    "sg:postcode":"LS6 2ET",
    "sg:province":"West Yorkshire",
    "sg:tags":[
        "system",
        "software"
    ],
    "wof:name":"Qubik Design",
    "wof:placetype":"venue"
},
  "geometry": {"coordinates":[-1.5605540276,53.8167953491],"type":"Point"}
}