{
  "type": "Feature",
  "properties": {
    "iso:country":"GB",
    "sg:address":"Tamian Way",
    "sg:city":"Hounslow",
    "sg:classifiers":[
        {
            "category":"Professional",
            "subcategory":"Printing & Photocopies",
            "type":"Services"
        }
    ],
    "sg:phone":"+44 20 8572 2260",
    "sg:postcode":"TW4 6BL",
    "sg:province":"Greater London",
    "sg:tags":[
        "printer"
    ],
    "wof:name":"Mercolour Graphics Ltd.",
    "wof:placetype":"venue"
},
  "geometry": {"coordinates":[-0.3973230124,51.4636917114],"type":"Point"}
}