{
  "type": "Feature",
  "properties": {
    "iso:country":"GB",
    "sg:address":"85 Forton Rd",
    "sg:city":"Gosport",
    "sg:classifiers":[
        {
            "category":"Professional",
            "subcategory":"Employment Agencies",
            "type":"Services"
        }
    ],
    "sg:phone":"+44 23 9252 9933",
    "sg:postcode":"PO12 4TG",
    "sg:province":"Hampshire",
    "sg:tags":[
        "consultant"
    ],
    "wof:name":"Cheers Bar Staffing Agency",
    "wof:placetype":"venue"
},
  "geometry": {"coordinates":[-1.132984,50.79932],"type":"Point"}
}