{
  "type": "Feature",
  "properties": {
    "addr:full":"14 London Road, Strood Rochester Kent ME2 3HT",
    "addr:housenumber":"14",
    "addr:postcode":"me2 3ht",
    "addr:street":"London Road",
    "iso:country":"GB",
    "sg:address":"14 London Road, Strood",
    "sg:city":"Rochester",
    "sg:classifiers":[
        {
            "category":"Retail",
            "subcategory":"Repair Shop",
            "type":"Services"
        }
    ],
    "sg:phone":"+44 1634 718253",
    "sg:postcode":"ME2 3HT",
    "sg:province":"Kent",
    "sg:tags":[
        "clocks",
        "watch"
    ],
    "wof:name":"I Roberts",
    "wof:placetype":"venue"
},
  "geometry": {"coordinates":[0.490797,51.39629],"type":"Point"}
}