{
  "type": "Feature",
  "properties": {
    "addr:full":"16 Wellesley Road, Long Stratton Norwich Norfolk NR15 2PD",
    "addr:housenumber":"16",
    "addr:postcode":"nr15 2pd",
    "addr:street":"Wellesley Road",
    "iso:country":"GB",
    "sg:address":"16 Wellesley Road, Long Stratton",
    "sg:city":"Norwich",
    "sg:classifiers":[
        {
            "category":"Retail",
            "subcategory":"Auto Repair",
            "type":"Services"
        }
    ],
    "sg:phone":"+44 1508 531926",
    "sg:postcode":"NR15 2PD",
    "sg:province":"Norfolk",
    "sg:tags":[
        "body",
        "car"
    ],
    "wof:name":"Ipswich Road Body Repairs",
    "wof:placetype":"venue"
},
  "geometry": {"coordinates":[1.221765,52.485989],"type":"Point"}
}