{
  "type": "Feature",
  "properties": {
    "addr:full":"Freedom Farm Stud, East Green, Great Bradley Newmarket Cambridgeshire CB8 9LU",
    "addr:postcode":"cb8 9lu",
    "addr:street":"East Green",
    "iso:country":"GB",
    "sg:address":"Freedom Farm Stud, East Green, Great Bradley",
    "sg:city":"Newmarket",
    "sg:classifiers":[
        {
            "category":"Farming",
            "subcategory":"Livestock Farm",
            "type":"Manufacturing & Wholesale Goods"
        },
        {
            "category":"Retail",
            "subcategory":"Animal Services",
            "type":"Services"
        }
    ],
    "sg:phone":"+44 1440 783667",
    "sg:postcode":"CB8 9LU",
    "sg:province":"Cambridgeshire",
    "sg:tags":[
        "breeder",
        "horse",
        "stud"
    ],
    "wof:name":"Freedom Farm Stud",
    "wof:placetype":"venue"
},
  "geometry": {"coordinates":[0.437007,52.151711],"type":"Point"}
}