{
  "type": "Feature",
  "properties": {
    "iso:country":"GB",
    "sg:address":"25 Gwydir St",
    "sg:city":"Cambridge",
    "sg:classifiers":[
        {
            "category":"Professional",
            "type":"Services"
        }
    ],
    "sg:postcode":"CB1 2LG",
    "sg:province":"Cambridgeshire",
    "sg:tags":[
        "writer"
    ],
    "wof:name":"G M Whitehead",
    "wof:placetype":"venue"
},
  "geometry": {"coordinates":[0.139029,52.20396],"type":"Point"}
}