{
  "type": "Feature",
  "properties": {
    "iso:country":"GB",
    "sg:address":"Far Grn Industrial Estate, Chell Street, Hanley",
    "sg:city":"Stoke-on-trent",
    "sg:classifiers":[
        {
            "category":"Professional",
            "subcategory":"Printing & Photocopies",
            "type":"Services"
        }
    ],
    "sg:phone":"+44 1782 274429",
    "sg:postcode":"ST1 6AZ",
    "sg:province":"Staffordshire",
    "sg:tags":[
        "engraving"
    ],
    "wof:name":"Trigg Engraving",
    "wof:placetype":"venue"
},
  "geometry": {"coordinates":[-2.161089,53.04147],"type":"Point"}
}