{
  "type": "Feature",
  "properties": {
    "addr:full":"Unit 19 Brierley Business Centre, Mirion Street Crewe Cheshire CW1 2AZ",
    "addr:housenumber":"unit 19",
    "addr:postcode":"cw1 2az",
    "addr:street":"Brierley Business;Mirion Street",
    "iso:country":"GB",
    "sg:address":"Unit 19 Brierley Business Centre, Mirion Street",
    "sg:city":"Crewe",
    "sg:classifiers":[
        {
            "category":"Manufacturing",
            "subcategory":"Electronics",
            "type":"Manufacturing & Wholesale Goods"
        }
    ],
    "sg:postcode":"CW1 2AZ",
    "sg:province":"Cheshire",
    "sg:tags":[
        "mnfr",
        "component",
        "electronic"
    ],
    "wof:name":"Ridgeway Electronic Services Ltd",
    "wof:placetype":"venue"
},
  "geometry": {"coordinates":[-2.446105,53.100578],"type":"Point"}
}