{
  "type": "Feature",
  "properties": {
    "addr:full":"80 Glebe Field Dr Wetherby North Yorkshire LS22 6WG",
    "addr:housenumber":"80",
    "addr:postcode":"ls22 6wg",
    "addr:street":"Glebe Field Dr",
    "iso:country":"GB",
    "sg:address":"80 Glebe Field Dr",
    "sg:city":"Wetherby",
    "sg:classifiers":[
        {
            "category":"Personal",
            "subcategory":"Tanning Parlor",
            "type":"Services"
        }
    ],
    "sg:postcode":"LS22 6WG",
    "sg:province":"North Yorkshire",
    "sg:tags":[
        "sunbeds"
    ],
    "wof:name":"Home-Tan Uva Sunbeds",
    "wof:placetype":"venue"
},
  "geometry": {"coordinates":[-1.394391,53.935715],"type":"Point"}
}