{
  "type": "Feature",
  "properties": {
    "addr:full":"20 Mellor Road, Cheadle Hulme Cheadle Cheshire SK8 5AU",
    "addr:housenumber":"20",
    "addr:postcode":"sk8 5au",
    "addr:street":"Mellor Road",
    "iso:country":"GB",
    "sg:address":"20 Mellor Road, Cheadle Hulme",
    "sg:city":"Cheadle",
    "sg:classifiers":[
        {
            "category":"Professional",
            "subcategory":"Engineering",
            "type":"Services"
        }
    ],
    "sg:phone":"+44 161 486 1521",
    "sg:postcode":"SK8 5AU",
    "sg:province":"Cheshire",
    "sg:tags":[
        "consultant",
        "structural"
    ],
    "wof:name":"Roscoe Capita Ltd.",
    "wof:placetype":"venue"
},
  "geometry": {"coordinates":[-2.1889328957,53.3749504089],"type":"Point"}
}