{
  "type": "Feature",
  "properties": {
    "iso:country":"GB",
    "sg:address":"78 Beaconsfield Road",
    "sg:city":"Norwich",
    "sg:classifiers":[
        {
            "category":"Food & Beverages",
            "subcategory":"Groceries & Convenience Stores",
            "type":"Retail Goods"
        }
    ],
    "sg:postcode":"NR3 4PW",
    "sg:province":"Norfolk",
    "wof:name":"Freshmarket",
    "wof:placetype":"venue"
},
  "geometry": {"coordinates":[1.299327,52.6399],"type":"Point"}
}