{
  "type": "Feature",
  "properties": {
    "iso:country":"GB",
    "sg:address":"10 Midhurst Road",
    "sg:city":"Liphook",
    "sg:classifiers":[
        {
            "category":"Fast Food",
            "type":"Food & Drink"
        }
    ],
    "sg:phone":"+44 1428 722927",
    "sg:postcode":"GU30 7ED",
    "sg:province":"Hampshire",
    "sg:tags":[
        "away",
        "meal",
        "outlet",
        "take"
    ],
    "wof:name":"Lees Garden",
    "wof:placetype":"venue"
},
  "geometry": {"coordinates":[-0.801923,51.07563],"type":"Point"}
}