{
  "type": "Feature",
  "properties": {
    "addr:full":"First Floor 754 Fulham Rd Fulham Greater London SW6 5SH",
    "addr:housenumber":"754",
    "addr:postcode":"sw6 5sh",
    "addr:street":"Fulham Rd",
    "iso:country":"GB",
    "sg:address":"First Floor 754 Fulham Rd",
    "sg:city":"Fulham",
    "sg:classifiers":[
        {
            "category":"Professional",
            "subcategory":"Management & Consulting",
            "type":"Services"
        }
    ],
    "sg:phone":"+44 20 7384 2232",
    "sg:postcode":"SW6 5SH",
    "sg:province":"Greater London",
    "sg:tags":[
        "music"
    ],
    "wof:name":"Music Media Management",
    "wof:placetype":"venue"
},
  "geometry": {"coordinates":[-0.2095319927,51.4727096558],"type":"Point"}
}