{
  "type": "Feature",
  "properties": {
    "iso:country":"GB",
    "sg:address":"55 Twyford Rd",
    "sg:city":"Eastleigh",
    "sg:classifiers":[
        {
            "category":"Building & Trades",
            "subcategory":"Construction",
            "type":"Services"
        }
    ],
    "sg:phone":"+44 23 8061 8303",
    "sg:postcode":"SO50 4HH",
    "sg:province":"Hampshire",
    "sg:tags":[
        "builder"
    ],
    "wof:name":"Oakshire Contracts Ltd",
    "wof:placetype":"venue"
},
  "geometry": {"coordinates":[-1.350437,50.97496],"type":"Point"}
}