{
  "type": "Feature",
  "properties": {
    "iso:country":"GB",
    "sg:address":"15 Portland Rd",
    "sg:city":"Walsall",
    "sg:classifiers":[
        {
            "category":"Health Services",
            "subcategory":"Doctor",
            "type":"Services"
        }
    ],
    "sg:phone":"+44 1922 452139",
    "sg:postcode":"WS9 8NS",
    "sg:province":"Staffordshire",
    "sg:tags":[
        "practitioners"
    ],
    "wof:name":"Harrison, J M",
    "wof:placetype":"venue"
},
  "geometry": {"coordinates":[-1.9177540541,52.6027183533],"type":"Point"}
}