{
  "type": "Feature",
  "properties": {
    "addr:full":"Sevelands Farm Lewes East Sussex BN7 3DF",
    "addr:postcode":"bn7 3df",
    "iso:country":"GB",
    "sg:address":"Sevelands Farm",
    "sg:city":"Lewes",
    "sg:classifiers":[
        {
            "category":"Building & Trades",
            "subcategory":"Construction",
            "type":"Services"
        }
    ],
    "sg:postcode":"BN7 3DF",
    "sg:province":"East Sussex",
    "sg:tags":[
        "builder"
    ],
    "wof:name":"G G E Reed",
    "wof:placetype":"venue"
},
  "geometry": {"coordinates":[0.0106199998,50.8732032776],"type":"Point"}
}