{
  "type": "Feature",
  "properties": {
    "addr:full":"Blandford Rd Salisbury Dorset SP5 4LN",
    "addr:postcode":"sp5 4ln",
    "addr:street":"Blandford Rd",
    "iso:country":"GB",
    "sg:address":"Blandford Rd",
    "sg:city":"Salisbury",
    "sg:classifiers":[
        {
            "category":"Shopping",
            "subcategory":"Pets & Pet Supplies",
            "type":"Retail Goods"
        }
    ],
    "sg:phone":"+44 1722 718213",
    "sg:postcode":"SP5 4LN",
    "sg:province":"Dorset",
    "sg:tags":[
        "cemetery",
        "crematorium"
    ],
    "wof:name":"Hillcrest Kennels & Cattery",
    "wof:placetype":"venue"
},
  "geometry": {"coordinates":[-1.849254,51.028313],"type":"Point"}
}