{
  "type": "Feature",
  "properties": {
    "addr:full":"The Old Boiler House, Cawdor Street, Eccles Manchester Greater Manchester M30 0GB",
    "addr:postcode":"m30 0gb",
    "addr:street":"Cawdor Street",
    "iso:country":"GB",
    "sg:address":"The Old Boiler House, Cawdor Street, Eccles",
    "sg:city":"Manchester",
    "sg:classifiers":[
        {
            "category":"Retail",
            "subcategory":"Auto Repair",
            "type":"Services"
        }
    ],
    "sg:phone":"+44 161 787 7723",
    "sg:postcode":"M30 0GB",
    "sg:province":"Greater Manchester",
    "sg:tags":[
        "body",
        "car"
    ],
    "wof:name":"Kieran Heavey",
    "wof:placetype":"venue"
},
  "geometry": {"coordinates":[-2.340709,53.483456],"type":"Point"}
}