{
  "type": "Feature",
  "properties": {
    "iso:country":"GB",
    "sg:address":"Bealey Industrial Estate, Dumers Lane",
    "sg:city":"Manchester",
    "sg:classifiers":[
        {
            "category":"Building & Trades",
            "subcategory":"Construction",
            "type":"Services"
        }
    ],
    "sg:postcode":"M26 2QE",
    "sg:province":"Greater Manchester",
    "sg:tags":[
        "demolition",
        "contractor"
    ],
    "wof:name":"Martin Flynn",
    "wof:placetype":"venue"
},
  "geometry": {"coordinates":[-2.3073539734,53.5676841736],"type":"Point"}
}