{
  "type": "Feature",
  "properties": {
    "addr:full":"23 St Martins St Wallingford Oxfordshire OX10 0AL",
    "addr:housenumber":"23",
    "addr:postcode":"ox10 0al",
    "addr:street":"St Martins St",
    "iso:country":"GB",
    "sg:address":"23 St Martins St",
    "sg:city":"Wallingford",
    "sg:classifiers":[
        {
            "category":"Real Estate",
            "subcategory":"Real Estate Agent",
            "type":"Services"
        }
    ],
    "sg:phone":"+44 1491 824470",
    "sg:postcode":"OX10 0AL",
    "sg:province":"Oxfordshire",
    "wof:name":"Homebase Property Management",
    "wof:placetype":"venue"
},
  "geometry": {"coordinates":[-1.1255480051,51.5984420776],"type":"Point"}
}