{
  "type": "Feature",
  "properties": {
    "iso:country":"GB",
    "sg:address":"13 Bannerman Pl",
    "sg:city":"Aberdeen",
    "sg:classifiers":[
        {
            "category":"Professional",
            "subcategory":"Engineering",
            "type":"Services"
        }
    ],
    "sg:phone":"+44 1224 685383",
    "sg:postcode":"AB16 7QA",
    "sg:province":"Aberdeen City",
    "sg:tags":[
        "contractor",
        "electrical",
        "engineer"
    ],
    "wof:name":"Warren Ivers Electrician",
    "wof:placetype":"venue"
},
  "geometry": {"coordinates":[-2.1667599678,57.1679344177],"type":"Point"}
}