{
  "type": "Feature",
  "properties": {
    "addr:full":"Northfield Mills, Sharp Lane, Almondbury Huddersfield West Yorkshire HD4 6SR",
    "addr:postcode":"hd4 6sr",
    "addr:street":"Northfield Mills Sharp Lane;West",
    "iso:country":"GB",
    "sg:address":"Northfield Mills, Sharp Lane, Almondbury",
    "sg:city":"Huddersfield",
    "sg:classifiers":[
        {
            "category":"Food & Beverages",
            "subcategory":"Candy",
            "type":"Retail Goods"
        }
    ],
    "sg:phone":"+44 1484 518528",
    "sg:postcode":"HD4 6SR",
    "sg:province":"West Yorkshire",
    "sg:tags":[
        "confectionery"
    ],
    "wof:name":"Simply Sweet & Partners",
    "wof:placetype":"venue"
},
  "geometry": {"coordinates":[-1.7491719723,53.6271438599],"type":"Point"}
}