{
  "type": "Feature",
  "properties": {
    "addr:full":"239 Wood Street Walthamstow Greater London E17 3NT",
    "addr:housenumber":"239",
    "addr:postcode":"e17 3nt",
    "addr:street":"Wood Street",
    "iso:country":"GB",
    "sg:address":"239 Wood Street",
    "sg:city":"Walthamstow",
    "sg:classifiers":[
        {
            "category":"Fast Food",
            "type":"Food & Drink"
        }
    ],
    "sg:phone":"+44 20 8509 3302",
    "sg:postcode":"E17 3NT",
    "sg:province":"Greater London",
    "sg:tags":[
        "away",
        "take"
    ],
    "wof:name":"Millennium Cafe",
    "wof:placetype":"venue"
},
  "geometry": {"coordinates":[-0.000996,51.584682],"type":"Point"}
}