{
  "type": "Feature",
  "properties": {
    "addr:full":"27 Beverley Gardens Maidenhead Berkshire SL6 6SN",
    "addr:housenumber":"27",
    "addr:postcode":"sl6 6sn",
    "addr:street":"Beverley Gardens",
    "iso:country":"GB",
    "sg:address":"27 Beverley Gardens",
    "sg:city":"Maidenhead",
    "sg:classifiers":[
        {
            "category":"Retail",
            "subcategory":"Driving School",
            "type":"Services"
        }
    ],
    "sg:phone":"+44 1628 670111",
    "sg:postcode":"SL6 6SN",
    "sg:province":"Berkshire",
    "wof:name":"Aa Driving School",
    "wof:placetype":"venue"
},
  "geometry": {"coordinates":[-0.751996994,51.5316505432],"type":"Point"}
}