{
  "type": "Feature",
  "properties": {
    "addr:full":"62 Whitchurch Road Cardiff Cardiff CF14 3LX",
    "addr:housenumber":"62",
    "addr:postcode":"cf14 3lx",
    "addr:street":"Whitchurch Road",
    "iso:country":"GB",
    "sg:address":"62 Whitchurch Road",
    "sg:city":"Cardiff",
    "sg:classifiers":[
        {
            "category":"Professional",
            "subcategory":"Accounting & Tax Preparation",
            "type":"Services"
        }
    ],
    "sg:phone":"+44 29 2023 1758",
    "sg:postcode":"CF14 3LX",
    "sg:province":"Cardiff",
    "sg:tags":[
        "accountant"
    ],
    "wof:name":"S N K Associates",
    "wof:placetype":"venue"
},
  "geometry": {"coordinates":[-3.186327,51.500114],"type":"Point"}
}