{
  "type": "Feature",
  "properties": {
    "addr:full":"484 High Rd, Tottenham Tottenham Greater London N17 9JF",
    "addr:housenumber":"484",
    "addr:postcode":"n17 9jf",
    "addr:street":"High Rd",
    "iso:country":"GB",
    "sg:address":"484 High Rd, Tottenham",
    "sg:city":"Tottenham",
    "sg:classifiers":[
        {
            "category":"Shopping",
            "subcategory":"Thrift Store",
            "type":"Retail Goods"
        }
    ],
    "sg:phone":"+44 20 8808 6808",
    "sg:postcode":"N17 9JF",
    "sg:province":"Greater London",
    "sg:tags":[
        "shop",
        "charity"
    ],
    "wof:name":"Sense",
    "wof:placetype":"venue"
},
  "geometry": {"coordinates":[-0.0694409981,51.5934715271],"type":"Point"}
}