{
  "type": "Feature",
  "properties": {
    "addr:full":"37 Midhurst Hill Bexleyheath Kent DA6 7NP",
    "addr:housenumber":"37",
    "addr:postcode":"da6 7np",
    "addr:street":"Midhurst Hill",
    "iso:country":"GB",
    "sg:address":"37 Midhurst Hill",
    "sg:city":"Bexleyheath",
    "sg:classifiers":[
        {
            "category":"Shopping",
            "subcategory":"Stationery & Office Supplies",
            "type":"Retail Goods"
        }
    ],
    "sg:phone":"+44 20 8303 8124",
    "sg:postcode":"DA6 7NP",
    "sg:province":"Kent",
    "wof:name":"Modern Mailing Methods Ltd.",
    "wof:placetype":"venue"
},
  "geometry": {"coordinates":[0.14411,51.45026],"type":"Point"}
}