{
  "type": "Feature",
  "properties": {
    "iso:country":"GB",
    "sg:address":"17-19 Euston Road",
    "sg:city":"Morecambe",
    "sg:classifiers":[
        {
            "category":"Banks & Credit Unions",
            "subcategory":"Bank",
            "type":"Services"
        }
    ],
    "sg:postcode":"LA4 5DE",
    "sg:province":"Lancashire",
    "wof:name":"Barclays Bank Plc",
    "wof:placetype":"venue"
},
  "geometry": {"coordinates":[-2.863879,54.071892],"type":"Point"}
}