{
  "type": "Feature",
  "properties": {
    "iso:country":"GB",
    "sg:address":"128 Victoria Road",
    "sg:city":"Bridgnorth",
    "sg:classifiers":[
        {
            "category":"Building & Trades",
            "subcategory":"Cleaning & Sanitation",
            "type":"Services"
        }
    ],
    "sg:phone":"+44 1746 764750",
    "sg:postcode":"WV16 4LG",
    "sg:province":"Shropshire",
    "sg:tags":[
        "commercial"
    ],
    "wof:name":"V & A Preen",
    "wof:placetype":"venue"
},
  "geometry": {"coordinates":[-2.434054,52.541451],"type":"Point"}
}