{
  "type": "Feature",
  "properties": {
    "addr:full":"C/o Glassman & Co, 8 Holywell Hill St Albans Hertfordshire AL1 1BZ",
    "addr:housenumber":"8",
    "addr:postcode":"al1 1bz",
    "addr:street":"C;Holywell Hill",
    "iso:country":"GB",
    "sg:address":"C/o Glassman & Co, 8 Holywell Hill",
    "sg:city":"St Albans",
    "sg:classifiers":[
        {
            "category":"Government",
            "subcategory":"Post Office",
            "type":"Public Place"
        }
    ],
    "sg:postcode":"AL1 1BZ",
    "sg:province":"Hertfordshire",
    "sg:tags":[
        "messenger",
        "courier"
    ],
    "wof:name":"Hand Delivery Ltd",
    "wof:placetype":"venue"
},
  "geometry": {"coordinates":[-0.34013,51.750671],"type":"Point"}
}