{
  "type": "Feature",
  "properties": {
    "iso:country":"GB",
    "sg:address":"9 Stocks Lane",
    "sg:city":"Knutsford",
    "sg:classifiers":[
        {
            "category":"Home & Garden",
            "subcategory":"Garden Supply",
            "type":"Retail Goods"
        }
    ],
    "sg:phone":"+44 1565 722624",
    "sg:postcode":"WA16 9EZ",
    "sg:province":"Cheshire",
    "sg:tags":[
        "nursery",
        "centre"
    ],
    "wof:name":"Royal Sluis Ltd",
    "wof:placetype":"venue"
},
  "geometry": {"coordinates":[-2.3404250145,53.2665061951],"type":"Point"}
}