{
  "type": "Feature",
  "properties": {
    "addr:full":"183b Fleet Rd Fleet Dorset GU13 8BL",
    "addr:housenumber":"183b",
    "addr:postcode":"gu13 8bl",
    "addr:street":"Fleet Rd",
    "iso:country":"GB",
    "sg:address":"183b Fleet Rd",
    "sg:city":"Fleet",
    "sg:classifiers":[
        {
            "category":"Travel",
            "subcategory":"Travel Agent",
            "type":"Entertainment"
        }
    ],
    "sg:phone":"+44 1252 620411",
    "sg:postcode":"GU13 8BL",
    "sg:province":"Dorset",
    "wof:name":"Going Places",
    "wof:placetype":"venue"
},
  "geometry": {"coordinates":[-0.8406389952,51.2822151184],"type":"Point"}
}