{
  "type": "Feature",
  "properties": {
    "addr:full":"Robin Banks Works, Frederick Street Darwen Lancashire BB3 1DY",
    "addr:postcode":"bb3 1dy",
    "addr:street":"Frederick Street",
    "iso:country":"GB",
    "sg:address":"Robin Banks Works, Frederick Street",
    "sg:city":"Darwen",
    "sg:classifiers":[
        {
            "category":"Manufacturing",
            "subcategory":"Metals",
            "type":"Manufacturing & Wholesale Goods"
        }
    ],
    "sg:phone":"+44 1254 701810",
    "sg:postcode":"BB3 1DY",
    "sg:province":"Lancashire",
    "sg:tags":[
        "steel",
        "stockholder"
    ],
    "wof:name":"Frank Barnes (Darwen) Ltd.",
    "wof:placetype":"venue"
},
  "geometry": {"coordinates":[-2.4671690464,53.6941986084],"type":"Point"}
}