{
  "type": "Feature",
  "properties": {
    "iso:country":"GB",
    "sg:address":"St Lukes Hall, Morley Hill",
    "sg:city":"Enfield",
    "sg:classifiers":[
        {
            "category":"Personal",
            "type":"Services"
        }
    ],
    "sg:phone":"+44 20 8803 7065",
    "sg:postcode":"EN2 0BL",
    "sg:province":"Greater London",
    "sg:tags":[
        "slimming",
        "product"
    ],
    "wof:name":"Slimming World",
    "wof:placetype":"venue"
},
  "geometry": {"coordinates":[-0.082615,51.667263],"type":"Point"}
}