{
  "type": "Feature",
  "properties": {
    "addr:full":"Within Debenhams Market Place Romford Essex RM1 3ET",
    "addr:postcode":"rm1 3et",
    "addr:street":"Market Place",
    "iso:country":"GB",
    "sg:address":"Within Debenhams Market Place",
    "sg:city":"Romford",
    "sg:classifiers":[
        {
            "category":"Communications",
            "type":"Services"
        }
    ],
    "sg:phone":"+44 1708 736536",
    "sg:postcode":"RM1 3ET",
    "sg:province":"Essex",
    "sg:tags":[
        "telecommunication"
    ],
    "wof:name":"Communicate",
    "wof:placetype":"venue"
},
  "geometry": {"coordinates":[0.1863150001,51.5813903809],"type":"Point"}
}