{
  "type": "Feature",
  "properties": {
    "iso:country":"GB",
    "sg:address":"Woodville Centre, Shirley Rd",
    "sg:city":"Manchester",
    "sg:classifiers":[
        {
            "category":"Professional",
            "subcategory":"Lawyer & Legal Services",
            "type":"Services"
        }
    ],
    "sg:phone":"+44 161 740 7899",
    "sg:postcode":"M8 0NE",
    "sg:province":"Greater Manchester",
    "sg:tags":[
        "advice",
        "counselling"
    ],
    "wof:name":"Manchester Vietnamese Refugee Community Association",
    "wof:placetype":"venue"
},
  "geometry": {"coordinates":[-2.23827,53.50885],"type":"Point"}
}