{
  "type": "Feature",
  "properties": {
    "addr:full":"21 Union St, Rosehearty Fraserburgh Aberdeenshire AB43 7JQ",
    "addr:housenumber":"21",
    "addr:postcode":"ab43 7jq",
    "addr:street":"Union St",
    "iso:country":"GB",
    "sg:address":"21 Union St, Rosehearty",
    "sg:city":"Fraserburgh",
    "sg:classifiers":[
        {
            "category":"Bus Charters",
            "type":"Transportation"
        }
    ],
    "sg:phone":"+44 1346 571610",
    "sg:postcode":"AB43 7JQ",
    "sg:province":"Aberdeenshire",
    "sg:tags":[
        "hire",
        "coach"
    ],
    "wof:name":"Rosehearty Service Station",
    "wof:placetype":"venue"
},
  "geometry": {"coordinates":[-2.1101169586,57.6961326599],"type":"Point"}
}