{
  "type": "Feature",
  "properties": {
    "addr:full":"27 Charlotte Street Portsmouth Hampshire PO1 4AH",
    "addr:housenumber":"27",
    "addr:postcode":"hampshire po1 4ah",
    "addr:street":"Charlotte Street",
    "iso:country":"GB",
    "sg:address":"27 Charlotte Street",
    "sg:city":"Portsmouth",
    "sg:classifiers":[
        {
            "category":"Restaurant",
            "type":"Food & Drink"
        }
    ],
    "sg:phone":"+44 23 9273 3234",
    "sg:postcode":"PO1 4AH",
    "sg:province":"Hampshire",
    "wof:name":"Munchers Restaurant",
    "wof:placetype":"venue"
},
  "geometry": {"coordinates":[-1.088903,50.801937],"type":"Point"}
}