{
  "type": "Feature",
  "properties": {
    "addr:full":"317 Haydons Road, Wimbledon London Greater London SW19 8TX",
    "addr:housenumber":"317",
    "addr:postcode":"sw19 8tx",
    "addr:street":"Haydons Road",
    "iso:country":"GB",
    "sg:address":"317 Haydons Road, Wimbledon",
    "sg:city":"London",
    "sg:classifiers":[
        {
            "category":"Government",
            "subcategory":"Post Office",
            "type":"Public Place"
        }
    ],
    "sg:phone":"+44 20 8542 1802",
    "sg:postcode":"SW19 8TX",
    "sg:province":"Greater London",
    "wof:name":"Haydons Rd Post Office",
    "wof:placetype":"venue"
},
  "geometry": {"coordinates":[-0.187755,51.42421],"type":"Point"}
}