{
  "type": "Feature",
  "properties": {
    "addr:full":"49 Atherton Road Ilford Essex IG5 0PQ",
    "addr:housenumber":"49",
    "addr:postcode":"ig5 0pq",
    "addr:street":"Atherton Road",
    "iso:country":"GB",
    "sg:address":"49 Atherton Road",
    "sg:city":"Ilford",
    "sg:classifiers":[
        {
            "category":"Shopping",
            "subcategory":"News",
            "type":"Retail Goods"
        }
    ],
    "sg:phone":"+44 20 8551 2980",
    "sg:postcode":"IG5 0PQ",
    "sg:province":"Essex",
    "sg:tags":[
        "newsagent"
    ],
    "wof:name":"R S Confectionery",
    "wof:placetype":"venue"
},
  "geometry": {"coordinates":[0.056151,51.594643],"type":"Point"}
}