{
  "type": "Feature",
  "properties": {
    "addr:full":"Chapel House, Ffordd Y Blaenau, Treuddyn Mold Denbighshire CH7 4NS",
    "addr:postcode":"ch7 4ns",
    "addr:street":"Ffordd Y Blaenau Treuddyn",
    "iso:country":"GB",
    "sg:address":"Chapel House, Ffordd Y Blaenau, Treuddyn",
    "sg:city":"Mold",
    "sg:classifiers":[
        {
            "category":"Freight",
            "type":"Transportation"
        }
    ],
    "sg:postcode":"CH7 4NS",
    "sg:province":"Denbighshire",
    "sg:tags":[
        "haulage",
        "road"
    ],
    "wof:name":"M N P Haulage",
    "wof:placetype":"venue"
},
  "geometry": {"coordinates":[-3.1136989594,53.1132545471],"type":"Point"}
}