{
  "type": "Feature",
  "properties": {
    "iso:country":"GB",
    "sg:address":"8 Dorking Close",
    "sg:city":"Worcester Park",
    "sg:classifiers":[
        {
            "category":"Autos & Motor Vehicles",
            "subcategory":"Motorcycle Sales",
            "type":"Retail Goods"
        }
    ],
    "sg:phone":"+44 1932 866028",
    "sg:postcode":"KT4 8NN",
    "sg:province":"Surrey",
    "sg:tags":[
        "chauffeur",
        "driven",
        "car"
    ],
    "wof:name":"Conquest Cars Ltd.",
    "wof:placetype":"venue"
},
  "geometry": {"coordinates":[-0.2234939933,51.3776435852],"type":"Point"}
}