{
  "type": "Feature",
  "properties": {
    "addr:full":"83 Sandringham Road Doncaster South Yorkshire DN2 5JA",
    "addr:housenumber":"83",
    "addr:postcode":"dn2 5ja",
    "addr:street":"Sandringham Road",
    "iso:country":"GB",
    "sg:address":"83 Sandringham Road",
    "sg:city":"Doncaster",
    "sg:classifiers":[
        {
            "category":"Food & Beverages",
            "subcategory":"Meat & Fish",
            "type":"Retail Goods"
        }
    ],
    "sg:phone":"+44 1302 341876",
    "sg:postcode":"DN2 5JA",
    "sg:province":"South Yorkshire",
    "sg:tags":[
        "butcher"
    ],
    "wof:name":"Bob Mason's Meat Market",
    "wof:placetype":"venue"
},
  "geometry": {"coordinates":[-1.104961,53.527443],"type":"Point"}
}