{
  "type": "Feature",
  "properties": {
    "addr:full":"42 Division St Sheffield South Yorkshire S1 4GF",
    "addr:housenumber":"42",
    "addr:postcode":"s1 4gf",
    "addr:street":"Division St",
    "iso:country":"GB",
    "sg:address":"42 Division St",
    "sg:city":"Sheffield",
    "sg:classifiers":[
        {
            "category":"Professional",
            "subcategory":"Lawyer & Legal Services",
            "type":"Services"
        }
    ],
    "sg:phone":"+44 114 276 8884",
    "sg:postcode":"S1 4GF",
    "sg:province":"South Yorkshire",
    "sg:tags":[
        "solicitor"
    ],
    "wof:name":"Richard Prentis & Co",
    "wof:placetype":"venue"
},
  "geometry": {"coordinates":[-1.474221,53.380131],"type":"Point"}
}