{
  "type": "Feature",
  "properties": {
    "iso:country":"GB",
    "sg:address":"Whittagreen Garage, Chapelknowe Rd",
    "sg:city":"Motherwell",
    "sg:classifiers":[
        {
            "category":"Shopping",
            "subcategory":"Baby Store",
            "type":"Retail Goods"
        }
    ],
    "sg:phone":"+44 1698 862076",
    "sg:postcode":"ML1 5LE",
    "sg:province":"North Lanarkshire",
    "sg:tags":[
        "nursery",
        "accessory"
    ],
    "wof:name":"Novelty Kid Co The",
    "wof:placetype":"venue"
},
  "geometry": {"coordinates":[-3.9469599724,55.8031692505],"type":"Point"}
}