{
  "type": "Feature",
  "properties": {
    "iso:country":"GB",
    "sg:address":"Anchorage Quay",
    "sg:city":"Salford",
    "sg:classifiers":[
        {
            "category":"Insurance",
            "subcategory":"Insurance Agent",
            "type":"Services"
        }
    ],
    "sg:phone":"+44 161 930 2525",
    "sg:postcode":"M5 2XE",
    "sg:province":"Greater Manchester",
    "wof:name":"Royal Liver Assurance Ltd.",
    "wof:placetype":"venue"
},
  "geometry": {"coordinates":[-2.2860739231,53.4741210938],"type":"Point"}
}