{
  "type": "Feature",
  "properties": {
    "addr:full":"Hamilton Road Glasgow Glasgow City G71 7RX",
    "addr:postcode":"g71 7rx",
    "addr:street":"Hamilton Road",
    "iso:country":"GB",
    "sg:address":"Hamilton Road",
    "sg:city":"Glasgow",
    "sg:classifiers":[
        {
            "category":"Utilities",
            "subcategory":"Sewage",
            "type":"Services"
        }
    ],
    "sg:phone":"+44 141 771 9383",
    "sg:postcode":"G71 7RX",
    "sg:province":"Glasgow City",
    "sg:tags":[
        "disposal"
    ],
    "wof:name":"Daldoie Sewage Works",
    "wof:placetype":"venue"
},
  "geometry": {"coordinates":[-4.116758,55.837616],"type":"Point"}
}