{
  "type": "Feature",
  "properties": {
    "addr:full":"Point Clear Clacton-on-sea Essex CO16 8LJ",
    "addr:postcode":"co16 8lj",
    "iso:country":"GB",
    "sg:address":"Point Clear",
    "sg:city":"Clacton-on-sea",
    "sg:classifiers":[
        {
            "category":"Recreation",
            "subcategory":"Campground",
            "type":"Entertainment"
        }
    ],
    "sg:phone":"+44 1255 821652",
    "sg:postcode":"CO16 8LJ",
    "sg:province":"Essex",
    "sg:tags":[
        "caravan",
        "park"
    ],
    "wof:name":"Fletchers Caravan Site",
    "wof:placetype":"venue"
},
  "geometry": {"coordinates":[1.0246499777,51.7995185852],"type":"Point"}
}