{
  "type": "Feature",
  "properties": {
    "iso:country":"GB",
    "sg:address":"9 Hurlfield",
    "sg:city":"Dartford",
    "sg:classifiers":[
        {
            "category":"Building & Trades",
            "subcategory":"Construction",
            "type":"Services"
        }
    ],
    "sg:postcode":"DA2 7BH",
    "sg:province":"Kent",
    "sg:tags":[
        "builder"
    ],
    "wof:name":"T Draper",
    "wof:placetype":"venue"
},
  "geometry": {"coordinates":[0.2047470063,51.4278717041],"type":"Point"}
}