{
  "type": "Feature",
  "properties": {
    "iso:country":"GB",
    "sg:address":"4 Moorfield Road, Duxford",
    "sg:city":"Cambridge",
    "sg:classifiers":[
        {
            "category":"Shopping",
            "subcategory":"Antiques",
            "type":"Retail Goods"
        }
    ],
    "sg:postcode":"CB2 4PS",
    "sg:province":"Cambridgeshire",
    "wof:name":"Riro D Mooney",
    "wof:placetype":"venue"
},
  "geometry": {"coordinates":[0.159413,52.094685],"type":"Point"}
}