{
  "type": "Feature",
  "properties": {
    "addr:full":"Enfield House, 303 Burton Road Derby Derbyshire DE23 6AG",
    "addr:housenumber":"303",
    "addr:postcode":"de23 6ag",
    "addr:street":"Burton Road",
    "iso:country":"GB",
    "sg:address":"Enfield House, 303 Burton Road",
    "sg:city":"Derby",
    "sg:classifiers":[
        {
            "category":"Wholesale",
            "subcategory":"Computers",
            "type":"Manufacturing & Wholesale Goods"
        },
        {
            "category":"Professional",
            "subcategory":"Computer Services",
            "type":"Services"
        }
    ],
    "sg:phone":"+44 1332 363981",
    "sg:postcode":"DE23 6AG",
    "sg:province":"Derbyshire",
    "sg:tags":[
        "supplier",
        "consumables",
        "system",
        "software"
    ],
    "wof:name":"Evets Communications Ltd.",
    "wof:placetype":"venue"
},
  "geometry": {"coordinates":[-1.4900820255,52.9109115601],"type":"Point"}
}