{
  "type": "Feature",
  "properties": {
    "addr:full":"John Loftus House, Summer Road Thames Ditton Surrey KT7 0RD",
    "addr:postcode":"kt7 0rd",
    "addr:street":"Summer Road",
    "iso:country":"GB",
    "sg:address":"John Loftus House, Summer Road",
    "sg:city":"Thames Ditton",
    "sg:classifiers":[
        {
            "category":"Professional",
            "subcategory":"Engineering",
            "type":"Services"
        }
    ],
    "sg:postcode":"KT7 0RD",
    "sg:province":"Surrey",
    "sg:tags":[
        "consulting",
        "engineer"
    ],
    "wof:name":"Nucleus Consultants Ltd",
    "wof:placetype":"venue"
},
  "geometry": {"coordinates":[-0.3390620053,51.3963470459],"type":"Point"}
}