{
  "type": "Feature",
  "properties": {
    "iso:country":"GB",
    "sg:address":"High Street, Winslow",
    "sg:city":"Buckingham",
    "sg:classifiers":[
        {
            "category":"Autos & Motor Vehicles",
            "subcategory":"Fuel & Gas Station",
            "type":"Retail Goods"
        }
    ],
    "sg:phone":"+44 1296 714450",
    "sg:postcode":"MK18 3DR",
    "sg:province":"Buckinghamshire",
    "sg:tags":[
        "petrol",
        "filling"
    ],
    "wof:name":"Icham Ltd.",
    "wof:placetype":"venue"
},
  "geometry": {"coordinates":[-0.876619,51.898666],"type":"Point"}
}