{
  "type": "Feature",
  "properties": {
    "addr:full":"The Village Shop Newtown Powys SY16 4NU",
    "addr:postcode":"sy16 4nu",
    "iso:country":"GB",
    "sg:address":"The Village Shop",
    "sg:city":"Newtown",
    "sg:classifiers":[
        {
            "category":"Shopping",
            "subcategory":"Department Store",
            "type":"Retail Goods"
        }
    ],
    "sg:phone":"+44 1686 670650",
    "sg:postcode":"SY16 4NU",
    "sg:province":"Powys",
    "wof:name":"L & H Danson",
    "wof:placetype":"venue"
},
  "geometry": {"coordinates":[-3.3146119118,52.5127754211],"type":"Point"}
}