{
  "type": "Feature",
  "properties": {
    "iso:country":"GB",
    "sg:address":"76 Duke Street",
    "sg:city":"Barrow-in-furness",
    "sg:classifiers":[
        {
            "category":"Insurance",
            "subcategory":"Insurance Agent",
            "type":"Services"
        }
    ],
    "sg:phone":"+44 1229 820779",
    "sg:postcode":"LA14 1RX",
    "sg:province":"Cumbria",
    "wof:name":"Royal London Mutual Insurance Society (The)",
    "wof:placetype":"venue"
},
  "geometry": {"coordinates":[-3.229065,54.112827],"type":"Point"}
}