{
  "type": "Feature",
  "properties": {
    "addr:full":"3 Hemmel Courts, Brandon Durham Durham DH7 8QS",
    "addr:housenumber":"3",
    "addr:postcode":"dh7 8qs",
    "addr:street":"Hemmel Courts",
    "iso:country":"GB",
    "sg:address":"3 Hemmel Courts, Brandon",
    "sg:city":"Durham",
    "sg:classifiers":[
        {
            "category":"Building & Trades",
            "subcategory":"Construction",
            "type":"Services"
        }
    ],
    "sg:postcode":"DH7 8QS",
    "sg:province":"Durham",
    "sg:tags":[
        "roofing"
    ],
    "wof:name":"Abbey Roofing",
    "wof:placetype":"venue"
},
  "geometry": {"coordinates":[-1.6215590239,54.7500305176],"type":"Point"}
}