{
  "type": "Feature",
  "properties": {
    "addr:full":"12-16 Bury Old Road Manchester Greater Manchester M8 9JN",
    "addr:housenumber":"12-16",
    "addr:postcode":"m8 9jn",
    "addr:street":"Bury Old Road",
    "iso:country":"GB",
    "sg:address":"12-16 Bury Old Road",
    "sg:city":"Manchester",
    "sg:classifiers":[
        {
            "category":"Fast Food",
            "type":"Food & Drink"
        }
    ],
    "sg:phone":"+44 161 721 4260",
    "sg:postcode":"M8 9JN",
    "sg:province":"Greater Manchester",
    "sg:tags":[
        "away",
        "take"
    ],
    "wof:name":"McDonalds Restaurants Ltd.",
    "wof:placetype":"venue"
},
  "geometry": {"coordinates":[-2.244907,53.511803],"type":"Point"}
}