{
  "type": "Feature",
  "properties": {
    "iso:country":"GB",
    "sg:address":"378 Julian Rd",
    "sg:city":"Glenrothes",
    "sg:classifiers":[
        {
            "category":"Professional",
            "subcategory":"Advertising",
            "type":"Services"
        }
    ],
    "sg:phone":"+44 1592 742974",
    "sg:postcode":"KY7 6SS",
    "sg:province":"Fife",
    "sg:tags":[
        "distribution",
        "circular"
    ],
    "wof:name":"B & J Leaflet Delivery Service",
    "wof:placetype":"venue"
},
  "geometry": {"coordinates":[-3.1675078869,56.2076339722],"type":"Point"}
}