{
  "type": "Feature",
  "properties": {
    "iso:country":"GB",
    "sg:address":"99 Picton Street",
    "sg:city":"Maesteg",
    "sg:classifiers":[
        {
            "category":"Food & Beverages",
            "subcategory":"Fruits & Vegetables",
            "type":"Retail Goods"
        }
    ],
    "sg:phone":"+44 1656 737607",
    "sg:postcode":"CF34 0EW",
    "sg:province":"Bridgend",
    "sg:tags":[
        "greengrocer"
    ],
    "wof:name":"Fruit Delight",
    "wof:placetype":"venue"
},
  "geometry": {"coordinates":[-3.661338,51.620068],"type":"Point"}
}