{
  "type": "Feature",
  "properties": {
    "addr:full":"Brookside Farm, Brook La Kettering Northamptonshire NN16 8SJ",
    "addr:postcode":"nn16 8sj",
    "addr:street":"Brook La Kettering",
    "iso:country":"GB",
    "sg:address":"Brookside Farm, Brook La",
    "sg:city":"Kettering",
    "sg:classifiers":[
        {
            "category":"Farming",
            "subcategory":"Farm",
            "type":"Manufacturing & Wholesale Goods"
        }
    ],
    "sg:phone":"+44 1536 770337",
    "sg:postcode":"NN16 8SJ",
    "sg:province":"Northamptonshire",
    "sg:tags":[
        "mixed",
        "crop"
    ],
    "wof:name":"A C Clarke & Son",
    "wof:placetype":"venue"
},
  "geometry": {"coordinates":[-0.7258039713,52.3988342285],"type":"Point"}
}