{
  "type": "Feature",
  "properties": {
    "addr:full":"Unit 15 Padgets Lane, South Moons Moat Redditch Warwickshire B98 0RA",
    "addr:housenumber":"unit 15",
    "addr:postcode":"b98 0ra",
    "addr:street":"Padgets Lane South Moons",
    "iso:country":"GB",
    "sg:address":"Unit 15 Padgets Lane, South Moons Moat",
    "sg:city":"Redditch",
    "sg:classifiers":[
        {
            "category":"Shopping",
            "subcategory":"Stationery & Office Supplies",
            "type":"Retail Goods"
        }
    ],
    "sg:phone":"+44 1527 518888",
    "sg:postcode":"B98 0RA",
    "sg:province":"Warwickshire",
    "sg:tags":[
        "box",
        "carton"
    ],
    "wof:name":"MARCH PACKAGING (MIDLANDS) LTD",
    "wof:placetype":"venue"
},
  "geometry": {"coordinates":[-1.8988790512,52.3093185425],"type":"Point"}
}