{
  "type": "Feature",
  "properties": {
    "addr:full":"Cefn Rhiwlas, Penybanc Llandeilo Carmarthenshire SA19 7TB",
    "addr:postcode":"sa19 7tb",
    "iso:country":"GB",
    "sg:address":"Cefn Rhiwlas, Penybanc",
    "sg:city":"Llandeilo",
    "sg:classifiers":[
        {
            "category":"Farming",
            "subcategory":"Livestock Farm",
            "type":"Manufacturing & Wholesale Goods"
        },
        {
            "category":"Farming",
            "subcategory":"Farm",
            "type":"Manufacturing & Wholesale Goods"
        }
    ],
    "sg:phone":"+44 1558 823225",
    "sg:postcode":"SA19 7TB",
    "sg:province":"Carmarthenshire",
    "sg:tags":[
        "mixed",
        "crop",
        "others"
    ],
    "wof:name":"M L Harries",
    "wof:placetype":"venue"
},
  "geometry": {"coordinates":[-4.013379,51.89764],"type":"Point"}
}