{
  "type": "Feature",
  "properties": {
    "iso:country":"GB",
    "sg:address":"1 Bellerby Rise",
    "sg:city":"Luton",
    "sg:classifiers":[
        {
            "category":"Building & Trades",
            "subcategory":"Plumbing",
            "type":"Services"
        },
        {
            "category":"Building & Trades",
            "subcategory":"Construction",
            "type":"Services"
        }
    ],
    "sg:phone":"+44 1582 595215",
    "sg:postcode":"LU4 9DU",
    "sg:province":"Bedfordshire",
    "sg:tags":[
        "central",
        "installation",
        "system",
        "servicing",
        "heating"
    ],
    "wof:name":"Flame Heating",
    "wof:placetype":"venue"
},
  "geometry": {"coordinates":[-0.480817,51.911938],"type":"Point"}
}