{
  "type": "Feature",
  "properties": {
    "addr:full":"64 North Albert Street Fleetwood Lancashire FY7 6AR",
    "addr:housenumber":"64",
    "addr:postcode":"fy7 6ar",
    "addr:street":"North Albert Street",
    "iso:country":"GB",
    "sg:address":"64 North Albert Street",
    "sg:city":"Fleetwood",
    "sg:classifiers":[
        {
            "category":"Fast Food",
            "type":"Food & Drink"
        }
    ],
    "sg:phone":"+44 1253 874792",
    "sg:postcode":"FY7 6AR",
    "sg:province":"Lancashire",
    "sg:tags":[
        "away",
        "take"
    ],
    "wof:name":"Penny's Phone-A-Pizza",
    "wof:placetype":"venue"
},
  "geometry": {"coordinates":[-3.0083339214,53.9263458252],"type":"Point"}
}