{
  "type": "Feature",
  "properties": {
    "addr:full":"11 Garrell Rd Glasgow East Dunbartonshire G65 9JX",
    "addr:housenumber":"11",
    "addr:postcode":"g65 9jx",
    "addr:street":"Garrell Rd",
    "iso:country":"GB",
    "sg:address":"11 Garrell Rd",
    "sg:city":"Glasgow",
    "sg:classifiers":[
        {
            "category":"Home & Garden",
            "subcategory":"Household Appliances",
            "type":"Retail Goods"
        },
        {
            "category":"Manufacturing",
            "subcategory":"Electronics",
            "type":"Manufacturing & Wholesale Goods"
        }
    ],
    "sg:postcode":"G65 9JX",
    "sg:province":"East Dunbartonshire",
    "sg:tags":[
        "domestic",
        "oven",
        "microwave"
    ],
    "wof:name":"Edinburgh & Glasgow Microwaves Ltd",
    "wof:placetype":"venue"
},
  "geometry": {"coordinates":[-4.0637450218,55.9741897583],"type":"Point"}
}