{
  "type": "Feature",
  "properties": {
    "addr:full":"I M O Car Wash, Hadfield Road Cardiff Cardiff CF11 8AQ",
    "addr:postcode":"cf11 8aq",
    "addr:street":"Hadfield Road",
    "iso:country":"GB",
    "sg:address":"I M O Car Wash, Hadfield Road",
    "sg:city":"Cardiff",
    "sg:classifiers":[
        {
            "category":"Parking",
            "type":"Transportation"
        }
    ],
    "sg:phone":"+44 29 2038 4576",
    "sg:postcode":"CF11 8AQ",
    "sg:province":"Cardiff",
    "sg:tags":[
        "car",
        "valet"
    ],
    "wof:name":"Hadfield Valeting",
    "wof:placetype":"venue"
},
  "geometry": {"coordinates":[-3.2072799206,51.4694786072],"type":"Point"}
}