{
  "type": "Feature",
  "properties": {
    "addr:full":"Toft Farm, Wrangle Boston Lincolnshire PE22 9HB",
    "addr:postcode":"pe22 9hb",
    "addr:street":"Toft",
    "iso:country":"GB",
    "sg:address":"Toft Farm, Wrangle",
    "sg:city":"Boston",
    "sg:classifiers":[
        {
            "category":"Farming",
            "subcategory":"Livestock Farm",
            "type":"Manufacturing & Wholesale Goods"
        }
    ],
    "sg:phone":"+44 1205 870489",
    "sg:postcode":"PE22 9HB",
    "sg:province":"Lincolnshire",
    "sg:tags":[
        "others"
    ],
    "wof:name":"Eric Lawrence Booley",
    "wof:placetype":"venue"
},
  "geometry": {"coordinates":[0.126063,53.038956],"type":"Point"}
}