{
  "type": "Feature",
  "properties": {
    "iso:country":"GB",
    "sg:address":"Witham Place",
    "sg:city":"Boston",
    "sg:classifiers":[
        {
            "category":"Community Center",
            "subcategory":"Youth",
            "type":"Public Place"
        }
    ],
    "sg:phone":"+44 1205 369042",
    "sg:postcode":"PE21 6LQ",
    "sg:province":"Lincolnshire",
    "sg:tags":[
        "organisation",
        "centre"
    ],
    "wof:name":"Boston Youth Centre",
    "wof:placetype":"venue"
},
  "geometry": {"coordinates":[-0.026919,52.980213],"type":"Point"}
}