{
  "type": "Feature",
  "properties": {
    "addr:full":"Railway Arches, Avenue Rd Forest Gate Greater London E7 0LB",
    "addr:postcode":"e7 0lb",
    "addr:street":"Railway Arches Avenue Rd;Gate",
    "iso:country":"GB",
    "sg:address":"Railway Arches, Avenue Rd",
    "sg:city":"Forest Gate",
    "sg:classifiers":[
        {
            "category":"Autos & Motor Vehicles",
            "subcategory":"Auto Supplies",
            "type":"Retail Goods"
        }
    ],
    "sg:phone":"+44 20 8599 0278",
    "sg:postcode":"E7 0LB",
    "sg:province":"Greater London",
    "sg:tags":[
        "tyre"
    ],
    "wof:name":"Meads Tyres",
    "wof:placetype":"venue"
},
  "geometry": {"coordinates":[0.0243100002,51.5512809753],"type":"Point"}
}