{
  "type": "Feature",
  "properties": {
    "iso:country":"GB",
    "sg:address":"34-36 Gipsy Lane",
    "sg:city":"Leicester",
    "sg:classifiers":[
        {
            "category":"Real Estate",
            "subcategory":"Real Estate Services",
            "type":"Services"
        },
        {
            "category":"Building & Trades",
            "subcategory":"Equipment Rental",
            "type":"Services"
        }
    ],
    "sg:phone":"+44 116 266 2456",
    "sg:postcode":"LE4 6TD",
    "sg:province":"Leicestershire",
    "sg:tags":[
        "hire",
        "leasing",
        "plant",
        "machinery"
    ],
    "wof:name":"Terratruck Distribution Services Ltd",
    "wof:placetype":"venue"
},
  "geometry": {"coordinates":[-1.110517025,52.6557312012],"type":"Point"}
}