{
  "type": "Feature",
  "properties": {
    "addr:full":"Pratts Farm, Pratts Farm Lane, Little Waltham Chelmsford Essex CM3 3PR",
    "addr:postcode":"cm3 3pr",
    "addr:street":"Pratts Farm Lane",
    "iso:country":"GB",
    "sg:address":"Pratts Farm, Pratts Farm Lane, Little Waltham",
    "sg:city":"Chelmsford",
    "sg:classifiers":[
        {
            "category":"Sports & Exercise",
            "subcategory":"Golf",
            "type":"Entertainment"
        }
    ],
    "sg:phone":"+44 1245 361100",
    "sg:postcode":"CM3 3PR",
    "sg:province":"Essex",
    "sg:tags":[
        "club",
        "course"
    ],
    "wof:name":"Regiment Way Golf Centre",
    "wof:placetype":"venue"
},
  "geometry": {"coordinates":[0.4727190137,51.7901077271],"type":"Point"}
}