{
  "type": "Feature",
  "properties": {
    "iso:country":"GB",
    "sg:address":"Old Cottage, High St, Creaton",
    "sg:city":"Northampton",
    "sg:classifiers":[
        {
            "category":"Building & Trades",
            "subcategory":"Construction",
            "type":"Services"
        }
    ],
    "sg:phone":"+44 1604 505600",
    "sg:postcode":"NN6 8NA",
    "sg:province":"Northamptonshire",
    "sg:tags":[
        "conservation",
        "craft",
        "thatching"
    ],
    "wof:name":"R.J Farmer",
    "wof:placetype":"venue"
},
  "geometry": {"coordinates":[-0.965574,52.339424],"type":"Point"}
}