{
  "type": "Feature",
  "properties": {
    "addr:full":"205 Wheatfield Dr Bristol Gloucestershire BS32 9DE",
    "addr:housenumber":"205",
    "addr:postcode":"bs32 9de",
    "addr:street":"Wheatfield Dr",
    "iso:country":"GB",
    "sg:address":"205 Wheatfield Dr",
    "sg:city":"Bristol",
    "sg:classifiers":[
        {
            "category":"Professional",
            "subcategory":"Management & Consulting",
            "type":"Services"
        }
    ],
    "sg:phone":"+44 1454 201430",
    "sg:postcode":"BS32 9DE",
    "sg:province":"Gloucestershire",
    "sg:tags":[
        "marketing",
        "consultant"
    ],
    "wof:name":"Concept Marketing",
    "wof:placetype":"venue"
},
  "geometry": {"coordinates":[-2.54991,51.53764],"type":"Point"}
}