{
  "type": "Feature",
  "properties": {
    "addr:full":"24 Nobles Close, Grove Wantage Berkshire OX12 0NR",
    "addr:housenumber":"24",
    "addr:postcode":"ox12 0nr",
    "addr:street":"Nobles Close Grove",
    "iso:country":"GB",
    "sg:address":"24 Nobles Close, Grove",
    "sg:city":"Wantage",
    "sg:classifiers":[
        {
            "category":"Recreation",
            "subcategory":"Playground",
            "type":"Entertainment"
        },
        {
            "category":"Recreation",
            "type":"Entertainment"
        }
    ],
    "sg:phone":"+44 1235 768280",
    "sg:postcode":"OX12 0NR",
    "sg:province":"Berkshire",
    "sg:tags":[
        "hospitality",
        "corporate",
        "leisure"
    ],
    "wof:name":"Country & Highland Events",
    "wof:placetype":"venue"
},
  "geometry": {"coordinates":[-1.426517,51.611652],"type":"Point"}
}