{
  "type": "Feature",
  "properties": {
    "iso:country":"GB",
    "sg:address":"University Road, Highfield",
    "sg:city":"Southampton",
    "sg:classifiers":[
        {
            "category":"Education",
            "subcategory":"University",
            "type":"Public Place"
        }
    ],
    "sg:phone":"+44 23 8059 5000",
    "sg:postcode":"SO17 1BJ",
    "sg:province":"Hampshire",
    "sg:tags":[
        "medical",
        "school"
    ],
    "wof:name":"University of Southampton",
    "wof:placetype":"venue"
},
  "geometry": {"coordinates":[-1.396474,50.937565],"type":"Point"}
}