{
  "type": "Feature",
  "properties": {
    "iso:country":"GB",
    "sg:address":"1 Kelvin Way, Foyers",
    "sg:city":"Inverness",
    "sg:classifiers":[
        {
            "category":"Farming",
            "subcategory":"Farm",
            "type":"Manufacturing & Wholesale Goods"
        }
    ],
    "sg:phone":"+44 1456 486607",
    "sg:postcode":"IV2 6YB",
    "sg:province":"Highland",
    "sg:tags":[
        "hatchery"
    ],
    "wof:name":"Landcatch Ltd.",
    "wof:placetype":"venue"
},
  "geometry": {"coordinates":[-4.4905819893,57.2508277893],"type":"Point"}
}