{
  "type": "Feature",
  "properties": {
    "addr:full":"124 Caverleigh Way Worcester Park Surrey KT4 8DQ",
    "addr:housenumber":"124",
    "addr:postcode":"kt4 8dq",
    "addr:street":"Caverleigh Way",
    "iso:country":"GB",
    "sg:address":"124 Caverleigh Way",
    "sg:city":"Worcester Park",
    "sg:classifiers":[
        {
            "category":"Building & Trades",
            "subcategory":"Construction",
            "type":"Services"
        }
    ],
    "sg:phone":"+44 20 8337 0340",
    "sg:postcode":"KT4 8DQ",
    "sg:province":"Surrey",
    "sg:tags":[
        "builder"
    ],
    "wof:name":"T L M Building Decorating & Property Maintenance",
    "wof:placetype":"venue"
},
  "geometry": {"coordinates":[-0.238595,51.385921],"type":"Point"}
}