{
  "type": "Feature",
  "properties": {
    "addr:full":"16a Caedmon Rd Holloway Greater London N7 6DH",
    "addr:housenumber":"16a",
    "addr:postcode":"n7 6dh",
    "addr:street":"Caedmon Rd",
    "iso:country":"GB",
    "sg:address":"16a Caedmon Rd",
    "sg:city":"Holloway",
    "sg:classifiers":[
        {
            "category":"Professional",
            "subcategory":"Art Services",
            "type":"Services"
        }
    ],
    "sg:phone":"+44 20 7607 6766",
    "sg:postcode":"N7 6DH",
    "sg:province":"Greater London",
    "sg:tags":[
        "photographer"
    ],
    "wof:name":"Scan Photographic Services",
    "wof:placetype":"venue"
},
  "geometry": {"coordinates":[-0.112388,51.556084],"type":"Point"}
}