{
  "type": "Feature",
  "properties": {
    "iso:country":"GB",
    "sg:address":"19 New Street, Southowram",
    "sg:city":"Halifax",
    "sg:classifiers":[
        {
            "category":"Social Services",
            "subcategory":"Adult Care",
            "type":"Services"
        },
        {
            "category":"Government",
            "subcategory":"Office",
            "type":"Public Place"
        }
    ],
    "sg:phone":"+44 1422 354177",
    "sg:postcode":"HX3 9SW",
    "sg:province":"West Yorkshire",
    "sg:tags":[
        "housing",
        "local",
        "sheltered"
    ],
    "wof:name":"Calderdale Metropolitan Borough Council",
    "wof:placetype":"venue"
},
  "geometry": {"coordinates":[-1.8296409845,53.7086486816],"type":"Point"}
}