{
  "type": "Feature",
  "properties": {
    "iso:country":"GB",
    "sg:address":"Castle Hill, Curries Close, Douglas",
    "sg:city":"Lanark",
    "sg:classifiers":[
        {
            "category":"Food & Beverages",
            "subcategory":"Fruits & Vegetables",
            "type":"Retail Goods"
        }
    ],
    "sg:postcode":"ML11 0QN",
    "sg:province":"South Lanarkshire",
    "sg:tags":[
        "greengrocer"
    ],
    "wof:name":"J Bain & Son",
    "wof:placetype":"venue"
},
  "geometry": {"coordinates":[-3.868423,55.559071],"type":"Point"}
}