{
  "type": "Feature",
  "properties": {
    "addr:full":"106 Piccadilly West End Hampshire W1V 9FL",
    "addr:housenumber":"106",
    "addr:street":"Piccadilly",
    "iso:country":"GB",
    "sg:address":"106 Piccadilly",
    "sg:city":"West End",
    "sg:classifiers":[
        {
            "category":"Education",
            "subcategory":"Special Training",
            "type":"Public Place"
        }
    ],
    "sg:phone":"+44 20 7409 2252",
    "sg:postcode":"W1V 9FL",
    "sg:province":"Hampshire",
    "sg:tags":[
        "school",
        "language"
    ],
    "wof:name":"Intuition Languages",
    "wof:placetype":"venue"
},
  "geometry": {"coordinates":[-0.13899,51.50758],"type":"Point"}
}