{
  "type": "Feature",
  "properties": {
    "addr:full":"73 Hollywood Way Woodford Green Essex IG8 9LG",
    "addr:housenumber":"73",
    "addr:postcode":"ig8 9lg",
    "addr:street":"Hollywood Way",
    "iso:country":"GB",
    "sg:address":"73 Hollywood Way",
    "sg:city":"Woodford Green",
    "sg:classifiers":[
        {
            "category":"Building & Trades",
            "subcategory":"Construction",
            "type":"Services"
        }
    ],
    "sg:phone":"+44 20 8527 5466",
    "sg:postcode":"IG8 9LG",
    "sg:province":"Essex",
    "sg:tags":[
        "builder"
    ],
    "wof:name":"Parnone (Builders) Ltd.",
    "wof:placetype":"venue"
},
  "geometry": {"coordinates":[0.0063299998,51.605014801],"type":"Point"}
}