{
  "type": "Feature",
  "properties": {
    "addr:full":"17 Dalrymple Road London Greater London SE4 2BQ",
    "addr:housenumber":"17",
    "addr:postcode":"se4 2bq",
    "addr:street":"Dalrymple Road",
    "iso:country":"GB",
    "sg:address":"17 Dalrymple Road",
    "sg:city":"London",
    "sg:classifiers":[
        {
            "category":"Farming",
            "subcategory":"Nursery",
            "type":"Manufacturing & Wholesale Goods"
        }
    ],
    "sg:phone":"+44 20 8692 8227",
    "sg:postcode":"SE4 2BQ",
    "sg:province":"Greater London",
    "sg:tags":[
        "creche"
    ],
    "wof:name":"Tansib Independent School Ltd.",
    "wof:placetype":"venue"
},
  "geometry": {"coordinates":[-0.036103,51.457466],"type":"Point"}
}