{
  "type": "Feature",
  "properties": {
    "addr:full":"Hollies, Sandhutton Thirsk North Yorkshire YO7 4RW",
    "addr:postcode":"yo7 4rw",
    "iso:country":"GB",
    "sg:address":"Hollies, Sandhutton",
    "sg:city":"Thirsk",
    "sg:classifiers":[
        {
            "category":"Utilities",
            "subcategory":"Natural Gas",
            "type":"Services"
        }
    ],
    "sg:postcode":"YO7 4RW",
    "sg:province":"North Yorkshire",
    "sg:tags":[
        "control",
        "energy",
        "management",
        "system"
    ],
    "wof:name":"M B Wallace Contractors",
    "wof:placetype":"venue"
},
  "geometry": {"coordinates":[-1.4155590534,54.2323684692],"type":"Point"}
}