{
  "type": "Feature",
  "properties": {
    "addr:full":"St Andrews Road Basingstoke Hampshire RG22 6PS",
    "addr:postcode":"rg22 6ps",
    "addr:street":"St Andrews Road",
    "iso:country":"GB",
    "sg:address":"St Andrews Road",
    "sg:city":"Basingstoke",
    "sg:classifiers":[
        {
            "category":"Education",
            "subcategory":"School",
            "type":"Public Place"
        }
    ],
    "sg:phone":"+44 1256 322148",
    "sg:postcode":"RG22 6PS",
    "sg:province":"Hampshire",
    "sg:tags":[
        "local",
        "authority"
    ],
    "wof:name":"Limington House School",
    "wof:placetype":"venue"
},
  "geometry": {"coordinates":[-1.1127539873,51.2588653564],"type":"Point"}
}