{
  "type": "Feature",
  "properties": {
    "iso:country":"GB",
    "sg:address":"Lower Leigh Farm, Combe Martin",
    "sg:city":"Ilfracombe",
    "sg:classifiers":[
        {
            "category":"Farming",
            "subcategory":"Livestock Farm",
            "type":"Manufacturing & Wholesale Goods"
        }
    ],
    "sg:phone":"+44 1271 882379",
    "sg:postcode":"EX34 0NG",
    "sg:province":"Devon",
    "sg:tags":[
        "others"
    ],
    "wof:name":"R C Johns & Son",
    "wof:placetype":"venue"
},
  "geometry": {"coordinates":[-4.0259652138,51.2004013062],"type":"Point"}
}