{
  "type": "Feature",
  "properties": {
    "addr:full":"251a Oldfield Lane North Greenford Greater London UB6 8PX",
    "addr:housenumber":"251a",
    "addr:postcode":"ub6 8px",
    "addr:street":"Oldfield Lane North",
    "iso:country":"GB",
    "sg:address":"251a Oldfield Lane North",
    "sg:city":"Greenford",
    "sg:classifiers":[
        {
            "category":"Real Estate",
            "subcategory":"Surveying",
            "type":"Services"
        }
    ],
    "sg:phone":"+44 20 8813 0202",
    "sg:postcode":"UB6 8PX",
    "sg:province":"Greater London",
    "sg:tags":[
        "building",
        "surveyor"
    ],
    "wof:name":"Anthony Fieldhouse & Co",
    "wof:placetype":"venue"
},
  "geometry": {"coordinates":[-0.3464489877,51.5421028137],"type":"Point"}
}