{
  "type": "Feature",
  "properties": {
    "addr:full":"26 Lyndhurst Gardens, Hampstead London Greater London NW3 5NW",
    "addr:housenumber":"26",
    "addr:postcode":"nw3 5nw",
    "addr:street":"Lyndhurst Gardens",
    "iso:country":"GB",
    "sg:address":"26 Lyndhurst Gardens, Hampstead",
    "sg:city":"London",
    "sg:classifiers":[
        {
            "category":"Education",
            "subcategory":"Special Training",
            "type":"Public Place"
        }
    ],
    "sg:phone":"+44 20 7435 3646",
    "sg:postcode":"NW3 5NW",
    "sg:province":"Greater London",
    "sg:tags":[
        "product",
        "centre"
    ],
    "wof:name":"Maria Montessori Training Organisation",
    "wof:placetype":"venue"
},
  "geometry": {"coordinates":[-0.171545,51.552315],"type":"Point"}
}