{
  "type": "Feature",
  "properties": {
    "iso:country":"GB",
    "sg:address":"Graham Road",
    "sg:city":"Bexleyheath",
    "sg:classifiers":[
        {
            "category":"Education",
            "subcategory":"School",
            "type":"Public Place"
        }
    ],
    "sg:phone":"+44 20 8303 5696",
    "sg:postcode":"DA6 7DA",
    "sg:province":"Kent",
    "sg:tags":[
        "local",
        "authority"
    ],
    "wof:name":"Bexleyheath School",
    "wof:placetype":"venue"
},
  "geometry": {"coordinates":[0.1432989985,51.4580154419],"type":"Point"}
}