{
  "type": "Feature",
  "properties": {
    "addr:full":"Greenway, Carlton-in-lindrick Worksop Nottinghamshire S81 9EY",
    "addr:postcode":"s81 9ey",
    "iso:country":"GB",
    "sg:address":"Greenway, Carlton-in-lindrick",
    "sg:city":"Worksop",
    "sg:classifiers":[
        {
            "category":"Food & Beverages",
            "subcategory":"Meat & Fish",
            "type":"Retail Goods"
        }
    ],
    "sg:phone":"+44 1909 730238",
    "sg:postcode":"S81 9EY",
    "sg:province":"Nottinghamshire",
    "sg:tags":[
        "butcher"
    ],
    "wof:name":"W & M Wright",
    "wof:placetype":"venue"
},
  "geometry": {"coordinates":[-1.1113699675,53.35546875],"type":"Point"}
}