{
  "type": "Feature",
  "properties": {
    "addr:full":"2 Seaton Street Middlesbrough North Yorkshire TS1 3NQ",
    "addr:housenumber":"2",
    "addr:postcode":"ts1 3nq",
    "addr:street":"Seaton Street",
    "iso:country":"GB",
    "sg:address":"2 Seaton Street",
    "sg:city":"Middlesbrough",
    "sg:classifiers":[
        {
            "category":"Food & Beverages",
            "subcategory":"Bakery",
            "type":"Retail Goods"
        }
    ],
    "sg:phone":"+44 1642 246179",
    "sg:postcode":"TS1 3NQ",
    "sg:province":"North Yorkshire",
    "sg:tags":[
        "baker"
    ],
    "wof:name":"Paul Morgans Bakery Ltd.",
    "wof:placetype":"venue"
},
  "geometry": {"coordinates":[-1.232078,54.569698],"type":"Point"}
}