{
  "type": "Feature",
  "properties": {
    "addr:full":"Kenton Lane, Stanmore Harrow Greater London HA3 6AQ",
    "addr:postcode":"ha3 6aq",
    "addr:street":"Kenton Lane",
    "iso:country":"GB",
    "sg:address":"Kenton Lane, Stanmore",
    "sg:city":"Harrow",
    "sg:classifiers":[
        {
            "category":"Building & Trades",
            "subcategory":"Construction",
            "type":"Services"
        }
    ],
    "sg:phone":"+44 20 8954 3018",
    "sg:postcode":"HA3 6AQ",
    "sg:province":"Greater London",
    "sg:tags":[
        "joiner",
        "carpenter"
    ],
    "wof:name":"Cabinet Makers",
    "wof:placetype":"venue"
},
  "geometry": {"coordinates":[-0.3282839954,51.6049804688],"type":"Point"}
}