{
  "type": "Feature",
  "properties": {
    "addr:full":"27 Columbus Ravine Scarborough North Yorkshire YO12 7JR",
    "addr:housenumber":"27",
    "addr:postcode":"yo12 7jr",
    "addr:street":"Columbus Ravine",
    "iso:country":"GB",
    "sg:address":"27 Columbus Ravine",
    "sg:city":"Scarborough",
    "sg:classifiers":[
        {
            "category":"Utilities",
            "subcategory":"Natural Gas",
            "type":"Services"
        }
    ],
    "sg:phone":"+44 1723 365647",
    "sg:postcode":"YO12 7JR",
    "sg:province":"North Yorkshire",
    "sg:tags":[
        "supplier"
    ],
    "wof:name":"B A T A",
    "wof:placetype":"venue"
},
  "geometry": {"coordinates":[-0.4107919931,54.2836380005],"type":"Point"}
}