{
  "type": "Feature",
  "properties": {
    "addr:full":"High Street, Rudston Driffield East Riding of Yorkshire YO25 4UB",
    "addr:postcode":"yo25 4ub",
    "addr:street":"High Street",
    "iso:country":"GB",
    "sg:address":"High Street, Rudston",
    "sg:city":"Driffield",
    "sg:classifiers":[
        {
            "category":"Bars & Pubs",
            "type":"Food & Drink"
        }
    ],
    "sg:phone":"+44 1262 420259",
    "sg:postcode":"YO25 4UB",
    "sg:province":"East Riding of Yorkshire",
    "sg:tags":[
        "pubs",
        "inn"
    ],
    "wof:name":"Bosville Arms",
    "wof:placetype":"venue"
},
  "geometry": {"coordinates":[-0.326778,54.09507],"type":"Point"}
}