{
  "type": "Feature",
  "properties": {
    "addr:full":"C/o H K M Harlow Khandhia Mistry, The Old Mill, 9 Soar La Leicester Leicestershire LE3 5DE",
    "addr:housenumber":"9",
    "addr:postcode":"le3 5de",
    "addr:street":"C;M;Soar La Leicester",
    "iso:country":"GB",
    "sg:address":"C/o H K M Harlow Khandhia Mistry, The Old Mill, 9 Soar La",
    "sg:city":"Leicester",
    "sg:classifiers":[
        {
            "category":"Professional",
            "subcategory":"Engineering",
            "type":"Services"
        }
    ],
    "sg:postcode":"LE3 5DE",
    "sg:province":"Leicestershire",
    "sg:tags":[
        "precision",
        "engineer"
    ],
    "wof:name":"Lesan Engineering Ltd",
    "wof:placetype":"venue"
},
  "geometry": {"coordinates":[-1.1421400309,52.6390800476],"type":"Point"}
}