{
  "type": "Feature",
  "properties": {
    "addr:full":"37 Atherley Road Shanklin Isle of Wight PO37 7AU",
    "addr:housenumber":"37",
    "addr:postcode":"po37 7au",
    "addr:street":"Atherley Road",
    "iso:country":"GB",
    "sg:address":"37 Atherley Road",
    "sg:city":"Shanklin",
    "sg:classifiers":[
        {
            "category":"Restaurant",
            "type":"Food & Drink"
        }
    ],
    "sg:phone":"+44 1983 866451",
    "sg:postcode":"PO37 7AU",
    "sg:province":"Isle of Wight",
    "wof:name":"Keats Kitchen",
    "wof:placetype":"venue"
},
  "geometry": {"coordinates":[-1.176258,50.633137],"type":"Point"}
}