{
  "type": "Feature",
  "properties": {
    "addr:full":"80a High St, Nailsea Bristol Somerset BS48 1AS",
    "addr:housenumber":"80a",
    "addr:postcode":"bs48 1as",
    "addr:street":"High St",
    "iso:country":"GB",
    "sg:address":"80a High St, Nailsea",
    "sg:city":"Bristol",
    "sg:classifiers":[
        {
            "category":"Banks & Credit Unions",
            "subcategory":"Bank",
            "type":"Services"
        }
    ],
    "sg:phone":"+44 1275 794788",
    "sg:postcode":"BS48 1AS",
    "sg:province":"Somerset",
    "sg:tags":[
        "broker",
        "mortgage"
    ],
    "wof:name":"Paradigm Mortgage Co Ltd",
    "wof:placetype":"venue"
},
  "geometry": {"coordinates":[-2.7539949417,51.4345092773],"type":"Point"}
}