{
  "type": "Feature",
  "properties": {
    "iso:country":"GB",
    "sg:address":"52 High Street, Bugbrooke",
    "sg:city":"Northampton",
    "sg:classifiers":[
        {
            "category":"Professional",
            "subcategory":"Art Services",
            "type":"Services"
        }
    ],
    "sg:postcode":"NN7 3PG",
    "sg:province":"Buckinghamshire",
    "sg:tags":[
        "consultant",
        "design"
    ],
    "wof:name":"J S P Design Associates",
    "wof:placetype":"venue"
},
  "geometry": {"coordinates":[-0.941075,52.174767],"type":"Point"}
}