{
  "type": "Feature",
  "properties": {
    "addr:full":"38 Provident Street Coventry West Midlands CV5 6ED",
    "addr:housenumber":"38",
    "addr:postcode":"cv5 6ed",
    "addr:street":"Provident Street",
    "iso:country":"GB",
    "sg:address":"38 Provident Street",
    "sg:city":"Coventry",
    "sg:classifiers":[
        {
            "category":"Professional",
            "subcategory":"Business Services",
            "type":"Services"
        }
    ],
    "sg:phone":"+44 871 733 3846",
    "sg:postcode":"CV5 6ED",
    "sg:province":"West Midlands",
    "sg:tags":[
        "import",
        "export",
        "agent"
    ],
    "wof:name":"Supla Ltd.",
    "wof:placetype":"venue"
},
  "geometry": {"coordinates":[-1.531823,52.397839],"type":"Point"}
}