{
  "type": "Feature",
  "properties": {
    "iso:country":"GB",
    "sg:address":"12 Bells Hill Grn, Stoke Poges",
    "sg:city":"Slough",
    "sg:classifiers":[
        {
            "category":"Professional",
            "subcategory":"Art Services",
            "type":"Services"
        }
    ],
    "sg:phone":"+44 1753 669444",
    "sg:postcode":"SL2 4BY",
    "sg:province":"Berkshire",
    "sg:tags":[
        "framing"
    ],
    "wof:name":"Trebor Art",
    "wof:placetype":"venue"
},
  "geometry": {"coordinates":[-0.585224,51.547337],"type":"Point"}
}