{
  "type": "Feature",
  "properties": {
    "addr:full":"80 Mornant Ave, Hartford Northwich Cheshire CW8 2FQ",
    "addr:housenumber":"80",
    "addr:postcode":"cw8 2fq",
    "addr:street":"Mornant Ave",
    "iso:country":"GB",
    "sg:address":"80 Mornant Ave, Hartford",
    "sg:city":"Northwich",
    "sg:classifiers":[
        {
            "category":"Sports & Exercise",
            "subcategory":"Gym",
            "type":"Entertainment"
        }
    ],
    "sg:postcode":"CW8 2FQ",
    "sg:province":"Cheshire",
    "sg:tags":[
        "fitness",
        "health",
        "centre"
    ],
    "wof:name":"Benbow,Sue,",
    "wof:placetype":"venue"
},
  "geometry": {"coordinates":[-2.550743,53.239323],"type":"Point"}
}