{
  "type": "Feature",
  "properties": {
    "addr:full":"15 Briar Fields Swindon Wiltshire SN1 2QN",
    "addr:housenumber":"15",
    "addr:postcode":"sn1 2qn",
    "addr:street":"Briar Fields",
    "iso:country":"GB",
    "sg:address":"15 Briar Fields",
    "sg:city":"Swindon",
    "sg:classifiers":[
        {
            "category":"Health Services",
            "subcategory":"Podiatrist",
            "type":"Services"
        }
    ],
    "sg:postcode":"SN1 2QN",
    "sg:province":"Wiltshire",
    "sg:tags":[
        "podiatrists",
        "chiropodist"
    ],
    "wof:name":"T E Woodfield",
    "wof:placetype":"venue"
},
  "geometry": {"coordinates":[-1.7671560049,51.5680885315],"type":"Point"}
}