{
  "type": "Feature",
  "properties": {
    "addr:full":"39 Church Road, Bishops Cleeve Cheltenham Gloucestershire GL52 8LP",
    "addr:housenumber":"39",
    "addr:postcode":"gl52 8lp",
    "addr:street":"Church Road",
    "iso:country":"GB",
    "sg:address":"39 Church Road, Bishops Cleeve",
    "sg:city":"Cheltenham",
    "sg:classifiers":[
        {
            "category":"Food & Beverages",
            "subcategory":"Meat & Fish",
            "type":"Retail Goods"
        }
    ],
    "sg:postcode":"GL52 8LP",
    "sg:province":"Gloucestershire",
    "sg:tags":[
        "butcher"
    ],
    "wof:name":"David Preece in Bishops Cleeve",
    "wof:placetype":"venue"
},
  "geometry": {"coordinates":[-2.0595378876,51.9473304749],"type":"Point"}
}