{
  "type": "Feature",
  "properties": {
    "iso:country":"GB",
    "sg:address":"17 High Street",
    "sg:city":"Arundel",
    "sg:classifiers":[
        {
            "category":"Food & Beverages",
            "subcategory":"Liquor & Beverages",
            "type":"Retail Goods"
        }
    ],
    "sg:phone":"+44 1903 882288",
    "sg:postcode":"BN18 9AD",
    "sg:province":"West Sussex",
    "sg:tags":[
        "beer",
        "spirit",
        "wines"
    ],
    "wof:name":"Pallant Wines Ltd.",
    "wof:placetype":"venue"
},
  "geometry": {"coordinates":[-0.553598,50.854237],"type":"Point"}
}