{
  "type": "Feature",
  "properties": {
    "iso:country":"GB",
    "sg:address":"Summerhayes, Exeter Rd",
    "sg:city":"Honiton",
    "sg:classifiers":[
        {
            "category":"Health Services",
            "subcategory":"Health Practitioner",
            "type":"Services"
        }
    ],
    "sg:phone":"+44 1404 46319",
    "sg:postcode":"EX14 8AL",
    "sg:province":"Devon",
    "sg:tags":[
        "osteopath"
    ],
    "wof:name":"C J Norgate",
    "wof:placetype":"venue"
},
  "geometry": {"coordinates":[-3.1969060898,50.7973861694],"type":"Point"}
}