{
  "type": "Feature",
  "properties": {
    "iso:country":"GB",
    "sg:address":"Ruskin Drive, Dentons Grn",
    "sg:city":"St Helens",
    "sg:classifiers":[
        {
            "category":"Organizations",
            "subcategory":"Membership Organization",
            "type":"Services"
        }
    ],
    "sg:phone":"+44 1744 22893",
    "sg:postcode":"WA10 6RP",
    "sg:province":"Merseyside",
    "sg:tags":[
        "club"
    ],
    "wof:name":"Ruskin Drive Social Club",
    "wof:placetype":"venue"
},
  "geometry": {"coordinates":[-2.754989,53.459435],"type":"Point"}
}