{
  "type": "Feature",
  "properties": {
    "addr:full":"Rear Of 101 Tottenham Lane London Greater London N8 9BG",
    "addr:postcode":"n8 9bg",
    "addr:street":"Tottenham Lane",
    "iso:country":"GB",
    "sg:address":"Rear Of 101 Tottenham Lane",
    "sg:city":"London",
    "sg:classifiers":[
        {
            "category":"Education",
            "subcategory":"Preschool",
            "type":"Public Place"
        }
    ],
    "sg:phone":"+44 20 8340 8119",
    "sg:postcode":"N8 9BG",
    "sg:province":"Greater London",
    "sg:tags":[
        "pre",
        "school",
        "playgroups",
        "pre-school"
    ],
    "wof:name":"101 Playgroup",
    "wof:placetype":"venue"
},
  "geometry": {"coordinates":[-0.1168899983,51.5833206177],"type":"Point"}
}