{
  "type": "Feature",
  "properties": {
    "addr:full":"Ewell Road, Cheam Sutton Surrey SM3 8AB",
    "addr:postcode":"sm3 8ab",
    "addr:street":"Ewell Road",
    "iso:country":"GB",
    "sg:address":"Ewell Road, Cheam",
    "sg:city":"Sutton",
    "sg:classifiers":[
        {
            "category":"Education",
            "subcategory":"School",
            "type":"Public Place"
        },
        {
            "category":"Government",
            "subcategory":"Office",
            "type":"Public Place"
        }
    ],
    "sg:phone":"+44 20 8394 1308",
    "sg:postcode":"SM3 8AB",
    "sg:province":"Surrey",
    "sg:tags":[
        "college",
        "local"
    ],
    "wof:name":"Nonsuch High School for Girls",
    "wof:placetype":"venue"
},
  "geometry": {"coordinates":[-0.216712,51.357628],"type":"Point"}
}