{
  "type": "Feature",
  "properties": {
    "iso:country":"GB",
    "sg:address":"68a Elm Gro",
    "sg:city":"Hayling Island",
    "sg:classifiers":[
        {
            "category":"Autos & Motor Vehicles",
            "subcategory":"Auto Supplies",
            "type":"Retail Goods"
        },
        {
            "category":"Shopping",
            "type":"Retail Goods"
        }
    ],
    "sg:phone":"+44 23 9246 2523",
    "sg:postcode":"PO11 9EF",
    "sg:province":"Hampshire",
    "sg:tags":[
        "car",
        "part",
        "accessory"
    ],
    "wof:name":"Motorcare Centre",
    "wof:placetype":"venue"
},
  "geometry": {"coordinates":[-0.977043,50.790607],"type":"Point"}
}