{
  "type": "Feature",
  "properties": {
    "addr:full":"Unit 4, Scottish Road Services Depot, Irvine Road Kilmarnock East Ayrshire KA3 2RH",
    "addr:housenumber":"unit 4",
    "addr:postcode":"ka3 2rh",
    "addr:street":"Scottish Road;Depot Irvine Road",
    "iso:country":"GB",
    "sg:address":"Unit 4, Scottish Road Services Depot, Irvine Road",
    "sg:city":"Kilmarnock",
    "sg:classifiers":[
        {
            "category":"Wholesale",
            "subcategory":"Scrap",
            "type":"Manufacturing & Wholesale Goods"
        }
    ],
    "sg:phone":"+44 1563 541205",
    "sg:postcode":"KA3 2RH",
    "sg:province":"East Ayrshire",
    "sg:tags":[
        "waste",
        "metal"
    ],
    "wof:name":"Smillie Metallics Ltd.",
    "wof:placetype":"venue"
},
  "geometry": {"coordinates":[-4.52768,55.63868],"type":"Point"}
}