{
  "type": "Feature",
  "properties": {
    "addr:full":"Fitzroy Park, Highgate London Greater London N6 6HT",
    "addr:postcode":"n6 6ht",
    "addr:street":"Highgate",
    "iso:country":"GB",
    "sg:address":"Fitzroy Park, Highgate",
    "sg:city":"London",
    "sg:classifiers":[
        {
            "category":"Arena",
            "subcategory":"Sports Club",
            "type":"Entertainment"
        }
    ],
    "sg:phone":"+44 20 8340 2038",
    "sg:postcode":"N6 6HT",
    "sg:province":"Greater London",
    "wof:name":"North London Bowling Club",
    "wof:placetype":"venue"
},
  "geometry": {"coordinates":[-0.149844,51.571449],"type":"Point"}
}