{
  "type": "Feature",
  "properties": {
    "iso:country":"GB",
    "sg:address":"28 Poulton Av",
    "sg:city":"Sutton",
    "sg:classifiers":[
        {
            "category":"Retail",
            "subcategory":"Repair Shop",
            "type":"Services"
        }
    ],
    "sg:phone":"+44 20 8647 0815",
    "sg:postcode":"SM1 3PY",
    "sg:province":"Surrey",
    "sg:tags":[
        "maintenance"
    ],
    "wof:name":"A G Holton",
    "wof:placetype":"venue"
},
  "geometry": {"coordinates":[-0.176215,51.372208],"type":"Point"}
}