{
  "type": "Feature",
  "properties": {
    "addr:full":"152 High Road London Greater London N22 6EB",
    "addr:housenumber":"152",
    "addr:postcode":"n22 6eb",
    "addr:street":"High Road",
    "iso:country":"GB",
    "sg:address":"152 High Road",
    "sg:city":"London",
    "sg:classifiers":[
        {
            "category":"Fast Food",
            "type":"Food & Drink"
        }
    ],
    "sg:phone":"+44 20 8881 4664",
    "sg:postcode":"N22 6EB",
    "sg:province":"Greater London",
    "sg:tags":[
        "away",
        "take"
    ],
    "wof:name":"Perfect Fried Chicken",
    "wof:placetype":"venue"
},
  "geometry": {"coordinates":[-0.1089880019,51.5962219238],"type":"Point"}
}