{
  "type": "Feature",
  "properties": {
    "addr:full":"106 Stoke Newington Church Street London Greater London N16 0LA",
    "addr:housenumber":"106",
    "addr:postcode":"n16 0la",
    "addr:street":"Stoke Newington Church Street",
    "iso:country":"GB",
    "sg:address":"106 Stoke Newington Church Street",
    "sg:city":"London",
    "sg:classifiers":[
        {
            "category":"Manufacturing",
            "subcategory":"Textiles",
            "type":"Manufacturing & Wholesale Goods"
        }
    ],
    "sg:phone":"+44 20 7254 1435",
    "sg:postcode":"N16 0LA",
    "sg:province":"Greater London",
    "sg:tags":[
        "knitwear"
    ],
    "wof:name":"Eutrex Textiles Mills",
    "wof:placetype":"venue"
},
  "geometry": {"coordinates":[-0.079131,51.562195],"type":"Point"}
}