{
  "type": "Feature",
  "properties": {
    "iso:country":"GB",
    "sg:address":"113 Mersey Dr, Whitefield",
    "sg:city":"Manchester",
    "sg:classifiers":[
        {
            "category":"Home & Garden",
            "subcategory":"Carpets & Floor Coverings",
            "type":"Retail Goods"
        }
    ],
    "sg:postcode":"M45 8LN",
    "sg:province":"Lancashire",
    "sg:tags":[
        "cleaner",
        "upholstery"
    ],
    "wof:name":"Thomlinson,Gary,",
    "wof:placetype":"venue"
},
  "geometry": {"coordinates":[-2.274216,53.556023],"type":"Point"}
}