{
  "type": "Feature",
  "properties": {
    "addr:full":"Russell Square Telford Shropshire TF7 5BB",
    "addr:postcode":"tf7 5bb",
    "addr:street":"Russell Square",
    "iso:country":"GB",
    "sg:address":"Russell Square",
    "sg:city":"Telford",
    "sg:classifiers":[
        {
            "category":"Communications",
            "type":"Services"
        }
    ],
    "sg:phone":"+44 1952 587444",
    "sg:postcode":"TF7 5BB",
    "sg:province":"Shropshire",
    "sg:tags":[
        "tv",
        "video",
        "radio"
    ],
    "wof:name":"Bargain Music",
    "wof:placetype":"venue"
},
  "geometry": {"coordinates":[-2.4510641098,52.6373901367],"type":"Point"}
}