{
  "type": "Feature",
  "properties": {
    "addr:full":"244 Bellhouse Rd Sheffield South Yorkshire S5 6HT",
    "addr:housenumber":"244",
    "addr:postcode":"s5 6ht",
    "addr:street":"Bellhouse Rd",
    "iso:country":"GB",
    "sg:address":"244 Bellhouse Rd",
    "sg:city":"Sheffield",
    "sg:classifiers":[
        {
            "category":"Building & Trades",
            "subcategory":"Construction",
            "type":"Services"
        }
    ],
    "sg:phone":"+44 114 245 0360",
    "sg:postcode":"S5 6HT",
    "sg:province":"South Yorkshire",
    "sg:tags":[
        "builder"
    ],
    "wof:name":"A B L Builders",
    "wof:placetype":"venue"
},
  "geometry": {"coordinates":[-1.4431630373,53.4227638245],"type":"Point"}
}