{
  "type": "Feature",
  "properties": {
    "addr:full":"155 Chiswick High Rd, Chiswick Chiswick Greater London W4 2DT",
    "addr:housenumber":"155",
    "addr:postcode":"w4 2dt",
    "addr:street":"Chiswick High Rd",
    "iso:country":"GB",
    "sg:address":"155 Chiswick High Rd, Chiswick",
    "sg:city":"Chiswick",
    "sg:classifiers":[
        {
            "category":"Professional",
            "subcategory":"Lawyer & Legal Services",
            "type":"Services"
        }
    ],
    "sg:phone":"+44 20 8400 7000",
    "sg:postcode":"W4 2DT",
    "sg:province":"Greater London",
    "sg:tags":[
        "solicitor"
    ],
    "wof:name":"Bruce Weir Webber With Robsons",
    "wof:placetype":"venue"
},
  "geometry": {"coordinates":[-0.2546530068,51.4928588867],"type":"Point"}
}