{
  "type": "Feature",
  "properties": {
    "iso:country":"GB",
    "sg:address":"Bullivant St",
    "sg:city":"Poplar",
    "sg:classifiers":[
        {
            "category":"Education",
            "subcategory":"School",
            "type":"Public Place"
        }
    ],
    "sg:phone":"+44 20 7987 2778",
    "sg:postcode":"E14 0ER",
    "sg:province":"Greater London",
    "sg:tags":[
        "local",
        "authority"
    ],
    "wof:name":"Woolmore Primary School",
    "wof:placetype":"venue"
},
  "geometry": {"coordinates":[-0.0165589992,51.5089416504],"type":"Point"}
}