{
  "type": "Feature",
  "properties": {
    "addr:full":"Manywells Ho, Pankridge St Farnham Hampshire GU10 5QU",
    "addr:postcode":"gu10 5qu",
    "addr:street":"St",
    "iso:country":"GB",
    "sg:address":"Manywells Ho, Pankridge St",
    "sg:city":"Farnham",
    "sg:classifiers":[
        {
            "category":"Professional",
            "subcategory":"Management & Consulting",
            "type":"Services"
        }
    ],
    "sg:phone":"+44 1252 851944",
    "sg:postcode":"GU10 5QU",
    "sg:province":"Hampshire",
    "sg:tags":[
        "consultant",
        "business"
    ],
    "wof:name":"Lea Consultancy",
    "wof:placetype":"venue"
},
  "geometry": {"coordinates":[-0.8008300066,51.2143211365],"type":"Point"}
}