{
  "type": "Feature",
  "properties": {
    "addr:full":"369a Oxford Street London Greater London W1C 2JN",
    "addr:housenumber":"369a",
    "addr:postcode":"w1c 2jn",
    "addr:street":"Oxford Street",
    "iso:country":"GB",
    "sg:address":"369a Oxford Street",
    "sg:city":"London",
    "sg:classifiers":[
        {
            "category":"Banks & Credit Unions",
            "subcategory":"Bureau De Change",
            "type":"Services"
        }
    ],
    "sg:phone":"+44 20 7408 0673",
    "sg:postcode":"W1C 2JN",
    "sg:province":"Greater London",
    "wof:name":"T T T Foreign Exchange Corporation",
    "wof:placetype":"venue"
},
  "geometry": {"coordinates":[-0.1482789963,51.5144996643],"type":"Point"}
}