{
  "type": "Feature",
  "properties": {
    "iso:country":"GB",
    "sg:address":"1a Queen Sq",
    "sg:city":"Bath",
    "sg:classifiers":[
        {
            "category":"Health Services",
            "subcategory":"Dentist",
            "type":"Services"
        }
    ],
    "sg:phone":"+44 1225 424336",
    "sg:postcode":"BA1 2HA",
    "sg:province":"Bath and North East Somerset",
    "wof:name":"I M Midgley",
    "wof:placetype":"venue"
},
  "geometry": {"coordinates":[-2.3629601002,51.3837013245],"type":"Point"}
}