{
  "type": "Feature",
  "properties": {
    "addr:full":"37 Prince Regent Street Stockton-on-tees Durham TS18 1DF",
    "addr:housenumber":"37",
    "addr:postcode":"ts18 1df",
    "addr:street":"Prince Regent Street",
    "iso:country":"GB",
    "sg:address":"37 Prince Regent Street",
    "sg:city":"Stockton-on-tees",
    "sg:classifiers":[
        {
            "category":"Bars & Pubs",
            "subcategory":"Nightclub",
            "type":"Food & Drink"
        }
    ],
    "sg:postcode":"TS18 1DF",
    "sg:province":"Durham",
    "sg:tags":[
        "club",
        "night"
    ],
    "wof:name":"Intime",
    "wof:placetype":"venue"
},
  "geometry": {"coordinates":[-1.3148020506,54.563419342],"type":"Point"}
}