{
  "type": "Feature",
  "properties": {
    "addr:full":"Apollo House, Chapel Place Ramsgate Kent CT11 9SA",
    "addr:postcode":"ct11 9sa",
    "addr:street":"Apollo;Chapel Place Ramsgate",
    "iso:country":"GB",
    "sg:address":"Apollo House, Chapel Place",
    "sg:city":"Ramsgate",
    "sg:classifiers":[
        {
            "category":"Social Services",
            "type":"Services"
        }
    ],
    "sg:phone":"+44 1843 587976",
    "sg:postcode":"CT11 9SA",
    "sg:province":"Kent",
    "wof:name":"Ramsgate Young Offenders Team",
    "wof:placetype":"venue"
},
  "geometry": {"coordinates":[1.4161649942,51.3356018066],"type":"Point"}
}