{
  "type": "Feature",
  "properties": {
    "addr:full":"86 Causewayside Edinburgh City of Edinburgh EH9 1PY",
    "addr:housenumber":"86",
    "addr:postcode":"eh9 1py",
    "addr:street":"Causewayside",
    "iso:country":"GB",
    "sg:address":"86 Causewayside",
    "sg:city":"Edinburgh",
    "sg:classifiers":[
        {
            "category":"Wholesale",
            "subcategory":"Music Publishers",
            "type":"Manufacturing & Wholesale Goods"
        }
    ],
    "sg:phone":"+44 131 668 3366",
    "sg:postcode":"EH9 1PY",
    "sg:province":"City of Edinburgh",
    "sg:tags":[
        "record"
    ],
    "wof:name":"R E L Records Ltd.",
    "wof:placetype":"venue"
},
  "geometry": {"coordinates":[-3.181341,55.938484],"type":"Point"}
}