{
  "type": "Feature",
  "properties": {
    "iso:country":"GB",
    "sg:address":"Rear Of 553 Aylestone Rd",
    "sg:city":"Leicester",
    "sg:classifiers":[
        {
            "category":"Retail",
            "subcategory":"Auto Repair",
            "type":"Services"
        }
    ],
    "sg:phone":"+44 116 283 9512",
    "sg:postcode":"LE2 8TD",
    "sg:province":"Leicestershire",
    "sg:tags":[
        "modification",
        "garage"
    ],
    "wof:name":"R Wynd Motor Engineers",
    "wof:placetype":"venue"
},
  "geometry": {"coordinates":[-1.1546740532,52.6029434204],"type":"Point"}
}