{
  "type": "Feature",
  "properties": {
    "addr:full":"Unit 3, St Marks Mews Brighton East Sussex BN2 5JJ",
    "addr:housenumber":"unit 3",
    "addr:postcode":"bn2 5jj",
    "addr:street":"St Marks Mews",
    "iso:country":"GB",
    "sg:address":"Unit 3, St Marks Mews",
    "sg:city":"Brighton",
    "sg:classifiers":[
        {
            "category":"Retail",
            "subcategory":"Auto Repair",
            "type":"Services"
        }
    ],
    "sg:phone":"+44 1273 693866",
    "sg:postcode":"BN2 5JJ",
    "sg:province":"East Sussex",
    "sg:tags":[
        "modification",
        "garage"
    ],
    "wof:name":"John Moore Auto Repairs",
    "wof:placetype":"venue"
},
  "geometry": {"coordinates":[-0.112959,50.817211],"type":"Point"}
}