{
  "type": "Feature",
  "properties": {
    "iso:country":"GB",
    "sg:address":"Norton Canes Docks, Lime Lane",
    "sg:city":"Walsall",
    "sg:classifiers":[
        {
            "category":"Marine",
            "type":"Transportation"
        }
    ],
    "sg:phone":"+44 1543 374370",
    "sg:postcode":"WS3 5AP",
    "sg:province":"Staffordshire",
    "sg:tags":[
        "inland",
        "waterway",
        "river"
    ],
    "wof:name":"Canal Transport Services Ltd.",
    "wof:placetype":"venue"
},
  "geometry": {"coordinates":[-1.97204,52.657459],"type":"Point"}
}