{
  "type": "Feature",
  "properties": {
    "iso:country":"GB",
    "sg:address":"Garden Studios, 11-15 Betterton Street",
    "sg:city":"London",
    "sg:classifiers":[
        {
            "category":"Organizations",
            "subcategory":"Community Association",
            "type":"Services"
        }
    ],
    "sg:phone":"+44 20 7470 8771",
    "sg:postcode":"WC2H 9BP",
    "sg:province":"Greater London",
    "sg:tags":[
        "relation",
        "public"
    ],
    "wof:name":"The Lippin Co. Ltd.",
    "wof:placetype":"venue"
},
  "geometry": {"coordinates":[-0.12351,51.515079],"type":"Point"}
}