{
  "type": "Feature",
  "properties": {
    "addr:full":"Chancery Lane Surgery, Chancery La Nuneaton Leicestershire CV10 0PB",
    "addr:postcode":"cv10 0pb",
    "addr:street":"La",
    "iso:country":"GB",
    "sg:address":"Chancery Lane Surgery, Chancery La",
    "sg:city":"Nuneaton",
    "sg:classifiers":[
        {
            "category":"Health Services",
            "subcategory":"Doctor",
            "type":"Services"
        }
    ],
    "sg:phone":"+44 24 7639 4766",
    "sg:postcode":"CV10 0PB",
    "sg:province":"Leicestershire",
    "sg:tags":[
        "practitioners"
    ],
    "wof:name":"Sidhu, B A L",
    "wof:placetype":"venue"
},
  "geometry": {"coordinates":[-1.520129,52.536999],"type":"Point"}
}