{
  "type": "Feature",
  "properties": {
    "addr:full":"8 Mull Street London Greater London SE1 2BA",
    "addr:housenumber":"8",
    "addr:postcode":"se1 2ba",
    "addr:street":"Mull Street",
    "iso:country":"GB",
    "sg:address":"8 Mull Street",
    "sg:city":"London",
    "sg:classifiers":[
        {
            "category":"Manufacturing",
            "subcategory":"Food",
            "type":"Manufacturing & Wholesale Goods"
        }
    ],
    "sg:phone":"+44 20 7213 9800",
    "sg:postcode":"SE1 2BA",
    "sg:province":"Greater London",
    "sg:tags":[
        "mnfr",
        "drink",
        "soft"
    ],
    "wof:name":"T & T Beverages Ltd.",
    "wof:placetype":"venue"
},
  "geometry": {"coordinates":[-0.090388,51.545338],"type":"Point"}
}