{
  "type": "Feature",
  "properties": {
    "addr:full":"3rd Floor, Granby Buildings Leicester Leicestershire LE1 6EH",
    "addr:housenumber":"3rd floor granby buildings",
    "addr:postcode":"le1 6eh",
    "iso:country":"GB",
    "sg:address":"3rd Floor, Granby Buildings",
    "sg:city":"Leicester",
    "sg:classifiers":[
        {
            "category":"Social Services",
            "subcategory":"Retirement Home",
            "type":"Services"
        }
    ],
    "sg:phone":"+44 116 255 8866",
    "sg:postcode":"LE1 6EH",
    "sg:province":"Leicestershire",
    "sg:tags":[
        "care"
    ],
    "wof:name":"BNA",
    "wof:placetype":"venue"
},
  "geometry": {"coordinates":[-1.1310100555,52.634059906],"type":"Point"}
}