{
  "type": "Feature",
  "properties": {
    "iso:country":"GB",
    "sg:address":"Unit 14d, Norman Way, Severn Bridge Industrial Estate",
    "sg:city":"Caldicot",
    "sg:classifiers":[
        {
            "category":"Wholesale",
            "subcategory":"Motor Vehicles",
            "type":"Manufacturing & Wholesale Goods"
        }
    ],
    "sg:phone":"+44 1291 424180",
    "sg:postcode":"NP26 5PT",
    "sg:province":"Monmouthshire",
    "sg:tags":[
        "aircraft",
        "spare"
    ],
    "wof:name":"Jetspares International Ltd.",
    "wof:placetype":"venue"
},
  "geometry": {"coordinates":[-2.735409,51.587524],"type":"Point"}
}