{
  "type": "Feature",
  "properties": {
    "iso:country":"GB",
    "sg:address":"223a Hatfield Road",
    "sg:city":"St Albans",
    "sg:classifiers":[
        {
            "category":"Freight",
            "type":"Transportation"
        },
        {
            "category":"Military Area",
            "subcategory":"Air Force Base",
            "type":"Public Place"
        }
    ],
    "sg:phone":"+44 1727 867909",
    "sg:postcode":"AL1 4TB",
    "sg:province":"Hertfordshire",
    "sg:tags":[
        "taxi",
        "hire",
        "haulage",
        "private",
        "road",
        "transport"
    ],
    "wof:name":"Albans Cars",
    "wof:placetype":"venue"
},
  "geometry": {"coordinates":[-0.309991,51.752121],"type":"Point"}
}