{
  "type": "Feature",
  "properties": {
    "addr:full":"Main Street, Stenhousemuir Larbert Falkirk FK5 4BL",
    "addr:postcode":"fk5 4bl",
    "addr:street":"Main Street",
    "iso:country":"GB",
    "sg:address":"Main Street, Stenhousemuir",
    "sg:city":"Larbert",
    "sg:classifiers":[
        {
            "category":"Professional",
            "subcategory":"Computer Services",
            "type":"Services"
        },
        {
            "category":"Government",
            "subcategory":"Office",
            "type":"Public Place"
        }
    ],
    "sg:phone":"+44 1324 503338",
    "sg:postcode":"FK5 4BL",
    "sg:province":"Falkirk",
    "sg:tags":[
        "information",
        "local"
    ],
    "wof:name":"Stenhousemuir One Stop Shop",
    "wof:placetype":"venue"
},
  "geometry": {"coordinates":[-3.8026061058,56.0326118469],"type":"Point"}
}