{
  "type": "Feature",
  "properties": {
    "iso:country":"GB",
    "sg:address":"29 Fire Station Square",
    "sg:city":"Salford",
    "sg:classifiers":[
        {
            "category":"Communications",
            "type":"Services"
        }
    ],
    "sg:postcode":"M5 4NZ",
    "sg:province":"Greater Manchester",
    "sg:tags":[
        "broadcasting"
    ],
    "wof:name":"Sorted",
    "wof:placetype":"venue"
},
  "geometry": {"coordinates":[-2.272485,53.483574],"type":"Point"}
}