{
  "type": "Feature",
  "properties": {
    "iso:country":"GB",
    "sg:address":"241 Wellesley Road, Methil",
    "sg:city":"Leven",
    "sg:classifiers":[
        {
            "category":"Insurance",
            "subcategory":"Insurance Agent",
            "type":"Services"
        }
    ],
    "sg:phone":"+44 1333 421018",
    "sg:postcode":"KY8 3BN",
    "sg:province":"Fife",
    "sg:tags":[
        "broker"
    ],
    "wof:name":"Cameron Nicol Insurance",
    "wof:placetype":"venue"
},
  "geometry": {"coordinates":[-3.014619112,56.1857452393],"type":"Point"}
}