{
  "type": "Feature",
  "properties": {
    "iso:country":"GB",
    "sg:address":"Cornwallis Road",
    "sg:city":"Oxford",
    "sg:classifiers":[
        {
            "category":"Arena",
            "subcategory":"Sports Club",
            "type":"Entertainment"
        }
    ],
    "sg:phone":"+44 1865 779329",
    "sg:postcode":"OX3 8LL",
    "sg:province":"Oxfordshire",
    "wof:name":"Florence Park Social Club Ltd.",
    "wof:placetype":"venue"
},
  "geometry": {"coordinates":[-1.2295490503,51.735004425],"type":"Point"}
}