{
  "type": "Feature",
  "properties": {
    "iso:country":"GB",
    "sg:address":"Whitby Abbey, East Cliff",
    "sg:city":"Whitby",
    "sg:classifiers":[
        {
            "category":"Landmark",
            "subcategory":"Tourist Attraction",
            "type":"Public Place"
        }
    ],
    "sg:phone":"+44 1947 603568",
    "sg:postcode":"YO22 4JT",
    "sg:province":"North Yorkshire",
    "sg:tags":[
        "interest"
    ],
    "wof:name":"English Heritage",
    "wof:placetype":"venue"
},
  "geometry": {"coordinates":[-0.535124,54.434509],"type":"Point"}
}