{
  "type": "Feature",
  "properties": {
    "addr:full":"Nedging Tye Service Station Ipswich Suffolk IP7 7BN",
    "addr:postcode":"ip7 7bn",
    "iso:country":"GB",
    "sg:address":"Nedging Tye Service Station",
    "sg:city":"Ipswich",
    "sg:classifiers":[
        {
            "category":"Retail",
            "subcategory":"Auto Repair",
            "type":"Services"
        }
    ],
    "sg:postcode":"IP7 7BN",
    "sg:province":"Suffolk",
    "sg:tags":[
        "modification",
        "garage"
    ],
    "wof:name":"A & S Chandler",
    "wof:placetype":"venue"
},
  "geometry": {"coordinates":[0.9494050145,52.1085014343],"type":"Point"}
}