{
  "type": "Feature",
  "properties": {
    "iso:country":"GB",
    "sg:address":"98 High St",
    "sg:city":"Colchester",
    "sg:classifiers":[
        {
            "category":"Fast Food",
            "type":"Food & Drink"
        }
    ],
    "sg:postcode":"CO5 9AA",
    "sg:province":"Essex",
    "sg:tags":[
        "away",
        "take"
    ],
    "wof:name":"Miah,Abthar,",
    "wof:placetype":"venue"
},
  "geometry": {"coordinates":[0.699962,51.83659],"type":"Point"}
}