{
  "type": "Feature",
  "properties": {
    "addr:full":"230 Cheddon Road Taunton Somerset TA2 7AY",
    "addr:housenumber":"230",
    "addr:postcode":"ta2 7ay",
    "addr:street":"Cheddon Road",
    "iso:country":"GB",
    "sg:address":"230 Cheddon Road",
    "sg:city":"Taunton",
    "sg:classifiers":[
        {
            "category":"Building & Trades",
            "subcategory":"Construction",
            "type":"Services"
        }
    ],
    "sg:postcode":"TA2 7AY",
    "sg:province":"Somerset",
    "sg:tags":[
        "decorator",
        "painter"
    ],
    "wof:name":"W Bristow Painter & Decorator",
    "wof:placetype":"venue"
},
  "geometry": {"coordinates":[-3.1011528969,51.0336647034],"type":"Point"}
}