{
  "type": "Feature",
  "properties": {
    "iso:country":"GB",
    "sg:address":"121 High Street",
    "sg:city":"Cambridge",
    "sg:classifiers":[
        {
            "category":"Manufacturing",
            "subcategory":"Building Materials",
            "type":"Manufacturing & Wholesale Goods"
        }
    ],
    "sg:phone":"+44 1223 870711",
    "sg:postcode":"CB2 5QB",
    "sg:province":"Cambridgeshire",
    "sg:tags":[
        "concrete",
        "product"
    ],
    "wof:name":"Peytons Pavings",
    "wof:placetype":"venue"
},
  "geometry": {"coordinates":[0.085109,52.142521],"type":"Point"}
}