{
  "type": "Feature",
  "properties": {
    "iso:country":"GB",
    "sg:address":"7 Hall St",
    "sg:city":"Willenhall",
    "sg:classifiers":[
        {
            "category":"Home & Garden",
            "subcategory":"Home Furnishings",
            "type":"Retail Goods"
        }
    ],
    "sg:phone":"+44 1902 631212",
    "sg:postcode":"WV13 1PL",
    "sg:province":"West Midlands",
    "sg:tags":[
        "blind",
        "curtain",
        "fitting"
    ],
    "wof:name":"G Woollery",
    "wof:placetype":"venue"
},
  "geometry": {"coordinates":[-2.052249,52.587421],"type":"Point"}
}