{
  "type": "Feature",
  "properties": {
    "addr:full":"71 North Valley Road Colne Lancashire BB8 9AQ",
    "addr:housenumber":"71",
    "addr:postcode":"bb8 9aq",
    "addr:street":"North Valley Road",
    "iso:country":"GB",
    "sg:address":"71 North Valley Road",
    "sg:city":"Colne",
    "sg:classifiers":[
        {
            "category":"Food & Beverages",
            "subcategory":"Liquor & Beverages",
            "type":"Retail Goods"
        },
        {
            "category":"Food & Beverages",
            "subcategory":"Groceries & Convenience Stores",
            "type":"Retail Goods"
        }
    ],
    "sg:phone":"+44 1282 860440",
    "sg:postcode":"BB8 9AQ",
    "sg:province":"Lancashire",
    "sg:tags":[
        "beer",
        "spirit",
        "wines"
    ],
    "wof:name":"Headline News Ltd",
    "wof:placetype":"venue"
},
  "geometry": {"coordinates":[-2.1770009995,53.8575935364],"type":"Point"}
}