{
  "type": "Feature",
  "properties": {
    "iso:country":"GB",
    "sg:address":"London Road, Anesbury",
    "sg:city":"Salisbury",
    "sg:classifiers":[
        {
            "category":"Autos & Motor Vehicles",
            "subcategory":"Automobile Sales",
            "type":"Retail Goods"
        }
    ],
    "sg:phone":"+44 1980 626111",
    "sg:postcode":"SP4 7EQ",
    "sg:province":"Hampshire",
    "sg:tags":[
        "car"
    ],
    "wof:name":"The Village Car Co.",
    "wof:placetype":"venue"
},
  "geometry": {"coordinates":[-1.772159,51.176556],"type":"Point"}
}