{
  "type": "Feature",
  "properties": {
    "addr:full":"2 The Old Mill, River Road Arundel West Sussex BN18 9JR",
    "addr:housenumber":"2",
    "addr:postcode":"bn18 9jr",
    "addr:street":"The Old Mill River Road",
    "iso:country":"GB",
    "sg:address":"2 The Old Mill, River Road",
    "sg:city":"Arundel",
    "sg:classifiers":[
        {
            "category":"Social Services",
            "type":"Services"
        }
    ],
    "sg:phone":"+44 1903 884498",
    "sg:postcode":"BN18 9JR",
    "sg:province":"West Sussex",
    "sg:tags":[
        "disability"
    ],
    "wof:name":"Southern Mobility Centre",
    "wof:placetype":"venue"
},
  "geometry": {"coordinates":[-0.5545889735,50.8548355103],"type":"Point"}
}