{
  "type": "Feature",
  "properties": {
    "addr:full":"63 Osborne Road Farnborough Hampshire GU14 6AP",
    "addr:housenumber":"63",
    "addr:postcode":"gu14 6ap",
    "addr:street":"Osborne Road",
    "iso:country":"GB",
    "sg:address":"63 Osborne Road",
    "sg:city":"Farnborough",
    "sg:classifiers":[
        {
            "category":"Shopping",
            "subcategory":"Stationery & Office Supplies",
            "type":"Retail Goods"
        }
    ],
    "sg:phone":"+44 1252 544457",
    "sg:postcode":"GU14 6AP",
    "sg:province":"Hampshire",
    "sg:tags":[
        "recording",
        "machine",
        "time"
    ],
    "wof:name":"Allday Time Systems Ltd.",
    "wof:placetype":"venue"
},
  "geometry": {"coordinates":[-0.752761,51.275517],"type":"Point"}
}