{
  "type": "Feature",
  "properties": {
    "addr:full":"1 Cedar Court, Taylor Business Park Warrington Cheshire WA3 6BT",
    "addr:housenumber":"1",
    "addr:postcode":"wa3 6bt",
    "addr:street":"Cedar Court",
    "iso:country":"GB",
    "sg:address":"1 Cedar Court, Taylor Business Park",
    "sg:city":"Warrington",
    "sg:classifiers":[
        {
            "category":"Retail",
            "subcategory":"Storage",
            "type":"Services"
        }
    ],
    "sg:phone":"+44 1925 767670",
    "sg:postcode":"WA3 6BT",
    "sg:province":"Cheshire",
    "sg:tags":[
        "household",
        "removal"
    ],
    "wof:name":"Storage Management (Data Services) Ltd.",
    "wof:placetype":"venue"
},
  "geometry": {"coordinates":[-2.5146698952,53.4461708069],"type":"Point"}
}