{
  "type": "Feature",
  "properties": {
    "iso:country":"GB",
    "sg:address":"204-206 Terminus Road",
    "sg:city":"Eastbourne",
    "sg:classifiers":[
        {
            "category":"Shopping",
            "subcategory":"Clothing, Apparel, & Fashions",
            "type":"Retail Goods"
        }
    ],
    "sg:postcode":"BN21 3DF",
    "sg:province":"East Sussex",
    "sg:tags":[
        "shop"
    ],
    "wof:name":"Elegant Lady",
    "wof:placetype":"venue"
},
  "geometry": {"coordinates":[0.289018,50.767296],"type":"Point"}
}