{
  "type": "Feature",
  "properties": {
    "iso:country":"GB",
    "sg:address":"12 High Street",
    "sg:city":"Lymington",
    "sg:classifiers":[
        {
            "category":"Travel",
            "subcategory":"Travel Agent",
            "type":"Entertainment"
        }
    ],
    "sg:phone":"+44 1590 677077",
    "sg:postcode":"SO41 9YH",
    "sg:province":"Hampshire",
    "sg:tags":[
        "agency",
        "activity"
    ],
    "wof:name":"Atkins Travel Ltd",
    "wof:placetype":"venue"
},
  "geometry": {"coordinates":[-1.539079,50.758762],"type":"Point"}
}