{
  "type": "Feature",
  "properties": {
    "addr:full":"Clarkehouse Rd Sheffield South Yorkshire S10 2LN",
    "addr:postcode":"s10 2ln",
    "addr:street":"Clarkehouse Rd",
    "iso:country":"GB",
    "sg:address":"Clarkehouse Rd",
    "sg:city":"Sheffield",
    "sg:classifiers":[
        {
            "category":"Landmark",
            "subcategory":"Tourist Attraction",
            "type":"Public Place"
        }
    ],
    "sg:phone":"+44 114 267 1115",
    "sg:postcode":"S10 2LN",
    "sg:province":"South Yorkshire",
    "sg:tags":[
        "interest"
    ],
    "wof:name":"Sheffield Botanical Gardens",
    "wof:placetype":"venue"
},
  "geometry": {"coordinates":[-1.4925090075,53.3768844604],"type":"Point"}
}