{
  "type": "Feature",
  "properties": {
    "addr:full":"93 Rudyard Avenue Stockton On Tees Durham TS19 9LF",
    "addr:housenumber":"93",
    "addr:postcode":"ts19 9lf",
    "addr:street":"Rudyard Avenue",
    "iso:country":"GB",
    "sg:address":"93 Rudyard Avenue",
    "sg:city":"Stockton On Tees",
    "sg:classifiers":[
        {
            "category":"Health Services",
            "subcategory":"Podiatrist",
            "type":"Services"
        }
    ],
    "sg:phone":"+44 1642 893840",
    "sg:postcode":"TS19 9LF",
    "sg:province":"Durham",
    "sg:tags":[
        "podiatrists",
        "chiropodist"
    ],
    "wof:name":"D O'Connor",
    "wof:placetype":"venue"
},
  "geometry": {"coordinates":[-1.345335,54.589302],"type":"Point"}
}