{
  "type": "Feature",
  "properties": {
    "addr:full":"Gamston District Centre, Lingsbarr Road, Gamston Nottingham Nottinghamshire NG2 6PS",
    "addr:postcode":"ng2 6ps",
    "addr:street":"Lingsbarr Road",
    "iso:country":"GB",
    "sg:address":"Gamston District Centre, Lingsbarr Road, Gamston",
    "sg:city":"Nottingham",
    "sg:classifiers":[
        {
            "category":"Food & Beverages",
            "subcategory":"Supermarket",
            "type":"Retail Goods"
        }
    ],
    "sg:phone":"+44 115 981 1787",
    "sg:postcode":"NG2 6PS",
    "sg:province":"Nottinghamshire",
    "wof:name":"Safeway Stores Ltd.",
    "wof:placetype":"venue"
},
  "geometry": {"coordinates":[-1.103499,52.927338],"type":"Point"}
}