{
  "type": "Feature",
  "properties": {
    "addr:full":"1 Bradford Way, Acton London Greater London W3 7SP",
    "addr:housenumber":"1",
    "addr:postcode":"w3 7sp",
    "addr:street":"Bradford Way",
    "iso:country":"GB",
    "sg:address":"1 Bradford Way, Acton",
    "sg:city":"London",
    "sg:classifiers":[
        {
            "category":"Wholesale",
            "subcategory":"Machinery & Supplies",
            "type":"Manufacturing & Wholesale Goods"
        }
    ],
    "sg:postcode":"W3 7SP",
    "sg:province":"Greater London",
    "sg:tags":[
        "theatrical"
    ],
    "wof:name":"Road Runner Film Services",
    "wof:placetype":"venue"
},
  "geometry": {"coordinates":[-0.25643,51.505009],"type":"Point"}
}