{
  "type": "Feature",
  "properties": {
    "addr:full":"1 Dudnance Lane, Pool Redruth Cornwall TR15 3QT",
    "addr:housenumber":"1",
    "addr:postcode":"tr15 3qt",
    "addr:street":"Dudnance Lane",
    "iso:country":"GB",
    "sg:address":"1 Dudnance Lane, Pool",
    "sg:city":"Redruth",
    "sg:classifiers":[
        {
            "category":"Home & Garden",
            "subcategory":"Building Materials",
            "type":"Retail Goods"
        }
    ],
    "sg:phone":"+44 1209 217177",
    "sg:postcode":"TR15 3QT",
    "sg:province":"Cornwall",
    "sg:tags":[
        "insulation",
        "installers"
    ],
    "wof:name":"Shield Insulation Services Ltd",
    "wof:placetype":"venue"
},
  "geometry": {"coordinates":[-5.274422,50.223057],"type":"Point"}
}