{
  "type": "Feature",
  "properties": {
    "addr:full":"Bonshaw Farm, Stewarton Kilmarnock East Ayrshire KA3 3EQ",
    "addr:postcode":"ka3 3eq",
    "addr:street":"East",
    "iso:country":"GB",
    "sg:address":"Bonshaw Farm, Stewarton",
    "sg:city":"Kilmarnock",
    "sg:classifiers":[
        {
            "category":"Retail",
            "subcategory":"Auto Repair",
            "type":"Services"
        }
    ],
    "sg:postcode":"KA3 3EQ",
    "sg:province":"East Ayrshire",
    "sg:tags":[
        "modification",
        "garage"
    ],
    "wof:name":"Hastings,Eric,",
    "wof:placetype":"venue"
},
  "geometry": {"coordinates":[-4.5715198517,55.6656799316],"type":"Point"}
}