{
  "type": "Feature",
  "properties": {
    "iso:country":"GB",
    "sg:address":"109 Corporation Rd",
    "sg:city":"Grimsby",
    "sg:classifiers":[
        {
            "category":"Retail",
            "subcategory":"Repair Shop",
            "type":"Services"
        }
    ],
    "sg:phone":"+44 1472 269010",
    "sg:postcode":"DN31 1UR",
    "sg:province":"Lincolnshire",
    "sg:tags":[
        "upholsterer"
    ],
    "wof:name":"Silk Force Design Ltd",
    "wof:placetype":"venue"
},
  "geometry": {"coordinates":[-0.092466,53.571171],"type":"Point"}
}