{
  "type": "Feature",
  "properties": {
    "addr:full":"Borders Farm, Borders Lane Etchingham East Sussex TN19 7AF",
    "addr:postcode":"tn19 7af",
    "addr:street":"Borders Lane",
    "iso:country":"GB",
    "sg:address":"Borders Farm, Borders Lane",
    "sg:city":"Etchingham",
    "sg:classifiers":[
        {
            "category":"Farming",
            "subcategory":"Dairy Farm",
            "type":"Manufacturing & Wholesale Goods"
        },
        {
            "category":"Farming",
            "subcategory":"Livestock Farm",
            "type":"Manufacturing & Wholesale Goods"
        }
    ],
    "sg:phone":"+44 1580 819493",
    "sg:postcode":"TN19 7AF",
    "sg:province":"East Sussex",
    "sg:tags":[
        "others",
        "farmer"
    ],
    "wof:name":"La Riviere Ltd",
    "wof:placetype":"venue"
},
  "geometry": {"coordinates":[0.4416419864,51.0093803406],"type":"Point"}
}