{
  "type": "Feature",
  "properties": {
    "addr:full":"3 Branwell Drive, Haworth Keighley North Yorkshire BD22 8HG",
    "addr:housenumber":"3",
    "addr:postcode":"bd22 8hg",
    "addr:street":"Branwell Drive",
    "iso:country":"GB",
    "sg:address":"3 Branwell Drive, Haworth",
    "sg:city":"Keighley",
    "sg:classifiers":[
        {
            "category":"Professional",
            "subcategory":"Lawyer & Legal Services",
            "type":"Services"
        }
    ],
    "sg:phone":"+44 1535 646164",
    "sg:postcode":"BD22 8HG",
    "sg:province":"North Yorkshire",
    "wof:name":"Northern Employment Law Consultants",
    "wof:placetype":"venue"
},
  "geometry": {"coordinates":[-1.950618,53.834755],"type":"Point"}
}