{
  "type": "Feature",
  "properties": {
    "addr:full":"201 The Broadway London Greater London NW9 7DE",
    "addr:housenumber":"201",
    "addr:postcode":"nw9 7de",
    "addr:street":"The Broadway",
    "iso:country":"GB",
    "sg:address":"201 The Broadway",
    "sg:city":"London",
    "sg:classifiers":[
        {
            "category":"Place Of Worship",
            "type":"Public Place"
        }
    ],
    "sg:phone":"+44 20 8202 1000",
    "sg:postcode":"NW9 7DE",
    "sg:province":"Greater London",
    "wof:name":"Gayatri Mandir",
    "wof:placetype":"venue"
},
  "geometry": {"coordinates":[-0.24064,51.578239],"type":"Point"}
}