{
  "type": "Feature",
  "properties": {
    "iso:country":"GB",
    "sg:address":"Odams (westown), Ide",
    "sg:city":"Exeter",
    "sg:classifiers":[
        {
            "category":"Building & Trades",
            "subcategory":"Plumbing",
            "type":"Services"
        },
        {
            "category":"Home & Garden",
            "subcategory":"Hardware",
            "type":"Retail Goods"
        }
    ],
    "sg:phone":"+44 1392 811597",
    "sg:postcode":"EX2 9TG",
    "sg:province":"Devon",
    "sg:tags":[
        "merchant",
        "equipment",
        "plumbers'",
        "heating"
    ],
    "wof:name":"J Voysey Clearview Stoves",
    "wof:placetype":"venue"
},
  "geometry": {"coordinates":[-3.556267,50.705021],"type":"Point"}
}