{
  "type": "Feature",
  "properties": {
    "addr:full":"27 Melton Rd Oakham Leicestershire LE15 6AX",
    "addr:housenumber":"27",
    "addr:postcode":"le15 6ax",
    "addr:street":"Melton Rd",
    "iso:country":"GB",
    "sg:address":"27 Melton Rd",
    "sg:city":"Oakham",
    "sg:classifiers":[
        {
            "category":"Professional",
            "type":"Services"
        }
    ],
    "sg:postcode":"LE15 6AX",
    "sg:province":"Leicestershire",
    "sg:tags":[
        "shopfitters"
    ],
    "wof:name":"Lexas Shopfitting",
    "wof:placetype":"venue"
},
  "geometry": {"coordinates":[-0.733213,52.671036],"type":"Point"}
}