{
  "type": "Feature",
  "properties": {
    "iso:country":"GB",
    "sg:address":"35 Wallgate",
    "sg:city":"Wigan",
    "sg:classifiers":[
        {
            "category":"Shopping",
            "subcategory":"Clothing, Apparel, & Fashions",
            "type":"Retail Goods"
        }
    ],
    "sg:phone":"+44 1942 829637",
    "sg:postcode":"WN1 1BE",
    "sg:province":"Lancashire",
    "sg:tags":[
        "ladieswear"
    ],
    "wof:name":"Direct Clothing",
    "wof:placetype":"venue"
},
  "geometry": {"coordinates":[-2.6327860355,53.5447387695],"type":"Point"}
}