{
  "type": "Feature",
  "properties": {
    "addr:full":"116 Columbus Ravine Scarborough North Yorkshire YO12 7QZ",
    "addr:housenumber":"116",
    "addr:postcode":"yo12 7qz",
    "addr:street":"Columbus Ravine",
    "iso:country":"GB",
    "sg:address":"116 Columbus Ravine",
    "sg:city":"Scarborough",
    "sg:classifiers":[
        {
            "category":"Travel",
            "subcategory":"Hotels & Motels",
            "type":"Entertainment"
        }
    ],
    "sg:phone":"+44 1723 372887",
    "sg:postcode":"YO12 7QZ",
    "sg:province":"North Yorkshire",
    "wof:name":"HOTEL ALMAR",
    "wof:placetype":"venue"
},
  "geometry": {"coordinates":[-0.4088920057,54.2885246277],"type":"Point"}
}