{
  "type": "Feature",
  "properties": {
    "addr:full":"26-30 Halford Street Leicester Leicestershire LE1 1JB",
    "addr:housenumber":"26-30",
    "addr:postcode":"le1 1jb",
    "addr:street":"Halford Street",
    "iso:country":"GB",
    "sg:address":"26-30 Halford Street",
    "sg:city":"Leicester",
    "sg:classifiers":[
        {
            "category":"Real Estate",
            "subcategory":"Real Estate Agent",
            "type":"Services"
        }
    ],
    "sg:phone":"+44 116 253 8711",
    "sg:postcode":"LE1 1JB",
    "sg:province":"Leicestershire",
    "wof:name":"Spencers",
    "wof:placetype":"venue"
},
  "geometry": {"coordinates":[-1.130439,52.634785],"type":"Point"}
}