{
  "type": "Feature",
  "properties": {
    "addr:full":"Templewood Road Colchester Essex CO4 3EZ",
    "addr:postcode":"co4 3ez",
    "addr:street":"Templewood Road Colchester",
    "iso:country":"GB",
    "sg:address":"Templewood Road",
    "sg:city":"Colchester",
    "sg:classifiers":[
        {
            "category":"Education",
            "subcategory":"School",
            "type":"Public Place"
        }
    ],
    "sg:phone":"+44 1206 860612",
    "sg:postcode":"CO4 3EZ",
    "sg:province":"Essex",
    "sg:tags":[
        "local",
        "authority"
    ],
    "wof:name":"Parsons Heath C of E Primary School",
    "wof:placetype":"venue"
},
  "geometry": {"coordinates":[0.936183,51.899902],"type":"Point"}
}