{
  "type": "Feature",
  "properties": {
    "addr:full":"Ferendune Court, Ash Close Faringdon Oxfordshire SN7 8ER",
    "addr:postcode":"sn7 8er",
    "addr:street":"Ash Close",
    "iso:country":"GB",
    "sg:address":"Ferendune Court, Ash Close",
    "sg:city":"Faringdon",
    "sg:classifiers":[
        {
            "category":"Organizations",
            "subcategory":"Community Association",
            "type":"Services"
        }
    ],
    "sg:postcode":"SN7 8ER",
    "sg:province":"Oxfordshire",
    "sg:tags":[
        "society",
        "housing"
    ],
    "wof:name":"Anchor Trust",
    "wof:placetype":"venue"
},
  "geometry": {"coordinates":[-1.5894800425,51.6559906006],"type":"Point"}
}