{
  "type": "Feature",
  "properties": {
    "addr:full":"21 Victoria Street Windermere Cumbria LA23 1AB",
    "addr:housenumber":"21",
    "addr:postcode":"la23 1ab",
    "addr:street":"Victoria Street",
    "iso:country":"GB",
    "sg:address":"21 Victoria Street",
    "sg:city":"Windermere",
    "sg:classifiers":[
        {
            "category":"Shopping",
            "subcategory":"Books",
            "type":"Retail Goods"
        }
    ],
    "sg:phone":"+44 15394 45855",
    "sg:postcode":"LA23 1AB",
    "sg:province":"Cumbria",
    "sg:tags":[
        "second-hand"
    ],
    "wof:name":"Book Fare",
    "wof:placetype":"venue"
},
  "geometry": {"coordinates":[-2.906111002,54.3794021606],"type":"Point"}
}