{
  "type": "Feature",
  "properties": {
    "addr:full":"12 Woodstock Street London Greater London W1C 2AF",
    "addr:housenumber":"12",
    "addr:postcode":"w1c 2af",
    "addr:street":"Woodstock Street",
    "iso:country":"GB",
    "sg:address":"12 Woodstock Street",
    "sg:city":"London",
    "sg:classifiers":[
        {
            "category":"Restaurant",
            "type":"Food & Drink"
        }
    ],
    "sg:phone":"+44 20 7408 0648",
    "sg:postcode":"W1C 2AF",
    "sg:province":"Greater London",
    "sg:tags":[
        "italian"
    ],
    "wof:name":"Bonbonniere Restaurant",
    "wof:placetype":"venue"
},
  "geometry": {"coordinates":[-0.1475789994,51.5141944885],"type":"Point"}
}