{
  "type": "Feature",
  "properties": {
    "iso:country":"GB",
    "sg:address":"23 King Street",
    "sg:city":"Whitehaven",
    "sg:classifiers":[
        {
            "category":"Real Estate",
            "subcategory":"Surveying",
            "type":"Services"
        }
    ],
    "sg:postcode":"CA28 7JN",
    "sg:province":"Cumbria",
    "sg:tags":[
        "surveyor",
        "valuer"
    ],
    "wof:name":"Adrian Windridge",
    "wof:placetype":"venue"
},
  "geometry": {"coordinates":[-3.5900990963,54.5480651855],"type":"Point"}
}