{
  "type": "Feature",
  "properties": {
    "addr:full":"15 Rawcliffe Street Blackpool Lancashire FY4 1BX",
    "addr:housenumber":"15",
    "addr:postcode":"fy4 1bx",
    "addr:street":"Rawcliffe Street",
    "iso:country":"GB",
    "sg:address":"15 Rawcliffe Street",
    "sg:city":"Blackpool",
    "sg:classifiers":[
        {
            "category":"Personal",
            "subcategory":"Beauty Salon",
            "type":"Services"
        }
    ],
    "sg:postcode":"FY4 1BX",
    "sg:province":"Lancashire",
    "sg:tags":[
        "lady",
        "hairdresser"
    ],
    "wof:name":"Helen",
    "wof:placetype":"venue"
},
  "geometry": {"coordinates":[-3.054208,53.797581],"type":"Point"}
}