{
  "type": "Feature",
  "properties": {
    "iso:country":"GB",
    "sg:address":"491-499 Edge Lane, Old Swan",
    "sg:city":"Liverpool",
    "sg:classifiers":[
        {
            "category":"Home & Garden",
            "subcategory":"Furniture",
            "type":"Retail Goods"
        }
    ],
    "sg:phone":"+44 151 259 1314",
    "sg:postcode":"L13 2EY",
    "sg:province":"Merseyside",
    "wof:name":"Mfi Furniture Centre",
    "wof:placetype":"venue"
},
  "geometry": {"coordinates":[-2.927064,53.41032],"type":"Point"}
}