{
  "type": "Feature",
  "properties": {
    "iso:country":"GB",
    "sg:address":"1 Sugar House Lane",
    "sg:city":"London",
    "sg:classifiers":[
        {
            "category":"Professional",
            "type":"Services"
        },
        {
            "category":"Professional",
            "subcategory":"Testing Lab",
            "type":"Services"
        }
    ],
    "sg:phone":"+44 20 8534 6222",
    "sg:postcode":"E15 2QN",
    "sg:province":"Greater London",
    "sg:tags":[
        "equipment",
        "inspection",
        "calibration"
    ],
    "wof:name":"London Analytical Laboratories Ltd.",
    "wof:placetype":"venue"
},
  "geometry": {"coordinates":[-0.0090779997,51.5319519043],"type":"Point"}
}