{
  "type": "Feature",
  "properties": {
    "addr:full":"Colmore Gate Birmingham West Midlands B3 2BN",
    "addr:postcode":"b3 2bn",
    "addr:street":"Colmore Gate",
    "iso:country":"GB",
    "sg:address":"Colmore Gate",
    "sg:city":"Birmingham",
    "sg:classifiers":[
        {
            "category":"Professional",
            "subcategory":"Accounting & Tax Preparation",
            "type":"Services"
        }
    ],
    "sg:phone":"+44 121 200 2211",
    "sg:postcode":"B3 2BN",
    "sg:province":"West Midlands",
    "sg:tags":[
        "accountant"
    ],
    "wof:name":"Deloitte & Touche",
    "wof:placetype":"venue"
},
  "geometry": {"coordinates":[-1.899724,52.481365],"type":"Point"}
}