{
  "type": "Feature",
  "properties": {
    "iso:country":"GB",
    "sg:address":"Craigellachie 273 Perth Rd",
    "sg:city":"Cowdenbeath",
    "sg:classifiers":[
        {
            "category":"Professional",
            "subcategory":"Engineering",
            "type":"Services"
        }
    ],
    "sg:phone":"+44 1383 515261",
    "sg:postcode":"KY4 9EY",
    "sg:province":"Fife",
    "sg:tags":[
        "contractor",
        "electrical",
        "engineer"
    ],
    "wof:name":"WP CONTRACTORS",
    "wof:placetype":"venue"
},
  "geometry": {"coordinates":[-3.3441588879,56.1121253967],"type":"Point"}
}