{
  "type": "Feature",
  "properties": {
    "iso:country":"GB",
    "sg:address":"166 Straford Street",
    "sg:city":"Walsall",
    "sg:classifiers":[
        {
            "category":"Military Area",
            "subcategory":"Air Force Base",
            "type":"Public Place"
        }
    ],
    "sg:phone":"+44 1922 642020",
    "sg:postcode":"WS2 8EA",
    "sg:province":"West Midlands",
    "sg:tags":[
        "taxi",
        "hire",
        "private"
    ],
    "wof:name":"T O A Walsall Taxis",
    "wof:placetype":"venue"
},
  "geometry": {"coordinates":[-1.98572,52.59222],"type":"Point"}
}