{
  "type": "Feature",
  "properties": {
    "iso:country":"GB",
    "sg:address":"36 Howe Street",
    "sg:city":"Edinburgh",
    "sg:classifiers":[
        {
            "category":"Food & Beverages",
            "subcategory":"Supermarket",
            "type":"Retail Goods"
        }
    ],
    "sg:postcode":"EH3 6TH",
    "sg:province":"City of Edinburgh",
    "wof:name":"Newtown Licenced Grocers",
    "wof:placetype":"venue"
},
  "geometry": {"coordinates":[-3.202694,55.956673],"type":"Point"}
}