{
  "type": "Feature",
  "properties": {
    "iso:country":"GB",
    "sg:address":"31 Clerkenwell Close",
    "sg:city":"London",
    "sg:classifiers":[
        {
            "category":"Retail",
            "subcategory":"Repair Shop",
            "type":"Services"
        }
    ],
    "sg:phone":"+44 20 7253 0285",
    "sg:postcode":"EC1R 0AT",
    "sg:province":"Greater London",
    "sg:tags":[
        "clocks",
        "watch"
    ],
    "wof:name":"Durapex",
    "wof:placetype":"venue"
},
  "geometry": {"coordinates":[-0.106765,51.524712],"type":"Point"}
}