{
  "type": "Feature",
  "properties": {
    "iso:country":"GB",
    "sg:address":"267 Thorpe Hall Avenue",
    "sg:city":"Southend-on-sea",
    "sg:classifiers":[
        {
            "category":"Building & Trades",
            "subcategory":"Construction",
            "type":"Services"
        }
    ],
    "sg:phone":"+44 1702 585643",
    "sg:postcode":"SS1 3SJ",
    "sg:province":"Essex",
    "sg:tags":[
        "builder"
    ],
    "wof:name":"D & N Builders",
    "wof:placetype":"venue"
},
  "geometry": {"coordinates":[0.755761,51.542183],"type":"Point"}
}