{
  "type": "Feature",
  "properties": {
    "iso:country":"GB",
    "sg:address":"39 Gilmour Road",
    "sg:city":"Edinburgh",
    "sg:classifiers":[
        {
            "category":"Professional",
            "subcategory":"Management & Consulting",
            "type":"Services"
        }
    ],
    "sg:phone":"+44 131 662 9768",
    "sg:postcode":"EH16 5NS",
    "sg:province":"City of Edinburgh",
    "sg:tags":[
        "consultant",
        "business"
    ],
    "wof:name":"Mayfield Consulting",
    "wof:placetype":"venue"
},
  "geometry": {"coordinates":[-3.169999,55.927883],"type":"Point"}
}