{
  "type": "Feature",
  "properties": {
    "addr:full":"7-9 Chapel Lane, Formby Liverpool Lancashire L37 4DL",
    "addr:housenumber":"7-9",
    "addr:postcode":"l37 4dl",
    "addr:street":"Chapel Lane",
    "iso:country":"GB",
    "sg:address":"7-9 Chapel Lane, Formby",
    "sg:city":"Liverpool",
    "sg:classifiers":[
        {
            "category":"Shopping",
            "subcategory":"Clothing, Apparel, & Fashions",
            "type":"Retail Goods"
        }
    ],
    "sg:phone":"+44 1704 832297",
    "sg:postcode":"L37 4DL",
    "sg:province":"Lancashire",
    "sg:tags":[
        "lady",
        "fashionwear",
        "ladieswear"
    ],
    "wof:name":"Dorothy Perkins",
    "wof:placetype":"venue"
},
  "geometry": {"coordinates":[-3.062173,53.556755],"type":"Point"}
}