{
  "type": "Feature",
  "properties": {
    "addr:full":"Unit 49-50, 2 Manor Gardens Holloway Greater London N7 6JZ",
    "addr:housenumber":"unit 49-50 2",
    "addr:postcode":"n7 6jz",
    "addr:street":"Manor Gardens",
    "iso:country":"GB",
    "sg:address":"Unit 49-50, 2 Manor Gardens",
    "sg:city":"Holloway",
    "sg:classifiers":[
        {
            "category":"Organizations",
            "subcategory":"Community Association",
            "type":"Services"
        }
    ],
    "sg:phone":"+44 20 7561 9400",
    "sg:postcode":"N7 6JZ",
    "sg:province":"Greater London",
    "sg:tags":[
        "society",
        "housing"
    ],
    "wof:name":"St. Ignatius Housing Association",
    "wof:placetype":"venue"
},
  "geometry": {"coordinates":[-0.122869,51.560089],"type":"Point"}
}