{
  "type": "Feature",
  "properties": {
    "iso:country":"GB",
    "sg:address":"21 Howard Street",
    "sg:city":"Oxford",
    "sg:classifiers":[
        {
            "category":"Communications",
            "subcategory":"Film & Video Production",
            "type":"Services"
        }
    ],
    "sg:phone":"+44 1865 248556",
    "sg:postcode":"OX4 3AY",
    "sg:province":"Oxfordshire",
    "sg:tags":[
        "tv"
    ],
    "wof:name":"S T Rentals",
    "wof:placetype":"venue"
},
  "geometry": {"coordinates":[-1.2343440056,51.739566803],"type":"Point"}
}