{
  "type": "Feature",
  "properties": {
    "addr:full":"90 High Street March Cambridgeshire PE15 9LQ",
    "addr:housenumber":"90",
    "addr:postcode":"pe15 9lq",
    "addr:street":"High Street",
    "iso:country":"GB",
    "sg:address":"90 High Street",
    "sg:city":"March",
    "sg:classifiers":[
        {
            "category":"Retail",
            "subcategory":"Veterinary Services",
            "type":"Services"
        }
    ],
    "sg:phone":"+44 1354 652246",
    "sg:postcode":"PE15 9LQ",
    "sg:province":"Cambridgeshire",
    "sg:tags":[
        "surgeon",
        "activity"
    ],
    "wof:name":"Amical Veterinary Centre",
    "wof:placetype":"venue"
},
  "geometry": {"coordinates":[0.0876120031,52.5461540222],"type":"Point"}
}