{
  "type": "Feature",
  "properties": {
    "addr:full":"65 Leather Lane London Greater London EC1N 7TJ",
    "addr:housenumber":"65",
    "addr:postcode":"ec1n 7tj",
    "addr:street":"Leather Lane",
    "iso:country":"GB",
    "sg:address":"65 Leather Lane",
    "sg:city":"London",
    "sg:classifiers":[
        {
            "category":"Shopping",
            "subcategory":"News",
            "type":"Retail Goods"
        }
    ],
    "sg:phone":"+44 20 7405 8013",
    "sg:postcode":"EC1N 7TJ",
    "sg:province":"Greater London",
    "sg:tags":[
        "newsagent"
    ],
    "wof:name":"Meads News",
    "wof:placetype":"venue"
},
  "geometry": {"coordinates":[-0.1094999984,51.520904541],"type":"Point"}
}