{
  "type": "Feature",
  "properties": {
    "iso:country":"GB",
    "sg:address":"56 Derwent Road East",
    "sg:city":"Liverpool",
    "sg:classifiers":[
        {
            "category":"Organizations",
            "subcategory":"Membership Organization",
            "type":"Services"
        }
    ],
    "sg:phone":"+44 151 280 5975",
    "sg:postcode":"L13 6QR",
    "sg:province":"Merseyside",
    "sg:tags":[
        "club"
    ],
    "wof:name":"Derwent Centre Club The",
    "wof:placetype":"venue"
},
  "geometry": {"coordinates":[-2.917608,53.418713],"type":"Point"}
}