{
  "type": "Feature",
  "properties": {
    "addr:full":"242 Walton Road Liverpool Merseyside L4 4BE",
    "addr:housenumber":"242",
    "addr:postcode":"l4 4be",
    "addr:street":"Walton Road",
    "iso:country":"GB",
    "sg:address":"242 Walton Road",
    "sg:city":"Liverpool",
    "sg:classifiers":[
        {
            "category":"Recreation",
            "subcategory":"Dog Park",
            "type":"Entertainment"
        }
    ],
    "sg:phone":"+44 151 207 4469",
    "sg:postcode":"L4 4BE",
    "sg:province":"Merseyside",
    "wof:name":"The Pet Centre",
    "wof:placetype":"venue"
},
  "geometry": {"coordinates":[-2.9716238976,53.4374351501],"type":"Point"}
}